{
  "type": "Feature",
  "properties": {
    "addr:full":"Lot 51 Warrambool Rd Wamberal NSW 2260",
    "addr:postcode":"2260",
    "addr:street":"Warrambool Rd",
    "iso:country":"AU",
    "sg:address":"Lot 51 Warrambool Rd",
    "sg:city":"Wamberal",
    "sg:classifiers":[
        {
            "category":"Professional",
            "subcategory":"Accounting & Tax Preparation",
            "type":"Services"
        }
    ],
    "sg:phone":"+61 2 4385 6768",
    "sg:postcode":"2260",
    "sg:province":"NSW",
    "sg:tags":[
        "accountant",
        "auditor"
    ],
    "wof:name":"Hypatidis John",
    "wof:placetype":"venue"
},
  "geometry": {"coordinates":[151.45341500000001,-33.406528],"type":"Point"}
}