{
  "type": "Feature",
  "properties": {
    "addr:full":"Cnr Isabella & Bent Sts Wingham NSW 2429",
    "addr:housenumber":"cnr",
    "addr:postcode":"2429",
    "addr:street":"Isabella & Bent",
    "iso:country":"AU",
    "sg:address":"Cnr Isabella & Bent Sts",
    "sg:city":"Wingham",
    "sg:classifiers":[
        {
            "category":"Real Estate",
            "subcategory":"Real Estate Agent",
            "type":"Services"
        }
    ],
    "sg:phone":"+61 2 6553 5511",
    "sg:postcode":"2429",
    "sg:province":"NSW",
    "wof:name":"Hooker L J",
    "wof:placetype":"venue"
},
  "geometry": {"coordinates":[152.36911000000001,-31.868181],"type":"Point"}
}