{
  "type": "Feature",
  "properties": {
    "addr:full":"86 Lynches Rd Armidale NSW 2350",
    "addr:housenumber":"86",
    "addr:postcode":"2350",
    "addr:street":"Lynches Rd",
    "iso:country":"AU",
    "sg:address":"86 Lynches Rd",
    "sg:city":"Armidale",
    "sg:classifiers":[
        {
            "category":"Utilities",
            "subcategory":"Water",
            "type":"Services"
        }
    ],
    "sg:phone":"+61 2 6771 2659",
    "sg:postcode":"2350",
    "sg:province":"NSW",
    "sg:tags":[
        "hot",
        "system"
    ],
    "wof:name":"Partridge D A & L",
    "wof:placetype":"venue"
},
  "geometry": {"coordinates":[151.65135192899999,-30.5275611877],"type":"Point"}
}