{
  "type": "Feature",
  "properties": {
    "addr:full":"Shop K/ 10 A'Beckett St Inverloch VIC 3996",
    "addr:postcode":"3996",
    "addr:street":"A'Beckett",
    "iso:country":"AU",
    "sg:address":"Shop K/ 10 A'Beckett St",
    "sg:city":"Inverloch",
    "sg:classifiers":[
        {
            "category":"Professional",
            "subcategory":"Art Services",
            "type":"Services"
        }
    ],
    "sg:phone":"+61 3 5674 1333",
    "sg:postcode":"3996",
    "sg:province":"VIC",
    "sg:tags":[
        "picture",
        "frame",
        "framing"
    ],
    "wof:name":"Framed Inverloch",
    "wof:placetype":"venue"
},
  "geometry": {"coordinates":[145.72792100000001,-38.633949],"type":"Point"}
}