{
  "type": "Feature",
  "properties": {
    "iso:country":"AU",
    "sg:address":"Shop K/ 10 A'Beckett St",
    "sg:city":"Inverloch",
    "sg:classifiers":[
        {
            "category":"Professional",
            "subcategory":"Art Services",
            "type":"Services"
        }
    ],
    "sg:phone":"+61 3 5674 1333",
    "sg:postcode":"3996",
    "sg:province":"VIC",
    "sg:tags":[
        "picture",
        "frame",
        "framing"
    ],
    "wof:name":"Framed Inverloch",
    "wof:placetype":"venue"
},
  "geometry": {"coordinates":[145.727921,-38.633949],"type":"Point"}
}