{
  "type": "Feature",
  "properties": {
    "addr:full":"26 Joel Crt Heathmont VIC 3135",
    "addr:housenumber":"26",
    "addr:postcode":"3135",
    "addr:street":"Joel Crt",
    "iso:country":"AU",
    "sg:address":"26 Joel Crt",
    "sg:city":"Heathmont",
    "sg:classifiers":[
        {
            "category":"Building & Trades",
            "subcategory":"Construction",
            "type":"Services"
        }
    ],
    "sg:phone":"+61 3 9870 4092",
    "sg:postcode":"3135",
    "sg:province":"VIC",
    "sg:tags":[
        "contractor"
    ],
    "wof:name":"B.O.C. Constructions",
    "wof:placetype":"venue"
},
  "geometry": {"coordinates":[145.232788086,-37.8296966553],"type":"Point"}
}