{
  "type": "Feature",
  "properties": {
    "addr:full":"22 Tatachilla Rd McLaren Vale SA 5171",
    "addr:housenumber":"22",
    "addr:postcode":"5171",
    "addr:street":"Tatachilla Rd",
    "iso:country":"AU",
    "sg:address":"22 Tatachilla Rd",
    "sg:city":"McLaren Vale",
    "sg:classifiers":[
        {
            "category":"Education",
            "subcategory":"Kindergarten",
            "type":"Public Place"
        }
    ],
    "sg:phone":"+61 8 8323 8684",
    "sg:postcode":"5171",
    "sg:province":"SA",
    "sg:tags":[
        "pre-schools"
    ],
    "wof:name":"Madge Sexton Kindergarten",
    "wof:placetype":"venue"
},
  "geometry": {"coordinates":[138.541290283,-35.2197685242],"type":"Point"}
}