{
  "type": "Feature",
  "properties": {
    "iso:country":"AU",
    "sg:address":"12 Princess Arc St",
    "sg:city":"Albans",
    "sg:classifiers":[
        {
            "category":"Health Services",
            "subcategory":"Doctor",
            "type":"Services"
        }
    ],
    "sg:phone":"+61 3 9367 9288",
    "sg:postcode":"3021",
    "sg:province":"VIC",
    "sg:tags":[
        "medical",
        "practitioner"
    ],
    "wof:name":"Luu Dr. M K",
    "wof:placetype":"venue"
},
  "geometry": {"coordinates":[144.80116272000001,-37.7452392578],"type":"Point"}
}