{
  "type": "Feature",
  "properties": {
    "iso:country":"AU",
    "sg:address":"5 Griffith&#039;s La",
    "sg:city":"Buderim",
    "sg:classifiers":[
        {
            "category":"Professional",
            "subcategory":"Art Services",
            "type":"Services"
        }
    ],
    "sg:phone":"+61 7 5456 2181",
    "sg:postcode":"4556",
    "sg:province":"QLD",
    "sg:tags":[
        "interior",
        "decorator"
    ],
    "wof:name":"EM Interiors",
    "wof:placetype":"venue"
},
  "geometry": {"coordinates":[153.09310913100001,-26.6773891449],"type":"Point"}
}