{
  "type": "Feature",
  "properties": {
    "addr:full":"146 Point Leo Rd Red Hill South VIC 3937",
    "addr:housenumber":"146",
    "addr:postcode":"3937",
    "addr:street":"Point Leo Rd",
    "iso:country":"AU",
    "sg:address":"146 Point Leo Rd",
    "sg:city":"Red Hill South",
    "sg:classifiers":[
        {
            "category":"Farming",
            "subcategory":"Nursery",
            "type":"Manufacturing & Wholesale Goods"
        }
    ],
    "sg:phone":"+61 3 5931 0080",
    "sg:postcode":"3937",
    "sg:province":"VIC",
    "wof:name":"The Knoll Lavender Farm",
    "wof:placetype":"venue"
},
  "geometry": {"coordinates":[145.04861450199999,-38.3999824524],"type":"Point"}
}