{
  "type": "Feature",
  "properties": {
    "iso:country":"AU",
    "sg:address":"470 Wellington St",
    "sg:city":"Clifton Hill",
    "sg:classifiers":[
        {
            "category":"Retail",
            "subcategory":"Veterinary Services",
            "type":"Services"
        }
    ],
    "sg:phone":"+61 3 9489 4055",
    "sg:postcode":"3068",
    "sg:province":"VIC",
    "sg:tags":[
        "surgeon"
    ],
    "wof:name":"Sandford Dr John R",
    "wof:placetype":"venue"
},
  "geometry": {"coordinates":[144.988845825,-37.7910728455],"type":"Point"}
}