{
  "type": "Feature",
  "properties": {
    "addr:full":"592 Station St Box Hill VIC 3128",
    "addr:housenumber":"592",
    "addr:postcode":"3128",
    "addr:street":"Station St",
    "iso:country":"AU",
    "sg:address":"592 Station St",
    "sg:city":"Box Hill",
    "sg:classifiers":[
        {
            "category":"Shopping",
            "subcategory":"Discount & Variety Stores",
            "type":"Retail Goods"
        }
    ],
    "sg:phone":"+61 3 9898 7066",
    "sg:postcode":"3128",
    "sg:province":"VIC",
    "sg:tags":[
        "shop",
        "adult"
    ],
    "wof:name":"Club X",
    "wof:placetype":"venue"
},
  "geometry": {"coordinates":[145.123809814,-37.8189964294],"type":"Point"}
}