{
  "type": "Feature",
  "properties": {
    "addr:full":"6 Rosewood Hts Craigie WA 6025",
    "addr:housenumber":"6",
    "addr:postcode":"6025",
    "addr:street":"Rosewood Hts",
    "iso:country":"AU",
    "sg:address":"6 Rosewood Hts",
    "sg:city":"Craigie",
    "sg:classifiers":[
        {
            "category":"Personal",
            "subcategory":"Massage",
            "type":"Services"
        }
    ],
    "sg:phone":"+61 412 372 481",
    "sg:postcode":"6025",
    "sg:province":"WA",
    "sg:tags":[
        "therapy"
    ],
    "wof:name":"Tsubu",
    "wof:placetype":"venue"
},
  "geometry": {"coordinates":[115.758682251,-31.7936573029],"type":"Point"}
}