{
  "type": "Feature",
  "properties": {
    "addr:full":"28 Lone Pine Pde Matraville NSW 2036",
    "addr:housenumber":"28",
    "addr:postcode":"2036",
    "addr:street":"Lone Pine Pde",
    "iso:country":"AU",
    "sg:address":"28 Lone Pine Pde",
    "sg:city":"Matraville",
    "sg:classifiers":[
        {
            "category":"Professional",
            "subcategory":"Secretarial Services",
            "type":"Services"
        }
    ],
    "sg:phone":"+61 2 9311 2882",
    "sg:postcode":"2036",
    "sg:province":"NSW",
    "sg:tags":[
        "typing"
    ],
    "wof:name":"Matraville Typing Services",
    "wof:placetype":"venue"
},
  "geometry": {"coordinates":[151.240524292,-33.9568023682],"type":"Point"}
}