{
  "type": "Feature",
  "properties": {
    "iso:country":"AU",
    "sg:address":"350 North Rd",
    "sg:city":"Langwarrin",
    "sg:classifiers":[
        {
            "category":"Autos & Motor Vehicles",
            "subcategory":"Boat Sales",
            "type":"Retail Goods"
        }
    ],
    "sg:phone":"+61 3 9789 7357",
    "sg:postcode":"3910",
    "sg:province":"VIC",
    "sg:tags":[
        "builder",
        "yacht",
        "repairer"
    ],
    "wof:name":"W & S Boatbuilders",
    "wof:placetype":"venue"
},
  "geometry": {"coordinates":[145.20843505900001,-38.1673431396],"type":"Point"}
}