{
  "type": "Feature",
  "properties": {
    "addr:full":"PO Box 930 Mt Waverley VIC 3149",
    "addr:postcode":"3149",
    "addr:street":"Mt",
    "iso:country":"AU",
    "sg:address":"PO Box 930",
    "sg:city":"Mt Waverley",
    "sg:classifiers":[
        {
            "category":"Professional",
            "type":"Services"
        }
    ],
    "sg:phone":"+61 3 9888 3322",
    "sg:postcode":"3149",
    "sg:province":"VIC",
    "sg:tags":[
        "industrial",
        "commercial",
        "catering"
    ],
    "wof:name":"Pancake Perfection",
    "wof:placetype":"venue"
},
  "geometry": {"coordinates":[145.12962341299999,-37.88489151],"type":"Point"}
}