{
  "type": "Feature",
  "properties": {
    "addr:full":"Southgate Corporate Park, 18 Southgate Ave Cannon Hill QLD 4170",
    "addr:housenumber":"18",
    "addr:postcode":"4170",
    "addr:street":"Southgate Ave",
    "iso:country":"AU",
    "sg:address":"Southgate Corporate Park, 18 Southgate Ave",
    "sg:city":"Cannon Hill",
    "sg:classifiers":[
        {
            "category":"Professional",
            "subcategory":"Printing & Photocopies",
            "type":"Services"
        }
    ],
    "sg:phone":"+61 7 3909 5000",
    "sg:postcode":"4170",
    "sg:province":"QLD",
    "sg:tags":[
        "photocopier"
    ],
    "wof:name":"Canon Australia Pty Ltd",
    "wof:placetype":"venue"
},
  "geometry": {"coordinates":[153.093215942,-27.4681797028],"type":"Point"}
}