{
  "type": "Feature",
  "properties": {
    "iso:country":"AU",
    "sg:address":"PO Box 149",
    "sg:city":"Gulgong",
    "sg:classifiers":[
        {
            "category":"Utilities",
            "subcategory":"Water",
            "type":"Services"
        }
    ],
    "sg:phone":"+61 2 6374 2808",
    "sg:postcode":"2852",
    "sg:province":"NSW",
    "sg:tags":[
        "equipment",
        "treatment"
    ],
    "wof:name":"Midwest Valves & Controls",
    "wof:placetype":"venue"
},
  "geometry": {"coordinates":[149.529404,-32.36274],"type":"Point"}
}