{
  "type": "Feature",
  "properties": {
    "addr:full":"119 Smith St Fitzroy VIC 3065",
    "addr:housenumber":"119",
    "addr:postcode":"3065",
    "addr:street":"Smith St",
    "iso:country":"AU",
    "sg:address":"119 Smith St",
    "sg:city":"Fitzroy",
    "sg:classifiers":[
        {
            "category":"Personal",
            "subcategory":"Beauty Salon",
            "type":"Services"
        }
    ],
    "sg:phone":"+61 3 9417 1561",
    "sg:postcode":"3065",
    "sg:province":"VIC",
    "sg:tags":[
        "hairdresser"
    ],
    "wof:name":"Prophecy Hair Cutter & Colour Specialists",
    "wof:placetype":"venue"
},
  "geometry": {"coordinates":[144.98298645,-37.8053970337],"type":"Point"}
}