{
  "type": "Feature",
  "properties": {
    "addr:full":"Lot 3 Deering St Yamba NSW 2464",
    "addr:postcode":"2464",
    "addr:street":"Deering St",
    "iso:country":"AU",
    "sg:address":"Lot 3 Deering St",
    "sg:city":"Yamba",
    "sg:classifiers":[
        {
            "category":"Retail",
            "subcategory":"Auto Repair",
            "type":"Services"
        }
    ],
    "sg:phone":"+61 2 6646 3990",
    "sg:postcode":"2464",
    "sg:province":"NSW",
    "sg:tags":[
        "repairer",
        "motor",
        "engineer"
    ],
    "wof:name":"West Yamba Automotive",
    "wof:placetype":"venue"
},
  "geometry": {"coordinates":[153.341705322,-29.4375591278],"type":"Point"}
}