{
  "type": "Feature",
  "properties": {
    "addr:full":"249 F Belmore Rd Balwyn North VIC 3104",
    "addr:housenumber":"249 f",
    "addr:postcode":"3104",
    "addr:street":"Belmore Rd",
    "iso:country":"AU",
    "sg:address":"249 F Belmore Rd",
    "sg:city":"Balwyn North",
    "sg:classifiers":[
        {
            "category":"Personal",
            "subcategory":"Beauty Salon",
            "type":"Services"
        }
    ],
    "sg:phone":"+61 3 9857 7100",
    "sg:postcode":"3104",
    "sg:province":"VIC",
    "sg:tags":[
        "hairdresser"
    ],
    "wof:name":"Trussardi Hair Design",
    "wof:placetype":"venue"
},
  "geometry": {"coordinates":[145.085540772,-37.7907905579],"type":"Point"}
}