{
  "type": "Feature",
  "properties": {
    "iso:country":"AU",
    "sg:address":"300 Perry Rd",
    "sg:city":"Keysborough",
    "sg:classifiers":[
        {
            "category":"Farming",
            "subcategory":"Nursery",
            "type":"Manufacturing & Wholesale Goods"
        }
    ],
    "sg:phone":"+61 3 9798 7066",
    "sg:postcode":"3173",
    "sg:province":"VIC",
    "wof:name":"Scotsburn Nurseries",
    "wof:placetype":"venue"
},
  "geometry": {"coordinates":[145.18190002399999,-38.0272140503],"type":"Point"}
}