{
  "type": "Feature",
  "properties": {
    "iso:country":"AU",
    "sg:address":"28 Baratta St",
    "sg:city":"Doncaster East",
    "sg:classifiers":[
        {
            "category":"Utilities",
            "subcategory":"Electric",
            "type":"Services"
        }
    ],
    "sg:phone":"+61 3 9842 0624",
    "sg:postcode":"3109",
    "sg:province":"VIC",
    "sg:tags":[
        "electrical",
        "contractor"
    ],
    "wof:name":"Full Power Electrics",
    "wof:placetype":"venue"
},
  "geometry": {"coordinates":[145.15440368599999,-37.7972984314],"type":"Point"}
}