{
  "type": "Feature",
  "properties": {
    "iso:country":"AU",
    "sg:address":"216 St Georges Rd",
    "sg:city":"Fitzroy North",
    "sg:classifiers":[
        {
            "category":"Cafe",
            "type":"Food & Drink"
        }
    ],
    "sg:phone":"+61 3 9489 7459",
    "sg:postcode":"3068",
    "sg:province":"VIC",
    "wof:name":"Caffe Piccante",
    "wof:placetype":"venue"
},
  "geometry": {"coordinates":[144.98339843799999,-37.7840270996],"type":"Point"}
}