{
  "type": "Feature",
  "properties": {
    "iso:country":"AU",
    "sg:address":"25 Toolooa St",
    "sg:city":"Gladstone",
    "sg:classifiers":[
        {
            "category":"Shopping",
            "subcategory":"Jewelry",
            "type":"Retail Goods"
        }
    ],
    "sg:phone":"+61 7 4972 0777",
    "sg:postcode":"4680",
    "sg:province":"QLD",
    "sg:tags":[
        "jeweller"
    ],
    "wof:name":"Speedi Cash",
    "wof:placetype":"venue"
},
  "geometry": {"coordinates":[151.26446533199999,-23.8489398956],"type":"Point"}
}