{
  "type": "Feature",
  "properties": {
    "addr:full":"138 Mort St Lithgow NSW 2790",
    "addr:housenumber":"138",
    "addr:postcode":"2790",
    "addr:street":"Mort St",
    "iso:country":"AU",
    "sg:address":"138 Mort St",
    "sg:city":"Lithgow",
    "sg:classifiers":[
        {
            "category":"Commercial Area",
            "type":"Public Place"
        }
    ],
    "sg:phone":"+61 2 6351 2486",
    "sg:postcode":"2790",
    "sg:province":"NSW",
    "sg:tags":[
        "heavy",
        "carrier"
    ],
    "wof:name":"Henry Plant & Equipment Hire Pty Ltd",
    "wof:placetype":"venue"
},
  "geometry": {"coordinates":[150.15974426299999,-33.4813499451],"type":"Point"}
}