{
  "type": "Feature",
  "properties": {
    "addr:full":"40 Louis St Doveton VIC 3177",
    "addr:housenumber":"40",
    "addr:postcode":"3177",
    "addr:street":"Louis St",
    "iso:country":"AU",
    "sg:address":"40 Louis St",
    "sg:city":"Doveton",
    "sg:classifiers":[
        {
            "category":"Manufacturing",
            "subcategory":"Tools & Machinery",
            "type":"Manufacturing & Wholesale Goods"
        }
    ],
    "sg:phone":"+61 400 248 679",
    "sg:postcode":"3177",
    "sg:province":"VIC",
    "sg:tags":[
        "earth",
        "excavating",
        "moving",
        "equipment"
    ],
    "wof:name":"Turf for Earth Works",
    "wof:placetype":"venue"
},
  "geometry": {"coordinates":[145.24621582,-37.9856414795],"type":"Point"}
}