{
  "type": "Feature",
  "properties": {
    "addr:full":"PO Box 666 Goondiwindi QLD 4390",
    "addr:postcode":"4390",
    "iso:country":"AU",
    "sg:address":"PO Box 666",
    "sg:city":"Goondiwindi",
    "sg:classifiers":[
        {
            "category":"Manufacturing",
            "subcategory":"Textiles",
            "type":"Manufacturing & Wholesale Goods"
        }
    ],
    "sg:phone":"+61 7 4671 1693",
    "sg:postcode":"4390",
    "sg:province":"QLD",
    "sg:tags":[
        "cotton"
    ],
    "wof:name":"MacIntyre Valley Cotton Growers Asscn Inc",
    "wof:placetype":"venue"
},
  "geometry": {"coordinates":[150.32357788100001,-28.5492191315],"type":"Point"}
}