{
  "type": "Feature",
  "properties": {
    "addr:full":"54 Deshon St Woolloongabba QLD 4102",
    "addr:housenumber":"54",
    "addr:postcode":"4102",
    "addr:street":"Deshon St",
    "iso:country":"AU",
    "sg:address":"54 Deshon St",
    "sg:city":"Woolloongabba",
    "sg:classifiers":[
        {
            "category":"Home & Garden",
            "subcategory":"Kitchen Supply",
            "type":"Retail Goods"
        }
    ],
    "sg:phone":"+61 7 3895 8119",
    "sg:postcode":"4102",
    "sg:province":"QLD",
    "sg:tags":[
        "equipment",
        "diving"
    ],
    "wof:name":"DEEP",
    "wof:placetype":"venue"
},
  "geometry": {"coordinates":[153.04478454599999,-27.4921302795],"type":"Point"}
}