{
  "type": "Feature",
  "properties": {
    "iso:country":"AU",
    "sg:address":"5 Baillie St",
    "sg:city":"North Melbourne",
    "sg:classifiers":[
        {
            "category":"Retail",
            "subcategory":"Auto Repair",
            "type":"Services"
        }
    ],
    "sg:phone":"+61 3 9329 7559",
    "sg:postcode":"3051",
    "sg:province":"VIC",
    "sg:tags":[
        "repairer",
        "motor",
        "engineer"
    ],
    "wof:name":"European Vehicle Services",
    "wof:placetype":"venue"
},
  "geometry": {"coordinates":[144.94764709500001,-37.8016052246],"type":"Point"}
}