{
  "type": "Feature",
  "properties": {
    "addr:full":"199 High St Thomastown VIC 3074",
    "addr:housenumber":"199",
    "addr:postcode":"3074",
    "addr:street":"High St",
    "iso:country":"AU",
    "sg:address":"199 High St",
    "sg:city":"Thomastown",
    "sg:classifiers":[
        {
            "category":"Real Estate",
            "subcategory":"Real Estate Services",
            "type":"Services"
        }
    ],
    "sg:phone":"+61 3 9466 3555",
    "sg:postcode":"3074",
    "sg:province":"VIC",
    "sg:tags":[
        "valuer"
    ],
    "wof:name":"BMT Property Valuers & Quantity Surveyors",
    "wof:placetype":"venue"
},
  "geometry": {"coordinates":[145.01364135700001,-37.6803436279],"type":"Point"}
}