{
  "type": "Feature",
  "properties": {
    "addr:full":"GPO Box 566 Melbourne VIC 3001",
    "addr:postcode":"3001",
    "iso:country":"AU",
    "sg:address":"GPO Box 566",
    "sg:city":"Melbourne",
    "sg:classifiers":[
        {
            "category":"Utilities",
            "subcategory":"Telephone",
            "type":"Services"
        }
    ],
    "sg:phone":"+61 1300 101 500",
    "sg:postcode":"3001",
    "sg:province":"VIC",
    "sg:tags":[
        "equipment",
        "system"
    ],
    "wof:name":"Phoneworks Pty Ltd",
    "wof:placetype":"venue"
},
  "geometry": {"coordinates":[144.881958008,-37.8325958252],"type":"Point"}
}