{
  "type": "Feature",
  "properties": {
    "addr:full":"32 Sterling Rd Minchinbury NSW 2770",
    "addr:housenumber":"32",
    "addr:postcode":"2770",
    "addr:street":"Sterling Rd",
    "iso:country":"AU",
    "sg:address":"32 Sterling Rd",
    "sg:city":"Minchinbury",
    "sg:classifiers":[
        {
            "category":"Building & Trades",
            "subcategory":"Construction",
            "type":"Services"
        }
    ],
    "sg:phone":"+61 2 9677 2361",
    "sg:postcode":"2770",
    "sg:province":"NSW",
    "sg:tags":[
        "industrial",
        "commercial",
        "air conditioning"
    ],
    "wof:name":"Be Cool Refrigeration Pty Ltd",
    "wof:placetype":"venue"
},
  "geometry": {"coordinates":[150.82005310100001,-33.782623291],"type":"Point"}
}