{
  "type": "Feature",
  "properties": {
    "addr:full":"Suite 16-17/ 1344 Gympie Rd Aspley QLD 4034",
    "addr:housenumber":"16-17 / 1344",
    "addr:postcode":"4034",
    "addr:street":"Gympie Rd",
    "iso:country":"AU",
    "sg:address":"Suite 16-17/ 1344 Gympie Rd",
    "sg:city":"Aspley",
    "sg:classifiers":[
        {
            "category":"Government",
            "subcategory":"Customs House",
            "type":"Public Place"
        }
    ],
    "sg:phone":"+61 7 3862 9499",
    "sg:postcode":"4034",
    "sg:province":"QLD",
    "sg:tags":[
        "title",
        "management",
        "stratum"
    ],
    "wof:name":"Skehan Body Corporate Managers",
    "wof:placetype":"venue"
},
  "geometry": {"coordinates":[153.016876,-27.364241],"type":"Point"}
}