{
  "type": "Feature",
  "properties": {
    "addr:full":"Unit 1/ 10 Jane St South Brisbane QLD 4101",
    "addr:housenumber":"10",
    "addr:postcode":"4101",
    "addr:street":"Jane St",
    "iso:country":"AU",
    "sg:address":"Unit 1/ 10 Jane St",
    "sg:city":"South Brisbane",
    "sg:classifiers":[
        {
            "category":"Professional",
            "subcategory":"Computer Services",
            "type":"Services"
        }
    ],
    "sg:phone":"+61 7 3342 7393",
    "sg:postcode":"4101",
    "sg:province":"QLD",
    "sg:tags":[
        "equipment",
        "networking",
        "installation"
    ],
    "wof:name":"One Time Solutions",
    "wof:placetype":"venue"
},
  "geometry": {"coordinates":[153.01194763199999,-27.4792499542],"type":"Point"}
}