{
  "type": "Feature",
  "properties": {
    "iso:country":"AU",
    "sg:address":"Lilianfels Ave",
    "sg:city":"Sydney",
    "sg:classifiers":[
        {
            "category":"Travel",
            "subcategory":"Hotels & Motels",
            "type":"Entertainment"
        }
    ],
    "sg:phone":"+61 2 4780 1200",
    "sg:postcode":"2000",
    "sg:province":"NSW",
    "sg:tags":[
        "accommodation"
    ],
    "wof:name":"Lilianfels Blue Mountains",
    "wof:placetype":"venue"
},
  "geometry": {"coordinates":[151.210006714,-33.8695793152],"type":"Point"}
}