{
  "type": "Feature",
  "properties": {
    "iso:country":"AU",
    "sg:address":"103 Kurnall Rd",
    "sg:city":"Welshpool",
    "sg:classifiers":[
        {
            "category":"Professional",
            "type":"Services"
        }
    ],
    "sg:phone":"+61 8 9356 8566",
    "sg:postcode":"6106",
    "sg:province":"WA",
    "sg:tags":[
        "transport"
    ],
    "wof:name":"Cleveland Freightlines Pty Ltd",
    "wof:placetype":"venue"
},
  "geometry": {"coordinates":[115.959602356,-31.9919948578],"type":"Point"}
}