{
  "type": "Feature",
  "properties": {
    "addr:full":"Suite 2/ 11 Colin Gr West Perth WA 6005",
    "addr:housenumber":"11",
    "addr:postcode":"6005",
    "addr:street":"Colin Gr",
    "iso:country":"AU",
    "sg:address":"Suite 2/ 11 Colin Gr",
    "sg:city":"West Perth",
    "sg:classifiers":[
        {
            "category":"Health Services",
            "subcategory":"Doctor",
            "type":"Services"
        }
    ],
    "sg:phone":"+61 8 9322 3944",
    "sg:postcode":"6005",
    "sg:province":"WA",
    "sg:tags":[
        "medical",
        "practitioner"
    ],
    "wof:name":"Barr Andrew Dr",
    "wof:placetype":"venue"
},
  "geometry": {"coordinates":[115.84262085,-31.9517116547],"type":"Point"}
}