{
  "type": "Feature",
  "properties": {
    "iso:country":"AU",
    "sg:address":"113 Shaftesbury Ave",
    "sg:city":"Bedford",
    "sg:classifiers":[
        {
            "category":"Building & Trades",
            "subcategory":"Construction",
            "type":"Services"
        }
    ],
    "sg:phone":"+61 8 9272 1197",
    "sg:postcode":"6052",
    "sg:province":"WA",
    "sg:tags":[
        "ceiling"
    ],
    "wof:name":"Bedford Ceilings Co",
    "wof:placetype":"venue"
},
  "geometry": {"coordinates":[115.894638062,-31.9116306305],"type":"Point"}
}