{
  "type": "Feature",
  "properties": {
    "iso:country":"AU",
    "sg:address":"398 Hawthorn Rd",
    "sg:city":"Caulfield",
    "sg:classifiers":[
        {
            "category":"Health Services",
            "subcategory":"Doctor",
            "type":"Services"
        }
    ],
    "sg:phone":"+61 3 9523 0630",
    "sg:postcode":"3162",
    "sg:province":"VIC",
    "sg:tags":[
        "podiatrist"
    ],
    "wof:name":"Equilibria Podiatry",
    "wof:placetype":"venue"
},
  "geometry": {"coordinates":[145.021392822,-37.8890151978],"type":"Point"}
}