{
  "type": "Feature",
  "properties": {
    "addr:full":"119 Riviera Rd Avondale Heights VIC 3034",
    "addr:housenumber":"119",
    "addr:postcode":"3034",
    "addr:street":"Riviera Rd",
    "iso:country":"AU",
    "sg:address":"119 Riviera Rd",
    "sg:city":"Avondale Heights",
    "sg:classifiers":[
        {
            "category":"Building & Trades",
            "subcategory":"Construction",
            "type":"Services"
        }
    ],
    "sg:phone":"+61 3 9337 7001",
    "sg:postcode":"3034",
    "sg:province":"VIC",
    "sg:tags":[
        "concrete",
        "contractor"
    ],
    "wof:name":"Fiasco Formwork",
    "wof:placetype":"venue"
},
  "geometry": {"coordinates":[144.87318400000001,-37.752796],"type":"Point"}
}