{
  "type": "Feature",
  "properties": {
    "iso:country":"AU",
    "sg:address":"3 Balfour St",
    "sg:city":"Brighton East",
    "sg:classifiers":[
        {
            "category":"Building & Trades",
            "subcategory":"Construction",
            "type":"Services"
        }
    ],
    "sg:phone":"+61 3 9592 6772",
    "sg:postcode":"3187",
    "sg:province":"VIC",
    "sg:tags":[
        "contractor"
    ],
    "wof:name":"Glover L T & Co Pty Ltd",
    "wof:placetype":"venue"
},
  "geometry": {"coordinates":[145.01214599599999,-37.9211273193],"type":"Point"}
}