{
  "type": "Feature",
  "properties": {
    "addr:full":"6 Chapman St Charlestown NSW 2290",
    "addr:housenumber":"6",
    "addr:postcode":"2290",
    "addr:street":"Chapman St",
    "iso:country":"AU",
    "sg:address":"6 Chapman St",
    "sg:city":"Charlestown",
    "sg:classifiers":[
        {
            "category":"Personal",
            "type":"Services"
        }
    ],
    "sg:phone":"+61 2 4943 9688",
    "sg:postcode":"2290",
    "sg:province":"NSW",
    "sg:tags":[
        "reducing",
        "treatment",
        "weight"
    ],
    "wof:name":"Jenny Craig Weight Loss Centres Pty Ltd",
    "wof:placetype":"venue"
},
  "geometry": {"coordinates":[151.69395446799999,-32.9614181519],"type":"Point"}
}