{
  "type": "Feature",
  "properties": {
    "addr:full":"3 Tilga St Canowindra NSW 2804",
    "addr:housenumber":"3",
    "addr:postcode":"2804",
    "addr:street":"Tilga St",
    "iso:country":"AU",
    "sg:address":"3 Tilga St",
    "sg:city":"Canowindra",
    "sg:classifiers":[
        {
            "category":"Travel",
            "subcategory":"Hotels & Motels",
            "type":"Entertainment"
        }
    ],
    "sg:phone":"+61 2 6344 1633",
    "sg:postcode":"2804",
    "sg:province":"NSW",
    "wof:name":"Canowindra Riverview Motel",
    "wof:placetype":"venue"
},
  "geometry": {"coordinates":[148.66531372099999,-33.5589828491],"type":"Point"}
}