{
  "type": "Feature",
  "properties": {
    "iso:country":"AU",
    "sg:address":"294A Nepean Hwy",
    "sg:city":"Edithvale",
    "sg:classifiers":[
        {
            "category":"Health Services",
            "subcategory":"Health Practitioner",
            "type":"Services"
        }
    ],
    "sg:phone":"+61 3 9772 0222",
    "sg:postcode":"3196",
    "sg:province":"VIC",
    "sg:tags":[
        "hypnotherapy"
    ],
    "wof:name":"Kay L. Green",
    "wof:placetype":"venue"
},
  "geometry": {"coordinates":[145.10971069300001,-38.0408058167],"type":"Point"}
}