{
  "type": "Feature",
  "properties": {
    "addr:full":"40 Peter St Kelso QLD 4815",
    "addr:housenumber":"40",
    "addr:postcode":"4815",
    "addr:street":"Peter St",
    "iso:country":"AU",
    "sg:address":"40 Peter St",
    "sg:city":"Kelso",
    "sg:classifiers":[
        {
            "category":"Utilities",
            "subcategory":"Electric",
            "type":"Services"
        }
    ],
    "sg:phone":"+61 7 4774 0058",
    "sg:postcode":"4815",
    "sg:province":"QLD",
    "sg:tags":[
        "electrical",
        "contractor"
    ],
    "wof:name":"D & S Hartley Electrical",
    "wof:placetype":"venue"
},
  "geometry": {"coordinates":[146.73228499999999,-19.387625],"type":"Point"}
}