{
  "type": "Feature",
  "properties": {
    "addr:full":"12 Ross St Glenbrook NSW 2773",
    "addr:housenumber":"12",
    "addr:postcode":"2773",
    "addr:street":"Ross St",
    "iso:country":"AU",
    "sg:address":"12 Ross St",
    "sg:city":"Glenbrook",
    "sg:classifiers":[
        {
            "category":"Cafe",
            "type":"Food & Drink"
        }
    ],
    "sg:phone":"+61 2 4739 3500",
    "sg:postcode":"2773",
    "sg:province":"NSW",
    "wof:name":"CCCongo - Jean-Stephane Estival",
    "wof:placetype":"venue"
},
  "geometry": {"coordinates":[150.62176513700001,-33.7668991089],"type":"Point"}
}