{
  "type": "Feature",
  "properties": {
    "iso:country":"AU",
    "sg:address":"Shop 8 34 Heaslip Rd",
    "sg:city":"Angle Vale",
    "sg:classifiers":[
        {
            "category":"Manufacturing",
            "subcategory":"Food",
            "type":"Manufacturing & Wholesale Goods"
        }
    ],
    "sg:phone":"+61 8 8284 8011",
    "sg:postcode":"5117",
    "sg:province":"SA",
    "sg:tags":[
        "function",
        "catering"
    ],
    "wof:name":"Angle Vale Village Butcher",
    "wof:placetype":"venue"
},
  "geometry": {"coordinates":[138.645553589,-34.6452865601],"type":"Point"}
}