{
  "type": "Feature",
  "properties": {
    "addr:full":"23 Saunders St Colac VIC 3250",
    "addr:housenumber":"23",
    "addr:postcode":"3250",
    "addr:street":"Saunders St",
    "iso:country":"AU",
    "sg:address":"23 Saunders St",
    "sg:city":"Colac",
    "sg:classifiers":[
        {
            "category":"Professional",
            "subcategory":"Engineering",
            "type":"Services"
        }
    ],
    "sg:phone":"+61 3 5231 6669",
    "sg:postcode":"3250",
    "sg:province":"VIC",
    "sg:tags":[
        "consultant",
        "geotechnical",
        "engineer"
    ],
    "wof:name":"Civiltest Pty. Ltd.",
    "wof:placetype":"venue"
},
  "geometry": {"coordinates":[143.61132799999999,-38.332932],"type":"Point"}
}