{
  "type": "Feature",
  "properties": {
    "addr:full":"PO Box 5608 Port Macquarie NSW 2444",
    "addr:postcode":"2444",
    "iso:country":"AU",
    "sg:address":"PO Box 5608",
    "sg:city":"Port Macquarie",
    "sg:classifiers":[
        {
            "category":"Building & Trades",
            "subcategory":"Landscaping Services",
            "type":"Services"
        }
    ],
    "sg:phone":"+61 2 6583 3052",
    "sg:postcode":"2444",
    "sg:province":"NSW",
    "sg:tags":[
        "inspection"
    ],
    "wof:name":"Port Macquarie Pre-Purchase Property Inspections",
    "wof:placetype":"venue"
},
  "geometry": {"coordinates":[152.90817300000001,-31.4296],"type":"Point"}
}