{
  "type": "Feature",
  "properties": {
    "addr:full":"Shop 1/ 10 Hanson St Corryong NSW 3707",
    "addr:housenumber":"shop 1 / 10",
    "addr:postcode":"3707",
    "addr:street":"Hanson St",
    "iso:country":"AU",
    "sg:address":"Shop 1/ 10 Hanson St",
    "sg:city":"Corryong",
    "sg:classifiers":[
        {
            "category":"Personal",
            "subcategory":"Beauty Salon",
            "type":"Services"
        }
    ],
    "sg:phone":"+61 2 6076 2667",
    "sg:postcode":"3707",
    "sg:province":"NSW",
    "wof:name":"Clinic Of Natural Beauty",
    "wof:placetype":"venue"
},
  "geometry": {"coordinates":[147.90623474099999,-36.1949234009],"type":"Point"}
}