{
  "type": "Feature",
  "properties": {
    "addr:full":"26 Freshwater Point Rd Legana TAS 7277",
    "addr:housenumber":"26",
    "addr:postcode":"7277",
    "addr:street":"Freshwater Point Rd",
    "iso:country":"AU",
    "sg:address":"26 Freshwater Point Rd",
    "sg:city":"Legana",
    "sg:classifiers":[
        {
            "category":"Government",
            "subcategory":"Post Office",
            "type":"Public Place"
        }
    ],
    "sg:phone":"+61 3 6330 2608",
    "sg:postcode":"7277",
    "sg:province":"TAS",
    "sg:tags":[
        "house",
        "doll"
    ],
    "wof:name":"Old Crafty Bits",
    "wof:placetype":"venue"
},
  "geometry": {"coordinates":[147.04069519000001,-41.364566803],"type":"Point"}
}