{
  "type": "Feature",
  "properties": {
    "addr:full":"3 Royal Crt Albany Creek QLD 4035",
    "addr:housenumber":"3",
    "addr:postcode":"4035",
    "addr:street":"Royal Crt",
    "iso:country":"AU",
    "sg:address":"3 Royal Crt",
    "sg:city":"Albany Creek",
    "sg:classifiers":[
        {
            "category":"Professional",
            "subcategory":"Computer Services",
            "type":"Services"
        }
    ],
    "sg:phone":"+61 7 3881 3792",
    "sg:postcode":"4035",
    "sg:province":"QLD",
    "sg:tags":[
        "package",
        "software"
    ],
    "wof:name":"Micro-Active Australia Pty Ltd",
    "wof:placetype":"venue"
},
  "geometry": {"coordinates":[152.97555500000001,-27.362186],"type":"Point"}
}