{
  "type": "Feature",
  "properties": {
    "addr:full":"84 Glebe Point Rd Glebe NSW 2037",
    "addr:housenumber":"84",
    "addr:postcode":"2037",
    "addr:street":"Glebe Point Rd",
    "iso:country":"AU",
    "sg:address":"84 Glebe Point Rd",
    "sg:city":"Glebe",
    "sg:classifiers":[
        {
            "category":"Organizations",
            "subcategory":"Community Association",
            "type":"Services"
        }
    ],
    "sg:phone":"+61 2 9552 2873",
    "sg:postcode":"2037",
    "sg:province":"NSW",
    "sg:tags":[
        "organisation",
        "family",
        "welfare"
    ],
    "wof:name":"Glebe Youth Centre",
    "wof:placetype":"venue"
},
  "geometry": {"coordinates":[151.18992614699999,-33.8824272156],"type":"Point"}
}