{
  "type": "Feature",
  "properties": {
    "iso:country":"AU",
    "sg:address":"13 Tanglebrush Pl",
    "sg:city":"Calamvale",
    "sg:classifiers":[
        {
            "category":"Health Services",
            "subcategory":"Health Practitioner",
            "type":"Services"
        }
    ],
    "sg:phone":"+61 7 3272 0700",
    "sg:postcode":"4116",
    "sg:province":"QLD",
    "sg:tags":[
        "acupuncture"
    ],
    "wof:name":"Huang Song",
    "wof:placetype":"venue"
},
  "geometry": {"coordinates":[153.056762695,-27.6212463379],"type":"Point"}
}