{
  "type": "Feature",
  "properties": {
    "addr:full":"Pittwater Rd Gladesville NSW 2111",
    "addr:postcode":"2111",
    "addr:street":"Pittwater Rd",
    "iso:country":"AU",
    "sg:address":"Pittwater Rd",
    "sg:city":"Gladesville",
    "sg:classifiers":[
        {
            "category":"Education",
            "subcategory":"School",
            "type":"Public Place"
        }
    ],
    "sg:phone":"+61 2 9817 2778",
    "sg:postcode":"2111",
    "sg:province":"NSW",
    "sg:tags":[
        "state",
        "-",
        "nsw"
    ],
    "wof:name":"Boronia Park Public School",
    "wof:placetype":"venue"
},
  "geometry": {"coordinates":[151.126831055,-33.8301696777],"type":"Point"}
}