{
  "type": "Feature",
  "properties": {
    "iso:country":"AU",
    "sg:address":"127 Norton St",
    "sg:city":"Leichhardt",
    "sg:classifiers":[
        {
            "category":"Food & Beverages",
            "subcategory":"Liquor & Beverages",
            "type":"Retail Goods"
        }
    ],
    "sg:phone":"+61 2 9569 1749",
    "sg:postcode":"2040",
    "sg:province":"NSW",
    "sg:tags":[
        "store"
    ],
    "wof:name":"BWS Liquor Stores",
    "wof:placetype":"venue"
},
  "geometry": {"coordinates":[151.157013,-33.882313],"type":"Point"}
}