{
  "type": "Feature",
  "properties": {
    "iso:country":"AU",
    "sg:address":"290 Springvale Rd",
    "sg:city":"Springvale",
    "sg:classifiers":[
        {
            "category":"Food & Beverages",
            "subcategory":"Groceries & Convenience Stores",
            "type":"Retail Goods"
        }
    ],
    "sg:phone":"+61 3 9547 8746",
    "sg:postcode":"3171",
    "sg:province":"VIC",
    "wof:name":"Vien Dong Pty Ltd",
    "wof:placetype":"venue"
},
  "geometry": {"coordinates":[145.15203857399999,-37.9522590637],"type":"Point"}
}