{
  "type": "Feature",
  "properties": {
    "iso:country":"AU",
    "sg:address":"Terangion St",
    "sg:city":"Nyngan",
    "sg:classifiers":[
        {
            "category":"Education",
            "subcategory":"School",
            "type":"Public Place"
        }
    ],
    "sg:phone":"+61 2 6832 1588",
    "sg:postcode":"2825",
    "sg:province":"NSW",
    "wof:name":"St Josephs School",
    "wof:placetype":"venue"
},
  "geometry": {"coordinates":[147.19413757300001,-31.5600280762],"type":"Point"}
}