{
  "type": "Feature",
  "properties": {
    "addr:full":"85 Gosport St Hemmant QLD 4174",
    "addr:housenumber":"85",
    "addr:postcode":"4174",
    "addr:street":"Gosport St",
    "iso:country":"AU",
    "sg:address":"85 Gosport St",
    "sg:city":"Hemmant",
    "sg:classifiers":[
        {
            "category":"Manufacturing",
            "subcategory":"Motor Vehicles & Parts",
            "type":"Manufacturing & Wholesale Goods"
        }
    ],
    "sg:phone":"+61 7 3348 4222",
    "sg:postcode":"4174",
    "sg:province":"QLD",
    "sg:tags":[
        "replacement"
    ],
    "wof:name":"Downtown Toyota",
    "wof:placetype":"venue"
},
  "geometry": {"coordinates":[153.13267517099999,-27.4393081665],"type":"Point"}
}