{
  "type": "Feature",
  "properties": {
    "iso:country":"AU",
    "sg:address":"12 Wesley Crt",
    "sg:city":"Burwood East",
    "sg:classifiers":[
        {
            "category":"Professional",
            "subcategory":"Computer Services",
            "type":"Services"
        }
    ],
    "sg:phone":"+61 1300 555 111",
    "sg:postcode":"3151",
    "sg:province":"VIC",
    "sg:tags":[
        "package",
        "software"
    ],
    "wof:name":"MYOB Australia Pty Ltd",
    "wof:placetype":"venue"
},
  "geometry": {"coordinates":[145.16502380399999,-37.8570556641],"type":"Point"}
}