{
  "type": "Feature",
  "properties": {
    "iso:country":"AU",
    "sg:address":"Unit 509/ 2 Atchison St St",
    "sg:city":"Leonards",
    "sg:classifiers":[
        {
            "category":"Building & Trades",
            "subcategory":"Landscaping Services",
            "type":"Services"
        }
    ],
    "sg:phone":"+61 2 9966 5245",
    "sg:postcode":"2065",
    "sg:province":"NSW",
    "sg:tags":[
        "designer",
        "landscape",
        "contractor"
    ],
    "wof:name":"Reflective Landscape Design",
    "wof:placetype":"venue"
},
  "geometry": {"coordinates":[151.195602417,-33.8227577209],"type":"Point"}
}