{
  "type": "Feature",
  "properties": {
    "addr:full":"Off Lord. St Port Macquarie NSW 2444",
    "addr:postcode":"2444",
    "addr:street":"Lord. St",
    "iso:country":"AU",
    "sg:address":"Off Lord. St",
    "sg:city":"Port Macquarie",
    "sg:classifiers":[
        {
            "category":"Arts & Performance",
            "subcategory":"Theater",
            "type":"Entertainment"
        }
    ],
    "sg:phone":"+61 2 6584 9473",
    "sg:postcode":"2444",
    "sg:province":"NSW",
    "sg:tags":[
        "theatre"
    ],
    "wof:name":"Players Theatre",
    "wof:placetype":"venue"
},
  "geometry": {"coordinates":[152.917114,-31.43004],"type":"Point"}
}