{
  "type": "Feature",
  "properties": {
    "addr:full":"1483 Pittwater Rd Narrabeen NSW 2101",
    "addr:housenumber":"1483",
    "addr:postcode":"2101",
    "addr:street":"Pittwater Rd",
    "iso:country":"AU",
    "sg:address":"1483 Pittwater Rd",
    "sg:city":"Narrabeen",
    "sg:classifiers":[
        {
            "category":"Banks & Credit Unions",
            "subcategory":"Financial Services",
            "type":"Services"
        }
    ],
    "sg:phone":"+61 2 9913 2619",
    "sg:postcode":"2101",
    "sg:province":"NSW",
    "sg:tags":[
        "financier"
    ],
    "wof:name":"Professional Mortgage Brokers",
    "wof:placetype":"venue"
},
  "geometry": {"coordinates":[151.296875,-33.712044],"type":"Point"}
}