{
  "type": "Feature",
  "properties": {
    "iso:country":"AU",
    "sg:address":"489 High St",
    "sg:city":"Northcote",
    "sg:classifiers":[
        {
            "category":"Shopping",
            "subcategory":"Jewelry",
            "type":"Retail Goods"
        }
    ],
    "sg:phone":"+61 3 9482 7007",
    "sg:postcode":"3070",
    "sg:province":"VIC",
    "sg:tags":[
        "jeweller"
    ],
    "wof:name":"Kirameki Jewellers",
    "wof:placetype":"venue"
},
  "geometry": {"coordinates":[144.999222,-37.765747],"type":"Point"}
}