{
  "type": "Feature",
  "properties": {
    "addr:full":"104 Shaftesbury Ave Bedford WA 6052",
    "addr:housenumber":"104",
    "addr:postcode":"6052",
    "addr:street":"Shaftesbury Ave",
    "iso:country":"AU",
    "sg:address":"104 Shaftesbury Ave",
    "sg:city":"Bedford",
    "sg:classifiers":[
        {
            "category":"Building & Trades",
            "subcategory":"Landscaping Services",
            "type":"Services"
        }
    ],
    "sg:phone":"+61 8 9272 5427",
    "sg:postcode":"6052",
    "sg:province":"WA",
    "sg:tags":[
        "gardener"
    ],
    "wof:name":"Hands On Gardening",
    "wof:placetype":"venue"
},
  "geometry": {"coordinates":[115.89566803,-31.9121341705],"type":"Point"}
}