{
  "type": "Feature",
  "properties": {
    "addr:full":"57 Galvin St Altona VIC 3018",
    "addr:housenumber":"57",
    "addr:postcode":"3018",
    "addr:street":"Galvin St",
    "iso:country":"AU",
    "sg:address":"57 Galvin St",
    "sg:city":"Altona",
    "sg:classifiers":[
        {
            "category":"Retail",
            "subcategory":"Repair Shop",
            "type":"Services"
        }
    ],
    "sg:phone":"+61 3 9398 5651",
    "sg:postcode":"3018",
    "sg:province":"VIC",
    "sg:tags":[
        "upholsterer"
    ],
    "wof:name":"Altona Upholstery",
    "wof:placetype":"venue"
},
  "geometry": {"coordinates":[144.80914306599999,-37.8595504761],"type":"Point"}
}