{
  "type": "Feature",
  "properties": {
    "iso:country":"AU",
    "sg:address":"366 Edgecliff Rd",
    "sg:city":"Woollahra",
    "sg:classifiers":[
        {
            "category":"Health Services",
            "subcategory":"Doctor",
            "type":"Services"
        }
    ],
    "sg:phone":"+61 2 9363 0489",
    "sg:postcode":"2025",
    "sg:province":"NSW",
    "sg:tags":[
        "medical",
        "practitioner"
    ],
    "wof:name":"Goldman L M",
    "wof:placetype":"venue"
},
  "geometry": {"coordinates":[151.24256897000001,-33.8843536377],"type":"Point"}
}