{
  "type": "Feature",
  "properties": {
    "addr:full":"442 Victoria St Wetherill Park NSW 2164",
    "addr:housenumber":"442",
    "addr:postcode":"2164",
    "addr:street":"Victoria St",
    "iso:country":"AU",
    "sg:address":"442 Victoria St",
    "sg:city":"Wetherill Park",
    "sg:classifiers":[
        {
            "category":"Retail",
            "subcategory":"Auto Repair",
            "type":"Services"
        }
    ],
    "sg:phone":"+61 2 9756 6236",
    "sg:postcode":"2164",
    "sg:province":"NSW",
    "sg:tags":[
        "repairer",
        "motor",
        "engineer"
    ],
    "wof:name":"Phillip & Son Auto Repairs",
    "wof:placetype":"venue"
},
  "geometry": {"coordinates":[150.89570617699999,-33.844707489],"type":"Point"}
}