{
  "type": "Feature",
  "properties": {
    "addr:full":"Shp1/ 53 Griffin Rd North Curl Curl NSW 2099",
    "addr:housenumber":"53",
    "addr:postcode":"2099",
    "addr:street":"Griffin Rd",
    "iso:country":"AU",
    "sg:address":"Shp1/ 53 Griffin Rd",
    "sg:city":"North Curl Curl",
    "sg:classifiers":[
        {
            "category":"Health Services",
            "subcategory":"Health Practitioner",
            "type":"Services"
        }
    ],
    "sg:phone":"+61 2 9905 3500",
    "sg:postcode":"2099",
    "sg:province":"NSW",
    "sg:tags":[
        "physiotherapist"
    ],
    "wof:name":"Ian Gard",
    "wof:placetype":"venue"
},
  "geometry": {"coordinates":[151.29562377900001,-33.7628517151],"type":"Point"}
}