{
  "type": "Feature",
  "properties": {
    "addr:full":"867 Centre Rd Bentleigh East VIC 3165",
    "addr:housenumber":"867",
    "addr:postcode":"3165",
    "addr:street":"Centre Rd",
    "iso:country":"AU",
    "sg:address":"867 Centre Rd",
    "sg:city":"Bentleigh East",
    "sg:classifiers":[
        {
            "category":"Health Services",
            "subcategory":"Doctor",
            "type":"Services"
        }
    ],
    "sg:phone":"+61 3 9579 2077",
    "sg:postcode":"3165",
    "sg:province":"VIC",
    "sg:tags":[
        "medical",
        "practitioner"
    ],
    "wof:name":"Fradkin Rebecca Dr",
    "wof:placetype":"venue"
},
  "geometry": {"coordinates":[145.06280517600001,-37.9215011597],"type":"Point"}
}