{
  "type": "Feature",
  "properties": {
    "iso:country":"AU",
    "sg:address":"29 Lonsdale St",
    "sg:city":"Braddon",
    "sg:classifiers":[
        {
            "category":"Fast Food",
            "type":"Food & Drink"
        }
    ],
    "sg:phone":"+61 2 6257 3732",
    "sg:postcode":"2612",
    "sg:province":"ACT",
    "sg:tags":[
        "away",
        "take"
    ],
    "wof:name":"Curryinahurry",
    "wof:placetype":"venue"
},
  "geometry": {"coordinates":[149.13287353499999,-35.2716331482],"type":"Point"}
}