{
  "type": "Feature",
  "properties": {
    "addr:full":"5 Lindfield Ave Edwardstown SA 5039",
    "addr:housenumber":"5",
    "addr:postcode":"5039",
    "addr:street":"Lindfield Ave",
    "iso:country":"AU",
    "sg:address":"5 Lindfield Ave",
    "sg:city":"Edwardstown",
    "sg:classifiers":[
        {
            "category":"Utilities",
            "subcategory":"Water",
            "type":"Services"
        }
    ],
    "sg:phone":"+61 1800 787 383",
    "sg:postcode":"5039",
    "sg:province":"SA",
    "sg:tags":[
        "equipment",
        "treatment"
    ],
    "wof:name":"Puretec Water Filtration",
    "wof:placetype":"venue"
},
  "geometry": {"coordinates":[138.57057189899999,-34.9687080383],"type":"Point"}
}