{
  "type": "Feature",
  "properties": {
    "addr:full":"181 Maddington Rd Maddington WA 6109",
    "addr:housenumber":"181",
    "addr:postcode":"6109",
    "addr:street":"Maddington Rd",
    "iso:country":"AU",
    "sg:address":"181 Maddington Rd",
    "sg:city":"Maddington",
    "sg:classifiers":[
        {
            "category":"Travel",
            "subcategory":"Hostel",
            "type":"Entertainment"
        }
    ],
    "sg:phone":"+61 8 9452 7900",
    "sg:postcode":"6109",
    "sg:province":"WA",
    "sg:tags":[
        "home"
    ],
    "wof:name":"Belrose Care",
    "wof:placetype":"venue"
},
  "geometry": {"coordinates":[115.99845886200001,-32.0430030823],"type":"Point"}
}