{
  "type": "Feature",
  "properties": {
    "iso:country":"AU",
    "sg:address":"6 Trudgian St",
    "sg:city":"Sunnybank",
    "sg:classifiers":[
        {
            "category":"Retail",
            "subcategory":"Auto Rental",
            "type":"Services"
        }
    ],
    "sg:phone":"+61 7 3216 9644",
    "sg:postcode":"4109",
    "sg:province":"QLD",
    "sg:tags":[
        "car",
        "wedding"
    ],
    "wof:name":"Abco Limousines",
    "wof:placetype":"venue"
},
  "geometry": {"coordinates":[153.06086730999999,-27.5802631378],"type":"Point"}
}