{
  "type": "Feature",
  "properties": {
    "addr:full":"30 Pacific Hwy Tuggerah NSW 2259",
    "addr:housenumber":"30",
    "addr:postcode":"2259",
    "addr:street":"Pacific Hwy",
    "iso:country":"AU",
    "sg:address":"30 Pacific Hwy",
    "sg:city":"Tuggerah",
    "sg:classifiers":[
        {
            "category":"Farming",
            "subcategory":"Nursery",
            "type":"Manufacturing & Wholesale Goods"
        }
    ],
    "sg:phone":"+61 2 4351 2099",
    "sg:postcode":"2259",
    "sg:province":"NSW",
    "wof:name":"Ramm Botanicals Pty Ltd",
    "wof:placetype":"venue"
},
  "geometry": {"coordinates":[151.41242980999999,-33.3153381348],"type":"Point"}
}