{
  "type": "Feature",
  "properties": {
    "iso:country":"AU",
    "sg:address":"2- 4 Helm Crt",
    "sg:city":"Epping",
    "sg:classifiers":[
        {
            "category":"Building & Trades",
            "subcategory":"Construction",
            "type":"Services"
        }
    ],
    "sg:phone":"+61 3 9408 9937",
    "sg:postcode":"3076",
    "sg:province":"VIC",
    "sg:tags":[
        "fencing",
        "contractor"
    ],
    "wof:name":"Citywide Temporary Fencing",
    "wof:placetype":"venue"
},
  "geometry": {"coordinates":[145.19224548299999,-38.1116104126],"type":"Point"}
}