{
  "type": "Feature",
  "properties": {
    "addr:full":"167 Church Rd Doncaster VIC 3108",
    "addr:housenumber":"167",
    "addr:postcode":"3108",
    "addr:street":"Church Rd",
    "iso:country":"AU",
    "sg:address":"167 Church Rd",
    "sg:city":"Doncaster",
    "sg:classifiers":[
        {
            "category":"Banks & Credit Unions",
            "subcategory":"Bank",
            "type":"Services"
        }
    ],
    "sg:phone":"+61 3 9855 9266",
    "sg:postcode":"3108",
    "sg:province":"VIC",
    "sg:tags":[
        "broker",
        "mortgage"
    ],
    "sg:website":"http://www.allhomeloans.com.au",
    "wof:name":"ALL Home Loans",
    "wof:placetype":"venue"
},
  "geometry": {"coordinates":[145.13871765100001,-37.7811546326],"type":"Point"}
}