{
  "type": "Feature",
  "properties": {
    "addr:full":"396 Smith St Albury NSW 2640",
    "addr:housenumber":"396",
    "addr:postcode":"2640",
    "addr:street":"Smith St",
    "iso:country":"AU",
    "sg:address":"396 Smith St",
    "sg:city":"Albury",
    "sg:classifiers":[
        {
            "category":"Professional",
            "subcategory":"Employment Agencies",
            "type":"Services"
        }
    ],
    "sg:phone":"+61 409 152 634",
    "sg:postcode":"2640",
    "sg:province":"NSW",
    "sg:tags":[
        "entertainer",
        "agent"
    ],
    "wof:name":"N.F.I Entertainment",
    "wof:placetype":"venue"
},
  "geometry": {"coordinates":[146.927978516,-36.0669898987],"type":"Point"}
}