{
  "type": "Feature",
  "properties": {
    "iso:country":"AU",
    "sg:address":"309 Mair St",
    "sg:city":"Ballarat",
    "sg:classifiers":[
        {
            "category":"Shopping",
            "subcategory":"Party Supplies",
            "type":"Retail Goods"
        }
    ],
    "sg:phone":"+61 3 5331 2008",
    "sg:postcode":"3350",
    "sg:province":"VIC",
    "sg:tags":[
        "children's"
    ],
    "wof:name":"Smartartz Creations",
    "wof:placetype":"venue"
},
  "geometry": {"coordinates":[143.85611,-37.559681],"type":"Point"}
}