{
  "type": "Feature",
  "properties": {
    "iso:country":"AU",
    "sg:address":"1/ 362 Mont Albert Rd",
    "sg:city":"Surrey Hills",
    "sg:classifiers":[
        {
            "category":"Wholesale",
            "subcategory":"Machinery & Supplies",
            "type":"Manufacturing & Wholesale Goods"
        }
    ],
    "sg:phone":"+61 3 9898 9393",
    "sg:postcode":"3127",
    "sg:province":"VIC",
    "sg:tags":[
        "equipment",
        "laboratory"
    ],
    "wof:name":"Graykon Scientific",
    "wof:placetype":"venue"
},
  "geometry": {"coordinates":[145.10545349099999,-37.821395874],"type":"Point"}
}