{
  "type": "Feature",
  "properties": {
    "iso:country":"AU",
    "sg:address":"19a Atchison Rd",
    "sg:city":"Macquarie Fields",
    "sg:classifiers":[
        {
            "category":"Government",
            "subcategory":"Fire Station",
            "type":"Public Place"
        }
    ],
    "sg:phone":"+61 2 9618 1557",
    "sg:postcode":"2564",
    "sg:province":"NSW",
    "sg:tags":[
        "equipment",
        "protection",
        "consultant"
    ],
    "wof:name":"City & Suburban Fire Pty Ltd",
    "wof:placetype":"venue"
},
  "geometry": {"coordinates":[150.88313293499999,-33.9876174927],"type":"Point"}
}