{
  "type": "Feature",
  "properties": {
    "iso:country":"AU",
    "sg:address":"555 Grange Rd",
    "sg:city":"Grange",
    "sg:classifiers":[
        {
            "category":"Health Services",
            "subcategory":"Doctor",
            "type":"Services"
        }
    ],
    "sg:phone":"+61 8 8353 1466",
    "sg:postcode":"5022",
    "sg:province":"SA",
    "sg:tags":[
        "medical",
        "practitioner"
    ],
    "wof:name":"Barnett Michael P",
    "wof:placetype":"venue"
},
  "geometry": {"coordinates":[138.50543212900001,-34.9066734314],"type":"Point"}
}