{
  "type": "Feature",
  "properties": {
    "addr:full":"10 Duke St Daylesford VIC 3460",
    "addr:housenumber":"10",
    "addr:postcode":"3460",
    "addr:street":"Duke St",
    "iso:country":"AU",
    "sg:address":"10 Duke St",
    "sg:city":"Daylesford",
    "sg:classifiers":[
        {
            "category":"Banks & Credit Unions",
            "subcategory":"Financial Services",
            "type":"Services"
        }
    ],
    "sg:phone":"+61 3 5348 3397",
    "sg:postcode":"3460",
    "sg:province":"VIC",
    "sg:tags":[
        "planning"
    ],
    "wof:name":"Genesys Wealth Advisers",
    "wof:placetype":"venue"
},
  "geometry": {"coordinates":[144.143966675,-37.3417854309],"type":"Point"}
}