{
  "type": "Feature",
  "properties": {
    "iso:country":"AU",
    "sg:address":"3 Bernborough Ave",
    "sg:city":"Balwyn",
    "sg:classifiers":[
        {
            "category":"Professional",
            "subcategory":"Management & Consulting",
            "type":"Services"
        }
    ],
    "sg:phone":"+61 3 9859 8690",
    "sg:postcode":"3103",
    "sg:province":"VIC",
    "sg:tags":[
        "consultant"
    ],
    "wof:name":"Yacono Tony & Associates Pty Ltd",
    "wof:placetype":"venue"
},
  "geometry": {"coordinates":[145.07522582999999,-37.8028831482],"type":"Point"}
}