{
  "type": "Feature",
  "properties": {
    "iso:country":"AU",
    "sg:address":"U 3/ 42 Whiters St",
    "sg:city":"Lakes Entrance",
    "sg:classifiers":[
        {
            "category":"Shopping",
            "subcategory":"Stationery & Office Supplies",
            "type":"Retail Goods"
        }
    ],
    "sg:phone":"+61 3 5155 2409",
    "sg:postcode":"3909",
    "sg:province":"VIC",
    "sg:tags":[
        "packaging",
        "material"
    ],
    "wof:name":"Gippsland Packaging Supplies",
    "wof:placetype":"venue"
},
  "geometry": {"coordinates":[148.00108337399999,-37.8730278015],"type":"Point"}
}