{
  "type": "Feature",
  "properties": {
    "addr:full":"33 Moodemere St Rutherglen VIC 3685",
    "addr:housenumber":"33",
    "addr:postcode":"3685",
    "addr:street":"Moodemere St",
    "iso:country":"AU",
    "sg:address":"33 Moodemere St",
    "sg:city":"Rutherglen",
    "sg:classifiers":[
        {
            "category":"Building & Trades",
            "subcategory":"Construction",
            "type":"Services"
        }
    ],
    "sg:phone":"+61 2 6032 9646",
    "sg:postcode":"3685",
    "sg:province":"VIC",
    "sg:tags":[
        "contractor"
    ],
    "wof:name":"Chandler L J",
    "wof:placetype":"venue"
},
  "geometry": {"coordinates":[146.44805908199999,-36.053401947],"type":"Point"}
}