{
  "type": "Feature",
  "properties": {
    "addr:full":"5 Mussolino Pl Yoogali NSW 2680",
    "addr:housenumber":"5",
    "addr:postcode":"2680",
    "addr:street":"Mussolino Pl",
    "iso:country":"AU",
    "sg:address":"5 Mussolino Pl",
    "sg:city":"Yoogali",
    "sg:classifiers":[
        {
            "category":"Home & Garden",
            "subcategory":"Carpets & Floor Coverings",
            "type":"Retail Goods"
        }
    ],
    "sg:phone":"+61 2 6962 2035",
    "sg:postcode":"2680",
    "sg:province":"NSW",
    "sg:tags":[
        "tile",
        "wall",
        "layer"
    ],
    "wof:name":"J D Rule",
    "wof:placetype":"venue"
},
  "geometry": {"coordinates":[146.08561700000001,-34.29578],"type":"Point"}
}