{
  "type": "Feature",
  "properties": {
    "iso:country":"AU",
    "sg:address":"159 Tucker Rd",
    "sg:city":"Bentleigh",
    "sg:classifiers":[
        {
            "category":"Health Services",
            "subcategory":"Dentist",
            "type":"Services"
        }
    ],
    "sg:phone":"+61 3 9557 8911",
    "sg:postcode":"3204",
    "sg:province":"VIC",
    "sg:tags":[
        "state",
        "orthodontist",
        "qld",
        "exc"
    ],
    "wof:name":"Centre Orthodontics",
    "wof:placetype":"venue"
},
  "geometry": {"coordinates":[145.026962,-37.91193],"type":"Point"}
}