{
  "type": "Feature",
  "properties": {
    "iso:country":"AU",
    "sg:address":"21 Parkyn Pde",
    "sg:city":"Mooloolaba",
    "sg:classifiers":[
        {
            "category":"Wholesale",
            "subcategory":"Seafood",
            "type":"Manufacturing & Wholesale Goods"
        }
    ],
    "sg:phone":"+61 7 5444 1165",
    "sg:postcode":"4557",
    "sg:province":"QLD",
    "sg:tags":[
        "fish"
    ],
    "wof:name":"Fisheries On The Spit",
    "wof:placetype":"venue"
},
  "geometry": {"coordinates":[153.132537842,-26.683763504],"type":"Point"}
}