{
  "type": "Feature",
  "properties": {
    "iso:country":"AU",
    "sg:address":"60 Newton St",
    "sg:city":"Whyalla",
    "sg:classifiers":[
        {
            "category":"Shopping",
            "subcategory":"Crafts & Fabrics",
            "type":"Retail Goods"
        }
    ],
    "sg:phone":"+61 8 8644 1449",
    "sg:postcode":"5600",
    "sg:province":"SA",
    "sg:tags":[
        "supply"
    ],
    "wof:name":"Daisy Chains Craft",
    "wof:placetype":"venue"
},
  "geometry": {"coordinates":[137.570053,-33.041969],"type":"Point"}
}