{
  "type": "Feature",
  "properties": {
    "addr:full":"1151 Creek Rd Carindale QLD 4152",
    "addr:housenumber":"1151",
    "addr:postcode":"4152",
    "addr:street":"Creek Rd",
    "iso:country":"AU",
    "sg:address":"1151 Creek Rd",
    "sg:city":"Carindale",
    "sg:classifiers":[
        {
            "category":"Personal",
            "subcategory":"Beauty Salon",
            "type":"Services"
        }
    ],
    "sg:phone":"+61 7 3398 6811",
    "sg:postcode":"4152",
    "sg:province":"QLD",
    "wof:name":"Professionail",
    "wof:placetype":"venue"
},
  "geometry": {"coordinates":[153.099975586,-27.5036334991],"type":"Point"}
}