{
  "type": "Feature",
  "properties": {
    "addr:full":"125 Main North Rd Nailsworth SA 5083",
    "addr:housenumber":"125",
    "addr:postcode":"5083",
    "addr:street":"Main North Rd",
    "iso:country":"AU",
    "sg:address":"125 Main North Rd",
    "sg:city":"Nailsworth",
    "sg:classifiers":[
        {
            "category":"Retail",
            "subcategory":"Auto Repair",
            "type":"Services"
        }
    ],
    "sg:phone":"+61 8 8269 2928",
    "sg:postcode":"5083",
    "sg:province":"SA",
    "sg:tags":[
        "sport",
        "motor"
    ],
    "wof:name":"Redback Imports",
    "wof:placetype":"venue"
},
  "geometry": {"coordinates":[138.60317993199999,-34.8871078491],"type":"Point"}
}