{
  "type": "Feature",
  "properties": {
    "addr:full":"259 Victoria Rd Gladesville NSW 2111",
    "addr:housenumber":"259",
    "addr:postcode":"2111",
    "addr:street":"Victoria Rd",
    "iso:country":"AU",
    "sg:address":"259 Victoria Rd",
    "sg:city":"Gladesville",
    "sg:classifiers":[
        {
            "category":"Professional",
            "subcategory":"Accounting & Tax Preparation",
            "type":"Services"
        }
    ],
    "sg:phone":"+61 2 9817 7511",
    "sg:postcode":"2111",
    "sg:province":"NSW",
    "sg:tags":[
        "consultant",
        "taxation"
    ],
    "wof:name":"H&R Block",
    "wof:placetype":"venue"
},
  "geometry": {"coordinates":[151.12677001899999,-33.8320732117],"type":"Point"}
}