{
  "type": "Feature",
  "properties": {
    "iso:country":"AU",
    "sg:address":"36 Merimbula Drv",
    "sg:city":"Merimbula",
    "sg:classifiers":[
        {
            "category":"Travel",
            "subcategory":"Hotels & Motels",
            "type":"Entertainment"
        }
    ],
    "sg:phone":"+61 2 6495 5900",
    "sg:postcode":"2548",
    "sg:province":"NSW",
    "wof:name":"Merimbula Gardens Motel",
    "wof:placetype":"venue"
},
  "geometry": {"coordinates":[149.904953003,-36.8890457153],"type":"Point"}
}