{
  "type": "Feature",
  "properties": {
    "addr:full":"55 Montgomery Rd Bonnyrigg NSW 2177",
    "addr:housenumber":"55",
    "addr:postcode":"2177",
    "addr:street":"Montgomery Rd",
    "iso:country":"AU",
    "sg:address":"55 Montgomery Rd",
    "sg:city":"Bonnyrigg",
    "sg:classifiers":[
        {
            "category":"Health Services",
            "subcategory":"Doctor",
            "type":"Services"
        }
    ],
    "sg:phone":"+61 2 9610 8747",
    "sg:postcode":"2177",
    "sg:province":"NSW",
    "sg:tags":[
        "medical",
        "practitioner"
    ],
    "wof:name":"Ho N",
    "wof:placetype":"venue"
},
  "geometry": {"coordinates":[150.884231567,-33.8960571289],"type":"Point"}
}