{
  "type": "Feature",
  "properties": {
    "addr:full":"113 Maroondah Hwy Ringwood VIC 3134",
    "addr:housenumber":"113",
    "addr:postcode":"3134",
    "addr:street":"Maroondah Hwy",
    "iso:country":"AU",
    "sg:address":"113 Maroondah Hwy",
    "sg:city":"Ringwood",
    "sg:classifiers":[
        {
            "category":"Autos & Motor Vehicles",
            "subcategory":"Auto Supplies",
            "type":"Retail Goods"
        }
    ],
    "sg:phone":"+61 3 9876 8866",
    "sg:postcode":"3134",
    "sg:province":"VIC",
    "sg:tags":[
        "part",
        "cycles",
        "accessory"
    ],
    "wof:name":"Doc Hogs Ringwood",
    "wof:placetype":"venue"
},
  "geometry": {"coordinates":[145.225738525,-37.8162155151],"type":"Point"}
}