{
  "type": "Feature",
  "properties": {
    "iso:country":"AU",
    "sg:address":"22-24 Enterprise St",
    "sg:city":"Bohle",
    "sg:classifiers":[
        {
            "category":"Manufacturing",
            "subcategory":"Tools & Machinery",
            "type":"Manufacturing & Wholesale Goods"
        }
    ],
    "sg:phone":"+61 7 4774 5811",
    "sg:postcode":"4818",
    "sg:province":"QLD",
    "sg:tags":[
        "manufactured",
        "specially",
        "designed"
    ],
    "wof:name":"Townsville Engineering Industries Pty Ltd",
    "wof:placetype":"venue"
},
  "geometry": {"coordinates":[146.711624,-19.260124],"type":"Point"}
}