{
  "type": "Feature",
  "properties": {
    "addr:full":"15 Goomalibee St Benalla VIC 3672",
    "addr:housenumber":"15",
    "addr:postcode":"3672",
    "addr:street":"Goomalibee St",
    "iso:country":"AU",
    "sg:address":"15 Goomalibee St",
    "sg:city":"Benalla",
    "sg:classifiers":[
        {
            "category":"Wholesale",
            "subcategory":"Medical Equipment & Supplies",
            "type":"Manufacturing & Wholesale Goods"
        }
    ],
    "sg:phone":"+61 3 5762 5835",
    "sg:postcode":"3672",
    "sg:province":"VIC",
    "sg:tags":[
        "plastering"
    ],
    "wof:name":"Holland Plastering Pty Ltd",
    "wof:placetype":"venue"
},
  "geometry": {"coordinates":[146.019836,-36.564095],"type":"Point"}
}