{
  "type": "Feature",
  "properties": {
    "addr:full":"15 Turramurra Ave Turramurra NSW 2074",
    "addr:housenumber":"15",
    "addr:postcode":"2074",
    "addr:street":"Turramurra Ave",
    "iso:country":"AU",
    "sg:address":"15 Turramurra Ave",
    "sg:city":"Turramurra",
    "sg:classifiers":[
        {
            "category":"Health Services",
            "subcategory":"Health Practitioner",
            "type":"Services"
        }
    ],
    "sg:phone":"+61 2 9144 1995",
    "sg:postcode":"2074",
    "sg:province":"NSW",
    "sg:tags":[
        "psychologist"
    ],
    "wof:name":"Personnel Assessment Services",
    "wof:placetype":"venue"
},
  "geometry": {"coordinates":[151.13136291500001,-33.7307548523],"type":"Point"}
}