{
  "type": "Feature",
  "properties": {
    "iso:country":"AU",
    "sg:address":"31 Boomerang Pl",
    "sg:city":"Seven Hills",
    "sg:classifiers":[
        {
            "category":"Personal",
            "type":"Services"
        }
    ],
    "sg:phone":"+61 2 9671 4388",
    "sg:postcode":"2147",
    "sg:province":"NSW",
    "sg:tags":[
        "dressmaker"
    ],
    "wof:name":"Pary Alterations",
    "wof:placetype":"venue"
},
  "geometry": {"coordinates":[150.93617248499999,-33.7747802734],"type":"Point"}
}