{
  "type": "Feature",
  "properties": {
    "iso:country":"AU",
    "sg:address":"20 Beaumont Rd",
    "sg:city":"Mt Kuring-gai",
    "sg:classifiers":[
        {
            "category":"Wholesale",
            "subcategory":"Construction Materials",
            "type":"Manufacturing & Wholesale Goods"
        }
    ],
    "sg:phone":"+61 2 9457 8040",
    "sg:postcode":"2080",
    "sg:province":"NSW",
    "sg:tags":[
        "steel",
        "wholesaler",
        "wool",
        "mfrs"
    ],
    "wof:name":"Sifa Pty Ltd",
    "wof:placetype":"venue"
},
  "geometry": {"coordinates":[151.13087463400001,-33.6413650513],"type":"Point"}
}