{
  "type": "Feature",
  "properties": {
    "iso:country":"AU",
    "sg:address":"467H Maroondah Hwy",
    "sg:city":"Ringwood",
    "sg:classifiers":[
        {
            "category":"Autos & Motor Vehicles",
            "subcategory":"Automobile Sales",
            "type":"Retail Goods"
        }
    ],
    "sg:phone":"+61 3 9847 0667",
    "sg:postcode":"3134",
    "sg:province":"VIC",
    "sg:tags":[
        "car",
        "used"
    ],
    "wof:name":"Quambee Motors",
    "wof:placetype":"venue"
},
  "geometry": {"coordinates":[145.25003051799999,-37.8005409241],"type":"Point"}
}