{
  "type": "Feature",
  "properties": {
    "addr:full":"11 Warburton St North Ward QLD 4810",
    "addr:housenumber":"11",
    "addr:postcode":"4810",
    "addr:street":"Warburton St",
    "iso:country":"AU",
    "sg:address":"11 Warburton St",
    "sg:city":"North Ward",
    "sg:classifiers":[
        {
            "category":"Education",
            "subcategory":"Kindergarten",
            "type":"Public Place"
        }
    ],
    "sg:phone":"+61 7 4724 1184",
    "sg:postcode":"4810",
    "sg:province":"QLD",
    "sg:tags":[
        "pre-schools"
    ],
    "wof:name":"Bo Peep",
    "wof:placetype":"venue"
},
  "geometry": {"coordinates":[146.809921,-19.249523],"type":"Point"}
}