{
  "type": "Feature",
  "properties": {
    "addr:full":"Roadside Mail Box 5688 Cowes VIC 3922",
    "addr:postcode":"3922",
    "iso:country":"AU",
    "sg:address":"Roadside Mail Box 5688",
    "sg:city":"Cowes",
    "sg:classifiers":[
        {
            "category":"Professional",
            "subcategory":"Business Services",
            "type":"Services"
        }
    ],
    "sg:phone":"+61 416 149 058",
    "sg:postcode":"3922",
    "sg:province":"VIC",
    "sg:tags":[
        "drafting"
    ],
    "wof:name":"Ausplan Drafting",
    "wof:placetype":"venue"
},
  "geometry": {"coordinates":[145.23898315400001,-38.4565200806],"type":"Point"}
}