{
  "type": "Feature",
  "properties": {
    "iso:country":"AU",
    "sg:address":"4 Queen St",
    "sg:city":"Revesby",
    "sg:classifiers":[
        {
            "category":"Retail",
            "subcategory":"Auto Repair",
            "type":"Services"
        }
    ],
    "sg:phone":"+61 2 9773 7595",
    "sg:postcode":"2212",
    "sg:province":"NSW",
    "sg:tags":[
        "beater",
        "painter",
        "panel"
    ],
    "wof:name":"Barbie Smash Repairs & Performance",
    "wof:placetype":"venue"
},
  "geometry": {"coordinates":[151.009903,-33.944115],"type":"Point"}
}