{
  "type": "Feature",
  "properties": {
    "addr:full":"level 1 80a Queens St Woollahra NSW 2025",
    "addr:postcode":"2025",
    "addr:street":"Queens St",
    "iso:country":"AU",
    "sg:address":"level 1 80a Queens St",
    "sg:city":"Woollahra",
    "sg:classifiers":[
        {
            "category":"Shopping",
            "subcategory":"Jewelry",
            "type":"Retail Goods"
        }
    ],
    "sg:phone":"+61 2 9327 3813",
    "sg:postcode":"2025",
    "sg:province":"NSW",
    "sg:tags":[
        "jeweller"
    ],
    "wof:name":"Tarasin Jewellers",
    "wof:placetype":"venue"
},
  "geometry": {"coordinates":[151.23573303200001,-33.8885726929],"type":"Point"}
}