{
  "type": "Feature",
  "properties": {
    "iso:country":"AU",
    "sg:address":"670 Anzac Hwy",
    "sg:city":"Glenelg",
    "sg:classifiers":[
        {
            "category":"Shopping",
            "subcategory":"Computers & Home Electronics",
            "type":"Retail Goods"
        }
    ],
    "sg:phone":"+61 8 8295 6800",
    "sg:postcode":"5045",
    "sg:province":"SA",
    "sg:tags":[
        "small",
        "equipment",
        "business"
    ],
    "wof:name":"Dick Smith Electronics",
    "wof:placetype":"venue"
},
  "geometry": {"coordinates":[138.520203,-34.976498],"type":"Point"}
}