{
  "type": "Feature",
  "properties": {
    "addr:full":"29 Nestor Drv Meadowbrook QLD 4131",
    "addr:housenumber":"29",
    "addr:postcode":"4131",
    "addr:street":"Nestor Drv",
    "iso:country":"AU",
    "sg:address":"29 Nestor Drv",
    "sg:city":"Meadowbrook",
    "sg:classifiers":[
        {
            "category":"Utilities",
            "subcategory":"Electric",
            "type":"Services"
        }
    ],
    "sg:phone":"+61 7 3200 3088",
    "sg:postcode":"4131",
    "sg:province":"QLD",
    "sg:tags":[
        "electrical",
        "contractor"
    ],
    "wof:name":"National Power Services",
    "wof:placetype":"venue"
},
  "geometry": {"coordinates":[153.135864258,-27.6686153412],"type":"Point"}
}