{
  "type": "Feature",
  "properties": {
    "addr:full":"Union Building, Monash University Caulfield East VIC 3145",
    "addr:postcode":"3145",
    "iso:country":"AU",
    "sg:address":"Union Building, Monash University",
    "sg:city":"Caulfield East",
    "sg:classifiers":[
        {
            "category":"Travel",
            "subcategory":"Travel Agent",
            "type":"Entertainment"
        }
    ],
    "sg:phone":"+61 3 9572 2811",
    "sg:postcode":"3145",
    "sg:province":"VIC",
    "sg:tags":[
        "consultant"
    ],
    "wof:name":"STA Travel",
    "wof:placetype":"venue"
},
  "geometry": {"coordinates":[145.04301452600001,-37.8770332336],"type":"Point"}
}