{
  "type": "Feature",
  "properties": {
    "addr:full":"71 Brown St West Wallsend NSW 2286",
    "addr:housenumber":"71",
    "addr:postcode":"2286",
    "addr:street":"Brown St",
    "iso:country":"AU",
    "sg:address":"71 Brown St",
    "sg:city":"West Wallsend",
    "sg:classifiers":[
        {
            "category":"Retail",
            "subcategory":"Laundry & Dry Cleaning",
            "type":"Services"
        }
    ],
    "sg:phone":"+61 2 4955 4200",
    "sg:postcode":"2286",
    "sg:province":"NSW",
    "sg:tags":[
        "machine",
        "commercial",
        "industrial",
        "washing"
    ],
    "wof:name":"Alpine Refrigeration",
    "wof:placetype":"venue"
},
  "geometry": {"coordinates":[151.57818603499999,-32.9045753479],"type":"Point"}
}