{
  "type": "Feature",
  "properties": {
    "iso:country":"AU",
    "sg:address":"135 Were St",
    "sg:city":"Brighton",
    "sg:classifiers":[
        {
            "category":"Building & Trades",
            "subcategory":"Cleaning & Sanitation",
            "type":"Services"
        }
    ],
    "sg:phone":"+61 3 9593 2266",
    "sg:postcode":"3186",
    "sg:province":"VIC",
    "sg:tags":[
        "commercial",
        "maintenance"
    ],
    "wof:name":"Property Maintenance (Contractors) Pty Ltd",
    "wof:placetype":"venue"
},
  "geometry": {"coordinates":[145.000534058,-37.9255828857],"type":"Point"}
}