{
  "type": "Feature",
  "properties": {
    "iso:country":"AU",
    "sg:address":"189 Abbottsford Rd",
    "sg:city":"Bowen Hills",
    "sg:classifiers":[
        {
            "category":"Autos & Motor Vehicles",
            "subcategory":"Automobile Sales",
            "type":"Retail Goods"
        }
    ],
    "sg:phone":"+61 7 3216 0460",
    "sg:postcode":"4006",
    "sg:province":"QLD",
    "sg:tags":[
        "car",
        "used"
    ],
    "wof:name":"Autoplus Consulting",
    "wof:placetype":"venue"
},
  "geometry": {"coordinates":[153.038665772,-27.4426040649],"type":"Point"}
}