{
  "type": "Feature",
  "properties": {
    "addr:full":"13 Gurner St Paddington NSW 2021",
    "addr:housenumber":"13",
    "addr:postcode":"2021",
    "addr:street":"Gurner St",
    "iso:country":"AU",
    "sg:address":"13 Gurner St",
    "sg:city":"Paddington",
    "sg:classifiers":[
        {
            "category":"Real Estate",
            "subcategory":"Real Estate Agent",
            "type":"Services"
        }
    ],
    "sg:phone":"+61 2 9361 4277",
    "sg:postcode":"2021",
    "sg:province":"NSW",
    "wof:name":"McGrath Bernard Real Estate Agents",
    "wof:placetype":"venue"
},
  "geometry": {"coordinates":[151.230224609,-33.882270813],"type":"Point"}
}