{
  "type": "Feature",
  "properties": {
    "addr:full":"3 Colchester Rd Rosebud VIC 3939",
    "addr:housenumber":"3",
    "addr:postcode":"3939",
    "addr:street":"Colchester Rd",
    "iso:country":"AU",
    "sg:address":"3 Colchester Rd",
    "sg:city":"Rosebud",
    "sg:classifiers":[
        {
            "category":"Home & Garden",
            "subcategory":"Building Materials",
            "type":"Retail Goods"
        }
    ],
    "sg:phone":"+61 3 5986 4201",
    "sg:postcode":"3939",
    "sg:province":"VIC",
    "sg:tags":[
        "fencing"
    ],
    "wof:name":"Peninsula Timber Pty Ltd",
    "wof:placetype":"venue"
},
  "geometry": {"coordinates":[144.88809204099999,-38.3793754578],"type":"Point"}
}