{
  "type": "Feature",
  "properties": {
    "addr:full":"86 Emerald Drv Port Macquarie NSW 2444",
    "addr:housenumber":"86",
    "addr:postcode":"2444",
    "addr:street":"Emerald Drv",
    "iso:country":"AU",
    "sg:address":"86 Emerald Drv",
    "sg:city":"Port Macquarie",
    "sg:classifiers":[
        {
            "category":"Government",
            "subcategory":"Court House",
            "type":"Public Place"
        }
    ],
    "sg:phone":"+61 2 6582 5033",
    "sg:postcode":"2444",
    "sg:province":"NSW",
    "sg:tags":[
        "personal",
        "marriage",
        "family",
        "counselling"
    ],
    "wof:name":"Elliott, Lyn",
    "wof:placetype":"venue"
},
  "geometry": {"coordinates":[152.90571600000001,-31.483015],"type":"Point"}
}