{
  "type": "Feature",
  "properties": {
    "addr:full":"Cnr Castle & Murray Valley Rds Tongala VIC 3621",
    "addr:postcode":"3621",
    "addr:street":"Cnr",
    "iso:country":"AU",
    "sg:address":"Cnr Castle & Murray Valley Rds",
    "sg:city":"Tongala",
    "sg:classifiers":[
        {
            "category":"Building & Trades",
            "subcategory":"Construction",
            "type":"Services"
        }
    ],
    "sg:phone":"+61 418 505 614",
    "sg:postcode":"3621",
    "sg:province":"VIC",
    "sg:tags":[
        "contractor"
    ],
    "wof:name":"Santilla Pty Ltd",
    "wof:placetype":"venue"
},
  "geometry": {"coordinates":[144.964477539,-36.1990013123],"type":"Point"}
}