{
  "type": "Feature",
  "properties": {
    "addr:full":"79 Moss St Slacks Creek QLD 4127",
    "addr:housenumber":"79",
    "addr:postcode":"4127",
    "addr:street":"Moss St",
    "iso:country":"AU",
    "sg:address":"79 Moss St",
    "sg:city":"Slacks Creek",
    "sg:classifiers":[
        {
            "category":"Autos & Motor Vehicles",
            "subcategory":"Auto Supplies",
            "type":"Retail Goods"
        }
    ],
    "sg:phone":"+61 7 3208 1933",
    "sg:postcode":"4127",
    "sg:province":"QLD",
    "sg:tags":[
        "tyre"
    ],
    "wof:name":"Ian Diffen World Of Tyres & Mufflers",
    "wof:placetype":"venue"
},
  "geometry": {"coordinates":[153.125686645,-27.620973587],"type":"Point"}
}