{
  "type": "Feature",
  "properties": {
    "addr:full":"PO Box 725 Everton Park QLD 4053",
    "addr:postcode":"4053",
    "iso:country":"AU",
    "sg:address":"PO Box 725",
    "sg:city":"Everton Park",
    "sg:classifiers":[
        {
            "category":"Health Services",
            "subcategory":"Doctor",
            "type":"Services"
        }
    ],
    "sg:phone":"+61 1300 305 303",
    "sg:postcode":"4053",
    "sg:province":"QLD",
    "sg:tags":[
        "occupational",
        "safety"
    ],
    "wof:name":"Microwave Safe Australia",
    "wof:placetype":"venue"
},
  "geometry": {"coordinates":[152.98692321799999,-27.3994598389],"type":"Point"}
}