{
  "type": "Feature",
  "properties": {
    "addr:full":"49 Sweenies Creek Rd Strathfieldsaye VIC 3551",
    "addr:housenumber":"49",
    "addr:postcode":"3551",
    "addr:street":"Sweenies Creek Rd",
    "iso:country":"AU",
    "sg:address":"49 Sweenies Creek Rd",
    "sg:city":"Strathfieldsaye",
    "sg:classifiers":[
        {
            "category":"Building & Trades",
            "subcategory":"Plumbing",
            "type":"Services"
        }
    ],
    "sg:phone":"+61 3 5439 5361",
    "sg:postcode":"3551",
    "sg:province":"VIC",
    "sg:tags":[
        "plumber",
        "gasfitters"
    ],
    "wof:name":"Welch G T & L L",
    "wof:placetype":"venue"
},
  "geometry": {"coordinates":[144.41319274899999,-36.8103561401],"type":"Point"}
}