{
  "type": "Feature",
  "properties": {
    "addr:full":"PO Box 122 Thredbo Village NSW 2625",
    "addr:postcode":"2625",
    "iso:country":"AU",
    "sg:address":"PO Box 122",
    "sg:city":"Thredbo Village",
    "sg:classifiers":[
        {
            "category":"Professional",
            "subcategory":"Accounting & Tax Preparation",
            "type":"Services"
        }
    ],
    "sg:phone":"+61 417 911 747",
    "sg:postcode":"2625",
    "sg:province":"NSW",
    "sg:tags":[
        "bookkeeping"
    ],
    "wof:name":"Caroline Simmons Solutions",
    "wof:placetype":"venue"
},
  "geometry": {"coordinates":[148.30847168,-36.5016517639],"type":"Point"}
}