{
  "type": "Feature",
  "properties": {
    "iso:country":"AU",
    "sg:address":"Evans St",
    "sg:city":"Port Adelaide",
    "sg:classifiers":[
        {
            "category":"Commercial Area",
            "type":"Public Place"
        }
    ],
    "sg:phone":"+61 8 8300 3120",
    "sg:postcode":"5015",
    "sg:province":"SA",
    "sg:tags":[
        "heavy",
        "carrier"
    ],
    "wof:name":"sideloader Express Transport",
    "wof:placetype":"venue"
},
  "geometry": {"coordinates":[138.52044677699999,-34.8459625244],"type":"Point"}
}