{
  "type": "Feature",
  "properties": {
    "addr:full":"Level 1, 2 Market St Newcastle NSW 2300",
    "addr:housenumber":"2",
    "addr:postcode":"2300",
    "addr:street":"Market St",
    "iso:country":"AU",
    "sg:address":"Level 1, 2 Market St",
    "sg:city":"Newcastle",
    "sg:classifiers":[
        {
            "category":"Professional",
            "subcategory":"Computer Services",
            "type":"Services"
        }
    ],
    "sg:phone":"+61 2 4925 3474",
    "sg:postcode":"2300",
    "sg:province":"NSW",
    "sg:tags":[
        "consultant",
        "system"
    ],
    "wof:name":"Strategic Information Technologies Pty Ltd",
    "wof:placetype":"venue"
},
  "geometry": {"coordinates":[151.78123500000001,-32.926548],"type":"Point"}
}