{
  "type": "Feature",
  "properties": {
    "addr:full":"238 Johnston St Fitzroy VIC 3065",
    "addr:housenumber":"238",
    "addr:postcode":"3065",
    "addr:street":"Johnston St",
    "iso:country":"AU",
    "sg:address":"238 Johnston St",
    "sg:city":"Fitzroy",
    "sg:classifiers":[
        {
            "category":"Manufacturing",
            "subcategory":"Textiles",
            "type":"Manufacturing & Wholesale Goods"
        }
    ],
    "sg:phone":"+61 3 9417 6422",
    "sg:postcode":"3065",
    "sg:province":"VIC",
    "sg:tags":[
        "machinery"
    ],
    "wof:name":"Mawby/// Stoll",
    "wof:placetype":"venue"
},
  "geometry": {"coordinates":[144.98289489699999,-37.7989273071],"type":"Point"}
}