{
  "type": "Feature",
  "properties": {
    "iso:country":"AU",
    "sg:address":"13 Basil Rd",
    "sg:city":"Bexley",
    "sg:classifiers":[
        {
            "category":"Home & Garden",
            "subcategory":"Home Furnishings",
            "type":"Retail Goods"
        }
    ],
    "sg:phone":"+61 2 9580 3010",
    "sg:postcode":"2207",
    "sg:province":"NSW",
    "sg:tags":[
        "candle"
    ],
    "wof:name":"Celebration Candles",
    "wof:placetype":"venue"
},
  "geometry": {"coordinates":[151.11004600000001,-33.957031],"type":"Point"}
}