{
  "type": "Feature",
  "properties": {
    "addr:full":"Market Square 201 Varsity Parade Varsity Lakes QLD 4227",
    "addr:housenumber":"201",
    "addr:postcode":"4227",
    "addr:street":"Varsity Parade",
    "iso:country":"AU",
    "sg:address":"Market Square 201",
    "sg:city":"Varsity Parade Varsity Lakes",
    "sg:classifiers":[
        {
            "category":"Health Services",
            "subcategory":"Doctor",
            "type":"Services"
        }
    ],
    "sg:phone":"+61 7 5562 2360",
    "sg:postcode":"4227",
    "sg:province":"QLD",
    "sg:tags":[
        "medical",
        "practitioner"
    ],
    "wof:name":"Varsity Medical Centre",
    "wof:placetype":"venue"
},
  "geometry": {"coordinates":[153.4140625,-28.0784416199],"type":"Point"}
}