{
  "type": "Feature",
  "properties": {
    "addr:full":"Hutton St Kyneton VIC 3444",
    "addr:postcode":"3444",
    "addr:street":"Hutton St",
    "iso:country":"AU",
    "sg:address":"Hutton St",
    "sg:city":"Kyneton",
    "sg:classifiers":[
        {
            "category":"Arts & Performance",
            "subcategory":"Dance",
            "type":"Entertainment"
        }
    ],
    "sg:phone":"+61 3 5422 1796",
    "sg:postcode":"3444",
    "sg:province":"VIC",
    "sg:tags":[
        "theatrical",
        "ballet",
        "tuition"
    ],
    "wof:name":"Hotpink Ballroom Dancing AC",
    "wof:placetype":"venue"
},
  "geometry": {"coordinates":[144.45335388199999,-37.2468910217],"type":"Point"}
}