{
  "type": "Feature",
  "properties": {
    "iso:country":"AU",
    "sg:address":"Lot 2 Jeeralang North Rd",
    "sg:city":"Hazelwood North",
    "sg:classifiers":[
        {
            "category":"Building & Trades",
            "subcategory":"Construction",
            "type":"Services"
        }
    ],
    "sg:phone":"+61 438 661 531",
    "sg:postcode":"3840",
    "sg:province":"VIC",
    "sg:tags":[
        "renovation",
        "alterations",
        "extension",
        "contractor"
    ],
    "wof:name":"Rowley R.E. Pty Ltd",
    "wof:placetype":"venue"
},
  "geometry": {"coordinates":[146.48756408700001,-38.2574691772],"type":"Point"}
}