{
  "type": "Feature",
  "properties": {
    "addr:full":"314 St Vincent St Port Adelaide SA 5015",
    "addr:housenumber":"314",
    "addr:postcode":"5015",
    "addr:street":"St Vincent St",
    "iso:country":"AU",
    "sg:address":"314 St Vincent St",
    "sg:city":"Port Adelaide",
    "sg:classifiers":[
        {
            "category":"Retail",
            "subcategory":"Auto Repair",
            "type":"Services"
        }
    ],
    "sg:phone":"+61 8 8447 2844",
    "sg:postcode":"5015",
    "sg:province":"SA",
    "sg:tags":[
        "electrical"
    ],
    "wof:name":"A.A.A.E.",
    "wof:placetype":"venue"
},
  "geometry": {"coordinates":[138.51019287099999,-34.8435401917],"type":"Point"}
}