{
  "type": "Feature",
  "properties": {
    "iso:country":"AU",
    "sg:address":"23 Hustler St",
    "sg:city":"Dianella",
    "sg:classifiers":[
        {
            "category":"Professional",
            "subcategory":"Art Services",
            "type":"Services"
        }
    ],
    "sg:phone":"+61 8 9276 7545",
    "sg:postcode":"6059",
    "sg:province":"WA",
    "sg:tags":[
        "artist"
    ],
    "wof:name":"Lazberger Anthony",
    "wof:placetype":"venue"
},
  "geometry": {"coordinates":[115.866882324,-31.8869667053],"type":"Point"}
}