{
  "type": "Feature",
  "properties": {
    "addr:full":"202 Condamine St Balgowlah NSW 2093",
    "addr:housenumber":"202",
    "addr:postcode":"2093",
    "addr:street":"Condamine St",
    "iso:country":"AU",
    "sg:address":"202 Condamine St",
    "sg:city":"Balgowlah",
    "sg:classifiers":[
        {
            "category":"Utilities",
            "subcategory":"Water",
            "type":"Services"
        }
    ],
    "sg:phone":"+61 2 9948 9799",
    "sg:postcode":"2093",
    "sg:province":"NSW",
    "sg:tags":[
        "hot",
        "system"
    ],
    "wof:name":"AGL Energy Shop",
    "wof:placetype":"venue"
},
  "geometry": {"coordinates":[151.266815186,-33.786693573],"type":"Point"}
}