{
  "type": "Feature",
  "properties": {
    "addr:full":"184 Green Valley Rd Green Valley NSW 2168",
    "addr:housenumber":"184",
    "addr:postcode":"2168",
    "addr:street":"Green Valley Rd",
    "iso:country":"AU",
    "sg:address":"184 Green Valley Rd",
    "sg:city":"Green Valley",
    "sg:classifiers":[
        {
            "category":"Autos & Motor Vehicles",
            "subcategory":"Fuel & Gas Station",
            "type":"Retail Goods"
        }
    ],
    "sg:phone":"+61 2 9607 3636",
    "sg:postcode":"2168",
    "sg:province":"NSW",
    "wof:name":"Ampol Metro Fuels Pty Ltd",
    "wof:placetype":"venue"
},
  "geometry": {"coordinates":[150.86854553200001,-33.9023399353],"type":"Point"}
}