{
  "type": "Feature",
  "properties": {
    "addr:full":"U36/7- 9 Percy St Auburn NSW 2144",
    "addr:housenumber":"9",
    "addr:postcode":"2144",
    "addr:street":"/ 7;Percy St",
    "iso:country":"AU",
    "sg:address":"U36/7- 9 Percy St",
    "sg:city":"Auburn",
    "sg:classifiers":[
        {
            "category":"Military Area",
            "subcategory":"Air Force Base",
            "type":"Public Place"
        }
    ],
    "sg:phone":"+61 2 9643 8399",
    "sg:postcode":"2144",
    "sg:province":"NSW",
    "sg:tags":[
        "wholesaler",
        "bag",
        "mfrs",
        "sack"
    ],
    "wof:name":"Apec Trading Pty Ltd",
    "wof:placetype":"venue"
},
  "geometry": {"coordinates":[151.03919982900001,-33.850982666],"type":"Point"}
}