{
  "type": "Feature",
  "properties": {
    "addr:full":"Alpha Rd Clermont QLD 4721",
    "addr:postcode":"4721",
    "addr:street":"Alpha Rd",
    "iso:country":"AU",
    "sg:address":"Alpha Rd",
    "sg:city":"Clermont",
    "sg:classifiers":[
        {
            "category":"Retail",
            "subcategory":"Auto Repair",
            "type":"Services"
        }
    ],
    "sg:phone":"+61 7 4983 3656",
    "sg:postcode":"4721",
    "sg:province":"QLD",
    "sg:tags":[
        "repairer",
        "motor",
        "engineer"
    ],
    "wof:name":"Belyando Motors",
    "wof:placetype":"venue"
},
  "geometry": {"coordinates":[147.64076232900001,-22.8019790649],"type":"Point"}
}