{
  "type": "Feature",
  "properties": {
    "addr:full":"2-3/ 36 Northbourne Ave Canberra City ACT 2601",
    "addr:housenumber":"2-3 / 36",
    "addr:postcode":"2601",
    "addr:street":"Northbourne Ave",
    "iso:country":"AU",
    "sg:address":"2-3/ 36 Northbourne Ave",
    "sg:city":"Canberra City",
    "sg:classifiers":[
        {
            "category":"Personal",
            "subcategory":"Beauty Salon",
            "type":"Services"
        }
    ],
    "sg:phone":"+61 2 6257 5799",
    "sg:postcode":"2601",
    "sg:province":"ACT",
    "wof:name":"Free Style Tattoo Piercing & Beauty",
    "wof:placetype":"venue"
},
  "geometry": {"coordinates":[149.129516602,-35.279209137],"type":"Point"}
}