{
  "type": "Feature",
  "properties": {
    "iso:country":"AU",
    "sg:address":"13 Corrie Rd",
    "sg:city":"Woonona",
    "sg:classifiers":[
        {
            "category":"Autos & Motor Vehicles",
            "subcategory":"Auto Supplies",
            "type":"Retail Goods"
        }
    ],
    "sg:phone":"+61 408 644 024",
    "sg:postcode":"2517",
    "sg:province":"NSW",
    "sg:tags":[
        "oil",
        "spirit"
    ],
    "wof:name":"J & J Duncan Pty Ltd",
    "wof:placetype":"venue"
},
  "geometry": {"coordinates":[150.903717,-34.337666],"type":"Point"}
}