{
  "type": "Feature",
  "properties": {
    "addr:full":"122 Grafton St Warwick QLD 4370",
    "addr:housenumber":"122",
    "addr:postcode":"4370",
    "addr:street":"Grafton St",
    "iso:country":"AU",
    "sg:address":"122 Grafton St",
    "sg:city":"Warwick",
    "sg:classifiers":[
        {
            "category":"Retail",
            "subcategory":"Auto Repair",
            "type":"Services"
        }
    ],
    "sg:phone":"+61 7 4661 2266",
    "sg:postcode":"4370",
    "sg:province":"QLD",
    "sg:tags":[
        "repairer",
        "motor",
        "engineer"
    ],
    "wof:name":"Holden",
    "wof:placetype":"venue"
},
  "geometry": {"coordinates":[152.03001403799999,-28.2159080505],"type":"Point"}
}