{
  "type": "Feature",
  "properties": {
    "addr:full":"31 Kurilpa St West End QLD 4101",
    "addr:housenumber":"31",
    "addr:postcode":"4101",
    "addr:street":"Kurilpa St",
    "iso:country":"AU",
    "sg:address":"31 Kurilpa St",
    "sg:city":"West End",
    "sg:classifiers":[
        {
            "category":"Real Estate",
            "subcategory":"Surveying",
            "type":"Services"
        }
    ],
    "sg:phone":"+61 7 3844 4407",
    "sg:postcode":"4101",
    "sg:province":"QLD",
    "sg:tags":[
        "surveyor",
        "land"
    ],
    "wof:name":"Hayes Survey Group Pty Ltd",
    "wof:placetype":"venue"
},
  "geometry": {"coordinates":[153.00123596200001,-27.4825496674],"type":"Point"}
}