{
  "type": "Feature",
  "properties": {
    "addr:full":"286 Argyle St North Hobart TAS 7000",
    "addr:housenumber":"286",
    "addr:postcode":"7000",
    "addr:street":"Argyle St",
    "iso:country":"AU",
    "sg:address":"286 Argyle St",
    "sg:city":"North Hobart",
    "sg:classifiers":[
        {
            "category":"Personal",
            "subcategory":"Shoe Repair & Shine",
            "type":"Services"
        }
    ],
    "sg:phone":"+61 3 6234 3443",
    "sg:postcode":"7000",
    "sg:province":"TAS",
    "sg:tags":[
        "reconditioning",
        "business",
        "furniture"
    ],
    "wof:name":"Direct Business Products",
    "wof:placetype":"venue"
},
  "geometry": {"coordinates":[147.318237305,-42.8727226257],"type":"Point"}
}