{
  "type": "Feature",
  "properties": {
    "addr:full":"22 Talbragar St Dubbo NSW 2830",
    "addr:housenumber":"22",
    "addr:postcode":"2830",
    "addr:street":"Talbragar St",
    "iso:country":"AU",
    "sg:address":"22 Talbragar St",
    "sg:city":"Dubbo",
    "sg:classifiers":[
        {
            "category":"Banks & Credit Unions",
            "subcategory":"Investment Brokerage",
            "type":"Services"
        }
    ],
    "sg:phone":"+61 2 6884 1910",
    "sg:postcode":"2830",
    "sg:province":"NSW",
    "sg:tags":[
        "management",
        "property"
    ],
    "wof:name":"Ray White Rural Dubbo",
    "wof:placetype":"venue"
},
  "geometry": {"coordinates":[148.60235595699999,-32.2447891235],"type":"Point"}
}