{
  "type": "Feature",
  "properties": {
    "addr:full":"38 Raymond St Blackburn North VIC 3130",
    "addr:housenumber":"38",
    "addr:postcode":"3130",
    "addr:street":"Raymond St",
    "iso:country":"AU",
    "sg:address":"38 Raymond St",
    "sg:city":"Blackburn North",
    "sg:classifiers":[
        {
            "category":"Personal",
            "subcategory":"Beauty Salon",
            "type":"Services"
        }
    ],
    "sg:phone":"+61 3 9878 6758",
    "sg:postcode":"3130",
    "sg:province":"VIC",
    "sg:tags":[
        "hairdresser"
    ],
    "wof:name":"Innovations In Hair",
    "wof:placetype":"venue"
},
  "geometry": {"coordinates":[145.15567016599999,-37.8049278259],"type":"Point"}
}