{
  "type": "Feature",
  "properties": {
    "addr:full":"90 Stirling Hwy North Fremantle WA 6159",
    "addr:housenumber":"90",
    "addr:postcode":"6159",
    "addr:street":"Stirling Hwy",
    "iso:country":"AU",
    "sg:address":"90 Stirling Hwy",
    "sg:city":"North Fremantle",
    "sg:classifiers":[
        {
            "category":"Food & Beverages",
            "subcategory":"Liquor & Beverages",
            "type":"Retail Goods"
        }
    ],
    "sg:phone":"+61 8 9335 4504",
    "sg:postcode":"6159",
    "sg:province":"WA",
    "sg:tags":[
        "store"
    ],
    "wof:name":"North Fremantle Cellars",
    "wof:placetype":"venue"
},
  "geometry": {"coordinates":[115.752747,-32.031277],"type":"Point"}
}