{
  "type": "Feature",
  "properties": {
    "addr:full":"Shop 6, East Quay Shopping Cen 217 Ron Penhaligon Way Robina QLD 4226",
    "addr:housenumber":"shop 6;217",
    "addr:postcode":"4226",
    "addr:street":"East Quay;Cen;Penhaligon Way",
    "iso:country":"AU",
    "sg:address":"Shop 6, East Quay Shopping Cen 217 Ron Penhaligon Way",
    "sg:city":"Robina",
    "sg:classifiers":[
        {
            "category":"Sports & Exercise",
            "subcategory":"Gym",
            "type":"Entertainment"
        }
    ],
    "sg:phone":"+61 7 5593 0039",
    "sg:postcode":"4226",
    "sg:province":"QLD",
    "sg:tags":[
        "personal",
        "trainer",
        "fitness"
    ],
    "wof:name":"Exclusively You Personal Training",
    "wof:placetype":"venue"
},
  "geometry": {"coordinates":[153.40492248499999,-28.0647792816],"type":"Point"}
}