{
  "type": "Feature",
  "properties": {
    "addr:full":"9 Queens Rd Hamilton QLD 4007",
    "addr:housenumber":"9",
    "addr:postcode":"4007",
    "addr:street":"Queens Rd",
    "iso:country":"AU",
    "sg:address":"9 Queens Rd",
    "sg:city":"Hamilton",
    "sg:classifiers":[
        {
            "category":"Education",
            "subcategory":"University",
            "type":"Public Place"
        }
    ],
    "sg:phone":"+61 7 3262 3769",
    "sg:postcode":"4007",
    "sg:province":"QLD",
    "sg:tags":[
        "educational",
        "organisation",
        "cultural"
    ],
    "wof:name":"The English-Speaking Union",
    "wof:placetype":"venue"
},
  "geometry": {"coordinates":[153.04911799999999,-27.436008],"type":"Point"}
}