{
  "type": "Feature",
  "properties": {
    "addr:full":"7 Foch Ave Coburg VIC 3058",
    "addr:housenumber":"7",
    "addr:postcode":"3058",
    "addr:street":"Foch Ave",
    "iso:country":"AU",
    "sg:address":"7 Foch Ave",
    "sg:city":"Coburg",
    "sg:classifiers":[
        {
            "category":"Building & Trades",
            "subcategory":"Construction",
            "type":"Services"
        }
    ],
    "sg:phone":"+61 417 587 393",
    "sg:postcode":"3058",
    "sg:province":"VIC",
    "sg:tags":[
        "joiner",
        "carpenter"
    ],
    "wof:name":"CP Building Services",
    "wof:placetype":"venue"
},
  "geometry": {"coordinates":[144.955566406,-37.7536773682],"type":"Point"}
}