{
  "type": "Feature",
  "properties": {
    "iso:country":"AU",
    "sg:address":"65 Maitland St",
    "sg:city":"Narrabri",
    "sg:classifiers":[
        {
            "category":"Professional",
            "subcategory":"Accounting & Tax Preparation",
            "type":"Services"
        }
    ],
    "sg:phone":"+61 2 6792 3706",
    "sg:postcode":"2390",
    "sg:province":"NSW",
    "sg:tags":[
        "consultant",
        "taxation"
    ],
    "wof:name":"D. B. Mahaffy & Associates Pty Ltd",
    "wof:placetype":"venue"
},
  "geometry": {"coordinates":[149.784057617,-30.3272094727],"type":"Point"}
}