{
  "type": "Feature",
  "properties": {
    "iso:country":"AU",
    "sg:address":"Unit 6b/ 12 Louise St",
    "sg:city":"Southport",
    "sg:classifiers":[
        {
            "category":"Education",
            "subcategory":"Library",
            "type":"Public Place"
        }
    ],
    "sg:phone":"+61 1300 300 369",
    "sg:postcode":"4215",
    "sg:province":"QLD",
    "sg:tags":[
        "equipment",
        "supply"
    ],
    "wof:name":"ABAX Kingfisher Library",
    "wof:placetype":"venue"
},
  "geometry": {"coordinates":[153.40332031200001,-27.9773426056],"type":"Point"}
}