{
  "type": "Feature",
  "properties": {
    "iso:country":"AU",
    "sg:address":"27 Fordson Rd",
    "sg:city":"Campbellfield",
    "sg:classifiers":[
        {
            "category":"Wholesale",
            "subcategory":"Auto Parts",
            "type":"Manufacturing & Wholesale Goods"
        }
    ],
    "sg:phone":"+61 3 9359 1455",
    "sg:postcode":"3061",
    "sg:province":"VIC",
    "sg:tags":[
        "recyclers"
    ],
    "wof:name":"Hume Auto Wreckers Pty Ltd",
    "wof:placetype":"venue"
},
  "geometry": {"coordinates":[144.95960998499999,-37.6742248535],"type":"Point"}
}