{
  "type": "Feature",
  "properties": {
    "addr:full":"23 Jane St Southport QLD 4215",
    "addr:housenumber":"23",
    "addr:postcode":"4215",
    "addr:street":"Jane St",
    "iso:country":"AU",
    "sg:address":"23 Jane St",
    "sg:city":"Southport",
    "sg:classifiers":[
        {
            "category":"Personal",
            "subcategory":"Hair Removal",
            "type":"Services"
        }
    ],
    "sg:phone":"+61 409 250 814",
    "sg:postcode":"4215",
    "sg:province":"QLD",
    "sg:tags":[
        "ornament"
    ],
    "wof:name":"T J K Hair Accessories",
    "wof:placetype":"venue"
},
  "geometry": {"coordinates":[153.400466919,-27.9811401367],"type":"Point"}
}