{
  "type": "Feature",
  "properties": {
    "iso:country":"AU",
    "sg:address":"22 Lyall St",
    "sg:city":"South Perth",
    "sg:classifiers":[
        {
            "category":"Wholesale",
            "subcategory":"Medical Equipment & Supplies",
            "type":"Manufacturing & Wholesale Goods"
        }
    ],
    "sg:phone":"+61 8 9367 1216",
    "sg:postcode":"6151",
    "sg:province":"WA",
    "sg:tags":[
        "dental"
    ],
    "wof:name":"Ray Purt Dental",
    "wof:placetype":"venue"
},
  "geometry": {"coordinates":[115.850906,-31.974693],"type":"Point"}
}