{
  "type": "Feature",
  "properties": {
    "addr:full":"165 Oberon St Oberon NSW 2787",
    "addr:housenumber":"165",
    "addr:postcode":"2787",
    "addr:street":"Oberon St",
    "iso:country":"AU",
    "sg:address":"165 Oberon St",
    "sg:city":"Oberon",
    "sg:classifiers":[
        {
            "category":"Personal",
            "subcategory":"Beauty Salon",
            "type":"Services"
        }
    ],
    "sg:phone":"+61 2 6336 1874",
    "sg:postcode":"2787",
    "sg:province":"NSW",
    "sg:tags":[
        "hairdresser"
    ],
    "wof:name":"Melita's Clippers",
    "wof:placetype":"venue"
},
  "geometry": {"coordinates":[149.856369019,-33.7038230896],"type":"Point"}
}