{
  "type": "Feature",
  "properties": {
    "addr:full":"2 Wattle St Ascot QLD 4007",
    "addr:housenumber":"2",
    "addr:postcode":"4007",
    "addr:street":"Wattle St",
    "iso:country":"AU",
    "sg:address":"2 Wattle St",
    "sg:city":"Ascot",
    "sg:classifiers":[
        {
            "category":"Structure",
            "subcategory":"Office Building",
            "type":"Public Place"
        }
    ],
    "sg:phone":"+61 7 3262 5673",
    "sg:postcode":"4007",
    "sg:province":"QLD",
    "sg:tags":[
        "tie",
        "concrete",
        "formwork",
        "form",
        "accessory"
    ],
    "wof:name":"Caruso G P & Co",
    "wof:placetype":"venue"
},
  "geometry": {"coordinates":[153.06187399999999,-27.424911],"type":"Point"}
}