{
  "type": "Feature",
  "properties": {
    "iso:country":"AU",
    "sg:address":"102 Cecil St",
    "sg:city":"Gnowangerup",
    "sg:classifiers":[
        {
            "category":"Wholesale",
            "subcategory":"Machinery & Supplies",
            "type":"Manufacturing & Wholesale Goods"
        }
    ],
    "sg:phone":"+61 1800 123 033",
    "sg:postcode":"6335",
    "sg:province":"WA",
    "sg:tags":[
        "instrument"
    ],
    "wof:name":"Southern Products Australia",
    "wof:placetype":"venue"
},
  "geometry": {"coordinates":[118.008636475,-33.9388961792],"type":"Point"}
}