{
  "type": "Feature",
  "properties": {
    "addr:full":"35 Shaftesbury Tce Marino SA 5049",
    "addr:housenumber":"35",
    "addr:postcode":"5049",
    "addr:street":"Shaftesbury Tce",
    "iso:country":"AU",
    "sg:address":"35 Shaftesbury Tce",
    "sg:city":"Marino",
    "sg:classifiers":[
        {
            "category":"Retail",
            "subcategory":"Auto Rental",
            "type":"Services"
        }
    ],
    "sg:phone":"+61 8 8296 6882",
    "sg:postcode":"5049",
    "sg:province":"SA",
    "sg:tags":[
        "car",
        "wedding"
    ],
    "sg:website":"http://www.classicjags.com.au",
    "wof:name":"Classic Jags",
    "wof:placetype":"venue"
},
  "geometry": {"coordinates":[138.50964400000001,-35.043995],"type":"Point"}
}