{
  "type": "Feature",
  "properties": {
    "addr:full":"128 Rundle Mall Adelaide SA 5000",
    "addr:housenumber":"128",
    "addr:postcode":"5000",
    "addr:street":"Rundle Mall",
    "iso:country":"AU",
    "sg:address":"128 Rundle Mall",
    "sg:city":"Adelaide",
    "sg:classifiers":[
        {
            "category":"Travel",
            "subcategory":"Hotels & Motels",
            "type":"Entertainment"
        }
    ],
    "sg:phone":"+61 8 8215 4444",
    "sg:postcode":"5000",
    "sg:province":"SA",
    "sg:tags":[
        "accommodation"
    ],
    "sg:website":"http://www.hotelrichmond.com.au",
    "wof:name":"Hotel Richmond",
    "wof:placetype":"venue"
},
  "geometry": {"coordinates":[138.60421752900001,-34.922618866],"type":"Point"}
}