{
  "type": "Feature",
  "properties": {
    "addr:full":"7 Glenridge Drv Tewantin QLD 4565",
    "addr:housenumber":"7",
    "addr:postcode":"4565",
    "addr:street":"Glenridge Drv",
    "iso:country":"AU",
    "sg:address":"7 Glenridge Drv",
    "sg:city":"Tewantin",
    "sg:classifiers":[
        {
            "category":"Building & Trades",
            "subcategory":"Construction",
            "type":"Services"
        }
    ],
    "sg:phone":"+61 7 5449 8794",
    "sg:postcode":"4565",
    "sg:province":"QLD",
    "sg:tags":[
        "earth",
        "excavating",
        "moving",
        "contractor"
    ],
    "wof:name":"Bills Bob Cat Service",
    "wof:placetype":"venue"
},
  "geometry": {"coordinates":[152.9740448,-26.3547534943],"type":"Point"}
}