{
  "type": "Feature",
  "properties": {
    "iso:country":"AU",
    "sg:address":"29 Malabar St",
    "sg:city":"East Launceston",
    "sg:classifiers":[
        {
            "category":"Building & Trades",
            "subcategory":"Construction",
            "type":"Services"
        }
    ],
    "sg:phone":"+61 407 885 569",
    "sg:postcode":"7250",
    "sg:province":"TAS",
    "sg:tags":[
        "contractor"
    ],
    "wof:name":"All Round Home Maintenance",
    "wof:placetype":"venue"
},
  "geometry": {"coordinates":[147.154754639,-41.4417533875],"type":"Point"}
}