{
  "type": "Feature",
  "properties": {
    "addr:full":"Suite 2/53 Mountain Gate Shopping Centre Ferntree Gully VIC 3156",
    "addr:postcode":"3156",
    "iso:country":"AU",
    "sg:address":"Suite 2/53 Mountain Gate Shopping Centre",
    "sg:city":"Ferntree Gully",
    "sg:classifiers":[
        {
            "category":"Personal",
            "subcategory":"Massage",
            "type":"Services"
        }
    ],
    "sg:phone":"+61 3 9753 5445",
    "sg:postcode":"3156",
    "sg:province":"VIC",
    "sg:tags":[
        "therapy"
    ],
    "sg:website":"http://www.aamt.com.au",
    "wof:name":"Debra Fenelon / Mountaingate Therapy Centre",
    "wof:placetype":"venue"
},
  "geometry": {"coordinates":[145.27479553200001,-37.8894691467],"type":"Point"}
}