{
  "type": "Feature",
  "properties": {
    "addr:full":"2/ 13 Stephens Rd Queanbeyan ACT 2620",
    "addr:housenumber":"/ 13",
    "addr:postcode":"2620",
    "addr:street":"Stephens Rd",
    "iso:country":"AU",
    "sg:address":"2/ 13 Stephens Rd",
    "sg:city":"Queanbeyan",
    "sg:classifiers":[
        {
            "category":"Government",
            "subcategory":"Fire Station",
            "type":"Public Place"
        }
    ],
    "sg:phone":"+61 2 6284 4899",
    "sg:postcode":"2620",
    "sg:province":"ACT",
    "sg:tags":[
        "equipment",
        "protection",
        "consultant"
    ],
    "wof:name":"Fire & Life Safety Pty Ltd",
    "wof:placetype":"venue"
},
  "geometry": {"coordinates":[149.20820617699999,-35.3462791443],"type":"Point"}
}