{
  "type": "Feature",
  "properties": {
    "iso:country":"AU",
    "sg:address":"Upton House, 1st Floor Thames St",
    "sg:city":"Box Hill",
    "sg:classifiers":[
        {
            "category":"Health Services",
            "subcategory":"Doctor",
            "type":"Services"
        }
    ],
    "sg:phone":"+61 3 9895 8000",
    "sg:postcode":"3128",
    "sg:province":"VIC",
    "sg:tags":[
        "medical",
        "practitioner"
    ],
    "wof:name":"Pring Bill",
    "wof:placetype":"venue"
},
  "geometry": {"coordinates":[145.125442505,-37.8136901855],"type":"Point"}
}