{
  "type": "Feature",
  "properties": {
    "addr:full":"Shop 37 Plumpton Marketplace, Cnt Hyatt & Jersey R Plumpton NSW 2761",
    "addr:housenumber":"shop 37",
    "addr:postcode":"2761",
    "addr:street":"Cnt;R Plumpton",
    "iso:country":"AU",
    "sg:address":"Shop 37 Plumpton Marketplace, Cnt Hyatt & Jersey R",
    "sg:city":"Plumpton",
    "sg:classifiers":[
        {
            "category":"Food & Beverages",
            "subcategory":"Bakery",
            "type":"Retail Goods"
        }
    ],
    "sg:phone":"+61 2 9832 1900",
    "sg:postcode":"2761",
    "sg:province":"NSW",
    "sg:tags":[
        "baker"
    ],
    "wof:name":"Bakers Delight Ltd",
    "wof:placetype":"venue"
},
  "geometry": {"coordinates":[150.83595299999999,-33.744141],"type":"Point"}
}