{
  "type": "Feature",
  "properties": {
    "iso:country":"AU",
    "sg:address":"22 Shoplands Rd",
    "sg:city":"Annangrove",
    "sg:classifiers":[
        {
            "category":"Building & Trades",
            "subcategory":"Construction",
            "type":"Services"
        }
    ],
    "sg:phone":"+61 2 9679 0264",
    "sg:postcode":"2156",
    "sg:province":"NSW",
    "sg:tags":[
        "contractor"
    ],
    "wof:name":"All Building and Repairs",
    "wof:placetype":"venue"
},
  "geometry": {"coordinates":[150.943267822,-33.6477012634],"type":"Point"}
}