{
  "type": "Feature",
  "properties": {
    "addr:full":"39 Fernando St Burpengary QLD 4505",
    "addr:housenumber":"39",
    "addr:postcode":"4505",
    "addr:street":"Fernando St",
    "iso:country":"AU",
    "sg:address":"39 Fernando St",
    "sg:city":"Burpengary",
    "sg:classifiers":[
        {
            "category":"Health Services",
            "subcategory":"Health Practitioner",
            "type":"Services"
        }
    ],
    "sg:phone":"+61 7 3888 2056",
    "sg:postcode":"4505",
    "sg:province":"QLD",
    "sg:tags":[
        "pathologist",
        "speech"
    ],
    "wof:name":"Communication Options",
    "wof:placetype":"venue"
},
  "geometry": {"coordinates":[152.96278381400001,-27.1666183472],"type":"Point"}
}