{
  "type": "Feature",
  "properties": {
    "addr:full":"254 Hintingdale Rd Oakleigh VIC 3166",
    "addr:housenumber":"254",
    "addr:postcode":"3166",
    "addr:street":"Hintingdale Rd",
    "iso:country":"AU",
    "sg:address":"254 Hintingdale Rd",
    "sg:city":"Oakleigh",
    "sg:classifiers":[
        {
            "category":"Retail",
            "subcategory":"Car Wash",
            "type":"Services"
        }
    ],
    "sg:phone":"+61 411 756 145",
    "sg:postcode":"3166",
    "sg:province":"VIC",
    "sg:tags":[
        "truck",
        "cleaning"
    ],
    "wof:name":"Clean Cut Detailing",
    "wof:placetype":"venue"
},
  "geometry": {"coordinates":[145.10459899899999,-37.9062538147],"type":"Point"}
}