{
  "type": "Feature",
  "properties": {
    "addr:full":"135 Musgrave St North Rockhampton QLD 4701",
    "addr:housenumber":"135",
    "addr:postcode":"4701",
    "addr:street":"Musgrave St North",
    "iso:country":"AU",
    "sg:address":"135 Musgrave St",
    "sg:city":"North Rockhampton",
    "sg:classifiers":[
        {
            "category":"Personal",
            "subcategory":"Beauty Salon",
            "type":"Services"
        }
    ],
    "sg:phone":"+61 7 4927 5319",
    "sg:postcode":"4701",
    "sg:province":"QLD",
    "sg:tags":[
        "hairdresser"
    ],
    "wof:name":"Rae-Lyn's Hair Fashions",
    "wof:placetype":"venue"
},
  "geometry": {"coordinates":[150.52206420900001,-23.3649539948],"type":"Point"}
}