{
  "type": "Feature",
  "properties": {
    "iso:country":"AU",
    "sg:address":"3 Boradino Pl",
    "sg:city":"Rowville",
    "sg:classifiers":[
        {
            "category":"Transit Center",
            "subcategory":"Freight",
            "type":"Transportation"
        }
    ],
    "sg:phone":"+61 3 9752 8678",
    "sg:postcode":"3178",
    "sg:province":"VIC",
    "sg:tags":[
        "forklift",
        "truck"
    ],
    "wof:name":"Forklift Field Service Pty Ltd",
    "wof:placetype":"venue"
},
  "geometry": {"coordinates":[145.27874755900001,-37.9055137634],"type":"Point"}
}