{
  "type": "Feature",
  "properties": {
    "addr:full":"Unit 2/ 5 Booran Drv Woodridge QLD 4114",
    "addr:postcode":"4114",
    "addr:street":"Booran Drv",
    "iso:country":"AU",
    "sg:address":"Unit 2/ 5 Booran Drv",
    "sg:city":"Woodridge",
    "sg:classifiers":[
        {
            "category":"Professional",
            "subcategory":"Engineering",
            "type":"Services"
        }
    ],
    "sg:phone":"+61 7 3208 6555",
    "sg:postcode":"4114",
    "sg:province":"QLD",
    "sg:tags":[
        "electronic",
        "engineer"
    ],
    "wof:name":"Masters & Young Pty Ltd",
    "wof:placetype":"venue"
},
  "geometry": {"coordinates":[153.11581420900001,-27.6232681274],"type":"Point"}
}