{
  "type": "Feature",
  "properties": {
    "addr:full":"16 Hutton St Osborne Park WA 6017",
    "addr:housenumber":"16",
    "addr:postcode":"6017",
    "addr:street":"Hutton St",
    "iso:country":"AU",
    "sg:address":"16 Hutton St",
    "sg:city":"Osborne Park",
    "sg:classifiers":[
        {
            "category":"Professional",
            "subcategory":"Printing & Photocopies",
            "type":"Services"
        }
    ],
    "sg:phone":"+61 8 9445 9554",
    "sg:postcode":"6017",
    "sg:province":"WA",
    "sg:tags":[
        "equipment",
        "plan"
    ],
    "wof:name":"Jiffy Printing",
    "wof:placetype":"venue"
},
  "geometry": {"coordinates":[115.81761932400001,-31.9041004181],"type":"Point"}
}