{
  "type": "Feature",
  "properties": {
    "addr:full":"23 Mine Rd Korumburra VIC 3950",
    "addr:housenumber":"23",
    "addr:postcode":"3950",
    "addr:street":"Mine Rd",
    "iso:country":"AU",
    "sg:address":"23 Mine Rd",
    "sg:city":"Korumburra",
    "sg:classifiers":[
        {
            "category":"Banks & Credit Unions",
            "subcategory":"Investment Brokerage",
            "type":"Services"
        }
    ],
    "sg:phone":"+61 3 5655 1868",
    "sg:postcode":"3950",
    "sg:province":"VIC",
    "sg:tags":[
        "radiator",
        "motor"
    ],
    "wof:name":"Korumburra Radiators",
    "wof:placetype":"venue"
},
  "geometry": {"coordinates":[145.827514648,-38.4360847473],"type":"Point"}
}