{
  "type": "Feature",
  "properties": {
    "iso:country":"AU",
    "sg:address":"Shop 8 Cleveland Shopng Cntr Middle St",
    "sg:city":"Cleveland",
    "sg:classifiers":[
        {
            "category":"Food & Beverages",
            "subcategory":"Bakery",
            "type":"Retail Goods"
        }
    ],
    "sg:phone":"+61 7 3821 3061",
    "sg:postcode":"4163",
    "sg:province":"QLD",
    "sg:tags":[
        "baker"
    ],
    "wof:name":"Brumbys Cleveland",
    "wof:placetype":"venue"
},
  "geometry": {"coordinates":[153.26658630399999,-27.5258235931],"type":"Point"}
}