{
  "type": "Feature",
  "properties": {
    "addr:full":"1137 Nambour Connection Rd Nambour QLD 4560",
    "addr:housenumber":"1137",
    "addr:postcode":"4560",
    "addr:street":"Nambour Connection Rd",
    "iso:country":"AU",
    "sg:address":"1137 Nambour Connection Rd",
    "sg:city":"Nambour",
    "sg:classifiers":[
        {
            "category":"Wholesale",
            "subcategory":"Machinery & Supplies",
            "type":"Manufacturing & Wholesale Goods"
        }
    ],
    "sg:phone":"+61 7 5441 5677",
    "sg:postcode":"4560",
    "sg:province":"QLD",
    "sg:tags":[
        "agricultural"
    ],
    "wof:name":"Nambour Tractors And Implements Sales & Service",
    "wof:placetype":"venue"
},
  "geometry": {"coordinates":[152.97056579599999,-26.5979728699],"type":"Point"}
}