{
  "type": "Feature",
  "properties": {
    "addr:full":"9 Oliver St Scarborough WA 6019",
    "addr:housenumber":"9",
    "addr:postcode":"6019",
    "addr:street":"Oliver St",
    "iso:country":"AU",
    "sg:address":"9 Oliver St",
    "sg:city":"Scarborough",
    "sg:classifiers":[
        {
            "category":"Shopping",
            "subcategory":"Bicycles & Sporting Goods",
            "type":"Retail Goods"
        }
    ],
    "sg:phone":"+61 8 9245 4657",
    "sg:postcode":"6019",
    "sg:province":"WA",
    "sg:tags":[
        "water",
        "equipment",
        "skiing"
    ],
    "wof:name":"Windesigns Australia",
    "wof:placetype":"venue"
},
  "geometry": {"coordinates":[115.76097106900001,-31.9025287628],"type":"Point"}
}