{
  "type": "Feature",
  "properties": {
    "addr:full":"64 Church St Rochester VIC 3561",
    "addr:housenumber":"64",
    "addr:postcode":"3561",
    "addr:street":"Church St",
    "iso:country":"AU",
    "sg:address":"64 Church St",
    "sg:city":"Rochester",
    "sg:classifiers":[
        {
            "category":"Building & Trades",
            "subcategory":"Construction",
            "type":"Services"
        }
    ],
    "sg:phone":"+61 400 043 249",
    "sg:postcode":"3561",
    "sg:province":"VIC",
    "sg:tags":[
        "fencing",
        "contractor"
    ],
    "wof:name":"Mtee Fencing",
    "wof:placetype":"venue"
},
  "geometry": {"coordinates":[144.70512390100001,-36.361000061],"type":"Point"}
}