{
  "type": "Feature",
  "properties": {
    "addr:full":"222 Cressy St Deniliquin NSW 2710",
    "addr:housenumber":"222",
    "addr:postcode":"2710",
    "addr:street":"Cressy St",
    "iso:country":"AU",
    "sg:address":"222 Cressy St",
    "sg:city":"Deniliquin",
    "sg:classifiers":[
        {
            "category":"Recreation",
            "subcategory":"Fishing",
            "type":"Entertainment"
        }
    ],
    "sg:phone":"+61 3 5881 1634",
    "sg:postcode":"2710",
    "sg:province":"NSW",
    "sg:tags":[
        "tackle"
    ],
    "wof:name":"Deni Sports Centre",
    "wof:placetype":"venue"
},
  "geometry": {"coordinates":[144.96188354500001,-35.5279693604],"type":"Point"}
}