{
  "type": "Feature",
  "properties": {
    "addr:full":"871 Bells Line Of Rd Kurrajong Hills NSW 2758",
    "addr:housenumber":"871",
    "addr:postcode":"2758",
    "addr:street":"Bells Line Of Rd",
    "iso:country":"AU",
    "sg:address":"871 Bells Line Of Rd",
    "sg:city":"Kurrajong Hills",
    "sg:classifiers":[
        {
            "category":"Building & Trades",
            "subcategory":"Pest Control",
            "type":"Services"
        }
    ],
    "sg:phone":"+61 2 4573 1133",
    "sg:postcode":"2758",
    "sg:province":"NSW",
    "wof:name":"Any Pest &#034;Bugs & Rugs&#034;",
    "wof:placetype":"venue"
},
  "geometry": {"coordinates":[150.64190673799999,-33.5417404175],"type":"Point"}
}