{
  "type": "Feature",
  "properties": {
    "iso:country":"AU",
    "sg:address":"42 Kindlebark Drv",
    "sg:city":"Medowie",
    "sg:classifiers":[
        {
            "category":"Education",
            "subcategory":"Kindergarten",
            "type":"Public Place"
        }
    ],
    "sg:phone":"+61 2 4982 8749",
    "sg:postcode":"2318",
    "sg:province":"NSW",
    "sg:tags":[
        "pre-schools"
    ],
    "wof:name":"Medowie Community Pre-School",
    "wof:placetype":"venue"
},
  "geometry": {"coordinates":[151.87965399999999,-32.738659],"type":"Point"}
}