{
  "type": "Feature",
  "properties": {
    "iso:country":"AU",
    "sg:address":"82 Smith St",
    "sg:city":"Warragul",
    "sg:classifiers":[
        {
            "category":"Shopping",
            "type":"Retail Goods"
        }
    ],
    "sg:phone":"+61 3 5622 3092",
    "sg:postcode":"3820",
    "sg:province":"VIC",
    "sg:tags":[
        "agent",
        "stock"
    ],
    "wof:name":"Gibbon Peter Livestock Pty Ltd",
    "wof:placetype":"venue"
},
  "geometry": {"coordinates":[145.93261699999999,-38.159809],"type":"Point"}
}