{
  "type": "Feature",
  "properties": {
    "iso:country":"AU",
    "sg:address":"408 Scarborough Beach Rd",
    "sg:city":"Osborne Park",
    "sg:classifiers":[
        {
            "category":"Health Services",
            "subcategory":"Health Practitioner",
            "type":"Services"
        }
    ],
    "sg:phone":"+61 8 9242 5112",
    "sg:postcode":"6017",
    "sg:province":"WA",
    "sg:tags":[
        "psychologist"
    ],
    "wof:name":"Castine Rochelle - Clin Psych Services",
    "wof:placetype":"venue"
},
  "geometry": {"coordinates":[115.813621521,-31.9097099304],"type":"Point"}
}