{
  "type": "Feature",
  "properties": {
    "addr:full":"1 Fithie St Blackburn VIC 3130",
    "addr:housenumber":"1",
    "addr:postcode":"3130",
    "addr:street":"Fithie St",
    "iso:country":"AU",
    "sg:address":"1 Fithie St",
    "sg:city":"Blackburn",
    "sg:classifiers":[
        {
            "category":"Recreation",
            "type":"Entertainment"
        }
    ],
    "sg:phone":"+61 3 9878 1528",
    "sg:postcode":"3130",
    "sg:province":"VIC",
    "sg:tags":[
        "children's",
        "play",
        "programme"
    ],
    "wof:name":"Mini Learners",
    "wof:placetype":"venue"
},
  "geometry": {"coordinates":[145.15371704099999,-37.8023872375],"type":"Point"}
}