{
  "type": "Feature",
  "properties": {
    "iso:country":"AU",
    "sg:address":"137 Gillies St",
    "sg:city":"Maryborough",
    "sg:classifiers":[
        {
            "category":"Professional",
            "subcategory":"Art Services",
            "type":"Services"
        }
    ],
    "sg:phone":"+61 407 680 887",
    "sg:postcode":"3465",
    "sg:province":"VIC",
    "sg:tags":[
        "decorator",
        "painter"
    ],
    "wof:name":"Tom Groves Painting Service",
    "wof:placetype":"venue"
},
  "geometry": {"coordinates":[143.749145508,-37.0437774658],"type":"Point"}
}