{
  "type": "Feature",
  "properties": {
    "addr:full":"Joyner St Parramatta NSW 2150",
    "addr:postcode":"2150",
    "addr:street":"Joyner St",
    "iso:country":"AU",
    "sg:address":"Joyner St",
    "sg:city":"Parramatta",
    "sg:classifiers":[
        {
            "category":"Building & Trades",
            "subcategory":"Construction",
            "type":"Services"
        }
    ],
    "sg:phone":"+61 2 9687 0033",
    "sg:postcode":"2150",
    "sg:province":"NSW",
    "sg:tags":[
        "home",
        "air conditioning"
    ],
    "wof:name":"Answer Group Australia",
    "wof:placetype":"venue"
},
  "geometry": {"coordinates":[150.99232482900001,-33.8174629211],"type":"Point"}
}