{
  "type": "Feature",
  "properties": {
    "iso:country":"AU",
    "sg:address":"3/ 16 Brolo Crt",
    "sg:city":"O&#039;Connor",
    "sg:classifiers":[
        {
            "category":"Wholesale",
            "subcategory":"Metals & Minerals",
            "type":"Manufacturing & Wholesale Goods"
        }
    ],
    "sg:phone":"+61 8 9331 6244",
    "sg:postcode":"6163",
    "sg:province":"WA",
    "sg:tags":[
        "steel",
        "stainless",
        "product",
        "equipment"
    ],
    "wof:name":"Auswide TotalWest Fabricators",
    "wof:placetype":"venue"
},
  "geometry": {"coordinates":[115.789497,-32.057903],"type":"Point"}
}