{
  "type": "Feature",
  "properties": {
    "addr:full":"47 Byron St Bulimba QLD 4171",
    "addr:housenumber":"47",
    "addr:postcode":"4171",
    "addr:street":"Byron St",
    "iso:country":"AU",
    "sg:address":"47 Byron St",
    "sg:city":"Bulimba",
    "sg:classifiers":[
        {
            "category":"Professional",
            "subcategory":"Computer Services",
            "type":"Services"
        }
    ],
    "sg:phone":"+61 7 3217 9922",
    "sg:postcode":"4171",
    "sg:province":"QLD",
    "sg:tags":[
        "package",
        "software"
    ],
    "wof:name":"Access Information Services Pty Ltd",
    "wof:placetype":"venue"
},
  "geometry": {"coordinates":[153.06134033199999,-27.4434833527],"type":"Point"}
}