{
  "type": "Feature",
  "properties": {
    "iso:country":"AU",
    "sg:address":"14 Seabourne Rd",
    "sg:city":"Taperoo",
    "sg:classifiers":[
        {
            "category":"Shopping",
            "subcategory":"Pawn Shop",
            "type":"Retail Goods"
        }
    ],
    "sg:phone":"+61 8 8248 5642",
    "sg:postcode":"5017",
    "sg:province":"SA",
    "sg:tags":[
        "pawnbroker"
    ],
    "wof:name":"Automotive Car Pawn",
    "wof:placetype":"venue"
},
  "geometry": {"coordinates":[138.50245666500001,-34.8060188293],"type":"Point"}
}