{
  "type": "Feature",
  "properties": {
    "iso:country":"AU",
    "sg:address":"5/ 38 Kenworth Pl",
    "sg:city":"Brendale",
    "sg:classifiers":[
        {
            "category":"Autos & Motor Vehicles",
            "subcategory":"Auto Supplies",
            "type":"Retail Goods"
        }
    ],
    "sg:phone":"+61 7 3889 6466",
    "sg:postcode":"4500",
    "sg:province":"QLD",
    "sg:tags":[
        "part",
        "cycles",
        "accessory"
    ],
    "wof:name":"Northside Motorcycle Workshop",
    "wof:placetype":"venue"
},
  "geometry": {"coordinates":[152.98843383799999,-27.3249816895],"type":"Point"}
}