{
  "type": "Feature",
  "properties": {
    "addr:full":"90 Binney St Euroa VIC 3666",
    "addr:housenumber":"90",
    "addr:postcode":"3666",
    "addr:street":"Binney St",
    "iso:country":"AU",
    "sg:address":"90 Binney St",
    "sg:city":"Euroa",
    "sg:classifiers":[
        {
            "category":"Health Services",
            "subcategory":"Doctor",
            "type":"Services"
        }
    ],
    "sg:phone":"+61 3 5795 2011",
    "sg:postcode":"3666",
    "sg:province":"VIC",
    "sg:tags":[
        "medical",
        "practitioner"
    ],
    "wof:name":"Altson Malcolm Dr",
    "wof:placetype":"venue"
},
  "geometry": {"coordinates":[145.57095336899999,-36.7513694763],"type":"Point"}
}