{
  "type": "Feature",
  "properties": {
    "addr:full":"50 Bultje St Dubbo NSW 2830",
    "addr:housenumber":"50",
    "addr:postcode":"2830",
    "addr:street":"Bultje St",
    "iso:country":"AU",
    "sg:address":"50 Bultje St",
    "sg:city":"Dubbo",
    "sg:classifiers":[
        {
            "category":"Health Services",
            "subcategory":"Doctor",
            "type":"Services"
        }
    ],
    "sg:phone":"+61 2 6884 3355",
    "sg:postcode":"2830",
    "sg:province":"NSW",
    "sg:tags":[
        "medical",
        "practitioner"
    ],
    "wof:name":"Weyand Jane Dr",
    "wof:placetype":"venue"
},
  "geometry": {"coordinates":[148.603439331,-32.2512893677],"type":"Point"}
}