{
  "type": "Feature",
  "properties": {
    "addr:full":"930 Pittwater Rd Dee Why NSW 2099",
    "addr:housenumber":"930",
    "addr:postcode":"2099",
    "addr:street":"Pittwater Rd",
    "iso:country":"AU",
    "sg:address":"930 Pittwater Rd",
    "sg:city":"Dee Why",
    "sg:classifiers":[
        {
            "category":"Social Services",
            "subcategory":"Child Care",
            "type":"Services"
        }
    ],
    "sg:phone":"+61 2 9972 0222",
    "sg:postcode":"2099",
    "sg:province":"NSW",
    "wof:name":"Kindy Time Dee Why",
    "wof:placetype":"venue"
},
  "geometry": {"coordinates":[151.28997802699999,-33.7493247986],"type":"Point"}
}