{
  "type": "Feature",
  "properties": {
    "addr:full":"PO Box 29 Rundle Mall Adelaide SA 5000",
    "addr:postcode":"5000",
    "addr:street":"Rundle Mall",
    "iso:country":"AU",
    "sg:address":"PO Box 29",
    "sg:city":"Rundle Mall Adelaide",
    "sg:classifiers":[
        {
            "category":"Health Services",
            "subcategory":"Doctor",
            "type":"Services"
        }
    ],
    "sg:phone":"+61 418 828 401",
    "sg:postcode":"5000",
    "sg:province":"SA",
    "sg:tags":[
        "occupational",
        "safety"
    ],
    "wof:name":"Safety Institute of Australia (S.A. Division)",
    "wof:placetype":"venue"
},
  "geometry": {"coordinates":[138.59693908700001,-34.922908783],"type":"Point"}
}