{
  "type": "Feature",
  "properties": {
    "addr:full":"Unit 9/ 55 Norfolk Rd Marion SA 5043",
    "addr:postcode":"5043",
    "addr:street":"Norfolk Rd",
    "iso:country":"AU",
    "sg:address":"Unit 9/ 55 Norfolk Rd",
    "sg:city":"Marion",
    "sg:classifiers":[
        {
            "category":"Retail",
            "subcategory":"Laundry & Dry Cleaning",
            "type":"Services"
        }
    ],
    "sg:phone":"+61 1300 885 287",
    "sg:postcode":"5043",
    "sg:province":"SA",
    "sg:tags":[
        "machine",
        "commercial",
        "industrial",
        "washing"
    ],
    "wof:name":"Laundry Innovations",
    "wof:placetype":"venue"
},
  "geometry": {"coordinates":[138.55682400000001,-35.013615],"type":"Point"}
}