{
  "type": "Feature",
  "properties": {
    "addr:full":"78 Cartwright St Ingham QLD 4850",
    "addr:housenumber":"78",
    "addr:postcode":"4850",
    "addr:street":"Cartwright St",
    "iso:country":"AU",
    "sg:address":"78 Cartwright St",
    "sg:city":"Ingham",
    "sg:classifiers":[
        {
            "category":"Manufacturing",
            "subcategory":"Motor Vehicles & Parts",
            "type":"Manufacturing & Wholesale Goods"
        }
    ],
    "sg:phone":"+61 7 4776 2750",
    "sg:postcode":"4850",
    "sg:province":"QLD",
    "sg:tags":[
        "replacement"
    ],
    "wof:name":"Ingham Car Wreckers",
    "wof:placetype":"venue"
},
  "geometry": {"coordinates":[146.164505005,-18.6486301422],"type":"Point"}
}