{
  "type": "Feature",
  "properties": {
    "iso:country":"AU",
    "sg:address":"15 Eaton Pde",
    "sg:city":"Laverton",
    "sg:classifiers":[
        {
            "category":"Utilities",
            "subcategory":"Electric",
            "type":"Services"
        }
    ],
    "sg:phone":"+61 418 361 075",
    "sg:postcode":"3028",
    "sg:province":"VIC",
    "sg:tags":[
        "electrical",
        "contractor"
    ],
    "wof:name":"R & N Sevior",
    "wof:placetype":"venue"
},
  "geometry": {"coordinates":[144.772293,-37.853676],"type":"Point"}
}