{
  "type": "Feature",
  "properties": {
    "addr:full":"U 10/ 477 Orrong Rd Welshpool WA 6106",
    "addr:housenumber":"10 / 477",
    "addr:postcode":"6106",
    "addr:street":"Orrong Rd",
    "iso:country":"AU",
    "sg:address":"U 10/ 477 Orrong Rd",
    "sg:city":"Welshpool",
    "sg:classifiers":[
        {
            "category":"Freight",
            "type":"Transportation"
        }
    ],
    "sg:phone":"+61 8 9356 3688",
    "sg:postcode":"6106",
    "sg:province":"WA",
    "sg:tags":[
        "cargo",
        "air"
    ],
    "wof:name":"C.T. Freight Pty Ltd",
    "wof:placetype":"venue"
},
  "geometry": {"coordinates":[115.972183227,-32.0026664734],"type":"Point"}
}