{
  "type": "Feature",
  "properties": {
    "addr:full":"Rannock Rd Rannock NSW 2701",
    "addr:postcode":"2701",
    "addr:street":"Rannock Rd",
    "iso:country":"AU",
    "sg:address":"Rannock Rd",
    "sg:city":"Rannock",
    "sg:classifiers":[
        {
            "category":"Commercial Area",
            "type":"Public Place"
        }
    ],
    "sg:phone":"+61 2 6927 8500",
    "sg:postcode":"2701",
    "sg:province":"NSW",
    "sg:tags":[
        "heavy",
        "carrier"
    ],
    "wof:name":"Gibbos Bulk Haulage",
    "wof:placetype":"venue"
},
  "geometry": {"coordinates":[147.25111389200001,-34.6082115173],"type":"Point"}
}