{
  "type": "Feature",
  "properties": {
    "iso:country":"AU",
    "sg:address":"25 King William St",
    "sg:city":"Reservoir",
    "sg:classifiers":[
        {
            "category":"Professional",
            "subcategory":"Art Services",
            "type":"Services"
        }
    ],
    "sg:phone":"+61 417 589 223",
    "sg:postcode":"3073",
    "sg:province":"VIC",
    "sg:tags":[
        "decorator",
        "painter"
    ],
    "wof:name":"A. Sergi Painting & Decorating",
    "wof:placetype":"venue"
},
  "geometry": {"coordinates":[145.01190185600001,-37.726776123],"type":"Point"}
}