{
  "type": "Feature",
  "properties": {
    "addr:full":"Shop 7,Woodville Park Shopping Centre Hoppers Crossing VIC 3029",
    "addr:housenumber":"shop 7",
    "addr:postcode":"3029",
    "addr:street":"Woodville Park",
    "iso:country":"AU",
    "sg:address":"Shop 7,Woodville Park Shopping Centre",
    "sg:city":"Hoppers Crossing",
    "sg:classifiers":[
        {
            "category":"Fast Food",
            "type":"Food & Drink"
        }
    ],
    "sg:phone":"+61 3 9749 5508",
    "sg:postcode":"3029",
    "sg:province":"VIC",
    "sg:tags":[
        "away",
        "take"
    ],
    "wof:name":"New Taste Chinese Take Away",
    "wof:placetype":"venue"
},
  "geometry": {"coordinates":[144.68980400000001,-37.879131],"type":"Point"}
}