{
  "type": "Feature",
  "properties": {
    "addr:full":"Unit 2/55- 57 Alexander Ave Taren Point NSW 2229",
    "addr:housenumber":"57",
    "addr:postcode":"2229",
    "addr:street":"Alexander Ave",
    "iso:country":"AU",
    "sg:address":"Unit 2/55- 57 Alexander Ave",
    "sg:city":"Taren Point",
    "sg:classifiers":[
        {
            "category":"Autos & Motor Vehicles",
            "subcategory":"Boat Sales",
            "type":"Retail Goods"
        }
    ],
    "sg:phone":"+61 2 9540 5864",
    "sg:postcode":"2229",
    "sg:province":"NSW",
    "sg:tags":[
        "builder",
        "yacht",
        "repairer"
    ],
    "wof:name":"Splits Fibreglass Boat Repairs",
    "wof:placetype":"venue"
},
  "geometry": {"coordinates":[151.12351989699999,-34.0226860046],"type":"Point"}
}