{
  "type": "Feature",
  "properties": {
    "iso:country":"AU",
    "sg:address":"4/ 13 Forsyth St",
    "sg:city":"O'Connor",
    "sg:classifiers":[
        {
            "category":"Utilities",
            "type":"Services"
        }
    ],
    "sg:phone":"+61 8 9331 5199",
    "sg:postcode":"6163",
    "sg:province":"WA",
    "sg:tags":[
        "refrigeration",
        "industrial",
        "commercial",
        "retail"
    ],
    "wof:name":"A & A Plastic Strip Curtains",
    "wof:placetype":"venue"
},
  "geometry": {"coordinates":[115.793068,-32.054993],"type":"Point"}
}