{
  "type": "Feature",
  "properties": {
    "iso:country":"AU",
    "sg:address":"Unit 1, 27- 29 Culgoa Crs",
    "sg:city":"Logan Village",
    "sg:classifiers":[
        {
            "category":"Professional",
            "subcategory":"Accounting & Tax Preparation",
            "type":"Services"
        }
    ],
    "sg:phone":"+61 1300 368 725",
    "sg:postcode":"4207",
    "sg:province":"QLD",
    "sg:tags":[
        "bookkeeping"
    ],
    "sg:website":"http://www.computerconsultants.com.au",
    "wof:name":"Computer Consultants.Com.Au",
    "wof:placetype":"venue"
},
  "geometry": {"coordinates":[153.233276367,-27.7373123169],"type":"Point"}
}