{
  "type": "Feature",
  "properties": {
    "addr:full":"28 Argyle St Camden NSW 2570",
    "addr:housenumber":"28",
    "addr:postcode":"2570",
    "addr:street":"Argyle St",
    "iso:country":"AU",
    "sg:address":"28 Argyle St",
    "sg:city":"Camden",
    "sg:classifiers":[
        {
            "category":"Autos & Motor Vehicles",
            "subcategory":"Fuel & Gas Station",
            "type":"Retail Goods"
        }
    ],
    "sg:phone":"+61 2 4655 7605",
    "sg:postcode":"2570",
    "sg:province":"NSW",
    "wof:name":"Mobil Oil Australia Pty Ltd",
    "wof:placetype":"venue"
},
  "geometry": {"coordinates":[150.699386597,-34.0534057617],"type":"Point"}
}