{
  "type": "Feature",
  "properties": {
    "addr:full":"Shop 6/ 83 Lytton Rd East Brisbane QLD 4169",
    "addr:housenumber":"shop 6 / 83",
    "addr:postcode":"4169",
    "addr:street":"Lytton Rd",
    "iso:country":"AU",
    "sg:address":"Shop 6/ 83 Lytton Rd",
    "sg:city":"East Brisbane",
    "sg:classifiers":[
        {
            "category":"Fast Food",
            "type":"Food & Drink"
        }
    ],
    "sg:phone":"+61 7 3891 6464",
    "sg:postcode":"4169",
    "sg:province":"QLD",
    "sg:tags":[
        "away",
        "take"
    ],
    "wof:name":"The Fishmongers Wife",
    "wof:placetype":"venue"
},
  "geometry": {"coordinates":[153.045120239,-27.4796085358],"type":"Point"}
}