{
  "type": "Feature",
  "properties": {
    "addr:full":"Suite 2, Level 1, 18 Smith St Parramatta NSW 2123",
    "addr:housenumber":"18",
    "addr:postcode":"2123",
    "addr:street":"Smith St",
    "iso:country":"AU",
    "sg:address":"Suite 2, Level 1, 18 Smith St",
    "sg:city":"Parramatta",
    "sg:classifiers":[
        {
            "category":"Real Estate",
            "subcategory":"Real Estate Agent",
            "type":"Services"
        }
    ],
    "sg:phone":"+61 1300 784 868",
    "sg:postcode":"2123",
    "sg:province":"NSW",
    "wof:name":"Richardson & Wrench Financial Solutions",
    "wof:placetype":"venue"
},
  "geometry": {"coordinates":[151.006469727,-33.8307876587],"type":"Point"}
}