{
  "type": "Feature",
  "properties": {
    "addr:full":"1/ 96 Pinjarra Rd Mandurah WA 6210",
    "addr:housenumber":"/ 96",
    "addr:postcode":"6210",
    "addr:street":"Pinjarra Rd",
    "iso:country":"AU",
    "sg:address":"1/ 96 Pinjarra Rd",
    "sg:city":"Mandurah",
    "sg:classifiers":[
        {
            "category":"Home & Garden",
            "subcategory":"Carpets & Floor Coverings",
            "type":"Retail Goods"
        }
    ],
    "sg:phone":"+61 8 9535 5655",
    "sg:postcode":"6210",
    "sg:province":"WA",
    "sg:tags":[
        "wood"
    ],
    "wof:name":"Mandurah Carpet Line",
    "wof:placetype":"venue"
},
  "geometry": {"coordinates":[115.726753,-32.534664],"type":"Point"}
}