{
  "type": "Feature",
  "properties": {
    "addr:full":"Cnr Park Tce & Main Nth Rd Salisbury SA 5108",
    "addr:postcode":"5108",
    "addr:street":"Park Tce & Main Nth Rd",
    "iso:country":"AU",
    "sg:address":"Cnr Park Tce & Main Nth Rd",
    "sg:city":"Salisbury",
    "sg:classifiers":[
        {
            "category":"Retail",
            "subcategory":"Auto Rental",
            "type":"Services"
        }
    ],
    "sg:phone":"+61 8 8283 3555",
    "sg:postcode":"5108",
    "sg:province":"SA",
    "sg:tags":[
        "car",
        "hire",
        "minibus"
    ],
    "wof:name":"Budget Rent A Car",
    "wof:placetype":"venue"
},
  "geometry": {"coordinates":[138.642120361,-34.7604484558],"type":"Point"}
}