{
  "type": "Feature",
  "properties": {
    "addr:full":"5 Woodville Rd Woodville SA 5011",
    "addr:housenumber":"5",
    "addr:postcode":"5011",
    "addr:street":"Woodville Rd",
    "iso:country":"AU",
    "sg:address":"5 Woodville Rd",
    "sg:city":"Woodville",
    "sg:classifiers":[
        {
            "category":"Retail",
            "subcategory":"Veterinary Services",
            "type":"Services"
        }
    ],
    "sg:phone":"+61 8 8268 6777",
    "sg:postcode":"5011",
    "sg:province":"SA",
    "sg:tags":[
        "surgeon"
    ],
    "wof:name":"Pet Doctor",
    "wof:placetype":"venue"
},
  "geometry": {"coordinates":[138.53773498499999,-34.8778495789],"type":"Point"}
}