{
  "type": "Feature",
  "properties": {
    "addr:full":"14 Pritchard St East Wentworthville NSW 2145",
    "addr:housenumber":"14",
    "addr:postcode":"2145",
    "addr:street":"Pritchard St East",
    "iso:country":"AU",
    "sg:address":"14 Pritchard St",
    "sg:city":"East Wentworthville",
    "sg:classifiers":[
        {
            "category":"Health Services",
            "subcategory":"Health Practitioner",
            "type":"Services"
        }
    ],
    "sg:phone":"+61 2 9631 9598",
    "sg:postcode":"2145",
    "sg:province":"NSW",
    "sg:tags":[
        "physiotherapist"
    ],
    "wof:name":"Garrett T",
    "wof:placetype":"venue"
},
  "geometry": {"coordinates":[150.97084045400001,-33.8088188171],"type":"Point"}
}