{
  "type": "Feature",
  "properties": {
    "iso:country":"AU",
    "sg:address":"21 Copland St",
    "sg:city":"Wagga Wagga",
    "sg:classifiers":[
        {
            "category":"Building & Trades",
            "subcategory":"Locksmith",
            "type":"Services"
        }
    ],
    "sg:phone":"+61 2 6921 3994",
    "sg:postcode":"2650",
    "sg:province":"NSW",
    "sg:tags":[
        "strongroom",
        "safe",
        "door"
    ],
    "wof:name":"Power Ammo",
    "wof:placetype":"venue"
},
  "geometry": {"coordinates":[147.41226196299999,-35.129825592],"type":"Point"}
}