{
  "type": "Feature",
  "properties": {
    "iso:country":"AU",
    "sg:address":"Bell St Chiropractic Clinic, 562 Bell St",
    "sg:city":"Pascoe Vale",
    "sg:classifiers":[
        {
            "category":"Health Services",
            "subcategory":"Doctor",
            "type":"Services"
        }
    ],
    "sg:phone":"+61 424 062 059",
    "sg:postcode":"3044",
    "sg:province":"VIC",
    "sg:tags":[
        "reflexology"
    ],
    "wof:name":"Lyndal McLean",
    "wof:placetype":"venue"
},
  "geometry": {"coordinates":[144.926071167,-37.7353248596],"type":"Point"}
}