{
  "type": "Feature",
  "properties": {
    "iso:country":"AU",
    "sg:address":"104 Grimshaw St",
    "sg:city":"Greensborough",
    "sg:classifiers":[
        {
            "category":"Personal",
            "subcategory":"Beauty Salon",
            "type":"Services"
        }
    ],
    "sg:phone":"+61 3 9435 3707",
    "sg:postcode":"3088",
    "sg:province":"VIC",
    "sg:tags":[
        "hairdresser"
    ],
    "wof:name":"Tifani Hair Specialists",
    "wof:placetype":"venue"
},
  "geometry": {"coordinates":[145.100997925,-37.7042236328],"type":"Point"}
}