{
  "type": "Feature",
  "properties": {
    "addr:full":"U1/ 51 Johnston St Southport QLD 4215",
    "addr:housenumber":"51",
    "addr:postcode":"4215",
    "addr:street":"U1 /;Johnston St",
    "iso:country":"AU",
    "sg:address":"U1/ 51 Johnston St",
    "sg:city":"Southport",
    "sg:classifiers":[
        {
            "category":"Food & Beverages",
            "subcategory":"Bakery",
            "type":"Retail Goods"
        }
    ],
    "sg:phone":"+61 407 392 435",
    "sg:postcode":"4215",
    "sg:province":"QLD",
    "sg:tags":[
        "baker"
    ],
    "wof:name":"Nordic Temptations",
    "wof:placetype":"venue"
},
  "geometry": {"coordinates":[153.40538024899999,-27.9656066895],"type":"Point"}
}