{
  "type": "Feature",
  "properties": {
    "addr:full":"Unit 2/ 15 Molesworth St Lismore NSW 2480",
    "addr:housenumber":"15",
    "addr:postcode":"2480",
    "addr:street":"Molesworth St",
    "iso:country":"AU",
    "sg:address":"Unit 2/ 15 Molesworth St",
    "sg:city":"Lismore",
    "sg:classifiers":[
        {
            "category":"Health Services",
            "subcategory":"Dentist",
            "type":"Services"
        }
    ],
    "sg:phone":"+61 2 6622 2244",
    "sg:postcode":"2480",
    "sg:province":"NSW",
    "sg:tags":[
        "dental",
        "prosthetist"
    ],
    "wof:name":"Lismore Denture Clinic",
    "wof:placetype":"venue"
},
  "geometry": {"coordinates":[153.27720642099999,-28.8070373535],"type":"Point"}
}