{
  "type": "Feature",
  "properties": {
    "iso:country":"AU",
    "sg:address":"13 Victoria St",
    "sg:city":"Robe",
    "sg:classifiers":[
        {
            "category":"Cafe",
            "type":"Food & Drink"
        }
    ],
    "sg:phone":"+61 8 8768 2018",
    "sg:postcode":"5276",
    "sg:province":"SA",
    "wof:name":"Robe Bakery & Coffee Lounge",
    "wof:placetype":"venue"
},
  "geometry": {"coordinates":[139.75924699999999,-37.163879],"type":"Point"}
}