{
  "type": "Feature",
  "properties": {
    "addr:full":"25 Caxton St Brisbane QLD 4000",
    "addr:housenumber":"25",
    "addr:postcode":"4000",
    "addr:street":"Caxton St",
    "iso:country":"AU",
    "sg:address":"25 Caxton St",
    "sg:city":"Brisbane",
    "sg:classifiers":[
        {
            "category":"Travel",
            "subcategory":"Hotels & Motels",
            "type":"Entertainment"
        }
    ],
    "sg:phone":"+61 7 3368 1932",
    "sg:postcode":"4000",
    "sg:province":"QLD",
    "sg:tags":[
        "pub"
    ],
    "wof:name":"Kitty O&#039;Sheas Irish Pub",
    "wof:placetype":"venue"
},
  "geometry": {"coordinates":[153.01287841800001,-27.4643993378],"type":"Point"}
}