{
  "type": "Feature",
  "properties": {
    "addr:full":"Herbert St West Ryde NSW 2114",
    "addr:postcode":"2114",
    "addr:street":"Herbert St",
    "iso:country":"AU",
    "sg:address":"Herbert St",
    "sg:city":"West Ryde",
    "sg:classifiers":[
        {
            "category":"Farming",
            "subcategory":"Farm & Veterinary Services",
            "type":"Manufacturing & Wholesale Goods"
        }
    ],
    "sg:phone":"+61 413 429 370",
    "sg:postcode":"2114",
    "sg:province":"NSW",
    "sg:tags":[
        "worm"
    ],
    "wof:name":"Worms & Wormcast",
    "wof:placetype":"venue"
},
  "geometry": {"coordinates":[151.09129333499999,-33.8068695068],"type":"Point"}
}