{
  "type": "Feature",
  "properties": {
    "addr:full":"Stonyfell Wine Complex Stonyfell Rd Stonyfell SA 5066",
    "addr:postcode":"5066",
    "addr:street":"Stonyfell Rd",
    "iso:country":"AU",
    "sg:address":"Stonyfell Wine Complex Stonyfell Rd",
    "sg:city":"Stonyfell",
    "sg:classifiers":[
        {
            "category":"Food & Beverages",
            "subcategory":"Liquor & Beverages",
            "type":"Retail Goods"
        }
    ],
    "sg:phone":"+61 8 8364 5477",
    "sg:postcode":"5066",
    "sg:province":"SA",
    "sg:tags":[
        "merchant",
        "spirit",
        "wine"
    ],
    "wof:name":"S & V Wine Merchants",
    "wof:placetype":"venue"
},
  "geometry": {"coordinates":[138.67071533199999,-34.9293708801],"type":"Point"}
}