{
  "type": "Feature",
  "properties": {
    "iso:country":"AU",
    "sg:address":"27 Nariel St",
    "sg:city":"Albion",
    "sg:classifiers":[
        {
            "category":"Banks & Credit Unions",
            "subcategory":"Bureau De Change",
            "type":"Services"
        }
    ],
    "sg:phone":"+61 7 3262 4822",
    "sg:postcode":"4010",
    "sg:province":"QLD",
    "sg:tags":[
        "gas",
        "natural",
        "lp",
        "equipment"
    ],
    "wof:name":"Sprint Gas (Aust) Pty Ltd",
    "wof:placetype":"venue"
},
  "geometry": {"coordinates":[153.043823242,-27.439081192],"type":"Point"}
}