{
  "type": "Feature",
  "properties": {
    "iso:country":"AU",
    "sg:address":"24- 26 Winbourne Ave",
    "sg:city":"Brookvale",
    "sg:classifiers":[
        {
            "category":"Autos & Motor Vehicles",
            "subcategory":"Auto Supplies",
            "type":"Retail Goods"
        }
    ],
    "sg:phone":"+61 2 9939 5133",
    "sg:postcode":"2100",
    "sg:province":"NSW",
    "sg:tags":[
        "camper-trailers",
        "caravan",
        "equipment"
    ],
    "wof:name":"Opposite Lock 4WD Accessories",
    "wof:placetype":"venue"
},
  "geometry": {"coordinates":[151.27786254899999,-33.7625389099],"type":"Point"}
}