{
  "type": "Feature",
  "properties": {
    "iso:country":"AU",
    "sg:address":"Maybe St",
    "sg:city":"Bombala",
    "sg:classifiers":[
        {
            "category":"Home & Garden",
            "subcategory":"Carpets & Floor Coverings",
            "type":"Retail Goods"
        }
    ],
    "sg:phone":"+61 2 6458 3265",
    "sg:postcode":"2632",
    "sg:province":"NSW",
    "wof:name":"Spoljaric N",
    "wof:placetype":"venue"
},
  "geometry": {"coordinates":[149.24008178700001,-36.9108772278],"type":"Point"}
}