{
  "type": "Feature",
  "properties": {
    "iso:country":"AU",
    "sg:address":"128a Dangar St",
    "sg:city":"Armidale",
    "sg:classifiers":[
        {
            "category":"Social Services",
            "type":"Services"
        }
    ],
    "sg:phone":"+61 2 6772 8968",
    "sg:postcode":"2350",
    "sg:province":"NSW",
    "sg:tags":[
        "domestic",
        "help"
    ],
    "wof:name":"Armidale & District Home Nursing & Home Help Service",
    "wof:placetype":"venue"
},
  "geometry": {"coordinates":[151.664627075,-30.5148067474],"type":"Point"}
}