{
  "type": "Feature",
  "properties": {
    "addr:full":"1st Floor, 781 Centre Rd Bentleigh East VIC 3165",
    "addr:housenumber":"781",
    "addr:postcode":"3165",
    "addr:street":"Centre Rd",
    "iso:country":"AU",
    "sg:address":"1st Floor, 781 Centre Rd",
    "sg:city":"Bentleigh East",
    "sg:classifiers":[
        {
            "category":"Health Services",
            "subcategory":"Dentist",
            "type":"Services"
        }
    ],
    "sg:phone":"+61 3 9579 5333",
    "sg:postcode":"3165",
    "sg:province":"VIC",
    "wof:name":"Magit Yelena Dr",
    "wof:placetype":"venue"
},
  "geometry": {"coordinates":[145.057983398,-37.9208564758],"type":"Point"}
}