{
  "type": "Feature",
  "properties": {
    "iso:country":"AU",
    "sg:address":"142 Tuckwell Rd",
    "sg:city":"Castle Hill",
    "sg:classifiers":[
        {
            "category":"Health Services",
            "subcategory":"Doctor",
            "type":"Services"
        }
    ],
    "sg:phone":"+61 2 9894 0040",
    "sg:postcode":"2154",
    "sg:province":"NSW",
    "sg:tags":[
        "medical",
        "practitioner"
    ],
    "wof:name":"Bell Peter Dr",
    "wof:placetype":"venue"
},
  "geometry": {"coordinates":[150.99290466299999,-33.7200012207],"type":"Point"}
}