{
  "type": "Feature",
  "properties": {
    "addr:full":"U9/ 30 Railway Tce Merrylands NSW 2160",
    "addr:housenumber":"30",
    "addr:postcode":"2160",
    "addr:street":"U9 /;Railway Tce",
    "iso:country":"AU",
    "sg:address":"U9/ 30 Railway Tce",
    "sg:city":"Merrylands",
    "sg:classifiers":[
        {
            "category":"Building & Trades",
            "subcategory":"Cleaning & Sanitation",
            "type":"Services"
        }
    ],
    "sg:phone":"+61 2 9637 3837",
    "sg:postcode":"2160",
    "sg:province":"NSW",
    "sg:tags":[
        "industrial",
        "commercial",
        "contractor"
    ],
    "wof:name":"High Top Cleaning Servies",
    "wof:placetype":"venue"
},
  "geometry": {"coordinates":[150.99974060100001,-33.8274459839],"type":"Point"}
}