{
  "type": "Feature",
  "properties": {
    "addr:full":"120 Kingston Rd Underwood QLD 4119",
    "addr:housenumber":"120",
    "addr:postcode":"4119",
    "addr:street":"Kingston Rd",
    "iso:country":"AU",
    "sg:address":"120 Kingston Rd",
    "sg:city":"Underwood",
    "sg:classifiers":[
        {
            "category":"Fast Food",
            "type":"Food & Drink"
        }
    ],
    "sg:phone":"+61 7 3808 5322",
    "sg:postcode":"4119",
    "sg:province":"QLD",
    "sg:tags":[
        "away",
        "take"
    ],
    "wof:name":"Double D's Carvery & Takeaway",
    "wof:placetype":"venue"
},
  "geometry": {"coordinates":[153.11567688,-27.6179161072],"type":"Point"}
}