{
  "type": "Feature",
  "properties": {
    "addr:full":"Unit 3, Island Cove 385 Oxley Drv Runaway Bay QLD 4216",
    "addr:housenumber":"385",
    "addr:postcode":"4216",
    "addr:street":"Oxley Drv",
    "iso:country":"AU",
    "sg:address":"Unit 3, Island Cove 385 Oxley Drv",
    "sg:city":"Runaway Bay",
    "sg:classifiers":[
        {
            "category":"Health Services",
            "subcategory":"Doctor",
            "type":"Services"
        }
    ],
    "sg:phone":"+61 7 5563 7500",
    "sg:postcode":"4216",
    "sg:province":"QLD",
    "sg:tags":[
        "nurse",
        "nursing"
    ],
    "wof:name":"Just Better Care",
    "wof:placetype":"venue"
},
  "geometry": {"coordinates":[153.38768005399999,-27.9211483002],"type":"Point"}
}