{
  "type": "Feature",
  "properties": {
    "addr:full":"Darwin Plaza, 41 Smith St Darwin NT 0801",
    "addr:housenumber":"41",
    "addr:postcode":"nt 0801",
    "addr:street":"Smith St",
    "iso:country":"AU",
    "sg:address":"Darwin Plaza, 41 Smith St",
    "sg:city":"Darwin",
    "sg:classifiers":[
        {
            "category":"Building & Trades",
            "subcategory":"Locksmith",
            "type":"Services"
        }
    ],
    "sg:phone":"+61 8 8981 6787",
    "sg:postcode":"0801",
    "sg:province":"NT",
    "sg:tags":[
        "lock"
    ],
    "wof:name":"Mister Minit",
    "wof:placetype":"venue"
},
  "geometry": {"coordinates":[130.84141540499999,-12.462931633],"type":"Point"}
}