{
  "type": "Feature",
  "properties": {
    "addr:full":"15 Douglas St Noble Park VIC 3174",
    "addr:housenumber":"15",
    "addr:postcode":"3174",
    "addr:street":"Douglas St",
    "iso:country":"AU",
    "sg:address":"15 Douglas St",
    "sg:city":"Noble Park",
    "sg:classifiers":[
        {
            "category":"Shopping",
            "subcategory":"Clothing, Apparel, & Fashions",
            "type":"Retail Goods"
        }
    ],
    "sg:phone":"+61 3 9546 8586",
    "sg:postcode":"3174",
    "sg:province":"VIC",
    "sg:tags":[
        "boutique"
    ],
    "wof:name":"Yumi Boutique",
    "wof:placetype":"venue"
},
  "geometry": {"coordinates":[145.17481994600001,-37.9660224915],"type":"Point"}
}