{
  "type": "Feature",
  "properties": {
    "iso:country":"AU",
    "sg:address":"24 Fourth Rd",
    "sg:city":"Armadale",
    "sg:classifiers":[
        {
            "category":"Health Services",
            "subcategory":"Dentist",
            "type":"Services"
        }
    ],
    "sg:phone":"+61 8 9497 9700",
    "sg:postcode":"6112",
    "sg:province":"WA",
    "wof:name":"Armadale Dental Centre",
    "wof:placetype":"venue"
},
  "geometry": {"coordinates":[116.016082764,-32.156162262],"type":"Point"}
}