{
  "type": "Feature",
  "properties": {
    "addr:full":"5 Ferry Rd Ettalong Beach NSW 2257",
    "addr:housenumber":"5",
    "addr:postcode":"2257",
    "addr:street":"Ferry Rd",
    "iso:country":"AU",
    "sg:address":"5 Ferry Rd",
    "sg:city":"Ettalong Beach",
    "sg:classifiers":[
        {
            "category":"Coffee & Tea",
            "type":"Food & Drink"
        }
    ],
    "sg:phone":"+61 2 4341 2866",
    "sg:postcode":"2257",
    "sg:province":"NSW",
    "sg:tags":[
        "kayak",
        "canoe"
    ],
    "wof:name":"Southern Adventures",
    "wof:placetype":"venue"
},
  "geometry": {"coordinates":[151.34223938,-33.5158538818],"type":"Point"}
}