{
  "type": "Feature",
  "properties": {
    "addr:full":"40 Pine Ave Leeton NSW 2705",
    "addr:housenumber":"40",
    "addr:postcode":"2705",
    "addr:street":"Pine Ave",
    "iso:country":"AU",
    "sg:address":"40 Pine Ave",
    "sg:city":"Leeton",
    "sg:classifiers":[
        {
            "category":"Banks & Credit Unions",
            "subcategory":"Financial Services",
            "type":"Services"
        }
    ],
    "sg:phone":"+61 2 6953 3636",
    "sg:postcode":"2705",
    "sg:province":"NSW",
    "sg:tags":[
        "loan",
        "finance",
        "mortgage"
    ],
    "wof:name":"Forrest Financial",
    "wof:placetype":"venue"
},
  "geometry": {"coordinates":[146.40487670900001,-34.5515174866],"type":"Point"}
}