{
  "type": "Feature",
  "properties": {
    "iso:country":"AU",
    "sg:address":"54 Phillips St",
    "sg:city":"Bracken Ridge",
    "sg:classifiers":[
        {
            "category":"Utilities",
            "subcategory":"Electric",
            "type":"Services"
        }
    ],
    "sg:phone":"+61 418 729 418",
    "sg:postcode":"4017",
    "sg:province":"QLD",
    "sg:tags":[
        "electrical",
        "contractor"
    ],
    "wof:name":"Heslop Electrical",
    "wof:placetype":"venue"
},
  "geometry": {"coordinates":[153.034500122,-27.3274154663],"type":"Point"}
}