{
  "type": "Feature",
  "properties": {
    "iso:country":"AU",
    "sg:address":"125 Flockton St",
    "sg:city":"Everton Park",
    "sg:classifiers":[
        {
            "category":"Health Services",
            "subcategory":"Doctor",
            "type":"Services"
        }
    ],
    "sg:phone":"+61 7 3832 3422",
    "sg:postcode":"4053",
    "sg:province":"QLD",
    "sg:tags":[
        "medical",
        "practitioner"
    ],
    "wof:name":"Anning F W",
    "wof:placetype":"venue"
},
  "geometry": {"coordinates":[152.990432739,-27.4060096741],"type":"Point"}
}