{
  "type": "Feature",
  "properties": {
    "addr:full":"125 Flockton St Everton Park QLD 4053",
    "addr:housenumber":"125",
    "addr:postcode":"4053",
    "addr:street":"Flockton St",
    "iso:country":"AU",
    "sg:address":"125 Flockton St",
    "sg:city":"Everton Park",
    "sg:classifiers":[
        {
            "category":"Health Services",
            "subcategory":"Doctor",
            "type":"Services"
        }
    ],
    "sg:phone":"+61 7 3832 3422",
    "sg:postcode":"4053",
    "sg:province":"QLD",
    "sg:tags":[
        "medical",
        "practitioner"
    ],
    "wof:name":"Anning F W",
    "wof:placetype":"venue"
},
  "geometry": {"coordinates":[152.990432739,-27.4060096741],"type":"Point"}
}