{
  "type": "Feature",
  "properties": {
    "iso:country":"AU",
    "sg:address":"57 McLeod St",
    "sg:city":"Cairns",
    "sg:classifiers":[
        {
            "category":"Shopping",
            "subcategory":"Computers & Home Electronics",
            "type":"Retail Goods"
        }
    ],
    "sg:phone":"+61 7 4041 4011",
    "sg:postcode":"4870",
    "sg:province":"QLD",
    "sg:tags":[
        "equipment",
        "multimedia"
    ],
    "wof:name":"MATV Specialists Australia",
    "wof:placetype":"venue"
},
  "geometry": {"coordinates":[145.76919555699999,-16.9205245972],"type":"Point"}
}