{
  "type": "Feature",
  "properties": {
    "iso:country":"AU",
    "sg:address":"2 Grant St",
    "sg:city":"Narrogin",
    "sg:classifiers":[
        {
            "category":"Autos & Motor Vehicles",
            "subcategory":"Auto Supplies",
            "type":"Retail Goods"
        }
    ],
    "sg:phone":"+61 8 9881 6460",
    "sg:postcode":"6312",
    "sg:province":"WA",
    "sg:tags":[
        "accessory"
    ],
    "wof:name":"A to Z Enterprises",
    "wof:placetype":"venue"
},
  "geometry": {"coordinates":[117.180908203,-32.9322853088],"type":"Point"}
}