{
  "type": "Feature",
  "properties": {
    "addr:full":"1 Anderson St South Melbourne VIC 3205",
    "addr:housenumber":"1",
    "addr:postcode":"3205",
    "addr:street":"Anderson St",
    "iso:country":"AU",
    "sg:address":"1 Anderson St",
    "sg:city":"South Melbourne",
    "sg:classifiers":[
        {
            "category":"Professional",
            "subcategory":"Art Services",
            "type":"Services"
        }
    ],
    "sg:phone":"+61 3 9699 8622",
    "sg:postcode":"3205",
    "sg:province":"VIC",
    "sg:tags":[
        "graphic",
        "designer"
    ],
    "wof:name":"X 2",
    "wof:placetype":"venue"
},
  "geometry": {"coordinates":[144.95997600000001,-37.83963],"type":"Point"}
}