{
  "type": "Feature",
  "properties": {
    "iso:country":"AU",
    "sg:address":"7 Princes St",
    "sg:city":"Caulfield East",
    "sg:classifiers":[
        {
            "category":"Health Services",
            "subcategory":"Optometrist",
            "type":"Services"
        }
    ],
    "sg:phone":"+61 3 9903 2500",
    "sg:postcode":"3145",
    "sg:province":"VIC",
    "wof:name":"Weisz Family Optical",
    "wof:placetype":"venue"
},
  "geometry": {"coordinates":[145.04301452600001,-37.8766326904],"type":"Point"}
}