{
  "type": "Feature",
  "properties": {
    "iso:country":"AU",
    "sg:address":"50 Currumbin Creek Rd",
    "sg:city":"Currumbin",
    "sg:classifiers":[
        {
            "category":"Utilities",
            "subcategory":"Telephone",
            "type":"Services"
        }
    ],
    "sg:phone":"+61 7 5598 5438",
    "sg:postcode":"4223",
    "sg:province":"QLD",
    "sg:tags":[
        "equipment",
        "system"
    ],
    "wof:name":"Datavoice Queensland",
    "wof:placetype":"venue"
},
  "geometry": {"coordinates":[153.472564697,-28.1436538696],"type":"Point"}
}