{
  "type": "Feature",
  "properties": {
    "addr:full":"2 Tranquility Pl Maddington WA 6109",
    "addr:housenumber":"2",
    "addr:postcode":"6109",
    "addr:street":"Tranquility Pl",
    "iso:country":"AU",
    "sg:address":"2 Tranquility Pl",
    "sg:city":"Maddington",
    "sg:classifiers":[
        {
            "category":"Building & Trades",
            "subcategory":"Construction",
            "type":"Services"
        }
    ],
    "sg:phone":"+61 407 187 875",
    "sg:postcode":"6109",
    "sg:province":"WA",
    "sg:tags":[
        "home",
        "air conditioning"
    ],
    "wof:name":"Vendair Maintenance",
    "wof:placetype":"venue"
},
  "geometry": {"coordinates":[115.985191345,-32.0596694946],"type":"Point"}
}