{
  "type": "Feature",
  "properties": {
    "addr:full":"Level 2 Forrest Chase Perth WA 6000",
    "addr:postcode":"6000",
    "iso:country":"AU",
    "sg:address":"Level 2 Forrest Chase",
    "sg:city":"Perth",
    "sg:classifiers":[
        {
            "category":"Shopping",
            "type":"Retail Goods"
        }
    ],
    "sg:phone":"+61 8 9325 5613",
    "sg:postcode":"6000",
    "sg:province":"WA",
    "sg:tags":[
        "repair",
        "travel"
    ],
    "wof:name":"Strandbags Pty Limited",
    "wof:placetype":"venue"
},
  "geometry": {"coordinates":[115.85439300500001,-31.9514198303],"type":"Point"}
}