{
  "type": "Feature",
  "properties": {
    "iso:country":"AU",
    "sg:address":"3 Sir William McKell Drv",
    "sg:city":"Pambula",
    "sg:classifiers":[
        {
            "category":"Home & Garden",
            "subcategory":"Garden Supply",
            "type":"Retail Goods"
        }
    ],
    "sg:phone":"+61 2 6495 2257",
    "sg:postcode":"2549",
    "sg:province":"NSW",
    "sg:tags":[
        "landscape"
    ],
    "wof:name":"Grimes Mick",
    "wof:placetype":"venue"
},
  "geometry": {"coordinates":[149.885620117,-36.9338417053],"type":"Point"}
}