{
  "type": "Feature",
  "properties": {
    "iso:country":"AU",
    "sg:address":"264 Port Drv",
    "sg:city":"Broome",
    "sg:classifiers":[
        {
            "category":"Retail",
            "subcategory":"Auto Rental",
            "type":"Services"
        }
    ],
    "sg:phone":"+61 8 9192 2859",
    "sg:postcode":"6725",
    "sg:province":"WA",
    "sg:tags":[
        "car",
        "hire",
        "minibus"
    ],
    "wof:name":"Access Broome Car Rental",
    "wof:placetype":"venue"
},
  "geometry": {"coordinates":[122.677589416,-18.2141704559],"type":"Point"}
}