{
  "type": "Feature",
  "properties": {
    "addr:full":"31 Darwin Rd Campbelltown NSW 2560",
    "addr:housenumber":"31",
    "addr:postcode":"2560",
    "addr:street":"Darwin Rd",
    "iso:country":"AU",
    "sg:address":"31 Darwin Rd",
    "sg:city":"Campbelltown",
    "sg:classifiers":[
        {
            "category":"Wholesale",
            "subcategory":"Construction Materials",
            "type":"Manufacturing & Wholesale Goods"
        }
    ],
    "sg:phone":"+61 1800 684 111",
    "sg:postcode":"2560",
    "sg:province":"NSW",
    "sg:tags":[
        "wholesaler",
        "lighting",
        "mfrs",
        "accessory"
    ],
    "wof:name":"Showers International Pty Ltd",
    "wof:placetype":"venue"
},
  "geometry": {"coordinates":[150.834274292,-34.0686607361],"type":"Point"}
}