{
  "type": "Feature",
  "properties": {
    "addr:full":"12- 14 Rutherford Rd Seaford VIC 3198",
    "addr:housenumber":"14",
    "addr:postcode":"3198",
    "addr:street":"Rutherford Rd",
    "iso:country":"AU",
    "sg:address":"12- 14 Rutherford Rd",
    "sg:city":"Seaford",
    "sg:classifiers":[
        {
            "category":"Retail",
            "subcategory":"Storage",
            "type":"Services"
        }
    ],
    "sg:phone":"+61 3 9775 0515",
    "sg:postcode":"3198",
    "sg:province":"VIC",
    "wof:name":"U-Own Storage",
    "wof:placetype":"venue"
},
  "geometry": {"coordinates":[145.15020751899999,-38.0986938477],"type":"Point"}
}