{
  "type": "Feature",
  "properties": {
    "iso:country":"AU",
    "sg:address":"Coleridge St",
    "sg:city":"Leichhardt",
    "sg:classifiers":[
        {
            "category":"Professional",
            "subcategory":"Art Services",
            "type":"Services"
        }
    ],
    "sg:phone":"+61 2 9564 3824",
    "sg:postcode":"2040",
    "sg:province":"NSW",
    "sg:tags":[
        "interior",
        "decorator"
    ],
    "wof:name":"Leichhardt Framing",
    "wof:placetype":"venue"
},
  "geometry": {"coordinates":[151.16246,-33.880936],"type":"Point"}
}