{
  "type": "Feature",
  "properties": {
    "iso:country":"AU",
    "sg:address":"134 Coleraine Rd",
    "sg:city":"Hamilton",
    "sg:classifiers":[
        {
            "category":"Education",
            "subcategory":"Kindergarten",
            "type":"Public Place"
        }
    ],
    "sg:phone":"+61 3 5572 2740",
    "sg:postcode":"3300",
    "sg:province":"VIC",
    "sg:tags":[
        "pre-schools"
    ],
    "wof:name":"North Hamilton Kindergarten Centre",
    "wof:placetype":"venue"
},
  "geometry": {"coordinates":[142.01316833499999,-37.7355155945],"type":"Point"}
}