{
  "type": "Feature",
  "properties": {
    "iso:country":"AU",
    "sg:address":"1 Bilby Pl",
    "sg:city":"Gosnells",
    "sg:classifiers":[
        {
            "category":"Utilities",
            "subcategory":"Electric",
            "type":"Services"
        }
    ],
    "sg:phone":"+61 8 9490 4859",
    "sg:postcode":"6110",
    "sg:province":"WA",
    "sg:tags":[
        "transformer"
    ],
    "wof:name":"Advanced Transformers Manufacturers",
    "wof:placetype":"venue"
},
  "geometry": {"coordinates":[115.981452942,-32.0830001831],"type":"Point"}
}