{
  "type": "Feature",
  "properties": {
    "iso:country":"AU",
    "sg:address":"73 Waterloo St",
    "sg:city":"Narrabeen",
    "sg:classifiers":[
        {
            "category":"Health Services",
            "subcategory":"Optometrist",
            "type":"Services"
        }
    ],
    "sg:phone":"+61 2 9913 8661",
    "sg:postcode":"2101",
    "sg:province":"NSW",
    "wof:name":"McConaghy D G",
    "wof:placetype":"venue"
},
  "geometry": {"coordinates":[151.297714,-33.712749],"type":"Point"}
}