{
  "type": "Feature",
  "properties": {
    "addr:full":"955 Centre Rd Oakleigh South VIC 3167",
    "addr:housenumber":"955",
    "addr:postcode":"3167",
    "addr:street":"Centre Rd",
    "iso:country":"AU",
    "sg:address":"955 Centre Rd",
    "sg:city":"Oakleigh South",
    "sg:classifiers":[
        {
            "category":"Health Services",
            "subcategory":"Dentist",
            "type":"Services"
        }
    ],
    "sg:phone":"+61 3 9570 5223",
    "sg:postcode":"3167",
    "sg:province":"VIC",
    "wof:name":"Klimowitsky Simon",
    "wof:placetype":"venue"
},
  "geometry": {"coordinates":[145.08338928200001,-37.9241981506],"type":"Point"}
}