{
  "type": "Feature",
  "properties": {
    "iso:country":"AU",
    "sg:address":"5 Trafalgar St",
    "sg:city":"Wodonga",
    "sg:classifiers":[
        {
            "category":"Retail",
            "subcategory":"Auto Repair",
            "type":"Services"
        }
    ],
    "sg:phone":"+61 2 6056 1064",
    "sg:postcode":"3690",
    "sg:province":"NSW",
    "sg:tags":[
        "repairer",
        "motor",
        "engineer"
    ],
    "wof:name":"Bruno's Mechanical Repairs",
    "wof:placetype":"venue"
},
  "geometry": {"coordinates":[146.86306762699999,-36.1133041382],"type":"Point"}
}