{
  "type": "Feature",
  "properties": {
    "iso:country":"AU",
    "sg:address":"Bay 1 & 2/ 43 Lillypool Rd",
    "sg:city":"South Grafton",
    "sg:classifiers":[
        {
            "category":"Wholesale",
            "subcategory":"Farm Supplies",
            "type":"Manufacturing & Wholesale Goods"
        }
    ],
    "sg:phone":"+61 2 6642 7130",
    "sg:postcode":"2460",
    "sg:province":"NSW",
    "sg:tags":[
        "equipment"
    ],
    "wof:name":"Hummelstads",
    "wof:placetype":"venue"
},
  "geometry": {"coordinates":[152.94662475600001,-29.737575531],"type":"Point"}
}