{
  "type": "Feature",
  "properties": {
    "addr:full":"PO Box 1012 Wahroonga NSW 2076",
    "addr:postcode":"2076",
    "iso:country":"AU",
    "sg:address":"PO Box 1012",
    "sg:city":"Wahroonga",
    "sg:classifiers":[
        {
            "category":"Professional",
            "subcategory":"Management & Consulting",
            "type":"Services"
        }
    ],
    "sg:phone":"+61 2 9487 2466",
    "sg:postcode":"2076",
    "sg:province":"NSW",
    "sg:tags":[
        "consultant"
    ],
    "wof:name":"Offshore Marketing Services",
    "wof:placetype":"venue"
},
  "geometry": {"coordinates":[151.117385864,-33.7187194824],"type":"Point"}
}