{
  "type": "Feature",
  "properties": {
    "addr:full":"Shop 5 & 6, 2 Cottesloe Drv Kewarra Beach QLD 4879",
    "addr:housenumber":"shop 5 &;2",
    "addr:postcode":"4879",
    "addr:street":"Cottesloe Drv",
    "iso:country":"AU",
    "sg:address":"Shop 5 & 6, 2 Cottesloe Drv",
    "sg:city":"Kewarra Beach",
    "sg:classifiers":[
        {
            "category":"Shopping",
            "subcategory":"Bicycles & Sporting Goods",
            "type":"Retail Goods"
        }
    ],
    "sg:phone":"+61 7 4057 6477",
    "sg:postcode":"4879",
    "sg:province":"QLD",
    "sg:tags":[
        "chemical",
        "equipment",
        "pool",
        "swimming"
    ],
    "wof:name":"Beaches Pool Supplies",
    "wof:placetype":"venue"
},
  "geometry": {"coordinates":[145.67869567899999,-16.7818126678],"type":"Point"}
}