{
  "type": "Feature",
  "properties": {
    "addr:full":"455 Melbourne Rd Newport VIC 3015",
    "addr:housenumber":"455",
    "addr:postcode":"3015",
    "addr:street":"Melbourne Rd",
    "iso:country":"AU",
    "sg:address":"455 Melbourne Rd",
    "sg:city":"Newport",
    "sg:classifiers":[
        {
            "category":"Retail",
            "subcategory":"Auto Repair",
            "type":"Services"
        }
    ],
    "sg:phone":"+61 3 9391 1416",
    "sg:postcode":"3015",
    "sg:province":"VIC",
    "sg:tags":[
        "repairer",
        "motor",
        "engineer"
    ],
    "wof:name":"V.J.S. Auto Repairs Pty Ltd",
    "wof:placetype":"venue"
},
  "geometry": {"coordinates":[144.88247680699999,-37.840423584],"type":"Point"}
}