{
  "type": "Feature",
  "properties": {
    "addr:full":"21 Dendron St Shailer Park QLD 4128",
    "addr:housenumber":"21",
    "addr:postcode":"4128",
    "addr:street":"Dendron St",
    "iso:country":"AU",
    "sg:address":"21 Dendron St",
    "sg:city":"Shailer Park",
    "sg:classifiers":[
        {
            "category":"Building & Trades",
            "subcategory":"Construction",
            "type":"Services"
        }
    ],
    "sg:phone":"+61 412 154 506",
    "sg:postcode":"4128",
    "sg:province":"QLD",
    "sg:tags":[
        "polishing",
        "sanding",
        "floor"
    ],
    "wof:name":"Boards To Sand Pty Ltd",
    "wof:placetype":"venue"
},
  "geometry": {"coordinates":[153.17489624000001,-27.6539573669],"type":"Point"}
}