{
  "type": "Feature",
  "properties": {
    "iso:country":"AU",
    "sg:address":"Shp L32 Altona Gate Shopng Ctr Miller St",
    "sg:city":"Altona",
    "sg:classifiers":[
        {
            "category":"Shopping",
            "subcategory":"Computers & Home Electronics",
            "type":"Retail Goods"
        }
    ],
    "sg:phone":"+61 3 9314 6611",
    "sg:postcode":"3018",
    "sg:province":"VIC",
    "sg:tags":[
        "small",
        "equipment",
        "business"
    ],
    "wof:name":"Dick Smith Electronics",
    "wof:placetype":"venue"
},
  "geometry": {"coordinates":[144.845245361,-37.8656539917],"type":"Point"}
}