{
  "type": "Feature",
  "properties": {
    "addr:full":"30 Forest Rd Ferntree Gully VIC 3156",
    "addr:housenumber":"30",
    "addr:postcode":"3156",
    "addr:street":"Forest Rd",
    "iso:country":"AU",
    "sg:address":"30 Forest Rd",
    "sg:city":"Ferntree Gully",
    "sg:classifiers":[
        {
            "category":"Social Services",
            "subcategory":"Retirement Home",
            "type":"Services"
        }
    ],
    "sg:phone":"+61 3 9752 2170",
    "sg:postcode":"3156",
    "sg:province":"VIC",
    "sg:tags":[
        "accommodation",
        "special"
    ],
    "wof:name":"Ferntree Gardens Special Accommodation Home",
    "wof:placetype":"venue"
},
  "geometry": {"coordinates":[145.297164917,-37.8845214844],"type":"Point"}
}