{
  "type": "Feature",
  "properties": {
    "iso:country":"AU",
    "sg:address":"2 Lorama Pl",
    "sg:city":"Kuraby",
    "sg:classifiers":[
        {
            "category":"Building & Trades",
            "subcategory":"Construction",
            "type":"Services"
        }
    ],
    "sg:phone":"+61 7 3841 8922",
    "sg:postcode":"4112",
    "sg:province":"QLD",
    "sg:tags":[
        "home",
        "air conditioning"
    ],
    "wof:name":"Tayair Airconditioning Pty Ltd",
    "wof:placetype":"venue"
},
  "geometry": {"coordinates":[153.099700928,-27.5978393555],"type":"Point"}
}