{
  "type": "Feature",
  "properties": {
    "addr:full":"9 Rawson St Lidcombe NSW 2141",
    "addr:housenumber":"9",
    "addr:postcode":"2141",
    "addr:street":"Rawson St",
    "iso:country":"AU",
    "sg:address":"9 Rawson St",
    "sg:city":"Lidcombe",
    "sg:classifiers":[
        {
            "category":"Professional",
            "subcategory":"Engineering",
            "type":"Services"
        }
    ],
    "sg:phone":"+61 425 300 059",
    "sg:postcode":"2141",
    "sg:province":"NSW",
    "sg:tags":[
        "civil",
        "engineer"
    ],
    "wof:name":"Aztec Engineers Pty Ltd",
    "wof:placetype":"venue"
},
  "geometry": {"coordinates":[151.05099487300001,-33.8606948853],"type":"Point"}
}