{
  "type": "Feature",
  "properties": {
    "addr:full":"39 Murray St Hobart TAS 7000",
    "addr:housenumber":"39",
    "addr:postcode":"7000",
    "addr:street":"Murray St",
    "iso:country":"AU",
    "sg:address":"39 Murray St",
    "sg:city":"Hobart",
    "sg:classifiers":[
        {
            "category":"Insurance",
            "subcategory":"Hazard Insurance",
            "type":"Services"
        }
    ],
    "sg:phone":"+61 3 6235 8333",
    "sg:postcode":"7000",
    "sg:province":"TAS",
    "sg:tags":[
        "fire",
        "accident",
        "marine"
    ],
    "wof:name":"Royal & Sun Alliance Insurance Australia Limited",
    "wof:placetype":"venue"
},
  "geometry": {"coordinates":[147.327194214,-42.883190155],"type":"Point"}
}