{
  "type": "Feature",
  "properties": {
    "addr:full":"Suite 2, Level 1/ 44-46 Marco Ave Revesby NSW 2212",
    "addr:housenumber":"/ 44-46",
    "addr:postcode":"2212",
    "addr:street":"Marco Ave",
    "iso:country":"AU",
    "sg:address":"Suite 2, Level 1/ 44-46 Marco Ave",
    "sg:city":"Revesby",
    "sg:classifiers":[
        {
            "category":"Real Estate",
            "subcategory":"Architect",
            "type":"Services"
        }
    ],
    "sg:phone":"+61 2 9785 5920",
    "sg:postcode":"2212",
    "sg:province":"NSW",
    "sg:tags":[
        "building",
        "designer"
    ],
    "wof:name":"Artmade Architectural Pty Ltd",
    "wof:placetype":"venue"
},
  "geometry": {"coordinates":[151.01577800000001,-33.951637],"type":"Point"}
}