{
  "type": "Feature",
  "properties": {
    "iso:country":"AU",
    "sg:address":"Cnr Hooper & Erin Sts",
    "sg:city":"Wilsonton",
    "sg:classifiers":[
        {
            "category":"Autos & Motor Vehicles",
            "subcategory":"Fuel & Gas Station",
            "type":"Retail Goods"
        }
    ],
    "sg:phone":"+61 7 4633 0168",
    "sg:postcode":"4350",
    "sg:province":"QLD",
    "wof:name":"Woolworths Petrol",
    "wof:placetype":"venue"
},
  "geometry": {"coordinates":[151.924927,-27.542982],"type":"Point"}
}