{
  "type": "Feature",
  "properties": {
    "iso:country":"AU",
    "sg:address":"2 Mansfield St",
    "sg:city":"Thornbury",
    "sg:classifiers":[
        {
            "category":"Education",
            "subcategory":"School",
            "type":"Public Place"
        }
    ],
    "sg:phone":"+61 3 9484 5333",
    "sg:postcode":"3071",
    "sg:province":"VIC",
    "sg:tags":[
        "co-educational"
    ],
    "wof:name":"St Mary's Primary",
    "wof:placetype":"venue"
},
  "geometry": {"coordinates":[145.00115966800001,-37.7565345764],"type":"Point"}
}