{
  "type": "Feature",
  "properties": {
    "addr:full":"Range St Barraba NSW 2347",
    "addr:postcode":"2347",
    "addr:street":"Range St",
    "iso:country":"AU",
    "sg:address":"Range St",
    "sg:city":"Barraba",
    "sg:classifiers":[
        {
            "category":"Autos & Motor Vehicles",
            "subcategory":"Auto Supplies",
            "type":"Retail Goods"
        }
    ],
    "sg:phone":"+61 2 6782 1622",
    "sg:postcode":"2347",
    "sg:province":"NSW",
    "sg:tags":[
        "oil",
        "spirit"
    ],
    "wof:name":"BP Oil",
    "wof:placetype":"venue"
},
  "geometry": {"coordinates":[150.60633850100001,-30.3920173645],"type":"Point"}
}