{
  "type": "Feature",
  "properties": {
    "iso:country":"AU",
    "sg:address":"21 Wiltshire St",
    "sg:city":"Salisbury",
    "sg:classifiers":[
        {
            "category":"Personal",
            "subcategory":"Massage",
            "type":"Services"
        }
    ],
    "sg:phone":"+61 8 8281 9711",
    "sg:postcode":"5108",
    "sg:province":"SA",
    "sg:tags":[
        "therapy"
    ],
    "wof:name":"Australian Health Education Centres",
    "wof:placetype":"venue"
},
  "geometry": {"coordinates":[138.6456604,-34.7633895874],"type":"Point"}
}