{
  "type": "Feature",
  "properties": {
    "addr:full":"Unit 2, 21- 23 Princes Hwy Engadine NSW 2233",
    "addr:housenumber":"21 23",
    "addr:postcode":"2233",
    "addr:street":"Princes Hwy",
    "iso:country":"AU",
    "sg:address":"Unit 2, 21- 23 Princes Hwy",
    "sg:city":"Engadine",
    "sg:classifiers":[
        {
            "category":"Retail",
            "subcategory":"Auto Repair",
            "type":"Services"
        }
    ],
    "sg:phone":"+61 2 9520 2175",
    "sg:postcode":"2233",
    "sg:province":"NSW",
    "sg:tags":[
        "clutch",
        "brake"
    ],
    "wof:name":"Engadine Automatic Transmissions",
    "wof:placetype":"venue"
},
  "geometry": {"coordinates":[150.99838256800001,-34.0964241028],"type":"Point"}
}