{
  "type": "Feature",
  "properties": {
    "addr:full":"2 Kotara Pl Kotara NSW 2289",
    "addr:housenumber":"2",
    "addr:postcode":"2289",
    "addr:street":"Kotara Pl",
    "iso:country":"AU",
    "sg:address":"2 Kotara Pl",
    "sg:city":"Kotara",
    "sg:classifiers":[
        {
            "category":"Building & Trades",
            "subcategory":"Cleaning & Sanitation",
            "type":"Services"
        }
    ],
    "sg:phone":"+61 2 4952 7211",
    "sg:postcode":"2289",
    "sg:province":"NSW",
    "sg:tags":[
        "abrasive",
        "blasting"
    ],
    "wof:name":"Marine & Industrial Coatings Pty Ltd",
    "wof:placetype":"venue"
},
  "geometry": {"coordinates":[151.699386597,-32.940158844],"type":"Point"}
}