{
  "type": "Feature",
  "properties": {
    "addr:full":"11 Nightingale St Mt Gravatt QLD 4122",
    "addr:housenumber":"11",
    "addr:postcode":"4122",
    "addr:street":"Nightingale St",
    "iso:country":"AU",
    "sg:address":"11 Nightingale St",
    "sg:city":"Mt Gravatt",
    "sg:classifiers":[
        {
            "category":"Communications",
            "type":"Services"
        }
    ],
    "sg:phone":"+61 7 3849 2860",
    "sg:postcode":"4122",
    "sg:province":"QLD",
    "sg:tags":[
        "public",
        "system",
        "address"
    ],
    "wof:name":"Seismic Sounds P.A. Hire",
    "wof:placetype":"venue"
},
  "geometry": {"coordinates":[153.087600708,-27.5344047546],"type":"Point"}
}