{
  "type": "Feature",
  "properties": {
    "addr:full":"220 Safety Bay Rd Safety Bay WA 6169",
    "addr:postcode":"6169",
    "addr:street":"Safety Bay Rd",
    "iso:country":"AU",
    "sg:address":"220 Safety Bay Rd",
    "sg:city":"Safety Bay",
    "sg:classifiers":[
        {
            "category":"Banks & Credit Unions",
            "subcategory":"Financial Services",
            "type":"Services"
        }
    ],
    "sg:phone":"+61 8 9591 2977",
    "sg:postcode":"6169",
    "sg:province":"WA",
    "sg:tags":[
        "settlement",
        "nt",
        "agent",
        "wa"
    ],
    "wof:name":"Oceanside Settlements",
    "wof:placetype":"venue"
},
  "geometry": {"coordinates":[115.711304,-32.302799],"type":"Point"}
}