{
  "type": "Feature",
  "properties": {
    "iso:country":"AU",
    "sg:address":"1210 Logan Rd",
    "sg:city":"Holland Park",
    "sg:classifiers":[
        {
            "category":"Home & Garden",
            "subcategory":"Building Materials",
            "type":"Retail Goods"
        }
    ],
    "sg:phone":"+61 7 3343 7499",
    "sg:postcode":"4121",
    "sg:province":"QLD",
    "sg:tags":[
        "ventilating",
        "equipment",
        "system"
    ],
    "sg:website":"http://www.cardiffair.com.au",
    "wof:name":"Cardiff Air Control Systems",
    "wof:placetype":"venue"
},
  "geometry": {"coordinates":[153.060546875,-27.5185947418],"type":"Point"}
}