{
  "type": "Feature",
  "properties": {
    "addr:full":"45 Charles St Coburg North VIC 3058",
    "addr:housenumber":"45",
    "addr:postcode":"3058",
    "addr:street":"Charles St",
    "iso:country":"AU",
    "sg:address":"45 Charles St",
    "sg:city":"Coburg North",
    "sg:classifiers":[
        {
            "category":"Retail",
            "subcategory":"Auto Repair",
            "type":"Services"
        }
    ],
    "sg:phone":"+61 3 9354 2962",
    "sg:postcode":"3058",
    "sg:province":"VIC",
    "sg:tags":[
        "repairer",
        "motor",
        "engineer"
    ],
    "wof:name":"Prestige Auto Venue",
    "wof:placetype":"venue"
},
  "geometry": {"coordinates":[144.955368042,-37.7305450439],"type":"Point"}
}