{
  "type": "Feature",
  "properties": {
    "iso:country":"AU",
    "sg:address":"31 Fox St",
    "sg:city":"Wynnum",
    "sg:classifiers":[
        {
            "category":"Autos & Motor Vehicles",
            "subcategory":"Boat Sales",
            "type":"Retail Goods"
        }
    ],
    "sg:phone":"+61 7 3396 9777",
    "sg:postcode":"4178",
    "sg:province":"QLD",
    "sg:tags":[
        "yacht"
    ],
    "wof:name":"Cruise Craft Fibre Glass Boats",
    "wof:placetype":"venue"
},
  "geometry": {"coordinates":[153.17251586899999,-27.4373016357],"type":"Point"}
}