{
  "type": "Feature",
  "properties": {
    "addr:full":"Cnr Sibley & Kianawah Rds Lindum QLD 4178",
    "addr:postcode":"4178",
    "addr:street":"Cnr",
    "iso:country":"AU",
    "sg:address":"Cnr Sibley & Kianawah Rds",
    "sg:city":"Lindum",
    "sg:classifiers":[
        {
            "category":"Autos & Motor Vehicles",
            "subcategory":"Fuel & Gas Station",
            "type":"Retail Goods"
        }
    ],
    "sg:phone":"+61 7 3396 3291",
    "sg:postcode":"4178",
    "sg:province":"QLD",
    "wof:name":"Neumann Petroleum",
    "wof:placetype":"venue"
},
  "geometry": {"coordinates":[153.14422607399999,-27.4427146912],"type":"Point"}
}