{
  "type": "Feature",
  "properties": {
    "addr:full":"17 Dobney Ave Wagga Wagga NSW 2650",
    "addr:housenumber":"17",
    "addr:postcode":"2650",
    "addr:street":"Dobney Ave",
    "iso:country":"AU",
    "sg:address":"17 Dobney Ave",
    "sg:city":"Wagga Wagga",
    "sg:classifiers":[
        {
            "category":"Retail",
            "subcategory":"Auto Repair",
            "type":"Services"
        }
    ],
    "sg:phone":"+61 2 6925 1030",
    "sg:postcode":"2650",
    "sg:province":"NSW",
    "sg:tags":[
        "wheel",
        "balancing",
        "alignment"
    ],
    "wof:name":"Tyreworld",
    "wof:placetype":"venue"
},
  "geometry": {"coordinates":[147.34808349599999,-35.1173782349],"type":"Point"}
}