{
  "type": "Feature",
  "properties": {
    "addr:full":"Cnr Keen & Zadoc Sts Lismore NSW 2480",
    "addr:postcode":"2480",
    "addr:street":"Cnr",
    "iso:country":"AU",
    "sg:address":"Cnr Keen & Zadoc Sts",
    "sg:city":"Lismore",
    "sg:classifiers":[
        {
            "category":"Cinema",
            "subcategory":"Movie Theater",
            "type":"Entertainment"
        }
    ],
    "sg:phone":"+61 2 6622 4350",
    "sg:postcode":"2480",
    "sg:province":"NSW",
    "wof:name":"Birch Carroll & Coyle Cinemas",
    "wof:placetype":"venue"
},
  "geometry": {"coordinates":[153.28054809599999,-28.8059978485],"type":"Point"}
}