{
  "type": "Feature",
  "properties": {
    "iso:country":"AU",
    "sg:address":"Unit 1/ 18 Anvil Rd",
    "sg:city":"Seven Hills",
    "sg:classifiers":[
        {
            "category":"Utilities",
            "subcategory":"Electric",
            "type":"Services"
        }
    ],
    "sg:phone":"+61 2 9838 7744",
    "sg:postcode":"2147",
    "sg:province":"NSW",
    "sg:tags":[
        "electrical",
        "contractor"
    ],
    "wof:name":"Kerfoot Electrics Pty Ltd",
    "wof:placetype":"venue"
},
  "geometry": {"coordinates":[150.95806884800001,-33.7786216736],"type":"Point"}
}