{
  "type": "Feature",
  "properties": {
    "addr:full":"245 Auburn St Goulburn NSW 2580",
    "addr:housenumber":"245",
    "addr:postcode":"2580",
    "addr:street":"Auburn St",
    "iso:country":"AU",
    "sg:address":"245 Auburn St",
    "sg:city":"Goulburn",
    "sg:classifiers":[
        {
            "category":"Industrial Area",
            "type":"Public Place"
        }
    ],
    "sg:phone":"+61 2 4821 9466",
    "sg:postcode":"2580",
    "sg:province":"NSW",
    "sg:tags":[
        "protective",
        "clothing"
    ],
    "wof:name":"Goulburn Country & Workwear",
    "wof:placetype":"venue"
},
  "geometry": {"coordinates":[149.72108459500001,-34.7516708374],"type":"Point"}
}