{
  "type": "Feature",
  "properties": {
    "addr:full":"280 Beerburrum Rd Caboolture QLD 4510",
    "addr:housenumber":"280",
    "addr:postcode":"4510",
    "addr:street":"Beerburrum Rd",
    "iso:country":"AU",
    "sg:address":"280 Beerburrum Rd",
    "sg:city":"Caboolture",
    "sg:classifiers":[
        {
            "category":"Communications",
            "subcategory":"News Services",
            "type":"Services"
        }
    ],
    "sg:phone":"+61 7 5495 4581",
    "sg:postcode":"4510",
    "sg:province":"QLD",
    "sg:tags":[
        "information",
        "tourist",
        "attractions"
    ],
    "wof:name":"The Caboolture Historical Society Inc",
    "wof:placetype":"venue"
},
  "geometry": {"coordinates":[152.948013,-27.054649],"type":"Point"}
}