{
  "type": "Feature",
  "properties": {
    "iso:country":"AU",
    "sg:address":"3 Lock Crt",
    "sg:city":"Sunbury",
    "sg:classifiers":[
        {
            "category":"Building & Trades",
            "subcategory":"Cleaning & Sanitation",
            "type":"Services"
        }
    ],
    "sg:phone":"+61 413 182 977",
    "sg:postcode":"3429",
    "sg:province":"VIC",
    "sg:tags":[
        "duct"
    ],
    "wof:name":"Air Purification Services",
    "wof:placetype":"venue"
},
  "geometry": {"coordinates":[144.73275756800001,-37.5605316162],"type":"Point"}
}