{
  "type": "Feature",
  "properties": {
    "iso:country":"AU",
    "sg:address":"Unit 3/ 101 Spencer St",
    "sg:city":"Bunbury",
    "sg:classifiers":[
        {
            "category":"Organizations",
            "subcategory":"Labor Organization",
            "type":"Services"
        }
    ],
    "sg:phone":"+61 8 9721 7933",
    "sg:postcode":"6230",
    "sg:province":"WA",
    "sg:tags":[
        "union"
    ],
    "wof:name":"Australian Manufacturing Workers Union",
    "wof:placetype":"venue"
},
  "geometry": {"coordinates":[115.641571,-33.346577],"type":"Point"}
}