{
  "type": "Feature",
  "properties": {
    "iso:country":"AU",
    "sg:address":"1/ 2 Musgrave Rd",
    "sg:city":"Coopers Plains",
    "sg:classifiers":[
        {
            "category":"Building & Trades",
            "subcategory":"Construction",
            "type":"Services"
        }
    ],
    "sg:phone":"+61 7 3830 0300",
    "sg:postcode":"4108",
    "sg:province":"QLD",
    "sg:tags":[
        "renovation",
        "alterations",
        "extension",
        "contractor"
    ],
    "wof:name":"Brisbane Roof Restorations",
    "wof:placetype":"venue"
},
  "geometry": {"coordinates":[153.02206420900001,-27.560541153],"type":"Point"}
}