{
  "type": "Feature",
  "properties": {
    "iso:country":"AU",
    "sg:address":"17 Harris Rd",
    "sg:city":"Underwood",
    "sg:classifiers":[
        {
            "category":"Building & Trades",
            "subcategory":"Construction",
            "type":"Services"
        }
    ],
    "sg:phone":"+61 412 610 420",
    "sg:postcode":"4119",
    "sg:province":"QLD",
    "sg:tags":[
        "plasterboard",
        "plasterer",
        "fixer"
    ],
    "wof:name":"Rochedale Plasterers",
    "wof:placetype":"venue"
},
  "geometry": {"coordinates":[153.11163330100001,-27.5977039337],"type":"Point"}
}