{
  "type": "Feature",
  "properties": {
    "iso:country":"AU",
    "sg:address":"31 Forsythe Pde",
    "sg:city":"Black Hill",
    "sg:classifiers":[
        {
            "category":"Building & Trades",
            "subcategory":"Plumbing",
            "type":"Services"
        }
    ],
    "sg:phone":"+61 2 4966 0540",
    "sg:postcode":"2322",
    "sg:province":"NSW",
    "sg:tags":[
        "plumber",
        "gasfitters"
    ],
    "wof:name":"Mansley Russell J",
    "wof:placetype":"venue"
},
  "geometry": {"coordinates":[151.638214111,-32.8301048279],"type":"Point"}
}