{
  "type": "Feature",
  "properties": {
    "addr:full":"Cnr Park Ave & Gordon St Coffs Harbour NSW 2450",
    "addr:postcode":"2450",
    "addr:street":"Ave;St",
    "iso:country":"AU",
    "sg:address":"Cnr Park Ave & Gordon St",
    "sg:city":"Coffs Harbour",
    "sg:classifiers":[
        {
            "category":"Food & Beverages",
            "subcategory":"Liquor & Beverages",
            "type":"Retail Goods"
        }
    ],
    "sg:phone":"+61 2 6652 2948",
    "sg:postcode":"2450",
    "sg:province":"NSW",
    "sg:tags":[
        "store"
    ],
    "wof:name":"Liquorland",
    "wof:placetype":"venue"
},
  "geometry": {"coordinates":[153.115936,-30.29847],"type":"Point"}
}