{
  "type": "Feature",
  "properties": {
    "iso:country":"AU",
    "sg:address":"208 Lyons Rd",
    "sg:city":"Five Dock",
    "sg:classifiers":[
        {
            "category":"Health Services",
            "subcategory":"Clinic",
            "type":"Services"
        }
    ],
    "sg:phone":"+61 2 9712 2914",
    "sg:postcode":"2046",
    "sg:province":"NSW",
    "sg:tags":[
        "aromatherapy"
    ],
    "wof:name":"Drummoyne Remedial Therapy",
    "wof:placetype":"venue"
},
  "geometry": {"coordinates":[151.14541600000001,-33.856918],"type":"Point"}
}