{
  "type": "Feature",
  "properties": {
    "iso:country":"AU",
    "sg:address":"47 Sealand Rd",
    "sg:city":"Fishing Point",
    "sg:classifiers":[
        {
            "category":"Education",
            "subcategory":"Music School",
            "type":"Public Place"
        }
    ],
    "sg:phone":"+61 2 4975 1602",
    "sg:postcode":"2283",
    "sg:province":"NSW",
    "sg:tags":[
        "choir",
        "bands",
        "orchestra"
    ],
    "wof:name":"Hunter Regional Band Association",
    "wof:placetype":"venue"
},
  "geometry": {"coordinates":[151.59454345699999,-33.0541191101],"type":"Point"}
}