{
  "type": "Feature",
  "properties": {
    "iso:country":"AU",
    "sg:address":"47 Killara Rd",
    "sg:city":"Campbellfield",
    "sg:classifiers":[
        {
            "category":"Retail",
            "subcategory":"Laundry & Dry Cleaning",
            "type":"Services"
        }
    ],
    "sg:phone":"+61 3 9357 0404",
    "sg:postcode":"3061",
    "sg:province":"VIC",
    "sg:tags":[
        "cloth",
        "supply"
    ],
    "wof:name":"Smiths Rags",
    "wof:placetype":"venue"
},
  "geometry": {"coordinates":[144.964401245,-37.6645240784],"type":"Point"}
}