{
  "type": "Feature",
  "properties": {
    "iso:country":"AU",
    "sg:address":"111 Junction St",
    "sg:city":"Nowra",
    "sg:classifiers":[
        {
            "category":"Fast Food",
            "type":"Food & Drink"
        }
    ],
    "sg:phone":"+61 2 4421 7504",
    "sg:postcode":"2541",
    "sg:province":"NSW",
    "sg:tags":[
        "away",
        "take"
    ],
    "wof:name":"Oasis The Take Away Foods",
    "wof:placetype":"venue"
},
  "geometry": {"coordinates":[150.60218810999999,-34.8743591309],"type":"Point"}
}