{
  "type": "Feature",
  "properties": {
    "addr:full":"Para Institute Of TAFE Woodford Rd Elizabeth SA 5112",
    "addr:postcode":"5112",
    "addr:street":"Woodford Rd",
    "iso:country":"AU",
    "sg:address":"Para Institute Of TAFE Woodford Rd",
    "sg:city":"Elizabeth",
    "sg:classifiers":[
        {
            "category":"Education",
            "subcategory":"Vocational School",
            "type":"Public Place"
        }
    ],
    "sg:phone":"+61 8 8207 9774",
    "sg:postcode":"5112",
    "sg:province":"SA",
    "sg:tags":[
        "beauty"
    ],
    "wof:name":"Advanced Academy Of Hair & Beauty The",
    "wof:placetype":"venue"
},
  "geometry": {"coordinates":[138.67036438,-34.7136764526],"type":"Point"}
}