{
  "type": "Feature",
  "properties": {
    "addr:full":"U1/ 111 Wicks Rd North Ryde NSW 2113",
    "addr:housenumber":"111",
    "addr:postcode":"2113",
    "addr:street":"U1 /;Wicks Rd",
    "iso:country":"AU",
    "sg:address":"U1/ 111 Wicks Rd",
    "sg:city":"North Ryde",
    "sg:classifiers":[
        {
            "category":"Travel",
            "subcategory":"Travel Agent",
            "type":"Entertainment"
        }
    ],
    "sg:phone":"+61 2 9888 5555",
    "sg:postcode":"2113",
    "sg:province":"NSW",
    "sg:tags":[
        "consultant"
    ],
    "wof:name":"Donna Barlow Travel Pty Ltd",
    "wof:placetype":"venue"
},
  "geometry": {"coordinates":[151.128662109,-33.791343689],"type":"Point"}
}