{
  "type": "Feature",
  "properties": {
    "addr:full":"8 Maxted St Bunbury WA 6230",
    "addr:housenumber":"8",
    "addr:postcode":"6230",
    "addr:street":"Maxted St",
    "iso:country":"AU",
    "sg:address":"8 Maxted St",
    "sg:city":"Bunbury",
    "sg:classifiers":[
        {
            "category":"Home & Garden",
            "subcategory":"Building Materials",
            "type":"Retail Goods"
        }
    ],
    "sg:phone":"+61 8 9725 6511",
    "sg:postcode":"6230",
    "sg:province":"WA",
    "sg:tags":[
        "insulation"
    ],
    "wof:name":"Thermo Sealed Batts",
    "wof:placetype":"venue"
},
  "geometry": {"coordinates":[115.671333,-33.365757],"type":"Point"}
}