{
  "type": "Feature",
  "properties": {
    "addr:full":"Suite 301/ 45 Lime St Sydney NSW 2000",
    "addr:housenumber":"/ 45",
    "addr:postcode":"2000",
    "addr:street":"Lime St",
    "iso:country":"AU",
    "sg:address":"Suite 301/ 45 Lime St",
    "sg:city":"Sydney",
    "sg:classifiers":[
        {
            "category":"Real Estate",
            "subcategory":"Real Estate Agent",
            "type":"Services"
        }
    ],
    "sg:phone":"+61 2 9299 2745",
    "sg:postcode":"2000",
    "sg:province":"NSW",
    "wof:name":"propertylistings.com.au",
    "wof:placetype":"venue"
},
  "geometry": {"coordinates":[151.20184326200001,-33.8682746887],"type":"Point"}
}