{
  "type": "Feature",
  "properties": {
    "addr:full":"30 Waratah St Ermington NSW 2115",
    "addr:housenumber":"30",
    "addr:postcode":"2115",
    "addr:street":"Waratah St",
    "iso:country":"AU",
    "sg:address":"30 Waratah St",
    "sg:city":"Ermington",
    "sg:classifiers":[
        {
            "category":"Wholesale",
            "subcategory":"Machinery & Supplies",
            "type":"Manufacturing & Wholesale Goods"
        }
    ],
    "sg:phone":"+61 2 9858 0190",
    "sg:postcode":"2115",
    "sg:province":"NSW",
    "sg:tags":[
        "equipment",
        "laboratory"
    ],
    "wof:name":"Dynaflow",
    "wof:placetype":"venue"
},
  "geometry": {"coordinates":[151.070770264,-33.8152732849],"type":"Point"}
}