{
  "type": "Feature",
  "properties": {
    "iso:country":"AU",
    "sg:address":"Hospital Rd",
    "sg:city":"Rosebery",
    "sg:classifiers":[
        {
            "category":"Health Services",
            "subcategory":"Doctor",
            "type":"Services"
        }
    ],
    "sg:phone":"+61 3 6473 1132",
    "sg:postcode":"7470",
    "sg:province":"TAS",
    "sg:tags":[
        "medical",
        "practitioner"
    ],
    "wof:name":"Oyewopo P",
    "wof:placetype":"venue"
},
  "geometry": {"coordinates":[145.54302978499999,-41.7765541077],"type":"Point"}
}