{
  "type": "Feature",
  "properties": {
    "iso:country":"AU",
    "sg:address":"Parkside Plaza, Wandella Rd",
    "sg:city":"Miranda",
    "sg:classifiers":[
        {
            "category":"Shopping",
            "subcategory":"Pawn Shop",
            "type":"Retail Goods"
        }
    ],
    "sg:phone":"+61 2 9526 2366",
    "sg:postcode":"2228",
    "sg:province":"NSW",
    "sg:tags":[
        "pawnbroker"
    ],
    "wof:name":"Cashwise",
    "wof:placetype":"venue"
},
  "geometry": {"coordinates":[151.102493286,-34.033908844],"type":"Point"}
}