{
  "type": "Feature",
  "properties": {
    "addr:full":"Shed 2, 241 Toombul Rd Northgate QLD 4013",
    "addr:housenumber":"2",
    "addr:postcode":"241;4013",
    "addr:street":"Toombul Rd",
    "iso:country":"AU",
    "sg:address":"Shed 2, 241 Toombul Rd",
    "sg:city":"Northgate",
    "sg:classifiers":[
        {
            "category":"Wholesale",
            "subcategory":"Auto Parts",
            "type":"Manufacturing & Wholesale Goods"
        }
    ],
    "sg:phone":"+61 7 3266 4688",
    "sg:postcode":"4013",
    "sg:province":"QLD",
    "sg:tags":[
        "recyclers"
    ],
    "wof:name":"A European Auto Dismantlers",
    "wof:placetype":"venue"
},
  "geometry": {"coordinates":[153.07347106899999,-27.3943023682],"type":"Point"}
}