{
  "type": "Feature",
  "properties": {
    "addr:full":"6 Murdock St Clayton South VIC 3169",
    "addr:housenumber":"6",
    "addr:postcode":"3169",
    "addr:street":"Murdock St",
    "iso:country":"AU",
    "sg:address":"6 Murdock St",
    "sg:city":"Clayton South",
    "sg:classifiers":[
        {
            "category":"Banks & Credit Unions",
            "subcategory":"Investment Brokerage",
            "type":"Services"
        }
    ],
    "sg:phone":"+61 3 9544 9220",
    "sg:postcode":"3169",
    "sg:province":"VIC",
    "sg:tags":[
        "paint",
        "supply",
        "removal"
    ],
    "wof:name":"Southern Paint Stripping",
    "wof:placetype":"venue"
},
  "geometry": {"coordinates":[145.11859130900001,-37.9337539673],"type":"Point"}
}