{
  "type": "Feature",
  "properties": {
    "addr:full":"10 Rudder Pl Kambah ACT 2902",
    "addr:housenumber":"10",
    "addr:postcode":"2902",
    "addr:street":"Rudder Pl",
    "iso:country":"AU",
    "sg:address":"10 Rudder Pl",
    "sg:city":"Kambah",
    "sg:classifiers":[
        {
            "category":"Banks & Credit Unions",
            "subcategory":"Investment Brokerage",
            "type":"Services"
        }
    ],
    "sg:phone":"+61 2 6161 5500",
    "sg:postcode":"2902",
    "sg:province":"ACT",
    "sg:tags":[
        "management",
        "property"
    ],
    "wof:name":"Wellsmore & Co Real Estate Pty Ltd",
    "wof:placetype":"venue"
},
  "geometry": {"coordinates":[149.04785156200001,-35.3942947388],"type":"Point"}
}