{
  "type": "Feature",
  "properties": {
    "addr:full":"9 Grassmere Pl Mawson Lakes SA 5095",
    "addr:housenumber":"9",
    "addr:postcode":"5095",
    "addr:street":"Grassmere Pl",
    "iso:country":"AU",
    "sg:address":"9 Grassmere Pl",
    "sg:city":"Mawson Lakes",
    "sg:classifiers":[
        {
            "category":"Building & Trades",
            "subcategory":"Plumbing",
            "type":"Services"
        }
    ],
    "sg:phone":"+61 418 819 784",
    "sg:postcode":"5095",
    "sg:province":"SA",
    "sg:tags":[
        "plumber",
        "gasfitters"
    ],
    "wof:name":"Executive Plumbing & Handyman",
    "wof:placetype":"venue"
},
  "geometry": {"coordinates":[138.60826110799999,-34.8130760193],"type":"Point"}
}