{
  "type": "Feature",
  "properties": {
    "iso:country":"AU",
    "sg:address":"Shop 2, 407 Hume Hwy",
    "sg:city":"Liverpool",
    "sg:classifiers":[
        {
            "category":"Building & Trades",
            "subcategory":"Equipment Rental",
            "type":"Services"
        }
    ],
    "sg:phone":"+61 2 9824 3549",
    "sg:postcode":"2170",
    "sg:province":"NSW",
    "sg:tags":[
        "fitness"
    ],
    "wof:name":"Liverpool Exercise Equipment. Hire and Sales",
    "wof:placetype":"venue"
},
  "geometry": {"coordinates":[150.91453552199999,-33.9361610413],"type":"Point"}
}