{
  "type": "Feature",
  "properties": {
    "addr:full":"429 Rokeby Rd Subiaco WA 6008",
    "addr:housenumber":"429",
    "addr:postcode":"6008",
    "addr:street":"Rokeby Rd",
    "iso:country":"AU",
    "sg:address":"429 Rokeby Rd",
    "sg:city":"Subiaco",
    "sg:classifiers":[
        {
            "category":"Social Services",
            "subcategory":"Retirement Home",
            "type":"Services"
        }
    ],
    "sg:phone":"+61 8 9381 8061",
    "sg:postcode":"6008",
    "sg:province":"WA",
    "sg:tags":[
        "accommodation",
        "special"
    ],
    "wof:name":"St Luke's Nursing Home",
    "wof:placetype":"venue"
},
  "geometry": {"coordinates":[115.823722839,-31.9572982788],"type":"Point"}
}