{
  "type": "Feature",
  "properties": {
    "iso:country":"AU",
    "sg:address":"629 Maroondah Hwy",
    "sg:city":"Coldstream",
    "sg:classifiers":[
        {
            "category":"Fast Food",
            "type":"Food & Drink"
        }
    ],
    "sg:phone":"+61 3 9739 0099",
    "sg:postcode":"3770",
    "sg:province":"VIC",
    "sg:tags":[
        "away",
        "take"
    ],
    "wof:name":"Roadrunners Roadhouse",
    "wof:placetype":"venue"
},
  "geometry": {"coordinates":[145.378479,-37.724499],"type":"Point"}
}