{
  "type": "Feature",
  "properties": {
    "iso:country":"AU",
    "sg:address":"21 Judith St",
    "sg:city":"Keilor East",
    "sg:classifiers":[
        {
            "category":"Building & Trades",
            "subcategory":"Construction",
            "type":"Services"
        }
    ],
    "sg:phone":"+61 3 9337 3092",
    "sg:postcode":"3033",
    "sg:province":"VIC",
    "sg:tags":[
        "road",
        "contractor"
    ],
    "wof:name":"Roadpac Pty Ltd",
    "wof:placetype":"venue"
},
  "geometry": {"coordinates":[144.876984,-37.746655],"type":"Point"}
}