{
  "type": "Feature",
  "properties": {
    "addr:full":"132 Upper Heidelberg Rd Ivanhoe VIC 3079",
    "addr:housenumber":"132",
    "addr:postcode":"3079",
    "addr:street":"Upper Heidelberg Rd",
    "iso:country":"AU",
    "sg:address":"132 Upper Heidelberg Rd",
    "sg:city":"Ivanhoe",
    "sg:classifiers":[
        {
            "category":"Banks & Credit Unions",
            "subcategory":"Investment Brokerage",
            "type":"Services"
        }
    ],
    "sg:phone":"+61 3 9497 4500",
    "sg:postcode":"3079",
    "sg:province":"VIC",
    "wof:name":"Lee Partners Financial Planners Pty Ltd",
    "wof:placetype":"venue"
},
  "geometry": {"coordinates":[145.04237365700001,-37.768989563],"type":"Point"}
}