{
  "type": "Feature",
  "properties": {
    "addr:full":"697- 699 Glenhuntly Rd Caulfield South VIC 3162",
    "addr:housenumber":"699",
    "addr:postcode":"3162",
    "addr:street":"Glenhuntly Rd",
    "iso:country":"AU",
    "sg:address":"697- 699 Glenhuntly Rd",
    "sg:city":"Caulfield South",
    "sg:classifiers":[
        {
            "category":"Banks & Credit Unions",
            "subcategory":"Financial Services",
            "type":"Services"
        }
    ],
    "sg:phone":"+61 3 9532 4099",
    "sg:postcode":"3162",
    "sg:province":"VIC",
    "sg:tags":[
        "loan",
        "finance",
        "mortgage"
    ],
    "wof:name":"Wizard",
    "wof:placetype":"venue"
},
  "geometry": {"coordinates":[145.018676758,-37.8863372803],"type":"Point"}
}