{
  "type": "Feature",
  "properties": {
    "addr:full":"7 Carrick Drv Tullamarine VIC 3043",
    "addr:housenumber":"7",
    "addr:postcode":"3043",
    "addr:street":"Carrick Drv",
    "iso:country":"AU",
    "sg:address":"7 Carrick Drv",
    "sg:city":"Tullamarine",
    "sg:classifiers":[
        {
            "category":"Professional",
            "subcategory":"Computer Services",
            "type":"Services"
        }
    ],
    "sg:phone":"+61 3 9335 1588",
    "sg:postcode":"3043",
    "sg:province":"VIC",
    "sg:tags":[
        "package",
        "software"
    ],
    "wof:name":"Leisure Link",
    "wof:placetype":"venue"
},
  "geometry": {"coordinates":[144.88291931099999,-37.7025108337],"type":"Point"}
}