{
  "type": "Feature",
  "properties": {
    "addr:full":"156 Kilrie Rd Ayr QLD 4807",
    "addr:housenumber":"156",
    "addr:postcode":"4807",
    "addr:street":"Kilrie Rd",
    "iso:country":"AU",
    "sg:address":"156 Kilrie Rd",
    "sg:city":"Ayr",
    "sg:classifiers":[
        {
            "category":"Retail",
            "subcategory":"Repair Shop",
            "type":"Services"
        }
    ],
    "sg:phone":"+61 7 4783 1299",
    "sg:postcode":"4807",
    "sg:province":"QLD",
    "sg:tags":[
        "leadlights"
    ],
    "wof:name":"Everything Leadlight",
    "wof:placetype":"venue"
},
  "geometry": {"coordinates":[147.41476440400001,-19.5950717926],"type":"Point"}
}