{
  "type": "Feature",
  "properties": {
    "addr:full":"98 Queen St Altona VIC 3018",
    "addr:housenumber":"98",
    "addr:postcode":"3018",
    "addr:street":"Queen St",
    "iso:country":"AU",
    "sg:address":"98 Queen St",
    "sg:city":"Altona",
    "sg:classifiers":[
        {
            "category":"Health Services",
            "subcategory":"Doctor",
            "type":"Services"
        }
    ],
    "sg:phone":"+61 3 9398 2932",
    "sg:postcode":"3018",
    "sg:province":"VIC",
    "sg:tags":[
        "medical",
        "practitioner"
    ],
    "wof:name":"Sahhar Sol B",
    "wof:placetype":"venue"
},
  "geometry": {"coordinates":[144.83250427199999,-37.8698577881],"type":"Point"}
}