{
  "type": "Feature",
  "properties": {
    "iso:country":"AU",
    "sg:address":"PO Box 215",
    "sg:city":"Carnegie",
    "sg:classifiers":[
        {
            "category":"Building & Trades",
            "subcategory":"Plumbing",
            "type":"Services"
        }
    ],
    "sg:phone":"+61 418 340 663",
    "sg:postcode":"3163",
    "sg:province":"VIC",
    "sg:tags":[
        "plumber",
        "gasfitters"
    ],
    "wof:name":"Eddington Allan Plumbing",
    "wof:placetype":"venue"
},
  "geometry": {"coordinates":[145.056762695,-37.8907585144],"type":"Point"}
}