{
  "type": "Feature",
  "properties": {
    "addr:full":"344 Como Pde Parkdale VIC 3195",
    "addr:housenumber":"344",
    "addr:postcode":"3195",
    "addr:street":"Como Pde",
    "iso:country":"AU",
    "sg:address":"344 Como Pde",
    "sg:city":"Parkdale",
    "sg:classifiers":[
        {
            "category":"Health Services",
            "subcategory":"Health Practitioner",
            "type":"Services"
        }
    ],
    "sg:phone":"+61 3 9587 2855",
    "sg:postcode":"3195",
    "sg:province":"VIC",
    "sg:tags":[
        "physiotherapist"
    ],
    "wof:name":"Como Physiotherapy & Rehabilitation",
    "wof:placetype":"venue"
},
  "geometry": {"coordinates":[145.078048706,-37.9950561523],"type":"Point"}
}