{
  "type": "Feature",
  "properties": {
    "addr:full":"Shp 5/ 60 Rosenthal St Doonside NSW 2767",
    "addr:housenumber":"/ 60",
    "addr:postcode":"2767",
    "addr:street":"Rosenthal St",
    "iso:country":"AU",
    "sg:address":"Shp 5/ 60 Rosenthal St",
    "sg:city":"Doonside",
    "sg:classifiers":[
        {
            "category":"Shopping",
            "subcategory":"Pets & Pet Supplies",
            "type":"Retail Goods"
        }
    ],
    "sg:phone":"+61 2 9831 3322",
    "sg:postcode":"2767",
    "sg:province":"NSW",
    "sg:tags":[
        "food"
    ],
    "wof:name":"Noah's Ark Pets",
    "wof:placetype":"venue"
},
  "geometry": {"coordinates":[150.877807617,-33.7707633972],"type":"Point"}
}