{
  "type": "Feature",
  "properties": {
    "addr:full":"1412 High St Malvern VIC 3144",
    "addr:housenumber":"1412",
    "addr:postcode":"3144",
    "addr:street":"High St",
    "iso:country":"AU",
    "sg:address":"1412 High St",
    "sg:city":"Malvern",
    "sg:classifiers":[
        {
            "category":"Fast Food",
            "type":"Food & Drink"
        }
    ],
    "sg:phone":"+61 3 9509 8699",
    "sg:postcode":"3144",
    "sg:province":"VIC",
    "sg:tags":[
        "away",
        "take"
    ],
    "wof:name":"Mario Boys Pizza",
    "wof:placetype":"venue"
},
  "geometry": {"coordinates":[145.040283203,-37.8581619263],"type":"Point"}
}