{
  "type": "Feature",
  "properties": {
    "iso:country":"AU",
    "sg:address":"2 Capri Crt",
    "sg:city":"Ocean Grove",
    "sg:classifiers":[
        {
            "category":"Government",
            "subcategory":"Post Office",
            "type":"Public Place"
        }
    ],
    "sg:phone":"+61 3 5256 3184",
    "sg:postcode":"3226",
    "sg:province":"VIC",
    "sg:tags":[
        "yoga"
    ],
    "wof:name":"Satyananda Yoga",
    "wof:placetype":"venue"
},
  "geometry": {"coordinates":[144.514877,-38.256989],"type":"Point"}
}