{
  "type": "Feature",
  "properties": {
    "addr:full":"248 Commercial Rd Yarram VIC 3971",
    "addr:housenumber":"248",
    "addr:postcode":"3971",
    "addr:street":"Commercial Rd",
    "iso:country":"AU",
    "sg:address":"248 Commercial Rd",
    "sg:city":"Yarram",
    "sg:classifiers":[
        {
            "category":"Shopping",
            "subcategory":"Crafts & Fabrics",
            "type":"Retail Goods"
        }
    ],
    "sg:phone":"+61 3 5182 5085",
    "sg:postcode":"3971",
    "sg:province":"VIC",
    "sg:tags":[
        "wool",
        "knitting",
        "accessory"
    ],
    "wof:name":"Gippsland Window Furnishings",
    "wof:placetype":"venue"
},
  "geometry": {"coordinates":[146.67564392099999,-38.5634880066],"type":"Point"}
}