{
  "type": "Feature",
  "properties": {
    "iso:country":"AU",
    "sg:address":"4 Howards Rd",
    "sg:city":"Beverley",
    "sg:classifiers":[
        {
            "category":"Government",
            "subcategory":"Fire Station",
            "type":"Public Place"
        }
    ],
    "sg:phone":"+61 8 8244 8311",
    "sg:postcode":"5009",
    "sg:province":"SA",
    "sg:tags":[
        "equipment",
        "protection",
        "consultant"
    ],
    "wof:name":"Titon Fire, Security & Electrical Services Pty Ltd",
    "wof:placetype":"venue"
},
  "geometry": {"coordinates":[138.54330444300001,-34.8871803284],"type":"Point"}
}