{
  "type": "Feature",
  "properties": {
    "addr:full":"92 Hertford St Delacombe VIC 3356",
    "addr:housenumber":"92",
    "addr:postcode":"3356",
    "addr:street":"Hertford St",
    "iso:country":"AU",
    "sg:address":"92 Hertford St",
    "sg:city":"Delacombe",
    "sg:classifiers":[
        {
            "category":"Home & Garden",
            "subcategory":"Building Materials",
            "type":"Retail Goods"
        }
    ],
    "sg:phone":"+61 3 5336 3732",
    "sg:postcode":"3356",
    "sg:province":"VIC",
    "sg:tags":[
        "fencing"
    ],
    "wof:name":"Adroit Fencing",
    "wof:placetype":"venue"
},
  "geometry": {"coordinates":[143.82853700000001,-37.586807],"type":"Point"}
}