{
  "type": "Feature",
  "properties": {
    "iso:country":"AU",
    "sg:address":"St",
    "sg:city":"Kilda East",
    "sg:classifiers":[
        {
            "category":"Professional",
            "subcategory":"Art Services",
            "type":"Services"
        }
    ],
    "sg:phone":"+61 418 554 930",
    "sg:postcode":"3183",
    "sg:province":"VIC",
    "sg:tags":[
        "interior",
        "designer"
    ],
    "wof:name":"Bronwen Drinnan",
    "wof:placetype":"venue"
},
  "geometry": {"coordinates":[144.996826172,-37.8614883423],"type":"Point"}
}