{
  "type": "Feature",
  "properties": {
    "iso:country":"AU",
    "sg:address":"92 Horizon Drv",
    "sg:city":"Middle Park",
    "sg:classifiers":[
        {
            "category":"Deli",
            "type":"Food & Drink"
        }
    ],
    "sg:phone":"+61 7 3279 6099",
    "sg:postcode":"4074",
    "sg:province":"QLD",
    "sg:tags":[
        "delicatessen"
    ],
    "wof:name":"Savvas Deli",
    "wof:placetype":"venue"
},
  "geometry": {"coordinates":[152.922897339,-27.5548191071],"type":"Point"}
}