{
  "type": "Feature",
  "properties": {
    "iso:country":"AU",
    "sg:address":"3 Glover Crt",
    "sg:city":"Berwick",
    "sg:classifiers":[
        {
            "category":"Building & Trades",
            "subcategory":"Landscaping Services",
            "type":"Services"
        }
    ],
    "sg:phone":"+61 3 9796 2270",
    "sg:postcode":"3806",
    "sg:province":"VIC",
    "sg:tags":[
        "consultant"
    ],
    "wof:name":"A B I Services Pty Ltd",
    "wof:placetype":"venue"
},
  "geometry": {"coordinates":[145.33575439399999,-38.0184135437],"type":"Point"}
}