{
  "type": "Feature",
  "properties": {
    "iso:country":"AU",
    "sg:address":"Shop 5 Selbourne St",
    "sg:city":"Mt Gravatt",
    "sg:classifiers":[
        {
            "category":"Personal",
            "subcategory":"Beauty Salon",
            "type":"Services"
        }
    ],
    "sg:phone":"+61 7 3349 7501",
    "sg:postcode":"4122",
    "sg:province":"QLD",
    "wof:name":"Jennique Beauty & Aroma Therapy Clinic",
    "wof:placetype":"venue"
},
  "geometry": {"coordinates":[153.07862854000001,-27.5369281769],"type":"Point"}
}