{
  "type": "Feature",
  "properties": {
    "iso:country":"AU",
    "sg:address":"406 Victoria St",
    "sg:city":"Darlinghurst",
    "sg:classifiers":[
        {
            "category":"Personal",
            "subcategory":"Beauty Salon",
            "type":"Services"
        }
    ],
    "sg:phone":"+61 2 8347 7437",
    "sg:postcode":"2010",
    "sg:province":"NSW",
    "wof:name":"Marie Gai",
    "wof:placetype":"venue"
},
  "geometry": {"coordinates":[151.220626831,-33.8804664612],"type":"Point"}
}