{
  "type": "Feature",
  "properties": {
    "addr:full":"68 Macquarie St Parramatta NSW 2150",
    "addr:housenumber":"68",
    "addr:postcode":"2150",
    "addr:street":"Macquarie St",
    "iso:country":"AU",
    "sg:address":"68 Macquarie St",
    "sg:city":"Parramatta",
    "sg:classifiers":[
        {
            "category":"Professional",
            "subcategory":"Employment Agencies",
            "type":"Services"
        }
    ],
    "sg:phone":"+61 2 9204 9470",
    "sg:postcode":"2150",
    "sg:province":"NSW",
    "wof:name":"Select Teleresources",
    "wof:placetype":"venue"
},
  "geometry": {"coordinates":[151.06236267099999,-33.9103279114],"type":"Point"}
}