{
  "type": "Feature",
  "properties": {
    "addr:full":"17 Lennox St Normanhurst NSW 2076",
    "addr:housenumber":"17",
    "addr:postcode":"2076",
    "addr:street":"Lennox St",
    "iso:country":"AU",
    "sg:address":"17 Lennox St",
    "sg:city":"Normanhurst",
    "sg:classifiers":[
        {
            "category":"Professional",
            "subcategory":"Art Services",
            "type":"Services"
        }
    ],
    "sg:phone":"+61 2 9980 5120",
    "sg:postcode":"2076",
    "sg:province":"NSW",
    "sg:tags":[
        "decorator",
        "painter"
    ],
    "wof:name":"Talbot's Creative Colours",
    "wof:placetype":"venue"
},
  "geometry": {"coordinates":[151.08868408199999,-33.7196884155],"type":"Point"}
}