{
  "type": "Feature",
  "properties": {
    "addr:full":"2 Heany St Mt Waverley VIC 3149",
    "addr:housenumber":"2",
    "addr:postcode":"3149",
    "addr:street":"Heany St Mt",
    "iso:country":"AU",
    "sg:address":"2 Heany St",
    "sg:city":"Mt Waverley",
    "sg:classifiers":[
        {
            "category":"Utilities",
            "subcategory":"Electric",
            "type":"Services"
        }
    ],
    "sg:phone":"+61 3 9807 8718",
    "sg:postcode":"3149",
    "sg:province":"VIC",
    "sg:tags":[
        "electrical",
        "contractor"
    ],
    "wof:name":"Fairlane Electrix",
    "wof:placetype":"venue"
},
  "geometry": {"coordinates":[145.11883544899999,-37.8806686401],"type":"Point"}
}