{
  "type": "Feature",
  "properties": {
    "addr:full":"Unit 1, No 9 Bon Mace Close, Tumbi Gardens Estate, Berkele NSW 2261",
    "addr:postcode":"2261",
    "addr:street":"Mace Close Tumbi Gardens",
    "iso:country":"AU",
    "sg:address":"Unit 1, No 9",
    "sg:city":"Bon Mace Close, Tumbi Gardens Estate, Berkele",
    "sg:classifiers":[
        {
            "category":"Home & Garden",
            "subcategory":"Building Materials",
            "type":"Retail Goods"
        }
    ],
    "sg:phone":"+61 2 4388 5144",
    "sg:postcode":"2261",
    "sg:province":"NSW",
    "sg:tags":[
        "balustrading"
    ],
    "wof:name":"Shower Screen Traders Pty Ltd",
    "wof:placetype":"venue"
},
  "geometry": {"coordinates":[151.447495,-33.362968],"type":"Point"}
}