{
  "type": "Feature",
  "properties": {
    "iso:country":"AU",
    "sg:address":"3/ 19 Cronulla St",
    "sg:city":"Cronulla",
    "sg:classifiers":[
        {
            "category":"Ice Cream",
            "type":"Food & Drink"
        }
    ],
    "sg:phone":"+61 2 9523 8501",
    "sg:postcode":"2230",
    "sg:province":"NSW",
    "sg:tags":[
        "retail"
    ],
    "wof:name":"Strawberry Fair Cafe",
    "wof:placetype":"venue"
},
  "geometry": {"coordinates":[151.15267944300001,-34.05235672],"type":"Point"}
}