{
  "type": "Feature",
  "properties": {
    "addr:full":"Ground Floor 70 Pitt St Sydney NSW 2000",
    "addr:housenumber":"70",
    "addr:postcode":"2000",
    "addr:street":"Pitt St",
    "iso:country":"AU",
    "sg:address":"Ground Floor 70 Pitt St",
    "sg:city":"Sydney",
    "sg:classifiers":[
        {
            "category":"Health Services",
            "subcategory":"Dentist",
            "type":"Services"
        }
    ],
    "sg:phone":"+61 2 9223 4767",
    "sg:postcode":"2000",
    "sg:province":"NSW",
    "wof:name":"Rosenberg Graham Dr",
    "wof:placetype":"venue"
},
  "geometry": {"coordinates":[151.208786011,-33.8659362793],"type":"Point"}
}