{
  "type": "Feature",
  "properties": {
    "addr:full":"14 Sir William McKell Dr Pambula NSW 2549",
    "addr:housenumber":"14",
    "addr:postcode":"2549",
    "addr:street":"Sir William Mckell Dr",
    "iso:country":"AU",
    "sg:address":"14 Sir William McKell Dr",
    "sg:city":"Pambula",
    "sg:classifiers":[
        {
            "category":"Retail",
            "subcategory":"Auto Repair",
            "type":"Services"
        }
    ],
    "sg:phone":"+61 2 6495 6147",
    "sg:postcode":"2549",
    "sg:province":"NSW",
    "sg:tags":[
        "wheel",
        "balancing",
        "alignment"
    ],
    "wof:name":"McDermott John Automotive",
    "wof:placetype":"venue"
},
  "geometry": {"coordinates":[149.886444092,-36.9362297058],"type":"Point"}
}