{
  "type": "Feature",
  "properties": {
    "addr:full":"43 Brisbane Drv Jensen QLD 4818",
    "addr:housenumber":"43",
    "addr:postcode":"4818",
    "addr:street":"Brisbane Drv",
    "iso:country":"AU",
    "sg:address":"43 Brisbane Drv",
    "sg:city":"Jensen",
    "sg:classifiers":[
        {
            "category":"Professional",
            "type":"Services"
        }
    ],
    "sg:phone":"+61 403 486 939",
    "sg:postcode":"4818",
    "sg:province":"QLD",
    "sg:tags":[
        "spray",
        "painting"
    ],
    "wof:name":"Aaron Lee Painting Pty Ltd",
    "wof:placetype":"venue"
},
  "geometry": {"coordinates":[146.65069600000001,-19.241823],"type":"Point"}
}