{
  "type": "Feature",
  "properties": {
    "iso:country":"AU",
    "sg:address":"164 Richmond St",
    "sg:city":"Maryborough",
    "sg:classifiers":[
        {
            "category":"Professional",
            "subcategory":"Research",
            "type":"Services"
        }
    ],
    "sg:phone":"+61 7 4123 1842",
    "sg:postcode":"4650",
    "sg:province":"QLD",
    "sg:tags":[
        "historical"
    ],
    "wof:name":"Maryborough District Family History Society",
    "wof:placetype":"venue"
},
  "geometry": {"coordinates":[152.703766,-25.539553],"type":"Point"}
}