{
  "type": "Feature",
  "properties": {
    "addr:full":"9- 11 Hardware La Melbourne VIC 3000",
    "addr:housenumber":"11",
    "addr:postcode":"3000",
    "addr:street":"9;La",
    "iso:country":"AU",
    "sg:address":"9- 11 Hardware La",
    "sg:city":"Melbourne",
    "sg:classifiers":[
        {
            "category":"Sports & Exercise",
            "subcategory":"Ski Slope",
            "type":"Entertainment"
        }
    ],
    "sg:phone":"+61 3 9670 1412",
    "sg:postcode":"3000",
    "sg:province":"VIC",
    "sg:tags":[
        "equipment",
        "hire",
        "retail",
        "snow"
    ],
    "sg:website":"http://www.auski.com.au",
    "wof:name":"Auski",
    "wof:placetype":"venue"
},
  "geometry": {"coordinates":[144.961471558,-37.8144798279],"type":"Point"}
}