{
  "type": "Feature",
  "properties": {
    "addr:full":"Shop 4 / 395 Hillsborough Rd Warners Bay NSW 2282",
    "addr:housenumber":"shop 4 / 395",
    "addr:postcode":"2282",
    "addr:street":"Hillsborough Rd",
    "iso:country":"AU",
    "sg:address":"Shop 4 / 395 Hillsborough Rd",
    "sg:city":"Warners Bay",
    "sg:classifiers":[
        {
            "category":"Building & Trades",
            "subcategory":"Equipment Rental",
            "type":"Services"
        }
    ],
    "sg:phone":"+61 2 4954 2233",
    "sg:postcode":"2282",
    "sg:province":"NSW",
    "sg:tags":[
        "fitness"
    ],
    "wof:name":"Workout World",
    "wof:placetype":"venue"
},
  "geometry": {"coordinates":[151.65312194800001,-32.9664611816],"type":"Point"}
}