{
  "type": "Feature",
  "properties": {
    "iso:country":"AU",
    "sg:address":"77 Warners Bay Rd",
    "sg:city":"Edgeworth",
    "sg:classifiers":[
        {
            "category":"Building & Trades",
            "subcategory":"Plumbing",
            "type":"Services"
        }
    ],
    "sg:phone":"+61 2 4965 7044",
    "sg:postcode":"2285",
    "sg:province":"NSW",
    "sg:tags":[
        "plumber",
        "gasfitters"
    ],
    "wof:name":"Adler S & K Quality Pools",
    "wof:placetype":"venue"
},
  "geometry": {"coordinates":[151.65419006400001,-32.9831504822],"type":"Point"}
}