{
  "type": "Feature",
  "properties": {
    "addr:full":"24 Ralston St Lane Cove NSW 2066",
    "addr:housenumber":"24",
    "addr:postcode":"2066",
    "addr:street":"Ralston St",
    "iso:country":"AU",
    "sg:address":"24 Ralston St",
    "sg:city":"Lane Cove",
    "sg:classifiers":[
        {
            "category":"Real Estate",
            "subcategory":"Architect",
            "type":"Services"
        }
    ],
    "sg:phone":"+61 2 9418 6104",
    "sg:postcode":"2066",
    "sg:province":"NSW",
    "wof:name":"Priestleys Architects",
    "wof:placetype":"venue"
},
  "geometry": {"coordinates":[151.17314148,-33.8092422485],"type":"Point"}
}