{
  "type": "Feature",
  "properties": {
    "iso:country":"AU",
    "sg:address":"65 Fairbank St",
    "sg:city":"Sunnybank",
    "sg:classifiers":[
        {
            "category":"Professional",
            "subcategory":"Accounting & Tax Preparation",
            "type":"Services"
        }
    ],
    "sg:phone":"+61 7 3344 3722",
    "sg:postcode":"4109",
    "sg:province":"QLD",
    "sg:tags":[
        "accountant",
        "auditor"
    ],
    "wof:name":"Business Links Financial Planning",
    "wof:placetype":"venue"
},
  "geometry": {"coordinates":[153.05398559599999,-27.5756874084],"type":"Point"}
}