{
  "type": "Feature",
  "properties": {
    "addr:full":"30 John St Cunnamulla QLD 4490",
    "addr:housenumber":"30",
    "addr:postcode":"4490",
    "addr:street":"John St",
    "iso:country":"AU",
    "sg:address":"30 John St",
    "sg:city":"Cunnamulla",
    "sg:classifiers":[
        {
            "category":"Food & Beverages",
            "subcategory":"Fruits & Vegetables",
            "type":"Retail Goods"
        }
    ],
    "sg:phone":"+61 7 4655 1222",
    "sg:postcode":"4490",
    "sg:province":"QLD",
    "sg:tags":[
        "greengrocer",
        "fruiterer"
    ],
    "wof:name":"Mills E & Sons",
    "wof:placetype":"venue"
},
  "geometry": {"coordinates":[145.684326172,-28.0689563751],"type":"Point"}
}