{
  "type": "Feature",
  "properties": {
    "addr:full":"38 Chateau Pl Belhus WA 6069",
    "addr:housenumber":"38",
    "addr:postcode":"6069",
    "addr:street":"Chateau Pl Belhus",
    "iso:country":"AU",
    "sg:address":"38 Chateau Pl",
    "sg:city":"Belhus",
    "sg:classifiers":[
        {
            "category":"Insurance",
            "subcategory":"Insurance Agent",
            "type":"Services"
        }
    ],
    "sg:phone":"+61 8 9296 1144",
    "sg:postcode":"6069",
    "sg:province":"WA",
    "sg:tags":[
        "bloodstock"
    ],
    "wof:name":"Belhus Racing",
    "wof:placetype":"venue"
},
  "geometry": {"coordinates":[116.00189209,-31.7711353302],"type":"Point"}
}