{
  "type": "Feature",
  "properties": {
    "addr:full":"2722 Old Northern Rd Glenorie NSW 2157",
    "addr:housenumber":"2722",
    "addr:postcode":"2157",
    "addr:street":"Old Northern Rd",
    "iso:country":"AU",
    "sg:address":"2722 Old Northern Rd",
    "sg:city":"Glenorie",
    "sg:classifiers":[
        {
            "category":"Building & Trades",
            "subcategory":"Construction",
            "type":"Services"
        }
    ],
    "sg:phone":"+61 2 9652 1241",
    "sg:postcode":"2157",
    "sg:province":"NSW",
    "sg:tags":[
        "earth",
        "excavating",
        "moving",
        "contractor"
    ],
    "wof:name":"Mark Holt Pty Ltd",
    "wof:placetype":"venue"
},
  "geometry": {"coordinates":[151.01286315900001,-33.5852737427],"type":"Point"}
}