{
  "type": "Feature",
  "properties": {
    "addr:full":"84 Oak St Beaumaris VIC 3193",
    "addr:housenumber":"84",
    "addr:postcode":"3193",
    "addr:street":"Oak St",
    "iso:country":"AU",
    "sg:address":"84 Oak St",
    "sg:city":"Beaumaris",
    "sg:classifiers":[
        {
            "category":"Organizations",
            "subcategory":"Community Association",
            "type":"Services"
        }
    ],
    "sg:phone":"+61 3 9589 3887",
    "sg:postcode":"3193",
    "sg:province":"VIC",
    "sg:tags":[
        "international",
        "organisation",
        "relation",
        "aid"
    ],
    "wof:name":"Samaritan's Purse Australia Limited",
    "wof:placetype":"venue"
},
  "geometry": {"coordinates":[145.04168701200001,-37.9840545654],"type":"Point"}
}