{
  "type": "Feature",
  "properties": {
    "addr:full":"3/ 134 Evan St South Mackay QLD 4740",
    "addr:housenumber":"/ 134",
    "addr:postcode":"4740",
    "addr:street":"Evan St",
    "iso:country":"AU",
    "sg:address":"3/ 134 Evan St",
    "sg:city":"South Mackay",
    "sg:classifiers":[
        {
            "category":"Personal",
            "subcategory":"Beauty Salon",
            "type":"Services"
        }
    ],
    "sg:phone":"+61 7 4957 3581",
    "sg:postcode":"4740",
    "sg:province":"QLD",
    "sg:tags":[
        "hairdresser"
    ],
    "wof:name":"L&#039;Auranda Beauty Salon",
    "wof:placetype":"venue"
},
  "geometry": {"coordinates":[149.18872099999999,-21.151598],"type":"Point"}
}