{
  "type": "Feature",
  "properties": {
    "addr:full":"1 Arthur St Gracemere QLD 4702",
    "addr:housenumber":"1",
    "addr:postcode":"4702",
    "addr:street":"Arthur St",
    "iso:country":"AU",
    "sg:address":"1 Arthur St",
    "sg:city":"Gracemere",
    "sg:classifiers":[
        {
            "category":"Professional",
            "subcategory":"Detective & Security Services",
            "type":"Services"
        }
    ],
    "sg:phone":"+61 7 4933 2333",
    "sg:postcode":"4702",
    "sg:province":"QLD",
    "sg:tags":[
        "protective",
        "rustproofing"
    ],
    "wof:name":"CouplerTec",
    "wof:placetype":"venue"
},
  "geometry": {"coordinates":[150.45913696299999,-23.4321155548],"type":"Point"}
}