{
  "type": "Feature",
  "properties": {
    "addr:full":"306- 308 Brunswick St Fitzroy VIC 3065",
    "addr:housenumber":"308",
    "addr:postcode":"3065",
    "addr:street":"Brunswick St",
    "iso:country":"AU",
    "sg:address":"306- 308 Brunswick St",
    "sg:city":"Fitzroy",
    "sg:classifiers":[
        {
            "category":"Shopping",
            "subcategory":"Stationery & Office Supplies",
            "type":"Retail Goods"
        }
    ],
    "sg:phone":"+61 3 9419 8033",
    "sg:postcode":"3065",
    "sg:province":"VIC",
    "wof:name":"Joel Harris Office Supplies",
    "wof:placetype":"venue"
},
  "geometry": {"coordinates":[144.97865295400001,-37.7980384827],"type":"Point"}
}