{
  "type": "Feature",
  "properties": {
    "addr:full":"200 Foote St Templestowe VIC 3106",
    "addr:housenumber":"200",
    "addr:postcode":"3106",
    "addr:street":"Foote St",
    "iso:country":"AU",
    "sg:address":"200 Foote St",
    "sg:city":"Templestowe",
    "sg:classifiers":[
        {
            "category":"Health Services",
            "subcategory":"Health Practitioner",
            "type":"Services"
        }
    ],
    "sg:phone":"+61 3 9846 1442",
    "sg:postcode":"3106",
    "sg:province":"VIC",
    "sg:tags":[
        "alternative"
    ],
    "wof:name":"Signature Sounds",
    "wof:placetype":"venue"
},
  "geometry": {"coordinates":[145.13229370100001,-37.7596244812],"type":"Point"}
}