{
  "type": "Feature",
  "properties": {
    "iso:country":"AU",
    "sg:address":"67 Kensington Rd",
    "sg:city":"Norwood",
    "sg:classifiers":[
        {
            "category":"Banks & Credit Unions",
            "subcategory":"Financial Services",
            "type":"Services"
        }
    ],
    "sg:phone":"+61 8 8333 1455",
    "sg:postcode":"5067",
    "sg:province":"SA",
    "sg:tags":[
        "loan",
        "finance",
        "mortgage"
    ],
    "wof:name":"Seniors Monetary Solutions",
    "wof:placetype":"venue"
},
  "geometry": {"coordinates":[138.629272461,-34.9276809692],"type":"Point"}
}