{
  "type": "Feature",
  "properties": {
    "addr:full":"76 Hoff St Mt Gravatt East QLD 4122",
    "addr:housenumber":"76",
    "addr:postcode":"4122",
    "addr:street":"Hoff St",
    "iso:country":"AU",
    "sg:address":"76 Hoff St",
    "sg:city":"Mt Gravatt East",
    "sg:classifiers":[
        {
            "category":"Real Estate",
            "subcategory":"Architect",
            "type":"Services"
        }
    ],
    "sg:phone":"+61 7 3343 2680",
    "sg:postcode":"4122",
    "sg:province":"QLD",
    "wof:name":"GREGG WINKEL ARCHITECTS PTY LTD",
    "wof:placetype":"venue"
},
  "geometry": {"coordinates":[153.08392334000001,-27.534576416],"type":"Point"}
}