{
  "type": "Feature",
  "properties": {
    "addr:full":"22 Niquet Ave Highbury SA 5089",
    "addr:housenumber":"22",
    "addr:postcode":"5089",
    "addr:street":"Niquet Ave",
    "iso:country":"AU",
    "sg:address":"22 Niquet Ave",
    "sg:city":"Highbury",
    "sg:classifiers":[
        {
            "category":"Real Estate",
            "subcategory":"Real Estate Agent",
            "type":"Services"
        }
    ],
    "sg:phone":"+61 8 8395 4217",
    "sg:postcode":"5089",
    "sg:province":"SA",
    "wof:name":"Brian Pomery Real Estate",
    "wof:placetype":"venue"
},
  "geometry": {"coordinates":[138.716506958,-34.8544502258],"type":"Point"}
}