{
  "type": "Feature",
  "properties": {
    "iso:country":"AU",
    "sg:address":"6 Short St",
    "sg:city":"Fremantle",
    "sg:classifiers":[
        {
            "category":"Transit Center",
            "subcategory":"Freight",
            "type":"Transportation"
        }
    ],
    "sg:phone":"+61 8 9335 9599",
    "sg:postcode":"6160",
    "sg:province":"WA",
    "sg:tags":[
        "agent",
        "shipping"
    ],
    "wof:name":"Hamburg Sud Australia Pty Ltd",
    "wof:placetype":"venue"
},
  "geometry": {"coordinates":[115.745178,-32.053482],"type":"Point"}
}