{
  "type": "Feature",
  "properties": {
    "iso:country":"AU",
    "sg:address":"6 Baker St",
    "sg:city":"Gosford",
    "sg:classifiers":[
        {
            "category":"Retail",
            "subcategory":"Event Space",
            "type":"Services"
        }
    ],
    "sg:phone":"+61 421 703 405",
    "sg:postcode":"2250",
    "sg:province":"NSW",
    "sg:tags":[
        "function",
        "organiser"
    ],
    "wof:name":"Ricks Oasis & After Dark",
    "wof:placetype":"venue"
},
  "geometry": {"coordinates":[151.340744019,-33.4271469116],"type":"Point"}
}