{
  "type": "Feature",
  "properties": {
    "addr:full":"Suite 2, 235 Main St Osborne Park WA 6017",
    "addr:housenumber":"235",
    "addr:postcode":"6017",
    "addr:street":"Main St",
    "iso:country":"AU",
    "sg:address":"Suite 2, 235 Main St",
    "sg:city":"Osborne Park",
    "sg:classifiers":[
        {
            "category":"Health Services",
            "subcategory":"Doctor",
            "type":"Services"
        }
    ],
    "sg:phone":"+61 8 9440 4333",
    "sg:postcode":"6017",
    "sg:province":"WA",
    "sg:tags":[
        "podiatrist"
    ],
    "wof:name":"Ashley Day Podiatry",
    "wof:placetype":"venue"
},
  "geometry": {"coordinates":[115.828086853,-31.8950862885],"type":"Point"}
}