{
  "type": "Feature",
  "properties": {
    "addr:full":"17 Standish Rd Myrtleford VIC 3737",
    "addr:housenumber":"17",
    "addr:postcode":"3737",
    "addr:street":"Standish Rd",
    "iso:country":"AU",
    "sg:address":"17 Standish Rd",
    "sg:city":"Myrtleford",
    "sg:classifiers":[
        {
            "category":"Wholesale",
            "subcategory":"Tobacco Products",
            "type":"Manufacturing & Wholesale Goods"
        }
    ],
    "sg:phone":"+61 3 5752 1991",
    "sg:postcode":"3737",
    "sg:province":"VIC",
    "sg:tags":[
        "grower"
    ],
    "wof:name":"Sacco D",
    "wof:placetype":"venue"
},
  "geometry": {"coordinates":[146.71975707999999,-36.564868927],"type":"Point"}
}