{
  "type": "Feature",
  "properties": {
    "addr:full":"4 Sark Pl Warnbro WA 6169",
    "addr:housenumber":"4",
    "addr:postcode":"6169",
    "addr:street":"Sark Pl",
    "iso:country":"AU",
    "sg:address":"4 Sark Pl",
    "sg:city":"Warnbro",
    "sg:classifiers":[
        {
            "category":"Home & Garden",
            "subcategory":"Building Materials",
            "type":"Retail Goods"
        }
    ],
    "sg:phone":"+61 8 9593 0360",
    "sg:postcode":"6169",
    "sg:province":"WA",
    "sg:tags":[
        "lawn",
        "cutting",
        "maintenance"
    ],
    "wof:name":"Master Cut Lawnmowing Service",
    "wof:placetype":"venue"
},
  "geometry": {"coordinates":[115.765762,-32.330788],"type":"Point"}
}