{
  "type": "Feature",
  "properties": {
    "iso:country":"AU",
    "sg:address":"60 Gordon Pde",
    "sg:city":"Manly",
    "sg:classifiers":[
        {
            "category":"Professional",
            "subcategory":"Business Services",
            "type":"Services"
        }
    ],
    "sg:phone":"+61 7 3396 0476",
    "sg:postcode":"4179",
    "sg:province":"QLD",
    "sg:tags":[
        "drafting"
    ],
    "wof:name":"P.G. & D.J. Chalk Building Designers",
    "wof:placetype":"venue"
},
  "geometry": {"coordinates":[153.17927551299999,-27.4545269012],"type":"Point"}
}