{
  "type": "Feature",
  "properties": {
    "iso:country":"AU",
    "sg:address":"PO Box 1009",
    "sg:city":"Chatswood",
    "sg:classifiers":[
        {
            "category":"Professional",
            "subcategory":"Employment Agencies",
            "type":"Services"
        }
    ],
    "sg:phone":"+61 1300 666 501",
    "sg:postcode":"2057",
    "sg:province":"NSW",
    "wof:name":"Head Hunter Personnel Consultants (The)",
    "wof:placetype":"venue"
},
  "geometry": {"coordinates":[151.190125,-33.792439],"type":"Point"}
}