{
  "type": "Feature",
  "properties": {
    "addr:full":"4 Bond St Mt Waverley VIC 3149",
    "addr:housenumber":"4",
    "addr:postcode":"3149",
    "addr:street":"Bond St Mt",
    "iso:country":"AU",
    "sg:address":"4 Bond St",
    "sg:city":"Mt Waverley",
    "sg:classifiers":[
        {
            "category":"Personal",
            "subcategory":"Beauty Salon",
            "type":"Services"
        }
    ],
    "sg:phone":"+61 3 8802 8447",
    "sg:postcode":"3149",
    "sg:province":"VIC",
    "sg:tags":[
        "hairdresser"
    ],
    "wof:name":"Axxess Hair Design",
    "wof:placetype":"venue"
},
  "geometry": {"coordinates":[145.138397217,-37.8794937134],"type":"Point"}
}