{
  "type": "Feature",
  "properties": {
    "addr:full":"4/ 16 The Centreway Lara VIC 3212",
    "addr:housenumber":"/ 16",
    "addr:postcode":"3212",
    "addr:street":"The Centreway",
    "iso:country":"AU",
    "sg:address":"4/ 16 The Centreway",
    "sg:city":"Lara",
    "sg:classifiers":[
        {
            "category":"Personal",
            "subcategory":"Beauty Salon",
            "type":"Services"
        }
    ],
    "sg:phone":"+61 3 5282 3747",
    "sg:postcode":"3212",
    "sg:province":"VIC",
    "sg:tags":[
        "hairdresser"
    ],
    "wof:name":"Clickity's Hair Design",
    "wof:placetype":"venue"
},
  "geometry": {"coordinates":[144.40692138700001,-38.0224838257],"type":"Point"}
}