{
  "type": "Feature",
  "properties": {
    "addr:full":"98 Rundle St Kent Town SA 5067",
    "addr:housenumber":"98",
    "addr:postcode":"5067",
    "addr:street":"Rundle St",
    "iso:country":"AU",
    "sg:address":"98 Rundle St",
    "sg:city":"Kent Town",
    "sg:classifiers":[
        {
            "category":"Health Services",
            "subcategory":"Doctor",
            "type":"Services"
        }
    ],
    "sg:phone":"+61 8 8362 8864",
    "sg:postcode":"5067",
    "sg:province":"SA",
    "sg:tags":[
        "medical",
        "practitioner"
    ],
    "wof:name":"Fry P L",
    "wof:placetype":"venue"
},
  "geometry": {"coordinates":[138.618606567,-34.9202461243],"type":"Point"}
}