{
  "type": "Feature",
  "properties": {
    "addr:full":"4 Mitchell Crt Carrara QLD 4211",
    "addr:housenumber":"4",
    "addr:postcode":"4211",
    "addr:street":"Mitchell Crt",
    "iso:country":"AU",
    "sg:address":"4 Mitchell Crt",
    "sg:city":"Carrara",
    "sg:classifiers":[
        {
            "category":"Building & Trades",
            "subcategory":"Construction",
            "type":"Services"
        }
    ],
    "sg:phone":"+61 7 5594 4298",
    "sg:postcode":"4211",
    "sg:province":"QLD",
    "sg:tags":[
        "renovation",
        "alterations",
        "extension",
        "contractor"
    ],
    "wof:name":"Moon Peter",
    "wof:placetype":"venue"
},
  "geometry": {"coordinates":[153.35777282699999,-28.0124015808],"type":"Point"}
}