{
  "type": "Feature",
  "properties": {
    "iso:country":"AU",
    "sg:address":"461 Harris St",
    "sg:city":"Pyrmont",
    "sg:classifiers":[
        {
            "category":"Manufacturing",
            "subcategory":"Food",
            "type":"Manufacturing & Wholesale Goods"
        }
    ],
    "sg:phone":"+61 2 8339 1039",
    "sg:postcode":"2009",
    "sg:province":"NSW",
    "sg:tags":[
        "function",
        "catering"
    ],
    "wof:name":"Lishas Catering",
    "wof:placetype":"venue"
},
  "geometry": {"coordinates":[151.19696044899999,-33.8749237061],"type":"Point"}
}