{
  "type": "Feature",
  "properties": {
    "iso:country":"AU",
    "sg:address":"237 Charters Towers Rd",
    "sg:city":"Hermit Park",
    "sg:classifiers":[
        {
            "category":"Wholesale",
            "subcategory":"Medical Equipment & Supplies",
            "type":"Manufacturing & Wholesale Goods"
        }
    ],
    "sg:phone":"+61 7 4725 2195",
    "sg:postcode":"4812",
    "sg:province":"QLD",
    "sg:tags":[
        "aid",
        "care",
        "health",
        "home"
    ],
    "wof:name":"Scooters",
    "wof:placetype":"venue"
},
  "geometry": {"coordinates":[146.79669200000001,-19.287279],"type":"Point"}
}