{
  "type": "Feature",
  "properties": {
    "addr:full":"78 North East Rd Walkerville SA 5081",
    "addr:housenumber":"78",
    "addr:postcode":"5081",
    "addr:street":"North East Rd",
    "iso:country":"AU",
    "sg:address":"78 North East Rd",
    "sg:city":"Walkerville",
    "sg:classifiers":[
        {
            "category":"Retail",
            "subcategory":"Auto Repair",
            "type":"Services"
        }
    ],
    "sg:phone":"+61 8 8265 9555",
    "sg:postcode":"5081",
    "sg:province":"SA",
    "sg:tags":[
        "repairer",
        "motor",
        "engineer"
    ],
    "wof:name":"Formula Honda",
    "wof:placetype":"venue"
},
  "geometry": {"coordinates":[138.61163330100001,-34.8910751343],"type":"Point"}
}