{
  "type": "Feature",
  "properties": {
    "iso:country":"AU",
    "sg:address":"3 Burden St",
    "sg:city":"Glenelg North",
    "sg:classifiers":[
        {
            "category":"Banks & Credit Unions",
            "subcategory":"Bank",
            "type":"Services"
        }
    ],
    "sg:phone":"+61 1300 361 805",
    "sg:postcode":"5045",
    "sg:province":"SA",
    "sg:tags":[
        "broker",
        "mortgage"
    ],
    "wof:name":"Mortgage Care",
    "wof:placetype":"venue"
},
  "geometry": {"coordinates":[138.5224,-34.971661],"type":"Point"}
}