{
  "type": "Feature",
  "properties": {
    "iso:country":"AU",
    "sg:address":"53c Playford Ave",
    "sg:city":"Whyalla Playford",
    "sg:classifiers":[
        {
            "category":"Health Services",
            "subcategory":"Doctor",
            "type":"Services"
        }
    ],
    "sg:phone":"+61 8 8645 0111",
    "sg:postcode":"5600",
    "sg:province":"SA",
    "sg:tags":[
        "medical",
        "practitioner"
    ],
    "wof:name":"Playford Clinic",
    "wof:placetype":"venue"
},
  "geometry": {"coordinates":[137.566818,-33.030563],"type":"Point"}
}