{
  "type": "Feature",
  "properties": {
    "addr:full":"145 Princes Hwy St Peters NSW 2044",
    "addr:housenumber":"145",
    "addr:postcode":"2044",
    "addr:street":"Princes Hwy",
    "iso:country":"AU",
    "sg:address":"145 Princes Hwy St",
    "sg:city":"Peters",
    "sg:classifiers":[
        {
            "category":"Banks & Credit Unions",
            "subcategory":"Investment Brokerage",
            "type":"Services"
        }
    ],
    "sg:phone":"+61 2 9590 8306",
    "sg:postcode":"2044",
    "sg:province":"NSW",
    "sg:tags":[
        "mfrg",
        "wholesale",
        "product",
        "sheepskin"
    ],
    "wof:name":"Australian Black Sheep",
    "wof:placetype":"venue"
},
  "geometry": {"coordinates":[151.179001,-33.912609],"type":"Point"}
}