{
  "type": "Feature",
  "properties": {
    "addr:full":"79 Hannah St Beecroft NSW 2119",
    "addr:housenumber":"79",
    "addr:postcode":"2119",
    "addr:street":"Hannah St",
    "iso:country":"AU",
    "sg:address":"79 Hannah St",
    "sg:city":"Beecroft",
    "sg:classifiers":[
        {
            "category":"Building & Trades",
            "subcategory":"Construction",
            "type":"Services"
        }
    ],
    "sg:phone":"+61 2 9980 6266",
    "sg:postcode":"2119",
    "sg:province":"NSW",
    "sg:tags":[
        "pool",
        "swimming"
    ],
    "wof:name":"Traditional Pools",
    "wof:placetype":"venue"
},
  "geometry": {"coordinates":[151.05487060600001,-33.7511177063],"type":"Point"}
}