{
  "type": "Feature",
  "properties": {
    "addr:full":"365 St Pauls Tce Fortitude Valley QLD 4006",
    "addr:housenumber":"365",
    "addr:postcode":"4006",
    "addr:street":"St Pauls Tce",
    "iso:country":"AU",
    "sg:address":"365 St",
    "sg:city":"Pauls Tce Fortitude Valley",
    "sg:classifiers":[
        {
            "category":"Professional",
            "subcategory":"Art Services",
            "type":"Services"
        }
    ],
    "sg:phone":"+61 7 3852 2525",
    "sg:postcode":"4006",
    "sg:province":"QLD",
    "sg:tags":[
        "interior",
        "designer"
    ],
    "wof:name":"Bligh Voller Nield Pty Ltd",
    "wof:placetype":"venue"
},
  "geometry": {"coordinates":[153.03239440900001,-27.4553966522],"type":"Point"}
}