{
  "type": "Feature",
  "properties": {
    "addr:full":"Young St Randwick NSW 2031",
    "addr:postcode":"2031",
    "addr:street":"Young St",
    "iso:country":"AU",
    "sg:address":"Young St",
    "sg:city":"Randwick",
    "sg:classifiers":[
        {
            "category":"Insurance",
            "subcategory":"Insurance Agent",
            "type":"Services"
        }
    ],
    "sg:phone":"+61 2 9399 7999",
    "sg:postcode":"2031",
    "sg:province":"NSW",
    "sg:tags":[
        "bloodstock"
    ],
    "wof:name":"William Inglis & Son Ltd",
    "wof:placetype":"venue"
},
  "geometry": {"coordinates":[151.23747253400001,-33.9216690063],"type":"Point"}
}