{
  "type": "Feature",
  "properties": {
    "addr:full":"179 Scenic Hwy Terrigal NSW 2260",
    "addr:housenumber":"179",
    "addr:postcode":"2260",
    "addr:street":"Scenic Hwy",
    "iso:country":"AU",
    "sg:address":"179 Scenic Hwy",
    "sg:city":"Terrigal",
    "sg:classifiers":[
        {
            "category":"Health Services",
            "subcategory":"Health Practitioner",
            "type":"Services"
        }
    ],
    "sg:phone":"+61 2 4385 5960",
    "sg:postcode":"2260",
    "sg:province":"NSW",
    "sg:tags":[
        "pathologist",
        "speech"
    ],
    "wof:name":"Laurence Annemarie",
    "wof:placetype":"venue"
},
  "geometry": {"coordinates":[151.435059,-33.448742],"type":"Point"}
}