{
  "type": "Feature",
  "properties": {
    "addr:full":"812 Stanley St Woolloongabba QLD 4102",
    "addr:housenumber":"812",
    "addr:postcode":"4102",
    "addr:street":"Stanley St",
    "iso:country":"AU",
    "sg:address":"812 Stanley St",
    "sg:city":"Woolloongabba",
    "sg:classifiers":[
        {
            "category":"Health Services",
            "subcategory":"Doctor",
            "type":"Services"
        }
    ],
    "sg:phone":"+61 7 3891 2000",
    "sg:postcode":"4102",
    "sg:province":"QLD",
    "sg:tags":[
        "podiatrist"
    ],
    "wof:name":"Eadie Podiatry",
    "wof:placetype":"venue"
},
  "geometry": {"coordinates":[153.03541564899999,-27.4866447449],"type":"Point"}
}