{
  "type": "Feature",
  "properties": {
    "addr:full":"Office No. 1 His Majestys La Perth WA 6000",
    "addr:postcode":"6000",
    "iso:country":"AU",
    "sg:address":"Office No. 1 His Majestys La",
    "sg:city":"Perth",
    "sg:classifiers":[
        {
            "category":"Retail",
            "subcategory":"Storage",
            "type":"Services"
        }
    ],
    "sg:phone":"+61 500 889 725",
    "sg:postcode":"6000",
    "sg:province":"WA",
    "sg:tags":[
        "removal",
        "furniture"
    ],
    "wof:name":"A AAA Maylands Mini Storage Units",
    "wof:placetype":"venue"
},
  "geometry": {"coordinates":[115.85415649399999,-31.9529247284],"type":"Point"}
}