{
  "type": "Feature",
  "properties": {
    "addr:full":"51 Vincent St Cessnock NSW 2325",
    "addr:housenumber":"51",
    "addr:postcode":"2325",
    "addr:street":"Vincent St",
    "iso:country":"AU",
    "sg:address":"51 Vincent St",
    "sg:city":"Cessnock",
    "sg:classifiers":[
        {
            "category":"Real Estate",
            "subcategory":"Real Estate Agent",
            "type":"Services"
        }
    ],
    "sg:phone":"+61 2 4990 5333",
    "sg:postcode":"2325",
    "sg:province":"NSW",
    "wof:name":"L J Hooker",
    "wof:placetype":"venue"
},
  "geometry": {"coordinates":[151.35643005399999,-32.833366394],"type":"Point"}
}