{
  "type": "Feature",
  "properties": {
    "addr:full":"108 Gladstone St Fyshwick ACT 2609",
    "addr:housenumber":"108",
    "addr:postcode":"2609",
    "addr:street":"Gladstone St",
    "iso:country":"AU",
    "sg:address":"108 Gladstone St",
    "sg:city":"Fyshwick",
    "sg:classifiers":[
        {
            "category":"Personal",
            "subcategory":"Adult",
            "type":"Services"
        }
    ],
    "sg:phone":"+61 2 6280 8002",
    "sg:postcode":"2609",
    "sg:province":"ACT",
    "sg:tags":[
        "vic",
        "except",
        "state",
        "escort",
        "social",
        "qld"
    ],
    "wof:name":"Victoria-Lace",
    "wof:placetype":"venue"
},
  "geometry": {"coordinates":[149.18066406200001,-35.3229217529],"type":"Point"}
}