{
  "type": "Feature",
  "properties": {
    "addr:full":"28 Sharland Ave Chatswood NSW 2067",
    "addr:housenumber":"28",
    "addr:postcode":"2067",
    "addr:street":"Sharland Ave",
    "iso:country":"AU",
    "sg:address":"28 Sharland Ave",
    "sg:city":"Chatswood",
    "sg:classifiers":[
        {
            "category":"Real Estate",
            "subcategory":"Real Estate Services",
            "type":"Services"
        }
    ],
    "sg:phone":"+61 2 9413 1114",
    "sg:postcode":"2067",
    "sg:province":"NSW",
    "sg:tags":[
        "consultant",
        "property"
    ],
    "wof:name":"Mottek & Associates Pty Ltd",
    "wof:placetype":"venue"
},
  "geometry": {"coordinates":[151.17471313499999,-33.8055381775],"type":"Point"}
}