{
  "type": "Feature",
  "properties": {
    "addr:full":"110 Montague St North Wollongong NSW 2500",
    "addr:housenumber":"110",
    "addr:postcode":"2500",
    "addr:street":"Montague St North",
    "iso:country":"AU",
    "sg:address":"110 Montague St",
    "sg:city":"North Wollongong",
    "sg:classifiers":[
        {
            "category":"Shopping",
            "subcategory":"Clothing, Apparel, & Fashions",
            "type":"Retail Goods"
        }
    ],
    "sg:phone":"+61 2 4229 7919",
    "sg:postcode":"2500",
    "sg:province":"NSW",
    "sg:tags":[
        "recycled",
        "clothing"
    ],
    "wof:name":"St Vincent De Paul Socy",
    "wof:placetype":"venue"
},
  "geometry": {"coordinates":[150.894226,-34.410522],"type":"Point"}
}