{
  "type": "Feature",
  "properties": {
    "addr:full":"Lot 12 Old Kildonan Rd Goondiwindi QLD 4390",
    "addr:postcode":"4390",
    "addr:street":"Old Kildonan Rd",
    "iso:country":"AU",
    "sg:address":"Lot 12 Old Kildonan Rd",
    "sg:city":"Goondiwindi",
    "sg:classifiers":[
        {
            "category":"Professional",
            "subcategory":"Business Services",
            "type":"Services"
        }
    ],
    "sg:phone":"+61 7 4671 3937",
    "sg:postcode":"4390",
    "sg:province":"QLD",
    "sg:tags":[
        "livestock",
        "transport"
    ],
    "wof:name":"Hottes Norm Transport",
    "wof:placetype":"venue"
},
  "geometry": {"coordinates":[150.324386597,-28.5513782501],"type":"Point"}
}