{
  "type": "Feature",
  "properties": {
    "addr:full":"7 Glen St Harbord NSW 2096",
    "addr:housenumber":"7",
    "addr:postcode":"2096",
    "addr:street":"Glen St",
    "iso:country":"AU",
    "sg:address":"7 Glen St",
    "sg:city":"Harbord",
    "sg:classifiers":[
        {
            "category":"Utilities",
            "subcategory":"Electric",
            "type":"Services"
        }
    ],
    "sg:phone":"+61 2 9905 0959",
    "sg:postcode":"2096",
    "sg:province":"NSW",
    "sg:tags":[
        "electrical",
        "contractor"
    ],
    "wof:name":"Gillard Mark Electrical Services",
    "wof:placetype":"venue"
},
  "geometry": {"coordinates":[151.28512573200001,-33.7767829895],"type":"Point"}
}