{
  "type": "Feature",
  "properties": {
    "addr:full":"26 Walbrook Drv Vermont South VIC 3133",
    "addr:housenumber":"26",
    "addr:postcode":"3133",
    "addr:street":"Walbrook Drv",
    "iso:country":"AU",
    "sg:address":"26 Walbrook Drv",
    "sg:city":"Vermont South",
    "sg:classifiers":[
        {
            "category":"Health Services",
            "subcategory":"Health Practitioner",
            "type":"Services"
        }
    ],
    "sg:phone":"+61 3 9802 2668",
    "sg:postcode":"3133",
    "sg:province":"VIC",
    "sg:tags":[
        "physiotherapist"
    ],
    "wof:name":"Durrant Phillipa",
    "wof:placetype":"venue"
},
  "geometry": {"coordinates":[145.18046569800001,-37.8464355469],"type":"Point"}
}