{
  "type": "Feature",
  "properties": {
    "addr:full":"2 Effingham St Mosman NSW 2088",
    "addr:housenumber":"2",
    "addr:postcode":"2088",
    "addr:street":"Effingham St",
    "iso:country":"AU",
    "sg:address":"2 Effingham St",
    "sg:city":"Mosman",
    "sg:classifiers":[
        {
            "category":"Health Services",
            "subcategory":"Health Practitioner",
            "type":"Services"
        }
    ],
    "sg:phone":"+61 2 9960 2135",
    "sg:postcode":"2088",
    "sg:province":"NSW",
    "sg:tags":[
        "physiotherapist"
    ],
    "wof:name":"Roberts Pamela",
    "wof:placetype":"venue"
},
  "geometry": {"coordinates":[151.24597168,-33.8345146179],"type":"Point"}
}