{
  "type": "Feature",
  "properties": {
    "iso:country":"AU",
    "sg:address":"3 William St",
    "sg:city":"Hawthorn",
    "sg:classifiers":[
        {
            "category":"Food & Beverages",
            "subcategory":"Groceries & Convenience Stores",
            "type":"Retail Goods"
        }
    ],
    "sg:phone":"+61 3 9818 1068",
    "sg:postcode":"3122",
    "sg:province":"VIC",
    "wof:name":"Hardys General Store",
    "wof:placetype":"venue"
},
  "geometry": {"coordinates":[145.040527344,-37.8195343018],"type":"Point"}
}