{
  "type": "Feature",
  "properties": {
    "addr:full":"56 Errol St North Melbourne VIC 3051",
    "addr:housenumber":"56",
    "addr:postcode":"3051",
    "addr:street":"Errol St",
    "iso:country":"AU",
    "sg:address":"56 Errol St",
    "sg:city":"North Melbourne",
    "sg:classifiers":[
        {
            "category":"Health Services",
            "subcategory":"Optometrist",
            "type":"Services"
        }
    ],
    "sg:phone":"+61 3 9329 9372",
    "sg:postcode":"3051",
    "sg:province":"VIC",
    "wof:name":"Andrew Harris",
    "wof:placetype":"venue"
},
  "geometry": {"coordinates":[144.949676514,-37.8037643433],"type":"Point"}
}