{
  "type": "Feature",
  "properties": {
    "addr:full":"11 Lunar Crs Noosa Heads QLD 4567",
    "addr:housenumber":"11",
    "addr:postcode":"4567",
    "addr:street":"Lunar Crs",
    "iso:country":"AU",
    "sg:address":"11 Lunar Crs",
    "sg:city":"Noosa Heads",
    "sg:classifiers":[
        {
            "category":"Arts & Performance",
            "subcategory":"Dance",
            "type":"Entertainment"
        }
    ],
    "sg:phone":"+61 7 5447 5384",
    "sg:postcode":"4567",
    "sg:province":"QLD",
    "sg:tags":[
        "theatrical",
        "ballet",
        "tuition"
    ],
    "wof:name":"Australian Dance Assessment Programme",
    "wof:placetype":"venue"
},
  "geometry": {"coordinates":[153.086105347,-26.3990192413],"type":"Point"}
}