{
  "type": "Feature",
  "properties": {
    "iso:country":"AU",
    "sg:address":"116 Winston Ave",
    "sg:city":"Melrose Park",
    "sg:classifiers":[
        {
            "category":"Personal",
            "subcategory":"Beauty Salon",
            "type":"Services"
        }
    ],
    "sg:phone":"+61 8 8177 0811",
    "sg:postcode":"5039",
    "sg:province":"SA",
    "sg:tags":[
        "hairdresser"
    ],
    "wof:name":"Platinum Scissors",
    "wof:placetype":"venue"
},
  "geometry": {"coordinates":[138.583053589,-34.9858131409],"type":"Point"}
}