{
  "type": "Feature",
  "properties": {
    "iso:country":"AU",
    "sg:address":"Koraba Rd",
    "sg:city":"Seisia",
    "sg:classifiers":[
        {
            "category":"Communications",
            "subcategory":"News Services",
            "type":"Services"
        }
    ],
    "sg:phone":"+61 7 4069 3243",
    "sg:postcode":"4876",
    "sg:province":"QLD",
    "sg:tags":[
        "information",
        "tourist",
        "attractions"
    ],
    "wof:name":"Seisia Holiday Park",
    "wof:placetype":"venue"
},
  "geometry": {"coordinates":[142.36856079099999,-10.8480701447],"type":"Point"}
}