{
  "type": "Feature",
  "properties": {
    "addr:full":"Suite 2 Kearns Shopping Centre Kearns NSW 2558",
    "addr:postcode":"2558",
    "iso:country":"AU",
    "sg:address":"Suite 2 Kearns Shopping Centre",
    "sg:city":"Kearns",
    "sg:classifiers":[
        {
            "category":"Education",
            "subcategory":"Special Training",
            "type":"Public Place"
        }
    ],
    "sg:phone":"+61 2 9820 2935",
    "sg:postcode":"2558",
    "sg:province":"NSW",
    "sg:tags":[
        "tuition-educational"
    ],
    "wof:name":"Kip McGrath Education Centre",
    "wof:placetype":"venue"
},
  "geometry": {"coordinates":[150.80958557100001,-34.0196151733],"type":"Point"}
}