{
  "type": "Feature",
  "properties": {
    "addr:full":"Bellfield Drv Lysterfield VIC 3156",
    "addr:postcode":"3156",
    "addr:street":"Bellfield Drv",
    "iso:country":"AU",
    "sg:address":"Bellfield Drv",
    "sg:city":"Lysterfield",
    "sg:classifiers":[
        {
            "category":"Education",
            "subcategory":"School",
            "type":"Public Place"
        }
    ],
    "sg:phone":"+61 3 9752 7953",
    "sg:postcode":"3156",
    "sg:province":"VIC",
    "sg:tags":[
        "state",
        "except",
        "nsw"
    ],
    "wof:name":"Lysterfield Primary",
    "wof:placetype":"venue"
},
  "geometry": {"coordinates":[145.27552795400001,-37.9152603149],"type":"Point"}
}