{
  "type": "Feature",
  "properties": {
    "addr:full":"Suite 202, 2nd Floor, 661 George St Sydney NSW 2000",
    "addr:housenumber":"661",
    "addr:postcode":"2000",
    "addr:street":"George St",
    "iso:country":"AU",
    "sg:address":"Suite 202, 2nd Floor, 661 George St",
    "sg:city":"Sydney",
    "sg:classifiers":[
        {
            "category":"Government",
            "subcategory":"Fire Station",
            "type":"Public Place"
        }
    ],
    "sg:phone":"+61 2 9212 2772",
    "sg:postcode":"2000",
    "sg:province":"NSW",
    "sg:tags":[
        "equipment",
        "protection",
        "consultant"
    ],
    "wof:name":"Atlas Fire Safety Technology",
    "wof:placetype":"venue"
},
  "geometry": {"coordinates":[151.205352783,-33.8791313171],"type":"Point"}
}