{
  "type": "Feature",
  "properties": {
    "addr:full":"20 Hamilton Ave Blackburn VIC 3130",
    "addr:housenumber":"20",
    "addr:postcode":"3130",
    "addr:street":"Hamilton Ave",
    "iso:country":"AU",
    "sg:address":"20 Hamilton Ave",
    "sg:city":"Blackburn",
    "sg:classifiers":[
        {
            "category":"Building & Trades",
            "subcategory":"Cleaning & Sanitation",
            "type":"Services"
        }
    ],
    "sg:phone":"+61 417 986 532",
    "sg:postcode":"3130",
    "sg:province":"VIC",
    "sg:tags":[
        "industrial",
        "commercial",
        "contractor"
    ],
    "wof:name":"Easyclean",
    "wof:placetype":"venue"
},
  "geometry": {"coordinates":[145.144775391,-37.8142738342],"type":"Point"}
}