{
  "type": "Feature",
  "properties": {
    "addr:full":"5 Riseley Crt Lenah Valley TAS 7008",
    "addr:housenumber":"5",
    "addr:postcode":"7008",
    "addr:street":"Riseley Crt",
    "iso:country":"AU",
    "sg:address":"5 Riseley Crt",
    "sg:city":"Lenah Valley",
    "sg:classifiers":[
        {
            "category":"Professional",
            "subcategory":"Art Services",
            "type":"Services"
        }
    ],
    "sg:phone":"+61 3 6228 1419",
    "sg:postcode":"7008",
    "sg:province":"TAS",
    "sg:tags":[
        "decorator",
        "painter"
    ],
    "wof:name":"Calabrese V & P",
    "wof:placetype":"venue"
},
  "geometry": {"coordinates":[147.275680542,-42.8582077026],"type":"Point"}
}