{
  "type": "Feature",
  "properties": {
    "iso:country":"AU",
    "sg:address":"267 Lygon St",
    "sg:city":"Carlton",
    "sg:classifiers":[
        {
            "category":"Manufacturing",
            "subcategory":"Textiles",
            "type":"Manufacturing & Wholesale Goods"
        }
    ],
    "sg:phone":"+61 1300 301 934",
    "sg:postcode":"3053",
    "sg:province":"VIC",
    "sg:tags":[
        "dyer"
    ],
    "wof:name":"Denim Doctor",
    "wof:placetype":"venue"
},
  "geometry": {"coordinates":[144.967041016,-37.7991447449],"type":"Point"}
}