{
  "type": "Feature",
  "properties": {
    "addr:full":"16 Thomas St Meringandan QLD 4352",
    "addr:housenumber":"16",
    "addr:postcode":"4352",
    "addr:street":"Thomas St",
    "iso:country":"AU",
    "sg:address":"16 Thomas St",
    "sg:city":"Meringandan",
    "sg:classifiers":[
        {
            "category":"Shopping",
            "subcategory":"Musical Instruments",
            "type":"Retail Goods"
        }
    ],
    "sg:phone":"+61 413 612 816",
    "sg:postcode":"4352",
    "sg:province":"QLD",
    "sg:tags":[
        "musician",
        "agent"
    ],
    "wof:name":"D.J. Mouse",
    "wof:placetype":"venue"
},
  "geometry": {"coordinates":[151.890579,-27.421093],"type":"Point"}
}