{
  "type": "Feature",
  "properties": {
    "addr:full":"Ground Floor, 95 Queen St Melbourne VIC 3000",
    "addr:housenumber":"95",
    "addr:postcode":"3000",
    "addr:street":"Queen St",
    "iso:country":"AU",
    "sg:address":"Ground Floor, 95 Queen St",
    "sg:city":"Melbourne",
    "sg:classifiers":[
        {
            "category":"Ice Cream",
            "type":"Food & Drink"
        }
    ],
    "sg:phone":"+61 3 9640 0940",
    "sg:postcode":"3000",
    "sg:province":"VIC",
    "sg:tags":[
        "specialised",
        "fitting",
        "lady",
        "wear"
    ],
    "wof:name":"Zentini",
    "wof:placetype":"venue"
},
  "geometry": {"coordinates":[144.96115112300001,-37.8163070679],"type":"Point"}
}