{
  "type": "Feature",
  "properties": {
    "iso:country":"AU",
    "sg:address":"Level 7/ 6 Underwood St",
    "sg:city":"Sydney",
    "sg:classifiers":[
        {
            "category":"Banks & Credit Unions",
            "subcategory":"Financial Services",
            "type":"Services"
        }
    ],
    "sg:phone":"+61 2 9247 7126",
    "sg:postcode":"2000",
    "sg:province":"NSW",
    "sg:tags":[
        "merchant",
        "banker"
    ],
    "wof:name":"Pacific Capital Corporation Ltd",
    "wof:placetype":"venue"
},
  "geometry": {"coordinates":[151.20831298799999,-33.8628044128],"type":"Point"}
}