{
  "type": "Feature",
  "properties": {
    "addr:full":"1, 22 Portside Crs Wickham NSW 2293",
    "addr:housenumber":"22",
    "addr:postcode":"2293",
    "addr:street":"1;Portside Crs",
    "iso:country":"AU",
    "sg:address":"1, 22 Portside Crs",
    "sg:city":"Wickham",
    "sg:classifiers":[
        {
            "category":"Government",
            "subcategory":"Customs House",
            "type":"Public Place"
        }
    ],
    "sg:phone":"+61 2 4962 4433",
    "sg:postcode":"2293",
    "sg:province":"NSW",
    "sg:tags":[
        "title",
        "management",
        "stratum"
    ],
    "sg:website":"http://www.cstm.com.au",
    "wof:name":"Community & Strata Title Management",
    "wof:placetype":"venue"
},
  "geometry": {"coordinates":[151.75743102999999,-32.9193992615],"type":"Point"}
}