{
  "type": "Feature",
  "properties": {
    "addr:full":"15 Martin Drv Ballarat VIC 3350",
    "addr:housenumber":"15",
    "addr:postcode":"3350",
    "addr:street":"Martin Drv",
    "iso:country":"AU",
    "sg:address":"15 Martin Drv",
    "sg:city":"Ballarat",
    "sg:classifiers":[
        {
            "category":"Wholesale",
            "subcategory":"Machinery & Supplies",
            "type":"Manufacturing & Wholesale Goods"
        }
    ],
    "sg:phone":"+61 3 5335 5235",
    "sg:postcode":"3350",
    "sg:province":"VIC",
    "sg:tags":[
        "agricultural"
    ],
    "wof:name":"B.R.H. Enterprises Pty Ltd",
    "wof:placetype":"venue"
},
  "geometry": {"coordinates":[143.841644,-37.543461],"type":"Point"}
}