{
  "type": "Feature",
  "properties": {
    "iso:country":"AU",
    "sg:address":"215 Flinders St",
    "sg:city":"Melbourne",
    "sg:classifiers":[
        {
            "category":"Shopping",
            "subcategory":"Jewelry",
            "type":"Retail Goods"
        }
    ],
    "sg:phone":"+61 3 9620 0750",
    "sg:postcode":"3000",
    "sg:province":"VIC",
    "sg:tags":[
        "jeweller"
    ],
    "wof:name":"Larama",
    "wof:placetype":"venue"
},
  "geometry": {"coordinates":[144.96685790999999,-37.8177528381],"type":"Point"}
}