{
  "type": "Feature",
  "properties": {
    "addr:full":"495 Blackburn Rd Mt Waverley VIC 3149",
    "addr:housenumber":"495",
    "addr:postcode":"3149",
    "addr:street":"Blackburn Rd",
    "iso:country":"AU",
    "sg:address":"495 Blackburn Rd",
    "sg:city":"Mt Waverley",
    "sg:classifiers":[
        {
            "category":"Professional",
            "subcategory":"Detective & Security Services",
            "type":"Services"
        }
    ],
    "sg:phone":"+61 3 9211 7000",
    "sg:postcode":"3149",
    "sg:province":"VIC",
    "sg:tags":[
        "consultant",
        "system"
    ],
    "wof:name":"Vision Systems Limited",
    "wof:placetype":"venue"
},
  "geometry": {"coordinates":[145.14364624000001,-37.8963241577],"type":"Point"}
}