{
  "type": "Feature",
  "properties": {
    "addr:full":"Shop T9, Direct Factory Outlets, 250 Centre Dandenong Road, Cheltenham Cheltenham VIC 3192",
    "addr:housenumber":"250",
    "addr:postcode":"3192",
    "addr:street":"Outlets;Dandenong Road",
    "iso:country":"AU",
    "sg:address":"Shop T9, Direct Factory Outlets, 250 Centre Dandenong Road, Cheltenham",
    "sg:city":"Cheltenham",
    "sg:classifiers":[
        {
            "category":"Retail",
            "subcategory":"Repair Shop",
            "type":"Services"
        }
    ],
    "sg:phone":"+61 3 9584 7922",
    "sg:postcode":"3192",
    "sg:province":"VIC",
    "sg:tags":[
        "handbag"
    ],
    "wof:name":"Katehill",
    "wof:placetype":"venue"
},
  "geometry": {"coordinates":[145.086700439,-37.9693908691],"type":"Point"}
}