{
  "type": "Feature",
  "properties": {
    "addr:full":"52 Parramatta Rd Forest Lodge NSW 2037",
    "addr:housenumber":"52",
    "addr:postcode":"2037",
    "addr:street":"Parramatta Rd",
    "iso:country":"AU",
    "sg:address":"52 Parramatta Rd",
    "sg:city":"Forest Lodge",
    "sg:classifiers":[
        {
            "category":"Building & Trades",
            "subcategory":"Construction",
            "type":"Services"
        }
    ],
    "sg:phone":"+61 2 9660 7188",
    "sg:postcode":"2037",
    "sg:province":"NSW",
    "sg:tags":[
        "contractor"
    ],
    "wof:name":"Dial -A-Master Builder",
    "wof:placetype":"venue"
},
  "geometry": {"coordinates":[151.183303833,-33.885181427],"type":"Point"}
}