{
  "type": "Feature",
  "properties": {
    "addr:full":"13 Holden St Buranda QLD 4102",
    "addr:housenumber":"13",
    "addr:postcode":"4102",
    "addr:street":"Holden St",
    "iso:country":"AU",
    "sg:address":"13 Holden St",
    "sg:city":"Buranda",
    "sg:classifiers":[
        {
            "category":"Farming",
            "subcategory":"Fish & Marine Products",
            "type":"Manufacturing & Wholesale Goods"
        }
    ],
    "sg:phone":"+61 7 3891 5969",
    "sg:postcode":"4102",
    "sg:province":"QLD",
    "sg:tags":[
        "supplier",
        "oyster",
        "farmer"
    ],
    "wof:name":"Troyco Pty Ltd",
    "wof:placetype":"venue"
},
  "geometry": {"coordinates":[153.04153442399999,-27.4908943176],"type":"Point"}
}