{
  "type": "Feature",
  "properties": {
    "iso:country":"AU",
    "sg:address":"8 King St",
    "sg:city":"Caboolture",
    "sg:classifiers":[
        {
            "category":"Professional",
            "subcategory":"Printing & Photocopies",
            "type":"Services"
        }
    ],
    "sg:phone":"+61 7 5495 5266",
    "sg:postcode":"4510",
    "sg:province":"QLD",
    "sg:tags":[
        "rubber",
        "stamp",
        "metal"
    ],
    "wof:name":"Sunshine Office Supplies (Northside)",
    "wof:placetype":"venue"
},
  "geometry": {"coordinates":[152.95356799999999,-27.084782],"type":"Point"}
}