{
  "type": "Feature",
  "properties": {
    "addr:full":"40 Ross St Forest Lodge NSW 2037",
    "addr:housenumber":"40",
    "addr:postcode":"2037",
    "addr:street":"Ross St",
    "iso:country":"AU",
    "sg:address":"40 Ross St",
    "sg:city":"Forest Lodge",
    "sg:classifiers":[
        {
            "category":"Food & Beverages",
            "subcategory":"Fruits & Vegetables",
            "type":"Retail Goods"
        }
    ],
    "sg:phone":"+61 2 9660 9665",
    "sg:postcode":"2037",
    "sg:province":"NSW",
    "sg:tags":[
        "greengrocer",
        "fruiterer"
    ],
    "wof:name":"Nissa Fruit And Vegies",
    "wof:placetype":"venue"
},
  "geometry": {"coordinates":[151.18258667000001,-33.8828048706],"type":"Point"}
}