{
  "type": "Feature",
  "properties": {
    "iso:country":"AU",
    "sg:address":"101 Orange St",
    "sg:city":"Oakleigh South",
    "sg:classifiers":[
        {
            "category":"Personal",
            "subcategory":"Beauty Salon",
            "type":"Services"
        }
    ],
    "sg:phone":"+61 3 9563 8000",
    "sg:postcode":"3167",
    "sg:province":"VIC",
    "sg:tags":[
        "hairdresser"
    ],
    "wof:name":"Danielle Hair Fashions",
    "wof:placetype":"venue"
},
  "geometry": {"coordinates":[145.08334350600001,-37.9179840088],"type":"Point"}
}