{
  "type": "Feature",
  "properties": {
    "addr:full":"9 Drew St Armidale NSW 2350",
    "addr:housenumber":"9",
    "addr:postcode":"2350",
    "addr:street":"Drew St",
    "iso:country":"AU",
    "sg:address":"9 Drew St",
    "sg:city":"Armidale",
    "sg:classifiers":[
        {
            "category":"Building & Trades",
            "subcategory":"Plumbing",
            "type":"Services"
        }
    ],
    "sg:phone":"+61 2 6772 2030",
    "sg:postcode":"2350",
    "sg:province":"NSW",
    "sg:tags":[
        "fitting",
        "hose",
        "supply"
    ],
    "wof:name":"Hosecomatic Australia",
    "wof:placetype":"venue"
},
  "geometry": {"coordinates":[151.644073486,-30.5108985901],"type":"Point"}
}