{
  "type": "Feature",
  "properties": {
    "addr:full":"280 Church St Newtown NSW 2042",
    "addr:housenumber":"280",
    "addr:postcode":"2042",
    "addr:street":"Church St",
    "iso:country":"AU",
    "sg:address":"280 Church St",
    "sg:city":"Newtown",
    "sg:classifiers":[
        {
            "category":"Health Services",
            "subcategory":"Doctor",
            "type":"Services"
        }
    ],
    "sg:phone":"+61 2 9516 2944",
    "sg:postcode":"2042",
    "sg:province":"NSW",
    "sg:tags":[
        "medical",
        "practitioner"
    ],
    "wof:name":"Sahade Myfanwy",
    "wof:placetype":"venue"
},
  "geometry": {"coordinates":[151.180984,-33.894886],"type":"Point"}
}