{
  "type": "Feature",
  "properties": {
    "iso:country":"AU",
    "sg:address":"Unit 19/ 174 Willoughby Rd",
    "sg:city":"Crows Nest",
    "sg:classifiers":[
        {
            "category":"Professional",
            "subcategory":"Business Services",
            "type":"Services"
        }
    ],
    "sg:phone":"+61 2 9437 6911",
    "sg:postcode":"2065",
    "sg:province":"NSW",
    "sg:tags":[
        "drafting"
    ],
    "wof:name":"Romeo Cad Drafting Pty Ltd",
    "wof:placetype":"venue"
},
  "geometry": {"coordinates":[151.200775147,-33.822177887],"type":"Point"}
}