{
  "type": "Feature",
  "properties": {
    "addr:full":"PO Box 310 Malvern VIC 3144",
    "addr:postcode":"3144",
    "iso:country":"AU",
    "sg:address":"PO Box 310",
    "sg:city":"Malvern",
    "sg:classifiers":[
        {
            "category":"Travel",
            "subcategory":"Hostel",
            "type":"Entertainment"
        }
    ],
    "sg:phone":"+61 3 9889 0211",
    "sg:postcode":"3144",
    "sg:province":"VIC",
    "sg:tags":[
        "home"
    ],
    "wof:name":"Tender Living Care (Vic) Pty Ltd",
    "wof:placetype":"venue"
},
  "geometry": {"coordinates":[145.03689575199999,-37.8525390625],"type":"Point"}
}