{
  "type": "Feature",
  "properties": {
    "iso:country":"AU",
    "sg:address":"3 Emerald St",
    "sg:city":"Cooroy",
    "sg:classifiers":[
        {
            "category":"Food & Beverages",
            "subcategory":"Supermarket",
            "type":"Retail Goods"
        }
    ],
    "sg:phone":"+61 7 5447 6061",
    "sg:postcode":"4563",
    "sg:province":"QLD",
    "sg:tags":[
        "grocery",
        "store"
    ],
    "wof:name":"Cooroy Supa IGA",
    "wof:placetype":"venue"
},
  "geometry": {"coordinates":[152.91000366200001,-26.4171600342],"type":"Point"}
}