{
  "type": "Feature",
  "properties": {
    "addr:full":"108 Old Pacific Hwy Oxenford QLD 4210",
    "addr:housenumber":"108",
    "addr:postcode":"4210",
    "addr:street":"Old Pacific Hwy",
    "iso:country":"AU",
    "sg:address":"108 Old Pacific Hwy",
    "sg:city":"Oxenford",
    "sg:classifiers":[
        {
            "category":"Real Estate",
            "subcategory":"Real Estate Agent",
            "type":"Services"
        }
    ],
    "sg:phone":"+61 7 5573 5533",
    "sg:postcode":"4210",
    "sg:province":"QLD",
    "wof:name":"Ray White Oxenford",
    "wof:placetype":"venue"
},
  "geometry": {"coordinates":[153.313842773,-27.8916625977],"type":"Point"}
}