{
  "type": "Feature",
  "properties": {
    "iso:country":"AU",
    "sg:address":"3 Bollen St",
    "sg:city":"Kilkenny",
    "sg:classifiers":[
        {
            "category":"Recreation",
            "subcategory":"Fishing",
            "type":"Entertainment"
        }
    ],
    "sg:phone":"+61 8 8244 9777",
    "sg:postcode":"5009",
    "sg:province":"SA",
    "sg:tags":[
        "tackle"
    ],
    "wof:name":"South Seas Tackle Wholesale",
    "wof:placetype":"venue"
},
  "geometry": {"coordinates":[138.556716919,-34.8782653809],"type":"Point"}
}