{
  "type": "Feature",
  "properties": {
    "addr:full":"89 Roslyn St Brighton VIC 3186",
    "addr:housenumber":"89",
    "addr:postcode":"3186",
    "addr:street":"Roslyn St",
    "iso:country":"AU",
    "sg:address":"89 Roslyn St",
    "sg:city":"Brighton",
    "sg:classifiers":[
        {
            "category":"Retail",
            "subcategory":"Storage",
            "type":"Services"
        }
    ],
    "sg:phone":"+61 3 9592 7756",
    "sg:postcode":"3186",
    "sg:province":"VIC",
    "sg:tags":[
        "removal",
        "furniture"
    ],
    "wof:name":"A. AAABA Taxi Trucks",
    "wof:placetype":"venue"
},
  "geometry": {"coordinates":[145.00292968799999,-37.9211387634],"type":"Point"}
}