{
  "type": "Feature",
  "properties": {
    "iso:country":"AU",
    "sg:address":"138 Wallarah Rd",
    "sg:city":"Gorokan",
    "sg:classifiers":[
        {
            "category":"Health Services",
            "subcategory":"Chiropractor",
            "type":"Services"
        }
    ],
    "sg:phone":"+61 2 4392 1825",
    "sg:postcode":"2263",
    "sg:province":"NSW",
    "wof:name":"Parker Gregory",
    "wof:placetype":"venue"
},
  "geometry": {"coordinates":[151.50633199999999,-33.255978],"type":"Point"}
}