{
  "type": "Feature",
  "properties": {
    "addr:full":"Unit 4/4 Vesper Drv Narre Warren VIC 3805",
    "addr:housenumber":"4",
    "addr:postcode":"3805",
    "addr:street":"Vesper Drv",
    "iso:country":"AU",
    "sg:address":"Unit 4/4 Vesper Drv",
    "sg:city":"Narre Warren",
    "sg:classifiers":[
        {
            "category":"Professional",
            "subcategory":"Printing & Photocopies",
            "type":"Services"
        }
    ],
    "sg:phone":"+61 3 8790 5611",
    "sg:postcode":"3805",
    "sg:province":"VIC",
    "sg:tags":[
        "photocopying"
    ],
    "wof:name":"Minuteman Press",
    "wof:placetype":"venue"
},
  "geometry": {"coordinates":[145.29676799999999,-38.020042],"type":"Point"}
}