{
  "type": "Feature",
  "properties": {
    "iso:country":"AU",
    "sg:address":"Redcliffe Jetty, Redcliffe Pde",
    "sg:city":"Redcliffe",
    "sg:classifiers":[
        {
            "category":"Retail",
            "subcategory":"Event Space",
            "type":"Services"
        }
    ],
    "sg:phone":"+61 7 3137 0111",
    "sg:postcode":"4020",
    "sg:province":"QLD",
    "sg:tags":[
        "venue",
        "reception",
        "wedding"
    ],
    "wof:name":"Eye Spy Events Company",
    "wof:placetype":"venue"
},
  "geometry": {"coordinates":[153.107224,-27.22217],"type":"Point"}
}