{
  "type": "Feature",
  "properties": {
    "addr:full":"26- 28 Old South Head Rd Rose Bay North NSW 2030",
    "addr:housenumber":"28",
    "addr:postcode":"2030",
    "addr:street":"Old South Head Rd",
    "iso:country":"AU",
    "sg:address":"26- 28 Old South Head Rd",
    "sg:city":"Rose Bay North",
    "sg:classifiers":[
        {
            "category":"Shopping",
            "subcategory":"Bicycles & Sporting Goods",
            "type":"Retail Goods"
        }
    ],
    "sg:phone":"+61 2 9388 8167",
    "sg:postcode":"2030",
    "sg:province":"NSW",
    "sg:tags":[
        "chemical",
        "equipment",
        "pool",
        "swimming"
    ],
    "wof:name":"Swimart Rosebay",
    "wof:placetype":"venue"
},
  "geometry": {"coordinates":[151.27830505399999,-33.8643074036],"type":"Point"}
}