{
  "type": "Feature",
  "properties": {
    "iso:country":"AU",
    "sg:address":"D Swamp Rd",
    "sg:city":"Gingin",
    "sg:classifiers":[
        {
            "category":"Professional",
            "subcategory":"Business Services",
            "type":"Services"
        }
    ],
    "sg:phone":"+61 8 9655 3074",
    "sg:postcode":"6503",
    "sg:province":"WA",
    "sg:tags":[
        "livestock",
        "transport"
    ],
    "wof:name":"Kimbolton Transport",
    "wof:placetype":"venue"
},
  "geometry": {"coordinates":[115.62657900000001,-31.208353],"type":"Point"}
}