{
  "type": "Feature",
  "properties": {
    "addr:full":"Level 1, Colonial Arcade, 25 Hay St Port Macquarie NSW 2444",
    "addr:housenumber":"25",
    "addr:postcode":"2444",
    "addr:street":"Hay St",
    "iso:country":"AU",
    "sg:address":"Level 1, Colonial Arcade, 25 Hay St",
    "sg:city":"Port Macquarie",
    "sg:classifiers":[
        {
            "category":"Government",
            "subcategory":"Customs House",
            "type":"Public Place"
        }
    ],
    "sg:phone":"+61 2 6583 6155",
    "sg:postcode":"2444",
    "sg:province":"NSW",
    "sg:tags":[
        "title",
        "management",
        "stratum"
    ],
    "wof:name":"SMS",
    "wof:placetype":"venue"
},
  "geometry": {"coordinates":[152.90939299999999,-31.430155],"type":"Point"}
}