{
  "type": "Feature",
  "properties": {
    "addr:full":"21 Crichton Rd Kyabram VIC 3620",
    "addr:housenumber":"21",
    "addr:postcode":"3620",
    "addr:street":"Crichton Rd",
    "iso:country":"AU",
    "sg:address":"21 Crichton Rd",
    "sg:city":"Kyabram",
    "sg:classifiers":[
        {
            "category":"Manufacturing",
            "subcategory":"Motor Vehicles & Parts",
            "type":"Manufacturing & Wholesale Goods"
        }
    ],
    "sg:phone":"+61 3 5852 3967",
    "sg:postcode":"3620",
    "sg:province":"VIC",
    "sg:tags":[
        "engine",
        "equipment",
        "diesel"
    ],
    "wof:name":"KY Truck & Tractor Repairs",
    "wof:placetype":"venue"
},
  "geometry": {"coordinates":[145.035644531,-36.3057250977],"type":"Point"}
}