{
  "type": "Feature",
  "properties": {
    "iso:country":"AU",
    "sg:address":"271 Norwood Pde",
    "sg:city":"Beulah Park",
    "sg:classifiers":[
        {
            "category":"Health Services",
            "subcategory":"Health Practitioner",
            "type":"Services"
        }
    ],
    "sg:phone":"+61 8 8331 7586",
    "sg:postcode":"5067",
    "sg:province":"SA",
    "sg:tags":[
        "physiotherapist"
    ],
    "wof:name":"Whitford Kevin",
    "wof:placetype":"venue"
},
  "geometry": {"coordinates":[138.642578125,-34.9147109985],"type":"Point"}
}