{
  "type": "Feature",
  "properties": {
    "addr:full":"305 Beach Rd Black Rock VIC 3193",
    "addr:housenumber":"305",
    "addr:postcode":"3193",
    "addr:street":"Beach Rd",
    "iso:country":"AU",
    "sg:address":"305 Beach Rd",
    "sg:city":"Black Rock",
    "sg:classifiers":[
        {
            "category":"Retail",
            "subcategory":"Event Space",
            "type":"Services"
        }
    ],
    "sg:phone":"+61 3 9589 6292",
    "sg:postcode":"3193",
    "sg:province":"VIC",
    "sg:tags":[
        "function",
        "organiser"
    ],
    "wof:name":"Risterante Sabatini",
    "wof:placetype":"venue"
},
  "geometry": {"coordinates":[145.01658630399999,-37.9765968323],"type":"Point"}
}