{
  "type": "Feature",
  "properties": {
    "addr:full":"219 Numurkah Rd Shepparton VIC 3630",
    "addr:housenumber":"219",
    "addr:postcode":"3630",
    "addr:street":"Numurkah Rd",
    "iso:country":"AU",
    "sg:address":"219 Numurkah Rd",
    "sg:city":"Shepparton",
    "sg:classifiers":[
        {
            "category":"Wholesale",
            "subcategory":"Machinery & Supplies",
            "type":"Manufacturing & Wholesale Goods"
        }
    ],
    "sg:phone":"+61 3 5820 9700",
    "sg:postcode":"3630",
    "sg:province":"VIC",
    "sg:tags":[
        "agricultural"
    ],
    "wof:name":"Haeuslers Shepparton",
    "wof:placetype":"venue"
},
  "geometry": {"coordinates":[145.40153503400001,-36.3498535156],"type":"Point"}
}