{
  "type": "Feature",
  "properties": {
    "iso:country":"AU",
    "sg:address":"Corner Heath & Watsons Rd",
    "sg:city":"Glen Waverley",
    "sg:classifiers":[
        {
            "category":"Education",
            "subcategory":"School",
            "type":"Public Place"
        }
    ],
    "sg:phone":"+61 3 8545 0300",
    "sg:postcode":"3150",
    "sg:province":"VIC",
    "sg:tags":[
        "state",
        "except",
        "nsw"
    ],
    "wof:name":"Brentwood Secondary College",
    "wof:placetype":"venue"
},
  "geometry": {"coordinates":[145.17015075699999,-37.890625],"type":"Point"}
}