{
  "type": "Feature",
  "properties": {
    "addr:full":"12 Franklin Ave Chelsea VIC 3196",
    "addr:housenumber":"12",
    "addr:postcode":"3196",
    "addr:street":"Franklin Ave",
    "iso:country":"AU",
    "sg:address":"12 Franklin Ave",
    "sg:city":"Chelsea",
    "sg:classifiers":[
        {
            "category":"Building & Trades",
            "subcategory":"Construction",
            "type":"Services"
        }
    ],
    "sg:phone":"+61 3 9772 1640",
    "sg:postcode":"3196",
    "sg:province":"VIC",
    "sg:tags":[
        "contractor"
    ],
    "wof:name":"Hildebrand Q L & L J Builders",
    "wof:placetype":"venue"
},
  "geometry": {"coordinates":[145.113189697,-38.0496902466],"type":"Point"}
}