{
  "type": "Feature",
  "properties": {
    "iso:country":"AU",
    "sg:address":"10 Bridge St",
    "sg:city":"Eltham",
    "sg:classifiers":[
        {
            "category":"Recreation",
            "type":"Entertainment"
        }
    ],
    "sg:phone":"+61 3 9439 6619",
    "sg:postcode":"3095",
    "sg:province":"VIC",
    "sg:tags":[
        "children's",
        "play",
        "programme"
    ],
    "wof:name":"Rare Bears Indoor Play Centre",
    "wof:placetype":"venue"
},
  "geometry": {"coordinates":[145.139160156,-37.7182998657],"type":"Point"}
}