{
  "type": "Feature",
  "properties": {
    "iso:country":"AU",
    "sg:address":"19 Hanrahan St",
    "sg:city":"Thomastown",
    "sg:classifiers":[
        {
            "category":"Building & Trades",
            "subcategory":"Construction",
            "type":"Services"
        }
    ],
    "sg:phone":"+61 3 9466 4333",
    "sg:postcode":"3074",
    "sg:province":"VIC",
    "sg:tags":[
        "industrial",
        "commercial",
        "air conditioning"
    ],
    "wof:name":"Bradmac Airconditioning Pty Ltd",
    "wof:placetype":"venue"
},
  "geometry": {"coordinates":[145.026245117,-37.6945075989],"type":"Point"}
}