{
  "type": "Feature",
  "properties": {
    "addr:full":"183 Bank St (Off Clarendon St) South Melbourne VIC 3205",
    "addr:housenumber":"183",
    "addr:postcode":"3205",
    "addr:street":"Bank St Off Clarendon St",
    "iso:country":"AU",
    "sg:address":"183 Bank St",
    "sg:city":"(Off Clarendon St) South Melbourne",
    "sg:classifiers":[
        {
            "category":"Health Services",
            "subcategory":"Doctor",
            "type":"Services"
        }
    ],
    "sg:phone":"+61 3 9645 7955",
    "sg:postcode":"3205",
    "sg:province":"VIC",
    "sg:tags":[
        "podiatrist"
    ],
    "wof:name":"Foot, Ankle & Rehabilitation Clinic",
    "wof:placetype":"venue"
},
  "geometry": {"coordinates":[144.961456,-37.834133],"type":"Point"}
}