{
  "type": "Feature",
  "properties": {
    "addr:full":"306 Clarendon Rd Lowood QLD 4311",
    "addr:housenumber":"306",
    "addr:postcode":"4311",
    "addr:street":"Clarendon Rd",
    "iso:country":"AU",
    "sg:address":"306 Clarendon Rd",
    "sg:city":"Lowood",
    "sg:classifiers":[
        {
            "category":"Farming",
            "subcategory":"Nursery",
            "type":"Manufacturing & Wholesale Goods"
        }
    ],
    "sg:phone":"+61 7 5426 2312",
    "sg:postcode":"4311",
    "sg:province":"QLD",
    "wof:name":"Glenwood Nursery",
    "wof:placetype":"venue"
},
  "geometry": {"coordinates":[152.51815795900001,-27.4395198822],"type":"Point"}
}