{
  "type": "Feature",
  "properties": {
    "addr:full":"24 Macquarie Rd Springwood NSW 2777",
    "addr:housenumber":"24",
    "addr:postcode":"2777",
    "addr:street":"Macquarie Rd",
    "iso:country":"AU",
    "sg:address":"24 Macquarie Rd",
    "sg:city":"Springwood",
    "sg:classifiers":[
        {
            "category":"Professional",
            "subcategory":"Detective & Security Services",
            "type":"Services"
        }
    ],
    "sg:phone":"+61 2 4751 5533",
    "sg:postcode":"2777",
    "sg:province":"NSW",
    "sg:tags":[
        "investigator"
    ],
    "wof:name":"Nightingale Investigators",
    "wof:placetype":"venue"
},
  "geometry": {"coordinates":[150.573486328,-33.7027702332],"type":"Point"}
}