{
  "type": "Feature",
  "properties": {
    "addr:full":"245 The Boulevarde Fairfield Heights NSW 2165",
    "addr:housenumber":"245",
    "addr:postcode":"2165",
    "addr:street":"The Boulevarde",
    "iso:country":"AU",
    "sg:address":"245 The Boulevarde",
    "sg:city":"Fairfield Heights",
    "sg:classifiers":[
        {
            "category":"Real Estate",
            "subcategory":"Surveying",
            "type":"Services"
        }
    ],
    "sg:phone":"+61 2 9609 2900",
    "sg:postcode":"2165",
    "sg:province":"NSW",
    "sg:tags":[
        "surveyor",
        "land"
    ],
    "wof:name":"Britten & Associates",
    "wof:placetype":"venue"
},
  "geometry": {"coordinates":[150.93864440900001,-33.8627929688],"type":"Point"}
}