{
  "type": "Feature",
  "properties": {
    "addr:full":"45 Majors Bay Rd Concord NSW 2137",
    "addr:housenumber":"45",
    "addr:postcode":"2137",
    "addr:street":"Majors Bay Rd",
    "iso:country":"AU",
    "sg:address":"45 Majors Bay Rd",
    "sg:city":"Concord",
    "sg:classifiers":[
        {
            "category":"Fast Food",
            "type":"Food & Drink"
        }
    ],
    "sg:phone":"+61 2 9743 6235",
    "sg:postcode":"2137",
    "sg:province":"NSW",
    "sg:tags":[
        "away",
        "take"
    ],
    "wof:name":"Concord Charcoal Chicken",
    "wof:placetype":"venue"
},
  "geometry": {"coordinates":[151.103515625,-33.8567237854],"type":"Point"}
}