{
  "type": "Feature",
  "properties": {
    "addr:full":"8/ 492 St Kilda Rd Melbourne VIC 3004",
    "addr:housenumber":"/ 492",
    "addr:postcode":"3004",
    "addr:street":"St Kilda Rd",
    "iso:country":"AU",
    "sg:address":"8/ 492 St Kilda Rd",
    "sg:city":"Melbourne",
    "sg:classifiers":[
        {
            "category":"Education",
            "subcategory":"Special Training",
            "type":"Public Place"
        }
    ],
    "sg:phone":"+61 3 9866 7788",
    "sg:postcode":"3004",
    "sg:province":"VIC",
    "sg:tags":[
        "development"
    ],
    "wof:name":"Media & Presentation Training",
    "wof:placetype":"venue"
},
  "geometry": {"coordinates":[144.977981567,-37.8439331055],"type":"Point"}
}