{
  "type": "Feature",
  "properties": {
    "addr:full":"55 Chapel St Windsor VIC 3181",
    "addr:housenumber":"55",
    "addr:postcode":"3181",
    "addr:street":"Chapel St",
    "iso:country":"AU",
    "sg:address":"55 Chapel St",
    "sg:city":"Windsor",
    "sg:classifiers":[
        {
            "category":"Personal",
            "subcategory":"Beauty Salon",
            "type":"Services"
        }
    ],
    "sg:phone":"+61 3 9510 8899",
    "sg:postcode":"3181",
    "sg:province":"VIC",
    "sg:tags":[
        "hairdresser"
    ],
    "wof:name":"Hair Crew",
    "wof:placetype":"venue"
},
  "geometry": {"coordinates":[144.99253845199999,-37.8553657532],"type":"Point"}
}