{
  "type": "Feature",
  "properties": {
    "iso:country":"AU",
    "sg:address":"Unit 2 23 Industrial Drv",
    "sg:city":"Braeside",
    "sg:classifiers":[
        {
            "category":"Retail",
            "subcategory":"Auto Repair",
            "type":"Services"
        }
    ],
    "sg:phone":"+61 3 9580 5687",
    "sg:postcode":"3195",
    "sg:province":"VIC",
    "sg:tags":[
        "beater",
        "painter",
        "panel"
    ],
    "wof:name":"Braeside Smash Repairs",
    "wof:placetype":"venue"
},
  "geometry": {"coordinates":[145.10874939000001,-38.0049743652],"type":"Point"}
}