{
  "type": "Feature",
  "properties": {
    "addr:full":"56 Thompson St Drummoyne NSW 2047",
    "addr:housenumber":"56",
    "addr:postcode":"2047",
    "addr:street":"Thompson St",
    "iso:country":"AU",
    "sg:address":"56 Thompson St",
    "sg:city":"Drummoyne",
    "sg:classifiers":[
        {
            "category":"Wholesale",
            "subcategory":"Drugs",
            "type":"Manufacturing & Wholesale Goods"
        }
    ],
    "sg:phone":"+61 2 9719 2800",
    "sg:postcode":"2047",
    "sg:province":"NSW",
    "sg:tags":[
        "wholesaler",
        "pharmaceutical",
        "product",
        "mfrs"
    ],
    "wof:name":"Datapharm Australia Pty Ltd",
    "wof:placetype":"venue"
},
  "geometry": {"coordinates":[151.15194700000001,-33.855587],"type":"Point"}
}