{
  "type": "Feature",
  "properties": {
    "iso:country":"AU",
    "sg:address":"PO Box 3115",
    "sg:city":"Grose Vale",
    "sg:classifiers":[
        {
            "category":"Education",
            "subcategory":"School",
            "type":"Public Place"
        }
    ],
    "sg:phone":"+61 2 4573 2218",
    "sg:postcode":"2753",
    "sg:province":"NSW",
    "wof:name":"Hawkesbury Independent School Inc",
    "wof:placetype":"venue"
},
  "geometry": {"coordinates":[150.65107727,-33.5760612488],"type":"Point"}
}