{
  "type": "Feature",
  "properties": {
    "iso:country":"AU",
    "sg:address":"4 Adalia Crt",
    "sg:city":"Kallaroo",
    "sg:classifiers":[
        {
            "category":"Mining & Drilling",
            "type":"Manufacturing & Wholesale Goods"
        }
    ],
    "sg:phone":"+61 8 9307 4189",
    "sg:postcode":"6025",
    "sg:province":"WA",
    "sg:tags":[
        "boring",
        "contractor"
    ],
    "wof:name":"Purewater Drilling Contractors",
    "wof:placetype":"venue"
},
  "geometry": {"coordinates":[115.75279235799999,-31.7903404236],"type":"Point"}
}