{
  "type": "Feature",
  "properties": {
    "addr:full":"Bunya Hwy Wondai QLD 4606",
    "addr:postcode":"4606",
    "addr:street":"Bunya Hwy",
    "iso:country":"AU",
    "sg:address":"Bunya Hwy",
    "sg:city":"Wondai",
    "sg:classifiers":[
        {
            "category":"Sports & Exercise",
            "subcategory":"Golf",
            "type":"Entertainment"
        }
    ],
    "sg:phone":"+61 7 4168 5582",
    "sg:postcode":"4606",
    "sg:province":"QLD",
    "sg:tags":[
        "club"
    ],
    "wof:name":"Wondai Golf & Bowling Club Inc",
    "wof:placetype":"venue"
},
  "geometry": {"coordinates":[151.87069700000001,-26.312489],"type":"Point"}
}