{
  "type": "Feature",
  "properties": {
    "addr:full":"The Plaza Noosa Junction, Sunshine Beach Rd Noosa Heads QLD 4567",
    "addr:postcode":"4567",
    "addr:street":"Beach Rd",
    "iso:country":"AU",
    "sg:address":"The Plaza Noosa Junction, Sunshine Beach Rd",
    "sg:city":"Noosa Heads",
    "sg:classifiers":[
        {
            "category":"Shopping",
            "subcategory":"Music",
            "type":"Retail Goods"
        }
    ],
    "sg:phone":"+61 7 5474 9444",
    "sg:postcode":"4567",
    "sg:province":"QLD",
    "sg:tags":[
        "store"
    ],
    "wof:name":"Vybes",
    "wof:placetype":"venue"
},
  "geometry": {"coordinates":[153.09002685600001,-26.3967170715],"type":"Point"}
}