{
  "type": "Feature",
  "properties": {
    "addr:full":"17 Learoyd Rd (Cnr Beaudesert Rd) Acacia Ridge QLD 4110",
    "addr:housenumber":"17",
    "addr:postcode":"4110",
    "addr:street":"Learoyd Rd Cnr Beaudesert Rd",
    "iso:country":"AU",
    "sg:address":"17 Learoyd Rd (Cnr Beaudesert Rd)",
    "sg:city":"Acacia Ridge",
    "sg:classifiers":[
        {
            "category":"Communications",
            "subcategory":"Television Station",
            "type":"Services"
        }
    ],
    "sg:phone":"+61 7 3717 2144",
    "sg:postcode":"4110",
    "sg:province":"QLD",
    "sg:tags":[
        "equipment",
        "laser"
    ],
    "sg:website":"http://www.abclasers.com.au",
    "wof:name":"ABC Lasers",
    "wof:placetype":"venue"
},
  "geometry": {"coordinates":[153.03880310100001,-27.5987243652],"type":"Point"}
}