{
  "type": "Feature",
  "properties": {
    "addr:full":"Cnr Bourke St & Botany Rd Alexandria NSW 2015",
    "addr:postcode":"2015",
    "addr:street":"Cnr Bourke St & Botany Rd",
    "iso:country":"AU",
    "sg:address":"Cnr Bourke St & Botany Rd",
    "sg:city":"Alexandria",
    "sg:classifiers":[
        {
            "category":"Manufacturing",
            "subcategory":"Motor Vehicles & Parts",
            "type":"Manufacturing & Wholesale Goods"
        }
    ],
    "sg:phone":"+61 2 9319 0011",
    "sg:postcode":"2015",
    "sg:province":"NSW",
    "sg:tags":[
        "replacement"
    ],
    "wof:name":"John Newell Mazda Eunos",
    "wof:placetype":"venue"
},
  "geometry": {"coordinates":[151.20286560100001,-33.9055213928],"type":"Point"}
}