{
  "type": "Feature",
  "properties": {
    "iso:country":"AU",
    "sg:address":"Lot 7 Mons Rd",
    "sg:city":"Forest Glen",
    "sg:classifiers":[
        {
            "category":"Freight",
            "type":"Transportation"
        }
    ],
    "sg:phone":"+61 1300 366 684",
    "sg:postcode":"4556",
    "sg:province":"QLD",
    "sg:tags":[
        "light",
        "carrier"
    ],
    "wof:name":"Toll Ipec Road Express",
    "wof:placetype":"venue"
},
  "geometry": {"coordinates":[153.01319885300001,-26.6885147095],"type":"Point"}
}