{
  "type": "Feature",
  "properties": {
    "addr:full":"9 Hawke Drv Woolgoolga NSW 2456",
    "addr:housenumber":"9",
    "addr:postcode":"2456",
    "addr:street":"Hawke Drv",
    "iso:country":"AU",
    "sg:address":"9 Hawke Drv",
    "sg:city":"Woolgoolga",
    "sg:classifiers":[
        {
            "category":"Retail",
            "subcategory":"Storage",
            "type":"Services"
        }
    ],
    "sg:phone":"+61 2 6653 7233",
    "sg:postcode":"2456",
    "sg:province":"NSW",
    "wof:name":"Caravan & Boat Storage",
    "wof:placetype":"venue"
},
  "geometry": {"coordinates":[153.194107,-30.121958],"type":"Point"}
}