{
  "type": "Feature",
  "properties": {
    "addr:full":"PO Box 2417 Graceville QLD 4075",
    "addr:postcode":"4075",
    "iso:country":"AU",
    "sg:address":"PO Box 2417",
    "sg:city":"Graceville",
    "sg:classifiers":[
        {
            "category":"Retail",
            "subcategory":"Funeral Services",
            "type":"Services"
        }
    ],
    "sg:phone":"+61 7 3716 0764",
    "sg:postcode":"4075",
    "sg:province":"QLD",
    "sg:tags":[
        "cemetery"
    ],
    "wof:name":"Cemetery Care",
    "wof:placetype":"venue"
},
  "geometry": {"coordinates":[152.97645568900001,-27.5224895477],"type":"Point"}
}