{
  "type": "Feature",
  "properties": {
    "iso:country":"AU",
    "sg:address":"58 Archibald St",
    "sg:city":"Mackay",
    "sg:classifiers":[
        {
            "category":"Manufacturing",
            "subcategory":"Motor Vehicles & Parts",
            "type":"Manufacturing & Wholesale Goods"
        }
    ],
    "sg:phone":"+61 7 4952 6622",
    "sg:postcode":"4740",
    "sg:province":"QLD",
    "sg:tags":[
        "engine",
        "equipment",
        "diesel"
    ],
    "wof:name":"M C S Automotive Engineering",
    "wof:placetype":"venue"
},
  "geometry": {"coordinates":[149.164963,-21.168056],"type":"Point"}
}