{
  "type": "Feature",
  "properties": {
    "addr:full":"1 Playford St Glen Osmond SA 5064",
    "addr:housenumber":"1",
    "addr:postcode":"5064",
    "addr:street":"Playford St",
    "iso:country":"AU",
    "sg:address":"1 Playford St",
    "sg:city":"Glen Osmond",
    "sg:classifiers":[
        {
            "category":"Building & Trades",
            "subcategory":"Construction",
            "type":"Services"
        }
    ],
    "sg:phone":"+61 8 8379 4442",
    "sg:postcode":"5064",
    "sg:province":"SA",
    "sg:tags":[
        "management"
    ],
    "wof:name":"Design Build Services",
    "wof:placetype":"venue"
},
  "geometry": {"coordinates":[138.650787353,-34.9588356018],"type":"Point"}
}