{
  "type": "Feature",
  "properties": {
    "addr:full":"16 Aero Rd Ingleburn NSW 2565",
    "addr:housenumber":"16",
    "addr:postcode":"2565",
    "addr:street":"Aero Rd",
    "iso:country":"AU",
    "sg:address":"16 Aero Rd",
    "sg:city":"Ingleburn",
    "sg:classifiers":[
        {
            "category":"Retail",
            "subcategory":"Auto Repair",
            "type":"Services"
        }
    ],
    "sg:phone":"+61 417 497 774",
    "sg:postcode":"2565",
    "sg:province":"NSW",
    "sg:tags":[
        "repairer",
        "motor",
        "engineer"
    ],
    "wof:name":"J.W.S Mech Repairs",
    "wof:placetype":"venue"
},
  "geometry": {"coordinates":[150.865844727,-33.993473053],"type":"Point"}
}