{
  "type": "Feature",
  "properties": {
    "addr:full":"17 Gordons Hill Rd Bellerive TAS 7018",
    "addr:housenumber":"17",
    "addr:postcode":"7018",
    "addr:street":"Gordons Hill Rd",
    "iso:country":"AU",
    "sg:address":"17 Gordons Hill Rd",
    "sg:city":"Bellerive",
    "sg:classifiers":[
        {
            "category":"Retail",
            "subcategory":"Laundry & Dry Cleaning",
            "type":"Services"
        }
    ],
    "sg:phone":"+61 3 6244 1149",
    "sg:postcode":"7018",
    "sg:province":"TAS",
    "sg:tags":[
        "truck",
        "tip",
        "contractor"
    ],
    "wof:name":"Garth BT",
    "wof:placetype":"venue"
},
  "geometry": {"coordinates":[147.37213134800001,-42.8645706177],"type":"Point"}
}