{
  "type": "Feature",
  "properties": {
    "iso:country":"AU",
    "sg:address":"282 Rathdown St",
    "sg:city":"Carlton North",
    "sg:classifiers":[
        {
            "category":"Real Estate",
            "subcategory":"Architect",
            "type":"Services"
        }
    ],
    "sg:phone":"+61 3 9349 1454",
    "sg:postcode":"3054",
    "sg:province":"VIC",
    "wof:name":"Cathi Colla Architects",
    "wof:placetype":"venue"
},
  "geometry": {"coordinates":[144.97171020499999,-37.7921028137],"type":"Point"}
}