{
  "type": "Feature",
  "properties": {
    "addr:full":"572- 574 Marion Rd Plympton Park SA 5038",
    "addr:housenumber":"574",
    "addr:postcode":"5038",
    "addr:street":"Marion Rd",
    "iso:country":"AU",
    "sg:address":"572- 574 Marion Rd",
    "sg:city":"Plympton Park",
    "sg:classifiers":[
        {
            "category":"Autos & Motor Vehicles",
            "subcategory":"Automobile Sales",
            "type":"Retail Goods"
        }
    ],
    "sg:phone":"+61 8 8371 5166",
    "sg:postcode":"5038",
    "sg:province":"SA",
    "sg:tags":[
        "car",
        "used"
    ],
    "wof:name":"Marion Road Car Sales",
    "wof:placetype":"venue"
},
  "geometry": {"coordinates":[138.55586242699999,-34.9803657532],"type":"Point"}
}