{
  "type": "Feature",
  "properties": {
    "addr:full":"Centrepoint Bldg, 12 Gregory Tce Alice Springs NT 0870",
    "addr:housenumber":"12",
    "addr:postcode":"nt 0870",
    "addr:street":"Gregory Tce",
    "iso:country":"AU",
    "sg:address":"Centrepoint Bldg, 12",
    "sg:city":"Gregory Tce Alice Springs",
    "sg:classifiers":[
        {
            "category":"Professional",
            "subcategory":"Management & Consulting",
            "type":"Services"
        }
    ],
    "sg:phone":"+61 8 8950 2100",
    "sg:postcode":"0870",
    "sg:province":"NT",
    "sg:tags":[
        "consultant",
        "migration"
    ],
    "wof:name":"Morgan Buckley",
    "wof:placetype":"venue"
},
  "geometry": {"coordinates":[133.85372924800001,-23.7290496826],"type":"Point"}
}