{
  "type": "Feature",
  "properties": {
    "iso:country":"AU",
    "sg:address":"21 Horton St",
    "sg:city":"Port Macquarie",
    "sg:classifiers":[
        {
            "category":"Real Estate",
            "subcategory":"Real Estate Agent",
            "type":"Services"
        }
    ],
    "sg:phone":"+61 2 6583 8800",
    "sg:postcode":"2444",
    "sg:province":"NSW",
    "sg:website":"http://www.prdnationwide.com.au",
    "wof:name":"PRDnationwide Port Macquarie",
    "wof:placetype":"venue"
},
  "geometry": {"coordinates":[152.908615,-31.432886],"type":"Point"}
}