{
  "type": "Feature",
  "properties": {
    "iso:country":"AU",
    "sg:address":"27 Bay St",
    "sg:city":"Port Macquarie",
    "sg:classifiers":[
        {
            "category":"Industrial Area",
            "type":"Public Place"
        }
    ],
    "sg:phone":"+61 418 658 202",
    "sg:postcode":"2444",
    "sg:province":"NSW",
    "sg:tags":[
        "protective",
        "clothing"
    ],
    "wof:name":"Bob Withers & Bob Uniforms & Boots",
    "wof:placetype":"venue"
},
  "geometry": {"coordinates":[152.895523,-31.428383],"type":"Point"}
}