{
  "type": "Feature",
  "properties": {
    "addr:full":"Shop 32, Mittagong Antique Centre, 85-87 Main St Mittagong NSW 2575",
    "addr:housenumber":"shop 32;85-87",
    "addr:postcode":"2575",
    "addr:street":"Main St",
    "iso:country":"AU",
    "sg:address":"Shop 32, Mittagong Antique Centre, 85-87 Main St",
    "sg:city":"Mittagong",
    "sg:classifiers":[
        {
            "category":"Shopping",
            "subcategory":"Clothing, Apparel, & Fashions",
            "type":"Retail Goods"
        }
    ],
    "sg:phone":"+61 2 4872 3191",
    "sg:postcode":"2575",
    "sg:province":"NSW",
    "sg:tags":[
        "recycled",
        "clothing"
    ],
    "wof:name":"Classic Vintage",
    "wof:placetype":"venue"
},
  "geometry": {"coordinates":[150.447174072,-34.4508628845],"type":"Point"}
}