{
  "type": "Feature",
  "properties": {
    "addr:full":"47 Sunburst Ave Balwyn North VIC 3104",
    "addr:housenumber":"47",
    "addr:postcode":"3104",
    "addr:street":"Sunburst Ave",
    "iso:country":"AU",
    "sg:address":"47 Sunburst Ave",
    "sg:city":"Balwyn North",
    "sg:classifiers":[
        {
            "category":"Home & Garden",
            "subcategory":"Home Furnishings",
            "type":"Retail Goods"
        }
    ],
    "sg:phone":"+61 407 020 383",
    "sg:postcode":"3104",
    "sg:province":"VIC",
    "sg:tags":[
        "storage",
        "rack",
        "wine"
    ],
    "wof:name":"Wineracks Australia",
    "wof:placetype":"venue"
},
  "geometry": {"coordinates":[145.07554626500001,-37.7891654968],"type":"Point"}
}