{
  "type": "Feature",
  "properties": {
    "addr:full":"203 Melbourne Rd Wodonga VIC 3690",
    "addr:housenumber":"203",
    "addr:postcode":"3690",
    "addr:street":"Melbourne Rd",
    "iso:country":"AU",
    "sg:address":"203 Melbourne Rd",
    "sg:city":"Wodonga",
    "sg:classifiers":[
        {
            "category":"Education",
            "subcategory":"Kindergarten",
            "type":"Public Place"
        }
    ],
    "sg:phone":"+61 2 6024 7799",
    "sg:postcode":"3690",
    "sg:province":"VIC",
    "sg:tags":[
        "pre-schools"
    ],
    "wof:name":"Bumble Bees Childcare Centres",
    "wof:placetype":"venue"
},
  "geometry": {"coordinates":[146.865631103,-36.1132316589],"type":"Point"}
}