{
  "type": "Feature",
  "properties": {
    "addr:full":"8 Deniliquin St Tocumwal NSW 2714",
    "addr:housenumber":"8",
    "addr:postcode":"2714",
    "addr:street":"Deniliquin St",
    "iso:country":"AU",
    "sg:address":"8 Deniliquin St",
    "sg:city":"Tocumwal",
    "sg:classifiers":[
        {
            "category":"Food & Beverages",
            "subcategory":"Supermarket",
            "type":"Retail Goods"
        }
    ],
    "sg:phone":"+61 3 5874 2209",
    "sg:postcode":"2714",
    "sg:province":"NSW",
    "sg:tags":[
        "grocery",
        "store"
    ],
    "wof:name":"Cromack Foodwise",
    "wof:placetype":"venue"
},
  "geometry": {"coordinates":[145.56561279300001,-35.8120956421],"type":"Point"}
}