{
  "type": "Feature",
  "properties": {
    "addr:full":"Level 3 South Tower 527 Gregory Tce Bowen Hills QLD 4006",
    "addr:housenumber":"527",
    "addr:postcode":"4006",
    "addr:street":"Gregory Tce",
    "iso:country":"AU",
    "sg:address":"Level 3 South Tower 527",
    "sg:city":"Gregory Tce Bowen Hills",
    "sg:classifiers":[
        {
            "category":"Professional",
            "subcategory":"Business Services",
            "type":"Services"
        }
    ],
    "sg:phone":"+61 7 3367 3300",
    "sg:postcode":"4006",
    "sg:province":"QLD",
    "sg:tags":[
        "record",
        "management",
        "storage"
    ],
    "wof:name":"GMB Records & Information Management Systems (RIMS)",
    "wof:placetype":"venue"
},
  "geometry": {"coordinates":[153.03707885700001,-27.4476394653],"type":"Point"}
}