{
  "type": "Feature",
  "properties": {
    "iso:country":"AU",
    "sg:address":"24 Conway St",
    "sg:city":"Lismore",
    "sg:classifiers":[
        {
            "category":"Health Services",
            "subcategory":"Doctor",
            "type":"Services"
        }
    ],
    "sg:phone":"+61 2 6622 1646",
    "sg:postcode":"2480",
    "sg:province":"NSW",
    "sg:tags":[
        "medical",
        "practitioner"
    ],
    "wof:name":"Cody David Dr",
    "wof:placetype":"venue"
},
  "geometry": {"coordinates":[153.27516174300001,-28.8110275269],"type":"Point"}
}