{
  "type": "Feature",
  "properties": {
    "addr:full":"McFarlane St Robe SA 5276",
    "addr:postcode":"5276",
    "addr:street":"Mcfarlane St",
    "iso:country":"AU",
    "sg:address":"McFarlane St",
    "sg:city":"Robe",
    "sg:classifiers":[
        {
            "category":"Farming",
            "subcategory":"Fish & Marine Products",
            "type":"Manufacturing & Wholesale Goods"
        }
    ],
    "sg:phone":"+61 8 8768 2189",
    "sg:postcode":"5276",
    "sg:province":"SA",
    "sg:tags":[
        "fisherman"
    ],
    "wof:name":"Dening R E",
    "wof:placetype":"venue"
},
  "geometry": {"coordinates":[139.76745600000001,-37.17025],"type":"Point"}
}