{
  "type": "Feature",
  "properties": {
    "addr:full":"372 Crown St Wollongong NSW 2500",
    "addr:housenumber":"372",
    "addr:postcode":"2500",
    "addr:street":"Crown St",
    "iso:country":"AU",
    "sg:address":"372 Crown St",
    "sg:city":"Wollongong",
    "sg:classifiers":[
        {
            "category":"Professional",
            "subcategory":"Employment Agencies",
            "type":"Services"
        }
    ],
    "sg:phone":"+61 2 4225 7360",
    "sg:postcode":"2500",
    "sg:province":"NSW",
    "wof:name":"ATS Workforce",
    "wof:placetype":"venue"
},
  "geometry": {"coordinates":[150.87948600000001,-34.425907],"type":"Point"}
}