{
  "type": "Feature",
  "properties": {
    "iso:country":"AU",
    "sg:address":"Unit 2, 365 High Rd",
    "sg:city":"Riverton",
    "sg:classifiers":[
        {
            "category":"Arts & Performance",
            "subcategory":"Dance",
            "type":"Entertainment"
        }
    ],
    "sg:phone":"+61 8 9259 6309",
    "sg:postcode":"6148",
    "sg:province":"WA",
    "sg:tags":[
        "theatrical",
        "ballet",
        "tuition"
    ],
    "wof:name":"Hot Shoe Dance Co",
    "wof:placetype":"venue"
},
  "geometry": {"coordinates":[115.909378,-32.038662],"type":"Point"}
}