{
  "type": "Feature",
  "properties": {
    "addr:full":"339 Crown St Surry Hills NSW 2010",
    "addr:housenumber":"339",
    "addr:postcode":"2010",
    "addr:street":"Crown St",
    "iso:country":"AU",
    "sg:address":"339 Crown St",
    "sg:city":"Surry Hills",
    "sg:classifiers":[
        {
            "category":"Organizations",
            "subcategory":"Community Association",
            "type":"Services"
        }
    ],
    "sg:phone":"+61 2 9360 3000",
    "sg:postcode":"2010",
    "sg:province":"NSW",
    "sg:tags":[
        "organisation",
        "family",
        "welfare"
    ],
    "wof:name":"Salvo Youth Line National Crisis Counselling Services",
    "wof:placetype":"venue"
},
  "geometry": {"coordinates":[151.214233398,-33.8833236694],"type":"Point"}
}