{
  "type": "Feature",
  "properties": {
    "addr:full":"Lilypond St Bemerside QLD 4850",
    "addr:postcode":"4850",
    "addr:street":"Lilypond St",
    "iso:country":"AU",
    "sg:address":"Lilypond St",
    "sg:city":"Bemerside",
    "sg:classifiers":[
        {
            "category":"Farming",
            "subcategory":"Farm",
            "type":"Manufacturing & Wholesale Goods"
        }
    ],
    "sg:phone":"+61 7 4777 2734",
    "sg:postcode":"4850",
    "sg:province":"QLD",
    "sg:tags":[
        "farmer"
    ],
    "wof:name":"Cantoni Bros",
    "wof:placetype":"venue"
},
  "geometry": {"coordinates":[146.18942260700001,-18.5701198578],"type":"Point"}
}