{
  "type": "Feature",
  "properties": {
    "iso:country":"AU",
    "sg:address":"Shop 9, 2 Main Drv",
    "sg:city":"Warana",
    "sg:classifiers":[
        {
            "category":"Building & Trades",
            "subcategory":"Plumbing",
            "type":"Services"
        }
    ],
    "sg:phone":"+61 7 5493 5368",
    "sg:postcode":"4575",
    "sg:province":"QLD",
    "sg:tags":[
        "pump",
        "repairer"
    ],
    "wof:name":"One Stop Watering Shop",
    "wof:placetype":"venue"
},
  "geometry": {"coordinates":[153.128723,-26.730988],"type":"Point"}
}