{
  "type": "Feature",
  "properties": {
    "iso:country":"AU",
    "sg:address":"Plaza 1, Australia Square, 95 Pitt St",
    "sg:city":"Sydney",
    "sg:classifiers":[
        {
            "category":"Building & Trades",
            "subcategory":"Construction",
            "type":"Services"
        }
    ],
    "sg:phone":"+61 2 8249 7500",
    "sg:postcode":"2000",
    "sg:province":"NSW",
    "sg:tags":[
        "management"
    ],
    "wof:name":"Project Control Group Pty Ltd",
    "wof:placetype":"venue"
},
  "geometry": {"coordinates":[151.20851135300001,-33.8654785156],"type":"Point"}
}