{
  "type": "Feature",
  "properties": {
    "addr:full":"55 Garden St South Yarra VIC 3141",
    "addr:housenumber":"55",
    "addr:postcode":"3141",
    "addr:street":"Garden St",
    "iso:country":"AU",
    "sg:address":"55 Garden St",
    "sg:city":"South Yarra",
    "sg:classifiers":[
        {
            "category":"Autos & Motor Vehicles",
            "subcategory":"Automobile Sales",
            "type":"Retail Goods"
        }
    ],
    "sg:phone":"+61 3 9826 4176",
    "sg:postcode":"3141",
    "sg:province":"VIC",
    "sg:tags":[
        "car",
        "new"
    ],
    "wof:name":"South Yarra Saab",
    "wof:placetype":"venue"
},
  "geometry": {"coordinates":[144.997589111,-37.8434333801],"type":"Point"}
}