{
  "type": "Feature",
  "properties": {
    "iso:country":"AU",
    "sg:address":"20 Nerang St",
    "sg:city":"Nerang",
    "sg:classifiers":[
        {
            "category":"Professional",
            "subcategory":"Engineering",
            "type":"Services"
        }
    ],
    "sg:phone":"+61 7 5596 5377",
    "sg:postcode":"4211",
    "sg:province":"QLD",
    "sg:tags":[
        "consulting",
        "engineer"
    ],
    "wof:name":"Auspacific Engineers Pty Ltd",
    "wof:placetype":"venue"
},
  "geometry": {"coordinates":[153.336593628,-27.9918441772],"type":"Point"}
}