{
  "type": "Feature",
  "properties": {
    "iso:country":"AU",
    "sg:address":"8 Panton Rd",
    "sg:city":"Mandurah",
    "sg:classifiers":[
        {
            "category":"Autos & Motor Vehicles",
            "subcategory":"Boat Sales",
            "type":"Retail Goods"
        }
    ],
    "sg:phone":"+61 8 9581 8180",
    "sg:postcode":"6210",
    "sg:province":"WA",
    "sg:tags":[
        "equipment",
        "yacht"
    ],
    "wof:name":"Mandurah Marine Trimmers",
    "wof:placetype":"venue"
},
  "geometry": {"coordinates":[115.745621,-32.512241],"type":"Point"}
}