{
  "type": "Feature",
  "properties": {
    "addr:full":"50 Edols St Geelong North VIC 3215",
    "addr:housenumber":"50",
    "addr:postcode":"3215",
    "addr:street":"Edols St",
    "iso:country":"AU",
    "sg:address":"50 Edols St",
    "sg:city":"Geelong North",
    "sg:classifiers":[
        {
            "category":"Autos & Motor Vehicles",
            "subcategory":"Auto Supplies",
            "type":"Retail Goods"
        }
    ],
    "sg:phone":"+61 3 5278 8454",
    "sg:postcode":"3215",
    "sg:province":"VIC",
    "sg:tags":[
        "part",
        "cycles",
        "accessory"
    ],
    "wof:name":"Small Coil Rewinds Pty Ltd",
    "wof:placetype":"venue"
},
  "geometry": {"coordinates":[144.351318359,-38.1075706482],"type":"Point"}
}