{
  "type": "Feature",
  "properties": {
    "iso:country":"AU",
    "sg:address":"18 Tournay St",
    "sg:city":"Peakhurst",
    "sg:classifiers":[
        {
            "category":"Shopping",
            "subcategory":"Baby Store",
            "type":"Retail Goods"
        }
    ],
    "sg:phone":"+61 2 9596 4163",
    "sg:postcode":"2210",
    "sg:province":"NSW",
    "sg:tags":[
        "wear"
    ],
    "wof:name":"Born Collection",
    "wof:placetype":"venue"
},
  "geometry": {"coordinates":[151.06741299999999,-33.959625],"type":"Point"}
}