{
  "type": "Feature",
  "properties": {
    "addr:full":"25 Wattle St Fullarton SA 5063",
    "addr:housenumber":"25",
    "addr:postcode":"5063",
    "addr:street":"Wattle St",
    "iso:country":"AU",
    "sg:address":"25 Wattle St",
    "sg:city":"Fullarton",
    "sg:classifiers":[
        {
            "category":"Education",
            "subcategory":"Music School",
            "type":"Public Place"
        }
    ],
    "sg:phone":"+61 8 8379 2515",
    "sg:postcode":"5063",
    "sg:province":"SA",
    "sg:tags":[
        "teacher"
    ],
    "wof:name":"Miller Anne",
    "wof:placetype":"venue"
},
  "geometry": {"coordinates":[138.63194274899999,-34.9536552429],"type":"Point"}
}