{
  "type": "Feature",
  "properties": {
    "addr:full":"8 Chicory Ave Cowes VIC 3922",
    "addr:housenumber":"8",
    "addr:postcode":"3922",
    "addr:street":"Chicory Ave",
    "iso:country":"AU",
    "sg:address":"8 Chicory Ave",
    "sg:city":"Cowes",
    "sg:classifiers":[
        {
            "category":"Professional",
            "subcategory":"Art Services",
            "type":"Services"
        }
    ],
    "sg:phone":"+61 3 5952 6448",
    "sg:postcode":"3922",
    "sg:province":"VIC",
    "sg:tags":[
        "interior",
        "decorator"
    ],
    "wof:name":"Interiors Unlimited",
    "wof:placetype":"venue"
},
  "geometry": {"coordinates":[145.22419738799999,-38.4559402466],"type":"Point"}
}