{
  "type": "Feature",
  "properties": {
    "iso:country":"AU",
    "sg:address":"77 Hampshire Rd",
    "sg:city":"Sunshine",
    "sg:classifiers":[
        {
            "category":"Home & Garden",
            "subcategory":"Home Furnishings",
            "type":"Retail Goods"
        }
    ],
    "sg:phone":"+61 3 9311 2987",
    "sg:postcode":"3020",
    "sg:province":"VIC",
    "sg:tags":[
        "shower",
        "screen"
    ],
    "wof:name":"Westside Glass",
    "wof:placetype":"venue"
},
  "geometry": {"coordinates":[144.831131,-37.790302],"type":"Point"}
}