{
  "type": "Feature",
  "properties": {
    "addr:full":"Waratah Shopping Village 111 Turton Rd Waratah NSW 2298",
    "addr:housenumber":"111",
    "addr:postcode":"2298",
    "addr:street":"Turton Rd",
    "iso:country":"AU",
    "sg:address":"Waratah Shopping Village 111 Turton Rd",
    "sg:city":"Waratah",
    "sg:classifiers":[
        {
            "category":"Ice Cream",
            "type":"Food & Drink"
        }
    ],
    "sg:phone":"+61 2 4967 7991",
    "sg:postcode":"2298",
    "sg:province":"NSW",
    "sg:tags":[
        "retail"
    ],
    "wof:name":"Baskin 31 Robbins",
    "wof:placetype":"venue"
},
  "geometry": {"coordinates":[151.727325439,-32.9070320129],"type":"Point"}
}