{
  "type": "Feature",
  "properties": {
    "addr:full":"211 Pascoe Vale Rd Essendon VIC 3040",
    "addr:housenumber":"211",
    "addr:postcode":"3040",
    "addr:street":"Pascoe Vale Rd",
    "iso:country":"AU",
    "sg:address":"211 Pascoe Vale Rd",
    "sg:city":"Essendon",
    "sg:classifiers":[
        {
            "category":"Health Services",
            "subcategory":"Doctor",
            "type":"Services"
        }
    ],
    "sg:phone":"+61 3 9370 7105",
    "sg:postcode":"3040",
    "sg:province":"VIC",
    "sg:tags":[
        "medical",
        "practitioner"
    ],
    "wof:name":"Family Medical Centre",
    "wof:placetype":"venue"
},
  "geometry": {"coordinates":[144.92593383799999,-37.7558021545],"type":"Point"}
}