{
  "type": "Feature",
  "properties": {
    "addr:full":"33 Dracon St Browns Plains QLD 4118",
    "addr:housenumber":"33",
    "addr:postcode":"4118",
    "addr:street":"Dracon St",
    "iso:country":"AU",
    "sg:address":"33 Dracon St",
    "sg:city":"Browns Plains",
    "sg:classifiers":[
        {
            "category":"Utilities",
            "subcategory":"Refuse",
            "type":"Services"
        }
    ],
    "sg:phone":"+61 419 678 395",
    "sg:postcode":"4118",
    "sg:province":"QLD",
    "sg:tags":[
        "disposal",
        "reduction",
        "waste"
    ],
    "wof:name":"Ezze Trash",
    "wof:placetype":"venue"
},
  "geometry": {"coordinates":[153.04234314000001,-27.6703281403],"type":"Point"}
}