{
  "type": "Feature",
  "properties": {
    "addr:full":"15 Kensal St Moorooka QLD 4105",
    "addr:housenumber":"15",
    "addr:postcode":"4105",
    "addr:street":"Kensal St",
    "iso:country":"AU",
    "sg:address":"15 Kensal St",
    "sg:city":"Moorooka",
    "sg:classifiers":[
        {
            "category":"Retail",
            "subcategory":"Auto Repair",
            "type":"Services"
        }
    ],
    "sg:phone":"+61 7 3848 8122",
    "sg:postcode":"4105",
    "sg:province":"QLD",
    "sg:tags":[
        "repairer",
        "motor",
        "engineer"
    ],
    "wof:name":"Repco Auto Repair",
    "wof:placetype":"venue"
},
  "geometry": {"coordinates":[153.018432617,-27.5284786224],"type":"Point"}
}