{
  "type": "Feature",
  "properties": {
    "addr:full":"14 Redfern Rd Minto NSW 2566",
    "addr:housenumber":"14",
    "addr:postcode":"2566",
    "addr:street":"Redfern Rd",
    "iso:country":"AU",
    "sg:address":"14 Redfern Rd",
    "sg:city":"Minto",
    "sg:classifiers":[
        {
            "category":"Fast Food",
            "type":"Food & Drink"
        }
    ],
    "sg:phone":"+61 2 9820 2011",
    "sg:postcode":"2566",
    "sg:province":"NSW",
    "sg:tags":[
        "away",
        "take"
    ],
    "wof:name":"Pizza Haven",
    "wof:placetype":"venue"
},
  "geometry": {"coordinates":[150.844284058,-34.0281410217],"type":"Point"}
}