{
  "type": "Feature",
  "properties": {
    "addr:full":"8 Bayldon Rd Queanbeyan ACT 2620",
    "addr:housenumber":"8",
    "addr:postcode":"2620",
    "addr:street":"Bayldon Rd",
    "iso:country":"AU",
    "sg:address":"8 Bayldon Rd",
    "sg:city":"Queanbeyan",
    "sg:classifiers":[
        {
            "category":"Retail",
            "subcategory":"Auto Repair",
            "type":"Services"
        }
    ],
    "sg:phone":"+61 2 6297 5944",
    "sg:postcode":"2620",
    "sg:province":"ACT",
    "sg:tags":[
        "fuel",
        "petrol",
        "injection"
    ],
    "wof:name":"Keft Roger",
    "wof:placetype":"venue"
},
  "geometry": {"coordinates":[149.206863403,-35.3513641357],"type":"Point"}
}