{
  "type": "Feature",
  "properties": {
    "addr:full":"141 Westfield St Maddington WA 6109",
    "addr:housenumber":"141",
    "addr:postcode":"6109",
    "addr:street":"Westfield St",
    "iso:country":"AU",
    "sg:address":"141 Westfield St",
    "sg:city":"Maddington",
    "sg:classifiers":[
        {
            "category":"Health Services",
            "subcategory":"Medical Lab",
            "type":"Services"
        }
    ],
    "sg:phone":"+61 8 9452 3072",
    "sg:postcode":"6109",
    "sg:province":"WA",
    "sg:tags":[
        "laboratory",
        "pathology"
    ],
    "wof:name":"St John Of God Pathology (WA)",
    "wof:placetype":"venue"
},
  "geometry": {"coordinates":[115.99407959,-32.0479660034],"type":"Point"}
}