{
  "type": "Feature",
  "properties": {
    "addr:full":"3 Swallow Rock Drv Grays Point NSW 2232",
    "addr:housenumber":"3",
    "addr:postcode":"2232",
    "addr:street":"Swallow Rock Drv",
    "iso:country":"AU",
    "sg:address":"3 Swallow Rock Drv",
    "sg:city":"Grays Point",
    "sg:classifiers":[
        {
            "category":"Utilities",
            "subcategory":"Electric",
            "type":"Services"
        }
    ],
    "sg:phone":"+61 418 240 951",
    "sg:postcode":"2232",
    "sg:province":"NSW",
    "sg:tags":[
        "electrical",
        "contractor"
    ],
    "wof:name":"P C M Electrical Contracting Services Pty Ltd",
    "wof:placetype":"venue"
},
  "geometry": {"coordinates":[151.08140564000001,-34.0592956543],"type":"Point"}
}