{
  "type": "Feature",
  "properties": {
    "addr:full":"284 Seaford Rd Seaford VIC 3198",
    "addr:housenumber":"284",
    "addr:postcode":"3198",
    "addr:street":"Seaford Rd",
    "iso:country":"AU",
    "sg:address":"284 Seaford Rd",
    "sg:city":"Seaford",
    "sg:classifiers":[
        {
            "category":"Health Services",
            "subcategory":"Doctor",
            "type":"Services"
        }
    ],
    "sg:phone":"+61 3 9786 2703",
    "sg:postcode":"3198",
    "sg:province":"VIC",
    "sg:tags":[
        "podiatrist"
    ],
    "wof:name":"Carol A Thomson Podiatry",
    "wof:placetype":"venue"
},
  "geometry": {"coordinates":[145.15692138700001,-38.1123580933],"type":"Point"}
}