{
  "type": "Feature",
  "properties": {
    "addr:full":"14 Burragah Way Duncraig WA 6023",
    "addr:housenumber":"14",
    "addr:postcode":"6023",
    "addr:street":"Burragah Way",
    "iso:country":"AU",
    "sg:address":"14 Burragah Way",
    "sg:city":"Duncraig",
    "sg:classifiers":[
        {
            "category":"Health Services",
            "subcategory":"Dentist",
            "type":"Services"
        }
    ],
    "sg:phone":"+61 8 9246 9911",
    "sg:postcode":"6023",
    "sg:province":"WA",
    "sg:website":"http://www.dvdental.com.au",
    "wof:name":"Duncraig Village Dental",
    "wof:placetype":"venue"
},
  "geometry": {"coordinates":[115.764427185,-31.841293335],"type":"Point"}
}