{
  "type": "Feature",
  "properties": {
    "iso:country":"AU",
    "sg:address":"Shop 24B Bathurst City Centre Howick St",
    "sg:city":"Bathurst",
    "sg:classifiers":[
        {
            "category":"Personal",
            "subcategory":"Beauty Salon",
            "type":"Services"
        }
    ],
    "sg:phone":"+61 2 6331 2344",
    "sg:postcode":"2795",
    "sg:province":"NSW",
    "sg:tags":[
        "hairdresser"
    ],
    "wof:name":"Just Cuts",
    "wof:placetype":"venue"
},
  "geometry": {"coordinates":[149.58558654800001,-33.4213638306],"type":"Point"}
}