{
  "type": "Feature",
  "properties": {
    "iso:country":"AU",
    "sg:address":"18 Kimbe Crt",
    "sg:city":"Mindarie",
    "sg:classifiers":[
        {
            "category":"Health Services",
            "subcategory":"Health Practitioner",
            "type":"Services"
        }
    ],
    "sg:phone":"+61 8 9407 8642",
    "sg:postcode":"6030",
    "sg:province":"WA",
    "sg:tags":[
        "pathologist",
        "speech"
    ],
    "wof:name":"Dr Elsa Popich",
    "wof:placetype":"venue"
},
  "geometry": {"coordinates":[115.712791443,-31.686044693],"type":"Point"}
}