{
  "type": "Feature",
  "properties": {
    "addr:full":"7 Wiluna St Fyshwick ACT 2609",
    "addr:housenumber":"7",
    "addr:postcode":"2609",
    "addr:street":"Wiluna St",
    "iso:country":"AU",
    "sg:address":"7 Wiluna St",
    "sg:city":"Fyshwick",
    "sg:classifiers":[
        {
            "category":"Building & Trades",
            "subcategory":"Construction",
            "type":"Services"
        }
    ],
    "sg:phone":"+61 2 6280 4310",
    "sg:postcode":"2609",
    "sg:province":"ACT",
    "sg:tags":[
        "worker",
        "metal"
    ],
    "wof:name":"Engineering Services Co-Ordination",
    "wof:placetype":"venue"
},
  "geometry": {"coordinates":[149.16468810999999,-35.3284759521],"type":"Point"}
}