{
  "type": "Feature",
  "properties": {
    "addr:full":"Unit 14, 17- 25 Greg Chappel Drv Burleigh Gardens QLD 4220",
    "addr:housenumber":"17 25",
    "addr:postcode":"4220",
    "addr:street":"Greg Chappel Drv",
    "iso:country":"AU",
    "sg:address":"Unit 14, 17- 25 Greg Chappel Drv",
    "sg:city":"Burleigh Gardens",
    "sg:classifiers":[
        {
            "category":"Autos & Motor Vehicles",
            "subcategory":"Motorcycle Sales",
            "type":"Retail Goods"
        }
    ],
    "sg:phone":"+61 407 118 868",
    "sg:postcode":"4220",
    "sg:province":"QLD",
    "sg:tags":[
        "outboard"
    ],
    "wof:name":"Victory Marine Aust. Pty. Ltd.",
    "wof:placetype":"venue"
},
  "geometry": {"coordinates":[153.432662964,-28.0981998444],"type":"Point"}
}