{
  "type": "Feature",
  "properties": {
    "iso:country":"AU",
    "sg:address":"25 Woodcroft Drv",
    "sg:city":"Morphett Vale",
    "sg:classifiers":[
        {
            "category":"Utilities",
            "subcategory":"Electric",
            "type":"Services"
        }
    ],
    "sg:phone":"+61 408 809 697",
    "sg:postcode":"5162",
    "sg:province":"SA",
    "sg:tags":[
        "electrical",
        "contractor"
    ],
    "wof:name":"Hunts Electrical Services",
    "wof:placetype":"venue"
},
  "geometry": {"coordinates":[138.53904724099999,-35.1082077026],"type":"Point"}
}