{
  "type": "Feature",
  "properties": {
    "addr:full":"2/ 201 Ferry Rd Southport QLD 4215",
    "addr:housenumber":"/ 201",
    "addr:postcode":"4215",
    "addr:street":"Ferry Rd",
    "iso:country":"AU",
    "sg:address":"2/ 201 Ferry Rd",
    "sg:city":"Southport",
    "sg:classifiers":[
        {
            "category":"Fast Food",
            "type":"Food & Drink"
        }
    ],
    "sg:phone":"+61 7 5564 0990",
    "sg:postcode":"4215",
    "sg:province":"QLD",
    "sg:tags":[
        "away",
        "take"
    ],
    "wof:name":"Fish on Ferry",
    "wof:placetype":"venue"
},
  "geometry": {"coordinates":[153.41242980999999,-27.9895401001],"type":"Point"}
}