{
  "type": "Feature",
  "properties": {
    "iso:country":"AU",
    "sg:address":"32 Gumma Rd",
    "sg:city":"Macksville",
    "sg:phone":"+61 2 6568 4222",
    "sg:postcode":"2447",
    "sg:province":"NSW",
    "wof:name":"Coopers Concreting",
    "wof:placetype":"venue"
},
  "geometry": {"coordinates":[152.93604999999999,-30.710346],"type":"Point"}
}