{
  "type": "Feature",
  "properties": {
    "iso:country":"AU",
    "sg:address":"27 Golf Links Rd",
    "sg:city":"Albany",
    "sg:classifiers":[
        {
            "category":"Autos & Motor Vehicles",
            "subcategory":"Fuel & Gas Station",
            "type":"Retail Goods"
        }
    ],
    "sg:phone":"+61 8 9841 6488",
    "sg:postcode":"6330",
    "sg:province":"WA",
    "wof:name":"Shell Co Of Australia Ltd The",
    "wof:placetype":"venue"
},
  "geometry": {"coordinates":[117.912666321,-35.0223922729],"type":"Point"}
}