{
  "type": "Feature",
  "properties": {
    "iso:country":"AU",
    "sg:address":"125 Leslie St",
    "sg:city":"Toowoomba",
    "sg:classifiers":[
        {
            "category":"Professional",
            "subcategory":"Employment Agencies",
            "type":"Services"
        }
    ],
    "sg:phone":"+61 7 4636 1409",
    "sg:postcode":"4350",
    "sg:province":"QLD",
    "sg:tags":[
        "hire",
        "labour",
        "contractor"
    ],
    "wof:name":"Taurus Employment Services",
    "wof:placetype":"venue"
},
  "geometry": {"coordinates":[151.987045,-27.596222],"type":"Point"}
}