{
  "type": "Feature",
  "properties": {
    "iso:country":"AU",
    "sg:address":"170 High St",
    "sg:city":"Shepparton",
    "sg:classifiers":[
        {
            "category":"Retail",
            "subcategory":"Event Space",
            "type":"Services"
        }
    ],
    "sg:phone":"+61 3 5831 1882",
    "sg:postcode":"3630",
    "sg:province":"VIC",
    "sg:tags":[
        "venue",
        "reception",
        "wedding"
    ],
    "wof:name":"Cellar 47",
    "wof:placetype":"venue"
},
  "geometry": {"coordinates":[145.404052734,-36.3818244934],"type":"Point"}
}