{
  "type": "Feature",
  "properties": {
    "addr:full":"4/ 163 Bellarine Hwy Newcomb VIC 3219",
    "addr:housenumber":"/ 163",
    "addr:postcode":"3219",
    "addr:street":"Bellarine Hwy",
    "iso:country":"AU",
    "sg:address":"4/ 163 Bellarine Hwy",
    "sg:city":"Newcomb",
    "sg:classifiers":[
        {
            "category":"Real Estate",
            "subcategory":"Real Estate Agent",
            "type":"Services"
        }
    ],
    "sg:phone":"+61 3 5248 8611",
    "sg:postcode":"3219",
    "sg:province":"VIC",
    "wof:name":"L.J. Hooker East Geelong",
    "wof:placetype":"venue"
},
  "geometry": {"coordinates":[144.36480712900001,-38.1507377625],"type":"Point"}
}