{
  "type": "Feature",
  "properties": {
    "addr:full":"361 Urana Rd Lavington NSW 2641",
    "addr:housenumber":"361",
    "addr:postcode":"2641",
    "addr:street":"Urana Rd",
    "iso:country":"AU",
    "sg:address":"361 Urana Rd",
    "sg:city":"Lavington",
    "sg:classifiers":[
        {
            "category":"Personal",
            "subcategory":"Hair Removal",
            "type":"Services"
        }
    ],
    "sg:phone":"+61 2 6040 0354",
    "sg:postcode":"2641",
    "sg:province":"NSW",
    "wof:name":"Unique Skin Health",
    "wof:placetype":"venue"
},
  "geometry": {"coordinates":[146.93060302699999,-36.047832489],"type":"Point"}
}