{
  "type": "Feature",
  "properties": {
    "addr:full":"Boogan Rd Mourilyan QLD 4858",
    "addr:postcode":"4858",
    "addr:street":"Boogan Rd",
    "iso:country":"AU",
    "sg:address":"Boogan Rd",
    "sg:city":"Mourilyan",
    "sg:classifiers":[
        {
            "category":"Farming",
            "subcategory":"Farm",
            "type":"Manufacturing & Wholesale Goods"
        }
    ],
    "sg:phone":"+61 7 4063 2124",
    "sg:postcode":"4858",
    "sg:province":"QLD",
    "sg:tags":[
        "farmer"
    ],
    "wof:name":"Friel & Co",
    "wof:placetype":"venue"
},
  "geometry": {"coordinates":[146.03367614699999,-17.5891494751],"type":"Point"}
}