{
  "type": "Feature",
  "properties": {
    "addr:full":"565 Military Rd Largs North SA 5016",
    "addr:housenumber":"565",
    "addr:postcode":"5016",
    "addr:street":"Military Rd",
    "iso:country":"AU",
    "sg:address":"565 Military Rd",
    "sg:city":"Largs North",
    "sg:classifiers":[
        {
            "category":"Travel",
            "subcategory":"Hotels & Motels",
            "type":"Entertainment"
        }
    ],
    "sg:phone":"+61 8 8248 2297",
    "sg:postcode":"5016",
    "sg:province":"SA",
    "sg:tags":[
        "pub"
    ],
    "wof:name":"Wee Willie's Tavern",
    "wof:placetype":"venue"
},
  "geometry": {"coordinates":[138.49415588400001,-34.8163108826],"type":"Point"}
}