{
  "type": "Feature",
  "properties": {
    "addr:full":"U2/ 9 Campbell St Artarmon NSW 2064",
    "addr:housenumber":"9",
    "addr:postcode":"2064",
    "addr:street":"U2 /;St",
    "iso:country":"AU",
    "sg:address":"U2/ 9 Campbell St",
    "sg:city":"Artarmon",
    "sg:classifiers":[
        {
            "category":"Social Services",
            "subcategory":"Child Care",
            "type":"Services"
        }
    ],
    "sg:phone":"+61 2 9436 2155",
    "sg:postcode":"2064",
    "sg:province":"NSW",
    "wof:name":"Lollipops Child Care Artarmon",
    "wof:placetype":"venue"
},
  "geometry": {"coordinates":[151.184326172,-33.8182754517],"type":"Point"}
}