{
  "type": "Feature",
  "properties": {
    "addr:full":"Suite5/ 71a Macquarie St Parramatta NSW 2150",
    "addr:housenumber":"71a",
    "addr:postcode":"2150",
    "addr:street":"Macquarie St",
    "iso:country":"AU",
    "sg:address":"Suite5/ 71a Macquarie St",
    "sg:city":"Parramatta",
    "sg:classifiers":[
        {
            "category":"Professional",
            "subcategory":"Management & Consulting",
            "type":"Services"
        }
    ],
    "sg:phone":"+61 2 9687 5155",
    "sg:postcode":"2150",
    "sg:province":"NSW",
    "sg:tags":[
        "project"
    ],
    "wof:name":"RK Civil & Environment Engineering Consultants",
    "wof:placetype":"venue"
},
  "geometry": {"coordinates":[151.06320190400001,-33.910194397],"type":"Point"}
}