{
  "type": "Feature",
  "properties": {
    "iso:country":"AU",
    "sg:address":"68 Patten St",
    "sg:city":"Sale",
    "sg:classifiers":[
        {
            "category":"Fast Food",
            "type":"Food & Drink"
        }
    ],
    "sg:phone":"+61 3 5144 1211",
    "sg:postcode":"3850",
    "sg:province":"VIC",
    "sg:tags":[
        "away",
        "take"
    ],
    "wof:name":"Get It India",
    "wof:placetype":"venue"
},
  "geometry": {"coordinates":[147.08853149399999,-38.1124038696],"type":"Point"}
}