{
  "type": "Feature",
  "properties": {
    "addr:full":"C/- 44A Standen St Murray Bridge SA 5253",
    "addr:postcode":"5253",
    "addr:street":"C / 44A Standen St",
    "iso:country":"AU",
    "sg:address":"C/- 44A Standen St",
    "sg:city":"Murray Bridge",
    "sg:classifiers":[
        {
            "category":"Arena",
            "subcategory":"Sports Club",
            "type":"Entertainment"
        }
    ],
    "sg:phone":"+61 418 319 217",
    "sg:postcode":"5253",
    "sg:province":"SA",
    "sg:tags":[
        "defence",
        "supply",
        "self",
        "instruction",
        "martial art"
    ],
    "wof:name":"Zen Do Ryu Freestyle Karate Academy",
    "wof:placetype":"venue"
},
  "geometry": {"coordinates":[139.270187378,-35.1236076355],"type":"Point"}
}