{
  "type": "Feature",
  "properties": {
    "addr:full":"17 Pipit Crt Caboolture QLD 4510",
    "addr:housenumber":"17",
    "addr:postcode":"4510",
    "addr:street":"Pipit Crt",
    "iso:country":"AU",
    "sg:address":"17 Pipit Crt",
    "sg:city":"Caboolture",
    "sg:classifiers":[
        {
            "category":"Building & Trades",
            "subcategory":"Landscaping Services",
            "type":"Services"
        }
    ],
    "sg:phone":"+61 409 281 600",
    "sg:postcode":"4510",
    "sg:province":"QLD",
    "sg:tags":[
        "designer",
        "landscape",
        "contractor"
    ],
    "wof:name":"Street Appeal Gardens",
    "wof:placetype":"venue"
},
  "geometry": {"coordinates":[152.91627500000001,-27.113981],"type":"Point"}
}