{
  "type": "Feature",
  "properties": {
    "addr:full":"2B Marlborough St Port Noarlunga South SA 5167",
    "addr:housenumber":"2b",
    "addr:postcode":"5167",
    "addr:street":"Marlborough St",
    "iso:country":"AU",
    "sg:address":"2B Marlborough St",
    "sg:city":"Port Noarlunga South",
    "sg:classifiers":[
        {
            "category":"Professional",
            "subcategory":"Art Services",
            "type":"Services"
        }
    ],
    "sg:phone":"+61 421 637 160",
    "sg:postcode":"5167",
    "sg:province":"SA",
    "sg:tags":[
        "product",
        "industrial",
        "designer"
    ],
    "wof:name":"ATC Design Solutions",
    "wof:placetype":"venue"
},
  "geometry": {"coordinates":[138.473587036,-35.1605567932],"type":"Point"}
}