{
  "type": "Feature",
  "properties": {
    "addr:full":"Shop 6 Whitsunday Arcade, Macalister St Mackay QLD 4740",
    "addr:housenumber":"shop 6",
    "addr:postcode":"4740",
    "addr:street":"Whitsunday Arcade Macalister St",
    "iso:country":"AU",
    "sg:address":"Shop 6 Whitsunday Arcade, Macalister St",
    "sg:city":"Mackay",
    "sg:classifiers":[
        {
            "category":"Banks & Credit Unions",
            "subcategory":"Financial Services",
            "type":"Services"
        }
    ],
    "sg:phone":"+61 7 4957 6602",
    "sg:postcode":"4740",
    "sg:province":"QLD",
    "sg:tags":[
        "coin"
    ],
    "wof:name":"John Platts Stamps & Coins",
    "wof:placetype":"venue"
},
  "geometry": {"coordinates":[149.18261699999999,-21.146034],"type":"Point"}
}