{
  "type": "Feature",
  "properties": {
    "addr:full":"100 Silverwater Rd Silverwater NSW 2128",
    "addr:housenumber":"100",
    "addr:postcode":"2128",
    "addr:street":"Silverwater Rd",
    "iso:country":"AU",
    "sg:address":"100 Silverwater Rd",
    "sg:city":"Silverwater",
    "sg:classifiers":[
        {
            "category":"Shopping",
            "subcategory":"Gifts & Souvenirs",
            "type":"Retail Goods"
        }
    ],
    "sg:phone":"+61 1300 738 555",
    "sg:postcode":"2128",
    "sg:province":"NSW",
    "sg:tags":[
        "shop",
        "supply"
    ],
    "wof:name":"Electus Distribution",
    "wof:placetype":"venue"
},
  "geometry": {"coordinates":[151.04844665499999,-33.8331108093],"type":"Point"}
}