{
  "type": "Feature",
  "properties": {
    "iso:country":"AU",
    "sg:address":"823 Acton Rd",
    "sg:city":"Acton Park",
    "sg:classifiers":[
        {
            "category":"Structure",
            "subcategory":"Office Building",
            "type":"Public Place"
        }
    ],
    "sg:phone":"+61 417 348 707",
    "sg:postcode":"7170",
    "sg:province":"TAS",
    "sg:tags":[
        "tie",
        "concrete",
        "formwork",
        "form",
        "accessory"
    ],
    "wof:name":"K A Constructions (Tas) Pty Ltd",
    "wof:placetype":"venue"
},
  "geometry": {"coordinates":[147.474685669,-42.8516197205],"type":"Point"}
}