{
  "type": "Feature",
  "properties": {
    "addr:full":"39 Collinsvale St Rocklea QLD 4106",
    "addr:housenumber":"39",
    "addr:postcode":"4106",
    "addr:street":"Collinsvale St",
    "iso:country":"AU",
    "sg:address":"39 Collinsvale St",
    "sg:city":"Rocklea",
    "sg:classifiers":[
        {
            "category":"Manufacturing",
            "subcategory":"Tools & Machinery",
            "type":"Manufacturing & Wholesale Goods"
        }
    ],
    "sg:phone":"+61 7 3277 5744",
    "sg:postcode":"4106",
    "sg:province":"QLD",
    "sg:tags":[
        "earth",
        "excavating",
        "moving",
        "equipment"
    ],
    "wof:name":"Ditch Witch Australia",
    "wof:placetype":"venue"
},
  "geometry": {"coordinates":[152.993484497,-27.5596218109],"type":"Point"}
}