{
  "type": "Feature",
  "properties": {
    "addr:full":"79 Waterloo Rd North Ryde NSW 2113",
    "addr:housenumber":"79",
    "addr:postcode":"2113",
    "addr:street":"Waterloo Rd",
    "iso:country":"AU",
    "sg:address":"79 Waterloo Rd",
    "sg:city":"North Ryde",
    "sg:classifiers":[
        {
            "category":"Professional",
            "subcategory":"Computer Services",
            "type":"Services"
        }
    ],
    "sg:phone":"+61 2 9889 4466",
    "sg:postcode":"2113",
    "sg:province":"NSW",
    "sg:tags":[
        "repairs",
        "upgrade",
        "equipment"
    ],
    "wof:name":"Lightning I.T.",
    "wof:placetype":"venue"
},
  "geometry": {"coordinates":[151.12466430699999,-33.7819824219],"type":"Point"}
}