{
  "type": "Feature",
  "properties": {
    "iso:country":"AU",
    "sg:address":"9 Charlston Pl",
    "sg:city":"Maroochydore",
    "sg:classifiers":[
        {
            "category":"Professional",
            "subcategory":"Detective & Security Services",
            "type":"Services"
        }
    ],
    "sg:phone":"+61 7 5443 5280",
    "sg:postcode":"4558",
    "sg:province":"QLD",
    "sg:tags":[
        "equipment",
        "window",
        "doors"
    ],
    "wof:name":"Action Screens & Glazing Pty Ltd",
    "wof:placetype":"venue"
},
  "geometry": {"coordinates":[153.05374145499999,-26.6556434631],"type":"Point"}
}