{
  "type": "Feature",
  "properties": {
    "addr:full":"3/ 35 Cranbrook Rd Batemans Bay NSW 2536",
    "addr:housenumber":"/ 35",
    "addr:postcode":"2536",
    "addr:street":"Cranbrook Rd",
    "iso:country":"AU",
    "sg:address":"3/ 35 Cranbrook Rd",
    "sg:city":"Batemans Bay",
    "sg:classifiers":[
        {
            "category":"Retail",
            "subcategory":"Auto Repair",
            "type":"Services"
        }
    ],
    "sg:phone":"+61 2 4478 6090",
    "sg:postcode":"2536",
    "sg:province":"NSW",
    "sg:tags":[
        "repairer",
        "motor",
        "engineer"
    ],
    "wof:name":"Jason Smith Automotive",
    "wof:placetype":"venue"
},
  "geometry": {"coordinates":[150.17083740199999,-35.7196311951],"type":"Point"}
}