{
  "type": "Feature",
  "properties": {
    "iso:country":"AU",
    "sg:address":"22 Broad St",
    "sg:city":"Sarina",
    "sg:classifiers":[
        {
            "category":"Travel",
            "subcategory":"Hotels & Motels",
            "type":"Entertainment"
        }
    ],
    "sg:phone":"+61 7 4943 1431",
    "sg:postcode":"4737",
    "sg:province":"QLD",
    "wof:name":"Sarina Motor Inn",
    "wof:placetype":"venue"
},
  "geometry": {"coordinates":[149.218094,-21.423914],"type":"Point"}
}