{
  "type": "Feature",
  "properties": {
    "addr:full":"2/ 53 Old Warrandyte Rd Donvale VIC 3111",
    "addr:housenumber":"/ 53",
    "addr:postcode":"3111",
    "addr:street":"Old Warrandyte Rd",
    "iso:country":"AU",
    "sg:address":"2/ 53 Old Warrandyte Rd",
    "sg:city":"Donvale",
    "sg:classifiers":[
        {
            "category":"Utilities",
            "subcategory":"Electric",
            "type":"Services"
        }
    ],
    "sg:phone":"+61 3 9483 7044",
    "sg:postcode":"3111",
    "sg:province":"VIC",
    "sg:tags":[
        "electrical",
        "contractor"
    ],
    "wof:name":"Bluethunder Services",
    "wof:placetype":"venue"
},
  "geometry": {"coordinates":[145.180374145,-37.7852706909],"type":"Point"}
}