{
  "type": "Feature",
  "properties": {
    "addr:full":"Mt Hooghly Rd Bet Bet VIC 3472",
    "addr:postcode":"3472",
    "addr:street":"Hooghly Rd",
    "iso:country":"AU",
    "sg:address":"Mt Hooghly Rd",
    "sg:city":"Bet Bet",
    "sg:classifiers":[
        {
            "category":"Retail",
            "subcategory":"Auto Repair",
            "type":"Services"
        }
    ],
    "sg:phone":"+61 3 5468 7318",
    "sg:postcode":"3472",
    "sg:province":"VIC",
    "sg:tags":[
        "electrical"
    ],
    "wof:name":"Goodman D & H",
    "wof:placetype":"venue"
},
  "geometry": {"coordinates":[143.67947387699999,-36.8808250427],"type":"Point"}
}