{
  "type": "Feature",
  "properties": {
    "addr:full":"175 Maroondah Hwy Ringwood VIC 3134",
    "addr:housenumber":"175",
    "addr:postcode":"3134",
    "addr:street":"Maroondah Hwy",
    "iso:country":"AU",
    "sg:address":"175 Maroondah Hwy",
    "sg:city":"Ringwood",
    "sg:classifiers":[
        {
            "category":"Shopping",
            "subcategory":"Jewelry",
            "type":"Retail Goods"
        }
    ],
    "sg:phone":"+61 3 9870 6758",
    "sg:postcode":"3134",
    "sg:province":"VIC",
    "sg:tags":[
        "jeweller"
    ],
    "wof:name":"Michael Hill Jeweller",
    "wof:placetype":"venue"
},
  "geometry": {"coordinates":[145.229537964,-37.8148956299],"type":"Point"}
}