{
  "type": "Feature",
  "properties": {
    "addr:full":"Ground Floor 13 London Cct Canberra ACT 2601",
    "addr:housenumber":"13",
    "addr:postcode":"2601",
    "addr:street":"London Cct",
    "iso:country":"AU",
    "sg:address":"Ground Floor 13",
    "sg:city":"London Cct Canberra",
    "sg:classifiers":[
        {
            "category":"Organizations",
            "subcategory":"Membership Organization",
            "type":"Services"
        }
    ],
    "sg:phone":"+61 2 6205 1325",
    "sg:postcode":"2601",
    "sg:province":"ACT",
    "sg:tags":[
        "support",
        "health",
        "organisation"
    ],
    "wof:name":"Healthpact",
    "wof:placetype":"venue"
},
  "geometry": {"coordinates":[149.12557983400001,-35.2810707092],"type":"Point"}
}