{
  "type": "Feature",
  "properties": {
    "iso:country":"AU",
    "sg:address":"Suite 9 / 66 Clarence St",
    "sg:city":"Port Macquarie",
    "sg:classifiers":[
        {
            "category":"Real Estate",
            "subcategory":"Architect",
            "type":"Services"
        }
    ],
    "sg:phone":"+61 2 6583 6393",
    "sg:postcode":"2444",
    "sg:province":"NSW",
    "sg:tags":[
        "building",
        "designer"
    ],
    "wof:name":"Steve Lockhart",
    "wof:placetype":"venue"
},
  "geometry": {"coordinates":[152.907135,-31.429361],"type":"Point"}
}