{
  "type": "Feature",
  "properties": {
    "iso:country":"AU",
    "sg:address":"1 Linear Ave",
    "sg:city":"Mullaloo",
    "sg:classifiers":[
        {
            "category":"Building & Trades",
            "subcategory":"Cleaning & Sanitation",
            "type":"Services"
        }
    ],
    "sg:phone":"+61 409 299 655",
    "sg:postcode":"6027",
    "sg:province":"WA",
    "sg:tags":[
        "chemical",
        "pressure",
        "steam",
        "contractor"
    ],
    "wof:name":"A Squirt It",
    "wof:placetype":"venue"
},
  "geometry": {"coordinates":[115.75048065199999,-31.7757549286],"type":"Point"}
}