{
  "type": "Feature",
  "properties": {
    "iso:country":"AU",
    "sg:address":"Shp 2/ 506 Mountain Hwy",
    "sg:city":"Bayswater",
    "sg:classifiers":[
        {
            "category":"Fast Food",
            "type":"Food & Drink"
        }
    ],
    "sg:phone":"+61 3 9720 2033",
    "sg:postcode":"3153",
    "sg:province":"VIC",
    "sg:tags":[
        "away",
        "take"
    ],
    "wof:name":"Sea Captain The",
    "wof:placetype":"venue"
},
  "geometry": {"coordinates":[145.246780395,-37.8440628052],"type":"Point"}
}