{
  "type": "Feature",
  "properties": {
    "addr:full":"144 Oakville Rd Oakville NSW 2765",
    "addr:housenumber":"144",
    "addr:postcode":"2765",
    "addr:street":"Oakville Rd",
    "iso:country":"AU",
    "sg:address":"144 Oakville Rd",
    "sg:city":"Oakville",
    "sg:classifiers":[
        {
            "category":"Manufacturing",
            "subcategory":"Metals",
            "type":"Manufacturing & Wholesale Goods"
        }
    ],
    "sg:phone":"+61 2 4572 3225",
    "sg:postcode":"2765",
    "sg:province":"NSW",
    "sg:tags":[
        "steel",
        "fabricator",
        "mfrs"
    ],
    "wof:name":"Chadweld Engineering & Steel Fabrication",
    "wof:placetype":"venue"
},
  "geometry": {"coordinates":[150.86203002900001,-33.6226272583],"type":"Point"}
}