{
  "type": "Feature",
  "properties": {
    "addr:full":"Shop 2 / 5 Church La Emerald QLD 4720",
    "addr:housenumber":"shop 2 / 5",
    "addr:postcode":"4720",
    "addr:street":"Church La",
    "iso:country":"AU",
    "sg:address":"Shop 2 / 5 Church La",
    "sg:city":"Emerald",
    "sg:classifiers":[
        {
            "category":"Personal",
            "subcategory":"Skin Care",
            "type":"Services"
        }
    ],
    "sg:phone":"+61 7 4982 1808",
    "sg:postcode":"4720",
    "sg:province":"QLD",
    "sg:tags":[
        "treatment"
    ],
    "wof:name":"Central Highlands Laser & Dermal Therapy Centre",
    "wof:placetype":"venue"
},
  "geometry": {"coordinates":[148.15763899999999,-23.520061],"type":"Point"}
}