{
  "type": "Feature",
  "properties": {
    "addr:full":"U 2/ 174 Forrest St Fremantle WA 6962",
    "addr:housenumber":"/ 174",
    "addr:postcode":"6962",
    "addr:street":"Forrest St",
    "iso:country":"AU",
    "sg:address":"U 2/ 174 Forrest St",
    "sg:city":"Fremantle",
    "sg:classifiers":[
        {
            "category":"Food & Beverages",
            "subcategory":"Fruits & Vegetables",
            "type":"Retail Goods"
        }
    ],
    "sg:phone":"+61 411 557 581",
    "sg:postcode":"6962",
    "sg:province":"WA",
    "sg:tags":[
        "consultant",
        "catering"
    ],
    "wof:name":"Cook In The Kitchen & Catering",
    "wof:placetype":"venue"
},
  "geometry": {"coordinates":[115.778397,-32.048122],"type":"Point"}
}