{
  "type": "Feature",
  "properties": {
    "iso:country":"AU",
    "sg:address":"Bayswater Primary School Gym Cnr Birch St & Mountain Hwy",
    "sg:city":"Bayswater",
    "sg:classifiers":[
        {
            "category":"Arena",
            "subcategory":"Sports Club",
            "type":"Entertainment"
        }
    ],
    "sg:phone":"+61 3 9723 4640",
    "sg:postcode":"3153",
    "sg:province":"VIC",
    "sg:tags":[
        "defence",
        "supply",
        "self",
        "instruction",
        "martial art"
    ],
    "wof:name":"No's Taekwondo",
    "wof:placetype":"venue"
},
  "geometry": {"coordinates":[145.259689331,-37.8428077698],"type":"Point"}
}