{
  "type": "Feature",
  "properties": {
    "addr:full":"6 Sarow Drv Warner QLD 4500",
    "addr:housenumber":"6",
    "addr:postcode":"4500",
    "addr:street":"Sarow Drv",
    "iso:country":"AU",
    "sg:address":"6 Sarow Drv",
    "sg:city":"Warner",
    "sg:classifiers":[
        {
            "category":"Building & Trades",
            "subcategory":"Equipment Rental",
            "type":"Services"
        }
    ],
    "sg:phone":"+61 408 746 675",
    "sg:postcode":"4500",
    "sg:province":"QLD",
    "sg:tags":[
        "crane",
        "hire"
    ],
    "wof:name":"Hickey M",
    "wof:placetype":"venue"
},
  "geometry": {"coordinates":[152.93930053700001,-27.2995567322],"type":"Point"}
}