{
  "type": "Feature",
  "properties": {
    "iso:country":"AU",
    "sg:address":"PO Box 2252",
    "sg:city":"Bowral",
    "sg:classifiers":[
        {
            "category":"Professional",
            "subcategory":"Art Services",
            "type":"Services"
        }
    ],
    "sg:phone":"+61 412 595 817",
    "sg:postcode":"2576",
    "sg:province":"NSW",
    "sg:tags":[
        "picture",
        "frame",
        "framing"
    ],
    "wof:name":"Art Installation",
    "wof:placetype":"venue"
},
  "geometry": {"coordinates":[150.385894775,-34.4550590515],"type":"Point"}
}