{
  "type": "Feature",
  "properties": {
    "addr:full":"17a Rose St Mile End SA 5031",
    "addr:housenumber":"17a",
    "addr:postcode":"5031",
    "addr:street":"Rose St",
    "iso:country":"AU",
    "sg:address":"17a Rose St",
    "sg:city":"Mile End",
    "sg:classifiers":[
        {
            "category":"Manufacturing",
            "subcategory":"Pottery",
            "type":"Manufacturing & Wholesale Goods"
        }
    ],
    "sg:phone":"+61 8 8443 4544",
    "sg:postcode":"5031",
    "sg:province":"SA",
    "wof:name":"The Pug Mill Pty Ltd",
    "wof:placetype":"venue"
},
  "geometry": {"coordinates":[138.57716369600001,-34.9221458435],"type":"Point"}
}