{
  "type": "Feature",
  "properties": {
    "addr:full":"56 Pentecost Ave Pymble NSW 2073",
    "addr:housenumber":"56",
    "addr:postcode":"2073",
    "addr:street":"Pentecost Ave",
    "iso:country":"AU",
    "sg:address":"56 Pentecost Ave",
    "sg:city":"Pymble",
    "sg:classifiers":[
        {
            "category":"Professional",
            "subcategory":"Management & Consulting",
            "type":"Services"
        }
    ],
    "sg:phone":"+61 2 9449 4557",
    "sg:postcode":"2073",
    "sg:province":"NSW",
    "sg:tags":[
        "consultant"
    ],
    "wof:name":"Pimstar Pty Ltd",
    "wof:placetype":"venue"
},
  "geometry": {"coordinates":[151.15249633799999,-33.7328491211],"type":"Point"}
}