{
  "type": "Feature",
  "properties": {
    "addr:full":"Ravensthorpe Rd Hyden WA 6359",
    "addr:postcode":"6359",
    "addr:street":"Ravensthorpe Rd",
    "iso:country":"AU",
    "sg:address":"Ravensthorpe Rd",
    "sg:city":"Hyden",
    "sg:classifiers":[
        {
            "category":"Sports & Exercise",
            "subcategory":"Golf",
            "type":"Entertainment"
        }
    ],
    "sg:phone":"+61 8 9880 5150",
    "sg:postcode":"6359",
    "sg:province":"WA",
    "sg:tags":[
        "club"
    ],
    "wof:name":"Hyden Golf Club",
    "wof:placetype":"venue"
},
  "geometry": {"coordinates":[118.865227,-32.44928],"type":"Point"}
}