{
  "type": "Feature",
  "properties": {
    "addr:full":"47 Eighth Ave Campsie NSW 2194",
    "addr:housenumber":"47",
    "addr:postcode":"2194",
    "addr:street":"Eighth Ave",
    "iso:country":"AU",
    "sg:address":"47 Eighth Ave",
    "sg:city":"Campsie",
    "sg:classifiers":[
        {
            "category":"Food & Beverages",
            "subcategory":"Groceries & Convenience Stores",
            "type":"Retail Goods"
        }
    ],
    "sg:phone":"+61 2 9787 4436",
    "sg:postcode":"2194",
    "sg:province":"NSW",
    "wof:name":"Ottogi Supermarket",
    "wof:placetype":"venue"
},
  "geometry": {"coordinates":[151.09913599999999,-33.906895],"type":"Point"}
}