{
  "type": "Feature",
  "properties": {
    "addr:full":"52 Days Rd Croydon Park SA 5008",
    "addr:housenumber":"52",
    "addr:postcode":"5008",
    "addr:street":"Days Rd",
    "iso:country":"AU",
    "sg:address":"52 Days Rd",
    "sg:city":"Croydon Park",
    "sg:classifiers":[
        {
            "category":"Home & Garden",
            "subcategory":"Furniture",
            "type":"Retail Goods"
        }
    ],
    "sg:phone":"+61 8 8346 1352",
    "sg:postcode":"5008",
    "sg:province":"SA",
    "sg:tags":[
        "repair",
        "restoration"
    ],
    "wof:name":"Adelaide Upholstering Service",
    "wof:placetype":"venue"
},
  "geometry": {"coordinates":[138.566406,-34.879353],"type":"Point"}
}