{
  "type": "Feature",
  "properties": {
    "iso:country":"AU",
    "sg:address":"892 Albany Hwy",
    "sg:city":"East Victoria Park",
    "sg:classifiers":[
        {
            "category":"Restaurant",
            "type":"Food & Drink"
        }
    ],
    "sg:phone":"+61 8 9472 0277",
    "sg:postcode":"6101",
    "sg:province":"WA",
    "wof:name":"Cinnamon On The Park",
    "wof:placetype":"venue"
},
  "geometry": {"coordinates":[115.904373169,-31.9862537384],"type":"Point"}
}