{
  "type": "Feature",
  "properties": {
    "addr:full":"138 Devonshire St Surry Hills NSW 2010",
    "addr:housenumber":"138",
    "addr:postcode":"2010",
    "addr:street":"Devonshire St",
    "iso:country":"AU",
    "sg:address":"138 Devonshire St",
    "sg:city":"Surry Hills",
    "sg:classifiers":[
        {
            "category":"Health Services",
            "subcategory":"Health Practitioner",
            "type":"Services"
        }
    ],
    "sg:phone":"+61 2 9690 0090",
    "sg:postcode":"2010",
    "sg:province":"NSW",
    "sg:tags":[
        "physiotherapist"
    ],
    "wof:name":"Magner Peter",
    "wof:placetype":"venue"
},
  "geometry": {"coordinates":[151.20945739699999,-33.8868865967],"type":"Point"}
}