{
  "type": "Feature",
  "properties": {
    "addr:full":"1/ 2 Walton St Kew VIC 3101",
    "addr:housenumber":"/ 2",
    "addr:postcode":"3101",
    "addr:street":"Walton St",
    "iso:country":"AU",
    "sg:address":"1/ 2 Walton St",
    "sg:city":"Kew",
    "sg:classifiers":[
        {
            "category":"Real Estate",
            "subcategory":"Architect",
            "type":"Services"
        }
    ],
    "sg:phone":"+61 3 9855 1222",
    "sg:postcode":"3101",
    "sg:province":"VIC",
    "wof:name":"Payne Pattenden Architects Pty Ltd",
    "wof:placetype":"venue"
},
  "geometry": {"coordinates":[145.03176879899999,-37.8056793213],"type":"Point"}
}