{
  "type": "Feature",
  "properties": {
    "addr:full":"Cnr Forest Rd & Stockton Ave Ferntree Gully VIC 3156",
    "addr:postcode":"3156",
    "addr:street":"Cnr Forest Rd & Stockton Ave",
    "iso:country":"AU",
    "sg:address":"Cnr Forest Rd & Stockton Ave",
    "sg:city":"Ferntree Gully",
    "sg:classifiers":[
        {
            "category":"Social Services",
            "subcategory":"Child Care",
            "type":"Services"
        }
    ],
    "sg:phone":"+61 3 9758 1004",
    "sg:postcode":"3156",
    "sg:province":"VIC",
    "sg:tags":[
        "support",
        "health"
    ],
    "wof:name":"Maternal & Child Health Centres",
    "wof:placetype":"venue"
},
  "geometry": {"coordinates":[145.296798706,-37.8838386536],"type":"Point"}
}