{
  "type": "Feature",
  "properties": {
    "addr:full":"Margaret St Redlynch QLD 4870",
    "addr:postcode":"4870",
    "addr:street":"Margaret St",
    "iso:country":"AU",
    "sg:address":"Margaret St",
    "sg:city":"Redlynch",
    "sg:classifiers":[
        {
            "category":"Retail",
            "subcategory":"Veterinary Services",
            "type":"Services"
        }
    ],
    "sg:phone":"+61 7 4039 3800",
    "sg:postcode":"4870",
    "sg:province":"QLD",
    "sg:tags":[
        "surgeon"
    ],
    "wof:name":"Redlynch Valley Vets",
    "wof:placetype":"venue"
},
  "geometry": {"coordinates":[145.69602966299999,-16.8885040283],"type":"Point"}
}