{
  "type": "Feature",
  "properties": {
    "addr:full":"17 Auckland St Wishart QLD 4122",
    "addr:housenumber":"17",
    "addr:postcode":"4122",
    "addr:street":"Auckland St",
    "iso:country":"AU",
    "sg:address":"17 Auckland St",
    "sg:city":"Wishart",
    "sg:classifiers":[
        {
            "category":"Building & Trades",
            "subcategory":"Cleaning & Sanitation",
            "type":"Services"
        }
    ],
    "sg:phone":"+61 1800 429 559",
    "sg:postcode":"4122",
    "sg:province":"QLD",
    "sg:tags":[
        "commercial",
        "maintenance"
    ],
    "wof:name":"1800 Maintenance Limited",
    "wof:placetype":"venue"
},
  "geometry": {"coordinates":[153.09466552699999,-27.5562553406],"type":"Point"}
}