{
  "type": "Feature",
  "properties": {
    "addr:full":"Shp1/ 8 Maple St Maleny QLD 4552",
    "addr:housenumber":"8",
    "addr:postcode":"4552",
    "addr:street":"Maple St",
    "iso:country":"AU",
    "sg:address":"Shp1/ 8 Maple St",
    "sg:city":"Maleny",
    "sg:classifiers":[
        {
            "category":"Cafe",
            "type":"Food & Drink"
        }
    ],
    "sg:phone":"+61 7 5499 9500",
    "sg:postcode":"4552",
    "sg:province":"QLD",
    "wof:name":"Captain Merv's Seafood",
    "wof:placetype":"venue"
},
  "geometry": {"coordinates":[152.85003662099999,-26.7581214905],"type":"Point"}
}