{
  "type": "Feature",
  "properties": {
    "addr:full":"U 7/ 19 Hawthorn Rd Caulfield North VIC 3161",
    "addr:housenumber":"19",
    "addr:postcode":"3161",
    "addr:street":"Hawthorn Rd",
    "iso:country":"AU",
    "sg:address":"U 7/ 19 Hawthorn Rd",
    "sg:city":"Caulfield North",
    "sg:classifiers":[
        {
            "category":"Professional",
            "subcategory":"Computer Services",
            "type":"Services"
        }
    ],
    "sg:phone":"+61 3 9509 2778",
    "sg:postcode":"3161",
    "sg:province":"VIC",
    "sg:tags":[
        "equipment",
        "networking",
        "installation"
    ],
    "wof:name":"Executive It Services Pty Ltd",
    "wof:placetype":"venue"
},
  "geometry": {"coordinates":[145.02574157699999,-37.8680152893],"type":"Point"}
}