{
  "type": "Feature",
  "properties": {
    "addr:full":"46 Riverview St Murwillumbah NSW 2484",
    "addr:housenumber":"46",
    "addr:postcode":"2484",
    "addr:street":"Riverview St",
    "iso:country":"AU",
    "sg:address":"46 Riverview St",
    "sg:city":"Murwillumbah",
    "sg:classifiers":[
        {
            "category":"Professional",
            "subcategory":"Art Services",
            "type":"Services"
        }
    ],
    "sg:phone":"+61 2 6672 3245",
    "sg:postcode":"2484",
    "sg:province":"NSW",
    "sg:tags":[
        "arranger",
        "music",
        "composer"
    ],
    "wof:name":"David John Weir",
    "wof:placetype":"venue"
},
  "geometry": {"coordinates":[153.391815186,-28.3302059174],"type":"Point"}
}