{
  "type": "Feature",
  "properties": {
    "iso:country":"AU",
    "sg:address":"PO Box 7",
    "sg:city":"Bullcreek",
    "sg:classifiers":[
        {
            "category":"Wholesale",
            "subcategory":"Non-durable Goods",
            "type":"Manufacturing & Wholesale Goods"
        }
    ],
    "sg:phone":"+61 8 9457 7945",
    "sg:postcode":"6149",
    "sg:province":"WA",
    "sg:tags":[
        "wholesaler",
        "craft",
        "mfrs"
    ],
    "wof:name":"Allcrafts Goods & Services",
    "wof:placetype":"venue"
},
  "geometry": {"coordinates":[115.87059,-32.066471],"type":"Point"}
}