{
  "type": "Feature",
  "properties": {
    "addr:full":"PO Box 3168 Weston Creek ACT 2611",
    "addr:postcode":"2611",
    "iso:country":"AU",
    "sg:address":"PO Box 3168",
    "sg:city":"Weston Creek",
    "sg:classifiers":[
        {
            "category":"Organizations",
            "subcategory":"Professional Association",
            "type":"Services"
        }
    ],
    "sg:phone":"+61 1300 889 461",
    "sg:postcode":"2611",
    "sg:province":"ACT",
    "sg:tags":[
        "web",
        "internet"
    ],
    "wof:name":"AussieHQ Pty Ltd",
    "wof:placetype":"venue"
},
  "geometry": {"coordinates":[149.052536011,-35.3397598267],"type":"Point"}
}