{
  "type": "Feature",
  "properties": {
    "addr:full":"MLC Centre, Lvl 10, Suite 1001 19 Martin Pl Sydney NSW 2000",
    "addr:housenumber":"19",
    "addr:postcode":"2000",
    "addr:street":"Martin Pl",
    "iso:country":"AU",
    "sg:address":"MLC Centre, Lvl 10, Suite 1001 19 Martin Pl",
    "sg:city":"Sydney",
    "sg:classifiers":[
        {
            "category":"Health Services",
            "subcategory":"Dentist",
            "type":"Services"
        }
    ],
    "sg:phone":"+61 2 9233 8762",
    "sg:postcode":"2000",
    "sg:province":"NSW",
    "wof:name":"Gallagher David",
    "wof:placetype":"venue"
},
  "geometry": {"coordinates":[151.209915161,-33.8659210205],"type":"Point"}
}