{
  "type": "Feature",
  "properties": {
    "addr:full":"Cnr Iolanthe & Through Sts (Opposite Bunnings) South Grafton NSW 2460",
    "addr:housenumber":"bunnings",
    "addr:postcode":"2460",
    "addr:street":"Cnr;Sts Opposite",
    "iso:country":"AU",
    "sg:address":"Cnr Iolanthe & Through Sts (Opposite Bunnings)",
    "sg:city":"South Grafton",
    "sg:classifiers":[
        {
            "category":"Wholesale",
            "subcategory":"Metals & Minerals",
            "type":"Manufacturing & Wholesale Goods"
        }
    ],
    "sg:phone":"+61 2 6643 1060",
    "sg:postcode":"2460",
    "sg:province":"NSW",
    "sg:tags":[
        "steel",
        "merchant"
    ],
    "wof:name":"Grafton Metal and Fabrication",
    "wof:placetype":"venue"
},
  "geometry": {"coordinates":[152.942871094,-29.7060470581],"type":"Point"}
}