{
  "type": "Feature",
  "properties": {
    "addr:full":"Suite 2 400 Barker Rd Subiaco WA 6008",
    "addr:housenumber":"400",
    "addr:postcode":"6008",
    "addr:street":"Barker Rd",
    "iso:country":"AU",
    "sg:address":"Suite 2 400 Barker Rd",
    "sg:city":"Subiaco",
    "sg:classifiers":[
        {
            "category":"Health Services",
            "subcategory":"Doctor",
            "type":"Services"
        }
    ],
    "sg:phone":"+61 8 9381 2400",
    "sg:postcode":"6008",
    "sg:province":"WA",
    "sg:tags":[
        "medical",
        "practitioner"
    ],
    "wof:name":"Farrell Louise Dr",
    "wof:placetype":"venue"
},
  "geometry": {"coordinates":[115.820587158,-31.9485588074],"type":"Point"}
}