{
  "type": "Feature",
  "properties": {
    "addr:full":"15 Belinda St Rye VIC 3941",
    "addr:housenumber":"15",
    "addr:postcode":"3941",
    "addr:street":"Belinda St",
    "iso:country":"AU",
    "sg:address":"15 Belinda St",
    "sg:city":"Rye",
    "sg:classifiers":[
        {
            "category":"Home & Garden",
            "subcategory":"Building Materials",
            "type":"Retail Goods"
        }
    ],
    "sg:phone":"+61 3 5985 9655",
    "sg:postcode":"3941",
    "sg:province":"VIC",
    "sg:tags":[
        "lawn",
        "cutting",
        "maintenance"
    ],
    "wof:name":"Rye Grass Home & Garden Care",
    "wof:placetype":"venue"
},
  "geometry": {"coordinates":[144.793533325,-38.3826446533],"type":"Point"}
}