{
  "type": "Feature",
  "properties": {
    "addr:full":"Bldg 27, 9 Ashley St West Footscray VIC 3012",
    "addr:housenumber":"9",
    "addr:postcode":"3012",
    "addr:street":"Ashley St",
    "iso:country":"AU",
    "sg:address":"Bldg 27, 9 Ashley St",
    "sg:city":"West Footscray",
    "sg:classifiers":[
        {
            "category":"Retail",
            "subcategory":"Storage",
            "type":"Services"
        }
    ],
    "sg:phone":"+61 3 9687 6498",
    "sg:postcode":"3012",
    "sg:province":"VIC",
    "wof:name":"Grace Records Management",
    "wof:placetype":"venue"
},
  "geometry": {"coordinates":[144.86216735799999,-37.7979698181],"type":"Point"}
}