{
  "type": "Feature",
  "properties": {
    "iso:country":"AU",
    "sg:address":"14 Sykamore Ave",
    "sg:city":"Emerald",
    "sg:classifiers":[
        {
            "category":"Building & Trades",
            "subcategory":"Construction",
            "type":"Services"
        }
    ],
    "sg:phone":"+61 3 5968 3277",
    "sg:postcode":"3782",
    "sg:province":"VIC",
    "sg:tags":[
        "contractor"
    ],
    "wof:name":"Glenola Constructions",
    "wof:placetype":"venue"
},
  "geometry": {"coordinates":[145.455368,-37.914879],"type":"Point"}
}