{
  "type": "Feature",
  "properties": {
    "addr:full":"14 Bridge St Balhannah SA 5242",
    "addr:housenumber":"14",
    "addr:postcode":"5242",
    "addr:street":"Bridge St",
    "iso:country":"AU",
    "sg:address":"14 Bridge St",
    "sg:city":"Balhannah",
    "sg:classifiers":[
        {
            "category":"Professional",
            "subcategory":"Accounting & Tax Preparation",
            "type":"Services"
        }
    ],
    "sg:phone":"+61 8 8388 4066",
    "sg:postcode":"5242",
    "sg:province":"SA",
    "sg:tags":[
        "accountant",
        "auditor"
    ],
    "wof:name":"EK Hemphill",
    "wof:placetype":"venue"
},
  "geometry": {"coordinates":[138.82635498100001,-34.989490509],"type":"Point"}
}