{
  "type": "Feature",
  "properties": {
    "addr:full":"118 Brown St Hamilton VIC 3300",
    "addr:housenumber":"118",
    "addr:postcode":"3300",
    "addr:street":"Brown St",
    "iso:country":"AU",
    "sg:address":"118 Brown St",
    "sg:city":"Hamilton",
    "sg:classifiers":[
        {
            "category":"Fast Food",
            "type":"Food & Drink"
        }
    ],
    "sg:phone":"+61 3 5571 1747",
    "sg:postcode":"3300",
    "sg:province":"VIC",
    "sg:tags":[
        "away",
        "take"
    ],
    "wof:name":"McDonald's Family Restaurants",
    "wof:placetype":"venue"
},
  "geometry": {"coordinates":[142.02377319300001,-37.7411956787],"type":"Point"}
}