{
  "type": "Feature",
  "properties": {
    "iso:country":"AU",
    "sg:address":"427 Victoria Ave",
    "sg:city":"Chatswood",
    "sg:classifiers":[
        {
            "category":"Health Services",
            "subcategory":"Dentist",
            "type":"Services"
        }
    ],
    "sg:phone":"+61 414 741 988",
    "sg:postcode":"2067",
    "sg:province":"NSW",
    "wof:name":"White Dental Clinic",
    "wof:placetype":"venue"
},
  "geometry": {"coordinates":[151.182937622,-33.7961235046],"type":"Point"}
}