{
  "type": "Feature",
  "properties": {
    "addr:full":"1216 Logan Rd Holland Park QLD 4121",
    "addr:housenumber":"1216",
    "addr:postcode":"4121",
    "addr:street":"Logan Rd",
    "iso:country":"AU",
    "sg:address":"1216 Logan Rd",
    "sg:city":"Holland Park",
    "sg:classifiers":[
        {
            "category":"Sports & Exercise",
            "subcategory":"Gym",
            "type":"Entertainment"
        }
    ],
    "sg:phone":"+61 413 883 070",
    "sg:postcode":"4121",
    "sg:province":"QLD",
    "sg:tags":[
        "personal",
        "trainer",
        "fitness"
    ],
    "wof:name":"STK Personal Training Services",
    "wof:placetype":"venue"
},
  "geometry": {"coordinates":[153.071533203,-27.528793335],"type":"Point"}
}