{
  "type": "Feature",
  "properties": {
    "addr:full":"4 Loch Carron Ave Farmborough Heights NSW 2526",
    "addr:housenumber":"4",
    "addr:postcode":"2526",
    "addr:street":"Loch Carron Ave",
    "iso:country":"AU",
    "sg:address":"4 Loch Carron Ave",
    "sg:city":"Farmborough Heights",
    "sg:classifiers":[
        {
            "category":"Home & Garden",
            "subcategory":"Building Materials",
            "type":"Retail Goods"
        }
    ],
    "sg:phone":"+61 2 4271 7777",
    "sg:postcode":"2526",
    "sg:province":"NSW",
    "sg:tags":[
        "concrete",
        "gutter",
        "kerb"
    ],
    "wof:name":"Kwik Kerb",
    "wof:placetype":"venue"
},
  "geometry": {"coordinates":[150.812210083,-34.4589805603],"type":"Point"}
}