{
  "type": "Feature",
  "properties": {
    "addr:full":"5 Albion St Waverley NSW 2024",
    "addr:housenumber":"5",
    "addr:postcode":"2024",
    "addr:street":"Albion St",
    "iso:country":"AU",
    "sg:address":"5 Albion St",
    "sg:city":"Waverley",
    "sg:classifiers":[
        {
            "category":"Shopping",
            "subcategory":"Clothing, Apparel, & Fashions",
            "type":"Retail Goods"
        }
    ],
    "sg:phone":"+61 2 9386 5656",
    "sg:postcode":"2024",
    "sg:province":"NSW",
    "sg:tags":[
        "boutique"
    ],
    "wof:name":"Rachel's Nest",
    "wof:placetype":"venue"
},
  "geometry": {"coordinates":[151.25468444800001,-33.902633667],"type":"Point"}
}