{
  "type": "Feature",
  "properties": {
    "addr:full":"74 Cochrane St Camira QLD 4300",
    "addr:housenumber":"74",
    "addr:postcode":"4300",
    "addr:street":"Cochrane St",
    "iso:country":"AU",
    "sg:address":"74 Cochrane St",
    "sg:city":"Camira",
    "sg:classifiers":[
        {
            "category":"Shopping",
            "subcategory":"Computers & Home Electronics",
            "type":"Retail Goods"
        }
    ],
    "sg:phone":"+61 7 3818 2641",
    "sg:postcode":"4300",
    "sg:province":"QLD",
    "sg:tags":[
        "equipment",
        "supply"
    ],
    "wof:name":"Dinky- Dye Inkjet Refills",
    "wof:placetype":"venue"
},
  "geometry": {"coordinates":[152.92535400400001,-27.6298828125],"type":"Point"}
}