{
  "type": "Feature",
  "properties": {
    "addr:full":"Unit 3/ 38 Cohn St Carlisle WA 6101",
    "addr:housenumber":"38",
    "addr:postcode":"6101",
    "addr:street":"Cohn St",
    "iso:country":"AU",
    "sg:address":"Unit 3/ 38 Cohn St",
    "sg:city":"Carlisle",
    "sg:classifiers":[
        {
            "category":"Retail",
            "subcategory":"Auto Repair",
            "type":"Services"
        }
    ],
    "sg:phone":"+61 8 9470 2444",
    "sg:postcode":"6101",
    "sg:province":"WA",
    "sg:tags":[
        "repairer",
        "motor",
        "engineer"
    ],
    "wof:name":"RMS Service Centre",
    "wof:placetype":"venue"
},
  "geometry": {"coordinates":[115.92456817599999,-31.9831619263],"type":"Point"}
}