{
  "type": "Feature",
  "properties": {
    "iso:country":"AU",
    "sg:address":"16 - 18 Eskay Rd",
    "sg:city":"Oakleigh South",
    "sg:classifiers":[
        {
            "category":"Professional",
            "subcategory":"Testing Lab",
            "type":"Services"
        }
    ],
    "sg:phone":"+61 3 9570 2883",
    "sg:postcode":"3167",
    "sg:province":"VIC",
    "sg:tags":[
        "inspection"
    ],
    "wof:name":"Thermoview East",
    "wof:placetype":"venue"
},
  "geometry": {"coordinates":[145.09260559099999,-37.9265899658],"type":"Point"}
}