{
  "type": "Feature",
  "properties": {
    "addr:full":"11 Toongabbie Crt Keysborough VIC 3173",
    "addr:housenumber":"11",
    "addr:postcode":"3173",
    "addr:street":"Toongabbie Crt",
    "iso:country":"AU",
    "sg:address":"11 Toongabbie Crt",
    "sg:city":"Keysborough",
    "sg:classifiers":[
        {
            "category":"Personal",
            "type":"Services"
        }
    ],
    "sg:phone":"+61 3 9701 8394",
    "sg:postcode":"3173",
    "sg:province":"VIC",
    "sg:tags":[
        "reducing",
        "treatment",
        "weight"
    ],
    "wof:name":"Alexander Brian",
    "wof:placetype":"venue"
},
  "geometry": {"coordinates":[145.17274475100001,-37.98462677],"type":"Point"}
}