{
  "type": "Feature",
  "properties": {
    "addr:full":"1096 Burwood Hwy Ferntree Gully VIC 3156",
    "addr:housenumber":"1096",
    "addr:postcode":"3156",
    "addr:street":"Burwood Hwy",
    "iso:country":"AU",
    "sg:address":"1096 Burwood Hwy",
    "sg:city":"Ferntree Gully",
    "sg:classifiers":[
        {
            "category":"Retail",
            "subcategory":"Funeral Services",
            "type":"Services"
        }
    ],
    "sg:phone":"+61 3 9758 2333",
    "sg:postcode":"3156",
    "sg:province":"VIC",
    "sg:tags":[
        "director"
    ],
    "wof:name":"Garner & Son",
    "wof:placetype":"venue"
},
  "geometry": {"coordinates":[145.295288086,-37.8887710571],"type":"Point"}
}