{
  "type": "Feature",
  "properties": {
    "iso:country":"AU",
    "sg:address":"U5/ 22 Lancaster St",
    "sg:city":"Ingleburn",
    "sg:classifiers":[
        {
            "category":"Autos & Motor Vehicles",
            "subcategory":"Boat Sales",
            "type":"Retail Goods"
        }
    ],
    "sg:phone":"+61 2 9605 5811",
    "sg:postcode":"2565",
    "sg:province":"NSW",
    "sg:tags":[
        "equipment",
        "yacht"
    ],
    "wof:name":"Record Marine",
    "wof:placetype":"venue"
},
  "geometry": {"coordinates":[150.862915039,-33.9928474426],"type":"Point"}
}