{
  "type": "Feature",
  "properties": {
    "iso:country":"AU",
    "sg:address":"121- 129",
    "sg:city":"Ridley Gr Ferryden Park",
    "sg:classifiers":[
        {
            "category":"Retail",
            "subcategory":"Self-service Laundry",
            "type":"Services"
        }
    ],
    "sg:phone":"+61 8 8255 8333",
    "sg:postcode":"5010",
    "sg:province":"SA",
    "wof:name":"Ferryden Park Laundrette",
    "wof:placetype":"venue"
},
  "geometry": {"coordinates":[138.55781555199999,-34.8639373779],"type":"Point"}
}