{
  "type": "Feature",
  "properties": {
    "addr:full":"Shp 25, 13 McLaren St Mt Barker SA 5251",
    "addr:housenumber":"13",
    "addr:postcode":"5251",
    "addr:street":"Mclaren St Mt",
    "iso:country":"AU",
    "sg:address":"Shp 25, 13 McLaren St",
    "sg:city":"Mt Barker",
    "sg:classifiers":[
        {
            "category":"Health Services",
            "subcategory":"Optometrist",
            "type":"Services"
        }
    ],
    "sg:phone":"+61 8 8391 0121",
    "sg:postcode":"5251",
    "sg:province":"SA",
    "wof:name":"OPSM",
    "wof:placetype":"venue"
},
  "geometry": {"coordinates":[138.861053467,-35.0659675598],"type":"Point"}
}