{
  "type": "Feature",
  "properties": {
    "addr:full":"Possum Brush Rd Taree NSW 2430",
    "addr:postcode":"2430",
    "addr:street":"Possum Brush Rd",
    "iso:country":"AU",
    "sg:address":"Possum Brush Rd",
    "sg:city":"Taree",
    "sg:classifiers":[
        {
            "category":"Cafe",
            "type":"Food & Drink"
        }
    ],
    "sg:phone":"+61 2 6554 3158",
    "sg:postcode":"2430",
    "sg:province":"NSW",
    "wof:name":"Possum Brush Gallery",
    "wof:placetype":"venue"
},
  "geometry": {"coordinates":[152.354996,-31.957214],"type":"Point"}
}