{
  "type": "Feature",
  "properties": {
    "addr:full":"5 McHarry Pl Shepparton VIC 3630",
    "addr:housenumber":"5",
    "addr:postcode":"3630",
    "addr:street":"Mcharry Pl",
    "iso:country":"AU",
    "sg:address":"5 McHarry Pl",
    "sg:city":"Shepparton",
    "sg:classifiers":[
        {
            "category":"Retail",
            "subcategory":"Storage",
            "type":"Services"
        }
    ],
    "sg:phone":"+61 3 5822 0825",
    "sg:postcode":"3630",
    "sg:province":"VIC",
    "sg:tags":[
        "shelving",
        "system"
    ],
    "wof:name":"G.V. Pallet Racking",
    "wof:placetype":"venue"
},
  "geometry": {"coordinates":[145.42477417000001,-36.3726272583],"type":"Point"}
}