{
  "type": "Feature",
  "properties": {
    "addr:full":"Fullerton St Stockton NSW 2295",
    "addr:postcode":"2295",
    "addr:street":"Fullerton St",
    "iso:country":"AU",
    "sg:address":"Fullerton St",
    "sg:city":"Stockton",
    "sg:classifiers":[
        {
            "category":"Organizations",
            "subcategory":"Non-profit Organization",
            "type":"Services"
        }
    ],
    "sg:phone":"+61 2 4928 0800",
    "sg:postcode":"2295",
    "sg:province":"NSW",
    "sg:tags":[
        "support",
        "disability",
        "organisation"
    ],
    "wof:name":"Kanangra Centre(Hunter Region Developmental Disability Service)",
    "wof:placetype":"venue"
},
  "geometry": {"coordinates":[151.78147888199999,-32.9164543152],"type":"Point"}
}