{
  "type": "Feature",
  "properties": {
    "addr:full":"79 Temple St Heyfield VIC 3858",
    "addr:housenumber":"79",
    "addr:postcode":"3858",
    "addr:street":"Temple St",
    "iso:country":"AU",
    "sg:address":"79 Temple St",
    "sg:city":"Heyfield",
    "sg:classifiers":[
        {
            "category":"Personal",
            "subcategory":"Massage",
            "type":"Services"
        }
    ],
    "sg:phone":"+61 3 5148 2400",
    "sg:postcode":"3858",
    "sg:province":"VIC",
    "sg:tags":[
        "therapy"
    ],
    "wof:name":"Heyfield Remedial Massage",
    "wof:placetype":"venue"
},
  "geometry": {"coordinates":[146.78482055699999,-37.9845046997],"type":"Point"}
}