{
  "type": "Feature",
  "properties": {
    "addr:full":"122 Mooroondu Rd Thorneside QLD 4158",
    "addr:housenumber":"122",
    "addr:postcode":"4158",
    "addr:street":"Mooroondu Rd",
    "iso:country":"AU",
    "sg:address":"122 Mooroondu Rd",
    "sg:city":"Thorneside",
    "sg:classifiers":[
        {
            "category":"Retail",
            "subcategory":"Auto Repair",
            "type":"Services"
        }
    ],
    "sg:phone":"+61 412 879 448",
    "sg:postcode":"4158",
    "sg:province":"QLD",
    "sg:tags":[
        "repairer",
        "motor",
        "engineer"
    ],
    "wof:name":"Phone-A-Home Mechanic",
    "wof:placetype":"venue"
},
  "geometry": {"coordinates":[153.20318603499999,-27.4811191559],"type":"Point"}
}