{
  "type": "Feature",
  "properties": {
    "addr:full":"13- 14 Dashwood Pl Darwin NT 0800",
    "addr:housenumber":"14",
    "addr:postcode":"nt 0800",
    "iso:country":"AU",
    "sg:address":"13- 14 Dashwood Pl",
    "sg:city":"Darwin",
    "sg:classifiers":[
        {
            "category":"Shopping",
            "subcategory":"Stationery & Office Supplies",
            "type":"Retail Goods"
        }
    ],
    "sg:phone":"+61 8 8981 5288",
    "sg:postcode":"0800",
    "sg:province":"NT",
    "sg:tags":[
        "equipment",
        "facsimile"
    ],
    "wof:name":"Darwin Business Machines Pty Ltd",
    "wof:placetype":"venue"
},
  "geometry": {"coordinates":[130.83700561500001,-12.4550819397],"type":"Point"}
}