{
  "type": "Feature",
  "properties": {
    "iso:country":"AU",
    "sg:address":"7 Middle St",
    "sg:city":"Forster",
    "sg:classifiers":[
        {
            "category":"Home & Garden",
            "subcategory":"Carpets & Floor Coverings",
            "type":"Retail Goods"
        }
    ],
    "sg:phone":"+61 2 6557 5076",
    "sg:postcode":"2428",
    "sg:province":"NSW",
    "sg:tags":[
        "wood"
    ],
    "wof:name":"Johnson Steve",
    "wof:placetype":"venue"
},
  "geometry": {"coordinates":[152.51448099999999,-32.184181],"type":"Point"}
}