{
  "type": "Feature",
  "properties": {
    "addr:full":"PO Box 179 Eumundi QLD 4562",
    "addr:postcode":"4562",
    "iso:country":"AU",
    "sg:address":"PO Box 179",
    "sg:city":"Eumundi",
    "sg:classifiers":[
        {
            "category":"Shopping",
            "subcategory":"Gifts & Souvenirs",
            "type":"Retail Goods"
        }
    ],
    "sg:phone":"+61 412 114 321",
    "sg:postcode":"4562",
    "sg:province":"QLD",
    "sg:tags":[
        "wrapping"
    ],
    "wof:name":"Classy Gift Wraps",
    "wof:placetype":"venue"
},
  "geometry": {"coordinates":[152.95066833499999,-26.4752693176],"type":"Point"}
}