{
  "type": "Feature",
  "properties": {
    "addr:full":"13a Godfrey St Walliston WA 6076",
    "addr:housenumber":"13a",
    "addr:postcode":"6076",
    "addr:street":"Godfrey St",
    "iso:country":"AU",
    "sg:address":"13a Godfrey St",
    "sg:city":"Walliston",
    "sg:classifiers":[
        {
            "category":"Professional",
            "type":"Services"
        }
    ],
    "sg:phone":"+61 8 9291 6196",
    "sg:postcode":"6076",
    "sg:province":"WA",
    "sg:tags":[
        "spray",
        "painting"
    ],
    "wof:name":"Michaelangelos Panel & Paint",
    "wof:placetype":"venue"
},
  "geometry": {"coordinates":[116.07128906200001,-31.9949989319],"type":"Point"}
}