{
  "type": "Feature",
  "properties": {
    "addr:full":"165 Canterbury Rd Bankstown NSW 2200",
    "addr:housenumber":"165",
    "addr:postcode":"2200",
    "addr:street":"Canterbury Rd",
    "iso:country":"AU",
    "sg:address":"165 Canterbury Rd",
    "sg:city":"Bankstown",
    "sg:classifiers":[
        {
            "category":"Home & Garden",
            "subcategory":"Building Materials",
            "type":"Retail Goods"
        }
    ],
    "sg:phone":"+61 2 9790 1984",
    "sg:postcode":"2200",
    "sg:province":"NSW",
    "sg:tags":[
        "supply"
    ],
    "wof:name":"Bansktown Building Suppliers Pty Ltd",
    "wof:placetype":"venue"
},
  "geometry": {"coordinates":[151.03005999999999,-33.933865],"type":"Point"}
}