{
  "type": "Feature",
  "properties": {
    "addr:full":"126- 140 Churchill Rd North Dry Creek SA 5094",
    "addr:housenumber":"140",
    "addr:postcode":"5094",
    "addr:street":"Churchill Rd North Dry",
    "iso:country":"AU",
    "sg:address":"126- 140 Churchill Rd",
    "sg:city":"North Dry Creek",
    "sg:classifiers":[
        {
            "category":"Banks & Credit Unions",
            "subcategory":"Bank",
            "type":"Services"
        }
    ],
    "sg:phone":"+61 13 15 57",
    "sg:postcode":"5094",
    "sg:province":"SA",
    "sg:tags":[
        "concrete",
        "reinforcement"
    ],
    "wof:name":"Smorgon Steel Reinforcing",
    "wof:placetype":"venue"
},
  "geometry": {"coordinates":[138.59144592300001,-34.8336334229],"type":"Point"}
}