{
  "type": "Feature",
  "properties": {
    "iso:country":"AU",
    "sg:address":"395 Main Rd",
    "sg:city":"Coromandel Valley",
    "sg:classifiers":[
        {
            "category":"Home & Garden",
            "subcategory":"Garden Supply",
            "type":"Retail Goods"
        }
    ],
    "sg:phone":"+61 8 8278 6133",
    "sg:postcode":"5051",
    "sg:province":"SA",
    "sg:tags":[
        "equipment"
    ],
    "wof:name":"Blackwood Landscape & Firewood Supplies",
    "wof:placetype":"venue"
},
  "geometry": {"coordinates":[138.622757,-35.043941],"type":"Point"}
}