{
  "type": "Feature",
  "properties": {
    "addr:full":"69 Napier St South Melbourne VIC 3205",
    "addr:housenumber":"69",
    "addr:postcode":"3205",
    "addr:street":"Napier St",
    "iso:country":"AU",
    "sg:address":"69 Napier St",
    "sg:city":"South Melbourne",
    "sg:classifiers":[
        {
            "category":"Professional",
            "subcategory":"Management & Consulting",
            "type":"Services"
        }
    ],
    "sg:phone":"+61 3 9696 9038",
    "sg:postcode":"3205",
    "sg:province":"VIC",
    "sg:tags":[
        "consultant"
    ],
    "wof:name":"Fast Track Assets Pty Ltd",
    "wof:placetype":"venue"
},
  "geometry": {"coordinates":[144.966904,-37.83506],"type":"Point"}
}