{
  "type": "Feature",
  "properties": {
    "addr:full":"PO Box 6332 Tweed Heads South QLD 2486",
    "addr:postcode":"2486",
    "iso:country":"AU",
    "sg:address":"PO Box 6332",
    "sg:city":"Tweed Heads South",
    "sg:classifiers":[
        {
            "category":"Shopping",
            "subcategory":"Stationery & Office Supplies",
            "type":"Retail Goods"
        }
    ],
    "sg:phone":"+61 7 5590 9398",
    "sg:postcode":"2486",
    "sg:province":"QLD",
    "sg:tags":[
        "equipment",
        "display",
        "exhibition"
    ],
    "wof:name":"Border Event Hire",
    "wof:placetype":"venue"
},
  "geometry": {"coordinates":[153.46539306599999,-28.2249069214],"type":"Point"}
}