{
  "type": "Feature",
  "properties": {
    "addr:full":"7 Beedham St Clontarf QLD 4019",
    "addr:housenumber":"7",
    "addr:postcode":"4019",
    "addr:street":"Beedham St",
    "iso:country":"AU",
    "sg:address":"7 Beedham St",
    "sg:city":"Clontarf",
    "sg:classifiers":[
        {
            "category":"Insurance",
            "subcategory":"Insurance Agent",
            "type":"Services"
        }
    ],
    "sg:phone":"+61 7 3284 9978",
    "sg:postcode":"4019",
    "sg:province":"QLD",
    "wof:name":"Anita Muecke Insurance & Financial Advice",
    "wof:placetype":"venue"
},
  "geometry": {"coordinates":[153.09182739299999,-27.2463302612],"type":"Point"}
}