{
  "type": "Feature",
  "properties": {
    "iso:country":"AU",
    "sg:address":"Argyle St",
    "sg:city":"Fawkner",
    "sg:classifiers":[
        {
            "category":"Education",
            "subcategory":"School",
            "type":"Public Place"
        }
    ],
    "sg:phone":"+61 3 9359 6463",
    "sg:postcode":"3060",
    "sg:province":"VIC",
    "sg:tags":[
        "co-educational"
    ],
    "wof:name":"St Mark's Parish Primary",
    "wof:placetype":"venue"
},
  "geometry": {"coordinates":[144.96711730999999,-37.7172431946],"type":"Point"}
}