{
  "type": "Feature",
  "properties": {
    "addr:full":"5 Victoria St Bunbury WA 6230",
    "addr:housenumber":"5",
    "addr:postcode":"6230",
    "addr:street":"Victoria St",
    "iso:country":"AU",
    "sg:address":"5 Victoria St",
    "sg:city":"Bunbury",
    "sg:classifiers":[
        {
            "category":"Manufacturing",
            "subcategory":"Pottery",
            "type":"Manufacturing & Wholesale Goods"
        }
    ],
    "sg:phone":"+61 8 9791 2266",
    "sg:postcode":"6230",
    "sg:province":"WA",
    "wof:name":"Port Pottery The",
    "wof:placetype":"venue"
},
  "geometry": {"coordinates":[115.636703,-33.318748],"type":"Point"}
}