{
  "type": "Feature",
  "properties": {
    "addr:full":"108-130 Diamond Creek Rd Greensborough VIC 3088",
    "addr:housenumber":"108-130",
    "addr:postcode":"3088",
    "addr:street":"Diamond Creek Rd",
    "iso:country":"AU",
    "sg:address":"108-130 Diamond Creek Rd",
    "sg:city":"Greensborough",
    "sg:classifiers":[
        {
            "category":"Organizations",
            "subcategory":"Non-profit Organization",
            "type":"Services"
        }
    ],
    "sg:phone":"+61 3 9434 5199",
    "sg:postcode":"3088",
    "sg:province":"VIC",
    "sg:tags":[
        "support",
        "disability",
        "organisation"
    ],
    "wof:name":"Churinga Employment Support Services",
    "wof:placetype":"venue"
},
  "geometry": {"coordinates":[145.114044189,-37.6903038025],"type":"Point"}
}