{
  "type": "Feature",
  "properties": {
    "iso:country":"AU",
    "sg:address":"Unit 2 No.11 Eddie Rd",
    "sg:city":"Minchinbury",
    "sg:classifiers":[
        {
            "category":"Home & Garden",
            "subcategory":"Building Materials",
            "type":"Retail Goods"
        }
    ],
    "sg:phone":"+61 2 9832 3763",
    "sg:postcode":"2770",
    "sg:province":"NSW",
    "sg:tags":[
        "laminate",
        "laminated",
        "panel"
    ],
    "wof:name":"Western Sydney Postforming Pty Ltd",
    "wof:placetype":"venue"
},
  "geometry": {"coordinates":[150.815582275,-33.7836608887],"type":"Point"}
}