{
  "type": "Feature",
  "properties": {
    "addr:full":"1/ 2 Isa St Fyshwick ACT 2609",
    "addr:housenumber":"/ 2",
    "addr:postcode":"2609",
    "addr:street":"Isa St",
    "iso:country":"AU",
    "sg:address":"1/ 2 Isa St",
    "sg:city":"Fyshwick",
    "sg:classifiers":[
        {
            "category":"Banks & Credit Unions",
            "subcategory":"Financial Services",
            "type":"Services"
        }
    ],
    "sg:phone":"+61 2 6236 9811",
    "sg:postcode":"2609",
    "sg:province":"ACT",
    "sg:tags":[
        "financier"
    ],
    "wof:name":"Capital Business Services",
    "wof:placetype":"venue"
},
  "geometry": {"coordinates":[149.17124939000001,-35.3279685974],"type":"Point"}
}