{
  "type": "Feature",
  "properties": {
    "iso:country":"AU",
    "sg:address":"Un 81, 149 Pyrmont St",
    "sg:city":"Pyrmont",
    "sg:classifiers":[
        {
            "category":"Professional",
            "subcategory":"Management & Consulting",
            "type":"Services"
        }
    ],
    "sg:phone":"+61 2 9552 1762",
    "sg:postcode":"2009",
    "sg:province":"NSW",
    "sg:tags":[
        "project"
    ],
    "wof:name":"Jo Louw Engineering Services Pty Ltd",
    "wof:placetype":"venue"
},
  "geometry": {"coordinates":[151.195709228,-33.8709793091],"type":"Point"}
}