{
  "type": "Feature",
  "properties": {
    "addr:full":"353 Balcombe Rd Beaumaris VIC 3193",
    "addr:housenumber":"353",
    "addr:postcode":"3193",
    "addr:street":"Balcombe Rd",
    "iso:country":"AU",
    "sg:address":"353 Balcombe Rd",
    "sg:city":"Beaumaris",
    "sg:classifiers":[
        {
            "category":"Personal",
            "subcategory":"Beauty Salon",
            "type":"Services"
        }
    ],
    "sg:phone":"+61 3 9589 5988",
    "sg:postcode":"3193",
    "sg:province":"VIC",
    "sg:tags":[
        "hairdresser"
    ],
    "wof:name":"Art Hair Studios",
    "wof:placetype":"venue"
},
  "geometry": {"coordinates":[145.04518127399999,-37.9789924622],"type":"Point"}
}