{
  "type": "Feature",
  "properties": {
    "iso:country":"AU",
    "sg:address":"161 Tongarra St",
    "sg:city":"Albion Park",
    "sg:classifiers":[
        {
            "category":"Food & Beverages",
            "subcategory":"Bakery",
            "type":"Retail Goods"
        }
    ],
    "sg:phone":"+61 2 4256 6053",
    "sg:postcode":"2527",
    "sg:province":"NSW",
    "sg:tags":[
        "baker"
    ],
    "wof:name":"Albion Park Bakery",
    "wof:placetype":"venue"
},
  "geometry": {"coordinates":[150.68646240199999,-34.5899848938],"type":"Point"}
}