{
  "type": "Feature",
  "properties": {
    "addr:full":"20 Elsegood St Dianella WA 6059",
    "addr:housenumber":"20",
    "addr:postcode":"6059",
    "addr:street":"Elsegood St",
    "iso:country":"AU",
    "sg:address":"20 Elsegood St",
    "sg:city":"Dianella",
    "sg:classifiers":[
        {
            "category":"Social Services",
            "subcategory":"Retirement Home",
            "type":"Services"
        }
    ],
    "sg:phone":"+61 8 9371 9907",
    "sg:postcode":"6059",
    "sg:province":"WA",
    "sg:tags":[
        "decoration",
        "supplier",
        "contractor"
    ],
    "wof:name":"Classique Celebrations",
    "wof:placetype":"venue"
},
  "geometry": {"coordinates":[115.87690734900001,-31.9073238373],"type":"Point"}
}