{
  "type": "Feature",
  "properties": {
    "addr:full":"11 Victoria Rd Balga WA 6061",
    "addr:housenumber":"11",
    "addr:postcode":"6061",
    "addr:street":"Victoria Rd",
    "iso:country":"AU",
    "sg:address":"11 Victoria Rd",
    "sg:city":"Balga",
    "sg:classifiers":[
        {
            "category":"Health Services",
            "subcategory":"Dentist",
            "type":"Services"
        }
    ],
    "sg:phone":"+61 8 9344 7420",
    "sg:postcode":"6061",
    "sg:province":"WA",
    "wof:name":"Gabrielle Ly",
    "wof:placetype":"venue"
},
  "geometry": {"coordinates":[115.828308105,-31.8613491058],"type":"Point"}
}