{
  "type": "Feature",
  "properties": {
    "addr:full":"1911 Greenhill Rd Uraidla SA 5142",
    "addr:housenumber":"1911",
    "addr:postcode":"5142",
    "addr:street":"Greenhill Rd",
    "iso:country":"AU",
    "sg:address":"1911 Greenhill Rd",
    "sg:city":"Uraidla",
    "sg:classifiers":[
        {
            "category":"Government",
            "subcategory":"Post Office",
            "type":"Public Place"
        }
    ],
    "sg:phone":"+61 8 8390 3041",
    "sg:postcode":"5142",
    "sg:province":"SA",
    "sg:tags":[
        "postal"
    ],
    "wof:name":"Australia Post",
    "wof:placetype":"venue"
},
  "geometry": {"coordinates":[138.745743,-34.957203],"type":"Point"}
}