{
  "type": "Feature",
  "properties": {
    "iso:country":"AU",
    "sg:address":"Unit 3/ 506 Nepean Hwy",
    "sg:city":"Frankston",
    "sg:classifiers":[
        {
            "category":"Professional",
            "subcategory":"Accounting & Tax Preparation",
            "type":"Services"
        }
    ],
    "sg:phone":"+61 3 9770 1563",
    "sg:postcode":"3199",
    "sg:province":"VIC",
    "sg:tags":[
        "accountant",
        "auditor"
    ],
    "wof:name":"L. I. Harper & Associates Chartered Accountants Business Consultants Internationally.",
    "wof:placetype":"venue"
},
  "geometry": {"coordinates":[145.11976623499999,-38.145111084],"type":"Point"}
}