{
  "type": "Feature",
  "properties": {
    "iso:country":"AU",
    "sg:address":"185 High St",
    "sg:city":"Prahran",
    "sg:classifiers":[
        {
            "category":"Shopping",
            "subcategory":"Party Supplies",
            "type":"Retail Goods"
        }
    ],
    "sg:phone":"+61 3 9533 6433",
    "sg:postcode":"3181",
    "sg:province":"VIC",
    "sg:tags":[
        "hire",
        "costume"
    ],
    "wof:name":"Tiara Costume Design",
    "wof:placetype":"venue"
},
  "geometry": {"coordinates":[144.99435424800001,-37.8518295288],"type":"Point"}
}