{
  "type": "Feature",
  "properties": {
    "iso:country":"AU",
    "sg:address":"677 Great Northern Hwy",
    "sg:city":"Herne Hill",
    "sg:classifiers":[
        {
            "category":"Retail",
            "subcategory":"Auto Repair",
            "type":"Services"
        }
    ],
    "sg:phone":"+61 8 9296 6555",
    "sg:postcode":"6056",
    "sg:province":"WA",
    "sg:tags":[
        "repairer",
        "motor",
        "engineer"
    ],
    "wof:name":"Andrews Automotives",
    "wof:placetype":"venue"
},
  "geometry": {"coordinates":[116.017021179,-31.8243141174],"type":"Point"}
}