{
  "type": "Feature",
  "properties": {
    "iso:country":"AU",
    "sg:address":"Cnr Ranford & Campbell Rds",
    "sg:city":"Canning Vale",
    "sg:classifiers":[
        {
            "category":"Health Services",
            "subcategory":"Medical Lab",
            "type":"Services"
        }
    ],
    "sg:phone":"+61 8 9456 0239",
    "sg:postcode":"6155",
    "sg:province":"WA",
    "sg:tags":[
        "laboratory",
        "pathology"
    ],
    "wof:name":"St John Of God Pathology (WA)",
    "wof:placetype":"venue"
},
  "geometry": {"coordinates":[115.9226,-32.091831],"type":"Point"}
}