{
  "type": "Feature",
  "properties": {
    "addr:full":"Lvl 28 333 Collins St Melbourne VIC 3000",
    "addr:housenumber":"333",
    "addr:postcode":"3000",
    "addr:street":"Collins St",
    "iso:country":"AU",
    "sg:address":"Lvl 28 333 Collins St",
    "sg:city":"Melbourne",
    "sg:classifiers":[
        {
            "category":"Insurance",
            "subcategory":"Insurance Agent",
            "type":"Services"
        }
    ],
    "sg:phone":"+61 3 9611 0500",
    "sg:postcode":"3000",
    "sg:province":"VIC",
    "wof:name":"Munich-American Riskpartners Australia Pty Ltd",
    "wof:placetype":"venue"
},
  "geometry": {"coordinates":[144.96321105999999,-37.8165855408],"type":"Point"}
}