{
  "type": "Feature",
  "properties": {
    "iso:country":"AU",
    "sg:address":"4 Parkgate Crt",
    "sg:city":"Upper Sturt",
    "sg:classifiers":[
        {
            "category":"Government",
            "subcategory":"Fire Station",
            "type":"Public Place"
        }
    ],
    "sg:phone":"+61 417 824 106",
    "sg:postcode":"5156",
    "sg:province":"SA",
    "sg:tags":[
        "equipment",
        "protection",
        "consultant"
    ],
    "wof:name":"Fire Training & Safety Service",
    "wof:placetype":"venue"
},
  "geometry": {"coordinates":[138.68023681599999,-35.0196495056],"type":"Point"}
}