{
  "type": "Feature",
  "properties": {
    "iso:country":"AU",
    "sg:address":"37 River Rd",
    "sg:city":"Wivenhoe",
    "sg:classifiers":[
        {
            "category":"Wholesale",
            "subcategory":"Metals & Minerals",
            "type":"Manufacturing & Wholesale Goods"
        }
    ],
    "sg:phone":"+61 3 6431 9303",
    "sg:postcode":"7320",
    "sg:province":"TAS",
    "sg:tags":[
        "steel",
        "merchant"
    ],
    "wof:name":"Metaland",
    "wof:placetype":"venue"
},
  "geometry": {"coordinates":[145.924637,-41.073296],"type":"Point"}
}