{
  "type": "Feature",
  "properties": {
    "iso:country":"AU",
    "sg:address":"\"Greenwood Farm\" Greenwood Rd",
    "sg:city":"Gingin",
    "sg:classifiers":[
        {
            "category":"Building & Trades",
            "subcategory":"Landscaping Services",
            "type":"Services"
        }
    ],
    "sg:phone":"+61 8 9655 3021",
    "sg:postcode":"6503",
    "sg:province":"WA",
    "sg:tags":[
        "grazier"
    ],
    "wof:name":"Nixon M D & M E",
    "wof:placetype":"venue"
},
  "geometry": {"coordinates":[115.594788,-31.220152],"type":"Point"}
}