{
  "type": "Feature",
  "properties": {
    "addr:full":"22 High St Kyneton VIC 3444",
    "addr:housenumber":"22",
    "addr:postcode":"3444",
    "addr:street":"High St",
    "iso:country":"AU",
    "sg:address":"22 High St",
    "sg:city":"Kyneton",
    "sg:classifiers":[
        {
            "category":"Shopping",
            "subcategory":"Clothing, Apparel, & Fashions",
            "type":"Retail Goods"
        }
    ],
    "sg:phone":"+61 3 5422 7244",
    "sg:postcode":"3444",
    "sg:province":"VIC",
    "sg:tags":[
        "lady",
        "wear"
    ],
    "wof:name":"Debz Fashion On The Move",
    "wof:placetype":"venue"
},
  "geometry": {"coordinates":[144.453567505,-37.2490997314],"type":"Point"}
}