{
  "type": "Feature",
  "properties": {
    "iso:country":"AU",
    "sg:address":"Unit 4/ 34 Station Rd",
    "sg:city":"Margaret River",
    "sg:classifiers":[
        {
            "category":"Retail",
            "subcategory":"Repair Shop",
            "type":"Services"
        }
    ],
    "sg:phone":"+61 8 9757 3820",
    "sg:postcode":"6285",
    "sg:province":"WA",
    "sg:tags":[
        "upholsterer"
    ],
    "wof:name":"Ray McCann Custom Upholsterers",
    "wof:placetype":"venue"
},
  "geometry": {"coordinates":[115.06955719,-33.9578781128],"type":"Point"}
}