{
  "type": "Feature",
  "properties": {
    "addr:full":"Unit 2 96 Tribute St Willetton WA 6155",
    "addr:housenumber":"96",
    "addr:postcode":"6155",
    "addr:street":"Tribute St",
    "iso:country":"AU",
    "sg:address":"Unit 2 96 Tribute St",
    "sg:city":"Willetton",
    "sg:classifiers":[
        {
            "category":"Shopping",
            "subcategory":"Computers & Home Electronics",
            "type":"Retail Goods"
        }
    ],
    "sg:phone":"+61 8 9457 5000",
    "sg:postcode":"6155",
    "sg:province":"WA",
    "sg:tags":[
        "hardware",
        "equipment"
    ],
    "wof:name":"Regis Computer Rentals & Sales",
    "wof:placetype":"venue"
},
  "geometry": {"coordinates":[115.893173,-32.030479],"type":"Point"}
}