{
  "type": "Feature",
  "properties": {
    "addr:full":"16 Uplands Rd Chirnside Park VIC 3116",
    "addr:housenumber":"16",
    "addr:postcode":"3116",
    "addr:street":"Uplands Rd",
    "iso:country":"AU",
    "sg:address":"16 Uplands Rd",
    "sg:city":"Chirnside Park",
    "sg:classifiers":[
        {
            "category":"Building & Trades",
            "subcategory":"Plumbing",
            "type":"Services"
        }
    ],
    "sg:phone":"+61 3 9726 9551",
    "sg:postcode":"3116",
    "sg:province":"VIC",
    "sg:tags":[
        "plumber",
        "gasfitters"
    ],
    "wof:name":"M & K Capuano Plumbing",
    "wof:placetype":"venue"
},
  "geometry": {"coordinates":[145.295684814,-37.7443847656],"type":"Point"}
}