{
  "type": "Feature",
  "properties": {
    "iso:country":"AU",
    "sg:address":"Un 2, 249 South Rd",
    "sg:city":"Mile End",
    "sg:classifiers":[
        {
            "category":"Professional",
            "subcategory":"Accounting & Tax Preparation",
            "type":"Services"
        }
    ],
    "sg:phone":"+61 8 8352 7004",
    "sg:postcode":"5031",
    "sg:province":"SA",
    "sg:tags":[
        "accountant",
        "auditor"
    ],
    "wof:name":"Susan Walker Accounting & Bookkeeping",
    "wof:placetype":"venue"
},
  "geometry": {"coordinates":[138.570404053,-34.9297561646],"type":"Point"}
}