{
  "type": "Feature",
  "properties": {
    "iso:country":"AU",
    "sg:address":"Cnr Holleywell Rd & Burrows St",
    "sg:city":"Biggera Waters",
    "sg:classifiers":[
        {
            "category":"Government",
            "subcategory":"Fire Station",
            "type":"Public Place"
        }
    ],
    "sg:phone":"+61 7 5563 7263",
    "sg:postcode":"4216",
    "sg:province":"QLD",
    "sg:tags":[
        "spring",
        "shock",
        "absorbers",
        "suspension"
    ],
    "wof:name":"Makka Tyres, Brakes and Suspension",
    "wof:placetype":"venue"
},
  "geometry": {"coordinates":[153.40025329599999,-27.9319286346],"type":"Point"}
}