{
  "type": "Feature",
  "properties": {
    "iso:country":"AU",
    "sg:address":"Level C, 120 Wood St",
    "sg:city":"Mackay",
    "sg:classifiers":[
        {
            "category":"Transit Center",
            "subcategory":"Freight",
            "type":"Transportation"
        }
    ],
    "sg:phone":"+61 7 4957 5246",
    "sg:postcode":"4740",
    "sg:province":"QLD",
    "sg:tags":[
        "agent",
        "shipping"
    ],
    "wof:name":"Hetherington Kingsbury Shipping Agency",
    "wof:placetype":"venue"
},
  "geometry": {"coordinates":[149.18525700000001,-21.14443],"type":"Point"}
}