{
  "type": "Feature",
  "properties": {
    "addr:full":"135 Tenth St Mildura VIC 3500",
    "addr:housenumber":"135",
    "addr:postcode":"3500",
    "addr:street":"Tenth St",
    "iso:country":"AU",
    "sg:address":"135 Tenth St",
    "sg:city":"Mildura",
    "sg:classifiers":[
        {
            "category":"Home & Garden",
            "subcategory":"Furniture",
            "type":"Retail Goods"
        }
    ],
    "sg:phone":"+61 3 5022 1777",
    "sg:postcode":"3500",
    "sg:province":"VIC",
    "sg:tags":[
        "business"
    ],
    "wof:name":"C & G Office National",
    "wof:placetype":"venue"
},
  "geometry": {"coordinates":[142.15773010300001,-34.1870422363],"type":"Point"}
}