{
  "type": "Feature",
  "properties": {
    "addr:full":"Level 10, 140 William St Melbourne VIC 3004",
    "addr:housenumber":"140",
    "addr:postcode":"3004",
    "addr:street":"William St",
    "iso:country":"AU",
    "sg:address":"Level 10, 140 William St",
    "sg:city":"Melbourne",
    "sg:classifiers":[
        {
            "category":"Professional",
            "subcategory":"Employment Agencies",
            "type":"Services"
        }
    ],
    "sg:phone":"+61 3 9235 5171",
    "sg:postcode":"3004",
    "sg:province":"VIC",
    "wof:name":"The Interchange Bench",
    "wof:placetype":"venue"
},
  "geometry": {"coordinates":[144.95840454099999,-37.8157501221],"type":"Point"}
}