{
  "type": "Feature",
  "properties": {
    "addr:full":"PO Box 2190 Tingalpa QLD 4173",
    "addr:postcode":"4173",
    "iso:country":"AU",
    "sg:address":"PO Box 2190",
    "sg:city":"Tingalpa",
    "sg:classifiers":[
        {
            "category":"Home & Garden",
            "subcategory":"Building Materials",
            "type":"Retail Goods"
        }
    ],
    "sg:phone":"+61 7 3890 0633",
    "sg:postcode":"4173",
    "sg:province":"QLD",
    "sg:tags":[
        "fitting",
        "door"
    ],
    "wof:name":"Queensland Shopfronts and Doors",
    "wof:placetype":"venue"
},
  "geometry": {"coordinates":[153.12922668499999,-27.4736309052],"type":"Point"}
}