{
  "type": "Feature",
  "properties": {
    "iso:country":"AU",
    "sg:address":"76 Malop St",
    "sg:city":"Geelong",
    "sg:classifiers":[
        {
            "category":"Fast Food",
            "type":"Food & Drink"
        }
    ],
    "sg:phone":"+61 3 5223 3288",
    "sg:postcode":"3220",
    "sg:province":"VIC",
    "sg:tags":[
        "away",
        "take"
    ],
    "wof:name":"Hi Sushi",
    "wof:placetype":"venue"
},
  "geometry": {"coordinates":[144.362427,-38.14777],"type":"Point"}
}