{
  "type": "Feature",
  "properties": {
    "addr:full":"Unit 4/ 17- 37 Wollongong Rd Arncliffe NSW 2205",
    "addr:housenumber":"37",
    "addr:postcode":"2205",
    "addr:street":"Wollongong Rd",
    "iso:country":"AU",
    "sg:address":"Unit 4/ 17- 37 Wollongong Rd",
    "sg:city":"Arncliffe",
    "sg:classifiers":[
        {
            "category":"Government",
            "subcategory":"Fire Station",
            "type":"Public Place"
        }
    ],
    "sg:phone":"+61 2 9567 4435",
    "sg:postcode":"2205",
    "sg:province":"NSW",
    "sg:tags":[
        "equipment",
        "protection",
        "consultant"
    ],
    "wof:name":"Complete Fire Door Specialists",
    "wof:placetype":"venue"
},
  "geometry": {"coordinates":[151.14747600000001,-33.934113],"type":"Point"}
}