{
  "type": "Feature",
  "properties": {
    "iso:country":"AU",
    "sg:address":"48 Portland Rd",
    "sg:city":"Heywood",
    "sg:classifiers":[
        {
            "category":"Retail",
            "subcategory":"Auto Repair",
            "type":"Services"
        }
    ],
    "sg:phone":"+61 3 5527 1996",
    "sg:postcode":"3304",
    "sg:province":"VIC",
    "sg:tags":[
        "repairer",
        "motor",
        "engineer"
    ],
    "wof:name":"Aces Repairs",
    "wof:placetype":"venue"
},
  "geometry": {"coordinates":[141.90667724599999,-38.1882171631],"type":"Point"}
}