{
  "type": "Feature",
  "properties": {
    "iso:country":"AU",
    "sg:address":"5 Key Crt",
    "sg:city":"Noosa Heads",
    "sg:classifiers":[
        {
            "category":"Organizations",
            "subcategory":"Professional Association",
            "type":"Services"
        }
    ],
    "sg:phone":"+61 411 356 635",
    "sg:postcode":"4567",
    "sg:province":"QLD",
    "sg:tags":[
        "web",
        "internet"
    ],
    "wof:name":"Xybaweb Web Designs",
    "wof:placetype":"venue"
},
  "geometry": {"coordinates":[153.08283996599999,-26.3904151917],"type":"Point"}
}