{
  "type": "Feature",
  "properties": {
    "addr:full":"21- 25 Junction St Guildford NSW 2161",
    "addr:housenumber":"25",
    "addr:postcode":"2161",
    "addr:street":"Junction St",
    "iso:country":"AU",
    "sg:address":"21- 25 Junction St",
    "sg:city":"Guildford",
    "sg:classifiers":[
        {
            "category":"Retail",
            "subcategory":"Auto Repair",
            "type":"Services"
        }
    ],
    "sg:phone":"+61 2 9681 3392",
    "sg:postcode":"2161",
    "sg:province":"NSW",
    "sg:tags":[
        "beater",
        "painter",
        "panel"
    ],
    "wof:name":"G & N Smash Repairs",
    "wof:placetype":"venue"
},
  "geometry": {"coordinates":[150.9790802,-33.8639373779],"type":"Point"}
}