{
  "type": "Feature",
  "properties": {
    "addr:full":"Conrad Pl Albury North NSW 2640",
    "addr:postcode":"2640",
    "addr:street":"Conrad Pl",
    "iso:country":"AU",
    "sg:address":"Conrad Pl",
    "sg:city":"Albury North",
    "sg:classifiers":[
        {
            "category":"Wholesale",
            "subcategory":"Apparel",
            "type":"Manufacturing & Wholesale Goods"
        }
    ],
    "sg:phone":"+61 2 6040 1000",
    "sg:postcode":"2640",
    "sg:province":"NSW",
    "sg:tags":[
        "wholesaler",
        "mfrs",
        "uniform"
    ],
    "wof:name":"Superior Fit Australia Pty Ltd",
    "wof:placetype":"venue"
},
  "geometry": {"coordinates":[146.96333313,-36.044303894],"type":"Point"}
}