{
  "type": "Feature",
  "properties": {
    "addr:full":"78 Holbrook St Invermay TAS 7248",
    "addr:housenumber":"78",
    "addr:postcode":"7248",
    "addr:street":"Holbrook St",
    "iso:country":"AU",
    "sg:address":"78 Holbrook St",
    "sg:city":"Invermay",
    "sg:classifiers":[
        {
            "category":"Utilities",
            "subcategory":"Water",
            "type":"Services"
        }
    ],
    "sg:phone":"+61 418 528 246",
    "sg:postcode":"7248",
    "sg:province":"TAS",
    "sg:tags":[
        "hot",
        "system"
    ],
    "wof:name":"Mark O'Byrne Plumbing",
    "wof:placetype":"venue"
},
  "geometry": {"coordinates":[147.13345336899999,-41.423160553],"type":"Point"}
}