{
  "type": "Feature",
  "properties": {
    "addr:full":"450 Montague Rd Modbury North SA 5092",
    "addr:housenumber":"450",
    "addr:postcode":"5092",
    "addr:street":"Montague Rd",
    "iso:country":"AU",
    "sg:address":"450 Montague Rd",
    "sg:city":"Modbury North",
    "sg:classifiers":[
        {
            "category":"Travel",
            "subcategory":"Hotels & Motels",
            "type":"Entertainment"
        }
    ],
    "sg:phone":"+61 8 8264 5266",
    "sg:postcode":"5092",
    "sg:province":"SA",
    "wof:name":"Clovercrest Hotel Motel",
    "wof:placetype":"venue"
},
  "geometry": {"coordinates":[138.67445373499999,-34.8286705017],"type":"Point"}
}