{
  "type": "Feature",
  "properties": {
    "addr:full":"35 Furnace Rd Welshpool WA 6106",
    "addr:housenumber":"35",
    "addr:postcode":"6106",
    "addr:street":"Furnace Rd",
    "iso:country":"AU",
    "sg:address":"35 Furnace Rd",
    "sg:city":"Welshpool",
    "sg:classifiers":[
        {
            "category":"Building & Trades",
            "subcategory":"Construction",
            "type":"Services"
        }
    ],
    "sg:phone":"+61 8 9358 5811",
    "sg:postcode":"6106",
    "sg:province":"WA",
    "sg:tags":[
        "scaffolding"
    ],
    "wof:name":"Celtic Scaffolding Pty Ltd",
    "wof:placetype":"venue"
},
  "geometry": {"coordinates":[115.948776245,-31.9954929352],"type":"Point"}
}