{
  "type": "Feature",
  "properties": {
    "iso:country":"AU",
    "sg:address":"212 Queen St",
    "sg:city":"Ayr",
    "sg:classifiers":[
        {
            "category":"Fast Food",
            "type":"Food & Drink"
        }
    ],
    "sg:phone":"+61 7 4783 3540",
    "sg:postcode":"4807",
    "sg:province":"QLD",
    "sg:tags":[
        "away",
        "take"
    ],
    "wof:name":"KFC",
    "wof:placetype":"venue"
},
  "geometry": {"coordinates":[147.40306091299999,-19.578666687],"type":"Point"}
}