{
  "type": "Feature",
  "properties": {
    "addr:full":"6th Floor 87 Wickham Tce Brisbane QLD 4000",
    "addr:housenumber":"87",
    "addr:postcode":"4000",
    "addr:street":"Wickham Tce",
    "iso:country":"AU",
    "sg:address":"6th Floor 87",
    "sg:city":"Wickham Tce Brisbane",
    "sg:classifiers":[
        {
            "category":"Wholesale",
            "subcategory":"Medical Equipment & Supplies",
            "type":"Manufacturing & Wholesale Goods"
        }
    ],
    "sg:phone":"+61 7 3832 4541",
    "sg:postcode":"4000",
    "sg:province":"QLD",
    "sg:tags":[
        "aids",
        "hearing"
    ],
    "sg:website":"http://www.hearingsolutions.com.au",
    "wof:name":"Hearing Solutions",
    "wof:placetype":"venue"
},
  "geometry": {"coordinates":[153.02684020999999,-27.4644565582],"type":"Point"}
}