{
  "type": "Feature",
  "properties": {
    "iso:country":"AU",
    "sg:address":"67 Ellena St",
    "sg:city":"Maryborough",
    "sg:classifiers":[
        {
            "category":"Banks & Credit Unions",
            "subcategory":"Investment Brokerage",
            "type":"Services"
        }
    ],
    "sg:phone":"+61 7 4122 1544",
    "sg:postcode":"4650",
    "sg:province":"QLD",
    "sg:tags":[
        "finance",
        "broker"
    ],
    "wof:name":"Boltons Finance",
    "wof:placetype":"venue"
},
  "geometry": {"coordinates":[152.701706,-25.539661],"type":"Point"}
}