{
  "type": "Feature",
  "properties": {
    "iso:country":"AU",
    "sg:address":"75 Queens Rd",
    "sg:city":"Hurstville",
    "sg:classifiers":[
        {
            "category":"Health Services",
            "subcategory":"Doctor",
            "type":"Services"
        }
    ],
    "sg:phone":"+61 2 9586 1875",
    "sg:postcode":"2220",
    "sg:province":"NSW",
    "sg:tags":[
        "medical",
        "practitioner"
    ],
    "wof:name":"Cardiac Health Institute",
    "wof:placetype":"venue"
},
  "geometry": {"coordinates":[151.10430908199999,-33.9627990723],"type":"Point"}
}