{
  "type": "Feature",
  "properties": {
    "addr:full":"15 Fitzmaurice St Kaleen ACT 2617",
    "addr:housenumber":"15",
    "addr:postcode":"2617",
    "addr:street":"Fitzmaurice St",
    "iso:country":"AU",
    "sg:address":"15 Fitzmaurice St",
    "sg:city":"Kaleen",
    "sg:classifiers":[
        {
            "category":"Shopping",
            "subcategory":"Discount & Variety Stores",
            "type":"Retail Goods"
        }
    ],
    "sg:phone":"+61 2 6241 5193",
    "sg:postcode":"2617",
    "sg:province":"ACT",
    "sg:tags":[
        "information",
        "cooking",
        "class"
    ],
    "wof:name":"Nutrition And You",
    "wof:placetype":"venue"
},
  "geometry": {"coordinates":[149.106811523,-35.2312850952],"type":"Point"}
}