{
  "type": "Feature",
  "properties": {
    "addr:full":"Shp 13/14 Browns Plains Shopping Cntr Browns Plains QLD 4118",
    "addr:housenumber":"13 / 14",
    "addr:postcode":"4118",
    "iso:country":"AU",
    "sg:address":"Shp 13/14 Browns Plains Shopping Cntr",
    "sg:city":"Browns Plains",
    "sg:classifiers":[
        {
            "category":"Shopping",
            "subcategory":"Clothing, Apparel, & Fashions",
            "type":"Retail Goods"
        }
    ],
    "sg:phone":"+61 7 3800 7883",
    "sg:postcode":"4118",
    "sg:province":"QLD",
    "sg:tags":[
        "jean"
    ],
    "wof:name":"Just Jeans",
    "wof:placetype":"venue"
},
  "geometry": {"coordinates":[153.039794922,-27.6604213715],"type":"Point"}
}