{
  "type": "Feature",
  "properties": {
    "addr:full":"Gardens Rd The Gardens NT 0820",
    "addr:postcode":"nt 0820",
    "addr:street":"Gardens Rd",
    "iso:country":"AU",
    "sg:address":"Gardens Rd",
    "sg:city":"The Gardens",
    "sg:classifiers":[
        {
            "category":"Recreation",
            "subcategory":"Amusement Park",
            "type":"Entertainment"
        }
    ],
    "sg:phone":"+61 8 8981 6365",
    "sg:postcode":"0820",
    "sg:province":"NT",
    "wof:name":"Gardens Park Mini Golf",
    "wof:placetype":"venue"
},
  "geometry": {"coordinates":[130.83473205600001,-12.4481048584],"type":"Point"}
}