{
  "type": "Feature",
  "properties": {
    "iso:country":"AU",
    "sg:address":"27 William Ave",
    "sg:city":"Hallam",
    "sg:classifiers":[
        {
            "category":"Building & Trades",
            "subcategory":"Cleaning & Sanitation",
            "type":"Services"
        }
    ],
    "sg:phone":"+61 401 625 395",
    "sg:postcode":"3803",
    "sg:province":"VIC",
    "sg:tags":[
        "cleaner",
        "repairer",
        "roof"
    ],
    "wof:name":"Bryan Ross Roofing",
    "wof:placetype":"venue"
},
  "geometry": {"coordinates":[145.25750732399999,-38.0002098083],"type":"Point"}
}