{
  "type": "Feature",
  "properties": {
    "addr:full":"25 Kensington St Waterloo NSW 2017",
    "addr:housenumber":"25",
    "addr:postcode":"2017",
    "addr:street":"Kensington St",
    "iso:country":"AU",
    "sg:address":"25 Kensington St",
    "sg:city":"Waterloo",
    "sg:classifiers":[
        {
            "category":"Home & Garden",
            "subcategory":"Building Materials",
            "type":"Retail Goods"
        }
    ],
    "sg:phone":"+61 2 9318 1826",
    "sg:postcode":"2017",
    "sg:province":"NSW",
    "sg:tags":[
        "balustrading"
    ],
    "wof:name":"A Proline Engineering",
    "wof:placetype":"venue"
},
  "geometry": {"coordinates":[151.206832886,-33.9000434875],"type":"Point"}
}