{
  "type": "Feature",
  "properties": {
    "addr:full":"42 Peridot St Bayview Heights QLD 4868",
    "addr:housenumber":"42",
    "addr:postcode":"4868",
    "addr:street":"Peridot St",
    "iso:country":"AU",
    "sg:address":"42 Peridot St",
    "sg:city":"Bayview Heights",
    "sg:classifiers":[
        {
            "category":"Building & Trades",
            "subcategory":"Construction",
            "type":"Services"
        }
    ],
    "sg:phone":"+61 408 770 878",
    "sg:postcode":"4868",
    "sg:province":"QLD",
    "sg:tags":[
        "contractor"
    ],
    "wof:name":"RI & AM Skaines Pty Ltd",
    "wof:placetype":"venue"
},
  "geometry": {"coordinates":[145.732177734,-16.9620914459],"type":"Point"}
}