{
  "type": "Feature",
  "properties": {
    "iso:country":"AU",
    "sg:address":"McDougall Building Ellerslie Rd",
    "sg:city":"Battery Point",
    "sg:classifiers":[
        {
            "category":"Professional",
            "subcategory":"Accounting & Tax Preparation",
            "type":"Services"
        }
    ],
    "sg:phone":"+61 3 6224 2632",
    "sg:postcode":"7004",
    "sg:province":"TAS",
    "sg:tags":[
        "pregnancy",
        "related",
        "counselling"
    ],
    "wof:name":"Human Life Protection Society Inc",
    "wof:placetype":"venue"
},
  "geometry": {"coordinates":[147.328659058,-42.8887672424],"type":"Point"}
}