{
  "type": "Feature",
  "properties": {
    "iso:country":"AU",
    "sg:address":"356 The Entrance Rd",
    "sg:city":"Long Jetty",
    "sg:classifiers":[
        {
            "category":"Personal",
            "subcategory":"Barber",
            "type":"Services"
        }
    ],
    "sg:phone":"+61 2 4332 0620",
    "sg:postcode":"2261",
    "sg:province":"NSW",
    "wof:name":"Maxwell S R",
    "wof:placetype":"venue"
},
  "geometry": {"coordinates":[151.482666,-33.360825],"type":"Point"}
}