{
  "type": "Feature",
  "properties": {
    "addr:full":"27 Jubilee St East Maitland NSW 2323",
    "addr:housenumber":"27",
    "addr:postcode":"2323",
    "addr:street":"Jubilee St",
    "iso:country":"AU",
    "sg:address":"27 Jubilee St",
    "sg:city":"East Maitland",
    "sg:classifiers":[
        {
            "category":"Social Services",
            "type":"Services"
        }
    ],
    "sg:phone":"+61 2 4934 4360",
    "sg:postcode":"2323",
    "sg:province":"NSW",
    "sg:tags":[
        "domestic",
        "help"
    ],
    "wof:name":"Shopmate",
    "wof:placetype":"venue"
},
  "geometry": {"coordinates":[151.593582153,-32.7557182312],"type":"Point"}
}