{
  "type": "Feature",
  "properties": {
    "iso:country":"AU",
    "sg:address":"16 Gulwa Ave",
    "sg:city":"Frankston",
    "sg:classifiers":[
        {
            "category":"Professional",
            "subcategory":"Computer Services",
            "type":"Services"
        }
    ],
    "sg:phone":"+61 3 9766 1697",
    "sg:postcode":"3199",
    "sg:province":"VIC",
    "sg:tags":[
        "training"
    ],
    "wof:name":"Achieve-it Computer Services",
    "wof:placetype":"venue"
},
  "geometry": {"coordinates":[145.1484375,-38.1584014893],"type":"Point"}
}