{
  "type": "Feature",
  "properties": {
    "addr:full":"29 Davis St Wetherill Park NSW 2164",
    "addr:housenumber":"29",
    "addr:postcode":"2164",
    "addr:street":"Davis St",
    "iso:country":"AU",
    "sg:address":"29 Davis St",
    "sg:city":"Wetherill Park",
    "sg:classifiers":[
        {
            "category":"Wholesale",
            "subcategory":"Apparel",
            "type":"Manufacturing & Wholesale Goods"
        }
    ],
    "sg:phone":"+61 1300 769 181",
    "sg:postcode":"2164",
    "sg:province":"NSW",
    "sg:tags":[
        "wholesaler",
        "men's",
        "mfrs",
        "sportswear"
    ],
    "wof:name":"DNC Leisurewear",
    "wof:placetype":"venue"
},
  "geometry": {"coordinates":[150.904953003,-33.8363952637],"type":"Point"}
}