{
  "type": "Feature",
  "properties": {
    "iso:country":"AU",
    "sg:address":"4140 Spencely Rd",
    "sg:city":"Humpty Doo",
    "sg:phone":"+61 8 8988 5633",
    "sg:postcode":"0836",
    "sg:province":"NT",
    "wof:name":"Practical Plastics",
    "wof:placetype":"venue"
},
  "geometry": {"coordinates":[131.095169,-12.577189],"type":"Point"}
}