{
  "type": "Feature",
  "properties": {
    "addr:full":"Cnr Kenwick Link & Boydell Rd Kenwick WA 6107",
    "addr:postcode":"6107",
    "addr:street":"Cnr;Rd",
    "iso:country":"AU",
    "sg:address":"Cnr Kenwick Link & Boydell Rd",
    "sg:city":"Kenwick",
    "sg:classifiers":[
        {
            "category":"Real Estate",
            "subcategory":"Real Estate Agent",
            "type":"Services"
        }
    ],
    "sg:phone":"+61 8 9459 5000",
    "sg:postcode":"6107",
    "sg:province":"WA",
    "sg:tags":[
        "handyman's",
        "equipment",
        "hire",
        "builders",
        "contractor"
    ],
    "wof:name":"Classic Hire",
    "wof:placetype":"venue"
},
  "geometry": {"coordinates":[115.97118377699999,-32.0432777405],"type":"Point"}
}