{
  "type": "Feature",
  "properties": {
    "addr:full":"30 Hawken Drv St Lucia QLD 4067",
    "addr:housenumber":"30",
    "addr:postcode":"4067",
    "addr:street":"Hawken Drv",
    "iso:country":"AU",
    "sg:address":"30 Hawken Drv",
    "sg:city":"St Lucia",
    "sg:classifiers":[
        {
            "category":"Personal",
            "subcategory":"Beauty Salon",
            "type":"Services"
        }
    ],
    "sg:phone":"+61 7 3870 9661",
    "sg:postcode":"4067",
    "sg:province":"QLD",
    "sg:tags":[
        "hairdresser"
    ],
    "wof:name":"Jackie Trout Hair Design",
    "wof:placetype":"venue"
},
  "geometry": {"coordinates":[152.99661254899999,-27.5016269684],"type":"Point"}
}