{
  "type": "Feature",
  "properties": {
    "addr:full":"12 Booran Drv Underwood QLD 4119",
    "addr:housenumber":"12",
    "addr:postcode":"4119",
    "addr:street":"Booran Drv",
    "iso:country":"AU",
    "sg:address":"12 Booran Drv",
    "sg:city":"Underwood",
    "sg:classifiers":[
        {
            "category":"Shopping",
            "subcategory":"Party Supplies",
            "type":"Retail Goods"
        }
    ],
    "sg:phone":"+61 7 3299 4844",
    "sg:postcode":"4119",
    "sg:province":"QLD",
    "wof:name":"Eds Party Hire",
    "wof:placetype":"venue"
},
  "geometry": {"coordinates":[153.11456298799999,-27.6231155396],"type":"Point"}
}