{
  "type": "Feature",
  "properties": {
    "addr:full":"42 William St Raymond Terrace NSW 2324",
    "addr:housenumber":"42",
    "addr:postcode":"2324",
    "addr:street":"William St",
    "iso:country":"AU",
    "sg:address":"42 William St",
    "sg:city":"Raymond Terrace",
    "sg:classifiers":[
        {
            "category":"Health Services",
            "subcategory":"Dentist",
            "type":"Services"
        }
    ],
    "sg:phone":"+61 2 4987 3368",
    "sg:postcode":"2324",
    "sg:province":"NSW",
    "wof:name":"Raymond Terrace Dental Care",
    "wof:placetype":"venue"
},
  "geometry": {"coordinates":[151.74411010700001,-32.7630958557],"type":"Point"}
}