{
  "type": "Feature",
  "properties": {
    "addr:full":"Shop 2072, Knox City Shopping Centre, Corner Stud road & Burwood Hwy Wantirna VIC 3152",
    "addr:housenumber":"2072",
    "addr:postcode":"3152",
    "addr:street":"Knox;Stud Road & Burwood Hwy",
    "iso:country":"AU",
    "sg:address":"Shop 2072, Knox City Shopping Centre, Corner Stud road & Burwood Hwy",
    "sg:city":"Wantirna",
    "sg:classifiers":[
        {
            "category":"Shopping",
            "subcategory":"Clothing, Apparel, & Fashions",
            "type":"Retail Goods"
        }
    ],
    "sg:phone":"+61 3 9887 2905",
    "sg:postcode":"3152",
    "sg:province":"VIC",
    "sg:tags":[
        "lady",
        "wear"
    ],
    "wof:name":"Brown Sugar",
    "wof:placetype":"venue"
},
  "geometry": {"coordinates":[145.23495483400001,-37.8695487976],"type":"Point"}
}