{
  "type": "Feature",
  "properties": {
    "iso:country":"AU",
    "sg:address":"370 Dorset Rd",
    "sg:city":"Croydon",
    "sg:classifiers":[
        {
            "category":"Building & Trades",
            "subcategory":"Cleaning & Sanitation",
            "type":"Services"
        }
    ],
    "sg:phone":"+61 3 9725 3125",
    "sg:postcode":"3136",
    "sg:province":"VIC",
    "sg:tags":[
        "sweep",
        "chimney"
    ],
    "wof:name":"A AAAnticyclone Chimney Sweep & Fireplaces",
    "wof:placetype":"venue"
},
  "geometry": {"coordinates":[145.28863525400001,-37.8048629761],"type":"Point"}
}