{
  "type": "Feature",
  "properties": {
    "addr:full":"PO Box 537 St Peters SA 5069",
    "addr:postcode":"5069",
    "iso:country":"AU",
    "sg:address":"PO Box 537",
    "sg:city":"St Peters",
    "sg:classifiers":[
        {
            "category":"Building & Trades",
            "subcategory":"Equipment Rental",
            "type":"Services"
        }
    ],
    "sg:phone":"+61 408 282 101",
    "sg:postcode":"5069",
    "sg:province":"SA",
    "sg:tags":[
        "demolition",
        "contractor"
    ],
    "wof:name":"DPC Demolition",
    "wof:placetype":"venue"
},
  "geometry": {"coordinates":[138.623504639,-34.9047203064],"type":"Point"}
}