{
  "type": "Feature",
  "properties": {
    "addr:full":"Penprase La Miranda NSW 2228",
    "addr:postcode":"2228",
    "iso:country":"AU",
    "sg:address":"Penprase La",
    "sg:city":"Miranda",
    "sg:classifiers":[
        {
            "category":"Retail",
            "subcategory":"Auto Repair",
            "type":"Services"
        }
    ],
    "sg:phone":"+61 2 9524 3813",
    "sg:postcode":"2228",
    "sg:province":"NSW",
    "sg:tags":[
        "repairer",
        "motor",
        "engineer"
    ],
    "wof:name":"King R W",
    "wof:placetype":"venue"
},
  "geometry": {"coordinates":[151.10154724099999,-34.0333900452],"type":"Point"}
}