{
  "type": "Feature",
  "properties": {
    "addr:full":"7a Jordan St Cobram VIC 3644",
    "addr:housenumber":"7a",
    "addr:postcode":"3644",
    "addr:street":"Jordan St",
    "iso:country":"AU",
    "sg:address":"7a Jordan St",
    "sg:city":"Cobram",
    "sg:classifiers":[
        {
            "category":"Retail",
            "subcategory":"Repair Shop",
            "type":"Services"
        }
    ],
    "sg:phone":"+61 3 5872 2959",
    "sg:postcode":"3644",
    "sg:province":"VIC",
    "sg:tags":[
        "upholsterer"
    ],
    "wof:name":"G.V. Upholstery",
    "wof:placetype":"venue"
},
  "geometry": {"coordinates":[145.64486694300001,-35.9190483093],"type":"Point"}
}