{
  "type": "Feature",
  "properties": {
    "iso:country":"AU",
    "sg:address":"Shop 12 & 13, 118 Princes Hwy",
    "sg:city":"Ulladulla",
    "sg:classifiers":[
        {
            "category":"Fast Food",
            "type":"Food & Drink"
        }
    ],
    "sg:phone":"+61 2 4455 5335",
    "sg:postcode":"2539",
    "sg:province":"NSW",
    "sg:tags":[
        "away",
        "take"
    ],
    "wof:name":"Nanny Clarks Coffee Lounge",
    "wof:placetype":"venue"
},
  "geometry": {"coordinates":[150.473846436,-35.3601608276],"type":"Point"}
}