{
  "type": "Feature",
  "properties": {
    "addr:full":"33 Steel St North Melbourne VIC 3051",
    "addr:housenumber":"33",
    "addr:postcode":"3051",
    "addr:street":"Steel St",
    "iso:country":"AU",
    "sg:address":"33 Steel St",
    "sg:city":"North Melbourne",
    "sg:classifiers":[
        {
            "category":"Home & Garden",
            "subcategory":"Hardware",
            "type":"Retail Goods"
        }
    ],
    "sg:phone":"+61 3 9328 4445",
    "sg:postcode":"3051",
    "sg:province":"VIC",
    "sg:tags":[
        "generating",
        "set",
        "generator"
    ],
    "wof:name":"East Coast Generator Services",
    "wof:placetype":"venue"
},
  "geometry": {"coordinates":[144.93765258799999,-37.7961425781],"type":"Point"}
}