{
  "type": "Feature",
  "properties": {
    "addr:full":"3 Underwood Rd Homebush NSW 2140",
    "addr:housenumber":"3",
    "addr:postcode":"2140",
    "addr:street":"Underwood Rd",
    "iso:country":"AU",
    "sg:address":"3 Underwood Rd",
    "sg:city":"Homebush",
    "sg:classifiers":[
        {
            "category":"Shopping",
            "subcategory":"Clothing, Apparel, & Fashions",
            "type":"Retail Goods"
        }
    ],
    "sg:phone":"+61 2 9746 0277",
    "sg:postcode":"2140",
    "sg:province":"NSW",
    "sg:tags":[
        "menswear"
    ],
    "wof:name":"Essential Man",
    "wof:placetype":"venue"
},
  "geometry": {"coordinates":[151.07818603499999,-33.8549499512],"type":"Point"}
}