{
  "type": "Feature",
  "properties": {
    "iso:country":"AU",
    "sg:address":"9 Julian Crt",
    "sg:city":"Bundoora",
    "sg:classifiers":[
        {
            "category":"Food & Beverages",
            "subcategory":"Bakery",
            "type":"Retail Goods"
        }
    ],
    "sg:phone":"+61 3 9466 8420",
    "sg:postcode":"3083",
    "sg:province":"VIC",
    "sg:tags":[
        "cake",
        "shop",
        "pastry"
    ],
    "wof:name":"Topspot Wholesale",
    "wof:placetype":"venue"
},
  "geometry": {"coordinates":[145.06813049300001,-37.7067184448],"type":"Point"}
}