{
  "type": "Feature",
  "properties": {
    "addr:full":"Level 1/ 243 Bay St Brighton VIC 3186",
    "addr:housenumber":"/ 243",
    "addr:postcode":"3186",
    "addr:street":"Bay St",
    "iso:country":"AU",
    "sg:address":"Level 1/ 243 Bay St",
    "sg:city":"Brighton",
    "sg:classifiers":[
        {
            "category":"Education",
            "subcategory":"Dance Studio",
            "type":"Public Place"
        }
    ],
    "sg:phone":"+61 3 9596 9588",
    "sg:postcode":"3186",
    "sg:province":"VIC",
    "sg:tags":[
        "venue",
        "tuition"
    ],
    "wof:name":"Belly Dance Kizmet",
    "wof:placetype":"venue"
},
  "geometry": {"coordinates":[145.00003051799999,-37.9050216675],"type":"Point"}
}