{
  "type": "Feature",
  "properties": {
    "iso:country":"AU",
    "sg:address":"388 Grand Junction Rd",
    "sg:city":"Mansfield Park",
    "sg:classifiers":[
        {
            "category":"Retail",
            "subcategory":"Auto Repair",
            "type":"Services"
        }
    ],
    "sg:phone":"+61 8 8244 0244",
    "sg:postcode":"5012",
    "sg:province":"SA",
    "sg:tags":[
        "electrical"
    ],
    "wof:name":"Ace Mobile Auto Electrical",
    "wof:placetype":"venue"
},
  "geometry": {"coordinates":[138.54835510300001,-34.850692749],"type":"Point"}
}