{
  "type": "Feature",
  "properties": {
    "iso:country":"AU",
    "sg:address":"164a Queen St",
    "sg:city":"Ayr",
    "sg:classifiers":[
        {
            "category":"Restaurant",
            "type":"Food & Drink"
        }
    ],
    "sg:phone":"+61 7 4783 2559",
    "sg:postcode":"4807",
    "sg:province":"QLD",
    "wof:name":"Ayr Chinese Restaurant",
    "wof:placetype":"venue"
},
  "geometry": {"coordinates":[147.404907227,-19.5766143799],"type":"Point"}
}