{
  "type": "Feature",
  "properties": {
    "addr:full":"35 Plunkett Rd Dandenong VIC 3175",
    "addr:housenumber":"35",
    "addr:postcode":"3175",
    "addr:street":"Plunkett Rd",
    "iso:country":"AU",
    "sg:address":"35 Plunkett Rd",
    "sg:city":"Dandenong",
    "sg:classifiers":[
        {
            "category":"Autos & Motor Vehicles",
            "subcategory":"Auto Supplies",
            "type":"Retail Goods"
        }
    ],
    "sg:phone":"+61 3 9794 7794",
    "sg:postcode":"3175",
    "sg:province":"VIC",
    "sg:tags":[
        "part",
        "cycles",
        "accessory"
    ],
    "wof:name":"C N C Cycleworks",
    "wof:placetype":"venue"
},
  "geometry": {"coordinates":[145.224853516,-37.9966163635],"type":"Point"}
}