{
  "type": "Feature",
  "properties": {
    "addr:full":"22 Hilly St Mortlake NSW 2137",
    "addr:housenumber":"22",
    "addr:postcode":"2137",
    "addr:street":"Hilly St",
    "iso:country":"AU",
    "sg:address":"22 Hilly St",
    "sg:city":"Mortlake",
    "sg:classifiers":[
        {
            "category":"Utilities",
            "subcategory":"Sewage",
            "type":"Services"
        }
    ],
    "sg:phone":"+61 2 9743 1333",
    "sg:postcode":"2137",
    "sg:province":"NSW",
    "sg:tags":[
        "equipment",
        "sewer",
        "cleaning"
    ],
    "wof:name":"Pumping Equipment",
    "wof:placetype":"venue"
},
  "geometry": {"coordinates":[151.10557556099999,-33.838722229],"type":"Point"}
}