{
  "type": "Feature",
  "properties": {
    "addr:full":"Suite 33 Cabrini Medical Centre Malvern VIC 3144",
    "addr:postcode":"3144",
    "iso:country":"AU",
    "sg:address":"Suite 33 Cabrini Medical Centre",
    "sg:city":"Malvern",
    "sg:classifiers":[
        {
            "category":"Health Services",
            "subcategory":"Doctor",
            "type":"Services"
        }
    ],
    "sg:phone":"+61 3 9576 0021",
    "sg:postcode":"3144",
    "sg:province":"VIC",
    "sg:tags":[
        "medical",
        "practitioner"
    ],
    "wof:name":"Habersberger Peter G",
    "wof:placetype":"venue"
},
  "geometry": {"coordinates":[145.03250122099999,-37.8626785278],"type":"Point"}
}