{
  "type": "Feature",
  "properties": {
    "addr:full":"13/ 45 Tomlinson Rd Welshpool WA 6106",
    "addr:housenumber":"13 / 45",
    "addr:postcode":"6106",
    "addr:street":"Tomlinson Rd",
    "iso:country":"AU",
    "sg:address":"13/ 45 Tomlinson Rd",
    "sg:city":"Welshpool",
    "sg:classifiers":[
        {
            "category":"Building & Trades",
            "subcategory":"Construction",
            "type":"Services"
        }
    ],
    "sg:phone":"+61 8 9358 1225",
    "sg:postcode":"6106",
    "sg:province":"WA",
    "sg:tags":[
        "fencing",
        "contractor"
    ],
    "wof:name":"Superior Steel Screens",
    "wof:placetype":"venue"
},
  "geometry": {"coordinates":[115.928886414,-31.9904766083],"type":"Point"}
}