{
  "type": "Feature",
  "properties": {
    "addr:full":"127 Tanti Ave Mornington VIC 3931",
    "addr:housenumber":"127",
    "addr:postcode":"3931",
    "addr:street":"Tanti Ave",
    "iso:country":"AU",
    "sg:address":"127 Tanti Ave",
    "sg:city":"Mornington",
    "sg:classifiers":[
        {
            "category":"Health Services",
            "subcategory":"Doctor",
            "type":"Services"
        }
    ],
    "sg:phone":"+61 3 5975 1388",
    "sg:postcode":"3931",
    "sg:province":"VIC",
    "sg:tags":[
        "medical",
        "practitioner"
    ],
    "wof:name":"Newton Richard Dr",
    "wof:placetype":"venue"
},
  "geometry": {"coordinates":[145.04762268100001,-38.224357605],"type":"Point"}
}