{
  "type": "Feature",
  "properties": {
    "addr:full":"Unit 4 94 Boniface St Archerfield QLD 4108",
    "addr:housenumber":"94",
    "addr:postcode":"4108",
    "addr:street":"Boniface St",
    "iso:country":"AU",
    "sg:address":"Unit 4 94 Boniface St",
    "sg:city":"Archerfield",
    "sg:classifiers":[
        {
            "category":"Retail",
            "subcategory":"Storage",
            "type":"Services"
        }
    ],
    "sg:phone":"+61 7 3276 7771",
    "sg:postcode":"4108",
    "sg:province":"QLD",
    "sg:tags":[
        "removal",
        "furniture"
    ],
    "wof:name":"Calleja Moving & Storage (Qld) Pty Ltd",
    "wof:placetype":"venue"
},
  "geometry": {"coordinates":[153.02027893100001,-27.5625839233],"type":"Point"}
}