{
  "type": "Feature",
  "properties": {
    "addr:full":"Unit 15/ 4 Leda Drv West Burleigh QLD 4219",
    "addr:housenumber":"/ 4",
    "addr:postcode":"4219",
    "addr:street":"Leda Drv West",
    "iso:country":"AU",
    "sg:address":"Unit 15/ 4 Leda Drv",
    "sg:city":"West Burleigh",
    "sg:classifiers":[
        {
            "category":"Shopping",
            "subcategory":"Bridal",
            "type":"Retail Goods"
        }
    ],
    "sg:phone":"+61 7 5520 0566",
    "sg:postcode":"4219",
    "sg:province":"QLD",
    "sg:tags":[
        "hire",
        "wear"
    ],
    "wof:name":"Diane Freis",
    "wof:placetype":"venue"
},
  "geometry": {"coordinates":[153.430709839,-28.103603363],"type":"Point"}
}