{
  "type": "Feature",
  "properties": {
    "addr:full":"13 Main St Minlaton SA 5575",
    "addr:housenumber":"13",
    "addr:postcode":"5575",
    "addr:street":"Main St",
    "iso:country":"AU",
    "sg:address":"13 Main St",
    "sg:city":"Minlaton",
    "sg:classifiers":[
        {
            "category":"Banks & Credit Unions",
            "subcategory":"Bureau De Change",
            "type":"Services"
        }
    ],
    "sg:phone":"+61 8 8853 2078",
    "sg:postcode":"5575",
    "sg:province":"SA",
    "sg:tags":[
        "repairs",
        "part",
        "appliance",
        "electrical"
    ],
    "wof:name":"Kims Electronics",
    "wof:placetype":"venue"
},
  "geometry": {"coordinates":[137.59611511200001,-34.7705192566],"type":"Point"}
}