{
  "type": "Feature",
  "properties": {
    "iso:country":"AU",
    "sg:address":"103 Powell Rd",
    "sg:city":"Baldivis",
    "sg:classifiers":[
        {
            "category":"Building & Trades",
            "subcategory":"Construction",
            "type":"Services"
        }
    ],
    "sg:phone":"+61 410 518 583",
    "sg:postcode":"6171",
    "sg:province":"WA",
    "sg:tags":[
        "renovation",
        "alterations",
        "extension",
        "contractor"
    ],
    "wof:name":"Windsor Homes",
    "wof:placetype":"venue"
},
  "geometry": {"coordinates":[115.848503,-32.340141],"type":"Point"}
}