{
  "type": "Feature",
  "properties": {
    "iso:country":"AU",
    "sg:address":"255 Clayton Rd",
    "sg:city":"Clayton",
    "sg:classifiers":[
        {
            "category":"Health Services",
            "subcategory":"Health Practitioner",
            "type":"Services"
        }
    ],
    "sg:phone":"+61 3 9563 7559",
    "sg:postcode":"3168",
    "sg:province":"VIC",
    "sg:tags":[
        "psychologist"
    ],
    "wof:name":"Wellspring Psychological Services",
    "wof:placetype":"venue"
},
  "geometry": {"coordinates":[145.120635986,-37.9194908142],"type":"Point"}
}