{
  "type": "Feature",
  "properties": {
    "iso:country":"AU",
    "sg:address":"274 Mulloway Rd",
    "sg:city":"Chain Valley Bay",
    "sg:classifiers":[
        {
            "category":"Social Services",
            "subcategory":"Retirement Home",
            "type":"Services"
        }
    ],
    "sg:phone":"+61 2 4358 1833",
    "sg:postcode":"2259",
    "sg:province":"NSW",
    "sg:tags":[
        "village"
    ],
    "wof:name":"Valhalla Village Pty Ltd",
    "wof:placetype":"venue"
},
  "geometry": {"coordinates":[151.57409668,-33.1733131409],"type":"Point"}
}