{
  "type": "Feature",
  "properties": {
    "addr:full":"31 Railway Pde Mt Lawley WA 6050",
    "addr:housenumber":"31",
    "addr:postcode":"6050",
    "addr:street":"Railway Pde",
    "iso:country":"AU",
    "sg:address":"31 Railway Pde",
    "sg:city":"Mt Lawley",
    "sg:classifiers":[
        {
            "category":"Health Services",
            "subcategory":"Health Practitioner",
            "type":"Services"
        }
    ],
    "sg:phone":"+61 8 9370 3822",
    "sg:postcode":"6050",
    "sg:province":"WA",
    "sg:tags":[
        "naturopath"
    ],
    "wof:name":"Champion Health Centre",
    "wof:placetype":"venue"
},
  "geometry": {"coordinates":[115.878303528,-31.9373760223],"type":"Point"}
}