{
  "type": "Feature",
  "properties": {
    "addr:full":"Kirston St Laidley QLD 4341",
    "addr:postcode":"4341",
    "iso:country":"AU",
    "sg:address":"Kirston St",
    "sg:city":"Laidley",
    "sg:classifiers":[
        {
            "category":"Retail",
            "subcategory":"Auto Repair",
            "type":"Services"
        }
    ],
    "sg:phone":"+61 7 5465 1888",
    "sg:postcode":"4341",
    "sg:province":"QLD",
    "sg:tags":[
        "automotive",
        "air conditioning"
    ],
    "wof:name":"Laidley Smash Repairs",
    "wof:placetype":"venue"
},
  "geometry": {"coordinates":[152.39385986299999,-27.6247692108],"type":"Point"}
}