{
  "type": "Feature",
  "properties": {
    "addr:full":"PO Box 198 Millicent SA 5280",
    "addr:postcode":"5280",
    "iso:country":"AU",
    "sg:address":"PO Box 198",
    "sg:city":"Millicent",
    "sg:classifiers":[
        {
            "category":"Building & Trades",
            "subcategory":"Construction",
            "type":"Services"
        }
    ],
    "sg:phone":"+61 428 375 475",
    "sg:postcode":"5280",
    "sg:province":"SA",
    "sg:tags":[
        "earth",
        "excavating",
        "moving",
        "contractor"
    ],
    "wof:name":"Garry Davies Bulldozing",
    "wof:placetype":"venue"
},
  "geometry": {"coordinates":[140.330185,-37.594742],"type":"Point"}
}