{
  "type": "Feature",
  "properties": {
    "iso:country":"AU",
    "sg:address":"239 Church St",
    "sg:city":"Richmond",
    "sg:classifiers":[
        {
            "category":"Real Estate",
            "subcategory":"Real Estate Agent",
            "type":"Services"
        }
    ],
    "sg:phone":"+61 3 9428 0169",
    "sg:postcode":"3121",
    "sg:province":"VIC",
    "wof:name":"Deves Harris",
    "wof:placetype":"venue"
},
  "geometry": {"coordinates":[144.99929809599999,-37.8188209534],"type":"Point"}
}