{
  "type": "Feature",
  "properties": {
    "iso:country":"AU",
    "sg:address":"Shop 4, 60 Memorial Ave",
    "sg:city":"Liverpool",
    "sg:classifiers":[
        {
            "category":"Travel",
            "subcategory":"Travel Agent",
            "type":"Entertainment"
        }
    ],
    "sg:phone":"+61 2 9824 2427",
    "sg:postcode":"2170",
    "sg:province":"NSW",
    "sg:tags":[
        "consultant"
    ],
    "wof:name":"Mega Travel",
    "wof:placetype":"venue"
},
  "geometry": {"coordinates":[150.92201232900001,-33.9241371155],"type":"Point"}
}