{
  "type": "Feature",
  "properties": {
    "iso:country":"AU",
    "sg:address":"5- 7 Freight Rd",
    "sg:city":"Tullamarine",
    "sg:classifiers":[
        {
            "category":"Retail",
            "subcategory":"Auto Repair",
            "type":"Services"
        }
    ],
    "sg:phone":"+61 3 9330 3555",
    "sg:postcode":"3043",
    "sg:province":"VIC",
    "sg:tags":[
        "gas",
        "conversion",
        "natural",
        "lp",
        "vehicle"
    ],
    "wof:name":"Advanced Fuels Technology Pty Ltd",
    "wof:placetype":"venue"
},
  "geometry": {"coordinates":[144.88044738799999,-37.6932449341],"type":"Point"}
}