{
  "type": "Feature",
  "properties": {
    "addr:full":"2 Thompson Rd North Geelong VIC 3215",
    "addr:housenumber":"2",
    "addr:postcode":"3215",
    "addr:street":"Thompson Rd",
    "iso:country":"AU",
    "sg:address":"2 Thompson Rd",
    "sg:city":"North Geelong",
    "sg:classifiers":[
        {
            "category":"Retail",
            "subcategory":"Event Space",
            "type":"Services"
        }
    ],
    "sg:phone":"+61 3 5278 2911",
    "sg:postcode":"3215",
    "sg:province":"VIC",
    "sg:tags":[
        "venue",
        "reception",
        "wedding"
    ],
    "wof:name":"The Sphinx",
    "wof:placetype":"venue"
},
  "geometry": {"coordinates":[144.340606689,-38.1260032654],"type":"Point"}
}