{
  "type": "Feature",
  "properties": {
    "iso:country":"AU",
    "sg:address":"13 Parkers Rd",
    "sg:city":"Sutherland's Creek",
    "sg:classifiers":[
        {
            "category":"Building & Trades",
            "subcategory":"Construction",
            "type":"Services"
        }
    ],
    "sg:phone":"+61 402 073 668",
    "sg:postcode":"3331",
    "sg:province":"VIC",
    "sg:tags":[
        "roof"
    ],
    "wof:name":"Normie Rowe",
    "wof:placetype":"venue"
},
  "geometry": {"coordinates":[144.139633,-37.968452],"type":"Point"}
}