{
  "type": "Feature",
  "properties": {
    "addr:full":"Mollymook Shopping Centre Cnr James Ave & Tallwood Ave Mollymook NSW 2539",
    "addr:postcode":"2539",
    "addr:street":"Cnr James Ave & Tallwood Ave",
    "iso:country":"AU",
    "sg:address":"Mollymook Shopping Centre Cnr James Ave & Tallwood Ave",
    "sg:city":"Mollymook",
    "sg:classifiers":[
        {
            "category":"Wholesale",
            "subcategory":"Medical Equipment & Supplies",
            "type":"Manufacturing & Wholesale Goods"
        }
    ],
    "sg:phone":"+61 2 4455 3425",
    "sg:postcode":"2539",
    "sg:province":"NSW",
    "sg:tags":[
        "aid",
        "care",
        "health",
        "home"
    ],
    "wof:name":"Mollymook Pharmacy",
    "wof:placetype":"venue"
},
  "geometry": {"coordinates":[150.47669982900001,-35.3239631653],"type":"Point"}
}