{
  "type": "Feature",
  "properties": {
    "iso:country":"AU",
    "sg:address":"117 Mona Vale Rd",
    "sg:city":"Mona Vale",
    "sg:classifiers":[
        {
            "category":"Building & Trades",
            "subcategory":"Construction",
            "type":"Services"
        }
    ],
    "sg:phone":"+61 2 9999 6852",
    "sg:postcode":"2103",
    "sg:province":"NSW",
    "sg:tags":[
        "concrete",
        "contractor"
    ],
    "wof:name":"Rocco Crea",
    "wof:placetype":"venue"
},
  "geometry": {"coordinates":[151.308059692,-33.6661262512],"type":"Point"}
}