{
  "type": "Feature",
  "properties": {
    "iso:country":"AU",
    "sg:address":"Arkell Crt",
    "sg:city":"Portland",
    "sg:classifiers":[
        {
            "category":"Retail",
            "subcategory":"Driving School",
            "type":"Services"
        }
    ],
    "sg:phone":"+61 3 5523 5315",
    "sg:postcode":"3305",
    "sg:province":"VIC",
    "wof:name":"Bayside Driving School",
    "wof:placetype":"venue"
},
  "geometry": {"coordinates":[141.61871337900001,-38.3602714539],"type":"Point"}
}