{
  "type": "Feature",
  "properties": {
    "addr:full":"6 Ramsden St Clifton Hill VIC 3068",
    "addr:housenumber":"6",
    "addr:postcode":"3068",
    "addr:street":"Ramsden St",
    "iso:country":"AU",
    "sg:address":"6 Ramsden St",
    "sg:city":"Clifton Hill",
    "sg:classifiers":[
        {
            "category":"Health Services",
            "subcategory":"Health Practitioner",
            "type":"Services"
        }
    ],
    "sg:phone":"+61 3 9481 5671",
    "sg:postcode":"3068",
    "sg:province":"VIC",
    "sg:tags":[
        "acupuncture"
    ],
    "wof:name":"Anne Templeton",
    "wof:placetype":"venue"
},
  "geometry": {"coordinates":[144.995605469,-37.790184021],"type":"Point"}
}