{
  "type": "Feature",
  "properties": {
    "addr:full":"Main Rd Morphett Vale SA 5162",
    "addr:postcode":"5162",
    "addr:street":"Main Rd",
    "iso:country":"AU",
    "sg:address":"Main Rd",
    "sg:city":"Morphett Vale",
    "sg:classifiers":[
        {
            "category":"Banks & Credit Unions",
            "subcategory":"Financial Services",
            "type":"Services"
        }
    ],
    "sg:phone":"+61 8 8326 7711",
    "sg:postcode":"5162",
    "sg:province":"SA",
    "sg:tags":[
        "planning"
    ],
    "wof:name":"Elders Financial Planning",
    "wof:placetype":"venue"
},
  "geometry": {"coordinates":[138.523635864,-35.1260871887],"type":"Point"}
}