{
  "type": "Feature",
  "properties": {
    "addr:full":"PO Box 3331 Bangor NSW 2234",
    "addr:postcode":"2234",
    "iso:country":"AU",
    "sg:address":"PO Box 3331",
    "sg:city":"Bangor",
    "sg:classifiers":[
        {
            "category":"Shopping",
            "subcategory":"Bicycles & Sporting Goods",
            "type":"Retail Goods"
        }
    ],
    "sg:phone":"+61 2 9541 1041",
    "sg:postcode":"2234",
    "sg:province":"NSW",
    "sg:tags":[
        "chemical",
        "equipment",
        "pool",
        "swimming"
    ],
    "wof:name":"Aqua Action Slides Pty Ltd",
    "wof:placetype":"venue"
},
  "geometry": {"coordinates":[151.02908325199999,-34.0186805725],"type":"Point"}
}