{
  "type": "Feature",
  "properties": {
    "addr:full":"Unit 1/ 6 Welder St Seven Hills NSW 2147",
    "addr:postcode":"2147",
    "addr:street":"Welder St",
    "iso:country":"AU",
    "sg:address":"Unit 1/ 6 Welder St",
    "sg:city":"Seven Hills",
    "sg:classifiers":[
        {
            "category":"Taxi",
            "type":"Transportation"
        }
    ],
    "sg:phone":"+61 2 9674 4411",
    "sg:postcode":"2147",
    "sg:province":"NSW",
    "sg:tags":[
        "truck"
    ],
    "wof:name":"OTS Taxi Trucks",
    "wof:placetype":"venue"
},
  "geometry": {"coordinates":[150.957962036,-33.7700958252],"type":"Point"}
}