{
  "type": "Feature",
  "properties": {
    "addr:full":"60 Pascoe Vale Rd Moonee Ponds VIC 3039",
    "addr:housenumber":"60",
    "addr:postcode":"3039",
    "addr:street":"Pascoe Vale Rd",
    "iso:country":"AU",
    "sg:address":"60 Pascoe Vale Rd",
    "sg:city":"Moonee Ponds",
    "sg:classifiers":[
        {
            "category":"Health Services",
            "subcategory":"Chiropractor",
            "type":"Services"
        }
    ],
    "sg:phone":"+61 3 9375 1948",
    "sg:postcode":"3039",
    "sg:province":"VIC",
    "wof:name":"Moonee Ponds Chiropractic Clinic",
    "wof:placetype":"venue"
},
  "geometry": {"coordinates":[144.925476,-37.764709],"type":"Point"}
}