{
  "type": "Feature",
  "properties": {
    "addr:full":"Hanson Rd Woodville North SA 5012",
    "addr:postcode":"5012",
    "addr:street":"Hanson Rd",
    "iso:country":"AU",
    "sg:address":"Hanson Rd",
    "sg:city":"Woodville North",
    "sg:classifiers":[
        {
            "category":"Arena",
            "subcategory":"Sports Club",
            "type":"Entertainment"
        }
    ],
    "sg:phone":"+61 8 8347 4047",
    "sg:postcode":"5012",
    "sg:province":"SA",
    "sg:tags":[
        "australian",
        "football",
        "rule"
    ],
    "wof:name":"Woodville North Sports Club Incorporated",
    "wof:placetype":"venue"
},
  "geometry": {"coordinates":[138.54771423299999,-34.8652267456],"type":"Point"}
}