{
  "type": "Feature",
  "properties": {
    "addr:full":"1st Floor 611 Dean St Albury NSW 2640",
    "addr:housenumber":"611",
    "addr:postcode":"2640",
    "addr:street":"Dean St",
    "iso:country":"AU",
    "sg:address":"1st Floor 611 Dean St",
    "sg:city":"Albury",
    "sg:classifiers":[
        {
            "category":"Health Services",
            "subcategory":"Health Practitioner",
            "type":"Services"
        }
    ],
    "sg:phone":"+61 2 6021 6256",
    "sg:postcode":"2640",
    "sg:province":"NSW",
    "sg:tags":[
        "hypnotherapy"
    ],
    "wof:name":"Paul Black",
    "wof:placetype":"venue"
},
  "geometry": {"coordinates":[146.91249084500001,-36.0804138184],"type":"Point"}
}