{
  "type": "Feature",
  "properties": {
    "addr:full":"165 Main St Osborne Park WA 6017",
    "addr:housenumber":"165",
    "addr:postcode":"6017",
    "addr:street":"Main St",
    "iso:country":"AU",
    "sg:address":"165 Main St",
    "sg:city":"Osborne Park",
    "sg:classifiers":[
        {
            "category":"Real Estate",
            "subcategory":"Real Estate Agent",
            "type":"Services"
        }
    ],
    "sg:phone":"+61 8 9344 3377",
    "sg:postcode":"6017",
    "sg:province":"WA",
    "wof:name":"Select First National",
    "wof:placetype":"venue"
},
  "geometry": {"coordinates":[115.828102112,-31.9002304077],"type":"Point"}
}