{
  "type": "Feature",
  "properties": {
    "addr:full":"9 Brennan Ave Maryborough QLD 4650",
    "addr:housenumber":"9",
    "addr:postcode":"4650",
    "addr:street":"Brennan Ave",
    "iso:country":"AU",
    "sg:address":"9 Brennan Ave",
    "sg:city":"Maryborough",
    "sg:classifiers":[
        {
            "category":"Shopping",
            "subcategory":"Computers & Home Electronics",
            "type":"Retail Goods"
        }
    ],
    "sg:phone":"+61 413 513 060",
    "sg:postcode":"4650",
    "sg:province":"QLD",
    "sg:tags":[
        "hardware",
        "equipment"
    ],
    "wof:name":"Computer Concepts & Services",
    "wof:placetype":"venue"
},
  "geometry": {"coordinates":[152.705017,-25.546366],"type":"Point"}
}