{
  "type": "Feature",
  "properties": {
    "iso:country":"AU",
    "sg:address":"22 Nolan St",
    "sg:city":"Raceview",
    "sg:classifiers":[
        {
            "category":"Home & Garden",
            "subcategory":"Building Materials",
            "type":"Retail Goods"
        }
    ],
    "sg:phone":"+61 418 982 810",
    "sg:postcode":"4305",
    "sg:province":"QLD",
    "sg:tags":[
        "secondhand"
    ],
    "wof:name":"A1 M.J. Demolition",
    "wof:placetype":"venue"
},
  "geometry": {"coordinates":[152.78590393100001,-27.6342811584],"type":"Point"}
}