{
  "type": "Feature",
  "properties": {
    "addr:full":"206 Glenmore Rd Paddington NSW 2021",
    "addr:housenumber":"206",
    "addr:postcode":"2021",
    "addr:street":"Glenmore Rd",
    "iso:country":"AU",
    "sg:address":"206 Glenmore Rd",
    "sg:city":"Paddington",
    "sg:classifiers":[
        {
            "category":"Professional",
            "subcategory":"Accounting & Tax Preparation",
            "type":"Services"
        }
    ],
    "sg:phone":"+61 2 9332 1897",
    "sg:postcode":"2021",
    "sg:province":"NSW",
    "sg:tags":[
        "accountant",
        "auditor"
    ],
    "wof:name":"Cavanagh Peter M & Co Pty Ltd",
    "wof:placetype":"venue"
},
  "geometry": {"coordinates":[151.22726440400001,-33.8820953369],"type":"Point"}
}