{
  "type": "Feature",
  "properties": {
    "iso:country":"AU",
    "sg:address":"355 Alice St",
    "sg:city":"Maryborough",
    "sg:classifiers":[
        {
            "category":"Retail",
            "subcategory":"Veterinary Services",
            "type":"Services"
        }
    ],
    "sg:phone":"+61 418 736 112",
    "sg:postcode":"4650",
    "sg:province":"QLD",
    "sg:tags":[
        "surgeon"
    ],
    "wof:name":"Maryborough Veterinary Surgery",
    "wof:placetype":"venue"
},
  "geometry": {"coordinates":[152.69390899999999,-25.536333],"type":"Point"}
}