{
  "type": "Feature",
  "properties": {
    "addr:full":"6 Church St Maroochydore QLD 4558",
    "addr:housenumber":"6",
    "addr:postcode":"4558",
    "addr:street":"Church St",
    "iso:country":"AU",
    "sg:address":"6 Church St",
    "sg:city":"Maroochydore",
    "sg:classifiers":[
        {
            "category":"Shopping",
            "subcategory":"Beauty & Cosmetics",
            "type":"Retail Goods"
        }
    ],
    "sg:phone":"+61 7 5479 5887",
    "sg:postcode":"4558",
    "sg:province":"QLD",
    "sg:tags":[
        "equipment",
        "salon",
        "supply"
    ],
    "wof:name":"CJs Wholesalers",
    "wof:placetype":"venue"
},
  "geometry": {"coordinates":[153.08889770499999,-26.6517658234],"type":"Point"}
}