{
  "type": "Feature",
  "properties": {
    "addr:full":"17a Nerang St Southport QLD 4215",
    "addr:housenumber":"17a",
    "addr:postcode":"4215",
    "addr:street":"Nerang St",
    "iso:country":"AU",
    "sg:address":"17a Nerang St",
    "sg:city":"Southport",
    "sg:classifiers":[
        {
            "category":"Health Services",
            "subcategory":"Optometrist",
            "type":"Services"
        }
    ],
    "sg:phone":"+61 7 5531 2870",
    "sg:postcode":"4215",
    "sg:province":"QLD",
    "sg:website":"http://www.bjob.optom.com.au",
    "wof:name":"Visions By Brian Job Optical",
    "wof:placetype":"venue"
},
  "geometry": {"coordinates":[153.414627075,-27.9670696259],"type":"Point"}
}