{
  "type": "Feature",
  "properties": {
    "iso:country":"AU",
    "sg:address":"78-80 Bellingara Rd",
    "sg:city":"Miranda",
    "sg:classifiers":[
        {
            "category":"Education",
            "subcategory":"Kindergarten",
            "type":"Public Place"
        }
    ],
    "sg:phone":"+61 2 9544 8331",
    "sg:postcode":"2228",
    "sg:province":"NSW",
    "sg:tags":[
        "pre-schools"
    ],
    "wof:name":"Time 4 Kindy",
    "wof:placetype":"venue"
},
  "geometry": {"coordinates":[151.10223388700001,-34.0235214233],"type":"Point"}
}