{
  "type": "Feature",
  "properties": {
    "addr:full":"1017 Victoria Rd West Ryde NSW 2114",
    "addr:housenumber":"1017",
    "addr:postcode":"2114",
    "addr:street":"Victoria Rd",
    "iso:country":"AU",
    "sg:address":"1017 Victoria Rd",
    "sg:city":"West Ryde",
    "sg:classifiers":[
        {
            "category":"Health Services",
            "subcategory":"Health Practitioner",
            "type":"Services"
        }
    ],
    "sg:phone":"+61 2 9807 3270",
    "sg:postcode":"2114",
    "sg:province":"NSW",
    "sg:tags":[
        "physiotherapist"
    ],
    "wof:name":"Reeve Rick & Theodosi Theo",
    "wof:placetype":"venue"
},
  "geometry": {"coordinates":[151.08711242699999,-33.8073005676],"type":"Point"}
}