{
  "type": "Feature",
  "properties": {
    "iso:country":"AU",
    "sg:address":"Dingo St",
    "sg:city":"Kadina",
    "sg:classifiers":[
        {
            "category":"Professional",
            "subcategory":"Art Services",
            "type":"Services"
        }
    ],
    "sg:phone":"+61 8 8821 3822",
    "sg:postcode":"5554",
    "sg:province":"SA",
    "sg:tags":[
        "picture",
        "frame",
        "framing"
    ],
    "wof:name":"Picturesque Framing & Gallery",
    "wof:placetype":"venue"
},
  "geometry": {"coordinates":[137.713134766,-33.9639015198],"type":"Point"}
}