{
  "type": "Feature",
  "properties": {
    "iso:country":"AU",
    "sg:address":"Shop 115 Mandurah Forum Shopping Centre",
    "sg:city":"Mandurah",
    "sg:classifiers":[
        {
            "category":"Organizations",
            "subcategory":"Community Association",
            "type":"Services"
        }
    ],
    "sg:phone":"+61 8 9535 9190",
    "sg:postcode":"6210",
    "sg:province":"WA",
    "sg:tags":[
        "organisation",
        "family",
        "welfare"
    ],
    "wof:name":"Parent Link Home Visiting Service",
    "wof:placetype":"venue"
},
  "geometry": {"coordinates":[115.724609,-32.5247],"type":"Point"}
}