{
  "type": "Feature",
  "properties": {
    "iso:country":"AU",
    "sg:address":"925a Riversdale Rd",
    "sg:city":"Surrey Hills",
    "sg:classifiers":[
        {
            "category":"Personal",
            "subcategory":"Beauty Salon",
            "type":"Services"
        }
    ],
    "sg:phone":"+61 3 9830 4961",
    "sg:postcode":"3127",
    "sg:province":"VIC",
    "sg:tags":[
        "hairdresser"
    ],
    "wof:name":"Studio 9 Two 5",
    "wof:placetype":"venue"
},
  "geometry": {"coordinates":[145.09310913100001,-37.8352355957],"type":"Point"}
}