{
  "type": "Feature",
  "properties": {
    "addr:full":"338 Raglan St Sale VIC 3850",
    "addr:housenumber":"338",
    "addr:postcode":"3850",
    "addr:street":"Raglan St",
    "iso:country":"AU",
    "sg:address":"338 Raglan St",
    "sg:city":"Sale",
    "sg:classifiers":[
        {
            "category":"Manufacturing",
            "subcategory":"Retail Goods",
            "type":"Manufacturing & Wholesale Goods"
        }
    ],
    "sg:phone":"+61 3 5144 7749",
    "sg:postcode":"3850",
    "sg:province":"VIC",
    "sg:tags":[
        "merchant",
        "pump",
        "mfrs"
    ],
    "wof:name":"Henry Drilling Pty Ltd",
    "wof:placetype":"venue"
},
  "geometry": {"coordinates":[147.09135437,-38.1014938354],"type":"Point"}
}