{
  "type": "Feature",
  "properties": {
    "addr:full":"8 Nilmar Ave Wodonga VIC 3690",
    "addr:housenumber":"8",
    "addr:postcode":"3690",
    "addr:street":"Nilmar Ave",
    "iso:country":"AU",
    "sg:address":"8 Nilmar Ave",
    "sg:city":"Wodonga",
    "sg:classifiers":[
        {
            "category":"Building & Trades",
            "subcategory":"Construction",
            "type":"Services"
        }
    ],
    "sg:phone":"+61 2 6024 5077",
    "sg:postcode":"3690",
    "sg:province":"VIC",
    "sg:tags":[
        "contractor"
    ],
    "wof:name":"Contemp Homes",
    "wof:placetype":"venue"
},
  "geometry": {"coordinates":[146.886795044,-36.1251907349],"type":"Point"}
}