{
  "type": "Feature",
  "properties": {
    "addr:full":"125 Kenning Rd Tarneit VIC 3029",
    "addr:housenumber":"125",
    "addr:postcode":"3029",
    "addr:street":"Kenning Rd",
    "iso:country":"AU",
    "sg:address":"125 Kenning Rd",
    "sg:city":"Tarneit",
    "sg:classifiers":[
        {
            "category":"Home & Garden",
            "subcategory":"Garden Supply",
            "type":"Retail Goods"
        }
    ],
    "sg:phone":"+61 3 9748 1237",
    "sg:postcode":"3029",
    "sg:province":"VIC",
    "sg:tags":[
        "shed"
    ],
    "wof:name":"My House Kennels & Cubbies",
    "wof:placetype":"venue"
},
  "geometry": {"coordinates":[144.66134600000001,-37.808613],"type":"Point"}
}