{
  "type": "Feature",
  "properties": {
    "iso:country":"AU",
    "sg:address":"3 Ramsay Crt",
    "sg:city":"The Patch",
    "sg:classifiers":[
        {
            "category":"Building & Trades",
            "subcategory":"Plumbing",
            "type":"Services"
        }
    ],
    "sg:phone":"+61 412 160 565",
    "sg:postcode":"3792",
    "sg:province":"VIC",
    "sg:tags":[
        "plumber",
        "gasfitters"
    ],
    "wof:name":"D R P Plumbing",
    "wof:placetype":"venue"
},
  "geometry": {"coordinates":[145.40182495100001,-37.8911209106],"type":"Point"}
}