{
  "type": "Feature",
  "properties": {
    "addr:full":"38- 48 Osborne St Lockhart NSW 2656",
    "addr:housenumber":"48",
    "addr:postcode":"2656",
    "addr:street":"Osborne St",
    "iso:country":"AU",
    "sg:address":"38- 48 Osborne St",
    "sg:city":"Lockhart",
    "sg:classifiers":[
        {
            "category":"Farming",
            "subcategory":"Fish & Marine Products",
            "type":"Manufacturing & Wholesale Goods"
        }
    ],
    "sg:phone":"+61 2 6920 5583",
    "sg:postcode":"2656",
    "sg:province":"NSW",
    "sg:tags":[
        "chemical",
        "supplier"
    ],
    "wof:name":"Lockhart Rural Service",
    "wof:placetype":"venue"
},
  "geometry": {"coordinates":[146.718994141,-35.2266693115],"type":"Point"}
}