{
  "type": "Feature",
  "properties": {
    "iso:country":"AU",
    "sg:address":"Unit 1/ 87 Catalano Cct",
    "sg:city":"Canning Vale",
    "sg:classifiers":[
        {
            "category":"Retail",
            "subcategory":"Auto Repair",
            "type":"Services"
        }
    ],
    "sg:phone":"+61 8 9456 5050",
    "sg:postcode":"6155",
    "sg:province":"WA",
    "sg:tags":[
        "repairer",
        "motor",
        "engineer"
    ],
    "wof:name":"UltraTune",
    "wof:placetype":"venue"
},
  "geometry": {"coordinates":[115.89653,-32.068272],"type":"Point"}
}