{
  "type": "Feature",
  "properties": {
    "addr:full":"Hull Rd Beecroft NSW 2119",
    "addr:postcode":"2119",
    "addr:street":"Hull Rd",
    "iso:country":"AU",
    "sg:address":"Hull Rd",
    "sg:city":"Beecroft",
    "sg:classifiers":[
        {
            "category":"Professional",
            "subcategory":"Computer Services",
            "type":"Services"
        }
    ],
    "sg:phone":"+61 2 9481 0293",
    "sg:postcode":"2119",
    "sg:province":"NSW",
    "sg:tags":[
        "consultant",
        "system"
    ],
    "wof:name":"Micro-Sas Pty Ltd",
    "wof:placetype":"venue"
},
  "geometry": {"coordinates":[151.05857849099999,-33.7512588501],"type":"Point"}
}