{
  "type": "Feature",
  "properties": {
    "iso:country":"AU",
    "sg:address":"Shop 2 50 Bay View Tce",
    "sg:city":"Claremont",
    "sg:classifiers":[
        {
            "category":"Health Services",
            "subcategory":"Optometrist",
            "type":"Services"
        }
    ],
    "sg:phone":"+61 8 9286 1469",
    "sg:postcode":"6010",
    "sg:province":"WA",
    "wof:name":"Friendlies EyeCare",
    "wof:placetype":"venue"
},
  "geometry": {"coordinates":[115.781143188,-31.9828147888],"type":"Point"}
}