{
  "type": "Feature",
  "properties": {
    "addr:full":"Unit 7/ 130 Forrester Rd St Marys NSW 2760",
    "addr:housenumber":"/ 130",
    "addr:postcode":"2760",
    "addr:street":"Forrester Rd",
    "iso:country":"AU",
    "sg:address":"Unit 7/ 130 Forrester Rd St",
    "sg:city":"Marys",
    "sg:classifiers":[
        {
            "category":"Home & Garden",
            "subcategory":"Building Materials",
            "type":"Retail Goods"
        }
    ],
    "sg:phone":"+61 2 4721 8666",
    "sg:postcode":"2760",
    "sg:province":"NSW",
    "sg:tags":[
        "shutter",
        "roller",
        "grille"
    ],
    "wof:name":"A AA Comfort Control Shutters",
    "wof:placetype":"venue"
},
  "geometry": {"coordinates":[150.775787353,-33.7544784546],"type":"Point"}
}