{
  "type": "Feature",
  "properties": {
    "iso:country":"AU",
    "sg:address":"18 Fitzroy St",
    "sg:city":"Marrickville",
    "sg:classifiers":[
        {
            "category":"Manufacturing",
            "subcategory":"Textiles",
            "type":"Manufacturing & Wholesale Goods"
        }
    ],
    "sg:phone":"+61 2 9519 7288",
    "sg:postcode":"2204",
    "sg:province":"NSW",
    "sg:tags":[
        "dyer"
    ],
    "wof:name":"Fabric Accessories Dye Service Pty Ltd",
    "wof:placetype":"venue"
},
  "geometry": {"coordinates":[151.164871,-33.909973],"type":"Point"}
}