{
  "type": "Feature",
  "properties": {
    "iso:country":"AU",
    "sg:address":"The Boulevarde Centre 5/ 68 Jessica Blvd",
    "sg:city":"Minyama",
    "sg:classifiers":[
        {
            "category":"Professional",
            "subcategory":"Accounting & Tax Preparation",
            "type":"Services"
        }
    ],
    "sg:phone":"+61 7 5444 3433",
    "sg:postcode":"4575",
    "sg:province":"QLD",
    "sg:tags":[
        "consultant",
        "taxation"
    ],
    "wof:name":"Jones Brendan CPA",
    "wof:placetype":"venue"
},
  "geometry": {"coordinates":[153.124054,-26.698994],"type":"Point"}
}