{
  "type": "Feature",
  "properties": {
    "addr:full":"23 Casino St South Lismore NSW 2480",
    "addr:housenumber":"23",
    "addr:postcode":"2480",
    "addr:street":"Casino St South",
    "iso:country":"AU",
    "sg:address":"23 Casino St",
    "sg:city":"South Lismore",
    "sg:classifiers":[
        {
            "category":"Retail",
            "subcategory":"Auto Repair",
            "type":"Services"
        }
    ],
    "sg:phone":"+61 2 6621 6495",
    "sg:postcode":"2480",
    "sg:province":"NSW",
    "sg:tags":[
        "transmission",
        "automotive",
        "car"
    ],
    "wof:name":"Wrights Clutch Service",
    "wof:placetype":"venue"
},
  "geometry": {"coordinates":[153.266967773,-28.8088703156],"type":"Point"}
}