{
  "type": "Feature",
  "properties": {
    "addr:full":"21 Bell St Coburg VIC 3058",
    "addr:housenumber":"21",
    "addr:postcode":"3058",
    "addr:street":"Bell St",
    "iso:country":"AU",
    "sg:address":"21 Bell St",
    "sg:city":"Coburg",
    "sg:classifiers":[
        {
            "category":"Health Services",
            "subcategory":"Health Practitioner",
            "type":"Services"
        }
    ],
    "sg:phone":"+61 3 9354 8686",
    "sg:postcode":"3058",
    "sg:province":"VIC",
    "sg:tags":[
        "psychologist"
    ],
    "wof:name":"Burnard Don",
    "wof:placetype":"venue"
},
  "geometry": {"coordinates":[144.970825195,-37.7416038513],"type":"Point"}
}