{
  "type": "Feature",
  "properties": {
    "iso:country":"AU",
    "sg:address":"Level 2, Bldg B, 482 Victoria Rd",
    "sg:city":"Gladesville",
    "sg:classifiers":[
        {
            "category":"Wholesale",
            "subcategory":"Machinery & Supplies",
            "type":"Manufacturing & Wholesale Goods"
        }
    ],
    "sg:phone":"+61 2 9879 9700",
    "sg:postcode":"2111",
    "sg:province":"NSW",
    "sg:tags":[
        "instrument",
        "scientific"
    ],
    "wof:name":"Leica Microsystems Pty Ltd",
    "wof:placetype":"venue"
},
  "geometry": {"coordinates":[151.120651245,-33.8215560913],"type":"Point"}
}