{
  "type": "Feature",
  "properties": {
    "iso:country":"AU",
    "sg:address":"36 Cox St",
    "sg:city":"Mudgee",
    "sg:classifiers":[
        {
            "category":"Utilities",
            "subcategory":"Water",
            "type":"Services"
        }
    ],
    "sg:phone":"+61 2 6372 1165",
    "sg:postcode":"2850",
    "sg:province":"NSW",
    "sg:tags":[
        "cartage"
    ],
    "wof:name":"MM & R Faucett",
    "wof:placetype":"venue"
},
  "geometry": {"coordinates":[149.57820100000001,-32.592354],"type":"Point"}
}