{
  "type": "Feature",
  "properties": {
    "iso:country":"AU",
    "sg:address":"7 Gothic Rd",
    "sg:city":"Aspendale",
    "sg:classifiers":[
        {
            "category":"Building & Trades",
            "subcategory":"Plumbing",
            "type":"Services"
        }
    ],
    "sg:phone":"+61 3 9580 7045",
    "sg:postcode":"3195",
    "sg:province":"VIC",
    "sg:tags":[
        "plumber",
        "gasfitters"
    ],
    "wof:name":"Chris Plumbing Service",
    "wof:placetype":"venue"
},
  "geometry": {"coordinates":[145.10357665999999,-38.0242996216],"type":"Point"}
}