{
  "type": "Feature",
  "properties": {
    "addr:full":"133 Moray St South Melbourne VIC 3205",
    "addr:housenumber":"133",
    "addr:postcode":"3205",
    "addr:street":"Moray St",
    "iso:country":"AU",
    "sg:address":"133 Moray St",
    "sg:city":"South Melbourne",
    "sg:classifiers":[
        {
            "category":"Utilities",
            "subcategory":"Telephone",
            "type":"Services"
        }
    ],
    "sg:phone":"+61 3 8695 8695",
    "sg:postcode":"3205",
    "sg:province":"VIC",
    "sg:tags":[
        "equipment",
        "system"
    ],
    "wof:name":"AdvaTel",
    "wof:placetype":"venue"
},
  "geometry": {"coordinates":[144.96232599999999,-37.830318],"type":"Point"}
}