{
  "type": "Feature",
  "properties": {
    "addr:full":"145 Croudace Rd Elermore Vale NSW 2287",
    "addr:housenumber":"145",
    "addr:postcode":"2287",
    "addr:street":"Croudace Rd",
    "iso:country":"AU",
    "sg:address":"145 Croudace Rd",
    "sg:city":"Elermore Vale",
    "sg:classifiers":[
        {
            "category":"Travel",
            "subcategory":"Hotels & Motels",
            "type":"Entertainment"
        }
    ],
    "sg:phone":"+61 2 4951 4666",
    "sg:postcode":"2287",
    "sg:province":"NSW",
    "sg:tags":[
        "pub"
    ],
    "wof:name":"Shaft Tavern",
    "wof:placetype":"venue"
},
  "geometry": {"coordinates":[151.67562866200001,-32.9164962769],"type":"Point"}
}