{
  "type": "Feature",
  "properties": {
    "iso:country":"AU",
    "sg:address":"30 Narellan Crs",
    "sg:city":"Bonnyrigg Heights",
    "sg:classifiers":[
        {
            "category":"Shopping",
            "subcategory":"Stationery & Office Supplies",
            "type":"Retail Goods"
        }
    ],
    "sg:phone":"+61 2 9823 2933",
    "sg:postcode":"2177",
    "sg:province":"NSW",
    "sg:tags":[
        "packaging",
        "material"
    ],
    "wof:name":"Equitty Packaging Pty Ltd",
    "wof:placetype":"venue"
},
  "geometry": {"coordinates":[150.869064331,-33.8894691467],"type":"Point"}
}