{
  "type": "Feature",
  "properties": {
    "iso:country":"AU",
    "sg:address":"134 Evans St",
    "sg:city":"Inverell",
    "sg:classifiers":[
        {
            "category":"Home & Garden",
            "subcategory":"Building Materials",
            "type":"Retail Goods"
        }
    ],
    "sg:phone":"+61 2 6722 3867",
    "sg:postcode":"2360",
    "sg:province":"NSW",
    "sg:tags":[
        "fencing"
    ],
    "wof:name":"Thom D W",
    "wof:placetype":"venue"
},
  "geometry": {"coordinates":[151.12294006400001,-29.7687091827],"type":"Point"}
}