{
  "type": "Feature",
  "properties": {
    "addr:full":"Shop 1/ 203 West Coast Hwy Scarborough WA 6019",
    "addr:housenumber":"shop 1 / 203",
    "addr:postcode":"6019",
    "addr:street":"West Coast Hwy",
    "iso:country":"AU",
    "sg:address":"Shop 1/ 203 West Coast Hwy",
    "sg:city":"Scarborough",
    "sg:classifiers":[
        {
            "category":"Professional",
            "subcategory":"Computer Services",
            "type":"Services"
        }
    ],
    "sg:phone":"+61 8 9245 7888",
    "sg:postcode":"6019",
    "sg:province":"WA",
    "sg:tags":[
        "repairs",
        "upgrade",
        "equipment"
    ],
    "wof:name":"JJorg Computer Solutions",
    "wof:placetype":"venue"
},
  "geometry": {"coordinates":[115.779388428,-31.894153595],"type":"Point"}
}