{
  "type": "Feature",
  "properties": {
    "addr:full":"Unit 4, 382 South Rd Richmond SA 5033",
    "addr:housenumber":"382",
    "addr:postcode":"5033",
    "addr:street":"South Rd",
    "iso:country":"AU",
    "sg:address":"Unit 4, 382 South Rd",
    "sg:city":"Richmond",
    "sg:classifiers":[
        {
            "category":"Shopping",
            "subcategory":"Mobile Phones",
            "type":"Retail Goods"
        }
    ],
    "sg:phone":"+61 407 808 757",
    "sg:postcode":"5033",
    "sg:province":"SA",
    "sg:tags":[
        "telephone",
        "accessory"
    ],
    "wof:name":"Ian Osborn",
    "wof:placetype":"venue"
},
  "geometry": {"coordinates":[138.57066345199999,-34.9396781921],"type":"Point"}
}