{
  "type": "Feature",
  "properties": {
    "iso:country":"AU",
    "sg:address":"PO Box 919",
    "sg:city":"Mackay",
    "sg:classifiers":[
        {
            "category":"Organizations",
            "subcategory":"Membership Organization",
            "type":"Services"
        }
    ],
    "sg:phone":"+61 7 4957 7904",
    "sg:postcode":"4740",
    "sg:province":"QLD",
    "sg:tags":[
        "club",
        "car"
    ],
    "wof:name":"Mackay Vintage Motor Club",
    "wof:placetype":"venue"
},
  "geometry": {"coordinates":[149.111847,-21.15519],"type":"Point"}
}