{
  "type": "Feature",
  "properties": {
    "iso:country":"AU",
    "sg:address":"2 Greenfield St",
    "sg:city":"Banksmeadow",
    "sg:classifiers":[
        {
            "category":"Professional",
            "type":"Services"
        }
    ],
    "sg:phone":"+61 2 9666 5411",
    "sg:postcode":"2019",
    "sg:province":"NSW",
    "sg:tags":[
        "transport"
    ],
    "wof:name":"F.B.T. Operations (NSW) Pty Ltd",
    "wof:placetype":"venue"
},
  "geometry": {"coordinates":[151.21104431099999,-33.9587059021],"type":"Point"}
}