{
  "type": "Feature",
  "properties": {
    "addr:full":"2/ 226 Leitchs Rd Brendale QLD 4500",
    "addr:housenumber":"/ 226",
    "addr:postcode":"4500",
    "addr:street":"Leitchs Rd",
    "iso:country":"AU",
    "sg:address":"2/ 226 Leitchs Rd",
    "sg:city":"Brendale",
    "sg:classifiers":[
        {
            "category":"Building & Trades",
            "subcategory":"Construction",
            "type":"Services"
        }
    ],
    "sg:phone":"+61 7 3889 9944",
    "sg:postcode":"4500",
    "sg:province":"QLD",
    "sg:tags":[
        "brick",
        "paving"
    ],
    "wof:name":"Havenstone",
    "wof:placetype":"venue"
},
  "geometry": {"coordinates":[152.97999572800001,-27.3232421875],"type":"Point"}
}