{
  "type": "Feature",
  "properties": {
    "addr:full":"1 Walter St Gosnells WA 6110",
    "addr:housenumber":"1",
    "addr:postcode":"6110",
    "addr:street":"Walter St",
    "iso:country":"AU",
    "sg:address":"1 Walter St",
    "sg:city":"Gosnells",
    "sg:classifiers":[
        {
            "category":"Professional",
            "subcategory":"Detective & Security Services",
            "type":"Services"
        }
    ],
    "sg:phone":"+61 8 9490 7869",
    "sg:postcode":"6110",
    "sg:province":"WA",
    "sg:tags":[
        "consultant",
        "system"
    ],
    "wof:name":"Tomuli T",
    "wof:placetype":"venue"
},
  "geometry": {"coordinates":[115.99684143099999,-32.0693016052],"type":"Point"}
}