{
  "type": "Feature",
  "properties": {
    "iso:country":"AU",
    "sg:address":"30 Malbaru Ave",
    "sg:city":"Ingle Farm",
    "sg:classifiers":[
        {
            "category":"Building & Trades",
            "subcategory":"Construction",
            "type":"Services"
        }
    ],
    "sg:phone":"+61 417 881 831",
    "sg:postcode":"5098",
    "sg:province":"SA",
    "sg:tags":[
        "polishing",
        "sanding",
        "floor"
    ],
    "wof:name":"Trevs Floors",
    "wof:placetype":"venue"
},
  "geometry": {"coordinates":[138.634277344,-34.8353004456],"type":"Point"}
}