{
  "type": "Feature",
  "properties": {
    "addr:full":"32 Bannockburn Rd View Bank VIC 3084",
    "addr:housenumber":"32",
    "addr:postcode":"3084",
    "addr:street":"Bannockburn Rd View",
    "iso:country":"AU",
    "sg:address":"32 Bannockburn Rd",
    "sg:city":"View Bank",
    "sg:classifiers":[
        {
            "category":"Education",
            "subcategory":"Kindergarten",
            "type":"Public Place"
        }
    ],
    "sg:phone":"+61 3 9432 8288",
    "sg:postcode":"3084",
    "sg:province":"VIC",
    "sg:tags":[
        "pre-schools"
    ],
    "wof:name":"Viewbank Child Care Centre Early Education & Kindergarten",
    "wof:placetype":"venue"
},
  "geometry": {"coordinates":[145.101654053,-37.7295417786],"type":"Point"}
}