{
  "type": "Feature",
  "properties": {
    "addr:full":"11 Ingham St Capalaba QLD 4157",
    "addr:housenumber":"11",
    "addr:postcode":"4157",
    "addr:street":"Ingham St",
    "iso:country":"AU",
    "sg:address":"11 Ingham St",
    "sg:city":"Capalaba",
    "sg:classifiers":[
        {
            "category":"Professional",
            "subcategory":"Art Services",
            "type":"Services"
        }
    ],
    "sg:phone":"+61 418 719 715",
    "sg:postcode":"4157",
    "sg:province":"QLD",
    "sg:tags":[
        "decorator",
        "painter"
    ],
    "wof:name":"Kaybre Professional Decorating Services",
    "wof:placetype":"venue"
},
  "geometry": {"coordinates":[153.20979309099999,-27.5228996277],"type":"Point"}
}