{
  "type": "Feature",
  "properties": {
    "addr:full":"36 Hepburn St Mt Magnet WA 6638",
    "addr:housenumber":"36",
    "addr:postcode":"6638",
    "addr:street":"Hepburn St Mt Magnet",
    "iso:country":"AU",
    "sg:address":"36 Hepburn St",
    "sg:city":"Mt Magnet",
    "sg:classifiers":[
        {
            "category":"Food & Beverages",
            "subcategory":"Supermarket",
            "type":"Retail Goods"
        }
    ],
    "sg:phone":"+61 8 9963 4030",
    "sg:postcode":"6638",
    "sg:province":"WA",
    "sg:tags":[
        "grocery",
        "store"
    ],
    "wof:name":"IGA Supermarkets",
    "wof:placetype":"venue"
},
  "geometry": {"coordinates":[117.848548889,-28.0650291443],"type":"Point"}
}