{
  "type": "Feature",
  "properties": {
    "addr:full":"Shop QF38 Centro Colonades Beach Rd Noarlunga Centre SA 5168",
    "addr:postcode":"5168",
    "addr:street":"Beach Rd",
    "iso:country":"AU",
    "sg:address":"Shop QF38 Centro Colonades Beach Rd",
    "sg:city":"Noarlunga Centre",
    "sg:classifiers":[
        {
            "category":"Shopping",
            "subcategory":"Clothing, Apparel, & Fashions",
            "type":"Retail Goods"
        }
    ],
    "sg:phone":"+61 8 8186 3133",
    "sg:postcode":"5168",
    "sg:province":"SA",
    "sg:tags":[
        "lady",
        "wear"
    ],
    "wof:name":"Giordano (Australia) Pty Ltd",
    "wof:placetype":"venue"
},
  "geometry": {"coordinates":[138.491790772,-35.1383476257],"type":"Point"}
}