{
  "type": "Feature",
  "properties": {
    "addr:full":"Cnr Campbell & George Street Queanbeyan NSW 2620",
    "addr:postcode":"2620",
    "addr:street":"Cnr;Street",
    "iso:country":"AU",
    "sg:address":"Cnr Campbell & George Street",
    "sg:city":"Queanbeyan",
    "sg:classifiers":[
        {
            "category":"Restaurant",
            "type":"Food & Drink"
        }
    ],
    "sg:phone":"+61 2 6284 2644",
    "sg:postcode":"2620",
    "sg:province":"NSW",
    "sg:website":"http://www.qbnbowlingclub.com.au",
    "wof:name":"Queanbeyan Bowling Club",
    "wof:placetype":"venue"
},
  "geometry": {"coordinates":[149.22659301799999,-35.3547859192],"type":"Point"}
}