{
  "type": "Feature",
  "properties": {
    "addr:full":"66 King St East Maitland NSW 2323",
    "addr:housenumber":"66",
    "addr:postcode":"2323",
    "addr:street":"King St",
    "iso:country":"AU",
    "sg:address":"66 King St",
    "sg:city":"East Maitland",
    "sg:classifiers":[
        {
            "category":"Professional",
            "subcategory":"Accounting & Tax Preparation",
            "type":"Services"
        }
    ],
    "sg:phone":"+61 2 4933 7575",
    "sg:postcode":"2323",
    "sg:province":"NSW",
    "sg:tags":[
        "consultant",
        "taxation"
    ],
    "wof:name":"George N.D.",
    "wof:placetype":"venue"
},
  "geometry": {"coordinates":[151.58645629899999,-32.750038147],"type":"Point"}
}