{
  "type": "Feature",
  "properties": {
    "addr:full":"1 U.T. Creek Rd ( National Park Rd Alexandra VIC 3714",
    "addr:postcode":"3714",
    "addr:street":"Creek Rd National Park Rd",
    "iso:country":"AU",
    "sg:address":"1 U.T. Creek Rd ( National Park Rd",
    "sg:city":"Alexandra",
    "sg:classifiers":[
        {
            "category":"Shopping",
            "subcategory":"Antiques",
            "type":"Retail Goods"
        }
    ],
    "sg:phone":"+61 3 5772 1174",
    "sg:postcode":"3714",
    "sg:province":"VIC",
    "wof:name":"Hall B M",
    "wof:placetype":"venue"
},
  "geometry": {"coordinates":[145.73634338400001,-37.1954650879],"type":"Point"}
}