{
  "type": "Feature",
  "properties": {
    "addr:full":"35 George St The Rocks NSW 2000",
    "addr:housenumber":"35",
    "addr:postcode":"2000",
    "addr:street":"George St",
    "iso:country":"AU",
    "sg:address":"35 George St",
    "sg:city":"The Rocks",
    "sg:classifiers":[
        {
            "category":"Cafe",
            "type":"Food & Drink"
        }
    ],
    "sg:phone":"+61 2 9241 5557",
    "sg:postcode":"2000",
    "sg:province":"NSW",
    "wof:name":"Swagman's Post Cafe",
    "wof:placetype":"venue"
},
  "geometry": {"coordinates":[151.208618164,-33.8575325012],"type":"Point"}
}