{
  "type": "Feature",
  "properties": {
    "addr:full":"Factory 2, 1625 Main Rd Research VIC 3095",
    "addr:housenumber":"2 1625",
    "addr:postcode":"3095",
    "addr:street":"Main Rd",
    "iso:country":"AU",
    "sg:address":"Factory 2, 1625 Main Rd",
    "sg:city":"Research",
    "sg:classifiers":[
        {
            "category":"Professional",
            "subcategory":"Engineering",
            "type":"Services"
        }
    ],
    "sg:phone":"+61 3 9437 0700",
    "sg:postcode":"3095",
    "sg:province":"VIC",
    "sg:tags":[
        "engineer"
    ],
    "wof:name":"Valley Engineering",
    "wof:placetype":"venue"
},
  "geometry": {"coordinates":[145.187591553,-37.7004852295],"type":"Point"}
}