{
  "type": "Feature",
  "properties": {
    "addr:full":"73a MacPherson St Bronte NSW 2024",
    "addr:housenumber":"73a",
    "addr:postcode":"2024",
    "addr:street":"Macpherson St",
    "iso:country":"AU",
    "sg:address":"73a MacPherson St",
    "sg:city":"Bronte",
    "sg:classifiers":[
        {
            "category":"Professional",
            "subcategory":"Employment Agencies",
            "type":"Services"
        }
    ],
    "sg:phone":"+61 2 9389 3907",
    "sg:postcode":"2024",
    "sg:province":"NSW",
    "sg:tags":[
        "entertainer",
        "agent"
    ],
    "wof:name":"Comic Roasts",
    "wof:placetype":"venue"
},
  "geometry": {"coordinates":[151.26193237300001,-33.9040374756],"type":"Point"}
}