{
  "type": "Feature",
  "properties": {
    "addr:full":"6/ 353 Mann St Gosford NSW 2250",
    "addr:housenumber":"/ 353",
    "addr:postcode":"2250",
    "addr:street":"Mann St",
    "iso:country":"AU",
    "sg:address":"6/ 353 Mann St",
    "sg:city":"Gosford",
    "sg:classifiers":[
        {
            "category":"Professional",
            "subcategory":"Accounting & Tax Preparation",
            "type":"Services"
        }
    ],
    "sg:phone":"+61 2 4323 3449",
    "sg:postcode":"2250",
    "sg:province":"NSW",
    "sg:tags":[
        "accountant",
        "auditor"
    ],
    "wof:name":"Mulligan Sean A. Chartered Accountant",
    "wof:placetype":"venue"
},
  "geometry": {"coordinates":[151.34379577600001,-33.4181632996],"type":"Point"}
}