{
  "type": "Feature",
  "properties": {
    "iso:country":"AU",
    "sg:address":"47 Redcliffe Pde",
    "sg:city":"Redcliffe",
    "sg:classifiers":[
        {
            "category":"Health Services",
            "subcategory":"Doctor",
            "type":"Services"
        }
    ],
    "sg:phone":"+61 7 3283 3488",
    "sg:postcode":"4020",
    "sg:province":"QLD",
    "sg:tags":[
        "medical",
        "practitioner"
    ],
    "wof:name":"Peninsula Eye Centre",
    "wof:placetype":"venue"
},
  "geometry": {"coordinates":[153.11532600000001,-27.228369],"type":"Point"}
}