{
  "type": "Feature",
  "properties": {
    "iso:country":"AU",
    "sg:address":"48a Simmat Ave",
    "sg:city":"Condell Park",
    "sg:classifiers":[
        {
            "category":"Food & Beverages",
            "subcategory":"Supermarket",
            "type":"Retail Goods"
        }
    ],
    "sg:phone":"+61 2 9790 6366",
    "sg:postcode":"2200",
    "sg:province":"NSW",
    "sg:tags":[
        "grocery",
        "store"
    ],
    "wof:name":"P Roufogalis",
    "wof:placetype":"venue"
},
  "geometry": {"coordinates":[151.011383,-33.92244],"type":"Point"}
}