{
  "type": "Feature",
  "properties": {
    "addr:full":"Shop 4, 620 Mogill Rd Chapel Hill QLD 4069",
    "addr:housenumber":"shop 4",
    "addr:postcode":"620;4069",
    "addr:street":"Mogill Rd",
    "iso:country":"AU",
    "sg:address":"Shop 4, 620 Mogill Rd",
    "sg:city":"Chapel Hill",
    "sg:classifiers":[
        {
            "category":"Ice Cream",
            "type":"Food & Drink"
        }
    ],
    "sg:phone":"+61 7 3720 1133",
    "sg:postcode":"4069",
    "sg:province":"QLD",
    "sg:tags":[
        "retail"
    ],
    "wof:name":"Baskin 31 Robbins",
    "wof:placetype":"venue"
},
  "geometry": {"coordinates":[152.960861206,-27.5054416656],"type":"Point"}
}