{
  "type": "Feature",
  "properties": {
    "addr:full":"97 Park Beach Rd Coffs Harbour NSW 2450",
    "addr:housenumber":"97",
    "addr:postcode":"2450",
    "addr:street":"Park Beach Rd",
    "iso:country":"AU",
    "sg:address":"97 Park Beach Rd",
    "sg:city":"Coffs Harbour",
    "sg:classifiers":[
        {
            "category":"Travel",
            "subcategory":"Hotels & Motels",
            "type":"Entertainment"
        }
    ],
    "sg:phone":"+61 2 6652 2055",
    "sg:postcode":"2450",
    "sg:province":"NSW",
    "wof:name":"Comfort Inn Park Beach",
    "wof:placetype":"venue"
},
  "geometry": {"coordinates":[153.132721,-30.285521],"type":"Point"}
}