{
  "type": "Feature",
  "properties": {
    "addr:full":"28 Wandoo St Brisbane QLD 4000",
    "addr:housenumber":"28",
    "addr:postcode":"4000",
    "addr:street":"Wandoo St",
    "iso:country":"AU",
    "sg:address":"28 Wandoo St",
    "sg:city":"Brisbane",
    "sg:classifiers":[
        {
            "category":"Manufacturing",
            "subcategory":"Food",
            "type":"Manufacturing & Wholesale Goods"
        }
    ],
    "sg:phone":"+61 7 3854 0274",
    "sg:postcode":"4000",
    "sg:province":"QLD",
    "sg:tags":[
        "function",
        "catering"
    ],
    "sg:website":"http://www.culinart.com.au",
    "wof:name":"Culinart Creative Catering",
    "wof:placetype":"venue"
},
  "geometry": {"coordinates":[153.04060363799999,-27.4556846619],"type":"Point"}
}