{
  "type": "Feature",
  "properties": {
    "iso:country":"AU",
    "sg:address":"21 Walter Bull Crs",
    "sg:city":"Griffith",
    "sg:classifiers":[
        {
            "category":"Building & Trades",
            "subcategory":"Construction",
            "type":"Services"
        }
    ],
    "sg:phone":"+61 2 6962 4705",
    "sg:postcode":"2680",
    "sg:province":"NSW",
    "sg:tags":[
        "contractor"
    ],
    "wof:name":"Beltrame Building",
    "wof:placetype":"venue"
},
  "geometry": {"coordinates":[146.050323,-34.28944],"type":"Point"}
}