{
  "type": "Feature",
  "properties": {
    "addr:full":"Shp 11/ 111 Remembrance Drv Tahmoor NSW 2573",
    "addr:housenumber":"11 / 111",
    "addr:postcode":"2573",
    "addr:street":"Remembrance Drv",
    "iso:country":"AU",
    "sg:address":"Shp 11/ 111 Remembrance Drv",
    "sg:city":"Tahmoor",
    "sg:classifiers":[
        {
            "category":"Food & Beverages",
            "subcategory":"Bakery",
            "type":"Retail Goods"
        }
    ],
    "sg:phone":"+61 2 4683 0988",
    "sg:postcode":"2573",
    "sg:province":"NSW",
    "sg:tags":[
        "baker"
    ],
    "wof:name":"Brumby's Bakery Tahmoor",
    "wof:placetype":"venue"
},
  "geometry": {"coordinates":[150.59387207,-34.2223510742],"type":"Point"}
}