{
  "type": "Feature",
  "properties": {
    "addr:full":"2 Oaks Crt Sorell TAS 7172",
    "addr:postcode":"7172",
    "addr:street":"2 Oaks Crt",
    "iso:country":"AU",
    "sg:address":"2 Oaks Crt",
    "sg:city":"Sorell",
    "sg:classifiers":[
        {
            "category":"Personal",
            "subcategory":"Massage",
            "type":"Services"
        }
    ],
    "sg:phone":"+61 3 6265 2871",
    "sg:postcode":"7172",
    "sg:province":"TAS",
    "sg:tags":[
        "therapy"
    ],
    "wof:name":"The Gentle Wind Touch",
    "wof:placetype":"venue"
},
  "geometry": {"coordinates":[147.56361389200001,-42.791267395],"type":"Point"}
}