{
  "type": "Feature",
  "properties": {
    "iso:country":"AU",
    "sg:address":"221 Bulwer St",
    "sg:city":"Perth",
    "sg:classifiers":[
        {
            "category":"Personal",
            "subcategory":"Beauty Salon",
            "type":"Services"
        }
    ],
    "sg:phone":"+61 8 9328 2205",
    "sg:postcode":"6000",
    "sg:province":"WA",
    "sg:tags":[
        "hairdresser"
    ],
    "wof:name":"Salon Nuevos",
    "wof:placetype":"venue"
},
  "geometry": {"coordinates":[115.860023498,-31.9394931793],"type":"Point"}
}