{
  "type": "Feature",
  "properties": {
    "addr:full":"Springhurst Rd Kukerin North WA 6352",
    "addr:postcode":"6352",
    "addr:street":"Springhurst Rd;North",
    "iso:country":"AU",
    "sg:address":"Springhurst Rd",
    "sg:city":"Kukerin North",
    "sg:classifiers":[
        {
            "category":"Farming",
            "subcategory":"Farm",
            "type":"Manufacturing & Wholesale Goods"
        }
    ],
    "sg:phone":"+61 8 9864 7912",
    "sg:postcode":"6352",
    "sg:province":"WA",
    "sg:tags":[
        "farmer"
    ],
    "wof:name":"Joyce H F",
    "wof:placetype":"venue"
},
  "geometry": {"coordinates":[118.065376,-33.168579],"type":"Point"}
}