{
  "type": "Feature",
  "properties": {
    "addr:full":"2 Rye Crt Glen Waverley VIC 3150",
    "addr:housenumber":"2",
    "addr:postcode":"3150",
    "addr:street":"Rye Crt",
    "iso:country":"AU",
    "sg:address":"2 Rye Crt",
    "sg:city":"Glen Waverley",
    "sg:classifiers":[
        {
            "category":"Health Services",
            "subcategory":"Health Practitioner",
            "type":"Services"
        }
    ],
    "sg:phone":"+61 3 9884 4545",
    "sg:postcode":"3150",
    "sg:province":"VIC",
    "sg:tags":[
        "alternative"
    ],
    "wof:name":"Rani's Natural Therapies",
    "wof:placetype":"venue"
},
  "geometry": {"coordinates":[145.170288086,-37.8642616272],"type":"Point"}
}