{
  "type": "Feature",
  "properties": {
    "addr:full":"65 Myers St Geelong VIC 3220",
    "addr:housenumber":"65",
    "addr:postcode":"3220",
    "addr:street":"Myers St",
    "iso:country":"AU",
    "sg:address":"65 Myers St",
    "sg:city":"Geelong",
    "sg:classifiers":[
        {
            "category":"Wholesale",
            "subcategory":"Medical Equipment & Supplies",
            "type":"Manufacturing & Wholesale Goods"
        }
    ],
    "sg:phone":"+61 3 5222 6666",
    "sg:postcode":"3220",
    "sg:province":"VIC",
    "sg:tags":[
        "aid",
        "care",
        "health",
        "home"
    ],
    "wof:name":"Whitecross",
    "wof:placetype":"venue"
},
  "geometry": {"coordinates":[144.357224,-38.150742],"type":"Point"}
}