{
  "type": "Feature",
  "properties": {
    "addr:full":"Cnr University Ave & Dwyer Circuit Driver NT 0830",
    "addr:postcode":"nt 0830",
    "addr:street":"University Ave & Dwyer Circuit",
    "iso:country":"AU",
    "sg:address":"Cnr University Ave",
    "sg:city":"& Dwyer Circuit Driver",
    "sg:classifiers":[
        {
            "category":"Sports & Exercise",
            "subcategory":"Golf",
            "type":"Entertainment"
        }
    ],
    "sg:phone":"+61 8 8932 1324",
    "sg:postcode":"0830",
    "sg:province":"NT",
    "sg:tags":[
        "club"
    ],
    "wof:name":"Palmerston Golf & Country Club Inc",
    "wof:placetype":"venue"
},
  "geometry": {"coordinates":[130.970642,-12.480787],"type":"Point"}
}