{
  "type": "Feature",
  "properties": {
    "addr:full":"Shop 9, Strand Arc Sydney NSW 2000",
    "addr:housenumber":"shop 9",
    "addr:postcode":"2000",
    "addr:street":"Strand Arc",
    "iso:country":"AU",
    "sg:address":"Shop 9, Strand Arc",
    "sg:city":"Sydney",
    "sg:classifiers":[
        {
            "category":"Shopping",
            "subcategory":"Luggage & Leather Goods",
            "type":"Retail Goods"
        }
    ],
    "sg:phone":"+61 2 9231 5525",
    "sg:postcode":"2000",
    "sg:province":"NSW",
    "wof:name":"Louis Cardini Leather",
    "wof:placetype":"venue"
},
  "geometry": {"coordinates":[151.20762634299999,-33.8696212769],"type":"Point"}
}