{
  "type": "Feature",
  "properties": {
    "addr:full":"9 Osborn Ave Rostrevor SA 5073",
    "addr:housenumber":"9",
    "addr:postcode":"5073",
    "addr:street":"Osborn Ave",
    "iso:country":"AU",
    "sg:address":"9 Osborn Ave",
    "sg:city":"Rostrevor",
    "sg:classifiers":[
        {
            "category":"Building & Trades",
            "subcategory":"Construction",
            "type":"Services"
        }
    ],
    "sg:phone":"+61 8 8365 9606",
    "sg:postcode":"5073",
    "sg:province":"SA",
    "sg:tags":[
        "fencing",
        "contractor"
    ],
    "wof:name":"Fivos Fencing",
    "wof:placetype":"venue"
},
  "geometry": {"coordinates":[138.69219970699999,-34.8899116516],"type":"Point"}
}