{
  "type": "Feature",
  "properties": {
    "iso:country":"AU",
    "sg:address":"Suite 1/ 195 Fullarton Rd",
    "sg:city":"Dulwich",
    "sg:classifiers":[
        {
            "category":"Building & Trades",
            "subcategory":"Construction",
            "type":"Services"
        }
    ],
    "sg:phone":"+61 8 8431 7122",
    "sg:postcode":"5065",
    "sg:province":"SA",
    "sg:tags":[
        "management"
    ],
    "wof:name":"Ursini Globus Pty Ltd",
    "wof:placetype":"venue"
},
  "geometry": {"coordinates":[138.624832153,-34.9393234253],"type":"Point"}
}