{
  "type": "Feature",
  "properties": {
    "iso:country":"AU",
    "sg:address":"122 Beaudesert Rd",
    "sg:city":"Moorooka",
    "sg:classifiers":[
        {
            "category":"Health Services",
            "subcategory":"Doctor",
            "type":"Services"
        }
    ],
    "sg:phone":"+61 7 3848 8554",
    "sg:postcode":"4105",
    "sg:province":"QLD",
    "sg:tags":[
        "medical",
        "practitioner"
    ],
    "wof:name":"Sullivan Nicolaides Pathology",
    "wof:placetype":"venue"
},
  "geometry": {"coordinates":[153.02407836899999,-27.5310115814],"type":"Point"}
}