{
  "type": "Feature",
  "properties": {
    "addr:full":"2821 Point Nepean Rd Blairgowrie VIC 3942",
    "addr:housenumber":"2821",
    "addr:postcode":"3942",
    "addr:street":"Point Nepean Rd",
    "iso:country":"AU",
    "sg:address":"2821 Point Nepean Rd",
    "sg:city":"Blairgowrie",
    "sg:classifiers":[
        {
            "category":"Food & Beverages",
            "subcategory":"Groceries & Convenience Stores",
            "type":"Retail Goods"
        }
    ],
    "sg:phone":"+61 3 5988 8276",
    "sg:postcode":"3942",
    "sg:province":"VIC",
    "wof:name":"Blairgowrie Milk Bar",
    "wof:placetype":"venue"
},
  "geometry": {"coordinates":[144.78013610799999,-38.3615379333],"type":"Point"}
}