{
  "type": "Feature",
  "properties": {
    "iso:country":"AU",
    "sg:address":"Unit 1 30 Todds Rd",
    "sg:city":"Lawnton",
    "sg:classifiers":[
        {
            "category":"Professional",
            "subcategory":"Art Services",
            "type":"Services"
        }
    ],
    "sg:phone":"+61 7 3285 2132",
    "sg:postcode":"4501",
    "sg:province":"QLD",
    "sg:tags":[
        "decorator",
        "painter"
    ],
    "wof:name":"Bergman G",
    "wof:placetype":"venue"
},
  "geometry": {"coordinates":[152.97892761200001,-27.2824058533],"type":"Point"}
}