{
  "type": "Feature",
  "properties": {
    "addr:full":"37 Grant St Alexandra VIC 3714",
    "addr:housenumber":"37",
    "addr:postcode":"3714",
    "addr:street":"Grant St",
    "iso:country":"AU",
    "sg:address":"37 Grant St",
    "sg:city":"Alexandra",
    "sg:classifiers":[
        {
            "category":"Shopping",
            "type":"Retail Goods"
        }
    ],
    "sg:phone":"+61 3 5772 2444",
    "sg:postcode":"3714",
    "sg:province":"VIC",
    "sg:tags":[
        "agent",
        "stock"
    ],
    "wof:name":"Rodwells & Co Pty Ltd",
    "wof:placetype":"venue"
},
  "geometry": {"coordinates":[145.70960998499999,-37.1912536621],"type":"Point"}
}