{
  "type": "Feature",
  "properties": {
    "iso:country":"AU",
    "sg:address":"2 Walter St",
    "sg:city":"Caboolture",
    "sg:classifiers":[
        {
            "category":"Education",
            "subcategory":"Kindergarten",
            "type":"Public Place"
        }
    ],
    "sg:phone":"+61 7 5499 1588",
    "sg:postcode":"4510",
    "sg:province":"QLD",
    "sg:tags":[
        "pre-schools"
    ],
    "wof:name":"C&K Caboolture Community Kindergarten & Preschool",
    "wof:placetype":"venue"
},
  "geometry": {"coordinates":[152.954926,-27.084093],"type":"Point"}
}