{
  "type": "Feature",
  "properties": {
    "addr:full":"18 Monger St Perth WA 6000",
    "addr:housenumber":"18",
    "addr:postcode":"6000",
    "addr:street":"Monger St",
    "iso:country":"AU",
    "sg:address":"18 Monger St",
    "sg:city":"Perth",
    "sg:classifiers":[
        {
            "category":"Government",
            "subcategory":"Post Office",
            "type":"Public Place"
        }
    ],
    "sg:phone":"+61 8 9328 9267",
    "sg:postcode":"6000",
    "sg:province":"WA",
    "sg:tags":[
        "yoga"
    ],
    "wof:name":"Ka Qi Qung-Fu",
    "wof:placetype":"venue"
},
  "geometry": {"coordinates":[115.86382293699999,-31.9450149536],"type":"Point"}
}