{
  "type": "Feature",
  "properties": {
    "addr:full":"28 Daphne St Forster NSW 2428",
    "addr:housenumber":"28",
    "addr:postcode":"2428",
    "addr:street":"Daphne St",
    "iso:country":"AU",
    "sg:address":"28 Daphne St",
    "sg:city":"Forster",
    "sg:classifiers":[
        {
            "category":"Home & Garden",
            "subcategory":"Carpets & Floor Coverings",
            "type":"Retail Goods"
        }
    ],
    "sg:phone":"+61 2 6554 9308",
    "sg:postcode":"2428",
    "sg:province":"NSW",
    "sg:tags":[
        "tile",
        "wall",
        "layer"
    ],
    "wof:name":"Stephen Neville",
    "wof:placetype":"venue"
},
  "geometry": {"coordinates":[152.53012100000001,-32.190319],"type":"Point"}
}