{
  "type": "Feature",
  "properties": {
    "iso:country":"AU",
    "sg:address":"34 Illawara Crs",
    "sg:city":"Bayswater North",
    "sg:classifiers":[
        {
            "category":"Professional",
            "subcategory":"Accounting & Tax Preparation",
            "type":"Services"
        }
    ],
    "sg:phone":"+61 3 9725 7999",
    "sg:postcode":"3153",
    "sg:province":"VIC",
    "sg:tags":[
        "bookkeeping"
    ],
    "wof:name":"Proud Book Works",
    "wof:placetype":"venue"
},
  "geometry": {"coordinates":[145.29005432100001,-37.8253211975],"type":"Point"}
}