{
  "type": "Feature",
  "properties": {
    "addr:full":"53 Johnson St Maffra VIC 3860",
    "addr:housenumber":"53",
    "addr:postcode":"3860",
    "addr:street":"Johnson St",
    "iso:country":"AU",
    "sg:address":"53 Johnson St",
    "sg:city":"Maffra",
    "sg:classifiers":[
        {
            "category":"Retail",
            "subcategory":"Auto Repair",
            "type":"Services"
        }
    ],
    "sg:phone":"+61 3 5147 1628",
    "sg:postcode":"3860",
    "sg:province":"VIC",
    "sg:tags":[
        "beater",
        "painter",
        "panel"
    ],
    "wof:name":"Maffra Panel Works & Towing Service",
    "wof:placetype":"venue"
},
  "geometry": {"coordinates":[146.97381591800001,-37.9662284851],"type":"Point"}
}