{
  "type": "Feature",
  "properties": {
    "iso:country":"AU",
    "sg:address":"Level 57, 19-29 Martin Pl",
    "sg:city":"Sydney",
    "sg:classifiers":[
        {
            "category":"Banks & Credit Unions",
            "subcategory":"Financial Services",
            "type":"Services"
        }
    ],
    "sg:phone":"+61 1300 796 160",
    "sg:postcode":"2000",
    "sg:province":"NSW",
    "sg:tags":[
        "loan",
        "finance",
        "mortgage"
    ],
    "wof:name":"Money Group Pty Ltd",
    "wof:placetype":"venue"
},
  "geometry": {"coordinates":[151.20866394000001,-33.8676757812],"type":"Point"}
}