{
  "type": "Feature",
  "properties": {
    "addr:full":"1539 Burwood Hwy Tecoma VIC 3160",
    "addr:housenumber":"1539",
    "addr:postcode":"3160",
    "addr:street":"Burwood Hwy",
    "iso:country":"AU",
    "sg:address":"1539 Burwood Hwy",
    "sg:city":"Tecoma",
    "sg:classifiers":[
        {
            "category":"Shopping",
            "subcategory":"Clothing, Apparel, & Fashions",
            "type":"Retail Goods"
        }
    ],
    "sg:phone":"+61 3 9754 2023",
    "sg:postcode":"3160",
    "sg:province":"VIC",
    "sg:tags":[
        "lady",
        "wear"
    ],
    "wof:name":"Rambling Rose Fashion & Furnishings",
    "wof:placetype":"venue"
},
  "geometry": {"coordinates":[145.34422302199999,-37.9065322876],"type":"Point"}
}