{
  "type": "Feature",
  "properties": {
    "addr:full":"6 Adalia St Kallaroo WA 6025",
    "addr:housenumber":"6",
    "addr:postcode":"6025",
    "addr:street":"Adalia St",
    "iso:country":"AU",
    "sg:address":"6 Adalia St",
    "sg:city":"Kallaroo",
    "sg:classifiers":[
        {
            "category":"Utilities",
            "subcategory":"Electric",
            "type":"Services"
        }
    ],
    "sg:phone":"+61 8 9401 5656",
    "sg:postcode":"6025",
    "sg:province":"WA",
    "sg:tags":[
        "electrical",
        "contractor"
    ],
    "wof:name":"Musca J",
    "wof:placetype":"venue"
},
  "geometry": {"coordinates":[115.75247192400001,-31.7902622223],"type":"Point"}
}