{
  "type": "Feature",
  "properties": {
    "addr:full":"628 Glenferrie Rd Hawthorn VIC 3122",
    "addr:housenumber":"628",
    "addr:postcode":"3122",
    "addr:street":"Glenferrie Rd",
    "iso:country":"AU",
    "sg:address":"628 Glenferrie Rd",
    "sg:city":"Hawthorn",
    "sg:classifiers":[
        {
            "category":"Professional",
            "subcategory":"Employment Agencies",
            "type":"Services"
        }
    ],
    "sg:phone":"+61 3 9818 3156",
    "sg:postcode":"3122",
    "sg:province":"VIC",
    "sg:tags":[
        "entertainer",
        "agent"
    ],
    "wof:name":"The Enchanted Kingdom",
    "wof:placetype":"venue"
},
  "geometry": {"coordinates":[145.035430908,-37.822971344],"type":"Point"}
}