{
  "type": "Feature",
  "properties": {
    "iso:country":"AU",
    "sg:address":"Unit 1/ 14 Bonnal Rd",
    "sg:city":"Erina",
    "sg:classifiers":[
        {
            "category":"Banks & Credit Unions",
            "subcategory":"Atm",
            "type":"Services"
        }
    ],
    "sg:phone":"+61 2 4365 4290",
    "sg:postcode":"2250",
    "sg:province":"NSW",
    "sg:tags":[
        "box",
        "case",
        "metal"
    ],
    "wof:name":"Alloy Mr",
    "wof:placetype":"venue"
},
  "geometry": {"coordinates":[151.383666992,-33.4351882935],"type":"Point"}
}