{
  "type": "Feature",
  "properties": {
    "addr:full":"Unit4/ 24 Attwell St Landsdale WA 6065",
    "addr:housenumber":"24",
    "addr:postcode":"6065",
    "addr:street":"Attwell St",
    "iso:country":"AU",
    "sg:address":"Unit4/ 24 Attwell St",
    "sg:city":"Landsdale",
    "sg:classifiers":[
        {
            "category":"Retail",
            "subcategory":"Auto Repair",
            "type":"Services"
        }
    ],
    "sg:phone":"+61 8 9309 1963",
    "sg:postcode":"6065",
    "sg:province":"WA",
    "sg:tags":[
        "repairer",
        "motor",
        "engineer"
    ],
    "wof:name":"J R P Automotives",
    "wof:placetype":"venue"
},
  "geometry": {"coordinates":[115.847732544,-31.8006858826],"type":"Point"}
}