{
  "type": "Feature",
  "properties": {
    "iso:country":"AU",
    "sg:address":"18 Harper St",
    "sg:city":"Harvey",
    "sg:classifiers":[
        {
            "category":"Utilities",
            "type":"Services"
        }
    ],
    "sg:phone":"+61 8 9729 1940",
    "sg:postcode":"6220",
    "sg:province":"WA",
    "sg:tags":[
        "refrigeration",
        "industrial",
        "commercial",
        "retail"
    ],
    "wof:name":"Waroona Refrigeration Services",
    "wof:placetype":"venue"
},
  "geometry": {"coordinates":[115.898331,-33.079079],"type":"Point"}
}