{
  "type": "Feature",
  "properties": {
    "addr:full":"3- 5 Vulcan Rd Canning Vale WA 6155",
    "addr:housenumber":"5",
    "addr:postcode":"6155",
    "addr:street":"Vulcan Rd",
    "iso:country":"AU",
    "sg:address":"3- 5 Vulcan Rd",
    "sg:city":"Canning Vale",
    "sg:classifiers":[
        {
            "category":"Banks & Credit Unions",
            "subcategory":"Bank",
            "type":"Services"
        }
    ],
    "sg:phone":"+61 8 9334 9600",
    "sg:postcode":"6155",
    "sg:province":"WA",
    "sg:tags":[
        "equipment",
        "sale",
        "point"
    ],
    "wof:name":"MBL Retail Solutions",
    "wof:placetype":"venue"
},
  "geometry": {"coordinates":[115.930313,-32.059536],"type":"Point"}
}