{
  "type": "Feature",
  "properties": {
    "iso:country":"AU",
    "sg:address":"20 Jervis St",
    "sg:city":"Tomerong",
    "sg:classifiers":[
        {
            "category":"Building & Trades",
            "subcategory":"Construction",
            "type":"Services"
        }
    ],
    "sg:phone":"+61 2 4443 5353",
    "sg:postcode":"2540",
    "sg:province":"NSW",
    "sg:tags":[
        "earth",
        "excavating",
        "moving",
        "contractor"
    ],
    "wof:name":"Jervis Bay Mini Diggers",
    "wof:placetype":"venue"
},
  "geometry": {"coordinates":[150.731155395,-34.9071731567],"type":"Point"}
}