{
  "type": "Feature",
  "properties": {
    "iso:country":"AU",
    "sg:address":"207 Hampshire Rd",
    "sg:city":"Sunshine",
    "sg:classifiers":[
        {
            "category":"Health Services",
            "subcategory":"Optometrist",
            "type":"Services"
        }
    ],
    "sg:phone":"+61 3 9311 2134",
    "sg:postcode":"3020",
    "sg:province":"VIC",
    "wof:name":"K C McLennan",
    "wof:placetype":"venue"
},
  "geometry": {"coordinates":[144.831726,-37.785763],"type":"Point"}
}