{
  "type": "Feature",
  "properties": {
    "addr:full":"39 Sydenham Rd Brookvale NSW 2100",
    "addr:housenumber":"39",
    "addr:postcode":"2100",
    "addr:street":"Sydenham Rd",
    "iso:country":"AU",
    "sg:address":"39 Sydenham Rd",
    "sg:city":"Brookvale",
    "sg:classifiers":[
        {
            "category":"Home & Garden",
            "subcategory":"Building Materials",
            "type":"Retail Goods"
        }
    ],
    "sg:phone":"+61 2 9938 4800",
    "sg:postcode":"2100",
    "sg:province":"NSW",
    "sg:tags":[
        "roofing"
    ],
    "wof:name":"A.M.R.",
    "wof:placetype":"venue"
},
  "geometry": {"coordinates":[151.27488708499999,-33.7643852234],"type":"Point"}
}