{
  "type": "Feature",
  "properties": {
    "addr:full":"67 Kelly St Pyramid Hill VIC 3575",
    "addr:housenumber":"67",
    "addr:postcode":"3575",
    "addr:street":"Kelly St",
    "iso:country":"AU",
    "sg:address":"67 Kelly St",
    "sg:city":"Pyramid Hill",
    "sg:classifiers":[
        {
            "category":"Education",
            "subcategory":"Kindergarten",
            "type":"Public Place"
        }
    ],
    "sg:phone":"+61 3 5455 7230",
    "sg:postcode":"3575",
    "sg:province":"VIC",
    "sg:tags":[
        "pre-schools"
    ],
    "wof:name":"Pyramid Hill Pre-School",
    "wof:placetype":"venue"
},
  "geometry": {"coordinates":[144.11488342300001,-36.0552215576],"type":"Point"}
}