{
  "type": "Feature",
  "properties": {
    "addr:full":"35 Bonnyrigg Ave Bonnyrigg NSW 2177",
    "addr:housenumber":"35",
    "addr:postcode":"2177",
    "addr:street":"Bonnyrigg Ave",
    "iso:country":"AU",
    "sg:address":"35 Bonnyrigg Ave",
    "sg:city":"Bonnyrigg",
    "sg:classifiers":[
        {
            "category":"Autos & Motor Vehicles",
            "subcategory":"Auto Supplies",
            "type":"Retail Goods"
        }
    ],
    "sg:phone":"+61 2 9822 0500",
    "sg:postcode":"2177",
    "sg:province":"NSW",
    "sg:tags":[
        "tyre"
    ],
    "wof:name":"Bonnyrigg Tyres & Mechanical Repairs",
    "wof:placetype":"venue"
},
  "geometry": {"coordinates":[150.885223389,-33.8903999329],"type":"Point"}
}