{
  "type": "Feature",
  "properties": {
    "iso:country":"AU",
    "sg:address":"125 Beach Rd",
    "sg:city":"Sandringham",
    "sg:classifiers":[
        {
            "category":"Communications",
            "subcategory":"News Services",
            "type":"Services"
        }
    ],
    "sg:phone":"+61 3 9598 2574",
    "sg:postcode":"3191",
    "sg:province":"VIC",
    "sg:tags":[
        "information",
        "tourist",
        "attractions"
    ],
    "wof:name":"Koala Golf Tours",
    "wof:placetype":"venue"
},
  "geometry": {"coordinates":[145.00474548299999,-37.9529647827],"type":"Point"}
}