{
  "type": "Feature",
  "properties": {
    "iso:country":"AU",
    "sg:address":"PO Box 4149",
    "sg:city":"Bundaberg South",
    "sg:classifiers":[
        {
            "category":"Banks & Credit Unions",
            "subcategory":"Investment Brokerage",
            "type":"Services"
        }
    ],
    "sg:phone":"+61 7 4154 3088",
    "sg:postcode":"4670",
    "sg:province":"QLD",
    "sg:tags":[
        "debt",
        "collection"
    ],
    "wof:name":"Advantage Credit Solutions",
    "wof:placetype":"venue"
},
  "geometry": {"coordinates":[152.35313415499999,-24.8744106293],"type":"Point"}
}