{
  "type": "Feature",
  "properties": {
    "iso:country":"AU",
    "sg:address":"18 Joseph St",
    "sg:city":"Blackburn North",
    "sg:classifiers":[
        {
            "category":"Ferry Terminal",
            "type":"Transportation"
        }
    ],
    "sg:phone":"+61 3 9896 7588",
    "sg:postcode":"3130",
    "sg:province":"VIC",
    "sg:tags":[
        "inverter",
        "rectifier"
    ],
    "wof:name":"Rectifier Technologies",
    "wof:placetype":"venue"
},
  "geometry": {"coordinates":[145.14500427199999,-37.8002471924],"type":"Point"}
}