{
  "type": "Feature",
  "properties": {
    "iso:country":"AU",
    "sg:address":"Shp2/ 60 Fairfield St",
    "sg:city":"Elizabeth Grove",
    "sg:classifiers":[
        {
            "category":"Fast Food",
            "type":"Food & Drink"
        }
    ],
    "sg:phone":"+61 8 8255 2862",
    "sg:postcode":"5112",
    "sg:province":"SA",
    "sg:tags":[
        "away",
        "take"
    ],
    "wof:name":"Elizabeth Grove Fish Shop",
    "wof:placetype":"venue"
},
  "geometry": {"coordinates":[138.66987609899999,-34.7353477478],"type":"Point"}
}