{
  "type": "Feature",
  "properties": {
    "addr:full":"140 Hammond Ave Wagga Wagga NSW 2650",
    "addr:housenumber":"140",
    "addr:postcode":"2650",
    "addr:street":"Hammond Ave",
    "iso:country":"AU",
    "sg:address":"140 Hammond Ave",
    "sg:city":"Wagga Wagga",
    "sg:classifiers":[
        {
            "category":"Personal",
            "type":"Services"
        }
    ],
    "sg:phone":"+61 2 6921 1110",
    "sg:postcode":"2650",
    "sg:province":"NSW",
    "sg:tags":[
        "reducing",
        "treatment",
        "weight"
    ],
    "wof:name":"Flexit Gymnasium",
    "wof:placetype":"venue"
},
  "geometry": {"coordinates":[147.396759033,-35.1228485107],"type":"Point"}
}