{
  "type": "Feature",
  "properties": {
    "addr:full":"26 Brisbane St Perth WA 6000",
    "addr:housenumber":"26",
    "addr:postcode":"6000",
    "addr:street":"Brisbane St",
    "iso:country":"AU",
    "sg:address":"26 Brisbane St",
    "sg:city":"Perth",
    "sg:classifiers":[
        {
            "category":"Real Estate",
            "subcategory":"Architect",
            "type":"Services"
        }
    ],
    "sg:phone":"+61 8 9328 2233",
    "sg:postcode":"6000",
    "sg:province":"WA",
    "wof:name":"Montague Grant Architects",
    "wof:placetype":"venue"
},
  "geometry": {"coordinates":[115.862258911,-31.94257164],"type":"Point"}
}