{
  "type": "Feature",
  "properties": {
    "iso:country":"AU",
    "sg:address":"28 Hawke Drv",
    "sg:city":"Woolgoolga",
    "sg:classifiers":[
        {
            "category":"Home & Garden",
            "subcategory":"Hardware",
            "type":"Retail Goods"
        }
    ],
    "sg:phone":"+61 2 6654 2956",
    "sg:postcode":"2456",
    "sg:province":"NSW",
    "sg:tags":[
        "rope",
        "twine"
    ],
    "wof:name":"Coastal Ropes",
    "wof:placetype":"venue"
},
  "geometry": {"coordinates":[153.196365,-30.122313],"type":"Point"}
}