{
  "type": "Feature",
  "properties": {
    "iso:country":"AU",
    "sg:address":"53 Eighth Ave",
    "sg:city":"Maylands",
    "sg:classifiers":[
        {
            "category":"Food & Beverages",
            "subcategory":"Liquor & Beverages",
            "type":"Retail Goods"
        }
    ],
    "sg:phone":"+61 8 9271 0933",
    "sg:postcode":"6051",
    "sg:province":"WA",
    "sg:tags":[
        "store"
    ],
    "wof:name":"Maylands Liquor Centre",
    "wof:placetype":"venue"
},
  "geometry": {"coordinates":[115.892929,-31.92972],"type":"Point"}
}