{
  "type": "Feature",
  "properties": {
    "addr:full":"Level 2/326 Hay St Perth WA 6000",
    "addr:housenumber":"/ 326",
    "addr:postcode":"6000",
    "addr:street":"Hay St",
    "iso:country":"AU",
    "sg:address":"Level 2/326 Hay St",
    "sg:city":"Perth",
    "sg:classifiers":[
        {
            "category":"Real Estate",
            "subcategory":"Surveying",
            "type":"Services"
        }
    ],
    "sg:phone":"+61 8 9221 7375",
    "sg:postcode":"6000",
    "sg:province":"WA",
    "sg:tags":[
        "map",
        "mapping"
    ],
    "wof:name":"Corporate Montage",
    "wof:placetype":"venue"
},
  "geometry": {"coordinates":[115.856056213,-31.9533615112],"type":"Point"}
}