{
  "type": "Feature",
  "properties": {
    "addr:full":"59 McMillan St Bairnsdale VIC 3875",
    "addr:housenumber":"59",
    "addr:postcode":"3875",
    "addr:street":"Mcmillan St",
    "iso:country":"AU",
    "sg:address":"59 McMillan St",
    "sg:city":"Bairnsdale",
    "sg:classifiers":[
        {
            "category":"Building & Trades",
            "subcategory":"Construction",
            "type":"Services"
        }
    ],
    "sg:phone":"+61 3 5152 1208",
    "sg:postcode":"3875",
    "sg:province":"VIC",
    "sg:tags":[
        "earth",
        "excavating",
        "moving",
        "contractor"
    ],
    "wof:name":"Willox Chris & Debbie",
    "wof:placetype":"venue"
},
  "geometry": {"coordinates":[147.65489196799999,-37.8227005005],"type":"Point"}
}