{
  "type": "Feature",
  "properties": {
    "addr:full":"97 Eddystone Ave Craigie WA 6025",
    "addr:housenumber":"97",
    "addr:postcode":"6025",
    "addr:street":"Eddystone Ave",
    "iso:country":"AU",
    "sg:address":"97 Eddystone Ave",
    "sg:city":"Craigie",
    "sg:classifiers":[
        {
            "category":"Retail",
            "subcategory":"Repair Shop",
            "type":"Services"
        }
    ],
    "sg:phone":"+61 8 9402 7006",
    "sg:postcode":"6025",
    "sg:province":"WA",
    "sg:tags":[
        "upholsterer"
    ],
    "wof:name":"Lino Uph",
    "wof:placetype":"venue"
},
  "geometry": {"coordinates":[115.767242432,-31.7860069275],"type":"Point"}
}