{
  "type": "Feature",
  "properties": {
    "addr:full":"Phipps St Nanango QLD 4615",
    "addr:postcode":"4615",
    "addr:street":"Phipps St",
    "iso:country":"AU",
    "sg:address":"Phipps St",
    "sg:city":"Nanango",
    "sg:classifiers":[
        {
            "category":"Social Services",
            "subcategory":"Adult Care",
            "type":"Services"
        }
    ],
    "sg:phone":"+61 7 4163 3622",
    "sg:postcode":"4615",
    "sg:province":"QLD",
    "sg:tags":[
        "towing"
    ],
    "wof:name":"Clayton's Towing Service Pty Ltd",
    "wof:placetype":"venue"
},
  "geometry": {"coordinates":[152.00094604500001,-26.6758708954],"type":"Point"}
}