{
  "type": "Feature",
  "properties": {
    "addr:full":"PO Box 92 Greenock SA 5360",
    "addr:postcode":"5360",
    "iso:country":"AU",
    "sg:address":"PO Box 92",
    "sg:city":"Greenock",
    "sg:classifiers":[
        {
            "category":"Farming",
            "subcategory":"Livestock Farm",
            "type":"Manufacturing & Wholesale Goods"
        }
    ],
    "sg:phone":"+61 8 8562 8250",
    "sg:postcode":"5360",
    "sg:province":"SA",
    "sg:tags":[
        "breeder",
        "horse",
        "stud"
    ],
    "wof:name":"El Talentos Stud (Andalusians)",
    "wof:placetype":"venue"
},
  "geometry": {"coordinates":[138.89671325699999,-34.4674491882],"type":"Point"}
}