{
  "type": "Feature",
  "properties": {
    "iso:country":"AU",
    "sg:address":"69c Central Ave",
    "sg:city":"Oak Flats",
    "sg:classifiers":[
        {
            "category":"Fast Food",
            "type":"Food & Drink"
        }
    ],
    "sg:phone":"+61 2 4256 4703",
    "sg:postcode":"2529",
    "sg:province":"NSW",
    "sg:tags":[
        "away",
        "take"
    ],
    "wof:name":"Pollis Kettle",
    "wof:placetype":"venue"
},
  "geometry": {"coordinates":[150.81900024399999,-34.5634803772],"type":"Point"}
}