{
  "type": "Feature",
  "properties": {
    "addr:full":"1 Main St Springfield Lakes QLD 4300",
    "addr:housenumber":"1",
    "addr:postcode":"4300",
    "addr:street":"Main St",
    "iso:country":"AU",
    "sg:address":"1 Main St",
    "sg:city":"Springfield Lakes",
    "sg:classifiers":[
        {
            "category":"Shopping",
            "subcategory":"Clothing, Apparel, & Fashions",
            "type":"Retail Goods"
        }
    ],
    "sg:phone":"+61 7 3470 0141",
    "sg:postcode":"4300",
    "sg:province":"QLD",
    "sg:tags":[
        "lady",
        "wear"
    ],
    "wof:name":"Witchery",
    "wof:placetype":"venue"
},
  "geometry": {"coordinates":[152.88902282699999,-27.6098613739],"type":"Point"}
}