{
  "type": "Feature",
  "properties": {
    "addr:full":"39 Koombahla Drv Tallebudgera QLD 4228",
    "addr:housenumber":"39",
    "addr:postcode":"4228",
    "addr:street":"Koombahla Drv",
    "iso:country":"AU",
    "sg:address":"39 Koombahla Drv",
    "sg:city":"Tallebudgera",
    "sg:classifiers":[
        {
            "category":"Farming",
            "subcategory":"Livestock Farm",
            "type":"Manufacturing & Wholesale Goods"
        }
    ],
    "sg:phone":"+61 7 5533 9180",
    "sg:postcode":"4228",
    "sg:province":"QLD",
    "sg:tags":[
        "breeder",
        "horse",
        "stud"
    ],
    "wof:name":"Tally Park Agistment Centre",
    "wof:placetype":"venue"
},
  "geometry": {"coordinates":[153.41778564399999,-28.1453495026],"type":"Point"}
}