{
  "type": "Feature",
  "properties": {
    "iso:country":"AU",
    "sg:address":"Factory 2/ 13 Downard St",
    "sg:city":"Braeside",
    "sg:classifiers":[
        {
            "category":"Shopping",
            "subcategory":"Stationery & Office Supplies",
            "type":"Retail Goods"
        }
    ],
    "sg:phone":"+61 3 9580 9422",
    "sg:postcode":"3195",
    "sg:province":"VIC",
    "sg:tags":[
        "merchant",
        "paper"
    ],
    "wof:name":"Russell Carr Paper",
    "wof:placetype":"venue"
},
  "geometry": {"coordinates":[145.11134338400001,-37.9906234741],"type":"Point"}
}