{
  "type": "Feature",
  "properties": {
    "addr:full":"3 Glenwood Ave Glen Waverley VIC 3150",
    "addr:housenumber":"3",
    "addr:postcode":"3150",
    "addr:street":"Glenwood Ave",
    "iso:country":"AU",
    "sg:address":"3 Glenwood Ave",
    "sg:city":"Glen Waverley",
    "sg:classifiers":[
        {
            "category":"Manufacturing",
            "subcategory":"Printing",
            "type":"Manufacturing & Wholesale Goods"
        }
    ],
    "sg:phone":"+61 3 9560 7772",
    "sg:postcode":"3150",
    "sg:province":"VIC",
    "sg:tags":[
        "wholesaler",
        "mfrs",
        "greeting",
        "card"
    ],
    "wof:name":"Rose Stereograph Co",
    "wof:placetype":"venue"
},
  "geometry": {"coordinates":[145.15753173799999,-37.8884162903],"type":"Point"}
}