{
  "type": "Feature",
  "properties": {
    "addr:full":"8 Fifth St Loxton SA 5333",
    "addr:housenumber":"8",
    "addr:postcode":"5333",
    "addr:street":"Fifth St",
    "iso:country":"AU",
    "sg:address":"8 Fifth St",
    "sg:city":"Loxton",
    "sg:classifiers":[
        {
            "category":"Home & Garden",
            "subcategory":"Building Materials",
            "type":"Retail Goods"
        }
    ],
    "sg:phone":"+61 8 8584 7126",
    "sg:postcode":"5333",
    "sg:province":"SA",
    "sg:tags":[
        "merchant",
        "glass",
        "glazier"
    ],
    "wof:name":"Bartsch H W & Sons Pty Ltd",
    "wof:placetype":"venue"
},
  "geometry": {"coordinates":[140.565505981,-34.4577026367],"type":"Point"}
}