{
  "type": "Feature",
  "properties": {
    "addr:full":"PO Box 159 Mt Garnet QLD 4872",
    "addr:postcode":"4872",
    "addr:street":"Garnet",
    "iso:country":"AU",
    "sg:address":"PO Box 159",
    "sg:city":"Mt Garnet",
    "sg:classifiers":[
        {
            "category":"Professional",
            "subcategory":"Computer Services",
            "type":"Services"
        }
    ],
    "sg:phone":"+61 7 4097 0276",
    "sg:postcode":"4872",
    "sg:province":"QLD",
    "sg:tags":[
        "repairs",
        "upgrade",
        "equipment"
    ],
    "wof:name":"Nq Rural Technology",
    "wof:placetype":"venue"
},
  "geometry": {"coordinates":[145.12661743199999,-17.6828651428],"type":"Point"}
}