{
  "type": "Feature",
  "properties": {
    "iso:country":"AU",
    "sg:address":"The Abbey Pl",
    "sg:city":"Caboolture",
    "sg:classifiers":[
        {
            "category":"Communications",
            "subcategory":"News Services",
            "type":"Services"
        }
    ],
    "sg:phone":"+61 7 5495 1652",
    "sg:postcode":"4510",
    "sg:province":"QLD",
    "sg:tags":[
        "information",
        "tourist",
        "attractions"
    ],
    "wof:name":"Abbey Museum Of Art & Archaeology Inc.",
    "wof:placetype":"venue"
},
  "geometry": {"coordinates":[152.949814,-27.07114],"type":"Point"}
}