{
  "type": "Feature",
  "properties": {
    "iso:country":"AU",
    "sg:address":"7 Wildflower Pl",
    "sg:city":"Dural",
    "sg:classifiers":[
        {
            "category":"Building & Trades",
            "subcategory":"Construction",
            "type":"Services"
        }
    ],
    "sg:phone":"+61 418 618 085",
    "sg:postcode":"2158",
    "sg:province":"NSW",
    "sg:tags":[
        "rendering",
        "cement"
    ],
    "wof:name":"Onay Cement Rendering",
    "wof:placetype":"venue"
},
  "geometry": {"coordinates":[151.030807495,-33.7157325745],"type":"Point"}
}