{
  "type": "Feature",
  "properties": {
    "addr:full":"15- 17 Argyle st St Parramatta NSW 2150",
    "addr:housenumber":"17",
    "addr:postcode":"2150",
    "addr:street":"Argyle St St",
    "iso:country":"AU",
    "sg:address":"15- 17 Argyle st St",
    "sg:city":"Parramatta",
    "sg:classifiers":[
        {
            "category":"Education",
            "subcategory":"Junior College",
            "type":"Public Place"
        }
    ],
    "sg:phone":"+61 2 9687 1097",
    "sg:postcode":"2150",
    "sg:province":"NSW",
    "sg:tags":[
        "make-up"
    ],
    "wof:name":"Mask Make-Up And Beauty",
    "wof:placetype":"venue"
},
  "geometry": {"coordinates":[151.03305053700001,-33.8419685364],"type":"Point"}
}