{
  "type": "Feature",
  "properties": {
    "iso:country":"AU",
    "sg:address":"U1/ 52 Hatherley Pde",
    "sg:city":"Winthrop",
    "sg:classifiers":[
        {
            "category":"Health Services",
            "subcategory":"Doctor",
            "type":"Services"
        }
    ],
    "sg:phone":"+61 8 9310 4400",
    "sg:postcode":"6150",
    "sg:province":"WA",
    "sg:tags":[
        "medical",
        "practitioner"
    ],
    "wof:name":"Leonard June",
    "wof:placetype":"venue"
},
  "geometry": {"coordinates":[115.83261899999999,-32.058208],"type":"Point"}
}