{
  "type": "Feature",
  "properties": {
    "addr:full":"2 Pioneer Drv Forster NSW 2428",
    "addr:housenumber":"2",
    "addr:postcode":"2428",
    "addr:street":"Pioneer Drv",
    "iso:country":"AU",
    "sg:address":"2 Pioneer Drv",
    "sg:city":"Forster",
    "sg:classifiers":[
        {
            "category":"Education",
            "subcategory":"Special Training",
            "type":"Public Place"
        }
    ],
    "sg:phone":"+61 2 6555 6055",
    "sg:postcode":"2428",
    "sg:province":"NSW",
    "sg:tags":[
        "development"
    ],
    "wof:name":"Little Pioneers Childcare& Education Centre",
    "wof:placetype":"venue"
},
  "geometry": {"coordinates":[152.53254699999999,-32.196636],"type":"Point"}
}