{
  "type": "Feature",
  "properties": {
    "iso:country":"AU",
    "sg:address":"Shop 4/ 118 York St",
    "sg:city":"Tahmoor",
    "sg:classifiers":[
        {
            "category":"Personal",
            "subcategory":"Beauty Salon",
            "type":"Services"
        }
    ],
    "sg:phone":"+61 2 4681 9787",
    "sg:postcode":"2573",
    "sg:province":"NSW",
    "sg:tags":[
        "hairdresser"
    ],
    "wof:name":"La Bonz Hair Studio",
    "wof:placetype":"venue"
},
  "geometry": {"coordinates":[150.58988952600001,-34.2264060974],"type":"Point"}
}