{
  "type": "Feature",
  "properties": {
    "iso:country":"AU",
    "sg:address":"8 Wright St",
    "sg:city":"Bayswater",
    "sg:classifiers":[
        {
            "category":"Retail",
            "subcategory":"Auto Rental",
            "type":"Services"
        }
    ],
    "sg:phone":"+61 8 9471 7766",
    "sg:postcode":"6053",
    "sg:province":"WA",
    "sg:tags":[
        "bus",
        "truck"
    ],
    "wof:name":"Buses You Drive Big & Small",
    "wof:placetype":"venue"
},
  "geometry": {"coordinates":[115.920349121,-31.9073848724],"type":"Point"}
}