{
  "type": "Feature",
  "properties": {
    "addr:full":"18 Broadway St Broadway NSW 2007",
    "addr:housenumber":"18",
    "addr:postcode":"2007",
    "addr:street":"Broadway St",
    "iso:country":"AU",
    "sg:address":"18 Broadway St",
    "sg:city":"Broadway",
    "sg:classifiers":[
        {
            "category":"Retail",
            "subcategory":"Auto Rental",
            "type":"Services"
        }
    ],
    "sg:phone":"+61 2 9212 3111",
    "sg:postcode":"2007",
    "sg:province":"NSW",
    "sg:tags":[
        "car",
        "hire",
        "minibus"
    ],
    "wof:name":"Car Hire Australia",
    "wof:placetype":"venue"
},
  "geometry": {"coordinates":[151.20039367699999,-33.8844032288],"type":"Point"}
}