{
  "type": "Feature",
  "properties": {
    "addr:full":"U 1/ 5 Kamholtz Crt Ashmore QLD 4214",
    "addr:housenumber":"5",
    "addr:postcode":"4214",
    "addr:street":"Kamholtz Crt",
    "iso:country":"AU",
    "sg:address":"U 1/ 5 Kamholtz Crt",
    "sg:city":"Ashmore",
    "sg:classifiers":[
        {
            "category":"Retail",
            "subcategory":"Auto Repair",
            "type":"Services"
        }
    ],
    "sg:phone":"+61 7 5539 4311",
    "sg:postcode":"4214",
    "sg:province":"QLD",
    "sg:tags":[
        "beater",
        "painter",
        "panel"
    ],
    "wof:name":"Matthew's Paint & Panel",
    "wof:placetype":"venue"
},
  "geometry": {"coordinates":[153.36045837399999,-27.9859886169],"type":"Point"}
}