{
  "type": "Feature",
  "properties": {
    "addr:full":"Paradise Centre, Cnr Burns & Lutana Sts Kawana Waters QLD 4575",
    "addr:postcode":"4575",
    "addr:street":"Cnr",
    "iso:country":"AU",
    "sg:address":"Paradise Centre, Cnr Burns & Lutana Sts",
    "sg:city":"Kawana Waters",
    "sg:classifiers":[
        {
            "category":"Personal",
            "subcategory":"Beauty Salon",
            "type":"Services"
        }
    ],
    "sg:phone":"+61 7 5444 2716",
    "sg:postcode":"4575",
    "sg:province":"QLD",
    "sg:tags":[
        "hairdresser"
    ],
    "wof:name":"Unseen Hair Studio & Day Spa",
    "wof:placetype":"venue"
},
  "geometry": {"coordinates":[153.12986799999999,-26.705536],"type":"Point"}
}