{
  "type": "Feature",
  "properties": {
    "addr:full":"Dewar St Lake Grace WA 6353",
    "addr:postcode":"6353",
    "addr:street":"Dewar St Lake Grace",
    "iso:country":"AU",
    "sg:address":"Dewar St",
    "sg:city":"Lake Grace",
    "sg:classifiers":[
        {
            "category":"Autos & Motor Vehicles",
            "subcategory":"Fuel & Gas Station",
            "type":"Retail Goods"
        }
    ],
    "sg:phone":"+61 8 9865 1221",
    "sg:postcode":"6353",
    "sg:province":"WA",
    "wof:name":"BP Australia Limited",
    "wof:placetype":"venue"
},
  "geometry": {"coordinates":[118.464973,-33.099316],"type":"Point"}
}