{
  "type": "Feature",
  "properties": {
    "addr:full":"1 First Ave Bongaree QLD 4507",
    "addr:housenumber":"1",
    "addr:postcode":"4507",
    "addr:street":"First Ave",
    "iso:country":"AU",
    "sg:address":"1 First Ave",
    "sg:city":"Bongaree",
    "sg:classifiers":[
        {
            "category":"Real Estate",
            "subcategory":"Real Estate Agent",
            "type":"Services"
        }
    ],
    "sg:phone":"+61 7 3408 1633",
    "sg:postcode":"4507",
    "sg:province":"QLD",
    "wof:name":"Bribie Island Real Estate The",
    "wof:placetype":"venue"
},
  "geometry": {"coordinates":[153.15953064000001,-27.0839729309],"type":"Point"}
}