{
  "type": "Feature",
  "properties": {
    "addr:full":"Studio - Lot 3 Berkeley Rd Berkeley NSW 2506",
    "addr:housenumber":"3",
    "addr:postcode":"2506",
    "addr:street":"Berkeley Rd",
    "iso:country":"AU",
    "sg:address":"Studio - Lot 3 Berkeley Rd",
    "sg:city":"Berkeley",
    "sg:classifiers":[
        {
            "category":"Education",
            "subcategory":"Dance Studio",
            "type":"Public Place"
        }
    ],
    "sg:phone":"+61 2 4271 8103",
    "sg:postcode":"2506",
    "sg:province":"NSW",
    "sg:tags":[
        "venue",
        "tuition"
    ],
    "wof:name":"D.Js Theatrical Dance Studio",
    "wof:placetype":"venue"
},
  "geometry": {"coordinates":[150.85548399999999,-34.478943],"type":"Point"}
}