{
  "type": "Feature",
  "properties": {
    "iso:country":"AU",
    "sg:address":"50 Vine St",
    "sg:city":"Moonee Ponds",
    "sg:classifiers":[
        {
            "category":"Home & Garden",
            "subcategory":"Carpets & Floor Coverings",
            "type":"Retail Goods"
        }
    ],
    "sg:phone":"+61 412 140 844",
    "sg:postcode":"3039",
    "sg:province":"VIC",
    "sg:tags":[
        "tile",
        "wall",
        "layer"
    ],
    "wof:name":"MCI Tiling",
    "wof:placetype":"venue"
},
  "geometry": {"coordinates":[144.93241900000001,-37.769058],"type":"Point"}
}