{
  "type": "Feature",
  "properties": {
    "addr:full":"80 Gypsum St Broken Hill NSW 2880",
    "addr:housenumber":"80",
    "addr:postcode":"2880",
    "addr:street":"Gypsum St",
    "iso:country":"AU",
    "sg:address":"80 Gypsum St",
    "sg:city":"Broken Hill",
    "sg:classifiers":[
        {
            "category":"Shopping",
            "subcategory":"Computers & Home Electronics",
            "type":"Retail Goods"
        }
    ],
    "sg:phone":"+61 8 8088 6662",
    "sg:postcode":"2880",
    "sg:province":"NSW",
    "sg:tags":[
        "small",
        "equipment",
        "business"
    ],
    "wof:name":"Kegzies Computer Services",
    "wof:placetype":"venue"
},
  "geometry": {"coordinates":[141.445922852,-31.9678611755],"type":"Point"}
}