{
  "type": "Feature",
  "properties": {
    "iso:country":"AU",
    "sg:address":"Unit 3/ 30-32 Beaconsfield Ave",
    "sg:city":"Midvale",
    "sg:classifiers":[
        {
            "category":"Autos & Motor Vehicles",
            "subcategory":"Automobile Sales",
            "type":"Retail Goods"
        }
    ],
    "sg:phone":"+61 412 952 366",
    "sg:postcode":"6056",
    "sg:province":"WA",
    "sg:tags":[
        "car",
        "used"
    ],
    "wof:name":"Creek Wholesale",
    "wof:placetype":"venue"
},
  "geometry": {"coordinates":[116.03431701700001,-31.8935317993],"type":"Point"}
}