{
  "type": "Feature",
  "properties": {
    "addr:full":"Unit 6/ 220 Balcatta Rd Balcatta WA 6021",
    "addr:housenumber":"/ 220",
    "addr:postcode":"6021",
    "addr:street":"Balcatta Rd",
    "iso:country":"AU",
    "sg:address":"Unit 6/ 220 Balcatta Rd",
    "sg:city":"Balcatta",
    "sg:classifiers":[
        {
            "category":"Fast Food",
            "type":"Food & Drink"
        }
    ],
    "sg:phone":"+61 8 9345 3346",
    "sg:postcode":"6021",
    "sg:province":"WA",
    "sg:tags":[
        "away",
        "take"
    ],
    "wof:name":"Sterling Lunch Bar",
    "wof:placetype":"venue"
},
  "geometry": {"coordinates":[115.81758117699999,-31.8626365662],"type":"Point"}
}