{
  "type": "Feature",
  "properties": {
    "iso:country":"AU",
    "sg:address":"193A Flinders St",
    "sg:city":"Yokine",
    "sg:classifiers":[
        {
            "category":"Personal",
            "subcategory":"Beauty Salon",
            "type":"Services"
        }
    ],
    "sg:phone":"+61 8 9440 6880",
    "sg:postcode":"6060",
    "sg:province":"WA",
    "sg:tags":[
        "hairdresser"
    ],
    "wof:name":"V Style Hair",
    "wof:placetype":"venue"
},
  "geometry": {"coordinates":[115.849250794,-31.8945980072],"type":"Point"}
}