{
  "type": "Feature",
  "properties": {
    "addr:full":"2/ 7 Fulham Rd Pimlico QLD 4812",
    "addr:housenumber":"/ 7",
    "addr:postcode":"4812",
    "addr:street":"Fulham Rd",
    "iso:country":"AU",
    "sg:address":"2/ 7 Fulham Rd",
    "sg:city":"Pimlico",
    "sg:classifiers":[
        {
            "category":"Professional",
            "subcategory":"Employment Agencies",
            "type":"Services"
        }
    ],
    "sg:phone":"+61 7 4729 0099",
    "sg:postcode":"4812",
    "sg:province":"QLD",
    "sg:tags":[
        "occupational",
        "therapist"
    ],
    "wof:name":"Debra Phillips Paediatric Occupational Therapy",
    "wof:placetype":"venue"
},
  "geometry": {"coordinates":[146.790009,-19.289486],"type":"Point"}
}