{
  "type": "Feature",
  "properties": {
    "addr:full":"62- 66 Princes Hwy Wurruk VIC 3850",
    "addr:housenumber":"66",
    "addr:postcode":"3850",
    "addr:street":"Princes Hwy",
    "iso:country":"AU",
    "sg:address":"62- 66 Princes Hwy",
    "sg:city":"Wurruk",
    "sg:classifiers":[
        {
            "category":"Wholesale",
            "subcategory":"Metals & Minerals",
            "type":"Manufacturing & Wholesale Goods"
        }
    ],
    "sg:phone":"+61 3 5143 0115",
    "sg:postcode":"3850",
    "sg:province":"VIC",
    "sg:tags":[
        "steel",
        "merchant"
    ],
    "wof:name":"Boord Trading Pty Ltd",
    "wof:placetype":"venue"
},
  "geometry": {"coordinates":[147.03546142600001,-38.1057128906],"type":"Point"}
}