{
  "type": "Feature",
  "properties": {
    "addr:full":"1 Gilbert Ave Pinnaroo SA 5304",
    "addr:housenumber":"1",
    "addr:postcode":"5304",
    "addr:street":"Gilbert Ave",
    "iso:country":"AU",
    "sg:address":"1 Gilbert Ave",
    "sg:city":"Pinnaroo",
    "sg:classifiers":[
        {
            "category":"Health Services",
            "subcategory":"Doctor",
            "type":"Services"
        }
    ],
    "sg:phone":"+61 8 8577 8013",
    "sg:postcode":"5304",
    "sg:province":"SA",
    "sg:tags":[
        "medical",
        "practitioner"
    ],
    "wof:name":"Mallee Medical Practice/ Pinnaroo",
    "wof:placetype":"venue"
},
  "geometry": {"coordinates":[140.91000366200001,-35.2550621033],"type":"Point"}
}