{
  "type": "Feature",
  "properties": {
    "addr:full":"24 Excalibur Ave Castle Hill NSW 2154",
    "addr:housenumber":"24",
    "addr:postcode":"2154",
    "addr:street":"Excalibur Ave",
    "iso:country":"AU",
    "sg:address":"24 Excalibur Ave",
    "sg:city":"Castle Hill",
    "sg:classifiers":[
        {
            "category":"Building & Trades",
            "subcategory":"Construction",
            "type":"Services"
        }
    ],
    "sg:phone":"+61 2 9659 0513",
    "sg:postcode":"2154",
    "sg:province":"NSW",
    "sg:tags":[
        "earth",
        "excavating",
        "moving",
        "contractor"
    ],
    "wof:name":"Dingo King",
    "wof:placetype":"venue"
},
  "geometry": {"coordinates":[150.991699219,-33.7108840942],"type":"Point"}
}