{
  "type": "Feature",
  "properties": {
    "addr:full":"5 Bailey Crs Warrnambool VIC 3280",
    "addr:housenumber":"5",
    "addr:postcode":"3280",
    "addr:street":"Bailey Crs",
    "iso:country":"AU",
    "sg:address":"5 Bailey Crs",
    "sg:city":"Warrnambool",
    "sg:classifiers":[
        {
            "category":"Home & Garden",
            "subcategory":"Carpets & Floor Coverings",
            "type":"Retail Goods"
        }
    ],
    "sg:phone":"+61 419 372 773",
    "sg:postcode":"3280",
    "sg:province":"VIC",
    "sg:tags":[
        "tile",
        "wall",
        "layer"
    ],
    "wof:name":"Morris Tiling",
    "wof:placetype":"venue"
},
  "geometry": {"coordinates":[142.50216674800001,-38.3887519836],"type":"Point"}
}