{
  "type": "Feature",
  "properties": {
    "addr:full":"5 King St Shepparton VIC 3630",
    "addr:housenumber":"5",
    "addr:postcode":"3630",
    "addr:street":"King St",
    "iso:country":"AU",
    "sg:address":"5 King St",
    "sg:city":"Shepparton",
    "sg:classifiers":[
        {
            "category":"Retail",
            "subcategory":"Car Wash",
            "type":"Services"
        }
    ],
    "sg:phone":"+61 418 579 040",
    "sg:postcode":"3630",
    "sg:province":"VIC",
    "sg:tags":[
        "truck",
        "cleaning"
    ],
    "wof:name":"Cassidys Garry Carpet Care",
    "wof:placetype":"venue"
},
  "geometry": {"coordinates":[145.399124145,-36.3668556213],"type":"Point"}
}