{
  "type": "Feature",
  "properties": {
    "iso:country":"AU",
    "sg:address":"72 Kermode St",
    "sg:city":"North Adelaide",
    "sg:classifiers":[
        {
            "category":"Real Estate",
            "subcategory":"Architect",
            "type":"Services"
        }
    ],
    "sg:phone":"+61 8 8267 1144",
    "sg:postcode":"5006",
    "sg:province":"SA",
    "sg:tags":[
        "building",
        "designer"
    ],
    "wof:name":"George Majda & Associates",
    "wof:placetype":"venue"
},
  "geometry": {"coordinates":[138.59863281200001,-34.9117355347],"type":"Point"}
}