{
  "type": "Feature",
  "properties": {
    "addr:full":"101 Gulf Point Drv North Haven SA 5018",
    "addr:housenumber":"101",
    "addr:postcode":"5018",
    "addr:street":"Gulf Point Drv",
    "iso:country":"AU",
    "sg:address":"101 Gulf Point Drv",
    "sg:city":"North Haven",
    "sg:classifiers":[
        {
            "category":"Real Estate",
            "subcategory":"Architect",
            "type":"Services"
        }
    ],
    "sg:phone":"+61 417 817 730",
    "sg:postcode":"5018",
    "sg:province":"SA",
    "wof:name":"Snowden Associates",
    "wof:placetype":"venue"
},
  "geometry": {"coordinates":[138.483642578,-34.7858161926],"type":"Point"}
}