{
  "type": "Feature",
  "properties": {
    "addr:full":"67 High St Cranbourne VIC 3977",
    "addr:housenumber":"67",
    "addr:postcode":"3977",
    "addr:street":"High St",
    "iso:country":"AU",
    "sg:address":"67 High St",
    "sg:city":"Cranbourne",
    "sg:classifiers":[
        {
            "category":"Personal",
            "subcategory":"Beauty Salon",
            "type":"Services"
        }
    ],
    "sg:phone":"+61 3 5995 5555",
    "sg:postcode":"3977",
    "sg:province":"VIC",
    "sg:tags":[
        "hairdresser"
    ],
    "wof:name":"The Hair Shaq",
    "wof:placetype":"venue"
},
  "geometry": {"coordinates":[145.28286743199999,-38.1114463806],"type":"Point"}
}