{
  "type": "Feature",
  "properties": {
    "iso:country":"AU",
    "sg:address":"490 Arthurs Seat Rd",
    "sg:city":"Red Hill",
    "sg:classifiers":[
        {
            "category":"Retail",
            "subcategory":"Auto Repair",
            "type":"Services"
        }
    ],
    "sg:phone":"+61 3 5989 2286",
    "sg:postcode":"3937",
    "sg:province":"VIC",
    "sg:tags":[
        "repairer",
        "motor",
        "engineer"
    ],
    "wof:name":"Euromech",
    "wof:placetype":"venue"
},
  "geometry": {"coordinates":[144.98043823200001,-38.3625679016],"type":"Point"}
}