{
  "type": "Feature",
  "properties": {
    "iso:country":"AU",
    "sg:address":"645 Deptford Rd",
    "sg:city":"Clifton Creek",
    "sg:classifiers":[
        {
            "category":"Manufacturing",
            "subcategory":"Buildings",
            "type":"Manufacturing & Wholesale Goods"
        }
    ],
    "sg:phone":"+61 3 5157 9339",
    "sg:postcode":"3875",
    "sg:province":"VIC",
    "sg:tags":[
        "transportable",
        "domestic",
        "relocatable"
    ],
    "wof:name":"Clifton Mobile Homes Pty.Ltd",
    "wof:placetype":"venue"
},
  "geometry": {"coordinates":[147.66241455100001,-37.7355422974],"type":"Point"}
}