{
  "type": "Feature",
  "properties": {
    "iso:country":"AU",
    "sg:address":"30 Church St",
    "sg:city":"Whittlesea",
    "sg:classifiers":[
        {
            "category":"Retail",
            "subcategory":"Funeral Services",
            "type":"Services"
        }
    ],
    "sg:phone":"+61 3 9716 3443",
    "sg:postcode":"3757",
    "sg:province":"VIC",
    "sg:tags":[
        "director"
    ],
    "wof:name":"Glen Funerals Pty Ltd",
    "wof:placetype":"venue"
},
  "geometry": {"coordinates":[145.118027,-37.513008],"type":"Point"}
}