{
  "type": "Feature",
  "properties": {
    "addr:full":"33 Fitzgerald Rd Laverton North VIC 3026",
    "addr:housenumber":"33",
    "addr:postcode":"3026",
    "addr:street":"Fitzgerald Rd",
    "iso:country":"AU",
    "sg:address":"33 Fitzgerald Rd",
    "sg:city":"Laverton North",
    "sg:classifiers":[
        {
            "category":"Building & Trades",
            "subcategory":"Construction",
            "type":"Services"
        }
    ],
    "sg:phone":"+61 1800 199 450",
    "sg:postcode":"3026",
    "sg:province":"VIC",
    "sg:tags":[
        "fencing",
        "contractor"
    ],
    "wof:name":"Smorgon Steel Group Ltd",
    "wof:placetype":"venue"
},
  "geometry": {"coordinates":[144.78654499999999,-37.822041],"type":"Point"}
}