{
  "type": "Feature",
  "properties": {
    "addr:full":"351 Seaview Rd Henley Beach SA 5022",
    "addr:housenumber":"351",
    "addr:postcode":"5022",
    "addr:street":"Seaview Rd",
    "iso:country":"AU",
    "sg:address":"351 Seaview Rd",
    "sg:city":"Henley Beach",
    "sg:classifiers":[
        {
            "category":"Banks & Credit Unions",
            "subcategory":"Investment Brokerage",
            "type":"Services"
        }
    ],
    "sg:phone":"+61 8 8378 1601",
    "sg:postcode":"5022",
    "sg:province":"SA",
    "sg:tags":[
        "management",
        "property"
    ],
    "wof:name":"Duffield Mutton & Associates Pty Ltd",
    "wof:placetype":"venue"
},
  "geometry": {"coordinates":[138.49517822300001,-34.9219551086],"type":"Point"}
}