{
  "type": "Feature",
  "properties": {
    "addr:full":"777 Main St Kangaroo Point QLD 4169",
    "addr:housenumber":"777",
    "addr:postcode":"4169",
    "addr:street":"Main St",
    "iso:country":"AU",
    "sg:address":"777 Main St",
    "sg:city":"Kangaroo Point",
    "sg:classifiers":[
        {
            "category":"Travel",
            "subcategory":"Hotels & Motels",
            "type":"Entertainment"
        }
    ],
    "sg:phone":"+61 7 3391 1061",
    "sg:postcode":"4169",
    "sg:province":"QLD",
    "wof:name":"Queensland Motel",
    "wof:placetype":"venue"
},
  "geometry": {"coordinates":[153.035690308,-27.4830513],"type":"Point"}
}