{
  "type": "Feature",
  "properties": {
    "addr:full":"Highpoint S/C, Shp 3134 Rosamond Rd Maribyrnong VIC 3032",
    "addr:housenumber":"3134",
    "addr:postcode":"3032",
    "addr:street":"Highpoint S /;Rosamond Rd",
    "iso:country":"AU",
    "sg:address":"Highpoint S/C, Shp 3134 Rosamond Rd",
    "sg:city":"Maribyrnong",
    "sg:classifiers":[
        {
            "category":"Social Services",
            "subcategory":"Child Care",
            "type":"Services"
        }
    ],
    "sg:phone":"+61 3 9317 4442",
    "sg:postcode":"3032",
    "sg:province":"VIC",
    "wof:name":"Munchkinland",
    "wof:placetype":"venue"
},
  "geometry": {"coordinates":[144.883835,-37.784706],"type":"Point"}
}