{
  "type": "Feature",
  "properties": {
    "iso:country":"AU",
    "sg:address":"251 Benetook Ave",
    "sg:city":"Mildura",
    "sg:classifiers":[
        {
            "category":"Wholesale",
            "subcategory":"Furniture",
            "type":"Manufacturing & Wholesale Goods"
        }
    ],
    "sg:phone":"+61 3 5023 3072",
    "sg:postcode":"3500",
    "sg:province":"VIC",
    "sg:tags":[
        "metal"
    ],
    "wof:name":"Noyce Tubular Design Furniture",
    "wof:placetype":"venue"
},
  "geometry": {"coordinates":[142.18145751899999,-34.195110321],"type":"Point"}
}