{
  "type": "Feature",
  "properties": {
    "iso:country":"AU",
    "sg:address":"14 Grandview Crt",
    "sg:city":"Camp Mountain",
    "sg:classifiers":[
        {
            "category":"Manufacturing",
            "subcategory":"Metals",
            "type":"Manufacturing & Wholesale Goods"
        }
    ],
    "sg:phone":"+61 7 3289 1151",
    "sg:postcode":"4520",
    "sg:province":"QLD",
    "sg:tags":[
        "coppersmith"
    ],
    "wof:name":"Sheetmetal &#034;n&#034; Stoves",
    "wof:placetype":"venue"
},
  "geometry": {"coordinates":[152.884003,-27.39517],"type":"Point"}
}