{
  "type": "Feature",
  "properties": {
    "addr:full":"Cnr Kingsholme and Tilbrook Streets, Teneriffe, Queensland 4005 Teneriffe QLD 4005",
    "addr:postcode":"4005;4005",
    "addr:street":"Cnr;Streets",
    "iso:country":"AU",
    "sg:address":"Cnr Kingsholme and Tilbrook Streets, Teneriffe, Queensland 4005",
    "sg:city":"Teneriffe",
    "sg:classifiers":[
        {
            "category":"Professional",
            "subcategory":"Computer Services",
            "type":"Services"
        }
    ],
    "sg:phone":"+61 7 3358 8838",
    "sg:postcode":"4005",
    "sg:province":"QLD",
    "sg:tags":[
        "package",
        "software"
    ],
    "wof:name":"Creative Designer Software Pty Ltd",
    "wof:placetype":"venue"
},
  "geometry": {"coordinates":[153.049224853,-27.4616012573],"type":"Point"}
}