{
  "type": "Feature",
  "properties": {
    "addr:full":"53 Wright St Highgate WA 6003",
    "addr:housenumber":"53",
    "addr:postcode":"6003",
    "addr:street":"Wright St",
    "iso:country":"AU",
    "sg:address":"53 Wright St",
    "sg:city":"Highgate",
    "sg:classifiers":[
        {
            "category":"Building & Trades",
            "subcategory":"Construction",
            "type":"Services"
        }
    ],
    "sg:phone":"+61 8 9227 5771",
    "sg:postcode":"6003",
    "sg:province":"WA",
    "sg:tags":[
        "renovation",
        "alterations",
        "extension",
        "contractor"
    ],
    "wof:name":"Linkpin Constructions",
    "wof:placetype":"venue"
},
  "geometry": {"coordinates":[115.872581482,-31.9419441223],"type":"Point"}
}