{
  "type": "Feature",
  "properties": {
    "addr:full":"206 Alison Rd Randwick NSW 2031",
    "addr:housenumber":"206",
    "addr:postcode":"2031",
    "addr:street":"Alison Rd",
    "iso:country":"AU",
    "sg:address":"206 Alison Rd",
    "sg:city":"Randwick",
    "sg:classifiers":[
        {
            "category":"Professional",
            "subcategory":"Computer Services",
            "type":"Services"
        }
    ],
    "sg:phone":"+61 2 9314 6441",
    "sg:postcode":"2031",
    "sg:province":"NSW",
    "sg:tags":[
        "consultant",
        "system"
    ],
    "wof:name":"Artificial Intelligence Systems Pty Ltd",
    "wof:placetype":"venue"
},
  "geometry": {"coordinates":[151.24232482900001,-33.913066864],"type":"Point"}
}