{
  "type": "Feature",
  "properties": {
    "addr:full":"PO Box 273 Mullumbimby NSW 2482",
    "addr:postcode":"2482",
    "iso:country":"AU",
    "sg:address":"PO Box 273",
    "sg:city":"Mullumbimby",
    "sg:classifiers":[
        {
            "category":"Home & Garden",
            "subcategory":"Building Materials",
            "type":"Retail Goods"
        }
    ],
    "sg:phone":"+61 418 661 145",
    "sg:postcode":"2482",
    "sg:province":"NSW",
    "sg:tags":[
        "retaining",
        "wall"
    ],
    "wof:name":"Brad Turk",
    "wof:placetype":"venue"
},
  "geometry": {"coordinates":[153.49993896500001,-28.5531997681],"type":"Point"}
}