{
  "type": "Feature",
  "properties": {
    "addr:full":"2/ 89 Hobart Rd Kings Meadows TAS 7249",
    "addr:housenumber":"/ 89",
    "addr:postcode":"7249",
    "addr:street":"Hobart Rd",
    "iso:country":"AU",
    "sg:address":"2/ 89 Hobart Rd",
    "sg:city":"Kings Meadows",
    "sg:classifiers":[
        {
            "category":"Fast Food",
            "type":"Food & Drink"
        }
    ],
    "sg:phone":"+61 3 6343 0599",
    "sg:postcode":"7249",
    "sg:province":"TAS",
    "sg:tags":[
        "away",
        "take"
    ],
    "wof:name":"Meadows Fish & Chips Takeaway",
    "wof:placetype":"venue"
},
  "geometry": {"coordinates":[147.15858459500001,-41.464176178],"type":"Point"}
}