{
  "type": "Feature",
  "properties": {
    "iso:country":"AU",
    "sg:address":"94 Lewis Rd",
    "sg:city":"Wantirna South",
    "sg:classifiers":[
        {
            "category":"Shopping",
            "subcategory":"Party Supplies",
            "type":"Retail Goods"
        }
    ],
    "sg:phone":"+61 3 8805 4333",
    "sg:postcode":"3152",
    "sg:province":"VIC",
    "sg:tags":[
        "children's"
    ],
    "wof:name":"A. Action Event Services",
    "wof:placetype":"venue"
},
  "geometry": {"coordinates":[145.25126648,-37.8662376404],"type":"Point"}
}