{
  "type": "Feature",
  "properties": {
    "iso:country":"AU",
    "sg:address":"1 De Witt St",
    "sg:city":"Battery Point",
    "sg:classifiers":[
        {
            "category":"Health Services",
            "subcategory":"Doctor",
            "type":"Services"
        }
    ],
    "sg:phone":"+61 3 6234 9511",
    "sg:postcode":"7004",
    "sg:province":"TAS",
    "sg:tags":[
        "medical",
        "practitioner"
    ],
    "wof:name":"Crawford Ian",
    "wof:placetype":"venue"
},
  "geometry": {"coordinates":[147.332595825,-42.8898429871],"type":"Point"}
}