{
  "type": "Feature",
  "properties": {
    "iso:country":"AU",
    "sg:address":"Young Rd",
    "sg:city":"Temora",
    "sg:classifiers":[
        {
            "category":"Farming",
            "subcategory":"Farm",
            "type":"Manufacturing & Wholesale Goods"
        }
    ],
    "sg:phone":"+61 2 6973 9440",
    "sg:postcode":"2666",
    "sg:province":"NSW",
    "sg:tags":[
        "farmer"
    ],
    "wof:name":"Southwell I K",
    "wof:placetype":"venue"
},
  "geometry": {"coordinates":[147.54591369600001,-34.4432487488],"type":"Point"}
}