{
  "type": "Feature",
  "properties": {
    "iso:country":"AU",
    "sg:address":"55 Handford Rd",
    "sg:city":"Zillmere",
    "sg:classifiers":[
        {
            "category":"Health Services",
            "subcategory":"Doctor",
            "type":"Services"
        }
    ],
    "sg:phone":"+61 7 3865 3832",
    "sg:postcode":"4034",
    "sg:province":"QLD",
    "sg:tags":[
        "medical",
        "practitioner"
    ],
    "wof:name":"Maher M & M",
    "wof:placetype":"venue"
},
  "geometry": {"coordinates":[153.038605,-27.357864],"type":"Point"}
}