{
  "type": "Feature",
  "properties": {
    "addr:full":"37 Coolibah Crt Mt Crosby QLD 4306",
    "addr:housenumber":"37",
    "addr:postcode":"4306",
    "addr:street":"Coolibah Crt",
    "iso:country":"AU",
    "sg:address":"37 Coolibah Crt",
    "sg:city":"Mt Crosby",
    "sg:classifiers":[
        {
            "category":"Professional",
            "subcategory":"Detective & Security Services",
            "type":"Services"
        }
    ],
    "sg:phone":"+61 7 3201 1343",
    "sg:postcode":"4306",
    "sg:province":"QLD",
    "sg:tags":[
        "equipment",
        "window",
        "doors"
    ],
    "wof:name":"Easy Close",
    "wof:placetype":"venue"
},
  "geometry": {"coordinates":[152.816604614,-27.5250511169],"type":"Point"}
}