{
  "type": "Feature",
  "properties": {
    "addr:full":"51 Railway St Lowood QLD 4311",
    "addr:housenumber":"51",
    "addr:postcode":"4311",
    "addr:street":"Railway St",
    "iso:country":"AU",
    "sg:address":"51 Railway St",
    "sg:city":"Lowood",
    "sg:classifiers":[
        {
            "category":"Autos & Motor Vehicles",
            "subcategory":"Auto Supplies",
            "type":"Retail Goods"
        }
    ],
    "sg:phone":"+61 7 5426 1711",
    "sg:postcode":"4311",
    "sg:province":"QLD",
    "sg:tags":[
        "tyre"
    ],
    "wof:name":"Yokohama",
    "wof:placetype":"venue"
},
  "geometry": {"coordinates":[152.583984375,-27.4653015137],"type":"Point"}
}