{
  "type": "Feature",
  "properties": {
    "iso:country":"AU",
    "sg:address":"Level 14, 207 Murray St",
    "sg:city":"Perth",
    "sg:classifiers":[
        {
            "category":"Education",
            "subcategory":"University",
            "type":"Public Place"
        }
    ],
    "sg:phone":"+61 8 9322 1919",
    "sg:postcode":"6000",
    "sg:province":"WA",
    "sg:tags":[
        "college",
        "tertiary"
    ],
    "wof:name":"Perth School Western Australia",
    "wof:placetype":"venue"
},
  "geometry": {"coordinates":[115.8543396,-31.9515380859],"type":"Point"}
}