{
  "type": "Feature",
  "properties": {
    "addr:full":"R7/ 3 The Piazza Homebush Bay NSW 2127",
    "addr:housenumber":"/ 3",
    "addr:postcode":"2127",
    "addr:street":"The Piazza Homebush",
    "iso:country":"AU",
    "sg:address":"R7/ 3 The Piazza",
    "sg:city":"Homebush Bay",
    "sg:classifiers":[
        {
            "category":"Health Services",
            "subcategory":"Doctor",
            "type":"Services"
        }
    ],
    "sg:phone":"+61 2 9739 8828",
    "sg:postcode":"2127",
    "sg:province":"NSW",
    "sg:tags":[
        "medical",
        "practitioner"
    ],
    "wof:name":"Lem Amelia Dr",
    "wof:placetype":"venue"
},
  "geometry": {"coordinates":[151.073486328,-33.8322982788],"type":"Point"}
}