{
  "type": "Feature",
  "properties": {
    "iso:country":"AU",
    "sg:address":"1/4 Watson Rd",
    "sg:city":"Padstow",
    "sg:classifiers":[
        {
            "category":"Retail",
            "subcategory":"Auto Repair",
            "type":"Services"
        }
    ],
    "sg:phone":"+61 2 9773 9416",
    "sg:postcode":"2211",
    "sg:province":"NSW",
    "sg:tags":[
        "repairer",
        "motor",
        "engineer"
    ],
    "wof:name":"Padstow Auto Care Centre",
    "wof:placetype":"venue"
},
  "geometry": {"coordinates":[151.034943,-33.94474],"type":"Point"}
}