{
  "type": "Feature",
  "properties": {
    "addr:full":"Shp3/ 84 Burnett St Buderim QLD 4556",
    "addr:housenumber":"84",
    "addr:postcode":"4556",
    "addr:street":"Burnett St",
    "iso:country":"AU",
    "sg:address":"Shp3/ 84 Burnett St",
    "sg:city":"Buderim",
    "sg:classifiers":[
        {
            "category":"Restaurant",
            "type":"Food & Drink"
        }
    ],
    "sg:phone":"+61 7 5445 3003",
    "sg:postcode":"4556",
    "sg:province":"QLD",
    "wof:name":"Chilli Charlies Cafe",
    "wof:placetype":"venue"
},
  "geometry": {"coordinates":[153.04838562,-26.6878051758],"type":"Point"}
}