{
  "type": "Feature",
  "properties": {
    "addr:full":"North Sydney Shopng World, 79-81 Berry St North Sydney NSW 2060",
    "addr:housenumber":"79-81",
    "addr:postcode":"2060",
    "addr:street":"Berry St",
    "iso:country":"AU",
    "sg:address":"North Sydney Shopng World, 79-81 Berry St",
    "sg:city":"North Sydney",
    "sg:classifiers":[
        {
            "category":"Shopping",
            "subcategory":"Mobile Phones",
            "type":"Retail Goods"
        }
    ],
    "sg:phone":"+61 2 9955 7111",
    "sg:postcode":"2060",
    "sg:province":"NSW",
    "sg:tags":[
        "telephone",
        "accessory"
    ],
    "wof:name":"Telstra Shop",
    "wof:placetype":"venue"
},
  "geometry": {"coordinates":[151.20933532699999,-33.8369903564],"type":"Point"}
}