{
  "type": "Feature",
  "properties": {
    "addr:full":"636 Parramatta Rd Croydon NSW 2132",
    "addr:housenumber":"636",
    "addr:postcode":"2132",
    "addr:street":"Parramatta Rd",
    "iso:country":"AU",
    "sg:address":"636 Parramatta Rd",
    "sg:city":"Croydon",
    "sg:classifiers":[
        {
            "category":"Retail",
            "subcategory":"Car Wash",
            "type":"Services"
        }
    ],
    "sg:phone":"+61 2 9798 9009",
    "sg:postcode":"2132",
    "sg:province":"NSW",
    "sg:tags":[
        "truck",
        "cleaning"
    ],
    "wof:name":"Ulltra Experts",
    "wof:placetype":"venue"
},
  "geometry": {"coordinates":[151.12109375,-33.8713150024],"type":"Point"}
}