{
  "type": "Feature",
  "properties": {
    "addr:full":"101 Old Maryborough Rd Pialba QLD 4655",
    "addr:housenumber":"101",
    "addr:postcode":"4655",
    "addr:street":"Old Maryborough Rd",
    "iso:country":"AU",
    "sg:address":"101 Old Maryborough Rd",
    "sg:city":"Pialba",
    "sg:classifiers":[
        {
            "category":"Retail",
            "subcategory":"Storage",
            "type":"Services"
        }
    ],
    "sg:phone":"+61 7 4128 6354",
    "sg:postcode":"4655",
    "sg:province":"QLD",
    "sg:tags":[
        "removal",
        "furniture"
    ],
    "wof:name":"Hervey Bay Rent-A-Box",
    "wof:placetype":"venue"
},
  "geometry": {"coordinates":[152.830139,-25.283262],"type":"Point"}
}