{
  "type": "Feature",
  "properties": {
    "iso:country":"AU",
    "sg:address":"671 Gympie Rd",
    "sg:city":"Chermside",
    "sg:classifiers":[
        {
            "category":"Health Services",
            "subcategory":"Doctor",
            "type":"Services"
        }
    ],
    "sg:phone":"+61 7 3359 7177",
    "sg:postcode":"4032",
    "sg:province":"QLD",
    "sg:tags":[
        "medical",
        "practitioner"
    ],
    "wof:name":"Queensland Diagnostic Imaging",
    "wof:placetype":"venue"
},
  "geometry": {"coordinates":[153.031601,-27.391348],"type":"Point"}
}