{
  "type": "Feature",
  "properties": {
    "iso:country":"AU",
    "sg:address":"26- 30 Railway St",
    "sg:city":"Woy Woy",
    "sg:classifiers":[
        {
            "category":"Health Services",
            "subcategory":"Doctor",
            "type":"Services"
        }
    ],
    "sg:phone":"+61 2 4344 4466",
    "sg:postcode":"2256",
    "sg:province":"NSW",
    "sg:tags":[
        "medical",
        "practitioner"
    ],
    "wof:name":"Sumar N",
    "wof:placetype":"venue"
},
  "geometry": {"coordinates":[151.303588867,-33.4979019165],"type":"Point"}
}