{
  "type": "Feature",
  "properties": {
    "iso:country":"AU",
    "sg:address":"7 Exton St",
    "sg:city":"North Lismore",
    "sg:classifiers":[
        {
            "category":"Retail",
            "subcategory":"Auto Repair",
            "type":"Services"
        }
    ],
    "sg:phone":"+61 2 6622 7773",
    "sg:postcode":"2480",
    "sg:province":"NSW",
    "sg:tags":[
        "repairer",
        "motor",
        "engineer"
    ],
    "wof:name":"Wilspeed Automotive Repairs",
    "wof:placetype":"venue"
},
  "geometry": {"coordinates":[153.27540588400001,-28.8017616272],"type":"Point"}
}