{
  "type": "Feature",
  "properties": {
    "addr:full":"Shop 2 & 3, 529- 539 New Canterbery Rd Dulwich Hill NSW 2203",
    "addr:housenumber":"shop 2 & 3",
    "addr:postcode":"529 539;2203",
    "addr:street":"New Canterbery Rd",
    "iso:country":"AU",
    "sg:address":"Shop 2 & 3, 529- 539 New Canterbery Rd",
    "sg:city":"Dulwich Hill",
    "sg:classifiers":[
        {
            "category":"Health Services",
            "subcategory":"Doctor",
            "type":"Services"
        }
    ],
    "sg:phone":"+61 2 9560 2088",
    "sg:postcode":"2203",
    "sg:province":"NSW",
    "sg:tags":[
        "medical",
        "practitioner"
    ],
    "wof:name":"Joseph Ehab Dr",
    "wof:placetype":"venue"
},
  "geometry": {"coordinates":[151.13940400000001,-33.904327],"type":"Point"}
}