{
  "type": "Feature",
  "properties": {
    "addr:full":"553 Whitehorse Rd Mitcham VIC 3132",
    "addr:housenumber":"553",
    "addr:postcode":"3132",
    "addr:street":"Whitehorse Rd",
    "iso:country":"AU",
    "sg:address":"553 Whitehorse Rd",
    "sg:city":"Mitcham",
    "sg:phone":"+61 3 9872 3600",
    "sg:postcode":"3132",
    "sg:province":"VIC",
    "wof:name":"Aquacatch Systems",
    "wof:placetype":"venue"
},
  "geometry": {"coordinates":[145.19598388700001,-37.8156814575],"type":"Point"}
}