{
  "type": "Feature",
  "properties": {
    "addr:full":"106 Crimea Rd Marsfield NSW 2122",
    "addr:housenumber":"106",
    "addr:postcode":"2122",
    "addr:street":"Crimea Rd",
    "iso:country":"AU",
    "sg:address":"106 Crimea Rd",
    "sg:city":"Marsfield",
    "sg:classifiers":[
        {
            "category":"Shopping",
            "subcategory":"Bridal",
            "type":"Retail Goods"
        }
    ],
    "sg:phone":"+61 407 184 886",
    "sg:postcode":"2122",
    "sg:province":"NSW",
    "sg:tags":[
        "hire",
        "wear"
    ],
    "wof:name":"Chantelle Bridal",
    "wof:placetype":"venue"
},
  "geometry": {"coordinates":[151.09986877399999,-33.7669868469],"type":"Point"}
}