{
  "type": "Feature",
  "properties": {
    "addr:full":"3/ 46 Southern Cross Cct Hervey Bay QLD 4655",
    "addr:housenumber":"/ 46",
    "addr:postcode":"4655",
    "addr:street":"Southern Cross Cct",
    "iso:country":"AU",
    "sg:address":"3/ 46 Southern Cross Cct",
    "sg:city":"Hervey Bay",
    "sg:classifiers":[
        {
            "category":"Retail",
            "subcategory":"Auto Rental",
            "type":"Services"
        }
    ],
    "sg:phone":"+61 7 4125 3633",
    "sg:postcode":"4655",
    "sg:province":"QLD",
    "sg:tags":[
        "car",
        "hire",
        "minibus"
    ],
    "wof:name":"Budget Rent A Car",
    "wof:placetype":"venue"
},
  "geometry": {"coordinates":[152.892731,-25.317932],"type":"Point"}
}