{
  "type": "Feature",
  "properties": {
    "iso:country":"AU",
    "sg:address":"47 Kenny St",
    "sg:city":"Wollongong",
    "sg:classifiers":[
        {
            "category":"Organizations",
            "subcategory":"Membership Organization",
            "type":"Services"
        }
    ],
    "sg:phone":"+61 2 4226 1163",
    "sg:postcode":"2500",
    "sg:province":"NSW",
    "sg:tags":[
        "support",
        "health",
        "organisation"
    ],
    "wof:name":"AIDS Council Of New South Wales (ACON) Illawarra Branch",
    "wof:placetype":"venue"
},
  "geometry": {"coordinates":[150.891769,-34.429501],"type":"Point"}
}