{
  "type": "Feature",
  "properties": {
    "addr:full":"17 Somerset Drv Carseldine QLD 4034",
    "addr:housenumber":"17",
    "addr:postcode":"4034",
    "addr:street":"Somerset Drv",
    "iso:country":"AU",
    "sg:address":"17 Somerset Drv",
    "sg:city":"Carseldine",
    "sg:classifiers":[
        {
            "category":"Utilities",
            "subcategory":"Electric",
            "type":"Services"
        }
    ],
    "sg:phone":"+61 7 3263 1914",
    "sg:postcode":"4034",
    "sg:province":"QLD",
    "sg:tags":[
        "electrical",
        "contractor"
    ],
    "sg:website":"http://www.jdelectrical.com.au",
    "wof:name":"JD Electrical & Communications Pty Ltd",
    "wof:placetype":"venue"
},
  "geometry": {"coordinates":[153.01591500000001,-27.338989],"type":"Point"}
}