{
  "type": "Feature",
  "properties": {
    "addr:full":"823 Botany Rd Rosebery NSW 2018",
    "addr:housenumber":"823",
    "addr:postcode":"2018",
    "addr:street":"Botany Rd",
    "iso:country":"AU",
    "sg:address":"823 Botany Rd",
    "sg:city":"Rosebery",
    "sg:classifiers":[
        {
            "category":"Home & Garden",
            "subcategory":"Building Materials",
            "type":"Retail Goods"
        }
    ],
    "sg:phone":"+61 2 9667 0244",
    "sg:postcode":"2018",
    "sg:province":"NSW",
    "sg:tags":[
        "merchant",
        "glass",
        "glazier"
    ],
    "wof:name":"Solaris Glass Blocks",
    "wof:placetype":"venue"
},
  "geometry": {"coordinates":[151.198532105,-33.9196052551],"type":"Point"}
}