{
  "type": "Feature",
  "properties": {
    "addr:full":"Level 4/ 34 Queens St Melbourne VIC 3000",
    "addr:housenumber":"/ 34",
    "addr:postcode":"3000",
    "addr:street":"Queens St",
    "iso:country":"AU",
    "sg:address":"Level 4/ 34 Queens St",
    "sg:city":"Melbourne",
    "sg:classifiers":[
        {
            "category":"Banks & Credit Unions",
            "subcategory":"Financial Services",
            "type":"Services"
        }
    ],
    "sg:phone":"+61 3 8614 1677",
    "sg:postcode":"3000",
    "sg:province":"VIC",
    "sg:tags":[
        "planning"
    ],
    "wof:name":"Money For Life - Money 101",
    "wof:placetype":"venue"
},
  "geometry": {"coordinates":[144.96226501500001,-37.8179359436],"type":"Point"}
}