{
  "type": "Feature",
  "properties": {
    "iso:country":"AU",
    "sg:address":"8 Morlyn Drv",
    "sg:city":"Mt Martha",
    "sg:classifiers":[
        {
            "category":"Building & Trades",
            "subcategory":"Construction",
            "type":"Services"
        }
    ],
    "sg:phone":"+61 3 5977 0192",
    "sg:postcode":"3934",
    "sg:province":"VIC",
    "sg:tags":[
        "earth",
        "excavating",
        "moving",
        "contractor"
    ],
    "wof:name":"Spray S W & Associates",
    "wof:placetype":"venue"
},
  "geometry": {"coordinates":[145.034225464,-38.2548904419],"type":"Point"}
}