{
  "type": "Feature",
  "properties": {
    "iso:country":"AU",
    "sg:address":"U8/ 59 King St",
    "sg:city":"Waverton",
    "sg:classifiers":[
        {
            "category":"Professional",
            "subcategory":"Computer Services",
            "type":"Services"
        }
    ],
    "sg:phone":"+61 2 8920 0866",
    "sg:postcode":"2060",
    "sg:province":"NSW",
    "sg:tags":[
        "consultant",
        "system"
    ],
    "wof:name":"MacAssist",
    "wof:placetype":"venue"
},
  "geometry": {"coordinates":[151.19758605999999,-33.8354263306],"type":"Point"}
}