{
  "type": "Feature",
  "properties": {
    "iso:country":"AU",
    "sg:address":"Suite A, 412 Bay St",
    "sg:city":"Brighton",
    "sg:classifiers":[
        {
            "category":"Personal",
            "subcategory":"Massage",
            "type":"Services"
        }
    ],
    "sg:phone":"+61 3 9596 4700",
    "sg:postcode":"3186",
    "sg:province":"VIC",
    "sg:tags":[
        "therapy"
    ],
    "wof:name":"B.M.S. Therapy",
    "wof:placetype":"venue"
},
  "geometry": {"coordinates":[145.00793457,-37.9064407349],"type":"Point"}
}