{
  "type": "Feature",
  "properties": {
    "iso:country":"AU",
    "sg:address":"92 Meurants La",
    "sg:city":"Glenwood",
    "sg:classifiers":[
        {
            "category":"Building & Trades",
            "subcategory":"Construction",
            "type":"Services"
        }
    ],
    "sg:phone":"+61 2 9831 2539",
    "sg:postcode":"2768",
    "sg:province":"NSW",
    "sg:tags":[
        "earth",
        "excavating",
        "moving",
        "contractor"
    ],
    "wof:name":"Galea P & M Plant Hire",
    "wof:placetype":"venue"
},
  "geometry": {"coordinates":[150.92823799999999,-33.738632],"type":"Point"}
}