{
  "type": "Feature",
  "properties": {
    "iso:country":"AU",
    "sg:address":"44/ 1 Halford St",
    "sg:city":"Castlemaine",
    "sg:classifiers":[
        {
            "category":"Real Estate",
            "subcategory":"Architect",
            "type":"Services"
        }
    ],
    "sg:phone":"+61 3 5470 6780",
    "sg:postcode":"3450",
    "sg:province":"VIC",
    "wof:name":"Stephen Lumb Architect",
    "wof:placetype":"venue"
},
  "geometry": {"coordinates":[144.219573975,-37.0516014099],"type":"Point"}
}