{
  "type": "Feature",
  "properties": {
    "iso:country":"AU",
    "sg:address":"Unit 9, 241 Mulgoa Rd",
    "sg:city":"Penrith",
    "sg:classifiers":[
        {
            "category":"Wholesale",
            "subcategory":"Construction Materials",
            "type":"Manufacturing & Wholesale Goods"
        }
    ],
    "sg:phone":"+61 2 4733 8051",
    "sg:postcode":"2750",
    "sg:province":"NSW",
    "sg:tags":[
        "wholesaler",
        "lighting",
        "mfrs",
        "accessory"
    ],
    "wof:name":"Lighting Centre",
    "wof:placetype":"venue"
},
  "geometry": {"coordinates":[150.67709350600001,-33.7684707642],"type":"Point"}
}