{
  "type": "Feature",
  "properties": {
    "iso:country":"AU",
    "sg:address":"12 Palmerston St",
    "sg:city":"Warragul",
    "sg:classifiers":[
        {
            "category":"Personal",
            "subcategory":"Beauty Salon",
            "type":"Services"
        }
    ],
    "sg:phone":"+61 3 5623 1795",
    "sg:postcode":"3820",
    "sg:province":"VIC",
    "sg:tags":[
        "hairdresser"
    ],
    "wof:name":"Cuts On Palmerston",
    "wof:placetype":"venue"
},
  "geometry": {"coordinates":[145.930954,-38.161533],"type":"Point"}
}