{
  "type": "Feature",
  "properties": {
    "addr:full":"9 Muntenten St Leeton NSW 2705",
    "addr:housenumber":"9",
    "addr:postcode":"2705",
    "addr:street":"Muntenten St",
    "iso:country":"AU",
    "sg:address":"9 Muntenten St",
    "sg:city":"Leeton",
    "sg:classifiers":[
        {
            "category":"Arena",
            "subcategory":"Sports Club",
            "type":"Entertainment"
        }
    ],
    "sg:phone":"+61 2 6953 2982",
    "sg:postcode":"2705",
    "sg:province":"NSW",
    "sg:tags":[
        "hunt",
        "racing"
    ],
    "wof:name":"Leeton Harness Racing Club Inc",
    "wof:placetype":"venue"
},
  "geometry": {"coordinates":[146.403076172,-34.5439834595],"type":"Point"}
}