{
  "type": "Feature",
  "properties": {
    "addr:full":"Cnr Ellsmore & Old Wingello Rds Bundanoon NSW 2578",
    "addr:postcode":"2578",
    "addr:street":"Cnr Ellsmore & Old Wingello Rds",
    "iso:country":"AU",
    "sg:address":"Cnr Ellsmore & Old Wingello Rds",
    "sg:city":"Bundanoon",
    "sg:classifiers":[
        {
            "category":"Government",
            "subcategory":"Court House",
            "type":"Public Place"
        }
    ],
    "sg:phone":"+61 2 4883 6599",
    "sg:postcode":"2578",
    "sg:province":"NSW",
    "sg:tags":[
        "personal",
        "marriage",
        "family",
        "counselling"
    ],
    "wof:name":"Petrea King",
    "wof:placetype":"venue"
},
  "geometry": {"coordinates":[150.29989624000001,-34.6553573608],"type":"Point"}
}