{
  "type": "Feature",
  "properties": {
    "addr:full":"Unit 2/ 18 Palings Crt Nerang QLD 4211",
    "addr:postcode":"4211",
    "addr:street":"18 Palings Crt",
    "iso:country":"AU",
    "sg:address":"Unit 2/ 18 Palings Crt",
    "sg:city":"Nerang",
    "sg:classifiers":[
        {
            "category":"Retail",
            "subcategory":"Repair Shop",
            "type":"Services"
        }
    ],
    "sg:phone":"+61 7 5596 4300",
    "sg:postcode":"4211",
    "sg:province":"QLD",
    "sg:tags":[
        "stove",
        "part",
        "range"
    ],
    "wof:name":"Day/Night Emergency Electrical Service",
    "wof:placetype":"venue"
},
  "geometry": {"coordinates":[153.34091186500001,-27.981470108],"type":"Point"}
}