{
  "type": "Feature",
  "properties": {
    "addr:full":"Shop 3 Redland Bay Village Cnr Broadwater Tce & Stradbroke St Redland Bay QLD 4165",
    "addr:housenumber":"shop 3",
    "addr:postcode":"4165",
    "addr:street":"Broadwater Tce & Stradbroke St",
    "iso:country":"AU",
    "sg:address":"Shop 3 Redland Bay Village Cnr Broadwater Tce & Stradbroke St",
    "sg:city":"Redland Bay",
    "sg:classifiers":[
        {
            "category":"Health Services",
            "subcategory":"Dentist",
            "type":"Services"
        }
    ],
    "sg:phone":"+61 7 3829 2299",
    "sg:postcode":"4165",
    "sg:province":"QLD",
    "wof:name":"Dr Nupur Hackwood",
    "wof:placetype":"venue"
},
  "geometry": {"coordinates":[153.296585083,-27.6128139496],"type":"Point"}
}