{
  "type": "Feature",
  "properties": {
    "addr:full":"6 Ferrier St Rockdale NSW 2216",
    "addr:housenumber":"6",
    "addr:postcode":"2216",
    "addr:street":"Ferrier St",
    "iso:country":"AU",
    "sg:address":"6 Ferrier St",
    "sg:city":"Rockdale",
    "sg:classifiers":[
        {
            "category":"Manufacturing",
            "subcategory":"Motor Vehicles & Parts",
            "type":"Manufacturing & Wholesale Goods"
        }
    ],
    "sg:phone":"+61 2 9567 4889",
    "sg:postcode":"2216",
    "sg:province":"NSW",
    "sg:tags":[
        "equipment",
        "cushion",
        "air"
    ],
    "wof:name":"Sippel & Co Pty Limited",
    "wof:placetype":"venue"
},
  "geometry": {"coordinates":[151.13484199999999,-33.950565],"type":"Point"}
}