{
  "type": "Feature",
  "properties": {
    "addr:full":"810- 834 Springvale Rd Braeside VIC 3195",
    "addr:housenumber":"810 834",
    "addr:postcode":"3195",
    "addr:street":"Springvale Rd",
    "iso:country":"AU",
    "sg:address":"810- 834 Springvale Rd",
    "sg:city":"Braeside",
    "sg:classifiers":[
        {
            "category":"Farming",
            "subcategory":"Farm & Veterinary Services",
            "type":"Manufacturing & Wholesale Goods"
        }
    ],
    "sg:phone":"+61 3 9798 2600",
    "sg:postcode":"3195",
    "sg:province":"VIC",
    "sg:tags":[
        "irrigation",
        "reticulation",
        "system"
    ],
    "wof:name":"One Stop Sprinklers",
    "wof:placetype":"venue"
},
  "geometry": {"coordinates":[145.14149475100001,-38.005569458],"type":"Point"}
}