{
  "type": "Feature",
  "properties": {
    "addr:full":"Gordan St Kulin WA 6365",
    "addr:postcode":"6365",
    "addr:street":"Gordan St",
    "iso:country":"AU",
    "sg:address":"Gordan St",
    "sg:city":"Kulin",
    "sg:classifiers":[
        {
            "category":"Education",
            "subcategory":"School",
            "type":"Public Place"
        }
    ],
    "sg:phone":"+61 8 9880 1264",
    "sg:postcode":"6365",
    "sg:province":"WA",
    "sg:tags":[
        "state",
        "except",
        "nsw"
    ],
    "wof:name":"Kulin District High School",
    "wof:placetype":"venue"
},
  "geometry": {"coordinates":[118.15432,-32.670189],"type":"Point"}
}