{
  "type": "Feature",
  "properties": {
    "addr:full":"Level 1, 190 Flinders St Adelaide SA 5000",
    "addr:housenumber":"190",
    "addr:postcode":"5000",
    "addr:street":"Flinders St",
    "iso:country":"AU",
    "sg:address":"Level 1, 190 Flinders St",
    "sg:city":"Adelaide",
    "sg:classifiers":[
        {
            "category":"Insurance",
            "subcategory":"Insurance Agent",
            "type":"Services"
        }
    ],
    "sg:phone":"+61 8 8223 1200",
    "sg:postcode":"5000",
    "sg:province":"SA",
    "sg:tags":[
        "broker"
    ],
    "wof:name":"Willis Australia Limited",
    "wof:placetype":"venue"
},
  "geometry": {"coordinates":[138.607711792,-34.9266242981],"type":"Point"}
}