{
  "type": "Feature",
  "properties": {
    "addr:full":"108 Morton Rd Ashwood VIC 3147",
    "addr:housenumber":"108",
    "addr:postcode":"3147",
    "addr:street":"Morton Rd",
    "iso:country":"AU",
    "sg:address":"108 Morton Rd",
    "sg:city":"Ashwood",
    "sg:classifiers":[
        {
            "category":"Building & Trades",
            "subcategory":"Plumbing",
            "type":"Services"
        }
    ],
    "sg:phone":"+61 418 556 905",
    "sg:postcode":"3147",
    "sg:province":"VIC",
    "sg:tags":[
        "plumber",
        "gasfitters"
    ],
    "wof:name":"John Beare",
    "wof:placetype":"venue"
},
  "geometry": {"coordinates":[145.0987854,-37.8635368347],"type":"Point"}
}