{
  "type": "Feature",
  "properties": {
    "addr:full":"Factory 3, 82- 96 Hampstead Rd Maidstone VIC 3012",
    "addr:housenumber":"82 96",
    "addr:postcode":"3012",
    "addr:street":"Hampstead Rd",
    "iso:country":"AU",
    "sg:address":"Factory 3, 82- 96 Hampstead Rd",
    "sg:city":"Maidstone",
    "sg:classifiers":[
        {
            "category":"Social Services",
            "subcategory":"Retirement Home",
            "type":"Services"
        }
    ],
    "sg:phone":"+61 3 9317 7010",
    "sg:postcode":"3012",
    "sg:province":"VIC",
    "sg:tags":[
        "t-shirt",
        "supplier"
    ],
    "wof:name":"Austrans Trading Pty Ltd",
    "wof:placetype":"venue"
},
  "geometry": {"coordinates":[144.87965393100001,-37.7761268616],"type":"Point"}
}