{
  "type": "Feature",
  "properties": {
    "addr:full":"210 Kelvin Grove Rd Kelvin Grove QLD 4059",
    "addr:housenumber":"210",
    "addr:postcode":"4059",
    "addr:street":"Kelvin Grove Rd",
    "iso:country":"AU",
    "sg:address":"210 Kelvin Grove Rd",
    "sg:city":"Kelvin Grove",
    "sg:classifiers":[
        {
            "category":"Real Estate",
            "subcategory":"Architect",
            "type":"Services"
        }
    ],
    "sg:phone":"+61 7 3856 1782",
    "sg:postcode":"4059",
    "sg:province":"QLD",
    "wof:name":"Alex Stavridis",
    "wof:placetype":"venue"
},
  "geometry": {"coordinates":[153.010864258,-27.4501628876],"type":"Point"}
}