{
  "type": "Feature",
  "properties": {
    "addr:full":"332 Goodwood Rd Clarence Park SA 5034",
    "addr:housenumber":"332",
    "addr:postcode":"5034",
    "addr:street":"Goodwood Rd",
    "iso:country":"AU",
    "sg:address":"332 Goodwood Rd",
    "sg:city":"Clarence Park",
    "sg:classifiers":[
        {
            "category":"Shopping",
            "subcategory":"Crafts & Fabrics",
            "type":"Retail Goods"
        }
    ],
    "sg:phone":"+61 8 8373 1226",
    "sg:postcode":"5034",
    "sg:province":"SA",
    "sg:tags":[
        "supply"
    ],
    "wof:name":"Quilt Cottage",
    "wof:placetype":"venue"
},
  "geometry": {"coordinates":[138.59056091299999,-34.965259552],"type":"Point"}
}