{
  "type": "Feature",
  "properties": {
    "iso:country":"AU",
    "sg:address":"Shop 2, 215 Railway Ave",
    "sg:city":"Kelmscott",
    "sg:classifiers":[
        {
            "category":"Retail",
            "subcategory":"Repair Shop",
            "type":"Services"
        }
    ],
    "sg:phone":"+61 8 9495 4935",
    "sg:postcode":"6111",
    "sg:province":"WA",
    "sg:tags":[
        "stove",
        "part",
        "range"
    ],
    "wof:name":"Kelmscott Stove & Appliance Parts",
    "wof:placetype":"venue"
},
  "geometry": {"coordinates":[116.013221741,-32.124786377],"type":"Point"}
}