{
  "type": "Feature",
  "properties": {
    "iso:country":"AU",
    "sg:address":"Nollamara Ave",
    "sg:city":"Nollamara",
    "sg:classifiers":[
        {
            "category":"Education",
            "subcategory":"School",
            "type":"Public Place"
        }
    ],
    "sg:phone":"+61 8 9349 1711",
    "sg:postcode":"6061",
    "sg:province":"WA",
    "sg:tags":[
        "state",
        "except",
        "nsw"
    ],
    "wof:name":"Mirrabooka Senior High School",
    "wof:placetype":"venue"
},
  "geometry": {"coordinates":[115.843658447,-31.880821228],"type":"Point"}
}