{
  "type": "Feature",
  "properties": {
    "iso:country":"AU",
    "sg:address":"161 Lonsdale St",
    "sg:city":"Melbourne",
    "sg:classifiers":[
        {
            "category":"Personal",
            "subcategory":"Shoe Repair & Shine",
            "type":"Services"
        }
    ],
    "sg:phone":"+61 3 9639 3655",
    "sg:postcode":"3000",
    "sg:province":"VIC",
    "sg:tags":[
        "footwear"
    ],
    "wof:name":"Lonsdale Shoe Repairs",
    "wof:placetype":"venue"
},
  "geometry": {"coordinates":[144.96751403799999,-37.8108787537],"type":"Point"}
}