{
  "type": "Feature",
  "properties": {
    "iso:country":"AU",
    "sg:address":"18 Ingham Rd",
    "sg:city":"West End",
    "sg:classifiers":[
        {
            "category":"Professional",
            "subcategory":"Business Services",
            "type":"Services"
        }
    ],
    "sg:phone":"+61 7 4771 2007",
    "sg:postcode":"4810",
    "sg:province":"QLD",
    "sg:tags":[
        "broker"
    ],
    "wof:name":"Beyond 2000 Business Brokers",
    "wof:placetype":"venue"
},
  "geometry": {"coordinates":[146.80308500000001,-19.268665],"type":"Point"}
}