{
  "type": "Feature",
  "properties": {
    "addr:full":"7 Azalea Crt Croydon VIC 3136",
    "addr:housenumber":"7",
    "addr:postcode":"3136",
    "addr:street":"Azalea Crt",
    "iso:country":"AU",
    "sg:address":"7 Azalea Crt",
    "sg:city":"Croydon",
    "sg:classifiers":[
        {
            "category":"Manufacturing",
            "subcategory":"Food",
            "type":"Manufacturing & Wholesale Goods"
        }
    ],
    "sg:phone":"+61 3 9761 5960",
    "sg:postcode":"3136",
    "sg:province":"VIC",
    "sg:tags":[
        "function",
        "catering"
    ],
    "wof:name":"KRC Spitroast Specialists",
    "wof:placetype":"venue"
},
  "geometry": {"coordinates":[145.27647399899999,-37.7838973999],"type":"Point"}
}