{
  "type": "Feature",
  "properties": {
    "iso:country":"AU",
    "sg:address":"359 Clyde St",
    "sg:city":"South Granville",
    "sg:classifiers":[
        {
            "category":"Retail",
            "subcategory":"Auto Repair",
            "type":"Services"
        }
    ],
    "sg:phone":"+61 2 9681 2585",
    "sg:postcode":"2142",
    "sg:province":"NSW",
    "sg:tags":[
        "beater",
        "painter",
        "panel"
    ],
    "wof:name":"Carlo's Body Shop",
    "wof:placetype":"venue"
},
  "geometry": {"coordinates":[151.00979614299999,-33.8627319336],"type":"Point"}
}