{
  "type": "Feature",
  "properties": {
    "iso:country":"AU",
    "sg:address":"Cnr Boorowa & Zouch Sts",
    "sg:city":"Young",
    "sg:classifiers":[
        {
            "category":"Utilities",
            "subcategory":"Fuel Oil & Lpg",
            "type":"Services"
        }
    ],
    "sg:phone":"+61 2 6382 4111",
    "sg:postcode":"2594",
    "sg:province":"NSW",
    "sg:tags":[
        "merchant"
    ],
    "wof:name":"Southwest Fuel Centre Pty Ltd",
    "wof:placetype":"venue"
},
  "geometry": {"coordinates":[148.30035400400001,-34.313911438],"type":"Point"}
}