{
  "type": "Feature",
  "properties": {
    "addr:full":"33 Russell St Vaucluse NSW 2030",
    "addr:housenumber":"33",
    "addr:postcode":"2030",
    "addr:street":"Russell St",
    "iso:country":"AU",
    "sg:address":"33 Russell St",
    "sg:city":"Vaucluse",
    "sg:classifiers":[
        {
            "category":"Health Services",
            "subcategory":"Health Practitioner",
            "type":"Services"
        }
    ],
    "sg:phone":"+61 2 9343 0422",
    "sg:postcode":"2030",
    "sg:province":"NSW",
    "sg:tags":[
        "physiotherapist"
    ],
    "wof:name":"Byrne Christine",
    "wof:placetype":"venue"
},
  "geometry": {"coordinates":[151.283126831,-33.8492164612],"type":"Point"}
}