{
  "type": "Feature",
  "properties": {
    "addr:full":"61 Bridge St Benalla VIC 3671",
    "addr:housenumber":"61",
    "addr:postcode":"3671",
    "addr:street":"Bridge St",
    "iso:country":"AU",
    "sg:address":"61 Bridge St",
    "sg:city":"Benalla",
    "sg:classifiers":[
        {
            "category":"Manufacturing",
            "subcategory":"Jewelry",
            "type":"Manufacturing & Wholesale Goods"
        }
    ],
    "sg:phone":"+61 3 5762 6150",
    "sg:postcode":"3671",
    "sg:province":"VIC",
    "sg:tags":[
        "mfrg",
        "jeweller"
    ],
    "wof:name":"Purdeys Leading Edge Jewellers",
    "wof:placetype":"venue"
},
  "geometry": {"coordinates":[145.98469499999999,-36.551334],"type":"Point"}
}