{
  "type": "Feature",
  "properties": {
    "addr:full":"29 Henderson Rd Knoxfield VIC 3180",
    "addr:housenumber":"29",
    "addr:postcode":"3180",
    "addr:street":"Henderson Rd",
    "iso:country":"AU",
    "sg:address":"29 Henderson Rd",
    "sg:city":"Knoxfield",
    "sg:classifiers":[
        {
            "category":"Autos & Motor Vehicles",
            "subcategory":"Fuel & Gas Station",
            "type":"Retail Goods"
        }
    ],
    "sg:phone":"+61 3 9763 9099",
    "sg:postcode":"3180",
    "sg:province":"VIC",
    "sg:tags":[
        "petrol",
        "marketing",
        "pump",
        "equipment"
    ],
    "wof:name":"Petro Quip Australia Pty Ltd",
    "wof:placetype":"venue"
},
  "geometry": {"coordinates":[145.248336792,-37.9036598206],"type":"Point"}
}