{
  "type": "Feature",
  "properties": {
    "addr:full":"100 Agnes St George Town TAS 7253",
    "addr:housenumber":"100",
    "addr:postcode":"7253",
    "addr:street":"Agnes St",
    "iso:country":"AU",
    "sg:address":"100 Agnes St",
    "sg:city":"George Town",
    "sg:classifiers":[
        {
            "category":"Travel",
            "subcategory":"Hotels & Motels",
            "type":"Entertainment"
        }
    ],
    "sg:phone":"+61 3 6382 1042",
    "sg:postcode":"7253",
    "sg:province":"TAS",
    "wof:name":"George Town Motor Inn",
    "wof:placetype":"venue"
},
  "geometry": {"coordinates":[146.83476257300001,-41.1067428589],"type":"Point"}
}