{
  "type": "Feature",
  "properties": {
    "addr:full":"679 Macauley St Albury NSW 2640",
    "addr:housenumber":"679",
    "addr:postcode":"2640",
    "addr:street":"Macauley St",
    "iso:country":"AU",
    "sg:address":"679 Macauley St",
    "sg:city":"Albury",
    "sg:classifiers":[
        {
            "category":"Real Estate",
            "subcategory":"Architect",
            "type":"Services"
        }
    ],
    "sg:phone":"+61 2 6021 3026",
    "sg:postcode":"2640",
    "sg:province":"NSW",
    "sg:tags":[
        "building",
        "designer"
    ],
    "wof:name":"Andrew Bentley Designs",
    "wof:placetype":"venue"
},
  "geometry": {"coordinates":[146.923828125,-36.0720252991],"type":"Point"}
}