{
  "type": "Feature",
  "properties": {
    "addr:full":"43 Plozzas Rd Haven VIC 3401",
    "addr:housenumber":"43",
    "addr:postcode":"3401",
    "addr:street":"Plozzas Rd",
    "iso:country":"AU",
    "sg:address":"43 Plozzas Rd",
    "sg:city":"Haven",
    "sg:classifiers":[
        {
            "category":"Building & Trades",
            "subcategory":"Construction",
            "type":"Services"
        }
    ],
    "sg:phone":"+61 3 5381 0106",
    "sg:postcode":"3401",
    "sg:province":"VIC",
    "sg:tags":[
        "contractor"
    ],
    "wof:name":"Wimmera Building Design & Drafting Service",
    "wof:placetype":"venue"
},
  "geometry": {"coordinates":[142.19212341299999,-36.7529983521],"type":"Point"}
}