{
  "type": "Feature",
  "properties": {
    "addr:full":"59 Wentworth St Caringbah NSW 2229",
    "addr:housenumber":"59",
    "addr:postcode":"2229",
    "addr:street":"Wentworth St",
    "iso:country":"AU",
    "sg:address":"59 Wentworth St",
    "sg:city":"Caringbah",
    "sg:classifiers":[
        {
            "category":"Utilities",
            "subcategory":"Electric",
            "type":"Services"
        }
    ],
    "sg:phone":"+61 2 9525 0707",
    "sg:postcode":"2229",
    "sg:province":"NSW",
    "sg:tags":[
        "electrical",
        "contractor"
    ],
    "wof:name":"M. & S.K. Electrics Pty Ltd",
    "wof:placetype":"venue"
},
  "geometry": {"coordinates":[151.12147522000001,-34.0587615967],"type":"Point"}
}