{
  "type": "Feature",
  "properties": {
    "addr:full":"Unit 1 1644 Ferntree Gully Rd Knoxfield VIC 3180",
    "addr:housenumber":"1644",
    "addr:postcode":"3180",
    "addr:street":"Ferntree Gully Rd",
    "iso:country":"AU",
    "sg:address":"Unit 1 1644 Ferntree Gully Rd",
    "sg:city":"Knoxfield",
    "sg:classifiers":[
        {
            "category":"Government",
            "subcategory":"Fire Station",
            "type":"Public Place"
        }
    ],
    "sg:phone":"+61 3 9763 7099",
    "sg:postcode":"3180",
    "sg:province":"VIC",
    "sg:tags":[
        "equipment",
        "protection",
        "consultant"
    ],
    "wof:name":"Firespray Pty Ltd",
    "wof:placetype":"venue"
},
  "geometry": {"coordinates":[145.25650024399999,-37.8927726746],"type":"Point"}
}