{
  "type": "Feature",
  "properties": {
    "addr:full":"160 Roma St Brisbane QLD 4000",
    "addr:postcode":"160;4000",
    "addr:street":"Roma St",
    "iso:country":"AU",
    "sg:address":"160 Roma St",
    "sg:city":"Brisbane",
    "sg:classifiers":[
        {
            "category":"Cafe",
            "type":"Food & Drink"
        }
    ],
    "sg:phone":"+61 7 3236 1090",
    "sg:postcode":"4000",
    "sg:province":"QLD",
    "wof:name":"Chez Nous Gourmet Sidewalk Cafe",
    "wof:placetype":"venue"
},
  "geometry": {"coordinates":[153.019073486,-27.4667396545],"type":"Point"}
}