{
  "type": "Feature",
  "properties": {
    "iso:country":"AU",
    "sg:address":"46 Scotchmer St",
    "sg:city":"Fitzroy",
    "sg:classifiers":[
        {
            "category":"Arts & Performance",
            "subcategory":"Music",
            "type":"Entertainment"
        }
    ],
    "sg:phone":"+61 403 485 055",
    "sg:postcode":"3065",
    "sg:province":"VIC",
    "sg:tags":[
        "mobile",
        "jockey",
        "disc"
    ],
    "wof:name":"Rouff Kutt",
    "wof:placetype":"venue"
},
  "geometry": {"coordinates":[144.979934692,-37.7829933167],"type":"Point"}
}