{
  "type": "Feature",
  "properties": {
    "iso:country":"AU",
    "sg:address":"44 Nobility St",
    "sg:city":"Moolap",
    "sg:classifiers":[
        {
            "category":"Manufacturing",
            "subcategory":"Petroleum Products",
            "type":"Manufacturing & Wholesale Goods"
        }
    ],
    "sg:phone":"+61 3 5248 8956",
    "sg:postcode":"3221",
    "sg:province":"VIC",
    "sg:tags":[
        "polystyrene"
    ],
    "wof:name":"Intricut",
    "wof:placetype":"venue"
},
  "geometry": {"coordinates":[144.411545,-38.168896],"type":"Point"}
}