{
  "type": "Feature",
  "properties": {
    "addr:full":"PO Box 89 Runaway Bay QLD 4216",
    "addr:postcode":"4216",
    "iso:country":"AU",
    "sg:address":"PO Box 89",
    "sg:city":"Runaway Bay",
    "sg:classifiers":[
        {
            "category":"Professional",
            "subcategory":"Detective & Security Services",
            "type":"Services"
        }
    ],
    "sg:phone":"+61 414 444 091",
    "sg:postcode":"4216",
    "sg:province":"QLD",
    "sg:tags":[
        "consultant",
        "system"
    ],
    "wof:name":"Coomera Security",
    "wof:placetype":"venue"
},
  "geometry": {"coordinates":[153.403930664,-27.9242191315],"type":"Point"}
}