{
  "type": "Feature",
  "properties": {
    "addr:full":"46 Fontenay Rd North Ryde NSW 2113",
    "addr:postcode":"2113",
    "addr:street":"Fontenay Rd",
    "iso:country":"AU",
    "sg:address":"46 Fontenay Rd",
    "sg:city":"North Ryde",
    "sg:classifiers":[
        {
            "category":"Government",
            "subcategory":"Fire Station",
            "type":"Public Place"
        }
    ],
    "sg:phone":"+61 2 9805 1046",
    "sg:postcode":"2113",
    "sg:province":"NSW",
    "sg:tags":[
        "equipment",
        "protection",
        "consultant"
    ],
    "wof:name":"Pirie Technics Pty Ltd",
    "wof:placetype":"venue"
},
  "geometry": {"coordinates":[151.13206481899999,-33.7781448364],"type":"Point"}
}