{
  "type": "Feature",
  "properties": {
    "addr:full":"19 Rheola St West Perth WA 6005",
    "addr:housenumber":"19",
    "addr:postcode":"6005",
    "addr:street":"Rheola St",
    "iso:country":"AU",
    "sg:address":"19 Rheola St",
    "sg:city":"West Perth",
    "sg:classifiers":[
        {
            "category":"Health Services",
            "subcategory":"Doctor",
            "type":"Services"
        }
    ],
    "sg:phone":"+61 8 9485 0688",
    "sg:postcode":"6005",
    "sg:province":"WA",
    "sg:tags":[
        "medical",
        "practitioner"
    ],
    "wof:name":"Monick Kerry Dr - Psychiatrist",
    "wof:placetype":"venue"
},
  "geometry": {"coordinates":[115.835289002,-31.9500389099],"type":"Point"}
}