{
  "type": "Feature",
  "properties": {
    "addr:full":"Montjoy Pde Lorne VIC 3232",
    "addr:postcode":"3232",
    "iso:country":"AU",
    "sg:address":"Montjoy Pde",
    "sg:city":"Lorne",
    "sg:classifiers":[
        {
            "category":"Organizations",
            "subcategory":"Community Association",
            "type":"Services"
        }
    ],
    "sg:phone":"+61 3 5289 1881",
    "sg:postcode":"3232",
    "sg:province":"VIC",
    "sg:tags":[
        "club",
        "senior",
        "citizen"
    ],
    "wof:name":"Winchelsea Senior Citizens Club",
    "wof:placetype":"venue"
},
  "geometry": {"coordinates":[143.97357199999999,-38.536469],"type":"Point"}
}