{
  "type": "Feature",
  "properties": {
    "iso:country":"AU",
    "sg:address":"Brightley Eaton Rd",
    "sg:city":"Miaview",
    "sg:classifiers":[
        {
            "category":"Farming",
            "subcategory":"Farm",
            "type":"Manufacturing & Wholesale Goods"
        }
    ],
    "sg:phone":"+61 7 4959 1045",
    "sg:postcode":"4740",
    "sg:province":"QLD",
    "sg:tags":[
        "farmer"
    ],
    "wof:name":"Civello J & E",
    "wof:placetype":"venue"
},
  "geometry": {"coordinates":[149.111847,-21.15519],"type":"Point"}
}