{
  "type": "Feature",
  "properties": {
    "addr:full":"Unit 1 27 Sevenoaks St Bentley WA 6102",
    "addr:housenumber":"27",
    "addr:postcode":"6102",
    "addr:street":"Sevenoaks St",
    "iso:country":"AU",
    "sg:address":"Unit 1 27 Sevenoaks St",
    "sg:city":"Bentley",
    "sg:classifiers":[
        {
            "category":"Home & Garden",
            "subcategory":"Building Materials",
            "type":"Retail Goods"
        }
    ],
    "sg:phone":"+61 8 9356 1446",
    "sg:postcode":"6102",
    "sg:province":"WA",
    "sg:tags":[
        "merchant",
        "glass",
        "glazier"
    ],
    "wof:name":"Recycled Glass",
    "wof:placetype":"venue"
},
  "geometry": {"coordinates":[115.92619323700001,-31.997800827],"type":"Point"}
}