{
  "type": "Feature",
  "properties": {
    "iso:country":"AU",
    "sg:address":"23 Young St",
    "sg:city":"St Kilda East",
    "sg:classifiers":[
        {
            "category":"Personal",
            "subcategory":"Beauty Salon",
            "type":"Services"
        }
    ],
    "sg:phone":"+61 3 9527 8809",
    "sg:postcode":"3183",
    "sg:province":"VIC",
    "sg:tags":[
        "hairdresser"
    ],
    "wof:name":"Bridget Travelling Hairdresser",
    "wof:placetype":"venue"
},
  "geometry": {"coordinates":[144.994384766,-37.8654251099],"type":"Point"}
}