{
  "type": "Feature",
  "properties": {
    "addr:full":"Shp 4-5/ 430 Prospect Rd Kilburn SA 5084",
    "addr:housenumber":"4-5 / 430",
    "addr:postcode":"5084",
    "addr:street":"Prospect Rd",
    "iso:country":"AU",
    "sg:address":"Shp 4-5/ 430 Prospect Rd",
    "sg:city":"Kilburn",
    "sg:classifiers":[
        {
            "category":"Food & Beverages",
            "subcategory":"Bakery",
            "type":"Retail Goods"
        }
    ],
    "sg:phone":"+61 8 8262 8446",
    "sg:postcode":"5084",
    "sg:province":"SA",
    "sg:tags":[
        "baker"
    ],
    "wof:name":"No. 8 Hot Bread",
    "wof:placetype":"venue"
},
  "geometry": {"coordinates":[138.592163086,-34.8616447449],"type":"Point"}
}