{
  "type": "Feature",
  "properties": {
    "iso:country":"AU",
    "sg:address":"Piccone's Shopping Village 113 Bruce Hwy",
    "sg:city":"Edmonton",
    "sg:classifiers":[
        {
            "category":"Communications",
            "subcategory":"Film & Video Production",
            "type":"Services"
        }
    ],
    "sg:phone":"+61 7 4055 4301",
    "sg:postcode":"4869",
    "sg:province":"QLD",
    "sg:tags":[
        "dvd",
        "library"
    ],
    "wof:name":"Aquarius Video",
    "wof:placetype":"venue"
},
  "geometry": {"coordinates":[145.744995117,-17.0203094482],"type":"Point"}
}