{
  "type": "Feature",
  "properties": {
    "iso:country":"AU",
    "sg:address":"9 Murrajong Rd",
    "sg:city":"Springwood",
    "sg:classifiers":[
        {
            "category":"Travel",
            "subcategory":"Hotels & Motels",
            "type":"Entertainment"
        }
    ],
    "sg:phone":"+61 7 3387 7000",
    "sg:postcode":"4127",
    "sg:province":"QLD",
    "sg:tags":[
        "accommodation"
    ],
    "sg:website":"http://www.springwoodtower.com.au",
    "wof:name":"Springwood Tower Hotel",
    "wof:placetype":"venue"
},
  "geometry": {"coordinates":[153.126785278,-27.6180419922],"type":"Point"}
}