{
  "type": "Feature",
  "properties": {
    "addr:full":"169 Macquarie St Parramatta NSW 1740",
    "addr:housenumber":"169",
    "addr:postcode":"1740",
    "addr:street":"Macquarie St",
    "iso:country":"AU",
    "sg:address":"169 Macquarie St",
    "sg:city":"Parramatta",
    "sg:classifiers":[
        {
            "category":"Utilities",
            "subcategory":"Electric",
            "type":"Services"
        }
    ],
    "sg:phone":"+61 1800 191 040",
    "sg:postcode":"1740",
    "sg:province":"NSW",
    "sg:tags":[
        "electrical",
        "contractor"
    ],
    "wof:name":"A.Ace 24Hr Electricalprompt Efficient Inexpensive Domestic & Commercial Repairs",
    "wof:placetype":"venue"
},
  "geometry": {"coordinates":[151.05711364699999,-33.9092903137],"type":"Point"}
}