{
  "type": "Feature",
  "properties": {
    "addr:full":"69 Northcote Ave Caringbah NSW 2229",
    "addr:housenumber":"69",
    "addr:postcode":"2229",
    "addr:street":"Northcote Ave",
    "iso:country":"AU",
    "sg:address":"69 Northcote Ave",
    "sg:city":"Caringbah",
    "sg:classifiers":[
        {
            "category":"Sports & Exercise",
            "subcategory":"Gym",
            "type":"Entertainment"
        }
    ],
    "sg:phone":"+61 2 9531 7231",
    "sg:postcode":"2229",
    "sg:province":"NSW",
    "sg:tags":[
        "personal",
        "trainer",
        "fitness"
    ],
    "wof:name":"Australian Personal Trainers Association Pty Ltd",
    "wof:placetype":"venue"
},
  "geometry": {"coordinates":[151.12408447300001,-34.0528106689],"type":"Point"}
}