{
  "type": "Feature",
  "properties": {
    "iso:country":"AU",
    "sg:address":"U4/ 25 Gillam Drv",
    "sg:city":"Kelmscott",
    "sg:classifiers":[
        {
            "category":"Shopping",
            "subcategory":"Books",
            "type":"Retail Goods"
        }
    ],
    "sg:phone":"+61 8 9495 4724",
    "sg:postcode":"6111",
    "sg:province":"WA",
    "sg:tags":[
        "wholesaler",
        "canvas",
        "mfrs"
    ],
    "wof:name":"Kelmscott Canvas & Trim",
    "wof:placetype":"venue"
},
  "geometry": {"coordinates":[116.007080078,-32.1281204224],"type":"Point"}
}