{
  "type": "Feature",
  "properties": {
    "iso:country":"AU",
    "sg:address":"Shops 3 & 4 120 Anderson St",
    "sg:city":"Cairns",
    "sg:classifiers":[
        {
            "category":"Building & Trades",
            "subcategory":"Plumbing",
            "type":"Services"
        }
    ],
    "sg:phone":"+61 408 773 245",
    "sg:postcode":"4870",
    "sg:province":"QLD",
    "sg:tags":[
        "plumber",
        "gasfitters"
    ],
    "wof:name":"Geck's Gas Fitting Services",
    "wof:placetype":"venue"
},
  "geometry": {"coordinates":[145.742874145,-16.91664505],"type":"Point"}
}