{
  "type": "Feature",
  "properties": {
    "addr:full":"Fcty1/ 75 Zenith Rd Dandenong South VIC 3164",
    "addr:housenumber":"75",
    "addr:postcode":"3164",
    "addr:street":"Zenith Rd",
    "iso:country":"AU",
    "sg:address":"Fcty1/ 75 Zenith Rd",
    "sg:city":"Dandenong South",
    "sg:classifiers":[
        {
            "category":"Professional",
            "subcategory":"Engineering",
            "type":"Services"
        }
    ],
    "sg:phone":"+61 3 9791 6358",
    "sg:postcode":"3164",
    "sg:province":"VIC",
    "sg:tags":[
        "installation",
        "maintenance",
        "engineer"
    ],
    "wof:name":"G T & J A Jones Engineering Pty Ltd",
    "wof:placetype":"venue"
},
  "geometry": {"coordinates":[145.223266602,-38.0202484131],"type":"Point"}
}