{
  "type": "Feature",
  "properties": {
    "addr:full":"Shp5/ 99 Bathurst St Hobart TAS 7000",
    "addr:housenumber":"99",
    "addr:postcode":"7000",
    "addr:street":"Bathurst St",
    "iso:country":"AU",
    "sg:address":"Shp5/ 99 Bathurst St",
    "sg:city":"Hobart",
    "sg:classifiers":[
        {
            "category":"Cafe",
            "type":"Food & Drink"
        }
    ],
    "sg:phone":"+61 3 6231 2819",
    "sg:postcode":"7000",
    "sg:province":"TAS",
    "wof:name":"Crisp Biscuit Cafe",
    "wof:placetype":"venue"
},
  "geometry": {"coordinates":[147.32505798299999,-42.8811073303],"type":"Point"}
}