{
  "type": "Feature",
  "properties": {
    "iso:country":"AU",
    "sg:address":"5 Ferry Rd",
    "sg:city":"Southport",
    "sg:classifiers":[
        {
            "category":"Building & Trades",
            "subcategory":"Construction",
            "type":"Services"
        }
    ],
    "sg:phone":"+61 7 5591 2766",
    "sg:postcode":"4215",
    "sg:province":"QLD",
    "sg:tags":[
        "window",
        "tinting"
    ],
    "sg:website":"http://www.cooltint.com.au",
    "wof:name":"Cooltint",
    "wof:placetype":"venue"
},
  "geometry": {"coordinates":[153.41096496599999,-27.973285675],"type":"Point"}
}