{
  "type": "Feature",
  "properties": {
    "addr:full":"Plaza Pde Maroochydore QLD 4558",
    "addr:postcode":"4558",
    "iso:country":"AU",
    "sg:address":"Plaza Pde",
    "sg:city":"Maroochydore",
    "sg:classifiers":[
        {
            "category":"Autos & Motor Vehicles",
            "subcategory":"Auto Supplies",
            "type":"Retail Goods"
        }
    ],
    "sg:phone":"+61 7 5443 2511",
    "sg:postcode":"4558",
    "sg:province":"QLD",
    "sg:tags":[
        "paint",
        "automotive"
    ],
    "wof:name":"KB Auto One",
    "wof:placetype":"venue"
},
  "geometry": {"coordinates":[153.082397461,-26.6562519073],"type":"Point"}
}