{
  "type": "Feature",
  "properties": {
    "addr:full":"Shop 2/ 140 Spit Rd Mosman NSW 2088",
    "addr:housenumber":"shop 2 / 140",
    "addr:postcode":"2088",
    "addr:street":"Spit Rd",
    "iso:country":"AU",
    "sg:address":"Shop 2/ 140 Spit Rd",
    "sg:city":"Mosman",
    "sg:classifiers":[
        {
            "category":"Retail",
            "subcategory":"Repair Shop",
            "type":"Services"
        }
    ],
    "sg:phone":"+61 2 9960 8840",
    "sg:postcode":"2088",
    "sg:province":"NSW",
    "sg:tags":[
        "upholsterer"
    ],
    "wof:name":"Mosman Upholstery",
    "wof:placetype":"venue"
},
  "geometry": {"coordinates":[151.24380493199999,-33.8184127808],"type":"Point"}
}