{
  "type": "Feature",
  "properties": {
    "iso:country":"AU",
    "sg:address":"60 Bonshor St",
    "sg:city":"Millicent",
    "sg:classifiers":[
        {
            "category":"Social Services",
            "subcategory":"Child Care",
            "type":"Services"
        }
    ],
    "sg:phone":"+61 8 8733 3030",
    "sg:postcode":"5280",
    "sg:province":"SA",
    "wof:name":"Gladys Smith Parent & Child Centre",
    "wof:placetype":"venue"
},
  "geometry": {"coordinates":[140.34463500000001,-37.601299],"type":"Point"}
}