{
  "type": "Feature",
  "properties": {
    "addr:full":"15 Orrvale Rd Shepparton VIC 3630",
    "addr:housenumber":"15",
    "addr:postcode":"3630",
    "addr:street":"Orrvale Rd",
    "iso:country":"AU",
    "sg:address":"15 Orrvale Rd",
    "sg:city":"Shepparton",
    "sg:classifiers":[
        {
            "category":"Personal",
            "type":"Services"
        }
    ],
    "sg:phone":"+61 408 570 737",
    "sg:postcode":"3630",
    "sg:province":"VIC",
    "sg:tags":[
        "wallpapering",
        "wallcovering"
    ],
    "wof:name":"Clark I.T. & P.J.",
    "wof:placetype":"venue"
},
  "geometry": {"coordinates":[145.44688415499999,-36.3938560486],"type":"Point"}
}