{
  "type": "Feature",
  "properties": {
    "addr:full":"95 Sydney St Kilmore VIC 3764",
    "addr:housenumber":"95",
    "addr:postcode":"3764",
    "addr:street":"Sydney St",
    "iso:country":"AU",
    "sg:address":"95 Sydney St",
    "sg:city":"Kilmore",
    "sg:classifiers":[
        {
            "category":"Travel",
            "subcategory":"Hotels & Motels",
            "type":"Entertainment"
        }
    ],
    "sg:phone":"+61 3 5782 1346",
    "sg:postcode":"3764",
    "sg:province":"VIC",
    "wof:name":"Wallan Motel",
    "wof:placetype":"venue"
},
  "geometry": {"coordinates":[144.94923400900001,-37.2879257202],"type":"Point"}
}