{
  "type": "Feature",
  "properties": {
    "addr:full":"10 Muskwood St Algester QLD 4115",
    "addr:housenumber":"10",
    "addr:postcode":"4115",
    "addr:street":"Muskwood St",
    "iso:country":"AU",
    "sg:address":"10 Muskwood St",
    "sg:city":"Algester",
    "sg:classifiers":[
        {
            "category":"Utilities",
            "subcategory":"Electric",
            "type":"Services"
        }
    ],
    "sg:phone":"+61 7 3273 8133",
    "sg:postcode":"4115",
    "sg:province":"QLD",
    "sg:tags":[
        "electrical",
        "contractor"
    ],
    "wof:name":"Brays Electrical Service",
    "wof:placetype":"venue"
},
  "geometry": {"coordinates":[153.034881592,-27.6129684448],"type":"Point"}
}