{
  "type": "Feature",
  "properties": {
    "addr:full":"53 Thomas St Moruya NSW 2537",
    "addr:housenumber":"53",
    "addr:postcode":"2537",
    "addr:street":"Thomas St",
    "iso:country":"AU",
    "sg:address":"53 Thomas St",
    "sg:city":"Moruya",
    "sg:classifiers":[
        {
            "category":"Building & Trades",
            "subcategory":"Construction",
            "type":"Services"
        }
    ],
    "sg:phone":"+61 2 4474 3702",
    "sg:postcode":"2537",
    "sg:province":"NSW",
    "sg:tags":[
        "waterproofing",
        "contractor"
    ],
    "wof:name":"Lavis Wayne",
    "wof:placetype":"venue"
},
  "geometry": {"coordinates":[150.07041931099999,-35.9114074707],"type":"Point"}
}