{
  "type": "Feature",
  "properties": {
    "addr:full":"27 Gresham St Adelaide SA 5000",
    "addr:housenumber":"27",
    "addr:postcode":"5000",
    "addr:street":"Gresham St",
    "iso:country":"AU",
    "sg:address":"27 Gresham St",
    "sg:city":"Adelaide",
    "sg:classifiers":[
        {
            "category":"Education",
            "subcategory":"Music School",
            "type":"Public Place"
        }
    ],
    "sg:phone":"+61 8 8212 1878",
    "sg:postcode":"5000",
    "sg:province":"SA",
    "sg:tags":[
        "choir",
        "bands",
        "orchestra"
    ],
    "wof:name":"Acoustic Juice",
    "wof:placetype":"venue"
},
  "geometry": {"coordinates":[138.5987854,-34.9228363037],"type":"Point"}
}