{
  "type": "Feature",
  "properties": {
    "addr:full":"East Victoria Park Education Support Centre 30 Beatty Ave East Victoria Park WA 6101",
    "addr:housenumber":"30",
    "addr:postcode":"6101",
    "addr:street":"Beatty Ave",
    "iso:country":"AU",
    "sg:address":"East Victoria Park Education Support Centre 30 Beatty Ave",
    "sg:city":"East Victoria Park",
    "sg:classifiers":[
        {
            "category":"Education",
            "subcategory":"School",
            "type":"Public Place"
        }
    ],
    "sg:phone":"+61 8 9470 3624",
    "sg:postcode":"6101",
    "sg:province":"WA",
    "sg:tags":[
        "state",
        "except",
        "nsw"
    ],
    "wof:name":"Schools Government (Public)",
    "wof:placetype":"venue"
},
  "geometry": {"coordinates":[115.906028748,-31.9775485992],"type":"Point"}
}