{
  "type": "Feature",
  "properties": {
    "addr:full":"2b Maple St Leeton NSW 2705",
    "addr:housenumber":"2b",
    "addr:postcode":"2705",
    "addr:street":"Maple St",
    "iso:country":"AU",
    "sg:address":"2b Maple St",
    "sg:city":"Leeton",
    "sg:classifiers":[
        {
            "category":"Home & Garden",
            "subcategory":"Garden Supply",
            "type":"Retail Goods"
        }
    ],
    "sg:phone":"+61 2 6953 3029",
    "sg:postcode":"2705",
    "sg:province":"NSW",
    "sg:tags":[
        "equipment"
    ],
    "wof:name":"Thrifty-Link Hardware",
    "wof:placetype":"venue"
},
  "geometry": {"coordinates":[146.40394592300001,-34.5502052307],"type":"Point"}
}