{
  "type": "Feature",
  "properties": {
    "addr:full":"Unit 2\\\\ 15 Halley Rd Balcatta WA 6021",
    "addr:housenumber":"15",
    "addr:postcode":"6021",
    "addr:street":"Halley Rd",
    "iso:country":"AU",
    "sg:address":"Unit 2\\\\ 15 Halley Rd",
    "sg:city":"Balcatta",
    "sg:classifiers":[
        {
            "category":"Building & Trades",
            "subcategory":"Construction",
            "type":"Services"
        }
    ],
    "sg:phone":"+61 8 9207 2933",
    "sg:postcode":"6021",
    "sg:province":"WA",
    "sg:tags":[
        "earth",
        "excavating",
        "moving",
        "contractor"
    ],
    "wof:name":"Delta Group",
    "wof:placetype":"venue"
},
  "geometry": {"coordinates":[115.824668884,-31.861782074],"type":"Point"}
}