{
  "type": "Feature",
  "properties": {
    "addr:full":"95 MacQuarie St George Town TAS 7253",
    "addr:housenumber":"95",
    "addr:postcode":"7253",
    "addr:street":"Macquarie St",
    "iso:country":"AU",
    "sg:address":"95 MacQuarie St",
    "sg:city":"George Town",
    "sg:classifiers":[
        {
            "category":"Food & Beverages",
            "subcategory":"Bakery",
            "type":"Retail Goods"
        }
    ],
    "sg:phone":"+61 3 6382 2560",
    "sg:postcode":"7253",
    "sg:province":"TAS",
    "sg:tags":[
        "baker"
    ],
    "wof:name":"The Oven Bakery",
    "wof:placetype":"venue"
},
  "geometry": {"coordinates":[146.82574462900001,-41.1061553955],"type":"Point"}
}