{
  "type": "Feature",
  "properties": {
    "addr:full":"Endeavour Valley Rd Cooktown QLD 4895",
    "addr:postcode":"4895",
    "addr:street":"Valley Rd",
    "iso:country":"AU",
    "sg:address":"Endeavour Valley Rd",
    "sg:city":"Cooktown",
    "sg:classifiers":[
        {
            "category":"Freight",
            "type":"Transportation"
        }
    ],
    "sg:phone":"+61 7 4069 5459",
    "sg:postcode":"4895",
    "sg:province":"QLD",
    "sg:tags":[
        "light",
        "carrier"
    ],
    "wof:name":"Maxwell General Carrying",
    "wof:placetype":"venue"
},
  "geometry": {"coordinates":[145.237915039,-15.4790372849],"type":"Point"}
}