{
  "type": "Feature",
  "properties": {
    "addr:full":"80 Governer Rd Mordialloc VIC 3195",
    "addr:housenumber":"80",
    "addr:postcode":"3195",
    "addr:street":"Governer Rd",
    "iso:country":"AU",
    "sg:address":"80 Governer Rd",
    "sg:city":"Mordialloc",
    "sg:classifiers":[
        {
            "category":"Building & Trades",
            "subcategory":"Construction",
            "type":"Services"
        }
    ],
    "sg:phone":"+61 3 9580 8683",
    "sg:postcode":"3195",
    "sg:province":"VIC",
    "sg:tags":[
        "brick",
        "paving"
    ],
    "wof:name":"Pave-A-Way",
    "wof:placetype":"venue"
},
  "geometry": {"coordinates":[145.09945678700001,-38.0085296631],"type":"Point"}
}