{
  "type": "Feature",
  "properties": {
    "iso:country":"AU",
    "sg:address":"11 Collins St",
    "sg:city":"Werribee",
    "sg:classifiers":[
        {
            "category":"Building & Trades",
            "subcategory":"Construction",
            "type":"Services"
        }
    ],
    "sg:phone":"+61 419 779 060",
    "sg:postcode":"3030",
    "sg:province":"VIC",
    "sg:tags":[
        "bricklayer"
    ],
    "wof:name":"A & M Cuzzupe Pty Ltd",
    "wof:placetype":"venue"
},
  "geometry": {"coordinates":[144.661423,-37.909752],"type":"Point"}
}