{
  "type": "Feature",
  "properties": {
    "addr:full":"152 Bungaree Rd Pendle Hill NSW 2145",
    "addr:housenumber":"152",
    "addr:postcode":"2145",
    "addr:street":"Bungaree Rd",
    "iso:country":"AU",
    "sg:address":"152 Bungaree Rd",
    "sg:city":"Pendle Hill",
    "sg:classifiers":[
        {
            "category":"Professional",
            "subcategory":"Engineering",
            "type":"Services"
        }
    ],
    "sg:phone":"+61 1300 664 224",
    "sg:postcode":"2145",
    "sg:province":"NSW",
    "sg:tags":[
        "engineer",
        "designing"
    ],
    "wof:name":"I.C.D. Asia Pacific Pty Ltd",
    "wof:placetype":"venue"
},
  "geometry": {"coordinates":[150.95831298799999,-33.8011665344],"type":"Point"}
}