{
  "type": "Feature",
  "properties": {
    "addr:full":"Ocean Keys Shopping Centre, 36 Ocean Keys Blv Clarkson WA 6030",
    "addr:housenumber":"36",
    "addr:postcode":"6030",
    "addr:street":"Ocean Keys Blv",
    "iso:country":"AU",
    "sg:address":"Ocean Keys Shopping Centre, 36",
    "sg:city":"Ocean Keys Blv Clarkson",
    "sg:classifiers":[
        {
            "category":"Travel",
            "subcategory":"Travel Agent",
            "type":"Entertainment"
        }
    ],
    "sg:phone":"+61 13 18 66",
    "sg:postcode":"6030",
    "sg:province":"WA",
    "sg:tags":[
        "consultant"
    ],
    "wof:name":"Flight Centre",
    "wof:placetype":"venue"
},
  "geometry": {"coordinates":[115.71710967999999,-31.6897106171],"type":"Point"}
}