{
  "type": "Feature",
  "properties": {
    "iso:country":"AU",
    "sg:address":"20 Annie St",
    "sg:city":"New Farm",
    "sg:classifiers":[
        {
            "category":"Building & Trades",
            "subcategory":"Construction",
            "type":"Services"
        }
    ],
    "sg:phone":"+61 418 720 727",
    "sg:postcode":"4005",
    "sg:province":"QLD",
    "sg:tags":[
        "renovation",
        "alterations",
        "extension",
        "contractor"
    ],
    "wof:name":"Stagnitti Sam & Sons Pty Ltd",
    "wof:placetype":"venue"
},
  "geometry": {"coordinates":[153.04263305699999,-27.4642887115],"type":"Point"}
}