{
  "type": "Feature",
  "properties": {
    "addr:full":"Unit 3/ 77 Basset St Mona Vale NSW 2103",
    "addr:housenumber":"77",
    "addr:postcode":"2103",
    "addr:street":"Basset St",
    "iso:country":"AU",
    "sg:address":"Unit 3/ 77 Basset St",
    "sg:city":"Mona Vale",
    "sg:classifiers":[
        {
            "category":"Building & Trades",
            "subcategory":"Construction",
            "type":"Services"
        }
    ],
    "sg:phone":"+61 2 9979 4650",
    "sg:postcode":"2103",
    "sg:province":"NSW",
    "sg:tags":[
        "joinery"
    ],
    "wof:name":"Jeffrey Broadfield Contemporary Building & Joinery",
    "wof:placetype":"venue"
},
  "geometry": {"coordinates":[151.306930542,-33.6717758179],"type":"Point"}
}