{
  "type": "Feature",
  "properties": {
    "addr:full":"35- 37 Victoria St Kerang VIC 3579",
    "addr:housenumber":"37",
    "addr:postcode":"3579",
    "addr:street":"Victoria St",
    "iso:country":"AU",
    "sg:address":"35- 37 Victoria St",
    "sg:city":"Kerang",
    "sg:classifiers":[
        {
            "category":"Professional",
            "subcategory":"Employment Agencies",
            "type":"Services"
        }
    ],
    "sg:phone":"+61 1800 786 360",
    "sg:postcode":"3579",
    "sg:province":"VIC",
    "wof:name":"Murray Mallee Training Co Ltd",
    "wof:placetype":"venue"
},
  "geometry": {"coordinates":[143.92047119099999,-35.7351951599],"type":"Point"}
}