{
  "type": "Feature",
  "properties": {
    "iso:country":"AU",
    "sg:address":"4 Kew Rd",
    "sg:city":"Laurieton",
    "sg:classifiers":[
        {
            "category":"Fast Food",
            "type":"Food & Drink"
        }
    ],
    "sg:phone":"+61 2 6559 7000",
    "sg:postcode":"2443",
    "sg:province":"NSW",
    "sg:tags":[
        "away",
        "take"
    ],
    "wof:name":"Eagle Boys Pizza Laurieton",
    "wof:placetype":"venue"
},
  "geometry": {"coordinates":[152.796524,-31.647682],"type":"Point"}
}