{
  "type": "Feature",
  "properties": {
    "iso:country":"AU",
    "sg:address":"Unit 3/ 2 Farnell St",
    "sg:city":"Surry Hills",
    "sg:classifiers":[
        {
            "category":"Manufacturing",
            "subcategory":"Apparel",
            "type":"Manufacturing & Wholesale Goods"
        }
    ],
    "sg:phone":"+61 2 9356 3339",
    "sg:postcode":"2010",
    "sg:province":"NSW",
    "sg:tags":[
        "wholesaler",
        "mfrs",
        "footwear"
    ],
    "wof:name":"Meller Kim Imports Pty Ltd",
    "wof:placetype":"venue"
},
  "geometry": {"coordinates":[151.21690368599999,-33.8854980469],"type":"Point"}
}