{
  "type": "Feature",
  "properties": {
    "addr:full":"520 Bunnerong Rd Matraville NSW 2036",
    "addr:housenumber":"520",
    "addr:postcode":"2036",
    "addr:street":"Bunnerong Rd",
    "iso:country":"AU",
    "sg:address":"520 Bunnerong Rd",
    "sg:city":"Matraville",
    "sg:classifiers":[
        {
            "category":"Health Services",
            "subcategory":"Doctor",
            "type":"Services"
        }
    ],
    "sg:phone":"+61 2 9311 1603",
    "sg:postcode":"2036",
    "sg:province":"NSW",
    "sg:tags":[
        "medical",
        "practitioner"
    ],
    "wof:name":"Sachdev P",
    "wof:placetype":"venue"
},
  "geometry": {"coordinates":[151.231201172,-33.9588661194],"type":"Point"}
}