{
  "type": "Feature",
  "properties": {
    "addr:full":"8 Wallace Ave Hurlstone Park NSW 2193",
    "addr:housenumber":"8",
    "addr:postcode":"2193",
    "addr:street":"Wallace Ave",
    "iso:country":"AU",
    "sg:address":"8 Wallace Ave",
    "sg:city":"Hurlstone Park",
    "sg:classifiers":[
        {
            "category":"Building & Trades",
            "subcategory":"Construction",
            "type":"Services"
        }
    ],
    "sg:phone":"+61 2 9559 5752",
    "sg:postcode":"2193",
    "sg:province":"NSW",
    "sg:tags":[
        "rendering",
        "cement"
    ],
    "wof:name":"Perestrello C",
    "wof:placetype":"venue"
},
  "geometry": {"coordinates":[151.13200399999999,-33.907803],"type":"Point"}
}