{
  "type": "Feature",
  "properties": {
    "iso:country":"AU",
    "sg:address":"17 Pearson Pl",
    "sg:city":"Floreat",
    "sg:classifiers":[
        {
            "category":"Building & Trades",
            "subcategory":"Construction",
            "type":"Services"
        }
    ],
    "sg:phone":"+61 8 9284 0924",
    "sg:postcode":"6014",
    "sg:province":"WA",
    "sg:tags":[
        "contractor"
    ],
    "wof:name":"Quaine Constructions",
    "wof:placetype":"venue"
},
  "geometry": {"coordinates":[115.80066680900001,-31.9315910339],"type":"Point"}
}