{
  "type": "Feature",
  "properties": {
    "addr:full":"488 Victoria St Richmond VIC 3121",
    "addr:housenumber":"488",
    "addr:postcode":"3121",
    "addr:street":"Victoria St",
    "iso:country":"AU",
    "sg:address":"488 Victoria St",
    "sg:city":"Richmond",
    "sg:classifiers":[
        {
            "category":"Professional",
            "subcategory":"Art Services",
            "type":"Services"
        }
    ],
    "sg:phone":"+61 416 161 114",
    "sg:postcode":"3121",
    "sg:province":"VIC",
    "sg:tags":[
        "graphic",
        "designer"
    ],
    "wof:name":"Design Literate Pty Ltd",
    "wof:placetype":"venue"
},
  "geometry": {"coordinates":[145.00831604000001,-37.811416626],"type":"Point"}
}