{
  "type": "Feature",
  "properties": {
    "addr:full":"Dollarburn Rd Warragul VIC 3820",
    "addr:postcode":"3820",
    "addr:street":"Dollarburn Rd",
    "iso:country":"AU",
    "sg:address":"Dollarburn Rd",
    "sg:city":"Warragul",
    "sg:classifiers":[
        {
            "category":"Food & Beverages",
            "subcategory":"Fruits & Vegetables",
            "type":"Retail Goods"
        }
    ],
    "sg:phone":"+61 3 5623 5992",
    "sg:postcode":"3820",
    "sg:province":"VIC",
    "sg:tags":[
        "grower"
    ],
    "wof:name":"Altamore M & B",
    "wof:placetype":"venue"
},
  "geometry": {"coordinates":[145.926727,-38.131588],"type":"Point"}
}