{
  "type": "Feature",
  "properties": {
    "addr:full":"45 Helen St Cooktown QLD 4895",
    "addr:housenumber":"45",
    "addr:postcode":"4895",
    "addr:street":"Helen St",
    "iso:country":"AU",
    "sg:address":"45 Helen St",
    "sg:city":"Cooktown",
    "sg:classifiers":[
        {
            "category":"Health Services",
            "subcategory":"Medical Lab",
            "type":"Services"
        }
    ],
    "sg:phone":"+61 7 4069 6996",
    "sg:postcode":"4895",
    "sg:province":"QLD",
    "sg:tags":[
        "laboratory",
        "pathology"
    ],
    "wof:name":"Sullivan Nicolaides Pathology Laboratories",
    "wof:placetype":"venue"
},
  "geometry": {"coordinates":[145.24879455600001,-15.4749584198],"type":"Point"}
}