{
  "type": "Feature",
  "properties": {
    "iso:country":"AU",
    "sg:address":"102 McLeod St",
    "sg:city":"Cairns",
    "sg:classifiers":[
        {
            "category":"Retail",
            "subcategory":"Repair Shop",
            "type":"Services"
        }
    ],
    "sg:phone":"+61 7 4031 4543",
    "sg:postcode":"4870",
    "sg:province":"QLD",
    "sg:tags":[
        "mending",
        "clothing",
        "alteration"
    ],
    "wof:name":"Abacus Alterations",
    "wof:placetype":"venue"
},
  "geometry": {"coordinates":[145.76881408700001,-16.919670105],"type":"Point"}
}