{
  "type": "Feature",
  "properties": {
    "addr:full":"St Vincents Private Hospital+Gormans Hill Rd Bathurst NSW 2795",
    "addr:postcode":"2795",
    "addr:street":"St;Hill Rd",
    "iso:country":"AU",
    "sg:address":"St Vincents Private Hospital+Gormans Hill Rd",
    "sg:city":"Bathurst",
    "sg:classifiers":[
        {
            "category":"Health Services",
            "subcategory":"Health Practitioner",
            "type":"Services"
        }
    ],
    "sg:phone":"+61 414 402 934",
    "sg:postcode":"2795",
    "sg:province":"NSW",
    "sg:tags":[
        "physiotherapist"
    ],
    "wof:name":"Jenny Dutton Hand and Upper Limb Physiotherapy",
    "wof:placetype":"venue"
},
  "geometry": {"coordinates":[149.582199097,-33.4737319946],"type":"Point"}
}