{
  "type": "Feature",
  "properties": {
    "iso:country":"AU",
    "sg:address":"58 Sandy Bay Rd",
    "sg:city":"Hobart",
    "sg:classifiers":[
        {
            "category":"Fast Food",
            "type":"Food & Drink"
        }
    ],
    "sg:phone":"+61 3 6223 4839",
    "sg:postcode":"7000",
    "sg:province":"TAS",
    "sg:tags":[
        "away",
        "take"
    ],
    "wof:name":"Culpepper's",
    "wof:placetype":"venue"
},
  "geometry": {"coordinates":[147.328659058,-42.8907279968],"type":"Point"}
}