{
  "type": "Feature",
  "properties": {
    "addr:full":"12 Main St Burpengary QLD 4505",
    "addr:housenumber":"12",
    "addr:postcode":"4505",
    "addr:street":"Main St",
    "iso:country":"AU",
    "sg:address":"12 Main St",
    "sg:city":"Burpengary",
    "sg:classifiers":[
        {
            "category":"Personal",
            "subcategory":"Beauty Salon",
            "type":"Services"
        }
    ],
    "sg:phone":"+61 7 3888 8807",
    "sg:postcode":"4505",
    "sg:province":"QLD",
    "wof:name":"Coco Beach Tanning & Beauty",
    "wof:placetype":"venue"
},
  "geometry": {"coordinates":[152.961791992,-27.2044391632],"type":"Point"}
}