{
  "type": "Feature",
  "properties": {
    "addr:full":"293 Charman Rd Cheltenham VIC 3192",
    "addr:housenumber":"293",
    "addr:postcode":"3192",
    "addr:street":"Charman Rd",
    "iso:country":"AU",
    "sg:address":"293 Charman Rd",
    "sg:city":"Cheltenham",
    "sg:classifiers":[
        {
            "category":"Retail",
            "subcategory":"Repair Shop",
            "type":"Services"
        }
    ],
    "sg:phone":"+61 3 9583 6917",
    "sg:postcode":"3192",
    "sg:province":"VIC",
    "sg:tags":[
        "machine",
        "sewing"
    ],
    "wof:name":"Milford Distributors Pty Ltd",
    "wof:placetype":"venue"
},
  "geometry": {"coordinates":[145.05549621599999,-37.9656181335],"type":"Point"}
}