{
  "type": "Feature",
  "properties": {
    "addr:full":"4/ 14 Hewlett St Granville NSW 2142",
    "addr:housenumber":"/ 14",
    "addr:postcode":"2142",
    "addr:street":"Hewlett St",
    "iso:country":"AU",
    "sg:address":"4/ 14 Hewlett St",
    "sg:city":"Granville",
    "sg:classifiers":[
        {
            "category":"Retail",
            "subcategory":"Storage",
            "type":"Services"
        }
    ],
    "sg:phone":"+61 414 214 907",
    "sg:postcode":"2142",
    "sg:province":"NSW",
    "sg:tags":[
        "removal",
        "furniture"
    ],
    "wof:name":"Aim Removals",
    "wof:placetype":"venue"
},
  "geometry": {"coordinates":[151.005737305,-33.832775116],"type":"Point"}
}