{
  "type": "Feature",
  "properties": {
    "addr:full":"358- 360 Mt Dandenong Rd Croydon VIC 3136",
    "addr:housenumber":"358 360",
    "addr:postcode":"3136",
    "addr:street":"Mt Dandenong Rd",
    "iso:country":"AU",
    "sg:address":"358- 360 Mt Dandenong Rd",
    "sg:city":"Croydon",
    "sg:classifiers":[
        {
            "category":"Arts & Performance",
            "subcategory":"Dance",
            "type":"Entertainment"
        }
    ],
    "sg:phone":"+61 3 9725 4951",
    "sg:postcode":"3136",
    "sg:province":"VIC",
    "sg:tags":[
        "theatrical",
        "ballet",
        "tuition"
    ],
    "wof:name":"Michelle Hart School Of Dance",
    "wof:placetype":"venue"
},
  "geometry": {"coordinates":[145.29544067399999,-37.8005256653],"type":"Point"}
}