{
  "type": "Feature",
  "properties": {
    "addr:full":"\"Tropical Park\" J.Pierce Rd Gracemere QLD 4702",
    "addr:postcode":"4702",
    "addr:street":"J.Pierce Rd",
    "iso:country":"AU",
    "sg:address":"\"Tropical Park\" J.Pierce Rd",
    "sg:city":"Gracemere",
    "sg:classifiers":[
        {
            "category":"Retail",
            "subcategory":"Animal Services",
            "type":"Services"
        }
    ],
    "sg:phone":"+61 7 4933 1319",
    "sg:postcode":"4702",
    "sg:province":"QLD",
    "sg:tags":[
        "breeder",
        "sheep",
        "stud",
        "cattle"
    ],
    "wof:name":"Tropical Brahman Stud",
    "wof:placetype":"venue"
},
  "geometry": {"coordinates":[150.48379516599999,-23.4814128876],"type":"Point"}
}