{
  "type": "Feature",
  "properties": {
    "addr:full":"62 Chelmer St East Chelmer QLD 4068",
    "addr:housenumber":"62",
    "addr:postcode":"4068",
    "addr:street":"Chelmer St East",
    "iso:country":"AU",
    "sg:address":"62 Chelmer St East",
    "sg:city":"Chelmer",
    "sg:classifiers":[
        {
            "category":"Government",
            "subcategory":"City Hall",
            "type":"Public Place"
        }
    ],
    "sg:phone":"+61 7 3379 8894",
    "sg:postcode":"4068",
    "sg:province":"QLD",
    "wof:name":"St David's Parish Hall",
    "wof:placetype":"venue"
},
  "geometry": {"coordinates":[152.97389221200001,-27.5144691467],"type":"Point"}
}