{
  "type": "Feature",
  "properties": {
    "addr:full":"Unit 19 / 6 Abbott Rd Seven Hills NSW 2147",
    "addr:housenumber":"/ 6",
    "addr:postcode":"2147",
    "addr:street":"Abbott Rd",
    "iso:country":"AU",
    "sg:address":"Unit 19 / 6 Abbott Rd",
    "sg:city":"Seven Hills",
    "sg:classifiers":[
        {
            "category":"Wholesale",
            "subcategory":"Medical Equipment & Supplies",
            "type":"Manufacturing & Wholesale Goods"
        }
    ],
    "sg:phone":"+61 2 9620 6744",
    "sg:postcode":"2147",
    "sg:province":"NSW",
    "sg:tags":[
        "aid",
        "care",
        "health",
        "home"
    ],
    "wof:name":"Niagara Therapy",
    "wof:placetype":"venue"
},
  "geometry": {"coordinates":[150.94554138199999,-33.7679710388],"type":"Point"}
}