{
  "type": "Feature",
  "properties": {
    "addr:full":"5th Flr, 12 Butler Rd Hurstville NSW 2220",
    "addr:housenumber":"12",
    "addr:postcode":"2220",
    "addr:street":"Butler Rd",
    "iso:country":"AU",
    "sg:address":"5th Flr, 12 Butler Rd",
    "sg:city":"Hurstville",
    "sg:classifiers":[
        {
            "category":"Banks & Credit Unions",
            "subcategory":"Financial Services",
            "type":"Services"
        }
    ],
    "sg:phone":"+61 2 9585 1222",
    "sg:postcode":"2220",
    "sg:province":"NSW",
    "sg:tags":[
        "planning"
    ],
    "wof:name":"Count Wealth Accountants",
    "wof:placetype":"venue"
},
  "geometry": {"coordinates":[151.10194397000001,-33.9682235718],"type":"Point"}
}