{
  "type": "Feature",
  "properties": {
    "addr:full":"223 James St Northbridge WA 6003",
    "addr:housenumber":"223",
    "addr:postcode":"6003",
    "addr:street":"James St",
    "iso:country":"AU",
    "sg:address":"223 James St",
    "sg:city":"Northbridge",
    "sg:classifiers":[
        {
            "category":"Government",
            "subcategory":"Court House",
            "type":"Public Place"
        }
    ],
    "sg:phone":"+61 8 9227 4300",
    "sg:postcode":"6003",
    "sg:province":"WA",
    "sg:tags":[
        "personal",
        "marriage",
        "family",
        "counselling"
    ],
    "wof:name":"Youthlink",
    "wof:placetype":"venue"
},
  "geometry": {"coordinates":[115.85389709499999,-31.9466094971],"type":"Point"}
}