{
  "type": "Feature",
  "properties": {
    "iso:country":"AU",
    "sg:address":"Shop 4 147 Balo St",
    "sg:city":"Moree",
    "sg:classifiers":[
        {
            "category":"Shopping",
            "subcategory":"Clothing, Apparel, & Fashions",
            "type":"Retail Goods"
        }
    ],
    "sg:phone":"+61 2 6752 3900",
    "sg:postcode":"2400",
    "sg:province":"NSW",
    "sg:tags":[
        "accessory"
    ],
    "wof:name":"Shoe Elegance",
    "wof:placetype":"venue"
},
  "geometry": {"coordinates":[149.84144592300001,-29.4648361206],"type":"Point"}
}