{
  "type": "Feature",
  "properties": {
    "iso:country":"AU",
    "sg:address":"Shop 3, 169 Leura Mall",
    "sg:city":"Leura",
    "sg:classifiers":[
        {
            "category":"Health Services",
            "subcategory":"Health Practitioner",
            "type":"Services"
        }
    ],
    "sg:phone":"+61 2 4784 3393",
    "sg:postcode":"2780",
    "sg:province":"NSW",
    "sg:tags":[
        "alternative"
    ],
    "wof:name":"Crozier Susan",
    "wof:placetype":"venue"
},
  "geometry": {"coordinates":[150.330810547,-33.7133102417],"type":"Point"}
}