{
  "type": "Feature",
  "properties": {
    "addr:full":"139 Brebner Drv West Lakes SA 5021",
    "addr:housenumber":"139",
    "addr:postcode":"5021",
    "addr:street":"Brebner Drv",
    "iso:country":"AU",
    "sg:address":"139 Brebner Drv",
    "sg:city":"West Lakes",
    "sg:classifiers":[
        {
            "category":"Insurance",
            "subcategory":"Hazard Insurance",
            "type":"Services"
        }
    ],
    "sg:phone":"+61 8 8202 4567",
    "sg:postcode":"5021",
    "sg:province":"SA",
    "sg:tags":[
        "motor",
        "vehicle"
    ],
    "wof:name":"RAA Insurance Ltd",
    "wof:placetype":"venue"
},
  "geometry": {"coordinates":[138.489135742,-34.8807029724],"type":"Point"}
}