{
  "type": "Feature",
  "properties": {
    "iso:country":"AU",
    "sg:address":"Level 7 114- 120 Castlereagh St",
    "sg:city":"Sydney",
    "sg:classifiers":[
        {
            "category":"Professional",
            "subcategory":"Computer Services",
            "type":"Services"
        }
    ],
    "sg:phone":"+61 2 9261 2499",
    "sg:postcode":"2000",
    "sg:province":"NSW",
    "sg:tags":[
        "training"
    ],
    "wof:name":"Icom Training",
    "wof:placetype":"venue"
},
  "geometry": {"coordinates":[151.209594727,-33.8710899353],"type":"Point"}
}