{
  "type": "Feature",
  "properties": {
    "iso:country":"AU",
    "sg:address":"22 Duke Ave",
    "sg:city":"Rodd Point",
    "sg:classifiers":[
        {
            "category":"Building & Trades",
            "subcategory":"Equipment Rental",
            "type":"Services"
        }
    ],
    "sg:phone":"+61 425 258 597",
    "sg:postcode":"2046",
    "sg:province":"NSW",
    "sg:tags":[
        "hire",
        "catering"
    ],
    "wof:name":"Raineri's Mobile Cafe",
    "wof:placetype":"venue"
},
  "geometry": {"coordinates":[151.141953,-33.865845],"type":"Point"}
}