{
  "type": "Feature",
  "properties": {
    "iso:country":"AU",
    "sg:address":"326- 328 Diagonal Rd",
    "sg:city":"Sturt",
    "sg:classifiers":[
        {
            "category":"Social Services",
            "subcategory":"Child Care",
            "type":"Services"
        }
    ],
    "sg:phone":"+61 8 8296 7776",
    "sg:postcode":"5047",
    "sg:province":"SA",
    "wof:name":"Diagonal Road Community Child Care Centre",
    "wof:placetype":"venue"
},
  "geometry": {"coordinates":[138.549911,-35.02066],"type":"Point"}
}