{
  "type": "Feature",
  "properties": {
    "iso:country":"AU",
    "sg:address":"43 Glendale Ave",
    "sg:city":"Hastings",
    "sg:classifiers":[
        {
            "category":"Retail",
            "subcategory":"Auto Repair",
            "type":"Services"
        }
    ],
    "sg:phone":"+61 3 5979 3550",
    "sg:postcode":"3915",
    "sg:province":"VIC",
    "sg:tags":[
        "testing",
        "inspection",
        "motor",
        "vehicle"
    ],
    "wof:name":"Ultra Car Care",
    "wof:placetype":"venue"
},
  "geometry": {"coordinates":[145.184890747,-38.3043365479],"type":"Point"}
}