{
  "type": "Feature",
  "properties": {
    "iso:country":"AU",
    "sg:address":"11 Ardross St",
    "sg:city":"Applecross",
    "sg:classifiers":[
        {
            "category":"Professional",
            "type":"Services"
        }
    ],
    "sg:phone":"+61 419 694 445",
    "sg:postcode":"6153",
    "sg:province":"WA",
    "sg:tags":[
        "transport"
    ],
    "wof:name":"Hender Interstate Transport",
    "wof:placetype":"venue"
},
  "geometry": {"coordinates":[115.83255800000001,-32.007229],"type":"Point"}
}