{
  "type": "Feature",
  "properties": {
    "addr:full":"102 King William Rd Hyde Park SA 5061",
    "addr:housenumber":"102",
    "addr:postcode":"5061",
    "addr:street":"King William Rd",
    "iso:country":"AU",
    "sg:address":"102 King William Rd",
    "sg:city":"Hyde Park",
    "sg:classifiers":[
        {
            "category":"Sports & Exercise",
            "subcategory":"Gym",
            "type":"Entertainment"
        }
    ],
    "sg:phone":"+61 8 8272 0422",
    "sg:postcode":"5061",
    "sg:province":"SA",
    "sg:tags":[
        "health",
        "fitness"
    ],
    "wof:name":"Mega Bike",
    "wof:placetype":"venue"
},
  "geometry": {"coordinates":[138.59971618599999,-34.9523086548],"type":"Point"}
}