{
  "type": "Feature",
  "properties": {
    "iso:country":"AU",
    "sg:address":"Shop 6, 9- 14 Grovenor La",
    "sg:city":"Neutral Bay",
    "sg:classifiers":[
        {
            "category":"Food & Beverages",
            "subcategory":"Fruits & Vegetables",
            "type":"Retail Goods"
        }
    ],
    "sg:phone":"+61 2 9909 1199",
    "sg:postcode":"2089",
    "sg:province":"NSW",
    "sg:tags":[
        "greengrocer",
        "fruiterer"
    ],
    "wof:name":"Freshest Group Pty Ltd",
    "wof:placetype":"venue"
},
  "geometry": {"coordinates":[151.22242736800001,-33.8309135437],"type":"Point"}
}