{
  "type": "Feature",
  "properties": {
    "addr:full":"586 Parramatta Rd Ashfield NSW 2131",
    "addr:housenumber":"586",
    "addr:postcode":"2131",
    "addr:street":"Parramatta Rd",
    "iso:country":"AU",
    "sg:address":"586 Parramatta Rd",
    "sg:city":"Ashfield",
    "sg:classifiers":[
        {
            "category":"Fast Food",
            "type":"Food & Drink"
        }
    ],
    "sg:phone":"+61 2 9716 4743",
    "sg:postcode":"2131",
    "sg:province":"NSW",
    "sg:tags":[
        "away",
        "take"
    ],
    "wof:name":"Subway Sandwiches & Salads",
    "wof:placetype":"venue"
},
  "geometry": {"coordinates":[151.126754761,-33.8737182617],"type":"Point"}
}