{
  "type": "Feature",
  "properties": {
    "addr:full":"30 Canara Ave La Perouse NSW 2036",
    "addr:housenumber":"30",
    "addr:postcode":"2036",
    "addr:street":"Canara Ave La",
    "iso:country":"AU",
    "sg:address":"30 Canara Ave",
    "sg:city":"La Perouse",
    "sg:classifiers":[
        {
            "category":"Education",
            "subcategory":"Kindergarten",
            "type":"Public Place"
        }
    ],
    "sg:phone":"+61 2 9661 5832",
    "sg:postcode":"2036",
    "sg:province":"NSW",
    "sg:tags":[
        "pre-schools"
    ],
    "wof:name":"KU Children's Services",
    "wof:placetype":"venue"
},
  "geometry": {"coordinates":[151.23475647000001,-33.9819602966],"type":"Point"}
}