{
  "type": "Feature",
  "properties": {
    "addr:full":"Unit 8/ 27 Allgas St Slacks Creek QLD 4127",
    "addr:postcode":"4127",
    "addr:street":"27 Allgas St",
    "iso:country":"AU",
    "sg:address":"Unit 8/ 27 Allgas St",
    "sg:city":"Slacks Creek",
    "sg:classifiers":[
        {
            "category":"Professional",
            "subcategory":"Computer Services",
            "type":"Services"
        }
    ],
    "sg:phone":"+61 7 3808 4888",
    "sg:postcode":"4127",
    "sg:province":"QLD",
    "sg:tags":[
        "technical",
        "support"
    ],
    "wof:name":"Business Computing Australia",
    "wof:placetype":"venue"
},
  "geometry": {"coordinates":[153.12246704099999,-27.6186408997],"type":"Point"}
}