{
  "type": "Feature",
  "properties": {
    "addr:full":"23 Redcliffe Pde Redcliffe QLD 4020",
    "addr:housenumber":"23",
    "addr:postcode":"4020",
    "addr:street":"Redcliffe Pde",
    "iso:country":"AU",
    "sg:address":"23 Redcliffe Pde",
    "sg:city":"Redcliffe",
    "sg:classifiers":[
        {
            "category":"Real Estate",
            "subcategory":"Real Estate Agent",
            "type":"Services"
        }
    ],
    "sg:phone":"+61 7 3883 2366",
    "sg:postcode":"4020",
    "sg:province":"QLD",
    "wof:name":"Elders Redcliffe",
    "wof:placetype":"venue"
},
  "geometry": {"coordinates":[153.11537200000001,-27.228485],"type":"Point"}
}