{
  "type": "Feature",
  "properties": {
    "addr:full":"The Cooperage - Studio 404/ 56 Bowman St Pyrmont NSW 2009",
    "addr:housenumber":"404 / 56",
    "addr:postcode":"2009",
    "addr:street":"Bowman St",
    "iso:country":"AU",
    "sg:address":"The Cooperage - Studio 404/ 56 Bowman St",
    "sg:city":"Pyrmont",
    "sg:classifiers":[
        {
            "category":"Real Estate",
            "subcategory":"Architect",
            "type":"Services"
        }
    ],
    "sg:phone":"+61 2 9566 2880",
    "sg:postcode":"2009",
    "sg:province":"NSW",
    "wof:name":"Connor & Solomon Architects",
    "wof:placetype":"venue"
},
  "geometry": {"coordinates":[151.18966674800001,-33.8673057556],"type":"Point"}
}