{
  "type": "Feature",
  "properties": {
    "addr:full":"Egret St Kooragang Island NSW 2304",
    "addr:postcode":"2304",
    "addr:street":"Egret St",
    "iso:country":"AU",
    "sg:address":"Egret St",
    "sg:city":"Kooragang Island",
    "sg:classifiers":[
        {
            "category":"Utilities",
            "subcategory":"Refuse",
            "type":"Services"
        }
    ],
    "sg:phone":"+61 2 4920 1455",
    "sg:postcode":"2304",
    "sg:province":"NSW",
    "sg:tags":[
        "disposal",
        "reduction",
        "waste"
    ],
    "wof:name":"Cleanaway",
    "wof:placetype":"venue"
},
  "geometry": {"coordinates":[151.764068603,-32.8818664551],"type":"Point"}
}