{
  "type": "Feature",
  "properties": {
    "addr:full":"114 High St Maryborough VIC 3465",
    "addr:housenumber":"114",
    "addr:postcode":"3465",
    "addr:street":"High St",
    "iso:country":"AU",
    "sg:address":"114 High St",
    "sg:city":"Maryborough",
    "sg:classifiers":[
        {
            "category":"Building & Trades",
            "subcategory":"Locksmith",
            "type":"Services"
        }
    ],
    "sg:phone":"+61 3 5461 5235",
    "sg:postcode":"3465",
    "sg:province":"VIC",
    "sg:tags":[
        "lock"
    ],
    "wof:name":"Maryborough Locksmiths",
    "wof:placetype":"venue"
},
  "geometry": {"coordinates":[143.73684692399999,-37.0475997925],"type":"Point"}
}