{
  "type": "Feature",
  "properties": {
    "iso:country":"AU",
    "sg:address":"59 Roberts Ave",
    "sg:city":"Mulgrave",
    "sg:classifiers":[
        {
            "category":"Building & Trades",
            "subcategory":"Equipment Rental",
            "type":"Services"
        }
    ],
    "sg:phone":"+61 3 9558 4377",
    "sg:postcode":"3170",
    "sg:province":"VIC",
    "sg:tags":[
        "hire",
        "catering"
    ],
    "wof:name":"Sheppard Catering Equipment",
    "wof:placetype":"venue"
},
  "geometry": {"coordinates":[145.14840698200001,-37.9259338379],"type":"Point"}
}