{
  "type": "Feature",
  "properties": {
    "iso:country":"AU",
    "sg:address":"96 Adelaide Rd",
    "sg:city":"Mannum",
    "sg:classifiers":[
        {
            "category":"Wholesale",
            "subcategory":"Machinery & Supplies",
            "type":"Manufacturing & Wholesale Goods"
        }
    ],
    "sg:phone":"+61 8 8569 1306",
    "sg:postcode":"5238",
    "sg:province":"SA",
    "sg:tags":[
        "agricultural"
    ],
    "wof:name":"Mannum Ag & Building Supplies",
    "wof:placetype":"venue"
},
  "geometry": {"coordinates":[139.30548095699999,-34.9156532288],"type":"Point"}
}