{
  "type": "Feature",
  "properties": {
    "addr:full":"36 Herbert St West Ryde NSW 2114",
    "addr:housenumber":"36",
    "addr:postcode":"2114",
    "addr:street":"Herbert St",
    "iso:country":"AU",
    "sg:address":"36 Herbert St",
    "sg:city":"West Ryde",
    "sg:classifiers":[
        {
            "category":"Retail",
            "subcategory":"Auto Repair",
            "type":"Services"
        }
    ],
    "sg:phone":"+61 2 9809 3238",
    "sg:postcode":"2114",
    "sg:province":"NSW",
    "sg:tags":[
        "repairer",
        "motor",
        "engineer"
    ],
    "wof:name":"McMillan G G Pty Ltd",
    "wof:placetype":"venue"
},
  "geometry": {"coordinates":[151.09158325199999,-33.8071289062],"type":"Point"}
}