{
  "type": "Feature",
  "properties": {
    "addr:full":"Unit 6, 14 Farrall Rd Midland WA 6056",
    "addr:housenumber":"14",
    "addr:postcode":"6056",
    "addr:street":"Farrall Rd",
    "iso:country":"AU",
    "sg:address":"Unit 6, 14 Farrall Rd",
    "sg:city":"Midland",
    "sg:classifiers":[
        {
            "category":"Shopping",
            "subcategory":"Bicycles & Sporting Goods",
            "type":"Retail Goods"
        }
    ],
    "sg:phone":"+61 8 9274 4275",
    "sg:postcode":"6056",
    "sg:province":"WA",
    "sg:tags":[
        "chemical",
        "equipment",
        "pool",
        "swimming"
    ],
    "sg:website":"http://www.swanpools.com.au",
    "wof:name":"Swan Pools",
    "wof:placetype":"venue"
},
  "geometry": {"coordinates":[116.033630371,-31.8841152191],"type":"Point"}
}