{
  "type": "Feature",
  "properties": {
    "addr:full":"Factory 1 10- 12 Intrepid St Berwick VIC 3806",
    "addr:housenumber":"10 12",
    "addr:postcode":"3806",
    "addr:street":"Intrepid St",
    "iso:country":"AU",
    "sg:address":"Factory 1 10- 12 Intrepid St",
    "sg:city":"Berwick",
    "sg:classifiers":[
        {
            "category":"Wholesale",
            "subcategory":"Furniture",
            "type":"Manufacturing & Wholesale Goods"
        }
    ],
    "sg:phone":"+61 3 9796 2566",
    "sg:postcode":"3806",
    "sg:province":"VIC",
    "sg:tags":[
        "wholesaler",
        "mfrs"
    ],
    "wof:name":"Flexiwood",
    "wof:placetype":"venue"
},
  "geometry": {"coordinates":[145.33952331500001,-38.037322998],"type":"Point"}
}