{
  "type": "Feature",
  "properties": {
    "iso:country":"AU",
    "sg:address":"94 Mann St",
    "sg:city":"Gosford",
    "sg:classifiers":[
        {
            "category":"Shopping",
            "subcategory":"Clothing, Apparel, & Fashions",
            "type":"Retail Goods"
        }
    ],
    "sg:phone":"+61 2 4323 6777",
    "sg:postcode":"2250",
    "sg:province":"NSW",
    "sg:tags":[
        "recycled",
        "clothing"
    ],
    "wof:name":"After-a-Fashion",
    "wof:placetype":"venue"
},
  "geometry": {"coordinates":[151.341629028,-33.4271240234],"type":"Point"}
}