{
  "type": "Feature",
  "properties": {
    "addr:full":"Lwr Grd Flr, 243 -249 Crown Street Wollongong NSW 2500",
    "addr:housenumber":"243 -249",
    "addr:postcode":"2500",
    "addr:street":"Lwr Grd;Crown Street",
    "iso:country":"AU",
    "sg:address":"Lwr Grd Flr, 243",
    "sg:city":"-249 Crown Street Wollongong",
    "sg:classifiers":[
        {
            "category":"Conference Center",
            "type":"Public Place"
        }
    ],
    "sg:phone":"+61 2 4225 1866",
    "sg:postcode":"2500",
    "sg:province":"NSW",
    "sg:tags":[
        "venue",
        "convention"
    ],
    "wof:name":"Ectarc Training Rooms",
    "wof:placetype":"venue"
},
  "geometry": {"coordinates":[150.891785,-34.425278],"type":"Point"}
}