{
  "type": "Feature",
  "properties": {
    "addr:full":"Lvl5/ 267 Castlereagh St Sydney NSW 2000",
    "addr:housenumber":"267",
    "addr:postcode":"2000",
    "addr:street":"Castlereagh St",
    "iso:country":"AU",
    "sg:address":"Lvl5/ 267 Castlereagh St",
    "sg:city":"Sydney",
    "sg:classifiers":[
        {
            "category":"Professional",
            "subcategory":"Accounting & Tax Preparation",
            "type":"Services"
        }
    ],
    "sg:phone":"+61 2 9283 4544",
    "sg:postcode":"2000",
    "sg:province":"NSW",
    "sg:tags":[
        "accountant",
        "auditor"
    ],
    "wof:name":"Jack Singh & Co",
    "wof:placetype":"venue"
},
  "geometry": {"coordinates":[151.20855712900001,-33.8773269653],"type":"Point"}
}