{
  "type": "Feature",
  "properties": {
    "iso:country":"AU",
    "sg:address":"Factory 6 Cnr Rudman Parade & Bee Crt",
    "sg:city":"Burleigh Heads",
    "sg:classifiers":[
        {
            "category":"Building & Trades",
            "subcategory":"Construction",
            "type":"Services"
        }
    ],
    "sg:phone":"+61 7 5593 5555",
    "sg:postcode":"4220",
    "sg:province":"QLD",
    "sg:tags":[
        "fencing",
        "contractor"
    ],
    "wof:name":"R & R Fencing (Qld) Pty Ltd",
    "wof:placetype":"venue"
},
  "geometry": {"coordinates":[153.42042541500001,-28.1025619507],"type":"Point"}
}