{
  "type": "Feature",
  "properties": {
    "iso:country":"AU",
    "sg:address":"48 Compton Rd",
    "sg:city":"Woodridge",
    "sg:classifiers":[
        {
            "category":"Autos & Motor Vehicles",
            "subcategory":"Automobile Sales",
            "type":"Retail Goods"
        }
    ],
    "sg:phone":"+61 7 3808 3800",
    "sg:postcode":"4114",
    "sg:province":"QLD",
    "sg:tags":[
        "car",
        "used"
    ],
    "wof:name":"Auto Outlet Centre",
    "wof:placetype":"venue"
},
  "geometry": {"coordinates":[153.10633850100001,-27.6190166473],"type":"Point"}
}