{
  "type": "Feature",
  "properties": {
    "addr:full":"90 Newton Rd Campbelltown SA 5074",
    "addr:housenumber":"90",
    "addr:postcode":"5074",
    "addr:street":"Newton Rd",
    "iso:country":"AU",
    "sg:address":"90 Newton Rd",
    "sg:city":"Campbelltown",
    "sg:classifiers":[
        {
            "category":"Home & Garden",
            "subcategory":"Garden Supply",
            "type":"Retail Goods"
        }
    ],
    "sg:phone":"+61 8 8165 0201",
    "sg:postcode":"5074",
    "sg:province":"SA",
    "sg:tags":[
        "equipment"
    ],
    "wof:name":"Advanced Growth",
    "wof:placetype":"venue"
},
  "geometry": {"coordinates":[138.673461914,-34.8786964417],"type":"Point"}
}