{
  "type": "Feature",
  "properties": {
    "addr:full":"68- 72 Fyans St Geelong VIC 3220",
    "addr:housenumber":"72",
    "addr:postcode":"3220",
    "addr:street":"Fyans St",
    "iso:country":"AU",
    "sg:address":"68- 72 Fyans St",
    "sg:city":"Geelong",
    "sg:classifiers":[
        {
            "category":"Manufacturing",
            "subcategory":"Motor Vehicles & Parts",
            "type":"Manufacturing & Wholesale Goods"
        }
    ],
    "sg:phone":"+61 3 5222 3000",
    "sg:postcode":"3220",
    "sg:province":"VIC",
    "sg:tags":[
        "replacement"
    ],
    "wof:name":"Blood Daihatsu",
    "wof:placetype":"venue"
},
  "geometry": {"coordinates":[144.35484299999999,-38.161999],"type":"Point"}
}