{
  "type": "Feature",
  "properties": {
    "iso:country":"AU",
    "sg:address":"708 Park Rd",
    "sg:city":"Park Orchards",
    "sg:classifiers":[
        {
            "category":"Building & Trades",
            "subcategory":"Plumbing",
            "type":"Services"
        }
    ],
    "sg:phone":"+61 408 369 409",
    "sg:postcode":"3114",
    "sg:province":"VIC",
    "sg:tags":[
        "plumber",
        "gasfitters"
    ],
    "wof:name":"B.V. Gow Plumbing Pty Ltd",
    "wof:placetype":"venue"
},
  "geometry": {"coordinates":[145.22679138199999,-37.7826118469],"type":"Point"}
}