{
  "type": "Feature",
  "properties": {
    "addr:full":"Ste 45 Lvl 2 Indooroopilly Shopngtwn Indooroopilly QLD 4068",
    "addr:postcode":"4068",
    "iso:country":"AU",
    "sg:address":"Ste 45 Lvl 2",
    "sg:city":"Indooroopilly Shopngtwn Indooroopilly",
    "sg:classifiers":[
        {
            "category":"Banks & Credit Unions",
            "subcategory":"Bank",
            "type":"Services"
        }
    ],
    "sg:phone":"+61 7 3872 1352",
    "sg:postcode":"4068",
    "sg:province":"QLD",
    "sg:tags":[
        "broker",
        "mortgage"
    ],
    "wof:name":"Mortgage Choice",
    "wof:placetype":"venue"
},
  "geometry": {"coordinates":[152.98945617699999,-27.4921836853],"type":"Point"}
}