{
  "type": "Feature",
  "properties": {
    "addr:full":"53 Dixon Rd Rockingham WA 6168",
    "addr:housenumber":"53",
    "addr:postcode":"6168",
    "addr:street":"Dixon Rd",
    "iso:country":"AU",
    "sg:address":"53 Dixon Rd",
    "sg:city":"Rockingham",
    "sg:classifiers":[
        {
            "category":"Autos & Motor Vehicles",
            "subcategory":"Auto Supplies",
            "type":"Retail Goods"
        }
    ],
    "sg:phone":"+61 8 9527 1184",
    "sg:postcode":"6168",
    "sg:province":"WA",
    "sg:tags":[
        "tyre"
    ],
    "wof:name":"Rockingham Medina Tyre Service",
    "wof:placetype":"venue"
},
  "geometry": {"coordinates":[115.75533299999999,-32.276825],"type":"Point"}
}