{
  "type": "Feature",
  "properties": {
    "addr:full":"Shop 4C, 145- 149 King St Warrawong NSW 2502",
    "addr:housenumber":"4c;149",
    "addr:postcode":"145;2502",
    "addr:street":"Shop;King St",
    "iso:country":"AU",
    "sg:address":"Shop 4C, 145- 149 King St",
    "sg:city":"Warrawong",
    "sg:classifiers":[
        {
            "category":"Home & Garden",
            "subcategory":"Household Appliances",
            "type":"Retail Goods"
        }
    ],
    "sg:phone":"+61 2 4276 4711",
    "sg:postcode":"2502",
    "sg:province":"NSW",
    "sg:tags":[
        "heating",
        "system"
    ],
    "wof:name":"AGL Energy Shop Warrawong",
    "wof:placetype":"venue"
},
  "geometry": {"coordinates":[150.88926699999999,-34.497326],"type":"Point"}
}