{
  "type": "Feature",
  "properties": {
    "addr:full":"3 Malton Crt Altona VIC 3018",
    "addr:housenumber":"3",
    "addr:postcode":"3018",
    "addr:street":"Malton Crt",
    "iso:country":"AU",
    "sg:address":"3 Malton Crt",
    "sg:city":"Altona",
    "sg:classifiers":[
        {
            "category":"Professional",
            "type":"Services"
        }
    ],
    "sg:phone":"+61 3 9398 3922",
    "sg:postcode":"3018",
    "sg:province":"VIC",
    "sg:tags":[
        "transport"
    ],
    "wof:name":"Cargomaster Pty Ltd",
    "wof:placetype":"venue"
},
  "geometry": {"coordinates":[144.80172729500001,-37.8594322205],"type":"Point"}
}