{
  "type": "Feature",
  "properties": {
    "addr:full":"9 Tincurrin Crt Robina QLD 4226",
    "addr:housenumber":"9",
    "addr:postcode":"4226",
    "addr:street":"Tincurrin Crt",
    "iso:country":"AU",
    "sg:address":"9 Tincurrin Crt",
    "sg:city":"Robina",
    "sg:classifiers":[
        {
            "category":"Sports & Exercise",
            "subcategory":"Gym",
            "type":"Entertainment"
        }
    ],
    "sg:phone":"+61 404 046 431",
    "sg:postcode":"4226",
    "sg:province":"QLD",
    "sg:tags":[
        "personal",
        "trainer",
        "fitness"
    ],
    "wof:name":"Halligans Fitness",
    "wof:placetype":"venue"
},
  "geometry": {"coordinates":[153.413772583,-28.0730857849],"type":"Point"}
}