{
  "type": "Feature",
  "properties": {
    "iso:country":"AU",
    "sg:address":"Suite 2/ 30 Brisbane St",
    "sg:city":"Mackay",
    "sg:classifiers":[
        {
            "category":"Building & Trades",
            "subcategory":"Construction",
            "type":"Services"
        }
    ],
    "sg:phone":"+61 419 024 795",
    "sg:postcode":"4740",
    "sg:province":"QLD",
    "sg:tags":[
        "contractor"
    ],
    "wof:name":"Dingle Paul",
    "wof:placetype":"venue"
},
  "geometry": {"coordinates":[149.187836,-21.14414],"type":"Point"}
}