{
  "type": "Feature",
  "properties": {
    "iso:country":"AU",
    "sg:address":"Arthur St",
    "sg:city":"Caloundra",
    "sg:classifiers":[
        {
            "category":"Arena",
            "subcategory":"Sports Club",
            "type":"Entertainment"
        }
    ],
    "sg:phone":"+61 7 5499 7777",
    "sg:postcode":"4551",
    "sg:province":"QLD",
    "sg:tags":[
        "union",
        "rugby"
    ],
    "wof:name":"Caloundra Rugby Union Club",
    "wof:placetype":"venue"
},
  "geometry": {"coordinates":[153.12382507300001,-26.7990837097],"type":"Point"}
}