{
  "type": "Feature",
  "properties": {
    "iso:country":"AU",
    "sg:address":"17 Bonython St",
    "sg:city":"Windsor",
    "sg:classifiers":[
        {
            "category":"Social Services",
            "subcategory":"Child Care",
            "type":"Services"
        }
    ],
    "sg:phone":"+61 7 3857 1288",
    "sg:postcode":"4030",
    "sg:province":"QLD",
    "wof:name":"Windsor Neighbourhood Child Care Centre",
    "wof:placetype":"venue"
},
  "geometry": {"coordinates":[153.03355400000001,-27.431604],"type":"Point"}
}