{
  "type": "Feature",
  "properties": {
    "addr:full":"First Floor, 72-74 Box Rd Taren Point NSW 2229",
    "addr:housenumber":"floor 72-74",
    "addr:postcode":"2229",
    "addr:street":"Box Rd",
    "iso:country":"AU",
    "sg:address":"First Floor, 72-74 Box Rd",
    "sg:city":"Taren Point",
    "sg:classifiers":[
        {
            "category":"Government",
            "subcategory":"Customs House",
            "type":"Public Place"
        }
    ],
    "sg:phone":"+61 2 9540 0600",
    "sg:postcode":"2229",
    "sg:province":"NSW",
    "sg:tags":[
        "title",
        "management",
        "stratum"
    ],
    "wof:name":"Strata Owners Services Pty Ltd",
    "wof:placetype":"venue"
},
  "geometry": {"coordinates":[151.11862182600001,-34.0240249634],"type":"Point"}
}