{
  "type": "Feature",
  "properties": {
    "iso:country":"AU",
    "sg:address":"Bundalla Rd",
    "sg:city":"Margate",
    "sg:classifiers":[
        {
            "category":"School Buses",
            "type":"Transportation"
        }
    ],
    "sg:phone":"+61 3 6267 1683",
    "sg:postcode":"7054",
    "sg:province":"TAS",
    "sg:tags":[
        "brick"
    ],
    "wof:name":"Timbercrete Tasmania",
    "wof:placetype":"venue"
},
  "geometry": {"coordinates":[147.272003,-43.029888],"type":"Point"}
}