{
  "type": "Feature",
  "properties": {
    "addr:full":"Unit 8/ 100 Bay Rd Waverton NSW 2060",
    "addr:housenumber":"/ 100",
    "addr:postcode":"2060",
    "addr:street":"Bay Rd",
    "iso:country":"AU",
    "sg:address":"Unit 8/ 100 Bay Rd",
    "sg:city":"Waverton",
    "sg:classifiers":[
        {
            "category":"Real Estate",
            "subcategory":"Architect",
            "type":"Services"
        }
    ],
    "sg:phone":"+61 2 9955 1466",
    "sg:postcode":"2060",
    "sg:province":"NSW",
    "wof:name":"Peter Hunt Architect",
    "wof:placetype":"venue"
},
  "geometry": {"coordinates":[151.196502686,-33.8381347656],"type":"Point"}
}