{
  "type": "Feature",
  "properties": {
    "addr:full":"24/ 97 Oaks Ave Dee Why NSW 2099",
    "addr:housenumber":"24 / 97",
    "addr:postcode":"2099",
    "addr:street":"Oaks Ave",
    "iso:country":"AU",
    "sg:address":"24/ 97 Oaks Ave",
    "sg:city":"Dee Why",
    "sg:classifiers":[
        {
            "category":"Professional",
            "subcategory":"Engineering",
            "type":"Services"
        }
    ],
    "sg:phone":"+61 405 309 639",
    "sg:postcode":"2099",
    "sg:province":"NSW",
    "sg:tags":[
        "consulting",
        "engineer"
    ],
    "wof:name":"IMD Concepts",
    "wof:placetype":"venue"
},
  "geometry": {"coordinates":[151.29351806599999,-33.7545890808],"type":"Point"}
}