{
  "type": "Feature",
  "properties": {
    "iso:country":"AU",
    "sg:address":"9 Ablehills Rd",
    "sg:city":"St Leonards",
    "sg:classifiers":[
        {
            "category":"Home & Garden",
            "subcategory":"Building Materials",
            "type":"Retail Goods"
        }
    ],
    "sg:phone":"+61 408 265 982",
    "sg:postcode":"7250",
    "sg:province":"TAS",
    "sg:tags":[
        "lawn",
        "cutting",
        "maintenance"
    ],
    "wof:name":"MJ Gleeson & Home Services",
    "wof:placetype":"venue"
},
  "geometry": {"coordinates":[147.198562622,-41.4528923035],"type":"Point"}
}