{
  "type": "Feature",
  "properties": {
    "addr:full":"233 Snowy Mountain Hwy Bega NSW 2550",
    "addr:housenumber":"233",
    "addr:postcode":"2550",
    "addr:street":"Snowy Mountain Hwy",
    "iso:country":"AU",
    "sg:address":"233 Snowy Mountain Hwy",
    "sg:city":"Bega",
    "sg:classifiers":[
        {
            "category":"Building & Trades",
            "subcategory":"Construction",
            "type":"Services"
        }
    ],
    "sg:phone":"+61 2 6492 0515",
    "sg:postcode":"2550",
    "sg:province":"NSW",
    "sg:tags":[
        "joinery"
    ],
    "wof:name":"Cooper Garry",
    "wof:placetype":"venue"
},
  "geometry": {"coordinates":[149.804397583,-36.6305503845],"type":"Point"}
}