{
  "type": "Feature",
  "properties": {
    "iso:country":"AU",
    "sg:address":"23 Killara St",
    "sg:city":"Currumbin Waters",
    "sg:classifiers":[
        {
            "category":"Utilities",
            "subcategory":"Electric",
            "type":"Services"
        }
    ],
    "sg:phone":"+61 7 5534 8111",
    "sg:postcode":"4223",
    "sg:province":"QLD",
    "sg:tags":[
        "electrical",
        "contractor"
    ],
    "wof:name":"Cabling & Contract Services",
    "wof:placetype":"venue"
},
  "geometry": {"coordinates":[153.45254516599999,-28.1479682922],"type":"Point"}
}