{
  "type": "Feature",
  "properties": {
    "iso:country":"AU",
    "sg:address":"12 Cheniston Rd",
    "sg:city":"Mt Macedon",
    "sg:classifiers":[
        {
            "category":"Building & Trades",
            "subcategory":"Construction",
            "type":"Services"
        }
    ],
    "sg:phone":"+61 3 5426 4223",
    "sg:postcode":"3441",
    "sg:province":"VIC",
    "sg:tags":[
        "joiner",
        "carpenter"
    ],
    "wof:name":"Carpentry & Renovations",
    "wof:placetype":"venue"
},
  "geometry": {"coordinates":[144.587493897,-37.4045639038],"type":"Point"}
}