{
  "type": "Feature",
  "properties": {
    "addr:full":"8- 10 Copernicus Way Keilor Downs VIC 3038",
    "addr:housenumber":"10",
    "addr:postcode":"3038",
    "addr:street":"8;Copernicus Way",
    "iso:country":"AU",
    "sg:address":"8- 10",
    "sg:city":"Copernicus Way Keilor Downs",
    "sg:classifiers":[
        {
            "category":"Health Services",
            "subcategory":"Dentist",
            "type":"Services"
        }
    ],
    "sg:phone":"+61 3 9366 8130",
    "sg:postcode":"3038",
    "sg:province":"VIC",
    "wof:name":"Keilor Downs Dental Surgery",
    "wof:placetype":"venue"
},
  "geometry": {"coordinates":[144.80604600000001,-37.723736],"type":"Point"}
}