{
  "type": "Feature",
  "properties": {
    "iso:country":"AU",
    "sg:address":"129 Princes Hwy",
    "sg:city":"Unanderra",
    "sg:classifiers":[
        {
            "category":"Personal",
            "subcategory":"Shoe Repair & Shine",
            "type":"Services"
        }
    ],
    "sg:phone":"+61 2 4272 4942",
    "sg:postcode":"2526",
    "sg:province":"NSW",
    "sg:tags":[
        "footwear"
    ],
    "wof:name":"Charlies Shoe Repairs",
    "wof:placetype":"venue"
},
  "geometry": {"coordinates":[150.844573975,-34.4554138184],"type":"Point"}
}