{
  "type": "Feature",
  "properties": {
    "addr:full":"PO Box 2401 Brookside Centre QLD 4053",
    "addr:postcode":"4053",
    "iso:country":"AU",
    "sg:address":"PO Box 2401",
    "sg:city":"Brookside Centre",
    "sg:classifiers":[
        {
            "category":"Building & Trades",
            "subcategory":"Cleaning & Sanitation",
            "type":"Services"
        }
    ],
    "sg:phone":"+61 7 3353 1994",
    "sg:postcode":"4053",
    "sg:province":"QLD",
    "sg:tags":[
        "industrial",
        "commercial",
        "contractor"
    ],
    "wof:name":"Jorge Cleaning Service",
    "wof:placetype":"venue"
},
  "geometry": {"coordinates":[152.97911071799999,-27.4088497162],"type":"Point"}
}