{
  "type": "Feature",
  "properties": {
    "addr:full":"Ste 1a, 132 Pacific Hwy Roseville NSW 2069",
    "addr:housenumber":"132",
    "addr:postcode":"2069",
    "addr:street":"Pacific Hwy",
    "iso:country":"AU",
    "sg:address":"Ste 1a, 132 Pacific Hwy",
    "sg:city":"Roseville",
    "sg:classifiers":[
        {
            "category":"Health Services",
            "subcategory":"Health Practitioner",
            "type":"Services"
        }
    ],
    "sg:phone":"+61 2 9416 5424",
    "sg:postcode":"2069",
    "sg:province":"NSW",
    "sg:tags":[
        "physiotherapist"
    ],
    "wof:name":"Powell T, McKenna C, Mussett A",
    "wof:placetype":"venue"
},
  "geometry": {"coordinates":[151.17593383799999,-33.783908844],"type":"Point"}
}