{
  "type": "Feature",
  "properties": {
    "addr:full":"82 Glendale Rd Glendale QLD 4711",
    "addr:housenumber":"82",
    "addr:postcode":"4711",
    "addr:street":"Glendale Rd",
    "iso:country":"AU",
    "sg:address":"82 Glendale Rd",
    "sg:city":"Glendale",
    "sg:classifiers":[
        {
            "category":"Building & Trades",
            "subcategory":"Landscaping Services",
            "type":"Services"
        }
    ],
    "sg:phone":"+61 419 905 979",
    "sg:postcode":"4711",
    "sg:province":"QLD",
    "sg:tags":[
        "slashing",
        "contractor"
    ],
    "wof:name":"Ivan's Excavator Hire Pty Ltd",
    "wof:placetype":"venue"
},
  "geometry": {"coordinates":[150.484832764,-23.2448673248],"type":"Point"}
}