{
  "type": "Feature",
  "properties": {
    "addr:full":"45 Coppin St Richmond VIC 3121",
    "addr:housenumber":"45",
    "addr:postcode":"3121",
    "addr:street":"Coppin St",
    "iso:country":"AU",
    "sg:address":"45 Coppin St",
    "sg:city":"Richmond",
    "sg:classifiers":[
        {
            "category":"Building & Trades",
            "subcategory":"Equipment Rental",
            "type":"Services"
        }
    ],
    "sg:phone":"+61 418 366 244",
    "sg:postcode":"3121",
    "sg:province":"VIC",
    "sg:tags":[
        "hire",
        "catering"
    ],
    "wof:name":"Caterent Pty Ltd",
    "wof:placetype":"venue"
},
  "geometry": {"coordinates":[145.003829956,-37.8198013306],"type":"Point"}
}