{
  "type": "Feature",
  "properties": {
    "addr:full":"Unit 11, 41 Fairfax St O&#039;Connor ACT 2602",
    "addr:housenumber":"41",
    "addr:postcode":"2602",
    "addr:street":"Fairfax St",
    "iso:country":"AU",
    "sg:address":"Unit 11, 41 Fairfax St",
    "sg:city":"O&#039;Connor",
    "sg:classifiers":[
        {
            "category":"Professional",
            "subcategory":"Art Services",
            "type":"Services"
        }
    ],
    "sg:phone":"+61 2 6257 5994",
    "sg:postcode":"2602",
    "sg:province":"ACT",
    "sg:tags":[
        "picture",
        "frame",
        "framing"
    ],
    "wof:name":"Wilderness Frames Australia",
    "wof:placetype":"venue"
},
  "geometry": {"coordinates":[149.10841369600001,-35.2595939636],"type":"Point"}
}