{
  "type": "Feature",
  "properties": {
    "addr:full":"170 Queens Pde Fitzroy North VIC 3068",
    "addr:housenumber":"170",
    "addr:postcode":"3068",
    "addr:street":"Queens Pde",
    "iso:country":"AU",
    "sg:address":"170 Queens Pde",
    "sg:city":"Fitzroy North",
    "sg:classifiers":[
        {
            "category":"Travel",
            "subcategory":"Hotels & Motels",
            "type":"Entertainment"
        }
    ],
    "sg:phone":"+61 3 9489 2861",
    "sg:postcode":"3068",
    "sg:province":"VIC",
    "sg:tags":[
        "accommodation"
    ],
    "wof:name":"Homestead Inn The Old",
    "wof:placetype":"venue"
},
  "geometry": {"coordinates":[144.99159240700001,-37.7886924744],"type":"Point"}
}