{
  "type": "Feature",
  "properties": {
    "addr:full":"Shop 1043 Westfields Hornsby NSW 2077",
    "addr:housenumber":"1043",
    "addr:postcode":"2077",
    "addr:street":"Westfields",
    "iso:country":"AU",
    "sg:address":"Shop 1043 Westfields",
    "sg:city":"Hornsby",
    "sg:classifiers":[
        {
            "category":"Health Services",
            "subcategory":"Doctor",
            "type":"Services"
        }
    ],
    "sg:phone":"+61 2 9476 6767",
    "sg:postcode":"2077",
    "sg:province":"NSW",
    "sg:tags":[
        "medical",
        "practitioner"
    ],
    "wof:name":"Hornsby Medical Centre",
    "wof:placetype":"venue"
},
  "geometry": {"coordinates":[151.09687805199999,-33.7007789612],"type":"Point"}
}