{
  "type": "Feature",
  "properties": {
    "iso:country":"AU",
    "sg:address":"58 Restwell St",
    "sg:city":"Bankstown",
    "sg:classifiers":[
        {
            "category":"Personal",
            "subcategory":"Beauty Salon",
            "type":"Services"
        }
    ],
    "sg:phone":"+61 2 9709 6159",
    "sg:postcode":"2200",
    "sg:province":"NSW",
    "sg:tags":[
        "hairdresser"
    ],
    "wof:name":"Hairy Thumbs",
    "wof:placetype":"venue"
},
  "geometry": {"coordinates":[151.03492700000001,-33.920963],"type":"Point"}
}