{
  "type": "Feature",
  "properties": {
    "addr:full":"Ksk10/ 206 Jull St Armadale WA 6112",
    "addr:housenumber":"206",
    "addr:postcode":"6112",
    "addr:street":"Jull St",
    "iso:country":"AU",
    "sg:address":"Ksk10/ 206 Jull St",
    "sg:city":"Armadale",
    "sg:classifiers":[
        {
            "category":"Fast Food",
            "type":"Food & Drink"
        }
    ],
    "sg:phone":"+61 8 9399 5504",
    "sg:postcode":"6112",
    "sg:province":"WA",
    "sg:tags":[
        "away",
        "take"
    ],
    "wof:name":"Fitchips Armadale",
    "wof:placetype":"venue"
},
  "geometry": {"coordinates":[116.020568848,-32.150226593],"type":"Point"}
}