{
  "type": "Feature",
  "properties": {
    "addr:full":"262 Williamson Rd Morayfield QLD 4506",
    "addr:housenumber":"262",
    "addr:postcode":"4506",
    "addr:street":"Williamson Rd",
    "iso:country":"AU",
    "sg:address":"262 Williamson Rd",
    "sg:city":"Morayfield",
    "sg:classifiers":[
        {
            "category":"Building & Trades",
            "subcategory":"Construction",
            "type":"Services"
        }
    ],
    "sg:phone":"+61 405 931 272",
    "sg:postcode":"4506",
    "sg:province":"QLD",
    "sg:tags":[
        "earth",
        "excavating",
        "moving",
        "contractor"
    ],
    "wof:name":"J & M Little Digger",
    "wof:placetype":"venue"
},
  "geometry": {"coordinates":[152.90965270999999,-27.1436386108],"type":"Point"}
}