{
  "type": "Feature",
  "properties": {
    "iso:country":"AU",
    "sg:address":"C & S Arcade First Ave",
    "sg:city":"Sawtell",
    "sg:classifiers":[
        {
            "category":"Fast Food",
            "type":"Food & Drink"
        }
    ],
    "sg:phone":"+61 2 6653 1969",
    "sg:postcode":"2452",
    "sg:province":"NSW",
    "sg:tags":[
        "away",
        "take"
    ],
    "wof:name":"Sawtell Seaside Seafood (VIVS)",
    "wof:placetype":"venue"
},
  "geometry": {"coordinates":[153.100204,-30.36904],"type":"Point"}
}