{
  "type": "Feature",
  "properties": {
    "addr:full":"PO Box 541 Epping NSW 1710",
    "addr:postcode":"1710",
    "iso:country":"AU",
    "sg:address":"PO Box 541",
    "sg:city":"Epping",
    "sg:classifiers":[
        {
            "category":"Real Estate",
            "subcategory":"Surveying",
            "type":"Services"
        }
    ],
    "sg:phone":"+61 2 9617 0013",
    "sg:postcode":"1710",
    "sg:province":"NSW",
    "sg:tags":[
        "surveyor",
        "quantity"
    ],
    "wof:name":"Knapman Associates",
    "wof:placetype":"venue"
},
  "geometry": {"coordinates":[151.08236694300001,-33.7725486755],"type":"Point"}
}