{
  "type": "Feature",
  "properties": {
    "addr:full":"36 Ridley Rd Woorree WA 6530",
    "addr:housenumber":"36",
    "addr:postcode":"6530",
    "addr:street":"Ridley Rd",
    "iso:country":"AU",
    "sg:address":"36 Ridley Rd",
    "sg:city":"Woorree",
    "sg:classifiers":[
        {
            "category":"Wholesale",
            "subcategory":"Farm Supplies",
            "type":"Manufacturing & Wholesale Goods"
        }
    ],
    "sg:phone":"+61 8 9921 2119",
    "sg:postcode":"6530",
    "sg:province":"WA",
    "sg:tags":[
        "material",
        "filtering"
    ],
    "wof:name":"H2Only",
    "wof:placetype":"venue"
},
  "geometry": {"coordinates":[114.669883728,-28.7644729614],"type":"Point"}
}