{
  "type": "Feature",
  "properties": {
    "iso:country":"AU",
    "sg:address":"Gorge Rd",
    "sg:city":"Cudlee Creek",
    "sg:classifiers":[
        {
            "category":"Building & Trades",
            "subcategory":"Construction",
            "type":"Services"
        }
    ],
    "sg:phone":"+61 8 8389 2341",
    "sg:postcode":"5232",
    "sg:province":"SA",
    "sg:tags":[
        "plasterboard",
        "plasterer",
        "fixer"
    ],
    "wof:name":"Holzer John S",
    "wof:placetype":"venue"
},
  "geometry": {"coordinates":[138.81480407699999,-34.8403015137],"type":"Point"}
}