{
  "type": "Feature",
  "properties": {
    "iso:country":"AU",
    "sg:address":"178 Baylis St",
    "sg:city":"Wagga Wagga",
    "sg:classifiers":[
        {
            "category":"Health Services",
            "subcategory":"Optometrist",
            "type":"Services"
        }
    ],
    "sg:phone":"+61 2 6931 7333",
    "sg:postcode":"2650",
    "sg:province":"NSW",
    "wof:name":"Mark Constantine",
    "wof:placetype":"venue"
},
  "geometry": {"coordinates":[147.3699646,-35.1120071411],"type":"Point"}
}