{
  "type": "Feature",
  "properties": {
    "addr:full":"176 Hawker St Quirindi NSW 2343",
    "addr:housenumber":"176",
    "addr:postcode":"2343",
    "addr:street":"Hawker St",
    "iso:country":"AU",
    "sg:address":"176 Hawker St",
    "sg:city":"Quirindi",
    "sg:classifiers":[
        {
            "category":"Utilities",
            "subcategory":"Water",
            "type":"Services"
        }
    ],
    "sg:phone":"+61 2 6746 2800",
    "sg:postcode":"2343",
    "sg:province":"NSW",
    "sg:tags":[
        "hot",
        "system"
    ],
    "wof:name":"N.W. Ritchie Electrical Service",
    "wof:placetype":"venue"
},
  "geometry": {"coordinates":[150.680786133,-31.4954986572],"type":"Point"}
}