{
  "type": "Feature",
  "properties": {
    "addr:full":"41 York St Singleton NSW 2330",
    "addr:housenumber":"41",
    "addr:postcode":"2330",
    "addr:street":"York St",
    "iso:country":"AU",
    "sg:address":"41 York St",
    "sg:city":"Singleton",
    "sg:classifiers":[
        {
            "category":"Building & Trades",
            "subcategory":"Cleaning & Sanitation",
            "type":"Services"
        }
    ],
    "sg:phone":"+61 2 6572 2185",
    "sg:postcode":"2330",
    "sg:province":"NSW",
    "sg:tags":[
        "industrial",
        "commercial",
        "contractor"
    ],
    "wof:name":"Capital Cleaning",
    "wof:placetype":"venue"
},
  "geometry": {"coordinates":[151.17146299999999,-32.567329],"type":"Point"}
}