{
  "type": "Feature",
  "properties": {
    "addr:full":"1/ 13 Anzac Rd Tuggerah NSW 2259",
    "addr:housenumber":"/ 13",
    "addr:postcode":"2259",
    "addr:street":"Anzac Rd",
    "iso:country":"AU",
    "sg:address":"1/ 13 Anzac Rd",
    "sg:city":"Tuggerah",
    "sg:classifiers":[
        {
            "category":"Retail",
            "subcategory":"Veterinary Services",
            "type":"Services"
        }
    ],
    "sg:phone":"+61 2 4353 9414",
    "sg:postcode":"2259",
    "sg:province":"NSW",
    "sg:tags":[
        "surgeon"
    ],
    "wof:name":"Onus, Victoria",
    "wof:placetype":"venue"
},
  "geometry": {"coordinates":[151.418167114,-33.3068580627],"type":"Point"}
}