{
  "type": "Feature",
  "properties": {
    "addr:full":"Spica St Southern Cross WA 6426",
    "addr:postcode":"6426",
    "addr:street":"Spica St",
    "iso:country":"AU",
    "sg:address":"Spica St",
    "sg:city":"Southern Cross",
    "sg:classifiers":[
        {
            "category":"Professional",
            "type":"Services"
        }
    ],
    "sg:phone":"+61 8 9049 1416",
    "sg:postcode":"6426",
    "sg:province":"WA",
    "sg:tags":[
        "industrial",
        "commercial",
        "catering"
    ],
    "wof:name":"Golden Valley Southern Cross",
    "wof:placetype":"venue"
},
  "geometry": {"coordinates":[119.330917,-31.232574],"type":"Point"}
}