{
  "type": "Feature",
  "properties": {
    "addr:full":"70 Belgrave St Kempsey NSW 2440",
    "addr:housenumber":"70",
    "addr:postcode":"2440",
    "addr:street":"Belgrave St",
    "iso:country":"AU",
    "sg:address":"70 Belgrave St",
    "sg:city":"Kempsey",
    "sg:classifiers":[
        {
            "category":"Utilities",
            "subcategory":"Electric",
            "type":"Services"
        }
    ],
    "sg:phone":"+61 2 6562 4525",
    "sg:postcode":"2440",
    "sg:province":"NSW",
    "sg:tags":[
        "electrical",
        "contractor"
    ],
    "wof:name":"Duyker & Co",
    "wof:placetype":"venue"
},
  "geometry": {"coordinates":[152.83987400000001,-31.080494],"type":"Point"}
}