{
  "type": "Feature",
  "properties": {
    "iso:country":"AU",
    "sg:address":"245 Windsor St",
    "sg:city":"Richmond",
    "sg:classifiers":[
        {
            "category":"Banks & Credit Unions",
            "subcategory":"Bank",
            "type":"Services"
        }
    ],
    "sg:phone":"+61 13 33 30",
    "sg:postcode":"2753",
    "sg:province":"NSW",
    "wof:name":"St.George Bank Limited.",
    "wof:placetype":"venue"
},
  "geometry": {"coordinates":[150.75010681099999,-33.5962486267],"type":"Point"}
}