{
  "type": "Feature",
  "properties": {
    "iso:country":"AU",
    "sg:address":"1 Duncan Pl",
    "sg:city":"Epping",
    "sg:classifiers":[
        {
            "category":"Health Services",
            "subcategory":"Health Practitioner",
            "type":"Services"
        }
    ],
    "sg:phone":"+61 2 9869 8578",
    "sg:postcode":"2121",
    "sg:province":"NSW",
    "sg:tags":[
        "psychologist"
    ],
    "wof:name":"Simmonds Derek",
    "wof:placetype":"venue"
},
  "geometry": {"coordinates":[151.07493591299999,-33.7757949829],"type":"Point"}
}