{
  "type": "Feature",
  "properties": {
    "iso:country":"AU",
    "sg:address":"35 Dalgety St",
    "sg:city":"Oakleigh",
    "sg:classifiers":[
        {
            "category":"Retail",
            "subcategory":"Auto Rental",
            "type":"Services"
        }
    ],
    "sg:phone":"+61 3 8506 2777",
    "sg:postcode":"3166",
    "sg:province":"VIC",
    "sg:tags":[
        "car",
        "hire",
        "minibus"
    ],
    "wof:name":"Quince's Self Drive Mini Buses Pty Ltd",
    "wof:placetype":"venue"
},
  "geometry": {"coordinates":[145.09332275400001,-37.8920249939],"type":"Point"}
}