{
  "type": "Feature",
  "properties": {
    "addr:full":"U2/ 4 New St Frankston VIC 3199",
    "addr:postcode":"3199",
    "addr:street":"U2 / 4 New St",
    "iso:country":"AU",
    "sg:address":"U2/ 4 New St",
    "sg:city":"Frankston",
    "sg:classifiers":[
        {
            "category":"Professional",
            "subcategory":"Computer Services",
            "type":"Services"
        }
    ],
    "sg:phone":"+61 3 9781 5277",
    "sg:postcode":"3199",
    "sg:province":"VIC",
    "sg:tags":[
        "tele-communications",
        "consultant"
    ],
    "wof:name":"Allecomm",
    "wof:placetype":"venue"
},
  "geometry": {"coordinates":[145.21945190400001,-37.9884300232],"type":"Point"}
}