{
  "type": "Feature",
  "properties": {
    "iso:country":"AU",
    "sg:address":"240 Fyansford-Gheringhap Rd",
    "sg:city":"Fyansford",
    "sg:classifiers":[
        {
            "category":"Manufacturing",
            "subcategory":"Rubber & Plastics",
            "type":"Manufacturing & Wholesale Goods"
        }
    ],
    "sg:phone":"+61 3 5222 2899",
    "sg:postcode":"3221",
    "sg:province":"VIC",
    "sg:tags":[
        "lime"
    ],
    "wof:name":"Geelong Lime",
    "wof:placetype":"venue"
},
  "geometry": {"coordinates":[144.288467,-38.138969],"type":"Point"}
}