{
  "type": "Feature",
  "properties": {
    "iso:country":"AU",
    "sg:address":"31 Manton Rd",
    "sg:city":"Oakleigh South",
    "sg:classifiers":[
        {
            "category":"Professional",
            "subcategory":"Accounting & Tax Preparation",
            "type":"Services"
        }
    ],
    "sg:phone":"+61 3 9562 7333",
    "sg:postcode":"3167",
    "sg:province":"VIC",
    "sg:tags":[
        "jukebox"
    ],
    "wof:name":"Vic Juke Entertainment",
    "wof:placetype":"venue"
},
  "geometry": {"coordinates":[145.11041259800001,-37.916431427],"type":"Point"}
}