{
  "type": "Feature",
  "properties": {
    "addr:full":"38 Victoria St Taree NSW 2430",
    "addr:housenumber":"38",
    "addr:postcode":"2430",
    "addr:street":"Victoria St",
    "iso:country":"AU",
    "sg:address":"38 Victoria St",
    "sg:city":"Taree",
    "sg:classifiers":[
        {
            "category":"Fast Food",
            "type":"Food & Drink"
        }
    ],
    "sg:phone":"+61 2 6552 5224",
    "sg:postcode":"2430",
    "sg:province":"NSW",
    "sg:tags":[
        "away",
        "take"
    ],
    "wof:name":"KFC",
    "wof:placetype":"venue"
},
  "geometry": {"coordinates":[152.46762100000001,-31.909533],"type":"Point"}
}