{
  "type": "Feature",
  "properties": {
    "addr:full":"24 Alexander Rd Avalon NSW 2107",
    "addr:housenumber":"24",
    "addr:postcode":"2107",
    "addr:street":"Alexander Rd",
    "iso:country":"AU",
    "sg:address":"24 Alexander Rd",
    "sg:city":"Avalon",
    "sg:classifiers":[
        {
            "category":"Building & Trades",
            "subcategory":"Construction",
            "type":"Services"
        }
    ],
    "sg:phone":"+61 422 168 410",
    "sg:postcode":"2107",
    "sg:province":"NSW",
    "sg:tags":[
        "renovation",
        "alterations",
        "extension",
        "contractor"
    ],
    "wof:name":"S. R. Kitchens & Bathrooms",
    "wof:placetype":"venue"
},
  "geometry": {"coordinates":[151.33651733400001,-33.6207389832],"type":"Point"}
}