{
  "type": "Feature",
  "properties": {
    "iso:country":"AU",
    "sg:address":"Cnr Kortum & Leda Drv",
    "sg:city":"West Burleigh",
    "sg:classifiers":[
        {
            "category":"Wholesale",
            "subcategory":"Electrical",
            "type":"Manufacturing & Wholesale Goods"
        }
    ],
    "sg:phone":"+61 7 5535 4211",
    "sg:postcode":"4219",
    "sg:province":"QLD",
    "sg:tags":[
        "wholesaler"
    ],
    "wof:name":"Haymans Electrical",
    "wof:placetype":"venue"
},
  "geometry": {"coordinates":[153.43121337900001,-28.1022491455],"type":"Point"}
}