{
  "type": "Feature",
  "properties": {
    "iso:country":"AU",
    "sg:address":"16 Colvin St",
    "sg:city":"Drayton",
    "sg:classifiers":[
        {
            "category":"Shopping",
            "subcategory":"Stationery & Office Supplies",
            "type":"Retail Goods"
        }
    ],
    "sg:phone":"+61 418 151 239",
    "sg:postcode":"4350",
    "sg:province":"QLD",
    "sg:tags":[
        "equipment",
        "dairy"
    ],
    "wof:name":"Downs Dairy Equipment Service",
    "wof:placetype":"venue"
},
  "geometry": {"coordinates":[151.913269,-27.5961],"type":"Point"}
}