{
  "type": "Feature",
  "properties": {
    "iso:country":"AU",
    "sg:address":"77 Corporation Ave",
    "sg:city":"Bathurst",
    "sg:classifiers":[
        {
            "category":"Banks & Credit Unions",
            "subcategory":"Bureau De Change",
            "type":"Services"
        }
    ],
    "sg:phone":"+61 2 6332 5244",
    "sg:postcode":"2795",
    "sg:province":"NSW",
    "sg:tags":[
        "equipment",
        "heat",
        "exchange"
    ],
    "wof:name":"Teralba Industries Fluid Process Equipment",
    "wof:placetype":"venue"
},
  "geometry": {"coordinates":[149.54318237300001,-33.413898468],"type":"Point"}
}