{
  "type": "Feature",
  "properties": {
    "addr:full":"4 Graham Rd Mt Gambier SA 5290",
    "addr:housenumber":"4",
    "addr:postcode":"5290",
    "addr:street":"Graham Rd",
    "iso:country":"AU",
    "sg:address":"4 Graham Rd",
    "sg:city":"Mt Gambier",
    "sg:classifiers":[
        {
            "category":"Wholesale",
            "subcategory":"Machinery & Supplies",
            "type":"Manufacturing & Wholesale Goods"
        }
    ],
    "sg:phone":"+61 8 8725 9011",
    "sg:postcode":"5290",
    "sg:province":"SA",
    "sg:tags":[
        "equipment",
        "welding"
    ],
    "wof:name":"BOC Gas & Gear",
    "wof:placetype":"venue"
},
  "geometry": {"coordinates":[140.75123600000001,-37.817318],"type":"Point"}
}