{
  "type": "Feature",
  "properties": {
    "iso:country":"AU",
    "sg:address":"Shop 5 The Atrium Cnr St Georges Tce & King",
    "sg:city":"Perth",
    "sg:classifiers":[
        {
            "category":"Health Services",
            "subcategory":"Dentist",
            "type":"Services"
        }
    ],
    "sg:phone":"+61 8 9321 1791",
    "sg:postcode":"6000",
    "sg:province":"WA",
    "wof:name":"King St Dental Centre",
    "wof:placetype":"venue"
},
  "geometry": {"coordinates":[115.854507446,-31.953414917],"type":"Point"}
}