{
  "type": "Feature",
  "properties": {
    "iso:country":"AU",
    "sg:address":"PO Box 18",
    "sg:city":"Kingston",
    "sg:classifiers":[
        {
            "category":"Building & Trades",
            "subcategory":"Pest Control",
            "type":"Services"
        }
    ],
    "sg:phone":"+61 438 295 744",
    "sg:postcode":"7050",
    "sg:province":"TAS",
    "wof:name":"Able Pest Control",
    "wof:placetype":"venue"
},
  "geometry": {"coordinates":[147.289917,-42.964359],"type":"Point"}
}