{
  "type": "Feature",
  "properties": {
    "addr:full":"90 Marconi Rd Morisset NSW 2264",
    "addr:housenumber":"90",
    "addr:postcode":"2264",
    "addr:street":"Marconi Rd",
    "iso:country":"AU",
    "sg:address":"90 Marconi Rd",
    "sg:city":"Morisset",
    "sg:classifiers":[
        {
            "category":"Building & Trades",
            "subcategory":"Plumbing",
            "type":"Services"
        }
    ],
    "sg:phone":"+61 2 4973 3226",
    "sg:postcode":"2264",
    "sg:province":"NSW",
    "sg:tags":[
        "plumber",
        "gasfitters"
    ],
    "wof:name":"Roxley Plumbing Pty Ltd",
    "wof:placetype":"venue"
},
  "geometry": {"coordinates":[151.50418099999999,-33.101326],"type":"Point"}
}