{
  "type": "Feature",
  "properties": {
    "iso:country":"AU",
    "sg:address":"43 Allen St",
    "sg:city":"South Townsville",
    "sg:classifiers":[
        {
            "category":"Health Services",
            "subcategory":"Health Practitioner",
            "type":"Services"
        }
    ],
    "sg:phone":"+61 7 4721 5344",
    "sg:postcode":"4810",
    "sg:province":"QLD",
    "sg:tags":[
        "hypnotherapy"
    ],
    "wof:name":"Hallows Rowena Dr Hypnotherapy",
    "wof:placetype":"venue"
},
  "geometry": {"coordinates":[146.827682,-19.264393],"type":"Point"}
}