{
  "type": "Feature",
  "properties": {
    "addr:full":"Shop 9, 1094-1118 Anzac Pde Maroubra NSW 2035",
    "addr:housenumber":"shop;1094-1118",
    "addr:postcode":"2035",
    "addr:street":"Anzac Pde",
    "iso:country":"AU",
    "sg:address":"Shop 9, 1094-1118 Anzac Pde",
    "sg:city":"Maroubra",
    "sg:classifiers":[
        {
            "category":"Utilities",
            "subcategory":"Telephone",
            "type":"Services"
        }
    ],
    "sg:phone":"+61 2 9311 0322",
    "sg:postcode":"2035",
    "sg:province":"NSW",
    "sg:tags":[
        "installation",
        "system",
        "maintenance"
    ],
    "wof:name":"Matrix Communication Services Pty Ltd",
    "wof:placetype":"venue"
},
  "geometry": {"coordinates":[151.242279053,-33.9524650574],"type":"Point"}
}