{
  "type": "Feature",
  "properties": {
    "iso:country":"AU",
    "sg:address":"88 Ellena St",
    "sg:city":"Maryborough",
    "sg:classifiers":[
        {
            "category":"Organizations",
            "subcategory":"Labor Organization",
            "type":"Services"
        }
    ],
    "sg:phone":"+61 7 4121 3230",
    "sg:postcode":"4650",
    "sg:province":"QLD",
    "sg:tags":[
        "union"
    ],
    "wof:name":"Australian Workers Union",
    "wof:placetype":"venue"
},
  "geometry": {"coordinates":[152.70077499999999,-25.539309],"type":"Point"}
}