{
  "type": "Feature",
  "properties": {
    "addr:full":"20 Gladstone St Moorooka QLD 4105",
    "addr:housenumber":"20",
    "addr:postcode":"4105",
    "addr:street":"Gladstone St",
    "iso:country":"AU",
    "sg:address":"20 Gladstone St",
    "sg:city":"Moorooka",
    "sg:classifiers":[
        {
            "category":"Utilities",
            "type":"Services"
        }
    ],
    "sg:phone":"+61 7 3276 8880",
    "sg:postcode":"4105",
    "sg:province":"QLD",
    "sg:tags":[
        "refrigeration",
        "industrial",
        "commercial",
        "retail"
    ],
    "wof:name":"Becon Catering Equipment",
    "wof:placetype":"venue"
},
  "geometry": {"coordinates":[153.01918029800001,-27.5448379517],"type":"Point"}
}