{
  "type": "Feature",
  "properties": {
    "addr:full":"334 New Cleveland Rd Tingalpa QLD 4173",
    "addr:housenumber":"334",
    "addr:postcode":"4173",
    "addr:street":"New Cleveland Rd",
    "iso:country":"AU",
    "sg:address":"334 New Cleveland Rd",
    "sg:city":"Tingalpa",
    "sg:classifiers":[
        {
            "category":"Transit Center",
            "subcategory":"Freight",
            "type":"Transportation"
        }
    ],
    "sg:phone":"+61 7 3390 8822",
    "sg:postcode":"4173",
    "sg:province":"QLD",
    "sg:tags":[
        "forklift",
        "truck"
    ],
    "wof:name":"Rapid/Lift",
    "wof:placetype":"venue"
},
  "geometry": {"coordinates":[153.13981628400001,-27.4816246033],"type":"Point"}
}