{
  "type": "Feature",
  "properties": {
    "addr:full":"88a Victoria St Smithfield NSW 2164",
    "addr:housenumber":"88a",
    "addr:postcode":"2164",
    "addr:street":"Victoria St",
    "iso:country":"AU",
    "sg:address":"88a Victoria St",
    "sg:city":"Smithfield",
    "sg:classifiers":[
        {
            "category":"Wholesale",
            "subcategory":"Auto Parts",
            "type":"Manufacturing & Wholesale Goods"
        }
    ],
    "sg:phone":"+61 2 9729 2316",
    "sg:postcode":"2164",
    "sg:province":"NSW",
    "sg:tags":[
        "recyclers"
    ],
    "wof:name":"Ultimate Jap Used Spares & Tyres",
    "wof:placetype":"venue"
},
  "geometry": {"coordinates":[150.93490600600001,-33.8504257202],"type":"Point"}
}