{
  "type": "Feature",
  "properties": {
    "iso:country":"AU",
    "sg:address":"296 Main South Rd",
    "sg:city":"Morphett Vale",
    "sg:classifiers":[
        {
            "category":"Building & Trades",
            "subcategory":"Plumbing",
            "type":"Services"
        }
    ],
    "sg:phone":"+61 8 8326 7100",
    "sg:postcode":"5162",
    "sg:province":"SA",
    "sg:tags":[
        "equipment",
        "valves"
    ],
    "wof:name":"Kirksey Corporation Pty Ltd",
    "wof:placetype":"venue"
},
  "geometry": {"coordinates":[138.522583008,-35.1159324646],"type":"Point"}
}