{
  "type": "Feature",
  "properties": {
    "addr:full":"154 South Rd Torrensville SA 5031",
    "addr:housenumber":"154",
    "addr:postcode":"5031",
    "addr:street":"South Rd",
    "iso:country":"AU",
    "sg:address":"154 South Rd",
    "sg:city":"Torrensville",
    "sg:classifiers":[
        {
            "category":"Manufacturing",
            "subcategory":"Food",
            "type":"Manufacturing & Wholesale Goods"
        }
    ],
    "sg:phone":"+61 8 8234 7666",
    "sg:postcode":"5031",
    "sg:province":"SA",
    "sg:tags":[
        "product",
        "nut",
        "edible"
    ],
    "wof:name":"SEB Sales & Marketing",
    "wof:placetype":"venue"
},
  "geometry": {"coordinates":[138.56939697300001,-34.9222488403],"type":"Point"}
}