{
  "type": "Feature",
  "properties": {
    "iso:country":"AU",
    "sg:address":"Unit 7/ 1 Nylex Ave",
    "sg:city":"Salisbury South",
    "sg:classifiers":[
        {
            "category":"Retail",
            "subcategory":"Car Wash",
            "type":"Services"
        }
    ],
    "sg:phone":"+61 8 8283 0439",
    "sg:postcode":"5106",
    "sg:province":"SA",
    "sg:tags":[
        "truck",
        "cleaning"
    ],
    "wof:name":"Final Touch Detailing",
    "wof:placetype":"venue"
},
  "geometry": {"coordinates":[138.64613299999999,-34.782696],"type":"Point"}
}