{
  "type": "Feature",
  "properties": {
    "iso:country":"AU",
    "sg:address":"44 Caramut Rd",
    "sg:city":"Warrnambool",
    "sg:classifiers":[
        {
            "category":"Utilities",
            "type":"Services"
        }
    ],
    "sg:phone":"+61 3 5561 1705",
    "sg:postcode":"3280",
    "sg:province":"VIC",
    "sg:tags":[
        "refrigeration",
        "industrial",
        "commercial",
        "retail"
    ],
    "wof:name":"West Fridge",
    "wof:placetype":"venue"
},
  "geometry": {"coordinates":[142.45950317399999,-38.3408432007],"type":"Point"}
}