{
  "type": "Feature",
  "properties": {
    "iso:country":"AU",
    "sg:address":"Shop 1 Orient St",
    "sg:city":"Batemans Bay",
    "sg:classifiers":[
        {
            "category":"Professional",
            "subcategory":"Printing & Photocopies",
            "type":"Services"
        }
    ],
    "sg:phone":"+61 2 4472 5811",
    "sg:postcode":"2536",
    "sg:province":"NSW",
    "sg:tags":[
        "rubber",
        "stamp",
        "metal"
    ],
    "wof:name":"Bay Office Supplies",
    "wof:placetype":"venue"
},
  "geometry": {"coordinates":[150.178222656,-35.7059669495],"type":"Point"}
}