{
  "type": "Feature",
  "properties": {
    "iso:country":"AU",
    "sg:address":"70 Raynham St",
    "sg:city":"Salisbury",
    "sg:classifiers":[
        {
            "category":"Home & Garden",
            "subcategory":"Building Materials",
            "type":"Retail Goods"
        }
    ],
    "sg:phone":"+61 7 3722 2711",
    "sg:postcode":"4107",
    "sg:province":"QLD",
    "sg:tags":[
        "ventilating",
        "equipment",
        "system"
    ],
    "wof:name":"A Approved Air Pty Ltd",
    "wof:placetype":"venue"
},
  "geometry": {"coordinates":[153.027175903,-27.5417098999],"type":"Point"}
}