{
  "type": "Feature",
  "properties": {
    "iso:country":"AU",
    "sg:address":"634 Frankston-Dandenong Rd",
    "sg:city":"Carrum Downs",
    "sg:classifiers":[
        {
            "category":"Industrial Area",
            "type":"Public Place"
        }
    ],
    "sg:phone":"+61 3 9782 6155",
    "sg:postcode":"3201",
    "sg:province":"VIC",
    "sg:tags":[
        "rural",
        "shed"
    ],
    "wof:name":"A & M Garages & Sheds",
    "wof:placetype":"venue"
},
  "geometry": {"coordinates":[145.177353,-38.093327],"type":"Point"}
}