{
  "type": "Feature",
  "properties": {
    "addr:full":"34 Slocombe St Goulburn NSW 2580",
    "addr:housenumber":"34",
    "addr:postcode":"2580",
    "addr:street":"Slocombe St",
    "iso:country":"AU",
    "sg:address":"34 Slocombe St",
    "sg:city":"Goulburn",
    "sg:classifiers":[
        {
            "category":"Health Services",
            "subcategory":"Health Practitioner",
            "type":"Services"
        }
    ],
    "sg:phone":"+61 2 4821 6161",
    "sg:postcode":"2580",
    "sg:province":"NSW",
    "sg:tags":[
        "acupuncture"
    ],
    "wof:name":"William White",
    "wof:placetype":"venue"
},
  "geometry": {"coordinates":[149.69229125999999,-34.755405426],"type":"Point"}
}