{
  "type": "Feature",
  "properties": {
    "addr:full":"6,28- 32 Lee Holm Rd St Marys NSW 2760",
    "addr:housenumber":"6,28 32",
    "addr:postcode":"2760",
    "addr:street":"Lee Holm Rd",
    "iso:country":"AU",
    "sg:address":"6,28- 32 Lee Holm Rd St",
    "sg:city":"Marys",
    "sg:classifiers":[
        {
            "category":"Building & Trades",
            "subcategory":"Construction",
            "type":"Services"
        }
    ],
    "sg:phone":"+61 2 9833 3328",
    "sg:postcode":"2760",
    "sg:province":"NSW",
    "sg:tags":[
        "builder",
        "designer",
        "room",
        "cool"
    ],
    "wof:name":"Retracom Insulated Panels",
    "wof:placetype":"venue"
},
  "geometry": {"coordinates":[150.769622803,-33.7510681152],"type":"Point"}
}