{
  "type": "Feature",
  "properties": {
    "iso:country":"AU",
    "sg:address":"26- 30 Warmatta St",
    "sg:city":"Finley",
    "sg:classifiers":[
        {
            "category":"Retail",
            "subcategory":"Auto Repair",
            "type":"Services"
        }
    ],
    "sg:phone":"+61 3 5883 1479",
    "sg:postcode":"2713",
    "sg:province":"NSW",
    "sg:tags":[
        "repairer",
        "motor",
        "engineer"
    ],
    "wof:name":"Repco Authorised Service",
    "wof:placetype":"venue"
},
  "geometry": {"coordinates":[145.57791137699999,-35.6419067383],"type":"Point"}
}