{
  "type": "Feature",
  "properties": {
    "iso:country":"AU",
    "sg:address":"25 Romany Pl",
    "sg:city":"Hoppers Crossing",
    "sg:classifiers":[
        {
            "category":"Building & Trades",
            "subcategory":"Construction",
            "type":"Services"
        }
    ],
    "sg:phone":"+61 3 9748 0234",
    "sg:postcode":"3029",
    "sg:province":"VIC",
    "sg:tags":[
        "contractor"
    ],
    "wof:name":"GDP Building Services",
    "wof:placetype":"venue"
},
  "geometry": {"coordinates":[144.67247,-37.859951],"type":"Point"}
}