{
  "type": "Feature",
  "properties": {
    "addr:full":"2/ 270 Pacific Hwy Crows Nest NSW 2065",
    "addr:housenumber":"/ 270",
    "addr:postcode":"2065",
    "addr:street":"Pacific Hwy",
    "iso:country":"AU",
    "sg:address":"2/ 270 Pacific Hwy",
    "sg:city":"Crows Nest",
    "sg:classifiers":[
        {
            "category":"Real Estate",
            "subcategory":"Surveying",
            "type":"Services"
        }
    ],
    "sg:phone":"+61 2 9906 1212",
    "sg:postcode":"2065",
    "sg:province":"NSW",
    "sg:tags":[
        "surveyor",
        "quantity"
    ],
    "wof:name":"Washington Brown Group",
    "wof:placetype":"venue"
},
  "geometry": {"coordinates":[151.198852539,-33.8254547119],"type":"Point"}
}