{
  "type": "Feature",
  "properties": {
    "addr:full":"Office: 200 Kensington Rd Marryatville SA 5068",
    "addr:postcode":"5068",
    "addr:street":"Kensington Rd",
    "iso:country":"AU",
    "sg:address":"Office: 200 Kensington Rd",
    "sg:city":"Marryatville",
    "sg:classifiers":[
        {
            "category":"Travel",
            "subcategory":"Hotels & Motels",
            "type":"Entertainment"
        }
    ],
    "sg:phone":"+61 408 855 582",
    "sg:postcode":"5068",
    "sg:province":"SA",
    "sg:tags":[
        "accommodation"
    ],
    "wof:name":"St. George Apartments",
    "wof:placetype":"venue"
},
  "geometry": {"coordinates":[138.64773559599999,-34.9267463684],"type":"Point"}
}