{
  "type": "Feature",
  "properties": {
    "addr:full":"Unit 3,104 Breakfast Creek Rd Newstead QLD 4006",
    "addr:postcode":"4006",
    "addr:street":"Breakfast Creek Rd",
    "iso:country":"AU",
    "sg:address":"Unit 3,104 Breakfast Creek Rd",
    "sg:city":"Newstead",
    "sg:classifiers":[
        {
            "category":"Social Services",
            "subcategory":"Job Training",
            "type":"Services"
        }
    ],
    "sg:phone":"+61 7 3257 3566",
    "sg:postcode":"4006",
    "sg:province":"QLD",
    "sg:tags":[
        "hire",
        "computer",
        "leasing"
    ],
    "wof:name":"Instrumentation & Computer Rentals Pty Ltd",
    "wof:placetype":"venue"
},
  "geometry": {"coordinates":[153.04237365700001,-27.445936203],"type":"Point"}
}