{
  "type": "Feature",
  "properties": {
    "addr:full":"56 Murray St Gawler SA 5118",
    "addr:housenumber":"56",
    "addr:postcode":"5118",
    "addr:street":"Murray St",
    "iso:country":"AU",
    "sg:address":"56 Murray St",
    "sg:city":"Gawler",
    "sg:classifiers":[
        {
            "category":"Health Services",
            "subcategory":"Optometrist",
            "type":"Services"
        }
    ],
    "sg:phone":"+61 8 8522 1580",
    "sg:postcode":"5118",
    "sg:province":"SA",
    "wof:name":"Ames Robert",
    "wof:placetype":"venue"
},
  "geometry": {"coordinates":[138.748886,-34.596325],"type":"Point"}
}