{
  "type": "Feature",
  "properties": {
    "iso:country":"AU",
    "sg:address":"12 Atherton St",
    "sg:city":"Buranda",
    "sg:classifiers":[
        {
            "category":"Retail",
            "subcategory":"Auto Repair",
            "type":"Services"
        }
    ],
    "sg:phone":"+61 7 3217 3649",
    "sg:postcode":"4102",
    "sg:province":"QLD",
    "sg:tags":[
        "repairer",
        "motor",
        "engineer"
    ],
    "wof:name":"Lyons",
    "wof:placetype":"venue"
},
  "geometry": {"coordinates":[153.04728698700001,-27.4937725067],"type":"Point"}
}