{
  "type": "Feature",
  "properties": {
    "iso:country":"AU",
    "sg:address":"31 Coal Rd",
    "sg:city":"Chuwar",
    "sg:classifiers":[
        {
            "category":"Building & Trades",
            "subcategory":"Plumbing",
            "type":"Services"
        }
    ],
    "sg:phone":"+61 417 723 404",
    "sg:postcode":"4306",
    "sg:province":"QLD",
    "sg:tags":[
        "plumber",
        "gasfitters"
    ],
    "wof:name":"Andrew Marler Plumbing",
    "wof:placetype":"venue"
},
  "geometry": {"coordinates":[152.78477477999999,-27.5711193085],"type":"Point"}
}