{
  "type": "Feature",
  "properties": {
    "iso:country":"AU",
    "sg:address":"12 Broome Pl",
    "sg:city":"Bligh Park",
    "sg:classifiers":[
        {
            "category":"Real Estate",
            "subcategory":"Architect",
            "type":"Services"
        }
    ],
    "sg:phone":"+61 2 4572 5873",
    "sg:postcode":"2756",
    "sg:province":"NSW",
    "sg:tags":[
        "building",
        "designer"
    ],
    "wof:name":"Nu-Dezines And Building Services",
    "wof:placetype":"venue"
},
  "geometry": {"coordinates":[150.79310607900001,-33.6359901428],"type":"Point"}
}