{
  "type": "Feature",
  "properties": {
    "addr:full":"Willows Rd Tolga QLD 4882",
    "addr:postcode":"4882",
    "addr:street":"Willows Rd",
    "iso:country":"AU",
    "sg:address":"Willows Rd",
    "sg:city":"Tolga",
    "sg:classifiers":[
        {
            "category":"Farming",
            "subcategory":"Fish & Marine Products",
            "type":"Manufacturing & Wholesale Goods"
        }
    ],
    "sg:phone":"+61 407 113 233",
    "sg:postcode":"4882",
    "sg:province":"QLD",
    "sg:tags":[
        "organic"
    ],
    "wof:name":"Living Rock",
    "wof:placetype":"venue"
},
  "geometry": {"coordinates":[145.48789977999999,-17.2067089081],"type":"Point"}
}