{
  "type": "Feature",
  "properties": {
    "addr:full":"12 Japura Pl Kearns NSW 2558",
    "addr:housenumber":"12",
    "addr:postcode":"2558",
    "addr:street":"Japura Pl",
    "iso:country":"AU",
    "sg:address":"12 Japura Pl",
    "sg:city":"Kearns",
    "sg:classifiers":[
        {
            "category":"Education",
            "subcategory":"Special Training",
            "type":"Public Place"
        }
    ],
    "sg:phone":"+61 2 9820 2935",
    "sg:postcode":"2558",
    "sg:province":"NSW",
    "sg:tags":[
        "tuition-educational"
    ],
    "wof:name":"Kip McGrath Education Centre (Campbelltown)",
    "wof:placetype":"venue"
},
  "geometry": {"coordinates":[150.802490234,-34.0195541382],"type":"Point"}
}