{
  "type": "Feature",
  "properties": {
    "addr:full":"9 Kessling Ave Kunda Park QLD 4556",
    "addr:housenumber":"9",
    "addr:postcode":"4556",
    "addr:street":"Kessling Ave Kunda",
    "iso:country":"AU",
    "sg:address":"9 Kessling Ave",
    "sg:city":"Kunda Park",
    "sg:classifiers":[
        {
            "category":"Utilities",
            "subcategory":"Fuel Oil & Lpg",
            "type":"Services"
        }
    ],
    "sg:phone":"+61 1300 667 202",
    "sg:postcode":"4556",
    "sg:province":"QLD",
    "sg:tags":[
        "merchant"
    ],
    "wof:name":"Flexitanker Australia",
    "wof:placetype":"venue"
},
  "geometry": {"coordinates":[153.031448364,-26.6677951813],"type":"Point"}
}