{
  "type": "Feature",
  "properties": {
    "iso:country":"AU",
    "sg:address":"Shop 9 Dunsborough Park Shpng Cntr 28-32 Dunn Bay Rd",
    "sg:city":"Dunsborough",
    "sg:classifiers":[
        {
            "category":"Deli",
            "type":"Food & Drink"
        }
    ],
    "sg:phone":"+61 8 9759 1877",
    "sg:postcode":"6281",
    "sg:province":"WA",
    "sg:tags":[
        "delicatessen"
    ],
    "wof:name":"The Food Farmacy",
    "wof:placetype":"venue"
},
  "geometry": {"coordinates":[115.102363586,-33.617225647],"type":"Point"}
}