{
  "type": "Feature",
  "properties": {
    "addr:full":"95 Warrandyte Rd Templestowe VIC 3106",
    "addr:housenumber":"95",
    "addr:postcode":"3106",
    "addr:street":"Warrandyte Rd",
    "iso:country":"AU",
    "sg:address":"95 Warrandyte Rd",
    "sg:city":"Templestowe",
    "sg:classifiers":[
        {
            "category":"Home & Garden",
            "subcategory":"Garden Supply",
            "type":"Retail Goods"
        }
    ],
    "sg:phone":"+61 3 9846 4877",
    "sg:postcode":"3106",
    "sg:province":"VIC",
    "sg:tags":[
        "equipment"
    ],
    "wof:name":"Aumann's Building & Garden Supplies",
    "wof:placetype":"venue"
},
  "geometry": {"coordinates":[145.16557312,-37.7504463196],"type":"Point"}
}