{
  "type": "Feature",
  "properties": {
    "addr:full":"8 Berkshire Rd Sunshine North VIC 3020",
    "addr:housenumber":"8",
    "addr:postcode":"3020",
    "addr:street":"Berkshire Rd",
    "iso:country":"AU",
    "sg:address":"8 Berkshire Rd",
    "sg:city":"Sunshine North",
    "sg:classifiers":[
        {
            "category":"Autos & Motor Vehicles",
            "subcategory":"Automobile Sales",
            "type":"Retail Goods"
        }
    ],
    "sg:phone":"+61 3 9311 3631",
    "sg:postcode":"3020",
    "sg:province":"VIC",
    "sg:tags":[
        "equipment",
        "trailer"
    ],
    "wof:name":"Sunshine Trailers",
    "wof:placetype":"venue"
},
  "geometry": {"coordinates":[144.84582499999999,-37.765846],"type":"Point"}
}