{
  "type": "Feature",
  "properties": {
    "addr:full":"29 Heathfield Rd Brighton East VIC 3187",
    "addr:housenumber":"29",
    "addr:postcode":"3187",
    "addr:street":"Heathfield Rd",
    "iso:country":"AU",
    "sg:address":"29 Heathfield Rd",
    "sg:city":"Brighton East",
    "sg:classifiers":[
        {
            "category":"Health Services",
            "subcategory":"Health Practitioner",
            "type":"Services"
        }
    ],
    "sg:phone":"+61 417 594 575",
    "sg:postcode":"3187",
    "sg:province":"VIC",
    "sg:tags":[
        "psychologist"
    ],
    "wof:name":"Wilkinson Janet",
    "wof:placetype":"venue"
},
  "geometry": {"coordinates":[145.008666992,-37.9273414612],"type":"Point"}
}