{
  "type": "Feature",
  "properties": {
    "addr:full":"63 McConnell St Bulimba QLD 4171",
    "addr:housenumber":"63",
    "addr:postcode":"4171",
    "addr:street":"Mcconnell St",
    "iso:country":"AU",
    "sg:address":"63 McConnell St",
    "sg:city":"Bulimba",
    "sg:classifiers":[
        {
            "category":"Retail",
            "subcategory":"Event Space",
            "type":"Services"
        }
    ],
    "sg:phone":"+61 7 3399 1302",
    "sg:postcode":"4171",
    "sg:province":"QLD",
    "sg:tags":[
        "venue",
        "reception",
        "wedding"
    ],
    "wof:name":"Brisbane 18 Footers Sailing Club Inc.",
    "wof:placetype":"venue"
},
  "geometry": {"coordinates":[153.056716919,-27.4426689148],"type":"Point"}
}