{
  "type": "Feature",
  "properties": {
    "addr:full":"479 Pacific Hwy Artarmon NSW 2064",
    "addr:housenumber":"479",
    "addr:postcode":"2064",
    "addr:street":"Pacific Hwy",
    "iso:country":"AU",
    "sg:address":"479 Pacific Hwy",
    "sg:city":"Artarmon",
    "sg:classifiers":[
        {
            "category":"Arts & Performance",
            "subcategory":"Art Gallery",
            "type":"Entertainment"
        }
    ],
    "sg:phone":"+61 2 9427 0322",
    "sg:postcode":"2064",
    "sg:province":"NSW",
    "wof:name":"Artarmon Galleries",
    "wof:placetype":"venue"
},
  "geometry": {"coordinates":[151.17732238799999,-33.8104286194],"type":"Point"}
}