{
  "type": "Feature",
  "properties": {
    "addr:full":"208 Elizabeth St Urangan QLD 4655",
    "addr:housenumber":"208",
    "addr:postcode":"4655",
    "addr:street":"Elizabeth St",
    "iso:country":"AU",
    "sg:address":"208 Elizabeth St",
    "sg:city":"Urangan",
    "sg:classifiers":[
        {
            "category":"Fast Food",
            "type":"Food & Drink"
        }
    ],
    "sg:phone":"+61 7 4125 1055",
    "sg:postcode":"4655",
    "sg:province":"QLD",
    "sg:tags":[
        "away",
        "take"
    ],
    "wof:name":"Anny's Takeaway & Convenient Store",
    "wof:placetype":"venue"
},
  "geometry": {"coordinates":[152.888184,-25.303156],"type":"Point"}
}