{
  "type": "Feature",
  "properties": {
    "iso:country":"AU",
    "sg:address":"9 Wattle St",
    "sg:city":"Kallangur",
    "sg:classifiers":[
        {
            "category":"Personal",
            "subcategory":"Nail Salon",
            "type":"Services"
        }
    ],
    "sg:phone":"+61 7 3293 0332",
    "sg:postcode":"4503",
    "sg:province":"QLD",
    "sg:tags":[
        "artificial"
    ],
    "wof:name":"Carleys Nail Cottage",
    "wof:placetype":"venue"
},
  "geometry": {"coordinates":[152.98023986800001,-27.2565097809],"type":"Point"}
}