{
  "type": "Feature",
  "properties": {
    "iso:country":"AU",
    "sg:address":"Bedulluck Barton Hwy",
    "sg:city":"Hall",
    "sg:classifiers":[
        {
            "category":"Utilities",
            "subcategory":"Refuse",
            "type":"Services"
        }
    ],
    "sg:phone":"+61 2 6230 2735",
    "sg:postcode":"2618",
    "sg:province":"ACT",
    "sg:tags":[
        "remover",
        "rubbish"
    ],
    "wof:name":"All Type Disposals",
    "wof:placetype":"venue"
},
  "geometry": {"coordinates":[149.06236267099999,-35.1742134094],"type":"Point"}
}