{
  "type": "Feature",
  "properties": {
    "iso:country":"AU",
    "sg:address":"206 Adair St",
    "sg:city":"Ballarat",
    "sg:classifiers":[
        {
            "category":"Retail",
            "subcategory":"Repair Shop",
            "type":"Services"
        }
    ],
    "sg:phone":"+61 3 5335 8250",
    "sg:postcode":"3350",
    "sg:province":"VIC",
    "sg:tags":[
        "leadlights"
    ],
    "wof:name":"Ballarat Security Leadlights",
    "wof:placetype":"venue"
},
  "geometry": {"coordinates":[143.83226,-37.5746],"type":"Point"}
}