{
  "type": "Feature",
  "properties": {
    "addr:full":"12 Belmont Ave Belmont WA 6104",
    "addr:housenumber":"12",
    "addr:postcode":"6104",
    "addr:street":"Belmont Ave",
    "iso:country":"AU",
    "sg:address":"12 Belmont Ave",
    "sg:city":"Belmont",
    "sg:classifiers":[
        {
            "category":"Restaurant",
            "type":"Food & Drink"
        }
    ],
    "sg:phone":"+61 8 9277 2918",
    "sg:postcode":"6104",
    "sg:province":"WA",
    "wof:name":"Colin Ho",
    "wof:placetype":"venue"
},
  "geometry": {"coordinates":[115.91844940199999,-31.9531135559],"type":"Point"}
}