{
  "type": "Feature",
  "properties": {
    "addr:full":"U1/ 10 Blackbutt Rd Port Macquarie NSW 2444",
    "addr:postcode":"2444",
    "addr:street":"U1 / 10 Blackbutt Rd",
    "iso:country":"AU",
    "sg:address":"U1/ 10 Blackbutt Rd",
    "sg:city":"Port Macquarie",
    "sg:classifiers":[
        {
            "category":"Food & Beverages",
            "subcategory":"Bakery",
            "type":"Retail Goods"
        }
    ],
    "sg:phone":"+61 2 6581 2177",
    "sg:postcode":"2444",
    "sg:province":"NSW",
    "sg:tags":[
        "baker"
    ],
    "wof:name":"Timbertown Wholesale Pies",
    "wof:placetype":"venue"
},
  "geometry": {"coordinates":[152.88853499999999,-31.451305],"type":"Point"}
}