{
  "type": "Feature",
  "properties": {
    "iso:country":"AU",
    "sg:address":"259 Whitehorse Rd",
    "sg:city":"Balwyn",
    "sg:classifiers":[
        {
            "category":"Professional",
            "subcategory":"Accounting & Tax Preparation",
            "type":"Services"
        }
    ],
    "sg:phone":"+61 3 9880 4900",
    "sg:postcode":"3103",
    "sg:province":"VIC",
    "sg:tags":[
        "accountant",
        "auditor"
    ],
    "wof:name":"K M S Financial Solutions",
    "wof:placetype":"venue"
},
  "geometry": {"coordinates":[145.077392578,-37.8122253418],"type":"Point"}
}