{
  "type": "Feature",
  "properties": {
    "addr:full":"5 Young St Devonport East TAS 7310",
    "addr:housenumber":"5",
    "addr:postcode":"7310",
    "addr:street":"Young St",
    "iso:country":"AU",
    "sg:address":"5 Young St",
    "sg:city":"Devonport East",
    "sg:classifiers":[
        {
            "category":"Retail",
            "subcategory":"Auto Repair",
            "type":"Services"
        }
    ],
    "sg:phone":"+61 3 6427 8633",
    "sg:postcode":"7310",
    "sg:province":"TAS",
    "sg:tags":[
        "repairer",
        "motor",
        "engineer"
    ],
    "wof:name":"Eastside Service Centre",
    "wof:placetype":"venue"
},
  "geometry": {"coordinates":[146.37059020999999,-41.1884422302],"type":"Point"}
}