{
  "type": "Feature",
  "properties": {
    "addr:full":"Verrall Cres Berri SA 5343",
    "addr:postcode":"5343",
    "addr:street":"Verrall Cres",
    "iso:country":"AU",
    "sg:address":"Verrall Cres",
    "sg:city":"Berri",
    "sg:classifiers":[
        {
            "category":"Retail",
            "subcategory":"Storage",
            "type":"Services"
        }
    ],
    "sg:phone":"+61 8 8582 2744",
    "sg:postcode":"5343",
    "sg:province":"SA",
    "sg:tags":[
        "removal",
        "furniture"
    ],
    "wof:name":"Riverland Self Storage",
    "wof:placetype":"venue"
},
  "geometry": {"coordinates":[140.60096740700001,-34.2857398987],"type":"Point"}
}