{
  "type": "Feature",
  "properties": {
    "addr:full":"338 Elizabeth Drv Mt Pritchard NSW 2170",
    "addr:housenumber":"338",
    "addr:postcode":"2170",
    "addr:street":"Elizabeth Drv;Pritchard",
    "iso:country":"AU",
    "sg:address":"338 Elizabeth Drv",
    "sg:city":"Mt Pritchard",
    "sg:classifiers":[
        {
            "category":"Freight",
            "type":"Transportation"
        }
    ],
    "sg:phone":"+61 2 8786 0866",
    "sg:postcode":"2170",
    "sg:province":"NSW",
    "sg:tags":[
        "transport",
        "refrigerated"
    ],
    "wof:name":"The Cool Movers",
    "wof:placetype":"venue"
},
  "geometry": {"coordinates":[150.89729309099999,-33.9040641785],"type":"Point"}
}