{
  "type": "Feature",
  "properties": {
    "iso:country":"AU",
    "sg:address":"508 Kooyong Rd",
    "sg:city":"Caulfield South",
    "sg:classifiers":[
        {
            "category":"Health Services",
            "subcategory":"Health Practitioner",
            "type":"Services"
        }
    ],
    "sg:phone":"+61 3 9596 3398",
    "sg:postcode":"3162",
    "sg:province":"VIC",
    "sg:tags":[
        "acupuncture"
    ],
    "wof:name":"Feng Richard",
    "wof:placetype":"venue"
},
  "geometry": {"coordinates":[145.01272582999999,-37.8987045288],"type":"Point"}
}