{
  "type": "Feature",
  "properties": {
    "addr:full":"Shop 2/ 623 Military Rd Mosman NSW 2088",
    "addr:housenumber":"shop 2 / 623",
    "addr:postcode":"2088",
    "addr:street":"Military Rd",
    "iso:country":"AU",
    "sg:address":"Shop 2/ 623 Military Rd",
    "sg:city":"Mosman",
    "sg:classifiers":[
        {
            "category":"Shopping",
            "subcategory":"Clothing, Apparel, & Fashions",
            "type":"Retail Goods"
        }
    ],
    "sg:phone":"+61 2 9969 6943",
    "sg:postcode":"2088",
    "sg:province":"NSW",
    "sg:tags":[
        "lady",
        "wear"
    ],
    "wof:name":"Simona",
    "wof:placetype":"venue"
},
  "geometry": {"coordinates":[151.242553711,-33.825378418],"type":"Point"}
}