{
  "type": "Feature",
  "properties": {
    "addr:full":"4/ 7 Marchesi St Kewdale WA 6105",
    "addr:housenumber":"/ 7",
    "addr:postcode":"6105",
    "addr:street":"Marchesi St",
    "iso:country":"AU",
    "sg:address":"4/ 7 Marchesi St",
    "sg:city":"Kewdale",
    "sg:classifiers":[
        {
            "category":"Building & Trades",
            "subcategory":"Construction",
            "type":"Services"
        }
    ],
    "sg:phone":"+61 8 9353 2222",
    "sg:postcode":"6105",
    "sg:province":"WA",
    "sg:tags":[
        "equipment",
        "balancing"
    ],
    "wof:name":"Advanced Driveshaft Services Pty Ltd",
    "wof:placetype":"venue"
},
  "geometry": {"coordinates":[115.960403442,-31.9780464172],"type":"Point"}
}