{
  "type": "Feature",
  "properties": {
    "iso:country":"AU",
    "sg:address":"17 Scott Crs",
    "sg:city":"Mildura",
    "sg:classifiers":[
        {
            "category":"Military Area",
            "subcategory":"Air Force Base",
            "type":"Public Place"
        }
    ],
    "sg:phone":"+61 3 5023 3495",
    "sg:postcode":"3500",
    "sg:province":"VIC",
    "sg:tags":[
        "box",
        "case",
        "wood"
    ],
    "wof:name":"SCM Bins & Pallets",
    "wof:placetype":"venue"
},
  "geometry": {"coordinates":[142.154098511,-34.2107391357],"type":"Point"}
}