{
  "type": "Feature",
  "properties": {
    "addr:full":"1a Auckland St North Perth WA 6006",
    "addr:housenumber":"1a",
    "addr:postcode":"6006",
    "addr:street":"Auckland St",
    "iso:country":"AU",
    "sg:address":"1a Auckland St",
    "sg:city":"North Perth",
    "sg:classifiers":[
        {
            "category":"Retail",
            "subcategory":"Auto Repair",
            "type":"Services"
        }
    ],
    "sg:phone":"+61 8 9444 1595",
    "sg:postcode":"6006",
    "sg:province":"WA",
    "sg:tags":[
        "electrical"
    ],
    "wof:name":"Tosi Auto Electrics",
    "wof:placetype":"venue"
},
  "geometry": {"coordinates":[115.847412109,-31.9241046906],"type":"Point"}
}