{
  "type": "Feature",
  "properties": {
    "iso:country":"AU",
    "sg:address":"42 Rudloc Rd",
    "sg:city":"Morley",
    "sg:classifiers":[
        {
            "category":"Professional",
            "subcategory":"Management & Consulting",
            "type":"Services"
        }
    ],
    "sg:phone":"+61 8 9275 7999",
    "sg:postcode":"6062",
    "sg:province":"WA",
    "sg:tags":[
        "consultant",
        "educational"
    ],
    "wof:name":"Eastern Suburbs Literacy Group",
    "wof:placetype":"venue"
},
  "geometry": {"coordinates":[115.894989014,-31.9031085968],"type":"Point"}
}