{
  "type": "Feature",
  "properties": {
    "addr:full":"4/ 276 Byrnes St Mareeba QLD 4880",
    "addr:housenumber":"/ 276",
    "addr:postcode":"4880",
    "addr:street":"Byrnes St",
    "iso:country":"AU",
    "sg:address":"4/ 276 Byrnes St",
    "sg:city":"Mareeba",
    "sg:classifiers":[
        {
            "category":"Retail",
            "subcategory":"Repair Shop",
            "type":"Services"
        }
    ],
    "sg:phone":"+61 7 4092 4999",
    "sg:postcode":"4880",
    "sg:province":"QLD",
    "sg:tags":[
        "windscreen"
    ],
    "wof:name":"Smith's Windscreens",
    "wof:placetype":"venue"
},
  "geometry": {"coordinates":[145.42341613799999,-17.0017642975],"type":"Point"}
}