{
  "type": "Feature",
  "properties": {
    "addr:full":"Myall Rd Casula NSW 2170",
    "addr:postcode":"2170",
    "addr:street":"Myall Rd",
    "iso:country":"AU",
    "sg:address":"Myall Rd",
    "sg:city":"Casula",
    "sg:classifiers":[
        {
            "category":"Education",
            "subcategory":"School",
            "type":"Public Place"
        }
    ],
    "sg:phone":"+61 2 9602 4320",
    "sg:postcode":"2170",
    "sg:province":"NSW",
    "sg:tags":[
        "state",
        "-",
        "nsw"
    ],
    "wof:name":"Casula High School",
    "wof:placetype":"venue"
},
  "geometry": {"coordinates":[150.89825439399999,-33.9534416199],"type":"Point"}
}