{
  "type": "Feature",
  "properties": {
    "iso:country":"AU",
    "sg:address":"9 Osmond St",
    "sg:city":"Maitland",
    "sg:classifiers":[
        {
            "category":"Commercial Area",
            "type":"Public Place"
        }
    ],
    "sg:phone":"+61 8 8832 2165",
    "sg:postcode":"5573",
    "sg:province":"SA",
    "sg:tags":[
        "heavy",
        "carrier"
    ],
    "wof:name":"Thomas Luke Transport: Bulk Carriers",
    "wof:placetype":"venue"
},
  "geometry": {"coordinates":[137.677658081,-34.369556427],"type":"Point"}
}