{
  "type": "Feature",
  "properties": {
    "iso:country":"AU",
    "sg:address":"Unit 5/ 349 Geelong Rd",
    "sg:city":"Footscray West",
    "sg:classifiers":[
        {
            "category":"Professional",
            "subcategory":"Art Services",
            "type":"Services"
        }
    ],
    "sg:phone":"+61 415 906 854",
    "sg:postcode":"3012",
    "sg:province":"VIC",
    "sg:tags":[
        "decorator",
        "painter"
    ],
    "wof:name":"Bayview Master Painters",
    "wof:placetype":"venue"
},
  "geometry": {"coordinates":[144.87648010300001,-37.8077163696],"type":"Point"}
}