{
  "type": "Feature",
  "properties": {
    "addr:full":"U1/ 33 Edina Rd Ferntree Gully VIC 3156",
    "addr:housenumber":"33",
    "addr:postcode":"3156",
    "addr:street":"U1 /;Edina Rd",
    "iso:country":"AU",
    "sg:address":"U1/ 33 Edina Rd",
    "sg:city":"Ferntree Gully",
    "sg:classifiers":[
        {
            "category":"Professional",
            "subcategory":"Art Services",
            "type":"Services"
        }
    ],
    "sg:phone":"+61 3 9758 3009",
    "sg:postcode":"3156",
    "sg:province":"VIC",
    "sg:tags":[
        "picture",
        "frame",
        "framing"
    ],
    "wof:name":"Kiah Framing Gallery",
    "wof:placetype":"venue"
},
  "geometry": {"coordinates":[145.28135681099999,-37.8751411438],"type":"Point"}
}