{
  "type": "Feature",
  "properties": {
    "iso:country":"AU",
    "sg:address":"341 Coventry St",
    "sg:city":"South Melbourne",
    "sg:classifiers":[
        {
            "category":"Organizations",
            "subcategory":"Membership Organization",
            "type":"Services"
        }
    ],
    "sg:phone":"+61 419 204 811",
    "sg:postcode":"3205",
    "sg:province":"VIC",
    "sg:tags":[
        "support",
        "health",
        "organisation"
    ],
    "wof:name":"Needle Syringe Program South of the Yarra Mobile",
    "wof:placetype":"venue"
},
  "geometry": {"coordinates":[144.956039,-37.833164],"type":"Point"}
}