{
  "type": "Feature",
  "properties": {
    "addr:full":"Shp3/ 170 Macquarie Rd Springwood NSW 2777",
    "addr:housenumber":"170",
    "addr:postcode":"2777",
    "addr:street":"Macquarie Rd",
    "iso:country":"AU",
    "sg:address":"Shp3/ 170 Macquarie Rd",
    "sg:city":"Springwood",
    "sg:classifiers":[
        {
            "category":"Cafe",
            "type":"Food & Drink"
        }
    ],
    "sg:phone":"+61 2 4751 5336",
    "sg:postcode":"2777",
    "sg:province":"NSW",
    "wof:name":"Old Bakery Coffee Shop",
    "wof:placetype":"venue"
},
  "geometry": {"coordinates":[150.56590270999999,-33.699016571],"type":"Point"}
}