{
  "type": "Feature",
  "properties": {
    "addr:full":"14 Queens Ave Mt Gambier SA 5290",
    "addr:housenumber":"14",
    "addr:postcode":"5290",
    "addr:street":"Queens Ave",
    "iso:country":"AU",
    "sg:address":"14 Queens Ave",
    "sg:city":"Mt Gambier",
    "sg:classifiers":[
        {
            "category":"Building & Trades",
            "subcategory":"Plumbing",
            "type":"Services"
        }
    ],
    "sg:phone":"+61 418 838 980",
    "sg:postcode":"5290",
    "sg:province":"SA",
    "sg:tags":[
        "plumber",
        "gasfitters"
    ],
    "wof:name":"Raymond Koczak Plumbing Services Pty Ltd",
    "wof:placetype":"venue"
},
  "geometry": {"coordinates":[140.78341699999999,-37.818851],"type":"Point"}
}