{
  "type": "Feature",
  "properties": {
    "addr:full":"Shop 7 Cnr Albion St & Old Hume Hwy Mittagong NSW 2575",
    "addr:housenumber":"shop 7",
    "addr:postcode":"2575",
    "addr:street":"Cnr Albion St & Old Hume Hwy",
    "iso:country":"AU",
    "sg:address":"Shop 7 Cnr Albion St & Old Hume Hwy",
    "sg:city":"Mittagong",
    "sg:classifiers":[
        {
            "category":"Professional",
            "subcategory":"Accounting & Tax Preparation",
            "type":"Services"
        }
    ],
    "sg:phone":"+61 2 4871 3970",
    "sg:postcode":"2575",
    "sg:province":"NSW",
    "sg:tags":[
        "accountant",
        "auditor"
    ],
    "wof:name":"Griffin Associates Pty Ltd",
    "wof:placetype":"venue"
},
  "geometry": {"coordinates":[150.45046997099999,-34.4502334595],"type":"Point"}
}