{
  "type": "Feature",
  "properties": {
    "iso:country":"AU",
    "sg:address":"Unit 10, 349 Macdonnell Rd",
    "sg:city":"Clontarf",
    "sg:classifiers":[
        {
            "category":"Professional",
            "subcategory":"Printing & Photocopies",
            "type":"Services"
        }
    ],
    "sg:phone":"+61 7 3283 1088",
    "sg:postcode":"4019",
    "sg:province":"QLD",
    "sg:tags":[
        "textile",
        "clothing"
    ],
    "wof:name":"Im-Magic Print",
    "wof:placetype":"venue"
},
  "geometry": {"coordinates":[153.085540772,-27.2342529297],"type":"Point"}
}