{
  "type": "Feature",
  "properties": {
    "addr:full":"100 Toronto Pde Sutherland NSW 2232",
    "addr:housenumber":"100",
    "addr:postcode":"2232",
    "addr:street":"Toronto Pde",
    "iso:country":"AU",
    "sg:address":"100 Toronto Pde",
    "sg:city":"Sutherland",
    "sg:classifiers":[
        {
            "category":"Building & Trades",
            "subcategory":"Construction",
            "type":"Services"
        }
    ],
    "sg:phone":"+61 2 9545 3365",
    "sg:postcode":"2232",
    "sg:province":"NSW",
    "sg:tags":[
        "joinery"
    ],
    "wof:name":"Allways Wood",
    "wof:placetype":"venue"
},
  "geometry": {"coordinates":[151.060348511,-34.0282974243],"type":"Point"}
}