{
  "type": "Feature",
  "properties": {
    "iso:country":"AU",
    "sg:address":"U1/ 2 Sunseeker Cl",
    "sg:city":"Noosaville",
    "sg:classifiers":[
        {
            "category":"Social Services",
            "subcategory":"Retirement Home",
            "type":"Services"
        }
    ],
    "sg:phone":"+61 7 5447 1525",
    "sg:postcode":"4566",
    "sg:province":"QLD",
    "sg:tags":[
        "decoration",
        "supplier",
        "contractor"
    ],
    "wof:name":"Coastal Provisions",
    "wof:placetype":"venue"
},
  "geometry": {"coordinates":[153.05047607399999,-26.4029693604],"type":"Point"}
}