{
  "type": "Feature",
  "properties": {
    "addr:full":"100 Nepean Hwy Dromana VIC 3936",
    "addr:housenumber":"100",
    "addr:postcode":"3936",
    "addr:street":"Nepean Hwy",
    "iso:country":"AU",
    "sg:address":"100 Nepean Hwy",
    "sg:city":"Dromana",
    "sg:classifiers":[
        {
            "category":"Autos & Motor Vehicles",
            "subcategory":"Boat Sales",
            "type":"Retail Goods"
        }
    ],
    "sg:phone":"+61 3 5987 0900",
    "sg:postcode":"3936",
    "sg:province":"VIC",
    "sg:tags":[
        "equipment",
        "yacht"
    ],
    "wof:name":"MY Marine",
    "wof:placetype":"venue"
},
  "geometry": {"coordinates":[144.975708008,-38.3280944824],"type":"Point"}
}