{
  "type": "Feature",
  "properties": {
    "addr:full":"21 Mitchell Rd Alexandria NSW 2015",
    "addr:housenumber":"21",
    "addr:postcode":"2015",
    "addr:street":"Mitchell Rd",
    "iso:country":"AU",
    "sg:address":"21 Mitchell Rd",
    "sg:city":"Alexandria",
    "sg:classifiers":[
        {
            "category":"Building & Trades",
            "subcategory":"Construction",
            "type":"Services"
        }
    ],
    "sg:phone":"+61 434 629 638",
    "sg:postcode":"2015",
    "sg:province":"NSW",
    "sg:tags":[
        "renovation",
        "alterations",
        "extension",
        "contractor"
    ],
    "wof:name":"Built By Lucas",
    "wof:placetype":"venue"
},
  "geometry": {"coordinates":[151.19505310100001,-33.8982620239],"type":"Point"}
}