{
  "type": "Feature",
  "properties": {
    "addr:full":"80 Minnegang St Warrawong NSW 2502",
    "addr:housenumber":"80",
    "addr:postcode":"2502",
    "addr:street":"Minnegang St",
    "iso:country":"AU",
    "sg:address":"80 Minnegang St",
    "sg:city":"Warrawong",
    "sg:classifiers":[
        {
            "category":"Food & Beverages",
            "subcategory":"Groceries & Convenience Stores",
            "type":"Retail Goods"
        }
    ],
    "sg:phone":"+61 2 4274 2786",
    "sg:postcode":"2502",
    "sg:province":"NSW",
    "wof:name":"Pecev J",
    "wof:placetype":"venue"
},
  "geometry": {"coordinates":[150.875046,-34.488579],"type":"Point"}
}