{
  "type": "Feature",
  "properties": {
    "iso:country":"AU",
    "sg:address":"3/ 454 Quakers Hill Pkwy",
    "sg:city":"Quakers Hill",
    "sg:classifiers":[
        {
            "category":"Fast Food",
            "type":"Food & Drink"
        }
    ],
    "sg:phone":"+61 2 9626 5300",
    "sg:postcode":"2763",
    "sg:province":"NSW",
    "sg:tags":[
        "away",
        "take"
    ],
    "wof:name":"Subway Quakers Hill",
    "wof:placetype":"venue"
},
  "geometry": {"coordinates":[150.87852477999999,-33.7318000793],"type":"Point"}
}