{
  "type": "Feature",
  "properties": {
    "addr:full":"77 Georgette Crs Endeavour Hills VIC 3802",
    "addr:housenumber":"77",
    "addr:postcode":"3802",
    "addr:street":"Georgette Crs",
    "iso:country":"AU",
    "sg:address":"77 Georgette Crs",
    "sg:city":"Endeavour Hills",
    "sg:classifiers":[
        {
            "category":"Professional",
            "subcategory":"Computer Services",
            "type":"Services"
        }
    ],
    "sg:phone":"+61 3 9700 2696",
    "sg:postcode":"3802",
    "sg:province":"VIC",
    "sg:tags":[
        "repairs",
        "upgrade",
        "equipment"
    ],
    "wof:name":"Hornbill Pty Ltd",
    "wof:placetype":"venue"
},
  "geometry": {"coordinates":[145.25584411599999,-37.96900177],"type":"Point"}
}