{
  "type": "Feature",
  "properties": {
    "iso:country":"AU",
    "sg:address":"124 Brunswick St",
    "sg:city":"Fortitude Valley",
    "sg:classifiers":[
        {
            "category":"Organizations",
            "subcategory":"Community Association",
            "type":"Services"
        }
    ],
    "sg:phone":"+61 7 3257 1904",
    "sg:postcode":"4006",
    "sg:province":"QLD",
    "sg:tags":[
        "organisation",
        "family",
        "welfare"
    ],
    "wof:name":"Emotions Anonymous",
    "wof:placetype":"venue"
},
  "geometry": {"coordinates":[153.03118896500001,-27.4552345276],"type":"Point"}
}