{
  "type": "Feature",
  "properties": {
    "addr:full":"Factory 2, Cnr Smethurst & Arundel Street Cranbourne VIC 3977",
    "addr:housenumber":"2",
    "addr:postcode":"3977",
    "addr:street":"Cnr Smethurst;Arundel Street",
    "iso:country":"AU",
    "sg:address":"Factory 2, Cnr Smethurst & Arundel Street",
    "sg:city":"Cranbourne",
    "sg:classifiers":[
        {
            "category":"Retail",
            "subcategory":"Auto Repair",
            "type":"Services"
        }
    ],
    "sg:phone":"+61 3 5996 4084",
    "sg:postcode":"3977",
    "sg:province":"VIC",
    "sg:tags":[
        "engine",
        "reconditioning"
    ],
    "wof:name":"Warby Engine Reconditioning",
    "wof:placetype":"venue"
},
  "geometry": {"coordinates":[145.28660583499999,-38.1036834717],"type":"Point"}
}