{
  "type": "Feature",
  "properties": {
    "addr:full":"2/ 59 Jersey Rd Bayswater VIC 3153",
    "addr:housenumber":"/ 59",
    "addr:postcode":"3153",
    "addr:street":"Jersey Rd",
    "iso:country":"AU",
    "sg:address":"2/ 59 Jersey Rd",
    "sg:city":"Bayswater",
    "sg:classifiers":[
        {
            "category":"Professional",
            "type":"Services"
        }
    ],
    "sg:phone":"+61 3 9720 4777",
    "sg:postcode":"3153",
    "sg:province":"VIC",
    "sg:tags":[
        "packaging",
        "filling",
        "assembling"
    ],
    "wof:name":"Precision Preweigh Pty Ltd",
    "wof:placetype":"venue"
},
  "geometry": {"coordinates":[145.27865600600001,-37.8470611572],"type":"Point"}
}