{
  "type": "Feature",
  "properties": {
    "addr:full":"Cnr Brunswick & Kent Sts New Farm QLD 4005",
    "addr:postcode":"4005",
    "iso:country":"AU",
    "sg:address":"Cnr Brunswick & Kent Sts",
    "sg:city":"New Farm",
    "sg:classifiers":[
        {
            "category":"Autos & Motor Vehicles",
            "subcategory":"Fuel & Gas Station",
            "type":"Retail Goods"
        }
    ],
    "sg:phone":"+61 7 3358 1752",
    "sg:postcode":"4005",
    "sg:province":"QLD",
    "wof:name":"BP",
    "wof:placetype":"venue"
},
  "geometry": {"coordinates":[153.044525147,-27.4658927917],"type":"Point"}
}