{
  "type": "Feature",
  "properties": {
    "addr:full":"77 Redcliffe Pde Redcliffe QLD 4020",
    "addr:housenumber":"77",
    "addr:postcode":"4020",
    "addr:street":"Redcliffe Pde",
    "iso:country":"AU",
    "sg:address":"77 Redcliffe Pde",
    "sg:city":"Redcliffe",
    "sg:classifiers":[
        {
            "category":"Food & Beverages",
            "subcategory":"Bakery",
            "type":"Retail Goods"
        }
    ],
    "sg:phone":"+61 7 3883 1515",
    "sg:postcode":"4020",
    "sg:province":"QLD",
    "sg:tags":[
        "cake",
        "shop",
        "pastry"
    ],
    "wof:name":"Great Australian Ice Creamery The",
    "wof:placetype":"venue"
},
  "geometry": {"coordinates":[153.11528000000001,-27.228222],"type":"Point"}
}