{
  "type": "Feature",
  "properties": {
    "iso:country":"AU",
    "sg:address":"176 Patterson Rd",
    "sg:city":"Bentleigh",
    "sg:classifiers":[
        {
            "category":"Professional",
            "subcategory":"Employment Agencies",
            "type":"Services"
        }
    ],
    "sg:phone":"+61 3 9557 2106",
    "sg:postcode":"3204",
    "sg:province":"VIC",
    "sg:tags":[
        "provider",
        "internet"
    ],
    "wof:name":"CorporatePERKS Pty Ltd",
    "wof:placetype":"venue"
},
  "geometry": {"coordinates":[145.042633,-37.926613],"type":"Point"}
}