{
  "type": "Feature",
  "properties": {
    "iso:country":"AU",
    "sg:address":"U5/ 1 Pitino Crt",
    "sg:city":"Osborne Park",
    "sg:classifiers":[
        {
            "category":"Autos & Motor Vehicles",
            "subcategory":"Auto Supplies",
            "type":"Retail Goods"
        }
    ],
    "sg:phone":"+61 8 9244 7994",
    "sg:postcode":"6017",
    "sg:province":"WA",
    "sg:tags":[
        "camper-trailers",
        "caravan",
        "equipment"
    ],
    "wof:name":"WA Joinery",
    "wof:placetype":"venue"
},
  "geometry": {"coordinates":[115.807762146,-31.8979301453],"type":"Point"}
}