{
  "type": "Feature",
  "properties": {
    "iso:country":"AU",
    "sg:address":"Unit 207 396 Scarborough Beach Rd",
    "sg:city":"Osborne Park",
    "sg:classifiers":[
        {
            "category":"Wholesale",
            "subcategory":"Drugs",
            "type":"Manufacturing & Wholesale Goods"
        }
    ],
    "sg:phone":"+61 8 9201 9266",
    "sg:postcode":"6017",
    "sg:province":"WA",
    "sg:tags":[
        "wholesaler",
        "pharmaceutical",
        "product",
        "mfrs"
    ],
    "wof:name":"Organon (Aust) Pty Ltd",
    "wof:placetype":"venue"
},
  "geometry": {"coordinates":[115.814582825,-31.9106483459],"type":"Point"}
}