{
  "type": "Feature",
  "properties": {
    "iso:country":"AU",
    "sg:address":"145 King St",
    "sg:city":"Warrawong",
    "sg:classifiers":[
        {
            "category":"Shopping",
            "subcategory":"Stationery & Office Supplies",
            "type":"Retail Goods"
        }
    ],
    "sg:phone":"+61 2 4276 1550",
    "sg:postcode":"2502",
    "sg:province":"NSW",
    "wof:name":"King Street Officesmart",
    "wof:placetype":"venue"
},
  "geometry": {"coordinates":[150.88928200000001,-34.497066],"type":"Point"}
}