{
  "type": "Feature",
  "properties": {
    "iso:country":"AU",
    "sg:address":"PO Box 302",
    "sg:city":"Hamilton Island",
    "sg:classifiers":[
        {
            "category":"Utilities",
            "subcategory":"Mobile Phone",
            "type":"Services"
        }
    ],
    "sg:phone":"+61 416 206 117",
    "sg:postcode":"4803",
    "sg:province":"QLD",
    "sg:tags":[
        "aviation",
        "consultant"
    ],
    "wof:name":"Joyce Aviation Services",
    "wof:placetype":"venue"
},
  "geometry": {"coordinates":[148.96368408199999,-20.3544101715],"type":"Point"}
}