{
  "type": "Feature",
  "properties": {
    "addr:full":"61 High St Woodend VIC 3442",
    "addr:housenumber":"61",
    "addr:postcode":"3442",
    "addr:street":"High St",
    "iso:country":"AU",
    "sg:address":"61 High St",
    "sg:city":"Woodend",
    "sg:classifiers":[
        {
            "category":"Wholesale",
            "subcategory":"Farm Supplies",
            "type":"Manufacturing & Wholesale Goods"
        }
    ],
    "sg:phone":"+61 3 5427 2753",
    "sg:postcode":"3442",
    "sg:province":"VIC",
    "sg:tags":[
        "equipment"
    ],
    "wof:name":"Woodend Produce Store Pty Ltd",
    "wof:placetype":"venue"
},
  "geometry": {"coordinates":[144.52784729000001,-37.3557357788],"type":"Point"}
}