{
  "type": "Feature",
  "properties": {
    "iso:country":"AU",
    "sg:address":"1 Gleeson St",
    "sg:city":"Burpengary",
    "sg:classifiers":[
        {
            "category":"Social Services",
            "subcategory":"Adult Care",
            "type":"Services"
        }
    ],
    "sg:phone":"+61 417 628 306",
    "sg:postcode":"4505",
    "sg:province":"QLD",
    "sg:tags":[
        "towing"
    ],
    "wof:name":"Pine Rivers Towing",
    "wof:placetype":"venue"
},
  "geometry": {"coordinates":[152.96690368599999,-27.1378631592],"type":"Point"}
}