{
  "type": "Feature",
  "properties": {
    "addr:full":"79 Byron St Inverell NSW 2360",
    "addr:housenumber":"79",
    "addr:postcode":"2360",
    "addr:street":"Byron St",
    "iso:country":"AU",
    "sg:address":"79 Byron St",
    "sg:city":"Inverell",
    "sg:classifiers":[
        {
            "category":"Shopping",
            "subcategory":"Clothing, Apparel, & Fashions",
            "type":"Retail Goods"
        }
    ],
    "sg:phone":"+61 2 6722 3508",
    "sg:postcode":"2360",
    "sg:province":"NSW",
    "sg:tags":[
        "lady",
        "wear"
    ],
    "wof:name":"Rockmans Stores Pty Limited",
    "wof:placetype":"venue"
},
  "geometry": {"coordinates":[151.114776611,-29.7715454102],"type":"Point"}
}