{
  "type": "Feature",
  "properties": {
    "iso:country":"AU",
    "sg:address":"Suite 3, 25 Foss St",
    "sg:city":"Palmyra",
    "sg:classifiers":[
        {
            "category":"Health Services",
            "subcategory":"Chiropractor",
            "type":"Services"
        }
    ],
    "sg:phone":"+61 8 9438 1500",
    "sg:postcode":"6157",
    "sg:province":"WA",
    "wof:name":"Grant Chiropractic Health Centre",
    "wof:placetype":"venue"
},
  "geometry": {"coordinates":[115.785767,-32.03614],"type":"Point"}
}