{
  "type": "Feature",
  "properties": {
    "addr:full":"Shop 7-9 The Mall, 90 Main St Mornington VIC 3931",
    "addr:housenumber":"shop 7-9;90",
    "addr:postcode":"3931",
    "addr:street":"The Mall;Main St",
    "iso:country":"AU",
    "sg:address":"Shop 7-9 The Mall, 90 Main St",
    "sg:city":"Mornington",
    "sg:classifiers":[
        {
            "category":"Shopping",
            "subcategory":"Optical Goods",
            "type":"Retail Goods"
        }
    ],
    "sg:phone":"+61 3 5973 5520",
    "sg:postcode":"3931",
    "sg:province":"VIC",
    "sg:tags":[
        "dispenser",
        "prescription"
    ],
    "wof:name":"20/20 Sight &#039;N&#039; Style",
    "wof:placetype":"venue"
},
  "geometry": {"coordinates":[145.038574219,-38.219291687],"type":"Point"}
}