{
  "type": "Feature",
  "properties": {
    "addr:full":"PO Box 339 Bentleigh East VIC 3165",
    "addr:postcode":"3165",
    "iso:country":"AU",
    "sg:address":"PO Box 339",
    "sg:city":"Bentleigh East",
    "sg:classifiers":[
        {
            "category":"Manufacturing",
            "subcategory":"Food",
            "type":"Manufacturing & Wholesale Goods"
        }
    ],
    "sg:phone":"+61 412 808 124",
    "sg:postcode":"3165",
    "sg:province":"VIC",
    "sg:tags":[
        "function",
        "catering"
    ],
    "wof:name":"New Zealand Natural Ice Cream - Event Catering",
    "wof:placetype":"venue"
},
  "geometry": {"coordinates":[145.06695556599999,-37.9222412109],"type":"Point"}
}