{
  "type": "Feature",
  "properties": {
    "iso:country":"AU",
    "sg:address":"140 Third Ave",
    "sg:city":"Kelmscott",
    "sg:classifiers":[
        {
            "category":"Building & Trades",
            "subcategory":"Locksmith",
            "type":"Services"
        }
    ],
    "sg:phone":"+61 8 9390 8888",
    "sg:postcode":"6111",
    "sg:province":"WA",
    "sg:tags":[
        "lock"
    ],
    "wof:name":"Armadale Lock & Key Service",
    "wof:placetype":"venue"
},
  "geometry": {"coordinates":[116.01014709499999,-32.1193771362],"type":"Point"}
}