{
  "type": "Feature",
  "properties": {
    "addr:full":"26 forrest oak chase, valla - tn is 65695283 Valla NSW 2448",
    "addr:housenumber":"26",
    "addr:postcode":"65695283;2448",
    "addr:street":"Forrest Oak Chase;Tn",
    "iso:country":"AU",
    "sg:address":"26 forrest oak chase, valla - tn is 65695283",
    "sg:city":"Valla",
    "sg:classifiers":[
        {
            "category":"Professional",
            "subcategory":"Art Services",
            "type":"Services"
        }
    ],
    "sg:phone":"+61 2 6569 5283",
    "sg:postcode":"2448",
    "sg:province":"NSW",
    "sg:tags":[
        "picture",
        "frame",
        "framing"
    ],
    "wof:name":"Eastcoast Picture Framing",
    "wof:placetype":"venue"
},
  "geometry": {"coordinates":[152.97485399999999,-30.598352],"type":"Point"}
}