{
  "type": "Feature",
  "properties": {
    "iso:country":"AU",
    "sg:address":"The Avenue Unit 124/ 136 Palm Meadows Drv",
    "sg:city":"Carrara",
    "sg:classifiers":[
        {
            "category":"Home & Garden",
            "subcategory":"Hardware",
            "type":"Retail Goods"
        }
    ],
    "sg:phone":"+61 7 5594 1879",
    "sg:postcode":"4211",
    "sg:province":"QLD",
    "sg:tags":[
        "rope",
        "twine"
    ],
    "wof:name":"The Rope Man",
    "wof:placetype":"venue"
},
  "geometry": {"coordinates":[153.37274169899999,-28.0234146118],"type":"Point"}
}