{
  "type": "Feature",
  "properties": {
    "iso:country":"AU",
    "sg:address":"Factory 3/ 170 Boundary Rd",
    "sg:city":"Braeside",
    "sg:classifiers":[
        {
            "category":"Transit Center",
            "subcategory":"Passenger",
            "type":"Transportation"
        }
    ],
    "sg:phone":"+61 3 9580 4477",
    "sg:postcode":"3195",
    "sg:province":"VIC",
    "sg:tags":[
        "frozen",
        "food",
        "retail"
    ],
    "wof:name":"Chef's Pantry",
    "wof:placetype":"venue"
},
  "geometry": {"coordinates":[145.105743408,-37.999835968],"type":"Point"}
}