{
  "type": "Feature",
  "properties": {
    "addr:full":"Level 14/ 210 George St Sydney NSW 2000",
    "addr:housenumber":"/ 210",
    "addr:postcode":"2000",
    "addr:street":"George St",
    "iso:country":"AU",
    "sg:address":"Level 14/ 210 George St",
    "sg:city":"Sydney",
    "sg:classifiers":[
        {
            "category":"Banks & Credit Unions",
            "subcategory":"Financial Services",
            "type":"Services"
        }
    ],
    "sg:phone":"+61 2 9251 5558",
    "sg:postcode":"2000",
    "sg:province":"NSW",
    "sg:tags":[
        "planning"
    ],
    "wof:name":"Gresham Street Services Pty Ltd",
    "wof:placetype":"venue"
},
  "geometry": {"coordinates":[151.207687378,-33.8627700806],"type":"Point"}
}