{
  "type": "Feature",
  "properties": {
    "addr:full":"2024 Wanneroo Rd Neerabup WA 6031",
    "addr:housenumber":"2024",
    "addr:postcode":"6031",
    "addr:street":"Wanneroo Rd",
    "iso:country":"AU",
    "sg:address":"2024 Wanneroo Rd",
    "sg:city":"Neerabup",
    "sg:classifiers":[
        {
            "category":"Home & Garden",
            "subcategory":"Garden Supply",
            "type":"Retail Goods"
        }
    ],
    "sg:phone":"+61 8 9407 5064",
    "sg:postcode":"6031",
    "sg:province":"WA",
    "sg:tags":[
        "equipment"
    ],
    "wof:name":"Seabreeze Landscape Supplies",
    "wof:placetype":"venue"
},
  "geometry": {"coordinates":[115.743370056,-31.6731815338],"type":"Point"}
}