{
  "type": "Feature",
  "properties": {
    "addr:full":"33 Bacon St Hindmarsh SA 5007",
    "addr:housenumber":"33",
    "addr:postcode":"5007",
    "addr:street":"Bacon St",
    "iso:country":"AU",
    "sg:address":"33 Bacon St",
    "sg:city":"Hindmarsh",
    "sg:classifiers":[
        {
            "category":"Arts & Performance",
            "subcategory":"Theater",
            "type":"Entertainment"
        }
    ],
    "sg:phone":"+61 8 8346 9990",
    "sg:postcode":"5007",
    "sg:province":"SA",
    "sg:tags":[
        "theatrical",
        "supply"
    ],
    "wof:name":"Party To The Max",
    "wof:placetype":"venue"
},
  "geometry": {"coordinates":[138.566574097,-34.9069328308],"type":"Point"}
}