{
  "type": "Feature",
  "properties": {
    "addr:full":"17 O'Connor Rd Armidale NSW 2350",
    "addr:housenumber":"17",
    "addr:postcode":"2350",
    "addr:street":"O'Connor Rd",
    "iso:country":"AU",
    "sg:address":"17 O'Connor Rd",
    "sg:city":"Armidale",
    "sg:classifiers":[
        {
            "category":"Building & Trades",
            "subcategory":"Plumbing",
            "type":"Services"
        }
    ],
    "sg:phone":"+61 2 6772 2191",
    "sg:postcode":"2350",
    "sg:province":"NSW",
    "sg:tags":[
        "plumber",
        "gasfitters"
    ],
    "wof:name":"Waterproof Plumbing",
    "wof:placetype":"venue"
},
  "geometry": {"coordinates":[151.67324829099999,-30.5024719238],"type":"Point"}
}