{
  "type": "Feature",
  "properties": {
    "iso:country":"AU",
    "sg:address":"Shop 16 Kalamunda Central Shopng Cntr",
    "sg:city":"Kalamunda",
    "sg:classifiers":[
        {
            "category":"Travel",
            "subcategory":"Travel Agent",
            "type":"Entertainment"
        }
    ],
    "sg:phone":"+61 8 9257 1900",
    "sg:postcode":"6076",
    "sg:province":"WA",
    "sg:tags":[
        "consultant"
    ],
    "wof:name":"Kalamunda Flight Centre",
    "wof:placetype":"venue"
},
  "geometry": {"coordinates":[116.05420684800001,-31.9702701569],"type":"Point"}
}