{
  "type": "Feature",
  "properties": {
    "addr:full":"68 Bulcock St Caloundra QLD 4551",
    "addr:housenumber":"68",
    "addr:postcode":"4551",
    "addr:street":"Bulcock St",
    "iso:country":"AU",
    "sg:address":"68 Bulcock St",
    "sg:city":"Caloundra",
    "sg:classifiers":[
        {
            "category":"Health Services",
            "subcategory":"Doctor",
            "type":"Services"
        }
    ],
    "sg:phone":"+61 7 5438 1488",
    "sg:postcode":"4551",
    "sg:province":"QLD",
    "sg:tags":[
        "medical",
        "practitioner"
    ],
    "wof:name":"Caloundra Bulk Billing Surgery",
    "wof:placetype":"venue"
},
  "geometry": {"coordinates":[153.129074097,-26.8046283722],"type":"Point"}
}