{
  "type": "Feature",
  "properties": {
    "addr:full":"4 Arcoona Rd Salisbury Plain SA 5109",
    "addr:housenumber":"4",
    "addr:postcode":"5109",
    "addr:street":"Arcoona Rd",
    "iso:country":"AU",
    "sg:address":"4 Arcoona Rd",
    "sg:city":"Salisbury Plain",
    "sg:classifiers":[
        {
            "category":"Retail",
            "subcategory":"Auto Repair",
            "type":"Services"
        }
    ],
    "sg:phone":"+61 8 8250 9875",
    "sg:postcode":"5109",
    "sg:province":"SA",
    "sg:tags":[
        "transmission",
        "automotive",
        "car"
    ],
    "wof:name":"Salisbury Transmission",
    "wof:placetype":"venue"
},
  "geometry": {"coordinates":[138.660644531,-34.7721252441],"type":"Point"}
}