{
  "type": "Feature",
  "properties": {
    "iso:country":"AU",
    "sg:address":"U1/ 297a Bexley Rd",
    "sg:city":"Bexley North",
    "sg:classifiers":[
        {
            "category":"Food & Beverages",
            "subcategory":"Bakery",
            "type":"Retail Goods"
        }
    ],
    "sg:phone":"+61 2 9554 9234",
    "sg:postcode":"2207",
    "sg:province":"NSW",
    "sg:tags":[
        "cake",
        "shop",
        "pastry"
    ],
    "wof:name":"Art Of Cakes",
    "wof:placetype":"venue"
},
  "geometry": {"coordinates":[151.11407500000001,-33.938614],"type":"Point"}
}