{
  "type": "Feature",
  "properties": {
    "iso:country":"AU",
    "sg:address":"276 Elizabeth Drv",
    "sg:city":"Vincentia",
    "sg:classifiers":[
        {
            "category":"Retail",
            "subcategory":"Repair Shop",
            "type":"Services"
        }
    ],
    "sg:phone":"+61 402 017 295",
    "sg:postcode":"2540",
    "sg:province":"NSW",
    "sg:tags":[
        "stove",
        "part",
        "range"
    ],
    "wof:name":"John Thorncraft Electrical",
    "wof:placetype":"venue"
},
  "geometry": {"coordinates":[150.68763732900001,-35.0725975037],"type":"Point"}
}