{
  "type": "Feature",
  "properties": {
    "addr:full":"37 Tenth St Mildura VIC 3500",
    "addr:housenumber":"37",
    "addr:postcode":"3500",
    "addr:street":"Tenth St",
    "iso:country":"AU",
    "sg:address":"37 Tenth St",
    "sg:city":"Mildura",
    "sg:classifiers":[
        {
            "category":"Professional",
            "type":"Services"
        }
    ],
    "sg:phone":"+61 1300 139 806",
    "sg:postcode":"3500",
    "sg:province":"VIC",
    "sg:tags":[
        "courier"
    ],
    "wof:name":"Vic Fast Couriers",
    "wof:placetype":"venue"
},
  "geometry": {"coordinates":[142.167236328,-34.1949462891],"type":"Point"}
}