{
  "type": "Feature",
  "properties": {
    "iso:country":"AU",
    "sg:address":"The Brickworks Centre 107 Ferry Rd",
    "sg:city":"Southport",
    "sg:classifiers":[
        {
            "category":"Home & Garden",
            "subcategory":"Garden Supply",
            "type":"Retail Goods"
        }
    ],
    "sg:phone":"+61 7 5532 8370",
    "sg:postcode":"4215",
    "sg:province":"QLD",
    "sg:tags":[
        "statuary",
        "fountains",
        "sundial"
    ],
    "wof:name":"Alfresco",
    "wof:placetype":"venue"
},
  "geometry": {"coordinates":[153.41082763700001,-27.9789466858],"type":"Point"}
}