{
  "type": "Feature",
  "properties": {
    "addr:full":"Cnr The Parade & Hodgson St Ocean Grove VIC 3226",
    "addr:postcode":"3226",
    "addr:street":"Cnr The Parade & Hodgson St",
    "iso:country":"AU",
    "sg:address":"Cnr The Parade & Hodgson St",
    "sg:city":"Ocean Grove",
    "sg:classifiers":[
        {
            "category":"Health Services",
            "subcategory":"Dentist",
            "type":"Services"
        }
    ],
    "sg:phone":"+61 3 5255 1443",
    "sg:postcode":"3226",
    "sg:province":"VIC",
    "wof:name":"Favaloro Phillip Dr",
    "wof:placetype":"venue"
},
  "geometry": {"coordinates":[144.53221099999999,-38.266647],"type":"Point"}
}