{
  "type": "Feature",
  "properties": {
    "addr:full":"46 Smith St Collingwood VIC 3066",
    "addr:housenumber":"46",
    "addr:postcode":"3066",
    "addr:street":"Smith St",
    "iso:country":"AU",
    "sg:address":"46 Smith St",
    "sg:city":"Collingwood",
    "sg:classifiers":[
        {
            "category":"Personal",
            "subcategory":"Beauty Salon",
            "type":"Services"
        }
    ],
    "sg:phone":"+61 3 9415 7434",
    "sg:postcode":"3066",
    "sg:province":"VIC",
    "sg:tags":[
        "hairdresser"
    ],
    "wof:name":"Fluff Hair",
    "wof:placetype":"venue"
},
  "geometry": {"coordinates":[144.98304748499999,-37.8070106506],"type":"Point"}
}