{
  "type": "Feature",
  "properties": {
    "addr:full":"Suite 8/ 13 Bridge St Epping NSW 2121",
    "addr:housenumber":"13",
    "addr:postcode":"2121",
    "addr:street":"Bridge St",
    "iso:country":"AU",
    "sg:address":"Suite 8/ 13 Bridge St",
    "sg:city":"Epping",
    "sg:classifiers":[
        {
            "category":"Manufacturing",
            "subcategory":"Jewelry",
            "type":"Manufacturing & Wholesale Goods"
        }
    ],
    "sg:phone":"+61 2 9868 6144",
    "sg:postcode":"2121",
    "sg:province":"NSW",
    "sg:tags":[
        "mfrg",
        "jeweller"
    ],
    "wof:name":"Berjani Jewellers",
    "wof:placetype":"venue"
},
  "geometry": {"coordinates":[151.081863403,-33.7739830017],"type":"Point"}
}