{
  "type": "Feature",
  "properties": {
    "addr:full":"2 Buvelot Pl Woodvale WA 6026",
    "addr:housenumber":"2",
    "addr:postcode":"6026",
    "addr:street":"Buvelot Pl",
    "iso:country":"AU",
    "sg:address":"2 Buvelot Pl",
    "sg:city":"Woodvale",
    "sg:classifiers":[
        {
            "category":"Banks & Credit Unions",
            "subcategory":"Investment Brokerage",
            "type":"Services"
        }
    ],
    "sg:phone":"+61 8 9409 9896",
    "sg:postcode":"6026",
    "sg:province":"WA",
    "sg:tags":[
        "water",
        "reticulation",
        "contractor"
    ],
    "wof:name":"A-1 Reticulation",
    "wof:placetype":"venue"
},
  "geometry": {"coordinates":[115.792732239,-31.780752182],"type":"Point"}
}