{
  "type": "Feature",
  "properties": {
    "addr:full":"40 Cityview Rd Balwyn North VIC 3104",
    "addr:housenumber":"40",
    "addr:postcode":"3104",
    "addr:street":"Cityview Rd",
    "iso:country":"AU",
    "sg:address":"40 Cityview Rd",
    "sg:city":"Balwyn North",
    "sg:classifiers":[
        {
            "category":"Personal",
            "type":"Services"
        }
    ],
    "sg:phone":"+61 3 9851 6216",
    "sg:postcode":"3104",
    "sg:province":"VIC",
    "sg:tags":[
        "reducing",
        "treatment",
        "weight"
    ],
    "wof:name":"Joanne Crisp",
    "wof:placetype":"venue"
},
  "geometry": {"coordinates":[145.07844543499999,-37.7904167175],"type":"Point"}
}