{
  "type": "Feature",
  "properties": {
    "iso:country":"AU",
    "sg:address":"58 Zealandia Rd",
    "sg:city":"Croydon North",
    "sg:classifiers":[
        {
            "category":"Organizations",
            "subcategory":"Non-profit Organization",
            "type":"Services"
        }
    ],
    "sg:phone":"+61 3 9723 6745",
    "sg:postcode":"3136",
    "sg:province":"VIC",
    "sg:tags":[
        "support",
        "disability",
        "organisation"
    ],
    "wof:name":"Disability Education & Training Services Unit, Paraplegic And Quadriplegic Association",
    "wof:placetype":"venue"
},
  "geometry": {"coordinates":[145.28503418,-37.7805099487],"type":"Point"}
}