{
  "type": "Feature",
  "properties": {
    "addr:full":"24/B Ellena St Maryborough QLD 4650",
    "addr:housenumber":"24 / b",
    "addr:postcode":"4650",
    "addr:street":"Ellena St",
    "iso:country":"AU",
    "sg:address":"24/B Ellena St",
    "sg:city":"Maryborough",
    "sg:classifiers":[
        {
            "category":"Health Services",
            "subcategory":"Dentist",
            "type":"Services"
        }
    ],
    "sg:phone":"+61 7 4121 6855",
    "sg:postcode":"4650",
    "sg:province":"QLD",
    "wof:name":"Pullen Robert",
    "wof:placetype":"venue"
},
  "geometry": {"coordinates":[152.69439700000001,-25.534395],"type":"Point"}
}