{
  "type": "Feature",
  "properties": {
    "addr:full":"158 Boundary St West End (Brisbane) QLD 4101",
    "addr:housenumber":"158",
    "addr:postcode":"4101",
    "addr:street":"Boundary St",
    "iso:country":"AU",
    "sg:address":"158 Boundary St",
    "sg:city":"West End (Brisbane)",
    "sg:classifiers":[
        {
            "category":"Health Services",
            "subcategory":"Health Practitioner",
            "type":"Services"
        }
    ],
    "sg:phone":"+61 7 3846 0440",
    "sg:postcode":"4101",
    "sg:province":"QLD",
    "sg:tags":[
        "homoeopath"
    ],
    "wof:name":"King Stephen",
    "wof:placetype":"venue"
},
  "geometry": {"coordinates":[153.012115478,-27.4812583923],"type":"Point"}
}