{
  "type": "Feature",
  "properties": {
    "iso:country":"AU",
    "sg:address":"222 Logan Rd",
    "sg:city":"Buranda",
    "sg:classifiers":[
        {
            "category":"Retail",
            "subcategory":"Auto Repair",
            "type":"Services"
        }
    ],
    "sg:phone":"+61 7 3393 1200",
    "sg:postcode":"4102",
    "sg:province":"QLD",
    "sg:tags":[
        "repairer",
        "motor",
        "engineer"
    ],
    "wof:name":"Mazda Service",
    "wof:placetype":"venue"
},
  "geometry": {"coordinates":[153.042205811,-27.4974651337],"type":"Point"}
}