{
  "type": "Feature",
  "properties": {
    "addr:full":"Level 4, 15 Blue St North Sydney NSW 2060",
    "addr:housenumber":"15",
    "addr:postcode":"2060",
    "addr:street":"Blue St",
    "iso:country":"AU",
    "sg:address":"Level 4, 15 Blue St",
    "sg:city":"North Sydney",
    "sg:classifiers":[
        {
            "category":"Communications",
            "subcategory":"Film & Video Production",
            "type":"Services"
        }
    ],
    "sg:phone":"+61 2 9978 1500",
    "sg:postcode":"2060",
    "sg:province":"NSW",
    "sg:tags":[
        "messaging",
        "voice"
    ],
    "wof:name":"Voice-Tel",
    "wof:placetype":"venue"
},
  "geometry": {"coordinates":[151.20791625999999,-33.8411407471],"type":"Point"}
}