{
  "type": "Feature",
  "properties": {
    "addr:full":"80 Greenmeadow Rd Mt Gravatt East QLD 4122",
    "addr:housenumber":"80",
    "addr:postcode":"4122",
    "addr:street":"Greenmeadow Rd",
    "iso:country":"AU",
    "sg:address":"80 Greenmeadow Rd",
    "sg:city":"Mt Gravatt East",
    "sg:classifiers":[
        {
            "category":"Retail",
            "subcategory":"Repair Shop",
            "type":"Services"
        }
    ],
    "sg:phone":"+61 7 3343 3502",
    "sg:postcode":"4122",
    "sg:province":"QLD",
    "sg:tags":[
        "mending",
        "clothing",
        "alteration"
    ],
    "wof:name":"Papas J & Sons",
    "wof:placetype":"venue"
},
  "geometry": {"coordinates":[153.09916687,-27.5221176147],"type":"Point"}
}