{
  "type": "Feature",
  "properties": {
    "iso:country":"AU",
    "sg:address":"54 Moore St",
    "sg:city":"Leichhardt",
    "sg:classifiers":[
        {
            "category":"Shopping",
            "subcategory":"Stationery & Office Supplies",
            "type":"Retail Goods"
        }
    ],
    "sg:phone":"+61 2 9564 6191",
    "sg:postcode":"2040",
    "sg:province":"NSW",
    "sg:tags":[
        "equipment",
        "display",
        "exhibition"
    ],
    "wof:name":"Bass Plastics",
    "wof:placetype":"venue"
},
  "geometry": {"coordinates":[151.16456600000001,-33.879459],"type":"Point"}
}