{
  "type": "Feature",
  "properties": {
    "addr:full":"5 Barth St Warwick QLD 4370",
    "addr:housenumber":"5",
    "addr:postcode":"4370",
    "addr:street":"Barth St",
    "iso:country":"AU",
    "sg:address":"5 Barth St",
    "sg:city":"Warwick",
    "sg:classifiers":[
        {
            "category":"Professional",
            "subcategory":"Art Services",
            "type":"Services"
        }
    ],
    "sg:phone":"+61 7 4661 4176",
    "sg:postcode":"4370",
    "sg:province":"QLD",
    "sg:tags":[
        "artist"
    ],
    "wof:name":"Jennifer & Ron Marshall",
    "wof:placetype":"venue"
},
  "geometry": {"coordinates":[152.030319214,-28.2130508423],"type":"Point"}
}