{
  "type": "Feature",
  "properties": {
    "addr:full":"13 Werrina Pde Blue Bay NSW 2261",
    "addr:housenumber":"13",
    "addr:postcode":"2261",
    "addr:street":"Werrina Pde;Bay",
    "iso:country":"AU",
    "sg:address":"13 Werrina Pde",
    "sg:city":"Blue Bay",
    "sg:classifiers":[
        {
            "category":"Building & Trades",
            "subcategory":"Plumbing",
            "type":"Services"
        }
    ],
    "sg:phone":"+61 2 4334 4521",
    "sg:postcode":"2261",
    "sg:province":"NSW",
    "sg:tags":[
        "plumber",
        "gasfitters"
    ],
    "wof:name":"Coastco Plumbing",
    "wof:placetype":"venue"
},
  "geometry": {"coordinates":[151.501373,-33.353893],"type":"Point"}
}