{
  "type": "Feature",
  "properties": {
    "iso:country":"AU",
    "sg:address":"56 Gladesville Rd",
    "sg:city":"Hunters Hill",
    "sg:classifiers":[
        {
            "category":"Health Services",
            "subcategory":"Dentist",
            "type":"Services"
        }
    ],
    "sg:phone":"+61 2 9817 2715",
    "sg:postcode":"2110",
    "sg:province":"NSW",
    "wof:name":"O&#039;Hehir M J",
    "wof:placetype":"venue"
},
  "geometry": {"coordinates":[151.144165039,-33.8336105347],"type":"Point"}
}