{
  "type": "Feature",
  "properties": {
    "iso:country":"AU",
    "sg:address":"251 Glebe Point Rd",
    "sg:city":"Glebe",
    "sg:classifiers":[
        {
            "category":"Real Estate",
            "subcategory":"Real Estate Agent",
            "type":"Services"
        }
    ],
    "sg:phone":"+61 2 9552 1099",
    "sg:postcode":"2037",
    "sg:province":"NSW",
    "wof:name":"Blake Kittle Pty Ltd",
    "wof:placetype":"venue"
},
  "geometry": {"coordinates":[151.18672180199999,-33.8791923523],"type":"Point"}
}