{
  "type": "Feature",
  "properties": {
    "addr:full":"27 Victoria St Victor Harbor SA 5211",
    "addr:housenumber":"27",
    "addr:postcode":"5211",
    "addr:street":"Victoria St",
    "iso:country":"AU",
    "sg:address":"27 Victoria St",
    "sg:city":"Victor Harbor",
    "sg:classifiers":[
        {
            "category":"Health Services",
            "subcategory":"Chiropractor",
            "type":"Services"
        }
    ],
    "sg:phone":"+61 8 8552 3511",
    "sg:postcode":"5211",
    "sg:province":"SA",
    "wof:name":"Barns Colin Dr",
    "wof:placetype":"venue"
},
  "geometry": {"coordinates":[138.619873047,-35.5561141968],"type":"Point"}
}