{
  "type": "Feature",
  "properties": {
    "iso:country":"AU",
    "sg:address":"22 Collaroy St",
    "sg:city":"Collaroy",
    "sg:classifiers":[
        {
            "category":"Shopping",
            "subcategory":"Bicycles & Sporting Goods",
            "type":"Retail Goods"
        }
    ],
    "sg:phone":"+61 2 9982 5372",
    "sg:postcode":"2097",
    "sg:province":"NSW",
    "sg:tags":[
        "chemical",
        "equipment",
        "pool",
        "swimming"
    ],
    "wof:name":"Tim Ryan Pool Renovations",
    "wof:placetype":"venue"
},
  "geometry": {"coordinates":[151.299118042,-33.7319259644],"type":"Point"}
}