{
  "type": "Feature",
  "properties": {
    "addr:full":"259 Orrong Rd St Kilda East VIC 3183",
    "addr:housenumber":"259",
    "addr:postcode":"3183",
    "addr:street":"Orrong Rd",
    "iso:country":"AU",
    "sg:address":"259 Orrong Rd St",
    "sg:city":"Kilda East",
    "sg:classifiers":[
        {
            "category":"Professional",
            "subcategory":"Business Services",
            "type":"Services"
        }
    ],
    "sg:phone":"+61 3 9507 2006",
    "sg:postcode":"3183",
    "sg:province":"VIC",
    "sg:tags":[
        "management",
        "event"
    ],
    "wof:name":"Expressions Conference & Events Management",
    "wof:placetype":"venue"
},
  "geometry": {"coordinates":[145.008575439,-37.8698997498],"type":"Point"}
}