{
  "type": "Feature",
  "properties": {
    "addr:full":"16 Military Rd Neutral Bay NSW 2089",
    "addr:housenumber":"16",
    "addr:postcode":"2089",
    "addr:street":"Military Rd",
    "iso:country":"AU",
    "sg:address":"16 Military Rd",
    "sg:city":"Neutral Bay",
    "sg:classifiers":[
        {
            "category":"Autos & Motor Vehicles",
            "subcategory":"Fuel & Gas Station",
            "type":"Retail Goods"
        }
    ],
    "sg:phone":"+61 2 9953 5393",
    "sg:postcode":"2089",
    "sg:province":"NSW",
    "wof:name":"Caltex Ampol Service Station",
    "wof:placetype":"venue"
},
  "geometry": {"coordinates":[151.216064453,-33.8291435242],"type":"Point"}
}