{
  "type": "Feature",
  "properties": {
    "iso:country":"AU",
    "sg:address":"115 Plenty Rd",
    "sg:city":"Preston",
    "sg:classifiers":[
        {
            "category":"Retail",
            "subcategory":"Storage",
            "type":"Services"
        }
    ],
    "sg:phone":"+61 3 9443 9988",
    "sg:postcode":"3072",
    "sg:province":"VIC",
    "sg:tags":[
        "shelving",
        "system"
    ],
    "wof:name":"VIS",
    "wof:placetype":"venue"
},
  "geometry": {"coordinates":[145.061157227,-37.6933784485],"type":"Point"}
}