{
  "type": "Feature",
  "properties": {
    "addr:full":"18 Boothby St Kedron QLD 4031",
    "addr:housenumber":"18",
    "addr:postcode":"4031",
    "addr:street":"Boothby St",
    "iso:country":"AU",
    "sg:address":"18 Boothby St",
    "sg:city":"Kedron",
    "sg:classifiers":[
        {
            "category":"Personal",
            "subcategory":"Beauty Salon",
            "type":"Services"
        }
    ],
    "sg:phone":"+61 7 3350 2133",
    "sg:postcode":"4031",
    "sg:province":"QLD",
    "sg:tags":[
        "hairdresser"
    ],
    "wof:name":"Active Salon Supplies",
    "wof:placetype":"venue"
},
  "geometry": {"coordinates":[153.03248600000001,-27.397436],"type":"Point"}
}