{
  "type": "Feature",
  "properties": {
    "iso:country":"AU",
    "sg:address":"PO Box 232",
    "sg:city":"Chermside South",
    "sg:classifiers":[
        {
            "category":"Professional",
            "subcategory":"Detective & Security Services",
            "type":"Services"
        }
    ],
    "sg:phone":"+61 7 3856 2669",
    "sg:postcode":"4032",
    "sg:province":"QLD",
    "sg:tags":[
        "guard",
        "patrol"
    ],
    "wof:name":"Amalgamated Security Company",
    "wof:placetype":"venue"
},
  "geometry": {"coordinates":[153.03128100000001,-27.39168],"type":"Point"}
}