{
  "type": "Feature",
  "properties": {
    "iso:country":"AU",
    "sg:address":"257 Annangrove Rd",
    "sg:city":"Rouse Hill",
    "sg:classifiers":[
        {
            "category":"Education",
            "subcategory":"Special Training",
            "type":"Public Place"
        }
    ],
    "sg:phone":"+61 2 9679 1098",
    "sg:postcode":"2155",
    "sg:province":"NSW",
    "sg:tags":[
        "diving",
        "school",
        "scuba"
    ],
    "wof:name":"Hills District Scuba School",
    "wof:placetype":"venue"
},
  "geometry": {"coordinates":[150.91258239699999,-33.6730155945],"type":"Point"}
}