{
  "type": "Feature",
  "properties": {
    "addr:full":"119 Mornington-Tyabb Rd Mornington VIC 3931",
    "addr:housenumber":"119",
    "addr:postcode":"3931",
    "addr:street":"Mornington-Tyabb Rd",
    "iso:country":"AU",
    "sg:address":"119 Mornington-Tyabb Rd",
    "sg:city":"Mornington",
    "sg:classifiers":[
        {
            "category":"Home & Garden",
            "subcategory":"Garden Supply",
            "type":"Retail Goods"
        }
    ],
    "sg:phone":"+61 3 5977 1944",
    "sg:postcode":"3931",
    "sg:province":"VIC",
    "sg:tags":[
        "equipment"
    ],
    "wof:name":"Peninsula Mowers",
    "wof:placetype":"venue"
},
  "geometry": {"coordinates":[145.056472778,-38.2358398438],"type":"Point"}
}