{
  "type": "Feature",
  "properties": {
    "iso:country":"AU",
    "sg:address":"20 Harriett St",
    "sg:city":"Clare",
    "sg:classifiers":[
        {
            "category":"Building & Trades",
            "subcategory":"Cleaning & Sanitation",
            "type":"Services"
        }
    ],
    "sg:phone":"+61 8 8842 2860",
    "sg:postcode":"5453",
    "sg:province":"SA",
    "sg:tags":[
        "industrial",
        "commercial",
        "contractor"
    ],
    "wof:name":"Clare Valley Cleaners",
    "wof:placetype":"venue"
},
  "geometry": {"coordinates":[138.607834,-33.830105],"type":"Point"}
}