{
  "type": "Feature",
  "properties": {
    "iso:country":"AU",
    "sg:address":"PO Box 1012",
    "sg:city":"Bentley DC",
    "sg:classifiers":[
        {
            "category":"Shopping",
            "subcategory":"Computers & Home Electronics",
            "type":"Retail Goods"
        }
    ],
    "sg:phone":"+61 412 762 962",
    "sg:postcode":"6983",
    "sg:province":"WA",
    "sg:tags":[
        "equipment",
        "multimedia"
    ],
    "wof:name":"Progressive Video",
    "wof:placetype":"venue"
},
  "geometry": {"coordinates":[115.918983,-32.001781],"type":"Point"}
}