{
  "type": "Feature",
  "properties": {
    "addr:full":"Factory 4/ 478 Maroondah Hwy Lilydale VIC 3140",
    "addr:housenumber":"/ 478",
    "addr:postcode":"3140",
    "addr:street":"Maroondah Hwy",
    "iso:country":"AU",
    "sg:address":"Factory 4/ 478 Maroondah Hwy",
    "sg:city":"Lilydale",
    "sg:classifiers":[
        {
            "category":"Retail",
            "subcategory":"Auto Repair",
            "type":"Services"
        }
    ],
    "sg:phone":"+61 3 9739 5643",
    "sg:postcode":"3140",
    "sg:province":"VIC",
    "sg:tags":[
        "repairer",
        "motor",
        "engineer"
    ],
    "wof:name":"Peter Wallace Motors",
    "wof:placetype":"venue"
},
  "geometry": {"coordinates":[145.110931397,-37.8649253845],"type":"Point"}
}