{
  "type": "Feature",
  "properties": {
    "addr:full":"Unit 11 45 Jijaws St Sumner Park QLD 4074",
    "addr:housenumber":"45",
    "addr:postcode":"4074",
    "addr:street":"Jijaws St",
    "iso:country":"AU",
    "sg:address":"Unit 11 45 Jijaws St",
    "sg:city":"Sumner Park",
    "sg:classifiers":[
        {
            "category":"Wholesale",
            "subcategory":"Machinery & Supplies",
            "type":"Manufacturing & Wholesale Goods"
        }
    ],
    "sg:phone":"+61 7 3279 2627",
    "sg:postcode":"4074",
    "sg:province":"QLD",
    "sg:tags":[
        "equipment",
        "hydraulic"
    ],
    "wof:name":"Flanges Australia",
    "wof:placetype":"venue"
},
  "geometry": {"coordinates":[152.93942260700001,-27.562789917],"type":"Point"}
}