{
  "type": "Feature",
  "properties": {
    "addr:full":"56 Murray St Bayswater WA 6053",
    "addr:housenumber":"56",
    "addr:postcode":"6053",
    "addr:street":"Murray St",
    "iso:country":"AU",
    "sg:address":"56 Murray St",
    "sg:city":"Bayswater",
    "sg:classifiers":[
        {
            "category":"Building & Trades",
            "subcategory":"Construction",
            "type":"Services"
        }
    ],
    "sg:phone":"+61 418 908 229",
    "sg:postcode":"6053",
    "sg:province":"WA",
    "sg:tags":[
        "home",
        "air conditioning"
    ],
    "wof:name":"James Refrigeration & Air Conditioning",
    "wof:placetype":"venue"
},
  "geometry": {"coordinates":[115.908737183,-31.9222164154],"type":"Point"}
}