{
  "type": "Feature",
  "properties": {
    "addr:full":"PO Box 5114 Bundaberg West QLD 4670",
    "addr:postcode":"4670",
    "iso:country":"AU",
    "sg:address":"PO Box 5114",
    "sg:city":"Bundaberg West",
    "sg:classifiers":[
        {
            "category":"Building & Trades",
            "subcategory":"Construction",
            "type":"Services"
        }
    ],
    "sg:phone":"+61 418 874 718",
    "sg:postcode":"4670",
    "sg:province":"QLD",
    "sg:tags":[
        "contractor"
    ],
    "wof:name":"Schuler Homes",
    "wof:placetype":"venue"
},
  "geometry": {"coordinates":[152.33720398,-24.8693695068],"type":"Point"}
}