{
  "type": "Feature",
  "properties": {
    "addr:full":"Shop 2 9 Al Elamein St Port Augusta SA 5710",
    "addr:housenumber":"shop;9",
    "addr:postcode":"5710",
    "addr:street":"Al Elamein St",
    "iso:country":"AU",
    "sg:address":"Shop 2 9 Al Elamein St",
    "sg:city":"Port Augusta",
    "sg:classifiers":[
        {
            "category":"Food & Beverages",
            "subcategory":"Liquor & Beverages",
            "type":"Retail Goods"
        }
    ],
    "sg:phone":"+61 8 8642 5535",
    "sg:postcode":"5710",
    "sg:province":"SA",
    "sg:tags":[
        "store"
    ],
    "wof:name":"Liquorland",
    "wof:placetype":"venue"
},
  "geometry": {"coordinates":[135.001022339,-29.6619091034],"type":"Point"}
}