{
  "type": "Feature",
  "properties": {
    "iso:country":"AU",
    "sg:address":"18 Mossberry St",
    "sg:city":"Blair Athol",
    "sg:classifiers":[
        {
            "category":"Professional",
            "subcategory":"Business Services",
            "type":"Services"
        }
    ],
    "sg:phone":"+61 2 4625 8078",
    "sg:postcode":"2560",
    "sg:province":"NSW",
    "sg:tags":[
        "exporter"
    ],
    "wof:name":"Australian Micronesian Exports",
    "wof:placetype":"venue"
},
  "geometry": {"coordinates":[150.80172729500001,-34.0642127991],"type":"Point"}
}