{
  "type": "Feature",
  "properties": {
    "addr:full":"1 Mowhawk Pl Erskine Park NSW 2759",
    "addr:housenumber":"1",
    "addr:postcode":"2759",
    "addr:street":"Mowhawk Pl",
    "iso:country":"AU",
    "sg:address":"1 Mowhawk Pl",
    "sg:city":"Erskine Park",
    "sg:classifiers":[
        {
            "category":"Education",
            "subcategory":"Music School",
            "type":"Public Place"
        }
    ],
    "sg:phone":"+61 2 9834 1273",
    "sg:postcode":"2759",
    "sg:province":"NSW",
    "sg:tags":[
        "choir",
        "bands",
        "orchestra"
    ],
    "wof:name":"The Roaring Days",
    "wof:placetype":"venue"
},
  "geometry": {"coordinates":[150.80992126500001,-33.8046455383],"type":"Point"}
}