{
  "type": "Feature",
  "properties": {
    "iso:country":"AU",
    "sg:address":"265 Shute Harbour Rd",
    "sg:city":"Airlie Beach",
    "sg:classifiers":[
        {
            "category":"Shopping",
            "subcategory":"Discount & Variety Stores",
            "type":"Retail Goods"
        }
    ],
    "sg:phone":"+61 7 4946 4886",
    "sg:postcode":"4802",
    "sg:province":"QLD",
    "sg:tags":[
        "shop",
        "adult"
    ],
    "wof:name":"Airlie Adult Haven",
    "wof:placetype":"venue"
},
  "geometry": {"coordinates":[148.717193603,-20.2680053711],"type":"Point"}
}