{
  "type": "Feature",
  "properties": {
    "iso:country":"AU",
    "sg:address":"1- 3 Duck St",
    "sg:city":"Auburn",
    "sg:classifiers":[
        {
            "category":"Utilities",
            "subcategory":"Recycling",
            "type":"Services"
        }
    ],
    "sg:phone":"+61 2 9748 4994",
    "sg:postcode":"2144",
    "sg:province":"NSW",
    "wof:name":"Reefway Environmental Services",
    "wof:placetype":"venue"
},
  "geometry": {"coordinates":[151.02713012699999,-33.8373146057],"type":"Point"}
}