{
  "type": "Feature",
  "properties": {
    "iso:country":"AU",
    "sg:address":"18a Yalgar Rd",
    "sg:city":"Kirrawee",
    "sg:classifiers":[
        {
            "category":"Train Station",
            "subcategory":"Rail",
            "type":"Transportation"
        }
    ],
    "sg:phone":"+61 2 9521 4717",
    "sg:postcode":"2232",
    "sg:province":"NSW",
    "sg:tags":[
        "marine",
        "engineer"
    ],
    "wof:name":"Rose A J & G V",
    "wof:placetype":"venue"
},
  "geometry": {"coordinates":[151.07530212399999,-34.0268936157],"type":"Point"}
}