{
  "type": "Feature",
  "properties": {
    "iso:country":"AU",
    "sg:address":"31 Mortimer Rd",
    "sg:city":"Archerfield",
    "sg:classifiers":[
        {
            "category":"Retail",
            "subcategory":"Repair Shop",
            "type":"Services"
        }
    ],
    "sg:phone":"+61 7 3277 3201",
    "sg:postcode":"4108",
    "sg:province":"QLD",
    "sg:tags":[
        "windscreen"
    ],
    "wof:name":"Alpha Glass & Windsceens",
    "wof:placetype":"venue"
},
  "geometry": {"coordinates":[153.00978088400001,-27.5775470734],"type":"Point"}
}