{
  "type": "Feature",
  "properties": {
    "addr:full":"95 Atchison St Crows Nest NSW 2065",
    "addr:housenumber":"95",
    "addr:postcode":"2065",
    "addr:street":"Atchison St",
    "iso:country":"AU",
    "sg:address":"95 Atchison St",
    "sg:city":"Crows Nest",
    "sg:classifiers":[
        {
            "category":"Farming",
            "subcategory":"Fish & Marine Products",
            "type":"Manufacturing & Wholesale Goods"
        }
    ],
    "sg:phone":"+61 2 9906 5883",
    "sg:postcode":"2065",
    "sg:province":"NSW",
    "sg:tags":[
        "slate"
    ],
    "wof:name":"Classic Roofing Pty Ltd",
    "wof:placetype":"venue"
},
  "geometry": {"coordinates":[151.20393371599999,-33.8235206604],"type":"Point"}
}