{
  "type": "Feature",
  "properties": {
    "addr:full":"PO Box 330 Casino NSW 2470",
    "addr:postcode":"2470",
    "iso:country":"AU",
    "sg:address":"PO Box 330",
    "sg:city":"Casino",
    "sg:classifiers":[
        {
            "category":"Home & Garden",
            "subcategory":"Building Materials",
            "type":"Retail Goods"
        }
    ],
    "sg:phone":"+61 2 6664 7355",
    "sg:postcode":"2470",
    "sg:province":"NSW",
    "sg:tags":[
        "supply"
    ],
    "wof:name":"Weepa Products Pty Ltd",
    "wof:placetype":"venue"
},
  "geometry": {"coordinates":[153.04786682100001,-28.8585395813],"type":"Point"}
}