{
  "type": "Feature",
  "properties": {
    "addr:full":"31 Bland Rd Springwood NSW 2777",
    "addr:housenumber":"31",
    "addr:postcode":"2777",
    "addr:street":"Bland Rd",
    "iso:country":"AU",
    "sg:address":"31 Bland Rd",
    "sg:city":"Springwood",
    "sg:classifiers":[
        {
            "category":"Professional",
            "subcategory":"Business Services",
            "type":"Services"
        }
    ],
    "sg:phone":"+61 2 4751 2012",
    "sg:postcode":"2777",
    "sg:province":"NSW",
    "sg:tags":[
        "drafting"
    ],
    "wof:name":"Lomatia Drafting",
    "wof:placetype":"venue"
},
  "geometry": {"coordinates":[150.56944274899999,-33.694229126],"type":"Point"}
}