{
  "type": "Feature",
  "properties": {
    "addr:full":"9 Creek St Crows Nest QLD 4355",
    "addr:housenumber":"9",
    "addr:postcode":"4355",
    "addr:street":"Creek St",
    "iso:country":"AU",
    "sg:address":"9 Creek St",
    "sg:city":"Crows Nest",
    "sg:classifiers":[
        {
            "category":"Retail",
            "subcategory":"Veterinary Services",
            "type":"Services"
        }
    ],
    "sg:phone":"+61 7 4698 1488",
    "sg:postcode":"4355",
    "sg:province":"QLD",
    "sg:tags":[
        "surgeon"
    ],
    "wof:name":"Chris Yeates Veterinary Surgeon",
    "wof:placetype":"venue"
},
  "geometry": {"coordinates":[152.05810500000001,-27.262396],"type":"Point"}
}