{
  "type": "Feature",
  "properties": {
    "addr:full":"Unit 5/ 2-14 Atkinson Rd Taren Point NSW 2229",
    "addr:housenumber":"/ 2-14",
    "addr:postcode":"2229",
    "addr:street":"Atkinson Rd",
    "iso:country":"AU",
    "sg:address":"Unit 5/ 2-14 Atkinson Rd",
    "sg:city":"Taren Point",
    "sg:classifiers":[
        {
            "category":"Manufacturing",
            "subcategory":"Paper Products",
            "type":"Manufacturing & Wholesale Goods"
        }
    ],
    "sg:phone":"+61 2 9531 0633",
    "sg:postcode":"2229",
    "sg:province":"NSW",
    "sg:tags":[
        "wholesaler",
        "brassware",
        "mfrs"
    ],
    "wof:name":"Viana Bronzes Pty Ltd",
    "wof:placetype":"venue"
},
  "geometry": {"coordinates":[151.12957763700001,-34.0224380493],"type":"Point"}
}