{
  "type": "Feature",
  "properties": {
    "addr:full":"21 Shakespears Drv St Clair NSW 2759",
    "addr:housenumber":"21",
    "addr:postcode":"2759",
    "addr:street":"Shakespears Drv",
    "iso:country":"AU",
    "sg:address":"21 Shakespears Drv",
    "sg:city":"St Clair",
    "sg:classifiers":[
        {
            "category":"Utilities",
            "subcategory":"Electric",
            "type":"Services"
        }
    ],
    "sg:phone":"+61 414 540 057",
    "sg:postcode":"2759",
    "sg:province":"NSW",
    "sg:tags":[
        "electrical",
        "contractor"
    ],
    "wof:name":"Exceptional Electrical Services",
    "wof:placetype":"venue"
},
  "geometry": {"coordinates":[150.788574219,-33.8026847839],"type":"Point"}
}