{
  "type": "Feature",
  "properties": {
    "iso:country":"AU",
    "sg:address":"6/ 19 Dominions Rd",
    "sg:city":"Ashmore",
    "sg:classifiers":[
        {
            "category":"Retail",
            "subcategory":"Auto Repair",
            "type":"Services"
        }
    ],
    "sg:phone":"+61 410 557 125",
    "sg:postcode":"4214",
    "sg:province":"QLD",
    "sg:tags":[
        "beater",
        "painter",
        "panel"
    ],
    "wof:name":"Wizard Smash Repairs",
    "wof:placetype":"venue"
},
  "geometry": {"coordinates":[153.383712769,-27.9801940918],"type":"Point"}
}