{
  "type": "Feature",
  "properties": {
    "iso:country":"AU",
    "sg:address":"69 Scaphella Ave",
    "sg:city":"Mullaloo",
    "sg:classifiers":[
        {
            "category":"Health Services",
            "subcategory":"Doctor",
            "type":"Services"
        }
    ],
    "sg:phone":"+61 8 9307 7088",
    "sg:postcode":"6027",
    "sg:province":"WA",
    "sg:tags":[
        "medical",
        "practitioner"
    ],
    "wof:name":"Georgy Dr Nagy",
    "wof:placetype":"venue"
},
  "geometry": {"coordinates":[115.74382782000001,-31.7790584564],"type":"Point"}
}