{
  "type": "Feature",
  "properties": {
    "iso:country":"AU",
    "sg:address":"PO Box 515",
    "sg:city":"Morayfield",
    "sg:classifiers":[
        {
            "category":"Professional",
            "subcategory":"Employment Agencies",
            "type":"Services"
        }
    ],
    "sg:phone":"+61 7 5497 0070",
    "sg:postcode":"4506",
    "sg:province":"QLD",
    "sg:tags":[
        "broker",
        "custom"
    ],
    "wof:name":"Customs Broker Locum Service",
    "wof:placetype":"venue"
},
  "geometry": {"coordinates":[152.94992065400001,-27.1089096069],"type":"Point"}
}