{
  "type": "Feature",
  "properties": {
    "addr:full":"Lot 37 Sanderson Tce Kalannie WA 6468",
    "addr:postcode":"6468",
    "addr:street":"Sanderson Tce",
    "iso:country":"AU",
    "sg:address":"Lot 37",
    "sg:city":"Sanderson Tce Kalannie",
    "sg:classifiers":[
        {
            "category":"Building & Trades",
            "subcategory":"Landscaping Services",
            "type":"Services"
        }
    ],
    "sg:phone":"+61 429 662 033",
    "sg:postcode":"6468",
    "sg:province":"WA",
    "sg:tags":[
        "fertilizer",
        "spreading",
        "insecticide"
    ],
    "wof:name":"Kalannie Contractors",
    "wof:placetype":"venue"
},
  "geometry": {"coordinates":[117.071342468,-30.2835712433],"type":"Point"}
}