{
  "type": "Feature",
  "properties": {
    "iso:country":"AU",
    "sg:address":"420 Punt Rd",
    "sg:city":"South Yarra",
    "sg:classifiers":[
        {
            "category":"Health Services",
            "subcategory":"Doctor",
            "type":"Services"
        }
    ],
    "sg:phone":"+61 3 9867 4877",
    "sg:postcode":"3141",
    "sg:province":"VIC",
    "sg:tags":[
        "podiatrist"
    ],
    "wof:name":"David Walker Podiatry",
    "wof:placetype":"venue"
},
  "geometry": {"coordinates":[144.98487854000001,-37.8455810547],"type":"Point"}
}