{
  "type": "Feature",
  "properties": {
    "addr:full":"906a Princes Hwy Engadine NSW 2233",
    "addr:housenumber":"906a",
    "addr:postcode":"2233",
    "addr:street":"Princes Hwy",
    "iso:country":"AU",
    "sg:address":"906a Princes Hwy",
    "sg:city":"Engadine",
    "sg:classifiers":[
        {
            "category":"Structure",
            "subcategory":"Office Building",
            "type":"Public Place"
        }
    ],
    "sg:phone":"+61 2 9520 6520",
    "sg:postcode":"2233",
    "sg:province":"NSW",
    "sg:tags":[
        "tie",
        "concrete",
        "formwork",
        "form",
        "accessory"
    ],
    "wof:name":"Renic Constructions Pty Ltd",
    "wof:placetype":"venue"
},
  "geometry": {"coordinates":[151.027420044,-34.0597000122],"type":"Point"}
}