{
  "type": "Feature",
  "properties": {
    "iso:country":"AU",
    "sg:address":"63 Sheppard St",
    "sg:city":"Hume",
    "sg:classifiers":[
        {
            "category":"Home & Garden",
            "subcategory":"Building Materials",
            "type":"Retail Goods"
        }
    ],
    "sg:phone":"+61 2 6260 1511",
    "sg:postcode":"2620",
    "sg:province":"ACT",
    "sg:tags":[
        "balustrading"
    ],
    "wof:name":"Argus Home Improvement Products",
    "wof:placetype":"venue"
},
  "geometry": {"coordinates":[149.165649414,-35.3921813965],"type":"Point"}
}