{
  "type": "Feature",
  "properties": {
    "addr:full":"1321 High Street Rd Wantirna VIC 3152",
    "addr:housenumber":"1321",
    "addr:postcode":"3152",
    "addr:street":"High Street Rd",
    "iso:country":"AU",
    "sg:address":"1321 High Street Rd",
    "sg:city":"Wantirna",
    "sg:classifiers":[
        {
            "category":"Autos & Motor Vehicles",
            "subcategory":"Fuel & Gas Station",
            "type":"Retail Goods"
        }
    ],
    "sg:phone":"+61 3 9887 5233",
    "sg:postcode":"3152",
    "sg:province":"VIC",
    "wof:name":"Better Choice",
    "wof:placetype":"venue"
},
  "geometry": {"coordinates":[145.22215270999999,-37.8766059875],"type":"Point"}
}