{
  "type": "Feature",
  "properties": {
    "addr:full":"587 Pacific Hwy Kanwal NSW 2259",
    "addr:housenumber":"587",
    "addr:postcode":"2259",
    "addr:street":"Pacific Hwy",
    "iso:country":"AU",
    "sg:address":"587 Pacific Hwy",
    "sg:city":"Kanwal",
    "sg:classifiers":[
        {
            "category":"Shopping",
            "subcategory":"Pets & Pet Supplies",
            "type":"Retail Goods"
        }
    ],
    "sg:phone":"+61 2 4392 7388",
    "sg:postcode":"2259",
    "sg:province":"NSW",
    "sg:tags":[
        "food"
    ],
    "wof:name":"Radleys Farm Pet & Garden Supplies",
    "wof:placetype":"venue"
},
  "geometry": {"coordinates":[151.48600769000001,-33.2576904297],"type":"Point"}
}