{
  "type": "Feature",
  "properties": {
    "iso:country":"AU",
    "sg:address":"54 Albert St",
    "sg:city":"Warragul",
    "sg:classifiers":[
        {
            "category":"Health Services",
            "subcategory":"Dentist",
            "type":"Services"
        }
    ],
    "sg:phone":"+61 3 5623 1861",
    "sg:postcode":"3820",
    "sg:province":"VIC",
    "wof:name":"Albert Street Dental Group",
    "wof:placetype":"venue"
},
  "geometry": {"coordinates":[145.934174,-38.160088],"type":"Point"}
}