{
  "type": "Feature",
  "properties": {
    "iso:country":"AU",
    "sg:address":"Cnr Hunter & Partridge Sts",
    "sg:city":"Charleville",
    "sg:classifiers":[
        {
            "category":"Education",
            "subcategory":"School",
            "type":"Public Place"
        }
    ],
    "sg:phone":"+61 7 4656 8888",
    "sg:postcode":"4470",
    "sg:province":"QLD",
    "sg:tags":[
        "state",
        "except",
        "nsw"
    ],
    "wof:name":"Charleville High School",
    "wof:placetype":"venue"
},
  "geometry": {"coordinates":[146.24920654300001,-26.4039325714],"type":"Point"}
}