{
  "type": "Feature",
  "properties": {
    "iso:country":"AU",
    "sg:address":"Shop 3/ 68 Hotham St",
    "sg:city":"Traralgon",
    "sg:classifiers":[
        {
            "category":"Personal",
            "subcategory":"Beauty Salon",
            "type":"Services"
        }
    ],
    "sg:phone":"+61 3 5174 6572",
    "sg:postcode":"3844",
    "sg:province":"VIC",
    "sg:tags":[
        "hairdresser"
    ],
    "wof:name":"Tosch D A",
    "wof:placetype":"venue"
},
  "geometry": {"coordinates":[146.53613281200001,-38.1973419189],"type":"Point"}
}