{
  "type": "Feature",
  "properties": {
    "iso:country":"AU",
    "sg:address":"405a Crown St",
    "sg:city":"Wollongong",
    "sg:classifiers":[
        {
            "category":"Building & Trades",
            "subcategory":"Cleaning & Sanitation",
            "type":"Services"
        }
    ],
    "sg:phone":"+61 2 4226 3253",
    "sg:postcode":"2500",
    "sg:province":"NSW",
    "sg:tags":[
        "cleaner",
        "repairer",
        "roof"
    ],
    "wof:name":"Re-Kote Roof Restorations",
    "wof:placetype":"venue"
},
  "geometry": {"coordinates":[150.881515503,-34.4261054993],"type":"Point"}
}