{
  "type": "Feature",
  "properties": {
    "iso:country":"AU",
    "sg:address":"1 Ringwood Rd",
    "sg:city":"Morphett Vale",
    "sg:classifiers":[
        {
            "category":"Building & Trades",
            "subcategory":"Construction",
            "type":"Services"
        }
    ],
    "sg:phone":"+61 8 8326 3330",
    "sg:postcode":"5162",
    "sg:province":"SA",
    "sg:tags":[
        "insulation",
        "contractor"
    ],
    "wof:name":"Polson Ceilings",
    "wof:placetype":"venue"
},
  "geometry": {"coordinates":[138.519088745,-35.1258811951],"type":"Point"}
}