{
  "type": "Feature",
  "properties": {
    "iso:country":"AU",
    "sg:address":"551 Wickham Tce",
    "sg:city":"Spring Hill",
    "sg:classifiers":[
        {
            "category":"Travel",
            "subcategory":"Hotels & Motels",
            "type":"Entertainment"
        }
    ],
    "sg:phone":"+61 7 3831 3111",
    "sg:postcode":"4000",
    "sg:province":"QLD",
    "sg:tags":[
        "accommodation"
    ],
    "sg:website":"http://www.hotelwatermarkbrisbane.com.au",
    "wof:name":"Watermark Hotel Brisbane",
    "wof:placetype":"venue"
},
  "geometry": {"coordinates":[153.01919555699999,-27.4611492157],"type":"Point"}
}