{
  "type": "Feature",
  "properties": {
    "iso:country":"AU",
    "sg:address":"Building 2, 75 Mary St",
    "sg:city":"St Peters",
    "sg:classifiers":[
        {
            "category":"Arts & Performance",
            "subcategory":"Theater",
            "type":"Entertainment"
        }
    ],
    "sg:phone":"+61 2 9519 4322",
    "sg:postcode":"2044",
    "sg:province":"NSW",
    "sg:tags":[
        "theatrical",
        "supply"
    ],
    "wof:name":"Anthony Phillips Costumes",
    "wof:placetype":"venue"
},
  "geometry": {"coordinates":[151.17257699999999,-33.91317],"type":"Point"}
}