{
  "type": "Feature",
  "properties": {
    "addr:full":"56 Dundas Crt Phillip ACT 2606",
    "addr:housenumber":"56",
    "addr:postcode":"2606",
    "addr:street":"Dundas Crt",
    "iso:country":"AU",
    "sg:address":"56 Dundas Crt",
    "sg:city":"Phillip",
    "sg:classifiers":[
        {
            "category":"Home & Garden",
            "subcategory":"Hardware",
            "type":"Retail Goods"
        }
    ],
    "sg:phone":"+61 2 6285 2608",
    "sg:postcode":"2606",
    "sg:province":"ACT",
    "sg:tags":[
        "plumber",
        "supply"
    ],
    "wof:name":"Reece Pty Ltd",
    "wof:placetype":"venue"
},
  "geometry": {"coordinates":[149.08792114299999,-35.3546638489],"type":"Point"}
}