{
  "type": "Feature",
  "properties": {
    "addr:full":"Cairns Central McLeod St Cairns QLD 4870",
    "addr:postcode":"4870",
    "addr:street":"St",
    "iso:country":"AU",
    "sg:address":"Cairns Central McLeod St",
    "sg:city":"Cairns",
    "sg:classifiers":[
        {
            "category":"Professional",
            "subcategory":"Art Services",
            "type":"Services"
        }
    ],
    "sg:phone":"+61 7 4041 4354",
    "sg:postcode":"4870",
    "sg:province":"QLD",
    "wof:name":"Q E Designs",
    "wof:placetype":"venue"
},
  "geometry": {"coordinates":[145.774169922,-16.926197052],"type":"Point"}
}