{
  "type": "Feature",
  "properties": {
    "addr:full":"Shop 5 Old Post Office Arcade George St Windsor NSW 2756",
    "addr:housenumber":"shop 5;post",
    "addr:postcode":"2756",
    "addr:street":"Old;Arcade George St",
    "iso:country":"AU",
    "sg:address":"Shop 5 Old Post Office Arcade George St",
    "sg:city":"Windsor",
    "sg:classifiers":[
        {
            "category":"Shopping",
            "subcategory":"Crafts & Fabrics",
            "type":"Retail Goods"
        }
    ],
    "sg:phone":"+61 2 4577 9100",
    "sg:postcode":"2756",
    "sg:province":"NSW",
    "sg:tags":[
        "supply"
    ],
    "wof:name":"Stamps & Stuff",
    "wof:placetype":"venue"
},
  "geometry": {"coordinates":[150.816970825,-33.6093215942],"type":"Point"}
}