{
  "type": "Feature",
  "properties": {
    "addr:full":"7/ 41 Badgally Rd Campbelltown NSW 2560",
    "addr:housenumber":"/ 41",
    "addr:postcode":"2560",
    "addr:street":"Badgally Rd",
    "iso:country":"AU",
    "sg:address":"7/ 41 Badgally Rd",
    "sg:city":"Campbelltown",
    "sg:classifiers":[
        {
            "category":"Autos & Motor Vehicles",
            "subcategory":"Auto Supplies",
            "type":"Retail Goods"
        }
    ],
    "sg:phone":"+61 2 4626 7711",
    "sg:postcode":"2560",
    "sg:province":"NSW",
    "sg:tags":[
        "tyre"
    ],
    "wof:name":"Blaxland Road Auto Tyre & Steer",
    "wof:placetype":"venue"
},
  "geometry": {"coordinates":[150.81413269000001,-34.0600738525],"type":"Point"}
}