{
  "type": "Feature",
  "properties": {
    "addr:full":"31 Albert Coates La Melbourne VIC 3000",
    "addr:housenumber":"31",
    "addr:postcode":"3000",
    "addr:street":"Albert Coates La",
    "iso:country":"AU",
    "sg:address":"31 Albert Coates La",
    "sg:city":"Melbourne",
    "sg:classifiers":[
        {
            "category":"Cafe",
            "type":"Food & Drink"
        }
    ],
    "sg:phone":"+61 3 9663 7026",
    "sg:postcode":"3000",
    "sg:province":"VIC",
    "wof:name":"Wedge Cafe The",
    "wof:placetype":"venue"
},
  "geometry": {"coordinates":[144.96507263199999,-37.8110466003],"type":"Point"}
}