{
  "type": "Feature",
  "properties": {
    "iso:country":"AU",
    "sg:address":"15/ 2 Executive Drv",
    "sg:city":"Burleigh Heads",
    "sg:classifiers":[
        {
            "category":"Banks & Credit Unions",
            "subcategory":"Financial Services",
            "type":"Services"
        }
    ],
    "sg:phone":"+61 7 5522 0020",
    "sg:postcode":"4220",
    "sg:province":"QLD",
    "sg:tags":[
        "planning"
    ],
    "wof:name":"Surfside Financial Services",
    "wof:placetype":"venue"
},
  "geometry": {"coordinates":[153.42283630399999,-28.0999984741],"type":"Point"}
}