{
  "type": "Feature",
  "properties": {
    "iso:country":"AU",
    "sg:address":"11 Sunrise Drv",
    "sg:city":"Boambee East",
    "sg:classifiers":[
        {
            "category":"Retail",
            "subcategory":"Repair Shop",
            "type":"Services"
        }
    ],
    "sg:phone":"+61 2 6658 6262",
    "sg:postcode":"2452",
    "sg:province":"NSW",
    "sg:tags":[
        "maintenance",
        "pool",
        "swimming"
    ],
    "wof:name":"C-Side Pool Service",
    "wof:placetype":"venue"
},
  "geometry": {"coordinates":[153.07188400000001,-30.353889],"type":"Point"}
}