{
  "type": "Feature",
  "properties": {
    "addr:full":"2 Railway Rd Tyabb VIC 3913",
    "addr:housenumber":"2",
    "addr:postcode":"3913",
    "addr:street":"Railway Rd",
    "iso:country":"AU",
    "sg:address":"2 Railway Rd",
    "sg:city":"Tyabb",
    "sg:classifiers":[
        {
            "category":"School Buses",
            "type":"Transportation"
        }
    ],
    "sg:phone":"+61 3 5977 4011",
    "sg:postcode":"3913",
    "sg:province":"VIC",
    "sg:tags":[
        "resistor"
    ],
    "wof:name":"Hurtle Webster Pty Ltd",
    "wof:placetype":"venue"
},
  "geometry": {"coordinates":[145.18882751500001,-38.2720069885],"type":"Point"}
}