{
  "type": "Feature",
  "properties": {
    "iso:country":"AU",
    "sg:address":"45-49 William St",
    "sg:city":"Tatura",
    "sg:classifiers":[
        {
            "category":"Manufacturing",
            "subcategory":"Metals",
            "type":"Manufacturing & Wholesale Goods"
        }
    ],
    "sg:phone":"+61 3 5824 3231",
    "sg:postcode":"3616",
    "sg:province":"VIC",
    "sg:tags":[
        "steel",
        "fabricator",
        "mfrs"
    ],
    "wof:name":"P F Engineering Developments Pty Ltd",
    "wof:placetype":"venue"
},
  "geometry": {"coordinates":[145.228881836,-36.434589386],"type":"Point"}
}