{
  "type": "Feature",
  "properties": {
    "addr:full":"187 Adelaide Rd Murray Bridge SA 5253",
    "addr:housenumber":"187",
    "addr:postcode":"5253",
    "addr:street":"Adelaide Rd",
    "iso:country":"AU",
    "sg:address":"187 Adelaide Rd",
    "sg:city":"Murray Bridge",
    "sg:classifiers":[
        {
            "category":"Food & Beverages",
            "subcategory":"Meat & Fish",
            "type":"Retail Goods"
        }
    ],
    "sg:phone":"+61 8 8532 3256",
    "sg:postcode":"5253",
    "sg:province":"SA",
    "sg:tags":[
        "seafood"
    ],
    "wof:name":"Nicks Fishmarket",
    "wof:placetype":"venue"
},
  "geometry": {"coordinates":[139.26832580600001,-35.1221313477],"type":"Point"}
}