{
  "type": "Feature",
  "properties": {
    "addr:full":"395 Mt Lyall Rd Nyora VIC 3987",
    "addr:housenumber":"395",
    "addr:postcode":"3987",
    "addr:street":"Mt Lyall Rd",
    "iso:country":"AU",
    "sg:address":"395 Mt Lyall Rd",
    "sg:city":"Nyora",
    "sg:classifiers":[
        {
            "category":"Farming",
            "subcategory":"Farm",
            "type":"Manufacturing & Wholesale Goods"
        }
    ],
    "sg:phone":"+61 3 5659 9239",
    "sg:postcode":"3987",
    "sg:province":"VIC",
    "sg:tags":[
        "farmer"
    ],
    "wof:name":"Barry W J & J L",
    "wof:placetype":"venue"
},
  "geometry": {"coordinates":[145.699142456,-38.2715187073],"type":"Point"}
}