{
  "type": "Feature",
  "properties": {
    "addr:full":"Suite 1, 16 Walan St Mooloolaba QLD 4557",
    "addr:housenumber":"16",
    "addr:postcode":"4557",
    "addr:street":"Walan St",
    "iso:country":"AU",
    "sg:address":"Suite 1, 16 Walan St",
    "sg:city":"Mooloolaba",
    "sg:classifiers":[
        {
            "category":"Health Services",
            "subcategory":"Health Practitioner",
            "type":"Services"
        }
    ],
    "sg:phone":"+61 7 5444 0394",
    "sg:postcode":"4557",
    "sg:province":"QLD",
    "sg:tags":[
        "physiotherapist"
    ],
    "wof:name":"Performance Physio & Rehab",
    "wof:placetype":"venue"
},
  "geometry": {"coordinates":[153.117950439,-26.6811656952],"type":"Point"}
}