{
  "type": "Feature",
  "properties": {
    "iso:country":"AU",
    "sg:address":"218- 220 Hammond Rd",
    "sg:city":"Dandenong South",
    "sg:classifiers":[
        {
            "category":"Banks & Credit Unions",
            "subcategory":"Bank",
            "type":"Services"
        }
    ],
    "sg:phone":"+61 3 9767 4111",
    "sg:postcode":"3175",
    "sg:province":"VIC",
    "sg:tags":[
        "equipment",
        "sale",
        "point"
    ],
    "wof:name":"Blitz By Design (Aust) Pty Ltd",
    "wof:placetype":"venue"
},
  "geometry": {"coordinates":[145.204910278,-38.0170288086],"type":"Point"}
}