{
  "type": "Feature",
  "properties": {
    "addr:full":"7 Wells St Gosford East NSW 2250",
    "addr:housenumber":"7",
    "addr:postcode":"2250",
    "addr:street":"Wells St",
    "iso:country":"AU",
    "sg:address":"7 Wells St",
    "sg:city":"Gosford East",
    "sg:classifiers":[
        {
            "category":"Recreation",
            "subcategory":"Fishing",
            "type":"Entertainment"
        }
    ],
    "sg:phone":"+61 2 4325 4255",
    "sg:postcode":"2250",
    "sg:province":"NSW",
    "sg:tags":[
        "tackle"
    ],
    "wof:name":"Coastline Bait & Tackle",
    "wof:placetype":"venue"
},
  "geometry": {"coordinates":[151.35028076200001,-33.4360771179],"type":"Point"}
}