{
  "type": "Feature",
  "properties": {
    "iso:country":"AU",
    "sg:address":"Shop 16 Brandon Park Shopping Cntr",
    "sg:city":"Brandon Park",
    "sg:classifiers":[
        {
            "category":"Shopping",
            "subcategory":"Mobile Phones",
            "type":"Retail Goods"
        }
    ],
    "sg:phone":"+61 3 9560 4522",
    "sg:postcode":"3170",
    "sg:province":"VIC",
    "sg:tags":[
        "telephone",
        "accessory"
    ],
    "wof:name":"Telstra Dealer Brandon Park",
    "wof:placetype":"venue"
},
  "geometry": {"coordinates":[145.17161560100001,-37.9170379639],"type":"Point"}
}