{
  "type": "Feature",
  "properties": {
    "iso:country":"AU",
    "sg:address":"3 Gollan St",
    "sg:city":"Ulverstone",
    "sg:classifiers":[
        {
            "category":"Sports & Exercise",
            "subcategory":"Gym",
            "type":"Entertainment"
        }
    ],
    "sg:phone":"+61 3 6425 1112",
    "sg:postcode":"7315",
    "sg:province":"TAS",
    "sg:tags":[
        "personal",
        "trainer",
        "fitness"
    ],
    "wof:name":"O 2 9 T",
    "wof:placetype":"venue"
},
  "geometry": {"coordinates":[146.17036438,-41.1586494446],"type":"Point"}
}