{
  "type": "Feature",
  "properties": {
    "addr:full":"309 Western Hwy Ararat VIC 3377",
    "addr:housenumber":"309",
    "addr:postcode":"3377",
    "addr:street":"Western Hwy",
    "iso:country":"AU",
    "sg:address":"309 Western Hwy",
    "sg:city":"Ararat",
    "sg:classifiers":[
        {
            "category":"Building & Trades",
            "subcategory":"Cleaning & Sanitation",
            "type":"Services"
        }
    ],
    "sg:phone":"+61 3 5352 2833",
    "sg:postcode":"3377",
    "sg:province":"VIC",
    "sg:tags":[
        "tank",
        "septic"
    ],
    "wof:name":"Ararat & District Septic Tank Cleaning",
    "wof:placetype":"venue"
},
  "geometry": {"coordinates":[142.91729736299999,-37.2613182068],"type":"Point"}
}