{
  "type": "Feature",
  "properties": {
    "addr:full":"3a Pittwater Rd Gladesville NSW 2111",
    "addr:housenumber":"3a",
    "addr:postcode":"2111",
    "addr:street":"Pittwater Rd",
    "iso:country":"AU",
    "sg:address":"3a Pittwater Rd",
    "sg:city":"Gladesville",
    "sg:classifiers":[
        {
            "category":"Health Services",
            "subcategory":"Doctor",
            "type":"Services"
        }
    ],
    "sg:phone":"+61 2 9817 2522",
    "sg:postcode":"2111",
    "sg:province":"NSW",
    "sg:tags":[
        "medical",
        "practitioner"
    ],
    "wof:name":"Davies Eileen P",
    "wof:placetype":"venue"
},
  "geometry": {"coordinates":[151.12739563,-33.8299865723],"type":"Point"}
}