{
  "type": "Feature",
  "properties": {
    "addr:full":"P.O.Box 376 Castle Hill Nsw 1765 Castle Hill NSW 2154",
    "addr:housenumber":"376",
    "addr:postcode":"1765;2154",
    "addr:street":"P.O.Box",
    "iso:country":"AU",
    "sg:address":"P.O.Box 376 Castle Hill Nsw 1765",
    "sg:city":"Castle Hill",
    "sg:classifiers":[
        {
            "category":"Professional",
            "subcategory":"Art Services",
            "type":"Services"
        }
    ],
    "sg:phone":"+61 2 9654 8800",
    "sg:postcode":"2154",
    "sg:province":"NSW",
    "sg:tags":[
        "graphic",
        "designer"
    ],
    "wof:name":"Grafmex",
    "wof:placetype":"venue"
},
  "geometry": {"coordinates":[151.01724243199999,-33.7308578491],"type":"Point"}
}