{
  "type": "Feature",
  "properties": {
    "addr:full":"Suite 101- 102/ 30 Fisher Rd Dee Why NSW 2099",
    "addr:housenumber":"102 / 30",
    "addr:postcode":"2099",
    "addr:street":"Fisher Rd",
    "iso:country":"AU",
    "sg:address":"Suite 101- 102/ 30 Fisher Rd",
    "sg:city":"Dee Why",
    "sg:classifiers":[
        {
            "category":"Health Services",
            "subcategory":"Health Practitioner",
            "type":"Services"
        }
    ],
    "sg:phone":"+61 2 9981 1049",
    "sg:postcode":"2099",
    "sg:province":"NSW",
    "sg:tags":[
        "osteopath"
    ],
    "wof:name":"Tobias-Szabo Gyula",
    "wof:placetype":"venue"
},
  "geometry": {"coordinates":[151.28480529800001,-33.7525482178],"type":"Point"}
}