{
  "type": "Feature",
  "properties": {
    "addr:full":"118 Macquarie St Dubbo NSW 2830",
    "addr:housenumber":"118",
    "addr:postcode":"2830",
    "addr:street":"Macquarie St",
    "iso:country":"AU",
    "sg:address":"118 Macquarie St",
    "sg:city":"Dubbo",
    "sg:classifiers":[
        {
            "category":"Health Services",
            "subcategory":"Dentist",
            "type":"Services"
        }
    ],
    "sg:phone":"+61 1300 306 084",
    "sg:postcode":"2830",
    "sg:province":"NSW",
    "wof:name":"Wisdom Teeth and Dental Implant Service",
    "wof:placetype":"venue"
},
  "geometry": {"coordinates":[148.60227966299999,-32.2628364563],"type":"Point"}
}