{
  "type": "Feature",
  "properties": {
    "addr:full":"36 South Rd Torrensville SA 5031",
    "addr:housenumber":"36",
    "addr:postcode":"5031",
    "addr:street":"South Rd",
    "iso:country":"AU",
    "sg:address":"36 South Rd",
    "sg:city":"Torrensville",
    "sg:classifiers":[
        {
            "category":"Manufacturing",
            "subcategory":"Food",
            "type":"Manufacturing & Wholesale Goods"
        }
    ],
    "sg:phone":"+61 8 8234 1123",
    "sg:postcode":"5031",
    "sg:province":"SA",
    "sg:tags":[
        "function",
        "catering"
    ],
    "wof:name":"Scrummys Cakes & Pastries",
    "wof:placetype":"venue"
},
  "geometry": {"coordinates":[138.56524658199999,-34.9136199951],"type":"Point"}
}