{
  "type": "Feature",
  "properties": {
    "addr:full":"177 Rosedale Rd St Ives NSW 2075",
    "addr:housenumber":"177",
    "addr:postcode":"2075",
    "addr:street":"Rosedale Rd",
    "iso:country":"AU",
    "sg:address":"177 Rosedale Rd",
    "sg:city":"St Ives",
    "sg:classifiers":[
        {
            "category":"Organizations",
            "subcategory":"Non-profit Organization",
            "type":"Services"
        }
    ],
    "sg:phone":"+61 2 9449 5355",
    "sg:postcode":"2075",
    "sg:province":"NSW",
    "sg:tags":[
        "support",
        "disability",
        "organisation"
    ],
    "wof:name":"Action For People with Disability",
    "wof:placetype":"venue"
},
  "geometry": {"coordinates":[151.16090393100001,-33.7307739258],"type":"Point"}
}