{
  "type": "Feature",
  "properties": {
    "addr:full":"10/ 31 York St St Kilda VIC 3182",
    "addr:housenumber":"10 / 31",
    "addr:postcode":"3182",
    "addr:street":"York St",
    "iso:country":"AU",
    "sg:address":"10/ 31 York St St",
    "sg:city":"Kilda",
    "sg:classifiers":[
        {
            "category":"Ferry Terminal",
            "type":"Transportation"
        }
    ],
    "sg:phone":"+61 418 817 924",
    "sg:postcode":"3182",
    "sg:province":"VIC",
    "sg:tags":[
        "raised",
        "floor"
    ],
    "wof:name":"Microfloor Systems Pty Ltd",
    "wof:placetype":"venue"
},
  "geometry": {"coordinates":[144.97056579599999,-37.8560562134],"type":"Point"}
}