{
  "type": "Feature",
  "properties": {
    "addr:full":"5 Lock Ave Werribee VIC 3030",
    "addr:housenumber":"5",
    "addr:postcode":"3030",
    "addr:street":"Lock Ave",
    "iso:country":"AU",
    "sg:address":"5 Lock Ave",
    "sg:city":"Werribee",
    "sg:classifiers":[
        {
            "category":"Retail",
            "subcategory":"Repair Shop",
            "type":"Services"
        }
    ],
    "sg:phone":"+61 3 9741 1842",
    "sg:postcode":"3030",
    "sg:province":"VIC",
    "sg:tags":[
        "upholsterer"
    ],
    "wof:name":"Werribee Upholstery",
    "wof:placetype":"venue"
},
  "geometry": {"coordinates":[144.662003,-37.911594],"type":"Point"}
}