{
  "type": "Feature",
  "properties": {
    "addr:full":"Shp3/ 10 Sherebrooke Blv Woodcroft SA 5162",
    "addr:postcode":"5162",
    "addr:street":"Sherebrooke Blv",
    "iso:country":"AU",
    "sg:address":"Shp3/ 10 Sherebrooke Blv",
    "sg:city":"Woodcroft",
    "sg:classifiers":[
        {
            "category":"Deli",
            "type":"Food & Drink"
        }
    ],
    "sg:phone":"+61 8 8322 6344",
    "sg:postcode":"5162",
    "sg:province":"SA",
    "sg:tags":[
        "delicatessen"
    ],
    "wof:name":"Woodcroft 7 Day Deli",
    "wof:placetype":"venue"
},
  "geometry": {"coordinates":[138.552124023,-35.094329834],"type":"Point"}
}