{
  "type": "Feature",
  "properties": {
    "iso:country":"AU",
    "sg:address":"9 Artisan Rd",
    "sg:city":"Seven Hills",
    "sg:classifiers":[
        {
            "category":"Banks & Credit Unions",
            "subcategory":"Bureau De Change",
            "type":"Services"
        }
    ],
    "sg:phone":"+61 2 9674 3444",
    "sg:postcode":"2147",
    "sg:province":"NSW",
    "sg:tags":[
        "repairs",
        "part",
        "appliance",
        "electrical"
    ],
    "wof:name":"GEC Electrical Wholesale",
    "wof:placetype":"venue"
},
  "geometry": {"coordinates":[150.95826721200001,-33.7757339478],"type":"Point"}
}