{
  "type": "Feature",
  "properties": {
    "addr:full":"Shop 4 Mt Baker Central Mt Barker SA 5251",
    "addr:housenumber":"shop 4",
    "addr:postcode":"5251",
    "addr:street":"Mt Baker Central Mt",
    "iso:country":"AU",
    "sg:address":"Shop 4",
    "sg:city":"Mt Baker Central Mt Barker",
    "sg:classifiers":[
        {
            "category":"Ice Cream",
            "type":"Food & Drink"
        }
    ],
    "sg:phone":"+61 8 8398 2709",
    "sg:postcode":"5251",
    "sg:province":"SA",
    "sg:tags":[
        "retail"
    ],
    "wof:name":"Wendys",
    "wof:placetype":"venue"
},
  "geometry": {"coordinates":[138.85289001500001,-35.0617103577],"type":"Point"}
}