{
  "type": "Feature",
  "properties": {
    "iso:country":"AU",
    "sg:address":"39 Chalder St",
    "sg:city":"Marrickville",
    "sg:classifiers":[
        {
            "category":"Retail",
            "subcategory":"Laundry & Dry Cleaning",
            "type":"Services"
        }
    ],
    "sg:phone":"+61 2 9560 0529",
    "sg:postcode":"2204",
    "sg:province":"NSW",
    "wof:name":"Cleana Service Pty Ltd",
    "wof:placetype":"venue"
},
  "geometry": {"coordinates":[151.16348300000001,-33.906857],"type":"Point"}
}