{
  "type": "Feature",
  "properties": {
    "addr:full":"11 Flinders St Kent Town SA 5067",
    "addr:housenumber":"11",
    "addr:postcode":"5067",
    "addr:street":"Flinders St",
    "iso:country":"AU",
    "sg:address":"11 Flinders St",
    "sg:city":"Kent Town",
    "sg:classifiers":[
        {
            "category":"Building & Trades",
            "subcategory":"Landscaping Services",
            "type":"Services"
        }
    ],
    "sg:phone":"+61 412 300 764",
    "sg:postcode":"5067",
    "sg:province":"SA",
    "sg:tags":[
        "designer",
        "landscape",
        "contractor"
    ],
    "wof:name":"Kloeden Susan Design",
    "wof:placetype":"venue"
},
  "geometry": {"coordinates":[138.619903564,-34.9244537354],"type":"Point"}
}