{
  "type": "Feature",
  "properties": {
    "iso:country":"AU",
    "sg:address":"Suite 3/ 115 Nerang St",
    "sg:city":"Southport",
    "sg:classifiers":[
        {
            "category":"Health Services",
            "subcategory":"Doctor",
            "type":"Services"
        }
    ],
    "sg:phone":"+61 7 5532 3667",
    "sg:postcode":"4215",
    "sg:province":"QLD",
    "sg:tags":[
        "medical",
        "practitioner"
    ],
    "wof:name":"Bignell, Stephen Dr",
    "wof:placetype":"venue"
},
  "geometry": {"coordinates":[153.408081055,-27.9706840515],"type":"Point"}
}