{
  "type": "Feature",
  "properties": {
    "addr:full":"21 Nile St Fairfield Heights NSW 2165",
    "addr:housenumber":"21",
    "addr:postcode":"2165",
    "addr:street":"Nile St",
    "iso:country":"AU",
    "sg:address":"21 Nile St",
    "sg:city":"Fairfield Heights",
    "sg:classifiers":[
        {
            "category":"Mining & Drilling",
            "type":"Manufacturing & Wholesale Goods"
        }
    ],
    "sg:phone":"+61 400 448 533",
    "sg:postcode":"2165",
    "sg:province":"NSW",
    "sg:tags":[
        "concrete",
        "breaking",
        "grinding",
        "sawing"
    ],
    "wof:name":"A & S Concrete Cutting & Core Drilling Services",
    "wof:placetype":"venue"
},
  "geometry": {"coordinates":[150.93521118199999,-33.865322113],"type":"Point"}
}