{
  "type": "Feature",
  "properties": {
    "addr:full":"Factory 4, 69 - 77 Mark Anthony Drv Dandenong South VIC 3175",
    "addr:housenumber":"69 77",
    "addr:postcode":"3175",
    "addr:street":"Mark Anthony Drv",
    "iso:country":"AU",
    "sg:address":"Factory 4, 69 - 77 Mark Anthony Drv",
    "sg:city":"Dandenong South",
    "sg:classifiers":[
        {
            "category":"Building & Trades",
            "subcategory":"Construction",
            "type":"Services"
        }
    ],
    "sg:phone":"+61 3 9706 6848",
    "sg:postcode":"3175",
    "sg:province":"VIC",
    "sg:tags":[
        "insulation",
        "contractor"
    ],
    "wof:name":"Town & Country Insulation",
    "wof:placetype":"venue"
},
  "geometry": {"coordinates":[145.19508361800001,-38.032245636],"type":"Point"}
}