{
  "type": "Feature",
  "properties": {
    "addr:full":"Shp 6/ 46 Kurrajong Rd Casula NSW 2170",
    "addr:housenumber":"/ 46",
    "addr:postcode":"2170",
    "addr:street":"Kurrajong Rd",
    "iso:country":"AU",
    "sg:address":"Shp 6/ 46 Kurrajong Rd",
    "sg:city":"Casula",
    "sg:classifiers":[
        {
            "category":"Personal",
            "subcategory":"Beauty Salon",
            "type":"Services"
        }
    ],
    "sg:phone":"+61 2 9734 7770",
    "sg:postcode":"2170",
    "sg:province":"NSW",
    "wof:name":"C B N Nail & Hair Dressings",
    "wof:placetype":"venue"
},
  "geometry": {"coordinates":[150.87979125999999,-33.9437942505],"type":"Point"}
}