{
  "type": "Feature",
  "properties": {
    "iso:country":"AU",
    "sg:address":"19 Riverleigh Ave",
    "sg:city":"Gerroa",
    "sg:classifiers":[
        {
            "category":"Fast Food",
            "type":"Food & Drink"
        }
    ],
    "sg:phone":"+61 2 4464 1657",
    "sg:postcode":"2534",
    "sg:province":"NSW",
    "sg:tags":[
        "away",
        "take"
    ],
    "wof:name":"Seahaven",
    "wof:placetype":"venue"
},
  "geometry": {"coordinates":[150.811157227,-34.7698783875],"type":"Point"}
}