{
  "type": "Feature",
  "properties": {
    "addr:full":"Factory 5 / 2A Backwell St Geelong North VIC 3215",
    "addr:housenumber":"/ 2a",
    "addr:postcode":"3215",
    "addr:street":"Backwell St",
    "iso:country":"AU",
    "sg:address":"Factory 5 / 2A Backwell St",
    "sg:city":"Geelong North",
    "sg:classifiers":[
        {
            "category":"Building & Trades",
            "subcategory":"Construction",
            "type":"Services"
        }
    ],
    "sg:phone":"+61 3 5278 6688",
    "sg:postcode":"3215",
    "sg:province":"VIC",
    "sg:tags":[
        "joinery"
    ],
    "wof:name":"Newtown Kitchens & Cabinets",
    "wof:placetype":"venue"
},
  "geometry": {"coordinates":[144.34898376500001,-38.1231880188],"type":"Point"}
}