{
  "type": "Feature",
  "properties": {
    "addr:full":"349 Somerville Rd Footscray West VIC 3012",
    "addr:housenumber":"349",
    "addr:postcode":"3012",
    "addr:street":"Somerville Rd",
    "iso:country":"AU",
    "sg:address":"349 Somerville Rd",
    "sg:city":"Footscray West",
    "sg:classifiers":[
        {
            "category":"Communications",
            "subcategory":"Film & Video Production",
            "type":"Services"
        }
    ],
    "sg:phone":"+61 3 9314 9252",
    "sg:postcode":"3012",
    "sg:province":"VIC",
    "sg:tags":[
        "dvd",
        "library"
    ],
    "wof:name":"Network Video Home Entertainment Centre",
    "wof:placetype":"venue"
},
  "geometry": {"coordinates":[144.87037658700001,-37.8114395142],"type":"Point"}
}