{
  "type": "Feature",
  "properties": {
    "iso:country":"AU",
    "sg:address":"23 Cross St",
    "sg:city":"Glen Innes",
    "sg:classifiers":[
        {
            "category":"Building & Trades",
            "subcategory":"Landscaping Services",
            "type":"Services"
        }
    ],
    "sg:phone":"+61 2 6732 5552",
    "sg:postcode":"2370",
    "sg:province":"NSW",
    "sg:tags":[
        "consultant"
    ],
    "wof:name":"Northstate Building Services",
    "wof:placetype":"venue"
},
  "geometry": {"coordinates":[151.738937378,-29.7456092834],"type":"Point"}
}