{
  "type": "Feature",
  "properties": {
    "iso:country":"AU",
    "sg:address":"Unit 13 & 14, 45 Bassett St",
    "sg:city":"Mona Vale",
    "sg:classifiers":[
        {
            "category":"Retail",
            "subcategory":"Auto Repair",
            "type":"Services"
        }
    ],
    "sg:phone":"+61 2 9997 7247",
    "sg:postcode":"2103",
    "sg:province":"NSW",
    "sg:tags":[
        "repairer",
        "motor",
        "engineer"
    ],
    "wof:name":"S T Kar Kraft Pty Limited",
    "wof:placetype":"venue"
},
  "geometry": {"coordinates":[151.31048584000001,-33.6736297607],"type":"Point"}
}