{
  "type": "Feature",
  "properties": {
    "addr:full":"14 Rickard St Turrella NSW 2205",
    "addr:housenumber":"14",
    "addr:postcode":"2205",
    "addr:street":"Rickard St",
    "iso:country":"AU",
    "sg:address":"14 Rickard St",
    "sg:city":"Turrella",
    "sg:classifiers":[
        {
            "category":"Building & Trades",
            "subcategory":"Construction",
            "type":"Services"
        }
    ],
    "sg:phone":"+61 2 9567 6230",
    "sg:postcode":"2205",
    "sg:province":"NSW",
    "sg:tags":[
        "concrete",
        "contractor"
    ],
    "wof:name":"Righetto M",
    "wof:placetype":"venue"
},
  "geometry": {"coordinates":[151.13748200000001,-33.931808],"type":"Point"}
}