{
  "type": "Feature",
  "properties": {
    "addr:full":"130 Siandra Drv Kareela NSW 2232",
    "addr:housenumber":"130",
    "addr:postcode":"2232",
    "addr:street":"Siandra Drv",
    "iso:country":"AU",
    "sg:address":"130 Siandra Drv",
    "sg:city":"Kareela",
    "sg:classifiers":[
        {
            "category":"Social Services",
            "subcategory":"Retirement Home",
            "type":"Services"
        }
    ],
    "sg:phone":"+61 410 263 584",
    "sg:postcode":"2232",
    "sg:province":"NSW",
    "sg:tags":[
        "environmental",
        "consultant",
        "pollution"
    ],
    "wof:name":"PJW Consulting Water & Waste Water",
    "wof:placetype":"venue"
},
  "geometry": {"coordinates":[151.08143615700001,-34.0101623535],"type":"Point"}
}