{
  "type": "Feature",
  "properties": {
    "addr:full":"531 South Dowling St Surry Hills NSW 2010",
    "addr:housenumber":"531",
    "addr:postcode":"2010",
    "addr:street":"South Dowling St",
    "iso:country":"AU",
    "sg:address":"531 South Dowling St",
    "sg:city":"Surry Hills",
    "sg:classifiers":[
        {
            "category":"Shopping",
            "subcategory":"Antiques",
            "type":"Retail Goods"
        }
    ],
    "sg:phone":"+61 2 9361 3244",
    "sg:postcode":"2010",
    "sg:province":"NSW",
    "sg:website":"http://www.sydantcent.com.au",
    "wof:name":"Sydney Antique Centre",
    "wof:placetype":"venue"
},
  "geometry": {"coordinates":[151.21751403799999,-33.8875198364],"type":"Point"}
}