{
  "type": "Feature",
  "properties": {
    "addr:full":"3 Maritime Crt Gillman SA 5013",
    "addr:housenumber":"3",
    "addr:postcode":"5013",
    "addr:street":"Maritime Crt",
    "iso:country":"AU",
    "sg:address":"3 Maritime Crt",
    "sg:city":"Gillman",
    "sg:classifiers":[
        {
            "category":"Manufacturing",
            "subcategory":"Rubber & Plastics",
            "type":"Manufacturing & Wholesale Goods"
        }
    ],
    "sg:phone":"+61 8 8240 4334",
    "sg:postcode":"5013",
    "sg:province":"SA",
    "sg:tags":[
        "wholesaler",
        "product",
        "mfrs"
    ],
    "wof:name":"Laserlite Australia",
    "wof:placetype":"venue"
},
  "geometry": {"coordinates":[138.52557373100001,-34.8429794312],"type":"Point"}
}