{
  "type": "Feature",
  "properties": {
    "iso:country":"AU",
    "sg:address":"34 Downs St",
    "sg:city":"North Ipswich",
    "sg:classifiers":[
        {
            "category":"Retail",
            "subcategory":"Repair Shop",
            "type":"Services"
        }
    ],
    "sg:phone":"+61 7 3282 8233",
    "sg:postcode":"4305",
    "sg:province":"QLD",
    "sg:tags":[
        "maintenance",
        "pool",
        "swimming"
    ],
    "wof:name":"Ipswich Pool Supplies",
    "wof:placetype":"venue"
},
  "geometry": {"coordinates":[152.76138305699999,-27.6035366058],"type":"Point"}
}