{
  "type": "Feature",
  "properties": {
    "addr:full":"11 Douglas St Emerald QLD 4720",
    "addr:housenumber":"11",
    "addr:postcode":"4720",
    "addr:street":"Douglas St",
    "iso:country":"AU",
    "sg:address":"11 Douglas St",
    "sg:city":"Emerald",
    "sg:classifiers":[
        {
            "category":"Farming",
            "subcategory":"Farm",
            "type":"Manufacturing & Wholesale Goods"
        }
    ],
    "sg:phone":"+61 7 4982 1061",
    "sg:postcode":"4720",
    "sg:province":"QLD",
    "sg:tags":[
        "farmer"
    ],
    "wof:name":"Hayes L J & K L",
    "wof:placetype":"venue"
},
  "geometry": {"coordinates":[148.14762899999999,-23.5266],"type":"Point"}
}