{
  "type": "Feature",
  "properties": {
    "iso:country":"AU",
    "sg:address":"86 Elizabeth St",
    "sg:city":"Urangan",
    "sg:classifiers":[
        {
            "category":"Home & Garden",
            "subcategory":"Hardware",
            "type":"Retail Goods"
        }
    ],
    "sg:phone":"+61 7 4125 3666",
    "sg:postcode":"4655",
    "sg:province":"QLD",
    "sg:tags":[
        "repair",
        "tool",
        "power"
    ],
    "wof:name":"Fraser Coast Tools & Bearings",
    "wof:placetype":"venue"
},
  "geometry": {"coordinates":[152.895645,-25.290636],"type":"Point"}
}