{
  "type": "Feature",
  "properties": {
    "iso:country":"AU",
    "sg:address":"1B/ 70 Prospect Tce",
    "sg:city":"Kelvin Grove",
    "sg:classifiers":[
        {
            "category":"Personal",
            "subcategory":"Beauty Salon",
            "type":"Services"
        }
    ],
    "sg:phone":"+61 7 3356 6692",
    "sg:postcode":"4059",
    "sg:province":"QLD",
    "sg:tags":[
        "hair",
        "treatment",
        "replacement"
    ],
    "wof:name":"New Generation Hair Systems",
    "wof:placetype":"venue"
},
  "geometry": {"coordinates":[153.010696411,-27.4510498047],"type":"Point"}
}