{
  "type": "Feature",
  "properties": {
    "iso:country":"AU",
    "sg:address":"393 Kent St",
    "sg:city":"Maryborough",
    "sg:classifiers":[
        {
            "category":"Food & Beverages",
            "subcategory":"Bakery",
            "type":"Retail Goods"
        }
    ],
    "sg:phone":"+61 7 4123 2777",
    "sg:postcode":"3465",
    "sg:province":"VIC",
    "sg:tags":[
        "baker"
    ],
    "wof:name":"Brumbys",
    "wof:placetype":"venue"
},
  "geometry": {"coordinates":[143.73561096200001,-37.0486412048],"type":"Point"}
}