{
  "type": "Feature",
  "properties": {
    "iso:country":"AU",
    "sg:address":"Unit 12/ 52a Holker St",
    "sg:city":"Silverwater",
    "sg:classifiers":[
        {
            "category":"Building & Trades",
            "subcategory":"Equipment Rental",
            "type":"Services"
        }
    ],
    "sg:phone":"+61 1300 786 688",
    "sg:postcode":"2128",
    "sg:province":"NSW",
    "sg:tags":[
        "fitness"
    ],
    "wof:name":"PBM Fitness",
    "wof:placetype":"venue"
},
  "geometry": {"coordinates":[151.047317505,-33.8297157288],"type":"Point"}
}