{
  "type": "Feature",
  "properties": {
    "addr:full":"520 Main North Rd Blair Athol SA 5084",
    "addr:housenumber":"520",
    "addr:postcode":"5084",
    "addr:street":"Main North Rd",
    "iso:country":"AU",
    "sg:address":"520 Main North Rd",
    "sg:city":"Blair Athol",
    "sg:classifiers":[
        {
            "category":"Autos & Motor Vehicles",
            "subcategory":"Automobile Sales",
            "type":"Retail Goods"
        }
    ],
    "sg:phone":"+61 8 8260 3147",
    "sg:postcode":"5084",
    "sg:province":"SA",
    "sg:tags":[
        "bus",
        "used",
        "truck"
    ],
    "wof:name":"S A Bus & Truck Wholesalers",
    "wof:placetype":"venue"
},
  "geometry": {"coordinates":[138.60011291500001,-34.8502922058],"type":"Point"}
}