{
  "type": "Feature",
  "properties": {
    "addr:full":"7a Pendrey Crt Woodridge QLD 4114",
    "addr:housenumber":"7a",
    "addr:postcode":"4114",
    "addr:street":"Pendrey Crt",
    "iso:country":"AU",
    "sg:address":"7a Pendrey Crt",
    "sg:city":"Woodridge",
    "sg:classifiers":[
        {
            "category":"Professional",
            "subcategory":"Engineering",
            "type":"Services"
        }
    ],
    "sg:phone":"+61 7 3299 5411",
    "sg:postcode":"4114",
    "sg:province":"QLD",
    "sg:tags":[
        "engineer"
    ],
    "wof:name":"GJR Engineering",
    "wof:placetype":"venue"
},
  "geometry": {"coordinates":[153.118408203,-27.6499843597],"type":"Point"}
}