{
  "type": "Feature",
  "properties": {
    "addr:full":"21 Piper Drv Ballina NSW 2478",
    "addr:housenumber":"21",
    "addr:postcode":"2478",
    "addr:street":"Piper Drv",
    "iso:country":"AU",
    "sg:address":"21 Piper Drv",
    "sg:city":"Ballina",
    "sg:classifiers":[
        {
            "category":"Wholesale",
            "subcategory":"Painting Supplies",
            "type":"Manufacturing & Wholesale Goods"
        }
    ],
    "sg:phone":"+61 2 6686 0253",
    "sg:postcode":"2478",
    "sg:province":"NSW",
    "sg:tags":[
        "product",
        "polyurethane"
    ],
    "wof:name":"East Coast Polyurethane",
    "wof:placetype":"venue"
},
  "geometry": {"coordinates":[153.55621337900001,-28.8473300934],"type":"Point"}
}