{
  "type": "Feature",
  "properties": {
    "addr:full":"8 Ridgeway Ave Southport QLD 4215",
    "addr:housenumber":"8",
    "addr:postcode":"4215",
    "addr:street":"Ridgeway Ave",
    "iso:country":"AU",
    "sg:address":"8 Ridgeway Ave",
    "sg:city":"Southport",
    "sg:classifiers":[
        {
            "category":"Building & Trades",
            "subcategory":"Construction",
            "type":"Services"
        }
    ],
    "sg:phone":"+61 7 5531 3370",
    "sg:postcode":"4215",
    "sg:province":"QLD",
    "sg:tags":[
        "builder",
        "designer",
        "room",
        "cool"
    ],
    "wof:name":"D & L Concreting Contractors",
    "wof:placetype":"venue"
},
  "geometry": {"coordinates":[153.405593872,-27.9814338684],"type":"Point"}
}