{
  "type": "Feature",
  "properties": {
    "addr:full":"188 Murphy St Bendigo VIC 3550",
    "addr:housenumber":"188",
    "addr:postcode":"3550",
    "addr:street":"Murphy St",
    "iso:country":"AU",
    "sg:address":"188 Murphy St",
    "sg:city":"Bendigo",
    "sg:classifiers":[
        {
            "category":"Professional",
            "type":"Services"
        }
    ],
    "sg:phone":"+61 3 5443 1476",
    "sg:postcode":"3550",
    "sg:province":"VIC",
    "sg:tags":[
        "transport"
    ],
    "wof:name":"Fitzpatrick Transport",
    "wof:placetype":"venue"
},
  "geometry": {"coordinates":[144.30630493199999,-36.7430496216],"type":"Point"}
}