{
  "type": "Feature",
  "properties": {
    "iso:country":"AU",
    "sg:address":"8 Railway Ave",
    "sg:city":"Wahroonga",
    "sg:classifiers":[
        {
            "category":"Fast Food",
            "type":"Food & Drink"
        }
    ],
    "sg:phone":"+61 2 9489 3035",
    "sg:postcode":"2076",
    "sg:province":"NSW",
    "sg:tags":[
        "away",
        "take"
    ],
    "wof:name":"The Limetree Cafe",
    "wof:placetype":"venue"
},
  "geometry": {"coordinates":[151.11695861800001,-33.7184486389],"type":"Point"}
}