{
  "type": "Feature",
  "properties": {
    "iso:country":"AU",
    "sg:address":"2 Ian Oliver Drv",
    "sg:city":"Waikerie",
    "sg:classifiers":[
        {
            "category":"Parking",
            "subcategory":"Lot",
            "type":"Transportation"
        }
    ],
    "sg:phone":"+61 8 8541 0600",
    "sg:postcode":"5330",
    "sg:province":"SA",
    "sg:tags":[
        "vegetable",
        "packing",
        "fruit",
        "pack"
    ],
    "wof:name":"Nippys Wailerie Producers",
    "wof:placetype":"venue"
},
  "geometry": {"coordinates":[139.988082886,-34.1808929443],"type":"Point"}
}