{
  "type": "Feature",
  "properties": {
    "iso:country":"AU",
    "sg:address":"Unit 2/ 27 Clydesdale St",
    "sg:city":"Como",
    "sg:classifiers":[
        {
            "category":"Real Estate",
            "subcategory":"Architect",
            "type":"Services"
        }
    ],
    "sg:phone":"+61 8 9450 4315",
    "sg:postcode":"6152",
    "sg:province":"WA",
    "wof:name":"Jodrell Peter Architect",
    "wof:placetype":"venue"
},
  "geometry": {"coordinates":[115.861679,-32.008518],"type":"Point"}
}