{
  "type": "Feature",
  "properties": {
    "iso:country":"AU",
    "sg:address":"94a Wyralla Rd",
    "sg:city":"Miranda",
    "sg:classifiers":[
        {
            "category":"Banks & Credit Unions",
            "subcategory":"Financial Services",
            "type":"Services"
        }
    ],
    "sg:phone":"+61 2 9531 6638",
    "sg:postcode":"2228",
    "sg:province":"NSW",
    "sg:tags":[
        "planning"
    ],
    "wof:name":"Robert Les Woods P/L",
    "wof:placetype":"venue"
},
  "geometry": {"coordinates":[151.09536743199999,-34.0412216187],"type":"Point"}
}