{
  "type": "Feature",
  "properties": {
    "addr:full":"744 Hampton St Brighton VIC 3186",
    "addr:housenumber":"744",
    "addr:postcode":"3186",
    "addr:street":"Hampton St",
    "iso:country":"AU",
    "sg:address":"744 Hampton St",
    "sg:city":"Brighton",
    "sg:classifiers":[
        {
            "category":"Retail",
            "subcategory":"Auto Repair",
            "type":"Services"
        }
    ],
    "sg:phone":"+61 3 9592 7692",
    "sg:postcode":"3186",
    "sg:province":"VIC",
    "sg:tags":[
        "beater",
        "painter",
        "panel"
    ],
    "wof:name":"Dendy Panels",
    "wof:placetype":"venue"
},
  "geometry": {"coordinates":[145.006149292,-37.9192733765],"type":"Point"}
}