{
  "type": "Feature",
  "properties": {
    "addr:full":"9 Caleb St Bentleigh East VIC 3165",
    "addr:housenumber":"9",
    "addr:postcode":"3165",
    "addr:street":"Caleb St",
    "iso:country":"AU",
    "sg:address":"9 Caleb St",
    "sg:city":"Bentleigh East",
    "sg:classifiers":[
        {
            "category":"Utilities",
            "subcategory":"Natural Gas",
            "type":"Services"
        }
    ],
    "sg:phone":"+61 3 9483 4256",
    "sg:postcode":"3165",
    "sg:province":"VIC",
    "sg:tags":[
        "solid",
        "plasterer"
    ],
    "wof:name":"Plaster Repair Co.",
    "wof:placetype":"venue"
},
  "geometry": {"coordinates":[145.05723571799999,-37.9216346741],"type":"Point"}
}