{
  "type": "Feature",
  "properties": {
    "addr:full":"PO Box 228 Archerfield QLD 4108",
    "addr:postcode":"4108",
    "iso:country":"AU",
    "sg:address":"PO Box 228",
    "sg:city":"Archerfield",
    "sg:classifiers":[
        {
            "category":"Home & Garden",
            "subcategory":"Hardware",
            "type":"Retail Goods"
        }
    ],
    "sg:phone":"+61 7 3255 6366",
    "sg:postcode":"4108",
    "sg:province":"QLD",
    "sg:tags":[
        "generating",
        "set",
        "generator"
    ],
    "wof:name":"Generator Solutions (Aust) Pty LTD",
    "wof:placetype":"venue"
},
  "geometry": {"coordinates":[153.01492309599999,-27.5681705475],"type":"Point"}
}