{
  "type": "Feature",
  "properties": {
    "iso:country":"AU",
    "sg:address":"Lot 12/ 75 York Rd",
    "sg:city":"Northam",
    "sg:classifiers":[
        {
            "category":"Farming",
            "subcategory":"Farm & Veterinary Services",
            "type":"Manufacturing & Wholesale Goods"
        }
    ],
    "sg:phone":"+61 8 9622 7557",
    "sg:postcode":"6401",
    "sg:province":"WA",
    "sg:tags":[
        "agricultural",
        "advisory"
    ],
    "wof:name":"Wantfa",
    "wof:placetype":"venue"
},
  "geometry": {"coordinates":[116.695320129,-31.6524219513],"type":"Point"}
}