{
  "type": "Feature",
  "properties": {
    "addr:full":"Shop 3 17 Short St Port Macquarie NSW 2444",
    "addr:housenumber":"shop;17",
    "addr:postcode":"2444",
    "addr:street":"Short St",
    "iso:country":"AU",
    "sg:address":"Shop 3 17 Short St",
    "sg:city":"Port Macquarie",
    "sg:classifiers":[
        {
            "category":"Professional",
            "subcategory":"Art Services",
            "type":"Services"
        }
    ],
    "sg:phone":"+61 2 6583 3997",
    "sg:postcode":"2444",
    "sg:province":"NSW",
    "sg:tags":[
        "picture",
        "frame",
        "framing"
    ],
    "wof:name":"Port Art Craft & Framing",
    "wof:placetype":"venue"
},
  "geometry": {"coordinates":[152.90670800000001,-31.430433],"type":"Point"}
}