{
  "type": "Feature",
  "properties": {
    "addr:full":"38 Parriwi Rd Mosman NSW 2088",
    "addr:housenumber":"38",
    "addr:postcode":"2088",
    "addr:street":"Parriwi Rd",
    "iso:country":"AU",
    "sg:address":"38 Parriwi Rd",
    "sg:city":"Mosman",
    "sg:classifiers":[
        {
            "category":"Building & Trades",
            "subcategory":"Construction",
            "type":"Services"
        }
    ],
    "sg:phone":"+61 2 9960 6457",
    "sg:postcode":"2088",
    "sg:province":"NSW",
    "sg:tags":[
        "management"
    ],
    "wof:name":"M A Howard Constructions",
    "wof:placetype":"venue"
},
  "geometry": {"coordinates":[151.24505615199999,-33.8138046265],"type":"Point"}
}