{
  "type": "Feature",
  "properties": {
    "addr:full":"4/ 25 Paton St Woy Woy NSW 2256",
    "addr:housenumber":"/ 25",
    "addr:postcode":"2256",
    "addr:street":"Paton St",
    "iso:country":"AU",
    "sg:address":"4/ 25 Paton St",
    "sg:city":"Woy Woy",
    "sg:classifiers":[
        {
            "category":"Utilities",
            "subcategory":"Electric",
            "type":"Services"
        }
    ],
    "sg:phone":"+61 416 015 883",
    "sg:postcode":"2256",
    "sg:province":"NSW",
    "sg:tags":[
        "electrical",
        "contractor"
    ],
    "wof:name":"Ben Munson Electrical",
    "wof:placetype":"venue"
},
  "geometry": {"coordinates":[151.320678711,-33.489402771],"type":"Point"}
}