{
  "type": "Feature",
  "properties": {
    "addr:full":"734- 736 Pittwater Rd Brookvale NSW 2100",
    "addr:housenumber":"736",
    "addr:postcode":"2100",
    "addr:street":"Pittwater Rd",
    "iso:country":"AU",
    "sg:address":"734- 736 Pittwater Rd",
    "sg:city":"Brookvale",
    "sg:classifiers":[
        {
            "category":"Home & Garden",
            "subcategory":"Carpets & Floor Coverings",
            "type":"Retail Goods"
        }
    ],
    "sg:phone":"+61 2 9939 3090",
    "sg:postcode":"2100",
    "sg:province":"NSW",
    "sg:tags":[
        "tile",
        "wall"
    ],
    "wof:name":"C T M",
    "wof:placetype":"venue"
},
  "geometry": {"coordinates":[151.273803711,-33.7612876892],"type":"Point"}
}