{
  "type": "Feature",
  "properties": {
    "iso:country":"AU",
    "sg:address":"Wyndham Rd",
    "sg:city":"Pambula",
    "sg:classifiers":[
        {
            "category":"Home & Garden",
            "subcategory":"Building Materials",
            "type":"Retail Goods"
        }
    ],
    "sg:phone":"+61 2 6495 6644",
    "sg:postcode":"2549",
    "sg:province":"NSW",
    "sg:tags":[
        "pre-mixed",
        "concrete"
    ],
    "wof:name":"Boral Country-Concrete & Quarries",
    "wof:placetype":"venue"
},
  "geometry": {"coordinates":[149.87449645999999,-36.9297485352],"type":"Point"}
}