{
  "type": "Feature",
  "properties": {
    "addr:full":"2 Eden Crt Toorak VIC 3142",
    "addr:housenumber":"2",
    "addr:postcode":"3142",
    "addr:street":"Eden Crt",
    "iso:country":"AU",
    "sg:address":"2 Eden Crt",
    "sg:city":"Toorak",
    "sg:classifiers":[
        {
            "category":"Building & Trades",
            "subcategory":"Landscaping Services",
            "type":"Services"
        }
    ],
    "sg:phone":"+61 3 9824 5410",
    "sg:postcode":"3142",
    "sg:province":"VIC",
    "sg:tags":[
        "designer",
        "landscape",
        "contractor"
    ],
    "wof:name":"Sam Daniell Landscape Design",
    "wof:placetype":"venue"
},
  "geometry": {"coordinates":[145.02430725100001,-37.8448638916],"type":"Point"}
}