{
  "type": "Feature",
  "properties": {
    "iso:country":"AU",
    "sg:address":"Woori Yallock Shopping Centre Shop10/ 1585 Warburton Hwy",
    "sg:city":"Woori Yallock",
    "sg:classifiers":[
        {
            "category":"Personal",
            "subcategory":"Beauty Salon",
            "type":"Services"
        }
    ],
    "sg:phone":"+61 3 5964 7877",
    "sg:postcode":"3139",
    "sg:province":"VIC",
    "sg:tags":[
        "hairdresser"
    ],
    "wof:name":"Country Rose Salon",
    "wof:placetype":"venue"
},
  "geometry": {"coordinates":[145.53109741200001,-37.7786407471],"type":"Point"}
}