{
  "type": "Feature",
  "properties": {
    "addr:full":"85 Male St Brighton VIC 3186",
    "addr:housenumber":"85",
    "addr:postcode":"3186",
    "addr:street":"Male St",
    "iso:country":"AU",
    "sg:address":"85 Male St",
    "sg:city":"Brighton",
    "sg:classifiers":[
        {
            "category":"Personal",
            "type":"Services"
        }
    ],
    "sg:phone":"+61 3 9593 2208",
    "sg:postcode":"3186",
    "sg:province":"VIC",
    "sg:tags":[
        "dressmaker"
    ],
    "wof:name":"Vanessa Oliver-Couture Dress Maker",
    "wof:placetype":"venue"
},
  "geometry": {"coordinates":[145.00242614699999,-37.9118003845],"type":"Point"}
}