{
  "type": "Feature",
  "properties": {
    "addr:full":"Factory 15 Mansfield St Inverell NSW 2360",
    "addr:housenumber":"15",
    "addr:postcode":"2360",
    "addr:street":"Mansfield St",
    "iso:country":"AU",
    "sg:address":"Factory 15 Mansfield St",
    "sg:city":"Inverell",
    "sg:classifiers":[
        {
            "category":"Professional",
            "subcategory":"Engineering",
            "type":"Services"
        }
    ],
    "sg:phone":"+61 2 6721 2412",
    "sg:postcode":"2360",
    "sg:province":"NSW",
    "sg:tags":[
        "engineer",
        "mechanical"
    ],
    "wof:name":"G J Lavender Automotive Repairs",
    "wof:placetype":"venue"
},
  "geometry": {"coordinates":[151.11537170400001,-29.7696628571],"type":"Point"}
}