{
  "type": "Feature",
  "properties": {
    "iso:country":"AU",
    "sg:address":"Shop 2/ 12 Anderson Wlk",
    "sg:city":"Smithfield",
    "sg:classifiers":[
        {
            "category":"Manufacturing",
            "subcategory":"Electronics",
            "type":"Manufacturing & Wholesale Goods"
        }
    ],
    "sg:phone":"+61 8 8254 6217",
    "sg:postcode":"5114",
    "sg:province":"SA",
    "sg:tags":[
        "oven",
        "microwave"
    ],
    "wof:name":"Serviscope Aust Pty Ltd",
    "wof:placetype":"venue"
},
  "geometry": {"coordinates":[138.690185547,-34.6824302673],"type":"Point"}
}