{
  "type": "Feature",
  "properties": {
    "addr:full":"16 Aldidja St Alice Springs NT 0870",
    "addr:housenumber":"16",
    "addr:postcode":"nt 0870",
    "addr:street":"Aldidja St",
    "iso:country":"AU",
    "sg:address":"16 Aldidja St",
    "sg:city":"Alice Springs",
    "sg:classifiers":[
        {
            "category":"Building & Trades",
            "subcategory":"Construction",
            "type":"Services"
        }
    ],
    "sg:phone":"+61 417 800 577",
    "sg:postcode":"0870",
    "sg:province":"NT",
    "sg:tags":[
        "ceiling"
    ],
    "wof:name":"Westies Plastering",
    "wof:placetype":"venue"
},
  "geometry": {"coordinates":[133.87130737300001,-23.6783504486],"type":"Point"}
}