{
  "type": "Feature",
  "properties": {
    "addr:full":"111 Hart St Semaphore SA 5019",
    "addr:housenumber":"111",
    "addr:postcode":"5019",
    "addr:street":"Hart St",
    "iso:country":"AU",
    "sg:address":"111 Hart St",
    "sg:city":"Semaphore",
    "sg:classifiers":[
        {
            "category":"Retail",
            "subcategory":"Storage",
            "type":"Services"
        }
    ],
    "sg:phone":"+61 414 773 471",
    "sg:postcode":"5019",
    "sg:province":"SA",
    "sg:tags":[
        "removal",
        "furniture"
    ],
    "wof:name":"G S Furniture Express",
    "wof:placetype":"venue"
},
  "geometry": {"coordinates":[138.486160278,-34.8449630737],"type":"Point"}
}