{
  "type": "Feature",
  "properties": {
    "addr:full":"Office 1 37 Agnes St Morningside QLD 4170",
    "addr:housenumber":"37",
    "addr:postcode":"4170",
    "addr:street":"Agnes St",
    "iso:country":"AU",
    "sg:address":"Office 1 37 Agnes St",
    "sg:city":"Morningside",
    "sg:classifiers":[
        {
            "category":"Building & Trades",
            "subcategory":"Construction",
            "type":"Services"
        }
    ],
    "sg:phone":"+61 7 3395 5000",
    "sg:postcode":"4170",
    "sg:province":"QLD",
    "sg:tags":[
        "contractor"
    ],
    "wof:name":"Dodmark Pty Ltd",
    "wof:placetype":"venue"
},
  "geometry": {"coordinates":[153.07188415499999,-27.4668064117],"type":"Point"}
}