{
  "type": "Feature",
  "properties": {
    "addr:full":"Unit 3 2045 Moggill Rd Kenmore QLD 4069",
    "addr:postcode":"2045;4069",
    "addr:street":"Moggill Rd",
    "iso:country":"AU",
    "sg:address":"Unit 3 2045 Moggill Rd",
    "sg:city":"Kenmore",
    "sg:classifiers":[
        {
            "category":"Professional",
            "subcategory":"Accounting & Tax Preparation",
            "type":"Services"
        }
    ],
    "sg:phone":"+61 7 3878 3377",
    "sg:postcode":"4069",
    "sg:province":"QLD",
    "sg:tags":[
        "accountant",
        "auditor"
    ],
    "wof:name":"Bob Mardell & Co",
    "wof:placetype":"venue"
},
  "geometry": {"coordinates":[152.938842773,-27.5074577332],"type":"Point"}
}