{
  "type": "Feature",
  "properties": {
    "iso:country":"AU",
    "sg:address":"211 McKinnon Rd",
    "sg:city":"McKinnon",
    "sg:classifiers":[
        {
            "category":"Banks & Credit Unions",
            "subcategory":"Investment Brokerage",
            "type":"Services"
        }
    ],
    "sg:phone":"+61 1300 555 199",
    "sg:postcode":"3204",
    "sg:province":"VIC",
    "sg:tags":[
        "finance",
        "broker"
    ],
    "wof:name":"Mortgage Masters Pty Ltd",
    "wof:placetype":"venue"
},
  "geometry": {"coordinates":[145.04039,-37.911163],"type":"Point"}
}