{
  "type": "Feature",
  "properties": {
    "iso:country":"AU",
    "sg:address":"Brothers Leagues Club, Hervey Range Rd",
    "sg:city":"Kirwan",
    "sg:classifiers":[
        {
            "category":"Recreation",
            "subcategory":"Amusement Park",
            "type":"Entertainment"
        }
    ],
    "sg:phone":"+61 7 4773 3404",
    "sg:postcode":"4817",
    "sg:province":"QLD",
    "wof:name":"Bingo City",
    "wof:placetype":"venue"
},
  "geometry": {"coordinates":[146.72744800000001,-19.317715],"type":"Point"}
}