{
  "type": "Feature",
  "properties": {
    "iso:country":"AU",
    "sg:address":"118 Whitehorse Rd",
    "sg:city":"Box Hill",
    "sg:classifiers":[
        {
            "category":"Autos & Motor Vehicles",
            "subcategory":"Automobile Sales",
            "type":"Retail Goods"
        }
    ],
    "sg:phone":"+61 3 9890 0291",
    "sg:postcode":"3128",
    "sg:province":"VIC",
    "sg:tags":[
        "car",
        "new"
    ],
    "wof:name":"Daihatsu Ward Motors",
    "wof:placetype":"venue"
},
  "geometry": {"coordinates":[145.12637329099999,-37.8185501099],"type":"Point"}
}