{
  "type": "Feature",
  "properties": {
    "addr:full":"131 Sandy Bay Rd Sandy Bay TAS 7005",
    "addr:housenumber":"131",
    "addr:postcode":"7005",
    "addr:street":"Sandy Bay Rd",
    "iso:country":"AU",
    "sg:address":"131 Sandy Bay Rd",
    "sg:city":"Sandy Bay",
    "sg:classifiers":[
        {
            "category":"Recreation",
            "subcategory":"Boat Charter",
            "type":"Entertainment"
        }
    ],
    "sg:phone":"+61 418 121 317",
    "sg:postcode":"7005",
    "sg:province":"TAS",
    "wof:name":"Precision Charters",
    "wof:placetype":"venue"
},
  "geometry": {"coordinates":[147.325515747,-42.8931274414],"type":"Point"}
}