{
  "type": "Feature",
  "properties": {
    "addr:full":"11 Bannons La Yarrambat VIC 3091",
    "addr:housenumber":"11",
    "addr:postcode":"3091",
    "addr:street":"Bannons La",
    "iso:country":"AU",
    "sg:address":"11 Bannons La",
    "sg:city":"Yarrambat",
    "sg:classifiers":[
        {
            "category":"Education",
            "subcategory":"Music School",
            "type":"Public Place"
        }
    ],
    "sg:phone":"+61 3 9436 1359",
    "sg:postcode":"3091",
    "sg:province":"VIC",
    "sg:tags":[
        "teacher"
    ],
    "wof:name":"Goodger R.D.",
    "wof:placetype":"venue"
},
  "geometry": {"coordinates":[145.136627197,-37.6257667542],"type":"Point"}
}