{
  "type": "Feature",
  "properties": {
    "iso:country":"AU",
    "sg:address":"147 Davey St",
    "sg:city":"Hobart",
    "sg:classifiers":[
        {
            "category":"Farming",
            "subcategory":"Vineyard",
            "type":"Manufacturing & Wholesale Goods"
        }
    ],
    "sg:phone":"+61 3 6223 3770",
    "sg:postcode":"7000",
    "sg:province":"TAS",
    "sg:tags":[
        "winery"
    ],
    "wof:name":"Wine Industry Tasmania",
    "wof:placetype":"venue"
},
  "geometry": {"coordinates":[147.32225036599999,-42.8900680542],"type":"Point"}
}