{
  "type": "Feature",
  "properties": {
    "iso:country":"AU",
    "sg:address":"PO Box 3",
    "sg:city":"Warragamba",
    "sg:classifiers":[
        {
            "category":"Professional",
            "subcategory":"Computer Services",
            "type":"Services"
        }
    ],
    "sg:phone":"+61 410 502 779",
    "sg:postcode":"2752",
    "sg:province":"NSW",
    "sg:tags":[
        "consultant",
        "system"
    ],
    "wof:name":"MCS Technology",
    "wof:placetype":"venue"
},
  "geometry": {"coordinates":[150.606292725,-33.890838623],"type":"Point"}
}