{
  "type": "Feature",
  "properties": {
    "addr:full":"20 Phillip Rd Avonsleigh VIC 3782",
    "addr:housenumber":"20",
    "addr:postcode":"3782",
    "addr:street":"Phillip Rd",
    "iso:country":"AU",
    "sg:address":"20 Phillip Rd",
    "sg:city":"Avonsleigh",
    "sg:classifiers":[
        {
            "category":"Wholesale",
            "subcategory":"Plants",
            "type":"Manufacturing & Wholesale Goods"
        }
    ],
    "sg:phone":"+61 419 006 533",
    "sg:postcode":"3782",
    "sg:province":"VIC",
    "sg:tags":[
        "florist"
    ],
    "wof:name":"Avonsleigh Lane Folage and Flowers",
    "wof:placetype":"venue"
},
  "geometry": {"coordinates":[145.47297699999999,-37.921227],"type":"Point"}
}