{
  "type": "Feature",
  "properties": {
    "iso:country":"AU",
    "sg:address":"808a Glenferrie Rd",
    "sg:city":"Hawthorn",
    "sg:classifiers":[
        {
            "category":"Education",
            "subcategory":"Special Training",
            "type":"Public Place"
        }
    ],
    "sg:phone":"+61 3 9818 2139",
    "sg:postcode":"3122",
    "sg:province":"VIC",
    "sg:tags":[
        "development"
    ],
    "wof:name":"Extend Australia Pty Ltd",
    "wof:placetype":"venue"
},
  "geometry": {"coordinates":[145.03643798799999,-37.8176612854],"type":"Point"}
}