{
  "type": "Feature",
  "properties": {
    "addr:full":"6 Sheldon Pl Bellevue Hill NSW 2023",
    "addr:housenumber":"6",
    "addr:postcode":"2023",
    "addr:street":"Sheldon Pl Bellevue",
    "iso:country":"AU",
    "sg:address":"6 Sheldon Pl",
    "sg:city":"Bellevue Hill",
    "sg:classifiers":[
        {
            "category":"Health Services",
            "subcategory":"Doctor",
            "type":"Services"
        }
    ],
    "sg:phone":"+61 2 9327 6555",
    "sg:postcode":"2023",
    "sg:province":"NSW",
    "sg:tags":[
        "medical",
        "practitioner"
    ],
    "wof:name":"Pantle G C Dr",
    "wof:placetype":"venue"
},
  "geometry": {"coordinates":[151.24977111800001,-33.875743866],"type":"Point"}
}