{
  "type": "Feature",
  "properties": {
    "iso:country":"AU",
    "sg:address":"84 Douglas",
    "sg:city":"Nowra",
    "sg:classifiers":[
        {
            "category":"Education",
            "subcategory":"Kindergarten",
            "type":"Public Place"
        }
    ],
    "sg:phone":"+61 2 4423 1131",
    "sg:postcode":"2541",
    "sg:province":"NSW",
    "sg:tags":[
        "pre-schools"
    ],
    "wof:name":"Douglas Street Preschool",
    "wof:placetype":"venue"
},
  "geometry": {"coordinates":[150.59999084500001,-34.8804206848],"type":"Point"}
}