{
  "type": "Feature",
  "properties": {
    "iso:country":"AU",
    "sg:address":"PO Box 875",
    "sg:city":"Mt Eliza",
    "sg:classifiers":[
        {
            "category":"Government",
            "subcategory":"Customs House",
            "type":"Public Place"
        }
    ],
    "sg:phone":"+61 3 9787 9723",
    "sg:postcode":"3930",
    "sg:province":"VIC",
    "sg:tags":[
        "title",
        "management",
        "stratum"
    ],
    "wof:name":"Focus Plus Management Group",
    "wof:placetype":"venue"
},
  "geometry": {"coordinates":[145.09501648,-38.1936798096],"type":"Point"}
}