{
  "type": "Feature",
  "properties": {
    "addr:full":"337 Balo St Moree NSW 2400",
    "addr:housenumber":"337",
    "addr:postcode":"2400",
    "addr:street":"Balo St",
    "iso:country":"AU",
    "sg:address":"337 Balo St",
    "sg:city":"Moree",
    "sg:classifiers":[
        {
            "category":"Organizations",
            "subcategory":"Non-profit Organization",
            "type":"Services"
        }
    ],
    "sg:phone":"+61 2 6752 6855",
    "sg:postcode":"2400",
    "sg:province":"NSW",
    "sg:tags":[
        "support",
        "disability",
        "organisation"
    ],
    "wof:name":"Moree Lifestyle Support Service",
    "wof:placetype":"venue"
},
  "geometry": {"coordinates":[149.841506958,-29.4755344391],"type":"Point"}
}