{
  "type": "Feature",
  "properties": {
    "addr:full":"ShpT20/ Ashley St Braybrook VIC 3019",
    "addr:postcode":"3019",
    "addr:street":"Ashley St",
    "iso:country":"AU",
    "sg:address":"ShpT20/ Ashley St",
    "sg:city":"Braybrook",
    "sg:classifiers":[
        {
            "category":"Personal",
            "subcategory":"Beauty Salon",
            "type":"Services"
        }
    ],
    "sg:phone":"+61 3 9687 7722",
    "sg:postcode":"3019",
    "sg:province":"VIC",
    "wof:name":"Oscar Nails",
    "wof:placetype":"venue"
},
  "geometry": {"coordinates":[144.864379883,-37.7861099243],"type":"Point"}
}