{
  "type": "Feature",
  "properties": {
    "iso:country":"AU",
    "sg:address":"207 Imlay St",
    "sg:city":"Eden",
    "sg:classifiers":[
        {
            "category":"Fast Food",
            "type":"Food & Drink"
        }
    ],
    "sg:phone":"+61 2 6496 1493",
    "sg:postcode":"2551",
    "sg:province":"NSW",
    "sg:tags":[
        "away",
        "take"
    ],
    "wof:name":"Cuppaz Home Style Meals",
    "wof:placetype":"venue"
},
  "geometry": {"coordinates":[149.91146850600001,-37.0731048584],"type":"Point"}
}