{
  "type": "Feature",
  "properties": {
    "iso:country":"AU",
    "sg:address":"Shp 1/ 47 Crescent Ave",
    "sg:city":"Taree",
    "sg:classifiers":[
        {
            "category":"Shopping",
            "subcategory":"Antiques",
            "type":"Retail Goods"
        }
    ],
    "sg:phone":"+61 2 6551 2011",
    "sg:postcode":"2430",
    "sg:province":"NSW",
    "wof:name":"Taree Country Antiques Centre",
    "wof:placetype":"venue"
},
  "geometry": {"coordinates":[152.471573,-31.906738],"type":"Point"}
}