{
  "type": "Feature",
  "properties": {
    "iso:country":"AU",
    "sg:address":"Shop 5/ Pioneer Plz",
    "sg:city":"Portland",
    "sg:classifiers":[
        {
            "category":"Cafe",
            "type":"Food & Drink"
        }
    ],
    "sg:phone":"+61 3 5523 3802",
    "sg:postcode":"3305",
    "sg:province":"VIC",
    "wof:name":"Cafe On Percy",
    "wof:placetype":"venue"
},
  "geometry": {"coordinates":[141.61425781200001,-38.3552894592],"type":"Point"}
}