{
  "type": "Feature",
  "properties": {
    "addr:full":"2 Kallaroo St San Remo NSW 2262",
    "addr:housenumber":"2",
    "addr:postcode":"2262",
    "addr:street":"Kallaroo St",
    "iso:country":"AU",
    "sg:address":"2 Kallaroo St",
    "sg:city":"San Remo",
    "sg:classifiers":[
        {
            "category":"Building & Trades",
            "subcategory":"Construction",
            "type":"Services"
        }
    ],
    "sg:phone":"+61 404 601 405",
    "sg:postcode":"2262",
    "sg:province":"NSW",
    "sg:tags":[
        "concrete",
        "contractor"
    ],
    "wof:name":"Micheal Durner",
    "wof:placetype":"venue"
},
  "geometry": {"coordinates":[151.515579,-33.219601],"type":"Point"}
}