{
  "type": "Feature",
  "properties": {
    "addr:full":"Lot4/ Mcmaster Rd Cloncurry QLD 4824",
    "addr:postcode":"4824",
    "addr:street":"Mcmaster Rd",
    "iso:country":"AU",
    "sg:address":"Lot4/ Mcmaster Rd",
    "sg:city":"Cloncurry",
    "sg:classifiers":[
        {
            "category":"Professional",
            "subcategory":"Engineering",
            "type":"Services"
        }
    ],
    "sg:phone":"+61 7 4742 0591",
    "sg:postcode":"4824",
    "sg:province":"QLD",
    "sg:tags":[
        "engineer"
    ],
    "wof:name":"Nasco Welding Pty Ltd",
    "wof:placetype":"venue"
},
  "geometry": {"coordinates":[140.510941,-20.672977],"type":"Point"}
}