{
  "type": "Feature",
  "properties": {
    "addr:full":"38- 40 Vernon Ave Heidelberg Heights VIC 3081",
    "addr:housenumber":"40",
    "addr:postcode":"3081",
    "addr:street":"Vernon Ave",
    "iso:country":"AU",
    "sg:address":"38- 40 Vernon Ave",
    "sg:city":"Heidelberg Heights",
    "sg:classifiers":[
        {
            "category":"Shopping",
            "subcategory":"Stationery & Office Supplies",
            "type":"Retail Goods"
        }
    ],
    "sg:phone":"+61 3 9457 2641",
    "sg:postcode":"3081",
    "sg:province":"VIC",
    "sg:tags":[
        "equipment",
        "display",
        "exhibition"
    ],
    "wof:name":"Asset Design & Display Services Pty Ltd",
    "wof:placetype":"venue"
},
  "geometry": {"coordinates":[145.05332946799999,-37.7322654724],"type":"Point"}
}