{
  "type": "Feature",
  "properties": {
    "addr:full":"Shop 4/ 116 Reed Rd Trinity Park QLD 4879",
    "addr:housenumber":"shop 4 / 116",
    "addr:postcode":"4879",
    "addr:street":"Reed Rd",
    "iso:country":"AU",
    "sg:address":"Shop 4/ 116 Reed Rd",
    "sg:city":"Trinity Park",
    "sg:classifiers":[
        {
            "category":"Health Services",
            "subcategory":"Health Practitioner",
            "type":"Services"
        }
    ],
    "sg:phone":"+61 7 4057 5566",
    "sg:postcode":"4879",
    "sg:province":"QLD",
    "sg:tags":[
        "herbalist"
    ],
    "wof:name":"Oakley Carole",
    "wof:placetype":"venue"
},
  "geometry": {"coordinates":[145.701446533,-16.8049888611],"type":"Point"}
}