{
  "type": "Feature",
  "properties": {
    "addr:full":"Bulban Rd Werribee VIC 3030",
    "addr:postcode":"3030",
    "addr:street":"Bulban Rd",
    "iso:country":"AU",
    "sg:address":"Bulban Rd",
    "sg:city":"Werribee",
    "sg:classifiers":[
        {
            "category":"Building & Trades",
            "subcategory":"Construction",
            "type":"Services"
        }
    ],
    "sg:phone":"+61 417 382 742",
    "sg:postcode":"3030",
    "sg:province":"VIC",
    "sg:tags":[
        "fencing",
        "contractor"
    ],
    "wof:name":"John Zaina",
    "wof:placetype":"venue"
},
  "geometry": {"coordinates":[144.650848,-37.903111],"type":"Point"}
}