{
  "type": "Feature",
  "properties": {
    "addr:full":"54 Redfern St Wetherill Park NSW 2164",
    "addr:housenumber":"54",
    "addr:postcode":"2164",
    "addr:street":"Redfern St",
    "iso:country":"AU",
    "sg:address":"54 Redfern St",
    "sg:city":"Wetherill Park",
    "sg:classifiers":[
        {
            "category":"Home & Garden",
            "subcategory":"Hardware",
            "type":"Retail Goods"
        }
    ],
    "sg:phone":"+61 2 8706 2400",
    "sg:postcode":"2164",
    "sg:province":"NSW",
    "sg:tags":[
        "pipe",
        "fitting",
        "plastic"
    ],
    "wof:name":"PPI Corporation Pty Ltd",
    "wof:placetype":"venue"
},
  "geometry": {"coordinates":[150.913299561,-33.843875885],"type":"Point"}
}