{
  "type": "Feature",
  "properties": {
    "addr:full":"34 Separation St Fairfield VIC 3078",
    "addr:housenumber":"34",
    "addr:postcode":"3078",
    "addr:street":"Separation St",
    "iso:country":"AU",
    "sg:address":"34 Separation St",
    "sg:city":"Fairfield",
    "sg:classifiers":[
        {
            "category":"Education",
            "subcategory":"Kindergarten",
            "type":"Public Place"
        }
    ],
    "sg:phone":"+61 3 9489 0262",
    "sg:postcode":"3078",
    "sg:province":"VIC",
    "sg:tags":[
        "pre-schools"
    ],
    "wof:name":"Alfred Nuttall Memorial Kindergarten",
    "wof:placetype":"venue"
},
  "geometry": {"coordinates":[145.02220153799999,-37.7718353271],"type":"Point"}
}