{
  "type": "Feature",
  "properties": {
    "addr:full":"Un 7/ 8 Exeter Way Caloundra QLD 4551",
    "addr:postcode":"4551",
    "addr:street":"Exeter",
    "iso:country":"AU",
    "sg:address":"Un 7/ 8 Exeter Way",
    "sg:city":"Caloundra",
    "sg:classifiers":[
        {
            "category":"Retail",
            "subcategory":"Auto Repair",
            "type":"Services"
        }
    ],
    "sg:phone":"+61 7 5437 2758",
    "sg:postcode":"4551",
    "sg:province":"QLD",
    "sg:tags":[
        "electrical"
    ],
    "wof:name":"Caloundra Custom Auto Electrics",
    "wof:placetype":"venue"
},
  "geometry": {"coordinates":[153.11538696299999,-26.7955703735],"type":"Point"}
}