{
  "type": "Feature",
  "properties": {
    "addr:full":"26 Outram St West Perth WA 6005",
    "addr:housenumber":"26",
    "addr:postcode":"6005",
    "addr:street":"Outram St",
    "iso:country":"AU",
    "sg:address":"26 Outram St",
    "sg:city":"West Perth",
    "sg:classifiers":[
        {
            "category":"Cafe",
            "type":"Food & Drink"
        }
    ],
    "sg:phone":"+61 8 9321 8806",
    "sg:postcode":"6005",
    "sg:province":"WA",
    "wof:name":"Outram Cafe & Gourmet Deli",
    "wof:placetype":"venue"
},
  "geometry": {"coordinates":[115.83899688699999,-31.949754715],"type":"Point"}
}