{
  "type": "Feature",
  "properties": {
    "addr:full":"142 Canterbury St Casino NSW 2470",
    "addr:housenumber":"142",
    "addr:postcode":"2470",
    "addr:street":"Canterbury St",
    "iso:country":"AU",
    "sg:address":"142 Canterbury St",
    "sg:city":"Casino",
    "sg:classifiers":[
        {
            "category":"Personal",
            "subcategory":"Beauty Salon",
            "type":"Services"
        }
    ],
    "sg:phone":"+61 2 6662 3970",
    "sg:postcode":"2470",
    "sg:province":"NSW",
    "sg:tags":[
        "hairdresser"
    ],
    "wof:name":"Casino-Sharon's Hair & Beauty",
    "wof:placetype":"venue"
},
  "geometry": {"coordinates":[153.046951294,-28.8624725342],"type":"Point"}
}