{
  "type": "Feature",
  "properties": {
    "addr:full":"225 Brunswick St Fortitude Valley QLD 4006",
    "addr:housenumber":"225",
    "addr:postcode":"4006",
    "addr:street":"Brunswick St",
    "iso:country":"AU",
    "sg:address":"225 Brunswick St",
    "sg:city":"Fortitude Valley",
    "sg:classifiers":[
        {
            "category":"Personal",
            "subcategory":"Adult",
            "type":"Services"
        }
    ],
    "sg:phone":"+61 7 3257 0364",
    "sg:postcode":"4006",
    "sg:province":"QLD",
    "sg:tags":[
        "product"
    ],
    "wof:name":"Peep Show",
    "wof:placetype":"venue"
},
  "geometry": {"coordinates":[153.032546997,-27.4566898346],"type":"Point"}
}