{
  "type": "Feature",
  "properties": {
    "addr:full":"Ocean St Victor Harbor SA 5211",
    "addr:postcode":"5211",
    "addr:street":"Ocean St",
    "iso:country":"AU",
    "sg:address":"Ocean St",
    "sg:city":"Victor Harbor",
    "sg:classifiers":[
        {
            "category":"Cinema",
            "subcategory":"Movie Theater",
            "type":"Entertainment"
        }
    ],
    "sg:phone":"+61 8 8552 1325",
    "sg:postcode":"5211",
    "sg:province":"SA",
    "wof:name":"Victa Cinema",
    "wof:placetype":"venue"
},
  "geometry": {"coordinates":[138.622955322,-35.5529022217],"type":"Point"}
}