{
  "type": "Feature",
  "properties": {
    "iso:country":"AU",
    "sg:address":"29 Colebard St E",
    "sg:city":"Acacia Ridge",
    "sg:classifiers":[
        {
            "category":"Professional",
            "subcategory":"Detective & Security Services",
            "type":"Services"
        }
    ],
    "sg:phone":"+61 7 3275 1566",
    "sg:postcode":"4110",
    "sg:province":"QLD",
    "sg:tags":[
        "consultant",
        "laser"
    ],
    "wof:name":"Rocklea Pressed Metals",
    "wof:placetype":"venue"
},
  "geometry": {"coordinates":[153.00531005900001,-27.5810031891],"type":"Point"}
}