{
  "type": "Feature",
  "properties": {
    "addr:full":"57 Wrights Pl Mt Cotton QLD 4165",
    "addr:housenumber":"57",
    "addr:postcode":"4165",
    "addr:street":"Wrights Pl Mt Cotton",
    "iso:country":"AU",
    "sg:address":"57 Wrights Pl",
    "sg:city":"Mt Cotton",
    "sg:classifiers":[
        {
            "category":"Education",
            "subcategory":"Special Training",
            "type":"Public Place"
        }
    ],
    "sg:phone":"+61 7 3206 6517",
    "sg:postcode":"4165",
    "sg:province":"QLD",
    "sg:tags":[
        "tuition-educational"
    ],
    "wof:name":"Primetime Education",
    "wof:placetype":"venue"
},
  "geometry": {"coordinates":[153.23794555699999,-27.6235961914],"type":"Point"}
}