{
  "type": "Feature",
  "properties": {
    "addr:full":"164 Old Prospect Rd South Wentworthville NSW 2145",
    "addr:housenumber":"164",
    "addr:postcode":"2145",
    "addr:street":"Old Prospect Rd",
    "iso:country":"AU",
    "sg:address":"164 Old Prospect Rd",
    "sg:city":"South Wentworthville",
    "sg:classifiers":[
        {
            "category":"Personal",
            "subcategory":"Beauty Salon",
            "type":"Services"
        }
    ],
    "sg:phone":"+61 410 313 195",
    "sg:postcode":"2145",
    "sg:province":"NSW",
    "sg:tags":[
        "supply",
        "artist",
        "make-up"
    ],
    "wof:name":"Make-Up By Angela",
    "wof:placetype":"venue"
},
  "geometry": {"coordinates":[150.95603942899999,-33.8182792664],"type":"Point"}
}