{
  "type": "Feature",
  "properties": {
    "addr:full":"PO Box 540 Riverstone NSW 2765",
    "addr:postcode":"2765",
    "iso:country":"AU",
    "sg:address":"PO Box 540",
    "sg:city":"Riverstone",
    "sg:classifiers":[
        {
            "category":"Building & Trades",
            "subcategory":"Construction",
            "type":"Services"
        }
    ],
    "sg:phone":"+61 2 9838 1536",
    "sg:postcode":"2765",
    "sg:province":"NSW",
    "sg:tags":[
        "earth",
        "excavating",
        "moving",
        "contractor"
    ],
    "wof:name":"Huntington Earthmoving Co",
    "wof:placetype":"venue"
},
  "geometry": {"coordinates":[150.86323547399999,-33.6785087585],"type":"Point"}
}