{
  "type": "Feature",
  "properties": {
    "addr:full":"34 Victoria St Biggenden QLD 4621",
    "addr:housenumber":"34",
    "addr:postcode":"4621",
    "addr:street":"Victoria St",
    "iso:country":"AU",
    "sg:address":"34 Victoria St",
    "sg:city":"Biggenden",
    "sg:classifiers":[
        {
            "category":"Commercial Area",
            "type":"Public Place"
        }
    ],
    "sg:phone":"+61 7 4127 1266",
    "sg:postcode":"4621",
    "sg:province":"QLD",
    "sg:tags":[
        "heavy",
        "carrier"
    ],
    "wof:name":"Dowling H & Sons",
    "wof:placetype":"venue"
},
  "geometry": {"coordinates":[152.04690600000001,-25.510515],"type":"Point"}
}