{
  "type": "Feature",
  "properties": {
    "addr:full":"PO Box 581 Wentworthville NSW 2145",
    "addr:postcode":"2145",
    "iso:country":"AU",
    "sg:address":"PO Box 581",
    "sg:city":"Wentworthville",
    "sg:classifiers":[
        {
            "category":"Utilities",
            "subcategory":"Electric",
            "type":"Services"
        }
    ],
    "sg:phone":"+61 410 511 915",
    "sg:postcode":"2145",
    "sg:province":"NSW",
    "sg:tags":[
        "electrical",
        "contractor"
    ],
    "wof:name":"Short's Circuits Electrical Services Aust Pty Ltd",
    "wof:placetype":"venue"
},
  "geometry": {"coordinates":[150.97215270999999,-33.8030815125],"type":"Point"}
}