{
  "type": "Feature",
  "properties": {
    "iso:country":"AU",
    "sg:address":"535 Kingsway Rd",
    "sg:city":"Miranda",
    "sg:classifiers":[
        {
            "category":"Health Services",
            "subcategory":"Chiropractor",
            "type":"Services"
        }
    ],
    "sg:phone":"+61 2 9526 1555",
    "sg:postcode":"2228",
    "sg:province":"NSW",
    "wof:name":"Southern Chiropractic Clinic",
    "wof:placetype":"venue"
},
  "geometry": {"coordinates":[151.103805542,-34.0341186523],"type":"Point"}
}