{
  "type": "Feature",
  "properties": {
    "addr:full":"Cnr Redland Bay & Neuman Rds Capalaba QLD 4157",
    "addr:postcode":"4157",
    "addr:street":"Cnr",
    "iso:country":"AU",
    "sg:address":"Cnr Redland Bay & Neuman Rds",
    "sg:city":"Capalaba",
    "sg:classifiers":[
        {
            "category":"Retail",
            "subcategory":"Auto Repair",
            "type":"Services"
        }
    ],
    "sg:phone":"+61 7 3823 4966",
    "sg:postcode":"4157",
    "sg:province":"QLD",
    "sg:tags":[
        "repairer",
        "motor",
        "engineer"
    ],
    "wof:name":"Hammond 4WD Centre Tyres & More Pty Ltd",
    "wof:placetype":"venue"
},
  "geometry": {"coordinates":[153.2109375,-27.5379753113],"type":"Point"}
}