{
  "type": "Feature",
  "properties": {
    "addr:full":"Shop 11 Mayfair Shopping Plaza Russell Crs Sandy Bay TAS 7005",
    "addr:housenumber":"shop 11",
    "addr:postcode":"7005",
    "addr:street":"Mayfair;Russell Crs",
    "iso:country":"AU",
    "sg:address":"Shop 11 Mayfair Shopping Plaza Russell Crs",
    "sg:city":"Sandy Bay",
    "sg:classifiers":[
        {
            "category":"Personal",
            "type":"Services"
        }
    ],
    "sg:phone":"+61 3 6223 5129",
    "sg:postcode":"7005",
    "sg:province":"TAS",
    "sg:tags":[
        "gift"
    ],
    "wof:name":"Fiori Exclusive Florist",
    "wof:placetype":"venue"
},
  "geometry": {"coordinates":[147.33280944800001,-42.9012489319],"type":"Point"}
}