{
  "type": "Feature",
  "properties": {
    "addr:full":"11 Donovan St Augusta WA 6290",
    "addr:housenumber":"11",
    "addr:postcode":"6290",
    "addr:street":"Donovan St",
    "iso:country":"AU",
    "sg:address":"11 Donovan St",
    "sg:city":"Augusta",
    "sg:classifiers":[
        {
            "category":"Health Services",
            "subcategory":"Doctor",
            "type":"Services"
        }
    ],
    "sg:phone":"+61 8 9758 1550",
    "sg:postcode":"6290",
    "sg:province":"WA",
    "sg:tags":[
        "medical",
        "practitioner"
    ],
    "wof:name":"Augusta Medical Centre",
    "wof:placetype":"venue"
},
  "geometry": {"coordinates":[115.157279968,-34.306552887],"type":"Point"}
}