{
  "type": "Feature",
  "properties": {
    "addr:full":"Suite 207, Level 2, 83 Longueville Rd Lane Cove NSW 2066",
    "addr:housenumber":"83",
    "addr:postcode":"2066",
    "addr:street":"207;Longueville Rd",
    "iso:country":"AU",
    "sg:address":"Suite 207, Level 2, 83 Longueville Rd",
    "sg:city":"Lane Cove",
    "sg:classifiers":[
        {
            "category":"Health Services",
            "subcategory":"Health Practitioner",
            "type":"Services"
        }
    ],
    "sg:phone":"+61 2 9427 9299",
    "sg:postcode":"2066",
    "sg:province":"NSW",
    "sg:tags":[
        "osteopath"
    ],
    "wof:name":"Amanda Hannaford Osteo Plus Lane Cove Pty Ltd",
    "wof:placetype":"venue"
},
  "geometry": {"coordinates":[151.170089722,-33.8140449524],"type":"Point"}
}