{
  "type": "Feature",
  "properties": {
    "iso:country":"AU",
    "sg:address":"106 Jetty Rd",
    "sg:city":"Glenelg",
    "sg:classifiers":[
        {
            "category":"Health Services",
            "subcategory":"Dentist",
            "type":"Services"
        }
    ],
    "sg:phone":"+61 8 8295 2607",
    "sg:postcode":"5045",
    "sg:province":"SA",
    "wof:name":"Moore Anthony T Dr",
    "wof:placetype":"venue"
},
  "geometry": {"coordinates":[138.516022,-34.98037],"type":"Point"}
}