{
  "type": "Feature",
  "properties": {
    "iso:country":"AU",
    "sg:address":"235 Sun Valley Rd",
    "sg:city":"Gladstone",
    "sg:classifiers":[
        {
            "category":"Manufacturing",
            "subcategory":"Tools & Machinery",
            "type":"Manufacturing & Wholesale Goods"
        }
    ],
    "sg:phone":"+61 412 553 542",
    "sg:postcode":"4680",
    "sg:province":"QLD",
    "sg:tags":[
        "earth",
        "excavating",
        "moving",
        "equipment"
    ],
    "wof:name":"Waterson Diesel",
    "wof:placetype":"venue"
},
  "geometry": {"coordinates":[151.24534606899999,-23.8747348785],"type":"Point"}
}