{
  "type": "Feature",
  "properties": {
    "addr:full":"Cnr Farm & Chappell Sts North Rockhampton QLD 4701",
    "addr:postcode":"4701",
    "addr:street":"North",
    "iso:country":"AU",
    "sg:address":"Cnr Farm & Chappell Sts",
    "sg:city":"North Rockhampton",
    "sg:classifiers":[
        {
            "category":"Retail",
            "subcategory":"Auto Repair",
            "type":"Services"
        }
    ],
    "sg:phone":"+61 7 4926 6644",
    "sg:postcode":"4701",
    "sg:province":"QLD",
    "sg:tags":[
        "wheel",
        "balancing",
        "alignment"
    ],
    "wof:name":"Meng Tyre Sales",
    "wof:placetype":"venue"
},
  "geometry": {"coordinates":[150.508911133,-23.3380355835],"type":"Point"}
}