{
  "type": "Feature",
  "properties": {
    "iso:country":"AU",
    "sg:address":"16 Harris Rd",
    "sg:city":"Dural",
    "sg:classifiers":[
        {
            "category":"Building & Trades",
            "subcategory":"Construction",
            "type":"Services"
        }
    ],
    "sg:phone":"+61 2 9651 7075",
    "sg:postcode":"2158",
    "sg:province":"NSW",
    "sg:tags":[
        "earth",
        "excavating",
        "moving",
        "contractor"
    ],
    "wof:name":"Hardrock Excavations Pty Ltd",
    "wof:placetype":"venue"
},
  "geometry": {"coordinates":[151.035064697,-33.700668335],"type":"Point"}
}