{
  "type": "Feature",
  "properties": {
    "addr:full":"Cnr Gnangara & Willmott Drv Waikiki WA 6169",
    "addr:postcode":"6169",
    "addr:street":"Cnr Gnangara & Willmott Drv",
    "iso:country":"AU",
    "sg:address":"Cnr Gnangara & Willmott Drv",
    "sg:city":"Waikiki",
    "sg:classifiers":[
        {
            "category":"Health Services",
            "subcategory":"Doctor",
            "type":"Services"
        }
    ],
    "sg:phone":"+61 8 9550 0222",
    "sg:postcode":"6169",
    "sg:province":"WA",
    "sg:tags":[
        "medical",
        "practitioner"
    ],
    "wof:name":"Coastal Private Hospital",
    "wof:placetype":"venue"
},
  "geometry": {"coordinates":[115.75295300000001,-32.315533],"type":"Point"}
}