{
  "type": "Feature",
  "properties": {
    "iso:country":"AU",
    "sg:address":"80 Parkstone Ave",
    "sg:city":"Pascoe Vale South",
    "sg:classifiers":[
        {
            "category":"Home & Garden",
            "subcategory":"Carpets & Floor Coverings",
            "type":"Retail Goods"
        }
    ],
    "sg:phone":"+61 417 776 686",
    "sg:postcode":"3044",
    "sg:province":"VIC",
    "sg:tags":[
        "tile",
        "wall",
        "layer"
    ],
    "wof:name":"Parkstone Tiling",
    "wof:placetype":"venue"
},
  "geometry": {"coordinates":[144.929122925,-37.7462997437],"type":"Point"}
}