{
  "type": "Feature",
  "properties": {
    "addr:full":"129 Powell St Roma QLD 4455",
    "addr:housenumber":"129",
    "addr:postcode":"4455",
    "addr:street":"Powell St",
    "iso:country":"AU",
    "sg:address":"129 Powell St",
    "sg:city":"Roma",
    "sg:classifiers":[
        {
            "category":"Travel",
            "subcategory":"Hostel",
            "type":"Entertainment"
        }
    ],
    "sg:phone":"+61 7 4622 4116",
    "sg:postcode":"4455",
    "sg:province":"QLD",
    "sg:tags":[
        "home"
    ],
    "wof:name":"Roma Rural Student Hostel",
    "wof:placetype":"venue"
},
  "geometry": {"coordinates":[148.78074645999999,-26.5620155334],"type":"Point"}
}