{
  "type": "Feature",
  "properties": {
    "addr:full":"Level 9/ 440 Collins St Melbourne VIC 3000",
    "addr:housenumber":"/ 440",
    "addr:postcode":"3000",
    "addr:street":"Collins St",
    "iso:country":"AU",
    "sg:address":"Level 9/ 440 Collins St",
    "sg:city":"Melbourne",
    "sg:classifiers":[
        {
            "category":"Communications",
            "subcategory":"News Services",
            "type":"Services"
        }
    ],
    "sg:phone":"+61 3 9607 1313",
    "sg:postcode":"3000",
    "sg:province":"VIC",
    "sg:tags":[
        "information",
        "tourist",
        "attractions"
    ],
    "wof:name":"Oz Discovery",
    "wof:placetype":"venue"
},
  "geometry": {"coordinates":[144.95979309099999,-37.8173065186],"type":"Point"}
}