{
  "type": "Feature",
  "properties": {
    "addr:full":"11 Wirraway Drv Mildura VIC 3500",
    "addr:housenumber":"11",
    "addr:postcode":"3500",
    "addr:street":"Wirraway Drv",
    "iso:country":"AU",
    "sg:address":"11 Wirraway Drv",
    "sg:city":"Mildura",
    "sg:classifiers":[
        {
            "category":"Personal",
            "subcategory":"Nail Salon",
            "type":"Services"
        }
    ],
    "sg:phone":"+61 3 5021 2785",
    "sg:postcode":"3500",
    "sg:province":"VIC",
    "sg:tags":[
        "artificial"
    ],
    "wof:name":"Schabooh Nails And Beauty",
    "wof:placetype":"venue"
},
  "geometry": {"coordinates":[142.18202209500001,-34.1961898804],"type":"Point"}
}