{
  "type": "Feature",
  "properties": {
    "addr:full":"PO Box 587 Southport Business Centre QLD 4215",
    "addr:postcode":"4215",
    "iso:country":"AU",
    "sg:address":"PO Box 587",
    "sg:city":"Southport Business Centre",
    "sg:classifiers":[
        {
            "category":"Arena",
            "subcategory":"Indoor Arena",
            "type":"Entertainment"
        }
    ],
    "sg:phone":"+61 417 607 790",
    "sg:postcode":"4215",
    "sg:province":"QLD",
    "sg:tags":[
        "club",
        "angling"
    ],
    "wof:name":"Southport Amateur Fishing Club Inc",
    "wof:placetype":"venue"
},
  "geometry": {"coordinates":[153.39855957,-27.9664897919],"type":"Point"}
}