{
  "type": "Feature",
  "properties": {
    "addr:full":"42 Alfred St Templestowe Lower VIC 3107",
    "addr:housenumber":"42",
    "addr:postcode":"3107",
    "addr:street":"Alfred St",
    "iso:country":"AU",
    "sg:address":"42 Alfred St",
    "sg:city":"Templestowe Lower",
    "sg:classifiers":[
        {
            "category":"Building & Trades",
            "subcategory":"Construction",
            "type":"Services"
        }
    ],
    "sg:phone":"+61 3 9850 3447",
    "sg:postcode":"3107",
    "sg:province":"VIC",
    "sg:tags":[
        "contractor"
    ],
    "wof:name":"Scottbuilt Nominees Pty Ltd",
    "wof:placetype":"venue"
},
  "geometry": {"coordinates":[145.10520935100001,-37.7639389038],"type":"Point"}
}