{
  "type": "Feature",
  "properties": {
    "addr:full":"383 St Pauls Tce Fortitude Valley QLD 4006",
    "addr:housenumber":"383",
    "addr:postcode":"4006",
    "addr:street":"St Pauls Tce",
    "iso:country":"AU",
    "sg:address":"383 St",
    "sg:city":"Pauls Tce Fortitude Valley",
    "sg:classifiers":[
        {
            "category":"Personal",
            "subcategory":"Tattoo Parlor",
            "type":"Services"
        }
    ],
    "sg:phone":"+61 7 3252 8881",
    "sg:postcode":"4006",
    "sg:province":"QLD",
    "sg:tags":[
        "tattooing"
    ],
    "wof:name":"High Energy Tattooing & Body Piercing",
    "wof:placetype":"venue"
},
  "geometry": {"coordinates":[153.03253173799999,-27.4552574158],"type":"Point"}
}