{
  "type": "Feature",
  "properties": {
    "iso:country":"AU",
    "sg:address":"U3/ 94 Delta St",
    "sg:city":"Geebung",
    "sg:classifiers":[
        {
            "category":"Education",
            "subcategory":"Special Training",
            "type":"Public Place"
        }
    ],
    "sg:phone":"+61 1800 143 113",
    "sg:postcode":"4034",
    "sg:province":"QLD",
    "sg:tags":[
        "development"
    ],
    "wof:name":"Vertical Horizonz Australia",
    "wof:placetype":"venue"
},
  "geometry": {"coordinates":[153.051987,-27.366133],"type":"Point"}
}