{
  "type": "Feature",
  "properties": {
    "addr:full":"18 Freemans St Lalor Park NSW 2147",
    "addr:housenumber":"18",
    "addr:postcode":"2147",
    "addr:street":"Freemans St",
    "iso:country":"AU",
    "sg:address":"18 Freemans St",
    "sg:city":"Lalor Park",
    "sg:classifiers":[
        {
            "category":"Fast Food",
            "type":"Food & Drink"
        }
    ],
    "sg:phone":"+61 2 9674 6630",
    "sg:postcode":"2147",
    "sg:province":"NSW",
    "sg:tags":[
        "away",
        "take"
    ],
    "wof:name":"Achilleon Take-Away No 2",
    "wof:placetype":"venue"
},
  "geometry": {"coordinates":[150.93072509800001,-33.76146698],"type":"Point"}
}