{
  "type": "Feature",
  "properties": {
    "iso:country":"AU",
    "sg:address":"Cnr Steel & Cato St",
    "sg:city":"Winnellie",
    "sg:classifiers":[
        {
            "category":"Food & Beverages",
            "subcategory":"Specialty",
            "type":"Retail Goods"
        }
    ],
    "sg:phone":"+61 8 8984 4402",
    "sg:postcode":"0820",
    "sg:province":"NT",
    "sg:tags":[
        "ice",
        "supply"
    ],
    "wof:name":"Darwin Ice Sales Pty Ltd",
    "wof:placetype":"venue"
},
  "geometry": {"coordinates":[130.86325073200001,-12.4290103912],"type":"Point"}
}