{
  "type": "Feature",
  "properties": {
    "iso:country":"AU",
    "sg:address":"\"Appleton\" College Rd",
    "sg:city":"Bathurst",
    "sg:classifiers":[
        {
            "category":"Manufacturing",
            "subcategory":"Wood Products",
            "type":"Manufacturing & Wholesale Goods"
        }
    ],
    "sg:phone":"+61 2 6331 8912",
    "sg:postcode":"2795",
    "sg:province":"NSW",
    "sg:tags":[
        "pallet",
        "platform"
    ],
    "wof:name":"Loscam Pallet Hire",
    "wof:placetype":"venue"
},
  "geometry": {"coordinates":[149.568359375,-33.444896698],"type":"Point"}
}