{
  "type": "Feature",
  "properties": {
    "iso:country":"AU",
    "sg:address":"855 South Rd",
    "sg:city":"Clarence Gardens",
    "sg:classifiers":[
        {
            "category":"Home & Garden",
            "subcategory":"Hardware",
            "type":"Retail Goods"
        }
    ],
    "sg:phone":"+61 8 8297 0622",
    "sg:postcode":"5039",
    "sg:province":"SA",
    "sg:tags":[
        "generating",
        "set",
        "generator"
    ],
    "wof:name":"Yamaha World",
    "wof:placetype":"venue"
},
  "geometry": {"coordinates":[138.57351684599999,-34.9717597961],"type":"Point"}
}