{
  "type": "Feature",
  "properties": {
    "addr:full":"103 Boundary St Townsville QLD 4810",
    "addr:housenumber":"103",
    "addr:postcode":"4810",
    "addr:street":"Boundary St",
    "iso:country":"AU",
    "sg:address":"103 Boundary St",
    "sg:city":"Townsville",
    "sg:classifiers":[
        {
            "category":"Banks & Credit Unions",
            "subcategory":"Financial Services",
            "type":"Services"
        }
    ],
    "sg:phone":"+61 7 4772 2200",
    "sg:postcode":"4810",
    "sg:province":"QLD",
    "sg:tags":[
        "advisory",
        "planning",
        "retirement"
    ],
    "wof:name":"Financially Yours",
    "wof:placetype":"venue"
},
  "geometry": {"coordinates":[146.815247,-19.271015],"type":"Point"}
}