{
  "type": "Feature",
  "properties": {
    "addr:full":"389 Hume Hwy Bankstown NSW 2200",
    "addr:housenumber":"389",
    "addr:postcode":"2200",
    "addr:street":"Hume Hwy",
    "iso:country":"AU",
    "sg:address":"389 Hume Hwy",
    "sg:city":"Bankstown",
    "sg:classifiers":[
        {
            "category":"Professional",
            "subcategory":"Art Services",
            "type":"Services"
        }
    ],
    "sg:phone":"+61 2 9790 3661",
    "sg:postcode":"2200",
    "sg:province":"NSW",
    "sg:tags":[
        "picture",
        "frame",
        "framing"
    ],
    "wof:name":"Pottery Cottage",
    "wof:placetype":"venue"
},
  "geometry": {"coordinates":[151.031387,-33.907848],"type":"Point"}
}