{
  "type": "Feature",
  "properties": {
    "iso:country":"AU",
    "sg:address":"19/ 37 Warman Rd",
    "sg:city":"Neerabup",
    "sg:classifiers":[
        {
            "category":"Shopping",
            "subcategory":"Bicycles & Sporting Goods",
            "type":"Retail Goods"
        }
    ],
    "sg:phone":"+61 8 9343 7665",
    "sg:postcode":"6031",
    "sg:province":"WA",
    "sg:tags":[
        "chemical",
        "equipment",
        "pool",
        "swimming"
    ],
    "wof:name":"ABW Pool Renovations",
    "wof:placetype":"venue"
},
  "geometry": {"coordinates":[115.785461426,-31.6853656769],"type":"Point"}
}