{
  "type": "Feature",
  "properties": {
    "iso:country":"AU",
    "sg:address":"Suite 102/ 83 Mount St",
    "sg:city":"North Sydney",
    "sg:classifiers":[
        {
            "category":"Professional",
            "subcategory":"Computer Services",
            "type":"Services"
        }
    ],
    "sg:phone":"+61 2 9900 9100",
    "sg:postcode":"2060",
    "sg:province":"NSW",
    "sg:tags":[
        "package",
        "software"
    ],
    "wof:name":"Computer Telephone Integration Pty Ltd",
    "wof:placetype":"venue"
},
  "geometry": {"coordinates":[151.20791625999999,-33.8390922546],"type":"Point"}
}