{
  "type": "Feature",
  "properties": {
    "addr:full":"124 Wallace Ave Strathfield NSW 2135",
    "addr:housenumber":"124",
    "addr:postcode":"2135",
    "addr:street":"Wallace Ave",
    "iso:country":"AU",
    "sg:address":"124 Wallace Ave",
    "sg:city":"Strathfield",
    "sg:classifiers":[
        {
            "category":"Professional",
            "subcategory":"Art Services",
            "type":"Services"
        }
    ],
    "sg:phone":"+61 2 9642 5605",
    "sg:postcode":"2135",
    "sg:province":"NSW",
    "sg:tags":[
        "decorator",
        "painter"
    ],
    "wof:name":"Fine Touch Painters",
    "wof:placetype":"venue"
},
  "geometry": {"coordinates":[151.08122253400001,-33.8791313171],"type":"Point"}
}