{
  "type": "Feature",
  "properties": {
    "iso:country":"AU",
    "sg:address":"53 Rusden St",
    "sg:city":"Kelvin Grove",
    "sg:classifiers":[
        {
            "category":"Professional",
            "subcategory":"Art Services",
            "type":"Services"
        }
    ],
    "sg:phone":"+61 7 3371 5520",
    "sg:postcode":"4059",
    "sg:province":"QLD",
    "sg:tags":[
        "decorator",
        "painter"
    ],
    "wof:name":"Clayton & Cosier Painters",
    "wof:placetype":"venue"
},
  "geometry": {"coordinates":[153.009689331,-27.4536113739],"type":"Point"}
}