{
  "type": "Feature",
  "properties": {
    "addr:full":"Unit 2, Ground Floor, 110 - 120 Botany Rd Alexandria NSW 2015",
    "addr:housenumber":"110 120",
    "addr:postcode":"2015",
    "addr:street":"Botany Rd",
    "iso:country":"AU",
    "sg:address":"Unit 2, Ground Floor, 110 - 120 Botany Rd",
    "sg:city":"Alexandria",
    "sg:classifiers":[
        {
            "category":"Shopping",
            "type":"Retail Goods"
        }
    ],
    "sg:phone":"+61 2 9318 9000",
    "sg:postcode":"2015",
    "sg:province":"NSW",
    "sg:tags":[
        "clearance",
        "factory",
        "outlet"
    ],
    "wof:name":"Sunbeam Factory Outlets",
    "wof:placetype":"venue"
},
  "geometry": {"coordinates":[151.199615478,-33.8980827332],"type":"Point"}
}