{
  "type": "Feature",
  "properties": {
    "addr:full":"Standing Drv Traralgon VIC 3844",
    "addr:postcode":"3844",
    "addr:street":"Standing Drv",
    "iso:country":"AU",
    "sg:address":"Standing Drv",
    "sg:city":"Traralgon",
    "sg:classifiers":[
        {
            "category":"Building & Trades",
            "subcategory":"Equipment Rental",
            "type":"Services"
        }
    ],
    "sg:phone":"+61 3 5174 5215",
    "sg:postcode":"3844",
    "sg:province":"VIC",
    "sg:tags":[
        "crane",
        "hire"
    ],
    "wof:name":"P & D Rigging & Crane Hire Pty Ltd",
    "wof:placetype":"venue"
},
  "geometry": {"coordinates":[146.56617736800001,-38.1910514832],"type":"Point"}
}