{
  "type": "Feature",
  "properties": {
    "iso:country":"AU",
    "sg:address":"66 Arndel Rd",
    "sg:city":"Horsley Park",
    "sg:classifiers":[
        {
            "category":"Utilities",
            "subcategory":"Electric",
            "type":"Services"
        }
    ],
    "sg:phone":"+61 414 425 571",
    "sg:postcode":"2164",
    "sg:province":"NSW",
    "sg:tags":[
        "electrical",
        "contractor"
    ],
    "wof:name":"Smedley Electrical Services",
    "wof:placetype":"venue"
},
  "geometry": {"coordinates":[150.91950988799999,-33.8440704346],"type":"Point"}
}