{
  "type": "Feature",
  "properties": {
    "iso:country":"AU",
    "sg:address":"6 Wongabel St",
    "sg:city":"Kenmore",
    "sg:classifiers":[
        {
            "category":"Education",
            "subcategory":"Vocational School",
            "type":"Public Place"
        }
    ],
    "sg:phone":"+61 7 3378 2213",
    "sg:postcode":"4069",
    "sg:province":"QLD",
    "sg:tags":[
        "cake",
        "decorating",
        "decorator"
    ],
    "wof:name":"Kenmore Cakes",
    "wof:placetype":"venue"
},
  "geometry": {"coordinates":[152.947998047,-27.509054184],"type":"Point"}
}