{
  "type": "Feature",
  "properties": {
    "iso:country":"AU",
    "sg:address":"28 Isles Drive",
    "sg:city":"Coffs Harbour",
    "sg:classifiers":[
        {
            "category":"Home & Garden",
            "subcategory":"Carpets & Floor Coverings",
            "type":"Retail Goods"
        }
    ],
    "sg:phone":"+61 2 6651 4133",
    "sg:postcode":"2450",
    "sg:province":"NSW",
    "sg:tags":[
        "tile",
        "wall"
    ],
    "wof:name":"Amber",
    "wof:placetype":"venue"
},
  "geometry": {"coordinates":[153.088135,-30.31572],"type":"Point"}
}