{
  "type": "Feature",
  "properties": {
    "addr:full":"82 Maitland St Muswellbrook NSW 2333",
    "addr:housenumber":"82",
    "addr:postcode":"2333",
    "addr:street":"Maitland St",
    "iso:country":"AU",
    "sg:address":"82 Maitland St",
    "sg:city":"Muswellbrook",
    "sg:classifiers":[
        {
            "category":"Retail",
            "subcategory":"Repair Shop",
            "type":"Services"
        }
    ],
    "sg:phone":"+61 2 6543 2404",
    "sg:postcode":"2333",
    "sg:province":"NSW",
    "sg:tags":[
        "machine",
        "repairs",
        "part",
        "dryer",
        "washing"
    ],
    "wof:name":"Warren Ward Refrigeration Pty Ltd",
    "wof:placetype":"venue"
},
  "geometry": {"coordinates":[150.89533996599999,-32.2756767273],"type":"Point"}
}