{
  "type": "Feature",
  "properties": {
    "addr:full":"41b Flinders St Lawson NSW 2783",
    "addr:housenumber":"41b",
    "addr:postcode":"2783",
    "addr:street":"Flinders St",
    "iso:country":"AU",
    "sg:address":"41b Flinders St",
    "sg:city":"Lawson",
    "sg:classifiers":[
        {
            "category":"Manufacturing",
            "subcategory":"Furniture",
            "type":"Manufacturing & Wholesale Goods"
        }
    ],
    "sg:phone":"+61 2 4759 1730",
    "sg:postcode":"2783",
    "sg:province":"NSW",
    "sg:tags":[
        "builder",
        "designer",
        "custom"
    ],
    "wof:name":"Country Cottage Kitchens",
    "wof:placetype":"venue"
},
  "geometry": {"coordinates":[150.441894531,-33.7259216309],"type":"Point"}
}