{
  "type": "Feature",
  "properties": {
    "addr:full":"15 Coolong Rd Vaucluse NSW 2030",
    "addr:housenumber":"15",
    "addr:postcode":"2030",
    "addr:street":"Coolong Rd",
    "iso:country":"AU",
    "sg:address":"15 Coolong Rd",
    "sg:city":"Vaucluse",
    "sg:classifiers":[
        {
            "category":"Health Services",
            "subcategory":"Doctor",
            "type":"Services"
        }
    ],
    "sg:phone":"+61 2 9337 5790",
    "sg:postcode":"2030",
    "sg:province":"NSW",
    "sg:tags":[
        "medical",
        "practitioner"
    ],
    "wof:name":"Lance J W",
    "wof:placetype":"venue"
},
  "geometry": {"coordinates":[151.270828247,-33.8521347046],"type":"Point"}
}