{
  "type": "Feature",
  "properties": {
    "iso:country":"AU",
    "sg:address":"6 64 Clarence St",
    "sg:city":"Sydney",
    "sg:classifiers":[
        {
            "category":"Professional",
            "type":"Services"
        }
    ],
    "sg:phone":"+61 2 9262 4222",
    "sg:postcode":"2000",
    "sg:province":"NSW",
    "sg:tags":[
        "auctioneer"
    ],
    "wof:name":"AuctionsPlus Pty Ltd",
    "wof:placetype":"venue"
},
  "geometry": {"coordinates":[151.205200195,-33.8665924072],"type":"Point"}
}