{
  "type": "Feature",
  "properties": {
    "addr:full":"Brighton Day Surgery 1 Jetty Rd Brighton SA 5048",
    "addr:housenumber":"1",
    "addr:postcode":"5048",
    "addr:street":"Jetty Rd",
    "iso:country":"AU",
    "sg:address":"Brighton Day Surgery 1 Jetty Rd",
    "sg:city":"Brighton",
    "sg:classifiers":[
        {
            "category":"Health Services",
            "subcategory":"Doctor",
            "type":"Services"
        }
    ],
    "sg:phone":"+61 8 8377 1775",
    "sg:postcode":"5048",
    "sg:province":"SA",
    "sg:tags":[
        "medical",
        "practitioner"
    ],
    "wof:name":"Lisa Marks Dr",
    "wof:placetype":"venue"
},
  "geometry": {"coordinates":[138.522705,-35.017052],"type":"Point"}
}