{
  "type": "Feature",
  "properties": {
    "addr:full":"U17/ 389 Payneham Rd Marden SA 5070",
    "addr:postcode":"5070",
    "addr:street":"/;Payneham Rd",
    "iso:country":"AU",
    "sg:address":"U17/ 389 Payneham Rd",
    "sg:city":"Marden",
    "sg:classifiers":[
        {
            "category":"Personal",
            "subcategory":"Beauty Salon",
            "type":"Services"
        }
    ],
    "sg:phone":"+61 8 8336 2978",
    "sg:postcode":"5070",
    "sg:province":"SA",
    "sg:tags":[
        "hairdresser"
    ],
    "wof:name":"Whoosh Hair Design",
    "wof:placetype":"venue"
},
  "geometry": {"coordinates":[138.64073181099999,-34.8956031799],"type":"Point"}
}