{
  "type": "Feature",
  "properties": {
    "addr:full":"83- 85 Bridge St Toowoomba QLD 4350",
    "addr:housenumber":"85",
    "addr:postcode":"4350",
    "addr:street":"Bridge St",
    "iso:country":"AU",
    "sg:address":"83- 85 Bridge St",
    "sg:city":"Toowoomba",
    "sg:classifiers":[
        {
            "category":"Autos & Motor Vehicles",
            "subcategory":"Fuel & Gas Station",
            "type":"Retail Goods"
        }
    ],
    "sg:phone":"+61 7 4632 6790",
    "sg:postcode":"4350",
    "sg:province":"QLD",
    "wof:name":"BP East",
    "wof:placetype":"venue"
},
  "geometry": {"coordinates":[151.90086400000001,-27.533897],"type":"Point"}
}