{
  "type": "Feature",
  "properties": {
    "iso:country":"AU",
    "sg:address":"PO Box 110",
    "sg:city":"Kingston SE",
    "sg:classifiers":[
        {
            "category":"Building & Trades",
            "subcategory":"Landscaping Services",
            "type":"Services"
        }
    ],
    "sg:phone":"+61 8 8767 6057",
    "sg:postcode":"5275",
    "sg:province":"SA",
    "sg:tags":[
        "grazier"
    ],
    "wof:name":"Jeffrey G N & M J",
    "wof:placetype":"venue"
},
  "geometry": {"coordinates":[139.861633,-36.825432],"type":"Point"}
}