{
  "type": "Feature",
  "properties": {
    "iso:country":"AU",
    "sg:address":"48 Keswick St",
    "sg:city":"Georges Hall",
    "sg:classifiers":[
        {
            "category":"Professional",
            "type":"Services"
        }
    ],
    "sg:phone":"+61 411 114 912",
    "sg:postcode":"2198",
    "sg:province":"NSW",
    "sg:tags":[
        "courier"
    ],
    "wof:name":"A Class Couriers",
    "wof:placetype":"venue"
},
  "geometry": {"coordinates":[150.98672500000001,-33.911434],"type":"Point"}
}