{
  "type": "Feature",
  "properties": {
    "iso:country":"AU",
    "sg:address":"Yellow Gold Shopping Centre 175 Wickham St",
    "sg:city":"Fortitude Valley",
    "sg:classifiers":[
        {
            "category":"Food & Beverages",
            "subcategory":"Meat & Fish",
            "type":"Retail Goods"
        }
    ],
    "sg:phone":"+61 7 3252 0299",
    "sg:postcode":"4006",
    "sg:province":"QLD",
    "sg:tags":[
        "seafood"
    ],
    "wof:name":"L & J Developments",
    "wof:placetype":"venue"
},
  "geometry": {"coordinates":[153.033294678,-27.4580383301],"type":"Point"}
}