{
  "type": "Feature",
  "properties": {
    "addr:full":"181 Harvey Rd Redlynch QLD 4870",
    "addr:housenumber":"181",
    "addr:postcode":"4870",
    "addr:street":"Harvey Rd",
    "iso:country":"AU",
    "sg:address":"181 Harvey Rd",
    "sg:city":"Redlynch",
    "sg:classifiers":[
        {
            "category":"Travel",
            "subcategory":"Travel Agent",
            "type":"Entertainment"
        }
    ],
    "sg:phone":"+61 7 4039 0200",
    "sg:postcode":"4870",
    "sg:province":"QLD",
    "sg:tags":[
        "consultant"
    ],
    "wof:name":"Diversion Dive Travel",
    "wof:placetype":"venue"
},
  "geometry": {"coordinates":[145.692993164,-16.888551712],"type":"Point"}
}