{
  "type": "Feature",
  "properties": {
    "addr:full":"18 Brooks Rd Denham Court NSW 2565",
    "addr:housenumber":"18",
    "addr:postcode":"2565",
    "addr:street":"Brooks Rd;Court",
    "iso:country":"AU",
    "sg:address":"18 Brooks Rd",
    "sg:city":"Denham Court",
    "sg:classifiers":[
        {
            "category":"Shopping",
            "subcategory":"Clothing, Apparel, & Fashions",
            "type":"Retail Goods"
        }
    ],
    "sg:phone":"+61 2 9829 8048",
    "sg:postcode":"2565",
    "sg:province":"NSW",
    "sg:tags":[
        "lady",
        "wear"
    ],
    "wof:name":"BBK International",
    "wof:placetype":"venue"
},
  "geometry": {"coordinates":[150.84866332999999,-33.9885368347],"type":"Point"}
}