{
  "type": "Feature",
  "properties": {
    "addr:full":"510 Great Western Hwy Pendle Hill NSW 2145",
    "addr:housenumber":"510",
    "addr:postcode":"2145",
    "addr:street":"Great Western Hwy",
    "iso:country":"AU",
    "sg:address":"510 Great Western Hwy",
    "sg:city":"Pendle Hill",
    "sg:classifiers":[
        {
            "category":"Autos & Motor Vehicles",
            "subcategory":"Auto Supplies",
            "type":"Retail Goods"
        }
    ],
    "sg:phone":"+61 2 9636 1133",
    "sg:postcode":"2145",
    "sg:province":"NSW",
    "sg:tags":[
        "equipment",
        "part",
        "truck"
    ],
    "wof:name":"Carasel Bull Bars",
    "wof:placetype":"venue"
},
  "geometry": {"coordinates":[150.952590942,-33.8114814758],"type":"Point"}
}