{
  "type": "Feature",
  "properties": {
    "addr:full":"5- 7 Humffray St North Ballarat VIC 3350",
    "addr:housenumber":"7",
    "addr:postcode":"3350",
    "addr:street":"Humffray St North",
    "iso:country":"AU",
    "sg:address":"5- 7 Humffray St",
    "sg:city":"North Ballarat",
    "sg:classifiers":[
        {
            "category":"Travel",
            "subcategory":"Hotels & Motels",
            "type":"Entertainment"
        }
    ],
    "sg:phone":"+61 3 5331 3277",
    "sg:postcode":"3350",
    "sg:province":"VIC",
    "wof:name":"Menzies Motor Inn",
    "wof:placetype":"venue"
},
  "geometry": {"coordinates":[143.86570699999999,-37.561958],"type":"Point"}
}