{
  "type": "Feature",
  "properties": {
    "iso:country":"AU",
    "sg:address":"609 Waterdale Rd",
    "sg:city":"Heidelberg West",
    "sg:classifiers":[
        {
            "category":"Retail",
            "subcategory":"Auto Repair",
            "type":"Services"
        }
    ],
    "sg:phone":"+61 3 9458 4427",
    "sg:postcode":"3081",
    "sg:province":"VIC",
    "sg:tags":[
        "beater",
        "painter",
        "panel"
    ],
    "wof:name":"Brumby's Smash Repairs",
    "wof:placetype":"venue"
},
  "geometry": {"coordinates":[145.04904174800001,-37.73412323],"type":"Point"}
}