{
  "type": "Feature",
  "properties": {
    "addr:full":"8 Pethick Rd McLaren Vale SA 5171",
    "addr:housenumber":"8",
    "addr:postcode":"5171",
    "addr:street":"Pethick Rd",
    "iso:country":"AU",
    "sg:address":"8 Pethick Rd",
    "sg:city":"McLaren Vale",
    "sg:classifiers":[
        {
            "category":"Communications",
            "subcategory":"News Services",
            "type":"Services"
        }
    ],
    "sg:phone":"+61 8 8323 8225",
    "sg:postcode":"5171",
    "sg:province":"SA",
    "sg:tags":[
        "information",
        "tourist",
        "attractions"
    ],
    "wof:name":"Camelot Carriage Complex",
    "wof:placetype":"venue"
},
  "geometry": {"coordinates":[138.53263855,-35.2417106628],"type":"Point"}
}