{
  "type": "Feature",
  "properties": {
    "addr:full":"29 Wallis St Seymour VIC 3660",
    "addr:housenumber":"29",
    "addr:postcode":"3660",
    "addr:street":"Wallis St",
    "iso:country":"AU",
    "sg:address":"29 Wallis St",
    "sg:city":"Seymour",
    "sg:classifiers":[
        {
            "category":"Retail",
            "subcategory":"Veterinary Services",
            "type":"Services"
        }
    ],
    "sg:phone":"+61 3 5799 1922",
    "sg:postcode":"3660",
    "sg:province":"VIC",
    "sg:tags":[
        "surgeon"
    ],
    "wof:name":"Kettlewell Jack Dr",
    "wof:placetype":"venue"
},
  "geometry": {"coordinates":[145.13548278799999,-37.0193443298],"type":"Point"}
}