{
  "type": "Feature",
  "properties": {
    "iso:country":"AU",
    "sg:address":"Unit 1/ 13 Creswell Rd",
    "sg:city":"Largs Bay",
    "sg:classifiers":[
        {
            "category":"Wholesale",
            "subcategory":"Machinery & Supplies",
            "type":"Manufacturing & Wholesale Goods"
        }
    ],
    "sg:phone":"+61 8 8242 5754",
    "sg:postcode":"5016",
    "sg:province":"SA",
    "sg:tags":[
        "equipment",
        "hydraulic"
    ],
    "wof:name":"Portside Hydraulics & Engineering",
    "wof:placetype":"venue"
},
  "geometry": {"coordinates":[138.50413513199999,-34.8228683472],"type":"Point"}
}