{
  "type": "Feature",
  "properties": {
    "addr:full":"16 Alberta Drv Woree QLD 4868",
    "addr:housenumber":"16",
    "addr:postcode":"4868",
    "addr:street":"Alberta Drv",
    "iso:country":"AU",
    "sg:address":"16 Alberta Drv",
    "sg:city":"Woree",
    "sg:classifiers":[
        {
            "category":"Professional",
            "subcategory":"Computer Services",
            "type":"Services"
        }
    ],
    "sg:phone":"+61 7 4054 1963",
    "sg:postcode":"4868",
    "sg:province":"QLD",
    "sg:tags":[
        "consultant",
        "system"
    ],
    "wof:name":"Kynaston Computers",
    "wof:placetype":"venue"
},
  "geometry": {"coordinates":[145.74429321299999,-16.964307785],"type":"Point"}
}