{
  "type": "Feature",
  "properties": {
    "addr:full":"Dudley St Gorokan NSW 2263",
    "addr:postcode":"2263",
    "addr:street":"Dudley St",
    "iso:country":"AU",
    "sg:address":"Dudley St",
    "sg:city":"Gorokan",
    "sg:classifiers":[
        {
            "category":"Education",
            "subcategory":"School",
            "type":"Public Place"
        }
    ],
    "sg:phone":"+61 2 4392 4200",
    "sg:postcode":"2263",
    "sg:province":"NSW",
    "sg:tags":[
        "state",
        "-",
        "nsw"
    ],
    "wof:name":"Gorokan Public School",
    "wof:placetype":"venue"
},
  "geometry": {"coordinates":[151.50741600000001,-33.254959],"type":"Point"}
}