{
  "type": "Feature",
  "properties": {
    "addr:full":"32 Finlay Rd Warrawee NSW 2074",
    "addr:housenumber":"32",
    "addr:postcode":"2074",
    "addr:street":"Finlay Rd",
    "iso:country":"AU",
    "sg:address":"32 Finlay Rd",
    "sg:city":"Warrawee",
    "sg:classifiers":[
        {
            "category":"Insurance",
            "subcategory":"Insurance Agent",
            "type":"Services"
        }
    ],
    "sg:phone":"+61 2 9488 8326",
    "sg:postcode":"2074",
    "sg:province":"NSW",
    "wof:name":"Karuna Pty Ltd",
    "wof:placetype":"venue"
},
  "geometry": {"coordinates":[151.12037658700001,-33.7330207825],"type":"Point"}
}