{
  "type": "Feature",
  "properties": {
    "addr:full":"Devereaux St Oak Park VIC 3046",
    "addr:postcode":"3046",
    "addr:street":"Devereaux St",
    "iso:country":"AU",
    "sg:address":"Devereaux St",
    "sg:city":"Oak Park",
    "sg:classifiers":[
        {
            "category":"Professional",
            "subcategory":"Art Services",
            "type":"Services"
        }
    ],
    "sg:phone":"+61 403 011 066",
    "sg:postcode":"3046",
    "sg:province":"VIC",
    "sg:tags":[
        "decorator",
        "painter"
    ],
    "wof:name":"Australia's Complete Painting Service",
    "wof:placetype":"venue"
},
  "geometry": {"coordinates":[144.91265869099999,-37.7147293091],"type":"Point"}
}