{
  "type": "Feature",
  "properties": {
    "addr:full":"25 Gray Reserve Rd Williamstown VIC 3016",
    "addr:housenumber":"25",
    "addr:postcode":"3016",
    "addr:street":"Gray Reserve Rd",
    "iso:country":"AU",
    "sg:address":"25 Gray Reserve Rd",
    "sg:city":"Williamstown",
    "sg:classifiers":[
        {
            "category":"Arena",
            "subcategory":"Indoor Arena",
            "type":"Entertainment"
        }
    ],
    "sg:phone":"+61 3 9397 7881",
    "sg:postcode":"3016",
    "sg:province":"VIC",
    "sg:tags":[
        "club",
        "angling"
    ],
    "wof:name":"Kororoit Creek Angling Club",
    "wof:placetype":"venue"
},
  "geometry": {"coordinates":[144.86544799800001,-37.8579711914],"type":"Point"}
}