{
  "type": "Feature",
  "properties": {
    "iso:country":"AU",
    "sg:address":"Lot 88 Chittering Rd",
    "sg:city":"Lower Chittering",
    "sg:classifiers":[
        {
            "category":"Farming",
            "subcategory":"Vineyard",
            "type":"Manufacturing & Wholesale Goods"
        }
    ],
    "sg:phone":"+61 8 9571 8800",
    "sg:postcode":"6084",
    "sg:province":"WA",
    "sg:tags":[
        "winery"
    ],
    "wof:name":"Western Range Wines Ltd",
    "wof:placetype":"venue"
},
  "geometry": {"coordinates":[116.08783721899999,-31.5706253052],"type":"Point"}
}