{
  "type": "Feature",
  "properties": {
    "addr:full":"37 Twentieth St Renmark SA 5341",
    "addr:housenumber":"37",
    "addr:postcode":"5341",
    "addr:street":"Twentieth St",
    "iso:country":"AU",
    "sg:address":"37 Twentieth St",
    "sg:city":"Renmark",
    "sg:classifiers":[
        {
            "category":"Wholesale",
            "subcategory":"Metals & Minerals",
            "type":"Manufacturing & Wholesale Goods"
        }
    ],
    "sg:phone":"+61 8 8586 5880",
    "sg:postcode":"5341",
    "sg:province":"SA",
    "sg:tags":[
        "steel",
        "merchant"
    ],
    "wof:name":"Discount Steel Supplies Pty Ltd",
    "wof:placetype":"venue"
},
  "geometry": {"coordinates":[140.74244689899999,-34.1783599854],"type":"Point"}
}