{
  "type": "Feature",
  "properties": {
    "iso:country":"AU",
    "sg:address":"544 Elizabeth St",
    "sg:city":"Melbourne",
    "sg:classifiers":[
        {
            "category":"Autos & Motor Vehicles",
            "subcategory":"Automobile Sales",
            "type":"Retail Goods"
        }
    ],
    "sg:phone":"+61 3 9347 4533",
    "sg:postcode":"3000",
    "sg:province":"VIC",
    "sg:tags":[
        "car",
        "new"
    ],
    "wof:name":"City Nissan",
    "wof:placetype":"venue"
},
  "geometry": {"coordinates":[144.95939636200001,-37.8053016663],"type":"Point"}
}