{
  "type": "Feature",
  "properties": {
    "iso:country":"AU",
    "sg:address":"8 River St",
    "sg:city":"Richmond",
    "sg:classifiers":[
        {
            "category":"Wholesale",
            "subcategory":"Machinery & Supplies",
            "type":"Manufacturing & Wholesale Goods"
        }
    ],
    "sg:phone":"+61 3 8420 8999",
    "sg:postcode":"3121",
    "sg:province":"VIC",
    "sg:tags":[
        "instrument",
        "scientific"
    ],
    "wof:name":"Seismology Research Centre",
    "wof:placetype":"venue"
},
  "geometry": {"coordinates":[145.013397217,-37.8156013489],"type":"Point"}
}