{
  "type": "Feature",
  "properties": {
    "addr:full":"59 McCoy St Myaree WA 6154",
    "addr:housenumber":"59",
    "addr:postcode":"6154",
    "addr:street":"Mccoy St",
    "iso:country":"AU",
    "sg:address":"59 McCoy St",
    "sg:city":"Myaree",
    "sg:classifiers":[
        {
            "category":"Retail",
            "subcategory":"Auto Repair",
            "type":"Services"
        }
    ],
    "sg:phone":"+61 1300 797 078",
    "sg:postcode":"6154",
    "sg:province":"WA",
    "sg:tags":[
        "repairer",
        "motor",
        "engineer"
    ],
    "wof:name":"RAC Auto Services",
    "wof:placetype":"venue"
},
  "geometry": {"coordinates":[115.81392700000001,-32.043659],"type":"Point"}
}