{
  "type": "Feature",
  "properties": {
    "addr:full":"31 Crosby Rd Albion QLD 4010",
    "addr:housenumber":"31",
    "addr:postcode":"4010",
    "addr:street":"Crosby Rd",
    "iso:country":"AU",
    "sg:address":"31 Crosby Rd",
    "sg:city":"Albion",
    "sg:classifiers":[
        {
            "category":"Retail",
            "subcategory":"Auto Repair",
            "type":"Services"
        }
    ],
    "sg:phone":"+61 7 3262 4831",
    "sg:postcode":"4010",
    "sg:province":"QLD",
    "sg:tags":[
        "beater",
        "painter",
        "panel"
    ],
    "wof:name":"Albion Smash Repairs",
    "wof:placetype":"venue"
},
  "geometry": {"coordinates":[153.044464111,-27.4323863983],"type":"Point"}
}