{
  "type": "Feature",
  "properties": {
    "iso:country":"AU",
    "sg:address":"Sussex St",
    "sg:city":"Haymarket",
    "sg:classifiers":[
        {
            "category":"Food & Beverages",
            "subcategory":"Bakery",
            "type":"Retail Goods"
        }
    ],
    "sg:phone":"+61 2 9281 1818",
    "sg:postcode":"2000",
    "sg:province":"NSW",
    "sg:tags":[
        "cake",
        "shop",
        "pastry"
    ],
    "wof:name":"Helen's Cake Shop",
    "wof:placetype":"venue"
},
  "geometry": {"coordinates":[151.20489501899999,-33.8791656494],"type":"Point"}
}