{
  "type": "Feature",
  "properties": {
    "addr:full":"Shop 1 & 2 92 Charlotte St Wynnum QLD 4178",
    "addr:housenumber":"shop 1 &;92",
    "addr:postcode":"4178",
    "addr:street":"2;Charlotte St",
    "iso:country":"AU",
    "sg:address":"Shop 1 & 2 92 Charlotte St",
    "sg:city":"Wynnum",
    "sg:classifiers":[
        {
            "category":"Professional",
            "subcategory":"Employment Agencies",
            "type":"Services"
        }
    ],
    "sg:phone":"+61 7 3396 3735",
    "sg:postcode":"4178",
    "sg:province":"QLD",
    "wof:name":"MAX Employment",
    "wof:placetype":"venue"
},
  "geometry": {"coordinates":[153.17251586899999,-27.4434108734],"type":"Point"}
}