{
  "type": "Feature",
  "properties": {
    "addr:full":"100 Grant St Alexandra VIC 3714",
    "addr:housenumber":"100",
    "addr:postcode":"3714",
    "addr:street":"Grant St",
    "iso:country":"AU",
    "sg:address":"100 Grant St",
    "sg:city":"Alexandra",
    "sg:classifiers":[
        {
            "category":"Home & Garden",
            "subcategory":"Household Appliances",
            "type":"Retail Goods"
        }
    ],
    "sg:phone":"+61 3 5772 1126",
    "sg:postcode":"3714",
    "sg:province":"VIC",
    "sg:tags":[
        "equipment",
        "gas"
    ],
    "wof:name":"Alexandra Traders Pty Ltd",
    "wof:placetype":"venue"
},
  "geometry": {"coordinates":[145.70962524399999,-37.1918449402],"type":"Point"}
}