{
  "type": "Feature",
  "properties": {
    "addr:full":"16 Austin St Hopetoun VIC 3396",
    "addr:housenumber":"16",
    "addr:postcode":"3396",
    "addr:street":"Austin St",
    "iso:country":"AU",
    "sg:address":"16 Austin St",
    "sg:city":"Hopetoun",
    "sg:classifiers":[
        {
            "category":"Travel",
            "subcategory":"Hotels & Motels",
            "type":"Entertainment"
        }
    ],
    "sg:phone":"+61 3 5083 3070",
    "sg:postcode":"3396",
    "sg:province":"VIC",
    "wof:name":"Hopetoun Community Hotel Motel",
    "wof:placetype":"venue"
},
  "geometry": {"coordinates":[142.363845825,-35.7274627686],"type":"Point"}
}