{
  "type": "Feature",
  "properties": {
    "addr:full":"38 Sanger St Corowa NSW 2646",
    "addr:housenumber":"38",
    "addr:postcode":"2646",
    "addr:street":"Sanger St",
    "iso:country":"AU",
    "sg:address":"38 Sanger St",
    "sg:city":"Corowa",
    "sg:classifiers":[
        {
            "category":"Shopping",
            "subcategory":"Clothing, Apparel, & Fashions",
            "type":"Retail Goods"
        }
    ],
    "sg:phone":"+61 2 6033 2011",
    "sg:postcode":"2646",
    "sg:province":"NSW",
    "sg:tags":[
        "jean"
    ],
    "wof:name":"Origin Clothing",
    "wof:placetype":"venue"
},
  "geometry": {"coordinates":[146.39134216299999,-35.9947929382],"type":"Point"}
}