{
  "type": "Feature",
  "properties": {
    "addr:full":"8 Railway Ave Werribee VIC 3030",
    "addr:housenumber":"8",
    "addr:postcode":"3030",
    "addr:street":"Railway Ave",
    "iso:country":"AU",
    "sg:address":"8 Railway Ave",
    "sg:city":"Werribee",
    "sg:classifiers":[
        {
            "category":"Home & Garden",
            "subcategory":"Carpets & Floor Coverings",
            "type":"Retail Goods"
        }
    ],
    "sg:phone":"+61 413 649 880",
    "sg:postcode":"3030",
    "sg:province":"VIC",
    "sg:tags":[
        "tile",
        "wall",
        "layer"
    ],
    "wof:name":"A & S Tilers",
    "wof:placetype":"venue"
},
  "geometry": {"coordinates":[144.66511499999999,-37.897202],"type":"Point"}
}