{
  "type": "Feature",
  "properties": {
    "addr:full":"29 Samford Rd Alderley QLD 4051",
    "addr:housenumber":"29",
    "addr:postcode":"4051",
    "addr:street":"Samford Rd",
    "iso:country":"AU",
    "sg:address":"29 Samford Rd",
    "sg:city":"Alderley",
    "sg:classifiers":[
        {
            "category":"Real Estate",
            "subcategory":"Real Estate Agent",
            "type":"Services"
        }
    ],
    "sg:phone":"+61 7 3856 0444",
    "sg:postcode":"4051",
    "sg:province":"QLD",
    "wof:name":"Brian Collins Real Estate",
    "wof:placetype":"venue"
},
  "geometry": {"coordinates":[152.99958801299999,-27.4247016907],"type":"Point"}
}