{
  "type": "Feature",
  "properties": {
    "iso:country":"AU",
    "sg:address":"Shop 18 Emerald Village Shopping Centre Hospital R",
    "sg:city":"Emerald",
    "sg:classifiers":[
        {
            "category":"Shopping",
            "subcategory":"Music",
            "type":"Retail Goods"
        }
    ],
    "sg:phone":"+61 7 4987 5510",
    "sg:postcode":"4720",
    "sg:province":"QLD",
    "sg:tags":[
        "instrument",
        "musical"
    ],
    "wof:name":"The Wolffs Den",
    "wof:placetype":"venue"
},
  "geometry": {"coordinates":[148.158096,-23.52412],"type":"Point"}
}