{
  "type": "Feature",
  "properties": {
    "addr:full":"79 Birchgrove Rd Balmain NSW 2041",
    "addr:housenumber":"79",
    "addr:postcode":"2041",
    "addr:street":"Birchgrove Rd",
    "iso:country":"AU",
    "sg:address":"79 Birchgrove Rd",
    "sg:city":"Balmain",
    "sg:classifiers":[
        {
            "category":"Professional",
            "subcategory":"Business Services",
            "type":"Services"
        }
    ],
    "sg:phone":"+61 2 9810 8595",
    "sg:postcode":"2041",
    "sg:province":"NSW",
    "sg:tags":[
        "drafting"
    ],
    "wof:name":"Willoughby Bruce",
    "wof:placetype":"venue"
},
  "geometry": {"coordinates":[151.177246,-33.853661],"type":"Point"}
}