{
  "type": "Feature",
  "properties": {
    "addr:full":"Factory 3/ 192 Old Geelong Rd Hoppers Crossing VIC 3029",
    "addr:housenumber":"/ 192",
    "addr:postcode":"3029",
    "addr:street":"Old Geelong Rd",
    "iso:country":"AU",
    "sg:address":"Factory 3/ 192 Old Geelong Rd",
    "sg:city":"Hoppers Crossing",
    "sg:classifiers":[
        {
            "category":"Professional",
            "subcategory":"Detective & Security Services",
            "type":"Services"
        }
    ],
    "sg:phone":"+61 3 9749 0671",
    "sg:postcode":"3029",
    "sg:province":"VIC",
    "sg:tags":[
        "equipment",
        "window",
        "doors"
    ],
    "wof:name":"Enkay Blinds & Screens",
    "wof:placetype":"venue"
},
  "geometry": {"coordinates":[144.71639999999999,-37.876114],"type":"Point"}
}