{
  "type": "Feature",
  "properties": {
    "iso:country":"AU",
    "sg:address":"758 Anzac Pde",
    "sg:city":"Maroubra",
    "sg:classifiers":[
        {
            "category":"Education",
            "subcategory":"School",
            "type":"Public Place"
        }
    ],
    "sg:phone":"+61 2 9349 6714",
    "sg:postcode":"2035",
    "sg:province":"NSW",
    "sg:tags":[
        "co-educational"
    ],
    "wof:name":"French Australian Pre-School",
    "wof:placetype":"venue"
},
  "geometry": {"coordinates":[151.23863220199999,-33.9367790222],"type":"Point"}
}