{
  "type": "Feature",
  "properties": {
    "iso:country":"AU",
    "sg:address":"Suite 6 / 539 Highett Rd",
    "sg:city":"Highett",
    "sg:classifiers":[
        {
            "category":"Social Services",
            "subcategory":"Child Care",
            "type":"Services"
        }
    ],
    "sg:phone":"+61 3 9532 2017",
    "sg:postcode":"3190",
    "sg:province":"VIC",
    "wof:name":"Child Care Centres&#039; Association Of Victoria Inc.",
    "wof:placetype":"venue"
},
  "geometry": {"coordinates":[145.04397582999999,-37.9488296509],"type":"Point"}
}