{
  "type": "Feature",
  "properties": {
    "addr:full":"205 Pt Nepean Rd Dromana VIC 3936",
    "addr:housenumber":"205",
    "addr:postcode":"3936",
    "addr:street":"Pt Nepean Rd",
    "iso:country":"AU",
    "sg:address":"205 Pt Nepean Rd",
    "sg:city":"Dromana",
    "sg:classifiers":[
        {
            "category":"Wholesale",
            "subcategory":"Medical Equipment & Supplies",
            "type":"Manufacturing & Wholesale Goods"
        }
    ],
    "sg:phone":"+61 3 5987 1516",
    "sg:postcode":"3936",
    "sg:province":"VIC",
    "sg:tags":[
        "aid",
        "care",
        "health",
        "home"
    ],
    "wof:name":"Pearse's Amcal Pharmacy",
    "wof:placetype":"venue"
},
  "geometry": {"coordinates":[144.965866089,-38.3323402405],"type":"Point"}
}