{
  "type": "Feature",
  "properties": {
    "addr:full":"Shp1/ 43 Appletree Rd Holmesville NSW 2286",
    "addr:housenumber":"43",
    "addr:postcode":"2286",
    "addr:street":"Appletree Rd",
    "iso:country":"AU",
    "sg:address":"Shp1/ 43 Appletree Rd",
    "sg:city":"Holmesville",
    "sg:classifiers":[
        {
            "category":"Food & Beverages",
            "subcategory":"Groceries & Convenience Stores",
            "type":"Retail Goods"
        }
    ],
    "sg:phone":"+61 2 4953 2963",
    "sg:postcode":"2286",
    "sg:province":"NSW",
    "wof:name":"Holmesville Mini Market",
    "wof:placetype":"venue"
},
  "geometry": {"coordinates":[151.581939697,-32.9155654907],"type":"Point"}
}