{
  "type": "Feature",
  "properties": {
    "addr:full":"3 Rob Veivers Drv Kuranda QLD 4872",
    "addr:housenumber":"3",
    "addr:postcode":"4872",
    "addr:street":"Rob Veivers Drv",
    "iso:country":"AU",
    "sg:address":"3 Rob Veivers Drv",
    "sg:city":"Kuranda",
    "sg:classifiers":[
        {
            "category":"Autos & Motor Vehicles",
            "subcategory":"Fuel & Gas Station",
            "type":"Retail Goods"
        }
    ],
    "sg:phone":"+61 7 4093 9400",
    "sg:postcode":"4872",
    "sg:province":"QLD",
    "wof:name":"BP Kuranda Roadhouse",
    "wof:placetype":"venue"
},
  "geometry": {"coordinates":[145.632980347,-16.8220977783],"type":"Point"}
}