{
  "type": "Feature",
  "properties": {
    "addr:full":"14 Nooramunga Ave Cambewarra NSW 2540",
    "addr:housenumber":"14",
    "addr:postcode":"2540",
    "addr:street":"Nooramunga Ave",
    "iso:country":"AU",
    "sg:address":"14 Nooramunga Ave",
    "sg:city":"Cambewarra",
    "sg:classifiers":[
        {
            "category":"Education",
            "subcategory":"Special Training",
            "type":"Public Place"
        }
    ],
    "sg:phone":"+61 413 589 467",
    "sg:postcode":"2540",
    "sg:province":"NSW",
    "sg:tags":[
        "development"
    ],
    "wof:name":"Confined Space Solutions",
    "wof:placetype":"venue"
},
  "geometry": {"coordinates":[150.55758667000001,-34.8195838928],"type":"Point"}
}