{
  "type": "Feature",
  "properties": {
    "addr:full":"136 Folland Ave Northgate SA 5085",
    "addr:housenumber":"136",
    "addr:postcode":"5085",
    "addr:street":"Folland Ave",
    "iso:country":"AU",
    "sg:address":"136 Folland Ave",
    "sg:city":"Northgate",
    "sg:classifiers":[
        {
            "category":"Education",
            "subcategory":"Kindergarten",
            "type":"Public Place"
        }
    ],
    "sg:phone":"+61 8 8369 2999",
    "sg:postcode":"5085",
    "sg:province":"SA",
    "sg:tags":[
        "pre-schools"
    ],
    "wof:name":"Northgate Children's Services",
    "wof:placetype":"venue"
},
  "geometry": {"coordinates":[138.63453674300001,-34.8577156067],"type":"Point"}
}