{
  "type": "Feature",
  "properties": {
    "addr:full":"23 Armstrong St Ballarat VIC 3350",
    "addr:housenumber":"23",
    "addr:postcode":"3350",
    "addr:street":"Armstrong St",
    "iso:country":"AU",
    "sg:address":"23 Armstrong St",
    "sg:city":"Ballarat",
    "sg:classifiers":[
        {
            "category":"Fast Food",
            "type":"Food & Drink"
        }
    ],
    "sg:phone":"+61 3 5332 2102",
    "sg:postcode":"3350",
    "sg:province":"VIC",
    "sg:tags":[
        "away",
        "take"
    ],
    "wof:name":"Pizza Haven",
    "wof:placetype":"venue"
},
  "geometry": {"coordinates":[143.856201,-37.563107],"type":"Point"}
}