{
  "type": "Feature",
  "properties": {
    "addr:full":"308 Walcott St North Perth WA 6006",
    "addr:housenumber":"308",
    "addr:postcode":"6006",
    "addr:street":"Walcott St",
    "iso:country":"AU",
    "sg:address":"308 Walcott St",
    "sg:city":"North Perth",
    "sg:classifiers":[
        {
            "category":"Wholesale",
            "subcategory":"Medical Equipment & Supplies",
            "type":"Manufacturing & Wholesale Goods"
        }
    ],
    "sg:phone":"+61 8 9271 7711",
    "sg:postcode":"6006",
    "sg:province":"WA",
    "sg:tags":[
        "aids",
        "hearing"
    ],
    "wof:name":"Sonic Hearing Pty Ltd",
    "wof:placetype":"venue"
},
  "geometry": {"coordinates":[115.857643127,-31.9217967987],"type":"Point"}
}