{
  "type": "Feature",
  "properties": {
    "iso:country":"AU",
    "sg:address":"4 John St",
    "sg:city":"Lidcombe",
    "sg:classifiers":[
        {
            "category":"Cafe",
            "type":"Food & Drink"
        }
    ],
    "sg:phone":"+61 2 9649 8008",
    "sg:postcode":"2141",
    "sg:province":"NSW",
    "wof:name":"J J Coffee House",
    "wof:placetype":"venue"
},
  "geometry": {"coordinates":[151.04437255900001,-33.8629646301],"type":"Point"}
}