{
  "type": "Feature",
  "properties": {
    "addr:full":"5 Oaklands Rd Somerton Park SA 5044",
    "addr:housenumber":"5",
    "addr:postcode":"5044",
    "addr:street":"Oaklands Rd",
    "iso:country":"AU",
    "sg:address":"5 Oaklands Rd",
    "sg:city":"Somerton Park",
    "sg:classifiers":[
        {
            "category":"Shopping",
            "subcategory":"Stationery & Office Supplies",
            "type":"Retail Goods"
        }
    ],
    "sg:phone":"+61 8 8376 7877",
    "sg:postcode":"5044",
    "sg:province":"SA",
    "sg:tags":[
        "equipment",
        "display",
        "exhibition"
    ],
    "wof:name":"Expanded Graphics",
    "wof:placetype":"venue"
},
  "geometry": {"coordinates":[138.52221700000001,-34.997257],"type":"Point"}
}