{
  "type": "Feature",
  "properties": {
    "iso:country":"AU",
    "sg:address":"Shop 3/ 166 Keira St",
    "sg:city":"Wollongong",
    "sg:classifiers":[
        {
            "category":"Restaurant",
            "type":"Food & Drink"
        }
    ],
    "sg:phone":"+61 2 4228 4811",
    "sg:postcode":"2500",
    "sg:province":"NSW",
    "wof:name":"Chef's Choice Restaurant",
    "wof:placetype":"venue"
},
  "geometry": {"coordinates":[150.893265,-34.423508],"type":"Point"}
}