{
  "type": "Feature",
  "properties": {
    "addr:full":"5 Scoresby Rd Bayswater VIC 3153",
    "addr:housenumber":"5",
    "addr:postcode":"3153",
    "addr:street":"Scoresby Rd",
    "iso:country":"AU",
    "sg:address":"5 Scoresby Rd",
    "sg:city":"Bayswater",
    "sg:classifiers":[
        {
            "category":"Home & Garden",
            "subcategory":"Hardware",
            "type":"Retail Goods"
        }
    ],
    "sg:phone":"+61 417 563 508",
    "sg:postcode":"3153",
    "sg:province":"VIC",
    "sg:tags":[
        "repair",
        "tool",
        "power"
    ],
    "wof:name":"Jag Power Tools",
    "wof:placetype":"venue"
},
  "geometry": {"coordinates":[145.271194458,-37.8395957947],"type":"Point"}
}