{
  "type": "Feature",
  "properties": {
    "addr:full":"500 Nepean Hwy Frankston VIC 3199",
    "addr:housenumber":"500",
    "addr:postcode":"3199",
    "addr:street":"Nepean Hwy",
    "iso:country":"AU",
    "sg:address":"500 Nepean Hwy",
    "sg:city":"Frankston",
    "sg:classifiers":[
        {
            "category":"Banks & Credit Unions",
            "subcategory":"Financial Services",
            "type":"Services"
        }
    ],
    "sg:phone":"+61 3 9781 3111",
    "sg:postcode":"3199",
    "sg:province":"VIC",
    "sg:tags":[
        "loan",
        "finance",
        "mortgage"
    ],
    "wof:name":"Prophet Home Loans",
    "wof:placetype":"venue"
},
  "geometry": {"coordinates":[145.12005615199999,-38.1447372437],"type":"Point"}
}