{
  "type": "Feature",
  "properties": {
    "iso:country":"AU",
    "sg:address":"8 Nelson St",
    "sg:city":"Nhill",
    "sg:classifiers":[
        {
            "category":"Autos & Motor Vehicles",
            "subcategory":"Fuel & Gas Station",
            "type":"Retail Goods"
        }
    ],
    "sg:phone":"+61 3 5391 1316",
    "sg:postcode":"3418",
    "sg:province":"VIC",
    "wof:name":"Mobil Oil Australia Pty Ltd",
    "wof:placetype":"venue"
},
  "geometry": {"coordinates":[141.661712647,-36.3342132568],"type":"Point"}
}