{
  "type": "Feature",
  "properties": {
    "addr:full":"6 Riddell Pde Elsternwick VIC 3185",
    "addr:housenumber":"6",
    "addr:postcode":"3185",
    "addr:street":"Riddell Pde",
    "iso:country":"AU",
    "sg:address":"6 Riddell Pde",
    "sg:city":"Elsternwick",
    "sg:classifiers":[
        {
            "category":"Government",
            "subcategory":"Customs House",
            "type":"Public Place"
        }
    ],
    "sg:phone":"+61 3 9523 5038",
    "sg:postcode":"3185",
    "sg:province":"VIC",
    "sg:tags":[
        "title",
        "management",
        "stratum"
    ],
    "wof:name":"Victoria Body Corporate Services Pty Ltd",
    "wof:placetype":"venue"
},
  "geometry": {"coordinates":[145.00205993599999,-37.8845748901],"type":"Point"}
}