{
  "type": "Feature",
  "properties": {
    "addr:full":"268 William St Perth WA 6000",
    "addr:housenumber":"268",
    "addr:postcode":"6000",
    "addr:street":"William St",
    "iso:country":"AU",
    "sg:address":"268 William St",
    "sg:city":"Perth",
    "sg:classifiers":[
        {
            "category":"Communications",
            "subcategory":"Film & Video Production",
            "type":"Services"
        }
    ],
    "sg:phone":"+61 8 9227 8261",
    "sg:postcode":"6000",
    "sg:province":"WA",
    "sg:tags":[
        "dvd",
        "library"
    ],
    "wof:name":"Cosmos Video Enterprises",
    "wof:placetype":"venue"
},
  "geometry": {"coordinates":[115.85674285899999,-31.9538383484],"type":"Point"}
}