{
  "type": "Feature",
  "properties": {
    "iso:country":"AU",
    "sg:address":"Victoria Gardens, 1/600 Victoria St",
    "sg:city":"Richmond",
    "sg:classifiers":[
        {
            "category":"Social Services",
            "subcategory":"Child Care",
            "type":"Services"
        }
    ],
    "sg:phone":"+61 3 8416 5300",
    "sg:postcode":"3121",
    "sg:province":"VIC",
    "sg:tags":[
        "fleet",
        "management"
    ],
    "wof:name":"Esanda FleetPartners",
    "wof:placetype":"venue"
},
  "geometry": {"coordinates":[145.00990295400001,-37.811630249],"type":"Point"}
}