{
  "type": "Feature",
  "properties": {
    "addr:full":"3 Killara Crt Mildura VIC 3500",
    "addr:housenumber":"3",
    "addr:postcode":"3500",
    "addr:street":"Killara Crt",
    "iso:country":"AU",
    "sg:address":"3 Killara Crt",
    "sg:city":"Mildura",
    "sg:classifiers":[
        {
            "category":"Shopping",
            "subcategory":"Stationery & Office Supplies",
            "type":"Retail Goods"
        }
    ],
    "sg:phone":"+61 3 5023 6817",
    "sg:postcode":"3500",
    "sg:province":"VIC",
    "sg:tags":[
        "equipment",
        "dairy"
    ],
    "wof:name":"Sunrise Milk Supply",
    "wof:placetype":"venue"
},
  "geometry": {"coordinates":[142.147705078,-34.203578949],"type":"Point"}
}