{
  "type": "Feature",
  "properties": {
    "addr:full":"450 Rokeby Rd Subiaco WA 6008",
    "addr:housenumber":"450",
    "addr:postcode":"6008",
    "addr:street":"Rokeby Rd",
    "iso:country":"AU",
    "sg:address":"450 Rokeby Rd",
    "sg:city":"Subiaco",
    "sg:classifiers":[
        {
            "category":"Arena",
            "subcategory":"Sports Club",
            "type":"Entertainment"
        }
    ],
    "sg:phone":"+61 8 9388 2053",
    "sg:postcode":"6008",
    "sg:province":"WA",
    "sg:tags":[
        "defence",
        "supply",
        "self",
        "instruction",
        "martial art"
    ],
    "wof:name":"Aikido Subiaco PCYC",
    "wof:placetype":"venue"
},
  "geometry": {"coordinates":[115.824012756,-31.9468021393],"type":"Point"}
}