{
  "type": "Feature",
  "properties": {
    "addr:full":"22 Glass St Richmond VIC 3121",
    "addr:housenumber":"22",
    "addr:postcode":"3121",
    "addr:street":"Glass St",
    "iso:country":"AU",
    "sg:address":"22 Glass St",
    "sg:city":"Richmond",
    "sg:classifiers":[
        {
            "category":"Professional",
            "subcategory":"Employment Agencies",
            "type":"Services"
        }
    ],
    "sg:phone":"+61 3 9421 0058",
    "sg:postcode":"3121",
    "sg:province":"VIC",
    "wof:name":"C R A Consulting Group",
    "wof:placetype":"venue"
},
  "geometry": {"coordinates":[145.00486755399999,-37.8244132996],"type":"Point"}
}