{
  "type": "Feature",
  "properties": {
    "addr:full":"PO Box 22 Anna Bay NSW 2316",
    "addr:postcode":"2316",
    "addr:street":"Anna Bay",
    "iso:country":"AU",
    "sg:address":"PO Box 22",
    "sg:city":"Anna Bay",
    "sg:classifiers":[
        {
            "category":"Professional",
            "subcategory":"Detective & Security Services",
            "type":"Services"
        }
    ],
    "sg:phone":"+61 400 138 786",
    "sg:postcode":"2316",
    "sg:province":"NSW",
    "sg:tags":[
        "guard",
        "patrol"
    ],
    "wof:name":"Newcastle Total Security",
    "wof:placetype":"venue"
},
  "geometry": {"coordinates":[152.08521999999999,-32.777599],"type":"Point"}
}