{
  "type": "Feature",
  "properties": {
    "addr:full":"88 Tweeddale Rd Applecross WA 6153",
    "addr:housenumber":"88",
    "addr:postcode":"6153",
    "addr:street":"Tweeddale Rd",
    "iso:country":"AU",
    "sg:address":"88 Tweeddale Rd",
    "sg:city":"Applecross",
    "sg:classifiers":[
        {
            "category":"Real Estate",
            "subcategory":"Developer",
            "type":"Services"
        }
    ],
    "sg:phone":"+61 8 9364 0400",
    "sg:postcode":"6153",
    "sg:province":"WA",
    "sg:tags":[
        "development"
    ],
    "wof:name":"Castelli Pty Ltd",
    "wof:placetype":"venue"
},
  "geometry": {"coordinates":[115.834152,-32.00845],"type":"Point"}
}