{
  "type": "Feature",
  "properties": {
    "addr:full":"34 Crossen St Echuca VIC 3564",
    "addr:housenumber":"34",
    "addr:postcode":"3564",
    "addr:street":"Crossen St",
    "iso:country":"AU",
    "sg:address":"34 Crossen St",
    "sg:city":"Echuca",
    "sg:classifiers":[
        {
            "category":"Retail",
            "subcategory":"Repair Shop",
            "type":"Services"
        }
    ],
    "sg:phone":"+61 3 5482 2916",
    "sg:postcode":"3564",
    "sg:province":"VIC",
    "sg:tags":[
        "upholsterer"
    ],
    "wof:name":"Shane's Upholstery",
    "wof:placetype":"venue"
},
  "geometry": {"coordinates":[144.73515319800001,-36.1413002014],"type":"Point"}
}