{
  "type": "Feature",
  "properties": {
    "addr:full":"114 River St Ballina NSW 2478",
    "addr:housenumber":"114",
    "addr:postcode":"2478",
    "addr:street":"River St",
    "iso:country":"AU",
    "sg:address":"114 River St",
    "sg:city":"Ballina",
    "sg:classifiers":[
        {
            "category":"Shopping",
            "subcategory":"Baby Store",
            "type":"Retail Goods"
        }
    ],
    "sg:phone":"+61 2 6686 6918",
    "sg:postcode":"2478",
    "sg:province":"NSW",
    "sg:tags":[
        "wear"
    ],
    "wof:name":"Brite Sparks",
    "wof:placetype":"venue"
},
  "geometry": {"coordinates":[153.56114196799999,-28.870847702],"type":"Point"}
}