{
  "type": "Feature",
  "properties": {
    "addr:full":"45 Tapscott St Maryborough QLD 4650",
    "addr:housenumber":"45",
    "addr:postcode":"4650",
    "addr:street":"Tapscott St",
    "iso:country":"AU",
    "sg:address":"45 Tapscott St",
    "sg:city":"Maryborough",
    "sg:classifiers":[
        {
            "category":"Building & Trades",
            "subcategory":"Construction",
            "type":"Services"
        }
    ],
    "sg:phone":"+61 7 4121 4918",
    "sg:postcode":"4650",
    "sg:province":"QLD",
    "sg:tags":[
        "concrete",
        "contractor"
    ],
    "wof:name":"Daniel Kennedy Concreting",
    "wof:placetype":"venue"
},
  "geometry": {"coordinates":[152.67993200000001,-25.546417],"type":"Point"}
}