{
  "type": "Feature",
  "properties": {
    "addr:full":"234 Clovelly Rd Clovelly NSW 2031",
    "addr:housenumber":"234",
    "addr:postcode":"2031",
    "addr:street":"Clovelly Rd",
    "iso:country":"AU",
    "sg:address":"234 Clovelly Rd",
    "sg:city":"Clovelly",
    "sg:classifiers":[
        {
            "category":"Health Services",
            "subcategory":"Health Practitioner",
            "type":"Services"
        }
    ],
    "sg:phone":"+61 2 9665 3999",
    "sg:postcode":"2031",
    "sg:province":"NSW",
    "sg:tags":[
        "physiotherapist"
    ],
    "wof:name":"Blows Brett",
    "wof:placetype":"venue"
},
  "geometry": {"coordinates":[151.25592040999999,-33.9118614197],"type":"Point"}
}