{
  "type": "Feature",
  "properties": {
    "iso:country":"AU",
    "sg:address":"7 Elliot Pl St",
    "sg:city":"Helens Park",
    "sg:classifiers":[
        {
            "category":"Building & Trades",
            "subcategory":"Plumbing",
            "type":"Services"
        }
    ],
    "sg:phone":"+61 2 4621 2546",
    "sg:postcode":"2560",
    "sg:province":"NSW",
    "sg:tags":[
        "plumber",
        "gasfitters"
    ],
    "wof:name":"Anything Plumbing",
    "wof:placetype":"venue"
},
  "geometry": {"coordinates":[150.80206298799999,-34.1140670776],"type":"Point"}
}