{
  "type": "Feature",
  "properties": {
    "addr:full":"1 Phillips St Cloncurry QLD 4824",
    "addr:housenumber":"1",
    "addr:postcode":"4824",
    "addr:street":"Phillips St",
    "iso:country":"AU",
    "sg:address":"1 Phillips St",
    "sg:city":"Cloncurry",
    "sg:classifiers":[
        {
            "category":"Building & Trades",
            "subcategory":"Plumbing",
            "type":"Services"
        }
    ],
    "sg:phone":"+61 7 4742 2696",
    "sg:postcode":"4824",
    "sg:province":"QLD",
    "sg:tags":[
        "plumber",
        "gasfitters"
    ],
    "wof:name":"Dane Swalling Plumbing",
    "wof:placetype":"venue"
},
  "geometry": {"coordinates":[140.51217700000001,-20.707001],"type":"Point"}
}