{
  "type": "Feature",
  "properties": {
    "iso:country":"AU",
    "sg:address":"Marraboor St",
    "sg:city":"Lake Boga",
    "sg:classifiers":[
        {
            "category":"Travel",
            "subcategory":"Hotels & Motels",
            "type":"Entertainment"
        }
    ],
    "sg:phone":"+61 3 5037 2140",
    "sg:postcode":"3584",
    "sg:province":"VIC",
    "sg:tags":[
        "accommodation"
    ],
    "wof:name":"Commercial Hotel",
    "wof:placetype":"venue"
},
  "geometry": {"coordinates":[143.630814,-35.460537],"type":"Point"}
}