{
  "type": "Feature",
  "properties": {
    "addr:full":"33 Griffen St Hamlyn Heights VIC 3215",
    "addr:housenumber":"33",
    "addr:postcode":"3215",
    "addr:street":"Griffen St",
    "iso:country":"AU",
    "sg:address":"33 Griffen St",
    "sg:city":"Hamlyn Heights",
    "sg:classifiers":[
        {
            "category":"Education",
            "subcategory":"Kindergarten",
            "type":"Public Place"
        }
    ],
    "sg:phone":"+61 3 5278 4875",
    "sg:postcode":"3215",
    "sg:province":"VIC",
    "sg:tags":[
        "pre-schools"
    ],
    "wof:name":"William Parker Memorial Kindergarten",
    "wof:placetype":"venue"
},
  "geometry": {"coordinates":[144.32685852,-38.1219482422],"type":"Point"}
}