{
  "type": "Feature",
  "properties": {
    "addr:full":"Shop 5 , Borrick Sq Altona North VIC 3025",
    "addr:housenumber":"shop 5",
    "addr:postcode":"3025",
    "addr:street":"Borrick Sq",
    "iso:country":"AU",
    "sg:address":"Shop 5",
    "sg:city":", Borrick Sq Altona North",
    "sg:classifiers":[
        {
            "category":"Personal",
            "subcategory":"Beauty Salon",
            "type":"Services"
        }
    ],
    "sg:phone":"+61 3 9399 3933",
    "sg:postcode":"3025",
    "sg:province":"VIC",
    "sg:tags":[
        "hairdresser"
    ],
    "wof:name":"Dare Hair & Beauty",
    "wof:placetype":"venue"
},
  "geometry": {"coordinates":[144.84596300000001,-37.835434],"type":"Point"}
}