{
  "type": "Feature",
  "properties": {
    "addr:full":"Cnr Cotton & Ferry Sts Nerang QLD 4211",
    "addr:postcode":"4211",
    "iso:country":"AU",
    "sg:address":"Cnr Cotton & Ferry Sts",
    "sg:city":"Nerang",
    "sg:classifiers":[
        {
            "category":"Retail",
            "subcategory":"Self-service Laundry",
            "type":"Services"
        }
    ],
    "sg:phone":"+61 7 5596 0224",
    "sg:postcode":"4211",
    "sg:province":"QLD",
    "wof:name":"Nerang One Stop Laundrette",
    "wof:placetype":"venue"
},
  "geometry": {"coordinates":[153.33505249000001,-27.9893112183],"type":"Point"}
}