{
  "type": "Feature",
  "properties": {
    "addr:full":"19 Pascoe St Pascoe Vale VIC 3044",
    "addr:housenumber":"19",
    "addr:postcode":"3044",
    "addr:street":"Pascoe St",
    "iso:country":"AU",
    "sg:address":"19 Pascoe St",
    "sg:city":"Pascoe Vale",
    "sg:classifiers":[
        {
            "category":"Food & Beverages",
            "subcategory":"Liquor & Beverages",
            "type":"Retail Goods"
        }
    ],
    "sg:phone":"+61 3 9306 9165",
    "sg:postcode":"3044",
    "sg:province":"VIC",
    "sg:tags":[
        "store"
    ],
    "wof:name":"Pascoe Liquor Merchants",
    "wof:placetype":"venue"
},
  "geometry": {"coordinates":[144.93504333499999,-37.7165031433],"type":"Point"}
}