{
  "type": "Feature",
  "properties": {
    "iso:country":"AU",
    "sg:address":"216 Darling St",
    "sg:city":"Balmain",
    "sg:classifiers":[
        {
            "category":"Professional",
            "subcategory":"Art Services",
            "type":"Services"
        }
    ],
    "sg:phone":"+61 2 9555 1392",
    "sg:postcode":"2041",
    "sg:province":"NSW",
    "sg:tags":[
        "picture",
        "frame",
        "framing"
    ],
    "sg:website":"http://www.thatframingplace.com.au",
    "wof:name":"That Framing Place",
    "wof:placetype":"venue"
},
  "geometry": {"coordinates":[151.183685,-33.858067],"type":"Point"}
}