{
  "type": "Feature",
  "properties": {
    "addr:full":"Jay St Bohle QLD 4818",
    "addr:postcode":"4818",
    "addr:street":"Jay St",
    "iso:country":"AU",
    "sg:address":"Jay St",
    "sg:city":"Bohle",
    "sg:classifiers":[
        {
            "category":"Professional",
            "subcategory":"Engineering",
            "type":"Services"
        }
    ],
    "sg:phone":"+61 13 62 11",
    "sg:postcode":"4818",
    "sg:province":"QLD",
    "sg:tags":[
        "building",
        "prefabricated",
        "transportable",
        "industrial",
        "commercial"
    ],
    "wof:name":"Ausco Building Systems",
    "wof:placetype":"venue"
},
  "geometry": {"coordinates":[146.71154799999999,-19.262779],"type":"Point"}
}