{
  "type": "Feature",
  "properties": {
    "addr:full":"1 A Margaret St Mt Gambier SA 5290",
    "addr:housenumber":"1 a",
    "addr:postcode":"5290",
    "addr:street":"Margaret St",
    "iso:country":"AU",
    "sg:address":"1 A Margaret St",
    "sg:city":"Mt Gambier",
    "sg:classifiers":[
        {
            "category":"Shopping",
            "subcategory":"Computers & Home Electronics",
            "type":"Retail Goods"
        }
    ],
    "sg:phone":"+61 8 8725 6000",
    "sg:postcode":"5290",
    "sg:province":"SA",
    "sg:tags":[
        "hi-fi",
        "equipment"
    ],
    "wof:name":"Aslin Hi-Fi Pty Ltd",
    "wof:placetype":"venue"
},
  "geometry": {"coordinates":[140.782715,-37.80975],"type":"Point"}
}