{
  "type": "Feature",
  "properties": {
    "iso:country":"AU",
    "sg:address":"3 Ourimbah Rd",
    "sg:city":"Tweed Heads West",
    "sg:classifiers":[
        {
            "category":"Fast Food",
            "type":"Food & Drink"
        }
    ],
    "sg:phone":"+61 7 5536 1827",
    "sg:postcode":"2485",
    "sg:province":"NSW",
    "sg:tags":[
        "away",
        "take"
    ],
    "wof:name":"Tasty Treats Snack Bar",
    "wof:placetype":"venue"
},
  "geometry": {"coordinates":[153.52879333499999,-28.1767311096],"type":"Point"}
}