{
  "type": "Feature",
  "properties": {
    "addr:full":"22 Mulberry St Loftus NSW 2232",
    "addr:housenumber":"22",
    "addr:postcode":"2232",
    "addr:street":"Mulberry St",
    "iso:country":"AU",
    "sg:address":"22 Mulberry St",
    "sg:city":"Loftus",
    "sg:classifiers":[
        {
            "category":"Building & Trades",
            "subcategory":"Construction",
            "type":"Services"
        }
    ],
    "sg:phone":"+61 2 9521 5742",
    "sg:postcode":"2232",
    "sg:province":"NSW",
    "sg:tags":[
        "welding"
    ],
    "wof:name":"C-G Fabrications",
    "wof:placetype":"venue"
},
  "geometry": {"coordinates":[151.04080200199999,-34.0491638184],"type":"Point"}
}