{
  "type": "Feature",
  "properties": {
    "addr:full":"300 Elizabeth St Sydney NSW 2000",
    "addr:housenumber":"300",
    "addr:postcode":"2000",
    "addr:street":"Elizabeth St",
    "iso:country":"AU",
    "sg:address":"300 Elizabeth St",
    "sg:city":"Sydney",
    "sg:classifiers":[
        {
            "category":"Animal Shelter",
            "type":"Public Place"
        }
    ],
    "sg:phone":"+61 2 9296 1555",
    "sg:postcode":"2000",
    "sg:province":"NSW",
    "sg:tags":[
        "consultant",
        "meteorological"
    ],
    "wof:name":"Bureau Of Meteorology",
    "wof:placetype":"venue"
},
  "geometry": {"coordinates":[151.20854187,-33.8831214905],"type":"Point"}
}