{
  "type": "Feature",
  "properties": {
    "addr:full":"12 Rushall St Fairfield VIC 3078",
    "addr:housenumber":"12",
    "addr:postcode":"3078",
    "addr:street":"Rushall St",
    "iso:country":"AU",
    "sg:address":"12 Rushall St",
    "sg:city":"Fairfield",
    "sg:classifiers":[
        {
            "category":"Building & Trades",
            "subcategory":"Landscaping Services",
            "type":"Services"
        }
    ],
    "sg:phone":"+61 3 9481 6557",
    "sg:postcode":"3078",
    "sg:province":"VIC",
    "sg:tags":[
        "gardener"
    ],
    "wof:name":"Valenzisi A C",
    "wof:placetype":"venue"
},
  "geometry": {"coordinates":[145.023162842,-37.7763519287],"type":"Point"}
}