{
  "type": "Feature",
  "properties": {
    "addr:full":"Cnr West Lakes Blvd & Brebner Dr West Lakes SA 5021",
    "addr:postcode":"5021",
    "addr:street":"Cnr West Lakes Blvd & Brebner Dr",
    "iso:country":"AU",
    "sg:address":"Cnr West Lakes Blvd & Brebner Dr",
    "sg:city":"West Lakes",
    "sg:classifiers":[
        {
            "category":"Communications",
            "subcategory":"Film & Video Production",
            "type":"Services"
        }
    ],
    "sg:phone":"+61 8 8355 5111",
    "sg:postcode":"5021",
    "sg:province":"SA",
    "sg:tags":[
        "dvd",
        "library"
    ],
    "wof:name":"Video Ezy",
    "wof:placetype":"venue"
},
  "geometry": {"coordinates":[138.491744995,-34.8766365051],"type":"Point"}
}