{
  "type": "Feature",
  "properties": {
    "addr:full":"68 Dore St Katanning WA 6317",
    "addr:housenumber":"68",
    "addr:postcode":"6317",
    "addr:street":"Dore St",
    "iso:country":"AU",
    "sg:address":"68 Dore St",
    "sg:city":"Katanning",
    "sg:classifiers":[
        {
            "category":"Professional",
            "subcategory":"Engineering",
            "type":"Services"
        }
    ],
    "sg:phone":"+61 8 9821 5005",
    "sg:postcode":"6317",
    "sg:province":"WA",
    "sg:tags":[
        "engineer"
    ],
    "wof:name":"Barry Marris Engineering",
    "wof:placetype":"venue"
},
  "geometry": {"coordinates":[117.562423706,-33.6957893372],"type":"Point"}
}