{
  "type": "Feature",
  "properties": {
    "addr:full":"13 Mortimer St Drysdale VIC 3222",
    "addr:housenumber":"13",
    "addr:postcode":"3222",
    "addr:street":"Mortimer St",
    "iso:country":"AU",
    "sg:address":"13 Mortimer St",
    "sg:city":"Drysdale",
    "sg:classifiers":[
        {
            "category":"Real Estate",
            "subcategory":"Real Estate Agent",
            "type":"Services"
        }
    ],
    "sg:phone":"+61 3 5251 3854",
    "sg:postcode":"3222",
    "sg:province":"VIC",
    "sg:tags":[
        "handyman's",
        "equipment",
        "hire",
        "builders",
        "contractor"
    ],
    "wof:name":"Penn Hire Services",
    "wof:placetype":"venue"
},
  "geometry": {"coordinates":[144.57543899999999,-38.174393],"type":"Point"}
}