{
  "type": "Feature",
  "properties": {
    "addr:full":"63 West New St Balgowlah Heights NSW 2093",
    "addr:housenumber":"63",
    "addr:postcode":"2093",
    "addr:street":"West New St",
    "iso:country":"AU",
    "sg:address":"63 West New St",
    "sg:city":"Balgowlah Heights",
    "sg:classifiers":[
        {
            "category":"Personal",
            "subcategory":"Beauty Salon",
            "type":"Services"
        }
    ],
    "sg:phone":"+61 2 9907 6555",
    "sg:postcode":"2093",
    "sg:province":"NSW",
    "wof:name":"La Diva Beauty Studio",
    "wof:placetype":"venue"
},
  "geometry": {"coordinates":[151.257156372,-33.8006286621],"type":"Point"}
}