{
  "type": "Feature",
  "properties": {
    "addr:full":"11 O'Briens Hill Rd O'Connell NSW 2795",
    "addr:housenumber":"11",
    "addr:postcode":"2795",
    "addr:street":"O'Briens Hill Rd",
    "iso:country":"AU",
    "sg:address":"11 O'Briens Hill Rd",
    "sg:city":"O'Connell",
    "sg:phone":"+61 2 6337 5041",
    "sg:postcode":"2795",
    "sg:province":"NSW",
    "wof:name":"Panorama Mobile Windscreens",
    "wof:placetype":"venue"
},
  "geometry": {"coordinates":[149.55354309099999,-33.5437316895],"type":"Point"}
}