{
  "type": "Feature",
  "properties": {
    "addr:full":"23 Mountain View Drv Lismore NSW 2480",
    "addr:housenumber":"23",
    "addr:postcode":"2480",
    "addr:street":"Mountain View Drv",
    "iso:country":"AU",
    "sg:address":"23 Mountain View Drv",
    "sg:city":"Lismore",
    "sg:classifiers":[
        {
            "category":"Communications",
            "type":"Services"
        }
    ],
    "sg:phone":"+61 2 6624 5202",
    "sg:postcode":"2480",
    "sg:province":"NSW",
    "sg:tags":[
        "equipment",
        "satellite"
    ],
    "wof:name":"Visionclear Antenna Services",
    "wof:placetype":"venue"
},
  "geometry": {"coordinates":[153.30848693900001,-28.8109588623],"type":"Point"}
}