{
  "type": "Feature",
  "properties": {
    "iso:country":"AU",
    "sg:address":"31 Park Rd",
    "sg:city":"Marrickville",
    "sg:classifiers":[
        {
            "category":"Education",
            "subcategory":"School",
            "type":"Public Place"
        }
    ],
    "sg:phone":"+61 2 9560 3309",
    "sg:postcode":"2204",
    "sg:province":"NSW",
    "sg:tags":[
        "state",
        "-",
        "nsw"
    ],
    "wof:name":"Wilkins Public School",
    "wof:placetype":"venue"
},
  "geometry": {"coordinates":[151.156723,-33.901192],"type":"Point"}
}