{
  "type": "Feature",
  "properties": {
    "addr:full":"105 Drummond St Carlton South VIC 3053",
    "addr:housenumber":"105",
    "addr:postcode":"3053",
    "addr:street":"Drummond St",
    "iso:country":"AU",
    "sg:address":"105 Drummond St",
    "sg:city":"Carlton South",
    "sg:classifiers":[
        {
            "category":"Health Services",
            "subcategory":"Doctor",
            "type":"Services"
        }
    ],
    "sg:phone":"+61 3 9639 2467",
    "sg:postcode":"3053",
    "sg:province":"VIC",
    "sg:tags":[
        "medical",
        "practitioner"
    ],
    "wof:name":"Miller Russell K",
    "wof:placetype":"venue"
},
  "geometry": {"coordinates":[144.967651367,-37.8042488098],"type":"Point"}
}