{
  "type": "Feature",
  "properties": {
    "iso:country":"AU",
    "sg:address":"21 Burton Rd",
    "sg:city":"Mt Hutton",
    "sg:classifiers":[
        {
            "category":"Farming",
            "subcategory":"Nursery",
            "type":"Manufacturing & Wholesale Goods"
        }
    ],
    "sg:phone":"+61 2 4948 6288",
    "sg:postcode":"2290",
    "sg:province":"NSW",
    "wof:name":"Greensale Nursery",
    "wof:placetype":"venue"
},
  "geometry": {"coordinates":[151.65931701700001,-32.9862823486],"type":"Point"}
}