{
  "type": "Feature",
  "properties": {
    "addr:full":"23 Miles St Mt Isa QLD 4825",
    "addr:housenumber":"23",
    "addr:postcode":"4825",
    "addr:street":"Miles St",
    "iso:country":"AU",
    "sg:address":"23 Miles St",
    "sg:city":"Mt Isa",
    "sg:classifiers":[
        {
            "category":"Banks & Credit Unions",
            "subcategory":"Financial Services",
            "type":"Services"
        }
    ],
    "sg:phone":"+61 7 4743 5033",
    "sg:postcode":"4825",
    "sg:province":"QLD",
    "sg:tags":[
        "loan",
        "finance",
        "mortgage"
    ],
    "wof:name":"C B F C Ltd",
    "wof:placetype":"venue"
},
  "geometry": {"coordinates":[139.491622925,-20.7255744934],"type":"Point"}
}