{
  "type": "Feature",
  "properties": {
    "addr:full":"Old Hume Hwy Gundagai NSW 2722",
    "addr:postcode":"2722",
    "addr:street":"Hume Hwy",
    "iso:country":"AU",
    "sg:address":"Old Hume Hwy",
    "sg:city":"Gundagai",
    "sg:classifiers":[
        {
            "category":"Health Services",
            "subcategory":"Dentist",
            "type":"Services"
        }
    ],
    "sg:phone":"+61 2 6944 1650",
    "sg:postcode":"2722",
    "sg:province":"NSW",
    "wof:name":"McDonald R M",
    "wof:placetype":"venue"
},
  "geometry": {"coordinates":[148.10122699999999,-35.06179],"type":"Point"}
}