{
  "type": "Feature",
  "properties": {
    "iso:country":"AU",
    "sg:address":"30 Henry St",
    "sg:city":"Windsor",
    "sg:classifiers":[
        {
            "category":"Professional",
            "subcategory":"Art Services",
            "type":"Services"
        }
    ],
    "sg:phone":"+61 3 9525 0936",
    "sg:postcode":"3181",
    "sg:province":"VIC",
    "sg:tags":[
        "commercial",
        "artist"
    ],
    "wof:name":"Bettina Guthridge Illustration",
    "wof:placetype":"venue"
},
  "geometry": {"coordinates":[144.98524475100001,-37.8544540405],"type":"Point"}
}