{
  "type": "Feature",
  "properties": {
    "iso:country":"AU",
    "sg:address":"Cnr Captain Cook Hwy & Bokissa Rd",
    "sg:city":"Palm Cove",
    "sg:classifiers":[
        {
            "category":"Real Estate",
            "subcategory":"Real Estate Agent",
            "type":"Services"
        }
    ],
    "sg:phone":"+61 7 4059 0111",
    "sg:postcode":"4879",
    "sg:province":"QLD",
    "wof:name":"Northern Exposure Realty",
    "wof:placetype":"venue"
},
  "geometry": {"coordinates":[145.66390991200001,-16.7427902222],"type":"Point"}
}