{
  "type": "Feature",
  "properties": {
    "addr:full":"105 Westfield Shopngtwn East St Pagewood NSW 2035",
    "addr:housenumber":"105",
    "addr:postcode":"2035",
    "addr:street":"Westfield Shopngtwn East St",
    "iso:country":"AU",
    "sg:address":"105 Westfield Shopngtwn East St",
    "sg:city":"Pagewood",
    "sg:classifiers":[
        {
            "category":"Personal",
            "subcategory":"Shoe Repair & Shine",
            "type":"Services"
        }
    ],
    "sg:phone":"+61 2 9349 3189",
    "sg:postcode":"2035",
    "sg:province":"NSW",
    "sg:tags":[
        "footwear"
    ],
    "wof:name":"Mister Minit Aust Pty Ltd",
    "wof:placetype":"venue"
},
  "geometry": {"coordinates":[151.22450256400001,-33.9438209534],"type":"Point"}
}