{
  "type": "Feature",
  "properties": {
    "addr:full":"188 .Glen Osmond Rd Fullarton SA 5063",
    "addr:housenumber":"188",
    "addr:postcode":"5063",
    "addr:street":"Glen Osmond Rd",
    "iso:country":"AU",
    "sg:address":"188 .Glen Osmond Rd",
    "sg:city":"Fullarton",
    "sg:classifiers":[
        {
            "category":"Professional",
            "subcategory":"Business Services",
            "type":"Services"
        }
    ],
    "sg:phone":"+61 8 8338 1177",
    "sg:postcode":"5063",
    "sg:province":"SA",
    "sg:tags":[
        "management",
        "event"
    ],
    "wof:name":"Southgate Event & Display Management",
    "wof:placetype":"venue"
},
  "geometry": {"coordinates":[138.6277771,-34.9479827881],"type":"Point"}
}