{
  "type": "Feature",
  "properties": {
    "addr:full":"Unit 30 17- 37 Lorraine St Peakhurst NSW 2210",
    "addr:housenumber":"17 37",
    "addr:postcode":"2210",
    "addr:street":"Lorraine St",
    "iso:country":"AU",
    "sg:address":"Unit 30 17- 37 Lorraine St",
    "sg:city":"Peakhurst",
    "sg:classifiers":[
        {
            "category":"Shopping",
            "subcategory":"Computers & Home Electronics",
            "type":"Retail Goods"
        }
    ],
    "sg:phone":"+61 2 9533 2300",
    "sg:postcode":"2210",
    "sg:province":"NSW",
    "sg:tags":[
        "wholesaler",
        "equipment",
        "electronic",
        "mfrs"
    ],
    "wof:name":"O.E.M. Electronics Pty Ltd",
    "wof:placetype":"venue"
},
  "geometry": {"coordinates":[151.06042500000001,-33.966297],"type":"Point"}
}