{
  "type": "Feature",
  "properties": {
    "addr:full":"190 MacQuarie St Windsor NSW 2756",
    "addr:housenumber":"190",
    "addr:postcode":"2756",
    "addr:street":"Macquarie St",
    "iso:country":"AU",
    "sg:address":"190 MacQuarie St",
    "sg:city":"Windsor",
    "sg:classifiers":[
        {
            "category":"Organizations",
            "subcategory":"Community Association",
            "type":"Services"
        }
    ],
    "sg:phone":"+61 2 4587 8091",
    "sg:postcode":"2756",
    "sg:province":"NSW",
    "sg:tags":[
        "organisation",
        "family",
        "welfare"
    ],
    "wof:name":"Hawkesbury Care Inc",
    "wof:placetype":"venue"
},
  "geometry": {"coordinates":[150.81300354000001,-33.6143951416],"type":"Point"}
}