{
  "type": "Feature",
  "properties": {
    "addr:full":"79 Osbourne Ave Umina NSW 2257",
    "addr:housenumber":"79",
    "addr:postcode":"2257",
    "addr:street":"Osbourne Ave",
    "iso:country":"AU",
    "sg:address":"79 Osbourne Ave",
    "sg:city":"Umina",
    "sg:classifiers":[
        {
            "category":"Manufacturing",
            "subcategory":"Apparel",
            "type":"Manufacturing & Wholesale Goods"
        }
    ],
    "sg:phone":"+61 2 4344 6228",
    "sg:postcode":"2257",
    "sg:province":"NSW",
    "sg:tags":[
        "wholesaler",
        "mfrs",
        "footwear"
    ],
    "wof:name":"Sole Sisters Fashion Footwear",
    "wof:placetype":"venue"
},
  "geometry": {"coordinates":[151.36076355,-33.5181312561],"type":"Point"}
}