{
  "type": "Feature",
  "properties": {
    "addr:full":"43- 47 Nepean Hwy Brighton VIC 3186",
    "addr:housenumber":"47",
    "addr:postcode":"3186",
    "addr:street":"Nepean Hwy",
    "iso:country":"AU",
    "sg:address":"43- 47 Nepean Hwy",
    "sg:city":"Brighton",
    "sg:classifiers":[
        {
            "category":"Retail",
            "subcategory":"Car Wash",
            "type":"Services"
        }
    ],
    "sg:phone":"+61 3 9523 9443",
    "sg:postcode":"3186",
    "sg:province":"VIC",
    "sg:tags":[
        "truck",
        "cleaning"
    ],
    "wof:name":"Clearwater Carwash Brighton",
    "wof:placetype":"venue"
},
  "geometry": {"coordinates":[145.001495361,-37.8888893127],"type":"Point"}
}