{
  "type": "Feature",
  "properties": {
    "iso:country":"AU",
    "sg:address":"Suite 7, Level 5, Manly National Building, 22 Central Ave",
    "sg:city":"Manly",
    "sg:classifiers":[
        {
            "category":"Education",
            "subcategory":"Special Training",
            "type":"Public Place"
        }
    ],
    "sg:phone":"+61 414 766 469",
    "sg:postcode":"2095",
    "sg:province":"NSW",
    "sg:tags":[
        "development"
    ],
    "wof:name":"LifeStyles Life Coaching",
    "wof:placetype":"venue"
},
  "geometry": {"coordinates":[151.28666687,-33.7968025208],"type":"Point"}
}