{
  "type": "Feature",
  "properties": {
    "addr:full":"43- 45 Stokes St Lane Cove NSW 2066",
    "addr:housenumber":"45",
    "addr:postcode":"2066",
    "addr:street":"Stokes St",
    "iso:country":"AU",
    "sg:address":"43- 45 Stokes St",
    "sg:city":"Lane Cove",
    "sg:classifiers":[
        {
            "category":"Health Services",
            "subcategory":"Health Practitioner",
            "type":"Services"
        }
    ],
    "sg:phone":"+61 2 9419 8070",
    "sg:postcode":"2066",
    "sg:province":"NSW",
    "sg:tags":[
        "hypnotherapy"
    ],
    "wof:name":"Tayler Lyn S",
    "wof:placetype":"venue"
},
  "geometry": {"coordinates":[151.17590332,-33.8081207275],"type":"Point"}
}