{
  "type": "Feature",
  "properties": {
    "iso:country":"AU",
    "sg:address":"14a Milsom St",
    "sg:city":"Coorparoo",
    "sg:classifiers":[
        {
            "category":"Education",
            "subcategory":"Music School",
            "type":"Public Place"
        }
    ],
    "sg:phone":"+61 7 3847 1744",
    "sg:postcode":"4151",
    "sg:province":"QLD",
    "sg:tags":[
        "television",
        "radio"
    ],
    "wof:name":"Lightsounds.",
    "wof:placetype":"venue"
},
  "geometry": {"coordinates":[153.05563354500001,-27.4876861572],"type":"Point"}
}