{
  "type": "Feature",
  "properties": {
    "addr:full":"Ste1/ 6 Hassal St Parramatta NSW 2123",
    "addr:postcode":"2123",
    "addr:street":"Hassal St",
    "iso:country":"AU",
    "sg:address":"Ste1/ 6 Hassal St",
    "sg:city":"Parramatta",
    "sg:classifiers":[
        {
            "category":"Travel",
            "subcategory":"Travel Agent",
            "type":"Entertainment"
        }
    ],
    "sg:phone":"+61 1300 551 603",
    "sg:postcode":"2123",
    "sg:province":"NSW",
    "sg:tags":[
        "consultant"
    ],
    "wof:name":"Surya Travels",
    "wof:placetype":"venue"
},
  "geometry": {"coordinates":[150.98887634299999,-33.8095016479],"type":"Point"}
}