{
  "type": "Feature",
  "properties": {
    "iso:country":"AU",
    "sg:address":"2433 Logan Rd",
    "sg:city":"Eight Mile Plains",
    "sg:classifiers":[
        {
            "category":"Autos & Motor Vehicles",
            "subcategory":"Auto Supplies",
            "type":"Retail Goods"
        }
    ],
    "sg:phone":"+61 7 3341 6622",
    "sg:postcode":"4113",
    "sg:province":"QLD",
    "sg:tags":[
        "camper-trailers",
        "caravan",
        "equipment"
    ],
    "wof:name":"Caravan County",
    "wof:placetype":"venue"
},
  "geometry": {"coordinates":[153.09085082999999,-27.573343277],"type":"Point"}
}