{
  "type": "Feature",
  "properties": {
    "iso:country":"AU",
    "sg:address":"6 Wright St",
    "sg:city":"Glenbrook",
    "sg:classifiers":[
        {
            "category":"Building & Trades",
            "subcategory":"Plumbing",
            "type":"Services"
        }
    ],
    "sg:phone":"+61 2 4739 5147",
    "sg:postcode":"2773",
    "sg:province":"NSW",
    "sg:tags":[
        "plumber",
        "gasfitters"
    ],
    "wof:name":"Drew Jonathan Plumbing Services",
    "wof:placetype":"venue"
},
  "geometry": {"coordinates":[150.618865967,-33.7695198059],"type":"Point"}
}