{
  "type": "Feature",
  "properties": {
    "addr:full":"Unit 4 35 Alexandra Ave South Yarra VIC 3141",
    "addr:housenumber":"35",
    "addr:postcode":"3141",
    "addr:street":"Alexandra Ave",
    "iso:country":"AU",
    "sg:address":"Unit 4 35 Alexandra Ave",
    "sg:city":"South Yarra",
    "sg:classifiers":[
        {
            "category":"Professional",
            "subcategory":"Computer Services",
            "type":"Services"
        }
    ],
    "sg:phone":"+61 3 9820 4333",
    "sg:postcode":"3141",
    "sg:province":"VIC",
    "sg:tags":[
        "consultant",
        "system"
    ],
    "wof:name":"Greg Hubbard Consulting",
    "wof:placetype":"venue"
},
  "geometry": {"coordinates":[144.986984253,-37.82995224],"type":"Point"}
}