{
  "type": "Feature",
  "properties": {
    "addr:full":"Cnr Picnic Pde & Ocean View Rd Ettalong NSW 2257",
    "addr:postcode":"2257",
    "addr:street":"Picnic;View Rd",
    "iso:country":"AU",
    "sg:address":"Cnr Picnic Pde & Ocean View Rd",
    "sg:city":"Ettalong",
    "sg:classifiers":[
        {
            "category":"Health Services",
            "subcategory":"Dentist",
            "type":"Services"
        }
    ],
    "sg:phone":"+61 2 4341 9722",
    "sg:postcode":"2257",
    "sg:province":"NSW",
    "wof:name":"Aulsebrook T.W., Or S., Mo A. & King A D.",
    "wof:placetype":"venue"
},
  "geometry": {"coordinates":[151.33691406200001,-33.5145149231],"type":"Point"}
}