{
  "type": "Feature",
  "properties": {
    "iso:country":"AU",
    "sg:address":"29 Anderson St",
    "sg:city":"Fortitude Valley",
    "sg:classifiers":[
        {
            "category":"Autos & Motor Vehicles",
            "subcategory":"Auto Supplies",
            "type":"Retail Goods"
        }
    ],
    "sg:phone":"+61 7 3252 2299",
    "sg:postcode":"4006",
    "sg:province":"QLD",
    "sg:tags":[
        "accessory"
    ],
    "wof:name":"Auto Fleece Seat Covers",
    "wof:placetype":"venue"
},
  "geometry": {"coordinates":[153.031692505,-27.4527816772],"type":"Point"}
}