{
  "type": "Feature",
  "properties": {
    "iso:country":"AU",
    "sg:address":"PO Box 36726",
    "sg:city":"Winnellie",
    "sg:classifiers":[
        {
            "category":"Organizations",
            "subcategory":"Professional Association",
            "type":"Services"
        }
    ],
    "sg:phone":"+61 437 853 629",
    "sg:postcode":"0906",
    "sg:province":"NT",
    "sg:tags":[
        "web",
        "internet"
    ],
    "wof:name":"Kool Katz Productions",
    "wof:placetype":"venue"
},
  "geometry": {"coordinates":[130.879913,-12.426623],"type":"Point"}
}