{
  "type": "Feature",
  "properties": {
    "iso:country":"AU",
    "sg:address":"14 Kareela Rd",
    "sg:city":"Chatswood",
    "sg:classifiers":[
        {
            "category":"Real Estate",
            "subcategory":"Real Estate Agent",
            "type":"Services"
        }
    ],
    "sg:phone":"+61 2 9890 7011",
    "sg:postcode":"2057",
    "sg:province":"NSW",
    "wof:name":"Greater West Realty",
    "wof:placetype":"venue"
},
  "geometry": {"coordinates":[151.170563,-33.793358],"type":"Point"}
}