{
  "type": "Feature",
  "properties": {
    "iso:country":"AU",
    "sg:address":"5 Junction St",
    "sg:city":"Auburn",
    "sg:classifiers":[
        {
            "category":"Professional",
            "subcategory":"Testing Lab",
            "type":"Services"
        }
    ],
    "sg:phone":"+61 2 9737 9686",
    "sg:postcode":"2144",
    "sg:province":"NSW",
    "sg:tags":[
        "inspection"
    ],
    "wof:name":"ARL Laboratory Services Pty Ltd",
    "wof:placetype":"venue"
},
  "geometry": {"coordinates":[151.03086852999999,-33.8358192444],"type":"Point"}
}