{
  "type": "Feature",
  "properties": {
    "addr:full":"198 Canleyvale Rd Canley Heights NSW 2166",
    "addr:housenumber":"198",
    "addr:postcode":"2166",
    "addr:street":"Canleyvale Rd",
    "iso:country":"AU",
    "sg:address":"198 Canleyvale Rd",
    "sg:city":"Canley Heights",
    "sg:classifiers":[
        {
            "category":"Real Estate",
            "subcategory":"Real Estate Agent",
            "type":"Services"
        }
    ],
    "sg:phone":"+61 2 9726 2155",
    "sg:postcode":"2166",
    "sg:province":"NSW",
    "wof:name":"New Century",
    "wof:placetype":"venue"
},
  "geometry": {"coordinates":[150.92666625999999,-33.8841247559],"type":"Point"}
}