{
  "type": "Feature",
  "properties": {
    "iso:country":"AU",
    "sg:address":"67- 69 Kiewa St",
    "sg:city":"Manildra",
    "sg:classifiers":[
        {
            "category":"Cafe",
            "type":"Food & Drink"
        }
    ],
    "sg:phone":"+61 2 6364 5494",
    "sg:postcode":"2865",
    "sg:province":"NSW",
    "wof:name":"Mama's Cafe",
    "wof:placetype":"venue"
},
  "geometry": {"coordinates":[148.69558699999999,-33.186653],"type":"Point"}
}