{
  "type": "Feature",
  "properties": {
    "iso:country":"AU",
    "sg:address":"8 Lyndhurst Crs",
    "sg:city":"Hunters Hill",
    "sg:classifiers":[
        {
            "category":"Professional",
            "subcategory":"Management & Consulting",
            "type":"Services"
        }
    ],
    "sg:phone":"+61 2 9879 6406",
    "sg:postcode":"2110",
    "sg:province":"NSW",
    "sg:tags":[
        "consultant"
    ],
    "wof:name":"Management Consortium",
    "wof:placetype":"venue"
},
  "geometry": {"coordinates":[151.151947022,-33.8359527588],"type":"Point"}
}