{
  "type": "Feature",
  "properties": {
    "addr:full":"Suite 3, 1 Campbell Crs Terrigal NSW 2260",
    "addr:housenumber":"1",
    "addr:postcode":"2260",
    "addr:street":"Campbell Crs",
    "iso:country":"AU",
    "sg:address":"Suite 3, 1 Campbell Crs",
    "sg:city":"Terrigal",
    "sg:classifiers":[
        {
            "category":"Professional",
            "subcategory":"Accounting & Tax Preparation",
            "type":"Services"
        }
    ],
    "sg:phone":"+61 2 4385 4263",
    "sg:postcode":"2260",
    "sg:province":"NSW",
    "sg:tags":[
        "consultant",
        "taxation"
    ],
    "wof:name":"SeaChange Taxation",
    "wof:placetype":"venue"
},
  "geometry": {"coordinates":[151.44570899999999,-33.4478],"type":"Point"}
}