{
  "type": "Feature",
  "properties": {
    "addr:full":"Depot 7 Cheney Place, Mitchell ACT 2911",
    "addr:housenumber":"7",
    "addr:postcode":"2911",
    "addr:street":"Depot;Cheney Place",
    "iso:country":"AU",
    "sg:address":"Depot 7 Cheney Place,",
    "sg:city":"Mitchell",
    "sg:classifiers":[
        {
            "category":"Real Estate",
            "subcategory":"Real Estate Operator",
            "type":"Services"
        }
    ],
    "sg:phone":"+61 2 6241 6461",
    "sg:postcode":"2911",
    "sg:province":"ACT",
    "sg:tags":[
        "concrete",
        "pumping"
    ],
    "wof:name":"Elvin Concrete Pumping",
    "wof:placetype":"venue"
},
  "geometry": {"coordinates":[149.14056396500001,-35.2123336792],"type":"Point"}
}