{
  "type": "Feature",
  "properties": {
    "addr:full":"Mail Svc 805 Mundubbera QLD 4626",
    "addr:housenumber":"805",
    "addr:postcode":"4626",
    "addr:street":"Mail Svc",
    "iso:country":"AU",
    "sg:address":"Mail Svc 805",
    "sg:city":"Mundubbera",
    "sg:classifiers":[
        {
            "category":"Farming",
            "subcategory":"Farm",
            "type":"Manufacturing & Wholesale Goods"
        }
    ],
    "sg:phone":"+61 7 4165 4262",
    "sg:postcode":"4626",
    "sg:province":"QLD",
    "sg:tags":[
        "farmer"
    ],
    "wof:name":"Beresford D T & P M",
    "wof:placetype":"venue"
},
  "geometry": {"coordinates":[151.31167600000001,-25.573799],"type":"Point"}
}