{
  "type": "Feature",
  "properties": {
    "iso:country":"AU",
    "sg:address":"Factory 3-81 Kularoo Drv",
    "sg:city":"Forster",
    "sg:classifiers":[
        {
            "category":"Building & Trades",
            "subcategory":"Equipment Rental",
            "type":"Services"
        }
    ],
    "sg:phone":"+61 2 6581 3213",
    "sg:postcode":"2428",
    "sg:province":"NSW",
    "sg:tags":[
        "supply",
        "catering"
    ],
    "wof:name":"Oxley Commercial Catering Equipment",
    "wof:placetype":"venue"
},
  "geometry": {"coordinates":[152.51516699999999,-32.194149],"type":"Point"}
}