{
  "type": "Feature",
  "properties": {
    "iso:country":"AU",
    "sg:address":"91 Fenden Rd",
    "sg:city":"Salisbury Plain",
    "sg:classifiers":[
        {
            "category":"Building & Trades",
            "subcategory":"Construction",
            "type":"Services"
        }
    ],
    "sg:phone":"+61 8 8250 9784",
    "sg:postcode":"5109",
    "sg:province":"SA",
    "sg:tags":[
        "earth",
        "excavating",
        "moving",
        "contractor"
    ],
    "wof:name":"Perrotta's Earthmoving",
    "wof:placetype":"venue"
},
  "geometry": {"coordinates":[138.65728759800001,-34.7625160217],"type":"Point"}
}