{
  "type": "Feature",
  "properties": {
    "addr:full":"374 Cormack Rd Wingfield SA 5013",
    "addr:housenumber":"374",
    "addr:postcode":"5013",
    "addr:street":"Cormack Rd",
    "iso:country":"AU",
    "sg:address":"374 Cormack Rd",
    "sg:city":"Wingfield",
    "sg:classifiers":[
        {
            "category":"Commercial Area",
            "type":"Public Place"
        }
    ],
    "sg:phone":"+61 8 8349 7366",
    "sg:postcode":"5013",
    "sg:province":"SA",
    "sg:tags":[
        "heavy",
        "carrier"
    ],
    "sg:website":"http://www.rapidhaulage.com.au",
    "wof:name":"Rapid Haulage",
    "wof:placetype":"venue"
},
  "geometry": {"coordinates":[138.57293701200001,-34.840007782],"type":"Point"}
}