{
  "type": "Feature",
  "properties": {
    "addr:full":"24 Schwebel St Marrickville NSW 2204",
    "addr:housenumber":"24",
    "addr:postcode":"2204",
    "addr:street":"Schwebel St",
    "iso:country":"AU",
    "sg:address":"24 Schwebel St",
    "sg:city":"Marrickville",
    "sg:classifiers":[
        {
            "category":"Professional",
            "subcategory":"Art Services",
            "type":"Services"
        }
    ],
    "sg:phone":"+61 415 894 848",
    "sg:postcode":"2204",
    "sg:province":"NSW",
    "sg:tags":[
        "decorator",
        "painter"
    ],
    "wof:name":"S&B Painting N Decorating",
    "wof:placetype":"venue"
},
  "geometry": {"coordinates":[151.15400700000001,-33.91534],"type":"Point"}
}