{
  "type": "Feature",
  "properties": {
    "iso:country":"AU",
    "sg:address":"39 Christmas St",
    "sg:city":"Northcote",
    "sg:classifiers":[
        {
            "category":"Building & Trades",
            "subcategory":"Construction",
            "type":"Services"
        }
    ],
    "sg:phone":"+61 411 524 402",
    "sg:postcode":"3070",
    "sg:province":"VIC",
    "sg:tags":[
        "earth",
        "excavating",
        "moving",
        "contractor"
    ],
    "wof:name":"Strathmore Excavators",
    "wof:placetype":"venue"
},
  "geometry": {"coordinates":[145.00895700000001,-37.766048],"type":"Point"}
}