{
  "type": "Feature",
  "properties": {
    "addr:full":"2nd Flr, 160 Castlereagh St Sydney NSW 2000",
    "addr:housenumber":"160",
    "addr:postcode":"2000",
    "addr:street":"Castlereagh St",
    "iso:country":"AU",
    "sg:address":"2nd Flr, 160 Castlereagh St",
    "sg:city":"Sydney",
    "sg:classifiers":[
        {
            "category":"Health Services",
            "subcategory":"Health Practitioner",
            "type":"Services"
        }
    ],
    "sg:phone":"+61 2 9518 9912",
    "sg:postcode":"2000",
    "sg:province":"NSW",
    "sg:tags":[
        "hypnotherapy"
    ],
    "wof:name":"Australian Hypnotherapists Association",
    "wof:placetype":"venue"
},
  "geometry": {"coordinates":[151.20945739699999,-33.8722724915],"type":"Point"}
}