{
  "type": "Feature",
  "properties": {
    "addr:full":"28 Second Ave Chelsea Heights VIC 3196",
    "addr:housenumber":"28",
    "addr:postcode":"3196",
    "addr:street":"Second Ave",
    "iso:country":"AU",
    "sg:address":"28 Second Ave",
    "sg:city":"Chelsea Heights",
    "sg:classifiers":[
        {
            "category":"Home & Garden",
            "subcategory":"Carpets & Floor Coverings",
            "type":"Retail Goods"
        }
    ],
    "sg:phone":"+61 425 755 143",
    "sg:postcode":"3196",
    "sg:province":"VIC",
    "sg:tags":[
        "wholesaler",
        "tie",
        "mfrs",
        "scarf"
    ],
    "wof:name":"Distino Of Melbourne",
    "wof:placetype":"venue"
},
  "geometry": {"coordinates":[145.132522583,-38.0442085266],"type":"Point"}
}