{
  "type": "Feature",
  "properties": {
    "addr:full":"106c Albany Hwy Kojonup WA 6395",
    "addr:housenumber":"106c",
    "addr:postcode":"6395",
    "addr:street":"Albany Hwy",
    "iso:country":"AU",
    "sg:address":"106c Albany Hwy",
    "sg:city":"Kojonup",
    "sg:classifiers":[
        {
            "category":"Food & Beverages",
            "subcategory":"Bakery",
            "type":"Retail Goods"
        }
    ],
    "sg:phone":"+61 8 9831 1097",
    "sg:postcode":"6395",
    "sg:province":"WA",
    "sg:tags":[
        "baker"
    ],
    "wof:name":"Kojonup Bakery",
    "wof:placetype":"venue"
},
  "geometry": {"coordinates":[117.15944671600001,-33.8362846375],"type":"Point"}
}