{
  "type": "Feature",
  "properties": {
    "addr:full":"Shop 3, 8585 Warrego Hwy Withcott QLD 4352",
    "addr:housenumber":"shop 3",
    "addr:postcode":"8585;4352",
    "addr:street":"Warrego Hwy",
    "iso:country":"AU",
    "sg:address":"Shop 3, 8585 Warrego Hwy",
    "sg:city":"Withcott",
    "sg:classifiers":[
        {
            "category":"Shopping",
            "subcategory":"Discount & Variety Stores",
            "type":"Retail Goods"
        }
    ],
    "sg:phone":"+61 7 4637 4314",
    "sg:postcode":"4352",
    "sg:province":"QLD",
    "sg:tags":[
        "shop",
        "adult"
    ],
    "wof:name":"Discount Adult Zone",
    "wof:placetype":"venue"
},
  "geometry": {"coordinates":[152.02441400000001,-27.553505],"type":"Point"}
}