{
  "type": "Feature",
  "properties": {
    "iso:country":"AU",
    "sg:address":"64 Luhrs Rd",
    "sg:city":"Payneham South",
    "sg:classifiers":[
        {
            "category":"Education",
            "subcategory":"Music School",
            "type":"Public Place"
        }
    ],
    "sg:phone":"+61 408 408 881",
    "sg:postcode":"5070",
    "sg:province":"SA",
    "sg:tags":[
        "teacher"
    ],
    "wof:name":"Trumpet Tutors",
    "wof:placetype":"venue"
},
  "geometry": {"coordinates":[138.64718627900001,-34.904712677],"type":"Point"}
}