{
  "type": "Feature",
  "properties": {
    "addr:full":"131 Leslie St Mandurah WA 6210",
    "addr:housenumber":"131",
    "addr:postcode":"6210",
    "addr:street":"Leslie St",
    "iso:country":"AU",
    "sg:address":"131 Leslie St",
    "sg:city":"Mandurah",
    "sg:classifiers":[
        {
            "category":"Recreation",
            "subcategory":"Boat Charter",
            "type":"Entertainment"
        }
    ],
    "sg:phone":"+61 8 9581 2383",
    "sg:postcode":"6210",
    "sg:province":"WA",
    "wof:name":"Paddle Steamer Decoy",
    "wof:placetype":"venue"
},
  "geometry": {"coordinates":[115.7304,-32.547405],"type":"Point"}
}