{
  "type": "Feature",
  "properties": {
    "addr:full":"654 Rocky Point Rd Sans Souci NSW 2219",
    "addr:housenumber":"654",
    "addr:postcode":"2219",
    "addr:street":"Rocky Point Rd",
    "iso:country":"AU",
    "sg:address":"654 Rocky Point Rd",
    "sg:city":"Sans Souci",
    "sg:classifiers":[
        {
            "category":"Building & Trades",
            "subcategory":"Equipment Rental",
            "type":"Services"
        }
    ],
    "sg:phone":"+61 419 748 202",
    "sg:postcode":"2219",
    "sg:province":"NSW",
    "sg:tags":[
        "party",
        "hire"
    ],
    "wof:name":"Elegant Hire",
    "wof:placetype":"venue"
},
  "geometry": {"coordinates":[151.12747200000001,-34.000141],"type":"Point"}
}