{
  "type": "Feature",
  "properties": {
    "addr:full":"209 King St Newtown NSW 2042",
    "addr:housenumber":"209",
    "addr:postcode":"2042",
    "addr:street":"King St",
    "iso:country":"AU",
    "sg:address":"209 King St",
    "sg:city":"Newtown",
    "sg:classifiers":[
        {
            "category":"Shopping",
            "subcategory":"Clothing, Apparel, & Fashions",
            "type":"Retail Goods"
        }
    ],
    "sg:phone":"+61 2 9519 7751",
    "sg:postcode":"2042",
    "sg:province":"NSW",
    "sg:tags":[
        "lady",
        "wear"
    ],
    "wof:name":"Phoenix Fashions",
    "wof:placetype":"venue"
},
  "geometry": {"coordinates":[151.181793,-33.89492],"type":"Point"}
}