{
  "type": "Feature",
  "properties": {
    "addr:full":"32 Kay St Traralgon VIC 3844",
    "addr:housenumber":"32",
    "addr:postcode":"3844",
    "addr:street":"Kay St",
    "iso:country":"AU",
    "sg:address":"32 Kay St",
    "sg:city":"Traralgon",
    "sg:classifiers":[
        {
            "category":"Insurance",
            "subcategory":"Hazard Insurance",
            "type":"Services"
        }
    ],
    "sg:phone":"+61 3 5176 1311",
    "sg:postcode":"3844",
    "sg:province":"VIC",
    "sg:tags":[
        "fire",
        "accident",
        "marine"
    ],
    "wof:name":"RACV Insurance",
    "wof:placetype":"venue"
},
  "geometry": {"coordinates":[146.535354614,-38.1947174072],"type":"Point"}
}