{
  "type": "Feature",
  "properties": {
    "addr:full":"354 Main Rd Toukley NSW 2263",
    "addr:housenumber":"354",
    "addr:postcode":"2263",
    "addr:street":"Main Rd",
    "iso:country":"AU",
    "sg:address":"354 Main Rd",
    "sg:city":"Toukley",
    "sg:classifiers":[
        {
            "category":"Food & Beverages",
            "subcategory":"Fruits & Vegetables",
            "type":"Retail Goods"
        }
    ],
    "sg:phone":"+61 2 4397 5222",
    "sg:postcode":"2263",
    "sg:province":"NSW",
    "sg:tags":[
        "consultant",
        "catering"
    ],
    "wof:name":"Jenns Cafe & Catering Services",
    "wof:placetype":"venue"
},
  "geometry": {"coordinates":[151.54823300000001,-33.266041],"type":"Point"}
}