{
  "type": "Feature",
  "properties": {
    "addr:full":"55 Kent St Epping NSW 2121",
    "addr:housenumber":"55",
    "addr:postcode":"2121",
    "addr:street":"Kent St",
    "iso:country":"AU",
    "sg:address":"55 Kent St",
    "sg:city":"Epping",
    "sg:classifiers":[
        {
            "category":"Health Services",
            "subcategory":"Dentist",
            "type":"Services"
        }
    ],
    "sg:phone":"+61 2 8800 5663",
    "sg:postcode":"2121",
    "sg:province":"NSW",
    "wof:name":"Yuen Dr Kent",
    "wof:placetype":"venue"
},
  "geometry": {"coordinates":[151.07611084000001,-33.7738723755],"type":"Point"}
}