{
  "type": "Feature",
  "properties": {
    "iso:country":"AU",
    "sg:address":"159 Samford Rd",
    "sg:city":"Enoggera",
    "sg:classifiers":[
        {
            "category":"Personal",
            "subcategory":"Barber",
            "type":"Services"
        }
    ],
    "sg:phone":"+61 7 3355 2251",
    "sg:postcode":"4051",
    "sg:province":"QLD",
    "wof:name":"Shearing Shed The, The Original Barbershop",
    "wof:placetype":"venue"
},
  "geometry": {"coordinates":[152.99302673299999,-27.4229927063],"type":"Point"}
}