{
  "type": "Feature",
  "properties": {
    "addr:full":"72 Saywell Rd Macquarie Fields NSW 2564",
    "addr:housenumber":"72",
    "addr:postcode":"2564",
    "addr:street":"Saywell Rd",
    "iso:country":"AU",
    "sg:address":"72 Saywell Rd",
    "sg:city":"Macquarie Fields",
    "sg:classifiers":[
        {
            "category":"Food & Beverages",
            "subcategory":"Bakery",
            "type":"Retail Goods"
        }
    ],
    "sg:phone":"+61 2 9618 3897",
    "sg:postcode":"2564",
    "sg:province":"NSW",
    "sg:tags":[
        "cake",
        "shop",
        "pastry"
    ],
    "wof:name":"Cheesecake Shop The",
    "wof:placetype":"venue"
},
  "geometry": {"coordinates":[150.888137817,-33.9934310913],"type":"Point"}
}