{
  "type": "Feature",
  "properties": {
    "addr:full":"10 Lawborough Ave Parkdale VIC 3195",
    "addr:housenumber":"10",
    "addr:postcode":"3195",
    "addr:street":"Lawborough Ave",
    "iso:country":"AU",
    "sg:address":"10 Lawborough Ave",
    "sg:city":"Parkdale",
    "sg:classifiers":[
        {
            "category":"Utilities",
            "subcategory":"Electric",
            "type":"Services"
        }
    ],
    "sg:phone":"+61 419 341 475",
    "sg:postcode":"3195",
    "sg:province":"VIC",
    "sg:tags":[
        "electrical",
        "contractor"
    ],
    "wof:name":"M.A.Elliott Electrical Services",
    "wof:placetype":"venue"
},
  "geometry": {"coordinates":[145.09138488799999,-37.9883880615],"type":"Point"}
}