{
  "type": "Feature",
  "properties": {
    "addr:full":"31 Langstaffe Drv Wendouree VIC 3355",
    "addr:housenumber":"31",
    "addr:postcode":"3355",
    "addr:street":"Langstaffe Drv",
    "iso:country":"AU",
    "sg:address":"31 Langstaffe Drv",
    "sg:city":"Wendouree",
    "sg:classifiers":[
        {
            "category":"Professional",
            "subcategory":"Business Services",
            "type":"Services"
        }
    ],
    "sg:phone":"+61 3 5339 9754",
    "sg:postcode":"3355",
    "sg:province":"VIC",
    "sg:tags":[
        "drafting"
    ],
    "wof:name":"Pickford & Associates Pty Ltd",
    "wof:placetype":"venue"
},
  "geometry": {"coordinates":[143.83021500000001,-37.520859],"type":"Point"}
}