{
  "type": "Feature",
  "properties": {
    "iso:country":"AU",
    "sg:address":"7 Leicester Way St",
    "sg:city":"Clair",
    "sg:classifiers":[
        {
            "category":"Building & Trades",
            "subcategory":"Construction",
            "type":"Services"
        }
    ],
    "sg:phone":"+61 400 664 868",
    "sg:postcode":"2759",
    "sg:province":"NSW",
    "sg:tags":[
        "contractor"
    ],
    "wof:name":"R. Vaccari & Sons",
    "wof:placetype":"venue"
},
  "geometry": {"coordinates":[150.79563903799999,-33.793636322],"type":"Point"}
}