{
  "type": "Feature",
  "properties": {
    "iso:country":"AU",
    "sg:address":"8 Julatten St",
    "sg:city":"Kedron",
    "sg:classifiers":[
        {
            "category":"Building & Trades",
            "subcategory":"Landscaping Services",
            "type":"Services"
        }
    ],
    "sg:phone":"+61 7 3349 7831",
    "sg:postcode":"4031",
    "sg:province":"QLD",
    "sg:tags":[
        "inspection"
    ],
    "wof:name":"Alert Home Inspections",
    "wof:placetype":"venue"
},
  "geometry": {"coordinates":[153.03156999999999,-27.403311],"type":"Point"}
}