{
  "type": "Feature",
  "properties": {
    "addr:full":"Un 7/ 1 Murray St Camden NSW 2570",
    "addr:housenumber":"1",
    "addr:postcode":"2570",
    "addr:street":"Murray St",
    "iso:country":"AU",
    "sg:address":"Un 7/ 1 Murray St",
    "sg:city":"Camden",
    "sg:classifiers":[
        {
            "category":"Fast Food",
            "type":"Food & Drink"
        }
    ],
    "sg:phone":"+61 2 4655 3272",
    "sg:postcode":"2570",
    "sg:province":"NSW",
    "sg:tags":[
        "away",
        "take"
    ],
    "wof:name":"Pronto Pizza",
    "wof:placetype":"venue"
},
  "geometry": {"coordinates":[150.69377136200001,-34.0556716919],"type":"Point"}
}