{
  "type": "Feature",
  "properties": {
    "addr:full":"689 Whitehorse Rd Mont Albert VIC 3127",
    "addr:housenumber":"689",
    "addr:postcode":"3127",
    "addr:street":"Whitehorse Rd",
    "iso:country":"AU",
    "sg:address":"689 Whitehorse Rd",
    "sg:city":"Mont Albert",
    "sg:classifiers":[
        {
            "category":"Social Services",
            "subcategory":"Child Care",
            "type":"Services"
        }
    ],
    "sg:phone":"+61 3 9899 7990",
    "sg:postcode":"3127",
    "sg:province":"VIC",
    "sg:tags":[
        "equipment",
        "identification"
    ],
    "wof:name":"TechEng Pty Ltd",
    "wof:placetype":"venue"
},
  "geometry": {"coordinates":[145.104736328,-37.8154945374],"type":"Point"}
}