{
  "type": "Feature",
  "properties": {
    "iso:country":"AU",
    "sg:address":"10 Simon St",
    "sg:city":"Blackburn",
    "sg:classifiers":[
        {
            "category":"Farming",
            "subcategory":"Farm & Veterinary Services",
            "type":"Manufacturing & Wholesale Goods"
        }
    ],
    "sg:phone":"+61 3 9878 6137",
    "sg:postcode":"3130",
    "sg:province":"VIC",
    "sg:tags":[
        "worm"
    ],
    "wof:name":"Trevor Ross",
    "wof:placetype":"venue"
},
  "geometry": {"coordinates":[145.15699768100001,-37.8040618896],"type":"Point"}
}