{
  "type": "Feature",
  "properties": {
    "addr:full":"215 Epsom Rd Chipping Norton NSW 2170",
    "addr:housenumber":"215",
    "addr:postcode":"2170",
    "addr:street":"Epsom Rd",
    "iso:country":"AU",
    "sg:address":"215 Epsom Rd",
    "sg:city":"Chipping Norton",
    "sg:classifiers":[
        {
            "category":"Utilities",
            "subcategory":"Refuse",
            "type":"Services"
        }
    ],
    "sg:phone":"+61 405 821 388",
    "sg:postcode":"2170",
    "sg:province":"NSW",
    "sg:tags":[
        "remover",
        "rubbish"
    ],
    "wof:name":"Trailer Bin Hire",
    "wof:placetype":"venue"
},
  "geometry": {"coordinates":[150.95318603499999,-33.9205436707],"type":"Point"}
}