{
  "type": "Feature",
  "properties": {
    "addr:full":"11 Bellbird Crt Ringwood VIC 3134",
    "addr:housenumber":"11",
    "addr:postcode":"3134",
    "addr:street":"Bellbird Crt",
    "iso:country":"AU",
    "sg:address":"11 Bellbird Crt",
    "sg:city":"Ringwood",
    "sg:classifiers":[
        {
            "category":"Building & Trades",
            "subcategory":"Plumbing",
            "type":"Services"
        }
    ],
    "sg:phone":"+61 3 9870 0244",
    "sg:postcode":"3134",
    "sg:province":"VIC",
    "sg:tags":[
        "plumber",
        "gasfitters"
    ],
    "wof:name":"Pankhurst Plumbing Pty Ltd",
    "wof:placetype":"venue"
},
  "geometry": {"coordinates":[145.229125977,-37.8343162537],"type":"Point"}
}