{
  "type": "Feature",
  "properties": {
    "iso:country":"AU",
    "sg:address":"38 Pixley Crs",
    "sg:city":"Heatley",
    "sg:classifiers":[
        {
            "category":"Building & Trades",
            "subcategory":"Construction",
            "type":"Services"
        }
    ],
    "sg:phone":"+61 7 4728 9823",
    "sg:postcode":"4814",
    "sg:province":"QLD",
    "sg:tags":[
        "concrete",
        "contractor"
    ],
    "wof:name":"A1 Decorative Concrete",
    "wof:placetype":"venue"
},
  "geometry": {"coordinates":[146.759506,-19.293171],"type":"Point"}
}