{
  "type": "Feature",
  "properties": {
    "addr:full":"100 City Rd Beenleigh QLD 4207",
    "addr:housenumber":"100",
    "addr:postcode":"4207",
    "addr:street":"City Rd",
    "iso:country":"AU",
    "sg:address":"100 City Rd",
    "sg:city":"Beenleigh",
    "sg:classifiers":[
        {
            "category":"Real Estate",
            "subcategory":"Real Estate Agent",
            "type":"Services"
        }
    ],
    "sg:phone":"+61 7 3807 7900",
    "sg:postcode":"4207",
    "sg:province":"QLD",
    "wof:name":"LJ Hooker Beenleigh",
    "wof:placetype":"venue"
},
  "geometry": {"coordinates":[153.202392578,-27.7150630951],"type":"Point"}
}