{
  "type": "Feature",
  "properties": {
    "addr:full":"2a Terry St Glenorchy TAS 7010",
    "addr:housenumber":"2a",
    "addr:postcode":"7010",
    "addr:street":"Terry St",
    "iso:country":"AU",
    "sg:address":"2a Terry St",
    "sg:city":"Glenorchy",
    "sg:classifiers":[
        {
            "category":"Personal",
            "type":"Services"
        }
    ],
    "sg:phone":"+61 3 6272 7892",
    "sg:postcode":"7010",
    "sg:province":"TAS",
    "sg:tags":[
        "counselling",
        "alcohol",
        "drug"
    ],
    "wof:name":"Anglicare Tasmania Inc",
    "wof:placetype":"venue"
},
  "geometry": {"coordinates":[147.275558472,-42.8338088989],"type":"Point"}
}