{
  "type": "Feature",
  "properties": {
    "addr:full":"7 / 25 Walters Drv Osborne Park DC WA 6017",
    "addr:housenumber":"/ 25",
    "addr:postcode":"6017",
    "addr:street":"Walters Drv",
    "iso:country":"AU",
    "sg:address":"7 / 25 Walters Drv",
    "sg:city":"Osborne Park DC",
    "sg:classifiers":[
        {
            "category":"Wholesale",
            "subcategory":"Drugs",
            "type":"Manufacturing & Wholesale Goods"
        }
    ],
    "sg:phone":"+61 8 9446 2344",
    "sg:postcode":"6017",
    "sg:province":"WA",
    "sg:tags":[
        "wholesaler",
        "pharmaceutical",
        "product",
        "mfrs"
    ],
    "wof:name":"Schering Pty Ltd",
    "wof:placetype":"venue"
},
  "geometry": {"coordinates":[115.811607361,-31.9096794128],"type":"Point"}
}