{
  "type": "Feature",
  "properties": {
    "iso:country":"AU",
    "sg:address":"15 Alpina St",
    "sg:city":"Frankston North",
    "sg:classifiers":[
        {
            "category":"Education",
            "subcategory":"School",
            "type":"Public Place"
        }
    ],
    "sg:phone":"+61 3 9786 3145",
    "sg:postcode":"3200",
    "sg:province":"VIC",
    "sg:tags":[
        "co-educational"
    ],
    "wof:name":"St Anthony's Coptic Orthodox College",
    "wof:placetype":"venue"
},
  "geometry": {"coordinates":[145.1586,-38.119987],"type":"Point"}
}