{
  "type": "Feature",
  "properties": {
    "iso:country":"AU",
    "sg:address":"PO Box 267",
    "sg:city":"Buninyong",
    "sg:classifiers":[
        {
            "category":"Utilities",
            "subcategory":"Electric",
            "type":"Services"
        }
    ],
    "sg:phone":"+61 417 518 930",
    "sg:postcode":"3357",
    "sg:province":"VIC",
    "sg:tags":[
        "electrical",
        "contractor"
    ],
    "wof:name":"Coopelec Pty Ltd",
    "wof:placetype":"venue"
},
  "geometry": {"coordinates":[143.886276,-37.650761],"type":"Point"}
}