{
  "type": "Feature",
  "properties": {
    "addr:full":"19 Quinns La Nowra South NSW 2541",
    "addr:housenumber":"19",
    "addr:postcode":"2541",
    "addr:street":"Quinns La",
    "iso:country":"AU",
    "sg:address":"19 Quinns La",
    "sg:city":"Nowra South",
    "sg:classifiers":[
        {
            "category":"Building & Trades",
            "subcategory":"Construction",
            "type":"Services"
        }
    ],
    "sg:phone":"+61 2 4423 6670",
    "sg:postcode":"2541",
    "sg:province":"NSW",
    "sg:tags":[
        "bitumen",
        "paving",
        "asphalt"
    ],
    "wof:name":"RJ & PS Smith Pty Ltd",
    "wof:placetype":"venue"
},
  "geometry": {"coordinates":[150.60383605999999,-34.9152984619],"type":"Point"}
}