{
  "type": "Feature",
  "properties": {
    "addr:full":"12 Stephen St Bunbury WA 6230",
    "addr:housenumber":"12",
    "addr:postcode":"6230",
    "addr:street":"Stephen St",
    "iso:country":"AU",
    "sg:address":"12 Stephen St",
    "sg:city":"Bunbury",
    "sg:classifiers":[
        {
            "category":"Shopping",
            "subcategory":"Clothing, Apparel, & Fashions",
            "type":"Retail Goods"
        }
    ],
    "sg:phone":"+61 8 9721 2434",
    "sg:postcode":"6230",
    "sg:province":"WA",
    "sg:tags":[
        "lady",
        "wear"
    ],
    "wof:name":"Gough's Ladies Fashions",
    "wof:placetype":"venue"
},
  "geometry": {"coordinates":[115.638931,-33.326031],"type":"Point"}
}