{
  "type": "Feature",
  "properties": {
    "addr:full":"409 Bridge Rd Richmond VIC 3121",
    "addr:housenumber":"409",
    "addr:postcode":"3121",
    "addr:street":"Bridge Rd",
    "iso:country":"AU",
    "sg:address":"409 Bridge Rd",
    "sg:city":"Richmond",
    "sg:classifiers":[
        {
            "category":"Real Estate",
            "subcategory":"Developer",
            "type":"Services"
        }
    ],
    "sg:phone":"+61 3 9428 0877",
    "sg:postcode":"3121",
    "sg:province":"VIC",
    "sg:tags":[
        "development"
    ],
    "wof:name":"Leesville Development Pty Ltd",
    "wof:placetype":"venue"
},
  "geometry": {"coordinates":[145.004180908,-37.8189239502],"type":"Point"}
}