{
  "type": "Feature",
  "properties": {
    "addr:full":"34 Craigburn Drv Flagstaff Hill SA 5159",
    "addr:housenumber":"34",
    "addr:postcode":"5159",
    "addr:street":"Craigburn Drv",
    "iso:country":"AU",
    "sg:address":"34 Craigburn Drv",
    "sg:city":"Flagstaff Hill",
    "sg:classifiers":[
        {
            "category":"Insurance",
            "subcategory":"Insurance Agent",
            "type":"Services"
        }
    ],
    "sg:phone":"+61 8 8370 7422",
    "sg:postcode":"5159",
    "sg:province":"SA",
    "sg:tags":[
        "broker"
    ],
    "wof:name":"Herraman Rob & Associates Pty Ltd",
    "wof:placetype":"venue"
},
  "geometry": {"coordinates":[138.609466553,-35.0569229126],"type":"Point"}
}