{
  "type": "Feature",
  "properties": {
    "addr:full":"68 ChurchChill St Childers QLD 4660",
    "addr:housenumber":"68",
    "addr:postcode":"4660",
    "addr:street":"Churchchill St",
    "iso:country":"AU",
    "sg:address":"68 ChurchChill St",
    "sg:city":"Childers",
    "sg:classifiers":[
        {
            "category":"Personal",
            "type":"Services"
        }
    ],
    "sg:phone":"+61 7 4126 3823",
    "sg:postcode":"4660",
    "sg:province":"QLD",
    "sg:tags":[
        "career",
        "counselling"
    ],
    "wof:name":"Neato Employment Services",
    "wof:placetype":"venue"
},
  "geometry": {"coordinates":[152.27906799300001,-25.2364807129],"type":"Point"}
}