{
  "type": "Feature",
  "properties": {
    "iso:country":"AU",
    "sg:address":"24 May St",
    "sg:city":"East Fremantle",
    "sg:classifiers":[
        {
            "category":"Real Estate",
            "subcategory":"Architect",
            "type":"Services"
        }
    ],
    "sg:phone":"+61 8 9438 3288",
    "sg:postcode":"6158",
    "sg:province":"WA",
    "sg:tags":[
        "building",
        "designer"
    ],
    "wof:name":"Kensington Design",
    "wof:placetype":"venue"
},
  "geometry": {"coordinates":[115.765488,-32.041721],"type":"Point"}
}