{
  "type": "Feature",
  "properties": {
    "addr:full":"Cnr Corunna & Slacksmith Sts Burren Junction NSW 2386",
    "addr:postcode":"2386",
    "addr:street":"Cnr",
    "iso:country":"AU",
    "sg:address":"Cnr Corunna & Slacksmith Sts",
    "sg:city":"Burren Junction",
    "sg:classifiers":[
        {
            "category":"Travel",
            "subcategory":"Hotels & Motels",
            "type":"Entertainment"
        }
    ],
    "sg:phone":"+61 2 6796 1440",
    "sg:postcode":"2386",
    "sg:province":"NSW",
    "sg:tags":[
        "accommodation"
    ],
    "wof:name":"Junction City Hotel",
    "wof:placetype":"venue"
},
  "geometry": {"coordinates":[148.970413208,-30.1062088013],"type":"Point"}
}