{
  "type": "Feature",
  "properties": {
    "addr:full":"516 Wangoom Rd Wangoom VIC 3279",
    "addr:housenumber":"516",
    "addr:postcode":"3279",
    "addr:street":"Wangoom Rd",
    "iso:country":"AU",
    "sg:address":"516 Wangoom Rd",
    "sg:city":"Wangoom",
    "sg:classifiers":[
        {
            "category":"Home & Garden",
            "subcategory":"Building Materials",
            "type":"Retail Goods"
        }
    ],
    "sg:phone":"+61 3 5567 1271",
    "sg:postcode":"3279",
    "sg:province":"VIC",
    "sg:tags":[
        "concrete",
        "gutter",
        "kerb"
    ],
    "wof:name":"Charles & Anne-Maree Cowell",
    "wof:placetype":"venue"
},
  "geometry": {"coordinates":[142.55682373100001,-38.3487892151],"type":"Point"}
}