{
  "type": "Feature",
  "properties": {
    "iso:country":"AU",
    "sg:address":"224 Mary St",
    "sg:city":"Gympie",
    "sg:classifiers":[
        {
            "category":"Professional",
            "subcategory":"Management & Consulting",
            "type":"Services"
        }
    ],
    "sg:phone":"+61 7 5482 5444",
    "sg:postcode":"4570",
    "sg:province":"QLD",
    "sg:tags":[
        "consultant",
        "economic"
    ],
    "wof:name":"Cooloola Regional Development Bureau",
    "wof:placetype":"venue"
},
  "geometry": {"coordinates":[152.659133911,-26.1889362335],"type":"Point"}
}