{
  "type": "Feature",
  "properties": {
    "addr:full":"248 Sunshine Ave Kealba VIC 3021",
    "addr:housenumber":"248",
    "addr:postcode":"3021",
    "addr:street":"Sunshine Ave",
    "iso:country":"AU",
    "sg:address":"248 Sunshine Ave",
    "sg:city":"Kealba",
    "sg:classifiers":[
        {
            "category":"Personal",
            "subcategory":"Beauty Salon",
            "type":"Services"
        }
    ],
    "sg:phone":"+61 3 9356 9822",
    "sg:postcode":"3021",
    "sg:province":"VIC",
    "wof:name":"Bella Medi Spa",
    "wof:placetype":"venue"
},
  "geometry": {"coordinates":[144.818558,-37.733112],"type":"Point"}
}