{
  "type": "Feature",
  "properties": {
    "iso:country":"AU",
    "sg:address":"94a Young St",
    "sg:city":"Frankston",
    "sg:classifiers":[
        {
            "category":"Personal",
            "subcategory":"Massage",
            "type":"Services"
        }
    ],
    "sg:phone":"+61 409 806 908",
    "sg:postcode":"3199",
    "sg:province":"VIC",
    "sg:tags":[
        "therapy"
    ],
    "wof:name":"Frankston Therapeutic Clinic",
    "wof:placetype":"venue"
},
  "geometry": {"coordinates":[145.12495422399999,-38.1441230774],"type":"Point"}
}