{
  "type": "Feature",
  "properties": {
    "addr:full":"Shop 3 121 Towradgi Rd Towradgi NSW 2518",
    "addr:housenumber":"shop 3",
    "addr:postcode":"121;2518",
    "addr:street":"Towradgi Rd",
    "iso:country":"AU",
    "sg:address":"Shop 3 121 Towradgi Rd",
    "sg:city":"Towradgi",
    "sg:classifiers":[
        {
            "category":"Fast Food",
            "type":"Food & Drink"
        }
    ],
    "sg:phone":"+61 2 4284 9863",
    "sg:postcode":"2518",
    "sg:province":"NSW",
    "sg:tags":[
        "away",
        "take"
    ],
    "wof:name":"Towradgi Chicken Shop",
    "wof:placetype":"venue"
},
  "geometry": {"coordinates":[150.902817,-34.383949],"type":"Point"}
}