{
  "type": "Feature",
  "properties": {
    "addr:full":"Unit 1, 66 Westchester Rd Malaga WA 6090",
    "addr:housenumber":"66",
    "addr:postcode":"6090",
    "addr:street":"Westchester Rd",
    "iso:country":"AU",
    "sg:address":"Unit 1, 66 Westchester Rd",
    "sg:city":"Malaga",
    "sg:classifiers":[
        {
            "category":"Utilities",
            "subcategory":"Sewage",
            "type":"Services"
        }
    ],
    "sg:phone":"+61 1800 028 584",
    "sg:postcode":"6090",
    "sg:province":"WA",
    "sg:tags":[
        "equipment",
        "sewer",
        "cleaning"
    ],
    "wof:name":"Sewer Equipment Co (AUST)",
    "wof:placetype":"venue"
},
  "geometry": {"coordinates":[115.88079834,-31.8545246124],"type":"Point"}
}