{
  "type": "Feature",
  "properties": {
    "addr:full":"Magog Crt Mandurah WA 6210",
    "addr:postcode":"6210",
    "addr:street":"Magog",
    "iso:country":"AU",
    "sg:address":"Magog Crt",
    "sg:city":"Mandurah",
    "sg:classifiers":[
        {
            "category":"Social Services",
            "subcategory":"Child Care",
            "type":"Services"
        }
    ],
    "sg:phone":"+61 1800 067 656",
    "sg:postcode":"6210",
    "sg:province":"WA",
    "sg:tags":[
        "baby",
        "sitter"
    ],
    "wof:name":"Rockingham Mandurah Babysitting Service",
    "wof:placetype":"venue"
},
  "geometry": {"coordinates":[115.752602,-32.537659],"type":"Point"}
}