{
  "type": "Feature",
  "properties": {
    "addr:full":"Lot 1/ Belmore St Ryde NSW 2112",
    "addr:housenumber":"1 /",
    "addr:postcode":"2112",
    "addr:street":"Belmore St",
    "iso:country":"AU",
    "sg:address":"Lot 1/ Belmore St",
    "sg:city":"Ryde",
    "sg:classifiers":[
        {
            "category":"Social Services",
            "subcategory":"Child Care",
            "type":"Services"
        }
    ],
    "sg:phone":"+61 2 9808 2692",
    "sg:postcode":"2112",
    "sg:province":"NSW",
    "wof:name":"Meadowbank Multi-Learning Centre",
    "wof:placetype":"venue"
},
  "geometry": {"coordinates":[151.097946167,-33.8172073364],"type":"Point"}
}