{
  "type": "Feature",
  "properties": {
    "iso:country":"AU",
    "sg:address":"24 Beverley St",
    "sg:city":"Mackay",
    "sg:classifiers":[
        {
            "category":"Building & Trades",
            "subcategory":"Landscaping Services",
            "type":"Services"
        }
    ],
    "sg:phone":"+61 7 4957 8759",
    "sg:postcode":"4740",
    "sg:province":"QLD",
    "sg:tags":[
        "designer",
        "landscape",
        "contractor"
    ],
    "wof:name":"Stewarts Landscaping Service",
    "wof:placetype":"venue"
},
  "geometry": {"coordinates":[149.194122,-21.166445],"type":"Point"}
}