{
  "type": "Feature",
  "properties": {
    "iso:country":"AU",
    "sg:address":"Level 1/ 18- 22 Thomson St",
    "sg:city":"South Melbourne",
    "sg:classifiers":[
        {
            "category":"Building & Trades",
            "subcategory":"Construction",
            "type":"Services"
        }
    ],
    "sg:phone":"+61 3 9645 5536",
    "sg:postcode":"3205",
    "sg:province":"VIC",
    "sg:tags":[
        "contractor"
    ],
    "wof:name":"Domain Builders Pty Ltd",
    "wof:placetype":"venue"
},
  "geometry": {"coordinates":[144.966171,-37.836861],"type":"Point"}
}