{
  "type": "Feature",
  "properties": {
    "addr:full":"76b George St Bathurst NSW 2795",
    "addr:housenumber":"76b",
    "addr:postcode":"2795",
    "addr:street":"George St",
    "iso:country":"AU",
    "sg:address":"76b George St",
    "sg:city":"Bathurst",
    "sg:classifiers":[
        {
            "category":"Professional",
            "subcategory":"Computer Services",
            "type":"Services"
        }
    ],
    "sg:phone":"+61 2 6331 0280",
    "sg:postcode":"2795",
    "sg:province":"NSW",
    "sg:tags":[
        "package",
        "software"
    ],
    "wof:name":"Bathurst Software Solutions",
    "wof:placetype":"venue"
},
  "geometry": {"coordinates":[149.55166625999999,-33.4029846191],"type":"Point"}
}