{
  "type": "Feature",
  "properties": {
    "iso:country":"AU",
    "sg:address":"28 Booloora Rd",
    "sg:city":"Springvale",
    "sg:classifiers":[
        {
            "category":"Retail",
            "subcategory":"Auto Repair",
            "type":"Services"
        }
    ],
    "sg:phone":"+61 3 9546 1000",
    "sg:postcode":"3171",
    "sg:province":"VIC",
    "sg:tags":[
        "repairer",
        "motor",
        "engineer"
    ],
    "wof:name":"Heather Hill & K.M. Automotive",
    "wof:placetype":"venue"
},
  "geometry": {"coordinates":[145.14068603499999,-37.9436149597],"type":"Point"}
}