{
  "type": "Feature",
  "properties": {
    "addr:full":"1- 7 Ellen Gowan St Hervey Bay QLD 4655",
    "addr:housenumber":"7",
    "addr:postcode":"4655",
    "addr:street":"Ellen Gowan St",
    "iso:country":"AU",
    "sg:address":"1- 7 Ellen Gowan St",
    "sg:city":"Hervey Bay",
    "sg:classifiers":[
        {
            "category":"Mining & Drilling",
            "type":"Manufacturing & Wholesale Goods"
        }
    ],
    "sg:phone":"+61 7 4128 4240",
    "sg:postcode":"4655",
    "sg:province":"QLD",
    "sg:tags":[
        "boring",
        "contractor"
    ],
    "wof:name":"Gopher Directional Drilling Services",
    "wof:placetype":"venue"
},
  "geometry": {"coordinates":[152.79847699999999,-25.299061],"type":"Point"}
}