{
  "type": "Feature",
  "properties": {
    "iso:country":"AU",
    "sg:address":"381 Argyle St",
    "sg:city":"Hobart",
    "sg:classifiers":[
        {
            "category":"Professional",
            "subcategory":"Accounting & Tax Preparation",
            "type":"Services"
        }
    ],
    "sg:phone":"+61 3 6231 5616",
    "sg:postcode":"7001",
    "sg:province":"TAS",
    "sg:tags":[
        "consultant",
        "taxation"
    ],
    "wof:name":"Dawson Peter N",
    "wof:placetype":"venue"
},
  "geometry": {"coordinates":[147.31655883799999,-42.8705482483],"type":"Point"}
}