{
  "type": "Feature",
  "properties": {
    "addr:full":"Shop 9, 76 Athlon Drv Tuggeranong ACT 2900",
    "addr:housenumber":"shop;76",
    "addr:postcode":"2900",
    "addr:street":"Athlon Drv",
    "iso:country":"AU",
    "sg:address":"Shop 9, 76 Athlon Drv",
    "sg:city":"Tuggeranong",
    "sg:classifiers":[
        {
            "category":"Fast Food",
            "type":"Food & Drink"
        }
    ],
    "sg:phone":"+61 2 6293 1711",
    "sg:postcode":"2900",
    "sg:province":"ACT",
    "sg:tags":[
        "away",
        "take"
    ],
    "wof:name":"Chalisa Indian Restaurant",
    "wof:placetype":"venue"
},
  "geometry": {"coordinates":[149.06393432600001,-35.4175949097],"type":"Point"}
}