{
  "type": "Feature",
  "properties": {
    "addr:full":"25/ 173 Lennox St Richmond VIC 3121",
    "addr:housenumber":"25 / 173",
    "addr:postcode":"3121",
    "addr:street":"Lennox St",
    "iso:country":"AU",
    "sg:address":"25/ 173 Lennox St",
    "sg:city":"Richmond",
    "sg:classifiers":[
        {
            "category":"Health Services",
            "subcategory":"Doctor",
            "type":"Services"
        }
    ],
    "sg:phone":"+61 3 9428 1817",
    "sg:postcode":"3121",
    "sg:province":"VIC",
    "sg:tags":[
        "medical",
        "practitioner"
    ],
    "wof:name":"Armstrong Mr Michael",
    "wof:placetype":"venue"
},
  "geometry": {"coordinates":[144.9949646,-37.8170166016],"type":"Point"}
}