{
  "type": "Feature",
  "properties": {
    "iso:country":"AU",
    "sg:address":"20 Booth St",
    "sg:city":"Annandale",
    "sg:classifiers":[
        {
            "category":"Retail",
            "subcategory":"Self-service Laundry",
            "type":"Services"
        }
    ],
    "sg:phone":"+61 2 9660 3596",
    "sg:postcode":"2038",
    "sg:province":"NSW",
    "wof:name":"Annandale Laundrette",
    "wof:placetype":"venue"
},
  "geometry": {"coordinates":[151.17315673799999,-33.8823928833],"type":"Point"}
}