{
  "type": "Feature",
  "properties": {
    "addr:full":"917 Wanneroo Rd Wanneroo WA 6065",
    "addr:housenumber":"917",
    "addr:postcode":"6065",
    "addr:street":"Wanneroo Rd",
    "iso:country":"AU",
    "sg:address":"917 Wanneroo Rd",
    "sg:city":"Wanneroo",
    "sg:classifiers":[
        {
            "category":"Sports & Exercise",
            "subcategory":"Gym",
            "type":"Entertainment"
        }
    ],
    "sg:phone":"+61 8 9405 3648",
    "sg:postcode":"6065",
    "sg:province":"WA",
    "sg:tags":[
        "health",
        "fitness"
    ],
    "wof:name":"Wanneroo Personal Training",
    "wof:placetype":"venue"
},
  "geometry": {"coordinates":[115.80532836899999,-31.7555198669],"type":"Point"}
}