{
  "type": "Feature",
  "properties": {
    "addr:full":"18 Horizon Drv Beenleigh QLD 4207",
    "addr:housenumber":"18",
    "addr:postcode":"4207",
    "addr:street":"Horizon Drv",
    "iso:country":"AU",
    "sg:address":"18 Horizon Drv",
    "sg:city":"Beenleigh",
    "sg:classifiers":[
        {
            "category":"Wholesale",
            "subcategory":"Electrical",
            "type":"Manufacturing & Wholesale Goods"
        }
    ],
    "sg:phone":"+61 7 3287 2803",
    "sg:postcode":"4207",
    "sg:province":"QLD",
    "sg:tags":[
        "wholesaler"
    ],
    "wof:name":"Dart Switchboards Pty Ltd",
    "wof:placetype":"venue"
},
  "geometry": {"coordinates":[153.18347168,-27.7148532867],"type":"Point"}
}