{
  "type": "Feature",
  "properties": {
    "addr:full":"140 Bolton St Eltham VIC 3095",
    "addr:housenumber":"140",
    "addr:postcode":"3095",
    "addr:street":"Bolton St",
    "iso:country":"AU",
    "sg:address":"140 Bolton St",
    "sg:city":"Eltham",
    "sg:classifiers":[
        {
            "category":"Professional",
            "subcategory":"Business Services",
            "type":"Services"
        }
    ],
    "sg:phone":"+61 3 9439 6046",
    "sg:postcode":"3095",
    "sg:province":"VIC",
    "sg:tags":[
        "drafting"
    ],
    "wof:name":"Cust John E",
    "wof:placetype":"venue"
},
  "geometry": {"coordinates":[145.13526916500001,-37.7309074402],"type":"Point"}
}