{
  "type": "Feature",
  "properties": {
    "iso:country":"AU",
    "sg:address":"40 Yiada St",
    "sg:city":"Kedron",
    "sg:classifiers":[
        {
            "category":"Building & Trades",
            "subcategory":"Plumbing",
            "type":"Services"
        }
    ],
    "sg:phone":"+61 417 787 539",
    "sg:postcode":"4031",
    "sg:province":"QLD",
    "sg:tags":[
        "plumber",
        "gasfitters"
    ],
    "wof:name":"Smith Brad Plumbing",
    "wof:placetype":"venue"
},
  "geometry": {"coordinates":[153.024246,-27.396135],"type":"Point"}
}