{
  "type": "Feature",
  "properties": {
    "addr:full":"123 Harris St Pyrmont NSW 2009",
    "addr:housenumber":"123",
    "addr:postcode":"2009",
    "addr:street":"Harris St",
    "iso:country":"AU",
    "sg:address":"123 Harris St",
    "sg:city":"Pyrmont",
    "sg:classifiers":[
        {
            "category":"Food & Beverages",
            "subcategory":"Liquor & Beverages",
            "type":"Retail Goods"
        }
    ],
    "sg:phone":"+61 2 9571 8577",
    "sg:postcode":"2009",
    "sg:province":"NSW",
    "sg:tags":[
        "store"
    ],
    "wof:name":"Pyrmont Cellars",
    "wof:placetype":"venue"
},
  "geometry": {"coordinates":[151.19357299800001,-33.869342804],"type":"Point"}
}