{
  "type": "Feature",
  "properties": {
    "addr:full":"20 Oborn Rd Mt Barker SA 5251",
    "addr:housenumber":"20",
    "addr:postcode":"5251",
    "addr:street":"Oborn Rd",
    "iso:country":"AU",
    "sg:address":"20 Oborn Rd",
    "sg:city":"Mt Barker",
    "sg:classifiers":[
        {
            "category":"Manufacturing",
            "subcategory":"Glass & Minerals",
            "type":"Manufacturing & Wholesale Goods"
        }
    ],
    "sg:phone":"+61 8 8393 0900",
    "sg:postcode":"5251",
    "sg:province":"SA",
    "sg:tags":[
        "exploration"
    ],
    "wof:name":"Geoscience Associates (Australia) Pty Ltd",
    "wof:placetype":"venue"
},
  "geometry": {"coordinates":[138.87422180199999,-35.079864502],"type":"Point"}
}