{
  "type": "Feature",
  "properties": {
    "iso:country":"AU",
    "sg:address":"22 Hannell St",
    "sg:city":"Wickham",
    "sg:classifiers":[
        {
            "category":"Professional",
            "subcategory":"Engineering",
            "type":"Services"
        }
    ],
    "sg:phone":"+61 2 4969 3823",
    "sg:postcode":"2293",
    "sg:province":"NSW",
    "sg:tags":[
        "engineer"
    ],
    "wof:name":"Dart Engineering Services",
    "wof:placetype":"venue"
},
  "geometry": {"coordinates":[151.76039123499999,-32.9240188599],"type":"Point"}
}