{
  "type": "Feature",
  "properties": {
    "addr:full":"Chermside 956 Gympie Rd Chermside QLD 4032",
    "addr:housenumber":"956",
    "addr:postcode":"qld 4032",
    "addr:street":"Chermside;Gympie Rd",
    "iso:country":"AU",
    "sg:address":"Chermside 956 Gympie Rd",
    "sg:city":"Chermside",
    "sg:classifiers":[
        {
            "category":"Health Services",
            "subcategory":"Doctor",
            "type":"Services"
        }
    ],
    "sg:phone":"+61 7 3839 9490",
    "sg:postcode":"4032",
    "sg:province":"QLD",
    "sg:tags":[
        "medical",
        "practitioner"
    ],
    "wof:name":"James Anthony N",
    "wof:placetype":"venue"
},
  "geometry": {"coordinates":[153.02018699999999,-27.392399],"type":"Point"}
}