{
  "type": "Feature",
  "properties": {
    "addr:full":"Lot22/ 6 Martin St Ravensthorpe WA 6346",
    "addr:housenumber":"6",
    "addr:postcode":"6346",
    "addr:street":"Martin St",
    "iso:country":"AU",
    "sg:address":"Lot22/ 6 Martin St",
    "sg:city":"Ravensthorpe",
    "sg:classifiers":[
        {
            "category":"Mining & Drilling",
            "type":"Manufacturing & Wholesale Goods"
        }
    ],
    "sg:phone":"+61 8 9838 1566",
    "sg:postcode":"6346",
    "sg:province":"WA",
    "sg:tags":[
        "equipment",
        "quarrying",
        "supply"
    ],
    "wof:name":"Cpc Ravensthorpe Pty Ltd",
    "wof:placetype":"venue"
},
  "geometry": {"coordinates":[120.038231,-33.584816],"type":"Point"}
}