{
  "type": "Feature",
  "properties": {
    "iso:country":"AU",
    "sg:address":"42 Randall St",
    "sg:city":"Slacks Creek",
    "sg:classifiers":[
        {
            "category":"Wholesale",
            "subcategory":"Machinery & Supplies",
            "type":"Manufacturing & Wholesale Goods"
        }
    ],
    "sg:phone":"+61 7 3808 9600",
    "sg:postcode":"4127",
    "sg:province":"QLD",
    "sg:tags":[
        "equipment",
        "system",
        "elevating",
        "conveying"
    ],
    "wof:name":"C C Components Qld Pty Ltd",
    "wof:placetype":"venue"
},
  "geometry": {"coordinates":[153.12254333499999,-27.6246032715],"type":"Point"}
}