{
  "type": "Feature",
  "properties": {
    "addr:full":"Gordon St Hopetoun WA 6348",
    "addr:postcode":"6348",
    "addr:street":"Gordon St",
    "iso:country":"AU",
    "sg:address":"Gordon St",
    "sg:city":"Hopetoun",
    "sg:classifiers":[
        {
            "category":"Farming",
            "subcategory":"Farm",
            "type":"Manufacturing & Wholesale Goods"
        }
    ],
    "sg:phone":"+61 8 9838 3153",
    "sg:postcode":"6348",
    "sg:province":"WA",
    "sg:tags":[
        "farmer"
    ],
    "wof:name":"Eckersley R A",
    "wof:placetype":"venue"
},
  "geometry": {"coordinates":[120.122139,-33.946541],"type":"Point"}
}