{
  "type": "Feature",
  "properties": {
    "addr:full":"11a Merriman St Kyle Bay NSW 2221",
    "addr:housenumber":"11a",
    "addr:postcode":"2221",
    "addr:street":"Merriman St",
    "iso:country":"AU",
    "sg:address":"11a Merriman St",
    "sg:city":"Kyle Bay",
    "sg:classifiers":[
        {
            "category":"Professional",
            "subcategory":"Engineering",
            "type":"Services"
        }
    ],
    "sg:phone":"+61 2 9546 4600",
    "sg:postcode":"2221",
    "sg:province":"NSW",
    "sg:tags":[
        "electronic",
        "engineer"
    ],
    "wof:name":"Automated Control Solutions",
    "wof:placetype":"venue"
},
  "geometry": {"coordinates":[151.102172852,-33.9879150391],"type":"Point"}
}