{
  "type": "Feature",
  "properties": {
    "addr:full":"41 / 756 Burwood Hwy Ferntree Gully VIC 3156",
    "addr:housenumber":"41 / 756",
    "addr:postcode":"3156",
    "addr:street":"Burwood Hwy",
    "iso:country":"AU",
    "sg:address":"41 / 756 Burwood Hwy",
    "sg:city":"Ferntree Gully",
    "sg:classifiers":[
        {
            "category":"Professional",
            "subcategory":"Art Services",
            "type":"Services"
        }
    ],
    "sg:phone":"+61 3 9752 2144",
    "sg:postcode":"3156",
    "sg:province":"VIC",
    "sg:tags":[
        "product",
        "industrial",
        "designer"
    ],
    "wof:name":"APS Plastics Pty Ltd",
    "wof:placetype":"venue"
},
  "geometry": {"coordinates":[145.30079650900001,-37.8910942078],"type":"Point"}
}