{
  "type": "Feature",
  "properties": {
    "addr:full":"Shp5/ 103 Evans St Sunbury VIC 3429",
    "addr:housenumber":"103",
    "addr:postcode":"3429",
    "addr:street":"Evans St",
    "iso:country":"AU",
    "sg:address":"Shp5/ 103 Evans St",
    "sg:city":"Sunbury",
    "sg:classifiers":[
        {
            "category":"Restaurant",
            "type":"Food & Drink"
        }
    ],
    "sg:phone":"+61 3 9740 4636",
    "sg:postcode":"3429",
    "sg:province":"VIC",
    "wof:name":"Bet C's Restaurant & Wine Bar",
    "wof:placetype":"venue"
},
  "geometry": {"coordinates":[144.7290802,-37.5800666809],"type":"Point"}
}