{
  "type": "Feature",
  "properties": {
    "addr:full":"16 Dubbo Rd Wellington NSW 2820",
    "addr:housenumber":"16",
    "addr:postcode":"2820",
    "addr:street":"Dubbo Rd",
    "iso:country":"AU",
    "sg:address":"16 Dubbo Rd",
    "sg:city":"Wellington",
    "sg:classifiers":[
        {
            "category":"Professional",
            "subcategory":"Engineering",
            "type":"Services"
        }
    ],
    "sg:phone":"+61 2 6845 2929",
    "sg:postcode":"2820",
    "sg:province":"NSW",
    "sg:tags":[
        "engineer",
        "mechanical"
    ],
    "wof:name":"N J S Mechanical",
    "wof:placetype":"venue"
},
  "geometry": {"coordinates":[148.942962647,-32.5556411743],"type":"Point"}
}