{
  "type": "Feature",
  "properties": {
    "addr:full":"10/ 47 Musgrave Rd Coopers Plains QLD 4108",
    "addr:housenumber":"10 / 47",
    "addr:postcode":"4108",
    "addr:street":"Musgrave Rd",
    "iso:country":"AU",
    "sg:address":"10/ 47 Musgrave Rd",
    "sg:city":"Coopers Plains",
    "sg:classifiers":[
        {
            "category":"Wholesale",
            "subcategory":"Apparel",
            "type":"Manufacturing & Wholesale Goods"
        }
    ],
    "sg:phone":"+61 7 3274 5811",
    "sg:postcode":"4108",
    "sg:province":"QLD",
    "sg:tags":[
        "wholesaler",
        "men's",
        "mfrs",
        "sportswear"
    ],
    "wof:name":"Aussie Trackwear",
    "wof:placetype":"venue"
},
  "geometry": {"coordinates":[153.02540588400001,-27.5612373352],"type":"Point"}
}