{
  "type": "Feature",
  "properties": {
    "addr:full":"244 Eastern Pde Gillman SA 5013",
    "addr:housenumber":"244",
    "addr:postcode":"5013",
    "addr:street":"Eastern Pde",
    "iso:country":"AU",
    "sg:address":"244 Eastern Pde",
    "sg:city":"Gillman",
    "sg:classifiers":[
        {
            "category":"Manufacturing",
            "subcategory":"Building Materials",
            "type":"Manufacturing & Wholesale Goods"
        }
    ],
    "sg:phone":"+61 8 8403 7600",
    "sg:postcode":"5013",
    "sg:province":"SA",
    "sg:tags":[
        "equipment",
        "handling"
    ],
    "wof:name":"Chep Australia",
    "wof:placetype":"venue"
},
  "geometry": {"coordinates":[138.526321411,-34.8400230408],"type":"Point"}
}