{
  "type": "Feature",
  "properties": {
    "iso:country":"AU",
    "sg:address":"13 Rachel Crt",
    "sg:city":"Sale",
    "sg:classifiers":[
        {
            "category":"Building & Trades",
            "subcategory":"Landscaping Services",
            "type":"Services"
        }
    ],
    "sg:phone":"+61 3 5144 5245",
    "sg:postcode":"3850",
    "sg:province":"VIC",
    "sg:tags":[
        "stump",
        "tree",
        "felling",
        "removal"
    ],
    "wof:name":"Sale Stump Busters",
    "wof:placetype":"venue"
},
  "geometry": {"coordinates":[147.091552734,-38.1048965454],"type":"Point"}
}