{
  "type": "Feature",
  "properties": {
    "addr:full":"Cnr Canal & Lilyfield Rds Leichhardt NSW 2040",
    "addr:postcode":"2040",
    "addr:street":"Cnr Canal &",
    "iso:country":"AU",
    "sg:address":"Cnr Canal & Lilyfield Rds",
    "sg:city":"Leichhardt",
    "sg:classifiers":[
        {
            "category":"Retail",
            "subcategory":"Storage",
            "type":"Services"
        }
    ],
    "sg:phone":"+61 2 9568 1400",
    "sg:postcode":"2040",
    "sg:province":"NSW",
    "wof:name":"Pyrmont Car Store",
    "wof:placetype":"venue"
},
  "geometry": {"coordinates":[151.15112300000001,-33.87257],"type":"Point"}
}