{
  "type": "Feature",
  "properties": {
    "addr:full":"8 Romaine St South Burnie TAS 7320",
    "addr:housenumber":"8",
    "addr:postcode":"7320",
    "addr:street":"Romaine St",
    "iso:country":"AU",
    "sg:address":"8 Romaine St",
    "sg:city":"South Burnie",
    "sg:classifiers":[
        {
            "category":"Building & Trades",
            "subcategory":"Construction",
            "type":"Services"
        }
    ],
    "sg:phone":"+61 3 6431 6768",
    "sg:postcode":"7320",
    "sg:province":"TAS",
    "sg:tags":[
        "roof"
    ],
    "wof:name":"John Eastley Roofing",
    "wof:placetype":"venue"
},
  "geometry": {"coordinates":[145.909164,-41.064785],"type":"Point"}
}