{
  "type": "Feature",
  "properties": {
    "addr:full":"Shop 6 115 Darby St Newcastle NSW 2300",
    "addr:housenumber":"shop 6 115",
    "addr:postcode":"2300",
    "addr:street":"Darby St",
    "iso:country":"AU",
    "sg:address":"Shop 6 115 Darby St",
    "sg:city":"Newcastle",
    "sg:classifiers":[
        {
            "category":"Manufacturing",
            "subcategory":"Food",
            "type":"Manufacturing & Wholesale Goods"
        }
    ],
    "sg:phone":"+61 2 4926 2115",
    "sg:postcode":"2300",
    "sg:province":"NSW",
    "sg:tags":[
        "function",
        "catering"
    ],
    "wof:name":"Darby Street Gourmet Deli",
    "wof:placetype":"venue"
},
  "geometry": {"coordinates":[151.772186,-32.931137],"type":"Point"}
}