{
  "type": "Feature",
  "properties": {
    "addr:full":"2 Craig Ave Manly NSW 2095",
    "addr:housenumber":"2",
    "addr:postcode":"2095",
    "addr:street":"Craig Ave",
    "iso:country":"AU",
    "sg:address":"2 Craig Ave",
    "sg:city":"Manly",
    "sg:classifiers":[
        {
            "category":"Real Estate",
            "subcategory":"Architect",
            "type":"Services"
        }
    ],
    "sg:phone":"+61 407 704 407",
    "sg:postcode":"2095",
    "sg:province":"NSW",
    "wof:name":"George Leich Architect",
    "wof:placetype":"venue"
},
  "geometry": {"coordinates":[151.28680419899999,-33.8059005737],"type":"Point"}
}