{
  "type": "Feature",
  "properties": {
    "addr:full":"Rm3/ 60 Victoria St Warragul VIC 3820",
    "addr:housenumber":"60",
    "addr:postcode":"3820",
    "addr:street":"Victoria St",
    "iso:country":"AU",
    "sg:address":"Rm3/ 60 Victoria St",
    "sg:city":"Warragul",
    "sg:classifiers":[
        {
            "category":"Health Services",
            "subcategory":"Chiropractor",
            "type":"Services"
        }
    ],
    "sg:phone":"+61 3 5622 2500",
    "sg:postcode":"3820",
    "sg:province":"VIC",
    "wof:name":"McMillan Anda",
    "wof:placetype":"venue"
},
  "geometry": {"coordinates":[145.92967200000001,-38.160477],"type":"Point"}
}