{
  "type": "Feature",
  "properties": {
    "iso:country":"AU",
    "sg:address":"9 Acacia Ave",
    "sg:city":"Forbes",
    "sg:classifiers":[
        {
            "category":"Farming",
            "subcategory":"Farm & Veterinary Services",
            "type":"Manufacturing & Wholesale Goods"
        }
    ],
    "sg:phone":"+61 2 6852 1084",
    "sg:postcode":"2871",
    "sg:province":"NSW",
    "sg:tags":[
        "contracting"
    ],
    "wof:name":"Geoff Morrison",
    "wof:placetype":"venue"
},
  "geometry": {"coordinates":[148.003616,-33.36591],"type":"Point"}
}