{
  "type": "Feature",
  "properties": {
    "iso:country":"AU",
    "sg:address":"Shop 2/ 53A Manning St",
    "sg:city":"Taree",
    "sg:classifiers":[
        {
            "category":"Shopping",
            "subcategory":"Antiques",
            "type":"Retail Goods"
        }
    ],
    "sg:phone":"+61 2 6551 8333",
    "sg:postcode":"2430",
    "sg:province":"NSW",
    "wof:name":"Isadoras Antiques & Jewellery",
    "wof:placetype":"venue"
},
  "geometry": {"coordinates":[152.46092200000001,-31.911568],"type":"Point"}
}