{
  "type": "Feature",
  "properties": {
    "addr:full":"41 Tuaggra St Maryborough VIC 3465",
    "addr:housenumber":"41",
    "addr:postcode":"3465",
    "addr:street":"Tuaggra St",
    "iso:country":"AU",
    "sg:address":"41 Tuaggra St",
    "sg:city":"Maryborough",
    "sg:classifiers":[
        {
            "category":"Health Services",
            "subcategory":"Optometrist",
            "type":"Services"
        }
    ],
    "sg:phone":"+61 3 5460 5433",
    "sg:postcode":"3465",
    "sg:province":"VIC",
    "wof:name":"Martonhelyi Renee",
    "wof:placetype":"venue"
},
  "geometry": {"coordinates":[143.73936462399999,-37.0462722778],"type":"Point"}
}