{
  "type": "Feature",
  "properties": {
    "addr:full":"Yorkey&#039;s Knob Rd Smithfield QLD 4350",
    "addr:postcode":"4350",
    "addr:street":"S Knob Rd",
    "iso:country":"AU",
    "sg:address":"Yorkey&#039;s Knob Rd",
    "sg:city":"Smithfield",
    "sg:classifiers":[
        {
            "category":"Farming",
            "subcategory":"Farm",
            "type":"Manufacturing & Wholesale Goods"
        }
    ],
    "sg:phone":"+61 7 4055 7138",
    "sg:postcode":"4350",
    "sg:province":"QLD",
    "sg:tags":[
        "farmer"
    ],
    "wof:name":"Gualtieri M",
    "wof:placetype":"venue"
},
  "geometry": {"coordinates":[151.92860400000001,-27.586323],"type":"Point"}
}