{
  "type": "Feature",
  "properties": {
    "iso:country":"AU",
    "sg:address":"Hollysmith Ave",
    "sg:city":"Moorabbin Airport",
    "sg:classifiers":[
        {
            "category":"Communications",
            "type":"Services"
        }
    ],
    "sg:phone":"+61 3 9580 9666",
    "sg:postcode":"3194",
    "sg:province":"VIC",
    "sg:tags":[
        "equipment",
        "radio"
    ],
    "wof:name":"Australian Two Way Radio Rentals",
    "wof:placetype":"venue"
},
  "geometry": {"coordinates":[145.090576172,-37.9758224487],"type":"Point"}
}