{
  "type": "Feature",
  "properties": {
    "addr:full":"36 Jellico Drv Scoresby VIC 3179",
    "addr:housenumber":"36",
    "addr:postcode":"3179",
    "addr:street":"Jellico Drv",
    "iso:country":"AU",
    "sg:address":"36 Jellico Drv",
    "sg:city":"Scoresby",
    "sg:classifiers":[
        {
            "category":"Home & Garden",
            "subcategory":"Garden Supply",
            "type":"Retail Goods"
        }
    ],
    "sg:phone":"+61 3 9763 8522",
    "sg:postcode":"3179",
    "sg:province":"VIC",
    "sg:tags":[
        "shadecloth"
    ],
    "wof:name":"Kelmatt Australia Pty Ltd",
    "wof:placetype":"venue"
},
  "geometry": {"coordinates":[145.21844482399999,-37.8967666626],"type":"Point"}
}