{
  "type": "Feature",
  "properties": {
    "addr:full":"114 King St Newtown NSW 2042",
    "addr:housenumber":"114",
    "addr:postcode":"2042",
    "addr:street":"King St",
    "iso:country":"AU",
    "sg:address":"114 King St",
    "sg:city":"Newtown",
    "sg:classifiers":[
        {
            "category":"Real Estate",
            "subcategory":"Real Estate Agent",
            "type":"Services"
        }
    ],
    "sg:phone":"+61 2 9565 1211",
    "sg:postcode":"2042",
    "sg:province":"NSW",
    "wof:name":"Inwest Pty Ltd",
    "wof:placetype":"venue"
},
  "geometry": {"coordinates":[151.18412799999999,-33.893311],"type":"Point"}
}