{
  "type": "Feature",
  "properties": {
    "addr:full":"195 Bellarine Hwy Newcomb VIC 3219",
    "addr:housenumber":"195",
    "addr:postcode":"3219",
    "addr:street":"Bellarine Hwy",
    "iso:country":"AU",
    "sg:address":"195 Bellarine Hwy",
    "sg:city":"Newcomb",
    "sg:classifiers":[
        {
            "category":"Travel",
            "subcategory":"Hotels & Motels",
            "type":"Entertainment"
        }
    ],
    "sg:phone":"+61 3 5248 2606",
    "sg:postcode":"3219",
    "sg:province":"VIC",
    "wof:name":"Peninsula Hotel-Motel",
    "wof:placetype":"venue"
},
  "geometry": {"coordinates":[144.39312744099999,-38.170879364],"type":"Point"}
}