{
  "type": "Feature",
  "properties": {
    "addr:full":"176 Fullarton Rd Dulwich SA 5065",
    "addr:housenumber":"176",
    "addr:postcode":"5065",
    "addr:street":"Fullarton Rd",
    "iso:country":"AU",
    "sg:address":"176 Fullarton Rd",
    "sg:city":"Dulwich",
    "sg:classifiers":[
        {
            "category":"Social Services",
            "subcategory":"Retirement Home",
            "type":"Services"
        }
    ],
    "sg:phone":"+61 8 8364 3111",
    "sg:postcode":"5065",
    "sg:province":"SA",
    "sg:tags":[
        "environmental",
        "consultant",
        "pollution"
    ],
    "wof:name":"Hydro Tasmania",
    "wof:placetype":"venue"
},
  "geometry": {"coordinates":[138.624542236,-34.9366493225],"type":"Point"}
}