{
  "type": "Feature",
  "properties": {
    "iso:country":"AU",
    "sg:address":"Unit 1 161 Deakin St",
    "sg:city":"Essendon",
    "sg:classifiers":[
        {
            "category":"Health Services",
            "subcategory":"Nursing And Care Facility",
            "type":"Services"
        }
    ],
    "sg:phone":"+61 3 9379 5344",
    "sg:postcode":"3040",
    "sg:province":"VIC",
    "sg:tags":[
        "home"
    ],
    "wof:name":"Kilbandon Pty Ltd",
    "wof:placetype":"venue"
},
  "geometry": {"coordinates":[144.89326477,-37.7380104065],"type":"Point"}
}