{
  "type": "Feature",
  "properties": {
    "addr:full":"148 Rowe St Eastwood NSW 2122",
    "addr:housenumber":"148",
    "addr:postcode":"2122",
    "addr:street":"Rowe St",
    "iso:country":"AU",
    "sg:address":"148 Rowe St",
    "sg:city":"Eastwood",
    "sg:classifiers":[
        {
            "category":"Health Services",
            "subcategory":"Dentist",
            "type":"Services"
        }
    ],
    "sg:phone":"+61 2 9874 5346",
    "sg:postcode":"2122",
    "sg:province":"NSW",
    "wof:name":"Thomas R B Dr",
    "wof:placetype":"venue"
},
  "geometry": {"coordinates":[151.08172607399999,-33.7915840149],"type":"Point"}
}