{
  "type": "Feature",
  "properties": {
    "addr:full":"Shp 2/ 188 Scarborough St North Southport QLD 4215",
    "addr:housenumber":"/ 188",
    "addr:postcode":"4215",
    "addr:street":"Scarborough St North",
    "iso:country":"AU",
    "sg:address":"Shp 2/ 188 Scarborough St",
    "sg:city":"North Southport",
    "sg:classifiers":[
        {
            "category":"Fast Food",
            "type":"Food & Drink"
        }
    ],
    "sg:phone":"+61 7 5531 0292",
    "sg:postcode":"4215",
    "sg:province":"QLD",
    "sg:tags":[
        "away",
        "take"
    ],
    "wof:name":"Southport Charcoal Chicken",
    "wof:placetype":"venue"
},
  "geometry": {"coordinates":[153.40989685100001,-27.9616851807],"type":"Point"}
}