{
  "type": "Feature",
  "properties": {
    "addr:full":"13 Lillihina Ave Cromer NSW 2099",
    "addr:housenumber":"13",
    "addr:postcode":"2099",
    "addr:street":"Lillihina Ave",
    "iso:country":"AU",
    "sg:address":"13 Lillihina Ave",
    "sg:city":"Cromer",
    "sg:classifiers":[
        {
            "category":"Wholesale",
            "subcategory":"Home Furnishings",
            "type":"Manufacturing & Wholesale Goods"
        }
    ],
    "sg:phone":"+61 2 9981 1151",
    "sg:postcode":"2099",
    "sg:province":"NSW",
    "sg:tags":[
        "wholesaler",
        "mfrs",
        "clock"
    ],
    "wof:name":"Wells J Importers",
    "wof:placetype":"venue"
},
  "geometry": {"coordinates":[151.272872925,-33.7401542664],"type":"Point"}
}