{
  "type": "Feature",
  "properties": {
    "addr:full":"492 Olive St Albury NSW 2640",
    "addr:housenumber":"492",
    "addr:postcode":"2640",
    "addr:street":"Olive St",
    "iso:country":"AU",
    "sg:address":"492 Olive St",
    "sg:city":"Albury",
    "sg:classifiers":[
        {
            "category":"Banks & Credit Unions",
            "subcategory":"Financial Services",
            "type":"Services"
        }
    ],
    "sg:phone":"+61 2 6051 3233",
    "sg:postcode":"2640",
    "sg:province":"NSW",
    "sg:tags":[
        "loan",
        "finance",
        "mortgage"
    ],
    "wof:name":"Hume Building Society",
    "wof:placetype":"venue"
},
  "geometry": {"coordinates":[146.918624878,-36.0794067383],"type":"Point"}
}