{
  "type": "Feature",
  "properties": {
    "iso:country":"AU",
    "sg:address":"Unit 7 217 Mickelham Rd",
    "sg:city":"Tullamarine",
    "sg:classifiers":[
        {
            "category":"Recreation",
            "type":"Entertainment"
        }
    ],
    "sg:phone":"+61 3 9330 0181",
    "sg:postcode":"3043",
    "sg:province":"VIC",
    "sg:tags":[
        "children's",
        "play",
        "programme"
    ],
    "wof:name":"Jump N Jiggle",
    "wof:placetype":"venue"
},
  "geometry": {"coordinates":[144.88238525400001,-37.6854133606],"type":"Point"}
}