{
  "type": "Feature",
  "properties": {
    "addr:full":"118 Argyle St Camden NSW 2570",
    "addr:housenumber":"118",
    "addr:postcode":"2570",
    "addr:street":"Argyle St",
    "iso:country":"AU",
    "sg:address":"118 Argyle St",
    "sg:city":"Camden",
    "sg:classifiers":[
        {
            "category":"Home & Garden",
            "subcategory":"Building Materials",
            "type":"Retail Goods"
        }
    ],
    "sg:phone":"+61 2 4647 0400",
    "sg:postcode":"2570",
    "sg:province":"NSW",
    "sg:tags":[
        "plaster",
        "plasterboard",
        "supply"
    ],
    "wof:name":"Ambleside Bulkheads",
    "wof:placetype":"venue"
},
  "geometry": {"coordinates":[150.69563293499999,-34.0547943115],"type":"Point"}
}