{
  "type": "Feature",
  "properties": {
    "iso:country":"AU",
    "sg:address":"16 Marie St",
    "sg:city":"Milton",
    "sg:classifiers":[
        {
            "category":"Autos & Motor Vehicles",
            "subcategory":"Automobile Sales",
            "type":"Retail Goods"
        }
    ],
    "sg:phone":"+61 7 3369 7333",
    "sg:postcode":"4064",
    "sg:province":"QLD",
    "sg:tags":[
        "car",
        "new"
    ],
    "wof:name":"Westpoint Autos (Qld) Pty Ltd",
    "wof:placetype":"venue"
},
  "geometry": {"coordinates":[153.004196167,-27.4722499847],"type":"Point"}
}