{
  "type": "Feature",
  "properties": {
    "addr:full":"Cnr Lambie & Sydney Sts Tumut NSW 2720",
    "addr:postcode":"2720",
    "addr:street":"Cnr",
    "iso:country":"AU",
    "sg:address":"Cnr Lambie & Sydney Sts",
    "sg:city":"Tumut",
    "sg:classifiers":[
        {
            "category":"Health Services",
            "subcategory":"Nursing And Care Facility",
            "type":"Services"
        }
    ],
    "sg:phone":"+61 2 6947 2844",
    "sg:postcode":"2720",
    "sg:province":"NSW",
    "sg:tags":[
        "home"
    ],
    "wof:name":"Australian Nursing Homes",
    "wof:placetype":"venue"
},
  "geometry": {"coordinates":[148.22105400000001,-35.312614],"type":"Point"}
}