{
  "type": "Feature",
  "properties": {
    "addr:full":"659 Mountain Hwy Bayswater VIC 3153",
    "addr:housenumber":"659",
    "addr:postcode":"3153",
    "addr:street":"Mountain Hwy",
    "iso:country":"AU",
    "sg:address":"659 Mountain Hwy",
    "sg:city":"Bayswater",
    "sg:classifiers":[
        {
            "category":"Autos & Motor Vehicles",
            "subcategory":"Fuel & Gas Station",
            "type":"Retail Goods"
        }
    ],
    "sg:phone":"+61 3 9720 0998",
    "sg:postcode":"3153",
    "sg:province":"VIC",
    "wof:name":"Plus Petrol",
    "wof:placetype":"venue"
},
  "geometry": {"coordinates":[145.26252746599999,-37.8414306641],"type":"Point"}
}