{
  "type": "Feature",
  "properties": {
    "addr:full":"Cnr Dabyshire St & Kororoit Creek Rd Williamstown VIC 3016",
    "addr:postcode":"3016",
    "addr:street":"Cnr Dabyshire St & Kororoit Creek Rd",
    "iso:country":"AU",
    "sg:address":"Cnr Dabyshire St & Kororoit Creek Rd",
    "sg:city":"Williamstown",
    "sg:classifiers":[
        {
            "category":"Manufacturing",
            "subcategory":"Tools & Machinery",
            "type":"Manufacturing & Wholesale Goods"
        }
    ],
    "sg:phone":"+61 3 9391 5088",
    "sg:postcode":"3016",
    "sg:province":"VIC",
    "wof:name":"Econweld",
    "wof:placetype":"venue"
},
  "geometry": {"coordinates":[144.889572144,-37.8579902649],"type":"Point"}
}