{
  "type": "Feature",
  "properties": {
    "addr:full":"4/ 36-40 Stuart Ave Hampton Park VIC 3976",
    "addr:housenumber":"/ 36-40",
    "addr:postcode":"3976",
    "addr:street":"Stuart Ave Hampton",
    "iso:country":"AU",
    "sg:address":"4/ 36-40 Stuart Ave",
    "sg:city":"Hampton Park",
    "sg:classifiers":[
        {
            "category":"Health Services",
            "subcategory":"Health Practitioner",
            "type":"Services"
        }
    ],
    "sg:phone":"+61 3 9799 3751",
    "sg:postcode":"3976",
    "sg:province":"VIC",
    "sg:tags":[
        "physiotherapist"
    ],
    "wof:name":"Eibl Mark",
    "wof:placetype":"venue"
},
  "geometry": {"coordinates":[145.26695251500001,-38.0356369019],"type":"Point"}
}