{
  "type": "Feature",
  "properties": {
    "addr:full":"61 Musgrave Rd Coopers Plains QLD 4108",
    "addr:housenumber":"61",
    "addr:postcode":"4108",
    "addr:street":"Musgrave Rd",
    "iso:country":"AU",
    "sg:address":"61 Musgrave Rd",
    "sg:city":"Coopers Plains",
    "sg:classifiers":[
        {
            "category":"Professional",
            "type":"Services"
        }
    ],
    "sg:phone":"+61 7 3875 2800",
    "sg:postcode":"4108",
    "sg:province":"QLD",
    "sg:tags":[
        "transport"
    ],
    "sg:website":"http://www.mjt.com.au",
    "wof:name":"Malcolm Janke Transport",
    "wof:placetype":"venue"
},
  "geometry": {"coordinates":[153.025756836,-27.561296463],"type":"Point"}
}