{
  "type": "Feature",
  "properties": {
    "addr:full":"3 Pye Pl Farrer ACT 2607",
    "addr:housenumber":"3",
    "addr:postcode":"2607",
    "addr:street":"Pye Pl",
    "iso:country":"AU",
    "sg:address":"3 Pye Pl",
    "sg:city":"Farrer",
    "sg:classifiers":[
        {
            "category":"Building & Trades",
            "subcategory":"Construction",
            "type":"Services"
        }
    ],
    "sg:phone":"+61 2 6286 7066",
    "sg:postcode":"2607",
    "sg:province":"ACT",
    "sg:tags":[
        "renovation",
        "alterations",
        "extension",
        "contractor"
    ],
    "wof:name":"Southside Building Contractors",
    "wof:placetype":"venue"
},
  "geometry": {"coordinates":[149.102127075,-35.3791732788],"type":"Point"}
}