{
  "type": "Feature",
  "properties": {
    "iso:country":"AU",
    "sg:address":"1143 Dandenong Rd",
    "sg:city":"Malvern East",
    "sg:classifiers":[
        {
            "category":"Organizations",
            "subcategory":"Professional Association",
            "type":"Services"
        }
    ],
    "sg:phone":"+61 3 9563 6625",
    "sg:postcode":"3145",
    "sg:province":"VIC",
    "sg:tags":[
        "web",
        "internet"
    ],
    "wof:name":"eWeb-Design.com.au",
    "wof:placetype":"venue"
},
  "geometry": {"coordinates":[145.061203003,-37.8840942383],"type":"Point"}
}