{
  "type": "Feature",
  "properties": {
    "addr:full":"1049 Barrenjoey Rd Palm Beach NSW 2108",
    "addr:housenumber":"1049",
    "addr:postcode":"2108",
    "addr:street":"Barrenjoey Rd",
    "iso:country":"AU",
    "sg:address":"1049 Barrenjoey Rd",
    "sg:city":"Palm Beach",
    "sg:classifiers":[
        {
            "category":"Banks & Credit Unions",
            "subcategory":"Investment Brokerage",
            "type":"Services"
        }
    ],
    "sg:phone":"+61 2 9974 1022",
    "sg:postcode":"2108",
    "sg:province":"NSW",
    "sg:tags":[
        "finance",
        "broker"
    ],
    "wof:name":"Gardiner Finance Pty Ltd",
    "wof:placetype":"venue"
},
  "geometry": {"coordinates":[151.31916809099999,-33.602432251],"type":"Point"}
}