{
  "type": "Feature",
  "properties": {
    "iso:country":"AU",
    "sg:address":"2 Zola Crt",
    "sg:city":"Glen Waverley",
    "sg:classifiers":[
        {
            "category":"Health Services",
            "subcategory":"Health Practitioner",
            "type":"Services"
        }
    ],
    "sg:phone":"+61 3 9886 8085",
    "sg:postcode":"3150",
    "sg:province":"VIC",
    "sg:tags":[
        "consultant",
        "conservation",
        "hearing"
    ],
    "wof:name":"Hearing Protection Services",
    "wof:placetype":"venue"
},
  "geometry": {"coordinates":[145.157806397,-37.8614387512],"type":"Point"}
}