{
  "type": "Feature",
  "properties": {
    "addr:full":"1 Fleet St Albany WA 6330",
    "addr:housenumber":"1",
    "addr:postcode":"6330",
    "addr:street":"Fleet St",
    "iso:country":"AU",
    "sg:address":"1 Fleet St",
    "sg:city":"Albany",
    "sg:classifiers":[
        {
            "category":"Building & Trades",
            "subcategory":"Construction",
            "type":"Services"
        }
    ],
    "sg:phone":"+61 427 429 839",
    "sg:postcode":"6330",
    "sg:province":"WA",
    "sg:tags":[
        "home",
        "air conditioning"
    ],
    "wof:name":"AG Air-Conditioning & Refrigeration",
    "wof:placetype":"venue"
},
  "geometry": {"coordinates":[117.843681335,-35.006275177],"type":"Point"}
}