{
  "type": "Feature",
  "properties": {
    "iso:country":"AU",
    "sg:address":"Wylandra St",
    "sg:city":"Dubbo West",
    "sg:classifiers":[
        {
            "category":"Conference Center",
            "type":"Public Place"
        }
    ],
    "sg:phone":"+61 2 6884 3000",
    "sg:postcode":"2830",
    "sg:province":"NSW",
    "sg:tags":[
        "venue",
        "convention"
    ],
    "sg:website":"http://www.westdubbobowlingclub.com.au",
    "wof:name":"West Dubbo Bowling Club",
    "wof:placetype":"venue"
},
  "geometry": {"coordinates":[148.593582153,-32.2476577759],"type":"Point"}
}