{
  "type": "Feature",
  "properties": {
    "addr:full":"21 Chifley Drv Maribyrnong VIC 3032",
    "addr:housenumber":"21",
    "addr:postcode":"3032",
    "addr:street":"Chifley Drv",
    "iso:country":"AU",
    "sg:address":"21 Chifley Drv",
    "sg:city":"Maribyrnong",
    "sg:classifiers":[
        {
            "category":"Building & Trades",
            "subcategory":"Construction",
            "type":"Services"
        }
    ],
    "sg:phone":"+61 411 299 306",
    "sg:postcode":"3032",
    "sg:province":"VIC",
    "sg:tags":[
        "contractor"
    ],
    "wof:name":"A.B.A Construction",
    "wof:placetype":"venue"
},
  "geometry": {"coordinates":[144.90124499999999,-37.766926],"type":"Point"}
}