{
  "type": "Feature",
  "properties": {
    "addr:full":"Unit 4/ 3 Kent Way Malaga WA 6090",
    "addr:housenumber":"3",
    "addr:postcode":"6090",
    "addr:street":"Kent Way",
    "iso:country":"AU",
    "sg:address":"Unit 4/ 3 Kent Way",
    "sg:city":"Malaga",
    "sg:classifiers":[
        {
            "category":"Professional",
            "subcategory":"Employment Agencies",
            "type":"Services"
        }
    ],
    "sg:phone":"+61 8 9248 5601",
    "sg:postcode":"6090",
    "sg:province":"WA",
    "sg:tags":[
        "hire",
        "labour",
        "contractor"
    ],
    "wof:name":"CCR Group Pty Ltd",
    "wof:placetype":"venue"
},
  "geometry": {"coordinates":[115.881469727,-31.8534431458],"type":"Point"}
}