{
  "type": "Feature",
  "properties": {
    "addr:full":"31 Nantes St Newtown VIC 3220",
    "addr:housenumber":"31",
    "addr:postcode":"3220",
    "addr:street":"Nantes St",
    "iso:country":"AU",
    "sg:address":"31 Nantes St",
    "sg:city":"Newtown",
    "sg:classifiers":[
        {
            "category":"Health Services",
            "subcategory":"Health Practitioner",
            "type":"Services"
        }
    ],
    "sg:phone":"+61 3 5229 7200",
    "sg:postcode":"3220",
    "sg:province":"VIC",
    "sg:tags":[
        "naturopath"
    ],
    "wof:name":"Alternative Health Sciences",
    "wof:placetype":"venue"
},
  "geometry": {"coordinates":[144.331299,-38.147129],"type":"Point"}
}