{
  "type": "Feature",
  "properties": {
    "addr:full":"PO Box 18 Strathpine QLD 4500",
    "addr:postcode":"4500",
    "iso:country":"AU",
    "sg:address":"PO Box 18",
    "sg:city":"Strathpine",
    "sg:classifiers":[
        {
            "category":"Utilities",
            "subcategory":"Refuse",
            "type":"Services"
        }
    ],
    "sg:phone":"+61 7 3205 8415",
    "sg:postcode":"4500",
    "sg:province":"QLD",
    "sg:tags":[
        "disposal",
        "reduction",
        "waste"
    ],
    "wof:name":"Alfa Bins",
    "wof:placetype":"venue"
},
  "geometry": {"coordinates":[152.987823486,-27.3017196655],"type":"Point"}
}