{
  "type": "Feature",
  "properties": {
    "iso:country":"AU",
    "sg:address":"Shop 3/ 535 Toorak Rd",
    "sg:city":"Toorak",
    "sg:classifiers":[
        {
            "category":"Shopping",
            "subcategory":"Antiques",
            "type":"Retail Goods"
        }
    ],
    "sg:phone":"+61 3 9824 0014",
    "sg:postcode":"3142",
    "sg:province":"VIC",
    "wof:name":"Pauline Ewers Toorak Decorative Arts Gallery",
    "wof:placetype":"venue"
},
  "geometry": {"coordinates":[145.01048278799999,-37.8411178589],"type":"Point"}
}