{
  "type": "Feature",
  "properties": {
    "addr:full":"65 Sixth St Home Hill QLD 4806",
    "addr:housenumber":"65",
    "addr:postcode":"4806",
    "addr:street":"Sixth St",
    "iso:country":"AU",
    "sg:address":"65 Sixth St",
    "sg:city":"Home Hill",
    "sg:classifiers":[
        {
            "category":"Professional",
            "subcategory":"Accounting & Tax Preparation",
            "type":"Services"
        }
    ],
    "sg:phone":"+61 7 4795 1463",
    "sg:postcode":"4806",
    "sg:province":"QLD",
    "sg:tags":[
        "bookkeeping"
    ],
    "wof:name":"Jims Bookkeeping Burdekin",
    "wof:placetype":"venue"
},
  "geometry": {"coordinates":[147.418045044,-19.6647109985],"type":"Point"}
}