{
  "type": "Feature",
  "properties": {
    "addr:full":"52 Devitt Ave Payneham South SA 5070",
    "addr:housenumber":"52",
    "addr:postcode":"5070",
    "addr:street":"Devitt Ave",
    "iso:country":"AU",
    "sg:address":"52 Devitt Ave",
    "sg:city":"Payneham South",
    "sg:classifiers":[
        {
            "category":"Deli",
            "type":"Food & Drink"
        }
    ],
    "sg:phone":"+61 8 8331 7008",
    "sg:postcode":"5070",
    "sg:province":"SA",
    "sg:tags":[
        "delicatessen"
    ],
    "wof:name":"Ashbrook Avenue Deli",
    "wof:placetype":"venue"
},
  "geometry": {"coordinates":[138.64607238799999,-34.9072570801],"type":"Point"}
}