{
  "type": "Feature",
  "properties": {
    "addr:full":"Shop 2, 10 Walla St Bundaberg QLD 4670",
    "addr:housenumber":"shop;10",
    "addr:postcode":"4670",
    "addr:street":"Walla St",
    "iso:country":"AU",
    "sg:address":"Shop 2, 10 Walla St",
    "sg:city":"Bundaberg",
    "sg:classifiers":[
        {
            "category":"Building & Trades",
            "subcategory":"Construction",
            "type":"Services"
        }
    ],
    "sg:phone":"+61 7 4153 1970",
    "sg:postcode":"4670",
    "sg:province":"QLD",
    "sg:tags":[
        "window",
        "tinting"
    ],
    "wof:name":"Just Tinting",
    "wof:placetype":"venue"
},
  "geometry": {"coordinates":[152.355667114,-24.8646221161],"type":"Point"}
}