{
  "type": "Feature",
  "properties": {
    "addr:full":"Shop 15, Central Plaza, Waterworth Drive Mt Annan NSW 2567",
    "addr:housenumber":"shop 15",
    "addr:postcode":"2567",
    "addr:street":"Central Plaza Waterworth Drive",
    "iso:country":"AU",
    "sg:address":"Shop 15, Central Plaza, Waterworth Drive",
    "sg:city":"Mt Annan",
    "sg:classifiers":[
        {
            "category":"Personal",
            "subcategory":"Beauty Salon",
            "type":"Services"
        }
    ],
    "sg:phone":"+61 2 4648 2911",
    "sg:postcode":"2567",
    "sg:province":"NSW",
    "sg:tags":[
        "hairdresser"
    ],
    "wof:name":"Hair & Beauty Temptations",
    "wof:placetype":"venue"
},
  "geometry": {"coordinates":[150.77203369099999,-34.0544090271],"type":"Point"}
}