{
  "type": "Feature",
  "properties": {
    "addr:full":"Suite 206 / 220 Pacific Hwy Crows Nest NSW 2065",
    "addr:housenumber":"/ 220",
    "addr:postcode":"2065",
    "addr:street":"Pacific Hwy",
    "iso:country":"AU",
    "sg:address":"Suite 206 / 220 Pacific Hwy",
    "sg:city":"Crows Nest",
    "sg:classifiers":[
        {
            "category":"Banks & Credit Unions",
            "subcategory":"Bureau De Change",
            "type":"Services"
        }
    ],
    "sg:phone":"+61 1300 888 912",
    "sg:postcode":"2065",
    "sg:province":"NSW",
    "sg:tags":[
        "currency",
        "exchange",
        "foreign"
    ],
    "wof:name":"Forex Plus Australia Pty Ltd",
    "wof:placetype":"venue"
},
  "geometry": {"coordinates":[151.198928833,-33.8255310059],"type":"Point"}
}