{
  "type": "Feature",
  "properties": {
    "iso:country":"AU",
    "sg:address":"177 Fitzgerald St",
    "sg:city":"Northam",
    "sg:classifiers":[
        {
            "category":"Health Services",
            "subcategory":"Dentist",
            "type":"Services"
        }
    ],
    "sg:phone":"+61 8 9622 1801",
    "sg:postcode":"6401",
    "sg:province":"WA",
    "wof:name":"Trevor Allen",
    "wof:placetype":"venue"
},
  "geometry": {"coordinates":[116.671302795,-31.6540279388],"type":"Point"}
}