{
  "type": "Feature",
  "properties": {
    "iso:country":"AU",
    "sg:address":"28 Warral St",
    "sg:city":"Duri",
    "sg:phone":"+61 2 6768 0363",
    "sg:postcode":"2344",
    "sg:province":"NSW",
    "wof:name":"Sweetwater Tank Cleaning",
    "wof:placetype":"venue"
},
  "geometry": {"coordinates":[150.81861877399999,-31.2131404877],"type":"Point"}
}