{
  "type": "Feature",
  "properties": {
    "iso:country":"AU",
    "sg:address":"157 Bussell Hwy",
    "sg:city":"Margaret River",
    "sg:classifiers":[
        {
            "category":"Professional",
            "subcategory":"Employment Agencies",
            "type":"Services"
        }
    ],
    "sg:phone":"+61 8 9757 3911",
    "sg:postcode":"6285",
    "sg:province":"WA",
    "wof:name":"Manpower- Margaret River",
    "wof:placetype":"venue"
},
  "geometry": {"coordinates":[115.07396697999999,-33.9543876648],"type":"Point"}
}