{
  "type": "Feature",
  "properties": {
    "iso:country":"AU",
    "sg:address":"Central Ave",
    "sg:city":"Mooroolbark",
    "sg:classifiers":[
        {
            "category":"Education",
            "subcategory":"School",
            "type":"Public Place"
        }
    ],
    "sg:phone":"+61 3 9725 7239",
    "sg:postcode":"3138",
    "sg:province":"VIC",
    "sg:tags":[
        "state",
        "except",
        "nsw"
    ],
    "wof:name":"Mooroolbark Primary",
    "wof:placetype":"venue"
},
  "geometry": {"coordinates":[145.30873107900001,-37.7876815796],"type":"Point"}
}