{
  "type": "Feature",
  "properties": {
    "iso:country":"AU",
    "sg:address":"54 Whiting St",
    "sg:city":"Artarmon",
    "sg:classifiers":[
        {
            "category":"Professional",
            "subcategory":"Art Services",
            "type":"Services"
        }
    ],
    "sg:phone":"+61 2 9901 3388",
    "sg:postcode":"2064",
    "sg:province":"NSW",
    "sg:tags":[
        "graphic",
        "designer"
    ],
    "wof:name":"Black Dog Graphics",
    "wof:placetype":"venue"
},
  "geometry": {"coordinates":[151.181915283,-33.8160247803],"type":"Point"}
}