{
  "type": "Feature",
  "properties": {
    "addr:full":"45 Spanos Rd Silkwood QLD 4856",
    "addr:housenumber":"45",
    "addr:postcode":"4856",
    "addr:street":"Spanos Rd",
    "iso:country":"AU",
    "sg:address":"45 Spanos Rd",
    "sg:city":"Silkwood",
    "sg:classifiers":[
        {
            "category":"Personal",
            "subcategory":"Beauty Salon",
            "type":"Services"
        }
    ],
    "sg:phone":"+61 7 4065 2144",
    "sg:postcode":"4856",
    "sg:province":"QLD",
    "sg:tags":[
        "hairdresser"
    ],
    "wof:name":"Silkwood Hair Inn",
    "wof:placetype":"venue"
},
  "geometry": {"coordinates":[146.02650451700001,-17.7471923828],"type":"Point"}
}