{
  "type": "Feature",
  "properties": {
    "addr:full":"76 Orchardtown Rd New Lambton NSW 2305",
    "addr:housenumber":"76",
    "addr:postcode":"2305",
    "addr:street":"Orchardtown Rd",
    "iso:country":"AU",
    "sg:address":"76 Orchardtown Rd",
    "sg:city":"New Lambton",
    "sg:classifiers":[
        {
            "category":"Personal",
            "subcategory":"Beauty Salon",
            "type":"Services"
        }
    ],
    "sg:phone":"+61 2 4953 9393",
    "sg:postcode":"2305",
    "sg:province":"NSW",
    "sg:tags":[
        "hairdresser"
    ],
    "wof:name":"Hello Gorgeous",
    "wof:placetype":"venue"
},
  "geometry": {"coordinates":[151.70765700000001,-32.934368],"type":"Point"}
}