{
  "type": "Feature",
  "properties": {
    "iso:country":"AU",
    "sg:address":"76 Orchardtown Rd",
    "sg:city":"New Lambton",
    "sg:classifiers":[
        {
            "category":"Personal",
            "subcategory":"Beauty Salon",
            "type":"Services"
        }
    ],
    "sg:phone":"+61 2 4953 9393",
    "sg:postcode":"2305",
    "sg:province":"NSW",
    "sg:tags":[
        "hairdresser"
    ],
    "wof:name":"Hello Gorgeous",
    "wof:placetype":"venue"
},
  "geometry": {"coordinates":[151.707657,-32.934368],"type":"Point"}
}