{
  "type": "Feature",
  "properties": {
    "addr:full":"109a Jetty Rd Glenelg SA 5045",
    "addr:housenumber":"109a",
    "addr:postcode":"5045",
    "addr:street":"Jetty Rd",
    "iso:country":"AU",
    "sg:address":"109a Jetty Rd",
    "sg:city":"Glenelg",
    "sg:classifiers":[
        {
            "category":"Restaurant",
            "type":"Food & Drink"
        }
    ],
    "sg:phone":"+61 8 8376 1366",
    "sg:postcode":"5045",
    "sg:province":"SA",
    "wof:name":"Yakumi Contemporary Japanese Cuisine",
    "wof:placetype":"venue"
},
  "geometry": {"coordinates":[138.51852400000001,-34.979984],"type":"Point"}
}