{
  "type": "Feature",
  "properties": {
    "iso:country":"AU",
    "sg:address":"Third St",
    "sg:city":"Harvey",
    "sg:classifiers":[
        {
            "category":"Juice Bar",
            "subcategory":"None",
            "type":"Food & Drink"
        }
    ],
    "sg:phone":"+61 8 9729 0600",
    "sg:postcode":"6220",
    "sg:province":"WA",
    "sg:tags":[
        "merchant",
        "fruit",
        "processor"
    ],
    "wof:name":"Harvey Fresh",
    "wof:placetype":"venue"
},
  "geometry": {"coordinates":[115.888329,-33.079655],"type":"Point"}
}