{
  "type": "Feature",
  "properties": {
    "iso:country":"AU",
    "sg:address":"145 Long Rd",
    "sg:city":"Eagle Heights",
    "sg:classifiers":[
        {
            "category":"Shopping",
            "subcategory":"Crafts & Fabrics",
            "type":"Retail Goods"
        }
    ],
    "sg:phone":"+61 7 5545 1196",
    "sg:postcode":"4271",
    "sg:province":"QLD",
    "sg:tags":[
        "supply"
    ],
    "wof:name":"Ingrid's Craft",
    "wof:placetype":"venue"
},
  "geometry": {"coordinates":[153.20103454599999,-27.9235153198],"type":"Point"}
}