{
  "type": "Feature",
  "properties": {
    "iso:country":"AU",
    "sg:address":"407 New South Head Rd",
    "sg:city":"Double Bay",
    "sg:classifiers":[
        {
            "category":"Professional",
            "subcategory":"Art Services",
            "type":"Services"
        }
    ],
    "sg:phone":"+61 2 9363 5888",
    "sg:postcode":"2028",
    "sg:province":"NSW",
    "sg:tags":[
        "graphic",
        "designer"
    ],
    "wof:name":"Deva Design",
    "wof:placetype":"venue"
},
  "geometry": {"coordinates":[151.24314880399999,-33.8777503967],"type":"Point"}
}