{
  "type": "Feature",
  "properties": {
    "addr:full":"159a Allison Rd Randwick NSW 2031",
    "addr:housenumber":"159a",
    "addr:postcode":"2031",
    "addr:street":"Allison Rd",
    "iso:country":"AU",
    "sg:address":"159a Allison Rd",
    "sg:city":"Randwick",
    "sg:classifiers":[
        {
            "category":"Health Services",
            "subcategory":"Health Practitioner",
            "type":"Services"
        }
    ],
    "sg:phone":"+61 2 9398 7194",
    "sg:postcode":"2031",
    "sg:province":"NSW",
    "sg:tags":[
        "osteopath"
    ],
    "wof:name":"Watterson N A",
    "wof:placetype":"venue"
},
  "geometry": {"coordinates":[151.239105225,-33.9128265381],"type":"Point"}
}