{
  "type": "Feature",
  "properties": {
    "iso:country":"AU",
    "sg:address":"468 Stuart Hwy",
    "sg:city":"Winnellie",
    "sg:classifiers":[
        {
            "category":"Professional",
            "subcategory":"Detective & Security Services",
            "type":"Services"
        }
    ],
    "sg:phone":"+61 8 8999 9006",
    "sg:postcode":"0820",
    "sg:province":"NT",
    "sg:tags":[
        "equipment",
        "window",
        "doors"
    ],
    "wof:name":"Acacia Property Services",
    "wof:placetype":"venue"
},
  "geometry": {"coordinates":[130.88345336899999,-12.4253253937],"type":"Point"}
}