{
  "type": "Feature",
  "properties": {
    "addr:full":"The Basement 816 Hay St Perth WA 6805",
    "addr:housenumber":"816",
    "addr:postcode":"6805",
    "addr:street":"Hay St",
    "iso:country":"AU",
    "sg:address":"The Basement 816 Hay St",
    "sg:city":"Perth",
    "sg:classifiers":[
        {
            "category":"Shopping",
            "subcategory":"Antiques",
            "type":"Retail Goods"
        }
    ],
    "sg:phone":"+61 8 9322 1828",
    "sg:postcode":"6805",
    "sg:province":"WA",
    "sg:tags":[
        "collectable",
        "memorabilia"
    ],
    "wof:name":"Triking Model Cars",
    "wof:placetype":"venue"
},
  "geometry": {"coordinates":[115.849564,-31.951262],"type":"Point"}
}