{
  "type": "Feature",
  "properties": {
    "iso:country":"AU",
    "sg:address":"19 York St",
    "sg:city":"Taree",
    "sg:classifiers":[
        {
            "category":"Health Services",
            "subcategory":"Doctor",
            "type":"Services"
        }
    ],
    "sg:phone":"+61 2 6552 3162",
    "sg:postcode":"2430",
    "sg:province":"NSW",
    "sg:tags":[
        "medical",
        "practitioner"
    ],
    "wof:name":"Slater,William",
    "wof:placetype":"venue"
},
  "geometry": {"coordinates":[152.455185,-31.909233],"type":"Point"}
}