{
  "type": "Feature",
  "properties": {
    "addr:full":"149 Woniora Rd South Hurstville NSW 2221",
    "addr:housenumber":"149",
    "addr:postcode":"2221",
    "addr:street":"Woniora Rd",
    "iso:country":"AU",
    "sg:address":"149 Woniora Rd",
    "sg:city":"South Hurstville",
    "sg:classifiers":[
        {
            "category":"Personal",
            "type":"Services"
        }
    ],
    "sg:phone":"+61 2 9546 2820",
    "sg:postcode":"2221",
    "sg:province":"NSW",
    "sg:tags":[
        "reducing",
        "treatment",
        "weight"
    ],
    "wof:name":"Philippa Aslanis",
    "wof:placetype":"venue"
},
  "geometry": {"coordinates":[151.107666016,-33.9756393433],"type":"Point"}
}