{
  "type": "Feature",
  "properties": {
    "iso:country":"AU",
    "sg:address":"77 Penda Ave",
    "sg:city":"Gladstone",
    "sg:classifiers":[
        {
            "category":"Utilities",
            "subcategory":"Water",
            "type":"Services"
        }
    ],
    "sg:phone":"+61 7 4978 1282",
    "sg:postcode":"4680",
    "sg:province":"QLD",
    "sg:tags":[
        "cartage"
    ],
    "wof:name":"Cap Coast Water & Truck Hire",
    "wof:placetype":"venue"
},
  "geometry": {"coordinates":[151.22946167000001,-23.8791408539],"type":"Point"}
}