{
  "type": "Feature",
  "properties": {
    "iso:country":"AU",
    "sg:address":"118 Hannan St",
    "sg:city":"Kalgoorlie",
    "sg:classifiers":[
        {
            "category":"Professional",
            "subcategory":"Printing & Photocopies",
            "type":"Services"
        }
    ],
    "sg:phone":"+61 8 9021 7810",
    "sg:postcode":"6430",
    "sg:province":"WA",
    "sg:tags":[
        "textile",
        "clothing"
    ],
    "wof:name":"Goldfields Screen Printing",
    "wof:placetype":"venue"
},
  "geometry": {"coordinates":[121.46750640899999,-30.7518119812],"type":"Point"}
}