{
  "type": "Feature",
  "properties": {
    "iso:country":"AU",
    "sg:address":"Unit 1-3 30-38 Watatah St",
    "sg:city":"Kirrawee",
    "sg:classifiers":[
        {
            "category":"Manufacturing",
            "subcategory":"Building Materials",
            "type":"Manufacturing & Wholesale Goods"
        }
    ],
    "sg:phone":"+61 2 9545 6666",
    "sg:postcode":"2232",
    "sg:province":"NSW",
    "sg:tags":[
        "concrete",
        "product"
    ],
    "wof:name":"Pro Stencil Pty Ltd",
    "wof:placetype":"venue"
},
  "geometry": {"coordinates":[151.075561523,-34.0288543701],"type":"Point"}
}