{
  "type": "Feature",
  "properties": {
    "iso:country":"AU",
    "sg:address":"45 Dorset Drv",
    "sg:city":"Rochedale",
    "sg:classifiers":[
        {
            "category":"Professional",
            "subcategory":"Art Services",
            "type":"Services"
        }
    ],
    "sg:phone":"+61 7 3341 1957",
    "sg:postcode":"4123",
    "sg:province":"QLD",
    "sg:tags":[
        "decorator",
        "painter"
    ],
    "wof:name":"Scanlon W C & A M",
    "wof:placetype":"venue"
},
  "geometry": {"coordinates":[153.13742065400001,-27.6094455719],"type":"Point"}
}