{
  "type": "Feature",
  "properties": {
    "addr:full":"19 Anderson St Werribee VIC 3030",
    "addr:housenumber":"19",
    "addr:postcode":"3030",
    "addr:street":"Anderson St",
    "iso:country":"AU",
    "sg:address":"19 Anderson St",
    "sg:city":"Werribee",
    "sg:classifiers":[
        {
            "category":"Professional",
            "subcategory":"Computer Services",
            "type":"Services"
        }
    ],
    "sg:phone":"+61 3 9742 3555",
    "sg:postcode":"3030",
    "sg:province":"VIC",
    "sg:tags":[
        "repairs",
        "upgrade",
        "equipment"
    ],
    "wof:name":"DTImaging",
    "wof:placetype":"venue"
},
  "geometry": {"coordinates":[144.662048,-37.904655],"type":"Point"}
}