{
  "type": "Feature",
  "properties": {
    "addr:full":"Barnes Drv Kambalda West WA 6444",
    "addr:postcode":"6444",
    "addr:street":"Barnes Drv",
    "iso:country":"AU",
    "sg:address":"Barnes Drv",
    "sg:city":"Kambalda West",
    "sg:classifiers":[
        {
            "category":"Social Services",
            "subcategory":"Child Care",
            "type":"Services"
        }
    ],
    "sg:phone":"+61 8 9027 1287",
    "sg:postcode":"6444",
    "sg:province":"WA",
    "sg:tags":[
        "support",
        "health"
    ],
    "wof:name":"June Crosbie Centre",
    "wof:placetype":"venue"
},
  "geometry": {"coordinates":[121.62109375,-31.2076377869],"type":"Point"}
}