{
  "type": "Feature",
  "properties": {
    "addr:full":"51 Claremont St South Yarra VIC 3141",
    "addr:housenumber":"51",
    "addr:postcode":"3141",
    "addr:street":"Claremont St",
    "iso:country":"AU",
    "sg:address":"51 Claremont St",
    "sg:city":"South Yarra",
    "sg:classifiers":[
        {
            "category":"Real Estate",
            "subcategory":"Real Estate Agent",
            "type":"Services"
        }
    ],
    "sg:phone":"+61 3 9829 9911",
    "sg:postcode":"3141",
    "sg:province":"VIC",
    "wof:name":"Castran John H Pty Ltd",
    "wof:placetype":"venue"
},
  "geometry": {"coordinates":[144.993972778,-37.8362083435],"type":"Point"}
}