{
  "type": "Feature",
  "properties": {
    "iso:country":"AU",
    "sg:address":"Factory 8/ 65-67 Canterbury Rd",
    "sg:city":"Montrose",
    "sg:classifiers":[
        {
            "category":"Autos & Motor Vehicles",
            "subcategory":"Automobile Sales",
            "type":"Retail Goods"
        }
    ],
    "sg:phone":"+61 3 9761 8308",
    "sg:postcode":"3765",
    "sg:province":"VIC",
    "sg:tags":[
        "car",
        "used"
    ],
    "wof:name":"Mustangs of Melbourne",
    "wof:placetype":"venue"
},
  "geometry": {"coordinates":[145.32728576700001,-37.8151245117],"type":"Point"}
}