{
  "type": "Feature",
  "properties": {
    "addr:full":"Shop 2/ 16 Blandford St Grange QLD 4051",
    "addr:housenumber":"shop 2 / 16",
    "addr:postcode":"4051",
    "addr:street":"Blandford St",
    "iso:country":"AU",
    "sg:address":"Shop 2/ 16 Blandford St",
    "sg:city":"Grange",
    "sg:classifiers":[
        {
            "category":"Health Services",
            "subcategory":"Health Practitioner",
            "type":"Services"
        }
    ],
    "sg:phone":"+61 7 3356 6166",
    "sg:postcode":"4051",
    "sg:province":"QLD",
    "sg:tags":[
        "acupuncture"
    ],
    "wof:name":"Hughes Herbal & Acpuncture",
    "wof:placetype":"venue"
},
  "geometry": {"coordinates":[153.00865173299999,-27.4211158752],"type":"Point"}
}