{
  "type": "Feature",
  "properties": {
    "iso:country":"AU",
    "sg:address":"9 Queen Victoria St",
    "sg:city":"Kogarah",
    "sg:classifiers":[
        {
            "category":"Health Services",
            "subcategory":"Doctor",
            "type":"Services"
        }
    ],
    "sg:phone":"+61 2 9588 2719",
    "sg:postcode":"2217",
    "sg:province":"NSW",
    "sg:tags":[
        "medical",
        "practitioner"
    ],
    "wof:name":"Ong B C",
    "wof:placetype":"venue"
},
  "geometry": {"coordinates":[151.13035600000001,-33.961514],"type":"Point"}
}