{
  "type": "Feature",
  "properties": {
    "iso:country":"AU",
    "sg:address":"72- 75 Hedley Rd",
    "sg:city":"Mt Thorley",
    "sg:classifiers":[
        {
            "category":"Building & Trades",
            "subcategory":"Cleaning & Sanitation",
            "type":"Services"
        }
    ],
    "sg:phone":"+61 2 6574 6577",
    "sg:postcode":"2330",
    "sg:province":"NSW",
    "sg:tags":[
        "abrasive",
        "blasting"
    ],
    "wof:name":"Ellavale Engineering",
    "wof:placetype":"venue"
},
  "geometry": {"coordinates":[151.109329,-32.620975],"type":"Point"}
}