{
  "type": "Feature",
  "properties": {
    "addr:full":"755 Corangamite Lake Rd Coragulac VIC 3249",
    "addr:housenumber":"755",
    "addr:postcode":"3249",
    "addr:street":"Corangamite Lake Rd",
    "iso:country":"AU",
    "sg:address":"755 Corangamite Lake Rd",
    "sg:city":"Coragulac",
    "sg:classifiers":[
        {
            "category":"Real Estate",
            "subcategory":"Surveying",
            "type":"Services"
        }
    ],
    "sg:phone":"+61 3 5233 1566",
    "sg:postcode":"3249",
    "sg:province":"VIC",
    "sg:tags":[
        "surveyor",
        "land"
    ],
    "wof:name":"Reed & Reed",
    "wof:placetype":"venue"
},
  "geometry": {"coordinates":[143.52560424800001,-38.262588501],"type":"Point"}
}