{
  "type": "Feature",
  "properties": {
    "iso:country":"AU",
    "sg:address":"104 Semaphore Rd",
    "sg:city":"Semaphore",
    "sg:classifiers":[
        {
            "category":"Fast Food",
            "type":"Food & Drink"
        }
    ],
    "sg:phone":"+61 8 8341 6711",
    "sg:postcode":"5019",
    "sg:province":"SA",
    "sg:tags":[
        "away",
        "take"
    ],
    "wof:name":"Pizza Haven",
    "wof:placetype":"venue"
},
  "geometry": {"coordinates":[138.48687744099999,-34.8396644592],"type":"Point"}
}