{
  "type": "Feature",
  "properties": {
    "addr:full":"2170 Orlando Rd Lambton NSW 2299",
    "addr:housenumber":"2170",
    "addr:postcode":"2299",
    "addr:street":"Orlando Rd",
    "iso:country":"AU",
    "sg:address":"2170 Orlando Rd",
    "sg:city":"Lambton",
    "sg:classifiers":[
        {
            "category":"Building & Trades",
            "subcategory":"Construction",
            "type":"Services"
        }
    ],
    "sg:phone":"+61 2 4957 6601",
    "sg:postcode":"2299",
    "sg:province":"NSW",
    "sg:tags":[
        "contractor"
    ],
    "wof:name":"Industry Database",
    "wof:placetype":"venue"
},
  "geometry": {"coordinates":[151.71736145,-32.917011261],"type":"Point"}
}