{
  "type": "Feature",
  "properties": {
    "addr:full":"49 Neptune St Maryborough QLD 4650",
    "addr:housenumber":"49",
    "addr:postcode":"4650",
    "addr:street":"Neptune St",
    "iso:country":"AU",
    "sg:address":"49 Neptune St",
    "sg:city":"Maryborough",
    "sg:classifiers":[
        {
            "category":"Building & Trades",
            "subcategory":"Construction",
            "type":"Services"
        }
    ],
    "sg:phone":"+61 7 4123 4533",
    "sg:postcode":"4650",
    "sg:province":"QLD",
    "sg:tags":[
        "fencing",
        "contractor"
    ],
    "wof:name":"Paul Hanley Fencing & Paving",
    "wof:placetype":"venue"
},
  "geometry": {"coordinates":[152.68454,-25.526335],"type":"Point"}
}