{
  "type": "Feature",
  "properties": {
    "addr:full":"81- 83 Latrobe Rd Morwell VIC 3840",
    "addr:housenumber":"83",
    "addr:postcode":"3840",
    "addr:street":"Latrobe Rd",
    "iso:country":"AU",
    "sg:address":"81- 83 Latrobe Rd",
    "sg:city":"Morwell",
    "sg:classifiers":[
        {
            "category":"Retail",
            "subcategory":"Auto Repair",
            "type":"Services"
        }
    ],
    "sg:phone":"+61 3 5134 3148",
    "sg:postcode":"3840",
    "sg:province":"VIC",
    "sg:tags":[
        "beater",
        "painter",
        "panel"
    ],
    "wof:name":"Dean J A",
    "wof:placetype":"venue"
},
  "geometry": {"coordinates":[146.395874023,-38.2281532288],"type":"Point"}
}