{
  "type": "Feature",
  "properties": {
    "addr:full":"481- 483 Willoughby Rd Willoughby NSW 2068",
    "addr:housenumber":"483",
    "addr:postcode":"2068",
    "addr:street":"Willoughby Rd",
    "iso:country":"AU",
    "sg:address":"481- 483 Willoughby Rd",
    "sg:city":"Willoughby",
    "sg:classifiers":[
        {
            "category":"Home & Garden",
            "subcategory":"Carpets & Floor Coverings",
            "type":"Retail Goods"
        }
    ],
    "sg:phone":"+61 2 9967 2743",
    "sg:postcode":"2068",
    "sg:province":"NSW",
    "sg:tags":[
        "tile",
        "wall"
    ],
    "wof:name":"Antonino & Carmel Gaudioso T/As Tile Emporium International",
    "wof:placetype":"venue"
},
  "geometry": {"coordinates":[151.19964599599999,-33.808216095],"type":"Point"}
}