{
  "type": "Feature",
  "properties": {
    "addr:full":"9 Anne St Moe VIC 3825",
    "addr:housenumber":"9",
    "addr:postcode":"3825",
    "addr:street":"Anne St",
    "iso:country":"AU",
    "sg:address":"9 Anne St",
    "sg:city":"Moe",
    "sg:classifiers":[
        {
            "category":"Building & Trades",
            "subcategory":"Construction",
            "type":"Services"
        }
    ],
    "sg:phone":"+61 3 5127 1183",
    "sg:postcode":"3825",
    "sg:province":"VIC",
    "sg:tags":[
        "concrete",
        "paving"
    ],
    "wof:name":"O'Meara Concreting",
    "wof:placetype":"venue"
},
  "geometry": {"coordinates":[146.26391599999999,-38.174858],"type":"Point"}
}