{
  "type": "Feature",
  "properties": {
    "addr:full":"Shop 38 Gladstone Central, Dawson Hwy Gladstone QLD 4680",
    "addr:housenumber":"shop 38",
    "addr:postcode":"4680",
    "addr:street":"Dawson Hwy",
    "iso:country":"AU",
    "sg:address":"Shop 38 Gladstone Central, Dawson Hwy",
    "sg:city":"Gladstone",
    "sg:classifiers":[
        {
            "category":"Insurance",
            "subcategory":"Health Insurance",
            "type":"Services"
        }
    ],
    "sg:phone":"+61 13 23 31",
    "sg:postcode":"4680",
    "sg:province":"QLD",
    "wof:name":"Medibank Private",
    "wof:placetype":"venue"
},
  "geometry": {"coordinates":[151.25689697300001,-23.8479690552],"type":"Point"}
}