{
  "type": "Feature",
  "properties": {
    "addr:full":"Unit 4/ 1 Akuna Drv Williamstown North VIC 3016",
    "addr:housenumber":"1",
    "addr:postcode":"3016",
    "addr:street":"Akuna Drv",
    "iso:country":"AU",
    "sg:address":"Unit 4/ 1 Akuna Drv",
    "sg:city":"Williamstown North",
    "sg:classifiers":[
        {
            "category":"Sports & Exercise",
            "subcategory":"Gym",
            "type":"Entertainment"
        }
    ],
    "sg:phone":"+61 3 9397 6199",
    "sg:postcode":"3016",
    "sg:province":"VIC",
    "sg:tags":[
        "personal",
        "trainer",
        "fitness"
    ],
    "wof:name":"Williamstown Personal Training",
    "wof:placetype":"venue"
},
  "geometry": {"coordinates":[144.87597656200001,-37.850189209],"type":"Point"}
}