{
  "type": "Feature",
  "properties": {
    "addr:full":"Unit 1, 18 Livingstone Rd Rockingham WA 6168",
    "addr:housenumber":"18",
    "addr:postcode":"6168",
    "addr:street":"Livingstone Rd",
    "iso:country":"AU",
    "sg:address":"Unit 1, 18 Livingstone Rd",
    "sg:city":"Rockingham",
    "sg:classifiers":[
        {
            "category":"Shopping",
            "subcategory":"Computers & Home Electronics",
            "type":"Retail Goods"
        }
    ],
    "sg:phone":"+61 8 9527 7926",
    "sg:postcode":"6168",
    "sg:province":"WA",
    "sg:tags":[
        "hardware",
        "equipment"
    ],
    "wof:name":"Adtech Computer Systems",
    "wof:placetype":"venue"
},
  "geometry": {"coordinates":[115.74185199999999,-32.286625],"type":"Point"}
}