{
  "type": "Feature",
  "properties": {
    "iso:country":"AU",
    "sg:address":"Mega Blacks Business Cntr 36 Hulme St",
    "sg:city":"Myaree",
    "sg:classifiers":[
        {
            "category":"Food & Beverages",
            "subcategory":"Supermarket",
            "type":"Retail Goods"
        }
    ],
    "sg:phone":"+61 8 9330 9096",
    "sg:postcode":"6154",
    "sg:province":"WA",
    "sg:tags":[
        "grocery",
        "store"
    ],
    "wof:name":"Yee Seng Oriental Supermarket",
    "wof:placetype":"venue"
},
  "geometry": {"coordinates":[115.812576,-32.046013],"type":"Point"}
}