{
  "type": "Feature",
  "properties": {
    "addr:full":"Shop 6 Regent Arcade Fitzroy St Kerang VIC 3579",
    "addr:housenumber":"shop 6",
    "addr:postcode":"3579",
    "addr:street":"Regent Arcade;St",
    "iso:country":"AU",
    "sg:address":"Shop 6 Regent Arcade Fitzroy St",
    "sg:city":"Kerang",
    "sg:classifiers":[
        {
            "category":"Personal",
            "subcategory":"Beauty Salon",
            "type":"Services"
        }
    ],
    "sg:phone":"+61 3 5452 2317",
    "sg:postcode":"3579",
    "sg:province":"VIC",
    "sg:tags":[
        "hairdresser"
    ],
    "wof:name":"Headmasters Unisex Salon",
    "wof:placetype":"venue"
},
  "geometry": {"coordinates":[143.91885375999999,-35.7348175049],"type":"Point"}
}