{
  "type": "Feature",
  "properties": {
    "addr:full":"Shop 4, Picton Town Sq, 150- 158 Argyle St Picton NSW 2571",
    "addr:housenumber":"shop 4;150 158",
    "addr:postcode":"2571",
    "addr:street":"Picton Town Sq;Argyle St",
    "iso:country":"AU",
    "sg:address":"Shop 4, Picton Town Sq, 150- 158 Argyle St",
    "sg:city":"Picton",
    "sg:classifiers":[
        {
            "category":"Retail",
            "subcategory":"Repair Shop",
            "type":"Services"
        }
    ],
    "sg:phone":"+61 2 4677 0455",
    "sg:postcode":"2571",
    "sg:province":"NSW",
    "sg:tags":[
        "mending",
        "clothing",
        "alteration"
    ],
    "wof:name":"Auroras",
    "wof:placetype":"venue"
},
  "geometry": {"coordinates":[150.61119079599999,-34.1699714661],"type":"Point"}
}