{
  "type": "Feature",
  "properties": {
    "addr:full":"928 Gympie Rd Chermside QLD 4032",
    "addr:housenumber":"928",
    "addr:postcode":"qld 4032",
    "addr:street":"Gympie Rd",
    "iso:country":"AU",
    "sg:address":"928 Gympie Rd",
    "sg:city":"Chermside",
    "sg:classifiers":[
        {
            "category":"Professional",
            "subcategory":"Employment Agencies",
            "type":"Services"
        }
    ],
    "sg:phone":"+61 7 3630 5688",
    "sg:postcode":"4032",
    "sg:province":"QLD",
    "wof:name":"Mission Australia",
    "wof:placetype":"venue"
},
  "geometry": {"coordinates":[153.02990700000001,-27.383305],"type":"Point"}
}