{
  "type": "Feature",
  "properties": {
    "iso:country":"AU",
    "sg:address":"97 Gray St",
    "sg:city":"Hamilton",
    "sg:classifiers":[
        {
            "category":"Shopping",
            "subcategory":"Jewelry",
            "type":"Retail Goods"
        }
    ],
    "sg:phone":"+61 3 5571 9922",
    "sg:postcode":"3300",
    "sg:province":"VIC",
    "sg:tags":[
        "jeweller"
    ],
    "wof:name":"Kleins Hamilton",
    "wof:placetype":"venue"
},
  "geometry": {"coordinates":[142.023162842,-37.7436332703],"type":"Point"}
}