{
  "type": "Feature",
  "properties": {
    "addr:full":"577 Lt Collins St Melbourne VIC 3000",
    "addr:housenumber":"577",
    "addr:postcode":"3000",
    "addr:street":"Lt Collins St",
    "iso:country":"AU",
    "sg:address":"577 Lt Collins St",
    "sg:city":"Melbourne",
    "sg:classifiers":[
        {
            "category":"Bars & Pubs",
            "subcategory":"Nightclub",
            "type":"Food & Drink"
        }
    ],
    "sg:phone":"+61 3 9629 3872",
    "sg:postcode":"3000",
    "sg:province":"VIC",
    "sg:tags":[
        "discotheque"
    ],
    "wof:name":"Tatou Bar & Nightclub",
    "wof:placetype":"venue"
},
  "geometry": {"coordinates":[144.970611572,-37.8142967224],"type":"Point"}
}