{
  "type": "Feature",
  "properties": {
    "addr:full":"Suite 2, 138a Church St Brighton VIC 3186",
    "addr:housenumber":"138a",
    "addr:postcode":"3186",
    "addr:street":"Church St",
    "iso:country":"AU",
    "sg:address":"Suite 2, 138a Church St",
    "sg:city":"Brighton",
    "sg:classifiers":[
        {
            "category":"Professional",
            "subcategory":"Employment Agencies",
            "type":"Services"
        }
    ],
    "sg:phone":"+61 3 9592 9923",
    "sg:postcode":"3186",
    "sg:province":"VIC",
    "wof:name":"Advance Personnel",
    "wof:placetype":"venue"
},
  "geometry": {"coordinates":[144.99644470199999,-37.9159317017],"type":"Point"}
}