{
  "type": "Feature",
  "properties": {
    "addr:full":"U1/ 19 Exhibition Drv Malaga WA 6090",
    "addr:housenumber":"19",
    "addr:postcode":"6090",
    "addr:street":"U1 /;Exhibition Drv",
    "iso:country":"AU",
    "sg:address":"U1/ 19 Exhibition Drv",
    "sg:city":"Malaga",
    "sg:classifiers":[
        {
            "category":"Retail",
            "subcategory":"Repair Shop",
            "type":"Services"
        }
    ],
    "sg:phone":"+61 8 9249 6203",
    "sg:postcode":"6090",
    "sg:province":"WA",
    "sg:tags":[
        "upholsterer"
    ],
    "wof:name":"Aemro Furniture Upholstery",
    "wof:placetype":"venue"
},
  "geometry": {"coordinates":[115.8826828,-31.852312088],"type":"Point"}
}