{
  "type": "Feature",
  "properties": {
    "addr:full":"415 Golden Four Drv Tugun QLD 4224",
    "addr:housenumber":"415",
    "addr:postcode":"4224",
    "addr:street":"Golden Four Drv",
    "iso:country":"AU",
    "sg:address":"415 Golden Four Drv",
    "sg:city":"Tugun",
    "sg:classifiers":[
        {
            "category":"Health Services",
            "subcategory":"Chiropractor",
            "type":"Services"
        }
    ],
    "sg:phone":"+61 1800 077 007",
    "sg:postcode":"4224",
    "sg:province":"QLD",
    "wof:name":"Chiropractors' Association Of Australia (QLD) Ltd",
    "wof:placetype":"venue"
},
  "geometry": {"coordinates":[153.49659729000001,-28.1447887421],"type":"Point"}
}