{
  "type": "Feature",
  "properties": {
    "addr:full":"52 Sheriff St Forbes NSW 2871",
    "addr:housenumber":"52",
    "addr:postcode":"2871",
    "addr:street":"Sheriff St",
    "iso:country":"AU",
    "sg:address":"52 Sheriff St",
    "sg:city":"Forbes",
    "sg:classifiers":[
        {
            "category":"Manufacturing",
            "subcategory":"Textiles",
            "type":"Manufacturing & Wholesale Goods"
        }
    ],
    "sg:phone":"+61 2 6851 4270",
    "sg:postcode":"2871",
    "sg:province":"NSW",
    "sg:tags":[
        "knitted",
        "woven",
        "fabric"
    ],
    "wof:name":"Cotton On Cottage",
    "wof:placetype":"venue"
},
  "geometry": {"coordinates":[148.008804,-33.38744],"type":"Point"}
}