{
  "type": "Feature",
  "properties": {
    "addr:full":"3/ 15 Crocker St Rockingham WA 6168",
    "addr:housenumber":"/ 15",
    "addr:postcode":"6168",
    "addr:street":"Crocker St",
    "iso:country":"AU",
    "sg:address":"3/ 15 Crocker St",
    "sg:city":"Rockingham",
    "sg:classifiers":[
        {
            "category":"Building & Trades",
            "subcategory":"Construction",
            "type":"Services"
        }
    ],
    "sg:phone":"+61 8 9434 2646",
    "sg:postcode":"6168",
    "sg:province":"WA",
    "sg:tags":[
        "insulation",
        "contractor"
    ],
    "wof:name":"Natra Fill",
    "wof:placetype":"venue"
},
  "geometry": {"coordinates":[115.74851200000001,-32.275124],"type":"Point"}
}