{
  "type": "Feature",
  "properties": {
    "addr:full":"Shop 7 &#034;The Gas Works&#034; Shakespeare St Mackay QLD 4740",
    "addr:housenumber":"shop 7 & # 034",
    "addr:postcode":"4740",
    "addr:street":"The;Shakespeare St",
    "iso:country":"AU",
    "sg:address":"Shop 7 &#034;The Gas Works&#034; Shakespeare St",
    "sg:city":"Mackay",
    "sg:classifiers":[
        {
            "category":"Real Estate",
            "subcategory":"Real Estate Agent",
            "type":"Services"
        }
    ],
    "sg:phone":"+61 7 4944 0088",
    "sg:postcode":"4740",
    "sg:province":"QLD",
    "wof:name":"L J Hooker",
    "wof:placetype":"venue"
},
  "geometry": {"coordinates":[149.18211400000001,-21.14711],"type":"Point"}
}