{
  "type": "Feature",
  "properties": {
    "addr:full":"Unit 5 14 Porrende St Narellan NSW 2567",
    "addr:housenumber":"14",
    "addr:postcode":"2567",
    "addr:street":"Porrende St",
    "iso:country":"AU",
    "sg:address":"Unit 5 14 Porrende St",
    "sg:city":"Narellan",
    "sg:classifiers":[
        {
            "category":"Wholesale",
            "subcategory":"Machinery & Supplies",
            "type":"Manufacturing & Wholesale Goods"
        }
    ],
    "sg:phone":"+61 404 465 408",
    "sg:postcode":"2567",
    "sg:province":"NSW",
    "wof:name":"Toolequip Industries",
    "wof:placetype":"venue"
},
  "geometry": {"coordinates":[150.72915649399999,-34.0324745178],"type":"Point"}
}