{
  "type": "Feature",
  "properties": {
    "addr:full":"105 Morphett Rd Camden Park SA 5038",
    "addr:housenumber":"105",
    "addr:postcode":"5038",
    "addr:street":"Morphett Rd",
    "iso:country":"AU",
    "sg:address":"105 Morphett Rd",
    "sg:city":"Camden Park",
    "sg:classifiers":[
        {
            "category":"Home & Garden",
            "subcategory":"Building Materials",
            "type":"Retail Goods"
        }
    ],
    "sg:phone":"+61 1300 134 344",
    "sg:postcode":"5038",
    "sg:province":"SA",
    "sg:tags":[
        "insect",
        "screen"
    ],
    "wof:name":"Phantom Screens",
    "wof:placetype":"venue"
},
  "geometry": {"coordinates":[138.53695678700001,-34.9627304077],"type":"Point"}
}