{
  "type": "Feature",
  "properties": {
    "addr:full":"2 Yorketown Rd Edithburgh SA 5583",
    "addr:housenumber":"2",
    "addr:postcode":"5583",
    "addr:street":"Yorketown Rd",
    "iso:country":"AU",
    "sg:address":"2 Yorketown Rd",
    "sg:city":"Edithburgh",
    "sg:classifiers":[
        {
            "category":"Building & Trades",
            "subcategory":"Construction",
            "type":"Services"
        }
    ],
    "sg:phone":"+61 8 8852 6255",
    "sg:postcode":"5583",
    "sg:province":"SA",
    "sg:tags":[
        "excavation",
        "foundation"
    ],
    "wof:name":"Edithburgh Concrete",
    "wof:placetype":"venue"
},
  "geometry": {"coordinates":[137.73951721200001,-35.0805969238],"type":"Point"}
}