{
  "type": "Feature",
  "properties": {
    "addr:full":"94 Bungower Rd Somerville VIC 3912",
    "addr:housenumber":"94",
    "addr:postcode":"3912",
    "addr:street":"Bungower Rd",
    "iso:country":"AU",
    "sg:address":"94 Bungower Rd",
    "sg:city":"Somerville",
    "sg:classifiers":[
        {
            "category":"Farming",
            "subcategory":"Nursery",
            "type":"Manufacturing & Wholesale Goods"
        }
    ],
    "sg:phone":"+61 3 5977 9277",
    "sg:postcode":"3912",
    "sg:province":"VIC",
    "wof:name":"Caroles Garden Clematis Nurseries",
    "wof:placetype":"venue"
},
  "geometry": {"coordinates":[145.19467163100001,-38.2384376526],"type":"Point"}
}