{
  "type": "Feature",
  "properties": {
    "iso:country":"AU",
    "sg:address":"Blyth Ave",
    "sg:city":"Gracemere",
    "sg:classifiers":[
        {
            "category":"Farming",
            "subcategory":"Farm",
            "type":"Manufacturing & Wholesale Goods"
        }
    ],
    "sg:phone":"+61 7 4933 1314",
    "sg:postcode":"4702",
    "sg:province":"QLD",
    "sg:tags":[
        "farmer"
    ],
    "wof:name":"Johnson E C & M M",
    "wof:placetype":"venue"
},
  "geometry": {"coordinates":[150.45863342300001,-23.4270191193],"type":"Point"}
}