{
  "type": "Feature",
  "properties": {
    "addr:full":"11 Curtis Pl Kings Park NSW 2148",
    "addr:housenumber":"11",
    "addr:postcode":"2148",
    "addr:street":"Curtis Pl",
    "iso:country":"AU",
    "sg:address":"11 Curtis Pl",
    "sg:city":"Kings Park",
    "sg:classifiers":[
        {
            "category":"Personal",
            "type":"Services"
        }
    ],
    "sg:phone":"+61 2 8577 2204",
    "sg:postcode":"2148",
    "sg:province":"NSW",
    "sg:tags":[
        "reducing",
        "treatment",
        "weight"
    ],
    "wof:name":"Herbalife Australasia Pty Ltd",
    "wof:placetype":"venue"
},
  "geometry": {"coordinates":[150.906936645,-33.7388572693],"type":"Point"}
}