{
  "type": "Feature",
  "properties": {
    "iso:country":"AU",
    "sg:address":"U7/ 34 Chapman Rd",
    "sg:city":"Hackham",
    "sg:classifiers":[
        {
            "category":"Building & Trades",
            "subcategory":"Cleaning & Sanitation",
            "type":"Services"
        }
    ],
    "sg:phone":"+61 8 8186 5788",
    "sg:postcode":"5163",
    "sg:province":"SA",
    "sg:tags":[
        "commercial",
        "maintenance"
    ],
    "wof:name":"S & M Joinery Pty Ltd",
    "wof:placetype":"venue"
},
  "geometry": {"coordinates":[138.52897644000001,-35.1531867981],"type":"Point"}
}