{
  "type": "Feature",
  "properties": {
    "addr:full":"1095 Gold Coast Hwy Palm Beach QLD 4221",
    "addr:housenumber":"1095",
    "addr:postcode":"4221",
    "addr:street":"Gold Coast Hwy",
    "iso:country":"AU",
    "sg:address":"1095 Gold Coast Hwy",
    "sg:city":"Palm Beach",
    "sg:classifiers":[
        {
            "category":"Real Estate",
            "subcategory":"Real Estate Agent",
            "type":"Services"
        }
    ],
    "sg:phone":"+61 7 5534 5050",
    "sg:postcode":"4221",
    "sg:province":"QLD",
    "wof:name":"Harcourts Queensland Pty Ltd",
    "wof:placetype":"venue"
},
  "geometry": {"coordinates":[153.471801758,-28.1192779541],"type":"Point"}
}