{
  "type": "Feature",
  "properties": {
    "addr:full":"55 Five Islands Rd Port Kembla NSW 2505",
    "addr:housenumber":"55",
    "addr:postcode":"2505",
    "addr:street":"Five Islands Rd",
    "iso:country":"AU",
    "sg:address":"55 Five Islands Rd",
    "sg:city":"Port Kembla",
    "sg:classifiers":[
        {
            "category":"Home & Garden",
            "subcategory":"Hardware",
            "type":"Retail Goods"
        }
    ],
    "sg:phone":"+61 13 15 52",
    "sg:postcode":"2505",
    "sg:province":"NSW",
    "sg:tags":[
        "generating",
        "set",
        "generator"
    ],
    "wof:name":"Coates Hire",
    "wof:placetype":"venue"
},
  "geometry": {"coordinates":[150.89591999999999,-34.478306],"type":"Point"}
}