{
  "type": "Feature",
  "properties": {
    "iso:country":"AU",
    "sg:address":"137 Railway Pl",
    "sg:city":"Williamstown",
    "sg:classifiers":[
        {
            "category":"Retail",
            "subcategory":"Veterinary Services",
            "type":"Services"
        }
    ],
    "sg:phone":"+61 3 9397 8002",
    "sg:postcode":"3016",
    "sg:province":"VIC",
    "sg:tags":[
        "surgeon"
    ],
    "wof:name":"Payne Robert J. Dr",
    "wof:placetype":"venue"
},
  "geometry": {"coordinates":[144.88983154300001,-37.8583717346],"type":"Point"}
}