{
  "type": "Feature",
  "properties": {
    "iso:country":"AU",
    "sg:address":"59 Azalea Ave",
    "sg:city":"Mill Park",
    "sg:classifiers":[
        {
            "category":"Education",
            "subcategory":"Kindergarten",
            "type":"Public Place"
        }
    ],
    "sg:phone":"+61 3 9404 4787",
    "sg:postcode":"3082",
    "sg:province":"VIC",
    "sg:tags":[
        "pre-schools"
    ],
    "wof:name":"Blossom Park Kindergarten Inc",
    "wof:placetype":"venue"
},
  "geometry": {"coordinates":[145.076339722,-37.6707954407],"type":"Point"}
}