{
  "type": "Feature",
  "properties": {
    "addr:full":"50 Carew St Deniliquin NSW 2710",
    "addr:housenumber":"50",
    "addr:postcode":"2710",
    "addr:street":"Carew St",
    "iso:country":"AU",
    "sg:address":"50 Carew St",
    "sg:city":"Deniliquin",
    "sg:classifiers":[
        {
            "category":"Building & Trades",
            "subcategory":"Construction",
            "type":"Services"
        }
    ],
    "sg:phone":"+61 3 5881 3384",
    "sg:postcode":"2710",
    "sg:province":"NSW",
    "sg:tags":[
        "contractor"
    ],
    "wof:name":"Nolan Tim",
    "wof:placetype":"venue"
},
  "geometry": {"coordinates":[144.97261047399999,-35.5509872437],"type":"Point"}
}