{
  "type": "Feature",
  "properties": {
    "addr:full":"Fcty 11/ 67 Garden Drv Tullamarine VIC 3043",
    "addr:housenumber":"11 / 67",
    "addr:postcode":"3043",
    "addr:street":"Garden Drv",
    "iso:country":"AU",
    "sg:address":"Fcty 11/ 67 Garden Drv",
    "sg:city":"Tullamarine",
    "sg:classifiers":[
        {
            "category":"Professional",
            "subcategory":"Art Services",
            "type":"Services"
        }
    ],
    "sg:phone":"+61 3 9338 2370",
    "sg:postcode":"3043",
    "sg:province":"VIC",
    "sg:tags":[
        "decorator",
        "painter"
    ],
    "wof:name":"T Jays Painting & Maintenance Contractors",
    "wof:placetype":"venue"
},
  "geometry": {"coordinates":[144.87614440900001,-37.689453125],"type":"Point"}
}