{
  "type": "Feature",
  "properties": {
    "iso:country":"AU",
    "sg:address":"Maryland Rd",
    "sg:city":"Thulimbah",
    "sg:classifiers":[
        {
            "category":"Parking",
            "subcategory":"Lot",
            "type":"Transportation"
        }
    ],
    "sg:phone":"+61 7 4683 2207",
    "sg:postcode":"4376",
    "sg:province":"QLD",
    "sg:tags":[
        "vegetable",
        "packing",
        "fruit",
        "pack"
    ],
    "wof:name":"G & J Mattiazzi Pty Ltd T/A The Stanthorpe Apple Shed",
    "wof:placetype":"venue"
},
  "geometry": {"coordinates":[151.95233154300001,-28.550409317],"type":"Point"}
}