{
  "type": "Feature",
  "properties": {
    "addr:full":"Bungana Ave Perth Airport WA 6105",
    "addr:postcode":"6105",
    "addr:street":"Bungana Ave",
    "iso:country":"AU",
    "sg:address":"Bungana Ave",
    "sg:city":"Perth Airport",
    "sg:classifiers":[
        {
            "category":"Airport",
            "subcategory":"General Aviation",
            "type":"Transportation"
        }
    ],
    "sg:phone":"+61 1800 808 545",
    "sg:postcode":"6105",
    "sg:province":"WA",
    "sg:tags":[
        "helicopter"
    ],
    "wof:name":"Helicopters (Australia) Pty Ltd",
    "wof:placetype":"venue"
},
  "geometry": {"coordinates":[115.95671081499999,-31.9261512756],"type":"Point"}
}