{
  "type": "Feature",
  "properties": {
    "addr:full":"466 Mt Dandenong Rd Kilsyth VIC 3137",
    "addr:housenumber":"466",
    "addr:postcode":"3137",
    "addr:street":"Mt Dandenong Rd",
    "iso:country":"AU",
    "sg:address":"466 Mt Dandenong Rd",
    "sg:city":"Kilsyth",
    "sg:classifiers":[
        {
            "category":"Health Services",
            "subcategory":"Dentist",
            "type":"Services"
        }
    ],
    "sg:phone":"+61 3 9723 2648",
    "sg:postcode":"3137",
    "sg:province":"VIC",
    "wof:name":"Cary James B & Maginness Keith T",
    "wof:placetype":"venue"
},
  "geometry": {"coordinates":[145.307769775,-37.8018722534],"type":"Point"}
}