{
  "type": "Feature",
  "properties": {
    "iso:country":"AU",
    "sg:address":"1112 Benetook Ave",
    "sg:city":"Mildura",
    "sg:classifiers":[
        {
            "category":"Wholesale",
            "subcategory":"Metals & Minerals",
            "type":"Manufacturing & Wholesale Goods"
        }
    ],
    "sg:phone":"+61 3 5023 5944",
    "sg:postcode":"3500",
    "sg:province":"VIC",
    "sg:tags":[
        "steel",
        "merchant"
    ],
    "wof:name":"OneSteel Metaland",
    "wof:placetype":"venue"
},
  "geometry": {"coordinates":[142.17098999000001,-34.2030029297],"type":"Point"}
}