{
  "type": "Feature",
  "properties": {
    "addr:full":"71 Hall St Bondi Beach NSW 2026",
    "addr:housenumber":"71",
    "addr:postcode":"2026",
    "addr:street":"Hall St",
    "iso:country":"AU",
    "sg:address":"71 Hall St",
    "sg:city":"Bondi Beach",
    "sg:classifiers":[
        {
            "category":"Shopping",
            "subcategory":"Clothing, Apparel, & Fashions",
            "type":"Retail Goods"
        }
    ],
    "sg:phone":"+61 2 9365 6855",
    "sg:postcode":"2026",
    "sg:province":"NSW",
    "sg:tags":[
        "lady",
        "wear"
    ],
    "wof:name":"Venetia Elaine",
    "wof:placetype":"venue"
},
  "geometry": {"coordinates":[151.27403259299999,-33.8913116455],"type":"Point"}
}