{
  "type": "Feature",
  "properties": {
    "addr:full":"Cnr Capel Ave & Pt Nepean Rd Rosebud West VIC 3940",
    "addr:postcode":"3940",
    "addr:street":"Capel Ave & Pt Nepean Rd",
    "iso:country":"AU",
    "sg:address":"Cnr Capel Ave & Pt Nepean Rd",
    "sg:city":"Rosebud West",
    "sg:classifiers":[
        {
            "category":"Professional",
            "subcategory":"Business Services",
            "type":"Services"
        }
    ],
    "sg:phone":"+61 3 5986 7677",
    "sg:postcode":"3940",
    "sg:province":"VIC",
    "sg:tags":[
        "drafting"
    ],
    "wof:name":"Long Beach Building Design & Drafting",
    "wof:placetype":"venue"
},
  "geometry": {"coordinates":[144.877243042,-38.3653297424],"type":"Point"}
}