{
  "type": "Feature",
  "properties": {
    "iso:country":"AU",
    "sg:address":"Shop 10 Mons Rd",
    "sg:city":"Forest Glen",
    "sg:classifiers":[
        {
            "category":"Food & Beverages",
            "subcategory":"Supermarket",
            "type":"Retail Goods"
        }
    ],
    "sg:phone":"+61 7 5445 6055",
    "sg:postcode":"4556",
    "sg:province":"QLD",
    "sg:tags":[
        "grocery",
        "store"
    ],
    "wof:name":"Forrest Glen 727 Supermarket",
    "wof:placetype":"venue"
},
  "geometry": {"coordinates":[153.01319885300001,-26.6885147095],"type":"Point"}
}