{
  "type": "Feature",
  "properties": {
    "iso:country":"AU",
    "sg:address":"1419 Botany Rd",
    "sg:city":"Botany",
    "sg:classifiers":[
        {
            "category":"Health Services",
            "subcategory":"Doctor",
            "type":"Services"
        }
    ],
    "sg:phone":"+61 2 9700 1115",
    "sg:postcode":"2019",
    "sg:province":"NSW",
    "sg:tags":[
        "medical",
        "practitioner"
    ],
    "wof:name":"Tuon Hunter",
    "wof:placetype":"venue"
},
  "geometry": {"coordinates":[151.19647216800001,-33.944316864],"type":"Point"}
}