{
  "type": "Feature",
  "properties": {
    "addr:full":"718 Fifteenth St Mildura VIC 3500",
    "addr:housenumber":"718",
    "addr:postcode":"3500",
    "addr:street":"Fifteenth St",
    "iso:country":"AU",
    "sg:address":"718 Fifteenth St",
    "sg:city":"Mildura",
    "sg:classifiers":[
        {
            "category":"Manufacturing",
            "subcategory":"Motor Vehicles & Parts",
            "type":"Manufacturing & Wholesale Goods"
        }
    ],
    "sg:phone":"+61 3 5023 8888",
    "sg:postcode":"3500",
    "sg:province":"VIC",
    "sg:tags":[
        "replacement"
    ],
    "wof:name":"Autobarn",
    "wof:placetype":"venue"
},
  "geometry": {"coordinates":[142.146362305,-34.2148132324],"type":"Point"}
}