{
  "type": "Feature",
  "properties": {
    "iso:country":"AU",
    "sg:address":"94 Valentine Ave",
    "sg:city":"Dianella",
    "sg:classifiers":[
        {
            "category":"Health Services",
            "subcategory":"Medical Lab",
            "type":"Services"
        }
    ],
    "sg:phone":"+61 8 9275 9898",
    "sg:postcode":"6059",
    "sg:province":"WA",
    "sg:tags":[
        "laboratory",
        "dental"
    ],
    "wof:name":"Leidolf Dental Laboratory",
    "wof:placetype":"venue"
},
  "geometry": {"coordinates":[115.882606506,-31.8921337128],"type":"Point"}
}