{
  "type": "Feature",
  "properties": {
    "addr:full":"Unit 2/ 31 Carter Rd Brookvale NSW 2100",
    "addr:housenumber":"31",
    "addr:postcode":"2100",
    "addr:street":"Carter Rd",
    "iso:country":"AU",
    "sg:address":"Unit 2/ 31 Carter Rd",
    "sg:city":"Brookvale",
    "sg:classifiers":[
        {
            "category":"Communications",
            "type":"Services"
        }
    ],
    "sg:phone":"+61 2 9938 6603",
    "sg:postcode":"2100",
    "sg:province":"NSW",
    "sg:tags":[
        "public",
        "system",
        "address"
    ],
    "wof:name":"IJS Logistics",
    "wof:placetype":"venue"
},
  "geometry": {"coordinates":[151.279006958,-33.7611808777],"type":"Point"}
}