{
  "type": "Feature",
  "properties": {
    "addr:full":"Lvl 3, 321 Kent St Sydney NSW 2000",
    "addr:housenumber":"321",
    "addr:postcode":"2000",
    "addr:street":"Kent St",
    "iso:country":"AU",
    "sg:address":"Lvl 3, 321 Kent St",
    "sg:city":"Sydney",
    "sg:classifiers":[
        {
            "category":"Health Services",
            "subcategory":"Doctor",
            "type":"Services"
        }
    ],
    "sg:phone":"+61 2 9221 9398",
    "sg:postcode":"2000",
    "sg:province":"NSW",
    "sg:tags":[
        "medical",
        "practitioner"
    ],
    "wof:name":"Dr Alison Gee",
    "wof:placetype":"venue"
},
  "geometry": {"coordinates":[151.20433044399999,-33.8676681519],"type":"Point"}
}