{
  "type": "Feature",
  "properties": {
    "iso:country":"AU",
    "sg:address":"111 Main St",
    "sg:city":"Bridport",
    "sg:classifiers":[
        {
            "category":"Shopping",
            "subcategory":"Clothing, Apparel, & Fashions",
            "type":"Retail Goods"
        }
    ],
    "sg:phone":"+61 3 6356 1453",
    "sg:postcode":"7262",
    "sg:province":"TAS",
    "sg:tags":[
        "lady",
        "wear"
    ],
    "wof:name":"Fashion By Gadd",
    "wof:placetype":"venue"
},
  "geometry": {"coordinates":[147.391769,-41.001137],"type":"Point"}
}