{
  "type": "Feature",
  "properties": {
    "addr:full":"Unit 3/ 82 Maribyrnong St Footscray VIC 3011",
    "addr:postcode":"3011",
    "addr:street":"Maribyrnong St",
    "iso:country":"AU",
    "sg:address":"Unit 3/ 82 Maribyrnong St",
    "sg:city":"Footscray",
    "sg:classifiers":[
        {
            "category":"Food & Beverages",
            "subcategory":"Groceries & Convenience Stores",
            "type":"Retail Goods"
        }
    ],
    "sg:phone":"+61 3 9596 5122",
    "sg:postcode":"3011",
    "sg:province":"VIC",
    "wof:name":"Sassy Foods",
    "wof:placetype":"venue"
},
  "geometry": {"coordinates":[144.90603637699999,-37.8071975708],"type":"Point"}
}