{
  "type": "Feature",
  "properties": {
    "addr:full":"945a Charlicks Rd Crafers SA 5152",
    "addr:housenumber":"945a",
    "addr:postcode":"5152",
    "addr:street":"Charlicks Rd",
    "iso:country":"AU",
    "sg:address":"945a Charlicks Rd",
    "sg:city":"Crafers",
    "sg:classifiers":[
        {
            "category":"Banks & Credit Unions",
            "subcategory":"Financial Services",
            "type":"Services"
        }
    ],
    "sg:phone":"+61 8 8370 9686",
    "sg:postcode":"5152",
    "sg:province":"SA",
    "sg:tags":[
        "advisory",
        "planning",
        "retirement"
    ],
    "wof:name":"Moneytrends",
    "wof:placetype":"venue"
},
  "geometry": {"coordinates":[138.69346618599999,-34.9931983948],"type":"Point"}
}