{
  "type": "Feature",
  "properties": {
    "addr:full":"1/ 2 Walcott St Mt Lawley WA 6050",
    "addr:housenumber":"/ 2",
    "addr:postcode":"6050",
    "addr:street":"Walcott St",
    "iso:country":"AU",
    "sg:address":"1/ 2 Walcott St",
    "sg:city":"Mt Lawley",
    "sg:classifiers":[
        {
            "category":"Home & Garden",
            "subcategory":"Building Materials",
            "type":"Retail Goods"
        }
    ],
    "sg:phone":"+61 8 9371 3877",
    "sg:postcode":"6050",
    "sg:province":"WA",
    "sg:tags":[
        "restoration",
        "supply"
    ],
    "wof:name":"Clinton Long Project Management Pty Ltd",
    "wof:placetype":"venue"
},
  "geometry": {"coordinates":[115.876792908,-31.9381313324],"type":"Point"}
}