{
  "type": "Feature",
  "properties": {
    "addr:full":"Shop2/ 689 Burke Rd Hawthorn East VIC 3123",
    "addr:housenumber":"689",
    "addr:postcode":"3123",
    "addr:street":"Burke Rd",
    "iso:country":"AU",
    "sg:address":"Shop2/ 689 Burke Rd",
    "sg:city":"Hawthorn East",
    "sg:classifiers":[
        {
            "category":"Cafe",
            "type":"Food & Drink"
        }
    ],
    "sg:phone":"+61 3 9804 0933",
    "sg:postcode":"3123",
    "sg:province":"VIC",
    "wof:name":"Sweet Shonas Fine Food Cafe",
    "wof:placetype":"venue"
},
  "geometry": {"coordinates":[145.05622863799999,-37.8329353333],"type":"Point"}
}