{
  "type": "Feature",
  "properties": {
    "addr:full":"19 Abbott Crs Malak NT 0812",
    "addr:housenumber":"19",
    "addr:postcode":"nt 0812",
    "addr:street":"Abbott Crs",
    "iso:country":"AU",
    "sg:address":"19 Abbott Crs",
    "sg:city":"Malak",
    "sg:classifiers":[
        {
            "category":"Building & Trades",
            "subcategory":"Equipment Rental",
            "type":"Services"
        }
    ],
    "sg:phone":"+61 424 450 124",
    "sg:postcode":"0812",
    "sg:province":"NT",
    "sg:tags":[
        "crane",
        "hire"
    ],
    "wof:name":"P & C Trewin",
    "wof:placetype":"venue"
},
  "geometry": {"coordinates":[130.90194700000001,-12.39768],"type":"Point"}
}