{
  "type": "Feature",
  "properties": {
    "addr:full":"7 Watting St Abbotsbury NSW 2176",
    "addr:housenumber":"7",
    "addr:postcode":"2176",
    "addr:street":"Watting St",
    "iso:country":"AU",
    "sg:address":"7 Watting St",
    "sg:city":"Abbotsbury",
    "sg:classifiers":[
        {
            "category":"Personal",
            "type":"Services"
        }
    ],
    "sg:phone":"+61 2 9434 6174",
    "sg:postcode":"2176",
    "sg:province":"NSW",
    "sg:tags":[
        "reducing",
        "treatment",
        "weight"
    ],
    "wof:name":"Violet Hanani",
    "wof:placetype":"venue"
},
  "geometry": {"coordinates":[150.86451721200001,-33.8667106628],"type":"Point"}
}