{
  "type": "Feature",
  "properties": {
    "iso:country":"AU",
    "sg:address":"178 Musgrave Rd",
    "sg:city":"Red Hill",
    "sg:classifiers":[
        {
            "category":"Professional",
            "subcategory":"Business Services",
            "type":"Services"
        }
    ],
    "sg:phone":"+61 7 3368 3918",
    "sg:postcode":"4059",
    "sg:province":"QLD",
    "sg:tags":[
        "fashion",
        "agent"
    ],
    "wof:name":"Danielle Lee Agencies Pty Ltd",
    "wof:placetype":"venue"
},
  "geometry": {"coordinates":[153.006149292,-27.4541969299],"type":"Point"}
}