{
  "type": "Feature",
  "properties": {
    "iso:country":"AU",
    "sg:address":"5 Stewart St",
    "sg:city":"Richmond",
    "sg:classifiers":[
        {
            "category":"Real Estate",
            "subcategory":"Developer",
            "type":"Services"
        }
    ],
    "sg:phone":"+61 3 9425 9443",
    "sg:postcode":"3121",
    "sg:province":"VIC",
    "sg:tags":[
        "development"
    ],
    "wof:name":"Mantello Holdings Pty Ltd",
    "wof:placetype":"venue"
},
  "geometry": {"coordinates":[144.989837647,-37.8234405518],"type":"Point"}
}