{
  "type": "Feature",
  "properties": {
    "addr:full":"PO Box 5257 East Lismore NSW 2480",
    "addr:postcode":"2480",
    "iso:country":"AU",
    "sg:address":"PO Box 5257",
    "sg:city":"East Lismore",
    "sg:classifiers":[
        {
            "category":"Structure",
            "subcategory":"Office Building",
            "type":"Public Place"
        }
    ],
    "sg:phone":"+61 415 833 401",
    "sg:postcode":"2480",
    "sg:province":"NSW",
    "sg:tags":[
        "tie",
        "concrete",
        "formwork",
        "form",
        "accessory"
    ],
    "wof:name":"A & A Lawson Concreting",
    "wof:placetype":"venue"
},
  "geometry": {"coordinates":[153.291381836,-28.8213405609],"type":"Point"}
}