{
  "type": "Feature",
  "properties": {
    "iso:country":"AU",
    "sg:address":"Shp3/ 3-5 Hewish Rd",
    "sg:city":"Croydon",
    "sg:classifiers":[
        {
            "category":"Sports & Exercise",
            "subcategory":"Gym",
            "type":"Entertainment"
        }
    ],
    "sg:phone":"+61 3 9723 3299",
    "sg:postcode":"3136",
    "sg:province":"VIC",
    "sg:tags":[
        "health",
        "fitness"
    ],
    "wof:name":"Vibro Mania",
    "wof:placetype":"venue"
},
  "geometry": {"coordinates":[145.28225707999999,-37.7959976196],"type":"Point"}
}