{
  "type": "Feature",
  "properties": {
    "addr:full":"Suite 3/ 34 McLachlan St Darwin NT 0800",
    "addr:housenumber":"34",
    "addr:postcode":"nt 0800",
    "addr:street":"Mclachlan St",
    "iso:country":"AU",
    "sg:address":"Suite 3/ 34 McLachlan St",
    "sg:city":"Darwin",
    "sg:classifiers":[
        {
            "category":"Insurance",
            "subcategory":"Insurance Agent",
            "type":"Services"
        }
    ],
    "sg:phone":"+61 8 8981 6377",
    "sg:postcode":"0800",
    "sg:province":"NT",
    "sg:tags":[
        "broker"
    ],
    "wof:name":"AFA General Insurance Brokers",
    "wof:placetype":"venue"
},
  "geometry": {"coordinates":[130.83970642099999,-12.4577188492],"type":"Point"}
}