{
  "type": "Feature",
  "properties": {
    "addr:full":"91 York St Sale VIC 3850",
    "addr:housenumber":"91",
    "addr:postcode":"3850",
    "addr:street":"York St",
    "iso:country":"AU",
    "sg:address":"91 York St",
    "sg:city":"Sale",
    "sg:classifiers":[
        {
            "category":"Travel",
            "subcategory":"Hotels & Motels",
            "type":"Entertainment"
        }
    ],
    "sg:phone":"+61 3 5144 1444",
    "sg:postcode":"3850",
    "sg:province":"VIC",
    "wof:name":"Midtown Motor Inn",
    "wof:placetype":"venue"
},
  "geometry": {"coordinates":[147.068115234,-38.111164093],"type":"Point"}
}