{
  "type": "Feature",
  "properties": {
    "iso:country":"AU",
    "sg:address":"217- 219 Elizabeth St",
    "sg:city":"Hobart",
    "sg:classifiers":[
        {
            "category":"Bars & Pubs",
            "subcategory":"Nightclub",
            "type":"Food & Drink"
        }
    ],
    "sg:phone":"+61 3 6234 9133",
    "sg:postcode":"7000",
    "sg:province":"TAS",
    "sg:tags":[
        "discotheque"
    ],
    "wof:name":"Lizbon Wine Bar",
    "wof:placetype":"venue"
},
  "geometry": {"coordinates":[147.321075439,-42.8783683777],"type":"Point"}
}