{
  "type": "Feature",
  "properties": {
    "iso:country":"AU",
    "sg:address":"Shop T218, Erina Fair, Terrigal Drv",
    "sg:city":"Erina",
    "sg:classifiers":[
        {
            "category":"Shopping",
            "subcategory":"Clothing, Apparel, & Fashions",
            "type":"Retail Goods"
        }
    ],
    "sg:phone":"+61 2 4365 0248",
    "sg:postcode":"2250",
    "sg:province":"NSW",
    "sg:tags":[
        "lady",
        "wear"
    ],
    "wof:name":"Esprit Retail Pty Ltd",
    "wof:placetype":"venue"
},
  "geometry": {"coordinates":[151.39523315400001,-33.4345855713],"type":"Point"}
}