{
  "type": "Feature",
  "properties": {
    "addr:full":"PO Box 262 Toowoomba QLD 4350",
    "addr:postcode":"4350",
    "iso:country":"AU",
    "sg:address":"PO Box 262",
    "sg:city":"Toowoomba",
    "sg:classifiers":[
        {
            "category":"Manufacturing",
            "subcategory":"Tools & Machinery",
            "type":"Manufacturing & Wholesale Goods"
        }
    ],
    "sg:phone":"+61 7 4634 8077",
    "sg:postcode":"4350",
    "sg:province":"QLD",
    "sg:tags":[
        "fastener",
        "industrial"
    ],
    "wof:name":"Toowoomba Fasteners",
    "wof:placetype":"venue"
},
  "geometry": {"coordinates":[151.92512500000001,-27.595259],"type":"Point"}
}