{
  "type": "Feature",
  "properties": {
    "iso:country":"AU",
    "sg:address":"977 Nudgee Rd",
    "sg:city":"Banyo",
    "sg:classifiers":[
        {
            "category":"Manufacturing",
            "subcategory":"Tools & Machinery",
            "type":"Manufacturing & Wholesale Goods"
        }
    ],
    "sg:phone":"+61 7 3267 8800",
    "sg:postcode":"4014",
    "sg:province":"QLD",
    "sg:tags":[
        "earth",
        "excavating",
        "moving",
        "equipment"
    ],
    "wof:name":"Drivetrain",
    "wof:placetype":"venue"
},
  "geometry": {"coordinates":[153.089447022,-27.3846683502],"type":"Point"}
}