{
  "type": "Feature",
  "properties": {
    "addr:full":"3 Hopetown Rd Kanwal NSW 2259",
    "addr:housenumber":"3",
    "addr:postcode":"2259",
    "addr:street":"Hopetown Rd",
    "iso:country":"AU",
    "sg:address":"3 Hopetown Rd",
    "sg:city":"Kanwal",
    "sg:classifiers":[
        {
            "category":"Professional",
            "subcategory":"Computer Services",
            "type":"Services"
        }
    ],
    "sg:phone":"+61 421 304 560",
    "sg:postcode":"2259",
    "sg:province":"NSW",
    "sg:tags":[
        "tele-communications",
        "consultant"
    ],
    "wof:name":"Mytel Communications",
    "wof:placetype":"venue"
},
  "geometry": {"coordinates":[151.48468017600001,-33.2656288147],"type":"Point"}
}