{
  "type": "Feature",
  "properties": {
    "addr:full":"36c Valiant Rd Holden Hill SA 5088",
    "addr:housenumber":"36c",
    "addr:postcode":"5088",
    "addr:street":"Valiant Rd",
    "iso:country":"AU",
    "sg:address":"36c Valiant Rd",
    "sg:city":"Holden Hill",
    "sg:classifiers":[
        {
            "category":"Personal",
            "subcategory":"Beauty Salon",
            "type":"Services"
        }
    ],
    "sg:phone":"+61 8 8266 0099",
    "sg:postcode":"5088",
    "sg:province":"SA",
    "sg:tags":[
        "hairdresser"
    ],
    "wof:name":"Rascal's Hair Designs",
    "wof:placetype":"venue"
},
  "geometry": {"coordinates":[138.67169189399999,-34.8544502258],"type":"Point"}
}