{
  "type": "Feature",
  "properties": {
    "addr:full":"56 Gymea Bay Rd Gymea NSW 2227",
    "addr:housenumber":"56",
    "addr:postcode":"2227",
    "addr:street":"Gymea Bay Rd",
    "iso:country":"AU",
    "sg:address":"56 Gymea Bay Rd",
    "sg:city":"Gymea",
    "sg:classifiers":[
        {
            "category":"Food & Beverages",
            "subcategory":"Bakery",
            "type":"Retail Goods"
        }
    ],
    "sg:phone":"+61 2 9524 8239",
    "sg:postcode":"2227",
    "sg:province":"NSW",
    "sg:tags":[
        "baker"
    ],
    "wof:name":"Jasabel Bakehouse",
    "wof:placetype":"venue"
},
  "geometry": {"coordinates":[151.08485412600001,-34.0351333618],"type":"Point"}
}