{
  "type": "Feature",
  "properties": {
    "addr:full":"1594 Jamberoo Mountain Rd Knights Hill NSW 2577",
    "addr:housenumber":"1594",
    "addr:postcode":"2577",
    "addr:street":"Jamberoo Mountain Rd",
    "iso:country":"AU",
    "sg:address":"1594 Jamberoo Mountain Rd",
    "sg:city":"Knights Hill",
    "sg:classifiers":[
        {
            "category":"Farming",
            "subcategory":"Livestock Farm",
            "type":"Manufacturing & Wholesale Goods"
        }
    ],
    "sg:phone":"+61 2 4885 2000",
    "sg:postcode":"2577",
    "sg:province":"NSW",
    "sg:tags":[
        "breeder",
        "horse",
        "stud"
    ],
    "wof:name":"Southern Star Walers",
    "wof:placetype":"venue"
},
  "geometry": {"coordinates":[150.677856445,-34.6229515076],"type":"Point"}
}