{
  "type": "Feature",
  "properties": {
    "addr:full":"1 Merloo Drv Nerang QLD 4211",
    "addr:housenumber":"1",
    "addr:postcode":"4211",
    "addr:street":"Merloo Drv",
    "iso:country":"AU",
    "sg:address":"1 Merloo Drv",
    "sg:city":"Nerang",
    "sg:classifiers":[
        {
            "category":"Food & Beverages",
            "subcategory":"Groceries & Convenience Stores",
            "type":"Retail Goods"
        }
    ],
    "sg:phone":"+61 7 5596 2959",
    "sg:postcode":"4211",
    "sg:province":"QLD",
    "wof:name":"Clearwater General Store",
    "wof:placetype":"venue"
},
  "geometry": {"coordinates":[153.301803589,-28.0021076202],"type":"Point"}
}