{
  "type": "Feature",
  "properties": {
    "iso:country":"AU",
    "sg:address":"1505 Chambers Flat Rd",
    "sg:city":"Munruben",
    "sg:classifiers":[
        {
            "category":"Utilities",
            "subcategory":"Electric",
            "type":"Services"
        }
    ],
    "sg:phone":"+61 7 3297 1529",
    "sg:postcode":"4125",
    "sg:province":"QLD",
    "sg:tags":[
        "electrical",
        "contractor"
    ],
    "wof:name":"Besafe Electrical & Security Systems",
    "wof:placetype":"venue"
},
  "geometry": {"coordinates":[153.030487061,-27.7576293945],"type":"Point"}
}