{
  "type": "Feature",
  "properties": {
    "iso:country":"AU",
    "sg:address":"91 Drummond Rd",
    "sg:city":"Shepparton",
    "sg:classifiers":[
        {
            "category":"Utilities",
            "subcategory":"Electric",
            "type":"Services"
        }
    ],
    "sg:phone":"+61 3 5821 3944",
    "sg:postcode":"3630",
    "sg:province":"VIC",
    "sg:tags":[
        "electrical",
        "contractor"
    ],
    "wof:name":"Watters Electrical & Data Contractors",
    "wof:placetype":"venue"
},
  "geometry": {"coordinates":[145.42314148,-36.3754806519],"type":"Point"}
}