{
  "type": "Feature",
  "properties": {
    "addr:full":"Cnr Dandenong & Police Rds Springvale VIC 3171",
    "addr:postcode":"3171",
    "addr:street":"Cnr",
    "iso:country":"AU",
    "sg:address":"Cnr Dandenong & Police Rds",
    "sg:city":"Springvale",
    "sg:classifiers":[
        {
            "category":"Fast Food",
            "type":"Food & Drink"
        }
    ],
    "sg:phone":"+61 3 9546 0900",
    "sg:postcode":"3171",
    "sg:province":"VIC",
    "sg:tags":[
        "away",
        "take"
    ],
    "wof:name":"KFC",
    "wof:placetype":"venue"
},
  "geometry": {"coordinates":[145.16189575199999,-37.9441184998],"type":"Point"}
}