{
  "type": "Feature",
  "properties": {
    "addr:full":"71 Wooley St Dickson ACT 2602",
    "addr:housenumber":"71",
    "addr:postcode":"2602",
    "addr:street":"Wooley St",
    "iso:country":"AU",
    "sg:address":"71 Wooley St",
    "sg:city":"Dickson",
    "sg:classifiers":[
        {
            "category":"Real Estate",
            "subcategory":"Real Estate Agent",
            "type":"Services"
        }
    ],
    "sg:phone":"+61 2 6257 3200",
    "sg:postcode":"2602",
    "sg:province":"ACT",
    "wof:name":"Harlock Real Estate Pty Ltd",
    "wof:placetype":"venue"
},
  "geometry": {"coordinates":[149.138427734,-35.2502593994],"type":"Point"}
}