{
  "type": "Feature",
  "properties": {
    "addr:full":"82 Arnold St Bendigo VIC 3550",
    "addr:housenumber":"82",
    "addr:postcode":"3550",
    "addr:street":"Arnold St",
    "iso:country":"AU",
    "sg:address":"82 Arnold St",
    "sg:city":"Bendigo",
    "sg:classifiers":[
        {
            "category":"Fast Food",
            "type":"Food & Drink"
        }
    ],
    "sg:phone":"+61 3 5443 6584",
    "sg:postcode":"3550",
    "sg:province":"VIC",
    "sg:tags":[
        "away",
        "take"
    ],
    "wof:name":"Debbie's Deli",
    "wof:placetype":"venue"
},
  "geometry": {"coordinates":[144.28590393100001,-36.7518005371],"type":"Point"}
}