{
  "type": "Feature",
  "properties": {
    "addr:full":"36 Washington Ave Mildura VIC 3500",
    "addr:housenumber":"36",
    "addr:postcode":"3500",
    "addr:street":"Washington Ave",
    "iso:country":"AU",
    "sg:address":"36 Washington Ave",
    "sg:city":"Mildura",
    "sg:classifiers":[
        {
            "category":"Professional",
            "subcategory":"Art Services",
            "type":"Services"
        }
    ],
    "sg:phone":"+61 3 5021 0161",
    "sg:postcode":"3500",
    "sg:province":"VIC",
    "sg:tags":[
        "picture",
        "frame",
        "framing"
    ],
    "wof:name":"Aussie Lead Art",
    "wof:placetype":"venue"
},
  "geometry": {"coordinates":[142.151977539,-34.171585083],"type":"Point"}
}