{
  "type": "Feature",
  "properties": {
    "addr:full":"134 Atkinson Rd Bli Bli QLD 4560",
    "addr:housenumber":"134",
    "addr:postcode":"4560",
    "addr:street":"Atkinson Rd",
    "iso:country":"AU",
    "sg:address":"134 Atkinson Rd",
    "sg:city":"Bli Bli",
    "sg:classifiers":[
        {
            "category":"Building & Trades",
            "subcategory":"Landscaping Services",
            "type":"Services"
        }
    ],
    "sg:phone":"+61 417 720 485",
    "sg:postcode":"4560",
    "sg:province":"QLD",
    "sg:tags":[
        "designer",
        "landscape",
        "contractor"
    ],
    "wof:name":"Greg Shepherd",
    "wof:placetype":"venue"
},
  "geometry": {"coordinates":[153.004196167,-26.6013736725],"type":"Point"}
}