{
  "type": "Feature",
  "properties": {
    "iso:country":"AU",
    "sg:address":"588 Henley Beach Rd",
    "sg:city":"Fulham",
    "sg:classifiers":[
        {
            "category":"Retail",
            "subcategory":"Auto Repair",
            "type":"Services"
        }
    ],
    "sg:phone":"+61 8 8356 4164",
    "sg:postcode":"5024",
    "sg:province":"SA",
    "sg:tags":[
        "repairer",
        "motor",
        "engineer"
    ],
    "wof:name":"Fulham Auto Repairs",
    "wof:placetype":"venue"
},
  "geometry": {"coordinates":[138.510009766,-34.9265518188],"type":"Point"}
}