{
  "type": "Feature",
  "properties": {
    "iso:country":"AU",
    "sg:address":"8-12 Howitt St",
    "sg:city":"Warragul",
    "sg:classifiers":[
        {
            "category":"Autos & Motor Vehicles",
            "subcategory":"Auto Supplies",
            "type":"Retail Goods"
        }
    ],
    "sg:phone":"+61 3 5623 5855",
    "sg:postcode":"3820",
    "sg:province":"VIC",
    "sg:tags":[
        "accessory"
    ],
    "wof:name":"Warragul Motor Wreckers",
    "wof:placetype":"venue"
},
  "geometry": {"coordinates":[145.938614,-38.143978],"type":"Point"}
}