{
  "type": "Feature",
  "properties": {
    "iso:country":"AU",
    "sg:address":"Sudlow Rd",
    "sg:city":"Bibra Lake",
    "sg:classifiers":[
        {
            "category":"Insurance",
            "subcategory":"Insurance Agent",
            "type":"Services"
        }
    ],
    "sg:phone":"+61 8 9434 9548",
    "sg:postcode":"6163",
    "sg:province":"WA",
    "sg:tags":[
        "wool",
        "broker"
    ],
    "wof:name":"Lempriere Aust Pty Ltd",
    "wof:placetype":"venue"
},
  "geometry": {"coordinates":[115.807861,-32.091057],"type":"Point"}
}