{
  "type": "Feature",
  "properties": {
    "addr:full":"145 Gipps Rd Keiraville NSW 2500",
    "addr:housenumber":"145",
    "addr:postcode":"2500",
    "addr:street":"Gipps Rd",
    "iso:country":"AU",
    "sg:address":"145 Gipps Rd",
    "sg:city":"Keiraville",
    "sg:classifiers":[
        {
            "category":"Health Services",
            "subcategory":"Health Practitioner",
            "type":"Services"
        }
    ],
    "sg:phone":"+61 2 4229 8821",
    "sg:postcode":"2500",
    "sg:province":"NSW",
    "sg:tags":[
        "naturopath"
    ],
    "wof:name":"Victoria, Healer & Health Practitioner",
    "wof:placetype":"venue"
},
  "geometry": {"coordinates":[150.878006,-34.415493],"type":"Point"}
}