{
  "type": "Feature",
  "properties": {
    "iso:country":"AU",
    "sg:address":"Lvl 4/ 424 George St",
    "sg:city":"Sydney",
    "sg:classifiers":[
        {
            "category":"Shopping",
            "subcategory":"Jewelry",
            "type":"Retail Goods"
        }
    ],
    "sg:phone":"+61 2 9233 5119",
    "sg:postcode":"2000",
    "sg:province":"NSW",
    "sg:tags":[
        "jeweller"
    ],
    "wof:name":"Lawrence Sanders P/L",
    "wof:placetype":"venue"
},
  "geometry": {"coordinates":[151.207122803,-33.8698883057],"type":"Point"}
}