{
  "type": "Feature",
  "properties": {
    "addr:full":"7 Scenic Ave Ringwood East VIC 3135",
    "addr:housenumber":"7",
    "addr:postcode":"3135",
    "addr:street":"Scenic Ave",
    "iso:country":"AU",
    "sg:address":"7 Scenic Ave",
    "sg:city":"Ringwood East",
    "sg:classifiers":[
        {
            "category":"Utilities",
            "subcategory":"Electric",
            "type":"Services"
        }
    ],
    "sg:phone":"+61 3 9870 8724",
    "sg:postcode":"3135",
    "sg:province":"VIC",
    "sg:tags":[
        "electrical",
        "contractor"
    ],
    "wof:name":"Adeney W K Electrics",
    "wof:placetype":"venue"
},
  "geometry": {"coordinates":[145.251342773,-37.8181686401],"type":"Point"}
}