{
  "type": "Feature",
  "properties": {
    "addr:full":"6 Melville Park Drv Berwick VIC 3806",
    "addr:housenumber":"6",
    "addr:postcode":"3806",
    "addr:street":"Melville Park Drv",
    "iso:country":"AU",
    "sg:address":"6 Melville Park Drv",
    "sg:city":"Berwick",
    "sg:classifiers":[
        {
            "category":"Social Services",
            "subcategory":"Retirement Home",
            "type":"Services"
        }
    ],
    "sg:phone":"+61 3 9796 1578",
    "sg:postcode":"3806",
    "sg:province":"VIC",
    "sg:tags":[
        "village"
    ],
    "wof:name":"Edrington Park Retirement Village",
    "wof:placetype":"venue"
},
  "geometry": {"coordinates":[145.353713989,-38.0366668701],"type":"Point"}
}