{
  "type": "Feature",
  "properties": {
    "iso:country":"AU",
    "sg:address":"Suite 508, 6 Cowper Wharf Rd",
    "sg:city":"Woolloomooloo",
    "sg:classifiers":[
        {
            "category":"Banks & Credit Unions",
            "subcategory":"Financial Services",
            "type":"Services"
        }
    ],
    "sg:phone":"+61 2 9358 4411",
    "sg:postcode":"2011",
    "sg:province":"NSW",
    "sg:tags":[
        "annuity",
        "rollover",
        "superannuation",
        "consultant"
    ],
    "wof:name":"Larkins Business Management",
    "wof:placetype":"venue"
},
  "geometry": {"coordinates":[151.21995544399999,-33.8689956665],"type":"Point"}
}