{
  "type": "Feature",
  "properties": {
    "addr:full":"Suite 1, 230 Main St Osborne Park WA 6017",
    "addr:housenumber":"230",
    "addr:postcode":"6017",
    "addr:street":"Main St",
    "iso:country":"AU",
    "sg:address":"Suite 1, 230 Main St",
    "sg:city":"Osborne Park",
    "sg:classifiers":[
        {
            "category":"Real Estate",
            "subcategory":"Real Estate Agent",
            "type":"Services"
        }
    ],
    "sg:phone":"+61 8 9349 5111",
    "sg:postcode":"6017",
    "sg:province":"WA",
    "wof:name":"Market Place Realty The",
    "wof:placetype":"venue"
},
  "geometry": {"coordinates":[115.828422546,-31.8968238831],"type":"Point"}
}