{
  "type": "Feature",
  "properties": {
    "iso:country":"AU",
    "sg:address":"Fraser Rd",
    "sg:city":"Mt Molloy",
    "sg:classifiers":[
        {
            "category":"Education",
            "subcategory":"School",
            "type":"Public Place"
        }
    ],
    "sg:phone":"+61 7 4094 1261",
    "sg:postcode":"4871",
    "sg:province":"QLD",
    "sg:tags":[
        "state",
        "except",
        "nsw"
    ],
    "wof:name":"Mount Molloy Primary School",
    "wof:placetype":"venue"
},
  "geometry": {"coordinates":[145.33169555699999,-16.6750621796],"type":"Point"}
}