{
  "type": "Feature",
  "properties": {
    "addr:full":"30 Bayfield St Rosny Park TAS 7018",
    "addr:housenumber":"30",
    "addr:postcode":"7018",
    "addr:street":"Bayfield St",
    "iso:country":"AU",
    "sg:address":"30 Bayfield St",
    "sg:city":"Rosny Park",
    "sg:classifiers":[
        {
            "category":"Professional",
            "subcategory":"Accounting & Tax Preparation",
            "type":"Services"
        }
    ],
    "sg:phone":"+61 3 6244 5144",
    "sg:postcode":"7018",
    "sg:province":"TAS",
    "sg:tags":[
        "accountant",
        "auditor"
    ],
    "wof:name":"Alomes David & Co",
    "wof:placetype":"venue"
},
  "geometry": {"coordinates":[147.37229919399999,-42.8669128418],"type":"Point"}
}