{
  "type": "Feature",
  "properties": {
    "iso:country":"AU",
    "sg:address":"69a Central Ave",
    "sg:city":"Oak Flats",
    "sg:classifiers":[
        {
            "category":"Shopping",
            "subcategory":"Crafts & Fabrics",
            "type":"Retail Goods"
        }
    ],
    "sg:phone":"+61 2 4257 4588",
    "sg:postcode":"2529",
    "sg:province":"NSW",
    "sg:tags":[
        "material",
        "dress"
    ],
    "wof:name":"Donnas Fabrics",
    "wof:placetype":"venue"
},
  "geometry": {"coordinates":[150.81900024399999,-34.5634803772],"type":"Point"}
}