{
  "type": "Feature",
  "properties": {
    "iso:country":"AU",
    "sg:address":"73 Chapel St St",
    "sg:city":"Kilda",
    "sg:classifiers":[
        {
            "category":"Organizations",
            "subcategory":"Professional Association",
            "type":"Services"
        }
    ],
    "sg:phone":"+61 3 9534 3507",
    "sg:postcode":"3182",
    "sg:province":"VIC",
    "sg:tags":[
        "web",
        "internet"
    ],
    "wof:name":"Equipe Internet Solutions",
    "wof:placetype":"venue"
},
  "geometry": {"coordinates":[144.990997314,-37.8639678955],"type":"Point"}
}