{
  "type": "Feature",
  "properties": {
    "addr:full":"89 Marshall Rd Dundas NSW 2117",
    "addr:housenumber":"89",
    "addr:postcode":"2117",
    "addr:street":"Marshall Rd",
    "iso:country":"AU",
    "sg:address":"89 Marshall Rd",
    "sg:city":"Dundas",
    "sg:classifiers":[
        {
            "category":"Shopping",
            "subcategory":"Clothing, Apparel, & Fashions",
            "type":"Retail Goods"
        }
    ],
    "sg:phone":"+61 2 9873 6559",
    "sg:postcode":"2117",
    "sg:province":"NSW",
    "sg:tags":[
        "millinery"
    ],
    "wof:name":"Eevn Headware",
    "wof:placetype":"venue"
},
  "geometry": {"coordinates":[151.045379639,-33.7876358032],"type":"Point"}
}