{
  "type": "Feature",
  "properties": {
    "addr:full":"7 Walker Pl Wetherill Park NSW 2164",
    "addr:housenumber":"7",
    "addr:postcode":"2164",
    "addr:street":"Walker Pl",
    "iso:country":"AU",
    "sg:address":"7 Walker Pl",
    "sg:city":"Wetherill Park",
    "sg:classifiers":[
        {
            "category":"Wholesale",
            "subcategory":"Painting Supplies",
            "type":"Manufacturing & Wholesale Goods"
        }
    ],
    "sg:phone":"+61 2 9609 6322",
    "sg:postcode":"2164",
    "sg:province":"NSW",
    "sg:tags":[
        "product",
        "cleaning"
    ],
    "wof:name":"Milestone Chemicals N.S.W.",
    "wof:placetype":"venue"
},
  "geometry": {"coordinates":[150.888504028,-33.843711853],"type":"Point"}
}