{
  "type": "Feature",
  "properties": {
    "addr:full":"3 Carrington Pl Orange NSW 2800",
    "addr:housenumber":"3",
    "addr:postcode":"2800",
    "addr:street":"Carrington Pl",
    "iso:country":"AU",
    "sg:address":"3 Carrington Pl",
    "sg:city":"Orange",
    "sg:classifiers":[
        {
            "category":"Wholesale",
            "subcategory":"Machinery & Supplies",
            "type":"Manufacturing & Wholesale Goods"
        }
    ],
    "sg:phone":"+61 2 6361 2873",
    "sg:postcode":"2800",
    "sg:province":"NSW",
    "sg:tags":[
        "equipment",
        "pneumatic"
    ],
    "wof:name":"SMC",
    "wof:placetype":"venue"
},
  "geometry": {"coordinates":[149.077560425,-33.2723274231],"type":"Point"}
}