{
  "type": "Feature",
  "properties": {
    "addr:full":"35 Stiles Ave Burswood WA 6100",
    "addr:housenumber":"35",
    "addr:postcode":"6100",
    "addr:street":"Stiles Ave",
    "iso:country":"AU",
    "sg:address":"35 Stiles Ave",
    "sg:city":"Burswood",
    "sg:classifiers":[
        {
            "category":"Manufacturing",
            "subcategory":"Rubber & Plastics",
            "type":"Manufacturing & Wholesale Goods"
        }
    ],
    "sg:phone":"+61 8 9470 3799",
    "sg:postcode":"6100",
    "sg:province":"WA",
    "sg:tags":[
        "fabricator"
    ],
    "wof:name":"Allglass Australia",
    "wof:placetype":"venue"
},
  "geometry": {"coordinates":[115.901771545,-31.9591598511],"type":"Point"}
}