{
  "type": "Feature",
  "properties": {
    "addr:full":"PO Box 793 Gungahlin ACT 2912",
    "addr:postcode":"2912",
    "iso:country":"AU",
    "sg:address":"PO Box 793",
    "sg:city":"Gungahlin",
    "sg:classifiers":[
        {
            "category":"Building & Trades",
            "subcategory":"Construction",
            "type":"Services"
        }
    ],
    "sg:phone":"+61 422 469 043",
    "sg:postcode":"2912",
    "sg:province":"ACT",
    "sg:tags":[
        "home",
        "air conditioning"
    ],
    "wof:name":"Apollo Air Conditioning & Heating Pty Ltd",
    "wof:placetype":"venue"
},
  "geometry": {"coordinates":[149.137405395,-35.1838493347],"type":"Point"}
}