{
  "type": "Feature",
  "properties": {
    "addr:full":"331 High St Preston VIC 3072",
    "addr:housenumber":"331",
    "addr:postcode":"3072",
    "addr:street":"High St",
    "iso:country":"AU",
    "sg:address":"331 High St",
    "sg:city":"Preston",
    "sg:classifiers":[
        {
            "category":"Shopping",
            "subcategory":"Clothing, Apparel, & Fashions",
            "type":"Retail Goods"
        }
    ],
    "sg:phone":"+61 3 9478 1874",
    "sg:postcode":"3072",
    "sg:province":"VIC",
    "sg:tags":[
        "recycled",
        "clothing"
    ],
    "wof:name":"The Salvation Army Family Stores",
    "wof:placetype":"venue"
},
  "geometry": {"coordinates":[145.00367736800001,-37.7409934998],"type":"Point"}
}