{
  "type": "Feature",
  "properties": {
    "iso:country":"AU",
    "sg:address":"5/ 146 Anderson St",
    "sg:city":"Manunda",
    "sg:classifiers":[
        {
            "category":"Food & Beverages",
            "subcategory":"Specialty",
            "type":"Retail Goods"
        }
    ],
    "sg:phone":"+61 7 4053 1726",
    "sg:postcode":"4870",
    "sg:province":"QLD",
    "sg:tags":[
        "product",
        "health"
    ],
    "wof:name":"Karen's Chemist",
    "wof:placetype":"venue"
},
  "geometry": {"coordinates":[145.74288940400001,-16.9166431427],"type":"Point"}
}