{
  "type": "Feature",
  "properties": {
    "addr:full":"Warrego Hwy Toowoomba QLD 4350",
    "addr:postcode":"4350",
    "addr:street":"Warrego Hwy",
    "iso:country":"AU",
    "sg:address":"Warrego Hwy",
    "sg:city":"Toowoomba",
    "sg:classifiers":[
        {
            "category":"Travel",
            "subcategory":"Hotels & Motels",
            "type":"Entertainment"
        }
    ],
    "sg:phone":"+61 7 4630 4060",
    "sg:postcode":"4350",
    "sg:province":"QLD",
    "wof:name":"Charlton Caravan Park",
    "wof:placetype":"venue"
},
  "geometry": {"coordinates":[151.869843,-27.527382],"type":"Point"}
}