{
  "type": "Feature",
  "properties": {
    "iso:country":"AU",
    "sg:address":"1/ 28 Prime Drv",
    "sg:city":"Seven Hills",
    "sg:classifiers":[
        {
            "category":"Wholesale",
            "subcategory":"Machinery & Supplies",
            "type":"Manufacturing & Wholesale Goods"
        }
    ],
    "sg:phone":"+61 2 9674 5395",
    "sg:postcode":"2147",
    "sg:province":"NSW",
    "sg:tags":[
        "instrument"
    ],
    "wof:name":"Walter Oakes Instrument Co Pty Ltd",
    "wof:placetype":"venue"
},
  "geometry": {"coordinates":[150.95343017600001,-33.772480011],"type":"Point"}
}