{
  "type": "Feature",
  "properties": {
    "iso:country":"AU",
    "sg:address":"16 Arthur St",
    "sg:city":"Baulkham Hills",
    "sg:classifiers":[
        {
            "category":"Food & Beverages",
            "subcategory":"Groceries & Convenience Stores",
            "type":"Retail Goods"
        }
    ],
    "sg:phone":"+61 2 9639 1321",
    "sg:postcode":"2153",
    "sg:province":"NSW",
    "wof:name":"Korkys Corner",
    "wof:placetype":"venue"
},
  "geometry": {"coordinates":[150.971435547,-33.8338279724],"type":"Point"}
}