{
  "type": "Feature",
  "properties": {
    "iso:country":"AU",
    "sg:address":"107 Dickson St",
    "sg:city":"Wooloowin",
    "sg:classifiers":[
        {
            "category":"Shopping",
            "subcategory":"Pets & Pet Supplies",
            "type":"Retail Goods"
        }
    ],
    "sg:phone":"+61 7 3857 1716",
    "sg:postcode":"4030",
    "sg:province":"QLD",
    "sg:tags":[
        "shop",
        "supplier"
    ],
    "wof:name":"Aquariums &#039;R&#039; Us",
    "wof:placetype":"venue"
},
  "geometry": {"coordinates":[153.046143,-27.415941],"type":"Point"}
}