{
  "type": "Feature",
  "properties": {
    "addr:full":"Level 1, 134-138 Thompson St Cowes VIC 3922",
    "addr:housenumber":"134-138",
    "addr:postcode":"3922",
    "addr:street":"Thompson St",
    "iso:country":"AU",
    "sg:address":"Level 1, 134-138 Thompson St",
    "sg:city":"Cowes",
    "sg:classifiers":[
        {
            "category":"Real Estate",
            "subcategory":"Real Estate Services",
            "type":"Services"
        }
    ],
    "sg:phone":"+61 3 5952 6311",
    "sg:postcode":"3922",
    "sg:province":"VIC",
    "sg:tags":[
        "valuer"
    ],
    "wof:name":"Lee C.J.A. Property",
    "wof:placetype":"venue"
},
  "geometry": {"coordinates":[145.238815308,-38.4542884827],"type":"Point"}
}