{
  "type": "Feature",
  "properties": {
    "addr:full":"56 Archer St Woodford QLD 4514",
    "addr:housenumber":"56",
    "addr:postcode":"4514",
    "addr:street":"Archer St",
    "iso:country":"AU",
    "sg:address":"56 Archer St",
    "sg:city":"Woodford",
    "sg:classifiers":[
        {
            "category":"Retail",
            "subcategory":"Veterinary Services",
            "type":"Services"
        }
    ],
    "sg:phone":"+61 7 5496 1166",
    "sg:postcode":"4514",
    "sg:province":"QLD",
    "sg:tags":[
        "surgeon"
    ],
    "wof:name":"Southern Cross Veterinarians",
    "wof:placetype":"venue"
},
  "geometry": {"coordinates":[152.77624499999999,-26.950668],"type":"Point"}
}