{
  "type": "Feature",
  "properties": {
    "addr:full":"111 Maroondah Hwy Ringwood VIC 3134",
    "addr:housenumber":"111",
    "addr:postcode":"3134",
    "addr:street":"Maroondah Hwy",
    "iso:country":"AU",
    "sg:address":"111 Maroondah Hwy",
    "sg:city":"Ringwood",
    "sg:classifiers":[
        {
            "category":"Communications",
            "subcategory":"Film & Video Production",
            "type":"Services"
        }
    ],
    "sg:phone":"+61 3 9870 3211",
    "sg:postcode":"3134",
    "sg:province":"VIC",
    "sg:tags":[
        "dvd",
        "library"
    ],
    "wof:name":"Movieland Video Libraries",
    "wof:placetype":"venue"
},
  "geometry": {"coordinates":[145.22564697300001,-37.816242218],"type":"Point"}
}