{
  "type": "Feature",
  "properties": {
    "iso:country":"AU",
    "sg:address":"PO Box 152",
    "sg:city":"Corrimal",
    "sg:classifiers":[
        {
            "category":"Real Estate",
            "subcategory":"Real Estate Agent",
            "type":"Services"
        }
    ],
    "sg:phone":"+61 412 424 226",
    "sg:postcode":"2518",
    "sg:province":"NSW",
    "wof:name":"Merritt Martin",
    "wof:placetype":"venue"
},
  "geometry": {"coordinates":[150.896683,-34.374062],"type":"Point"}
}