{
  "type": "Feature",
  "properties": {
    "addr:full":"229 Queen St Ayr QLD 4807",
    "addr:housenumber":"229",
    "addr:postcode":"4807",
    "addr:street":"Queen St",
    "iso:country":"AU",
    "sg:address":"229 Queen St",
    "sg:city":"Ayr",
    "sg:classifiers":[
        {
            "category":"Autos & Motor Vehicles",
            "subcategory":"Motorcycle Sales",
            "type":"Retail Goods"
        }
    ],
    "sg:phone":"+61 7 4783 1530",
    "sg:postcode":"4807",
    "sg:province":"QLD",
    "sg:tags":[
        "outboard"
    ],
    "wof:name":"Coral Coast Marine Sales & Service",
    "wof:placetype":"venue"
},
  "geometry": {"coordinates":[147.400268555,-19.5815105438],"type":"Point"}
}