{
  "type": "Feature",
  "properties": {
    "iso:country":"AU",
    "sg:address":"150 Beaufort St",
    "sg:city":"Perth",
    "sg:classifiers":[
        {
            "category":"Professional",
            "subcategory":"Printing & Photocopies",
            "type":"Services"
        }
    ],
    "sg:phone":"+61 8 9227 9998",
    "sg:postcode":"6000",
    "sg:province":"WA",
    "sg:tags":[
        "laminating"
    ],
    "wof:name":"Print Finishing Line",
    "wof:placetype":"venue"
},
  "geometry": {"coordinates":[115.86376190199999,-31.9480209351],"type":"Point"}
}