{
  "type": "Feature",
  "properties": {
    "addr:full":"1 Durham Rd Cooee TAS 7320",
    "addr:housenumber":"1",
    "addr:postcode":"7320",
    "addr:street":"Durham Rd",
    "iso:country":"AU",
    "sg:address":"1 Durham Rd",
    "sg:city":"Cooee",
    "sg:classifiers":[
        {
            "category":"Wholesale",
            "subcategory":"Painting Supplies",
            "type":"Manufacturing & Wholesale Goods"
        }
    ],
    "sg:phone":"+61 3 6432 1988",
    "sg:postcode":"7320",
    "sg:province":"TAS",
    "sg:tags":[
        "product",
        "cleaning"
    ],
    "wof:name":"Tasman Chemicals Pty Ltd",
    "wof:placetype":"venue"
},
  "geometry": {"coordinates":[145.875641,-41.041275],"type":"Point"}
}