{
  "type": "Feature",
  "properties": {
    "iso:country":"AU",
    "sg:address":"83 Railway St",
    "sg:city":"Corrimal",
    "sg:classifiers":[
        {
            "category":"Insurance",
            "subcategory":"Hazard Insurance",
            "type":"Services"
        }
    ],
    "sg:phone":"+61 2 4285 4607",
    "sg:postcode":"2518",
    "sg:province":"NSW",
    "sg:tags":[
        "loss",
        "adjuster",
        "assessor"
    ],
    "wof:name":"L.A.C. Loss Adjusters",
    "wof:placetype":"venue"
},
  "geometry": {"coordinates":[150.89999399999999,-34.373348],"type":"Point"}
}