{
  "type": "Feature",
  "properties": {
    "addr:full":"104 Glenlyon St Gladstone QLD 4680",
    "addr:housenumber":"104",
    "addr:postcode":"4680",
    "addr:street":"Glenlyon St",
    "iso:country":"AU",
    "sg:address":"104 Glenlyon St",
    "sg:city":"Gladstone",
    "sg:classifiers":[
        {
            "category":"Travel",
            "subcategory":"Hotels & Motels",
            "type":"Entertainment"
        }
    ],
    "sg:phone":"+61 7 4972 4922",
    "sg:postcode":"4680",
    "sg:province":"QLD",
    "wof:name":"Siesta Villa Motor Inn",
    "wof:placetype":"venue"
},
  "geometry": {"coordinates":[151.25628662099999,-23.847661972],"type":"Point"}
}