{
  "type": "Feature",
  "properties": {
    "iso:country":"AU",
    "sg:address":"91 Queen St",
    "sg:city":"Brisbane",
    "sg:classifiers":[
        {
            "category":"Shopping",
            "subcategory":"Clothing, Apparel, & Fashions",
            "type":"Retail Goods"
        }
    ],
    "sg:phone":"+61 7 3211 3530",
    "sg:postcode":"4000",
    "sg:province":"QLD",
    "sg:tags":[
        "boutique"
    ],
    "wof:name":"Carla Zampatti Pty Ltd",
    "wof:placetype":"venue"
},
  "geometry": {"coordinates":[153.02461242699999,-27.4702720642],"type":"Point"}
}