{
  "type": "Feature",
  "properties": {
    "iso:country":"AU",
    "sg:address":"Melton Valley Drv",
    "sg:city":"Melton",
    "sg:classifiers":[
        {
            "category":"Retail",
            "subcategory":"Event Space",
            "type":"Services"
        }
    ],
    "sg:phone":"+61 3 9743 2590",
    "sg:postcode":"3337",
    "sg:province":"VIC",
    "sg:tags":[
        "venue",
        "reception",
        "wedding"
    ],
    "wof:name":"Melton Valley Golf Club",
    "wof:placetype":"venue"
},
  "geometry": {"coordinates":[144.59794600000001,-37.682808],"type":"Point"}
}