{
  "type": "Feature",
  "properties": {
    "addr:full":"Shop 341 Homer St Earlwood NSW 2206",
    "addr:housenumber":"341",
    "addr:postcode":"2206",
    "addr:street":"Homer St",
    "iso:country":"AU",
    "sg:address":"Shop 341 Homer St",
    "sg:city":"Earlwood",
    "sg:classifiers":[
        {
            "category":"Shopping",
            "subcategory":"Bridal",
            "type":"Retail Goods"
        }
    ],
    "sg:phone":"+61 2 9558 5648",
    "sg:postcode":"2206",
    "sg:province":"NSW",
    "sg:tags":[
        "hire",
        "wear"
    ],
    "wof:name":"Personalised Weddings",
    "wof:placetype":"venue"
},
  "geometry": {"coordinates":[151.12586999999999,-33.926281],"type":"Point"}
}