{
  "type": "Feature",
  "properties": {
    "addr:full":"122 Wembley Rd Woodridge QLD 4114",
    "addr:housenumber":"122",
    "addr:postcode":"4114",
    "addr:street":"Wembley Rd",
    "iso:country":"AU",
    "sg:address":"122 Wembley Rd",
    "sg:city":"Woodridge",
    "sg:classifiers":[
        {
            "category":"Fast Food",
            "type":"Food & Drink"
        }
    ],
    "sg:phone":"+61 7 3808 4422",
    "sg:postcode":"4114",
    "sg:province":"QLD",
    "sg:tags":[
        "away",
        "take"
    ],
    "wof:name":"McDonald's Family Restaurants",
    "wof:placetype":"venue"
},
  "geometry": {"coordinates":[153.107330322,-27.6412239075],"type":"Point"}
}