{
  "type": "Feature",
  "properties": {
    "addr:full":"101 Jervis St Nowra NSW 2541",
    "addr:housenumber":"101",
    "addr:postcode":"2541",
    "addr:street":"Jervis St",
    "iso:country":"AU",
    "sg:address":"101 Jervis St",
    "sg:city":"Nowra",
    "sg:classifiers":[
        {
            "category":"Education",
            "subcategory":"Kindergarten",
            "type":"Public Place"
        }
    ],
    "sg:phone":"+61 2 4421 4604",
    "sg:postcode":"2541",
    "sg:province":"NSW",
    "sg:tags":[
        "pre-schools"
    ],
    "wof:name":"Lyrebird Pre-School Kindergarten",
    "wof:placetype":"venue"
},
  "geometry": {"coordinates":[150.607666016,-34.8835334778],"type":"Point"}
}