{
  "type": "Feature",
  "properties": {
    "iso:country":"AU",
    "sg:address":"4, 42 Westchester Rd",
    "sg:city":"Malaga",
    "sg:classifiers":[
        {
            "category":"Wholesale",
            "subcategory":"Machinery & Supplies",
            "type":"Manufacturing & Wholesale Goods"
        }
    ],
    "sg:phone":"+61 8 9248 5108",
    "sg:postcode":"6090",
    "sg:province":"WA",
    "sg:tags":[
        "equipment",
        "welding"
    ],
    "wof:name":"Malaga Welding & Industrial Supplies",
    "wof:placetype":"venue"
},
  "geometry": {"coordinates":[115.88079834,-31.8567466736],"type":"Point"}
}