{
  "type": "Feature",
  "properties": {
    "addr:full":"Shop 3, 68 Ballina St Lennox Head NSW 2478",
    "addr:housenumber":"shop;68",
    "addr:postcode":"2478",
    "addr:street":"Ballina St",
    "iso:country":"AU",
    "sg:address":"Shop 3, 68 Ballina St",
    "sg:city":"Lennox Head",
    "sg:classifiers":[
        {
            "category":"Personal",
            "subcategory":"Beauty Salon",
            "type":"Services"
        }
    ],
    "sg:phone":"+61 2 6687 5122",
    "sg:postcode":"2478",
    "sg:province":"NSW",
    "wof:name":"Vital Beauty Salon",
    "wof:placetype":"venue"
},
  "geometry": {"coordinates":[153.59356689399999,-28.7960929871],"type":"Point"}
}