{
  "type": "Feature",
  "properties": {
    "addr:full":"305 Firmin La Hazelwood VIC 3840",
    "addr:housenumber":"305",
    "addr:postcode":"3840",
    "addr:street":"Firmin La",
    "iso:country":"AU",
    "sg:address":"305 Firmin La",
    "sg:city":"Hazelwood",
    "sg:classifiers":[
        {
            "category":"Building & Trades",
            "subcategory":"Pest Control",
            "type":"Services"
        }
    ],
    "sg:phone":"+61 3 5166 1822",
    "sg:postcode":"3840",
    "sg:province":"VIC",
    "wof:name":"Combridge Pest Control",
    "wof:placetype":"venue"
},
  "geometry": {"coordinates":[146.431564331,-38.2478179932],"type":"Point"}
}