{
  "type": "Feature",
  "properties": {
    "addr:full":"Gibbes St Rockdale NSW 2216",
    "addr:postcode":"2216",
    "addr:street":"Gibbes St",
    "iso:country":"AU",
    "sg:address":"Gibbes St",
    "sg:city":"Rockdale",
    "sg:classifiers":[
        {
            "category":"Professional",
            "subcategory":"Computer Services",
            "type":"Services"
        }
    ],
    "sg:phone":"+61 2 9597 3218",
    "sg:postcode":"2216",
    "sg:province":"NSW",
    "sg:tags":[
        "consultant",
        "system"
    ],
    "wof:name":"V C B Computing Alternatives",
    "wof:placetype":"venue"
},
  "geometry": {"coordinates":[151.143585,-33.954433],"type":"Point"}
}