{
  "type": "Feature",
  "properties": {
    "iso:country":"AU",
    "sg:address":"12 Hordern Pl",
    "sg:city":"Camperdown",
    "sg:classifiers":[
        {
            "category":"Shopping",
            "subcategory":"Antiques",
            "type":"Retail Goods"
        }
    ],
    "sg:phone":"+61 2 9519 0644",
    "sg:postcode":"2050",
    "sg:province":"NSW",
    "sg:tags":[
        "restoration",
        "reproduction"
    ],
    "wof:name":"Fraser Antiques",
    "wof:placetype":"venue"
},
  "geometry": {"coordinates":[151.174057,-33.888977],"type":"Point"}
}