{
  "type": "Feature",
  "properties": {
    "iso:country":"AU",
    "sg:address":"14 - 16 Coghlan St",
    "sg:city":"Broome",
    "sg:classifiers":[
        {
            "category":"Retail",
            "subcategory":"Auto Rental",
            "type":"Services"
        }
    ],
    "sg:phone":"+61 8 9193 5980",
    "sg:postcode":"6725",
    "sg:province":"WA",
    "sg:tags":[
        "car",
        "hire",
        "minibus"
    ],
    "wof:name":"Avis",
    "wof:placetype":"venue"
},
  "geometry": {"coordinates":[122.237190247,-17.9539585114],"type":"Point"}
}