{
  "type": "Feature",
  "properties": {
    "addr:full":"70 Camooweal St Mt Isa QLD 4825",
    "addr:housenumber":"70",
    "addr:postcode":"4825",
    "addr:street":"Camooweal St",
    "iso:country":"AU",
    "sg:address":"70 Camooweal St",
    "sg:city":"Mt Isa",
    "sg:classifiers":[
        {
            "category":"Insurance",
            "subcategory":"Health Insurance",
            "type":"Services"
        }
    ],
    "sg:phone":"+61 7 4743 2777",
    "sg:postcode":"4825",
    "sg:province":"QLD",
    "wof:name":"Queensland Country Health Ltd",
    "wof:placetype":"venue"
},
  "geometry": {"coordinates":[139.49284399999999,-20.728317],"type":"Point"}
}