{
  "type": "Feature",
  "properties": {
    "addr:full":"29 Hulme Crt Myaree WA 6154",
    "addr:housenumber":"29",
    "addr:postcode":"6154",
    "addr:street":"Hulme Crt",
    "iso:country":"AU",
    "sg:address":"29 Hulme Crt",
    "sg:city":"Myaree",
    "sg:classifiers":[
        {
            "category":"Retail",
            "subcategory":"Storage",
            "type":"Services"
        }
    ],
    "sg:phone":"+61 8 9329 9028",
    "sg:postcode":"6154",
    "sg:province":"WA",
    "sg:tags":[
        "equipment",
        "computer",
        "secondhand"
    ],
    "wof:name":"DV Computers",
    "wof:placetype":"venue"
},
  "geometry": {"coordinates":[115.81218699999999,-32.044041],"type":"Point"}
}