{
  "type": "Feature",
  "properties": {
    "addr:full":"Connell Ave Kelmscott WA 6111",
    "addr:postcode":"6111",
    "addr:street":"Connell Ave",
    "iso:country":"AU",
    "sg:address":"Connell Ave",
    "sg:city":"Kelmscott",
    "sg:classifiers":[
        {
            "category":"Education",
            "subcategory":"School",
            "type":"Public Place"
        }
    ],
    "sg:phone":"+61 8 9390 5922",
    "sg:postcode":"6111",
    "sg:province":"WA",
    "sg:tags":[
        "state",
        "except",
        "nsw"
    ],
    "wof:name":"Clifton Hills Primary",
    "wof:placetype":"venue"
},
  "geometry": {"coordinates":[116.022216797,-32.1126174927],"type":"Point"}
}