{
  "type": "Feature",
  "properties": {
    "addr:full":"63 Dumbarton St Reservoir VIC 3073",
    "addr:housenumber":"63",
    "addr:postcode":"3073",
    "addr:street":"Dumbarton St",
    "iso:country":"AU",
    "sg:address":"63 Dumbarton St",
    "sg:city":"Reservoir",
    "sg:classifiers":[
        {
            "category":"Education",
            "subcategory":"Vocational School",
            "type":"Public Place"
        }
    ],
    "sg:phone":"+61 3 9469 5119",
    "sg:postcode":"3073",
    "sg:province":"VIC",
    "sg:tags":[
        "cake",
        "decorating",
        "decorator"
    ],
    "wof:name":"Three Tiers For You",
    "wof:placetype":"venue"
},
  "geometry": {"coordinates":[145.03016662600001,-37.7022819519],"type":"Point"}
}