{
  "type": "Feature",
  "properties": {
    "iso:country":"AU",
    "sg:address":"2145 Wynnum Rd",
    "sg:city":"Wynnum West",
    "sg:classifiers":[
        {
            "category":"Professional",
            "subcategory":"Computer Services",
            "type":"Services"
        }
    ],
    "sg:phone":"+61 7 3393 4404",
    "sg:postcode":"4178",
    "sg:province":"QLD",
    "sg:tags":[
        "equipment",
        "networking",
        "installation"
    ],
    "wof:name":"CPU Computers",
    "wof:placetype":"venue"
},
  "geometry": {"coordinates":[153.158004761,-27.4485797882],"type":"Point"}
}