{
  "type": "Feature",
  "properties": {
    "iso:country":"AU",
    "sg:address":"150 Brighton Ave",
    "sg:city":"Toronto",
    "sg:classifiers":[
        {
            "category":"Government",
            "subcategory":"Court House",
            "type":"Public Place"
        }
    ],
    "sg:phone":"+61 419 161 516",
    "sg:postcode":"2283",
    "sg:province":"NSW",
    "sg:tags":[
        "personal",
        "marriage",
        "family",
        "counselling"
    ],
    "wof:name":"Ellamentary Counselling & Piano",
    "wof:placetype":"venue"
},
  "geometry": {"coordinates":[151.593185425,-33.0144081116],"type":"Point"}
}