{
  "type": "Feature",
  "properties": {
    "addr:full":"PO Box 7240 Kariong NSW 2250",
    "addr:postcode":"2250",
    "iso:country":"AU",
    "sg:address":"PO Box 7240",
    "sg:city":"Kariong",
    "sg:classifiers":[
        {
            "category":"Building & Trades",
            "subcategory":"Construction",
            "type":"Services"
        }
    ],
    "sg:phone":"+61 407 490 496",
    "sg:postcode":"2250",
    "sg:province":"NSW",
    "sg:tags":[
        "joiner",
        "carpenter"
    ],
    "wof:name":"Phoenix Quality Builders",
    "wof:placetype":"venue"
},
  "geometry": {"coordinates":[151.29620361299999,-33.438331604],"type":"Point"}
}