{
  "type": "Feature",
  "properties": {
    "iso:country":"AU",
    "sg:address":"Mitchell Rd",
    "sg:city":"Cronulla",
    "sg:classifiers":[
        {
            "category":"Arena",
            "subcategory":"Sports Club",
            "type":"Entertainment"
        }
    ],
    "sg:phone":"+61 2 9523 7295",
    "sg:postcode":"2230",
    "sg:province":"NSW",
    "sg:tags":[
        "life",
        "surfing",
        "saving"
    ],
    "wof:name":"Elouera Surf Lifesaving Club",
    "wof:placetype":"venue"
},
  "geometry": {"coordinates":[151.15516662600001,-34.050163269],"type":"Point"}
}