{
  "type": "Feature",
  "properties": {
    "addr:full":"12 Station St Moorabbin VIC 3189",
    "addr:housenumber":"12",
    "addr:postcode":"3189",
    "addr:street":"Station St",
    "iso:country":"AU",
    "sg:address":"12 Station St",
    "sg:city":"Moorabbin",
    "sg:classifiers":[
        {
            "category":"Health Services",
            "subcategory":"Dentist",
            "type":"Services"
        }
    ],
    "sg:phone":"+61 3 9553 1249",
    "sg:postcode":"3189",
    "sg:province":"VIC",
    "sg:website":"http://www.lewelldental.com.au",
    "wof:name":"Lewell Dental",
    "wof:placetype":"venue"
},
  "geometry": {"coordinates":[145.03729248100001,-37.9347763062],"type":"Point"}
}