{
  "type": "Feature",
  "properties": {
    "addr:full":"Unit 10 16 Keegan St O'Connor WA 6163",
    "addr:housenumber":"16",
    "addr:postcode":"6163",
    "addr:street":"Keegan St",
    "iso:country":"AU",
    "sg:address":"Unit 10 16 Keegan St",
    "sg:city":"O'Connor",
    "sg:classifiers":[
        {
            "category":"Building & Trades",
            "subcategory":"Construction",
            "type":"Services"
        }
    ],
    "sg:phone":"+61 412 914 129",
    "sg:postcode":"6163",
    "sg:province":"WA",
    "sg:tags":[
        "builder",
        "designer",
        "room",
        "cool"
    ],
    "wof:name":"Scott Refrigeration & Airconditioning",
    "wof:placetype":"venue"
},
  "geometry": {"coordinates":[115.79557,-32.061398],"type":"Point"}
}