{
  "type": "Feature",
  "properties": {
    "addr:full":"21 Pritchard St Swan Hill NSW 3585",
    "addr:housenumber":"21",
    "addr:postcode":"3585",
    "addr:street":"Pritchard St",
    "iso:country":"AU",
    "sg:address":"21 Pritchard St",
    "sg:city":"Swan Hill",
    "sg:classifiers":[
        {
            "category":"Sports & Exercise",
            "subcategory":"Gym",
            "type":"Entertainment"
        }
    ],
    "sg:phone":"+61 3 5032 5222",
    "sg:postcode":"3585",
    "sg:province":"NSW",
    "sg:tags":[
        "health",
        "fitness"
    ],
    "wof:name":"Swan Hill Leisure Centre",
    "wof:placetype":"venue"
},
  "geometry": {"coordinates":[143.55131499999999,-35.337563],"type":"Point"}
}