{
  "type": "Feature",
  "properties": {
    "addr:full":"527 Princes Hwy Noble Park VIC 3174",
    "addr:housenumber":"527",
    "addr:postcode":"3174",
    "addr:street":"Princes Hwy",
    "iso:country":"AU",
    "sg:address":"527 Princes Hwy",
    "sg:city":"Noble Park",
    "sg:classifiers":[
        {
            "category":"Professional",
            "subcategory":"Business Services",
            "type":"Services"
        }
    ],
    "sg:phone":"+61 3 9546 0261",
    "sg:postcode":"3174",
    "sg:province":"VIC",
    "sg:tags":[
        "drafting"
    ],
    "wof:name":"Noble Steel Drafters",
    "wof:placetype":"venue"
},
  "geometry": {"coordinates":[145.17657470699999,-37.9514808655],"type":"Point"}
}