{
  "type": "Feature",
  "properties": {
    "addr:full":"1 Mary Ellen Crs Goonellabah NSW 2480",
    "addr:housenumber":"1",
    "addr:postcode":"2480",
    "addr:street":"Mary Ellen Crs",
    "iso:country":"AU",
    "sg:address":"1 Mary Ellen Crs",
    "sg:city":"Goonellabah",
    "sg:classifiers":[
        {
            "category":"Personal",
            "subcategory":"Beauty Salon",
            "type":"Services"
        }
    ],
    "sg:phone":"+61 2 6624 7551",
    "sg:postcode":"2480",
    "sg:province":"NSW",
    "sg:tags":[
        "hairdresser"
    ],
    "wof:name":"Snipz Hair Design",
    "wof:placetype":"venue"
},
  "geometry": {"coordinates":[153.33561706500001,-28.8171806335],"type":"Point"}
}