{
  "type": "Feature",
  "properties": {
    "iso:country":"AU",
    "sg:address":"616 Stanley St",
    "sg:city":"Woolloongabba",
    "sg:classifiers":[
        {
            "category":"Internet Cafe",
            "subcategory":"None",
            "type":"Food & Drink"
        }
    ],
    "sg:phone":"+61 7 3846 0445",
    "sg:postcode":"4102",
    "sg:province":"QLD",
    "wof:name":"AFK Cafe",
    "wof:placetype":"venue"
},
  "geometry": {"coordinates":[153.02986145,-27.4854106903],"type":"Point"}
}