{
  "type": "Feature",
  "properties": {
    "iso:country":"AU",
    "sg:address":"PO Box 800",
    "sg:city":"Nedlands",
    "sg:classifiers":[
        {
            "category":"Education",
            "subcategory":"Dance Studio",
            "type":"Public Place"
        }
    ],
    "sg:phone":"+61 411 460 660",
    "sg:postcode":"6009",
    "sg:province":"WA",
    "sg:tags":[
        "instruction",
        "language"
    ],
    "wof:name":"Turkish Language & Translation Services Nedlands",
    "wof:placetype":"venue"
},
  "geometry": {"coordinates":[115.803146,-31.9792],"type":"Point"}
}