{
  "type": "Feature",
  "properties": {
    "addr:full":"23 Light St Fortitude Valley QLD 4006",
    "addr:housenumber":"23",
    "addr:postcode":"4006",
    "addr:street":"Light St",
    "iso:country":"AU",
    "sg:address":"23 Light St",
    "sg:city":"Fortitude Valley",
    "sg:classifiers":[
        {
            "category":"Insurance",
            "subcategory":"Life Insurance",
            "type":"Services"
        }
    ],
    "sg:phone":"+61 7 3854 1730",
    "sg:postcode":"4006",
    "sg:province":"QLD",
    "wof:name":"Oracle Risk Management",
    "wof:placetype":"venue"
},
  "geometry": {"coordinates":[153.03828430199999,-27.4513511658],"type":"Point"}
}