{
  "type": "Feature",
  "properties": {
    "addr:full":"16 Glenview Crs Frankston VIC 3199",
    "addr:housenumber":"16",
    "addr:postcode":"3199",
    "addr:street":"Glenview Crs",
    "iso:country":"AU",
    "sg:address":"16 Glenview Crs",
    "sg:city":"Frankston",
    "sg:classifiers":[
        {
            "category":"Building & Trades",
            "subcategory":"Construction",
            "type":"Services"
        }
    ],
    "sg:phone":"+61 3 9789 6022",
    "sg:postcode":"3199",
    "sg:province":"VIC",
    "sg:tags":[
        "fencing",
        "contractor"
    ],
    "wof:name":"Bradshaw G & S",
    "wof:placetype":"venue"
},
  "geometry": {"coordinates":[145.283004761,-37.9099082947],"type":"Point"}
}