{
  "type": "Feature",
  "properties": {
    "iso:country":"AU",
    "sg:address":"195 Elizabeth St",
    "sg:city":"Brisbane",
    "sg:classifiers":[
        {
            "category":"Shopping",
            "subcategory":"Music",
            "type":"Retail Goods"
        }
    ],
    "sg:phone":"+61 7 3210 0550",
    "sg:postcode":"4000",
    "sg:province":"QLD",
    "sg:tags":[
        "store"
    ],
    "wof:name":"Central Station Records",
    "wof:placetype":"venue"
},
  "geometry": {"coordinates":[153.02734375,-27.4695205688],"type":"Point"}
}