{
  "type": "Feature",
  "properties": {
    "addr:full":"20 Sturt Ave Hawthorndene SA 5051",
    "addr:housenumber":"20",
    "addr:postcode":"5051",
    "addr:street":"Sturt Ave",
    "iso:country":"AU",
    "sg:address":"20 Sturt Ave",
    "sg:city":"Hawthorndene",
    "sg:classifiers":[
        {
            "category":"Professional",
            "subcategory":"Art Services",
            "type":"Services"
        }
    ],
    "sg:phone":"+61 8 8278 5298",
    "sg:postcode":"5051",
    "sg:province":"SA",
    "sg:tags":[
        "graphic",
        "designer"
    ],
    "wof:name":"Smeets Peter Artwork & Design",
    "wof:placetype":"venue"
},
  "geometry": {"coordinates":[138.62713600000001,-35.024578],"type":"Point"}
}