{
  "type": "Feature",
  "properties": {
    "iso:country":"AU",
    "sg:address":"157 Granite St",
    "sg:city":"Geebung",
    "sg:classifiers":[
        {
            "category":"Wholesale",
            "subcategory":"Metals & Minerals",
            "type":"Manufacturing & Wholesale Goods"
        }
    ],
    "sg:phone":"+61 7 3865 1169",
    "sg:postcode":"4034",
    "sg:province":"QLD",
    "sg:tags":[
        "steel",
        "stainless",
        "product",
        "equipment"
    ],
    "wof:name":"Aquadux Pty Ltd",
    "wof:placetype":"venue"
},
  "geometry": {"coordinates":[153.05429100000001,-27.364996],"type":"Point"}
}