{
  "type": "Feature",
  "properties": {
    "iso:country":"AU",
    "sg:address":"17 Bellvue St",
    "sg:city":"Preston",
    "sg:classifiers":[
        {
            "category":"Autos & Motor Vehicles",
            "subcategory":"Boat Sales",
            "type":"Retail Goods"
        }
    ],
    "sg:phone":"+61 1300 303 765",
    "sg:postcode":"3072",
    "sg:province":"VIC",
    "sg:tags":[
        "yacht"
    ],
    "wof:name":"Australian Car Buying Group",
    "wof:placetype":"venue"
},
  "geometry": {"coordinates":[144.97703552199999,-37.7666053772],"type":"Point"}
}