{
  "type": "Feature",
  "properties": {
    "addr:full":"Deloraine Ave Urangan QLD 4655",
    "addr:postcode":"4655",
    "addr:street":"Deloraine Ave",
    "iso:country":"AU",
    "sg:address":"Deloraine Ave",
    "sg:city":"Urangan",
    "sg:classifiers":[
        {
            "category":"Building & Trades",
            "subcategory":"Construction",
            "type":"Services"
        }
    ],
    "sg:phone":"+61 417 753 275",
    "sg:postcode":"4655",
    "sg:province":"QLD",
    "sg:tags":[
        "pool",
        "swimming"
    ],
    "wof:name":"C Walker",
    "wof:placetype":"venue"
},
  "geometry": {"coordinates":[152.89575199999999,-25.298901],"type":"Point"}
}