{
  "type": "Feature",
  "properties": {
    "addr:full":"U2/ 11 Timms Crt Woodridge QLD 4114",
    "addr:housenumber":"11",
    "addr:postcode":"4114",
    "addr:street":"U2 /;Timms Crt",
    "iso:country":"AU",
    "sg:address":"U2/ 11 Timms Crt",
    "sg:city":"Woodridge",
    "sg:classifiers":[
        {
            "category":"Recreation",
            "subcategory":"Picnic Area",
            "type":"Entertainment"
        }
    ],
    "sg:phone":"+61 7 3299 2622",
    "sg:postcode":"4114",
    "sg:province":"QLD",
    "sg:tags":[
        "snap",
        "fastener",
        "slide"
    ],
    "wof:name":"M J Management & Distribution",
    "wof:placetype":"venue"
},
  "geometry": {"coordinates":[153.10700988799999,-27.620349884],"type":"Point"}
}