{
  "type": "Feature",
  "properties": {
    "iso:country":"AU",
    "sg:address":"10 Sandridge Rd",
    "sg:city":"Bunbury",
    "sg:classifiers":[
        {
            "category":"Autos & Motor Vehicles",
            "subcategory":"Automobile Sales",
            "type":"Retail Goods"
        }
    ],
    "sg:phone":"+61 8 9721 3522",
    "sg:postcode":"6230",
    "sg:province":"WA",
    "sg:tags":[
        "equipment",
        "trailer"
    ],
    "wof:name":"Bunbury Bearings",
    "wof:placetype":"venue"
},
  "geometry": {"coordinates":[115.648178,-33.341118],"type":"Point"}
}