{
  "type": "Feature",
  "properties": {
    "addr:full":"27 Whitehouse St Garbutt QLD 4814",
    "addr:housenumber":"27",
    "addr:postcode":"4814",
    "addr:street":"Whitehouse St",
    "iso:country":"AU",
    "sg:address":"27 Whitehouse St",
    "sg:city":"Garbutt",
    "sg:classifiers":[
        {
            "category":"Freight",
            "type":"Transportation"
        }
    ],
    "sg:phone":"+61 7 4775 1744",
    "sg:postcode":"4814",
    "sg:province":"QLD",
    "sg:tags":[
        "light",
        "carrier"
    ],
    "wof:name":"Superior Messenger Service",
    "wof:placetype":"venue"
},
  "geometry": {"coordinates":[146.755066,-19.269295],"type":"Point"}
}