{
  "type": "Feature",
  "properties": {
    "addr:full":"2/ 7 Rouse Rd Mandurah WA 6210",
    "addr:housenumber":"/ 7",
    "addr:postcode":"6210",
    "addr:street":"Rouse Rd",
    "iso:country":"AU",
    "sg:address":"2/ 7 Rouse Rd",
    "sg:city":"Mandurah",
    "sg:classifiers":[
        {
            "category":"Professional",
            "type":"Services"
        }
    ],
    "sg:phone":"+61 8 9582 0998",
    "sg:postcode":"6210",
    "sg:province":"WA",
    "sg:tags":[
        "transport"
    ],
    "wof:name":"Dudley Park Courier Service",
    "wof:placetype":"venue"
},
  "geometry": {"coordinates":[115.75058,-32.514706],"type":"Point"}
}