{
  "type": "Feature",
  "properties": {
    "iso:country":"AU",
    "sg:address":"66 Dulwich Ave",
    "sg:city":"Dulwich",
    "sg:classifiers":[
        {
            "category":"Food & Beverages",
            "subcategory":"Bakery",
            "type":"Retail Goods"
        }
    ],
    "sg:phone":"+61 8 8364 1836",
    "sg:postcode":"5065",
    "sg:province":"SA",
    "sg:tags":[
        "baker"
    ],
    "wof:name":"Dulwich Bakery",
    "wof:placetype":"venue"
},
  "geometry": {"coordinates":[138.631347656,-34.9351501465],"type":"Point"}
}