{
  "type": "Feature",
  "properties": {
    "iso:country":"AU",
    "sg:address":"234 Wollombi Rd",
    "sg:city":"Cessnock",
    "sg:classifiers":[
        {
            "category":"Travel",
            "subcategory":"Hotels & Motels",
            "type":"Entertainment"
        }
    ],
    "sg:phone":"+61 2 4990 1002",
    "sg:postcode":"2325",
    "sg:province":"NSW",
    "sg:tags":[
        "accommodation"
    ],
    "wof:name":"Cessnock Hotel",
    "wof:placetype":"venue"
},
  "geometry": {"coordinates":[151.35647582999999,-32.8319168091],"type":"Point"}
}