{
  "type": "Feature",
  "properties": {
    "addr:full":"44 Queen St Ulverstone TAS 7315",
    "addr:housenumber":"44",
    "addr:postcode":"7315",
    "addr:street":"Queen St",
    "iso:country":"AU",
    "sg:address":"44 Queen St",
    "sg:city":"Ulverstone",
    "sg:classifiers":[
        {
            "category":"Personal",
            "subcategory":"Massage",
            "type":"Services"
        }
    ],
    "sg:phone":"+61 3 6425 5574",
    "sg:postcode":"7315",
    "sg:province":"TAS",
    "sg:tags":[
        "therapy"
    ],
    "wof:name":"Bellchambers Paul",
    "wof:placetype":"venue"
},
  "geometry": {"coordinates":[146.16355895999999,-41.1518363953],"type":"Point"}
}