{
  "type": "Feature",
  "properties": {
    "iso:country":"AU",
    "sg:address":"444 Cambridge St",
    "sg:city":"Floreat",
    "sg:classifiers":[
        {
            "category":"Professional",
            "subcategory":"Engineering",
            "type":"Services"
        }
    ],
    "sg:phone":"+61 8 9285 8611",
    "sg:postcode":"6014",
    "sg:province":"WA",
    "sg:tags":[
        "engineer",
        "designing"
    ],
    "wof:name":"Sigma Delta Technologies Pty Ltd",
    "wof:placetype":"venue"
},
  "geometry": {"coordinates":[115.800926209,-31.9406452179],"type":"Point"}
}