{
  "type": "Feature",
  "properties": {
    "addr:full":"Unit 1/ 5 Cook Drv Coffs Harbour NSW 2450",
    "addr:postcode":"2450",
    "addr:street":"Cook Drv",
    "iso:country":"AU",
    "sg:address":"Unit 1/ 5 Cook Drv",
    "sg:city":"Coffs Harbour",
    "sg:classifiers":[
        {
            "category":"Autos & Motor Vehicles",
            "subcategory":"Auto Supplies",
            "type":"Retail Goods"
        }
    ],
    "sg:phone":"+61 2 6651 9255",
    "sg:postcode":"2450",
    "sg:province":"NSW",
    "sg:tags":[
        "paint",
        "automotive"
    ],
    "wof:name":"Ward's Auto Paint Supplies",
    "wof:placetype":"venue"
},
  "geometry": {"coordinates":[153.097183,-30.314667],"type":"Point"}
}