{
  "type": "Feature",
  "properties": {
    "addr:full":"PO Box 533 Wagga Wagga NSW 2650",
    "addr:postcode":"2650",
    "iso:country":"AU",
    "sg:address":"PO Box 533",
    "sg:city":"Wagga Wagga",
    "sg:classifiers":[
        {
            "category":"Professional",
            "subcategory":"Art Services",
            "type":"Services"
        }
    ],
    "sg:phone":"+61 418 693 781",
    "sg:postcode":"2650",
    "sg:province":"NSW",
    "sg:tags":[
        "interior",
        "designer"
    ],
    "wof:name":"Willdesign",
    "wof:placetype":"venue"
},
  "geometry": {"coordinates":[147.395629883,-35.1227111816],"type":"Point"}
}