{
  "type": "Feature",
  "properties": {
    "addr:full":"11 Norray Ave Mt Waverley VIC 3149",
    "addr:housenumber":"11",
    "addr:postcode":"3149",
    "addr:street":"Norray Ave Mt",
    "iso:country":"AU",
    "sg:address":"11 Norray Ave",
    "sg:city":"Mt Waverley",
    "sg:classifiers":[
        {
            "category":"Building & Trades",
            "subcategory":"Plumbing",
            "type":"Services"
        }
    ],
    "sg:phone":"+61 3 9808 9494",
    "sg:postcode":"3149",
    "sg:province":"VIC",
    "sg:tags":[
        "plumber",
        "gasfitters"
    ],
    "wof:name":"A. Phil Morrison Plumbing",
    "wof:placetype":"venue"
},
  "geometry": {"coordinates":[145.132354736,-37.8634567261],"type":"Point"}
}