{
  "type": "Feature",
  "properties": {
    "iso:country":"AU",
    "sg:address":"100 Eagle St",
    "sg:city":"Brisbane",
    "sg:classifiers":[
        {
            "category":"Professional",
            "subcategory":"Employment Agencies",
            "type":"Services"
        }
    ],
    "sg:phone":"+61 7 3016 6655",
    "sg:postcode":"4000",
    "sg:province":"QLD",
    "sg:tags":[
        "hire",
        "labour",
        "contractor"
    ],
    "wof:name":"QPL",
    "wof:placetype":"venue"
},
  "geometry": {"coordinates":[153.030059814,-27.4675216675],"type":"Point"}
}