{
  "type": "Feature",
  "properties": {
    "addr:full":"29 Hayward St Stafford QLD 4053",
    "addr:housenumber":"29",
    "addr:postcode":"4053",
    "addr:street":"Hayward St",
    "iso:country":"AU",
    "sg:address":"29 Hayward St",
    "sg:city":"Stafford",
    "sg:classifiers":[
        {
            "category":"Retail",
            "subcategory":"Auto Repair",
            "type":"Services"
        }
    ],
    "sg:phone":"+61 7 3856 5047",
    "sg:postcode":"4053",
    "sg:province":"QLD",
    "sg:tags":[
        "engine",
        "reconditioning"
    ],
    "sg:website":"http://www.quickfitengineservice.com.au",
    "wof:name":"Quick Fit Engine Service",
    "wof:placetype":"venue"
},
  "geometry": {"coordinates":[153.01411438,-27.415096283],"type":"Point"}
}