{
  "type": "Feature",
  "properties": {
    "addr:full":"69 Parramatta Rd Lidcombe NSW 2141",
    "addr:housenumber":"69",
    "addr:postcode":"2141",
    "addr:street":"Parramatta Rd",
    "iso:country":"AU",
    "sg:address":"69 Parramatta Rd",
    "sg:city":"Lidcombe",
    "sg:classifiers":[
        {
            "category":"Wholesale",
            "subcategory":"Music Publishers",
            "type":"Manufacturing & Wholesale Goods"
        }
    ],
    "sg:phone":"+61 2 9748 6055",
    "sg:postcode":"2141",
    "sg:province":"NSW",
    "sg:tags":[
        "wholesaler",
        "dvd",
        "mfrs",
        "cd"
    ],
    "wof:name":"Outback Music",
    "wof:placetype":"venue"
},
  "geometry": {"coordinates":[151.043457031,-33.8456268311],"type":"Point"}
}