{
  "type": "Feature",
  "properties": {
    "addr:full":"Shp 1/ 62 Prince St Busselton WA 6280",
    "addr:housenumber":"/ 62",
    "addr:postcode":"6280",
    "addr:street":"Prince St",
    "iso:country":"AU",
    "sg:address":"Shp 1/ 62 Prince St",
    "sg:city":"Busselton",
    "sg:classifiers":[
        {
            "category":"Shopping",
            "subcategory":"Crafts & Fabrics",
            "type":"Retail Goods"
        }
    ],
    "sg:phone":"+61 8 9751 5911",
    "sg:postcode":"6280",
    "sg:province":"WA",
    "sg:tags":[
        "supply"
    ],
    "wof:name":"Ormalu Beads",
    "wof:placetype":"venue"
},
  "geometry": {"coordinates":[115.34645080599999,-33.6508216858],"type":"Point"}
}