{
  "type": "Feature",
  "properties": {
    "addr:full":"Forest Lake Blv Forest Lake QLD 4078",
    "addr:postcode":"4078",
    "addr:street":"Forest Lake Blv",
    "iso:country":"AU",
    "sg:address":"Forest Lake Blv",
    "sg:city":"Forest Lake",
    "sg:classifiers":[
        {
            "category":"Shopping",
            "subcategory":"Clothing, Apparel, & Fashions",
            "type":"Retail Goods"
        }
    ],
    "sg:phone":"+61 7 3278 8380",
    "sg:postcode":"4078",
    "sg:province":"QLD",
    "sg:tags":[
        "lady",
        "wear"
    ],
    "wof:name":"Rockmans Stores Pty Limited",
    "wof:placetype":"venue"
},
  "geometry": {"coordinates":[153.02505493199999,-27.6665706635],"type":"Point"}
}