{
  "type": "Feature",
  "properties": {
    "addr:full":"52 Broadmeadow Rd Broadmeadow NSW 2292",
    "addr:housenumber":"52",
    "addr:postcode":"2292",
    "addr:street":"Broadmeadow Rd",
    "iso:country":"AU",
    "sg:address":"52 Broadmeadow Rd",
    "sg:city":"Broadmeadow",
    "sg:classifiers":[
        {
            "category":"Retail",
            "subcategory":"Auto Repair",
            "type":"Services"
        }
    ],
    "sg:phone":"+61 2 4969 1175",
    "sg:postcode":"2292",
    "sg:province":"NSW",
    "sg:tags":[
        "repairer",
        "motor",
        "engineer"
    ],
    "wof:name":"Broadmeadow Pitt Stop",
    "wof:placetype":"venue"
},
  "geometry": {"coordinates":[151.732055664,-32.9162750244],"type":"Point"}
}