{
  "type": "Feature",
  "properties": {
    "addr:full":"Schnapper Creek Rd Tin Can Bay QLD 4580",
    "addr:postcode":"4580",
    "addr:street":"Creek Rd",
    "iso:country":"AU",
    "sg:address":"Schnapper Creek Rd",
    "sg:city":"Tin Can Bay",
    "sg:classifiers":[
        {
            "category":"Education",
            "subcategory":"School",
            "type":"Public Place"
        }
    ],
    "sg:phone":"+61 7 5488 1222",
    "sg:postcode":"4580",
    "sg:province":"QLD",
    "sg:tags":[
        "state",
        "except",
        "nsw"
    ],
    "wof:name":"Tin Can Bay Primary School",
    "wof:placetype":"venue"
},
  "geometry": {"coordinates":[152.99282836899999,-25.9243831635],"type":"Point"}
}