{
  "type": "Feature",
  "properties": {
    "addr:full":"5 Treetop Crt Narre Warren South VIC 3805",
    "addr:housenumber":"5",
    "addr:postcode":"3805",
    "addr:street":"Treetop Crt",
    "iso:country":"AU",
    "sg:address":"5 Treetop Crt",
    "sg:city":"Narre Warren South",
    "sg:classifiers":[
        {
            "category":"Arts & Performance",
            "subcategory":"Dance",
            "type":"Entertainment"
        }
    ],
    "sg:phone":"+61 3 9705 2919",
    "sg:postcode":"3805",
    "sg:province":"VIC",
    "sg:tags":[
        "theatrical",
        "ballet",
        "tuition"
    ],
    "wof:name":"Karen May School Of Dance",
    "wof:placetype":"venue"
},
  "geometry": {"coordinates":[145.317474,-38.056248],"type":"Point"}
}