{
  "type": "Feature",
  "properties": {
    "addr:full":"Tourist Drv Dandaragan East WA 6507",
    "addr:postcode":"6507",
    "addr:street":"Tourist Drv",
    "iso:country":"AU",
    "sg:address":"Tourist Drv",
    "sg:city":"Dandaragan East",
    "sg:classifiers":[
        {
            "category":"Farming",
            "subcategory":"Farm",
            "type":"Manufacturing & Wholesale Goods"
        }
    ],
    "sg:phone":"+61 8 9651 3031",
    "sg:postcode":"6507",
    "sg:province":"WA",
    "sg:tags":[
        "farmer"
    ],
    "wof:name":"Moltoni C & T",
    "wof:placetype":"venue"
},
  "geometry": {"coordinates":[115.696198,-30.750675],"type":"Point"}
}