{
  "type": "Feature",
  "properties": {
    "addr:full":"394 Darling St Balmain NSW 2041",
    "addr:housenumber":"394",
    "addr:postcode":"2041",
    "addr:street":"Darling St",
    "iso:country":"AU",
    "sg:address":"394 Darling St",
    "sg:city":"Balmain",
    "sg:classifiers":[
        {
            "category":"Health Services",
            "subcategory":"Dentist",
            "type":"Services"
        }
    ],
    "sg:phone":"+61 1800 336 891",
    "sg:postcode":"2041",
    "sg:province":"NSW",
    "sg:tags":[
        "dental",
        "prosthetist"
    ],
    "wof:name":"Natural Looking Dentures",
    "wof:placetype":"venue"
},
  "geometry": {"coordinates":[151.175308,-33.856068],"type":"Point"}
}