{
  "type": "Feature",
  "properties": {
    "iso:country":"AU",
    "sg:address":"PO Box 979",
    "sg:city":"Kent Town",
    "sg:classifiers":[
        {
            "category":"Building & Trades",
            "subcategory":"Construction",
            "type":"Services"
        }
    ],
    "sg:phone":"+61 1300 551 301",
    "sg:postcode":"5071",
    "sg:province":"SA",
    "sg:tags":[
        "contractor"
    ],
    "wof:name":"Danlaid Contracting Pty Ltd",
    "wof:placetype":"venue"
},
  "geometry": {"coordinates":[138.616363525,-34.9215393066],"type":"Point"}
}