{
  "type": "Feature",
  "properties": {
    "addr:full":"112 Burelli St Wollongong NSW 2500",
    "addr:housenumber":"112",
    "addr:postcode":"2500",
    "addr:street":"Burelli St",
    "iso:country":"AU",
    "sg:address":"112 Burelli St",
    "sg:city":"Wollongong",
    "sg:classifiers":[
        {
            "category":"Travel",
            "subcategory":"Hotels & Motels",
            "type":"Entertainment"
        }
    ],
    "sg:phone":"+61 2 4229 7444",
    "sg:postcode":"2500",
    "sg:province":"NSW",
    "sg:tags":[
        "accommodation"
    ],
    "wof:name":"Quality Hotel City Pacific",
    "wof:placetype":"venue"
},
  "geometry": {"coordinates":[150.88980100000001,-34.426346],"type":"Point"}
}