{
  "type": "Feature",
  "properties": {
    "iso:country":"AU",
    "sg:address":"Shop 1/ 291 Trower Rd",
    "sg:city":"Casuarina",
    "sg:classifiers":[
        {
            "category":"Personal",
            "type":"Services"
        }
    ],
    "sg:phone":"+61 8 8927 7419",
    "sg:postcode":"0810",
    "sg:province":"NT",
    "sg:tags":[
        "reducing",
        "treatment",
        "weight"
    ],
    "wof:name":"Curves Casuarina",
    "wof:placetype":"venue"
},
  "geometry": {"coordinates":[130.883499145,-12.3704385757],"type":"Point"}
}