{
  "type": "Feature",
  "properties": {
    "iso:country":"AU",
    "sg:address":"101 Logan River Rd",
    "sg:city":"Beenleigh",
    "sg:classifiers":[
        {
            "category":"Shopping",
            "type":"Retail Goods"
        }
    ],
    "sg:phone":"+61 7 3287 2796",
    "sg:postcode":"4207",
    "sg:province":"QLD",
    "sg:tags":[
        "produce",
        "grain"
    ],
    "wof:name":"Beenleigh Farm Supplies & Village Produce & Rural Supplies",
    "wof:placetype":"venue"
},
  "geometry": {"coordinates":[153.18380737300001,-27.7132759094],"type":"Point"}
}