{
  "type": "Feature",
  "properties": {
    "addr:full":"90 Alfred St Charleville QLD 4470",
    "addr:housenumber":"90",
    "addr:postcode":"4470",
    "addr:street":"Alfred St",
    "iso:country":"AU",
    "sg:address":"90 Alfred St",
    "sg:city":"Charleville",
    "sg:classifiers":[
        {
            "category":"Professional",
            "subcategory":"Employment Agencies",
            "type":"Services"
        }
    ],
    "sg:phone":"+61 1300 360 562",
    "sg:postcode":"4470",
    "sg:province":"QLD",
    "wof:name":"Jobfind Centre",
    "wof:placetype":"venue"
},
  "geometry": {"coordinates":[146.24256897000001,-26.3996562958],"type":"Point"}
}