{
  "type": "Feature",
  "properties": {
    "addr:full":"266 Sturt St Townsville City QLD 4810",
    "addr:housenumber":"266",
    "addr:postcode":"4810",
    "addr:street":"Sturt St",
    "iso:country":"AU",
    "sg:address":"266 Sturt St",
    "sg:city":"Townsville City",
    "sg:classifiers":[
        {
            "category":"Health Services",
            "subcategory":"Doctor",
            "type":"Services"
        }
    ],
    "sg:phone":"+61 7 4772 2999",
    "sg:postcode":"4810",
    "sg:province":"QLD",
    "sg:tags":[
        "podiatrist"
    ],
    "wof:name":"Fit Feet Podiatry Clinic",
    "wof:placetype":"venue"
},
  "geometry": {"coordinates":[146.813492,-19.262209],"type":"Point"}
}