{
  "type": "Feature",
  "properties": {
    "iso:country":"AU",
    "sg:address":"43 Buckingham Ave",
    "sg:city":"Springvale",
    "sg:classifiers":[
        {
            "category":"Autos & Motor Vehicles",
            "subcategory":"Auto Supplies",
            "type":"Retail Goods"
        }
    ],
    "sg:phone":"+61 3 9562 3463",
    "sg:postcode":"3171",
    "sg:province":"VIC",
    "sg:tags":[
        "accessory"
    ],
    "wof:name":"Saigon Auto Parts",
    "wof:placetype":"venue"
},
  "geometry": {"coordinates":[145.151046753,-37.9524688721],"type":"Point"}
}