{
  "type": "Feature",
  "properties": {
    "iso:country":"AU",
    "sg:address":"1 Violet St",
    "sg:city":"Katoomba",
    "sg:classifiers":[
        {
            "category":"Communications",
            "subcategory":"News Services",
            "type":"Services"
        }
    ],
    "sg:phone":"+61 1300 759 929",
    "sg:postcode":"2780",
    "sg:province":"NSW",
    "sg:tags":[
        "information",
        "tourist",
        "attractions"
    ],
    "wof:name":"Katoomba Scenic Railway",
    "wof:placetype":"venue"
},
  "geometry": {"coordinates":[150.298736572,-33.7286834717],"type":"Point"}
}