{
  "type": "Feature",
  "properties": {
    "iso:country":"AU",
    "sg:address":"PO Box 2833",
    "sg:city":"Rowville",
    "sg:classifiers":[
        {
            "category":"Professional",
            "subcategory":"Computer Services",
            "type":"Services"
        }
    ],
    "sg:phone":"+61 425 769 514",
    "sg:postcode":"3178",
    "sg:province":"VIC",
    "sg:tags":[
        "equipment",
        "networking",
        "installation"
    ],
    "wof:name":"Janda Solutions Pty Ltd",
    "wof:placetype":"venue"
},
  "geometry": {"coordinates":[145.24317932100001,-37.9258804321],"type":"Point"}
}