{
  "type": "Feature",
  "properties": {
    "addr:full":"Corrimal Tennis Centre Wilga St Corrimal NSW 2518",
    "addr:postcode":"2518",
    "addr:street":"St",
    "iso:country":"AU",
    "sg:address":"Corrimal Tennis Centre Wilga St",
    "sg:city":"Corrimal",
    "sg:classifiers":[
        {
            "category":"Sports & Exercise",
            "subcategory":"Sports Center",
            "type":"Entertainment"
        }
    ],
    "sg:phone":"+61 2 4283 4335",
    "sg:postcode":"2518",
    "sg:province":"NSW",
    "sg:tags":[
        "coach",
        "tennis"
    ],
    "wof:name":"Royle Greg",
    "wof:placetype":"venue"
},
  "geometry": {"coordinates":[150.89913899999999,-34.371326],"type":"Point"}
}