{
  "type": "Feature",
  "properties": {
    "addr:full":"430 Anzac Pde Kingsford NSW 2032",
    "addr:housenumber":"430",
    "addr:postcode":"2032",
    "addr:street":"Anzac Pde",
    "iso:country":"AU",
    "sg:address":"430 Anzac Pde",
    "sg:city":"Kingsford",
    "sg:classifiers":[
        {
            "category":"Fast Food",
            "type":"Food & Drink"
        }
    ],
    "sg:phone":"+61 2 9697 0011",
    "sg:postcode":"2032",
    "sg:province":"NSW",
    "sg:tags":[
        "away",
        "take"
    ],
    "wof:name":"Yong Gong Kitchen & Enlightment Pty Ltd",
    "wof:placetype":"venue"
},
  "geometry": {"coordinates":[151.22697448700001,-33.9216117859],"type":"Point"}
}