{
  "type": "Feature",
  "properties": {
    "iso:country":"AU",
    "sg:address":"Royal Adelaide Hospital, Main Entrance, Level 3, N",
    "sg:city":"Adelaide",
    "sg:classifiers":[
        {
            "category":"Personal",
            "subcategory":"Beauty Salon",
            "type":"Services"
        }
    ],
    "sg:phone":"+61 8 8224 0088",
    "sg:postcode":"5000",
    "sg:province":"SA",
    "sg:tags":[
        "hairdresser"
    ],
    "wof:name":"Hairific",
    "wof:placetype":"venue"
},
  "geometry": {"coordinates":[138.590408325,-34.9250106812],"type":"Point"}
}