{
  "type": "Feature",
  "properties": {
    "addr:full":"15 Moordale St Chapel Hill QLD 4069",
    "addr:housenumber":"15",
    "addr:postcode":"4069",
    "addr:street":"Moordale St",
    "iso:country":"AU",
    "sg:address":"15 Moordale St",
    "sg:city":"Chapel Hill",
    "sg:classifiers":[
        {
            "category":"Organizations",
            "subcategory":"Non-profit Organization",
            "type":"Services"
        }
    ],
    "sg:phone":"+61 7 3720 2345",
    "sg:postcode":"4069",
    "sg:province":"QLD",
    "sg:tags":[
        "support",
        "disability",
        "organisation"
    ],
    "wof:name":"Riding for Disabled Association of Queensland Inc",
    "wof:placetype":"venue"
},
  "geometry": {"coordinates":[152.959747314,-27.50522995],"type":"Point"}
}