{
  "type": "Feature",
  "properties": {
    "addr:full":"41 Pacific Hwy Tweed Heads South NSW 2486",
    "addr:housenumber":"41",
    "addr:postcode":"2486",
    "addr:street":"Pacific Hwy",
    "iso:country":"AU",
    "sg:address":"41 Pacific Hwy",
    "sg:city":"Tweed Heads South",
    "sg:classifiers":[
        {
            "category":"Autos & Motor Vehicles",
            "subcategory":"Automobile Sales",
            "type":"Retail Goods"
        }
    ],
    "sg:phone":"+61 7 5599 8855",
    "sg:postcode":"2486",
    "sg:province":"NSW",
    "sg:tags":[
        "car",
        "used"
    ],
    "wof:name":"Town & Country Car Sales",
    "wof:placetype":"venue"
},
  "geometry": {"coordinates":[153.541946411,-28.2063026428],"type":"Point"}
}