{
  "type": "Feature",
  "properties": {
    "addr:full":"130 Gilba Rd Girraween NSW 2145",
    "addr:housenumber":"130",
    "addr:postcode":"2145",
    "addr:street":"Gilba Rd",
    "iso:country":"AU",
    "sg:address":"130 Gilba Rd",
    "sg:city":"Girraween",
    "sg:classifiers":[
        {
            "category":"Shopping",
            "type":"Retail Goods"
        }
    ],
    "sg:phone":"+61 2 9896 8644",
    "sg:postcode":"2145",
    "sg:province":"NSW",
    "sg:tags":[
        "equipment",
        "safety",
        "accessory"
    ],
    "wof:name":"Roofsafe Industrial Safety",
    "wof:placetype":"venue"
},
  "geometry": {"coordinates":[150.94212341299999,-33.7974586487],"type":"Point"}
}