{
  "type": "Feature",
  "properties": {
    "addr:full":"Albany Hwy Williams WA 6391",
    "addr:postcode":"6391",
    "addr:street":"Albany Hwy",
    "iso:country":"AU",
    "sg:address":"Albany Hwy",
    "sg:city":"Williams",
    "sg:classifiers":[
        {
            "category":"Autos & Motor Vehicles",
            "subcategory":"Fuel & Gas Station",
            "type":"Retail Goods"
        }
    ],
    "sg:phone":"+61 8 9885 1104",
    "sg:postcode":"6391",
    "sg:province":"WA",
    "wof:name":"Caltex",
    "wof:placetype":"venue"
},
  "geometry": {"coordinates":[116.878082275,-33.0242958069],"type":"Point"}
}