{
  "type": "Feature",
  "properties": {
    "iso:country":"AU",
    "sg:address":"54a Carrier St",
    "sg:city":"Benalla",
    "sg:classifiers":[
        {
            "category":"Personal",
            "subcategory":"Skin Care",
            "type":"Services"
        }
    ],
    "sg:phone":"+61 3 5762 8404",
    "sg:postcode":"3672",
    "sg:province":"VIC",
    "sg:tags":[
        "treatment"
    ],
    "wof:name":"Lavish Skin Therapy Clinic",
    "wof:placetype":"venue"
},
  "geometry": {"coordinates":[145.985413,-36.550365],"type":"Point"}
}