{
  "type": "Feature",
  "properties": {
    "addr:full":"90 Market St South Melbourne VIC 3205",
    "addr:housenumber":"90",
    "addr:postcode":"3205",
    "addr:street":"Market St",
    "iso:country":"AU",
    "sg:address":"90 Market St",
    "sg:city":"South Melbourne",
    "sg:classifiers":[
        {
            "category":"Autos & Motor Vehicles",
            "subcategory":"Automobile Sales",
            "type":"Retail Goods"
        }
    ],
    "sg:phone":"+61 3 9699 6711",
    "sg:postcode":"3205",
    "sg:province":"VIC",
    "sg:tags":[
        "car",
        "new"
    ],
    "wof:name":"Lamborghini Melbourne - Service",
    "wof:placetype":"venue"
},
  "geometry": {"coordinates":[144.95829800000001,-37.829762],"type":"Point"}
}