{
  "type": "Feature",
  "properties": {
    "addr:full":"3 Bass Crt Heathmont VIC 3135",
    "addr:housenumber":"3",
    "addr:postcode":"3135",
    "addr:street":"Bass Crt",
    "iso:country":"AU",
    "sg:address":"3 Bass Crt",
    "sg:city":"Heathmont",
    "sg:classifiers":[
        {
            "category":"Manufacturing",
            "subcategory":"Tools & Machinery",
            "type":"Manufacturing & Wholesale Goods"
        }
    ],
    "sg:phone":"+61 3 9870 3694",
    "sg:postcode":"3135",
    "sg:province":"VIC",
    "sg:tags":[
        "manufactured",
        "specially",
        "designed"
    ],
    "wof:name":"Cannon Industrial Design P/L",
    "wof:placetype":"venue"
},
  "geometry": {"coordinates":[145.22857665999999,-37.8279876709],"type":"Point"}
}