{
  "type": "Feature",
  "properties": {
    "iso:country":"AU",
    "sg:address":"542 Footscray Rd",
    "sg:city":"West Melbourne",
    "sg:classifiers":[
        {
            "category":"Food & Beverages",
            "subcategory":"Fruits & Vegetables",
            "type":"Retail Goods"
        }
    ],
    "sg:phone":"+61 3 9258 6100",
    "sg:postcode":"3003",
    "sg:province":"VIC",
    "sg:tags":[
        "wholesale"
    ],
    "wof:name":"Melbourne Markets Wholesale Fruit & Vegetable Market",
    "wof:placetype":"venue"
},
  "geometry": {"coordinates":[144.92155456500001,-37.8076972961],"type":"Point"}
}