{
  "type": "Feature",
  "properties": {
    "iso:country":"AU",
    "sg:address":"82 Haldon St",
    "sg:city":"Lakemba",
    "sg:classifiers":[
        {
            "category":"Real Estate",
            "subcategory":"Real Estate Agent",
            "type":"Services"
        }
    ],
    "sg:phone":"+61 2 9750 0271",
    "sg:postcode":"2195",
    "sg:province":"NSW",
    "wof:name":"Century 21 K & L Realty",
    "wof:placetype":"venue"
},
  "geometry": {"coordinates":[151.077423,-33.920769],"type":"Point"}
}