{
  "type": "Feature",
  "properties": {
    "addr:full":"82 Haldon St Lakemba NSW 2195",
    "addr:housenumber":"82",
    "addr:postcode":"2195",
    "addr:street":"Haldon St",
    "iso:country":"AU",
    "sg:address":"82 Haldon St",
    "sg:city":"Lakemba",
    "sg:classifiers":[
        {
            "category":"Real Estate",
            "subcategory":"Real Estate Agent",
            "type":"Services"
        }
    ],
    "sg:phone":"+61 2 9750 0271",
    "sg:postcode":"2195",
    "sg:province":"NSW",
    "wof:name":"Century 21 K & L Realty",
    "wof:placetype":"venue"
},
  "geometry": {"coordinates":[151.07742300000001,-33.920769],"type":"Point"}
}