{
  "type": "Feature",
  "properties": {
    "iso:country":"AU",
    "sg:address":"143 Sir Donald Bradman Drv",
    "sg:city":"Hilton",
    "sg:classifiers":[
        {
            "category":"Professional",
            "subcategory":"Business Services",
            "type":"Services"
        }
    ],
    "sg:phone":"+61 8 8443 7944",
    "sg:postcode":"5033",
    "sg:province":"SA",
    "sg:tags":[
        "consultant",
        "promoter",
        "entertainment"
    ],
    "wof:name":"Mighty Good Entertainment",
    "wof:placetype":"venue"
},
  "geometry": {"coordinates":[138.56413269000001,-34.9323616028],"type":"Point"}
}