{
  "type": "Feature",
  "properties": {
    "addr:full":"Suite 8/ 32 Camberwell Rd Hawthorn East VIC 3123",
    "addr:housenumber":"32",
    "addr:postcode":"3123",
    "addr:street":"Camberwell Rd",
    "iso:country":"AU",
    "sg:address":"Suite 8/ 32 Camberwell Rd",
    "sg:city":"Hawthorn East",
    "sg:classifiers":[
        {
            "category":"Banks & Credit Unions",
            "subcategory":"Financial Services",
            "type":"Services"
        }
    ],
    "sg:phone":"+61 1300 889 918",
    "sg:postcode":"3123",
    "sg:province":"VIC",
    "sg:tags":[
        "loan",
        "finance",
        "mortgage"
    ],
    "wof:name":"Stellar Finance Pty Ltd",
    "wof:placetype":"venue"
},
  "geometry": {"coordinates":[145.04989624000001,-37.8256378174],"type":"Point"}
}