{
  "type": "Feature",
  "properties": {
    "iso:country":"AU",
    "sg:address":"10 Beltana Rd",
    "sg:city":"Pialligo",
    "sg:classifiers":[
        {
            "category":"Farming",
            "subcategory":"Orchard",
            "type":"Manufacturing & Wholesale Goods"
        }
    ],
    "sg:phone":"+61 2 6248 9228",
    "sg:postcode":"2609",
    "sg:province":"ACT",
    "sg:tags":[
        "pear",
        "apple",
        "grower"
    ],
    "wof:name":"Pialligo Apples",
    "wof:placetype":"venue"
},
  "geometry": {"coordinates":[149.18055725100001,-35.3069877625],"type":"Point"}
}