{
  "type": "Feature",
  "properties": {
    "iso:country":"AU",
    "sg:address":"64- 66 Rose St",
    "sg:city":"Wee Waa",
    "sg:classifiers":[
        {
            "category":"Professional",
            "subcategory":"Detective & Security Services",
            "type":"Services"
        }
    ],
    "sg:phone":"+61 428 142 061",
    "sg:postcode":"2388",
    "sg:province":"NSW",
    "sg:tags":[
        "consultant",
        "system"
    ],
    "wof:name":"Huggy Bear Security",
    "wof:placetype":"venue"
},
  "geometry": {"coordinates":[149.43797302199999,-30.2277450562],"type":"Point"}
}