{
  "type": "Feature",
  "properties": {
    "iso:country":"AU",
    "sg:address":"Wyong Rd",
    "sg:city":"Killarney Vale",
    "sg:classifiers":[
        {
            "category":"Food & Beverages",
            "subcategory":"Supermarket",
            "type":"Retail Goods"
        }
    ],
    "sg:phone":"+61 2 4332 7492",
    "sg:postcode":"2261",
    "sg:province":"NSW",
    "sg:tags":[
        "grocery",
        "store"
    ],
    "wof:name":"Bi-Lo Pty Limited",
    "wof:placetype":"venue"
},
  "geometry": {"coordinates":[151.46009799999999,-33.364826],"type":"Point"}
}