{
  "type": "Feature",
  "properties": {
    "addr:full":"40 Trevan Rd Lismore NSW 2480",
    "addr:housenumber":"40",
    "addr:postcode":"2480",
    "addr:street":"Trevan Rd",
    "iso:country":"AU",
    "sg:address":"40 Trevan Rd",
    "sg:city":"Lismore",
    "sg:classifiers":[
        {
            "category":"Retail",
            "subcategory":"Storage",
            "type":"Services"
        }
    ],
    "sg:phone":"+61 418 412 621",
    "sg:postcode":"2480",
    "sg:province":"NSW",
    "wof:name":"Hillside Storage",
    "wof:placetype":"venue"
},
  "geometry": {"coordinates":[153.272537231,-28.830039978],"type":"Point"}
}