{
  "type": "Feature",
  "properties": {
    "addr:full":"Bldg 13 , Sport & Recreation Centre, University of Wo NSW 2500",
    "addr:postcode":"2500",
    "iso:country":"AU",
    "sg:address":"Bldg 13",
    "sg:city":", Sport & Recreation Centre, University of Wo",
    "sg:classifiers":[
        {
            "category":"Health Services",
            "subcategory":"Health Practitioner",
            "type":"Services"
        }
    ],
    "sg:phone":"+61 2 4221 3057",
    "sg:postcode":"2500",
    "sg:province":"NSW",
    "sg:tags":[
        "dietitian"
    ],
    "wof:name":"Exercise Science and Rehabilitation Centre",
    "wof:placetype":"venue"
},
  "geometry": {"coordinates":[150.882645,-34.410782],"type":"Point"}
}