{
  "type": "Feature",
  "properties": {
    "addr:full":"PO Box 116 Yandina QLD 4561",
    "addr:postcode":"4561",
    "iso:country":"AU",
    "sg:address":"PO Box 116",
    "sg:city":"Yandina",
    "sg:classifiers":[
        {
            "category":"Building & Trades",
            "subcategory":"Construction",
            "type":"Services"
        }
    ],
    "sg:phone":"+61 408 885 454",
    "sg:postcode":"4561",
    "sg:province":"QLD",
    "sg:tags":[
        "concrete",
        "treatment",
        "repair"
    ],
    "wof:name":"Murray's Concrete Washing & Resealing",
    "wof:placetype":"venue"
},
  "geometry": {"coordinates":[152.956344605,-26.5604496002],"type":"Point"}
}