{
  "type": "Feature",
  "properties": {
    "iso:country":"AU",
    "sg:address":"PO Box 5356",
    "sg:city":"Chittaway Bay",
    "sg:classifiers":[
        {
            "category":"Banks & Credit Unions",
            "subcategory":"Bank",
            "type":"Services"
        }
    ],
    "sg:phone":"+61 421 270 783",
    "sg:postcode":"2261",
    "sg:province":"NSW",
    "sg:tags":[
        "broker",
        "mortgage"
    ],
    "wof:name":"Prestige Mortgage & Financial Solutions",
    "wof:placetype":"venue"
},
  "geometry": {"coordinates":[151.496353,-33.358421],"type":"Point"}
}