{
  "type": "Feature",
  "properties": {
    "iso:country":"AU",
    "sg:address":"Locked Bag 36",
    "sg:city":"South Melbourne",
    "sg:classifiers":[
        {
            "category":"Organizations",
            "subcategory":"Professional Association",
            "type":"Services"
        }
    ],
    "sg:phone":"+61 3 9690 8000",
    "sg:postcode":"3205",
    "sg:province":"VIC",
    "sg:tags":[
        "organisation",
        "business"
    ],
    "wof:name":"Australian Computer Society",
    "wof:placetype":"venue"
},
  "geometry": {"coordinates":[144.968521,-37.812973],"type":"Point"}
}