{
  "type": "Feature",
  "properties": {
    "iso:country":"AU",
    "sg:address":"32 Garsed St",
    "sg:city":"Bendigo",
    "sg:classifiers":[
        {
            "category":"Professional",
            "subcategory":"Research",
            "type":"Services"
        }
    ],
    "sg:phone":"+61 3 5444 4788",
    "sg:postcode":"3550",
    "sg:province":"VIC",
    "sg:tags":[
        "market"
    ],
    "wof:name":"Compelling Economics",
    "wof:placetype":"venue"
},
  "geometry": {"coordinates":[144.280563355,-36.7640800476],"type":"Point"}
}