{
  "type": "Feature",
  "properties": {
    "iso:country":"AU",
    "sg:address":"18 Colwyn Rd",
    "sg:city":"Bayswater",
    "sg:classifiers":[
        {
            "category":"Manufacturing",
            "subcategory":"Building Materials",
            "type":"Manufacturing & Wholesale Goods"
        }
    ],
    "sg:phone":"+61 8 9279 1102",
    "sg:postcode":"6053",
    "sg:province":"WA",
    "sg:tags":[
        "concrete",
        "product"
    ],
    "wof:name":"Edgeline Cement Products",
    "wof:placetype":"venue"
},
  "geometry": {"coordinates":[115.932189941,-31.9215717316],"type":"Point"}
}