{
  "type": "Feature",
  "properties": {
    "addr:full":"Eungella Rd Finch Hatton QLD 4756",
    "addr:postcode":"4756",
    "addr:street":"Eungella Rd",
    "iso:country":"AU",
    "sg:address":"Eungella Rd",
    "sg:city":"Finch Hatton",
    "sg:classifiers":[
        {
            "category":"Autos & Motor Vehicles",
            "subcategory":"Fuel & Gas Station",
            "type":"Retail Goods"
        }
    ],
    "sg:phone":"+61 7 4958 3174",
    "sg:postcode":"4756",
    "sg:province":"QLD",
    "wof:name":"BP Trueman Siding Services",
    "wof:placetype":"venue"
},
  "geometry": {"coordinates":[148.518417,-21.18026],"type":"Point"}
}