{
  "type": "Feature",
  "properties": {
    "addr:full":"21 Skinner St Adavale QLD 4474",
    "addr:housenumber":"21",
    "addr:postcode":"4474",
    "addr:street":"Skinner St",
    "iso:country":"AU",
    "sg:address":"21 Skinner St",
    "sg:city":"Adavale",
    "sg:classifiers":[
        {
            "category":"Building & Trades",
            "subcategory":"Landscaping Services",
            "type":"Services"
        }
    ],
    "sg:phone":"+61 7 4656 3368",
    "sg:postcode":"4474",
    "sg:province":"QLD",
    "sg:tags":[
        "grazier"
    ],
    "wof:name":"NQ & DL Hodson Contractor",
    "wof:placetype":"venue"
},
  "geometry": {"coordinates":[144.59857177699999,-25.9079666138],"type":"Point"}
}