{
  "type": "Feature",
  "properties": {
    "addr:full":"72 Exford Drv Mornington VIC 3931",
    "addr:housenumber":"72",
    "addr:postcode":"3931",
    "addr:street":"Exford Drv",
    "iso:country":"AU",
    "sg:address":"72 Exford Drv",
    "sg:city":"Mornington",
    "sg:classifiers":[
        {
            "category":"Social Services",
            "subcategory":"Child Care",
            "type":"Services"
        }
    ],
    "sg:phone":"+61 3 5976 1022",
    "sg:postcode":"3931",
    "sg:province":"VIC",
    "wof:name":"Padua Kindergarten & Childcare Centre",
    "wof:placetype":"venue"
},
  "geometry": {"coordinates":[145.06854248100001,-38.2202568054],"type":"Point"}
}