{
  "type": "Feature",
  "properties": {
    "addr:full":"8 Oliver St Inverell NSW 2360",
    "addr:housenumber":"8",
    "addr:postcode":"2360",
    "addr:street":"Oliver St",
    "iso:country":"AU",
    "sg:address":"8 Oliver St",
    "sg:city":"Inverell",
    "sg:classifiers":[
        {
            "category":"Fast Food",
            "type":"Food & Drink"
        }
    ],
    "sg:phone":"+61 2 6722 4543",
    "sg:postcode":"2360",
    "sg:province":"NSW",
    "sg:tags":[
        "away",
        "take"
    ],
    "wof:name":"Tin Cheung Chinese Restaurant",
    "wof:placetype":"venue"
},
  "geometry": {"coordinates":[151.114013672,-29.7732467651],"type":"Point"}
}