{
  "type": "Feature",
  "properties": {
    "iso:country":"AU",
    "sg:address":"881 Albany Hwy",
    "sg:city":"East Victoria Park",
    "sg:classifiers":[
        {
            "category":"Military Area",
            "subcategory":"Air Force Base",
            "type":"Public Place"
        }
    ],
    "sg:phone":"+61 8 9472 3376",
    "sg:postcode":"6101",
    "sg:province":"WA",
    "sg:tags":[
        "men's",
        "tailor"
    ],
    "wof:name":"My Collection Multi Service",
    "wof:placetype":"venue"
},
  "geometry": {"coordinates":[115.903869629,-31.9859905243],"type":"Point"}
}