{
  "type": "Feature",
  "properties": {
    "addr:full":"433 Cleveland St Surry Hills NSW 2010",
    "addr:housenumber":"433",
    "addr:postcode":"2010",
    "addr:street":"Cleveland St",
    "iso:country":"AU",
    "sg:address":"433 Cleveland St",
    "sg:city":"Surry Hills",
    "sg:classifiers":[
        {
            "category":"Retail",
            "subcategory":"Event Space",
            "type":"Services"
        }
    ],
    "sg:phone":"+61 2 9698 1908",
    "sg:postcode":"2010",
    "sg:province":"NSW",
    "sg:tags":[
        "function",
        "organiser"
    ],
    "wof:name":"Bar Cleveland",
    "wof:placetype":"venue"
},
  "geometry": {"coordinates":[151.217086792,-33.8793449402],"type":"Point"}
}