{
  "type": "Feature",
  "properties": {
    "iso:country":"AU",
    "sg:address":"77 Elizabeth St",
    "sg:city":"Brisbane",
    "sg:classifiers":[
        {
            "category":"Real Estate",
            "subcategory":"Developer",
            "type":"Services"
        }
    ],
    "sg:phone":"+61 7 3210 0882",
    "sg:postcode":"4000",
    "sg:province":"QLD",
    "sg:tags":[
        "development"
    ],
    "wof:name":"Godfrey Mantle Group of Companies",
    "wof:placetype":"venue"
},
  "geometry": {"coordinates":[153.025192261,-27.4711933136],"type":"Point"}
}