{
  "type": "Feature",
  "properties": {
    "addr:full":"77 High St Woodend VIC 3442",
    "addr:housenumber":"77",
    "addr:postcode":"3442",
    "addr:street":"High St",
    "iso:country":"AU",
    "sg:address":"77 High St",
    "sg:city":"Woodend",
    "sg:classifiers":[
        {
            "category":"Fast Food",
            "type":"Food & Drink"
        }
    ],
    "sg:phone":"+61 3 5427 2470",
    "sg:postcode":"3442",
    "sg:province":"VIC",
    "sg:tags":[
        "away",
        "take"
    ],
    "wof:name":"Mountain View Andrews Cafe",
    "wof:placetype":"venue"
},
  "geometry": {"coordinates":[144.52812194800001,-37.3554801941],"type":"Point"}
}