{
  "type": "Feature",
  "properties": {
    "addr:full":"151 Sussex St East Victoria Park WA 6101",
    "addr:housenumber":"151",
    "addr:postcode":"6101",
    "addr:street":"Sussex St",
    "iso:country":"AU",
    "sg:address":"151 Sussex St",
    "sg:city":"East Victoria Park",
    "sg:classifiers":[
        {
            "category":"Utilities",
            "subcategory":"Water",
            "type":"Services"
        }
    ],
    "sg:phone":"+61 8 9362 5577",
    "sg:postcode":"6101",
    "sg:province":"WA",
    "sg:tags":[
        "equipment",
        "treatment"
    ],
    "wof:name":"Biostat Engineering",
    "wof:placetype":"venue"
},
  "geometry": {"coordinates":[115.891326904,-31.99177742],"type":"Point"}
}