{
  "type": "Feature",
  "properties": {
    "addr:full":"Suite 3, 17 Peel St South Brisbane QLD 4101",
    "addr:housenumber":"17",
    "addr:postcode":"4101",
    "addr:street":"Peel St",
    "iso:country":"AU",
    "sg:address":"Suite 3, 17 Peel St",
    "sg:city":"South Brisbane",
    "sg:classifiers":[
        {
            "category":"Professional",
            "subcategory":"Employment Agencies",
            "type":"Services"
        }
    ],
    "sg:phone":"+61 7 3846 7533",
    "sg:postcode":"4101",
    "sg:province":"QLD",
    "wof:name":"Alpha Office Solutions",
    "wof:placetype":"venue"
},
  "geometry": {"coordinates":[153.01678466800001,-27.4723453522],"type":"Point"}
}