{
  "type": "Feature",
  "properties": {
    "iso:country":"AU",
    "sg:address":"U6/ 19 Expo Court Crt",
    "sg:city":"Ashmore",
    "sg:classifiers":[
        {
            "category":"Building & Trades",
            "subcategory":"Equipment Rental",
            "type":"Services"
        }
    ],
    "sg:phone":"+61 7 5532 8568",
    "sg:postcode":"4214",
    "sg:province":"QLD",
    "sg:tags":[
        "fitness"
    ],
    "wof:name":"Pro-Arc International",
    "wof:placetype":"venue"
},
  "geometry": {"coordinates":[153.38560485799999,-27.9806461334],"type":"Point"}
}