{
  "type": "Feature",
  "properties": {
    "addr:full":"Unit 8/ 25 Tea Tree Ave Currumbin QLD 4223",
    "addr:housenumber":"25",
    "addr:postcode":"4223",
    "addr:street":"Tea Tree Ave",
    "iso:country":"AU",
    "sg:address":"Unit 8/ 25 Tea Tree Ave",
    "sg:city":"Currumbin",
    "sg:classifiers":[
        {
            "category":"Autos & Motor Vehicles",
            "subcategory":"Auto Supplies",
            "type":"Retail Goods"
        }
    ],
    "sg:phone":"+61 7 5598 2677",
    "sg:postcode":"4223",
    "sg:province":"QLD",
    "sg:tags":[
        "tyre"
    ],
    "wof:name":"Able Tyre & Mechanical",
    "wof:placetype":"venue"
},
  "geometry": {"coordinates":[153.47428894000001,-28.1453132629],"type":"Point"}
}