{
  "type": "Feature",
  "properties": {
    "addr:full":"832 Wellington St West Perth WA 6005",
    "addr:housenumber":"832",
    "addr:postcode":"6005",
    "addr:street":"Wellington St",
    "iso:country":"AU",
    "sg:address":"832 Wellington St",
    "sg:city":"West Perth",
    "sg:classifiers":[
        {
            "category":"Insurance",
            "subcategory":"Hazard Insurance",
            "type":"Services"
        }
    ],
    "sg:phone":"+61 13 17 03",
    "sg:postcode":"6005",
    "sg:province":"WA",
    "sg:tags":[
        "fire",
        "accident",
        "marine"
    ],
    "wof:name":"RAC Travel",
    "wof:placetype":"venue"
},
  "geometry": {"coordinates":[115.849006653,-31.9480037689],"type":"Point"}
}