{
  "type": "Feature",
  "properties": {
    "iso:country":"AU",
    "sg:address":"33 Murchison St",
    "sg:city":"Marysville",
    "sg:classifiers":[
        {
            "category":"Travel",
            "subcategory":"Hotels & Motels",
            "type":"Entertainment"
        }
    ],
    "sg:phone":"+61 3 5963 3225",
    "sg:postcode":"3779",
    "sg:province":"VIC",
    "wof:name":"Tower Motel",
    "wof:placetype":"venue"
},
  "geometry": {"coordinates":[145.74569700000001,-37.510601],"type":"Point"}
}