{
  "type": "Feature",
  "properties": {
    "iso:country":"AU",
    "sg:address":"Eyre Hwy",
    "sg:city":"Ceduna",
    "sg:classifiers":[
        {
            "category":"Health Services",
            "subcategory":"Doctor",
            "type":"Services"
        }
    ],
    "sg:phone":"+61 8 8626 2160",
    "sg:postcode":"5690",
    "sg:province":"SA",
    "sg:tags":[
        "medical",
        "practitioner"
    ],
    "wof:name":"Ceduna Family Medical Practice",
    "wof:placetype":"venue"
},
  "geometry": {"coordinates":[133.67453002900001,-32.121131897],"type":"Point"}
}