{
  "type": "Feature",
  "properties": {
    "addr:full":"21 Woodward Ave Strathfield NSW 2135",
    "addr:housenumber":"21",
    "addr:postcode":"2135",
    "addr:street":"Woodward Ave",
    "iso:country":"AU",
    "sg:address":"21 Woodward Ave",
    "sg:city":"Strathfield",
    "sg:classifiers":[
        {
            "category":"Health Services",
            "subcategory":"Doctor",
            "type":"Services"
        }
    ],
    "sg:phone":"+61 2 9642 4022",
    "sg:postcode":"2135",
    "sg:province":"NSW",
    "sg:tags":[
        "medical",
        "practitioner"
    ],
    "wof:name":"Law J R",
    "wof:placetype":"venue"
},
  "geometry": {"coordinates":[151.08880615199999,-33.8781242371],"type":"Point"}
}