{
  "type": "Feature",
  "properties": {
    "addr:full":"42 Main St St Marys TAS 7215",
    "addr:housenumber":"42",
    "addr:postcode":"7215",
    "addr:street":"Main St",
    "iso:country":"AU",
    "sg:address":"42 Main St St",
    "sg:city":"Marys",
    "sg:classifiers":[
        {
            "category":"Food & Beverages",
            "subcategory":"Specialty",
            "type":"Retail Goods"
        }
    ],
    "sg:phone":"+61 3 6372 2172",
    "sg:postcode":"7215",
    "sg:province":"TAS",
    "sg:tags":[
        "product",
        "health"
    ],
    "wof:name":"St Marys Health & Beauty Centre",
    "wof:placetype":"venue"
},
  "geometry": {"coordinates":[148.185349,-41.579933],"type":"Point"}
}