{
  "type": "Feature",
  "properties": {
    "addr:full":"Poppett Rd Wamboin ACT 2620",
    "addr:postcode":"2620",
    "addr:street":"Poppett Rd",
    "iso:country":"AU",
    "sg:address":"Poppett Rd",
    "sg:city":"Wamboin",
    "sg:classifiers":[
        {
            "category":"Shopping",
            "subcategory":"Clothing, Apparel, & Fashions",
            "type":"Retail Goods"
        }
    ],
    "sg:phone":"+61 2 6238 3249",
    "sg:postcode":"2620",
    "sg:province":"ACT",
    "sg:tags":[
        "textile",
        "designer"
    ],
    "wof:name":"Camelot Mohair Co",
    "wof:placetype":"venue"
},
  "geometry": {"coordinates":[149.292358398,-35.2629737854],"type":"Point"}
}