{
  "type": "Feature",
  "properties": {
    "addr:full":"Factory 2 9 Tower Crt Noble Park VIC 3174",
    "addr:housenumber":"9",
    "addr:postcode":"3174",
    "addr:street":"Tower Crt",
    "iso:country":"AU",
    "sg:address":"Factory 2 9 Tower Crt",
    "sg:city":"Noble Park",
    "sg:classifiers":[
        {
            "category":"Wholesale",
            "subcategory":"Painting Supplies",
            "type":"Manufacturing & Wholesale Goods"
        }
    ],
    "sg:phone":"+61 3 9769 1788",
    "sg:postcode":"3174",
    "sg:province":"VIC",
    "sg:tags":[
        "product",
        "cleaning"
    ],
    "wof:name":"Jaegar Australia Pty Ltd",
    "wof:placetype":"venue"
},
  "geometry": {"coordinates":[145.19007873499999,-37.9816703796],"type":"Point"}
}