{
  "type": "Feature",
  "properties": {
    "addr:full":"52 Angove Park Drv Tea Tree Gully SA 5091",
    "addr:housenumber":"52",
    "addr:postcode":"5091",
    "addr:street":"Angove Park Drv",
    "iso:country":"AU",
    "sg:address":"52 Angove Park Drv",
    "sg:city":"Tea Tree Gully",
    "sg:classifiers":[
        {
            "category":"Professional",
            "subcategory":"Business Services",
            "type":"Services"
        }
    ],
    "sg:phone":"+61 8 8395 2308",
    "sg:postcode":"5091",
    "sg:province":"SA",
    "sg:tags":[
        "drafting"
    ],
    "wof:name":"Gully Design Technology Pty Ltd",
    "wof:placetype":"venue"
},
  "geometry": {"coordinates":[138.72340393100001,-34.8222846985],"type":"Point"}
}