{
  "type": "Feature",
  "properties": {
    "addr:full":"Jumbunna Rd Korumburra VIC 3950",
    "addr:postcode":"3950",
    "addr:street":"Jumbunna Rd",
    "iso:country":"AU",
    "sg:address":"Jumbunna Rd",
    "sg:city":"Korumburra",
    "sg:classifiers":[
        {
            "category":"Building & Trades",
            "subcategory":"Construction",
            "type":"Services"
        }
    ],
    "sg:phone":"+61 3 5657 3341",
    "sg:postcode":"3950",
    "sg:province":"VIC",
    "sg:tags":[
        "monumental",
        "mason"
    ],
    "wof:name":"Barry Wakley Sculptor Pty.Ltd.",
    "wof:placetype":"venue"
},
  "geometry": {"coordinates":[145.82281494099999,-38.4323501587],"type":"Point"}
}