{
  "type": "Feature",
  "properties": {
    "addr:full":"6/ 184 Duke St Sunshine VIC 3020",
    "addr:housenumber":"/ 184",
    "addr:postcode":"3020",
    "addr:street":"Duke St",
    "iso:country":"AU",
    "sg:address":"6/ 184 Duke St",
    "sg:city":"Sunshine",
    "sg:classifiers":[
        {
            "category":"Retail",
            "subcategory":"Auto Repair",
            "type":"Services"
        }
    ],
    "sg:phone":"+61 3 9310 1399",
    "sg:postcode":"3020",
    "sg:province":"VIC",
    "sg:tags":[
        "clutch",
        "brake"
    ],
    "wof:name":"Motafit Service Centres",
    "wof:placetype":"venue"
},
  "geometry": {"coordinates":[144.84809899999999,-37.774334],"type":"Point"}
}