{
  "type": "Feature",
  "properties": {
    "iso:country":"AU",
    "sg:address":"61 Great Valley Rd",
    "sg:city":"Glen Iris",
    "sg:classifiers":[
        {
            "category":"Health Services",
            "subcategory":"Doctor",
            "type":"Services"
        }
    ],
    "sg:phone":"+61 3 9889 5341",
    "sg:postcode":"3146",
    "sg:province":"VIC",
    "sg:tags":[
        "medical",
        "practitioner"
    ],
    "wof:name":"Himmelreich E",
    "wof:placetype":"venue"
},
  "geometry": {"coordinates":[145.064376831,-37.8526992798],"type":"Point"}
}