{
  "type": "Feature",
  "properties": {
    "iso:country":"AU",
    "sg:address":"Shp 2, 63/13 Ernest St",
    "sg:city":"Crows Nest",
    "sg:classifiers":[
        {
            "category":"Shopping",
            "subcategory":"Baby Store",
            "type":"Retail Goods"
        }
    ],
    "sg:phone":"+61 2 9438 5694",
    "sg:postcode":"2065",
    "sg:province":"NSW",
    "sg:tags":[
        "wear"
    ],
    "wof:name":"Dunnikins Pty Ltd",
    "wof:placetype":"venue"
},
  "geometry": {"coordinates":[151.20315551799999,-33.8261070251],"type":"Point"}
}