{
  "type": "Feature",
  "properties": {
    "addr:full":"16 Old Maitland Rd Sandgate NSW 2304",
    "addr:housenumber":"16",
    "addr:postcode":"2304",
    "addr:street":"Old Maitland Rd",
    "iso:country":"AU",
    "sg:address":"16 Old Maitland Rd",
    "sg:city":"Sandgate",
    "sg:classifiers":[
        {
            "category":"Utilities",
            "subcategory":"Water",
            "type":"Services"
        }
    ],
    "sg:phone":"+61 2 4960 8999",
    "sg:postcode":"2304",
    "sg:province":"NSW",
    "sg:tags":[
        "hot",
        "system"
    ],
    "sg:website":"http://www.mullane.com.au",
    "wof:name":"H L Mullane & Sons Pty Ltd",
    "wof:placetype":"venue"
},
  "geometry": {"coordinates":[151.702758789,-32.8599433899],"type":"Point"}
}