{
  "type": "Feature",
  "properties": {
    "iso:country":"AU",
    "sg:address":"Cnr Broadway & Bay St",
    "sg:city":"Broadway",
    "sg:classifiers":[
        {
            "category":"Travel",
            "subcategory":"Hotels & Motels",
            "type":"Entertainment"
        }
    ],
    "sg:phone":"+61 2 9338 5000",
    "sg:postcode":"2007",
    "sg:province":"NSW",
    "sg:tags":[
        "accommodation"
    ],
    "sg:website":"http://www.hotelunilodge.citysearch.com.au",
    "wof:name":"Hotel Unilodge Sydney",
    "wof:placetype":"venue"
},
  "geometry": {"coordinates":[151.19497680699999,-33.8843994141],"type":"Point"}
}