{
  "type": "Feature",
  "properties": {
    "iso:country":"AU",
    "sg:address":"Shop 3, Bulky Good Center, Hollywood Plaza Shopping Center, Winzor Rd",
    "sg:city":"Salisbury Downs",
    "sg:classifiers":[
        {
            "category":"Shopping",
            "subcategory":"Computers & Home Electronics",
            "type":"Retail Goods"
        }
    ],
    "sg:phone":"+61 8 8283 2293",
    "sg:postcode":"5108",
    "sg:province":"SA",
    "sg:tags":[
        "small",
        "equipment",
        "business"
    ],
    "wof:name":"Dick Smith Electronics",
    "wof:placetype":"venue"
},
  "geometry": {"coordinates":[138.61895751899999,-34.7697105408],"type":"Point"}
}