{
  "type": "Feature",
  "properties": {
    "iso:country":"AU",
    "sg:address":"1 Chapel La",
    "sg:city":"Rockdale",
    "sg:classifiers":[
        {
            "category":"Shopping",
            "subcategory":"Clothing, Apparel, & Fashions",
            "type":"Retail Goods"
        }
    ],
    "sg:phone":"+61 2 9567 1699",
    "sg:postcode":"2216",
    "sg:province":"NSW",
    "sg:tags":[
        "menswear"
    ],
    "wof:name":"Sierra Blue International Pty Ltd",
    "wof:placetype":"venue"
},
  "geometry": {"coordinates":[151.13916,-33.954933],"type":"Point"}
}