{
  "type": "Feature",
  "properties": {
    "iso:country":"AU",
    "sg:address":"Centro Milton, Baroona Rd",
    "sg:city":"Milton",
    "sg:classifiers":[
        {
            "category":"Education",
            "subcategory":"Dance Studio",
            "type":"Public Place"
        }
    ],
    "sg:phone":"+61 7 3369 1133",
    "sg:postcode":"4064",
    "sg:province":"QLD",
    "sg:tags":[
        "venue",
        "tuition"
    ],
    "sg:website":"http://www.thepremierdance.com",
    "wof:name":"The Premier Dance Academy",
    "wof:placetype":"venue"
},
  "geometry": {"coordinates":[153.003509522,-27.469039917],"type":"Point"}
}