{
  "type": "Feature",
  "properties": {
    "addr:full":"6 Staple St Seventeen Mile Rocks QLD 4073",
    "addr:housenumber":"6",
    "addr:postcode":"4073",
    "addr:street":"Staple St",
    "iso:country":"AU",
    "sg:address":"6 Staple St",
    "sg:city":"Seventeen Mile Rocks",
    "sg:classifiers":[
        {
            "category":"Home & Garden",
            "subcategory":"Hardware",
            "type":"Retail Goods"
        }
    ],
    "sg:phone":"+61 7 3279 2633",
    "sg:postcode":"4073",
    "sg:province":"QLD",
    "sg:tags":[
        "battery",
        "dry",
        "rechargeable",
        "cell"
    ],
    "wof:name":"Battery Specialties Pty Ltd",
    "wof:placetype":"venue"
},
  "geometry": {"coordinates":[152.953948975,-27.5449905396],"type":"Point"}
}