{
  "type": "Feature",
  "properties": {
    "addr:full":"11 Commercial Rd Fortitude Valley QLD 4006",
    "addr:housenumber":"11",
    "addr:postcode":"4006",
    "addr:street":"Commercial Rd",
    "iso:country":"AU",
    "sg:address":"11 Commercial Rd",
    "sg:city":"Fortitude Valley",
    "sg:classifiers":[
        {
            "category":"Home & Garden",
            "subcategory":"Furniture",
            "type":"Retail Goods"
        }
    ],
    "sg:phone":"+61 7 3854 1600",
    "sg:postcode":"4006",
    "sg:province":"QLD",
    "sg:tags":[
        "business"
    ],
    "wof:name":"Office Furniture Interiors Pty Ltd",
    "wof:placetype":"venue"
},
  "geometry": {"coordinates":[153.04086303700001,-27.4529132843],"type":"Point"}
}