{
  "type": "Feature",
  "properties": {
    "addr:full":"68 Nelson St Smithton TAS 7330",
    "addr:housenumber":"68",
    "addr:postcode":"7330",
    "addr:street":"Nelson St",
    "iso:country":"AU",
    "sg:address":"68 Nelson St",
    "sg:city":"Smithton",
    "sg:classifiers":[
        {
            "category":"Building & Trades",
            "subcategory":"Construction",
            "type":"Services"
        }
    ],
    "sg:phone":"+61 3 6452 1579",
    "sg:postcode":"7330",
    "sg:province":"TAS",
    "sg:tags":[
        "contractor"
    ],
    "wof:name":"Smith N R & A E",
    "wof:placetype":"venue"
},
  "geometry": {"coordinates":[145.120743,-40.849075],"type":"Point"}
}