{
  "type": "Feature",
  "properties": {
    "addr:full":"Unit 6 48 Dellamarta Rd Wangara WA 6065",
    "addr:housenumber":"48",
    "addr:postcode":"6065",
    "addr:street":"Dellamarta Rd",
    "iso:country":"AU",
    "sg:address":"Unit 6 48 Dellamarta Rd",
    "sg:city":"Wangara",
    "sg:classifiers":[
        {
            "category":"Wholesale",
            "subcategory":"Electrical",
            "type":"Manufacturing & Wholesale Goods"
        }
    ],
    "sg:phone":"+61 8 9302 3444",
    "sg:postcode":"6065",
    "sg:province":"WA",
    "sg:tags":[
        "wholesaler",
        "mfrs",
        "accessory"
    ],
    "wof:name":"APE Manufacturing",
    "wof:placetype":"venue"
},
  "geometry": {"coordinates":[115.82334136999999,-31.7890415192],"type":"Point"}
}