{
  "type": "Feature",
  "properties": {
    "iso:country":"AU",
    "sg:address":"1/ 28 Onslow Ave",
    "sg:city":"Campbellfield",
    "sg:classifiers":[
        {
            "category":"Retail",
            "subcategory":"Laundry & Dry Cleaning",
            "type":"Services"
        }
    ],
    "sg:phone":"+61 3 9359 4533",
    "sg:postcode":"3061",
    "sg:province":"VIC",
    "sg:tags":[
        "cloth",
        "supply"
    ],
    "wof:name":"Lyn Marc Textiles",
    "wof:placetype":"venue"
},
  "geometry": {"coordinates":[144.96490478499999,-37.6879386902],"type":"Point"}
}