{
  "type": "Feature",
  "properties": {
    "iso:country":"AU",
    "sg:address":"294 Warialda St",
    "sg:city":"Moree",
    "sg:classifiers":[
        {
            "category":"Organizations",
            "subcategory":"Non-profit Organization",
            "type":"Services"
        }
    ],
    "sg:phone":"+61 2 6752 1550",
    "sg:postcode":"2400",
    "sg:province":"NSW",
    "sg:tags":[
        "support",
        "disability",
        "organisation"
    ],
    "wof:name":"Proclaimed Place Moree",
    "wof:placetype":"venue"
},
  "geometry": {"coordinates":[149.84600830100001,-29.4706516266],"type":"Point"}
}