{
  "type": "Feature",
  "properties": {
    "addr:full":"PO Box 1097N Cairns North QLD 4870",
    "addr:postcode":"4870",
    "iso:country":"AU",
    "sg:address":"PO Box 1097N",
    "sg:city":"Cairns North",
    "sg:classifiers":[
        {
            "category":"Professional",
            "subcategory":"Accounting & Tax Preparation",
            "type":"Services"
        }
    ],
    "sg:phone":"+61 7 4047 6427",
    "sg:postcode":"4870",
    "sg:province":"QLD",
    "sg:tags":[
        "consultant",
        "taxation"
    ],
    "wof:name":"Grosskopf Neal",
    "wof:placetype":"venue"
},
  "geometry": {"coordinates":[145.759002686,-16.9041805267],"type":"Point"}
}