{
  "type": "Feature",
  "properties": {
    "iso:country":"AU",
    "sg:address":"87 Macpherson St",
    "sg:city":"Bronte",
    "sg:classifiers":[
        {
            "category":"Personal",
            "subcategory":"Massage",
            "type":"Services"
        }
    ],
    "sg:phone":"+61 2 9369 5802",
    "sg:postcode":"2024",
    "sg:province":"NSW",
    "sg:tags":[
        "therapy"
    ],
    "wof:name":"Cogill Henry",
    "wof:placetype":"venue"
},
  "geometry": {"coordinates":[151.26139831500001,-33.9059371948],"type":"Point"}
}