{
  "type": "Feature",
  "properties": {
    "iso:country":"AU",
    "sg:address":"188 Nicklin Way",
    "sg:city":"Warana",
    "sg:classifiers":[
        {
            "category":"Coffee & Tea",
            "type":"Food & Drink"
        }
    ],
    "sg:phone":"+61 7 5493 4233",
    "sg:postcode":"4575",
    "sg:province":"QLD",
    "sg:tags":[
        "kayak",
        "canoe"
    ],
    "sg:website":"http://www.ozflytesurfcraft.com.au",
    "wof:name":"Ozflyte Surfcraft",
    "wof:placetype":"venue"
},
  "geometry": {"coordinates":[153.12922699999999,-26.722794],"type":"Point"}
}