{
  "type": "Feature",
  "properties": {
    "addr:full":"783 High St Thornbury VIC 3071",
    "addr:housenumber":"783",
    "addr:postcode":"3071",
    "addr:street":"High St",
    "iso:country":"AU",
    "sg:address":"783 High St",
    "sg:city":"Thornbury",
    "sg:classifiers":[
        {
            "category":"Retail",
            "subcategory":"Repair Shop",
            "type":"Services"
        }
    ],
    "sg:phone":"+61 3 9480 5422",
    "sg:postcode":"3071",
    "sg:province":"VIC",
    "sg:tags":[
        "machine",
        "repairs",
        "part",
        "dryer",
        "washing"
    ],
    "wof:name":"Darebin Home Appliance & Services",
    "wof:placetype":"venue"
},
  "geometry": {"coordinates":[145.00070190400001,-37.7570610046],"type":"Point"}
}