{
  "type": "Feature",
  "properties": {
    "addr:full":"338 Pacific Hwy Hexham NSW 2322",
    "addr:housenumber":"338",
    "addr:postcode":"2322",
    "addr:street":"Pacific Hwy",
    "iso:country":"AU",
    "sg:address":"338 Pacific Hwy",
    "sg:city":"Hexham",
    "sg:classifiers":[
        {
            "category":"Recreation",
            "subcategory":"Water Park",
            "type":"Entertainment"
        }
    ],
    "sg:phone":"+61 2 4964 8687",
    "sg:postcode":"2322",
    "sg:province":"NSW",
    "sg:tags":[
        "control",
        "seepage"
    ],
    "wof:name":"Beltreco Ltd",
    "wof:placetype":"venue"
},
  "geometry": {"coordinates":[151.723587036,-32.7925605774],"type":"Point"}
}