{
  "type": "Feature",
  "properties": {
    "addr:full":"51 Cochrane St Paddington QLD 4064",
    "addr:housenumber":"51",
    "addr:postcode":"4064",
    "addr:street":"Cochrane St",
    "iso:country":"AU",
    "sg:address":"51 Cochrane St",
    "sg:city":"Paddington",
    "sg:classifiers":[
        {
            "category":"Professional",
            "subcategory":"Secretarial Services",
            "type":"Services"
        }
    ],
    "sg:phone":"+61 7 3511 7540",
    "sg:postcode":"4064",
    "sg:province":"QLD",
    "sg:tags":[
        "typing"
    ],
    "wof:name":"DLS Enterprises",
    "wof:placetype":"venue"
},
  "geometry": {"coordinates":[153.00338745100001,-27.4572105408],"type":"Point"}
}