{
  "type": "Feature",
  "properties": {
    "addr:full":"107 Upton St Bundall QLD 4217",
    "addr:housenumber":"107",
    "addr:postcode":"4217",
    "addr:street":"Upton St",
    "iso:country":"AU",
    "sg:address":"107 Upton St",
    "sg:city":"Bundall",
    "sg:classifiers":[
        {
            "category":"Professional",
            "subcategory":"Accounting & Tax Preparation",
            "type":"Services"
        }
    ],
    "sg:phone":"+61 7 5574 2344",
    "sg:postcode":"4217",
    "sg:province":"QLD",
    "sg:tags":[
        "accountant",
        "auditor"
    ],
    "wof:name":"Camerons Accountants & Auditors",
    "wof:placetype":"venue"
},
  "geometry": {"coordinates":[153.41395568900001,-28.0009689331],"type":"Point"}
}