{
  "type": "Feature",
  "properties": {
    "iso:country":"AU",
    "sg:address":"1/10 Mint St",
    "sg:city":"Wodonga",
    "sg:classifiers":[
        {
            "category":"Retail",
            "subcategory":"Car Wash",
            "type":"Services"
        }
    ],
    "sg:phone":"+61 2 6024 6222",
    "sg:postcode":"3690",
    "sg:province":"VIC",
    "sg:tags":[
        "truck",
        "cleaning"
    ],
    "wof:name":"Auto Image Car Detailing",
    "wof:placetype":"venue"
},
  "geometry": {"coordinates":[146.89703369099999,-36.1231803894],"type":"Point"}
}