{
  "type": "Feature",
  "properties": {
    "addr:full":"35 Curlewis St Garran ACT 2605",
    "addr:housenumber":"35",
    "addr:postcode":"2605",
    "addr:street":"Curlewis St",
    "iso:country":"AU",
    "sg:address":"35 Curlewis St",
    "sg:city":"Garran",
    "sg:classifiers":[
        {
            "category":"Shopping",
            "subcategory":"Computers & Home Electronics",
            "type":"Retail Goods"
        }
    ],
    "sg:phone":"+61 417 455 108",
    "sg:postcode":"2605",
    "sg:province":"ACT",
    "sg:tags":[
        "ergonomics"
    ],
    "wof:name":"Frith J J & Associates",
    "wof:placetype":"venue"
},
  "geometry": {"coordinates":[149.11256408700001,-35.3411140442],"type":"Point"}
}