{
  "type": "Feature",
  "properties": {
    "addr:full":"Wills St Charleville QLD 4470",
    "addr:postcode":"4470",
    "addr:street":"Wills St",
    "iso:country":"AU",
    "sg:address":"Wills St",
    "sg:city":"Charleville",
    "sg:classifiers":[
        {
            "category":"Education",
            "subcategory":"School",
            "type":"Public Place"
        }
    ],
    "sg:phone":"+61 7 4654 1106",
    "sg:postcode":"4470",
    "sg:province":"QLD",
    "sg:tags":[
        "state",
        "except",
        "nsw"
    ],
    "wof:name":"Charleville Primary",
    "wof:placetype":"venue"
},
  "geometry": {"coordinates":[146.24322509800001,-26.4055633545],"type":"Point"}
}