{
  "type": "Feature",
  "properties": {
    "addr:full":"Hassell Ave Kendenup WA 6323",
    "addr:postcode":"6323",
    "addr:street":"Hassell Ave",
    "iso:country":"AU",
    "sg:address":"Hassell Ave",
    "sg:city":"Kendenup",
    "sg:classifiers":[
        {
            "category":"Food & Beverages",
            "subcategory":"Groceries & Convenience Stores",
            "type":"Retail Goods"
        }
    ],
    "sg:phone":"+61 8 9851 4001",
    "sg:postcode":"6323",
    "sg:province":"WA",
    "wof:name":"Kendenup Stores",
    "wof:placetype":"venue"
},
  "geometry": {"coordinates":[117.628501892,-34.4918441772],"type":"Point"}
}