{
  "type": "Feature",
  "properties": {
    "addr:full":"8 Princeton Ave Kotara NSW 2289",
    "addr:housenumber":"8",
    "addr:postcode":"2289",
    "addr:street":"Princeton Ave",
    "iso:country":"AU",
    "sg:address":"8 Princeton Ave",
    "sg:city":"Kotara",
    "sg:classifiers":[
        {
            "category":"Sports & Exercise",
            "subcategory":"Gym",
            "type":"Entertainment"
        }
    ],
    "sg:phone":"+61 2 4952 6577",
    "sg:postcode":"2289",
    "sg:province":"NSW",
    "sg:tags":[
        "health",
        "fitness"
    ],
    "wof:name":"Bel-Air Squash & Fitness Centre",
    "wof:placetype":"venue"
},
  "geometry": {"coordinates":[151.70867919899999,-32.9412689209],"type":"Point"}
}