{
  "type": "Feature",
  "properties": {
    "iso:country":"AU",
    "sg:address":"42 O'Dea Ave",
    "sg:city":"Waterloo",
    "sg:classifiers":[
        {
            "category":"Retail",
            "subcategory":"Storage",
            "type":"Services"
        }
    ],
    "sg:phone":"+61 2 9699 8366",
    "sg:postcode":"2017",
    "sg:province":"NSW",
    "wof:name":"Rent-A-Space Self Storage",
    "wof:placetype":"venue"
},
  "geometry": {"coordinates":[151.210861206,-33.9033050537],"type":"Point"}
}