{
  "type": "Feature",
  "properties": {
    "iso:country":"AU",
    "sg:address":"Shop 21",
    "sg:city":"Mountain Gate Shopng Cntr Ferntree Gully",
    "sg:classifiers":[
        {
            "category":"Fast Food",
            "type":"Food & Drink"
        }
    ],
    "sg:phone":"+61 3 9758 2658",
    "sg:postcode":"3156",
    "sg:province":"VIC",
    "sg:tags":[
        "away",
        "take"
    ],
    "wof:name":"Mountain Gate Charcoal Chicken",
    "wof:placetype":"venue"
},
  "geometry": {"coordinates":[145.27656555199999,-37.8871994019],"type":"Point"}
}