{
  "type": "Feature",
  "properties": {
    "addr:full":"11 Vangeli St Arndell Park NSW 2148",
    "addr:housenumber":"11",
    "addr:postcode":"2148",
    "addr:street":"Vangeli St",
    "iso:country":"AU",
    "sg:address":"11 Vangeli St",
    "sg:city":"Arndell Park",
    "sg:classifiers":[
        {
            "category":"Autos & Motor Vehicles",
            "subcategory":"Auto Supplies",
            "type":"Retail Goods"
        }
    ],
    "sg:phone":"+61 2 9678 9999",
    "sg:postcode":"2148",
    "sg:province":"NSW",
    "sg:tags":[
        "battery",
        "automotive"
    ],
    "wof:name":"ABI-BSM Pty Ltd (Battery Supermarkets)",
    "wof:placetype":"venue"
},
  "geometry": {"coordinates":[150.88339233400001,-33.7906646729],"type":"Point"}
}