{
  "type": "Feature",
  "properties": {
    "iso:country":"AU",
    "sg:address":"3/ 324 Upper Heidelberg Rd",
    "sg:city":"Ivanhoe",
    "sg:classifiers":[
        {
            "category":"Farming",
            "subcategory":"Nursery",
            "type":"Manufacturing & Wholesale Goods"
        }
    ],
    "sg:phone":"+61 3 9499 2646",
    "sg:postcode":"3079",
    "sg:province":"VIC",
    "wof:name":"Hedlen Advanced Landscape Plants",
    "wof:placetype":"venue"
},
  "geometry": {"coordinates":[145.049682617,-37.7620658875],"type":"Point"}
}