{
  "type": "Feature",
  "properties": {
    "addr:full":"Wholesale - 34 Hamilton St Huntingdale VIC 3166",
    "addr:housenumber":"34",
    "addr:postcode":"3166",
    "addr:street":"Hamilton St",
    "iso:country":"AU",
    "sg:address":"Wholesale - 34 Hamilton St",
    "sg:city":"Huntingdale",
    "sg:classifiers":[
        {
            "category":"Food & Beverages",
            "subcategory":"Meat & Fish",
            "type":"Retail Goods"
        }
    ],
    "sg:phone":"+61 3 9568 2132",
    "sg:postcode":"3166",
    "sg:province":"VIC",
    "sg:tags":[
        "seafood"
    ],
    "wof:name":"Fish Pier",
    "wof:placetype":"venue"
},
  "geometry": {"coordinates":[145.10086059599999,-37.9080886841],"type":"Point"}
}