{
  "type": "Feature",
  "properties": {
    "addr:full":"13 Cromford Crs Narre Warren South VIC 3805",
    "addr:housenumber":"13",
    "addr:postcode":"3805",
    "addr:street":"Cromford Crs",
    "iso:country":"AU",
    "sg:address":"13 Cromford Crs",
    "sg:city":"Narre Warren South",
    "sg:classifiers":[
        {
            "category":"Social Services",
            "subcategory":"Adult Care",
            "type":"Services"
        }
    ],
    "sg:phone":"+61 3 8790 5594",
    "sg:postcode":"3805",
    "sg:province":"VIC",
    "sg:tags":[
        "towing"
    ],
    "wof:name":"Casey Towing",
    "wof:placetype":"venue"
},
  "geometry": {"coordinates":[145.298950195,-38.0660896301],"type":"Point"}
}