{
  "type": "Feature",
  "properties": {
    "addr:full":"930 Glenhuntly Rd Caulfield VIC 3162",
    "addr:housenumber":"930",
    "addr:postcode":"3162",
    "addr:street":"Glenhuntly Rd",
    "iso:country":"AU",
    "sg:address":"930 Glenhuntly Rd",
    "sg:city":"Caulfield",
    "sg:classifiers":[
        {
            "category":"Manufacturing",
            "subcategory":"Wood Products",
            "type":"Manufacturing & Wholesale Goods"
        }
    ],
    "sg:phone":"+61 3 9571 9037",
    "sg:postcode":"3162",
    "sg:province":"VIC",
    "sg:tags":[
        "polisher",
        "french"
    ],
    "wof:name":"Mills R G",
    "wof:placetype":"venue"
},
  "geometry": {"coordinates":[145.029296875,-37.8879127502],"type":"Point"}
}