{
  "type": "Feature",
  "properties": {
    "iso:country":"AU",
    "sg:address":"223b Unley Rd",
    "sg:city":"Malvern",
    "sg:classifiers":[
        {
            "category":"Shopping",
            "subcategory":"Clothing, Apparel, & Fashions",
            "type":"Retail Goods"
        }
    ],
    "sg:phone":"+61 8 8272 3536",
    "sg:postcode":"5061",
    "sg:province":"SA",
    "sg:tags":[
        "lady",
        "wear"
    ],
    "wof:name":"Panache Boutique",
    "wof:placetype":"venue"
},
  "geometry": {"coordinates":[138.608154297,-34.9566001892],"type":"Point"}
}