{
  "type": "Feature",
  "properties": {
    "addr:full":"468 Sheridan St Aeroglen QLD 4870",
    "addr:housenumber":"468",
    "addr:postcode":"4870",
    "addr:street":"Sheridan St",
    "iso:country":"AU",
    "sg:address":"468 Sheridan St",
    "sg:city":"Aeroglen",
    "sg:classifiers":[
        {
            "category":"Professional",
            "subcategory":"Detective & Security Services",
            "type":"Services"
        }
    ],
    "sg:phone":"+61 7 4053 2400",
    "sg:postcode":"4870",
    "sg:province":"QLD",
    "sg:tags":[
        "equipment",
        "window",
        "doors"
    ],
    "wof:name":"Superior Security Screens",
    "wof:placetype":"venue"
},
  "geometry": {"coordinates":[145.752883911,-16.8923835754],"type":"Point"}
}