{
  "type": "Feature",
  "properties": {
    "iso:country":"AU",
    "sg:address":"50 Barnes St",
    "sg:city":"Tamworth",
    "sg:classifiers":[
        {
            "category":"Shopping",
            "type":"Retail Goods"
        }
    ],
    "sg:phone":"+61 2 6765 4822",
    "sg:postcode":"2340",
    "sg:province":"NSW",
    "sg:tags":[
        "equipment",
        "safety",
        "accessory"
    ],
    "wof:name":"Bearquip",
    "wof:placetype":"venue"
},
  "geometry": {"coordinates":[150.91232299800001,-31.0914535522],"type":"Point"}
}