{
  "type": "Feature",
  "properties": {
    "iso:country":"AU",
    "sg:address":"17 Reservoir St",
    "sg:city":"Gunnedah",
    "sg:classifiers":[
        {
            "category":"Health Services",
            "subcategory":"Health Practitioner",
            "type":"Services"
        }
    ],
    "sg:phone":"+61 407 788 418",
    "sg:postcode":"2380",
    "sg:province":"NSW",
    "sg:tags":[
        "psychologist"
    ],
    "wof:name":"Heather Vernon",
    "wof:placetype":"venue"
},
  "geometry": {"coordinates":[150.252716064,-30.985118866],"type":"Point"}
}