{
  "type": "Feature",
  "properties": {
    "iso:country":"AU",
    "sg:address":"9 Point O&#039;Halloran Rd",
    "sg:city":"Victoria Point",
    "sg:classifiers":[
        {
            "category":"Manufacturing",
            "subcategory":"Food",
            "type":"Manufacturing & Wholesale Goods"
        }
    ],
    "sg:phone":"+61 7 3820 8095",
    "sg:postcode":"4165",
    "sg:province":"QLD",
    "sg:tags":[
        "function",
        "catering"
    ],
    "wof:name":"AAA Bayside Catering",
    "wof:placetype":"venue"
},
  "geometry": {"coordinates":[153.28512573200001,-27.595079422],"type":"Point"}
}