{
  "type": "Feature",
  "properties": {
    "addr:full":"Shop 241 Warringah Mall Brookvale NSW 2100",
    "addr:housenumber":"241",
    "addr:postcode":"2100",
    "addr:street":"Warringah Mall",
    "iso:country":"AU",
    "sg:address":"Shop 241 Warringah Mall",
    "sg:city":"Brookvale",
    "sg:classifiers":[
        {
            "category":"Food & Beverages",
            "subcategory":"Specialty",
            "type":"Retail Goods"
        }
    ],
    "sg:phone":"+61 2 9939 6503",
    "sg:postcode":"2100",
    "sg:province":"NSW",
    "sg:tags":[
        "product",
        "health"
    ],
    "wof:name":"Healthy Life",
    "wof:placetype":"venue"
},
  "geometry": {"coordinates":[151.25636291500001,-33.7532043457],"type":"Point"}
}