{
  "type": "Feature",
  "properties": {
    "addr:full":"Shp 2/454- 460 Samford Rd Gaythorne QLD 4051",
    "addr:housenumber":"/ 454 460",
    "addr:postcode":"4051",
    "addr:street":"Samford Rd",
    "iso:country":"AU",
    "sg:address":"Shp 2/454- 460 Samford Rd",
    "sg:city":"Gaythorne",
    "sg:classifiers":[
        {
            "category":"Personal",
            "subcategory":"Beauty Salon",
            "type":"Services"
        }
    ],
    "sg:phone":"+61 7 3855 3133",
    "sg:postcode":"4051",
    "sg:province":"QLD",
    "wof:name":"Shimmer Skin & Body",
    "wof:placetype":"venue"
},
  "geometry": {"coordinates":[152.982254028,-27.4175567627],"type":"Point"}
}