{
  "type": "Feature",
  "properties": {
    "iso:country":"AU",
    "sg:address":"23-25 Agosta Drv",
    "sg:city":"Laverton North",
    "sg:classifiers":[
        {
            "category":"Farming",
            "subcategory":"Crops",
            "type":"Manufacturing & Wholesale Goods"
        }
    ],
    "sg:phone":"+61 3 9369 9200",
    "sg:postcode":"3026",
    "sg:province":"VIC",
    "sg:tags":[
        "warehousing"
    ],
    "wof:name":"Universal Logistic Solutions",
    "wof:placetype":"venue"
},
  "geometry": {"coordinates":[144.801636,-37.820835],"type":"Point"}
}