{
  "type": "Feature",
  "properties": {
    "addr:full":"235 River St Ballina NSW 2478",
    "addr:housenumber":"235",
    "addr:postcode":"2478",
    "addr:street":"River St",
    "iso:country":"AU",
    "sg:address":"235 River St",
    "sg:city":"Ballina",
    "sg:classifiers":[
        {
            "category":"Personal",
            "type":"Services"
        }
    ],
    "sg:phone":"+61 2 6686 5100",
    "sg:postcode":"2478",
    "sg:province":"NSW",
    "sg:tags":[
        "gift"
    ],
    "wof:name":"Ballina Florist",
    "wof:placetype":"venue"
},
  "geometry": {"coordinates":[153.556915283,-28.8688907623],"type":"Point"}
}