{
  "type": "Feature",
  "properties": {
    "addr:full":"Shp 9, Lvl 4 , Robina Town Cntr Robina QLD 4226",
    "addr:housenumber":"4",
    "addr:postcode":"4226",
    "addr:street":"Robina Town",
    "iso:country":"AU",
    "sg:address":"Shp 9, Lvl 4",
    "sg:city":", Robina Town Cntr Robina",
    "sg:classifiers":[
        {
            "category":"Banks & Credit Unions",
            "subcategory":"Bank",
            "type":"Services"
        }
    ],
    "sg:phone":"+61 7 5575 7733",
    "sg:postcode":"4226",
    "sg:province":"QLD",
    "wof:name":"Bendigo Bank",
    "wof:placetype":"venue"
},
  "geometry": {"coordinates":[153.38798523,-28.0730552673],"type":"Point"}
}