{
  "type": "Feature",
  "properties": {
    "addr:full":"38 Were St Montmorency VIC 3094",
    "addr:housenumber":"38",
    "addr:postcode":"3094",
    "addr:street":"Were St",
    "iso:country":"AU",
    "sg:address":"38 Were St",
    "sg:city":"Montmorency",
    "sg:classifiers":[
        {
            "category":"Food & Beverages",
            "subcategory":"Fruits & Vegetables",
            "type":"Retail Goods"
        }
    ],
    "sg:phone":"+61 3 9432 0534",
    "sg:postcode":"3094",
    "sg:province":"VIC",
    "sg:tags":[
        "greengrocer",
        "fruiterer"
    ],
    "wof:name":"Antons Fruit Tree",
    "wof:placetype":"venue"
},
  "geometry": {"coordinates":[145.121368408,-37.7162857056],"type":"Point"}
}