{
  "type": "Feature",
  "properties": {
    "addr:full":"16 Allen St Korong Vale VIC 3520",
    "addr:housenumber":"16",
    "addr:postcode":"3520",
    "addr:street":"Allen St",
    "iso:country":"AU",
    "sg:address":"16 Allen St",
    "sg:city":"Korong Vale",
    "sg:classifiers":[
        {
            "category":"Food & Beverages",
            "subcategory":"Groceries & Convenience Stores",
            "type":"Retail Goods"
        }
    ],
    "sg:phone":"+61 3 5494 7203",
    "sg:postcode":"3520",
    "sg:province":"VIC",
    "wof:name":"Korong Vale General Store",
    "wof:placetype":"venue"
},
  "geometry": {"coordinates":[143.705734253,-36.3565711975],"type":"Point"}
}