{
  "type": "Feature",
  "properties": {
    "addr:full":"Shp1/ 49 Cheek Ave Gawler East SA 5118",
    "addr:postcode":"5118",
    "addr:street":"Cheek Ave",
    "iso:country":"AU",
    "sg:address":"Shp1/ 49 Cheek Ave",
    "sg:city":"Gawler East",
    "sg:classifiers":[
        {
            "category":"Deli",
            "type":"Food & Drink"
        }
    ],
    "sg:phone":"+61 8 8523 0501",
    "sg:postcode":"5118",
    "sg:province":"SA",
    "sg:tags":[
        "delicatessen"
    ],
    "wof:name":"Cheek Ave Super Deli",
    "wof:placetype":"venue"
},
  "geometry": {"coordinates":[138.76383999999999,-34.59293],"type":"Point"}
}