{
  "type": "Feature",
  "properties": {
    "addr:full":"7 Macrobertson St Lower Templestowe VIC 3107",
    "addr:housenumber":"7",
    "addr:postcode":"3107",
    "addr:street":"Macrobertson St",
    "iso:country":"AU",
    "sg:address":"7 Macrobertson St",
    "sg:city":"Lower Templestowe",
    "sg:classifiers":[
        {
            "category":"Building & Trades",
            "subcategory":"Plumbing",
            "type":"Services"
        }
    ],
    "sg:phone":"+61 3 9850 1705",
    "sg:postcode":"3107",
    "sg:province":"VIC",
    "sg:tags":[
        "plumber",
        "gasfitters"
    ],
    "wof:name":"Andrewartha Plumbing Contractors",
    "wof:placetype":"venue"
},
  "geometry": {"coordinates":[145.11845398,-37.7598686218],"type":"Point"}
}