{
  "type": "Feature",
  "properties": {
    "iso:country":"AU",
    "sg:address":"64 Hansen St",
    "sg:city":"Corryong",
    "sg:classifiers":[
        {
            "category":"Shopping",
            "type":"Retail Goods"
        }
    ],
    "sg:phone":"+61 2 6076 2054",
    "sg:postcode":"3707",
    "sg:province":"VIC",
    "sg:tags":[
        "agent",
        "stock"
    ],
    "wof:name":"Costello Rural",
    "wof:placetype":"venue"
},
  "geometry": {"coordinates":[147.90342712399999,-36.1960792542],"type":"Point"}
}