{
  "type": "Feature",
  "properties": {
    "addr:full":"Mt Drummond Rd Mt Drummond SA 5607",
    "addr:postcode":"5607",
    "addr:street":"Mt Drummond Rd",
    "iso:country":"AU",
    "sg:address":"Mt Drummond Rd",
    "sg:city":"Mt Drummond",
    "sg:classifiers":[
        {
            "category":"Farming",
            "subcategory":"Farm",
            "type":"Manufacturing & Wholesale Goods"
        }
    ],
    "sg:phone":"+61 8 8687 7474",
    "sg:postcode":"5607",
    "sg:province":"SA",
    "sg:tags":[
        "farmer"
    ],
    "wof:name":"Doudle Michael M",
    "wof:placetype":"venue"
},
  "geometry": {"coordinates":[135.386292,-34.217407],"type":"Point"}
}