{
  "type": "Feature",
  "properties": {
    "addr:full":"PO Box 1280 Elwood VIC 3184",
    "addr:postcode":"3184",
    "iso:country":"AU",
    "sg:address":"PO Box 1280",
    "sg:city":"Elwood",
    "sg:classifiers":[
        {
            "category":"Building & Trades",
            "subcategory":"Construction",
            "type":"Services"
        }
    ],
    "sg:phone":"+61 3 9531 6866",
    "sg:postcode":"3184",
    "sg:province":"VIC",
    "sg:tags":[
        "polishing",
        "sanding",
        "floor"
    ],
    "wof:name":"AMPA Floor Systems",
    "wof:placetype":"venue"
},
  "geometry": {"coordinates":[144.98576355,-37.8810195923],"type":"Point"}
}