{
  "type": "Feature",
  "properties": {
    "iso:country":"AU",
    "sg:address":"Phoenecian 25 Queensland Ave",
    "sg:city":"Broadbeach",
    "sg:classifiers":[
        {
            "category":"Cafe",
            "type":"Food & Drink"
        }
    ],
    "sg:phone":"+61 7 5527 6287",
    "sg:postcode":"4218",
    "sg:province":"QLD",
    "wof:name":"Decadence",
    "wof:placetype":"venue"
},
  "geometry": {"coordinates":[153.43168640100001,-28.0274410248],"type":"Point"}
}