{
  "type": "Feature",
  "properties": {
    "addr:full":"27 Royal Crs Kinglake VIC 3763",
    "addr:housenumber":"27",
    "addr:postcode":"3763",
    "addr:street":"Royal Crs Kinglake",
    "iso:country":"AU",
    "sg:address":"27 Royal Crs",
    "sg:city":"Kinglake",
    "sg:classifiers":[
        {
            "category":"Train Station",
            "subcategory":"Light Rail",
            "type":"Transportation"
        }
    ],
    "sg:phone":"+61 3 5786 1686",
    "sg:postcode":"3763",
    "sg:province":"VIC",
    "sg:tags":[
        "equipment",
        "energy",
        "solar"
    ],
    "wof:name":"AAA Alternate Power Systems",
    "wof:placetype":"venue"
},
  "geometry": {"coordinates":[145.34014892600001,-37.5305786133],"type":"Point"}
}