{
  "type": "Feature",
  "properties": {
    "addr:full":"326 South Pine Rd Brendale QLD 4500",
    "addr:housenumber":"326",
    "addr:postcode":"4500",
    "addr:street":"South Pine Rd",
    "iso:country":"AU",
    "sg:address":"326 South Pine Rd",
    "sg:city":"Brendale",
    "sg:classifiers":[
        {
            "category":"Industrial Area",
            "type":"Public Place"
        }
    ],
    "sg:phone":"+61 7 3205 7052",
    "sg:postcode":"4500",
    "sg:province":"QLD",
    "sg:tags":[
        "rural",
        "shed"
    ],
    "wof:name":"Brisbane Garden Sheds",
    "wof:placetype":"venue"
},
  "geometry": {"coordinates":[152.98733520499999,-27.3244762421],"type":"Point"}
}