{
  "type": "Feature",
  "properties": {
    "addr:full":"Shop 5A 131 Elizabeth St Brisbane QLD 4000",
    "addr:housenumber":"shop 5a 131",
    "addr:postcode":"4000",
    "addr:street":"Elizabeth St",
    "iso:country":"AU",
    "sg:address":"Shop 5A 131 Elizabeth St",
    "sg:city":"Brisbane",
    "sg:classifiers":[
        {
            "category":"Travel",
            "subcategory":"Travel Agent",
            "type":"Entertainment"
        }
    ],
    "sg:phone":"+61 7 3211 8900",
    "sg:postcode":"4000",
    "sg:province":"QLD",
    "sg:tags":[
        "consultant"
    ],
    "wof:name":"Backpackers World Travel",
    "wof:placetype":"venue"
},
  "geometry": {"coordinates":[153.026245117,-27.4703807831],"type":"Point"}
}