{
  "type": "Feature",
  "properties": {
    "addr:full":"21 Clarence Drv Helensvale QLD 4212",
    "addr:housenumber":"21",
    "addr:postcode":"4212",
    "addr:street":"Clarence Drv",
    "iso:country":"AU",
    "sg:address":"21 Clarence Drv",
    "sg:city":"Helensvale",
    "sg:classifiers":[
        {
            "category":"Utilities",
            "subcategory":"Water",
            "type":"Services"
        }
    ],
    "sg:phone":"+61 417 756 010",
    "sg:postcode":"4212",
    "sg:province":"QLD",
    "sg:tags":[
        "hot",
        "system"
    ],
    "wof:name":"Gary Sullivan Electrical",
    "wof:placetype":"venue"
},
  "geometry": {"coordinates":[153.32591247600001,-27.8897171021],"type":"Point"}
}