{
  "type": "Feature",
  "properties": {
    "iso:country":"AU",
    "sg:address":"Oakdowns Pde",
    "sg:city":"Oakdowns",
    "sg:classifiers":[
        {
            "category":"Education",
            "subcategory":"Kindergarten",
            "type":"Public Place"
        }
    ],
    "sg:phone":"+61 3 6247 6589",
    "sg:postcode":"7019",
    "sg:province":"TAS",
    "sg:tags":[
        "pre-schools"
    ],
    "wof:name":"Oakdowns Early Learning Centre",
    "wof:placetype":"venue"
},
  "geometry": {"coordinates":[147.456863403,-42.8998832703],"type":"Point"}
}