{
  "type": "Feature",
  "properties": {
    "iso:country":"AU",
    "sg:address":"Brodie St",
    "sg:city":"Hughenden",
    "sg:classifiers":[
        {
            "category":"Organizations",
            "subcategory":"Professional Association",
            "type":"Services"
        }
    ],
    "sg:phone":"+61 7 4741 1329",
    "sg:postcode":"4821",
    "sg:province":"QLD",
    "sg:tags":[
        "rural",
        "organisation",
        "production",
        "primary"
    ],
    "wof:name":"Hughenden Show Society Inc.",
    "wof:placetype":"venue"
},
  "geometry": {"coordinates":[144.19488525400001,-20.8416843414],"type":"Point"}
}