{
  "type": "Feature",
  "properties": {
    "addr:full":"2 Loftus St Narrabeen NSW 2101",
    "addr:housenumber":"2",
    "addr:postcode":"2101",
    "addr:street":"Loftus St",
    "iso:country":"AU",
    "sg:address":"2 Loftus St",
    "sg:city":"Narrabeen",
    "sg:classifiers":[
        {
            "category":"Autos & Motor Vehicles",
            "subcategory":"Boat Sales",
            "type":"Retail Goods"
        }
    ],
    "sg:phone":"+61 2 9979 6888",
    "sg:postcode":"2101",
    "sg:province":"NSW",
    "sg:tags":[
        "yacht"
    ],
    "wof:name":"Williams Cedric Marine Pty Ltd",
    "wof:placetype":"venue"
},
  "geometry": {"coordinates":[151.301941,-33.710381],"type":"Point"}
}