{
  "type": "Feature",
  "properties": {
    "iso:country":"AU",
    "sg:address":"Lot11/ Dray's Rd",
    "sg:city":"Bowen",
    "sg:classifiers":[
        {
            "category":"Personal",
            "subcategory":"Nail Salon",
            "type":"Services"
        }
    ],
    "sg:phone":"+61 437 798 576",
    "sg:postcode":"4805",
    "sg:province":"QLD",
    "sg:tags":[
        "artificial"
    ],
    "wof:name":"Rusti Nailz",
    "wof:placetype":"venue"
},
  "geometry": {"coordinates":[148.22084045400001,-20.0146598816],"type":"Point"}
}