{
  "type": "Feature",
  "properties": {
    "iso:country":"AU",
    "sg:address":"4 Werribee St",
    "sg:city":"North Rockhampton",
    "sg:classifiers":[
        {
            "category":"Utilities",
            "subcategory":"Refuse",
            "type":"Services"
        }
    ],
    "sg:phone":"+61 7 4923 7800",
    "sg:postcode":"4701",
    "sg:province":"QLD",
    "sg:tags":[
        "disposal",
        "reduction",
        "waste"
    ],
    "wof:name":"Wanless Wastecorp",
    "wof:placetype":"venue"
},
  "geometry": {"coordinates":[150.503143311,-23.3313598633],"type":"Point"}
}