{
  "type": "Feature",
  "properties": {
    "addr:full":"2a/ 15 Parnell St Strathfield NSW 2135",
    "addr:housenumber":"2a / 15",
    "addr:postcode":"2135",
    "addr:street":"Parnell St",
    "iso:country":"AU",
    "sg:address":"2a/ 15 Parnell St",
    "sg:city":"Strathfield",
    "sg:classifiers":[
        {
            "category":"Real Estate",
            "subcategory":"Real Estate Agent",
            "type":"Services"
        }
    ],
    "sg:phone":"+61 2 9744 5511",
    "sg:postcode":"2135",
    "sg:province":"NSW",
    "wof:name":"Ray White Strathfield",
    "wof:placetype":"venue"
},
  "geometry": {"coordinates":[151.09669494600001,-33.8736495972],"type":"Point"}
}