{
  "type": "Feature",
  "properties": {
    "addr:full":"8 Alma Rd New Lambton NSW 2305",
    "addr:housenumber":"8",
    "addr:postcode":"2305",
    "addr:street":"Alma Rd",
    "iso:country":"AU",
    "sg:address":"8 Alma Rd",
    "sg:city":"New Lambton",
    "sg:classifiers":[
        {
            "category":"Government",
            "subcategory":"Fire Station",
            "type":"Public Place"
        }
    ],
    "sg:phone":"+61 2 4952 8855",
    "sg:postcode":"2305",
    "sg:province":"NSW",
    "sg:tags":[
        "brigade"
    ],
    "wof:name":"Fire Brigades-NSW",
    "wof:placetype":"venue"
},
  "geometry": {"coordinates":[151.71455399999999,-32.922058],"type":"Point"}
}