{
  "type": "Feature",
  "properties": {
    "addr:full":"Shop 10 wyndham mall 294 Wyndham St Shepparton VIC 3630",
    "addr:housenumber":"shop 10;294",
    "addr:postcode":"3630",
    "addr:street":"Wyndham Mall;Wyndham St",
    "iso:country":"AU",
    "sg:address":"Shop 10 wyndham mall 294 Wyndham St",
    "sg:city":"Shepparton",
    "sg:classifiers":[
        {
            "category":"Personal",
            "subcategory":"Beauty Salon",
            "type":"Services"
        }
    ],
    "sg:phone":"+61 3 5822 4847",
    "sg:postcode":"3630",
    "sg:province":"VIC",
    "wof:name":"Cosmetic & Fragrance Collection",
    "wof:placetype":"venue"
},
  "geometry": {"coordinates":[145.39944457999999,-36.3796386719],"type":"Point"}
}