{
  "type": "Feature",
  "properties": {
    "addr:full":"8 Rowland St Slacks Creek QLD 4127",
    "addr:housenumber":"8",
    "addr:postcode":"4127",
    "addr:street":"Rowland St",
    "iso:country":"AU",
    "sg:address":"8 Rowland St",
    "sg:city":"Slacks Creek",
    "sg:classifiers":[
        {
            "category":"Autos & Motor Vehicles",
            "subcategory":"Auto Supplies",
            "type":"Retail Goods"
        }
    ],
    "sg:phone":"+61 7 3804 3455",
    "sg:postcode":"4127",
    "sg:province":"QLD",
    "sg:tags":[
        "tyre"
    ],
    "wof:name":"Second Hand Tyre King The",
    "wof:placetype":"venue"
},
  "geometry": {"coordinates":[153.127227783,-27.628988266],"type":"Point"}
}