{
  "type": "Feature",
  "properties": {
    "iso:country":"AU",
    "sg:address":"9 Vivian St",
    "sg:city":"Nambour",
    "sg:classifiers":[
        {
            "category":"Retail",
            "subcategory":"Repair Shop",
            "type":"Services"
        }
    ],
    "sg:phone":"+61 403 048 507",
    "sg:postcode":"4560",
    "sg:province":"QLD",
    "sg:tags":[
        "machine",
        "sewing"
    ],
    "wof:name":"The Sewing Machine Doctor",
    "wof:placetype":"venue"
},
  "geometry": {"coordinates":[152.93255615199999,-26.6176357269],"type":"Point"}
}