{
  "type": "Feature",
  "properties": {
    "addr:full":"Suite 1 Level 1, 127- 129 John St Singleton NSW 2330",
    "addr:housenumber":"127 129",
    "addr:postcode":"2330",
    "addr:street":"John St",
    "iso:country":"AU",
    "sg:address":"Suite 1 Level 1, 127- 129 John St",
    "sg:city":"Singleton",
    "sg:classifiers":[
        {
            "category":"Professional",
            "subcategory":"Engineering",
            "type":"Services"
        }
    ],
    "sg:phone":"+61 2 6575 2600",
    "sg:postcode":"2330",
    "sg:province":"NSW",
    "sg:tags":[
        "consulting",
        "engineer"
    ],
    "wof:name":"WorleyParsons",
    "wof:placetype":"venue"
},
  "geometry": {"coordinates":[151.167542,-32.565079],"type":"Point"}
}