{
  "type": "Feature",
  "properties": {
    "addr:full":"31 Mildura St Norseman WA 6443",
    "addr:housenumber":"31",
    "addr:postcode":"6443",
    "addr:street":"Mildura St",
    "iso:country":"AU",
    "sg:address":"31 Mildura St",
    "sg:city":"Norseman",
    "sg:classifiers":[
        {
            "category":"Retail",
            "subcategory":"Funeral Services",
            "type":"Services"
        }
    ],
    "sg:phone":"+61 8 9039 1117",
    "sg:postcode":"6443",
    "sg:province":"WA",
    "sg:tags":[
        "director"
    ],
    "wof:name":"Hogan P & L Funeral Directors",
    "wof:placetype":"venue"
},
  "geometry": {"coordinates":[121.774047852,-32.1996192932],"type":"Point"}
}