{
  "type": "Feature",
  "properties": {
    "addr:full":"107 Archibald St Mackay QLD 4740",
    "addr:housenumber":"107",
    "addr:postcode":"4740",
    "addr:street":"Archibald St",
    "iso:country":"AU",
    "sg:address":"107 Archibald St",
    "sg:city":"Mackay",
    "sg:classifiers":[
        {
            "category":"Building & Trades",
            "subcategory":"Construction",
            "type":"Services"
        }
    ],
    "sg:phone":"+61 407 125 871",
    "sg:postcode":"4740",
    "sg:province":"QLD",
    "sg:tags":[
        "welding"
    ],
    "wof:name":"Glen Harmer Welding",
    "wof:placetype":"venue"
},
  "geometry": {"coordinates":[149.15417500000001,-21.018156],"type":"Point"}
}