{
  "type": "Feature",
  "properties": {
    "iso:country":"AU",
    "sg:address":"Forbes St",
    "sg:city":"Turner",
    "sg:classifiers":[
        {
            "category":"Building & Trades",
            "subcategory":"Construction",
            "type":"Services"
        }
    ],
    "sg:phone":"+61 419 635 627",
    "sg:postcode":"2612",
    "sg:province":"ACT",
    "sg:tags":[
        "plasterboard",
        "plasterer",
        "fixer"
    ],
    "wof:name":"Thatcher A H",
    "wof:placetype":"venue"
},
  "geometry": {"coordinates":[149.1300354,-35.264919281],"type":"Point"}
}