{
  "type": "Feature",
  "properties": {
    "addr:full":"Cnr Fern & Station Sts Mullumbimby NSW 2482",
    "addr:postcode":"2482",
    "addr:street":"Cnr",
    "iso:country":"AU",
    "sg:address":"Cnr Fern & Station Sts",
    "sg:city":"Mullumbimby",
    "sg:classifiers":[
        {
            "category":"Education",
            "subcategory":"Kindergarten",
            "type":"Public Place"
        }
    ],
    "sg:phone":"+61 2 6684 1269",
    "sg:postcode":"2482",
    "sg:province":"NSW",
    "sg:tags":[
        "pre-schools"
    ],
    "wof:name":"Mullumbimby Community Preschool",
    "wof:placetype":"venue"
},
  "geometry": {"coordinates":[153.49937439000001,-28.5563545227],"type":"Point"}
}