{
  "type": "Feature",
  "properties": {
    "addr:full":"3/ 76 Commercial Drv Thomastown VIC 3074",
    "addr:housenumber":"/ 76",
    "addr:postcode":"3074",
    "addr:street":"Commercial Drv",
    "iso:country":"AU",
    "sg:address":"3/ 76 Commercial Drv",
    "sg:city":"Thomastown",
    "sg:classifiers":[
        {
            "category":"Professional",
            "type":"Services"
        }
    ],
    "sg:phone":"+61 3 9465 8218",
    "sg:postcode":"3074",
    "sg:province":"VIC",
    "sg:tags":[
        "coating",
        "powder"
    ],
    "wof:name":"Northern Powder Coating",
    "wof:placetype":"venue"
},
  "geometry": {"coordinates":[145.04225158700001,-37.6893882751],"type":"Point"}
}