{
  "type": "Feature",
  "properties": {
    "iso:country":"AU",
    "sg:address":"19 Stanley St",
    "sg:city":"Wallan",
    "sg:classifiers":[
        {
            "category":"Building & Trades",
            "subcategory":"Construction",
            "type":"Services"
        }
    ],
    "sg:phone":"+61 1300 376 278",
    "sg:postcode":"3756",
    "sg:province":"VIC",
    "sg:tags":[
        "earth",
        "excavating",
        "moving",
        "contractor"
    ],
    "wof:name":"J & K EarthSmart",
    "wof:placetype":"venue"
},
  "geometry": {"coordinates":[144.976074,-37.415119],"type":"Point"}
}