{
  "type": "Feature",
  "properties": {
    "addr:full":"1 Bando Rd Springvale VIC 3171",
    "addr:housenumber":"1",
    "addr:postcode":"3171",
    "addr:street":"Bando Rd",
    "iso:country":"AU",
    "sg:address":"1 Bando Rd",
    "sg:city":"Springvale",
    "sg:classifiers":[
        {
            "category":"Utilities",
            "subcategory":"Refuse",
            "type":"Services"
        }
    ],
    "sg:phone":"+61 3 9870 7302",
    "sg:postcode":"3171",
    "sg:province":"VIC",
    "sg:tags":[
        "remover",
        "rubbish"
    ],
    "wof:name":"A Class Bin Hire",
    "wof:placetype":"venue"
},
  "geometry": {"coordinates":[145.14140319800001,-37.9459037781],"type":"Point"}
}