{
  "type": "Feature",
  "properties": {
    "iso:country":"AU",
    "sg:address":"60 York St",
    "sg:city":"Queenton",
    "sg:classifiers":[
        {
            "category":"Travel",
            "subcategory":"Hotels & Motels",
            "type":"Entertainment"
        }
    ],
    "sg:phone":"+61 7 4787 1998",
    "sg:postcode":"4820",
    "sg:province":"QLD",
    "wof:name":"Accomodation For Workers",
    "wof:placetype":"venue"
},
  "geometry": {"coordinates":[146.265503,-20.083467],"type":"Point"}
}