{
  "type": "Feature",
  "properties": {
    "addr:full":"Suite 3, 235 Rocky Pt Rd Ramsgate NSW 2217",
    "addr:housenumber":"235",
    "addr:postcode":"2217",
    "addr:street":"Rocky Pt Rd",
    "iso:country":"AU",
    "sg:address":"Suite 3, 235 Rocky Pt Rd",
    "sg:city":"Ramsgate",
    "sg:classifiers":[
        {
            "category":"Health Services",
            "subcategory":"Dentist",
            "type":"Services"
        }
    ],
    "sg:phone":"+61 2 9583 1006",
    "sg:postcode":"2217",
    "sg:province":"NSW",
    "sg:tags":[
        "dental",
        "prosthetist"
    ],
    "wof:name":"Angus Richard Dental Laboratory",
    "wof:placetype":"venue"
},
  "geometry": {"coordinates":[151.135986,-33.984837],"type":"Point"}
}