{
  "type": "Feature",
  "properties": {
    "addr:full":"39 Piper St Caboolture QLD 4510",
    "addr:housenumber":"39",
    "addr:postcode":"4510",
    "addr:street":"Piper St",
    "iso:country":"AU",
    "sg:address":"39 Piper St",
    "sg:city":"Caboolture",
    "sg:classifiers":[
        {
            "category":"Wholesale",
            "subcategory":"Medical Equipment & Supplies",
            "type":"Manufacturing & Wholesale Goods"
        }
    ],
    "sg:phone":"+61 7 5498 3388",
    "sg:postcode":"4510",
    "sg:province":"QLD",
    "sg:tags":[
        "plastering"
    ],
    "wof:name":"Lafarge Plastermasta",
    "wof:placetype":"venue"
},
  "geometry": {"coordinates":[152.985535,-27.08292],"type":"Point"}
}