{
  "type": "Feature",
  "properties": {
    "addr:full":"Burngup Rd North Pingaring WA 6357",
    "addr:postcode":"6357",
    "addr:street":"Burngup Rd North Pingaring",
    "iso:country":"AU",
    "sg:address":"Burngup Rd North",
    "sg:city":"Pingaring",
    "sg:classifiers":[
        {
            "category":"Farming",
            "subcategory":"Farm",
            "type":"Manufacturing & Wholesale Goods"
        }
    ],
    "sg:phone":"+61 8 9866 8039",
    "sg:postcode":"6357",
    "sg:province":"WA",
    "sg:tags":[
        "farmer"
    ],
    "wof:name":"Jenks Harry",
    "wof:placetype":"venue"
},
  "geometry": {"coordinates":[118.66029399999999,-32.739906],"type":"Point"}
}