{
  "type": "Feature",
  "properties": {
    "addr:full":"Suite 4/ 23 Glen Affric St The Gap QLD 4061",
    "addr:postcode":"4061",
    "addr:street":"St",
    "iso:country":"AU",
    "sg:address":"Suite 4/ 23 Glen Affric St",
    "sg:city":"The Gap",
    "sg:classifiers":[
        {
            "category":"Professional",
            "subcategory":"Accounting & Tax Preparation",
            "type":"Services"
        }
    ],
    "sg:phone":"+61 7 3300 1000",
    "sg:postcode":"4061",
    "sg:province":"QLD",
    "sg:tags":[
        "accountant",
        "auditor"
    ],
    "wof:name":"Northwest Bookkeeping Pty Ltd",
    "wof:placetype":"venue"
},
  "geometry": {"coordinates":[152.953613281,-27.4460029602],"type":"Point"}
}