{
  "type": "Feature",
  "properties": {
    "addr:full":"Cnr Cygnet Ave & New Lake Entrance Rd Shellharbour NSW 2529",
    "addr:postcode":"2529",
    "addr:street":"Cnr Cygnet Ave & New Lake Entrance Rd",
    "iso:country":"AU",
    "sg:address":"Cnr Cygnet Ave & New Lake Entrance Rd",
    "sg:city":"Shellharbour",
    "sg:classifiers":[
        {
            "category":"Autos & Motor Vehicles",
            "subcategory":"Auto Supplies",
            "type":"Retail Goods"
        }
    ],
    "sg:phone":"+61 2 4297 3600",
    "sg:postcode":"2529",
    "sg:province":"NSW",
    "sg:tags":[
        "wheel",
        "automotive",
        "rim"
    ],
    "wof:name":"Bob Jane T-Marts",
    "wof:placetype":"venue"
},
  "geometry": {"coordinates":[150.83392334000001,-34.5693473816],"type":"Point"}
}