{
  "type": "Feature",
  "properties": {
    "addr:full":"4 Exeter Crt Dandenong VIC 3175",
    "addr:housenumber":"4",
    "addr:postcode":"3175",
    "addr:street":"Exeter Crt",
    "iso:country":"AU",
    "sg:address":"4 Exeter Crt",
    "sg:city":"Dandenong",
    "sg:classifiers":[
        {
            "category":"Utilities",
            "subcategory":"Water",
            "type":"Services"
        }
    ],
    "sg:phone":"+61 409 961 085",
    "sg:postcode":"3175",
    "sg:province":"VIC",
    "sg:tags":[
        "hot",
        "system"
    ],
    "wof:name":"Moores Emergency Plumbing Service",
    "wof:placetype":"venue"
},
  "geometry": {"coordinates":[145.209747314,-37.9745483398],"type":"Point"}
}