{
  "type": "Feature",
  "properties": {
    "addr:full":"60 Nerang St Nerang QLD 4211",
    "addr:housenumber":"60",
    "addr:postcode":"4211",
    "addr:street":"Nerang St",
    "iso:country":"AU",
    "sg:address":"60 Nerang St",
    "sg:city":"Nerang",
    "sg:classifiers":[
        {
            "category":"Education",
            "subcategory":"Special Training",
            "type":"Public Place"
        }
    ],
    "sg:phone":"+61 7 5527 4710",
    "sg:postcode":"4211",
    "sg:province":"QLD",
    "sg:tags":[
        "development"
    ],
    "wof:name":"Campion College",
    "wof:placetype":"venue"
},
  "geometry": {"coordinates":[153.339187622,-27.9880695343],"type":"Point"}
}