{
  "type": "Feature",
  "properties": {
    "addr:full":"13 Zinnea St Elanora QLD 4221",
    "addr:housenumber":"13",
    "addr:postcode":"4221",
    "addr:street":"Zinnea St",
    "iso:country":"AU",
    "sg:address":"13 Zinnea St",
    "sg:city":"Elanora",
    "sg:classifiers":[
        {
            "category":"Professional",
            "subcategory":"Art Services",
            "type":"Services"
        }
    ],
    "sg:phone":"+61 7 5534 9271",
    "sg:postcode":"4221",
    "sg:province":"QLD",
    "sg:tags":[
        "decorator",
        "painter"
    ],
    "wof:name":"B & S Whien Painting Service",
    "wof:placetype":"venue"
},
  "geometry": {"coordinates":[153.44798278799999,-28.1323013306],"type":"Point"}
}