{
  "type": "Feature",
  "properties": {
    "iso:country":"AU",
    "sg:address":"38 Merrivale Drv",
    "sg:city":"Warrnambool",
    "sg:classifiers":[
        {
            "category":"Utilities",
            "subcategory":"Natural Gas",
            "type":"Services"
        }
    ],
    "sg:phone":"+61 3 5562 9955",
    "sg:postcode":"3280",
    "sg:province":"VIC",
    "sg:tags":[
        "solid",
        "plasterer"
    ],
    "wof:name":"Munday's Rendering",
    "wof:placetype":"venue"
},
  "geometry": {"coordinates":[142.469482422,-38.3839683533],"type":"Point"}
}