{
  "type": "Feature",
  "properties": {
    "iso:country":"AU",
    "sg:address":"22 Enterprise St",
    "sg:city":"Caloundra",
    "sg:classifiers":[
        {
            "category":"Bus Charters",
            "type":"Transportation"
        }
    ],
    "sg:phone":"+61 7 5437 0981",
    "sg:postcode":"4551",
    "sg:province":"QLD",
    "sg:tags":[
        "builder"
    ],
    "wof:name":"Bus & R.V Modifications",
    "wof:placetype":"venue"
},
  "geometry": {"coordinates":[153.11549377399999,-26.7956523895],"type":"Point"}
}