{
  "type": "Feature",
  "properties": {
    "addr:full":"50 Newmarket St Hendra QLD 4011",
    "addr:housenumber":"50",
    "addr:postcode":"4011",
    "addr:street":"Newmarket St",
    "iso:country":"AU",
    "sg:address":"50 Newmarket St",
    "sg:city":"Hendra",
    "sg:classifiers":[
        {
            "category":"Personal",
            "type":"Services"
        }
    ],
    "sg:phone":"+61 7 3268 4489",
    "sg:postcode":"4011",
    "sg:province":"QLD",
    "sg:tags":[
        "dressmaker"
    ],
    "wof:name":"Ayhwa Design",
    "wof:placetype":"venue"
},
  "geometry": {"coordinates":[153.07048,-27.420446],"type":"Point"}
}