{
  "type": "Feature",
  "properties": {
    "addr:full":"78 Condamine St Balgowlah NSW 2093",
    "addr:housenumber":"78",
    "addr:postcode":"2093",
    "addr:street":"Condamine St",
    "iso:country":"AU",
    "sg:address":"78 Condamine St",
    "sg:city":"Balgowlah",
    "sg:classifiers":[
        {
            "category":"Banks & Credit Unions",
            "subcategory":"Financial Services",
            "type":"Services"
        }
    ],
    "sg:phone":"+61 414 675 271",
    "sg:postcode":"2093",
    "sg:province":"NSW",
    "sg:tags":[
        "assistance",
        "roadside"
    ],
    "wof:name":"Manly Warringah Battery Service",
    "wof:placetype":"venue"
},
  "geometry": {"coordinates":[151.26435852,-33.797416687],"type":"Point"}
}