{
  "type": "Feature",
  "properties": {
    "iso:country":"AU",
    "sg:address":"12 McKenzie St",
    "sg:city":"Blackwater",
    "sg:classifiers":[
        {
            "category":"Retail",
            "subcategory":"Car Wash",
            "type":"Services"
        }
    ],
    "sg:phone":"+61 7 4982 6470",
    "sg:postcode":"4717",
    "sg:province":"QLD",
    "sg:tags":[
        "merchant",
        "oil",
        "refiner"
    ],
    "wof:name":"BP Oil",
    "wof:placetype":"venue"
},
  "geometry": {"coordinates":[148.879639,-23.583017],"type":"Point"}
}