{
  "type": "Feature",
  "properties": {
    "addr:full":"67 Waterworks Rd Red Hill QLD 4059",
    "addr:housenumber":"67",
    "addr:postcode":"4059",
    "addr:street":"Waterworks Rd",
    "iso:country":"AU",
    "sg:address":"67 Waterworks Rd",
    "sg:city":"Red Hill",
    "sg:classifiers":[
        {
            "category":"Shopping",
            "subcategory":"Crafts & Fabrics",
            "type":"Retail Goods"
        }
    ],
    "sg:phone":"+61 7 3369 1832",
    "sg:postcode":"4059",
    "sg:province":"QLD",
    "sg:tags":[
        "supply"
    ],
    "wof:name":"Terracotta Factory The",
    "wof:placetype":"venue"
},
  "geometry": {"coordinates":[153.000823975,-27.4504051208],"type":"Point"}
}