{
  "type": "Feature",
  "properties": {
    "addr:full":"5 Wirrecoo St Berrara NSW 2540",
    "addr:housenumber":"5",
    "addr:postcode":"2540",
    "addr:street":"Wirrecoo St",
    "iso:country":"AU",
    "sg:address":"5 Wirrecoo St",
    "sg:city":"Berrara",
    "sg:classifiers":[
        {
            "category":"Education",
            "subcategory":"Special Training",
            "type":"Public Place"
        }
    ],
    "sg:phone":"+61 2 4441 2937",
    "sg:postcode":"2540",
    "sg:province":"NSW",
    "sg:tags":[
        "school",
        "sailing"
    ],
    "wof:name":"Lets Go Sailing",
    "wof:placetype":"venue"
},
  "geometry": {"coordinates":[150.55271911599999,-35.2063560486],"type":"Point"}
}