{
  "type": "Feature",
  "properties": {
    "addr:full":"58 Mentmore Ave Rosebery NSW 2018",
    "addr:housenumber":"58",
    "addr:postcode":"2018",
    "addr:street":"Mentmore Ave",
    "iso:country":"AU",
    "sg:address":"58 Mentmore Ave",
    "sg:city":"Rosebery",
    "sg:classifiers":[
        {
            "category":"Professional",
            "subcategory":"Printing & Photocopies",
            "type":"Services"
        }
    ],
    "sg:phone":"+61 2 9517 9355",
    "sg:postcode":"2018",
    "sg:province":"NSW",
    "sg:tags":[
        "screen",
        "printer"
    ],
    "wof:name":"Megaprint Systemised Screenprinting",
    "wof:placetype":"venue"
},
  "geometry": {"coordinates":[151.20297241200001,-33.9180412292],"type":"Point"}
}