{
  "type": "Feature",
  "properties": {
    "addr:full":"Lvl 10, 101 Collins St Melbourne VIC 3001",
    "addr:housenumber":"101",
    "addr:postcode":"3001",
    "addr:street":"Collins St",
    "iso:country":"AU",
    "sg:address":"Lvl 10, 101 Collins St",
    "sg:city":"Melbourne",
    "sg:classifiers":[
        {
            "category":"Banks & Credit Unions",
            "subcategory":"Financial Services",
            "type":"Services"
        }
    ],
    "sg:phone":"+61 3 8616 1000",
    "sg:postcode":"3001",
    "sg:province":"VIC",
    "sg:tags":[
        "planning"
    ],
    "wof:name":"Genesys Wealth Advisers",
    "wof:placetype":"venue"
},
  "geometry": {"coordinates":[144.97036743199999,-37.8144950867],"type":"Point"}
}