{
  "type": "Feature",
  "properties": {
    "addr:full":"Shop 1006 , Westfield Shopng Cntr Helensvale QLD 4212",
    "addr:housenumber":"1006",
    "addr:postcode":"4212",
    "addr:street":"Westfield Shopng Cntr",
    "iso:country":"AU",
    "sg:address":"Shop 1006",
    "sg:city":", Westfield Shopng Cntr Helensvale",
    "sg:classifiers":[
        {
            "category":"Shopping",
            "subcategory":"Mobile Phones",
            "type":"Retail Goods"
        }
    ],
    "sg:phone":"+61 7 5500 0264",
    "sg:postcode":"4212",
    "sg:province":"QLD",
    "sg:tags":[
        "telephone",
        "accessory"
    ],
    "wof:name":"Optus World",
    "wof:placetype":"venue"
},
  "geometry": {"coordinates":[153.376190186,-27.8801403046],"type":"Point"}
}