{
  "type": "Feature",
  "properties": {
    "addr:full":"30 Murray St Swansea NSW 2281",
    "addr:housenumber":"30",
    "addr:postcode":"2281",
    "addr:street":"Murray St",
    "iso:country":"AU",
    "sg:address":"30 Murray St",
    "sg:city":"Swansea",
    "sg:classifiers":[
        {
            "category":"Retail",
            "subcategory":"Laundry & Dry Cleaning",
            "type":"Services"
        }
    ],
    "sg:phone":"+61 409 365 479",
    "sg:postcode":"2281",
    "sg:province":"NSW",
    "sg:tags":[
        "manicurist"
    ],
    "wof:name":"Naomis Mobile Skin & Body",
    "wof:placetype":"venue"
},
  "geometry": {"coordinates":[151.634475708,-33.0939598083],"type":"Point"}
}