{
  "type": "Feature",
  "properties": {
    "addr:full":"13 Kyamba Crt Bayswater North VIC 3153",
    "addr:housenumber":"13",
    "addr:postcode":"3153",
    "addr:street":"Kyamba Crt",
    "iso:country":"AU",
    "sg:address":"13 Kyamba Crt",
    "sg:city":"Bayswater North",
    "sg:classifiers":[
        {
            "category":"Social Services",
            "subcategory":"Retirement Home",
            "type":"Services"
        }
    ],
    "sg:phone":"+61 3 8711 3454",
    "sg:postcode":"3153",
    "sg:province":"VIC",
    "sg:tags":[
        "environmental",
        "consultant",
        "pollution"
    ],
    "wof:name":"Biosphere Pty Ltd",
    "wof:placetype":"venue"
},
  "geometry": {"coordinates":[145.27268981899999,-37.8192634583],"type":"Point"}
}