{
  "type": "Feature",
  "properties": {
    "iso:country":"AU",
    "sg:address":"176 Leach Hwy",
    "sg:city":"Melville",
    "sg:classifiers":[
        {
            "category":"Autos & Motor Vehicles",
            "subcategory":"Automobile Sales",
            "type":"Retail Goods"
        }
    ],
    "sg:phone":"+61 8 9330 4900",
    "sg:postcode":"6156",
    "sg:province":"WA",
    "sg:tags":[
        "car",
        "new"
    ],
    "wof:name":"Melville Subaru",
    "wof:placetype":"venue"
},
  "geometry": {"coordinates":[115.812012,-32.046455],"type":"Point"}
}