{
  "type": "Feature",
  "properties": {
    "addr:full":"10 McIntosh St Airport West VIC 3042",
    "addr:housenumber":"10",
    "addr:postcode":"3042",
    "addr:street":"Mcintosh St",
    "iso:country":"AU",
    "sg:address":"10 McIntosh St",
    "sg:city":"Airport West",
    "sg:classifiers":[
        {
            "category":"Manufacturing",
            "subcategory":"Rubber & Plastics",
            "type":"Manufacturing & Wholesale Goods"
        }
    ],
    "sg:phone":"+61 3 9310 4188",
    "sg:postcode":"3042",
    "sg:province":"VIC",
    "sg:tags":[
        "fabricator"
    ],
    "wof:name":"Ridgeway P.C. & Co Pty Ltd",
    "wof:placetype":"venue"
},
  "geometry": {"coordinates":[144.890335083,-37.7211914062],"type":"Point"}
}