{
  "type": "Feature",
  "properties": {
    "iso:country":"AU",
    "sg:address":"1 Havelock Ave",
    "sg:city":"Coogee",
    "sg:classifiers":[
        {
            "category":"Personal",
            "subcategory":"Massage",
            "type":"Services"
        }
    ],
    "sg:phone":"+61 2 9664 4400",
    "sg:postcode":"2034",
    "sg:province":"NSW",
    "sg:tags":[
        "therapy"
    ],
    "wof:name":"Massage By The Sea",
    "wof:placetype":"venue"
},
  "geometry": {"coordinates":[151.254928589,-33.9242324829],"type":"Point"}
}