{
  "type": "Feature",
  "properties": {
    "addr:full":"1131 Childers Hwy Bundaberg QLD 4670",
    "addr:housenumber":"1131",
    "addr:postcode":"4670",
    "addr:street":"Childers Hwy",
    "iso:country":"AU",
    "sg:address":"1131 Childers Hwy",
    "sg:city":"Bundaberg",
    "sg:classifiers":[
        {
            "category":"Professional",
            "subcategory":"Engineering",
            "type":"Services"
        }
    ],
    "sg:phone":"+61 7 4155 1600",
    "sg:postcode":"4670",
    "sg:province":"QLD",
    "sg:tags":[
        "building",
        "prefabricated",
        "transportable",
        "industrial",
        "commercial"
    ],
    "wof:name":"Farmshed",
    "wof:placetype":"venue"
},
  "geometry": {"coordinates":[152.31675720199999,-24.8927383423],"type":"Point"}
}