{
  "type": "Feature",
  "properties": {
    "addr:full":"PO Box 347 North Adelaide SA 5006",
    "addr:postcode":"5006",
    "iso:country":"AU",
    "sg:address":"PO Box 347",
    "sg:city":"North Adelaide",
    "sg:classifiers":[
        {
            "category":"Education",
            "subcategory":"Special Training",
            "type":"Public Place"
        }
    ],
    "sg:phone":"+61 8 8239 2323",
    "sg:postcode":"5006",
    "sg:province":"SA",
    "sg:tags":[
        "development"
    ],
    "wof:name":"Enterprising Partnerships Pty Ltd",
    "wof:placetype":"venue"
},
  "geometry": {"coordinates":[138.59492492699999,-34.9090194702],"type":"Point"}
}