{
  "type": "Feature",
  "properties": {
    "addr:full":"Suite 6 Bluff Rd Black Rock VIC 3193",
    "addr:postcode":"3193",
    "addr:street":"Bluff Rd",
    "iso:country":"AU",
    "sg:address":"Suite 6 Bluff Rd",
    "sg:city":"Black Rock",
    "sg:classifiers":[
        {
            "category":"Real Estate",
            "subcategory":"Architect",
            "type":"Services"
        }
    ],
    "sg:phone":"+61 3 9533 5399",
    "sg:postcode":"3193",
    "sg:province":"VIC",
    "wof:name":"Cosentino Tony Architects",
    "wof:placetype":"venue"
},
  "geometry": {"coordinates":[145.01643371599999,-37.9752197266],"type":"Point"}
}