{
  "type": "Feature",
  "properties": {
    "addr:full":"6/ 22 Somerton Rd Somerton VIC 3062",
    "addr:housenumber":"/ 22",
    "addr:postcode":"3062",
    "addr:street":"Somerton Rd",
    "iso:country":"AU",
    "sg:address":"6/ 22 Somerton Rd",
    "sg:city":"Somerton",
    "sg:classifiers":[
        {
            "category":"Professional",
            "subcategory":"Detective & Security Services",
            "type":"Services"
        }
    ],
    "sg:phone":"+61 3 9308 6366",
    "sg:postcode":"3062",
    "sg:province":"VIC",
    "sg:tags":[
        "equipment",
        "window",
        "doors"
    ],
    "wof:name":"AAA Somerton Windows",
    "wof:placetype":"venue"
},
  "geometry": {"coordinates":[144.94842529300001,-37.6428833008],"type":"Point"}
}