{
  "type": "Feature",
  "properties": {
    "addr:full":"6 Klingner Rd Redcliffe QLD 4020",
    "addr:housenumber":"6",
    "addr:postcode":"4020",
    "addr:street":"Klingner Rd",
    "iso:country":"AU",
    "sg:address":"6 Klingner Rd",
    "sg:city":"Redcliffe",
    "sg:classifiers":[
        {
            "category":"Health Services",
            "subcategory":"Dentist",
            "type":"Services"
        }
    ],
    "sg:phone":"+61 7 3883 1542",
    "sg:postcode":"4020",
    "sg:province":"QLD",
    "sg:tags":[
        "dental",
        "prosthetist"
    ],
    "wof:name":"Bayside Denture Clinic",
    "wof:placetype":"venue"
},
  "geometry": {"coordinates":[153.11416600000001,-27.222979],"type":"Point"}
}