{
  "type": "Feature",
  "properties": {
    "addr:full":"457 Nepean Hwy Frankston VIC 3199",
    "addr:housenumber":"457",
    "addr:postcode":"3199",
    "addr:street":"Nepean Hwy",
    "iso:country":"AU",
    "sg:address":"457 Nepean Hwy",
    "sg:city":"Frankston",
    "sg:classifiers":[
        {
            "category":"Food & Beverages",
            "subcategory":"Supermarket",
            "type":"Retail Goods"
        }
    ],
    "sg:phone":"+61 3 9770 1077",
    "sg:postcode":"3199",
    "sg:province":"VIC",
    "sg:tags":[
        "grocery",
        "store"
    ],
    "wof:name":"Ritchies Stores Pty Ltd",
    "wof:placetype":"venue"
},
  "geometry": {"coordinates":[145.009841919,-37.9072036743],"type":"Point"}
}