{
  "type": "Feature",
  "properties": {
    "addr:full":"Roadside Mail Box 724 Waroona WA 6215",
    "addr:postcode":"6215",
    "iso:country":"AU",
    "sg:address":"Roadside Mail Box 724",
    "sg:city":"Waroona",
    "sg:classifiers":[
        {
            "category":"Building & Trades",
            "subcategory":"Landscaping Services",
            "type":"Services"
        }
    ],
    "sg:phone":"+61 8 9733 1456",
    "sg:postcode":"6215",
    "sg:province":"WA",
    "sg:tags":[
        "grazier"
    ],
    "wof:name":"Yundapharma",
    "wof:placetype":"venue"
},
  "geometry": {"coordinates":[115.92150100000001,-32.842999],"type":"Point"}
}