{
  "type": "Feature",
  "properties": {
    "addr:full":"Shop 51 Waverley Gardens Shopping Cntr Mulgrave VIC 3170",
    "addr:housenumber":"shop 51",
    "addr:postcode":"3170",
    "addr:street":"Waverley Gardens Shopping Cntr",
    "iso:country":"AU",
    "sg:address":"Shop 51",
    "sg:city":"Waverley Gardens Shopping Cntr Mulgrave",
    "sg:classifiers":[
        {
            "category":"Food & Beverages",
            "subcategory":"Specialty",
            "type":"Retail Goods"
        }
    ],
    "sg:phone":"+61 3 9547 7285",
    "sg:postcode":"3170",
    "sg:province":"VIC",
    "sg:tags":[
        "product",
        "health"
    ],
    "wof:name":"Absolute Health",
    "wof:placetype":"venue"
},
  "geometry": {"coordinates":[145.122116089,-37.8839378357],"type":"Point"}
}