{
  "type": "Feature",
  "properties": {
    "addr:full":"7 Kappella St Kippa-Ring QLD 4021",
    "addr:housenumber":"7",
    "addr:postcode":"4021",
    "addr:street":"Kappella St",
    "iso:country":"AU",
    "sg:address":"7 Kappella St",
    "sg:city":"Kippa-Ring",
    "sg:classifiers":[
        {
            "category":"Education",
            "subcategory":"Kindergarten",
            "type":"Public Place"
        }
    ],
    "sg:phone":"+61 7 3284 8124",
    "sg:postcode":"4021",
    "sg:province":"QLD",
    "sg:tags":[
        "pre-schools"
    ],
    "wof:name":"C&K Kippa-Ring Community Kindergarten & Preschool",
    "wof:placetype":"venue"
},
  "geometry": {"coordinates":[153.08818099999999,-27.229143],"type":"Point"}
}