{
  "type": "Feature",
  "properties": {
    "addr:full":"16 New South Wales Cres Forrest ACT 2603",
    "addr:housenumber":"16",
    "addr:postcode":"2603",
    "addr:street":"Cres",
    "iso:country":"AU",
    "sg:address":"16 New South Wales Cres",
    "sg:city":"Forrest",
    "sg:classifiers":[
        {
            "category":"Travel",
            "subcategory":"Hotels & Motels",
            "type":"Entertainment"
        }
    ],
    "sg:phone":"+61 2 6295 3722",
    "sg:postcode":"2603",
    "sg:province":"ACT",
    "sg:website":"http://www.telopeainn.com.au",
    "wof:name":"Telopea Inn On The Park",
    "wof:placetype":"venue"
},
  "geometry": {"coordinates":[149.13481140100001,-35.3158226013],"type":"Point"}
}