{
  "type": "Feature",
  "properties": {
    "addr:full":"2/ 5 Babdoyle St Loganholme QLD 4129",
    "addr:housenumber":"/ 5",
    "addr:postcode":"4129",
    "addr:street":"Babdoyle St",
    "iso:country":"AU",
    "sg:address":"2/ 5 Babdoyle St",
    "sg:city":"Loganholme",
    "sg:classifiers":[
        {
            "category":"Professional",
            "subcategory":"Detective & Security Services",
            "type":"Services"
        }
    ],
    "sg:phone":"+61 7 3209 9896",
    "sg:postcode":"4129",
    "sg:province":"QLD",
    "sg:tags":[
        "equipment",
        "window",
        "doors"
    ],
    "wof:name":"Brisbane Blinds & Screens",
    "wof:placetype":"venue"
},
  "geometry": {"coordinates":[153.19073486299999,-27.6808261871],"type":"Point"}
}