{
  "type": "Feature",
  "properties": {
    "addr:full":"12 Dublin St Port Lincoln SA 5606",
    "addr:housenumber":"12",
    "addr:postcode":"5606",
    "addr:street":"Dublin St",
    "iso:country":"AU",
    "sg:address":"12 Dublin St",
    "sg:city":"Port Lincoln",
    "sg:classifiers":[
        {
            "category":"Real Estate",
            "subcategory":"Architect",
            "type":"Services"
        }
    ],
    "sg:phone":"+61 8 8683 3355",
    "sg:postcode":"5606",
    "sg:province":"SA",
    "sg:tags":[
        "building",
        "designer"
    ],
    "wof:name":"Penna Planning & Design",
    "wof:placetype":"venue"
},
  "geometry": {"coordinates":[135.864105,-34.734077],"type":"Point"}
}