{
  "type": "Feature",
  "properties": {
    "addr:full":"68 Centenary Drv Mill Park VIC 3082",
    "addr:housenumber":"68",
    "addr:postcode":"3082",
    "addr:street":"Centenary Drv",
    "iso:country":"AU",
    "sg:address":"68 Centenary Drv",
    "sg:city":"Mill Park",
    "sg:classifiers":[
        {
            "category":"Education",
            "subcategory":"Kindergarten",
            "type":"Public Place"
        }
    ],
    "sg:phone":"+61 3 9436 7671",
    "sg:postcode":"3082",
    "sg:province":"VIC",
    "sg:tags":[
        "pre-schools"
    ],
    "wof:name":"Centenary Drive Kindergarten",
    "wof:placetype":"venue"
},
  "geometry": {"coordinates":[145.06724548299999,-37.6585655212],"type":"Point"}
}