{
  "type": "Feature",
  "properties": {
    "addr:full":"57 Edward St Brisbane QLD 4000",
    "addr:housenumber":"57",
    "addr:postcode":"4000",
    "addr:street":"Edward St",
    "iso:country":"AU",
    "sg:address":"57 Edward St",
    "sg:city":"Brisbane",
    "sg:classifiers":[
        {
            "category":"Shopping",
            "subcategory":"Optical Goods",
            "type":"Retail Goods"
        }
    ],
    "sg:phone":"+61 7 3221 5299",
    "sg:postcode":"4000",
    "sg:province":"QLD",
    "sg:tags":[
        "dispenser",
        "prescription"
    ],
    "wof:name":"Eyes On Edward",
    "wof:placetype":"venue"
},
  "geometry": {"coordinates":[153.029693603,-27.4709510803],"type":"Point"}
}