{
  "type": "Feature",
  "properties": {
    "addr:full":"PO Box 175 Pascoe Vale South VIC 3044",
    "addr:postcode":"3044",
    "iso:country":"AU",
    "sg:address":"PO Box 175",
    "sg:city":"Pascoe Vale South",
    "sg:classifiers":[
        {
            "category":"Organizations",
            "subcategory":"Non-profit Organization",
            "type":"Services"
        }
    ],
    "sg:phone":"+61 3 9354 3337",
    "sg:postcode":"3044",
    "sg:province":"VIC",
    "sg:tags":[
        "support",
        "disability",
        "organisation"
    ],
    "wof:name":"Carinya Society",
    "wof:placetype":"venue"
},
  "geometry": {"coordinates":[144.93988037099999,-37.7414398193],"type":"Point"}
}