{
  "type": "Feature",
  "properties": {
    "iso:country":"AU",
    "sg:address":"175 Boundary Rd",
    "sg:city":"Narre Warren North",
    "sg:classifiers":[
        {
            "category":"Utilities",
            "subcategory":"Electric",
            "type":"Services"
        }
    ],
    "sg:phone":"+61 3 8790 4584",
    "sg:postcode":"3804",
    "sg:province":"VIC",
    "sg:tags":[
        "electrical",
        "contractor"
    ],
    "wof:name":"W H Electrics (Vic) Pty Ltd",
    "wof:placetype":"venue"
},
  "geometry": {"coordinates":[145.34754943900001,-37.9700813293],"type":"Point"}
}