{
  "type": "Feature",
  "properties": {
    "addr:full":"Recycle Park 13 Vernon Smith Crt Ottoway SA 5013",
    "addr:housenumber":"13",
    "addr:postcode":"5013",
    "addr:street":"Vernon Smith Crt",
    "iso:country":"AU",
    "sg:address":"Recycle Park 13 Vernon Smith Crt",
    "sg:city":"Ottoway",
    "sg:classifiers":[
        {
            "category":"Building & Trades",
            "subcategory":"Construction",
            "type":"Services"
        }
    ],
    "sg:phone":"+61 8 8341 0288",
    "sg:postcode":"5013",
    "sg:province":"SA",
    "sg:tags":[
        "welding"
    ],
    "wof:name":"B & G Fabricators",
    "wof:placetype":"venue"
},
  "geometry": {"coordinates":[138.541946411,-34.8501434326],"type":"Point"}
}