{
  "type": "Feature",
  "properties": {
    "iso:country":"AU",
    "sg:address":"Unit 2, 1 Tucks Rd",
    "sg:city":"Seven Hills",
    "sg:classifiers":[
        {
            "category":"Home & Garden",
            "subcategory":"Furniture",
            "type":"Retail Goods"
        }
    ],
    "sg:phone":"+61 2 9674 6888",
    "sg:postcode":"2147",
    "sg:province":"NSW",
    "sg:tags":[
        "business"
    ],
    "wof:name":"Minicost Office Furniture by McEnnally",
    "wof:placetype":"venue"
},
  "geometry": {"coordinates":[150.95559692399999,-33.776096344],"type":"Point"}
}