{
  "type": "Feature",
  "properties": {
    "addr:full":"910 North Rd Bentleigh East VIC 3165",
    "addr:housenumber":"910",
    "addr:postcode":"3165",
    "addr:street":"North Rd",
    "iso:country":"AU",
    "sg:address":"910 North Rd",
    "sg:city":"Bentleigh East",
    "sg:classifiers":[
        {
            "category":"Utilities",
            "subcategory":"Mobile Phone",
            "type":"Services"
        }
    ],
    "sg:phone":"+61 3 9563 7333",
    "sg:postcode":"3165",
    "sg:province":"VIC",
    "sg:tags":[
        "repair",
        "telephone"
    ],
    "wof:name":"Comm Clinic",
    "wof:placetype":"venue"
},
  "geometry": {"coordinates":[145.06135559099999,-37.906703949],"type":"Point"}
}