{
  "type": "Feature",
  "properties": {
    "addr:full":"Lamont St Bermagui NSW 2546",
    "addr:postcode":"2546",
    "addr:street":"Lamont St",
    "iso:country":"AU",
    "sg:address":"Lamont St",
    "sg:city":"Bermagui",
    "sg:classifiers":[
        {
            "category":"Wholesale",
            "subcategory":"Seafood",
            "type":"Manufacturing & Wholesale Goods"
        }
    ],
    "sg:phone":"+61 2 6493 4239",
    "sg:postcode":"2546",
    "sg:province":"NSW",
    "sg:tags":[
        "fish"
    ],
    "wof:name":"Bermagui Seafood Supplies",
    "wof:placetype":"venue"
},
  "geometry": {"coordinates":[150.076904297,-36.4270820618],"type":"Point"}
}