{
  "type": "Feature",
  "properties": {
    "addr:full":"English Rd Elimbah QLD 4516",
    "addr:postcode":"4516",
    "addr:street":"English Rd",
    "iso:country":"AU",
    "sg:address":"English Rd",
    "sg:city":"Elimbah",
    "sg:classifiers":[
        {
            "category":"Organizations",
            "subcategory":"Professional Association",
            "type":"Services"
        }
    ],
    "sg:phone":"+61 7 5496 7637",
    "sg:postcode":"4516",
    "sg:province":"QLD",
    "sg:tags":[
        "rural",
        "organisation",
        "production",
        "primary"
    ],
    "wof:name":"Elimbah Fruitgrowers Co-Op Association Ltd",
    "wof:placetype":"venue"
},
  "geometry": {"coordinates":[152.944321,-27.011499],"type":"Point"}
}