{
  "type": "Feature",
  "properties": {
    "iso:country":"AU",
    "sg:address":"7749 Channel Hwy",
    "sg:city":"Cygnet",
    "sg:classifiers":[
        {
            "category":"Professional",
            "subcategory":"Computer Services",
            "type":"Services"
        }
    ],
    "sg:phone":"+61 417 590 561",
    "sg:postcode":"7112",
    "sg:province":"TAS",
    "sg:tags":[
        "package",
        "software"
    ],
    "wof:name":"Whitchurch Consulting",
    "wof:placetype":"venue"
},
  "geometry": {"coordinates":[147.06411743199999,-43.143901825],"type":"Point"}
}