{
  "type": "Feature",
  "properties": {
    "addr:full":"44 Queens St Busselton WA 6280",
    "addr:housenumber":"44",
    "addr:postcode":"6280",
    "addr:street":"Queens St",
    "iso:country":"AU",
    "sg:address":"44 Queens St",
    "sg:city":"Busselton",
    "sg:classifiers":[
        {
            "category":"Food & Beverages",
            "subcategory":"Supermarket",
            "type":"Retail Goods"
        }
    ],
    "sg:phone":"+61 8 9751 2666",
    "sg:postcode":"6280",
    "sg:province":"WA",
    "sg:tags":[
        "grocery",
        "store"
    ],
    "wof:name":"Woolworths (WA) Pty Ltd",
    "wof:placetype":"venue"
},
  "geometry": {"coordinates":[115.343788147,-33.6470375061],"type":"Point"}
}