{
  "type": "Feature",
  "properties": {
    "addr:full":"91 Woods St Donald VIC 3480",
    "addr:housenumber":"91",
    "addr:postcode":"3480",
    "addr:street":"Woods St",
    "iso:country":"AU",
    "sg:address":"91 Woods St",
    "sg:city":"Donald",
    "sg:classifiers":[
        {
            "category":"Autos & Motor Vehicles",
            "subcategory":"Auto Supplies",
            "type":"Retail Goods"
        }
    ],
    "sg:phone":"+61 3 5497 1591",
    "sg:postcode":"3480",
    "sg:province":"VIC",
    "sg:tags":[
        "battery",
        "automotive"
    ],
    "wof:name":"Beaurepaires",
    "wof:placetype":"venue"
},
  "geometry": {"coordinates":[142.98405456500001,-36.3719482422],"type":"Point"}
}