{
  "type": "Feature",
  "properties": {
    "addr:full":"Shop 9/ 160 Racecourse Rd Ascot QLD 4007",
    "addr:housenumber":"shop 9 / 160",
    "addr:postcode":"4007",
    "addr:street":"Racecourse Rd",
    "iso:country":"AU",
    "sg:address":"Shop 9/ 160 Racecourse Rd",
    "sg:city":"Ascot",
    "sg:classifiers":[
        {
            "category":"Real Estate",
            "subcategory":"Real Estate Agent",
            "type":"Services"
        }
    ],
    "sg:phone":"+61 7 3868 1888",
    "sg:postcode":"4007",
    "sg:province":"QLD",
    "wof:name":"RE / MAX Results",
    "wof:placetype":"venue"
},
  "geometry": {"coordinates":[153.06527700000001,-27.432259],"type":"Point"}
}