{
  "type": "Feature",
  "properties": {
    "addr:full":"160 Montgomery St Lake Bolac VIC 3351",
    "addr:housenumber":"160",
    "addr:postcode":"3351",
    "addr:street":"Montgomery St",
    "iso:country":"AU",
    "sg:address":"160 Montgomery St",
    "sg:city":"Lake Bolac",
    "sg:classifiers":[
        {
            "category":"Farming",
            "subcategory":"Farm & Veterinary Services",
            "type":"Manufacturing & Wholesale Goods"
        }
    ],
    "sg:phone":"+61 429 998 375",
    "sg:postcode":"3351",
    "sg:province":"VIC",
    "sg:tags":[
        "shearing",
        "contractor"
    ],
    "wof:name":"Possum Gully Shearing Co Pty Ltd",
    "wof:placetype":"venue"
},
  "geometry": {"coordinates":[142.83955399999999,-37.714275],"type":"Point"}
}