{
  "type": "Feature",
  "properties": {
    "addr:full":"37 Emery Crs Queanbeyan ACT 2620",
    "addr:housenumber":"37",
    "addr:postcode":"2620",
    "addr:street":"Emery Crs",
    "iso:country":"AU",
    "sg:address":"37 Emery Crs",
    "sg:city":"Queanbeyan",
    "sg:classifiers":[
        {
            "category":"Education",
            "subcategory":"Special Training",
            "type":"Public Place"
        }
    ],
    "sg:phone":"+61 2 6299 7686",
    "sg:postcode":"2620",
    "sg:province":"ACT",
    "sg:tags":[
        "tuition-educational"
    ],
    "wof:name":"Litracy Skills",
    "wof:placetype":"venue"
},
  "geometry": {"coordinates":[149.046386719,-35.3591308594],"type":"Point"}
}