{
  "type": "Feature",
  "properties": {
    "iso:country":"AU",
    "sg:address":"17 Parkes Rd",
    "sg:city":"Collaroy",
    "sg:classifiers":[
        {
            "category":"Personal",
            "type":"Services"
        }
    ],
    "sg:phone":"+61 2 9971 6184",
    "sg:postcode":"2097",
    "sg:province":"NSW",
    "sg:tags":[
        "dressmaker"
    ],
    "wof:name":"Hannagan Y",
    "wof:placetype":"venue"
},
  "geometry": {"coordinates":[151.290740967,-33.7398719788],"type":"Point"}
}