{
  "type": "Feature",
  "properties": {
    "addr:full":"10 Northview St Mermaid Waters QLD 4218",
    "addr:housenumber":"10",
    "addr:postcode":"4218",
    "addr:street":"Northview St",
    "iso:country":"AU",
    "sg:address":"10 Northview St",
    "sg:city":"Mermaid Waters",
    "sg:classifiers":[
        {
            "category":"Retail",
            "subcategory":"Auto Repair",
            "type":"Services"
        }
    ],
    "sg:phone":"+61 7 5554 6664",
    "sg:postcode":"4218",
    "sg:province":"QLD",
    "sg:tags":[
        "gas",
        "conversion",
        "natural",
        "lp",
        "vehicle"
    ],
    "wof:name":"Fuel Solutions Australia",
    "wof:placetype":"venue"
},
  "geometry": {"coordinates":[153.43197631800001,-28.0402698517],"type":"Point"}
}