{
  "type": "Feature",
  "properties": {
    "addr:full":"109 Melbourne St South Brisbane QLD 4101",
    "addr:housenumber":"109",
    "addr:postcode":"4101",
    "addr:street":"Melbourne St",
    "iso:country":"AU",
    "sg:address":"109 Melbourne St",
    "sg:city":"South Brisbane",
    "sg:classifiers":[
        {
            "category":"Professional",
            "type":"Services"
        }
    ],
    "sg:phone":"+61 7 3840 5503",
    "sg:postcode":"4101",
    "sg:province":"QLD",
    "sg:tags":[
        "auctioneer"
    ],
    "wof:name":"Primac Elders Limited",
    "wof:placetype":"venue"
},
  "geometry": {"coordinates":[153.01739501899999,-27.4743480682],"type":"Point"}
}