{
  "type": "Feature",
  "properties": {
    "addr:full":"292 Myola Rd Toolleen VIC 3551",
    "addr:housenumber":"292",
    "addr:postcode":"3551",
    "addr:street":"Myola Rd",
    "iso:country":"AU",
    "sg:address":"292 Myola Rd",
    "sg:city":"Toolleen",
    "sg:classifiers":[
        {
            "category":"Farming",
            "subcategory":"Livestock Farm",
            "type":"Manufacturing & Wholesale Goods"
        }
    ],
    "sg:phone":"+61 3 5433 6243",
    "sg:postcode":"3551",
    "sg:province":"VIC",
    "sg:tags":[
        "breeder",
        "horse",
        "stud"
    ],
    "wof:name":"Hamblin B J",
    "wof:placetype":"venue"
},
  "geometry": {"coordinates":[144.71890258799999,-36.6489982605],"type":"Point"}
}