{
  "type": "Feature",
  "properties": {
    "addr:full":"1 Acheson Pl Coburg North VIC 3058",
    "addr:housenumber":"1",
    "addr:postcode":"3058",
    "addr:street":"Acheson Pl",
    "iso:country":"AU",
    "sg:address":"1 Acheson Pl",
    "sg:city":"Coburg North",
    "sg:classifiers":[
        {
            "category":"Wholesale",
            "subcategory":"Machinery & Supplies",
            "type":"Manufacturing & Wholesale Goods"
        }
    ],
    "sg:phone":"+61 3 9354 9911",
    "sg:postcode":"3058",
    "sg:province":"VIC",
    "sg:tags":[
        "equipment",
        "welding"
    ],
    "wof:name":"Gasgep Industries Pty Ltd",
    "wof:placetype":"venue"
},
  "geometry": {"coordinates":[144.97308349599999,-37.727306366],"type":"Point"}
}