{
  "type": "Feature",
  "properties": {
    "iso:country":"AU",
    "sg:address":"177 Cathedral St",
    "sg:city":"Perth",
    "sg:classifiers":[
        {
            "category":"Food & Beverages",
            "subcategory":"Liquor & Beverages",
            "type":"Retail Goods"
        }
    ],
    "sg:phone":"+61 1300 723 723",
    "sg:postcode":"6000",
    "sg:province":"WA",
    "sg:tags":[
        "merchant",
        "spirit",
        "wine"
    ],
    "wof:name":"The Wine Society",
    "wof:placetype":"venue"
},
  "geometry": {"coordinates":[115.86076355,-31.9556503296],"type":"Point"}
}