{
  "type": "Feature",
  "properties": {
    "iso:country":"AU",
    "sg:address":"25 Church La",
    "sg:city":"Cranebrook",
    "sg:classifiers":[
        {
            "category":"Building & Trades",
            "subcategory":"Cleaning & Sanitation",
            "type":"Services"
        }
    ],
    "sg:phone":"+61 405 209 991",
    "sg:postcode":"2749",
    "sg:province":"NSW",
    "sg:tags":[
        "chemical",
        "pressure",
        "steam",
        "contractor"
    ],
    "wof:name":"Driveway Lovers",
    "wof:placetype":"venue"
},
  "geometry": {"coordinates":[150.69796752900001,-33.6994972229],"type":"Point"}
}