{
  "type": "Feature",
  "properties": {
    "addr:full":"13/ 364 Bilsen Rd Geebung QLD 4034",
    "addr:housenumber":"13 / 364",
    "addr:postcode":"4034",
    "addr:street":"Bilsen Rd",
    "iso:country":"AU",
    "sg:address":"13/ 364 Bilsen Rd",
    "sg:city":"Geebung",
    "sg:classifiers":[
        {
            "category":"Wholesale",
            "subcategory":"Construction Materials",
            "type":"Manufacturing & Wholesale Goods"
        }
    ],
    "sg:phone":"+61 7 3865 2714",
    "sg:postcode":"4034",
    "sg:province":"QLD",
    "sg:tags":[
        "protective",
        "coating"
    ],
    "wof:name":"A.V.G. Powder Coating",
    "wof:placetype":"venue"
},
  "geometry": {"coordinates":[153.055328,-27.374023],"type":"Point"}
}