{
  "type": "Feature",
  "properties": {
    "addr:full":"43 Padstow Pde Padstow NSW 2211",
    "addr:housenumber":"43",
    "addr:postcode":"2211",
    "addr:street":"Padstow Pde",
    "iso:country":"AU",
    "sg:address":"43 Padstow Pde",
    "sg:city":"Padstow",
    "sg:classifiers":[
        {
            "category":"Food & Beverages",
            "subcategory":"Bakery",
            "type":"Retail Goods"
        }
    ],
    "sg:phone":"+61 2 9773 9788",
    "sg:postcode":"2211",
    "sg:province":"NSW",
    "sg:tags":[
        "cake",
        "shop",
        "pastry"
    ],
    "wof:name":"Cake It Away",
    "wof:placetype":"venue"
},
  "geometry": {"coordinates":[151.033005,-33.953362],"type":"Point"}
}