{
  "type": "Feature",
  "properties": {
    "addr:full":"3 Lawson St Malabar NSW 2036",
    "addr:housenumber":"3",
    "addr:postcode":"2036",
    "addr:street":"Lawson St",
    "iso:country":"AU",
    "sg:address":"3 Lawson St",
    "sg:city":"Malabar",
    "sg:classifiers":[
        {
            "category":"Food & Beverages",
            "subcategory":"Liquor & Beverages",
            "type":"Retail Goods"
        }
    ],
    "sg:phone":"+61 2 9661 4184",
    "sg:postcode":"2036",
    "sg:province":"NSW",
    "sg:tags":[
        "store"
    ],
    "wof:name":"Discount Liquor & Tobacconist Malabar",
    "wof:placetype":"venue"
},
  "geometry": {"coordinates":[151.24085998499999,-33.957244873],"type":"Point"}
}