{
  "type": "Feature",
  "properties": {
    "addr:full":"30 Bottlebrush St Thurgoona NSW 2640",
    "addr:housenumber":"30",
    "addr:postcode":"2640",
    "addr:street":"Bottlebrush St",
    "iso:country":"AU",
    "sg:address":"30 Bottlebrush St",
    "sg:city":"Thurgoona",
    "sg:classifiers":[
        {
            "category":"Organizations",
            "subcategory":"Non-profit Organization",
            "type":"Services"
        }
    ],
    "sg:phone":"+61 2 6043 1001",
    "sg:postcode":"2640",
    "sg:province":"NSW",
    "sg:tags":[
        "support",
        "disability",
        "organisation"
    ],
    "wof:name":"Mother Of God Brothers",
    "wof:placetype":"venue"
},
  "geometry": {"coordinates":[146.98309326200001,-36.0485305786],"type":"Point"}
}