{
  "type": "Feature",
  "properties": {
    "addr:full":"16 Craig St Mundaring WA 6073",
    "addr:housenumber":"16",
    "addr:postcode":"6073",
    "addr:street":"Craig St",
    "iso:country":"AU",
    "sg:address":"16 Craig St",
    "sg:city":"Mundaring",
    "sg:classifiers":[
        {
            "category":"Health Services",
            "subcategory":"Health Practitioner",
            "type":"Services"
        }
    ],
    "sg:phone":"+61 8 9295 1223",
    "sg:postcode":"6073",
    "sg:province":"WA",
    "sg:tags":[
        "bowen",
        "therapy"
    ],
    "wof:name":"Norma D Logan",
    "wof:placetype":"venue"
},
  "geometry": {"coordinates":[116.168800354,-31.9035835266],"type":"Point"}
}