{
  "type": "Feature",
  "properties": {
    "addr:full":"147 York St Forbes NSW 2871",
    "addr:housenumber":"147",
    "addr:postcode":"2871",
    "addr:street":"York St",
    "iso:country":"AU",
    "sg:address":"147 York St",
    "sg:city":"Forbes",
    "sg:classifiers":[
        {
            "category":"Manufacturing",
            "subcategory":"Food",
            "type":"Manufacturing & Wholesale Goods"
        }
    ],
    "sg:phone":"+61 2 6852 4201",
    "sg:postcode":"2871",
    "sg:province":"NSW",
    "sg:tags":[
        "function",
        "catering"
    ],
    "wof:name":"All-U-Want Party Hire",
    "wof:placetype":"venue"
},
  "geometry": {"coordinates":[147.997559,-33.38047],"type":"Point"}
}