{
  "type": "Feature",
  "properties": {
    "addr:full":"Shop 36 Cnr Central Ave & Boat Harbour Drv Hervey Bay QLD 4655",
    "addr:housenumber":"shop 36",
    "addr:postcode":"4655",
    "addr:street":"Cnr Central Ave & Boat Harbour Drv",
    "iso:country":"AU",
    "sg:address":"Shop 36 Cnr Central Ave & Boat Harbour Drv",
    "sg:city":"Hervey Bay",
    "sg:classifiers":[
        {
            "category":"Shopping",
            "subcategory":"Clothing, Apparel, & Fashions",
            "type":"Retail Goods"
        }
    ],
    "sg:phone":"+61 7 4124 3350",
    "sg:postcode":"4655",
    "sg:province":"QLD",
    "sg:tags":[
        "lady",
        "wear"
    ],
    "wof:name":"Suzanne Grae",
    "wof:placetype":"venue"
},
  "geometry": {"coordinates":[152.83442700000001,-25.287815],"type":"Point"}
}