{
  "type": "Feature",
  "properties": {
    "iso:country":"AU",
    "sg:address":"15 Holly Rd",
    "sg:city":"Victoria Point",
    "sg:classifiers":[
        {
            "category":"Autos & Motor Vehicles",
            "subcategory":"Auto Supplies",
            "type":"Retail Goods"
        }
    ],
    "sg:phone":"+61 7 3820 6811",
    "sg:postcode":"4165",
    "sg:province":"QLD",
    "sg:tags":[
        "garage",
        "equipment"
    ],
    "wof:name":"TSR Electronics Pty Ltd",
    "wof:placetype":"venue"
},
  "geometry": {"coordinates":[153.29359435999999,-27.5953025818],"type":"Point"}
}