{
  "type": "Feature",
  "properties": {
    "iso:country":"AU",
    "sg:address":"91 Main Rd",
    "sg:city":"Lower Plenty",
    "sg:classifiers":[
        {
            "category":"Fast Food",
            "type":"Food & Drink"
        }
    ],
    "sg:phone":"+61 3 9435 3285",
    "sg:postcode":"3093",
    "sg:province":"VIC",
    "sg:tags":[
        "away",
        "take"
    ],
    "wof:name":"Lower Plenty Fish Shop",
    "wof:placetype":"venue"
},
  "geometry": {"coordinates":[145.11276245100001,-37.7272338867],"type":"Point"}
}