{
  "type": "Feature",
  "properties": {
    "addr:full":"79 Essex St Wembley WA 6014",
    "addr:housenumber":"79",
    "addr:postcode":"6014",
    "addr:street":"Essex St",
    "iso:country":"AU",
    "sg:address":"79 Essex St",
    "sg:city":"Wembley",
    "sg:classifiers":[
        {
            "category":"Building & Trades",
            "subcategory":"Construction",
            "type":"Services"
        }
    ],
    "sg:phone":"+61 8 9383 9094",
    "sg:postcode":"6014",
    "sg:province":"WA",
    "sg:tags":[
        "roof"
    ],
    "wof:name":"Bower Roof Plumbing",
    "wof:placetype":"venue"
},
  "geometry": {"coordinates":[115.81627655,-31.9350452423],"type":"Point"}
}