{
  "type": "Feature",
  "properties": {
    "addr:full":"14 Christensen Rd Stapylton QLD 4207",
    "addr:housenumber":"14",
    "addr:postcode":"4207",
    "addr:street":"Christensen Rd",
    "iso:country":"AU",
    "sg:address":"14 Christensen Rd",
    "sg:city":"Stapylton",
    "sg:classifiers":[
        {
            "category":"Building & Trades",
            "subcategory":"Construction",
            "type":"Services"
        }
    ],
    "sg:phone":"+61 7 3807 8582",
    "sg:postcode":"4207",
    "sg:province":"QLD",
    "sg:tags":[
        "home",
        "air conditioning"
    ],
    "wof:name":"Q- AirCon & HotWater",
    "wof:placetype":"venue"
},
  "geometry": {"coordinates":[153.23078918499999,-27.7358436584],"type":"Point"}
}