{
  "type": "Feature",
  "properties": {
    "iso:country":"AU",
    "sg:address":"116 Catherine Field Rd",
    "sg:city":"Catherine Field",
    "sg:classifiers":[
        {
            "category":"Home & Garden",
            "subcategory":"Building Materials",
            "type":"Retail Goods"
        }
    ],
    "sg:phone":"+61 418 146 063",
    "sg:postcode":"2171",
    "sg:province":"NSW",
    "sg:tags":[
        "lawn",
        "cutting",
        "maintenance"
    ],
    "wof:name":"Pollards Mowing & Garden Services",
    "wof:placetype":"venue"
},
  "geometry": {"coordinates":[150.846237183,-33.9284286499],"type":"Point"}
}