{
  "type": "Feature",
  "properties": {
    "addr:full":"755 Anzac Pde Maroubra NSW 2035",
    "addr:housenumber":"755",
    "addr:postcode":"2035",
    "addr:street":"Anzac Pde",
    "iso:country":"AU",
    "sg:address":"755 Anzac Pde",
    "sg:city":"Maroubra",
    "sg:classifiers":[
        {
            "category":"Food & Beverages",
            "subcategory":"Groceries & Convenience Stores",
            "type":"Retail Goods"
        }
    ],
    "sg:phone":"+61 2 9344 8598",
    "sg:postcode":"2035",
    "sg:province":"NSW",
    "wof:name":"7 Eleven Food Store",
    "wof:placetype":"venue"
},
  "geometry": {"coordinates":[151.23907470699999,-33.9419517517],"type":"Point"}
}