{
  "type": "Feature",
  "properties": {
    "addr:full":"32 Malabar St East Launceston TAS 7250",
    "addr:housenumber":"32",
    "addr:postcode":"7250",
    "addr:street":"Malabar St East",
    "iso:country":"AU",
    "sg:address":"32 Malabar St",
    "sg:city":"East Launceston",
    "sg:classifiers":[
        {
            "category":"Building & Trades",
            "subcategory":"Construction",
            "type":"Services"
        }
    ],
    "sg:phone":"+61 3 6334 5180",
    "sg:postcode":"7250",
    "sg:province":"TAS",
    "sg:tags":[
        "plasterboard",
        "plasterer",
        "fixer"
    ],
    "wof:name":"Paul Williams",
    "wof:placetype":"venue"
},
  "geometry": {"coordinates":[147.15419006400001,-41.4415512085],"type":"Point"}
}