{
  "type": "Feature",
  "properties": {
    "addr:full":"380 Bruce Crs Warnervale NSW 2259",
    "addr:housenumber":"380",
    "addr:postcode":"2259",
    "addr:street":"Bruce Crs",
    "iso:country":"AU",
    "sg:address":"380 Bruce Crs",
    "sg:city":"Warnervale",
    "sg:classifiers":[
        {
            "category":"Home & Garden",
            "subcategory":"Carpets & Floor Coverings",
            "type":"Retail Goods"
        }
    ],
    "sg:phone":"+61 409 986 239",
    "sg:postcode":"2259",
    "sg:province":"NSW",
    "sg:tags":[
        "tile",
        "wall",
        "layer"
    ],
    "wof:name":"Vince Albanese Floor & Wall Tiling",
    "wof:placetype":"venue"
},
  "geometry": {"coordinates":[151.423217773,-33.2335090637],"type":"Point"}
}