{
  "type": "Feature",
  "properties": {
    "addr:full":"PO Box 2001 Hampton East VIC 3188",
    "addr:postcode":"3188",
    "iso:country":"AU",
    "sg:address":"PO Box 2001",
    "sg:city":"Hampton East",
    "sg:classifiers":[
        {
            "category":"Arts & Performance",
            "subcategory":"Music",
            "type":"Entertainment"
        }
    ],
    "sg:phone":"+61 3 9555 9501",
    "sg:postcode":"3188",
    "sg:province":"VIC",
    "sg:tags":[
        "mobile",
        "jockey",
        "disc"
    ],
    "wof:name":"SMD-Southern Mobile Disco",
    "wof:placetype":"venue"
},
  "geometry": {"coordinates":[145.025299072,-37.9317817688],"type":"Point"}
}