{
  "type": "Feature",
  "properties": {
    "iso:country":"AU",
    "sg:address":"222 Charters Towers Rd",
    "sg:city":"Hermit Park",
    "sg:classifiers":[
        {
            "category":"Health Services",
            "subcategory":"Doctor",
            "type":"Services"
        }
    ],
    "sg:phone":"+61 7 4725 5355",
    "sg:postcode":"4812",
    "sg:province":"QLD",
    "sg:tags":[
        "medical",
        "practitioner"
    ],
    "wof:name":"Askin Christine",
    "wof:placetype":"venue"
},
  "geometry": {"coordinates":[146.79743999999999,-19.285244],"type":"Point"}
}