{
  "type": "Feature",
  "properties": {
    "iso:country":"AU",
    "sg:address":"Shop 4 536 Oxley Ave",
    "sg:city":"Redcliffe",
    "sg:classifiers":[
        {
            "category":"Fast Food",
            "type":"Food & Drink"
        }
    ],
    "sg:phone":"+61 7 3203 8690",
    "sg:postcode":"4020",
    "sg:province":"QLD",
    "sg:tags":[
        "away",
        "take"
    ],
    "wof:name":"Midway Takeaway",
    "wof:placetype":"venue"
},
  "geometry": {"coordinates":[153.109787,-27.227966],"type":"Point"}
}