{
  "type": "Feature",
  "properties": {
    "addr:full":"51 May St Glenroy VIC 3046",
    "addr:housenumber":"51",
    "addr:postcode":"3046",
    "addr:street":"May St",
    "iso:country":"AU",
    "sg:address":"51 May St",
    "sg:city":"Glenroy",
    "sg:classifiers":[
        {
            "category":"Building & Trades",
            "subcategory":"Construction",
            "type":"Services"
        }
    ],
    "sg:phone":"+61 3 9306 3315",
    "sg:postcode":"3046",
    "sg:province":"VIC",
    "sg:tags":[
        "joiner",
        "carpenter"
    ],
    "wof:name":"Farrugia S",
    "wof:placetype":"venue"
},
  "geometry": {"coordinates":[144.94659423799999,-37.6982116699],"type":"Point"}
}