{
  "type": "Feature",
  "properties": {
    "addr:full":"16 Cresthill Ave Regents Park QLD 4118",
    "addr:housenumber":"16",
    "addr:postcode":"4118",
    "addr:street":"Cresthill Ave",
    "iso:country":"AU",
    "sg:address":"16 Cresthill Ave",
    "sg:city":"Regents Park",
    "sg:classifiers":[
        {
            "category":"Professional",
            "subcategory":"Art Services",
            "type":"Services"
        }
    ],
    "sg:phone":"+61 419 772 656",
    "sg:postcode":"4118",
    "sg:province":"QLD",
    "sg:tags":[
        "decorator",
        "painter"
    ],
    "wof:name":"Afrar Pty Ltd",
    "wof:placetype":"venue"
},
  "geometry": {"coordinates":[153.038665772,-27.6724815369],"type":"Point"}
}