{
  "type": "Feature",
  "properties": {
    "addr:full":"43 Pineapple St Zillmere QLD 4034",
    "addr:housenumber":"43",
    "addr:postcode":"4034",
    "addr:street":"Pineapple St",
    "iso:country":"AU",
    "sg:address":"43 Pineapple St",
    "sg:city":"Zillmere",
    "sg:classifiers":[
        {
            "category":"Retail",
            "subcategory":"Storage",
            "type":"Services"
        }
    ],
    "sg:phone":"+61 7 3263 6688",
    "sg:postcode":"4034",
    "sg:province":"QLD",
    "wof:name":"Stormart Self Storage Zillmere",
    "wof:placetype":"venue"
},
  "geometry": {"coordinates":[153.032837,-27.356586],"type":"Point"}
}