{
  "type": "Feature",
  "properties": {
    "addr:full":"98 Stirling Hwy North Fremantle WA 6159",
    "addr:housenumber":"98",
    "addr:postcode":"6159",
    "addr:street":"Stirling Hwy",
    "iso:country":"AU",
    "sg:address":"98 Stirling Hwy",
    "sg:city":"North Fremantle",
    "sg:classifiers":[
        {
            "category":"Real Estate",
            "subcategory":"Real Estate Agent",
            "type":"Services"
        }
    ],
    "sg:phone":"+61 8 9335 2477",
    "sg:postcode":"6159",
    "sg:province":"WA",
    "wof:name":"Leighton Real Estate",
    "wof:placetype":"venue"
},
  "geometry": {"coordinates":[115.75273900000001,-32.031242],"type":"Point"}
}