{
  "type": "Feature",
  "properties": {
    "addr:full":"20 Orange St Eastwood NSW 2122",
    "addr:housenumber":"20",
    "addr:postcode":"2122",
    "addr:street":"Orange St",
    "iso:country":"AU",
    "sg:address":"20 Orange St",
    "sg:city":"Eastwood",
    "sg:classifiers":[
        {
            "category":"Building & Trades",
            "subcategory":"Cleaning & Sanitation",
            "type":"Services"
        }
    ],
    "sg:phone":"+61 1300 697 933",
    "sg:postcode":"2122",
    "sg:province":"NSW",
    "sg:tags":[
        "sweeping",
        "machine"
    ],
    "wof:name":"Tempest Sweeping Services",
    "wof:placetype":"venue"
},
  "geometry": {"coordinates":[151.09442138700001,-33.7908096313],"type":"Point"}
}