{
  "type": "Feature",
  "properties": {
    "iso:country":"AU",
    "sg:address":"Suite 10 78 Campbell Pde",
    "sg:city":"Bondi Beach",
    "sg:classifiers":[
        {
            "category":"Government",
            "subcategory":"Post Office",
            "type":"Public Place"
        }
    ],
    "sg:phone":"+61 2 9130 1295",
    "sg:postcode":"2026",
    "sg:province":"NSW",
    "sg:tags":[
        "yoga"
    ],
    "wof:name":"Bondi Beach Iyengar Yoga Institute",
    "wof:placetype":"venue"
},
  "geometry": {"coordinates":[151.27305602999999,-33.8920135498],"type":"Point"}
}