{
  "type": "Feature",
  "properties": {
    "addr:full":"PO Box 77 Luddenham NSW 2745",
    "addr:postcode":"2745",
    "iso:country":"AU",
    "sg:address":"PO Box 77",
    "sg:city":"Luddenham",
    "sg:classifiers":[
        {
            "category":"Sports & Exercise",
            "subcategory":"Gym",
            "type":"Entertainment"
        }
    ],
    "sg:phone":"+61 420 984 565",
    "sg:postcode":"2745",
    "sg:province":"NSW",
    "sg:tags":[
        "personal",
        "trainer",
        "fitness"
    ],
    "wof:name":"You-nique Health & Fitness",
    "wof:placetype":"venue"
},
  "geometry": {"coordinates":[150.69390869099999,-33.8820610046],"type":"Point"}
}