{
  "type": "Feature",
  "properties": {
    "addr:full":"664 Kessels Rd Upper Mt Gravatt QLD 4122",
    "addr:housenumber":"664",
    "addr:postcode":"4122",
    "addr:street":"Kessels Rd Upper",
    "iso:country":"AU",
    "sg:address":"664 Kessels Rd",
    "sg:city":"Upper Mt Gravatt",
    "sg:classifiers":[
        {
            "category":"Health Services",
            "subcategory":"Dentist",
            "type":"Services"
        }
    ],
    "sg:phone":"+61 7 3219 2680",
    "sg:postcode":"4122",
    "sg:province":"QLD",
    "wof:name":"Tran H Dr",
    "wof:placetype":"venue"
},
  "geometry": {"coordinates":[153.08026123100001,-27.56001091],"type":"Point"}
}