{
  "type": "Feature",
  "properties": {
    "iso:country":"AU",
    "sg:address":"183 Glen Osmond Rd",
    "sg:city":"Frewville",
    "sg:classifiers":[
        {
            "category":"Real Estate",
            "subcategory":"Architect",
            "type":"Services"
        }
    ],
    "sg:phone":"+61 8 8379 9367",
    "sg:postcode":"5063",
    "sg:province":"SA",
    "wof:name":"Treloar Deane & Associates Pty Ltd",
    "wof:placetype":"venue"
},
  "geometry": {"coordinates":[138.62716674800001,-34.9473495483],"type":"Point"}
}