{
  "type": "Feature",
  "properties": {
    "iso:country":"AU",
    "sg:address":"9 Huntly St",
    "sg:city":"Moonee Ponds",
    "sg:classifiers":[
        {
            "category":"Utilities",
            "subcategory":"Electric",
            "type":"Services"
        }
    ],
    "sg:phone":"+61 419 547 415",
    "sg:postcode":"3039",
    "sg:province":"VIC",
    "sg:tags":[
        "electrical",
        "contractor"
    ],
    "wof:name":"Barec Electrical",
    "wof:placetype":"venue"
},
  "geometry": {"coordinates":[144.906555,-37.765884],"type":"Point"}
}