{
  "type": "Feature",
  "properties": {
    "iso:country":"AU",
    "sg:address":"361a Pakington St",
    "sg:city":"Newtown",
    "sg:classifiers":[
        {
            "category":"Shopping",
            "subcategory":"Clothing, Apparel, & Fashions",
            "type":"Retail Goods"
        }
    ],
    "sg:phone":"+61 3 5229 3373",
    "sg:postcode":"3220",
    "sg:province":"VIC",
    "sg:tags":[
        "boutique"
    ],
    "wof:name":"Chandelier Boutique",
    "wof:placetype":"venue"
},
  "geometry": {"coordinates":[144.34478799999999,-38.158443],"type":"Point"}
}