{
  "type": "Feature",
  "properties": {
    "addr:full":"Level 2/ 143 Brisbane St Ipswich QLD 4305",
    "addr:housenumber":"/ 143",
    "addr:postcode":"4305",
    "addr:street":"Brisbane St",
    "iso:country":"AU",
    "sg:address":"Level 2/ 143 Brisbane St",
    "sg:city":"Ipswich",
    "sg:classifiers":[
        {
            "category":"Health Services",
            "subcategory":"Doctor",
            "type":"Services"
        }
    ],
    "sg:phone":"+61 7 3281 0044",
    "sg:postcode":"4305",
    "sg:province":"QLD",
    "sg:tags":[
        "medical",
        "practitioner"
    ],
    "wof:name":"Bodetti Walter C",
    "wof:placetype":"venue"
},
  "geometry": {"coordinates":[152.75877380399999,-27.6140117645],"type":"Point"}
}