{
  "type": "Feature",
  "properties": {
    "iso:country":"AU",
    "sg:address":"168 Ballarat Rd",
    "sg:city":"Footscray",
    "sg:classifiers":[
        {
            "category":"Home & Garden",
            "subcategory":"Building Materials",
            "type":"Retail Goods"
        }
    ],
    "sg:phone":"+61 3 9689 1800",
    "sg:postcode":"3011",
    "sg:province":"VIC",
    "sg:tags":[
        "supply"
    ],
    "wof:name":"A To Z Building Centre",
    "wof:placetype":"venue"
},
  "geometry": {"coordinates":[144.893234253,-37.7922439575],"type":"Point"}
}