{
  "type": "Feature",
  "properties": {
    "iso:country":"AU",
    "sg:address":"101 Bolsover St",
    "sg:city":"Rockhampton",
    "sg:classifiers":[
        {
            "category":"Shopping",
            "subcategory":"Antiques",
            "type":"Retail Goods"
        }
    ],
    "sg:phone":"+61 7 4922 9202",
    "sg:postcode":"4702",
    "sg:province":"QLD",
    "wof:name":"City Traders",
    "wof:placetype":"venue"
},
  "geometry": {"coordinates":[150.50958251899999,-23.3753356934],"type":"Point"}
}