{
  "type": "Feature",
  "properties": {
    "addr:full":"PO Box 757 Toronto NSW 2283",
    "addr:postcode":"2283",
    "iso:country":"AU",
    "sg:address":"PO Box 757",
    "sg:city":"Toronto",
    "sg:classifiers":[
        {
            "category":"Home & Garden",
            "subcategory":"Building Materials",
            "type":"Retail Goods"
        }
    ],
    "sg:phone":"+61 2 4959 5319",
    "sg:postcode":"2283",
    "sg:province":"NSW",
    "sg:tags":[
        "fencing"
    ],
    "wof:name":"Westlakes Fencing",
    "wof:placetype":"venue"
},
  "geometry": {"coordinates":[151.585083008,-33.0113792419],"type":"Point"}
}