{
  "type": "Feature",
  "properties": {
    "addr:full":"30 Turner St Augusta WA 6290",
    "addr:housenumber":"30",
    "addr:postcode":"6290",
    "addr:street":"Turner St",
    "iso:country":"AU",
    "sg:address":"30 Turner St",
    "sg:city":"Augusta",
    "sg:classifiers":[
        {
            "category":"Farming",
            "subcategory":"Fish & Marine Products",
            "type":"Manufacturing & Wholesale Goods"
        }
    ],
    "sg:phone":"+61 8 9758 1961",
    "sg:postcode":"6290",
    "sg:province":"WA",
    "sg:tags":[
        "fisherman"
    ],
    "wof:name":"Jeff Cook",
    "wof:placetype":"venue"
},
  "geometry": {"coordinates":[115.16738891599999,-34.3289070129],"type":"Point"}
}