{
  "type": "Feature",
  "properties": {
    "addr:full":"PO Box 5034 Greenwich NSW 2065",
    "addr:postcode":"2065",
    "iso:country":"AU",
    "sg:address":"PO Box 5034",
    "sg:city":"Greenwich",
    "sg:classifiers":[
        {
            "category":"Sports & Exercise",
            "subcategory":"Ski Resort",
            "type":"Entertainment"
        }
    ],
    "sg:phone":"+61 2 9439 1622",
    "sg:postcode":"2065",
    "sg:province":"NSW",
    "sg:tags":[
        "tour",
        "centres"
    ],
    "wof:name":"Barina Milpara Lodge Ltd",
    "wof:placetype":"venue"
},
  "geometry": {"coordinates":[151.187744141,-33.8271217346],"type":"Point"}
}