{
  "type": "Feature",
  "properties": {
    "iso:country":"AU",
    "sg:address":"47- 49 Burwood Rd",
    "sg:city":"Concord",
    "sg:classifiers":[
        {
            "category":"Health Services",
            "subcategory":"Doctor",
            "type":"Services"
        }
    ],
    "sg:phone":"+61 2 9744 2666",
    "sg:postcode":"2137",
    "sg:province":"NSW",
    "sg:tags":[
        "medical",
        "practitioner"
    ],
    "wof:name":"Hazard Hugh Dr",
    "wof:placetype":"venue"
},
  "geometry": {"coordinates":[151.10638427699999,-33.8654174805],"type":"Point"}
}