{
  "type": "Feature",
  "properties": {
    "addr:full":"Slaven Rd Glossop SA 5344",
    "addr:postcode":"5344",
    "addr:street":"Slaven Rd",
    "iso:country":"AU",
    "sg:address":"Slaven Rd",
    "sg:city":"Glossop",
    "sg:classifiers":[
        {
            "category":"Farming",
            "subcategory":"Berry Farm",
            "type":"Manufacturing & Wholesale Goods"
        }
    ],
    "sg:phone":"+61 8 8583 7177",
    "sg:postcode":"5344",
    "sg:province":"SA",
    "sg:tags":[
        "fruit",
        "grower"
    ],
    "wof:name":"Radak L",
    "wof:placetype":"venue"
},
  "geometry": {"coordinates":[140.528106689,-34.2826004028],"type":"Point"}
}