{
  "type": "Feature",
  "properties": {
    "iso:country":"AU",
    "sg:address":"50 Geelong Rd",
    "sg:city":"Footscray",
    "sg:classifiers":[
        {
            "category":"Travel",
            "subcategory":"Hotels & Motels",
            "type":"Entertainment"
        }
    ],
    "sg:phone":"+61 3 9689 2822",
    "sg:postcode":"3011",
    "sg:province":"VIC",
    "wof:name":"Footscray (Palms) Motel",
    "wof:placetype":"venue"
},
  "geometry": {"coordinates":[144.89483642600001,-37.7972717285],"type":"Point"}
}