{
  "type": "Feature",
  "properties": {
    "addr:full":"384 - 386 Bourke St Melbourne VIC 3000",
    "addr:housenumber":"386",
    "addr:postcode":"3000",
    "addr:street":"Bourke St",
    "iso:country":"AU",
    "sg:address":"384 - 386 Bourke St",
    "sg:city":"Melbourne",
    "sg:classifiers":[
        {
            "category":"Health Services",
            "subcategory":"Optometrist",
            "type":"Services"
        }
    ],
    "sg:phone":"+61 3 9670 9885",
    "sg:postcode":"3000",
    "sg:province":"VIC",
    "wof:name":"OPSM",
    "wof:placetype":"venue"
},
  "geometry": {"coordinates":[144.96220398,-37.8143920898],"type":"Point"}
}