{
  "type": "Feature",
  "properties": {
    "iso:country":"AU",
    "sg:address":"16/6- 10 Railway Pde",
    "sg:city":"Westmead",
    "sg:classifiers":[
        {
            "category":"Professional",
            "subcategory":"Art Services",
            "type":"Services"
        }
    ],
    "sg:phone":"+61 412 159 614",
    "sg:postcode":"2145",
    "sg:province":"NSW",
    "sg:tags":[
        "decorator",
        "painter"
    ],
    "wof:name":"Deven Painting & Decorating",
    "wof:placetype":"venue"
},
  "geometry": {"coordinates":[150.98991394000001,-33.8088493347],"type":"Point"}
}