{
  "type": "Feature",
  "properties": {
    "addr:full":"Shop 7/ 172 Ladywood Rd Modbury Heights SA 5092",
    "addr:housenumber":"shop 7 / 172",
    "addr:postcode":"5092",
    "addr:street":"Ladywood Rd",
    "iso:country":"AU",
    "sg:address":"Shop 7/ 172 Ladywood Rd",
    "sg:city":"Modbury Heights",
    "sg:classifiers":[
        {
            "category":"Personal",
            "subcategory":"Massage",
            "type":"Services"
        }
    ],
    "sg:phone":"+61 8 8263 2111",
    "sg:postcode":"5092",
    "sg:province":"SA",
    "sg:tags":[
        "therapy"
    ],
    "wof:name":"Back To Feet At Inspiring Choices",
    "wof:placetype":"venue"
},
  "geometry": {"coordinates":[138.68635559099999,-34.8099517822],"type":"Point"}
}