{
  "type": "Feature",
  "properties": {
    "addr:full":"3 Corro St Aberfoyle Park SA 5159",
    "addr:housenumber":"3",
    "addr:postcode":"5159",
    "addr:street":"Corro St",
    "iso:country":"AU",
    "sg:address":"3 Corro St",
    "sg:city":"Aberfoyle Park",
    "sg:classifiers":[
        {
            "category":"Sports & Exercise",
            "subcategory":"Sports Center",
            "type":"Entertainment"
        }
    ],
    "sg:phone":"+61 8 8370 4749",
    "sg:postcode":"5159",
    "sg:province":"SA",
    "sg:tags":[
        "coach",
        "tennis"
    ],
    "wof:name":"Sam Wall",
    "wof:placetype":"venue"
},
  "geometry": {"coordinates":[138.60035705600001,-35.0707321167],"type":"Point"}
}