{
  "type": "Feature",
  "properties": {
    "addr:full":"515 Kent St Sydney NSW 2000",
    "addr:housenumber":"515",
    "addr:postcode":"2000",
    "addr:street":"Kent St",
    "iso:country":"AU",
    "sg:address":"515 Kent St",
    "sg:city":"Sydney",
    "sg:classifiers":[
        {
            "category":"Professional",
            "subcategory":"Accounting & Tax Preparation",
            "type":"Services"
        }
    ],
    "sg:phone":"+61 2 9267 1688",
    "sg:postcode":"2000",
    "sg:province":"NSW",
    "sg:tags":[
        "consultant",
        "taxation"
    ],
    "wof:name":"CPA",
    "wof:placetype":"venue"
},
  "geometry": {"coordinates":[151.205169678,-33.8747024536],"type":"Point"}
}