{
  "type": "Feature",
  "properties": {
    "addr:full":"10 Martinez Ave Townsville QLD 4810",
    "addr:housenumber":"10",
    "addr:postcode":"4810",
    "addr:street":"Martinez Ave",
    "iso:country":"AU",
    "sg:address":"10 Martinez Ave",
    "sg:city":"Townsville",
    "sg:classifiers":[
        {
            "category":"Wholesale",
            "subcategory":"Medical Equipment & Supplies",
            "type":"Manufacturing & Wholesale Goods"
        }
    ],
    "sg:phone":"+61 7 4728 4858",
    "sg:postcode":"4810",
    "sg:province":"QLD",
    "sg:tags":[
        "aids",
        "hearing"
    ],
    "wof:name":"All North Hearing",
    "wof:placetype":"venue"
},
  "geometry": {"coordinates":[146.785629,-19.269545],"type":"Point"}
}