{
  "type": "Feature",
  "properties": {
    "iso:country":"AU",
    "sg:address":"Bungonia Rd",
    "sg:city":"Goulburn",
    "sg:classifiers":[
        {
            "category":"Retail",
            "subcategory":"Event Space",
            "type":"Services"
        }
    ],
    "sg:phone":"+61 2 4821 6071",
    "sg:postcode":"2580",
    "sg:province":"NSW",
    "sg:tags":[
        "function",
        "organiser"
    ],
    "wof:name":"Goulburn Brewery",
    "wof:placetype":"venue"
},
  "geometry": {"coordinates":[149.71588134800001,-34.7640037537],"type":"Point"}
}