{
  "type": "Feature",
  "properties": {
    "addr:full":"PO Box 803 Toormina NSW 2452",
    "addr:postcode":"2452",
    "iso:country":"AU",
    "sg:address":"PO Box 803",
    "sg:city":"Toormina",
    "sg:classifiers":[
        {
            "category":"Arena",
            "subcategory":"Sports Club",
            "type":"Entertainment"
        }
    ],
    "sg:phone":"+61 2 6658 8556",
    "sg:postcode":"2452",
    "sg:province":"NSW",
    "sg:tags":[
        "organisation",
        "sporting"
    ],
    "wof:name":"Australian Rugby League Development",
    "wof:placetype":"venue"
},
  "geometry": {"coordinates":[153.090576,-30.35095],"type":"Point"}
}