{
  "type": "Feature",
  "properties": {
    "iso:country":"AU",
    "sg:address":"Burney St",
    "sg:city":"Blyth",
    "sg:classifiers":[
        {
            "category":"Farming",
            "subcategory":"Farm & Veterinary Services",
            "type":"Manufacturing & Wholesale Goods"
        }
    ],
    "sg:phone":"+61 8 8844 5111",
    "sg:postcode":"5462",
    "sg:province":"SA",
    "sg:tags":[
        "contracting"
    ],
    "wof:name":"Rippa Dippa Pty Ltd",
    "wof:placetype":"venue"
},
  "geometry": {"coordinates":[138.491547,-33.843994],"type":"Point"}
}