{
  "type": "Feature",
  "properties": {
    "iso:country":"AU",
    "sg:address":"610- 612 Burke Rd",
    "sg:city":"Camberwell",
    "sg:classifiers":[
        {
            "category":"Food & Beverages",
            "subcategory":"Liquor & Beverages",
            "type":"Retail Goods"
        }
    ],
    "sg:phone":"+61 3 9813 1896",
    "sg:postcode":"3124",
    "sg:province":"VIC",
    "sg:tags":[
        "store"
    ],
    "wof:name":"Vintage Cellars",
    "wof:placetype":"venue"
},
  "geometry": {"coordinates":[145.05714416500001,-37.8298530579],"type":"Point"}
}