{
  "type": "Feature",
  "properties": {
    "addr:full":"33 Ferry St Maryborough QLD 4650",
    "addr:housenumber":"33",
    "addr:postcode":"4650",
    "addr:street":"Ferry St",
    "iso:country":"AU",
    "sg:address":"33 Ferry St",
    "sg:city":"Maryborough",
    "sg:classifiers":[
        {
            "category":"Restaurant",
            "type":"Food & Drink"
        }
    ],
    "sg:phone":"+61 7 4121 3295",
    "sg:postcode":"4650",
    "sg:province":"QLD",
    "wof:name":"Cockys Grill",
    "wof:placetype":"venue"
},
  "geometry": {"coordinates":[152.69006300000001,-25.541706],"type":"Point"}
}