{
  "type": "Feature",
  "properties": {
    "addr:full":"259 - 263 George St Liverpool NSW 2170",
    "addr:housenumber":"263",
    "addr:postcode":"2170",
    "addr:street":"George St",
    "iso:country":"AU",
    "sg:address":"259 - 263 George St",
    "sg:city":"Liverpool",
    "sg:classifiers":[
        {
            "category":"Health Services",
            "subcategory":"Dentist",
            "type":"Services"
        }
    ],
    "sg:phone":"+61 2 9821 4480",
    "sg:postcode":"2170",
    "sg:province":"NSW",
    "wof:name":"The Smiles Dr",
    "wof:placetype":"venue"
},
  "geometry": {"coordinates":[150.9243927,-33.9244842529],"type":"Point"}
}