{
  "type": "Feature",
  "properties": {
    "addr:full":"122 Military Rd Guildford NSW 2161",
    "addr:housenumber":"122",
    "addr:postcode":"2161",
    "addr:street":"Military Rd",
    "iso:country":"AU",
    "sg:address":"122 Military Rd",
    "sg:city":"Guildford",
    "sg:classifiers":[
        {
            "category":"Food & Beverages",
            "subcategory":"Bakery",
            "type":"Retail Goods"
        }
    ],
    "sg:phone":"+61 2 9681 5188",
    "sg:postcode":"2161",
    "sg:province":"NSW",
    "sg:tags":[
        "baker"
    ],
    "wof:name":"Patrick Hot Bread Shop",
    "wof:placetype":"venue"
},
  "geometry": {"coordinates":[150.98565673799999,-33.8537826538],"type":"Point"}
}