{
  "type": "Feature",
  "properties": {
    "addr:full":"PO Box 64 Kings Meadows TAS 7249",
    "addr:postcode":"7249",
    "iso:country":"AU",
    "sg:address":"PO Box 64",
    "sg:city":"Kings Meadows",
    "sg:classifiers":[
        {
            "category":"Retail",
            "subcategory":"Auto Repair",
            "type":"Services"
        }
    ],
    "sg:phone":"+61 3 6344 4201",
    "sg:postcode":"7249",
    "sg:province":"TAS",
    "sg:tags":[
        "electrical"
    ],
    "wof:name":"JLH Auto Electrical & Instrumental Services",
    "wof:placetype":"venue"
},
  "geometry": {"coordinates":[147.16050720199999,-41.4677696228],"type":"Point"}
}