{
  "type": "Feature",
  "properties": {
    "iso:country":"AU",
    "sg:address":"19 Belvidere Rd",
    "sg:city":"Saddleworth",
    "sg:classifiers":[
        {
            "category":"Health Services",
            "subcategory":"Doctor",
            "type":"Services"
        }
    ],
    "sg:phone":"+61 8 8847 4008",
    "sg:postcode":"5413",
    "sg:province":"SA",
    "sg:tags":[
        "medical",
        "practitioner"
    ],
    "wof:name":"Saddleworth Doctors Surgery",
    "wof:placetype":"venue"
},
  "geometry": {"coordinates":[138.78047180199999,-34.0831260681],"type":"Point"}
}