{
  "type": "Feature",
  "properties": {
    "addr:full":"Cnr Kenny & Burelli Sts Wollongong NSW 2500",
    "addr:postcode":"2500",
    "addr:street":"Cnr Kenny & Burelli Sts",
    "iso:country":"AU",
    "sg:address":"Cnr Kenny & Burelli Sts",
    "sg:city":"Wollongong",
    "sg:classifiers":[
        {
            "category":"Building & Trades",
            "subcategory":"Locksmith",
            "type":"Services"
        }
    ],
    "sg:phone":"+61 2 4229 2346",
    "sg:postcode":"2500",
    "sg:province":"NSW",
    "sg:tags":[
        "strongroom",
        "safe",
        "door"
    ],
    "wof:name":"Mawson Lock Service",
    "wof:placetype":"venue"
},
  "geometry": {"coordinates":[150.890289,-34.426338],"type":"Point"}
}