{
  "type": "Feature",
  "properties": {
    "addr:full":"7 Armstrong Rd Applecross WA 6153",
    "addr:housenumber":"7",
    "addr:postcode":"6153",
    "addr:street":"Armstrong Rd",
    "iso:country":"AU",
    "sg:address":"7 Armstrong Rd",
    "sg:city":"Applecross",
    "sg:classifiers":[
        {
            "category":"Social Services",
            "subcategory":"Retirement Home",
            "type":"Services"
        }
    ],
    "sg:phone":"+61 8 9316 0411",
    "sg:postcode":"6153",
    "sg:province":"WA",
    "sg:tags":[
        "life",
        "coaching"
    ],
    "wof:name":"In Search For Balance In Life",
    "wof:placetype":"venue"
},
  "geometry": {"coordinates":[115.84272,-32.011272],"type":"Point"}
}