{
  "type": "Feature",
  "properties": {
    "addr:full":"14 Cooloola Drv Toowoomba QLD 4350",
    "addr:housenumber":"14",
    "addr:postcode":"4350",
    "addr:street":"Cooloola Drv",
    "iso:country":"AU",
    "sg:address":"14 Cooloola Drv",
    "sg:city":"Toowoomba",
    "sg:classifiers":[
        {
            "category":"Sports & Exercise",
            "subcategory":"Sports Center",
            "type":"Entertainment"
        }
    ],
    "sg:phone":"+61 7 4635 6161",
    "sg:postcode":"4350",
    "sg:province":"QLD",
    "sg:tags":[
        "coach",
        "tennis"
    ],
    "wof:name":"Gaydon M D",
    "wof:placetype":"venue"
},
  "geometry": {"coordinates":[151.98826600000001,-27.58569],"type":"Point"}
}