{
  "type": "Feature",
  "properties": {
    "addr:full":"Ste 5/ 17 Frederick St Oatley NSW 2223",
    "addr:housenumber":"17",
    "addr:postcode":"2223",
    "addr:street":"Frederick St",
    "iso:country":"AU",
    "sg:address":"Ste 5/ 17 Frederick St",
    "sg:city":"Oatley",
    "sg:classifiers":[
        {
            "category":"Government",
            "subcategory":"Court House",
            "type":"Public Place"
        }
    ],
    "sg:phone":"+61 2 9580 3295",
    "sg:postcode":"2223",
    "sg:province":"NSW",
    "sg:tags":[
        "personal",
        "marriage",
        "family",
        "counselling"
    ],
    "wof:name":"Oatley Village Counselling",
    "wof:placetype":"venue"
},
  "geometry": {"coordinates":[151.081100464,-33.981300354],"type":"Point"}
}