{
  "type": "Feature",
  "properties": {
    "iso:country":"AU",
    "sg:address":"12 Mary St St",
    "sg:city":"Peters",
    "sg:classifiers":[
        {
            "category":"Manufacturing",
            "subcategory":"Glass & Minerals",
            "type":"Manufacturing & Wholesale Goods"
        }
    ],
    "sg:phone":"+61 2 9517 2916",
    "sg:postcode":"2044",
    "sg:province":"NSW",
    "sg:tags":[
        "tube",
        "rod",
        "pipes"
    ],
    "wof:name":"Custom-Blown Glassware",
    "wof:placetype":"venue"
},
  "geometry": {"coordinates":[151.173721,-33.914825],"type":"Point"}
}