{
  "type": "Feature",
  "properties": {
    "iso:country":"AU",
    "sg:address":"PO Box 161",
    "sg:city":"Richlands",
    "sg:classifiers":[
        {
            "category":"Real Estate",
            "subcategory":"Architect",
            "type":"Services"
        }
    ],
    "sg:phone":"+61 1800 637 504",
    "sg:postcode":"4077",
    "sg:province":"QLD",
    "sg:tags":[
        "raw",
        "material",
        "plastic"
    ],
    "wof:name":"Polymers International Australia Pty Ltd",
    "wof:placetype":"venue"
},
  "geometry": {"coordinates":[152.95428466800001,-27.5964202881],"type":"Point"}
}