{
  "type": "Feature",
  "properties": {
    "addr:full":"57 Glen Rd Belgrave Heights VIC 3160",
    "addr:housenumber":"57",
    "addr:postcode":"3160",
    "addr:street":"Glen Rd",
    "iso:country":"AU",
    "sg:address":"57 Glen Rd",
    "sg:city":"Belgrave Heights",
    "sg:classifiers":[
        {
            "category":"Health Services",
            "subcategory":"Health Practitioner",
            "type":"Services"
        }
    ],
    "sg:phone":"+61 3 9754 5857",
    "sg:postcode":"3160",
    "sg:province":"VIC",
    "sg:tags":[
        "naturopath"
    ],
    "wof:name":"Belgrave Naturopathic Centre",
    "wof:placetype":"venue"
},
  "geometry": {"coordinates":[145.345245361,-37.9209594727],"type":"Point"}
}