{
  "type": "Feature",
  "properties": {
    "addr:full":"PO Box 52 St Clair NSW 2759",
    "addr:postcode":"2759",
    "iso:country":"AU",
    "sg:address":"PO Box 52 St",
    "sg:city":"Clair",
    "sg:classifiers":[
        {
            "category":"Retail",
            "subcategory":"Funeral Services",
            "type":"Services"
        }
    ],
    "sg:phone":"+61 413 682 141",
    "sg:postcode":"2759",
    "sg:province":"NSW",
    "sg:tags":[
        "supply"
    ],
    "wof:name":"Coffin Casket Timber & Plastic Handle Specialist",
    "wof:placetype":"venue"
},
  "geometry": {"coordinates":[150.77980041500001,-33.7973594666],"type":"Point"}
}