{
  "type": "Feature",
  "properties": {
    "addr:full":"250 Victoria Rd Drummoyne NSW 2047",
    "addr:housenumber":"250",
    "addr:postcode":"2047",
    "addr:street":"Victoria Rd",
    "iso:country":"AU",
    "sg:address":"250 Victoria Rd",
    "sg:city":"Drummoyne",
    "sg:classifiers":[
        {
            "category":"Health Services",
            "subcategory":"Doctor",
            "type":"Services"
        }
    ],
    "sg:phone":"+61 2 9819 6444",
    "sg:postcode":"2047",
    "sg:province":"NSW",
    "sg:tags":[
        "medical",
        "practitioner"
    ],
    "wof:name":"Benger Ross S",
    "wof:placetype":"venue"
},
  "geometry": {"coordinates":[151.15342699999999,-33.849342],"type":"Point"}
}