{
  "type": "Feature",
  "properties": {
    "addr:full":"47 Douglas St Richmond NSW 2753",
    "addr:housenumber":"47",
    "addr:postcode":"2753",
    "addr:street":"Douglas St",
    "iso:country":"AU",
    "sg:address":"47 Douglas St",
    "sg:city":"Richmond",
    "sg:classifiers":[
        {
            "category":"Utilities",
            "subcategory":"Water",
            "type":"Services"
        }
    ],
    "sg:phone":"+61 2 4578 3051",
    "sg:postcode":"2753",
    "sg:province":"NSW",
    "sg:tags":[
        "cartage"
    ],
    "wof:name":"Hieler Michael",
    "wof:placetype":"venue"
},
  "geometry": {"coordinates":[150.722091675,-33.5714225769],"type":"Point"}
}