{
  "type": "Feature",
  "properties": {
    "addr:full":"67 Regency Rd Croydon Park SA 5008",
    "addr:housenumber":"67",
    "addr:postcode":"5008",
    "addr:street":"Regency Rd",
    "iso:country":"AU",
    "sg:address":"67 Regency Rd",
    "sg:city":"Croydon Park",
    "sg:classifiers":[
        {
            "category":"Organizations",
            "subcategory":"Professional Association",
            "type":"Services"
        }
    ],
    "sg:phone":"+61 8 8243 7911",
    "sg:postcode":"5008",
    "sg:province":"SA",
    "sg:tags":[
        "organisation",
        "business"
    ],
    "wof:name":"Australasian Production & Inventory Control Society Incorporated South Australia",
    "wof:placetype":"venue"
},
  "geometry": {"coordinates":[138.56805399999999,-34.875366],"type":"Point"}
}