{
  "type": "Feature",
  "properties": {
    "iso:country":"AU",
    "sg:address":"67 Regency Rd",
    "sg:city":"Croydon Park",
    "sg:classifiers":[
        {
            "category":"Organizations",
            "subcategory":"Professional Association",
            "type":"Services"
        }
    ],
    "sg:phone":"+61 8 8243 7911",
    "sg:postcode":"5008",
    "sg:province":"SA",
    "sg:tags":[
        "organisation",
        "business"
    ],
    "wof:name":"Australasian Production & Inventory Control Society Incorporated South Australia",
    "wof:placetype":"venue"
},
  "geometry": {"coordinates":[138.568054,-34.875366],"type":"Point"}
}