{
  "type": "Feature",
  "properties": {
    "iso:country":"AU",
    "sg:address":"3/ 58 Golf Ave",
    "sg:city":"Mona Vale",
    "sg:classifiers":[
        {
            "category":"Education",
            "subcategory":"Special Training",
            "type":"Public Place"
        }
    ],
    "sg:phone":"+61 2 8004 2279",
    "sg:postcode":"2103",
    "sg:province":"NSW",
    "sg:tags":[
        "development"
    ],
    "wof:name":"Moving On Training",
    "wof:placetype":"venue"
},
  "geometry": {"coordinates":[151.311309814,-33.6802978516],"type":"Point"}
}