{
  "type": "Feature",
  "properties": {
    "iso:country":"AU",
    "sg:address":"44 Murray St",
    "sg:city":"Nuriootpa",
    "sg:classifiers":[
        {
            "category":"Professional",
            "subcategory":"Employment Agencies",
            "type":"Services"
        }
    ],
    "sg:phone":"+61 8 8561 2000",
    "sg:postcode":"5355",
    "sg:province":"SA",
    "wof:name":"Integrated Group",
    "wof:placetype":"venue"
},
  "geometry": {"coordinates":[138.99667358400001,-34.4703826904],"type":"Point"}
}