{
  "type": "Feature",
  "properties": {
    "addr:full":"72 Barrier St Fyshwick ACT 2609",
    "addr:housenumber":"72",
    "addr:postcode":"2609",
    "addr:street":"Barrier St",
    "iso:country":"AU",
    "sg:address":"72 Barrier St",
    "sg:city":"Fyshwick",
    "sg:classifiers":[
        {
            "category":"Home & Garden",
            "subcategory":"Furniture",
            "type":"Retail Goods"
        }
    ],
    "sg:phone":"+61 2 6239 3611",
    "sg:postcode":"2609",
    "sg:province":"ACT",
    "sg:tags":[
        "business"
    ],
    "wof:name":"Re-New",
    "wof:placetype":"venue"
},
  "geometry": {"coordinates":[149.17137145999999,-35.3280181885],"type":"Point"}
}