{
  "type": "Feature",
  "properties": {
    "addr:full":"Shop 23, Tweed Mall Cnr Bay & Wharf Sts Tweed Heads NSW 2485",
    "addr:housenumber":"shop 23",
    "addr:postcode":"2485",
    "addr:street":"Tweed Mall Cnr Bay &;Sts",
    "iso:country":"AU",
    "sg:address":"Shop 23, Tweed Mall Cnr Bay & Wharf Sts",
    "sg:city":"Tweed Heads",
    "sg:classifiers":[
        {
            "category":"Personal",
            "subcategory":"Beauty Salon",
            "type":"Services"
        }
    ],
    "sg:phone":"+61 7 5599 4100",
    "sg:postcode":"2485",
    "sg:province":"NSW",
    "sg:tags":[
        "hairdresser"
    ],
    "wof:name":"Price Attack",
    "wof:placetype":"venue"
},
  "geometry": {"coordinates":[153.54087829599999,-28.1707725525],"type":"Point"}
}