{
  "type": "Feature",
  "properties": {
    "iso:country":"AU",
    "sg:address":"1 Holden Ave",
    "sg:city":"Epping",
    "sg:classifiers":[
        {
            "category":"Building & Trades",
            "subcategory":"Construction",
            "type":"Services"
        }
    ],
    "sg:phone":"+61 409 661 314",
    "sg:postcode":"1710",
    "sg:province":"NSW",
    "sg:tags":[
        "contractor"
    ],
    "wof:name":"Shearing D G & C R",
    "wof:placetype":"venue"
},
  "geometry": {"coordinates":[151.07008361800001,-33.7670516968],"type":"Point"}
}