{
  "type": "Feature",
  "properties": {
    "iso:country":"AU",
    "sg:address":"Shop 12, Village Shopping Centre 78 Celeber Drv",
    "sg:city":"Andergrove",
    "sg:classifiers":[
        {
            "category":"Fast Food",
            "type":"Food & Drink"
        }
    ],
    "sg:phone":"+61 7 4942 8428",
    "sg:postcode":"4740",
    "sg:province":"QLD",
    "sg:tags":[
        "away",
        "take"
    ],
    "wof:name":"Sorbellos Pasta Express",
    "wof:placetype":"venue"
},
  "geometry": {"coordinates":[149.178009,-21.097298],"type":"Point"}
}