{
  "type": "Feature",
  "properties": {
    "iso:country":"AU",
    "sg:address":"6 Park Pde",
    "sg:city":"Bondi",
    "sg:classifiers":[
        {
            "category":"Building & Trades",
            "subcategory":"Plumbing",
            "type":"Services"
        }
    ],
    "sg:phone":"+61 2 9389 7529",
    "sg:postcode":"2026",
    "sg:province":"NSW",
    "sg:tags":[
        "plumber",
        "gasfitters"
    ],
    "wof:name":"Timothy Murphy",
    "wof:placetype":"venue"
},
  "geometry": {"coordinates":[151.25981140100001,-33.8939094543],"type":"Point"}
}