{
  "type": "Feature",
  "properties": {
    "iso:country":"AU",
    "sg:address":"83A Nicholson St",
    "sg:city":"Brunswick East",
    "sg:classifiers":[
        {
            "category":"Wholesale",
            "subcategory":"Metals & Minerals",
            "type":"Manufacturing & Wholesale Goods"
        }
    ],
    "sg:phone":"+61 3 9387 1735",
    "sg:postcode":"3057",
    "sg:province":"VIC",
    "sg:tags":[
        "steel",
        "merchant"
    ],
    "wof:name":"McPherson Steel",
    "wof:placetype":"venue"
},
  "geometry": {"coordinates":[144.978713989,-37.7749214172],"type":"Point"}
}