{
  "type": "Feature",
  "properties": {
    "addr:full":"PO Box 401 Emu Plains NSW 2750",
    "addr:postcode":"2750",
    "iso:country":"AU",
    "sg:address":"PO Box 401",
    "sg:city":"Emu Plains",
    "sg:classifiers":[
        {
            "category":"Shopping",
            "subcategory":"Computers & Home Electronics",
            "type":"Retail Goods"
        }
    ],
    "sg:phone":"+61 2 4773 8251",
    "sg:postcode":"2750",
    "sg:province":"NSW",
    "sg:tags":[
        "equipment",
        "supply"
    ],
    "wof:name":"Dynabytes Consulting",
    "wof:placetype":"venue"
},
  "geometry": {"coordinates":[150.65957641599999,-33.7534790039],"type":"Point"}
}