{
  "type": "Feature",
  "properties": {
    "addr:full":"89 Ryrie St Geelong VIC 3220",
    "addr:housenumber":"89",
    "addr:postcode":"3220",
    "addr:street":"Ryrie St",
    "iso:country":"AU",
    "sg:address":"89 Ryrie St",
    "sg:city":"Geelong",
    "sg:classifiers":[
        {
            "category":"Education",
            "subcategory":"Special Training",
            "type":"Public Place"
        }
    ],
    "sg:phone":"+61 3 5222 6906",
    "sg:postcode":"3220",
    "sg:province":"VIC",
    "sg:tags":[
        "development"
    ],
    "wof:name":"MEGT(Australia) Ltd",
    "wof:placetype":"venue"
},
  "geometry": {"coordinates":[144.35762,-38.148499],"type":"Point"}
}