{
  "type": "Feature",
  "properties": {
    "addr:full":"Shop 5 Amiens Ave Milperra NSW 2214",
    "addr:housenumber":"shop 5",
    "addr:postcode":"2214",
    "addr:street":"Amiens Ave",
    "iso:country":"AU",
    "sg:address":"Shop 5 Amiens Ave",
    "sg:city":"Milperra",
    "sg:classifiers":[
        {
            "category":"Personal",
            "subcategory":"Nail Salon",
            "type":"Services"
        }
    ],
    "sg:phone":"+61 417 231 210",
    "sg:postcode":"2214",
    "sg:province":"NSW",
    "sg:tags":[
        "artificial"
    ],
    "wof:name":"Melissa's Nail Bar",
    "wof:placetype":"venue"
},
  "geometry": {"coordinates":[150.98071300000001,-33.938072],"type":"Point"}
}