{
  "type": "Feature",
  "properties": {
    "iso:country":"AU",
    "sg:address":"70 Bakers Rd",
    "sg:city":"Coburg North",
    "sg:classifiers":[
        {
            "category":"Wholesale",
            "subcategory":"Furniture",
            "type":"Manufacturing & Wholesale Goods"
        }
    ],
    "sg:phone":"+61 3 9350 1544",
    "sg:postcode":"3058",
    "sg:province":"VIC",
    "sg:tags":[
        "wholesaler",
        "mfrs"
    ],
    "wof:name":"Wellbuilt Furniture Manufacturers Pty Ltd",
    "wof:placetype":"venue"
},
  "geometry": {"coordinates":[144.9556427,-37.7263565063],"type":"Point"}
}