{
  "type": "Feature",
  "properties": {
    "iso:country":"AU",
    "sg:address":"36 Palmer St",
    "sg:city":"Woorinen South",
    "sg:classifiers":[
        {
            "category":"Food & Beverages",
            "subcategory":"Groceries & Convenience Stores",
            "type":"Retail Goods"
        }
    ],
    "sg:phone":"+61 3 5037 6465",
    "sg:postcode":"3588",
    "sg:province":"VIC",
    "wof:name":"Treseder R M & J",
    "wof:placetype":"venue"
},
  "geometry": {"coordinates":[143.454224,-35.291515],"type":"Point"}
}