{
  "type": "Feature",
  "properties": {
    "iso:country":"AU",
    "sg:address":"358 Moorandah Hwy",
    "sg:city":"Croydon North",
    "sg:classifiers":[
        {
            "category":"Building & Trades",
            "subcategory":"Construction",
            "type":"Services"
        }
    ],
    "sg:phone":"+61 3 9722 1118",
    "sg:postcode":"3136",
    "sg:province":"VIC",
    "sg:tags":[
        "contractor"
    ],
    "wof:name":"ECS Group (Aust) Pty Ltd",
    "wof:placetype":"venue"
},
  "geometry": {"coordinates":[145.284057617,-37.7831382751],"type":"Point"}
}