{
  "type": "Feature",
  "properties": {
    "iso:country":"AU",
    "sg:address":"67-85 Wotton St",
    "sg:city":"Aitkenvale",
    "sg:classifiers":[
        {
            "category":"Education",
            "subcategory":"School",
            "type":"Public Place"
        }
    ],
    "sg:phone":"+61 7 4779 0266",
    "sg:postcode":"4814",
    "sg:province":"QLD",
    "sg:tags":[
        "state",
        "except",
        "nsw"
    ],
    "wof:name":"Aitkenvale Primary",
    "wof:placetype":"venue"
},
  "geometry": {"coordinates":[146.762787,-19.296804],"type":"Point"}
}