{
  "type": "Feature",
  "properties": {
    "addr:full":"8 Holland Pl Wilson WA 6107",
    "addr:housenumber":"8",
    "addr:postcode":"6107",
    "addr:street":"Holland Pl",
    "iso:country":"AU",
    "sg:address":"8 Holland Pl",
    "sg:city":"Wilson",
    "sg:classifiers":[
        {
            "category":"Mining & Drilling",
            "type":"Manufacturing & Wholesale Goods"
        }
    ],
    "sg:phone":"+61 8 9458 7820",
    "sg:postcode":"6107",
    "sg:province":"WA",
    "sg:tags":[
        "boring",
        "contractor"
    ],
    "wof:name":"Canningvale Water Bores",
    "wof:placetype":"venue"
},
  "geometry": {"coordinates":[115.90814209,-32.023601532],"type":"Point"}
}