{
  "type": "Feature",
  "properties": {
    "addr:full":"2 Glentilt Rd Glen Iris VIC 3146",
    "addr:housenumber":"2",
    "addr:postcode":"3146",
    "addr:street":"Glentilt Rd",
    "iso:country":"AU",
    "sg:address":"2 Glentilt Rd",
    "sg:city":"Glen Iris",
    "sg:classifiers":[
        {
            "category":"Building & Trades",
            "subcategory":"Construction",
            "type":"Services"
        }
    ],
    "sg:phone":"+61 407 599 390",
    "sg:postcode":"3146",
    "sg:province":"VIC",
    "sg:tags":[
        "contractor"
    ],
    "wof:name":"Kanellis Bros Constructions Pty Ltd",
    "wof:placetype":"venue"
},
  "geometry": {"coordinates":[145.05020141599999,-37.8540077209],"type":"Point"}
}