{
  "type": "Feature",
  "properties": {
    "addr:full":"107 Murphy St Wangaratta VIC 3677",
    "addr:housenumber":"107",
    "addr:postcode":"3677",
    "addr:street":"Murphy St",
    "iso:country":"AU",
    "sg:address":"107 Murphy St",
    "sg:city":"Wangaratta",
    "sg:classifiers":[
        {
            "category":"Personal",
            "subcategory":"Beauty Salon",
            "type":"Services"
        }
    ],
    "sg:phone":"+61 3 5722 3638",
    "sg:postcode":"3677",
    "sg:province":"VIC",
    "sg:tags":[
        "hairdresser"
    ],
    "wof:name":"GioVanni's Design",
    "wof:placetype":"venue"
},
  "geometry": {"coordinates":[146.32786560100001,-36.354309082],"type":"Point"}
}