{
  "type": "Feature",
  "properties": {
    "addr:full":"3 Beauchamp Ave Chatswood NSW 2067",
    "addr:housenumber":"3",
    "addr:postcode":"2067",
    "addr:street":"Beauchamp Ave",
    "iso:country":"AU",
    "sg:address":"3 Beauchamp Ave",
    "sg:city":"Chatswood",
    "sg:classifiers":[
        {
            "category":"Home & Garden",
            "subcategory":"Building Materials",
            "type":"Retail Goods"
        }
    ],
    "sg:phone":"+61 2 9411 2252",
    "sg:postcode":"2067",
    "sg:province":"NSW",
    "sg:tags":[
        "retaining",
        "wall"
    ],
    "wof:name":"Loc-A-Bloc Industries Pty Limited",
    "wof:placetype":"venue"
},
  "geometry": {"coordinates":[151.18754577600001,-33.7896766663],"type":"Point"}
}