{
  "type": "Feature",
  "properties": {
    "iso:country":"AU",
    "sg:address":"Boneo Rd",
    "sg:city":"Boneo",
    "sg:classifiers":[
        {
            "category":"Food & Beverages",
            "subcategory":"Fruits & Vegetables",
            "type":"Retail Goods"
        }
    ],
    "sg:phone":"+61 3 5988 6333",
    "sg:postcode":"3939",
    "sg:province":"VIC",
    "sg:tags":[
        "grower"
    ],
    "wof:name":"Burrell G G",
    "wof:placetype":"venue"
},
  "geometry": {"coordinates":[144.888946533,-38.3807525635],"type":"Point"}
}