{
  "type": "Feature",
  "properties": {
    "addr:full":"62 Plumer St Wellington Point QLD 4160",
    "addr:housenumber":"62",
    "addr:postcode":"4160",
    "addr:street":"Plumer St",
    "iso:country":"AU",
    "sg:address":"62 Plumer St",
    "sg:city":"Wellington Point",
    "sg:classifiers":[
        {
            "category":"Communications",
            "type":"Services"
        }
    ],
    "sg:phone":"+61 405 622 822",
    "sg:postcode":"4160",
    "sg:province":"QLD",
    "sg:tags":[
        "translation"
    ],
    "wof:name":"De Vries Saskia",
    "wof:placetype":"venue"
},
  "geometry": {"coordinates":[153.24339294399999,-27.5067062378],"type":"Point"}
}