{
  "type": "Feature",
  "properties": {
    "addr:full":"6 Sutton Way, Darch WA 6065",
    "addr:housenumber":"6",
    "addr:postcode":"6065",
    "addr:street":"Sutton Way",
    "iso:country":"AU",
    "sg:address":"6 Sutton Way,",
    "sg:city":"Darch",
    "sg:classifiers":[
        {
            "category":"Arts & Performance",
            "subcategory":"Music",
            "type":"Entertainment"
        }
    ],
    "sg:phone":"+61 8 9302 5074",
    "sg:postcode":"6065",
    "sg:province":"WA",
    "sg:tags":[
        "mobile",
        "jockey",
        "disc"
    ],
    "sg:website":"http://www.udj.com.au",
    "wof:name":"UDJ Productions",
    "wof:placetype":"venue"
},
  "geometry": {"coordinates":[115.842430115,-31.8072528839],"type":"Point"}
}