{
  "type": "Feature",
  "properties": {
    "addr:full":"75 Victor Rd Dee Why NSW 2099",
    "addr:housenumber":"75",
    "addr:postcode":"2099",
    "addr:street":"Victor Rd",
    "iso:country":"AU",
    "sg:address":"75 Victor Rd",
    "sg:city":"Dee Why",
    "sg:classifiers":[
        {
            "category":"Military Area",
            "subcategory":"Coast Guard Base",
            "type":"Public Place"
        }
    ],
    "sg:phone":"+61 419 271 953",
    "sg:postcode":"2099",
    "sg:province":"NSW",
    "sg:tags":[
        "sound",
        "engineer"
    ],
    "wof:name":"Zappa Productions Pty Ltd",
    "wof:placetype":"venue"
},
  "geometry": {"coordinates":[151.27899169899999,-33.7522315979],"type":"Point"}
}