{
  "type": "Feature",
  "properties": {
    "addr:full":"1 Brasch St Bundaberg QLD 4670",
    "addr:housenumber":"1",
    "addr:postcode":"4670",
    "addr:street":"Brasch St",
    "iso:country":"AU",
    "sg:address":"1 Brasch St",
    "sg:city":"Bundaberg",
    "sg:classifiers":[
        {
            "category":"Personal",
            "subcategory":"Beauty Salon",
            "type":"Services"
        }
    ],
    "sg:phone":"+61 7 4151 5831",
    "sg:postcode":"4670",
    "sg:province":"QLD",
    "sg:tags":[
        "hairdresser"
    ],
    "wof:name":"Kepnock Hair Fashions",
    "wof:placetype":"venue"
},
  "geometry": {"coordinates":[152.368286133,-24.8778896332],"type":"Point"}
}