{
  "type": "Feature",
  "properties": {
    "addr:full":"2 Ewing La Glenning Valley NSW 2259",
    "addr:housenumber":"2",
    "addr:postcode":"2259",
    "addr:street":"Ewing La Glenning",
    "iso:country":"AU",
    "sg:address":"2 Ewing La",
    "sg:city":"Glenning Valley",
    "sg:classifiers":[
        {
            "category":"Building & Trades",
            "subcategory":"Construction",
            "type":"Services"
        }
    ],
    "sg:phone":"+61 2 4388 2235",
    "sg:postcode":"2259",
    "sg:province":"NSW",
    "sg:tags":[
        "plasterboard",
        "plasterer",
        "fixer"
    ],
    "wof:name":"Bell P P",
    "wof:placetype":"venue"
},
  "geometry": {"coordinates":[151.42172241200001,-33.3517608643],"type":"Point"}
}