{
  "type": "Feature",
  "properties": {
    "addr:full":"53 Royal Pde Parkville VIC 3052",
    "addr:housenumber":"53",
    "addr:postcode":"3052",
    "addr:street":"Royal Pde",
    "iso:country":"AU",
    "sg:address":"53 Royal Pde",
    "sg:city":"Parkville",
    "sg:classifiers":[
        {
            "category":"Fast Food",
            "type":"Food & Drink"
        }
    ],
    "sg:phone":"+61 3 9347 4870",
    "sg:postcode":"3052",
    "sg:province":"VIC",
    "sg:tags":[
        "away",
        "take"
    ],
    "wof:name":"Cafe Royale",
    "wof:placetype":"venue"
},
  "geometry": {"coordinates":[144.957763672,-37.7953910828],"type":"Point"}
}