{
  "type": "Feature",
  "properties": {
    "iso:country":"AU",
    "sg:address":"7A Merriman St",
    "sg:city":"Kyle Bay",
    "sg:classifiers":[
        {
            "category":"Professional",
            "subcategory":"Art Services",
            "type":"Services"
        }
    ],
    "sg:phone":"+61 418 453 875",
    "sg:postcode":"2221",
    "sg:province":"NSW",
    "sg:tags":[
        "interior",
        "decorator"
    ],
    "wof:name":"Price-less Interiors",
    "wof:placetype":"venue"
},
  "geometry": {"coordinates":[151.101654053,-33.9877662659],"type":"Point"}
}