{
  "type": "Feature",
  "properties": {
    "addr:full":"Suite 4/ 1 Darling St Wollongong NSW 2500",
    "addr:housenumber":"1",
    "addr:postcode":"2500",
    "addr:street":"Darling St",
    "iso:country":"AU",
    "sg:address":"Suite 4/ 1 Darling St",
    "sg:city":"Wollongong",
    "sg:classifiers":[
        {
            "category":"Health Services",
            "subcategory":"Doctor",
            "type":"Services"
        }
    ],
    "sg:phone":"+61 2 4229 9466",
    "sg:postcode":"2500",
    "sg:province":"NSW",
    "sg:tags":[
        "medical",
        "practitioner"
    ],
    "wof:name":"Stanton Arthur",
    "wof:placetype":"venue"
},
  "geometry": {"coordinates":[150.88490300000001,-34.42461],"type":"Point"}
}