{
  "type": "Feature",
  "properties": {
    "addr:full":"96 Chum St Bendigo VIC 3550",
    "addr:housenumber":"96",
    "addr:postcode":"3550",
    "addr:street":"Chum St",
    "iso:country":"AU",
    "sg:address":"96 Chum St",
    "sg:city":"Bendigo",
    "sg:classifiers":[
        {
            "category":"Home & Garden",
            "subcategory":"Carpets & Floor Coverings",
            "type":"Retail Goods"
        }
    ],
    "sg:phone":"+61 3 5443 2022",
    "sg:postcode":"3550",
    "sg:province":"VIC",
    "sg:tags":[
        "layer",
        "planner"
    ],
    "wof:name":"Mahon G R",
    "wof:placetype":"venue"
},
  "geometry": {"coordinates":[144.250396728,-36.7636756897],"type":"Point"}
}