{
  "type": "Feature",
  "properties": {
    "addr:full":"114 Victoria St New Lambton NSW 2305",
    "addr:housenumber":"114",
    "addr:postcode":"2305",
    "addr:street":"Victoria St",
    "iso:country":"AU",
    "sg:address":"114 Victoria St",
    "sg:city":"New Lambton",
    "sg:classifiers":[
        {
            "category":"Health Services",
            "subcategory":"Health Practitioner",
            "type":"Services"
        }
    ],
    "sg:phone":"+61 2 4957 4031",
    "sg:postcode":"2305",
    "sg:province":"NSW",
    "sg:tags":[
        "pathologist",
        "speech"
    ],
    "wof:name":"Cathrine Hart",
    "wof:placetype":"venue"
},
  "geometry": {"coordinates":[151.71028100000001,-32.923531],"type":"Point"}
}