{
  "type": "Feature",
  "properties": {
    "iso:country":"AU",
    "sg:address":"Shop 5/ 621 Ocean Drv",
    "sg:city":"North Haven",
    "sg:classifiers":[
        {
            "category":"Personal",
            "subcategory":"Beauty Salon",
            "type":"Services"
        }
    ],
    "sg:phone":"+61 2 6559 6677",
    "sg:postcode":"2443",
    "sg:province":"NSW",
    "sg:tags":[
        "hairdresser"
    ],
    "wof:name":"Dolphin Cove Hair Studio",
    "wof:placetype":"venue"
},
  "geometry": {"coordinates":[152.81720000000001,-31.639902],"type":"Point"}
}