{
  "type": "Feature",
  "properties": {
    "addr:full":"87 Belmont Ave Belmont WA 6104",
    "addr:housenumber":"87",
    "addr:postcode":"6104",
    "addr:street":"Belmont Ave",
    "iso:country":"AU",
    "sg:address":"87 Belmont Ave",
    "sg:city":"Belmont",
    "sg:classifiers":[
        {
            "category":"Wholesale",
            "subcategory":"Auto Parts",
            "type":"Manufacturing & Wholesale Goods"
        }
    ],
    "sg:phone":"+61 8 9479 6141",
    "sg:postcode":"6104",
    "sg:province":"WA",
    "sg:tags":[
        "tyre"
    ],
    "wof:name":"Getagrip Tyres Pty Ltd",
    "wof:placetype":"venue"
},
  "geometry": {"coordinates":[115.924049377,-31.9575443268],"type":"Point"}
}