{
  "type": "Feature",
  "properties": {
    "addr:full":"33 Beaver St Clifton Beach QLD 4879",
    "addr:housenumber":"33",
    "addr:postcode":"4879",
    "addr:street":"Beaver St",
    "iso:country":"AU",
    "sg:address":"33 Beaver St",
    "sg:city":"Clifton Beach",
    "sg:classifiers":[
        {
            "category":"Shopping",
            "subcategory":"Stationery & Office Supplies",
            "type":"Retail Goods"
        }
    ],
    "sg:phone":"+61 7 4059 1717",
    "sg:postcode":"4879",
    "sg:province":"QLD",
    "sg:tags":[
        "equipment",
        "sailboarding"
    ],
    "wof:name":"Briggs Peter",
    "wof:placetype":"venue"
},
  "geometry": {"coordinates":[145.67228698700001,-16.7654304504],"type":"Point"}
}