{
  "type": "Feature",
  "properties": {
    "iso:country":"AU",
    "sg:address":"6 Cecil St",
    "sg:city":"Monterey",
    "sg:classifiers":[
        {
            "category":"Building & Trades",
            "subcategory":"Pest Control",
            "type":"Services"
        }
    ],
    "sg:phone":"+61 2 9593 2019",
    "sg:postcode":"2217",
    "sg:province":"NSW",
    "wof:name":"Peter Fisher Pest Control",
    "wof:placetype":"venue"
},
  "geometry": {"coordinates":[151.150238,-33.968174],"type":"Point"}
}