{
  "type": "Feature",
  "properties": {
    "iso:country":"AU",
    "sg:address":"32 Lisgar St",
    "sg:city":"Granville",
    "sg:classifiers":[
        {
            "category":"Building & Trades",
            "subcategory":"Plumbing",
            "type":"Services"
        }
    ],
    "sg:phone":"+61 409 460 994",
    "sg:postcode":"2142",
    "sg:province":"NSW",
    "sg:tags":[
        "plumber",
        "gasfitters"
    ],
    "wof:name":"S.D.A. Plumbing",
    "wof:placetype":"venue"
},
  "geometry": {"coordinates":[151.00680542000001,-33.8463058472],"type":"Point"}
}