{
  "type": "Feature",
  "properties": {
    "iso:country":"AU",
    "sg:address":"14 Inman Rd",
    "sg:city":"Dee Why",
    "sg:classifiers":[
        {
            "category":"Manufacturing",
            "subcategory":"Electronics",
            "type":"Manufacturing & Wholesale Goods"
        }
    ],
    "sg:phone":"+61 2 9982 7663",
    "sg:postcode":"2099",
    "sg:province":"NSW",
    "sg:tags":[
        "equipment",
        "supply"
    ],
    "wof:name":"Mentor Fabrications Pty Ltd",
    "wof:placetype":"venue"
},
  "geometry": {"coordinates":[151.28663635300001,-33.7362365723],"type":"Point"}
}