{
  "type": "Feature",
  "properties": {
    "iso:country":"AU",
    "sg:address":"116 Russell St",
    "sg:city":"Toowoomba",
    "sg:classifiers":[
        {
            "category":"Health Services",
            "subcategory":"Doctor",
            "type":"Services"
        }
    ],
    "sg:phone":"+61 7 4632 9030",
    "sg:postcode":"4350",
    "sg:province":"QLD",
    "sg:tags":[
        "medical",
        "practitioner"
    ],
    "wof:name":"van Gend David",
    "wof:placetype":"venue"
},
  "geometry": {"coordinates":[151.94828799999999,-27.558418],"type":"Point"}
}