{
  "type": "Feature",
  "properties": {
    "iso:country":"AU",
    "sg:address":"1197 Riversdale Rd",
    "sg:city":"Box Hill South",
    "sg:classifiers":[
        {
            "category":"Health Services",
            "subcategory":"Health Practitioner",
            "type":"Services"
        }
    ],
    "sg:phone":"+61 3 9808 8657",
    "sg:postcode":"3128",
    "sg:province":"VIC",
    "sg:tags":[
        "psychologist"
    ],
    "wof:name":"Cantwell Peter Dr",
    "wof:placetype":"venue"
},
  "geometry": {"coordinates":[145.117431641,-37.8380661011],"type":"Point"}
}