{
  "type": "Feature",
  "properties": {
    "iso:country":"AU",
    "sg:address":"16 Francesco Drv",
    "sg:city":"Dandenong North",
    "sg:classifiers":[
        {
            "category":"Building & Trades",
            "subcategory":"Cleaning & Sanitation",
            "type":"Services"
        }
    ],
    "sg:phone":"+61 413 246 388",
    "sg:postcode":"3175",
    "sg:province":"VIC",
    "sg:tags":[
        "sweeping",
        "machine"
    ],
    "wof:name":"Sweepmobile",
    "wof:placetype":"venue"
},
  "geometry": {"coordinates":[145.21795654300001,-37.9489059448],"type":"Point"}
}