{
  "type": "Feature",
  "properties": {
    "iso:country":"AU",
    "sg:address":"14- 16",
    "sg:city":"The Concourse Cowes",
    "sg:classifiers":[
        {
            "category":"Manufacturing",
            "subcategory":"Metals",
            "type":"Manufacturing & Wholesale Goods"
        }
    ],
    "sg:phone":"+61 3 5952 1432",
    "sg:postcode":"3922",
    "sg:province":"VIC",
    "sg:tags":[
        "steel",
        "fabricator",
        "mfrs"
    ],
    "wof:name":"Island Steel",
    "wof:placetype":"venue"
},
  "geometry": {"coordinates":[145.25047302199999,-38.4572143555],"type":"Point"}
}