{
  "type": "Feature",
  "properties": {
    "addr:full":"56 Taylor St Epsom VIC 3551",
    "addr:housenumber":"56",
    "addr:postcode":"3551",
    "addr:street":"Taylor St",
    "iso:country":"AU",
    "sg:address":"56 Taylor St",
    "sg:city":"Epsom",
    "sg:classifiers":[
        {
            "category":"Manufacturing",
            "subcategory":"Pottery",
            "type":"Manufacturing & Wholesale Goods"
        }
    ],
    "sg:phone":"+61 3 5448 4702",
    "sg:postcode":"3551",
    "sg:province":"VIC",
    "wof:name":"Potters Arms",
    "wof:placetype":"venue"
},
  "geometry": {"coordinates":[144.32119750999999,-36.7122688293],"type":"Point"}
}