{
  "type": "Feature",
  "properties": {
    "iso:country":"AU",
    "sg:address":"137 Westall Rd",
    "sg:city":"Clayton South",
    "sg:classifiers":[
        {
            "category":"Wholesale",
            "subcategory":"Auto Parts",
            "type":"Manufacturing & Wholesale Goods"
        }
    ],
    "sg:phone":"+61 3 9558 5346",
    "sg:postcode":"3169",
    "sg:province":"VIC",
    "sg:tags":[
        "recyclers"
    ],
    "wof:name":"A All Lazer Maz Spares",
    "wof:placetype":"venue"
},
  "geometry": {"coordinates":[145.137817383,-37.9515304565],"type":"Point"}
}