{
  "type": "Feature",
  "properties": {
    "addr:full":"487 Mitcham Rd Mitcham VIC 3132",
    "addr:housenumber":"487",
    "addr:postcode":"3132",
    "addr:street":"Mitcham Rd",
    "iso:country":"AU",
    "sg:address":"487 Mitcham Rd",
    "sg:city":"Mitcham",
    "sg:classifiers":[
        {
            "category":"Health Services",
            "subcategory":"Doctor",
            "type":"Services"
        }
    ],
    "sg:phone":"+61 3 9873 4143",
    "sg:postcode":"3132",
    "sg:province":"VIC",
    "sg:tags":[
        "medical",
        "practitioner"
    ],
    "wof:name":"Rangeview Medical Surgery & Acupuncture Centre",
    "wof:placetype":"venue"
},
  "geometry": {"coordinates":[145.19480895999999,-37.8280448914],"type":"Point"}
}