{
  "type": "Feature",
  "properties": {
    "addr:full":"107 Graham Drv Sandy Beach NSW 2456",
    "addr:housenumber":"107",
    "addr:postcode":"2456",
    "addr:street":"Graham Drv",
    "iso:country":"AU",
    "sg:address":"107 Graham Drv",
    "sg:city":"Sandy Beach",
    "sg:classifiers":[
        {
            "category":"Professional",
            "subcategory":"Art Services",
            "type":"Services"
        }
    ],
    "sg:phone":"+61 2 6656 2083",
    "sg:postcode":"2456",
    "sg:province":"NSW",
    "sg:tags":[
        "decorator",
        "painter"
    ],
    "wof:name":"Peters G",
    "wof:placetype":"venue"
},
  "geometry": {"coordinates":[153.18615700000001,-30.151886],"type":"Point"}
}