{
  "type": "Feature",
  "properties": {
    "addr:full":"6 Loder St Atherton QLD 4883",
    "addr:housenumber":"6",
    "addr:postcode":"4883",
    "addr:street":"Loder St",
    "iso:country":"AU",
    "sg:address":"6 Loder St",
    "sg:city":"Atherton",
    "sg:classifiers":[
        {
            "category":"Arena",
            "subcategory":"Sports Club",
            "type":"Entertainment"
        }
    ],
    "sg:phone":"+61 7 4091 4256",
    "sg:postcode":"4883",
    "sg:province":"QLD",
    "sg:tags":[
        "tour",
        "holiday"
    ],
    "wof:name":"Toyne's Golf Tours",
    "wof:placetype":"venue"
},
  "geometry": {"coordinates":[145.47372436500001,-17.2733001709],"type":"Point"}
}