{
  "type": "Feature",
  "properties": {
    "iso:country":"AU",
    "sg:address":"Suite 1/ 14 Salmon St",
    "sg:city":"Port Melbourne",
    "sg:classifiers":[
        {
            "category":"Retail",
            "subcategory":"Event Space",
            "type":"Services"
        }
    ],
    "sg:phone":"+61 3 9646 3888",
    "sg:postcode":"3207",
    "sg:province":"VIC",
    "sg:tags":[
        "function",
        "organiser"
    ],
    "wof:name":"Republic Events",
    "wof:placetype":"venue"
},
  "geometry": {"coordinates":[144.925125,-37.834881],"type":"Point"}
}