{
  "type": "Feature",
  "properties": {
    "iso:country":"AU",
    "sg:address":"357 Glenmore Rd",
    "sg:city":"Paddington",
    "sg:classifiers":[
        {
            "category":"Personal",
            "subcategory":"Day Spa",
            "type":"Services"
        }
    ],
    "sg:phone":"+61 2 9331 7933",
    "sg:postcode":"2021",
    "sg:province":"NSW",
    "wof:name":"Milk Day Spa",
    "wof:placetype":"venue"
},
  "geometry": {"coordinates":[151.232025147,-33.8805389404],"type":"Point"}
}