{
  "type": "Feature",
  "properties": {
    "addr:full":"16 Mt Ninderry Crt Coolum Beach QLD 4573",
    "addr:housenumber":"16",
    "addr:postcode":"4573",
    "addr:street":"Mt Ninderry Crt",
    "iso:country":"AU",
    "sg:address":"16 Mt Ninderry Crt",
    "sg:city":"Coolum Beach",
    "sg:classifiers":[
        {
            "category":"Building & Trades",
            "subcategory":"Landscaping Services",
            "type":"Services"
        }
    ],
    "sg:phone":"+61 404 031 194",
    "sg:postcode":"4573",
    "sg:province":"QLD",
    "sg:tags":[
        "stump",
        "tree",
        "felling",
        "removal"
    ],
    "wof:name":"Craig Hawkins Tree Climbing",
    "wof:placetype":"venue"
},
  "geometry": {"coordinates":[153.086838,-26.537987],"type":"Point"}
}