{
  "type": "Feature",
  "properties": {
    "iso:country":"AU",
    "sg:address":"21 Dobney Ave",
    "sg:city":"Wagga Wagga",
    "sg:classifiers":[
        {
            "category":"Structure",
            "subcategory":"Bridge",
            "type":"Public Place"
        }
    ],
    "sg:phone":"+61 2 6925 1642",
    "sg:postcode":"2650",
    "sg:province":"NSW",
    "sg:tags":[
        "chainsaw",
        "brushcutters"
    ],
    "wof:name":"Judds Engineering Pty Ltd",
    "wof:placetype":"venue"
},
  "geometry": {"coordinates":[147.34776306099999,-35.1177101135],"type":"Point"}
}