{
  "type": "Feature",
  "properties": {
    "iso:country":"AU",
    "sg:address":"2/ 15 Pattie St",
    "sg:city":"Cannington",
    "sg:classifiers":[
        {
            "category":"Banks & Credit Unions",
            "subcategory":"Financial Services",
            "type":"Services"
        }
    ],
    "sg:phone":"+61 8 9458 6022",
    "sg:postcode":"6107",
    "sg:province":"WA",
    "sg:tags":[
        "settlement",
        "nt",
        "agent",
        "wa"
    ],
    "wof:name":"Castle Settlements",
    "wof:placetype":"venue"
},
  "geometry": {"coordinates":[115.936401367,-32.0159492493],"type":"Point"}
}