{
  "type": "Feature",
  "properties": {
    "iso:country":"AU",
    "sg:address":"19b Charlotte St",
    "sg:city":"Ashfield",
    "sg:classifiers":[
        {
            "category":"Shopping",
            "subcategory":"Clothing, Apparel, & Fashions",
            "type":"Retail Goods"
        }
    ],
    "sg:phone":"+61 2 9799 6933",
    "sg:postcode":"2131",
    "sg:province":"NSW",
    "sg:tags":[
        "recycled",
        "clothing"
    ],
    "wof:name":"After-a-Fashion",
    "wof:placetype":"venue"
},
  "geometry": {"coordinates":[151.12591552699999,-33.8869132996],"type":"Point"}
}