{
  "type": "Feature",
  "properties": {
    "addr:full":"12 Thelma Ave Biggera Waters QLD 4216",
    "addr:housenumber":"12",
    "addr:postcode":"4216",
    "addr:street":"Thelma Ave",
    "iso:country":"AU",
    "sg:address":"12 Thelma Ave",
    "sg:city":"Biggera Waters",
    "sg:classifiers":[
        {
            "category":"Health Services",
            "subcategory":"Health Practitioner",
            "type":"Services"
        }
    ],
    "sg:phone":"+61 7 5563 9739",
    "sg:postcode":"4216",
    "sg:province":"QLD",
    "sg:tags":[
        "psychologist"
    ],
    "wof:name":"Peter Phillips",
    "wof:placetype":"venue"
},
  "geometry": {"coordinates":[153.39930725100001,-27.933681488],"type":"Point"}
}