{
  "type": "Feature",
  "properties": {
    "iso:country":"AU",
    "sg:address":"429 Elizabeth St",
    "sg:city":"Sydney",
    "sg:classifiers":[
        {
            "category":"Wholesale",
            "subcategory":"Apparel",
            "type":"Manufacturing & Wholesale Goods"
        }
    ],
    "sg:phone":"+61 2 9281 9409",
    "sg:postcode":"2000",
    "sg:province":"NSW",
    "sg:tags":[
        "wholesaler",
        "mfrs",
        "cap",
        "hat"
    ],
    "wof:name":"Hills Wholesale",
    "wof:placetype":"venue"
},
  "geometry": {"coordinates":[151.209075928,-33.8787574768],"type":"Point"}
}