{
  "type": "Feature",
  "properties": {
    "addr:full":"9- 11 Malua St Reservoir VIC 3073",
    "addr:housenumber":"11",
    "addr:postcode":"3073",
    "addr:street":"9;St",
    "iso:country":"AU",
    "sg:address":"9- 11 Malua St",
    "sg:city":"Reservoir",
    "sg:classifiers":[
        {
            "category":"Shopping",
            "subcategory":"Stationery & Office Supplies",
            "type":"Retail Goods"
        }
    ],
    "sg:phone":"+61 3 9462 2011",
    "sg:postcode":"3073",
    "sg:province":"VIC",
    "sg:tags":[
        "packaging",
        "material"
    ],
    "wof:name":"Plastic Technology Pty Ltd",
    "wof:placetype":"venue"
},
  "geometry": {"coordinates":[144.98223876899999,-37.7186050415],"type":"Point"}
}