{
  "type": "Feature",
  "properties": {
    "addr:full":"182 Johnston St Fitzroy VIC 3065",
    "addr:housenumber":"182",
    "addr:postcode":"3065",
    "addr:street":"Johnston St",
    "iso:country":"AU",
    "sg:address":"182 Johnston St",
    "sg:city":"Fitzroy",
    "sg:classifiers":[
        {
            "category":"Manufacturing",
            "subcategory":"Furniture",
            "type":"Manufacturing & Wholesale Goods"
        }
    ],
    "sg:phone":"+61 3 9419 2422",
    "sg:postcode":"3065",
    "sg:province":"VIC",
    "sg:tags":[
        "builder",
        "designer",
        "custom"
    ],
    "wof:name":"Sacha Design",
    "wof:placetype":"venue"
},
  "geometry": {"coordinates":[144.981033325,-37.7987213135],"type":"Point"}
}