{
  "type": "Feature",
  "properties": {
    "addr:full":"147 Fryers St Shepparton VIC 3630",
    "addr:housenumber":"147",
    "addr:postcode":"3630",
    "addr:street":"Fryers St",
    "iso:country":"AU",
    "sg:address":"147 Fryers St",
    "sg:city":"Shepparton",
    "sg:classifiers":[
        {
            "category":"Personal",
            "subcategory":"Piercing",
            "type":"Services"
        }
    ],
    "sg:phone":"+61 3 5831 8027",
    "sg:postcode":"3630",
    "sg:province":"VIC",
    "sg:tags":[
        "body",
        "ear"
    ],
    "wof:name":"Perfect Circle Tattooing",
    "wof:placetype":"venue"
},
  "geometry": {"coordinates":[145.40348815900001,-36.3792915344],"type":"Point"}
}