{
  "type": "Feature",
  "properties": {
    "addr:full":"32 Plume St Norlane VIC 3214",
    "addr:housenumber":"32",
    "addr:postcode":"3214",
    "addr:street":"Plume St",
    "iso:country":"AU",
    "sg:address":"32 Plume St",
    "sg:city":"Norlane",
    "sg:classifiers":[
        {
            "category":"Social Services",
            "subcategory":"Child Care",
            "type":"Services"
        }
    ],
    "sg:phone":"+61 3 5272 1375",
    "sg:postcode":"3214",
    "sg:province":"VIC",
    "sg:tags":[
        "support",
        "health"
    ],
    "wof:name":"Norlane",
    "wof:placetype":"venue"
},
  "geometry": {"coordinates":[144.35919189399999,-38.0926055908],"type":"Point"}
}