{
  "type": "Feature",
  "properties": {
    "addr:full":"95 King William Rd Unley SA 5061",
    "addr:housenumber":"95",
    "addr:postcode":"5061",
    "addr:street":"King William Rd",
    "iso:country":"AU",
    "sg:address":"95 King William Rd",
    "sg:city":"Unley",
    "sg:classifiers":[
        {
            "category":"Health Services",
            "subcategory":"Health Practitioner",
            "type":"Services"
        }
    ],
    "sg:phone":"+61 8 8357 8577",
    "sg:postcode":"5061",
    "sg:province":"SA",
    "sg:tags":[
        "physiotherapist"
    ],
    "wof:name":"Headache Clinic",
    "wof:placetype":"venue"
},
  "geometry": {"coordinates":[138.60028076200001,-34.9555053711],"type":"Point"}
}