{
  "type": "Feature",
  "properties": {
    "iso:country":"AU",
    "sg:address":"RMB 7163",
    "sg:city":"Horsham",
    "sg:classifiers":[
        {
            "category":"Community Center",
            "subcategory":"Social",
            "type":"Public Place"
        }
    ],
    "sg:phone":"+61 409 445 021",
    "sg:postcode":"3400",
    "sg:province":"VIC",
    "sg:tags":[
        "precision",
        "grinding"
    ],
    "wof:name":"McTees Mobile Reel Grinding Service",
    "wof:placetype":"venue"
},
  "geometry": {"coordinates":[142.19619750999999,-36.7172393799],"type":"Point"}
}