{
  "type": "Feature",
  "properties": {
    "addr:full":"342 Thomas La Broken Hill NSW 2880",
    "addr:housenumber":"342",
    "addr:postcode":"2880",
    "addr:street":"Thomas La",
    "iso:country":"AU",
    "sg:address":"342 Thomas La",
    "sg:city":"Broken Hill",
    "sg:classifiers":[
        {
            "category":"Building & Trades",
            "subcategory":"Plumbing",
            "type":"Services"
        }
    ],
    "sg:phone":"+61 8 8088 3733",
    "sg:postcode":"2880",
    "sg:province":"NSW",
    "sg:tags":[
        "plumber",
        "gasfitters"
    ],
    "wof:name":"Andrew Gould Plumbing",
    "wof:placetype":"venue"
},
  "geometry": {"coordinates":[141.48599243199999,-31.944442749],"type":"Point"}
}