{
  "type": "Feature",
  "properties": {
    "iso:country":"AU",
    "sg:address":"40 Radford Road (cnr Parer)",
    "sg:city":"Reservoir",
    "sg:classifiers":[
        {
            "category":"Shopping",
            "subcategory":"Crafts & Fabrics",
            "type":"Retail Goods"
        }
    ],
    "sg:phone":"+61 3 9478 4257",
    "sg:postcode":"3073",
    "sg:province":"VIC",
    "sg:tags":[
        "synthetic",
        "canvas",
        "product"
    ],
    "wof:name":"O'Briens Caravan Annexes & Canvas Goods",
    "wof:placetype":"venue"
},
  "geometry": {"coordinates":[145.005584717,-37.7278137207],"type":"Point"}
}