{
  "type": "Feature",
  "properties": {
    "iso:country":"AU",
    "sg:address":"7- 11 Beardsworth Ave",
    "sg:city":"Chelsea",
    "sg:classifiers":[
        {
            "category":"Travel",
            "subcategory":"Hostel",
            "type":"Entertainment"
        }
    ],
    "sg:phone":"+61 3 9776 1111",
    "sg:postcode":"3196",
    "sg:province":"VIC",
    "sg:tags":[
        "home"
    ],
    "wof:name":"Chelsea Manor",
    "wof:placetype":"venue"
},
  "geometry": {"coordinates":[145.122955322,-38.0489959717],"type":"Point"}
}