{
  "type": "Feature",
  "properties": {
    "addr:full":"59 Forrester Rd St Marys NSW 2760",
    "addr:housenumber":"59",
    "addr:postcode":"2760",
    "addr:street":"Forrester Rd",
    "iso:country":"AU",
    "sg:address":"59 Forrester Rd",
    "sg:city":"St Marys",
    "sg:classifiers":[
        {
            "category":"Manufacturing",
            "subcategory":"Rubber & Plastics",
            "type":"Manufacturing & Wholesale Goods"
        }
    ],
    "sg:phone":"+61 2 9673 2007",
    "sg:postcode":"2760",
    "sg:province":"NSW",
    "sg:tags":[
        "moulders"
    ],
    "wof:name":"Pacific Plastics Pty Ltd",
    "wof:placetype":"venue"
},
  "geometry": {"coordinates":[150.77517700199999,-33.7609939575],"type":"Point"}
}