{
  "type": "Feature",
  "properties": {
    "addr:full":"Gwen Hardie Lodge Mermaid Ave Albany WA 6330",
    "addr:postcode":"6330",
    "addr:street":"Mermaid Ave",
    "iso:country":"AU",
    "sg:address":"Gwen Hardie Lodge Mermaid Ave",
    "sg:city":"Albany",
    "sg:classifiers":[
        {
            "category":"Health Services",
            "subcategory":"Doctor",
            "type":"Services"
        }
    ],
    "sg:phone":"+61 8 9844 1105",
    "sg:postcode":"6330",
    "sg:province":"WA",
    "sg:tags":[
        "nurse",
        "nursing"
    ],
    "wof:name":"Silver Chain",
    "wof:placetype":"venue"
},
  "geometry": {"coordinates":[117.941429138,-34.9973983765],"type":"Point"}
}