{
  "type": "Feature",
  "properties": {
    "addr:full":"78 Williams Rd Prahran VIC 3181",
    "addr:housenumber":"78",
    "addr:postcode":"3181",
    "addr:street":"Williams Rd",
    "iso:country":"AU",
    "sg:address":"78 Williams Rd",
    "sg:city":"Prahran",
    "sg:classifiers":[
        {
            "category":"Restaurant",
            "type":"Food & Drink"
        }
    ],
    "sg:phone":"+61 3 9525 2178",
    "sg:postcode":"3181",
    "sg:province":"VIC",
    "wof:name":"Jacques Reymond Restaurant",
    "wof:placetype":"venue"
},
  "geometry": {"coordinates":[145.00250244099999,-37.8537521362],"type":"Point"}
}