{
  "type": "Feature",
  "properties": {
    "addr:full":"2/ 203 Clarence St Sydney NSW 2000",
    "addr:housenumber":"/ 203",
    "addr:postcode":"2000",
    "addr:street":"Clarence St",
    "iso:country":"AU",
    "sg:address":"2/ 203 Clarence St",
    "sg:city":"Sydney",
    "sg:classifiers":[
        {
            "category":"Arts & Performance",
            "subcategory":"Art Gallery",
            "type":"Entertainment"
        }
    ],
    "sg:phone":"+61 2 9262 4170",
    "sg:postcode":"2000",
    "sg:province":"NSW",
    "wof:name":"Pendulum Gallery",
    "wof:placetype":"venue"
},
  "geometry": {"coordinates":[151.205245972,-33.8696708679],"type":"Point"}
}