{
  "type": "Feature",
  "properties": {
    "addr:full":"5 Halley Rd Balcatta WA 6021",
    "addr:housenumber":"5",
    "addr:postcode":"6021",
    "addr:street":"Halley Rd",
    "iso:country":"AU",
    "sg:address":"5 Halley Rd",
    "sg:city":"Balcatta",
    "sg:classifiers":[
        {
            "category":"Manufacturing",
            "subcategory":"Metals",
            "type":"Manufacturing & Wholesale Goods"
        }
    ],
    "sg:phone":"+61 8 9344 2220",
    "sg:postcode":"6021",
    "sg:province":"WA",
    "sg:tags":[
        "steel",
        "fabricator",
        "mfrs"
    ],
    "wof:name":"Fabricon Steel Fabricators",
    "wof:placetype":"venue"
},
  "geometry": {"coordinates":[115.823181152,-31.8613948822],"type":"Point"}
}