{
  "type": "Feature",
  "properties": {
    "iso:country":"AU",
    "sg:address":"65 Denison St",
    "sg:city":"Carrington",
    "sg:classifiers":[
        {
            "category":"Professional",
            "type":"Services"
        }
    ],
    "sg:phone":"+61 2 4962 4803",
    "sg:postcode":"2294",
    "sg:province":"NSW",
    "sg:tags":[
        "shop",
        "fitting"
    ],
    "wof:name":"Australian DisplayWall Industries",
    "wof:placetype":"venue"
},
  "geometry": {"coordinates":[151.76504516599999,-32.918548584],"type":"Point"}
}