{
  "type": "Feature",
  "properties": {
    "addr:full":"Shop 5 , Sturt Mall Wagga Wagga NSW 2650",
    "addr:housenumber":"shop 5",
    "addr:postcode":"2650",
    "addr:street":"Sturt Mall",
    "iso:country":"AU",
    "sg:address":"Shop 5",
    "sg:city":", Sturt Mall Wagga Wagga",
    "sg:classifiers":[
        {
            "category":"Shopping",
            "subcategory":"Jewelry",
            "type":"Retail Goods"
        }
    ],
    "sg:phone":"+61 2 6921 3369",
    "sg:postcode":"2650",
    "sg:province":"NSW",
    "sg:tags":[
        "jeweller"
    ],
    "wof:name":"Diamonds on Baylis",
    "wof:placetype":"venue"
},
  "geometry": {"coordinates":[147.37083435100001,-35.1054801941],"type":"Point"}
}