{
  "type": "Feature",
  "properties": {
    "iso:country":"AU",
    "sg:address":"Shop 5/ 18 Coldstream St",
    "sg:city":"Yamba",
    "sg:classifiers":[
        {
            "category":"Professional",
            "subcategory":"Computer Services",
            "type":"Services"
        }
    ],
    "sg:phone":"+61 2 6646 8912",
    "sg:postcode":"2464",
    "sg:province":"NSW",
    "sg:tags":[
        "repairs",
        "upgrade",
        "equipment"
    ],
    "wof:name":"Yamcom",
    "wof:placetype":"venue"
},
  "geometry": {"coordinates":[153.360473633,-29.437046051],"type":"Point"}
}