{
  "type": "Feature",
  "properties": {
    "addr:full":"1st Floor, Karalta Plaza Karalta Rd Erina NSW 2250",
    "addr:postcode":"2250",
    "addr:street":"Karalta Rd",
    "iso:country":"AU",
    "sg:address":"1st Floor, Karalta Plaza Karalta Rd",
    "sg:city":"Erina",
    "sg:classifiers":[
        {
            "category":"Professional",
            "subcategory":"Accounting & Tax Preparation",
            "type":"Services"
        }
    ],
    "sg:phone":"+61 2 4365 3838",
    "sg:postcode":"2250",
    "sg:province":"NSW",
    "sg:tags":[
        "consultant",
        "taxation"
    ],
    "wof:name":"Herford Max & Co",
    "wof:placetype":"venue"
},
  "geometry": {"coordinates":[151.39375305199999,-33.4400520325],"type":"Point"}
}