{
  "type": "Feature",
  "properties": {
    "addr:full":"PO Box 1421 Mona Vale NSW 1660",
    "addr:postcode":"1660",
    "iso:country":"AU",
    "sg:address":"PO Box 1421",
    "sg:city":"Mona Vale",
    "sg:classifiers":[
        {
            "category":"Government",
            "subcategory":"Customs House",
            "type":"Public Place"
        }
    ],
    "sg:phone":"+61 2 9940 0508",
    "sg:postcode":"1660",
    "sg:province":"NSW",
    "sg:tags":[
        "title",
        "management",
        "stratum"
    ],
    "wof:name":"Northside Strata",
    "wof:placetype":"venue"
},
  "geometry": {"coordinates":[151.303222656,-33.6786308289],"type":"Point"}
}