{
  "type": "Feature",
  "properties": {
    "iso:country":"AU",
    "sg:address":"17 Bilmark Pl",
    "sg:city":"Brighton-le-Sands",
    "sg:classifiers":[
        {
            "category":"Building & Trades",
            "subcategory":"Construction",
            "type":"Services"
        }
    ],
    "sg:phone":"+61 421 519 503",
    "sg:postcode":"2216",
    "sg:province":"NSW",
    "sg:tags":[
        "polishing",
        "sanding",
        "floor"
    ],
    "wof:name":"Envirosand",
    "wof:placetype":"venue"
},
  "geometry": {"coordinates":[151.15535,-33.95166],"type":"Point"}
}