{
  "type": "Feature",
  "properties": {
    "addr:full":"18 Napoleon St Cottesloe WA 6011",
    "addr:housenumber":"18",
    "addr:postcode":"6011",
    "addr:street":"Napoleon St",
    "iso:country":"AU",
    "sg:address":"18 Napoleon St",
    "sg:city":"Cottesloe",
    "sg:classifiers":[
        {
            "category":"Manufacturing",
            "subcategory":"Jewelry",
            "type":"Manufacturing & Wholesale Goods"
        }
    ],
    "sg:phone":"+61 8 9385 5330",
    "sg:postcode":"6011",
    "sg:province":"WA",
    "sg:tags":[
        "mfrg",
        "jeweller"
    ],
    "wof:name":"Scagnetti Jewels",
    "wof:placetype":"venue"
},
  "geometry": {"coordinates":[115.76183319099999,-31.9977741241],"type":"Point"}
}