{
  "type": "Feature",
  "properties": {
    "addr:full":"Suite 2, Windemere Shopping Centre, 48 Goggs Rd Jindalee QLD 4074",
    "addr:housenumber":"48",
    "addr:postcode":"4074",
    "addr:street":"Goggs Rd",
    "iso:country":"AU",
    "sg:address":"Suite 2, Windemere Shopping Centre, 48 Goggs Rd",
    "sg:city":"Jindalee",
    "sg:classifiers":[
        {
            "category":"Health Services",
            "subcategory":"Dentist",
            "type":"Services"
        }
    ],
    "sg:phone":"+61 7 3376 2651",
    "sg:postcode":"4074",
    "sg:province":"QLD",
    "sg:tags":[
        "qld",
        "orthodontist"
    ],
    "wof:name":"Inline Orthodontics",
    "wof:placetype":"venue"
},
  "geometry": {"coordinates":[152.94964599599999,-27.5341205597],"type":"Point"}
}