{
  "type": "Feature",
  "properties": {
    "iso:country":"AU",
    "sg:address":"1216 Pipers Brook Rd",
    "sg:city":"Pipers Brook",
    "sg:classifiers":[
        {
            "category":"Farming",
            "subcategory":"Vineyard",
            "type":"Manufacturing & Wholesale Goods"
        }
    ],
    "sg:phone":"+61 3 6382 7527",
    "sg:postcode":"7254",
    "sg:province":"TAS",
    "sg:tags":[
        "winery"
    ],
    "wof:name":"Pipers Brook Vineyard",
    "wof:placetype":"venue"
},
  "geometry": {"coordinates":[147.18307495100001,-41.0650634766],"type":"Point"}
}