{
  "type": "Feature",
  "properties": {
    "addr:full":"21 Bridge St Murray Bridge SA 5253",
    "addr:housenumber":"21",
    "addr:postcode":"5253",
    "addr:street":"Bridge St",
    "iso:country":"AU",
    "sg:address":"21 Bridge St",
    "sg:city":"Murray Bridge",
    "sg:classifiers":[
        {
            "category":"Personal",
            "subcategory":"Barber",
            "type":"Services"
        }
    ],
    "sg:phone":"+61 8 8532 1679",
    "sg:postcode":"5253",
    "sg:province":"SA",
    "wof:name":"Hair For Him",
    "wof:placetype":"venue"
},
  "geometry": {"coordinates":[139.27622985799999,-35.1184196472],"type":"Point"}
}