{
  "type": "Feature",
  "properties": {
    "iso:country":"AU",
    "sg:address":"61 Argyle St",
    "sg:city":"Camden",
    "sg:classifiers":[
        {
            "category":"Health Services",
            "subcategory":"Optometrist",
            "type":"Services"
        }
    ],
    "sg:phone":"+61 2 4655 2944",
    "sg:postcode":"2570",
    "sg:province":"NSW",
    "sg:website":"http://www.oaansw.com.au",
    "wof:name":"Rod Tracey Optometrists",
    "wof:placetype":"venue"
},
  "geometry": {"coordinates":[150.697189331,-34.0537796021],"type":"Point"}
}