{
  "type": "Feature",
  "properties": {
    "addr:full":"PO Box 5048 Empire Bay NSW 2257",
    "addr:postcode":"2257",
    "iso:country":"AU",
    "sg:address":"PO Box 5048",
    "sg:city":"Empire Bay",
    "sg:classifiers":[
        {
            "category":"Recreation",
            "subcategory":"Boat Charter",
            "type":"Entertainment"
        }
    ],
    "sg:phone":"+61 2 4363 1311",
    "sg:postcode":"2257",
    "sg:province":"NSW",
    "wof:name":"Central Coast Ferries",
    "wof:placetype":"venue"
},
  "geometry": {"coordinates":[151.36109924300001,-33.4996299744],"type":"Point"}
}