{
  "type": "Feature",
  "properties": {
    "addr:full":"41 Malinya Rd Davistown NSW 2251",
    "addr:housenumber":"41",
    "addr:postcode":"2251",
    "addr:street":"Malinya Rd",
    "iso:country":"AU",
    "sg:address":"41 Malinya Rd",
    "sg:city":"Davistown",
    "sg:classifiers":[
        {
            "category":"Building & Trades",
            "subcategory":"Plumbing",
            "type":"Services"
        }
    ],
    "sg:phone":"+61 2 4363 1133",
    "sg:postcode":"2251",
    "sg:province":"NSW",
    "sg:tags":[
        "plumber",
        "gasfitters"
    ],
    "wof:name":"D.C.H. Plumbing",
    "wof:placetype":"venue"
},
  "geometry": {"coordinates":[151.354934692,-33.4850196838],"type":"Point"}
}