{
  "type": "Feature",
  "properties": {
    "addr:full":"33 Falmouth St Somerset TAS 7322",
    "addr:housenumber":"33",
    "addr:postcode":"7322",
    "addr:street":"Falmouth St",
    "iso:country":"AU",
    "sg:address":"33 Falmouth St",
    "sg:city":"Somerset",
    "sg:classifiers":[
        {
            "category":"Health Services",
            "subcategory":"Doctor",
            "type":"Services"
        }
    ],
    "sg:phone":"+61 3 6435 1421",
    "sg:postcode":"7322",
    "sg:province":"TAS",
    "sg:tags":[
        "medical",
        "practitioner"
    ],
    "wof:name":"Barnes N M",
    "wof:placetype":"venue"
},
  "geometry": {"coordinates":[145.833282,-41.041592],"type":"Point"}
}