{
  "type": "Feature",
  "properties": {
    "addr:full":"507 Coolamon Scenic Drv Coorabell NSW 2479",
    "addr:housenumber":"507",
    "addr:postcode":"2479",
    "addr:street":"Coolamon Scenic Drv",
    "iso:country":"AU",
    "sg:address":"507 Coolamon Scenic Drv",
    "sg:city":"Coorabell",
    "sg:classifiers":[
        {
            "category":"Building & Trades",
            "subcategory":"Construction",
            "type":"Services"
        }
    ],
    "sg:phone":"+61 2 6684 7381",
    "sg:postcode":"2479",
    "sg:province":"NSW",
    "sg:tags":[
        "renovation",
        "alterations",
        "extension",
        "contractor"
    ],
    "wof:name":"Lennox Building Services",
    "wof:placetype":"venue"
},
  "geometry": {"coordinates":[153.49717712399999,-28.6312675476],"type":"Point"}
}