{
  "type": "Feature",
  "properties": {
    "iso:country":"AU",
    "sg:address":"PO Box 425",
    "sg:city":"Salisbury",
    "sg:classifiers":[
        {
            "category":"Banks & Credit Unions",
            "subcategory":"Investment Brokerage",
            "type":"Services"
        }
    ],
    "sg:phone":"+61 8 8182 3568",
    "sg:postcode":"5108",
    "sg:province":"SA",
    "wof:name":"Urban Assets Pty Ltd",
    "wof:placetype":"venue"
},
  "geometry": {"coordinates":[138.642120361,-34.7604484558],"type":"Point"}
}