{
  "type": "Feature",
  "properties": {
    "addr:full":"Level 8 65 Murray St Hobart TAS 7000",
    "addr:housenumber":"65",
    "addr:postcode":"7000",
    "addr:street":"Murray St",
    "iso:country":"AU",
    "sg:address":"Level 8 65 Murray St",
    "sg:city":"Hobart",
    "sg:classifiers":[
        {
            "category":"Professional",
            "subcategory":"Employment Agencies",
            "type":"Services"
        }
    ],
    "sg:phone":"+61 3 6234 7966",
    "sg:postcode":"7000",
    "sg:province":"TAS",
    "wof:name":"Jet Recruitment",
    "wof:placetype":"venue"
},
  "geometry": {"coordinates":[147.32594299300001,-42.882598877],"type":"Point"}
}