{
  "type": "Feature",
  "properties": {
    "addr:full":"27 Griffiths St Coolangatta NSW 2535",
    "addr:housenumber":"27",
    "addr:postcode":"2535",
    "addr:street":"Griffiths St",
    "iso:country":"AU",
    "sg:address":"27 Griffiths St",
    "sg:city":"Coolangatta",
    "sg:classifiers":[
        {
            "category":"Banks & Credit Unions",
            "subcategory":"Bank",
            "type":"Services"
        }
    ],
    "sg:phone":"+61 7 5536 6599",
    "sg:postcode":"2535",
    "sg:province":"NSW",
    "wof:name":"St.George Bank Limited",
    "wof:placetype":"venue"
},
  "geometry": {"coordinates":[150.73045349099999,-34.8464889526],"type":"Point"}
}