{
  "type": "Feature",
  "properties": {
    "iso:country":"AU",
    "sg:address":"9 Orontes Ave",
    "sg:city":"Bridgewater",
    "sg:classifiers":[
        {
            "category":"Home & Garden",
            "subcategory":"Garden Supply",
            "type":"Retail Goods"
        }
    ],
    "sg:phone":"+61 8 8339 8422",
    "sg:postcode":"5155",
    "sg:province":"SA",
    "sg:tags":[
        "turf",
        "lawn"
    ],
    "wof:name":"United Landscaping",
    "wof:placetype":"venue"
},
  "geometry": {"coordinates":[138.76693725600001,-35.0120735168],"type":"Point"}
}