{
  "type": "Feature",
  "properties": {
    "addr:full":"PO Box 512 Gisborne VIC 3437",
    "addr:postcode":"3437",
    "iso:country":"AU",
    "sg:address":"PO Box 512",
    "sg:city":"Gisborne",
    "sg:classifiers":[
        {
            "category":"Manufacturing",
            "subcategory":"Musical Instruments",
            "type":"Manufacturing & Wholesale Goods"
        }
    ],
    "sg:phone":"+61 1800 246 228",
    "sg:postcode":"3437",
    "sg:province":"VIC",
    "sg:tags":[
        "repair",
        "maker"
    ],
    "wof:name":"Wombat Woodwind & Brass",
    "wof:placetype":"venue"
},
  "geometry": {"coordinates":[144.59135437,-37.4869995117],"type":"Point"}
}