{
  "type": "Feature",
  "properties": {
    "addr:full":"PO Box 147 Ferny Creek VIC 3786",
    "addr:postcode":"3786",
    "iso:country":"AU",
    "sg:address":"PO Box 147",
    "sg:city":"Ferny Creek",
    "sg:classifiers":[
        {
            "category":"Professional",
            "subcategory":"Employment Agencies",
            "type":"Services"
        }
    ],
    "sg:phone":"+61 3 9755 1433",
    "sg:postcode":"3786",
    "sg:province":"VIC",
    "sg:tags":[
        "entertainer",
        "agent"
    ],
    "wof:name":"3 R Promotions",
    "wof:placetype":"venue"
},
  "geometry": {"coordinates":[145.342896,-37.875191],"type":"Point"}
}