{
  "type": "Feature",
  "properties": {
    "addr:full":"Suite 1-2, 431 St Kilda Rd Melbourne VIC 3000",
    "addr:housenumber":"431",
    "addr:postcode":"3000",
    "addr:street":"St Kilda Rd",
    "iso:country":"AU",
    "sg:address":"Suite 1-2, 431 St Kilda Rd",
    "sg:city":"Melbourne",
    "sg:classifiers":[
        {
            "category":"Real Estate",
            "subcategory":"Real Estate Agent",
            "type":"Services"
        }
    ],
    "sg:phone":"+61 3 9519 8333",
    "sg:postcode":"3000",
    "sg:province":"VIC",
    "wof:name":"TBM.com.au- Talbot Birner Morley",
    "wof:placetype":"venue"
},
  "geometry": {"coordinates":[144.96751403799999,-37.8176269531],"type":"Point"}
}