{
  "type": "Feature",
  "properties": {
    "addr:full":"1169 Heatherton Rd Noble Park VIC 3174",
    "addr:housenumber":"1169",
    "addr:postcode":"3174",
    "addr:street":"Heatherton Rd",
    "iso:country":"AU",
    "sg:address":"1169 Heatherton Rd",
    "sg:city":"Noble Park",
    "sg:classifiers":[
        {
            "category":"Government",
            "subcategory":"Court House",
            "type":"Public Place"
        }
    ],
    "sg:phone":"+61 3 9547 8666",
    "sg:postcode":"3174",
    "sg:province":"VIC",
    "sg:tags":[
        "personal",
        "marriage",
        "family",
        "counselling"
    ],
    "wof:name":"Pet Bereavement Support Group",
    "wof:placetype":"venue"
},
  "geometry": {"coordinates":[145.18687439000001,-37.9663963318],"type":"Point"}
}