{
  "type": "Feature",
  "properties": {
    "addr:full":"43 Roma Rd St Ives NSW 2075",
    "addr:housenumber":"43",
    "addr:postcode":"2075",
    "addr:street":"Roma Rd",
    "iso:country":"AU",
    "sg:address":"43 Roma Rd",
    "sg:city":"St Ives",
    "sg:classifiers":[
        {
            "category":"Shopping",
            "subcategory":"Crafts & Fabrics",
            "type":"Retail Goods"
        }
    ],
    "sg:phone":"+61 427 972 708",
    "sg:postcode":"2075",
    "sg:province":"NSW",
    "sg:tags":[
        "supply"
    ],
    "wof:name":"Threads & Things",
    "wof:placetype":"venue"
},
  "geometry": {"coordinates":[151.177536011,-33.7140922546],"type":"Point"}
}