{
  "type": "Feature",
  "properties": {
    "iso:country":"AU",
    "sg:address":"15 Raymond Ave",
    "sg:city":"Bayswater",
    "sg:classifiers":[
        {
            "category":"Fast Food",
            "type":"Food & Drink"
        }
    ],
    "sg:phone":"+61 8 9271 0377",
    "sg:postcode":"6053",
    "sg:province":"WA",
    "sg:tags":[
        "away",
        "take"
    ],
    "wof:name":"Goldies Lunch Bar",
    "wof:placetype":"venue"
},
  "geometry": {"coordinates":[115.91771697999999,-31.9083862305],"type":"Point"}
}