{
  "type": "Feature",
  "properties": {
    "iso:country":"AU",
    "sg:address":"181 Safety Bay Rd",
    "sg:city":"Shoalwater",
    "sg:classifiers":[
        {
            "category":"Autos & Motor Vehicles",
            "subcategory":"Boat Sales",
            "type":"Retail Goods"
        }
    ],
    "sg:phone":"+61 8 9528 2800",
    "sg:postcode":"6169",
    "sg:province":"WA",
    "sg:tags":[
        "yacht"
    ],
    "wof:name":"Safety Bay Boating Centre",
    "wof:placetype":"venue"
},
  "geometry": {"coordinates":[115.710358,-32.291473],"type":"Point"}
}