{
  "type": "Feature",
  "properties": {
    "iso:country":"AU",
    "sg:address":"30 Bellevue Rd",
    "sg:city":"(Cnr Bakali Rd) Forresters Beach",
    "sg:classifiers":[
        {
            "category":"Building & Trades",
            "subcategory":"Construction",
            "type":"Services"
        }
    ],
    "sg:phone":"+61 2 4385 8777",
    "sg:postcode":"2260",
    "sg:province":"NSW",
    "sg:tags":[
        "pool",
        "swimming"
    ],
    "wof:name":"Reef Pools Central Coast-Hunter Pty Ltd",
    "wof:placetype":"venue"
},
  "geometry": {"coordinates":[151.464767,-33.399887],"type":"Point"}
}