{
  "type": "Feature",
  "properties": {
    "addr:full":"95 East Ave Clarence Park SA 5034",
    "addr:housenumber":"95",
    "addr:postcode":"5034",
    "addr:street":"East Ave",
    "iso:country":"AU",
    "sg:address":"95 East Ave",
    "sg:city":"Clarence Park",
    "sg:classifiers":[
        {
            "category":"Health Services",
            "subcategory":"Dentist",
            "type":"Services"
        }
    ],
    "sg:phone":"+61 8 8297 4777",
    "sg:postcode":"5034",
    "sg:province":"SA",
    "wof:name":"Karl Scarpin Dr",
    "wof:placetype":"venue"
},
  "geometry": {"coordinates":[138.58192443900001,-34.9664039612],"type":"Point"}
}