{
  "type": "Feature",
  "properties": {
    "iso:country":"AU",
    "sg:address":"39 Elanora Drv",
    "sg:city":"Cooloongup",
    "sg:classifiers":[
        {
            "category":"Health Services",
            "subcategory":"Doctor",
            "type":"Services"
        }
    ],
    "sg:phone":"+61 8 9592 0880",
    "sg:postcode":"6168",
    "sg:province":"WA",
    "sg:tags":[
        "medical",
        "practitioner"
    ],
    "wof:name":"GP After Hours Rockingham Kwinana",
    "wof:placetype":"venue"
},
  "geometry": {"coordinates":[115.76503,-32.293003],"type":"Point"}
}