{
  "type": "Feature",
  "properties": {
    "addr:full":"171 Kensington Rd West Melbourne VIC 3003",
    "addr:housenumber":"171",
    "addr:postcode":"3003",
    "addr:street":"Kensington Rd",
    "iso:country":"AU",
    "sg:address":"171 Kensington Rd",
    "sg:city":"West Melbourne",
    "sg:classifiers":[
        {
            "category":"Shopping",
            "subcategory":"Crafts & Fabrics",
            "type":"Retail Goods"
        }
    ],
    "sg:phone":"+61 1800 337 006",
    "sg:postcode":"3003",
    "sg:province":"VIC",
    "sg:tags":[
        "supply"
    ],
    "wof:name":"Leffler H & Son Pty Ltd",
    "wof:placetype":"venue"
},
  "geometry": {"coordinates":[144.91937255900001,-37.7990951538],"type":"Point"}
}