{
  "type": "Feature",
  "properties": {
    "addr:full":"Shop 2, 67 Bentinck St Ballina NSW 2478",
    "addr:housenumber":"shop;67",
    "addr:postcode":"2478",
    "addr:street":"Bentinck St",
    "iso:country":"AU",
    "sg:address":"Shop 2, 67 Bentinck St",
    "sg:city":"Ballina",
    "sg:classifiers":[
        {
            "category":"Building & Trades",
            "subcategory":"Construction",
            "type":"Services"
        }
    ],
    "sg:phone":"+61 2 6686 7372",
    "sg:postcode":"2478",
    "sg:province":"NSW",
    "sg:tags":[
        "home",
        "air conditioning"
    ],
    "wof:name":"Aircompliance Airconditioning",
    "wof:placetype":"venue"
},
  "geometry": {"coordinates":[153.561599731,-28.8633823395],"type":"Point"}
}