{
  "type": "Feature",
  "properties": {
    "addr:full":"5/ 181 First Ave Bongaree QLD 4507",
    "addr:housenumber":"/ 181",
    "addr:postcode":"4507",
    "addr:street":"First Ave",
    "iso:country":"AU",
    "sg:address":"5/ 181 First Ave",
    "sg:city":"Bongaree",
    "sg:classifiers":[
        {
            "category":"Retail",
            "subcategory":"Car Wash",
            "type":"Services"
        }
    ],
    "sg:phone":"+61 7 3408 0014",
    "sg:postcode":"4507",
    "sg:province":"QLD",
    "sg:tags":[
        "truck",
        "cleaning"
    ],
    "wof:name":"Bribie Island Car Detailing",
    "wof:placetype":"venue"
},
  "geometry": {"coordinates":[153.17669677699999,-27.0797367096],"type":"Point"}
}