{
  "type": "Feature",
  "properties": {
    "addr:full":"29 Bertram St Chatswood NSW 2067",
    "addr:housenumber":"29",
    "addr:postcode":"2067",
    "addr:street":"Bertram St",
    "iso:country":"AU",
    "sg:address":"29 Bertram St",
    "sg:city":"Chatswood",
    "sg:classifiers":[
        {
            "category":"Professional",
            "subcategory":"Accounting & Tax Preparation",
            "type":"Services"
        }
    ],
    "sg:phone":"+61 2 9412 2300",
    "sg:postcode":"2067",
    "sg:province":"NSW",
    "sg:tags":[
        "accountant",
        "auditor"
    ],
    "wof:name":"Elliott S. Bruce & Co",
    "wof:placetype":"venue"
},
  "geometry": {"coordinates":[151.18692016599999,-33.796710968],"type":"Point"}
}