{
  "type": "Feature",
  "properties": {
    "addr:full":"20a Lovell Rd Eastwood NSW 2122",
    "addr:housenumber":"20a",
    "addr:postcode":"2122",
    "addr:street":"Lovell Rd",
    "iso:country":"AU",
    "sg:address":"20a Lovell Rd",
    "sg:city":"Eastwood",
    "sg:classifiers":[
        {
            "category":"Professional",
            "subcategory":"Art Services",
            "type":"Services"
        }
    ],
    "sg:phone":"+61 2 9869 0060",
    "sg:postcode":"2122",
    "sg:province":"NSW",
    "sg:tags":[
        "decorator",
        "painter"
    ],
    "wof:name":"Epping Painting Service",
    "wof:placetype":"venue"
},
  "geometry": {"coordinates":[151.09147644000001,-33.7913780212],"type":"Point"}
}