{
  "type": "Feature",
  "properties": {
    "iso:country":"AU",
    "sg:address":"43 Rosedale Ave",
    "sg:city":"Greenacre",
    "sg:classifiers":[
        {
            "category":"Wholesale",
            "subcategory":"Auto Parts",
            "type":"Manufacturing & Wholesale Goods"
        }
    ],
    "sg:phone":"+61 2 9707 1799",
    "sg:postcode":"2190",
    "sg:province":"NSW",
    "sg:tags":[
        "recyclers"
    ],
    "wof:name":"Ford Wreckers",
    "wof:placetype":"venue"
},
  "geometry": {"coordinates":[151.041214,-33.900459],"type":"Point"}
}