{
  "type": "Feature",
  "properties": {
    "addr:full":"PO Box 268 Wangara WA 6065",
    "addr:postcode":"6065",
    "iso:country":"AU",
    "sg:address":"PO Box 268",
    "sg:city":"Wangara",
    "sg:classifiers":[
        {
            "category":"Professional",
            "subcategory":"Business Services",
            "type":"Services"
        }
    ],
    "sg:phone":"+61 407 733 320",
    "sg:postcode":"6065",
    "sg:province":"WA",
    "sg:tags":[
        "drafting"
    ],
    "wof:name":"Algib Mobile Drafting",
    "wof:placetype":"venue"
},
  "geometry": {"coordinates":[115.830238342,-31.7956504822],"type":"Point"}
}