{
  "type": "Feature",
  "properties": {
    "addr:full":"89 Montefiores St Wellington NSW 2820",
    "addr:housenumber":"89",
    "addr:postcode":"2820",
    "addr:street":"Montefiores St",
    "iso:country":"AU",
    "sg:address":"89 Montefiores St",
    "sg:city":"Wellington",
    "sg:classifiers":[
        {
            "category":"Travel",
            "subcategory":"Hotels & Motels",
            "type":"Entertainment"
        }
    ],
    "sg:phone":"+61 2 6845 3636",
    "sg:postcode":"2820",
    "sg:province":"NSW",
    "sg:tags":[
        "accommodation"
    ],
    "wof:name":"Lion Of Waterloo Tavern",
    "wof:placetype":"venue"
},
  "geometry": {"coordinates":[148.931152344,-32.5408554077],"type":"Point"}
}