{
  "type": "Feature",
  "properties": {
    "addr:full":"6 Sixth St Murray Bridge SA 5253",
    "addr:housenumber":"6",
    "addr:postcode":"5253",
    "addr:street":"Sixth St",
    "iso:country":"AU",
    "sg:address":"6 Sixth St",
    "sg:city":"Murray Bridge",
    "sg:classifiers":[
        {
            "category":"Cafe",
            "type":"Food & Drink"
        }
    ],
    "sg:phone":"+61 8 8532 4111",
    "sg:postcode":"5253",
    "sg:province":"SA",
    "wof:name":"Clock Tower Restaurant & Cafe",
    "wof:placetype":"venue"
},
  "geometry": {"coordinates":[139.276245117,-35.1183013916],"type":"Point"}
}