{
  "type": "Feature",
  "properties": {
    "addr:full":"PO Box 589 Claremont WA 6010",
    "addr:postcode":"6010",
    "iso:country":"AU",
    "sg:address":"PO Box 589",
    "sg:city":"Claremont",
    "sg:classifiers":[
        {
            "category":"Food & Beverages",
            "subcategory":"Liquor & Beverages",
            "type":"Retail Goods"
        }
    ],
    "sg:phone":"+61 8 9385 3885",
    "sg:postcode":"6010",
    "sg:province":"WA",
    "sg:tags":[
        "merchant",
        "spirit",
        "wine"
    ],
    "wof:name":"F.M. Liquor Pty Ltd",
    "wof:placetype":"venue"
},
  "geometry": {"coordinates":[115.78008270300001,-31.9835300446],"type":"Point"}
}