{
  "type": "Feature",
  "properties": {
    "addr:full":"1st Floor, 45a Mt Eliza Way Mt Eliza VIC 3930",
    "addr:housenumber":"45a",
    "addr:postcode":"3930",
    "addr:street":"Mt Eliza Way",
    "iso:country":"AU",
    "sg:address":"1st Floor, 45a Mt Eliza Way",
    "sg:city":"Mt Eliza",
    "sg:classifiers":[
        {
            "category":"Real Estate",
            "subcategory":"Surveying",
            "type":"Services"
        }
    ],
    "sg:phone":"+61 3 9787 7444",
    "sg:postcode":"3930",
    "sg:province":"VIC",
    "sg:tags":[
        "surveyor",
        "marine",
        "cargo"
    ],
    "wof:name":"Rikard-Bell Michael & Associates",
    "wof:placetype":"venue"
},
  "geometry": {"coordinates":[145.091400147,-38.182674408],"type":"Point"}
}