{
  "type": "Feature",
  "properties": {
    "iso:country":"AU",
    "sg:address":"8 Bowra St",
    "sg:city":"Urunga",
    "sg:classifiers":[
        {
            "category":"Food & Beverages",
            "subcategory":"Meat & Fish",
            "type":"Retail Goods"
        }
    ],
    "sg:phone":"+61 2 6655 6910",
    "sg:postcode":"2455",
    "sg:province":"NSW",
    "sg:tags":[
        "seafood"
    ],
    "wof:name":"Urunga Seafoods",
    "wof:placetype":"venue"
},
  "geometry": {"coordinates":[153.021103,-30.495771],"type":"Point"}
}