{
  "type": "Feature",
  "properties": {
    "addr:full":"16 Point St Fremantle WA 6160",
    "addr:housenumber":"16",
    "addr:postcode":"6160",
    "addr:street":"Point St",
    "iso:country":"AU",
    "sg:address":"16 Point St",
    "sg:city":"Fremantle",
    "sg:classifiers":[
        {
            "category":"Building & Trades",
            "subcategory":"Equipment Rental",
            "type":"Services"
        }
    ],
    "sg:phone":"+61 8 9430 4082",
    "sg:postcode":"6160",
    "sg:province":"WA",
    "sg:tags":[
        "fitness"
    ],
    "wof:name":"Momentum Skate Shop",
    "wof:placetype":"venue"
},
  "geometry": {"coordinates":[115.74955,-32.052086],"type":"Point"}
}