{
  "type": "Feature",
  "properties": {
    "addr:full":"90 Wakelin Rd Port Lincoln SA 5606",
    "addr:housenumber":"90",
    "addr:postcode":"5606",
    "addr:street":"Wakelin Rd",
    "iso:country":"AU",
    "sg:address":"90 Wakelin Rd",
    "sg:city":"Port Lincoln",
    "sg:classifiers":[
        {
            "category":"Building & Trades",
            "subcategory":"Construction",
            "type":"Services"
        }
    ],
    "sg:phone":"+61 8 8683 3935",
    "sg:postcode":"5606",
    "sg:province":"SA",
    "sg:tags":[
        "plasterboard",
        "plasterer",
        "fixer"
    ],
    "wof:name":"Smith Peter & Dianne",
    "wof:placetype":"venue"
},
  "geometry": {"coordinates":[135.852036,-34.728481],"type":"Point"}
}