{
  "type": "Feature",
  "properties": {
    "addr:full":"244 Branyan Drv Bundaberg QLD 4670",
    "addr:housenumber":"244",
    "addr:postcode":"4670",
    "addr:street":"Branyan Drv",
    "iso:country":"AU",
    "sg:address":"244 Branyan Drv",
    "sg:city":"Bundaberg",
    "sg:classifiers":[
        {
            "category":"Building & Trades",
            "subcategory":"Construction",
            "type":"Services"
        }
    ],
    "sg:phone":"+61 7 4153 2444",
    "sg:postcode":"4670",
    "sg:province":"QLD",
    "sg:tags":[
        "builder",
        "designer",
        "room",
        "cool"
    ],
    "wof:name":"Mac's Refrigeration",
    "wof:placetype":"venue"
},
  "geometry": {"coordinates":[152.30992126500001,-24.8843765259],"type":"Point"}
}