{
  "type": "Feature",
  "properties": {
    "iso:country":"AU",
    "sg:address":"Bay Junction Shopping Centre, Brighton Rd",
    "sg:city":"(Cnr Jetty Rd) Glenelg",
    "sg:classifiers":[
        {
            "category":"Government",
            "subcategory":"Post Office",
            "type":"Public Place"
        }
    ],
    "sg:phone":"+61 8 8295 3331",
    "sg:postcode":"5045",
    "sg:province":"SA",
    "sg:tags":[
        "postal"
    ],
    "wof:name":"Australia Post",
    "wof:placetype":"venue"
},
  "geometry": {"coordinates":[138.52015700000001,-34.979061],"type":"Point"}
}