{
  "type": "Feature",
  "properties": {
    "addr:full":"Un 2a/ 53 Cosgrove Rd South Strathfield NSW 2136",
    "addr:housenumber":"53",
    "addr:postcode":"2136",
    "addr:street":"Cosgrove Rd South",
    "iso:country":"AU",
    "sg:address":"Un 2a/ 53 Cosgrove Rd",
    "sg:city":"South Strathfield",
    "sg:classifiers":[
        {
            "category":"Fast Food",
            "type":"Food & Drink"
        }
    ],
    "sg:phone":"+61 2 9642 7641",
    "sg:postcode":"2136",
    "sg:province":"NSW",
    "sg:tags":[
        "away",
        "take"
    ],
    "wof:name":"Jacks Foods",
    "wof:placetype":"venue"
},
  "geometry": {"coordinates":[151.076705933,-33.9014205933],"type":"Point"}
}