{
  "type": "Feature",
  "properties": {
    "addr:full":"PO Box 1568 Albany DC WA 6331",
    "addr:postcode":"6331",
    "iso:country":"AU",
    "sg:address":"PO Box 1568",
    "sg:city":"Albany DC",
    "sg:classifiers":[
        {
            "category":"Building & Trades",
            "subcategory":"Landscaping Services",
            "type":"Services"
        }
    ],
    "sg:phone":"+61 8 9844 3003",
    "sg:postcode":"6331",
    "sg:province":"WA",
    "sg:tags":[
        "stump",
        "tree",
        "felling",
        "removal"
    ],
    "wof:name":"Albany Travel Tower",
    "wof:placetype":"venue"
},
  "geometry": {"coordinates":[117.859283447,-35.0605697632],"type":"Point"}
}