{
  "type": "Feature",
  "properties": {
    "addr:full":"Unit 2/ 323 Charlestown Rd Charlestown NSW 2290",
    "addr:housenumber":"/ 323",
    "addr:postcode":"2290",
    "addr:street":"Charlestown Rd",
    "iso:country":"AU",
    "sg:address":"Unit 2/ 323 Charlestown Rd",
    "sg:city":"Charlestown",
    "sg:classifiers":[
        {
            "category":"Real Estate",
            "subcategory":"Surveying",
            "type":"Services"
        }
    ],
    "sg:phone":"+61 2 4943 1755",
    "sg:postcode":"2290",
    "sg:province":"NSW",
    "sg:tags":[
        "building",
        "surveyor"
    ],
    "wof:name":"BCA Certifiers (Aust) Pty Ltd",
    "wof:placetype":"venue"
},
  "geometry": {"coordinates":[151.686813355,-32.9571762085],"type":"Point"}
}