{
  "type": "Feature",
  "properties": {
    "addr:full":"96 Hope St White Gum Valley WA 6162",
    "addr:housenumber":"96",
    "addr:postcode":"6162",
    "addr:street":"Hope St",
    "iso:country":"AU",
    "sg:address":"96 Hope St",
    "sg:city":"White Gum Valley",
    "sg:classifiers":[
        {
            "category":"Recreation",
            "subcategory":"Fishing",
            "type":"Entertainment"
        }
    ],
    "sg:phone":"+61 418 909 807",
    "sg:postcode":"6162",
    "sg:province":"WA",
    "sg:tags":[
        "tackle"
    ],
    "wof:name":"Les Moyle's Custom Tackle",
    "wof:placetype":"venue"
},
  "geometry": {"coordinates":[115.773872,-32.058262],"type":"Point"}
}