{
  "type": "Feature",
  "properties": {
    "addr:full":"PO Box 938 Campbelltown NSW 2560",
    "addr:postcode":"2560",
    "iso:country":"AU",
    "sg:address":"PO Box 938",
    "sg:city":"Campbelltown",
    "sg:classifiers":[
        {
            "category":"Utilities",
            "subcategory":"Water",
            "type":"Services"
        }
    ],
    "sg:phone":"+61 2 4655 4664",
    "sg:postcode":"2560",
    "sg:province":"NSW",
    "sg:tags":[
        "hot",
        "system"
    ],
    "wof:name":"M.P.E. (Menangle Park Electrical)",
    "wof:placetype":"venue"
},
  "geometry": {"coordinates":[150.81658935600001,-34.0640983582],"type":"Point"}
}