{
  "type": "Feature",
  "properties": {
    "iso:country":"AU",
    "sg:address":"13 Ralph Black Drv",
    "sg:city":"North Wollongong",
    "sg:classifiers":[
        {
            "category":"Home & Garden",
            "subcategory":"Building Materials",
            "type":"Retail Goods"
        }
    ],
    "sg:phone":"+61 2 4227 3105",
    "sg:postcode":"2500",
    "sg:province":"NSW",
    "sg:tags":[
        "balustrading"
    ],
    "wof:name":"Rick's Wrought Iron & Aluminium",
    "wof:placetype":"venue"
},
  "geometry": {"coordinates":[150.893524,-34.408081],"type":"Point"}
}