{
  "type": "Feature",
  "properties": {
    "iso:country":"AU",
    "sg:address":"School La",
    "sg:city":"Yandaran",
    "sg:classifiers":[
        {
            "category":"Education",
            "subcategory":"School",
            "type":"Public Place"
        }
    ],
    "sg:phone":"+61 7 4156 1108",
    "sg:postcode":"4673",
    "sg:province":"QLD",
    "sg:tags":[
        "state",
        "except",
        "nsw"
    ],
    "wof:name":"Yandaran Primary",
    "wof:placetype":"venue"
},
  "geometry": {"coordinates":[152.11236572300001,-24.7245979309],"type":"Point"}
}