{
  "type": "Feature",
  "properties": {
    "addr:full":"71 Lt Malop St Geelong VIC 3220",
    "addr:housenumber":"71",
    "addr:postcode":"3220",
    "addr:street":"Lt Malop St",
    "iso:country":"AU",
    "sg:address":"71 Lt Malop St",
    "sg:city":"Geelong",
    "sg:classifiers":[
        {
            "category":"Education",
            "subcategory":"Junior College",
            "type":"Public Place"
        }
    ],
    "sg:phone":"+61 3 5221 3577",
    "sg:postcode":"3220",
    "sg:province":"VIC",
    "sg:tags":[
        "business"
    ],
    "wof:name":"Macquarie Commercial College",
    "wof:placetype":"venue"
},
  "geometry": {"coordinates":[144.35878,-38.146667],"type":"Point"}
}