{
  "type": "Feature",
  "properties": {
    "addr:full":"210 Beechworth Rd Wodonga VIC 3689",
    "addr:housenumber":"210",
    "addr:postcode":"3689",
    "addr:street":"Beechworth Rd",
    "iso:country":"AU",
    "sg:address":"210 Beechworth Rd",
    "sg:city":"Wodonga",
    "sg:classifiers":[
        {
            "category":"Health Services",
            "subcategory":"Health Practitioner",
            "type":"Services"
        }
    ],
    "sg:phone":"+61 2 6027 1016",
    "sg:postcode":"3689",
    "sg:province":"VIC",
    "sg:tags":[
        "psychologist"
    ],
    "wof:name":"Pamela Czarnecki",
    "wof:placetype":"venue"
},
  "geometry": {"coordinates":[146.88795500000001,-36.126896],"type":"Point"}
}