{
  "type": "Feature",
  "properties": {
    "addr:full":"Shop 4 Samford Central Mary Ring Drv Samford QLD 4520",
    "addr:housenumber":"shop 4",
    "addr:postcode":"4520",
    "addr:street":"Samford Central Mary Ring Drv",
    "iso:country":"AU",
    "sg:address":"Shop 4 Samford Central Mary Ring Drv",
    "sg:city":"Samford",
    "sg:classifiers":[
        {
            "category":"Personal",
            "subcategory":"Beauty Salon",
            "type":"Services"
        }
    ],
    "sg:phone":"+61 7 3289 1720",
    "sg:postcode":"4520",
    "sg:province":"QLD",
    "sg:tags":[
        "hairdresser"
    ],
    "wof:name":"4 Non Blondes",
    "wof:placetype":"venue"
},
  "geometry": {"coordinates":[152.88505599999999,-27.372774],"type":"Point"}
}