{
  "type": "Feature",
  "properties": {
    "iso:country":"AU",
    "sg:address":"158 Church Rd",
    "sg:city":"Dromedary",
    "sg:classifiers":[
        {
            "category":"Building & Trades",
            "subcategory":"Cleaning & Sanitation",
            "type":"Services"
        }
    ],
    "sg:phone":"+61 417 105 002",
    "sg:postcode":"7030",
    "sg:province":"TAS",
    "sg:tags":[
        "sweep",
        "chimney"
    ],
    "wof:name":"Brian Forster",
    "wof:placetype":"venue"
},
  "geometry": {"coordinates":[147.15972900400001,-42.7277107239],"type":"Point"}
}