{
  "type": "Feature",
  "properties": {
    "addr:full":"1 Bellerine St Geelong VIC 3220",
    "addr:housenumber":"1",
    "addr:postcode":"3220",
    "addr:street":"Bellerine St",
    "iso:country":"AU",
    "sg:address":"1 Bellerine St",
    "sg:city":"Geelong",
    "sg:classifiers":[
        {
            "category":"Travel",
            "subcategory":"Hotels & Motels",
            "type":"Entertainment"
        }
    ],
    "sg:phone":"+61 3 5221 5577",
    "sg:postcode":"3220",
    "sg:province":"VIC",
    "wof:name":"Comfort Inn Eastern Sands",
    "wof:placetype":"venue"
},
  "geometry": {"coordinates":[144.36634799999999,-38.147823],"type":"Point"}
}