{
  "type": "Feature",
  "properties": {
    "addr:full":"34 Edinburgh St Port Lincoln SA 5606",
    "addr:housenumber":"34",
    "addr:postcode":"5606",
    "addr:street":"Edinburgh St",
    "iso:country":"AU",
    "sg:address":"34 Edinburgh St",
    "sg:city":"Port Lincoln",
    "sg:classifiers":[
        {
            "category":"Retail",
            "subcategory":"Repair Shop",
            "type":"Services"
        }
    ],
    "sg:phone":"+61 8 8682 4579",
    "sg:postcode":"5606",
    "sg:province":"SA",
    "sg:tags":[
        "windscreen"
    ],
    "wof:name":"Geoff Whitehead Motors",
    "wof:placetype":"venue"
},
  "geometry": {"coordinates":[135.86215200000001,-34.725216],"type":"Point"}
}