{
  "type": "Feature",
  "properties": {
    "addr:full":"Bonnie Vale Bundeena NSW 2230",
    "addr:postcode":"2230",
    "iso:country":"AU",
    "sg:address":"Bonnie Vale",
    "sg:city":"Bundeena",
    "sg:classifiers":[
        {
            "category":"Coffee & Tea",
            "type":"Food & Drink"
        }
    ],
    "sg:phone":"+61 2 9544 5294",
    "sg:postcode":"2230",
    "sg:province":"NSW",
    "sg:tags":[
        "kayak",
        "canoe"
    ],
    "wof:name":"Bundeena Kayaks - Kayak Hire, Tours, Sales & Courses",
    "wof:placetype":"venue"
},
  "geometry": {"coordinates":[151.146316528,-34.084148407],"type":"Point"}
}