{
  "type": "Feature",
  "properties": {
    "iso:country":"AU",
    "sg:address":"189 Katoomba St",
    "sg:city":"Katoomba",
    "sg:classifiers":[
        {
            "category":"Fast Food",
            "type":"Food & Drink"
        }
    ],
    "sg:phone":"+61 2 4782 3445",
    "sg:postcode":"2780",
    "sg:province":"NSW",
    "sg:tags":[
        "away",
        "take"
    ],
    "wof:name":"Ashram The",
    "wof:placetype":"venue"
},
  "geometry": {"coordinates":[150.31146240199999,-33.7154197693],"type":"Point"}
}