{
  "type": "Feature",
  "properties": {
    "addr:full":"3 Adelaide St High Wycombe WA 6057",
    "addr:housenumber":"3",
    "addr:postcode":"6057",
    "addr:street":"Adelaide St",
    "iso:country":"AU",
    "sg:address":"3 Adelaide St",
    "sg:city":"High Wycombe",
    "sg:classifiers":[
        {
            "category":"Food & Beverages",
            "subcategory":"Specialty",
            "type":"Retail Goods"
        }
    ],
    "sg:phone":"+61 8 9454 6072",
    "sg:postcode":"6057",
    "sg:province":"WA",
    "sg:tags":[
        "ice",
        "supply"
    ],
    "wof:name":"The Pure Ice Company",
    "wof:placetype":"venue"
},
  "geometry": {"coordinates":[116.01027679400001,-31.928478241],"type":"Point"}
}