{
  "type": "Feature",
  "properties": {
    "addr:full":"39 Erith Rd Buxton NSW 2571",
    "addr:housenumber":"39",
    "addr:postcode":"2571",
    "addr:street":"Erith Rd",
    "iso:country":"AU",
    "sg:address":"39 Erith Rd",
    "sg:city":"Buxton",
    "sg:classifiers":[
        {
            "category":"Utilities",
            "subcategory":"Refuse",
            "type":"Services"
        }
    ],
    "sg:phone":"+61 410 603 692",
    "sg:postcode":"2571",
    "sg:province":"NSW",
    "sg:tags":[
        "remover",
        "rubbish"
    ],
    "wof:name":"Southern Cross Rural Fencing",
    "wof:placetype":"venue"
},
  "geometry": {"coordinates":[150.53353881800001,-34.2576446533],"type":"Point"}
}