{
  "type": "Feature",
  "properties": {
    "addr:full":"1 Denbrow St West Beach SA 5024",
    "addr:housenumber":"1",
    "addr:postcode":"5024",
    "addr:street":"Denbrow St",
    "iso:country":"AU",
    "sg:address":"1 Denbrow St",
    "sg:city":"West Beach",
    "sg:classifiers":[
        {
            "category":"Organizations",
            "subcategory":"Non-profit Organization",
            "type":"Services"
        }
    ],
    "sg:phone":"+61 8 8353 8162",
    "sg:postcode":"5024",
    "sg:province":"SA",
    "sg:tags":[
        "support",
        "disability",
        "organisation"
    ],
    "wof:name":"Conductive Education SA",
    "wof:placetype":"venue"
},
  "geometry": {"coordinates":[138.50718689000001,-34.9420776367],"type":"Point"}
}