{
  "type": "Feature",
  "properties": {
    "iso:country":"AU",
    "sg:address":"105 Billa Rd",
    "sg:city":"Bangor",
    "sg:classifiers":[
        {
            "category":"Health Services",
            "subcategory":"Doctor",
            "type":"Services"
        }
    ],
    "sg:phone":"+61 2 9543 2276",
    "sg:postcode":"2234",
    "sg:province":"NSW",
    "sg:tags":[
        "medical",
        "practitioner"
    ],
    "wof:name":"Wilmot S",
    "wof:placetype":"venue"
},
  "geometry": {"coordinates":[151.026123047,-34.0174026489],"type":"Point"}
}