{
  "type": "Feature",
  "properties": {
    "addr:full":"16 Main Rd Boolaroo NSW 2284",
    "addr:housenumber":"16",
    "addr:postcode":"2284",
    "addr:street":"Main Rd",
    "iso:country":"AU",
    "sg:address":"16 Main Rd",
    "sg:city":"Boolaroo",
    "sg:classifiers":[
        {
            "category":"Health Services",
            "subcategory":"Dentist",
            "type":"Services"
        }
    ],
    "sg:phone":"+61 2 4958 6099",
    "sg:postcode":"2284",
    "sg:province":"NSW",
    "wof:name":"Macquarie Family Dental",
    "wof:placetype":"venue"
},
  "geometry": {"coordinates":[151.62362670900001,-32.9513206482],"type":"Point"}
}