{
  "type": "Feature",
  "properties": {
    "iso:country":"AU",
    "sg:address":"27 Burton Ave",
    "sg:city":"Moorebank",
    "sg:classifiers":[
        {
            "category":"Communications",
            "subcategory":"Film & Video Production",
            "type":"Services"
        }
    ],
    "sg:phone":"+61 400 607 414",
    "sg:postcode":"2170",
    "sg:province":"NSW",
    "sg:tags":[
        "made",
        "clothing",
        "custom"
    ],
    "wof:name":"Chantal .Pascal",
    "wof:placetype":"venue"
},
  "geometry": {"coordinates":[150.950408936,-33.9407958984],"type":"Point"}
}