{
  "type": "Feature",
  "properties": {
    "iso:country":"AU",
    "sg:address":"Shp3/ 6 Funnell Drv",
    "sg:city":"Modanville",
    "sg:classifiers":[
        {
            "category":"Fast Food",
            "type":"Food & Drink"
        }
    ],
    "sg:phone":"+61 2 6628 2005",
    "sg:postcode":"2480",
    "sg:province":"NSW",
    "sg:tags":[
        "away",
        "take"
    ],
    "wof:name":"Birdwing Takeaway",
    "wof:placetype":"venue"
},
  "geometry": {"coordinates":[153.29818725600001,-28.7122917175],"type":"Point"}
}