{
  "type": "Feature",
  "properties": {
    "addr:full":"Cnr Yuille St & Overport Rd Frankston VIC 3199",
    "addr:postcode":"3199",
    "addr:street":"Cnr Yuille St & Overport Rd",
    "iso:country":"AU",
    "sg:address":"Cnr Yuille St & Overport Rd",
    "sg:city":"Frankston",
    "sg:classifiers":[
        {
            "category":"Personal",
            "subcategory":"Beauty Salon",
            "type":"Services"
        }
    ],
    "sg:phone":"+61 3 9783 4350",
    "sg:postcode":"3199",
    "sg:province":"VIC",
    "sg:tags":[
        "hairdresser"
    ],
    "wof:name":"The Mall Hair Studio",
    "wof:placetype":"venue"
},
  "geometry": {"coordinates":[145.12289428700001,-38.1579017639],"type":"Point"}
}