{
  "type": "Feature",
  "properties": {
    "addr:full":"29 Main Rd Wivenhoe TAS 7320",
    "addr:housenumber":"29",
    "addr:postcode":"7320",
    "addr:street":"Main Rd",
    "iso:country":"AU",
    "sg:address":"29 Main Rd",
    "sg:city":"Wivenhoe",
    "sg:classifiers":[
        {
            "category":"Autos & Motor Vehicles",
            "subcategory":"Auto Supplies",
            "type":"Retail Goods"
        }
    ],
    "sg:phone":"+61 3 6431 7255",
    "sg:postcode":"7320",
    "sg:province":"TAS",
    "sg:tags":[
        "part",
        "cycles",
        "accessory"
    ],
    "wof:name":"Motor Cycle Scene",
    "wof:placetype":"venue"
},
  "geometry": {"coordinates":[145.93374600000001,-41.06794],"type":"Point"}
}