{
  "type": "Feature",
  "properties": {
    "iso:country":"AU",
    "sg:address":"74 Mitchell St",
    "sg:city":"Bourke",
    "sg:classifiers":[
        {
            "category":"Travel",
            "subcategory":"Hotels & Motels",
            "type":"Entertainment"
        }
    ],
    "sg:phone":"+61 2 6872 2288",
    "sg:postcode":"2840",
    "sg:province":"NSW",
    "wof:name":"Darling River Motel",
    "wof:placetype":"venue"
},
  "geometry": {"coordinates":[145.936523,-30.088648],"type":"Point"}
}