{
  "type": "Feature",
  "properties": {
    "addr:full":"Lot 4 Hirsts Rd Boolarra VIC 3870",
    "addr:postcode":"3870",
    "addr:street":"Hirsts Rd",
    "iso:country":"AU",
    "sg:address":"Lot 4 Hirsts Rd",
    "sg:city":"Boolarra",
    "sg:classifiers":[
        {
            "category":"Professional",
            "subcategory":"Art Services",
            "type":"Services"
        }
    ],
    "sg:phone":"+61 3 5169 6599",
    "sg:postcode":"3870",
    "sg:province":"VIC",
    "sg:tags":[
        "graphic",
        "designer"
    ],
    "wof:name":"Vivid Illusions",
    "wof:placetype":"venue"
},
  "geometry": {"coordinates":[146.275665283,-38.3745536804],"type":"Point"}
}