{
  "type": "Feature",
  "properties": {
    "iso:country":"AU",
    "sg:address":"3363 Shute Harbour Rd",
    "sg:city":"Shute Harbour",
    "sg:classifiers":[
        {
            "category":"Manufacturing",
            "subcategory":"Watercraft",
            "type":"Manufacturing & Wholesale Goods"
        }
    ],
    "sg:phone":"+61 7 4946 9008",
    "sg:postcode":"4802",
    "sg:province":"QLD",
    "sg:tags":[
        "sail",
        "marine",
        "maker"
    ],
    "wof:name":"Tasman Sails",
    "wof:placetype":"venue"
},
  "geometry": {"coordinates":[148.78457641599999,-20.2903652191],"type":"Point"}
}