{
  "type": "Feature",
  "properties": {
    "addr:full":"16 Butler Rd Hurstville NSW 2220",
    "addr:housenumber":"16",
    "addr:postcode":"2220",
    "addr:street":"Butler Rd",
    "iso:country":"AU",
    "sg:address":"16 Butler Rd",
    "sg:city":"Hurstville",
    "sg:classifiers":[
        {
            "category":"Health Services",
            "subcategory":"Doctor",
            "type":"Services"
        }
    ],
    "sg:phone":"+61 2 9579 1322",
    "sg:postcode":"2220",
    "sg:province":"NSW",
    "sg:tags":[
        "medical",
        "practitioner"
    ],
    "wof:name":"Stoloff Anthony",
    "wof:placetype":"venue"
},
  "geometry": {"coordinates":[151.10186767600001,-33.9683456421],"type":"Point"}
}