{
  "type": "Feature",
  "properties": {
    "addr:full":"2 Hall St Hawthorn East VIC 3123",
    "addr:housenumber":"2",
    "addr:postcode":"3123",
    "addr:street":"Hall St",
    "iso:country":"AU",
    "sg:address":"2 Hall St",
    "sg:city":"Hawthorn East",
    "sg:classifiers":[
        {
            "category":"Shopping",
            "subcategory":"Computers & Home Electronics",
            "type":"Retail Goods"
        }
    ],
    "sg:phone":"+61 3 9804 1700",
    "sg:postcode":"3123",
    "sg:province":"VIC",
    "sg:tags":[
        "hardware",
        "equipment"
    ],
    "wof:name":"Southern Cross Computer Systems",
    "wof:placetype":"venue"
},
  "geometry": {"coordinates":[145.04122924800001,-37.8441925049],"type":"Point"}
}