{
  "type": "Feature",
  "properties": {
    "addr:full":"47 Spencer St Rose Bay NSW 2029",
    "addr:housenumber":"47",
    "addr:postcode":"2029",
    "addr:street":"Spencer St",
    "iso:country":"AU",
    "sg:address":"47 Spencer St",
    "sg:city":"Rose Bay",
    "sg:classifiers":[
        {
            "category":"Building & Trades",
            "subcategory":"Construction",
            "type":"Services"
        }
    ],
    "sg:phone":"+61 2 9388 1998",
    "sg:postcode":"2029",
    "sg:province":"NSW",
    "sg:tags":[
        "contractor"
    ],
    "wof:name":"Gunlake Constructions",
    "wof:placetype":"venue"
},
  "geometry": {"coordinates":[151.27534484899999,-33.8695297241],"type":"Point"}
}