{
  "type": "Feature",
  "properties": {
    "addr:full":"383 Napier St White Hills VIC 3550",
    "addr:housenumber":"383",
    "addr:postcode":"3550",
    "addr:street":"Napier St",
    "iso:country":"AU",
    "sg:address":"383 Napier St",
    "sg:city":"White Hills",
    "sg:classifiers":[
        {
            "category":"Education",
            "subcategory":"School",
            "type":"Public Place"
        }
    ],
    "sg:phone":"+61 3 5443 2133",
    "sg:postcode":"3550",
    "sg:province":"VIC",
    "sg:tags":[
        "state",
        "except",
        "nsw"
    ],
    "wof:name":"Weeroona College Bendigo",
    "wof:placetype":"venue"
},
  "geometry": {"coordinates":[144.298553467,-36.7393951416],"type":"Point"}
}