{
  "type": "Feature",
  "properties": {
    "addr:full":"3 Pembury Rd Minto NSW 2566",
    "addr:housenumber":"3",
    "addr:postcode":"2566",
    "addr:street":"Pembury Rd",
    "iso:country":"AU",
    "sg:address":"3 Pembury Rd",
    "sg:city":"Minto",
    "sg:classifiers":[
        {
            "category":"Professional",
            "type":"Services"
        }
    ],
    "sg:phone":"+61 2 9820 3377",
    "sg:postcode":"2566",
    "sg:province":"NSW",
    "sg:tags":[
        "transport"
    ],
    "wof:name":"Friend J R & C A Transport Pty Ltd",
    "wof:placetype":"venue"
},
  "geometry": {"coordinates":[150.83509826700001,-34.035785675],"type":"Point"}
}