{
  "type": "Feature",
  "properties": {
    "addr:full":"Suite 20, Level 1, 755 Albany Hwy East Victoria Park WA 6101",
    "addr:housenumber":"755",
    "addr:postcode":"6101",
    "addr:street":"Albany Hwy",
    "iso:country":"AU",
    "sg:address":"Suite 20, Level 1, 755 Albany Hwy",
    "sg:city":"East Victoria Park",
    "sg:classifiers":[
        {
            "category":"Health Services",
            "subcategory":"Health Practitioner",
            "type":"Services"
        }
    ],
    "sg:phone":"+61 8 9262 0446",
    "sg:postcode":"6101",
    "sg:province":"WA",
    "sg:tags":[
        "psychologist"
    ],
    "wof:name":"Hastings Susan",
    "wof:placetype":"venue"
},
  "geometry": {"coordinates":[115.901626587,-31.9826049805],"type":"Point"}
}