{
  "type": "Feature",
  "properties": {
    "addr:full":"219 High St Northcote VIC 3070",
    "addr:housenumber":"219",
    "addr:postcode":"3070",
    "addr:street":"High St",
    "iso:country":"AU",
    "sg:address":"219 High St",
    "sg:city":"Northcote",
    "sg:classifiers":[
        {
            "category":"Shopping",
            "subcategory":"Party Supplies",
            "type":"Retail Goods"
        }
    ],
    "sg:phone":"+61 3 9481 6653",
    "sg:postcode":"3070",
    "sg:province":"VIC",
    "sg:tags":[
        "hire",
        "costume"
    ],
    "wof:name":"Yoretymes Emporium Of History",
    "wof:placetype":"venue"
},
  "geometry": {"coordinates":[144.99795499999999,-37.773739],"type":"Point"}
}