{
  "type": "Feature",
  "properties": {
    "iso:country":"AU",
    "sg:address":"89 Wallis Ave",
    "sg:city":"Strathfield",
    "sg:classifiers":[
        {
            "category":"Home & Garden",
            "subcategory":"Carpets & Floor Coverings",
            "type":"Retail Goods"
        }
    ],
    "sg:phone":"+61 2 9642 4960",
    "sg:postcode":"2135",
    "sg:province":"NSW",
    "sg:tags":[
        "wood"
    ],
    "wof:name":"Bondy the Builder",
    "wof:placetype":"venue"
},
  "geometry": {"coordinates":[151.07911682100001,-33.8867378235],"type":"Point"}
}