{
  "type": "Feature",
  "properties": {
    "iso:country":"AU",
    "sg:address":"Shop 7 Medilink Retail Building, 100 Angus Smith Drv",
    "sg:city":"Douglas",
    "sg:classifiers":[
        {
            "category":"Health Services",
            "subcategory":"Doctor",
            "type":"Services"
        }
    ],
    "sg:phone":"+61 1300 552 252",
    "sg:postcode":"4814",
    "sg:province":"QLD",
    "sg:tags":[
        "medical",
        "practitioner"
    ],
    "wof:name":"Afterhours + GP",
    "wof:placetype":"venue"
},
  "geometry": {"coordinates":[146.73469499999999,-19.330072],"type":"Point"}
}