{
  "type": "Feature",
  "properties": {
    "addr:full":"Gladstone Central Shopping Ctr 57-63 Dawson Hwy Gladstone QLD 4680",
    "addr:housenumber":"57-63",
    "addr:postcode":"4680",
    "addr:street":"Shopping;Dawson Hwy",
    "iso:country":"AU",
    "sg:address":"Gladstone Central Shopping Ctr 57-63 Dawson Hwy",
    "sg:city":"Gladstone",
    "sg:classifiers":[
        {
            "category":"Banks & Credit Unions",
            "subcategory":"Financial Services",
            "type":"Services"
        }
    ],
    "sg:phone":"+61 7 4972 6787",
    "sg:postcode":"4680",
    "sg:province":"QLD",
    "sg:tags":[
        "surgeon",
        "oral",
        "dental",
        "maxillofacial"
    ],
    "wof:name":"Young Ian G",
    "wof:placetype":"venue"
},
  "geometry": {"coordinates":[151.24075317399999,-23.8680782318],"type":"Point"}
}