{
  "type": "Feature",
  "properties": {
    "addr:full":"15a Elizabeth St Wahroonga NSW 2076",
    "addr:housenumber":"15a",
    "addr:postcode":"2076",
    "addr:street":"Elizabeth St",
    "iso:country":"AU",
    "sg:address":"15a Elizabeth St",
    "sg:city":"Wahroonga",
    "sg:classifiers":[
        {
            "category":"Professional",
            "subcategory":"Computer Services",
            "type":"Services"
        }
    ],
    "sg:phone":"+61 2 9487 1891",
    "sg:postcode":"2076",
    "sg:province":"NSW",
    "sg:tags":[
        "consultant",
        "system"
    ],
    "wof:name":"Global Direction Pty Ltd",
    "wof:placetype":"venue"
},
  "geometry": {"coordinates":[151.10374450699999,-33.7300682068],"type":"Point"}
}