{
  "type": "Feature",
  "properties": {
    "iso:country":"AU",
    "sg:address":"510 Terrace Rd",
    "sg:city":"Freemans Reach",
    "sg:classifiers":[
        {
            "category":"Building & Trades",
            "subcategory":"Construction",
            "type":"Services"
        }
    ],
    "sg:phone":"+61 2 4579 6301",
    "sg:postcode":"2756",
    "sg:province":"NSW",
    "sg:tags":[
        "joiner",
        "carpenter"
    ],
    "wof:name":"White M R",
    "wof:placetype":"venue"
},
  "geometry": {"coordinates":[150.76858520499999,-33.5645713806],"type":"Point"}
}