{
  "type": "Feature",
  "properties": {
    "addr:full":"Mugga La Symonston ACT 2609",
    "addr:postcode":"2609",
    "iso:country":"AU",
    "sg:address":"Mugga La",
    "sg:city":"Symonston",
    "sg:classifiers":[
        {
            "category":"Utilities",
            "subcategory":"Recycling",
            "type":"Services"
        }
    ],
    "sg:phone":"+61 2 6239 7916",
    "sg:postcode":"2609",
    "sg:province":"ACT",
    "wof:name":"A.C.T. Recycling P/L",
    "wof:placetype":"venue"
},
  "geometry": {"coordinates":[149.15721130399999,-35.3480415344],"type":"Point"}
}