{
  "type": "Feature",
  "properties": {
    "addr:full":"5 Munro St Armadale VIC 3143",
    "addr:housenumber":"5",
    "addr:postcode":"3143",
    "addr:street":"Munro St",
    "iso:country":"AU",
    "sg:address":"5 Munro St",
    "sg:city":"Armadale",
    "sg:classifiers":[
        {
            "category":"Government",
            "subcategory":"Court House",
            "type":"Public Place"
        }
    ],
    "sg:phone":"+61 3 9822 9668",
    "sg:postcode":"3143",
    "sg:province":"VIC",
    "sg:tags":[
        "personal",
        "marriage",
        "family",
        "counselling"
    ],
    "wof:name":"Lily Rosenberg",
    "wof:placetype":"venue"
},
  "geometry": {"coordinates":[145.01838684099999,-37.8530654907],"type":"Point"}
}