{
  "type": "Feature",
  "properties": {
    "addr:full":"Unit 2/ 9 Vangeli St Arndell Park NSW 2148",
    "addr:housenumber":"9",
    "addr:postcode":"2148",
    "addr:street":"Vangeli St",
    "iso:country":"AU",
    "sg:address":"Unit 2/ 9 Vangeli St",
    "sg:city":"Arndell Park",
    "sg:classifiers":[
        {
            "category":"Professional",
            "type":"Services"
        }
    ],
    "sg:phone":"+61 2 9672 1990",
    "sg:postcode":"2148",
    "sg:province":"NSW",
    "sg:tags":[
        "shop",
        "fitting"
    ],
    "wof:name":"Nicom Interiors Pty Ltd",
    "wof:placetype":"venue"
},
  "geometry": {"coordinates":[150.88345336899999,-33.7903900146],"type":"Point"}
}