{
  "type": "Feature",
  "properties": {
    "addr:full":"537 Prospect Rd Gepps Cross SA 5094",
    "addr:housenumber":"537",
    "addr:postcode":"5094",
    "addr:street":"Prospect Rd",
    "iso:country":"AU",
    "sg:address":"537 Prospect Rd",
    "sg:city":"Gepps Cross",
    "sg:classifiers":[
        {
            "category":"Utilities",
            "subcategory":"Refuse",
            "type":"Services"
        }
    ],
    "sg:phone":"+61 8 8203 3238",
    "sg:postcode":"5094",
    "sg:province":"SA",
    "sg:tags":[
        "remover",
        "rubbish"
    ],
    "wof:name":"Pacific Waste Management",
    "wof:placetype":"venue"
},
  "geometry": {"coordinates":[138.59132385300001,-34.8459091187],"type":"Point"}
}