{
  "type": "Feature",
  "properties": {
    "iso:country":"AU",
    "sg:address":"2 / 5 Woodford Pl",
    "sg:city":"Thornton",
    "sg:classifiers":[
        {
            "category":"Home & Garden",
            "subcategory":"Hardware",
            "type":"Retail Goods"
        }
    ],
    "sg:phone":"+61 2 4966 1776",
    "sg:postcode":"2322",
    "sg:province":"NSW",
    "sg:tags":[
        "generating",
        "set",
        "generator"
    ],
    "wof:name":"GTSA Engineering",
    "wof:placetype":"venue"
},
  "geometry": {"coordinates":[151.63897705100001,-32.7884178162],"type":"Point"}
}