{
  "type": "Feature",
  "properties": {
    "addr:full":"Shop G07 Karrinyup Shopping Centre, 200 Karrinyup Rd Karrinyup WA 6018",
    "addr:housenumber":"g07;200",
    "addr:postcode":"6018",
    "addr:street":"Karrinyup Rd",
    "iso:country":"AU",
    "sg:address":"Shop G07 Karrinyup Shopping Centre, 200 Karrinyup Rd",
    "sg:city":"Karrinyup",
    "sg:classifiers":[
        {
            "category":"Health Services",
            "subcategory":"Optometrist",
            "type":"Services"
        }
    ],
    "sg:phone":"+61 8 9446 9033",
    "sg:postcode":"6018",
    "sg:province":"WA",
    "wof:name":"Laubman & Pank",
    "wof:placetype":"venue"
},
  "geometry": {"coordinates":[115.770820618,-31.8734607697],"type":"Point"}
}