{
  "type": "Feature",
  "properties": {
    "iso:country":"AU",
    "sg:address":"Mt Toby Rd",
    "sg:city":"Mirani",
    "sg:classifiers":[
        {
            "category":"Farming",
            "subcategory":"Farm & Veterinary Services",
            "type":"Manufacturing & Wholesale Goods"
        }
    ],
    "sg:phone":"+61 7 4959 1909",
    "sg:postcode":"4754",
    "sg:province":"QLD",
    "sg:tags":[
        "irrigation",
        "reticulation",
        "system"
    ],
    "wof:name":"Trickle Tec",
    "wof:placetype":"venue"
},
  "geometry": {"coordinates":[148.840393,-21.103699],"type":"Point"}
}