{
  "type": "Feature",
  "properties": {
    "addr:full":"63 Grant St Alexandra VIC 3714",
    "addr:housenumber":"63",
    "addr:postcode":"3714",
    "addr:street":"Grant St",
    "iso:country":"AU",
    "sg:address":"63 Grant St",
    "sg:city":"Alexandra",
    "sg:classifiers":[
        {
            "category":"Health Services",
            "subcategory":"Dentist",
            "type":"Services"
        }
    ],
    "sg:phone":"+61 3 5772 2298",
    "sg:postcode":"3714",
    "sg:province":"VIC",
    "sg:tags":[
        "technician",
        "dental"
    ],
    "wof:name":"Gordic Nikolas S",
    "wof:placetype":"venue"
},
  "geometry": {"coordinates":[145.70948791500001,-37.1911125183],"type":"Point"}
}