{
  "type": "Feature",
  "properties": {
    "iso:country":"AU",
    "sg:address":"3/ 73 Outram St",
    "sg:city":"West Perth",
    "sg:classifiers":[
        {
            "category":"Professional",
            "subcategory":"Business Services",
            "type":"Services"
        }
    ],
    "sg:phone":"+61 8 9322 7785",
    "sg:postcode":"6005",
    "sg:province":"WA",
    "sg:tags":[
        "exporter"
    ],
    "wof:name":"Arabaust Exports Pty Ltd",
    "wof:placetype":"venue"
},
  "geometry": {"coordinates":[115.840286255,-31.9469413757],"type":"Point"}
}