{
  "type": "Feature",
  "properties": {
    "addr:full":"Ste4/1- 7 Maroondah Hwy Croydon VIC 3136",
    "addr:housenumber":"7",
    "addr:postcode":"3136",
    "addr:street":"Maroondah Hwy",
    "iso:country":"AU",
    "sg:address":"Ste4/1- 7 Maroondah Hwy",
    "sg:city":"Croydon",
    "sg:classifiers":[
        {
            "category":"Professional",
            "subcategory":"Computer Services",
            "type":"Services"
        }
    ],
    "sg:phone":"+61 3 9870 8188",
    "sg:postcode":"3136",
    "sg:province":"VIC",
    "sg:tags":[
        "package",
        "software"
    ],
    "wof:name":"E Nableapps Pty Ltd",
    "wof:placetype":"venue"
},
  "geometry": {"coordinates":[145.26040649399999,-37.7927970886],"type":"Point"}
}