{
  "type": "Feature",
  "properties": {
    "iso:country":"AU",
    "sg:address":"PO Box 3",
    "sg:city":"Yea",
    "sg:classifiers":[
        {
            "category":"Real Estate",
            "subcategory":"Real Estate Services",
            "type":"Services"
        }
    ],
    "sg:phone":"+61 412 178 845",
    "sg:postcode":"3717",
    "sg:province":"VIC",
    "sg:tags":[
        "consultant",
        "property"
    ],
    "wof:name":"Dawson Advisory Pty Ltd",
    "wof:placetype":"venue"
},
  "geometry": {"coordinates":[145.41664123499999,-37.2135009766],"type":"Point"}
}