{
  "type": "Feature",
  "properties": {
    "iso:country":"AU",
    "sg:address":"Thorncraft Pde",
    "sg:city":"Campsie",
    "sg:classifiers":[
        {
            "category":"Health Services",
            "subcategory":"Dentist",
            "type":"Services"
        }
    ],
    "sg:phone":"+61 2 9787 0047",
    "sg:postcode":"2194",
    "sg:province":"NSW",
    "wof:name":"Campsie Dental Clinic",
    "wof:placetype":"venue"
},
  "geometry": {"coordinates":[151.097534,-33.91618],"type":"Point"}
}