{
  "type": "Feature",
  "properties": {
    "addr:full":"4 Hanson St Freeling SA 5372",
    "addr:housenumber":"4",
    "addr:postcode":"5372",
    "addr:street":"Hanson St",
    "iso:country":"AU",
    "sg:address":"4 Hanson St",
    "sg:city":"Freeling",
    "sg:classifiers":[
        {
            "category":"Fast Food",
            "type":"Food & Drink"
        }
    ],
    "sg:phone":"+61 8 8525 2600",
    "sg:postcode":"5372",
    "sg:province":"SA",
    "sg:tags":[
        "away",
        "take"
    ],
    "wof:name":"Freeling Fast Food",
    "wof:placetype":"venue"
},
  "geometry": {"coordinates":[138.809082031,-34.4545974731],"type":"Point"}
}