{
  "type": "Feature",
  "properties": {
    "iso:country":"AU",
    "sg:address":"18 Ryan St",
    "sg:city":"Coburg",
    "sg:classifiers":[
        {
            "category":"Manufacturing",
            "subcategory":"Tools & Machinery",
            "type":"Manufacturing & Wholesale Goods"
        }
    ],
    "sg:phone":"+61 3 9354 4283",
    "sg:postcode":"3058",
    "sg:province":"VIC",
    "sg:tags":[
        "earth",
        "excavating",
        "moving",
        "equipment"
    ],
    "wof:name":"Gumus Bobcat & Truck Hire",
    "wof:placetype":"venue"
},
  "geometry": {"coordinates":[144.9634552,-37.735118866],"type":"Point"}
}