{
  "type": "Feature",
  "properties": {
    "addr:full":"133 Victoria Rd Rozelle NSW 2039",
    "addr:housenumber":"133",
    "addr:postcode":"2039",
    "addr:street":"Victoria Rd",
    "iso:country":"AU",
    "sg:address":"133 Victoria Rd",
    "sg:city":"Rozelle",
    "sg:classifiers":[
        {
            "category":"Manufacturing",
            "subcategory":"Furniture",
            "type":"Manufacturing & Wholesale Goods"
        }
    ],
    "sg:phone":"+61 2 9555 9594",
    "sg:postcode":"2039",
    "sg:province":"NSW",
    "sg:tags":[
        "builder",
        "designer",
        "custom"
    ],
    "wof:name":"Settings",
    "wof:placetype":"venue"
},
  "geometry": {"coordinates":[151.16729736299999,-33.8619155884],"type":"Point"}
}