{
  "type": "Feature",
  "properties": {
    "addr:full":"Lvl 1, 49 Hume St Crows Nest NSW 2065",
    "addr:housenumber":"49",
    "addr:postcode":"2065",
    "addr:street":"Hume St",
    "iso:country":"AU",
    "sg:address":"Lvl 1, 49 Hume St",
    "sg:city":"Crows Nest",
    "sg:classifiers":[
        {
            "category":"Shopping",
            "subcategory":"Computers & Home Electronics",
            "type":"Retail Goods"
        }
    ],
    "sg:phone":"+61 2 9437 1577",
    "sg:postcode":"2065",
    "sg:province":"NSW",
    "sg:tags":[
        "equipment",
        "multimedia"
    ],
    "sg:website":"http://www.b-line.net.au",
    "wof:name":"B-Line Edit Services P/L",
    "wof:placetype":"venue"
},
  "geometry": {"coordinates":[151.20013427699999,-33.824760437],"type":"Point"}
}