{
  "type": "Feature",
  "properties": {
    "addr:full":"Kempe St (Cnr South Tce) Alice Springs NT 0870",
    "addr:postcode":"nt 0870",
    "addr:street":"Kempe St Cnr South Tce",
    "iso:country":"AU",
    "sg:address":"Kempe St",
    "sg:city":"(Cnr South Tce) Alice Springs",
    "sg:classifiers":[
        {
            "category":"Organizations",
            "subcategory":"Community Association",
            "type":"Services"
        }
    ],
    "sg:phone":"+61 8 8953 4895",
    "sg:postcode":"0870",
    "sg:province":"NT",
    "sg:tags":[
        "organisation",
        "family",
        "welfare"
    ],
    "wof:name":"Central Australian Aboriginal Child Care Agency",
    "wof:placetype":"venue"
},
  "geometry": {"coordinates":[133.87216186500001,-23.716917038],"type":"Point"}
}