{
  "type": "Feature",
  "properties": {
    "addr:full":"PO Box 3393 Bassendean DC WA 6942",
    "addr:postcode":"6942",
    "iso:country":"AU",
    "sg:address":"PO Box 3393",
    "sg:city":"Bassendean DC",
    "sg:classifiers":[
        {
            "category":"Farming",
            "subcategory":"Farm & Veterinary Services",
            "type":"Manufacturing & Wholesale Goods"
        }
    ],
    "sg:phone":"+61 8 9270 0999",
    "sg:postcode":"6942",
    "sg:province":"WA",
    "sg:tags":[
        "seedsman"
    ],
    "wof:name":"Landcare Services",
    "wof:placetype":"venue"
},
  "geometry": {"coordinates":[115.922943115,-31.9122695923],"type":"Point"}
}