{
  "type": "Feature",
  "properties": {
    "addr:full":"3 Mowbray Drv Wantirna South VIC 3152",
    "addr:housenumber":"3",
    "addr:postcode":"3152",
    "addr:street":"Mowbray Drv",
    "iso:country":"AU",
    "sg:address":"3 Mowbray Drv",
    "sg:city":"Wantirna South",
    "sg:classifiers":[
        {
            "category":"Building & Trades",
            "subcategory":"Plumbing",
            "type":"Services"
        }
    ],
    "sg:phone":"+61 419 361 676",
    "sg:postcode":"3152",
    "sg:province":"VIC",
    "sg:tags":[
        "plumber",
        "gasfitters"
    ],
    "wof:name":"Stephen Dance Plumbing Pty Ltd",
    "wof:placetype":"venue"
},
  "geometry": {"coordinates":[145.224975586,-37.8777313232],"type":"Point"}
}