{
  "type": "Feature",
  "properties": {
    "addr:full":"7 Elizabeth St Coburg North VIC 3058",
    "addr:housenumber":"7",
    "addr:postcode":"3058",
    "addr:street":"Elizabeth St",
    "iso:country":"AU",
    "sg:address":"7 Elizabeth St",
    "sg:city":"Coburg North",
    "sg:classifiers":[
        {
            "category":"Retail",
            "subcategory":"Car Wash",
            "type":"Services"
        }
    ],
    "sg:phone":"+61 3 9350 6500",
    "sg:postcode":"3058",
    "sg:province":"VIC",
    "sg:tags":[
        "truck",
        "cleaning"
    ],
    "wof:name":"Bablon Car Wash",
    "wof:placetype":"venue"
},
  "geometry": {"coordinates":[144.97994995100001,-37.7420692444],"type":"Point"}
}