{
  "type": "Feature",
  "properties": {
    "addr:full":"Kiewa Valley Hwy Tawonga South VIC 3698",
    "addr:postcode":"3698",
    "addr:street":"Valley Hwy",
    "iso:country":"AU",
    "sg:address":"Kiewa Valley Hwy",
    "sg:city":"Tawonga South",
    "sg:classifiers":[
        {
            "category":"Sports & Exercise",
            "subcategory":"Ski Slope",
            "type":"Entertainment"
        }
    ],
    "sg:phone":"+61 3 5754 4000",
    "sg:postcode":"3698",
    "sg:province":"VIC",
    "sg:tags":[
        "equipment",
        "hire",
        "retail",
        "snow"
    ],
    "wof:name":"Kiewa Valley Ski Hire",
    "wof:placetype":"venue"
},
  "geometry": {"coordinates":[147.16433699999999,-36.741505],"type":"Point"}
}