{
  "type": "Feature",
  "properties": {
    "addr:full":"556 Pacific Hwy St Leonards NSW 2065",
    "addr:housenumber":"556",
    "addr:postcode":"2065",
    "addr:street":"Pacific Hwy",
    "iso:country":"AU",
    "sg:address":"556 Pacific Hwy",
    "sg:city":"St Leonards",
    "sg:classifiers":[
        {
            "category":"Fast Food",
            "type":"Food & Drink"
        }
    ],
    "sg:phone":"+61 2 9906 5991",
    "sg:postcode":"2065",
    "sg:province":"NSW",
    "sg:tags":[
        "away",
        "take"
    ],
    "wof:name":"Indian Curry Hut",
    "wof:placetype":"venue"
},
  "geometry": {"coordinates":[151.19535827600001,-33.8234596252],"type":"Point"}
}