{
  "type": "Feature",
  "properties": {
    "iso:country":"AU",
    "sg:address":"2 Strang St",
    "sg:city":"Hamilton Hill",
    "sg:classifiers":[
        {
            "category":"Government",
            "subcategory":"City Hall",
            "type":"Public Place"
        }
    ],
    "sg:phone":"+61 8 9335 2002",
    "sg:postcode":"6163",
    "sg:province":"WA",
    "wof:name":"W.A. Portuguese Club Hall",
    "wof:placetype":"venue"
},
  "geometry": {"coordinates":[115.763573,-32.073608],"type":"Point"}
}