{
  "type": "Feature",
  "properties": {
    "addr:full":"2 Strang St Hamilton Hill WA 6163",
    "addr:housenumber":"2",
    "addr:postcode":"6163",
    "addr:street":"Strang St",
    "iso:country":"AU",
    "sg:address":"2 Strang St",
    "sg:city":"Hamilton Hill",
    "sg:classifiers":[
        {
            "category":"Government",
            "subcategory":"City Hall",
            "type":"Public Place"
        }
    ],
    "sg:phone":"+61 8 9335 2002",
    "sg:postcode":"6163",
    "sg:province":"WA",
    "wof:name":"W.A. Portuguese Club Hall",
    "wof:placetype":"venue"
},
  "geometry": {"coordinates":[115.76357299999999,-32.073608],"type":"Point"}
}