{
  "type": "Feature",
  "properties": {
    "addr:full":"12th Floor 344 Queen St Brisbane QLD 4000",
    "addr:housenumber":"344",
    "addr:postcode":"4000",
    "addr:street":"Queen St",
    "iso:country":"AU",
    "sg:address":"12th Floor 344 Queen St",
    "sg:city":"Brisbane",
    "sg:classifiers":[
        {
            "category":"Health Services",
            "subcategory":"Dentist",
            "type":"Services"
        }
    ],
    "sg:phone":"+61 7 3221 8100",
    "sg:postcode":"4000",
    "sg:province":"QLD",
    "wof:name":"Hoyling K J",
    "wof:placetype":"venue"
},
  "geometry": {"coordinates":[153.029006958,-27.4665374756],"type":"Point"}
}