{
  "type": "Feature",
  "properties": {
    "addr:full":"264 Sturt St Townsville QLD 4810",
    "addr:housenumber":"264",
    "addr:postcode":"4810",
    "addr:street":"Sturt St",
    "iso:country":"AU",
    "sg:address":"264 Sturt St",
    "sg:city":"Townsville",
    "sg:classifiers":[
        {
            "category":"Real Estate",
            "subcategory":"Real Estate Agent",
            "type":"Services"
        }
    ],
    "sg:phone":"+61 7 4724 1723",
    "sg:postcode":"4810",
    "sg:province":"QLD",
    "wof:name":"Coral Sea Property Services",
    "wof:placetype":"venue"
},
  "geometry": {"coordinates":[146.81350699999999,-19.262197],"type":"Point"}
}