{
  "type": "Feature",
  "properties": {
    "addr:full":"4 Benalla Ave Ashfield NSW 2131",
    "addr:housenumber":"4",
    "addr:postcode":"2131",
    "addr:street":"Benalla Ave",
    "iso:country":"AU",
    "sg:address":"4 Benalla Ave",
    "sg:city":"Ashfield",
    "sg:classifiers":[
        {
            "category":"Professional",
            "subcategory":"Accounting & Tax Preparation",
            "type":"Services"
        }
    ],
    "sg:phone":"+61 2 9716 9637",
    "sg:postcode":"2131",
    "sg:province":"NSW",
    "sg:tags":[
        "bookkeeping"
    ],
    "wof:name":"Premier Data Services",
    "wof:placetype":"venue"
},
  "geometry": {"coordinates":[151.12113952600001,-33.8853034973],"type":"Point"}
}