{
  "type": "Feature",
  "properties": {
    "iso:country":"AU",
    "sg:address":"7 Edward St",
    "sg:city":"Carlton",
    "sg:classifiers":[
        {
            "category":"Professional",
            "subcategory":"Art Services",
            "type":"Services"
        }
    ],
    "sg:phone":"+61 421 302 620",
    "sg:postcode":"2218",
    "sg:province":"NSW",
    "sg:tags":[
        "decorator",
        "painter"
    ],
    "wof:name":"Joe Sokkar Painting Sevices",
    "wof:placetype":"venue"
},
  "geometry": {"coordinates":[151.12088,-33.973873],"type":"Point"}
}