{
  "type": "Feature",
  "properties": {
    "iso:country":"AU",
    "sg:address":"114 Montague St",
    "sg:city":"North Wollongong",
    "sg:classifiers":[
        {
            "category":"Fast Food",
            "type":"Food & Drink"
        }
    ],
    "sg:phone":"+61 2 4226 2679",
    "sg:postcode":"2500",
    "sg:province":"NSW",
    "sg:tags":[
        "away",
        "take"
    ],
    "wof:name":"Betta Lunches",
    "wof:placetype":"venue"
},
  "geometry": {"coordinates":[150.894226,-34.410522],"type":"Point"}
}