{
  "type": "Feature",
  "properties": {
    "iso:country":"AU",
    "sg:address":"Unit 13, 26- 32 Abel St",
    "sg:city":"Penrith",
    "sg:classifiers":[
        {
            "category":"Education",
            "subcategory":"Dance Studio",
            "type":"Public Place"
        }
    ],
    "sg:phone":"+61 2 4732 2824",
    "sg:postcode":"2750",
    "sg:province":"NSW",
    "sg:tags":[
        "venue",
        "tuition"
    ],
    "sg:website":"http://www.impactdance.com.au",
    "wof:name":"Impact Dance",
    "wof:placetype":"venue"
},
  "geometry": {"coordinates":[150.68414306599999,-33.7651824951],"type":"Point"}
}