{
  "type": "Feature",
  "properties": {
    "addr:full":"14 Bona Ave Belvedere Estate QLD 4860",
    "addr:housenumber":"14",
    "addr:postcode":"4860",
    "addr:street":"Bona Ave Belvedere Estate",
    "iso:country":"AU",
    "sg:address":"14 Bona Ave",
    "sg:city":"Belvedere Estate",
    "sg:classifiers":[
        {
            "category":"Food & Beverages",
            "subcategory":"Fruits & Vegetables",
            "type":"Retail Goods"
        }
    ],
    "sg:phone":"+61 7 4061 4026",
    "sg:postcode":"4860",
    "sg:province":"QLD",
    "sg:tags":[
        "greengrocer",
        "fruiterer"
    ],
    "wof:name":"Xiong Banana Farms",
    "wof:placetype":"venue"
},
  "geometry": {"coordinates":[145.98796081500001,-17.5227222443],"type":"Point"}
}