{
  "type": "Feature",
  "properties": {
    "addr:full":"Railway St Koorda WA 6475",
    "addr:postcode":"6475",
    "addr:street":"Railway St",
    "iso:country":"AU",
    "sg:address":"Railway St",
    "sg:city":"Koorda",
    "sg:classifiers":[
        {
            "category":"Travel",
            "subcategory":"Hotels & Motels",
            "type":"Entertainment"
        }
    ],
    "sg:phone":"+61 8 9684 1226",
    "sg:postcode":"6475",
    "sg:province":"WA",
    "sg:tags":[
        "accommodation"
    ],
    "wof:name":"Koorda Hotel",
    "wof:placetype":"venue"
},
  "geometry": {"coordinates":[117.48204040500001,-30.8242759705],"type":"Point"}
}