{
  "type": "Feature",
  "properties": {
    "addr:full":"11a Macarthur Ave Revesby NSW 2212",
    "addr:housenumber":"11a",
    "addr:postcode":"2212",
    "addr:street":"Macarthur Ave",
    "iso:country":"AU",
    "sg:address":"11a Macarthur Ave",
    "sg:city":"Revesby",
    "sg:classifiers":[
        {
            "category":"Health Services",
            "subcategory":"Health Practitioner",
            "type":"Services"
        }
    ],
    "sg:phone":"+61 2 9772 2586",
    "sg:postcode":"2212",
    "sg:province":"NSW",
    "sg:tags":[
        "physiotherapist"
    ],
    "wof:name":"Revesby Physiotherapy & Sports Injury Centre",
    "wof:placetype":"venue"
},
  "geometry": {"coordinates":[151.01470900000001,-33.953831],"type":"Point"}
}