{
  "type": "Feature",
  "properties": {
    "iso:country":"AU",
    "sg:address":"Hanna St",
    "sg:city":"Lavington",
    "sg:classifiers":[
        {
            "category":"Arena",
            "subcategory":"Sports Club",
            "type":"Entertainment"
        }
    ],
    "sg:phone":"+61 2 6040 2585",
    "sg:postcode":"2641",
    "sg:province":"NSW",
    "sg:tags":[
        "australian",
        "football",
        "rule"
    ],
    "wof:name":"Lavington Football Club",
    "wof:placetype":"venue"
},
  "geometry": {"coordinates":[146.911987305,-36.035118103],"type":"Point"}
}