{
  "type": "Feature",
  "properties": {
    "addr:full":"Lot 2- 38 Cureton Ave Mildura VIC 3500",
    "addr:housenumber":"38",
    "addr:postcode":"3500",
    "addr:street":"Cureton Ave",
    "iso:country":"AU",
    "sg:address":"Lot 2- 38 Cureton Ave",
    "sg:city":"Mildura",
    "sg:classifiers":[
        {
            "category":"Retail",
            "subcategory":"Auto Repair",
            "type":"Services"
        }
    ],
    "sg:phone":"+61 3 5023 7646",
    "sg:postcode":"3500",
    "sg:province":"VIC",
    "sg:tags":[
        "repairer",
        "motor",
        "engineer"
    ],
    "wof:name":"Joe Nocera Automotive Repairs",
    "wof:placetype":"venue"
},
  "geometry": {"coordinates":[142.17295837399999,-34.1893997192],"type":"Point"}
}