{
  "type": "Feature",
  "properties": {
    "addr:full":"3rd Flr Colonial Mutual Bldg Cnr Marcus Clarke St Canberra City ACT 2601",
    "addr:postcode":"2601",
    "addr:street":"Cnr Marcus Clarke St",
    "iso:country":"AU",
    "sg:address":"3rd Flr Colonial Mutual Bldg Cnr Marcus Clarke St",
    "sg:city":"Canberra City",
    "sg:classifiers":[
        {
            "category":"Health Services",
            "subcategory":"Dentist",
            "type":"Services"
        }
    ],
    "sg:phone":"+61 2 6249 8551",
    "sg:postcode":"2601",
    "sg:province":"ACT",
    "wof:name":"Horwood Bradley W Dr",
    "wof:placetype":"venue"
},
  "geometry": {"coordinates":[149.126052856,-35.2788696289],"type":"Point"}
}