{
  "type": "Feature",
  "properties": {
    "addr:full":"Mt Lawley Business Centre 151 Walcott St Mt Lawley WA 6050",
    "addr:housenumber":"151",
    "addr:postcode":"6050",
    "addr:street":"Walcott St",
    "iso:country":"AU",
    "sg:address":"Mt Lawley Business Centre 151 Walcott St",
    "sg:city":"Mt Lawley",
    "sg:classifiers":[
        {
            "category":"Health Services",
            "subcategory":"Health Practitioner",
            "type":"Services"
        }
    ],
    "sg:phone":"+61 8 9328 6684",
    "sg:postcode":"6050",
    "sg:province":"WA",
    "sg:tags":[
        "psychologist"
    ],
    "wof:name":"Franklin Kevin Dr",
    "wof:placetype":"venue"
},
  "geometry": {"coordinates":[115.86681366000001,-31.9300498962],"type":"Point"}
}