{
  "type": "Feature",
  "properties": {
    "addr:full":"9 High Ave Clearview SA 5085",
    "addr:housenumber":"9",
    "addr:postcode":"5085",
    "addr:street":"High Ave",
    "iso:country":"AU",
    "sg:address":"9 High Ave",
    "sg:city":"Clearview",
    "sg:classifiers":[
        {
            "category":"Personal",
            "subcategory":"Massage",
            "type":"Services"
        }
    ],
    "sg:phone":"+61 8 8349 8162",
    "sg:postcode":"5085",
    "sg:province":"SA",
    "sg:tags":[
        "therapy"
    ],
    "wof:name":"Herse Jacquie",
    "wof:placetype":"venue"
},
  "geometry": {"coordinates":[138.612670898,-34.864025116],"type":"Point"}
}