{
  "type": "Feature",
  "properties": {
    "iso:country":"AU",
    "sg:address":"493 Bunnerong Rd",
    "sg:city":"Matraville",
    "sg:classifiers":[
        {
            "category":"Health Services",
            "subcategory":"Dentist",
            "type":"Services"
        }
    ],
    "sg:phone":"+61 2 9311 3277",
    "sg:postcode":"2036",
    "sg:province":"NSW",
    "wof:name":"George D Papadeas Dr",
    "wof:placetype":"venue"
},
  "geometry": {"coordinates":[151.23121643100001,-33.9578590393],"type":"Point"}
}