{
  "type": "Feature",
  "properties": {
    "iso:country":"AU",
    "sg:address":"RMB 1186 Great Alpine Rd",
    "sg:city":"Bright",
    "sg:classifiers":[
        {
            "category":"Utilities",
            "subcategory":"Electric",
            "type":"Services"
        }
    ],
    "sg:phone":"+61 3 5759 2651",
    "sg:postcode":"3741",
    "sg:province":"VIC",
    "sg:tags":[
        "electrical",
        "contractor"
    ],
    "wof:name":"Travis Morton Electrical",
    "wof:placetype":"venue"
},
  "geometry": {"coordinates":[146.943039,-36.721279],"type":"Point"}
}