{
  "type": "Feature",
  "properties": {
    "addr:full":"Lwr Level 93-99 Maroondah Hwy Ringwood VIC 3134",
    "addr:housenumber":"93-99",
    "addr:postcode":"3134",
    "addr:street":"Maroondah Hwy",
    "iso:country":"AU",
    "sg:address":"Lwr Level 93-99 Maroondah Hwy",
    "sg:city":"Ringwood",
    "sg:classifiers":[
        {
            "category":"Health Services",
            "subcategory":"Health Practitioner",
            "type":"Services"
        }
    ],
    "sg:phone":"+61 3 9876 0888",
    "sg:postcode":"3134",
    "sg:province":"VIC",
    "sg:tags":[
        "physiotherapist"
    ],
    "wof:name":"Owen, Esther",
    "wof:placetype":"venue"
},
  "geometry": {"coordinates":[145.225067139,-37.8164024353],"type":"Point"}
}