{
  "type": "Feature",
  "properties": {
    "iso:country":"AU",
    "sg:address":"Main Rd Halls Gap Town Centre",
    "sg:city":"Halls Gap",
    "sg:classifiers":[
        {
            "category":"Travel",
            "subcategory":"Hotels & Motels",
            "type":"Entertainment"
        }
    ],
    "sg:phone":"+61 3 5356 4232",
    "sg:postcode":"3381",
    "sg:province":"VIC",
    "wof:name":"Mountain Grand Boutique Hotel",
    "wof:placetype":"venue"
},
  "geometry": {"coordinates":[142.52487182600001,-37.1499710083],"type":"Point"}
}