{
  "type": "Feature",
  "properties": {
    "addr:full":"42 Ardross St Applecross WA 6153",
    "addr:housenumber":"42",
    "addr:postcode":"6153",
    "addr:street":"Ardross St",
    "iso:country":"AU",
    "sg:address":"42 Ardross St",
    "sg:city":"Applecross",
    "sg:classifiers":[
        {
            "category":"Cafe",
            "type":"Food & Drink"
        }
    ],
    "sg:phone":"+61 8 9364 6535",
    "sg:postcode":"6153",
    "sg:province":"WA",
    "wof:name":"L&#039;S Cafe",
    "wof:placetype":"venue"
},
  "geometry": {"coordinates":[115.835342,-32.010784],"type":"Point"}
}