{
  "type": "Feature",
  "properties": {
    "iso:country":"AU",
    "sg:address":"201 Sayers Rd",
    "sg:city":"Hoppers Crossing",
    "sg:classifiers":[
        {
            "category":"Education",
            "subcategory":"School",
            "type":"Public Place"
        }
    ],
    "sg:phone":"+61 3 9269 5000",
    "sg:postcode":"3029",
    "sg:province":"VIC",
    "wof:name":"Islamic Schools Of Victoria Werribee College",
    "wof:placetype":"venue"
},
  "geometry": {"coordinates":[144.723557,-37.8521],"type":"Point"}
}