{
  "type": "Feature",
  "properties": {
    "addr:full":"PO Box 45 Ferny Creek VIC 3786",
    "addr:postcode":"3786",
    "iso:country":"AU",
    "sg:address":"PO Box 45",
    "sg:city":"Ferny Creek",
    "sg:classifiers":[
        {
            "category":"Banks & Credit Unions",
            "subcategory":"Bank",
            "type":"Services"
        }
    ],
    "sg:phone":"+61 404 057 475",
    "sg:postcode":"3786",
    "sg:province":"VIC",
    "sg:tags":[
        "sealing",
        "compound"
    ],
    "wof:name":"Allwall Jointsealing Pty Ltd",
    "wof:placetype":"venue"
},
  "geometry": {"coordinates":[145.342896,-37.875191],"type":"Point"}
}