{
  "type": "Feature",
  "properties": {
    "iso:country":"AU",
    "sg:address":"27 Campbell St",
    "sg:city":"Colac",
    "sg:classifiers":[
        {
            "category":"Building & Trades",
            "subcategory":"Plumbing",
            "type":"Services"
        }
    ],
    "sg:phone":"+61 408 316 219",
    "sg:postcode":"3250",
    "sg:province":"VIC",
    "sg:tags":[
        "plumber",
        "gasfitters"
    ],
    "wof:name":"McLennan Luke Plumbing",
    "wof:placetype":"venue"
},
  "geometry": {"coordinates":[143.582138,-38.346649],"type":"Point"}
}