{
  "type": "Feature",
  "properties": {
    "addr:full":"404 The Entrance Rd Long Jetty NSW 2261",
    "addr:housenumber":"404",
    "addr:postcode":"2261",
    "addr:street":"The Entrance Rd",
    "iso:country":"AU",
    "sg:address":"404 The Entrance Rd",
    "sg:city":"Long Jetty",
    "sg:classifiers":[
        {
            "category":"Retail",
            "subcategory":"Auto Repair",
            "type":"Services"
        }
    ],
    "sg:phone":"+61 2 4334 1400",
    "sg:postcode":"2261",
    "sg:province":"NSW",
    "sg:tags":[
        "beater",
        "painter",
        "panel"
    ],
    "wof:name":"Craig Green Smash Repairs",
    "wof:placetype":"venue"
},
  "geometry": {"coordinates":[151.48045300000001,-33.36237],"type":"Point"}
}