{
  "type": "Feature",
  "properties": {
    "iso:country":"AU",
    "sg:address":"Unit 17/ 365 West Botany St",
    "sg:city":"Rockdale",
    "sg:classifiers":[
        {
            "category":"Manufacturing",
            "subcategory":"Jewelry",
            "type":"Manufacturing & Wholesale Goods"
        }
    ],
    "sg:phone":"+61 2 9599 4270",
    "sg:postcode":"2216",
    "sg:province":"NSW",
    "sg:tags":[
        "designer",
        "jewellery"
    ],
    "wof:name":"Green Wax Design",
    "wof:placetype":"venue"
},
  "geometry": {"coordinates":[151.14686599999999,-33.957245],"type":"Point"}
}