{
  "type": "Feature",
  "properties": {
    "iso:country":"AU",
    "sg:address":"25 - 31 Ventura Pl",
    "sg:city":"Dandenong South",
    "sg:classifiers":[
        {
            "category":"Autos & Motor Vehicles",
            "subcategory":"Boat Sales",
            "type":"Retail Goods"
        }
    ],
    "sg:phone":"+61 3 9702 8555",
    "sg:postcode":"3175",
    "sg:province":"VIC",
    "sg:tags":[
        "yacht"
    ],
    "wof:name":"Bar Crusher Boats",
    "wof:placetype":"venue"
},
  "geometry": {"coordinates":[145.23089599599999,-38.0263366699],"type":"Point"}
}