{
  "type": "Feature",
  "properties": {
    "iso:country":"AU",
    "sg:address":"PO Box 9178",
    "sg:city":"Wynnum West",
    "sg:classifiers":[
        {
            "category":"Professional",
            "subcategory":"Business Services",
            "type":"Services"
        }
    ],
    "sg:phone":"+61 7 3822 8244",
    "sg:postcode":"4178",
    "sg:province":"QLD",
    "sg:tags":[
        "record",
        "management",
        "storage"
    ],
    "wof:name":"Document Storage by Oikos",
    "wof:placetype":"venue"
},
  "geometry": {"coordinates":[153.15487670900001,-27.4547290802],"type":"Point"}
}