{
  "type": "Feature",
  "properties": {
    "addr:full":"1 Allen St South Brisbane QLD 4101",
    "addr:housenumber":"1",
    "addr:postcode":"4101",
    "addr:street":"Allen St",
    "iso:country":"AU",
    "sg:address":"1 Allen St",
    "sg:city":"South Brisbane",
    "sg:classifiers":[
        {
            "category":"Travel",
            "subcategory":"Hotels & Motels",
            "type":"Entertainment"
        }
    ],
    "sg:phone":"+61 7 3846 3188",
    "sg:postcode":"4101",
    "sg:province":"QLD",
    "wof:name":"Golden Chain Mater Hill Motel",
    "wof:placetype":"venue"
},
  "geometry": {"coordinates":[153.03036499000001,-27.4839420319],"type":"Point"}
}