{
  "type": "Feature",
  "properties": {
    "addr:full":"Shp12a/ Rutherford Rd Muswellbrook NSW 2333",
    "addr:postcode":"2333",
    "addr:street":"Rutherford Rd",
    "iso:country":"AU",
    "sg:address":"Shp12a/ Rutherford Rd",
    "sg:city":"Muswellbrook",
    "sg:classifiers":[
        {
            "category":"Professional",
            "subcategory":"Computer Services",
            "type":"Services"
        }
    ],
    "sg:phone":"+61 2 6541 0433",
    "sg:postcode":"2333",
    "sg:province":"NSW",
    "sg:tags":[
        "tele-communications",
        "consultant"
    ],
    "wof:name":"Telstra Muswellbrook",
    "wof:placetype":"venue"
},
  "geometry": {"coordinates":[150.89881897000001,-32.2799186707],"type":"Point"}
}