{
  "type": "Feature",
  "properties": {
    "addr:full":"Shop 2, 33 Florence St Hornsby NSW 2077",
    "addr:housenumber":"shop;33",
    "addr:postcode":"2077",
    "addr:street":"Florence St",
    "iso:country":"AU",
    "sg:address":"Shop 2, 33 Florence St",
    "sg:city":"Hornsby",
    "sg:classifiers":[
        {
            "category":"Professional",
            "subcategory":"Art Services",
            "type":"Services"
        }
    ],
    "sg:phone":"+61 2 9987 1618",
    "sg:postcode":"2077",
    "sg:province":"NSW",
    "sg:tags":[
        "picture",
        "frame",
        "framing"
    ],
    "wof:name":"Hornsby Framing",
    "wof:placetype":"venue"
},
  "geometry": {"coordinates":[151.10076904300001,-33.7038841248],"type":"Point"}
}