{
  "type": "Feature",
  "properties": {
    "addr:full":"Shop 4, 28 Gap Rd Sunbury VIC 3429",
    "addr:housenumber":"shop;28",
    "addr:postcode":"3429",
    "addr:street":"Gap Rd",
    "iso:country":"AU",
    "sg:address":"Shop 4, 28 Gap Rd",
    "sg:city":"Sunbury",
    "sg:classifiers":[
        {
            "category":"Cafe",
            "type":"Food & Drink"
        }
    ],
    "sg:phone":"+61 3 9740 2500",
    "sg:postcode":"3429",
    "sg:province":"VIC",
    "wof:name":"Legends Lunch Bar",
    "wof:placetype":"venue"
},
  "geometry": {"coordinates":[144.72476196299999,-37.580493927],"type":"Point"}
}