{
  "type": "Feature",
  "properties": {
    "iso:country":"AU",
    "sg:address":"48 O&#039;Hea St",
    "sg:city":"Coburg",
    "sg:classifiers":[
        {
            "category":"Health Services",
            "subcategory":"Health Practitioner",
            "type":"Services"
        }
    ],
    "sg:phone":"+61 3 9354 5465",
    "sg:postcode":"3058",
    "sg:province":"VIC",
    "sg:tags":[
        "psychologist"
    ],
    "sg:website":"http://www.linkspsychology.com.au",
    "wof:name":"Links Psychology",
    "wof:placetype":"venue"
},
  "geometry": {"coordinates":[144.96209716800001,-37.7373580933],"type":"Point"}
}