{
  "type": "Feature",
  "properties": {
    "addr:full":"7 Bilkurra St Tamworth NSW 2340",
    "addr:housenumber":"7",
    "addr:postcode":"2340",
    "addr:street":"Bilkurra St",
    "iso:country":"AU",
    "sg:address":"7 Bilkurra St",
    "sg:city":"Tamworth",
    "sg:classifiers":[
        {
            "category":"Building & Trades",
            "subcategory":"Construction",
            "type":"Services"
        }
    ],
    "sg:phone":"+61 413 315 267",
    "sg:postcode":"2340",
    "sg:province":"NSW",
    "sg:tags":[
        "plasterboard",
        "plasterer",
        "fixer"
    ],
    "wof:name":"Mathew Whitson Plasterer",
    "wof:placetype":"venue"
},
  "geometry": {"coordinates":[150.92424011200001,-31.1157131195],"type":"Point"}
}