{
  "type": "Feature",
  "properties": {
    "addr:full":"68 Single St Werris Creek NSW 2341",
    "addr:housenumber":"68",
    "addr:postcode":"2341",
    "addr:street":"Single St",
    "iso:country":"AU",
    "sg:address":"68 Single St",
    "sg:city":"Werris Creek",
    "sg:classifiers":[
        {
            "category":"Travel",
            "subcategory":"Hotels & Motels",
            "type":"Entertainment"
        }
    ],
    "sg:phone":"+61 2 6768 7024",
    "sg:postcode":"2341",
    "sg:province":"NSW",
    "sg:tags":[
        "accommodation"
    ],
    "wof:name":"Railway Hotel",
    "wof:placetype":"venue"
},
  "geometry": {"coordinates":[150.64717102,-31.3510704041],"type":"Point"}
}