{
  "type": "Feature",
  "properties": {
    "iso:country":"AU",
    "sg:address":"1 Tarata Drv",
    "sg:city":"Doveton",
    "sg:classifiers":[
        {
            "category":"Building & Trades",
            "subcategory":"Landscaping Services",
            "type":"Services"
        }
    ],
    "sg:phone":"+61 411 520 460",
    "sg:postcode":"3177",
    "sg:province":"VIC",
    "sg:tags":[
        "stump",
        "tree",
        "felling",
        "removal"
    ],
    "wof:name":"Dandy Tree Service",
    "wof:placetype":"venue"
},
  "geometry": {"coordinates":[145.24061584500001,-37.9977531433],"type":"Point"}
}