{
  "type": "Feature",
  "properties": {
    "iso:country":"AU",
    "sg:address":"Lot 31 Kessling Ave",
    "sg:city":"Kunda Park",
    "sg:classifiers":[
        {
            "category":"Building & Trades",
            "subcategory":"Construction",
            "type":"Services"
        }
    ],
    "sg:phone":"+61 7 5445 3233",
    "sg:postcode":"4556",
    "sg:province":"QLD",
    "sg:tags":[
        "scaffolding"
    ],
    "wof:name":"Boral Formwork & Scaffolding",
    "wof:placetype":"venue"
},
  "geometry": {"coordinates":[153.031646728,-26.6692771912],"type":"Point"}
}