{
  "type": "Feature",
  "properties": {
    "addr:full":"Cnr Mataram & Albatross St Winnellie NT 0820",
    "addr:postcode":"nt 0820",
    "addr:street":"Cnr;St",
    "iso:country":"AU",
    "sg:address":"Cnr Mataram & Albatross St",
    "sg:city":"Winnellie",
    "sg:classifiers":[
        {
            "category":"Building & Trades",
            "subcategory":"Landscaping Services",
            "type":"Services"
        }
    ],
    "sg:phone":"+61 402 737 200",
    "sg:postcode":"0820",
    "sg:province":"NT",
    "sg:tags":[
        "stump",
        "tree",
        "felling",
        "removal"
    ],
    "wof:name":"Top End Tree Removal",
    "wof:placetype":"venue"
},
  "geometry": {"coordinates":[130.890533447,-12.4276189804],"type":"Point"}
}