{
  "type": "Feature",
  "properties": {
    "addr:full":"1543 Old Burke Rd Kew East VIC 3102",
    "addr:housenumber":"1543",
    "addr:postcode":"3102",
    "addr:street":"Old Burke Rd",
    "iso:country":"AU",
    "sg:address":"1543 Old Burke Rd",
    "sg:city":"Kew East",
    "sg:classifiers":[
        {
            "category":"Commercial Area",
            "type":"Public Place"
        }
    ],
    "sg:phone":"+61 428 855 429",
    "sg:postcode":"3102",
    "sg:province":"VIC",
    "sg:tags":[
        "heavy",
        "carrier"
    ],
    "wof:name":"Boyer W. L.",
    "wof:placetype":"venue"
},
  "geometry": {"coordinates":[145.06195068400001,-37.7861824036],"type":"Point"}
}