{
  "type": "Feature",
  "properties": {
    "iso:country":"AU",
    "sg:address":"749 Centre Rd",
    "sg:city":"Bentleigh East",
    "sg:classifiers":[
        {
            "category":"Shopping",
            "subcategory":"Crafts & Fabrics",
            "type":"Retail Goods"
        }
    ],
    "sg:phone":"+61 3 9570 4211",
    "sg:postcode":"3165",
    "sg:province":"VIC",
    "sg:tags":[
        "material",
        "dress"
    ],
    "wof:name":"Bargain Box Fabric Stores",
    "wof:placetype":"venue"
},
  "geometry": {"coordinates":[145.05679321299999,-37.9207115173],"type":"Point"}
}