{
  "type": "Feature",
  "properties": {
    "addr:full":"1/ 435 Fullarton Rd Highgate SA 5063",
    "addr:housenumber":"/ 435",
    "addr:postcode":"5063",
    "addr:street":"Fullarton Rd",
    "iso:country":"AU",
    "sg:address":"1/ 435 Fullarton Rd",
    "sg:city":"Highgate",
    "sg:classifiers":[
        {
            "category":"Professional",
            "subcategory":"Employment Agencies",
            "type":"Services"
        }
    ],
    "sg:phone":"+61 8 8357 3044",
    "sg:postcode":"5063",
    "sg:province":"SA",
    "wof:name":"ProcureNet",
    "wof:placetype":"venue"
},
  "geometry": {"coordinates":[138.62594604500001,-34.9595565796],"type":"Point"}
}