{
  "type": "Feature",
  "properties": {
    "addr:full":"Shp7/ 184 Goondoon St Gladstone QLD 4680",
    "addr:housenumber":"184",
    "addr:postcode":"4680",
    "addr:street":"Goondoon St",
    "iso:country":"AU",
    "sg:address":"Shp7/ 184 Goondoon St",
    "sg:city":"Gladstone",
    "sg:classifiers":[
        {
            "category":"Fast Food",
            "type":"Food & Drink"
        }
    ],
    "sg:phone":"+61 7 4972 5160",
    "sg:postcode":"4680",
    "sg:province":"QLD",
    "sg:tags":[
        "away",
        "take"
    ],
    "wof:name":"Valley Carvery Cafe",
    "wof:placetype":"venue"
},
  "geometry": {"coordinates":[151.259155273,-23.8480319977],"type":"Point"}
}