{
  "type": "Feature",
  "properties": {
    "iso:country":"AU",
    "sg:address":"Lvl 1/ 365 Little Collins St",
    "sg:city":"Melbourne",
    "sg:classifiers":[
        {
            "category":"Professional",
            "subcategory":"Computer Services",
            "type":"Services"
        }
    ],
    "sg:phone":"+61 3 8676 0570",
    "sg:postcode":"3000",
    "sg:province":"VIC",
    "sg:tags":[
        "consultant",
        "system"
    ],
    "wof:name":"Dius Computing Pty Ltd",
    "wof:placetype":"venue"
},
  "geometry": {"coordinates":[144.96270751899999,-37.8156089783],"type":"Point"}
}