{
  "type": "Feature",
  "properties": {
    "iso:country":"AU",
    "sg:address":"5 Eton Crt",
    "sg:city":"Cambridge Park",
    "sg:classifiers":[
        {
            "category":"Retail",
            "subcategory":"Repair Shop",
            "type":"Services"
        }
    ],
    "sg:phone":"+61 2 4731 2419",
    "sg:postcode":"2747",
    "sg:province":"NSW",
    "sg:tags":[
        "machine",
        "repairs",
        "part",
        "dryer",
        "washing"
    ],
    "wof:name":"Hooke R G",
    "wof:placetype":"venue"
},
  "geometry": {"coordinates":[150.73146057100001,-33.7498664856],"type":"Point"}
}