{
  "type": "Feature",
  "properties": {
    "addr:full":"1 Merino St Kings Meadows TAS 7249",
    "addr:housenumber":"1",
    "addr:postcode":"7249",
    "addr:street":"Merino St",
    "iso:country":"AU",
    "sg:address":"1 Merino St",
    "sg:city":"Kings Meadows",
    "sg:classifiers":[
        {
            "category":"Wholesale",
            "subcategory":"Hardware",
            "type":"Manufacturing & Wholesale Goods"
        }
    ],
    "sg:phone":"+61 3 6343 0477",
    "sg:postcode":"7249",
    "sg:province":"TAS",
    "wof:name":"Tuff Hardware",
    "wof:placetype":"venue"
},
  "geometry": {"coordinates":[147.16392517099999,-41.475730896],"type":"Point"}
}