{
  "type": "Feature",
  "properties": {
    "addr:full":"Suite 1, 30 Ainsbury Pde Clarkson WA 6030",
    "addr:housenumber":"30",
    "addr:postcode":"6030",
    "addr:street":"Ainsbury Pde",
    "iso:country":"AU",
    "sg:address":"Suite 1, 30 Ainsbury Pde",
    "sg:city":"Clarkson",
    "sg:classifiers":[
        {
            "category":"Sports & Exercise",
            "subcategory":"Gym",
            "type":"Entertainment"
        }
    ],
    "sg:phone":"+61 8 9305 9877",
    "sg:postcode":"6030",
    "sg:province":"WA",
    "sg:tags":[
        "health",
        "fitness"
    ],
    "wof:name":"Curves",
    "wof:placetype":"venue"
},
  "geometry": {"coordinates":[115.71621704099999,-31.6795730591],"type":"Point"}
}