{
  "type": "Feature",
  "properties": {
    "addr:full":"65 Brooklyn Rd Brooklyn NSW 2083",
    "addr:housenumber":"65",
    "addr:postcode":"2083",
    "addr:street":"Brooklyn Rd",
    "iso:country":"AU",
    "sg:address":"65 Brooklyn Rd",
    "sg:city":"Brooklyn",
    "sg:classifiers":[
        {
            "category":"Recreation",
            "subcategory":"Boat Charter",
            "type":"Entertainment"
        }
    ],
    "sg:phone":"+61 2 9985 7368",
    "sg:postcode":"2083",
    "sg:province":"NSW",
    "sg:tags":[
        "hire",
        "drive"
    ],
    "sg:website":"http://www.holidaysafloat.com.au",
    "wof:name":"Holidays Afloat Brooklyn Pty Ltd",
    "wof:placetype":"venue"
},
  "geometry": {"coordinates":[151.20623779300001,-33.5486373901],"type":"Point"}
}