{
  "type": "Feature",
  "properties": {
    "iso:country":"AU",
    "sg:address":"Bruce Hwy",
    "sg:city":"Monkland",
    "sg:classifiers":[
        {
            "category":"Autos & Motor Vehicles",
            "subcategory":"Fuel & Gas Station",
            "type":"Retail Goods"
        }
    ],
    "sg:phone":"+61 7 5482 1031",
    "sg:postcode":"4570",
    "sg:province":"QLD",
    "wof:name":"Shell Monkland",
    "wof:placetype":"venue"
},
  "geometry": {"coordinates":[152.685668945,-26.2183570862],"type":"Point"}
}