{
  "type": "Feature",
  "properties": {
    "iso:country":"AU",
    "sg:address":"37 Corvette Rd",
    "sg:city":"Seaford",
    "sg:classifiers":[
        {
            "category":"Government",
            "subcategory":"Fire Station",
            "type":"Public Place"
        }
    ],
    "sg:phone":"+61 8 8327 0135",
    "sg:postcode":"5169",
    "sg:province":"SA",
    "sg:tags":[
        "equipment",
        "protection",
        "consultant"
    ],
    "wof:name":"Fortress Fire Protection",
    "wof:placetype":"venue"
},
  "geometry": {"coordinates":[138.470535278,-35.1902618408],"type":"Point"}
}