{
  "type": "Feature",
  "properties": {
    "iso:country":"AU",
    "sg:address":"472 Old Cleveland Rd",
    "sg:city":"Camp Hill",
    "sg:classifiers":[
        {
            "category":"Professional",
            "subcategory":"Detective & Security Services",
            "type":"Services"
        }
    ],
    "sg:phone":"+61 7 3398 9255",
    "sg:postcode":"4152",
    "sg:province":"QLD",
    "sg:tags":[
        "consultant",
        "system"
    ],
    "wof:name":"Zapalarm Security Fences",
    "wof:placetype":"venue"
},
  "geometry": {"coordinates":[153.067016602,-27.4915885925],"type":"Point"}
}