{
  "type": "Feature",
  "properties": {
    "addr:full":"117 Hume St Wodonga VIC 3690",
    "addr:housenumber":"117",
    "addr:postcode":"3690",
    "addr:street":"Hume St",
    "iso:country":"AU",
    "sg:address":"117 Hume St",
    "sg:city":"Wodonga",
    "sg:classifiers":[
        {
            "category":"Banks & Credit Unions",
            "subcategory":"Bank",
            "type":"Services"
        }
    ],
    "sg:phone":"+61 2 6056 7400",
    "sg:postcode":"3690",
    "sg:province":"VIC",
    "sg:tags":[
        "broker",
        "mortgage"
    ],
    "wof:name":"Smartline",
    "wof:placetype":"venue"
},
  "geometry": {"coordinates":[146.885528564,-36.1243095398],"type":"Point"}
}