{
  "type": "Feature",
  "properties": {
    "iso:country":"AU",
    "sg:address":"193-197 Cumberland Hwy",
    "sg:city":"Smithfield",
    "sg:classifiers":[
        {
            "category":"Wholesale",
            "subcategory":"Home Furnishings",
            "type":"Manufacturing & Wholesale Goods"
        }
    ],
    "sg:phone":"+61 2 9609 6924",
    "sg:postcode":"2164",
    "sg:province":"NSW",
    "wof:name":"WoolComfort Pty Ltd",
    "wof:placetype":"venue"
},
  "geometry": {"coordinates":[150.933349609,-33.8410644531],"type":"Point"}
}