{
  "type": "Feature",
  "properties": {
    "addr:full":"12 Abor St Capella QLD 4702",
    "addr:housenumber":"12",
    "addr:postcode":"4702",
    "addr:street":"Abor St",
    "iso:country":"AU",
    "sg:address":"12 Abor St",
    "sg:city":"Capella",
    "sg:classifiers":[
        {
            "category":"Travel",
            "subcategory":"Hotels & Motels",
            "type":"Entertainment"
        }
    ],
    "sg:phone":"+61 7 4984 9752",
    "sg:postcode":"4702",
    "sg:province":"QLD",
    "wof:name":"Capella Bottlebrush Motel",
    "wof:placetype":"venue"
},
  "geometry": {"coordinates":[147.698364258,-23.417673111],"type":"Point"}
}