{
  "type": "Feature",
  "properties": {
    "addr:full":"522 Whitehorse Rd Mitcham VIC 3132",
    "addr:housenumber":"522",
    "addr:postcode":"3132",
    "addr:street":"Whitehorse Rd",
    "iso:country":"AU",
    "sg:address":"522 Whitehorse Rd",
    "sg:city":"Mitcham",
    "sg:classifiers":[
        {
            "category":"Personal",
            "subcategory":"Beauty Salon",
            "type":"Services"
        }
    ],
    "sg:phone":"+61 3 9873 2127",
    "sg:postcode":"3132",
    "sg:province":"VIC",
    "sg:tags":[
        "hairdresser"
    ],
    "wof:name":"Creative Edge Hair & Beauty",
    "wof:placetype":"venue"
},
  "geometry": {"coordinates":[145.19207763700001,-37.816783905],"type":"Point"}
}