{
  "type": "Feature",
  "properties": {
    "addr:full":"114 Tone Rd Wangaratta VIC 3677",
    "addr:housenumber":"114",
    "addr:postcode":"3677",
    "addr:street":"Tone Rd",
    "iso:country":"AU",
    "sg:address":"114 Tone Rd",
    "sg:city":"Wangaratta",
    "sg:classifiers":[
        {
            "category":"Autos & Motor Vehicles",
            "subcategory":"Fuel & Gas Station",
            "type":"Retail Goods"
        }
    ],
    "sg:phone":"+61 3 5721 5307",
    "sg:postcode":"3677",
    "sg:province":"VIC",
    "wof:name":"Oates M R & J E Service Station",
    "wof:placetype":"venue"
},
  "geometry": {"coordinates":[146.29299926799999,-36.3689231873],"type":"Point"}
}