{
  "type": "Feature",
  "properties": {
    "addr:full":"Waldorf Apartments, Akuna St Canberra City ACT 2601",
    "addr:postcode":"2601",
    "addr:street":"Akuna St",
    "iso:country":"AU",
    "sg:address":"Waldorf Apartments, Akuna St",
    "sg:city":"Canberra City",
    "sg:classifiers":[
        {
            "category":"Personal",
            "subcategory":"Beauty Salon",
            "type":"Services"
        }
    ],
    "sg:phone":"+61 2 6247 3974",
    "sg:postcode":"2601",
    "sg:province":"ACT",
    "sg:tags":[
        "hairdresser"
    ],
    "wof:name":"Phillip The Executive Hair Salon",
    "wof:placetype":"venue"
},
  "geometry": {"coordinates":[149.132156372,-35.281879425],"type":"Point"}
}