{
  "type": "Feature",
  "properties": {
    "addr:full":"372 Bridge Rd Richmond VIC 3121",
    "addr:housenumber":"372",
    "addr:postcode":"3121",
    "addr:street":"Bridge Rd",
    "iso:country":"AU",
    "sg:address":"372 Bridge Rd",
    "sg:city":"Richmond",
    "sg:classifiers":[
        {
            "category":"Travel",
            "subcategory":"Hotels & Motels",
            "type":"Entertainment"
        }
    ],
    "sg:phone":"+61 3 9428 6895",
    "sg:postcode":"3121",
    "sg:province":"VIC",
    "sg:tags":[
        "pub"
    ],
    "wof:name":"Spread Eagle Hotel",
    "wof:placetype":"venue"
},
  "geometry": {"coordinates":[145.00392150900001,-37.8191642761],"type":"Point"}
}