{
  "type": "Feature",
  "properties": {
    "addr:full":"14/ 32 Sixth Ave Maylands WA 6051",
    "addr:housenumber":"14 / 32",
    "addr:postcode":"6051",
    "addr:street":"Sixth Ave",
    "iso:country":"AU",
    "sg:address":"14/ 32 Sixth Ave",
    "sg:city":"Maylands",
    "sg:classifiers":[
        {
            "category":"Personal",
            "type":"Services"
        }
    ],
    "sg:phone":"+61 8 9272 1772",
    "sg:postcode":"6051",
    "sg:province":"WA",
    "sg:tags":[
        "reducing",
        "treatment",
        "weight"
    ],
    "wof:name":"Herbalife Maylands",
    "wof:placetype":"venue"
},
  "geometry": {"coordinates":[115.89366099999999,-31.93306],"type":"Point"}
}