{
  "type": "Feature",
  "properties": {
    "addr:full":"Surry Hills St Surry Hills NSW 2010",
    "addr:postcode":"2010",
    "addr:street":"Surry Hills St",
    "iso:country":"AU",
    "sg:address":"Surry Hills St",
    "sg:city":"Surry Hills",
    "sg:classifiers":[
        {
            "category":"Professional",
            "subcategory":"Employment Agencies",
            "type":"Services"
        }
    ],
    "sg:phone":"+61 2 9211 8274",
    "sg:postcode":"2010",
    "sg:province":"NSW",
    "sg:tags":[
        "provider",
        "internet"
    ],
    "wof:name":"Chris Freeman",
    "wof:placetype":"venue"
},
  "geometry": {"coordinates":[151.20588684099999,-33.8962478638],"type":"Point"}
}