{
  "type": "Feature",
  "properties": {
    "addr:full":"114 Climie St Cranbrook WA 6321",
    "addr:housenumber":"114",
    "addr:postcode":"6321",
    "addr:street":"Climie St",
    "iso:country":"AU",
    "sg:address":"114 Climie St",
    "sg:city":"Cranbrook",
    "sg:classifiers":[
        {
            "category":"Farming",
            "subcategory":"Farm",
            "type":"Manufacturing & Wholesale Goods"
        }
    ],
    "sg:phone":"+61 8 9826 1042",
    "sg:postcode":"6321",
    "sg:province":"WA",
    "sg:tags":[
        "farmer"
    ],
    "wof:name":"Williamson B A & S",
    "wof:placetype":"venue"
},
  "geometry": {"coordinates":[117.549087524,-34.2996864319],"type":"Point"}
}