{
  "type": "Feature",
  "properties": {
    "iso:country":"AU",
    "sg:address":"7th Floor 250 Victoria Pde",
    "sg:city":"East Melbourne",
    "sg:classifiers":[
        {
            "category":"Real Estate",
            "subcategory":"Architect",
            "type":"Services"
        }
    ],
    "sg:phone":"+61 3 9429 5433",
    "sg:postcode":"3002",
    "sg:province":"VIC",
    "wof:name":"Architecture Alliance",
    "wof:placetype":"venue"
},
  "geometry": {"coordinates":[144.98043823200001,-37.8090019226],"type":"Point"}
}