{
  "type": "Feature",
  "properties": {
    "addr:full":"Hosptl David St Dandenong VIC 3175",
    "addr:postcode":"3175",
    "addr:street":"David St",
    "iso:country":"AU",
    "sg:address":"Hosptl David St",
    "sg:city":"Dandenong",
    "sg:classifiers":[
        {
            "category":"Banks & Credit Unions",
            "subcategory":"Bank",
            "type":"Services"
        }
    ],
    "sg:phone":"+61 3 9793 4209",
    "sg:postcode":"3175",
    "sg:province":"VIC",
    "wof:name":"National Commercial Banking",
    "wof:placetype":"venue"
},
  "geometry": {"coordinates":[145.22073364299999,-37.9774627686],"type":"Point"}
}