{
  "type": "Feature",
  "properties": {
    "addr:full":"315 New St Brighton VIC 3186",
    "addr:housenumber":"315",
    "addr:postcode":"3186",
    "addr:street":"New St",
    "iso:country":"AU",
    "sg:address":"315 New St",
    "sg:city":"Brighton",
    "sg:classifiers":[
        {
            "category":"Utilities",
            "subcategory":"Water",
            "type":"Services"
        }
    ],
    "sg:phone":"+61 1300 768 337",
    "sg:postcode":"3186",
    "sg:province":"VIC",
    "sg:tags":[
        "equipment",
        "treatment"
    ],
    "wof:name":"Dophin Water Saving Solutions Pty Ltd",
    "wof:placetype":"venue"
},
  "geometry": {"coordinates":[144.99285888700001,-37.9051132202],"type":"Point"}
}