{
  "type": "Feature",
  "properties": {
    "addr:full":"Level 3, Suite 4, 1292 Hay St Perth WA 6000",
    "addr:housenumber":"1292",
    "addr:postcode":"6000",
    "addr:street":"Hay St",
    "iso:country":"AU",
    "sg:address":"Level 3, Suite 4, 1292 Hay St",
    "sg:city":"Perth",
    "sg:classifiers":[
        {
            "category":"Banks & Credit Unions",
            "subcategory":"Investment Brokerage",
            "type":"Services"
        }
    ],
    "sg:phone":"+61 8 9229 2800",
    "sg:postcode":"6000",
    "sg:province":"WA",
    "wof:name":"BlackRock Investment Management (Australia) Limited",
    "wof:placetype":"venue"
},
  "geometry": {"coordinates":[115.83984375,-31.947807312],"type":"Point"}
}