{
  "type": "Feature",
  "properties": {
    "addr:full":"16b Addison St Shellharbour NSW 2529",
    "addr:housenumber":"16b",
    "addr:postcode":"2529",
    "addr:street":"Addison St",
    "iso:country":"AU",
    "sg:address":"16b Addison St",
    "sg:city":"Shellharbour",
    "sg:classifiers":[
        {
            "category":"Health Services",
            "subcategory":"Health Practitioner",
            "type":"Services"
        }
    ],
    "sg:phone":"+61 401 199 273",
    "sg:postcode":"2529",
    "sg:province":"NSW",
    "sg:tags":[
        "naturopath"
    ],
    "wof:name":"Antonio Braga",
    "wof:placetype":"venue"
},
  "geometry": {"coordinates":[150.86753845199999,-34.5793151855],"type":"Point"}
}