{
  "type": "Feature",
  "properties": {
    "addr:full":"Shp1/ 128-130 Beach St Coogee NSW 2034",
    "addr:housenumber":"128-130",
    "addr:postcode":"2034",
    "addr:street":"Beach St",
    "iso:country":"AU",
    "sg:address":"Shp1/ 128-130 Beach St",
    "sg:city":"Coogee",
    "sg:classifiers":[
        {
            "category":"Retail",
            "subcategory":"Laundry & Dry Cleaning",
            "type":"Services"
        }
    ],
    "sg:phone":"+61 2 9665 2161",
    "sg:postcode":"2034",
    "sg:province":"NSW",
    "wof:name":"Beach Street Gallery Laundrette",
    "wof:placetype":"venue"
},
  "geometry": {"coordinates":[151.258422852,-33.9185638428],"type":"Point"}
}