{
  "type": "Feature",
  "properties": {
    "addr:full":"PO Box 1052 Altona Meadows VIC 3028",
    "addr:postcode":"3028",
    "iso:country":"AU",
    "sg:address":"PO Box 1052",
    "sg:city":"Altona Meadows",
    "sg:classifiers":[
        {
            "category":"Shopping",
            "subcategory":"Musical Instruments",
            "type":"Retail Goods"
        }
    ],
    "sg:phone":"+61 417 304 178",
    "sg:postcode":"3028",
    "sg:province":"VIC",
    "sg:tags":[
        "musician",
        "agent"
    ],
    "wof:name":"Alfi & Co.",
    "wof:placetype":"venue"
},
  "geometry": {"coordinates":[144.77748099999999,-37.872028],"type":"Point"}
}