{
  "type": "Feature",
  "properties": {
    "iso:country":"AU",
    "sg:address":"Hume St",
    "sg:city":"Pittsworth",
    "sg:classifiers":[
        {
            "category":"Education",
            "subcategory":"School",
            "type":"Public Place"
        }
    ],
    "sg:phone":"+61 7 4693 1000",
    "sg:postcode":"4356",
    "sg:province":"QLD",
    "sg:tags":[
        "state",
        "except",
        "nsw"
    ],
    "wof:name":"Pittsworth Preschool",
    "wof:placetype":"venue"
},
  "geometry": {"coordinates":[151.63803100000001,-27.717382],"type":"Point"}
}