{
  "type": "Feature",
  "properties": {
    "iso:country":"AU",
    "sg:address":"Unit 6 14 King Edward Rd",
    "sg:city":"Osborne Park",
    "sg:classifiers":[
        {
            "category":"Autos & Motor Vehicles",
            "subcategory":"Boat Sales",
            "type":"Retail Goods"
        }
    ],
    "sg:phone":"+61 8 9446 4513",
    "sg:postcode":"6017",
    "sg:province":"WA",
    "sg:tags":[
        "equipment",
        "yacht"
    ],
    "wof:name":"E A Redford Engineering",
    "wof:placetype":"venue"
},
  "geometry": {"coordinates":[115.80622863799999,-31.9027328491],"type":"Point"}
}