{
  "type": "Feature",
  "properties": {
    "iso:country":"AU",
    "sg:address":"65 Old Logan Rd",
    "sg:city":"Gailes",
    "sg:classifiers":[
        {
            "category":"Personal",
            "subcategory":"Beauty Salon",
            "type":"Services"
        }
    ],
    "sg:phone":"+61 7 3879 4598",
    "sg:postcode":"4300",
    "sg:province":"QLD",
    "sg:tags":[
        "hairdresser"
    ],
    "wof:name":"La Papillon",
    "wof:placetype":"venue"
},
  "geometry": {"coordinates":[152.915740967,-27.6109771729],"type":"Point"}
}