{
  "type": "Feature",
  "properties": {
    "iso:country":"AU",
    "sg:address":"Unit 1, 10 Carrington Rd",
    "sg:city":"Marrickville",
    "sg:classifiers":[
        {
            "category":"Retail",
            "subcategory":"Laundry & Dry Cleaning",
            "type":"Services"
        }
    ],
    "sg:phone":"+61 2 9558 3388",
    "sg:postcode":"2204",
    "sg:province":"NSW",
    "sg:tags":[
        "ironing"
    ],
    "wof:name":"Global Fashion Service Pty Ltd",
    "wof:placetype":"venue"
},
  "geometry": {"coordinates":[151.15690599999999,-33.917988],"type":"Point"}
}