{
  "type": "Feature",
  "properties": {
    "addr:full":"53 Bathurst Drv Bentley Park QLD 4869",
    "addr:housenumber":"53",
    "addr:postcode":"4869",
    "addr:street":"Bathurst Drv",
    "iso:country":"AU",
    "sg:address":"53 Bathurst Drv",
    "sg:city":"Bentley Park",
    "sg:classifiers":[
        {
            "category":"Professional",
            "subcategory":"Art Services",
            "type":"Services"
        }
    ],
    "sg:phone":"+61 7 4055 5055",
    "sg:postcode":"4869",
    "sg:province":"QLD",
    "sg:tags":[
        "decorator",
        "painter"
    ],
    "wof:name":"Anita & Noel Budge",
    "wof:placetype":"venue"
},
  "geometry": {"coordinates":[145.732299805,-17.0087242126],"type":"Point"}
}