{
  "type": "Feature",
  "properties": {
    "addr:full":"40 Sheffield Rd Welshpool WA 6106",
    "addr:housenumber":"40",
    "addr:postcode":"6106",
    "addr:street":"Sheffield Rd",
    "iso:country":"AU",
    "sg:address":"40 Sheffield Rd",
    "sg:city":"Welshpool",
    "sg:classifiers":[
        {
            "category":"Professional",
            "type":"Services"
        }
    ],
    "sg:phone":"+61 8 9458 6417",
    "sg:postcode":"6106",
    "sg:province":"WA",
    "sg:tags":[
        "transport"
    ],
    "wof:name":"Sun Transport",
    "wof:placetype":"venue"
},
  "geometry": {"coordinates":[115.969009399,-31.9895038605],"type":"Point"}
}