{
  "type": "Feature",
  "properties": {
    "addr:full":"160 Henderson Rd Munster WA 6166",
    "addr:housenumber":"160",
    "addr:postcode":"6166",
    "addr:street":"Henderson Rd",
    "iso:country":"AU",
    "sg:address":"160 Henderson Rd",
    "sg:city":"Munster",
    "sg:classifiers":[
        {
            "category":"Food & Beverages",
            "subcategory":"Fruits & Vegetables",
            "type":"Retail Goods"
        }
    ],
    "sg:phone":"+61 8 9410 2611",
    "sg:postcode":"6166",
    "sg:province":"WA",
    "sg:tags":[
        "wholesale"
    ],
    "wof:name":"Homestyle Vegetable Processors Pty Ltd",
    "wof:placetype":"venue"
},
  "geometry": {"coordinates":[115.811127,-32.139507],"type":"Point"}
}