{
  "type": "Feature",
  "properties": {
    "iso:country":"AU",
    "sg:address":"20 Azzopardi Ave",
    "sg:city":"Glendenning",
    "sg:classifiers":[
        {
            "category":"Professional",
            "subcategory":"Art Services",
            "type":"Services"
        }
    ],
    "sg:phone":"+61 402 642 770",
    "sg:postcode":"2761",
    "sg:province":"NSW",
    "sg:tags":[
        "artist"
    ],
    "wof:name":"Koatic Dzigns",
    "wof:placetype":"venue"
},
  "geometry": {"coordinates":[150.84968599999999,-33.743813],"type":"Point"}
}