{
  "type": "Feature",
  "properties": {
    "iso:country":"AU",
    "sg:address":"First Floor 75 Mount St",
    "sg:city":"Burnie",
    "sg:classifiers":[
        {
            "category":"Professional",
            "subcategory":"Accounting & Tax Preparation",
            "type":"Services"
        }
    ],
    "sg:phone":"+61 3 6431 3933",
    "sg:postcode":"7320",
    "sg:province":"TAS",
    "sg:tags":[
        "consultant",
        "taxation"
    ],
    "wof:name":"Austin Stevens & Co",
    "wof:placetype":"venue"
},
  "geometry": {"coordinates":[145.904816,-41.053852],"type":"Point"}
}