{
  "type": "Feature",
  "properties": {
    "addr:full":"First Floor 75 Mount St Burnie TAS 7320",
    "addr:housenumber":"75",
    "addr:postcode":"7320",
    "addr:street":"Floor;Mount St",
    "iso:country":"AU",
    "sg:address":"First Floor 75 Mount St",
    "sg:city":"Burnie",
    "sg:classifiers":[
        {
            "category":"Professional",
            "subcategory":"Accounting & Tax Preparation",
            "type":"Services"
        }
    ],
    "sg:phone":"+61 3 6431 3933",
    "sg:postcode":"7320",
    "sg:province":"TAS",
    "sg:tags":[
        "consultant",
        "taxation"
    ],
    "wof:name":"Austin Stevens & Co",
    "wof:placetype":"venue"
},
  "geometry": {"coordinates":[145.90481600000001,-41.053852],"type":"Point"}
}