{
  "type": "Feature",
  "properties": {
    "iso:country":"AU",
    "sg:address":"41 Carrington St",
    "sg:city":"Revesby",
    "sg:classifiers":[
        {
            "category":"Professional",
            "type":"Services"
        }
    ],
    "sg:phone":"+61 2 9792 4877",
    "sg:postcode":"2212",
    "sg:province":"NSW",
    "sg:tags":[
        "control",
        "equipment",
        "traffic"
    ],
    "wof:name":"Silver Services Traffic Control Pty Ltd",
    "wof:placetype":"venue"
},
  "geometry": {"coordinates":[151.01200900000001,-33.940594],"type":"Point"}
}