{
  "type": "Feature",
  "properties": {
    "addr:full":"13 Ayr St Reservoir VIC 3073",
    "addr:housenumber":"13",
    "addr:postcode":"3073",
    "addr:street":"Ayr St",
    "iso:country":"AU",
    "sg:address":"13 Ayr St",
    "sg:city":"Reservoir",
    "sg:classifiers":[
        {
            "category":"Utilities",
            "subcategory":"Electric",
            "type":"Services"
        }
    ],
    "sg:phone":"+61 411 862 600",
    "sg:postcode":"3073",
    "sg:province":"VIC",
    "sg:tags":[
        "electrical",
        "contractor"
    ],
    "wof:name":"MBE Electrical Services",
    "wof:placetype":"venue"
},
  "geometry": {"coordinates":[145.03221130399999,-37.7063713074],"type":"Point"}
}