{
  "type": "Feature",
  "properties": {
    "addr:full":"17 Pickett St Footscray VIC 3011",
    "addr:housenumber":"17",
    "addr:postcode":"3011",
    "addr:street":"Pickett St",
    "iso:country":"AU",
    "sg:address":"17 Pickett St",
    "sg:city":"Footscray",
    "sg:classifiers":[
        {
            "category":"Health Services",
            "subcategory":"Doctor",
            "type":"Services"
        }
    ],
    "sg:phone":"+61 3 9687 3895",
    "sg:postcode":"3011",
    "sg:province":"VIC",
    "sg:tags":[
        "medical",
        "practitioner"
    ],
    "wof:name":"The Specialist Centre",
    "wof:placetype":"venue"
},
  "geometry": {"coordinates":[144.89642334000001,-37.8017463684],"type":"Point"}
}