{
  "type": "Feature",
  "properties": {
    "iso:country":"AU",
    "sg:address":"14 Kelso Crs",
    "sg:city":"Moorebank",
    "sg:classifiers":[
        {
            "category":"Autos & Motor Vehicles",
            "subcategory":"Auto Supplies",
            "type":"Retail Goods"
        }
    ],
    "sg:phone":"+61 2 9601 0500",
    "sg:postcode":"2170",
    "sg:province":"NSW",
    "sg:tags":[
        "camper-trailers",
        "caravan",
        "equipment"
    ],
    "wof:name":"Oasis Bodybuilding Pty Ltd",
    "wof:placetype":"venue"
},
  "geometry": {"coordinates":[150.922927856,-33.9513893127],"type":"Point"}
}