{
  "type": "Feature",
  "properties": {
    "addr:full":"14 Station St Pakenham VIC 3810",
    "addr:housenumber":"14",
    "addr:postcode":"3810",
    "addr:street":"Station St",
    "iso:country":"AU",
    "sg:address":"14 Station St",
    "sg:city":"Pakenham",
    "sg:classifiers":[
        {
            "category":"Recreation",
            "subcategory":"Fishing",
            "type":"Entertainment"
        }
    ],
    "sg:phone":"+61 3 5941 3310",
    "sg:postcode":"3810",
    "sg:province":"VIC",
    "sg:tags":[
        "tackle"
    ],
    "wof:name":"Fishtales Bait & Tackle",
    "wof:placetype":"venue"
},
  "geometry": {"coordinates":[145.48388700000001,-38.079056],"type":"Point"}
}