{
  "type": "Feature",
  "properties": {
    "addr:full":"16-20 Lemmon Rd Fishermen's Wharf Geraldton WA 6530",
    "addr:housenumber":"16-20",
    "addr:postcode":"6530",
    "addr:street":"Lemmon Rd Fishermen'S Wharf",
    "iso:country":"AU",
    "sg:address":"16-20 Lemmon Rd Fishermen's Wharf",
    "sg:city":"Geraldton",
    "sg:classifiers":[
        {
            "category":"Train Station",
            "subcategory":"Rail",
            "type":"Transportation"
        }
    ],
    "sg:phone":"+61 8 9965 3340",
    "sg:postcode":"6530",
    "sg:province":"WA",
    "sg:tags":[
        "marine",
        "engineer"
    ],
    "wof:name":"Xtreme Marine",
    "wof:placetype":"venue"
},
  "geometry": {"coordinates":[114.59058380099999,-28.7755012512],"type":"Point"}
}