{
  "type": "Feature",
  "properties": {
    "iso:country":"AU",
    "sg:address":"15 Shepherdson Rd",
    "sg:city":"Parafield Gardens",
    "sg:classifiers":[
        {
            "category":"Education",
            "subcategory":"School",
            "type":"Public Place"
        }
    ],
    "sg:phone":"+61 8 8258 9855",
    "sg:postcode":"5107",
    "sg:province":"SA",
    "sg:tags":[
        "state",
        "except",
        "nsw"
    ],
    "wof:name":"Parafield Gardens High",
    "wof:placetype":"venue"
},
  "geometry": {"coordinates":[138.60923767099999,-34.7825317383],"type":"Point"}
}