{
  "type": "Feature",
  "properties": {
    "addr:full":"Unit 16, Leeming Forum Shopping Centre, Farrington Leeming WA 6149",
    "addr:postcode":"6149",
    "iso:country":"AU",
    "sg:address":"Unit 16, Leeming Forum Shopping Centre, Farrington",
    "sg:city":"Leeming",
    "sg:classifiers":[
        {
            "category":"Real Estate",
            "subcategory":"Real Estate Agent",
            "type":"Services"
        }
    ],
    "sg:phone":"+61 8 9332 4000",
    "sg:postcode":"6149",
    "sg:province":"WA",
    "wof:name":"L J Hooker",
    "wof:placetype":"venue"
},
  "geometry": {"coordinates":[115.85984000000001,-32.079472],"type":"Point"}
}