{
  "type": "Feature",
  "properties": {
    "addr:full":"Unit 3/ 1 Price St Melrose Park SA 5039",
    "addr:housenumber":"1",
    "addr:postcode":"5039",
    "addr:street":"Price St",
    "iso:country":"AU",
    "sg:address":"Unit 3/ 1 Price St",
    "sg:city":"Melrose Park",
    "sg:classifiers":[
        {
            "category":"Shopping",
            "subcategory":"Pets & Pet Supplies",
            "type":"Retail Goods"
        }
    ],
    "sg:phone":"+61 409 820 776",
    "sg:postcode":"5039",
    "sg:province":"SA",
    "sg:tags":[
        "shop",
        "supplier"
    ],
    "wof:name":"JDA Sales & Marketing Pty Ltd",
    "wof:placetype":"venue"
},
  "geometry": {"coordinates":[138.57437133799999,-34.9807014465],"type":"Point"}
}