{
  "type": "Feature",
  "properties": {
    "iso:country":"AU",
    "sg:address":"70 Lillee Crs",
    "sg:city":"Tullamarine",
    "sg:classifiers":[
        {
            "category":"Wholesale",
            "subcategory":"Electrical",
            "type":"Manufacturing & Wholesale Goods"
        }
    ],
    "sg:phone":"+61 3 9338 3544",
    "sg:postcode":"3043",
    "sg:province":"VIC",
    "sg:tags":[
        "control",
        "equipment",
        "switch"
    ],
    "wof:name":"E.G.O Australia Pty Ltd",
    "wof:placetype":"venue"
},
  "geometry": {"coordinates":[144.86845398,-37.7137413025],"type":"Point"}
}