{
  "type": "Feature",
  "properties": {
    "iso:country":"AU",
    "sg:address":"281- 283 Maroondah Hwy",
    "sg:city":"Healesville",
    "sg:classifiers":[
        {
            "category":"Wholesale",
            "subcategory":"Farm Supplies",
            "type":"Manufacturing & Wholesale Goods"
        }
    ],
    "sg:phone":"+61 3 5962 2555",
    "sg:postcode":"3777",
    "sg:province":"VIC",
    "sg:tags":[
        "feed",
        "supplement",
        "stock"
    ],
    "wof:name":"Healesville Stockfeed & Farm Supplies",
    "wof:placetype":"venue"
},
  "geometry": {"coordinates":[145.52160599999999,-37.651596],"type":"Point"}
}