{
  "type": "Feature",
  "properties": {
    "addr:full":"19 Clissold St Mollymook NSW 2539",
    "addr:housenumber":"19",
    "addr:postcode":"2539",
    "addr:street":"Clissold St",
    "iso:country":"AU",
    "sg:address":"19 Clissold St",
    "sg:city":"Mollymook",
    "sg:classifiers":[
        {
            "category":"Building & Trades",
            "subcategory":"Cleaning & Sanitation",
            "type":"Services"
        }
    ],
    "sg:phone":"+61 2 4455 2715",
    "sg:postcode":"2539",
    "sg:province":"NSW",
    "sg:tags":[
        "sweep",
        "chimney"
    ],
    "wof:name":"S & J Jones",
    "wof:placetype":"venue"
},
  "geometry": {"coordinates":[150.47206115700001,-35.3426856995],"type":"Point"}
}