{
  "type": "Feature",
  "properties": {
    "addr:full":"Nelson Rd Point Lonsdale VIC 3225",
    "addr:postcode":"3225",
    "addr:street":"Nelson Rd",
    "iso:country":"AU",
    "sg:address":"Nelson Rd",
    "sg:city":"Point Lonsdale",
    "sg:classifiers":[
        {
            "category":"Health Services",
            "subcategory":"Doctor",
            "type":"Services"
        }
    ],
    "sg:phone":"+61 3 5258 0888",
    "sg:postcode":"3225",
    "sg:province":"VIC",
    "sg:tags":[
        "medical",
        "practitioner"
    ],
    "wof:name":"Condon Catherine Dr.",
    "wof:placetype":"venue"
},
  "geometry": {"coordinates":[144.618439,-38.273781],"type":"Point"}
}