{
  "type": "Feature",
  "properties": {
    "iso:country":"AU",
    "sg:address":"28 Linton St",
    "sg:city":"Kangaroo Point",
    "sg:classifiers":[
        {
            "category":"Farming",
            "subcategory":"Farm & Veterinary Services",
            "type":"Manufacturing & Wholesale Goods"
        }
    ],
    "sg:phone":"+61 7 3392 3399",
    "sg:postcode":"4169",
    "sg:province":"QLD",
    "sg:tags":[
        "agricultural",
        "advisory"
    ],
    "wof:name":"Sugar InSite",
    "wof:placetype":"venue"
},
  "geometry": {"coordinates":[153.036834717,-27.483669281],"type":"Point"}
}