{
  "type": "Feature",
  "properties": {
    "addr:full":"15 Auburn St Moree NSW 2400",
    "addr:housenumber":"15",
    "addr:postcode":"2400",
    "addr:street":"Auburn St",
    "iso:country":"AU",
    "sg:address":"15 Auburn St",
    "sg:city":"Moree",
    "sg:classifiers":[
        {
            "category":"Health Services",
            "subcategory":"Health Practitioner",
            "type":"Services"
        }
    ],
    "sg:phone":"+61 2 6752 3752",
    "sg:postcode":"2400",
    "sg:province":"NSW",
    "sg:tags":[
        "physiotherapist"
    ],
    "wof:name":"Clyne Tina",
    "wof:placetype":"venue"
},
  "geometry": {"coordinates":[149.84031677199999,-29.4647026062],"type":"Point"}
}