{
  "type": "Feature",
  "properties": {
    "iso:country":"AU",
    "sg:address":"Shp 7/ 284 Whitewood Rd",
    "sg:city":"Howard Springs",
    "sg:classifiers":[
        {
            "category":"Fast Food",
            "type":"Food & Drink"
        }
    ],
    "sg:phone":"+61 8 8983 2303",
    "sg:postcode":"0835",
    "sg:province":"NT",
    "sg:tags":[
        "away",
        "take"
    ],
    "wof:name":"Barra To Go Takeaway",
    "wof:placetype":"venue"
},
  "geometry": {"coordinates":[131.043793,-12.496365],"type":"Point"}
}