{
  "type": "Feature",
  "properties": {
    "addr:full":"15 Alexandra St Hunters Hill NSW 2110",
    "addr:housenumber":"15",
    "addr:postcode":"2110",
    "addr:street":"Alexandra St",
    "iso:country":"AU",
    "sg:address":"15 Alexandra St",
    "sg:city":"Hunters Hill",
    "sg:classifiers":[
        {
            "category":"Professional",
            "subcategory":"Art Services",
            "type":"Services"
        }
    ],
    "sg:phone":"+61 2 9817 4803",
    "sg:postcode":"2110",
    "sg:province":"NSW",
    "sg:tags":[
        "artist"
    ],
    "wof:name":"Hansen Ian",
    "wof:placetype":"venue"
},
  "geometry": {"coordinates":[151.150100708,-33.8343925476],"type":"Point"}
}