{
  "type": "Feature",
  "properties": {
    "addr:full":"PO Box 1258 Thuringowa Central QLD 4817",
    "addr:postcode":"4817",
    "iso:country":"AU",
    "sg:address":"PO Box 1258",
    "sg:city":"Thuringowa Central",
    "sg:classifiers":[
        {
            "category":"Building & Trades",
            "subcategory":"Construction",
            "type":"Services"
        }
    ],
    "sg:phone":"+61 7 4751 3341",
    "sg:postcode":"4817",
    "sg:province":"QLD",
    "sg:tags":[
        "earth",
        "excavating",
        "moving",
        "contractor"
    ],
    "wof:name":"Cleveland Bay Excavations",
    "wof:placetype":"venue"
},
  "geometry": {"coordinates":[146.723907,-19.31901],"type":"Point"}
}