{
  "type": "Feature",
  "properties": {
    "addr:full":"13 Cooper St Smithfield NSW 2164",
    "addr:housenumber":"13",
    "addr:postcode":"2164",
    "addr:street":"Cooper St",
    "iso:country":"AU",
    "sg:address":"13 Cooper St",
    "sg:city":"Smithfield",
    "sg:classifiers":[
        {
            "category":"Wholesale",
            "subcategory":"Construction Materials",
            "type":"Manufacturing & Wholesale Goods"
        }
    ],
    "sg:phone":"+61 2 8786 6000",
    "sg:postcode":"2164",
    "sg:province":"NSW",
    "sg:tags":[
        "wholesaler",
        "lighting",
        "mfrs",
        "accessory"
    ],
    "wof:name":"Thorn Lighting",
    "wof:placetype":"venue"
},
  "geometry": {"coordinates":[150.93632507300001,-33.838508606],"type":"Point"}
}