{
  "type": "Feature",
  "properties": {
    "iso:country":"AU",
    "sg:address":"38a Nash St",
    "sg:city":"Gympie",
    "sg:classifiers":[
        {
            "category":"Health Services",
            "subcategory":"Doctor",
            "type":"Services"
        }
    ],
    "sg:phone":"+61 7 5482 7368",
    "sg:postcode":"4570",
    "sg:province":"QLD",
    "sg:tags":[
        "medical",
        "practitioner"
    ],
    "wof:name":"Curley Ian R",
    "wof:placetype":"venue"
},
  "geometry": {"coordinates":[152.660354614,-26.1885032654],"type":"Point"}
}