{
  "type": "Feature",
  "properties": {
    "addr:full":"PO Box 913 Traralgon VIC 3844",
    "addr:postcode":"3844",
    "iso:country":"AU",
    "sg:address":"PO Box 913",
    "sg:city":"Traralgon",
    "sg:classifiers":[
        {
            "category":"Professional",
            "subcategory":"Art Services",
            "type":"Services"
        }
    ],
    "sg:phone":"+61 3 5175 0660",
    "sg:postcode":"3844",
    "sg:province":"VIC",
    "sg:tags":[
        "graphic",
        "designer"
    ],
    "wof:name":"KDH Advertising",
    "wof:placetype":"venue"
},
  "geometry": {"coordinates":[146.53814697300001,-38.1949501038],"type":"Point"}
}