{
  "type": "Feature",
  "properties": {
    "addr:full":"17 Thomas St Grange QLD 4051",
    "addr:housenumber":"17",
    "addr:postcode":"4051",
    "addr:street":"Thomas St",
    "iso:country":"AU",
    "sg:address":"17 Thomas St",
    "sg:city":"Grange",
    "sg:classifiers":[
        {
            "category":"Government",
            "subcategory":"Court House",
            "type":"Public Place"
        }
    ],
    "sg:phone":"+61 7 3356 4937",
    "sg:postcode":"4051",
    "sg:province":"QLD",
    "sg:tags":[
        "personal",
        "marriage",
        "family",
        "counselling"
    ],
    "wof:name":"Clinical Counselling Centre",
    "wof:placetype":"venue"
},
  "geometry": {"coordinates":[153.01411438,-27.4290142059],"type":"Point"}
}