{
  "type": "Feature",
  "properties": {
    "iso:country":"AU",
    "sg:address":"Cnr Kent & Pulgul Sts",
    "sg:city":"Urangan",
    "sg:classifiers":[
        {
            "category":"Retail",
            "subcategory":"Auto Repair",
            "type":"Services"
        }
    ],
    "sg:phone":"+61 7 4124 9308",
    "sg:postcode":"4655",
    "sg:province":"QLD",
    "sg:tags":[
        "repairer",
        "motor",
        "engineer"
    ],
    "wof:name":"UltraTune",
    "wof:placetype":"venue"
},
  "geometry": {"coordinates":[152.901566,-25.287195],"type":"Point"}
}