{
  "type": "Feature",
  "properties": {
    "addr:full":"150 Hobart Rd Kings Meadows TAS 7249",
    "addr:housenumber":"150",
    "addr:postcode":"7249",
    "addr:street":"Hobart Rd",
    "iso:country":"AU",
    "sg:address":"150 Hobart Rd",
    "sg:city":"Kings Meadows",
    "sg:classifiers":[
        {
            "category":"Wholesale",
            "subcategory":"Furniture",
            "type":"Manufacturing & Wholesale Goods"
        }
    ],
    "sg:phone":"+61 3 6343 5229",
    "sg:postcode":"7249",
    "sg:province":"TAS",
    "sg:tags":[
        "wholesaler",
        "mfrs"
    ],
    "wof:name":"Cover Up Furniture & Upholstery",
    "wof:placetype":"venue"
},
  "geometry": {"coordinates":[147.16139221200001,-41.4697761536],"type":"Point"}
}