{
  "type": "Feature",
  "properties": {
    "addr:full":"53 Beaudesert Rd Moorooka QLD 4105",
    "addr:housenumber":"53",
    "addr:postcode":"4105",
    "addr:street":"Beaudesert Rd",
    "iso:country":"AU",
    "sg:address":"53 Beaudesert Rd",
    "sg:city":"Moorooka",
    "sg:classifiers":[
        {
            "category":"Education",
            "subcategory":"Music School",
            "type":"Public Place"
        }
    ],
    "sg:phone":"+61 7 3848 4304",
    "sg:postcode":"4105",
    "sg:province":"QLD",
    "sg:tags":[
        "teacher"
    ],
    "wof:name":"D&#039;Arcy Cassandra",
    "wof:placetype":"venue"
},
  "geometry": {"coordinates":[153.022872925,-27.5280265808],"type":"Point"}
}