{
  "type": "Feature",
  "properties": {
    "addr:full":"6 Pulbrook Pde Hornsby NSW 2077",
    "addr:housenumber":"6",
    "addr:postcode":"2077",
    "addr:street":"Pulbrook Pde",
    "iso:country":"AU",
    "sg:address":"6 Pulbrook Pde",
    "sg:city":"Hornsby",
    "sg:classifiers":[
        {
            "category":"Professional",
            "subcategory":"Accounting & Tax Preparation",
            "type":"Services"
        }
    ],
    "sg:phone":"+61 2 9477 4240",
    "sg:postcode":"2077",
    "sg:province":"NSW",
    "sg:tags":[
        "accountant",
        "auditor"
    ],
    "wof:name":"Harris Consulting",
    "wof:placetype":"venue"
},
  "geometry": {"coordinates":[151.107788086,-33.6995697021],"type":"Point"}
}