{
  "type": "Feature",
  "properties": {
    "addr:full":"Shop 1/ 25 Manning St Tuncurry NSW 2428",
    "addr:housenumber":"shop 1 / 25",
    "addr:postcode":"2428",
    "addr:street":"Manning St",
    "iso:country":"AU",
    "sg:address":"Shop 1/ 25 Manning St",
    "sg:city":"Tuncurry",
    "sg:classifiers":[
        {
            "category":"Personal",
            "subcategory":"Beauty Salon",
            "type":"Services"
        }
    ],
    "sg:phone":"+61 2 6554 5501",
    "sg:postcode":"2428",
    "sg:province":"NSW",
    "wof:name":"Aaqua Marine Day Spa",
    "wof:placetype":"venue"
},
  "geometry": {"coordinates":[152.49896200000001,-32.173714],"type":"Point"}
}