{
  "type": "Feature",
  "properties": {
    "addr:full":"59 Lord St Gladstone QLD 4680",
    "addr:housenumber":"59",
    "addr:postcode":"4680",
    "addr:street":"Lord St",
    "iso:country":"AU",
    "sg:address":"59 Lord St",
    "sg:city":"Gladstone",
    "sg:classifiers":[
        {
            "category":"Retail",
            "subcategory":"Auto Repair",
            "type":"Services"
        }
    ],
    "sg:phone":"+61 7 4972 3283",
    "sg:postcode":"4680",
    "sg:province":"QLD",
    "sg:tags":[
        "beater",
        "painter",
        "panel"
    ],
    "wof:name":"Thrings Body Works",
    "wof:placetype":"venue"
},
  "geometry": {"coordinates":[151.24827575699999,-23.8421401978],"type":"Point"}
}