{
  "type": "Feature",
  "properties": {
    "addr:full":"Unit 8/ 29 Coombes Drv Penrith NSW 2750",
    "addr:housenumber":"29",
    "addr:postcode":"2750",
    "addr:street":"Coombes Drv",
    "iso:country":"AU",
    "sg:address":"Unit 8/ 29 Coombes Drv",
    "sg:city":"Penrith",
    "sg:classifiers":[
        {
            "category":"Building & Trades",
            "subcategory":"Plumbing",
            "type":"Services"
        }
    ],
    "sg:phone":"+61 2 4722 2244",
    "sg:postcode":"2750",
    "sg:province":"NSW",
    "sg:tags":[
        "plumber",
        "gasfitters"
    ],
    "wof:name":"Leonay Plumbing Pty Ltd.",
    "wof:placetype":"venue"
},
  "geometry": {"coordinates":[150.702514648,-33.7432556152],"type":"Point"}
}