{
  "type": "Feature",
  "properties": {
    "iso:country":"AU",
    "sg:address":"30b Agnes St",
    "sg:city":"Kingston SE",
    "sg:classifiers":[
        {
            "category":"Professional",
            "subcategory":"Accounting & Tax Preparation",
            "type":"Services"
        }
    ],
    "sg:phone":"+61 8 8767 2928",
    "sg:postcode":"5275",
    "sg:province":"SA",
    "sg:tags":[
        "consultant",
        "taxation"
    ],
    "wof:name":"Murray Nankivell",
    "wof:placetype":"venue"
},
  "geometry": {"coordinates":[139.856964,-36.828999],"type":"Point"}
}