{
  "type": "Feature",
  "properties": {
    "addr:full":"10 Webb St Croydon NSW 2132",
    "addr:housenumber":"10",
    "addr:postcode":"2132",
    "addr:street":"Webb St",
    "iso:country":"AU",
    "sg:address":"10 Webb St",
    "sg:city":"Croydon",
    "sg:classifiers":[
        {
            "category":"Autos & Motor Vehicles",
            "subcategory":"Automobile Sales",
            "type":"Retail Goods"
        }
    ],
    "sg:phone":"+61 409 518 275",
    "sg:postcode":"2132",
    "sg:province":"NSW",
    "sg:tags":[
        "car",
        "used"
    ],
    "wof:name":"Sellfast Pty Ltd",
    "wof:placetype":"venue"
},
  "geometry": {"coordinates":[151.11349487300001,-33.8781394958],"type":"Point"}
}