{
  "type": "Feature",
  "properties": {
    "addr:full":"Fcty3/ 189 Cheltenham Rd Keysborough VIC 3173",
    "addr:housenumber":"189",
    "addr:postcode":"3173",
    "addr:street":"Cheltenham Rd",
    "iso:country":"AU",
    "sg:address":"Fcty3/ 189 Cheltenham Rd",
    "sg:city":"Keysborough",
    "sg:classifiers":[
        {
            "category":"Professional",
            "type":"Services"
        }
    ],
    "sg:phone":"+61 3 9701 5181",
    "sg:postcode":"3173",
    "sg:province":"VIC",
    "sg:tags":[
        "shop",
        "fitting"
    ],
    "wof:name":"Direct Shopfitting",
    "wof:placetype":"venue"
},
  "geometry": {"coordinates":[145.189727783,-37.9927330017],"type":"Point"}
}