{
  "type": "Feature",
  "properties": {
    "iso:country":"AU",
    "sg:address":"51 Beulah Rd",
    "sg:city":"Norwood",
    "sg:classifiers":[
        {
            "category":"Professional",
            "subcategory":"Printing & Photocopies",
            "type":"Services"
        }
    ],
    "sg:phone":"+61 8 8212 2277",
    "sg:postcode":"5067",
    "sg:province":"SA",
    "sg:tags":[
        "photocopier"
    ],
    "wof:name":"Metropolitan Business Equipment",
    "wof:placetype":"venue"
},
  "geometry": {"coordinates":[138.63130188,-34.918182373],"type":"Point"}
}