{
  "type": "Feature",
  "properties": {
    "iso:country":"AU",
    "sg:address":"Abbotsfield Rd",
    "sg:city":"Claremont",
    "sg:classifiers":[
        {
            "category":"Education",
            "subcategory":"School",
            "type":"Public Place"
        }
    ],
    "sg:phone":"+61 3 6249 2639",
    "sg:postcode":"7011",
    "sg:province":"TAS",
    "sg:tags":[
        "state",
        "except",
        "nsw"
    ],
    "wof:name":"Abbotsfield Primary School",
    "wof:placetype":"venue"
},
  "geometry": {"coordinates":[147.24586486800001,-42.7885627747],"type":"Point"}
}