{
  "type": "Feature",
  "properties": {
    "addr:full":"270 Hillsborough Rd Warners Bay NSW 2282",
    "addr:housenumber":"270",
    "addr:postcode":"2282",
    "addr:street":"Hillsborough Rd",
    "iso:country":"AU",
    "sg:address":"270 Hillsborough Rd",
    "sg:city":"Warners Bay",
    "sg:classifiers":[
        {
            "category":"Retail",
            "subcategory":"Event Space",
            "type":"Services"
        }
    ],
    "sg:phone":"+61 1300 851 112",
    "sg:postcode":"2282",
    "sg:province":"NSW",
    "sg:tags":[
        "venue",
        "reception",
        "wedding"
    ],
    "wof:name":"Glades Wedding & Conference Centre The",
    "wof:placetype":"venue"
},
  "geometry": {"coordinates":[151.658935547,-32.9644737244],"type":"Point"}
}