{
  "type": "Feature",
  "properties": {
    "addr:full":"205 Armstrong Sth St Ballarat VIC 3350",
    "addr:housenumber":"205",
    "addr:postcode":"3350",
    "addr:street":"Armstrong Sth St",
    "iso:country":"AU",
    "sg:address":"205 Armstrong Sth St",
    "sg:city":"Ballarat",
    "sg:classifiers":[
        {
            "category":"Home & Garden",
            "subcategory":"Carpets & Floor Coverings",
            "type":"Retail Goods"
        }
    ],
    "sg:phone":"+61 413 046 030",
    "sg:postcode":"3350",
    "sg:province":"VIC",
    "sg:tags":[
        "wood"
    ],
    "wof:name":"Master Plus",
    "wof:placetype":"venue"
},
  "geometry": {"coordinates":[143.85557600000001,-37.566433],"type":"Point"}
}