{
  "type": "Feature",
  "properties": {
    "addr:full":"\"Famidale\" Adams Rd Yanakie VIC 3960",
    "addr:postcode":"3960",
    "addr:street":"Adams Rd",
    "iso:country":"AU",
    "sg:address":"\"Famidale\" Adams Rd",
    "sg:city":"Yanakie",
    "sg:classifiers":[
        {
            "category":"Professional",
            "subcategory":"Management & Consulting",
            "type":"Services"
        }
    ],
    "sg:phone":"+61 3 5687 1380",
    "sg:postcode":"3960",
    "sg:province":"VIC",
    "sg:tags":[
        "consultant",
        "educational"
    ],
    "wof:name":"Ewart Special Ed Services",
    "wof:placetype":"venue"
},
  "geometry": {"coordinates":[146.15786743199999,-38.7893943787],"type":"Point"}
}