{
  "type": "Feature",
  "properties": {
    "iso:country":"AU",
    "sg:address":"2 Wharf St",
    "sg:city":"Murwillumbah",
    "sg:classifiers":[
        {
            "category":"Cafe",
            "type":"Food & Drink"
        }
    ],
    "sg:phone":"+61 2 6672 8590",
    "sg:postcode":"2484",
    "sg:province":"NSW",
    "wof:name":"Wharf St Cafe",
    "wof:placetype":"venue"
},
  "geometry": {"coordinates":[153.39944457999999,-28.3271827698],"type":"Point"}
}