{
  "type": "Feature",
  "properties": {
    "addr:full":"18 Lester Hansen St Slade Point QLD 4740",
    "addr:housenumber":"18",
    "addr:postcode":"4740",
    "addr:street":"Lester Hansen St",
    "iso:country":"AU",
    "sg:address":"18 Lester Hansen St",
    "sg:city":"Slade Point",
    "sg:classifiers":[
        {
            "category":"Real Estate",
            "subcategory":"Architect",
            "type":"Services"
        }
    ],
    "sg:phone":"+61 408 202 134",
    "sg:postcode":"4740",
    "sg:province":"QLD",
    "sg:tags":[
        "builder",
        "repairer",
        "ship"
    ],
    "wof:name":"Vision Yachts",
    "wof:placetype":"venue"
},
  "geometry": {"coordinates":[149.214539,-21.087542],"type":"Point"}
}