{
  "type": "Feature",
  "properties": {
    "addr:full":"49 Dion Crs Riverside TAS 7250",
    "addr:housenumber":"49",
    "addr:postcode":"7250",
    "addr:street":"Dion Crs",
    "iso:country":"AU",
    "sg:address":"49 Dion Crs",
    "sg:city":"Riverside",
    "sg:classifiers":[
        {
            "category":"Building & Trades",
            "subcategory":"Landscaping Services",
            "type":"Services"
        }
    ],
    "sg:phone":"+61 3 6327 2991",
    "sg:postcode":"7250",
    "sg:province":"TAS",
    "sg:tags":[
        "gardener"
    ],
    "wof:name":"Clarke Max",
    "wof:placetype":"venue"
},
  "geometry": {"coordinates":[147.092849731,-41.4066505432],"type":"Point"}
}