{
  "type": "Feature",
  "properties": {
    "addr:full":"39 Laverick Ave Tomago NSW 2322",
    "addr:housenumber":"39",
    "addr:postcode":"2322",
    "addr:street":"Laverick Ave",
    "iso:country":"AU",
    "sg:address":"39 Laverick Ave",
    "sg:city":"Tomago",
    "sg:classifiers":[
        {
            "category":"Professional",
            "subcategory":"Engineering",
            "type":"Services"
        }
    ],
    "sg:phone":"+61 2 4964 8648",
    "sg:postcode":"2322",
    "sg:province":"NSW",
    "sg:tags":[
        "electrical",
        "engineer"
    ],
    "wof:name":"Rutherford Power Pty Ltd",
    "wof:placetype":"venue"
},
  "geometry": {"coordinates":[151.70701599099999,-32.8266487122],"type":"Point"}
}