{
  "type": "Feature",
  "properties": {
    "addr:full":"149 Barker St Casino NSW 2470",
    "addr:housenumber":"149",
    "addr:postcode":"2470",
    "addr:street":"Barker St",
    "iso:country":"AU",
    "sg:address":"149 Barker St",
    "sg:city":"Casino",
    "sg:classifiers":[
        {
            "category":"Health Services",
            "subcategory":"Health Practitioner",
            "type":"Services"
        }
    ],
    "sg:phone":"+61 2 6662 4753",
    "sg:postcode":"2470",
    "sg:province":"NSW",
    "sg:tags":[
        "acupuncture"
    ],
    "wof:name":"Alberth, Mich\ufffdle",
    "wof:placetype":"venue"
},
  "geometry": {"coordinates":[153.04876709000001,-28.8651638031],"type":"Point"}
}