{
  "type": "Feature",
  "properties": {
    "iso:country":"AU",
    "sg:address":"132 Scrub Hill Rd",
    "sg:city":"Pialba",
    "sg:classifiers":[
        {
            "category":"Home & Garden",
            "subcategory":"Garden Supply",
            "type":"Retail Goods"
        }
    ],
    "sg:phone":"+61 7 4124 1769",
    "sg:postcode":"4655",
    "sg:province":"QLD",
    "sg:tags":[
        "fertilizer"
    ],
    "wof:name":"Daniell's Nursery & Garden Supplies",
    "wof:placetype":"venue"
},
  "geometry": {"coordinates":[152.807434,-25.302099],"type":"Point"}
}