{
  "type": "Feature",
  "properties": {
    "addr:full":"20 Faunce St Queanbeyan NSW 2620",
    "addr:housenumber":"20",
    "addr:postcode":"2620",
    "addr:street":"Faunce St",
    "iso:country":"AU",
    "sg:address":"20 Faunce St",
    "sg:city":"Queanbeyan",
    "sg:classifiers":[
        {
            "category":"Home & Garden",
            "subcategory":"Hardware",
            "type":"Retail Goods"
        }
    ],
    "sg:phone":"+61 2 6299 0833",
    "sg:postcode":"2620",
    "sg:province":"NSW",
    "sg:tags":[
        "pipe",
        "fitting",
        "plastic"
    ],
    "wof:name":"Pipe King",
    "wof:placetype":"venue"
},
  "geometry": {"coordinates":[149.24964904800001,-35.3413772583],"type":"Point"}
}