{
  "type": "Feature",
  "properties": {
    "addr:full":"4/ 402 Warrandyte Heidelberg Rd Warrandyte VIC 3113",
    "addr:housenumber":"/ 402",
    "addr:postcode":"3113",
    "addr:street":"Heidelberg Rd",
    "iso:country":"AU",
    "sg:address":"4/ 402 Warrandyte Heidelberg Rd",
    "sg:city":"Warrandyte",
    "sg:classifiers":[
        {
            "category":"Health Services",
            "subcategory":"Doctor",
            "type":"Services"
        }
    ],
    "sg:phone":"+61 3 9844 0466",
    "sg:postcode":"3113",
    "sg:province":"VIC",
    "sg:tags":[
        "medical",
        "practitioner"
    ],
    "wof:name":"Reid Gail Dr",
    "wof:placetype":"venue"
},
  "geometry": {"coordinates":[145.207275391,-37.7470626831],"type":"Point"}
}