{
  "type": "Feature",
  "properties": {
    "addr:full":"71 Massie St Cooma NSW 2630",
    "addr:housenumber":"71",
    "addr:postcode":"2630",
    "addr:street":"Massie St",
    "iso:country":"AU",
    "sg:address":"71 Massie St",
    "sg:city":"Cooma",
    "sg:classifiers":[
        {
            "category":"Shopping",
            "type":"Retail Goods"
        }
    ],
    "sg:phone":"+61 2 6452 1000",
    "sg:postcode":"2630",
    "sg:province":"NSW",
    "sg:tags":[
        "agent",
        "stock"
    ],
    "wof:name":"Elders Limited",
    "wof:placetype":"venue"
},
  "geometry": {"coordinates":[149.125854492,-36.2335090637],"type":"Point"}
}