{
  "type": "Feature",
  "properties": {
    "addr:full":"18 Hedland Pl Karratha WA 6714",
    "addr:housenumber":"18",
    "addr:postcode":"6714",
    "addr:street":"Hedland Pl Karratha",
    "iso:country":"AU",
    "sg:address":"18 Hedland Pl",
    "sg:city":"Karratha",
    "sg:classifiers":[
        {
            "category":"Personal",
            "subcategory":"Beauty Salon",
            "type":"Services"
        }
    ],
    "sg:phone":"+61 8 9185 1892",
    "sg:postcode":"6714",
    "sg:province":"WA",
    "sg:tags":[
        "hairdresser"
    ],
    "wof:name":"Lorraes Hair Studio",
    "wof:placetype":"venue"
},
  "geometry": {"coordinates":[116.84796905499999,-20.7340354919],"type":"Point"}
}