{
  "type": "Feature",
  "properties": {
    "addr:full":"6-8 Darley Rd Upper Caboolture QLD 4510",
    "addr:housenumber":"6-8",
    "addr:postcode":"4510",
    "addr:street":"Darley Rd",
    "iso:country":"AU",
    "sg:address":"6-8 Darley Rd",
    "sg:city":"Upper Caboolture",
    "sg:classifiers":[
        {
            "category":"Freight",
            "type":"Transportation"
        }
    ],
    "sg:phone":"+61 423 639 237",
    "sg:postcode":"4510",
    "sg:province":"QLD",
    "sg:tags":[
        "cargo",
        "container"
    ],
    "wof:name":"Bj Container Hire Childers",
    "wof:placetype":"venue"
},
  "geometry": {"coordinates":[152.90917999999999,-27.10626],"type":"Point"}
}