{
  "type": "Feature",
  "properties": {
    "addr:full":"Shp2a/ 16 Doig St Cleveland QLD 4163",
    "addr:postcode":"4163",
    "addr:street":"Doig St",
    "iso:country":"AU",
    "sg:address":"Shp2a/ 16 Doig St",
    "sg:city":"Cleveland",
    "sg:classifiers":[
        {
            "category":"Personal",
            "subcategory":"Beauty Salon",
            "type":"Services"
        }
    ],
    "sg:phone":"+61 7 3821 0244",
    "sg:postcode":"4163",
    "sg:province":"QLD",
    "sg:tags":[
        "hairdresser"
    ],
    "wof:name":"Allusion Hair & Beauty",
    "wof:placetype":"venue"
},
  "geometry": {"coordinates":[153.26568603499999,-27.5276851654],"type":"Point"}
}