{
  "type": "Feature",
  "properties": {
    "iso:country":"AU",
    "sg:address":"Diamond St",
    "sg:city":"Eltham",
    "sg:classifiers":[
        {
            "category":"Social Services",
            "subcategory":"Adult Care",
            "type":"Services"
        }
    ],
    "sg:phone":"+61 3 9431 0100",
    "sg:postcode":"3095",
    "sg:province":"VIC",
    "sg:tags":[
        "aged"
    ],
    "wof:name":"Melbourne Citymission",
    "wof:placetype":"venue"
},
  "geometry": {"coordinates":[145.14907836899999,-37.7115707397],"type":"Point"}
}