{
  "type": "Feature",
  "properties": {
    "addr:full":"3 Amsted Rd Bayswater VIC 3153",
    "addr:housenumber":"3",
    "addr:postcode":"3153",
    "addr:street":"Amsted Rd",
    "iso:country":"AU",
    "sg:address":"3 Amsted Rd",
    "sg:city":"Bayswater",
    "sg:classifiers":[
        {
            "category":"Professional",
            "subcategory":"Engineering",
            "type":"Services"
        }
    ],
    "sg:phone":"+61 3 9762 5733",
    "sg:postcode":"3153",
    "sg:province":"VIC",
    "sg:tags":[
        "engineer"
    ],
    "wof:name":"Henka Engineering (Aust) Pty Ltd",
    "wof:placetype":"venue"
},
  "geometry": {"coordinates":[145.28480529800001,-37.8446121216],"type":"Point"}
}