{
  "type": "Feature",
  "properties": {
    "addr:full":"8 Miami Pl Launceston TAS 7250",
    "addr:housenumber":"8",
    "addr:postcode":"7250",
    "addr:street":"Pl",
    "iso:country":"AU",
    "sg:address":"8 Miami Pl",
    "sg:city":"Launceston",
    "sg:classifiers":[
        {
            "category":"Professional",
            "subcategory":"Art Services",
            "type":"Services"
        }
    ],
    "sg:phone":"+61 3 6344 9628",
    "sg:postcode":"7250",
    "sg:province":"TAS",
    "sg:tags":[
        "commercial",
        "artist"
    ],
    "wof:name":"Allanby Signs & Design Service",
    "wof:placetype":"venue"
},
  "geometry": {"coordinates":[147.17230224599999,-41.4813690186],"type":"Point"}
}