{
  "type": "Feature",
  "properties": {
    "addr:full":"18 Addison St Shellharbour NSW 2529",
    "addr:housenumber":"18",
    "addr:postcode":"2529",
    "addr:street":"Addison St",
    "iso:country":"AU",
    "sg:address":"18 Addison St",
    "sg:city":"Shellharbour",
    "sg:classifiers":[
        {
            "category":"Communications",
            "subcategory":"Film & Video Production",
            "type":"Services"
        }
    ],
    "sg:phone":"+61 2 4297 8880",
    "sg:postcode":"2529",
    "sg:province":"NSW",
    "sg:tags":[
        "dvd",
        "library"
    ],
    "wof:name":"Leading Edge Video Shellharbour",
    "wof:placetype":"venue"
},
  "geometry": {"coordinates":[150.86749267600001,-34.579334259],"type":"Point"}
}