{
  "type": "Feature",
  "properties": {
    "addr:full":"19 Jared Rd Altona Meadows VIC 3028",
    "addr:housenumber":"19",
    "addr:postcode":"3028",
    "addr:street":"Jared Rd",
    "iso:country":"AU",
    "sg:address":"19 Jared Rd",
    "sg:city":"Altona Meadows",
    "sg:classifiers":[
        {
            "category":"Shopping",
            "subcategory":"Clothing, Apparel, & Fashions",
            "type":"Retail Goods"
        }
    ],
    "sg:phone":"+61 413 334 501",
    "sg:postcode":"3028",
    "sg:province":"VIC",
    "sg:tags":[
        "menswear"
    ],
    "wof:name":"Formal Wear Express",
    "wof:placetype":"venue"
},
  "geometry": {"coordinates":[144.769318,-37.88073],"type":"Point"}
}