{
  "type": "Feature",
  "properties": {
    "addr:full":"1 Solander Rd Kings Langley NSW 2147",
    "addr:housenumber":"1",
    "addr:postcode":"2147",
    "addr:street":"Solander Rd",
    "iso:country":"AU",
    "sg:address":"1 Solander Rd",
    "sg:city":"Kings Langley",
    "sg:classifiers":[
        {
            "category":"Food & Beverages",
            "subcategory":"Liquor & Beverages",
            "type":"Retail Goods"
        }
    ],
    "sg:phone":"+61 2 9624 3475",
    "sg:postcode":"2147",
    "sg:province":"NSW",
    "sg:tags":[
        "store"
    ],
    "wof:name":"Kings Langley Cellars",
    "wof:placetype":"venue"
},
  "geometry": {"coordinates":[150.942749023,-33.7542762756],"type":"Point"}
}