{
  "type": "Feature",
  "properties": {
    "addr:full":"U5/ 10 McCourt St West Leederville WA 6007",
    "addr:housenumber":"10",
    "addr:postcode":"6007",
    "addr:street":"U5 /;Mccourt St West",
    "iso:country":"AU",
    "sg:address":"U5/ 10 McCourt St",
    "sg:city":"West Leederville",
    "sg:classifiers":[
        {
            "category":"Health Services",
            "subcategory":"Doctor",
            "type":"Services"
        }
    ],
    "sg:phone":"+61 8 9388 7145",
    "sg:postcode":"6007",
    "sg:province":"WA",
    "sg:tags":[
        "medical",
        "practitioner"
    ],
    "wof:name":"Walsh P.J.",
    "wof:placetype":"venue"
},
  "geometry": {"coordinates":[115.827850342,-31.9428043365],"type":"Point"}
}