{
  "type": "Feature",
  "properties": {
    "addr:full":"31 Station Rd Margaret River WA 6285",
    "addr:housenumber":"31",
    "addr:postcode":"6285",
    "addr:street":"Station Rd",
    "iso:country":"AU",
    "sg:address":"31 Station Rd",
    "sg:city":"Margaret River",
    "sg:classifiers":[
        {
            "category":"Deli",
            "type":"Food & Drink"
        }
    ],
    "sg:phone":"+61 8 9757 9012",
    "sg:postcode":"6285",
    "sg:province":"WA",
    "sg:tags":[
        "delicatessen"
    ],
    "wof:name":"The Foodroom",
    "wof:placetype":"venue"
},
  "geometry": {"coordinates":[115.06996154799999,-33.9575271606],"type":"Point"}
}