{
  "type": "Feature",
  "properties": {
    "iso:country":"AU",
    "sg:address":"31 Station Rd",
    "sg:city":"Margaret River",
    "sg:classifiers":[
        {
            "category":"Deli",
            "type":"Food & Drink"
        }
    ],
    "sg:phone":"+61 8 9757 9012",
    "sg:postcode":"6285",
    "sg:province":"WA",
    "sg:tags":[
        "delicatessen"
    ],
    "wof:name":"The Foodroom",
    "wof:placetype":"venue"
},
  "geometry": {"coordinates":[115.06996154799999,-33.9575271606],"type":"Point"}
}