{
  "type": "Feature",
  "properties": {
    "iso:country":"AU",
    "sg:address":"68- 70 Parramatta Rd",
    "sg:city":"Underwood",
    "sg:classifiers":[
        {
            "category":"Manufacturing",
            "subcategory":"Tools & Machinery",
            "type":"Manufacturing & Wholesale Goods"
        }
    ],
    "sg:phone":"+61 7 3808 9851",
    "sg:postcode":"4119",
    "sg:province":"QLD",
    "sg:tags":[
        "equipment",
        "scale",
        "weighing"
    ],
    "wof:name":"Wedderburn Scales",
    "wof:placetype":"venue"
},
  "geometry": {"coordinates":[153.118865967,-27.617559433],"type":"Point"}
}