{
  "type": "Feature",
  "properties": {
    "iso:country":"AU",
    "sg:address":"70 Gemvale Rd",
    "sg:city":"Reedy Creek",
    "sg:classifiers":[
        {
            "category":"Education",
            "subcategory":"Junior College",
            "type":"Public Place"
        }
    ],
    "sg:phone":"+61 7 5593 4386",
    "sg:postcode":"4228",
    "sg:province":"QLD",
    "sg:tags":[
        "business"
    ],
    "wof:name":"King's International College",
    "wof:placetype":"venue"
},
  "geometry": {"coordinates":[153.39840698200001,-28.0982608795],"type":"Point"}
}