{
  "type": "Feature",
  "properties": {
    "addr:full":"Benowa Gardens Shopping Centre Cnr Ashmore & Benow Benowa QLD 4217",
    "addr:postcode":"4217",
    "addr:street":"Cnr",
    "iso:country":"AU",
    "sg:address":"Benowa Gardens Shopping Centre Cnr Ashmore & Benow",
    "sg:city":"Benowa",
    "sg:classifiers":[
        {
            "category":"Arts & Performance",
            "subcategory":"Art Gallery",
            "type":"Entertainment"
        }
    ],
    "sg:phone":"+61 7 5597 6414",
    "sg:postcode":"4217",
    "sg:province":"QLD",
    "wof:name":"Bruce Macfie Gallery Of Fine Art",
    "wof:placetype":"venue"
},
  "geometry": {"coordinates":[153.391082764,-28.00989151],"type":"Point"}
}