{
  "type": "Feature",
  "properties": {
    "iso:country":"AU",
    "sg:address":"Cnr Sheridan & Upward Sts",
    "sg:city":"Cairns North",
    "sg:classifiers":[
        {
            "category":"Education",
            "subcategory":"School",
            "type":"Public Place"
        }
    ],
    "sg:phone":"+61 7 4050 3033",
    "sg:postcode":"4870",
    "sg:province":"QLD",
    "wof:name":"Cairns High School",
    "wof:placetype":"venue"
},
  "geometry": {"coordinates":[145.75787353499999,-16.9035758972],"type":"Point"}
}