{
  "type": "Feature",
  "properties": {
    "iso:country":"AU",
    "sg:address":"107 Murilla St",
    "sg:city":"Miles",
    "sg:classifiers":[
        {
            "category":"Retail",
            "subcategory":"Funeral Services",
            "type":"Services"
        }
    ],
    "sg:phone":"+61 7 4627 2494",
    "sg:postcode":"4415",
    "sg:province":"QLD",
    "sg:tags":[
        "cremation"
    ],
    "wof:name":"Courtesy Funerals",
    "wof:placetype":"venue"
},
  "geometry": {"coordinates":[150.18989563,-26.6596603394],"type":"Point"}
}