{
  "type": "Feature",
  "properties": {
    "addr:full":"12029 Carnarvon Hwy St George QLD 4487",
    "addr:housenumber":"12029",
    "addr:postcode":"4487",
    "addr:street":"Carnarvon Hwy",
    "iso:country":"AU",
    "sg:address":"12029 Carnarvon Hwy",
    "sg:city":"St George",
    "sg:classifiers":[
        {
            "category":"Retail",
            "subcategory":"Veterinary Services",
            "type":"Services"
        }
    ],
    "sg:phone":"+61 7 4625 5929",
    "sg:postcode":"4487",
    "sg:province":"QLD",
    "sg:tags":[
        "surgeon"
    ],
    "wof:name":"Goodwin Chris",
    "wof:placetype":"venue"
},
  "geometry": {"coordinates":[148.58958435100001,-28.0445137024],"type":"Point"}
}