{
  "type": "Feature",
  "properties": {
    "addr:full":"Suite 2 / Crows Nest NSW 2065",
    "addr:housenumber":"/",
    "addr:postcode":"2065",
    "iso:country":"AU",
    "sg:address":"Suite 2",
    "sg:city":"/ Crows Nest",
    "sg:classifiers":[
        {
            "category":"Food & Beverages",
            "subcategory":"Liquor & Beverages",
            "type":"Retail Goods"
        }
    ],
    "sg:phone":"+61 2 9929 3722",
    "sg:postcode":"2065",
    "sg:province":"NSW",
    "sg:tags":[
        "merchant",
        "spirit",
        "wine"
    ],
    "wof:name":"Haviland Wine Merchants",
    "wof:placetype":"venue"
},
  "geometry": {"coordinates":[151.19818115199999,-33.8367576599],"type":"Point"}
}