{
  "type": "Feature",
  "properties": {
    "iso:country":"AU",
    "sg:address":"3 Innes St",
    "sg:city":"Five Dock",
    "sg:classifiers":[
        {
            "category":"Building & Trades",
            "subcategory":"Plumbing",
            "type":"Services"
        }
    ],
    "sg:phone":"+61 2 9713 2877",
    "sg:postcode":"2046",
    "sg:province":"NSW",
    "sg:tags":[
        "plumber",
        "gasfitters"
    ],
    "wof:name":"Abbotsford Plumbing P/L",
    "wof:placetype":"venue"
},
  "geometry": {"coordinates":[151.129303,-33.863678],"type":"Point"}
}