{
  "type": "Feature",
  "properties": {
    "addr:full":"Shop 4/ 1098 Ipswich Rd Moorooka QLD 4105",
    "addr:housenumber":"shop 4 / 1098",
    "addr:postcode":"4105",
    "addr:street":"Ipswich Rd",
    "iso:country":"AU",
    "sg:address":"Shop 4/ 1098 Ipswich Rd",
    "sg:city":"Moorooka",
    "sg:classifiers":[
        {
            "category":"Autos & Motor Vehicles",
            "subcategory":"Auto Supplies",
            "type":"Retail Goods"
        }
    ],
    "sg:phone":"+61 7 3848 3972",
    "sg:postcode":"4105",
    "sg:province":"QLD",
    "sg:tags":[
        "accessory"
    ],
    "wof:name":"Autopro",
    "wof:placetype":"venue"
},
  "geometry": {"coordinates":[153.01495361299999,-27.5351829529],"type":"Point"}
}