{
  "type": "Feature",
  "properties": {
    "addr:full":"81 Rankin Rd Ferntree Gully VIC 3156",
    "addr:housenumber":"81",
    "addr:postcode":"3156",
    "addr:street":"Rankin Rd",
    "iso:country":"AU",
    "sg:address":"81 Rankin Rd",
    "sg:city":"Ferntree Gully",
    "sg:classifiers":[
        {
            "category":"Communications",
            "type":"Services"
        }
    ],
    "sg:phone":"+61 3 9758 8079",
    "sg:postcode":"3156",
    "sg:province":"VIC",
    "sg:tags":[
        "equipment",
        "radio"
    ],
    "wof:name":"Portable Communication Services",
    "wof:placetype":"venue"
},
  "geometry": {"coordinates":[145.27084350600001,-37.870388031],"type":"Point"}
}