{
  "type": "Feature",
  "properties": {
    "addr:full":"276- 296 Alfred St St George QLD 4487",
    "addr:housenumber":"296",
    "addr:postcode":"4487",
    "addr:street":"Alfred St",
    "iso:country":"AU",
    "sg:address":"276- 296 Alfred St St",
    "sg:city":"George",
    "sg:classifiers":[
        {
            "category":"Social Services",
            "subcategory":"Child Care",
            "type":"Services"
        }
    ],
    "sg:phone":"+61 7 4625 5150",
    "sg:postcode":"4487",
    "sg:province":"QLD",
    "wof:name":"Warrawee Early Childhood Centre",
    "wof:placetype":"venue"
},
  "geometry": {"coordinates":[148.568115234,-28.0493392944],"type":"Point"}
}