{
  "type": "Feature",
  "properties": {
    "iso:country":"AU",
    "sg:address":"41- 43 Georgetown Rd",
    "sg:city":"Georgetown",
    "sg:classifiers":[
        {
            "category":"Manufacturing",
            "subcategory":"Food",
            "type":"Manufacturing & Wholesale Goods"
        }
    ],
    "sg:phone":"+61 2 4968 1381",
    "sg:postcode":"2298",
    "sg:province":"NSW",
    "sg:tags":[
        "function",
        "catering"
    ],
    "wof:name":"Henny Penny Foods",
    "wof:placetype":"venue"
},
  "geometry": {"coordinates":[151.73011779800001,-32.9085426331],"type":"Point"}
}