{
  "type": "Feature",
  "properties": {
    "addr:full":"PO Box 1112 Tully QLD 4854",
    "addr:postcode":"4854",
    "iso:country":"AU",
    "sg:address":"PO Box 1112",
    "sg:city":"Tully",
    "sg:classifiers":[
        {
            "category":"Building & Trades",
            "subcategory":"Plumbing",
            "type":"Services"
        }
    ],
    "sg:phone":"+61 7 4068 2799",
    "sg:postcode":"4854",
    "sg:province":"QLD",
    "sg:tags":[
        "plumber",
        "gasfitters"
    ],
    "wof:name":"Ando's Plumbing Service",
    "wof:placetype":"venue"
},
  "geometry": {"coordinates":[145.93263244600001,-17.933889389],"type":"Point"}
}