{
  "type": "Feature",
  "properties": {
    "addr:full":"PO Box 99 Woodford NSW 2778",
    "addr:postcode":"2778",
    "iso:country":"AU",
    "sg:address":"PO Box 99",
    "sg:city":"Woodford",
    "sg:classifiers":[
        {
            "category":"Shopping",
            "subcategory":"Crafts & Fabrics",
            "type":"Retail Goods"
        }
    ],
    "sg:phone":"+61 2 4758 8122",
    "sg:postcode":"2778",
    "sg:province":"NSW",
    "sg:tags":[
        "supply"
    ],
    "wof:name":"Cotton Patch The",
    "wof:placetype":"venue"
},
  "geometry": {"coordinates":[150.47720336899999,-33.7344589233],"type":"Point"}
}