{
  "type": "Feature",
  "properties": {
    "addr:full":"14 Halls Rd Arcadia NSW 2159",
    "addr:housenumber":"14",
    "addr:postcode":"2159",
    "addr:street":"Halls Rd",
    "iso:country":"AU",
    "sg:address":"14 Halls Rd",
    "sg:city":"Arcadia",
    "sg:classifiers":[
        {
            "category":"Farming",
            "subcategory":"Nursery",
            "type":"Manufacturing & Wholesale Goods"
        }
    ],
    "sg:phone":"+61 2 9653 2511",
    "sg:postcode":"2159",
    "sg:province":"NSW",
    "wof:name":"Total Plant Solutions",
    "wof:placetype":"venue"
},
  "geometry": {"coordinates":[151.034255981,-33.6281356812],"type":"Point"}
}