{
  "type": "Feature",
  "properties": {
    "addr:full":"342 Saunders Rd Oakville NSW 2765",
    "addr:housenumber":"342",
    "addr:postcode":"2765",
    "addr:street":"Saunders Rd",
    "iso:country":"AU",
    "sg:address":"342 Saunders Rd",
    "sg:city":"Oakville",
    "sg:classifiers":[
        {
            "category":"Farming",
            "subcategory":"Nursery",
            "type":"Manufacturing & Wholesale Goods"
        }
    ],
    "sg:phone":"+61 2 4573 6386",
    "sg:postcode":"2765",
    "sg:province":"NSW",
    "wof:name":"Bellamy's Nursery Pty Ltd",
    "wof:placetype":"venue"
},
  "geometry": {"coordinates":[150.887008667,-33.6183433533],"type":"Point"}
}