{
  "type": "Feature",
  "properties": {
    "addr:full":"Glenarvon Rd Lorn NSW 2320",
    "addr:postcode":"2320",
    "addr:street":"Glenarvon Rd",
    "iso:country":"AU",
    "sg:address":"Glenarvon Rd",
    "sg:city":"Lorn",
    "sg:classifiers":[
        {
            "category":"Home & Garden",
            "subcategory":"Garden Supply",
            "type":"Retail Goods"
        }
    ],
    "sg:phone":"+61 427 447 121",
    "sg:postcode":"2320",
    "sg:province":"NSW",
    "sg:tags":[
        "turf",
        "lawn"
    ],
    "wof:name":"Terrace Turf Supplies",
    "wof:placetype":"venue"
},
  "geometry": {"coordinates":[151.56640625,-32.7242050171],"type":"Point"}
}