{
  "type": "Feature",
  "properties": {
    "addr:full":"56 Cummins Rd Wagga Wagga NSW 2650",
    "addr:housenumber":"56",
    "addr:postcode":"2650",
    "addr:street":"Cummins Rd",
    "iso:country":"AU",
    "sg:address":"56 Cummins Rd",
    "sg:city":"Wagga Wagga",
    "sg:classifiers":[
        {
            "category":"Farming",
            "subcategory":"Nursery",
            "type":"Manufacturing & Wholesale Goods"
        }
    ],
    "sg:phone":"+61 2 6922 5746",
    "sg:postcode":"2650",
    "sg:province":"NSW",
    "wof:name":"Rapleys Landscape Supplies & Nursery",
    "wof:placetype":"venue"
},
  "geometry": {"coordinates":[147.40762329099999,-35.1679496765],"type":"Point"}
}