{
  "type": "Feature",
  "properties": {
    "addr:full":"5a Railway Pde Meadowbank NSW 2114",
    "addr:housenumber":"5a",
    "addr:postcode":"2114",
    "addr:street":"Railway Pde",
    "iso:country":"AU",
    "sg:address":"5a Railway Pde",
    "sg:city":"Meadowbank",
    "sg:classifiers":[
        {
            "category":"Retail",
            "subcategory":"Self-service Laundry",
            "type":"Services"
        }
    ],
    "sg:phone":"+61 2 9809 2311",
    "sg:postcode":"2114",
    "sg:province":"NSW",
    "wof:name":"Meadowbank Coin-Op Laundry",
    "wof:placetype":"venue"
},
  "geometry": {"coordinates":[151.09078979500001,-33.8160705566],"type":"Point"}
}