{
  "type": "Feature",
  "properties": {
    "iso:country":"AU",
    "sg:address":"Shp 2, 8 George St",
    "sg:city":"Warilla",
    "sg:classifiers":[
        {
            "category":"Shopping",
            "subcategory":"Clothing, Apparel, & Fashions",
            "type":"Retail Goods"
        }
    ],
    "sg:phone":"+61 2 4297 4344",
    "sg:postcode":"2528",
    "sg:province":"NSW",
    "sg:tags":[
        "lady",
        "wear"
    ],
    "wof:name":"Have To Have It",
    "wof:placetype":"venue"
},
  "geometry": {"coordinates":[150.86134338400001,-34.5526847839],"type":"Point"}
}