{
  "type": "Feature",
  "properties": {
    "iso:country":"AU",
    "sg:address":"7 Geebung St",
    "sg:city":"Cooma",
    "sg:classifiers":[
        {
            "category":"Professional",
            "subcategory":"Computer Services",
            "type":"Services"
        }
    ],
    "sg:phone":"+61 2 6452 5140",
    "sg:postcode":"2630",
    "sg:province":"NSW",
    "sg:tags":[
        "tele-communications",
        "consultant"
    ],
    "wof:name":"High Country Communications Pty Ltd",
    "wof:placetype":"venue"
},
  "geometry": {"coordinates":[149.14927673299999,-36.2245521545],"type":"Point"}
}