{
  "type": "Feature",
  "properties": {
    "addr:full":"14 Griffith St Coolangatta QLD 4225",
    "addr:housenumber":"14",
    "addr:postcode":"4225",
    "addr:street":"Griffith St",
    "iso:country":"AU",
    "sg:address":"14 Griffith St",
    "sg:city":"Coolangatta",
    "sg:classifiers":[
        {
            "category":"Real Estate",
            "subcategory":"Real Estate Agent",
            "type":"Services"
        }
    ],
    "sg:phone":"+61 7 5536 9699",
    "sg:postcode":"4225",
    "sg:province":"QLD",
    "wof:name":"Beachside Properties (Coolangatta) Pty Ltd",
    "wof:placetype":"venue"
},
  "geometry": {"coordinates":[153.53602600100001,-28.1682624817],"type":"Point"}
}