{
  "type": "Feature",
  "properties": {
    "addr:full":"1 Federal Rd Kalgoorlie WA 6430",
    "addr:housenumber":"1",
    "addr:postcode":"6430",
    "addr:street":"Federal Rd",
    "iso:country":"AU",
    "sg:address":"1 Federal Rd",
    "sg:city":"Kalgoorlie",
    "sg:classifiers":[
        {
            "category":"Retail",
            "subcategory":"Auto Rental",
            "type":"Services"
        }
    ],
    "sg:phone":"+61 8 9022 2277",
    "sg:postcode":"6430",
    "sg:province":"WA",
    "sg:tags":[
        "bus",
        "truck"
    ],
    "wof:name":"South Perth Four Wheel Drive Rentals & Corefleet",
    "wof:placetype":"venue"
},
  "geometry": {"coordinates":[121.486160278,-30.7586116791],"type":"Point"}
}