{
  "type": "Feature",
  "properties": {
    "addr:full":"56 Edwards Ave Bomaderry NSW 2541",
    "addr:housenumber":"56",
    "addr:postcode":"2541",
    "addr:street":"Edwards Ave",
    "iso:country":"AU",
    "sg:address":"56 Edwards Ave",
    "sg:city":"Bomaderry",
    "sg:classifiers":[
        {
            "category":"Building & Trades",
            "subcategory":"Construction",
            "type":"Services"
        }
    ],
    "sg:phone":"+61 427 698 736",
    "sg:postcode":"2541",
    "sg:province":"NSW",
    "sg:tags":[
        "ceiling"
    ],
    "wof:name":"Ian Vaughan",
    "wof:placetype":"venue"
},
  "geometry": {"coordinates":[150.615966797,-34.8386802673],"type":"Point"}
}