{
  "type": "Feature",
  "properties": {
    "iso:country":"AU",
    "sg:address":"1230 Logan Rd",
    "sg:city":"Mt Gravatt",
    "sg:classifiers":[
        {
            "category":"Professional",
            "subcategory":"Art Services",
            "type":"Services"
        }
    ],
    "sg:phone":"+61 7 3849 8164",
    "sg:postcode":"4122",
    "sg:province":"QLD",
    "sg:tags":[
        "picture",
        "frame",
        "framing"
    ],
    "sg:website":"http://www.fixaframe.com.au",
    "wof:name":"Fix-a-Frame",
    "wof:placetype":"venue"
},
  "geometry": {"coordinates":[153.07359314000001,-27.5314979553],"type":"Point"}
}