{
  "type": "Feature",
  "properties": {
    "iso:country":"AU",
    "sg:address":"Level 3, 10 Rudd St",
    "sg:city":"Canberra City",
    "sg:classifiers":[
        {
            "category":"Professional",
            "subcategory":"Computer Services",
            "type":"Services"
        }
    ],
    "sg:phone":"+61 1300 367 965",
    "sg:postcode":"2601",
    "sg:province":"ACT",
    "sg:tags":[
        "package",
        "software"
    ],
    "wof:name":"Software AG",
    "wof:placetype":"venue"
},
  "geometry": {"coordinates":[149.12718200699999,-35.2767333984],"type":"Point"}
}