{
  "type": "Feature",
  "properties": {
    "addr:full":"476 Fitzgerald St North Perth WA 6006",
    "addr:housenumber":"476",
    "addr:postcode":"6006",
    "addr:street":"Fitzgerald St",
    "iso:country":"AU",
    "sg:address":"476 Fitzgerald St",
    "sg:city":"North Perth",
    "sg:classifiers":[
        {
            "category":"Personal",
            "type":"Services"
        }
    ],
    "sg:phone":"+61 8 9228 1204",
    "sg:postcode":"6006",
    "sg:province":"WA",
    "sg:tags":[
        "gift"
    ],
    "wof:name":"Huss",
    "wof:placetype":"venue"
},
  "geometry": {"coordinates":[115.859352112,-31.9303474426],"type":"Point"}
}