{
  "type": "Feature",
  "properties": {
    "iso:country":"AU",
    "sg:address":"34 Albert St",
    "sg:city":"Malvern East",
    "sg:classifiers":[
        {
            "category":"Banks & Credit Unions",
            "subcategory":"Bank",
            "type":"Services"
        }
    ],
    "sg:phone":"+61 3 9505 7676",
    "sg:postcode":"3145",
    "sg:province":"VIC",
    "sg:tags":[
        "broker",
        "mortgage"
    ],
    "wof:name":"Reward Home & Commercial Loans",
    "wof:placetype":"venue"
},
  "geometry": {"coordinates":[145.064208984,-37.8745307922],"type":"Point"}
}