{
  "type": "Feature",
  "properties": {
    "addr:full":"19 Woolley St Dickson ACT 2602",
    "addr:housenumber":"19",
    "addr:postcode":"2602",
    "addr:street":"Woolley St",
    "iso:country":"AU",
    "sg:address":"19 Woolley St",
    "sg:city":"Dickson",
    "sg:classifiers":[
        {
            "category":"Communications",
            "subcategory":"Film & Video Production",
            "type":"Services"
        }
    ],
    "sg:phone":"+61 2 6257 5988",
    "sg:postcode":"2602",
    "sg:province":"ACT",
    "sg:tags":[
        "dvd",
        "library"
    ],
    "wof:name":"New World (Hong Kong) Video Ltd",
    "wof:placetype":"venue"
},
  "geometry": {"coordinates":[149.136444092,-35.2506561279],"type":"Point"}
}