{
  "type": "Feature",
  "properties": {
    "addr:full":"13 Willmott Crt Rochedale South QLD 4123",
    "addr:housenumber":"13",
    "addr:postcode":"4123",
    "addr:street":"Willmott Crt",
    "iso:country":"AU",
    "sg:address":"13 Willmott Crt",
    "sg:city":"Rochedale South",
    "sg:classifiers":[
        {
            "category":"Professional",
            "subcategory":"Management & Consulting",
            "type":"Services"
        }
    ],
    "sg:phone":"+61 412 872 109",
    "sg:postcode":"4123",
    "sg:province":"QLD",
    "sg:tags":[
        "consultant"
    ],
    "wof:name":"Workplace Resources",
    "wof:placetype":"venue"
},
  "geometry": {"coordinates":[153.14283752399999,-27.6059932709],"type":"Point"}
}