{
  "type": "Feature",
  "properties": {
    "addr:full":"Shop 3 Crimea Shopping Centre Morley WA 6062",
    "addr:housenumber":"shop 3",
    "addr:postcode":"6062",
    "addr:street":"Crimea Shopping",
    "iso:country":"AU",
    "sg:address":"Shop 3 Crimea Shopping Centre",
    "sg:city":"Morley",
    "sg:classifiers":[
        {
            "category":"Food & Beverages",
            "subcategory":"Fruits & Vegetables",
            "type":"Retail Goods"
        }
    ],
    "sg:phone":"+61 8 9276 8042",
    "sg:postcode":"6062",
    "sg:province":"WA",
    "sg:tags":[
        "greengrocer",
        "fruiterer"
    ],
    "wof:name":"Crimea Growers Market",
    "wof:placetype":"venue"
},
  "geometry": {"coordinates":[115.903831482,-31.8996658325],"type":"Point"}
}