{
  "type": "Feature",
  "properties": {
    "addr:full":"13 Villiers Drv Currumbin Waters QLD 4223",
    "addr:housenumber":"13",
    "addr:postcode":"4223",
    "addr:street":"Villiers Drv",
    "iso:country":"AU",
    "sg:address":"13 Villiers Drv",
    "sg:city":"Currumbin Waters",
    "sg:classifiers":[
        {
            "category":"Retail",
            "subcategory":"Auto Repair",
            "type":"Services"
        }
    ],
    "sg:phone":"+61 7 5534 6422",
    "sg:postcode":"4223",
    "sg:province":"QLD",
    "sg:tags":[
        "wheel",
        "balancing",
        "alignment"
    ],
    "wof:name":"Currumbin Steering",
    "wof:placetype":"venue"
},
  "geometry": {"coordinates":[153.47383117699999,-28.1511001587],"type":"Point"}
}