{
  "type": "Feature",
  "properties": {
    "addr:full":"Tumby Bay Rd Cummins SA 5631",
    "addr:postcode":"5631",
    "addr:street":"Tumby Bay Rd",
    "iso:country":"AU",
    "sg:address":"Tumby Bay Rd",
    "sg:city":"Cummins",
    "sg:classifiers":[
        {
            "category":"Travel",
            "subcategory":"Hostel",
            "type":"Entertainment"
        }
    ],
    "sg:phone":"+61 8 8676 2488",
    "sg:postcode":"5631",
    "sg:province":"SA",
    "sg:tags":[
        "home"
    ],
    "wof:name":"Miroma Place Hostel",
    "wof:placetype":"venue"
},
  "geometry": {"coordinates":[135.730224609,-34.2616424561],"type":"Point"}
}