{
  "type": "Feature",
  "properties": {
    "addr:full":"Ground Floor 26- 28 Prospect St Box Hill VIC 3128",
    "addr:housenumber":"26 28",
    "addr:postcode":"3128",
    "addr:street":"Prospect St",
    "iso:country":"AU",
    "sg:address":"Ground Floor 26- 28 Prospect St",
    "sg:city":"Box Hill",
    "sg:classifiers":[
        {
            "category":"Professional",
            "subcategory":"Business Services",
            "type":"Services"
        }
    ],
    "sg:phone":"+61 3 9899 0099",
    "sg:postcode":"3128",
    "sg:province":"VIC",
    "sg:tags":[
        "broker"
    ],
    "sg:website":"http://www.opexcorp.com.au",
    "wof:name":"Opex Corporate Business Brokers",
    "wof:placetype":"venue"
},
  "geometry": {"coordinates":[145.11741638199999,-37.8178901672],"type":"Point"}
}