{
  "type": "Feature",
  "properties": {
    "addr:full":"496 City Rd South Melbourne VIC 3205",
    "addr:housenumber":"496",
    "addr:postcode":"3205",
    "addr:street":"City Rd",
    "iso:country":"AU",
    "sg:address":"496 City Rd",
    "sg:city":"South Melbourne",
    "sg:classifiers":[
        {
            "category":"Personal",
            "subcategory":"Massage",
            "type":"Services"
        }
    ],
    "sg:phone":"+61 3 9699 6595",
    "sg:postcode":"3205",
    "sg:province":"VIC",
    "sg:tags":[
        "therapy"
    ],
    "wof:name":"City South Massage Therapy",
    "wof:placetype":"venue"
},
  "geometry": {"coordinates":[144.95263700000001,-37.832077],"type":"Point"}
}