{
  "type": "Feature",
  "properties": {
    "addr:full":"Unit 2/ 107 Bentinck St Bathurst NSW 2795",
    "addr:housenumber":"/ 107",
    "addr:postcode":"2795",
    "addr:street":"Bentinck St",
    "iso:country":"AU",
    "sg:address":"Unit 2/ 107 Bentinck St",
    "sg:city":"Bathurst",
    "sg:classifiers":[
        {
            "category":"Professional",
            "subcategory":"Computer Services",
            "type":"Services"
        }
    ],
    "sg:phone":"+61 2 6331 4235",
    "sg:postcode":"2795",
    "sg:province":"NSW",
    "sg:tags":[
        "tele-communications",
        "consultant"
    ],
    "wof:name":"Milcom & Aqua Training Communications",
    "wof:placetype":"venue"
},
  "geometry": {"coordinates":[149.58091735799999,-33.4204292297],"type":"Point"}
}