{
  "type": "Feature",
  "properties": {
    "addr:full":"Level 2, 55 Grandview St Pymble NSW 2073",
    "addr:housenumber":"55",
    "addr:postcode":"2073",
    "addr:street":"Grandview St",
    "iso:country":"AU",
    "sg:address":"Level 2, 55 Grandview St",
    "sg:city":"Pymble",
    "sg:classifiers":[
        {
            "category":"Professional",
            "subcategory":"Detective & Security Services",
            "type":"Services"
        }
    ],
    "sg:phone":"+61 2 9988 4777",
    "sg:postcode":"2073",
    "sg:province":"NSW",
    "sg:tags":[
        "investigator"
    ],
    "wof:name":"Lee Kelly & Associates Pty Ltd",
    "wof:placetype":"venue"
},
  "geometry": {"coordinates":[151.14382934599999,-33.744934082],"type":"Point"}
}