{
  "type": "Feature",
  "properties": {
    "addr:full":"Imperial Centre Mann St Gosford NSW 2250",
    "addr:postcode":"2250",
    "addr:street":"Mann St",
    "iso:country":"AU",
    "sg:address":"Imperial Centre Mann St",
    "sg:city":"Gosford",
    "sg:classifiers":[
        {
            "category":"Fast Food",
            "type":"Food & Drink"
        }
    ],
    "sg:phone":"+61 2 4324 8533",
    "sg:postcode":"2250",
    "sg:province":"NSW",
    "sg:tags":[
        "away",
        "take"
    ],
    "wof:name":"Chengs Chinese Takeaway",
    "wof:placetype":"venue"
},
  "geometry": {"coordinates":[151.34251403799999,-33.4237060547],"type":"Point"}
}