{
  "type": "Feature",
  "properties": {
    "addr:full":"U3/ 64 Riverside Rd Chipping Norton NSW 2170",
    "addr:housenumber":"64",
    "addr:postcode":"2170",
    "addr:street":"U3 /;Riverside Rd",
    "iso:country":"AU",
    "sg:address":"U3/ 64 Riverside Rd",
    "sg:city":"Chipping Norton",
    "sg:classifiers":[
        {
            "category":"Retail",
            "subcategory":"Auto Repair",
            "type":"Services"
        }
    ],
    "sg:phone":"+61 2 9755 1199",
    "sg:postcode":"2170",
    "sg:province":"NSW",
    "sg:tags":[
        "beater",
        "painter",
        "panel"
    ],
    "wof:name":"Ceko Prestige Automotive",
    "wof:placetype":"venue"
},
  "geometry": {"coordinates":[150.96841430699999,-33.9194221497],"type":"Point"}
}