{
  "type": "Feature",
  "properties": {
    "addr:full":"51 Miller St Newcomb VIC 3219",
    "addr:housenumber":"51",
    "addr:postcode":"3219",
    "addr:street":"Miller St",
    "iso:country":"AU",
    "sg:address":"51 Miller St",
    "sg:city":"Newcomb",
    "sg:classifiers":[
        {
            "category":"Professional",
            "subcategory":"Art Services",
            "type":"Services"
        }
    ],
    "sg:phone":"+61 3 5248 5805",
    "sg:postcode":"3219",
    "sg:province":"VIC",
    "sg:tags":[
        "decorator",
        "painter"
    ],
    "wof:name":"Davie C.T. & E.M.",
    "wof:placetype":"venue"
},
  "geometry": {"coordinates":[144.39068603499999,-38.1628112793],"type":"Point"}
}