{
  "type": "Feature",
  "properties": {
    "addr:full":"14 Leoben Crt Karama NT 0812",
    "addr:housenumber":"14",
    "addr:postcode":"nt 0812",
    "addr:street":"Leoben Crt",
    "iso:country":"AU",
    "sg:address":"14 Leoben Crt",
    "sg:city":"Karama",
    "sg:classifiers":[
        {
            "category":"Home & Garden",
            "subcategory":"Building Materials",
            "type":"Retail Goods"
        }
    ],
    "sg:phone":"+61 8 8927 0535",
    "sg:postcode":"0812",
    "sg:province":"NT",
    "sg:tags":[
        "lawn",
        "cutting",
        "maintenance"
    ],
    "wof:name":"Darwin Lawn Care",
    "wof:placetype":"venue"
},
  "geometry": {"coordinates":[130.921143,-12.405702],"type":"Point"}
}