{
  "type": "Feature",
  "properties": {
    "addr:full":"86 Cheltenham Rd Dandenong VIC 3175",
    "addr:housenumber":"86",
    "addr:postcode":"3175",
    "addr:street":"Cheltenham Rd",
    "iso:country":"AU",
    "sg:address":"86 Cheltenham Rd",
    "sg:city":"Dandenong",
    "sg:classifiers":[
        {
            "category":"Home & Garden",
            "subcategory":"Carpets & Floor Coverings",
            "type":"Retail Goods"
        }
    ],
    "sg:phone":"+61 3 9792 3445",
    "sg:postcode":"3175",
    "sg:province":"VIC",
    "sg:tags":[
        "layer"
    ],
    "wof:name":"My-Kraft Floors",
    "wof:placetype":"venue"
},
  "geometry": {"coordinates":[145.19969177199999,-37.9909858704],"type":"Point"}
}