{
  "type": "Feature",
  "properties": {
    "addr:full":"83 Bowral Rd Mittagong NSW 2575",
    "addr:housenumber":"83",
    "addr:postcode":"2575",
    "addr:street":"Bowral Rd",
    "iso:country":"AU",
    "sg:address":"83 Bowral Rd",
    "sg:city":"Mittagong",
    "sg:classifiers":[
        {
            "category":"Health Services",
            "subcategory":"Health Practitioner",
            "type":"Services"
        }
    ],
    "sg:phone":"+61 2 4872 1063",
    "sg:postcode":"2575",
    "sg:province":"NSW",
    "sg:tags":[
        "naturopath"
    ],
    "wof:name":"Gamble Jon",
    "wof:placetype":"venue"
},
  "geometry": {"coordinates":[150.434448242,-34.4536781311],"type":"Point"}
}