{
  "type": "Feature",
  "properties": {
    "addr:full":"29 Bannerman St Ermington NSW 2115",
    "addr:housenumber":"29",
    "addr:postcode":"2115",
    "addr:street":"Bannerman St",
    "iso:country":"AU",
    "sg:address":"29 Bannerman St",
    "sg:city":"Ermington",
    "sg:classifiers":[
        {
            "category":"Utilities",
            "subcategory":"Telephone",
            "type":"Services"
        }
    ],
    "sg:phone":"+61 2 9638 1818",
    "sg:postcode":"2115",
    "sg:province":"NSW",
    "sg:tags":[
        "equipment",
        "system"
    ],
    "wof:name":"Jeff Galbraith Communications Pty Ltd",
    "wof:placetype":"venue"
},
  "geometry": {"coordinates":[151.06033325199999,-33.8153648376],"type":"Point"}
}