{
  "type": "Feature",
  "properties": {
    "iso:country":"AU",
    "sg:address":"Gembrook Rd",
    "sg:city":"Cockatoo",
    "sg:classifiers":[
        {
            "category":"Education",
            "subcategory":"School",
            "type":"Public Place"
        }
    ],
    "sg:phone":"+61 3 5968 8017",
    "sg:postcode":"3781",
    "sg:province":"VIC",
    "sg:tags":[
        "state",
        "except",
        "nsw"
    ],
    "wof:name":"Cockatoo Primary School",
    "wof:placetype":"venue"
},
  "geometry": {"coordinates":[145.546783,-37.958244],"type":"Point"}
}