{
  "type": "Feature",
  "properties": {
    "addr:full":"77a Acland St St Kilda VIC 3182",
    "addr:housenumber":"77a",
    "addr:postcode":"3182",
    "addr:street":"Acland St",
    "iso:country":"AU",
    "sg:address":"77a Acland St",
    "sg:city":"St Kilda",
    "sg:classifiers":[
        {
            "category":"Professional",
            "subcategory":"Art Services",
            "type":"Services"
        }
    ],
    "sg:phone":"+61 3 9537 1822",
    "sg:postcode":"3182",
    "sg:province":"VIC",
    "sg:tags":[
        "graphic",
        "designer"
    ],
    "wof:name":"Hoyne Design Pty Ltd",
    "wof:placetype":"venue"
},
  "geometry": {"coordinates":[144.97883605999999,-37.8678092957],"type":"Point"}
}