{
  "type": "Feature",
  "properties": {
    "iso:country":"AU",
    "sg:address":"494 Main North Rd",
    "sg:city":"Blair Athol",
    "sg:classifiers":[
        {
            "category":"Building & Trades",
            "subcategory":"Construction",
            "type":"Services"
        }
    ],
    "sg:phone":"+61 8 8262 8900",
    "sg:postcode":"5084",
    "sg:province":"SA",
    "sg:tags":[
        "monumental",
        "mason"
    ],
    "wof:name":"Memorials SA",
    "wof:placetype":"venue"
},
  "geometry": {"coordinates":[138.60023498499999,-34.8521270752],"type":"Point"}
}