{
  "type": "Feature",
  "properties": {
    "iso:country":"AU",
    "sg:address":"7/ 19 Boden Rd",
    "sg:city":"Seven Hills",
    "sg:classifiers":[
        {
            "category":"Social Services",
            "subcategory":"Retirement Home",
            "type":"Services"
        }
    ],
    "sg:phone":"+61 2 9624 4088",
    "sg:postcode":"2147",
    "sg:province":"NSW",
    "sg:tags":[
        "decoration",
        "supplier",
        "contractor"
    ],
    "sg:website":"http://www.vipdecorating.com",
    "wof:name":"VIP Decorating Services",
    "wof:placetype":"venue"
},
  "geometry": {"coordinates":[150.95855712900001,-33.7722625732],"type":"Point"}
}