{
  "type": "Feature",
  "properties": {
    "addr:full":"15 Victoria Ave Glen Eden QLD 4680",
    "addr:housenumber":"15",
    "addr:postcode":"4680",
    "addr:street":"Victoria Ave",
    "iso:country":"AU",
    "sg:address":"15 Victoria Ave",
    "sg:city":"Glen Eden",
    "sg:classifiers":[
        {
            "category":"Real Estate",
            "subcategory":"Architect",
            "type":"Services"
        }
    ],
    "sg:phone":"+61 7 4979 0466",
    "sg:postcode":"4680",
    "sg:province":"QLD",
    "sg:tags":[
        "building",
        "designer"
    ],
    "wof:name":"BKD Designs",
    "wof:placetype":"venue"
},
  "geometry": {"coordinates":[151.26957702600001,-23.8997688293],"type":"Point"}
}