{
  "type": "Feature",
  "properties": {
    "iso:country":"AU",
    "sg:address":"79 Liebig St",
    "sg:city":"Warrnambool",
    "sg:classifiers":[
        {
            "category":"Professional",
            "subcategory":"Art Services",
            "type":"Services"
        }
    ],
    "sg:phone":"+61 1300 131 220",
    "sg:postcode":"3280",
    "sg:province":"VIC",
    "sg:tags":[
        "graphic",
        "designer"
    ],
    "wof:name":"Cactus House",
    "wof:placetype":"venue"
},
  "geometry": {"coordinates":[142.48286438,-38.3845367432],"type":"Point"}
}