{
  "type": "Feature",
  "properties": {
    "addr:full":"637 Princes Hwy Blakehurst NSW 2221",
    "addr:housenumber":"637",
    "addr:postcode":"2221",
    "addr:street":"Princes Hwy",
    "iso:country":"AU",
    "sg:address":"637 Princes Hwy",
    "sg:city":"Blakehurst",
    "sg:classifiers":[
        {
            "category":"Food & Beverages",
            "subcategory":"Bakery",
            "type":"Retail Goods"
        }
    ],
    "sg:phone":"+61 2 9546 8300",
    "sg:postcode":"2221",
    "sg:province":"NSW",
    "sg:tags":[
        "cake",
        "shop",
        "pastry"
    ],
    "wof:name":"Mother Natures Hot Bread & Cakeshop",
    "wof:placetype":"venue"
},
  "geometry": {"coordinates":[151.112182617,-33.9889717102],"type":"Point"}
}