{
  "type": "Feature",
  "properties": {
    "iso:country":"AU",
    "sg:address":"24 Charonia Rd",
    "sg:city":"Mullaloo",
    "sg:classifiers":[
        {
            "category":"Farming",
            "subcategory":"Farm & Veterinary Services",
            "type":"Manufacturing & Wholesale Goods"
        }
    ],
    "sg:phone":"+61 8 9403 5006",
    "sg:postcode":"6027",
    "sg:province":"WA",
    "sg:tags":[
        "irrigation",
        "reticulation",
        "system"
    ],
    "wof:name":"Rain Bird (Australia) Pty Ltd",
    "wof:placetype":"venue"
},
  "geometry": {"coordinates":[115.749473572,-31.7779636383],"type":"Point"}
}