{
  "type": "Feature",
  "properties": {
    "iso:country":"AU",
    "sg:address":"12 Harp St",
    "sg:city":"Campsie",
    "sg:classifiers":[
        {
            "category":"Home & Garden",
            "subcategory":"Hardware",
            "type":"Retail Goods"
        }
    ],
    "sg:phone":"+61 2 9787 4763",
    "sg:postcode":"2194",
    "sg:province":"NSW",
    "sg:tags":[
        "printed",
        "circuit"
    ],
    "wof:name":"Precision Circuits Pty Ltd",
    "wof:placetype":"venue"
},
  "geometry": {"coordinates":[151.10278299999999,-33.923653],"type":"Point"}
}