{
  "type": "Feature",
  "properties": {
    "addr:full":"40- 46 Robbs Rd Footscray West VIC 3012",
    "addr:housenumber":"46",
    "addr:postcode":"3012",
    "addr:street":"Robbs Rd",
    "iso:country":"AU",
    "sg:address":"40- 46 Robbs Rd",
    "sg:city":"Footscray West",
    "sg:classifiers":[
        {
            "category":"Wholesale",
            "subcategory":"Apparel",
            "type":"Manufacturing & Wholesale Goods"
        }
    ],
    "sg:phone":"+61 3 9316 8800",
    "sg:postcode":"3012",
    "sg:province":"VIC",
    "sg:tags":[
        "wholesaler",
        "mfrs",
        "sportswear",
        "women's"
    ],
    "wof:name":"Swiss Models Sportswear Pty Ltd",
    "wof:placetype":"venue"
},
  "geometry": {"coordinates":[144.87498474099999,-37.804473877],"type":"Point"}
}