{
  "type": "Feature",
  "properties": {
    "addr:full":"71 Collins St Melbourne VIC 3000",
    "addr:housenumber":"71",
    "addr:postcode":"3000",
    "addr:street":"Collins St",
    "iso:country":"AU",
    "sg:address":"71 Collins St",
    "sg:city":"Melbourne",
    "sg:classifiers":[
        {
            "category":"Bars & Pubs",
            "subcategory":"Wine Bar",
            "type":"Food & Drink"
        }
    ],
    "sg:phone":"+61 3 9663 4678",
    "sg:postcode":"3000",
    "sg:province":"VIC",
    "wof:name":"The Trader Bar Pty Ltd",
    "wof:placetype":"venue"
},
  "geometry": {"coordinates":[144.971191406,-37.8142623901],"type":"Point"}
}