{
  "type": "Feature",
  "properties": {
    "addr:full":"738a Mount Alexander Rd Moonee Ponds VIC 3039",
    "addr:housenumber":"738a",
    "addr:postcode":"3039",
    "addr:street":"Mount Alexander Rd",
    "iso:country":"AU",
    "sg:address":"738a Mount Alexander Rd",
    "sg:city":"Moonee Ponds",
    "sg:classifiers":[
        {
            "category":"Professional",
            "subcategory":"Computer Services",
            "type":"Services"
        }
    ],
    "sg:phone":"+61 3 9370 9077",
    "sg:postcode":"3039",
    "sg:province":"VIC",
    "sg:tags":[
        "consultant",
        "system"
    ],
    "wof:name":"Respect Computer Consultants",
    "wof:placetype":"venue"
},
  "geometry": {"coordinates":[144.92512500000001,-37.767296],"type":"Point"}
}