{
  "type": "Feature",
  "properties": {
    "addr:full":"357 Georges River Rd Croydon Park NSW 2133",
    "addr:housenumber":"357",
    "addr:postcode":"2133",
    "addr:street":"Georges River Rd",
    "iso:country":"AU",
    "sg:address":"357 Georges River Rd",
    "sg:city":"Croydon Park",
    "sg:classifiers":[
        {
            "category":"Social Services",
            "subcategory":"Child Care",
            "type":"Services"
        }
    ],
    "sg:phone":"+61 2 9742 5384",
    "sg:postcode":"2133",
    "sg:province":"NSW",
    "wof:name":"Enfield Montessori Long Day Care Centre",
    "wof:placetype":"venue"
},
  "geometry": {"coordinates":[151.115478516,-33.8936729431],"type":"Point"}
}