{
  "type": "Feature",
  "properties": {
    "iso:country":"AU",
    "sg:address":"57-59 Dandaloo St",
    "sg:city":"Narromine",
    "sg:classifiers":[
        {
            "category":"Real Estate",
            "subcategory":"Real Estate Services",
            "type":"Services"
        }
    ],
    "sg:phone":"+61 2 6889 1755",
    "sg:postcode":"2821",
    "sg:province":"NSW",
    "sg:tags":[
        "valuer"
    ],
    "wof:name":"W Burke & Co",
    "wof:placetype":"venue"
},
  "geometry": {"coordinates":[148.23916625999999,-32.235206604],"type":"Point"}
}