{
  "type": "Feature",
  "properties": {
    "addr:full":"82 Main St Rutherglen VIC 3685",
    "addr:housenumber":"82",
    "addr:postcode":"3685",
    "addr:street":"Main St",
    "iso:country":"AU",
    "sg:address":"82 Main St",
    "sg:city":"Rutherglen",
    "sg:classifiers":[
        {
            "category":"Cafe",
            "type":"Food & Drink"
        }
    ],
    "sg:phone":"+61 2 6032 7662",
    "sg:postcode":"3685",
    "sg:province":"VIC",
    "wof:name":"Forks & Corks",
    "wof:placetype":"venue"
},
  "geometry": {"coordinates":[146.461181641,-36.0549240112],"type":"Point"}
}