{
  "type": "Feature",
  "properties": {
    "iso:country":"AU",
    "sg:address":"685 Pine Ridge Rd",
    "sg:city":"Biggera Waters",
    "sg:classifiers":[
        {
            "category":"Home & Garden",
            "subcategory":"Hardware",
            "type":"Retail Goods"
        }
    ],
    "sg:phone":"+61 7 5563 2379",
    "sg:postcode":"4216",
    "sg:province":"QLD",
    "sg:tags":[
        "supply",
        "maker",
        "cabinet"
    ],
    "sg:website":"http://www.bluewaterboatservices.com.au",
    "wof:name":"Bluewater Boat Services Pty Ltd",
    "wof:placetype":"venue"
},
  "geometry": {"coordinates":[153.38435363799999,-27.9217357635],"type":"Point"}
}