{
  "type": "Feature",
  "properties": {
    "addr:full":"8 Umina St Jindalee QLD 4074",
    "addr:housenumber":"8",
    "addr:postcode":"4074",
    "addr:street":"Umina St",
    "iso:country":"AU",
    "sg:address":"8 Umina St",
    "sg:city":"Jindalee",
    "sg:classifiers":[
        {
            "category":"Communications",
            "type":"Services"
        }
    ],
    "sg:phone":"+61 412 088 428",
    "sg:postcode":"4074",
    "sg:province":"QLD",
    "sg:tags":[
        "translation"
    ],
    "wof:name":"Jeune Son",
    "wof:placetype":"venue"
},
  "geometry": {"coordinates":[152.94004821799999,-27.5345973969],"type":"Point"}
}