{
  "type": "Feature",
  "properties": {
    "iso:country":"AU",
    "sg:address":"134a Forrest St",
    "sg:city":"Fremantle",
    "sg:classifiers":[
        {
            "category":"Building & Trades",
            "subcategory":"Pest Control",
            "type":"Services"
        }
    ],
    "sg:phone":"+61 8 9433 1299",
    "sg:postcode":"6962",
    "sg:province":"WA",
    "wof:name":"Protector Pest Control",
    "wof:placetype":"venue"
},
  "geometry": {"coordinates":[115.772408,-32.04818],"type":"Point"}
}