{
  "type": "Feature",
  "properties": {
    "iso:country":"AU",
    "sg:address":"7 Royal Ave",
    "sg:city":"Glen Huntly",
    "sg:classifiers":[
        {
            "category":"Home & Garden",
            "subcategory":"Building Materials",
            "type":"Retail Goods"
        }
    ],
    "sg:phone":"+61 1800 777 995",
    "sg:postcode":"3163",
    "sg:province":"VIC",
    "sg:tags":[
        "merchant",
        "glass",
        "glazier"
    ],
    "wof:name":"Allens Glen Huntly Glass",
    "wof:placetype":"venue"
},
  "geometry": {"coordinates":[145.042572022,-37.8903045654],"type":"Point"}
}