{
  "type": "Feature",
  "properties": {
    "addr:full":"4 Hansen St Brighton East VIC 3187",
    "addr:housenumber":"4",
    "addr:postcode":"3187",
    "addr:street":"Hansen St",
    "iso:country":"AU",
    "sg:address":"4 Hansen St",
    "sg:city":"Brighton East",
    "sg:classifiers":[
        {
            "category":"Health Services",
            "subcategory":"Health Practitioner",
            "type":"Services"
        }
    ],
    "sg:phone":"+61 3 9530 5247",
    "sg:postcode":"3187",
    "sg:province":"VIC",
    "sg:tags":[
        "psychotherapist"
    ],
    "wof:name":"Brighton Clinical Hypnotherapy",
    "wof:placetype":"venue"
},
  "geometry": {"coordinates":[145.02272033700001,-37.9217567444],"type":"Point"}
}