{
  "type": "Feature",
  "properties": {
    "addr:full":"1 Greenview Crt Bentleigh East VIC 3165",
    "addr:housenumber":"1",
    "addr:postcode":"3165",
    "addr:street":"Greenview Crt",
    "iso:country":"AU",
    "sg:address":"1 Greenview Crt",
    "sg:city":"Bentleigh East",
    "sg:classifiers":[
        {
            "category":"Military Area",
            "subcategory":"Air Force Base",
            "type":"Public Place"
        }
    ],
    "sg:phone":"+61 3 9579 0310",
    "sg:postcode":"3165",
    "sg:province":"VIC",
    "sg:tags":[
        "conditioner",
        "treatment",
        "soil"
    ],
    "wof:name":"Nutratherm Australia",
    "wof:placetype":"venue"
},
  "geometry": {"coordinates":[145.07362365700001,-37.936668396],"type":"Point"}
}