{
  "type": "Feature",
  "properties": {
    "addr:full":"17 Canara Rd Westminster WA 6061",
    "addr:housenumber":"17",
    "addr:postcode":"6061",
    "addr:street":"Canara Rd",
    "iso:country":"AU",
    "sg:address":"17 Canara Rd",
    "sg:city":"Westminster",
    "sg:classifiers":[
        {
            "category":"Building & Trades",
            "subcategory":"Construction",
            "type":"Services"
        }
    ],
    "sg:phone":"+61 415 612 577",
    "sg:postcode":"6061",
    "sg:province":"WA",
    "sg:tags":[
        "plasterboard",
        "plasterer",
        "fixer"
    ],
    "wof:name":"VG Plastering",
    "wof:placetype":"venue"
},
  "geometry": {"coordinates":[115.835212708,-31.8699626923],"type":"Point"}
}