{
  "type": "Feature",
  "properties": {
    "addr:full":"83 Barrack St Perth WA 6000",
    "addr:housenumber":"83",
    "addr:postcode":"6000",
    "addr:street":"Barrack St",
    "iso:country":"AU",
    "sg:address":"83 Barrack St",
    "sg:city":"Perth",
    "sg:classifiers":[
        {
            "category":"Arena",
            "subcategory":"Horse Racetrack",
            "type":"Entertainment"
        }
    ],
    "sg:phone":"+61 8 9325 5295",
    "sg:postcode":"6000",
    "sg:province":"WA",
    "sg:tags":[
        "retail",
        "swimwear"
    ],
    "wof:name":"Wendy's Swimwear",
    "wof:placetype":"venue"
},
  "geometry": {"coordinates":[115.860427856,-31.9539203644],"type":"Point"}
}