{
  "type": "Feature",
  "properties": {
    "addr:full":"Lot 3 25th St Renmark SA 5341",
    "addr:housenumber":"3",
    "addr:postcode":"5341",
    "addr:street":"25Th St",
    "iso:country":"AU",
    "sg:address":"Lot 3 25th St",
    "sg:city":"Renmark",
    "sg:classifiers":[
        {
            "category":"Utilities",
            "subcategory":"Electric",
            "type":"Services"
        }
    ],
    "sg:phone":"+61 8 8595 1010",
    "sg:postcode":"5341",
    "sg:province":"SA",
    "sg:tags":[
        "electrical",
        "contractor"
    ],
    "wof:name":"Searly Electrical",
    "wof:placetype":"venue"
},
  "geometry": {"coordinates":[140.72373962399999,-34.1914863586],"type":"Point"}
}