{
  "type": "Feature",
  "properties": {
    "addr:full":"PO Box 1541 Subiaco WA 6927",
    "addr:postcode":"6927",
    "iso:country":"AU",
    "sg:address":"PO Box 1541",
    "sg:city":"Subiaco",
    "sg:classifiers":[
        {
            "category":"Personal",
            "subcategory":"Beauty Salon",
            "type":"Services"
        }
    ],
    "sg:phone":"+61 407 197 178",
    "sg:postcode":"6927",
    "sg:province":"WA",
    "sg:tags":[
        "supply",
        "artist",
        "make-up"
    ],
    "wof:name":"Fiorella Make-Up Artist",
    "wof:placetype":"venue"
},
  "geometry": {"coordinates":[115.824012756,-31.9468002319],"type":"Point"}
}