{
  "type": "Feature",
  "properties": {
    "iso:country":"AU",
    "sg:address":"916 High St",
    "sg:city":"Armadale",
    "sg:classifiers":[
        {
            "category":"Home & Garden",
            "subcategory":"Furniture",
            "type":"Retail Goods"
        }
    ],
    "sg:phone":"+61 3 9576 3022",
    "sg:postcode":"3143",
    "sg:province":"VIC",
    "sg:tags":[
        "outdoor"
    ],
    "wof:name":"Parterre",
    "wof:placetype":"venue"
},
  "geometry": {"coordinates":[145.018875122,-37.8553848267],"type":"Point"}
}