{
  "type": "Feature",
  "properties": {
    "addr:full":"1 Rhonda St Revesby NSW 2212",
    "addr:housenumber":"1",
    "addr:postcode":"2212",
    "addr:street":"Rhonda St",
    "iso:country":"AU",
    "sg:address":"1 Rhonda St",
    "sg:city":"Revesby",
    "sg:classifiers":[
        {
            "category":"Home & Garden",
            "subcategory":"Carpets & Floor Coverings",
            "type":"Retail Goods"
        }
    ],
    "sg:phone":"+61 2 9773 5308",
    "sg:postcode":"2212",
    "sg:province":"NSW",
    "sg:tags":[
        "tile",
        "wall",
        "layer"
    ],
    "wof:name":"Host R",
    "wof:placetype":"venue"
},
  "geometry": {"coordinates":[151.02340699999999,-33.949169],"type":"Point"}
}