{
  "type": "Feature",
  "properties": {
    "iso:country":"AU",
    "sg:address":"249 Sandy Bay Rd",
    "sg:city":"Sandy Bay",
    "sg:classifiers":[
        {
            "category":"Health Services",
            "subcategory":"Health Practitioner",
            "type":"Services"
        }
    ],
    "sg:phone":"+61 3 6224 9291",
    "sg:postcode":"7005",
    "sg:province":"TAS",
    "sg:tags":[
        "naturopath"
    ],
    "wof:name":"Emerald Alchemy",
    "wof:placetype":"venue"
},
  "geometry": {"coordinates":[147.32827758799999,-42.8964385986],"type":"Point"}
}