{
  "type": "Feature",
  "properties": {
    "iso:country":"AU",
    "sg:address":"114 Hemmings St",
    "sg:city":"Dandenong",
    "sg:classifiers":[
        {
            "category":"Banks & Credit Unions",
            "subcategory":"Financial Services",
            "type":"Services"
        }
    ],
    "sg:phone":"+61 3 9706 8463",
    "sg:postcode":"3175",
    "sg:province":"VIC",
    "sg:tags":[
        "finance",
        "motor",
        "vehicle"
    ],
    "wof:name":"Car Loans R Us",
    "wof:placetype":"venue"
},
  "geometry": {"coordinates":[145.20106506400001,-37.982460022],"type":"Point"}
}