{
  "type": "Feature",
  "properties": {
    "addr:full":"Level 1 East, 610 Victoria St Richmond VIC 3121",
    "addr:postcode":"3121",
    "addr:street":"East 610 Victoria St",
    "iso:country":"AU",
    "sg:address":"Level 1 East, 610 Victoria St",
    "sg:city":"Richmond",
    "sg:classifiers":[
        {
            "category":"Building & Trades",
            "subcategory":"Landscaping Services",
            "type":"Services"
        }
    ],
    "sg:phone":"+61 3 9428 6300",
    "sg:postcode":"3121",
    "sg:province":"VIC",
    "sg:tags":[
        "architect",
        "landscape"
    ],
    "wof:name":"Ground Control Landscape Architecture Pty Ltd",
    "wof:placetype":"venue"
},
  "geometry": {"coordinates":[145.01133727999999,-37.8117332458],"type":"Point"}
}