{
  "type": "Feature",
  "properties": {
    "addr:full":"Anzac Pde La Perouse NSW 2036",
    "addr:postcode":"2036",
    "addr:street":"Anzac Pde La",
    "iso:country":"AU",
    "sg:address":"Anzac Pde La",
    "sg:city":"Perouse",
    "sg:classifiers":[
        {
            "category":"Communications",
            "subcategory":"News Services",
            "type":"Services"
        }
    ],
    "sg:phone":"+61 2 9311 3379",
    "sg:postcode":"2036",
    "sg:province":"NSW",
    "sg:tags":[
        "information",
        "tourist",
        "attractions"
    ],
    "wof:name":"Bare Island Fort",
    "wof:placetype":"venue"
},
  "geometry": {"coordinates":[151.231292725,-33.987903595],"type":"Point"}
}