{
  "type": "Feature",
  "properties": {
    "addr:full":"69 Nicholson St Brunswick VIC 3056",
    "addr:housenumber":"69",
    "addr:postcode":"3056",
    "addr:street":"Nicholson St",
    "iso:country":"AU",
    "sg:address":"69 Nicholson St",
    "sg:city":"Brunswick",
    "sg:classifiers":[
        {
            "category":"Wholesale",
            "subcategory":"Non-durable Goods",
            "type":"Manufacturing & Wholesale Goods"
        }
    ],
    "sg:phone":"+61 3 9380 3700",
    "sg:postcode":"3056",
    "sg:province":"VIC",
    "sg:tags":[
        "textile"
    ],
    "wof:name":"Kay Toby",
    "wof:placetype":"venue"
},
  "geometry": {"coordinates":[144.978607178,-37.7755279541],"type":"Point"}
}