{
  "type": "Feature",
  "properties": {
    "addr:full":"21 Howard Pl Epping North NSW 2121",
    "addr:housenumber":"21",
    "addr:postcode":"2121",
    "addr:street":"Howard Pl",
    "iso:country":"AU",
    "sg:address":"21 Howard Pl",
    "sg:city":"Epping North",
    "sg:classifiers":[
        {
            "category":"Health Services",
            "subcategory":"Health Practitioner",
            "type":"Services"
        }
    ],
    "sg:phone":"+61 2 9876 3842",
    "sg:postcode":"2121",
    "sg:province":"NSW",
    "sg:tags":[
        "psychologist"
    ],
    "wof:name":"Todd Vija Honor",
    "wof:placetype":"venue"
},
  "geometry": {"coordinates":[151.09715270999999,-33.7622528076],"type":"Point"}
}