{
  "type": "Feature",
  "properties": {
    "addr:full":"Box Hill Central Shopping Cntr Whitehorse Rd Box Hill VIC 3128",
    "addr:postcode":"3128",
    "addr:street":"Whitehorse Rd",
    "iso:country":"AU",
    "sg:address":"Box Hill Central Shopping Cntr Whitehorse Rd",
    "sg:city":"Box Hill",
    "sg:classifiers":[
        {
            "category":"Casinos & Gambling",
            "type":"Entertainment"
        }
    ],
    "sg:phone":"+61 3 9890 5974",
    "sg:postcode":"3128",
    "sg:province":"VIC",
    "sg:tags":[
        "lottery",
        "agent"
    ],
    "wof:name":"Box Hill Tattslotto",
    "wof:placetype":"venue"
},
  "geometry": {"coordinates":[145.12361145,-37.8178825378],"type":"Point"}
}