{
  "type": "Feature",
  "properties": {
    "iso:country":"AU",
    "sg:address":"Level 6, 500 Bourke St",
    "sg:city":"Melbourne",
    "sg:classifiers":[
        {
            "category":"Organizations",
            "subcategory":"Professional Association",
            "type":"Services"
        }
    ],
    "sg:phone":"+61 1300 362 646",
    "sg:postcode":"3000",
    "sg:province":"VIC",
    "sg:tags":[
        "web",
        "internet"
    ],
    "wof:name":"Kiboodle",
    "wof:placetype":"venue"
},
  "geometry": {"coordinates":[144.95875549300001,-37.8153839111],"type":"Point"}
}