{
  "type": "Feature",
  "properties": {
    "addr:full":"17 Seven Oaks St Alexandra Hills QLD 4161",
    "addr:housenumber":"17",
    "addr:postcode":"4161",
    "addr:street":"Seven Oaks St",
    "iso:country":"AU",
    "sg:address":"17 Seven Oaks St",
    "sg:city":"Alexandra Hills",
    "sg:classifiers":[
        {
            "category":"Building & Trades",
            "subcategory":"Construction",
            "type":"Services"
        }
    ],
    "sg:phone":"+61 411 887 750",
    "sg:postcode":"4161",
    "sg:province":"QLD",
    "sg:tags":[
        "contractor"
    ],
    "wof:name":"Redlands Constructions",
    "wof:placetype":"venue"
},
  "geometry": {"coordinates":[153.23042297399999,-27.5468864441],"type":"Point"}
}