{
  "type": "Feature",
  "properties": {
    "addr:full":"49 Chifley Drv Preston VIC 3072",
    "addr:housenumber":"49",
    "addr:postcode":"3072",
    "addr:street":"Chifley Drv",
    "iso:country":"AU",
    "sg:address":"49 Chifley Drv",
    "sg:city":"Preston",
    "sg:classifiers":[
        {
            "category":"Manufacturing",
            "subcategory":"Retail Goods",
            "type":"Manufacturing & Wholesale Goods"
        }
    ],
    "sg:phone":"+61 3 9480 5444",
    "sg:postcode":"3072",
    "sg:province":"VIC",
    "sg:tags":[
        "merchant",
        "tallow"
    ],
    "wof:name":"Bonebusters",
    "wof:placetype":"venue"
},
  "geometry": {"coordinates":[145.02899169899999,-37.7515525818],"type":"Point"}
}