{
  "type": "Feature",
  "properties": {
    "addr:full":"Level 1, 110-112 Argyle St Fitzroy VIC 3065",
    "addr:housenumber":"110-112",
    "addr:postcode":"3065",
    "addr:street":"Argyle St",
    "iso:country":"AU",
    "sg:address":"Level 1, 110-112 Argyle St",
    "sg:city":"Fitzroy",
    "sg:classifiers":[
        {
            "category":"Government",
            "subcategory":"Post Office",
            "type":"Public Place"
        }
    ],
    "sg:phone":"+61 3 9419 1598",
    "sg:postcode":"3065",
    "sg:province":"VIC",
    "sg:tags":[
        "yoga"
    ],
    "wof:name":"Ashtanga Yoga Centre of Melbourne",
    "wof:placetype":"venue"
},
  "geometry": {"coordinates":[144.97889709500001,-37.797668457],"type":"Point"}
}