{
  "type": "Feature",
  "properties": {
    "addr:full":"PO Box 5007 Greenwich NSW 2065",
    "addr:postcode":"2065",
    "iso:country":"AU",
    "sg:address":"PO Box 5007",
    "sg:city":"Greenwich",
    "sg:classifiers":[
        {
            "category":"Banks & Credit Unions",
            "subcategory":"Investment Brokerage",
            "type":"Services"
        }
    ],
    "sg:phone":"+61 1800 770 727",
    "sg:postcode":"2065",
    "sg:province":"NSW",
    "sg:tags":[
        "shutter",
        "louvre"
    ],
    "wof:name":"Woodys Plantation Shutters",
    "wof:placetype":"venue"
},
  "geometry": {"coordinates":[151.187744141,-33.8271217346],"type":"Point"}
}