{
  "type": "Feature",
  "properties": {
    "iso:country":"AU",
    "sg:address":"Lvl 3/ 293 Camberwell Rd",
    "sg:city":"Camberwell",
    "sg:classifiers":[
        {
            "category":"Insurance",
            "subcategory":"Insurance Agent",
            "type":"Services"
        }
    ],
    "sg:phone":"+61 3 9811 0320",
    "sg:postcode":"3124",
    "sg:province":"VIC",
    "wof:name":"National Hole-In-One Association",
    "wof:placetype":"venue"
},
  "geometry": {"coordinates":[145.058425903,-37.8325462341],"type":"Point"}
}