{
  "type": "Feature",
  "properties": {
    "addr:full":"Level 2, 306 St Vincent St Port Adelaide SA 5015",
    "addr:housenumber":"306",
    "addr:postcode":"5015",
    "addr:street":"St Vincent St",
    "iso:country":"AU",
    "sg:address":"Level 2, 306 St Vincent St",
    "sg:city":"Port Adelaide",
    "sg:classifiers":[
        {
            "category":"Freight",
            "type":"Transportation"
        }
    ],
    "sg:phone":"+61 8 8248 9300",
    "sg:postcode":"5015",
    "sg:province":"SA",
    "sg:tags":[
        "cargo",
        "container"
    ],
    "wof:name":"DP World Adelaide Pty Ltd",
    "wof:placetype":"venue"
},
  "geometry": {"coordinates":[138.509277344,-34.8437232971],"type":"Point"}
}