{
  "type": "Feature",
  "properties": {
    "iso:country":"AU",
    "sg:address":"26 Gordon St",
    "sg:city":"Glenelg",
    "sg:classifiers":[
        {
            "category":"Arts & Performance",
            "subcategory":"Art Gallery",
            "type":"Entertainment"
        }
    ],
    "sg:phone":"+61 8 8294 0321",
    "sg:postcode":"5045",
    "sg:province":"SA",
    "wof:name":"Glenelg Fine Art Galleries",
    "wof:placetype":"venue"
},
  "geometry": {"coordinates":[138.51783800000001,-34.9786],"type":"Point"}
}