{
  "type": "Feature",
  "properties": {
    "addr:full":"The Buderim Hub Buderim QLD 4556",
    "addr:postcode":"4556",
    "iso:country":"AU",
    "sg:address":"The Buderim Hub",
    "sg:city":"Buderim",
    "sg:classifiers":[
        {
            "category":"Personal",
            "subcategory":"Beauty Salon",
            "type":"Services"
        }
    ],
    "sg:phone":"+61 7 5445 3431",
    "sg:postcode":"4556",
    "sg:province":"QLD",
    "sg:tags":[
        "hairdresser"
    ],
    "wof:name":"Headlines",
    "wof:placetype":"venue"
},
  "geometry": {"coordinates":[153.04881286599999,-26.6876907349],"type":"Point"}
}