{
  "type": "Feature",
  "properties": {
    "addr:full":"53 Carnarvon Rd Strathmore VIC 3041",
    "addr:housenumber":"53",
    "addr:postcode":"3041",
    "addr:street":"Carnarvon Rd",
    "iso:country":"AU",
    "sg:address":"53 Carnarvon Rd",
    "sg:city":"Strathmore",
    "sg:classifiers":[
        {
            "category":"Home & Garden",
            "subcategory":"Carpets & Floor Coverings",
            "type":"Retail Goods"
        }
    ],
    "sg:phone":"+61 3 9379 4503",
    "sg:postcode":"3041",
    "sg:province":"VIC",
    "wof:name":"Marvic Floors",
    "wof:placetype":"venue"
},
  "geometry": {"coordinates":[144.91050720199999,-37.7392501831],"type":"Point"}
}