{
  "type": "Feature",
  "properties": {
    "iso:country":"AU",
    "sg:address":"55 Whiters St",
    "sg:city":"Lakes Entrance",
    "sg:classifiers":[
        {
            "category":"Retail",
            "subcategory":"Auto Repair",
            "type":"Services"
        }
    ],
    "sg:phone":"+61 3 5155 1255",
    "sg:postcode":"3909",
    "sg:province":"VIC",
    "sg:tags":[
        "beater",
        "painter",
        "panel"
    ],
    "wof:name":"Peters Top End Panels",
    "wof:placetype":"venue"
},
  "geometry": {"coordinates":[148.00112915,-37.871257782],"type":"Point"}
}