{
  "type": "Feature",
  "properties": {
    "iso:country":"AU",
    "sg:address":"Shp3/ 119 Horton St",
    "sg:city":"Port Macquarie",
    "sg:classifiers":[
        {
            "category":"Personal",
            "subcategory":"Beauty Salon",
            "type":"Services"
        }
    ],
    "sg:phone":"+61 2 6584 9998",
    "sg:postcode":"2444",
    "sg:province":"NSW",
    "wof:name":"Trendz Nail & Beauty Care",
    "wof:placetype":"venue"
},
  "geometry": {"coordinates":[152.908264,-31.432211],"type":"Point"}
}