{
  "type": "Feature",
  "properties": {
    "addr:full":"1354 Botany Rd Botany NSW 2019",
    "addr:housenumber":"1354",
    "addr:postcode":"2019",
    "addr:street":"Botany Rd",
    "iso:country":"AU",
    "sg:address":"1354 Botany Rd",
    "sg:city":"Botany",
    "sg:classifiers":[
        {
            "category":"Travel",
            "subcategory":"Hotels & Motels",
            "type":"Entertainment"
        }
    ],
    "sg:phone":"+61 2 9316 8822",
    "sg:postcode":"2019",
    "sg:province":"NSW",
    "sg:tags":[
        "accommodation"
    ],
    "wof:name":"Sir Joseph Banks Hotel",
    "wof:placetype":"venue"
},
  "geometry": {"coordinates":[151.19572448700001,-33.9430160522],"type":"Point"}
}