{
  "type": "Feature",
  "properties": {
    "addr:full":"21 Oliver St Goolwa SA 5214",
    "addr:housenumber":"21",
    "addr:postcode":"5214",
    "addr:street":"Oliver St",
    "iso:country":"AU",
    "sg:address":"21 Oliver St",
    "sg:city":"Goolwa",
    "sg:classifiers":[
        {
            "category":"Real Estate",
            "subcategory":"Real Estate Agent",
            "type":"Services"
        }
    ],
    "sg:phone":"+61 8 8555 0267",
    "sg:postcode":"5214",
    "sg:province":"SA",
    "wof:name":"Fleurieu Realty Group",
    "wof:placetype":"venue"
},
  "geometry": {"coordinates":[138.78123474099999,-35.5058174133],"type":"Point"}
}