{
  "type": "Feature",
  "properties": {
    "addr:full":"Timaru St Terrey Hills NSW 2084",
    "addr:postcode":"2084",
    "addr:street":"Timaru St",
    "iso:country":"AU",
    "sg:address":"Timaru St",
    "sg:city":"Terrey Hills",
    "sg:classifiers":[
        {
            "category":"Train Station",
            "subcategory":"Light Rail",
            "type":"Transportation"
        }
    ],
    "sg:phone":"+61 2 9264 0717",
    "sg:postcode":"2084",
    "sg:province":"NSW",
    "sg:tags":[
        "equipment",
        "energy",
        "solar"
    ],
    "wof:name":"Optional Power",
    "wof:placetype":"venue"
},
  "geometry": {"coordinates":[151.230392456,-33.6778411865],"type":"Point"}
}