{
  "type": "Feature",
  "properties": {
    "addr:full":"Lvl3/ 627 Chapel St South Yarra VIC 3141",
    "addr:housenumber":"627",
    "addr:postcode":"3141",
    "addr:street":"Chapel St",
    "iso:country":"AU",
    "sg:address":"Lvl3/ 627 Chapel St",
    "sg:city":"South Yarra",
    "sg:classifiers":[
        {
            "category":"Professional",
            "subcategory":"Research",
            "type":"Services"
        }
    ],
    "sg:phone":"+61 3 9826 4755",
    "sg:postcode":"3141",
    "sg:province":"VIC",
    "sg:tags":[
        "market"
    ],
    "wof:name":"Lewers Research",
    "wof:placetype":"venue"
},
  "geometry": {"coordinates":[144.99566650400001,-37.8383979797],"type":"Point"}
}