{
  "type": "Feature",
  "properties": {
    "addr:full":"RSD 4166 Mannum SA 5238",
    "addr:postcode":"5238",
    "iso:country":"AU",
    "sg:address":"RSD 4166",
    "sg:city":"Mannum",
    "sg:classifiers":[
        {
            "category":"Building & Trades",
            "subcategory":"Cleaning & Sanitation",
            "type":"Services"
        }
    ],
    "sg:phone":"+61 427 227 740",
    "sg:postcode":"5238",
    "sg:province":"SA",
    "sg:tags":[
        "tank",
        "septic"
    ],
    "wof:name":"Mannum Septic Pumping",
    "wof:placetype":"venue"
},
  "geometry": {"coordinates":[139.28233337399999,-34.9041213989],"type":"Point"}
}