{
  "type": "Feature",
  "properties": {
    "addr:full":"14 Calliandra Pl Sinnamon Park QLD 4073",
    "addr:housenumber":"14",
    "addr:postcode":"4073",
    "addr:street":"Calliandra Pl",
    "iso:country":"AU",
    "sg:address":"14 Calliandra Pl",
    "sg:city":"Sinnamon Park",
    "sg:classifiers":[
        {
            "category":"Health Services",
            "subcategory":"Health Practitioner",
            "type":"Services"
        }
    ],
    "sg:phone":"+61 7 3376 5182",
    "sg:postcode":"4073",
    "sg:province":"QLD",
    "sg:tags":[
        "psychologist"
    ],
    "wof:name":"The Discovery Clinic",
    "wof:placetype":"venue"
},
  "geometry": {"coordinates":[152.94796752900001,-27.5424480438],"type":"Point"}
}