{
  "type": "Feature",
  "properties": {
    "addr:full":"707 Forest Rd Bexley NSW 2207",
    "addr:housenumber":"707",
    "addr:postcode":"2207",
    "addr:street":"Forest Rd",
    "iso:country":"AU",
    "sg:address":"707 Forest Rd",
    "sg:city":"Bexley",
    "sg:classifiers":[
        {
            "category":"Food & Beverages",
            "subcategory":"Fruits & Vegetables",
            "type":"Retail Goods"
        }
    ],
    "sg:phone":"+61 2 9588 5035",
    "sg:postcode":"2207",
    "sg:province":"NSW",
    "sg:tags":[
        "wholesale"
    ],
    "wof:name":"F.A.S.T Fruit Supplies",
    "wof:placetype":"venue"
},
  "geometry": {"coordinates":[151.11625699999999,-33.960613],"type":"Point"}
}