{
  "type": "Feature",
  "properties": {
    "addr:full":"U17/ 20 Close St Canterbury NSW 2193",
    "addr:postcode":"2193",
    "addr:street":"/ 20 Close St",
    "iso:country":"AU",
    "sg:address":"U17/ 20 Close St",
    "sg:city":"Canterbury",
    "sg:classifiers":[
        {
            "category":"Professional",
            "subcategory":"Employment Agencies",
            "type":"Services"
        }
    ],
    "sg:phone":"+61 2 9787 3596",
    "sg:postcode":"2193",
    "sg:province":"NSW",
    "wof:name":"Sign Post Australia",
    "wof:placetype":"venue"
},
  "geometry": {"coordinates":[151.12008700000001,-33.913826],"type":"Point"}
}