{
  "type": "Feature",
  "properties": {
    "iso:country":"AU",
    "sg:address":"158 Maurice Rd",
    "sg:city":"Murray Bridge",
    "sg:classifiers":[
        {
            "category":"Wholesale",
            "subcategory":"Auto Parts",
            "type":"Manufacturing & Wholesale Goods"
        }
    ],
    "sg:phone":"+61 8 8532 2944",
    "sg:postcode":"5253",
    "sg:province":"SA",
    "sg:tags":[
        "recyclers"
    ],
    "wof:name":"Murray Bridge One Stop",
    "wof:placetype":"venue"
},
  "geometry": {"coordinates":[139.249923706,-35.1191444397],"type":"Point"}
}