{
  "type": "Feature",
  "properties": {
    "addr:full":"389 Galston Rd Galston NSW 2159",
    "addr:housenumber":"389",
    "addr:postcode":"2159",
    "addr:street":"Galston Rd",
    "iso:country":"AU",
    "sg:address":"389 Galston Rd",
    "sg:city":"Galston",
    "sg:classifiers":[
        {
            "category":"Farming",
            "subcategory":"Berry Farm",
            "type":"Manufacturing & Wholesale Goods"
        }
    ],
    "sg:phone":"+61 2 9653 1331",
    "sg:postcode":"2159",
    "sg:province":"NSW",
    "sg:tags":[
        "fruit",
        "grower"
    ],
    "wof:name":"Waddell Orchards",
    "wof:placetype":"venue"
},
  "geometry": {"coordinates":[151.040161133,-33.6562461853],"type":"Point"}
}