{
  "type": "Feature",
  "properties": {
    "iso:country":"AU",
    "sg:address":"1168 Beaudesert Rd",
    "sg:city":"Acacia Ridge",
    "sg:classifiers":[
        {
            "category":"Personal",
            "subcategory":"Beauty Salon",
            "type":"Services"
        }
    ],
    "sg:phone":"+61 7 3277 5001",
    "sg:postcode":"4110",
    "sg:province":"QLD",
    "sg:tags":[
        "hairdresser"
    ],
    "wof:name":"Kathy's Hair Studio",
    "wof:placetype":"venue"
},
  "geometry": {"coordinates":[153.02928161599999,-27.5915966034],"type":"Point"}
}