{
  "type": "Feature",
  "properties": {
    "iso:country":"AU",
    "sg:address":"13-15 Asling St",
    "sg:city":"Brighton",
    "sg:classifiers":[
        {
            "category":"Social Services",
            "subcategory":"Child Care",
            "type":"Services"
        }
    ],
    "sg:phone":"+61 3 9596 0355",
    "sg:postcode":"3186",
    "sg:province":"VIC",
    "wof:name":"Bambini Early Learning Centre",
    "wof:placetype":"venue"
},
  "geometry": {"coordinates":[145.001754761,-37.9036026001],"type":"Point"}
}