{
  "type": "Feature",
  "properties": {
    "iso:country":"AU",
    "sg:address":"106 Ferry Rd",
    "sg:city":"Southport",
    "sg:classifiers":[
        {
            "category":"Autos & Motor Vehicles",
            "subcategory":"Boat Sales",
            "type":"Retail Goods"
        }
    ],
    "sg:phone":"+61 7 5531 4926",
    "sg:postcode":"4215",
    "sg:province":"QLD",
    "sg:tags":[
        "equipment",
        "yacht"
    ],
    "wof:name":"Coastal Foam Superstore",
    "wof:placetype":"venue"
},
  "geometry": {"coordinates":[153.41087341299999,-27.9801597595],"type":"Point"}
}