{
  "type": "Feature",
  "properties": {
    "addr:full":"13 Griffin Rd North Curl Curl NSW 2099",
    "addr:housenumber":"13",
    "addr:postcode":"2099",
    "addr:street":"Griffin Rd",
    "iso:country":"AU",
    "sg:address":"13 Griffin Rd",
    "sg:city":"North Curl Curl",
    "sg:classifiers":[
        {
            "category":"Real Estate",
            "subcategory":"Real Estate Services",
            "type":"Services"
        }
    ],
    "sg:phone":"+61 2 9905 9955",
    "sg:postcode":"2099",
    "sg:province":"NSW",
    "sg:tags":[
        "consultant",
        "property"
    ],
    "wof:name":"Property Bloom Aust Pty Ltd",
    "wof:placetype":"venue"
},
  "geometry": {"coordinates":[151.29518127399999,-33.7648620605],"type":"Point"}
}