{
  "type": "Feature",
  "properties": {
    "addr:full":"Level 5, 3 Smail St Broadway NSW 2007",
    "addr:housenumber":"3",
    "addr:postcode":"2007",
    "addr:street":"Smail St",
    "iso:country":"AU",
    "sg:address":"Level 5, 3 Smail St",
    "sg:city":"Broadway",
    "sg:classifiers":[
        {
            "category":"Organizations",
            "subcategory":"Professional Association",
            "type":"Services"
        }
    ],
    "sg:phone":"+61 2 9344 3543",
    "sg:postcode":"2007",
    "sg:province":"NSW",
    "sg:tags":[
        "web",
        "internet"
    ],
    "wof:name":"Sydneyweb Design & Consulting",
    "wof:placetype":"venue"
},
  "geometry": {"coordinates":[151.19566345199999,-33.8829650879],"type":"Point"}
}