{
  "type": "Feature",
  "properties": {
    "addr:full":"Cnr Andrew Smith Drv & Cook St Parafield Gardens SA 5107",
    "addr:postcode":"5107",
    "addr:street":"Cnr Andrew Smith Drv & Cook St",
    "iso:country":"AU",
    "sg:address":"Cnr Andrew Smith Drv & Cook St",
    "sg:city":"Parafield Gardens",
    "sg:classifiers":[
        {
            "category":"Retail",
            "subcategory":"Self-service Laundry",
            "type":"Services"
        }
    ],
    "sg:phone":"+61 8 8250 7273",
    "sg:postcode":"5107",
    "sg:province":"SA",
    "wof:name":"The Pines Laundromat",
    "wof:placetype":"venue"
},
  "geometry": {"coordinates":[138.60508727999999,-34.7722358704],"type":"Point"}
}