{
  "type": "Feature",
  "properties": {
    "addr:full":"21 Mayes Ave Caloundra QLD 4551",
    "addr:housenumber":"21",
    "addr:postcode":"4551",
    "addr:street":"Mayes Ave",
    "iso:country":"AU",
    "sg:address":"21 Mayes Ave",
    "sg:city":"Caloundra",
    "sg:classifiers":[
        {
            "category":"Shopping",
            "subcategory":"Stationery & Office Supplies",
            "type":"Retail Goods"
        }
    ],
    "sg:phone":"+61 7 5491 3065",
    "sg:postcode":"4551",
    "sg:province":"QLD",
    "sg:tags":[
        "equipment",
        "sailboarding"
    ],
    "wof:name":"Sunshine Coast Sailboards",
    "wof:placetype":"venue"
},
  "geometry": {"coordinates":[153.12150573700001,-26.8027305603],"type":"Point"}
}