{
  "type": "Feature",
  "properties": {
    "iso:country":"AU",
    "sg:address":"53 Whitely St",
    "sg:city":"Wellington",
    "sg:classifiers":[
        {
            "category":"Utilities",
            "subcategory":"Electric",
            "type":"Services"
        }
    ],
    "sg:phone":"+61 2 6845 1729",
    "sg:postcode":"2820",
    "sg:province":"NSW",
    "sg:tags":[
        "electrical",
        "contractor"
    ],
    "wof:name":"Lohses Electrical Service",
    "wof:placetype":"venue"
},
  "geometry": {"coordinates":[148.943725586,-32.5473022461],"type":"Point"}
}