{
  "type": "Feature",
  "properties": {
    "iso:country":"AU",
    "sg:address":"21 Summit Rd",
    "sg:city":"Burwood",
    "sg:classifiers":[
        {
            "category":"Retail",
            "subcategory":"Auto Rental",
            "type":"Services"
        }
    ],
    "sg:phone":"+61 3 9710 1914",
    "sg:postcode":"3125",
    "sg:province":"VIC",
    "sg:tags":[
        "car",
        "wedding"
    ],
    "wof:name":"A Weddings by Wolseleys",
    "wof:placetype":"venue"
},
  "geometry": {"coordinates":[145.12315368599999,-37.8465461731],"type":"Point"}
}