{
  "type": "Feature",
  "properties": {
    "addr:full":"4 Dilop Drv Epping VIC 3076",
    "addr:housenumber":"4",
    "addr:postcode":"3076",
    "addr:street":"Dilop Drv",
    "iso:country":"AU",
    "sg:address":"4 Dilop Drv",
    "sg:city":"Epping",
    "sg:classifiers":[
        {
            "category":"Autos & Motor Vehicles",
            "subcategory":"Auto Supplies",
            "type":"Retail Goods"
        }
    ],
    "sg:phone":"+61 3 9408 6493",
    "sg:postcode":"3076",
    "sg:province":"VIC",
    "sg:tags":[
        "battery",
        "automotive"
    ],
    "wof:name":"Epping Battery Centre",
    "wof:placetype":"venue"
},
  "geometry": {"coordinates":[145.02037048299999,-37.6433448792],"type":"Point"}
}