{
  "type": "Feature",
  "properties": {
    "addr:full":"3477 Ipswich Rd Wacol QLD 4076",
    "addr:housenumber":"3477",
    "addr:postcode":"4076",
    "addr:street":"Ipswich Rd",
    "iso:country":"AU",
    "sg:address":"3477 Ipswich Rd",
    "sg:city":"Wacol",
    "sg:classifiers":[
        {
            "category":"Industrial Area",
            "type":"Public Place"
        }
    ],
    "sg:phone":"+61 1300 131 147",
    "sg:postcode":"4076",
    "sg:province":"QLD",
    "sg:tags":[
        "rural",
        "shed"
    ],
    "wof:name":"Shed Co",
    "wof:placetype":"venue"
},
  "geometry": {"coordinates":[152.92404174800001,-27.5920448303],"type":"Point"}
}