{
  "type": "Feature",
  "properties": {
    "addr:full":"Bradshaw Crs Manning WA 6152",
    "addr:postcode":"6152",
    "addr:street":"Bradshaw Crs",
    "iso:country":"AU",
    "sg:address":"Bradshaw Crs",
    "sg:city":"Manning",
    "sg:classifiers":[
        {
            "category":"Government",
            "subcategory":"City Hall",
            "type":"Public Place"
        }
    ],
    "sg:phone":"+61 8 9474 0756",
    "sg:postcode":"6152",
    "sg:province":"WA",
    "wof:name":"Manning Hall",
    "wof:placetype":"venue"
},
  "geometry": {"coordinates":[115.868973,-32.015171],"type":"Point"}
}