{
  "type": "Feature",
  "properties": {
    "addr:full":"9 Charleville Rd Wagga Wagga NSW 2650",
    "addr:housenumber":"9",
    "addr:postcode":"2650",
    "addr:street":"Charleville Rd",
    "iso:country":"AU",
    "sg:address":"9 Charleville Rd",
    "sg:city":"Wagga Wagga",
    "sg:classifiers":[
        {
            "category":"Government",
            "subcategory":"Post Office",
            "type":"Public Place"
        }
    ],
    "sg:phone":"+61 2 6925 4274",
    "sg:postcode":"2650",
    "sg:province":"NSW",
    "sg:tags":[
        "house",
        "doll"
    ],
    "wof:name":"Alicia Bebes",
    "wof:placetype":"venue"
},
  "geometry": {"coordinates":[147.35223388700001,-35.1282806396],"type":"Point"}
}