{
  "type": "Feature",
  "properties": {
    "addr:full":"23 Tramway Pde Beaumaris VIC 3193",
    "addr:housenumber":"23",
    "addr:postcode":"3193",
    "addr:street":"Tramway Pde",
    "iso:country":"AU",
    "sg:address":"23 Tramway Pde",
    "sg:city":"Beaumaris",
    "sg:classifiers":[
        {
            "category":"Building & Trades",
            "subcategory":"Landscaping Services",
            "type":"Services"
        }
    ],
    "sg:phone":"+61 3 9589 0911",
    "sg:postcode":"3193",
    "sg:province":"VIC",
    "sg:tags":[
        "stump",
        "tree",
        "felling",
        "removal"
    ],
    "wof:name":"Robinson Gary",
    "wof:placetype":"venue"
},
  "geometry": {"coordinates":[145.037475586,-37.993057251],"type":"Point"}
}