{
  "type": "Feature",
  "properties": {
    "addr:full":"330 Pacific Hwy Lindfield NSW 2070",
    "addr:housenumber":"330",
    "addr:postcode":"2070",
    "addr:street":"Pacific Hwy",
    "iso:country":"AU",
    "sg:address":"330 Pacific Hwy",
    "sg:city":"Lindfield",
    "sg:classifiers":[
        {
            "category":"Health Services",
            "subcategory":"Health Practitioner",
            "type":"Services"
        }
    ],
    "sg:phone":"+61 2 9416 7247",
    "sg:postcode":"2070",
    "sg:province":"NSW",
    "sg:tags":[
        "physiotherapist"
    ],
    "wof:name":"Meredith Melanie",
    "wof:placetype":"venue"
},
  "geometry": {"coordinates":[151.168533325,-33.7752380371],"type":"Point"}
}