{
  "type": "Feature",
  "properties": {
    "iso:country":"AU",
    "sg:address":"607 Nepean Hwy",
    "sg:city":"Frankston South",
    "sg:classifiers":[
        {
            "category":"Arts & Performance",
            "subcategory":"Music",
            "type":"Entertainment"
        }
    ],
    "sg:phone":"+61 411 781 996",
    "sg:postcode":"3199",
    "sg:province":"VIC",
    "sg:tags":[
        "mobile",
        "jockey",
        "disc"
    ],
    "wof:name":"Music Design",
    "wof:placetype":"venue"
},
  "geometry": {"coordinates":[145.10536193900001,-38.1577644348],"type":"Point"}
}