{
  "type": "Feature",
  "properties": {
    "iso:country":"AU",
    "sg:address":"37a Commercial Drv",
    "sg:city":"Thomastown",
    "sg:classifiers":[
        {
            "category":"Manufacturing",
            "subcategory":"Tools & Machinery",
            "type":"Manufacturing & Wholesale Goods"
        }
    ],
    "sg:phone":"+61 3 9466 2229",
    "sg:postcode":"3074",
    "sg:province":"VIC",
    "sg:tags":[
        "toolmaker"
    ],
    "wof:name":"I.C.E Industries Pty Ltd",
    "wof:placetype":"venue"
},
  "geometry": {"coordinates":[145.041213989,-37.6893577576],"type":"Point"}
}