{
  "type": "Feature",
  "properties": {
    "iso:country":"AU",
    "sg:address":"14a Claremont St",
    "sg:city":"South Yarra",
    "sg:classifiers":[
        {
            "category":"Bars & Pubs",
            "subcategory":"Nightclub",
            "type":"Food & Drink"
        }
    ],
    "sg:phone":"+61 3 9826 8373",
    "sg:postcode":"3141",
    "sg:province":"VIC",
    "sg:tags":[
        "discotheque"
    ],
    "wof:name":"Warehouse Niteclub The",
    "wof:placetype":"venue"
},
  "geometry": {"coordinates":[144.99392700199999,-37.8380889893],"type":"Point"}
}