{
  "type": "Feature",
  "properties": {
    "iso:country":"AU",
    "sg:address":"437 Old Geelong Rd",
    "sg:city":"Hoppers Crossing",
    "sg:classifiers":[
        {
            "category":"Banks & Credit Unions",
            "subcategory":"Investment Brokerage",
            "type":"Services"
        }
    ],
    "sg:phone":"+61 3 9369 6566",
    "sg:postcode":"3029",
    "sg:province":"VIC",
    "sg:tags":[
        "repairer",
        "typewriter"
    ],
    "wof:name":"Metro Ribbons Pty Ltd",
    "wof:placetype":"venue"
},
  "geometry": {"coordinates":[144.731506,-37.868725],"type":"Point"}
}