{
  "type": "Feature",
  "properties": {
    "iso:country":"AU",
    "sg:address":"Stoney Rise Rd",
    "sg:city":"Devonport",
    "sg:classifiers":[
        {
            "category":"Home & Garden",
            "subcategory":"Building Materials",
            "type":"Retail Goods"
        }
    ],
    "sg:phone":"+61 3 6421 5720",
    "sg:postcode":"7310",
    "sg:province":"TAS",
    "sg:tags":[
        "pre-mixed",
        "concrete"
    ],
    "wof:name":"Boral Construction Materials Group Ltd",
    "wof:placetype":"venue"
},
  "geometry": {"coordinates":[146.335372925,-41.1946678162],"type":"Point"}
}