{
  "type": "Feature",
  "properties": {
    "addr:full":"250 Brunker Rd Adamstown NSW 2289",
    "addr:housenumber":"250",
    "addr:postcode":"2289",
    "addr:street":"Brunker Rd",
    "iso:country":"AU",
    "sg:address":"250 Brunker Rd",
    "sg:city":"Adamstown",
    "sg:classifiers":[
        {
            "category":"Banks & Credit Unions",
            "subcategory":"Financial Services",
            "type":"Services"
        }
    ],
    "sg:phone":"+61 13 19 87",
    "sg:postcode":"2289",
    "sg:province":"NSW",
    "sg:tags":[
        "building",
        "society"
    ],
    "wof:name":"Newcastle Permanent Building Society Ltd",
    "wof:placetype":"venue"
},
  "geometry": {"coordinates":[151.72572326700001,-32.9343299866],"type":"Point"}
}