{
  "type": "Feature",
  "properties": {
    "addr:full":"\"Vinegrove\" Albany St Berry NSW 2535",
    "addr:postcode":"2535",
    "addr:street":"Albany St",
    "iso:country":"AU",
    "sg:address":"\"Vinegrove\" Albany St",
    "sg:city":"Berry",
    "sg:classifiers":[
        {
            "category":"Farming",
            "subcategory":"Dairy Farm",
            "type":"Manufacturing & Wholesale Goods"
        }
    ],
    "sg:phone":"+61 2 4464 1170",
    "sg:postcode":"2535",
    "sg:province":"NSW",
    "wof:name":"J R & S V Hall",
    "wof:placetype":"venue"
},
  "geometry": {"coordinates":[150.693069458,-34.779914856],"type":"Point"}
}