{
  "type": "Feature",
  "properties": {
    "addr:full":"750 Gloucester Rd Wingham NSW 2429",
    "addr:housenumber":"750",
    "addr:postcode":"2429",
    "addr:street":"Gloucester Rd",
    "iso:country":"AU",
    "sg:address":"750 Gloucester Rd",
    "sg:city":"Wingham",
    "sg:classifiers":[
        {
            "category":"Farming",
            "subcategory":"Farm",
            "type":"Manufacturing & Wholesale Goods"
        }
    ],
    "sg:phone":"+61 2 6553 4242",
    "sg:postcode":"2429",
    "sg:province":"NSW",
    "sg:tags":[
        "farmer"
    ],
    "wof:name":"Walsh E P",
    "wof:placetype":"venue"
},
  "geometry": {"coordinates":[152.357834,-31.874146],"type":"Point"}
}