{
  "type": "Feature",
  "properties": {
    "iso:country":"AU",
    "sg:address":"Mayes Ave",
    "sg:city":"Woodridge",
    "sg:classifiers":[
        {
            "category":"Fast Food",
            "type":"Food & Drink"
        }
    ],
    "sg:phone":"+61 7 3208 8333",
    "sg:postcode":"4114",
    "sg:province":"QLD",
    "sg:tags":[
        "away",
        "take"
    ],
    "wof:name":"KFC",
    "wof:placetype":"venue"
},
  "geometry": {"coordinates":[153.10958862300001,-27.6425743103],"type":"Point"}
}