{
  "type": "Feature",
  "properties": {
    "iso:country":"AU",
    "sg:address":"St",
    "sg:city":"Albans Park",
    "sg:classifiers":[
        {
            "category":"Shopping",
            "subcategory":"Party Supplies",
            "type":"Retail Goods"
        }
    ],
    "sg:phone":"+61 3 5248 6959",
    "sg:postcode":"3219",
    "sg:province":"VIC",
    "sg:tags":[
        "children's"
    ],
    "wof:name":"Kids Love Castles",
    "wof:placetype":"venue"
},
  "geometry": {"coordinates":[144.38893127399999,-38.1841583252],"type":"Point"}
}