{
  "type": "Feature",
  "properties": {
    "addr:full":"Centre, Shepparton Private Hosp. Fitzgerald St Shepparton VIC 3630",
    "addr:postcode":"3630",
    "addr:street":"St",
    "iso:country":"AU",
    "sg:address":"Centre, Shepparton Private Hosp. Fitzgerald St",
    "sg:city":"Shepparton",
    "sg:classifiers":[
        {
            "category":"Health Services",
            "subcategory":"Doctor",
            "type":"Services"
        }
    ],
    "sg:phone":"+61 3 5821 6877",
    "sg:postcode":"3630",
    "sg:province":"VIC",
    "sg:tags":[
        "medical",
        "practitioner"
    ],
    "wof:name":"Critchley I J",
    "wof:placetype":"venue"
},
  "geometry": {"coordinates":[145.41163635300001,-36.3617172241],"type":"Point"}
}