{
  "type": "Feature",
  "properties": {
    "addr:full":"5 Toonburra St Bundaberg QLD 4670",
    "addr:housenumber":"5",
    "addr:postcode":"4670",
    "addr:street":"Toonburra St",
    "iso:country":"AU",
    "sg:address":"5 Toonburra St",
    "sg:city":"Bundaberg",
    "sg:classifiers":[
        {
            "category":"Building & Trades",
            "subcategory":"Plumbing",
            "type":"Services"
        }
    ],
    "sg:phone":"+61 7 4151 2399",
    "sg:postcode":"4670",
    "sg:province":"QLD",
    "sg:tags":[
        "fitting",
        "hose",
        "supply"
    ],
    "wof:name":"Brake & Clutch Service",
    "wof:placetype":"venue"
},
  "geometry": {"coordinates":[152.35624694800001,-24.8636703491],"type":"Point"}
}