{
  "type": "Feature",
  "properties": {
    "addr:full":"91 Old Cleveland Rd Stones Corner QLD 4120",
    "addr:housenumber":"91",
    "addr:postcode":"4120",
    "addr:street":"Old Cleveland Rd",
    "iso:country":"AU",
    "sg:address":"91 Old Cleveland Rd",
    "sg:city":"Stones Corner",
    "sg:classifiers":[
        {
            "category":"Retail",
            "subcategory":"Repair Shop",
            "type":"Services"
        }
    ],
    "sg:phone":"+61 7 3397 2797",
    "sg:postcode":"4120",
    "sg:province":"QLD",
    "sg:tags":[
        "upholsterer"
    ],
    "wof:name":"A-1 Furniture Upholsterers",
    "wof:placetype":"venue"
},
  "geometry": {"coordinates":[153.046966553,-27.498884201],"type":"Point"}
}