{
  "type": "Feature",
  "properties": {
    "addr:full":"Mt Carmel Campus Flinders Hwy Charters Towers QLD 4820",
    "addr:postcode":"4820",
    "addr:street":"Flinders Hwy",
    "iso:country":"AU",
    "sg:address":"Mt Carmel Campus Flinders Hwy",
    "sg:city":"Charters Towers",
    "sg:classifiers":[
        {
            "category":"Education",
            "subcategory":"School",
            "type":"Public Place"
        }
    ],
    "sg:phone":"+61 7 4787 1744",
    "sg:postcode":"4820",
    "sg:province":"QLD",
    "wof:name":"Columba Catholic College",
    "wof:placetype":"venue"
},
  "geometry": {"coordinates":[146.26220699999999,-20.077763],"type":"Point"}
}