{
  "type": "Feature",
  "properties": {
    "iso:country":"AU",
    "sg:address":"166 Ocean St",
    "sg:city":"Narrabeen",
    "sg:classifiers":[
        {
            "category":"Fast Food",
            "type":"Food & Drink"
        }
    ],
    "sg:phone":"+61 2 9970 6193",
    "sg:postcode":"2101",
    "sg:province":"NSW",
    "sg:tags":[
        "away",
        "take"
    ],
    "wof:name":"Gina's Mixed Business",
    "wof:placetype":"venue"
},
  "geometry": {"coordinates":[151.301895,-33.709156],"type":"Point"}
}