{
  "type": "Feature",
  "properties": {
    "addr:full":"41 Edward St Ottoway SA 5013",
    "addr:housenumber":"41",
    "addr:postcode":"5013",
    "addr:street":"Edward St",
    "iso:country":"AU",
    "sg:address":"41 Edward St",
    "sg:city":"Ottoway",
    "sg:classifiers":[
        {
            "category":"Mining & Drilling",
            "type":"Manufacturing & Wholesale Goods"
        }
    ],
    "sg:phone":"+61 414 612 199",
    "sg:postcode":"5013",
    "sg:province":"SA",
    "sg:tags":[
        "concrete",
        "breaking",
        "grinding",
        "sawing"
    ],
    "wof:name":"Supercore",
    "wof:placetype":"venue"
},
  "geometry": {"coordinates":[138.53001403799999,-34.8466567993],"type":"Point"}
}