{
  "type": "Feature",
  "properties": {
    "addr:full":"21 Troy Drv Goondiwindi QLD 4390",
    "addr:housenumber":"21",
    "addr:postcode":"4390",
    "addr:street":"Troy Drv",
    "iso:country":"AU",
    "sg:address":"21 Troy Drv",
    "sg:city":"Goondiwindi",
    "sg:classifiers":[
        {
            "category":"Building & Trades",
            "subcategory":"Construction",
            "type":"Services"
        }
    ],
    "sg:phone":"+61 7 4671 3200",
    "sg:postcode":"4390",
    "sg:province":"QLD",
    "sg:tags":[
        "welding"
    ],
    "wof:name":"Agfab Pty Ltd",
    "wof:placetype":"venue"
},
  "geometry": {"coordinates":[150.29612731899999,-28.5301895142],"type":"Point"}
}