{
  "type": "Feature",
  "properties": {
    "addr:full":"176 Swan Drv Derrimut VIC 3030",
    "addr:housenumber":"176",
    "addr:postcode":"3030",
    "addr:street":"Swan Drv",
    "iso:country":"AU",
    "sg:address":"176 Swan Drv",
    "sg:city":"Derrimut",
    "sg:classifiers":[
        {
            "category":"Commercial Area",
            "type":"Public Place"
        }
    ],
    "sg:phone":"+61 3 9368 7270",
    "sg:postcode":"3030",
    "sg:province":"VIC",
    "sg:tags":[
        "heavy",
        "carrier"
    ],
    "wof:name":"J.J. Williams Transport",
    "wof:placetype":"venue"
},
  "geometry": {"coordinates":[144.74522400000001,-37.926224],"type":"Point"}
}