{
  "type": "Feature",
  "properties": {
    "addr:full":"98 Bazaar St Maryborough QLD 4650",
    "addr:housenumber":"98",
    "addr:postcode":"4650",
    "addr:street":"Bazaar St",
    "iso:country":"AU",
    "sg:address":"98 Bazaar St",
    "sg:city":"Maryborough",
    "sg:classifiers":[
        {
            "category":"Professional",
            "subcategory":"Accounting & Tax Preparation",
            "type":"Services"
        }
    ],
    "sg:phone":"+61 7 4123 2199",
    "sg:postcode":"4650",
    "sg:province":"QLD",
    "sg:tags":[
        "consultant",
        "taxation"
    ],
    "wof:name":"Alison & Associates Chartered Accountants",
    "wof:placetype":"venue"
},
  "geometry": {"coordinates":[152.70164500000001,-25.540209],"type":"Point"}
}