{
  "type": "Feature",
  "properties": {
    "addr:full":"8 Orient Crt Buderim QLD 4556",
    "addr:housenumber":"8",
    "addr:postcode":"4556",
    "addr:street":"Orient Crt",
    "iso:country":"AU",
    "sg:address":"8 Orient Crt",
    "sg:city":"Buderim",
    "sg:classifiers":[
        {
            "category":"Professional",
            "subcategory":"Employment Agencies",
            "type":"Services"
        }
    ],
    "sg:phone":"+61 7 5445 1746",
    "sg:postcode":"4556",
    "sg:province":"QLD",
    "sg:tags":[
        "entertainer",
        "agent"
    ],
    "wof:name":"T E Showband",
    "wof:placetype":"venue"
},
  "geometry": {"coordinates":[153.039749145,-26.6943683624],"type":"Point"}
}