{
  "type": "Feature",
  "properties": {
    "iso:country":"AU",
    "sg:address":"Gilbert St",
    "sg:city":"Lyndoch",
    "sg:classifiers":[
        {
            "category":"Wholesale",
            "subcategory":"Machinery & Supplies",
            "type":"Manufacturing & Wholesale Goods"
        }
    ],
    "sg:phone":"+61 8 8524 4140",
    "sg:postcode":"5351",
    "sg:province":"SA",
    "sg:tags":[
        "agricultural"
    ],
    "wof:name":"Lyndoch Motors",
    "wof:placetype":"venue"
},
  "geometry": {"coordinates":[138.89027404800001,-34.6016616821],"type":"Point"}
}