{
  "type": "Feature",
  "properties": {
    "iso:country":"AU",
    "sg:address":"Shop 1/ 3 Gilbert Crt",
    "sg:city":"Boyne Island",
    "sg:classifiers":[
        {
            "category":"Health Services",
            "subcategory":"Health Practitioner",
            "type":"Services"
        }
    ],
    "sg:phone":"+61 7 4973 8883",
    "sg:postcode":"4680",
    "sg:province":"QLD",
    "sg:tags":[
        "physiotherapist"
    ],
    "wof:name":"Physioshop",
    "wof:placetype":"venue"
},
  "geometry": {"coordinates":[151.35299682600001,-23.9463253021],"type":"Point"}
}