{
  "type": "Feature",
  "properties": {
    "addr:full":"592 Ross River Rd Kirwan QLD 4817",
    "addr:housenumber":"592",
    "addr:postcode":"4817",
    "addr:street":"Ross River Rd",
    "iso:country":"AU",
    "sg:address":"592 Ross River Rd",
    "sg:city":"Kirwan",
    "sg:classifiers":[
        {
            "category":"Education",
            "subcategory":"School",
            "type":"Public Place"
        }
    ],
    "sg:phone":"+61 7 4726 1333",
    "sg:postcode":"4817",
    "sg:province":"QLD",
    "sg:tags":[
        "state",
        "except",
        "nsw"
    ],
    "wof:name":"Weir Primary",
    "wof:placetype":"venue"
},
  "geometry": {"coordinates":[146.740005,-19.313599],"type":"Point"}
}