{
  "type": "Feature",
  "properties": {
    "addr:full":"6/ 32 Mountjoy Pde Lorne VIC 3232",
    "addr:housenumber":"/ 32",
    "addr:postcode":"3232",
    "addr:street":"Mountjoy Pde",
    "iso:country":"AU",
    "sg:address":"6/ 32 Mountjoy Pde",
    "sg:city":"Lorne",
    "sg:classifiers":[
        {
            "category":"Real Estate",
            "subcategory":"Real Estate Agent",
            "type":"Services"
        }
    ],
    "sg:phone":"+61 3 5289 1278",
    "sg:postcode":"3232",
    "sg:province":"VIC",
    "wof:name":"Smyth Real Estate",
    "wof:placetype":"venue"
},
  "geometry": {"coordinates":[143.97511299999999,-38.539795],"type":"Point"}
}