{
  "type": "Feature",
  "properties": {
    "addr:full":"85 Jubilee St Dubbo NSW 2830",
    "addr:housenumber":"85",
    "addr:postcode":"2830",
    "addr:street":"Jubilee St",
    "iso:country":"AU",
    "sg:address":"85 Jubilee St",
    "sg:city":"Dubbo",
    "sg:classifiers":[
        {
            "category":"Personal",
            "subcategory":"Beauty Salon",
            "type":"Services"
        }
    ],
    "sg:phone":"+61 2 6882 6881",
    "sg:postcode":"2830",
    "sg:province":"NSW",
    "sg:tags":[
        "hairdresser"
    ],
    "wof:name":"Pure Platinum Hair Studio",
    "wof:placetype":"venue"
},
  "geometry": {"coordinates":[148.61167907699999,-32.264251709],"type":"Point"}
}