{
  "type": "Feature",
  "properties": {
    "addr:full":"502/ 39 East Esplanade Manly NSW 2095",
    "addr:housenumber":"502 / 39",
    "addr:postcode":"2095",
    "addr:street":"East Esplanade",
    "iso:country":"AU",
    "sg:address":"502/ 39",
    "sg:city":"East Esplanade Manly",
    "sg:classifiers":[
        {
            "category":"Health Services",
            "subcategory":"Doctor",
            "type":"Services"
        }
    ],
    "sg:phone":"+61 2 9976 0055",
    "sg:postcode":"2095",
    "sg:province":"NSW",
    "sg:tags":[
        "medical",
        "practitioner"
    ],
    "wof:name":"North Shore Dermatology & Specialist Skin Cancer Centre",
    "wof:placetype":"venue"
},
  "geometry": {"coordinates":[151.28582763700001,-33.799911499],"type":"Point"}
}