{
  "type": "Feature",
  "properties": {
    "iso:country":"AU",
    "sg:address":"5 Athena Pl",
    "sg:city":"Roleystone",
    "sg:classifiers":[
        {
            "category":"Building & Trades",
            "subcategory":"Cleaning & Sanitation",
            "type":"Services"
        }
    ],
    "sg:phone":"+61 8 9496 3285",
    "sg:postcode":"6111",
    "sg:province":"WA",
    "sg:tags":[
        "industrial",
        "commercial",
        "contractor"
    ],
    "wof:name":"D & E Cleaning Services",
    "wof:placetype":"venue"
},
  "geometry": {"coordinates":[116.07787322999999,-32.1174545288],"type":"Point"}
}