{
  "type": "Feature",
  "properties": {
    "addr:full":"U503/ 1 Como Crs Southport QLD 4215",
    "addr:housenumber":"u503 / 1",
    "addr:postcode":"4215",
    "addr:street":"Como Crs",
    "iso:country":"AU",
    "sg:address":"U503/ 1 Como Crs",
    "sg:city":"Southport",
    "sg:classifiers":[
        {
            "category":"Banks & Credit Unions",
            "subcategory":"Financial Services",
            "type":"Services"
        }
    ],
    "sg:phone":"+61 7 5532 1066",
    "sg:postcode":"4215",
    "sg:province":"QLD",
    "sg:tags":[
        "loan",
        "finance",
        "mortgage"
    ],
    "wof:name":"Teamwork Finance",
    "wof:placetype":"venue"
},
  "geometry": {"coordinates":[153.417434692,-27.9714431763],"type":"Point"}
}