{
  "type": "Feature",
  "properties": {
    "iso:country":"AU",
    "sg:address":"Unit 6, 116 McCredie Rd",
    "sg:city":"Guildford",
    "sg:classifiers":[
        {
            "category":"Retail",
            "subcategory":"Storage",
            "type":"Services"
        }
    ],
    "sg:phone":"+61 2 9632 8909",
    "sg:postcode":"2161",
    "sg:province":"NSW",
    "sg:tags":[
        "removal",
        "furniture"
    ],
    "wof:name":"Fine-Form Removals",
    "wof:placetype":"venue"
},
  "geometry": {"coordinates":[150.960479736,-33.8503189087],"type":"Point"}
}