{
  "type": "Feature",
  "properties": {
    "addr:full":"83 A Kedron Brook Rd Wilston QLD 4051",
    "addr:housenumber":"83 a",
    "addr:postcode":"4051",
    "addr:street":"Kedron Brook Rd",
    "iso:country":"AU",
    "sg:address":"83 A Kedron Brook Rd",
    "sg:city":"Wilston",
    "sg:classifiers":[
        {
            "category":"Cafe",
            "type":"Food & Drink"
        }
    ],
    "sg:phone":"+61 7 3856 1508",
    "sg:postcode":"4051",
    "sg:province":"QLD",
    "wof:name":"Urban Bites Retail",
    "wof:placetype":"venue"
},
  "geometry": {"coordinates":[153.01963806099999,-27.4321956635],"type":"Point"}
}