{
  "type": "Feature",
  "properties": {
    "addr:full":"50 Consett St Concord West NSW 2138",
    "addr:housenumber":"50",
    "addr:postcode":"2138",
    "addr:street":"Consett St",
    "iso:country":"AU",
    "sg:address":"50 Consett St",
    "sg:city":"Concord West",
    "sg:classifiers":[
        {
            "category":"Professional",
            "subcategory":"Computer Services",
            "type":"Services"
        }
    ],
    "sg:phone":"+61 2 8765 0688",
    "sg:postcode":"2138",
    "sg:province":"NSW",
    "sg:tags":[
        "package",
        "software"
    ],
    "wof:name":"SSoM Software",
    "wof:placetype":"venue"
},
  "geometry": {"coordinates":[151.08811950699999,-33.8523216248],"type":"Point"}
}