{
  "type": "Feature",
  "properties": {
    "iso:country":"AU",
    "sg:address":"AMP Chambers Level 2, 57 Hunter St",
    "sg:city":"Newcastle",
    "sg:classifiers":[
        {
            "category":"Health Services",
            "subcategory":"Dentist",
            "type":"Services"
        }
    ],
    "sg:phone":"+61 2 4929 3077",
    "sg:postcode":"2300",
    "sg:province":"NSW",
    "wof:name":"McCabe Damon Dr. B.D.S. (Syd)",
    "wof:placetype":"venue"
},
  "geometry": {"coordinates":[151.783875,-32.927822],"type":"Point"}
}