{
  "type": "Feature",
  "properties": {
    "addr:full":"Factory 3 4-6 Somerleigh Rd Laverton North VIC 3026",
    "addr:housenumber":"4-6",
    "addr:postcode":"3026",
    "addr:street":"Somerleigh Rd",
    "iso:country":"AU",
    "sg:address":"Factory 3 4-6 Somerleigh Rd",
    "sg:city":"Laverton North",
    "sg:classifiers":[
        {
            "category":"Manufacturing",
            "subcategory":"Tools & Machinery",
            "type":"Manufacturing & Wholesale Goods"
        }
    ],
    "sg:phone":"+61 3 9315 3788",
    "sg:postcode":"3026",
    "sg:province":"VIC",
    "sg:tags":[
        "earth",
        "excavating",
        "moving",
        "equipment"
    ],
    "wof:name":"Walkers Hammers (Vic)",
    "wof:placetype":"venue"
},
  "geometry": {"coordinates":[144.81338500000001,-37.816269],"type":"Point"}
}