{
  "type": "Feature",
  "properties": {
    "iso:country":"AU",
    "sg:address":"127 Murray St",
    "sg:city":"Finley",
    "sg:classifiers":[
        {
            "category":"Food & Beverages",
            "subcategory":"Bakery",
            "type":"Retail Goods"
        }
    ],
    "sg:phone":"+61 3 5883 3277",
    "sg:postcode":"2713",
    "sg:province":"NSW",
    "sg:tags":[
        "baker"
    ],
    "wof:name":"Finley Hot Bread",
    "wof:placetype":"venue"
},
  "geometry": {"coordinates":[145.57786560100001,-35.6412963867],"type":"Point"}
}