{
  "type": "Feature",
  "properties": {
    "iso:country":"AU",
    "sg:address":"55 Pacific Hwy",
    "sg:city":"Waitara",
    "sg:classifiers":[
        {
            "category":"Travel",
            "subcategory":"Hotels & Motels",
            "type":"Entertainment"
        }
    ],
    "sg:phone":"+61 2 9489 3220",
    "sg:postcode":"2077",
    "sg:province":"NSW",
    "sg:tags":[
        "pub"
    ],
    "wof:name":"Blue Gum Hotel",
    "wof:placetype":"venue"
},
  "geometry": {"coordinates":[151.10304260300001,-33.7106399536],"type":"Point"}
}