{
  "type": "Feature",
  "properties": {
    "addr:full":"Cnr Hunter & Albion Sts Brassall QLD 4305",
    "addr:postcode":"4305",
    "addr:street":"Cnr",
    "iso:country":"AU",
    "sg:address":"Cnr Hunter & Albion Sts",
    "sg:city":"Brassall",
    "sg:classifiers":[
        {
            "category":"Health Services",
            "subcategory":"Dentist",
            "type":"Services"
        }
    ],
    "sg:phone":"+61 7 3201 4106",
    "sg:postcode":"4305",
    "sg:province":"QLD",
    "wof:name":"Brassall Clinic Dental",
    "wof:placetype":"venue"
},
  "geometry": {"coordinates":[152.74511718799999,-27.5983943939],"type":"Point"}
}