{
  "type": "Feature",
  "properties": {
    "addr:full":"Level 3, Aughtie Drv Albert Park VIC 3206",
    "addr:postcode":"3206",
    "addr:street":"Aughtie Drv",
    "iso:country":"AU",
    "sg:address":"Level 3, Aughtie Drv",
    "sg:city":"Albert Park",
    "sg:classifiers":[
        {
            "category":"Personal",
            "subcategory":"Massage",
            "type":"Services"
        }
    ],
    "sg:phone":"+61 3 9682 3011",
    "sg:postcode":"3206",
    "sg:province":"VIC",
    "sg:tags":[
        "therapy"
    ],
    "wof:name":"DiMicheli Maria",
    "wof:placetype":"venue"
},
  "geometry": {"coordinates":[144.974976,-37.853333],"type":"Point"}
}