{
  "type": "Feature",
  "properties": {
    "addr:full":"320 Cooperabung Drv Telegraph Point NSW 2441",
    "addr:housenumber":"320",
    "addr:postcode":"2441",
    "addr:street":"Cooperabung Drv",
    "iso:country":"AU",
    "sg:address":"320 Cooperabung Drv",
    "sg:city":"Telegraph Point",
    "sg:classifiers":[
        {
            "category":"Manufacturing",
            "subcategory":"Lumber",
            "type":"Manufacturing & Wholesale Goods"
        }
    ],
    "sg:phone":"+61 2 6585 0225",
    "sg:postcode":"2441",
    "sg:province":"NSW",
    "sg:tags":[
        "sawmillers"
    ],
    "wof:name":"K.C. Cooper & Sons",
    "wof:placetype":"venue"
},
  "geometry": {"coordinates":[152.81286600000001,-31.303932],"type":"Point"}
}