{
  "type": "Feature",
  "properties": {
    "addr:full":"125 Manning Rd Woollahra NSW 2025",
    "addr:housenumber":"125",
    "addr:postcode":"2025",
    "addr:street":"Manning Rd",
    "iso:country":"AU",
    "sg:address":"125 Manning Rd",
    "sg:city":"Woollahra",
    "sg:classifiers":[
        {
            "category":"Retail",
            "subcategory":"Veterinary Services",
            "type":"Services"
        }
    ],
    "sg:phone":"+61 2 9363 4045",
    "sg:postcode":"2025",
    "sg:province":"NSW",
    "sg:tags":[
        "surgeon"
    ],
    "wof:name":"Malik Richard Dr",
    "wof:placetype":"venue"
},
  "geometry": {"coordinates":[151.24630737300001,-33.8861885071],"type":"Point"}
}