{
  "type": "Feature",
  "properties": {
    "addr:full":"175 Lord St Newtown NSW 2042",
    "addr:housenumber":"175",
    "addr:postcode":"2042",
    "addr:street":"Lord St",
    "iso:country":"AU",
    "sg:address":"175 Lord St",
    "sg:city":"Newtown",
    "sg:classifiers":[
        {
            "category":"Home & Garden",
            "subcategory":"Building Materials",
            "type":"Retail Goods"
        }
    ],
    "sg:phone":"+61 2 9519 7776",
    "sg:postcode":"2042",
    "sg:province":"NSW",
    "sg:tags":[
        "roofing"
    ],
    "wof:name":"Fold-N-Roll",
    "wof:placetype":"venue"
},
  "geometry": {"coordinates":[151.175186,-33.908215],"type":"Point"}
}