{
  "type": "Feature",
  "properties": {
    "addr:full":"7 Orchard St Upper Swan WA 6069",
    "addr:housenumber":"7",
    "addr:postcode":"6069",
    "addr:street":"Orchard St Upper",
    "iso:country":"AU",
    "sg:address":"7 Orchard St",
    "sg:city":"Upper Swan",
    "sg:classifiers":[
        {
            "category":"Building & Trades",
            "subcategory":"Construction",
            "type":"Services"
        }
    ],
    "sg:phone":"+61 8 9296 4204",
    "sg:postcode":"6069",
    "sg:province":"WA",
    "sg:tags":[
        "ceiling"
    ],
    "wof:name":"Jarvis JR & LM",
    "wof:placetype":"venue"
},
  "geometry": {"coordinates":[116.030319214,-31.7692546844],"type":"Point"}
}