{
  "type": "Feature",
  "properties": {
    "addr:full":"75 Greta Rd Wangaratta VIC 3677",
    "addr:housenumber":"75",
    "addr:postcode":"3677",
    "addr:street":"Greta Rd",
    "iso:country":"AU",
    "sg:address":"75 Greta Rd",
    "sg:city":"Wangaratta",
    "sg:classifiers":[
        {
            "category":"Autos & Motor Vehicles",
            "subcategory":"Fuel & Gas Station",
            "type":"Retail Goods"
        }
    ],
    "sg:phone":"+61 409 024 127",
    "sg:postcode":"3677",
    "sg:province":"VIC",
    "wof:name":"Mobil Wangaratta",
    "wof:placetype":"venue"
},
  "geometry": {"coordinates":[146.313354492,-36.3699798584],"type":"Point"}
}