{
  "type": "Feature",
  "properties": {
    "addr:full":"28 Sir Joseph Banks St Botany NSW 2019",
    "addr:housenumber":"28",
    "addr:postcode":"2019",
    "addr:street":"Sir Joseph Banks St",
    "iso:country":"AU",
    "sg:address":"28 Sir Joseph Banks St",
    "sg:city":"Botany",
    "sg:classifiers":[
        {
            "category":"Manufacturing",
            "subcategory":"Glass & Minerals",
            "type":"Manufacturing & Wholesale Goods"
        }
    ],
    "sg:phone":"+61 2 9316 7525",
    "sg:postcode":"2019",
    "sg:province":"NSW",
    "sg:tags":[
        "repair",
        "fibreglass",
        "product"
    ],
    "wof:name":"Ijon Engineering (NSW) Pty Ltd",
    "wof:placetype":"venue"
},
  "geometry": {"coordinates":[151.202224731,-33.9503555298],"type":"Point"}
}