{
  "type": "Feature",
  "properties": {
    "iso:country":"AU",
    "sg:address":"Shop 4 130 Oyster Bay Rd",
    "sg:city":"Oyster Bay",
    "sg:classifiers":[
        {
            "category":"Food & Beverages",
            "subcategory":"Liquor & Beverages",
            "type":"Retail Goods"
        }
    ],
    "sg:phone":"+61 2 9528 5885",
    "sg:postcode":"2225",
    "sg:province":"NSW",
    "sg:tags":[
        "store"
    ],
    "wof:name":"Oyster Bay Cellars",
    "wof:placetype":"venue"
},
  "geometry": {"coordinates":[151.081008911,-34.0069885254],"type":"Point"}
}