{
  "type": "Feature",
  "properties": {
    "addr:full":"93 Cecil Ave Castle Hill NSW 2154",
    "addr:housenumber":"93",
    "addr:postcode":"2154",
    "addr:street":"Cecil Ave",
    "iso:country":"AU",
    "sg:address":"93 Cecil Ave",
    "sg:city":"Castle Hill",
    "sg:classifiers":[
        {
            "category":"Manufacturing",
            "subcategory":"Tools & Machinery",
            "type":"Manufacturing & Wholesale Goods"
        }
    ],
    "sg:phone":"+61 2 9899 3468",
    "sg:postcode":"2154",
    "sg:province":"NSW",
    "sg:tags":[
        "equipment",
        "scale",
        "weighing"
    ],
    "wof:name":"Electronic Load Weighing Co Of Australia Pty Ltd",
    "wof:placetype":"venue"
},
  "geometry": {"coordinates":[151.00114440900001,-33.7339057922],"type":"Point"}
}