{
  "type": "Feature",
  "properties": {
    "addr:full":"32 Borthwick Ave Murarrie QLD 4172",
    "addr:housenumber":"32",
    "addr:postcode":"4172",
    "addr:street":"Borthwick Ave",
    "iso:country":"AU",
    "sg:address":"32 Borthwick Ave",
    "sg:city":"Murarrie",
    "sg:classifiers":[
        {
            "category":"Social Services",
            "subcategory":"Retirement Home",
            "type":"Services"
        }
    ],
    "sg:phone":"+61 7 3896 0500",
    "sg:postcode":"4172",
    "sg:province":"QLD",
    "sg:tags":[
        "t-shirt",
        "supplier"
    ],
    "sg:website":"http://www.epiclegend.com",
    "wof:name":"Epicentre Trading Pty Ltd",
    "wof:placetype":"venue"
},
  "geometry": {"coordinates":[153.10325622600001,-27.4539031982],"type":"Point"}
}