{
  "type": "Feature",
  "properties": {
    "addr:full":"15 Waverly Crt Ormiston QLD 4160",
    "addr:housenumber":"15",
    "addr:postcode":"4160",
    "addr:street":"Waverly Crt",
    "iso:country":"AU",
    "sg:address":"15 Waverly Crt",
    "sg:city":"Ormiston",
    "sg:classifiers":[
        {
            "category":"Utilities",
            "subcategory":"Electric",
            "type":"Services"
        }
    ],
    "sg:phone":"+61 418 882 580",
    "sg:postcode":"4160",
    "sg:province":"QLD",
    "sg:tags":[
        "electrical",
        "contractor"
    ],
    "wof:name":"Jory S & K Electrical Pty Ltd",
    "wof:placetype":"venue"
},
  "geometry": {"coordinates":[153.25921630900001,-27.5049724579],"type":"Point"}
}