{
  "type": "Feature",
  "properties": {
    "iso:country":"AU",
    "sg:address":"116 Morphett Rd",
    "sg:city":"Glengowrie",
    "sg:classifiers":[
        {
            "category":"Building & Trades",
            "subcategory":"Construction",
            "type":"Services"
        }
    ],
    "sg:phone":"+61 8 8295 6164",
    "sg:postcode":"5044",
    "sg:province":"SA",
    "sg:tags":[
        "contractor"
    ],
    "wof:name":"Webber D R Pty Ltd",
    "wof:placetype":"venue"
},
  "geometry": {"coordinates":[138.538925,-34.993023],"type":"Point"}
}