{
  "type": "Feature",
  "properties": {
    "iso:country":"AU",
    "sg:address":"28 Collingwood St",
    "sg:city":"Albion",
    "sg:classifiers":[
        {
            "category":"Manufacturing",
            "subcategory":"Tools & Machinery",
            "type":"Manufacturing & Wholesale Goods"
        }
    ],
    "sg:phone":"+61 7 3262 7000",
    "sg:postcode":"4010",
    "sg:province":"QLD",
    "wof:name":"Kingcraft Australia",
    "wof:placetype":"venue"
},
  "geometry": {"coordinates":[153.04458618199999,-27.4329872131],"type":"Point"}
}