{
  "type": "Feature",
  "properties": {
    "iso:country":"AU",
    "sg:address":"Shop 2, 258 Auburn St",
    "sg:city":"Goulburn",
    "sg:classifiers":[
        {
            "category":"Shopping",
            "subcategory":"Clothing, Apparel, & Fashions",
            "type":"Retail Goods"
        }
    ],
    "sg:phone":"+61 2 4823 5340",
    "sg:postcode":"2580",
    "sg:province":"NSW",
    "sg:tags":[
        "accessory"
    ],
    "wof:name":"Bags On Auburn",
    "wof:placetype":"venue"
},
  "geometry": {"coordinates":[149.71978759800001,-34.7527618408],"type":"Point"}
}