{
  "type": "Feature",
  "properties": {
    "addr:full":"293 Pennant Hills Rd Thornleigh NSW 2120",
    "addr:housenumber":"293",
    "addr:postcode":"2120",
    "addr:street":"Pennant Hills Rd",
    "iso:country":"AU",
    "sg:address":"293 Pennant Hills Rd",
    "sg:city":"Thornleigh",
    "sg:classifiers":[
        {
            "category":"Arts & Performance",
            "subcategory":"Dance",
            "type":"Entertainment"
        }
    ],
    "sg:phone":"+61 2 9875 5345",
    "sg:postcode":"2120",
    "sg:province":"NSW",
    "sg:tags":[
        "theatrical",
        "ballet",
        "tuition"
    ],
    "wof:name":"Dancexpress",
    "wof:placetype":"venue"
},
  "geometry": {"coordinates":[151.08114624000001,-33.7310943604],"type":"Point"}
}