{
  "type": "Feature",
  "properties": {
    "addr:full":"28 Avalon Pde Avalon NSW 2107",
    "addr:housenumber":"28",
    "addr:postcode":"2107",
    "addr:street":"Avalon Pde",
    "iso:country":"AU",
    "sg:address":"28 Avalon Pde",
    "sg:city":"Avalon",
    "sg:classifiers":[
        {
            "category":"Food & Beverages",
            "subcategory":"Bakery",
            "type":"Retail Goods"
        }
    ],
    "sg:phone":"+61 2 9918 2948",
    "sg:postcode":"2107",
    "sg:province":"NSW",
    "sg:tags":[
        "cake",
        "shop",
        "pastry"
    ],
    "wof:name":"La Banette",
    "wof:placetype":"venue"
},
  "geometry": {"coordinates":[151.328521728,-33.6359024048],"type":"Point"}
}