{
  "type": "Feature",
  "properties": {
    "addr:full":"21 Strangways Rd Angle Vale SA 5117",
    "addr:housenumber":"21",
    "addr:postcode":"5117",
    "addr:street":"Strangways Rd",
    "iso:country":"AU",
    "sg:address":"21 Strangways Rd",
    "sg:city":"Angle Vale",
    "sg:classifiers":[
        {
            "category":"Building & Trades",
            "subcategory":"Construction",
            "type":"Services"
        }
    ],
    "sg:phone":"+61 8 8284 9260",
    "sg:postcode":"5117",
    "sg:province":"SA",
    "sg:tags":[
        "fencing",
        "contractor"
    ],
    "wof:name":"AV Fencing",
    "wof:placetype":"venue"
},
  "geometry": {"coordinates":[138.63946533199999,-34.6455230713],"type":"Point"}
}