{
  "type": "Feature",
  "properties": {
    "addr:full":"170 Glenroy Rd Glenroy VIC 3046",
    "addr:housenumber":"170",
    "addr:postcode":"3046",
    "addr:street":"Glenroy Rd",
    "iso:country":"AU",
    "sg:address":"170 Glenroy Rd",
    "sg:city":"Glenroy",
    "sg:classifiers":[
        {
            "category":"Personal",
            "subcategory":"Massage",
            "type":"Services"
        }
    ],
    "sg:phone":"+61 3 9323 6232",
    "sg:postcode":"3046",
    "sg:province":"VIC",
    "sg:tags":[
        "therapy"
    ],
    "wof:name":"Burnett Wendy",
    "wof:placetype":"venue"
},
  "geometry": {"coordinates":[144.920684814,-37.7052726746],"type":"Point"}
}