{
  "type": "Feature",
  "properties": {
    "iso:country":"AU",
    "sg:address":"Level 19/1 Farrer Place, Sydney",
    "sg:city":"Sydney",
    "sg:classifiers":[
        {
            "category":"Real Estate",
            "subcategory":"Real Estate Services",
            "type":"Services"
        }
    ],
    "sg:phone":"+61 2 9324 4211",
    "sg:postcode":"2000",
    "sg:province":"NSW",
    "sg:tags":[
        "consultant",
        "property"
    ],
    "wof:name":"Grant Samuel Property",
    "wof:placetype":"venue"
},
  "geometry": {"coordinates":[151.21072387699999,-33.8643341064],"type":"Point"}
}