{
  "type": "Feature",
  "properties": {
    "addr:full":"15 Fletcher St Byron Bay NSW 2481",
    "addr:housenumber":"15",
    "addr:postcode":"2481",
    "addr:street":"Fletcher St",
    "iso:country":"AU",
    "sg:address":"15 Fletcher St",
    "sg:city":"Byron Bay",
    "sg:classifiers":[
        {
            "category":"Real Estate",
            "subcategory":"Real Estate Agent",
            "type":"Services"
        }
    ],
    "sg:phone":"+61 2 6685 6222",
    "sg:postcode":"2481",
    "sg:province":"NSW",
    "wof:name":"Elders Real Estate NSW",
    "wof:placetype":"venue"
},
  "geometry": {"coordinates":[153.613815308,-28.6435031891],"type":"Point"}
}