{
  "type": "Feature",
  "properties": {
    "addr:full":"132 Victoria St Taree NSW 2430",
    "addr:housenumber":"132",
    "addr:postcode":"2430",
    "addr:street":"Victoria St",
    "iso:country":"AU",
    "sg:address":"132 Victoria St",
    "sg:city":"Taree",
    "sg:classifiers":[
        {
            "category":"Banks & Credit Unions",
            "subcategory":"Financial Services",
            "type":"Services"
        }
    ],
    "sg:phone":"+61 2 6552 4211",
    "sg:postcode":"2430",
    "sg:province":"NSW",
    "sg:tags":[
        "loan",
        "finance",
        "mortgage"
    ],
    "wof:name":"John Vaughan & Walker Smith",
    "wof:placetype":"venue"
},
  "geometry": {"coordinates":[152.462524,-31.912674],"type":"Point"}
}