{
  "type": "Feature",
  "properties": {
    "iso:country":"AU",
    "sg:address":"90 Kelly St",
    "sg:city":"Scone",
    "sg:classifiers":[
        {
            "category":"Health Services",
            "subcategory":"Chiropractor",
            "type":"Services"
        }
    ],
    "sg:phone":"+61 2 6543 4880",
    "sg:postcode":"2337",
    "sg:province":"NSW",
    "wof:name":"Collins Jonathan",
    "wof:placetype":"venue"
},
  "geometry": {"coordinates":[150.868484497,-32.0469322205],"type":"Point"}
}