{
  "type": "Feature",
  "properties": {
    "addr:full":"10 Jarvisfield Rd Picton NSW 2571",
    "addr:housenumber":"10",
    "addr:postcode":"2571",
    "addr:street":"Jarvisfield Rd",
    "iso:country":"AU",
    "sg:address":"10 Jarvisfield Rd",
    "sg:city":"Picton",
    "sg:classifiers":[
        {
            "category":"Social Services",
            "subcategory":"Adult Care",
            "type":"Services"
        }
    ],
    "sg:phone":"+61 2 4677 2444",
    "sg:postcode":"2571",
    "sg:province":"NSW",
    "sg:tags":[
        "towing"
    ],
    "wof:name":"Arrow Tilt Trays Service Pty Ltd",
    "wof:placetype":"venue"
},
  "geometry": {"coordinates":[150.621856689,-34.1638946533],"type":"Point"}
}