{
  "type": "Feature",
  "properties": {
    "addr:full":"9/26- 28 Wolseley St Drummoyne NSW 2047",
    "addr:housenumber":"/;28",
    "addr:postcode":"2047",
    "addr:street":"26;Wolseley St",
    "iso:country":"AU",
    "sg:address":"9/26- 28 Wolseley St",
    "sg:city":"Drummoyne",
    "sg:classifiers":[
        {
            "category":"Professional",
            "subcategory":"Computer Services",
            "type":"Services"
        }
    ],
    "sg:phone":"+61 2 9719 9558",
    "sg:postcode":"2047",
    "sg:province":"NSW",
    "sg:tags":[
        "repairs",
        "upgrade",
        "equipment"
    ],
    "wof:name":"F1 PC Help",
    "wof:placetype":"venue"
},
  "geometry": {"coordinates":[151.152435,-33.846184],"type":"Point"}
}