{
  "type": "Feature",
  "properties": {
    "iso:country":"AU",
    "sg:address":"Borambil Rd",
    "sg:city":"Quirindi",
    "sg:classifiers":[
        {
            "category":"Wholesale",
            "subcategory":"Fruits & Vegetables",
            "type":"Manufacturing & Wholesale Goods"
        }
    ],
    "sg:phone":"+61 2 6746 1331",
    "sg:postcode":"2343",
    "sg:province":"NSW",
    "sg:tags":[
        "produce",
        "grain"
    ],
    "wof:name":"Bayliss Trading Pty Ltd",
    "wof:placetype":"venue"
},
  "geometry": {"coordinates":[150.64862060600001,-31.5104522705],"type":"Point"}
}