{
  "type": "Feature",
  "properties": {
    "addr:full":"104 Poole St Welshpool WA 6106",
    "addr:housenumber":"104",
    "addr:postcode":"6106",
    "addr:street":"Poole St",
    "iso:country":"AU",
    "sg:address":"104 Poole St",
    "sg:city":"Welshpool",
    "sg:classifiers":[
        {
            "category":"Bars & Pubs",
            "subcategory":"Sports Bar",
            "type":"Food & Drink"
        }
    ],
    "sg:phone":"+61 8 9451 5022",
    "sg:postcode":"6106",
    "sg:province":"WA",
    "sg:tags":[
        "rolling",
        "forming",
        "metal"
    ],
    "wof:name":"Metallion Pty Ltd",
    "wof:placetype":"venue"
},
  "geometry": {"coordinates":[115.945617676,-31.9936141968],"type":"Point"}
}