{
  "type": "Feature",
  "properties": {
    "addr:full":"347 St Georges Rd Fitzroy North VIC 3068",
    "addr:housenumber":"347",
    "addr:postcode":"3068",
    "addr:street":"St Georges Rd",
    "iso:country":"AU",
    "sg:address":"347 St Georges Rd",
    "sg:city":"Fitzroy North",
    "sg:classifiers":[
        {
            "category":"Retail",
            "subcategory":"Laundry & Dry Cleaning",
            "type":"Services"
        }
    ],
    "sg:phone":"+61 3 9482 2588",
    "sg:postcode":"3068",
    "sg:province":"VIC",
    "sg:tags":[
        "manicurist"
    ],
    "wof:name":"Skintuition Beauty Therapy",
    "wof:placetype":"venue"
},
  "geometry": {"coordinates":[144.98692321799999,-37.7795143127],"type":"Point"}
}