{
  "type": "Feature",
  "properties": {
    "addr:full":"PO Box 1169 Maroubra NSW 2035",
    "addr:postcode":"2035",
    "iso:country":"AU",
    "sg:address":"PO Box 1169",
    "sg:city":"Maroubra",
    "sg:classifiers":[
        {
            "category":"Shopping",
            "subcategory":"Party Supplies",
            "type":"Retail Goods"
        }
    ],
    "sg:phone":"+61 2 9665 8296",
    "sg:postcode":"2035",
    "sg:province":"NSW",
    "sg:tags":[
        "children's"
    ],
    "wof:name":"Ramons Circus Spectacular",
    "wof:placetype":"venue"
},
  "geometry": {"coordinates":[151.23866272000001,-33.9415092468],"type":"Point"}
}