{
  "type": "Feature",
  "properties": {
    "iso:country":"AU",
    "sg:address":"7 Nullum St",
    "sg:city":"Murwillumbah",
    "sg:classifiers":[
        {
            "category":"Health Services",
            "subcategory":"Doctor",
            "type":"Services"
        }
    ],
    "sg:phone":"+61 2 6672 2844",
    "sg:postcode":"2484",
    "sg:province":"NSW",
    "sg:tags":[
        "podiatrist"
    ],
    "wof:name":"Jody Richter Podiatry Services",
    "wof:placetype":"venue"
},
  "geometry": {"coordinates":[153.39332580600001,-28.3274383545],"type":"Point"}
}