{
  "type": "Feature",
  "properties": {
    "iso:country":"AU",
    "sg:address":"4 Lakeview Ave",
    "sg:city":"Merimbula",
    "sg:classifiers":[
        {
            "category":"Utilities",
            "subcategory":"Water",
            "type":"Services"
        }
    ],
    "sg:phone":"+61 2 6495 3901",
    "sg:postcode":"2548",
    "sg:province":"NSW",
    "sg:tags":[
        "hot",
        "system"
    ],
    "wof:name":"L & G Electrics Pty Ltd",
    "wof:placetype":"venue"
},
  "geometry": {"coordinates":[149.92616272000001,-36.8882522583],"type":"Point"}
}