{
  "type": "Feature",
  "properties": {
    "addr:full":"Eaton Central Bunya Park Drv Eatons Hill QLD 4037",
    "addr:postcode":"4037",
    "addr:street":"Park Drv",
    "iso:country":"AU",
    "sg:address":"Eaton Central Bunya Park Drv",
    "sg:city":"Eatons Hill",
    "sg:classifiers":[
        {
            "category":"Education",
            "subcategory":"Kindergarten",
            "type":"Public Place"
        }
    ],
    "sg:phone":"+61 7 3264 6277",
    "sg:postcode":"4037",
    "sg:province":"QLD",
    "sg:tags":[
        "pre-schools"
    ],
    "wof:name":"Mother Duck Child Care & Pre-School Centres",
    "wof:placetype":"venue"
},
  "geometry": {"coordinates":[152.95341500000001,-27.341265],"type":"Point"}
}