{
  "type": "Feature",
  "properties": {
    "addr:full":"72 Sheppard St Hume ACT 2620",
    "addr:housenumber":"72",
    "addr:postcode":"2620",
    "addr:street":"Sheppard St",
    "iso:country":"AU",
    "sg:address":"72 Sheppard St",
    "sg:city":"Hume",
    "sg:classifiers":[
        {
            "category":"Professional",
            "subcategory":"Accounting & Tax Preparation",
            "type":"Services"
        }
    ],
    "sg:phone":"+61 2 6260 1238",
    "sg:postcode":"2620",
    "sg:province":"ACT",
    "sg:tags":[
        "record",
        "business",
        "destruction"
    ],
    "wof:name":"Canberra Paper Recycling Pty Ltd",
    "wof:placetype":"venue"
},
  "geometry": {"coordinates":[149.16645813,-35.3912658691],"type":"Point"}
}