{
  "type": "Feature",
  "properties": {
    "addr:full":"23 McDonald Crs Bassendean WA 6054",
    "addr:housenumber":"23",
    "addr:postcode":"6054",
    "addr:street":"Mcdonald Crs",
    "iso:country":"AU",
    "sg:address":"23 McDonald Crs",
    "sg:city":"Bassendean",
    "sg:classifiers":[
        {
            "category":"Wholesale",
            "subcategory":"Painting Supplies",
            "type":"Manufacturing & Wholesale Goods"
        }
    ],
    "sg:phone":"+61 8 9379 3300",
    "sg:postcode":"6054",
    "sg:province":"WA",
    "sg:tags":[
        "equipment",
        "spraying"
    ],
    "wof:name":"Aussie Spray & Blast Systems",
    "wof:placetype":"venue"
},
  "geometry": {"coordinates":[115.937797546,-31.9049663544],"type":"Point"}
}