{
  "type": "Feature",
  "properties": {
    "iso:country":"AU",
    "sg:address":"Playford Ave",
    "sg:city":"Whyalla",
    "sg:classifiers":[
        {
            "category":"Building & Trades",
            "subcategory":"Construction",
            "type":"Services"
        }
    ],
    "sg:phone":"+61 429 451 357",
    "sg:postcode":"5600",
    "sg:province":"SA",
    "sg:tags":[
        "concrete",
        "contractor"
    ],
    "wof:name":"Whyalla Concrete Pumping",
    "wof:placetype":"venue"
},
  "geometry": {"coordinates":[137.563004,-33.035633],"type":"Point"}
}