{
  "type": "Feature",
  "properties": {
    "addr:full":"39 Owen Rd Kelmscott WA 6111",
    "addr:housenumber":"39",
    "addr:postcode":"6111",
    "addr:street":"Owen Rd",
    "iso:country":"AU",
    "sg:address":"39 Owen Rd",
    "sg:city":"Kelmscott",
    "sg:classifiers":[
        {
            "category":"Transit Center",
            "subcategory":"Passenger",
            "type":"Transportation"
        }
    ],
    "sg:phone":"+61 8 9497 4610",
    "sg:postcode":"6111",
    "sg:province":"WA",
    "sg:tags":[
        "wood",
        "moulding",
        "plastic"
    ],
    "wof:name":"Glosswood Pty Ltd",
    "wof:placetype":"venue"
},
  "geometry": {"coordinates":[116.00607299799999,-32.1325683594],"type":"Point"}
}