{
  "type": "Feature",
  "properties": {
    "iso:country":"AU",
    "sg:address":"City Link Plaza, Morisset St",
    "sg:city":"Queanbeyan",
    "sg:classifiers":[
        {
            "category":"Personal",
            "subcategory":"Nail Salon",
            "type":"Services"
        }
    ],
    "sg:phone":"+61 2 6298 1226",
    "sg:postcode":"2620",
    "sg:province":"ACT",
    "sg:tags":[
        "artificial"
    ],
    "wof:name":"Deleva Total Beauty Care",
    "wof:placetype":"venue"
},
  "geometry": {"coordinates":[149.23194885300001,-35.3519973755],"type":"Point"}
}