{
  "type": "Feature",
  "properties": {
    "iso:country":"AU",
    "sg:address":"369 Princes Hwy",
    "sg:city":"Woonona",
    "sg:classifiers":[
        {
            "category":"Shopping",
            "subcategory":"Clothing, Apparel, & Fashions",
            "type":"Retail Goods"
        }
    ],
    "sg:phone":"+61 2 4283 1933",
    "sg:postcode":"2517",
    "sg:province":"NSW",
    "sg:tags":[
        "lady",
        "wear"
    ],
    "wof:name":"Jo's Dressing Room",
    "wof:placetype":"venue"
},
  "geometry": {"coordinates":[150.90713500999999,-34.3407173157],"type":"Point"}
}