{
  "type": "Feature",
  "properties": {
    "addr:full":"378 Goodwood Rd Goodwood SA 5034",
    "addr:housenumber":"378",
    "addr:postcode":"5034",
    "addr:street":"Goodwood Rd",
    "iso:country":"AU",
    "sg:address":"378 Goodwood Rd",
    "sg:city":"Goodwood",
    "sg:classifiers":[
        {
            "category":"Personal",
            "subcategory":"Massage",
            "type":"Services"
        }
    ],
    "sg:phone":"+61 8 8373 3896",
    "sg:postcode":"5034",
    "sg:province":"SA",
    "sg:tags":[
        "therapy"
    ],
    "wof:name":"Massage Concepts",
    "wof:placetype":"venue"
},
  "geometry": {"coordinates":[138.58970642099999,-34.952091217],"type":"Point"}
}