{
  "type": "Feature",
  "properties": {
    "addr:full":"72- 74 Brushy Park Rd Wonga Park VIC 3115",
    "addr:housenumber":"74",
    "addr:postcode":"3115",
    "addr:street":"Brushy Park Rd",
    "iso:country":"AU",
    "sg:address":"72- 74 Brushy Park Rd",
    "sg:city":"Wonga Park",
    "sg:classifiers":[
        {
            "category":"Farming",
            "subcategory":"Livestock Farm",
            "type":"Manufacturing & Wholesale Goods"
        }
    ],
    "sg:phone":"+61 3 9722 2248",
    "sg:postcode":"3115",
    "sg:province":"VIC",
    "sg:tags":[
        "agistment"
    ],
    "wof:name":"Creekford Agistment",
    "wof:placetype":"venue"
},
  "geometry": {"coordinates":[145.28221130399999,-37.74061203],"type":"Point"}
}