{
  "type": "Feature",
  "properties": {
    "iso:country":"AU",
    "sg:address":"Suite 1/ 15 Lascelles St",
    "sg:city":"Brighton",
    "sg:classifiers":[
        {
            "category":"Professional",
            "subcategory":"Accounting & Tax Preparation",
            "type":"Services"
        }
    ],
    "sg:phone":"+61 7 3269 0099",
    "sg:postcode":"4017",
    "sg:province":"QLD",
    "sg:tags":[
        "accountant",
        "auditor"
    ],
    "wof:name":"Maggs R J",
    "wof:placetype":"venue"
},
  "geometry": {"coordinates":[153.05062866200001,-27.2946166992],"type":"Point"}
}