{
  "type": "Feature",
  "properties": {
    "addr:full":"19 Flinders St Wollongong NSW 2500",
    "addr:housenumber":"19",
    "addr:postcode":"2500",
    "addr:street":"Flinders St",
    "iso:country":"AU",
    "sg:address":"19 Flinders St",
    "sg:city":"Wollongong",
    "sg:classifiers":[
        {
            "category":"Education",
            "subcategory":"University",
            "type":"Public Place"
        }
    ],
    "sg:phone":"+61 2 4229 1980",
    "sg:postcode":"2500",
    "sg:province":"NSW",
    "sg:tags":[
        "college",
        "tertiary"
    ],
    "wof:name":"Richard Johnson College",
    "wof:placetype":"venue"
},
  "geometry": {"coordinates":[150.89297500000001,-34.415424],"type":"Point"}
}