{
  "type": "Feature",
  "properties": {
    "addr:full":"48 Ball St St Marys NSW 2760",
    "addr:housenumber":"48",
    "addr:postcode":"2760",
    "addr:street":"Ball St",
    "iso:country":"AU",
    "sg:address":"48 Ball St",
    "sg:city":"St Marys",
    "sg:classifiers":[
        {
            "category":"Retail",
            "subcategory":"Auto Repair",
            "type":"Services"
        }
    ],
    "sg:phone":"+61 2 9623 8826",
    "sg:postcode":"2760",
    "sg:province":"NSW",
    "sg:tags":[
        "engine",
        "reconditioning"
    ],
    "wof:name":"JTS Performance Heads",
    "wof:placetype":"venue"
},
  "geometry": {"coordinates":[150.78910827600001,-33.7747383118],"type":"Point"}
}