{
  "type": "Feature",
  "properties": {
    "iso:country":"AU",
    "sg:address":"157 Elizabeth St",
    "sg:city":"Brisbane",
    "sg:classifiers":[
        {
            "category":"Restaurant",
            "type":"Food & Drink"
        }
    ],
    "sg:phone":"+61 7 3229 9033",
    "sg:postcode":"4000",
    "sg:province":"QLD",
    "wof:name":"Davids Restaurant",
    "wof:placetype":"venue"
},
  "geometry": {"coordinates":[153.026687622,-27.4700317383],"type":"Point"}
}