{
  "type": "Feature",
  "properties": {
    "iso:country":"AU",
    "sg:address":"38 North St",
    "sg:city":"Narrabeen",
    "sg:classifiers":[
        {
            "category":"Utilities",
            "subcategory":"Sewage",
            "type":"Services"
        }
    ],
    "sg:phone":"+61 2 9982 2358",
    "sg:postcode":"2101",
    "sg:province":"NSW",
    "sg:tags":[
        "arboriculturist"
    ],
    "wof:name":"A Golden Apple",
    "wof:placetype":"venue"
},
  "geometry": {"coordinates":[151.21998600000001,-33.717766],"type":"Point"}
}