{
  "type": "Feature",
  "properties": {
    "addr:full":"5 Horne St Port Kembla NSW 2505",
    "addr:housenumber":"5",
    "addr:postcode":"2505",
    "addr:street":"Horne St",
    "iso:country":"AU",
    "sg:address":"5 Horne St",
    "sg:city":"Port Kembla",
    "sg:classifiers":[
        {
            "category":"Freight",
            "type":"Transportation"
        }
    ],
    "sg:phone":"+61 13 15 31",
    "sg:postcode":"2505",
    "sg:province":"NSW",
    "sg:tags":[
        "light",
        "carrier"
    ],
    "wof:name":"Wards Skyroad",
    "wof:placetype":"venue"
},
  "geometry": {"coordinates":[150.89782700000001,-34.479683],"type":"Point"}
}