{
  "type": "Feature",
  "properties": {
    "addr:full":"PO Box 37 West Beach SA 5024",
    "addr:postcode":"5024",
    "iso:country":"AU",
    "sg:address":"PO Box 37",
    "sg:city":"West Beach",
    "sg:classifiers":[
        {
            "category":"Banks & Credit Unions",
            "subcategory":"Financial Services",
            "type":"Services"
        }
    ],
    "sg:phone":"+61 8 8355 5375",
    "sg:postcode":"5024",
    "sg:province":"SA",
    "sg:tags":[
        "franchising"
    ],
    "wof:name":"Franchise Alliance",
    "wof:placetype":"venue"
},
  "geometry": {"coordinates":[138.50054931599999,-34.9379615784],"type":"Point"}
}