{
  "type": "Feature",
  "properties": {
    "iso:country":"AU",
    "sg:address":"Shop 2 172 Merrylands Rd",
    "sg:city":"Merrylands",
    "sg:classifiers":[
        {
            "category":"Health Services",
            "subcategory":"Doctor",
            "type":"Services"
        }
    ],
    "sg:phone":"+61 2 9897 2997",
    "sg:postcode":"2160",
    "sg:province":"NSW",
    "sg:tags":[
        "medical",
        "practitioner"
    ],
    "wof:name":"Goh Tin Kay",
    "wof:placetype":"venue"
},
  "geometry": {"coordinates":[150.98997497600001,-33.836643219],"type":"Point"}
}