{
  "type": "Feature",
  "properties": {
    "iso:country":"AU",
    "sg:address":"5th Flr, 447 Kent St",
    "sg:city":"Sydney",
    "sg:classifiers":[
        {
            "category":"Real Estate",
            "subcategory":"Surveying",
            "type":"Services"
        }
    ],
    "sg:phone":"+61 2 9283 6677",
    "sg:postcode":"2000",
    "sg:province":"NSW",
    "sg:tags":[
        "surveyor",
        "land"
    ],
    "wof:name":"Dunlop Thorpe & Co Pty Ltd",
    "wof:placetype":"venue"
},
  "geometry": {"coordinates":[151.20492553700001,-33.8723449707],"type":"Point"}
}