{
  "type": "Feature",
  "properties": {
    "addr:full":"Old Bush Rd Engadine NSW 2233",
    "addr:postcode":"2233",
    "addr:street":"Bush Rd",
    "iso:country":"AU",
    "sg:address":"Old Bush Rd",
    "sg:city":"Engadine",
    "sg:classifiers":[
        {
            "category":"Education",
            "subcategory":"School",
            "type":"Public Place"
        }
    ],
    "sg:phone":"+61 2 9520 0792",
    "sg:postcode":"2233",
    "sg:province":"NSW",
    "sg:tags":[
        "state",
        "-",
        "nsw"
    ],
    "wof:name":"Yarrawarrah Public School",
    "wof:placetype":"venue"
},
  "geometry": {"coordinates":[151.02760314899999,-34.0581130981],"type":"Point"}
}