{
  "type": "Feature",
  "properties": {
    "addr:full":"82 Goderich St Launceston TAS 7900",
    "addr:housenumber":"82",
    "addr:postcode":"7900",
    "addr:street":"Goderich St",
    "iso:country":"AU",
    "sg:address":"82 Goderich St",
    "sg:city":"Launceston",
    "sg:classifiers":[
        {
            "category":"Banks & Credit Unions",
            "subcategory":"Investment Brokerage",
            "type":"Services"
        }
    ],
    "sg:phone":"+61 439 597 176",
    "sg:postcode":"7900",
    "sg:province":"TAS",
    "sg:tags":[
        "shutter",
        "louvre"
    ],
    "wof:name":"Designer Window Fashions",
    "wof:placetype":"venue"
},
  "geometry": {"coordinates":[147.130981445,-41.4244270325],"type":"Point"}
}