{
  "type": "Feature",
  "properties": {
    "addr:full":"Shp 3/ 19 Yulong Ave Terrey Hills NSW 2084",
    "addr:housenumber":"/ 19",
    "addr:postcode":"2084",
    "addr:street":"Yulong Ave",
    "iso:country":"AU",
    "sg:address":"Shp 3/ 19 Yulong Ave",
    "sg:city":"Terrey Hills",
    "sg:classifiers":[
        {
            "category":"Deli",
            "type":"Food & Drink"
        }
    ],
    "sg:phone":"+61 2 9986 2206",
    "sg:postcode":"2084",
    "sg:province":"NSW",
    "sg:tags":[
        "delicatessen"
    ],
    "wof:name":"Delisshhh Pty Ltd",
    "wof:placetype":"venue"
},
  "geometry": {"coordinates":[151.227905273,-33.6827278137],"type":"Point"}
}