{
  "type": "Feature",
  "properties": {
    "iso:country":"AU",
    "sg:address":"Clifton Rd",
    "sg:city":"Brunswick Junction",
    "sg:classifiers":[
        {
            "category":"Farming",
            "subcategory":"Farm",
            "type":"Manufacturing & Wholesale Goods"
        }
    ],
    "sg:phone":"+61 8 9726 1068",
    "sg:postcode":"6224",
    "sg:province":"WA",
    "sg:tags":[
        "farmer"
    ],
    "wof:name":"Mitting SA & MJ, VA & KF",
    "wof:placetype":"venue"
},
  "geometry": {"coordinates":[115.838158,-33.251869],"type":"Point"}
}