{
  "type": "Feature",
  "properties": {
    "addr:full":"124 Old South Head Rd Vaucluse NSW 2030",
    "addr:housenumber":"124",
    "addr:postcode":"2030",
    "addr:street":"Old South Head Rd",
    "iso:country":"AU",
    "sg:address":"124 Old South Head Rd",
    "sg:city":"Vaucluse",
    "sg:classifiers":[
        {
            "category":"Health Services",
            "subcategory":"Health Practitioner",
            "type":"Services"
        }
    ],
    "sg:phone":"+61 2 9388 8125",
    "sg:postcode":"2030",
    "sg:province":"NSW",
    "sg:tags":[
        "alternative"
    ],
    "wof:name":"Well Healed Yoga & Natural Therapies",
    "wof:placetype":"venue"
},
  "geometry": {"coordinates":[151.28123474099999,-33.8578834534],"type":"Point"}
}