{
  "type": "Feature",
  "properties": {
    "addr:full":"Level 2, 460 Church St North Parramatta NSW 2151",
    "addr:housenumber":"460",
    "addr:postcode":"2151",
    "addr:street":"Church St",
    "iso:country":"AU",
    "sg:address":"Level 2, 460 Church St",
    "sg:city":"North Parramatta",
    "sg:classifiers":[
        {
            "category":"Wholesale",
            "subcategory":"Auto Parts",
            "type":"Manufacturing & Wholesale Goods"
        }
    ],
    "sg:phone":"+61 2 8836 3000",
    "sg:postcode":"2151",
    "sg:province":"NSW",
    "sg:tags":[
        "tyre"
    ],
    "wof:name":"Tyre Marketers",
    "wof:placetype":"venue"
},
  "geometry": {"coordinates":[151.00601196299999,-33.8055000305],"type":"Point"}
}