{
  "type": "Feature",
  "properties": {
    "iso:country":"AU",
    "sg:address":"Shop 3/ 85 Prospect Rd",
    "sg:city":"Prospect",
    "sg:classifiers":[
        {
            "category":"Food & Beverages",
            "subcategory":"Bakery",
            "type":"Retail Goods"
        }
    ],
    "sg:phone":"+61 8 8344 9643",
    "sg:postcode":"5082",
    "sg:province":"SA",
    "sg:tags":[
        "baker"
    ],
    "wof:name":"Hot Cross Bakery",
    "wof:placetype":"venue"
},
  "geometry": {"coordinates":[138.59425354000001,-34.8879241943],"type":"Point"}
}