{
  "type": "Feature",
  "properties": {
    "addr:full":"Boathouse Rd Kew VIC 3101",
    "addr:postcode":"3101",
    "addr:street":"Boathouse Rd",
    "iso:country":"AU",
    "sg:address":"Boathouse Rd",
    "sg:city":"Kew",
    "sg:classifiers":[
        {
            "category":"Restaurant",
            "type":"Food & Drink"
        }
    ],
    "sg:phone":"+61 3 9853 1828",
    "sg:postcode":"3101",
    "sg:province":"VIC",
    "wof:name":"Beate's Restaurant At Studley Park Boathouse",
    "wof:placetype":"venue"
},
  "geometry": {"coordinates":[145.011062622,-37.8009185791],"type":"Point"}
}