{
  "type": "Feature",
  "properties": {
    "addr:full":"38 Denistone Rd Eastwood NSW 2122",
    "addr:housenumber":"38",
    "addr:postcode":"2122",
    "addr:street":"Denistone Rd",
    "iso:country":"AU",
    "sg:address":"38 Denistone Rd",
    "sg:city":"Eastwood",
    "sg:classifiers":[
        {
            "category":"Health Services",
            "subcategory":"Health Practitioner",
            "type":"Services"
        }
    ],
    "sg:phone":"+61 2 9874 1153",
    "sg:postcode":"2122",
    "sg:province":"NSW",
    "sg:tags":[
        "hypnotherapy"
    ],
    "wof:name":"N.S.W. School Of Hypnotic Sciences The",
    "wof:placetype":"venue"
},
  "geometry": {"coordinates":[151.09010314899999,-33.7944564819],"type":"Point"}
}