{
  "type": "Feature",
  "properties": {
    "addr:full":"Narla Rd Belmont North NSW 2280",
    "addr:postcode":"2280",
    "addr:street":"Narla Rd",
    "iso:country":"AU",
    "sg:address":"Narla Rd",
    "sg:city":"Belmont North",
    "sg:classifiers":[
        {
            "category":"Arts & Performance",
            "subcategory":"Dance",
            "type":"Entertainment"
        }
    ],
    "sg:phone":"+61 408 671 177",
    "sg:postcode":"2280",
    "sg:province":"NSW",
    "sg:tags":[
        "theatrical",
        "ballet",
        "tuition"
    ],
    "wof:name":"Imagine Dance Studios",
    "wof:placetype":"venue"
},
  "geometry": {"coordinates":[151.660354614,-33.0234222412],"type":"Point"}
}