{
  "type": "Feature",
  "properties": {
    "iso:country":"AU",
    "sg:address":"34 Railway Rd South",
    "sg:city":"Mulgrave",
    "sg:classifiers":[
        {
            "category":"Manufacturing",
            "subcategory":"Tools & Machinery",
            "type":"Manufacturing & Wholesale Goods"
        }
    ],
    "sg:phone":"+61 2 4577 7716",
    "sg:postcode":"2756",
    "sg:province":"NSW",
    "sg:tags":[
        "toolmaker"
    ],
    "wof:name":"GT Tooling",
    "wof:placetype":"venue"
},
  "geometry": {"coordinates":[150.83328247099999,-33.628238678],"type":"Point"}
}