{
  "type": "Feature",
  "properties": {
    "iso:country":"AU",
    "sg:address":"Cnr Tedder Ave",
    "sg:city":"& Breaker Main Beach",
    "sg:classifiers":[
        {
            "category":"Health Services",
            "subcategory":"Health Practitioner",
            "type":"Services"
        }
    ],
    "sg:phone":"+61 7 5532 0999",
    "sg:postcode":"4217",
    "sg:province":"QLD",
    "sg:tags":[
        "physiotherapist"
    ],
    "wof:name":"Main Beach Physiotherapy",
    "wof:placetype":"venue"
},
  "geometry": {"coordinates":[153.424285889,-27.9819030762],"type":"Point"}
}