{
  "type": "Feature",
  "properties": {
    "addr:full":"37 Sowden Drv Samson WA 6163",
    "addr:housenumber":"37",
    "addr:postcode":"6163",
    "addr:street":"Sowden Drv",
    "iso:country":"AU",
    "sg:address":"37 Sowden Drv",
    "sg:city":"Samson",
    "sg:classifiers":[
        {
            "category":"Professional",
            "subcategory":"Art Services",
            "type":"Services"
        }
    ],
    "sg:phone":"+61 414 914 135",
    "sg:postcode":"6163",
    "sg:province":"WA",
    "sg:tags":[
        "decorator",
        "painter"
    ],
    "wof:name":"Koch Painters",
    "wof:placetype":"venue"
},
  "geometry": {"coordinates":[115.794319,-32.067905],"type":"Point"}
}