{
  "type": "Feature",
  "properties": {
    "iso:country":"AU",
    "sg:address":"56 Bay Tce",
    "sg:city":"Wynnum",
    "sg:classifiers":[
        {
            "category":"Government",
            "subcategory":"City Hall",
            "type":"Public Place"
        }
    ],
    "sg:phone":"+61 7 3403 4233",
    "sg:postcode":"4178",
    "sg:province":"QLD",
    "wof:name":"Wynnum Hall",
    "wof:placetype":"venue"
},
  "geometry": {"coordinates":[153.17730712900001,-27.4468307495],"type":"Point"}
}