{
  "type": "Feature",
  "properties": {
    "addr:full":"PO Box 582 Wynnum QLD 4178",
    "addr:postcode":"4178",
    "iso:country":"AU",
    "sg:address":"PO Box 582",
    "sg:city":"Wynnum",
    "sg:classifiers":[
        {
            "category":"Personal",
            "subcategory":"Beauty Salon",
            "type":"Services"
        }
    ],
    "sg:phone":"+61 409 632 695",
    "sg:postcode":"4178",
    "sg:province":"QLD",
    "sg:tags":[
        "hairdresser"
    ],
    "wof:name":"Location Hair Stylists",
    "wof:placetype":"venue"
},
  "geometry": {"coordinates":[153.17198181099999,-27.44190979],"type":"Point"}
}