{
  "type": "Feature",
  "properties": {
    "addr:full":"PO Box 89 Edwardstown SA 5039",
    "addr:postcode":"5039",
    "iso:country":"AU",
    "sg:address":"PO Box 89",
    "sg:city":"Edwardstown",
    "sg:classifiers":[
        {
            "category":"Government",
            "subcategory":"Department Of Motor Vehicles",
            "type":"Public Place"
        }
    ],
    "sg:phone":"+61 439 034 797",
    "sg:postcode":"5039",
    "sg:province":"SA",
    "sg:tags":[
        "tank",
        "cleaning"
    ],
    "wof:name":"Yates Rainwater Systems",
    "wof:placetype":"venue"
},
  "geometry": {"coordinates":[138.572540283,-34.9700393677],"type":"Point"}
}