{
  "type": "Feature",
  "properties": {
    "addr:full":"156 Woodgrove Rd Hall ACT 2618",
    "addr:housenumber":"156",
    "addr:postcode":"2618",
    "addr:street":"Woodgrove Rd",
    "iso:country":"AU",
    "sg:address":"156 Woodgrove Rd",
    "sg:city":"Hall",
    "sg:classifiers":[
        {
            "category":"Farming",
            "subcategory":"Vineyard",
            "type":"Manufacturing & Wholesale Goods"
        }
    ],
    "sg:phone":"+61 2 6230 2023",
    "sg:postcode":"2618",
    "sg:province":"ACT",
    "sg:tags":[
        "winery"
    ],
    "wof:name":"Brindabella Hills Winery",
    "wof:placetype":"venue"
},
  "geometry": {"coordinates":[148.97291564899999,-35.1674423218],"type":"Point"}
}