{
  "type": "Feature",
  "properties": {
    "addr:full":"10 Salisbury Ave Mont Albert VIC 3127",
    "addr:housenumber":"10",
    "addr:postcode":"3127",
    "addr:street":"Salisbury Ave",
    "iso:country":"AU",
    "sg:address":"10 Salisbury Ave",
    "sg:city":"Mont Albert",
    "sg:classifiers":[
        {
            "category":"Organizations",
            "subcategory":"Professional Association",
            "type":"Services"
        }
    ],
    "sg:phone":"+61 3 9018 9188",
    "sg:postcode":"3127",
    "sg:province":"VIC",
    "sg:tags":[
        "web",
        "internet"
    ],
    "wof:name":"Hotshot",
    "wof:placetype":"venue"
},
  "geometry": {"coordinates":[145.10757446299999,-37.8204917908],"type":"Point"}
}