{
  "type": "Feature",
  "properties": {
    "addr:full":"Cnr Bargo River Rd & Remembrance Drv Tahmoor NSW 2573",
    "addr:postcode":"2573",
    "addr:street":"Cnr Bargo River Rd & Remembrance Drv",
    "iso:country":"AU",
    "sg:address":"Cnr Bargo River Rd & Remembrance Drv",
    "sg:city":"Tahmoor",
    "sg:classifiers":[
        {
            "category":"Manufacturing",
            "subcategory":"Motor Vehicles & Parts",
            "type":"Manufacturing & Wholesale Goods"
        }
    ],
    "sg:phone":"+61 2 4683 2519",
    "sg:postcode":"2573",
    "sg:province":"NSW",
    "sg:tags":[
        "replacement"
    ],
    "wof:name":"Tahmoor Parts & Panels",
    "wof:placetype":"venue"
},
  "geometry": {"coordinates":[150.580474853,-34.2347488403],"type":"Point"}
}