{
  "type": "Feature",
  "properties": {
    "addr:full":"18 Hayward Ave Torrensville SA 5031",
    "addr:housenumber":"18",
    "addr:postcode":"5031",
    "addr:street":"Hayward Ave",
    "iso:country":"AU",
    "sg:address":"18 Hayward Ave",
    "sg:city":"Torrensville",
    "sg:classifiers":[
        {
            "category":"Professional",
            "subcategory":"Art Services",
            "type":"Services"
        }
    ],
    "sg:phone":"+61 418 622 213",
    "sg:postcode":"5031",
    "sg:province":"SA",
    "sg:tags":[
        "decorator",
        "painter"
    ],
    "wof:name":"Karassoulos John",
    "wof:placetype":"venue"
},
  "geometry": {"coordinates":[138.55761718799999,-34.921787262],"type":"Point"}
}