{
  "type": "Feature",
  "properties": {
    "addr:full":"53 Miller St Gilgandra NSW 2827",
    "addr:housenumber":"53",
    "addr:postcode":"2827",
    "addr:street":"Miller St",
    "iso:country":"AU",
    "sg:address":"53 Miller St",
    "sg:city":"Gilgandra",
    "sg:classifiers":[
        {
            "category":"Insurance",
            "subcategory":"Hazard Insurance",
            "type":"Services"
        }
    ],
    "sg:phone":"+61 2 6847 2288",
    "sg:postcode":"2827",
    "sg:province":"NSW",
    "sg:tags":[
        "fire",
        "accident",
        "marine"
    ],
    "wof:name":"Gilgandra Insurance Services",
    "wof:placetype":"venue"
},
  "geometry": {"coordinates":[148.66531372099999,-31.7130699158],"type":"Point"}
}