{
  "type": "Feature",
  "properties": {
    "addr:full":"9 Bellairs Ave Seddon VIC 3011",
    "addr:housenumber":"9",
    "addr:postcode":"3011",
    "addr:street":"Bellairs Ave",
    "iso:country":"AU",
    "sg:address":"9 Bellairs Ave",
    "sg:city":"Seddon",
    "sg:classifiers":[
        {
            "category":"Building & Trades",
            "subcategory":"Construction",
            "type":"Services"
        }
    ],
    "sg:phone":"+61 3 9689 2211",
    "sg:postcode":"3011",
    "sg:province":"VIC",
    "sg:tags":[
        "management"
    ],
    "wof:name":"Redesign Developments",
    "wof:placetype":"venue"
},
  "geometry": {"coordinates":[144.895385742,-37.8097953796],"type":"Point"}
}