{
  "type": "Feature",
  "properties": {
    "addr:full":"282 Ashburton Ave Paraburdoo WA 6754",
    "addr:housenumber":"282",
    "addr:postcode":"6754",
    "addr:street":"Ashburton Ave",
    "iso:country":"AU",
    "sg:address":"282 Ashburton Ave",
    "sg:city":"Paraburdoo",
    "sg:classifiers":[
        {
            "category":"Social Services",
            "subcategory":"Child Care",
            "type":"Services"
        }
    ],
    "sg:phone":"+61 8 9189 5243",
    "sg:postcode":"6754",
    "sg:province":"WA",
    "wof:name":"Child Day Care Centre Paraburdoo",
    "wof:placetype":"venue"
},
  "geometry": {"coordinates":[117.67523956300001,-23.2005729675],"type":"Point"}
}