{
  "type": "Feature",
  "properties": {
    "addr:full":"4 Albert St Cardwell QLD 4849",
    "addr:housenumber":"4",
    "addr:postcode":"4849",
    "addr:street":"Albert St",
    "iso:country":"AU",
    "sg:address":"4 Albert St",
    "sg:city":"Cardwell",
    "sg:classifiers":[
        {
            "category":"Food & Beverages",
            "subcategory":"Meat & Fish",
            "type":"Retail Goods"
        }
    ],
    "sg:phone":"+61 7 4066 2077",
    "sg:postcode":"4849",
    "sg:province":"QLD",
    "sg:tags":[
        "aquaculture"
    ],
    "wof:name":"Blue Water Barramundi",
    "wof:placetype":"venue"
},
  "geometry": {"coordinates":[146.014938,-18.250635],"type":"Point"}
}