{
  "type": "Feature",
  "properties": {
    "addr:full":"16 Milford St Kilsyth VIC 3137",
    "addr:housenumber":"16",
    "addr:postcode":"3137",
    "addr:street":"Milford St",
    "iso:country":"AU",
    "sg:address":"16 Milford St",
    "sg:city":"Kilsyth",
    "sg:classifiers":[
        {
            "category":"Communications",
            "type":"Services"
        }
    ],
    "sg:phone":"+61 3 9728 6081",
    "sg:postcode":"3137",
    "sg:province":"VIC",
    "sg:tags":[
        "equipment",
        "satellite"
    ],
    "wof:name":"Elder Rod",
    "wof:placetype":"venue"
},
  "geometry": {"coordinates":[145.32640075699999,-37.8034439087],"type":"Point"}
}