{
  "type": "Feature",
  "properties": {
    "addr:full":"368 Sussex St Sydney NSW 2000",
    "addr:housenumber":"368",
    "addr:postcode":"2000",
    "addr:street":"Sussex St",
    "iso:country":"AU",
    "sg:address":"368 Sussex St",
    "sg:city":"Sydney",
    "sg:classifiers":[
        {
            "category":"Personal",
            "type":"Services"
        }
    ],
    "sg:phone":"+61 2 9262 9189",
    "sg:postcode":"2000",
    "sg:province":"NSW",
    "sg:tags":[
        "introduction",
        "social"
    ],
    "wof:name":"Sydney International Introduction Agency",
    "wof:placetype":"venue"
},
  "geometry": {"coordinates":[151.20469665499999,-33.8762512207],"type":"Point"}
}