{
  "type": "Feature",
  "properties": {
    "addr:full":"Shop 6, 1 Clarke St Earlwood NSW 2206",
    "addr:housenumber":"shop;1",
    "addr:postcode":"2206",
    "addr:street":"Clarke St",
    "iso:country":"AU",
    "sg:address":"Shop 6, 1 Clarke St",
    "sg:city":"Earlwood",
    "sg:classifiers":[
        {
            "category":"Fast Food",
            "type":"Food & Drink"
        }
    ],
    "sg:phone":"+61 2 9481 1111",
    "sg:postcode":"2206",
    "sg:province":"NSW",
    "sg:tags":[
        "away",
        "take"
    ],
    "wof:name":"Pizza Hut",
    "wof:placetype":"venue"
},
  "geometry": {"coordinates":[151.12510700000001,-33.926262],"type":"Point"}
}