{
  "type": "Feature",
  "properties": {
    "addr:full":"Unit 2 643 Dundas Rd Forrestfield WA 6058",
    "addr:housenumber":"643",
    "addr:postcode":"6058",
    "addr:street":"Dundas Rd",
    "iso:country":"AU",
    "sg:address":"Unit 2 643 Dundas Rd",
    "sg:city":"Forrestfield",
    "sg:classifiers":[
        {
            "category":"Shopping",
            "subcategory":"Stationery & Office Supplies",
            "type":"Retail Goods"
        }
    ],
    "sg:phone":"+61 1300 479 727",
    "sg:postcode":"6058",
    "sg:province":"WA",
    "sg:tags":[
        "packaging",
        "material"
    ],
    "wof:name":"Integrated Packaging",
    "wof:placetype":"venue"
},
  "geometry": {"coordinates":[115.984558105,-31.9804420471],"type":"Point"}
}