{
  "type": "Feature",
  "properties": {
    "addr:full":"Level 5 470 St Kilda Rd Melbourne VIC 3001",
    "addr:housenumber":"470",
    "addr:postcode":"3001",
    "addr:street":"St Kilda Rd",
    "iso:country":"AU",
    "sg:address":"Level 5 470 St Kilda Rd",
    "sg:city":"Melbourne",
    "sg:classifiers":[
        {
            "category":"Organizations",
            "subcategory":"Professional Association",
            "type":"Services"
        }
    ],
    "sg:phone":"+61 3 9867 6599",
    "sg:postcode":"3001",
    "sg:province":"VIC",
    "sg:tags":[
        "web",
        "internet"
    ],
    "wof:name":"Purpose Group",
    "wof:placetype":"venue"
},
  "geometry": {"coordinates":[144.97691345199999,-37.8409957886],"type":"Point"}
}