{
  "type": "Feature",
  "properties": {
    "iso:country":"AU",
    "sg:address":"360 Burnley St",
    "sg:city":"Richmond",
    "sg:classifiers":[
        {
            "category":"Building & Trades",
            "subcategory":"Landscaping Services",
            "type":"Services"
        }
    ],
    "sg:phone":"+61 1300 635 776",
    "sg:postcode":"3121",
    "sg:province":"VIC",
    "sg:tags":[
        "designer",
        "landscape",
        "contractor"
    ],
    "wof:name":"Melbourne Courtyards",
    "wof:placetype":"venue"
},
  "geometry": {"coordinates":[145.007080078,-37.8252105713],"type":"Point"}
}