{
  "type": "Feature",
  "properties": {
    "addr:full":"44 Nurrawallee St Ulladulla NSW 2539",
    "addr:housenumber":"44",
    "addr:postcode":"2539",
    "addr:street":"Nurrawallee St",
    "iso:country":"AU",
    "sg:address":"44 Nurrawallee St",
    "sg:city":"Ulladulla",
    "sg:classifiers":[
        {
            "category":"Professional",
            "type":"Services"
        }
    ],
    "sg:phone":"+61 2 4455 2206",
    "sg:postcode":"2539",
    "sg:province":"NSW",
    "sg:tags":[
        "transport"
    ],
    "wof:name":"Austin Transport Co Pty Ltd",
    "wof:placetype":"venue"
},
  "geometry": {"coordinates":[150.47601318400001,-35.3501014709],"type":"Point"}
}