{
  "type": "Feature",
  "properties": {
    "addr:full":"243/ 1 Serisier Ave Main Beach QLD 4217",
    "addr:housenumber":"243 / 1",
    "addr:postcode":"4217",
    "addr:street":"Serisier Ave",
    "iso:country":"AU",
    "sg:address":"243/ 1 Serisier Ave",
    "sg:city":"Main Beach",
    "sg:classifiers":[
        {
            "category":"Professional",
            "type":"Services"
        }
    ],
    "sg:phone":"+61 7 5503 1822",
    "sg:postcode":"4217",
    "sg:province":"QLD",
    "sg:tags":[
        "quality",
        "assurance"
    ],
    "wof:name":"International Certifications Australia Pty Ltd",
    "wof:placetype":"venue"
},
  "geometry": {"coordinates":[153.42689514200001,-27.982011795],"type":"Point"}
}