{
  "type": "Feature",
  "properties": {
    "iso:country":"AU",
    "sg:address":"180 Bromley Rd",
    "sg:city":"Robinvale",
    "sg:classifiers":[
        {
            "category":"Utilities",
            "type":"Services"
        }
    ],
    "sg:phone":"+61 3 5026 3106",
    "sg:postcode":"3549",
    "sg:province":"VIC",
    "sg:tags":[
        "refrigeration",
        "industrial",
        "commercial",
        "retail"
    ],
    "wof:name":"Macair Refrigeration & Air Conditioning Pty Ltd",
    "wof:placetype":"venue"
},
  "geometry": {"coordinates":[142.771286011,-34.5858421326],"type":"Point"}
}