{
  "type": "Feature",
  "properties": {
    "addr:full":"42 bennett Rd St Marys NSW 2760",
    "addr:housenumber":"42",
    "addr:postcode":"2760",
    "addr:street":"Bennett Rd",
    "iso:country":"AU",
    "sg:address":"42 bennett Rd",
    "sg:city":"St Marys",
    "sg:classifiers":[
        {
            "category":"Retail",
            "subcategory":"Auto Repair",
            "type":"Services"
        }
    ],
    "sg:phone":"+61 2 8807 8363",
    "sg:postcode":"2760",
    "sg:province":"NSW",
    "sg:tags":[
        "repairer",
        "motor",
        "engineer"
    ],
    "wof:name":"Mr Tune Mobile Mechanic",
    "wof:placetype":"venue"
},
  "geometry": {"coordinates":[150.79318237300001,-33.7779006958],"type":"Point"}
}