{
  "type": "Feature",
  "properties": {
    "addr:full":"84 Cambridge St West Perth WA 6005",
    "addr:housenumber":"84",
    "addr:postcode":"6005",
    "addr:street":"Cambridge St",
    "iso:country":"AU",
    "sg:address":"84 Cambridge St",
    "sg:city":"West Perth",
    "sg:classifiers":[
        {
            "category":"Government",
            "subcategory":"City Hall",
            "type":"Public Place"
        }
    ],
    "sg:phone":"+61 8 9387 9100",
    "sg:postcode":"6005",
    "sg:province":"WA",
    "wof:name":"Leaderville Town Hall",
    "wof:placetype":"venue"
},
  "geometry": {"coordinates":[115.83647918699999,-31.9405517578],"type":"Point"}
}