{
  "type": "Feature",
  "properties": {
    "iso:country":"AU",
    "sg:address":"163 Bellarine Hwy",
    "sg:city":"Newcomb",
    "sg:classifiers":[
        {
            "category":"Education",
            "subcategory":"Special Training",
            "type":"Public Place"
        }
    ],
    "sg:phone":"+61 3 5248 3488",
    "sg:postcode":"3219",
    "sg:province":"VIC",
    "sg:tags":[
        "diving",
        "school",
        "scuba"
    ],
    "wof:name":"Henderson Dive Instruction",
    "wof:placetype":"venue"
},
  "geometry": {"coordinates":[144.403564453,-38.1736679077],"type":"Point"}
}