{
  "type": "Feature",
  "properties": {
    "addr:full":"Unit 2/ 5 Tiwi Gardens Rd Tiwi NT 0810",
    "addr:housenumber":"5",
    "addr:postcode":"nt 0810",
    "addr:street":"Tiwi Gardens Rd",
    "iso:country":"AU",
    "sg:address":"Unit 2/ 5 Tiwi Gardens Rd",
    "sg:city":"Tiwi",
    "sg:classifiers":[
        {
            "category":"Health Services",
            "subcategory":"Medical Lab",
            "type":"Services"
        }
    ],
    "sg:phone":"+61 8 8947 9333",
    "sg:postcode":"0810",
    "sg:province":"NT",
    "sg:tags":[
        "laboratory",
        "dental"
    ],
    "wof:name":"Hackney Dental Laboratory",
    "wof:placetype":"venue"
},
  "geometry": {"coordinates":[130.87356567399999,-12.3628587723],"type":"Point"}
}