{
  "type": "Feature",
  "properties": {
    "addr:full":"Shop 222, Westfield Eastgardens, Bunnerong Rd Eastgardens NSW 2036",
    "addr:housenumber":"222",
    "addr:postcode":"2036",
    "addr:street":"Westfield Eastgardens Bunnerong Rd",
    "iso:country":"AU",
    "sg:address":"Shop 222, Westfield Eastgardens, Bunnerong Rd",
    "sg:city":"Eastgardens",
    "sg:classifiers":[
        {
            "category":"Shopping",
            "subcategory":"Shoes",
            "type":"Retail Goods"
        }
    ],
    "sg:phone":"+61 2 9349 4069",
    "sg:postcode":"2036",
    "sg:province":"NSW",
    "sg:tags":[
        "footwear"
    ],
    "wof:name":"Payless Shoes Pty Limited",
    "wof:placetype":"venue"
},
  "geometry": {"coordinates":[151.22669982900001,-33.9444389343],"type":"Point"}
}