{
  "type": "Feature",
  "properties": {
    "addr:full":"281 Manns Rd Gosford West NSW 2250",
    "addr:housenumber":"281",
    "addr:postcode":"2250",
    "addr:street":"Manns Rd",
    "iso:country":"AU",
    "sg:address":"281 Manns Rd",
    "sg:city":"Gosford West",
    "sg:classifiers":[
        {
            "category":"Autos & Motor Vehicles",
            "subcategory":"Automobile Sales",
            "type":"Retail Goods"
        }
    ],
    "sg:phone":"+61 2 4322 2211",
    "sg:postcode":"2250",
    "sg:province":"NSW",
    "sg:tags":[
        "car",
        "used"
    ],
    "wof:name":"Asset Motors Pty Ltd",
    "wof:placetype":"venue"
},
  "geometry": {"coordinates":[151.31939697300001,-33.4244995117],"type":"Point"}
}