{
  "type": "Feature",
  "properties": {
    "addr:full":"Terrymont Rd Warrimoo NSW 2774",
    "addr:postcode":"2774",
    "addr:street":"Terrymont Rd",
    "iso:country":"AU",
    "sg:address":"Terrymont Rd",
    "sg:city":"Warrimoo",
    "sg:classifiers":[
        {
            "category":"Building & Trades",
            "subcategory":"Construction",
            "type":"Services"
        }
    ],
    "sg:phone":"+61 413 184 858",
    "sg:postcode":"2774",
    "sg:province":"NSW",
    "sg:tags":[
        "contractor"
    ],
    "wof:name":"Creative Carpentry Blue Mountains",
    "wof:placetype":"venue"
},
  "geometry": {"coordinates":[150.60171508799999,-33.7190933228],"type":"Point"}
}