{
  "type": "Feature",
  "properties": {
    "addr:full":"Level 3, 493 Little Bourke St Melbourne VIC 3000",
    "addr:housenumber":"493",
    "addr:postcode":"3000",
    "addr:street":"Little Bourke St",
    "iso:country":"AU",
    "sg:address":"Level 3, 493 Little Bourke St",
    "sg:city":"Melbourne",
    "sg:classifiers":[
        {
            "category":"Shopping",
            "subcategory":"Computers & Home Electronics",
            "type":"Retail Goods"
        }
    ],
    "sg:phone":"+61 1800 425 425",
    "sg:postcode":"3000",
    "sg:province":"VIC",
    "sg:tags":[
        "hardware",
        "equipment"
    ],
    "wof:name":"Hal Data Services Pty Limited",
    "wof:placetype":"venue"
},
  "geometry": {"coordinates":[144.95817565900001,-37.8147010803],"type":"Point"}
}