{
  "type": "Feature",
  "properties": {
    "addr:full":"PO Box 828 Joondalup WA 6027",
    "addr:postcode":"6027",
    "iso:country":"AU",
    "sg:address":"PO Box 828",
    "sg:city":"Joondalup",
    "sg:classifiers":[
        {
            "category":"Shopping",
            "subcategory":"Computers & Home Electronics",
            "type":"Retail Goods"
        }
    ],
    "sg:phone":"+61 8 9301 2722",
    "sg:postcode":"6027",
    "sg:province":"WA",
    "sg:tags":[
        "equipment",
        "supply"
    ],
    "wof:name":"S2M2 Pty Ltd",
    "wof:placetype":"venue"
},
  "geometry": {"coordinates":[115.759986877,-31.7324905396],"type":"Point"}
}