{
  "type": "Feature",
  "properties": {
    "addr:full":"PO Box 249 Annandale NSW 2038",
    "addr:postcode":"2038",
    "iso:country":"AU",
    "sg:address":"PO Box 249",
    "sg:city":"Annandale",
    "sg:classifiers":[
        {
            "category":"Professional",
            "subcategory":"Business Services",
            "type":"Services"
        }
    ],
    "sg:phone":"+61 2 9569 4843",
    "sg:postcode":"2038",
    "sg:province":"NSW",
    "sg:tags":[
        "consultant",
        "promoter",
        "entertainment"
    ],
    "wof:name":"Doyles Promotions Pty Ltd",
    "wof:placetype":"venue"
},
  "geometry": {"coordinates":[151.169723511,-33.8796691895],"type":"Point"}
}