{
  "type": "Feature",
  "properties": {
    "iso:country":"AU",
    "sg:address":"128 Main North Rd",
    "sg:city":"Prospect",
    "sg:classifiers":[
        {
            "category":"Wholesale",
            "subcategory":"Apparel",
            "type":"Manufacturing & Wholesale Goods"
        }
    ],
    "sg:phone":"+61 8 8269 2144",
    "sg:postcode":"5082",
    "sg:province":"SA",
    "sg:tags":[
        "wholesaler",
        "mfrs",
        "menswear"
    ],
    "wof:name":"Jem Designs Unisex",
    "wof:placetype":"venue"
},
  "geometry": {"coordinates":[138.60276794399999,-34.887752533],"type":"Point"}
}