{
  "type": "Feature",
  "properties": {
    "addr:full":"1212 Anzac Pde Malabar NSW 2036",
    "addr:housenumber":"1212",
    "addr:postcode":"2036",
    "addr:street":"Anzac Pde",
    "iso:country":"AU",
    "sg:address":"1212 Anzac Pde",
    "sg:city":"Malabar",
    "sg:classifiers":[
        {
            "category":"Health Services",
            "subcategory":"Doctor",
            "type":"Services"
        }
    ],
    "sg:phone":"+61 2 9661 9926",
    "sg:postcode":"2036",
    "sg:province":"NSW",
    "sg:tags":[
        "medical",
        "practitioner"
    ],
    "wof:name":"Leong S F",
    "wof:placetype":"venue"
},
  "geometry": {"coordinates":[151.24693298299999,-33.9620552063],"type":"Point"}
}