{
  "type": "Feature",
  "properties": {
    "addr:full":"471 Main St Mordialloc VIC 3195",
    "addr:housenumber":"471",
    "addr:postcode":"3195",
    "addr:street":"Main St",
    "iso:country":"AU",
    "sg:address":"471 Main St",
    "sg:city":"Mordialloc",
    "sg:classifiers":[
        {
            "category":"Fast Food",
            "type":"Food & Drink"
        }
    ],
    "sg:phone":"+61 3 9580 9407",
    "sg:postcode":"3195",
    "sg:province":"VIC",
    "sg:tags":[
        "away",
        "take"
    ],
    "wof:name":"White Rooster",
    "wof:placetype":"venue"
},
  "geometry": {"coordinates":[145.08625793499999,-38.0059432983],"type":"Point"}
}