{
  "type": "Feature",
  "properties": {
    "addr:full":"31 Old Pacific Hwy Yatala QLD 4207",
    "addr:housenumber":"31",
    "addr:postcode":"4207",
    "addr:street":"Old Pacific Hwy",
    "iso:country":"AU",
    "sg:address":"31 Old Pacific Hwy",
    "sg:city":"Yatala",
    "sg:classifiers":[
        {
            "category":"Retail",
            "subcategory":"Auto Repair",
            "type":"Services"
        }
    ],
    "sg:phone":"+61 7 3287 5882",
    "sg:postcode":"4207",
    "sg:province":"QLD",
    "sg:tags":[
        "electrical"
    ],
    "wof:name":"Yatala Auto & Marine Electrical Services",
    "wof:placetype":"venue"
},
  "geometry": {"coordinates":[153.22410583499999,-27.7333316803],"type":"Point"}
}