{
  "type": "Feature",
  "properties": {
    "addr:full":"23 Britton St Smithfield NSW 2164",
    "addr:housenumber":"23",
    "addr:postcode":"2164",
    "addr:street":"Britton St",
    "iso:country":"AU",
    "sg:address":"23 Britton St",
    "sg:city":"Smithfield",
    "sg:classifiers":[
        {
            "category":"Home & Garden",
            "subcategory":"Building Materials",
            "type":"Retail Goods"
        }
    ],
    "sg:phone":"+61 2 9616 7444",
    "sg:postcode":"2164",
    "sg:province":"NSW",
    "sg:tags":[
        "balustrading"
    ],
    "wof:name":"Laser Lace",
    "wof:placetype":"venue"
},
  "geometry": {"coordinates":[150.945755005,-33.8435745239],"type":"Point"}
}