{
  "type": "Feature",
  "properties": {
    "iso:country":"AU",
    "sg:address":"72 Morehead St",
    "sg:city":"Bungalow",
    "sg:classifiers":[
        {
            "category":"Building & Trades",
            "subcategory":"Construction",
            "type":"Services"
        }
    ],
    "sg:phone":"+61 7 4035 4615",
    "sg:postcode":"4870",
    "sg:province":"QLD",
    "sg:tags":[
        "stonework",
        "stone",
        "mason"
    ],
    "wof:name":"Trinity Monuments",
    "wof:placetype":"venue"
},
  "geometry": {"coordinates":[145.75946044899999,-16.9388332367],"type":"Point"}
}