{
  "type": "Feature",
  "properties": {
    "iso:country":"AU",
    "sg:address":"2/ 40 Biloela St",
    "sg:city":"Villawood",
    "sg:classifiers":[
        {
            "category":"Manufacturing",
            "subcategory":"Tools & Machinery",
            "type":"Manufacturing & Wholesale Goods"
        }
    ],
    "sg:phone":"+61 2 8707 2500",
    "sg:postcode":"2163",
    "sg:province":"NSW",
    "sg:tags":[
        "toolmaker"
    ],
    "wof:name":"Bishop Manufacturing Technology",
    "wof:placetype":"venue"
},
  "geometry": {"coordinates":[150.98840332,-33.8873138428],"type":"Point"}
}