{
  "type": "Feature",
  "properties": {
    "iso:country":"AU",
    "sg:address":"521 High St",
    "sg:city":"Penrith",
    "sg:classifiers":[
        {
            "category":"Building & Trades",
            "subcategory":"Equipment Rental",
            "type":"Services"
        }
    ],
    "sg:phone":"+61 2 4721 5677",
    "sg:postcode":"2750",
    "sg:province":"NSW",
    "sg:tags":[
        "party",
        "hire"
    ],
    "wof:name":"Spotlight Party Supplies (SPARTYS)",
    "wof:placetype":"venue"
},
  "geometry": {"coordinates":[150.91554260300001,-33.8950271606],"type":"Point"}
}