{
  "type": "Feature",
  "properties": {
    "iso:country":"AU",
    "sg:address":"2 Growden St",
    "sg:city":"Merredin",
    "sg:classifiers":[
        {
            "category":"Personal",
            "subcategory":"Beauty Salon",
            "type":"Services"
        }
    ],
    "sg:phone":"+61 8 9041 2583",
    "sg:postcode":"6415",
    "sg:province":"WA",
    "wof:name":"Cassina's Beauty Clinic",
    "wof:placetype":"venue"
},
  "geometry": {"coordinates":[118.273529053,-31.4773254395],"type":"Point"}
}