{
  "type": "Feature",
  "properties": {
    "iso:country":"AU",
    "sg:address":"Post Office Centre 94 Byrnes St",
    "sg:city":"Mareeba",
    "sg:classifiers":[
        {
            "category":"Health Services",
            "subcategory":"Medical Lab",
            "type":"Services"
        }
    ],
    "sg:phone":"+61 7 4092 3808",
    "sg:postcode":"4880",
    "sg:province":"QLD",
    "sg:tags":[
        "laboratory",
        "pathology"
    ],
    "wof:name":"Sullivan Nicolaides Pathology Laboratories",
    "wof:placetype":"venue"
},
  "geometry": {"coordinates":[145.422363281,-16.9937229156],"type":"Point"}
}