{
  "type": "Feature",
  "properties": {
    "addr:full":"14 Thesiger Crt Deakin ACT 2600",
    "addr:housenumber":"14",
    "addr:postcode":"2600",
    "addr:street":"Thesiger Crt",
    "iso:country":"AU",
    "sg:address":"14 Thesiger Crt",
    "sg:city":"Deakin",
    "sg:classifiers":[
        {
            "category":"Health Services",
            "subcategory":"Doctor",
            "type":"Services"
        }
    ],
    "sg:phone":"+61 2 6282 2399",
    "sg:postcode":"2600",
    "sg:province":"ACT",
    "sg:tags":[
        "occupational",
        "safety"
    ],
    "wof:name":"St John Ambulance Australia (ACT)",
    "wof:placetype":"venue"
},
  "geometry": {"coordinates":[149.09513855,-35.3176422119],"type":"Point"}
}