{
  "type": "Feature",
  "properties": {
    "iso:country":"AU",
    "sg:address":"11 Carisbrooke Ave",
    "sg:city":"Kotara",
    "sg:classifiers":[
        {
            "category":"Real Estate",
            "subcategory":"Real Estate Agent",
            "type":"Services"
        }
    ],
    "sg:phone":"+61 2 4952 8690",
    "sg:postcode":"2289",
    "sg:province":"NSW",
    "wof:name":"Peter Aloupis",
    "wof:placetype":"venue"
},
  "geometry": {"coordinates":[151.690582275,-32.9399986267],"type":"Point"}
}