{
  "type": "Feature",
  "properties": {
    "addr:full":"212 Albion St Brunswick VIC 3056",
    "addr:housenumber":"212",
    "addr:postcode":"3056",
    "addr:street":"Albion St",
    "iso:country":"AU",
    "sg:address":"212 Albion St",
    "sg:city":"Brunswick",
    "sg:classifiers":[
        {
            "category":"Farming",
            "subcategory":"Orchard",
            "type":"Manufacturing & Wholesale Goods"
        }
    ],
    "sg:phone":"+61 3 9384 1755",
    "sg:postcode":"3056",
    "sg:province":"VIC",
    "sg:tags":[
        "wholesaler",
        "jean",
        "mfrs"
    ],
    "wof:name":"My Jean Co Pty Ltd",
    "wof:placetype":"venue"
},
  "geometry": {"coordinates":[144.961395264,-37.7606964111],"type":"Point"}
}