{
  "type": "Feature",
  "properties": {
    "addr:full":"Shop 2 Lot 168 Phillip St Pottsville NSW 2489",
    "addr:housenumber":"shop 2 lot 168",
    "addr:postcode":"2489",
    "addr:street":"Phillip St",
    "iso:country":"AU",
    "sg:address":"Shop 2 Lot 168 Phillip St",
    "sg:city":"Pottsville",
    "sg:classifiers":[
        {
            "category":"Personal",
            "subcategory":"Beauty Salon",
            "type":"Services"
        }
    ],
    "sg:phone":"+61 2 6676 4465",
    "sg:postcode":"2489",
    "sg:province":"NSW",
    "sg:tags":[
        "hairdresser"
    ],
    "wof:name":"Revive Hair & Body",
    "wof:placetype":"venue"
},
  "geometry": {"coordinates":[153.564697266,-28.3901805878],"type":"Point"}
}