{
  "type": "Feature",
  "properties": {
    "addr:full":"Shp3/ 41 Robinson St Carnarvon WA 6701",
    "addr:housenumber":"41",
    "addr:postcode":"6701",
    "addr:street":"Robinson St",
    "iso:country":"AU",
    "sg:address":"Shp3/ 41 Robinson St",
    "sg:city":"Carnarvon",
    "sg:classifiers":[
        {
            "category":"Fast Food",
            "type":"Food & Drink"
        }
    ],
    "sg:phone":"+61 8 9941 1879",
    "sg:postcode":"6701",
    "sg:province":"WA",
    "sg:tags":[
        "away",
        "take"
    ],
    "wof:name":"Westcoast Fish & Chips",
    "wof:placetype":"venue"
},
  "geometry": {"coordinates":[113.65609741199999,-24.885225296],"type":"Point"}
}