{
  "type": "Feature",
  "properties": {
    "addr:full":"6 Marzan St Rural View Mackay QLD 4740",
    "addr:housenumber":"6",
    "addr:postcode":"4740",
    "addr:street":"Marzan St",
    "iso:country":"AU",
    "sg:address":"6 Marzan St",
    "sg:city":"Rural View Mackay",
    "sg:classifiers":[
        {
            "category":"Retail",
            "subcategory":"Storage",
            "type":"Services"
        }
    ],
    "sg:phone":"+61 7 4957 6266",
    "sg:postcode":"4740",
    "sg:province":"QLD",
    "sg:tags":[
        "removal",
        "furniture"
    ],
    "wof:name":"Wridgways",
    "wof:placetype":"venue"
},
  "geometry": {"coordinates":[149.153885,-21.066399],"type":"Point"}
}