{
  "type": "Feature",
  "properties": {
    "addr:full":"131 Reservoir Rd Cardiff Heights NSW 2285",
    "addr:housenumber":"131",
    "addr:postcode":"2285",
    "addr:street":"Reservoir Rd",
    "iso:country":"AU",
    "sg:address":"131 Reservoir Rd",
    "sg:city":"Cardiff Heights",
    "sg:classifiers":[
        {
            "category":"Professional",
            "subcategory":"Detective & Security Services",
            "type":"Services"
        }
    ],
    "sg:phone":"+61 2 4954 3220",
    "sg:postcode":"2285",
    "sg:province":"NSW",
    "sg:tags":[
        "consultant",
        "system"
    ],
    "wof:name":"At Shadowhawk",
    "wof:placetype":"venue"
},
  "geometry": {"coordinates":[151.66365051299999,-32.9300270081],"type":"Point"}
}