{
  "type": "Feature",
  "properties": {
    "iso:country":"AU",
    "sg:address":"943 Ferntree Gully Rd",
    "sg:city":"Wheelers Hill",
    "sg:classifiers":[
        {
            "category":"Building & Trades",
            "subcategory":"Construction",
            "type":"Services"
        }
    ],
    "sg:phone":"+61 3 9561 2485",
    "sg:postcode":"3150",
    "sg:province":"VIC",
    "sg:tags":[
        "earth",
        "excavating",
        "moving",
        "contractor"
    ],
    "wof:name":"Catco Pty Ltd",
    "wof:placetype":"venue"
},
  "geometry": {"coordinates":[145.19610595699999,-37.9072418213],"type":"Point"}
}