{
  "type": "Feature",
  "properties": {
    "iso:country":"AU",
    "sg:address":"Shop 1 95 Eumundi Memorial Drv",
    "sg:city":"Eumundi",
    "sg:classifiers":[
        {
            "category":"Fast Food",
            "type":"Food & Drink"
        }
    ],
    "sg:phone":"+61 7 5442 7116",
    "sg:postcode":"4562",
    "sg:province":"QLD",
    "sg:tags":[
        "away",
        "take"
    ],
    "wof:name":"Eu-Sushi",
    "wof:placetype":"venue"
},
  "geometry": {"coordinates":[152.93565368599999,-26.4677391052],"type":"Point"}
}