{
  "type": "Feature",
  "properties": {
    "addr:full":"5 Queens St Iluka NSW 2466",
    "addr:housenumber":"5",
    "addr:postcode":"2466",
    "addr:street":"Queens St",
    "iso:country":"AU",
    "sg:address":"5 Queens St",
    "sg:city":"Iluka",
    "sg:classifiers":[
        {
            "category":"Travel",
            "subcategory":"Hotels & Motels",
            "type":"Entertainment"
        }
    ],
    "sg:phone":"+61 2 6646 6122",
    "sg:postcode":"2466",
    "sg:province":"NSW",
    "sg:tags":[
        "accommodation"
    ],
    "wof:name":"Sedgers Reef Hotel",
    "wof:placetype":"venue"
},
  "geometry": {"coordinates":[153.35121154800001,-29.4085979462],"type":"Point"}
}