{
  "type": "Feature",
  "properties": {
    "iso:country":"AU",
    "sg:address":"90 Woodhall St",
    "sg:city":"Stirling",
    "sg:classifiers":[
        {
            "category":"Professional",
            "subcategory":"Accounting & Tax Preparation",
            "type":"Services"
        }
    ],
    "sg:phone":"+61 8 9349 9189",
    "sg:postcode":"6021",
    "sg:province":"WA",
    "sg:tags":[
        "bookkeeping"
    ],
    "wof:name":"Book-Keeping Network The",
    "wof:placetype":"venue"
},
  "geometry": {"coordinates":[115.817489624,-31.8774375916],"type":"Point"}
}