{
  "type": "Feature",
  "properties": {
    "iso:country":"AU",
    "sg:address":"1 A Brandon St",
    "sg:city":"South Perth",
    "sg:classifiers":[
        {
            "category":"Home & Garden",
            "subcategory":"Building Materials",
            "type":"Retail Goods"
        }
    ],
    "sg:phone":"+61 407 046 787",
    "sg:postcode":"6151",
    "sg:province":"WA",
    "sg:tags":[
        "lawn",
        "cutting",
        "maintenance"
    ],
    "wof:name":"Best Cut Lawn Mowing Service",
    "wof:placetype":"venue"
},
  "geometry": {"coordinates":[115.876419,-31.9774],"type":"Point"}
}