{
  "type": "Feature",
  "properties": {
    "iso:country":"AU",
    "sg:address":"Morrell St",
    "sg:city":"Mooroopna",
    "sg:classifiers":[
        {
            "category":"Organizations",
            "subcategory":"Community Association",
            "type":"Services"
        }
    ],
    "sg:phone":"+61 3 5825 3099",
    "sg:postcode":"3629",
    "sg:province":"VIC",
    "sg:tags":[
        "club",
        "senior",
        "citizen"
    ],
    "wof:name":"Mooroopna Senior Citizens Club",
    "wof:placetype":"venue"
},
  "geometry": {"coordinates":[145.35922241200001,-36.3936347961],"type":"Point"}
}