{
  "type": "Feature",
  "properties": {
    "addr:full":"10 William St East Lilydale VIC 3140",
    "addr:housenumber":"10",
    "addr:postcode":"3140",
    "addr:street":"William St East",
    "iso:country":"AU",
    "sg:address":"10 William St East",
    "sg:city":"Lilydale",
    "sg:classifiers":[
        {
            "category":"Professional",
            "type":"Services"
        }
    ],
    "sg:phone":"+61 3 9735 5515",
    "sg:postcode":"3140",
    "sg:province":"VIC",
    "sg:tags":[
        "courier"
    ],
    "wof:name":"Pack & Send",
    "wof:placetype":"venue"
},
  "geometry": {"coordinates":[145.34602355999999,-37.757648468],"type":"Point"}
}