{
  "type": "Feature",
  "properties": {
    "iso:country":"AU",
    "sg:address":"79 Gipps St",
    "sg:city":"Wollongong",
    "sg:classifiers":[
        {
            "category":"Manufacturing",
            "subcategory":"Metals",
            "type":"Manufacturing & Wholesale Goods"
        }
    ],
    "sg:phone":"+61 2 4228 5188",
    "sg:postcode":"2500",
    "sg:province":"NSW",
    "sg:tags":[
        "wholesaler",
        "aluminium",
        "mfrs"
    ],
    "wof:name":"Alumark Aluminium Supply",
    "wof:placetype":"venue"
},
  "geometry": {"coordinates":[150.892075,-34.417355],"type":"Point"}
}