{
  "type": "Feature",
  "properties": {
    "addr:full":"16 Francisco Crs Bullcreek WA 6149",
    "addr:housenumber":"16",
    "addr:postcode":"6149",
    "addr:street":"Francisco Crs Bullcreek",
    "iso:country":"AU",
    "sg:address":"16 Francisco Crs",
    "sg:city":"Bullcreek",
    "sg:classifiers":[
        {
            "category":"Health Services",
            "subcategory":"Health Practitioner",
            "type":"Services"
        }
    ],
    "sg:phone":"+61 8 9310 3254",
    "sg:postcode":"6149",
    "sg:province":"WA",
    "sg:tags":[
        "psychologist"
    ],
    "wof:name":"Taylor Graham",
    "wof:placetype":"venue"
},
  "geometry": {"coordinates":[115.87059000000001,-32.066471],"type":"Point"}
}