{
  "type": "Feature",
  "properties": {
    "addr:full":"Wedel Rd Alton Downs QLD 4702",
    "addr:postcode":"4702",
    "addr:street":"Wedel Rd",
    "iso:country":"AU",
    "sg:address":"Wedel Rd",
    "sg:city":"Alton Downs",
    "sg:classifiers":[
        {
            "category":"Autos & Motor Vehicles",
            "subcategory":"Boat Sales",
            "type":"Retail Goods"
        }
    ],
    "sg:phone":"+61 7 4934 1118",
    "sg:postcode":"4702",
    "sg:province":"QLD",
    "sg:tags":[
        "yacht"
    ],
    "wof:name":"Queensland Ski Marine",
    "wof:placetype":"venue"
},
  "geometry": {"coordinates":[150.42123413100001,-23.2889709473],"type":"Point"}
}