{
  "type": "Feature",
  "properties": {
    "addr:full":"140 Parramatta Rd Granville NSW 2142",
    "addr:housenumber":"140",
    "addr:postcode":"2142",
    "addr:street":"Parramatta Rd",
    "iso:country":"AU",
    "sg:address":"140 Parramatta Rd",
    "sg:city":"Granville",
    "sg:classifiers":[
        {
            "category":"Education",
            "subcategory":"Vocational School",
            "type":"Public Place"
        }
    ],
    "sg:phone":"+61 2 9603 1165",
    "sg:postcode":"2142",
    "sg:province":"NSW",
    "sg:tags":[
        "beauty"
    ],
    "wof:name":"New Hollywood Nails The",
    "wof:placetype":"venue"
},
  "geometry": {"coordinates":[151.01139831500001,-33.8304023743],"type":"Point"}
}