{
  "type": "Feature",
  "properties": {
    "iso:country":"AU",
    "sg:address":"438 Goodwood Rd",
    "sg:city":"Cumberland Park",
    "sg:classifiers":[
        {
            "category":"Education",
            "subcategory":"Special Training",
            "type":"Public Place"
        }
    ],
    "sg:phone":"+61 8 8357 9222",
    "sg:postcode":"5041",
    "sg:province":"SA",
    "sg:tags":[
        "development"
    ],
    "wof:name":"Anthony Stone Consultants",
    "wof:placetype":"venue"
},
  "geometry": {"coordinates":[138.591156,-34.9729],"type":"Point"}
}