{
  "type": "Feature",
  "properties": {
    "addr:full":"Royal North Shore Hosptl St Leonards NSW 2065",
    "addr:postcode":"2065",
    "iso:country":"AU",
    "sg:address":"Royal North Shore Hosptl",
    "sg:city":"St Leonards",
    "sg:classifiers":[
        {
            "category":"Health Services",
            "subcategory":"Doctor",
            "type":"Services"
        }
    ],
    "sg:phone":"+61 2 9436 3719",
    "sg:postcode":"2065",
    "sg:province":"NSW",
    "sg:tags":[
        "medical",
        "practitioner"
    ],
    "wof:name":"Piper D W Dr",
    "wof:placetype":"venue"
},
  "geometry": {"coordinates":[151.197509766,-33.8237915039],"type":"Point"}
}