{
  "type": "Feature",
  "properties": {
    "iso:country":"AU",
    "sg:address":"Unit 3/ 32 Export Drv",
    "sg:city":"Ernest",
    "sg:classifiers":[
        {
            "category":"Building & Trades",
            "subcategory":"Construction",
            "type":"Services"
        }
    ],
    "sg:phone":"+61 7 5563 3555",
    "sg:postcode":"4214",
    "sg:province":"QLD",
    "sg:tags":[
        "contractor"
    ],
    "wof:name":"Steve Willoughby Constructions",
    "wof:placetype":"venue"
},
  "geometry": {"coordinates":[153.35885620100001,-27.9676876068],"type":"Point"}
}