{
  "type": "Feature",
  "properties": {
    "addr:full":"7 Weir St Kiama NSW 2533",
    "addr:housenumber":"7",
    "addr:postcode":"2533",
    "addr:street":"Weir St",
    "iso:country":"AU",
    "sg:address":"7 Weir St",
    "sg:city":"Kiama",
    "sg:classifiers":[
        {
            "category":"Building & Trades",
            "subcategory":"Construction",
            "type":"Services"
        }
    ],
    "sg:phone":"+61 2 4232 2895",
    "sg:postcode":"2533",
    "sg:province":"NSW",
    "sg:tags":[
        "contractor"
    ],
    "wof:name":"C & C Symonds Pty Ltd",
    "wof:placetype":"venue"
},
  "geometry": {"coordinates":[150.842285156,-34.6960105896],"type":"Point"}
}