{
  "type": "Feature",
  "properties": {
    "iso:country":"AU",
    "sg:address":"PO Box 717",
    "sg:city":"Samford",
    "sg:classifiers":[
        {
            "category":"Health Services",
            "subcategory":"Doctor",
            "type":"Services"
        }
    ],
    "sg:phone":"+61 7 3289 5255",
    "sg:postcode":"4520",
    "sg:province":"QLD",
    "sg:tags":[
        "medical",
        "practitioner"
    ],
    "wof:name":"Brown Jenny Dr",
    "wof:placetype":"venue"
},
  "geometry": {"coordinates":[152.886642,-27.373671],"type":"Point"}
}