{
  "type": "Feature",
  "properties": {
    "addr:full":"110 Mountjoy Pde Lorne VIC 3232",
    "addr:housenumber":"110",
    "addr:postcode":"3232",
    "addr:street":"Mountjoy Pde",
    "iso:country":"AU",
    "sg:address":"110 Mountjoy Pde",
    "sg:city":"Lorne",
    "sg:classifiers":[
        {
            "category":"Shopping",
            "subcategory":"Clothing, Apparel, & Fashions",
            "type":"Retail Goods"
        }
    ],
    "sg:phone":"+61 3 5289 2250",
    "sg:postcode":"3232",
    "sg:province":"VIC",
    "sg:tags":[
        "lady",
        "wear"
    ],
    "wof:name":"Beachclub Clothing",
    "wof:placetype":"venue"
},
  "geometry": {"coordinates":[143.97511299999999,-38.540417],"type":"Point"}
}