{
  "type": "Feature",
  "properties": {
    "addr:full":"155 Victoria Rd Marrickville NSW 2204",
    "addr:housenumber":"155",
    "addr:postcode":"2204",
    "addr:street":"Victoria Rd",
    "iso:country":"AU",
    "sg:address":"155 Victoria Rd",
    "sg:city":"Marrickville",
    "sg:classifiers":[
        {
            "category":"Social Services",
            "type":"Services"
        }
    ],
    "sg:phone":"+61 2 9560 7344",
    "sg:postcode":"2204",
    "sg:province":"NSW",
    "sg:tags":[
        "disabled",
        "person",
        "equipment"
    ],
    "wof:name":"P.R. King & Sons Pty Ltd",
    "wof:placetype":"venue"
},
  "geometry": {"coordinates":[151.16372699999999,-33.907585],"type":"Point"}
}