{
  "type": "Feature",
  "properties": {
    "iso:country":"AU",
    "sg:address":"Ste5/ 27 Raglan St",
    "sg:city":"South Melbourne",
    "sg:classifiers":[
        {
            "category":"Professional",
            "subcategory":"Computer Services",
            "type":"Services"
        }
    ],
    "sg:phone":"+61 3 8696 3300",
    "sg:postcode":"3205",
    "sg:province":"VIC",
    "sg:tags":[
        "package",
        "software"
    ],
    "wof:name":"Avinet Pty Ltd",
    "wof:placetype":"venue"
},
  "geometry": {"coordinates":[144.965576,-37.836723],"type":"Point"}
}