{
  "type": "Feature",
  "properties": {
    "addr:full":"Hamilton Rd Port Fairy VIC 3284",
    "addr:postcode":"3284",
    "addr:street":"Hamilton Rd",
    "iso:country":"AU",
    "sg:address":"Hamilton Rd",
    "sg:city":"Port Fairy",
    "sg:classifiers":[
        {
            "category":"Building & Trades",
            "subcategory":"Construction",
            "type":"Services"
        }
    ],
    "sg:phone":"+61 3 5568 2655",
    "sg:postcode":"3284",
    "sg:province":"VIC",
    "sg:tags":[
        "stonework",
        "stone",
        "mason"
    ],
    "wof:name":"Bam Stone",
    "wof:placetype":"venue"
},
  "geometry": {"coordinates":[142.227127075,-38.3846092224],"type":"Point"}
}