{
  "type": "Feature",
  "properties": {
    "iso:country":"AU",
    "sg:address":"161 Broadway",
    "sg:city":"Nedlands",
    "sg:classifiers":[
        {
            "category":"Restaurant",
            "type":"Food & Drink"
        }
    ],
    "sg:phone":"+61 8 9389 8410",
    "sg:postcode":"6009",
    "sg:province":"WA",
    "wof:name":"Greco's On Broadway",
    "wof:placetype":"venue"
},
  "geometry": {"coordinates":[115.814972,-31.988121],"type":"Point"}
}