{
  "type": "Feature",
  "properties": {
    "addr:full":"80 McDougall St Kirribilli NSW 2061",
    "addr:housenumber":"80",
    "addr:postcode":"2061",
    "addr:street":"Mcdougall St",
    "iso:country":"AU",
    "sg:address":"80 McDougall St",
    "sg:city":"Kirribilli",
    "sg:classifiers":[
        {
            "category":"Recreation",
            "type":"Entertainment"
        }
    ],
    "sg:phone":"+61 1800 763 762",
    "sg:postcode":"2061",
    "sg:province":"NSW",
    "sg:tags":[
        "supply",
        "outdoor",
        "adventure",
        "activity"
    ],
    "wof:name":"Adrenalin Club",
    "wof:placetype":"venue"
},
  "geometry": {"coordinates":[151.21531677199999,-33.8454780579],"type":"Point"}
}