{
  "type": "Feature",
  "properties": {
    "addr:full":"44 William St Norwood SA 5067",
    "addr:housenumber":"44",
    "addr:postcode":"5067",
    "addr:street":"William St",
    "iso:country":"AU",
    "sg:address":"44 William St",
    "sg:city":"Norwood",
    "sg:classifiers":[
        {
            "category":"Real Estate",
            "subcategory":"Real Estate Agent",
            "type":"Services"
        }
    ],
    "sg:phone":"+61 8 8331 8755",
    "sg:postcode":"5067",
    "sg:province":"SA",
    "wof:name":"Profile Real Estate",
    "wof:placetype":"venue"
},
  "geometry": {"coordinates":[138.627349853,-34.9248046875],"type":"Point"}
}