{
  "type": "Feature",
  "properties": {
    "iso:country":"AU",
    "sg:address":"Unit 8/ 4 Pritchard St",
    "sg:city":"O&#039;Connor",
    "sg:classifiers":[
        {
            "category":"Autos & Motor Vehicles",
            "subcategory":"Boat Sales",
            "type":"Retail Goods"
        }
    ],
    "sg:phone":"+61 8 9337 1144",
    "sg:postcode":"6163",
    "sg:province":"WA",
    "sg:tags":[
        "equipment",
        "yacht"
    ],
    "wof:name":"Gamemaster Marine Products",
    "wof:placetype":"venue"
},
  "geometry": {"coordinates":[115.792572,-32.063107],"type":"Point"}
}