{
  "type": "Feature",
  "properties": {
    "addr:full":"55 Port Rd Kadina SA 5554",
    "addr:housenumber":"55",
    "addr:postcode":"5554",
    "addr:street":"Port Rd",
    "iso:country":"AU",
    "sg:address":"55 Port Rd",
    "sg:city":"Kadina",
    "sg:classifiers":[
        {
            "category":"Autos & Motor Vehicles",
            "subcategory":"Motorcycle Sales",
            "type":"Retail Goods"
        }
    ],
    "sg:phone":"+61 8 8821 2604",
    "sg:postcode":"5554",
    "sg:province":"SA",
    "sg:tags":[
        "outboard"
    ],
    "wof:name":"Yorke Peninsula Marine",
    "wof:placetype":"venue"
},
  "geometry": {"coordinates":[137.697555542,-33.9594497681],"type":"Point"}
}