{
  "type": "Feature",
  "properties": {
    "iso:country":"AU",
    "sg:address":"23 Ethel St",
    "sg:city":"Hyde Park",
    "sg:classifiers":[
        {
            "category":"Professional",
            "subcategory":"Business Services",
            "type":"Services"
        }
    ],
    "sg:phone":"+61 7 4772 4780",
    "sg:postcode":"4812",
    "sg:province":"QLD",
    "sg:tags":[
        "drafting"
    ],
    "wof:name":"Archimedes Cadrafting",
    "wof:placetype":"venue"
},
  "geometry": {"coordinates":[146.793533,-19.277493],"type":"Point"}
}