{
  "type": "Feature",
  "properties": {
    "addr:full":"25 Waratah Pde Narraweena NSW 2099",
    "addr:housenumber":"25",
    "addr:postcode":"2099",
    "addr:street":"Waratah Pde",
    "iso:country":"AU",
    "sg:address":"25 Waratah Pde",
    "sg:city":"Narraweena",
    "sg:classifiers":[
        {
            "category":"Building & Trades",
            "subcategory":"Landscaping Services",
            "type":"Services"
        }
    ],
    "sg:phone":"+61 2 9971 5289",
    "sg:postcode":"2099",
    "sg:province":"NSW",
    "sg:tags":[
        "control",
        "weed"
    ],
    "wof:name":"Horizon Pest Control",
    "wof:placetype":"venue"
},
  "geometry": {"coordinates":[151.271774292,-33.752986908],"type":"Point"}
}