{
  "type": "Feature",
  "properties": {
    "iso:country":"AU",
    "sg:address":"12 Church Rd",
    "sg:city":"Maddington",
    "sg:classifiers":[
        {
            "category":"Wholesale",
            "subcategory":"Scrap",
            "type":"Manufacturing & Wholesale Goods"
        }
    ],
    "sg:phone":"+61 8 9452 8822",
    "sg:postcode":"6109",
    "sg:province":"WA",
    "sg:tags":[
        "merchant",
        "metal"
    ],
    "sg:website":"http://www.lrmetals.com",
    "wof:name":"LR Metals & Machinery",
    "wof:placetype":"venue"
},
  "geometry": {"coordinates":[115.97984314,-32.0465049744],"type":"Point"}
}