{
  "type": "Feature",
  "properties": {
    "iso:country":"AU",
    "sg:address":"90 Garden St",
    "sg:city":"Narrabeen",
    "sg:classifiers":[
        {
            "category":"Retail",
            "subcategory":"Auto Repair",
            "type":"Services"
        }
    ],
    "sg:phone":"+61 2 9913 1677",
    "sg:postcode":"2101",
    "sg:province":"NSW",
    "sg:tags":[
        "repairer",
        "motor",
        "engineer"
    ],
    "wof:name":"Nelson Tony Motors Pty Ltd",
    "wof:placetype":"venue"
},
  "geometry": {"coordinates":[151.294815,-33.700474],"type":"Point"}
}