{
  "type": "Feature",
  "properties": {
    "iso:country":"AU",
    "sg:address":"215 Nebo Rd",
    "sg:city":"Mackay",
    "sg:classifiers":[
        {
            "category":"Travel",
            "subcategory":"Hotels & Motels",
            "type":"Entertainment"
        }
    ],
    "sg:phone":"+61 7 4952 1800",
    "sg:postcode":"4740",
    "sg:province":"QLD",
    "wof:name":"Hi-Way Units Motel",
    "wof:placetype":"venue"
},
  "geometry": {"coordinates":[149.161316,-21.15958],"type":"Point"}
}