{
  "type": "Feature",
  "properties": {
    "iso:country":"AU",
    "sg:address":"124a Henley Beach Rd",
    "sg:city":"Torrensville",
    "sg:classifiers":[
        {
            "category":"Personal",
            "subcategory":"Beauty Salon",
            "type":"Services"
        }
    ],
    "sg:phone":"+61 8 8352 2446",
    "sg:postcode":"5031",
    "sg:province":"SA",
    "sg:tags":[
        "hairdresser"
    ],
    "wof:name":"Steve & George Hair Creations",
    "wof:placetype":"venue"
},
  "geometry": {"coordinates":[138.56741332999999,-34.9236297607],"type":"Point"}
}