{
  "type": "Feature",
  "properties": {
    "iso:country":"AU",
    "sg:address":"1 Mt Spec Rd",
    "sg:city":"Paluma",
    "sg:classifiers":[
        {
            "category":"Travel",
            "subcategory":"Hotels & Motels",
            "type":"Entertainment"
        }
    ],
    "sg:phone":"+61 7 4770 8688",
    "sg:postcode":"4816",
    "sg:province":"QLD",
    "wof:name":"Rainforest Inn Paluma",
    "wof:placetype":"venue"
},
  "geometry": {"coordinates":[146.208023,-19.008656],"type":"Point"}
}