{
  "type": "Feature",
  "properties": {
    "iso:country":"AU",
    "sg:address":"Adelaide St",
    "sg:city":"Raymond Terrace",
    "sg:classifiers":[
        {
            "category":"Education",
            "subcategory":"School",
            "type":"Public Place"
        }
    ],
    "sg:phone":"+61 2 4987 2083",
    "sg:postcode":"2324",
    "sg:province":"NSW",
    "sg:tags":[
        "state",
        "-",
        "nsw"
    ],
    "wof:name":"Raymond Terrace Primary",
    "wof:placetype":"venue"
},
  "geometry": {"coordinates":[151.75942993199999,-32.7531661987],"type":"Point"}
}