{
  "type": "Feature",
  "properties": {
    "addr:full":"238 Hawthorn Rd Vermont South VIC 3133",
    "addr:housenumber":"238",
    "addr:postcode":"3133",
    "addr:street":"Hawthorn Rd",
    "iso:country":"AU",
    "sg:address":"238 Hawthorn Rd",
    "sg:city":"Vermont South",
    "sg:classifiers":[
        {
            "category":"Health Services",
            "subcategory":"Health Practitioner",
            "type":"Services"
        }
    ],
    "sg:phone":"+61 3 9803 3149",
    "sg:postcode":"3133",
    "sg:province":"VIC",
    "sg:tags":[
        "naturopath"
    ],
    "wof:name":"Kevin Kane",
    "wof:placetype":"venue"
},
  "geometry": {"coordinates":[145.17950439399999,-37.8490982056],"type":"Point"}
}