{
  "type": "Feature",
  "properties": {
    "addr:full":"43 Macquarie St Silkstone QLD 4304",
    "addr:housenumber":"43",
    "addr:postcode":"4304",
    "addr:street":"Macquarie St",
    "iso:country":"AU",
    "sg:address":"43 Macquarie St",
    "sg:city":"Silkstone",
    "sg:classifiers":[
        {
            "category":"Professional",
            "subcategory":"Accounting & Tax Preparation",
            "type":"Services"
        }
    ],
    "sg:phone":"+61 7 3830 5318",
    "sg:postcode":"4304",
    "sg:province":"QLD",
    "sg:tags":[
        "bookkeeping"
    ],
    "wof:name":"Professional Payroll Services",
    "wof:placetype":"venue"
},
  "geometry": {"coordinates":[152.786453247,-27.6204986572],"type":"Point"}
}