{
  "type": "Feature",
  "properties": {
    "addr:full":"Shop 33/ 75 Lynbrook Blv Lynbrook VIC 3975",
    "addr:housenumber":"shop 33 / 75",
    "addr:postcode":"3975",
    "addr:street":"Lynbrook Blv",
    "iso:country":"AU",
    "sg:address":"Shop 33/ 75",
    "sg:city":"Lynbrook Blv Lynbrook",
    "sg:classifiers":[
        {
            "category":"Ice Cream",
            "type":"Food & Drink"
        }
    ],
    "sg:phone":"+61 3 8787 8121",
    "sg:postcode":"3975",
    "sg:province":"VIC",
    "sg:tags":[
        "retail"
    ],
    "wof:name":"Frekles Ice Creamery & Juice Bar",
    "wof:placetype":"venue"
},
  "geometry": {"coordinates":[145.25309753400001,-38.0529289246],"type":"Point"}
}