{
  "type": "Feature",
  "properties": {
    "addr:full":"2a Nirvana St Pendle Hill NSW 2145",
    "addr:housenumber":"2a",
    "addr:postcode":"2145",
    "addr:street":"Nirvana St",
    "iso:country":"AU",
    "sg:address":"2a Nirvana St",
    "sg:city":"Pendle Hill",
    "sg:classifiers":[
        {
            "category":"Retail",
            "subcategory":"Auto Repair",
            "type":"Services"
        }
    ],
    "sg:phone":"+61 2 9896 1212",
    "sg:postcode":"2145",
    "sg:province":"NSW",
    "sg:tags":[
        "repairer",
        "motor",
        "engineer"
    ],
    "wof:name":"MJM Automotive Mechanical Services",
    "wof:placetype":"venue"
},
  "geometry": {"coordinates":[150.95541381800001,-33.7977600098],"type":"Point"}
}