{
  "type": "Feature",
  "properties": {
    "addr:full":"9 Byron St Clayton South VIC 3169",
    "addr:housenumber":"9",
    "addr:postcode":"3169",
    "addr:street":"Byron St",
    "iso:country":"AU",
    "sg:address":"9 Byron St",
    "sg:city":"Clayton South",
    "sg:classifiers":[
        {
            "category":"Education",
            "subcategory":"Music School",
            "type":"Public Place"
        }
    ],
    "sg:phone":"+61 3 9543 3345",
    "sg:postcode":"3169",
    "sg:province":"VIC",
    "sg:tags":[
        "teacher"
    ],
    "wof:name":"Clayton Piano Music School",
    "wof:placetype":"venue"
},
  "geometry": {"coordinates":[145.11903381400001,-37.9352607727],"type":"Point"}
}