{
  "type": "Feature",
  "properties": {
    "addr:full":"27 Paynesville Rd Paynesville VIC 3880",
    "addr:housenumber":"27",
    "addr:postcode":"3880",
    "addr:street":"Paynesville Rd",
    "iso:country":"AU",
    "sg:address":"27 Paynesville Rd",
    "sg:city":"Paynesville",
    "sg:classifiers":[
        {
            "category":"Building & Trades",
            "subcategory":"Construction",
            "type":"Services"
        }
    ],
    "sg:phone":"+61 3 5157 6399",
    "sg:postcode":"3880",
    "sg:province":"VIC",
    "sg:tags":[
        "contractor"
    ],
    "wof:name":"Tomlinson S & M A Builders Pty Ltd",
    "wof:placetype":"venue"
},
  "geometry": {"coordinates":[147.71981811500001,-37.9074935913],"type":"Point"}
}