{
  "type": "Feature",
  "properties": {
    "addr:full":"1574 Burwood Hwy Tecoma VIC 3160",
    "addr:housenumber":"1574",
    "addr:postcode":"3160",
    "addr:street":"Burwood Hwy",
    "iso:country":"AU",
    "sg:address":"1574 Burwood Hwy",
    "sg:city":"Tecoma",
    "sg:classifiers":[
        {
            "category":"Health Services",
            "subcategory":"Health Practitioner",
            "type":"Services"
        }
    ],
    "sg:phone":"+61 3 9754 8772",
    "sg:postcode":"3160",
    "sg:province":"VIC",
    "sg:tags":[
        "physiotherapist"
    ],
    "wof:name":"Belgrave-Tecoma Physiotherapy",
    "wof:placetype":"venue"
},
  "geometry": {"coordinates":[145.346603394,-37.9073066711],"type":"Point"}
}