{
  "type": "Feature",
  "properties": {
    "addr:full":"Burford St Muttaburra QLD 4732",
    "addr:postcode":"4732",
    "addr:street":"Burford St",
    "iso:country":"AU",
    "sg:address":"Burford St",
    "sg:city":"Muttaburra",
    "sg:classifiers":[
        {
            "category":"Autos & Motor Vehicles",
            "subcategory":"Fuel & Gas Station",
            "type":"Retail Goods"
        }
    ],
    "sg:phone":"+61 7 4658 7238",
    "sg:postcode":"4732",
    "sg:province":"QLD",
    "wof:name":"BP Australia Limited",
    "wof:placetype":"venue"
},
  "geometry": {"coordinates":[144.54646299999999,-22.59358],"type":"Point"}
}