{
  "type": "Feature",
  "properties": {
    "addr:full":"30-62 Barcom Ave Rushcutters Bay NSW 2011",
    "addr:housenumber":"30-62",
    "addr:postcode":"2011",
    "addr:street":"Barcom Ave",
    "iso:country":"AU",
    "sg:address":"30-62 Barcom Ave",
    "sg:city":"Rushcutters Bay",
    "sg:classifiers":[
        {
            "category":"Retail",
            "subcategory":"Storage",
            "type":"Services"
        }
    ],
    "sg:phone":"+61 2 9361 3380",
    "sg:postcode":"2011",
    "sg:province":"NSW",
    "wof:name":"Inner City Packaging",
    "wof:placetype":"venue"
},
  "geometry": {"coordinates":[151.227127075,-33.8770523071],"type":"Point"}
}