{
  "type": "Feature",
  "properties": {
    "addr:full":"Cnr Crosskeys & C B Fisher Drv Cavan SA 5094",
    "addr:postcode":"5094",
    "addr:street":"Cnr;Fisher Drv",
    "iso:country":"AU",
    "sg:address":"Cnr Crosskeys & C B Fisher Drv",
    "sg:city":"Cavan",
    "sg:classifiers":[
        {
            "category":"Home & Garden",
            "subcategory":"Household Appliances",
            "type":"Retail Goods"
        }
    ],
    "sg:phone":"+61 8 8262 6866",
    "sg:postcode":"5094",
    "sg:province":"SA",
    "sg:tags":[
        "chemical",
        "equipment",
        "steam",
        "cleaning",
        "pressure"
    ],
    "wof:name":"ERS Australia Pty Ltd",
    "wof:placetype":"venue"
},
  "geometry": {"coordinates":[138.600875855,-34.8255119324],"type":"Point"}
}