{
  "type": "Feature",
  "properties": {
    "addr:full":"7 Iluka Crt Jan Juc VIC 3228",
    "addr:housenumber":"7",
    "addr:postcode":"3228",
    "addr:street":"Iluka Crt",
    "iso:country":"AU",
    "sg:address":"7 Iluka Crt",
    "sg:city":"Jan Juc",
    "sg:classifiers":[
        {
            "category":"Building & Trades",
            "subcategory":"Construction",
            "type":"Services"
        }
    ],
    "sg:phone":"+61 3 5261 3931",
    "sg:postcode":"3228",
    "sg:province":"VIC",
    "sg:tags":[
        "contractor"
    ],
    "wof:name":"Shill Outdoor Constructions",
    "wof:placetype":"venue"
},
  "geometry": {"coordinates":[144.29440299999999,-38.351349],"type":"Point"}
}