{
  "type": "Feature",
  "properties": {
    "iso:country":"AU",
    "sg:address":"3/ 58 Miguel Rd",
    "sg:city":"Bibra Lake",
    "sg:classifiers":[
        {
            "category":"Building & Trades",
            "subcategory":"Construction",
            "type":"Services"
        }
    ],
    "sg:phone":"+61 1800 980 001",
    "sg:postcode":"6163",
    "sg:province":"WA",
    "sg:tags":[
        "insulation",
        "contractor"
    ],
    "wof:name":"A AA Insulation Removers",
    "wof:placetype":"venue"
},
  "geometry": {"coordinates":[115.80999,-32.11203],"type":"Point"}
}