{
  "type": "Feature",
  "properties": {
    "addr:full":"225 Croatia Ave Edmondson Park NSW 2171",
    "addr:housenumber":"225",
    "addr:postcode":"2171",
    "addr:street":"Croatia Ave",
    "iso:country":"AU",
    "sg:address":"225 Croatia Ave",
    "sg:city":"Edmondson Park",
    "sg:classifiers":[
        {
            "category":"Building & Trades",
            "subcategory":"Construction",
            "type":"Services"
        }
    ],
    "sg:phone":"+61 2 9607 6858",
    "sg:postcode":"2171",
    "sg:province":"NSW",
    "sg:tags":[
        "joiner",
        "carpenter"
    ],
    "wof:name":"Doriguzzi Construction Pty Ltd",
    "wof:placetype":"venue"
},
  "geometry": {"coordinates":[150.86184692399999,-33.9623374939],"type":"Point"}
}