{
  "type": "Feature",
  "properties": {
    "addr:full":"37 Little Barber St Gunnedah NSW 2380",
    "addr:housenumber":"37",
    "addr:postcode":"2380",
    "addr:street":"Little Barber St",
    "iso:country":"AU",
    "sg:address":"37 Little Barber St",
    "sg:city":"Gunnedah",
    "sg:classifiers":[
        {
            "category":"Utilities",
            "subcategory":"Water",
            "type":"Services"
        }
    ],
    "sg:phone":"+61 428 659 401",
    "sg:postcode":"2380",
    "sg:province":"NSW",
    "sg:tags":[
        "hot",
        "system"
    ],
    "wof:name":"Giddings Electrical Pty Ltd",
    "wof:placetype":"venue"
},
  "geometry": {"coordinates":[150.25117492699999,-30.9778747559],"type":"Point"}
}