{
  "type": "Feature",
  "properties": {
    "addr:full":"Suite 1/ 268 Main Rd Toukley NSW 2263",
    "addr:housenumber":"/ 268",
    "addr:postcode":"2263",
    "addr:street":"Main Rd",
    "iso:country":"AU",
    "sg:address":"Suite 1/ 268 Main Rd",
    "sg:city":"Toukley",
    "sg:classifiers":[
        {
            "category":"Health Services",
            "subcategory":"Health Practitioner",
            "type":"Services"
        }
    ],
    "sg:phone":"+61 2 4397 2040",
    "sg:postcode":"2263",
    "sg:province":"NSW",
    "sg:tags":[
        "naturopath"
    ],
    "wof:name":"Toukley Health & Harmony Natural Lifestyle Centre",
    "wof:placetype":"venue"
},
  "geometry": {"coordinates":[151.54130599999999,-33.263725],"type":"Point"}
}