{
  "type": "Feature",
  "properties": {
    "iso:country":"AU",
    "sg:address":"35 River St",
    "sg:city":"Bellerive",
    "sg:classifiers":[
        {
            "category":"Professional",
            "subcategory":"Art Services",
            "type":"Services"
        }
    ],
    "sg:phone":"+61 3 6245 1133",
    "sg:postcode":"7018",
    "sg:province":"TAS",
    "sg:tags":[
        "decorator",
        "painter"
    ],
    "wof:name":"Topcoat Painters",
    "wof:placetype":"venue"
},
  "geometry": {"coordinates":[147.38313293499999,-42.8720626831],"type":"Point"}
}