{
  "type": "Feature",
  "properties": {
    "addr:full":"Elizabeth Drv Mt Pritchard NSW 2170",
    "addr:postcode":"2170",
    "addr:street":"Elizabeth Drv;Pritchard",
    "iso:country":"AU",
    "sg:address":"Elizabeth Drv",
    "sg:city":"Mt Pritchard",
    "sg:classifiers":[
        {
            "category":"Autos & Motor Vehicles",
            "subcategory":"Fuel & Gas Station",
            "type":"Retail Goods"
        }
    ],
    "sg:phone":"+61 2 9610 4580",
    "sg:postcode":"2170",
    "sg:province":"NSW",
    "wof:name":"Meadows Automotive",
    "wof:placetype":"venue"
},
  "geometry": {"coordinates":[150.90301513700001,-33.9115715027],"type":"Point"}
}