{
  "type": "Feature",
  "properties": {
    "iso:country":"AU",
    "sg:address":"Shop 627 Chirnside Shopping Centre",
    "sg:city":"Chirnside Park",
    "sg:classifiers":[
        {
            "category":"Shopping",
            "subcategory":"Music",
            "type":"Retail Goods"
        }
    ],
    "sg:phone":"+61 3 9727 2030",
    "sg:postcode":"3116",
    "sg:province":"VIC",
    "sg:tags":[
        "store"
    ],
    "wof:name":"Sanity",
    "wof:placetype":"venue"
},
  "geometry": {"coordinates":[145.321655273,-37.7562484741],"type":"Point"}
}