{
  "type": "Feature",
  "properties": {
    "addr:full":"56 Berry St North Sydney NSW 2060",
    "addr:housenumber":"56",
    "addr:postcode":"2060",
    "addr:street":"Berry St",
    "iso:country":"AU",
    "sg:address":"56 Berry St",
    "sg:city":"North Sydney",
    "sg:classifiers":[
        {
            "category":"Professional",
            "type":"Services"
        }
    ],
    "sg:phone":"+61 2 9455 0999",
    "sg:postcode":"2060",
    "sg:province":"NSW",
    "sg:tags":[
        "message",
        "answering",
        "telephone"
    ],
    "wof:name":"Christie Corporate",
    "wof:placetype":"venue"
},
  "geometry": {"coordinates":[151.207855225,-33.8367729187],"type":"Point"}
}