{
  "type": "Feature",
  "properties": {
    "addr:full":"12 William St Nhill VIC 3418",
    "addr:housenumber":"12",
    "addr:postcode":"3418",
    "addr:street":"William St",
    "iso:country":"AU",
    "sg:address":"12 William St",
    "sg:city":"Nhill",
    "sg:classifiers":[
        {
            "category":"Professional",
            "subcategory":"Business Services",
            "type":"Services"
        }
    ],
    "sg:phone":"+61 3 5391 1805",
    "sg:postcode":"3418",
    "sg:province":"VIC",
    "sg:tags":[
        "livestock",
        "transport"
    ],
    "wof:name":"Bone G J",
    "wof:placetype":"venue"
},
  "geometry": {"coordinates":[141.65997314399999,-36.3370094299],"type":"Point"}
}