{
  "type": "Feature",
  "properties": {
    "addr:full":"19 / 77 Queens Rd Melbourne VIC 3004",
    "addr:housenumber":"19 / 77",
    "addr:postcode":"3004",
    "addr:street":"Queens Rd",
    "iso:country":"AU",
    "sg:address":"19 / 77 Queens Rd",
    "sg:city":"Melbourne",
    "sg:classifiers":[
        {
            "category":"Personal",
            "subcategory":"Massage",
            "type":"Services"
        }
    ],
    "sg:phone":"+61 1800 777 734",
    "sg:postcode":"3004",
    "sg:province":"VIC",
    "sg:tags":[
        "therapy"
    ],
    "wof:name":"Merkas Health",
    "wof:placetype":"venue"
},
  "geometry": {"coordinates":[144.97921752900001,-37.8528785706],"type":"Point"}
}