{
  "type": "Feature",
  "properties": {
    "iso:country":"AU",
    "sg:address":"110 George St",
    "sg:city":"Launceston",
    "sg:classifiers":[
        {
            "category":"Shopping",
            "type":"Retail Goods"
        }
    ],
    "sg:phone":"+61 3 6331 4240",
    "sg:postcode":"7250",
    "sg:province":"TAS",
    "sg:tags":[
        "repair",
        "travel"
    ],
    "wof:name":"Paddy Pallin",
    "wof:placetype":"venue"
},
  "geometry": {"coordinates":[147.140716553,-41.4368133545],"type":"Point"}
}