{
  "type": "Feature",
  "properties": {
    "addr:full":"77 Kedron Brook Rd Wilston QLD 4051",
    "addr:housenumber":"77",
    "addr:postcode":"4051",
    "addr:street":"Kedron Brook Rd",
    "iso:country":"AU",
    "sg:address":"77 Kedron Brook Rd",
    "sg:city":"Wilston",
    "sg:classifiers":[
        {
            "category":"Real Estate",
            "subcategory":"Real Estate Agent",
            "type":"Services"
        }
    ],
    "sg:phone":"+61 7 3552 5555",
    "sg:postcode":"4051",
    "sg:province":"QLD",
    "wof:name":"Inner City Property",
    "wof:placetype":"venue"
},
  "geometry": {"coordinates":[153.020065308,-27.4325752258],"type":"Point"}
}