{
  "type": "Feature",
  "properties": {
    "iso:country":"AU",
    "sg:address":"16 Bulletin Pl",
    "sg:city":"Sydney",
    "sg:classifiers":[
        {
            "category":"Restaurant",
            "type":"Food & Drink"
        }
    ],
    "sg:phone":"+61 2 9251 2929",
    "sg:postcode":"2000",
    "sg:province":"NSW",
    "wof:name":"Alfredo Authentic Italian Restaurant",
    "wof:placetype":"venue"
},
  "geometry": {"coordinates":[151.20980835,-33.8626403809],"type":"Point"}
}