{
  "type": "Feature",
  "properties": {
    "addr:full":"100 Union Rd Ascot Vale VIC 3032",
    "addr:housenumber":"100",
    "addr:postcode":"3032",
    "addr:street":"Union Rd",
    "iso:country":"AU",
    "sg:address":"100 Union Rd",
    "sg:city":"Ascot Vale",
    "sg:classifiers":[
        {
            "category":"Manufacturing",
            "subcategory":"Food",
            "type":"Manufacturing & Wholesale Goods"
        }
    ],
    "sg:phone":"+61 3 9370 8243",
    "sg:postcode":"3032",
    "sg:province":"VIC",
    "sg:tags":[
        "function",
        "catering"
    ],
    "wof:name":"Ascot Buffet",
    "wof:placetype":"venue"
},
  "geometry": {"coordinates":[144.915558,-37.776794],"type":"Point"}
}