{
  "type": "Feature",
  "properties": {
    "iso:country":"AU",
    "sg:address":"31- 35 Oonoonba Rd",
    "sg:city":"Oonoonba",
    "sg:classifiers":[
        {
            "category":"Manufacturing",
            "subcategory":"Paper Products",
            "type":"Manufacturing & Wholesale Goods"
        }
    ],
    "sg:phone":"+61 7 4778 1544",
    "sg:postcode":"4811",
    "sg:province":"QLD",
    "sg:tags":[
        "box",
        "fibre",
        "carton",
        "cardboard"
    ],
    "wof:name":"Finjon Paper & Cardboard Recycling",
    "wof:placetype":"venue"
},
  "geometry": {"coordinates":[146.810303,-19.303938],"type":"Point"}
}