{
  "type": "Feature",
  "properties": {
    "iso:country":"AU",
    "sg:address":"51 Strathnaver Ave",
    "sg:city":"Strathmore",
    "sg:classifiers":[
        {
            "category":"Communications",
            "subcategory":"News Services",
            "type":"Services"
        }
    ],
    "sg:phone":"+61 3 9531 3286",
    "sg:postcode":"3041",
    "sg:province":"VIC",
    "sg:tags":[
        "information",
        "tourist",
        "attractions"
    ],
    "wof:name":"Bukem Tours",
    "wof:placetype":"venue"
},
  "geometry": {"coordinates":[144.90374755900001,-37.7183609009],"type":"Point"}
}