{
  "type": "Feature",
  "properties": {
    "iso:country":"AU",
    "sg:address":"41 Malcomson St",
    "sg:city":"Mackay",
    "sg:phone":"+61 7 4951 1711",
    "sg:postcode":"4740",
    "sg:province":"QLD",
    "wof:name":"Calbars.com.au",
    "wof:placetype":"venue"
},
  "geometry": {"coordinates":[149.17065400000001,-21.122244],"type":"Point"}
}