{
  "type": "Feature",
  "properties": {
    "addr:full":"PO Box 1201 Busselton WA 6280",
    "addr:postcode":"6280",
    "iso:country":"AU",
    "sg:address":"PO Box 1201",
    "sg:city":"Busselton",
    "sg:classifiers":[
        {
            "category":"Social Services",
            "subcategory":"Child Care",
            "type":"Services"
        }
    ],
    "sg:phone":"+61 8 9752 4033",
    "sg:postcode":"6280",
    "sg:province":"WA",
    "wof:name":"The Nest Family Resource Centre",
    "wof:placetype":"venue"
},
  "geometry": {"coordinates":[115.344818115,-33.652141571],"type":"Point"}
}