{
  "type": "Feature",
  "properties": {
    "addr:full":"Basement Level, 306 Little Collins St Melbourne VIC 3000",
    "addr:housenumber":"306",
    "addr:postcode":"3000",
    "addr:street":"Little Collins St",
    "iso:country":"AU",
    "sg:address":"Basement Level, 306 Little Collins St",
    "sg:city":"Melbourne",
    "sg:classifiers":[
        {
            "category":"Personal",
            "subcategory":"Beauty Salon",
            "type":"Services"
        }
    ],
    "sg:phone":"+61 3 9654 8385",
    "sg:postcode":"3000",
    "sg:province":"VIC",
    "sg:tags":[
        "hairdresser"
    ],
    "wof:name":"Peter Young Salon",
    "wof:placetype":"venue"
},
  "geometry": {"coordinates":[144.96437072800001,-37.8148727417],"type":"Point"}
}