{
  "type": "Feature",
  "properties": {
    "addr:full":"Cnr Elizabeth & Victoria Sts Melbourne VIC 3000",
    "addr:postcode":"3000",
    "addr:street":"Cnr;Sts",
    "iso:country":"AU",
    "sg:address":"Cnr Elizabeth & Victoria Sts",
    "sg:city":"Melbourne",
    "sg:classifiers":[
        {
            "category":"Building & Trades",
            "subcategory":"Landscaping Services",
            "type":"Services"
        }
    ],
    "sg:phone":"+61 3 9320 5822",
    "sg:postcode":"3000",
    "sg:province":"VIC",
    "sg:tags":[
        "market"
    ],
    "sg:website":"http://www.qvm.com.au",
    "wof:name":"Queen Victoria Market",
    "wof:placetype":"venue"
},
  "geometry": {"coordinates":[144.970306397,-37.8075332642],"type":"Point"}
}