{
  "type": "Feature",
  "properties": {
    "iso:country":"AU",
    "sg:address":"85 Penhurst Rd",
    "sg:city":"Narwee",
    "sg:classifiers":[
        {
            "category":"Social Services",
            "subcategory":"Child Care",
            "type":"Services"
        }
    ],
    "sg:phone":"+61 2 9584 9513",
    "sg:postcode":"2209",
    "sg:province":"NSW",
    "wof:name":"Active Kids",
    "wof:placetype":"venue"
},
  "geometry": {"coordinates":[151.07153299999999,-33.94273],"type":"Point"}
}