{
  "type": "Feature",
  "properties": {
    "iso:country":"AU",
    "sg:address":"8 Haworth Crt",
    "sg:city":"Breakwater",
    "sg:classifiers":[
        {
            "category":"Food & Beverages",
            "subcategory":"Bakery",
            "type":"Retail Goods"
        }
    ],
    "sg:phone":"+61 3 5248 1929",
    "sg:postcode":"3219",
    "sg:province":"VIC",
    "sg:tags":[
        "cake",
        "shop",
        "pastry"
    ],
    "wof:name":"Hi-Lite Routleys",
    "wof:placetype":"venue"
},
  "geometry": {"coordinates":[144.38023376500001,-38.1836967468],"type":"Point"}
}