{
  "type": "Feature",
  "properties": {
    "iso:country":"AU",
    "sg:address":"Taylors Rd",
    "sg:city":"Keilor Downs",
    "sg:classifiers":[
        {
            "category":"Fast Food",
            "type":"Food & Drink"
        }
    ],
    "sg:phone":"+61 3 9364 1470",
    "sg:postcode":"3038",
    "sg:province":"VIC",
    "sg:tags":[
        "away",
        "take"
    ],
    "wof:name":"KFC",
    "wof:placetype":"venue"
},
  "geometry": {"coordinates":[144.79144299999999,-37.727741],"type":"Point"}
}