{
  "type": "Feature",
  "properties": {
    "addr:full":"Level 2, 307 Queen St Brisbane City QLD 4000",
    "addr:housenumber":"307",
    "addr:postcode":"4000",
    "addr:street":"Queen St",
    "iso:country":"AU",
    "sg:address":"Level 2, 307 Queen St",
    "sg:city":"Brisbane City",
    "sg:classifiers":[
        {
            "category":"Personal",
            "subcategory":"Massage",
            "type":"Services"
        }
    ],
    "sg:phone":"+61 7 3301 2345",
    "sg:postcode":"4000",
    "sg:province":"QLD",
    "sg:tags":[
        "therapy"
    ],
    "sg:website":"http://www.aamt.com.au",
    "wof:name":"The Remedial Massage Care Clinic",
    "wof:placetype":"venue"
},
  "geometry": {"coordinates":[153.0284729,-27.4672889709],"type":"Point"}
}