{
  "type": "Feature",
  "properties": {
    "iso:country":"AU",
    "sg:address":"Shop 1 62 Hesse St",
    "sg:city":"Queenscliff",
    "sg:classifiers":[
        {
            "category":"Shopping",
            "subcategory":"Clothing, Apparel, & Fashions",
            "type":"Retail Goods"
        }
    ],
    "sg:phone":"+61 3 5258 4018",
    "sg:postcode":"3225",
    "sg:province":"VIC",
    "sg:tags":[
        "lady",
        "wear"
    ],
    "wof:name":"Beachclub Clothing",
    "wof:placetype":"venue"
},
  "geometry": {"coordinates":[144.66066000000001,-38.267857],"type":"Point"}
}