{
  "type": "Feature",
  "properties": {
    "addr:full":"5 Sherrifs Rd Lonsdale SA 5160",
    "addr:housenumber":"5",
    "addr:postcode":"5160",
    "addr:street":"Sherrifs Rd",
    "iso:country":"AU",
    "sg:address":"5 Sherrifs Rd",
    "sg:city":"Lonsdale",
    "sg:classifiers":[
        {
            "category":"Wholesale",
            "subcategory":"Machinery & Supplies",
            "type":"Manufacturing & Wholesale Goods"
        }
    ],
    "sg:phone":"+61 8 8322 8288",
    "sg:postcode":"5160",
    "sg:province":"SA",
    "wof:name":"Futura Machinery Sales & Service",
    "wof:placetype":"venue"
},
  "geometry": {"coordinates":[138.504394531,-35.1060523987],"type":"Point"}
}