{
  "type": "Feature",
  "properties": {
    "addr:full":"PO Box 113 Campania TAS 7026",
    "addr:postcode":"7026",
    "iso:country":"AU",
    "sg:address":"PO Box 113",
    "sg:city":"Campania",
    "sg:classifiers":[
        {
            "category":"Farming",
            "subcategory":"Nursery",
            "type":"Manufacturing & Wholesale Goods"
        }
    ],
    "sg:phone":"+61 3 6260 4544",
    "sg:postcode":"7026",
    "sg:province":"TAS",
    "wof:name":"Bush Regenerators",
    "wof:placetype":"venue"
},
  "geometry": {"coordinates":[147.42112731899999,-42.6648101807],"type":"Point"}
}