{
  "type": "Feature",
  "properties": {
    "addr:full":"2 Dind St Milsons Point NSW 2061",
    "addr:housenumber":"2",
    "addr:postcode":"2061",
    "addr:street":"Dind St",
    "iso:country":"AU",
    "sg:address":"2 Dind St",
    "sg:city":"Milsons Point",
    "sg:classifiers":[
        {
            "category":"Professional",
            "subcategory":"Employment Agencies",
            "type":"Services"
        }
    ],
    "sg:phone":"+61 2 9460 1529",
    "sg:postcode":"2061",
    "sg:province":"NSW",
    "wof:name":"Expr3ss!",
    "wof:placetype":"venue"
},
  "geometry": {"coordinates":[151.211013794,-33.847782135],"type":"Point"}
}