{
  "type": "Feature",
  "properties": {
    "addr:full":"64 Doggett St Fortitude Valley QLD 4006",
    "addr:housenumber":"64",
    "addr:postcode":"4006",
    "addr:street":"Doggett St",
    "iso:country":"AU",
    "sg:address":"64 Doggett St",
    "sg:city":"Fortitude Valley",
    "sg:classifiers":[
        {
            "category":"Professional",
            "type":"Services"
        }
    ],
    "sg:phone":"+61 7 3252 4857",
    "sg:postcode":"4006",
    "sg:province":"QLD",
    "sg:tags":[
        "spray",
        "painting"
    ],
    "wof:name":"Murphy P J Smash Repairs Pty Ltd",
    "wof:placetype":"venue"
},
  "geometry": {"coordinates":[153.043411255,-27.4528656006],"type":"Point"}
}