{
  "type": "Feature",
  "properties": {
    "addr:full":"2/ 78-80 Bayfield Rd Bayswater VIC 3153",
    "addr:housenumber":"/ 78-80",
    "addr:postcode":"3153",
    "addr:street":"Bayfield Rd",
    "iso:country":"AU",
    "sg:address":"2/ 78-80 Bayfield Rd",
    "sg:city":"Bayswater",
    "sg:classifiers":[
        {
            "category":"Building & Trades",
            "subcategory":"Plumbing",
            "type":"Services"
        }
    ],
    "sg:phone":"+61 1800 507 654",
    "sg:postcode":"3153",
    "sg:province":"VIC",
    "sg:tags":[
        "plumber",
        "gasfitters"
    ],
    "wof:name":"Water Save Plumbing",
    "wof:placetype":"venue"
},
  "geometry": {"coordinates":[145.27842712399999,-37.8248062134],"type":"Point"}
}