{
  "type": "Feature",
  "properties": {
    "iso:country":"AU",
    "sg:address":"Unit 4/ 91 Park St",
    "sg:city":"Pascoe Vale",
    "sg:classifiers":[
        {
            "category":"Building & Trades",
            "subcategory":"Construction",
            "type":"Services"
        }
    ],
    "sg:phone":"+61 416 657 053",
    "sg:postcode":"3044",
    "sg:province":"VIC",
    "sg:tags":[
        "plasterboard",
        "plasterer",
        "fixer"
    ],
    "wof:name":"Tiger Plastering",
    "wof:placetype":"venue"
},
  "geometry": {"coordinates":[144.92257690400001,-37.7218360901],"type":"Point"}
}