{
  "type": "Feature",
  "properties": {
    "addr:full":"31 Victoria St Millthorpe NSW 2798",
    "addr:housenumber":"31",
    "addr:postcode":"2798",
    "addr:street":"Victoria St",
    "iso:country":"AU",
    "sg:address":"31 Victoria St",
    "sg:city":"Millthorpe",
    "sg:classifiers":[
        {
            "category":"Autos & Motor Vehicles",
            "subcategory":"Fuel & Gas Station",
            "type":"Retail Goods"
        }
    ],
    "sg:phone":"+61 2 6366 3287",
    "sg:postcode":"2798",
    "sg:province":"NSW",
    "wof:name":"Millthorpe Motors",
    "wof:placetype":"venue"
},
  "geometry": {"coordinates":[149.184524536,-33.4460411072],"type":"Point"}
}