{
  "type": "Feature",
  "properties": {
    "addr:full":"13 Nicol St Proserpine QLD 4800",
    "addr:housenumber":"13",
    "addr:postcode":"4800",
    "addr:street":"Nicol St",
    "iso:country":"AU",
    "sg:address":"13 Nicol St",
    "sg:city":"Proserpine",
    "sg:classifiers":[
        {
            "category":"Building & Trades",
            "subcategory":"Construction",
            "type":"Services"
        }
    ],
    "sg:phone":"+61 7 4945 1127",
    "sg:postcode":"4800",
    "sg:province":"QLD",
    "sg:tags":[
        "earth",
        "excavating",
        "moving",
        "contractor"
    ],
    "wof:name":"Humphries & Sons",
    "wof:placetype":"venue"
},
  "geometry": {"coordinates":[148.573486328,-20.4052963257],"type":"Point"}
}