{
  "type": "Feature",
  "properties": {
    "addr:full":"20 Gwynne St Richmond VIC 3121",
    "addr:housenumber":"20",
    "addr:postcode":"3121",
    "addr:street":"Gwynne St",
    "iso:country":"AU",
    "sg:address":"20 Gwynne St",
    "sg:city":"Richmond",
    "sg:classifiers":[
        {
            "category":"Home & Garden",
            "subcategory":"Building Materials",
            "type":"Retail Goods"
        }
    ],
    "sg:phone":"+61 3 9429 2557",
    "sg:postcode":"3121",
    "sg:province":"VIC",
    "sg:tags":[
        "merchant",
        "glass",
        "glazier"
    ],
    "wof:name":"Creative Shower Screens",
    "wof:placetype":"venue"
},
  "geometry": {"coordinates":[144.99316406200001,-37.8274230957],"type":"Point"}
}