{
  "type": "Feature",
  "properties": {
    "iso:country":"AU",
    "sg:address":"PO Box 49",
    "sg:city":"Koroit",
    "sg:classifiers":[
        {
            "category":"Professional",
            "type":"Services"
        }
    ],
    "sg:phone":"+61 418 521 086",
    "sg:postcode":"3282",
    "sg:province":"VIC",
    "sg:tags":[
        "quality",
        "assurance"
    ],
    "wof:name":"Colin Supple & Associates Pty Ltd",
    "wof:placetype":"venue"
},
  "geometry": {"coordinates":[142.370193481,-38.2380409241],"type":"Point"}
}