{
  "type": "Feature",
  "properties": {
    "addr:full":"85 Majors Bay Rd Concord NSW 2137",
    "addr:housenumber":"85",
    "addr:postcode":"2137",
    "addr:street":"Majors Bay Rd",
    "iso:country":"AU",
    "sg:address":"85 Majors Bay Rd",
    "sg:city":"Concord",
    "sg:classifiers":[
        {
            "category":"Food & Beverages",
            "subcategory":"Bakery",
            "type":"Retail Goods"
        }
    ],
    "sg:phone":"+61 2 9743 5194",
    "sg:postcode":"2137",
    "sg:province":"NSW",
    "sg:tags":[
        "baker"
    ],
    "wof:name":"Sunflower Hot Bread",
    "wof:placetype":"venue"
},
  "geometry": {"coordinates":[151.103317261,-33.8554229736],"type":"Point"}
}