{
  "type": "Feature",
  "properties": {
    "iso:country":"AU",
    "sg:address":"535 Boat Harbour Drv",
    "sg:city":"Torquay",
    "sg:classifiers":[
        {
            "category":"Building & Trades",
            "subcategory":"Construction",
            "type":"Services"
        }
    ],
    "sg:phone":"+61 7 4125 2300",
    "sg:postcode":"4655",
    "sg:province":"QLD",
    "sg:tags":[
        "fencing",
        "contractor"
    ],
    "wof:name":"Universal Fencing World",
    "wof:placetype":"venue"
},
  "geometry": {"coordinates":[152.874527,-25.290947],"type":"Point"}
}