{
  "type": "Feature",
  "properties": {
    "addr:full":"59 Plummer Rd Mentone VIC 3194",
    "addr:housenumber":"59",
    "addr:postcode":"3194",
    "addr:street":"Plummer Rd",
    "iso:country":"AU",
    "sg:address":"59 Plummer Rd",
    "sg:city":"Mentone",
    "sg:classifiers":[
        {
            "category":"Building & Trades",
            "subcategory":"Construction",
            "type":"Services"
        }
    ],
    "sg:phone":"+61 409 862 030",
    "sg:postcode":"3194",
    "sg:province":"VIC",
    "sg:tags":[
        "fencing",
        "contractor"
    ],
    "wof:name":"Upfront Fencing",
    "wof:placetype":"venue"
},
  "geometry": {"coordinates":[145.058227539,-37.9821357727],"type":"Point"}
}