{
  "type": "Feature",
  "properties": {
    "iso:country":"AU",
    "sg:address":"11 Murphy St",
    "sg:city":"Invermay",
    "sg:classifiers":[
        {
            "category":"Retail",
            "subcategory":"Auto Repair",
            "type":"Services"
        }
    ],
    "sg:phone":"+61 3 6334 4332",
    "sg:postcode":"7248",
    "sg:province":"TAS",
    "sg:tags":[
        "hire",
        "go-kart"
    ],
    "wof:name":"Kart Magic Entertainment Centre",
    "wof:placetype":"venue"
},
  "geometry": {"coordinates":[147.12550354000001,-41.4259109497],"type":"Point"}
}