{
  "type": "Feature",
  "properties": {
    "addr:full":"PO Box 5042 Empire Bay NSW 2257",
    "addr:postcode":"2257",
    "iso:country":"AU",
    "sg:address":"PO Box 5042",
    "sg:city":"Empire Bay",
    "sg:classifiers":[
        {
            "category":"Professional",
            "subcategory":"Detective & Security Services",
            "type":"Services"
        }
    ],
    "sg:phone":"+61 2 4369 1793",
    "sg:postcode":"2257",
    "sg:province":"NSW",
    "sg:tags":[
        "consultant",
        "system"
    ],
    "wof:name":"Floyd Electrical Contracting",
    "wof:placetype":"venue"
},
  "geometry": {"coordinates":[151.36109924300001,-33.4996299744],"type":"Point"}
}