{
  "type": "Feature",
  "properties": {
    "addr:full":"1304 Samford Rd Ferny Grove QLD 4055",
    "addr:housenumber":"1304",
    "addr:postcode":"4055",
    "addr:street":"Samford Rd",
    "iso:country":"AU",
    "sg:address":"1304 Samford Rd",
    "sg:city":"Ferny Grove",
    "sg:classifiers":[
        {
            "category":"Health Services",
            "subcategory":"Dentist",
            "type":"Services"
        }
    ],
    "sg:phone":"+61 7 3351 5333",
    "sg:postcode":"4055",
    "sg:province":"QLD",
    "wof:name":"A.J. Sheppard Dental",
    "wof:placetype":"venue"
},
  "geometry": {"coordinates":[152.93768310600001,-27.402633667],"type":"Point"}
}