{
  "type": "Feature",
  "properties": {
    "addr:full":"41 Chapel St Glenorchy TAS 7010",
    "addr:housenumber":"41",
    "addr:postcode":"7010",
    "addr:street":"Chapel St",
    "iso:country":"AU",
    "sg:address":"41 Chapel St",
    "sg:city":"Glenorchy",
    "sg:classifiers":[
        {
            "category":"Home & Garden",
            "subcategory":"Household Appliances",
            "type":"Retail Goods"
        }
    ],
    "sg:phone":"+61 3 6274 1111",
    "sg:postcode":"7010",
    "sg:province":"TAS",
    "sg:tags":[
        "heating",
        "system"
    ],
    "wof:name":"Southern Air Refrigeration",
    "wof:placetype":"venue"
},
  "geometry": {"coordinates":[147.26828002900001,-42.8342018127],"type":"Point"}
}