{
  "type": "Feature",
  "properties": {
    "addr:full":"190 Abercrombie St Chippendale NSW 2008",
    "addr:housenumber":"190",
    "addr:postcode":"2008",
    "addr:street":"Abercrombie St",
    "iso:country":"AU",
    "sg:address":"190 Abercrombie St",
    "sg:city":"Chippendale",
    "sg:classifiers":[
        {
            "category":"Shopping",
            "subcategory":"Stationery & Office Supplies",
            "type":"Retail Goods"
        }
    ],
    "sg:phone":"+61 2 9699 6993",
    "sg:postcode":"2008",
    "sg:province":"NSW",
    "sg:tags":[
        "equipment",
        "display",
        "exhibition"
    ],
    "wof:name":"Exhibitionism Pty Ltd",
    "wof:placetype":"venue"
},
  "geometry": {"coordinates":[151.19789123499999,-33.8899497986],"type":"Point"}
}