{
  "type": "Feature",
  "properties": {
    "iso:country":"AU",
    "sg:address":"418 Payneham Rd",
    "sg:city":"Glynde",
    "sg:classifiers":[
        {
            "category":"Health Services",
            "subcategory":"Doctor",
            "type":"Services"
        }
    ],
    "sg:phone":"+61 8 8337 1222",
    "sg:postcode":"5070",
    "sg:province":"SA",
    "sg:tags":[
        "medical",
        "practitioner"
    ],
    "wof:name":"Agrawal Surendra",
    "wof:placetype":"venue"
},
  "geometry": {"coordinates":[138.648895264,-34.8926124573],"type":"Point"}
}