{
  "type": "Feature",
  "properties": {
    "addr:full":"328 Aberdeen St West Perth WA 6005",
    "addr:housenumber":"328",
    "addr:postcode":"6005",
    "addr:street":"Aberdeen St",
    "iso:country":"AU",
    "sg:address":"328 Aberdeen St",
    "sg:city":"West Perth",
    "sg:classifiers":[
        {
            "category":"Professional",
            "subcategory":"Accounting & Tax Preparation",
            "type":"Services"
        }
    ],
    "sg:phone":"+61 8 9227 6022",
    "sg:postcode":"6005",
    "sg:province":"WA",
    "sg:tags":[
        "accountant",
        "auditor"
    ],
    "wof:name":"D.A.M. Bookkeeping & Accounting Services",
    "wof:placetype":"venue"
},
  "geometry": {"coordinates":[115.853843689,-31.9441585541],"type":"Point"}
}