{
  "type": "Feature",
  "properties": {
    "iso:country":"AU",
    "sg:address":"95 Leaver St",
    "sg:city":"Yenda",
    "sg:classifiers":[
        {
            "category":"Manufacturing",
            "subcategory":"Food",
            "type":"Manufacturing & Wholesale Goods"
        }
    ],
    "sg:phone":"+61 2 6968 1484",
    "sg:postcode":"2681",
    "sg:province":"NSW",
    "sg:tags":[
        "function",
        "catering"
    ],
    "wof:name":"In Bocca Catering",
    "wof:placetype":"venue"
},
  "geometry": {"coordinates":[146.194305,-34.253613],"type":"Point"}
}