{
  "type": "Feature",
  "properties": {
    "addr:full":"11 Cleeland Rd Oakleigh South VIC 3167",
    "addr:housenumber":"11",
    "addr:postcode":"3167",
    "addr:street":"Cleeland Rd",
    "iso:country":"AU",
    "sg:address":"11 Cleeland Rd",
    "sg:city":"Oakleigh South",
    "sg:classifiers":[
        {
            "category":"Shopping",
            "subcategory":"Stationery & Office Supplies",
            "type":"Retail Goods"
        }
    ],
    "sg:phone":"+61 3 9544 9777",
    "sg:postcode":"3167",
    "sg:province":"VIC",
    "sg:tags":[
        "packaging",
        "material"
    ],
    "wof:name":"Cryovac Shrink Film",
    "wof:placetype":"venue"
},
  "geometry": {"coordinates":[145.09556579599999,-37.930683136],"type":"Point"}
}