{
  "type": "Feature",
  "properties": {
    "iso:country":"AU",
    "sg:address":"48 Nyah Rd",
    "sg:city":"Swan Hill",
    "sg:classifiers":[
        {
            "category":"Manufacturing",
            "subcategory":"Paper Products",
            "type":"Manufacturing & Wholesale Goods"
        }
    ],
    "sg:phone":"+61 3 5032 1694",
    "sg:postcode":"3585",
    "sg:province":"NSW",
    "sg:tags":[
        "bag"
    ],
    "wof:name":"Glens Paper Supplies",
    "wof:placetype":"venue"
},
  "geometry": {"coordinates":[143.55452,-35.330639],"type":"Point"}
}