{
  "type": "Feature",
  "properties": {
    "addr:full":"1093 Old Princes Hwy Engadine NSW 2233",
    "addr:housenumber":"1093",
    "addr:postcode":"2233",
    "addr:street":"Old Princes Hwy",
    "iso:country":"AU",
    "sg:address":"1093 Old Princes Hwy",
    "sg:city":"Engadine",
    "sg:classifiers":[
        {
            "category":"Health Services",
            "subcategory":"Doctor",
            "type":"Services"
        }
    ],
    "sg:phone":"+61 2 9520 8932",
    "sg:postcode":"2233",
    "sg:province":"NSW",
    "sg:tags":[
        "medical",
        "practitioner"
    ],
    "wof:name":"Hampson Sugerman Macquarie Pathology",
    "wof:placetype":"venue"
},
  "geometry": {"coordinates":[151.01184082,-34.0663871765],"type":"Point"}
}