{
  "type": "Feature",
  "properties": {
    "addr:full":"PO Box 714 Archerfield QLD 4108",
    "addr:postcode":"4108",
    "iso:country":"AU",
    "sg:address":"PO Box 714",
    "sg:city":"Archerfield",
    "sg:classifiers":[
        {
            "category":"Wholesale",
            "subcategory":"Machinery & Supplies",
            "type":"Manufacturing & Wholesale Goods"
        }
    ],
    "sg:phone":"+61 7 3875 1175",
    "sg:postcode":"4108",
    "sg:province":"QLD",
    "sg:tags":[
        "engine",
        "petrol"
    ],
    "wof:name":"Briggs & Stratton",
    "wof:placetype":"venue"
},
  "geometry": {"coordinates":[153.01492309599999,-27.5681705475],"type":"Point"}
}