{
  "type": "Feature",
  "properties": {
    "addr:full":"Suit 2 Level 15 275 Alfred St North Sydney NSW 2060",
    "addr:housenumber":"15 275",
    "addr:postcode":"2060",
    "addr:street":"Alfred St",
    "iso:country":"AU",
    "sg:address":"Suit 2 Level 15 275 Alfred St",
    "sg:city":"North Sydney",
    "sg:classifiers":[
        {
            "category":"Professional",
            "subcategory":"Art Services",
            "type":"Services"
        }
    ],
    "sg:phone":"+61 2 9954 3454",
    "sg:postcode":"2060",
    "sg:province":"NSW",
    "sg:tags":[
        "graphic",
        "designer"
    ],
    "wof:name":"Symbiation Pty Ltd",
    "wof:placetype":"venue"
},
  "geometry": {"coordinates":[151.21134948700001,-33.8402252197],"type":"Point"}
}