{
  "type": "Feature",
  "properties": {
    "addr:full":"Shop 3 9 McEwan St Riverview QLD 4303",
    "addr:housenumber":"shop;9",
    "addr:postcode":"4303",
    "addr:street":"Mcewan St",
    "iso:country":"AU",
    "sg:address":"Shop 3 9 McEwan St",
    "sg:city":"Riverview",
    "sg:classifiers":[
        {
            "category":"Fast Food",
            "type":"Food & Drink"
        }
    ],
    "sg:phone":"+61 7 3282 4339",
    "sg:postcode":"4303",
    "sg:province":"QLD",
    "sg:tags":[
        "away",
        "take"
    ],
    "wof:name":"Zsaskia",
    "wof:placetype":"venue"
},
  "geometry": {"coordinates":[152.848754883,-27.5959072113],"type":"Point"}
}