{
  "type": "Feature",
  "properties": {
    "addr:full":"43 Aulberry Pde Leeming WA 6149",
    "addr:housenumber":"43",
    "addr:postcode":"6149",
    "addr:street":"Aulberry Pde",
    "iso:country":"AU",
    "sg:address":"43 Aulberry Pde",
    "sg:city":"Leeming",
    "sg:classifiers":[
        {
            "category":"Communications",
            "subcategory":"Film & Video Production",
            "type":"Services"
        }
    ],
    "sg:phone":"+61 8 9312 2992",
    "sg:postcode":"6149",
    "sg:province":"WA",
    "sg:tags":[
        "print",
        "poster",
        "wholesale",
        "pictures"
    ],
    "wof:name":"Graphico Agencies",
    "wof:placetype":"venue"
},
  "geometry": {"coordinates":[115.851929,-32.074345],"type":"Point"}
}