{
  "type": "Feature",
  "properties": {
    "addr:full":"14 hastings St Noosa Heads QLD 4567",
    "addr:housenumber":"14",
    "addr:postcode":"4567",
    "addr:street":"Hastings St",
    "iso:country":"AU",
    "sg:address":"14 hastings St",
    "sg:city":"Noosa Heads",
    "sg:classifiers":[
        {
            "category":"Shopping",
            "subcategory":"Clothing, Apparel, & Fashions",
            "type":"Retail Goods"
        }
    ],
    "sg:phone":"+61 7 5447 4176",
    "sg:postcode":"4567",
    "sg:province":"QLD",
    "sg:tags":[
        "lady",
        "wear"
    ],
    "wof:name":"Witchery",
    "wof:placetype":"venue"
},
  "geometry": {"coordinates":[153.088165283,-26.3864040375],"type":"Point"}
}