{
  "type": "Feature",
  "properties": {
    "addr:full":"124 Steel St Capalaba QLD 4157",
    "addr:housenumber":"124",
    "addr:postcode":"4157",
    "addr:street":"Steel St",
    "iso:country":"AU",
    "sg:address":"124 Steel St",
    "sg:city":"Capalaba",
    "sg:classifiers":[
        {
            "category":"Structure",
            "subcategory":"Building",
            "type":"Public Place"
        }
    ],
    "sg:phone":"+61 1800 244 441",
    "sg:postcode":"4157",
    "sg:province":"QLD",
    "sg:tags":[
        "sail",
        "shade"
    ],
    "wof:name":"Instant Up Marquee Systems",
    "wof:placetype":"venue"
},
  "geometry": {"coordinates":[153.20492553700001,-27.5335216522],"type":"Point"}
}