{
  "type": "Feature",
  "properties": {
    "addr:full":"Suite 1 , Level 1 Jewellstown Plz Jewells NSW 2280",
    "addr:postcode":"2280",
    "addr:street":"Jewellstown Plz",
    "iso:country":"AU",
    "sg:address":"Suite 1",
    "sg:city":", Level 1 Jewellstown Plz Jewells",
    "sg:classifiers":[
        {
            "category":"Professional",
            "subcategory":"Testing Lab",
            "type":"Services"
        }
    ],
    "sg:phone":"+61 2 4947 1289",
    "sg:postcode":"2280",
    "sg:province":"NSW",
    "sg:tags":[
        "inspection"
    ],
    "wof:name":"HSB Australia",
    "wof:placetype":"venue"
},
  "geometry": {"coordinates":[151.68318176299999,-33.0133895874],"type":"Point"}
}