{
  "type": "Feature",
  "properties": {
    "iso:country":"AU",
    "sg:address":"Scherger St",
    "sg:city":"Moorooka",
    "sg:classifiers":[
        {
            "category":"Home & Garden",
            "subcategory":"Building Materials",
            "type":"Retail Goods"
        }
    ],
    "sg:phone":"+61 1800 202 606",
    "sg:postcode":"4105",
    "sg:province":"QLD",
    "sg:tags":[
        "lawn",
        "cutting",
        "maintenance"
    ],
    "wof:name":"Greenvital",
    "wof:placetype":"venue"
},
  "geometry": {"coordinates":[153.030487061,-27.5375518799],"type":"Point"}
}