{
  "type": "Feature",
  "properties": {
    "iso:country":"AU",
    "sg:address":"Unit 6 58 Islander Rd",
    "sg:city":"Pialba",
    "sg:classifiers":[
        {
            "category":"Utilities",
            "type":"Services"
        }
    ],
    "sg:phone":"+61 7 4128 1126",
    "sg:postcode":"4655",
    "sg:province":"QLD",
    "sg:tags":[
        "equipment",
        "towing"
    ],
    "wof:name":"Robins Mechanical Services",
    "wof:placetype":"venue"
},
  "geometry": {"coordinates":[152.837357,-25.291656],"type":"Point"}
}