{
  "type": "Feature",
  "properties": {
    "addr:full":"Walker St Townsville QLD 4810",
    "addr:postcode":"4810",
    "addr:street":"Walker St",
    "iso:country":"AU",
    "sg:address":"Walker St",
    "sg:city":"Townsville",
    "sg:classifiers":[
        {
            "category":"Professional",
            "subcategory":"Employment Agencies",
            "type":"Services"
        }
    ],
    "sg:phone":"+61 13 19 01",
    "sg:postcode":"4810",
    "sg:province":"QLD",
    "wof:name":"Defence Force Recruiting Centre",
    "wof:placetype":"venue"
},
  "geometry": {"coordinates":[146.807175,-19.265556],"type":"Point"}
}