{
  "type": "Feature",
  "properties": {
    "addr:full":"17 Irrewillipe Rd Elliminyt VIC 3249",
    "addr:housenumber":"17",
    "addr:postcode":"3249",
    "addr:street":"Irrewillipe Rd",
    "iso:country":"AU",
    "sg:address":"17 Irrewillipe Rd",
    "sg:city":"Elliminyt",
    "sg:classifiers":[
        {
            "category":"Home & Garden",
            "subcategory":"Building Materials",
            "type":"Retail Goods"
        }
    ],
    "sg:phone":"+61 405 523 676",
    "sg:postcode":"3249",
    "sg:province":"VIC",
    "sg:tags":[
        "lawn",
        "cutting",
        "maintenance"
    ],
    "wof:name":"Adam Browns Home & Garden Maintenance Pty Ltd",
    "wof:placetype":"venue"
},
  "geometry": {"coordinates":[143.37001037600001,-38.415802002],"type":"Point"}
}