{
  "type": "Feature",
  "properties": {
    "iso:country":"AU",
    "sg:address":"19 Mathew St",
    "sg:city":"Nambour",
    "sg:classifiers":[
        {
            "category":"Health Services",
            "subcategory":"Dentist",
            "type":"Services"
        }
    ],
    "sg:phone":"+61 7 5441 3583",
    "sg:postcode":"4560",
    "sg:province":"QLD",
    "wof:name":"Ray Robinson",
    "wof:placetype":"venue"
},
  "geometry": {"coordinates":[152.96160888700001,-26.6238937378],"type":"Point"}
}