{
  "type": "Feature",
  "properties": {
    "iso:country":"AU",
    "sg:address":"20 Laurel St",
    "sg:city":"Mullaloo",
    "sg:classifiers":[
        {
            "category":"Professional",
            "subcategory":"Employment Agencies",
            "type":"Services"
        }
    ],
    "sg:phone":"+61 8 9307 3515",
    "sg:postcode":"6027",
    "sg:province":"WA",
    "sg:tags":[
        "provider",
        "internet"
    ],
    "wof:name":"Native Web Design",
    "wof:placetype":"venue"
},
  "geometry": {"coordinates":[115.738243103,-31.7842178345],"type":"Point"}
}