{
  "type": "Feature",
  "properties": {
    "addr:full":"25 Argon St Sumner Park QLD 4074",
    "addr:housenumber":"25",
    "addr:postcode":"4074",
    "addr:street":"Argon St",
    "iso:country":"AU",
    "sg:address":"25 Argon St",
    "sg:city":"Sumner Park",
    "sg:classifiers":[
        {
            "category":"Building & Trades",
            "subcategory":"Landscaping Services",
            "type":"Services"
        }
    ],
    "sg:phone":"+61 7 3376 7544",
    "sg:postcode":"4074",
    "sg:province":"QLD",
    "sg:tags":[
        "inspection"
    ],
    "wof:name":"Sommer & Staff Constructions Pty Ltd",
    "wof:placetype":"venue"
},
  "geometry": {"coordinates":[152.933425903,-27.562625885],"type":"Point"}
}