{
  "type": "Feature",
  "properties": {
    "iso:country":"AU",
    "sg:address":"516 Pacific Hwy",
    "sg:city":"Belmont",
    "sg:classifiers":[
        {
            "category":"Health Services",
            "subcategory":"Chiropractor",
            "type":"Services"
        }
    ],
    "sg:phone":"+61 2 4945 8688",
    "sg:postcode":"2280",
    "sg:province":"NSW",
    "wof:name":"Ingall Klara",
    "wof:placetype":"venue"
},
  "geometry": {"coordinates":[151.660766602,-33.0339813232],"type":"Point"}
}