{
  "type": "Feature",
  "properties": {
    "addr:full":"McLaren St Hughenden QLD 4821",
    "addr:postcode":"4821",
    "addr:street":"Mclaren St",
    "iso:country":"AU",
    "sg:address":"McLaren St",
    "sg:city":"Hughenden",
    "sg:classifiers":[
        {
            "category":"Education",
            "subcategory":"School",
            "type":"Public Place"
        }
    ],
    "sg:phone":"+61 7 4741 1599",
    "sg:postcode":"4821",
    "sg:province":"QLD",
    "sg:tags":[
        "state",
        "except",
        "nsw"
    ],
    "wof:name":"Hughenden Preschool",
    "wof:placetype":"venue"
},
  "geometry": {"coordinates":[144.19218444800001,-20.8510131836],"type":"Point"}
}