{
  "type": "Feature",
  "properties": {
    "addr:full":"14 Annetta Crt St Albans VIC 3021",
    "addr:housenumber":"14",
    "addr:postcode":"3021",
    "addr:street":"Annetta Crt",
    "iso:country":"AU",
    "sg:address":"14 Annetta Crt",
    "sg:city":"St Albans",
    "sg:classifiers":[
        {
            "category":"Building & Trades",
            "subcategory":"Construction",
            "type":"Services"
        }
    ],
    "sg:phone":"+61 3 9367 7532",
    "sg:postcode":"3021",
    "sg:province":"VIC",
    "sg:tags":[
        "renovation",
        "alterations",
        "extension",
        "contractor"
    ],
    "wof:name":"Urban Carpentry",
    "wof:placetype":"venue"
},
  "geometry": {"coordinates":[144.77203399999999,-37.743935],"type":"Point"}
}