{
  "type": "Feature",
  "properties": {
    "addr:full":"6- 8 Attercliffe Ave Pascoe Vale VIC 3044",
    "addr:housenumber":"8",
    "addr:postcode":"3044",
    "addr:street":"Attercliffe Ave",
    "iso:country":"AU",
    "sg:address":"6- 8 Attercliffe Ave",
    "sg:city":"Pascoe Vale",
    "sg:classifiers":[
        {
            "category":"Wholesale",
            "subcategory":"Machinery & Supplies",
            "type":"Manufacturing & Wholesale Goods"
        }
    ],
    "sg:phone":"+61 3 9354 3634",
    "sg:postcode":"3044",
    "sg:province":"VIC",
    "sg:tags":[
        "equipment",
        "system",
        "elevating",
        "conveying"
    ],
    "wof:name":"Screw Conveyor Engineering Pty Ltd",
    "wof:placetype":"venue"
},
  "geometry": {"coordinates":[144.94813537600001,-37.7292251587],"type":"Point"}
}