{
  "type": "Feature",
  "properties": {
    "addr:full":"The Well At Camberwell The Well at Camberwell 793 Burke Rd Camberwell VIC 3124",
    "addr:housenumber":"793",
    "addr:postcode":"3124",
    "addr:street":"Burke Rd",
    "iso:country":"AU",
    "sg:address":"The Well At Camberwell The Well at Camberwell 793 Burke Rd",
    "sg:city":"Camberwell",
    "sg:classifiers":[
        {
            "category":"Professional",
            "subcategory":"Business Services",
            "type":"Services"
        }
    ],
    "sg:phone":"+61 3 9813 2707",
    "sg:postcode":"3124",
    "sg:province":"VIC",
    "sg:tags":[
        "processing",
        "word"
    ],
    "wof:name":"Camberwell Secretariat",
    "wof:placetype":"venue"
},
  "geometry": {"coordinates":[145.05836486800001,-37.8261451721],"type":"Point"}
}