{
  "type": "Feature",
  "properties": {
    "addr:full":"838 Doncaster Rd Doncaster VIC 3108",
    "addr:housenumber":"838",
    "addr:postcode":"3108",
    "addr:street":"Doncaster Rd",
    "iso:country":"AU",
    "sg:address":"838 Doncaster Rd",
    "sg:city":"Doncaster",
    "sg:classifiers":[
        {
            "category":"Health Services",
            "subcategory":"Doctor",
            "type":"Services"
        }
    ],
    "sg:phone":"+61 3 9848 2255",
    "sg:postcode":"3108",
    "sg:province":"VIC",
    "sg:tags":[
        "medical",
        "practitioner"
    ],
    "wof:name":"Preston H",
    "wof:placetype":"venue"
},
  "geometry": {"coordinates":[145.14346313499999,-37.7871017456],"type":"Point"}
}