{
  "type": "Feature",
  "properties": {
    "addr:full":"29 Ipswich Rd Woolloongabba QLD 4102",
    "addr:housenumber":"29",
    "addr:postcode":"4102",
    "addr:street":"Ipswich Rd",
    "iso:country":"AU",
    "sg:address":"29 Ipswich Rd",
    "sg:city":"Woolloongabba",
    "sg:classifiers":[
        {
            "category":"Autos & Motor Vehicles",
            "subcategory":"Auto Supplies",
            "type":"Retail Goods"
        }
    ],
    "sg:phone":"+61 7 3391 8588",
    "sg:postcode":"4102",
    "sg:province":"QLD",
    "sg:tags":[
        "accessory"
    ],
    "wof:name":"Goodtime Products",
    "wof:placetype":"venue"
},
  "geometry": {"coordinates":[153.035842895,-27.4873962402],"type":"Point"}
}