{
  "type": "Feature",
  "properties": {
    "iso:country":"AU",
    "sg:address":"Shop 8 107 Latrobe Tce",
    "sg:city":"Paddington",
    "sg:classifiers":[
        {
            "category":"Fast Food",
            "type":"Food & Drink"
        }
    ],
    "sg:phone":"+61 7 3876 5800",
    "sg:postcode":"4064",
    "sg:province":"QLD",
    "sg:tags":[
        "away",
        "take"
    ],
    "wof:name":"Poppy Thai Takeaway",
    "wof:placetype":"venue"
},
  "geometry": {"coordinates":[152.997756958,-27.4589214325],"type":"Point"}
}