{
  "type": "Feature",
  "properties": {
    "addr:full":"PO Box 1170 Bongaree QLD 4507",
    "addr:postcode":"4507",
    "iso:country":"AU",
    "sg:address":"PO Box 1170",
    "sg:city":"Bongaree",
    "sg:classifiers":[
        {
            "category":"Professional",
            "type":"Services"
        }
    ],
    "sg:phone":"+61 7 3408 3131",
    "sg:postcode":"4507",
    "sg:province":"QLD",
    "sg:tags":[
        "transport"
    ],
    "wof:name":"Bellmere Haulage & Contracting",
    "wof:placetype":"venue"
},
  "geometry": {"coordinates":[153.1668396,-27.0792503357],"type":"Point"}
}