{
  "type": "Feature",
  "properties": {
    "addr:full":"80 Hamilton St Gisborne VIC 3437",
    "addr:housenumber":"80",
    "addr:postcode":"3437",
    "addr:street":"Hamilton St",
    "iso:country":"AU",
    "sg:address":"80 Hamilton St",
    "sg:city":"Gisborne",
    "sg:classifiers":[
        {
            "category":"Health Services",
            "subcategory":"Doctor",
            "type":"Services"
        }
    ],
    "sg:phone":"+61 3 5428 2211",
    "sg:postcode":"3437",
    "sg:province":"VIC",
    "sg:tags":[
        "medical",
        "practitioner"
    ],
    "wof:name":"Conron David",
    "wof:placetype":"venue"
},
  "geometry": {"coordinates":[144.58340454099999,-37.4867744446],"type":"Point"}
}