{
  "type": "Feature",
  "properties": {
    "iso:country":"AU",
    "sg:address":"75 Bold St",
    "sg:city":"Laurieton",
    "sg:classifiers":[
        {
            "category":"Organizations",
            "subcategory":"Membership Organization",
            "type":"Services"
        }
    ],
    "sg:phone":"+61 2 6559 9048",
    "sg:postcode":"2443",
    "sg:province":"NSW",
    "sg:tags":[
        "railway"
    ],
    "wof:name":"TravelScene American Express",
    "wof:placetype":"venue"
},
  "geometry": {"coordinates":[152.796875,-31.649132],"type":"Point"}
}