{
  "type": "Feature",
  "properties": {
    "addr:full":"Rayner St Dalwallinu WA 6609",
    "addr:postcode":"6609",
    "addr:street":"Rayner St",
    "iso:country":"AU",
    "sg:address":"Rayner St",
    "sg:city":"Dalwallinu",
    "sg:classifiers":[
        {
            "category":"Shopping",
            "type":"Retail Goods"
        }
    ],
    "sg:phone":"+61 8 9661 2000",
    "sg:postcode":"6609",
    "sg:province":"WA",
    "sg:tags":[
        "agent",
        "stock"
    ],
    "wof:name":"Elders Limited",
    "wof:placetype":"venue"
},
  "geometry": {"coordinates":[116.662139893,-30.2780990601],"type":"Point"}
}