{
  "type": "Feature",
  "properties": {
    "addr:full":"Freemantle Rd Bathurst NSW 2795",
    "addr:postcode":"2795",
    "addr:street":"Freemantle Rd",
    "iso:country":"AU",
    "sg:address":"Freemantle Rd",
    "sg:city":"Bathurst",
    "sg:classifiers":[
        {
            "category":"Home & Garden",
            "subcategory":"Building Materials",
            "type":"Retail Goods"
        }
    ],
    "sg:phone":"+61 2 6337 4224",
    "sg:postcode":"2795",
    "sg:province":"NSW",
    "sg:tags":[
        "fencing"
    ],
    "wof:name":"A.1.1 Services",
    "wof:placetype":"venue"
},
  "geometry": {"coordinates":[149.53457641599999,-33.3719291687],"type":"Point"}
}