{
  "type": "Feature",
  "properties": {
    "addr:full":"14 Ferndale Ave Upwey VIC 3158",
    "addr:housenumber":"14",
    "addr:postcode":"3158",
    "addr:street":"Ferndale Ave",
    "iso:country":"AU",
    "sg:address":"14 Ferndale Ave",
    "sg:city":"Upwey",
    "sg:classifiers":[
        {
            "category":"Industrial Area",
            "type":"Public Place"
        }
    ],
    "sg:phone":"+61 3 9754 2616",
    "sg:postcode":"3158",
    "sg:province":"VIC",
    "sg:tags":[
        "protective",
        "clothing"
    ],
    "wof:name":"Team Enterprise Australia",
    "wof:placetype":"venue"
},
  "geometry": {"coordinates":[145.33119201700001,-37.9171447754],"type":"Point"}
}