{
  "type": "Feature",
  "properties": {
    "addr:full":"295 High St Penrith NSW 2750",
    "addr:housenumber":"295",
    "addr:postcode":"2750",
    "addr:street":"High St",
    "iso:country":"AU",
    "sg:address":"295 High St",
    "sg:city":"Penrith",
    "sg:classifiers":[
        {
            "category":"Health Services",
            "subcategory":"Doctor",
            "type":"Services"
        }
    ],
    "sg:phone":"+61 2 4731 1811",
    "sg:postcode":"2750",
    "sg:province":"NSW",
    "sg:tags":[
        "medical",
        "practitioner"
    ],
    "wof:name":"Liew Simon Dr",
    "wof:placetype":"venue"
},
  "geometry": {"coordinates":[150.91560363799999,-33.894733429],"type":"Point"}
}