{
  "type": "Feature",
  "properties": {
    "addr:full":"Mc Edward St Birdwoodton VIC 3505",
    "addr:postcode":"3505",
    "addr:street":"Mc Edward St",
    "iso:country":"AU",
    "sg:address":"Mc Edward St",
    "sg:city":"Birdwoodton",
    "sg:classifiers":[
        {
            "category":"Sports & Exercise",
            "subcategory":"Golf",
            "type":"Entertainment"
        }
    ],
    "sg:phone":"+61 3 5025 6421",
    "sg:postcode":"3505",
    "sg:province":"VIC",
    "sg:tags":[
        "club"
    ],
    "wof:name":"Merbein Golf Club",
    "wof:placetype":"venue"
},
  "geometry": {"coordinates":[142.08102417000001,-34.1997756958],"type":"Point"}
}