{
  "type": "Feature",
  "properties": {
    "iso:country":"AU",
    "sg:address":"Unit 4 19 Rudloc Rd",
    "sg:city":"Morley",
    "sg:classifiers":[
        {
            "category":"Retail",
            "subcategory":"Auto Repair",
            "type":"Services"
        }
    ],
    "sg:phone":"+61 8 9276 9787",
    "sg:postcode":"6062",
    "sg:province":"WA",
    "sg:tags":[
        "repairer",
        "motor",
        "engineer"
    ],
    "wof:name":"Markham Motors",
    "wof:placetype":"venue"
},
  "geometry": {"coordinates":[115.89636993400001,-31.9019126892],"type":"Point"}
}