{
  "type": "Feature",
  "properties": {
    "addr:full":"PO Box 408 Margate QLD 4019",
    "addr:postcode":"4019",
    "iso:country":"AU",
    "sg:address":"PO Box 408",
    "sg:city":"Margate",
    "sg:classifiers":[
        {
            "category":"Professional",
            "subcategory":"Secretarial Services",
            "type":"Services"
        }
    ],
    "sg:phone":"+61 412 912 461",
    "sg:postcode":"4019",
    "sg:province":"QLD",
    "sg:tags":[
        "typing"
    ],
    "wof:name":"Admin On The Go",
    "wof:placetype":"venue"
},
  "geometry": {"coordinates":[153.099441528,-27.2423706055],"type":"Point"}
}