{
  "type": "Feature",
  "properties": {
    "iso:country":"AU",
    "sg:address":"36 Petterson Ave",
    "sg:city":"Kardinya",
    "sg:classifiers":[
        {
            "category":"Communications",
            "type":"Services"
        }
    ],
    "sg:phone":"+61 8 9331 2411",
    "sg:postcode":"6163",
    "sg:province":"WA",
    "sg:tags":[
        "equipment",
        "satellite"
    ],
    "wof:name":"A.A. Antenna Services",
    "wof:placetype":"venue"
},
  "geometry": {"coordinates":[115.806839,-32.069168],"type":"Point"}
}