{
  "type": "Feature",
  "properties": {
    "iso:country":"AU",
    "sg:address":"6/321-325 Abernethy Rd",
    "sg:city":"Belmont",
    "sg:classifiers":[
        {
            "category":"Health Services",
            "subcategory":"Doctor",
            "type":"Services"
        }
    ],
    "sg:phone":"+61 8 9277 2111",
    "sg:postcode":"6104",
    "sg:province":"WA",
    "sg:tags":[
        "medical",
        "practitioner"
    ],
    "wof:name":"Uniradiology",
    "wof:placetype":"venue"
},
  "geometry": {"coordinates":[115.937431335,-31.9632034302],"type":"Point"}
}