{
  "type": "Feature",
  "properties": {
    "addr:full":"4/ 6 Kularoo Drv Forster NSW 2428",
    "addr:housenumber":"/ 6",
    "addr:postcode":"2428",
    "addr:street":"Kularoo Drv",
    "iso:country":"AU",
    "sg:address":"4/ 6 Kularoo Drv",
    "sg:city":"Forster",
    "sg:classifiers":[
        {
            "category":"Banks & Credit Unions",
            "subcategory":"Investment Brokerage",
            "type":"Services"
        }
    ],
    "sg:phone":"+61 2 6555 8499",
    "sg:postcode":"2428",
    "sg:province":"NSW",
    "sg:tags":[
        "radiator",
        "motor"
    ],
    "wof:name":"Koolaz Radiator & Airconditioning Services",
    "wof:placetype":"venue"
},
  "geometry": {"coordinates":[152.514465,-32.194344],"type":"Point"}
}