{
  "type": "Feature",
  "properties": {
    "addr:full":"Cnr High Street & Barwon Heads Rd Belmont VIC 3216",
    "addr:postcode":"3216",
    "addr:street":"High Street & Barwon Heads Rd",
    "iso:country":"AU",
    "sg:address":"Cnr High Street & Barwon Heads Rd",
    "sg:city":"Belmont",
    "sg:classifiers":[
        {
            "category":"Ice Cream",
            "type":"Food & Drink"
        }
    ],
    "sg:phone":"+61 417 531 881",
    "sg:postcode":"3216",
    "sg:province":"VIC",
    "sg:tags":[
        "retail"
    ],
    "wof:name":"Wendy's Belmont",
    "wof:placetype":"venue"
},
  "geometry": {"coordinates":[144.342697144,-38.1750869751],"type":"Point"}
}