{
  "type": "Feature",
  "properties": {
    "iso:country":"AU",
    "sg:address":"45 Chapel St",
    "sg:city":"Fitzroy",
    "sg:classifiers":[
        {
            "category":"Shopping",
            "subcategory":"Party Supplies",
            "type":"Retail Goods"
        }
    ],
    "sg:phone":"+61 3 9417 7926",
    "sg:postcode":"3065",
    "sg:province":"VIC",
    "sg:tags":[
        "hire",
        "costume"
    ],
    "wof:name":"Laurel Frank Costume Maker",
    "wof:placetype":"venue"
},
  "geometry": {"coordinates":[144.98243713400001,-37.7992935181],"type":"Point"}
}