{
  "type": "Feature",
  "properties": {
    "addr:full":"92 Ocean Pde The Entrance NSW 2261",
    "addr:housenumber":"92",
    "addr:postcode":"2261",
    "addr:street":"Ocean Pde The",
    "iso:country":"AU",
    "sg:address":"92 Ocean Pde",
    "sg:city":"The Entrance",
    "sg:classifiers":[
        {
            "category":"Building & Trades",
            "subcategory":"Construction",
            "type":"Services"
        }
    ],
    "sg:phone":"+61 2 4332 5544",
    "sg:postcode":"2261",
    "sg:province":"NSW",
    "sg:tags":[
        "contractor"
    ],
    "wof:name":"Betta Homes Pty Ltd",
    "wof:placetype":"venue"
},
  "geometry": {"coordinates":[151.50271599999999,-33.350323],"type":"Point"}
}