{
  "type": "Feature",
  "properties": {
    "addr:full":"41 Malvern St Bayswater VIC 3153",
    "addr:housenumber":"41",
    "addr:postcode":"3153",
    "addr:street":"Malvern St",
    "iso:country":"AU",
    "sg:address":"41 Malvern St",
    "sg:city":"Bayswater",
    "sg:classifiers":[
        {
            "category":"Home & Garden",
            "subcategory":"Building Materials",
            "type":"Retail Goods"
        }
    ],
    "sg:phone":"+61 3 9729 2577",
    "sg:postcode":"3153",
    "sg:province":"VIC",
    "sg:tags":[
        "laminate",
        "laminated",
        "panel"
    ],
    "wof:name":"Kleverkamp Bros Post Formers",
    "wof:placetype":"venue"
},
  "geometry": {"coordinates":[145.276046753,-37.8432769775],"type":"Point"}
}