{
  "type": "Feature",
  "properties": {
    "iso:country":"AU",
    "sg:address":"Unit 19c/ 78 Gibson Ave",
    "sg:city":"Padstow",
    "sg:classifiers":[
        {
            "category":"Building & Trades",
            "subcategory":"Construction",
            "type":"Services"
        }
    ],
    "sg:phone":"+61 2 9773 6992",
    "sg:postcode":"2211",
    "sg:province":"NSW",
    "sg:tags":[
        "plasterboard",
        "plasterer",
        "fixer"
    ],
    "wof:name":"Regent Interiors Pty Ltd",
    "wof:placetype":"venue"
},
  "geometry": {"coordinates":[151.027893,-33.940811],"type":"Point"}
}