{
  "type": "Feature",
  "properties": {
    "addr:full":"3/ 37 East St Daylesford VIC 3460",
    "addr:housenumber":"/ 37",
    "addr:postcode":"3460",
    "addr:street":"East St",
    "iso:country":"AU",
    "sg:address":"3/ 37 East St",
    "sg:city":"Daylesford",
    "sg:classifiers":[
        {
            "category":"Shopping",
            "subcategory":"Stationery & Office Supplies",
            "type":"Retail Goods"
        }
    ],
    "sg:phone":"+61 418 476 316",
    "sg:postcode":"3460",
    "sg:province":"VIC",
    "sg:tags":[
        "equipment",
        "display",
        "exhibition"
    ],
    "wof:name":"Mi-fine",
    "wof:placetype":"venue"
},
  "geometry": {"coordinates":[144.155029297,-37.3466148376],"type":"Point"}
}