{
  "type": "Feature",
  "properties": {
    "iso:country":"AU",
    "sg:address":"35 James St",
    "sg:city":"Charlestown",
    "sg:classifiers":[
        {
            "category":"Banks & Credit Unions",
            "subcategory":"Atm",
            "type":"Services"
        }
    ],
    "sg:phone":"+61 2 4943 5435",
    "sg:postcode":"2290",
    "sg:province":"NSW",
    "sg:tags":[
        "shelf"
    ],
    "wof:name":"Bill Cupitts Companies",
    "wof:placetype":"venue"
},
  "geometry": {"coordinates":[151.697799683,-32.9690742493],"type":"Point"}
}