{
  "type": "Feature",
  "properties": {
    "addr:full":"124 Lamb St Murgon QLD 4605",
    "addr:housenumber":"124",
    "addr:postcode":"4605",
    "addr:street":"Lamb St",
    "iso:country":"AU",
    "sg:address":"124 Lamb St",
    "sg:city":"Murgon",
    "sg:classifiers":[
        {
            "category":"Autos & Motor Vehicles",
            "subcategory":"Fuel & Gas Station",
            "type":"Retail Goods"
        }
    ],
    "sg:phone":"+61 7 4168 1668",
    "sg:postcode":"4605",
    "sg:province":"QLD",
    "wof:name":"Murgon Tyre & Auto",
    "wof:placetype":"venue"
},
  "geometry": {"coordinates":[151.93920900000001,-26.240759],"type":"Point"}
}