{
  "type": "Feature",
  "properties": {
    "iso:country":"AU",
    "sg:address":"Shop 3/ 65 Willoughby Rd",
    "sg:city":"Crows Nest",
    "sg:classifiers":[
        {
            "category":"Personal",
            "subcategory":"Beauty Salon",
            "type":"Services"
        }
    ],
    "sg:phone":"+61 2 9436 3483",
    "sg:postcode":"2065",
    "sg:province":"NSW",
    "wof:name":"Mon Ami Ella Bache Skin Fitness Centre",
    "wof:placetype":"venue"
},
  "geometry": {"coordinates":[151.20103454599999,-33.8253669739],"type":"Point"}
}