{
  "type": "Feature",
  "properties": {
    "addr:full":"63 Eaton Pl Karama NT 0812",
    "addr:housenumber":"63",
    "addr:postcode":"nt 0812",
    "addr:street":"Eaton Pl",
    "iso:country":"AU",
    "sg:address":"63 Eaton Pl",
    "sg:city":"Karama",
    "sg:classifiers":[
        {
            "category":"Professional",
            "subcategory":"Engineering",
            "type":"Services"
        }
    ],
    "sg:phone":"+61 8 8927 9993",
    "sg:postcode":"0812",
    "sg:province":"NT",
    "sg:tags":[
        "civil",
        "engineer"
    ],
    "wof:name":"Territory Construction Services",
    "wof:placetype":"venue"
},
  "geometry": {"coordinates":[130.919556,-12.404822],"type":"Point"}
}