{
  "type": "Feature",
  "properties": {
    "addr:full":"24 Williamson Rd Ingleburn NSW 2565",
    "addr:housenumber":"24",
    "addr:postcode":"2565",
    "addr:street":"Williamson Rd",
    "iso:country":"AU",
    "sg:address":"24 Williamson Rd",
    "sg:city":"Ingleburn",
    "sg:classifiers":[
        {
            "category":"Home & Garden",
            "subcategory":"Furniture",
            "type":"Retail Goods"
        }
    ],
    "sg:phone":"+61 2 8796 6288",
    "sg:postcode":"2565",
    "sg:province":"NSW",
    "sg:tags":[
        "business"
    ],
    "wof:name":"Bosco Storage Solutions",
    "wof:placetype":"venue"
},
  "geometry": {"coordinates":[150.85626220699999,-33.9927368164],"type":"Point"}
}