{
  "type": "Feature",
  "properties": {
    "addr:full":"118 Mileham St Windsor NSW 2756",
    "addr:housenumber":"118",
    "addr:postcode":"2756",
    "addr:street":"Mileham St",
    "iso:country":"AU",
    "sg:address":"118 Mileham St",
    "sg:city":"Windsor",
    "sg:classifiers":[
        {
            "category":"Manufacturing",
            "subcategory":"Rubber & Plastics",
            "type":"Manufacturing & Wholesale Goods"
        }
    ],
    "sg:phone":"+61 2 4577 0700",
    "sg:postcode":"2756",
    "sg:province":"NSW",
    "sg:tags":[
        "wholesaler",
        "product",
        "mfrs"
    ],
    "wof:name":"Polarcup",
    "wof:placetype":"venue"
},
  "geometry": {"coordinates":[150.814743042,-33.6144294739],"type":"Point"}
}