{
  "type": "Feature",
  "properties": {
    "addr:full":"Calder Hwy Kangaroo Flat VIC 3555",
    "addr:postcode":"3555",
    "addr:street":"Calder Hwy",
    "iso:country":"AU",
    "sg:address":"Calder Hwy",
    "sg:city":"Kangaroo Flat",
    "sg:classifiers":[
        {
            "category":"Travel",
            "subcategory":"Hotels & Motels",
            "type":"Entertainment"
        }
    ],
    "sg:phone":"+61 3 5447 9568",
    "sg:postcode":"3555",
    "sg:province":"VIC",
    "wof:name":"A-Line Holiday Village",
    "wof:placetype":"venue"
},
  "geometry": {"coordinates":[144.239776611,-36.8320159912],"type":"Point"}
}