{
  "type": "Feature",
  "properties": {
    "addr:full":"296 Clarendon St South Melbourne VIC 3205",
    "addr:housenumber":"296",
    "addr:postcode":"3205",
    "addr:street":"Clarendon St",
    "iso:country":"AU",
    "sg:address":"296 Clarendon St",
    "sg:city":"South Melbourne",
    "sg:classifiers":[
        {
            "category":"Shopping",
            "subcategory":"Clothing, Apparel, & Fashions",
            "type":"Retail Goods"
        }
    ],
    "sg:phone":"+61 3 9699 9071",
    "sg:postcode":"3205",
    "sg:province":"VIC",
    "sg:tags":[
        "hire",
        "men's",
        "wear",
        "formal"
    ],
    "wof:name":"Walter Benson Formal Hire",
    "wof:placetype":"venue"
},
  "geometry": {"coordinates":[144.96061700000001,-37.833454],"type":"Point"}
}