{
  "type": "Feature",
  "properties": {
    "addr:full":"1 Kremzow Rd Brendale QLD 4500",
    "addr:housenumber":"1",
    "addr:postcode":"4500",
    "addr:street":"Kremzow Rd",
    "iso:country":"AU",
    "sg:address":"1 Kremzow Rd",
    "sg:city":"Brendale",
    "sg:classifiers":[
        {
            "category":"Health Services",
            "subcategory":"Dentist",
            "type":"Services"
        }
    ],
    "sg:phone":"+61 7 3889 8889",
    "sg:postcode":"4500",
    "sg:province":"QLD",
    "wof:name":"A.A. Franklin (Dr)",
    "wof:placetype":"venue"
},
  "geometry": {"coordinates":[152.983444214,-27.3175735474],"type":"Point"}
}