{
  "type": "Feature",
  "properties": {
    "addr:full":"Poole St Albury NSW 2640",
    "addr:postcode":"2640",
    "addr:street":"Poole St",
    "iso:country":"AU",
    "sg:address":"Poole St",
    "sg:city":"Albury",
    "sg:classifiers":[
        {
            "category":"Health Services",
            "subcategory":"Nursing And Care Facility",
            "type":"Services"
        }
    ],
    "sg:phone":"+61 2 6023 0000",
    "sg:postcode":"2640",
    "sg:province":"NSW",
    "sg:tags":[
        "home"
    ],
    "wof:name":"Marianella Nursing Home",
    "wof:placetype":"venue"
},
  "geometry": {"coordinates":[146.911712647,-36.0697212219],"type":"Point"}
}