{
  "type": "Feature",
  "properties": {
    "addr:full":"11 Gillis St Dubbo NSW 2830",
    "addr:housenumber":"11",
    "addr:postcode":"2830",
    "addr:street":"Gillis St",
    "iso:country":"AU",
    "sg:address":"11 Gillis St",
    "sg:city":"Dubbo",
    "sg:classifiers":[
        {
            "category":"Health Services",
            "subcategory":"Doctor",
            "type":"Services"
        }
    ],
    "sg:phone":"+61 2 6885 7919",
    "sg:postcode":"2830",
    "sg:province":"NSW",
    "sg:tags":[
        "medical",
        "practitioner"
    ],
    "wof:name":"Hardacre Geoff",
    "wof:placetype":"venue"
},
  "geometry": {"coordinates":[148.62591552699999,-32.2416801453],"type":"Point"}
}