{
  "type": "Feature",
  "properties": {
    "iso:country":"AU",
    "sg:address":"55 Westminster Drv",
    "sg:city":"Castle Hill",
    "sg:classifiers":[
        {
            "category":"Manufacturing",
            "subcategory":"Tools & Machinery",
            "type":"Manufacturing & Wholesale Goods"
        }
    ],
    "sg:phone":"+61 2 8850 0816",
    "sg:postcode":"2154",
    "sg:province":"NSW",
    "sg:tags":[
        "manufactured",
        "specially",
        "designed"
    ],
    "wof:name":"Hydratech Design Pty Ltd",
    "wof:placetype":"venue"
},
  "geometry": {"coordinates":[151.02410888700001,-33.7230148315],"type":"Point"}
}