{
  "type": "Feature",
  "properties": {
    "addr:full":"23a Burnie St Clovelly NSW 2031",
    "addr:postcode":"2031",
    "addr:street":"Burnie St",
    "iso:country":"AU",
    "sg:address":"23a Burnie St",
    "sg:city":"Clovelly",
    "sg:classifiers":[
        {
            "category":"Health Services",
            "subcategory":"Health Practitioner",
            "type":"Services"
        }
    ],
    "sg:phone":"+61 2 9665 5244",
    "sg:postcode":"2031",
    "sg:province":"NSW",
    "sg:tags":[
        "homoeopath"
    ],
    "wof:name":"Direction Of Cure",
    "wof:placetype":"venue"
},
  "geometry": {"coordinates":[151.26190185600001,-33.9117774963],"type":"Point"}
}