{
  "type": "Feature",
  "properties": {
    "iso:country":"AU",
    "sg:address":"1170 Greenhill Rd",
    "sg:city":"Uraidla",
    "sg:classifiers":[
        {
            "category":"Wholesale",
            "subcategory":"Machinery & Supplies",
            "type":"Manufacturing & Wholesale Goods"
        }
    ],
    "sg:phone":"+61 8 8390 1759",
    "sg:postcode":"5142",
    "sg:province":"SA",
    "sg:tags":[
        "agricultural"
    ],
    "wof:name":"Chris Grow Engineering Pty Ltd",
    "wof:placetype":"venue"
},
  "geometry": {"coordinates":[138.745712,-34.957737],"type":"Point"}
}