{
  "type": "Feature",
  "properties": {
    "iso:country":"AU",
    "sg:address":"38 Landsborough Parade,",
    "sg:city":"Golden Beach",
    "sg:classifiers":[
        {
            "category":"Personal",
            "subcategory":"Beauty Salon",
            "type":"Services"
        }
    ],
    "sg:phone":"+61 7 5437 3317",
    "sg:postcode":"4551",
    "sg:province":"QLD",
    "sg:tags":[
        "hairdresser"
    ],
    "wof:name":"One @ Golden Beach",
    "wof:placetype":"venue"
},
  "geometry": {"coordinates":[153.119995117,-26.8204078674],"type":"Point"}
}