{
  "type": "Feature",
  "properties": {
    "iso:country":"AU",
    "sg:address":"241 Queen Victoria St",
    "sg:city":"Fremantle",
    "sg:classifiers":[
        {
            "category":"Shopping",
            "subcategory":"Party Supplies",
            "type":"Retail Goods"
        }
    ],
    "sg:phone":"+61 8 9431 7112",
    "sg:postcode":"6160",
    "sg:province":"WA",
    "sg:tags":[
        "selling",
        "plan"
    ],
    "wof:name":"The Gift Box",
    "wof:placetype":"venue"
},
  "geometry": {"coordinates":[115.751022,-32.048187],"type":"Point"}
}