{
  "type": "Feature",
  "properties": {
    "addr:full":"4 Regent St Waverley TAS 7250",
    "addr:housenumber":"4",
    "addr:postcode":"7250",
    "addr:street":"Regent St",
    "iso:country":"AU",
    "sg:address":"4 Regent St",
    "sg:city":"Waverley",
    "sg:classifiers":[
        {
            "category":"Home & Garden",
            "subcategory":"Building Materials",
            "type":"Retail Goods"
        }
    ],
    "sg:phone":"+61 3 6339 1490",
    "sg:postcode":"7250",
    "sg:province":"TAS",
    "sg:tags":[
        "lawn",
        "cutting",
        "maintenance"
    ],
    "wof:name":"Any Odd Jobs - James",
    "wof:placetype":"venue"
},
  "geometry": {"coordinates":[147.19044494600001,-41.4348831177],"type":"Point"}
}