{
  "type": "Feature",
  "properties": {
    "addr:full":"Lvl 1 , Bridgepoint+3 Brady Mosman NSW 2088",
    "addr:postcode":"2088",
    "iso:country":"AU",
    "sg:address":"Lvl 1",
    "sg:city":", Bridgepoint+3 Brady Mosman",
    "sg:classifiers":[
        {
            "category":"Real Estate",
            "subcategory":"Real Estate Services",
            "type":"Services"
        }
    ],
    "sg:phone":"+61 411 324 932",
    "sg:postcode":"2088",
    "sg:province":"NSW",
    "sg:tags":[
        "valuer"
    ],
    "wof:name":"Harnett Guy & Associates",
    "wof:placetype":"venue"
},
  "geometry": {"coordinates":[151.23458862300001,-33.8206558228],"type":"Point"}
}