{
  "type": "Feature",
  "properties": {
    "iso:country":"AU",
    "sg:address":"4 Beach Rd",
    "sg:city":"Ayr",
    "sg:classifiers":[
        {
            "category":"Manufacturing",
            "subcategory":"Tools & Machinery",
            "type":"Manufacturing & Wholesale Goods"
        }
    ],
    "sg:phone":"+61 419 672 860",
    "sg:postcode":"4807",
    "sg:province":"QLD",
    "sg:tags":[
        "earth",
        "excavating",
        "moving",
        "equipment"
    ],
    "wof:name":"Huski Plant Hire",
    "wof:placetype":"venue"
},
  "geometry": {"coordinates":[147.404296875,-19.572479248],"type":"Point"}
}