{
  "type": "Feature",
  "properties": {
    "addr:full":"47 Helen St Mt Gambier SA 5290",
    "addr:housenumber":"47",
    "addr:postcode":"5290",
    "addr:street":"Helen St",
    "iso:country":"AU",
    "sg:address":"47 Helen St",
    "sg:city":"Mt Gambier",
    "sg:classifiers":[
        {
            "category":"Social Services",
            "subcategory":"Child Care",
            "type":"Services"
        }
    ],
    "sg:phone":"+61 8 8724 9575",
    "sg:postcode":"5290",
    "sg:province":"SA",
    "wof:name":"Helen Street Child Care Centre",
    "wof:placetype":"venue"
},
  "geometry": {"coordinates":[140.77662699999999,-37.829594],"type":"Point"}
}