{
  "type": "Feature",
  "properties": {
    "iso:country":"AU",
    "sg:address":"Level 17 26 St Georges Tce",
    "sg:city":"Perth",
    "sg:classifiers":[
        {
            "category":"Banks & Credit Unions",
            "subcategory":"Financial Services",
            "type":"Services"
        }
    ],
    "sg:phone":"+61 8 9221 7070",
    "sg:postcode":"6000",
    "sg:province":"WA",
    "sg:tags":[
        "financier"
    ],
    "wof:name":"Matrix Finance Group",
    "wof:placetype":"venue"
},
  "geometry": {"coordinates":[115.863182068,-31.9567337036],"type":"Point"}
}