{
  "type": "Feature",
  "properties": {
    "addr:full":"46 Mologa Rd Heidelberg West VIC 3081",
    "addr:housenumber":"46",
    "addr:postcode":"3081",
    "addr:street":"Mologa Rd",
    "iso:country":"AU",
    "sg:address":"46 Mologa Rd",
    "sg:city":"Heidelberg West",
    "sg:classifiers":[
        {
            "category":"Mining & Drilling",
            "type":"Manufacturing & Wholesale Goods"
        }
    ],
    "sg:phone":"+61 412 311 963",
    "sg:postcode":"3081",
    "sg:province":"VIC",
    "sg:tags":[
        "concrete",
        "breaking",
        "grinding",
        "sawing"
    ],
    "wof:name":"Knight L M & L M Pty Ltd",
    "wof:placetype":"venue"
},
  "geometry": {"coordinates":[145.04826355,-37.7333908081],"type":"Point"}
}