{
  "type": "Feature",
  "properties": {
    "addr:full":"34 Snapper St Kawungan QLD 4655",
    "addr:housenumber":"34",
    "addr:postcode":"4655",
    "addr:street":"Snapper St Kawungan",
    "iso:country":"AU",
    "sg:address":"34 Snapper St",
    "sg:city":"Kawungan",
    "sg:classifiers":[
        {
            "category":"Utilities",
            "subcategory":"Electric",
            "type":"Services"
        }
    ],
    "sg:phone":"+61 428 797 180",
    "sg:postcode":"4655",
    "sg:province":"QLD",
    "sg:tags":[
        "electrical",
        "contractor"
    ],
    "wof:name":"Twidale Electrical",
    "wof:placetype":"venue"
},
  "geometry": {"coordinates":[152.84707599999999,-25.303585],"type":"Point"}
}