{
  "type": "Feature",
  "properties": {
    "iso:country":"AU",
    "sg:address":"31 Forbes Crs",
    "sg:city":"Engadine",
    "sg:classifiers":[
        {
            "category":"Building & Trades",
            "subcategory":"Construction",
            "type":"Services"
        }
    ],
    "sg:phone":"+61 2 9548 5168",
    "sg:postcode":"2233",
    "sg:province":"NSW",
    "sg:tags":[
        "bricklayer"
    ],
    "wof:name":"Abermain Bricklaying Pty Ltd",
    "wof:placetype":"venue"
},
  "geometry": {"coordinates":[151.011627197,-34.0525245667],"type":"Point"}
}