{
  "type": "Feature",
  "properties": {
    "iso:country":"AU",
    "sg:address":"6 Ballymena St",
    "sg:city":"Plumpton",
    "sg:classifiers":[
        {
            "category":"Building & Trades",
            "subcategory":"Equipment Rental",
            "type":"Services"
        }
    ],
    "sg:phone":"+61 2 9628 4221",
    "sg:postcode":"2761",
    "sg:province":"NSW",
    "sg:tags":[
        "platform",
        "hire",
        "work",
        "elevating"
    ],
    "wof:name":"C & B Travel Tower Hire",
    "wof:placetype":"venue"
},
  "geometry": {"coordinates":[150.83421300000001,-33.747028],"type":"Point"}
}