{
  "type": "Feature",
  "properties": {
    "iso:country":"AU",
    "sg:address":"Denison St",
    "sg:city":"Hamilton",
    "sg:classifiers":[
        {
            "category":"Travel",
            "subcategory":"Hotels & Motels",
            "type":"Entertainment"
        }
    ],
    "sg:phone":"+61 2 4961 3176",
    "sg:postcode":"2303",
    "sg:province":"NSW",
    "sg:tags":[
        "accommodation"
    ],
    "wof:name":"Bennett Hotel",
    "wof:placetype":"venue"
},
  "geometry": {"coordinates":[151.746277,-32.925095],"type":"Point"}
}