{
  "type": "Feature",
  "properties": {
    "addr:full":"20 Ossie Crt Parkwood QLD 4214",
    "addr:housenumber":"20",
    "addr:postcode":"4214",
    "addr:street":"Ossie Crt",
    "iso:country":"AU",
    "sg:address":"20 Ossie Crt",
    "sg:city":"Parkwood",
    "sg:classifiers":[
        {
            "category":"Utilities",
            "type":"Services"
        }
    ],
    "sg:phone":"+61 7 5574 4767",
    "sg:postcode":"4214",
    "sg:province":"QLD",
    "sg:tags":[
        "refrigeration",
        "industrial",
        "commercial",
        "retail"
    ],
    "wof:name":"K2ring Commercial Distribution Pty Ltd",
    "wof:placetype":"venue"
},
  "geometry": {"coordinates":[153.366363525,-27.9544239044],"type":"Point"}
}