{
  "type": "Feature",
  "properties": {
    "addr:full":"Shp58/ 181 Reynolds Rd Doncaster East VIC 3109",
    "addr:housenumber":"181",
    "addr:postcode":"3109",
    "addr:street":"Reynolds Rd",
    "iso:country":"AU",
    "sg:address":"Shp58/ 181 Reynolds Rd",
    "sg:city":"Doncaster East",
    "sg:classifiers":[
        {
            "category":"Restaurant",
            "type":"Food & Drink"
        }
    ],
    "sg:phone":"+61 3 9842 7766",
    "sg:postcode":"3109",
    "sg:province":"VIC",
    "sg:tags":[
        "pizza"
    ],
    "wof:name":"Panic Pizza The Pines",
    "wof:placetype":"venue"
},
  "geometry": {"coordinates":[145.167800903,-37.7634353638],"type":"Point"}
}