{
  "type": "Feature",
  "properties": {
    "iso:country":"AU",
    "sg:address":"Unit 4/46- 50 Regent St",
    "sg:city":"Richmond",
    "sg:classifiers":[
        {
            "category":"Professional",
            "subcategory":"Art Services",
            "type":"Services"
        }
    ],
    "sg:phone":"+61 3 9419 0797",
    "sg:postcode":"3121",
    "sg:province":"VIC",
    "sg:tags":[
        "product",
        "industrial",
        "designer"
    ],
    "wof:name":"Thylacine Design & Project Management",
    "wof:placetype":"venue"
},
  "geometry": {"coordinates":[144.99186706500001,-37.811958313],"type":"Point"}
}