{
  "type": "Feature",
  "properties": {
    "addr:full":"145 Arina Rd Pheasants Nest NSW 2574",
    "addr:housenumber":"145",
    "addr:postcode":"2574",
    "addr:street":"Arina Rd",
    "iso:country":"AU",
    "sg:address":"145 Arina Rd",
    "sg:city":"Pheasants Nest",
    "sg:classifiers":[
        {
            "category":"Building & Trades",
            "subcategory":"Construction",
            "type":"Services"
        }
    ],
    "sg:phone":"+61 412 422 740",
    "sg:postcode":"2574",
    "sg:province":"NSW",
    "sg:tags":[
        "joiner",
        "carpenter"
    ],
    "wof:name":"Duffy Michael",
    "wof:placetype":"venue"
},
  "geometry": {"coordinates":[150.612915039,-34.264415741],"type":"Point"}
}