{
  "type": "Feature",
  "properties": {
    "addr:full":"Unit 6, 27 Allgas St Slacks Creek QLD 4127",
    "addr:housenumber":"27",
    "addr:postcode":"4127",
    "addr:street":"Allgas St",
    "iso:country":"AU",
    "sg:address":"Unit 6, 27 Allgas St",
    "sg:city":"Slacks Creek",
    "sg:classifiers":[
        {
            "category":"Building & Trades",
            "subcategory":"Construction",
            "type":"Services"
        }
    ],
    "sg:phone":"+61 7 3209 5433",
    "sg:postcode":"4127",
    "sg:province":"QLD",
    "sg:tags":[
        "ceiling"
    ],
    "wof:name":"Lynmac Construction",
    "wof:placetype":"venue"
},
  "geometry": {"coordinates":[153.12246704099999,-27.6186408997],"type":"Point"}
}