{
  "type": "Feature",
  "properties": {
    "addr:full":"Hendy Main Rd Moriac VIC 3240",
    "addr:postcode":"3240",
    "addr:street":"Main Rd",
    "iso:country":"AU",
    "sg:address":"Hendy Main Rd",
    "sg:city":"Moriac",
    "sg:classifiers":[
        {
            "category":"Building & Trades",
            "subcategory":"Construction",
            "type":"Services"
        }
    ],
    "sg:phone":"+61 418 332 769",
    "sg:postcode":"3240",
    "sg:province":"VIC",
    "sg:tags":[
        "contractor"
    ],
    "wof:name":"Homebiz Building-Joinery",
    "wof:placetype":"venue"
},
  "geometry": {"coordinates":[144.17523193400001,-38.242023468],"type":"Point"}
}