{
  "type": "Feature",
  "properties": {
    "addr:full":"136 Normanby St Warragul VIC 3820",
    "addr:housenumber":"136",
    "addr:postcode":"3820",
    "addr:street":"Normanby St",
    "iso:country":"AU",
    "sg:address":"136 Normanby St",
    "sg:city":"Warragul",
    "sg:classifiers":[
        {
            "category":"Government",
            "subcategory":"Court House",
            "type":"Public Place"
        }
    ],
    "sg:phone":"+61 3 5622 1680",
    "sg:postcode":"3820",
    "sg:province":"VIC",
    "sg:tags":[
        "personal",
        "marriage",
        "family",
        "counselling"
    ],
    "wof:name":"West Gippsland Counselling Services",
    "wof:placetype":"venue"
},
  "geometry": {"coordinates":[145.94010900000001,-38.159012],"type":"Point"}
}