{
  "type": "Feature",
  "properties": {
    "iso:country":"AU",
    "sg:address":"PO Box 1724",
    "sg:city":"Green Valley",
    "sg:classifiers":[
        {
            "category":"Building & Trades",
            "subcategory":"Cleaning & Sanitation",
            "type":"Services"
        }
    ],
    "sg:phone":"+61 2 9608 6184",
    "sg:postcode":"2168",
    "sg:province":"NSW",
    "sg:tags":[
        "asbestos",
        "treatment",
        "removal"
    ],
    "wof:name":"LBS Asbestos Removal Technical Services & Roofing",
    "wof:placetype":"venue"
},
  "geometry": {"coordinates":[150.86651611299999,-33.9027404785],"type":"Point"}
}