{
  "type": "Feature",
  "properties": {
    "iso:country":"AU",
    "sg:address":"36 Bass Hwy",
    "sg:city":"Cooee",
    "sg:classifiers":[
        {
            "category":"Retail",
            "subcategory":"Repair Shop",
            "type":"Services"
        }
    ],
    "sg:phone":"+61 3 6431 9766",
    "sg:postcode":"7320",
    "sg:province":"TAS",
    "sg:tags":[
        "windscreen"
    ],
    "wof:name":"Protector Autoglass",
    "wof:placetype":"venue"
},
  "geometry": {"coordinates":[145.87780799999999,-41.041698],"type":"Point"}
}