{
  "type": "Feature",
  "properties": {
    "addr:full":"165 Nelson Pl Williamstown VIC 3016",
    "addr:housenumber":"165",
    "addr:postcode":"3016",
    "addr:street":"Nelson Pl",
    "iso:country":"AU",
    "sg:address":"165 Nelson Pl",
    "sg:city":"Williamstown",
    "sg:classifiers":[
        {
            "category":"Cafe",
            "type":"Food & Drink"
        }
    ],
    "sg:phone":"+61 3 9397 2600",
    "sg:postcode":"3016",
    "sg:province":"VIC",
    "wof:name":"Schwabs Galley",
    "wof:placetype":"venue"
},
  "geometry": {"coordinates":[144.90391540499999,-37.8629951477],"type":"Point"}
}