{
  "type": "Feature",
  "properties": {
    "iso:country":"AU",
    "sg:address":"198 Liverpool St",
    "sg:city":"East Sydney",
    "sg:classifiers":[
        {
            "category":"Retail",
            "subcategory":"Auto Repair",
            "type":"Services"
        }
    ],
    "sg:phone":"+61 2 9331 3677",
    "sg:postcode":"2010",
    "sg:province":"NSW",
    "sg:tags":[
        "beater",
        "painter",
        "panel"
    ],
    "wof:name":"Hargrave Motor Repairs Pty Ltd",
    "wof:placetype":"venue"
},
  "geometry": {"coordinates":[151.214553833,-33.8770904541],"type":"Point"}
}