{
  "type": "Feature",
  "properties": {
    "addr:full":"Ste 8/ 245 Churchill Ave Subiaco WA 6008",
    "addr:housenumber":"/ 245",
    "addr:postcode":"6008",
    "addr:street":"Churchill Ave",
    "iso:country":"AU",
    "sg:address":"Ste 8/ 245 Churchill Ave",
    "sg:city":"Subiaco",
    "sg:classifiers":[
        {
            "category":"Building & Trades",
            "subcategory":"Construction",
            "type":"Services"
        }
    ],
    "sg:phone":"+61 8 9380 2500",
    "sg:postcode":"6008",
    "sg:province":"WA",
    "sg:tags":[
        "management"
    ],
    "wof:name":"Rise Construction Pty Ltd",
    "wof:placetype":"venue"
},
  "geometry": {"coordinates":[115.83215332,-31.9434642792],"type":"Point"}
}