{
  "type": "Feature",
  "properties": {
    "addr:full":"Peel Rd Baulkham Hills NSW 2153",
    "addr:postcode":"2153",
    "addr:street":"Peel Rd",
    "iso:country":"AU",
    "sg:address":"Peel Rd",
    "sg:city":"Baulkham Hills",
    "sg:classifiers":[
        {
            "category":"Social Services",
            "subcategory":"Child Care",
            "type":"Services"
        }
    ],
    "sg:phone":"+61 2 9624 4098",
    "sg:postcode":"2153",
    "sg:province":"NSW",
    "wof:name":"Winston Hills After School Care",
    "wof:placetype":"venue"
},
  "geometry": {"coordinates":[150.99415588400001,-33.775428772],"type":"Point"}
}