{
  "type": "Feature",
  "properties": {
    "addr:full":"2 Louie St Corrimal NSW 2518",
    "addr:housenumber":"2",
    "addr:postcode":"2518",
    "addr:street":"Louie St",
    "iso:country":"AU",
    "sg:address":"2 Louie St",
    "sg:city":"Corrimal",
    "sg:classifiers":[
        {
            "category":"Arena",
            "subcategory":"Sports Club",
            "type":"Entertainment"
        }
    ],
    "sg:phone":"+61 2 4284 2272",
    "sg:postcode":"2518",
    "sg:province":"NSW",
    "sg:tags":[
        "league",
        "rugby"
    ],
    "wof:name":"Wollongong Bulls R.L.F.C",
    "wof:placetype":"venue"
},
  "geometry": {"coordinates":[150.90618900000001,-34.368599],"type":"Point"}
}