{
  "type": "Feature",
  "properties": {
    "addr:full":"1/ 1 Vuko Pl Warriewood NSW 2102",
    "addr:housenumber":"/ 1",
    "addr:postcode":"2102",
    "addr:street":"Vuko Pl",
    "iso:country":"AU",
    "sg:address":"1/ 1 Vuko Pl",
    "sg:city":"Warriewood",
    "sg:classifiers":[
        {
            "category":"Health Services",
            "subcategory":"Health Practitioner",
            "type":"Services"
        }
    ],
    "sg:phone":"+61 2 9999 2211",
    "sg:postcode":"2102",
    "sg:province":"NSW",
    "sg:tags":[
        "acupuncture"
    ],
    "wof:name":"Wingfield Amy",
    "wof:placetype":"venue"
},
  "geometry": {"coordinates":[151.301727,-33.693279],"type":"Point"}
}