{
  "type": "Feature",
  "properties": {
    "iso:country":"AU",
    "sg:address":"14 Gibbs St",
    "sg:city":"Cannington",
    "sg:classifiers":[
        {
            "category":"Wholesale",
            "subcategory":"Painting Supplies",
            "type":"Manufacturing & Wholesale Goods"
        }
    ],
    "sg:phone":"+61 8 9356 1874",
    "sg:postcode":"6107",
    "sg:province":"WA",
    "sg:tags":[
        "equipment",
        "spraying"
    ],
    "wof:name":"Automotive Paint Tools & Equipment",
    "wof:placetype":"venue"
},
  "geometry": {"coordinates":[115.946960449,-32.0128593445],"type":"Point"}
}