{
  "type": "Feature",
  "properties": {
    "addr:full":"70 Birch Forest Rd Berrima NSW 2577",
    "addr:housenumber":"70",
    "addr:postcode":"2577",
    "addr:street":"Birch Forest Rd",
    "iso:country":"AU",
    "sg:address":"70 Birch Forest Rd",
    "sg:city":"Berrima",
    "sg:classifiers":[
        {
            "category":"Utilities",
            "subcategory":"Refuse",
            "type":"Services"
        }
    ],
    "sg:phone":"+61 2 4877 1444",
    "sg:postcode":"2577",
    "sg:province":"NSW",
    "sg:tags":[
        "remover",
        "rubbish"
    ],
    "wof:name":"Highlands Tip Trips",
    "wof:placetype":"venue"
},
  "geometry": {"coordinates":[150.296783447,-34.4590377808],"type":"Point"}
}