{
  "type": "Feature",
  "properties": {
    "addr:full":"3 Daintree Pl Gosford West NSW 2250",
    "addr:housenumber":"3",
    "addr:postcode":"2250",
    "addr:street":"Daintree Pl",
    "iso:country":"AU",
    "sg:address":"3 Daintree Pl",
    "sg:city":"Gosford West",
    "sg:classifiers":[
        {
            "category":"Manufacturing",
            "subcategory":"Tools & Machinery",
            "type":"Manufacturing & Wholesale Goods"
        }
    ],
    "sg:phone":"+61 2 4323 1444",
    "sg:postcode":"2250",
    "sg:province":"NSW",
    "sg:tags":[
        "toolmaker"
    ],
    "wof:name":"Irwin Jeff Engineering Pty Ltd",
    "wof:placetype":"venue"
},
  "geometry": {"coordinates":[151.32696533199999,-33.412071228],"type":"Point"}
}