{
  "type": "Feature",
  "properties": {
    "iso:country":"AU",
    "sg:address":"Logan Rd",
    "sg:city":"Springwood",
    "sg:classifiers":[
        {
            "category":"Home & Garden",
            "subcategory":"Furniture",
            "type":"Retail Goods"
        }
    ],
    "sg:phone":"+61 7 3841 5388",
    "sg:postcode":"4127",
    "sg:province":"QLD",
    "sg:tags":[
        "outdoor"
    ],
    "wof:name":"Early Settler",
    "wof:placetype":"venue"
},
  "geometry": {"coordinates":[153.124237061,-27.6150302887],"type":"Point"}
}