{
  "type": "Feature",
  "properties": {
    "addr:full":"269 Padstow Rd Eight Mile Plains QLD 4113",
    "addr:housenumber":"269",
    "addr:postcode":"4113",
    "addr:street":"Padstow Rd",
    "iso:country":"AU",
    "sg:address":"269 Padstow Rd",
    "sg:city":"Eight Mile Plains",
    "sg:classifiers":[
        {
            "category":"Manufacturing",
            "subcategory":"Pottery",
            "type":"Manufacturing & Wholesale Goods"
        }
    ],
    "sg:phone":"+61 7 3219 8912",
    "sg:postcode":"4113",
    "sg:province":"QLD",
    "wof:name":"Monte Lupo Studio",
    "wof:placetype":"venue"
},
  "geometry": {"coordinates":[153.088912964,-27.575586319],"type":"Point"}
}