{
  "type": "Feature",
  "properties": {
    "iso:country":"AU",
    "sg:address":"185 Elizabeth St",
    "sg:city":"Sydney",
    "sg:classifiers":[
        {
            "category":"Education",
            "subcategory":"Special Training",
            "type":"Public Place"
        }
    ],
    "sg:phone":"+61 2 9555 8671",
    "sg:postcode":"2000",
    "sg:province":"NSW",
    "sg:tags":[
        "tuition-educational"
    ],
    "wof:name":"Ian MacRae Radio School",
    "wof:placetype":"venue"
},
  "geometry": {"coordinates":[151.20986938499999,-33.8726425171],"type":"Point"}
}