{
  "type": "Feature",
  "properties": {
    "addr:full":"Cnr Ferntree Gully & Scoresby Rd 511 Scoresby Rd Ferntree Gully VIC 3156",
    "addr:postcode":"3156",
    "addr:street":"Rd 511 Scoresby Rd",
    "iso:country":"AU",
    "sg:address":"Cnr Ferntree Gully & Scoresby Rd 511 Scoresby Rd",
    "sg:city":"Ferntree Gully",
    "sg:classifiers":[
        {
            "category":"Fast Food",
            "type":"Food & Drink"
        }
    ],
    "sg:phone":"+61 3 9763 3633",
    "sg:postcode":"3156",
    "sg:province":"VIC",
    "sg:tags":[
        "away",
        "take"
    ],
    "wof:name":"Flames House Of Charcoal Chicken",
    "wof:placetype":"venue"
},
  "geometry": {"coordinates":[145.25784301799999,-37.8911552429],"type":"Point"}
}