{
  "type": "Feature",
  "properties": {
    "addr:full":"63 Northern Rd Heidelberg VIC 3084",
    "addr:housenumber":"63",
    "addr:postcode":"3084",
    "addr:street":"Northern Rd",
    "iso:country":"AU",
    "sg:address":"63 Northern Rd",
    "sg:city":"Heidelberg",
    "sg:classifiers":[
        {
            "category":"Building & Trades",
            "subcategory":"Construction",
            "type":"Services"
        }
    ],
    "sg:phone":"+61 3 9458 1666",
    "sg:postcode":"3084",
    "sg:province":"VIC",
    "sg:tags":[
        "contractor"
    ],
    "wof:name":"Supa Group Constructions",
    "wof:placetype":"venue"
},
  "geometry": {"coordinates":[145.05987548799999,-37.7305870056],"type":"Point"}
}