{
  "type": "Feature",
  "properties": {
    "iso:country":"AU",
    "sg:address":"\"Tandara\" Tatiara Rd",
    "sg:city":"Bordertown",
    "sg:classifiers":[
        {
            "category":"Farming",
            "subcategory":"Farm",
            "type":"Manufacturing & Wholesale Goods"
        }
    ],
    "sg:phone":"+61 8 8752 1904",
    "sg:postcode":"5268",
    "sg:province":"SA",
    "sg:tags":[
        "farmer"
    ],
    "wof:name":"Grosser Peter D",
    "wof:placetype":"venue"
},
  "geometry": {"coordinates":[140.79745500000001,-36.323135],"type":"Point"}
}