{
  "type": "Feature",
  "properties": {
    "iso:country":"AU",
    "sg:address":"779 Washpool Rd",
    "sg:city":"Stroud",
    "sg:classifiers":[
        {
            "category":"Farming",
            "subcategory":"Farm",
            "type":"Manufacturing & Wholesale Goods"
        }
    ],
    "sg:phone":"+61 2 4994 5236",
    "sg:postcode":"2425",
    "sg:province":"NSW",
    "sg:tags":[
        "farmer"
    ],
    "wof:name":"Wilson K G",
    "wof:placetype":"venue"
},
  "geometry": {"coordinates":[151.946807861,-32.4440345764],"type":"Point"}
}