{
  "type": "Feature",
  "properties": {
    "iso:country":"AU",
    "sg:address":"12/ 27 Dale St",
    "sg:city":"Brookvale",
    "sg:classifiers":[
        {
            "category":"Shopping",
            "subcategory":"Computers & Home Electronics",
            "type":"Retail Goods"
        }
    ],
    "sg:phone":"+61 2 9905 8797",
    "sg:postcode":"2100",
    "sg:province":"NSW",
    "sg:tags":[
        "equipment",
        "supply"
    ],
    "wof:name":"Vital Peripheral Supplies",
    "wof:placetype":"venue"
},
  "geometry": {"coordinates":[151.26858520499999,-33.765045166],"type":"Point"}
}