{
  "type": "Feature",
  "properties": {
    "addr:full":"114 Cunningham St Sale VIC 3850",
    "addr:housenumber":"114",
    "addr:postcode":"3850",
    "addr:street":"Cunningham St",
    "iso:country":"AU",
    "sg:address":"114 Cunningham St",
    "sg:city":"Sale",
    "sg:classifiers":[
        {
            "category":"Autos & Motor Vehicles",
            "subcategory":"Auto Supplies",
            "type":"Retail Goods"
        }
    ],
    "sg:phone":"+61 3 5144 2977",
    "sg:postcode":"3850",
    "sg:province":"VIC",
    "sg:tags":[
        "battery",
        "automotive"
    ],
    "wof:name":"Beaurepaires",
    "wof:placetype":"venue"
},
  "geometry": {"coordinates":[147.06849670400001,-38.1073799133],"type":"Point"}
}