{
  "type": "Feature",
  "properties": {
    "iso:country":"AU",
    "sg:address":"Shp T59 Harbourtown, 272 Tapleys Rd West Beach",
    "sg:city":"West Beach",
    "sg:classifiers":[
        {
            "category":"Utilities",
            "subcategory":"Refuse",
            "type":"Services"
        }
    ],
    "sg:phone":"+61 8 8235 2902",
    "sg:postcode":"5024",
    "sg:province":"SA",
    "sg:tags":[
        "leather",
        "retail",
        "clothing"
    ],
    "wof:name":"Atelier 15",
    "wof:placetype":"venue"
},
  "geometry": {"coordinates":[138.50306701700001,-34.9456977844],"type":"Point"}
}