{
  "type": "Feature",
  "properties": {
    "iso:country":"AU",
    "sg:address":"586 Willoughby Rd",
    "sg:city":"Willoughby",
    "sg:classifiers":[
        {
            "category":"Building & Trades",
            "subcategory":"Landscaping Services",
            "type":"Services"
        }
    ],
    "sg:phone":"+61 2 9958 9400",
    "sg:postcode":"2068",
    "sg:province":"NSW",
    "sg:tags":[
        "designer",
        "landscape",
        "contractor"
    ],
    "wof:name":"Design Landscapes Pty Ltd",
    "wof:placetype":"venue"
},
  "geometry": {"coordinates":[151.19918823200001,-33.8069953918],"type":"Point"}
}