{
  "type": "Feature",
  "properties": {
    "addr:full":"2 Tharratt St Thornbury VIC 3071",
    "addr:housenumber":"2",
    "addr:postcode":"3071",
    "addr:street":"Tharratt St",
    "iso:country":"AU",
    "sg:address":"2 Tharratt St",
    "sg:city":"Thornbury",
    "sg:classifiers":[
        {
            "category":"Retail",
            "subcategory":"Driving School",
            "type":"Services"
        }
    ],
    "sg:phone":"+61 3 9436 9748",
    "sg:postcode":"3071",
    "sg:province":"VIC",
    "wof:name":"Roadsafe Driving School",
    "wof:placetype":"venue"
},
  "geometry": {"coordinates":[145.00880432100001,-37.7536582947],"type":"Point"}
}