{
  "type": "Feature",
  "properties": {
    "addr:full":"21 Bennet Ave Melrose Park SA 5039",
    "addr:housenumber":"21",
    "addr:postcode":"5039",
    "addr:street":"Bennet Ave",
    "iso:country":"AU",
    "sg:address":"21 Bennet Ave",
    "sg:city":"Melrose Park",
    "sg:classifiers":[
        {
            "category":"Retail",
            "subcategory":"Auto Repair",
            "type":"Services"
        }
    ],
    "sg:phone":"+61 8 8277 8887",
    "sg:postcode":"5039",
    "sg:province":"SA",
    "sg:tags":[
        "beater",
        "painter",
        "panel"
    ],
    "wof:name":"Edwardstown Custom Body Repairs",
    "wof:placetype":"venue"
},
  "geometry": {"coordinates":[138.57771301299999,-34.9906845093],"type":"Point"}
}