{
  "type": "Feature",
  "properties": {
    "addr:full":"1 Gertrude St Arncliffe NSW 2205",
    "addr:housenumber":"1",
    "addr:postcode":"2205",
    "addr:street":"Gertrude St",
    "iso:country":"AU",
    "sg:address":"1 Gertrude St",
    "sg:city":"Arncliffe",
    "sg:classifiers":[
        {
            "category":"Retail",
            "subcategory":"Auto Repair",
            "type":"Services"
        }
    ],
    "sg:phone":"+61 2 9567 1487",
    "sg:postcode":"2205",
    "sg:province":"NSW",
    "sg:tags":[
        "repairer",
        "motor",
        "engineer"
    ],
    "wof:name":"Ennis Auto Repairs",
    "wof:placetype":"venue"
},
  "geometry": {"coordinates":[151.15351899999999,-33.932941],"type":"Point"}
}