{
  "type": "Feature",
  "properties": {
    "iso:country":"AU",
    "sg:address":"Suite 1, 2 Coora Crs",
    "sg:city":"Currimundi",
    "sg:classifiers":[
        {
            "category":"Personal",
            "subcategory":"Massage",
            "type":"Services"
        }
    ],
    "sg:phone":"+61 7 5437 7165",
    "sg:postcode":"4551",
    "sg:province":"QLD",
    "sg:tags":[
        "therapy"
    ],
    "wof:name":"Bowen By Nature",
    "wof:placetype":"venue"
},
  "geometry": {"coordinates":[153.12115478499999,-26.7692909241],"type":"Point"}
}