{
  "type": "Feature",
  "properties": {
    "addr:full":"57 Merrill Crs Warranwood VIC 3134",
    "addr:housenumber":"57",
    "addr:postcode":"3134",
    "addr:street":"Merrill Crs",
    "iso:country":"AU",
    "sg:address":"57 Merrill Crs",
    "sg:city":"Warranwood",
    "sg:classifiers":[
        {
            "category":"Professional",
            "subcategory":"Computer Services",
            "type":"Services"
        }
    ],
    "sg:phone":"+61 3 9879 0351",
    "sg:postcode":"3134",
    "sg:province":"VIC",
    "sg:tags":[
        "consultant",
        "system"
    ],
    "wof:name":"Baber Enterprises Pty Ltd",
    "wof:placetype":"venue"
},
  "geometry": {"coordinates":[145.24896240199999,-37.7755813599],"type":"Point"}
}