{
  "type": "Feature",
  "properties": {
    "addr:full":"11 Simpson St Mt Isa QLD 4825",
    "addr:housenumber":"11",
    "addr:postcode":"4825",
    "addr:street":"Simpson St",
    "iso:country":"AU",
    "sg:address":"11 Simpson St",
    "sg:city":"Mt Isa",
    "sg:classifiers":[
        {
            "category":"Shopping",
            "subcategory":"Music",
            "type":"Retail Goods"
        }
    ],
    "sg:phone":"+61 7 4743 4124",
    "sg:postcode":"4825",
    "sg:province":"QLD",
    "sg:tags":[
        "instrument",
        "musical"
    ],
    "wof:name":"Tulloch Musical World",
    "wof:placetype":"venue"
},
  "geometry": {"coordinates":[139.493988,-20.727594],"type":"Point"}
}