{
  "type": "Feature",
  "properties": {
    "addr:full":"532 Canterbury Rd Campsie NSW 2194",
    "addr:housenumber":"532",
    "addr:postcode":"2194",
    "addr:street":"Canterbury Rd",
    "iso:country":"AU",
    "sg:address":"532 Canterbury Rd",
    "sg:city":"Campsie",
    "sg:classifiers":[
        {
            "category":"Health Services",
            "subcategory":"Medical Lab",
            "type":"Services"
        }
    ],
    "sg:phone":"+61 2 9789 1680",
    "sg:postcode":"2194",
    "sg:province":"NSW",
    "sg:tags":[
        "laboratory",
        "pathology"
    ],
    "wof:name":"Medtest Pty Ltd",
    "wof:placetype":"venue"
},
  "geometry": {"coordinates":[151.09910600000001,-33.920555],"type":"Point"}
}