{
  "type": "Feature",
  "properties": {
    "iso:country":"AU",
    "sg:address":"164 Cowper St",
    "sg:city":"Warrawong",
    "sg:classifiers":[
        {
            "category":"Professional",
            "subcategory":"Business Services",
            "type":"Services"
        }
    ],
    "sg:phone":"+61 2 4274 6666",
    "sg:postcode":"2502",
    "sg:province":"NSW",
    "sg:tags":[
        "broker"
    ],
    "wof:name":"Ray White Warrawong",
    "wof:placetype":"venue"
},
  "geometry": {"coordinates":[150.889679,-34.485115],"type":"Point"}
}