{
  "type": "Feature",
  "properties": {
    "addr:full":"545 Union Rd North Albury NSW 2640",
    "addr:housenumber":"545",
    "addr:postcode":"2640",
    "addr:street":"Union Rd",
    "iso:country":"AU",
    "sg:address":"545 Union Rd",
    "sg:city":"North Albury",
    "sg:classifiers":[
        {
            "category":"Food & Beverages",
            "subcategory":"Supermarket",
            "type":"Retail Goods"
        }
    ],
    "sg:phone":"+61 2 6040 2440",
    "sg:postcode":"2640",
    "sg:province":"NSW",
    "sg:tags":[
        "grocery",
        "store"
    ],
    "wof:name":"IGA Norris Park",
    "wof:placetype":"venue"
},
  "geometry": {"coordinates":[146.92146301299999,-36.0510749817],"type":"Point"}
}