{
  "type": "Feature",
  "properties": {
    "iso:country":"AU",
    "sg:address":"14 Stanton Rd",
    "sg:city":"Haberfield",
    "sg:classifiers":[
        {
            "category":"Health Services",
            "subcategory":"Nursing And Care Facility",
            "type":"Services"
        }
    ],
    "sg:phone":"+61 2 9798 6585",
    "sg:postcode":"2045",
    "sg:province":"NSW",
    "sg:tags":[
        "home"
    ],
    "wof:name":"Woodfield Nursing Home",
    "wof:placetype":"venue"
},
  "geometry": {"coordinates":[151.141617,-33.885773],"type":"Point"}
}