{
  "type": "Feature",
  "properties": {
    "addr:full":"112 Diagonal Rd Somerton Park SA 5044",
    "addr:housenumber":"112",
    "addr:postcode":"5044",
    "addr:street":"Diagonal Rd",
    "iso:country":"AU",
    "sg:address":"112 Diagonal Rd",
    "sg:city":"Somerton Park",
    "sg:classifiers":[
        {
            "category":"Utilities",
            "subcategory":"Refuse",
            "type":"Services"
        }
    ],
    "sg:phone":"+61 8 8295 2466",
    "sg:postcode":"5044",
    "sg:province":"SA",
    "sg:tags":[
        "remover",
        "rubbish"
    ],
    "wof:name":"Adelaide Bob Cat Hire",
    "wof:placetype":"venue"
},
  "geometry": {"coordinates":[138.52975499999999,-34.995441],"type":"Point"}
}