{
  "type": "Feature",
  "properties": {
    "iso:country":"AU",
    "sg:address":"94 Balham Rd",
    "sg:city":"Rocklea",
    "sg:classifiers":[
        {
            "category":"Professional",
            "subcategory":"Employment Agencies",
            "type":"Services"
        }
    ],
    "sg:phone":"+61 7 3277 7777",
    "sg:postcode":"4106",
    "sg:province":"QLD",
    "sg:tags":[
        "hire",
        "labour",
        "contractor"
    ],
    "wof:name":"Action Staff",
    "wof:placetype":"venue"
},
  "geometry": {"coordinates":[153.00950622600001,-27.5467262268],"type":"Point"}
}