{
  "type": "Feature",
  "properties": {
    "addr:full":"Level 9/ 259 Wickham Tce Brisbane QLD 4000",
    "addr:housenumber":"/ 259",
    "addr:postcode":"4000",
    "addr:street":"Wickham Tce",
    "iso:country":"AU",
    "sg:address":"Level 9/ 259 Wickham Tce",
    "sg:city":"Brisbane",
    "sg:classifiers":[
        {
            "category":"Health Services",
            "subcategory":"Doctor",
            "type":"Services"
        }
    ],
    "sg:phone":"+61 7 3834 6543",
    "sg:postcode":"4000",
    "sg:province":"QLD",
    "sg:tags":[
        "medical",
        "practitioner"
    ],
    "wof:name":"Coleman Stephen",
    "wof:placetype":"venue"
},
  "geometry": {"coordinates":[153.02226257300001,-27.4651184082],"type":"Point"}
}