{
  "type": "Feature",
  "properties": {
    "addr:full":"333 Canning Hwy Bicton WA 6157",
    "addr:housenumber":"333",
    "addr:postcode":"6157",
    "addr:street":"Canning Hwy",
    "iso:country":"AU",
    "sg:address":"333 Canning Hwy",
    "sg:city":"Bicton",
    "sg:classifiers":[
        {
            "category":"Travel",
            "subcategory":"Travel Agent",
            "type":"Entertainment"
        }
    ],
    "sg:phone":"+61 8 9339 3099",
    "sg:postcode":"6157",
    "sg:province":"WA",
    "sg:tags":[
        "consultant"
    ],
    "wof:name":"Debretts Travel Services",
    "wof:placetype":"venue"
},
  "geometry": {"coordinates":[115.785049,-32.036266],"type":"Point"}
}