{
  "type": "Feature",
  "properties": {
    "addr:full":"4 Warncliffe Rd Ivanhoe VIC 3079",
    "addr:housenumber":"4",
    "addr:postcode":"3079",
    "addr:street":"Warncliffe Rd",
    "iso:country":"AU",
    "sg:address":"4 Warncliffe Rd",
    "sg:city":"Ivanhoe",
    "sg:classifiers":[
        {
            "category":"Wholesale",
            "subcategory":"Painting Supplies",
            "type":"Manufacturing & Wholesale Goods"
        }
    ],
    "sg:phone":"+61 3 9499 2268",
    "sg:postcode":"3079",
    "sg:province":"VIC",
    "sg:tags":[
        "product",
        "cleaning"
    ],
    "wof:name":"Jones M M",
    "wof:placetype":"venue"
},
  "geometry": {"coordinates":[145.05906677199999,-37.7773742676],"type":"Point"}
}