{
  "type": "Feature",
  "properties": {
    "iso:country":"AU",
    "sg:address":"4 Surrey Rd",
    "sg:city":"Mt Waverley",
    "sg:classifiers":[
        {
            "category":"Airline",
            "type":"Transportation"
        }
    ],
    "sg:phone":"+61 3 9833 3511",
    "sg:postcode":"3149",
    "sg:province":"VIC",
    "sg:tags":[
        "aircraft",
        "rental",
        "charter"
    ],
    "wof:name":"Corporate Cabin Crew (Australia)",
    "wof:placetype":"venue"
},
  "geometry": {"coordinates":[145.11958313,-37.8636703491],"type":"Point"}
}