{
  "type": "Feature",
  "properties": {
    "addr:full":"16 Windale St Dandenong VIC 3175",
    "addr:housenumber":"16",
    "addr:postcode":"3175",
    "addr:street":"Windale St",
    "iso:country":"AU",
    "sg:address":"16 Windale St",
    "sg:city":"Dandenong",
    "sg:classifiers":[
        {
            "category":"Utilities",
            "subcategory":"Refuse",
            "type":"Services"
        }
    ],
    "sg:phone":"+61 408 586 499",
    "sg:postcode":"3175",
    "sg:province":"VIC",
    "sg:tags":[
        "remover",
        "rubbish"
    ],
    "wof:name":"Waste Lift Bin Hire",
    "wof:placetype":"venue"
},
  "geometry": {"coordinates":[145.226638794,-37.9972305298],"type":"Point"}
}