{
  "type": "Feature",
  "properties": {
    "iso:country":"AU",
    "sg:address":"138 Springvale Rd",
    "sg:city":"Glen Waverley",
    "sg:classifiers":[
        {
            "category":"Transit Center",
            "subcategory":"Freight",
            "type":"Transportation"
        }
    ],
    "sg:phone":"+61 402 890 147",
    "sg:postcode":"3150",
    "sg:province":"VIC",
    "sg:tags":[
        "honey",
        "merchant"
    ],
    "wof:name":"Ambrosia Apiaries Pty Ltd",
    "wof:placetype":"venue"
},
  "geometry": {"coordinates":[145.16607665999999,-37.879650116],"type":"Point"}
}