{
  "type": "Feature",
  "properties": {
    "addr:full":"6 Iluka St Narrabundah ACT 2604",
    "addr:housenumber":"6",
    "addr:postcode":"2604",
    "addr:street":"Iluka St",
    "iso:country":"AU",
    "sg:address":"6 Iluka St",
    "sg:city":"Narrabundah",
    "sg:classifiers":[
        {
            "category":"Food & Beverages",
            "subcategory":"Bakery",
            "type":"Retail Goods"
        }
    ],
    "sg:phone":"+61 2 6295 7545",
    "sg:postcode":"2604",
    "sg:province":"ACT",
    "sg:tags":[
        "baker"
    ],
    "wof:name":"Danny's Bakery",
    "wof:placetype":"venue"
},
  "geometry": {"coordinates":[149.15415954599999,-35.3325004578],"type":"Point"}
}