{
  "type": "Feature",
  "properties": {
    "addr:full":"15 Railway St Gatton QLD 4343",
    "addr:housenumber":"15",
    "addr:postcode":"4343",
    "addr:street":"Railway St",
    "iso:country":"AU",
    "sg:address":"15 Railway St",
    "sg:city":"Gatton",
    "sg:classifiers":[
        {
            "category":"Food & Beverages",
            "subcategory":"Fruits & Vegetables",
            "type":"Retail Goods"
        }
    ],
    "sg:phone":"+61 7 5462 1168",
    "sg:postcode":"4343",
    "sg:province":"QLD",
    "sg:tags":[
        "wholesale"
    ],
    "wof:name":"Boko's Fruit Mart",
    "wof:placetype":"venue"
},
  "geometry": {"coordinates":[152.27691650400001,-27.5573272705],"type":"Point"}
}