{
  "type": "Feature",
  "properties": {
    "addr:full":"Princess Alexandra Hospital Ipswich Rd Woolloongabba QLD 4102",
    "addr:postcode":"4102",
    "addr:street":"Ipswich Rd",
    "iso:country":"AU",
    "sg:address":"Princess Alexandra Hospital Ipswich Rd",
    "sg:city":"Woolloongabba",
    "sg:classifiers":[
        {
            "category":"Health Services",
            "subcategory":"Doctor",
            "type":"Services"
        }
    ],
    "sg:phone":"+61 7 3240 2721",
    "sg:postcode":"4102",
    "sg:province":"QLD",
    "sg:tags":[
        "medical",
        "practitioner"
    ],
    "wof:name":"Cameron D P",
    "wof:placetype":"venue"
},
  "geometry": {"coordinates":[153.035842895,-27.4891166687],"type":"Point"}
}