{
  "type": "Feature",
  "properties": {
    "addr:full":"PO Box 5112 Elizabeth Vale SA 5112",
    "addr:postcode":"5112",
    "iso:country":"AU",
    "sg:address":"PO Box 5112",
    "sg:city":"Elizabeth Vale",
    "sg:classifiers":[
        {
            "category":"Organizations",
            "subcategory":"Membership Organization",
            "type":"Services"
        }
    ],
    "sg:phone":"+61 8 8289 8606",
    "sg:postcode":"5112",
    "sg:province":"SA",
    "sg:tags":[
        "club",
        "car"
    ],
    "wof:name":"Ford F100 Club of Australia",
    "wof:placetype":"venue"
},
  "geometry": {"coordinates":[138.66709899899999,-34.7487602234],"type":"Point"}
}