{
  "type": "Feature",
  "properties": {
    "iso:country":"AU",
    "sg:address":"14 Mile Rd",
    "sg:city":"Garfield",
    "sg:classifiers":[
        {
            "category":"Farming",
            "subcategory":"Livestock Farm",
            "type":"Manufacturing & Wholesale Goods"
        }
    ],
    "sg:phone":"+61 3 5629 2217",
    "sg:postcode":"3814",
    "sg:province":"VIC",
    "sg:tags":[
        "agistment"
    ],
    "wof:name":"Wujeri Park Agistment",
    "wof:placetype":"venue"
},
  "geometry": {"coordinates":[145.709,-38.114147],"type":"Point"}
}