{
  "type": "Feature",
  "properties": {
    "addr:full":"90 Centre St Casino NSW 2470",
    "addr:housenumber":"90",
    "addr:postcode":"2470",
    "addr:street":"Centre St",
    "iso:country":"AU",
    "sg:address":"90 Centre St",
    "sg:city":"Casino",
    "sg:classifiers":[
        {
            "category":"Health Services",
            "subcategory":"Doctor",
            "type":"Services"
        }
    ],
    "sg:phone":"+61 2 6662 1733",
    "sg:postcode":"2470",
    "sg:province":"NSW",
    "sg:tags":[
        "medical",
        "practitioner"
    ],
    "wof:name":"Castagna A C Dr",
    "wof:placetype":"venue"
},
  "geometry": {"coordinates":[153.04745483400001,-28.8560276031],"type":"Point"}
}