{
  "type": "Feature",
  "properties": {
    "iso:country":"AU",
    "sg:address":"127 Hampton St",
    "sg:city":"Bridgetown",
    "sg:classifiers":[
        {
            "category":"Shopping",
            "subcategory":"Beauty & Cosmetics",
            "type":"Retail Goods"
        }
    ],
    "sg:phone":"+61 8 9761 1004",
    "sg:postcode":"6255",
    "sg:province":"WA",
    "wof:name":"Bridgetown Pharmacy",
    "wof:placetype":"venue"
},
  "geometry": {"coordinates":[116.137046814,-33.9577026367],"type":"Point"}
}