{
  "type": "Feature",
  "properties": {
    "addr:full":"223 Melville Rd Brunswick West VIC 3055",
    "addr:housenumber":"223",
    "addr:postcode":"3055",
    "addr:street":"Melville Rd",
    "iso:country":"AU",
    "sg:address":"223 Melville Rd",
    "sg:city":"Brunswick West",
    "sg:classifiers":[
        {
            "category":"Health Services",
            "subcategory":"Doctor",
            "type":"Services"
        }
    ],
    "sg:phone":"+61 3 9383 2493",
    "sg:postcode":"3055",
    "sg:province":"VIC",
    "sg:tags":[
        "medical",
        "practitioner"
    ],
    "wof:name":"Brunswick West Surgery",
    "wof:placetype":"venue"
},
  "geometry": {"coordinates":[144.94557189899999,-37.7542304993],"type":"Point"}
}