{
  "type": "Feature",
  "properties": {
    "addr:full":"10 Hepburn Ave Beaumaris VIC 3193",
    "addr:housenumber":"10",
    "addr:postcode":"3193",
    "addr:street":"Hepburn Ave",
    "iso:country":"AU",
    "sg:address":"10 Hepburn Ave",
    "sg:city":"Beaumaris",
    "sg:classifiers":[
        {
            "category":"Professional",
            "subcategory":"Research",
            "type":"Services"
        }
    ],
    "sg:phone":"+61 3 9589 2120",
    "sg:postcode":"3193",
    "sg:province":"VIC",
    "sg:tags":[
        "industrial",
        "scientific"
    ],
    "wof:name":"Holographic N D T & L I Q C Pty Ltd",
    "wof:placetype":"venue"
},
  "geometry": {"coordinates":[145.028686523,-37.9750900269],"type":"Point"}
}