{
  "type": "Feature",
  "properties": {
    "addr:full":"3A Smart St Mandurah WA 6210",
    "addr:housenumber":"3a",
    "addr:postcode":"6210",
    "addr:street":"Smart St",
    "iso:country":"AU",
    "sg:address":"3A Smart St",
    "sg:city":"Mandurah",
    "sg:classifiers":[
        {
            "category":"Real Estate",
            "subcategory":"Real Estate Agent",
            "type":"Services"
        }
    ],
    "sg:phone":"+61 8 9535 7349",
    "sg:postcode":"6210",
    "sg:province":"WA",
    "wof:name":"Draco Realty",
    "wof:placetype":"venue"
},
  "geometry": {"coordinates":[115.719398,-32.533474],"type":"Point"}
}