{
  "type": "Feature",
  "properties": {
    "iso:country":"AU",
    "sg:address":"Lower North East Rd",
    "sg:city":"Houghton",
    "sg:classifiers":[
        {
            "category":"Professional",
            "subcategory":"Engineering",
            "type":"Services"
        }
    ],
    "sg:phone":"+61 8 8380 5420",
    "sg:postcode":"5131",
    "sg:province":"SA",
    "sg:tags":[
        "engineer"
    ],
    "wof:name":"Martin T G",
    "wof:placetype":"venue"
},
  "geometry": {"coordinates":[138.76165771500001,-34.828327179],"type":"Point"}
}