{
  "type": "Feature",
  "properties": {
    "addr:full":"365 Bayswater Rd Garbutt QLD 4814",
    "addr:housenumber":"365",
    "addr:postcode":"4814",
    "addr:street":"Bayswater Rd",
    "iso:country":"AU",
    "sg:address":"365 Bayswater Rd",
    "sg:city":"Garbutt",
    "sg:classifiers":[
        {
            "category":"Professional",
            "subcategory":"Employment Agencies",
            "type":"Services"
        }
    ],
    "sg:phone":"+61 7 4725 5690",
    "sg:postcode":"4814",
    "sg:province":"QLD",
    "sg:tags":[
        "entertainer",
        "agent"
    ],
    "wof:name":"Metro Music",
    "wof:placetype":"venue"
},
  "geometry": {"coordinates":[146.760559,-19.272945],"type":"Point"}
}