{
  "type": "Feature",
  "properties": {
    "addr:full":"PO Box 43 Cambooya QLD 4358",
    "addr:postcode":"4358",
    "iso:country":"AU",
    "sg:address":"PO Box 43",
    "sg:city":"Cambooya",
    "sg:classifiers":[
        {
            "category":"Home & Garden",
            "subcategory":"Building Materials",
            "type":"Retail Goods"
        }
    ],
    "sg:phone":"+61 422 524 425",
    "sg:postcode":"4358",
    "sg:province":"QLD",
    "sg:tags":[
        "concrete",
        "gutter",
        "kerb"
    ],
    "wof:name":"Kerb Concrete & Bobcat",
    "wof:placetype":"venue"
},
  "geometry": {"coordinates":[151.873627,-27.708389],"type":"Point"}
}