{
  "type": "Feature",
  "properties": {
    "iso:country":"AU",
    "sg:address":"Shp16/ 21 North Avoca Pde",
    "sg:city":"Avoca",
    "sg:classifiers":[
        {
            "category":"Personal",
            "subcategory":"Beauty Salon",
            "type":"Services"
        }
    ],
    "sg:phone":"+61 2 4385 2163",
    "sg:postcode":"2577",
    "sg:province":"NSW",
    "wof:name":"Revive Body & Skin Retreat",
    "wof:placetype":"venue"
},
  "geometry": {"coordinates":[150.479248047,-34.5752410889],"type":"Point"}
}