{
  "type": "Feature",
  "properties": {
    "iso:country":"AU",
    "sg:address":"Shop 20, Australind Shopping Centre, Old Coast Roa",
    "sg:city":"Australind",
    "sg:classifiers":[
        {
            "category":"Health Services",
            "subcategory":"Optometrist",
            "type":"Services"
        }
    ],
    "sg:phone":"+61 8 9796 1966",
    "sg:postcode":"6233",
    "sg:province":"WA",
    "wof:name":"eyes@australind",
    "wof:placetype":"venue"
},
  "geometry": {"coordinates":[115.714844,-33.275146],"type":"Point"}
}