{
  "type": "Feature",
  "properties": {
    "iso:country":"AU",
    "sg:address":"Lot 4 Acyrod St",
    "sg:city":"Parkes",
    "sg:classifiers":[
        {
            "category":"Professional",
            "subcategory":"Engineering",
            "type":"Services"
        }
    ],
    "sg:phone":"+61 2 6863 4019",
    "sg:postcode":"2870",
    "sg:province":"NSW",
    "sg:tags":[
        "engineer"
    ],
    "wof:name":"Pivotal Engineering",
    "wof:placetype":"venue"
},
  "geometry": {"coordinates":[148.160049,-33.148266],"type":"Point"}
}