{
  "type": "Feature",
  "properties": {
    "addr:full":"8 Falls Rd Mt Evelyn VIC 3796",
    "addr:housenumber":"8",
    "addr:postcode":"3796",
    "addr:street":"Falls Rd",
    "iso:country":"AU",
    "sg:address":"8 Falls Rd",
    "sg:city":"Mt Evelyn",
    "sg:classifiers":[
        {
            "category":"Building & Trades",
            "subcategory":"Construction",
            "type":"Services"
        }
    ],
    "sg:phone":"+61 3 9736 3437",
    "sg:postcode":"3796",
    "sg:province":"VIC",
    "sg:tags":[
        "equipment",
        "system",
        "automation"
    ],
    "wof:name":"Applied Robotic Engineering",
    "wof:placetype":"venue"
},
  "geometry": {"coordinates":[145.37359619099999,-37.7929801941],"type":"Point"}
}