{
  "type": "Feature",
  "properties": {
    "addr:full":"21 Rutherglen Rd Newborough VIC 3825",
    "addr:housenumber":"21",
    "addr:postcode":"3825",
    "addr:street":"Rutherglen Rd",
    "iso:country":"AU",
    "sg:address":"21 Rutherglen Rd",
    "sg:city":"Newborough",
    "sg:classifiers":[
        {
            "category":"Shopping",
            "subcategory":"Bicycles & Sporting Goods",
            "type":"Retail Goods"
        }
    ],
    "sg:phone":"+61 3 5127 4133",
    "sg:postcode":"3825",
    "sg:province":"VIC",
    "sg:tags":[
        "chemical",
        "equipment",
        "pool",
        "swimming"
    ],
    "wof:name":"Latrobe Valley Pools & Chemicals",
    "wof:placetype":"venue"
},
  "geometry": {"coordinates":[146.29089400000001,-38.185818],"type":"Point"}
}