{
  "type": "Feature",
  "properties": {
    "iso:country":"AU",
    "sg:address":"20 Gordon St",
    "sg:city":"Coffs Harbour",
    "sg:classifiers":[
        {
            "category":"Shopping",
            "subcategory":"Pawn Shop",
            "type":"Retail Goods"
        }
    ],
    "sg:phone":"+61 2 6652 4333",
    "sg:postcode":"2450",
    "sg:province":"NSW",
    "sg:tags":[
        "pawnbroker"
    ],
    "wof:name":"Coffs Cash Express",
    "wof:placetype":"venue"
},
  "geometry": {"coordinates":[153.115875,-30.298706],"type":"Point"}
}