{
  "type": "Feature",
  "properties": {
    "addr:full":"36 KIllara Rd Campbellfield VIC 3061",
    "addr:housenumber":"36",
    "addr:postcode":"3061",
    "addr:street":"Killara Rd",
    "iso:country":"AU",
    "sg:address":"36 KIllara Rd",
    "sg:city":"Campbellfield",
    "sg:classifiers":[
        {
            "category":"Wholesale",
            "subcategory":"Auto Parts",
            "type":"Manufacturing & Wholesale Goods"
        }
    ],
    "sg:phone":"+61 433 424 457",
    "sg:postcode":"3061",
    "sg:province":"VIC",
    "sg:tags":[
        "recyclers"
    ],
    "wof:name":"Sac Car Removals",
    "wof:placetype":"venue"
},
  "geometry": {"coordinates":[144.96458435100001,-37.6652603149],"type":"Point"}
}