{
  "type": "Feature",
  "properties": {
    "addr:full":"7- 9 Progress St Mornington VIC 3931",
    "addr:housenumber":"9",
    "addr:postcode":"3931",
    "addr:street":"Progress St",
    "iso:country":"AU",
    "sg:address":"7- 9 Progress St",
    "sg:city":"Mornington",
    "sg:classifiers":[
        {
            "category":"Autos & Motor Vehicles",
            "subcategory":"Auto Supplies",
            "type":"Retail Goods"
        }
    ],
    "sg:phone":"+61 13 66 73",
    "sg:postcode":"3931",
    "sg:province":"VIC",
    "sg:tags":[
        "tyre"
    ],
    "wof:name":"Tyres & More",
    "wof:placetype":"venue"
},
  "geometry": {"coordinates":[145.056808472,-38.2355117798],"type":"Point"}
}