{
  "type": "Feature",
  "properties": {
    "iso:country":"AU",
    "sg:address":"15 River Rd",
    "sg:city":"Bayswater",
    "sg:classifiers":[
        {
            "category":"Manufacturing",
            "subcategory":"Furniture",
            "type":"Manufacturing & Wholesale Goods"
        }
    ],
    "sg:phone":"+61 8 9279 7022",
    "sg:postcode":"6053",
    "sg:province":"WA",
    "sg:tags":[
        "builder",
        "designer",
        "custom"
    ],
    "wof:name":"Issa Furniture Industries",
    "wof:placetype":"venue"
},
  "geometry": {"coordinates":[115.929092407,-31.9217090607],"type":"Point"}
}