{
  "type": "Feature",
  "properties": {
    "addr:full":"3 Preo Pl Tathra NSW 2550",
    "addr:housenumber":"3",
    "addr:postcode":"2550",
    "addr:street":"Preo Pl",
    "iso:country":"AU",
    "sg:address":"3 Preo Pl",
    "sg:city":"Tathra",
    "sg:classifiers":[
        {
            "category":"Professional",
            "subcategory":"Art Services",
            "type":"Services"
        }
    ],
    "sg:phone":"+61 2 6494 4128",
    "sg:postcode":"2550",
    "sg:province":"NSW",
    "sg:tags":[
        "artist"
    ],
    "wof:name":"David Mills",
    "wof:placetype":"venue"
},
  "geometry": {"coordinates":[149.985397339,-36.7294692993],"type":"Point"}
}