{
  "type": "Feature",
  "properties": {
    "addr:full":"138 Burnett St Buderim QLD 4556",
    "addr:housenumber":"138",
    "addr:postcode":"4556",
    "addr:street":"Burnett St",
    "iso:country":"AU",
    "sg:address":"138 Burnett St",
    "sg:city":"Buderim",
    "sg:classifiers":[
        {
            "category":"Museum",
            "subcategory":"Art Museum",
            "type":"Entertainment"
        }
    ],
    "sg:phone":"+61 7 5450 1722",
    "sg:postcode":"4556",
    "sg:province":"QLD",
    "sg:tags":[
        "antique",
        "fine",
        "valuer"
    ],
    "wof:name":"Tiffany Jones Fine Art Gallery",
    "wof:placetype":"venue"
},
  "geometry": {"coordinates":[153.04551696799999,-26.6910667419],"type":"Point"}
}