{
  "type": "Feature",
  "properties": {
    "iso:country":"AU",
    "sg:address":"Redgate Rd",
    "sg:city":"Witchcliffe",
    "sg:classifiers":[
        {
            "category":"Shopping",
            "subcategory":"Crafts & Fabrics",
            "type":"Retail Goods"
        }
    ],
    "sg:phone":"+61 8 9757 6415",
    "sg:postcode":"6286",
    "sg:province":"WA",
    "sg:tags":[
        "supply"
    ],
    "wof:name":"BB Bears Craft & Coffee",
    "wof:placetype":"venue"
},
  "geometry": {"coordinates":[115.09967041,-34.0261650085],"type":"Point"}
}