{
  "type": "Feature",
  "properties": {
    "addr:full":"4 Kitchen Rd Dandenong VIC 3175",
    "addr:housenumber":"4",
    "addr:postcode":"3175",
    "addr:street":"Kitchen Rd",
    "iso:country":"AU",
    "sg:address":"4 Kitchen Rd",
    "sg:city":"Dandenong",
    "sg:classifiers":[
        {
            "category":"Professional",
            "type":"Services"
        }
    ],
    "sg:phone":"+61 3 9706 4442",
    "sg:postcode":"3175",
    "sg:province":"VIC",
    "sg:tags":[
        "forwarding",
        "agent",
        "transport"
    ],
    "wof:name":"Brite Solutions Pty Ltd",
    "wof:placetype":"venue"
},
  "geometry": {"coordinates":[145.22329711899999,-38.0293426514],"type":"Point"}
}