{
  "type": "Feature",
  "properties": {
    "addr:full":"RSD 70 Gumeracha SA 5233",
    "addr:housenumber":"70",
    "addr:postcode":"5233",
    "addr:street":"Gumeracha",
    "iso:country":"AU",
    "sg:address":"RSD 70",
    "sg:city":"Gumeracha",
    "sg:classifiers":[
        {
            "category":"Building & Trades",
            "subcategory":"Construction",
            "type":"Services"
        }
    ],
    "sg:phone":"+61 408 821 825",
    "sg:postcode":"5233",
    "sg:province":"SA",
    "sg:tags":[
        "joiner",
        "carpenter"
    ],
    "wof:name":"Kersley D L & K M",
    "wof:placetype":"venue"
},
  "geometry": {"coordinates":[138.88230895999999,-34.8258018494],"type":"Point"}
}