{
  "type": "Feature",
  "properties": {
    "addr:full":"Unit 1- 185 Moggill Rd Taringa QLD 4068",
    "addr:housenumber":"185",
    "addr:postcode":"4068",
    "addr:street":"Moggill Rd",
    "iso:country":"AU",
    "sg:address":"Unit 1- 185 Moggill Rd",
    "sg:city":"Taringa",
    "sg:classifiers":[
        {
            "category":"Shopping",
            "subcategory":"Computers & Home Electronics",
            "type":"Retail Goods"
        }
    ],
    "sg:phone":"+61 7 3371 8556",
    "sg:postcode":"4068",
    "sg:province":"QLD",
    "sg:tags":[
        "equipment",
        "supply"
    ],
    "wof:name":"NCR Australia Pty Ltd",
    "wof:placetype":"venue"
},
  "geometry": {"coordinates":[152.97914123499999,-27.4926929474],"type":"Point"}
}