{
  "type": "Feature",
  "properties": {
    "addr:full":"3 Currong St Chadwick WA 6450",
    "addr:housenumber":"3",
    "addr:postcode":"6450",
    "addr:street":"Currong St",
    "iso:country":"AU",
    "sg:address":"3 Currong St",
    "sg:city":"Chadwick",
    "sg:classifiers":[
        {
            "category":"Retail",
            "subcategory":"Auto Repair",
            "type":"Services"
        }
    ],
    "sg:phone":"+61 8 9072 1411",
    "sg:postcode":"6450",
    "sg:province":"WA",
    "sg:tags":[
        "repairer",
        "motor",
        "engineer"
    ],
    "wof:name":"Dave's Mechanical Service",
    "wof:placetype":"venue"
},
  "geometry": {"coordinates":[121.88739776600001,-33.8379516602],"type":"Point"}
}