{
  "type": "Feature",
  "properties": {
    "iso:country":"AU",
    "sg:address":"65 Maitland Vale Rd",
    "sg:city":"Bolwarra Heights",
    "sg:classifiers":[
        {
            "category":"Professional",
            "subcategory":"Employment Agencies",
            "type":"Services"
        }
    ],
    "sg:phone":"+61 2 4995 6161",
    "sg:postcode":"2320",
    "sg:province":"NSW",
    "sg:tags":[
        "entertainer",
        "agent"
    ],
    "wof:name":"Joy Puppet Theatre",
    "wof:placetype":"venue"
},
  "geometry": {"coordinates":[151.57548523,-32.6867370605],"type":"Point"}
}