{
  "type": "Feature",
  "properties": {
    "iso:country":"AU",
    "sg:address":"Shop 47 Marrickville Metro Cnr Sidmore & Murray Sts",
    "sg:city":"Marrickville",
    "sg:classifiers":[
        {
            "category":"Shopping",
            "subcategory":"Clothing, Apparel, & Fashions",
            "type":"Retail Goods"
        }
    ],
    "sg:phone":"+61 2 9519 7580",
    "sg:postcode":"2204",
    "sg:province":"NSW",
    "sg:tags":[
        "menswear"
    ],
    "wof:name":"Lowes",
    "wof:placetype":"venue"
},
  "geometry": {"coordinates":[151.155319214,-33.9101753235],"type":"Point"}
}