{
  "type": "Feature",
  "properties": {
    "addr:full":"76 Cochrane St Paddington QLD 4064",
    "addr:housenumber":"76",
    "addr:postcode":"4064",
    "addr:street":"Cochrane St",
    "iso:country":"AU",
    "sg:address":"76 Cochrane St",
    "sg:city":"Paddington",
    "sg:classifiers":[
        {
            "category":"Personal",
            "subcategory":"Beauty Salon",
            "type":"Services"
        }
    ],
    "sg:phone":"+61 7 3368 3552",
    "sg:postcode":"4064",
    "sg:province":"QLD",
    "sg:tags":[
        "hairdresser"
    ],
    "wof:name":"Bach Hair",
    "wof:placetype":"venue"
},
  "geometry": {"coordinates":[153.00433349599999,-27.455909729],"type":"Point"}
}