{
  "type": "Feature",
  "properties": {
    "addr:full":"Shp1/ 67 Emerald Drv Regents Park QLD 4118",
    "addr:housenumber":"67",
    "addr:postcode":"4118",
    "addr:street":"Emerald Drv",
    "iso:country":"AU",
    "sg:address":"Shp1/ 67 Emerald Drv",
    "sg:city":"Regents Park",
    "sg:classifiers":[
        {
            "category":"Shopping",
            "subcategory":"Baby Store",
            "type":"Retail Goods"
        }
    ],
    "sg:phone":"+61 7 3806 7460",
    "sg:postcode":"4118",
    "sg:province":"QLD",
    "sg:tags":[
        "children's",
        "wear"
    ],
    "wof:name":"Kidz Clobber",
    "wof:placetype":"venue"
},
  "geometry": {"coordinates":[153.03593444800001,-27.6807250977],"type":"Point"}
}