{
  "type": "Feature",
  "properties": {
    "iso:country":"AU",
    "sg:address":"25 Vintage Pl",
    "sg:city":"Minchinbury",
    "sg:classifiers":[
        {
            "category":"Professional",
            "subcategory":"Computer Services",
            "type":"Services"
        }
    ],
    "sg:phone":"+61 2 9832 7544",
    "sg:postcode":"2770",
    "sg:province":"NSW",
    "sg:tags":[
        "consultant",
        "system"
    ],
    "wof:name":"Riverwillow Pty Ltd",
    "wof:placetype":"venue"
},
  "geometry": {"coordinates":[150.83702087399999,-33.7858390808],"type":"Point"}
}