{
  "type": "Feature",
  "properties": {
    "addr:full":"Shop 59 Straithfield Plz Strathfield NSW 2135",
    "addr:housenumber":"shop 59",
    "addr:postcode":"2135",
    "addr:street":"Straithfield Plz",
    "iso:country":"AU",
    "sg:address":"Shop 59",
    "sg:city":"Straithfield Plz Strathfield",
    "sg:classifiers":[
        {
            "category":"Shopping",
            "subcategory":"Mobile Phones",
            "type":"Retail Goods"
        }
    ],
    "sg:phone":"+61 2 9763 2225",
    "sg:postcode":"2135",
    "sg:province":"NSW",
    "sg:tags":[
        "telephone",
        "accessory"
    ],
    "wof:name":"UEI Communications",
    "wof:placetype":"venue"
},
  "geometry": {"coordinates":[151.09165954599999,-33.8767852783],"type":"Point"}
}