{
  "type": "Feature",
  "properties": {
    "addr:full":"146 Scarborough St Southport QLD 4215",
    "addr:housenumber":"146",
    "addr:postcode":"4215",
    "addr:street":"Scarborough St",
    "iso:country":"AU",
    "sg:address":"146 Scarborough St",
    "sg:city":"Southport",
    "sg:classifiers":[
        {
            "category":"Travel",
            "subcategory":"Hotels & Motels",
            "type":"Entertainment"
        }
    ],
    "sg:phone":"+61 7 5591 6399",
    "sg:postcode":"4215",
    "sg:province":"QLD",
    "sg:tags":[
        "accommodation"
    ],
    "wof:name":"Del Plaza Hotel",
    "wof:placetype":"venue"
},
  "geometry": {"coordinates":[153.41166687,-27.964214325],"type":"Point"}
}