{
  "type": "Feature",
  "properties": {
    "iso:country":"AU",
    "sg:address":"49 Norval St",
    "sg:city":"Auburn",
    "sg:classifiers":[
        {
            "category":"Health Services",
            "subcategory":"Doctor",
            "type":"Services"
        }
    ],
    "sg:phone":"+61 2 9646 3522",
    "sg:postcode":"2144",
    "sg:province":"NSW",
    "sg:tags":[
        "medical",
        "practitioner"
    ],
    "wof:name":"Richards Bruce Dr",
    "wof:placetype":"venue"
},
  "geometry": {"coordinates":[151.032470703,-33.8591651917],"type":"Point"}
}