{
  "type": "Feature",
  "properties": {
    "addr:full":"240 Cowper St Goulburn NSW 2580",
    "addr:housenumber":"240",
    "addr:postcode":"2580",
    "addr:street":"Cowper St",
    "iso:country":"AU",
    "sg:address":"240 Cowper St",
    "sg:city":"Goulburn",
    "sg:classifiers":[
        {
            "category":"Social Services",
            "subcategory":"Retirement Home",
            "type":"Services"
        }
    ],
    "sg:phone":"+61 2 4821 0973",
    "sg:postcode":"2580",
    "sg:province":"NSW",
    "sg:tags":[
        "environmental",
        "consultant",
        "pollution"
    ],
    "wof:name":"Laterals Environmental",
    "wof:placetype":"venue"
},
  "geometry": {"coordinates":[149.71841430699999,-34.7470092773],"type":"Point"}
}