{
  "type": "Feature",
  "properties": {
    "iso:country":"AU",
    "sg:address":"10 Elcho Pl",
    "sg:city":"Carindale",
    "sg:classifiers":[
        {
            "category":"Professional",
            "subcategory":"Art Services",
            "type":"Services"
        }
    ],
    "sg:phone":"+61 7 3398 2553",
    "sg:postcode":"4152",
    "sg:province":"QLD",
    "sg:tags":[
        "decorator",
        "painter"
    ],
    "wof:name":"A & A Painters",
    "wof:placetype":"venue"
},
  "geometry": {"coordinates":[153.11239624000001,-27.5021800995],"type":"Point"}
}