{
  "type": "Feature",
  "properties": {
    "addr:full":"255 Clayton Rd Clayton VIC 3168",
    "addr:housenumber":"255",
    "addr:postcode":"3168",
    "addr:street":"Clayton Rd",
    "iso:country":"AU",
    "sg:address":"255 Clayton Rd",
    "sg:city":"Clayton",
    "sg:classifiers":[
        {
            "category":"Health Services",
            "subcategory":"Doctor",
            "type":"Services"
        }
    ],
    "sg:phone":"+61 3 9013 9795",
    "sg:postcode":"3168",
    "sg:province":"VIC",
    "sg:tags":[
        "medical",
        "practitioner"
    ],
    "wof:name":"Bella Weisman Dr",
    "wof:placetype":"venue"
},
  "geometry": {"coordinates":[145.120635986,-37.9194908142],"type":"Point"}
}