{
  "type": "Feature",
  "properties": {
    "addr:full":"Unit 3/ 484 Stirling Hwy Cottesloe WA 6011",
    "addr:housenumber":"/ 484",
    "addr:postcode":"6011",
    "addr:street":"Stirling Hwy",
    "iso:country":"AU",
    "sg:address":"Unit 3/ 484 Stirling Hwy",
    "sg:city":"Cottesloe",
    "sg:classifiers":[
        {
            "category":"Health Services",
            "subcategory":"Doctor",
            "type":"Services"
        }
    ],
    "sg:phone":"+61 8 9383 3435",
    "sg:postcode":"6011",
    "sg:province":"WA",
    "sg:tags":[
        "medical",
        "practitioner"
    ],
    "wof:name":"Health Watch Clinics",
    "wof:placetype":"venue"
},
  "geometry": {"coordinates":[115.762283325,-31.9989547729],"type":"Point"}
}