{
  "type": "Feature",
  "properties": {
    "iso:country":"AU",
    "sg:address":"211- 215 Canterbury Rd",
    "sg:city":"Canterbury",
    "sg:classifiers":[
        {
            "category":"Professional",
            "subcategory":"Detective & Security Services",
            "type":"Services"
        }
    ],
    "sg:phone":"+61 2 9718 8288",
    "sg:postcode":"2193",
    "sg:province":"NSW",
    "sg:tags":[
        "equipment",
        "window",
        "doors"
    ],
    "wof:name":"Gatewise Pty Ltd",
    "wof:placetype":"venue"
},
  "geometry": {"coordinates":[151.117813,-33.912815],"type":"Point"}
}