{
  "type": "Feature",
  "properties": {
    "addr:full":"211- 215 Canterbury Rd Canterbury NSW 2193",
    "addr:housenumber":"215",
    "addr:postcode":"2193",
    "addr:street":"Canterbury Rd",
    "iso:country":"AU",
    "sg:address":"211- 215 Canterbury Rd",
    "sg:city":"Canterbury",
    "sg:classifiers":[
        {
            "category":"Professional",
            "subcategory":"Detective & Security Services",
            "type":"Services"
        }
    ],
    "sg:phone":"+61 2 9718 8288",
    "sg:postcode":"2193",
    "sg:province":"NSW",
    "sg:tags":[
        "equipment",
        "window",
        "doors"
    ],
    "wof:name":"Gatewise Pty Ltd",
    "wof:placetype":"venue"
},
  "geometry": {"coordinates":[151.11781300000001,-33.912815],"type":"Point"}
}