{
  "type": "Feature",
  "properties": {
    "iso:country":"AU",
    "sg:address":"4C Targo St",
    "sg:city":"Bundaberg",
    "sg:classifiers":[
        {
            "category":"Professional",
            "subcategory":"Printing & Photocopies",
            "type":"Services"
        }
    ],
    "sg:phone":"+61 7 4152 0600",
    "sg:postcode":"4670",
    "sg:province":"QLD",
    "sg:tags":[
        "photocopying"
    ],
    "wof:name":"Discount Stationery and Copy Centre",
    "wof:placetype":"venue"
},
  "geometry": {"coordinates":[152.350952148,-24.8647327423],"type":"Point"}
}