{
  "type": "Feature",
  "properties": {
    "addr:full":"351 Dalton Rd Epping VIC 3076",
    "addr:housenumber":"351",
    "addr:postcode":"3076",
    "addr:street":"Dalton Rd",
    "iso:country":"AU",
    "sg:address":"351 Dalton Rd",
    "sg:city":"Epping",
    "sg:classifiers":[
        {
            "category":"Health Services",
            "subcategory":"Optometrist",
            "type":"Services"
        }
    ],
    "sg:phone":"+61 3 9408 8414",
    "sg:postcode":"3076",
    "sg:province":"VIC",
    "wof:name":"De Santis Vision Consultants",
    "wof:placetype":"venue"
},
  "geometry": {"coordinates":[144.929077148,-37.6498374939],"type":"Point"}
}