{
  "type": "Feature",
  "properties": {
    "iso:country":"AU",
    "sg:address":"PO Box 4178",
    "sg:city":"Edgeworth",
    "sg:classifiers":[
        {
            "category":"Professional",
            "subcategory":"Accounting & Tax Preparation",
            "type":"Services"
        }
    ],
    "sg:phone":"+61 2 4958 8881",
    "sg:postcode":"2285",
    "sg:province":"NSW",
    "sg:tags":[
        "accountant",
        "auditor"
    ],
    "wof:name":"Archer Accounting",
    "wof:placetype":"venue"
},
  "geometry": {"coordinates":[151.612884522,-32.9235305786],"type":"Point"}
}