{
  "type": "Feature",
  "properties": {
    "addr:full":"10 Campus St Indooroopilly QLD 4068",
    "addr:housenumber":"10",
    "addr:postcode":"4068",
    "addr:street":"Campus St",
    "iso:country":"AU",
    "sg:address":"10 Campus St",
    "sg:city":"Indooroopilly",
    "sg:classifiers":[
        {
            "category":"Utilities",
            "subcategory":"Telephone",
            "type":"Services"
        }
    ],
    "sg:phone":"+61 7 3281 5978",
    "sg:postcode":"4068",
    "sg:province":"QLD",
    "sg:tags":[
        "equipment",
        "system"
    ],
    "wof:name":"Brisbane Telephone Systems",
    "wof:placetype":"venue"
},
  "geometry": {"coordinates":[152.97962951700001,-27.5016689301],"type":"Point"}
}