{
  "type": "Feature",
  "properties": {
    "addr:full":"Cnr Charles & Cimitiere Sts Launceston TAS 7250",
    "addr:postcode":"7250",
    "addr:street":"Cnr",
    "iso:country":"AU",
    "sg:address":"Cnr Charles & Cimitiere Sts",
    "sg:city":"Launceston",
    "sg:classifiers":[
        {
            "category":"Organizations",
            "subcategory":"Professional Association",
            "type":"Services"
        }
    ],
    "sg:phone":"+61 3 6331 6377",
    "sg:postcode":"7250",
    "sg:province":"TAS",
    "sg:tags":[
        "rural",
        "organisation",
        "production",
        "primary"
    ],
    "wof:name":"Tasmanian Farmers & Graziers Association",
    "wof:placetype":"venue"
},
  "geometry": {"coordinates":[147.133422852,-41.4366607666],"type":"Point"}
}