{
  "type": "Feature",
  "properties": {
    "addr:full":"6-7 Cotter St Underbool VIC 3509",
    "addr:housenumber":"6-7",
    "addr:postcode":"3509",
    "addr:street":"Cotter St",
    "iso:country":"AU",
    "sg:address":"6-7 Cotter St",
    "sg:city":"Underbool",
    "sg:classifiers":[
        {
            "category":"Autos & Motor Vehicles",
            "subcategory":"Fuel & Gas Station",
            "type":"Retail Goods"
        }
    ],
    "sg:phone":"+61 3 5094 6270",
    "sg:postcode":"3509",
    "sg:province":"VIC",
    "wof:name":"Ampol Service Station",
    "wof:placetype":"venue"
},
  "geometry": {"coordinates":[141.80760192899999,-35.1696205139],"type":"Point"}
}