{
  "type": "Feature",
  "properties": {
    "addr:full":"83-89 Currie St Adelaide SA 5000",
    "addr:housenumber":"83-89",
    "addr:postcode":"5000",
    "addr:street":"Currie St",
    "iso:country":"AU",
    "sg:address":"83-89 Currie St",
    "sg:city":"Adelaide",
    "sg:classifiers":[
        {
            "category":"Professional",
            "subcategory":"Accounting & Tax Preparation",
            "type":"Services"
        }
    ],
    "sg:phone":"+61 8 8231 4725",
    "sg:postcode":"5000",
    "sg:province":"SA",
    "sg:tags":[
        "accountant",
        "auditor"
    ],
    "wof:name":"Standish D M",
    "wof:placetype":"venue"
},
  "geometry": {"coordinates":[138.59637451200001,-34.924747467],"type":"Point"}
}