{
  "type": "Feature",
  "properties": {
    "addr:full":"Cnr colchester & Tribune St South Brisbane QLD 4101",
    "addr:postcode":"4101",
    "addr:street":"Cnr;St",
    "iso:country":"AU",
    "sg:address":"Cnr colchester & Tribune St",
    "sg:city":"South Brisbane",
    "sg:classifiers":[
        {
            "category":"Food & Beverages",
            "subcategory":"Bakery",
            "type":"Retail Goods"
        }
    ],
    "sg:phone":"+61 7 3244 5845",
    "sg:postcode":"4101",
    "sg:province":"QLD",
    "sg:tags":[
        "baker"
    ],
    "wof:name":"Demeters Bakery",
    "wof:placetype":"venue"
},
  "geometry": {"coordinates":[153.02084350600001,-27.4794311523],"type":"Point"}
}