{
  "type": "Feature",
  "properties": {
    "addr:full":"2- 6 Dixon Ave Croydon VIC 3136",
    "addr:housenumber":"6",
    "addr:postcode":"3136",
    "addr:street":"Dixon Ave",
    "iso:country":"AU",
    "sg:address":"2- 6 Dixon Ave",
    "sg:city":"Croydon",
    "sg:classifiers":[
        {
            "category":"Organizations",
            "subcategory":"Non-profit Organization",
            "type":"Services"
        }
    ],
    "sg:phone":"+61 3 9725 8677",
    "sg:postcode":"3136",
    "sg:province":"VIC",
    "sg:tags":[
        "support",
        "disability",
        "organisation"
    ],
    "wof:name":"Monkami Centre Inc.",
    "wof:placetype":"venue"
},
  "geometry": {"coordinates":[145.29133605999999,-37.785900116],"type":"Point"}
}