{
  "type": "Feature",
  "properties": {
    "addr:full":"Suite 5, 884 Beaufort St 884 Beaufort St Inglewood WA 6052",
    "addr:housenumber":"884;884",
    "addr:postcode":"6052",
    "addr:street":"Beaufort St;Beaufort St",
    "iso:country":"AU",
    "sg:address":"Suite 5, 884 Beaufort St 884 Beaufort St",
    "sg:city":"Inglewood",
    "sg:classifiers":[
        {
            "category":"Organizations",
            "subcategory":"Professional Association",
            "type":"Services"
        }
    ],
    "sg:phone":"+61 8 9228 2233",
    "sg:postcode":"6052",
    "sg:province":"WA",
    "sg:tags":[
        "web",
        "internet"
    ],
    "wof:name":"Bam Creative",
    "wof:placetype":"venue"
},
  "geometry": {"coordinates":[115.886482239,-31.9211196899],"type":"Point"}
}