{
  "type": "Feature",
  "properties": {
    "addr:full":"55 Molesworth St Lismore NSW 2480",
    "addr:housenumber":"55",
    "addr:postcode":"2480",
    "addr:street":"Molesworth St",
    "iso:country":"AU",
    "sg:address":"55 Molesworth St",
    "sg:city":"Lismore",
    "sg:classifiers":[
        {
            "category":"Professional",
            "subcategory":"Accounting & Tax Preparation",
            "type":"Services"
        }
    ],
    "sg:phone":"+61 2 6621 5701",
    "sg:postcode":"2480",
    "sg:province":"NSW",
    "sg:tags":[
        "consultant",
        "taxation"
    ],
    "wof:name":"Nind Peter H",
    "wof:placetype":"venue"
},
  "geometry": {"coordinates":[153.27699279800001,-28.8073348999],"type":"Point"}
}