{
  "type": "Feature",
  "properties": {
    "iso:country":"AU",
    "sg:address":"59 Mawson Rd",
    "sg:city":"Meadows",
    "sg:classifiers":[
        {
            "category":"Retail",
            "subcategory":"Veterinary Services",
            "type":"Services"
        }
    ],
    "sg:phone":"+61 8 8388 3455",
    "sg:postcode":"5201",
    "sg:province":"SA",
    "sg:tags":[
        "surgeon"
    ],
    "wof:name":"Meadows Veterinary Surgery",
    "wof:placetype":"venue"
},
  "geometry": {"coordinates":[138.744537353,-35.1826629639],"type":"Point"}
}