{
  "type": "Feature",
  "properties": {
    "iso:country":"AU",
    "sg:address":"Lookout Rd",
    "sg:city":"New Lambton",
    "sg:classifiers":[
        {
            "category":"Social Services",
            "subcategory":"Child Care",
            "type":"Services"
        }
    ],
    "sg:phone":"+61 2 4921 4161",
    "sg:postcode":"2305",
    "sg:province":"NSW",
    "wof:name":"Possum Place Child Care Centre",
    "wof:placetype":"venue"
},
  "geometry": {"coordinates":[151.70137,-32.922161],"type":"Point"}
}