{
  "type": "Feature",
  "properties": {
    "iso:country":"AU",
    "sg:address":"221 Barker St",
    "sg:city":"Castlemaine",
    "sg:classifiers":[
        {
            "category":"Fast Food",
            "type":"Food & Drink"
        }
    ],
    "sg:phone":"+61 3 5472 1697",
    "sg:postcode":"3450",
    "sg:province":"VIC",
    "sg:tags":[
        "away",
        "take"
    ],
    "wof:name":"Allstart Noodles",
    "wof:placetype":"venue"
},
  "geometry": {"coordinates":[144.22198486299999,-37.0486412048],"type":"Point"}
}