{
  "type": "Feature",
  "properties": {
    "addr:full":"6 Hartwell Crt St Clair NSW 2759",
    "addr:housenumber":"6",
    "addr:postcode":"2759",
    "addr:street":"Hartwell Crt",
    "iso:country":"AU",
    "sg:address":"6 Hartwell Crt",
    "sg:city":"St Clair",
    "sg:classifiers":[
        {
            "category":"Building & Trades",
            "subcategory":"Construction",
            "type":"Services"
        }
    ],
    "sg:phone":"+61 2 9670 5551",
    "sg:postcode":"2759",
    "sg:province":"NSW",
    "sg:tags":[
        "home",
        "air conditioning"
    ],
    "wof:name":"Anjums Airconditioning",
    "wof:placetype":"venue"
},
  "geometry": {"coordinates":[150.80456543,-33.7919616699],"type":"Point"}
}