{
  "type": "Feature",
  "properties": {
    "iso:country":"AU",
    "sg:address":"84 Kedron Park Rd",
    "sg:city":"Wooloowin",
    "sg:classifiers":[
        {
            "category":"Conference Center",
            "type":"Public Place"
        }
    ],
    "sg:phone":"+61 7 3357 0500",
    "sg:postcode":"4030",
    "sg:province":"QLD",
    "sg:tags":[
        "venue",
        "convention"
    ],
    "wof:name":"Warilda Conference Centre",
    "wof:placetype":"venue"
},
  "geometry": {"coordinates":[153.03952,-27.418343],"type":"Point"}
}