{
  "type": "Feature",
  "properties": {
    "addr:full":"Shop 7 Sturt Mall Wagga Wagga NSW 2650",
    "addr:housenumber":"shop 7",
    "addr:postcode":"2650",
    "addr:street":"Sturt Mall",
    "iso:country":"AU",
    "sg:address":"Shop 7 Sturt Mall",
    "sg:city":"Wagga Wagga",
    "sg:classifiers":[
        {
            "category":"Food & Beverages",
            "subcategory":"Bakery",
            "type":"Retail Goods"
        }
    ],
    "sg:phone":"+61 2 6921 3441",
    "sg:postcode":"2650",
    "sg:province":"NSW",
    "sg:tags":[
        "baker"
    ],
    "wof:name":"Bread Crock Bakery Cafe",
    "wof:placetype":"venue"
},
  "geometry": {"coordinates":[147.37083435100001,-35.1054801941],"type":"Point"}
}