{
  "type": "Feature",
  "properties": {
    "addr:full":"4 Berith St Umina NSW 2257",
    "addr:housenumber":"4",
    "addr:postcode":"2257",
    "addr:street":"Berith St",
    "iso:country":"AU",
    "sg:address":"4 Berith St",
    "sg:city":"Umina",
    "sg:classifiers":[
        {
            "category":"Government",
            "subcategory":"Court House",
            "type":"Public Place"
        }
    ],
    "sg:phone":"+61 2 4342 7447",
    "sg:postcode":"2257",
    "sg:province":"NSW",
    "sg:tags":[
        "personal",
        "marriage",
        "family",
        "counselling"
    ],
    "wof:name":"Sue McConaghey",
    "wof:placetype":"venue"
},
  "geometry": {"coordinates":[151.318237305,-33.5219726562],"type":"Point"}
}