{
  "type": "Feature",
  "properties": {
    "addr:full":"21 Osprey Drv Berkeley NSW 2506",
    "addr:housenumber":"21",
    "addr:postcode":"2506",
    "addr:street":"Osprey Drv",
    "iso:country":"AU",
    "sg:address":"21 Osprey Drv",
    "sg:city":"Berkeley",
    "sg:classifiers":[
        {
            "category":"Retail",
            "subcategory":"Auto Repair",
            "type":"Services"
        }
    ],
    "sg:phone":"+61 409 828 807",
    "sg:postcode":"2506",
    "sg:province":"NSW",
    "sg:tags":[
        "repairer",
        "motor",
        "engineer"
    ],
    "wof:name":"Coast To Coast Automotive",
    "wof:placetype":"venue"
},
  "geometry": {"coordinates":[150.86293000000001,-34.478771],"type":"Point"}
}