{
  "type": "Feature",
  "properties": {
    "iso:country":"AU",
    "sg:address":"Unit 6 8- 12 Sandilands St",
    "sg:city":"South Melbourne",
    "sg:classifiers":[
        {
            "category":"Professional",
            "subcategory":"Art Services",
            "type":"Services"
        }
    ],
    "sg:phone":"+61 3 9696 6397",
    "sg:postcode":"3205",
    "sg:province":"VIC",
    "sg:tags":[
        "graphic",
        "designer"
    ],
    "wof:name":"Colour & Movement Design",
    "wof:placetype":"venue"
},
  "geometry": {"coordinates":[144.96817016599999,-37.836566925],"type":"Point"}
}