{
  "type": "Feature",
  "properties": {
    "addr:full":"24 Edward St Wagga Wagga NSW 2650",
    "addr:housenumber":"24",
    "addr:postcode":"2650",
    "addr:street":"Edward St",
    "iso:country":"AU",
    "sg:address":"24 Edward St",
    "sg:city":"Wagga Wagga",
    "sg:classifiers":[
        {
            "category":"Transit Center",
            "subcategory":"Freight",
            "type":"Transportation"
        }
    ],
    "sg:phone":"+61 2 6921 8699",
    "sg:postcode":"2650",
    "sg:province":"NSW",
    "sg:tags":[
        "weighbridge"
    ],
    "wof:name":"Mac's Trailers & Towbars",
    "wof:placetype":"venue"
},
  "geometry": {"coordinates":[147.37796020499999,-35.1213569641],"type":"Point"}
}