{
  "type": "Feature",
  "properties": {
    "addr:full":"131 Panorama Drv Nambour QLD 4560",
    "addr:housenumber":"131",
    "addr:postcode":"4560",
    "addr:street":"Panorama Drv",
    "iso:country":"AU",
    "sg:address":"131 Panorama Drv",
    "sg:city":"Nambour",
    "sg:classifiers":[
        {
            "category":"Building & Trades",
            "subcategory":"Construction",
            "type":"Services"
        }
    ],
    "sg:phone":"+61 7 5441 3065",
    "sg:postcode":"4560",
    "sg:province":"QLD",
    "sg:tags":[
        "contractor"
    ],
    "wof:name":"Brown & Thorne Pty Ltd",
    "wof:placetype":"venue"
},
  "geometry": {"coordinates":[152.971435547,-26.6332206726],"type":"Point"}
}