{
  "type": "Feature",
  "properties": {
    "iso:country":"AU",
    "sg:address":"61 Belmont St",
    "sg:city":"Merrylands",
    "sg:classifiers":[
        {
            "category":"Home & Garden",
            "subcategory":"Furniture",
            "type":"Retail Goods"
        }
    ],
    "sg:phone":"+61 411 693 283",
    "sg:postcode":"2160",
    "sg:province":"NSW",
    "sg:tags":[
        "repair",
        "restoration"
    ],
    "wof:name":"Cas Mobile Furniture Repairs",
    "wof:placetype":"venue"
},
  "geometry": {"coordinates":[150.98469543499999,-33.844379425],"type":"Point"}
}