{
  "type": "Feature",
  "properties": {
    "addr:full":"15 Mitchell St Rosebud VIC 3939",
    "addr:housenumber":"15",
    "addr:postcode":"3939",
    "addr:street":"Mitchell St",
    "iso:country":"AU",
    "sg:address":"15 Mitchell St",
    "sg:city":"Rosebud",
    "sg:classifiers":[
        {
            "category":"Education",
            "subcategory":"University",
            "type":"Public Place"
        }
    ],
    "sg:phone":"+61 3 5982 2811",
    "sg:postcode":"3939",
    "sg:province":"VIC",
    "sg:tags":[
        "educational",
        "organisation",
        "cultural"
    ],
    "wof:name":"Peninsula Adult Education & Literacy",
    "wof:placetype":"venue"
},
  "geometry": {"coordinates":[144.91282653799999,-38.3543395996],"type":"Point"}
}