{
  "type": "Feature",
  "properties": {
    "addr:full":"247 Bay St Brighton-le-Sands NSW 2216",
    "addr:housenumber":"247",
    "addr:postcode":"2216",
    "addr:street":"Bay St",
    "iso:country":"AU",
    "sg:address":"247 Bay St",
    "sg:city":"Brighton-le-Sands",
    "sg:classifiers":[
        {
            "category":"Health Services",
            "subcategory":"Dentist",
            "type":"Services"
        }
    ],
    "sg:phone":"+61 2 9597 7999",
    "sg:postcode":"2216",
    "sg:province":"NSW",
    "wof:name":"Australian Institute of Implant Dentistry",
    "wof:placetype":"venue"
},
  "geometry": {"coordinates":[151.15206900000001,-33.959259],"type":"Point"}
}