{
  "type": "Feature",
  "properties": {
    "addr:full":"Rowlands Creek Rd Uki NSW 2484",
    "addr:postcode":"nsw 2484",
    "addr:street":"Creek Rd",
    "iso:country":"AU",
    "sg:address":"Rowlands Creek Rd",
    "sg:city":"Uki",
    "sg:classifiers":[
        {
            "category":"Building & Trades",
            "subcategory":"Plumbing",
            "type":"Services"
        }
    ],
    "sg:phone":"+61 2 6679 5478",
    "sg:postcode":"2484",
    "sg:province":"NSW",
    "sg:tags":[
        "plumber",
        "gasfitters"
    ],
    "wof:name":"Daly M J",
    "wof:placetype":"venue"
},
  "geometry": {"coordinates":[153.33596801799999,-28.413980484],"type":"Point"}
}