{
  "type": "Feature",
  "properties": {
    "addr:full":"27 Dennis St Campbellfield VIC 3061",
    "addr:housenumber":"27",
    "addr:postcode":"3061",
    "addr:street":"Dennis St",
    "iso:country":"AU",
    "sg:address":"27 Dennis St",
    "sg:city":"Campbellfield",
    "sg:classifiers":[
        {
            "category":"Shopping",
            "subcategory":"Crafts & Fabrics",
            "type":"Retail Goods"
        }
    ],
    "sg:phone":"+61 3 9308 9255",
    "sg:postcode":"3061",
    "sg:province":"VIC",
    "sg:tags":[
        "adhesive"
    ],
    "wof:name":"Ardex Australia Pty Ltd",
    "wof:placetype":"venue"
},
  "geometry": {"coordinates":[144.94139099099999,-37.6433067322],"type":"Point"}
}