{
  "type": "Feature",
  "properties": {
    "iso:country":"AU",
    "sg:address":"28 Banksia Ave",
    "sg:city":"Engadine",
    "sg:classifiers":[
        {
            "category":"Banks & Credit Unions",
            "subcategory":"Financial Services",
            "type":"Services"
        }
    ],
    "sg:phone":"+61 2 9548 0222",
    "sg:postcode":"2233",
    "sg:province":"NSW",
    "sg:tags":[
        "planning"
    ],
    "wof:name":"Financial Cents",
    "wof:placetype":"venue"
},
  "geometry": {"coordinates":[151.00802612300001,-34.0604438782],"type":"Point"}
}