{
  "type": "Feature",
  "properties": {
    "addr:full":"PO Box 119 Billinudgel NSW 2483",
    "addr:postcode":"2483",
    "iso:country":"AU",
    "sg:address":"PO Box 119",
    "sg:city":"Billinudgel",
    "sg:classifiers":[
        {
            "category":"Health Services",
            "subcategory":"Health Practitioner",
            "type":"Services"
        }
    ],
    "sg:phone":"+61 2 6680 4434",
    "sg:postcode":"2483",
    "sg:province":"NSW",
    "sg:tags":[
        "technique",
        "alexander"
    ],
    "wof:name":"Varda Shepherd",
    "wof:placetype":"venue"
},
  "geometry": {"coordinates":[153.51637268100001,-28.4881706238],"type":"Point"}
}