{
  "type": "Feature",
  "properties": {
    "addr:full":"54 Forge St Blacktown NSW 2148",
    "addr:housenumber":"54",
    "addr:postcode":"2148",
    "addr:street":"Forge St",
    "iso:country":"AU",
    "sg:address":"54 Forge St",
    "sg:city":"Blacktown",
    "sg:classifiers":[
        {
            "category":"Autos & Motor Vehicles",
            "subcategory":"Automobile Sales",
            "type":"Retail Goods"
        }
    ],
    "sg:phone":"+61 2 9831 3599",
    "sg:postcode":"2148",
    "sg:province":"NSW",
    "sg:tags":[
        "equipment",
        "trailer"
    ],
    "wof:name":"Carter Wesco",
    "wof:placetype":"venue"
},
  "geometry": {"coordinates":[150.91030883799999,-33.7522125244],"type":"Point"}
}