{
  "type": "Feature",
  "properties": {
    "addr:full":"13 Lalor St Ballarat East VIC 3350",
    "addr:housenumber":"13",
    "addr:postcode":"3350",
    "addr:street":"Lalor St",
    "iso:country":"AU",
    "sg:address":"13 Lalor St",
    "sg:city":"Ballarat East",
    "sg:classifiers":[
        {
            "category":"Building & Trades",
            "subcategory":"Construction",
            "type":"Services"
        }
    ],
    "sg:phone":"+61 3 5331 7933",
    "sg:postcode":"3350",
    "sg:province":"VIC",
    "sg:tags":[
        "industrial",
        "commercial",
        "air conditioning"
    ],
    "wof:name":"Aquair Pty Ltd",
    "wof:placetype":"venue"
},
  "geometry": {"coordinates":[143.88986199999999,-37.563496],"type":"Point"}
}