{
  "type": "Feature",
  "properties": {
    "iso:country":"AU",
    "sg:address":"193 Grange Rd",
    "sg:city":"St Georges Basin",
    "sg:classifiers":[
        {
            "category":"Building & Trades",
            "subcategory":"Plumbing",
            "type":"Services"
        }
    ],
    "sg:phone":"+61 2 4443 4610",
    "sg:postcode":"2540",
    "sg:province":"NSW",
    "sg:tags":[
        "plumber",
        "gasfitters"
    ],
    "wof:name":"Purdy Bill",
    "wof:placetype":"venue"
},
  "geometry": {"coordinates":[150.57228088400001,-35.0827598572],"type":"Point"}
}