{
  "type": "Feature",
  "properties": {
    "addr:full":"66 Hillwood Ave Warwick WA 6024",
    "addr:housenumber":"66",
    "addr:postcode":"6024",
    "addr:street":"Hillwood Ave",
    "iso:country":"AU",
    "sg:address":"66 Hillwood Ave",
    "sg:city":"Warwick",
    "sg:classifiers":[
        {
            "category":"Insurance",
            "subcategory":"Insurance Agent",
            "type":"Services"
        }
    ],
    "sg:phone":"+61 8 9448 1864",
    "sg:postcode":"6024",
    "sg:province":"WA",
    "sg:tags":[
        "broker"
    ],
    "wof:name":"Statham Reg",
    "wof:placetype":"venue"
},
  "geometry": {"coordinates":[115.80342102,-31.8352298737],"type":"Point"}
}