{
  "type": "Feature",
  "properties": {
    "iso:country":"AU",
    "sg:address":"2/43- 49 Sandgate Rd",
    "sg:city":"Albion",
    "sg:classifiers":[
        {
            "category":"Shopping",
            "subcategory":"Computers & Home Electronics",
            "type":"Retail Goods"
        }
    ],
    "sg:phone":"+61 7 3862 2622",
    "sg:postcode":"4010",
    "sg:province":"QLD",
    "sg:tags":[
        "hardware",
        "equipment"
    ],
    "wof:name":"Anabelle Bits Pty Ltd",
    "wof:placetype":"venue"
},
  "geometry": {"coordinates":[153.04293823200001,-27.439043045],"type":"Point"}
}