{
  "type": "Feature",
  "properties": {
    "addr:full":"Somersby 25 Somersby Falls Rd Somersby NSW 2250",
    "addr:housenumber":"25",
    "addr:postcode":"2250",
    "addr:street":"Somersby;Falls Rd",
    "iso:country":"AU",
    "sg:address":"Somersby 25 Somersby Falls Rd",
    "sg:city":"Somersby",
    "sg:classifiers":[
        {
            "category":"Building & Trades",
            "subcategory":"Construction",
            "type":"Services"
        }
    ],
    "sg:phone":"+61 13 67 24",
    "sg:postcode":"2250",
    "sg:province":"NSW",
    "sg:tags":[
        "scaffolding"
    ],
    "wof:name":"PCH Group Ltd",
    "wof:placetype":"venue"
},
  "geometry": {"coordinates":[151.27713012699999,-33.4023170471],"type":"Point"}
}