{
  "type": "Feature",
  "properties": {
    "addr:full":"Cnr Mimosa & Prairie Vale Rds Bossley Park NSW 2176",
    "addr:postcode":"2176",
    "addr:street":"Cnr Mimosa &;Vale",
    "iso:country":"AU",
    "sg:address":"Cnr Mimosa & Prairie Vale Rds",
    "sg:city":"Bossley Park",
    "sg:classifiers":[
        {
            "category":"Education",
            "subcategory":"School",
            "type":"Public Place"
        }
    ],
    "sg:phone":"+61 2 9604 0922",
    "sg:postcode":"2176",
    "sg:province":"NSW",
    "sg:tags":[
        "state",
        "-",
        "nsw"
    ],
    "wof:name":"Prairie Vale Public School",
    "wof:placetype":"venue"
},
  "geometry": {"coordinates":[150.890335083,-33.8608055115],"type":"Point"}
}