{
  "type": "Feature",
  "properties": {
    "addr:full":"Mc.Intosh St Inverloch VIC 3996",
    "addr:postcode":"3996",
    "iso:country":"AU",
    "sg:address":"Mc.Intosh St",
    "sg:city":"Inverloch",
    "sg:classifiers":[
        {
            "category":"Retail",
            "subcategory":"Storage",
            "type":"Services"
        }
    ],
    "sg:phone":"+61 3 5674 3655",
    "sg:postcode":"3996",
    "sg:province":"VIC",
    "sg:tags":[
        "removal",
        "furniture"
    ],
    "wof:name":"Inverloch Storage Units",
    "wof:placetype":"venue"
},
  "geometry": {"coordinates":[145.71803299999999,-38.629723],"type":"Point"}
}