{
  "type": "Feature",
  "properties": {
    "iso:country":"AU",
    "sg:address":"Upper Rosemount Rd",
    "sg:city":"Nambour",
    "sg:classifiers":[
        {
            "category":"Wholesale",
            "subcategory":"Machinery & Supplies",
            "type":"Manufacturing & Wholesale Goods"
        }
    ],
    "sg:phone":"+61 408 708 724",
    "sg:postcode":"4560",
    "sg:province":"QLD",
    "sg:tags":[
        "agricultural"
    ],
    "wof:name":"Mobile Machinery Repairs",
    "wof:placetype":"venue"
},
  "geometry": {"coordinates":[152.99667358400001,-26.6279659271],"type":"Point"}
}