{
  "type": "Feature",
  "properties": {
    "addr:full":"61 Gallipoli Ave Umina NSW 2257",
    "addr:housenumber":"61",
    "addr:postcode":"2257",
    "addr:street":"Gallipoli Ave",
    "iso:country":"AU",
    "sg:address":"61 Gallipoli Ave",
    "sg:city":"Umina",
    "sg:classifiers":[
        {
            "category":"Building & Trades",
            "subcategory":"Construction",
            "type":"Services"
        }
    ],
    "sg:phone":"+61 2 4344 6338",
    "sg:postcode":"2257",
    "sg:province":"NSW",
    "sg:tags":[
        "industrial",
        "commercial",
        "air conditioning"
    ],
    "wof:name":"Banks Air Conditioning",
    "wof:placetype":"venue"
},
  "geometry": {"coordinates":[151.32330322300001,-33.5065498352],"type":"Point"}
}