{
  "type": "Feature",
  "properties": {
    "addr:full":"2/ 10 Wingate Rd McGraths Hill NSW 2756",
    "addr:housenumber":"/ 10",
    "addr:postcode":"2756",
    "addr:street":"Wingate Rd",
    "iso:country":"AU",
    "sg:address":"2/ 10 Wingate Rd",
    "sg:city":"McGraths Hill",
    "sg:classifiers":[
        {
            "category":"Home & Garden",
            "subcategory":"Building Materials",
            "type":"Retail Goods"
        }
    ],
    "sg:phone":"+61 2 4577 4444",
    "sg:postcode":"2756",
    "sg:province":"NSW",
    "sg:tags":[
        "merchant",
        "glass",
        "glazier"
    ],
    "wof:name":"Wilberforce Glass & Aluminium",
    "wof:placetype":"venue"
},
  "geometry": {"coordinates":[150.83535766599999,-33.6214103699],"type":"Point"}
}