{
  "type": "Feature",
  "properties": {
    "addr:full":"687 Faraday Rd Sutton Grange VIC 3448",
    "addr:housenumber":"687",
    "addr:postcode":"3448",
    "addr:street":"Faraday Rd",
    "iso:country":"AU",
    "sg:address":"687 Faraday Rd",
    "sg:city":"Sutton Grange",
    "sg:classifiers":[
        {
            "category":"Banks & Credit Unions",
            "subcategory":"Bureau De Change",
            "type":"Services"
        }
    ],
    "sg:phone":"+61 3 5474 8144",
    "sg:postcode":"3448",
    "sg:province":"VIC",
    "sg:tags":[
        "preparation",
        "processing",
        "data"
    ],
    "wof:name":"Northfield Computing Pty Ltd",
    "wof:placetype":"venue"
},
  "geometry": {"coordinates":[144.34605407699999,-37.1383552551],"type":"Point"}
}