{
  "type": "Feature",
  "properties": {
    "addr:full":"10- 12 Prospect St Box Hill VIC 3128",
    "addr:housenumber":"12",
    "addr:postcode":"3128",
    "addr:street":"Prospect St",
    "iso:country":"AU",
    "sg:address":"10- 12 Prospect St",
    "sg:city":"Box Hill",
    "sg:classifiers":[
        {
            "category":"Professional",
            "subcategory":"Computer Services",
            "type":"Services"
        }
    ],
    "sg:phone":"+61 3 9890 3799",
    "sg:postcode":"3128",
    "sg:province":"VIC",
    "sg:tags":[
        "package",
        "software"
    ],
    "wof:name":"Infomaster Australia Pty Ltd",
    "wof:placetype":"venue"
},
  "geometry": {"coordinates":[145.118774414,-37.8180236816],"type":"Point"}
}