{
  "type": "Feature",
  "properties": {
    "iso:country":"AU",
    "sg:address":"Shop 5 81 Glenfern Rd",
    "sg:city":"Ferntree Gully",
    "sg:classifiers":[
        {
            "category":"Personal",
            "subcategory":"Beauty Salon",
            "type":"Services"
        }
    ],
    "sg:phone":"+61 3 9758 7034",
    "sg:postcode":"3156",
    "sg:province":"VIC",
    "wof:name":"Bonita Skin & Body Care",
    "wof:placetype":"venue"
},
  "geometry": {"coordinates":[145.29354858400001,-37.8954315186],"type":"Point"}
}