{
  "type": "Feature",
  "properties": {
    "addr:full":"Level 7, 459 Little Collins St Melbourne VIC 3000",
    "addr:housenumber":"459",
    "addr:postcode":"3000",
    "addr:street":"Little Collins St",
    "iso:country":"AU",
    "sg:address":"Level 7, 459 Little Collins St",
    "sg:city":"Melbourne",
    "sg:classifiers":[
        {
            "category":"Professional",
            "subcategory":"Management & Consulting",
            "type":"Services"
        }
    ],
    "sg:phone":"+61 3 9592 9478",
    "sg:postcode":"3000",
    "sg:province":"VIC",
    "sg:tags":[
        "consultant",
        "migration"
    ],
    "wof:name":"Penkhull Grove Consulting Group",
    "wof:placetype":"venue"
},
  "geometry": {"coordinates":[144.95942688,-37.8165664673],"type":"Point"}
}