{
  "type": "Feature",
  "properties": {
    "addr:full":"Shop T12 Copperfield Drv Rosemeadow NSW 2560",
    "addr:housenumber":"t12",
    "addr:postcode":"2560",
    "addr:street":"Copperfield Drv",
    "iso:country":"AU",
    "sg:address":"Shop T12 Copperfield Drv",
    "sg:city":"Rosemeadow",
    "sg:classifiers":[
        {
            "category":"Shopping",
            "subcategory":"Jewelry",
            "type":"Retail Goods"
        }
    ],
    "sg:phone":"+61 2 4628 8448",
    "sg:postcode":"2560",
    "sg:province":"NSW",
    "sg:tags":[
        "jeweller"
    ],
    "wof:name":"Rosemeadow Jewellers",
    "wof:placetype":"venue"
},
  "geometry": {"coordinates":[150.797897339,-34.1005134583],"type":"Point"}
}