{
  "type": "Feature",
  "properties": {
    "addr:full":"115 Spence St Cairns QLD 4870",
    "addr:housenumber":"115",
    "addr:postcode":"4870",
    "addr:street":"Spence St",
    "iso:country":"AU",
    "sg:address":"115 Spence St",
    "sg:city":"Cairns",
    "sg:classifiers":[
        {
            "category":"Home & Garden",
            "subcategory":"Hardware",
            "type":"Retail Goods"
        }
    ],
    "sg:phone":"+61 7 4031 0647",
    "sg:postcode":"4870",
    "sg:province":"QLD",
    "sg:tags":[
        "battery",
        "dry",
        "rechargeable",
        "cell"
    ],
    "wof:name":"Battery Power FNQ",
    "wof:placetype":"venue"
},
  "geometry": {"coordinates":[145.770553589,-16.9293193817],"type":"Point"}
}