{
  "type": "Feature",
  "properties": {
    "addr:full":"174 Bourke Rd Umina NSW 2257",
    "addr:housenumber":"174",
    "addr:postcode":"2257",
    "addr:street":"Bourke Rd",
    "iso:country":"AU",
    "sg:address":"174 Bourke Rd",
    "sg:city":"Umina",
    "sg:classifiers":[
        {
            "category":"Food & Beverages",
            "subcategory":"Groceries & Convenience Stores",
            "type":"Retail Goods"
        }
    ],
    "sg:phone":"+61 2 4341 7149",
    "sg:postcode":"2257",
    "sg:province":"NSW",
    "wof:name":"Bourke Road Store",
    "wof:placetype":"venue"
},
  "geometry": {"coordinates":[151.32043457,-33.5106086731],"type":"Point"}
}