{
  "type": "Feature",
  "properties": {
    "addr:full":"Suite 4, Level 1, 285 Hunter St Newcastle NSW 2300",
    "addr:housenumber":"285",
    "addr:postcode":"2300",
    "addr:street":"Hunter St",
    "iso:country":"AU",
    "sg:address":"Suite 4, Level 1, 285 Hunter St",
    "sg:city":"Newcastle",
    "sg:classifiers":[
        {
            "category":"Building & Trades",
            "subcategory":"Cleaning & Sanitation",
            "type":"Services"
        }
    ],
    "sg:phone":"+61 2 4904 2800",
    "sg:postcode":"2300",
    "sg:province":"NSW",
    "sg:tags":[
        "commercial",
        "maintenance"
    ],
    "wof:name":"Alliance Network International Pty Ltd",
    "wof:placetype":"venue"
},
  "geometry": {"coordinates":[151.77583300000001,-32.92672],"type":"Point"}
}