{
  "type": "Feature",
  "properties": {
    "iso:country":"AU",
    "sg:address":"Suite 4, Level 1, 285 Hunter St",
    "sg:city":"Newcastle",
    "sg:classifiers":[
        {
            "category":"Building & Trades",
            "subcategory":"Cleaning & Sanitation",
            "type":"Services"
        }
    ],
    "sg:phone":"+61 2 4904 2800",
    "sg:postcode":"2300",
    "sg:province":"NSW",
    "sg:tags":[
        "commercial",
        "maintenance"
    ],
    "wof:name":"Alliance Network International Pty Ltd",
    "wof:placetype":"venue"
},
  "geometry": {"coordinates":[151.775833,-32.92672],"type":"Point"}
}