{
  "type": "Feature",
  "properties": {
    "addr:full":"73 Popeks Rd Maldon VIC 3463",
    "addr:housenumber":"73",
    "addr:postcode":"3463",
    "addr:street":"Popeks Rd",
    "iso:country":"AU",
    "sg:address":"73 Popeks Rd",
    "sg:city":"Maldon",
    "sg:classifiers":[
        {
            "category":"Personal",
            "subcategory":"Massage",
            "type":"Services"
        }
    ],
    "sg:phone":"+61 3 5475 2607",
    "sg:postcode":"3463",
    "sg:province":"VIC",
    "sg:tags":[
        "therapy"
    ],
    "wof:name":"Wendy Bradys Massage Clinic",
    "wof:placetype":"venue"
},
  "geometry": {"coordinates":[144.068969727,-37.0158920288],"type":"Point"}
}