{
  "type": "Feature",
  "properties": {
    "addr:full":"53 Benningfield Rd Bullcreek WA 6149",
    "addr:housenumber":"53",
    "addr:postcode":"6149",
    "addr:street":"Benningfield Rd",
    "iso:country":"AU",
    "sg:address":"53 Benningfield Rd",
    "sg:city":"Bullcreek",
    "sg:classifiers":[
        {
            "category":"Professional",
            "subcategory":"Computer Services",
            "type":"Services"
        }
    ],
    "sg:phone":"+61 8 9313 8899",
    "sg:postcode":"6149",
    "sg:province":"WA",
    "sg:tags":[
        "repairs",
        "upgrade",
        "equipment"
    ],
    "wof:name":"Printer Computer Service Centre",
    "wof:placetype":"venue"
},
  "geometry": {"coordinates":[115.858261,-32.062695],"type":"Point"}
}