{
  "type": "Feature",
  "properties": {
    "addr:full":"117a North Rd Ryde NSW 2112",
    "addr:housenumber":"117a",
    "addr:postcode":"2112",
    "addr:street":"North Rd",
    "iso:country":"AU",
    "sg:address":"117a North Rd",
    "sg:city":"Ryde",
    "sg:classifiers":[
        {
            "category":"Food & Beverages",
            "subcategory":"Bakery",
            "type":"Retail Goods"
        }
    ],
    "sg:phone":"+61 2 9888 6483",
    "sg:postcode":"2112",
    "sg:province":"NSW",
    "sg:tags":[
        "cake",
        "shop",
        "pastry"
    ],
    "wof:name":"Midway Cakes",
    "wof:placetype":"venue"
},
  "geometry": {"coordinates":[151.10264587399999,-33.7957458496],"type":"Point"}
}