{
  "type": "Feature",
  "properties": {
    "addr:full":"Shop 58 Burleigh City Shopping Centre Burleigh Heads QLD 4220",
    "addr:housenumber":"shop 58",
    "addr:postcode":"4220",
    "addr:street":"Burleigh City",
    "iso:country":"AU",
    "sg:address":"Shop 58 Burleigh City Shopping Centre",
    "sg:city":"Burleigh Heads",
    "sg:classifiers":[
        {
            "category":"Shopping",
            "subcategory":"Clothing, Apparel, & Fashions",
            "type":"Retail Goods"
        }
    ],
    "sg:phone":"+61 7 5576 4632",
    "sg:postcode":"4220",
    "sg:province":"QLD",
    "sg:tags":[
        "lady",
        "wear"
    ],
    "wof:name":"Suzanne Grae",
    "wof:placetype":"venue"
},
  "geometry": {"coordinates":[153.44358825699999,-28.0881938934],"type":"Point"}
}