{
  "type": "Feature",
  "properties": {
    "addr:full":"Murray Valley Hwy Bonegilla VIC 3691",
    "addr:postcode":"3691",
    "addr:street":"Valley Hwy",
    "iso:country":"AU",
    "sg:address":"Murray Valley Hwy",
    "sg:city":"Bonegilla",
    "sg:classifiers":[
        {
            "category":"Autos & Motor Vehicles",
            "subcategory":"Motorcycle Sales",
            "type":"Retail Goods"
        }
    ],
    "sg:phone":"+61 2 6020 6060",
    "sg:postcode":"3691",
    "sg:province":"VIC",
    "sg:tags":[
        "outboard"
    ],
    "wof:name":"Bonegilla Boat Shop",
    "wof:placetype":"venue"
},
  "geometry": {"coordinates":[147.00543200000001,-36.141171],"type":"Point"}
}