{
  "type": "Feature",
  "properties": {
    "iso:country":"AU",
    "sg:address":"Shp 27/ 15-31 Cooper St",
    "sg:city":"Surry Hills",
    "sg:classifiers":[
        {
            "category":"Wholesale",
            "subcategory":"Apparel",
            "type":"Manufacturing & Wholesale Goods"
        }
    ],
    "sg:phone":"+61 2 9281 1124",
    "sg:postcode":"2010",
    "sg:province":"NSW",
    "sg:tags":[
        "wholesaler",
        "mfrs",
        "sportswear",
        "women's"
    ],
    "wof:name":"Pizzuto Pty Ltd",
    "wof:placetype":"venue"
},
  "geometry": {"coordinates":[151.20948791500001,-33.8857574463],"type":"Point"}
}