{
  "type": "Feature",
  "properties": {
    "addr:full":"18 Dixon St Clayton VIC 3168",
    "addr:housenumber":"18",
    "addr:postcode":"3168",
    "addr:street":"Dixon St",
    "iso:country":"AU",
    "sg:address":"18 Dixon St",
    "sg:city":"Clayton",
    "sg:classifiers":[
        {
            "category":"Health Services",
            "subcategory":"Doctor",
            "type":"Services"
        }
    ],
    "sg:phone":"+61 3 9562 9664",
    "sg:postcode":"3168",
    "sg:province":"VIC",
    "sg:tags":[
        "medical",
        "practitioner"
    ],
    "wof:name":"MacNaughton Judith Dr",
    "wof:placetype":"venue"
},
  "geometry": {"coordinates":[145.122848511,-37.9193344116],"type":"Point"}
}