{
  "type": "Feature",
  "properties": {
    "addr:full":"Old Coast Rd Nambucca Heads NSW 2448",
    "addr:postcode":"2448",
    "addr:street":"Coast Rd",
    "iso:country":"AU",
    "sg:address":"Old Coast Rd",
    "sg:city":"Nambucca Heads",
    "sg:classifiers":[
        {
            "category":"Home & Garden",
            "subcategory":"Building Materials",
            "type":"Retail Goods"
        }
    ],
    "sg:phone":"+61 1300 682 980",
    "sg:postcode":"2448",
    "sg:province":"NSW",
    "sg:tags":[
        "pre-mixed",
        "concrete"
    ],
    "wof:name":"The Kancon Concrete Group",
    "wof:placetype":"venue"
},
  "geometry": {"coordinates":[152.98327599999999,-30.636917],"type":"Point"}
}