{
  "type": "Feature",
  "properties": {
    "addr:full":"707a Forest Rd Bexley NSW 2207",
    "addr:housenumber":"707a",
    "addr:postcode":"2207",
    "addr:street":"Forest Rd",
    "iso:country":"AU",
    "sg:address":"707a Forest Rd",
    "sg:city":"Bexley",
    "sg:classifiers":[
        {
            "category":"Autos & Motor Vehicles",
            "subcategory":"Auto Supplies",
            "type":"Retail Goods"
        }
    ],
    "sg:phone":"+61 2 9553 9014",
    "sg:postcode":"2207",
    "sg:province":"NSW",
    "sg:tags":[
        "accessory"
    ],
    "wof:name":"D P Car Seat Covers",
    "wof:placetype":"venue"
},
  "geometry": {"coordinates":[151.11625699999999,-33.960613],"type":"Point"}
}