{
  "type": "Feature",
  "properties": {
    "iso:country":"AU",
    "sg:address":"The Old Post Office 115 Brisbane St",
    "sg:city":"Perth",
    "sg:classifiers":[
        {
            "category":"Education",
            "subcategory":"Dance Studio",
            "type":"Public Place"
        }
    ],
    "sg:phone":"+61 8 9328 8965",
    "sg:postcode":"6000",
    "sg:province":"WA",
    "sg:tags":[
        "instruction",
        "language"
    ],
    "wof:name":"The Language Centre Bookshop",
    "wof:placetype":"venue"
},
  "geometry": {"coordinates":[115.861427307,-31.9422035217],"type":"Point"}
}