{
  "type": "Feature",
  "properties": {
    "addr:full":"Barker St Casino NSW 2470",
    "addr:postcode":"2470",
    "addr:street":"Barker St",
    "iso:country":"AU",
    "sg:address":"Barker St",
    "sg:city":"Casino",
    "sg:classifiers":[
        {
            "category":"Organizations",
            "subcategory":"Professional Association",
            "type":"Services"
        }
    ],
    "sg:phone":"+61 2 6662 1544",
    "sg:postcode":"2470",
    "sg:province":"NSW",
    "sg:tags":[
        "rural",
        "organisation",
        "production",
        "primary"
    ],
    "wof:name":"Veterinary Inspectors Office",
    "wof:placetype":"venue"
},
  "geometry": {"coordinates":[153.047149658,-28.8647956848],"type":"Point"}
}