{
  "type": "Feature",
  "properties": {
    "addr:full":"Shop 39, Vermont South Shopping Centre, Burwood Hw Vermont VIC 3133",
    "addr:housenumber":"shop 39",
    "addr:postcode":"3133",
    "addr:street":"Burwood Hw",
    "iso:country":"AU",
    "sg:address":"Shop 39, Vermont South Shopping Centre, Burwood Hw",
    "sg:city":"Vermont",
    "sg:classifiers":[
        {
            "category":"Personal",
            "subcategory":"Beauty Salon",
            "type":"Services"
        }
    ],
    "sg:phone":"+61 3 9803 4673",
    "sg:postcode":"3133",
    "sg:province":"VIC",
    "sg:tags":[
        "hairdresser"
    ],
    "wof:name":"Realms Hair & Beauty",
    "wof:placetype":"venue"
},
  "geometry": {"coordinates":[145.188552856,-37.8570556641],"type":"Point"}
}