{
  "type": "Feature",
  "properties": {
    "addr:full":"U1/ 435 Old Geelong Rd Hoppers Crossing VIC 3029",
    "addr:housenumber":"435",
    "addr:postcode":"3029",
    "addr:street":"U1 /;Old Geelong Rd",
    "iso:country":"AU",
    "sg:address":"U1/ 435 Old Geelong Rd",
    "sg:city":"Hoppers Crossing",
    "sg:classifiers":[
        {
            "category":"Professional",
            "subcategory":"Printing & Photocopies",
            "type":"Services"
        }
    ],
    "sg:phone":"+61 3 9369 5714",
    "sg:postcode":"3029",
    "sg:province":"VIC",
    "sg:tags":[
        "screen",
        "printer"
    ],
    "wof:name":"Bee Wear Promotions",
    "wof:placetype":"venue"
},
  "geometry": {"coordinates":[144.731369,-37.868774],"type":"Point"}
}