{
  "type": "Feature",
  "properties": {
    "addr:full":"2 Close St Wallsend NSW 2287",
    "addr:housenumber":"2",
    "addr:postcode":"2287",
    "addr:street":"Close St",
    "iso:country":"AU",
    "sg:address":"2 Close St",
    "sg:city":"Wallsend",
    "sg:classifiers":[
        {
            "category":"Home & Garden",
            "subcategory":"Garden Supply",
            "type":"Retail Goods"
        }
    ],
    "sg:phone":"+61 2 4950 1300",
    "sg:postcode":"2287",
    "sg:province":"NSW",
    "sg:tags":[
        "landscape"
    ],
    "wof:name":"About Treated Pine",
    "wof:placetype":"venue"
},
  "geometry": {"coordinates":[151.669647217,-32.9105682373],"type":"Point"}
}