{
  "type": "Feature",
  "properties": {
    "iso:country":"AU",
    "sg:address":"4 Frobisher Rd",
    "sg:city":"Osborne Park",
    "sg:classifiers":[
        {
            "category":"Arts & Performance",
            "subcategory":"Dance",
            "type":"Entertainment"
        }
    ],
    "sg:phone":"+61 412 777 202",
    "sg:postcode":"6017",
    "sg:province":"WA",
    "sg:tags":[
        "theatrical",
        "ballet",
        "tuition"
    ],
    "wof:name":"Vogue Entertainment Australia",
    "wof:placetype":"venue"
},
  "geometry": {"coordinates":[115.819580078,-31.9138031006],"type":"Point"}
}