{
  "type": "Feature",
  "properties": {
    "addr:full":"444 Burwood Hwy Wantirna VIC 3152",
    "addr:housenumber":"444",
    "addr:postcode":"3152",
    "addr:street":"Burwood Hwy",
    "iso:country":"AU",
    "sg:address":"444 Burwood Hwy",
    "sg:city":"Wantirna",
    "sg:classifiers":[
        {
            "category":"Personal",
            "subcategory":"Tanning Parlor",
            "type":"Services"
        }
    ],
    "sg:phone":"+61 3 9801 8488",
    "sg:postcode":"3152",
    "sg:province":"VIC",
    "sg:tags":[
        "solarium"
    ],
    "wof:name":"Body Bronze",
    "wof:placetype":"venue"
},
  "geometry": {"coordinates":[145.238723755,-37.8704681396],"type":"Point"}
}