{
  "type": "Feature",
  "properties": {
    "addr:full":"488 Crown St Surry Hills NSW 2010",
    "addr:housenumber":"488",
    "addr:postcode":"2010",
    "addr:street":"Crown St",
    "iso:country":"AU",
    "sg:address":"488 Crown St",
    "sg:city":"Surry Hills",
    "sg:classifiers":[
        {
            "category":"Cafe",
            "type":"Food & Drink"
        }
    ],
    "sg:phone":"+61 2 9383 9388",
    "sg:postcode":"2010",
    "sg:province":"NSW",
    "wof:name":"Fuel",
    "wof:placetype":"venue"
},
  "geometry": {"coordinates":[151.21386718799999,-33.8868522644],"type":"Point"}
}