{
  "type": "Feature",
  "properties": {
    "addr:full":"31 Cleeland Rd Oakleigh South VIC 3167",
    "addr:housenumber":"31",
    "addr:postcode":"3167",
    "addr:street":"Cleeland Rd",
    "iso:country":"AU",
    "sg:address":"31 Cleeland Rd",
    "sg:city":"Oakleigh South",
    "sg:classifiers":[
        {
            "category":"Fast Food",
            "type":"Food & Drink"
        }
    ],
    "sg:phone":"+61 3 9543 8840",
    "sg:postcode":"3167",
    "sg:province":"VIC",
    "sg:tags":[
        "away",
        "take"
    ],
    "wof:name":"Chris's Takeaway",
    "wof:placetype":"venue"
},
  "geometry": {"coordinates":[145.09753418,-37.9307899475],"type":"Point"}
}