{
  "type": "Feature",
  "properties": {
    "iso:country":"AU",
    "sg:address":"Cnr Thompson & Woodbine Rds",
    "sg:city":"Cranbourne",
    "sg:classifiers":[
        {
            "category":"Health Services",
            "subcategory":"Doctor",
            "type":"Services"
        }
    ],
    "sg:phone":"+61 3 5996 9000",
    "sg:postcode":"3977",
    "sg:province":"VIC",
    "sg:tags":[
        "medical",
        "practitioner"
    ],
    "wof:name":"Thompson Road Clinic",
    "wof:placetype":"venue"
},
  "geometry": {"coordinates":[145.27923584000001,-38.0815505981],"type":"Point"}
}