{
  "type": "Feature",
  "properties": {
    "iso:country":"AU",
    "sg:address":"23 Iliffe St",
    "sg:city":"Bexley",
    "sg:classifiers":[
        {
            "category":"Retail",
            "subcategory":"Repair Shop",
            "type":"Services"
        }
    ],
    "sg:phone":"+61 2 9579 3622",
    "sg:postcode":"2207",
    "sg:province":"NSW",
    "sg:tags":[
        "machine",
        "repairs",
        "part",
        "dryer",
        "washing"
    ],
    "wof:name":"Belair Repair Service",
    "wof:placetype":"venue"
},
  "geometry": {"coordinates":[151.112457,-33.953564],"type":"Point"}
}