{
  "type": "Feature",
  "properties": {
    "iso:country":"AU",
    "sg:address":"15 Leake St",
    "sg:city":"Essendon",
    "sg:classifiers":[
        {
            "category":"Restaurant",
            "type":"Food & Drink"
        }
    ],
    "sg:phone":"+61 3 9379 7223",
    "sg:postcode":"3040",
    "sg:province":"VIC",
    "wof:name":"Ameer Tandoori Restaurant",
    "wof:placetype":"venue"
},
  "geometry": {"coordinates":[144.91033935600001,-37.7467193604],"type":"Point"}
}