{
  "type": "Feature",
  "properties": {
    "addr:full":"Level 2/ 1 McLaren St North Sydney NSW 2060",
    "addr:housenumber":"/ 1",
    "addr:postcode":"2060",
    "addr:street":"Mclaren St",
    "iso:country":"AU",
    "sg:address":"Level 2/ 1 McLaren St",
    "sg:city":"North Sydney",
    "sg:classifiers":[
        {
            "category":"Professional",
            "subcategory":"Research",
            "type":"Services"
        }
    ],
    "sg:phone":"+61 2 9954 0319",
    "sg:postcode":"2060",
    "sg:province":"NSW",
    "sg:tags":[
        "market"
    ],
    "wof:name":"Ipsos Australia Pty Ltd",
    "wof:placetype":"venue"
},
  "geometry": {"coordinates":[151.20616149899999,-33.8344306946],"type":"Point"}
}