{
  "type": "Feature",
  "properties": {
    "addr:full":"45 Albert St Wickham NSW 2293",
    "addr:housenumber":"45",
    "addr:postcode":"2293",
    "addr:street":"Albert St",
    "iso:country":"AU",
    "sg:address":"45 Albert St",
    "sg:city":"Wickham",
    "sg:classifiers":[
        {
            "category":"Autos & Motor Vehicles",
            "subcategory":"Auto Supplies",
            "type":"Retail Goods"
        }
    ],
    "sg:phone":"+61 2 4969 5244",
    "sg:postcode":"2293",
    "sg:province":"NSW",
    "sg:tags":[
        "accessory"
    ],
    "wof:name":"Pit Crew",
    "wof:placetype":"venue"
},
  "geometry": {"coordinates":[151.75611877399999,-32.9181175232],"type":"Point"}
}