{
  "type": "Feature",
  "properties": {
    "iso:country":"AU",
    "sg:address":"PO Box 100",
    "sg:city":"South Fremantle",
    "sg:classifiers":[
        {
            "category":"Building & Trades",
            "subcategory":"Construction",
            "type":"Services"
        }
    ],
    "sg:phone":"+61 8 9335 6265",
    "sg:postcode":"6162",
    "sg:province":"WA",
    "sg:tags":[
        "contractor"
    ],
    "wof:name":"Home Owner Builders The",
    "wof:placetype":"venue"
},
  "geometry": {"coordinates":[115.974152,-32.067917],"type":"Point"}
}