{
  "type": "Feature",
  "properties": {
    "addr:full":"Van Delft St Jabiru NT 0886",
    "addr:postcode":"nt 0886",
    "addr:street":"St",
    "iso:country":"AU",
    "sg:address":"Van Delft St",
    "sg:city":"Jabiru",
    "sg:classifiers":[
        {
            "category":"Education",
            "subcategory":"Special Training",
            "type":"Public Place"
        }
    ],
    "sg:phone":"+61 8 8979 2442",
    "sg:postcode":"0886",
    "sg:province":"NT",
    "sg:tags":[
        "development"
    ],
    "wof:name":"Jabiru Open College",
    "wof:placetype":"venue"
},
  "geometry": {"coordinates":[132.83247399999999,-12.673943],"type":"Point"}
}