{
  "type": "Feature",
  "properties": {
    "iso:country":"AU",
    "sg:address":"142 Burns Rd",
    "sg:city":"Springwood",
    "sg:classifiers":[
        {
            "category":"Government",
            "subcategory":"Post Office",
            "type":"Public Place"
        }
    ],
    "sg:phone":"+61 2 4753 7599",
    "sg:postcode":"2777",
    "sg:province":"NSW",
    "sg:tags":[
        "yoga"
    ],
    "wof:name":"Elizabeth Godleman RNIYTA",
    "wof:placetype":"venue"
},
  "geometry": {"coordinates":[150.56854248100001,-33.7161560059],"type":"Point"}
}