{
  "type": "Feature",
  "properties": {
    "addr:full":"Unit 7, 245 Milne Rd Modbury North SA 5092",
    "addr:housenumber":"245",
    "addr:postcode":"5092",
    "addr:street":"Milne Rd",
    "iso:country":"AU",
    "sg:address":"Unit 7, 245 Milne Rd",
    "sg:city":"Modbury North",
    "sg:classifiers":[
        {
            "category":"Health Services",
            "subcategory":"Chiropractor",
            "type":"Services"
        }
    ],
    "sg:phone":"+61 8 8264 7373",
    "sg:postcode":"5092",
    "sg:province":"SA",
    "wof:name":"Dwyer Sarah Dr",
    "wof:placetype":"venue"
},
  "geometry": {"coordinates":[138.68624877900001,-34.8179130554],"type":"Point"}
}