{
  "type": "Feature",
  "properties": {
    "addr:full":"6/ 31 Kylie Pl Cheltenham VIC 3192",
    "addr:housenumber":"/ 31",
    "addr:postcode":"3192",
    "addr:street":"Kylie Pl",
    "iso:country":"AU",
    "sg:address":"6/ 31 Kylie Pl",
    "sg:city":"Cheltenham",
    "sg:classifiers":[
        {
            "category":"Farming",
            "subcategory":"Dairy Farm",
            "type":"Manufacturing & Wholesale Goods"
        }
    ],
    "sg:phone":"+61 3 9553 2477",
    "sg:postcode":"3192",
    "sg:province":"VIC",
    "sg:tags":[
        "wholesaler",
        "product",
        "mfrs"
    ],
    "wof:name":"Kirk Food Associates Pty Ltd",
    "wof:placetype":"venue"
},
  "geometry": {"coordinates":[145.06329345699999,-37.9509506226],"type":"Point"}
}