{
  "type": "Feature",
  "properties": {
    "addr:full":"88-90 Vale St Cooma NSW 2630",
    "addr:housenumber":"88-90",
    "addr:postcode":"2630",
    "addr:street":"Vale St",
    "iso:country":"AU",
    "sg:address":"88-90 Vale St",
    "sg:city":"Cooma",
    "sg:classifiers":[
        {
            "category":"Banks & Credit Unions",
            "subcategory":"Bureau De Change",
            "type":"Services"
        }
    ],
    "sg:phone":"+61 2 6452 3095",
    "sg:postcode":"2630",
    "sg:province":"NSW",
    "sg:tags":[
        "repairs",
        "part",
        "appliance",
        "electrical"
    ],
    "wof:name":"Hayden Electronics",
    "wof:placetype":"venue"
},
  "geometry": {"coordinates":[149.125488281,-36.236289978],"type":"Point"}
}