{
  "type": "Feature",
  "properties": {
    "addr:full":"18 Sharon School Rd Sharon QLD 4670",
    "addr:housenumber":"18",
    "addr:postcode":"4670",
    "addr:street":"Sharon School Rd",
    "iso:country":"AU",
    "sg:address":"18 Sharon School Rd",
    "sg:city":"Sharon",
    "sg:classifiers":[
        {
            "category":"Education",
            "subcategory":"School",
            "type":"Public Place"
        }
    ],
    "sg:phone":"+61 7 4159 9103",
    "sg:postcode":"4670",
    "sg:province":"QLD",
    "sg:tags":[
        "state",
        "except",
        "nsw"
    ],
    "wof:name":"Sharon Primary",
    "wof:placetype":"venue"
},
  "geometry": {"coordinates":[152.263305664,-24.8728065491],"type":"Point"}
}