{
  "type": "Feature",
  "properties": {
    "addr:full":"Ksk14/ 271 Police Rd Mulgrave NSW 2756",
    "addr:housenumber":"271",
    "addr:postcode":"2756",
    "addr:street":"Police Rd",
    "iso:country":"AU",
    "sg:address":"Ksk14/ 271 Police Rd",
    "sg:city":"Mulgrave",
    "sg:classifiers":[
        {
            "category":"Shopping",
            "subcategory":"Mobile Phones",
            "type":"Retail Goods"
        }
    ],
    "sg:phone":"+61 3 9548 1777",
    "sg:postcode":"2756",
    "sg:province":"NSW",
    "sg:tags":[
        "telephone",
        "accessory"
    ],
    "wof:name":"Mo's Mobiles Waverely Gardens",
    "wof:placetype":"venue"
},
  "geometry": {"coordinates":[150.83291625999999,-33.6265983582],"type":"Point"}
}