{
  "type": "Feature",
  "properties": {
    "iso:country":"AU",
    "sg:address":"5 Windermere Ave",
    "sg:city":"Albion Park",
    "sg:classifiers":[
        {
            "category":"Professional",
            "type":"Services"
        }
    ],
    "sg:phone":"+61 412 050 859",
    "sg:postcode":"2527",
    "sg:province":"NSW",
    "sg:tags":[
        "spray",
        "painting"
    ],
    "wof:name":"Petts Elecotro Static Spray Painting Pty Ltd",
    "wof:placetype":"venue"
},
  "geometry": {"coordinates":[150.78721618599999,-34.5886611938],"type":"Point"}
}