{
  "type": "Feature",
  "properties": {
    "addr:full":"U10/ 55 Graham Hoppers Crossing VIC 3029",
    "addr:postcode":"3029",
    "addr:street":"/ 55",
    "iso:country":"AU",
    "sg:address":"U10/ 55",
    "sg:city":"Graham Hoppers Crossing",
    "sg:classifiers":[
        {
            "category":"Recreation",
            "subcategory":"Amusement Park",
            "type":"Entertainment"
        }
    ],
    "sg:phone":"+61 3 9931 0770",
    "sg:postcode":"3029",
    "sg:province":"VIC",
    "wof:name":"Wonderland",
    "wof:placetype":"venue"
},
  "geometry": {"coordinates":[144.72903400000001,-37.872608],"type":"Point"}
}