{
  "type": "Feature",
  "properties": {
    "addr:full":"1057 Padman Drv Albury NSW 2640",
    "addr:housenumber":"1057",
    "addr:postcode":"2640",
    "addr:street":"Padman Drv",
    "iso:country":"AU",
    "sg:address":"1057 Padman Drv",
    "sg:city":"Albury",
    "sg:classifiers":[
        {
            "category":"Building & Trades",
            "subcategory":"Construction",
            "type":"Services"
        }
    ],
    "sg:phone":"+61 2 6041 5599",
    "sg:postcode":"2640",
    "sg:province":"NSW",
    "sg:tags":[
        "contractor"
    ],
    "wof:name":"Gould N W & P A",
    "wof:placetype":"venue"
},
  "geometry": {"coordinates":[146.88557434099999,-36.0789756775],"type":"Point"}
}