{
  "type": "Feature",
  "properties": {
    "iso:country":"AU",
    "sg:address":"PO Box 5691",
    "sg:city":"MC Townsville",
    "sg:classifiers":[
        {
            "category":"Education",
            "subcategory":"Dance Studio",
            "type":"Public Place"
        }
    ],
    "sg:phone":"+61 7 4725 1286",
    "sg:postcode":"4810",
    "sg:province":"QLD",
    "sg:tags":[
        "venue",
        "tuition"
    ],
    "wof:name":"R.A.D. Regional Advisory Panel N.Q.",
    "wof:placetype":"venue"
},
  "geometry": {"coordinates":[146.75546299999999,-19.2351],"type":"Point"}
}