{
  "type": "Feature",
  "properties": {
    "addr:full":"96 Cooroora St Dicky Beach QLD 4551",
    "addr:housenumber":"96",
    "addr:postcode":"4551",
    "addr:street":"Cooroora St",
    "iso:country":"AU",
    "sg:address":"96 Cooroora St",
    "sg:city":"Dicky Beach",
    "sg:classifiers":[
        {
            "category":"Professional",
            "subcategory":"Art Services",
            "type":"Services"
        }
    ],
    "sg:phone":"+61 418 696 203",
    "sg:postcode":"4551",
    "sg:province":"QLD",
    "sg:tags":[
        "decorator",
        "painter"
    ],
    "wof:name":"Paul Grubner",
    "wof:placetype":"venue"
},
  "geometry": {"coordinates":[153.13284301799999,-26.7857494354],"type":"Point"}
}