{
  "type": "Feature",
  "properties": {
    "addr:full":"PO Box 8327 South Perth WA 6151",
    "addr:postcode":"6151",
    "iso:country":"AU",
    "sg:address":"PO Box 8327",
    "sg:city":"South Perth",
    "sg:classifiers":[
        {
            "category":"Building & Trades",
            "subcategory":"Cleaning & Sanitation",
            "type":"Services"
        }
    ],
    "sg:phone":"+61 8 9313 3282",
    "sg:postcode":"6151",
    "sg:province":"WA",
    "sg:tags":[
        "industrial",
        "commercial",
        "contractor"
    ],
    "wof:name":"Lincoln Cleaning Service",
    "wof:placetype":"venue"
},
  "geometry": {"coordinates":[115.870239,-31.98105],"type":"Point"}
}