{
  "type": "Feature",
  "properties": {
    "addr:full":"12- 14 Octal St Yatala QLD 4207",
    "addr:housenumber":"14",
    "addr:postcode":"4207",
    "addr:street":"Octal St",
    "iso:country":"AU",
    "sg:address":"12- 14 Octal St",
    "sg:city":"Yatala",
    "sg:classifiers":[
        {
            "category":"Autos & Motor Vehicles",
            "subcategory":"Automobile Sales",
            "type":"Retail Goods"
        }
    ],
    "sg:phone":"+61 7 3804 7310",
    "sg:postcode":"4207",
    "sg:province":"QLD",
    "sg:tags":[
        "car",
        "new"
    ],
    "wof:name":"AEC Bullet Supercars",
    "wof:placetype":"venue"
},
  "geometry": {"coordinates":[153.23535156200001,-27.7612457275],"type":"Point"}
}