{
  "type": "Feature",
  "properties": {
    "iso:country":"AU",
    "sg:address":"Shed 2, Drummond Drive Cnr Dennis Little Drv",
    "sg:city":"Gympie",
    "sg:classifiers":[
        {
            "category":"Bars & Pubs",
            "subcategory":"Oxygen Bar",
            "type":"Food & Drink"
        }
    ],
    "sg:phone":"+61 7 5481 1633",
    "sg:postcode":"4570",
    "sg:province":"QLD",
    "sg:tags":[
        "equipment",
        "pump",
        "concrete"
    ],
    "wof:name":"Flowcrete (Queensland)",
    "wof:placetype":"venue"
},
  "geometry": {"coordinates":[152.69708251899999,-26.2254562378],"type":"Point"}
}