{
  "type": "Feature",
  "properties": {
    "addr:full":"153 Lister St Sunnybank QLD 4109",
    "addr:housenumber":"153",
    "addr:postcode":"4109",
    "addr:street":"Lister St",
    "iso:country":"AU",
    "sg:address":"153 Lister St",
    "sg:city":"Sunnybank",
    "sg:classifiers":[
        {
            "category":"Education",
            "subcategory":"School",
            "type":"Public Place"
        }
    ],
    "sg:phone":"+61 7 3423 7499",
    "sg:postcode":"4109",
    "sg:province":"QLD",
    "wof:name":"Southside Education Centre",
    "wof:placetype":"venue"
},
  "geometry": {"coordinates":[153.05447387699999,-27.5779590607],"type":"Point"}
}