{
  "type": "Feature",
  "properties": {
    "addr:full":"9 Glenelg St South Brisbane QLD 4101",
    "addr:housenumber":"9",
    "addr:postcode":"4101",
    "addr:street":"Glenelg St",
    "iso:country":"AU",
    "sg:address":"9 Glenelg St",
    "sg:city":"South Brisbane",
    "sg:classifiers":[
        {
            "category":"Real Estate",
            "subcategory":"Developer",
            "type":"Services"
        }
    ],
    "sg:phone":"+61 7 3255 0888",
    "sg:postcode":"4101",
    "sg:province":"QLD",
    "sg:tags":[
        "development"
    ],
    "wof:name":"Brisbane Convention Centre Hotel",
    "wof:placetype":"venue"
},
  "geometry": {"coordinates":[153.020751953,-27.4776916504],"type":"Point"}
}