{
  "type": "Feature",
  "properties": {
    "addr:full":"10 Sandala Crt Dandenong VIC 3175",
    "addr:housenumber":"10",
    "addr:postcode":"3175",
    "addr:street":"Sandala Crt",
    "iso:country":"AU",
    "sg:address":"10 Sandala Crt",
    "sg:city":"Dandenong",
    "sg:classifiers":[
        {
            "category":"Health Services",
            "subcategory":"Medical Lab",
            "type":"Services"
        }
    ],
    "sg:phone":"+61 3 9795 2302",
    "sg:postcode":"3175",
    "sg:province":"VIC",
    "sg:tags":[
        "laboratory",
        "dental"
    ],
    "wof:name":"Bite-Rite Dental Laboratory",
    "wof:placetype":"venue"
},
  "geometry": {"coordinates":[145.213943481,-37.96326828],"type":"Point"}
}