{
  "type": "Feature",
  "properties": {
    "addr:full":"Church St Lidcombe NSW 2141",
    "addr:postcode":"2141",
    "addr:street":"Church St",
    "iso:country":"AU",
    "sg:address":"Church St",
    "sg:city":"Lidcombe",
    "sg:classifiers":[
        {
            "category":"Arena",
            "subcategory":"Sports Club",
            "type":"Entertainment"
        }
    ],
    "sg:phone":"+61 2 9646 1622",
    "sg:postcode":"2141",
    "sg:province":"NSW",
    "sg:tags":[
        "organisation",
        "sporting"
    ],
    "wof:name":"Sydney Basketball Council Association Inc.",
    "wof:placetype":"venue"
},
  "geometry": {"coordinates":[151.04331970199999,-33.8624649048],"type":"Point"}
}