{
  "type": "Feature",
  "properties": {
    "iso:country":"AU",
    "sg:address":"52 Vinnicombe Drv",
    "sg:city":"Canning Vale",
    "sg:classifiers":[
        {
            "category":"Home & Garden",
            "subcategory":"Building Materials",
            "type":"Retail Goods"
        }
    ],
    "sg:phone":"+61 8 9249 1222",
    "sg:postcode":"6155",
    "sg:province":"WA",
    "sg:tags":[
        "shutter",
        "roller",
        "grille"
    ],
    "wof:name":"Modular Metals Garage Doors",
    "wof:placetype":"venue"
},
  "geometry": {"coordinates":[115.916008,-32.058918],"type":"Point"}
}