{
  "type": "Feature",
  "properties": {
    "iso:country":"AU",
    "sg:address":"16- 18 Enterprise Drv",
    "sg:city":"Beaudesert",
    "sg:classifiers":[
        {
            "category":"Building & Trades",
            "subcategory":"Equipment Rental",
            "type":"Services"
        }
    ],
    "sg:phone":"+61 7 5541 2522",
    "sg:postcode":"4285",
    "sg:province":"QLD",
    "sg:tags":[
        "crane",
        "hire"
    ],
    "wof:name":"Snows Crane Hire",
    "wof:placetype":"venue"
},
  "geometry": {"coordinates":[152.994324,-27.967976],"type":"Point"}
}