{
  "type": "Feature",
  "properties": {
    "addr:full":"16 Parr Pde Narraweena NSW 2099",
    "addr:housenumber":"16",
    "addr:postcode":"2099",
    "addr:street":"Parr Pde",
    "iso:country":"AU",
    "sg:address":"16 Parr Pde",
    "sg:city":"Narraweena",
    "sg:classifiers":[
        {
            "category":"Building & Trades",
            "subcategory":"Plumbing",
            "type":"Services"
        }
    ],
    "sg:phone":"+61 418 272 233",
    "sg:postcode":"2099",
    "sg:province":"NSW",
    "sg:tags":[
        "plumber",
        "gasfitters"
    ],
    "wof:name":"City To Surf Plumbing & Drainage",
    "wof:placetype":"venue"
},
  "geometry": {"coordinates":[151.278762817,-33.7483024597],"type":"Point"}
}