{
  "type": "Feature",
  "properties": {
    "addr:full":"117 Newton Rd Wetherill Park NSW 2164",
    "addr:housenumber":"117",
    "addr:postcode":"2164",
    "addr:street":"Newton Rd",
    "iso:country":"AU",
    "sg:address":"117 Newton Rd",
    "sg:city":"Wetherill Park",
    "sg:classifiers":[
        {
            "category":"Manufacturing",
            "subcategory":"Petroleum Products",
            "type":"Manufacturing & Wholesale Goods"
        }
    ],
    "sg:phone":"+61 2 9756 5660",
    "sg:postcode":"2164",
    "sg:province":"NSW",
    "sg:tags":[
        "lubricant"
    ],
    "wof:name":"Pennzoil Products Australia Co",
    "wof:placetype":"venue"
},
  "geometry": {"coordinates":[150.893341064,-33.8450660706],"type":"Point"}
}