{
  "type": "Feature",
  "properties": {
    "iso:country":"AU",
    "sg:address":"55- 57 Nullum St",
    "sg:city":"Murwillumbah",
    "sg:classifiers":[
        {
            "category":"Autos & Motor Vehicles",
            "subcategory":"Auto Supplies",
            "type":"Retail Goods"
        }
    ],
    "sg:phone":"+61 2 6672 3675",
    "sg:postcode":"2484",
    "sg:province":"NSW",
    "sg:tags":[
        "accessory"
    ],
    "wof:name":"Auto One",
    "wof:placetype":"venue"
},
  "geometry": {"coordinates":[153.39224243199999,-28.3333911896],"type":"Point"}
}