{
  "type": "Feature",
  "properties": {
    "iso:country":"AU",
    "sg:address":"6/ 23 Runway Drv",
    "sg:city":"Marcoola Beach",
    "sg:classifiers":[
        {
            "category":"Communications",
            "subcategory":"Film & Video Production",
            "type":"Services"
        }
    ],
    "sg:phone":"+61 7 5448 7888",
    "sg:postcode":"4564",
    "sg:province":"QLD",
    "sg:tags":[
        "equipment",
        "amplification",
        "music"
    ],
    "wof:name":"Beyma Acoustics Australia",
    "wof:placetype":"venue"
},
  "geometry": {"coordinates":[153.085037231,-26.6083717346],"type":"Point"}
}