{
  "type": "Feature",
  "properties": {
    "iso:country":"AU",
    "sg:address":"4 Glenelg Ave",
    "sg:city":"Mermaid Beach",
    "sg:classifiers":[
        {
            "category":"Real Estate",
            "subcategory":"Real Estate Agent",
            "type":"Services"
        }
    ],
    "sg:phone":"+61 7 5526 5400",
    "sg:postcode":"4218",
    "sg:province":"QLD",
    "wof:name":"AFG Realty",
    "wof:placetype":"venue"
},
  "geometry": {"coordinates":[153.43475341800001,-28.0451164246],"type":"Point"}
}