{
  "type": "Feature",
  "properties": {
    "addr:full":"Shp 3 344 Main North Rd Blair Athol SA 5084",
    "addr:housenumber":"344",
    "addr:postcode":"5084",
    "addr:street":"Main North Rd",
    "iso:country":"AU",
    "sg:address":"Shp 3 344 Main North Rd",
    "sg:city":"Blair Athol",
    "sg:classifiers":[
        {
            "category":"Professional",
            "subcategory":"Computer Services",
            "type":"Services"
        }
    ],
    "sg:phone":"+61 8 8367 7706",
    "sg:postcode":"5084",
    "sg:province":"SA",
    "sg:tags":[
        "repairs",
        "upgrade",
        "equipment"
    ],
    "wof:name":"ECPS Pty Ltd",
    "wof:placetype":"venue"
},
  "geometry": {"coordinates":[138.601364136,-34.8674964905],"type":"Point"}
}