{
  "type": "Feature",
  "properties": {
    "addr:full":"8 Johnson Drv Irymple VIC 3498",
    "addr:housenumber":"8",
    "addr:postcode":"3498",
    "addr:street":"Johnson Drv",
    "iso:country":"AU",
    "sg:address":"8 Johnson Drv",
    "sg:city":"Irymple",
    "sg:classifiers":[
        {
            "category":"Home & Garden",
            "subcategory":"Building Materials",
            "type":"Retail Goods"
        }
    ],
    "sg:phone":"+61 3 5024 7218",
    "sg:postcode":"3498",
    "sg:province":"VIC",
    "sg:tags":[
        "fitting",
        "door"
    ],
    "wof:name":"Auto Door Control Services.",
    "wof:placetype":"venue"
},
  "geometry": {"coordinates":[142.173583984,-34.2351417542],"type":"Point"}
}