{
  "type": "Feature",
  "properties": {
    "addr:full":"5 Hayton Pl Bridgewater TAS 7030",
    "addr:housenumber":"5",
    "addr:postcode":"7030",
    "addr:street":"Pl",
    "iso:country":"AU",
    "sg:address":"5 Hayton Pl",
    "sg:city":"Bridgewater",
    "sg:classifiers":[
        {
            "category":"Retail",
            "subcategory":"Auto Repair",
            "type":"Services"
        }
    ],
    "sg:phone":"+61 3 6263 3763",
    "sg:postcode":"7030",
    "sg:province":"TAS",
    "sg:tags":[
        "repairer",
        "motor",
        "engineer"
    ],
    "wof:name":"Phil Rhodes Mechanical",
    "wof:placetype":"venue"
},
  "geometry": {"coordinates":[147.22926330600001,-42.739025116],"type":"Point"}
}