{
  "type": "Feature",
  "properties": {
    "addr:full":"829 The Entrance Rd Wamberal NSW 2260",
    "addr:housenumber":"829",
    "addr:postcode":"2260",
    "addr:street":"The Entrance Rd",
    "iso:country":"AU",
    "sg:address":"829 The Entrance Rd",
    "sg:city":"Wamberal",
    "sg:classifiers":[
        {
            "category":"Health Services",
            "subcategory":"Chiropractor",
            "type":"Services"
        }
    ],
    "sg:phone":"+61 2 4384 4944",
    "sg:postcode":"2260",
    "sg:province":"NSW",
    "wof:name":"Tim Clarke",
    "wof:placetype":"venue"
},
  "geometry": {"coordinates":[151.44740300000001,-33.417408],"type":"Point"}
}