{
  "type": "Feature",
  "properties": {
    "iso:country":"AU",
    "sg:address":"60 Lamb St",
    "sg:city":"Murgon",
    "sg:classifiers":[
        {
            "category":"Banks & Credit Unions",
            "subcategory":"Bank",
            "type":"Services"
        }
    ],
    "sg:phone":"+61 7 4169 5555",
    "sg:postcode":"4605",
    "sg:province":"QLD",
    "wof:name":"Bank of Queensland",
    "wof:placetype":"venue"
},
  "geometry": {"coordinates":[151.942184,-26.242569],"type":"Point"}
}