{
  "type": "Feature",
  "properties": {
    "addr:full":"31 Olinda Crs Olinda VIC 3788",
    "addr:housenumber":"31",
    "addr:postcode":"3788",
    "addr:street":"Olinda Crs",
    "iso:country":"AU",
    "sg:address":"31 Olinda Crs",
    "sg:city":"Olinda",
    "sg:classifiers":[
        {
            "category":"Farming",
            "subcategory":"Nursery",
            "type":"Manufacturing & Wholesale Goods"
        }
    ],
    "sg:phone":"+61 3 9751 1021",
    "sg:postcode":"3788",
    "sg:province":"VIC",
    "wof:name":"Boulters Olinda Nursery Pty Ltd",
    "wof:placetype":"venue"
},
  "geometry": {"coordinates":[145.35775799999999,-37.855225],"type":"Point"}
}