{
  "type": "Feature",
  "properties": {
    "iso:country":"AU",
    "sg:address":"69 Fishery Point Rd",
    "sg:city":"Mirrabooka",
    "sg:classifiers":[
        {
            "category":"Autos & Motor Vehicles",
            "subcategory":"Fuel & Gas Station",
            "type":"Retail Goods"
        }
    ],
    "sg:phone":"+61 2 4973 3107",
    "sg:postcode":"2264",
    "sg:province":"NSW",
    "wof:name":"Mirrabooka Motors Mechanical & Fuel Supply",
    "wof:placetype":"venue"
},
  "geometry": {"coordinates":[151.551193,-33.107246],"type":"Point"}
}