{
  "type": "Feature",
  "properties": {
    "addr:full":"Shd46/ 400 Somerville Rd West Footscray VIC 3012",
    "addr:housenumber":"400",
    "addr:postcode":"3012",
    "addr:street":"Somerville Rd",
    "iso:country":"AU",
    "sg:address":"Shd46/ 400 Somerville Rd",
    "sg:city":"West Footscray",
    "sg:classifiers":[
        {
            "category":"Shopping",
            "type":"Retail Goods"
        }
    ],
    "sg:phone":"+61 3 9318 0627",
    "sg:postcode":"3012",
    "sg:province":"VIC",
    "sg:tags":[
        "product",
        "plastic"
    ],
    "wof:name":"All Round Packaging Pty Ltd",
    "wof:placetype":"venue"
},
  "geometry": {"coordinates":[144.863006592,-37.8103256226],"type":"Point"}
}