{
  "type": "Feature",
  "properties": {
    "addr:full":"34 Lord St Sandy Bay TAS 7005",
    "addr:housenumber":"34",
    "addr:postcode":"7005",
    "addr:street":"Lord St",
    "iso:country":"AU",
    "sg:address":"34 Lord St",
    "sg:city":"Sandy Bay",
    "sg:classifiers":[
        {
            "category":"Retail",
            "subcategory":"Auto Rental",
            "type":"Services"
        }
    ],
    "sg:phone":"+61 400 902 465",
    "sg:postcode":"7005",
    "sg:province":"TAS",
    "sg:tags":[
        "car",
        "wedding"
    ],
    "wof:name":"Campbell Stretch Limousine Hire",
    "wof:placetype":"venue"
},
  "geometry": {"coordinates":[147.324951172,-42.8989028931],"type":"Point"}
}