{
  "type": "Feature",
  "properties": {
    "iso:country":"AU",
    "sg:address":"37 Main Ave",
    "sg:city":"Wavell Heights",
    "sg:classifiers":[
        {
            "category":"Home & Garden",
            "subcategory":"Building Materials",
            "type":"Retail Goods"
        }
    ],
    "sg:phone":"+61 7 3265 7933",
    "sg:postcode":"4012",
    "sg:province":"QLD",
    "sg:tags":[
        "wall",
        "frame",
        "truss",
        "roof"
    ],
    "wof:name":"Versace Timbers",
    "wof:placetype":"venue"
},
  "geometry": {"coordinates":[153.050689697,-27.3843212128],"type":"Point"}
}