{
  "type": "Feature",
  "properties": {
    "iso:country":"AU",
    "sg:address":"50 Ninth Ave",
    "sg:city":"Townsville",
    "sg:classifiers":[
        {
            "category":"Wholesale",
            "subcategory":"Seafood",
            "type":"Manufacturing & Wholesale Goods"
        }
    ],
    "sg:phone":"+61 408 757 796",
    "sg:postcode":"4810",
    "sg:province":"QLD",
    "sg:tags":[
        "fish"
    ],
    "wof:name":"Great Barrier Reef Sea Food",
    "wof:placetype":"venue"
},
  "geometry": {"coordinates":[146.81646699999999,-19.272776],"type":"Point"}
}