{
  "type": "Feature",
  "properties": {
    "addr:full":"43 Viney St Clayton South VIC 3169",
    "addr:housenumber":"43",
    "addr:postcode":"3169",
    "addr:street":"Viney St",
    "iso:country":"AU",
    "sg:address":"43 Viney St",
    "sg:city":"Clayton South",
    "sg:classifiers":[
        {
            "category":"Personal",
            "subcategory":"Beauty Salon",
            "type":"Services"
        }
    ],
    "sg:phone":"+61 3 9551 5162",
    "sg:postcode":"3169",
    "sg:province":"VIC",
    "sg:tags":[
        "supply",
        "artist",
        "make-up"
    ],
    "wof:name":"Susan Make Up Artist Nail Technician",
    "wof:placetype":"venue"
},
  "geometry": {"coordinates":[145.102249145,-37.9377822876],"type":"Point"}
}