{
  "type": "Feature",
  "properties": {
    "addr:full":"23 Millie St Guildford NSW 2161",
    "addr:housenumber":"23",
    "addr:postcode":"2161",
    "addr:street":"Millie St",
    "iso:country":"AU",
    "sg:address":"23 Millie St",
    "sg:city":"Guildford",
    "sg:classifiers":[
        {
            "category":"Personal",
            "type":"Services"
        }
    ],
    "sg:phone":"+61 2 8011 4351",
    "sg:postcode":"2161",
    "sg:province":"NSW",
    "sg:tags":[
        "reducing",
        "treatment",
        "weight"
    ],
    "wof:name":"Faivre Nicolas",
    "wof:placetype":"venue"
},
  "geometry": {"coordinates":[150.98069763199999,-33.8578414917],"type":"Point"}
}