{
  "type": "Feature",
  "properties": {
    "iso:country":"AU",
    "sg:address":"472 McKinnon Drv",
    "sg:city":"Tewantin",
    "sg:classifiers":[
        {
            "category":"Farming",
            "subcategory":"Nursery",
            "type":"Manufacturing & Wholesale Goods"
        }
    ],
    "sg:phone":"+61 7 5442 4454",
    "sg:postcode":"4565",
    "sg:province":"QLD",
    "wof:name":"Noosa Lakes Plant Nursery Pty Ltd",
    "wof:placetype":"venue"
},
  "geometry": {"coordinates":[152.989776611,-26.3772907257],"type":"Point"}
}