{
  "type": "Feature",
  "properties": {
    "addr:full":"408 Mt Alexander Rd Ascot Vale VIC 3032",
    "addr:housenumber":"408",
    "addr:postcode":"3032",
    "addr:street":"Mt Alexander Rd",
    "iso:country":"AU",
    "sg:address":"408 Mt Alexander Rd",
    "sg:city":"Ascot Vale",
    "sg:classifiers":[
        {
            "category":"Banks & Credit Unions",
            "subcategory":"Investment Brokerage",
            "type":"Services"
        }
    ],
    "sg:phone":"+61 3 9370 8279",
    "sg:postcode":"3032",
    "sg:province":"VIC",
    "sg:tags":[
        "radiator",
        "motor"
    ],
    "wof:name":"Ascot-Moonee Radiators",
    "wof:placetype":"venue"
},
  "geometry": {"coordinates":[144.929947,-37.777542],"type":"Point"}
}