{
  "type": "Feature",
  "properties": {
    "iso:country":"AU",
    "sg:address":"Stoney Creek Rd",
    "sg:city":"Bexley",
    "sg:classifiers":[
        {
            "category":"Sports & Exercise",
            "subcategory":"Golf",
            "type":"Entertainment"
        }
    ],
    "sg:phone":"+61 2 9150 9062",
    "sg:postcode":"2207",
    "sg:province":"NSW",
    "sg:tags":[
        "club"
    ],
    "wof:name":"Bexley Golf Club",
    "wof:placetype":"venue"
},
  "geometry": {"coordinates":[151.124146,-33.949841],"type":"Point"}
}