{
  "type": "Feature",
  "properties": {
    "iso:country":"AU",
    "sg:address":"Cnr Monaro & Crawford Sts",
    "sg:city":"Queanbeyan",
    "sg:classifiers":[
        {
            "category":"Shopping",
            "subcategory":"Optical Goods",
            "type":"Retail Goods"
        }
    ],
    "sg:phone":"+61 2 6299 0966",
    "sg:postcode":"2620",
    "sg:province":"NSW",
    "sg:tags":[
        "dispenser",
        "prescription"
    ],
    "wof:name":"ACT Optical",
    "wof:placetype":"venue"
},
  "geometry": {"coordinates":[149.23321533199999,-35.3538398743],"type":"Point"}
}