{
  "type": "Feature",
  "properties": {
    "addr:full":"69 Blyth St Altona VIC 3018",
    "addr:housenumber":"69",
    "addr:postcode":"3018",
    "addr:street":"Blyth St",
    "iso:country":"AU",
    "sg:address":"69 Blyth St",
    "sg:city":"Altona",
    "sg:classifiers":[
        {
            "category":"Health Services",
            "subcategory":"Health Practitioner",
            "type":"Services"
        }
    ],
    "sg:phone":"+61 3 9315 0100",
    "sg:postcode":"3018",
    "sg:province":"VIC",
    "sg:tags":[
        "physiotherapist"
    ],
    "wof:name":"Altona Beach Physiotherapy",
    "wof:placetype":"venue"
},
  "geometry": {"coordinates":[144.82781982399999,-37.8679122925],"type":"Point"}
}