{
  "type": "Feature",
  "properties": {
    "addr:full":"6 Ranceby Rd Poowong VIC 3988",
    "addr:housenumber":"6",
    "addr:postcode":"3988",
    "addr:street":"Ranceby Rd",
    "iso:country":"AU",
    "sg:address":"6 Ranceby Rd",
    "sg:city":"Poowong",
    "sg:classifiers":[
        {
            "category":"Fast Food",
            "type":"Food & Drink"
        }
    ],
    "sg:phone":"+61 3 5659 2366",
    "sg:postcode":"3988",
    "sg:province":"VIC",
    "sg:tags":[
        "away",
        "take"
    ],
    "wof:name":"Poowong Milk Bar",
    "wof:placetype":"venue"
},
  "geometry": {"coordinates":[145.76388549800001,-38.3430290222],"type":"Point"}
}