{
  "type": "Feature",
  "properties": {
    "iso:country":"AU",
    "sg:address":"22 Cameron St",
    "sg:city":"Launceston",
    "sg:classifiers":[
        {
            "category":"Professional",
            "subcategory":"Computer Services",
            "type":"Services"
        }
    ],
    "sg:phone":"+61 3 6334 7730",
    "sg:postcode":"7250",
    "sg:province":"TAS",
    "sg:tags":[
        "equipment",
        "networking",
        "installation"
    ],
    "wof:name":"Beyond Computer Consultants",
    "wof:placetype":"venue"
},
  "geometry": {"coordinates":[147.14076232900001,-41.4340591431],"type":"Point"}
}