{
  "type": "Feature",
  "properties": {
    "addr:full":"26 Capitol Link Drv Campbellfield VIC 3061",
    "addr:postcode":"3061",
    "addr:street":"Capitol Link Drv",
    "iso:country":"AU",
    "sg:address":"26 Capitol Link Drv",
    "sg:city":"Campbellfield",
    "sg:classifiers":[
        {
            "category":"Manufacturing",
            "subcategory":"Furniture",
            "type":"Manufacturing & Wholesale Goods"
        }
    ],
    "sg:phone":"+61 3 9357 9500",
    "sg:postcode":"3061",
    "sg:province":"VIC",
    "sg:tags":[
        "builder",
        "designer",
        "custom"
    ],
    "wof:name":"Lifestyle Furniture",
    "wof:placetype":"venue"
},
  "geometry": {"coordinates":[144.963821411,-37.6556549072],"type":"Point"}
}