{
  "type": "Feature",
  "properties": {
    "addr:full":"8 Romoly Drv Forest Hill VIC 3131",
    "addr:housenumber":"8",
    "addr:postcode":"3131",
    "addr:street":"Romoly Drv",
    "iso:country":"AU",
    "sg:address":"8 Romoly Drv",
    "sg:city":"Forest Hill",
    "sg:classifiers":[
        {
            "category":"Home & Garden",
            "subcategory":"Carpets & Floor Coverings",
            "type":"Retail Goods"
        }
    ],
    "sg:phone":"+61 3 9803 1792",
    "sg:postcode":"3131",
    "sg:province":"VIC",
    "sg:tags":[
        "wood"
    ],
    "wof:name":"A La Page Timber Flooring & Blinds",
    "wof:placetype":"venue"
},
  "geometry": {"coordinates":[145.16113281200001,-37.8456573486],"type":"Point"}
}