{
  "type": "Feature",
  "properties": {
    "addr:full":"109 Strickland Pde Ballarat VIC 3350",
    "addr:housenumber":"109",
    "addr:postcode":"3350",
    "addr:street":"Strickland Pde",
    "iso:country":"AU",
    "sg:address":"109 Strickland Pde",
    "sg:city":"Ballarat",
    "sg:classifiers":[
        {
            "category":"Building & Trades",
            "subcategory":"Construction",
            "type":"Services"
        }
    ],
    "sg:phone":"+61 3 5332 6555",
    "sg:postcode":"3350",
    "sg:province":"VIC",
    "sg:tags":[
        "contractor"
    ],
    "wof:name":"Richards Peter",
    "wof:placetype":"venue"
},
  "geometry": {"coordinates":[143.90481600000001,-37.560658],"type":"Point"}
}