{
  "type": "Feature",
  "properties": {
    "addr:full":"440 Flinders St Nollamara WA 6061",
    "addr:housenumber":"440",
    "addr:postcode":"6061",
    "addr:street":"Flinders St",
    "iso:country":"AU",
    "sg:address":"440 Flinders St",
    "sg:city":"Nollamara",
    "sg:classifiers":[
        {
            "category":"Health Services",
            "subcategory":"Dentist",
            "type":"Services"
        }
    ],
    "sg:phone":"+61 8 9349 1749",
    "sg:postcode":"6061",
    "sg:province":"WA",
    "wof:name":"Ng Bill",
    "wof:placetype":"venue"
},
  "geometry": {"coordinates":[115.84565734900001,-31.8708400726],"type":"Point"}
}