{
  "type": "Feature",
  "properties": {
    "iso:country":"AU",
    "sg:address":"U1/ 40 Templeton St",
    "sg:city":"Cook",
    "sg:classifiers":[
        {
            "category":"Professional",
            "subcategory":"Art Services",
            "type":"Services"
        }
    ],
    "sg:phone":"+61 2 6251 5277",
    "sg:postcode":"2614",
    "sg:province":"ACT",
    "sg:tags":[
        "product",
        "industrial",
        "designer"
    ],
    "wof:name":"Industrious Design",
    "wof:placetype":"venue"
},
  "geometry": {"coordinates":[149.06031799300001,-35.2590866089],"type":"Point"}
}