{
  "type": "Feature",
  "properties": {
    "iso:country":"AU",
    "sg:address":"Un 3 17 Advance Pl",
    "sg:city":"Sunrise Beach",
    "sg:classifiers":[
        {
            "category":"Building & Trades",
            "subcategory":"Plumbing",
            "type":"Services"
        }
    ],
    "sg:phone":"+61 7 5455 3609",
    "sg:postcode":"4567",
    "sg:province":"QLD",
    "sg:tags":[
        "plumber",
        "gasfitters"
    ],
    "wof:name":"RGM Plumbing & Gas Fitting Services",
    "wof:placetype":"venue"
},
  "geometry": {"coordinates":[153.10206604000001,-26.4086608887],"type":"Point"}
}