{
  "type": "Feature",
  "properties": {
    "addr:full":"67 St Andrews Drv Loganholme QLD 4129",
    "addr:housenumber":"67",
    "addr:postcode":"4129",
    "addr:street":"St Andrews Drv",
    "iso:country":"AU",
    "sg:address":"67 St Andrews Drv",
    "sg:city":"Loganholme",
    "sg:classifiers":[
        {
            "category":"Wholesale",
            "subcategory":"Medical Equipment & Supplies",
            "type":"Manufacturing & Wholesale Goods"
        }
    ],
    "sg:phone":"+61 7 3287 6221",
    "sg:postcode":"4129",
    "sg:province":"QLD",
    "sg:tags":[
        "aid",
        "care",
        "health",
        "home"
    ],
    "wof:name":"JTC Products",
    "wof:placetype":"venue"
},
  "geometry": {"coordinates":[153.20745849599999,-27.6780452728],"type":"Point"}
}