{
  "type": "Feature",
  "properties": {
    "addr:full":"88 Mann St Gosford NSW 2250",
    "addr:housenumber":"88",
    "addr:postcode":"2250",
    "addr:street":"Mann St",
    "iso:country":"AU",
    "sg:address":"88 Mann St",
    "sg:city":"Gosford",
    "sg:classifiers":[
        {
            "category":"Banks & Credit Unions",
            "subcategory":"Bank",
            "type":"Services"
        }
    ],
    "sg:phone":"+61 2 4322 5444",
    "sg:postcode":"2250",
    "sg:province":"NSW",
    "sg:tags":[
        "broker",
        "mortgage"
    ],
    "wof:name":"Resi Mortgage Corporation Central Coast",
    "wof:placetype":"venue"
},
  "geometry": {"coordinates":[151.34158325199999,-33.4273071289],"type":"Point"}
}