{
  "type": "Feature",
  "properties": {
    "addr:full":"87 / 50 - 60 Lloyd St Kensington VIC 3031",
    "addr:housenumber":"87 / 50 60",
    "addr:postcode":"3031",
    "addr:street":"Lloyd St",
    "iso:country":"AU",
    "sg:address":"87 / 50 - 60 Lloyd St",
    "sg:city":"Kensington",
    "sg:classifiers":[
        {
            "category":"Manufacturing",
            "subcategory":"Furniture",
            "type":"Manufacturing & Wholesale Goods"
        }
    ],
    "sg:phone":"+61 1300 552 424",
    "sg:postcode":"3031",
    "sg:province":"VIC",
    "sg:tags":[
        "equipment",
        "hire"
    ],
    "sg:website":"http://www.abacusrentit.com.au",
    "wof:name":"Abacus Rent It",
    "wof:placetype":"venue"
},
  "geometry": {"coordinates":[144.93246500000001,-37.800919],"type":"Point"}
}