{
  "type": "Feature",
  "properties": {
    "iso:country":"AU",
    "sg:address":"Bay 6, Lot 1 Cook Drv",
    "sg:city":"Coffs Harbour",
    "sg:classifiers":[
        {
            "category":"Shopping",
            "type":"Retail Goods"
        }
    ],
    "sg:phone":"+61 2 6651 7745",
    "sg:postcode":"2450",
    "sg:province":"NSW",
    "sg:tags":[
        "equipment",
        "safety",
        "accessory"
    ],
    "wof:name":"Coffs Workwear & Safety",
    "wof:placetype":"venue"
},
  "geometry": {"coordinates":[153.096725,-30.313881],"type":"Point"}
}