{
  "type": "Feature",
  "properties": {
    "iso:country":"AU",
    "sg:address":"196 Main South Rd",
    "sg:city":"Morphett Vale",
    "sg:classifiers":[
        {
            "category":"Communications",
            "subcategory":"Film & Video Production",
            "type":"Services"
        }
    ],
    "sg:phone":"+61 8 8382 4306",
    "sg:postcode":"5162",
    "sg:province":"SA",
    "sg:tags":[
        "dvd",
        "library"
    ],
    "wof:name":"Video Ezy",
    "wof:placetype":"venue"
},
  "geometry": {"coordinates":[138.52384948700001,-35.1255912781],"type":"Point"}
}