{
  "type": "Feature",
  "properties": {
    "iso:country":"AU",
    "sg:address":"34 Kimberly Rd",
    "sg:city":"Dandenong",
    "sg:classifiers":[
        {
            "category":"Manufacturing",
            "subcategory":"Metals",
            "type":"Manufacturing & Wholesale Goods"
        }
    ],
    "sg:phone":"+61 3 9706 8107",
    "sg:postcode":"3175",
    "sg:province":"VIC",
    "sg:tags":[
        "spinner"
    ],
    "wof:name":"Bancell Metal Spinners",
    "wof:placetype":"venue"
},
  "geometry": {"coordinates":[145.20761108400001,-38.0316505432],"type":"Point"}
}