{
  "type": "Feature",
  "properties": {
    "iso:country":"AU",
    "sg:address":"15 Blakesley Rd",
    "sg:city":"South Hurstville",
    "sg:classifiers":[
        {
            "category":"Building & Trades",
            "subcategory":"Construction",
            "type":"Services"
        }
    ],
    "sg:phone":"+61 2 9546 2873",
    "sg:postcode":"2221",
    "sg:province":"NSW",
    "sg:tags":[
        "earth",
        "excavating",
        "moving",
        "contractor"
    ],
    "wof:name":"Sayed-Ahmad",
    "wof:placetype":"venue"
},
  "geometry": {"coordinates":[151.111450195,-33.9784965515],"type":"Point"}
}