{
  "type": "Feature",
  "properties": {
    "iso:country":"AU",
    "sg:address":"PO Box 5028",
    "sg:city":"Geelong North",
    "sg:classifiers":[
        {
            "category":"Professional",
            "subcategory":"Art Services",
            "type":"Services"
        }
    ],
    "sg:phone":"+61 1300 363 296",
    "sg:postcode":"3215",
    "sg:province":"VIC",
    "sg:tags":[
        "decorator",
        "painter"
    ],
    "wof:name":"Jon McGlashan Painting",
    "wof:placetype":"venue"
},
  "geometry": {"coordinates":[144.351287842,-38.11536026],"type":"Point"}
}