{
  "type": "Feature",
  "properties": {
    "iso:country":"AU",
    "sg:address":"Shp 6, 143 Warrandyte Rd",
    "sg:city":"Langwarrin",
    "sg:classifiers":[
        {
            "category":"Food & Beverages",
            "subcategory":"Liquor & Beverages",
            "type":"Retail Goods"
        }
    ],
    "sg:phone":"+61 3 9776 5559",
    "sg:postcode":"3910",
    "sg:province":"VIC",
    "sg:tags":[
        "store"
    ],
    "wof:name":"Cellarbrations At Langwarrin",
    "wof:placetype":"venue"
},
  "geometry": {"coordinates":[145.18836975100001,-38.1652336121],"type":"Point"}
}