{
  "type": "Feature",
  "properties": {
    "addr:full":"67- 69 Spring St South Grafton NSW 2460",
    "addr:housenumber":"69",
    "addr:postcode":"2460",
    "addr:street":"Spring St",
    "iso:country":"AU",
    "sg:address":"67- 69 Spring St",
    "sg:city":"South Grafton",
    "sg:classifiers":[
        {
            "category":"Shopping",
            "subcategory":"Discount & Variety Stores",
            "type":"Retail Goods"
        }
    ],
    "sg:phone":"+61 2 6643 5322",
    "sg:postcode":"2460",
    "sg:province":"NSW",
    "sg:tags":[
        "shop",
        "adult"
    ],
    "wof:name":"S & S Lingerie and Adult Novelties",
    "wof:placetype":"venue"
},
  "geometry": {"coordinates":[152.93580627399999,-29.7036743164],"type":"Point"}
}