{
  "type": "Feature",
  "properties": {
    "addr:full":"189A Baylis St Wagga Wagga NSW 2650",
    "addr:housenumber":"189a",
    "addr:postcode":"2650",
    "addr:street":"Baylis St",
    "iso:country":"AU",
    "sg:address":"189A Baylis St",
    "sg:city":"Wagga Wagga",
    "sg:classifiers":[
        {
            "category":"Industrial Area",
            "type":"Public Place"
        }
    ],
    "sg:phone":"+61 2 6921 0766",
    "sg:postcode":"2650",
    "sg:province":"NSW",
    "sg:tags":[
        "protective",
        "clothing"
    ],
    "wof:name":"Booted Out",
    "wof:placetype":"venue"
},
  "geometry": {"coordinates":[147.370330811,-35.1117935181],"type":"Point"}
}