{
  "type": "Feature",
  "properties": {
    "iso:country":"AU",
    "sg:address":"118 Waldron Rd",
    "sg:city":"Chester Hill",
    "sg:classifiers":[
        {
            "category":"Personal",
            "subcategory":"Beauty Salon",
            "type":"Services"
        }
    ],
    "sg:phone":"+61 2 9644 7354",
    "sg:postcode":"2162",
    "sg:province":"NSW",
    "sg:tags":[
        "hairdresser"
    ],
    "wof:name":"A.G. Hair Images",
    "wof:placetype":"venue"
},
  "geometry": {"coordinates":[151.00460815400001,-33.8834228516],"type":"Point"}
}