{
  "type": "Feature",
  "properties": {
    "iso:country":"AU",
    "sg:address":"Suite 14/15- 17 Kildare Rd",
    "sg:city":"Blacktown",
    "sg:classifiers":[
        {
            "category":"Real Estate",
            "subcategory":"Real Estate Agent",
            "type":"Services"
        }
    ],
    "sg:phone":"+61 2 8814 8222",
    "sg:postcode":"2148",
    "sg:province":"NSW",
    "wof:name":"Laing + Simmons Blacktown",
    "wof:placetype":"venue"
},
  "geometry": {"coordinates":[150.908370972,-33.7699584961],"type":"Point"}
}