{
  "type": "Feature",
  "properties": {
    "addr:full":"Unit 1 1073 Dandenong Rd Malvern East VIC 3145",
    "addr:housenumber":"1073",
    "addr:postcode":"3145",
    "addr:street":"Dandenong Rd",
    "iso:country":"AU",
    "sg:address":"Unit 1 1073 Dandenong Rd",
    "sg:city":"Malvern East",
    "sg:classifiers":[
        {
            "category":"Wholesale",
            "subcategory":"Home Furnishings",
            "type":"Manufacturing & Wholesale Goods"
        }
    ],
    "sg:phone":"+61 1800 675 880",
    "sg:postcode":"3145",
    "sg:province":"VIC",
    "sg:tags":[
        "wholesaler",
        "mfrs",
        "kitchenware"
    ],
    "wof:name":"Dine Rite",
    "wof:placetype":"venue"
},
  "geometry": {"coordinates":[145.05630493199999,-37.8833656311],"type":"Point"}
}