{
  "type": "Feature",
  "properties": {
    "addr:full":"7 Aberdeen St Perth WA 6000",
    "addr:housenumber":"7",
    "addr:postcode":"6000",
    "addr:street":"Aberdeen St",
    "iso:country":"AU",
    "sg:address":"7 Aberdeen St",
    "sg:city":"Perth",
    "sg:classifiers":[
        {
            "category":"Professional",
            "subcategory":"Research",
            "type":"Services"
        }
    ],
    "sg:phone":"+61 8 9325 4899",
    "sg:postcode":"6000",
    "sg:province":"WA",
    "sg:tags":[
        "market"
    ],
    "wof:name":"Morgan (Roy) Research",
    "wof:placetype":"venue"
},
  "geometry": {"coordinates":[115.852546692,-31.9546794891],"type":"Point"}
}