{
  "type": "Feature",
  "properties": {
    "iso:country":"AU",
    "sg:address":"Shop 2/ 68a Queenscliff Rd",
    "sg:city":"Queenscliff",
    "sg:classifiers":[
        {
            "category":"Personal",
            "subcategory":"Beauty Salon",
            "type":"Services"
        }
    ],
    "sg:phone":"+61 2 9907 3295",
    "sg:postcode":"2096",
    "sg:province":"NSW",
    "sg:tags":[
        "hairdresser"
    ],
    "wof:name":"Headspace Hair",
    "wof:placetype":"venue"
},
  "geometry": {"coordinates":[151.28791809099999,-33.7839736938],"type":"Point"}
}