{
  "type": "Feature",
  "properties": {
    "iso:country":"AU",
    "sg:address":"2/ 35 Church St",
    "sg:city":"Traralgon",
    "sg:classifiers":[
        {
            "category":"Banks & Credit Unions",
            "subcategory":"Investment Brokerage",
            "type":"Services"
        }
    ],
    "sg:phone":"+61 3 5174 5064",
    "sg:postcode":"3844",
    "sg:province":"VIC",
    "sg:tags":[
        "shutter",
        "louvre"
    ],
    "wof:name":"Victory Curtains & Blinds",
    "wof:placetype":"venue"
},
  "geometry": {"coordinates":[146.53515625,-38.1961784363],"type":"Point"}
}