{
  "type": "Feature",
  "properties": {
    "addr:full":"17 Golden Oak Crs Carindale QLD 4152",
    "addr:housenumber":"17",
    "addr:postcode":"4152",
    "addr:street":"Golden Oak Crs",
    "iso:country":"AU",
    "sg:address":"17 Golden Oak Crs",
    "sg:city":"Carindale",
    "sg:classifiers":[
        {
            "category":"Landmark",
            "subcategory":"Scenic View",
            "type":"Public Place"
        }
    ],
    "sg:phone":"+61 7 3343 6711",
    "sg:postcode":"4152",
    "sg:province":"QLD",
    "sg:tags":[
        "staircase",
        "handrail"
    ],
    "wof:name":"Rope & Rigging Co The",
    "wof:placetype":"venue"
},
  "geometry": {"coordinates":[153.102005005,-27.5056304932],"type":"Point"}
}