{
  "type": "Feature",
  "properties": {
    "iso:country":"AU",
    "sg:address":"23 Fairbrother St",
    "sg:city":"Belmont",
    "sg:classifiers":[
        {
            "category":"Social Services",
            "subcategory":"Job Training",
            "type":"Services"
        }
    ],
    "sg:phone":"+61 8 9477 4887",
    "sg:postcode":"6104",
    "sg:province":"WA",
    "sg:tags":[
        "control",
        "equipment",
        "noise"
    ],
    "wof:name":"Automotive Noise & Heat Control",
    "wof:placetype":"venue"
},
  "geometry": {"coordinates":[115.92825317400001,-31.9516639709],"type":"Point"}
}