{
  "type": "Feature",
  "properties": {
    "iso:country":"AU",
    "sg:address":"28 Henry St St",
    "sg:city":"George",
    "sg:classifiers":[
        {
            "category":"Building & Trades",
            "subcategory":"Construction",
            "type":"Services"
        }
    ],
    "sg:phone":"+61 7 4625 4156",
    "sg:postcode":"4487",
    "sg:province":"QLD",
    "sg:tags":[
        "concrete",
        "contractor"
    ],
    "wof:name":"Fletcher G J & R M",
    "wof:placetype":"venue"
},
  "geometry": {"coordinates":[148.58189392099999,-28.0364055634],"type":"Point"}
}