{
  "type": "Feature",
  "properties": {
    "addr:full":"Cnr Lloyd St & Elgee Rd Midland WA 6056",
    "addr:postcode":"6056",
    "addr:street":"St & Elgee Rd",
    "iso:country":"AU",
    "sg:address":"Cnr Lloyd St & Elgee Rd",
    "sg:city":"Midland",
    "sg:classifiers":[
        {
            "category":"Building & Trades",
            "subcategory":"Construction",
            "type":"Services"
        }
    ],
    "sg:phone":"+61 8 9274 6089",
    "sg:postcode":"6056",
    "sg:province":"WA",
    "sg:tags":[
        "brick",
        "paving"
    ],
    "wof:name":"Rare Earth Pavers & Poured Limestone",
    "wof:placetype":"venue"
},
  "geometry": {"coordinates":[116.013580322,-31.8911552429],"type":"Point"}
}