{
  "type": "Feature",
  "properties": {
    "addr:full":"1 Molloy St Torrington QLD 4350",
    "addr:housenumber":"1",
    "addr:postcode":"4350",
    "addr:street":"Molloy St",
    "iso:country":"AU",
    "sg:address":"1 Molloy St",
    "sg:city":"Torrington",
    "sg:classifiers":[
        {
            "category":"Retail",
            "subcategory":"Storage",
            "type":"Services"
        }
    ],
    "sg:phone":"+61 7 4634 0526",
    "sg:postcode":"4350",
    "sg:province":"QLD",
    "sg:tags":[
        "removal",
        "furniture"
    ],
    "wof:name":"Allied Pickford",
    "wof:placetype":"venue"
},
  "geometry": {"coordinates":[151.89830000000001,-27.555094],"type":"Point"}
}