{
  "type": "Feature",
  "properties": {
    "addr:full":"129 Nelson Pl Williamstown VIC 3016",
    "addr:housenumber":"129",
    "addr:postcode":"3016",
    "addr:street":"Nelson Pl",
    "iso:country":"AU",
    "sg:address":"129 Nelson Pl",
    "sg:city":"Williamstown",
    "sg:classifiers":[
        {
            "category":"Fast Food",
            "type":"Food & Drink"
        }
    ],
    "sg:phone":"+61 3 9399 9961",
    "sg:postcode":"3016",
    "sg:province":"VIC",
    "sg:tags":[
        "away",
        "take"
    ],
    "wof:name":"Mussel's Fish & Chippery",
    "wof:placetype":"venue"
},
  "geometry": {"coordinates":[144.90513610799999,-37.8634185791],"type":"Point"}
}