{
  "type": "Feature",
  "properties": {
    "addr:full":"7- 9 Merriwa St Gordon NSW 2072",
    "addr:housenumber":"9",
    "addr:postcode":"2072",
    "addr:street":"Merriwa St",
    "iso:country":"AU",
    "sg:address":"7- 9 Merriwa St",
    "sg:city":"Gordon",
    "sg:classifiers":[
        {
            "category":"Professional",
            "subcategory":"Computer Services",
            "type":"Services"
        }
    ],
    "sg:phone":"+61 2 9418 2611",
    "sg:postcode":"2072",
    "sg:province":"NSW",
    "sg:tags":[
        "consultant",
        "system"
    ],
    "wof:name":"Computer Systems Engineering Pty Ltd",
    "wof:placetype":"venue"
},
  "geometry": {"coordinates":[151.148162842,-33.7527618408],"type":"Point"}
}