{
  "type": "Feature",
  "properties": {
    "addr:full":"7 Glasgow St Gympie QLD 4570",
    "addr:housenumber":"7",
    "addr:postcode":"4570",
    "addr:street":"Glasgow St",
    "iso:country":"AU",
    "sg:address":"7 Glasgow St",
    "sg:city":"Gympie",
    "sg:classifiers":[
        {
            "category":"Building & Trades",
            "subcategory":"Construction",
            "type":"Services"
        }
    ],
    "sg:phone":"+61 7 5482 4790",
    "sg:postcode":"4570",
    "sg:province":"QLD",
    "sg:tags":[
        "concrete",
        "contractor"
    ],
    "wof:name":"Dakin John",
    "wof:placetype":"venue"
},
  "geometry": {"coordinates":[152.666671753,-26.173664093],"type":"Point"}
}