{
  "type": "Feature",
  "properties": {
    "addr:full":"Cnr Burwood Hwy & Ferntree Gully Rd Ferntree Gully VIC 3156",
    "addr:postcode":"3156",
    "addr:street":"Burwood Hwy & Ferntree Gully Rd",
    "iso:country":"AU",
    "sg:address":"Cnr Burwood Hwy & Ferntree Gully Rd",
    "sg:city":"Ferntree Gully",
    "sg:classifiers":[
        {
            "category":"Food & Beverages",
            "subcategory":"Supermarket",
            "type":"Retail Goods"
        }
    ],
    "sg:phone":"+61 3 9753 6042",
    "sg:postcode":"3156",
    "sg:province":"VIC",
    "sg:tags":[
        "grocery",
        "store"
    ],
    "wof:name":"Safeway",
    "wof:placetype":"venue"
},
  "geometry": {"coordinates":[145.29675293,-37.8885650635],"type":"Point"}
}