{
  "type": "Feature",
  "properties": {
    "addr:full":"290 Enoggera Rd Newmarket QLD 4051",
    "addr:housenumber":"290",
    "addr:postcode":"4051",
    "addr:street":"Enoggera Rd",
    "iso:country":"AU",
    "sg:address":"290 Enoggera Rd",
    "sg:city":"Newmarket",
    "sg:classifiers":[
        {
            "category":"Fast Food",
            "type":"Food & Drink"
        }
    ],
    "sg:phone":"+61 7 3356 0973",
    "sg:postcode":"4051",
    "sg:province":"QLD",
    "sg:tags":[
        "away",
        "take"
    ],
    "wof:name":"McDonald's Family Restaurants",
    "wof:placetype":"venue"
},
  "geometry": {"coordinates":[153.00486755399999,-27.4322853088],"type":"Point"}
}