{
  "type": "Feature",
  "properties": {
    "addr:full":"PO Box 20 Glenorchy TAS 7010",
    "addr:postcode":"7010",
    "iso:country":"AU",
    "sg:address":"PO Box 20",
    "sg:city":"Glenorchy",
    "sg:classifiers":[
        {
            "category":"Building & Trades",
            "subcategory":"Construction",
            "type":"Services"
        }
    ],
    "sg:phone":"+61 3 6272 7269",
    "sg:postcode":"7010",
    "sg:province":"TAS",
    "sg:tags":[
        "installation",
        "air conditioning"
    ],
    "wof:name":"Wright Refrigeration",
    "wof:placetype":"venue"
},
  "geometry": {"coordinates":[147.279754639,-42.8336982727],"type":"Point"}
}