{
  "type": "Feature",
  "properties": {
    "addr:full":"1 Albion St Pennant Hills NSW 2120",
    "addr:housenumber":"1",
    "addr:postcode":"2120",
    "addr:street":"Albion St",
    "iso:country":"AU",
    "sg:address":"1 Albion St",
    "sg:city":"Pennant Hills",
    "sg:classifiers":[
        {
            "category":"Professional",
            "subcategory":"Computer Services",
            "type":"Services"
        }
    ],
    "sg:phone":"+61 2 9875 3497",
    "sg:postcode":"2120",
    "sg:province":"NSW",
    "sg:tags":[
        "consultant",
        "system"
    ],
    "wof:name":"Murnik Horson International & Associates",
    "wof:placetype":"venue"
},
  "geometry": {"coordinates":[151.07545471200001,-33.7360687256],"type":"Point"}
}