{
  "type": "Feature",
  "properties": {
    "addr:full":"Industrial Drv Gosford NSW 2250",
    "addr:postcode":"2250",
    "addr:street":"Industrial Drv",
    "iso:country":"AU",
    "sg:address":"Industrial Drv",
    "sg:city":"Gosford",
    "sg:classifiers":[
        {
            "category":"Freight",
            "type":"Transportation"
        }
    ],
    "sg:phone":"+61 433 176 084",
    "sg:postcode":"2250",
    "sg:province":"NSW",
    "sg:tags":[
        "cargo",
        "container"
    ],
    "wof:name":"Intermodal Solutions Pty Ltd",
    "wof:placetype":"venue"
},
  "geometry": {"coordinates":[151.34249877900001,-33.4237213135],"type":"Point"}
}