{
  "type": "Feature",
  "properties": {
    "addr:full":"U 4/ 3 Hinkler Crt Brendale QLD 4500",
    "addr:housenumber":"3",
    "addr:postcode":"4500",
    "addr:street":"Hinkler Crt",
    "iso:country":"AU",
    "sg:address":"U 4/ 3 Hinkler Crt",
    "sg:city":"Brendale",
    "sg:classifiers":[
        {
            "category":"Professional",
            "subcategory":"Computer Services",
            "type":"Services"
        }
    ],
    "sg:phone":"+61 7 3817 8888",
    "sg:postcode":"4500",
    "sg:province":"QLD",
    "sg:tags":[
        "consultant",
        "system"
    ],
    "wof:name":"Thinking Space It Solutions Pty Ltd",
    "wof:placetype":"venue"
},
  "geometry": {"coordinates":[152.989746094,-27.3158855438],"type":"Point"}
}