{
  "type": "Feature",
  "properties": {
    "iso:country":"AU",
    "sg:address":"417 Bridge St",
    "sg:city":"Wilsonton",
    "sg:classifiers":[
        {
            "category":"Personal",
            "subcategory":"Beauty Salon",
            "type":"Services"
        }
    ],
    "sg:phone":"+61 7 4633 1000",
    "sg:postcode":"4350",
    "sg:province":"QLD",
    "sg:tags":[
        "hairdresser"
    ],
    "wof:name":"Louises Place",
    "wof:placetype":"venue"
},
  "geometry": {"coordinates":[151.918137,-27.541111],"type":"Point"}
}