{
  "type": "Feature",
  "properties": {
    "addr:full":"14 Hayes St Caboolture QLD 4510",
    "addr:housenumber":"14",
    "addr:postcode":"4510",
    "addr:street":"Hayes St",
    "iso:country":"AU",
    "sg:address":"14 Hayes St",
    "sg:city":"Caboolture",
    "sg:classifiers":[
        {
            "category":"Health Services",
            "subcategory":"Doctor",
            "type":"Services"
        }
    ],
    "sg:phone":"+61 7 5428 8166",
    "sg:postcode":"4510",
    "sg:province":"QLD",
    "sg:tags":[
        "nurse",
        "nursing"
    ],
    "wof:name":"Blue Nurses Mobile Respite Service",
    "wof:placetype":"venue"
},
  "geometry": {"coordinates":[152.95469700000001,-27.081387],"type":"Point"}
}