{
  "type": "Feature",
  "properties": {
    "iso:country":"AU",
    "sg:address":"17 Pritchard Pl",
    "sg:city":"Peakhurst",
    "sg:classifiers":[
        {
            "category":"Retail",
            "subcategory":"Auto Repair",
            "type":"Services"
        }
    ],
    "sg:phone":"+61 2 9533 6171",
    "sg:postcode":"2210",
    "sg:province":"NSW",
    "sg:tags":[
        "repairer",
        "motor",
        "engineer"
    ],
    "wof:name":"Steve's Mechanical Repairs",
    "wof:placetype":"venue"
},
  "geometry": {"coordinates":[151.061813,-33.961781],"type":"Point"}
}