{
  "type": "Feature",
  "properties": {
    "iso:country":"AU",
    "sg:address":"PO Box 3013",
    "sg:city":"Glossodia",
    "sg:classifiers":[
        {
            "category":"Building & Trades",
            "subcategory":"Pest Control",
            "type":"Services"
        }
    ],
    "sg:phone":"+61 2 4576 6621",
    "sg:postcode":"2756",
    "sg:province":"NSW",
    "wof:name":"AJA Pest Management",
    "wof:placetype":"venue"
},
  "geometry": {"coordinates":[150.79563903799999,-33.5379219055],"type":"Point"}
}