{
  "type": "Feature",
  "properties": {
    "addr:full":"Kurraba Rd Neutral Bay NSW 2089",
    "addr:postcode":"2089",
    "addr:street":"Kurraba Rd",
    "iso:country":"AU",
    "sg:address":"Kurraba Rd",
    "sg:city":"Neutral Bay",
    "sg:classifiers":[
        {
            "category":"Recreation",
            "subcategory":"Boat Charter",
            "type":"Entertainment"
        }
    ],
    "sg:phone":"+61 2 9206 6666",
    "sg:postcode":"2089",
    "sg:province":"NSW",
    "wof:name":"John Cadman Cruising Restaurant The",
    "wof:placetype":"venue"
},
  "geometry": {"coordinates":[151.219680786,-33.8399162292],"type":"Point"}
}