{
  "type": "Feature",
  "properties": {
    "addr:full":"PO Box 48 Derby WA 6728",
    "addr:postcode":"6728",
    "iso:country":"AU",
    "sg:address":"PO Box 48",
    "sg:city":"Derby",
    "sg:classifiers":[
        {
            "category":"Communications",
            "subcategory":"News Services",
            "type":"Services"
        }
    ],
    "sg:phone":"+61 8 9191 1426",
    "sg:postcode":"6728",
    "sg:province":"WA",
    "sg:tags":[
        "information",
        "tourist",
        "attractions"
    ],
    "wof:name":"Derby Visitor Centre",
    "wof:placetype":"venue"
},
  "geometry": {"coordinates":[123.665222168,-17.3448696136],"type":"Point"}
}