{
  "type": "Feature",
  "properties": {
    "addr:full":"53 Fullarton Rd Kent Town SA 5067",
    "addr:housenumber":"53",
    "addr:postcode":"5067",
    "addr:street":"Fullarton Rd",
    "iso:country":"AU",
    "sg:address":"53 Fullarton Rd",
    "sg:city":"Kent Town",
    "sg:classifiers":[
        {
            "category":"Banks & Credit Unions",
            "subcategory":"Investment Brokerage",
            "type":"Services"
        }
    ],
    "sg:phone":"+61 8 8332 3011",
    "sg:postcode":"5067",
    "sg:province":"SA",
    "sg:tags":[
        "management",
        "property"
    ],
    "wof:name":"Neale Realty Property Management",
    "wof:placetype":"venue"
},
  "geometry": {"coordinates":[138.62327575699999,-34.9201622009],"type":"Point"}
}