{
  "type": "Feature",
  "properties": {
    "addr:full":"6 St Mary&#039;s Crt Bundaberg QLD 4670",
    "addr:housenumber":"6",
    "addr:postcode":"4670",
    "addr:street":"St Mary &;039 S Crt",
    "iso:country":"AU",
    "sg:address":"6 St Mary&#039;s Crt",
    "sg:city":"Bundaberg",
    "sg:classifiers":[
        {
            "category":"Retail",
            "subcategory":"Driving School",
            "type":"Services"
        }
    ],
    "sg:phone":"+61 7 4151 4493",
    "sg:postcode":"4670",
    "sg:province":"QLD",
    "wof:name":"Joe Kitching",
    "wof:placetype":"venue"
},
  "geometry": {"coordinates":[152.34669494600001,-24.8670501709],"type":"Point"}
}