{
  "type": "Feature",
  "properties": {
    "addr:full":"Cnr Archerfield & Freeman Rds Richlands QLD 4077",
    "addr:postcode":"4077",
    "addr:street":"Cnr",
    "iso:country":"AU",
    "sg:address":"Cnr Archerfield & Freeman Rds",
    "sg:city":"Richlands",
    "sg:classifiers":[
        {
            "category":"Shopping",
            "subcategory":"Stationery & Office Supplies",
            "type":"Retail Goods"
        }
    ],
    "sg:phone":"+61 7 3375 7100",
    "sg:postcode":"4077",
    "sg:province":"QLD",
    "sg:tags":[
        "packaging",
        "material"
    ],
    "wof:name":"Packmate",
    "wof:placetype":"venue"
},
  "geometry": {"coordinates":[152.959594727,-27.594789505],"type":"Point"}
}