{
  "type": "Feature",
  "properties": {
    "addr:full":"16-18 Jewell Crt Bendigo East VIC 3550",
    "addr:housenumber":"16-18",
    "addr:postcode":"3550",
    "addr:street":"Jewell Crt",
    "iso:country":"AU",
    "sg:address":"16-18 Jewell Crt",
    "sg:city":"Bendigo East",
    "sg:classifiers":[
        {
            "category":"Retail",
            "subcategory":"Auto Repair",
            "type":"Services"
        }
    ],
    "sg:phone":"+61 3 5441 1578",
    "sg:postcode":"3550",
    "sg:province":"VIC",
    "sg:tags":[
        "beater",
        "painter",
        "panel"
    ],
    "wof:name":"Justin Kings Panels",
    "wof:placetype":"venue"
},
  "geometry": {"coordinates":[144.308792114,-36.7433853149],"type":"Point"}
}