{
  "type": "Feature",
  "properties": {
    "addr:full":"11- 13 Moncrief Rd Nunawading VIC 3131",
    "addr:housenumber":"13",
    "addr:postcode":"3131",
    "addr:street":"Moncrief Rd",
    "iso:country":"AU",
    "sg:address":"11- 13 Moncrief Rd",
    "sg:city":"Nunawading",
    "sg:classifiers":[
        {
            "category":"Wholesale",
            "subcategory":"Music Publishers",
            "type":"Manufacturing & Wholesale Goods"
        }
    ],
    "sg:phone":"+61 3 9894 4900",
    "sg:postcode":"3131",
    "sg:province":"VIC",
    "sg:tags":[
        "wholesaler",
        "dvd",
        "mfrs",
        "cd"
    ],
    "wof:name":"Word Australia",
    "wof:placetype":"venue"
},
  "geometry": {"coordinates":[145.17036438,-37.8193397522],"type":"Point"}
}