{
  "type": "Feature",
  "properties": {
    "addr:full":"12 Sylvia Crt Coromandel Valley SA 5051",
    "addr:housenumber":"12",
    "addr:postcode":"5051",
    "addr:street":"Sylvia Crt",
    "iso:country":"AU",
    "sg:address":"12 Sylvia Crt",
    "sg:city":"Coromandel Valley",
    "sg:classifiers":[
        {
            "category":"Professional",
            "subcategory":"Accounting & Tax Preparation",
            "type":"Services"
        }
    ],
    "sg:phone":"+61 8 8270 2079",
    "sg:postcode":"5051",
    "sg:province":"SA",
    "sg:tags":[
        "consultant",
        "taxation"
    ],
    "wof:name":"Southern Taxation Services",
    "wof:placetype":"venue"
},
  "geometry": {"coordinates":[138.61816400000001,-35.048176],"type":"Point"}
}