{
  "type": "Feature",
  "properties": {
    "addr:full":"Shop 35 Marina Mirage Inlet Rd Port Douglas QLD 4877",
    "addr:housenumber":"shop 35",
    "addr:postcode":"4877",
    "addr:street":"Inlet Rd",
    "iso:country":"AU",
    "sg:address":"Shop 35 Marina Mirage Inlet Rd",
    "sg:city":"Port Douglas",
    "sg:classifiers":[
        {
            "category":"Shopping",
            "subcategory":"Baby Store",
            "type":"Retail Goods"
        }
    ],
    "sg:phone":"+61 7 4099 5992",
    "sg:postcode":"4877",
    "sg:province":"QLD",
    "sg:tags":[
        "children's",
        "wear"
    ],
    "wof:name":"Just Kidding",
    "wof:placetype":"venue"
},
  "geometry": {"coordinates":[145.46543884299999,-16.4844493866],"type":"Point"}
}