{
  "type": "Feature",
  "properties": {
    "addr:full":"301 Ann St Brisbane QLD 4000",
    "addr:housenumber":"301",
    "addr:postcode":"4000",
    "addr:street":"Ann St",
    "iso:country":"AU",
    "sg:address":"301 Ann St",
    "sg:city":"Brisbane",
    "sg:classifiers":[
        {
            "category":"Sports & Exercise",
            "subcategory":"Gym",
            "type":"Entertainment"
        }
    ],
    "sg:phone":"+61 7 3220 0130",
    "sg:postcode":"4000",
    "sg:province":"QLD",
    "sg:tags":[
        "health",
        "fitness"
    ],
    "wof:name":"Rothbury Health & Lifestyle Connection",
    "wof:placetype":"venue"
},
  "geometry": {"coordinates":[153.02740478499999,-27.4654941559],"type":"Point"}
}