{
  "type": "Feature",
  "properties": {
    "iso:country":"AU",
    "sg:address":"Range Rd",
    "sg:city":"Uraidla",
    "sg:classifiers":[
        {
            "category":"Food & Beverages",
            "subcategory":"Fruits & Vegetables",
            "type":"Retail Goods"
        }
    ],
    "sg:phone":"+61 8 8390 1765",
    "sg:postcode":"5142",
    "sg:province":"SA",
    "sg:tags":[
        "wholesale"
    ],
    "wof:name":"Parker A F & Sons",
    "wof:placetype":"venue"
},
  "geometry": {"coordinates":[138.750931,-34.960896],"type":"Point"}
}