{
  "type": "Feature",
  "properties": {
    "iso:country":"AU",
    "sg:address":"11 Housman St",
    "sg:city":"Wetherill Park",
    "sg:classifiers":[
        {
            "category":"Health Services",
            "subcategory":"Dentist",
            "type":"Services"
        }
    ],
    "sg:phone":"+61 2 9729 4788",
    "sg:postcode":"2164",
    "sg:province":"NSW",
    "wof:name":"Tan K C & Associates",
    "wof:placetype":"venue"
},
  "geometry": {"coordinates":[150.89991760300001,-33.8564605713],"type":"Point"}
}