{
  "type": "Feature",
  "properties": {
    "addr:full":"Suite 9, 1917- 1919 Albany Hwy Maddington WA 6109",
    "addr:housenumber":"1917 1919",
    "addr:postcode":"6109",
    "addr:street":"Albany Hwy",
    "iso:country":"AU",
    "sg:address":"Suite 9, 1917- 1919 Albany Hwy",
    "sg:city":"Maddington",
    "sg:classifiers":[
        {
            "category":"Professional",
            "subcategory":"Engineering",
            "type":"Services"
        }
    ],
    "sg:phone":"+61 418 946 662",
    "sg:postcode":"6109",
    "sg:province":"WA",
    "sg:tags":[
        "engineer",
        "designing"
    ],
    "wof:name":"DJB Design Pty Ltd",
    "wof:placetype":"venue"
},
  "geometry": {"coordinates":[115.98525238000001,-32.0519790649],"type":"Point"}
}