{
  "type": "Feature",
  "properties": {
    "addr:full":"10 Crow St Gladstone QLD 4680",
    "addr:housenumber":"10",
    "addr:postcode":"4680",
    "addr:street":"Crow St",
    "iso:country":"AU",
    "sg:address":"10 Crow St",
    "sg:city":"Gladstone",
    "sg:classifiers":[
        {
            "category":"Building & Trades",
            "subcategory":"Construction",
            "type":"Services"
        }
    ],
    "sg:phone":"+61 7 4972 9954",
    "sg:postcode":"4680",
    "sg:province":"QLD",
    "sg:tags":[
        "earth",
        "excavating",
        "moving",
        "contractor"
    ],
    "wof:name":"Kerfoot Earthmoving",
    "wof:placetype":"venue"
},
  "geometry": {"coordinates":[151.24932861299999,-23.8421096802],"type":"Point"}
}