{
  "type": "Feature",
  "properties": {
    "addr:full":"53 Grace St Herberton QLD 4872",
    "addr:housenumber":"53",
    "addr:postcode":"4872",
    "addr:street":"Grace St",
    "iso:country":"AU",
    "sg:address":"53 Grace St",
    "sg:city":"Herberton",
    "sg:classifiers":[
        {
            "category":"Food & Beverages",
            "subcategory":"Supermarket",
            "type":"Retail Goods"
        }
    ],
    "sg:phone":"+61 7 4096 2236",
    "sg:postcode":"4872",
    "sg:province":"QLD",
    "sg:tags":[
        "grocery",
        "store"
    ],
    "wof:name":"Herberton Convenience Store",
    "wof:placetype":"venue"
},
  "geometry": {"coordinates":[145.38551330600001,-17.3838233948],"type":"Point"}
}