{
  "type": "Feature",
  "properties": {
    "addr:full":"Cnr Clayton & Thabeban Rd Bundaberg QLD 4670",
    "addr:postcode":"4670",
    "addr:street":"Cnr;Rd",
    "iso:country":"AU",
    "sg:address":"Cnr Clayton & Thabeban Rd",
    "sg:city":"Bundaberg",
    "sg:classifiers":[
        {
            "category":"Home & Garden",
            "subcategory":"Building Materials",
            "type":"Retail Goods"
        }
    ],
    "sg:phone":"+61 7 4152 2077",
    "sg:postcode":"4670",
    "sg:province":"QLD",
    "sg:tags":[
        "fencing"
    ],
    "wof:name":"Ace Fabrications Pty Ltd",
    "wof:placetype":"venue"
},
  "geometry": {"coordinates":[152.35256957999999,-24.8950405121],"type":"Point"}
}