{
  "type": "Feature",
  "properties": {
    "iso:country":"AU",
    "sg:address":"PO Box 91",
    "sg:city":"Portland",
    "sg:classifiers":[
        {
            "category":"Building & Trades",
            "subcategory":"Construction",
            "type":"Services"
        }
    ],
    "sg:phone":"+61 404 472 241",
    "sg:postcode":"2847",
    "sg:province":"NSW",
    "sg:tags":[
        "joiner",
        "carpenter"
    ],
    "wof:name":"SR & LM Cunningham",
    "wof:placetype":"venue"
},
  "geometry": {"coordinates":[149.98175000000001,-33.35305],"type":"Point"}
}