{
  "type": "Feature",
  "properties": {
    "addr:full":"281 Old Northern Rd Castle Hill NSW 2154",
    "addr:housenumber":"281",
    "addr:postcode":"2154",
    "addr:street":"Old Northern Rd",
    "iso:country":"AU",
    "sg:address":"281 Old Northern Rd",
    "sg:city":"Castle Hill",
    "sg:classifiers":[
        {
            "category":"Personal",
            "subcategory":"Beauty Salon",
            "type":"Services"
        }
    ],
    "sg:phone":"+61 2 9634 2073",
    "sg:postcode":"2154",
    "sg:province":"NSW",
    "sg:tags":[
        "hairdresser"
    ],
    "wof:name":"Goldies Locks",
    "wof:placetype":"venue"
},
  "geometry": {"coordinates":[151.00494384800001,-33.7331962585],"type":"Point"}
}