{
  "type": "Feature",
  "properties": {
    "iso:country":"AU",
    "sg:address":"1 Wild Duck Drv Via Rafferty&#039;s Rd",
    "sg:city":"Cams Wharf",
    "sg:classifiers":[
        {
            "category":"Travel",
            "subcategory":"Hotels & Motels",
            "type":"Entertainment"
        }
    ],
    "sg:phone":"+61 2 4972 5555",
    "sg:postcode":"2281",
    "sg:province":"NSW",
    "sg:tags":[
        "accommodation"
    ],
    "wof:name":"Raffertys Resort Lake Macquarie",
    "wof:placetype":"venue"
},
  "geometry": {"coordinates":[151.64662170400001,-33.1084709167],"type":"Point"}
}