{
  "type": "Feature",
  "properties": {
    "addr:full":"Fulham Rd Rowville VIC 3178",
    "addr:postcode":"3178",
    "addr:street":"Fulham Rd",
    "iso:country":"AU",
    "sg:address":"Fulham Rd",
    "sg:city":"Rowville",
    "sg:classifiers":[
        {
            "category":"Professional",
            "subcategory":"Art Services",
            "type":"Services"
        }
    ],
    "sg:phone":"+61 3 9763 8478",
    "sg:postcode":"3178",
    "sg:province":"VIC",
    "sg:tags":[
        "picture",
        "frame",
        "framing"
    ],
    "wof:name":"Apex Art",
    "wof:placetype":"venue"
},
  "geometry": {"coordinates":[145.23997497600001,-37.9188919067],"type":"Point"}
}