{
  "type": "Feature",
  "properties": {
    "addr:full":"26 - 32 Berry St Nowra NSW 2540",
    "addr:housenumber":"32",
    "addr:postcode":"2540",
    "addr:street":"Berry St",
    "iso:country":"AU",
    "sg:address":"26 - 32 Berry St",
    "sg:city":"Nowra",
    "sg:classifiers":[
        {
            "category":"Building & Trades",
            "subcategory":"Equipment Rental",
            "type":"Services"
        }
    ],
    "sg:phone":"+61 2 4421 4413",
    "sg:postcode":"2540",
    "sg:province":"NSW",
    "sg:tags":[
        "party",
        "hire"
    ],
    "wof:name":"Spotlight Party Supplies (SPARTYS)",
    "wof:placetype":"venue"
},
  "geometry": {"coordinates":[150.67161560100001,-35.0481300354],"type":"Point"}
}