{
  "type": "Feature",
  "properties": {
    "iso:country":"AU",
    "sg:address":"Lvl 3, 2A Lord St",
    "sg:city":"Botany",
    "sg:classifiers":[
        {
            "category":"Government",
            "subcategory":"Fire Station",
            "type":"Public Place"
        }
    ],
    "sg:phone":"+61 1800 074 000",
    "sg:postcode":"2019",
    "sg:province":"NSW",
    "sg:tags":[
        "equipment",
        "protection",
        "consultant"
    ],
    "wof:name":"Assured Fire",
    "wof:placetype":"venue"
},
  "geometry": {"coordinates":[151.195220947,-33.9405937195],"type":"Point"}
}