{
  "type": "Feature",
  "properties": {
    "addr:full":"180 Fyans St (cnr Crown St) South Geelong VIC 3220",
    "addr:housenumber":"180",
    "addr:postcode":"3220",
    "addr:street":"Fyans St Cnr Crown St",
    "iso:country":"AU",
    "sg:address":"180 Fyans St (cnr Crown St)",
    "sg:city":"South Geelong",
    "sg:classifiers":[
        {
            "category":"Autos & Motor Vehicles",
            "subcategory":"Automobile Sales",
            "type":"Retail Goods"
        }
    ],
    "sg:phone":"+61 3 5222 4450",
    "sg:postcode":"3220",
    "sg:province":"VIC",
    "sg:tags":[
        "car",
        "used"
    ],
    "wof:name":"Campana Car Sales & Service",
    "wof:placetype":"venue"
},
  "geometry": {"coordinates":[144.367493,-38.165527],"type":"Point"}
}