{
  "type": "Feature",
  "properties": {
    "addr:full":"\"Oxford\" E Summerville Rd Borallon QLD 4306",
    "addr:postcode":"4306",
    "addr:street":"Summerville Rd",
    "iso:country":"AU",
    "sg:address":"\"Oxford\" E Summerville Rd",
    "sg:city":"Borallon",
    "sg:classifiers":[
        {
            "category":"Farming",
            "subcategory":"Livestock Farm",
            "type":"Manufacturing & Wholesale Goods"
        }
    ],
    "sg:phone":"+61 7 5464 3704",
    "sg:postcode":"4306",
    "sg:province":"QLD",
    "sg:tags":[
        "breeder",
        "horse",
        "stud"
    ],
    "wof:name":"Bremervale Arabian Stud",
    "wof:placetype":"venue"
},
  "geometry": {"coordinates":[152.688354492,-27.5022563934],"type":"Point"}
}