{
  "type": "Feature",
  "properties": {
    "addr:full":"30 Feltbush Mews Canning Vale WA 6155",
    "addr:housenumber":"30",
    "addr:postcode":"6155",
    "addr:street":"Feltbush Mews",
    "iso:country":"AU",
    "sg:address":"30 Feltbush Mews",
    "sg:city":"Canning Vale",
    "sg:classifiers":[
        {
            "category":"Building & Trades",
            "subcategory":"Cleaning & Sanitation",
            "type":"Services"
        }
    ],
    "sg:phone":"+61 417 778 669",
    "sg:postcode":"6155",
    "sg:province":"WA",
    "sg:tags":[
        "chemical",
        "pressure",
        "steam",
        "contractor"
    ],
    "wof:name":"HydroJet",
    "wof:placetype":"venue"
},
  "geometry": {"coordinates":[115.919518,-32.078243],"type":"Point"}
}