{
  "type": "Feature",
  "properties": {
    "addr:full":"23 Park Rd Cheltenham VIC 3192",
    "addr:housenumber":"23",
    "addr:postcode":"3192",
    "addr:street":"Park Rd",
    "iso:country":"AU",
    "sg:address":"23 Park Rd",
    "sg:city":"Cheltenham",
    "sg:classifiers":[
        {
            "category":"Professional",
            "subcategory":"Engineering",
            "type":"Services"
        }
    ],
    "sg:phone":"+61 3 9583 5107",
    "sg:postcode":"3192",
    "sg:province":"VIC",
    "sg:tags":[
        "engineer"
    ],
    "wof:name":"Kaine Engineering",
    "wof:placetype":"venue"
},
  "geometry": {"coordinates":[145.04014587399999,-37.9633216858],"type":"Point"}
}