{
  "type": "Feature",
  "properties": {
    "addr:full":"75 Blackwall Rd Woy Woy NSW 2256",
    "addr:housenumber":"75",
    "addr:postcode":"2256",
    "addr:street":"Blackwall Rd",
    "iso:country":"AU",
    "sg:address":"75 Blackwall Rd",
    "sg:city":"Woy Woy",
    "sg:classifiers":[
        {
            "category":"Personal",
            "subcategory":"Beauty Salon",
            "type":"Services"
        }
    ],
    "sg:phone":"+61 2 4341 8106",
    "sg:postcode":"2256",
    "sg:province":"NSW",
    "sg:tags":[
        "hairdresser"
    ],
    "wof:name":"Lesleys Talk Of The Town Hair Salon",
    "wof:placetype":"venue"
},
  "geometry": {"coordinates":[151.32525634800001,-33.4871444702],"type":"Point"}
}