{
  "type": "Feature",
  "properties": {
    "iso:country":"AU",
    "sg:address":"16 Derby St",
    "sg:city":"Walcha",
    "sg:classifiers":[
        {
            "category":"Personal",
            "subcategory":"Tattoo Parlor",
            "type":"Services"
        }
    ],
    "sg:phone":"+61 2 6778 0340",
    "sg:postcode":"2354",
    "sg:province":"NSW",
    "sg:tags":[
        "tattooing"
    ],
    "wof:name":"Beauty On Derby",
    "wof:placetype":"venue"
},
  "geometry": {"coordinates":[151.59364318900001,-30.9845981598],"type":"Point"}
}