{
  "type": "Feature",
  "properties": {
    "addr:full":"17 Rowntree St Balmain NSW 2041",
    "addr:housenumber":"17",
    "addr:postcode":"2041",
    "addr:street":"Rowntree St",
    "iso:country":"AU",
    "sg:address":"17 Rowntree St",
    "sg:city":"Balmain",
    "sg:classifiers":[
        {
            "category":"Education",
            "subcategory":"Vocational School",
            "type":"Public Place"
        }
    ],
    "sg:phone":"+61 2 9810 3843",
    "sg:postcode":"2041",
    "sg:province":"NSW",
    "sg:tags":[
        "cake",
        "decorating",
        "decorator"
    ],
    "wof:name":"Planet Cake",
    "wof:placetype":"venue"
},
  "geometry": {"coordinates":[151.178436,-33.855862],"type":"Point"}
}