{
  "type": "Feature",
  "properties": {
    "iso:country":"AU",
    "sg:address":"12 Grassmere Crt",
    "sg:city":"Banora Point",
    "sg:classifiers":[
        {
            "category":"Utilities",
            "subcategory":"Electric",
            "type":"Services"
        }
    ],
    "sg:phone":"+61 418 753 726",
    "sg:postcode":"2486",
    "sg:province":"NSW",
    "sg:tags":[
        "electrical",
        "contractor"
    ],
    "wof:name":"Bob Woods Electrical",
    "wof:placetype":"venue"
},
  "geometry": {"coordinates":[153.52656555199999,-28.2118587494],"type":"Point"}
}