{
  "type": "Feature",
  "properties": {
    "iso:country":"AU",
    "sg:address":"PO Box 30",
    "sg:city":"Tathra",
    "sg:classifiers":[
        {
            "category":"Education",
            "subcategory":"Dance Studio",
            "type":"Public Place"
        }
    ],
    "sg:phone":"+61 2 6494 4376",
    "sg:postcode":"2550",
    "sg:province":"NSW",
    "sg:tags":[
        "venue",
        "tuition"
    ],
    "wof:name":"Insight Dance & Movement",
    "wof:placetype":"venue"
},
  "geometry": {"coordinates":[149.985397339,-36.7294692993],"type":"Point"}
}