{
  "type": "Feature",
  "properties": {
    "iso:country":"AU",
    "sg:address":"1 Christine Ave",
    "sg:city":"Robina",
    "sg:classifiers":[
        {
            "category":"Health Services",
            "subcategory":"Dentist",
            "type":"Services"
        }
    ],
    "sg:phone":"+61 7 5576 4900",
    "sg:postcode":"4226",
    "sg:province":"QLD",
    "wof:name":"Christine Avenue Dental Surgery",
    "wof:placetype":"venue"
},
  "geometry": {"coordinates":[153.40054321299999,-28.0878810883],"type":"Point"}
}