{
  "type": "Feature",
  "properties": {
    "iso:country":"AU",
    "sg:address":"13 Ibis St",
    "sg:city":"Maroochydore",
    "sg:classifiers":[
        {
            "category":"Building & Trades",
            "subcategory":"Construction",
            "type":"Services"
        }
    ],
    "sg:phone":"+61 7 5445 3464",
    "sg:postcode":"4558",
    "sg:province":"QLD",
    "sg:tags":[
        "contractor"
    ],
    "wof:name":"Butler Paul",
    "wof:placetype":"venue"
},
  "geometry": {"coordinates":[153.054031372,-26.661775589],"type":"Point"}
}