{
  "type": "Feature",
  "properties": {
    "iso:country":"AU",
    "sg:address":"20 Lucky Drv",
    "sg:city":"Billinudgel",
    "sg:classifiers":[
        {
            "category":"Retail",
            "subcategory":"Veterinary Services",
            "type":"Services"
        }
    ],
    "sg:phone":"+61 2 6680 3480",
    "sg:postcode":"2483",
    "sg:province":"NSW",
    "sg:tags":[
        "surgeon"
    ],
    "wof:name":"Billinudgel/Ocean Shores",
    "wof:placetype":"venue"
},
  "geometry": {"coordinates":[153.529388428,-28.5062656403],"type":"Point"}
}