{
  "type": "Feature",
  "properties": {
    "iso:country":"AU",
    "sg:address":"270 Avalon Rd",
    "sg:city":"Lara",
    "sg:classifiers":[
        {
            "category":"Farming",
            "subcategory":"Livestock Farm",
            "type":"Manufacturing & Wholesale Goods"
        }
    ],
    "sg:phone":"+61 415 177 188",
    "sg:postcode":"3212",
    "sg:province":"VIC",
    "sg:tags":[
        "breeder",
        "horse",
        "stud"
    ],
    "wof:name":"Painted Acres performance paint & quater horse stud",
    "wof:placetype":"venue"
},
  "geometry": {"coordinates":[144.426544189,-38.0606842041],"type":"Point"}
}