{
  "type": "Feature",
  "properties": {
    "iso:country":"AU",
    "sg:address":"50 Grattan St",
    "sg:city":"Carlton",
    "sg:classifiers":[
        {
            "category":"Retail",
            "subcategory":"Event Space",
            "type":"Services"
        }
    ],
    "sg:phone":"+61 3 9347 0444",
    "sg:postcode":"3053",
    "sg:province":"VIC",
    "sg:tags":[
        "venue",
        "reception",
        "wedding"
    ],
    "wof:name":"Celebrate In Style",
    "wof:placetype":"venue"
},
  "geometry": {"coordinates":[144.96794128400001,-37.8007011414],"type":"Point"}
}