{
  "type": "Feature",
  "properties": {
    "addr:full":"47 Russell St Abbotsford VIC 3067",
    "addr:housenumber":"47",
    "addr:postcode":"3067",
    "addr:street":"Russell St",
    "iso:country":"AU",
    "sg:address":"47 Russell St",
    "sg:city":"Abbotsford",
    "sg:classifiers":[
        {
            "category":"Retail",
            "subcategory":"Auto Repair",
            "type":"Services"
        }
    ],
    "sg:phone":"+61 3 9416 5145",
    "sg:postcode":"3067",
    "sg:province":"VIC",
    "sg:tags":[
        "repairer",
        "motor",
        "engineer"
    ],
    "wof:name":"Kim Abbotsford Auto Repair",
    "wof:placetype":"venue"
},
  "geometry": {"coordinates":[144.993286133,-37.8052597046],"type":"Point"}
}