{
  "type": "Feature",
  "properties": {
    "iso:country":"AU",
    "sg:address":"Gipps St",
    "sg:city":"Wellington",
    "sg:classifiers":[
        {
            "category":"Education",
            "subcategory":"School",
            "type":"Public Place"
        }
    ],
    "sg:phone":"+61 2 6845 1999",
    "sg:postcode":"2820",
    "sg:province":"NSW",
    "wof:name":"Wellington Christian School",
    "wof:placetype":"venue"
},
  "geometry": {"coordinates":[148.93048095699999,-32.5410079956],"type":"Point"}
}