{
  "type": "Feature",
  "properties": {
    "addr:full":"9 King St Chinchilla QLD 4413",
    "addr:housenumber":"9",
    "addr:postcode":"4413",
    "addr:street":"King St",
    "iso:country":"AU",
    "sg:address":"9 King St",
    "sg:city":"Chinchilla",
    "sg:classifiers":[
        {
            "category":"Commercial Area",
            "type":"Public Place"
        }
    ],
    "sg:phone":"+61 7 4662 7864",
    "sg:postcode":"4413",
    "sg:province":"QLD",
    "sg:tags":[
        "heavy",
        "carrier"
    ],
    "wof:name":"Kurtz Transport Pty Ltd",
    "wof:placetype":"venue"
},
  "geometry": {"coordinates":[150.634643555,-26.7348556519],"type":"Point"}
}