{
  "type": "Feature",
  "properties": {
    "iso:country":"AU",
    "sg:address":"299 Annerley Rd",
    "sg:city":"Annerley",
    "sg:classifiers":[
        {
            "category":"Shopping",
            "subcategory":"Mobile Phones",
            "type":"Retail Goods"
        }
    ],
    "sg:phone":"+61 7 3392 1655",
    "sg:postcode":"4103",
    "sg:province":"QLD",
    "sg:tags":[
        "telephone",
        "accessory"
    ],
    "wof:name":"AAA Celcom",
    "wof:placetype":"venue"
},
  "geometry": {"coordinates":[153.030792236,-27.5030326843],"type":"Point"}
}