{
  "type": "Feature",
  "properties": {
    "iso:country":"AU",
    "sg:address":"Shp 6/ 1 Kingfisher Drv",
    "sg:city":"Hewett",
    "sg:classifiers":[
        {
            "category":"Food & Beverages",
            "subcategory":"Bakery",
            "type":"Retail Goods"
        }
    ],
    "sg:phone":"+61 8 8522 5805",
    "sg:postcode":"5118",
    "sg:province":"SA",
    "sg:tags":[
        "baker"
    ],
    "wof:name":"Hewitt Country Bakery",
    "wof:placetype":"venue"
},
  "geometry": {"coordinates":[138.748367,-34.578655],"type":"Point"}
}