{
  "type": "Feature",
  "properties": {
    "iso:country":"AU",
    "sg:address":"30 Sorrell St",
    "sg:city":"Parramatta",
    "sg:classifiers":[
        {
            "category":"Shopping",
            "subcategory":"Beauty & Cosmetics",
            "type":"Retail Goods"
        }
    ],
    "sg:phone":"+61 2 9630 6388",
    "sg:postcode":"2150",
    "sg:province":"NSW",
    "sg:tags":[
        "equipment",
        "salon",
        "supply"
    ],
    "wof:name":"Meikin Li Rees",
    "wof:placetype":"venue"
},
  "geometry": {"coordinates":[151.00733947800001,-33.8077201843],"type":"Point"}
}