{
  "type": "Feature",
  "properties": {
    "iso:country":"AU",
    "sg:address":"255 Wickham Rd",
    "sg:city":"Moorabbin",
    "sg:classifiers":[
        {
            "category":"Professional",
            "subcategory":"Detective & Security Services",
            "type":"Services"
        }
    ],
    "sg:phone":"+61 3 9523 5555",
    "sg:postcode":"3189",
    "sg:province":"VIC",
    "sg:tags":[
        "equipment",
        "window",
        "doors"
    ],
    "wof:name":"Steel Iron Security Pty Ltd",
    "wof:placetype":"venue"
},
  "geometry": {"coordinates":[145.05398559599999,-37.9464302063],"type":"Point"}
}