{
  "type": "Feature",
  "properties": {
    "addr:full":"37 Westview St Karrinyup WA 6018",
    "addr:housenumber":"37",
    "addr:postcode":"6018",
    "addr:street":"Westview St",
    "iso:country":"AU",
    "sg:address":"37 Westview St",
    "sg:city":"Karrinyup",
    "sg:classifiers":[
        {
            "category":"Professional",
            "subcategory":"Engineering",
            "type":"Services"
        }
    ],
    "sg:phone":"+61 8 9341 7299",
    "sg:postcode":"6018",
    "sg:province":"WA",
    "sg:tags":[
        "consulting",
        "engineer"
    ],
    "wof:name":"Marcom Electronics",
    "wof:placetype":"venue"
},
  "geometry": {"coordinates":[115.773971558,-31.8841056824],"type":"Point"}
}