{
  "type": "Feature",
  "properties": {
    "iso:country":"AU",
    "sg:address":"Unit 1, 164 Smart Rd",
    "sg:city":"St Agnes",
    "sg:classifiers":[
        {
            "category":"Building & Trades",
            "subcategory":"Pest Control",
            "type":"Services"
        }
    ],
    "sg:phone":"+61 8 8523 1898",
    "sg:postcode":"5097",
    "sg:province":"SA",
    "wof:name":"Doug Aufderheide",
    "wof:placetype":"venue"
},
  "geometry": {"coordinates":[138.71241760300001,-34.8319816589],"type":"Point"}
}