{
  "type": "Feature",
  "properties": {
    "addr:full":"Church St Dampier WA 6713",
    "addr:postcode":"6713",
    "addr:street":"Church St",
    "iso:country":"AU",
    "sg:address":"Church St",
    "sg:city":"Dampier",
    "sg:classifiers":[
        {
            "category":"Education",
            "subcategory":"School",
            "type":"Public Place"
        }
    ],
    "sg:phone":"+61 8 9183 1174",
    "sg:postcode":"6713",
    "sg:province":"WA",
    "sg:tags":[
        "state",
        "except",
        "nsw"
    ],
    "wof:name":"Dampier Primary School",
    "wof:placetype":"venue"
},
  "geometry": {"coordinates":[116.710632324,-20.6622867584],"type":"Point"}
}