{
  "type": "Feature",
  "properties": {
    "addr:full":"60 Auburn St Sutherland NSW 2232",
    "addr:housenumber":"60",
    "addr:postcode":"2232",
    "addr:street":"Auburn St",
    "iso:country":"AU",
    "sg:address":"60 Auburn St",
    "sg:city":"Sutherland",
    "sg:classifiers":[
        {
            "category":"Professional",
            "subcategory":"Detective & Security Services",
            "type":"Services"
        }
    ],
    "sg:phone":"+61 2 9545 1849",
    "sg:postcode":"2232",
    "sg:province":"NSW",
    "sg:tags":[
        "consultant",
        "system"
    ],
    "wof:name":"Capsis Security Alarms",
    "wof:placetype":"venue"
},
  "geometry": {"coordinates":[151.06497192399999,-34.0333747864],"type":"Point"}
}