{
  "type": "Feature",
  "properties": {
    "addr:full":"Level 3, 20 Terrace Rd East Perth WA 6004",
    "addr:housenumber":"20",
    "addr:postcode":"6004",
    "addr:street":"Terrace Rd East",
    "iso:country":"AU",
    "sg:address":"Level 3, 20 Terrace Rd",
    "sg:city":"East Perth",
    "sg:classifiers":[
        {
            "category":"Professional",
            "subcategory":"Engineering",
            "type":"Services"
        }
    ],
    "sg:phone":"+61 8 9326 0100",
    "sg:postcode":"6004",
    "sg:province":"WA",
    "sg:tags":[
        "consultant",
        "geotechnical",
        "engineer"
    ],
    "wof:name":"URS",
    "wof:placetype":"venue"
},
  "geometry": {"coordinates":[115.87323761,-31.9619522095],"type":"Point"}
}