{
  "type": "Feature",
  "properties": {
    "addr:full":"1/24 Russell La Batemans Bay NSW 2536",
    "addr:housenumber":"/ 24",
    "addr:postcode":"2536",
    "addr:street":"Russell La",
    "iso:country":"AU",
    "sg:address":"1/24 Russell La",
    "sg:city":"Batemans Bay",
    "sg:classifiers":[
        {
            "category":"Building & Trades",
            "subcategory":"Construction",
            "type":"Services"
        }
    ],
    "sg:phone":"+61 2 4472 4142",
    "sg:postcode":"2536",
    "sg:province":"NSW",
    "sg:tags":[
        "joinery"
    ],
    "wof:name":"Advanced Kitchens",
    "wof:placetype":"venue"
},
  "geometry": {"coordinates":[150.178192139,-35.7182693481],"type":"Point"}
}