{
  "type": "Feature",
  "properties": {
    "iso:country":"AU",
    "sg:address":"32 Geelong Ave",
    "sg:city":"Holland Park",
    "sg:classifiers":[
        {
            "category":"Real Estate",
            "subcategory":"Architect",
            "type":"Services"
        }
    ],
    "sg:phone":"+61 7 3397 0748",
    "sg:postcode":"4121",
    "sg:province":"QLD",
    "sg:tags":[
        "building",
        "designer"
    ],
    "wof:name":"Maclennan Darryl Domestic Design",
    "wof:placetype":"venue"
},
  "geometry": {"coordinates":[153.064163208,-27.5123252869],"type":"Point"}
}