{
  "type": "Feature",
  "properties": {
    "iso:country":"AU",
    "sg:address":"15 Silicon Pl",
    "sg:city":"Tullamarine",
    "sg:classifiers":[
        {
            "category":"Shopping",
            "subcategory":"Musical Instruments",
            "type":"Retail Goods"
        }
    ],
    "sg:phone":"+61 3 9335 6455",
    "sg:postcode":"3043",
    "sg:province":"VIC",
    "sg:tags":[
        "case"
    ],
    "wof:name":"Penn Fabrication Pty Ltd",
    "wof:placetype":"venue"
},
  "geometry": {"coordinates":[144.87461852999999,-37.7129173279],"type":"Point"}
}