{
  "type": "Feature",
  "properties": {
    "addr:full":"12 Unley Rd Unley SA 5061",
    "addr:housenumber":"12",
    "addr:postcode":"5061",
    "addr:street":"Unley Rd",
    "iso:country":"AU",
    "sg:address":"12 Unley Rd",
    "sg:city":"Unley",
    "sg:classifiers":[
        {
            "category":"Health Services",
            "subcategory":"Doctor",
            "type":"Services"
        }
    ],
    "sg:phone":"+61 8 8373 4165",
    "sg:postcode":"5061",
    "sg:province":"SA",
    "sg:tags":[
        "medical",
        "practitioner"
    ],
    "wof:name":"Cord-Udy N S Dr",
    "wof:placetype":"venue"
},
  "geometry": {"coordinates":[138.60664367699999,-34.9413948059],"type":"Point"}
}