{
  "type": "Feature",
  "properties": {
    "addr:full":"70 Macquoid St Queanbeyan NSW 2620",
    "addr:housenumber":"70",
    "addr:postcode":"2620",
    "addr:street":"Macquoid St",
    "iso:country":"AU",
    "sg:address":"70 Macquoid St",
    "sg:city":"Queanbeyan",
    "sg:classifiers":[
        {
            "category":"Building & Trades",
            "subcategory":"Construction",
            "type":"Services"
        }
    ],
    "sg:phone":"+61 2 6299 4566",
    "sg:postcode":"2620",
    "sg:province":"NSW",
    "sg:tags":[
        "contractor"
    ],
    "wof:name":"Professional Home Improvements Pty Ltd",
    "wof:placetype":"venue"
},
  "geometry": {"coordinates":[149.24249267600001,-35.3500976562],"type":"Point"}
}