{
  "type": "Feature",
  "properties": {
    "addr:full":"The Metro-- 260 Unley Rd Hyde Park SA 5061",
    "addr:housenumber":"260",
    "addr:postcode":"5061",
    "addr:street":"Unley Rd",
    "iso:country":"AU",
    "sg:address":"The Metro-- 260 Unley Rd",
    "sg:city":"Hyde Park",
    "sg:classifiers":[
        {
            "category":"Personal",
            "subcategory":"Beauty Salon",
            "type":"Services"
        }
    ],
    "sg:phone":"+61 8 8272 2720",
    "sg:postcode":"5061",
    "sg:province":"SA",
    "sg:tags":[
        "hairdresser"
    ],
    "wof:name":"Michael Agar Hair",
    "wof:placetype":"venue"
},
  "geometry": {"coordinates":[138.607620239,-34.9542427063],"type":"Point"}
}