{
  "type": "Feature",
  "properties": {
    "addr:full":"15 Doyle St Narrabri NSW 2390",
    "addr:housenumber":"15",
    "addr:postcode":"2390",
    "addr:street":"Doyle St",
    "iso:country":"AU",
    "sg:address":"15 Doyle St",
    "sg:city":"Narrabri",
    "sg:classifiers":[
        {
            "category":"Manufacturing",
            "subcategory":"Food",
            "type":"Manufacturing & Wholesale Goods"
        }
    ],
    "sg:phone":"+61 2 6792 4178",
    "sg:postcode":"2390",
    "sg:province":"NSW",
    "sg:tags":[
        "function",
        "catering"
    ],
    "wof:name":"Katrina O&#039;Brien",
    "wof:placetype":"venue"
},
  "geometry": {"coordinates":[149.78434753400001,-30.3240318298],"type":"Point"}
}