{
  "type": "Feature",
  "properties": {
    "addr:full":"Unit 2/ 25 Alison Rd Randwick NSW 2031",
    "addr:housenumber":"25",
    "addr:postcode":"2031",
    "addr:street":"Alison Rd",
    "iso:country":"AU",
    "sg:address":"Unit 2/ 25 Alison Rd",
    "sg:city":"Randwick",
    "sg:classifiers":[
        {
            "category":"Building & Trades",
            "subcategory":"Landscaping Services",
            "type":"Services"
        }
    ],
    "sg:phone":"+61 412 489 869",
    "sg:postcode":"2031",
    "sg:province":"NSW",
    "sg:tags":[
        "gardener"
    ],
    "wof:name":"Eastern Suburbs Garden Works",
    "wof:placetype":"venue"
},
  "geometry": {"coordinates":[151.22535705600001,-33.9037628174],"type":"Point"}
}