{
  "type": "Feature",
  "properties": {
    "iso:country":"AU",
    "sg:address":"126 Toongabbie Rd",
    "sg:city":"Toongabbie",
    "sg:classifiers":[
        {
            "category":"Manufacturing",
            "subcategory":"Glass & Minerals",
            "type":"Manufacturing & Wholesale Goods"
        }
    ],
    "sg:phone":"+61 401 620 210",
    "sg:postcode":"2146",
    "sg:province":"NSW",
    "sg:tags":[
        "merchant",
        "granite",
        "marble"
    ],
    "wof:name":"Modern Touch Marble & Granite",
    "wof:placetype":"venue"
},
  "geometry": {"coordinates":[150.94013977,-33.7937774658],"type":"Point"}
}