{
  "type": "Feature",
  "properties": {
    "addr:full":"140 - 142 Henry St Penrith NSW 2751",
    "addr:housenumber":"142",
    "addr:postcode":"2751",
    "addr:street":"Henry St",
    "iso:country":"AU",
    "sg:address":"140 - 142 Henry St",
    "sg:city":"Penrith",
    "sg:classifiers":[
        {
            "category":"Professional",
            "subcategory":"Computer Services",
            "type":"Services"
        }
    ],
    "sg:phone":"+61 2 4731 2046",
    "sg:postcode":"2751",
    "sg:province":"NSW",
    "sg:tags":[
        "training"
    ],
    "wof:name":"Master Computer Coaching",
    "wof:placetype":"venue"
},
  "geometry": {"coordinates":[150.69601440400001,-33.7440681458],"type":"Point"}
}