{
  "type": "Feature",
  "properties": {
    "addr:full":"Level 1/ 2 Rutherford Rds Seaford VIC 3198",
    "addr:housenumber":"/ 2",
    "addr:postcode":"3198",
    "addr:street":"Rutherford Rds",
    "iso:country":"AU",
    "sg:address":"Level 1/ 2 Rutherford Rds",
    "sg:city":"Seaford",
    "sg:classifiers":[
        {
            "category":"Real Estate",
            "subcategory":"Surveying",
            "type":"Services"
        }
    ],
    "sg:phone":"+61 3 9775 0871",
    "sg:postcode":"3198",
    "sg:province":"VIC",
    "sg:tags":[
        "building",
        "surveyor"
    ],
    "wof:name":"CH Group Pty Ltd",
    "wof:placetype":"venue"
},
  "geometry": {"coordinates":[145.151687622,-38.0990982056],"type":"Point"}
}