{
  "type": "Feature",
  "properties": {
    "addr:full":"5 Erringhi Pl McGraths Hill NSW 2756",
    "addr:housenumber":"5",
    "addr:postcode":"2756",
    "addr:street":"Erringhi Pl",
    "iso:country":"AU",
    "sg:address":"5 Erringhi Pl",
    "sg:city":"McGraths Hill",
    "sg:classifiers":[
        {
            "category":"Professional",
            "subcategory":"Art Services",
            "type":"Services"
        }
    ],
    "sg:phone":"+61 414 657 810",
    "sg:postcode":"2756",
    "sg:province":"NSW",
    "sg:tags":[
        "decorator",
        "painter"
    ],
    "wof:name":"Futi The Painter",
    "wof:placetype":"venue"
},
  "geometry": {"coordinates":[150.84121704099999,-33.6177978516],"type":"Point"}
}