{
  "type": "Feature",
  "properties": {
    "addr:full":"165-169 Cambridge St South Grafton NSW 2460",
    "addr:housenumber":"165-169",
    "addr:postcode":"2460",
    "addr:street":"Cambridge St",
    "iso:country":"AU",
    "sg:address":"165-169 Cambridge St",
    "sg:city":"South Grafton",
    "sg:classifiers":[
        {
            "category":"Home & Garden",
            "subcategory":"Garden Supply",
            "type":"Retail Goods"
        }
    ],
    "sg:phone":"+61 2 6642 6099",
    "sg:postcode":"2460",
    "sg:province":"NSW",
    "sg:tags":[
        "equipment"
    ],
    "wof:name":"Daisy Wheel Nursery",
    "wof:placetype":"venue"
},
  "geometry": {"coordinates":[152.931884766,-29.7119121552],"type":"Point"}
}