{
  "type": "Feature",
  "properties": {
    "addr:full":"142 Irvine Rd Gympie QLD 4570",
    "addr:housenumber":"142",
    "addr:postcode":"4570",
    "addr:street":"Irvine Rd",
    "iso:country":"AU",
    "sg:address":"142 Irvine Rd",
    "sg:city":"Gympie",
    "sg:classifiers":[
        {
            "category":"Cafe",
            "type":"Food & Drink"
        }
    ],
    "sg:phone":"+61 7 5482 2210",
    "sg:postcode":"4570",
    "sg:province":"QLD",
    "wof:name":"Highbury Mountain",
    "wof:placetype":"venue"
},
  "geometry": {"coordinates":[152.61639404300001,-26.1561641693],"type":"Point"}
}