{
  "type": "Feature",
  "properties": {
    "iso:country":"AU",
    "sg:address":"8 Young Crt",
    "sg:city":"Delahey",
    "sg:classifiers":[
        {
            "category":"Building & Trades",
            "subcategory":"Construction",
            "type":"Services"
        }
    ],
    "sg:phone":"+61 419 565 191",
    "sg:postcode":"3037",
    "sg:province":"VIC",
    "sg:tags":[
        "joiner",
        "carpenter"
    ],
    "wof:name":"Carpenter - Serge",
    "wof:placetype":"venue"
},
  "geometry": {"coordinates":[144.775803,-37.720715],"type":"Point"}
}