{
  "type": "Feature",
  "properties": {
    "iso:country":"AU",
    "sg:address":"Unit 27/ 7 Anella Ave",
    "sg:city":"Castle Hill",
    "sg:classifiers":[
        {
            "category":"Professional",
            "subcategory":"Engineering",
            "type":"Services"
        }
    ],
    "sg:phone":"+61 2 9894 1049",
    "sg:postcode":"2154",
    "sg:province":"NSW",
    "sg:tags":[
        "electronic",
        "engineer"
    ],
    "wof:name":"Barnes Electronics",
    "wof:placetype":"venue"
},
  "geometry": {"coordinates":[151.001052856,-33.7178192139],"type":"Point"}
}