{
  "type": "Feature",
  "properties": {
    "addr:full":"Head Office Lvl 1/ 269 Glenferrie Rd Malvern VIC 3144",
    "addr:housenumber":"/ 269",
    "addr:postcode":"3144",
    "addr:street":"Glenferrie Rd",
    "iso:country":"AU",
    "sg:address":"Head Office Lvl 1/ 269 Glenferrie Rd",
    "sg:city":"Malvern",
    "sg:classifiers":[
        {
            "category":"Health Services",
            "subcategory":"Doctor",
            "type":"Services"
        }
    ],
    "sg:phone":"+61 3 9500 9088",
    "sg:postcode":"3144",
    "sg:province":"VIC",
    "sg:tags":[
        "occupational",
        "safety"
    ],
    "wof:name":"Health By Design",
    "wof:placetype":"venue"
},
  "geometry": {"coordinates":[145.029022217,-37.8572311401],"type":"Point"}
}