{
  "type": "Feature",
  "properties": {
    "iso:country":"AU",
    "sg:address":"89 King St",
    "sg:city":"Clifton",
    "sg:classifiers":[
        {
            "category":"Real Estate",
            "subcategory":"Real Estate Agent",
            "type":"Services"
        }
    ],
    "sg:phone":"+61 427 659 189",
    "sg:postcode":"4361",
    "sg:province":"QLD",
    "wof:name":"Harcourts Rural Clifton",
    "wof:placetype":"venue"
},
  "geometry": {"coordinates":[151.90609741200001,-27.9324932098],"type":"Point"}
}