{
  "type": "Feature",
  "properties": {
    "iso:country":"AU",
    "sg:address":"New England Hwy",
    "sg:city":"Applethorpe",
    "sg:classifiers":[
        {
            "category":"Professional",
            "subcategory":"Accounting & Tax Preparation",
            "type":"Services"
        }
    ],
    "sg:phone":"+61 7 4683 2483",
    "sg:postcode":"4378",
    "sg:province":"QLD",
    "sg:tags":[
        "consultant",
        "taxation"
    ],
    "wof:name":"United Tax & Accounting",
    "wof:placetype":"venue"
},
  "geometry": {"coordinates":[151.955535889,-28.6184406281],"type":"Point"}
}