{
  "type": "Feature",
  "properties": {
    "iso:country":"AU",
    "sg:address":"Unit 3/ 41-43 Higginbotham Rd",
    "sg:city":"Gladesville",
    "sg:classifiers":[
        {
            "category":"Home & Garden",
            "subcategory":"Building Materials",
            "type":"Retail Goods"
        }
    ],
    "sg:phone":"+61 2 9809 1378",
    "sg:postcode":"2111",
    "sg:province":"NSW",
    "sg:tags":[
        "plaster",
        "plasterboard",
        "supply"
    ],
    "wof:name":"Plaster Vent Works",
    "wof:placetype":"venue"
},
  "geometry": {"coordinates":[151.12319946299999,-33.8159255981],"type":"Point"}
}