{
  "type": "Feature",
  "properties": {
    "iso:country":"AU",
    "sg:address":"1 Drummond St",
    "sg:city":"Carlton",
    "sg:classifiers":[
        {
            "category":"Health Services",
            "subcategory":"Health Practitioner",
            "type":"Services"
        }
    ],
    "sg:phone":"+61 3 9383 4171",
    "sg:postcode":"3053",
    "sg:province":"VIC",
    "sg:tags":[
        "psychologist"
    ],
    "wof:name":"Brink Vanda Dr",
    "wof:placetype":"venue"
},
  "geometry": {"coordinates":[144.967163086,-37.8070335388],"type":"Point"}
}