{
  "type": "Feature",
  "properties": {
    "addr:full":"Shop 27 Marina Mirage Port Douglas QLD 4877",
    "addr:housenumber":"shop 27",
    "addr:postcode":"4877",
    "iso:country":"AU",
    "sg:address":"Shop 27 Marina Mirage",
    "sg:city":"Port Douglas",
    "sg:classifiers":[
        {
            "category":"Personal",
            "type":"Services"
        }
    ],
    "sg:phone":"+61 7 4099 4868",
    "sg:postcode":"4877",
    "sg:province":"QLD",
    "sg:tags":[
        "gift"
    ],
    "wof:name":"Maggie's Total Gift Solutions",
    "wof:placetype":"venue"
},
  "geometry": {"coordinates":[145.46543884299999,-16.4844493866],"type":"Point"}
}