{
  "type": "Feature",
  "properties": {
    "addr:full":"46 Crimea St Parramatta NSW 2150",
    "addr:housenumber":"46",
    "addr:postcode":"2150",
    "addr:street":"Crimea St",
    "iso:country":"AU",
    "sg:address":"46 Crimea St",
    "sg:city":"Parramatta",
    "sg:classifiers":[
        {
            "category":"Food & Beverages",
            "subcategory":"Groceries & Convenience Stores",
            "type":"Retail Goods"
        }
    ],
    "sg:phone":"+61 2 9633 1650",
    "sg:postcode":"2150",
    "sg:province":"NSW",
    "wof:name":"D & N Mixed Business",
    "wof:placetype":"venue"
},
  "geometry": {"coordinates":[150.99342346200001,-33.8229751587],"type":"Point"}
}