{
  "type": "Feature",
  "properties": {
    "addr:full":"Shop 6 Philip Centre Boree St Ulladulla NSW 2539",
    "addr:housenumber":"shop 6",
    "addr:postcode":"2539",
    "addr:street":"Philip Centre Boree St",
    "iso:country":"AU",
    "sg:address":"Shop 6 Philip Centre Boree St",
    "sg:city":"Ulladulla",
    "sg:classifiers":[
        {
            "category":"Health Services",
            "subcategory":"Health Practitioner",
            "type":"Services"
        }
    ],
    "sg:phone":"+61 2 4455 1212",
    "sg:postcode":"2539",
    "sg:province":"NSW",
    "sg:tags":[
        "osteopath"
    ],
    "wof:name":"Ulladulla Chiropractic & Osteopathic Centre",
    "wof:placetype":"venue"
},
  "geometry": {"coordinates":[150.472747803,-35.3585700989],"type":"Point"}
}