{
  "type": "Feature",
  "properties": {
    "iso:country":"AU",
    "sg:address":"36 Kerferd St",
    "sg:city":"Malvern East",
    "sg:classifiers":[
        {
            "category":"Banks & Credit Unions",
            "subcategory":"Financial Services",
            "type":"Services"
        }
    ],
    "sg:phone":"+61 3 9500 1079",
    "sg:postcode":"3145",
    "sg:province":"VIC",
    "sg:tags":[
        "planning"
    ],
    "sg:website":"http://www.fpa.asn.au",
    "wof:name":"Aussie Financial Management",
    "wof:placetype":"venue"
},
  "geometry": {"coordinates":[145.044189453,-37.8694267273],"type":"Point"}
}