{
  "type": "Feature",
  "properties": {
    "addr:full":"221 Ross River Rd Aitkenvale QLD 4814",
    "addr:housenumber":"221",
    "addr:postcode":"4814",
    "addr:street":"Ross River Rd",
    "iso:country":"AU",
    "sg:address":"221 Ross River Rd",
    "sg:city":"Aitkenvale",
    "sg:classifiers":[
        {
            "category":"Health Services",
            "subcategory":"Chiropractor",
            "type":"Services"
        }
    ],
    "sg:phone":"+61 7 4779 8245",
    "sg:postcode":"4814",
    "sg:province":"QLD",
    "wof:name":"Penrose Mark J Dr",
    "wof:placetype":"venue"
},
  "geometry": {"coordinates":[146.77363600000001,-19.29631],"type":"Point"}
}