{
  "type": "Feature",
  "properties": {
    "iso:country":"AU",
    "sg:address":"48 George St",
    "sg:city":"Mackay",
    "sg:classifiers":[
        {
            "category":"Building & Trades",
            "subcategory":"Construction",
            "type":"Services"
        }
    ],
    "sg:phone":"+61 7 4957 4747",
    "sg:postcode":"4740",
    "sg:province":"QLD",
    "sg:tags":[
        "contractor"
    ],
    "wof:name":"Ricciardi Builders",
    "wof:placetype":"venue"
},
  "geometry": {"coordinates":[149.178543,-21.150232],"type":"Point"}
}