{
  "type": "Feature",
  "properties": {
    "addr:full":"Unit 2/ 32 Pope St Beverley SA 5009",
    "addr:housenumber":"32",
    "addr:postcode":"5009",
    "addr:street":"Pope St",
    "iso:country":"AU",
    "sg:address":"Unit 2/ 32 Pope St",
    "sg:city":"Beverley",
    "sg:classifiers":[
        {
            "category":"Building & Trades",
            "subcategory":"Cleaning & Sanitation",
            "type":"Services"
        }
    ],
    "sg:phone":"+61 8 8244 1900",
    "sg:postcode":"5009",
    "sg:province":"SA",
    "sg:tags":[
        "industrial",
        "commercial",
        "contractor"
    ],
    "wof:name":"Exact Cleaning & Maintenance Services",
    "wof:placetype":"venue"
},
  "geometry": {"coordinates":[138.544464111,-34.8899345398],"type":"Point"}
}