{
  "type": "Feature",
  "properties": {
    "iso:country":"AU",
    "sg:address":"Suite 5, 266 Campbell Pde",
    "sg:city":"Bondi",
    "sg:classifiers":[
        {
            "category":"Utilities",
            "subcategory":"Telephone",
            "type":"Services"
        }
    ],
    "sg:phone":"+61 2 9365 1008",
    "sg:postcode":"2026",
    "sg:province":"NSW",
    "sg:tags":[
        "equipment",
        "system"
    ],
    "wof:name":"Krack Solutions",
    "wof:placetype":"venue"
},
  "geometry": {"coordinates":[151.28195190400001,-33.889591217],"type":"Point"}
}