{
  "type": "Feature",
  "properties": {
    "iso:country":"AU",
    "sg:address":"Hamilton Pl",
    "sg:city":"Mt Waverley",
    "sg:classifiers":[
        {
            "category":"Banks & Credit Unions",
            "subcategory":"Financial Services",
            "type":"Services"
        }
    ],
    "sg:phone":"+61 411 474 441",
    "sg:postcode":"3149",
    "sg:province":"VIC",
    "sg:tags":[
        "franchising"
    ],
    "wof:name":"open2view.com.au",
    "wof:placetype":"venue"
},
  "geometry": {"coordinates":[145.128143311,-37.8769721985],"type":"Point"}
}