{
  "type": "Feature",
  "properties": {
    "iso:country":"AU",
    "sg:address":"248 Merrylands Rd",
    "sg:city":"Merrylands",
    "sg:classifiers":[
        {
            "category":"Personal",
            "subcategory":"Beauty Salon",
            "type":"Services"
        }
    ],
    "sg:phone":"+61 2 9682 3113",
    "sg:postcode":"2160",
    "sg:province":"NSW",
    "wof:name":"Luscious Beauty",
    "wof:placetype":"venue"
},
  "geometry": {"coordinates":[150.98776245100001,-33.8361854553],"type":"Point"}
}