{
  "type": "Feature",
  "properties": {
    "iso:country":"AU",
    "sg:address":"PO Box 463",
    "sg:city":"Jurien Bay",
    "sg:classifiers":[
        {
            "category":"Wholesale",
            "subcategory":"Farm Supplies",
            "type":"Manufacturing & Wholesale Goods"
        }
    ],
    "sg:phone":"+61 8 9652 1272",
    "sg:postcode":"6516",
    "sg:province":"WA",
    "sg:tags":[
        "feed",
        "supplement",
        "stock"
    ],
    "wof:name":"Haggarty Nominees",
    "wof:placetype":"venue"
},
  "geometry": {"coordinates":[115.043266,-30.302891],"type":"Point"}
}