{
  "type": "Feature",
  "properties": {
    "addr:full":"40 Barwell Ave Barmera SA 5345",
    "addr:housenumber":"40",
    "addr:postcode":"5345",
    "addr:street":"Barwell Ave",
    "iso:country":"AU",
    "sg:address":"40 Barwell Ave",
    "sg:city":"Barmera",
    "sg:classifiers":[
        {
            "category":"Shopping",
            "subcategory":"Shoes",
            "type":"Retail Goods"
        }
    ],
    "sg:phone":"+61 8 8588 2455",
    "sg:postcode":"5345",
    "sg:province":"SA",
    "sg:tags":[
        "footwear"
    ],
    "wof:name":"Country Shoe Box The",
    "wof:placetype":"venue"
},
  "geometry": {"coordinates":[140.46470642099999,-34.2516441345],"type":"Point"}
}