{
  "type": "Feature",
  "properties": {
    "addr:full":"PO Box 1500 Shepparton VIC 3631",
    "addr:postcode":"3631",
    "iso:country":"AU",
    "sg:address":"PO Box 1500",
    "sg:city":"Shepparton",
    "sg:classifiers":[
        {
            "category":"Professional",
            "subcategory":"Lawyer & Legal Services",
            "type":"Services"
        }
    ],
    "sg:phone":"+61 3 5821 5833",
    "sg:postcode":"3631",
    "sg:province":"VIC",
    "sg:tags":[
        "process",
        "server"
    ],
    "wof:name":"Ausway Process Pty Ltd",
    "wof:placetype":"venue"
},
  "geometry": {"coordinates":[145.40174865700001,-36.381401062],"type":"Point"}
}