{
  "type": "Feature",
  "properties": {
    "addr:full":"13 Rose St Bridgetown WA 6255",
    "addr:housenumber":"13",
    "addr:postcode":"6255",
    "addr:street":"Rose St",
    "iso:country":"AU",
    "sg:address":"13 Rose St",
    "sg:city":"Bridgetown",
    "sg:classifiers":[
        {
            "category":"Home & Garden",
            "subcategory":"Building Materials",
            "type":"Retail Goods"
        }
    ],
    "sg:phone":"+61 8 9761 4711",
    "sg:postcode":"6255",
    "sg:province":"WA",
    "sg:tags":[
        "merchant",
        "glass",
        "glazier"
    ],
    "wof:name":"Bridgetown Glass Service",
    "wof:placetype":"venue"
},
  "geometry": {"coordinates":[116.139198303,-33.9571990967],"type":"Point"}
}