{
  "type": "Feature",
  "properties": {
    "iso:country":"AU",
    "sg:address":"6 Bellevue St",
    "sg:city":"Maroubra",
    "sg:classifiers":[
        {
            "category":"Professional",
            "subcategory":"Art Services",
            "type":"Services"
        }
    ],
    "sg:phone":"+61 2 9344 4637",
    "sg:postcode":"2035",
    "sg:province":"NSW",
    "sg:tags":[
        "interior",
        "decorator"
    ],
    "wof:name":"Colourworks Studio Of Interior Design",
    "wof:placetype":"venue"
},
  "geometry": {"coordinates":[151.258575439,-33.9421043396],"type":"Point"}
}