{
  "type": "Feature",
  "properties": {
    "addr:full":"15 Byron Bay Rd Bangalow NSW 2479",
    "addr:housenumber":"15",
    "addr:postcode":"2479",
    "addr:street":"Byron Bay Rd",
    "iso:country":"AU",
    "sg:address":"15 Byron Bay Rd",
    "sg:city":"Bangalow",
    "sg:classifiers":[
        {
            "category":"Building & Trades",
            "subcategory":"Construction",
            "type":"Services"
        }
    ],
    "sg:phone":"+61 2 6687 1758",
    "sg:postcode":"2479",
    "sg:province":"NSW",
    "sg:tags":[
        "contractor"
    ],
    "wof:name":"RM Crouch Building Pty Ltd",
    "wof:placetype":"venue"
},
  "geometry": {"coordinates":[153.52984619099999,-28.6843967438],"type":"Point"}
}