{
  "type": "Feature",
  "properties": {
    "addr:full":"19 Dorset St Brahma Lodge SA 5109",
    "addr:housenumber":"19",
    "addr:postcode":"5109",
    "addr:street":"Dorset St",
    "iso:country":"AU",
    "sg:address":"19 Dorset St",
    "sg:city":"Brahma Lodge",
    "sg:classifiers":[
        {
            "category":"Travel",
            "subcategory":"Resort",
            "type":"Entertainment"
        }
    ],
    "sg:phone":"+61 8 8258 5033",
    "sg:postcode":"5109",
    "sg:province":"SA",
    "sg:tags":[
        "club",
        "caravan"
    ],
    "wof:name":"Elizabethan Caravan Club Inc",
    "wof:placetype":"venue"
},
  "geometry": {"coordinates":[138.651885986,-34.7732925415],"type":"Point"}
}