{
  "type": "Feature",
  "properties": {
    "addr:full":"PO Box 341 Jamison Centre ACT 2614",
    "addr:postcode":"2614",
    "iso:country":"AU",
    "sg:address":"PO Box 341",
    "sg:city":"Jamison Centre",
    "sg:classifiers":[
        {
            "category":"Coffee & Tea",
            "type":"Food & Drink"
        }
    ],
    "sg:phone":"+61 2 6288 6799",
    "sg:postcode":"2614",
    "sg:province":"ACT",
    "sg:tags":[
        "kayak",
        "canoe"
    ],
    "wof:name":"Burley Griffin Canoe Club",
    "wof:placetype":"venue"
},
  "geometry": {"coordinates":[149.05946350100001,-35.2556686401],"type":"Point"}
}