{
  "type": "Feature",
  "properties": {
    "iso:country":"AU",
    "sg:address":"Clifford Gardens Shopping Centre+ Cnr James & Anza",
    "sg:city":"Toowoomba",
    "sg:classifiers":[
        {
            "category":"Government",
            "subcategory":"Post Office",
            "type":"Public Place"
        }
    ],
    "sg:phone":"+61 13 13 18",
    "sg:postcode":"4350",
    "sg:province":"QLD",
    "sg:tags":[
        "postal"
    ],
    "wof:name":"Australia Post",
    "wof:placetype":"venue"
},
  "geometry": {"coordinates":[151.92172199999999,-27.577253],"type":"Point"}
}