{
  "type": "Feature",
  "properties": {
    "iso:country":"AU",
    "sg:address":"223 Abbotsford St",
    "sg:city":"North Melbourne",
    "sg:classifiers":[
        {
            "category":"Real Estate",
            "subcategory":"Architect",
            "type":"Services"
        }
    ],
    "sg:phone":"+61 3 9328 3500",
    "sg:postcode":"3051",
    "sg:province":"VIC",
    "wof:name":"Meldrum Architecture",
    "wof:placetype":"venue"
},
  "geometry": {"coordinates":[144.94541931099999,-37.8022232056],"type":"Point"}
}