{
  "type": "Feature",
  "properties": {
    "iso:country":"AU",
    "sg:address":"Level 7 70 Phillip St",
    "sg:city":"Sydney",
    "sg:classifiers":[
        {
            "category":"Insurance",
            "subcategory":"Title Insurance",
            "type":"Services"
        }
    ],
    "sg:phone":"+61 2 9251 6911",
    "sg:postcode":"2000",
    "sg:province":"NSW",
    "sg:tags":[
        "reinsurance"
    ],
    "wof:name":"Hannover Life Re of Australasia Ltd",
    "wof:placetype":"venue"
},
  "geometry": {"coordinates":[151.21188354500001,-33.8642272949],"type":"Point"}
}