{
  "type": "Feature",
  "properties": {
    "iso:country":"AU",
    "sg:address":"5 Peel St",
    "sg:city":"Holroyd",
    "sg:classifiers":[
        {
            "category":"Retail",
            "subcategory":"Auto Repair",
            "type":"Services"
        }
    ],
    "sg:phone":"+61 2 9637 1973",
    "sg:postcode":"2145",
    "sg:province":"NSW",
    "sg:tags":[
        "repairer",
        "motor",
        "engineer"
    ],
    "wof:name":"Craft Differentials",
    "wof:placetype":"venue"
},
  "geometry": {"coordinates":[150.997924805,-33.8305931091],"type":"Point"}
}