{
  "type": "Feature",
  "properties": {
    "addr:full":"Cnr Ferguson St & Albany Creek Rd Albany Creek QLD 4035",
    "addr:postcode":"4035",
    "addr:street":"Cnr Ferguson St & Albany Creek Rd",
    "iso:country":"AU",
    "sg:address":"Cnr Ferguson St & Albany Creek Rd",
    "sg:city":"Albany Creek",
    "sg:classifiers":[
        {
            "category":"Cafe",
            "type":"Food & Drink"
        }
    ],
    "sg:phone":"+61 7 3325 3020",
    "sg:postcode":"4035",
    "sg:province":"QLD",
    "wof:name":"Coffee Club The",
    "wof:placetype":"venue"
},
  "geometry": {"coordinates":[152.968414,-27.34544],"type":"Point"}
}