{
  "type": "Feature",
  "properties": {
    "addr:full":"1 Clifton Crt Portland VIC 3305",
    "addr:housenumber":"1",
    "addr:postcode":"3305",
    "addr:street":"Clifton Crt",
    "iso:country":"AU",
    "sg:address":"1 Clifton Crt",
    "sg:city":"Portland",
    "sg:classifiers":[
        {
            "category":"Building & Trades",
            "subcategory":"Construction",
            "type":"Services"
        }
    ],
    "sg:phone":"+61 3 5523 1027",
    "sg:postcode":"3305",
    "sg:province":"VIC",
    "sg:tags":[
        "fencing",
        "contractor"
    ],
    "wof:name":"Malseed N Bruce & B L",
    "wof:placetype":"venue"
},
  "geometry": {"coordinates":[141.60821533199999,-38.3351745605],"type":"Point"}
}