{
  "type": "Feature",
  "properties": {
    "iso:country":"AU",
    "sg:address":"Gilpin St",
    "sg:city":"Esperance",
    "sg:classifiers":[
        {
            "category":"Government",
            "subcategory":"Post Office",
            "type":"Public Place"
        }
    ],
    "sg:phone":"+61 8 9071 5850",
    "sg:postcode":"6450",
    "sg:province":"WA",
    "sg:tags":[
        "silo"
    ],
    "wof:name":"Parker Silos & Sheet Metal",
    "wof:placetype":"venue"
},
  "geometry": {"coordinates":[121.887710571,-33.8405265808],"type":"Point"}
}