{
  "type": "Feature",
  "properties": {
    "addr:full":"Shop 6 48-49 Forrest St Collie WA 6225",
    "addr:housenumber":"shop 6 48-49",
    "addr:postcode":"6225",
    "addr:street":"Forrest St",
    "iso:country":"AU",
    "sg:address":"Shop 6 48-49 Forrest St",
    "sg:city":"Collie",
    "sg:classifiers":[
        {
            "category":"Banks & Credit Unions",
            "subcategory":"Bank",
            "type":"Services"
        }
    ],
    "sg:phone":"+61 13 20 32",
    "sg:postcode":"6225",
    "sg:province":"WA",
    "wof:name":"Westpac",
    "wof:placetype":"venue"
},
  "geometry": {"coordinates":[116.154617,-33.358883],"type":"Point"}
}