{
  "type": "Feature",
  "properties": {
    "addr:full":"Quondong Rd Grenfell NSW 2810",
    "addr:postcode":"2810",
    "addr:street":"Quondong Rd",
    "iso:country":"AU",
    "sg:address":"Quondong Rd",
    "sg:city":"Grenfell",
    "sg:classifiers":[
        {
            "category":"Building & Trades",
            "subcategory":"Construction",
            "type":"Services"
        }
    ],
    "sg:phone":"+61 2 6343 1477",
    "sg:postcode":"2810",
    "sg:province":"NSW",
    "sg:tags":[
        "contractor"
    ],
    "wof:name":"Nealon R.A.",
    "wof:placetype":"venue"
},
  "geometry": {"coordinates":[148.170776367,-33.9017372131],"type":"Point"}
}