{
  "type": "Feature",
  "properties": {
    "addr:full":"166 Fryar Rd Eagleby QLD 4207",
    "addr:housenumber":"166",
    "addr:postcode":"4207",
    "addr:street":"Fryar Rd",
    "iso:country":"AU",
    "sg:address":"166 Fryar Rd",
    "sg:city":"Eagleby",
    "sg:classifiers":[
        {
            "category":"Travel",
            "subcategory":"Hotels & Motels",
            "type":"Entertainment"
        }
    ],
    "sg:phone":"+61 7 3382 0149",
    "sg:postcode":"4207",
    "sg:province":"QLD",
    "sg:tags":[
        "accommodation"
    ],
    "wof:name":"Eagle Tavern",
    "wof:placetype":"venue"
},
  "geometry": {"coordinates":[153.213348389,-27.7000427246],"type":"Point"}
}