{
  "type": "Feature",
  "properties": {
    "addr:full":"102 Spring St Arncliffe NSW 2205",
    "addr:housenumber":"102",
    "addr:postcode":"2205",
    "addr:street":"Spring St",
    "iso:country":"AU",
    "sg:address":"102 Spring St",
    "sg:city":"Arncliffe",
    "sg:classifiers":[
        {
            "category":"Building & Trades",
            "subcategory":"Construction",
            "type":"Services"
        }
    ],
    "sg:phone":"+61 2 4294 9911",
    "sg:postcode":"2205",
    "sg:province":"NSW",
    "sg:tags":[
        "scaffolding"
    ],
    "wof:name":"Donerite Scaffolding & Rigging Pty Ltd",
    "wof:placetype":"venue"
},
  "geometry": {"coordinates":[151.149216,-33.944508],"type":"Point"}
}