{
  "type": "Feature",
  "properties": {
    "iso:country":"AU",
    "sg:address":"80 Talbragar St",
    "sg:city":"Dubbo",
    "sg:classifiers":[
        {
            "category":"Cafe",
            "type":"Food & Drink"
        }
    ],
    "sg:phone":"+61 2 6884 9993",
    "sg:postcode":"2830",
    "sg:province":"NSW",
    "wof:name":"The Biker",
    "wof:placetype":"venue"
},
  "geometry": {"coordinates":[148.60409545900001,-32.2449607849],"type":"Point"}
}