{
  "type": "Feature",
  "properties": {
    "iso:country":"AU",
    "sg:address":"Queen St",
    "sg:city":"Yeppoon",
    "sg:classifiers":[
        {
            "category":"Education",
            "subcategory":"School",
            "type":"Public Place"
        }
    ],
    "sg:phone":"+61 7 4939 9600",
    "sg:postcode":"4703",
    "sg:province":"QLD",
    "sg:tags":[
        "girl"
    ],
    "wof:name":"St Ursula's",
    "wof:placetype":"venue"
},
  "geometry": {"coordinates":[150.74627685600001,-23.1301231384],"type":"Point"}
}