{
  "type": "Feature",
  "properties": {
    "addr:full":"51 Tweed Coast Rd Cabarita Beach NSW 2488",
    "addr:housenumber":"51",
    "addr:postcode":"2488",
    "addr:street":"Tweed Coast Rd",
    "iso:country":"AU",
    "sg:address":"51 Tweed Coast Rd",
    "sg:city":"Cabarita Beach",
    "sg:classifiers":[
        {
            "category":"Health Services",
            "subcategory":"Health Practitioner",
            "type":"Services"
        }
    ],
    "sg:phone":"+61 2 6676 4577",
    "sg:postcode":"2488",
    "sg:province":"NSW",
    "sg:tags":[
        "physiotherapist"
    ],
    "wof:name":"Cabarita Beach Physiotherapy and Sports Injury Centre",
    "wof:placetype":"venue"
},
  "geometry": {"coordinates":[153.56611599999999,-28.335567],"type":"Point"}
}