{
  "type": "Feature",
  "properties": {
    "addr:full":"Shop 30 Bullcreek Shopping Centre Bullcreek WA 6149",
    "addr:housenumber":"shop 30",
    "addr:postcode":"6149",
    "addr:street":"Bullcreek",
    "iso:country":"AU",
    "sg:address":"Shop 30 Bullcreek Shopping Centre",
    "sg:city":"Bullcreek",
    "sg:classifiers":[
        {
            "category":"Shopping",
            "subcategory":"Mobile Phones",
            "type":"Retail Goods"
        }
    ],
    "sg:phone":"+61 8 9332 0288",
    "sg:postcode":"6149",
    "sg:province":"WA",
    "sg:tags":[
        "telephone",
        "accessory"
    ],
    "wof:name":"TELSTRA",
    "wof:placetype":"venue"
},
  "geometry": {"coordinates":[115.87059000000001,-32.066471],"type":"Point"}
}