{
  "type": "Feature",
  "properties": {
    "iso:country":"AU",
    "sg:address":"504 Princes Hwy",
    "sg:city":"Noble Park",
    "sg:classifiers":[
        {
            "category":"Shopping",
            "subcategory":"News",
            "type":"Retail Goods"
        }
    ],
    "sg:phone":"+61 3 9213 3111",
    "sg:postcode":"3174",
    "sg:province":"VIC",
    "sg:tags":[
        "magazine",
        "periodical"
    ],
    "wof:name":"Hannanprint Victoria",
    "wof:placetype":"venue"
},
  "geometry": {"coordinates":[145.18107605,-37.954460144],"type":"Point"}
}