{
  "type": "Feature",
  "properties": {
    "addr:full":"28 Saunders St North Beach WA 6020",
    "addr:housenumber":"28",
    "addr:postcode":"6020",
    "addr:street":"Saunders St",
    "iso:country":"AU",
    "sg:address":"28 Saunders St",
    "sg:city":"North Beach",
    "sg:classifiers":[
        {
            "category":"Building & Trades",
            "subcategory":"Equipment Rental",
            "type":"Services"
        }
    ],
    "sg:phone":"+61 8 9448 7564",
    "sg:postcode":"6020",
    "sg:province":"WA",
    "sg:tags":[
        "supply",
        "catering"
    ],
    "wof:name":"Coastal Commercial Kitchen Services",
    "wof:placetype":"venue"
},
  "geometry": {"coordinates":[115.755569458,-31.8655357361],"type":"Point"}
}