{
  "type": "Feature",
  "properties": {
    "addr:full":"Olympic Hwy Young NSW 2594",
    "addr:postcode":"2594",
    "addr:street":"Olympic Hwy",
    "iso:country":"AU",
    "sg:address":"Olympic Hwy",
    "sg:city":"Young",
    "sg:classifiers":[
        {
            "category":"Building & Trades",
            "subcategory":"Construction",
            "type":"Services"
        }
    ],
    "sg:phone":"+61 2 6382 2196",
    "sg:postcode":"2594",
    "sg:province":"NSW",
    "sg:tags":[
        "bitumen",
        "paving",
        "asphalt"
    ],
    "wof:name":"Southern Asphalters Pty Ltd",
    "wof:placetype":"venue"
},
  "geometry": {"coordinates":[148.29432678200001,-34.3139953613],"type":"Point"}
}