{
  "type": "Feature",
  "properties": {
    "iso:country":"AU",
    "sg:address":"The Galleria, off Walter Rd",
    "sg:city":"Morley",
    "sg:classifiers":[
        {
            "category":"Fast Food",
            "type":"Food & Drink"
        }
    ],
    "sg:phone":"+61 8 9275 8777",
    "sg:postcode":"6062",
    "sg:province":"WA",
    "sg:tags":[
        "away",
        "take"
    ],
    "wof:name":"Fast Eddys Cafe",
    "wof:placetype":"venue"
},
  "geometry": {"coordinates":[115.896888733,-31.8942699432],"type":"Point"}
}