{
  "type": "Feature",
  "properties": {
    "addr:full":"221 Logan Rd Buranda QLD 4102",
    "addr:housenumber":"221",
    "addr:postcode":"4102",
    "addr:street":"Logan Rd",
    "iso:country":"AU",
    "sg:address":"221 Logan Rd",
    "sg:city":"Buranda",
    "sg:classifiers":[
        {
            "category":"Professional",
            "subcategory":"Accounting & Tax Preparation",
            "type":"Services"
        }
    ],
    "sg:phone":"+61 7 3891 0500",
    "sg:postcode":"4102",
    "sg:province":"QLD",
    "sg:tags":[
        "deduction",
        "payroll"
    ],
    "wof:name":"ADP Employer Systems",
    "wof:placetype":"venue"
},
  "geometry": {"coordinates":[153.04197692899999,-27.4976139069],"type":"Point"}
}