{
  "type": "Feature",
  "properties": {
    "addr:full":"540 Brunswick St New Farm QLD 4005",
    "addr:housenumber":"540",
    "addr:postcode":"4005",
    "addr:street":"Brunswick St",
    "iso:country":"AU",
    "sg:address":"540 Brunswick St",
    "sg:city":"New Farm",
    "sg:classifiers":[
        {
            "category":"Retail",
            "subcategory":"Laundry & Dry Cleaning",
            "type":"Services"
        }
    ],
    "sg:phone":"+61 7 3254 3699",
    "sg:postcode":"4005",
    "sg:province":"QLD",
    "wof:name":"New Farm Laundry Mat",
    "wof:placetype":"venue"
},
  "geometry": {"coordinates":[153.03929138199999,-27.4616088867],"type":"Point"}
}