{
  "type": "Feature",
  "properties": {
    "addr:full":"412 Waverley Rd Malvern East VIC 3145",
    "addr:housenumber":"412",
    "addr:postcode":"3145",
    "addr:street":"Waverley Rd",
    "iso:country":"AU",
    "sg:address":"412 Waverley Rd",
    "sg:city":"Malvern East",
    "sg:classifiers":[
        {
            "category":"Social Services",
            "subcategory":"Child Care",
            "type":"Services"
        }
    ],
    "sg:phone":"+61 3 9572 3838",
    "sg:postcode":"3145",
    "sg:province":"VIC",
    "wof:name":"Little Paddington Early Learning Centre",
    "wof:placetype":"venue"
},
  "geometry": {"coordinates":[145.06515502900001,-37.8781547546],"type":"Point"}
}