{
  "type": "Feature",
  "properties": {
    "addr:full":"Cnr Esplanade & Upward Sts Cairns QLD 4870",
    "addr:postcode":"4870",
    "addr:street":"Cnr Esplanade & Upward Sts",
    "iso:country":"AU",
    "sg:address":"Cnr Esplanade & Upward Sts",
    "sg:city":"Cairns",
    "sg:classifiers":[
        {
            "category":"Arena",
            "subcategory":"Sports Club",
            "type":"Entertainment"
        }
    ],
    "sg:phone":"+61 417 109 071",
    "sg:postcode":"4870",
    "sg:province":"QLD",
    "sg:tags":[
        "defence",
        "supply",
        "self",
        "instruction",
        "martial art"
    ],
    "wof:name":"Ueda Dojo",
    "wof:placetype":"venue"
},
  "geometry": {"coordinates":[145.784057617,-16.939289093],"type":"Point"}
}