{
  "type": "Feature",
  "properties": {
    "addr:full":"1334 Mount Rd Highclere TAS 7321",
    "addr:housenumber":"1334",
    "addr:postcode":"7321",
    "addr:street":"Mount Rd",
    "iso:country":"AU",
    "sg:address":"1334 Mount Rd",
    "sg:city":"Highclere",
    "sg:classifiers":[
        {
            "category":"Building & Trades",
            "subcategory":"Construction",
            "type":"Services"
        }
    ],
    "sg:phone":"+61 3 6435 7372",
    "sg:postcode":"7321",
    "sg:province":"TAS",
    "sg:tags":[
        "earth",
        "excavating",
        "moving",
        "contractor"
    ],
    "wof:name":"Leon & Christine Russell",
    "wof:placetype":"venue"
},
  "geometry": {"coordinates":[145.89205899999999,-41.089214],"type":"Point"}
}