{
  "type": "Feature",
  "properties": {
    "addr:full":"54 Malvern St Bayswater VIC 3153",
    "addr:housenumber":"54",
    "addr:postcode":"3153",
    "addr:street":"Malvern St",
    "iso:country":"AU",
    "sg:address":"54 Malvern St",
    "sg:city":"Bayswater",
    "sg:classifiers":[
        {
            "category":"Autos & Motor Vehicles",
            "subcategory":"Boat Sales",
            "type":"Retail Goods"
        }
    ],
    "sg:phone":"+61 3 9720 1544",
    "sg:postcode":"3153",
    "sg:province":"VIC",
    "sg:tags":[
        "equipment",
        "yacht"
    ],
    "sg:website":"http://www.propshopmarine.com.au",
    "wof:name":"Prop Shop Marine",
    "wof:placetype":"venue"
},
  "geometry": {"coordinates":[145.27749633799999,-37.84375],"type":"Point"}
}