{
  "type": "Feature",
  "properties": {
    "iso:country":"AU",
    "sg:address":"390 Shute Harbour Rd",
    "sg:city":"Airlie Beach",
    "sg:classifiers":[
        {
            "category":"Personal",
            "subcategory":"Massage",
            "type":"Services"
        }
    ],
    "sg:phone":"+61 7 4946 5822",
    "sg:postcode":"4802",
    "sg:province":"QLD",
    "sg:tags":[
        "therapy"
    ],
    "wof:name":"Whitsunday Natural Health",
    "wof:placetype":"venue"
},
  "geometry": {"coordinates":[148.71946716299999,-20.2692680359],"type":"Point"}
}