{
  "type": "Feature",
  "properties": {
    "iso:country":"AU",
    "sg:address":"9 a Gilbert Rd",
    "sg:city":"Preston",
    "sg:classifiers":[
        {
            "category":"Professional",
            "subcategory":"Art Services",
            "type":"Services"
        }
    ],
    "sg:phone":"+61 3 9480 4377",
    "sg:postcode":"3072",
    "sg:province":"VIC",
    "sg:tags":[
        "graphic",
        "designer"
    ],
    "wof:name":"Ooga Booga",
    "wof:placetype":"venue"
},
  "geometry": {"coordinates":[144.98982238799999,-37.7395858765],"type":"Point"}
}