{
  "type": "Feature",
  "properties": {
    "addr:full":"323 Margaret St Toowoomba QLD 4350",
    "addr:housenumber":"323",
    "addr:postcode":"4350",
    "addr:street":"Margaret St",
    "iso:country":"AU",
    "sg:address":"323 Margaret St",
    "sg:city":"Toowoomba",
    "sg:classifiers":[
        {
            "category":"Farming",
            "subcategory":"Farm & Veterinary Services",
            "type":"Manufacturing & Wholesale Goods"
        }
    ],
    "sg:phone":"+61 7 4637 9099",
    "sg:postcode":"4350",
    "sg:province":"QLD",
    "sg:tags":[
        "agricultural",
        "advisory"
    ],
    "wof:name":"Kondinin Group",
    "wof:placetype":"venue"
},
  "geometry": {"coordinates":[151.94529700000001,-27.559772],"type":"Point"}
}