{
  "type": "Feature",
  "properties": {
    "addr:full":"53 Slater Pde Keilor East VIC 3033",
    "addr:housenumber":"53",
    "addr:postcode":"3033",
    "addr:street":"Slater Pde",
    "iso:country":"AU",
    "sg:address":"53 Slater Pde",
    "sg:city":"Keilor East",
    "sg:classifiers":[
        {
            "category":"Retail",
            "subcategory":"Auto Repair",
            "type":"Services"
        }
    ],
    "sg:phone":"+61 3 9331 6536",
    "sg:postcode":"3033",
    "sg:province":"VIC",
    "sg:tags":[
        "testing",
        "inspection",
        "motor",
        "vehicle"
    ],
    "wof:name":"Serv Group (AUST)",
    "wof:placetype":"venue"
},
  "geometry": {"coordinates":[144.855118,-37.734722],"type":"Point"}
}