{
  "type": "Feature",
  "properties": {
    "iso:country":"AU",
    "sg:address":"166 Commonwealth Ave",
    "sg:city":"Yarralumla",
    "sg:classifiers":[
        {
            "category":"Personal",
            "subcategory":"Beauty Salon",
            "type":"Services"
        }
    ],
    "sg:phone":"+61 2 6273 2818",
    "sg:postcode":"2600",
    "sg:province":"ACT",
    "sg:tags":[
        "hairdresser"
    ],
    "wof:name":"Endless Hair",
    "wof:placetype":"venue"
},
  "geometry": {"coordinates":[149.12495422399999,-35.3048324585],"type":"Point"}
}