{
  "type": "Feature",
  "properties": {
    "iso:country":"AU",
    "sg:address":"11 - 13 Rhodes St",
    "sg:city":"West Ryde",
    "sg:classifiers":[
        {
            "category":"Professional",
            "type":"Services"
        }
    ],
    "sg:phone":"+61 2 9807 1499",
    "sg:postcode":"2114",
    "sg:province":"NSW",
    "sg:tags":[
        "shop",
        "fitting"
    ],
    "wof:name":"Dixon & Swanson Pty Ltd",
    "wof:placetype":"venue"
},
  "geometry": {"coordinates":[151.09147644000001,-33.8117980957],"type":"Point"}
}