{
  "type": "Feature",
  "properties": {
    "addr:full":"152 Como Pde West Parkdale VIC 3194",
    "addr:housenumber":"152",
    "addr:postcode":"3194",
    "addr:street":"Como Pde West",
    "iso:country":"AU",
    "sg:address":"152 Como Pde",
    "sg:city":"West Parkdale",
    "sg:classifiers":[
        {
            "category":"Health Services",
            "subcategory":"Doctor",
            "type":"Services"
        }
    ],
    "sg:phone":"+61 3 9387 1000",
    "sg:postcode":"3194",
    "sg:province":"VIC",
    "sg:tags":[
        "medical",
        "practitioner"
    ],
    "wof:name":"Engler Dennis",
    "wof:placetype":"venue"
},
  "geometry": {"coordinates":[145.072799683,-37.9904708862],"type":"Point"}
}