{
  "type": "Feature",
  "properties": {
    "addr:full":"88 Ebbern St Darra QLD 4076",
    "addr:housenumber":"88",
    "addr:postcode":"4076",
    "addr:street":"Ebbern St",
    "iso:country":"AU",
    "sg:address":"88 Ebbern St",
    "sg:city":"Darra",
    "sg:classifiers":[
        {
            "category":"Wholesale",
            "subcategory":"Construction Materials",
            "type":"Manufacturing & Wholesale Goods"
        }
    ],
    "sg:phone":"+61 7 3715 7300",
    "sg:postcode":"4076",
    "sg:province":"QLD",
    "sg:tags":[
        "wholesaler",
        "lighting",
        "mfrs",
        "accessory"
    ],
    "wof:name":"Oriel Lighting",
    "wof:placetype":"venue"
},
  "geometry": {"coordinates":[152.94758605999999,-27.5669345856],"type":"Point"}
}