{
  "type": "Feature",
  "properties": {
    "iso:country":"AU",
    "sg:address":"1 King St",
    "sg:city":"Rockdale",
    "sg:classifiers":[
        {
            "category":"Deli",
            "type":"Food & Drink"
        }
    ],
    "sg:phone":"+61 2 9567 5782",
    "sg:postcode":"2216",
    "sg:province":"NSW",
    "sg:tags":[
        "delicatessen"
    ],
    "wof:name":"Balkan Deli",
    "wof:placetype":"venue"
},
  "geometry": {"coordinates":[151.138412,-33.952454],"type":"Point"}
}