{
  "type": "Feature",
  "properties": {
    "addr:full":"479 Coleyville Rd Coleyville QLD 4307",
    "addr:housenumber":"479",
    "addr:postcode":"4307",
    "addr:street":"Coleyville Rd",
    "iso:country":"AU",
    "sg:address":"479 Coleyville Rd",
    "sg:city":"Coleyville",
    "sg:classifiers":[
        {
            "category":"Building & Trades",
            "subcategory":"Plumbing",
            "type":"Services"
        }
    ],
    "sg:phone":"+61 7 5467 1011",
    "sg:postcode":"4307",
    "sg:province":"QLD",
    "sg:tags":[
        "pipe",
        "line",
        "contractor"
    ],
    "wof:name":"Bellrise Investments Pty Ltd",
    "wof:placetype":"venue"
},
  "geometry": {"coordinates":[152.56344604500001,-27.82006073],"type":"Point"}
}