{
  "type": "Feature",
  "properties": {
    "iso:country":"AU",
    "sg:address":"Waterloo Rd",
    "sg:city":"Greenacre",
    "sg:classifiers":[
        {
            "category":"Organizations",
            "subcategory":"Community Association",
            "type":"Services"
        }
    ],
    "sg:phone":"+61 2 9750 5870",
    "sg:postcode":"2190",
    "sg:province":"NSW",
    "sg:tags":[
        "club",
        "senior",
        "citizen"
    ],
    "wof:name":"Senior Citizens' Centres",
    "wof:placetype":"venue"
},
  "geometry": {"coordinates":[151.060196,-33.8936],"type":"Point"}
}