{
  "type": "Feature",
  "properties": {
    "addr:full":"1/ 254 Marine Pde Labrador QLD 4215",
    "addr:housenumber":"/ 254",
    "addr:postcode":"4215",
    "addr:street":"Marine Pde",
    "iso:country":"AU",
    "sg:address":"1/ 254 Marine Pde",
    "sg:city":"Labrador",
    "sg:classifiers":[
        {
            "category":"Banks & Credit Unions",
            "subcategory":"Financial Services",
            "type":"Services"
        }
    ],
    "sg:phone":"+61 7 5532 3185",
    "sg:postcode":"4215",
    "sg:province":"QLD",
    "sg:tags":[
        "advisory",
        "planning",
        "retirement"
    ],
    "wof:name":"Barron Ian & Associates",
    "wof:placetype":"venue"
},
  "geometry": {"coordinates":[153.40957641599999,-27.948600769],"type":"Point"}
}