{
  "type": "Feature",
  "properties": {
    "addr:full":"376 Bent St Grafton NSW 2460",
    "addr:housenumber":"376",
    "addr:postcode":"2460",
    "addr:street":"Bent St",
    "iso:country":"AU",
    "sg:address":"376 Bent St",
    "sg:city":"Grafton",
    "sg:classifiers":[
        {
            "category":"Shopping",
            "subcategory":"Party Supplies",
            "type":"Retail Goods"
        }
    ],
    "sg:phone":"+61 2 6642 7544",
    "sg:postcode":"2460",
    "sg:province":"NSW",
    "sg:tags":[
        "selling",
        "plan"
    ],
    "wof:name":"Just Like Leadlight",
    "wof:placetype":"venue"
},
  "geometry": {"coordinates":[152.922897339,-29.7302474976],"type":"Point"}
}