{
  "type": "Feature",
  "properties": {
    "addr:full":"7 Huntsmore Rd Minto NSW 2566",
    "addr:housenumber":"7",
    "addr:postcode":"2566",
    "addr:street":"Huntsmore Rd",
    "iso:country":"AU",
    "sg:address":"7 Huntsmore Rd",
    "sg:city":"Minto",
    "sg:classifiers":[
        {
            "category":"Manufacturing",
            "subcategory":"Rubber & Plastics",
            "type":"Manufacturing & Wholesale Goods"
        }
    ],
    "sg:phone":"+61 2 9603 4133",
    "sg:postcode":"2566",
    "sg:province":"NSW",
    "sg:tags":[
        "wholesaler",
        "product",
        "mfrs"
    ],
    "sg:website":"http://www.rasapprotech.com.au",
    "wof:name":"RAS ApproTech",
    "wof:placetype":"venue"
},
  "geometry": {"coordinates":[150.83697509800001,-34.0360374451],"type":"Point"}
}