{
  "type": "Feature",
  "properties": {
    "addr:full":"1 Good St Granville NSW 2142",
    "addr:housenumber":"1",
    "addr:postcode":"2142",
    "addr:street":"Good St",
    "iso:country":"AU",
    "sg:address":"1 Good St",
    "sg:city":"Granville",
    "sg:classifiers":[
        {
            "category":"Shopping",
            "subcategory":"Pawn Shop",
            "type":"Retail Goods"
        }
    ],
    "sg:phone":"+61 2 9897 5627",
    "sg:postcode":"2142",
    "sg:province":"NSW",
    "sg:tags":[
        "pawnbroker"
    ],
    "wof:name":"Cash Convenience",
    "wof:placetype":"venue"
},
  "geometry": {"coordinates":[151.01153564399999,-33.8320884705],"type":"Point"}
}