{
  "type": "Feature",
  "properties": {
    "addr:full":"Cornelia Creek Rd Echuca VIC 3564",
    "addr:postcode":"3564",
    "addr:street":"Cornelia Creek Rd",
    "iso:country":"AU",
    "sg:address":"Cornelia Creek Rd",
    "sg:city":"Echuca",
    "sg:classifiers":[
        {
            "category":"Farming",
            "subcategory":"Vineyard",
            "type":"Manufacturing & Wholesale Goods"
        }
    ],
    "sg:phone":"+61 3 5482 2516",
    "sg:postcode":"3564",
    "sg:province":"VIC",
    "sg:tags":[
        "winery"
    ],
    "wof:name":"Tisdall Wines",
    "wof:placetype":"venue"
},
  "geometry": {"coordinates":[144.74836730999999,-36.1293907166],"type":"Point"}
}