{
  "type": "Feature",
  "properties": {
    "addr:full":"381 Camberwell Rd Camberwell VIC 3124",
    "addr:housenumber":"381",
    "addr:postcode":"3124",
    "addr:street":"Camberwell Rd",
    "iso:country":"AU",
    "sg:address":"381 Camberwell Rd",
    "sg:city":"Camberwell",
    "sg:classifiers":[
        {
            "category":"Personal",
            "subcategory":"Beauty Salon",
            "type":"Services"
        }
    ],
    "sg:phone":"+61 3 9882 5585",
    "sg:postcode":"3124",
    "sg:province":"VIC",
    "sg:tags":[
        "hairdresser"
    ],
    "wof:name":"Oodoo Hair & Body",
    "wof:placetype":"venue"
},
  "geometry": {"coordinates":[145.06098938,-37.8347740173],"type":"Point"}
}