{
  "type": "Feature",
  "properties": {
    "addr:full":"80 Henry St Guildford NSW 2161",
    "addr:housenumber":"80",
    "addr:postcode":"2161",
    "addr:street":"Henry St",
    "iso:country":"AU",
    "sg:address":"80 Henry St",
    "sg:city":"Guildford",
    "sg:classifiers":[
        {
            "category":"Home & Garden",
            "subcategory":"Carpets & Floor Coverings",
            "type":"Retail Goods"
        }
    ],
    "sg:phone":"+61 404 246 739",
    "sg:postcode":"2161",
    "sg:province":"NSW",
    "sg:tags":[
        "tile",
        "wall"
    ],
    "wof:name":"AMF Master Tiling",
    "wof:placetype":"venue"
},
  "geometry": {"coordinates":[150.98431396500001,-33.8599357605],"type":"Point"}
}