{
  "type": "Feature",
  "properties": {
    "addr:full":"430 Moreland Rd Coburg VIC 3058",
    "addr:housenumber":"430",
    "addr:postcode":"3058",
    "addr:street":"Moreland Rd",
    "iso:country":"AU",
    "sg:address":"430 Moreland Rd",
    "sg:city":"Coburg",
    "sg:classifiers":[
        {
            "category":"Autos & Motor Vehicles",
            "subcategory":"Fuel & Gas Station",
            "type":"Retail Goods"
        }
    ],
    "sg:phone":"+61 3 9384 2908",
    "sg:postcode":"3058",
    "sg:province":"VIC",
    "wof:name":"Plus Petrol",
    "wof:placetype":"venue"
},
  "geometry": {"coordinates":[144.96505737300001,-37.7555389404],"type":"Point"}
}