{
  "type": "Feature",
  "properties": {
    "iso:country":"AU",
    "sg:address":"17 George St",
    "sg:city":"North Strathfield",
    "sg:classifiers":[
        {
            "category":"Sports & Exercise",
            "subcategory":"Gym",
            "type":"Entertainment"
        }
    ],
    "sg:phone":"+61 2 8765 8806",
    "sg:postcode":"2137",
    "sg:province":"NSW",
    "sg:tags":[
        "pilate",
        "method"
    ],
    "wof:name":"Leeon & Shaw Pilates Pty Ltd",
    "wof:placetype":"venue"
},
  "geometry": {"coordinates":[151.08705139200001,-33.8592948914],"type":"Point"}
}