{
  "type": "Feature",
  "properties": {
    "addr:full":"Melvin St Bundaberg QLD 4670",
    "addr:postcode":"4670",
    "addr:street":"Melvin St",
    "iso:country":"AU",
    "sg:address":"Melvin St",
    "sg:city":"Bundaberg",
    "sg:classifiers":[
        {
            "category":"Real Estate",
            "subcategory":"Real Estate Agent",
            "type":"Services"
        }
    ],
    "sg:phone":"+61 7 4153 1147",
    "sg:postcode":"4670",
    "sg:province":"QLD",
    "sg:tags":[
        "steel",
        "foundry",
        "iron"
    ],
    "wof:name":"Bundaberg Metal Industries Pty Ltd",
    "wof:placetype":"venue"
},
  "geometry": {"coordinates":[152.35174560600001,-24.891368866],"type":"Point"}
}