{
  "type": "Feature",
  "properties": {
    "addr:full":"Shop 5/ 482 Golden Four Drv Tugun QLD 4224",
    "addr:housenumber":"shop 5 / 482",
    "addr:postcode":"4224",
    "addr:street":"Golden Four Drv",
    "iso:country":"AU",
    "sg:address":"Shop 5/ 482 Golden Four Drv",
    "sg:city":"Tugun",
    "sg:classifiers":[
        {
            "category":"Banks & Credit Unions",
            "subcategory":"Investment Brokerage",
            "type":"Services"
        }
    ],
    "sg:phone":"+61 7 5534 1888",
    "sg:postcode":"4224",
    "sg:province":"QLD",
    "sg:tags":[
        "management",
        "property"
    ],
    "wof:name":"Andrew Reynolds",
    "wof:placetype":"venue"
},
  "geometry": {"coordinates":[153.49290466299999,-28.1419849396],"type":"Point"}
}