{
  "type": "Feature",
  "properties": {
    "addr:full":"Level 7, 91 Phillip St Parramatta NSW 2150",
    "addr:housenumber":"91",
    "addr:postcode":"2150",
    "addr:street":"Phillip St",
    "iso:country":"AU",
    "sg:address":"Level 7, 91 Phillip St",
    "sg:city":"Parramatta",
    "sg:classifiers":[
        {
            "category":"Professional",
            "subcategory":"Art Services",
            "type":"Services"
        }
    ],
    "sg:phone":"+61 2 9613 4660",
    "sg:postcode":"2150",
    "sg:province":"NSW",
    "sg:tags":[
        "graphic",
        "designer"
    ],
    "wof:name":"Creative Fusion",
    "wof:placetype":"venue"
},
  "geometry": {"coordinates":[151.00668335,-33.81483078],"type":"Point"}
}