{
  "type": "Feature",
  "properties": {
    "addr:full":"340 Canning Hwy Bicton WA 6157",
    "addr:housenumber":"340",
    "addr:postcode":"6157",
    "addr:street":"Canning Hwy",
    "iso:country":"AU",
    "sg:address":"340 Canning Hwy",
    "sg:city":"Bicton",
    "sg:classifiers":[
        {
            "category":"Health Services",
            "subcategory":"Doctor",
            "type":"Services"
        }
    ],
    "sg:phone":"+61 8 9339 0300",
    "sg:postcode":"6157",
    "sg:province":"WA",
    "sg:tags":[
        "medical",
        "practitioner"
    ],
    "wof:name":"Bicton-Palmyra Medical Practice",
    "wof:placetype":"venue"
},
  "geometry": {"coordinates":[115.78344,-32.036659],"type":"Point"}
}