{
  "type": "Feature",
  "properties": {
    "addr:full":"130 Eagle St Redbank Plains QLD 4301",
    "addr:housenumber":"130",
    "addr:postcode":"4301",
    "addr:street":"Eagle St",
    "iso:country":"AU",
    "sg:address":"130 Eagle St",
    "sg:city":"Redbank Plains",
    "sg:classifiers":[
        {
            "category":"Manufacturing",
            "subcategory":"Building Materials",
            "type":"Manufacturing & Wholesale Goods"
        }
    ],
    "sg:phone":"+61 7 3814 0066",
    "sg:postcode":"4301",
    "sg:province":"QLD",
    "sg:tags":[
        "concrete",
        "product"
    ],
    "wof:name":"Ipswich Concrete & Colour Supplies",
    "wof:placetype":"venue"
},
  "geometry": {"coordinates":[152.874801636,-27.6263542175],"type":"Point"}
}