{
  "type": "Feature",
  "properties": {
    "addr:full":"27- 29 Fitzpatrick St Revesby NSW 2212",
    "addr:housenumber":"29",
    "addr:postcode":"2212",
    "addr:street":"Fitzpatrick St",
    "iso:country":"AU",
    "sg:address":"27- 29 Fitzpatrick St",
    "sg:city":"Revesby",
    "sg:classifiers":[
        {
            "category":"Building & Trades",
            "subcategory":"Construction",
            "type":"Services"
        }
    ],
    "sg:phone":"+61 2 9774 2088",
    "sg:postcode":"2212",
    "sg:province":"NSW",
    "sg:tags":[
        "scaffolding"
    ],
    "wof:name":"Advance Scaffold",
    "wof:placetype":"venue"
},
  "geometry": {"coordinates":[151.003265,-33.936565],"type":"Point"}
}