{
  "type": "Feature",
  "properties": {
    "addr:full":"77 Enterprise St Bundaberg QLD 4670",
    "addr:housenumber":"77",
    "addr:postcode":"4670",
    "addr:street":"Enterprise St",
    "iso:country":"AU",
    "sg:address":"77 Enterprise St",
    "sg:city":"Bundaberg",
    "sg:classifiers":[
        {
            "category":"Wholesale",
            "subcategory":"Farm Supplies",
            "type":"Manufacturing & Wholesale Goods"
        }
    ],
    "sg:phone":"+61 7 4153 3200",
    "sg:postcode":"4670",
    "sg:province":"QLD",
    "sg:tags":[
        "feed",
        "supplement",
        "stock"
    ],
    "wof:name":"Bundaberg Stock Feeds",
    "wof:placetype":"venue"
},
  "geometry": {"coordinates":[152.339447022,-24.8914318085],"type":"Point"}
}