{
  "type": "Feature",
  "properties": {
    "iso:country":"AU",
    "sg:address":"65 High St",
    "sg:city":"Maryborough",
    "sg:classifiers":[
        {
            "category":"Autos & Motor Vehicles",
            "subcategory":"Automobile Sales",
            "type":"Retail Goods"
        }
    ],
    "sg:phone":"+61 3 5461 5175",
    "sg:postcode":"3465",
    "sg:province":"VIC",
    "sg:tags":[
        "car",
        "used"
    ],
    "wof:name":"Eclipse Ford",
    "wof:placetype":"venue"
},
  "geometry": {"coordinates":[143.73565673799999,-37.0480537415],"type":"Point"}
}