{
  "type": "Feature",
  "properties": {
    "addr:full":"119 Fairview Drv Willow Vale QLD 4209",
    "addr:housenumber":"119",
    "addr:postcode":"4209",
    "addr:street":"Fairview Drv",
    "iso:country":"AU",
    "sg:address":"119 Fairview Drv",
    "sg:city":"Willow Vale",
    "sg:classifiers":[
        {
            "category":"Home & Garden",
            "subcategory":"Building Materials",
            "type":"Retail Goods"
        }
    ],
    "sg:phone":"+61 7 5546 7001",
    "sg:postcode":"4209",
    "sg:province":"QLD",
    "sg:tags":[
        "lawn",
        "cutting",
        "maintenance"
    ],
    "wof:name":"Steve & Petrina Scott",
    "wof:placetype":"venue"
},
  "geometry": {"coordinates":[153.260665894,-27.8292121887],"type":"Point"}
}