{
  "type": "Feature",
  "properties": {
    "addr:full":"20 Winbourne Rd Brookvale NSW 2100",
    "addr:housenumber":"20",
    "addr:postcode":"2100",
    "addr:street":"Winbourne Rd",
    "iso:country":"AU",
    "sg:address":"20 Winbourne Rd",
    "sg:city":"Brookvale",
    "sg:classifiers":[
        {
            "category":"Retail",
            "subcategory":"Auto Repair",
            "type":"Services"
        }
    ],
    "sg:phone":"+61 2 9905 3594",
    "sg:postcode":"2100",
    "sg:province":"NSW",
    "sg:tags":[
        "beater",
        "painter",
        "panel"
    ],
    "wof:name":"Vescio Mick Smash Repairs",
    "wof:placetype":"venue"
},
  "geometry": {"coordinates":[151.27818298299999,-33.7625808716],"type":"Point"}
}