{
  "type": "Feature",
  "properties": {
    "iso:country":"AU",
    "sg:address":"10 Maitland St",
    "sg:city":"Burleigh Heads",
    "sg:classifiers":[
        {
            "category":"Professional",
            "subcategory":"Computer Services",
            "type":"Services"
        }
    ],
    "sg:phone":"+61 7 5576 5186",
    "sg:postcode":"4220",
    "sg:province":"QLD",
    "sg:tags":[
        "equipment",
        "networking",
        "installation"
    ],
    "wof:name":"Marsh David Computers",
    "wof:placetype":"venue"
},
  "geometry": {"coordinates":[153.441696167,-28.0825824738],"type":"Point"}
}