{
  "type": "Feature",
  "properties": {
    "addr:full":"109 Brenan St Smithfield NSW 2164",
    "addr:housenumber":"109",
    "addr:postcode":"2164",
    "addr:street":"Brenan St",
    "iso:country":"AU",
    "sg:address":"109 Brenan St",
    "sg:city":"Smithfield",
    "sg:classifiers":[
        {
            "category":"Shopping",
            "subcategory":"Stationery & Office Supplies",
            "type":"Retail Goods"
        }
    ],
    "sg:phone":"+61 2 9604 8096",
    "sg:postcode":"2164",
    "sg:province":"NSW",
    "sg:tags":[
        "partition"
    ],
    "wof:name":"E & N Specialised Interiors Pty Ltd",
    "wof:placetype":"venue"
},
  "geometry": {"coordinates":[150.93670654300001,-33.8571395874],"type":"Point"}
}