{
  "type": "Feature",
  "properties": {
    "iso:country":"AU",
    "sg:address":"Shop 206 Redbank Plaza Collingwood Drv",
    "sg:city":"Redbank",
    "sg:classifiers":[
        {
            "category":"Shopping",
            "subcategory":"Clothing, Apparel, & Fashions",
            "type":"Retail Goods"
        }
    ],
    "sg:phone":"+61 7 3818 1728",
    "sg:postcode":"4301",
    "sg:province":"QLD",
    "sg:tags":[
        "menswear"
    ],
    "wof:name":"Lowes",
    "wof:placetype":"venue"
},
  "geometry": {"coordinates":[152.870407105,-27.6047439575],"type":"Point"}
}