{
  "type": "Feature",
  "properties": {
    "addr:full":"113 Left Bank Rd Mullumbimby NSW 2482",
    "addr:housenumber":"113",
    "addr:postcode":"2482",
    "addr:street":"Left Bank Rd",
    "iso:country":"AU",
    "sg:address":"113 Left Bank Rd",
    "sg:city":"Mullumbimby",
    "sg:classifiers":[
        {
            "category":"Building & Trades",
            "subcategory":"Landscaping Services",
            "type":"Services"
        }
    ],
    "sg:phone":"+61 2 6684 2621",
    "sg:postcode":"2482",
    "sg:province":"NSW",
    "sg:tags":[
        "slashing",
        "contractor"
    ],
    "wof:name":"4 in 1 Bucket",
    "wof:placetype":"venue"
},
  "geometry": {"coordinates":[153.49993896500001,-28.5531997681],"type":"Point"}
}