{
  "type": "Feature",
  "properties": {
    "iso:country":"AU",
    "sg:address":"Shop 5/72- 74 Main St",
    "sg:city":"Blacktown",
    "sg:classifiers":[
        {
            "category":"Shopping",
            "subcategory":"Mobile Phones",
            "type":"Retail Goods"
        }
    ],
    "sg:phone":"+61 2 9676 2977",
    "sg:postcode":"2148",
    "sg:province":"NSW",
    "sg:tags":[
        "telephone",
        "accessory"
    ],
    "wof:name":"Cellscope Pty Ltd",
    "wof:placetype":"venue"
},
  "geometry": {"coordinates":[150.90911865199999,-33.770149231],"type":"Point"}
}