{
  "type": "Feature",
  "properties": {
    "addr:full":"42 Larra St Yennora NSW 2161",
    "addr:housenumber":"42",
    "addr:postcode":"2161",
    "addr:street":"Larra St",
    "iso:country":"AU",
    "sg:address":"42 Larra St",
    "sg:city":"Yennora",
    "sg:classifiers":[
        {
            "category":"Real Estate",
            "subcategory":"Surveying",
            "type":"Services"
        }
    ],
    "sg:phone":"+61 2 9721 0300",
    "sg:postcode":"2161",
    "sg:province":"NSW",
    "sg:tags":[
        "map",
        "mapping"
    ],
    "wof:name":"Granite Co",
    "wof:placetype":"venue"
},
  "geometry": {"coordinates":[150.97459411599999,-33.8639297485],"type":"Point"}
}