{
  "type": "Feature",
  "properties": {
    "addr:full":"724 Botany Rd Mascot NSW 2020",
    "addr:housenumber":"724",
    "addr:postcode":"2020",
    "addr:street":"Botany Rd",
    "iso:country":"AU",
    "sg:address":"724 Botany Rd",
    "sg:city":"Mascot",
    "sg:classifiers":[
        {
            "category":"Professional",
            "subcategory":"Detective & Security Services",
            "type":"Services"
        }
    ],
    "sg:phone":"+61 1300 303 661",
    "sg:postcode":"2020",
    "sg:province":"NSW",
    "sg:tags":[
        "domestic",
        "alarm",
        "commercial",
        "burglar"
    ],
    "wof:name":"P.R.V. Security",
    "wof:placetype":"venue"
},
  "geometry": {"coordinates":[151.19427490199999,-33.9353485107],"type":"Point"}
}