{
  "type": "Feature",
  "properties": {
    "addr:full":"17 Cumberland Ave Nowra South NSW 2541",
    "addr:housenumber":"17",
    "addr:postcode":"2541",
    "addr:street":"Cumberland Ave",
    "iso:country":"AU",
    "sg:address":"17 Cumberland Ave",
    "sg:city":"Nowra South",
    "sg:classifiers":[
        {
            "category":"Professional",
            "subcategory":"Engineering",
            "type":"Services"
        }
    ],
    "sg:phone":"+61 2 4421 8946",
    "sg:postcode":"2541",
    "sg:province":"NSW",
    "sg:tags":[
        "engineer"
    ],
    "wof:name":"Glenview Industries",
    "wof:placetype":"venue"
},
  "geometry": {"coordinates":[150.586425781,-34.9100151062],"type":"Point"}
}