{
  "type": "Feature",
  "properties": {
    "addr:full":"105 King St Doncaster East VIC 3109",
    "addr:housenumber":"105",
    "addr:postcode":"3109",
    "addr:street":"King St",
    "iso:country":"AU",
    "sg:address":"105 King St",
    "sg:city":"Doncaster East",
    "sg:classifiers":[
        {
            "category":"Health Services",
            "subcategory":"Dentist",
            "type":"Services"
        }
    ],
    "sg:phone":"+61 3 9841 8033",
    "sg:postcode":"3109",
    "sg:province":"VIC",
    "wof:name":"Newstadt Gary Dr",
    "wof:placetype":"venue"
},
  "geometry": {"coordinates":[145.15786743199999,-37.774269104],"type":"Point"}
}