{
  "type": "Feature",
  "properties": {
    "addr:full":"7 Warraba Rd Narrabeen NSW 2101",
    "addr:housenumber":"7",
    "addr:postcode":"2101",
    "addr:street":"Warraba Rd",
    "iso:country":"AU",
    "sg:address":"7 Warraba Rd",
    "sg:city":"Narrabeen",
    "sg:classifiers":[
        {
            "category":"Retail",
            "subcategory":"Auto Repair",
            "type":"Services"
        }
    ],
    "sg:phone":"+61 2 9913 7244",
    "sg:postcode":"2101",
    "sg:province":"NSW",
    "sg:tags":[
        "repairer",
        "motor",
        "engineer"
    ],
    "wof:name":"Swan Motors Service NSW",
    "wof:placetype":"venue"
},
  "geometry": {"coordinates":[151.29449500000001,-33.701954],"type":"Point"}
}