{
  "type": "Feature",
  "properties": {
    "addr:full":"48 Brighton St Torquay QLD 4655",
    "addr:housenumber":"48",
    "addr:postcode":"4655",
    "addr:street":"Brighton St",
    "iso:country":"AU",
    "sg:address":"48 Brighton St",
    "sg:city":"Torquay",
    "sg:classifiers":[
        {
            "category":"Utilities",
            "subcategory":"Electric",
            "type":"Services"
        }
    ],
    "sg:phone":"+61 418 797 239",
    "sg:postcode":"4655",
    "sg:province":"QLD",
    "sg:tags":[
        "electrical",
        "contractor"
    ],
    "wof:name":"Tony Darlington Electrical",
    "wof:placetype":"venue"
},
  "geometry": {"coordinates":[152.81929,-25.255402],"type":"Point"}
}