{
  "type": "Feature",
  "properties": {
    "addr:full":"26 Edward St Arncliffe NSW 2205",
    "addr:housenumber":"26",
    "addr:postcode":"2205",
    "addr:street":"Edward St",
    "iso:country":"AU",
    "sg:address":"26 Edward St",
    "sg:city":"Arncliffe",
    "sg:classifiers":[
        {
            "category":"Building & Trades",
            "subcategory":"Construction",
            "type":"Services"
        }
    ],
    "sg:phone":"+61 409 619 016",
    "sg:postcode":"2205",
    "sg:province":"NSW",
    "sg:tags":[
        "concrete",
        "contractor"
    ],
    "wof:name":"ABA The Paving Man",
    "wof:placetype":"venue"
},
  "geometry": {"coordinates":[151.143112,-33.932102],"type":"Point"}
}