{
  "type": "Feature",
  "properties": {
    "addr:full":"Church St Tinaroo Falls QLD 4872",
    "addr:postcode":"4872",
    "addr:street":"Church St",
    "iso:country":"AU",
    "sg:address":"Church St",
    "sg:city":"Tinaroo Falls",
    "sg:classifiers":[
        {
            "category":"Manufacturing",
            "subcategory":"Food",
            "type":"Manufacturing & Wholesale Goods"
        }
    ],
    "sg:phone":"+61 7 4095 8242",
    "sg:postcode":"4872",
    "sg:province":"QLD",
    "sg:tags":[
        "function",
        "catering"
    ],
    "wof:name":"Pensini's Cafe Restaurant",
    "wof:placetype":"venue"
},
  "geometry": {"coordinates":[145.550415039,-17.1708698273],"type":"Point"}
}