{
  "type": "Feature",
  "properties": {
    "iso:country":"AU",
    "sg:address":"889 Stuart Hwy",
    "sg:city":"Berrimah",
    "sg:classifiers":[
        {
            "category":"Transit Center",
            "subcategory":"Freight",
            "type":"Transportation"
        }
    ],
    "sg:phone":"+61 13 25 54",
    "sg:postcode":"0828",
    "sg:province":"NT",
    "sg:tags":[
        "agent",
        "shipping"
    ],
    "wof:name":"Allied Pickfords",
    "wof:placetype":"venue"
},
  "geometry": {"coordinates":[130.96742248499999,-12.4556388855],"type":"Point"}
}