{
  "type": "Feature",
  "properties": {
    "addr:full":"Rufus Crt Narre Warren VIC 3805",
    "addr:postcode":"3805",
    "addr:street":"Rufus Crt",
    "iso:country":"AU",
    "sg:address":"Rufus Crt",
    "sg:city":"Narre Warren",
    "sg:classifiers":[
        {
            "category":"Transit Center",
            "subcategory":"Passenger",
            "type":"Transportation"
        }
    ],
    "sg:phone":"+61 3 8790 1799",
    "sg:postcode":"3805",
    "sg:province":"VIC",
    "sg:tags":[
        "frozen",
        "food",
        "retail"
    ],
    "wof:name":"Sinnic Food Services",
    "wof:placetype":"venue"
},
  "geometry": {"coordinates":[145.31407200000001,-38.01561],"type":"Point"}
}