{
  "type": "Feature",
  "properties": {
    "iso:country":"AU",
    "sg:address":"196 Waterloo Rd",
    "sg:city":"Greenacre",
    "sg:classifiers":[
        {
            "category":"Retail",
            "subcategory":"Auto Repair",
            "type":"Services"
        }
    ],
    "sg:phone":"+61 2 9740 5751",
    "sg:postcode":"2190",
    "sg:province":"NSW",
    "sg:tags":[
        "electrical"
    ],
    "wof:name":"C & P Auto Electrical Engineers Pty Ltd",
    "wof:placetype":"venue"
},
  "geometry": {"coordinates":[151.058304,-33.90144],"type":"Point"}
}