{
  "type": "Feature",
  "properties": {
    "addr:full":"16 Frankston Gardens Drv Carrum Downs VIC 3201",
    "addr:housenumber":"16",
    "addr:postcode":"3201",
    "addr:street":"Frankston Gardens Drv",
    "iso:country":"AU",
    "sg:address":"16 Frankston Gardens Drv",
    "sg:city":"Carrum Downs",
    "sg:classifiers":[
        {
            "category":"Home & Garden",
            "subcategory":"Building Materials",
            "type":"Retail Goods"
        }
    ],
    "sg:phone":"+61 3 9785 2044",
    "sg:postcode":"3201",
    "sg:province":"VIC",
    "sg:tags":[
        "fitting",
        "door"
    ],
    "wof:name":"Schiffer Manufacturing P/L",
    "wof:placetype":"venue"
},
  "geometry": {"coordinates":[145.16357400000001,-38.105011],"type":"Point"}
}