{
  "type": "Feature",
  "properties": {
    "iso:country":"AU",
    "sg:address":"569 Bayswater Rd",
    "sg:city":"Mt Louisa",
    "sg:classifiers":[
        {
            "category":"Education",
            "subcategory":"School",
            "type":"Public Place"
        }
    ],
    "sg:phone":"+61 7 4722 9201",
    "sg:postcode":"4814",
    "sg:province":"QLD",
    "wof:name":"Calvary Christian College",
    "wof:placetype":"venue"
},
  "geometry": {"coordinates":[146.739655,-19.270653],"type":"Point"}
}