{
  "type": "Feature",
  "properties": {
    "addr:full":"Lot 411 Riverside Drv West End (Brisbane) QLD 4101",
    "addr:postcode":"4101",
    "addr:street":"Riverside Drv",
    "iso:country":"AU",
    "sg:address":"Lot 411 Riverside Drv",
    "sg:city":"West End (Brisbane)",
    "sg:classifiers":[
        {
            "category":"Recreation",
            "subcategory":"Boat Charter",
            "type":"Entertainment"
        }
    ],
    "sg:phone":"+61 7 3255 3455",
    "sg:postcode":"4101",
    "sg:province":"QLD",
    "sg:website":"http://www.theisland.net.au",
    "wof:name":"The Island",
    "wof:placetype":"venue"
},
  "geometry": {"coordinates":[153.00286865199999,-27.478887558],"type":"Point"}
}