{
  "type": "Feature",
  "properties": {
    "iso:country":"AU",
    "sg:address":"146 Edgar Rd",
    "sg:city":"Port Curtis",
    "sg:classifiers":[
        {
            "category":"Building & Trades",
            "subcategory":"Plumbing",
            "type":"Services"
        }
    ],
    "sg:phone":"+61 429 669 499",
    "sg:postcode":"4700",
    "sg:province":"QLD",
    "sg:tags":[
        "plumber",
        "gasfitters"
    ],
    "wof:name":"Tony Harney",
    "wof:placetype":"venue"
},
  "geometry": {"coordinates":[150.517822266,-23.4375457764],"type":"Point"}
}