{
  "type": "Feature",
  "properties": {
    "addr:full":"871 Pacific Hwy Chatswood NSW 2067",
    "addr:housenumber":"871",
    "addr:postcode":"2067",
    "addr:street":"Pacific Hwy",
    "iso:country":"AU",
    "sg:address":"871 Pacific Hwy",
    "sg:city":"Chatswood",
    "sg:classifiers":[
        {
            "category":"Sports & Exercise",
            "subcategory":"Ski Slope",
            "type":"Entertainment"
        }
    ],
    "sg:phone":"+61 2 9415 3555",
    "sg:postcode":"2067",
    "sg:province":"NSW",
    "sg:tags":[
        "equipment",
        "hire",
        "retail",
        "snow"
    ],
    "wof:name":"Bolsal Pty Ltd",
    "wof:placetype":"venue"
},
  "geometry": {"coordinates":[151.18020629899999,-33.7925186157],"type":"Point"}
}