{
  "type": "Feature",
  "properties": {
    "iso:country":"AU",
    "sg:address":"Ste 2b/ 17 Connor St",
    "sg:city":"Burleigh Heads",
    "sg:classifiers":[
        {
            "category":"Banks & Credit Unions",
            "subcategory":"Financial Services",
            "type":"Services"
        }
    ],
    "sg:phone":"+61 7 5520 6063",
    "sg:postcode":"4220",
    "sg:province":"QLD",
    "sg:tags":[
        "planning"
    ],
    "wof:name":"Hyland Investments Corporation",
    "wof:placetype":"venue"
},
  "geometry": {"coordinates":[153.45173645,-28.0892448425],"type":"Point"}
}