{
  "type": "Feature",
  "properties": {
    "addr:full":"618 Heidelberg-Kinglake Rd Diamond Creek VIC 3089",
    "addr:housenumber":"618",
    "addr:postcode":"3089",
    "addr:street":"Heidelberg-Kinglake Rd",
    "iso:country":"AU",
    "sg:address":"618 Heidelberg-Kinglake Rd",
    "sg:city":"Diamond Creek",
    "sg:classifiers":[
        {
            "category":"Professional",
            "subcategory":"Printing & Photocopies",
            "type":"Services"
        }
    ],
    "sg:phone":"+61 3 9718 0251",
    "sg:postcode":"3089",
    "sg:province":"VIC",
    "sg:tags":[
        "screen",
        "printer"
    ],
    "wof:name":"The Sign Centre",
    "wof:placetype":"venue"
},
  "geometry": {"coordinates":[145.15799000000001,-37.674252],"type":"Point"}
}