{
  "type": "Feature",
  "properties": {
    "addr:full":"186 Exhibition St Melbourne VIC 3000",
    "addr:housenumber":"186",
    "addr:postcode":"3000",
    "addr:street":"Exhibition St",
    "iso:country":"AU",
    "sg:address":"186 Exhibition St",
    "sg:city":"Melbourne",
    "sg:classifiers":[
        {
            "category":"Restaurant",
            "type":"Food & Drink"
        }
    ],
    "sg:phone":"+61 3 9662 0511",
    "sg:postcode":"3000",
    "sg:province":"VIC",
    "wof:name":"CBD Cafe Bar & Restaurant",
    "wof:placetype":"venue"
},
  "geometry": {"coordinates":[144.97038269000001,-37.8112792969],"type":"Point"}
}