{
  "type": "Feature",
  "properties": {
    "iso:country":"AU",
    "sg:address":"255 Edmondson Ave",
    "sg:city":"Austral",
    "sg:classifiers":[
        {
            "category":"Personal",
            "subcategory":"Beauty Salon",
            "type":"Services"
        }
    ],
    "sg:phone":"+61 2 9606 8440",
    "sg:postcode":"2171",
    "sg:province":"NSW",
    "sg:tags":[
        "hairdresser"
    ],
    "wof:name":"V`oila Hair Artists",
    "wof:placetype":"venue"
},
  "geometry": {"coordinates":[150.812255859,-33.9325675964],"type":"Point"}
}