{
  "type": "Feature",
  "properties": {
    "addr:full":"Victoria St Loch VIC 3945",
    "addr:postcode":"3945",
    "addr:street":"Victoria St",
    "iso:country":"AU",
    "sg:address":"Victoria St",
    "sg:city":"Loch",
    "sg:classifiers":[
        {
            "category":"Retail",
            "subcategory":"Auto Repair",
            "type":"Services"
        }
    ],
    "sg:phone":"+61 3 5659 4360",
    "sg:postcode":"3945",
    "sg:province":"VIC",
    "sg:tags":[
        "repairer",
        "motor",
        "engineer"
    ],
    "wof:name":"Elton Motors",
    "wof:placetype":"venue"
},
  "geometry": {"coordinates":[145.70698547399999,-38.3687782288],"type":"Point"}
}