{
  "type": "Feature",
  "properties": {
    "addr:full":"20 South St Rydalmere NSW 2116",
    "addr:housenumber":"20",
    "addr:postcode":"2116",
    "addr:street":"South St",
    "iso:country":"AU",
    "sg:address":"20 South St",
    "sg:city":"Rydalmere",
    "sg:classifiers":[
        {
            "category":"Professional",
            "type":"Services"
        }
    ],
    "sg:phone":"+61 13 26 10",
    "sg:postcode":"2116",
    "sg:province":"NSW",
    "sg:tags":[
        "courier"
    ],
    "wof:name":"Fedex Express Rydalmere",
    "wof:placetype":"venue"
},
  "geometry": {"coordinates":[151.010986328,-33.8333206177],"type":"Point"}
}