{
  "type": "Feature",
  "properties": {
    "addr:full":"3 King St Nanango QLD 4615",
    "addr:housenumber":"3",
    "addr:postcode":"4615",
    "addr:street":"King St",
    "iso:country":"AU",
    "sg:address":"3 King St",
    "sg:city":"Nanango",
    "sg:classifiers":[
        {
            "category":"Autos & Motor Vehicles",
            "subcategory":"Fuel & Gas Station",
            "type":"Retail Goods"
        }
    ],
    "sg:phone":"+61 7 4163 1175",
    "sg:postcode":"4615",
    "sg:province":"QLD",
    "wof:name":"BP Nanango",
    "wof:placetype":"venue"
},
  "geometry": {"coordinates":[151.99745178200001,-26.6792430878],"type":"Point"}
}