{
  "type": "Feature",
  "properties": {
    "iso:country":"AU",
    "sg:address":"13 Allambie Rd",
    "sg:city":"Allambie Heights",
    "sg:classifiers":[
        {
            "category":"Building & Trades",
            "subcategory":"Construction",
            "type":"Services"
        }
    ],
    "sg:phone":"+61 2 9905 4886",
    "sg:postcode":"2100",
    "sg:province":"NSW",
    "sg:tags":[
        "contractor"
    ],
    "wof:name":"Pickworth Building",
    "wof:placetype":"venue"
},
  "geometry": {"coordinates":[151.26124572800001,-33.7740287781],"type":"Point"}
}