{
  "type": "Feature",
  "properties": {
    "iso:country":"AU",
    "sg:address":"11 Nundah St",
    "sg:city":"Nundah",
    "sg:classifiers":[
        {
            "category":"Shopping",
            "subcategory":"Shoes",
            "type":"Retail Goods"
        }
    ],
    "sg:phone":"+61 7 3260 7899",
    "sg:postcode":"4012",
    "sg:province":"QLD",
    "sg:tags":[
        "footwear"
    ],
    "wof:name":"Grahams Shoes",
    "wof:placetype":"venue"
},
  "geometry": {"coordinates":[153.06138610799999,-27.4005527496],"type":"Point"}
}