{
  "type": "Feature",
  "properties": {
    "addr:full":"Shop 3 108 Wanneroo Rd Tuart Hill WA 6060",
    "addr:housenumber":"shop 3 108",
    "addr:postcode":"6060",
    "addr:street":"Wanneroo Rd",
    "iso:country":"AU",
    "sg:address":"Shop 3 108 Wanneroo Rd",
    "sg:city":"Tuart Hill",
    "sg:classifiers":[
        {
            "category":"Government",
            "subcategory":"Post Office",
            "type":"Public Place"
        }
    ],
    "sg:phone":"+61 8 9349 1194",
    "sg:postcode":"6060",
    "sg:province":"WA",
    "sg:tags":[
        "postal"
    ],
    "wof:name":"Australia Post",
    "wof:placetype":"venue"
},
  "geometry": {"coordinates":[115.842529297,-31.9008235931],"type":"Point"}
}