{
  "type": "Feature",
  "properties": {
    "addr:full":"Lot 49, Old Maitland Rd Mardi NSW 2259",
    "addr:postcode":"2259",
    "addr:street":"Old Maitland Rd",
    "iso:country":"AU",
    "sg:address":"Lot 49, Old Maitland Rd",
    "sg:city":"Mardi",
    "sg:classifiers":[
        {
            "category":"Professional",
            "subcategory":"Engineering",
            "type":"Services"
        }
    ],
    "sg:phone":"+61 2 4353 9447",
    "sg:postcode":"2259",
    "sg:province":"NSW",
    "sg:tags":[
        "refrigeration",
        "engineer"
    ],
    "wof:name":"Regnis Refrigeration (NSW) Pty Ltd",
    "wof:placetype":"venue"
},
  "geometry": {"coordinates":[151.39942932100001,-33.3097381592],"type":"Point"}
}