{
  "type": "Feature",
  "properties": {
    "iso:country":"AU",
    "sg:address":"182- 184 York St",
    "sg:city":"South Melbourne",
    "sg:classifiers":[
        {
            "category":"Manufacturing",
            "subcategory":"Food",
            "type":"Manufacturing & Wholesale Goods"
        }
    ],
    "sg:phone":"+61 3 9699 8889",
    "sg:postcode":"3205",
    "sg:province":"VIC",
    "sg:tags":[
        "function",
        "catering"
    ],
    "wof:name":"A AAABoutown",
    "wof:placetype":"venue"
},
  "geometry": {"coordinates":[144.95576500000001,-37.83173],"type":"Point"}
}