{
  "type": "Feature",
  "properties": {
    "addr:full":"22 Beach Ave Mordialloc VIC 3195",
    "addr:housenumber":"22",
    "addr:postcode":"3195",
    "addr:street":"Beach Ave",
    "iso:country":"AU",
    "sg:address":"22 Beach Ave",
    "sg:city":"Mordialloc",
    "sg:classifiers":[
        {
            "category":"Manufacturing",
            "subcategory":"Glass & Minerals",
            "type":"Manufacturing & Wholesale Goods"
        }
    ],
    "sg:phone":"+61 3 9580 6508",
    "sg:postcode":"3195",
    "sg:province":"VIC",
    "sg:tags":[
        "repair",
        "fibreglass",
        "product"
    ],
    "wof:name":"Ram Fibreglassing Pty Ltd",
    "wof:placetype":"venue"
},
  "geometry": {"coordinates":[145.10104370100001,-38.0083427429],"type":"Point"}
}