{
  "type": "Feature",
  "properties": {
    "iso:country":"AU",
    "sg:address":"331 Bell St",
    "sg:city":"Pascoe Vale South",
    "sg:classifiers":[
        {
            "category":"Professional",
            "subcategory":"Computer Services",
            "type":"Services"
        }
    ],
    "sg:phone":"+61 3 9354 8655",
    "sg:postcode":"3044",
    "sg:province":"VIC",
    "sg:tags":[
        "package",
        "software"
    ],
    "wof:name":"Flexdata Software House & Computer Peripheral",
    "wof:placetype":"venue"
},
  "geometry": {"coordinates":[144.946075439,-37.7393531799],"type":"Point"}
}