{
  "type": "Feature",
  "properties": {
    "addr:full":"6 Gunya St Regents Park NSW 2143",
    "addr:housenumber":"6",
    "addr:postcode":"2143",
    "addr:street":"Gunya St",
    "iso:country":"AU",
    "sg:address":"6 Gunya St",
    "sg:city":"Regents Park",
    "sg:classifiers":[
        {
            "category":"Wholesale",
            "subcategory":"Machinery & Supplies",
            "type":"Manufacturing & Wholesale Goods"
        }
    ],
    "sg:phone":"+61 2 9644 6899",
    "sg:postcode":"2143",
    "sg:province":"NSW",
    "sg:tags":[
        "equipment",
        "hydraulic"
    ],
    "wof:name":"All Filters Sales & Service",
    "wof:placetype":"venue"
},
  "geometry": {"coordinates":[151.02308654800001,-33.8860931396],"type":"Point"}
}