{
  "type": "Feature",
  "properties": {
    "iso:country":"AU",
    "sg:address":"Crestwood Drv",
    "sg:city":"Molendinar",
    "sg:classifiers":[
        {
            "category":"Building & Trades",
            "subcategory":"Construction",
            "type":"Services"
        }
    ],
    "sg:phone":"+61 7 5539 4618",
    "sg:postcode":"4214",
    "sg:province":"QLD",
    "sg:tags":[
        "contractor"
    ],
    "wof:name":"Plantation Homes",
    "wof:placetype":"venue"
},
  "geometry": {"coordinates":[153.36891174300001,-27.9745235443],"type":"Point"}
}