{
  "type": "Feature",
  "properties": {
    "iso:country":"AU",
    "sg:address":"532 Hampton St",
    "sg:city":"Hampton",
    "sg:classifiers":[
        {
            "category":"Professional",
            "subcategory":"Secretarial Services",
            "type":"Services"
        }
    ],
    "sg:phone":"+61 3 9597 0979",
    "sg:postcode":"3188",
    "sg:province":"VIC",
    "sg:tags":[
        "typing"
    ],
    "wof:name":"Society Of Business Communicators",
    "wof:placetype":"venue"
},
  "geometry": {"coordinates":[145.00352477999999,-37.9328422546],"type":"Point"}
}