{
  "type": "Feature",
  "properties": {
    "iso:country":"AU",
    "sg:address":"15 Exford Rd",
    "sg:city":"Melton South",
    "sg:classifiers":[
        {
            "category":"Food & Beverages",
            "subcategory":"Supermarket",
            "type":"Retail Goods"
        }
    ],
    "sg:phone":"+61 3 9743 8611",
    "sg:postcode":"3338",
    "sg:province":"VIC",
    "sg:tags":[
        "grocery",
        "store"
    ],
    "wof:name":"Meltons Licensed Supermarket",
    "wof:placetype":"venue"
},
  "geometry": {"coordinates":[144.57450900000001,-37.705032],"type":"Point"}
}