{
  "type": "Feature",
  "properties": {
    "addr:full":"426 Canterbury Rd Campsie NSW 2194",
    "addr:housenumber":"426",
    "addr:postcode":"2194",
    "addr:street":"Canterbury Rd",
    "iso:country":"AU",
    "sg:address":"426 Canterbury Rd",
    "sg:city":"Campsie",
    "sg:classifiers":[
        {
            "category":"Industrial Area",
            "type":"Public Place"
        }
    ],
    "sg:phone":"+61 2 9718 3028",
    "sg:postcode":"2194",
    "sg:province":"NSW",
    "sg:tags":[
        "protective",
        "clothing"
    ],
    "wof:name":"Helm Uniforms Pty Ltd",
    "wof:placetype":"venue"
},
  "geometry": {"coordinates":[151.105087,-33.918083],"type":"Point"}
}