{
  "type": "Feature",
  "properties": {
    "iso:country":"AU",
    "sg:address":"14 Short St",
    "sg:city":"Grenfell",
    "sg:classifiers":[
        {
            "category":"Wholesale",
            "subcategory":"Machinery & Supplies",
            "type":"Manufacturing & Wholesale Goods"
        }
    ],
    "sg:phone":"+61 2 6343 2328",
    "sg:postcode":"2810",
    "sg:province":"NSW",
    "sg:tags":[
        "agricultural"
    ],
    "wof:name":"Reynolds Tractor & Diesel Service",
    "wof:placetype":"venue"
},
  "geometry": {"coordinates":[148.16392517099999,-33.8937797546],"type":"Point"}
}