{
  "type": "Feature",
  "properties": {
    "addr:full":"87 Church St Parramatta NSW 2150",
    "addr:housenumber":"87",
    "addr:postcode":"2150",
    "addr:street":"Church St",
    "iso:country":"AU",
    "sg:address":"87 Church St",
    "sg:city":"Parramatta",
    "sg:classifiers":[
        {
            "category":"Retail",
            "subcategory":"Driving School",
            "type":"Services"
        }
    ],
    "sg:phone":"+61 2 9893 7588",
    "sg:postcode":"2150",
    "sg:province":"NSW",
    "wof:name":"Motorcycle Learners",
    "wof:placetype":"venue"
},
  "geometry": {"coordinates":[151.044158936,-33.8628616333],"type":"Point"}
}