{
  "type": "Feature",
  "properties": {
    "addr:full":"Port Pacific Building Shop 2 Murray St Port Macquarie NSW 2444",
    "addr:housenumber":"2",
    "addr:postcode":"2444",
    "addr:street":"Murray St",
    "iso:country":"AU",
    "sg:address":"Port Pacific Building Shop 2 Murray St",
    "sg:city":"Port Macquarie",
    "sg:classifiers":[
        {
            "category":"Personal",
            "subcategory":"Massage",
            "type":"Services"
        }
    ],
    "sg:phone":"+61 2 6583 2911",
    "sg:postcode":"2444",
    "sg:province":"NSW",
    "sg:tags":[
        "therapy"
    ],
    "wof:name":"Hewes Barry",
    "wof:placetype":"venue"
},
  "geometry": {"coordinates":[152.91099500000001,-31.428864],"type":"Point"}
}