{
  "type": "Feature",
  "properties": {
    "iso:country":"AU",
    "sg:address":"192 Newmarket Rd",
    "sg:city":"Newmarket",
    "sg:classifiers":[
        {
            "category":"Personal",
            "subcategory":"Beauty Salon",
            "type":"Services"
        }
    ],
    "sg:phone":"+61 7 3356 4842",
    "sg:postcode":"4051",
    "sg:province":"QLD",
    "sg:tags":[
        "hairdresser"
    ],
    "wof:name":"Close Clip Saloon",
    "wof:placetype":"venue"
},
  "geometry": {"coordinates":[153.02049255399999,-27.4366531372],"type":"Point"}
}