{
  "type": "Feature",
  "properties": {
    "iso:country":"AU",
    "sg:address":"26 Akma Crt",
    "sg:city":"Taylors Lakes",
    "sg:classifiers":[
        {
            "category":"Professional",
            "subcategory":"Computer Services",
            "type":"Services"
        }
    ],
    "sg:phone":"+61 3 9390 1198",
    "sg:postcode":"3038",
    "sg:province":"VIC",
    "sg:tags":[
        "training"
    ],
    "wof:name":"Disk-Co-Tech Pty Ltd",
    "wof:placetype":"venue"
},
  "geometry": {"coordinates":[144.79612700000001,-37.707256],"type":"Point"}
}