{
  "type": "Feature",
  "properties": {
    "iso:country":"AU",
    "sg:address":"282 Richardson St",
    "sg:city":"Middle Park",
    "sg:classifiers":[
        {
            "category":"Health Services",
            "subcategory":"Chiropractor",
            "type":"Services"
        }
    ],
    "sg:phone":"+61 3 9682 8866",
    "sg:postcode":"3206",
    "sg:province":"VIC",
    "wof:name":"Doherty Sonya Dr",
    "wof:placetype":"venue"
},
  "geometry": {"coordinates":[144.963791,-37.850643],"type":"Point"}
}