{
  "type": "Feature",
  "properties": {
    "iso:country":"AU",
    "sg:address":"1/ 194 Turf St",
    "sg:city":"Grafton",
    "sg:classifiers":[
        {
            "category":"Social Services",
            "subcategory":"Retirement Home",
            "type":"Services"
        }
    ],
    "sg:phone":"+61 2 6642 5991",
    "sg:postcode":"2460",
    "sg:province":"NSW",
    "sg:tags":[
        "village"
    ],
    "wof:name":"Clarence Village Association Inc",
    "wof:placetype":"venue"
},
  "geometry": {"coordinates":[152.93580627399999,-29.6723041534],"type":"Point"}
}