{
  "type": "Feature",
  "properties": {
    "iso:country":"AU",
    "sg:address":"Clarke St",
    "sg:city":"Northcote",
    "sg:classifiers":[
        {
            "category":"Education",
            "subcategory":"Kindergarten",
            "type":"Public Place"
        }
    ],
    "sg:phone":"+61 3 9486 4147",
    "sg:postcode":"3070",
    "sg:province":"VIC",
    "sg:tags":[
        "pre-schools"
    ],
    "wof:name":"Westgarth Kindergarten",
    "wof:placetype":"venue"
},
  "geometry": {"coordinates":[144.998215,-37.776585],"type":"Point"}
}