{
  "type": "Feature",
  "properties": {
    "addr:full":"22 Nixon Rd Wingfield SA 5013",
    "addr:housenumber":"22",
    "addr:postcode":"5013",
    "addr:street":"Nixon Rd",
    "iso:country":"AU",
    "sg:address":"22 Nixon Rd",
    "sg:city":"Wingfield",
    "sg:classifiers":[
        {
            "category":"Building & Trades",
            "subcategory":"Equipment Rental",
            "type":"Services"
        }
    ],
    "sg:phone":"+61 8 8347 3388",
    "sg:postcode":"5013",
    "sg:province":"SA",
    "sg:tags":[
        "repairing",
        "changing",
        "retreading",
        "tyre"
    ],
    "wof:name":"Jackson Garage Equipment Pty Ltd",
    "wof:placetype":"venue"
},
  "geometry": {"coordinates":[138.557830811,-34.8353118896],"type":"Point"}
}