{
  "type": "Feature",
  "properties": {
    "addr:full":"68 Railway Ave (Cnr Stanley Ave) Ringwood East VIC 3135",
    "addr:housenumber":"68",
    "addr:postcode":"3135",
    "addr:street":"Railway Ave Cnr Stanley Ave",
    "iso:country":"AU",
    "sg:address":"68 Railway Ave (Cnr Stanley Ave)",
    "sg:city":"Ringwood East",
    "sg:classifiers":[
        {
            "category":"Health Services",
            "subcategory":"Health Practitioner",
            "type":"Services"
        }
    ],
    "sg:phone":"+61 3 9879 4544",
    "sg:postcode":"3135",
    "sg:province":"VIC",
    "sg:tags":[
        "physiotherapist"
    ],
    "wof:name":"Yeap Eric",
    "wof:placetype":"venue"
},
  "geometry": {"coordinates":[145.250534058,-37.8122634888],"type":"Point"}
}