{
  "type": "Feature",
  "properties": {
    "addr:full":"67 James Cook Drv Endeavour Hills VIC 3802",
    "addr:housenumber":"67",
    "addr:postcode":"3802",
    "addr:street":"James Cook Drv",
    "iso:country":"AU",
    "sg:address":"67 James Cook Drv",
    "sg:city":"Endeavour Hills",
    "sg:classifiers":[
        {
            "category":"Fast Food",
            "type":"Food & Drink"
        }
    ],
    "sg:phone":"+61 3 9700 1760",
    "sg:postcode":"3802",
    "sg:province":"VIC",
    "sg:tags":[
        "away",
        "take"
    ],
    "wof:name":"Mini Mart",
    "wof:placetype":"venue"
},
  "geometry": {"coordinates":[145.245437622,-37.9802932739],"type":"Point"}
}