{
  "type": "Feature",
  "properties": {
    "addr:full":"39 Avondale Rd Cooranbong NSW 2265",
    "addr:housenumber":"39",
    "addr:postcode":"2265",
    "addr:street":"Avondale Rd",
    "iso:country":"AU",
    "sg:address":"39 Avondale Rd",
    "sg:city":"Cooranbong",
    "sg:classifiers":[
        {
            "category":"Farming",
            "subcategory":"Farm & Veterinary Services",
            "type":"Manufacturing & Wholesale Goods"
        }
    ],
    "sg:phone":"+61 2 4977 1286",
    "sg:postcode":"2265",
    "sg:province":"NSW",
    "sg:tags":[
        "worm"
    ],
    "wof:name":"Good Earth Worm Company The",
    "wof:placetype":"venue"
},
  "geometry": {"coordinates":[151.46284499999999,-33.072945],"type":"Point"}
}