{
  "type": "Feature",
  "properties": {
    "addr:full":"52 Tingal Rd Wynnum QLD 4178",
    "addr:housenumber":"52",
    "addr:postcode":"4178",
    "addr:street":"Tingal Rd",
    "iso:country":"AU",
    "sg:address":"52 Tingal Rd",
    "sg:city":"Wynnum",
    "sg:classifiers":[
        {
            "category":"Professional",
            "subcategory":"Accounting & Tax Preparation",
            "type":"Services"
        }
    ],
    "sg:phone":"+61 7 3893 7200",
    "sg:postcode":"4178",
    "sg:province":"QLD",
    "sg:tags":[
        "accountant",
        "auditor"
    ],
    "wof:name":"Vagg Accounting",
    "wof:placetype":"venue"
},
  "geometry": {"coordinates":[153.17344665499999,-27.4481048584],"type":"Point"}
}