{
  "type": "Feature",
  "properties": {
    "addr:full":"118- 120 Argyle St Fitzroy VIC 3065",
    "addr:housenumber":"120",
    "addr:postcode":"3065",
    "addr:street":"Argyle St",
    "iso:country":"AU",
    "sg:address":"118- 120 Argyle St",
    "sg:city":"Fitzroy",
    "sg:classifiers":[
        {
            "category":"Professional",
            "type":"Services"
        }
    ],
    "sg:phone":"+61 3 9416 0403",
    "sg:postcode":"3065",
    "sg:province":"VIC",
    "sg:tags":[
        "mail",
        "contractor"
    ],
    "wof:name":"Pack & Deliver",
    "wof:placetype":"venue"
},
  "geometry": {"coordinates":[144.97952270499999,-37.7977333069],"type":"Point"}
}