{
  "type": "Feature",
  "properties": {
    "addr:full":"7 Archibald Pl Heatherbrae NSW 2324",
    "addr:housenumber":"7",
    "addr:postcode":"2324",
    "addr:street":"Archibald Pl",
    "iso:country":"AU",
    "sg:address":"7 Archibald Pl",
    "sg:city":"Heatherbrae",
    "sg:classifiers":[
        {
            "category":"Autos & Motor Vehicles",
            "subcategory":"Automobile Sales",
            "type":"Retail Goods"
        }
    ],
    "sg:phone":"+61 2 4983 1377",
    "sg:postcode":"2324",
    "sg:province":"NSW",
    "sg:tags":[
        "equipment",
        "trailer"
    ],
    "wof:name":"Marlin Trailers",
    "wof:placetype":"venue"
},
  "geometry": {"coordinates":[151.73806762699999,-32.7843666077],"type":"Point"}
}