{
  "type": "Feature",
  "properties": {
    "iso:country":"AU",
    "sg:address":"17 Bundaroo St",
    "sg:city":"Bowral",
    "sg:classifiers":[
        {
            "category":"Professional",
            "subcategory":"Art Services",
            "type":"Services"
        }
    ],
    "sg:phone":"+61 2 4862 1452",
    "sg:postcode":"2576",
    "sg:province":"NSW",
    "sg:tags":[
        "interior",
        "decorator"
    ],
    "wof:name":"Campbell & Robertson Fabrics",
    "wof:placetype":"venue"
},
  "geometry": {"coordinates":[150.41995239299999,-34.4769477844],"type":"Point"}
}