{
  "type": "Feature",
  "properties": {
    "iso:country":"AU",
    "sg:address":"Calk St",
    "sg:city":"Coburg",
    "sg:classifiers":[
        {
            "category":"Recreation",
            "type":"Entertainment"
        }
    ],
    "sg:phone":"+61 3 8300 7388",
    "sg:postcode":"3058",
    "sg:province":"VIC",
    "sg:tags":[
        "hire",
        "tour",
        "motor",
        "cycle"
    ],
    "wof:name":"Bike - Cam",
    "wof:placetype":"venue"
},
  "geometry": {"coordinates":[144.98248290999999,-37.7259864807],"type":"Point"}
}