{
  "type": "Feature",
  "properties": {
    "addr:full":"2934 Logan Rd Underwood QLD 4119",
    "addr:housenumber":"2934",
    "addr:postcode":"4119",
    "addr:street":"Logan Rd",
    "iso:country":"AU",
    "sg:address":"2934 Logan Rd",
    "sg:city":"Underwood",
    "sg:classifiers":[
        {
            "category":"Home & Garden",
            "subcategory":"Carpets & Floor Coverings",
            "type":"Retail Goods"
        }
    ],
    "sg:phone":"+61 7 3341 2177",
    "sg:postcode":"4119",
    "sg:province":"QLD",
    "sg:tags":[
        "tile",
        "wall"
    ],
    "wof:name":"Abetta Carpet & Tile Court",
    "wof:placetype":"venue"
},
  "geometry": {"coordinates":[153.113082886,-27.6088638306],"type":"Point"}
}