{
  "type": "Feature",
  "properties": {
    "iso:country":"AU",
    "sg:address":"83 Mitchell St",
    "sg:city":"Northcote",
    "sg:classifiers":[
        {
            "category":"Building & Trades",
            "subcategory":"Cleaning & Sanitation",
            "type":"Services"
        }
    ],
    "sg:phone":"+61 3 9481 6424",
    "sg:postcode":"3070",
    "sg:province":"VIC",
    "sg:tags":[
        "cleaner",
        "repairer",
        "roof"
    ],
    "wof:name":"C & N Davey",
    "wof:placetype":"venue"
},
  "geometry": {"coordinates":[145.005066,-37.772648],"type":"Point"}
}