{
  "type": "Feature",
  "properties": {
    "addr:full":"101 Patrick St Laidley QLD 4341",
    "addr:housenumber":"101",
    "addr:postcode":"4341",
    "addr:street":"Patrick St",
    "iso:country":"AU",
    "sg:address":"101 Patrick St",
    "sg:city":"Laidley",
    "sg:classifiers":[
        {
            "category":"Real Estate",
            "subcategory":"Real Estate Agent",
            "type":"Services"
        }
    ],
    "sg:phone":"+61 7 5465 1800",
    "sg:postcode":"4341",
    "sg:province":"QLD",
    "wof:name":"Elders Real Estate",
    "wof:placetype":"venue"
},
  "geometry": {"coordinates":[152.39364624000001,-27.6315937042],"type":"Point"}
}