{
  "type": "Feature",
  "properties": {
    "addr:full":"169 Bosworth Rd Bairnsdale VIC 3875",
    "addr:housenumber":"169",
    "addr:postcode":"3875",
    "addr:street":"Bosworth Rd",
    "iso:country":"AU",
    "sg:address":"169 Bosworth Rd",
    "sg:city":"Bairnsdale",
    "sg:classifiers":[
        {
            "category":"Shopping",
            "subcategory":"Crafts & Fabrics",
            "type":"Retail Goods"
        }
    ],
    "sg:phone":"+61 3 5152 4704",
    "sg:postcode":"3875",
    "sg:province":"VIC",
    "sg:tags":[
        "synthetic",
        "canvas",
        "product"
    ],
    "wof:name":"Murphy K & L",
    "wof:placetype":"venue"
},
  "geometry": {"coordinates":[147.60121154800001,-37.8378410339],"type":"Point"}
}