{
  "type": "Feature",
  "properties": {
    "addr:full":"Great Western Hwy Bathurst NSW 2795",
    "addr:postcode":"2795",
    "addr:street":"Great Western Hwy",
    "iso:country":"AU",
    "sg:address":"Great Western Hwy",
    "sg:city":"Bathurst",
    "sg:classifiers":[
        {
            "category":"Communications",
            "subcategory":"News Services",
            "type":"Services"
        }
    ],
    "sg:phone":"+61 2 6332 1444",
    "sg:postcode":"2795",
    "sg:province":"NSW",
    "sg:tags":[
        "information",
        "tourist",
        "attractions"
    ],
    "wof:name":"Visitor Information Centres",
    "wof:placetype":"venue"
},
  "geometry": {"coordinates":[149.616744995,-33.4194297791],"type":"Point"}
}