{
  "type": "Feature",
  "properties": {
    "iso:country":"AU",
    "sg:address":"20 Kurri St",
    "sg:city":"Loftus",
    "sg:classifiers":[
        {
            "category":"Health Services",
            "subcategory":"Doctor",
            "type":"Services"
        }
    ],
    "sg:phone":"+61 2 9542 2663",
    "sg:postcode":"2232",
    "sg:province":"NSW",
    "sg:tags":[
        "occupational",
        "safety"
    ],
    "wof:name":"Workplace Risk Management Services Pty Ltd",
    "wof:placetype":"venue"
},
  "geometry": {"coordinates":[151.045043945,-34.0508384705],"type":"Point"}
}