{
  "type": "Feature",
  "properties": {
    "iso:country":"AU",
    "sg:address":"26 Augusta St",
    "sg:city":"Willetton",
    "sg:classifiers":[
        {
            "category":"Building & Trades",
            "subcategory":"Plumbing",
            "type":"Services"
        }
    ],
    "sg:phone":"+61 8 9457 3251",
    "sg:postcode":"6155",
    "sg:province":"WA",
    "sg:tags":[
        "plumber",
        "gasfitters"
    ],
    "wof:name":"I.G. Greeve",
    "wof:placetype":"venue"
},
  "geometry": {"coordinates":[115.880257,-32.043102],"type":"Point"}
}