{
  "type": "Feature",
  "properties": {
    "iso:country":"AU",
    "sg:address":"150 Liverpool St",
    "sg:city":"Scone",
    "sg:classifiers":[
        {
            "category":"Professional",
            "subcategory":"Accounting & Tax Preparation",
            "type":"Services"
        }
    ],
    "sg:phone":"+61 2 6545 1411",
    "sg:postcode":"2337",
    "sg:province":"NSW",
    "sg:tags":[
        "consultant",
        "taxation"
    ],
    "wof:name":"David Cantwell & Co",
    "wof:placetype":"venue"
},
  "geometry": {"coordinates":[150.87022399899999,-32.0509185791],"type":"Point"}
}