{
  "type": "Feature",
  "properties": {
    "iso:country":"AU",
    "sg:address":"5th Floor 606 St Kilda Rd",
    "sg:city":"Melbourne",
    "sg:classifiers":[
        {
            "category":"Travel",
            "subcategory":"Travel Agent",
            "type":"Entertainment"
        }
    ],
    "sg:phone":"+61 3 8686 1566",
    "sg:postcode":"3000",
    "sg:province":"VIC",
    "sg:tags":[
        "consultant"
    ],
    "wof:name":"NGT Travel Conferences & Incentives",
    "wof:placetype":"venue"
},
  "geometry": {"coordinates":[144.980636597,-37.8511695862],"type":"Point"}
}