{
  "type": "Feature",
  "properties": {
    "iso:country":"AU",
    "sg:address":"Bowker St",
    "sg:city":"North Brighton",
    "sg:classifiers":[
        {
            "category":"Education",
            "subcategory":"School",
            "type":"Public Place"
        }
    ],
    "sg:phone":"+61 8 8296 8904",
    "sg:postcode":"5048",
    "sg:province":"SA",
    "sg:tags":[
        "state",
        "except",
        "nsw"
    ],
    "wof:name":"Paringa Park Primary",
    "wof:placetype":"venue"
},
  "geometry": {"coordinates":[138.52262899999999,-35.002102],"type":"Point"}
}