{
  "type": "Feature",
  "properties": {
    "iso:country":"AU",
    "sg:address":"32 Ford St",
    "sg:city":"Beechworth",
    "sg:classifiers":[
        {
            "category":"Cafe",
            "type":"Food & Drink"
        }
    ],
    "sg:phone":"+61 3 5728 2299",
    "sg:postcode":"3747",
    "sg:province":"VIC",
    "wof:name":"Top End Deli Cafe",
    "wof:placetype":"venue"
},
  "geometry": {"coordinates":[146.68457000000001,-36.361385],"type":"Point"}
}