{
  "type": "Feature",
  "properties": {
    "addr:full":"255 Darling St Balmain NSW 2041",
    "addr:housenumber":"255",
    "addr:postcode":"2041",
    "addr:street":"Darling St",
    "iso:country":"AU",
    "sg:address":"255 Darling St",
    "sg:city":"Balmain",
    "sg:classifiers":[
        {
            "category":"Travel",
            "subcategory":"Hotels & Motels",
            "type":"Entertainment"
        }
    ],
    "sg:phone":"+61 2 9810 1749",
    "sg:postcode":"2041",
    "sg:province":"NSW",
    "sg:tags":[
        "accommodation"
    ],
    "wof:name":"Balmain Monkey Bar",
    "wof:placetype":"venue"
},
  "geometry": {"coordinates":[151.18211400000001,-33.857586],"type":"Point"}
}