{
  "type": "Feature",
  "properties": {
    "addr:full":"604 Pacific Hwy Belmont NSW 2280",
    "addr:housenumber":"604",
    "addr:postcode":"2280",
    "addr:street":"Pacific Hwy",
    "iso:country":"AU",
    "sg:address":"604 Pacific Hwy",
    "sg:city":"Belmont",
    "sg:classifiers":[
        {
            "category":"Professional",
            "subcategory":"Computer Services",
            "type":"Services"
        }
    ],
    "sg:phone":"+61 2 4945 3377",
    "sg:postcode":"2280",
    "sg:province":"NSW",
    "sg:tags":[
        "package",
        "software"
    ],
    "wof:name":"Bailin Computers",
    "wof:placetype":"venue"
},
  "geometry": {"coordinates":[151.66017150900001,-33.037197113],"type":"Point"}
}