{
  "type": "Feature",
  "properties": {
    "addr:full":"17 Muros Pl Midvale WA 6056",
    "addr:housenumber":"17",
    "addr:postcode":"6056",
    "addr:street":"Pl",
    "iso:country":"AU",
    "sg:address":"17 Muros Pl",
    "sg:city":"Midvale",
    "sg:classifiers":[
        {
            "category":"Retail",
            "subcategory":"Auto Repair",
            "type":"Services"
        }
    ],
    "sg:phone":"+61 8 9250 6455",
    "sg:postcode":"6056",
    "sg:province":"WA",
    "sg:tags":[
        "electrical"
    ],
    "wof:name":"G M Mining Electrics",
    "wof:placetype":"venue"
},
  "geometry": {"coordinates":[116.031913757,-31.8880367279],"type":"Point"}
}