{
  "type": "Feature",
  "properties": {
    "addr:full":"Shop 29 Westfield Shoppintown, Toombul QLD 4012",
    "addr:housenumber":"shop 29",
    "addr:postcode":"4012",
    "addr:street":"Westfield Shoppintown",
    "iso:country":"AU",
    "sg:address":"Shop 29",
    "sg:city":"Westfield Shoppintown, Toombul",
    "sg:classifiers":[
        {
            "category":"Shopping",
            "subcategory":"Mobile Phones",
            "type":"Retail Goods"
        }
    ],
    "sg:phone":"+61 7 3630 4266",
    "sg:postcode":"4012",
    "sg:province":"QLD",
    "sg:tags":[
        "telephone",
        "accessory"
    ],
    "wof:name":"Vodafone Digicall",
    "wof:placetype":"venue"
},
  "geometry": {"coordinates":[153.05982971200001,-27.4076595306],"type":"Point"}
}