{
  "type": "Feature",
  "properties": {
    "addr:full":"PO Box 4224 Frankston South VIC 3199",
    "addr:postcode":"3199",
    "iso:country":"AU",
    "sg:address":"PO Box 4224",
    "sg:city":"Frankston South",
    "sg:classifiers":[
        {
            "category":"Health Services",
            "subcategory":"Doctor",
            "type":"Services"
        }
    ],
    "sg:phone":"+61 3 5971 2100",
    "sg:postcode":"3199",
    "sg:province":"VIC",
    "sg:tags":[
        "nurse",
        "nursing"
    ],
    "wof:name":"Caring For You",
    "wof:placetype":"venue"
},
  "geometry": {"coordinates":[145.146118164,-38.1903152466],"type":"Point"}
}