{
  "type": "Feature",
  "properties": {
    "iso:country":"AU",
    "sg:address":"Unit 7/ 8 Clare Mace Crs",
    "sg:city":"Berkeley Vale",
    "sg:classifiers":[
        {
            "category":"Home & Garden",
            "subcategory":"Building Materials",
            "type":"Retail Goods"
        }
    ],
    "sg:phone":"+61 2 4389 1378",
    "sg:postcode":"2261",
    "sg:province":"NSW",
    "sg:tags":[
        "insect",
        "screen"
    ],
    "wof:name":"Allcoast Security Doors & Blinds",
    "wof:placetype":"venue"
},
  "geometry": {"coordinates":[151.438583,-33.344639],"type":"Point"}
}