{
  "type": "Feature",
  "properties": {
    "addr:full":"5 Farringdon St Largs North SA 5016",
    "addr:housenumber":"5",
    "addr:postcode":"5016",
    "addr:street":"Farringdon St",
    "iso:country":"AU",
    "sg:address":"5 Farringdon St",
    "sg:city":"Largs North",
    "sg:classifiers":[
        {
            "category":"Shopping",
            "subcategory":"Musical Instruments",
            "type":"Retail Goods"
        }
    ],
    "sg:phone":"+61 8 8248 1670",
    "sg:postcode":"5016",
    "sg:province":"SA",
    "sg:tags":[
        "musician",
        "agent"
    ],
    "wof:name":"Adelaide's Just Jazz Bands' Agency",
    "wof:placetype":"venue"
},
  "geometry": {"coordinates":[138.49253845199999,-34.8173751831],"type":"Point"}
}