{
  "type": "Feature",
  "properties": {
    "iso:country":"AU",
    "sg:address":"Room 46, 3rd Floor, Holyman House, 52-56 Brisbane St",
    "sg:city":"Launceston",
    "sg:classifiers":[
        {
            "category":"Health Services",
            "subcategory":"Health Practitioner",
            "type":"Services"
        }
    ],
    "sg:phone":"+61 417 521 485",
    "sg:postcode":"7250",
    "sg:province":"TAS",
    "sg:tags":[
        "psychotherapist"
    ],
    "wof:name":"Rosalind de Virieux",
    "wof:placetype":"venue"
},
  "geometry": {"coordinates":[147.11703491200001,-41.473991394],"type":"Point"}
}