{
  "type": "Feature",
  "properties": {
    "addr:full":"81 Maroondah Hwy Croydon VIC 3136",
    "addr:housenumber":"81",
    "addr:postcode":"3136",
    "addr:street":"Maroondah Hwy",
    "iso:country":"AU",
    "sg:address":"81 Maroondah Hwy",
    "sg:city":"Croydon",
    "sg:classifiers":[
        {
            "category":"Retail",
            "subcategory":"Auto Repair",
            "type":"Services"
        }
    ],
    "sg:phone":"+61 3 9725 4007",
    "sg:postcode":"3136",
    "sg:province":"VIC",
    "sg:tags":[
        "camper-trailers",
        "caravan",
        "servicing"
    ],
    "wof:name":"Caravan Service Centres-Vic",
    "wof:placetype":"venue"
},
  "geometry": {"coordinates":[145.26654052699999,-37.7894515991],"type":"Point"}
}