{
  "type": "Feature",
  "properties": {
    "iso:country":"AU",
    "sg:address":"18 Morison St",
    "sg:city":"Maffra",
    "sg:classifiers":[
        {
            "category":"Building & Trades",
            "subcategory":"Construction",
            "type":"Services"
        }
    ],
    "sg:phone":"+61 407 846 184",
    "sg:postcode":"3860",
    "sg:province":"VIC",
    "sg:tags":[
        "contractor"
    ],
    "wof:name":"Corker Constructions",
    "wof:placetype":"venue"
},
  "geometry": {"coordinates":[146.989105225,-37.9572753906],"type":"Point"}
}