{
  "type": "Feature",
  "properties": {
    "iso:country":"AU",
    "sg:address":"Beenleigh Family Practice, 9 James St",
    "sg:city":"Beenleigh",
    "sg:classifiers":[
        {
            "category":"Health Services",
            "subcategory":"Health Practitioner",
            "type":"Services"
        }
    ],
    "sg:phone":"+61 417 078 956",
    "sg:postcode":"4207",
    "sg:province":"QLD",
    "sg:tags":[
        "dietitian"
    ],
    "wof:name":"Aloysa Hourigan+",
    "wof:placetype":"venue"
},
  "geometry": {"coordinates":[153.199462891,-27.7178020477],"type":"Point"}
}