{
  "type": "Feature",
  "properties": {
    "iso:country":"AU",
    "sg:address":"235 Jones St",
    "sg:city":"Ultimo",
    "sg:classifiers":[
        {
            "category":"Professional",
            "subcategory":"Accounting & Tax Preparation",
            "type":"Services"
        }
    ],
    "sg:phone":"+61 2 9211 5957",
    "sg:postcode":"2007",
    "sg:province":"NSW",
    "sg:tags":[
        "accountant",
        "auditor"
    ],
    "wof:name":"Cox Peter & Lemberg",
    "wof:placetype":"venue"
},
  "geometry": {"coordinates":[151.19909668,-33.8828315735],"type":"Point"}
}