{
  "type": "Feature",
  "properties": {
    "addr:full":"59 North West Coastal Hwy Geraldton WA 6530",
    "addr:housenumber":"59",
    "addr:postcode":"6530",
    "addr:street":"North West Coastal Hwy",
    "iso:country":"AU",
    "sg:address":"59 North West Coastal Hwy",
    "sg:city":"Geraldton",
    "sg:classifiers":[
        {
            "category":"Professional",
            "subcategory":"Computer Services",
            "type":"Services"
        }
    ],
    "sg:phone":"+61 8 9964 2722",
    "sg:postcode":"6530",
    "sg:province":"WA",
    "sg:tags":[
        "on-line",
        "provider"
    ],
    "wof:name":"Modnet Internet Services",
    "wof:placetype":"venue"
},
  "geometry": {"coordinates":[114.625930786,-28.7762870789],"type":"Point"}
}