{
  "type": "Feature",
  "properties": {
    "addr:full":"2 Little St Dulwich Hill NSW 2203",
    "addr:housenumber":"2",
    "addr:postcode":"2203",
    "addr:street":"Little St",
    "iso:country":"AU",
    "sg:address":"2 Little St",
    "sg:city":"Dulwich Hill",
    "sg:classifiers":[
        {
            "category":"Manufacturing",
            "subcategory":"Wood Products",
            "type":"Manufacturing & Wholesale Goods"
        }
    ],
    "sg:phone":"+61 2 9550 0043",
    "sg:postcode":"2203",
    "sg:province":"NSW",
    "sg:tags":[
        "polisher",
        "french"
    ],
    "wof:name":"Wilfix Restorations",
    "wof:placetype":"venue"
},
  "geometry": {"coordinates":[151.14151000000001,-33.898342],"type":"Point"}
}