{
  "type": "Feature",
  "properties": {
    "iso:country":"AU",
    "sg:address":"228 Seventeen Miles Rocks Rd",
    "sg:city":"Oxley",
    "sg:classifiers":[
        {
            "category":"Organizations",
            "subcategory":"Community Association",
            "type":"Services"
        }
    ],
    "sg:phone":"+61 412 618 610",
    "sg:postcode":"4075",
    "sg:province":"QLD",
    "sg:tags":[
        "equipment",
        "system",
        "vacuum"
    ],
    "wof:name":"R Blanchard Manufacturing",
    "wof:placetype":"venue"
},
  "geometry": {"coordinates":[152.959381103,-27.5532798767],"type":"Point"}
}