{
  "type": "Feature",
  "properties": {
    "addr:full":"110 Hill St Toowoomba QLD 4350",
    "addr:housenumber":"110",
    "addr:postcode":"4350",
    "addr:street":"Hill St",
    "iso:country":"AU",
    "sg:address":"110 Hill St",
    "sg:city":"Toowoomba",
    "sg:classifiers":[
        {
            "category":"Social Services",
            "subcategory":"Adult Care",
            "type":"Services"
        }
    ],
    "sg:phone":"+61 7 4632 4599",
    "sg:postcode":"4350",
    "sg:province":"QLD",
    "sg:tags":[
        "towing"
    ],
    "wof:name":"Newtown Towing Service",
    "wof:placetype":"venue"
},
  "geometry": {"coordinates":[151.93696600000001,-27.56053],"type":"Point"}
}