{
  "type": "Feature",
  "properties": {
    "addr:full":"65 Lynn St Boggabri NSW 2382",
    "addr:housenumber":"65",
    "addr:postcode":"2382",
    "addr:street":"Lynn St",
    "iso:country":"AU",
    "sg:address":"65 Lynn St",
    "sg:city":"Boggabri",
    "sg:classifiers":[
        {
            "category":"Building & Trades",
            "subcategory":"Construction",
            "type":"Services"
        }
    ],
    "sg:phone":"+61 429 118 219",
    "sg:postcode":"2382",
    "sg:province":"NSW",
    "sg:tags":[
        "earth",
        "excavating",
        "moving",
        "contractor"
    ],
    "wof:name":"Bird Chris",
    "wof:placetype":"venue"
},
  "geometry": {"coordinates":[150.04722595199999,-30.7033824921],"type":"Point"}
}