{
  "type": "Feature",
  "properties": {
    "addr:full":"64 Mohair Rd Lockwood VIC 3551",
    "addr:housenumber":"64",
    "addr:postcode":"3551",
    "addr:street":"Mohair Rd",
    "iso:country":"AU",
    "sg:address":"64 Mohair Rd",
    "sg:city":"Lockwood",
    "sg:classifiers":[
        {
            "category":"Social Services",
            "subcategory":"Child Care",
            "type":"Services"
        }
    ],
    "sg:phone":"+61 3 5435 3506",
    "sg:postcode":"3551",
    "sg:province":"VIC",
    "sg:tags":[
        "childbirth"
    ],
    "wof:name":"Robyn Smith",
    "wof:placetype":"venue"
},
  "geometry": {"coordinates":[144.14541625999999,-36.8141517639],"type":"Point"}
}