{
  "type": "Feature",
  "properties": {
    "iso:country":"AU",
    "sg:address":"15 Dawson St South",
    "sg:city":"Ballarat",
    "sg:classifiers":[
        {
            "category":"Health Services",
            "subcategory":"Health Practitioner",
            "type":"Services"
        }
    ],
    "sg:phone":"+61 3 5337 2913",
    "sg:postcode":"3350",
    "sg:province":"VIC",
    "sg:tags":[
        "psychologist"
    ],
    "wof:name":"Duckett Therese Psychologist",
    "wof:placetype":"venue"
},
  "geometry": {"coordinates":[143.853485,-37.559658],"type":"Point"}
}