{
  "type": "Feature",
  "properties": {
    "addr:full":"Lvl 6/ 461 Bourke St Melbourne VIC 3000",
    "addr:housenumber":"/ 461",
    "addr:postcode":"3000",
    "addr:street":"Bourke St",
    "iso:country":"AU",
    "sg:address":"Lvl 6/ 461 Bourke St",
    "sg:city":"Melbourne",
    "sg:classifiers":[
        {
            "category":"Education",
            "subcategory":"Special Training",
            "type":"Public Place"
        }
    ],
    "sg:phone":"+61 3 9600 1811",
    "sg:postcode":"3000",
    "sg:province":"VIC",
    "sg:tags":[
        "development"
    ],
    "wof:name":"Jetset Training College",
    "wof:placetype":"venue"
},
  "geometry": {"coordinates":[144.960205078,-37.8152389526],"type":"Point"}
}