{
  "type": "Feature",
  "properties": {
    "addr:full":"130 Ballarat Rd Hamilton VIC 3300",
    "addr:housenumber":"130",
    "addr:postcode":"3300",
    "addr:street":"Ballarat Rd",
    "iso:country":"AU",
    "sg:address":"130 Ballarat Rd",
    "sg:city":"Hamilton",
    "sg:classifiers":[
        {
            "category":"Retail",
            "subcategory":"Storage",
            "type":"Services"
        }
    ],
    "sg:phone":"+61 3 5571 1711",
    "sg:postcode":"3300",
    "sg:province":"VIC",
    "sg:tags":[
        "removal",
        "furniture"
    ],
    "wof:name":"Ararat Removals",
    "wof:placetype":"venue"
},
  "geometry": {"coordinates":[142.04879760700001,-37.7438278198],"type":"Point"}
}