{
  "type": "Feature",
  "properties": {
    "addr:full":"PO Box 111 Hughenden QLD 4821",
    "addr:postcode":"4821",
    "iso:country":"AU",
    "sg:address":"PO Box 111",
    "sg:city":"Hughenden",
    "sg:classifiers":[
        {
            "category":"Autos & Motor Vehicles",
            "subcategory":"Fuel & Gas Station",
            "type":"Retail Goods"
        }
    ],
    "sg:phone":"+61 7 4741 1311",
    "sg:postcode":"4821",
    "sg:province":"QLD",
    "wof:name":"BP Australia Limited",
    "wof:placetype":"venue"
},
  "geometry": {"coordinates":[144.191604614,-20.8422698975],"type":"Point"}
}