{
  "type": "Feature",
  "properties": {
    "addr:full":"8 Cornwallis St Redfern NSW 2016",
    "addr:housenumber":"8",
    "addr:postcode":"2016",
    "addr:street":"Cornwallis St",
    "iso:country":"AU",
    "sg:address":"8 Cornwallis St",
    "sg:city":"Redfern",
    "sg:classifiers":[
        {
            "category":"Shopping",
            "subcategory":"Computers & Home Electronics",
            "type":"Retail Goods"
        }
    ],
    "sg:phone":"+61 2 9209 4446",
    "sg:postcode":"2016",
    "sg:province":"NSW",
    "sg:tags":[
        "equipment",
        "supply"
    ],
    "wof:name":"Net Leverage Pty Ltd",
    "wof:placetype":"venue"
},
  "geometry": {"coordinates":[151.197875977,-33.8938598633],"type":"Point"}
}