{
  "type": "Feature",
  "properties": {
    "addr:full":"Craig St Bendigo VIC 3550",
    "addr:postcode":"3550",
    "addr:street":"Craig St",
    "iso:country":"AU",
    "sg:address":"Craig St",
    "sg:city":"Bendigo",
    "sg:classifiers":[
        {
            "category":"Home & Garden",
            "subcategory":"Building Materials",
            "type":"Retail Goods"
        }
    ],
    "sg:phone":"+61 3 5442 2288",
    "sg:postcode":"3550",
    "sg:province":"VIC",
    "sg:tags":[
        "fencing"
    ],
    "wof:name":"Onesteel Metaland",
    "wof:placetype":"venue"
},
  "geometry": {"coordinates":[144.262329102,-36.7415847778],"type":"Point"}
}