{
  "type": "Feature",
  "properties": {
    "iso:country":"AU",
    "sg:address":"Suite 4, 39 Market St",
    "sg:city":"Wollongong",
    "sg:classifiers":[
        {
            "category":"Professional",
            "subcategory":"Accounting & Tax Preparation",
            "type":"Services"
        }
    ],
    "sg:phone":"+61 2 4226 4240",
    "sg:postcode":"2500",
    "sg:province":"NSW",
    "sg:tags":[
        "accountant",
        "auditor"
    ],
    "wof:name":"K.I.S. Accounting Systems",
    "wof:placetype":"venue"
},
  "geometry": {"coordinates":[150.898056,-34.424149],"type":"Point"}
}