{
  "type": "Feature",
  "properties": {
    "iso:country":"AU",
    "sg:address":"374 Warrigal Rd",
    "sg:city":"Ashburton",
    "sg:classifiers":[
        {
            "category":"Cafe",
            "type":"Food & Drink"
        }
    ],
    "sg:phone":"+61 3 9813 8633",
    "sg:postcode":"3147",
    "sg:province":"VIC",
    "wof:name":"That Aroma Cafe",
    "wof:placetype":"venue"
},
  "geometry": {"coordinates":[145.092987061,-37.8639602661],"type":"Point"}
}