{
  "type": "Feature",
  "properties": {
    "addr:full":"32 Springfield Ave Kings Cross NSW 2011",
    "addr:housenumber":"32",
    "addr:postcode":"2011",
    "addr:street":"Springfield Ave",
    "iso:country":"AU",
    "sg:address":"32 Springfield Ave",
    "sg:city":"Kings Cross",
    "sg:classifiers":[
        {
            "category":"Fast Food",
            "type":"Food & Drink"
        }
    ],
    "sg:phone":"+61 2 9357 1341",
    "sg:postcode":"2011",
    "sg:province":"NSW",
    "sg:tags":[
        "away",
        "take"
    ],
    "wof:name":"Hungry Jacks Pty Ltd",
    "wof:placetype":"venue"
},
  "geometry": {"coordinates":[151.22390747099999,-33.8728065491],"type":"Point"}
}