{
  "type": "Feature",
  "properties": {
    "addr:full":"359 Pelias St Exmouth WA 6707",
    "addr:housenumber":"359",
    "addr:postcode":"6707",
    "addr:street":"Pelias St",
    "iso:country":"AU",
    "sg:address":"359 Pelias St",
    "sg:city":"Exmouth",
    "sg:classifiers":[
        {
            "category":"Building & Trades",
            "subcategory":"Construction",
            "type":"Services"
        }
    ],
    "sg:phone":"+61 8 9949 1049",
    "sg:postcode":"6707",
    "sg:province":"WA",
    "sg:tags":[
        "earth",
        "excavating",
        "moving",
        "contractor"
    ],
    "wof:name":"Exmouth Quarries & Concrete",
    "wof:placetype":"venue"
},
  "geometry": {"coordinates":[114.128547669,-21.9378452301],"type":"Point"}
}