{
  "type": "Feature",
  "properties": {
    "addr:full":"125 Cremorne St Richmond VIC 3121",
    "addr:housenumber":"125",
    "addr:postcode":"3121",
    "addr:street":"Cremorne St",
    "iso:country":"AU",
    "sg:address":"125 Cremorne St",
    "sg:city":"Richmond",
    "sg:classifiers":[
        {
            "category":"Manufacturing",
            "subcategory":"Retail Goods",
            "type":"Manufacturing & Wholesale Goods"
        }
    ],
    "sg:phone":"+61 3 9426 3400",
    "sg:postcode":"3121",
    "sg:province":"VIC",
    "sg:tags":[
        "merchant",
        "pump",
        "mfrs"
    ],
    "wof:name":"Orange Pumps",
    "wof:placetype":"venue"
},
  "geometry": {"coordinates":[144.990600586,-37.8291091919],"type":"Point"}
}