{
  "type": "Feature",
  "properties": {
    "addr:full":"19 Firth St Arncliffe NSW 2205",
    "addr:housenumber":"19",
    "addr:postcode":"2205",
    "addr:street":"Firth St",
    "iso:country":"AU",
    "sg:address":"19 Firth St",
    "sg:city":"Arncliffe",
    "sg:classifiers":[
        {
            "category":"Real Estate",
            "subcategory":"Real Estate Agent",
            "type":"Services"
        }
    ],
    "sg:phone":"+61 2 9597 7777",
    "sg:postcode":"2205",
    "sg:province":"NSW",
    "wof:name":"L.J. Hooker",
    "wof:placetype":"venue"
},
  "geometry": {"coordinates":[151.14660599999999,-33.936703],"type":"Point"}
}