{
  "type": "Feature",
  "properties": {
    "iso:country":"AU",
    "sg:address":"2 Advantage Drv",
    "sg:city":"Dandenong",
    "sg:classifiers":[
        {
            "category":"Shopping",
            "subcategory":"Stationery & Office Supplies",
            "type":"Retail Goods"
        }
    ],
    "sg:phone":"+61 3 9706 8511",
    "sg:postcode":"3175",
    "sg:province":"VIC",
    "sg:tags":[
        "packaging",
        "material"
    ],
    "wof:name":"Entapack Pty Ltd",
    "wof:placetype":"venue"
},
  "geometry": {"coordinates":[145.225906372,-38.0192642212],"type":"Point"}
}