{
  "type": "Feature",
  "properties": {
    "iso:country":"AU",
    "sg:address":"9 Browning Pl",
    "sg:city":"Seven Hills",
    "sg:classifiers":[
        {
            "category":"Home & Garden",
            "subcategory":"Carpets & Floor Coverings",
            "type":"Retail Goods"
        }
    ],
    "sg:phone":"+61 2 9624 1638",
    "sg:postcode":"2147",
    "sg:province":"NSW",
    "sg:tags":[
        "tile",
        "wall"
    ],
    "wof:name":"W Wright & Sons Tiling",
    "wof:placetype":"venue"
},
  "geometry": {"coordinates":[150.94097900400001,-33.7644958496],"type":"Point"}
}