{
  "type": "Feature",
  "properties": {
    "iso:country":"AU",
    "sg:address":"42 Narrawa Ave",
    "sg:city":"Erina",
    "sg:classifiers":[
        {
            "category":"Personal",
            "subcategory":"Beauty Salon",
            "type":"Services"
        }
    ],
    "sg:phone":"+61 2 4367 2164",
    "sg:postcode":"2250",
    "sg:province":"NSW",
    "sg:tags":[
        "hairdresser"
    ],
    "wof:name":"Evoke Hair By Rebecca Webb",
    "wof:placetype":"venue"
},
  "geometry": {"coordinates":[151.38973999000001,-33.4327507019],"type":"Point"}
}