{
  "type": "Feature",
  "properties": {
    "iso:country":"AU",
    "sg:address":"2 Judith Crt",
    "sg:city":"Mt Waverley",
    "sg:classifiers":[
        {
            "category":"Building & Trades",
            "subcategory":"Plumbing",
            "type":"Services"
        }
    ],
    "sg:phone":"+61 407 600 610",
    "sg:postcode":"3149",
    "sg:province":"VIC",
    "sg:tags":[
        "drainers"
    ],
    "wof:name":"Pipes Cameras Action Pty Ltd",
    "wof:placetype":"venue"
},
  "geometry": {"coordinates":[145.13648986800001,-37.8868026733],"type":"Point"}
}