{
  "type": "Feature",
  "properties": {
    "iso:country":"AU",
    "sg:address":"Seaview St",
    "sg:city":"Clovelly",
    "sg:classifiers":[
        {
            "category":"Social Services",
            "subcategory":"Child Care",
            "type":"Services"
        }
    ],
    "sg:phone":"+61 407 451 351",
    "sg:postcode":"2031",
    "sg:province":"NSW",
    "wof:name":"Serendipity Home Based Professional Child Care",
    "wof:placetype":"venue"
},
  "geometry": {"coordinates":[151.25617980999999,-33.9095153809],"type":"Point"}
}