{
  "type": "Feature",
  "properties": {
    "addr:full":"21 Crofton Ave Tenambit NSW 2323",
    "addr:housenumber":"21",
    "addr:postcode":"2323",
    "addr:street":"Crofton Ave",
    "iso:country":"AU",
    "sg:address":"21 Crofton Ave",
    "sg:city":"Tenambit",
    "sg:classifiers":[
        {
            "category":"Personal",
            "subcategory":"Beauty Salon",
            "type":"Services"
        }
    ],
    "sg:phone":"+61 2 4933 9743",
    "sg:postcode":"2323",
    "sg:province":"NSW",
    "sg:tags":[
        "hairdresser"
    ],
    "wof:name":"Rowena Pryde Hairdressing",
    "wof:placetype":"venue"
},
  "geometry": {"coordinates":[151.60820007300001,-32.7368774414],"type":"Point"}
}