{
  "type": "Feature",
  "properties": {
    "addr:full":"63 Crows Nest Rd Wollstonecraft NSW 2065",
    "addr:housenumber":"63",
    "addr:postcode":"2065",
    "addr:street":"Crows Nest Rd",
    "iso:country":"AU",
    "sg:address":"63 Crows Nest Rd",
    "sg:city":"Wollstonecraft",
    "sg:classifiers":[
        {
            "category":"Professional",
            "subcategory":"Business Services",
            "type":"Services"
        }
    ],
    "sg:phone":"+61 2 9955 7830",
    "sg:postcode":"2065",
    "sg:province":"NSW",
    "sg:tags":[
        "drafting"
    ],
    "wof:name":"T & I Drafting Services",
    "wof:placetype":"venue"
},
  "geometry": {"coordinates":[151.203567505,-33.833442688],"type":"Point"}
}