{
  "type": "Feature",
  "properties": {
    "addr:full":"Bell Rd Corio VIC 3214",
    "addr:postcode":"3214",
    "addr:street":"Bell Rd",
    "iso:country":"AU",
    "sg:address":"Bell Rd",
    "sg:city":"Corio",
    "sg:classifiers":[
        {
            "category":"Utilities",
            "subcategory":"Refuse",
            "type":"Services"
        }
    ],
    "sg:phone":"+61 3 5275 7987",
    "sg:postcode":"3214",
    "sg:province":"VIC",
    "sg:tags":[
        "disposal",
        "reduction",
        "waste"
    ],
    "wof:name":"Corio Landfill",
    "wof:placetype":"venue"
},
  "geometry": {"coordinates":[144.39247131400001,-38.0585670471],"type":"Point"}
}