{
  "type": "Feature",
  "properties": {
    "addr:full":"27 Norman St Gordonvale QLD 4865",
    "addr:housenumber":"27",
    "addr:postcode":"4865",
    "addr:street":"Norman St",
    "iso:country":"AU",
    "sg:address":"27 Norman St",
    "sg:city":"Gordonvale",
    "sg:classifiers":[
        {
            "category":"Health Services",
            "subcategory":"Doctor",
            "type":"Services"
        }
    ],
    "sg:phone":"+61 7 4056 3600",
    "sg:postcode":"4865",
    "sg:province":"QLD",
    "sg:tags":[
        "medical",
        "practitioner"
    ],
    "wof:name":"Gordonvale Family Medical Centre",
    "wof:placetype":"venue"
},
  "geometry": {"coordinates":[145.78593444800001,-17.0964450836],"type":"Point"}
}