{
  "type": "Feature",
  "properties": {
    "addr:full":"27 Bentley Rd St Marys NSW 2760",
    "addr:housenumber":"27",
    "addr:postcode":"2760",
    "addr:street":"Bentley Rd",
    "iso:country":"AU",
    "sg:address":"27 Bentley Rd",
    "sg:city":"St Marys",
    "sg:classifiers":[
        {
            "category":"Social Services",
            "subcategory":"Child Care",
            "type":"Services"
        }
    ],
    "sg:phone":"+61 2 9623 1499",
    "sg:postcode":"2760",
    "sg:province":"NSW",
    "wof:name":"Keymer Child Care Centre",
    "wof:placetype":"venue"
},
  "geometry": {"coordinates":[150.793624878,-33.7811355591],"type":"Point"}
}