{
  "type": "Feature",
  "properties": {
    "addr:full":"130 Haldon St Lakemba NSW 2195",
    "addr:housenumber":"130",
    "addr:postcode":"2195",
    "addr:street":"Haldon St",
    "iso:country":"AU",
    "sg:address":"130 Haldon St",
    "sg:city":"Lakemba",
    "sg:classifiers":[
        {
            "category":"Communications",
            "subcategory":"Film & Video Production",
            "type":"Services"
        }
    ],
    "sg:phone":"+61 2 9750 3344",
    "sg:postcode":"2195",
    "sg:province":"NSW",
    "sg:tags":[
        "dvd",
        "library"
    ],
    "wof:name":"Civic Video Pty Ltd",
    "wof:placetype":"venue"
},
  "geometry": {"coordinates":[151.078247,-33.922104],"type":"Point"}
}