{
  "type": "Feature",
  "properties": {
    "addr:full":"338 Mann St Gosford NSW 2250",
    "addr:housenumber":"338",
    "addr:postcode":"2250",
    "addr:street":"Mann St",
    "iso:country":"AU",
    "sg:address":"338 Mann St",
    "sg:city":"Gosford",
    "sg:classifiers":[
        {
            "category":"Retail",
            "subcategory":"Auto Repair",
            "type":"Services"
        }
    ],
    "sg:phone":"+61 2 4324 1477",
    "sg:postcode":"2250",
    "sg:province":"NSW",
    "sg:tags":[
        "repairer",
        "motor",
        "engineer"
    ],
    "wof:name":"Ultra Tune",
    "wof:placetype":"venue"
},
  "geometry": {"coordinates":[151.343383789,-33.418674469],"type":"Point"}
}