{
  "type": "Feature",
  "properties": {
    "addr:full":"111 Warrington Rd Byford WA 6122",
    "addr:housenumber":"111",
    "addr:postcode":"6122",
    "addr:street":"Warrington Rd",
    "iso:country":"AU",
    "sg:address":"111 Warrington Rd",
    "sg:city":"Byford",
    "sg:classifiers":[
        {
            "category":"Building & Trades",
            "subcategory":"Construction",
            "type":"Services"
        }
    ],
    "sg:phone":"+61 418 949 650",
    "sg:postcode":"6122",
    "sg:province":"WA",
    "sg:tags":[
        "joiner",
        "carpenter"
    ],
    "wof:name":"DKC Carpentry Service",
    "wof:placetype":"venue"
},
  "geometry": {"coordinates":[115.996200562,-32.2335128784],"type":"Point"}
}