{
  "type": "Feature",
  "properties": {
    "addr:full":"195 Glenrock Pde Koolewong NSW 2256",
    "addr:housenumber":"195",
    "addr:postcode":"2256",
    "addr:street":"Glenrock Pde",
    "iso:country":"AU",
    "sg:address":"195 Glenrock Pde",
    "sg:city":"Koolewong",
    "sg:classifiers":[
        {
            "category":"Recreation",
            "subcategory":"Boat Charter",
            "type":"Entertainment"
        }
    ],
    "sg:phone":"+61 2 4343 1195",
    "sg:postcode":"2256",
    "sg:province":"NSW",
    "wof:name":"Jerry O&#039;Neill",
    "wof:placetype":"venue"
},
  "geometry": {"coordinates":[151.313323975,-33.4628601074],"type":"Point"}
}