{
  "type": "Feature",
  "properties": {
    "addr:full":"Shop 33 The Walk 309 Bourke St Melbourne VIC 3000",
    "addr:housenumber":"shop 33;309",
    "addr:postcode":"3000",
    "addr:street":"The Walk;Bourke St",
    "iso:country":"AU",
    "sg:address":"Shop 33 The Walk 309 Bourke St",
    "sg:city":"Melbourne",
    "sg:classifiers":[
        {
            "category":"Fast Food",
            "type":"Food & Drink"
        }
    ],
    "sg:phone":"+61 3 9654 1541",
    "sg:postcode":"3000",
    "sg:province":"VIC",
    "sg:tags":[
        "away",
        "take"
    ],
    "wof:name":"Hot-Sub Sandwich",
    "wof:placetype":"venue"
},
  "geometry": {"coordinates":[144.96452331500001,-37.8143997192],"type":"Point"}
}