{
  "type": "Feature",
  "properties": {
    "addr:full":"120 San Mateo Ave Mildura VIC 3500",
    "addr:housenumber":"120",
    "addr:postcode":"3500",
    "addr:street":"San Mateo Ave",
    "iso:country":"AU",
    "sg:address":"120 San Mateo Ave",
    "sg:city":"Mildura",
    "sg:classifiers":[
        {
            "category":"Retail",
            "subcategory":"Repair Shop",
            "type":"Services"
        }
    ],
    "sg:phone":"+61 3 5021 4957",
    "sg:postcode":"3500",
    "sg:province":"VIC",
    "sg:tags":[
        "machine",
        "repairs",
        "part",
        "dryer",
        "washing"
    ],
    "wof:name":"Shayne Tonzing",
    "wof:placetype":"venue"
},
  "geometry": {"coordinates":[142.16636657699999,-34.1913146973],"type":"Point"}
}