{
  "type": "Feature",
  "properties": {
    "iso:country":"AU",
    "sg:address":"14 McGorrery Pl",
    "sg:city":"Jabiru",
    "sg:classifiers":[
        {
            "category":"Communications",
            "subcategory":"News Services",
            "type":"Services"
        }
    ],
    "sg:phone":"+61 8 8979 2567",
    "sg:postcode":"0886",
    "sg:province":"NT",
    "sg:tags":[
        "information",
        "tourist",
        "attractions"
    ],
    "wof:name":"Lord Of Kakadu Tours",
    "wof:placetype":"venue"
},
  "geometry": {"coordinates":[132.836166,-12.67414],"type":"Point"}
}