{
  "type": "Feature",
  "properties": {
    "addr:full":"553 David St Albury NSW 2640",
    "addr:housenumber":"553",
    "addr:postcode":"2640",
    "addr:street":"David St",
    "iso:country":"AU",
    "sg:address":"553 David St",
    "sg:city":"Albury",
    "sg:classifiers":[
        {
            "category":"Professional",
            "subcategory":"Engineering",
            "type":"Services"
        }
    ],
    "sg:phone":"+61 2 6023 6488",
    "sg:postcode":"2640",
    "sg:province":"NSW",
    "sg:tags":[
        "consulting",
        "engineer"
    ],
    "wof:name":"Coomes Consulting",
    "wof:placetype":"venue"
},
  "geometry": {"coordinates":[146.92103576700001,-36.0787734985],"type":"Point"}
}