{
  "type": "Feature",
  "properties": {
    "addr:full":"Einstein Drv Golden Grove SA 5125",
    "addr:postcode":"5125",
    "addr:street":"Einstein Drv",
    "iso:country":"AU",
    "sg:address":"Einstein Drv",
    "sg:city":"Golden Grove",
    "sg:classifiers":[
        {
            "category":"Manufacturing",
            "subcategory":"Building Materials",
            "type":"Manufacturing & Wholesale Goods"
        }
    ],
    "sg:phone":"+61 8 8289 1600",
    "sg:postcode":"5125",
    "sg:province":"SA",
    "sg:tags":[
        "equipment",
        "handling"
    ],
    "wof:name":"Northern Conveyors",
    "wof:placetype":"venue"
},
  "geometry": {"coordinates":[138.71388200000001,-34.788921],"type":"Point"}
}