{
  "type": "Feature",
  "properties": {
    "iso:country":"AU",
    "sg:address":"266- 270 Portarlington Rd",
    "sg:city":"Moolap",
    "sg:classifiers":[
        {
            "category":"Building & Trades",
            "subcategory":"Equipment Rental",
            "type":"Services"
        }
    ],
    "sg:phone":"+61 3 5248 4114",
    "sg:postcode":"3221",
    "sg:province":"VIC",
    "sg:tags":[
        "crane",
        "hire"
    ],
    "wof:name":"Eastside Crane Hire",
    "wof:placetype":"venue"
},
  "geometry": {"coordinates":[144.420395,-38.166019],"type":"Point"}
}