{
  "type": "Feature",
  "properties": {
    "addr:full":"28 Bridge St Sydney NSW 2000",
    "addr:housenumber":"28",
    "addr:postcode":"2000",
    "addr:street":"Bridge St",
    "iso:country":"AU",
    "sg:address":"28 Bridge St",
    "sg:city":"Sydney",
    "sg:classifiers":[
        {
            "category":"Banks & Credit Unions",
            "subcategory":"Bank",
            "type":"Services"
        }
    ],
    "sg:phone":"+61 1300 308 008",
    "sg:postcode":"2000",
    "sg:province":"NSW",
    "wof:name":"HSBC",
    "wof:placetype":"venue"
},
  "geometry": {"coordinates":[151.20883178700001,-33.863483429],"type":"Point"}
}