{
  "type": "Feature",
  "properties": {
    "addr:full":"34 Redfern St Wetherill Park NSW 2164",
    "addr:housenumber":"34",
    "addr:postcode":"2164",
    "addr:street":"Redfern St",
    "iso:country":"AU",
    "sg:address":"34 Redfern St",
    "sg:city":"Wetherill Park",
    "sg:classifiers":[
        {
            "category":"Manufacturing",
            "subcategory":"Paper Products",
            "type":"Manufacturing & Wholesale Goods"
        }
    ],
    "sg:phone":"+61 2 8787 2222",
    "sg:postcode":"2164",
    "sg:province":"NSW",
    "sg:tags":[
        "wholesaler",
        "mfrs"
    ],
    "wof:name":"ABC Tissue Products Pty Ltd",
    "wof:placetype":"venue"
},
  "geometry": {"coordinates":[150.91229248100001,-33.8437767029],"type":"Point"}
}