{
  "type": "Feature",
  "properties": {
    "iso:country":"AU",
    "sg:address":"31a Hutchinson St",
    "sg:city":"Mt Barker",
    "sg:classifiers":[
        {
            "category":"Utilities",
            "subcategory":"Electric",
            "type":"Services"
        }
    ],
    "sg:phone":"+61 8 8398 2662",
    "sg:postcode":"5251",
    "sg:province":"SA",
    "sg:tags":[
        "tube",
        "lamps",
        "globe"
    ],
    "wof:name":"Mount Barker Lighting",
    "wof:placetype":"venue"
},
  "geometry": {"coordinates":[138.86007690400001,-35.0663604736],"type":"Point"}
}