{
  "type": "Feature",
  "properties": {
    "iso:country":"AU",
    "sg:address":"187 Williamstown Rd",
    "sg:city":"Port Melbourne",
    "sg:classifiers":[
        {
            "category":"Manufacturing",
            "subcategory":"Paper Products",
            "type":"Manufacturing & Wholesale Goods"
        }
    ],
    "sg:phone":"+61 3 9646 4421",
    "sg:postcode":"3207",
    "sg:province":"VIC",
    "sg:tags":[
        "bag"
    ],
    "wof:name":"Charles Gabb & Co Pty Ltd",
    "wof:placetype":"venue"
},
  "geometry": {"coordinates":[144.915054,-37.836769],"type":"Point"}
}