{
  "type": "Feature",
  "properties": {
    "addr:full":"35 Parer Rd Airport West VIC 3042",
    "addr:housenumber":"35",
    "addr:postcode":"3042",
    "addr:street":"Parer Rd",
    "iso:country":"AU",
    "sg:address":"35 Parer Rd",
    "sg:city":"Airport West",
    "sg:classifiers":[
        {
            "category":"Building & Trades",
            "subcategory":"Landscaping Services",
            "type":"Services"
        }
    ],
    "sg:phone":"+61 3 9338 2911",
    "sg:postcode":"3042",
    "sg:province":"VIC",
    "sg:tags":[
        "designer",
        "landscape",
        "contractor"
    ],
    "wof:name":"Peco Constructions Pty Ltd",
    "wof:placetype":"venue"
},
  "geometry": {"coordinates":[144.88844299300001,-37.7202148438],"type":"Point"}
}