{
  "type": "Feature",
  "properties": {
    "addr:full":"594 Rode Rd Chermside QLD 4032",
    "addr:postcode":"qld 4032",
    "addr:street":"Rode Rd",
    "iso:country":"AU",
    "sg:address":"594 Rode Rd",
    "sg:city":"Chermside",
    "sg:classifiers":[
        {
            "category":"Building & Trades",
            "subcategory":"Construction",
            "type":"Services"
        }
    ],
    "sg:phone":"+61 7 3359 3025",
    "sg:postcode":"4032",
    "sg:province":"QLD",
    "sg:tags":[
        "window",
        "timber"
    ],
    "sg:website":"http://www.allkind.com.au",
    "wof:name":"Allkind Joinery",
    "wof:placetype":"venue"
},
  "geometry": {"coordinates":[153.02380400000001,-27.393087],"type":"Point"}
}