{
  "type": "Feature",
  "properties": {
    "iso:country":"AU",
    "sg:address":"275 Canning Hwy",
    "sg:city":"Palmyra",
    "sg:classifiers":[
        {
            "category":"Health Services",
            "subcategory":"Doctor",
            "type":"Services"
        }
    ],
    "sg:phone":"+61 8 9339 7799",
    "sg:postcode":"6157",
    "sg:province":"WA",
    "sg:tags":[
        "medical",
        "practitioner"
    ],
    "wof:name":"Ballard Shannon Dr",
    "wof:placetype":"venue"
},
  "geometry": {"coordinates":[115.777184,-32.038151],"type":"Point"}
}