{
  "type": "Feature",
  "properties": {
    "iso:country":"AU",
    "sg:address":"136 West St",
    "sg:city":"Gundagai",
    "sg:classifiers":[
        {
            "category":"Social Services",
            "subcategory":"Child Care",
            "type":"Services"
        }
    ],
    "sg:phone":"+61 2 6944 1889",
    "sg:postcode":"2722",
    "sg:province":"NSW",
    "wof:name":"Gumnut Child Care Centre",
    "wof:placetype":"venue"
},
  "geometry": {"coordinates":[148.098404,-35.064407],"type":"Point"}
}