{
  "type": "Feature",
  "properties": {
    "addr:full":"136 West St Gundagai NSW 2722",
    "addr:housenumber":"136",
    "addr:postcode":"2722",
    "addr:street":"West St",
    "iso:country":"AU",
    "sg:address":"136 West St",
    "sg:city":"Gundagai",
    "sg:classifiers":[
        {
            "category":"Social Services",
            "subcategory":"Child Care",
            "type":"Services"
        }
    ],
    "sg:phone":"+61 2 6944 1889",
    "sg:postcode":"2722",
    "sg:province":"NSW",
    "wof:name":"Gumnut Child Care Centre",
    "wof:placetype":"venue"
},
  "geometry": {"coordinates":[148.09840399999999,-35.064407],"type":"Point"}
}