{
  "type": "Feature",
  "properties": {
    "addr:full":"27 Marlin St Kawungan QLD 4655",
    "addr:housenumber":"27",
    "addr:postcode":"4655",
    "addr:street":"Marlin St",
    "iso:country":"AU",
    "sg:address":"27 Marlin St",
    "sg:city":"Kawungan",
    "sg:classifiers":[
        {
            "category":"Building & Trades",
            "subcategory":"Construction",
            "type":"Services"
        }
    ],
    "sg:phone":"+61 419 661 318",
    "sg:postcode":"4655",
    "sg:province":"QLD",
    "sg:tags":[
        "brick",
        "paving"
    ],
    "wof:name":"Wide Bay Paving & Edging",
    "wof:placetype":"venue"
},
  "geometry": {"coordinates":[152.85235599999999,-25.304447],"type":"Point"}
}