{
  "type": "Feature",
  "properties": {
    "addr:full":"Level 2 38 George St Parramatta NSW 2150",
    "addr:housenumber":"38",
    "addr:postcode":"2150",
    "addr:street":"George St",
    "iso:country":"AU",
    "sg:address":"Level 2 38 George St",
    "sg:city":"Parramatta",
    "sg:classifiers":[
        {
            "category":"Banks & Credit Unions",
            "subcategory":"Financial Services",
            "type":"Services"
        }
    ],
    "sg:phone":"+61 2 9806 0512",
    "sg:postcode":"2150",
    "sg:province":"NSW",
    "sg:tags":[
        "planning"
    ],
    "sg:website":"http://www.fpa.asn.au",
    "wof:name":"McHattan Warren Financial Services",
    "wof:placetype":"venue"
},
  "geometry": {"coordinates":[151.01791381800001,-33.8326683044],"type":"Point"}
}