{
  "type": "Feature",
  "properties": {
    "addr:full":"91 Jane St West End (Brisbane) QLD 4101",
    "addr:housenumber":"91",
    "addr:postcode":"4101",
    "addr:street":"Jane St",
    "iso:country":"AU",
    "sg:address":"91 Jane St",
    "sg:city":"West End (Brisbane)",
    "sg:classifiers":[
        {
            "category":"Cafe",
            "type":"Food & Drink"
        }
    ],
    "sg:phone":"+61 7 3255 2273",
    "sg:postcode":"4101",
    "sg:province":"QLD",
    "wof:name":"Stove",
    "wof:placetype":"venue"
},
  "geometry": {"coordinates":[153.00692749000001,-27.4782428741],"type":"Point"}
}