{
  "type": "Feature",
  "properties": {
    "addr:full":"Cambridge Ave Fairy Meadow NSW 2519",
    "addr:postcode":"2519",
    "addr:street":"Cambridge Ave",
    "iso:country":"AU",
    "sg:address":"Cambridge Ave",
    "sg:city":"Fairy Meadow",
    "sg:classifiers":[
        {
            "category":"Retail",
            "subcategory":"Event Space",
            "type":"Services"
        }
    ],
    "sg:phone":"+61 2 4283 6300",
    "sg:postcode":"2519",
    "sg:province":"NSW",
    "sg:tags":[
        "function",
        "organiser"
    ],
    "wof:name":"Fairy Meadow Bowling Club",
    "wof:placetype":"venue"
},
  "geometry": {"coordinates":[150.892685,-34.391949],"type":"Point"}
}