{
  "type": "Feature",
  "properties": {
    "iso:country":"AU",
    "sg:address":"61 Oceanic Drv",
    "sg:city":"Mermaid Beach",
    "sg:classifiers":[
        {
            "category":"Home & Garden",
            "subcategory":"Hardware",
            "type":"Retail Goods"
        }
    ],
    "sg:phone":"+61 7 5575 4910",
    "sg:postcode":"4218",
    "sg:province":"QLD",
    "sg:tags":[
        "pipe",
        "fitting",
        "plastic"
    ],
    "wof:name":"Contractors & Industrial Sales Pty Ltd",
    "wof:placetype":"venue"
},
  "geometry": {"coordinates":[153.42449951200001,-28.0573959351],"type":"Point"}
}