{
  "type": "Feature",
  "properties": {
    "iso:country":"AU",
    "sg:address":"35- 37 Tullamarine Park Rd",
    "sg:city":"Tullamarine",
    "sg:classifiers":[
        {
            "category":"Professional",
            "type":"Services"
        }
    ],
    "sg:phone":"+61 3 9335 4444",
    "sg:postcode":"3043",
    "sg:province":"VIC",
    "sg:tags":[
        "forwarding",
        "agent",
        "transport"
    ],
    "wof:name":"I.T.A.C. Services (Aust) Pty Ltd",
    "wof:placetype":"venue"
},
  "geometry": {"coordinates":[144.87066650400001,-37.7103424072],"type":"Point"}
}