{
  "type": "Feature",
  "properties": {
    "addr:full":"984 Toorak Rd Camberwell VIC 3124",
    "addr:housenumber":"984",
    "addr:postcode":"3124",
    "addr:street":"Toorak Rd",
    "iso:country":"AU",
    "sg:address":"984 Toorak Rd",
    "sg:city":"Camberwell",
    "sg:classifiers":[
        {
            "category":"Health Services",
            "subcategory":"Doctor",
            "type":"Services"
        }
    ],
    "sg:phone":"+61 3 9889 5885",
    "sg:postcode":"3124",
    "sg:province":"VIC",
    "sg:tags":[
        "medical",
        "practitioner"
    ],
    "wof:name":"Stobie Michael",
    "wof:placetype":"venue"
},
  "geometry": {"coordinates":[145.07528686500001,-37.8481369019],"type":"Point"}
}