{
  "type": "Feature",
  "properties": {
    "addr:full":"15 Lime St Sydney NSW 2000",
    "addr:housenumber":"15",
    "addr:postcode":"2000",
    "addr:street":"Lime St",
    "iso:country":"AU",
    "sg:address":"15 Lime St",
    "sg:city":"Sydney",
    "sg:classifiers":[
        {
            "category":"Professional",
            "subcategory":"Research",
            "type":"Services"
        }
    ],
    "sg:phone":"+61 2 9279 2200",
    "sg:postcode":"2000",
    "sg:province":"NSW",
    "sg:tags":[
        "market"
    ],
    "wof:name":"SuperRatings Pty Ltd",
    "wof:placetype":"venue"
},
  "geometry": {"coordinates":[151.20164489699999,-33.8664932251],"type":"Point"}
}