{
  "type": "Feature",
  "properties": {
    "iso:country":"AU",
    "sg:address":"ShpFC5/ 121 South Gippsland Hwy",
    "sg:city":"Cranbourne",
    "sg:classifiers":[
        {
            "category":"Fast Food",
            "type":"Food & Drink"
        }
    ],
    "sg:phone":"+61 3 5995 9500",
    "sg:postcode":"3977",
    "sg:province":"VIC",
    "sg:tags":[
        "away",
        "take"
    ],
    "wof:name":"Lite Lunchbox",
    "wof:placetype":"venue"
},
  "geometry": {"coordinates":[145.27557373100001,-38.0809745789],"type":"Point"}
}