{
  "type": "Feature",
  "properties": {
    "iso:country":"AU",
    "sg:address":"86 Oxley Station Rd",
    "sg:city":"Oxley",
    "sg:classifiers":[
        {
            "category":"Organizations",
            "subcategory":"Community Association",
            "type":"Services"
        }
    ],
    "sg:phone":"+61 7 3278 1103",
    "sg:postcode":"4075",
    "sg:province":"QLD",
    "sg:tags":[
        "club",
        "senior",
        "citizen"
    ],
    "wof:name":"Oxley Senior Citizens Club",
    "wof:placetype":"venue"
},
  "geometry": {"coordinates":[152.97547912600001,-27.5550556183],"type":"Point"}
}