{
  "type": "Feature",
  "properties": {
    "iso:country":"AU",
    "sg:address":"23 Lewis Pl",
    "sg:city":"Picnic Point",
    "sg:classifiers":[
        {
            "category":"Utilities",
            "subcategory":"Electric",
            "type":"Services"
        }
    ],
    "sg:phone":"+61 2 9772 1656",
    "sg:postcode":"2213",
    "sg:province":"NSW",
    "sg:tags":[
        "electrical",
        "contractor"
    ],
    "wof:name":"Willis Electrics Pty Ltd",
    "wof:placetype":"venue"
},
  "geometry": {"coordinates":[151.003754,-33.962402],"type":"Point"}
}