{
  "type": "Feature",
  "properties": {
    "addr:full":"Shed 5 / 858 Nudgee Rd Northgate QLD 4013",
    "addr:housenumber":"5 / 858",
    "addr:postcode":"4013",
    "addr:street":"Nudgee Rd",
    "iso:country":"AU",
    "sg:address":"Shed 5 / 858 Nudgee Rd",
    "sg:city":"Northgate",
    "sg:classifiers":[
        {
            "category":"Train Station",
            "subcategory":"Rail",
            "type":"Transportation"
        }
    ],
    "sg:phone":"+61 7 3266 4324",
    "sg:postcode":"4013",
    "sg:province":"QLD",
    "sg:tags":[
        "wallboard"
    ],
    "wof:name":"Colonial Wall Linings",
    "wof:placetype":"venue"
},
  "geometry": {"coordinates":[153.08172607399999,-27.3909568787],"type":"Point"}
}