{
  "type": "Feature",
  "properties": {
    "iso:country":"AU",
    "sg:address":"L2, 35-37 Dickson Ave",
    "sg:city":"Artarmon",
    "sg:classifiers":[
        {
            "category":"Professional",
            "subcategory":"Printing & Photocopies",
            "type":"Services"
        }
    ],
    "sg:phone":"+61 2 9460 9985",
    "sg:postcode":"2064",
    "sg:province":"NSW",
    "sg:tags":[
        "trophy"
    ],
    "wof:name":"Accumark",
    "wof:placetype":"venue"
},
  "geometry": {"coordinates":[151.18414306599999,-33.8158111572],"type":"Point"}
}