{
  "type": "Feature",
  "properties": {
    "addr:full":"54 Slip Rd Paynesville VIC 3880",
    "addr:housenumber":"54",
    "addr:postcode":"3880",
    "addr:street":"Slip Rd",
    "iso:country":"AU",
    "sg:address":"54 Slip Rd",
    "sg:city":"Paynesville",
    "sg:classifiers":[
        {
            "category":"Autos & Motor Vehicles",
            "subcategory":"Boat Sales",
            "type":"Retail Goods"
        }
    ],
    "sg:phone":"+61 3 5156 6099",
    "sg:postcode":"3880",
    "sg:province":"VIC",
    "sg:tags":[
        "builder",
        "yacht",
        "repairer"
    ],
    "wof:name":"Ashworth Maritime Services",
    "wof:placetype":"venue"
},
  "geometry": {"coordinates":[147.72711181599999,-37.9093742371],"type":"Point"}
}