{
  "type": "Feature",
  "properties": {
    "addr:full":"81 Archibald St Paget QLD 4740",
    "addr:housenumber":"81",
    "addr:postcode":"4740",
    "addr:street":"Archibald St",
    "iso:country":"AU",
    "sg:address":"81 Archibald St",
    "sg:city":"Paget",
    "sg:classifiers":[
        {
            "category":"Autos & Motor Vehicles",
            "subcategory":"Motorcycle Sales",
            "type":"Retail Goods"
        }
    ],
    "sg:phone":"+61 7 4952 1412",
    "sg:postcode":"4740",
    "sg:province":"QLD",
    "sg:tags":[
        "outboard"
    ],
    "wof:name":"Thomson Dick Marine",
    "wof:placetype":"venue"
},
  "geometry": {"coordinates":[149.16467299999999,-21.168264],"type":"Point"}
}