{
  "type": "Feature",
  "properties": {
    "addr:full":"PO Box 2101 Kew VIC 3101",
    "addr:postcode":"3101",
    "iso:country":"AU",
    "sg:address":"PO Box 2101",
    "sg:city":"Kew",
    "sg:classifiers":[
        {
            "category":"Education",
            "subcategory":"Special Training",
            "type":"Public Place"
        }
    ],
    "sg:phone":"+61 405 144 092",
    "sg:postcode":"3101",
    "sg:province":"VIC",
    "sg:tags":[
        "development"
    ],
    "wof:name":"One Thousand & One",
    "wof:placetype":"venue"
},
  "geometry": {"coordinates":[145.030883789,-37.8014717102],"type":"Point"}
}