{
  "type": "Feature",
  "properties": {
    "addr:full":"182 Magill Rd Norwood SA 5067",
    "addr:housenumber":"182",
    "addr:postcode":"5067",
    "addr:street":"Magill Rd",
    "iso:country":"AU",
    "sg:address":"182 Magill Rd",
    "sg:city":"Norwood",
    "sg:classifiers":[
        {
            "category":"Professional",
            "subcategory":"Accounting & Tax Preparation",
            "type":"Services"
        }
    ],
    "sg:phone":"+61 8 8364 1930",
    "sg:postcode":"5067",
    "sg:province":"SA",
    "sg:tags":[
        "distributor",
        "lock",
        "mfrs"
    ],
    "wof:name":"Lockwood Security Products Pty Limited",
    "wof:placetype":"venue"
},
  "geometry": {"coordinates":[138.637084961,-34.9150924683],"type":"Point"}
}