{
  "type": "Feature",
  "properties": {
    "addr:full":"46 Lesouef Drv Kardinya WA 6163",
    "addr:housenumber":"46",
    "addr:postcode":"6163",
    "addr:street":"Lesouef Drv",
    "iso:country":"AU",
    "sg:address":"46 Lesouef Drv",
    "sg:city":"Kardinya",
    "sg:classifiers":[
        {
            "category":"Building & Trades",
            "subcategory":"Construction",
            "type":"Services"
        }
    ],
    "sg:phone":"+61 8 9314 2979",
    "sg:postcode":"6163",
    "sg:province":"WA",
    "sg:tags":[
        "contractor"
    ],
    "wof:name":"Roy Hunter Builders",
    "wof:placetype":"venue"
},
  "geometry": {"coordinates":[115.809372,-32.066303],"type":"Point"}
}