{
  "type": "Feature",
  "properties": {
    "iso:country":"AU",
    "sg:address":"Globe Derby Drv",
    "sg:city":"Globe Derby Park",
    "sg:classifiers":[
        {
            "category":"Arena",
            "subcategory":"Sports Club",
            "type":"Entertainment"
        }
    ],
    "sg:phone":"+61 8 8285 2899",
    "sg:postcode":"5110",
    "sg:province":"SA",
    "sg:tags":[
        "organisation",
        "sporting"
    ],
    "wof:name":"Harness Racing SA Ltd",
    "wof:placetype":"venue"
},
  "geometry": {"coordinates":[138.585403442,-34.7939529419],"type":"Point"}
}