{
  "type": "Feature",
  "properties": {
    "addr:full":"104 Main Rd Moonah TAS 7009",
    "addr:housenumber":"104",
    "addr:postcode":"7009",
    "addr:street":"Main Rd",
    "iso:country":"AU",
    "sg:address":"104 Main Rd",
    "sg:city":"Moonah",
    "sg:classifiers":[
        {
            "category":"Personal",
            "type":"Services"
        }
    ],
    "sg:phone":"+61 3 6274 1992",
    "sg:postcode":"7009",
    "sg:province":"TAS",
    "sg:tags":[
        "dressmaker"
    ],
    "wof:name":"Strutt Design Studio",
    "wof:placetype":"venue"
},
  "geometry": {"coordinates":[147.294525147,-42.8464355469],"type":"Point"}
}