{
  "type": "Feature",
  "properties": {
    "addr:full":"26 Water St Werrington NSW 2747",
    "addr:housenumber":"26",
    "addr:postcode":"2747",
    "addr:street":"Water St",
    "iso:country":"AU",
    "sg:address":"26 Water St",
    "sg:city":"Werrington",
    "sg:classifiers":[
        {
            "category":"Commercial Area",
            "type":"Public Place"
        }
    ],
    "sg:phone":"+61 2 9623 1841",
    "sg:postcode":"2747",
    "sg:province":"NSW",
    "sg:tags":[
        "heavy",
        "carrier"
    ],
    "wof:name":"Warwil Road Transport",
    "wof:placetype":"venue"
},
  "geometry": {"coordinates":[150.752441406,-33.7664833069],"type":"Point"}
}