{
  "type": "Feature",
  "properties": {
    "iso:country":"AU",
    "sg:address":"PO Box 268",
    "sg:city":"Clayfield",
    "sg:classifiers":[
        {
            "category":"Banks & Credit Unions",
            "subcategory":"Bank",
            "type":"Services"
        }
    ],
    "sg:phone":"+61 7 3862 4088",
    "sg:postcode":"4011",
    "sg:province":"QLD",
    "sg:tags":[
        "broker",
        "mortgage"
    ],
    "wof:name":"Australasian Finance Group",
    "wof:placetype":"venue"
},
  "geometry": {"coordinates":[153.05898999999999,-27.41213],"type":"Point"}
}