{
  "type": "Feature",
  "properties": {
    "addr:full":"Lvl 3,OCE House 50 McDougall St Milton QLD 4064",
    "addr:housenumber":"50",
    "addr:postcode":"4064",
    "addr:street":"Mcdougall St",
    "iso:country":"AU",
    "sg:address":"Lvl 3,OCE House 50 McDougall St",
    "sg:city":"Milton",
    "sg:classifiers":[
        {
            "category":"Building & Trades",
            "subcategory":"Construction",
            "type":"Services"
        }
    ],
    "sg:phone":"+61 7 5592 4477",
    "sg:postcode":"4064",
    "sg:province":"QLD",
    "sg:tags":[
        "management"
    ],
    "wof:name":"Broad Construction Services (Qld) Pty Ltd",
    "wof:placetype":"venue"
},
  "geometry": {"coordinates":[153.00607299800001,-27.4713726044],"type":"Point"}
}