{
  "type": "Feature",
  "properties": {
    "addr:full":"109 Victoria St Footscray VIC 3011",
    "addr:housenumber":"109",
    "addr:postcode":"3011",
    "addr:street":"Victoria St",
    "iso:country":"AU",
    "sg:address":"109 Victoria St",
    "sg:city":"Footscray",
    "sg:classifiers":[
        {
            "category":"Retail",
            "subcategory":"Funeral Services",
            "type":"Services"
        }
    ],
    "sg:phone":"+61 3 9689 2199",
    "sg:postcode":"3011",
    "sg:province":"VIC",
    "sg:tags":[
        "director"
    ],
    "wof:name":"Hollibone Stanley A & Son Pty Ltd",
    "wof:placetype":"venue"
},
  "geometry": {"coordinates":[144.892044067,-37.8061485291],"type":"Point"}
}