{
  "type": "Feature",
  "properties": {
    "iso:country":"AU",
    "sg:address":"PO Box 2140",
    "sg:city":"Fountain Gate Shopping Centre Narre Warren",
    "sg:classifiers":[
        {
            "category":"Ice Cream",
            "type":"Food & Drink"
        }
    ],
    "sg:phone":"+61 3 5996 0652",
    "sg:postcode":"3805",
    "sg:province":"VIC",
    "sg:tags":[
        "specialised",
        "fitting",
        "lady",
        "wear"
    ],
    "wof:name":"Big Time Casuals",
    "wof:placetype":"venue"
},
  "geometry": {"coordinates":[145.302155,-38.014935],"type":"Point"}
}