{
  "type": "Feature",
  "properties": {
    "iso:country":"AU",
    "sg:address":"39 Willis St",
    "sg:city":"Winchelsea",
    "sg:classifiers":[
        {
            "category":"Professional",
            "subcategory":"Engineering",
            "type":"Services"
        }
    ],
    "sg:phone":"+61 3 5267 2011",
    "sg:postcode":"3241",
    "sg:province":"VIC",
    "sg:tags":[
        "engineer"
    ],
    "wof:name":"Knuckey's Winchelsea Pty Ltd",
    "wof:placetype":"venue"
},
  "geometry": {"coordinates":[143.99522399899999,-38.2378005981],"type":"Point"}
}