{
  "type": "Feature",
  "properties": {
    "iso:country":"AU",
    "sg:address":"6 Day Rd",
    "sg:city":"Rockingham",
    "sg:classifiers":[
        {
            "category":"Autos & Motor Vehicles",
            "subcategory":"Automobile Sales",
            "type":"Retail Goods"
        }
    ],
    "sg:phone":"+61 8 9529 1208",
    "sg:postcode":"6168",
    "sg:province":"WA",
    "sg:tags":[
        "car",
        "used"
    ],
    "wof:name":"Wheels In Motion",
    "wof:placetype":"venue"
},
  "geometry": {"coordinates":[115.773979,-32.276039],"type":"Point"}
}