{
  "type": "Feature",
  "properties": {
    "addr:full":"Unit 1/ 2-4 Precision Drv Molendinar QLD 4214",
    "addr:housenumber":"2-4",
    "addr:postcode":"4214",
    "addr:street":"Precision Drv",
    "iso:country":"AU",
    "sg:address":"Unit 1/ 2-4 Precision Drv",
    "sg:city":"Molendinar",
    "sg:classifiers":[
        {
            "category":"Retail",
            "subcategory":"Auto Repair",
            "type":"Services"
        }
    ],
    "sg:phone":"+61 7 5563 3999",
    "sg:postcode":"4214",
    "sg:province":"QLD",
    "sg:tags":[
        "beater",
        "painter",
        "panel"
    ],
    "wof:name":"Gold Coast Paint Works",
    "wof:placetype":"venue"
},
  "geometry": {"coordinates":[153.3618927,-27.9640464783],"type":"Point"}
}