{
  "type": "Feature",
  "properties": {
    "iso:country":"AU",
    "sg:address":"3 Dunlop Rd",
    "sg:city":"Forresters Beach",
    "sg:classifiers":[
        {
            "category":"Professional",
            "subcategory":"Art Services",
            "type":"Services"
        }
    ],
    "sg:phone":"+61 2 4384 2793",
    "sg:postcode":"2260",
    "sg:province":"NSW",
    "sg:tags":[
        "decorator",
        "painter"
    ],
    "wof:name":"Robert J Swan Painting",
    "wof:placetype":"venue"
},
  "geometry": {"coordinates":[151.468063,-33.406815],"type":"Point"}
}