{
  "type": "Feature",
  "properties": {
    "addr:full":"95 Bridge Rd Marsfield NSW 2122",
    "addr:housenumber":"95",
    "addr:postcode":"2122",
    "addr:street":"Bridge Rd",
    "iso:country":"AU",
    "sg:address":"95 Bridge Rd",
    "sg:city":"Marsfield",
    "sg:classifiers":[
        {
            "category":"Building & Trades",
            "subcategory":"Cleaning & Sanitation",
            "type":"Services"
        }
    ],
    "sg:phone":"+61 2 9801 9910",
    "sg:postcode":"2122",
    "sg:province":"NSW",
    "sg:tags":[
        "window"
    ],
    "wof:name":"Antons Window Cleaning",
    "wof:placetype":"venue"
},
  "geometry": {"coordinates":[151.10760498100001,-33.7921142578],"type":"Point"}
}