{
  "type": "Feature",
  "properties": {
    "addr:full":"5 Marathon St Taree NSW 2430",
    "addr:housenumber":"5",
    "addr:postcode":"2430",
    "addr:street":"Marathon St",
    "iso:country":"AU",
    "sg:address":"5 Marathon St",
    "sg:city":"Taree",
    "sg:classifiers":[
        {
            "category":"Wholesale",
            "subcategory":"Apparel",
            "type":"Manufacturing & Wholesale Goods"
        }
    ],
    "sg:phone":"+61 2 6552 2371",
    "sg:postcode":"2430",
    "sg:province":"NSW",
    "sg:tags":[
        "wholesaler",
        "mfrs",
        "uniform"
    ],
    "wof:name":"Coastal Corporate Clothing",
    "wof:placetype":"venue"
},
  "geometry": {"coordinates":[152.461456,-31.913006],"type":"Point"}
}