{
  "type": "Feature",
  "properties": {
    "addr:full":"Cnr Newnham & Logan Rds Upper Mt Gravatt QLD 4122",
    "addr:postcode":"4122",
    "addr:street":"Cnr",
    "iso:country":"AU",
    "sg:address":"Cnr Newnham & Logan Rds",
    "sg:city":"Upper Mt Gravatt",
    "sg:classifiers":[
        {
            "category":"Health Services",
            "subcategory":"Dentist",
            "type":"Services"
        }
    ],
    "sg:phone":"+61 7 3849 4989",
    "sg:postcode":"4122",
    "sg:province":"QLD",
    "wof:name":"Gooley John P J & Assoc",
    "wof:placetype":"venue"
},
  "geometry": {"coordinates":[153.094284058,-27.5322532654],"type":"Point"}
}