{
  "type": "Feature",
  "properties": {
    "iso:country":"AU",
    "sg:address":"Melvista Ave",
    "sg:city":"Nedlands",
    "sg:classifiers":[
        {
            "category":"Sports & Exercise",
            "subcategory":"Golf",
            "type":"Entertainment"
        }
    ],
    "sg:phone":"+61 8 9389 1244",
    "sg:postcode":"6009",
    "sg:province":"WA",
    "sg:tags":[
        "club"
    ],
    "wof:name":"Nedlands Golf Club (Inc)",
    "wof:placetype":"venue"
},
  "geometry": {"coordinates":[115.80837200000001,-31.989164],"type":"Point"}
}