{
  "type": "Feature",
  "properties": {
    "addr:full":"8 Jaques St Ourimbah NSW 2258",
    "addr:housenumber":"8",
    "addr:postcode":"2258",
    "addr:street":"Jaques St",
    "iso:country":"AU",
    "sg:address":"8 Jaques St",
    "sg:city":"Ourimbah",
    "sg:classifiers":[
        {
            "category":"Retail",
            "subcategory":"Storage",
            "type":"Services"
        }
    ],
    "sg:phone":"+61 2 4362 7220",
    "sg:postcode":"2258",
    "sg:province":"NSW",
    "sg:tags":[
        "removal",
        "furniture"
    ],
    "wof:name":"Gamma Carriers",
    "wof:placetype":"venue"
},
  "geometry": {"coordinates":[151.36944580100001,-33.3629837036],"type":"Point"}
}