{
  "type": "Feature",
  "properties": {
    "addr:full":"171 Heaths Rd Hoppers Crossing VIC 3029",
    "addr:housenumber":"171",
    "addr:postcode":"3029",
    "addr:street":"Heaths Rd",
    "iso:country":"AU",
    "sg:address":"171 Heaths Rd",
    "sg:city":"Hoppers Crossing",
    "sg:classifiers":[
        {
            "category":"Health Services",
            "subcategory":"Health Practitioner",
            "type":"Services"
        }
    ],
    "sg:phone":"+61 3 9749 5110",
    "sg:postcode":"3029",
    "sg:province":"VIC",
    "sg:tags":[
        "physiotherapist"
    ],
    "wof:name":"Cahill Ellen",
    "wof:placetype":"venue"
},
  "geometry": {"coordinates":[144.689896,-37.878532],"type":"Point"}
}