{
  "type": "Feature",
  "properties": {
    "iso:country":"AU",
    "sg:address":"12 Chris Crt",
    "sg:city":"Aspendale Gardens",
    "sg:classifiers":[
        {
            "category":"Building & Trades",
            "subcategory":"Construction",
            "type":"Services"
        }
    ],
    "sg:phone":"+61 418 996 869",
    "sg:postcode":"3195",
    "sg:province":"VIC",
    "sg:tags":[
        "contractor"
    ],
    "wof:name":"Geraghty Constructions",
    "wof:placetype":"venue"
},
  "geometry": {"coordinates":[145.11965942399999,-38.0211601257],"type":"Point"}
}