{
  "type": "Feature",
  "properties": {
    "iso:country":"AU",
    "sg:address":"2 Tamlin Pl",
    "sg:city":"Chirnside Park",
    "sg:classifiers":[
        {
            "category":"Utilities",
            "subcategory":"Electric",
            "type":"Services"
        }
    ],
    "sg:phone":"+61 418 306 899",
    "sg:postcode":"3116",
    "sg:province":"VIC",
    "sg:tags":[
        "electrical",
        "contractor"
    ],
    "wof:name":"Baker Electrical Services",
    "wof:placetype":"venue"
},
  "geometry": {"coordinates":[145.301345825,-37.759979248],"type":"Point"}
}