{
  "type": "Feature",
  "properties": {
    "iso:country":"AU",
    "sg:address":"Cnr Coventry & Safety Bay Rds",
    "sg:city":"Safety Bay",
    "sg:classifiers":[
        {
            "category":"Food & Beverages",
            "subcategory":"Supermarket",
            "type":"Retail Goods"
        }
    ],
    "sg:phone":"+61 8 9553 1900",
    "sg:postcode":"6169",
    "sg:province":"WA",
    "sg:tags":[
        "grocery",
        "store"
    ],
    "wof:name":"Supa IGA",
    "wof:placetype":"venue"
},
  "geometry": {"coordinates":[115.71013600000001,-32.293411],"type":"Point"}
}