{
  "type": "Feature",
  "properties": {
    "addr:full":"PO Box 209 Ettalong NSW 2257",
    "addr:postcode":"2257",
    "iso:country":"AU",
    "sg:address":"PO Box 209",
    "sg:city":"Ettalong",
    "sg:classifiers":[
        {
            "category":"Building & Trades",
            "subcategory":"Construction",
            "type":"Services"
        }
    ],
    "sg:phone":"+61 404 870 847",
    "sg:postcode":"2257",
    "sg:province":"NSW",
    "sg:tags":[
        "contractor"
    ],
    "wof:name":"LJ Hall Builders",
    "wof:placetype":"venue"
},
  "geometry": {"coordinates":[151.34234619099999,-33.5241317749],"type":"Point"}
}