{
  "type": "Feature",
  "properties": {
    "iso:country":"AU",
    "sg:address":"Suite 2, Level 1, 825 Zillmere Rd",
    "sg:city":"Aspley",
    "sg:classifiers":[
        {
            "category":"Sports & Exercise",
            "subcategory":"Gym",
            "type":"Entertainment"
        }
    ],
    "sg:phone":"+61 7 3263 9310",
    "sg:postcode":"4034",
    "sg:province":"QLD",
    "sg:tags":[
        "health",
        "fitness"
    ],
    "wof:name":"Designing Women",
    "wof:placetype":"venue"
},
  "geometry": {"coordinates":[153.017517,-27.356058],"type":"Point"}
}