{
  "type": "Feature",
  "properties": {
    "iso:country":"AU",
    "sg:address":"101 Scarborough Beach Rd",
    "sg:city":"Mt Hawthorn",
    "sg:classifiers":[
        {
            "category":"Building & Trades",
            "subcategory":"Plumbing",
            "type":"Services"
        }
    ],
    "sg:phone":"+61 8 9443 3466",
    "sg:postcode":"6016",
    "sg:province":"WA",
    "sg:tags":[
        "consultant"
    ],
    "wof:name":"P J Wright & Associates Pty Ltd",
    "wof:placetype":"venue"
},
  "geometry": {"coordinates":[115.843971252,-31.9234104156],"type":"Point"}
}