{
  "type": "Feature",
  "properties": {
    "addr:full":"140 St George's Tce Perth WA 6000",
    "addr:housenumber":"140",
    "addr:postcode":"6000",
    "addr:street":"St George'S Tce",
    "iso:country":"AU",
    "sg:address":"140 St George's Tce",
    "sg:city":"Perth",
    "sg:classifiers":[
        {
            "category":"Professional",
            "subcategory":"Computer Services",
            "type":"Services"
        }
    ],
    "sg:phone":"+61 8 9422 2000",
    "sg:postcode":"6000",
    "sg:province":"WA",
    "sg:tags":[
        "consultant",
        "system"
    ],
    "wof:name":"Harman Information Technology",
    "wof:placetype":"venue"
},
  "geometry": {"coordinates":[115.852546692,-31.9546794891],"type":"Point"}
}