{
  "type": "Feature",
  "properties": {
    "addr:full":"30 Nuggett St Kerang VIC 3579",
    "addr:housenumber":"30",
    "addr:postcode":"3579",
    "addr:street":"Nuggett St",
    "iso:country":"AU",
    "sg:address":"30 Nuggett St",
    "sg:city":"Kerang",
    "sg:classifiers":[
        {
            "category":"Farming",
            "subcategory":"Dairy Farm",
            "type":"Manufacturing & Wholesale Goods"
        }
    ],
    "sg:phone":"+61 3 5452 1087",
    "sg:postcode":"3579",
    "sg:province":"VIC",
    "wof:name":"Gannawarra Milk Supply",
    "wof:placetype":"venue"
},
  "geometry": {"coordinates":[143.918258667,-35.7215423584],"type":"Point"}
}