{
  "type": "Feature",
  "properties": {
    "addr:full":"246 Main St Lilydale VIC 3140",
    "addr:housenumber":"246",
    "addr:postcode":"3140",
    "addr:street":"Main St",
    "iso:country":"AU",
    "sg:address":"246 Main St",
    "sg:city":"Lilydale",
    "sg:classifiers":[
        {
            "category":"Retail",
            "subcategory":"Storage",
            "type":"Services"
        }
    ],
    "sg:phone":"+61 3 9735 0345",
    "sg:postcode":"3140",
    "sg:province":"VIC",
    "wof:name":"Maroondah Self Storage",
    "wof:placetype":"venue"
},
  "geometry": {"coordinates":[145.34681701700001,-37.7612876892],"type":"Point"}
}