{
  "type": "Feature",
  "properties": {
    "iso:country":"AU",
    "sg:address":"Farm 91 M.S Green",
    "sg:city":"Rowan",
    "sg:classifiers":[
        {
            "category":"Farming",
            "subcategory":"Farm",
            "type":"Manufacturing & Wholesale Goods"
        }
    ],
    "sg:phone":"+61 2 6954 9151",
    "sg:postcode":"2650",
    "sg:province":"NSW",
    "sg:tags":[
        "farmer"
    ],
    "wof:name":"Evans D B",
    "wof:placetype":"venue"
},
  "geometry": {"coordinates":[147.327667236,-35.1949386597],"type":"Point"}
}