{
  "type": "Feature",
  "properties": {
    "addr:full":"Lot 1533 Pyramid Rd Karratha WA 6714",
    "addr:housenumber":"1533",
    "addr:postcode":"6714",
    "addr:street":"Pyramid Rd",
    "iso:country":"AU",
    "sg:address":"Lot 1533 Pyramid Rd",
    "sg:city":"Karratha",
    "sg:classifiers":[
        {
            "category":"Professional",
            "subcategory":"Engineering",
            "type":"Services"
        }
    ],
    "sg:phone":"+61 8 9144 4062",
    "sg:postcode":"6714",
    "sg:province":"WA",
    "sg:tags":[
        "building",
        "prefabricated",
        "transportable",
        "industrial",
        "commercial"
    ],
    "wof:name":"Ausco Building Systems",
    "wof:placetype":"venue"
},
  "geometry": {"coordinates":[116.843971252,-20.7356300354],"type":"Point"}
}