{
  "type": "Feature",
  "properties": {
    "addr:full":"1 Cobborah Rd Dubbo NSW 2830",
    "addr:housenumber":"1",
    "addr:postcode":"2830",
    "addr:street":"Cobborah Rd",
    "iso:country":"AU",
    "sg:address":"1 Cobborah Rd",
    "sg:city":"Dubbo",
    "sg:classifiers":[
        {
            "category":"Building & Trades",
            "subcategory":"Construction",
            "type":"Services"
        }
    ],
    "sg:phone":"+61 2 6882 4266",
    "sg:postcode":"2830",
    "sg:province":"NSW",
    "sg:tags":[
        "joinery"
    ],
    "wof:name":"Ramiens Timber Co Dubbo",
    "wof:placetype":"venue"
},
  "geometry": {"coordinates":[148.61590576200001,-32.2437057495],"type":"Point"}
}