{
  "type": "Feature",
  "properties": {
    "iso:country":"AU",
    "sg:address":"40 Shiers St",
    "sg:city":"Alphington",
    "sg:classifiers":[
        {
            "category":"Health Services",
            "subcategory":"Health Practitioner",
            "type":"Services"
        }
    ],
    "sg:phone":"+61 3 9499 6215",
    "sg:postcode":"3078",
    "sg:province":"VIC",
    "sg:tags":[
        "psychotherapist"
    ],
    "wof:name":"Robyn Riley",
    "wof:placetype":"venue"
},
  "geometry": {"coordinates":[145.03094482399999,-37.7720031738],"type":"Point"}
}