{
  "type": "Feature",
  "properties": {
    "addr:full":"21 The Boulevarde St Toronto NSW 2283",
    "addr:housenumber":"21",
    "addr:postcode":"2283",
    "addr:street":"The Boulevarde St",
    "iso:country":"AU",
    "sg:address":"21 The Boulevarde St",
    "sg:city":"Toronto",
    "sg:classifiers":[
        {
            "category":"Real Estate",
            "subcategory":"Real Estate Agent",
            "type":"Services"
        }
    ],
    "sg:phone":"+61 2 4959 6577",
    "sg:postcode":"2283",
    "sg:province":"NSW",
    "wof:name":"Ray White Real Estate",
    "wof:placetype":"venue"
},
  "geometry": {"coordinates":[151.585083008,-33.0113792419],"type":"Point"}
}