{
  "type": "Feature",
  "properties": {
    "addr:full":"26 Northgate Drv Thomastown VIC 3074",
    "addr:housenumber":"26",
    "addr:postcode":"3074",
    "addr:street":"Northgate Drv",
    "iso:country":"AU",
    "sg:address":"26 Northgate Drv",
    "sg:city":"Thomastown",
    "sg:classifiers":[
        {
            "category":"Shopping",
            "subcategory":"Stationery & Office Supplies",
            "type":"Retail Goods"
        }
    ],
    "sg:phone":"+61 3 9464 6644",
    "sg:postcode":"3074",
    "sg:province":"VIC",
    "sg:tags":[
        "equipment",
        "display",
        "exhibition"
    ],
    "wof:name":"EG Design",
    "wof:placetype":"venue"
},
  "geometry": {"coordinates":[145.039962769,-37.6907615662],"type":"Point"}
}