{
  "type": "Feature",
  "properties": {
    "addr:full":"Northside Plaza 222 Musgrave St North Rockhampton QLD 4701",
    "addr:housenumber":"222",
    "addr:postcode":"4701",
    "addr:street":"Musgrave St North",
    "iso:country":"AU",
    "sg:address":"Northside Plaza 222 Musgrave St",
    "sg:city":"North Rockhampton",
    "sg:classifiers":[
        {
            "category":"Health Services",
            "subcategory":"Doctor",
            "type":"Services"
        }
    ],
    "sg:phone":"+61 7 4927 7611",
    "sg:postcode":"4701",
    "sg:province":"QLD",
    "sg:tags":[
        "medical",
        "practitioner"
    ],
    "wof:name":"Musgrave Street Family Practice",
    "wof:placetype":"venue"
},
  "geometry": {"coordinates":[150.523513794,-23.35978508],"type":"Point"}
}