{
  "type": "Feature",
  "properties": {
    "iso:country":"AU",
    "sg:address":"2/ 3 Wolseley Pl",
    "sg:city":"Thomastown",
    "sg:classifiers":[
        {
            "category":"Autos & Motor Vehicles",
            "subcategory":"Auto Supplies",
            "type":"Retail Goods"
        }
    ],
    "sg:phone":"+61 1800 039 612",
    "sg:postcode":"3074",
    "sg:province":"VIC",
    "sg:tags":[
        "battery",
        "automotive"
    ],
    "wof:name":"A AAAFBSR PTY LTD",
    "wof:placetype":"venue"
},
  "geometry": {"coordinates":[145.001663208,-37.6895828247],"type":"Point"}
}