{
  "type": "Feature",
  "properties": {
    "addr:full":"119 Kings Rd Hyde Park QLD 4812",
    "addr:housenumber":"119",
    "addr:postcode":"4812",
    "addr:street":"Kings Rd",
    "iso:country":"AU",
    "sg:address":"119 Kings Rd",
    "sg:city":"Hyde Park",
    "sg:classifiers":[
        {
            "category":"Health Services",
            "subcategory":"Doctor",
            "type":"Services"
        }
    ],
    "sg:phone":"+61 7 4725 2677",
    "sg:postcode":"4812",
    "sg:province":"QLD",
    "sg:tags":[
        "medical",
        "practitioner"
    ],
    "wof:name":"North Queensland Day Surgical Centre",
    "wof:placetype":"venue"
},
  "geometry": {"coordinates":[146.79156499999999,-19.279669],"type":"Point"}
}