{
  "type": "Feature",
  "properties": {
    "addr:full":"38 Aitkens Rd Warrnambool VIC 3280",
    "addr:housenumber":"38",
    "addr:postcode":"3280",
    "addr:street":"Aitkens Rd",
    "iso:country":"AU",
    "sg:address":"38 Aitkens Rd",
    "sg:city":"Warrnambool",
    "sg:classifiers":[
        {
            "category":"Health Services",
            "subcategory":"Nursing And Care Facility",
            "type":"Services"
        }
    ],
    "sg:phone":"+61 408 585 467",
    "sg:postcode":"3280",
    "sg:province":"VIC",
    "sg:tags":[
        "treatment",
        "preservation",
        "timber"
    ],
    "wof:name":"Mick O&#039;Brien Floor Sanding",
    "wof:placetype":"venue"
},
  "geometry": {"coordinates":[142.470214844,-38.3731307983],"type":"Point"}
}