{
  "type": "Feature",
  "properties": {
    "addr:full":"10 Casuarina St Oak Flats NSW 2529",
    "addr:housenumber":"10",
    "addr:postcode":"2529",
    "addr:street":"Casuarina St Oak Flats",
    "iso:country":"AU",
    "sg:address":"10 Casuarina St",
    "sg:city":"Oak Flats",
    "sg:classifiers":[
        {
            "category":"Freight",
            "type":"Transportation"
        }
    ],
    "sg:phone":"+61 2 4256 6142",
    "sg:postcode":"2529",
    "sg:province":"NSW",
    "sg:tags":[
        "light",
        "carrier"
    ],
    "wof:name":"Leisure Coast Removals",
    "wof:placetype":"venue"
},
  "geometry": {"coordinates":[150.80744934099999,-34.5655288696],"type":"Point"}
}