{
  "type": "Feature",
  "properties": {
    "addr:full":"Murray Valley Hwy Cobram NSW 3644",
    "addr:postcode":"3644",
    "addr:street":"Valley Hwy",
    "iso:country":"AU",
    "sg:address":"Murray Valley Hwy",
    "sg:city":"Cobram",
    "sg:classifiers":[
        {
            "category":"Arts & Performance",
            "subcategory":"Art Gallery",
            "type":"Entertainment"
        }
    ],
    "sg:phone":"+61 3 5871 1451",
    "sg:postcode":"3644",
    "sg:province":"NSW",
    "wof:name":"Sunset Studio Gallery",
    "wof:placetype":"venue"
},
  "geometry": {"coordinates":[145.59437560999999,-35.9254798889],"type":"Point"}
}