{
  "type": "Feature",
  "properties": {
    "iso:country":"AU",
    "sg:address":"16 Beresford Ave",
    "sg:city":"Chatswood",
    "sg:classifiers":[
        {
            "category":"Health Services",
            "subcategory":"Health Practitioner",
            "type":"Services"
        }
    ],
    "sg:phone":"+61 2 9419 5108",
    "sg:postcode":"2067",
    "sg:province":"NSW",
    "sg:tags":[
        "homoeopath"
    ],
    "wof:name":"Crook Laima",
    "wof:placetype":"venue"
},
  "geometry": {"coordinates":[151.173370361,-33.8031997681],"type":"Point"}
}