{
  "type": "Feature",
  "properties": {
    "addr:full":"304,260 Little Collins St Melbourne VIC 3000",
    "addr:housenumber":"304,260",
    "addr:postcode":"3000",
    "addr:street":"Little Collins St",
    "iso:country":"AU",
    "sg:address":"304,260 Little Collins St",
    "sg:city":"Melbourne",
    "sg:classifiers":[
        {
            "category":"Real Estate",
            "subcategory":"Real Estate Operator",
            "type":"Services"
        }
    ],
    "sg:phone":"+61 405 774 352",
    "sg:postcode":"3000",
    "sg:province":"VIC",
    "sg:tags":[
        "building",
        "consultant",
        "management"
    ],
    "wof:name":"Carillon Group",
    "wof:placetype":"venue"
},
  "geometry": {"coordinates":[144.966140747,-37.8143501282],"type":"Point"}
}