{
  "type": "Feature",
  "properties": {
    "iso:country":"AU",
    "sg:address":"27 Gundagai St",
    "sg:city":"Coffs Harbour",
    "sg:classifiers":[
        {
            "category":"Banks & Credit Unions",
            "subcategory":"Financial Services",
            "type":"Services"
        }
    ],
    "sg:phone":"+61 2 6652 7444",
    "sg:postcode":"2450",
    "sg:province":"NSW",
    "sg:tags":[
        "loan",
        "finance",
        "mortgage"
    ],
    "wof:name":"The Mortgage Bureau Coffs Harbour",
    "wof:placetype":"venue"
},
  "geometry": {"coordinates":[153.106262,-30.29192],"type":"Point"}
}