{
  "type": "Feature",
  "properties": {
    "iso:country":"AU",
    "sg:address":"64 Mount Combe Rd",
    "sg:city":"Yandina",
    "sg:classifiers":[
        {
            "category":"Arts & Performance",
            "subcategory":"Art Gallery",
            "type":"Entertainment"
        }
    ],
    "sg:phone":"+61 7 5446 8042",
    "sg:postcode":"4561",
    "sg:province":"QLD",
    "wof:name":"Van Dorssen Art Studio",
    "wof:placetype":"venue"
},
  "geometry": {"coordinates":[152.94830322300001,-26.585100174],"type":"Point"}
}