{
  "type": "Feature",
  "properties": {
    "addr:full":"5 Collins St Narrabeen NSW 2101",
    "addr:housenumber":"5",
    "addr:postcode":"2101",
    "addr:street":"Collins St",
    "iso:country":"AU",
    "sg:address":"5 Collins St",
    "sg:city":"Narrabeen",
    "sg:classifiers":[
        {
            "category":"Professional",
            "subcategory":"Computer Services",
            "type":"Services"
        }
    ],
    "sg:phone":"+61 2 9970 8588",
    "sg:postcode":"2101",
    "sg:province":"NSW",
    "sg:tags":[
        "equipment",
        "networking",
        "installation"
    ],
    "wof:name":"Powertronix Electrical Services",
    "wof:placetype":"venue"
},
  "geometry": {"coordinates":[151.30169699999999,-33.701534],"type":"Point"}
}