{
  "type": "Feature",
  "properties": {
    "iso:country":"AU",
    "sg:address":"58 Hodgson Crs",
    "sg:city":"Pearce",
    "sg:classifiers":[
        {
            "category":"Health Services",
            "subcategory":"Doctor",
            "type":"Services"
        }
    ],
    "sg:phone":"+61 2 6286 1010",
    "sg:postcode":"2607",
    "sg:province":"ACT",
    "sg:tags":[
        "medical",
        "practitioner"
    ],
    "wof:name":"Cleary Gerard C",
    "wof:placetype":"venue"
},
  "geometry": {"coordinates":[149.08221435600001,-35.3647613525],"type":"Point"}
}