{
  "type": "Feature",
  "properties": {
    "addr:full":"9 Bauhinia St Birkdale QLD 4159",
    "addr:housenumber":"9",
    "addr:postcode":"4159",
    "addr:street":"Bauhinia St",
    "iso:country":"AU",
    "sg:address":"9 Bauhinia St",
    "sg:city":"Birkdale",
    "sg:classifiers":[
        {
            "category":"Personal",
            "subcategory":"Massage",
            "type":"Services"
        }
    ],
    "sg:phone":"+61 417 193 919",
    "sg:postcode":"4159",
    "sg:province":"QLD",
    "sg:tags":[
        "therapy"
    ],
    "wof:name":"Bodytone The Therapist",
    "wof:placetype":"venue"
},
  "geometry": {"coordinates":[153.214553833,-27.4980354309],"type":"Point"}
}