{
  "type": "Feature",
  "properties": {
    "iso:country":"AU",
    "sg:address":"Selhurst St",
    "sg:city":"Coopers Plains",
    "sg:classifiers":[
        {
            "category":"Wholesale",
            "subcategory":"Scrap",
            "type":"Manufacturing & Wholesale Goods"
        }
    ],
    "sg:phone":"+61 7 3344 4444",
    "sg:postcode":"4108",
    "sg:province":"QLD",
    "sg:tags":[
        "merchant",
        "metal"
    ],
    "wof:name":"Wanless Metal Recyclers",
    "wof:placetype":"venue"
},
  "geometry": {"coordinates":[153.036087036,-27.5714073181],"type":"Point"}
}