{
  "type": "Feature",
  "properties": {
    "addr:full":"1251 Albany Hwy Cannington WA 6107",
    "addr:housenumber":"1251",
    "addr:postcode":"6107",
    "addr:street":"Albany Hwy",
    "iso:country":"AU",
    "sg:address":"1251 Albany Hwy",
    "sg:city":"Cannington",
    "sg:classifiers":[
        {
            "category":"Manufacturing",
            "subcategory":"Motor Vehicles & Parts",
            "type":"Manufacturing & Wholesale Goods"
        }
    ],
    "sg:phone":"+61 1800 198 093",
    "sg:postcode":"6107",
    "sg:province":"WA",
    "sg:tags":[
        "replacement"
    ],
    "wof:name":"Total Subaru",
    "wof:placetype":"venue"
},
  "geometry": {"coordinates":[115.927978516,-32.0132064819],"type":"Point"}
}