{
  "type": "Feature",
  "properties": {
    "addr:full":"124 Gardenvale Rd Gardenvale VIC 3185",
    "addr:housenumber":"124",
    "addr:postcode":"3185",
    "addr:street":"Gardenvale Rd",
    "iso:country":"AU",
    "sg:address":"124 Gardenvale Rd",
    "sg:city":"Gardenvale",
    "sg:classifiers":[
        {
            "category":"Personal",
            "subcategory":"Beauty Salon",
            "type":"Services"
        }
    ],
    "sg:phone":"+61 3 9530 8300",
    "sg:postcode":"3185",
    "sg:province":"VIC",
    "sg:tags":[
        "hairdresser"
    ],
    "wof:name":"Chicago Hair",
    "wof:placetype":"venue"
},
  "geometry": {"coordinates":[145.00630188,-37.8975486755],"type":"Point"}
}