{
  "type": "Feature",
  "properties": {
    "iso:country":"AU",
    "sg:address":"527 Beaufort St",
    "sg:city":"Highgate",
    "sg:classifiers":[
        {
            "category":"Food & Beverages",
            "subcategory":"Supermarket",
            "type":"Retail Goods"
        }
    ],
    "sg:phone":"+61 8 9328 9570",
    "sg:postcode":"6003",
    "sg:province":"WA",
    "sg:tags":[
        "grocery",
        "store"
    ],
    "wof:name":"Daily Supermarket",
    "wof:placetype":"venue"
},
  "geometry": {"coordinates":[115.86988830599999,-31.9377555847],"type":"Point"}
}