{
  "type": "Feature",
  "properties": {
    "addr:full":"Firths Rd Benalla VIC 3672",
    "addr:postcode":"3672",
    "addr:street":"Firths Rd",
    "iso:country":"AU",
    "sg:address":"Firths Rd",
    "sg:city":"Benalla",
    "sg:classifiers":[
        {
            "category":"Wholesale",
            "subcategory":"Meat",
            "type":"Manufacturing & Wholesale Goods"
        }
    ],
    "sg:phone":"+61 3 5762 6897",
    "sg:postcode":"3672",
    "sg:province":"VIC",
    "sg:tags":[
        "abattoir"
    ],
    "wof:name":"C A Sinclair",
    "wof:placetype":"venue"
},
  "geometry": {"coordinates":[145.93125900000001,-36.57058],"type":"Point"}
}