{
  "type": "Feature",
  "properties": {
    "addr:full":"Lakelands Drv Dapto NSW 2530",
    "addr:postcode":"2530",
    "addr:street":"Lakelands Drv",
    "iso:country":"AU",
    "sg:address":"Lakelands Drv",
    "sg:city":"Dapto",
    "sg:classifiers":[
        {
            "category":"Education",
            "subcategory":"School",
            "type":"Public Place"
        }
    ],
    "sg:phone":"+61 2 4261 1540",
    "sg:postcode":"2530",
    "sg:province":"NSW",
    "sg:tags":[
        "state",
        "-",
        "nsw"
    ],
    "wof:name":"Lakelands Public School",
    "wof:placetype":"venue"
},
  "geometry": {"coordinates":[150.79481506400001,-34.5023155212],"type":"Point"}
}