{
  "type": "Feature",
  "properties": {
    "iso:country":"AU",
    "sg:address":"88- 90 Railway Rd",
    "sg:city":"Blackburn",
    "sg:classifiers":[
        {
            "category":"Retail",
            "subcategory":"Auto Repair",
            "type":"Services"
        }
    ],
    "sg:phone":"+61 3 9878 3222",
    "sg:postcode":"3130",
    "sg:province":"VIC",
    "sg:tags":[
        "beater",
        "painter",
        "panel"
    ],
    "wof:name":"Bencar Nominees",
    "wof:placetype":"venue"
},
  "geometry": {"coordinates":[145.156814575,-37.8185195923],"type":"Point"}
}