{
  "type": "Feature",
  "properties": {
    "addr:full":"139- 141 Darling St Dubbo NSW 2830",
    "addr:housenumber":"141",
    "addr:postcode":"2830",
    "addr:street":"Darling St",
    "iso:country":"AU",
    "sg:address":"139- 141 Darling St",
    "sg:city":"Dubbo",
    "sg:classifiers":[
        {
            "category":"Home & Garden",
            "subcategory":"Carpets & Floor Coverings",
            "type":"Retail Goods"
        }
    ],
    "sg:phone":"+61 2 6882 7077",
    "sg:postcode":"2830",
    "sg:province":"NSW",
    "sg:tags":[
        "wood"
    ],
    "wof:name":"Carpet Court Dubbo",
    "wof:placetype":"venue"
},
  "geometry": {"coordinates":[148.60604858400001,-32.2486076355],"type":"Point"}
}