{
  "type": "Feature",
  "properties": {
    "addr:full":"Burchill St Loganholme QLD 4129",
    "addr:postcode":"4129",
    "addr:street":"Burchill St",
    "iso:country":"AU",
    "sg:address":"Burchill St",
    "sg:city":"Loganholme",
    "sg:classifiers":[
        {
            "category":"Organizations",
            "subcategory":"Membership Organization",
            "type":"Services"
        }
    ],
    "sg:phone":"+61 7 5547 0191",
    "sg:postcode":"4129",
    "sg:province":"QLD",
    "sg:tags":[
        "club",
        "car"
    ],
    "wof:name":"Rods Inc Hot Rod Club, Loganholme",
    "wof:placetype":"venue"
},
  "geometry": {"coordinates":[153.19070434599999,-27.6799163818],"type":"Point"}
}