{
  "type": "Feature",
  "properties": {
    "iso:country":"AU",
    "sg:address":"344 Glen Huntly Rd",
    "sg:city":"Elsternwick",
    "sg:classifiers":[
        {
            "category":"Shopping",
            "subcategory":"Mobile Phones",
            "type":"Retail Goods"
        }
    ],
    "sg:phone":"+61 3 9532 9355",
    "sg:postcode":"3185",
    "sg:province":"VIC",
    "sg:tags":[
        "telephone",
        "accessory"
    ],
    "wof:name":"Leading Edge Telecoms Elsternwick",
    "wof:placetype":"venue"
},
  "geometry": {"coordinates":[145.00331115700001,-37.8847160339],"type":"Point"}
}