{
  "type": "Feature",
  "properties": {
    "addr:full":"Cnr Bruce Hwy & Excelsior Rd Gympie QLD 4570",
    "addr:postcode":"4570",
    "addr:street":"Cnr Bruce Hwy & Excelsior Rd",
    "iso:country":"AU",
    "sg:address":"Cnr Bruce Hwy & Excelsior Rd",
    "sg:city":"Gympie",
    "sg:classifiers":[
        {
            "category":"Fast Food",
            "type":"Food & Drink"
        }
    ],
    "sg:phone":"+61 1300 749 924",
    "sg:postcode":"4570",
    "sg:province":"QLD",
    "sg:tags":[
        "away",
        "take"
    ],
    "wof:name":"Pizza Hut",
    "wof:placetype":"venue"
},
  "geometry": {"coordinates":[152.65594482399999,-26.190279007],"type":"Point"}
}