{
  "type": "Feature",
  "properties": {
    "addr:full":"38 Progress Drv Nightcliff NT 0810",
    "addr:housenumber":"38",
    "addr:postcode":"nt 0810",
    "addr:street":"Progress Drv",
    "iso:country":"AU",
    "sg:address":"38 Progress Drv",
    "sg:city":"Nightcliff",
    "sg:classifiers":[
        {
            "category":"Fast Food",
            "type":"Food & Drink"
        }
    ],
    "sg:phone":"+61 8 8985 4758",
    "sg:postcode":"0810",
    "sg:province":"NT",
    "sg:tags":[
        "away",
        "take"
    ],
    "wof:name":"Nightcliff Fish & Chip Shop",
    "wof:placetype":"venue"
},
  "geometry": {"coordinates":[130.85096740700001,-12.3876447678],"type":"Point"}
}