{
  "type": "Feature",
  "properties": {
    "addr:full":"5 John St Kingston TAS 7050",
    "addr:housenumber":"5",
    "addr:postcode":"7050",
    "addr:street":"John St",
    "iso:country":"AU",
    "sg:address":"5 John St",
    "sg:city":"Kingston",
    "sg:classifiers":[
        {
            "category":"Health Services",
            "subcategory":"Doctor",
            "type":"Services"
        }
    ],
    "sg:phone":"+61 3 6229 1987",
    "sg:postcode":"7050",
    "sg:province":"TAS",
    "sg:tags":[
        "medical",
        "practitioner"
    ],
    "wof:name":"Pitney Peter",
    "wof:placetype":"venue"
},
  "geometry": {"coordinates":[147.309021,-42.975315],"type":"Point"}
}