{
  "type": "Feature",
  "properties": {
    "iso:country":"AU",
    "sg:address":"14 Towradgi Rd",
    "sg:city":"Towradgi",
    "sg:classifiers":[
        {
            "category":"Professional",
            "subcategory":"Printing & Photocopies",
            "type":"Services"
        }
    ],
    "sg:phone":"+61 2 4284 2448",
    "sg:postcode":"2518",
    "sg:province":"NSW",
    "sg:tags":[
        "textile",
        "clothing"
    ],
    "wof:name":"BS T-Shirt & Screen Printing",
    "wof:placetype":"venue"
},
  "geometry": {"coordinates":[150.908478,-34.384483],"type":"Point"}
}