{
  "type": "Feature",
  "properties": {
    "addr:full":"Gate Lodge Birdwood Ave Melbourne VIC 3000",
    "addr:postcode":"3000",
    "addr:street":"Birdwood Ave",
    "iso:country":"AU",
    "sg:address":"Gate Lodge Birdwood Ave",
    "sg:city":"Melbourne",
    "sg:classifiers":[
        {
            "category":"Education",
            "subcategory":"University",
            "type":"Public Place"
        }
    ],
    "sg:phone":"+61 3 9650 6398",
    "sg:postcode":"3000",
    "sg:province":"VIC",
    "sg:tags":[
        "educational",
        "organisation",
        "cultural"
    ],
    "wof:name":"Friends of the Royal Botanic Gardens Melbourne Inc",
    "wof:placetype":"venue"
},
  "geometry": {"coordinates":[144.97308349599999,-37.8278198242],"type":"Point"}
}