{
  "type": "Feature",
  "properties": {
    "addr:full":"20 Lincon St Clonbinane VIC 3658",
    "addr:housenumber":"20",
    "addr:postcode":"3658",
    "addr:street":"Lincon St",
    "iso:country":"AU",
    "sg:address":"20 Lincon St",
    "sg:city":"Clonbinane",
    "sg:classifiers":[
        {
            "category":"Professional",
            "type":"Services"
        }
    ],
    "sg:phone":"+61 428 431 927",
    "sg:postcode":"3658",
    "sg:province":"VIC",
    "sg:tags":[
        "transport"
    ],
    "wof:name":"E & C Pty Ltd",
    "wof:placetype":"venue"
},
  "geometry": {"coordinates":[145.068527222,-37.2999801636],"type":"Point"}
}