{
  "type": "Feature",
  "properties": {
    "addr:full":"Level 20, 264- 278 George St Sydney NSW 2000",
    "addr:housenumber":"264 278",
    "addr:postcode":"2000",
    "addr:street":"George St",
    "iso:country":"AU",
    "sg:address":"Level 20, 264- 278 George St",
    "sg:city":"Sydney",
    "sg:classifiers":[
        {
            "category":"Professional",
            "subcategory":"Employment Agencies",
            "type":"Services"
        }
    ],
    "sg:phone":"+61 2 8274 3900",
    "sg:postcode":"2000",
    "sg:province":"NSW",
    "wof:name":"Hallis",
    "wof:placetype":"venue"
},
  "geometry": {"coordinates":[151.20750427199999,-33.864906311],"type":"Point"}
}