{
  "type": "Feature",
  "properties": {
    "addr:full":"55 Patterson St Mt Nasura WA 6112",
    "addr:housenumber":"55",
    "addr:postcode":"6112",
    "addr:street":"Patterson St;Nasura",
    "iso:country":"AU",
    "sg:address":"55 Patterson St",
    "sg:city":"Mt Nasura",
    "sg:classifiers":[
        {
            "category":"Professional",
            "subcategory":"Engineering",
            "type":"Services"
        }
    ],
    "sg:phone":"+61 412 773 217",
    "sg:postcode":"6112",
    "sg:province":"WA",
    "sg:tags":[
        "consulting",
        "engineer"
    ],
    "wof:name":"KMCT Engineering Pty Ltd",
    "wof:placetype":"venue"
},
  "geometry": {"coordinates":[116.032432556,-32.1327056885],"type":"Point"}
}