{
  "type": "Feature",
  "properties": {
    "addr:full":"1 Fry St Chatswood NSW 2067",
    "addr:housenumber":"1",
    "addr:postcode":"2067",
    "addr:street":"Fry St",
    "iso:country":"AU",
    "sg:address":"1 Fry St",
    "sg:city":"Chatswood",
    "sg:classifiers":[
        {
            "category":"Building & Trades",
            "subcategory":"Construction",
            "type":"Services"
        }
    ],
    "sg:phone":"+61 2 9419 4918",
    "sg:postcode":"2067",
    "sg:province":"NSW",
    "sg:tags":[
        "stonework",
        "stone",
        "mason"
    ],
    "wof:name":"Artarmon Building Services",
    "wof:placetype":"venue"
},
  "geometry": {"coordinates":[151.19435119600001,-33.7992362976],"type":"Point"}
}