{
  "type": "Feature",
  "properties": {
    "addr:full":"3 Burnie Crt Rochedale South QLD 4123",
    "addr:postcode":"4123",
    "addr:street":"Burnie Crt",
    "iso:country":"AU",
    "sg:address":"3 Burnie Crt",
    "sg:city":"Rochedale South",
    "sg:classifiers":[
        {
            "category":"Insurance",
            "subcategory":"Hazard Insurance",
            "type":"Services"
        }
    ],
    "sg:phone":"+61 7 3841 3857",
    "sg:postcode":"4123",
    "sg:province":"QLD",
    "sg:tags":[
        "loss",
        "adjuster",
        "assessor"
    ],
    "wof:name":"Robinsons Insurance Loss Adjusters",
    "wof:placetype":"venue"
},
  "geometry": {"coordinates":[153.14207458499999,-27.5957736969],"type":"Point"}
}