{
  "type": "Feature",
  "properties": {
    "iso:country":"AU",
    "sg:address":"533 Kiewa St",
    "sg:city":"Albury",
    "sg:classifiers":[
        {
            "category":"Banks & Credit Unions",
            "subcategory":"Financial Services",
            "type":"Services"
        }
    ],
    "sg:phone":"+61 2 6041 1177",
    "sg:postcode":"2640",
    "sg:province":"NSW",
    "sg:tags":[
        "planning"
    ],
    "wof:name":"Moriarty Financial Services",
    "wof:placetype":"venue"
},
  "geometry": {"coordinates":[146.91716003400001,-36.0711174011],"type":"Point"}
}