{
  "type": "Feature",
  "properties": {
    "iso:country":"AU",
    "sg:address":"Suite P1 2 Portrush Rd",
    "sg:city":"Payneham",
    "sg:classifiers":[
        {
            "category":"Autos & Motor Vehicles",
            "subcategory":"Automobile Sales",
            "type":"Retail Goods"
        }
    ],
    "sg:phone":"+61 8 8165 1467",
    "sg:postcode":"5070",
    "sg:province":"SA",
    "sg:tags":[
        "car",
        "new"
    ],
    "wof:name":"Hyundai Motor Company Australia Pty Ltd",
    "wof:placetype":"venue"
},
  "geometry": {"coordinates":[138.63929748499999,-34.8966178894],"type":"Point"}
}