{
  "type": "Feature",
  "properties": {
    "addr:full":"17 Moore St Moe VIC 3825",
    "addr:housenumber":"17",
    "addr:postcode":"3825",
    "addr:street":"Moore St",
    "iso:country":"AU",
    "sg:address":"17 Moore St",
    "sg:city":"Moe",
    "sg:classifiers":[
        {
            "category":"Communications",
            "subcategory":"Film & Video Production",
            "type":"Services"
        }
    ],
    "sg:phone":"+61 3 5127 8022",
    "sg:postcode":"3825",
    "sg:province":"VIC",
    "sg:tags":[
        "dvd",
        "library"
    ],
    "wof:name":"Magnum Movies",
    "wof:placetype":"venue"
},
  "geometry": {"coordinates":[146.26149000000001,-38.174271],"type":"Point"}
}