{
  "type": "Feature",
  "properties": {
    "addr:full":"217 Beams Rd Taigum QLD 4018",
    "addr:housenumber":"217",
    "addr:postcode":"4018",
    "addr:street":"Beams Rd",
    "iso:country":"AU",
    "sg:address":"217 Beams Rd",
    "sg:city":"Taigum",
    "sg:classifiers":[
        {
            "category":"Travel",
            "subcategory":"Hotels & Motels",
            "type":"Entertainment"
        }
    ],
    "sg:phone":"+61 7 3865 3888",
    "sg:postcode":"4018",
    "sg:province":"QLD",
    "sg:tags":[
        "accommodation"
    ],
    "wof:name":"Taigum Tavern",
    "wof:placetype":"venue"
},
  "geometry": {"coordinates":[153.048813,-27.351427],"type":"Point"}
}