{
  "type": "Feature",
  "properties": {
    "addr:full":"60 Piper St Yarrawonga VIC 3730",
    "addr:housenumber":"60",
    "addr:postcode":"3730",
    "addr:street":"Piper St",
    "iso:country":"AU",
    "sg:address":"60 Piper St",
    "sg:city":"Yarrawonga",
    "sg:classifiers":[
        {
            "category":"Professional",
            "subcategory":"Printing & Photocopies",
            "type":"Services"
        }
    ],
    "sg:phone":"+61 3 5743 3262",
    "sg:postcode":"3730",
    "sg:province":"VIC",
    "sg:tags":[
        "trophy"
    ],
    "wof:name":"Border Trophies",
    "wof:placetype":"venue"
},
  "geometry": {"coordinates":[146.01153564399999,-36.010887146],"type":"Point"}
}