{
  "type": "Feature",
  "properties": {
    "addr:full":"19 Dalton St Redcliffe QLD 4020",
    "addr:housenumber":"19",
    "addr:postcode":"4020",
    "addr:street":"Dalton St",
    "iso:country":"AU",
    "sg:address":"19 Dalton St",
    "sg:city":"Redcliffe",
    "sg:classifiers":[
        {
            "category":"Building & Trades",
            "subcategory":"Construction",
            "type":"Services"
        }
    ],
    "sg:phone":"+61 7 3284 4069",
    "sg:postcode":"4020",
    "sg:province":"QLD",
    "sg:tags":[
        "industrial",
        "commercial",
        "air conditioning"
    ],
    "wof:name":"North Pine (Aust) Pty Ltd",
    "wof:placetype":"venue"
},
  "geometry": {"coordinates":[153.09522999999999,-27.224745],"type":"Point"}
}