{
  "type": "Feature",
  "properties": {
    "addr:full":"15/ 43 Butterfield St Herston QLD 4006",
    "addr:housenumber":"15 / 43",
    "addr:postcode":"4006",
    "addr:street":"Butterfield St",
    "iso:country":"AU",
    "sg:address":"15/ 43 Butterfield St",
    "sg:city":"Herston",
    "sg:classifiers":[
        {
            "category":"Professional",
            "type":"Services"
        }
    ],
    "sg:phone":"+61 7 3252 9900",
    "sg:postcode":"4006",
    "sg:province":"QLD",
    "sg:tags":[
        "shop",
        "fitting"
    ],
    "sg:website":"http://www.oconnorinteriors.com.au",
    "wof:name":"O&#039;Connor Interiors",
    "wof:placetype":"venue"
},
  "geometry": {"coordinates":[153.026779175,-27.4452610016],"type":"Point"}
}