{
  "type": "Feature",
  "properties": {
    "addr:full":"PO Box 5006 Warrnambool VIC 3280",
    "addr:postcode":"3280",
    "iso:country":"AU",
    "sg:address":"PO Box 5006",
    "sg:city":"Warrnambool",
    "sg:classifiers":[
        {
            "category":"Professional",
            "subcategory":"Art Services",
            "type":"Services"
        }
    ],
    "sg:phone":"+61 437 956 077",
    "sg:postcode":"3280",
    "sg:province":"VIC",
    "sg:tags":[
        "decorator",
        "painter"
    ],
    "wof:name":"Central Painting Solutions",
    "wof:placetype":"venue"
},
  "geometry": {"coordinates":[142.48323059099999,-38.3842582703],"type":"Point"}
}