{
  "type": "Feature",
  "properties": {
    "addr:full":"Unit 12 7 Delarge St Joondalup WA 6027",
    "addr:housenumber":"7",
    "addr:postcode":"6027",
    "addr:street":"Delarge St",
    "iso:country":"AU",
    "sg:address":"Unit 12 7 Delarge St",
    "sg:city":"Joondalup",
    "sg:classifiers":[
        {
            "category":"Banks & Credit Unions",
            "subcategory":"Financial Services",
            "type":"Services"
        }
    ],
    "sg:phone":"+61 8 9301 0137",
    "sg:postcode":"6027",
    "sg:province":"WA",
    "sg:tags":[
        "planning"
    ],
    "wof:name":"Scott Harlow Pty Ltd",
    "wof:placetype":"venue"
},
  "geometry": {"coordinates":[115.762702942,-31.7448863983],"type":"Point"}
}