{
  "type": "Feature",
  "properties": {
    "addr:full":"256 Manns Rd Gosford West NSW 2250",
    "addr:housenumber":"256",
    "addr:postcode":"2250",
    "addr:street":"Manns Rd",
    "iso:country":"AU",
    "sg:address":"256 Manns Rd",
    "sg:city":"Gosford West",
    "sg:classifiers":[
        {
            "category":"Taxi",
            "type":"Transportation"
        }
    ],
    "sg:phone":"+61 1300 665 777",
    "sg:postcode":"2250",
    "sg:province":"NSW",
    "sg:tags":[
        "cab"
    ],
    "wof:name":"Avoca Taxi Service",
    "wof:placetype":"venue"
},
  "geometry": {"coordinates":[151.31942749000001,-33.4244308472],"type":"Point"}
}