{
  "type": "Feature",
  "properties": {
    "iso:country":"AU",
    "sg:address":"16 Newcombe St",
    "sg:city":"Portarlington",
    "sg:classifiers":[
        {
            "category":"Health Services",
            "subcategory":"Doctor",
            "type":"Services"
        }
    ],
    "sg:phone":"+61 3 5259 2968",
    "sg:postcode":"3223",
    "sg:province":"VIC",
    "sg:tags":[
        "medical",
        "practitioner"
    ],
    "wof:name":"French Colin Dr.",
    "wof:placetype":"venue"
},
  "geometry": {"coordinates":[144.649353,-38.114716],"type":"Point"}
}