{
  "type": "Feature",
  "properties": {
    "addr:full":"101 Macleay St Potts Point NSW 2011",
    "addr:housenumber":"101",
    "addr:postcode":"2011",
    "addr:street":"Macleay St",
    "iso:country":"AU",
    "sg:address":"101 Macleay St",
    "sg:city":"Potts Point",
    "sg:classifiers":[
        {
            "category":"Education",
            "subcategory":"Special Training",
            "type":"Public Place"
        }
    ],
    "sg:phone":"+61 2 9368 1008",
    "sg:postcode":"2011",
    "sg:province":"NSW",
    "sg:tags":[
        "tuition-educational"
    ],
    "wof:name":"Advance Tuition & Guidance Service",
    "wof:placetype":"venue"
},
  "geometry": {"coordinates":[151.22494506800001,-33.8717880249],"type":"Point"}
}