{
  "type": "Feature",
  "properties": {
    "iso:country":"AU",
    "sg:address":"51 Francis St",
    "sg:city":"Bairnsdale",
    "sg:classifiers":[
        {
            "category":"Health Services",
            "subcategory":"Health Practitioner",
            "type":"Services"
        }
    ],
    "sg:phone":"+61 3 5153 1679",
    "sg:postcode":"3875",
    "sg:province":"VIC",
    "sg:tags":[
        "naturopath"
    ],
    "wof:name":"Diane Wood.",
    "wof:placetype":"venue"
},
  "geometry": {"coordinates":[147.62374877900001,-37.8251457214],"type":"Point"}
}