{
  "type": "Feature",
  "properties": {
    "addr:full":"19 Surfsound Ave Wallabi Point NSW 2430",
    "addr:housenumber":"19",
    "addr:postcode":"2430",
    "addr:street":"Surfsound Ave",
    "iso:country":"AU",
    "sg:address":"19 Surfsound Ave",
    "sg:city":"Wallabi Point",
    "sg:classifiers":[
        {
            "category":"Building & Trades",
            "subcategory":"Construction",
            "type":"Services"
        }
    ],
    "sg:phone":"+61 2 6557 4254",
    "sg:postcode":"2430",
    "sg:province":"NSW",
    "sg:tags":[
        "excavation",
        "foundation"
    ],
    "wof:name":"Shantull Excavations Pty Ltd",
    "wof:placetype":"venue"
},
  "geometry": {"coordinates":[152.56806900000001,-31.99321],"type":"Point"}
}