{
  "type": "Feature",
  "properties": {
    "addr:full":"23 Main St Hervey Bay QLD 4655",
    "addr:housenumber":"23",
    "addr:postcode":"4655",
    "addr:street":"Main St",
    "iso:country":"AU",
    "sg:address":"23 Main St",
    "sg:city":"Hervey Bay",
    "sg:classifiers":[
        {
            "category":"Building & Trades",
            "subcategory":"Locksmith",
            "type":"Services"
        }
    ],
    "sg:phone":"+61 7 4124 1241",
    "sg:postcode":"4655",
    "sg:province":"QLD",
    "sg:tags":[
        "strongroom",
        "safe",
        "door"
    ],
    "wof:name":"Souter (Wide Bay) Locksmiths & Security Agents",
    "wof:placetype":"venue"
},
  "geometry": {"coordinates":[152.837357,-25.291407],"type":"Point"}
}