{
  "type": "Feature",
  "properties": {
    "addr:full":"5 Chatham Rd Hamilton NSW 2303",
    "addr:housenumber":"5",
    "addr:postcode":"2303",
    "addr:street":"Chatham Rd",
    "iso:country":"AU",
    "sg:address":"5 Chatham Rd",
    "sg:city":"Hamilton",
    "sg:classifiers":[
        {
            "category":"Autos & Motor Vehicles",
            "subcategory":"Fuel & Gas Station",
            "type":"Retail Goods"
        }
    ],
    "sg:phone":"+61 2 4962 0888",
    "sg:postcode":"2303",
    "sg:province":"NSW",
    "wof:name":"Shell Australia Limited",
    "wof:placetype":"venue"
},
  "geometry": {"coordinates":[151.73895300000001,-32.916355],"type":"Point"}
}