{
  "type": "Feature",
  "properties": {
    "iso:country":"AU",
    "sg:address":"Cnr Bangholme & Hammond Rds",
    "sg:city":"Dandenong South",
    "sg:classifiers":[
        {
            "category":"Autos & Motor Vehicles",
            "subcategory":"Automobile Sales",
            "type":"Retail Goods"
        }
    ],
    "sg:phone":"+61 3 9706 5689",
    "sg:postcode":"3175",
    "sg:province":"VIC",
    "sg:tags":[
        "equipment",
        "trailer"
    ],
    "wof:name":"Rowville Horse Trainers",
    "wof:placetype":"venue"
},
  "geometry": {"coordinates":[145.202514648,-38.0381355286],"type":"Point"}
}