{
  "type": "Feature",
  "properties": {
    "addr:full":"Suite 2/ 81 Ferguson St Williamstown VIC 3016",
    "addr:housenumber":"81",
    "addr:postcode":"3016",
    "addr:street":"Ferguson St",
    "iso:country":"AU",
    "sg:address":"Suite 2/ 81 Ferguson St",
    "sg:city":"Williamstown",
    "sg:classifiers":[
        {
            "category":"Health Services",
            "subcategory":"Doctor",
            "type":"Services"
        }
    ],
    "sg:phone":"+61 3 9397 7300",
    "sg:postcode":"3016",
    "sg:province":"VIC",
    "sg:tags":[
        "medical",
        "practitioner"
    ],
    "wof:name":"Burbidge M",
    "wof:placetype":"venue"
},
  "geometry": {"coordinates":[144.89773559599999,-37.8590888977],"type":"Point"}
}