{
  "type": "Feature",
  "properties": {
    "addr:full":"139 Bourke St Melbourne VIC 3000",
    "addr:housenumber":"139",
    "addr:postcode":"3000",
    "addr:street":"Bourke St",
    "iso:country":"AU",
    "sg:address":"139 Bourke St",
    "sg:city":"Melbourne",
    "sg:classifiers":[
        {
            "category":"Retail",
            "subcategory":"Event Space",
            "type":"Services"
        }
    ],
    "sg:phone":"+61 3 9663 3177",
    "sg:postcode":"3000",
    "sg:province":"VIC",
    "sg:tags":[
        "function",
        "organiser"
    ],
    "wof:name":"Publicity Nightclub",
    "wof:placetype":"venue"
},
  "geometry": {"coordinates":[144.96925354000001,-37.8125915527],"type":"Point"}
}