{
  "type": "Feature",
  "properties": {
    "addr:full":"Pioneer Village Museum Little Alexander St Burnie TAS 7320",
    "addr:postcode":"7320",
    "addr:street":"St",
    "iso:country":"AU",
    "sg:address":"Pioneer Village Museum Little Alexander St",
    "sg:city":"Burnie",
    "sg:classifiers":[
        {
            "category":"Travel",
            "subcategory":"Travel Agent",
            "type":"Entertainment"
        }
    ],
    "sg:phone":"+61 3 6434 6111",
    "sg:postcode":"7320",
    "sg:province":"TAS",
    "sg:tags":[
        "consultant"
    ],
    "wof:name":"Tasmanian Travel & Information Centre - Burnie",
    "wof:placetype":"venue"
},
  "geometry": {"coordinates":[145.90258800000001,-41.053162],"type":"Point"}
}