{
  "type": "Feature",
  "properties": {
    "iso:country":"AU",
    "sg:address":"116 Coogee Bay Rd",
    "sg:city":"Coogee",
    "sg:classifiers":[
        {
            "category":"Food & Beverages",
            "subcategory":"Liquor & Beverages",
            "type":"Retail Goods"
        }
    ],
    "sg:phone":"+61 2 9665 2233",
    "sg:postcode":"2034",
    "sg:province":"NSW",
    "sg:tags":[
        "store"
    ],
    "wof:name":"First Estate Liquor",
    "wof:placetype":"venue"
},
  "geometry": {"coordinates":[151.24998474099999,-33.9196815491],"type":"Point"}
}