{
  "type": "Feature",
  "properties": {
    "addr:full":"Pitt St Windsor NSW 2756",
    "addr:postcode":"2756",
    "addr:street":"Pitt St",
    "iso:country":"AU",
    "sg:address":"Pitt St",
    "sg:city":"Windsor",
    "sg:classifiers":[
        {
            "category":"Home & Garden",
            "subcategory":"Garden Supply",
            "type":"Retail Goods"
        }
    ],
    "sg:phone":"+61 2 4577 4221",
    "sg:postcode":"2756",
    "sg:province":"NSW",
    "sg:tags":[
        "turf",
        "lawn"
    ],
    "wof:name":"President Turf Supplies",
    "wof:placetype":"venue"
},
  "geometry": {"coordinates":[150.82705688499999,-33.6060371399],"type":"Point"}
}