{
  "type": "Feature",
  "properties": {
    "iso:country":"AU",
    "sg:address":"170 Victoria Rd",
    "sg:city":"Drummoyne",
    "sg:classifiers":[
        {
            "category":"Personal",
            "subcategory":"Hair Removal",
            "type":"Services"
        }
    ],
    "sg:phone":"+61 2 9719 1391",
    "sg:postcode":"2047",
    "sg:province":"NSW",
    "wof:name":"Permanence",
    "wof:placetype":"venue"
},
  "geometry": {"coordinates":[151.155502,-33.851818],"type":"Point"}
}