{
  "type": "Feature",
  "properties": {
    "addr:full":"90 Beecroft Rd Beecroft NSW 2119",
    "addr:housenumber":"90",
    "addr:postcode":"2119",
    "addr:street":"Beecroft Rd",
    "iso:country":"AU",
    "sg:address":"90 Beecroft Rd",
    "sg:city":"Beecroft",
    "sg:classifiers":[
        {
            "category":"Social Services",
            "subcategory":"Child Care",
            "type":"Services"
        }
    ],
    "sg:phone":"+61 2 9980 8224",
    "sg:postcode":"2119",
    "sg:province":"NSW",
    "wof:name":"Beecroft Out-Of-School Hours Centre",
    "wof:placetype":"venue"
},
  "geometry": {"coordinates":[151.065307617,-33.7524757385],"type":"Point"}
}