{
  "type": "Feature",
  "properties": {
    "iso:country":"AU",
    "sg:address":"30 Slade Rd",
    "sg:city":"Bardwell Park",
    "sg:classifiers":[
        {
            "category":"Personal",
            "subcategory":"Beauty Salon",
            "type":"Services"
        }
    ],
    "sg:phone":"+61 2 9567 3680",
    "sg:postcode":"2207",
    "sg:province":"NSW",
    "sg:tags":[
        "hairdresser"
    ],
    "wof:name":"Vince's Hair Stylist",
    "wof:placetype":"venue"
},
  "geometry": {"coordinates":[151.121979,-33.933727],"type":"Point"}
}