{
  "type": "Feature",
  "properties": {
    "addr:full":"124 Thompson Ave Cowes VIC 3922",
    "addr:housenumber":"124",
    "addr:postcode":"3922",
    "addr:street":"Thompson Ave",
    "iso:country":"AU",
    "sg:address":"124 Thompson Ave",
    "sg:city":"Cowes",
    "sg:classifiers":[
        {
            "category":"Autos & Motor Vehicles",
            "subcategory":"Fuel & Gas Station",
            "type":"Retail Goods"
        }
    ],
    "sg:phone":"+61 3 5952 3455",
    "sg:postcode":"3922",
    "sg:province":"VIC",
    "wof:name":"Mobil Oil Aust Pty Ltd",
    "wof:placetype":"venue"
},
  "geometry": {"coordinates":[145.23878479000001,-38.4531478882],"type":"Point"}
}