{
  "type": "Feature",
  "properties": {
    "addr:full":"19 Commerce Crt Noosaville QLD 4566",
    "addr:housenumber":"19",
    "addr:postcode":"4566",
    "addr:street":"Commerce Crt",
    "iso:country":"AU",
    "sg:address":"19 Commerce Crt",
    "sg:city":"Noosaville",
    "sg:classifiers":[
        {
            "category":"Wholesale",
            "subcategory":"Apparel",
            "type":"Manufacturing & Wholesale Goods"
        }
    ],
    "sg:phone":"+61 7 5449 8677",
    "sg:postcode":"4566",
    "sg:province":"QLD",
    "sg:tags":[
        "wholesaler",
        "mfrs",
        "uniform"
    ],
    "wof:name":"Freedom Screenprinting",
    "wof:placetype":"venue"
},
  "geometry": {"coordinates":[153.04600524899999,-26.4116668701],"type":"Point"}
}