{
  "type": "Feature",
  "properties": {
    "addr:full":"13 Timberside Drv Beaconsfield VIC 3807",
    "addr:housenumber":"13",
    "addr:postcode":"3807",
    "addr:street":"Timberside Drv",
    "iso:country":"AU",
    "sg:address":"13 Timberside Drv",
    "sg:city":"Beaconsfield",
    "sg:classifiers":[
        {
            "category":"Professional",
            "subcategory":"Art Services",
            "type":"Services"
        }
    ],
    "sg:phone":"+61 3 9769 7859",
    "sg:postcode":"3807",
    "sg:province":"VIC",
    "sg:tags":[
        "decorator",
        "painter"
    ],
    "wof:name":"Ashdown Painting & Decorating Services",
    "wof:placetype":"venue"
},
  "geometry": {"coordinates":[145.37638855,-38.0443687439],"type":"Point"}
}