{
  "type": "Feature",
  "properties": {
    "addr:full":"30 Coast Rd Pottsville NSW 2489",
    "addr:housenumber":"30",
    "addr:postcode":"2489",
    "addr:street":"Coast Rd",
    "iso:country":"AU",
    "sg:address":"30 Coast Rd",
    "sg:city":"Pottsville",
    "sg:classifiers":[
        {
            "category":"Travel",
            "subcategory":"Hotels & Motels",
            "type":"Entertainment"
        }
    ],
    "sg:phone":"+61 2 6676 1107",
    "sg:postcode":"2489",
    "sg:province":"NSW",
    "wof:name":"Pottsville Beach Motel & Restaurant",
    "wof:placetype":"venue"
},
  "geometry": {"coordinates":[153.5652771,-28.3899497986],"type":"Point"}
}