{
  "type": "Feature",
  "properties": {
    "addr:full":"Shop 13 K-Mart Plaza Shopng Cntr Cnr Nathan St & Ross River Rd Aitkenvale QLD 4814",
    "addr:housenumber":"shop 13",
    "addr:postcode":"4814",
    "addr:street":"Plaza;Nathan St & Ross River Rd",
    "iso:country":"AU",
    "sg:address":"Shop 13 K-Mart Plaza Shopng Cntr Cnr Nathan St & Ross River Rd",
    "sg:city":"Aitkenvale",
    "sg:classifiers":[
        {
            "category":"Food & Beverages",
            "subcategory":"Liquor & Beverages",
            "type":"Retail Goods"
        }
    ],
    "sg:phone":"+61 7 4725 5804",
    "sg:postcode":"4814",
    "sg:province":"QLD",
    "sg:tags":[
        "store"
    ],
    "wof:name":"BWS Liquor Stores",
    "wof:placetype":"venue"
},
  "geometry": {"coordinates":[146.76194799999999,-19.295038],"type":"Point"}
}