{
  "type": "Feature",
  "properties": {
    "addr:full":"26 Jade St Maddington WA 6109",
    "addr:housenumber":"26",
    "addr:postcode":"6109",
    "addr:street":"Jade St",
    "iso:country":"AU",
    "sg:address":"26 Jade St",
    "sg:city":"Maddington",
    "sg:classifiers":[
        {
            "category":"Manufacturing",
            "subcategory":"Buildings",
            "type":"Manufacturing & Wholesale Goods"
        }
    ],
    "sg:phone":"+61 8 9493 1410",
    "sg:postcode":"6109",
    "sg:province":"WA",
    "sg:tags":[
        "transportable",
        "domestic",
        "relocatable"
    ],
    "wof:name":"Kent Corporation Pty Ltd",
    "wof:placetype":"venue"
},
  "geometry": {"coordinates":[115.999549866,-32.0394554138],"type":"Point"}
}