{
  "type": "Feature",
  "properties": {
    "addr:full":"150 Goodwood Rd Goodwood SA 5034",
    "addr:housenumber":"150",
    "addr:postcode":"5034",
    "addr:street":"Goodwood Rd",
    "iso:country":"AU",
    "sg:address":"150 Goodwood Rd",
    "sg:city":"Goodwood",
    "sg:classifiers":[
        {
            "category":"Personal",
            "type":"Services"
        }
    ],
    "sg:phone":"+61 8 8357 9555",
    "sg:postcode":"5034",
    "sg:province":"SA",
    "sg:tags":[
        "gift"
    ],
    "wof:name":"Adelaides Goodwood Florist",
    "wof:placetype":"venue"
},
  "geometry": {"coordinates":[138.589553833,-34.9522819519],"type":"Point"}
}