{
  "type": "Feature",
  "properties": {
    "addr:full":"39 Stanton Drv West Pennant Hills NSW 2125",
    "addr:housenumber":"39",
    "addr:postcode":"2125",
    "addr:street":"Stanton Drv",
    "iso:country":"AU",
    "sg:address":"39 Stanton Drv",
    "sg:city":"West Pennant Hills",
    "sg:classifiers":[
        {
            "category":"Education",
            "subcategory":"Music School",
            "type":"Public Place"
        }
    ],
    "sg:phone":"+61 2 9871 0271",
    "sg:postcode":"2125",
    "sg:province":"NSW",
    "sg:tags":[
        "teacher"
    ],
    "wof:name":"Teaching Services Australia",
    "wof:placetype":"venue"
},
  "geometry": {"coordinates":[151.03343200699999,-33.7556915283],"type":"Point"}
}