{
  "type": "Feature",
  "properties": {
    "addr:full":"24 Thomas St East Cannington WA 6107",
    "addr:housenumber":"24",
    "addr:postcode":"6107",
    "addr:street":"Thomas St East",
    "iso:country":"AU",
    "sg:address":"24 Thomas St",
    "sg:city":"East Cannington",
    "sg:classifiers":[
        {
            "category":"Health Services",
            "subcategory":"Health Practitioner",
            "type":"Services"
        }
    ],
    "sg:phone":"+61 8 9358 4408",
    "sg:postcode":"6107",
    "sg:province":"WA",
    "sg:tags":[
        "naturopath"
    ],
    "wof:name":"Mavis Carruthers-Abundant Life Naturopath Centre",
    "wof:placetype":"venue"
},
  "geometry": {"coordinates":[115.94814300500001,-32.0099258423],"type":"Point"}
}