{
  "type": "Feature",
  "properties": {
    "iso:country":"AU",
    "sg:address":"222 George St",
    "sg:city":"Quirindi",
    "sg:classifiers":[
        {
            "category":"Travel",
            "subcategory":"Hotels & Motels",
            "type":"Entertainment"
        }
    ],
    "sg:phone":"+61 2 6746 2264",
    "sg:postcode":"2343",
    "sg:province":"NSW",
    "sg:tags":[
        "accommodation"
    ],
    "wof:name":"Commercial Hotel",
    "wof:placetype":"venue"
},
  "geometry": {"coordinates":[150.67897033700001,-31.5120830536],"type":"Point"}
}