{
  "type": "Feature",
  "properties": {
    "addr:full":"8 Beaumont Rd Mt Kuring-gai NSW 2080",
    "addr:housenumber":"8",
    "addr:postcode":"2080",
    "addr:street":"Beaumont Rd",
    "iso:country":"AU",
    "sg:address":"8 Beaumont Rd",
    "sg:city":"Mt Kuring-gai",
    "sg:classifiers":[
        {
            "category":"Autos & Motor Vehicles",
            "subcategory":"Automobile Sales",
            "type":"Retail Goods"
        }
    ],
    "sg:phone":"+61 1300 786 184",
    "sg:postcode":"2080",
    "sg:province":"NSW",
    "sg:tags":[
        "bus",
        "used",
        "truck"
    ],
    "wof:name":"Waste Equipment Sales N.S.W.",
    "wof:placetype":"venue"
},
  "geometry": {"coordinates":[151.132568359,-33.6433334351],"type":"Point"}
}