{
  "type": "Feature",
  "properties": {
    "addr:full":"Lot 11/ Marks St Belmont NSW 2280",
    "addr:housenumber":"/",
    "addr:postcode":"2280",
    "addr:street":"Marks St",
    "iso:country":"AU",
    "sg:address":"Lot 11/ Marks St",
    "sg:city":"Belmont",
    "sg:classifiers":[
        {
            "category":"Shopping",
            "subcategory":"Bicycles & Sporting Goods",
            "type":"Retail Goods"
        }
    ],
    "sg:phone":"+61 2 4945 5336",
    "sg:postcode":"2280",
    "sg:province":"NSW",
    "sg:tags":[
        "chemical",
        "equipment",
        "pool",
        "swimming"
    ],
    "wof:name":"Master Pool Supply",
    "wof:placetype":"venue"
},
  "geometry": {"coordinates":[151.65858459500001,-33.03099823],"type":"Point"}
}