{
  "type": "Feature",
  "properties": {
    "iso:country":"AU",
    "sg:address":"Shop 8/ 1374 Gympie Rd",
    "sg:city":"Aspley",
    "sg:classifiers":[
        {
            "category":"Personal",
            "subcategory":"Beauty Salon",
            "type":"Services"
        }
    ],
    "sg:phone":"+61 7 3862 7879",
    "sg:postcode":"4034",
    "sg:province":"QLD",
    "sg:tags":[
        "supply",
        "artist",
        "make-up"
    ],
    "wof:name":"Annettes Makeup & Hair Studio",
    "wof:placetype":"venue"
},
  "geometry": {"coordinates":[153.016907,-27.36215],"type":"Point"}
}