{
  "type": "Feature",
  "properties": {
    "addr:full":"2 Goondoon St Gladstone QLD 4680",
    "addr:housenumber":"2",
    "addr:postcode":"4680",
    "addr:street":"Goondoon St",
    "iso:country":"AU",
    "sg:address":"2 Goondoon St",
    "sg:city":"Gladstone",
    "sg:classifiers":[
        {
            "category":"Health Services",
            "subcategory":"Doctor",
            "type":"Services"
        }
    ],
    "sg:phone":"+61 7 4972 9558",
    "sg:postcode":"4680",
    "sg:province":"QLD",
    "sg:tags":[
        "medical",
        "practitioner"
    ],
    "wof:name":"Dermatix Laser and Skin Care",
    "wof:placetype":"venue"
},
  "geometry": {"coordinates":[151.25274658199999,-23.8380260468],"type":"Point"}
}