{
  "type": "Feature",
  "properties": {
    "addr:full":"8 Brady Rd Oak Valley QLD 4811",
    "addr:housenumber":"8",
    "addr:postcode":"4811",
    "addr:street":"Brady Rd",
    "iso:country":"AU",
    "sg:address":"8 Brady Rd",
    "sg:city":"Oak Valley",
    "sg:classifiers":[
        {
            "category":"Building & Trades",
            "subcategory":"Plumbing",
            "type":"Services"
        }
    ],
    "sg:phone":"+61 7 4778 4847",
    "sg:postcode":"4811",
    "sg:province":"QLD",
    "sg:tags":[
        "plumber",
        "gasfitters"
    ],
    "wof:name":"G K C Plumbing & Irrigation Services",
    "wof:placetype":"venue"
},
  "geometry": {"coordinates":[146.81506300000001,-19.421146],"type":"Point"}
}