{
  "type": "Feature",
  "properties": {
    "iso:country":"AU",
    "sg:address":"244 Leach Hwy",
    "sg:city":"Myaree",
    "sg:classifiers":[
        {
            "category":"Retail",
            "subcategory":"Storage",
            "type":"Services"
        }
    ],
    "sg:phone":"+61 8 9330 7188",
    "sg:postcode":"6154",
    "sg:province":"WA",
    "wof:name":"Guardsman",
    "wof:placetype":"venue"
},
  "geometry": {"coordinates":[115.819359,-32.045918],"type":"Point"}
}