{
  "type": "Feature",
  "properties": {
    "addr:full":"244 Leach Hwy Myaree WA 6154",
    "addr:housenumber":"244",
    "addr:postcode":"6154",
    "addr:street":"Leach Hwy",
    "iso:country":"AU",
    "sg:address":"244 Leach Hwy",
    "sg:city":"Myaree",
    "sg:classifiers":[
        {
            "category":"Retail",
            "subcategory":"Storage",
            "type":"Services"
        }
    ],
    "sg:phone":"+61 8 9330 7188",
    "sg:postcode":"6154",
    "sg:province":"WA",
    "wof:name":"Guardsman",
    "wof:placetype":"venue"
},
  "geometry": {"coordinates":[115.81935900000001,-32.045918],"type":"Point"}
}