{
  "type": "Feature",
  "properties": {
    "addr:full":"50 Lexton Rd Box Hill VIC 3128",
    "addr:housenumber":"50",
    "addr:postcode":"3128",
    "addr:street":"Lexton Rd",
    "iso:country":"AU",
    "sg:address":"50 Lexton Rd",
    "sg:city":"Box Hill",
    "sg:classifiers":[
        {
            "category":"Retail",
            "subcategory":"Storage",
            "type":"Services"
        }
    ],
    "sg:phone":"+61 3 9899 1566",
    "sg:postcode":"3128",
    "sg:province":"VIC",
    "wof:name":"Storage One",
    "wof:placetype":"venue"
},
  "geometry": {"coordinates":[145.137252808,-37.8123054504],"type":"Point"}
}