{
  "type": "Feature",
  "properties": {
    "addr:full":"4 Lumea Pl Dharruk NSW 2770",
    "addr:housenumber":"4",
    "addr:postcode":"2770",
    "addr:street":"Lumea Pl",
    "iso:country":"AU",
    "sg:address":"4 Lumea Pl",
    "sg:city":"Dharruk",
    "sg:classifiers":[
        {
            "category":"Shopping",
            "type":"Retail Goods"
        }
    ],
    "sg:phone":"+61 401 093 377",
    "sg:postcode":"2770",
    "sg:province":"NSW",
    "sg:tags":[
        "equipment",
        "safety",
        "accessory"
    ],
    "wof:name":"INTERNATIONAL HEIGHT SAFETY",
    "wof:placetype":"venue"
},
  "geometry": {"coordinates":[150.81695556599999,-33.753162384],"type":"Point"}
}