{
  "type": "Feature",
  "properties": {
    "iso:country":"AU",
    "sg:address":"25 Glaisher Pde",
    "sg:city":"Cronulla",
    "sg:classifiers":[
        {
            "category":"Building & Trades",
            "subcategory":"Construction",
            "type":"Services"
        }
    ],
    "sg:phone":"+61 2 9527 7133",
    "sg:postcode":"2230",
    "sg:province":"NSW",
    "sg:tags":[
        "contractor"
    ],
    "wof:name":"Streater Constructions Pty Ltd",
    "wof:placetype":"venue"
},
  "geometry": {"coordinates":[151.15245056099999,-34.0719642639],"type":"Point"}
}