{
  "type": "Feature",
  "properties": {
    "addr:full":"133 Sutton St Redcliffe QLD 4020",
    "addr:housenumber":"133",
    "addr:postcode":"4020",
    "addr:street":"Sutton St",
    "iso:country":"AU",
    "sg:address":"133 Sutton St",
    "sg:city":"Redcliffe",
    "sg:classifiers":[
        {
            "category":"Banks & Credit Unions",
            "subcategory":"Financial Services",
            "type":"Services"
        }
    ],
    "sg:phone":"+61 7 3283 8311",
    "sg:postcode":"4020",
    "sg:province":"QLD",
    "sg:tags":[
        "loan",
        "finance",
        "mortgage"
    ],
    "wof:name":"Pacific Home Loans & Finance",
    "wof:placetype":"venue"
},
  "geometry": {"coordinates":[153.11462399999999,-27.229353],"type":"Point"}
}