{
  "type": "Feature",
  "properties": {
    "addr:full":"175 Summer St Orange NSW 2800",
    "addr:housenumber":"175",
    "addr:postcode":"2800",
    "addr:street":"Summer St",
    "iso:country":"AU",
    "sg:address":"175 Summer St",
    "sg:city":"Orange",
    "sg:classifiers":[
        {
            "category":"Shopping",
            "subcategory":"Clothing, Apparel, & Fashions",
            "type":"Retail Goods"
        }
    ],
    "sg:phone":"+61 2 6361 7933",
    "sg:postcode":"2800",
    "sg:province":"NSW",
    "sg:tags":[
        "menswear"
    ],
    "wof:name":"Hartfords Menswear",
    "wof:placetype":"venue"
},
  "geometry": {"coordinates":[149.090087891,-33.2820968628],"type":"Point"}
}