{
  "type": "Feature",
  "properties": {
    "iso:country":"AU",
    "sg:address":"420 Princes Hwy",
    "sg:city":"Corrimal",
    "sg:classifiers":[
        {
            "category":"Health Services",
            "subcategory":"Dentist",
            "type":"Services"
        }
    ],
    "sg:phone":"+61 2 4285 2279",
    "sg:postcode":"2518",
    "sg:province":"NSW",
    "wof:name":"Choi Chloe",
    "wof:placetype":"venue"
},
  "geometry": {"coordinates":[150.89639299999999,-34.381001],"type":"Point"}
}