{
  "type": "Feature",
  "properties": {
    "addr:full":"9 Greengate Rd Killara NSW 2071",
    "addr:housenumber":"9",
    "addr:postcode":"2071",
    "addr:street":"Greengate Rd",
    "iso:country":"AU",
    "sg:address":"9 Greengate Rd",
    "sg:city":"Killara",
    "sg:classifiers":[
        {
            "category":"Travel",
            "subcategory":"Hostel",
            "type":"Entertainment"
        }
    ],
    "sg:phone":"+61 2 9499 2644",
    "sg:postcode":"2071",
    "sg:province":"NSW",
    "sg:tags":[
        "home"
    ],
    "wof:name":"Abbotsholme Apartments",
    "wof:placetype":"venue"
},
  "geometry": {"coordinates":[151.15646362300001,-33.7629432678],"type":"Point"}
}