{
  "type": "Feature",
  "properties": {
    "iso:country":"AU",
    "sg:address":"9 Royal Park Ave",
    "sg:city":"Caroline Springs",
    "sg:classifiers":[
        {
            "category":"Personal",
            "subcategory":"Beauty Salon",
            "type":"Services"
        }
    ],
    "sg:phone":"+61 409 136 939",
    "sg:postcode":"3023",
    "sg:province":"VIC",
    "wof:name":"A Westside Beauty",
    "wof:placetype":"venue"
},
  "geometry": {"coordinates":[144.741592,-37.726887],"type":"Point"}
}