{
  "type": "Feature",
  "properties": {
    "iso:country":"AU",
    "sg:address":"17 Judith Drv",
    "sg:city":"Athelstone",
    "sg:classifiers":[
        {
            "category":"Shopping",
            "subcategory":"Clothing, Apparel, & Fashions",
            "type":"Retail Goods"
        }
    ],
    "sg:phone":"+61 418 833 539",
    "sg:postcode":"5076",
    "sg:province":"SA",
    "sg:tags":[
        "accessory"
    ],
    "wof:name":"Peter Cooper & Associates",
    "wof:placetype":"venue"
},
  "geometry": {"coordinates":[138.69920349099999,-34.8795661926],"type":"Point"}
}