{
  "type": "Feature",
  "properties": {
    "addr:full":"113 Mary's Mount Rd Goulburn NSW 2580",
    "addr:housenumber":"113",
    "addr:postcode":"2580",
    "addr:street":"Mary'S Mount Rd",
    "iso:country":"AU",
    "sg:address":"113 Mary's Mount Rd",
    "sg:city":"Goulburn",
    "sg:classifiers":[
        {
            "category":"Professional",
            "type":"Services"
        }
    ],
    "sg:phone":"+61 2 4821 2810",
    "sg:postcode":"2580",
    "sg:province":"NSW",
    "sg:tags":[
        "shop",
        "fitting"
    ],
    "wof:name":"Argyle Kitchens & Joinery",
    "wof:placetype":"venue"
},
  "geometry": {"coordinates":[149.719650269,-34.7250099182],"type":"Point"}
}