{
  "type": "Feature",
  "properties": {
    "addr:full":"12 Overton Rd Frankston VIC 3199",
    "addr:housenumber":"12",
    "addr:postcode":"3199",
    "addr:street":"Overton Rd",
    "iso:country":"AU",
    "sg:address":"12 Overton Rd",
    "sg:city":"Frankston",
    "sg:classifiers":[
        {
            "category":"Professional",
            "subcategory":"Art Services",
            "type":"Services"
        }
    ],
    "sg:phone":"+61 401 440 395",
    "sg:postcode":"3199",
    "sg:province":"VIC",
    "sg:tags":[
        "graphic",
        "designer"
    ],
    "wof:name":"Ling Design",
    "wof:placetype":"venue"
},
  "geometry": {"coordinates":[145.12579345699999,-38.128818512],"type":"Point"}
}