{
  "type": "Feature",
  "properties": {
    "iso:country":"AU",
    "sg:address":"Hoddy St",
    "sg:city":"Goomalling",
    "sg:classifiers":[
        {
            "category":"Education",
            "subcategory":"School",
            "type":"Public Place"
        }
    ],
    "sg:phone":"+61 8 9629 1174",
    "sg:postcode":"6460",
    "sg:province":"WA",
    "sg:tags":[
        "state",
        "except",
        "nsw"
    ],
    "wof:name":"Sacred Heart Catholic School",
    "wof:placetype":"venue"
},
  "geometry": {"coordinates":[116.82642364500001,-31.2996253967],"type":"Point"}
}