{
  "type": "Feature",
  "properties": {
    "addr:full":"508 Mt Macedon Rd Mt Macedon VIC 3441",
    "addr:housenumber":"508",
    "addr:postcode":"3441",
    "addr:street":"Mt Macedon Rd",
    "iso:country":"AU",
    "sg:address":"508 Mt Macedon Rd",
    "sg:city":"Mt Macedon",
    "sg:classifiers":[
        {
            "category":"Professional",
            "subcategory":"Computer Services",
            "type":"Services"
        }
    ],
    "sg:phone":"+61 408 476 343",
    "sg:postcode":"3441",
    "sg:province":"VIC",
    "sg:tags":[
        "consultant",
        "system"
    ],
    "wof:name":"Blueprint I.T. Services Pty Ltd",
    "wof:placetype":"venue"
},
  "geometry": {"coordinates":[144.59300231899999,-37.3925590515],"type":"Point"}
}