{
  "type": "Feature",
  "properties": {
    "iso:country":"AU",
    "sg:address":"72 Keys Rd",
    "sg:city":"Moorabbin",
    "sg:classifiers":[
        {
            "category":"Utilities",
            "subcategory":"Electric",
            "type":"Services"
        }
    ],
    "sg:phone":"+61 3 9553 0887",
    "sg:postcode":"3189",
    "sg:province":"VIC",
    "sg:tags":[
        "electrical",
        "contractor"
    ],
    "wof:name":"Active Electrical Distributors Pty Ltd",
    "wof:placetype":"venue"
},
  "geometry": {"coordinates":[145.066604614,-37.9486465454],"type":"Point"}
}