{
  "type": "Feature",
  "properties": {
    "addr:full":"183a Greville St Prahran VIC 3181",
    "addr:housenumber":"183a",
    "addr:postcode":"3181",
    "addr:street":"Greville St",
    "iso:country":"AU",
    "sg:address":"183a Greville St",
    "sg:city":"Prahran",
    "sg:classifiers":[
        {
            "category":"Real Estate",
            "subcategory":"Architect",
            "type":"Services"
        }
    ],
    "sg:phone":"+61 3 9521 1800",
    "sg:postcode":"3181",
    "sg:province":"VIC",
    "sg:tags":[
        "building",
        "designer"
    ],
    "wof:name":"Burns Goldberg",
    "wof:placetype":"venue"
},
  "geometry": {"coordinates":[144.99296569800001,-37.8493270874],"type":"Point"}
}