{
  "type": "Feature",
  "properties": {
    "iso:country":"AU",
    "sg:address":"486 Great Western Hwy",
    "sg:city":"Pendle Hill",
    "sg:classifiers":[
        {
            "category":"Professional",
            "subcategory":"Accounting & Tax Preparation",
            "type":"Services"
        }
    ],
    "sg:phone":"+61 2 9631 9522",
    "sg:postcode":"2145",
    "sg:province":"NSW",
    "sg:tags":[
        "accountant",
        "auditor"
    ],
    "wof:name":"Gibson Prout & Associates",
    "wof:placetype":"venue"
},
  "geometry": {"coordinates":[150.954681397,-33.8119544983],"type":"Point"}
}