{
  "type": "Feature",
  "properties": {
    "addr:full":"80 Ballina Rd Lismore NSW 2480",
    "addr:housenumber":"80",
    "addr:postcode":"2480",
    "addr:street":"Ballina Rd",
    "iso:country":"AU",
    "sg:address":"80 Ballina Rd",
    "sg:city":"Lismore",
    "sg:classifiers":[
        {
            "category":"Autos & Motor Vehicles",
            "subcategory":"Automobile Sales",
            "type":"Retail Goods"
        }
    ],
    "sg:phone":"+61 2 6621 2599",
    "sg:postcode":"2480",
    "sg:province":"NSW",
    "sg:tags":[
        "car",
        "used"
    ],
    "wof:name":"Lismore Nissan",
    "wof:placetype":"venue"
},
  "geometry": {"coordinates":[153.28018188499999,-28.8083381653],"type":"Point"}
}