{
  "type": "Feature",
  "properties": {
    "addr:full":"Alexandra Ave Sunshine VIC 3020",
    "addr:postcode":"3020",
    "addr:street":"Alexandra Ave",
    "iso:country":"AU",
    "sg:address":"Alexandra Ave",
    "sg:city":"Sunshine",
    "sg:classifiers":[
        {
            "category":"Social Services",
            "subcategory":"Child Care",
            "type":"Services"
        }
    ],
    "sg:phone":"+61 3 9249 4292",
    "sg:postcode":"3020",
    "sg:province":"VIC",
    "sg:tags":[
        "support",
        "health"
    ],
    "wof:name":"Maternal & Child Health Centres",
    "wof:placetype":"venue"
},
  "geometry": {"coordinates":[144.836975,-37.784996],"type":"Point"}
}