{
  "type": "Feature",
  "properties": {
    "addr:full":"10 Carlyle St Mackay QLD 4740",
    "addr:housenumber":"10",
    "addr:postcode":"4740",
    "addr:street":"Carlyle St",
    "iso:country":"AU",
    "sg:address":"10 Carlyle St",
    "sg:city":"Mackay",
    "sg:classifiers":[
        {
            "category":"Recreation",
            "type":"Entertainment"
        }
    ],
    "sg:phone":"+61 7 4957 2000",
    "sg:postcode":"4740",
    "sg:province":"QLD",
    "sg:tags":[
        "supply",
        "outdoor",
        "adventure",
        "activity"
    ],
    "wof:name":"Great Outdoors Camping",
    "wof:placetype":"venue"
},
  "geometry": {"coordinates":[149.19383199999999,-21.144348],"type":"Point"}
}