{
  "type": "Feature",
  "properties": {
    "addr:full":"12 Throsby St Casula NSW 2170",
    "addr:housenumber":"12",
    "addr:postcode":"2170",
    "addr:street":"Throsby St",
    "iso:country":"AU",
    "sg:address":"12 Throsby St",
    "sg:city":"Casula",
    "sg:classifiers":[
        {
            "category":"Utilities",
            "subcategory":"Telephone",
            "type":"Services"
        }
    ],
    "sg:phone":"+61 2 9601 3092",
    "sg:postcode":"2170",
    "sg:province":"NSW",
    "sg:tags":[
        "installation",
        "system",
        "maintenance"
    ],
    "wof:name":"Garval Communications Pty Ltd",
    "wof:placetype":"venue"
},
  "geometry": {"coordinates":[150.892974853,-33.9499435425],"type":"Point"}
}