{
  "type": "Feature",
  "properties": {
    "iso:country":"AU",
    "sg:address":"Cnr William & Albany Sts",
    "sg:city":"Gosford",
    "sg:classifiers":[
        {
            "category":"Health Services",
            "subcategory":"Chiropractor",
            "type":"Services"
        }
    ],
    "sg:phone":"+61 2 4324 3659",
    "sg:postcode":"2250",
    "sg:province":"NSW",
    "wof:name":"Flynn John",
    "wof:placetype":"venue"
},
  "geometry": {"coordinates":[151.34249877900001,-33.4237213135],"type":"Point"}
}