{
  "type": "Feature",
  "properties": {
    "addr:full":"189 Musgrave St North Rockhampton QLD 4701",
    "addr:housenumber":"189",
    "addr:postcode":"4701",
    "addr:street":"Musgrave St North",
    "iso:country":"AU",
    "sg:address":"189 Musgrave St",
    "sg:city":"North Rockhampton",
    "sg:classifiers":[
        {
            "category":"Banks & Credit Unions",
            "subcategory":"Bureau De Change",
            "type":"Services"
        }
    ],
    "sg:phone":"+61 7 4922 7720",
    "sg:postcode":"4701",
    "sg:province":"QLD",
    "sg:tags":[
        "gas",
        "natural",
        "lp",
        "equipment"
    ],
    "wof:name":"Freitag Nominees",
    "wof:placetype":"venue"
},
  "geometry": {"coordinates":[150.522613525,-23.3618240356],"type":"Point"}
}