{
  "type": "Feature",
  "properties": {
    "addr:full":"1011 Coolawanyah Rd Karratha WA 6714",
    "addr:housenumber":"1011",
    "addr:postcode":"6714",
    "addr:street":"Coolawanyah Rd",
    "iso:country":"AU",
    "sg:address":"1011 Coolawanyah Rd",
    "sg:city":"Karratha",
    "sg:classifiers":[
        {
            "category":"Utilities",
            "subcategory":"Refuse",
            "type":"Services"
        }
    ],
    "sg:phone":"+61 8 9185 3422",
    "sg:postcode":"6714",
    "sg:province":"WA",
    "sg:tags":[
        "disposal",
        "reduction",
        "waste"
    ],
    "wof:name":"Lyons & Peirce Karratha",
    "wof:placetype":"venue"
},
  "geometry": {"coordinates":[116.866523743,-20.7693634033],"type":"Point"}
}