{
  "type": "Feature",
  "properties": {
    "addr:full":"1a Chardon Bridge Rd Cedar Creek QLD 4520",
    "addr:housenumber":"1a",
    "addr:postcode":"4520",
    "addr:street":"Chardon Bridge Rd",
    "iso:country":"AU",
    "sg:address":"1a Chardon Bridge Rd",
    "sg:city":"Cedar Creek",
    "sg:classifiers":[
        {
            "category":"Education",
            "subcategory":"School",
            "type":"Public Place"
        }
    ],
    "sg:phone":"+61 7 5546 4152",
    "sg:postcode":"4520",
    "sg:province":"QLD",
    "sg:tags":[
        "state",
        "except",
        "nsw"
    ],
    "wof:name":"Cedar Creek Primary School",
    "wof:placetype":"venue"
},
  "geometry": {"coordinates":[152.796753,-27.32493],"type":"Point"}
}