{
  "type": "Feature",
  "properties": {
    "addr:full":"Fact 4/ 53 Barry St Bayswater VIC 3153",
    "addr:housenumber":"4 / 53",
    "addr:postcode":"3153",
    "addr:street":"Fact;Barry St",
    "iso:country":"AU",
    "sg:address":"Fact 4/ 53 Barry St",
    "sg:city":"Bayswater",
    "sg:classifiers":[
        {
            "category":"Building & Trades",
            "subcategory":"Construction",
            "type":"Services"
        }
    ],
    "sg:phone":"+61 3 9762 4977",
    "sg:postcode":"3153",
    "sg:province":"VIC",
    "sg:tags":[
        "spouting",
        "guttering"
    ],
    "wof:name":"Atherton Plumbing Pty Ltd",
    "wof:placetype":"venue"
},
  "geometry": {"coordinates":[145.28128051799999,-37.8475875854],"type":"Point"}
}