{
  "type": "Feature",
  "properties": {
    "addr:full":"29 Scott St Warracknabeal VIC 3393",
    "addr:housenumber":"29",
    "addr:postcode":"3393",
    "addr:street":"Scott St",
    "iso:country":"AU",
    "sg:address":"29 Scott St",
    "sg:city":"Warracknabeal",
    "sg:classifiers":[
        {
            "category":"Manufacturing",
            "subcategory":"Chemicals & Compounds",
            "type":"Manufacturing & Wholesale Goods"
        }
    ],
    "sg:phone":"+61 3 5398 1500",
    "sg:postcode":"3393",
    "sg:province":"VIC",
    "sg:tags":[
        "agricultural"
    ],
    "wof:name":"Smith Robert & Co Pty Ltd",
    "wof:placetype":"venue"
},
  "geometry": {"coordinates":[142.395187378,-36.2476730347],"type":"Point"}
}