{
  "type": "Feature",
  "properties": {
    "addr:full":"Waaia Bearii Rd Waaia VIC 3637",
    "addr:postcode":"3637",
    "addr:street":"Bearii Rd",
    "iso:country":"AU",
    "sg:address":"Waaia Bearii Rd",
    "sg:city":"Waaia",
    "sg:classifiers":[
        {
            "category":"Building & Trades",
            "subcategory":"Construction",
            "type":"Services"
        }
    ],
    "sg:phone":"+61 3 5864 1006",
    "sg:postcode":"3637",
    "sg:province":"VIC",
    "sg:tags":[
        "earth",
        "excavating",
        "moving",
        "contractor"
    ],
    "wof:name":"Tyndall A B & J A",
    "wof:placetype":"venue"
},
  "geometry": {"coordinates":[145.331756592,-36.050983429],"type":"Point"}
}