{
  "type": "Feature",
  "properties": {
    "iso:country":"AU",
    "sg:address":"78 Watsonia Rd",
    "sg:city":"Watsonia",
    "sg:classifiers":[
        {
            "category":"Shopping",
            "subcategory":"Clothing, Apparel, & Fashions",
            "type":"Retail Goods"
        }
    ],
    "sg:phone":"+61 3 9435 5964",
    "sg:postcode":"3087",
    "sg:province":"VIC",
    "sg:tags":[
        "recycled",
        "clothing"
    ],
    "wof:name":"Brotherhood of St Laurence",
    "wof:placetype":"venue"
},
  "geometry": {"coordinates":[145.08302307100001,-37.7098617554],"type":"Point"}
}