{
  "type": "Feature",
  "properties": {
    "iso:country":"AU",
    "sg:address":"PO Box 90",
    "sg:city":"Gelorup",
    "sg:classifiers":[
        {
            "category":"Building & Trades",
            "subcategory":"Construction",
            "type":"Services"
        }
    ],
    "sg:phone":"+61 417 963 383",
    "sg:postcode":"6230",
    "sg:province":"WA",
    "sg:tags":[
        "plasterboard",
        "plasterer",
        "fixer"
    ],
    "wof:name":"Utopian Plastering",
    "wof:placetype":"venue"
},
  "geometry": {"coordinates":[115.648071,-33.416309],"type":"Point"}
}