{
  "type": "Feature",
  "properties": {
    "addr:full":"5 Stratford Pl Bundoora VIC 3083",
    "addr:housenumber":"5",
    "addr:postcode":"3083",
    "addr:street":"Stratford Pl",
    "iso:country":"AU",
    "sg:address":"5 Stratford Pl",
    "sg:city":"Bundoora",
    "sg:classifiers":[
        {
            "category":"Building & Trades",
            "subcategory":"Landscaping Services",
            "type":"Services"
        }
    ],
    "sg:phone":"+61 417 381 319",
    "sg:postcode":"3083",
    "sg:province":"VIC",
    "sg:tags":[
        "designer",
        "landscape",
        "contractor"
    ],
    "wof:name":"Grizzly Adams",
    "wof:placetype":"venue"
},
  "geometry": {"coordinates":[145.06907653799999,-37.7003059387],"type":"Point"}
}