{
  "type": "Feature",
  "properties": {
    "addr:full":"U13/ 45 Normanby Rd Notting Hill VIC 3168",
    "addr:housenumber":"45",
    "addr:postcode":"3168",
    "addr:street":"/;Normanby Rd",
    "iso:country":"AU",
    "sg:address":"U13/ 45 Normanby Rd",
    "sg:city":"Notting Hill",
    "sg:classifiers":[
        {
            "category":"Utilities",
            "subcategory":"Telephone",
            "type":"Services"
        }
    ],
    "sg:phone":"+61 1300 669 103",
    "sg:postcode":"3168",
    "sg:province":"VIC",
    "sg:tags":[
        "installation",
        "system",
        "maintenance"
    ],
    "wof:name":"Leading Mobiles",
    "wof:placetype":"venue"
},
  "geometry": {"coordinates":[145.133544922,-37.905544281],"type":"Point"}
}