{
  "type": "Feature",
  "properties": {
    "iso:country":"AU",
    "sg:address":"PO Box 21",
    "sg:city":"Sunbury",
    "sg:classifiers":[
        {
            "category":"Home & Garden",
            "subcategory":"Building Materials",
            "type":"Retail Goods"
        }
    ],
    "sg:phone":"+61 3 5428 4021",
    "sg:postcode":"3429",
    "sg:province":"VIC",
    "sg:tags":[
        "roofing"
    ],
    "wof:name":"A Sunbury Wall Frames & Trusses Pty Ltd",
    "wof:placetype":"venue"
},
  "geometry": {"coordinates":[144.7290802,-37.5800704956],"type":"Point"}
}