{
  "type": "Feature",
  "properties": {
    "addr:full":"45 Hardinge St Deniliquin NSW 2710",
    "addr:housenumber":"45",
    "addr:postcode":"2710",
    "addr:street":"Hardinge St",
    "iso:country":"AU",
    "sg:address":"45 Hardinge St",
    "sg:city":"Deniliquin",
    "sg:classifiers":[
        {
            "category":"Building & Trades",
            "subcategory":"Equipment Rental",
            "type":"Services"
        }
    ],
    "sg:phone":"+61 3 5881 1944",
    "sg:postcode":"2710",
    "sg:province":"NSW",
    "sg:tags":[
        "hire",
        "catering"
    ],
    "wof:name":"Deniliquin Party Hire",
    "wof:placetype":"venue"
},
  "geometry": {"coordinates":[144.95231628400001,-35.5328178406],"type":"Point"}
}