{
  "type": "Feature",
  "properties": {
    "addr:full":"8 Homedale Ave Concord NSW 2137",
    "addr:housenumber":"8",
    "addr:postcode":"2137",
    "addr:street":"Homedale Ave",
    "iso:country":"AU",
    "sg:address":"8 Homedale Ave",
    "sg:city":"Concord",
    "sg:classifiers":[
        {
            "category":"Home & Garden",
            "subcategory":"Carpets & Floor Coverings",
            "type":"Retail Goods"
        }
    ],
    "sg:phone":"+61 403 222 505",
    "sg:postcode":"2137",
    "sg:province":"NSW",
    "sg:tags":[
        "tile",
        "wall",
        "layer"
    ],
    "wof:name":"Disano Carmelo",
    "wof:placetype":"venue"
},
  "geometry": {"coordinates":[151.09472656200001,-33.8598442078],"type":"Point"}
}