{
  "type": "Feature",
  "properties": {
    "addr:full":"144 Parry St Newcastle NSW 2300",
    "addr:housenumber":"144",
    "addr:postcode":"2300",
    "addr:street":"Parry St",
    "iso:country":"AU",
    "sg:address":"144 Parry St",
    "sg:city":"Newcastle",
    "sg:classifiers":[
        {
            "category":"Shopping",
            "subcategory":"Antiques",
            "type":"Retail Goods"
        }
    ],
    "sg:phone":"+61 2 4961 6484",
    "sg:postcode":"2300",
    "sg:province":"NSW",
    "wof:name":"Newcastle Antique Centre",
    "wof:placetype":"venue"
},
  "geometry": {"coordinates":[151.76182600000001,-32.9291],"type":"Point"}
}