{
  "type": "Feature",
  "properties": {
    "addr:full":"5 Cobbera Crt Carindale QLD 4152",
    "addr:housenumber":"5",
    "addr:postcode":"4152",
    "addr:street":"Cobbera Crt",
    "iso:country":"AU",
    "sg:address":"5 Cobbera Crt",
    "sg:city":"Carindale",
    "sg:classifiers":[
        {
            "category":"Health Services",
            "subcategory":"Health Practitioner",
            "type":"Services"
        }
    ],
    "sg:phone":"+61 7 3395 3188",
    "sg:postcode":"4152",
    "sg:province":"QLD",
    "sg:tags":[
        "psychologist"
    ],
    "wof:name":"Jane Ward",
    "wof:placetype":"venue"
},
  "geometry": {"coordinates":[153.10472106899999,-27.5092601776],"type":"Point"}
}