{
  "type": "Feature",
  "properties": {
    "addr:full":"15 Shylock Crs Sunnybank Hills QLD 4109",
    "addr:housenumber":"15",
    "addr:postcode":"4109",
    "addr:street":"Shylock Crs",
    "iso:country":"AU",
    "sg:address":"15 Shylock Crs",
    "sg:city":"Sunnybank Hills",
    "sg:classifiers":[
        {
            "category":"Building & Trades",
            "subcategory":"Construction",
            "type":"Services"
        }
    ],
    "sg:phone":"+61 7 3272 3222",
    "sg:postcode":"4109",
    "sg:province":"QLD",
    "sg:tags":[
        "joiner",
        "carpenter"
    ],
    "wof:name":"Friends Carpentry Services",
    "wof:placetype":"venue"
},
  "geometry": {"coordinates":[153.05857849099999,-27.598690033],"type":"Point"}
}