{
  "type": "Feature",
  "properties": {
    "iso:country":"AU",
    "sg:address":"2/ 1 Skyline Pl",
    "sg:city":"Frenchs Forest",
    "sg:classifiers":[
        {
            "category":"Professional",
            "subcategory":"Computer Services",
            "type":"Services"
        }
    ],
    "sg:phone":"+61 2 9454 4444",
    "sg:postcode":"2086",
    "sg:province":"NSW",
    "sg:tags":[
        "package",
        "software"
    ],
    "wof:name":"Intercad Pty Ltd",
    "wof:placetype":"venue"
},
  "geometry": {"coordinates":[151.238479614,-33.7507019043],"type":"Point"}
}