{
  "type": "Feature",
  "properties": {
    "addr:full":"6- 10 Tooronga Tce Beverly Hills NSW 2209",
    "addr:housenumber":"10",
    "addr:postcode":"2209",
    "addr:street":"6;Tooronga Tce",
    "iso:country":"AU",
    "sg:address":"6- 10 Tooronga Tce",
    "sg:city":"Beverly Hills",
    "sg:classifiers":[
        {
            "category":"Banks & Credit Unions",
            "subcategory":"Financial Services",
            "type":"Services"
        }
    ],
    "sg:phone":"+61 2 9503 1100",
    "sg:postcode":"2209",
    "sg:province":"NSW",
    "sg:tags":[
        "planning"
    ],
    "wof:name":"Count Wealth Accountants",
    "wof:placetype":"venue"
},
  "geometry": {"coordinates":[151.080872,-33.948555],"type":"Point"}
}