{
  "type": "Feature",
  "properties": {
    "addr:full":"Mount Dandenong Rd Ringwood East VIC 3135",
    "addr:postcode":"3135",
    "addr:street":"Mount Dandenong Rd",
    "iso:country":"AU",
    "sg:address":"Mount Dandenong Rd",
    "sg:city":"Ringwood East",
    "sg:classifiers":[
        {
            "category":"Arena",
            "subcategory":"Sports Club",
            "type":"Entertainment"
        }
    ],
    "sg:phone":"+61 3 9870 8216",
    "sg:postcode":"3135",
    "sg:province":"VIC",
    "sg:tags":[
        "australian",
        "football",
        "rule"
    ],
    "wof:name":"East Ringwood Football Club",
    "wof:placetype":"venue"
},
  "geometry": {"coordinates":[145.24942016599999,-37.8085670471],"type":"Point"}
}