{
  "type": "Feature",
  "properties": {
    "addr:full":"956a Whitehorse Rd Box Hill VIC 3128",
    "addr:housenumber":"956a",
    "addr:postcode":"3128",
    "addr:street":"Whitehorse Rd",
    "iso:country":"AU",
    "sg:address":"956a Whitehorse Rd",
    "sg:city":"Box Hill",
    "sg:classifiers":[
        {
            "category":"Shopping",
            "subcategory":"Mobile Phones",
            "type":"Retail Goods"
        }
    ],
    "sg:phone":"+61 3 9898 8332",
    "sg:postcode":"3128",
    "sg:province":"VIC",
    "sg:tags":[
        "telephone",
        "accessory"
    ],
    "wof:name":"Wonder Phone",
    "wof:placetype":"venue"
},
  "geometry": {"coordinates":[145.123657227,-37.8183746338],"type":"Point"}
}