{
  "type": "Feature",
  "properties": {
    "iso:country":"AU",
    "sg:address":"32 Preston St",
    "sg:city":"Penrith",
    "sg:classifiers":[
        {
            "category":"Retail",
            "subcategory":"Auto Repair",
            "type":"Services"
        }
    ],
    "sg:phone":"+61 2 4731 6313",
    "sg:postcode":"2750",
    "sg:province":"NSW",
    "sg:tags":[
        "fuel",
        "petrol",
        "injection"
    ],
    "wof:name":"Booth's Automotive Repairs",
    "wof:placetype":"venue"
},
  "geometry": {"coordinates":[150.685913086,-33.7631912231],"type":"Point"}
}