{
  "type": "Feature",
  "properties": {
    "iso:country":"AU",
    "sg:address":"33a Taylor St",
    "sg:city":"Moonee Ponds",
    "sg:classifiers":[
        {
            "category":"Professional",
            "subcategory":"Employment Agencies",
            "type":"Services"
        }
    ],
    "sg:phone":"+61 3 9370 9871",
    "sg:postcode":"3039",
    "sg:province":"VIC",
    "wof:name":"Essendon Network For Employment & Training (E.N.E.T)",
    "wof:placetype":"venue"
},
  "geometry": {"coordinates":[144.920013,-37.764008],"type":"Point"}
}