{
  "type": "Feature",
  "properties": {
    "addr:full":"Shop 8,2 Byass St South Hedland WA 6722",
    "addr:housenumber":"8,2",
    "addr:postcode":"6722",
    "addr:street":"Byass St South",
    "iso:country":"AU",
    "sg:address":"Shop 8,2 Byass St",
    "sg:city":"South Hedland",
    "sg:classifiers":[
        {
            "category":"Real Estate",
            "subcategory":"Real Estate Agent",
            "type":"Services"
        }
    ],
    "sg:phone":"+61 8 9140 2300",
    "sg:postcode":"6722",
    "sg:province":"WA",
    "wof:name":"Ray White Port Hedland",
    "wof:placetype":"venue"
},
  "geometry": {"coordinates":[118.60534668,-20.4126968384],"type":"Point"}
}