{
  "type": "Feature",
  "properties": {
    "addr:full":"75 Market St Wollongong NSW 2500",
    "addr:housenumber":"75",
    "addr:postcode":"2500",
    "addr:street":"Market St",
    "iso:country":"AU",
    "sg:address":"75 Market St",
    "sg:city":"Wollongong",
    "sg:classifiers":[
        {
            "category":"Health Services",
            "subcategory":"Doctor",
            "type":"Services"
        }
    ],
    "sg:phone":"+61 2 4227 3322",
    "sg:postcode":"2500",
    "sg:province":"NSW",
    "sg:tags":[
        "medical",
        "practitioner"
    ],
    "wof:name":"Slobodniuk R A",
    "wof:placetype":"venue"
},
  "geometry": {"coordinates":[150.89227299999999,-34.423336],"type":"Point"}
}