{
  "type": "Feature",
  "properties": {
    "addr:full":"Star City Casino Pirrama Rd Pyrmont NSW 2009",
    "addr:postcode":"2009",
    "addr:street":"Pirrama Rd",
    "iso:country":"AU",
    "sg:address":"Star City Casino Pirrama Rd",
    "sg:city":"Pyrmont",
    "sg:classifiers":[
        {
            "category":"Cinema",
            "subcategory":"Movie Theater",
            "type":"Entertainment"
        }
    ],
    "sg:phone":"+61 2 9657 9657",
    "sg:postcode":"2009",
    "sg:province":"NSW",
    "wof:name":"Lyric Theatre at Star City",
    "wof:placetype":"venue"
},
  "geometry": {"coordinates":[151.196899414,-33.8685073853],"type":"Point"}
}