{
  "type": "Feature",
  "properties": {
    "addr:full":"PO Box 589 East Maitland NSW 2323",
    "addr:postcode":"2323",
    "iso:country":"AU",
    "sg:address":"PO Box 589",
    "sg:city":"East Maitland",
    "sg:classifiers":[
        {
            "category":"Real Estate",
            "subcategory":"Real Estate Operator",
            "type":"Services"
        }
    ],
    "sg:phone":"+61 414 275 561",
    "sg:postcode":"2323",
    "sg:province":"NSW",
    "sg:tags":[
        "concrete",
        "pumping"
    ],
    "wof:name":"Newcastle Pumpcrete",
    "wof:placetype":"venue"
},
  "geometry": {"coordinates":[151.58555602999999,-32.753780365],"type":"Point"}
}