{
  "type": "Feature",
  "properties": {
    "addr:full":"229 The Entrance Rd Erina NSW 2250",
    "addr:housenumber":"229",
    "addr:postcode":"2250",
    "addr:street":"The Entrance Rd",
    "iso:country":"AU",
    "sg:address":"229 The Entrance Rd",
    "sg:city":"Erina",
    "sg:classifiers":[
        {
            "category":"Recreation",
            "subcategory":"Fishing",
            "type":"Entertainment"
        }
    ],
    "sg:phone":"+61 2 4367 5555",
    "sg:postcode":"2250",
    "sg:province":"NSW",
    "sg:tags":[
        "tackle"
    ],
    "wof:name":"Freddy's Fishing World",
    "wof:placetype":"venue"
},
  "geometry": {"coordinates":[151.390136719,-33.4333763123],"type":"Point"}
}