{
  "type": "Feature",
  "properties": {
    "addr:full":"Units 12,13,14 & 15 280 Southern Rd Bargo NSW 2574",
    "addr:housenumber":"280",
    "addr:postcode":"2574",
    "addr:street":"15;Southern Rd",
    "iso:country":"AU",
    "sg:address":"Units 12,13,14 & 15 280 Southern Rd",
    "sg:city":"Bargo",
    "sg:classifiers":[
        {
            "category":"Retail",
            "subcategory":"Auto Repair",
            "type":"Services"
        }
    ],
    "sg:phone":"+61 2 4684 1862",
    "sg:postcode":"2574",
    "sg:province":"NSW",
    "sg:tags":[
        "beater",
        "painter",
        "panel"
    ],
    "wof:name":"J J Performance Smash Repairs",
    "wof:placetype":"venue"
},
  "geometry": {"coordinates":[150.60569763199999,-34.2839660645],"type":"Point"}
}