{
  "type": "Feature",
  "properties": {
    "iso:country":"AU",
    "sg:address":"137 East St",
    "sg:city":"Narrandera",
    "sg:classifiers":[
        {
            "category":"Travel",
            "subcategory":"Hotels & Motels",
            "type":"Entertainment"
        }
    ],
    "sg:phone":"+61 2 6959 2007",
    "sg:postcode":"2700",
    "sg:province":"NSW",
    "sg:tags":[
        "accommodation"
    ],
    "wof:name":"Royal Mail Hotel",
    "wof:placetype":"venue"
},
  "geometry": {"coordinates":[146.553268433,-34.7468109131],"type":"Point"}
}