{
  "type": "Feature",
  "properties": {
    "addr:full":"31 Jewell La East Perth WA 6004",
    "addr:housenumber":"31",
    "addr:postcode":"6004",
    "addr:street":"Jewell La East",
    "iso:country":"AU",
    "sg:address":"31 Jewell La",
    "sg:city":"East Perth",
    "sg:classifiers":[
        {
            "category":"Building & Trades",
            "subcategory":"Construction",
            "type":"Services"
        }
    ],
    "sg:phone":"+61 8 9218 8112",
    "sg:postcode":"6004",
    "sg:province":"WA",
    "sg:tags":[
        "contractor"
    ],
    "wof:name":"Kelmont Homes",
    "wof:placetype":"venue"
},
  "geometry": {"coordinates":[115.880462647,-31.9497203827],"type":"Point"}
}