{
  "type": "Feature",
  "properties": {
    "iso:country":"AU",
    "sg:address":"\"Glenlands\" Bouldercombe Rd Via Rockhampton",
    "sg:city":"Bouldercombe",
    "sg:classifiers":[
        {
            "category":"Building & Trades",
            "subcategory":"Landscaping Services",
            "type":"Services"
        }
    ],
    "sg:phone":"+61 7 4934 0195",
    "sg:postcode":"4702",
    "sg:province":"QLD",
    "sg:tags":[
        "grazier"
    ],
    "wof:name":"Childs B & V",
    "wof:placetype":"venue"
},
  "geometry": {"coordinates":[150.50003051799999,-23.4711399078],"type":"Point"}
}