{
  "type": "Feature",
  "properties": {
    "addr:full":"Desert Pea Caravn Pk Augusta St Laverton WA 6440",
    "addr:postcode":"6440",
    "addr:street":"Desert;Augusta St",
    "iso:country":"AU",
    "sg:address":"Desert Pea Caravn Pk Augusta St",
    "sg:city":"Laverton",
    "sg:classifiers":[
        {
            "category":"Fast Food",
            "type":"Food & Drink"
        }
    ],
    "sg:phone":"+61 8 9031 1525",
    "sg:postcode":"6440",
    "sg:province":"WA",
    "sg:tags":[
        "away",
        "take"
    ],
    "wof:name":"Thistle Doo",
    "wof:placetype":"venue"
},
  "geometry": {"coordinates":[122.403297424,-28.6257190704],"type":"Point"}
}