{
  "type": "Feature",
  "properties": {
    "addr:full":"21 Kenyon Rd Bexley NSW 2207",
    "addr:housenumber":"21",
    "addr:postcode":"2207",
    "addr:street":"Kenyon Rd",
    "iso:country":"AU",
    "sg:address":"21 Kenyon Rd",
    "sg:city":"Bexley",
    "sg:classifiers":[
        {
            "category":"Professional",
            "subcategory":"Art Services",
            "type":"Services"
        }
    ],
    "sg:phone":"+61 412 288 893",
    "sg:postcode":"2207",
    "sg:province":"NSW",
    "sg:tags":[
        "decorator",
        "painter"
    ],
    "wof:name":"Midcity Painting Contractors",
    "wof:placetype":"venue"
},
  "geometry": {"coordinates":[151.111313,-33.957279],"type":"Point"}
}