{
  "type": "Feature",
  "properties": {
    "addr:full":"Waterport Rd (Corner Pit Lane) Victor Harbor SA 5211",
    "addr:postcode":"5211",
    "addr:street":"Waterport Rd Corner Pit Lane",
    "iso:country":"AU",
    "sg:address":"Waterport Rd",
    "sg:city":"(Corner Pit Lane) Victor Harbor",
    "sg:classifiers":[
        {
            "category":"Wholesale",
            "subcategory":"Farm Supplies",
            "type":"Manufacturing & Wholesale Goods"
        }
    ],
    "sg:phone":"+61 8 8552 4455",
    "sg:postcode":"5211",
    "sg:province":"SA",
    "sg:tags":[
        "feed",
        "supplement",
        "stock"
    ],
    "wof:name":"Garden Works",
    "wof:placetype":"venue"
},
  "geometry": {"coordinates":[138.64457702600001,-35.525062561],"type":"Point"}
}