{
  "type": "Feature",
  "properties": {
    "iso:country":"AU",
    "sg:address":"188 Pacific Hwy",
    "sg:city":"Tuggerah",
    "sg:classifiers":[
        {
            "category":"Professional",
            "subcategory":"Detective & Security Services",
            "type":"Services"
        }
    ],
    "sg:phone":"+61 2 4356 7080",
    "sg:postcode":"2259",
    "sg:province":"NSW",
    "sg:tags":[
        "equipment",
        "window",
        "doors"
    ],
    "wof:name":"Bradnams Windows & Doors",
    "wof:placetype":"venue"
},
  "geometry": {"coordinates":[151.42291259800001,-33.2930526733],"type":"Point"}
}