{
  "type": "Feature",
  "properties": {
    "iso:country":"AU",
    "sg:address":"599 Riversdale Rd",
    "sg:city":"Camberwell",
    "sg:classifiers":[
        {
            "category":"Health Services",
            "subcategory":"Doctor",
            "type":"Services"
        }
    ],
    "sg:phone":"+61 3 9882 9144",
    "sg:postcode":"3124",
    "sg:province":"VIC",
    "sg:tags":[
        "medical",
        "practitioner"
    ],
    "wof:name":"Martens Karen Dr",
    "wof:placetype":"venue"
},
  "geometry": {"coordinates":[145.06353759800001,-37.8319816589],"type":"Point"}
}