{
  "type": "Feature",
  "properties": {
    "addr:full":"Unit 1/ 3 Stoddart Rd Prospect NSW 2148",
    "addr:postcode":"2148",
    "addr:street":"Stoddart Rd",
    "iso:country":"AU",
    "sg:address":"Unit 1/ 3 Stoddart Rd",
    "sg:city":"Prospect",
    "sg:classifiers":[
        {
            "category":"Wholesale",
            "subcategory":"Machinery & Supplies",
            "type":"Manufacturing & Wholesale Goods"
        }
    ],
    "sg:phone":"+61 2 9688 1562",
    "sg:postcode":"2148",
    "sg:province":"NSW",
    "sg:tags":[
        "equipment",
        "hydraulic"
    ],
    "wof:name":"Coastal Hydraulics & Pneumatic Services",
    "wof:placetype":"venue"
},
  "geometry": {"coordinates":[150.92367553700001,-33.8004417419],"type":"Point"}
}