{
  "type": "Feature",
  "properties": {
    "addr:full":"238 North St Toowoomba QLD 4350",
    "addr:housenumber":"238",
    "addr:postcode":"4350",
    "addr:street":"North St",
    "iso:country":"AU",
    "sg:address":"238 North St",
    "sg:city":"Toowoomba",
    "sg:classifiers":[
        {
            "category":"Building & Trades",
            "subcategory":"Plumbing",
            "type":"Services"
        }
    ],
    "sg:phone":"+61 7 4633 3383",
    "sg:postcode":"4350",
    "sg:province":"QLD",
    "sg:tags":[
        "plumber",
        "gasfitters"
    ],
    "sg:website":"http://www.plumberstoday.com",
    "wof:name":"Plumbers Today",
    "wof:placetype":"venue"
},
  "geometry": {"coordinates":[151.928314,-27.538273],"type":"Point"}
}