{
  "type": "Feature",
  "properties": {
    "iso:country":"AU",
    "sg:address":"449 High St",
    "sg:city":"Northcote",
    "sg:classifiers":[
        {
            "category":"Communications",
            "subcategory":"Film & Video Production",
            "type":"Services"
        }
    ],
    "sg:phone":"+61 3 9481 6494",
    "sg:postcode":"3070",
    "sg:province":"VIC",
    "sg:tags":[
        "dvd",
        "library"
    ],
    "wof:name":"Top Video",
    "wof:placetype":"venue"
},
  "geometry": {"coordinates":[144.99902299999999,-37.767128],"type":"Point"}
}