{
  "type": "Feature",
  "properties": {
    "addr:full":"44 Sharp St Cooma NSW 2630",
    "addr:housenumber":"44",
    "addr:postcode":"2630",
    "addr:street":"Sharp St",
    "iso:country":"AU",
    "sg:address":"44 Sharp St",
    "sg:city":"Cooma",
    "sg:classifiers":[
        {
            "category":"Structure",
            "subcategory":"Bridge",
            "type":"Public Place"
        }
    ],
    "sg:phone":"+61 2 6452 4956",
    "sg:postcode":"2630",
    "sg:province":"NSW",
    "sg:tags":[
        "chainsaw",
        "brushcutters"
    ],
    "wof:name":"Stihl Shop Cooma",
    "wof:placetype":"venue"
},
  "geometry": {"coordinates":[149.13412475600001,-36.2313613892],"type":"Point"}
}