{
  "type": "Feature",
  "properties": {
    "addr:full":"4 Torpey Pl Broadmeadow NSW 2292",
    "addr:housenumber":"4",
    "addr:postcode":"2292",
    "addr:street":"Torpey Pl",
    "iso:country":"AU",
    "sg:address":"4 Torpey Pl",
    "sg:city":"Broadmeadow",
    "sg:classifiers":[
        {
            "category":"Health Services",
            "subcategory":"Health Practitioner",
            "type":"Services"
        }
    ],
    "sg:phone":"+61 421 328 083",
    "sg:postcode":"2292",
    "sg:province":"NSW",
    "sg:tags":[
        "alternative"
    ],
    "wof:name":"Karen Edwards",
    "wof:placetype":"venue"
},
  "geometry": {"coordinates":[151.73863220199999,-32.9237556458],"type":"Point"}
}