{
  "type": "Feature",
  "properties": {
    "iso:country":"AU",
    "sg:address":"28 Cowper Ave",
    "sg:city":"Pagewood",
    "sg:classifiers":[
        {
            "category":"Health Services",
            "subcategory":"Health Practitioner",
            "type":"Services"
        }
    ],
    "sg:phone":"+61 2 9316 8124",
    "sg:postcode":"2035",
    "sg:province":"NSW",
    "sg:tags":[
        "osteopath"
    ],
    "wof:name":"Landon Peggy",
    "wof:placetype":"venue"
},
  "geometry": {"coordinates":[151.217727661,-33.940196991],"type":"Point"}
}