{
  "type": "Feature",
  "properties": {
    "addr:full":"783 Burke Rd Camberwell VIC 3124",
    "addr:housenumber":"783",
    "addr:postcode":"3124",
    "addr:street":"Burke Rd",
    "iso:country":"AU",
    "sg:address":"783 Burke Rd",
    "sg:city":"Camberwell",
    "sg:classifiers":[
        {
            "category":"Shopping",
            "subcategory":"Shoes",
            "type":"Retail Goods"
        }
    ],
    "sg:phone":"+61 3 9882 8944",
    "sg:postcode":"3124",
    "sg:province":"VIC",
    "sg:tags":[
        "footwear"
    ],
    "wof:name":"Mulberry Hill Shoes",
    "wof:placetype":"venue"
},
  "geometry": {"coordinates":[145.056884766,-37.8294258118],"type":"Point"}
}