{
  "type": "Feature",
  "properties": {
    "addr:full":"6 Stapleton Rd East Ballina NSW 2478",
    "addr:housenumber":"6",
    "addr:postcode":"2478",
    "addr:street":"Stapleton Rd",
    "iso:country":"AU",
    "sg:address":"6 Stapleton Rd",
    "sg:city":"East Ballina",
    "sg:classifiers":[
        {
            "category":"Wholesale",
            "subcategory":"Apparel",
            "type":"Manufacturing & Wholesale Goods"
        }
    ],
    "sg:phone":"+61 2 6686 4046",
    "sg:postcode":"2478",
    "sg:province":"NSW",
    "sg:tags":[
        "wholesaler",
        "mfrs",
        "sportswear",
        "women's"
    ],
    "wof:name":"Ozinet Performance Wear",
    "wof:placetype":"venue"
},
  "geometry": {"coordinates":[153.5806427,-28.8564357758],"type":"Point"}
}