{
  "type": "Feature",
  "properties": {
    "addr:full":"Production Pl Penrith NSW 2750",
    "addr:postcode":"2750",
    "addr:street":"Production Pl",
    "iso:country":"AU",
    "sg:address":"Production Pl",
    "sg:city":"Penrith",
    "sg:classifiers":[
        {
            "category":"Building & Trades",
            "subcategory":"Construction",
            "type":"Services"
        }
    ],
    "sg:phone":"+61 2 4736 3363",
    "sg:postcode":"2750",
    "sg:province":"NSW",
    "sg:tags":[
        "concrete",
        "contractor"
    ],
    "wof:name":"FYNA Concreting & Excavations",
    "wof:placetype":"venue"
},
  "geometry": {"coordinates":[150.68467712399999,-33.7688522339],"type":"Point"}
}