{
  "type": "Feature",
  "properties": {
    "iso:country":"AU",
    "sg:address":"260 Wright St",
    "sg:city":"Adelaide",
    "sg:classifiers":[
        {
            "category":"Shopping",
            "subcategory":"Computers & Home Electronics",
            "type":"Retail Goods"
        }
    ],
    "sg:phone":"+61 8 8231 3000",
    "sg:postcode":"5000",
    "sg:province":"SA",
    "sg:tags":[
        "hardware",
        "equipment"
    ],
    "wof:name":"Multi Media Interlan (Aust) Pty Ltd",
    "wof:placetype":"venue"
},
  "geometry": {"coordinates":[138.599243164,-34.931427002],"type":"Point"}
}