{
  "type": "Feature",
  "properties": {
    "addr:full":"Suite 1 Whitford Medical Centre Cnr Whitfords & Dampier Ave Kallaroo WA 6025",
    "addr:postcode":"6025",
    "addr:street":"Cnr Whitfords & Dampier Ave",
    "iso:country":"AU",
    "sg:address":"Suite 1 Whitford Medical Centre Cnr Whitfords & Dampier Ave",
    "sg:city":"Kallaroo",
    "sg:classifiers":[
        {
            "category":"Health Services",
            "subcategory":"Dentist",
            "type":"Services"
        }
    ],
    "sg:phone":"+61 8 9401 1376",
    "sg:postcode":"6025",
    "sg:province":"WA",
    "wof:name":"Ball Jenny Dr",
    "wof:placetype":"venue"
},
  "geometry": {"coordinates":[115.744438171,-31.7961959839],"type":"Point"}
}