{
  "type": "Feature",
  "properties": {
    "addr:full":"16 Swinburne St Geelong North VIC 3215",
    "addr:housenumber":"16",
    "addr:postcode":"3215",
    "addr:street":"Swinburne St",
    "iso:country":"AU",
    "sg:address":"16 Swinburne St",
    "sg:city":"Geelong North",
    "sg:classifiers":[
        {
            "category":"Health Services",
            "subcategory":"Doctor",
            "type":"Services"
        }
    ],
    "sg:phone":"+61 3 5277 1490",
    "sg:postcode":"3215",
    "sg:province":"VIC",
    "sg:tags":[
        "nurse",
        "nursing"
    ],
    "wof:name":"Homebirth Midwife",
    "wof:placetype":"venue"
},
  "geometry": {"coordinates":[144.35548400900001,-38.1198692322],"type":"Point"}
}