{
  "type": "Feature",
  "properties": {
    "iso:country":"AU",
    "sg:address":"364 Norton St",
    "sg:city":"Leichhardt",
    "sg:classifiers":[
        {
            "category":"Shopping",
            "subcategory":"Stationery & Office Supplies",
            "type":"Retail Goods"
        }
    ],
    "sg:phone":"+61 2 9569 3033",
    "sg:postcode":"2040",
    "sg:province":"NSW",
    "sg:tags":[
        "partition"
    ],
    "wof:name":"Lexicom Interiors Pty Ltd",
    "wof:placetype":"venue"
},
  "geometry": {"coordinates":[151.15588399999999,-33.874592],"type":"Point"}
}