{
  "type": "Feature",
  "properties": {
    "iso:country":"AU",
    "sg:address":"961 Glen Huntly Rd",
    "sg:city":"Caulfield",
    "sg:classifiers":[
        {
            "category":"Health Services",
            "subcategory":"Doctor",
            "type":"Services"
        }
    ],
    "sg:phone":"+61 3 9569 3311",
    "sg:postcode":"3162",
    "sg:province":"VIC",
    "sg:tags":[
        "medical",
        "practitioner"
    ],
    "wof:name":"Caulfield Laser Eye Clinic",
    "wof:placetype":"venue"
},
  "geometry": {"coordinates":[145.030487061,-37.887802124],"type":"Point"}
}