{
  "type": "Feature",
  "properties": {
    "iso:country":"AU",
    "sg:address":"Shp2/ 132 Colac Rd",
    "sg:city":"Waurn Ponds",
    "sg:classifiers":[
        {
            "category":"Fast Food",
            "type":"Food & Drink"
        }
    ],
    "sg:phone":"+61 3 5243 1999",
    "sg:postcode":"3216",
    "sg:province":"VIC",
    "sg:tags":[
        "away",
        "take"
    ],
    "wof:name":"Bubba's Pizza Pasta & More",
    "wof:placetype":"venue"
},
  "geometry": {"coordinates":[144.32661438,-38.1868133545],"type":"Point"}
}