{
  "type": "Feature",
  "properties": {
    "addr:full":"Lvl1, 35 Lawson St Penrith NSW 2750",
    "addr:housenumber":"35",
    "addr:postcode":"2750",
    "addr:street":"Lawson St",
    "iso:country":"AU",
    "sg:address":"Lvl1, 35 Lawson St",
    "sg:city":"Penrith",
    "sg:classifiers":[
        {
            "category":"Banks & Credit Unions",
            "subcategory":"Financial Services",
            "type":"Services"
        }
    ],
    "sg:phone":"+61 2 4731 4833",
    "sg:postcode":"2750",
    "sg:province":"NSW",
    "sg:tags":[
        "planning"
    ],
    "wof:name":"Lifespan Financial Planning Pty Ltd",
    "wof:placetype":"venue"
},
  "geometry": {"coordinates":[150.66273498499999,-33.750415802],"type":"Point"}
}