{
  "type": "Feature",
  "properties": {
    "iso:country":"AU",
    "sg:address":"Gilmore Ave",
    "sg:city":"Leda",
    "sg:classifiers":[
        {
            "category":"Deli",
            "type":"Food & Drink"
        }
    ],
    "sg:phone":"+61 8 9439 4443",
    "sg:postcode":"6170",
    "sg:province":"WA",
    "sg:tags":[
        "delicatessen"
    ],
    "wof:name":"Leda Continental Supa Deli",
    "wof:placetype":"venue"
},
  "geometry": {"coordinates":[115.807518,-32.259644],"type":"Point"}
}