{
  "type": "Feature",
  "properties": {
    "iso:country":"AU",
    "sg:address":"80 Amaroo Drv",
    "sg:city":"Moree",
    "sg:classifiers":[
        {
            "category":"Personal",
            "type":"Services"
        }
    ],
    "sg:phone":"+61 2 6752 2584",
    "sg:postcode":"2400",
    "sg:province":"NSW",
    "sg:tags":[
        "wallpapering",
        "wallcovering"
    ],
    "wof:name":"Wayne Tucker",
    "wof:placetype":"venue"
},
  "geometry": {"coordinates":[149.839385986,-29.4845600128],"type":"Point"}
}