{
  "type": "Feature",
  "properties": {
    "iso:country":"AU",
    "sg:address":"86 Neurum Rd",
    "sg:city":"Yaroomba",
    "sg:classifiers":[
        {
            "category":"Professional",
            "subcategory":"Art Services",
            "type":"Services"
        }
    ],
    "sg:phone":"+61 7 5446 4684",
    "sg:postcode":"4573",
    "sg:province":"QLD",
    "sg:tags":[
        "decorator",
        "painter"
    ],
    "wof:name":"Steve Wildman",
    "wof:placetype":"venue"
},
  "geometry": {"coordinates":[153.09364299999999,-26.547958],"type":"Point"}
}