{
  "type": "Feature",
  "properties": {
    "addr:full":"Riddell Rd Sunbury VIC 3429",
    "addr:postcode":"3429",
    "addr:street":"Riddell Rd",
    "iso:country":"AU",
    "sg:address":"Riddell Rd",
    "sg:city":"Sunbury",
    "sg:classifiers":[
        {
            "category":"Government",
            "subcategory":"City Hall",
            "type":"Public Place"
        }
    ],
    "sg:phone":"+61 3 9205 2583",
    "sg:postcode":"3429",
    "sg:province":"VIC",
    "wof:name":"Sunbury Recreation Stadium",
    "wof:placetype":"venue"
},
  "geometry": {"coordinates":[144.728118897,-37.5753097534],"type":"Point"}
}