{
  "type": "Feature",
  "properties": {
    "iso:country":"AU",
    "sg:address":"62 Oxley Drv",
    "sg:city":"Mittagong",
    "sg:classifiers":[
        {
            "category":"Health Services",
            "subcategory":"Chiropractor",
            "type":"Services"
        }
    ],
    "sg:phone":"+61 2 4871 2000",
    "sg:postcode":"2575",
    "sg:province":"NSW",
    "wof:name":"Hutter Franz",
    "wof:placetype":"venue"
},
  "geometry": {"coordinates":[150.44471740700001,-34.4611206055],"type":"Point"}
}