{
  "type": "Feature",
  "properties": {
    "addr:full":"167a Barkly St Footscray VIC 3011",
    "addr:housenumber":"167a",
    "addr:postcode":"3011",
    "addr:street":"Barkly St",
    "iso:country":"AU",
    "sg:address":"167a Barkly St",
    "sg:city":"Footscray",
    "sg:classifiers":[
        {
            "category":"Professional",
            "subcategory":"Accounting & Tax Preparation",
            "type":"Services"
        }
    ],
    "sg:phone":"+61 3 9687 9103",
    "sg:postcode":"3011",
    "sg:province":"VIC",
    "sg:tags":[
        "consultant",
        "taxation"
    ],
    "wof:name":"Yet You Wong & Co",
    "wof:placetype":"venue"
},
  "geometry": {"coordinates":[144.89747619600001,-37.7996292114],"type":"Point"}
}