{
  "type": "Feature",
  "properties": {
    "iso:country":"AU",
    "sg:address":"84-86 Leader St",
    "sg:city":"Forestville",
    "sg:classifiers":[
        {
            "category":"Home & Garden",
            "subcategory":"Garden Supply",
            "type":"Retail Goods"
        }
    ],
    "sg:phone":"+61 8 8297 7000",
    "sg:postcode":"5035",
    "sg:province":"SA",
    "sg:tags":[
        "equipment"
    ],
    "wof:name":"Water Motion Energy",
    "wof:placetype":"venue"
},
  "geometry": {"coordinates":[138.58151245100001,-34.9488563538],"type":"Point"}
}