{
  "type": "Feature",
  "properties": {
    "addr:full":"Beach Rd Batemans Bay NSW 2536",
    "addr:postcode":"2536",
    "addr:street":"Beach Rd",
    "iso:country":"AU",
    "sg:address":"Beach Rd",
    "sg:city":"Batemans Bay",
    "sg:classifiers":[
        {
            "category":"Professional",
            "subcategory":"Art Services",
            "type":"Services"
        }
    ],
    "sg:phone":"+61 2 4472 4466",
    "sg:postcode":"2536",
    "sg:province":"NSW",
    "sg:tags":[
        "decorator",
        "painter"
    ],
    "wof:name":"Mastercraft Painting Contractors Pty Ltd",
    "wof:placetype":"venue"
},
  "geometry": {"coordinates":[150.17732238799999,-35.7083892822],"type":"Point"}
}