{
  "type": "Feature",
  "properties": {
    "iso:country":"AU",
    "sg:address":"90 Bushlands Rd",
    "sg:city":"Hovea",
    "sg:classifiers":[
        {
            "category":"Building & Trades",
            "subcategory":"Construction",
            "type":"Services"
        }
    ],
    "sg:phone":"+61 8 9295 5338",
    "sg:postcode":"6071",
    "sg:province":"WA",
    "sg:tags":[
        "earth",
        "excavating",
        "moving",
        "contractor"
    ],
    "wof:name":"Kais Contractors Pty Ltd",
    "wof:placetype":"venue"
},
  "geometry": {"coordinates":[116.11328125,-31.8838329315],"type":"Point"}
}