{
  "type": "Feature",
  "properties": {
    "addr:full":"6 Halleendale Rd Walliston WA 6076",
    "addr:housenumber":"6",
    "addr:postcode":"6076",
    "addr:street":"Halleendale Rd",
    "iso:country":"AU",
    "sg:address":"6 Halleendale Rd",
    "sg:city":"Walliston",
    "sg:classifiers":[
        {
            "category":"Education",
            "subcategory":"School",
            "type":"Public Place"
        }
    ],
    "sg:phone":"+61 8 9291 8749",
    "sg:postcode":"6076",
    "sg:province":"WA",
    "sg:tags":[
        "co-educational"
    ],
    "wof:name":"Kalamunda Christian School",
    "wof:placetype":"venue"
},
  "geometry": {"coordinates":[116.068466187,-32.0013961792],"type":"Point"}
}