{
  "type": "Feature",
  "properties": {
    "iso:country":"AU",
    "sg:address":"10 Philippa Crt",
    "sg:city":"Kellyville",
    "sg:classifiers":[
        {
            "category":"Professional",
            "subcategory":"Printing & Photocopies",
            "type":"Services"
        }
    ],
    "sg:phone":"+61 2 8824 5135",
    "sg:postcode":"2155",
    "sg:province":"NSW",
    "sg:tags":[
        "publishing",
        "desktop"
    ],
    "wof:name":"byDesign Graphics & Print",
    "wof:placetype":"venue"
},
  "geometry": {"coordinates":[150.978973389,-33.702999115],"type":"Point"}
}