{
  "type": "Feature",
  "properties": {
    "addr:full":"Lvl 1/ 9 Park Ave Coffs Harbour NSW 2450",
    "addr:housenumber":"/ 9",
    "addr:postcode":"2450",
    "addr:street":"Park Ave",
    "iso:country":"AU",
    "sg:address":"Lvl 1/ 9 Park Ave",
    "sg:city":"Coffs Harbour",
    "sg:classifiers":[
        {
            "category":"Health Services",
            "subcategory":"Doctor",
            "type":"Services"
        }
    ],
    "sg:phone":"+61 2 6659 2159",
    "sg:postcode":"2450",
    "sg:province":"NSW",
    "sg:tags":[
        "medical",
        "practitioner"
    ],
    "wof:name":"Strum Dr John Robert",
    "wof:placetype":"venue"
},
  "geometry": {"coordinates":[153.11454800000001,-30.297506],"type":"Point"}
}