{
  "type": "Feature",
  "properties": {
    "addr:full":"PO Box 6044 Ryde NSW 2112",
    "addr:postcode":"2112",
    "iso:country":"AU",
    "sg:address":"PO Box 6044",
    "sg:city":"Ryde",
    "sg:classifiers":[
        {
            "category":"Building & Trades",
            "subcategory":"Plumbing",
            "type":"Services"
        }
    ],
    "sg:phone":"+61 418 969 974",
    "sg:postcode":"2112",
    "sg:province":"NSW",
    "sg:tags":[
        "plumber",
        "gasfitters"
    ],
    "wof:name":"Timmins Paul",
    "wof:placetype":"venue"
},
  "geometry": {"coordinates":[151.11233520499999,-33.8131599426],"type":"Point"}
}