{
  "type": "Feature",
  "properties": {
    "addr:full":"Laycock St Carey Bay NSW 2283",
    "addr:postcode":"2283",
    "addr:street":"Laycock St",
    "iso:country":"AU",
    "sg:address":"Laycock St",
    "sg:city":"Carey Bay",
    "sg:classifiers":[
        {
            "category":"Health Services",
            "subcategory":"Nursing And Care Facility",
            "type":"Services"
        }
    ],
    "sg:phone":"+61 2 4959 1137",
    "sg:postcode":"2283",
    "sg:province":"NSW",
    "sg:tags":[
        "home"
    ],
    "wof:name":"Carey Bay Nursing Home",
    "wof:placetype":"venue"
},
  "geometry": {"coordinates":[151.60621643100001,-33.0268516541],"type":"Point"}
}