{
  "type": "Feature",
  "properties": {
    "iso:country":"AU",
    "sg:address":"47 Webber Pde",
    "sg:city":"Keilor East",
    "sg:classifiers":[
        {
            "category":"Banks & Credit Unions",
            "subcategory":"Atm",
            "type":"Services"
        }
    ],
    "sg:phone":"+61 3 9331 5721",
    "sg:postcode":"3033",
    "sg:province":"VIC",
    "sg:tags":[
        "box",
        "case",
        "metal"
    ],
    "wof:name":"AGM Tool Boxes",
    "wof:placetype":"venue"
},
  "geometry": {"coordinates":[144.856033,-37.733147],"type":"Point"}
}