{
  "type": "Feature",
  "properties": {
    "iso:country":"AU",
    "sg:address":"9 Bass Pl",
    "sg:city":"Paradise Point",
    "sg:classifiers":[
        {
            "category":"Manufacturing",
            "subcategory":"Jewelry",
            "type":"Manufacturing & Wholesale Goods"
        }
    ],
    "sg:phone":"+61 7 5577 2087",
    "sg:postcode":"4216",
    "sg:province":"QLD",
    "sg:tags":[
        "mfrg",
        "jeweller"
    ],
    "wof:name":"Body Gold",
    "wof:placetype":"venue"
},
  "geometry": {"coordinates":[153.38656616200001,-27.8805980682],"type":"Point"}
}