{
  "type": "Feature",
  "properties": {
    "addr:full":"39 Grosvenor St Bondi Junction NSW 2022",
    "addr:housenumber":"39",
    "addr:postcode":"2022",
    "addr:street":"Grosvenor St",
    "iso:country":"AU",
    "sg:address":"39 Grosvenor St",
    "sg:city":"Bondi Junction",
    "sg:classifiers":[
        {
            "category":"Professional",
            "subcategory":"Management & Consulting",
            "type":"Services"
        }
    ],
    "sg:phone":"+61 2 9369 2466",
    "sg:postcode":"2022",
    "sg:province":"NSW",
    "sg:tags":[
        "consultant"
    ],
    "wof:name":"Alliance",
    "wof:placetype":"venue"
},
  "geometry": {"coordinates":[151.24974060100001,-33.8903160095],"type":"Point"}
}