{
  "type": "Feature",
  "properties": {
    "iso:country":"AU",
    "sg:address":"Unit 1/Lot 119 Gingin Rd",
    "sg:city":"Lancelin",
    "sg:classifiers":[
        {
            "category":"Fast Food",
            "type":"Food & Drink"
        }
    ],
    "sg:phone":"+61 8 9655 1040",
    "sg:postcode":"6044",
    "sg:province":"WA",
    "sg:tags":[
        "away",
        "take"
    ],
    "wof:name":"L J's Diner",
    "wof:placetype":"venue"
},
  "geometry": {"coordinates":[115.332221985,-31.0199260712],"type":"Point"}
}