{
  "type": "Feature",
  "properties": {
    "addr:full":"City Arcade Murray St Level Perth WA 6000",
    "addr:postcode":"6000",
    "addr:street":"Murray St",
    "iso:country":"AU",
    "sg:address":"City Arcade Murray St Level",
    "sg:city":"Perth",
    "sg:classifiers":[
        {
            "category":"Shopping",
            "subcategory":"Clothing, Apparel, & Fashions",
            "type":"Retail Goods"
        }
    ],
    "sg:phone":"+61 8 9481 1588",
    "sg:postcode":"6000",
    "sg:province":"WA",
    "sg:tags":[
        "lady",
        "wear"
    ],
    "wof:name":"Memphis",
    "wof:placetype":"venue"
},
  "geometry": {"coordinates":[115.85439300500001,-31.9514198303],"type":"Point"}
}