{
  "type": "Feature",
  "properties": {
    "iso:country":"AU",
    "sg:address":"80 Beverley Hill St",
    "sg:city":"Moorooka",
    "sg:classifiers":[
        {
            "category":"Health Services",
            "subcategory":"Doctor",
            "type":"Services"
        }
    ],
    "sg:phone":"+61 7 3848 7924",
    "sg:postcode":"4105",
    "sg:province":"QLD",
    "sg:tags":[
        "occupational",
        "safety"
    ],
    "wof:name":"David Moore & Associates Pty Ltd",
    "wof:placetype":"venue"
},
  "geometry": {"coordinates":[153.03054809599999,-27.5289363861],"type":"Point"}
}