{
  "type": "Feature",
  "properties": {
    "iso:country":"AU",
    "sg:address":"PO Box 49",
    "sg:city":"Mallala",
    "sg:classifiers":[
        {
            "category":"Retail",
            "subcategory":"Auto Repair",
            "type":"Services"
        }
    ],
    "sg:phone":"+61 8 8527 2106",
    "sg:postcode":"5502",
    "sg:province":"SA",
    "sg:tags":[
        "camper-trailers",
        "caravan",
        "servicing"
    ],
    "wof:name":"Caravan Refrigeration Services S.A.",
    "wof:placetype":"venue"
},
  "geometry": {"coordinates":[138.509964,-34.437969],"type":"Point"}
}