{
  "type": "Feature",
  "properties": {
    "iso:country":"AU",
    "sg:address":"428 Whitehorse Rd",
    "sg:city":"Nunawading",
    "sg:classifiers":[
        {
            "category":"Autos & Motor Vehicles",
            "subcategory":"Auto Supplies",
            "type":"Retail Goods"
        }
    ],
    "sg:phone":"+61 3 9872 3799",
    "sg:postcode":"3131",
    "sg:province":"VIC",
    "sg:tags":[
        "automotive",
        "stereo",
        "radio"
    ],
    "wof:name":"JB HI-FI",
    "wof:placetype":"venue"
},
  "geometry": {"coordinates":[145.18440246599999,-37.8179740906],"type":"Point"}
}