{
  "type": "Feature",
  "properties": {
    "iso:country":"AU",
    "sg:address":"29 Barrie Rd",
    "sg:city":"Tullamarine",
    "sg:classifiers":[
        {
            "category":"Banks & Credit Unions",
            "subcategory":"Investment Brokerage",
            "type":"Services"
        }
    ],
    "sg:phone":"+61 3 9372 7822",
    "sg:postcode":"3043",
    "sg:province":"VIC",
    "sg:tags":[
        "debt",
        "collection"
    ],
    "wof:name":"Australian Commercial Collections",
    "wof:placetype":"venue"
},
  "geometry": {"coordinates":[144.87644958499999,-37.7134208679],"type":"Point"}
}