{
  "type": "Feature",
  "properties": {
    "addr:full":"87 Cheltenham Rd Cheltenham NSW 2119",
    "addr:housenumber":"87",
    "addr:postcode":"2119",
    "addr:street":"Cheltenham Rd",
    "iso:country":"AU",
    "sg:address":"87 Cheltenham Rd",
    "sg:city":"Cheltenham",
    "sg:classifiers":[
        {
            "category":"Personal",
            "type":"Services"
        }
    ],
    "sg:phone":"+61 2 9877 0640",
    "sg:postcode":"2119",
    "sg:province":"NSW",
    "sg:tags":[
        "reducing",
        "treatment",
        "weight"
    ],
    "wof:name":"Herbalife Australasia Pty Ltd",
    "wof:placetype":"venue"
},
  "geometry": {"coordinates":[151.07293701200001,-33.7609558105],"type":"Point"}
}