{
  "type": "Feature",
  "properties": {
    "addr:full":"29a Worthing St Westminster WA 6061",
    "addr:housenumber":"29a",
    "addr:postcode":"6061",
    "addr:street":"Worthing St",
    "iso:country":"AU",
    "sg:address":"29a Worthing St",
    "sg:city":"Westminster",
    "sg:classifiers":[
        {
            "category":"Professional",
            "subcategory":"Art Services",
            "type":"Services"
        }
    ],
    "sg:phone":"+61 8 9349 3447",
    "sg:postcode":"6061",
    "sg:province":"WA",
    "sg:tags":[
        "decorator",
        "painter"
    ],
    "wof:name":"Longerlasting Painting Service",
    "wof:placetype":"venue"
},
  "geometry": {"coordinates":[115.84429168699999,-31.8674163818],"type":"Point"}
}