{
  "type": "Feature",
  "properties": {
    "addr:full":"85 Epping Rd North Ryde NSW 2113",
    "addr:housenumber":"85",
    "addr:postcode":"2113",
    "addr:street":"Epping Rd",
    "iso:country":"AU",
    "sg:address":"85 Epping Rd",
    "sg:city":"North Ryde",
    "sg:classifiers":[
        {
            "category":"Social Services",
            "subcategory":"Child Care",
            "type":"Services"
        }
    ],
    "sg:phone":"+61 1800 812 681",
    "sg:postcode":"2113",
    "sg:province":"NSW",
    "sg:tags":[
        "fleet",
        "management"
    ],
    "wof:name":"Fleet Card",
    "wof:placetype":"venue"
},
  "geometry": {"coordinates":[151.12698364299999,-33.7889137268],"type":"Point"}
}