{
  "type": "Feature",
  "properties": {
    "addr:full":"Suite 1, Karingal Arcade, 382 Ruthven St Toowoomba QLD 4350",
    "addr:housenumber":"382",
    "addr:postcode":"4350",
    "addr:street":"Ruthven St",
    "iso:country":"AU",
    "sg:address":"Suite 1, Karingal Arcade, 382 Ruthven St",
    "sg:city":"Toowoomba",
    "sg:classifiers":[
        {
            "category":"Insurance",
            "subcategory":"Hazard Insurance",
            "type":"Services"
        }
    ],
    "sg:phone":"+61 7 4638 4777",
    "sg:postcode":"4350",
    "sg:province":"QLD",
    "sg:tags":[
        "loss",
        "adjuster",
        "assessor"
    ],
    "wof:name":"Freemans Toowoomba",
    "wof:placetype":"venue"
},
  "geometry": {"coordinates":[151.95228599999999,-27.568277],"type":"Point"}
}