{
  "type": "Feature",
  "properties": {
    "addr:full":"26 Landscape Drv Doncaster East VIC 3109",
    "addr:housenumber":"26",
    "addr:postcode":"3109",
    "addr:street":"Landscape Drv",
    "iso:country":"AU",
    "sg:address":"26 Landscape Drv",
    "sg:city":"Doncaster East",
    "sg:classifiers":[
        {
            "category":"Home & Garden",
            "subcategory":"Building Materials",
            "type":"Retail Goods"
        }
    ],
    "sg:phone":"+61 3 9848 3478",
    "sg:postcode":"3109",
    "sg:province":"VIC",
    "sg:tags":[
        "merchant",
        "glass",
        "glazier"
    ],
    "wof:name":"Castle Glass Aust Pty Ltd",
    "wof:placetype":"venue"
},
  "geometry": {"coordinates":[145.16897582999999,-37.7782554626],"type":"Point"}
}