{
  "type": "Feature",
  "properties": {
    "addr:full":"Ocean Beach Rd Woy Woy NSW 2256",
    "addr:postcode":"2256",
    "addr:street":"Ocean Beach Rd",
    "iso:country":"AU",
    "sg:address":"Ocean Beach Rd",
    "sg:city":"Woy Woy",
    "sg:classifiers":[
        {
            "category":"Organizations",
            "subcategory":"Community Association",
            "type":"Services"
        }
    ],
    "sg:phone":"+61 2 4341 6699",
    "sg:postcode":"2256",
    "sg:province":"NSW",
    "sg:tags":[
        "organisation",
        "family",
        "welfare"
    ],
    "wof:name":"Meals On Wheels Woy Woy & District",
    "wof:placetype":"venue"
},
  "geometry": {"coordinates":[151.32095336899999,-33.4916877747],"type":"Point"}
}