{
  "type": "Feature",
  "properties": {
    "addr:full":"51 Kirkpatrick Crs Noranda WA 6062",
    "addr:housenumber":"51",
    "addr:postcode":"6062",
    "addr:street":"Kirkpatrick Crs",
    "iso:country":"AU",
    "sg:address":"51 Kirkpatrick Crs",
    "sg:city":"Noranda",
    "sg:classifiers":[
        {
            "category":"Building & Trades",
            "subcategory":"Plumbing",
            "type":"Services"
        }
    ],
    "sg:phone":"+61 8 9276 1446",
    "sg:postcode":"6062",
    "sg:province":"WA",
    "sg:tags":[
        "consultant"
    ],
    "wof:name":"WA Hydraulic Consultants",
    "wof:placetype":"venue"
},
  "geometry": {"coordinates":[115.895881653,-31.8754997253],"type":"Point"}
}