{
  "type": "Feature",
  "properties": {
    "addr:full":"141 Victoria Rd Bellevue Hill NSW 2023",
    "addr:housenumber":"141",
    "addr:postcode":"2023",
    "addr:street":"Victoria Rd",
    "iso:country":"AU",
    "sg:address":"141 Victoria Rd",
    "sg:city":"Bellevue Hill",
    "sg:classifiers":[
        {
            "category":"Wholesale",
            "subcategory":"Music Publishers",
            "type":"Manufacturing & Wholesale Goods"
        }
    ],
    "sg:phone":"+61 2 9387 8159",
    "sg:postcode":"2023",
    "sg:province":"NSW",
    "sg:tags":[
        "wholesaler",
        "dvd",
        "mfrs",
        "cd"
    ],
    "wof:name":"Atom Records",
    "wof:placetype":"venue"
},
  "geometry": {"coordinates":[151.259689331,-33.8844451904],"type":"Point"}
}