{
  "type": "Feature",
  "properties": {
    "addr:full":"33 Bremen Drv Salisbury South SA 5106",
    "addr:housenumber":"33",
    "addr:postcode":"5106",
    "addr:street":"Bremen Drv",
    "iso:country":"AU",
    "sg:address":"33 Bremen Drv",
    "sg:city":"Salisbury South",
    "sg:classifiers":[
        {
            "category":"Building & Trades",
            "subcategory":"Construction",
            "type":"Services"
        }
    ],
    "sg:phone":"+61 8 8250 6776",
    "sg:postcode":"5106",
    "sg:province":"SA",
    "sg:tags":[
        "welding"
    ],
    "wof:name":"Bremen Welding Specialists Pty Ltd",
    "wof:placetype":"venue"
},
  "geometry": {"coordinates":[138.63742099999999,-34.784149],"type":"Point"}
}