{
  "type": "Feature",
  "properties": {
    "iso:country":"AU",
    "sg:address":"Wollombi Rd",
    "sg:city":"Cessnock",
    "sg:classifiers":[
        {
            "category":"Education",
            "subcategory":"School",
            "type":"Public Place"
        }
    ],
    "sg:phone":"+61 2 4990 1637",
    "sg:postcode":"2325",
    "sg:province":"NSW",
    "sg:tags":[
        "state",
        "-",
        "nsw"
    ],
    "wof:name":"West Cessnock Public School",
    "wof:placetype":"venue"
},
  "geometry": {"coordinates":[151.35494995100001,-32.8325805664],"type":"Point"}
}