{
  "type": "Feature",
  "properties": {
    "addr:full":"12 Linga Long Rd Yarramalong NSW 2259",
    "addr:housenumber":"12",
    "addr:postcode":"2259",
    "addr:street":"Linga Long Rd",
    "iso:country":"AU",
    "sg:address":"12 Linga Long Rd",
    "sg:city":"Yarramalong",
    "sg:classifiers":[
        {
            "category":"Autos & Motor Vehicles",
            "subcategory":"Auto Supplies",
            "type":"Retail Goods"
        }
    ],
    "sg:phone":"+61 414 844 736",
    "sg:postcode":"2259",
    "sg:province":"NSW",
    "sg:tags":[
        "part",
        "cycles",
        "accessory"
    ],
    "wof:name":"Bub's Motorcycles",
    "wof:placetype":"venue"
},
  "geometry": {"coordinates":[151.27967834500001,-33.2242012024],"type":"Point"}
}