{
  "type": "Feature",
  "properties": {
    "iso:country":"AU",
    "sg:address":"126 Kullaroo Rd",
    "sg:city":"Summerland Point",
    "sg:classifiers":[
        {
            "category":"Home & Garden",
            "subcategory":"Building Materials",
            "type":"Retail Goods"
        }
    ],
    "sg:phone":"+61 1800 727 872",
    "sg:postcode":"2259",
    "sg:province":"NSW",
    "sg:tags":[
        "merchant",
        "glass",
        "glazier"
    ],
    "sg:website":"http://www.optimumtinting.com.au",
    "wof:name":"Optimum Tinting Group",
    "wof:placetype":"venue"
},
  "geometry": {"coordinates":[151.55891418499999,-33.1333808899],"type":"Point"}
}