{
  "type": "Feature",
  "properties": {
    "addr:full":"293 Great Western Hwy Lawson NSW 2783",
    "addr:housenumber":"293",
    "addr:postcode":"2783",
    "addr:street":"Great Western Hwy",
    "iso:country":"AU",
    "sg:address":"293 Great Western Hwy",
    "sg:city":"Lawson",
    "sg:classifiers":[
        {
            "category":"Personal",
            "subcategory":"Beauty Salon",
            "type":"Services"
        }
    ],
    "sg:phone":"+61 2 4759 2248",
    "sg:postcode":"2783",
    "sg:province":"NSW",
    "sg:tags":[
        "hairdresser"
    ],
    "wof:name":"Tailor Made Hair",
    "wof:placetype":"venue"
},
  "geometry": {"coordinates":[150.429229736,-33.7198677063],"type":"Point"}
}