{
  "type": "Feature",
  "properties": {
    "iso:country":"AU",
    "sg:address":"Crosby La",
    "sg:city":"Mansfield",
    "sg:classifiers":[
        {
            "category":"Retail",
            "subcategory":"Storage",
            "type":"Services"
        }
    ],
    "sg:phone":"+61 428 316 649",
    "sg:postcode":"3722",
    "sg:province":"VIC",
    "wof:name":"The Big Green Shed",
    "wof:placetype":"venue"
},
  "geometry": {"coordinates":[146.10159301799999,-37.0784225464],"type":"Point"}
}