{
  "type": "Feature",
  "properties": {
    "addr:full":"Level 5/ 26 College St Sydney NSW 2000",
    "addr:housenumber":"/ 26",
    "addr:postcode":"2000",
    "addr:street":"College St",
    "iso:country":"AU",
    "sg:address":"Level 5/ 26 College St",
    "sg:city":"Sydney",
    "sg:classifiers":[
        {
            "category":"Building & Trades",
            "subcategory":"Construction",
            "type":"Services"
        }
    ],
    "sg:phone":"+61 2 9332 9444",
    "sg:postcode":"2000",
    "sg:province":"NSW",
    "sg:tags":[
        "contractor"
    ],
    "wof:name":"Thiess Pty Ltd",
    "wof:placetype":"venue"
},
  "geometry": {"coordinates":[151.21307373100001,-33.8704872131],"type":"Point"}
}