{
  "type": "Feature",
  "properties": {
    "iso:country":"AU",
    "sg:address":"39 Woondooma St",
    "sg:city":"Bundaberg",
    "sg:classifiers":[
        {
            "category":"Social Services",
            "subcategory":"Child Care",
            "type":"Services"
        }
    ],
    "sg:phone":"+61 7 4152 4436",
    "sg:postcode":"4670",
    "sg:province":"QLD",
    "wof:name":"YMCA",
    "wof:placetype":"venue"
},
  "geometry": {"coordinates":[152.35093689000001,-24.8679161072],"type":"Point"}
}