{
  "type": "Feature",
  "properties": {
    "iso:country":"AU",
    "sg:address":"104 Canterbury Rd",
    "sg:city":"Canterbury",
    "sg:classifiers":[
        {
            "category":"Retail",
            "subcategory":"Auto Repair",
            "type":"Services"
        }
    ],
    "sg:phone":"+61 2 9558 2121",
    "sg:postcode":"2193",
    "sg:province":"NSW",
    "sg:tags":[
        "electrical"
    ],
    "wof:name":"Canterbury Auto Electrical & Airconditioning Services",
    "wof:placetype":"venue"
},
  "geometry": {"coordinates":[151.12501499999999,-33.908398],"type":"Point"}
}