{
  "type": "Feature",
  "properties": {
    "addr:full":"306 Victoria Ave Chatswood NSW 2057",
    "addr:housenumber":"306",
    "addr:postcode":"2057",
    "addr:street":"Victoria Ave",
    "iso:country":"AU",
    "sg:address":"306 Victoria Ave",
    "sg:city":"Chatswood",
    "sg:classifiers":[
        {
            "category":"Education",
            "subcategory":"Special Training",
            "type":"Public Place"
        }
    ],
    "sg:phone":"+61 2 9411 4144",
    "sg:postcode":"2057",
    "sg:province":"NSW",
    "sg:tags":[
        "tuition-educational"
    ],
    "wof:name":"I Can Read Chatswood",
    "wof:placetype":"venue"
},
  "geometry": {"coordinates":[151.18583699999999,-33.795589],"type":"Point"}
}