{
  "type": "Feature",
  "properties": {
    "addr:full":"25 Trousdell Crt Toowoomba QLD 4350",
    "addr:housenumber":"25",
    "addr:postcode":"4350",
    "addr:street":"Trousdell Crt",
    "iso:country":"AU",
    "sg:address":"25 Trousdell Crt",
    "sg:city":"Toowoomba",
    "sg:classifiers":[
        {
            "category":"Retail",
            "subcategory":"Repair Shop",
            "type":"Services"
        }
    ],
    "sg:phone":"+61 7 4634 6668",
    "sg:postcode":"4350",
    "sg:province":"QLD",
    "sg:tags":[
        "upholsterer"
    ],
    "wof:name":"AAA Canvas & Upholstery",
    "wof:placetype":"venue"
},
  "geometry": {"coordinates":[151.93705700000001,-27.540499],"type":"Point"}
}