{
  "type": "Feature",
  "properties": {
    "addr:full":"389 Clarke St Northcote VIC 3070",
    "addr:housenumber":"389",
    "addr:postcode":"3070",
    "addr:street":"Clarke St",
    "iso:country":"AU",
    "sg:address":"389 Clarke St",
    "sg:city":"Northcote",
    "sg:classifiers":[
        {
            "category":"Taxi",
            "type":"Transportation"
        }
    ],
    "sg:phone":"+61 3 9481 6222",
    "sg:postcode":"3070",
    "sg:province":"VIC",
    "sg:tags":[
        "cab"
    ],
    "wof:name":"Doaba Motors Pty Ltd",
    "wof:placetype":"venue"
},
  "geometry": {"coordinates":[145.010132,-37.777931],"type":"Point"}
}