{
  "type": "Feature",
  "properties": {
    "addr:full":"Moorak Hall Rd Moorak SA 5291",
    "addr:postcode":"5291",
    "addr:street":"Hall Rd",
    "iso:country":"AU",
    "sg:address":"Moorak Hall Rd",
    "sg:city":"Moorak",
    "sg:classifiers":[
        {
            "category":"Farming",
            "subcategory":"Farm",
            "type":"Manufacturing & Wholesale Goods"
        }
    ],
    "sg:phone":"+61 8 8725 5949",
    "sg:postcode":"5291",
    "sg:province":"SA",
    "sg:tags":[
        "farmer"
    ],
    "wof:name":"Di Rito G",
    "wof:placetype":"venue"
},
  "geometry": {"coordinates":[140.73764,-37.853687],"type":"Point"}
}