{
  "type": "Feature",
  "properties": {
    "addr:full":"4 Harlem Pl Mandurah WA 6210",
    "addr:housenumber":"4",
    "addr:postcode":"6210",
    "addr:street":"Harlem Pl",
    "iso:country":"AU",
    "sg:address":"4 Harlem Pl",
    "sg:city":"Mandurah",
    "sg:classifiers":[
        {
            "category":"Taxi",
            "type":"Transportation"
        }
    ],
    "sg:phone":"+61 13 10 08",
    "sg:postcode":"6210",
    "sg:province":"WA",
    "sg:tags":[
        "cab"
    ],
    "wof:name":"Mandurah Taxi Service",
    "wof:placetype":"venue"
},
  "geometry": {"coordinates":[115.750557,-32.517525],"type":"Point"}
}