{
  "type": "Feature",
  "properties": {
    "addr:full":"82 Belmore St Ryde NSW 2112",
    "addr:housenumber":"82",
    "addr:postcode":"2112",
    "addr:street":"Belmore St",
    "iso:country":"AU",
    "sg:address":"82 Belmore St",
    "sg:city":"Ryde",
    "sg:classifiers":[
        {
            "category":"Retail",
            "subcategory":"Auto Repair",
            "type":"Services"
        }
    ],
    "sg:phone":"+61 2 9809 2110",
    "sg:postcode":"2112",
    "sg:province":"NSW",
    "sg:tags":[
        "repairer",
        "motor",
        "engineer"
    ],
    "wof:name":"B Middleton",
    "wof:placetype":"venue"
},
  "geometry": {"coordinates":[151.09645080600001,-33.8199157715],"type":"Point"}
}