{
  "type": "Feature",
  "properties": {
    "iso:country":"AU",
    "sg:address":"25 Duckworth St",
    "sg:city":"Garbutt",
    "sg:classifiers":[
        {
            "category":"Retail",
            "subcategory":"Auto Repair",
            "type":"Services"
        }
    ],
    "sg:phone":"+61 7 4725 5885",
    "sg:postcode":"4814",
    "sg:province":"QLD",
    "sg:tags":[
        "repairer",
        "motor",
        "engineer"
    ],
    "wof:name":"North Coast Kustoms",
    "wof:placetype":"venue"
},
  "geometry": {"coordinates":[146.76033,-19.265766],"type":"Point"}
}