{
  "type": "Feature",
  "properties": {
    "iso:country":"AU",
    "sg:address":"5 Buckland St",
    "sg:city":"Mitchell",
    "sg:classifiers":[
        {
            "category":"Manufacturing",
            "subcategory":"Glass & Minerals",
            "type":"Manufacturing & Wholesale Goods"
        }
    ],
    "sg:phone":"+61 2 6253 9339",
    "sg:postcode":"2911",
    "sg:province":"ACT",
    "sg:tags":[
        "merchant",
        "granite",
        "marble"
    ],
    "wof:name":"Roccro",
    "wof:placetype":"venue"
},
  "geometry": {"coordinates":[149.140701294,-35.2175102234],"type":"Point"}
}