{
  "type": "Feature",
  "properties": {
    "addr:full":"113 Oberon St Oberon NSW 2787",
    "addr:housenumber":"113",
    "addr:postcode":"2787",
    "addr:street":"Oberon St",
    "iso:country":"AU",
    "sg:address":"113 Oberon St",
    "sg:city":"Oberon",
    "sg:classifiers":[
        {
            "category":"Travel",
            "subcategory":"Hotels & Motels",
            "type":"Entertainment"
        }
    ],
    "sg:phone":"+61 2 6336 1011",
    "sg:postcode":"2787",
    "sg:province":"NSW",
    "sg:tags":[
        "accommodation"
    ],
    "wof:name":"Royal Hotel",
    "wof:placetype":"venue"
},
  "geometry": {"coordinates":[149.85882568400001,-33.7041740417],"type":"Point"}
}