{
  "type": "Feature",
  "properties": {
    "iso:country":"AU",
    "sg:address":"29 Moncrief Rd",
    "sg:city":"Cannon Hill",
    "sg:classifiers":[
        {
            "category":"Professional",
            "subcategory":"Detective & Security Services",
            "type":"Services"
        }
    ],
    "sg:phone":"+61 7 3216 6424",
    "sg:postcode":"4170",
    "sg:province":"QLD",
    "sg:tags":[
        "guard",
        "patrol"
    ],
    "wof:name":"D.N.A. Security Services",
    "wof:placetype":"venue"
},
  "geometry": {"coordinates":[153.085174561,-27.4628562927],"type":"Point"}
}