{
  "type": "Feature",
  "properties": {
    "addr:full":"68 Glanmire Rd Baulkham Hills NSW 2153",
    "addr:housenumber":"68",
    "addr:postcode":"2153",
    "addr:street":"Glanmire Rd",
    "iso:country":"AU",
    "sg:address":"68 Glanmire Rd",
    "sg:city":"Baulkham Hills",
    "sg:classifiers":[
        {
            "category":"Home & Garden",
            "subcategory":"Building Materials",
            "type":"Retail Goods"
        }
    ],
    "sg:phone":"+61 2 9624 6015",
    "sg:postcode":"2153",
    "sg:province":"NSW",
    "sg:tags":[
        "lawn",
        "cutting",
        "maintenance"
    ],
    "wof:name":"Gill T J",
    "wof:placetype":"venue"
},
  "geometry": {"coordinates":[150.976806641,-33.748714447],"type":"Point"}
}