{
  "type": "Feature",
  "properties": {
    "iso:country":"AU",
    "sg:address":"Bangor Centre Suite 5 Lower Level Crn Menai & Yala Rd",
    "sg:city":"Bangor",
    "sg:classifiers":[
        {
            "category":"Professional",
            "subcategory":"Accounting & Tax Preparation",
            "type":"Services"
        }
    ],
    "sg:phone":"+61 2 9543 4336",
    "sg:postcode":"2234",
    "sg:province":"NSW",
    "sg:tags":[
        "consultant",
        "taxation"
    ],
    "wof:name":"Jones Steven",
    "wof:placetype":"venue"
},
  "geometry": {"coordinates":[151.029098511,-34.0186538696],"type":"Point"}
}