{
  "type": "Feature",
  "properties": {
    "addr:full":"547 Pennant Hills Rd West Pennant Hills NSW 2125",
    "addr:housenumber":"547",
    "addr:postcode":"2125",
    "addr:street":"Pennant Hills Rd",
    "iso:country":"AU",
    "sg:address":"547 Pennant Hills Rd",
    "sg:city":"West Pennant Hills",
    "sg:classifiers":[
        {
            "category":"Utilities",
            "subcategory":"Electric",
            "type":"Services"
        }
    ],
    "sg:phone":"+61 2 9980 8317",
    "sg:postcode":"2125",
    "sg:province":"NSW",
    "sg:tags":[
        "electrical",
        "contractor"
    ],
    "wof:name":"Adept Integrations",
    "wof:placetype":"venue"
},
  "geometry": {"coordinates":[151.05020141599999,-33.7475090027],"type":"Point"}
}