{
  "type": "Feature",
  "properties": {
    "iso:country":"AU",
    "sg:address":"39 Tinarra Crs",
    "sg:city":"Kenmore Hills",
    "sg:classifiers":[
        {
            "category":"Professional",
            "subcategory":"Computer Services",
            "type":"Services"
        }
    ],
    "sg:phone":"+61 7 3378 5499",
    "sg:postcode":"4069",
    "sg:province":"QLD",
    "sg:tags":[
        "package",
        "software"
    ],
    "wof:name":"Concept User Group",
    "wof:placetype":"venue"
},
  "geometry": {"coordinates":[152.926055908,-27.4949703217],"type":"Point"}
}