{
  "type": "Feature",
  "properties": {
    "iso:country":"AU",
    "sg:address":"25 Childs Drv",
    "sg:city":"Burpengary",
    "sg:classifiers":[
        {
            "category":"Health Services",
            "subcategory":"Health Practitioner",
            "type":"Services"
        }
    ],
    "sg:phone":"+61 7 3888 4021",
    "sg:postcode":"4505",
    "sg:province":"QLD",
    "sg:tags":[
        "acupuncture"
    ],
    "wof:name":"Lennon Cheran",
    "wof:placetype":"venue"
},
  "geometry": {"coordinates":[152.984741211,-27.1555213928],"type":"Point"}
}