{
  "type": "Feature",
  "properties": {
    "addr:full":"Belair National Park Upper Sturt Rd Belair SA 5052",
    "addr:postcode":"5052",
    "addr:street":"Upper Sturt Rd",
    "iso:country":"AU",
    "sg:address":"Belair National Park Upper Sturt Rd",
    "sg:city":"Belair",
    "sg:classifiers":[
        {
            "category":"Retail",
            "subcategory":"Event Space",
            "type":"Services"
        }
    ],
    "sg:phone":"+61 8 8278 5477",
    "sg:postcode":"5052",
    "sg:province":"SA",
    "sg:tags":[
        "venue",
        "reception",
        "wedding"
    ],
    "wof:name":"Old Government House",
    "wof:placetype":"venue"
},
  "geometry": {"coordinates":[138.632599,-34.999878],"type":"Point"}
}