{
  "type": "Feature",
  "properties": {
    "addr:full":"154 Church St Mudgee NSW 2850",
    "addr:housenumber":"154",
    "addr:postcode":"2850",
    "addr:street":"Church St",
    "iso:country":"AU",
    "sg:address":"154 Church St",
    "sg:city":"Mudgee",
    "sg:classifiers":[
        {
            "category":"Organizations",
            "subcategory":"Community Association",
            "type":"Services"
        }
    ],
    "sg:phone":"+61 2 6372 2699",
    "sg:postcode":"2850",
    "sg:province":"NSW",
    "sg:tags":[
        "organisation",
        "family",
        "welfare"
    ],
    "wof:name":"Mudgee Family Support Service",
    "wof:placetype":"venue"
},
  "geometry": {"coordinates":[149.585037231,-32.6081542969],"type":"Point"}
}