{
  "type": "Feature",
  "properties": {
    "addr:full":"2 Meath Ave Athelstone SA 5076",
    "addr:housenumber":"2",
    "addr:postcode":"5076",
    "addr:street":"Meath Ave",
    "iso:country":"AU",
    "sg:address":"2 Meath Ave",
    "sg:city":"Athelstone",
    "sg:classifiers":[
        {
            "category":"Utilities",
            "subcategory":"Electric",
            "type":"Services"
        }
    ],
    "sg:phone":"+61 411 196 764",
    "sg:postcode":"5076",
    "sg:province":"SA",
    "sg:tags":[
        "electrical",
        "contractor"
    ],
    "wof:name":"Cardone Electrical Contractors",
    "wof:placetype":"venue"
},
  "geometry": {"coordinates":[138.70463562,-34.8656387329],"type":"Point"}
}