{
  "type": "Feature",
  "properties": {
    "addr:full":"27 Murrumbeena Rd Murrumbeena VIC 3163",
    "addr:housenumber":"27",
    "addr:postcode":"3163",
    "addr:street":"Murrumbeena Rd",
    "iso:country":"AU",
    "sg:address":"27 Murrumbeena Rd",
    "sg:city":"Murrumbeena",
    "sg:classifiers":[
        {
            "category":"Building & Trades",
            "subcategory":"Plumbing",
            "type":"Services"
        }
    ],
    "sg:phone":"+61 3 9564 7275",
    "sg:postcode":"3163",
    "sg:province":"VIC",
    "sg:tags":[
        "plumber",
        "gasfitters"
    ],
    "wof:name":"K.G.K. Plumbing",
    "wof:placetype":"venue"
},
  "geometry": {"coordinates":[145.06690979000001,-37.8868026733],"type":"Point"}
}