{
  "type": "Feature",
  "properties": {
    "iso:country":"AU",
    "sg:address":"PO Box 120",
    "sg:city":"Rathdowney",
    "sg:classifiers":[
        {
            "category":"Building & Trades",
            "subcategory":"Landscaping Services",
            "type":"Services"
        }
    ],
    "sg:phone":"+61 7 5544 3285",
    "sg:postcode":"4287",
    "sg:province":"QLD",
    "sg:tags":[
        "architect",
        "landscape"
    ],
    "wof:name":"Seale Jennifer",
    "wof:placetype":"venue"
},
  "geometry": {"coordinates":[152.794693,-28.20701],"type":"Point"}
}