{
  "type": "Feature",
  "properties": {
    "addr:full":"61 Devereux Rd Glenside SA 5065",
    "addr:housenumber":"61",
    "addr:postcode":"5065",
    "addr:street":"Devereux Rd",
    "iso:country":"AU",
    "sg:address":"61 Devereux Rd",
    "sg:city":"Glenside",
    "sg:classifiers":[
        {
            "category":"Health Services",
            "subcategory":"Dentist",
            "type":"Services"
        }
    ],
    "sg:phone":"+61 8 8379 7399",
    "sg:postcode":"5065",
    "sg:province":"SA",
    "wof:name":"Bhela Satpal Singh",
    "wof:placetype":"venue"
},
  "geometry": {"coordinates":[138.65179443400001,-34.9457015991],"type":"Point"}
}