{
  "type": "Feature",
  "properties": {
    "addr:full":"27 Melissa St Duncraig WA 6023",
    "addr:housenumber":"27",
    "addr:postcode":"6023",
    "addr:street":"Melissa St",
    "iso:country":"AU",
    "sg:address":"27 Melissa St",
    "sg:city":"Duncraig",
    "sg:classifiers":[
        {
            "category":"Professional",
            "subcategory":"Detective & Security Services",
            "type":"Services"
        }
    ],
    "sg:phone":"+61 8 9483 6663",
    "sg:postcode":"6023",
    "sg:province":"WA",
    "sg:tags":[
        "domestic",
        "alarm",
        "commercial",
        "burglar"
    ],
    "wof:name":"A1 Secure Solutions",
    "wof:placetype":"venue"
},
  "geometry": {"coordinates":[115.76252746599999,-31.8179244995],"type":"Point"}
}