{
  "type": "Feature",
  "properties": {
    "addr:full":"Suite 8 370 Church St Parramatta NSW 2150",
    "addr:housenumber":"370",
    "addr:postcode":"2150",
    "addr:street":"Church St",
    "iso:country":"AU",
    "sg:address":"Suite 8 370 Church St",
    "sg:city":"Parramatta",
    "sg:classifiers":[
        {
            "category":"Insurance",
            "subcategory":"Insurance Agent",
            "type":"Services"
        }
    ],
    "sg:phone":"+61 2 9890 4788",
    "sg:postcode":"2150",
    "sg:province":"NSW",
    "sg:tags":[
        "broker"
    ],
    "wof:name":"Omega Insurance Brokers Pty Ltd",
    "wof:placetype":"venue"
},
  "geometry": {"coordinates":[151.005401611,-33.8091583252],"type":"Point"}
}