{
  "type": "Feature",
  "properties": {
    "addr:full":"PO Box 2179 Burwood North NSW 2134",
    "addr:postcode":"2134",
    "iso:country":"AU",
    "sg:address":"PO Box 2179",
    "sg:city":"Burwood North",
    "sg:classifiers":[
        {
            "category":"Food & Beverages",
            "subcategory":"Fruits & Vegetables",
            "type":"Retail Goods"
        }
    ],
    "sg:phone":"+61 2 9980 7065",
    "sg:postcode":"2134",
    "sg:province":"NSW",
    "sg:tags":[
        "consultant",
        "catering"
    ],
    "wof:name":"Vickis Events",
    "wof:placetype":"venue"
},
  "geometry": {"coordinates":[151.10392761200001,-33.8761482239],"type":"Point"}
}