{
  "type": "Feature",
  "properties": {
    "addr:full":"71 Balmain St Richmond VIC 3121",
    "addr:housenumber":"71",
    "addr:postcode":"3121",
    "addr:street":"Balmain St",
    "iso:country":"AU",
    "sg:address":"71 Balmain St",
    "sg:city":"Richmond",
    "sg:classifiers":[
        {
            "category":"Wholesale",
            "subcategory":"Non-durable Goods",
            "type":"Manufacturing & Wholesale Goods"
        }
    ],
    "sg:phone":"+61 3 9421 1400",
    "sg:postcode":"3121",
    "sg:province":"VIC",
    "sg:tags":[
        "wholesaler",
        "mfrs",
        "cosmetic"
    ],
    "wof:name":"She Australia Enterprises Pty Ltd",
    "wof:placetype":"venue"
},
  "geometry": {"coordinates":[144.99418640100001,-37.8300552368],"type":"Point"}
}