{
  "type": "Feature",
  "properties": {
    "addr:full":"74 Palm Beach Ave Palm Beach QLD 4221",
    "addr:housenumber":"74",
    "addr:postcode":"4221",
    "addr:street":"Palm Beach Ave",
    "iso:country":"AU",
    "sg:address":"74 Palm Beach Ave",
    "sg:city":"Palm Beach",
    "sg:classifiers":[
        {
            "category":"Manufacturing",
            "subcategory":"Motor Vehicles & Parts",
            "type":"Manufacturing & Wholesale Goods"
        }
    ],
    "sg:phone":"+61 7 5598 3868",
    "sg:postcode":"4221",
    "sg:province":"QLD",
    "sg:tags":[
        "wholesaler",
        "cycle",
        "mfrs",
        "accessory"
    ],
    "wof:name":"American Spares & Repairs",
    "wof:placetype":"venue"
},
  "geometry": {"coordinates":[153.468383789,-28.1229381561],"type":"Point"}
}