{
  "type": "Feature",
  "properties": {
    "addr:full":"46 Barrington Ave Kew VIC 3101",
    "addr:housenumber":"46",
    "addr:postcode":"3101",
    "addr:street":"Barrington Ave",
    "iso:country":"AU",
    "sg:address":"46 Barrington Ave",
    "sg:city":"Kew",
    "sg:classifiers":[
        {
            "category":"Professional",
            "subcategory":"Engineering",
            "type":"Services"
        }
    ],
    "sg:phone":"+61 3 9817 1334",
    "sg:postcode":"3101",
    "sg:province":"VIC",
    "sg:tags":[
        "consulting",
        "engineer"
    ],
    "wof:name":"Strucomp",
    "wof:placetype":"venue"
},
  "geometry": {"coordinates":[145.04460144000001,-37.8050308228],"type":"Point"}
}