{
  "type": "Feature",
  "properties": {
    "addr:full":"99 Goynes Rd Epsom VIC 3551",
    "addr:housenumber":"99",
    "addr:postcode":"3551",
    "addr:street":"Goynes Rd",
    "iso:country":"AU",
    "sg:address":"99 Goynes Rd",
    "sg:city":"Epsom",
    "sg:classifiers":[
        {
            "category":"Government",
            "subcategory":"Court House",
            "type":"Public Place"
        }
    ],
    "sg:phone":"+61 3 5448 4538",
    "sg:postcode":"3551",
    "sg:province":"VIC",
    "sg:tags":[
        "personal",
        "marriage",
        "family",
        "counselling"
    ],
    "wof:name":"Ansell Rosemary",
    "wof:placetype":"venue"
},
  "geometry": {"coordinates":[144.308395386,-36.7103538513],"type":"Point"}
}