{
  "type": "Feature",
  "properties": {
    "iso:country":"AU",
    "sg:address":"1521 High St",
    "sg:city":"Glen Iris",
    "sg:classifiers":[
        {
            "category":"Shopping",
            "subcategory":"Bridal",
            "type":"Retail Goods"
        }
    ],
    "sg:phone":"+61 3 9885 0111",
    "sg:postcode":"3146",
    "sg:province":"VIC",
    "sg:tags":[
        "hire",
        "wear"
    ],
    "wof:name":"Lorena Maree Dressmaking Salon",
    "wof:placetype":"venue"
},
  "geometry": {"coordinates":[145.05752563499999,-37.8599128723],"type":"Point"}
}