{
  "type": "Feature",
  "properties": {
    "addr:full":"144 Jonson St Byron Bay NSW 2481",
    "addr:housenumber":"144",
    "addr:postcode":"2481",
    "addr:street":"Jonson St",
    "iso:country":"AU",
    "sg:address":"144 Jonson St",
    "sg:city":"Byron Bay",
    "sg:classifiers":[
        {
            "category":"Arena",
            "subcategory":"Sports Club",
            "type":"Entertainment"
        }
    ],
    "sg:phone":"+61 2 6685 8181",
    "sg:postcode":"2481",
    "sg:province":"NSW",
    "sg:tags":[
        "defence",
        "supply",
        "self",
        "instruction",
        "martial art"
    ],
    "wof:name":"Vision Studios",
    "wof:placetype":"venue"
},
  "geometry": {"coordinates":[153.61293029800001,-28.649023056],"type":"Point"}
}