{
  "type": "Feature",
  "properties": {
    "addr:full":"Unit 4/ 43-53 Bridge Rd Stanmore NSW 2048",
    "addr:housenumber":"/ 43-53",
    "addr:postcode":"2048",
    "addr:street":"Bridge Rd",
    "iso:country":"AU",
    "sg:address":"Unit 4/ 43-53 Bridge Rd",
    "sg:city":"Stanmore",
    "sg:classifiers":[
        {
            "category":"Professional",
            "subcategory":"Art Services",
            "type":"Services"
        }
    ],
    "sg:phone":"+61 2 9516 1144",
    "sg:postcode":"2048",
    "sg:province":"NSW",
    "sg:tags":[
        "graphic",
        "designer"
    ],
    "wof:name":"Gina Selleck Design",
    "wof:placetype":"venue"
},
  "geometry": {"coordinates":[151.17077599999999,-33.890785],"type":"Point"}
}