{
  "type": "Feature",
  "properties": {
    "iso:country":"AU",
    "sg:address":"PO Box 751",
    "sg:city":"Bankstown",
    "sg:classifiers":[
        {
            "category":"Wholesale",
            "subcategory":"Home Furnishings",
            "type":"Manufacturing & Wholesale Goods"
        }
    ],
    "sg:phone":"+61 419 259 510",
    "sg:postcode":"1885",
    "sg:province":"NSW",
    "sg:tags":[
        "terrazzo"
    ],
    "wof:name":"Byzantium Grinding & Polishing, Concrete & Stone",
    "wof:placetype":"venue"
},
  "geometry": {"coordinates":[151.034912109,-33.9195404053],"type":"Point"}
}