{
  "type": "Feature",
  "properties": {
    "addr:full":"Ste 5A/19- 21 Broken Bay Rd Ettalong Beach NSW 2257",
    "addr:housenumber":"21",
    "addr:postcode":"2257",
    "addr:street":"Broken Bay Rd",
    "iso:country":"AU",
    "sg:address":"Ste 5A/19- 21 Broken Bay Rd",
    "sg:city":"Ettalong Beach",
    "sg:classifiers":[
        {
            "category":"Real Estate",
            "subcategory":"Real Estate Agent",
            "type":"Services"
        }
    ],
    "sg:phone":"+61 2 4344 7877",
    "sg:postcode":"2257",
    "sg:province":"NSW",
    "wof:name":"Your Realty Real Estate Pty Ltd",
    "wof:placetype":"venue"
},
  "geometry": {"coordinates":[151.334259033,-33.5139083862],"type":"Point"}
}