{
  "type": "Feature",
  "properties": {
    "addr:full":"13 Grantham St Burwood NSW 2134",
    "addr:housenumber":"13",
    "addr:postcode":"2134",
    "addr:street":"Grantham St",
    "iso:country":"AU",
    "sg:address":"13 Grantham St",
    "sg:city":"Burwood",
    "sg:classifiers":[
        {
            "category":"Government",
            "subcategory":"Court House",
            "type":"Public Place"
        }
    ],
    "sg:phone":"+61 1300 555 578",
    "sg:postcode":"2134",
    "sg:province":"NSW",
    "sg:tags":[
        "personal",
        "marriage",
        "family",
        "counselling"
    ],
    "wof:name":"Dona Maria Pre & Post Natal Depression Support Network",
    "wof:placetype":"venue"
},
  "geometry": {"coordinates":[151.10081481899999,-33.868938446],"type":"Point"}
}