{
  "type": "Feature",
  "properties": {
    "iso:country":"AU",
    "sg:address":"PO Box 1790",
    "sg:city":"Emerald",
    "sg:classifiers":[
        {
            "category":"Professional",
            "subcategory":"Employment Agencies",
            "type":"Services"
        }
    ],
    "sg:phone":"+61 7 4982 2300",
    "sg:postcode":"4720",
    "sg:province":"QLD",
    "sg:tags":[
        "hire",
        "labour",
        "contractor"
    ],
    "wof:name":"Queensland Mining Employment Services",
    "wof:placetype":"venue"
},
  "geometry": {"coordinates":[148.158157,-23.52487],"type":"Point"}
}