{
  "type": "Feature",
  "properties": {
    "iso:country":"AU",
    "sg:address":"20 Albion St",
    "sg:city":"Katanning",
    "sg:classifiers":[
        {
            "category":"Wholesale",
            "subcategory":"Machinery & Supplies",
            "type":"Manufacturing & Wholesale Goods"
        }
    ],
    "sg:phone":"+61 8 9821 2349",
    "sg:postcode":"6317",
    "sg:province":"WA",
    "sg:tags":[
        "agricultural"
    ],
    "wof:name":"Katanning Exhaust Centre",
    "wof:placetype":"venue"
},
  "geometry": {"coordinates":[117.555610657,-33.6925048828],"type":"Point"}
}