{
  "type": "Feature",
  "properties": {
    "iso:country":"AU",
    "sg:address":"14a Denmead Ave",
    "sg:city":"Campbelltown",
    "sg:classifiers":[
        {
            "category":"Building & Trades",
            "subcategory":"Construction",
            "type":"Services"
        }
    ],
    "sg:phone":"+61 8 8365 7225",
    "sg:postcode":"5074",
    "sg:province":"SA",
    "sg:tags":[
        "contractor"
    ],
    "wof:name":"Clairville Constructions Pty Ltd",
    "wof:placetype":"venue"
},
  "geometry": {"coordinates":[138.66604614299999,-34.8786048889],"type":"Point"}
}