{
  "type": "Feature",
  "properties": {
    "iso:country":"AU",
    "sg:address":"23a Wells Pde",
    "sg:city":"Blackmans Bay",
    "sg:classifiers":[
        {
            "category":"Travel",
            "subcategory":"Hostel",
            "type":"Entertainment"
        }
    ],
    "sg:phone":"+61 3 6229 1397",
    "sg:postcode":"7052",
    "sg:province":"TAS",
    "sg:tags":[
        "home"
    ],
    "wof:name":"Hawthorn Village Aged Care Home",
    "wof:placetype":"venue"
},
  "geometry": {"coordinates":[147.32431,-42.999805],"type":"Point"}
}