{
  "type": "Feature",
  "properties": {
    "iso:country":"AU",
    "sg:address":"Doug Nichols St",
    "sg:city":"Tongala",
    "sg:classifiers":[
        {
            "category":"Sports & Exercise",
            "subcategory":"Sports Center",
            "type":"Entertainment"
        }
    ],
    "sg:phone":"+61 3 5859 0835",
    "sg:postcode":"3621",
    "sg:province":"VIC",
    "sg:tags":[
        "ground"
    ],
    "wof:name":"Tongala Leisure Centre",
    "wof:placetype":"venue"
},
  "geometry": {"coordinates":[144.964477539,-36.1990013123],"type":"Point"}
}