{
  "type": "Feature",
  "properties": {
    "iso:country":"AU",
    "sg:address":"1 Warrick St",
    "sg:city":"Ascot Vale",
    "sg:classifiers":[
        {
            "category":"Retail",
            "subcategory":"Auto Repair",
            "type":"Services"
        }
    ],
    "sg:phone":"+61 3 9370 9734",
    "sg:postcode":"3032",
    "sg:province":"VIC",
    "sg:tags":[
        "repairer",
        "motor",
        "engineer"
    ],
    "wof:name":"Waratah Motors",
    "wof:placetype":"venue"
},
  "geometry": {"coordinates":[144.928619,-37.775463],"type":"Point"}
}