{
  "type": "Feature",
  "properties": {
    "addr:full":"Office 4/ 16 Minnie St Cairns QLD 4870",
    "addr:housenumber":"16",
    "addr:postcode":"4870",
    "addr:street":"Minnie St",
    "iso:country":"AU",
    "sg:address":"Office 4/ 16 Minnie St",
    "sg:city":"Cairns",
    "sg:classifiers":[
        {
            "category":"Real Estate",
            "subcategory":"Real Estate Services",
            "type":"Services"
        }
    ],
    "sg:phone":"+61 7 4051 1900",
    "sg:postcode":"4870",
    "sg:province":"QLD",
    "sg:tags":[
        "valuer"
    ],
    "wof:name":"Herriots Pty Ltd",
    "wof:placetype":"venue"
},
  "geometry": {"coordinates":[145.76881408700001,-16.9189453125],"type":"Point"}
}