{
  "type": "Feature",
  "properties": {
    "addr:full":"73 Industrial Drv Braeside VIC 3195",
    "addr:housenumber":"73",
    "addr:postcode":"3195",
    "addr:street":"Industrial Drv",
    "iso:country":"AU",
    "sg:address":"73 Industrial Drv",
    "sg:city":"Braeside",
    "sg:classifiers":[
        {
            "category":"Retail",
            "subcategory":"Car Wash",
            "type":"Services"
        }
    ],
    "sg:phone":"+61 3 9587 7888",
    "sg:postcode":"3195",
    "sg:province":"VIC",
    "sg:tags":[
        "wholesaler",
        "apron",
        "mfrs"
    ],
    "wof:name":"Screenline Pty Ltd",
    "wof:placetype":"venue"
},
  "geometry": {"coordinates":[145.112823486,-38.0076026917],"type":"Point"}
}