{
  "type": "Feature",
  "properties": {
    "iso:country":"AU",
    "sg:address":"Unit 4/ 76 Sunnyholt Rd",
    "sg:city":"Blacktown",
    "sg:classifiers":[
        {
            "category":"Building & Trades",
            "subcategory":"Construction",
            "type":"Services"
        }
    ],
    "sg:phone":"+61 2 9672 1140",
    "sg:postcode":"2148",
    "sg:province":"NSW",
    "sg:tags":[
        "window",
        "tinting"
    ],
    "sg:website":"http://www.platinumtint.com.au",
    "wof:name":"Platinum Window Tinting",
    "wof:placetype":"venue"
},
  "geometry": {"coordinates":[150.911621094,-33.7712593079],"type":"Point"}
}