{
  "type": "Feature",
  "properties": {
    "iso:country":"AU",
    "sg:address":"56 Bellevue Ave",
    "sg:city":"Highton",
    "sg:classifiers":[
        {
            "category":"Professional",
            "subcategory":"Computer Services",
            "type":"Services"
        }
    ],
    "sg:phone":"+61 422 580 618",
    "sg:postcode":"3216",
    "sg:province":"VIC",
    "sg:tags":[
        "package",
        "software"
    ],
    "wof:name":"Max Graphics",
    "wof:placetype":"venue"
},
  "geometry": {"coordinates":[144.32330322300001,-38.1778640747],"type":"Point"}
}