{
  "type": "Feature",
  "properties": {
    "iso:country":"AU",
    "sg:address":"214 Princes Hwy",
    "sg:city":"Hallam",
    "sg:classifiers":[
        {
            "category":"Health Services",
            "subcategory":"Doctor",
            "type":"Services"
        }
    ],
    "sg:phone":"+61 3 9703 1322",
    "sg:postcode":"3803",
    "sg:province":"VIC",
    "sg:tags":[
        "medical",
        "practitioner"
    ],
    "wof:name":"Phan Toai Dr",
    "wof:placetype":"venue"
},
  "geometry": {"coordinates":[145.27070617699999,-38.0055274963],"type":"Point"}
}