{
  "type": "Feature",
  "properties": {
    "iso:country":"AU",
    "sg:address":"11 Trade Way",
    "sg:city":"Kilsyth",
    "sg:classifiers":[
        {
            "category":"Organizations",
            "subcategory":"Labor Organization",
            "type":"Services"
        }
    ],
    "sg:phone":"+61 3 9761 4405",
    "sg:postcode":"3137",
    "sg:province":"VIC",
    "sg:tags":[
        "dust",
        "fume",
        "control",
        "equipment"
    ],
    "sg:website":"http://www.a-p-s.com",
    "wof:name":"Air Pollution Systems",
    "wof:placetype":"venue"
},
  "geometry": {"coordinates":[145.30523681599999,-37.8218841553],"type":"Point"}
}