{
  "type": "Feature",
  "properties": {
    "addr:full":"Lvl 1, Suite 1 & 2 445 Illawarra Rd Marrickville NSW 2204",
    "addr:housenumber":"&;445",
    "addr:postcode":"2204",
    "addr:street":"2;Illawarra Rd",
    "iso:country":"AU",
    "sg:address":"Lvl 1, Suite 1 & 2 445 Illawarra Rd",
    "sg:city":"Marrickville",
    "sg:classifiers":[
        {
            "category":"Health Services",
            "subcategory":"Dentist",
            "type":"Services"
        }
    ],
    "sg:phone":"+61 2 9559 3440",
    "sg:postcode":"2204",
    "sg:province":"NSW",
    "wof:name":"Yannopoulos Dr Stan",
    "wof:placetype":"venue"
},
  "geometry": {"coordinates":[151.15016199999999,-33.916134],"type":"Point"}
}