{
  "type": "Feature",
  "properties": {
    "addr:full":"Mt Druitt Shopping Centre Shop C2 Luxford Rd Mt Druitt NSW 2770",
    "addr:housenumber":"c2",
    "addr:postcode":"2770",
    "addr:street":"Luxford Rd",
    "iso:country":"AU",
    "sg:address":"Mt Druitt Shopping Centre Shop C2 Luxford Rd",
    "sg:city":"Mt Druitt",
    "sg:classifiers":[
        {
            "category":"Fast Food",
            "type":"Food & Drink"
        }
    ],
    "sg:phone":"+61 2 9625 7991",
    "sg:postcode":"2770",
    "sg:province":"NSW",
    "sg:tags":[
        "away",
        "take"
    ],
    "wof:name":"KFC",
    "wof:placetype":"venue"
},
  "geometry": {"coordinates":[150.81736755399999,-33.7643470764],"type":"Point"}
}