{
  "type": "Feature",
  "properties": {
    "addr:full":"Unit 2/ 29 Second St Boolaroo NSW 2284",
    "addr:housenumber":"29",
    "addr:postcode":"2284",
    "addr:street":"Second St",
    "iso:country":"AU",
    "sg:address":"Unit 2/ 29 Second St",
    "sg:city":"Boolaroo",
    "sg:classifiers":[
        {
            "category":"Landmark",
            "subcategory":"Scenic View",
            "type":"Public Place"
        }
    ],
    "sg:phone":"+61 404 105 109",
    "sg:postcode":"2284",
    "sg:province":"NSW",
    "sg:tags":[
        "staircase",
        "handrail"
    ],
    "wof:name":"Extreme Stainless & Alloys",
    "wof:placetype":"venue"
},
  "geometry": {"coordinates":[151.623245239,-32.9506225586],"type":"Point"}
}