{
  "type": "Feature",
  "properties": {
    "iso:country":"AU",
    "sg:address":"1st Flr 84 Smith St",
    "sg:city":"Darwin",
    "sg:classifiers":[
        {
            "category":"Professional",
            "subcategory":"Lawyer & Legal Services",
            "type":"Services"
        }
    ],
    "sg:phone":"+61 8 8981 9000",
    "sg:postcode":"0800",
    "sg:province":"NT",
    "sg:tags":[
        "process",
        "server"
    ],
    "wof:name":"NCS NT Pty Ltd",
    "wof:placetype":"venue"
},
  "geometry": {"coordinates":[130.83909606899999,-12.4603357315],"type":"Point"}
}