{
  "type": "Feature",
  "properties": {
    "addr:full":"252 Main Rd Derwent Park TAS 7009",
    "addr:housenumber":"252",
    "addr:postcode":"7009",
    "addr:street":"Main Rd",
    "iso:country":"AU",
    "sg:address":"252 Main Rd",
    "sg:city":"Derwent Park",
    "sg:classifiers":[
        {
            "category":"Health Services",
            "subcategory":"Doctor",
            "type":"Services"
        }
    ],
    "sg:phone":"+61 1300 731 788",
    "sg:postcode":"7009",
    "sg:province":"TAS",
    "sg:tags":[
        "medical",
        "practitioner"
    ],
    "wof:name":"After Hours Doctor",
    "wof:placetype":"venue"
},
  "geometry": {"coordinates":[147.28732299800001,-42.8367538452],"type":"Point"}
}