{
  "type": "Feature",
  "properties": {
    "addr:full":"21 Ada St Drysdale VIC 3222",
    "addr:housenumber":"21",
    "addr:postcode":"3222",
    "addr:street":"Ada St",
    "iso:country":"AU",
    "sg:address":"21 Ada St",
    "sg:city":"Drysdale",
    "sg:classifiers":[
        {
            "category":"Home & Garden",
            "subcategory":"Building Materials",
            "type":"Retail Goods"
        }
    ],
    "sg:phone":"+61 402 321 379",
    "sg:postcode":"3222",
    "sg:province":"VIC",
    "sg:tags":[
        "fitting",
        "door"
    ],
    "wof:name":"Central Garage Door Services",
    "wof:placetype":"venue"
},
  "geometry": {"coordinates":[144.55616800000001,-38.165062],"type":"Point"}
}