{
  "type": "Feature",
  "properties": {
    "iso:country":"AU",
    "sg:address":"21 Ada St",
    "sg:city":"Drysdale",
    "sg:classifiers":[
        {
            "category":"Home & Garden",
            "subcategory":"Building Materials",
            "type":"Retail Goods"
        }
    ],
    "sg:phone":"+61 402 321 379",
    "sg:postcode":"3222",
    "sg:province":"VIC",
    "sg:tags":[
        "fitting",
        "door"
    ],
    "wof:name":"Central Garage Door Services",
    "wof:placetype":"venue"
},
  "geometry": {"coordinates":[144.556168,-38.165062],"type":"Point"}
}