{
  "type": "Feature",
  "properties": {
    "iso:country":"AU",
    "sg:address":"4/ 7 Boyd Crs",
    "sg:city":"Hamilton Hill",
    "sg:classifiers":[
        {
            "category":"Home & Garden",
            "subcategory":"Hardware",
            "type":"Retail Goods"
        }
    ],
    "sg:phone":"+61 8 9335 6525",
    "sg:postcode":"6163",
    "sg:province":"WA",
    "sg:tags":[
        "supply",
        "maker",
        "cabinet"
    ],
    "wof:name":"The Edge Free Formers",
    "wof:placetype":"venue"
},
  "geometry": {"coordinates":[115.77831999999999,-32.080891],"type":"Point"}
}