{
  "type": "Feature",
  "properties": {
    "iso:country":"AU",
    "sg:address":"Unit 3 & 4, 5 Burns St",
    "sg:city":"Kawana Waters",
    "sg:classifiers":[
        {
            "category":"Farming",
            "subcategory":"Fish & Marine Products",
            "type":"Manufacturing & Wholesale Goods"
        }
    ],
    "sg:phone":"+61 7 5444 5552",
    "sg:postcode":"4575",
    "sg:province":"QLD",
    "sg:tags":[
        "organic"
    ],
    "wof:name":"Nude Food Organics",
    "wof:placetype":"venue"
},
  "geometry": {"coordinates":[153.130508,-26.705221],"type":"Point"}
}