{
  "type": "Feature",
  "properties": {
    "addr:full":"334 South St O'Connor WA 6163",
    "addr:housenumber":"334",
    "addr:postcode":"6163",
    "addr:street":"South St",
    "iso:country":"AU",
    "sg:address":"334 South St",
    "sg:city":"O'Connor",
    "sg:classifiers":[
        {
            "category":"Building & Trades",
            "subcategory":"Construction",
            "type":"Services"
        }
    ],
    "sg:phone":"+61 8 9331 7866",
    "sg:postcode":"6163",
    "sg:province":"WA",
    "sg:tags":[
        "pool",
        "swimming"
    ],
    "wof:name":"Clark Pools & Spas",
    "wof:placetype":"venue"
},
  "geometry": {"coordinates":[115.784271,-32.063366],"type":"Point"}
}