{
  "type": "Feature",
  "properties": {
    "addr:full":"144 Anzac Ave Collaroy NSW 2097",
    "addr:housenumber":"144",
    "addr:postcode":"2097",
    "addr:street":"Anzac Ave",
    "iso:country":"AU",
    "sg:address":"144 Anzac Ave",
    "sg:city":"Collaroy",
    "sg:classifiers":[
        {
            "category":"Real Estate",
            "subcategory":"Surveying",
            "type":"Services"
        }
    ],
    "sg:phone":"+61 417 449 037",
    "sg:postcode":"2097",
    "sg:province":"NSW",
    "sg:tags":[
        "surveyor",
        "land"
    ],
    "wof:name":"Kiprovich & Associates Pty Ltd",
    "wof:placetype":"venue"
},
  "geometry": {"coordinates":[151.29063415499999,-33.7356758118],"type":"Point"}
}