{
  "type": "Feature",
  "properties": {
    "addr:full":"Shp 8b, 233 Berrigan Drv Jandakot WA 6164",
    "addr:housenumber":"8b 233",
    "addr:postcode":"6164",
    "addr:street":"Berrigan Drv",
    "iso:country":"AU",
    "sg:address":"Shp 8b, 233 Berrigan Drv",
    "sg:city":"Jandakot",
    "sg:classifiers":[
        {
            "category":"Shopping",
            "subcategory":"Crafts & Fabrics",
            "type":"Retail Goods"
        }
    ],
    "sg:phone":"+61 8 9417 3665",
    "sg:postcode":"6164",
    "sg:province":"WA",
    "sg:tags":[
        "supply"
    ],
    "wof:name":"Just Scrapbooking",
    "wof:placetype":"venue"
},
  "geometry": {"coordinates":[115.858856,-32.107849],"type":"Point"}
}