{
  "type": "Feature",
  "properties": {
    "iso:country":"AU",
    "sg:address":"125 Calarie Rd",
    "sg:city":"Forbes",
    "sg:classifiers":[
        {
            "category":"Utilities",
            "subcategory":"Electric",
            "type":"Services"
        }
    ],
    "sg:phone":"+61 2 6851 1453",
    "sg:postcode":"2871",
    "sg:province":"NSW",
    "sg:tags":[
        "electrical",
        "contractor"
    ],
    "wof:name":"Trevor Williams Electrical Pty Ltd",
    "wof:placetype":"venue"
},
  "geometry": {"coordinates":[148.01370199999999,-33.351646],"type":"Point"}
}