{
  "type": "Feature",
  "properties": {
    "addr:full":"51 Haldon St Lakemba NSW 2195",
    "addr:housenumber":"51",
    "addr:postcode":"2195",
    "addr:street":"Haldon St",
    "iso:country":"AU",
    "sg:address":"51 Haldon St",
    "sg:city":"Lakemba",
    "sg:classifiers":[
        {
            "category":"Health Services",
            "subcategory":"Doctor",
            "type":"Services"
        }
    ],
    "sg:phone":"+61 2 9759 3138",
    "sg:postcode":"2195",
    "sg:province":"NSW",
    "sg:tags":[
        "medical",
        "practitioner"
    ],
    "wof:name":"Selim F",
    "wof:placetype":"venue"
},
  "geometry": {"coordinates":[151.076843,-33.919186],"type":"Point"}
}