{
  "type": "Feature",
  "properties": {
    "iso:country":"AU",
    "sg:address":"Slaughterhouse La",
    "sg:city":"Poowong",
    "sg:classifiers":[
        {
            "category":"Wholesale",
            "subcategory":"Meat",
            "type":"Manufacturing & Wholesale Goods"
        }
    ],
    "sg:phone":"+61 3 5659 2280",
    "sg:postcode":"3988",
    "sg:province":"VIC",
    "sg:tags":[
        "packing",
        "exporting"
    ],
    "wof:name":"GBP Export",
    "wof:placetype":"venue"
},
  "geometry": {"coordinates":[145.770553589,-38.340297699],"type":"Point"}
}