{
  "type": "Feature",
  "properties": {
    "addr:full":"162- 164 Nelson St Lilydale VIC 3140",
    "addr:housenumber":"164",
    "addr:postcode":"3140",
    "addr:street":"Nelson St",
    "iso:country":"AU",
    "sg:address":"162- 164 Nelson St",
    "sg:city":"Lilydale",
    "sg:classifiers":[
        {
            "category":"Social Services",
            "subcategory":"Child Care",
            "type":"Services"
        }
    ],
    "sg:phone":"+61 3 9739 6766",
    "sg:postcode":"3140",
    "sg:province":"VIC",
    "wof:name":"Como Park Child Care & Kindergarten",
    "wof:placetype":"venue"
},
  "geometry": {"coordinates":[145.37161254899999,-37.7617797852],"type":"Point"}
}