{
  "type": "Feature",
  "properties": {
    "addr:full":"Shop 3/ 625 Ruthven St Toowoomba QLD 4350",
    "addr:housenumber":"shop 3 / 625",
    "addr:postcode":"4350",
    "addr:street":"Ruthven St",
    "iso:country":"AU",
    "sg:address":"Shop 3/ 625 Ruthven St",
    "sg:city":"Toowoomba",
    "sg:classifiers":[
        {
            "category":"Personal",
            "subcategory":"Massage",
            "type":"Services"
        }
    ],
    "sg:phone":"+61 7 4637 8688",
    "sg:postcode":"4350",
    "sg:province":"QLD",
    "sg:tags":[
        "therapy"
    ],
    "wof:name":"Chinese Therapeutic Massage Clinic",
    "wof:placetype":"venue"
},
  "geometry": {"coordinates":[151.95233200000001,-27.56802],"type":"Point"}
}