{
  "type": "Feature",
  "properties": {
    "addr:full":"67 Grantulla Rd Kallista VIC 3791",
    "addr:housenumber":"67",
    "addr:postcode":"3791",
    "addr:street":"Grantulla Rd",
    "iso:country":"AU",
    "sg:address":"67 Grantulla Rd",
    "sg:city":"Kallista",
    "sg:classifiers":[
        {
            "category":"Professional",
            "subcategory":"Computer Services",
            "type":"Services"
        }
    ],
    "sg:phone":"+61 3 9752 0375",
    "sg:postcode":"3791",
    "sg:province":"VIC",
    "sg:tags":[
        "package",
        "software"
    ],
    "wof:name":"Samsa Consulting Group Pty Ltd",
    "wof:placetype":"venue"
},
  "geometry": {"coordinates":[145.39466857900001,-37.8987960815],"type":"Point"}
}