{
  "type": "Feature",
  "properties": {
    "addr:full":"5 McCall Pl Wanneroo WA 6065",
    "addr:housenumber":"5",
    "addr:postcode":"6065",
    "addr:street":"Mccall Pl",
    "iso:country":"AU",
    "sg:address":"5 McCall Pl",
    "sg:city":"Wanneroo",
    "sg:classifiers":[
        {
            "category":"Building & Trades",
            "subcategory":"Construction",
            "type":"Services"
        }
    ],
    "sg:phone":"+61 8 9405 1531",
    "sg:postcode":"6065",
    "sg:province":"WA",
    "sg:tags":[
        "bitumen",
        "paving",
        "asphalt"
    ],
    "wof:name":"Alpha Earthmoving",
    "wof:placetype":"venue"
},
  "geometry": {"coordinates":[115.829872131,-31.7799835205],"type":"Point"}
}