{
  "type": "Feature",
  "properties": {
    "addr:full":"62 Dudley St Annerley QLD 4103",
    "addr:housenumber":"62",
    "addr:postcode":"4103",
    "addr:street":"Dudley St",
    "iso:country":"AU",
    "sg:address":"62 Dudley St",
    "sg:city":"Annerley",
    "sg:classifiers":[
        {
            "category":"Social Services",
            "subcategory":"Retirement Home",
            "type":"Services"
        }
    ],
    "sg:phone":"+61 7 3848 5971",
    "sg:postcode":"4103",
    "sg:province":"QLD",
    "sg:tags":[
        "village"
    ],
    "wof:name":"Westminster House Annerley",
    "wof:placetype":"venue"
},
  "geometry": {"coordinates":[153.03138732900001,-27.5104484558],"type":"Point"}
}