{
  "type": "Feature",
  "properties": {
    "iso:country":"AU",
    "sg:address":"6- 10 First Ave",
    "sg:city":"Marsden",
    "sg:classifiers":[
        {
            "category":"Education",
            "subcategory":"Kindergarten",
            "type":"Public Place"
        }
    ],
    "sg:phone":"+61 7 3805 2133",
    "sg:postcode":"4132",
    "sg:province":"QLD",
    "sg:tags":[
        "pre-schools"
    ],
    "wof:name":"Marsden Child Care Centres",
    "wof:placetype":"venue"
},
  "geometry": {"coordinates":[153.099975586,-27.6803359985],"type":"Point"}
}