{
  "type": "Feature",
  "properties": {
    "addr:full":"146 Kidds Rd Doveton VIC 3177",
    "addr:housenumber":"146",
    "addr:postcode":"3177",
    "addr:street":"Kidds Rd",
    "iso:country":"AU",
    "sg:address":"146 Kidds Rd",
    "sg:city":"Doveton",
    "sg:classifiers":[
        {
            "category":"Education",
            "subcategory":"School",
            "type":"Public Place"
        }
    ],
    "sg:phone":"+61 3 9709 7350",
    "sg:postcode":"3177",
    "sg:province":"VIC",
    "sg:tags":[
        "co-educational"
    ],
    "wof:name":"Maranatha Christian School",
    "wof:placetype":"venue"
},
  "geometry": {"coordinates":[145.2368927,-37.9872550964],"type":"Point"}
}