{
  "type": "Feature",
  "properties": {
    "addr:full":"23 Rooks Rd Nunawading VIC 3131",
    "addr:housenumber":"23",
    "addr:postcode":"3131",
    "addr:street":"Rooks Rd",
    "iso:country":"AU",
    "sg:address":"23 Rooks Rd",
    "sg:city":"Nunawading",
    "sg:classifiers":[
        {
            "category":"Retail",
            "subcategory":"Auto Repair",
            "type":"Services"
        }
    ],
    "sg:phone":"+61 3 9873 5622",
    "sg:postcode":"3131",
    "sg:province":"VIC",
    "sg:tags":[
        "beater",
        "painter",
        "panel"
    ],
    "wof:name":"R & E Panel Masters Pty Ltd",
    "wof:placetype":"venue"
},
  "geometry": {"coordinates":[145.18565368599999,-37.8192558289],"type":"Point"}
}