{
  "type": "Feature",
  "properties": {
    "addr:full":"62 Clarks Rd Loganholme QLD 4129",
    "addr:housenumber":"62",
    "addr:postcode":"4129",
    "addr:street":"Clarks Rd",
    "iso:country":"AU",
    "sg:address":"62 Clarks Rd",
    "sg:city":"Loganholme",
    "sg:classifiers":[
        {
            "category":"Farming",
            "subcategory":"Nursery",
            "type":"Manufacturing & Wholesale Goods"
        }
    ],
    "sg:phone":"+61 7 3209 9001",
    "sg:postcode":"4129",
    "sg:province":"QLD",
    "wof:name":"Impact Grasses",
    "wof:placetype":"venue"
},
  "geometry": {"coordinates":[153.185714722,-27.6915836334],"type":"Point"}
}