{
  "type": "Feature",
  "properties": {
    "addr:full":"42 Melbourne Ave Glenroy VIC 3046",
    "addr:housenumber":"42",
    "addr:postcode":"3046",
    "addr:street":"Melbourne Ave",
    "iso:country":"AU",
    "sg:address":"42 Melbourne Ave",
    "sg:city":"Glenroy",
    "sg:classifiers":[
        {
            "category":"Professional",
            "subcategory":"Art Services",
            "type":"Services"
        }
    ],
    "sg:phone":"+61 419 200 469",
    "sg:postcode":"3046",
    "sg:province":"VIC",
    "sg:tags":[
        "decorator",
        "painter"
    ],
    "wof:name":"Stones Painting",
    "wof:placetype":"venue"
},
  "geometry": {"coordinates":[144.93440246599999,-37.7043075562],"type":"Point"}
}