{
  "type": "Feature",
  "properties": {
    "iso:country":"AU",
    "sg:address":"Tailor Ave",
    "sg:city":"Golden Beach",
    "sg:classifiers":[
        {
            "category":"Building & Trades",
            "subcategory":"Construction",
            "type":"Services"
        }
    ],
    "sg:phone":"+61 7 5492 4836",
    "sg:postcode":"4551",
    "sg:province":"QLD",
    "sg:tags":[
        "joiner",
        "carpenter"
    ],
    "wof:name":"Greg Doodson",
    "wof:placetype":"venue"
},
  "geometry": {"coordinates":[153.11915588400001,-26.8212203979],"type":"Point"}
}