{
  "type": "Feature",
  "properties": {
    "addr:full":"Level 2, 45 Williams St Melbourne VIC 3000",
    "addr:housenumber":"45",
    "addr:postcode":"3000",
    "addr:street":"Williams St",
    "iso:country":"AU",
    "sg:address":"Level 2, 45 Williams St",
    "sg:city":"Melbourne",
    "sg:classifiers":[
        {
            "category":"Banks & Credit Unions",
            "subcategory":"Investment Brokerage",
            "type":"Services"
        }
    ],
    "sg:phone":"+61 3 9670 9122",
    "sg:postcode":"3000",
    "sg:province":"VIC",
    "sg:tags":[
        "debt",
        "collection"
    ],
    "wof:name":"Waterman Receivables Management Pty Ltd",
    "wof:placetype":"venue"
},
  "geometry": {"coordinates":[144.95936584500001,-37.8185272217],"type":"Point"}
}