{
  "type": "Feature",
  "properties": {
    "addr:full":"19 Arabian Crt Hindmarsh Valley SA 5211",
    "addr:housenumber":"19",
    "addr:postcode":"5211",
    "addr:street":"Arabian Crt",
    "iso:country":"AU",
    "sg:address":"19 Arabian Crt",
    "sg:city":"Hindmarsh Valley",
    "sg:classifiers":[
        {
            "category":"Building & Trades",
            "subcategory":"Construction",
            "type":"Services"
        }
    ],
    "sg:phone":"+61 407 717 255",
    "sg:postcode":"5211",
    "sg:province":"SA",
    "sg:tags":[
        "joiner",
        "carpenter"
    ],
    "wof:name":"Hindmarsh Valley Carpentry",
    "wof:placetype":"venue"
},
  "geometry": {"coordinates":[138.623245239,-35.5129547119],"type":"Point"}
}