{
  "type": "Feature",
  "properties": {
    "addr:full":"18 Beachcraft St Bray Park QLD 4500",
    "addr:housenumber":"18",
    "addr:postcode":"4500",
    "addr:street":"Beachcraft St Bray Park",
    "iso:country":"AU",
    "sg:address":"18 Beachcraft St",
    "sg:city":"Bray Park",
    "sg:classifiers":[
        {
            "category":"Wholesale",
            "subcategory":"Scrap",
            "type":"Manufacturing & Wholesale Goods"
        }
    ],
    "sg:phone":"+61 418 723 367",
    "sg:postcode":"4500",
    "sg:province":"QLD",
    "sg:tags":[
        "merchant",
        "metal"
    ],
    "wof:name":"Ace Scrap Metal",
    "wof:placetype":"venue"
},
  "geometry": {"coordinates":[152.965530395,-27.2861881256],"type":"Point"}
}