{
  "type": "Feature",
  "properties": {
    "addr:full":"4 Griffin Rd White Rock QLD 4868",
    "addr:housenumber":"4",
    "addr:postcode":"4868",
    "addr:street":"Griffin Rd",
    "iso:country":"AU",
    "sg:address":"4 Griffin Rd",
    "sg:city":"White Rock",
    "sg:classifiers":[
        {
            "category":"Home & Garden",
            "subcategory":"Garden Supply",
            "type":"Retail Goods"
        }
    ],
    "sg:phone":"+61 7 4036 2386",
    "sg:postcode":"4868",
    "sg:province":"QLD",
    "sg:tags":[
        "equipment"
    ],
    "wof:name":"Southside Raw Materials",
    "wof:placetype":"venue"
},
  "geometry": {"coordinates":[145.74281310999999,-16.9910144806],"type":"Point"}
}