{
  "type": "Feature",
  "properties": {
    "addr:full":"500 Churchill Rd Kilburn SA 5084",
    "addr:housenumber":"500",
    "addr:postcode":"5084",
    "addr:street":"Churchill Rd",
    "iso:country":"AU",
    "sg:address":"500 Churchill Rd",
    "sg:city":"Kilburn",
    "sg:classifiers":[
        {
            "category":"Shopping",
            "subcategory":"Party Supplies",
            "type":"Retail Goods"
        }
    ],
    "sg:phone":"+61 1800 244 422",
    "sg:postcode":"5084",
    "sg:province":"SA",
    "sg:tags":[
        "toilet",
        "portable"
    ],
    "wof:name":"Executive Washrooms",
    "wof:placetype":"venue"
},
  "geometry": {"coordinates":[138.58297729500001,-34.8552246094],"type":"Point"}
}