{
  "type": "Feature",
  "properties": {
    "iso:country":"AU",
    "sg:address":"Harpers La",
    "sg:city":"Wedderburn",
    "sg:classifiers":[
        {
            "category":"Professional",
            "type":"Services"
        }
    ],
    "sg:phone":"+61 3 5494 3240",
    "sg:postcode":"3518",
    "sg:province":"VIC",
    "sg:tags":[
        "buyer",
        "merchant",
        "wool"
    ],
    "wof:name":"Jackson Kevin",
    "wof:placetype":"venue"
},
  "geometry": {"coordinates":[143.624313,-36.423252],"type":"Point"}
}