{
  "type": "Feature",
  "properties": {
    "addr:full":"90 Warriewood St Chandler QLD 4155",
    "addr:housenumber":"90",
    "addr:postcode":"4155",
    "addr:street":"Warriewood St",
    "iso:country":"AU",
    "sg:address":"90 Warriewood St",
    "sg:city":"Chandler",
    "sg:classifiers":[
        {
            "category":"Building & Trades",
            "subcategory":"Pest Control",
            "type":"Services"
        }
    ],
    "sg:phone":"+61 7 3245 5525",
    "sg:postcode":"4155",
    "sg:province":"QLD",
    "wof:name":"White Ant Co The",
    "wof:placetype":"venue"
},
  "geometry": {"coordinates":[153.16169738799999,-27.5146350861],"type":"Point"}
}