{
  "type": "Feature",
  "properties": {
    "addr:full":"34 Satinwood Crt Bardon QLD 4065",
    "addr:housenumber":"34",
    "addr:postcode":"4065",
    "addr:street":"Satinwood Crt",
    "iso:country":"AU",
    "sg:address":"34 Satinwood Crt",
    "sg:city":"Bardon",
    "sg:classifiers":[
        {
            "category":"Autos & Motor Vehicles",
            "subcategory":"Boat Sales",
            "type":"Retail Goods"
        }
    ],
    "sg:phone":"+61 1800 989 888",
    "sg:postcode":"4065",
    "sg:province":"QLD",
    "sg:tags":[
        "yacht"
    ],
    "wof:name":"Princess Yachts Australia",
    "wof:placetype":"venue"
},
  "geometry": {"coordinates":[152.97752380399999,-27.4696445465],"type":"Point"}
}