{
  "type": "Feature",
  "properties": {
    "iso:country":"AU",
    "sg:address":"Suite 4/ 6 Maluka St",
    "sg:city":"Palmerston",
    "sg:classifiers":[
        {
            "category":"Health Services",
            "subcategory":"Dentist",
            "type":"Services"
        }
    ],
    "sg:phone":"+61 8 8981 8113",
    "sg:postcode":"0830",
    "sg:province":"NT",
    "wof:name":"Palmerston Tooth Replacement Centre",
    "wof:placetype":"venue"
},
  "geometry": {"coordinates":[130.987595,-12.481539],"type":"Point"}
}