{
  "type": "Feature",
  "properties": {
    "iso:country":"AU",
    "sg:address":"Unit 10, 219 Onslow Rd",
    "sg:city":"Shenton Park",
    "sg:classifiers":[
        {
            "category":"Banks & Credit Unions",
            "subcategory":"Financial Services",
            "type":"Services"
        }
    ],
    "sg:phone":"+61 8 9380 4844",
    "sg:postcode":"6008",
    "sg:province":"WA",
    "sg:tags":[
        "planning"
    ],
    "wof:name":"Winchcombe Carson Financial Planning Pty Ltd",
    "wof:placetype":"venue"
},
  "geometry": {"coordinates":[115.811683655,-31.9609603882],"type":"Point"}
}