{
  "type": "Feature",
  "properties": {
    "iso:country":"AU",
    "sg:address":"PO Box 1054",
    "sg:city":"Dickson",
    "sg:classifiers":[
        {
            "category":"Building & Trades",
            "subcategory":"Construction",
            "type":"Services"
        }
    ],
    "sg:phone":"+61 410 504 435",
    "sg:postcode":"2602",
    "sg:province":"ACT",
    "sg:tags":[
        "brick",
        "paving"
    ],
    "wof:name":"Drake-Brockman Landscapes",
    "wof:placetype":"venue"
},
  "geometry": {"coordinates":[149.142944336,-35.2521018982],"type":"Point"}
}