{
  "type": "Feature",
  "properties": {
    "iso:country":"AU",
    "sg:address":"Boland Centre Lake St",
    "sg:city":"Cairns",
    "sg:classifiers":[
        {
            "category":"Personal",
            "subcategory":"Beauty Salon",
            "type":"Services"
        }
    ],
    "sg:phone":"+61 7 4041 0441",
    "sg:postcode":"4870",
    "sg:province":"QLD",
    "sg:tags":[
        "hairdresser"
    ],
    "wof:name":"Adam & Eva",
    "wof:placetype":"venue"
},
  "geometry": {"coordinates":[145.756317139,-16.9318656921],"type":"Point"}
}