{
  "type": "Feature",
  "properties": {
    "addr:full":"70 Nicholson St Abbotsford VIC 3067",
    "addr:housenumber":"70",
    "addr:postcode":"3067",
    "addr:street":"Nicholson St",
    "iso:country":"AU",
    "sg:address":"70 Nicholson St",
    "sg:city":"Abbotsford",
    "sg:classifiers":[
        {
            "category":"Shopping",
            "subcategory":"Antiques",
            "type":"Retail Goods"
        }
    ],
    "sg:phone":"+61 3 9419 7009",
    "sg:postcode":"3067",
    "sg:province":"VIC",
    "wof:name":"Rohan Fielding Decor Pty Ltd",
    "wof:placetype":"venue"
},
  "geometry": {"coordinates":[144.99659729000001,-37.8071174622],"type":"Point"}
}