{
  "type": "Feature",
  "properties": {
    "addr:full":"7 Brennan Drv Wantirna South VIC 3152",
    "addr:housenumber":"7",
    "addr:postcode":"3152",
    "addr:street":"Brennan Drv",
    "iso:country":"AU",
    "sg:address":"7 Brennan Drv",
    "sg:city":"Wantirna South",
    "sg:classifiers":[
        {
            "category":"Building & Trades",
            "subcategory":"Plumbing",
            "type":"Services"
        }
    ],
    "sg:phone":"+61 419 575 445",
    "sg:postcode":"3152",
    "sg:province":"VIC",
    "sg:tags":[
        "plumber",
        "gasfitters"
    ],
    "wof:name":"The Fussy Plumber",
    "wof:placetype":"venue"
},
  "geometry": {"coordinates":[145.22410583499999,-37.8874282837],"type":"Point"}
}