{
  "type": "Feature",
  "properties": {
    "iso:country":"AU",
    "sg:address":"59 Raglan St",
    "sg:city":"Mosman",
    "sg:classifiers":[
        {
            "category":"Professional",
            "subcategory":"Management & Consulting",
            "type":"Services"
        }
    ],
    "sg:phone":"+61 2 9969 3913",
    "sg:postcode":"2088",
    "sg:province":"NSW",
    "sg:tags":[
        "consultant"
    ],
    "wof:name":"Megan Bartlett & Associates Pty Ltd",
    "wof:placetype":"venue"
},
  "geometry": {"coordinates":[151.23760986299999,-33.8359298706],"type":"Point"}
}