{
  "type": "Feature",
  "properties": {
    "addr:full":"PO Box 588 Mitchell ACT 2911",
    "addr:postcode":"2911",
    "iso:country":"AU",
    "sg:address":"PO Box 588",
    "sg:city":"Mitchell",
    "sg:classifiers":[
        {
            "category":"Professional",
            "subcategory":"Detective & Security Services",
            "type":"Services"
        }
    ],
    "sg:phone":"+61 2 6242 6700",
    "sg:postcode":"2911",
    "sg:province":"ACT",
    "sg:tags":[
        "consultant",
        "system"
    ],
    "wof:name":"National Capital Alarms",
    "wof:placetype":"venue"
},
  "geometry": {"coordinates":[149.13471984899999,-35.2194900513],"type":"Point"}
}