{
  "type": "Feature",
  "properties": {
    "addr:full":"PO Box 778 Gosford NSW 2250",
    "addr:postcode":"2250",
    "iso:country":"AU",
    "sg:address":"PO Box 778",
    "sg:city":"Gosford",
    "sg:classifiers":[
        {
            "category":"Insurance",
            "subcategory":"Hazard Insurance",
            "type":"Services"
        }
    ],
    "sg:phone":"+61 2 4382 4388",
    "sg:postcode":"2250",
    "sg:province":"NSW",
    "sg:tags":[
        "loss",
        "adjuster",
        "assessor"
    ],
    "wof:name":"Wyatt Gallagher Bassett",
    "wof:placetype":"venue"
},
  "geometry": {"coordinates":[151.34249877900001,-33.4237213135],"type":"Point"}
}