{
  "type": "Feature",
  "properties": {
    "addr:full":"258 Bennett Rd St Clair NSW 2759",
    "addr:housenumber":"258",
    "addr:postcode":"2759",
    "addr:street":"Bennett Rd",
    "iso:country":"AU",
    "sg:address":"258 Bennett Rd",
    "sg:city":"St Clair",
    "sg:classifiers":[
        {
            "category":"Personal",
            "subcategory":"Beauty Salon",
            "type":"Services"
        }
    ],
    "sg:phone":"+61 2 9834 5068",
    "sg:postcode":"2759",
    "sg:province":"NSW",
    "sg:tags":[
        "hairdresser"
    ],
    "wof:name":"Hair On Bennett",
    "wof:placetype":"venue"
},
  "geometry": {"coordinates":[150.79060363799999,-33.8044204712],"type":"Point"}
}