{
  "type": "Feature",
  "properties": {
    "addr:full":"42 Gardendale Crs Burleigh Waters QLD 4220",
    "addr:housenumber":"42",
    "addr:postcode":"4220",
    "addr:street":"Gardendale Crs",
    "iso:country":"AU",
    "sg:address":"42 Gardendale Crs",
    "sg:city":"Burleigh Waters",
    "sg:classifiers":[
        {
            "category":"Organizations",
            "subcategory":"Membership Organization",
            "type":"Services"
        }
    ],
    "sg:phone":"+61 7 5520 3564",
    "sg:postcode":"4220",
    "sg:province":"QLD",
    "sg:tags":[
        "equipment",
        "inter-communication",
        "system"
    ],
    "wof:name":"AES",
    "wof:placetype":"venue"
},
  "geometry": {"coordinates":[153.434082031,-28.080160141],"type":"Point"}
}