{
  "type": "Feature",
  "properties": {
    "addr:full":"73 Union Rd Ascot Vale VIC 3032",
    "addr:housenumber":"73",
    "addr:postcode":"3032",
    "addr:street":"Union Rd",
    "iso:country":"AU",
    "sg:address":"73 Union Rd",
    "sg:city":"Ascot Vale",
    "sg:classifiers":[
        {
            "category":"Health Services",
            "subcategory":"Doctor",
            "type":"Services"
        }
    ],
    "sg:phone":"+61 3 9370 3322",
    "sg:postcode":"3032",
    "sg:province":"VIC",
    "sg:tags":[
        "medical",
        "practitioner"
    ],
    "wof:name":"McCorkell John A Dr",
    "wof:placetype":"venue"
},
  "geometry": {"coordinates":[144.91514599999999,-37.777416],"type":"Point"}
}