{
  "type": "Feature",
  "properties": {
    "addr:full":"9 Tamar Ave George Town TAS 7253",
    "addr:housenumber":"9",
    "addr:postcode":"7253",
    "addr:street":"Tamar Ave",
    "iso:country":"AU",
    "sg:address":"9 Tamar Ave",
    "sg:city":"George Town",
    "sg:classifiers":[
        {
            "category":"Retail",
            "subcategory":"Funeral Services",
            "type":"Services"
        }
    ],
    "sg:phone":"+61 3 6382 4124",
    "sg:postcode":"7253",
    "sg:province":"TAS",
    "sg:tags":[
        "director"
    ],
    "wof:name":"Tamar Valley Funerals",
    "wof:placetype":"venue"
},
  "geometry": {"coordinates":[146.819488525,-41.1237373352],"type":"Point"}
}