{
  "type": "Feature",
  "properties": {
    "addr:full":"19 Boxtree Rd Montrose VIC 3765",
    "addr:housenumber":"19",
    "addr:postcode":"3765",
    "addr:street":"Boxtree Rd",
    "iso:country":"AU",
    "sg:address":"19 Boxtree Rd",
    "sg:city":"Montrose",
    "sg:classifiers":[
        {
            "category":"Social Services",
            "subcategory":"Child Care",
            "type":"Services"
        }
    ],
    "sg:phone":"+61 3 9761 9027",
    "sg:postcode":"3765",
    "sg:province":"VIC",
    "sg:tags":[
        "childbirth"
    ],
    "wof:name":"Learning Curves Childbirth Classes",
    "wof:placetype":"venue"
},
  "geometry": {"coordinates":[145.33952331500001,-37.8145065308],"type":"Point"}
}