{
  "type": "Feature",
  "properties": {
    "iso:country":"AU",
    "sg:address":"700 Ballarat Rd",
    "sg:city":"Batesford",
    "sg:classifiers":[
        {
            "category":"Retail",
            "subcategory":"Event Space",
            "type":"Services"
        }
    ],
    "sg:phone":"+61 3 5276 1201",
    "sg:postcode":"3221",
    "sg:province":"VIC",
    "sg:tags":[
        "venue",
        "reception",
        "wedding"
    ],
    "wof:name":"Derwent Hotel",
    "wof:placetype":"venue"
},
  "geometry": {"coordinates":[144.32202100000001,-38.106583],"type":"Point"}
}