{
  "type": "Feature",
  "properties": {
    "addr:full":"476 Hume St Albury NSW 2640",
    "addr:housenumber":"476",
    "addr:postcode":"2640",
    "addr:street":"Hume St",
    "iso:country":"AU",
    "sg:address":"476 Hume St",
    "sg:city":"Albury",
    "sg:classifiers":[
        {
            "category":"Government",
            "subcategory":"Fire Station",
            "type":"Public Place"
        }
    ],
    "sg:phone":"+61 2 6021 2477",
    "sg:postcode":"2640",
    "sg:province":"NSW",
    "sg:tags":[
        "spring",
        "shock",
        "absorbers",
        "suspension"
    ],
    "wof:name":"Hume Exhaust & Towbars & 4WD Pty Ltd",
    "wof:placetype":"venue"
},
  "geometry": {"coordinates":[146.91894531200001,-36.0851097107],"type":"Point"}
}