{
  "type": "Feature",
  "properties": {
    "addr:full":"6 Brentwick St Chermside QLD 4032",
    "addr:housenumber":"6",
    "addr:postcode":"qld 4032",
    "addr:street":"Brentwick St",
    "iso:country":"AU",
    "sg:address":"6 Brentwick St",
    "sg:city":"Chermside",
    "sg:classifiers":[
        {
            "category":"Shopping",
            "subcategory":"Computers & Home Electronics",
            "type":"Retail Goods"
        }
    ],
    "sg:phone":"+61 417 719 131",
    "sg:postcode":"4032",
    "sg:province":"QLD",
    "sg:tags":[
        "hardware",
        "equipment"
    ],
    "wof:name":"Ventura Software Solutions Pty Ltd",
    "wof:placetype":"venue"
},
  "geometry": {"coordinates":[153.025497,-27.378794],"type":"Point"}
}