{
  "type": "Feature",
  "properties": {
    "iso:country":"AU",
    "sg:address":"PO Box 169",
    "sg:city":"Ascot Vale",
    "sg:classifiers":[
        {
            "category":"Building & Trades",
            "subcategory":"Locksmith",
            "type":"Services"
        }
    ],
    "sg:phone":"+61 3 9326 2005",
    "sg:postcode":"3032",
    "sg:province":"VIC",
    "sg:tags":[
        "strongroom",
        "safe",
        "door"
    ],
    "wof:name":"Stafast Safe Co",
    "wof:placetype":"venue"
},
  "geometry": {"coordinates":[144.91554300000001,-37.7756],"type":"Point"}
}