{
  "type": "Feature",
  "properties": {
    "addr:full":"600 Stafford Rd Stafford West QLD 4053",
    "addr:housenumber":"600",
    "addr:postcode":"4053",
    "addr:street":"Stafford Rd",
    "iso:country":"AU",
    "sg:address":"600 Stafford Rd",
    "sg:city":"Stafford West",
    "sg:classifiers":[
        {
            "category":"Health Services",
            "subcategory":"Doctor",
            "type":"Services"
        }
    ],
    "sg:phone":"+61 7 3354 1188",
    "sg:postcode":"4053",
    "sg:province":"QLD",
    "sg:tags":[
        "medical",
        "practitioner"
    ],
    "wof:name":"Smith P D",
    "wof:placetype":"venue"
},
  "geometry": {"coordinates":[152.99957275400001,-27.4078578949],"type":"Point"}
}