{
  "type": "Feature",
  "properties": {
    "iso:country":"AU",
    "sg:address":"3/ 31 Uralla Rd",
    "sg:city":"Port Macquarie",
    "sg:classifiers":[
        {
            "category":"Building & Trades",
            "subcategory":"Construction",
            "type":"Services"
        }
    ],
    "sg:phone":"+61 2 6581 0117",
    "sg:postcode":"2444",
    "sg:province":"NSW",
    "sg:tags":[
        "fencing",
        "contractor"
    ],
    "wof:name":"Russty Bolts",
    "wof:placetype":"venue"
},
  "geometry": {"coordinates":[152.882843,-31.45363],"type":"Point"}
}