{
  "type": "Feature",
  "properties": {
    "addr:full":"317 Liverpool Rd Ashfield NSW 2131",
    "addr:housenumber":"317",
    "addr:postcode":"2131",
    "addr:street":"Liverpool Rd",
    "iso:country":"AU",
    "sg:address":"317 Liverpool Rd",
    "sg:city":"Ashfield",
    "sg:classifiers":[
        {
            "category":"Fast Food",
            "type":"Food & Drink"
        }
    ],
    "sg:phone":"+61 2 9716 7718",
    "sg:postcode":"2131",
    "sg:province":"NSW",
    "sg:tags":[
        "away",
        "take"
    ],
    "wof:name":"Pu Tai Thai Restaurant & Takeaway",
    "wof:placetype":"venue"
},
  "geometry": {"coordinates":[151.122924805,-33.8876419067],"type":"Point"}
}