{
  "type": "Feature",
  "properties": {
    "addr:full":"655 High St Kew East VIC 3102",
    "addr:housenumber":"655",
    "addr:postcode":"3102",
    "addr:street":"High St",
    "iso:country":"AU",
    "sg:address":"655 High St",
    "sg:city":"Kew East",
    "sg:classifiers":[
        {
            "category":"Food & Beverages",
            "subcategory":"Supermarket",
            "type":"Retail Goods"
        }
    ],
    "sg:phone":"+61 3 9859 1782",
    "sg:postcode":"3102",
    "sg:province":"VIC",
    "sg:tags":[
        "grocery",
        "store"
    ],
    "wof:name":"Friendly Grocers IGA",
    "wof:placetype":"venue"
},
  "geometry": {"coordinates":[145.05195617699999,-37.798576355],"type":"Point"}
}