{
  "type": "Feature",
  "properties": {
    "addr:full":"96 Main St Kandanga QLD 4570",
    "addr:housenumber":"96",
    "addr:postcode":"4570",
    "addr:street":"Main St",
    "iso:country":"AU",
    "sg:address":"96 Main St",
    "sg:city":"Kandanga",
    "sg:classifiers":[
        {
            "category":"Farming",
            "subcategory":"Poultry Farm",
            "type":"Manufacturing & Wholesale Goods"
        }
    ],
    "sg:phone":"+61 7 5484 3392",
    "sg:postcode":"4570",
    "sg:province":"QLD",
    "sg:tags":[
        "farmer"
    ],
    "wof:name":"Kandanga Poultry Products",
    "wof:placetype":"venue"
},
  "geometry": {"coordinates":[152.66921997099999,-26.1777496338],"type":"Point"}
}