{
  "type": "Feature",
  "properties": {
    "addr:full":"43 Paynters Rd Wonga Park VIC 3115",
    "addr:housenumber":"43",
    "addr:postcode":"3115",
    "addr:street":"Paynters Rd",
    "iso:country":"AU",
    "sg:address":"43 Paynters Rd",
    "sg:city":"Wonga Park",
    "sg:classifiers":[
        {
            "category":"Utilities",
            "subcategory":"Electric",
            "type":"Services"
        }
    ],
    "sg:phone":"+61 3 9722 2112",
    "sg:postcode":"3115",
    "sg:province":"VIC",
    "sg:tags":[
        "electrical",
        "contractor"
    ],
    "wof:name":"Power-Packed Electrics",
    "wof:placetype":"venue"
},
  "geometry": {"coordinates":[145.28288269000001,-37.7305335999],"type":"Point"}
}