{
  "type": "Feature",
  "properties": {
    "addr:full":"Unit1/ 58 Pendlebury Rd Cardiff NSW 2285",
    "addr:postcode":"2285",
    "addr:street":"Pendlebury Rd",
    "iso:country":"AU",
    "sg:address":"Unit1/ 58 Pendlebury Rd",
    "sg:city":"Cardiff",
    "sg:classifiers":[
        {
            "category":"Professional",
            "subcategory":"Engineering",
            "type":"Services"
        }
    ],
    "sg:phone":"+61 2 4956 8116",
    "sg:postcode":"2285",
    "sg:province":"NSW",
    "sg:tags":[
        "diesel",
        "engineer"
    ],
    "wof:name":"Great Northern Automotive",
    "wof:placetype":"venue"
},
  "geometry": {"coordinates":[151.651046753,-32.9396781921],"type":"Point"}
}