{
  "type": "Feature",
  "properties": {
    "addr:full":"34 Belmore St Wollongong NSW 2500",
    "addr:housenumber":"34",
    "addr:postcode":"2500",
    "addr:street":"Belmore St",
    "iso:country":"AU",
    "sg:address":"34 Belmore St",
    "sg:city":"Wollongong",
    "sg:classifiers":[
        {
            "category":"Retail",
            "subcategory":"Funeral Services",
            "type":"Services"
        }
    ],
    "sg:phone":"+61 2 4228 9622",
    "sg:postcode":"2500",
    "sg:province":"NSW",
    "sg:tags":[
        "director"
    ],
    "wof:name":"Parsons H Funeral Directors",
    "wof:placetype":"venue"
},
  "geometry": {"coordinates":[150.88960299999999,-34.423618],"type":"Point"}
}