{
  "type": "Feature",
  "properties": {
    "iso:country":"AU",
    "sg:address":"Level 7/ 360 Queen St",
    "sg:city":"Brisbane",
    "sg:classifiers":[
        {
            "category":"Professional",
            "subcategory":"Management & Consulting",
            "type":"Services"
        }
    ],
    "sg:phone":"+61 7 3120 0638",
    "sg:postcode":"4000",
    "sg:province":"QLD",
    "sg:tags":[
        "consultant",
        "business"
    ],
    "wof:name":"Parm Capital Services Pty Ltd",
    "wof:placetype":"venue"
},
  "geometry": {"coordinates":[153.02932739299999,-27.4662971497],"type":"Point"}
}