{
  "type": "Feature",
  "properties": {
    "iso:country":"AU",
    "sg:address":"18 Alexandria Rd",
    "sg:city":"Mackay",
    "sg:classifiers":[
        {
            "category":"Health Services",
            "subcategory":"Health Practitioner",
            "type":"Services"
        }
    ],
    "sg:phone":"+61 7 4954 5109",
    "sg:postcode":"4740",
    "sg:province":"QLD",
    "sg:tags":[
        "bowen",
        "therapy"
    ],
    "wof:name":"Kathryn Howarth",
    "wof:placetype":"venue"
},
  "geometry": {"coordinates":[149.08985899999999,-21.168497],"type":"Point"}
}