{
  "type": "Feature",
  "properties": {
    "addr:full":"Unit 6 / 1191 Anzac Ave Kallangur QLD 4503",
    "addr:housenumber":"/ 1191",
    "addr:postcode":"4503",
    "addr:street":"Anzac Ave",
    "iso:country":"AU",
    "sg:address":"Unit 6 / 1191 Anzac Ave",
    "sg:city":"Kallangur",
    "sg:classifiers":[
        {
            "category":"Professional",
            "subcategory":"Printing & Photocopies",
            "type":"Services"
        }
    ],
    "sg:phone":"+61 7 3889 2502",
    "sg:postcode":"4503",
    "sg:province":"QLD",
    "sg:tags":[
        "screen",
        "printer"
    ],
    "wof:name":"Screenprint Dynamics",
    "wof:placetype":"venue"
},
  "geometry": {"coordinates":[152.997283936,-27.2496147156],"type":"Point"}
}