{
  "type": "Feature",
  "properties": {
    "addr:full":"69 Mitcham Rd Donvale VIC 3111",
    "addr:housenumber":"69",
    "addr:postcode":"3111",
    "addr:street":"Mitcham Rd",
    "iso:country":"AU",
    "sg:address":"69 Mitcham Rd",
    "sg:city":"Donvale",
    "sg:classifiers":[
        {
            "category":"Food & Beverages",
            "subcategory":"Groceries & Convenience Stores",
            "type":"Retail Goods"
        }
    ],
    "sg:phone":"+61 3 9873 3453",
    "sg:postcode":"3111",
    "sg:province":"VIC",
    "wof:name":"Donvale Milkbar",
    "wof:placetype":"venue"
},
  "geometry": {"coordinates":[145.17987060600001,-37.7968177795],"type":"Point"}
}