{
  "type": "Feature",
  "properties": {
    "addr:full":"92 Lime Ave Mildura VIC 3500",
    "addr:housenumber":"92",
    "addr:postcode":"3500",
    "addr:street":"Lime Ave",
    "iso:country":"AU",
    "sg:address":"92 Lime Ave",
    "sg:city":"Mildura",
    "sg:classifiers":[
        {
            "category":"Banks & Credit Unions",
            "subcategory":"Bank",
            "type":"Services"
        }
    ],
    "sg:phone":"+61 3 5021 5101",
    "sg:postcode":"3500",
    "sg:province":"VIC",
    "sg:tags":[
        "broker",
        "mortgage"
    ],
    "wof:name":"Mildura Home Loans",
    "wof:placetype":"venue"
},
  "geometry": {"coordinates":[142.158035278,-34.1835479736],"type":"Point"}
}