{
  "type": "Feature",
  "properties": {
    "addr:full":"8-10 Swanpool Ave Chelsea VIC 3196",
    "addr:housenumber":"8-10",
    "addr:postcode":"3196",
    "addr:street":"Swanpool Ave",
    "iso:country":"AU",
    "sg:address":"8-10 Swanpool Ave",
    "sg:city":"Chelsea",
    "sg:classifiers":[
        {
            "category":"Recreation",
            "type":"Entertainment"
        }
    ],
    "sg:phone":"+61 3 9772 6205",
    "sg:postcode":"3196",
    "sg:province":"VIC",
    "sg:tags":[
        "children's",
        "play",
        "programme"
    ],
    "wof:name":"Swanpool Ave Playgroup",
    "wof:placetype":"venue"
},
  "geometry": {"coordinates":[145.11601257300001,-38.0468292236],"type":"Point"}
}