{
  "type": "Feature",
  "properties": {
    "addr:full":"Cnr Milton Rd & Croydon St Toowong QLD 4066",
    "addr:postcode":"4066",
    "addr:street":"Cnr Milton Rd & Croydon St",
    "iso:country":"AU",
    "sg:address":"Cnr Milton Rd & Croydon St",
    "sg:city":"Toowong",
    "sg:classifiers":[
        {
            "category":"Restaurant",
            "type":"Food & Drink"
        }
    ],
    "sg:phone":"+61 7 3371 1744",
    "sg:postcode":"4066",
    "sg:province":"QLD",
    "sg:tags":[
        "pizza"
    ],
    "wof:name":"Eagle Boys Pizza",
    "wof:placetype":"venue"
},
  "geometry": {"coordinates":[152.98562622099999,-27.4785041809],"type":"Point"}
}