{
  "type": "Feature",
  "properties": {
    "iso:country":"AU",
    "sg:address":"51 Vivian St",
    "sg:city":"Inverell",
    "sg:classifiers":[
        {
            "category":"Communications",
            "subcategory":"Film & Video Production",
            "type":"Services"
        }
    ],
    "sg:phone":"+61 2 6721 2111",
    "sg:postcode":"2360",
    "sg:province":"NSW",
    "sg:tags":[
        "dvd",
        "library"
    ],
    "wof:name":"Video Ezy",
    "wof:placetype":"venue"
},
  "geometry": {"coordinates":[151.11468505900001,-29.7758293152],"type":"Point"}
}