{
  "type": "Feature",
  "properties": {
    "iso:country":"AU",
    "sg:address":"41 Hannam St",
    "sg:city":"Wynnum North",
    "sg:classifiers":[
        {
            "category":"Building & Trades",
            "subcategory":"Plumbing",
            "type":"Services"
        }
    ],
    "sg:phone":"+61 7 3396 6828",
    "sg:postcode":"4178",
    "sg:province":"QLD",
    "sg:tags":[
        "plumber",
        "gasfitters"
    ],
    "wof:name":"Farquharson A L",
    "wof:placetype":"venue"
},
  "geometry": {"coordinates":[153.157913208,-27.4319591522],"type":"Point"}
}