{
  "type": "Feature",
  "properties": {
    "addr:full":"9/ 8 Market St Box Hill VIC 3128",
    "addr:housenumber":"/ 8",
    "addr:postcode":"3128",
    "addr:street":"Market St",
    "iso:country":"AU",
    "sg:address":"9/ 8 Market St",
    "sg:city":"Box Hill",
    "sg:classifiers":[
        {
            "category":"Professional",
            "subcategory":"Accounting & Tax Preparation",
            "type":"Services"
        }
    ],
    "sg:phone":"+61 3 9899 8688",
    "sg:postcode":"3128",
    "sg:province":"VIC",
    "sg:tags":[
        "consultant",
        "taxation"
    ],
    "wof:name":"Lee E H & Co Pty Ltd",
    "wof:placetype":"venue"
},
  "geometry": {"coordinates":[145.122390747,-37.8184127808],"type":"Point"}
}