{
  "type": "Feature",
  "properties": {
    "addr:full":"66 Wingewarra St Dubbo NSW 2830",
    "addr:housenumber":"66",
    "addr:postcode":"2830",
    "addr:street":"Wingewarra St",
    "iso:country":"AU",
    "sg:address":"66 Wingewarra St",
    "sg:city":"Dubbo",
    "sg:classifiers":[
        {
            "category":"Sports & Exercise",
            "subcategory":"Gym",
            "type":"Entertainment"
        }
    ],
    "sg:phone":"+61 2 6884 3443",
    "sg:postcode":"2830",
    "sg:province":"NSW",
    "sg:tags":[
        "health",
        "fitness"
    ],
    "wof:name":"Inside Out Health & Fitness",
    "wof:placetype":"venue"
},
  "geometry": {"coordinates":[148.601394653,-32.2489013672],"type":"Point"}
}