{
  "type": "Feature",
  "properties": {
    "addr:full":"Balfe St Paramatta Park Cairns QLD 4870",
    "addr:postcode":"4870",
    "addr:street":"Balfe St Paramatta",
    "iso:country":"AU",
    "sg:address":"Balfe St Paramatta Park",
    "sg:city":"Cairns",
    "sg:classifiers":[
        {
            "category":"Education",
            "subcategory":"School",
            "type":"Public Place"
        }
    ],
    "sg:phone":"+61 7 4042 8128",
    "sg:postcode":"4870",
    "sg:province":"QLD",
    "sg:tags":[
        "state",
        "except",
        "nsw"
    ],
    "wof:name":"Parramatta Preschool",
    "wof:placetype":"venue"
},
  "geometry": {"coordinates":[145.763381958,-16.9252758026],"type":"Point"}
}