{
  "type": "Feature",
  "properties": {
    "iso:country":"AU",
    "sg:address":"Factory 2, 54- 60 Vesper Drv",
    "sg:city":"Narre Warren",
    "sg:classifiers":[
        {
            "category":"Building & Trades",
            "subcategory":"Construction",
            "type":"Services"
        }
    ],
    "sg:phone":"+61 3 9705 6956",
    "sg:postcode":"3805",
    "sg:province":"VIC",
    "sg:tags":[
        "decking",
        "contractor"
    ],
    "wof:name":"Aust Decking Co.",
    "wof:placetype":"venue"
},
  "geometry": {"coordinates":[145.29335,-38.019577],"type":"Point"}
}