{
  "type": "Feature",
  "properties": {
    "addr:full":"PO Box 1865+ Southport Delivery Centre QLD 4215",
    "addr:housenumber":"+",
    "addr:postcode":"4215",
    "iso:country":"AU",
    "sg:address":"PO Box 1865+",
    "sg:city":"Southport Delivery Centre",
    "sg:classifiers":[
        {
            "category":"Organizations",
            "subcategory":"Professional Association",
            "type":"Services"
        }
    ],
    "sg:phone":"+61 7 3852 5008",
    "sg:postcode":"4215",
    "sg:province":"QLD",
    "sg:tags":[
        "web",
        "internet"
    ],
    "wof:name":"Cybermarket.com.au",
    "wof:placetype":"venue"
},
  "geometry": {"coordinates":[153.39855957,-27.9664897919],"type":"Point"}
}