{
  "type": "Feature",
  "properties": {
    "iso:country":"AU",
    "sg:address":"63 Haig St",
    "sg:city":"Southbank",
    "sg:classifiers":[
        {
            "category":"Professional",
            "subcategory":"Testing Lab",
            "type":"Services"
        }
    ],
    "sg:phone":"+61 3 9690 6988",
    "sg:postcode":"3006",
    "sg:province":"VIC",
    "sg:tags":[
        "inspection"
    ],
    "wof:name":"Tubemakers Pipelines Research Centre",
    "wof:placetype":"venue"
},
  "geometry": {"coordinates":[144.95687866200001,-37.8274612427],"type":"Point"}
}