{
  "type": "Feature",
  "properties": {
    "addr:full":"PO Box 342 Braeside VIC 3195",
    "addr:postcode":"3195",
    "iso:country":"AU",
    "sg:address":"PO Box 342",
    "sg:city":"Braeside",
    "sg:classifiers":[
        {
            "category":"Utilities",
            "subcategory":"Electric",
            "type":"Services"
        }
    ],
    "sg:phone":"+61 3 9587 4906",
    "sg:postcode":"3195",
    "sg:province":"VIC",
    "sg:tags":[
        "electrical",
        "contractor"
    ],
    "wof:name":"Kingston Electrical Services",
    "wof:placetype":"venue"
},
  "geometry": {"coordinates":[145.11375427199999,-38.0084381104],"type":"Point"}
}