{
  "type": "Feature",
  "properties": {
    "addr:full":"1 Resolution Drv Unanderra NSW 2526",
    "addr:housenumber":"1",
    "addr:postcode":"2526",
    "addr:street":"Resolution Drv",
    "iso:country":"AU",
    "sg:address":"1 Resolution Drv",
    "sg:city":"Unanderra",
    "sg:classifiers":[
        {
            "category":"Shopping",
            "subcategory":"Computers & Home Electronics",
            "type":"Retail Goods"
        }
    ],
    "sg:phone":"+61 2 4272 1922",
    "sg:postcode":"2526",
    "sg:province":"NSW",
    "sg:tags":[
        "wholesaler",
        "equipment",
        "electronic",
        "mfrs"
    ],
    "wof:name":"Macelec (Excell Control)",
    "wof:placetype":"venue"
},
  "geometry": {"coordinates":[150.851730347,-34.4583091736],"type":"Point"}
}