{
  "type": "Feature",
  "properties": {
    "iso:country":"AU",
    "sg:address":"Vale St",
    "sg:city":"Portland",
    "sg:classifiers":[
        {
            "category":"Education",
            "subcategory":"School",
            "type":"Public Place"
        }
    ],
    "sg:phone":"+61 2 6355 5233",
    "sg:postcode":"2847",
    "sg:province":"NSW",
    "sg:tags":[
        "state",
        "-",
        "nsw"
    ],
    "wof:name":"Portland Central School",
    "wof:placetype":"venue"
},
  "geometry": {"coordinates":[149.98039199999999,-33.354034],"type":"Point"}
}