{
  "type": "Feature",
  "properties": {
    "addr:full":"Suite 307, 685 Burke Rd Camberwell VIC 3124",
    "addr:housenumber":"685",
    "addr:postcode":"3124",
    "addr:street":"Burke Rd",
    "iso:country":"AU",
    "sg:address":"Suite 307, 685 Burke Rd",
    "sg:city":"Camberwell",
    "sg:classifiers":[
        {
            "category":"Health Services",
            "subcategory":"Doctor",
            "type":"Services"
        }
    ],
    "sg:phone":"+61 1300 730 100",
    "sg:postcode":"3124",
    "sg:province":"VIC",
    "sg:tags":[
        "medical",
        "practitioner"
    ],
    "wof:name":"Vein Care",
    "wof:placetype":"venue"
},
  "geometry": {"coordinates":[145.056182861,-37.8331413269],"type":"Point"}
}