{
  "type": "Feature",
  "properties": {
    "addr:full":"41 Beachcomber Drv Byron Bay NSW 2481",
    "addr:housenumber":"41",
    "addr:postcode":"2481",
    "addr:street":"Beachcomber Drv",
    "iso:country":"AU",
    "sg:address":"41 Beachcomber Drv",
    "sg:city":"Byron Bay",
    "sg:classifiers":[
        {
            "category":"Professional",
            "subcategory":"Art Services",
            "type":"Services"
        }
    ],
    "sg:phone":"+61 2 6680 7378",
    "sg:postcode":"2481",
    "sg:province":"NSW",
    "sg:tags":[
        "arranger",
        "music",
        "composer"
    ],
    "wof:name":"Labyrinth Studios",
    "wof:placetype":"venue"
},
  "geometry": {"coordinates":[153.62286376899999,-28.656703949],"type":"Point"}
}