{
  "type": "Feature",
  "properties": {
    "iso:country":"AU",
    "sg:address":"60 Craig St",
    "sg:city":"Wishart",
    "sg:classifiers":[
        {
            "category":"Utilities",
            "subcategory":"Electric",
            "type":"Services"
        }
    ],
    "sg:phone":"+61 7 3349 0668",
    "sg:postcode":"4122",
    "sg:province":"QLD",
    "sg:tags":[
        "electrical",
        "contractor"
    ],
    "wof:name":"Sampson B.J. Pty Ltd",
    "wof:placetype":"venue"
},
  "geometry": {"coordinates":[153.09817504899999,-27.5615997314],"type":"Point"}
}