{
  "type": "Feature",
  "properties": {
    "addr:full":"Cnr Somerset Rd & Capricorn Hwy Gracemere QLD 4702",
    "addr:postcode":"4702",
    "addr:street":"Cnr Somerset Rd & Capricorn Hwy",
    "iso:country":"AU",
    "sg:address":"Cnr Somerset Rd & Capricorn Hwy",
    "sg:city":"Gracemere",
    "sg:classifiers":[
        {
            "category":"Autos & Motor Vehicles",
            "subcategory":"Auto Supplies",
            "type":"Retail Goods"
        }
    ],
    "sg:phone":"+61 7 4933 2444",
    "sg:postcode":"4702",
    "sg:province":"QLD",
    "sg:tags":[
        "equipment",
        "part",
        "truck"
    ],
    "wof:name":"Zebra Wrecking Co. Pty Ltd",
    "wof:placetype":"venue"
},
  "geometry": {"coordinates":[150.43955993599999,-23.4451541901],"type":"Point"}
}