{
  "type": "Feature",
  "properties": {
    "addr:full":"Rosamel Rd Australind WA 6233",
    "addr:postcode":"6233",
    "addr:street":"Rosamel Rd",
    "iso:country":"AU",
    "sg:address":"Rosamel Rd",
    "sg:city":"Australind",
    "sg:classifiers":[
        {
            "category":"Wholesale",
            "subcategory":"Meat",
            "type":"Manufacturing & Wholesale Goods"
        }
    ],
    "sg:phone":"+61 8 9797 4100",
    "sg:postcode":"6233",
    "sg:province":"WA",
    "sg:tags":[
        "abattoir"
    ],
    "wof:name":"Goodchild Abattoirs Pty Ltd",
    "wof:placetype":"venue"
},
  "geometry": {"coordinates":[115.735519,-33.212128],"type":"Point"}
}