{
  "type": "Feature",
  "properties": {
    "addr:full":"55 Junction Rd Moorebank NSW 2170",
    "addr:housenumber":"55",
    "addr:postcode":"2170",
    "addr:street":"Junction Rd",
    "iso:country":"AU",
    "sg:address":"55 Junction Rd",
    "sg:city":"Moorebank",
    "sg:classifiers":[
        {
            "category":"Retail",
            "subcategory":"Laundry & Dry Cleaning",
            "type":"Services"
        }
    ],
    "sg:phone":"+61 2 9601 2806",
    "sg:postcode":"2170",
    "sg:province":"NSW",
    "sg:tags":[
        "cloth",
        "supply"
    ],
    "wof:name":"R.S.N.M Rags",
    "wof:placetype":"venue"
},
  "geometry": {"coordinates":[150.94683837900001,-33.938369751],"type":"Point"}
}