{
  "type": "Feature",
  "properties": {
    "iso:country":"AU",
    "sg:address":"2/ 12 Federal Rd",
    "sg:city":"Kalgoorlie",
    "sg:classifiers":[
        {
            "category":"Shopping",
            "subcategory":"Computers & Home Electronics",
            "type":"Retail Goods"
        }
    ],
    "sg:phone":"+61 8 9080 1999",
    "sg:postcode":"6430",
    "sg:province":"WA",
    "sg:tags":[
        "hardware",
        "equipment"
    ],
    "wof:name":"ComputerCORP",
    "wof:placetype":"venue"
},
  "geometry": {"coordinates":[121.48654174799999,-30.7600631714],"type":"Point"}
}