{
  "type": "Feature",
  "properties": {
    "addr:full":"82 High St Northcote VIC 3070",
    "addr:housenumber":"82",
    "addr:postcode":"3070",
    "addr:street":"High St",
    "iso:country":"AU",
    "sg:address":"82 High St",
    "sg:city":"Northcote",
    "sg:classifiers":[
        {
            "category":"Professional",
            "subcategory":"Detective & Security Services",
            "type":"Services"
        }
    ],
    "sg:phone":"+61 3 9486 5565",
    "sg:postcode":"3070",
    "sg:province":"VIC",
    "sg:tags":[
        "guard",
        "patrol"
    ],
    "wof:name":"Crown Security Services",
    "wof:placetype":"venue"
},
  "geometry": {"coordinates":[144.99700899999999,-37.780293],"type":"Point"}
}