{
  "type": "Feature",
  "properties": {
    "iso:country":"AU",
    "sg:address":"378 Sydney Rd",
    "sg:city":"Balgowlah",
    "sg:classifiers":[
        {
            "category":"Cafe",
            "type":"Food & Drink"
        }
    ],
    "sg:phone":"+61 2 9948 7600",
    "sg:postcode":"2093",
    "sg:province":"NSW",
    "wof:name":"Full Of Beans Cafe",
    "wof:placetype":"venue"
},
  "geometry": {"coordinates":[151.263305664,-33.794002533],"type":"Point"}
}