{
  "type": "Feature",
  "properties": {
    "addr:full":"Level 1/ 84 Moorabool St Geelong VIC 3220",
    "addr:housenumber":"/ 84",
    "addr:postcode":"3220",
    "addr:street":"Moorabool St",
    "iso:country":"AU",
    "sg:address":"Level 1/ 84 Moorabool St",
    "sg:city":"Geelong",
    "sg:classifiers":[
        {
            "category":"Personal",
            "subcategory":"Beauty Salon",
            "type":"Services"
        }
    ],
    "sg:phone":"+61 3 5222 8441",
    "sg:postcode":"3220",
    "sg:province":"VIC",
    "sg:tags":[
        "hair",
        "treatment",
        "replacement"
    ],
    "wof:name":"The Hair Institute",
    "wof:placetype":"venue"
},
  "geometry": {"coordinates":[144.360657,-38.147064],"type":"Point"}
}