{
  "type": "Feature",
  "properties": {
    "iso:country":"AU",
    "sg:address":"95 Market St",
    "sg:city":"Mudgee",
    "sg:classifiers":[
        {
            "category":"Retail",
            "subcategory":"Laundry & Dry Cleaning",
            "type":"Services"
        }
    ],
    "sg:phone":"+61 2 6372 1746",
    "sg:postcode":"2850",
    "sg:province":"NSW",
    "wof:name":"Barclay Dry Cleaners",
    "wof:placetype":"venue"
},
  "geometry": {"coordinates":[149.57536300000001,-32.587692],"type":"Point"}
}