{
  "type": "Feature",
  "properties": {
    "addr:full":"124 Huon Creek Rd Wodonga VIC 3690",
    "addr:housenumber":"124",
    "addr:postcode":"3690",
    "addr:street":"Huon Creek Rd",
    "iso:country":"AU",
    "sg:address":"124 Huon Creek Rd",
    "sg:city":"Wodonga",
    "sg:classifiers":[
        {
            "category":"Professional",
            "subcategory":"Management & Consulting",
            "type":"Services"
        }
    ],
    "sg:phone":"+61 2 6056 1515",
    "sg:postcode":"3690",
    "sg:province":"VIC",
    "sg:tags":[
        "consultant"
    ],
    "wof:name":"Patrilla Creations",
    "wof:placetype":"venue"
},
  "geometry": {"coordinates":[146.89125060999999,-36.1147155762],"type":"Point"}
}