{
  "type": "Feature",
  "properties": {
    "addr:full":"Shop 2/ 270 Sandy Point Rd Salamander Bay NSW 2317",
    "addr:housenumber":"shop 2 / 270",
    "addr:postcode":"2317",
    "addr:street":"Sandy Point Rd",
    "iso:country":"AU",
    "sg:address":"Shop 2/ 270 Sandy Point Rd",
    "sg:city":"Salamander Bay",
    "sg:classifiers":[
        {
            "category":"Communications",
            "subcategory":"Film & Video Production",
            "type":"Services"
        }
    ],
    "sg:phone":"+61 2 4981 2006",
    "sg:postcode":"2317",
    "sg:province":"NSW",
    "sg:tags":[
        "dvd",
        "library"
    ],
    "wof:name":"Video Ezy",
    "wof:placetype":"venue"
},
  "geometry": {"coordinates":[152.10993999999999,-32.733707],"type":"Point"}
}