{
  "type": "Feature",
  "properties": {
    "addr:full":"84 Glenfarne St Bexley NSW 2207",
    "addr:housenumber":"84",
    "addr:postcode":"2207",
    "addr:street":"Glenfarne St",
    "iso:country":"AU",
    "sg:address":"84 Glenfarne St",
    "sg:city":"Bexley",
    "sg:classifiers":[
        {
            "category":"Education",
            "subcategory":"Kindergarten",
            "type":"Public Place"
        }
    ],
    "sg:phone":"+61 2 9587 6889",
    "sg:postcode":"2207",
    "sg:province":"NSW",
    "sg:tags":[
        "pre-schools"
    ],
    "wof:name":"MLC Bexley Kindergarten",
    "wof:placetype":"venue"
},
  "geometry": {"coordinates":[151.118774,-33.958702],"type":"Point"}
}