{
  "type": "Feature",
  "properties": {
    "iso:country":"AU",
    "sg:address":"Manufacturing Plant , Cerium St",
    "sg:city":"Narangba",
    "sg:classifiers":[
        {
            "category":"Manufacturing",
            "subcategory":"Building Materials",
            "type":"Manufacturing & Wholesale Goods"
        }
    ],
    "sg:phone":"+61 7 3888 0403",
    "sg:postcode":"4504",
    "sg:province":"QLD",
    "sg:tags":[
        "concrete",
        "product"
    ],
    "wof:name":"Kallangar Concrete Products",
    "wof:placetype":"venue"
},
  "geometry": {"coordinates":[152.985305786,-27.1929550171],"type":"Point"}
}