{
  "type": "Feature",
  "properties": {
    "iso:country":"AU",
    "sg:address":"754c Pennant Hills Rd",
    "sg:city":"Carlingford",
    "sg:classifiers":[
        {
            "category":"Building & Trades",
            "subcategory":"Construction",
            "type":"Services"
        }
    ],
    "sg:phone":"+61 2 9873 4891",
    "sg:postcode":"2118",
    "sg:province":"NSW",
    "sg:tags":[
        "contractor"
    ],
    "wof:name":"Apec Developments Pty Ltd",
    "wof:placetype":"venue"
},
  "geometry": {"coordinates":[151.051071167,-33.7721557617],"type":"Point"}
}