{
  "type": "Feature",
  "properties": {
    "addr:full":"Teramby Rd Nelson Bay NSW 2315",
    "addr:postcode":"2315",
    "addr:street":"Teramby Rd",
    "iso:country":"AU",
    "sg:address":"Teramby Rd",
    "sg:city":"Nelson Bay",
    "sg:classifiers":[
        {
            "category":"Travel",
            "subcategory":"Travel Agent",
            "type":"Entertainment"
        }
    ],
    "sg:phone":"+61 2 4984 1844",
    "sg:postcode":"2315",
    "sg:province":"NSW",
    "sg:tags":[
        "tour",
        "holiday",
        "adventure"
    ],
    "wof:name":"Bill Knaggs Boat Hire",
    "wof:placetype":"venue"
},
  "geometry": {"coordinates":[152.144745,-32.720287],"type":"Point"}
}