{
  "type": "Feature",
  "properties": {
    "iso:country":"AU",
    "sg:address":"185 Gulnare Rd",
    "sg:city":"Bees Creek",
    "sg:classifiers":[
        {
            "category":"Banks & Credit Unions",
            "subcategory":"Bureau De Change",
            "type":"Services"
        }
    ],
    "sg:phone":"+61 8 8988 4114",
    "sg:postcode":"0822",
    "sg:province":"NT",
    "sg:tags":[
        "beekeeping",
        "supply"
    ],
    "wof:name":"Bees Creek Honey",
    "wof:placetype":"venue"
},
  "geometry": {"coordinates":[131.05586199999999,-12.584183],"type":"Point"}
}