{
  "type": "Feature",
  "properties": {
    "addr:full":"7 Doric St Scarborough WA 6019",
    "addr:housenumber":"7",
    "addr:postcode":"6019",
    "addr:street":"Doric St",
    "iso:country":"AU",
    "sg:address":"7 Doric St",
    "sg:city":"Scarborough",
    "sg:classifiers":[
        {
            "category":"Food & Beverages",
            "subcategory":"Supermarket",
            "type":"Retail Goods"
        }
    ],
    "sg:phone":"+61 8 9341 2247",
    "sg:postcode":"6019",
    "sg:province":"WA",
    "sg:tags":[
        "grocery",
        "store"
    ],
    "wof:name":"Doric Sreet Minimart",
    "wof:placetype":"venue"
},
  "geometry": {"coordinates":[115.772583008,-31.9050254822],"type":"Point"}
}