{
  "type": "Feature",
  "properties": {
    "addr:full":"2395 South Western Hwy Serpentine WA 6125",
    "addr:housenumber":"2395",
    "addr:postcode":"6125",
    "addr:street":"South Western Hwy",
    "iso:country":"AU",
    "sg:address":"2395 South Western Hwy",
    "sg:city":"Serpentine",
    "sg:classifiers":[
        {
            "category":"Retail",
            "subcategory":"Veterinary Services",
            "type":"Services"
        }
    ],
    "sg:phone":"+61 8 9525 2197",
    "sg:postcode":"6125",
    "sg:province":"WA",
    "sg:tags":[
        "surgeon"
    ],
    "wof:name":"Serpentine Veterinary Hospital",
    "wof:placetype":"venue"
},
  "geometry": {"coordinates":[115.994003296,-32.3595199585],"type":"Point"}
}