{
  "type": "Feature",
  "properties": {
    "addr:full":"27 Marigold St Revesby NSW 2212",
    "addr:housenumber":"27",
    "addr:postcode":"2212",
    "addr:street":"Marigold St",
    "iso:country":"AU",
    "sg:address":"27 Marigold St",
    "sg:city":"Revesby",
    "sg:classifiers":[
        {
            "category":"Home & Garden",
            "subcategory":"Building Materials",
            "type":"Retail Goods"
        }
    ],
    "sg:phone":"+61 2 9771 6722",
    "sg:postcode":"2212",
    "sg:province":"NSW",
    "sg:tags":[
        "supply"
    ],
    "wof:name":"Cheaper Building Supplies Pty Ltd",
    "wof:placetype":"venue"
},
  "geometry": {"coordinates":[150.99951200000001,-33.936508],"type":"Point"}
}