{
  "type": "Feature",
  "properties": {
    "addr:full":"7 Kelray Pl Asquith NSW 2077",
    "addr:housenumber":"7",
    "addr:postcode":"2077",
    "addr:street":"Kelray Pl",
    "iso:country":"AU",
    "sg:address":"7 Kelray Pl",
    "sg:city":"Asquith",
    "sg:classifiers":[
        {
            "category":"Shopping",
            "subcategory":"Computers & Home Electronics",
            "type":"Retail Goods"
        }
    ],
    "sg:phone":"+61 2 9476 0788",
    "sg:postcode":"2077",
    "sg:province":"NSW",
    "sg:tags":[
        "hardware",
        "equipment"
    ],
    "wof:name":"Pearl Computer Pty Ltd",
    "wof:placetype":"venue"
},
  "geometry": {"coordinates":[151.11007690400001,-33.6946754456],"type":"Point"}
}