{
  "type": "Feature",
  "properties": {
    "iso:country":"AU",
    "sg:address":"284 Main Rd",
    "sg:city":"Cardiff",
    "sg:classifiers":[
        {
            "category":"Banks & Credit Unions",
            "subcategory":"Financial Services",
            "type":"Services"
        }
    ],
    "sg:phone":"+61 13 19 87",
    "sg:postcode":"2285",
    "sg:province":"NSW",
    "sg:tags":[
        "building",
        "society"
    ],
    "wof:name":"Newcastle Permanent Building Society Ltd",
    "wof:placetype":"venue"
},
  "geometry": {"coordinates":[151.65985107399999,-32.9399337769],"type":"Point"}
}