{
  "type": "Feature",
  "properties": {
    "iso:country":"AU",
    "sg:address":"Fac 1",
    "sg:city":"/49 Merola Way Campbellfield",
    "sg:classifiers":[
        {
            "category":"Utilities",
            "subcategory":"Electric",
            "type":"Services"
        }
    ],
    "sg:phone":"+61 3 9357 8816",
    "sg:postcode":"3061",
    "sg:province":"VIC",
    "sg:tags":[
        "electrical",
        "contractor"
    ],
    "wof:name":"EES Electrics Pty Ltd",
    "wof:placetype":"venue"
},
  "geometry": {"coordinates":[144.960327148,-37.6544494629],"type":"Point"}
}