{
  "type": "Feature",
  "properties": {
    "iso:country":"AU",
    "sg:address":"1st Floor Hardy Bros Building 245 Albert St",
    "sg:city":"Brisbane City",
    "sg:classifiers":[
        {
            "category":"Health Services",
            "subcategory":"Dentist",
            "type":"Services"
        }
    ],
    "sg:phone":"+61 7 3229 4121",
    "sg:postcode":"4000",
    "sg:province":"QLD",
    "wof:name":"Angelo Nicholas",
    "wof:placetype":"venue"
},
  "geometry": {"coordinates":[153.0259552,-27.4701690674],"type":"Point"}
}