{
  "type": "Feature",
  "properties": {
    "addr:full":"15/ 81 Waratah Ave Dalkeith WA 6009",
    "addr:housenumber":"15 / 81",
    "addr:postcode":"6009",
    "addr:street":"Waratah Ave",
    "iso:country":"AU",
    "sg:address":"15/ 81 Waratah Ave",
    "sg:city":"Dalkeith",
    "sg:classifiers":[
        {
            "category":"Health Services",
            "subcategory":"Health Practitioner",
            "type":"Services"
        }
    ],
    "sg:phone":"+61 8 9383 2824",
    "sg:postcode":"6009",
    "sg:province":"WA",
    "sg:tags":[
        "psychotherapist"
    ],
    "wof:name":"Mummert, Jennifer",
    "wof:placetype":"venue"
},
  "geometry": {"coordinates":[115.798332,-31.994621],"type":"Point"}
}