{
  "type": "Feature",
  "properties": {
    "addr:full":"The Specialist Medical Centre, 1 Newland St Bondi Junction NSW 2022",
    "addr:housenumber":"1",
    "addr:postcode":"2022",
    "addr:street":"Newland St",
    "iso:country":"AU",
    "sg:address":"The Specialist Medical Centre, 1 Newland St",
    "sg:city":"Bondi Junction",
    "sg:classifiers":[
        {
            "category":"Health Services",
            "subcategory":"Doctor",
            "type":"Services"
        }
    ],
    "sg:phone":"+61 2 9369 3666",
    "sg:postcode":"2022",
    "sg:province":"NSW",
    "sg:tags":[
        "medical",
        "practitioner"
    ],
    "wof:name":"Flynn Peter",
    "wof:placetype":"venue"
},
  "geometry": {"coordinates":[151.24723815900001,-33.8920059204],"type":"Point"}
}