{
  "type": "Feature",
  "properties": {
    "iso:country":"AU",
    "sg:address":"PO Box 4227",
    "sg:city":"Kirwan",
    "sg:classifiers":[
        {
            "category":"Building & Trades",
            "subcategory":"Construction",
            "type":"Services"
        }
    ],
    "sg:phone":"+61 417 763 218",
    "sg:postcode":"4817",
    "sg:province":"QLD",
    "sg:tags":[
        "contractor"
    ],
    "wof:name":"Ramsbotham G B & D E",
    "wof:placetype":"venue"
},
  "geometry": {"coordinates":[146.735168,-19.30369],"type":"Point"}
}