{
  "type": "Feature",
  "properties": {
    "iso:country":"AU",
    "sg:address":"1525 High St",
    "sg:city":"Glen Iris",
    "sg:classifiers":[
        {
            "category":"Organizations",
            "subcategory":"Non-profit Organization",
            "type":"Services"
        }
    ],
    "sg:phone":"+61 3 9886 9222",
    "sg:postcode":"3146",
    "sg:province":"VIC",
    "sg:tags":[
        "support",
        "disability",
        "organisation"
    ],
    "wof:name":"Eastwork",
    "wof:placetype":"venue"
},
  "geometry": {"coordinates":[145.05764770499999,-37.8599128723],"type":"Point"}
}