{
  "type": "Feature",
  "properties": {
    "addr:full":"189 Old Southern Rd Nowra NSW 2541",
    "addr:housenumber":"189",
    "addr:postcode":"2541",
    "addr:street":"Old Southern Rd",
    "iso:country":"AU",
    "sg:address":"189 Old Southern Rd",
    "sg:city":"Nowra",
    "sg:classifiers":[
        {
            "category":"Health Services",
            "subcategory":"Nursing And Care Facility",
            "type":"Services"
        }
    ],
    "sg:phone":"+61 2 4421 3744",
    "sg:postcode":"2541",
    "sg:province":"NSW",
    "sg:tags":[
        "home"
    ],
    "wof:name":"Anglicare Chesalon Nursing Home",
    "wof:placetype":"venue"
},
  "geometry": {"coordinates":[150.621627808,-34.8953514099],"type":"Point"}
}