{
  "type": "Feature",
  "properties": {
    "iso:country":"AU",
    "sg:address":"3B Rain Pl",
    "sg:city":"Bayswater",
    "sg:classifiers":[
        {
            "category":"Arts & Performance",
            "subcategory":"Music",
            "type":"Entertainment"
        }
    ],
    "sg:phone":"+61 419 853 775",
    "sg:postcode":"6053",
    "sg:province":"WA",
    "sg:tags":[
        "mobile",
        "jockey",
        "disc"
    ],
    "wof:name":"Audiowave Sound Entertainment",
    "wof:placetype":"venue"
},
  "geometry": {"coordinates":[115.904846191,-31.9247684479],"type":"Point"}
}