{
  "type": "Feature",
  "properties": {
    "addr:full":"Showroom 15 Scanlan St Bentleigh East VIC 3165",
    "addr:housenumber":"15",
    "addr:postcode":"3165",
    "addr:street":"Scanlan St",
    "iso:country":"AU",
    "sg:address":"Showroom 15 Scanlan St",
    "sg:city":"Bentleigh East",
    "sg:classifiers":[
        {
            "category":"Professional",
            "subcategory":"Management & Consulting",
            "type":"Services"
        }
    ],
    "sg:phone":"+61 3 9563 7988",
    "sg:postcode":"3165",
    "sg:province":"VIC",
    "sg:tags":[
        "consultant",
        "energy"
    ],
    "wof:name":"A-Temp Energy Ratings",
    "wof:placetype":"venue"
},
  "geometry": {"coordinates":[145.06971740700001,-37.9367332458],"type":"Point"}
}