{
  "type": "Feature",
  "properties": {
    "addr:full":"34 Dorothy Rd Whitsundays QLD 4802",
    "addr:housenumber":"34",
    "addr:postcode":"4802",
    "addr:street":"Dorothy Rd",
    "iso:country":"AU",
    "sg:address":"34 Dorothy Rd",
    "sg:city":"Whitsundays",
    "sg:classifiers":[
        {
            "category":"Social Services",
            "subcategory":"Child Care",
            "type":"Services"
        }
    ],
    "sg:phone":"+61 7 4948 3989",
    "sg:postcode":"4802",
    "sg:province":"QLD",
    "wof:name":"VIP Kids Australia Pty Ltd",
    "wof:placetype":"venue"
},
  "geometry": {"coordinates":[148.65602111800001,-20.2577095032],"type":"Point"}
}