{
  "type": "Feature",
  "properties": {
    "iso:country":"AU",
    "sg:address":"49 Glen Osmond Rd",
    "sg:city":"Eastwood",
    "sg:classifiers":[
        {
            "category":"Health Services",
            "subcategory":"Doctor",
            "type":"Services"
        }
    ],
    "sg:phone":"+61 8 8271 5678",
    "sg:postcode":"5063",
    "sg:province":"SA",
    "sg:tags":[
        "medical",
        "practitioner"
    ],
    "wof:name":"Smith Donald S",
    "wof:placetype":"venue"
},
  "geometry": {"coordinates":[138.62008667000001,-34.9430809021],"type":"Point"}
}