{
  "type": "Feature",
  "properties": {
    "addr:full":"Shop 2 / 111 Grant St Alexandra VIC 3714",
    "addr:housenumber":"shop 2 / 111",
    "addr:postcode":"3714",
    "addr:street":"Grant St",
    "iso:country":"AU",
    "sg:address":"Shop 2 / 111 Grant St",
    "sg:city":"Alexandra",
    "sg:classifiers":[
        {
            "category":"Utilities",
            "subcategory":"Water",
            "type":"Services"
        }
    ],
    "sg:phone":"+61 3 5772 1605",
    "sg:postcode":"3714",
    "sg:province":"VIC",
    "sg:tags":[
        "hot",
        "system"
    ],
    "wof:name":"Acks Merchandising & Plumbing Pty. Ltd.",
    "wof:placetype":"venue"
},
  "geometry": {"coordinates":[145.70838928200001,-37.1923713684],"type":"Point"}
}