{
  "type": "Feature",
  "properties": {
    "addr:full":"14 McLachlan St Darwin NT 0800",
    "addr:housenumber":"14",
    "addr:postcode":"nt 0800",
    "addr:street":"Mclachlan St",
    "iso:country":"AU",
    "sg:address":"14 McLachlan St",
    "sg:city":"Darwin",
    "sg:classifiers":[
        {
            "category":"Autos & Motor Vehicles",
            "subcategory":"Automobile Sales",
            "type":"Retail Goods"
        }
    ],
    "sg:phone":"+61 8 8981 3397",
    "sg:postcode":"0800",
    "sg:province":"NT",
    "sg:tags":[
        "car",
        "used"
    ],
    "wof:name":"Dustins Auto Sales",
    "wof:placetype":"venue"
},
  "geometry": {"coordinates":[130.83782959000001,-12.4596586227],"type":"Point"}
}