{
  "type": "Feature",
  "properties": {
    "addr:full":"91 Antill St Downer ACT 2602",
    "addr:housenumber":"91",
    "addr:postcode":"2602",
    "addr:street":"Antill St",
    "iso:country":"AU",
    "sg:address":"91 Antill St",
    "sg:city":"Downer",
    "sg:classifiers":[
        {
            "category":"Real Estate",
            "subcategory":"Real Estate Services",
            "type":"Services"
        }
    ],
    "sg:phone":"+61 2 6257 9158",
    "sg:postcode":"2602",
    "sg:province":"ACT",
    "sg:tags":[
        "valuer"
    ],
    "wof:name":"Colin Davies & Associates",
    "wof:placetype":"venue"
},
  "geometry": {"coordinates":[149.14195251500001,-35.2485771179],"type":"Point"}
}