{
  "type": "Feature",
  "properties": {
    "addr:full":"21 Bridge Rd North Ryde NSW 2113",
    "addr:housenumber":"21",
    "addr:postcode":"2113",
    "addr:street":"Bridge Rd",
    "iso:country":"AU",
    "sg:address":"21 Bridge Rd",
    "sg:city":"North Ryde",
    "sg:classifiers":[
        {
            "category":"Building & Trades",
            "subcategory":"Construction",
            "type":"Services"
        }
    ],
    "sg:phone":"+61 2 9887 2665",
    "sg:postcode":"2113",
    "sg:province":"NSW",
    "sg:tags":[
        "renovation",
        "alterations",
        "extension",
        "contractor"
    ],
    "wof:name":"Norman T D",
    "wof:placetype":"venue"
},
  "geometry": {"coordinates":[151.11233520499999,-33.7955856323],"type":"Point"}
}