{
  "type": "Feature",
  "properties": {
    "iso:country":"AU",
    "sg:address":"PO Box 775",
    "sg:city":"Warragul",
    "sg:classifiers":[
        {
            "category":"Utilities",
            "subcategory":"Telephone",
            "type":"Services"
        }
    ],
    "sg:phone":"+61 3 5623 5552",
    "sg:postcode":"3820",
    "sg:province":"VIC",
    "sg:tags":[
        "installation",
        "system",
        "maintenance"
    ],
    "wof:name":"R.N.R. Electronics",
    "wof:placetype":"venue"
},
  "geometry": {"coordinates":[145.938614,-38.143978],"type":"Point"}
}