{
  "type": "Feature",
  "properties": {
    "iso:country":"AU",
    "sg:address":"PO Box 10",
    "sg:city":"Woollahra",
    "sg:classifiers":[
        {
            "category":"Professional",
            "subcategory":"Accounting & Tax Preparation",
            "type":"Services"
        }
    ],
    "sg:phone":"+61 417 714 001",
    "sg:postcode":"2025",
    "sg:province":"NSW",
    "sg:tags":[
        "bookkeeping"
    ],
    "wof:name":"Mobile Business Accounts",
    "wof:placetype":"venue"
},
  "geometry": {"coordinates":[151.24412536599999,-33.8857917786],"type":"Point"}
}