{
  "type": "Feature",
  "properties": {
    "addr:full":"81 Donald Ave Umina NSW 2257",
    "addr:housenumber":"81",
    "addr:postcode":"2257",
    "addr:street":"Donald Ave",
    "iso:country":"AU",
    "sg:address":"81 Donald Ave",
    "sg:city":"Umina",
    "sg:classifiers":[
        {
            "category":"Building & Trades",
            "subcategory":"Plumbing",
            "type":"Services"
        }
    ],
    "sg:phone":"+61 2 4341 9604",
    "sg:postcode":"2257",
    "sg:province":"NSW",
    "sg:tags":[
        "plumber",
        "gasfitters"
    ],
    "wof:name":"Knock D J",
    "wof:placetype":"venue"
},
  "geometry": {"coordinates":[151.320236206,-33.5092048645],"type":"Point"}
}