{
  "type": "Feature",
  "properties": {
    "iso:country":"AU",
    "sg:address":"29 Monash Ave",
    "sg:city":"Olinda",
    "sg:classifiers":[
        {
            "category":"Professional",
            "subcategory":"Art Services",
            "type":"Services"
        }
    ],
    "sg:phone":"+61 3 9755 1996",
    "sg:postcode":"3788",
    "sg:province":"VIC",
    "sg:tags":[
        "sculptor"
    ],
    "wof:name":"Elaine S Pullum",
    "wof:placetype":"venue"
},
  "geometry": {"coordinates":[145.364532,-37.854939],"type":"Point"}
}