{
  "type": "Feature",
  "properties": {
    "addr:full":"1/ 109 Canterbury Rd Heathmont VIC 3135",
    "addr:housenumber":"/ 109",
    "addr:postcode":"3135",
    "addr:street":"Canterbury Rd",
    "iso:country":"AU",
    "sg:address":"1/ 109 Canterbury Rd",
    "sg:city":"Heathmont",
    "sg:classifiers":[
        {
            "category":"Wholesale",
            "subcategory":"Apparel",
            "type":"Manufacturing & Wholesale Goods"
        }
    ],
    "sg:phone":"+61 3 9729 2228",
    "sg:postcode":"3135",
    "sg:province":"VIC",
    "sg:tags":[
        "wholesaler",
        "mfrs",
        "glove"
    ],
    "wof:name":"Mokpok International Pty Ltd",
    "wof:placetype":"venue"
},
  "geometry": {"coordinates":[145.24603271500001,-37.827999115],"type":"Point"}
}