{
  "type": "Feature",
  "properties": {
    "addr:full":"Shp4/ 64 Argyle St Camden NSW 2570",
    "addr:housenumber":"64",
    "addr:postcode":"2570",
    "addr:street":"Argyle St",
    "iso:country":"AU",
    "sg:address":"Shp4/ 64 Argyle St",
    "sg:city":"Camden",
    "sg:classifiers":[
        {
            "category":"Food & Beverages",
            "subcategory":"Meat & Fish",
            "type":"Retail Goods"
        }
    ],
    "sg:phone":"+61 2 4655 1167",
    "sg:postcode":"2570",
    "sg:province":"NSW",
    "sg:tags":[
        "seafood"
    ],
    "wof:name":"Blue Wave Seafood",
    "wof:placetype":"venue"
},
  "geometry": {"coordinates":[150.69700622600001,-34.0542564392],"type":"Point"}
}