{
  "type": "Feature",
  "properties": {
    "addr:full":"Killcare Kiosk, Beach Road Killcare NSW 2257",
    "addr:postcode":"2257",
    "addr:street":"Beach Road",
    "iso:country":"AU",
    "sg:address":"Killcare Kiosk, Beach Road",
    "sg:city":"Killcare",
    "sg:classifiers":[
        {
            "category":"Fast Food",
            "type":"Food & Drink"
        }
    ],
    "sg:phone":"+61 2 4360 1330",
    "sg:postcode":"2257",
    "sg:province":"NSW",
    "sg:tags":[
        "away",
        "take"
    ],
    "wof:name":"Steve & Helena Hansen",
    "wof:placetype":"venue"
},
  "geometry": {"coordinates":[151.36190795900001,-33.525100708],"type":"Point"}
}