{
  "type": "Feature",
  "properties": {
    "addr:full":"Grindle St Rocklea QLD 4106",
    "addr:postcode":"4106",
    "addr:street":"Grindle St",
    "iso:country":"AU",
    "sg:address":"Grindle St",
    "sg:city":"Rocklea",
    "sg:classifiers":[
        {
            "category":"Retail",
            "subcategory":"Auto Repair",
            "type":"Services"
        }
    ],
    "sg:phone":"+61 411 317 336",
    "sg:postcode":"4106",
    "sg:province":"QLD",
    "sg:tags":[
        "bus",
        "truck"
    ],
    "wof:name":"Forsters Car & Truck Electrics",
    "wof:placetype":"venue"
},
  "geometry": {"coordinates":[153.001098633,-27.554775238],"type":"Point"}
}