{
  "type": "Feature",
  "properties": {
    "addr:full":"60 Hunter St Tatura VIC 3616",
    "addr:housenumber":"60",
    "addr:postcode":"3616",
    "addr:street":"Hunter St",
    "iso:country":"AU",
    "sg:address":"60 Hunter St",
    "sg:city":"Tatura",
    "sg:classifiers":[
        {
            "category":"Travel",
            "subcategory":"Hostel",
            "type":"Entertainment"
        }
    ],
    "sg:phone":"+61 3 5824 2274",
    "sg:postcode":"3616",
    "sg:province":"VIC",
    "sg:tags":[
        "home"
    ],
    "wof:name":"Moyola Cottages & Lodge Inc",
    "wof:placetype":"venue"
},
  "geometry": {"coordinates":[145.22428894000001,-36.438331604],"type":"Point"}
}