{
  "type": "Feature",
  "properties": {
    "iso:country":"AU",
    "sg:address":"5 Memory La",
    "sg:city":"Rowville",
    "sg:classifiers":[
        {
            "category":"Building & Trades",
            "subcategory":"Construction",
            "type":"Services"
        }
    ],
    "sg:phone":"+61 400 636 007",
    "sg:postcode":"3178",
    "sg:province":"VIC",
    "sg:tags":[
        "window",
        "aluminium"
    ],
    "wof:name":"Budget All Window Replacements",
    "wof:placetype":"venue"
},
  "geometry": {"coordinates":[145.24879455600001,-37.9403762817],"type":"Point"}
}