{
  "type": "Feature",
  "properties": {
    "addr:full":"277 Crown St Surry Hills NSW 2010",
    "addr:housenumber":"277",
    "addr:postcode":"2010",
    "addr:street":"Crown St",
    "iso:country":"AU",
    "sg:address":"277 Crown St",
    "sg:city":"Surry Hills",
    "sg:classifiers":[
        {
            "category":"Sports & Exercise",
            "subcategory":"Gym",
            "type":"Entertainment"
        }
    ],
    "sg:phone":"+61 1300 889 060",
    "sg:postcode":"2010",
    "sg:province":"NSW",
    "sg:tags":[
        "personal",
        "trainer",
        "fitness"
    ],
    "wof:name":"Get Fit Australia.",
    "wof:placetype":"venue"
},
  "geometry": {"coordinates":[151.214752197,-33.8807220459],"type":"Point"}
}