{
  "type": "Feature",
  "properties": {
    "addr:full":"33 High St Lancefield VIC 3435",
    "addr:housenumber":"33",
    "addr:postcode":"3435",
    "addr:street":"High St",
    "iso:country":"AU",
    "sg:address":"33 High St",
    "sg:city":"Lancefield",
    "sg:classifiers":[
        {
            "category":"Arts & Performance",
            "subcategory":"Art Gallery",
            "type":"Entertainment"
        }
    ],
    "sg:phone":"+61 3 5429 2435",
    "sg:postcode":"3435",
    "sg:province":"VIC",
    "wof:name":"Bankart Gallery The",
    "wof:placetype":"venue"
},
  "geometry": {"coordinates":[144.732223511,-37.2769508362],"type":"Point"}
}