{
  "type": "Feature",
  "properties": {
    "iso:country":"AU",
    "sg:address":"7 1 Piccadilly Crcle",
    "sg:city":"Joondalup",
    "sg:classifiers":[
        {
            "category":"Building & Trades",
            "subcategory":"Landscaping Services",
            "type":"Services"
        }
    ],
    "sg:phone":"+61 439 586 691",
    "sg:postcode":"6027",
    "sg:province":"WA",
    "sg:tags":[
        "designer",
        "landscape",
        "contractor"
    ],
    "wof:name":"Jungle Fever Lanscaping & Irrigation",
    "wof:placetype":"venue"
},
  "geometry": {"coordinates":[115.759986877,-31.7324905396],"type":"Point"}
}