{
  "type": "Feature",
  "properties": {
    "addr:full":"35 Susan St Kootingal NSW 2352",
    "addr:housenumber":"35",
    "addr:postcode":"2352",
    "addr:street":"Susan St",
    "iso:country":"AU",
    "sg:address":"35 Susan St",
    "sg:city":"Kootingal",
    "sg:classifiers":[
        {
            "category":"Shopping",
            "subcategory":"Crafts & Fabrics",
            "type":"Retail Goods"
        }
    ],
    "sg:phone":"+61 2 6760 3835",
    "sg:postcode":"2352",
    "sg:province":"NSW",
    "sg:tags":[
        "quilting"
    ],
    "wof:name":"Dragon Quilt Services",
    "wof:placetype":"venue"
},
  "geometry": {"coordinates":[151.06057739299999,-31.0436077118],"type":"Point"}
}