{
  "type": "Feature",
  "properties": {
    "iso:country":"AU",
    "sg:address":"16 Lacey St",
    "sg:city":"Perth",
    "sg:classifiers":[
        {
            "category":"Education",
            "subcategory":"Special Training",
            "type":"Public Place"
        }
    ],
    "sg:phone":"+61 8 9228 0808",
    "sg:postcode":"6000",
    "sg:province":"WA",
    "sg:tags":[
        "development"
    ],
    "wof:name":"Natcon Commercial Group",
    "wof:placetype":"venue"
},
  "geometry": {"coordinates":[115.868057251,-31.9452095032],"type":"Point"}
}