{
  "type": "Feature",
  "properties": {
    "addr:full":"Shop 18 Foothills Shopng Cntr,Lissiman St Gosnells WA 6110",
    "addr:housenumber":"shop 18",
    "addr:postcode":"6110",
    "addr:street":"St",
    "iso:country":"AU",
    "sg:address":"Shop 18 Foothills Shopng Cntr,Lissiman St",
    "sg:city":"Gosnells",
    "sg:classifiers":[
        {
            "category":"Personal",
            "subcategory":"Beauty Salon",
            "type":"Services"
        }
    ],
    "sg:phone":"+61 8 9490 1330",
    "sg:postcode":"6110",
    "sg:province":"WA",
    "sg:tags":[
        "hairdresser"
    ],
    "wof:name":"Harry Ks Hair Care For Men",
    "wof:placetype":"venue"
},
  "geometry": {"coordinates":[116.000602722,-32.0715904236],"type":"Point"}
}