{
  "type": "Feature",
  "properties": {
    "addr:full":"U2/ 122 Long St Smithfield NSW 2164",
    "addr:housenumber":"122",
    "addr:postcode":"2164",
    "addr:street":"U2 /;Long St",
    "iso:country":"AU",
    "sg:address":"U2/ 122 Long St",
    "sg:city":"Smithfield",
    "sg:classifiers":[
        {
            "category":"Building & Trades",
            "subcategory":"Construction",
            "type":"Services"
        }
    ],
    "sg:phone":"+61 2 9609 4791",
    "sg:postcode":"2164",
    "sg:province":"NSW",
    "sg:tags":[
        "bitumen",
        "paving",
        "asphalt"
    ],
    "wof:name":"Western Region Plant & Equipment Repairs",
    "wof:placetype":"venue"
},
  "geometry": {"coordinates":[150.93278503400001,-33.8410797119],"type":"Point"}
}