{
  "type": "Feature",
  "properties": {
    "iso:country":"AU",
    "sg:address":"32 Arkwright Crs",
    "sg:city":"Taree",
    "sg:phone":"+61 2 6551 6650",
    "sg:postcode":"2430",
    "sg:province":"NSW",
    "wof:name":"Taree Fibreglass Taree Tanks",
    "wof:placetype":"venue"
},
  "geometry": {"coordinates":[152.461517,-31.91313],"type":"Point"}
}