{
  "type": "Feature",
  "properties": {
    "addr:full":"2- 14 Reilly St Smithtown NSW 2440",
    "addr:housenumber":"14",
    "addr:postcode":"2440",
    "addr:street":"2;Reilly St",
    "iso:country":"AU",
    "sg:address":"2- 14 Reilly St",
    "sg:city":"Smithtown",
    "sg:classifiers":[
        {
            "category":"Utilities",
            "subcategory":"Water",
            "type":"Services"
        }
    ],
    "sg:phone":"+61 408 655 036",
    "sg:postcode":"2440",
    "sg:province":"NSW",
    "sg:tags":[
        "hot",
        "system"
    ],
    "wof:name":"John Wright Plumbing & Roofing",
    "wof:placetype":"venue"
},
  "geometry": {"coordinates":[152.94236799999999,-31.017683],"type":"Point"}
}