{
  "type": "Feature",
  "properties": {
    "addr:full":"PO Box 51 Riddells Creek VIC 3431",
    "addr:postcode":"3431",
    "iso:country":"AU",
    "sg:address":"PO Box 51",
    "sg:city":"Riddells Creek",
    "sg:classifiers":[
        {
            "category":"Building & Trades",
            "subcategory":"Construction",
            "type":"Services"
        }
    ],
    "sg:phone":"+61 418 527 105",
    "sg:postcode":"3431",
    "sg:province":"VIC",
    "sg:tags":[
        "contractor"
    ],
    "wof:name":"Alternate Dwellings Pty Ltd",
    "wof:placetype":"venue"
},
  "geometry": {"coordinates":[144.682937622,-37.4472885132],"type":"Point"}
}