{
  "type": "Feature",
  "properties": {
    "addr:full":"67 Railway St Mudgeeraba QLD 4213",
    "addr:housenumber":"67",
    "addr:postcode":"4213",
    "addr:street":"Railway St",
    "iso:country":"AU",
    "sg:address":"67 Railway St",
    "sg:city":"Mudgeeraba",
    "sg:classifiers":[
        {
            "category":"Health Services",
            "subcategory":"Health Practitioner",
            "type":"Services"
        }
    ],
    "sg:phone":"+61 7 5530 4956",
    "sg:postcode":"4213",
    "sg:province":"QLD",
    "sg:tags":[
        "physiotherapist"
    ],
    "wof:name":"Mudgeeraba Physiotherapy Centre",
    "wof:placetype":"venue"
},
  "geometry": {"coordinates":[153.364212036,-28.0797843933],"type":"Point"}
}