{
  "type": "Feature",
  "properties": {
    "addr:full":"2291 Point Nepean Rd Rye VIC 3941",
    "addr:housenumber":"2291",
    "addr:postcode":"3941",
    "addr:street":"Point Nepean Rd",
    "iso:country":"AU",
    "sg:address":"2291 Point Nepean Rd",
    "sg:city":"Rye",
    "sg:classifiers":[
        {
            "category":"Food & Beverages",
            "subcategory":"Bakery",
            "type":"Retail Goods"
        }
    ],
    "sg:phone":"+61 3 5985 2381",
    "sg:postcode":"3941",
    "sg:province":"VIC",
    "sg:tags":[
        "cake",
        "shop",
        "pastry"
    ],
    "wof:name":"Schmitters Cakes",
    "wof:placetype":"venue"
},
  "geometry": {"coordinates":[144.82565307600001,-38.3708381653],"type":"Point"}
}