{
  "type": "Feature",
  "properties": {
    "addr:full":"Calder Hwy Irymple VIC 3498",
    "addr:postcode":"3498",
    "addr:street":"Calder Hwy",
    "iso:country":"AU",
    "sg:address":"Calder Hwy",
    "sg:city":"Irymple",
    "sg:classifiers":[
        {
            "category":"Organizations",
            "subcategory":"Non-profit Organization",
            "type":"Services"
        }
    ],
    "sg:phone":"+61 3 5024 6153",
    "sg:postcode":"3498",
    "sg:province":"VIC",
    "sg:tags":[
        "environmental",
        "organisation",
        "conservation"
    ],
    "wof:name":"Greening Australia Victoria Inc",
    "wof:placetype":"venue"
},
  "geometry": {"coordinates":[142.177612305,-34.2411155701],"type":"Point"}
}