{
  "type": "Feature",
  "properties": {
    "addr:full":"3/ 193 Camooweal St Mt Isa QLD 4825",
    "addr:housenumber":"/ 193",
    "addr:postcode":"4825",
    "addr:street":"Camooweal St",
    "iso:country":"AU",
    "sg:address":"3/ 193 Camooweal St",
    "sg:city":"Mt Isa",
    "sg:classifiers":[
        {
            "category":"Professional",
            "subcategory":"Art Services",
            "type":"Services"
        }
    ],
    "sg:phone":"+61 7 4743 3681",
    "sg:postcode":"4825",
    "sg:province":"QLD",
    "sg:tags":[
        "decorator",
        "painter"
    ],
    "wof:name":"Horne D K",
    "wof:placetype":"venue"
},
  "geometry": {"coordinates":[139.496307,-20.71483],"type":"Point"}
}