{
  "type": "Feature",
  "properties": {
    "addr:full":"6 James Cook Ave Singleton Heights NSW 2330",
    "addr:housenumber":"6",
    "addr:postcode":"2330",
    "addr:street":"James Cook Ave",
    "iso:country":"AU",
    "sg:address":"6 James Cook Ave",
    "sg:city":"Singleton Heights",
    "sg:classifiers":[
        {
            "category":"Personal",
            "subcategory":"Massage",
            "type":"Services"
        }
    ],
    "sg:phone":"+61 2 6573 1260",
    "sg:postcode":"2330",
    "sg:province":"NSW",
    "sg:tags":[
        "therapy"
    ],
    "wof:name":"Deirdre Partridge",
    "wof:placetype":"venue"
},
  "geometry": {"coordinates":[151.15931699999999,-32.552776],"type":"Point"}
}