{
  "type": "Feature",
  "properties": {
    "iso:country":"AU",
    "sg:address":"Cnr Cowper & Antill Sts",
    "sg:city":"Dickson",
    "sg:classifiers":[
        {
            "category":"Health Services",
            "subcategory":"Dentist",
            "type":"Services"
        }
    ],
    "sg:phone":"+61 2 6257 2896",
    "sg:postcode":"2602",
    "sg:province":"ACT",
    "wof:name":"Dickson Park Dental Care",
    "wof:placetype":"venue"
},
  "geometry": {"coordinates":[149.14065551799999,-35.2504806519],"type":"Point"}
}