{
  "type": "Feature",
  "properties": {
    "addr:full":"221 Mars St Welshpool WA 6106",
    "addr:housenumber":"221",
    "addr:postcode":"6106",
    "addr:street":"Mars St",
    "iso:country":"AU",
    "sg:address":"221 Mars St",
    "sg:city":"Welshpool",
    "sg:classifiers":[
        {
            "category":"Building & Trades",
            "subcategory":"Equipment Rental",
            "type":"Services"
        }
    ],
    "sg:phone":"+61 8 9472 4646",
    "sg:postcode":"6106",
    "sg:province":"WA",
    "sg:tags":[
        "platform",
        "hire",
        "work",
        "elevating"
    ],
    "wof:name":"Hilift",
    "wof:placetype":"venue"
},
  "geometry": {"coordinates":[115.926712036,-31.987077713],"type":"Point"}
}