{
  "type": "Feature",
  "properties": {
    "addr:full":"3/ 27 East St Ipswich QLD 4305",
    "addr:housenumber":"/ 27",
    "addr:postcode":"4305",
    "addr:street":"East St",
    "iso:country":"AU",
    "sg:address":"3/ 27 East St",
    "sg:city":"Ipswich",
    "sg:classifiers":[
        {
            "category":"Professional",
            "subcategory":"Employment Agencies",
            "type":"Services"
        }
    ],
    "sg:phone":"+61 7 3812 3800",
    "sg:postcode":"4305",
    "sg:province":"QLD",
    "wof:name":"MAX Employment",
    "wof:placetype":"venue"
},
  "geometry": {"coordinates":[152.760787964,-27.6144294739],"type":"Point"}
}