{
  "type": "Feature",
  "properties": {
    "iso:country":"AU",
    "sg:address":"PO Box 539",
    "sg:city":"Kenmore",
    "sg:classifiers":[
        {
            "category":"Building & Trades",
            "subcategory":"Landscaping Services",
            "type":"Services"
        }
    ],
    "sg:phone":"+61 7 3202 6465",
    "sg:postcode":"4069",
    "sg:province":"QLD",
    "sg:tags":[
        "designer",
        "landscape",
        "contractor"
    ],
    "wof:name":"Bob Windle Landscapes",
    "wof:placetype":"venue"
},
  "geometry": {"coordinates":[152.93849182100001,-27.508430481],"type":"Point"}
}