{
  "type": "Feature",
  "properties": {
    "iso:country":"AU",
    "sg:address":"17 Liberty Crt",
    "sg:city":"Morayfield",
    "sg:classifiers":[
        {
            "category":"Professional",
            "subcategory":"Art Services",
            "type":"Services"
        }
    ],
    "sg:phone":"+61 414 867 488",
    "sg:postcode":"4506",
    "sg:province":"QLD",
    "sg:tags":[
        "decorator",
        "painter"
    ],
    "wof:name":"C & J Painters",
    "wof:placetype":"venue"
},
  "geometry": {"coordinates":[152.94108581500001,-27.1117973328],"type":"Point"}
}