{
  "type": "Feature",
  "properties": {
    "addr:full":"9 Heinrich Crt South Mackay QLD 4740",
    "addr:housenumber":"9",
    "addr:postcode":"4740",
    "addr:street":"Heinrich Crt",
    "iso:country":"AU",
    "sg:address":"9 Heinrich Crt",
    "sg:city":"South Mackay",
    "sg:classifiers":[
        {
            "category":"Retail",
            "subcategory":"Storage",
            "type":"Services"
        }
    ],
    "sg:phone":"+61 7 4952 3333",
    "sg:postcode":"4740",
    "sg:province":"QLD",
    "sg:tags":[
        "removal",
        "furniture"
    ],
    "sg:website":"http://fraterremovals.citysearch.com.au",
    "wof:name":"Frater Removals",
    "wof:placetype":"venue"
},
  "geometry": {"coordinates":[149.17291299999999,-21.170816],"type":"Point"}
}