{
  "type": "Feature",
  "properties": {
    "addr:full":"44 Omega Ave Cleveland QLD 4163",
    "addr:housenumber":"44",
    "addr:postcode":"4163",
    "addr:street":"Omega Ave",
    "iso:country":"AU",
    "sg:address":"44 Omega Ave",
    "sg:city":"Cleveland",
    "sg:classifiers":[
        {
            "category":"Building & Trades",
            "subcategory":"Plumbing",
            "type":"Services"
        }
    ],
    "sg:phone":"+61 413 940 726",
    "sg:postcode":"4163",
    "sg:province":"QLD",
    "sg:tags":[
        "plumber",
        "gasfitters"
    ],
    "wof:name":"Ray Davies Plumbing",
    "wof:placetype":"venue"
},
  "geometry": {"coordinates":[153.27854919399999,-27.5465011597],"type":"Point"}
}