{
  "type": "Feature",
  "properties": {
    "addr:full":"Oxleys Bridge Rd The Rock NSW 2655",
    "addr:postcode":"2655",
    "addr:street":"Bridge Rd",
    "iso:country":"AU",
    "sg:address":"Oxleys Bridge Rd",
    "sg:city":"The Rock",
    "sg:classifiers":[
        {
            "category":"Professional",
            "subcategory":"Engineering",
            "type":"Services"
        }
    ],
    "sg:phone":"+61 2 6928 5536",
    "sg:postcode":"2655",
    "sg:province":"NSW",
    "sg:tags":[
        "consulting",
        "engineer"
    ],
    "wof:name":"Paul Hagenbach",
    "wof:placetype":"venue"
},
  "geometry": {"coordinates":[147.11558532699999,-35.2674407959],"type":"Point"}
}