{
  "type": "Feature",
  "properties": {
    "iso:country":"AU",
    "sg:address":"71 Forsyth St",
    "sg:city":"O&#039;Connor",
    "sg:classifiers":[
        {
            "category":"Manufacturing",
            "subcategory":"Rubber & Plastics",
            "type":"Manufacturing & Wholesale Goods"
        }
    ],
    "sg:phone":"+61 8 9331 1877",
    "sg:postcode":"6163",
    "sg:province":"WA",
    "sg:tags":[
        "moulders"
    ],
    "wof:name":"Spectro Industries",
    "wof:placetype":"venue"
},
  "geometry": {"coordinates":[115.787567,-32.056602],"type":"Point"}
}