{
  "type": "Feature",
  "properties": {
    "addr:full":"10 Campbell Pde Bondi Beach NSW 2026",
    "addr:housenumber":"10",
    "addr:postcode":"2026",
    "addr:street":"Campbell Pde",
    "iso:country":"AU",
    "sg:address":"10 Campbell Pde",
    "sg:city":"Bondi Beach",
    "sg:classifiers":[
        {
            "category":"Retail",
            "subcategory":"Laundry & Dry Cleaning",
            "type":"Services"
        }
    ],
    "sg:phone":"+61 2 9130 3987",
    "sg:postcode":"2026",
    "sg:province":"NSW",
    "wof:name":"Pacific Laundry",
    "wof:placetype":"venue"
},
  "geometry": {"coordinates":[151.27311706500001,-33.8947525024],"type":"Point"}
}