{
  "type": "Feature",
  "properties": {
    "addr:full":"21 Queen St Binalong NSW 2584",
    "addr:housenumber":"21",
    "addr:postcode":"2584",
    "addr:street":"Queen St",
    "iso:country":"AU",
    "sg:address":"21 Queen St",
    "sg:city":"Binalong",
    "sg:classifiers":[
        {
            "category":"Manufacturing",
            "subcategory":"Glass & Minerals",
            "type":"Manufacturing & Wholesale Goods"
        }
    ],
    "sg:phone":"+61 2 6227 4312",
    "sg:postcode":"2584",
    "sg:province":"NSW",
    "sg:tags":[
        "blowing"
    ],
    "wof:name":"Peter Minson Art Glass",
    "wof:placetype":"venue"
},
  "geometry": {"coordinates":[148.63055419899999,-34.6700553894],"type":"Point"}
}