{
  "type": "Feature",
  "properties": {
    "addr:full":"26 Somerville St Sorell TAS 7172",
    "addr:housenumber":"26",
    "addr:postcode":"7172",
    "addr:street":"Somerville St",
    "iso:country":"AU",
    "sg:address":"26 Somerville St",
    "sg:city":"Sorell",
    "sg:classifiers":[
        {
            "category":"Restaurant",
            "type":"Food & Drink"
        }
    ],
    "sg:phone":"+61 3 6265 2804",
    "sg:postcode":"7172",
    "sg:province":"TAS",
    "wof:name":"Blue Bell Inn",
    "wof:placetype":"venue"
},
  "geometry": {"coordinates":[147.559890747,-42.7842216492],"type":"Point"}
}