{
  "type": "Feature",
  "properties": {
    "addr:full":"18 Blandford Ave Bronte NSW 2024",
    "addr:housenumber":"18",
    "addr:postcode":"2024",
    "addr:street":"Blandford Ave",
    "iso:country":"AU",
    "sg:address":"18 Blandford Ave",
    "sg:city":"Bronte",
    "sg:classifiers":[
        {
            "category":"Museum",
            "subcategory":"Art Museum",
            "type":"Entertainment"
        }
    ],
    "sg:phone":"+61 419 483 710",
    "sg:postcode":"2024",
    "sg:province":"NSW",
    "sg:tags":[
        "antique",
        "fine",
        "valuer"
    ],
    "wof:name":"Wright Andrew",
    "wof:placetype":"venue"
},
  "geometry": {"coordinates":[151.25997924800001,-33.8993759155],"type":"Point"}
}