{
  "type": "Feature",
  "properties": {
    "iso:country":"AU",
    "sg:address":"53 Bay St",
    "sg:city":"Port Melbourne",
    "sg:classifiers":[
        {
            "category":"Professional",
            "subcategory":"Employment Agencies",
            "type":"Services"
        }
    ],
    "sg:phone":"+61 3 9329 5399",
    "sg:postcode":"3207",
    "sg:province":"VIC",
    "sg:tags":[
        "broker",
        "custom"
    ],
    "wof:name":"Bayport International",
    "wof:placetype":"venue"
},
  "geometry": {"coordinates":[144.93928500000001,-37.841671],"type":"Point"}
}