{
  "type": "Feature",
  "properties": {
    "addr:full":"55 Padstow Pde Padstow NSW 2211",
    "addr:housenumber":"55",
    "addr:postcode":"2211",
    "addr:street":"Padstow Pde",
    "iso:country":"AU",
    "sg:address":"55 Padstow Pde",
    "sg:city":"Padstow",
    "sg:classifiers":[
        {
            "category":"Shopping",
            "subcategory":"Clothing, Apparel, & Fashions",
            "type":"Retail Goods"
        }
    ],
    "sg:phone":"+61 2 9792 2291",
    "sg:postcode":"2211",
    "sg:province":"NSW",
    "sg:tags":[
        "lady",
        "wear"
    ],
    "wof:name":"Freez Clothing Co Gymea",
    "wof:placetype":"venue"
},
  "geometry": {"coordinates":[151.03338600000001,-33.953655],"type":"Point"}
}