{
  "type": "Feature",
  "properties": {
    "iso:country":"AU",
    "sg:address":"292 Pakington St",
    "sg:city":"Newtown",
    "sg:classifiers":[
        {
            "category":"Building & Trades",
            "subcategory":"Construction",
            "type":"Services"
        }
    ],
    "sg:phone":"+61 418 520 087",
    "sg:postcode":"3220",
    "sg:province":"VIC",
    "sg:tags":[
        "contractor"
    ],
    "wof:name":"Russell Peter J Master Builder",
    "wof:placetype":"venue"
},
  "geometry": {"coordinates":[144.346085,-38.153309],"type":"Point"}
}