{
  "type": "Feature",
  "properties": {
    "iso:country":"AU",
    "sg:address":"4 Farnham St",
    "sg:city":"Wellington Point",
    "sg:classifiers":[
        {
            "category":"Personal",
            "subcategory":"Beauty Salon",
            "type":"Services"
        }
    ],
    "sg:phone":"+61 7 3822 8000",
    "sg:postcode":"4160",
    "sg:province":"QLD",
    "sg:tags":[
        "hair",
        "wedding"
    ],
    "wof:name":"Brush and Blush",
    "wof:placetype":"venue"
},
  "geometry": {"coordinates":[153.241363525,-27.4994506836],"type":"Point"}
}