{
  "type": "Feature",
  "properties": {
    "addr:full":"22 Melody La Coogee NSW 2034",
    "addr:housenumber":"22",
    "addr:postcode":"2034",
    "addr:street":"Melody La",
    "iso:country":"AU",
    "sg:address":"22 Melody La",
    "sg:city":"Coogee",
    "sg:classifiers":[
        {
            "category":"Sports & Exercise",
            "subcategory":"Gym",
            "type":"Entertainment"
        }
    ],
    "sg:phone":"+61 401 049 119",
    "sg:postcode":"2034",
    "sg:province":"NSW",
    "sg:tags":[
        "meditation"
    ],
    "wof:name":"Melody Meditation",
    "wof:placetype":"venue"
},
  "geometry": {"coordinates":[151.25042724599999,-33.9155578613],"type":"Point"}
}