{
  "type": "Feature",
  "properties": {
    "addr:full":"127B Old Pittwater Rd Brookvale NSW 2100",
    "addr:housenumber":"127b",
    "addr:postcode":"2100",
    "addr:street":"Old Pittwater Rd",
    "iso:country":"AU",
    "sg:address":"127B Old Pittwater Rd",
    "sg:city":"Brookvale",
    "sg:classifiers":[
        {
            "category":"Social Services",
            "subcategory":"Child Care",
            "type":"Services"
        }
    ],
    "sg:phone":"+61 2 9938 1826",
    "sg:postcode":"2100",
    "sg:province":"NSW",
    "wof:name":"Warringah Mall Kindergarten",
    "wof:placetype":"venue"
},
  "geometry": {"coordinates":[151.262374878,-33.7674865723],"type":"Point"}
}