{
  "type": "Feature",
  "properties": {
    "iso:country":"AU",
    "sg:address":"13-15 Forrester St",
    "sg:city":"Kingsgrove",
    "sg:classifiers":[
        {
            "category":"Building & Trades",
            "subcategory":"Plumbing",
            "type":"Services"
        }
    ],
    "sg:phone":"+61 414 788 668",
    "sg:postcode":"2208",
    "sg:province":"NSW",
    "sg:tags":[
        "plumber",
        "gasfitters"
    ],
    "wof:name":"J S & B Plumbing Services",
    "wof:placetype":"venue"
},
  "geometry": {"coordinates":[151.097534,-33.938126],"type":"Point"}
}