{
  "type": "Feature",
  "properties": {
    "iso:country":"AU",
    "sg:address":"39 Carrington Rd",
    "sg:city":"Marrickville",
    "sg:classifiers":[
        {
            "category":"Shopping",
            "type":"Retail Goods"
        }
    ],
    "sg:phone":"+61 2 9559 1088",
    "sg:postcode":"2204",
    "sg:province":"NSW",
    "sg:tags":[
        "equipment",
        "safety",
        "accessory"
    ],
    "wof:name":"Rope In Motion",
    "wof:placetype":"venue"
},
  "geometry": {"coordinates":[151.156525,-33.917976],"type":"Point"}
}