{
  "type": "Feature",
  "properties": {
    "iso:country":"AU",
    "sg:address":"236 Victoria St",
    "sg:city":"Taree",
    "sg:classifiers":[
        {
            "category":"Travel",
            "subcategory":"Hotels & Motels",
            "type":"Entertainment"
        }
    ],
    "sg:phone":"+61 2 6552 1153",
    "sg:postcode":"2430",
    "sg:province":"NSW",
    "sg:tags":[
        "accommodation"
    ],
    "wof:name":"Fotheringhams Hotel",
    "wof:placetype":"venue"
},
  "geometry": {"coordinates":[152.459442,-31.914541],"type":"Point"}
}