{
  "type": "Feature",
  "properties": {
    "addr:full":"PO Box 100 Villawood NSW 2163",
    "addr:postcode":"2163",
    "iso:country":"AU",
    "sg:address":"PO Box 100",
    "sg:city":"Villawood",
    "sg:classifiers":[
        {
            "category":"Bars & Pubs",
            "subcategory":"Nightclub",
            "type":"Food & Drink"
        }
    ],
    "sg:phone":"+61 2 9788 7472",
    "sg:postcode":"2163",
    "sg:province":"NSW",
    "sg:tags":[
        "karaoke"
    ],
    "wof:name":"VCD Entertainment Karaoke",
    "wof:placetype":"venue"
},
  "geometry": {"coordinates":[150.977859497,-33.8805198669],"type":"Point"}
}