{
  "type": "Feature",
  "properties": {
    "addr:full":"413 Payneham Rd Felixstow SA 5070",
    "addr:housenumber":"413",
    "addr:postcode":"5070",
    "addr:street":"Payneham Rd",
    "iso:country":"AU",
    "sg:address":"413 Payneham Rd",
    "sg:city":"Felixstow",
    "sg:classifiers":[
        {
            "category":"Banks & Credit Unions",
            "subcategory":"Investment Brokerage",
            "type":"Services"
        }
    ],
    "sg:phone":"+61 8 8365 2766",
    "sg:postcode":"5070",
    "sg:province":"SA",
    "sg:tags":[
        "finance",
        "broker"
    ],
    "wof:name":"Yes Home Loans",
    "wof:placetype":"venue"
},
  "geometry": {"coordinates":[138.65313720699999,-34.8909225464],"type":"Point"}
}