{
  "type": "Feature",
  "properties": {
    "addr:full":"58 Gardiner Pde Glen Iris VIC 3146",
    "addr:housenumber":"58",
    "addr:postcode":"3146",
    "addr:street":"Gardiner Pde",
    "iso:country":"AU",
    "sg:address":"58 Gardiner Pde",
    "sg:city":"Glen Iris",
    "sg:classifiers":[
        {
            "category":"Professional",
            "subcategory":"Accounting & Tax Preparation",
            "type":"Services"
        }
    ],
    "sg:phone":"+61 3 9813 8829",
    "sg:postcode":"3146",
    "sg:province":"VIC",
    "sg:tags":[
        "accountant",
        "auditor"
    ],
    "wof:name":"Ferguson Stuart",
    "wof:placetype":"venue"
},
  "geometry": {"coordinates":[145.061004639,-37.8555488586],"type":"Point"}
}