{
  "type": "Feature",
  "properties": {
    "addr:full":"434 Old Northern Rd Dural NSW 2158",
    "addr:housenumber":"434",
    "addr:postcode":"2158",
    "addr:street":"Old Northern Rd",
    "iso:country":"AU",
    "sg:address":"434 Old Northern Rd",
    "sg:city":"Dural",
    "sg:classifiers":[
        {
            "category":"Health Services",
            "subcategory":"Health Practitioner",
            "type":"Services"
        }
    ],
    "sg:phone":"+61 2 9634 6683",
    "sg:postcode":"2158",
    "sg:province":"NSW",
    "sg:tags":[
        "osteopath"
    ],
    "wof:name":"Madar Leonard P",
    "wof:placetype":"venue"
},
  "geometry": {"coordinates":[151.0181427,-33.6946220398],"type":"Point"}
}