{
  "type": "Feature",
  "properties": {
    "iso:country":"AU",
    "sg:address":"Cnr Wyndham & Weightman Sts",
    "sg:city":"Herston",
    "sg:classifiers":[
        {
            "category":"Travel",
            "subcategory":"Hotels & Motels",
            "type":"Entertainment"
        }
    ],
    "sg:phone":"+61 7 3216 0111",
    "sg:postcode":"4006",
    "sg:province":"QLD",
    "wof:name":"Herston Place Motel",
    "wof:placetype":"venue"
},
  "geometry": {"coordinates":[153.022674561,-27.448589325],"type":"Point"}
}