{
  "type": "Feature",
  "properties": {
    "addr:full":"47 Kansas Ave Bell Post Hill VIC 3215",
    "addr:postcode":"3215",
    "addr:street":"Kansas Ave",
    "iso:country":"AU",
    "sg:address":"47 Kansas Ave",
    "sg:city":"Bell Post Hill",
    "sg:classifiers":[
        {
            "category":"Home & Garden",
            "subcategory":"Garden Supply",
            "type":"Retail Goods"
        }
    ],
    "sg:phone":"+61 3 5278 8279",
    "sg:postcode":"3215",
    "sg:province":"VIC",
    "sg:tags":[
        "equipment"
    ],
    "wof:name":"Geelong Lawn Mower Repair Service",
    "wof:placetype":"venue"
},
  "geometry": {"coordinates":[144.32963562,-38.0954322815],"type":"Point"}
}