{
  "type": "Feature",
  "properties": {
    "addr:full":"3 Yamba Rd Yamba NSW 2464",
    "addr:housenumber":"3",
    "addr:postcode":"2464",
    "addr:street":"Yamba Rd",
    "iso:country":"AU",
    "sg:address":"3 Yamba Rd",
    "sg:city":"Yamba",
    "sg:classifiers":[
        {
            "category":"Cafe",
            "type":"Food & Drink"
        }
    ],
    "sg:phone":"+61 2 6646 9898",
    "sg:postcode":"2464",
    "sg:province":"NSW",
    "wof:name":"Yamba Marina",
    "wof:placetype":"venue"
},
  "geometry": {"coordinates":[153.33335876500001,-29.4310321808],"type":"Point"}
}