{
  "type": "Feature",
  "properties": {
    "addr:full":"300 Cobbitty Rd Cobbitty NSW 2570",
    "addr:housenumber":"300",
    "addr:postcode":"2570",
    "addr:street":"Cobbitty Rd",
    "iso:country":"AU",
    "sg:address":"300 Cobbitty Rd",
    "sg:city":"Cobbitty",
    "sg:classifiers":[
        {
            "category":"Arts & Performance",
            "subcategory":"Art Gallery",
            "type":"Entertainment"
        }
    ],
    "sg:phone":"+61 2 4651 2471",
    "sg:postcode":"2570",
    "sg:province":"NSW",
    "wof:name":"Cobbitty Fine Art Gallery",
    "wof:placetype":"venue"
},
  "geometry": {"coordinates":[150.6849823,-34.0153884888],"type":"Point"}
}