{
  "type": "Feature",
  "properties": {
    "iso:country":"AU",
    "sg:address":"10 Davis Rd",
    "sg:city":"Wetherill Park",
    "sg:classifiers":[
        {
            "category":"Military Area",
            "subcategory":"Army Base",
            "type":"Public Place"
        }
    ],
    "sg:phone":"+61 2 9604 0366",
    "sg:postcode":"2164",
    "sg:province":"NSW",
    "sg:tags":[
        "wholesaler",
        "mfrs",
        "cement",
        "supply"
    ],
    "wof:name":"Building Products Supplies Pty Ltd",
    "wof:placetype":"venue"
},
  "geometry": {"coordinates":[150.90219116200001,-33.8366355896],"type":"Point"}
}