{
  "type": "Feature",
  "properties": {
    "addr:full":"50 Osborne Ave Springvale VIC 3171",
    "addr:housenumber":"50",
    "addr:postcode":"3171",
    "addr:street":"Osborne Ave",
    "iso:country":"AU",
    "sg:address":"50 Osborne Ave",
    "sg:city":"Springvale",
    "sg:classifiers":[
        {
            "category":"Home & Garden",
            "subcategory":"Building Materials",
            "type":"Retail Goods"
        }
    ],
    "sg:phone":"+61 3 9549 7333",
    "sg:postcode":"3171",
    "sg:province":"VIC",
    "sg:tags":[
        "supply"
    ],
    "wof:name":"Big J Doors & Windows",
    "wof:placetype":"venue"
},
  "geometry": {"coordinates":[145.14244079599999,-37.9463119507],"type":"Point"}
}