{
  "type": "Feature",
  "properties": {
    "addr:full":"Ste 2/ 26 Ross St Parramatta NSW 2150",
    "addr:housenumber":"26",
    "addr:postcode":"2150",
    "addr:street":"Ross St",
    "iso:country":"AU",
    "sg:address":"Ste 2/ 26 Ross St",
    "sg:city":"Parramatta",
    "sg:classifiers":[
        {
            "category":"Shopping",
            "subcategory":"Computers & Home Electronics",
            "type":"Retail Goods"
        }
    ],
    "sg:phone":"+61 2 9630 2461",
    "sg:postcode":"2150",
    "sg:province":"NSW",
    "sg:tags":[
        "hardware",
        "equipment"
    ],
    "wof:name":"Strontium Australia Pty Ltd",
    "wof:placetype":"venue"
},
  "geometry": {"coordinates":[150.91192626899999,-33.7792663574],"type":"Point"}
}