{
  "type": "Feature",
  "properties": {
    "addr:full":"Unit 7/ 99 Ramsgate Ave North Bondi NSW 2026",
    "addr:housenumber":"99",
    "addr:postcode":"2026",
    "addr:street":"Ramsgate Ave",
    "iso:country":"AU",
    "sg:address":"Unit 7/ 99 Ramsgate Ave",
    "sg:city":"North Bondi",
    "sg:classifiers":[
        {
            "category":"Shopping",
            "subcategory":"Musical Instruments",
            "type":"Retail Goods"
        }
    ],
    "sg:phone":"+61 2 9365 0648",
    "sg:postcode":"2026",
    "sg:province":"NSW",
    "sg:tags":[
        "musician",
        "agent"
    ],
    "wof:name":"Anthony Thomas Management",
    "wof:placetype":"venue"
},
  "geometry": {"coordinates":[151.276443481,-33.8866996765],"type":"Point"}
}