{
  "type": "Feature",
  "properties": {
    "addr:full":"180 Main Rd Speers Point NSW 2284",
    "addr:housenumber":"180",
    "addr:postcode":"2284",
    "addr:street":"Main Rd",
    "iso:country":"AU",
    "sg:address":"180 Main Rd",
    "sg:city":"Speers Point",
    "sg:classifiers":[
        {
            "category":"Professional",
            "subcategory":"Accounting & Tax Preparation",
            "type":"Services"
        }
    ],
    "sg:phone":"+61 2 4958 1829",
    "sg:postcode":"2284",
    "sg:province":"NSW",
    "sg:tags":[
        "accountant",
        "auditor"
    ],
    "wof:name":"O'Brien David & Associates",
    "wof:placetype":"venue"
},
  "geometry": {"coordinates":[151.62286376899999,-32.9639968872],"type":"Point"}
}