{
  "type": "Feature",
  "properties": {
    "addr:full":"Wesley Hospital Evan Thompson Building, level 9, Suite 1, 24 Chasely Street Auchenflower QLD 4066",
    "addr:housenumber":"24",
    "addr:postcode":"4066",
    "addr:street":"Chasely Street",
    "iso:country":"AU",
    "sg:address":"Wesley Hospital Evan Thompson Building, level 9, Suite 1, 24 Chasely Street",
    "sg:city":"Auchenflower",
    "sg:classifiers":[
        {
            "category":"Health Services",
            "subcategory":"Doctor",
            "type":"Services"
        }
    ],
    "sg:phone":"+61 7 3876 8405",
    "sg:postcode":"4066",
    "sg:province":"QLD",
    "sg:tags":[
        "medical",
        "practitioner"
    ],
    "wof:name":"Scott Andrew Dr",
    "wof:placetype":"venue"
},
  "geometry": {"coordinates":[152.998046875,-27.4772014618],"type":"Point"}
}