{
  "type": "Feature",
  "properties": {
    "addr:full":"Shp2/ 192 Queen St Campbelltown NSW 2560",
    "addr:housenumber":"192",
    "addr:postcode":"2560",
    "addr:street":"Queen St",
    "iso:country":"AU",
    "sg:address":"Shp2/ 192 Queen St",
    "sg:city":"Campbelltown",
    "sg:classifiers":[
        {
            "category":"Health Services",
            "subcategory":"Optometrist",
            "type":"Services"
        }
    ],
    "sg:phone":"+61 2 4627 6098",
    "sg:postcode":"2560",
    "sg:province":"NSW",
    "wof:name":"Schwarz Susan J",
    "wof:placetype":"venue"
},
  "geometry": {"coordinates":[150.814086914,-34.067073822],"type":"Point"}
}