{
  "type": "Feature",
  "properties": {
    "addr:full":"Southern Access Rd Cairns QLD 4870",
    "addr:postcode":"4870",
    "addr:street":"Rd",
    "iso:country":"AU",
    "sg:address":"Southern Access Rd",
    "sg:city":"Cairns",
    "sg:classifiers":[
        {
            "category":"Banks & Credit Unions",
            "subcategory":"Financial Services",
            "type":"Services"
        }
    ],
    "sg:phone":"+61 7 4052 4333",
    "sg:postcode":"4870",
    "sg:province":"QLD",
    "sg:tags":[
        "finance",
        "motor",
        "vehicle"
    ],
    "wof:name":"Adams Motor Group",
    "wof:placetype":"venue"
},
  "geometry": {"coordinates":[145.66958618199999,-17.0185699463],"type":"Point"}
}