{
  "type": "Feature",
  "properties": {
    "iso:country":"AU",
    "sg:address":"Sheraton On The Park, 161 Elizabeth St",
    "sg:city":"Sydney",
    "sg:classifiers":[
        {
            "category":"Sports & Exercise",
            "subcategory":"Gym",
            "type":"Entertainment"
        }
    ],
    "sg:phone":"+61 2 9286 6830",
    "sg:postcode":"2000",
    "sg:province":"NSW",
    "sg:tags":[
        "health",
        "fitness"
    ],
    "wof:name":"Health Club The",
    "wof:placetype":"venue"
},
  "geometry": {"coordinates":[151.20996093799999,-33.8717727661],"type":"Point"}
}