{
  "type": "Feature",
  "properties": {
    "addr:full":"189 Alkera Rd Ballarat VIC 3350",
    "addr:housenumber":"189",
    "addr:postcode":"3350",
    "addr:street":"Alkera Rd",
    "iso:country":"AU",
    "sg:address":"189 Alkera Rd",
    "sg:city":"Ballarat",
    "sg:classifiers":[
        {
            "category":"Health Services",
            "subcategory":"Health Practitioner",
            "type":"Services"
        }
    ],
    "sg:phone":"+61 3 5333 3525",
    "sg:postcode":"3350",
    "sg:province":"VIC",
    "sg:tags":[
        "reiki"
    ],
    "wof:name":"Alkera Holistic Therapies",
    "wof:placetype":"venue"
},
  "geometry": {"coordinates":[143.89184599999999,-37.516743],"type":"Point"}
}