{
  "type": "Feature",
  "properties": {
    "addr:full":"9 Gooch St Thornbury VIC 3071",
    "addr:housenumber":"9",
    "addr:postcode":"3071",
    "addr:street":"Gooch St",
    "iso:country":"AU",
    "sg:address":"9 Gooch St",
    "sg:city":"Thornbury",
    "sg:classifiers":[
        {
            "category":"Building & Trades",
            "subcategory":"Landscaping Services",
            "type":"Services"
        }
    ],
    "sg:phone":"+61 3 9484 1421",
    "sg:postcode":"3071",
    "sg:province":"VIC",
    "sg:tags":[
        "designer",
        "landscape",
        "contractor"
    ],
    "wof:name":"Creative Garden Construction",
    "wof:placetype":"venue"
},
  "geometry": {"coordinates":[145.00137329099999,-37.7578773499],"type":"Point"}
}