{
  "type": "Feature",
  "properties": {
    "iso:country":"AU",
    "sg:address":"21 Albert St",
    "sg:city":"Erskineville",
    "sg:classifiers":[
        {
            "category":"Real Estate",
            "subcategory":"Architect",
            "type":"Services"
        }
    ],
    "sg:phone":"+61 2 9557 6396",
    "sg:postcode":"2043",
    "sg:province":"NSW",
    "wof:name":"Trevor Hall Architects",
    "wof:placetype":"venue"
},
  "geometry": {"coordinates":[151.183807,-33.898003],"type":"Point"}
}