{
  "type": "Feature",
  "properties": {
    "addr:full":"20 Playford Drv Morphett Vale SA 5162",
    "addr:housenumber":"20",
    "addr:postcode":"5162",
    "addr:street":"Playford Drv",
    "iso:country":"AU",
    "sg:address":"20 Playford Drv",
    "sg:city":"Morphett Vale",
    "sg:classifiers":[
        {
            "category":"Home & Garden",
            "subcategory":"Building Materials",
            "type":"Retail Goods"
        }
    ],
    "sg:phone":"+61 8 8325 1757",
    "sg:postcode":"5162",
    "sg:province":"SA",
    "sg:tags":[
        "fire",
        "resistant",
        "supply"
    ],
    "wof:name":"B.W.D Fire Protection",
    "wof:placetype":"venue"
},
  "geometry": {"coordinates":[138.541107178,-35.1277542114],"type":"Point"}
}