{
  "type": "Feature",
  "properties": {
    "addr:full":"Shop 7 , Woolworths Market Plaza Morayfield QLD 4506",
    "addr:housenumber":"shop 7",
    "addr:postcode":"4506",
    "iso:country":"AU",
    "sg:address":"Shop 7",
    "sg:city":", Woolworths Market Plaza Morayfield",
    "sg:classifiers":[
        {
            "category":"Health Services",
            "subcategory":"Optometrist",
            "type":"Services"
        }
    ],
    "sg:phone":"+61 7 5499 3166",
    "sg:postcode":"4506",
    "sg:province":"QLD",
    "wof:name":"Kevin Leung Optometrist",
    "wof:placetype":"venue"
},
  "geometry": {"coordinates":[152.94992065400001,-27.1089096069],"type":"Point"}
}