{
  "type": "Feature",
  "properties": {
    "iso:country":"AU",
    "sg:address":"Unit 2 The Clock Tower",
    "sg:city":"Coconut Grove",
    "sg:classifiers":[
        {
            "category":"Professional",
            "subcategory":"Accounting & Tax Preparation",
            "type":"Services"
        }
    ],
    "sg:phone":"+61 8 8948 0144",
    "sg:postcode":"0810",
    "sg:province":"NT",
    "sg:tags":[
        "pregnancy",
        "related",
        "counselling"
    ],
    "wof:name":"Family Planning Services",
    "wof:placetype":"venue"
},
  "geometry": {"coordinates":[130.84251403799999,-12.4638319016],"type":"Point"}
}