{
  "type": "Feature",
  "properties": {
    "addr:full":"7 Yarrowee St Currajong QLD 4812",
    "addr:housenumber":"7",
    "addr:postcode":"4812",
    "addr:street":"Yarrowee St",
    "iso:country":"AU",
    "sg:address":"7 Yarrowee St",
    "sg:city":"Currajong",
    "sg:classifiers":[
        {
            "category":"Landmark",
            "subcategory":"Fountain",
            "type":"Public Place"
        }
    ],
    "sg:phone":"+61 7 4725 3618",
    "sg:postcode":"4812",
    "sg:province":"QLD",
    "sg:tags":[
        "wholesaler",
        "spring",
        "mfrs"
    ],
    "wof:name":"Tyrepower Townsville",
    "wof:placetype":"venue"
},
  "geometry": {"coordinates":[146.773605,-19.273041],"type":"Point"}
}