{
  "type": "Feature",
  "properties": {
    "addr:full":"Shop 6, Cowra Plaza S/Centre, Cnr Kendal & Macquarie Sts Cowra NSW 2794",
    "addr:housenumber":"shop 6",
    "addr:postcode":"2794",
    "addr:street":"Cnr",
    "iso:country":"AU",
    "sg:address":"Shop 6, Cowra Plaza S/Centre, Cnr Kendal & Macquarie Sts",
    "sg:city":"Cowra",
    "sg:classifiers":[
        {
            "category":"Shopping",
            "subcategory":"Clothing, Apparel, & Fashions",
            "type":"Retail Goods"
        }
    ],
    "sg:phone":"+61 2 6342 5918",
    "sg:postcode":"2794",
    "sg:province":"NSW",
    "sg:tags":[
        "lady",
        "wear"
    ],
    "wof:name":"Noni B",
    "wof:placetype":"venue"
},
  "geometry": {"coordinates":[148.68864440900001,-33.8348197937],"type":"Point"}
}