{
  "type": "Feature",
  "properties": {
    "addr:full":"9 Chapel Rd Bankstown NSW 2200",
    "addr:housenumber":"9",
    "addr:postcode":"2200",
    "addr:street":"Chapel Rd",
    "iso:country":"AU",
    "sg:address":"9 Chapel Rd",
    "sg:city":"Bankstown",
    "sg:classifiers":[
        {
            "category":"Sports & Exercise",
            "subcategory":"Gym",
            "type":"Entertainment"
        }
    ],
    "sg:phone":"+61 1300 557 799",
    "sg:postcode":"2200",
    "sg:province":"NSW",
    "sg:tags":[
        "health",
        "fitness"
    ],
    "wof:name":"Fitness First Bankstown",
    "wof:placetype":"venue"
},
  "geometry": {"coordinates":[151.031586,-33.920647],"type":"Point"}
}