{
  "type": "Feature",
  "properties": {
    "iso:country":"AU",
    "sg:address":"Barley Rd",
    "sg:city":"Port Lincoln",
    "sg:classifiers":[
        {
            "category":"Health Services",
            "subcategory":"Dentist",
            "type":"Services"
        }
    ],
    "sg:phone":"+61 8 8682 3103",
    "sg:postcode":"5606",
    "sg:province":"SA",
    "wof:name":"Dental-S.A. Dental Service",
    "wof:placetype":"venue"
},
  "geometry": {"coordinates":[135.848236,-34.741428],"type":"Point"}
}