{
  "type": "Feature",
  "properties": {
    "iso:country":"AU",
    "sg:address":"464 Woodhill Mountain Rd",
    "sg:city":"Woodhill",
    "sg:classifiers":[
        {
            "category":"Professional",
            "subcategory":"Printing & Photocopies",
            "type":"Services"
        }
    ],
    "sg:phone":"+61 2 4464 1977",
    "sg:postcode":"2535",
    "sg:province":"NSW",
    "sg:tags":[
        "publishing",
        "desktop"
    ],
    "wof:name":"Windward Publications Pty Ltd",
    "wof:placetype":"venue"
},
  "geometry": {"coordinates":[150.693969727,-34.7381019592],"type":"Point"}
}