{
  "type": "Feature",
  "properties": {
    "addr:full":"15 Lowen Rd Glen Waverley VIC 3150",
    "addr:housenumber":"15",
    "addr:postcode":"3150",
    "addr:street":"Lowen Rd",
    "iso:country":"AU",
    "sg:address":"15 Lowen Rd",
    "sg:city":"Glen Waverley",
    "sg:classifiers":[
        {
            "category":"Health Services",
            "subcategory":"Health Practitioner",
            "type":"Services"
        }
    ],
    "sg:phone":"+61 412 021 093",
    "sg:postcode":"3150",
    "sg:province":"VIC",
    "sg:tags":[
        "dietitian"
    ],
    "wof:name":"Jennifer D Ballard",
    "wof:placetype":"venue"
},
  "geometry": {"coordinates":[145.155487061,-37.8659439087],"type":"Point"}
}