{
  "type": "Feature",
  "properties": {
    "addr:full":"PO Box 341 Burpengary QLD 4505",
    "addr:postcode":"4505",
    "iso:country":"AU",
    "sg:address":"PO Box 341",
    "sg:city":"Burpengary",
    "sg:classifiers":[
        {
            "category":"Wholesale",
            "subcategory":"Apparel",
            "type":"Manufacturing & Wholesale Goods"
        }
    ],
    "sg:phone":"+61 7 3886 8500",
    "sg:postcode":"4505",
    "sg:province":"QLD",
    "sg:tags":[
        "wholesaler",
        "mfrs",
        "uniform"
    ],
    "wof:name":"House Of Aprons",
    "wof:placetype":"venue"
},
  "geometry": {"coordinates":[152.9921875,-27.1472892761],"type":"Point"}
}