{
  "type": "Feature",
  "properties": {
    "addr:full":"Martins Rd Parafield Gardens SA 5107",
    "addr:postcode":"5107",
    "addr:street":"Martins Rd",
    "iso:country":"AU",
    "sg:address":"Martins Rd",
    "sg:city":"Parafield Gardens",
    "sg:classifiers":[
        {
            "category":"Food & Beverages",
            "subcategory":"Supermarket",
            "type":"Retail Goods"
        }
    ],
    "sg:phone":"+61 8 8285 1911",
    "sg:postcode":"5107",
    "sg:province":"SA",
    "sg:tags":[
        "grocery",
        "store"
    ],
    "wof:name":"Martins Plaza IGA Everyday",
    "wof:placetype":"venue"
},
  "geometry": {"coordinates":[138.607620239,-34.7824325562],"type":"Point"}
}