{
  "type": "Feature",
  "properties": {
    "addr:full":"Shop 16 Regent Arc Adelaide SA 5000",
    "addr:housenumber":"shop 16",
    "addr:postcode":"5000",
    "addr:street":"Regent Arc",
    "iso:country":"AU",
    "sg:address":"Shop 16 Regent Arc",
    "sg:city":"Adelaide",
    "sg:classifiers":[
        {
            "category":"Shopping",
            "subcategory":"Clothing, Apparel, & Fashions",
            "type":"Retail Goods"
        }
    ],
    "sg:phone":"+61 8 8232 5171",
    "sg:postcode":"5000",
    "sg:province":"SA",
    "sg:tags":[
        "boutique"
    ],
    "wof:name":"Showies Boutique",
    "wof:placetype":"venue"
},
  "geometry": {"coordinates":[138.603515625,-34.9234390259],"type":"Point"}
}