{
  "type": "Feature",
  "properties": {
    "addr:full":"16 Joyce St Pendle Hill NSW 2145",
    "addr:housenumber":"16",
    "addr:postcode":"2145",
    "addr:street":"Joyce St",
    "iso:country":"AU",
    "sg:address":"16 Joyce St",
    "sg:city":"Pendle Hill",
    "sg:classifiers":[
        {
            "category":"Retail",
            "subcategory":"Auto Repair",
            "type":"Services"
        }
    ],
    "sg:phone":"+61 408 163 100",
    "sg:postcode":"2145",
    "sg:province":"NSW",
    "sg:tags":[
        "repairer",
        "motor",
        "engineer"
    ],
    "wof:name":"Ashmore Motors Pty Ltd",
    "wof:placetype":"venue"
},
  "geometry": {"coordinates":[150.95645141599999,-33.8020744324],"type":"Point"}
}