{
  "type": "Feature",
  "properties": {
    "addr:full":"188 John St Singleton NSW 2330",
    "addr:housenumber":"188",
    "addr:postcode":"2330",
    "addr:street":"John St",
    "iso:country":"AU",
    "sg:address":"188 John St",
    "sg:city":"Singleton",
    "sg:classifiers":[
        {
            "category":"Professional",
            "subcategory":"Testing Lab",
            "type":"Services"
        }
    ],
    "sg:phone":"+61 2 6572 3377",
    "sg:postcode":"2330",
    "sg:province":"NSW",
    "sg:tags":[
        "soil",
        "investigation"
    ],
    "wof:name":"Parsons Brinckerhoff",
    "wof:placetype":"venue"
},
  "geometry": {"coordinates":[151.170151,-32.562019],"type":"Point"}
}