{
  "type": "Feature",
  "properties": {
    "iso:country":"AU",
    "sg:address":"750 Princess Hwy",
    "sg:city":"Laverton North",
    "sg:classifiers":[
        {
            "category":"Retail",
            "subcategory":"Auto Repair",
            "type":"Services"
        }
    ],
    "sg:phone":"+61 3 9314 9333",
    "sg:postcode":"3026",
    "sg:province":"VIC",
    "sg:tags":[
        "repairer",
        "motor",
        "engineer"
    ],
    "wof:name":"Merc German Prestige Pty Ltd",
    "wof:placetype":"venue"
},
  "geometry": {"coordinates":[144.826828,-37.822758],"type":"Point"}
}