{
  "type": "Feature",
  "properties": {
    "addr:full":"32 Buckajo Rd North Bega NSW 2550",
    "addr:housenumber":"32",
    "addr:postcode":"2550",
    "addr:street":"Buckajo Rd",
    "iso:country":"AU",
    "sg:address":"32 Buckajo Rd",
    "sg:city":"North Bega",
    "sg:classifiers":[
        {
            "category":"Home & Garden",
            "subcategory":"Garden Supply",
            "type":"Retail Goods"
        }
    ],
    "sg:phone":"+61 2 6492 4028",
    "sg:postcode":"2550",
    "sg:province":"NSW",
    "sg:tags":[
        "landscape"
    ],
    "wof:name":"Bega Landscape Supplies",
    "wof:placetype":"venue"
},
  "geometry": {"coordinates":[149.82330322300001,-36.6747970581],"type":"Point"}
}