{
  "type": "Feature",
  "properties": {
    "addr:full":"293 Parramatta Rd Auburn NSW 2144",
    "addr:housenumber":"293",
    "addr:postcode":"2144",
    "addr:street":"Parramatta Rd",
    "iso:country":"AU",
    "sg:address":"293 Parramatta Rd",
    "sg:city":"Auburn",
    "sg:classifiers":[
        {
            "category":"Government",
            "subcategory":"Department Of Motor Vehicles",
            "type":"Public Place"
        }
    ],
    "sg:phone":"+61 2 9648 4284",
    "sg:postcode":"2144",
    "sg:province":"NSW",
    "sg:tags":[
        "wholesaler",
        "mfrs",
        "accessory"
    ],
    "wof:name":"Loadrail",
    "wof:placetype":"venue"
},
  "geometry": {"coordinates":[151.02536010700001,-33.8367805481],"type":"Point"}
}