{
  "type": "Feature",
  "properties": {
    "iso:country":"AU",
    "sg:address":"93 Newton Rd",
    "sg:city":"Wetherill Park",
    "sg:classifiers":[
        {
            "category":"Autos & Motor Vehicles",
            "subcategory":"Boat Sales",
            "type":"Retail Goods"
        }
    ],
    "sg:phone":"+61 2 9756 5745",
    "sg:postcode":"2164",
    "sg:province":"NSW",
    "sg:tags":[
        "builder",
        "yacht",
        "repairer"
    ],
    "wof:name":"Ocean Spray Marine",
    "wof:placetype":"venue"
},
  "geometry": {"coordinates":[150.891555786,-33.8476486206],"type":"Point"}
}