{
  "type": "Feature",
  "properties": {
    "iso:country":"AU",
    "sg:address":"Suite 23, Level 1, 2- 14 Station Pl",
    "sg:city":"Werribee",
    "sg:classifiers":[
        {
            "category":"Professional",
            "subcategory":"Accounting & Tax Preparation",
            "type":"Services"
        }
    ],
    "sg:phone":"+61 3 9742 3844",
    "sg:postcode":"3030",
    "sg:province":"VIC",
    "sg:tags":[
        "accountant",
        "auditor"
    ],
    "wof:name":"Accounting, Business & Tax Professionals, CPA's",
    "wof:placetype":"venue"
},
  "geometry": {"coordinates":[144.66153,-37.900047],"type":"Point"}
}