{
  "type": "Feature",
  "properties": {
    "iso:country":"AU",
    "sg:address":"8 Amy St",
    "sg:city":"Moonah",
    "sg:classifiers":[
        {
            "category":"Retail",
            "subcategory":"Auto Repair",
            "type":"Services"
        }
    ],
    "sg:phone":"+61 3 6273 2010",
    "sg:postcode":"7009",
    "sg:province":"TAS",
    "sg:tags":[
        "testing",
        "inspection",
        "motor",
        "vehicle"
    ],
    "wof:name":"Dawes Automotive",
    "wof:placetype":"venue"
},
  "geometry": {"coordinates":[147.29246520999999,-42.8447532654],"type":"Point"}
}