{
  "type": "Feature",
  "properties": {
    "addr:full":"271 Burke Rd Glen Iris VIC 3146",
    "addr:housenumber":"271",
    "addr:postcode":"3146",
    "addr:street":"Burke Rd",
    "iso:country":"AU",
    "sg:address":"271 Burke Rd",
    "sg:city":"Glen Iris",
    "sg:classifiers":[
        {
            "category":"Shopping",
            "subcategory":"Stationery & Office Supplies",
            "type":"Retail Goods"
        }
    ],
    "sg:phone":"+61 412 349 048",
    "sg:postcode":"3146",
    "sg:province":"VIC",
    "sg:tags":[
        "equipment",
        "display",
        "exhibition"
    ],
    "wof:name":"The Prop Shop",
    "wof:placetype":"venue"
},
  "geometry": {"coordinates":[145.05215454099999,-37.8540039062],"type":"Point"}
}