{
  "type": "Feature",
  "properties": {
    "addr:full":"35 Machinery Drv Tweed Heads South NSW 2486",
    "addr:postcode":"2486",
    "addr:street":"Machinery Drv",
    "iso:country":"AU",
    "sg:address":"35 Machinery Drv",
    "sg:city":"Tweed Heads South",
    "sg:classifiers":[
        {
            "category":"Home & Garden",
            "subcategory":"Hardware",
            "type":"Retail Goods"
        }
    ],
    "sg:phone":"+61 7 5524 3919",
    "sg:postcode":"2486",
    "sg:province":"NSW",
    "sg:tags":[
        "nut",
        "bolt"
    ],
    "wof:name":"Southern Cross Fasteners",
    "wof:placetype":"venue"
},
  "geometry": {"coordinates":[153.542892456,-28.2038803101],"type":"Point"}
}