{
  "type": "Feature",
  "properties": {
    "iso:country":"AU",
    "sg:address":"116 Oswald La",
    "sg:city":"Lochinvar",
    "sg:classifiers":[
        {
            "category":"Farming",
            "subcategory":"Livestock Farm",
            "type":"Manufacturing & Wholesale Goods"
        }
    ],
    "sg:phone":"+61 2 4930 7899",
    "sg:postcode":"2321",
    "sg:province":"NSW",
    "sg:tags":[
        "breeder",
        "horse",
        "stud"
    ],
    "wof:name":"Helden Park Studs",
    "wof:placetype":"venue"
},
  "geometry": {"coordinates":[151.42228698700001,-32.6966094971],"type":"Point"}
}