{
  "type": "Feature",
  "properties": {
    "addr:full":"Shop 4/ 226 Oxford St Leederville WA 6007",
    "addr:housenumber":"shop 4 / 226",
    "addr:postcode":"6007",
    "addr:street":"Oxford St",
    "iso:country":"AU",
    "sg:address":"Shop 4/ 226 Oxford St",
    "sg:city":"Leederville",
    "sg:classifiers":[
        {
            "category":"Personal",
            "subcategory":"Beauty Salon",
            "type":"Services"
        }
    ],
    "sg:phone":"+61 8 9444 3344",
    "sg:postcode":"6007",
    "sg:province":"WA",
    "sg:tags":[
        "hairdresser"
    ],
    "wof:name":"NRG Hairdressing",
    "wof:placetype":"venue"
},
  "geometry": {"coordinates":[115.841392517,-31.9333763123],"type":"Point"}
}