{
  "type": "Feature",
  "properties": {
    "addr:full":"102 Cumberland Rd Pascoe Vale VIC 3044",
    "addr:housenumber":"102",
    "addr:postcode":"3044",
    "addr:street":"Cumberland Rd",
    "iso:country":"AU",
    "sg:address":"102 Cumberland Rd",
    "sg:city":"Pascoe Vale",
    "sg:classifiers":[
        {
            "category":"Personal",
            "subcategory":"Massage",
            "type":"Services"
        }
    ],
    "sg:phone":"+61 3 9354 3210",
    "sg:postcode":"3044",
    "sg:province":"VIC",
    "sg:tags":[
        "therapy"
    ],
    "wof:name":"Brooke Michie",
    "wof:placetype":"venue"
},
  "geometry": {"coordinates":[144.93942260700001,-37.7269821167],"type":"Point"}
}