{
  "type": "Feature",
  "properties": {
    "iso:country":"AU",
    "sg:address":"212 High St",
    "sg:city":"Heathcote",
    "sg:classifiers":[
        {
            "category":"Autos & Motor Vehicles",
            "subcategory":"Fuel & Gas Station",
            "type":"Retail Goods"
        }
    ],
    "sg:phone":"+61 3 5433 2090",
    "sg:postcode":"3523",
    "sg:province":"VIC",
    "wof:name":"Heathcote Northend Roadhouse Pty Ltd",
    "wof:placetype":"venue"
},
  "geometry": {"coordinates":[144.702698,-36.916119],"type":"Point"}
}