{
  "type": "Feature",
  "properties": {
    "addr:full":"69 Frederick St Northgate QLD 4013",
    "addr:housenumber":"69",
    "addr:postcode":"4013",
    "addr:street":"Frederick St",
    "iso:country":"AU",
    "sg:address":"69 Frederick St",
    "sg:city":"Northgate",
    "sg:classifiers":[
        {
            "category":"Mining & Drilling",
            "type":"Manufacturing & Wholesale Goods"
        }
    ],
    "sg:phone":"+61 7 3256 7092",
    "sg:postcode":"4013",
    "sg:province":"QLD",
    "sg:tags":[
        "boring",
        "contractor"
    ],
    "wof:name":"Queensland Pre-Stressing Pty Ltd",
    "wof:placetype":"venue"
},
  "geometry": {"coordinates":[153.07643127399999,-27.3864212036],"type":"Point"}
}