{
  "type": "Feature",
  "properties": {
    "addr:full":"82 Michelangelo Crs Mackenzie QLD 4156",
    "addr:housenumber":"82",
    "addr:postcode":"4156",
    "addr:street":"Michelangelo Crs",
    "iso:country":"AU",
    "sg:address":"82 Michelangelo Crs",
    "sg:city":"Mackenzie",
    "sg:classifiers":[
        {
            "category":"Education",
            "subcategory":"Music School",
            "type":"Public Place"
        }
    ],
    "sg:phone":"+61 414 892 716",
    "sg:postcode":"4156",
    "sg:province":"QLD",
    "sg:tags":[
        "therapy",
        "relaxation"
    ],
    "wof:name":"Floation Centre South Side",
    "wof:placetype":"venue"
},
  "geometry": {"coordinates":[153.122116089,-27.5388393402],"type":"Point"}
}