{
  "type": "Feature",
  "properties": {
    "addr:full":"53 Richard St Newcomb VIC 3219",
    "addr:housenumber":"53",
    "addr:postcode":"3219",
    "addr:street":"Richard St",
    "iso:country":"AU",
    "sg:address":"53 Richard St",
    "sg:city":"Newcomb",
    "sg:classifiers":[
        {
            "category":"Education",
            "subcategory":"Kindergarten",
            "type":"Public Place"
        }
    ],
    "sg:phone":"+61 3 5248 1741",
    "sg:postcode":"3219",
    "sg:province":"VIC",
    "sg:tags":[
        "pre-schools"
    ],
    "wof:name":"Kirralee Kindergarten",
    "wof:placetype":"venue"
},
  "geometry": {"coordinates":[144.39968872099999,-38.1658401489],"type":"Point"}
}