{
  "type": "Feature",
  "properties": {
    "addr:full":"21 Lea Rd Mulgrave VIC 3170",
    "addr:housenumber":"21",
    "addr:postcode":"3170",
    "addr:street":"Lea Rd",
    "iso:country":"AU",
    "sg:address":"21 Lea Rd",
    "sg:city":"Mulgrave",
    "sg:classifiers":[
        {
            "category":"Insurance",
            "subcategory":"Insurance Agent",
            "type":"Services"
        }
    ],
    "sg:phone":"+61 3 9560 5444",
    "sg:postcode":"3170",
    "sg:province":"VIC",
    "sg:tags":[
        "broker"
    ],
    "wof:name":"Rodgers Bob Insurances Pty Ltd",
    "wof:placetype":"venue"
},
  "geometry": {"coordinates":[145.16891479500001,-37.9225959778],"type":"Point"}
}