{
  "type": "Feature",
  "properties": {
    "iso:country":"AU",
    "sg:address":"Lot 7 Alice St",
    "sg:city":"Mittagong",
    "sg:classifiers":[
        {
            "category":"Social Services",
            "subcategory":"Adult Care",
            "type":"Services"
        }
    ],
    "sg:phone":"+61 2 4872 4665",
    "sg:postcode":"2575",
    "sg:province":"NSW",
    "sg:tags":[
        "aged"
    ],
    "wof:name":"Anglican Retirement Villages Community Services",
    "wof:placetype":"venue"
},
  "geometry": {"coordinates":[150.449493408,-34.450214386],"type":"Point"}
}