{
  "type": "Feature",
  "properties": {
    "addr:full":"200 Burraneer Bay Rd Cronulla NSW 2230",
    "addr:housenumber":"200",
    "addr:postcode":"2230",
    "addr:street":"Burraneer Bay Rd",
    "iso:country":"AU",
    "sg:address":"200 Burraneer Bay Rd",
    "sg:city":"Cronulla",
    "sg:classifiers":[
        {
            "category":"Building & Trades",
            "subcategory":"Construction",
            "type":"Services"
        }
    ],
    "sg:phone":"+61 2 9527 1107",
    "sg:postcode":"2230",
    "sg:province":"NSW",
    "sg:tags":[
        "joiner",
        "carpenter"
    ],
    "wof:name":"Bezzina Contract Carpenters Pty Ltd",
    "wof:placetype":"venue"
},
  "geometry": {"coordinates":[151.13006591800001,-34.051525116],"type":"Point"}
}