{
  "type": "Feature",
  "properties": {
    "addr:full":"U17/ 38 Union St Adelaide SA 5000",
    "addr:postcode":"5000",
    "addr:street":"/ 38 Union St",
    "iso:country":"AU",
    "sg:address":"U17/ 38 Union St",
    "sg:city":"Adelaide",
    "sg:classifiers":[
        {
            "category":"Utilities",
            "subcategory":"Telephone",
            "type":"Services"
        }
    ],
    "sg:phone":"+61 8 8227 0050",
    "sg:postcode":"5000",
    "sg:province":"SA",
    "sg:tags":[
        "accessory"
    ],
    "wof:name":"Tel Pacific Pty Ltd",
    "wof:placetype":"venue"
},
  "geometry": {"coordinates":[138.608840942,-34.9237632751],"type":"Point"}
}