{
  "type": "Feature",
  "properties": {
    "iso:country":"AU",
    "sg:address":"17 Southerly St",
    "sg:city":"Mermaid Waters",
    "sg:classifiers":[
        {
            "category":"Building & Trades",
            "subcategory":"Plumbing",
            "type":"Services"
        }
    ],
    "sg:phone":"+61 7 5526 6899",
    "sg:postcode":"4218",
    "sg:province":"QLD",
    "sg:tags":[
        "plumber",
        "gasfitters"
    ],
    "wof:name":"Skrabanich M & C",
    "wof:placetype":"venue"
},
  "geometry": {"coordinates":[153.417800903,-28.0475654602],"type":"Point"}
}