{
  "type": "Feature",
  "properties": {
    "addr:full":"1 A Newman Rd Croydon VIC 3136",
    "addr:housenumber":"1 a",
    "addr:postcode":"3136",
    "addr:street":"Newman Rd",
    "iso:country":"AU",
    "sg:address":"1 A Newman Rd",
    "sg:city":"Croydon",
    "sg:classifiers":[
        {
            "category":"Wholesale",
            "subcategory":"Machinery & Supplies",
            "type":"Manufacturing & Wholesale Goods"
        }
    ],
    "sg:phone":"+61 3 9725 1819",
    "sg:postcode":"3136",
    "sg:province":"VIC",
    "sg:tags":[
        "machine",
        "tool",
        "engineer"
    ],
    "wof:name":"Cape Diamond Pty Ltd",
    "wof:placetype":"venue"
},
  "geometry": {"coordinates":[145.30592346200001,-37.7879180908],"type":"Point"}
}