{
  "type": "Feature",
  "properties": {
    "iso:country":"AU",
    "sg:address":"8/ 17 High St",
    "sg:city":"Fremantle",
    "sg:classifiers":[
        {
            "category":"Education",
            "subcategory":"School",
            "type":"Public Place"
        }
    ],
    "sg:phone":"+61 8 9433 5838",
    "sg:postcode":"6160",
    "sg:province":"WA",
    "sg:tags":[
        "correspondence"
    ],
    "wof:name":"Indo-Asian Language & Secretarial Academy",
    "wof:placetype":"venue"
},
  "geometry": {"coordinates":[115.745148,-32.054771],"type":"Point"}
}