{
  "type": "Feature",
  "properties": {
    "iso:country":"AU",
    "sg:address":"29 Ayrshire Crs",
    "sg:city":"Sandgate",
    "sg:classifiers":[
        {
            "category":"Retail",
            "subcategory":"Storage",
            "type":"Services"
        }
    ],
    "sg:phone":"+61 2 4960 2751",
    "sg:postcode":"2304",
    "sg:province":"NSW",
    "wof:name":"Kennards Self Storage",
    "wof:placetype":"venue"
},
  "geometry": {"coordinates":[151.704711914,-32.8609695435],"type":"Point"}
}