{
  "type": "Feature",
  "properties": {
    "iso:country":"AU",
    "sg:address":"Farndons Rd",
    "sg:city":"Mt Dandenong",
    "sg:classifiers":[
        {
            "category":"Education",
            "subcategory":"School",
            "type":"Public Place"
        }
    ],
    "sg:phone":"+61 3 9751 1136",
    "sg:postcode":"3767",
    "sg:province":"VIC",
    "sg:tags":[
        "state",
        "except",
        "nsw"
    ],
    "wof:name":"Mt Dandenong Primary",
    "wof:placetype":"venue"
},
  "geometry": {"coordinates":[145.36155700699999,-37.8300743103],"type":"Point"}
}