{
  "type": "Feature",
  "properties": {
    "addr:full":"439 St Georges Rd Thornbury VIC 3071",
    "addr:housenumber":"439",
    "addr:postcode":"3071",
    "addr:street":"St Georges Rd",
    "iso:country":"AU",
    "sg:address":"439 St Georges Rd",
    "sg:city":"Thornbury",
    "sg:classifiers":[
        {
            "category":"Shopping",
            "subcategory":"Antiques",
            "type":"Retail Goods"
        }
    ],
    "sg:phone":"+61 3 9484 2443",
    "sg:postcode":"3071",
    "sg:province":"VIC",
    "wof:name":"Tonys",
    "wof:placetype":"venue"
},
  "geometry": {"coordinates":[144.99334716800001,-37.7568321228],"type":"Point"}
}