{
  "type": "Feature",
  "properties": {
    "iso:country":"AU",
    "sg:address":"Caseys Rd",
    "sg:city":"Sanctuary Cove",
    "sg:classifiers":[
        {
            "category":"Travel",
            "subcategory":"Hotels & Motels",
            "type":"Entertainment"
        }
    ],
    "sg:phone":"+61 7 5577 9944",
    "sg:postcode":"4212",
    "sg:province":"QLD",
    "wof:name":"Sanctuary Cove Villas",
    "wof:placetype":"venue"
},
  "geometry": {"coordinates":[153.355377197,-27.8620681763],"type":"Point"}
}