{
  "type": "Feature",
  "properties": {
    "iso:country":"AU",
    "sg:address":"Level 5",
    "sg:city":"Westfield Shopping Centre Parramatta Westfiel",
    "sg:classifiers":[
        {
            "category":"Shopping",
            "subcategory":"Mobile Phones",
            "type":"Retail Goods"
        }
    ],
    "sg:phone":"+61 2 9635 6122",
    "sg:postcode":"2150",
    "sg:province":"NSW",
    "sg:tags":[
        "telephone",
        "accessory"
    ],
    "wof:name":"Dr Boom Communications",
    "wof:placetype":"venue"
},
  "geometry": {"coordinates":[151.00135803200001,-33.8177185059],"type":"Point"}
}