{
  "type": "Feature",
  "properties": {
    "iso:country":"AU",
    "sg:address":"163 Glenferrie Rd",
    "sg:city":"Malvern",
    "sg:classifiers":[
        {
            "category":"Shopping",
            "subcategory":"Gifts & Souvenirs",
            "type":"Retail Goods"
        }
    ],
    "sg:phone":"+61 3 9509 3253",
    "sg:postcode":"3144",
    "sg:province":"VIC",
    "sg:tags":[
        "print",
        "poster",
        "pictures"
    ],
    "wof:name":"Picture Market",
    "wof:placetype":"venue"
},
  "geometry": {"coordinates":[145.0284729,-37.8606300354],"type":"Point"}
}