{
  "type": "Feature",
  "properties": {
    "iso:country":"AU",
    "sg:address":"School Rd",
    "sg:city":"Torrumbarry",
    "sg:classifiers":[
        {
            "category":"Education",
            "subcategory":"School",
            "type":"Public Place"
        }
    ],
    "sg:phone":"+61 3 5487 7285",
    "sg:postcode":"3562",
    "sg:province":"VIC",
    "sg:tags":[
        "state",
        "except",
        "nsw"
    ],
    "wof:name":"Welton Primary School",
    "wof:placetype":"venue"
},
  "geometry": {"coordinates":[144.528564453,-36.0112915039],"type":"Point"}
}