{
  "type": "Feature",
  "properties": {
    "addr:full":"U3/ 33 Windsor St Richmond NSW 2753",
    "addr:housenumber":"33",
    "addr:postcode":"2753",
    "addr:street":"U3 /;Windsor St",
    "iso:country":"AU",
    "sg:address":"U3/ 33 Windsor St",
    "sg:city":"Richmond",
    "sg:classifiers":[
        {
            "category":"Personal",
            "subcategory":"Beauty Salon",
            "type":"Services"
        }
    ],
    "sg:phone":"+61 2 4578 6666",
    "sg:postcode":"2753",
    "sg:province":"NSW",
    "wof:name":"Beauty & Hair Supplies",
    "wof:placetype":"venue"
},
  "geometry": {"coordinates":[150.756759644,-33.599407196],"type":"Point"}
}