{
  "type": "Feature",
  "properties": {
    "addr:full":"1015 Howitt St Ballarat VIC 3350",
    "addr:housenumber":"1015",
    "addr:postcode":"3350",
    "addr:street":"Howitt St",
    "iso:country":"AU",
    "sg:address":"1015 Howitt St",
    "sg:city":"Ballarat",
    "sg:classifiers":[
        {
            "category":"Structure",
            "subcategory":"Bridge",
            "type":"Public Place"
        }
    ],
    "sg:phone":"+61 3 5339 6008",
    "sg:postcode":"3350",
    "sg:province":"VIC",
    "sg:tags":[
        "chainsaw",
        "brushcutters"
    ],
    "wof:name":"Torquepower",
    "wof:placetype":"venue"
},
  "geometry": {"coordinates":[143.838425,-37.541206],"type":"Point"}
}