{
  "type": "Feature",
  "properties": {
    "iso:country":"AU",
    "sg:address":"PO Box 951",
    "sg:city":"Glen Waverley",
    "sg:classifiers":[
        {
            "category":"Organizations",
            "subcategory":"Professional Association",
            "type":"Services"
        }
    ],
    "sg:phone":"+61 3 9887 1877",
    "sg:postcode":"8706",
    "sg:province":"VIC",
    "sg:tags":[
        "web",
        "internet"
    ],
    "wof:name":"Intense Design",
    "wof:placetype":"venue"
},
  "geometry": {"coordinates":[145.165115,-37.882961],"type":"Point"}
}