{
  "type": "Feature",
  "properties": {
    "iso:country":"AU",
    "sg:address":"28/ 41-49 Norcal Rd",
    "sg:city":"Nunawading",
    "sg:classifiers":[
        {
            "category":"Wholesale",
            "subcategory":"Painting Supplies",
            "type":"Manufacturing & Wholesale Goods"
        }
    ],
    "sg:phone":"+61 3 9872 5898",
    "sg:postcode":"3131",
    "sg:province":"VIC",
    "sg:tags":[
        "product",
        "cleaning"
    ],
    "wof:name":"MCH Australia Pty Ltd",
    "wof:placetype":"venue"
},
  "geometry": {"coordinates":[145.181365967,-37.8223228455],"type":"Point"}
}