{
  "type": "Feature",
  "properties": {
    "iso:country":"AU",
    "sg:address":"121- 127 Jardine St",
    "sg:city":"Fairy Meadow",
    "sg:classifiers":[
        {
            "category":"Organizations",
            "subcategory":"Community Association",
            "type":"Services"
        }
    ],
    "sg:phone":"+61 2 4284 8777",
    "sg:postcode":"2519",
    "sg:province":"NSW",
    "sg:tags":[
        "cheese",
        "product"
    ],
    "wof:name":"Corrado & Frank Distributors Pty Ltd",
    "wof:placetype":"venue"
},
  "geometry": {"coordinates":[150.891373,-34.388412],"type":"Point"}
}