{
  "type": "Feature",
  "properties": {
    "iso:country":"AU",
    "sg:address":"46 Cassidy St",
    "sg:city":"Kalgoorlie",
    "sg:classifiers":[
        {
            "category":"Retail",
            "subcategory":"Funeral Services",
            "type":"Services"
        }
    ],
    "sg:phone":"+61 8 9021 2023",
    "sg:postcode":"6430",
    "sg:province":"WA",
    "sg:tags":[
        "director"
    ],
    "wof:name":"Goldfields Funeral Directors",
    "wof:placetype":"venue"
},
  "geometry": {"coordinates":[121.47479248,-30.7494659424],"type":"Point"}
}