{
  "type": "Feature",
  "properties": {
    "addr:full":"94 Glengala Rd Sunshine West VIC 3020",
    "addr:housenumber":"94",
    "addr:postcode":"3020",
    "addr:street":"Glengala Rd",
    "iso:country":"AU",
    "sg:address":"94 Glengala Rd",
    "sg:city":"Sunshine West",
    "sg:classifiers":[
        {
            "category":"Building & Trades",
            "subcategory":"Construction",
            "type":"Services"
        }
    ],
    "sg:phone":"+61 418 530 652",
    "sg:postcode":"3020",
    "sg:province":"VIC",
    "sg:tags":[
        "contractor"
    ],
    "wof:name":"Dynasty Homes (Aust) Pty Ltd",
    "wof:placetype":"venue"
},
  "geometry": {"coordinates":[144.81622300000001,-37.789993],"type":"Point"}
}