{
  "type": "Feature",
  "properties": {
    "addr:full":"Lvl 1/ 86 Bay St Broadway NSW 2007",
    "addr:housenumber":"/ 86",
    "addr:postcode":"2007",
    "addr:street":"Bay St",
    "iso:country":"AU",
    "sg:address":"Lvl 1/ 86 Bay St",
    "sg:city":"Broadway",
    "sg:classifiers":[
        {
            "category":"Professional",
            "subcategory":"Accounting & Tax Preparation",
            "type":"Services"
        }
    ],
    "sg:phone":"+61 2 9281 5750",
    "sg:postcode":"2007",
    "sg:province":"NSW",
    "sg:tags":[
        "accountant",
        "auditor"
    ],
    "wof:name":"Broadway Accountants",
    "wof:placetype":"venue"
},
  "geometry": {"coordinates":[151.19512939399999,-33.8837013245],"type":"Point"}
}