{
  "type": "Feature",
  "properties": {
    "addr:full":"182 Princes Hwy Hallam VIC 3803",
    "addr:housenumber":"182",
    "addr:postcode":"3803",
    "addr:street":"Princes Hwy",
    "iso:country":"AU",
    "sg:address":"182 Princes Hwy",
    "sg:city":"Hallam",
    "sg:classifiers":[
        {
            "category":"Health Services",
            "subcategory":"Health Practitioner",
            "type":"Services"
        }
    ],
    "sg:phone":"+61 1800 647 464",
    "sg:postcode":"3803",
    "sg:province":"VIC",
    "sg:tags":[
        "psychologist"
    ],
    "wof:name":"Joan Spencer & Associates",
    "wof:placetype":"venue"
},
  "geometry": {"coordinates":[145.267181397,-38.0050773621],"type":"Point"}
}