{
  "type": "Feature",
  "properties": {
    "iso:country":"AU",
    "sg:address":"405 Newman Rd",
    "sg:city":"Geebung",
    "sg:phone":"+61 13 19 26",
    "sg:postcode":"4034",
    "sg:province":"QLD",
    "wof:name":"Everhard Industries",
    "wof:placetype":"venue"
},
  "geometry": {"coordinates":[153.048462,-27.36669],"type":"Point"}
}