{
  "type": "Feature",
  "properties": {
    "iso:country":"AU",
    "sg:address":"26 Chandler St",
    "sg:city":"Belconnen",
    "sg:classifiers":[
        {
            "category":"Social Services",
            "subcategory":"Child Care",
            "type":"Services"
        }
    ],
    "sg:phone":"+61 2 6264 0200",
    "sg:postcode":"2617",
    "sg:province":"ACT",
    "wof:name":"Belconnen Community Service",
    "wof:placetype":"venue"
},
  "geometry": {"coordinates":[149.070144653,-35.2389411926],"type":"Point"}
}