{
  "type": "Feature",
  "properties": {
    "addr:full":"187- 189 Orlando St Coffs Harbour NSW 2450",
    "addr:housenumber":"189",
    "addr:postcode":"2450",
    "addr:street":"Orlando St",
    "iso:country":"AU",
    "sg:address":"187- 189 Orlando St",
    "sg:city":"Coffs Harbour",
    "sg:classifiers":[
        {
            "category":"Autos & Motor Vehicles",
            "subcategory":"Automobile Sales",
            "type":"Retail Goods"
        }
    ],
    "sg:phone":"+61 2 6652 3666",
    "sg:postcode":"2450",
    "sg:province":"NSW",
    "sg:tags":[
        "car",
        "used"
    ],
    "wof:name":"Alliance Motors",
    "wof:placetype":"venue"
},
  "geometry": {"coordinates":[153.12745699999999,-30.285246],"type":"Point"}
}