{
  "type": "Feature",
  "properties": {
    "addr:full":"3/ 28 Auger Way Margaret River WA 6285",
    "addr:housenumber":"/ 28",
    "addr:postcode":"6285",
    "addr:street":"Auger Way",
    "iso:country":"AU",
    "sg:address":"3/ 28 Auger Way",
    "sg:city":"Margaret River",
    "sg:classifiers":[
        {
            "category":"Professional",
            "subcategory":"Engineering",
            "type":"Services"
        }
    ],
    "sg:phone":"+61 8 9757 9927",
    "sg:postcode":"6285",
    "sg:province":"WA",
    "sg:tags":[
        "diesel",
        "engineer"
    ],
    "wof:name":"Margaret River Diesel Power",
    "wof:placetype":"venue"
},
  "geometry": {"coordinates":[115.06980133099999,-33.9651222229],"type":"Point"}
}