{
  "type": "Feature",
  "properties": {
    "addr:full":"Peawah St Wedgefield WA 6721",
    "addr:postcode":"6721",
    "addr:street":"St",
    "iso:country":"AU",
    "sg:address":"Peawah St",
    "sg:city":"Wedgefield",
    "sg:classifiers":[
        {
            "category":"Wholesale",
            "subcategory":"Machinery & Supplies",
            "type":"Manufacturing & Wholesale Goods"
        }
    ],
    "sg:phone":"+61 8 9172 3456",
    "sg:postcode":"6721",
    "sg:province":"WA",
    "sg:tags":[
        "equipment",
        "welding"
    ],
    "wof:name":"BOC Gas & Gear",
    "wof:placetype":"venue"
},
  "geometry": {"coordinates":[118.59201049799999,-20.3698635101],"type":"Point"}
}