{
  "type": "Feature",
  "properties": {
    "iso:country":"AU",
    "sg:address":"2 Hampstead Rd",
    "sg:city":"Auburn",
    "sg:classifiers":[
        {
            "category":"Retail",
            "subcategory":"Auto Repair",
            "type":"Services"
        }
    ],
    "sg:phone":"+61 2 9648 3064",
    "sg:postcode":"2144",
    "sg:province":"NSW",
    "sg:tags":[
        "repairer",
        "motor",
        "engineer"
    ],
    "wof:name":"Auburn Diesel & Motor Repairs Pty Ltd",
    "wof:placetype":"venue"
},
  "geometry": {"coordinates":[151.02809143100001,-33.8440628052],"type":"Point"}
}