{
  "type": "Feature",
  "properties": {
    "addr:full":"Shop 7 51 Rockingham Rd Hamilton Hill WA 6163",
    "addr:housenumber":"shop;51",
    "addr:postcode":"6163",
    "addr:street":"Rockingham Rd",
    "iso:country":"AU",
    "sg:address":"Shop 7 51 Rockingham Rd",
    "sg:city":"Hamilton Hill",
    "sg:classifiers":[
        {
            "category":"Shopping",
            "subcategory":"Baby Store",
            "type":"Retail Goods"
        }
    ],
    "sg:phone":"+61 8 9430 7707",
    "sg:postcode":"6163",
    "sg:province":"WA",
    "sg:tags":[
        "wear"
    ],
    "wof:name":"Costa Azzurra Emporium",
    "wof:placetype":"venue"
},
  "geometry": {"coordinates":[115.769676,-32.082283],"type":"Point"}
}