{
  "type": "Feature",
  "properties": {
    "iso:country":"AU",
    "sg:address":"11 Seventh Ave",
    "sg:city":"South Perth",
    "sg:classifiers":[
        {
            "category":"Utilities",
            "subcategory":"Water",
            "type":"Services"
        }
    ],
    "sg:phone":"+61 8 9474 1894",
    "sg:postcode":"6151",
    "sg:province":"WA",
    "sg:tags":[
        "hot",
        "system"
    ],
    "wof:name":"A Premier Electrics",
    "wof:placetype":"venue"
},
  "geometry": {"coordinates":[115.885239,-31.98214],"type":"Point"}
}