{
  "type": "Feature",
  "properties": {
    "addr:full":"Whitecross Rd Winmalee NSW 2777",
    "addr:postcode":"2777",
    "addr:street":"Whitecross Rd",
    "iso:country":"AU",
    "sg:address":"Whitecross Rd",
    "sg:city":"Winmalee",
    "sg:classifiers":[
        {
            "category":"Food & Beverages",
            "subcategory":"Supermarket",
            "type":"Retail Goods"
        }
    ],
    "sg:phone":"+61 2 4754 2676",
    "sg:postcode":"2777",
    "sg:province":"NSW",
    "sg:tags":[
        "grocery",
        "store"
    ],
    "wof:name":"Bi-Lo",
    "wof:placetype":"venue"
},
  "geometry": {"coordinates":[150.60940551799999,-33.6720542908],"type":"Point"}
}