{
  "type": "Feature",
  "properties": {
    "addr:full":"Shop 2 6 Oak St Evans Head NSW 2473",
    "addr:housenumber":"shop;6",
    "addr:postcode":"2473",
    "addr:street":"Oak St Evans",
    "iso:country":"AU",
    "sg:address":"Shop 2 6 Oak St",
    "sg:city":"Evans Head",
    "sg:classifiers":[
        {
            "category":"Personal",
            "subcategory":"Beauty Salon",
            "type":"Services"
        }
    ],
    "sg:phone":"+61 2 6682 4538",
    "sg:postcode":"2473",
    "sg:province":"NSW",
    "sg:tags":[
        "hairdresser"
    ],
    "wof:name":"Julies Hairbyz",
    "wof:placetype":"venue"
},
  "geometry": {"coordinates":[153.43125915499999,-29.117937088],"type":"Point"}
}