{
  "type": "Feature",
  "properties": {
    "addr:full":"Warrenbayne Rd Warrenbayne VIC 3670",
    "addr:postcode":"3670",
    "addr:street":"Warrenbayne Rd",
    "iso:country":"AU",
    "sg:address":"Warrenbayne Rd",
    "sg:city":"Warrenbayne",
    "sg:classifiers":[
        {
            "category":"Building & Trades",
            "subcategory":"Plumbing",
            "type":"Services"
        }
    ],
    "sg:phone":"+61 3 5763 2398",
    "sg:postcode":"3670",
    "sg:province":"VIC",
    "sg:tags":[
        "plumber",
        "gasfitters"
    ],
    "wof:name":"Connell K & E",
    "wof:placetype":"venue"
},
  "geometry": {"coordinates":[145.87571700000001,-36.640335],"type":"Point"}
}