{
  "type": "Feature",
  "properties": {
    "addr:full":"29 Windsor Ave Springvale VIC 3171",
    "addr:housenumber":"29",
    "addr:postcode":"3171",
    "addr:street":"Windsor Ave",
    "iso:country":"AU",
    "sg:address":"29 Windsor Ave",
    "sg:city":"Springvale",
    "sg:classifiers":[
        {
            "category":"Insurance",
            "subcategory":"Life Insurance",
            "type":"Services"
        }
    ],
    "sg:phone":"+61 3 9548 4466",
    "sg:postcode":"3171",
    "sg:province":"VIC",
    "wof:name":"Mekong Corporate Services Pty Ltd",
    "wof:placetype":"venue"
},
  "geometry": {"coordinates":[145.147506714,-37.9512023926],"type":"Point"}
}