{
  "type": "Feature",
  "properties": {
    "addr:full":"100 Shoal Point Rd Bucasia QLD 4750",
    "addr:housenumber":"100",
    "addr:postcode":"4750",
    "addr:street":"Shoal Point Rd",
    "iso:country":"AU",
    "sg:address":"100 Shoal Point Rd",
    "sg:city":"Bucasia",
    "sg:classifiers":[
        {
            "category":"Building & Trades",
            "subcategory":"Construction",
            "type":"Services"
        }
    ],
    "sg:phone":"+61 417 735 671",
    "sg:postcode":"4750",
    "sg:province":"QLD",
    "sg:tags":[
        "renovation",
        "alterations",
        "extension",
        "contractor"
    ],
    "wof:name":"David Groves Building",
    "wof:placetype":"venue"
},
  "geometry": {"coordinates":[149.15472399999999,-21.024698],"type":"Point"}
}