{
  "type": "Feature",
  "properties": {
    "addr:full":"Shop 4 5- 9 Hopetoun Rd Park Orchards VIC 3114",
    "addr:housenumber":"shop;5 9",
    "addr:postcode":"3114",
    "addr:street":"Hopetoun Rd",
    "iso:country":"AU",
    "sg:address":"Shop 4 5- 9 Hopetoun Rd",
    "sg:city":"Park Orchards",
    "sg:classifiers":[
        {
            "category":"Personal",
            "subcategory":"Beauty Salon",
            "type":"Services"
        }
    ],
    "sg:phone":"+61 3 9876 5390",
    "sg:postcode":"3114",
    "sg:province":"VIC",
    "sg:tags":[
        "hairdresser"
    ],
    "wof:name":"Julies Cutting Edge & Hair Design",
    "wof:placetype":"venue"
},
  "geometry": {"coordinates":[145.21731567399999,-37.7795791626],"type":"Point"}
}