{
  "type": "Feature",
  "properties": {
    "addr:full":"17 Corporate Ave Rowville VIC 3178",
    "addr:housenumber":"17",
    "addr:postcode":"3178",
    "addr:street":"Corporate Ave",
    "iso:country":"AU",
    "sg:address":"17 Corporate Ave",
    "sg:city":"Rowville",
    "sg:classifiers":[
        {
            "category":"Military Area",
            "subcategory":"Air Force Base",
            "type":"Public Place"
        }
    ],
    "sg:phone":"+61 3 9213 9300",
    "sg:postcode":"3178",
    "sg:province":"VIC",
    "sg:tags":[
        "equipment",
        "speed",
        "variation"
    ],
    "wof:name":"Vacon Pacific Pty Ltd",
    "wof:placetype":"venue"
},
  "geometry": {"coordinates":[145.21961975100001,-37.9243431091],"type":"Point"}
}