{
  "type": "Feature",
  "properties": {
    "addr:full":"197 Mulgrave Rd Cairns QLD 4870",
    "addr:housenumber":"197",
    "addr:postcode":"4870",
    "addr:street":"Mulgrave Rd",
    "iso:country":"AU",
    "sg:address":"197 Mulgrave Rd",
    "sg:city":"Cairns",
    "sg:classifiers":[
        {
            "category":"Professional",
            "subcategory":"Art Services",
            "type":"Services"
        }
    ],
    "sg:phone":"+61 7 4051 6058",
    "sg:postcode":"4870",
    "sg:province":"QLD",
    "sg:tags":[
        "interior",
        "decorator"
    ],
    "wof:name":"Discount Curtains",
    "wof:placetype":"venue"
},
  "geometry": {"coordinates":[145.74357605,-16.9398918152],"type":"Point"}
}