{
  "type": "Feature",
  "properties": {
    "iso:country":"AU",
    "sg:address":"Level 1 40 Carnarvon Rd",
    "sg:city":"Roseville",
    "sg:classifiers":[
        {
            "category":"Education",
            "subcategory":"Special Training",
            "type":"Public Place"
        }
    ],
    "sg:phone":"+61 2 9416 6900",
    "sg:postcode":"2069",
    "sg:province":"NSW",
    "sg:tags":[
        "development"
    ],
    "wof:name":"Cross Cultural Management Services Pty Ltd",
    "wof:placetype":"venue"
},
  "geometry": {"coordinates":[151.187866211,-33.7746772766],"type":"Point"}
}