{
  "type": "Feature",
  "properties": {
    "iso:country":"AU",
    "sg:address":"100 Main Rd",
    "sg:city":"Adventure Bay",
    "sg:classifiers":[
        {
            "category":"Building & Trades",
            "subcategory":"Construction",
            "type":"Services"
        }
    ],
    "sg:phone":"+61 428 975 408",
    "sg:postcode":"7150",
    "sg:province":"TAS",
    "sg:tags":[
        "earth",
        "excavating",
        "moving",
        "contractor"
    ],
    "wof:name":"Bruny Island Freighting Service",
    "wof:placetype":"venue"
},
  "geometry": {"coordinates":[147.19984435999999,-43.0165748596],"type":"Point"}
}