{
  "type": "Feature",
  "properties": {
    "iso:country":"AU",
    "sg:address":"Shop 28",
    "sg:city":"-30 Tea Tree Plaza Modbury",
    "sg:classifiers":[
        {
            "category":"Food & Beverages",
            "subcategory":"Fruits & Vegetables",
            "type":"Retail Goods"
        }
    ],
    "sg:phone":"+61 8 8263 0588",
    "sg:postcode":"5092",
    "sg:province":"SA",
    "sg:tags":[
        "greengrocer",
        "fruiterer"
    ],
    "wof:name":"Tropicana Fruit & Veg",
    "wof:placetype":"venue"
},
  "geometry": {"coordinates":[138.69236755399999,-34.8331794739],"type":"Point"}
}