{
  "type": "Feature",
  "properties": {
    "iso:country":"AU",
    "sg:address":"Shop 6/ 32 Canberra St St",
    "sg:city":"Johns Park",
    "sg:classifiers":[
        {
            "category":"Personal",
            "subcategory":"Beauty Salon",
            "type":"Services"
        }
    ],
    "sg:phone":"+61 2 9610 0588",
    "sg:postcode":"2176",
    "sg:province":"NSW",
    "sg:tags":[
        "hairdresser"
    ],
    "wof:name":"Bopha Hair Salon",
    "wof:placetype":"venue"
},
  "geometry": {"coordinates":[150.89921569800001,-33.8777122498],"type":"Point"}
}