{
  "type": "Feature",
  "properties": {
    "addr:full":"5 Ardmore Crt Macleod VIC 3085",
    "addr:housenumber":"5",
    "addr:postcode":"3085",
    "addr:street":"Ardmore Crt",
    "iso:country":"AU",
    "sg:address":"5 Ardmore Crt",
    "sg:city":"Macleod",
    "sg:classifiers":[
        {
            "category":"Utilities",
            "subcategory":"Electric",
            "type":"Services"
        }
    ],
    "sg:phone":"+61 418 171 051",
    "sg:postcode":"3085",
    "sg:province":"VIC",
    "sg:tags":[
        "electrical",
        "contractor"
    ],
    "wof:name":"PAZ Electrics",
    "wof:placetype":"venue"
},
  "geometry": {"coordinates":[145.066894531,-37.7201004028],"type":"Point"}
}