{
  "type": "Feature",
  "properties": {
    "iso:country":"AU",
    "sg:address":"12- 18 Yarra Pl",
    "sg:city":"South Melbourne",
    "sg:classifiers":[
        {
            "category":"Wholesale",
            "subcategory":"Apparel",
            "type":"Manufacturing & Wholesale Goods"
        }
    ],
    "sg:phone":"+61 3 9646 2633",
    "sg:postcode":"3205",
    "sg:province":"VIC",
    "sg:tags":[
        "wholesaler",
        "mfrs",
        "uniform"
    ],
    "wof:name":"Lodown Distribution Australia Pty Ltd",
    "wof:placetype":"venue"
},
  "geometry": {"coordinates":[144.960327,-37.831291],"type":"Point"}
}