{
  "type": "Feature",
  "properties": {
    "addr:full":"Syndicate Rd Tully QLD 4854",
    "addr:postcode":"4854",
    "addr:street":"Syndicate Rd",
    "iso:country":"AU",
    "sg:address":"Syndicate Rd",
    "sg:city":"Tully",
    "sg:classifiers":[
        {
            "category":"Home & Garden",
            "subcategory":"Carpets & Floor Coverings",
            "type":"Retail Goods"
        }
    ],
    "sg:phone":"+61 7 4066 7945",
    "sg:postcode":"4854",
    "sg:province":"QLD",
    "sg:tags":[
        "banana",
        "grower"
    ],
    "wof:name":"Chiquita North Queensland Pty Ltd",
    "wof:placetype":"venue"
},
  "geometry": {"coordinates":[145.913864136,-17.9704265594],"type":"Point"}
}