{
  "type": "Feature",
  "properties": {
    "iso:country":"AU",
    "sg:address":"32 Hampstead Rd",
    "sg:city":"Maidstone",
    "sg:classifiers":[
        {
            "category":"Shopping",
            "subcategory":"Party Supplies",
            "type":"Retail Goods"
        }
    ],
    "sg:phone":"+61 3 9318 8534",
    "sg:postcode":"3012",
    "sg:province":"VIC",
    "sg:tags":[
        "hire",
        "costume"
    ],
    "wof:name":"Whizz Bang Costume Hire",
    "wof:placetype":"venue"
},
  "geometry": {"coordinates":[144.873413086,-37.7800788879],"type":"Point"}
}