{
  "type": "Feature",
  "properties": {
    "addr:full":"Level 2 Suite 10 57- 59 Anzac Hwy Ashford SA 5035",
    "addr:housenumber":"57 59",
    "addr:postcode":"5035",
    "addr:street":"Anzac Hwy",
    "iso:country":"AU",
    "sg:address":"Level 2 Suite 10 57- 59 Anzac Hwy",
    "sg:city":"Ashford",
    "sg:classifiers":[
        {
            "category":"Health Services",
            "subcategory":"Doctor",
            "type":"Services"
        }
    ],
    "sg:phone":"+61 8 8297 6888",
    "sg:postcode":"5035",
    "sg:province":"SA",
    "sg:tags":[
        "medical",
        "practitioner"
    ],
    "wof:name":"Sheppard Mark",
    "wof:placetype":"venue"
},
  "geometry": {"coordinates":[138.57688903799999,-34.9488449097],"type":"Point"}
}