{
  "type": "Feature",
  "properties": {
    "addr:full":"Suite 1B, 780 Darling St Rozelle NSW 2039",
    "addr:housenumber":"suite 1b 780",
    "addr:postcode":"2039",
    "addr:street":"Darling St",
    "iso:country":"AU",
    "sg:address":"Suite 1B, 780 Darling St",
    "sg:city":"Rozelle",
    "sg:classifiers":[
        {
            "category":"Health Services",
            "subcategory":"Health Practitioner",
            "type":"Services"
        }
    ],
    "sg:phone":"+61 2 9810 2203",
    "sg:postcode":"2039",
    "sg:province":"NSW",
    "sg:tags":[
        "physiotherapist"
    ],
    "wof:name":"Sargood J W",
    "wof:placetype":"venue"
},
  "geometry": {"coordinates":[151.16702270499999,-33.8659057617],"type":"Point"}
}