{
  "type": "Feature",
  "properties": {
    "addr:full":"Shop 1/ 12 Garfield Rd East Riverstone NSW 2765",
    "addr:housenumber":"shop 1 / 12",
    "addr:postcode":"2765",
    "addr:street":"Garfield Rd East",
    "iso:country":"AU",
    "sg:address":"Shop 1/ 12 Garfield Rd East",
    "sg:city":"Riverstone",
    "sg:classifiers":[
        {
            "category":"Fast Food",
            "type":"Food & Drink"
        }
    ],
    "sg:phone":"+61 2 9838 1618",
    "sg:postcode":"2765",
    "sg:province":"NSW",
    "sg:tags":[
        "away",
        "take"
    ],
    "wof:name":"Pizza Street",
    "wof:placetype":"venue"
},
  "geometry": {"coordinates":[150.86143493599999,-33.6796112061],"type":"Point"}
}