{
  "type": "Feature",
  "properties": {
    "addr:full":"69 Clifton St Balwyn North VIC 3104",
    "addr:housenumber":"69",
    "addr:postcode":"3104",
    "addr:street":"Clifton St",
    "iso:country":"AU",
    "sg:address":"69 Clifton St",
    "sg:city":"Balwyn North",
    "sg:classifiers":[
        {
            "category":"Professional",
            "subcategory":"Computer Services",
            "type":"Services"
        }
    ],
    "sg:phone":"+61 3 9857 3558",
    "sg:postcode":"3104",
    "sg:province":"VIC",
    "sg:tags":[
        "repairs",
        "upgrade",
        "equipment"
    ],
    "wof:name":"Trojan Computers",
    "wof:placetype":"venue"
},
  "geometry": {"coordinates":[145.102416992,-37.7939949036],"type":"Point"}
}