{
  "type": "Feature",
  "properties": {
    "addr:full":"Shp18/ 9 Throssell Rd South Hedland WA 6722",
    "addr:postcode":"6722",
    "addr:street":"Throssell Rd",
    "iso:country":"AU",
    "sg:address":"Shp18/ 9 Throssell Rd",
    "sg:city":"South Hedland",
    "sg:classifiers":[
        {
            "category":"Retail",
            "subcategory":"Auto Repair",
            "type":"Services"
        }
    ],
    "sg:phone":"+61 8 9172 1144",
    "sg:postcode":"6722",
    "sg:province":"WA",
    "sg:tags":[
        "electrical"
    ],
    "wof:name":"West Coast Auto N Sound",
    "wof:placetype":"venue"
},
  "geometry": {"coordinates":[118.601127624,-20.4092636108],"type":"Point"}
}