{
  "type": "Feature",
  "properties": {
    "iso:country":"AU",
    "sg:address":"Shop 30 Alstonville Plz",
    "sg:city":"Alstonville",
    "sg:classifiers":[
        {
            "category":"Personal",
            "subcategory":"Beauty Salon",
            "type":"Services"
        }
    ],
    "sg:phone":"+61 410 685 584",
    "sg:postcode":"2477",
    "sg:province":"NSW",
    "sg:tags":[
        "hairdresser"
    ],
    "wof:name":"Tozer's Top Cuts",
    "wof:placetype":"venue"
},
  "geometry": {"coordinates":[153.44003295900001,-28.8416900635],"type":"Point"}
}