{
  "type": "Feature",
  "properties": {
    "addr:full":"25- 37 Chapman St Blackburn VIC 3130",
    "addr:housenumber":"37",
    "addr:postcode":"3130",
    "addr:street":"Chapman St",
    "iso:country":"AU",
    "sg:address":"25- 37 Chapman St",
    "sg:city":"Blackburn",
    "sg:classifiers":[
        {
            "category":"Structure",
            "subcategory":"Factory",
            "type":"Public Place"
        }
    ],
    "sg:phone":"+61 1300 667 373",
    "sg:postcode":"3130",
    "sg:province":"VIC",
    "sg:tags":[
        "seating",
        "system"
    ],
    "wof:name":"M. G. P. Group Pty Ltd",
    "wof:placetype":"venue"
},
  "geometry": {"coordinates":[145.145217895,-37.8012962341],"type":"Point"}
}