{
  "type": "Feature",
  "properties": {
    "addr:full":"Shop 1-2 60a Lambert Rd Royston Park SA 5070",
    "addr:housenumber":"shop 1-2 60a",
    "addr:postcode":"5070",
    "addr:street":"Lambert Rd",
    "iso:country":"AU",
    "sg:address":"Shop 1-2 60a Lambert Rd",
    "sg:city":"Royston Park",
    "sg:classifiers":[
        {
            "category":"Building & Trades",
            "subcategory":"Construction",
            "type":"Services"
        }
    ],
    "sg:phone":"+61 8 8363 4770",
    "sg:postcode":"5070",
    "sg:province":"SA",
    "sg:tags":[
        "repairing",
        "window"
    ],
    "wof:name":"Leadlight Design & Repair",
    "wof:placetype":"venue"
},
  "geometry": {"coordinates":[138.627243042,-34.8978805542],"type":"Point"}
}