{
  "type": "Feature",
  "properties": {
    "addr:full":"Lvl 1/ 275 West St Umina Beach NSW 2257",
    "addr:housenumber":"/ 275",
    "addr:postcode":"2257",
    "addr:street":"West St",
    "iso:country":"AU",
    "sg:address":"Lvl 1/ 275 West St",
    "sg:city":"Umina Beach",
    "sg:classifiers":[
        {
            "category":"Real Estate",
            "subcategory":"Architect",
            "type":"Services"
        }
    ],
    "sg:phone":"+61 2 4342 2721",
    "sg:postcode":"2257",
    "sg:province":"NSW",
    "sg:tags":[
        "building",
        "designer"
    ],
    "sg:website":"http://www.knight-mapleton.com.au",
    "wof:name":"Knight-Mapleton Design Partners",
    "wof:placetype":"venue"
},
  "geometry": {"coordinates":[151.32008361800001,-33.5214424133],"type":"Point"}
}