{
  "type": "Feature",
  "properties": {
    "addr:full":"Noosa Junction Shopping Centre, Cnr Noosa-Tewantin & Sunshine Beach Rd Noosa Heads QLD 4567",
    "addr:postcode":"4567",
    "addr:street":"Cnr Noosa-Tewantin &;Beach Rd",
    "iso:country":"AU",
    "sg:address":"Noosa Junction Shopping Centre, Cnr Noosa-Tewantin & Sunshine Beach Rd",
    "sg:city":"Noosa Heads",
    "sg:classifiers":[
        {
            "category":"Banks & Credit Unions",
            "subcategory":"Bank",
            "type":"Services"
        }
    ],
    "sg:phone":"+61 7 5449 2177",
    "sg:postcode":"4567",
    "sg:province":"QLD",
    "wof:name":"Bank of Queensland",
    "wof:placetype":"venue"
},
  "geometry": {"coordinates":[153.09002685600001,-26.3967170715],"type":"Point"}
}