{
  "type": "Feature",
  "properties": {
    "addr:full":"5 Burraneer St Leumeah NSW 2560",
    "addr:housenumber":"5",
    "addr:postcode":"2560",
    "addr:street":"Burraneer St",
    "iso:country":"AU",
    "sg:address":"5 Burraneer St",
    "sg:city":"Leumeah",
    "sg:classifiers":[
        {
            "category":"Home & Garden",
            "subcategory":"Carpets & Floor Coverings",
            "type":"Retail Goods"
        }
    ],
    "sg:phone":"+61 2 4625 2003",
    "sg:postcode":"2560",
    "sg:province":"NSW",
    "wof:name":"Campbelltown Floor Coverings Pty Ltd",
    "wof:placetype":"venue"
},
  "geometry": {"coordinates":[150.835083008,-34.0560073853],"type":"Point"}
}