{
  "type": "Feature",
  "properties": {
    "iso:country":"AU",
    "sg:address":"173 Neptune St",
    "sg:city":"Maryborough",
    "sg:classifiers":[
        {
            "category":"Organizations",
            "subcategory":"Non-profit Organization",
            "type":"Services"
        }
    ],
    "sg:phone":"+61 7 4123 6735",
    "sg:postcode":"4650",
    "sg:province":"QLD",
    "sg:tags":[
        "support",
        "disability",
        "organisation"
    ],
    "wof:name":"Family Support Team",
    "wof:placetype":"venue"
},
  "geometry": {"coordinates":[152.696793,-25.512976],"type":"Point"}
}