{
  "type": "Feature",
  "properties": {
    "iso:country":"AU",
    "sg:address":"525 North Rd",
    "sg:city":"Ormond",
    "sg:classifiers":[
        {
            "category":"Communications",
            "subcategory":"Film & Video Production",
            "type":"Services"
        }
    ],
    "sg:phone":"+61 3 9578 0676",
    "sg:postcode":"3204",
    "sg:province":"VIC",
    "sg:tags":[
        "dvd",
        "library"
    ],
    "wof:name":"Top Video",
    "wof:placetype":"venue"
},
  "geometry": {"coordinates":[145.041443,-37.903984],"type":"Point"}
}