{
  "type": "Feature",
  "properties": {
    "iso:country":"AU",
    "sg:address":"12 Bowling Pl",
    "sg:city":"Melville",
    "sg:classifiers":[
        {
            "category":"Health Services",
            "subcategory":"Health Practitioner",
            "type":"Services"
        }
    ],
    "sg:phone":"+61 8 9330 2007",
    "sg:postcode":"6156",
    "sg:province":"WA",
    "sg:tags":[
        "physiotherapist"
    ],
    "wof:name":"Adams Carolyn",
    "wof:placetype":"venue"
},
  "geometry": {"coordinates":[115.804321,-32.040272],"type":"Point"}
}