{
  "type": "Feature",
  "properties": {
    "addr:full":"PO Box 1386 Townsville QLD 4810",
    "addr:postcode":"4810",
    "iso:country":"AU",
    "sg:address":"PO Box 1386",
    "sg:city":"Townsville",
    "sg:classifiers":[
        {
            "category":"Professional",
            "subcategory":"Accounting & Tax Preparation",
            "type":"Services"
        }
    ],
    "sg:phone":"+61 13 15 46",
    "sg:postcode":"4810",
    "sg:province":"QLD",
    "sg:tags":[
        "bookkeeping"
    ],
    "wof:name":"Jim's Bookkeeping",
    "wof:placetype":"venue"
},
  "geometry": {"coordinates":[146.75546299999999,-19.2351],"type":"Point"}
}