{
  "type": "Feature",
  "properties": {
    "addr:full":"24 Coldstream St Coogee NSW 2034",
    "addr:housenumber":"24",
    "addr:postcode":"2034",
    "addr:street":"Coldstream St",
    "iso:country":"AU",
    "sg:address":"24 Coldstream St",
    "sg:city":"Coogee",
    "sg:classifiers":[
        {
            "category":"Professional",
            "subcategory":"Detective & Security Services",
            "type":"Services"
        }
    ],
    "sg:phone":"+61 500 888 872",
    "sg:postcode":"2034",
    "sg:province":"NSW",
    "sg:tags":[
        "consultant",
        "system"
    ],
    "wof:name":"Robot Security & Communications",
    "wof:placetype":"venue"
},
  "geometry": {"coordinates":[151.25584411599999,-33.9328460693],"type":"Point"}
}