{
  "type": "Feature",
  "properties": {
    "iso:country":"AU",
    "sg:address":"2a Ringwood St",
    "sg:city":"Ringwood",
    "sg:classifiers":[
        {
            "category":"Insurance",
            "subcategory":"Health Insurance",
            "type":"Services"
        }
    ],
    "sg:phone":"+61 3 9870 5854",
    "sg:postcode":"3134",
    "sg:province":"VIC",
    "wof:name":"HBA",
    "wof:placetype":"venue"
},
  "geometry": {"coordinates":[145.22720336899999,-37.8152313232],"type":"Point"}
}