{
  "type": "Feature",
  "properties": {
    "iso:country":"AU",
    "sg:address":"Duckworth St",
    "sg:city":"Garbutt",
    "sg:classifiers":[
        {
            "category":"Autos & Motor Vehicles",
            "subcategory":"Automobile Sales",
            "type":"Retail Goods"
        }
    ],
    "sg:phone":"+61 7 4759 4200",
    "sg:postcode":"4814",
    "sg:province":"QLD",
    "sg:tags":[
        "car",
        "new"
    ],
    "wof:name":"Mike Carney Toyota",
    "wof:placetype":"venue"
},
  "geometry": {"coordinates":[146.76091,-19.263388],"type":"Point"}
}