{
  "type": "Feature",
  "properties": {
    "addr:full":"Riverina Hwy Bungowannah NSW 2642",
    "addr:postcode":"2642",
    "addr:street":"Riverina Hwy",
    "iso:country":"AU",
    "sg:address":"Riverina Hwy",
    "sg:city":"Bungowannah",
    "sg:classifiers":[
        {
            "category":"Manufacturing",
            "subcategory":"Aerospace",
            "type":"Manufacturing & Wholesale Goods"
        }
    ],
    "sg:phone":"+61 2 6023 2376",
    "sg:postcode":"2642",
    "sg:province":"NSW",
    "sg:tags":[
        "equipment",
        "aircraft",
        "maintenance"
    ],
    "wof:name":"Ramsay Aviation Maintenance Services",
    "wof:placetype":"venue"
},
  "geometry": {"coordinates":[146.868652344,-35.9804878235],"type":"Point"}
}