{
  "type": "Feature",
  "properties": {
    "iso:country":"AU",
    "sg:address":"Level 1/ 500 Hunter St",
    "sg:city":"Newcastle",
    "sg:classifiers":[
        {
            "category":"Organizations",
            "subcategory":"Professional Association",
            "type":"Services"
        }
    ],
    "sg:phone":"+61 2 4927 5077",
    "sg:postcode":"2300",
    "sg:province":"NSW",
    "sg:tags":[
        "web",
        "internet"
    ],
    "wof:name":"Feral Art Website Productions",
    "wof:placetype":"venue"
},
  "geometry": {"coordinates":[151.769897,-32.927067],"type":"Point"}
}