{
  "type": "Feature",
  "properties": {
    "addr:full":"208- 212 Maitland Rd Islington NSW 2296",
    "addr:housenumber":"212",
    "addr:postcode":"2296",
    "addr:street":"Maitland Rd",
    "iso:country":"AU",
    "sg:address":"208- 212 Maitland Rd",
    "sg:city":"Islington",
    "sg:classifiers":[
        {
            "category":"Home & Garden",
            "subcategory":"Furniture",
            "type":"Retail Goods"
        }
    ],
    "sg:phone":"+61 2 4969 3922",
    "sg:postcode":"2296",
    "sg:province":"NSW",
    "sg:tags":[
        "business"
    ],
    "sg:website":"http://www.officecity.com.au",
    "wof:name":"Office City",
    "wof:placetype":"venue"
},
  "geometry": {"coordinates":[151.746658325,-32.9128379822],"type":"Point"}
}