{
  "type": "Feature",
  "properties": {
    "iso:country":"AU",
    "sg:address":"25 North St",
    "sg:city":"Angaston",
    "sg:classifiers":[
        {
            "category":"Building & Trades",
            "subcategory":"Construction",
            "type":"Services"
        }
    ],
    "sg:phone":"+61 408 825 937",
    "sg:postcode":"5353",
    "sg:province":"SA",
    "sg:tags":[
        "earth",
        "excavating",
        "moving",
        "contractor"
    ],
    "wof:name":"Rohrlach Constructions Pty Ltd",
    "wof:placetype":"venue"
},
  "geometry": {"coordinates":[139.05380249000001,-34.5038642883],"type":"Point"}
}