{
  "type": "Feature",
  "properties": {
    "addr:full":"9 Dornoch Crt Croydon VIC 3136",
    "addr:housenumber":"9",
    "addr:postcode":"3136",
    "addr:street":"Dornoch Crt",
    "iso:country":"AU",
    "sg:address":"9 Dornoch Crt",
    "sg:city":"Croydon",
    "sg:classifiers":[
        {
            "category":"Personal",
            "subcategory":"Massage",
            "type":"Services"
        }
    ],
    "sg:phone":"+61 3 9723 6909",
    "sg:postcode":"3136",
    "sg:province":"VIC",
    "sg:tags":[
        "therapy"
    ],
    "wof:name":"Wild Dolphin",
    "wof:placetype":"venue"
},
  "geometry": {"coordinates":[145.29893493599999,-37.7878646851],"type":"Point"}
}