{
  "type": "Feature",
  "properties": {
    "iso:country":"AU",
    "sg:address":"U33/ 21 Kellett St",
    "sg:city":"Potts Point",
    "sg:classifiers":[
        {
            "category":"Professional",
            "subcategory":"Employment Agencies",
            "type":"Services"
        }
    ],
    "sg:phone":"+61 2 8354 0516",
    "sg:postcode":"2011",
    "sg:province":"NSW",
    "wof:name":"Dedicated Recruitment Solution",
    "wof:placetype":"venue"
},
  "geometry": {"coordinates":[151.22471618599999,-33.8744506836],"type":"Point"}
}