{
  "type": "Feature",
  "properties": {
    "iso:country":"AU",
    "sg:address":"4th Floor, 63 Market St",
    "sg:city":"Wollongong",
    "sg:classifiers":[
        {
            "category":"Professional",
            "subcategory":"Management & Consulting",
            "type":"Services"
        }
    ],
    "sg:phone":"+61 2 4222 2666",
    "sg:postcode":"2500",
    "sg:province":"NSW",
    "sg:tags":[
        "consultant",
        "migration"
    ],
    "wof:name":"Hansons Lawyers",
    "wof:placetype":"venue"
},
  "geometry": {"coordinates":[150.894226,-34.423626],"type":"Point"}
}