{
  "type": "Feature",
  "properties": {
    "addr:full":"135 Stuart Hwy Parap NT 0820",
    "addr:housenumber":"135",
    "addr:postcode":"nt 0820",
    "addr:street":"Stuart Hwy",
    "iso:country":"AU",
    "sg:address":"135 Stuart Hwy",
    "sg:city":"Parap",
    "sg:classifiers":[
        {
            "category":"Home & Garden",
            "subcategory":"Furniture",
            "type":"Retail Goods"
        }
    ],
    "sg:phone":"+61 8 8981 8411",
    "sg:postcode":"0820",
    "sg:province":"NT",
    "sg:tags":[
        "business"
    ],
    "sg:website":"http://www.sbadistributors.com.au",
    "wof:name":"S.B.A Office National",
    "wof:placetype":"venue"
},
  "geometry": {"coordinates":[130.840866089,-12.4392566681],"type":"Point"}
}