{
  "type": "Feature",
  "properties": {
    "addr:full":"45 Charles St Kenilworth QLD 4574",
    "addr:housenumber":"45",
    "addr:postcode":"4574",
    "addr:street":"Charles St",
    "iso:country":"AU",
    "sg:address":"45 Charles St",
    "sg:city":"Kenilworth",
    "sg:classifiers":[
        {
            "category":"Organizations",
            "subcategory":"Community Association",
            "type":"Services"
        }
    ],
    "sg:phone":"+61 7 5446 0144",
    "sg:postcode":"4574",
    "sg:province":"QLD",
    "sg:tags":[
        "cheese",
        "product"
    ],
    "wof:name":"Kenilworth Cheese",
    "wof:placetype":"venue"
},
  "geometry": {"coordinates":[152.72572299999999,-26.596684],"type":"Point"}
}