{
  "type": "Feature",
  "properties": {
    "addr:full":"34- 36 Slater Pde Keilor East VIC 3033",
    "addr:housenumber":"36",
    "addr:postcode":"3033",
    "addr:street":"Slater Pde",
    "iso:country":"AU",
    "sg:address":"34- 36 Slater Pde",
    "sg:city":"Keilor East",
    "sg:classifiers":[
        {
            "category":"Wholesale",
            "subcategory":"Auto Parts",
            "type":"Manufacturing & Wholesale Goods"
        }
    ],
    "sg:phone":"+61 3 9336 2028",
    "sg:postcode":"3033",
    "sg:province":"VIC",
    "sg:tags":[
        "recyclers"
    ],
    "wof:name":"Swedish Wreckers Pty Ltd",
    "wof:placetype":"venue"
},
  "geometry": {"coordinates":[144.856506,-37.735046],"type":"Point"}
}