{
  "type": "Feature",
  "properties": {
    "iso:country":"AU",
    "sg:address":"2/ 125 Brisbane Rd",
    "sg:city":"Booval",
    "sg:classifiers":[
        {
            "category":"Health Services",
            "subcategory":"Doctor",
            "type":"Services"
        }
    ],
    "sg:phone":"+61 7 3812 4099",
    "sg:postcode":"4304",
    "sg:province":"QLD",
    "sg:tags":[
        "medical",
        "practitioner"
    ],
    "wof:name":"Clarke & Robertson Radiology",
    "wof:placetype":"venue"
},
  "geometry": {"coordinates":[152.78865051299999,-27.6144752502],"type":"Point"}
}