{
  "type": "Feature",
  "properties": {
    "iso:country":"AU",
    "sg:address":"115 Cooper St",
    "sg:city":"Surry Hills",
    "sg:classifiers":[
        {
            "category":"Professional",
            "subcategory":"Employment Agencies",
            "type":"Services"
        }
    ],
    "sg:phone":"+61 2 8204 7800",
    "sg:postcode":"2010",
    "sg:province":"NSW",
    "sg:tags":[
        "provider",
        "internet"
    ],
    "wof:name":"Purescript Online Services",
    "wof:placetype":"venue"
},
  "geometry": {"coordinates":[151.211395264,-33.8865394592],"type":"Point"}
}