{
  "type": "Feature",
  "properties": {
    "addr:full":"PO Box 392 Shoreham VIC 3916",
    "addr:postcode":"3916",
    "iso:country":"AU",
    "sg:address":"PO Box 392",
    "sg:city":"Shoreham",
    "sg:classifiers":[
        {
            "category":"Education",
            "subcategory":"Special Training",
            "type":"Public Place"
        }
    ],
    "sg:phone":"+61 3 5989 8774",
    "sg:postcode":"3916",
    "sg:province":"VIC",
    "sg:tags":[
        "development"
    ],
    "wof:name":"Authentic Choices Pty Ltd",
    "wof:placetype":"venue"
},
  "geometry": {"coordinates":[145.04161071799999,-38.4311103821],"type":"Point"}
}