{
  "type": "Feature",
  "properties": {
    "iso:country":"AU",
    "sg:address":"93 Bulla Rd",
    "sg:city":"Bulla",
    "sg:classifiers":[
        {
            "category":"Building & Trades",
            "subcategory":"Cleaning & Sanitation",
            "type":"Services"
        }
    ],
    "sg:phone":"+61 417 143 272",
    "sg:postcode":"3428",
    "sg:province":"VIC",
    "sg:tags":[
        "commercial",
        "maintenance"
    ],
    "wof:name":"Diversified Maintenance & Construction Services",
    "wof:placetype":"venue"
},
  "geometry": {"coordinates":[144.80470275900001,-37.6374855042],"type":"Point"}
}