{
  "type": "Feature",
  "properties": {
    "addr:full":"5 Harker St Alphington VIC 3078",
    "addr:housenumber":"5",
    "addr:postcode":"3078",
    "addr:street":"Harker St",
    "iso:country":"AU",
    "sg:address":"5 Harker St",
    "sg:city":"Alphington",
    "sg:classifiers":[
        {
            "category":"Home & Garden",
            "subcategory":"Building Materials",
            "type":"Retail Goods"
        }
    ],
    "sg:phone":"+61 3 9499 2064",
    "sg:postcode":"3078",
    "sg:province":"VIC",
    "sg:tags":[
        "tile",
        "roofing"
    ],
    "wof:name":"Vickers Roofing",
    "wof:placetype":"venue"
},
  "geometry": {"coordinates":[145.03009033199999,-37.7804222107],"type":"Point"}
}