{
  "type": "Feature",
  "properties": {
    "iso:country":"AU",
    "sg:address":"Birdwood Ave",
    "sg:city":"Ferntree Gully",
    "sg:classifiers":[
        {
            "category":"Building & Trades",
            "subcategory":"Plumbing",
            "type":"Services"
        }
    ],
    "sg:phone":"+61 418 558 747",
    "sg:postcode":"3156",
    "sg:province":"VIC",
    "sg:tags":[
        "plumber",
        "gasfitters"
    ],
    "wof:name":"Neil Jones",
    "wof:placetype":"venue"
},
  "geometry": {"coordinates":[145.304122925,-37.8780212402],"type":"Point"}
}