{
  "type": "Feature",
  "properties": {
    "iso:country":"AU",
    "sg:address":"Kalaroo Rd",
    "sg:city":"Redhead",
    "sg:classifiers":[
        {
            "category":"Manufacturing",
            "subcategory":"Metals",
            "type":"Manufacturing & Wholesale Goods"
        }
    ],
    "sg:phone":"+61 2 4944 7060",
    "sg:postcode":"2290",
    "sg:province":"NSW",
    "sg:tags":[
        "steel",
        "fabricator",
        "mfrs"
    ],
    "wof:name":"Mansman Fabrications",
    "wof:placetype":"venue"
},
  "geometry": {"coordinates":[151.707321167,-33.0117073059],"type":"Point"}
}