{
  "type": "Feature",
  "properties": {
    "addr:full":"15 Torquil Ave Carlingford NSW 2118",
    "addr:housenumber":"15",
    "addr:postcode":"2118",
    "addr:street":"Torquil Ave",
    "iso:country":"AU",
    "sg:address":"15 Torquil Ave",
    "sg:city":"Carlingford",
    "sg:classifiers":[
        {
            "category":"Health Services",
            "subcategory":"Health Practitioner",
            "type":"Services"
        }
    ],
    "sg:phone":"+61 2 9873 4893",
    "sg:postcode":"2118",
    "sg:province":"NSW",
    "sg:tags":[
        "naturopath"
    ],
    "wof:name":"Staples Cheryl",
    "wof:placetype":"venue"
},
  "geometry": {"coordinates":[151.052566528,-33.7711029053],"type":"Point"}
}