{
  "type": "Feature",
  "properties": {
    "addr:full":"PO Box 6578 Halifax Street SA 5000",
    "addr:postcode":"5000",
    "addr:street":"Halifax Street",
    "iso:country":"AU",
    "sg:address":"PO Box 6578",
    "sg:city":"Halifax Street",
    "sg:classifiers":[
        {
            "category":"Social Services",
            "subcategory":"Adult Care",
            "type":"Services"
        }
    ],
    "sg:phone":"+61 1800 003 308",
    "sg:postcode":"5000",
    "sg:province":"SA",
    "sg:tags":[
        "disadvantaged",
        "aid",
        "organisation",
        "group"
    ],
    "wof:name":"Family Accommodation Information & Referral Services",
    "wof:placetype":"venue"
},
  "geometry": {"coordinates":[138.601318359,-34.9327659607],"type":"Point"}
}