{
  "type": "Feature",
  "properties": {
    "iso:country":"AU",
    "sg:address":"PO Box 838",
    "sg:city":"Glenelg",
    "sg:classifiers":[
        {
            "category":"Health Services",
            "subcategory":"Doctor",
            "type":"Services"
        }
    ],
    "sg:phone":"+61 417 800 650",
    "sg:postcode":"5045",
    "sg:province":"SA",
    "sg:tags":[
        "occupational",
        "safety"
    ],
    "wof:name":"CC Reliable Services Pty Ltd",
    "wof:placetype":"venue"
},
  "geometry": {"coordinates":[138.52745100000001,-34.968399],"type":"Point"}
}