{
  "type": "Feature",
  "properties": {
    "addr:full":"Cnr Stuart Hwy & Angliss Rd Berrimah NT 0828",
    "addr:postcode":"nt 0828",
    "addr:street":"Cnr Stuart Hwy & Angliss Rd",
    "iso:country":"AU",
    "sg:address":"Cnr Stuart Hwy & Angliss Rd",
    "sg:city":"Berrimah",
    "sg:classifiers":[
        {
            "category":"Home & Garden",
            "subcategory":"Building Materials",
            "type":"Retail Goods"
        }
    ],
    "sg:phone":"+61 8 8984 4070",
    "sg:postcode":"0828",
    "sg:province":"NT",
    "sg:tags":[
        "ventilating",
        "equipment",
        "system"
    ],
    "wof:name":"Edmonds Pty Limited",
    "wof:placetype":"venue"
},
  "geometry": {"coordinates":[130.94943237300001,-12.443110466],"type":"Point"}
}