{
  "type": "Feature",
  "properties": {
    "addr:full":"Bel Air Resort 2625 Gold Coast Hwy Broadbeach QLD 4218",
    "addr:housenumber":"2625",
    "addr:postcode":"4218",
    "addr:street":"Gold Coast Hwy",
    "iso:country":"AU",
    "sg:address":"Bel Air Resort 2625 Gold Coast Hwy",
    "sg:city":"Broadbeach",
    "sg:classifiers":[
        {
            "category":"Personal",
            "subcategory":"Beauty Salon",
            "type":"Services"
        }
    ],
    "sg:phone":"+61 7 5526 7933",
    "sg:postcode":"4218",
    "sg:province":"QLD",
    "sg:tags":[
        "hairdresser"
    ],
    "wof:name":"Beau Monde Day Spa",
    "wof:placetype":"venue"
},
  "geometry": {"coordinates":[153.431808472,-28.0359535217],"type":"Point"}
}