{
  "type": "Feature",
  "properties": {
    "addr:full":"21 Turnberry Pl Connolly WA 6027",
    "addr:housenumber":"21",
    "addr:postcode":"6027",
    "addr:street":"Turnberry Pl Connolly",
    "iso:country":"AU",
    "sg:address":"21 Turnberry Pl",
    "sg:city":"Connolly",
    "sg:classifiers":[
        {
            "category":"Utilities",
            "subcategory":"Refuse",
            "type":"Services"
        }
    ],
    "sg:phone":"+61 8 9300 2222",
    "sg:postcode":"6027",
    "sg:province":"WA",
    "sg:tags":[
        "remover",
        "rubbish"
    ],
    "wof:name":"Easy-Rid Trailer Hire",
    "wof:placetype":"venue"
},
  "geometry": {"coordinates":[115.759162903,-31.7531547546],"type":"Point"}
}