{
  "type": "Feature",
  "properties": {
    "addr:full":"45 Beach Rd Ayr QLD 4807",
    "addr:housenumber":"45",
    "addr:postcode":"4807",
    "addr:street":"Beach Rd",
    "iso:country":"AU",
    "sg:address":"45 Beach Rd",
    "sg:city":"Ayr",
    "sg:classifiers":[
        {
            "category":"Building & Trades",
            "subcategory":"Cleaning & Sanitation",
            "type":"Services"
        }
    ],
    "sg:phone":"+61 7 4783 2946",
    "sg:postcode":"4807",
    "sg:province":"QLD",
    "sg:tags":[
        "industrial",
        "commercial",
        "contractor"
    ],
    "wof:name":"Jetstream House Washing",
    "wof:placetype":"venue"
},
  "geometry": {"coordinates":[147.404296875,-19.572479248],"type":"Point"}
}