{
  "type": "Feature",
  "properties": {
    "addr:full":"PO Box 3253 Victoria Point QLD 4165",
    "addr:postcode":"4165",
    "iso:country":"AU",
    "sg:address":"PO Box 3253",
    "sg:city":"Victoria Point",
    "sg:classifiers":[
        {
            "category":"Retail",
            "subcategory":"Auto Rental",
            "type":"Services"
        }
    ],
    "sg:phone":"+61 433 145 791",
    "sg:postcode":"4165",
    "sg:province":"QLD",
    "sg:tags":[
        "chauffeur",
        "car",
        "hire",
        "driven",
        "limousine"
    ],
    "wof:name":"A. Award Wedding Cars",
    "wof:placetype":"venue"
},
  "geometry": {"coordinates":[153.28512573200001,-27.595079422],"type":"Point"}
}