{
  "type": "Feature",
  "properties": {
    "addr:full":"1 Bibby Crt Moorabbin VIC 3189",
    "addr:housenumber":"1",
    "addr:postcode":"3189",
    "addr:street":"Bibby Crt",
    "iso:country":"AU",
    "sg:address":"1 Bibby Crt",
    "sg:city":"Moorabbin",
    "sg:classifiers":[
        {
            "category":"Professional",
            "subcategory":"Art Services",
            "type":"Services"
        }
    ],
    "sg:phone":"+61 3 9553 4246",
    "sg:postcode":"3189",
    "sg:province":"VIC",
    "sg:tags":[
        "picture",
        "frame",
        "framing"
    ],
    "wof:name":"Murdoch & Barclay Pty Ltd",
    "wof:placetype":"venue"
},
  "geometry": {"coordinates":[145.067062378,-37.94373703],"type":"Point"}
}