{
  "type": "Feature",
  "properties": {
    "addr:full":"19 Rudloc Rd Morley WA 6062",
    "addr:housenumber":"19",
    "addr:postcode":"6062",
    "addr:street":"Rudloc Rd",
    "iso:country":"AU",
    "sg:address":"19 Rudloc Rd",
    "sg:city":"Morley",
    "sg:classifiers":[
        {
            "category":"Autos & Motor Vehicles",
            "subcategory":"Auto Supplies",
            "type":"Retail Goods"
        }
    ],
    "sg:phone":"+61 8 9375 9919",
    "sg:postcode":"6062",
    "sg:province":"WA",
    "sg:tags":[
        "accessory"
    ],
    "wof:name":"Allbike Transporters and Services",
    "wof:placetype":"venue"
},
  "geometry": {"coordinates":[115.89636993400001,-31.9019126892],"type":"Point"}
}