{
  "type": "Feature",
  "properties": {
    "addr:full":"Shp7a/ 51 John St Cabramatta NSW 2166",
    "addr:housenumber":"51",
    "addr:postcode":"2166",
    "addr:street":"John St",
    "iso:country":"AU",
    "sg:address":"Shp7a/ 51 John St",
    "sg:city":"Cabramatta",
    "sg:classifiers":[
        {
            "category":"Shopping",
            "subcategory":"Clothing, Apparel, & Fashions",
            "type":"Retail Goods"
        }
    ],
    "sg:phone":"+61 2 9726 6730",
    "sg:postcode":"2166",
    "sg:province":"NSW",
    "sg:tags":[
        "lady",
        "wear"
    ],
    "wof:name":"BB Hun",
    "wof:placetype":"venue"
},
  "geometry": {"coordinates":[150.937057495,-33.8950767517],"type":"Point"}
}