{
  "type": "Feature",
  "properties": {
    "iso:country":"AU",
    "sg:address":"293 Parramatta Rd",
    "sg:city":"Five Dock",
    "sg:classifiers":[
        {
            "category":"Building & Trades",
            "subcategory":"Plumbing",
            "type":"Services"
        }
    ],
    "sg:phone":"+61 2 9744 5944",
    "sg:postcode":"2046",
    "sg:province":"NSW",
    "sg:tags":[
        "plumber",
        "gasfitters"
    ],
    "wof:name":"All Professional Plumbing Draining & Gasfitting Maintenance Services",
    "wof:placetype":"venue"
},
  "geometry": {"coordinates":[151.12709,-33.873672],"type":"Point"}
}