{
  "type": "Feature",
  "properties": {
    "addr:full":"198 Sladen St Cranbourne VIC 3977",
    "addr:housenumber":"198",
    "addr:postcode":"3977",
    "addr:street":"Sladen St",
    "iso:country":"AU",
    "sg:address":"198 Sladen St",
    "sg:city":"Cranbourne",
    "sg:classifiers":[
        {
            "category":"Retail",
            "subcategory":"Storage",
            "type":"Services"
        }
    ],
    "sg:phone":"+61 3 5995 3177",
    "sg:postcode":"3977",
    "sg:province":"VIC",
    "wof:name":"A Abkeepsafe Self Storage",
    "wof:placetype":"venue"
},
  "geometry": {"coordinates":[145.286743164,-38.1136741638],"type":"Point"}
}