{
  "type": "Feature",
  "properties": {
    "addr:full":"54a Hargraves St Castlemaine VIC 3450",
    "addr:housenumber":"54a",
    "addr:postcode":"3450",
    "addr:street":"Hargraves St",
    "iso:country":"AU",
    "sg:address":"54a Hargraves St",
    "sg:city":"Castlemaine",
    "sg:classifiers":[
        {
            "category":"Health Services",
            "subcategory":"Dentist",
            "type":"Services"
        }
    ],
    "sg:phone":"+61 3 5472 3437",
    "sg:postcode":"3450",
    "sg:province":"VIC",
    "wof:name":"Kinnersley J M",
    "wof:placetype":"venue"
},
  "geometry": {"coordinates":[144.219604492,-37.0653991699],"type":"Point"}
}