{
  "type": "Feature",
  "properties": {
    "addr:full":"Mc Ewen Rd Stanhope VIC 3623",
    "addr:postcode":"3623",
    "addr:street":"Mc Ewen Rd",
    "iso:country":"AU",
    "sg:address":"Mc Ewen Rd",
    "sg:city":"Stanhope",
    "sg:classifiers":[
        {
            "category":"Farming",
            "subcategory":"Farm",
            "type":"Manufacturing & Wholesale Goods"
        }
    ],
    "sg:phone":"+61 3 5857 2461",
    "sg:postcode":"3623",
    "sg:province":"VIC",
    "sg:tags":[
        "farmer"
    ],
    "wof:name":"Crooks Michael",
    "wof:placetype":"venue"
},
  "geometry": {"coordinates":[145.031860352,-36.4481430054],"type":"Point"}
}