{
  "type": "Feature",
  "properties": {
    "iso:country":"AU",
    "sg:address":"2 Reeves Crt",
    "sg:city":"Kew",
    "sg:classifiers":[
        {
            "category":"Commercial Area",
            "type":"Public Place"
        }
    ],
    "sg:phone":"+61 3 9855 1337",
    "sg:postcode":"3101",
    "sg:province":"VIC",
    "sg:tags":[
        "clothing",
        "label"
    ],
    "wof:name":"Kwik Tapes",
    "wof:placetype":"venue"
},
  "geometry": {"coordinates":[145.01206970199999,-37.8084983826],"type":"Point"}
}