{
  "type": "Feature",
  "properties": {
    "addr:full":"228A Whitehorse Rd Balwyn VIC 3103",
    "addr:housenumber":"228a",
    "addr:postcode":"3103",
    "addr:street":"Whitehorse Rd",
    "iso:country":"AU",
    "sg:address":"228A Whitehorse Rd",
    "sg:city":"Balwyn",
    "sg:classifiers":[
        {
            "category":"Education",
            "subcategory":"University",
            "type":"Public Place"
        }
    ],
    "sg:phone":"+61 1800 653 477",
    "sg:postcode":"3103",
    "sg:province":"VIC",
    "sg:tags":[
        "educational",
        "organisation",
        "cultural"
    ],
    "wof:name":"American Institute for Foreign Study (Australia) Pty Ltd",
    "wof:placetype":"venue"
},
  "geometry": {"coordinates":[145.08079528799999,-37.8128623962],"type":"Point"}
}