{
  "type": "Feature",
  "properties": {
    "iso:country":"AU",
    "sg:address":"18 Farrar Pde",
    "sg:city":"Merredin",
    "sg:classifiers":[
        {
            "category":"Organizations",
            "subcategory":"Professional Association",
            "type":"Services"
        }
    ],
    "sg:phone":"+61 8 9041 1203",
    "sg:postcode":"6415",
    "sg:province":"WA",
    "sg:tags":[
        "web",
        "internet"
    ],
    "wof:name":"Brian L Goddard",
    "wof:placetype":"venue"
},
  "geometry": {"coordinates":[118.29010772700001,-31.487487793],"type":"Point"}
}