{
  "type": "Feature",
  "properties": {
    "addr:full":"70 Mair St East Ballarat VIC 3354",
    "addr:housenumber":"70",
    "addr:postcode":"3354",
    "addr:street":"Mair St East",
    "iso:country":"AU",
    "sg:address":"70 Mair St East",
    "sg:city":"Ballarat",
    "sg:classifiers":[
        {
            "category":"Home & Garden",
            "subcategory":"Building Materials",
            "type":"Retail Goods"
        }
    ],
    "sg:phone":"+61 3 5333 4213",
    "sg:postcode":"3354",
    "sg:province":"VIC",
    "sg:tags":[
        "fitting",
        "door"
    ],
    "wof:name":"Doors Plus",
    "wof:placetype":"venue"
},
  "geometry": {"coordinates":[143.86549400000001,-37.560715],"type":"Point"}
}