{
  "type": "Feature",
  "properties": {
    "addr:full":"Level 1/ 120 Hampden Rd Artarmon NSW 2064",
    "addr:housenumber":"/ 120",
    "addr:postcode":"2064",
    "addr:street":"Hampden Rd",
    "iso:country":"AU",
    "sg:address":"Level 1/ 120 Hampden Rd",
    "sg:city":"Artarmon",
    "sg:classifiers":[
        {
            "category":"Education",
            "subcategory":"Special Training",
            "type":"Public Place"
        }
    ],
    "sg:phone":"+61 2 9904 8200",
    "sg:postcode":"2064",
    "sg:province":"NSW",
    "sg:tags":[
        "development"
    ],
    "wof:name":"Associations Forum Pty Ltd",
    "wof:placetype":"venue"
},
  "geometry": {"coordinates":[151.18373107900001,-33.8083267212],"type":"Point"}
}