{
  "type": "Feature",
  "properties": {
    "addr:full":"PO Box 41 Wellers Hill QLD 4121",
    "addr:postcode":"4121",
    "iso:country":"AU",
    "sg:address":"PO Box 41",
    "sg:city":"Wellers Hill",
    "sg:classifiers":[
        {
            "category":"Education",
            "subcategory":"Special Training",
            "type":"Public Place"
        }
    ],
    "sg:phone":"+61 7 3411 8045",
    "sg:postcode":"4121",
    "sg:province":"QLD",
    "sg:tags":[
        "tuition-educational"
    ],
    "wof:name":"Andersen Academic",
    "wof:placetype":"venue"
},
  "geometry": {"coordinates":[153.049926758,-27.5195102692],"type":"Point"}
}