{
  "type": "Feature",
  "properties": {
    "addr:full":"PO Box 8054 Oakleigh East VIC 3166",
    "addr:postcode":"3166",
    "iso:country":"AU",
    "sg:address":"PO Box 8054",
    "sg:city":"Oakleigh East",
    "sg:classifiers":[
        {
            "category":"Professional",
            "subcategory":"Art Services",
            "type":"Services"
        }
    ],
    "sg:phone":"+61 3 8502 2240",
    "sg:postcode":"3166",
    "sg:province":"VIC",
    "sg:tags":[
        "graphic",
        "designer"
    ],
    "wof:name":"Damage Design",
    "wof:placetype":"venue"
},
  "geometry": {"coordinates":[145.114135742,-37.9014396667],"type":"Point"}
}