{
  "type": "Feature",
  "properties": {
    "addr:full":"44 Sydney St Mt Tarcoola WA 6530",
    "addr:housenumber":"44",
    "addr:postcode":"6530",
    "addr:street":"Sydney St",
    "iso:country":"AU",
    "sg:address":"44 Sydney St",
    "sg:city":"Mt Tarcoola",
    "sg:classifiers":[
        {
            "category":"Health Services",
            "subcategory":"Health Practitioner",
            "type":"Services"
        }
    ],
    "sg:phone":"+61 8 9921 7879",
    "sg:postcode":"6530",
    "sg:province":"WA",
    "sg:tags":[
        "physiotherapist"
    ],
    "wof:name":"Tarcoola Physiotherapy",
    "wof:placetype":"venue"
},
  "geometry": {"coordinates":[114.620857239,-28.7974967957],"type":"Point"}
}