{
  "type": "Feature",
  "properties": {
    "addr:full":"10 Hassall St Smithfield NSW 2164",
    "addr:housenumber":"10",
    "addr:postcode":"2164",
    "addr:street":"Hassall St",
    "iso:country":"AU",
    "sg:address":"10 Hassall St",
    "sg:city":"Smithfield",
    "sg:classifiers":[
        {
            "category":"Health Services",
            "subcategory":"Doctor",
            "type":"Services"
        }
    ],
    "sg:phone":"+61 2 9604 7377",
    "sg:postcode":"2164",
    "sg:province":"NSW",
    "sg:tags":[
        "medical",
        "practitioner"
    ],
    "wof:name":"Yung K M",
    "wof:placetype":"venue"
},
  "geometry": {"coordinates":[150.922149658,-33.8503913879],"type":"Point"}
}