{
  "type": "Feature",
  "properties": {
    "addr:full":"Princes Hwy Narre Warren VIC 3805",
    "addr:postcode":"3805",
    "addr:street":"Princes Hwy",
    "iso:country":"AU",
    "sg:address":"Princes Hwy",
    "sg:city":"Narre Warren",
    "sg:classifiers":[
        {
            "category":"Shopping",
            "subcategory":"Clothing, Apparel, & Fashions",
            "type":"Retail Goods"
        }
    ],
    "sg:phone":"+61 3 9705 6348",
    "sg:postcode":"3805",
    "sg:province":"VIC",
    "sg:tags":[
        "jean"
    ],
    "wof:name":"JeansWest",
    "wof:placetype":"venue"
},
  "geometry": {"coordinates":[145.302155,-38.014935],"type":"Point"}
}