{
  "type": "Feature",
  "properties": {
    "addr:full":"87 Campbell Pde Beachmere QLD 4510",
    "addr:housenumber":"87",
    "addr:postcode":"4510",
    "addr:street":"Campbell Pde",
    "iso:country":"AU",
    "sg:address":"87 Campbell Pde",
    "sg:city":"Beachmere",
    "sg:classifiers":[
        {
            "category":"Farming",
            "subcategory":"Nursery",
            "type":"Manufacturing & Wholesale Goods"
        }
    ],
    "sg:phone":"+61 7 5496 2905",
    "sg:postcode":"4510",
    "sg:province":"QLD",
    "wof:name":"Dracaena Farm Nursery",
    "wof:placetype":"venue"
},
  "geometry": {"coordinates":[153.072586,-27.103909],"type":"Point"}
}