{
  "type": "Feature",
  "properties": {
    "addr:full":"3 Ethel St Deception Bay QLD 4508",
    "addr:housenumber":"3",
    "addr:postcode":"4508",
    "addr:street":"Ethel St",
    "iso:country":"AU",
    "sg:address":"3 Ethel St",
    "sg:city":"Deception Bay",
    "sg:classifiers":[
        {
            "category":"Building & Trades",
            "subcategory":"Construction",
            "type":"Services"
        }
    ],
    "sg:phone":"+61 412 888 694",
    "sg:postcode":"4508",
    "sg:province":"QLD",
    "sg:tags":[
        "earth",
        "excavating",
        "moving",
        "contractor"
    ],
    "wof:name":"Aussie Mini Diggers",
    "wof:placetype":"venue"
},
  "geometry": {"coordinates":[153.0078125,-27.1872844696],"type":"Point"}
}