{
  "type": "Feature",
  "properties": {
    "addr:full":"141 George St Avalon NSW 2107",
    "addr:housenumber":"141",
    "addr:postcode":"2107",
    "addr:street":"George St",
    "iso:country":"AU",
    "sg:address":"141 George St",
    "sg:city":"Avalon",
    "sg:classifiers":[
        {
            "category":"Food & Beverages",
            "subcategory":"Specialty",
            "type":"Retail Goods"
        }
    ],
    "sg:phone":"+61 2 9970 8622",
    "sg:postcode":"2107",
    "sg:province":"NSW",
    "sg:tags":[
        "product",
        "health"
    ],
    "wof:name":"Efamol",
    "wof:placetype":"venue"
},
  "geometry": {"coordinates":[151.32200622600001,-33.6213607788],"type":"Point"}
}