{
  "type": "Feature",
  "properties": {
    "addr:full":"326 Badger Creek Rd Healesville VIC 3777",
    "addr:housenumber":"326",
    "addr:postcode":"3777",
    "addr:street":"Badger Creek Rd",
    "iso:country":"AU",
    "sg:address":"326 Badger Creek Rd",
    "sg:city":"Healesville",
    "sg:classifiers":[
        {
            "category":"Travel",
            "subcategory":"Hotels & Motels",
            "type":"Entertainment"
        }
    ],
    "sg:phone":"+61 3 5962 5148",
    "sg:postcode":"3777",
    "sg:province":"VIC",
    "wof:name":"Golden Chain Sanctuary House Healesville Hotel",
    "wof:placetype":"venue"
},
  "geometry": {"coordinates":[145.53270000000001,-37.677204],"type":"Point"}
}