{
  "type": "Feature",
  "properties": {
    "addr:full":"152 Elizabeth St Launceston TAS 7250",
    "addr:housenumber":"152",
    "addr:postcode":"7250",
    "addr:street":"Elizabeth St",
    "iso:country":"AU",
    "sg:address":"152 Elizabeth St",
    "sg:city":"Launceston",
    "sg:classifiers":[
        {
            "category":"Travel",
            "subcategory":"Hotels & Motels",
            "type":"Entertainment"
        }
    ],
    "sg:phone":"+61 3 6331 4137",
    "sg:postcode":"7250",
    "sg:province":"TAS",
    "sg:tags":[
        "accommodation"
    ],
    "wof:name":"Crown Bar & Bottle Shop The",
    "wof:placetype":"venue"
},
  "geometry": {"coordinates":[147.135955811,-41.4415664673],"type":"Point"}
}