{
  "type": "Feature",
  "properties": {
    "iso:country":"AU",
    "sg:address":"Cnr Warburton St & Talara Rd",
    "sg:city":"Gymea",
    "sg:classifiers":[
        {
            "category":"Health Services",
            "subcategory":"Doctor",
            "type":"Services"
        }
    ],
    "sg:phone":"+61 2 9526 2900",
    "sg:postcode":"2227",
    "sg:province":"NSW",
    "sg:tags":[
        "podiatrist"
    ],
    "sg:website":"http://www.podiatry.asn.au",
    "wof:name":"Shire Podiatry Gymea",
    "wof:placetype":"venue"
},
  "geometry": {"coordinates":[151.08506774899999,-34.0333747864],"type":"Point"}
}