{
  "type": "Feature",
  "properties": {
    "addr:full":"72 Seaview St Mollymook NSW 2539",
    "addr:housenumber":"72",
    "addr:postcode":"2539",
    "addr:street":"Seaview St",
    "iso:country":"AU",
    "sg:address":"72 Seaview St",
    "sg:city":"Mollymook",
    "sg:classifiers":[
        {
            "category":"Building & Trades",
            "subcategory":"Plumbing",
            "type":"Services"
        }
    ],
    "sg:phone":"+61 414 527 296",
    "sg:postcode":"2539",
    "sg:province":"NSW",
    "sg:tags":[
        "plumber",
        "gasfitters"
    ],
    "wof:name":"Matt's Plumbing",
    "wof:placetype":"venue"
},
  "geometry": {"coordinates":[150.471633911,-35.3464355469],"type":"Point"}
}