{
  "type": "Feature",
  "properties": {
    "addr:full":"3/ 7 Boundary St Brisbane QLD 4000",
    "addr:housenumber":"/ 7",
    "addr:postcode":"4000",
    "addr:street":"Boundary St",
    "iso:country":"AU",
    "sg:address":"3/ 7 Boundary St",
    "sg:city":"Brisbane",
    "sg:classifiers":[
        {
            "category":"Real Estate",
            "subcategory":"Architect",
            "type":"Services"
        }
    ],
    "sg:phone":"+61 7 3839 3234",
    "sg:postcode":"4000",
    "sg:province":"QLD",
    "wof:name":"John Jory Architect",
    "wof:placetype":"venue"
},
  "geometry": {"coordinates":[153.03057861299999,-27.4617347717],"type":"Point"}
}