{
  "type": "Feature",
  "properties": {
    "addr:full":"103 Main St Murwillumbah NSW 2484",
    "addr:housenumber":"103",
    "addr:postcode":"2484",
    "addr:street":"Main St",
    "iso:country":"AU",
    "sg:address":"103 Main St",
    "sg:city":"Murwillumbah",
    "sg:classifiers":[
        {
            "category":"Food & Beverages",
            "subcategory":"Fruits & Vegetables",
            "type":"Retail Goods"
        }
    ],
    "sg:phone":"+61 2 6672 1155",
    "sg:postcode":"2484",
    "sg:province":"NSW",
    "sg:tags":[
        "greengrocer",
        "fruiterer"
    ],
    "wof:name":"Tweed Fruit Exchange",
    "wof:placetype":"venue"
},
  "geometry": {"coordinates":[153.40342712399999,-28.3228321075],"type":"Point"}
}