{
  "type": "Feature",
  "properties": {
    "addr:full":"8 Winifred St Kingston QLD 4114",
    "addr:housenumber":"8",
    "addr:postcode":"4114",
    "addr:street":"Winifred St",
    "iso:country":"AU",
    "sg:address":"8 Winifred St",
    "sg:city":"Kingston",
    "sg:classifiers":[
        {
            "category":"Retail",
            "subcategory":"Repair Shop",
            "type":"Services"
        }
    ],
    "sg:phone":"+61 7 3208 9913",
    "sg:postcode":"4114",
    "sg:province":"QLD",
    "sg:tags":[
        "machine",
        "sewing"
    ],
    "wof:name":"R.J. Sewing Machine Service (QLD)",
    "wof:placetype":"venue"
},
  "geometry": {"coordinates":[153.114135742,-27.646692276],"type":"Point"}
}