{
  "type": "Feature",
  "properties": {
    "addr:full":"71a Terry Rd West Ryde NSW 2114",
    "addr:housenumber":"71a",
    "addr:postcode":"2114",
    "addr:street":"Terry Rd",
    "iso:country":"AU",
    "sg:address":"71a Terry Rd",
    "sg:city":"West Ryde",
    "sg:classifiers":[
        {
            "category":"Manufacturing",
            "subcategory":"Building Materials",
            "type":"Manufacturing & Wholesale Goods"
        }
    ],
    "sg:phone":"+61 2 9809 3025",
    "sg:postcode":"2114",
    "sg:province":"NSW",
    "sg:tags":[
        "fibreglass"
    ],
    "wof:name":"P.J.C. Fibreglass Products",
    "wof:placetype":"venue"
},
  "geometry": {"coordinates":[151.09523010300001,-33.8008728027],"type":"Point"}
}