{
  "type": "Feature",
  "properties": {
    "addr:full":"52 Smith St Alice Springs NT 0870",
    "addr:housenumber":"52",
    "addr:postcode":"nt 0870",
    "addr:street":"Smith St",
    "iso:country":"AU",
    "sg:address":"52 Smith St",
    "sg:city":"Alice Springs",
    "sg:classifiers":[
        {
            "category":"Home & Garden",
            "subcategory":"Building Materials",
            "type":"Retail Goods"
        }
    ],
    "sg:phone":"+61 8 8952 1855",
    "sg:postcode":"0870",
    "sg:province":"NT",
    "sg:tags":[
        "wall",
        "frame",
        "truss",
        "roof"
    ],
    "wof:name":"Central Australian Construction Solutions",
    "wof:placetype":"venue"
},
  "geometry": {"coordinates":[133.866699219,-23.6910705566],"type":"Point"}
}