{
  "type": "Feature",
  "properties": {
    "iso:country":"AU",
    "sg:address":"Purves Rd",
    "sg:city":"Arthurs Seat",
    "sg:classifiers":[
        {
            "category":"Restaurant",
            "type":"Food & Drink"
        }
    ],
    "sg:phone":"+61 419 500 575",
    "sg:postcode":"3936",
    "sg:province":"VIC",
    "wof:name":"Chris Geurts",
    "wof:placetype":"venue"
},
  "geometry": {"coordinates":[144.950271606,-38.3550872803],"type":"Point"}
}