{
  "type": "Feature",
  "properties": {
    "iso:country":"AU",
    "sg:address":"12 Amy St",
    "sg:city":"Erskineville",
    "sg:classifiers":[
        {
            "category":"Sports & Exercise",
            "subcategory":"Gym",
            "type":"Entertainment"
        }
    ],
    "sg:phone":"+61 410 600 777",
    "sg:postcode":"2043",
    "sg:province":"NSW",
    "sg:tags":[
        "personal",
        "trainer",
        "fitness"
    ],
    "wof:name":"Trim With Tim",
    "wof:placetype":"venue"
},
  "geometry": {"coordinates":[151.18293800000001,-33.904034],"type":"Point"}
}