{
  "type": "Feature",
  "properties": {
    "addr:full":"29 Hunter St Blacktown NSW 2148",
    "addr:housenumber":"29",
    "addr:postcode":"2148",
    "addr:street":"Hunter St",
    "iso:country":"AU",
    "sg:address":"29 Hunter St",
    "sg:city":"Blacktown",
    "sg:classifiers":[
        {
            "category":"Autos & Motor Vehicles",
            "subcategory":"Boat Sales",
            "type":"Retail Goods"
        }
    ],
    "sg:phone":"+61 407 405 724",
    "sg:postcode":"2148",
    "sg:province":"NSW",
    "sg:tags":[
        "builder",
        "yacht",
        "repairer"
    ],
    "wof:name":"Carrick Graham Shipwright & Boatbuilder",
    "wof:placetype":"venue"
},
  "geometry": {"coordinates":[150.885055542,-33.7804450989],"type":"Point"}
}