{
  "type": "Feature",
  "properties": {
    "iso:country":"AU",
    "sg:address":"53 Gow St",
    "sg:city":"Padstow",
    "sg:classifiers":[
        {
            "category":"Wholesale",
            "subcategory":"Home Furnishings",
            "type":"Manufacturing & Wholesale Goods"
        }
    ],
    "sg:phone":"+61 2 9707 2888",
    "sg:postcode":"2211",
    "sg:province":"NSW",
    "wof:name":"Awood Furniture",
    "wof:placetype":"venue"
},
  "geometry": {"coordinates":[151.034409,-33.937511],"type":"Point"}
}