{
  "type": "Feature",
  "properties": {
    "addr:full":"39 Erskine St Dubbo NSW 2830",
    "addr:housenumber":"39",
    "addr:postcode":"2830",
    "addr:street":"Erskine St",
    "iso:country":"AU",
    "sg:address":"39 Erskine St",
    "sg:city":"Dubbo",
    "sg:classifiers":[
        {
            "category":"Professional",
            "subcategory":"Printing & Photocopies",
            "type":"Services"
        }
    ],
    "sg:phone":"+61 2 6882 6155",
    "sg:postcode":"2830",
    "sg:province":"NSW",
    "sg:tags":[
        "photocopier"
    ],
    "wof:name":"Inland Technology",
    "wof:placetype":"venue"
},
  "geometry": {"coordinates":[148.604248047,-32.2428970337],"type":"Point"}
}