{
  "type": "Feature",
  "properties": {
    "iso:country":"AU",
    "sg:address":"2 Production St",
    "sg:city":"Beenleigh",
    "sg:classifiers":[
        {
            "category":"Manufacturing",
            "subcategory":"Chemicals & Compounds",
            "type":"Manufacturing & Wholesale Goods"
        }
    ],
    "sg:phone":"+61 7 3807 4788",
    "sg:postcode":"4207",
    "sg:province":"QLD",
    "sg:tags":[
        "equipment",
        "processing"
    ],
    "wof:name":"Metric Manufacturing & Sales Pty Ltd",
    "wof:placetype":"venue"
},
  "geometry": {"coordinates":[153.184814453,-27.7120857239],"type":"Point"}
}