{
  "type": "Feature",
  "properties": {
    "addr:full":"23 Barlee St Busselton WA 6280",
    "addr:housenumber":"23",
    "addr:postcode":"6280",
    "addr:street":"Barlee St",
    "iso:country":"AU",
    "sg:address":"23 Barlee St",
    "sg:city":"Busselton",
    "sg:classifiers":[
        {
            "category":"Professional",
            "subcategory":"Accounting & Tax Preparation",
            "type":"Services"
        }
    ],
    "sg:phone":"+61 8 9751 1777",
    "sg:postcode":"6280",
    "sg:province":"WA",
    "sg:tags":[
        "consultant",
        "taxation"
    ],
    "wof:name":"Bray Bookkeeping Accounting",
    "wof:placetype":"venue"
},
  "geometry": {"coordinates":[115.34452819800001,-33.6604270935],"type":"Point"}
}