{
  "type": "Feature",
  "properties": {
    "iso:country":"AU",
    "sg:address":"Unit 1 72 Everard Ave",
    "sg:city":"Keswick",
    "sg:classifiers":[
        {
            "category":"Professional",
            "subcategory":"Detective & Security Services",
            "type":"Services"
        }
    ],
    "sg:phone":"+61 8 8297 5555",
    "sg:postcode":"5035",
    "sg:province":"SA",
    "sg:tags":[
        "consultant",
        "system"
    ],
    "wof:name":"Security Merchants Australia Pty Ltd",
    "wof:placetype":"venue"
},
  "geometry": {"coordinates":[138.57862854000001,-34.9458389282],"type":"Point"}
}