{
  "type": "Feature",
  "properties": {
    "addr:full":"44a Chapel St Glenorchy TAS 7010",
    "addr:housenumber":"44a",
    "addr:postcode":"7010",
    "addr:street":"Chapel St",
    "iso:country":"AU",
    "sg:address":"44a Chapel St",
    "sg:city":"Glenorchy",
    "sg:classifiers":[
        {
            "category":"Wholesale",
            "subcategory":"Machinery & Supplies",
            "type":"Manufacturing & Wholesale Goods"
        }
    ],
    "sg:phone":"+61 3 6272 3311",
    "sg:postcode":"7010",
    "sg:province":"TAS",
    "sg:tags":[
        "equipment",
        "hydraulic"
    ],
    "wof:name":"Grubb Engineering",
    "wof:placetype":"venue"
},
  "geometry": {"coordinates":[147.26763915999999,-42.8347244263],"type":"Point"}
}