{
  "type": "Feature",
  "properties": {
    "addr:full":"39 Darby St Newcastle NSW 2300",
    "addr:housenumber":"39",
    "addr:postcode":"2300",
    "addr:street":"Darby St",
    "iso:country":"AU",
    "sg:address":"39 Darby St",
    "sg:city":"Newcastle",
    "sg:classifiers":[
        {
            "category":"Shopping",
            "subcategory":"Gifts & Souvenirs",
            "type":"Retail Goods"
        }
    ],
    "sg:phone":"+61 2 4929 3411",
    "sg:postcode":"2300",
    "sg:province":"NSW",
    "sg:tags":[
        "print",
        "poster",
        "pictures"
    ],
    "wof:name":"Heath Wade Photography Gallery",
    "wof:placetype":"venue"
},
  "geometry": {"coordinates":[151.77387999999999,-32.928802],"type":"Point"}
}