{
  "type": "Feature",
  "properties": {
    "addr:full":"70 Beach Pde Morisset NSW 2264",
    "addr:housenumber":"70",
    "addr:postcode":"2264",
    "addr:street":"Beach Pde",
    "iso:country":"AU",
    "sg:address":"70 Beach Pde",
    "sg:city":"Morisset",
    "sg:classifiers":[
        {
            "category":"Professional",
            "subcategory":"Engineering",
            "type":"Services"
        }
    ],
    "sg:phone":"+61 412 618 279",
    "sg:postcode":"2264",
    "sg:province":"NSW",
    "sg:tags":[
        "engineer"
    ],
    "wof:name":"Morisset Engineering",
    "wof:placetype":"venue"
},
  "geometry": {"coordinates":[151.56019599999999,-33.10125],"type":"Point"}
}