{
  "type": "Feature",
  "properties": {
    "iso:country":"AU",
    "sg:address":"1 Lower Grieve Rd",
    "sg:city":"Avonsleigh",
    "sg:classifiers":[
        {
            "category":"Shopping",
            "subcategory":"Computers & Home Electronics",
            "type":"Retail Goods"
        }
    ],
    "sg:phone":"+61 1800 636 913",
    "sg:postcode":"3782",
    "sg:province":"VIC",
    "sg:tags":[
        "small",
        "equipment",
        "business"
    ],
    "wof:name":"Stanford North Pty Ltd",
    "wof:placetype":"venue"
},
  "geometry": {"coordinates":[145.473267,-37.925819],"type":"Point"}
}