{
  "type": "Feature",
  "properties": {
    "iso:country":"AU",
    "sg:address":"PO Box 75",
    "sg:city":"Brighton",
    "sg:classifiers":[
        {
            "category":"Social Services",
            "subcategory":"Job Training",
            "type":"Services"
        }
    ],
    "sg:phone":"+61 411 516 907",
    "sg:postcode":"5048",
    "sg:province":"SA",
    "sg:tags":[
        "interpreter"
    ],
    "wof:name":"Spanish International Translating Service",
    "wof:placetype":"venue"
},
  "geometry": {"coordinates":[138.51779199999999,-35.01717],"type":"Point"}
}