{
  "type": "Feature",
  "properties": {
    "iso:country":"AU",
    "sg:address":"8 John Radley Ave",
    "sg:city":"Dural",
    "sg:classifiers":[
        {
            "category":"Professional",
            "subcategory":"Computer Services",
            "type":"Services"
        }
    ],
    "sg:phone":"+61 419 202 750",
    "sg:postcode":"2158",
    "sg:province":"NSW",
    "sg:tags":[
        "consultant",
        "system"
    ],
    "wof:name":"Inforad Pty Ltd",
    "wof:placetype":"venue"
},
  "geometry": {"coordinates":[151.03222656200001,-33.7166366577],"type":"Point"}
}