{
  "type": "Feature",
  "properties": {
    "iso:country":"AU",
    "sg:address":"35 Silvertop Rd",
    "sg:city":"Doonan",
    "sg:classifiers":[
        {
            "category":"Building & Trades",
            "subcategory":"Construction",
            "type":"Services"
        }
    ],
    "sg:phone":"+61 419 784 759",
    "sg:postcode":"4562",
    "sg:province":"QLD",
    "sg:tags":[
        "earth",
        "excavating",
        "moving",
        "contractor"
    ],
    "wof:name":"Dingo Equipment Hire",
    "wof:placetype":"venue"
},
  "geometry": {"coordinates":[153.012176514,-26.460149765],"type":"Point"}
}