{
  "type": "Feature",
  "properties": {
    "addr:full":"26 Clermont St Bardon QLD 4065",
    "addr:housenumber":"26",
    "addr:postcode":"4065",
    "addr:street":"Clermont St",
    "iso:country":"AU",
    "sg:address":"26 Clermont St",
    "sg:city":"Bardon",
    "sg:classifiers":[
        {
            "category":"Professional",
            "subcategory":"Art Services",
            "type":"Services"
        }
    ],
    "sg:phone":"+61 7 3217 5754",
    "sg:postcode":"4065",
    "sg:province":"QLD",
    "sg:tags":[
        "product",
        "industrial",
        "designer"
    ],
    "wof:name":"Immacon Australia",
    "wof:placetype":"venue"
},
  "geometry": {"coordinates":[152.98292541500001,-27.4586257935],"type":"Point"}
}