{
  "type": "Feature",
  "properties": {
    "iso:country":"AU",
    "sg:address":"9 Ivanhoe Rd",
    "sg:city":"Croydon",
    "sg:classifiers":[
        {
            "category":"Building & Trades",
            "subcategory":"Construction",
            "type":"Services"
        }
    ],
    "sg:phone":"+61 412 955 261",
    "sg:postcode":"2132",
    "sg:province":"NSW",
    "sg:tags":[
        "earth",
        "excavating",
        "moving",
        "contractor"
    ],
    "wof:name":"Wamgold Wamgold",
    "wof:placetype":"venue"
},
  "geometry": {"coordinates":[151.11891174300001,-33.8773956299],"type":"Point"}
}