{
  "type": "Feature",
  "properties": {
    "addr:full":"26 Andall Rd Park Ridge South QLD 4125",
    "addr:housenumber":"26",
    "addr:postcode":"4125",
    "addr:street":"Andall Rd",
    "iso:country":"AU",
    "sg:address":"26 Andall Rd",
    "sg:city":"Park Ridge South",
    "sg:classifiers":[
        {
            "category":"Home & Garden",
            "subcategory":"Furniture",
            "type":"Retail Goods"
        }
    ],
    "sg:phone":"+61 7 3802 2242",
    "sg:postcode":"4125",
    "sg:province":"QLD",
    "sg:tags":[
        "business"
    ],
    "wof:name":"Advanced Office Chairs Pty Ltd",
    "wof:placetype":"venue"
},
  "geometry": {"coordinates":[153.02053832999999,-27.7239055634],"type":"Point"}
}