{
  "type": "Feature",
  "properties": {
    "addr:full":"PO Box 398 Mt Eliza VIC 3930",
    "addr:postcode":"3930",
    "iso:country":"AU",
    "sg:address":"PO Box 398",
    "sg:city":"Mt Eliza",
    "sg:classifiers":[
        {
            "category":"Utilities",
            "subcategory":"Electric",
            "type":"Services"
        }
    ],
    "sg:phone":"+61 418 313 544",
    "sg:postcode":"3930",
    "sg:province":"VIC",
    "sg:tags":[
        "electrical",
        "contractor"
    ],
    "wof:name":"Southgate Electrics Pty Ltd",
    "wof:placetype":"venue"
},
  "geometry": {"coordinates":[145.09501648,-38.1936798096],"type":"Point"}
}