{
  "type": "Feature",
  "properties": {
    "addr:full":"Unit 2 / 2 Clements Way Boulder WA 6432",
    "addr:housenumber":"2",
    "addr:postcode":"6432",
    "addr:street":"Clements Way",
    "iso:country":"AU",
    "sg:address":"Unit 2",
    "sg:city":"/ 2 Clements Way Boulder",
    "sg:classifiers":[
        {
            "category":"Shopping",
            "type":"Retail Goods"
        }
    ],
    "sg:phone":"+61 8 9093 1644",
    "sg:postcode":"6432",
    "sg:province":"WA",
    "sg:tags":[
        "equipment",
        "safety",
        "accessory"
    ],
    "wof:name":"Mercury Firesafety",
    "wof:placetype":"venue"
},
  "geometry": {"coordinates":[121.489936829,-30.7768592834],"type":"Point"}
}