{
  "type": "Feature",
  "properties": {
    "addr:full":"66 Kingsley Drv Kingsley WA 6026",
    "addr:housenumber":"66",
    "addr:postcode":"6026",
    "addr:street":"Kingsley Drv",
    "iso:country":"AU",
    "sg:address":"66 Kingsley Drv",
    "sg:city":"Kingsley",
    "sg:classifiers":[
        {
            "category":"Fast Food",
            "type":"Food & Drink"
        }
    ],
    "sg:phone":"+61 8 9409 8366",
    "sg:postcode":"6026",
    "sg:province":"WA",
    "sg:tags":[
        "away",
        "take"
    ],
    "wof:name":"Kingsley Drive Fish House",
    "wof:placetype":"venue"
},
  "geometry": {"coordinates":[115.78748321499999,-31.8054103851],"type":"Point"}
}