{
  "type": "Feature",
  "properties": {
    "addr:full":"17 Market St Box Hill VIC 3128",
    "addr:housenumber":"17",
    "addr:postcode":"3128",
    "addr:street":"Market St",
    "iso:country":"AU",
    "sg:address":"17 Market St",
    "sg:city":"Box Hill",
    "sg:classifiers":[
        {
            "category":"Personal",
            "subcategory":"Shoe Repair & Shine",
            "type":"Services"
        }
    ],
    "sg:phone":"+61 3 9890 9626",
    "sg:postcode":"3128",
    "sg:province":"VIC",
    "sg:tags":[
        "footwear"
    ],
    "wof:name":"Cavallo Nero Quality Shoe Repairs",
    "wof:placetype":"venue"
},
  "geometry": {"coordinates":[145.13902282699999,-37.8198127747],"type":"Point"}
}