{
  "type": "Feature",
  "properties": {
    "iso:country":"AU",
    "sg:address":"24a Chiltern Rd",
    "sg:city":"Ingleside",
    "sg:classifiers":[
        {
            "category":"Autos & Motor Vehicles",
            "subcategory":"Auto Supplies",
            "type":"Retail Goods"
        }
    ],
    "sg:phone":"+61 2 9997 7436",
    "sg:postcode":"2101",
    "sg:province":"NSW",
    "sg:tags":[
        "accessory"
    ],
    "wof:name":"Importdriver.com.au",
    "wof:placetype":"venue"
},
  "geometry": {"coordinates":[151.267273,-33.665943],"type":"Point"}
}