{
  "type": "Feature",
  "properties": {
    "iso:country":"AU",
    "sg:address":"5 Governor Macquarie Drv",
    "sg:city":"Chipping Norton",
    "sg:classifiers":[
        {
            "category":"Professional",
            "type":"Services"
        }
    ],
    "sg:phone":"+61 2 9782 9444",
    "sg:postcode":"2170",
    "sg:province":"NSW",
    "sg:tags":[
        "auctioneer"
    ],
    "wof:name":"Pickles Auctions - Industrial",
    "wof:placetype":"venue"
},
  "geometry": {"coordinates":[150.962524414,-33.927520752],"type":"Point"}
}