{
  "type": "Feature",
  "properties": {
    "iso:country":"AU",
    "sg:address":"18- 24 Hotham St",
    "sg:city":"Traralgon",
    "sg:classifiers":[
        {
            "category":"Communications",
            "subcategory":"Film & Video Production",
            "type":"Services"
        }
    ],
    "sg:phone":"+61 1800 707 707",
    "sg:postcode":"3844",
    "sg:province":"VIC",
    "sg:tags":[
        "society",
        "housing",
        "co-operative"
    ],
    "wof:name":"La Trobe Financial",
    "wof:placetype":"venue"
},
  "geometry": {"coordinates":[146.53834533700001,-38.1972541809],"type":"Point"}
}