{
  "type": "Feature",
  "properties": {
    "iso:country":"AU",
    "sg:address":"Palmyra St",
    "sg:city":"Walkerston",
    "sg:classifiers":[
        {
            "category":"Farming",
            "subcategory":"Farm",
            "type":"Manufacturing & Wholesale Goods"
        }
    ],
    "sg:phone":"+61 7 4959 2101",
    "sg:postcode":"4751",
    "sg:province":"QLD",
    "sg:tags":[
        "farmer"
    ],
    "wof:name":"Battaia D I & J",
    "wof:placetype":"venue"
},
  "geometry": {"coordinates":[149.06546,-21.16041],"type":"Point"}
}