{
  "type": "Feature",
  "properties": {
    "addr:full":"307 South Rd Mile End SA 5031",
    "addr:housenumber":"307",
    "addr:postcode":"5031",
    "addr:street":"South Rd",
    "iso:country":"AU",
    "sg:address":"307 South Rd",
    "sg:city":"Mile End",
    "sg:classifiers":[
        {
            "category":"Manufacturing",
            "subcategory":"Tools & Machinery",
            "type":"Manufacturing & Wholesale Goods"
        }
    ],
    "sg:phone":"+61 8 8352 5777",
    "sg:postcode":"5031",
    "sg:province":"SA",
    "sg:tags":[
        "earth",
        "excavating",
        "moving",
        "equipment"
    ],
    "wof:name":"Extensive Wheel Services",
    "wof:placetype":"venue"
},
  "geometry": {"coordinates":[138.570755005,-34.9340629578],"type":"Point"}
}