{
  "type": "Feature",
  "properties": {
    "addr:full":"Suite 2/ 28 French St Pimlico QLD 4812",
    "addr:housenumber":"28",
    "addr:postcode":"4812",
    "addr:street":"French St",
    "iso:country":"AU",
    "sg:address":"Suite 2/ 28 French St",
    "sg:city":"Pimlico",
    "sg:classifiers":[
        {
            "category":"Arena",
            "subcategory":"Sports Club",
            "type":"Entertainment"
        }
    ],
    "sg:phone":"+61 7 4725 6133",
    "sg:postcode":"4812",
    "sg:province":"QLD",
    "sg:tags":[
        "organisation",
        "sporting"
    ],
    "wof:name":"North Queensland Touch Association",
    "wof:placetype":"venue"
},
  "geometry": {"coordinates":[146.79006999999999,-19.279303],"type":"Point"}
}