{
  "type": "Feature",
  "properties": {
    "iso:country":"AU",
    "sg:address":"52 Frobisher St",
    "sg:city":"Osborne Park",
    "sg:classifiers":[
        {
            "category":"Utilities",
            "subcategory":"Water",
            "type":"Services"
        }
    ],
    "sg:phone":"+61 8 9201 1111",
    "sg:postcode":"6017",
    "sg:province":"WA",
    "sg:tags":[
        "equipment",
        "treatment"
    ],
    "wof:name":"H2Only",
    "wof:placetype":"venue"
},
  "geometry": {"coordinates":[115.81954956,-31.9088382721],"type":"Point"}
}