{
  "type": "Feature",
  "properties": {
    "iso:country":"AU",
    "sg:address":"U5/ 18 Addison Ave",
    "sg:city":"Bulimba",
    "sg:classifiers":[
        {
            "category":"Professional",
            "subcategory":"Management & Consulting",
            "type":"Services"
        }
    ],
    "sg:phone":"+61 7 3399 5460",
    "sg:postcode":"4171",
    "sg:province":"QLD",
    "sg:tags":[
        "consultant"
    ],
    "wof:name":"Asset Partnership Pty Ltd",
    "wof:placetype":"venue"
},
  "geometry": {"coordinates":[153.053390503,-27.4517307281],"type":"Point"}
}