{
  "type": "Feature",
  "properties": {
    "addr:full":"9 Reservoir St Frankston VIC 3199",
    "addr:housenumber":"9",
    "addr:postcode":"3199",
    "addr:street":"Reservoir St",
    "iso:country":"AU",
    "sg:address":"9 Reservoir St",
    "sg:city":"Frankston",
    "sg:classifiers":[
        {
            "category":"Wholesale",
            "subcategory":"Painting Supplies",
            "type":"Manufacturing & Wholesale Goods"
        }
    ],
    "sg:phone":"+61 3 9783 3106",
    "sg:postcode":"3199",
    "sg:province":"VIC",
    "sg:tags":[
        "product",
        "cleaning"
    ],
    "wof:name":"Amway Of Australia Pty Ltd",
    "wof:placetype":"venue"
},
  "geometry": {"coordinates":[145.00282287600001,-37.7218475342],"type":"Point"}
}