{
  "type": "Feature",
  "properties": {
    "addr:full":"PO Box 202 Charlestown NSW 2290",
    "addr:postcode":"2290",
    "iso:country":"AU",
    "sg:address":"PO Box 202",
    "sg:city":"Charlestown",
    "sg:classifiers":[
        {
            "category":"Transit Center",
            "subcategory":"Freight",
            "type":"Transportation"
        }
    ],
    "sg:phone":"+61 2 4942 5905",
    "sg:postcode":"2290",
    "sg:province":"NSW",
    "sg:tags":[
        "agent",
        "shipping"
    ],
    "wof:name":"Rohlig Australia Pty Ltd",
    "wof:placetype":"venue"
},
  "geometry": {"coordinates":[151.68812560999999,-32.9578514099],"type":"Point"}
}