{
  "type": "Feature",
  "properties": {
    "addr:full":"17 Bolton Drv Strathdale VIC 3550",
    "addr:housenumber":"17",
    "addr:postcode":"3550",
    "addr:street":"Bolton Drv",
    "iso:country":"AU",
    "sg:address":"17 Bolton Drv",
    "sg:city":"Strathdale",
    "sg:classifiers":[
        {
            "category":"Government",
            "subcategory":"Post Office",
            "type":"Public Place"
        }
    ],
    "sg:phone":"+61 3 5441 1311",
    "sg:postcode":"3550",
    "sg:province":"VIC",
    "sg:tags":[
        "equipment",
        "hole",
        "contractor"
    ],
    "wof:name":"A Dingo Digger",
    "wof:placetype":"venue"
},
  "geometry": {"coordinates":[144.30569457999999,-36.7769584656],"type":"Point"}
}