{
  "type": "Feature",
  "properties": {
    "addr:full":"26 Swinson Rd Blacktown NSW 2148",
    "addr:housenumber":"26",
    "addr:postcode":"2148",
    "addr:street":"Swinson Rd",
    "iso:country":"AU",
    "sg:address":"26 Swinson Rd",
    "sg:city":"Blacktown",
    "sg:classifiers":[
        {
            "category":"Organizations",
            "subcategory":"Community Association",
            "type":"Services"
        }
    ],
    "sg:phone":"+61 2 9621 2458",
    "sg:postcode":"2148",
    "sg:province":"NSW",
    "sg:tags":[
        "organisation",
        "family",
        "welfare"
    ],
    "wof:name":"Swinson Cottage Family Centre",
    "wof:placetype":"venue"
},
  "geometry": {"coordinates":[150.90667724599999,-33.77576828],"type":"Point"}
}