{
  "type": "Feature",
  "properties": {
    "iso:country":"AU",
    "sg:address":"Shop 27",
    "sg:city":"Centrepoint Plaza Shopping Centre Caloundra",
    "sg:classifiers":[
        {
            "category":"Shopping",
            "subcategory":"Clothing, Apparel, & Fashions",
            "type":"Retail Goods"
        }
    ],
    "sg:phone":"+61 7 5499 7433",
    "sg:postcode":"4551",
    "sg:province":"QLD",
    "sg:tags":[
        "boutique"
    ],
    "wof:name":"Expressions By Cathy Pty Ltd",
    "wof:placetype":"venue"
},
  "geometry": {"coordinates":[153.124755859,-26.7936191559],"type":"Point"}
}