{
  "type": "Feature",
  "properties": {
    "addr:full":"36 Baker St Toowoomba QLD 4350",
    "addr:housenumber":"36",
    "addr:postcode":"4350",
    "addr:street":"Baker St",
    "iso:country":"AU",
    "sg:address":"36 Baker St",
    "sg:city":"Toowoomba",
    "sg:classifiers":[
        {
            "category":"Social Services",
            "subcategory":"Child Care",
            "type":"Services"
        }
    ],
    "sg:phone":"+61 7 4630 1722",
    "sg:postcode":"4350",
    "sg:province":"QLD",
    "wof:name":"Garndoo Jarowair",
    "wof:placetype":"venue"
},
  "geometry": {"coordinates":[151.92489599999999,-27.598755],"type":"Point"}
}