{
  "type": "Feature",
  "properties": {
    "addr:full":"14 Augustus St Modbury Heights SA 5092",
    "addr:housenumber":"14",
    "addr:postcode":"5092",
    "addr:street":"Augustus St",
    "iso:country":"AU",
    "sg:address":"14 Augustus St",
    "sg:city":"Modbury Heights",
    "sg:classifiers":[
        {
            "category":"Travel",
            "subcategory":"Resort",
            "type":"Entertainment"
        }
    ],
    "sg:phone":"+61 8 8396 2357",
    "sg:postcode":"5092",
    "sg:province":"SA",
    "sg:tags":[
        "club",
        "caravan"
    ],
    "wof:name":"United Caravan Club",
    "wof:placetype":"venue"
},
  "geometry": {"coordinates":[138.680587769,-34.8110351562],"type":"Point"}
}