{
  "type": "Feature",
  "properties": {
    "addr:full":"Cnr Watson & Riddell Sts Molong NSW 2866",
    "addr:postcode":"2866",
    "addr:street":"Cnr",
    "iso:country":"AU",
    "sg:address":"Cnr Watson & Riddell Sts",
    "sg:city":"Molong",
    "sg:classifiers":[
        {
            "category":"Autos & Motor Vehicles",
            "subcategory":"Automobile Sales",
            "type":"Retail Goods"
        }
    ],
    "sg:phone":"+61 2 6366 8863",
    "sg:postcode":"2866",
    "sg:province":"NSW",
    "sg:tags":[
        "car",
        "used"
    ],
    "wof:name":"Glenroi Car Sales",
    "wof:placetype":"venue"
},
  "geometry": {"coordinates":[148.869507,-33.094131],"type":"Point"}
}