{
  "type": "Feature",
  "properties": {
    "iso:country":"AU",
    "sg:address":"Suite 1/10- 12 Old Castle Hill Rd",
    "sg:city":"Castle Hill",
    "sg:classifiers":[
        {
            "category":"Health Services",
            "subcategory":"Health Practitioner",
            "type":"Services"
        }
    ],
    "sg:phone":"+61 2 9894 9087",
    "sg:postcode":"2154",
    "sg:province":"NSW",
    "sg:tags":[
        "naturopath"
    ],
    "wof:name":"R J Lucy Natural Therapist",
    "wof:placetype":"venue"
},
  "geometry": {"coordinates":[151.008636475,-33.7304115295],"type":"Point"}
}