{
  "type": "Feature",
  "properties": {
    "iso:country":"AU",
    "sg:address":"16 Attwell St",
    "sg:city":"Landsdale",
    "sg:classifiers":[
        {
            "category":"Wholesale",
            "subcategory":"Furniture",
            "type":"Manufacturing & Wholesale Goods"
        }
    ],
    "sg:phone":"+61 8 9409 1106",
    "sg:postcode":"6065",
    "sg:province":"WA",
    "sg:tags":[
        "wholesaler",
        "mfrs"
    ],
    "wof:name":"Vinwood Furniture",
    "wof:placetype":"venue"
},
  "geometry": {"coordinates":[115.847686768,-31.7998523712],"type":"Point"}
}