{
  "type": "Feature",
  "properties": {
    "addr:full":"61 Grote St Adelaide SA 5000",
    "addr:postcode":"5000",
    "addr:street":"Grote St",
    "iso:country":"AU",
    "sg:address":"61 Grote St",
    "sg:city":"Adelaide",
    "sg:classifiers":[
        {
            "category":"Shopping",
            "subcategory":"Clothing, Apparel, & Fashions",
            "type":"Retail Goods"
        }
    ],
    "sg:phone":"+61 8 8231 0190",
    "sg:postcode":"5000",
    "sg:province":"SA",
    "sg:tags":[
        "lady",
        "wear"
    ],
    "wof:name":"Hot Wear",
    "wof:placetype":"venue"
},
  "geometry": {"coordinates":[138.597091675,-34.9289855957],"type":"Point"}
}