{
  "type": "Feature",
  "properties": {
    "iso:country":"AU",
    "sg:address":"2 Chaffers St",
    "sg:city":"Morley",
    "sg:classifiers":[
        {
            "category":"Social Services",
            "subcategory":"Child Care",
            "type":"Services"
        }
    ],
    "sg:phone":"+61 8 6278 4342",
    "sg:postcode":"6062",
    "sg:province":"WA",
    "wof:name":"Jellybeans Child Care",
    "wof:placetype":"venue"
},
  "geometry": {"coordinates":[115.924789429,-31.8799953461],"type":"Point"}
}