{
  "type": "Feature",
  "properties": {
    "addr:full":"126 Ayr St Doncaster VIC 3108",
    "addr:housenumber":"126",
    "addr:postcode":"3108",
    "addr:street":"Ayr St",
    "iso:country":"AU",
    "sg:address":"126 Ayr St",
    "sg:city":"Doncaster",
    "sg:classifiers":[
        {
            "category":"Professional",
            "subcategory":"Computer Services",
            "type":"Services"
        }
    ],
    "sg:phone":"+61 3 9852 3611",
    "sg:postcode":"3108",
    "sg:province":"VIC",
    "sg:tags":[
        "consultant",
        "system"
    ],
    "wof:name":"Software Adeptations Pty Ltd",
    "wof:placetype":"venue"
},
  "geometry": {"coordinates":[145.103912353,-37.7766036987],"type":"Point"}
}