{
  "type": "Feature",
  "properties": {
    "iso:country":"AU",
    "sg:address":"32 Kayleigh Drv",
    "sg:city":"Maroochydore",
    "sg:classifiers":[
        {
            "category":"Banks & Credit Unions",
            "subcategory":"Bureau De Change",
            "type":"Services"
        }
    ],
    "sg:phone":"+61 7 5479 6885",
    "sg:postcode":"4558",
    "sg:province":"QLD",
    "sg:tags":[
        "repairs",
        "part",
        "appliance",
        "electrical"
    ],
    "wof:name":"Appliance Repairs & Electrical Services Of Qld",
    "wof:placetype":"venue"
},
  "geometry": {"coordinates":[153.088912964,-26.6698036194],"type":"Point"}
}