{
  "type": "Feature",
  "properties": {
    "addr:full":"3350 Frankston-Flinders Rd Merricks VIC 3916",
    "addr:housenumber":"3350",
    "addr:postcode":"3916",
    "addr:street":"Frankston-Flinders Rd",
    "iso:country":"AU",
    "sg:address":"3350 Frankston-Flinders Rd",
    "sg:city":"Merricks",
    "sg:classifiers":[
        {
            "category":"Professional",
            "subcategory":"Art Services",
            "type":"Services"
        }
    ],
    "sg:phone":"+61 3 5983 5492",
    "sg:postcode":"3916",
    "sg:province":"VIC",
    "sg:tags":[
        "artist"
    ],
    "wof:name":"Beavan Bill",
    "wof:placetype":"venue"
},
  "geometry": {"coordinates":[145.09727477999999,-38.3868293762],"type":"Point"}
}