{
  "type": "Feature",
  "properties": {
    "iso:country":"AU",
    "sg:address":"51- 57 Bell St",
    "sg:city":"Kangaroo Point",
    "sg:classifiers":[
        {
            "category":"Professional",
            "subcategory":"Computer Services",
            "type":"Services"
        }
    ],
    "sg:phone":"+61 7 3891 1199",
    "sg:postcode":"4169",
    "sg:province":"QLD",
    "sg:tags":[
        "repairs",
        "upgrade",
        "equipment"
    ],
    "wof:name":"International Technology Corporation",
    "wof:placetype":"venue"
},
  "geometry": {"coordinates":[153.03599548299999,-27.4794578552],"type":"Point"}
}