{
  "type": "Feature",
  "properties": {
    "addr:full":"12 Old Great Northern Hwy Midland WA 6056",
    "addr:housenumber":"12",
    "addr:postcode":"6056",
    "addr:street":"Old Great Northern Hwy",
    "iso:country":"AU",
    "sg:address":"12 Old Great Northern Hwy",
    "sg:city":"Midland",
    "sg:classifiers":[
        {
            "category":"Real Estate",
            "subcategory":"Real Estate Agent",
            "type":"Services"
        }
    ],
    "sg:phone":"+61 1300 454 077",
    "sg:postcode":"6056",
    "sg:province":"WA",
    "wof:name":"C.R.T. Real Estate Pty Ltd",
    "wof:placetype":"venue"
},
  "geometry": {"coordinates":[116.003547669,-31.8878326416],"type":"Point"}
}