{
  "type": "Feature",
  "properties": {
    "addr:full":"1706 McKinnon Rd Pinelands NT 0829",
    "addr:housenumber":"1706",
    "addr:postcode":"nt 0829",
    "addr:street":"Mckinnon Rd",
    "iso:country":"AU",
    "sg:address":"1706 McKinnon Rd",
    "sg:city":"Pinelands",
    "sg:classifiers":[
        {
            "category":"Manufacturing",
            "subcategory":"Metals",
            "type":"Manufacturing & Wholesale Goods"
        }
    ],
    "sg:phone":"+61 8 8932 2627",
    "sg:postcode":"0829",
    "sg:province":"NT",
    "sg:tags":[
        "steel",
        "fabricator",
        "mfrs"
    ],
    "wof:name":"Blumax NT",
    "wof:placetype":"venue"
},
  "geometry": {"coordinates":[130.964233398,-12.4541091919],"type":"Point"}
}