{
  "type": "Feature",
  "properties": {
    "iso:country":"AU",
    "sg:address":"126 Otho St",
    "sg:city":"Inverell",
    "sg:classifiers":[
        {
            "category":"Shopping",
            "subcategory":"Gifts & Souvenirs",
            "type":"Retail Goods"
        }
    ],
    "sg:phone":"+61 2 6721 3343",
    "sg:postcode":"2360",
    "sg:province":"NSW",
    "sg:tags":[
        "print",
        "poster",
        "pictures"
    ],
    "wof:name":"Edgewood Framing",
    "wof:placetype":"venue"
},
  "geometry": {"coordinates":[151.11395263700001,-29.7759819031],"type":"Point"}
}