{
  "type": "Feature",
  "properties": {
    "addr:full":"191 Errol St North Melbourne VIC 3051",
    "addr:housenumber":"191",
    "addr:postcode":"3051",
    "addr:street":"Errol St",
    "iso:country":"AU",
    "sg:address":"191 Errol St",
    "sg:city":"North Melbourne",
    "sg:classifiers":[
        {
            "category":"Professional",
            "subcategory":"Computer Services",
            "type":"Services"
        }
    ],
    "sg:phone":"+61 3 9328 2509",
    "sg:postcode":"3051",
    "sg:province":"VIC",
    "sg:tags":[
        "consultant",
        "system"
    ],
    "wof:name":"Culvenor & Associates Pty Ltd",
    "wof:placetype":"venue"
},
  "geometry": {"coordinates":[144.94999694800001,-37.8000297546],"type":"Point"}
}