{
  "type": "Feature",
  "properties": {
    "addr:full":"552 High Street Rd Mt Waverley VIC 3149",
    "addr:housenumber":"552",
    "addr:postcode":"3149",
    "addr:street":"High Street Rd",
    "iso:country":"AU",
    "sg:address":"552 High Street Rd",
    "sg:city":"Mt Waverley",
    "sg:classifiers":[
        {
            "category":"Building & Trades",
            "subcategory":"Landscaping Services",
            "type":"Services"
        }
    ],
    "sg:phone":"+61 3 9803 9057",
    "sg:postcode":"3149",
    "sg:province":"VIC",
    "sg:tags":[
        "gardener"
    ],
    "wof:name":"Greenmount Nurseries",
    "wof:placetype":"venue"
},
  "geometry": {"coordinates":[145.14689636200001,-37.8721351624],"type":"Point"}
}