{
  "type": "Feature",
  "properties": {
    "addr:full":"Suite 12, 36 Finchley St Milton QLD 4064",
    "addr:housenumber":"36",
    "addr:postcode":"4064",
    "addr:street":"Finchley St",
    "iso:country":"AU",
    "sg:address":"Suite 12, 36 Finchley St",
    "sg:city":"Milton",
    "sg:classifiers":[
        {
            "category":"Banks & Credit Unions",
            "subcategory":"Bank",
            "type":"Services"
        }
    ],
    "sg:phone":"+61 1300 782 900",
    "sg:postcode":"4064",
    "sg:province":"QLD",
    "sg:tags":[
        "broker",
        "mortgage"
    ],
    "wof:name":"Direct Deal Finance",
    "wof:placetype":"venue"
},
  "geometry": {"coordinates":[153.00590515100001,-27.4657993317],"type":"Point"}
}