{
  "type": "Feature",
  "properties": {
    "addr:full":"211 Waverley Rd Malvern East VIC 3145",
    "addr:housenumber":"211",
    "addr:postcode":"3145",
    "addr:street":"Waverley Rd",
    "iso:country":"AU",
    "sg:address":"211 Waverley Rd",
    "sg:city":"Malvern East",
    "sg:classifiers":[
        {
            "category":"Building & Trades",
            "subcategory":"Construction",
            "type":"Services"
        }
    ],
    "sg:phone":"+61 3 9573 1200",
    "sg:postcode":"3145",
    "sg:province":"VIC",
    "sg:tags":[
        "contractor"
    ],
    "wof:name":"Executive Homes",
    "wof:placetype":"venue"
},
  "geometry": {"coordinates":[145.05250549300001,-37.8763313293],"type":"Point"}
}