{
  "type": "Feature",
  "properties": {
    "addr:full":"Lot 54 Avoca Drv Green Point NSW 2251",
    "addr:postcode":"2251",
    "addr:street":"Avoca Drv",
    "iso:country":"AU",
    "sg:address":"Lot 54 Avoca Drv",
    "sg:city":"Green Point",
    "sg:classifiers":[
        {
            "category":"Autos & Motor Vehicles",
            "subcategory":"Fuel & Gas Station",
            "type":"Retail Goods"
        }
    ],
    "sg:phone":"+61 2 4369 7498",
    "sg:postcode":"2251",
    "sg:province":"NSW",
    "wof:name":"Metro Green Point",
    "wof:placetype":"venue"
},
  "geometry": {"coordinates":[151.36541748100001,-33.4491462708],"type":"Point"}
}