{
  "type": "Feature",
  "properties": {
    "addr:full":"5 Bourton Rd Merrimac QLD 4226",
    "addr:housenumber":"5",
    "addr:postcode":"4226",
    "addr:street":"Bourton Rd",
    "iso:country":"AU",
    "sg:address":"5 Bourton Rd",
    "sg:city":"Merrimac",
    "sg:classifiers":[
        {
            "category":"Travel",
            "subcategory":"Hostel",
            "type":"Entertainment"
        }
    ],
    "sg:phone":"+61 7 5559 4600",
    "sg:postcode":"4226",
    "sg:province":"QLD",
    "sg:tags":[
        "home"
    ],
    "wof:name":"Bruno Vogt's",
    "wof:placetype":"venue"
},
  "geometry": {"coordinates":[153.36026000999999,-28.0500469208],"type":"Point"}
}