{
  "type": "Feature",
  "properties": {
    "addr:full":"271 Bambra Rd Caulfield South VIC 3162",
    "addr:housenumber":"271",
    "addr:postcode":"3162",
    "addr:street":"Bambra Rd",
    "iso:country":"AU",
    "sg:address":"271 Bambra Rd",
    "sg:city":"Caulfield South",
    "sg:classifiers":[
        {
            "category":"Real Estate",
            "subcategory":"Real Estate Agent",
            "type":"Services"
        }
    ],
    "sg:phone":"+61 3 9532 8711",
    "sg:postcode":"3162",
    "sg:province":"VIC",
    "wof:name":"Gelfand B & B",
    "wof:placetype":"venue"
},
  "geometry": {"coordinates":[145.02772522000001,-37.8925476074],"type":"Point"}
}