{
  "type": "Feature",
  "properties": {
    "addr:full":"6 Molong Rd Gymea Bay NSW 2227",
    "addr:housenumber":"6",
    "addr:postcode":"2227",
    "addr:street":"Molong Rd",
    "iso:country":"AU",
    "sg:address":"6 Molong Rd",
    "sg:city":"Gymea Bay",
    "sg:classifiers":[
        {
            "category":"Professional",
            "subcategory":"Management & Consulting",
            "type":"Services"
        }
    ],
    "sg:phone":"+61 2 9524 0054",
    "sg:postcode":"2227",
    "sg:province":"NSW",
    "sg:tags":[
        "consultant"
    ],
    "wof:name":"New Venture Management Services",
    "wof:placetype":"venue"
},
  "geometry": {"coordinates":[151.08392334000001,-34.0524978638],"type":"Point"}
}