{
  "type": "Feature",
  "properties": {
    "addr:full":"Unit 1, 9 Waxman Pde Brunswick West VIC 3055",
    "addr:housenumber":"9",
    "addr:postcode":"3055",
    "addr:street":"Waxman Pde",
    "iso:country":"AU",
    "sg:address":"Unit 1, 9 Waxman Pde",
    "sg:city":"Brunswick West",
    "sg:classifiers":[
        {
            "category":"Building & Trades",
            "subcategory":"Cleaning & Sanitation",
            "type":"Services"
        }
    ],
    "sg:phone":"+61 412 612 666",
    "sg:postcode":"3055",
    "sg:province":"VIC",
    "sg:tags":[
        "cleaner",
        "repairer",
        "roof"
    ],
    "wof:name":"MDB Constructions",
    "wof:placetype":"venue"
},
  "geometry": {"coordinates":[144.93446350100001,-37.7582015991],"type":"Point"}
}