{
  "type": "Feature",
  "properties": {
    "iso:country":"AU",
    "sg:address":"Phillip St",
    "sg:city":"Dubbo",
    "sg:classifiers":[
        {
            "category":"Utilities",
            "subcategory":"Fuel Oil & Lpg",
            "type":"Services"
        }
    ],
    "sg:phone":"+61 2 6882 2600",
    "sg:postcode":"2830",
    "sg:province":"NSW",
    "sg:tags":[
        "merchant"
    ],
    "wof:name":"Caltex Energy NSW",
    "wof:placetype":"venue"
},
  "geometry": {"coordinates":[148.615310669,-32.2450942993],"type":"Point"}
}