{
  "type": "Feature",
  "properties": {
    "addr:full":"27 Boomerang Rd Mundijong WA 6123",
    "addr:housenumber":"27",
    "addr:postcode":"6123",
    "addr:street":"Boomerang Rd",
    "iso:country":"AU",
    "sg:address":"27 Boomerang Rd",
    "sg:city":"Mundijong",
    "sg:classifiers":[
        {
            "category":"Wholesale",
            "subcategory":"Farm Supplies",
            "type":"Manufacturing & Wholesale Goods"
        }
    ],
    "sg:phone":"+61 8 9526 2322",
    "sg:postcode":"6123",
    "sg:province":"WA",
    "sg:tags":[
        "feed",
        "supplement",
        "stock"
    ],
    "wof:name":"Boomerang Stockfeeds",
    "wof:placetype":"venue"
},
  "geometry": {"coordinates":[115.969566345,-32.2788200378],"type":"Point"}
}