{
  "type": "Feature",
  "properties": {
    "addr:full":"369 Greenhill Rd Toorak Gardens SA 5065",
    "addr:housenumber":"369",
    "addr:postcode":"5065",
    "addr:street":"Greenhill Rd Toorak Gardens",
    "iso:country":"AU",
    "sg:address":"369 Greenhill Rd",
    "sg:city":"Toorak Gardens",
    "sg:classifiers":[
        {
            "category":"Organizations",
            "subcategory":"Non-profit Organization",
            "type":"Services"
        }
    ],
    "sg:phone":"+61 8 8338 2200",
    "sg:postcode":"5065",
    "sg:province":"SA",
    "sg:tags":[
        "support",
        "disability",
        "organisation"
    ],
    "wof:name":"Assist Home Care",
    "wof:placetype":"venue"
},
  "geometry": {"coordinates":[138.642654419,-34.9418182373],"type":"Point"}
}