{
  "type": "Feature",
  "properties": {
    "addr:full":"29 Eleventh St Mildura VIC 3500",
    "addr:housenumber":"29",
    "addr:postcode":"3500",
    "addr:street":"Eleventh St",
    "iso:country":"AU",
    "sg:address":"29 Eleventh St",
    "sg:city":"Mildura",
    "sg:classifiers":[
        {
            "category":"Home & Garden",
            "subcategory":"Garden Supply",
            "type":"Retail Goods"
        }
    ],
    "sg:phone":"+61 3 5023 1383",
    "sg:postcode":"3500",
    "sg:province":"VIC",
    "sg:tags":[
        "equipment"
    ],
    "wof:name":"Mildura Mini Mix & Garden Supplies",
    "wof:placetype":"venue"
},
  "geometry": {"coordinates":[142.17466735799999,-34.2041473389],"type":"Point"}
}