{
  "type": "Feature",
  "properties": {
    "addr:full":"198 Fifteenth Ave West Hoxton NSW 2171",
    "addr:housenumber":"198",
    "addr:postcode":"2171",
    "addr:street":"Fifteenth Ave West",
    "iso:country":"AU",
    "sg:address":"198 Fifteenth Ave",
    "sg:city":"West Hoxton",
    "sg:classifiers":[
        {
            "category":"Retail",
            "subcategory":"Auto Repair",
            "type":"Services"
        }
    ],
    "sg:phone":"+61 2 9607 7903",
    "sg:postcode":"2171",
    "sg:province":"NSW",
    "sg:tags":[
        "bus",
        "truck"
    ],
    "wof:name":"Avati Auto Repairs",
    "wof:placetype":"venue"
},
  "geometry": {"coordinates":[150.831787109,-33.9212226868],"type":"Point"}
}