{
  "type": "Feature",
  "properties": {
    "addr:full":"Unit 10/ 2 Beauchamp Rd Banksmeadow NSW 2019",
    "addr:housenumber":"/ 2",
    "addr:postcode":"2019",
    "addr:street":"Beauchamp Rd",
    "iso:country":"AU",
    "sg:address":"Unit 10/ 2 Beauchamp Rd",
    "sg:city":"Banksmeadow",
    "sg:classifiers":[
        {
            "category":"Professional",
            "type":"Services"
        }
    ],
    "sg:phone":"+61 2 8335 9888",
    "sg:postcode":"2019",
    "sg:province":"NSW",
    "sg:tags":[
        "forwarding",
        "agent",
        "transport"
    ],
    "wof:name":"ABX Logistics P/L",
    "wof:placetype":"venue"
},
  "geometry": {"coordinates":[151.22073364299999,-33.9598350525],"type":"Point"}
}