{
  "type": "Feature",
  "properties": {
    "addr:full":"Cricketers Arms Rd Blacktown NSW 2148",
    "addr:postcode":"2148",
    "addr:street":"Arms Rd",
    "iso:country":"AU",
    "sg:address":"Cricketers Arms Rd",
    "sg:city":"Blacktown",
    "sg:classifiers":[
        {
            "category":"Building & Trades",
            "subcategory":"Landscaping Services",
            "type":"Services"
        }
    ],
    "sg:phone":"+61 2 9747 1986",
    "sg:postcode":"2148",
    "sg:province":"NSW",
    "sg:tags":[
        "market"
    ],
    "wof:name":"Blacktown Markets",
    "wof:placetype":"venue"
},
  "geometry": {"coordinates":[150.90272522000001,-33.8057365417],"type":"Point"}
}