{
  "type": "Feature",
  "properties": {
    "iso:country":"AU",
    "sg:address":"7- 9 Devonshire Rd",
    "sg:city":"Sunshine",
    "sg:classifiers":[
        {
            "category":"Health Services",
            "subcategory":"Dentist",
            "type":"Services"
        }
    ],
    "sg:phone":"+61 3 9791 6230",
    "sg:postcode":"3020",
    "sg:province":"VIC",
    "wof:name":"McDonald Andrew J",
    "wof:placetype":"venue"
},
  "geometry": {"coordinates":[144.831802,-37.784683],"type":"Point"}
}