{
  "type": "Feature",
  "properties": {
    "addr:full":"Shop 3, Albion Centre 119 Wallace St Braidwood NSW 2622",
    "addr:housenumber":"shop 3;119",
    "addr:postcode":"2622",
    "addr:street":"Albion;Wallace St",
    "iso:country":"AU",
    "sg:address":"Shop 3, Albion Centre 119 Wallace St",
    "sg:city":"Braidwood",
    "sg:classifiers":[
        {
            "category":"Shopping",
            "subcategory":"Antiques",
            "type":"Retail Goods"
        }
    ],
    "sg:phone":"+61 2 4842 2052",
    "sg:postcode":"2622",
    "sg:province":"NSW",
    "wof:name":"Jacksons On Wallace",
    "wof:placetype":"venue"
},
  "geometry": {"coordinates":[149.80116272000001,-35.4370765686],"type":"Point"}
}