{
  "type": "Feature",
  "properties": {
    "addr:full":"PO Box 185 Sea Lake VIC 3533",
    "addr:postcode":"3533",
    "iso:country":"AU",
    "sg:address":"PO Box 185",
    "sg:city":"Sea Lake",
    "sg:classifiers":[
        {
            "category":"Utilities",
            "subcategory":"Electric",
            "type":"Services"
        }
    ],
    "sg:phone":"+61 3 5070 2097",
    "sg:postcode":"3533",
    "sg:province":"VIC",
    "sg:tags":[
        "electrical",
        "contractor"
    ],
    "wof:name":"C & M Pearce Electrical",
    "wof:placetype":"venue"
},
  "geometry": {"coordinates":[142.84956399999999,-35.504398],"type":"Point"}
}