{
  "type": "Feature",
  "properties": {
    "iso:country":"AU",
    "sg:address":"3 Langford Drv",
    "sg:city":"Elizabeth",
    "sg:classifiers":[
        {
            "category":"Education",
            "subcategory":"Kindergarten",
            "type":"Public Place"
        }
    ],
    "sg:phone":"+61 8 8252 5032",
    "sg:postcode":"5112",
    "sg:province":"SA",
    "sg:tags":[
        "pre-schools"
    ],
    "wof:name":"Playford Children's Centre",
    "wof:placetype":"venue"
},
  "geometry": {"coordinates":[138.66505432100001,-34.7210083008],"type":"Point"}
}