{
  "type": "Feature",
  "properties": {
    "iso:country":"AU",
    "sg:address":"213 Holt St",
    "sg:city":"Eagle Farm",
    "sg:classifiers":[
        {
            "category":"Professional",
            "type":"Services"
        }
    ],
    "sg:phone":"+61 7 3868 0999",
    "sg:postcode":"4009",
    "sg:province":"QLD",
    "sg:tags":[
        "courier"
    ],
    "wof:name":"Busfreight",
    "wof:placetype":"venue"
},
  "geometry": {"coordinates":[153.10243225100001,-27.4364776611],"type":"Point"}
}