{
  "type": "Feature",
  "properties": {
    "addr:full":"P.O. Box 193 Collins St (West) Melbourne VIC 3000",
    "addr:postcode":"3000",
    "addr:street":"Collins St",
    "iso:country":"AU",
    "sg:address":"P.O. Box 193 Collins St",
    "sg:city":"(West) Melbourne",
    "sg:classifiers":[
        {
            "category":"Professional",
            "subcategory":"Employment Agencies",
            "type":"Services"
        }
    ],
    "sg:phone":"+61 3 9642 3333",
    "sg:postcode":"3000",
    "sg:province":"VIC",
    "sg:tags":[
        "provider",
        "internet"
    ],
    "wof:name":"Internex Australia Pty Ltd",
    "wof:placetype":"venue"
},
  "geometry": {"coordinates":[144.970611572,-37.8142967224],"type":"Point"}
}