{
  "type": "Feature",
  "properties": {
    "addr:full":"85 Bowden St Ryde NSW 2112",
    "addr:housenumber":"85",
    "addr:postcode":"2112",
    "addr:street":"Bowden St",
    "iso:country":"AU",
    "sg:address":"85 Bowden St",
    "sg:city":"Ryde",
    "sg:classifiers":[
        {
            "category":"Bars & Pubs",
            "subcategory":"Nightclub",
            "type":"Food & Drink"
        }
    ],
    "sg:phone":"+61 2 9809 5916",
    "sg:postcode":"2112",
    "sg:province":"NSW",
    "sg:tags":[
        "karaoke"
    ],
    "wof:name":"A.AA Aachen Jukebox & Karaoke Hire",
    "wof:placetype":"venue"
},
  "geometry": {"coordinates":[151.095214844,-33.8144378662],"type":"Point"}
}