{
  "type": "Feature",
  "properties": {
    "iso:country":"AU",
    "sg:address":"50 Dodd Rd",
    "sg:city":"Bickley",
    "sg:classifiers":[
        {
            "category":"Professional",
            "subcategory":"Computer Services",
            "type":"Services"
        }
    ],
    "sg:phone":"+61 8 9291 0101",
    "sg:postcode":"6076",
    "sg:province":"WA",
    "sg:tags":[
        "consultant",
        "system"
    ],
    "wof:name":"Spiral Technology Pty Ltd",
    "wof:placetype":"venue"
},
  "geometry": {"coordinates":[116.105171204,-32.0055961609],"type":"Point"}
}