{
  "type": "Feature",
  "properties": {
    "addr:full":"198 Tranmere Rd Howrah TAS 7018",
    "addr:housenumber":"198",
    "addr:postcode":"7018",
    "addr:street":"Tranmere Rd",
    "iso:country":"AU",
    "sg:address":"198 Tranmere Rd",
    "sg:city":"Howrah",
    "sg:classifiers":[
        {
            "category":"Recreation",
            "subcategory":"Water Park",
            "type":"Entertainment"
        }
    ],
    "sg:phone":"+61 3 6247 9446",
    "sg:postcode":"7018",
    "sg:province":"TAS",
    "sg:tags":[
        "control",
        "seepage"
    ],
    "wof:name":"Advanced Damp Proofing",
    "wof:placetype":"venue"
},
  "geometry": {"coordinates":[147.418136597,-42.9053382874],"type":"Point"}
}