{
  "type": "Feature",
  "properties": {
    "iso:country":"AU",
    "sg:address":"Level 2/ 21 Mary St",
    "sg:city":"Brisbane",
    "sg:classifiers":[
        {
            "category":"Health Services",
            "subcategory":"Health Practitioner",
            "type":"Services"
        }
    ],
    "sg:phone":"+61 7 3012 7007",
    "sg:postcode":"4000",
    "sg:province":"QLD",
    "sg:tags":[
        "physiotherapist"
    ],
    "sg:website":"http://www.revivestudio.com.au",
    "wof:name":"Revive Pilates and Physiotheraphy",
    "wof:placetype":"venue"
},
  "geometry": {"coordinates":[153.02638244600001,-27.4729442596],"type":"Point"}
}