{
  "type": "Feature",
  "properties": {
    "addr:full":"33 Kent St Deakin ACT 2600",
    "addr:housenumber":"33",
    "addr:postcode":"2600",
    "addr:street":"Kent St Deakin",
    "iso:country":"AU",
    "sg:address":"33 Kent St",
    "sg:city":"Deakin",
    "sg:classifiers":[
        {
            "category":"Banks & Credit Unions",
            "subcategory":"Financial Services",
            "type":"Services"
        }
    ],
    "sg:phone":"+61 2 6282 5474",
    "sg:postcode":"2600",
    "sg:province":"ACT",
    "sg:tags":[
        "planning"
    ],
    "wof:name":"AXA Financial Planning",
    "wof:placetype":"venue"
},
  "geometry": {"coordinates":[149.09843444800001,-35.3164825439],"type":"Point"}
}