{
  "type": "Feature",
  "properties": {
    "addr:full":"PO Box 582 Toowoomba QLD 4350",
    "addr:postcode":"4350",
    "iso:country":"AU",
    "sg:address":"PO Box 582",
    "sg:city":"Toowoomba",
    "sg:classifiers":[
        {
            "category":"Professional",
            "subcategory":"Art Services",
            "type":"Services"
        }
    ],
    "sg:phone":"+61 417 563 452",
    "sg:postcode":"4350",
    "sg:province":"QLD",
    "sg:tags":[
        "decorator",
        "painter"
    ],
    "wof:name":"McLean Don",
    "wof:placetype":"venue"
},
  "geometry": {"coordinates":[151.875641,-27.55761],"type":"Point"}
}