{
  "type": "Feature",
  "properties": {
    "addr:full":"Shop 6C, Showgrounds Shopping Cntr, 157 Mulgrave Rd Cairns QLD 4870",
    "addr:housenumber":"6c;157",
    "addr:postcode":"4870",
    "addr:street":"Shop;Mulgrave Rd",
    "iso:country":"AU",
    "sg:address":"Shop 6C, Showgrounds Shopping Cntr, 157 Mulgrave Rd",
    "sg:city":"Cairns",
    "sg:classifiers":[
        {
            "category":"Shopping",
            "subcategory":"Bicycles & Sporting Goods",
            "type":"Retail Goods"
        }
    ],
    "sg:phone":"+61 7 4051 7280",
    "sg:postcode":"4870",
    "sg:province":"QLD",
    "sg:tags":[
        "chemical",
        "equipment",
        "pool",
        "swimming"
    ],
    "wof:name":"PoolWerx Cairns",
    "wof:placetype":"venue"
},
  "geometry": {"coordinates":[145.74366760300001,-16.9398193359],"type":"Point"}
}