{
  "type": "Feature",
  "properties": {
    "addr:full":"2a Crane Rd Castle Hill NSW 2154",
    "addr:housenumber":"2a",
    "addr:postcode":"2154",
    "addr:street":"Crane Rd",
    "iso:country":"AU",
    "sg:address":"2a Crane Rd",
    "sg:city":"Castle Hill",
    "sg:classifiers":[
        {
            "category":"Real Estate",
            "subcategory":"Developer",
            "type":"Services"
        }
    ],
    "sg:phone":"+61 2 9634 5222",
    "sg:postcode":"2154",
    "sg:province":"NSW",
    "sg:tags":[
        "development"
    ],
    "wof:name":"Castlehaven Realtors",
    "wof:placetype":"venue"
},
  "geometry": {"coordinates":[151.00604248100001,-33.7325134277],"type":"Point"}
}