{
  "type": "Feature",
  "properties": {
    "addr:full":"Suite 106/ 153 Park St Melbourne VIC 3000",
    "addr:housenumber":"/ 153",
    "addr:postcode":"3000",
    "addr:street":"Park St",
    "iso:country":"AU",
    "sg:address":"Suite 106/ 153 Park St",
    "sg:city":"Melbourne",
    "sg:classifiers":[
        {
            "category":"Professional",
            "subcategory":"Computer Services",
            "type":"Services"
        }
    ],
    "sg:phone":"+61 3 9690 6744",
    "sg:postcode":"3000",
    "sg:province":"VIC",
    "sg:tags":[
        "on-line",
        "provider"
    ],
    "wof:name":"AudioNET",
    "wof:placetype":"venue"
},
  "geometry": {"coordinates":[144.96910095199999,-37.8052864075],"type":"Point"}
}