{
  "type": "Feature",
  "properties": {
    "addr:full":"2 30 Princess St Seddon VIC 3011",
    "addr:housenumber":"30",
    "addr:postcode":"3011",
    "addr:street":"2;Princess St",
    "iso:country":"AU",
    "sg:address":"2 30 Princess St",
    "sg:city":"Seddon",
    "sg:classifiers":[
        {
            "category":"Utilities",
            "subcategory":"Refuse",
            "type":"Services"
        }
    ],
    "sg:phone":"+61 421 831 208",
    "sg:postcode":"3011",
    "sg:province":"VIC",
    "sg:tags":[
        "remover",
        "rubbish"
    ],
    "wof:name":"Action Rubbish Removers",
    "wof:placetype":"venue"
},
  "geometry": {"coordinates":[144.89627075199999,-37.8103485107],"type":"Point"}
}