{
  "type": "Feature",
  "properties": {
    "addr:full":"PO Box 364 Pambula NSW 2549",
    "addr:postcode":"2549",
    "iso:country":"AU",
    "sg:address":"PO Box 364",
    "sg:city":"Pambula",
    "sg:classifiers":[
        {
            "category":"Building & Trades",
            "subcategory":"Construction",
            "type":"Services"
        }
    ],
    "sg:phone":"+61 414 536 005",
    "sg:postcode":"2549",
    "sg:province":"NSW",
    "sg:tags":[
        "contractor"
    ],
    "wof:name":"Jim Moss Building Pty Ltd",
    "wof:placetype":"venue"
},
  "geometry": {"coordinates":[149.87449645999999,-36.9297485352],"type":"Point"}
}