{
  "type": "Feature",
  "properties": {
    "iso:country":"AU",
    "sg:address":"182 Main Rd",
    "sg:city":"McLaren Vale",
    "sg:classifiers":[
        {
            "category":"Real Estate",
            "subcategory":"Architect",
            "type":"Services"
        }
    ],
    "sg:phone":"+61 8 8323 8100",
    "sg:postcode":"5171",
    "sg:province":"SA",
    "wof:name":"Angus+ Dowie Architecture",
    "wof:placetype":"venue"
},
  "geometry": {"coordinates":[138.53874206500001,-35.2157287598],"type":"Point"}
}