{
  "type": "Feature",
  "properties": {
    "addr:full":"Shop 8 Stratton Shopping Centre Stratton WA 6056",
    "addr:housenumber":"shop 8",
    "addr:postcode":"6056",
    "addr:street":"Stratton Shopping",
    "iso:country":"AU",
    "sg:address":"Shop 8 Stratton Shopping Centre",
    "sg:city":"Stratton",
    "sg:classifiers":[
        {
            "category":"Food & Beverages",
            "subcategory":"Bakery",
            "type":"Retail Goods"
        }
    ],
    "sg:phone":"+61 8 9250 1744",
    "sg:postcode":"6056",
    "sg:province":"WA",
    "sg:tags":[
        "baker"
    ],
    "wof:name":"B B H French Hot Bread",
    "wof:placetype":"venue"
},
  "geometry": {"coordinates":[116.04772186300001,-31.8633403778],"type":"Point"}
}