{
  "type": "Feature",
  "properties": {
    "addr:full":"Camp Mountain Rd Camp Mountain QLD 4520",
    "addr:postcode":"4520",
    "addr:street":"Camp Mountain Rd",
    "iso:country":"AU",
    "sg:address":"Camp Mountain Rd",
    "sg:city":"Camp Mountain",
    "sg:classifiers":[
        {
            "category":"Shopping",
            "subcategory":"Gifts & Souvenirs",
            "type":"Retail Goods"
        }
    ],
    "sg:phone":"+61 7 3289 1677",
    "sg:postcode":"4520",
    "sg:province":"QLD",
    "sg:tags":[
        "wrapping"
    ],
    "wof:name":"Acorn Distributors",
    "wof:placetype":"venue"
},
  "geometry": {"coordinates":[152.888687,-27.39316],"type":"Point"}
}