{
  "type": "Feature",
  "properties": {
    "addr:full":"73 Pascoe St Glen Iris VIC 3146",
    "addr:housenumber":"73",
    "addr:postcode":"3146",
    "addr:street":"Pascoe St",
    "iso:country":"AU",
    "sg:address":"73 Pascoe St",
    "sg:city":"Glen Iris",
    "sg:classifiers":[
        {
            "category":"Personal",
            "subcategory":"Tattoo Parlor",
            "type":"Services"
        }
    ],
    "sg:phone":"+61 3 9889 1471",
    "sg:postcode":"3146",
    "sg:province":"VIC",
    "sg:tags":[
        "resume"
    ],
    "wof:name":"Custom CVs",
    "wof:placetype":"venue"
},
  "geometry": {"coordinates":[145.09280395499999,-37.8602142334],"type":"Point"}
}