{
  "type": "Feature",
  "properties": {
    "iso:country":"AU",
    "sg:address":"10 Best St",
    "sg:city":"Wagga Wagga",
    "sg:classifiers":[
        {
            "category":"Restaurant",
            "type":"Food & Drink"
        }
    ],
    "sg:phone":"+61 2 6931 8903",
    "sg:postcode":"2650",
    "sg:province":"NSW",
    "wof:name":"Cafe Lulaba",
    "wof:placetype":"venue"
},
  "geometry": {"coordinates":[147.365768433,-35.1181793213],"type":"Point"}
}