{
  "type": "Feature",
  "properties": {
    "addr:full":"Wakefield St Alderley QLD 4051",
    "addr:postcode":"4051",
    "addr:street":"Wakefield St",
    "iso:country":"AU",
    "sg:address":"Wakefield St",
    "sg:city":"Alderley",
    "sg:classifiers":[
        {
            "category":"Building & Trades",
            "subcategory":"Construction",
            "type":"Services"
        }
    ],
    "sg:phone":"+61 417 786 032",
    "sg:postcode":"4051",
    "sg:province":"QLD",
    "sg:tags":[
        "renovation",
        "alterations",
        "extension",
        "contractor"
    ],
    "wof:name":"G W H Constructions",
    "wof:placetype":"venue"
},
  "geometry": {"coordinates":[153.001785278,-27.4254264832],"type":"Point"}
}