{
  "type": "Feature",
  "properties": {
    "iso:country":"AU",
    "sg:address":"PO Box 101",
    "sg:city":"Diggers Rest",
    "sg:classifiers":[
        {
            "category":"Professional",
            "subcategory":"Employment Agencies",
            "type":"Services"
        }
    ],
    "sg:phone":"+61 3 9740 0295",
    "sg:postcode":"3427",
    "sg:province":"VIC",
    "wof:name":"Hamilton Project Services",
    "wof:placetype":"venue"
},
  "geometry": {"coordinates":[144.70118713400001,-37.6138801575],"type":"Point"}
}