{
  "type": "Feature",
  "properties": {
    "addr:full":"205 Peel St North Melbourne VIC 3051",
    "addr:housenumber":"205",
    "addr:postcode":"3051",
    "addr:street":"Peel St",
    "iso:country":"AU",
    "sg:address":"205 Peel St",
    "sg:city":"North Melbourne",
    "sg:classifiers":[
        {
            "category":"Autos & Motor Vehicles",
            "subcategory":"Automobile Sales",
            "type":"Retail Goods"
        }
    ],
    "sg:phone":"+61 3 9329 8888",
    "sg:postcode":"3051",
    "sg:province":"VIC",
    "sg:tags":[
        "car",
        "new"
    ],
    "wof:name":"Zagame Citroen",
    "wof:placetype":"venue"
},
  "geometry": {"coordinates":[144.95619201700001,-37.8028564453],"type":"Point"}
}