{
  "type": "Feature",
  "properties": {
    "addr:full":"52 Clifton St Balwyn North VIC 3104",
    "addr:housenumber":"52",
    "addr:postcode":"3104",
    "addr:street":"Clifton St",
    "iso:country":"AU",
    "sg:address":"52 Clifton St",
    "sg:city":"Balwyn North",
    "sg:classifiers":[
        {
            "category":"Wholesale",
            "subcategory":"Hardware",
            "type":"Manufacturing & Wholesale Goods"
        }
    ],
    "sg:phone":"+61 3 9857 5838",
    "sg:postcode":"3104",
    "sg:province":"VIC",
    "wof:name":"Ladco Australia",
    "wof:placetype":"venue"
},
  "geometry": {"coordinates":[145.10159301799999,-37.7953796387],"type":"Point"}
}