{
  "type": "Feature",
  "properties": {
    "addr:full":"6 Tibrockney St Highett VIC 3190",
    "addr:housenumber":"6",
    "addr:postcode":"3190",
    "addr:street":"Tibrockney St",
    "iso:country":"AU",
    "sg:address":"6 Tibrockney St",
    "sg:city":"Highett",
    "sg:classifiers":[
        {
            "category":"Home & Garden",
            "subcategory":"Garden Supply",
            "type":"Retail Goods"
        }
    ],
    "sg:phone":"+61 3 9555 9594",
    "sg:postcode":"3190",
    "sg:province":"VIC",
    "sg:tags":[
        "equipment"
    ],
    "wof:name":"Jim Stephens (Cartage Contractor) Pty Ltd",
    "wof:placetype":"venue"
},
  "geometry": {"coordinates":[145.03382873499999,-37.9539756775],"type":"Point"}
}