{
  "type": "Feature",
  "properties": {
    "addr:full":"Shop 109 Mirrabooka Shopng Cntr Mirrabooka WA 6061",
    "addr:housenumber":"109",
    "addr:postcode":"6061",
    "iso:country":"AU",
    "sg:address":"Shop 109",
    "sg:city":"Mirrabooka Shopng Cntr Mirrabooka",
    "sg:classifiers":[
        {
            "category":"Fast Food",
            "type":"Food & Drink"
        }
    ],
    "sg:phone":"+61 8 9344 1318",
    "sg:postcode":"6061",
    "sg:province":"WA",
    "sg:tags":[
        "away",
        "take"
    ],
    "wof:name":"Puffin Fresh",
    "wof:placetype":"venue"
},
  "geometry": {"coordinates":[115.85492706300001,-31.8529624939],"type":"Point"}
}