{
  "type": "Feature",
  "properties": {
    "addr:full":"32 Marnpar Rd Seven Hills NSW 2147",
    "addr:housenumber":"32",
    "addr:postcode":"2147",
    "addr:street":"Marnpar Rd",
    "iso:country":"AU",
    "sg:address":"32 Marnpar Rd",
    "sg:city":"Seven Hills",
    "sg:classifiers":[
        {
            "category":"Professional",
            "subcategory":"Art Services",
            "type":"Services"
        }
    ],
    "sg:phone":"+61 2 9674 7176",
    "sg:postcode":"2147",
    "sg:province":"NSW",
    "sg:tags":[
        "decorator",
        "painter"
    ],
    "wof:name":"Brien P S",
    "wof:placetype":"venue"
},
  "geometry": {"coordinates":[150.94654846200001,-33.7633666992],"type":"Point"}
}