{
  "type": "Feature",
  "properties": {
    "iso:country":"AU",
    "sg:address":"3 Garnet St",
    "sg:city":"Coogee",
    "sg:classifiers":[
        {
            "category":"Education",
            "subcategory":"Special Training",
            "type":"Public Place"
        }
    ],
    "sg:phone":"+61 2 9665 9127",
    "sg:postcode":"2034",
    "sg:province":"NSW",
    "sg:tags":[
        "development"
    ],
    "wof:name":"John Rock Consultants Pty Ltd",
    "wof:placetype":"venue"
},
  "geometry": {"coordinates":[151.258178711,-33.9283943176],"type":"Point"}
}