{
  "type": "Feature",
  "properties": {
    "addr:full":"Shop12/ 89 Bay Tce Wynnum QLD 4178",
    "addr:housenumber":"89",
    "addr:postcode":"4178",
    "addr:street":"Bay Tce",
    "iso:country":"AU",
    "sg:address":"Shop12/ 89 Bay Tce",
    "sg:city":"Wynnum",
    "sg:classifiers":[
        {
            "category":"Personal",
            "subcategory":"Beauty Salon",
            "type":"Services"
        }
    ],
    "sg:phone":"+61 7 3393 5016",
    "sg:postcode":"4178",
    "sg:province":"QLD",
    "sg:tags":[
        "hairdresser"
    ],
    "wof:name":"JPS Hair",
    "wof:placetype":"venue"
},
  "geometry": {"coordinates":[153.17326355,-27.4434680939],"type":"Point"}
}