{
  "type": "Feature",
  "properties": {
    "iso:country":"AU",
    "sg:address":"49 Marcia St",
    "sg:city":"Coffs Harbour",
    "sg:classifiers":[
        {
            "category":"Professional",
            "subcategory":"Computer Services",
            "type":"Services"
        }
    ],
    "sg:phone":"+61 2 6613 0561",
    "sg:postcode":"2450",
    "sg:province":"NSW",
    "sg:tags":[
        "equipment",
        "networking",
        "installation"
    ],
    "wof:name":"Groundup Design Solutions",
    "wof:placetype":"venue"
},
  "geometry": {"coordinates":[153.11979700000001,-30.289576],"type":"Point"}
}