{
  "type": "Feature",
  "properties": {
    "addr:full":"78 Old Canterbury Rd Lewisham NSW 2049",
    "addr:housenumber":"78",
    "addr:postcode":"2049",
    "addr:street":"Old Canterbury Rd",
    "iso:country":"AU",
    "sg:address":"78 Old Canterbury Rd",
    "sg:city":"Lewisham",
    "sg:classifiers":[
        {
            "category":"Banks & Credit Unions",
            "subcategory":"Atm",
            "type":"Services"
        }
    ],
    "sg:phone":"+61 2 9337 2737",
    "sg:postcode":"2049",
    "sg:province":"NSW",
    "sg:tags":[
        "wholesaler",
        "mfrs",
        "envelope"
    ],
    "wof:name":"Ecocern Post-Consumer Recycled Paper Bags & Packaging Products",
    "wof:placetype":"venue"
},
  "geometry": {"coordinates":[151.14520300000001,-33.894363],"type":"Point"}
}