{
  "type": "Feature",
  "properties": {
    "addr:full":"PO Box 254 Crafers SA 5152",
    "addr:postcode":"5152",
    "iso:country":"AU",
    "sg:address":"PO Box 254",
    "sg:city":"Crafers",
    "sg:classifiers":[
        {
            "category":"Building & Trades",
            "subcategory":"Cleaning & Sanitation",
            "type":"Services"
        }
    ],
    "sg:phone":"+61 8 8283 3656",
    "sg:postcode":"5152",
    "sg:province":"SA",
    "sg:tags":[
        "tank",
        "septic"
    ],
    "wof:name":"Septic Pumping Services",
    "wof:placetype":"venue"
},
  "geometry": {"coordinates":[138.70338439899999,-34.9972000122],"type":"Point"}
}