{
  "type": "Feature",
  "properties": {
    "addr:full":"Shop 5, 302- 308 Wyndham St Shepparton VIC 3630",
    "addr:housenumber":"shop 5;308",
    "addr:postcode":"302;3630",
    "addr:street":"Wyndham St",
    "iso:country":"AU",
    "sg:address":"Shop 5, 302- 308 Wyndham St",
    "sg:city":"Shepparton",
    "sg:classifiers":[
        {
            "category":"Professional",
            "subcategory":"Accounting & Tax Preparation",
            "type":"Services"
        }
    ],
    "sg:phone":"+61 3 5831 7111",
    "sg:postcode":"3630",
    "sg:province":"VIC",
    "sg:tags":[
        "accountant",
        "auditor"
    ],
    "wof:name":"Tax City",
    "wof:placetype":"venue"
},
  "geometry": {"coordinates":[145.39941406200001,-36.3798828125],"type":"Point"}
}