{
  "type": "Feature",
  "properties": {
    "iso:country":"AU",
    "sg:address":"64-66 Thuringowa Drv",
    "sg:city":"Kirwan",
    "sg:classifiers":[
        {
            "category":"Health Services",
            "subcategory":"Health Practitioner",
            "type":"Services"
        }
    ],
    "sg:phone":"+61 7 4723 1721",
    "sg:postcode":"4817",
    "sg:province":"QLD",
    "sg:tags":[
        "dietitian"
    ],
    "wof:name":"Robynn Morros Weight Loss Clinic",
    "wof:placetype":"venue"
},
  "geometry": {"coordinates":[146.730209,-19.311283],"type":"Point"}
}