{
  "type": "Feature",
  "properties": {
    "addr:full":"3 Mitchell Pl Parkinson QLD 4115",
    "addr:housenumber":"3",
    "addr:postcode":"4115",
    "addr:street":"Mitchell Pl Parkinson",
    "iso:country":"AU",
    "sg:address":"3 Mitchell Pl",
    "sg:city":"Parkinson",
    "sg:classifiers":[
        {
            "category":"Professional",
            "subcategory":"Detective & Security Services",
            "type":"Services"
        }
    ],
    "sg:phone":"+61 411 197 857",
    "sg:postcode":"4115",
    "sg:province":"QLD",
    "sg:tags":[
        "consultant",
        "system"
    ],
    "wof:name":"Select Security & Communication",
    "wof:placetype":"venue"
},
  "geometry": {"coordinates":[153.041290283,-27.6376857758],"type":"Point"}
}