{
  "type": "Feature",
  "properties": {
    "addr:full":"106 Jones Ave Moree NSW 2400",
    "addr:housenumber":"106",
    "addr:postcode":"2400",
    "addr:street":"Jones Ave",
    "iso:country":"AU",
    "sg:address":"106 Jones Ave",
    "sg:city":"Moree",
    "sg:classifiers":[
        {
            "category":"Social Services",
            "subcategory":"Adult Care",
            "type":"Services"
        }
    ],
    "sg:phone":"+61 428 449 353",
    "sg:postcode":"2400",
    "sg:province":"NSW",
    "sg:tags":[
        "towing"
    ],
    "wof:name":"Moree Heavy Towing",
    "wof:placetype":"venue"
},
  "geometry": {"coordinates":[149.83038330100001,-29.4795398712],"type":"Point"}
}