{
  "type": "Feature",
  "properties": {
    "iso:country":"AU",
    "sg:address":"Woodlawn Drv",
    "sg:city":"Budgewoi",
    "sg:classifiers":[
        {
            "category":"Personal",
            "type":"Services"
        }
    ],
    "sg:phone":"+61 2 4390 0506",
    "sg:postcode":"2262",
    "sg:province":"NSW",
    "sg:tags":[
        "wallpapering",
        "wallcovering"
    ],
    "wof:name":"Ascension Colours",
    "wof:placetype":"venue"
},
  "geometry": {"coordinates":[151.550217,-33.230507],"type":"Point"}
}