{
  "type": "Feature",
  "properties": {
    "addr:full":"22 Crawley Crt Armadale WA 6112",
    "addr:housenumber":"22",
    "addr:postcode":"6112",
    "addr:street":"Crawley Crt",
    "iso:country":"AU",
    "sg:address":"22 Crawley Crt",
    "sg:city":"Armadale",
    "sg:classifiers":[
        {
            "category":"Utilities",
            "subcategory":"Water",
            "type":"Services"
        }
    ],
    "sg:phone":"+61 414 397 026",
    "sg:postcode":"6112",
    "sg:province":"WA",
    "sg:tags":[
        "cartage"
    ],
    "wof:name":"Taylor's Water Cartage",
    "wof:placetype":"venue"
},
  "geometry": {"coordinates":[116.012550354,-32.1359443665],"type":"Point"}
}