{
  "type": "Feature",
  "properties": {
    "addr:full":"12 Lawrence Pl Maleny QLD 4552",
    "addr:housenumber":"12",
    "addr:postcode":"4552",
    "addr:street":"Lawrence Pl",
    "iso:country":"AU",
    "sg:address":"12 Lawrence Pl",
    "sg:city":"Maleny",
    "sg:classifiers":[
        {
            "category":"Personal",
            "type":"Services"
        }
    ],
    "sg:phone":"+61 1300 851 415",
    "sg:postcode":"4552",
    "sg:province":"QLD",
    "sg:tags":[
        "introduction",
        "social"
    ],
    "wof:name":"Friends Unlimited Network",
    "wof:placetype":"venue"
},
  "geometry": {"coordinates":[152.82374572800001,-26.7500667572],"type":"Point"}
}