{
  "type": "Feature",
  "properties": {
    "addr:full":"191 Church St Parramatta NSW 2150",
    "addr:housenumber":"191",
    "addr:postcode":"2150",
    "addr:street":"Church St",
    "iso:country":"AU",
    "sg:address":"191 Church St",
    "sg:city":"Parramatta",
    "sg:classifiers":[
        {
            "category":"Health Services",
            "subcategory":"Doctor",
            "type":"Services"
        }
    ],
    "sg:phone":"+61 2 9635 3966",
    "sg:postcode":"2150",
    "sg:province":"NSW",
    "sg:tags":[
        "medical",
        "practitioner"
    ],
    "wof:name":"Malouf Michael",
    "wof:placetype":"venue"
},
  "geometry": {"coordinates":[151.11875915499999,-33.8752250671],"type":"Point"}
}