{
  "type": "Feature",
  "properties": {
    "addr:full":"27 Fitzroy St St Kilda VIC 3182",
    "addr:housenumber":"27",
    "addr:postcode":"3182",
    "addr:street":"Fitzroy St",
    "iso:country":"AU",
    "sg:address":"27 Fitzroy St",
    "sg:city":"St Kilda",
    "sg:classifiers":[
        {
            "category":"Food & Beverages",
            "subcategory":"Groceries & Convenience Stores",
            "type":"Retail Goods"
        }
    ],
    "sg:phone":"+61 3 9534 4544",
    "sg:postcode":"3182",
    "sg:province":"VIC",
    "wof:name":"Andoniou H",
    "wof:placetype":"venue"
},
  "geometry": {"coordinates":[144.9737854,-37.8620567322],"type":"Point"}
}