{
  "type": "Feature",
  "properties": {
    "addr:full":"11 Ladybird St Kallangur QLD 4503",
    "addr:housenumber":"11",
    "addr:postcode":"4503",
    "addr:street":"Ladybird St",
    "iso:country":"AU",
    "sg:address":"11 Ladybird St",
    "sg:city":"Kallangur",
    "sg:classifiers":[
        {
            "category":"Building & Trades",
            "subcategory":"Construction",
            "type":"Services"
        }
    ],
    "sg:phone":"+61 417 743 840",
    "sg:postcode":"4503",
    "sg:province":"QLD",
    "sg:tags":[
        "earth",
        "excavating",
        "moving",
        "contractor"
    ],
    "wof:name":"Colledge Plant Hire",
    "wof:placetype":"venue"
},
  "geometry": {"coordinates":[152.995925903,-27.2467689514],"type":"Point"}
}