{
  "type": "Feature",
  "properties": {
    "iso:country":"AU",
    "sg:address":"29a Maxweld St",
    "sg:city":"Ardeer",
    "sg:classifiers":[
        {
            "category":"Fast Food",
            "type":"Food & Drink"
        }
    ],
    "sg:phone":"+61 3 8361 7300",
    "sg:postcode":"3022",
    "sg:province":"VIC",
    "sg:tags":[
        "away",
        "take"
    ],
    "wof:name":"Tina's Fish Chip & Pizza Shop",
    "wof:placetype":"venue"
},
  "geometry": {"coordinates":[144.80375699999999,-37.780407],"type":"Point"}
}