{
  "type": "Feature",
  "properties": {
    "addr:full":"33 Northam St Glen Waverley VIC 3150",
    "addr:housenumber":"33",
    "addr:postcode":"3150",
    "addr:street":"Northam St",
    "iso:country":"AU",
    "sg:address":"33 Northam St",
    "sg:city":"Glen Waverley",
    "sg:classifiers":[
        {
            "category":"Health Services",
            "subcategory":"Doctor",
            "type":"Services"
        }
    ],
    "sg:phone":"+61 3 9561 9172",
    "sg:postcode":"3150",
    "sg:province":"VIC",
    "sg:tags":[
        "occupational",
        "safety"
    ],
    "wof:name":"Pam Pryor & Associates Pty Ltd",
    "wof:placetype":"venue"
},
  "geometry": {"coordinates":[145.19032287600001,-37.8915710449],"type":"Point"}
}