{
  "type": "Feature",
  "properties": {
    "addr:full":"98 Fulcher Rd Red Hill QLD 4059",
    "addr:housenumber":"98",
    "addr:postcode":"4059",
    "addr:street":"Fulcher Rd",
    "iso:country":"AU",
    "sg:address":"98 Fulcher Rd",
    "sg:city":"Red Hill",
    "sg:classifiers":[
        {
            "category":"Travel",
            "subcategory":"Travel Agent",
            "type":"Entertainment"
        }
    ],
    "sg:phone":"+61 7 3511 6466",
    "sg:postcode":"4059",
    "sg:province":"QLD",
    "sg:tags":[
        "consultant"
    ],
    "wof:name":"Gullivers Corporate Connections",
    "wof:placetype":"venue"
},
  "geometry": {"coordinates":[152.99609375,-27.4480857849],"type":"Point"}
}