{
  "type": "Feature",
  "properties": {
    "addr:full":"17 Sunderland St Moonah TAS 7009",
    "addr:housenumber":"17",
    "addr:postcode":"7009",
    "addr:street":"Sunderland St",
    "iso:country":"AU",
    "sg:address":"17 Sunderland St",
    "sg:city":"Moonah",
    "sg:classifiers":[
        {
            "category":"Retail",
            "subcategory":"Auto Repair",
            "type":"Services"
        }
    ],
    "sg:phone":"+61 3 6272 1614",
    "sg:postcode":"7009",
    "sg:province":"TAS",
    "sg:tags":[
        "repairer",
        "motor",
        "engineer"
    ],
    "wof:name":"A V McGuinness",
    "wof:placetype":"venue"
},
  "geometry": {"coordinates":[147.29496765100001,-42.8412246704],"type":"Point"}
}