{
  "type": "Feature",
  "properties": {
    "addr:full":"Shop 506 a & b Carousel Centre Bondi NSW 2026",
    "addr:housenumber":"506 a &",
    "addr:postcode":"2026",
    "iso:country":"AU",
    "sg:address":"Shop 506",
    "sg:city":"a & b Carousel Centre Bondi",
    "sg:classifiers":[
        {
            "category":"Shopping",
            "subcategory":"Clothing, Apparel, & Fashions",
            "type":"Retail Goods"
        }
    ],
    "sg:phone":"+61 2 9389 2723",
    "sg:postcode":"2026",
    "sg:province":"NSW",
    "sg:tags":[
        "lady",
        "wear"
    ],
    "wof:name":"Country Road Clothing Pty Ltd",
    "wof:placetype":"venue"
},
  "geometry": {"coordinates":[151.27041625999999,-33.8949127197],"type":"Point"}
}