{
  "type": "Feature",
  "properties": {
    "addr:full":"17- 19 Wharf St Logan Village QLD 4207",
    "addr:housenumber":"19",
    "addr:postcode":"4207",
    "addr:street":"Wharf St",
    "iso:country":"AU",
    "sg:address":"17- 19 Wharf St",
    "sg:city":"Logan Village",
    "sg:classifiers":[
        {
            "category":"Health Services",
            "subcategory":"Doctor",
            "type":"Services"
        }
    ],
    "sg:phone":"+61 7 5546 3955",
    "sg:postcode":"4207",
    "sg:province":"QLD",
    "sg:tags":[
        "medical",
        "practitioner"
    ],
    "wof:name":"Sabdia S",
    "wof:placetype":"venue"
},
  "geometry": {"coordinates":[153.105667114,-27.7671794891],"type":"Point"}
}