{
  "type": "Feature",
  "properties": {
    "addr:full":"Unit 2/ 4 Centre Pl Wetherill Park NSW 2164",
    "addr:housenumber":"4",
    "addr:postcode":"2164",
    "addr:street":"Centre Pl",
    "iso:country":"AU",
    "sg:address":"Unit 2/ 4 Centre Pl",
    "sg:city":"Wetherill Park",
    "sg:classifiers":[
        {
            "category":"Professional",
            "subcategory":"Computer Services",
            "type":"Services"
        }
    ],
    "sg:phone":"+61 2 9725 4611",
    "sg:postcode":"2164",
    "sg:province":"NSW",
    "sg:tags":[
        "consultant",
        "system"
    ],
    "wof:name":"I.T Wise Computers & Consultants",
    "wof:placetype":"venue"
},
  "geometry": {"coordinates":[150.901901245,-33.8437614441],"type":"Point"}
}