{
  "type": "Feature",
  "properties": {
    "addr:full":"940 Old Northern Rd Glenorie NSW 2157",
    "addr:housenumber":"940",
    "addr:postcode":"2157",
    "addr:street":"Old Northern Rd",
    "iso:country":"AU",
    "sg:address":"940 Old Northern Rd",
    "sg:city":"Glenorie",
    "sg:classifiers":[
        {
            "category":"Food & Beverages",
            "subcategory":"Liquor & Beverages",
            "type":"Retail Goods"
        }
    ],
    "sg:phone":"+61 2 9652 1420",
    "sg:postcode":"2157",
    "sg:province":"NSW",
    "sg:tags":[
        "store"
    ],
    "wof:name":"Glenorie Cellars",
    "wof:placetype":"venue"
},
  "geometry": {"coordinates":[151.00758361800001,-33.601436615],"type":"Point"}
}