{
  "type": "Feature",
  "properties": {
    "addr:full":"228 Dorset Rd Boronia VIC 3155",
    "addr:housenumber":"228",
    "addr:postcode":"3155",
    "addr:street":"Dorset Rd",
    "iso:country":"AU",
    "sg:address":"228 Dorset Rd",
    "sg:city":"Boronia",
    "sg:classifiers":[
        {
            "category":"Retail",
            "subcategory":"Storage",
            "type":"Services"
        }
    ],
    "sg:phone":"+61 3 9762 6111",
    "sg:postcode":"3155",
    "sg:province":"VIC",
    "sg:tags":[
        "removal",
        "furniture"
    ],
    "wof:name":"Acme Removals",
    "wof:placetype":"venue"
},
  "geometry": {"coordinates":[145.285812378,-37.8614654541],"type":"Point"}
}