{
  "type": "Feature",
  "properties": {
    "addr:full":"16 Foam St Tuross Head NSW 2537",
    "addr:housenumber":"16",
    "addr:postcode":"2537",
    "addr:street":"Foam St",
    "iso:country":"AU",
    "sg:address":"16 Foam St",
    "sg:city":"Tuross Head",
    "sg:classifiers":[
        {
            "category":"Home & Garden",
            "subcategory":"Carpets & Floor Coverings",
            "type":"Retail Goods"
        }
    ],
    "sg:phone":"+61 2 4473 6175",
    "sg:postcode":"2537",
    "sg:province":"NSW",
    "sg:tags":[
        "layer"
    ],
    "wof:name":"Carey P A & P E",
    "wof:placetype":"venue"
},
  "geometry": {"coordinates":[150.12495422399999,-36.0439186096],"type":"Point"}
}