{
  "type": "Feature",
  "properties": {
    "addr:full":"19 Station St Kogarah NSW 2217",
    "addr:housenumber":"19",
    "addr:postcode":"2217",
    "addr:street":"Station St",
    "iso:country":"AU",
    "sg:address":"19 Station St",
    "sg:city":"Kogarah",
    "sg:classifiers":[
        {
            "category":"Real Estate",
            "subcategory":"Real Estate Agent",
            "type":"Services"
        }
    ],
    "sg:phone":"+61 2 9588 4455",
    "sg:postcode":"2217",
    "sg:province":"NSW",
    "wof:name":"L.J. Hooker",
    "wof:placetype":"venue"
},
  "geometry": {"coordinates":[151.13192699999999,-33.962353],"type":"Point"}
}