{
  "type": "Feature",
  "properties": {
    "addr:full":"1419 Mt Alfred Rd Moogerah QLD 4309",
    "addr:housenumber":"1419",
    "addr:postcode":"4309",
    "addr:street":"Mt Alfred Rd",
    "iso:country":"AU",
    "sg:address":"1419 Mt Alfred Rd",
    "sg:city":"Moogerah",
    "sg:classifiers":[
        {
            "category":"Education",
            "subcategory":"Special Training",
            "type":"Public Place"
        }
    ],
    "sg:phone":"+61 7 5463 5677",
    "sg:postcode":"4309",
    "sg:province":"QLD",
    "sg:tags":[
        "tuition-educational"
    ],
    "wof:name":"Quantum Literacy",
    "wof:placetype":"venue"
},
  "geometry": {"coordinates":[152.57090759299999,-28.0729198456],"type":"Point"}
}