{
  "type": "Feature",
  "properties": {
    "iso:country":"AU",
    "sg:address":"78 Yaringa Rd",
    "sg:city":"Castle Hill",
    "sg:classifiers":[
        {
            "category":"Professional",
            "subcategory":"Computer Services",
            "type":"Services"
        }
    ],
    "sg:phone":"+61 418 425 494",
    "sg:postcode":"2154",
    "sg:province":"NSW",
    "sg:tags":[
        "consultant",
        "system"
    ],
    "wof:name":"Positive Complete Concepts Pty Ltd",
    "wof:placetype":"venue"
},
  "geometry": {"coordinates":[151.00624084500001,-33.7182159424],"type":"Point"}
}