{
  "type": "Feature",
  "properties": {
    "addr:full":"62 Murray Rd Preston East VIC 3072",
    "addr:housenumber":"62",
    "addr:postcode":"3072",
    "addr:street":"Murray Rd",
    "iso:country":"AU",
    "sg:address":"62 Murray Rd",
    "sg:city":"Preston East",
    "sg:classifiers":[
        {
            "category":"Education",
            "subcategory":"School",
            "type":"Public Place"
        }
    ],
    "sg:phone":"+61 3 9478 1333",
    "sg:postcode":"3072",
    "sg:province":"VIC",
    "sg:tags":[
        "state",
        "except",
        "nsw"
    ],
    "wof:name":"Northland Secondary College",
    "wof:placetype":"venue"
},
  "geometry": {"coordinates":[145.02532959000001,-37.7401924133],"type":"Point"}
}