{
  "type": "Feature",
  "properties": {
    "iso:country":"AU",
    "sg:address":"29 Enterprise Ave",
    "sg:city":"Padstow",
    "sg:classifiers":[
        {
            "category":"Manufacturing",
            "subcategory":"Tools & Machinery",
            "type":"Manufacturing & Wholesale Goods"
        }
    ],
    "sg:phone":"+61 2 9771 2236",
    "sg:postcode":"2211",
    "sg:province":"NSW",
    "sg:tags":[
        "toolmaker"
    ],
    "wof:name":"E.P.C. Engineering Pty Ltd",
    "wof:placetype":"venue"
},
  "geometry": {"coordinates":[151.032623,-33.944382],"type":"Point"}
}