{
  "type": "Feature",
  "properties": {
    "addr:full":"Shop 40, Engadine Court, Caldarra Ave Engadine NSW 2233",
    "addr:housenumber":"shop 40",
    "addr:postcode":"2233",
    "addr:street":"Engadine Court Caldarra Ave",
    "iso:country":"AU",
    "sg:address":"Shop 40, Engadine Court, Caldarra Ave",
    "sg:city":"Engadine",
    "sg:classifiers":[
        {
            "category":"Professional",
            "subcategory":"Art Services",
            "type":"Services"
        }
    ],
    "sg:phone":"+61 2 9520 3078",
    "sg:postcode":"2233",
    "sg:province":"NSW",
    "sg:tags":[
        "artist"
    ],
    "wof:name":"Hutchings Daniel",
    "wof:placetype":"venue"
},
  "geometry": {"coordinates":[151.014434814,-34.0660438538],"type":"Point"}
}