{
  "type": "Feature",
  "properties": {
    "addr:full":"89 Golden Valley Hwy Shepparton VIC 3630",
    "addr:housenumber":"89",
    "addr:postcode":"3630",
    "addr:street":"Golden Valley Hwy",
    "iso:country":"AU",
    "sg:address":"89 Golden Valley Hwy",
    "sg:city":"Shepparton",
    "sg:classifiers":[
        {
            "category":"Building & Trades",
            "subcategory":"Construction",
            "type":"Services"
        }
    ],
    "sg:phone":"+61 3 5823 5539",
    "sg:postcode":"3630",
    "sg:province":"VIC",
    "sg:tags":[
        "contractor"
    ],
    "wof:name":"Australian Lifestyle Homes Pty Ltd",
    "wof:placetype":"venue"
},
  "geometry": {"coordinates":[145.38880920400001,-36.4690895081],"type":"Point"}
}