{
  "type": "Feature",
  "properties": {
    "iso:country":"AU",
    "sg:address":"84 Patton St",
    "sg:city":"Broken Hill",
    "sg:classifiers":[
        {
            "category":"Autos & Motor Vehicles",
            "subcategory":"Fuel & Gas Station",
            "type":"Retail Goods"
        }
    ],
    "sg:phone":"+61 8 8087 3653",
    "sg:postcode":"2880",
    "sg:province":"NSW",
    "wof:name":"Mobil Oil Australia Pty Ltd",
    "wof:placetype":"venue"
},
  "geometry": {"coordinates":[141.45877075199999,-31.9814739227],"type":"Point"}
}