{
  "type": "Feature",
  "properties": {
    "addr:full":"PO Box 454 Parkes NSW 2870",
    "addr:postcode":"2870",
    "iso:country":"AU",
    "sg:address":"PO Box 454",
    "sg:city":"Parkes",
    "sg:classifiers":[
        {
            "category":"Professional",
            "type":"Services"
        }
    ],
    "sg:phone":"+61 412 210 344",
    "sg:postcode":"2870",
    "sg:province":"NSW",
    "sg:tags":[
        "control",
        "equipment",
        "traffic"
    ],
    "wof:name":"Steve McGraths Tree Service",
    "wof:placetype":"venue"
},
  "geometry": {"coordinates":[148.17460600000001,-33.136871],"type":"Point"}
}