{
  "type": "Feature",
  "properties": {
    "addr:full":"12 Marril St Queanbeyan ACT 2620",
    "addr:housenumber":"12",
    "addr:postcode":"2620",
    "addr:street":"Marril St",
    "iso:country":"AU",
    "sg:address":"12 Marril St",
    "sg:city":"Queanbeyan",
    "sg:classifiers":[
        {
            "category":"Building & Trades",
            "subcategory":"Construction",
            "type":"Services"
        }
    ],
    "sg:phone":"+61 422 279 007",
    "sg:postcode":"2620",
    "sg:province":"ACT",
    "sg:tags":[
        "joinery"
    ],
    "wof:name":"V.B Joinery Services",
    "wof:placetype":"venue"
},
  "geometry": {"coordinates":[149.201934814,-35.3639602661],"type":"Point"}
}