{
  "type": "Feature",
  "properties": {
    "addr:full":"270 Lt Collins St Melbourne VIC 3000",
    "addr:housenumber":"270",
    "addr:postcode":"3000",
    "addr:street":"Lt Collins St",
    "iso:country":"AU",
    "sg:address":"270 Lt Collins St",
    "sg:city":"Melbourne",
    "sg:classifiers":[
        {
            "category":"Shopping",
            "subcategory":"Clothing, Apparel, & Fashions",
            "type":"Retail Goods"
        }
    ],
    "sg:phone":"+61 3 9654 1288",
    "sg:postcode":"3000",
    "sg:province":"VIC",
    "sg:tags":[
        "menswear"
    ],
    "wof:name":"High & Mighty Big & Tall Menswear",
    "wof:placetype":"venue"
},
  "geometry": {"coordinates":[144.970611572,-37.8142967224],"type":"Point"}
}