{
  "type": "Feature",
  "properties": {
    "addr:full":"Shop 1/ 181 Southwell Crs Hamilton Hill WA 6163",
    "addr:housenumber":"shop 1 / 181",
    "addr:postcode":"6163",
    "addr:street":"Southwell Crs",
    "iso:country":"AU",
    "sg:address":"Shop 1/ 181 Southwell Crs",
    "sg:city":"Hamilton Hill",
    "sg:classifiers":[
        {
            "category":"Food & Beverages",
            "subcategory":"Supermarket",
            "type":"Retail Goods"
        }
    ],
    "sg:phone":"+61 8 9418 6104",
    "sg:postcode":"6163",
    "sg:province":"WA",
    "sg:tags":[
        "grocery",
        "store"
    ],
    "wof:name":"Eziway Food Stores",
    "wof:placetype":"venue"
},
  "geometry": {"coordinates":[115.77831999999999,-32.080891],"type":"Point"}
}