{
  "type": "Feature",
  "properties": {
    "iso:country":"AU",
    "sg:address":"7A Gibbes St",
    "sg:city":"Chatswood",
    "sg:classifiers":[
        {
            "category":"Professional",
            "subcategory":"Computer Services",
            "type":"Services"
        }
    ],
    "sg:phone":"+61 2 9417 0635",
    "sg:postcode":"2067",
    "sg:province":"NSW",
    "sg:tags":[
        "package",
        "software"
    ],
    "wof:name":"QED Australia",
    "wof:placetype":"venue"
},
  "geometry": {"coordinates":[151.20054626500001,-33.7901420593],"type":"Point"}
}