{
  "type": "Feature",
  "properties": {
    "iso:country":"AU",
    "sg:address":"Cnr Darling St & Birchgrove Rd",
    "sg:city":"Balmain",
    "sg:classifiers":[
        {
            "category":"Travel",
            "subcategory":"Hotels & Motels",
            "type":"Entertainment"
        }
    ],
    "sg:phone":"+61 2 9810 3700",
    "sg:postcode":"2041",
    "sg:province":"NSW",
    "sg:tags":[
        "accommodation"
    ],
    "wof:name":"Balmain Lodge",
    "wof:placetype":"venue"
},
  "geometry": {"coordinates":[151.17585800000001,-33.855991],"type":"Point"}
}