{
  "type": "Feature",
  "properties": {
    "addr:full":"24 Boulder Rd Malaga WA 6090",
    "addr:housenumber":"24",
    "addr:postcode":"6090",
    "addr:street":"Boulder Rd",
    "iso:country":"AU",
    "sg:address":"24 Boulder Rd",
    "sg:city":"Malaga",
    "sg:classifiers":[
        {
            "category":"Retail",
            "subcategory":"Auto Repair",
            "type":"Services"
        }
    ],
    "sg:phone":"+61 8 9209 1661",
    "sg:postcode":"6090",
    "sg:province":"WA",
    "sg:tags":[
        "beater",
        "painter",
        "panel"
    ],
    "wof:name":"Fletchers Malaga Smash Repairs",
    "wof:placetype":"venue"
},
  "geometry": {"coordinates":[115.902770996,-31.8649253845],"type":"Point"}
}