{
  "type": "Feature",
  "properties": {
    "addr:full":"46 King St Inglewood QLD 4387",
    "addr:housenumber":"46",
    "addr:postcode":"4387",
    "addr:street":"King St",
    "iso:country":"AU",
    "sg:address":"46 King St",
    "sg:city":"Inglewood",
    "sg:classifiers":[
        {
            "category":"Manufacturing",
            "subcategory":"Lumber",
            "type":"Manufacturing & Wholesale Goods"
        }
    ],
    "sg:phone":"+61 7 4652 1335",
    "sg:postcode":"4387",
    "sg:province":"QLD",
    "sg:tags":[
        "sawmillers"
    ],
    "wof:name":"Bretts Inglewood Sawmilling Pty Ltd",
    "wof:placetype":"venue"
},
  "geometry": {"coordinates":[151.07681299999999,-28.421043],"type":"Point"}
}