{
  "type": "Feature",
  "properties": {
    "addr:full":"1/ 50 Bolton St Newcastle NSW 2300",
    "addr:housenumber":"/ 50",
    "addr:postcode":"2300",
    "addr:street":"Bolton St",
    "iso:country":"AU",
    "sg:address":"1/ 50 Bolton St",
    "sg:city":"Newcastle",
    "sg:classifiers":[
        {
            "category":"Health Services",
            "subcategory":"Doctor",
            "type":"Services"
        }
    ],
    "sg:phone":"+61 2 4926 2966",
    "sg:postcode":"2300",
    "sg:province":"NSW",
    "sg:tags":[
        "medical",
        "practitioner"
    ],
    "wof:name":"Hunter Vein Clinic",
    "wof:placetype":"venue"
},
  "geometry": {"coordinates":[151.78244000000001,-32.929279],"type":"Point"}
}