{
  "type": "Feature",
  "properties": {
    "addr:full":"88 Sydney St Riverstone NSW 2765",
    "addr:housenumber":"88",
    "addr:postcode":"2765",
    "addr:street":"Sydney St",
    "iso:country":"AU",
    "sg:address":"88 Sydney St",
    "sg:city":"Riverstone",
    "sg:classifiers":[
        {
            "category":"Shopping",
            "type":"Retail Goods"
        }
    ],
    "sg:phone":"+61 434 676 231",
    "sg:postcode":"2765",
    "sg:province":"NSW",
    "sg:tags":[
        "equipment",
        "safety",
        "accessory"
    ],
    "wof:name":"Australian Anchor Access",
    "wof:placetype":"venue"
},
  "geometry": {"coordinates":[150.86439514200001,-33.6675491333],"type":"Point"}
}