{
  "type": "Feature",
  "properties": {
    "addr:full":"4 Allen St Hurstville South NSW 2221",
    "addr:housenumber":"4",
    "addr:postcode":"2221",
    "addr:street":"Allen St",
    "iso:country":"AU",
    "sg:address":"4 Allen St",
    "sg:city":"Hurstville South",
    "sg:classifiers":[
        {
            "category":"Education",
            "subcategory":"Kindergarten",
            "type":"Public Place"
        }
    ],
    "sg:phone":"+61 2 9546 4927",
    "sg:postcode":"2221",
    "sg:province":"NSW",
    "sg:tags":[
        "pre-schools"
    ],
    "wof:name":"Camelot Kindergarten",
    "wof:placetype":"venue"
},
  "geometry": {"coordinates":[151.10589599599999,-33.9774589539],"type":"Point"}
}