{
  "type": "Feature",
  "properties": {
    "addr:full":"504 A Victoria Rd Ryde NSW 2112",
    "addr:housenumber":"504 a",
    "addr:postcode":"2112",
    "addr:street":"Victoria Rd",
    "iso:country":"AU",
    "sg:address":"504 A Victoria Rd",
    "sg:city":"Ryde",
    "sg:classifiers":[
        {
            "category":"Personal",
            "subcategory":"Day Spa",
            "type":"Services"
        }
    ],
    "sg:phone":"+61 2 9334 0050",
    "sg:postcode":"2112",
    "sg:province":"NSW",
    "wof:name":"Regeneration Health Spa",
    "wof:placetype":"venue"
},
  "geometry": {"coordinates":[151.11097717300001,-33.8165283203],"type":"Point"}
}