{
  "type": "Feature",
  "properties": {
    "iso:country":"AU",
    "sg:address":"54 Hursley Rd",
    "sg:city":"Toowoomba",
    "sg:classifiers":[
        {
            "category":"Travel",
            "subcategory":"Hotels & Motels",
            "type":"Entertainment"
        }
    ],
    "sg:phone":"+61 7 4659 2000",
    "sg:postcode":"4350",
    "sg:province":"QLD",
    "sg:website":"http://www.cliffordparkmotorinn.com.au",
    "wof:name":"Clifford Park Holiday Motor Inn",
    "wof:placetype":"venue"
},
  "geometry": {"coordinates":[151.883408,-27.551971],"type":"Point"}
}