{
  "type": "Feature",
  "properties": {
    "addr:full":"240 Hampstead Rd Clearview SA 5085",
    "addr:housenumber":"240",
    "addr:postcode":"5085",
    "addr:street":"Hampstead Rd",
    "iso:country":"AU",
    "sg:address":"240 Hampstead Rd",
    "sg:city":"Clearview",
    "sg:classifiers":[
        {
            "category":"Real Estate",
            "subcategory":"Real Estate Agent",
            "type":"Services"
        }
    ],
    "sg:phone":"+61 8 8359 1911",
    "sg:postcode":"5085",
    "sg:province":"SA",
    "wof:name":"Hooker L.J. Clearview",
    "wof:placetype":"venue"
},
  "geometry": {"coordinates":[138.61819457999999,-34.8557319641],"type":"Point"}
}