{
  "type": "Feature",
  "properties": {
    "addr:full":"Church St Ryde NSW 2112",
    "addr:postcode":"2112",
    "addr:street":"Church St",
    "iso:country":"AU",
    "sg:address":"Church St",
    "sg:city":"Ryde",
    "sg:classifiers":[
        {
            "category":"Education",
            "subcategory":"Music School",
            "type":"Public Place"
        }
    ],
    "sg:phone":"+61 2 9453 9484",
    "sg:postcode":"2112",
    "sg:province":"NSW",
    "sg:tags":[
        "teacher"
    ],
    "wof:name":"International School Of Music",
    "wof:placetype":"venue"
},
  "geometry": {"coordinates":[151.10533142099999,-33.8141860962],"type":"Point"}
}