{
  "type": "Feature",
  "properties": {
    "addr:full":"237 Burnley St Richmond VIC 3121",
    "addr:housenumber":"237",
    "addr:postcode":"3121",
    "addr:street":"Burnley St",
    "iso:country":"AU",
    "sg:address":"237 Burnley St",
    "sg:city":"Richmond",
    "sg:classifiers":[
        {
            "category":"Cafe",
            "type":"Food & Drink"
        }
    ],
    "sg:phone":"+61 3 9428 7592",
    "sg:postcode":"3121",
    "sg:province":"VIC",
    "wof:name":"Serenity Cafe",
    "wof:placetype":"venue"
},
  "geometry": {"coordinates":[145.008056641,-37.8216667175],"type":"Point"}
}