{
  "type": "Feature",
  "properties": {
    "addr:full":"Bronberg Plaza, Slatyer Ave Benowa QLD 4217",
    "addr:postcode":"4217",
    "addr:street":"Bronberg;Slatyer Ave",
    "iso:country":"AU",
    "sg:address":"Bronberg Plaza, Slatyer Ave",
    "sg:city":"Benowa",
    "sg:classifiers":[
        {
            "category":"Food & Beverages",
            "subcategory":"Specialty",
            "type":"Retail Goods"
        }
    ],
    "sg:phone":"+61 7 5597 4900",
    "sg:postcode":"4217",
    "sg:province":"QLD",
    "sg:tags":[
        "product",
        "health"
    ],
    "wof:name":"Mrs Flannerys Natural Grocers",
    "wof:placetype":"venue"
},
  "geometry": {"coordinates":[153.40025329599999,-27.9965572357],"type":"Point"}
}