{
  "type": "Feature",
  "properties": {
    "addr:full":"Rubbish Dump Rd Cummins SA 5631",
    "addr:postcode":"5631",
    "addr:street":"Dump Rd",
    "iso:country":"AU",
    "sg:address":"Rubbish Dump Rd",
    "sg:city":"Cummins",
    "sg:classifiers":[
        {
            "category":"Wholesale",
            "subcategory":"Plants",
            "type":"Manufacturing & Wholesale Goods"
        }
    ],
    "sg:phone":"+61 8 8676 2112",
    "sg:postcode":"5631",
    "sg:province":"SA",
    "sg:tags":[
        "florist"
    ],
    "wof:name":"Coolangatta Cut Flowers",
    "wof:placetype":"venue"
},
  "geometry": {"coordinates":[135.73020935100001,-34.2616500854],"type":"Point"}
}