{
  "type": "Feature",
  "properties": {
    "iso:country":"AU",
    "sg:address":"101 Victory Rd",
    "sg:city":"Airport West",
    "sg:classifiers":[
        {
            "category":"Education",
            "subcategory":"Special Training",
            "type":"Public Place"
        }
    ],
    "sg:phone":"+61 3 9338 1697",
    "sg:postcode":"3042",
    "sg:province":"VIC",
    "sg:tags":[
        "drama",
        "speech",
        "speaking",
        "tuition"
    ],
    "wof:name":"Victory Learning Studio",
    "wof:placetype":"venue"
},
  "geometry": {"coordinates":[144.88269043,-37.7178382874],"type":"Point"}
}