{
  "type": "Feature",
  "properties": {
    "iso:country":"AU",
    "sg:address":"159 St John St",
    "sg:city":"Launceston",
    "sg:classifiers":[
        {
            "category":"Health Services",
            "subcategory":"Doctor",
            "type":"Services"
        }
    ],
    "sg:phone":"+61 3 6334 3636",
    "sg:postcode":"7250",
    "sg:province":"TAS",
    "sg:tags":[
        "medical",
        "practitioner"
    ],
    "wof:name":"Roberts J R, Beamish M R, Clark D R",
    "wof:placetype":"venue"
},
  "geometry": {"coordinates":[147.141815186,-41.4409217834],"type":"Point"}
}