{
  "type": "Feature",
  "properties": {
    "addr:full":"12 Apollo St Warriewood NSW 2102",
    "addr:housenumber":"12",
    "addr:postcode":"2102",
    "addr:street":"Apollo St",
    "iso:country":"AU",
    "sg:address":"12 Apollo St",
    "sg:city":"Warriewood",
    "sg:classifiers":[
        {
            "category":"Manufacturing",
            "subcategory":"Rubber & Plastics",
            "type":"Manufacturing & Wholesale Goods"
        }
    ],
    "sg:phone":"+61 2 9997 7622",
    "sg:postcode":"2102",
    "sg:province":"NSW",
    "sg:tags":[
        "moulders"
    ],
    "wof:name":"Bev-Cap Pty Ltd",
    "wof:placetype":"venue"
},
  "geometry": {"coordinates":[151.29029800000001,-33.679539],"type":"Point"}
}