{
  "type": "Feature",
  "properties": {
    "iso:country":"AU",
    "sg:address":"Level 1/ 15 Foster St",
    "sg:city":"Surry Hills",
    "sg:classifiers":[
        {
            "category":"Organizations",
            "subcategory":"Professional Association",
            "type":"Services"
        }
    ],
    "sg:phone":"+61 2 9280 4233",
    "sg:postcode":"2010",
    "sg:province":"NSW",
    "sg:tags":[
        "web",
        "internet"
    ],
    "wof:name":"Frost Design",
    "wof:placetype":"venue"
},
  "geometry": {"coordinates":[151.210327148,-33.8798904419],"type":"Point"}
}