{
  "type": "Feature",
  "properties": {
    "iso:country":"AU",
    "sg:address":"77 Adelaide St",
    "sg:city":"Maryborough",
    "sg:classifiers":[
        {
            "category":"Wholesale",
            "subcategory":"Painting Supplies",
            "type":"Manufacturing & Wholesale Goods"
        }
    ],
    "sg:phone":"+61 7 4121 6192",
    "sg:postcode":"4650",
    "sg:province":"QLD",
    "sg:tags":[
        "painter"
    ],
    "wof:name":"Maryborough Paint Centre",
    "wof:placetype":"venue"
},
  "geometry": {"coordinates":[152.700378,-25.540297],"type":"Point"}
}