{
  "type": "Feature",
  "properties": {
    "addr:full":"Flr 2/ 175 Marrickville Rd Marrickville NSW 2204",
    "addr:housenumber":"/ 175",
    "addr:postcode":"2204",
    "addr:street":"Marrickville Rd",
    "iso:country":"AU",
    "sg:address":"Flr 2/ 175 Marrickville Rd",
    "sg:city":"Marrickville",
    "sg:classifiers":[
        {
            "category":"Arts & Performance",
            "subcategory":"Art Gallery",
            "type":"Entertainment"
        }
    ],
    "sg:phone":"+61 2 9560 3470",
    "sg:postcode":"2204",
    "sg:province":"NSW",
    "wof:name":"Sydney Non Objective Group",
    "wof:placetype":"venue"
},
  "geometry": {"coordinates":[151.15860000000001,-33.911427],"type":"Point"}
}