{
  "type": "Feature",
  "properties": {
    "iso:country":"AU",
    "sg:address":"9 Wattle St",
    "sg:city":"Rydalmere",
    "sg:classifiers":[
        {
            "category":"Professional",
            "subcategory":"Art Services",
            "type":"Services"
        }
    ],
    "sg:phone":"+61 2 9613 7561",
    "sg:postcode":"2116",
    "sg:province":"NSW",
    "sg:tags":[
        "interior",
        "decorator"
    ],
    "wof:name":"Wilton Interior Vision",
    "wof:placetype":"venue"
},
  "geometry": {"coordinates":[151.093917847,-33.8069610596],"type":"Point"}
}