{
  "type": "Feature",
  "properties": {
    "addr:full":"156 Gladstone St Fyshwick ACT 2609",
    "addr:housenumber":"156",
    "addr:postcode":"2609",
    "addr:street":"Gladstone St",
    "iso:country":"AU",
    "sg:address":"156 Gladstone St",
    "sg:city":"Fyshwick",
    "sg:classifiers":[
        {
            "category":"Manufacturing",
            "subcategory":"Metals",
            "type":"Manufacturing & Wholesale Goods"
        }
    ],
    "sg:phone":"+61 2 6280 7833",
    "sg:postcode":"2609",
    "sg:province":"ACT",
    "sg:tags":[
        "wholesaler",
        "aluminium",
        "mfrs"
    ],
    "sg:website":"http://www.capral.com.au",
    "wof:name":"Capral Aluminium",
    "wof:placetype":"venue"
},
  "geometry": {"coordinates":[149.184814453,-35.3270454407],"type":"Point"}
}