{
  "type": "Feature",
  "properties": {
    "addr:full":"246 Argyle St Hobart TAS 7001",
    "addr:housenumber":"246",
    "addr:postcode":"7001",
    "addr:street":"Argyle St",
    "iso:country":"AU",
    "sg:address":"246 Argyle St",
    "sg:city":"Hobart",
    "sg:classifiers":[
        {
            "category":"Shopping",
            "type":"Retail Goods"
        }
    ],
    "sg:phone":"+61 3 6234 9088",
    "sg:postcode":"7001",
    "sg:province":"TAS",
    "sg:tags":[
        "product",
        "plastic"
    ],
    "wof:name":"Statewide Skylights",
    "wof:placetype":"venue"
},
  "geometry": {"coordinates":[147.32063293499999,-42.8747215271],"type":"Point"}
}