{
  "type": "Feature",
  "properties": {
    "iso:country":"AU",
    "sg:address":"Shop 2/ 21",
    "sg:city":"Eli Waters Shopping Vlge Eli Waters",
    "sg:classifiers":[
        {
            "category":"Communications",
            "subcategory":"Film & Video Production",
            "type":"Services"
        }
    ],
    "sg:phone":"+61 7 4194 1451",
    "sg:postcode":"4655",
    "sg:province":"QLD",
    "sg:tags":[
        "dvd",
        "library"
    ],
    "wof:name":"Network Video Eli Waters",
    "wof:placetype":"venue"
},
  "geometry": {"coordinates":[152.81457499999999,-25.288879],"type":"Point"}
}