{
  "type": "Feature",
  "properties": {
    "iso:country":"AU",
    "sg:address":"19- 21",
    "sg:city":"Traders Way Mt Isa",
    "sg:classifiers":[
        {
            "category":"Building & Trades",
            "subcategory":"Construction",
            "type":"Services"
        }
    ],
    "sg:phone":"+61 7 4743 3262",
    "sg:postcode":"4825",
    "sg:province":"QLD",
    "sg:tags":[
        "welding"
    ],
    "wof:name":"Primary Welders",
    "wof:placetype":"venue"
},
  "geometry": {"coordinates":[139.50309799999999,-20.704348],"type":"Point"}
}