{
  "type": "Feature",
  "properties": {
    "addr:full":"Shop 2 Commercial Cntr Adelaide Airport SA 5950",
    "addr:housenumber":"shop 2",
    "addr:postcode":"5950",
    "addr:street":"Commercial Cntr",
    "iso:country":"AU",
    "sg:address":"Shop 2 Commercial Cntr",
    "sg:city":"Adelaide Airport",
    "sg:classifiers":[
        {
            "category":"Government",
            "subcategory":"Post Office",
            "type":"Public Place"
        }
    ],
    "sg:phone":"+61 8 8234 4022",
    "sg:postcode":"5950",
    "sg:province":"SA",
    "sg:tags":[
        "postal"
    ],
    "wof:name":"Australia Post",
    "wof:placetype":"venue"
},
  "geometry": {"coordinates":[138.52940368599999,-34.9463996887],"type":"Point"}
}