{
  "type": "Feature",
  "properties": {
    "iso:country":"AU",
    "sg:address":"49/ 15 Labouchere Rd",
    "sg:city":"South Perth",
    "sg:classifiers":[
        {
            "category":"Retail",
            "subcategory":"Event Space",
            "type":"Services"
        }
    ],
    "sg:phone":"+61 8 9474 9555",
    "sg:postcode":"6151",
    "sg:province":"WA",
    "sg:tags":[
        "function",
        "organiser"
    ],
    "wof:name":"Reflections By The Swan",
    "wof:placetype":"venue"
},
  "geometry": {"coordinates":[115.850922,-31.973946],"type":"Point"}
}