{
  "type": "Feature",
  "properties": {
    "addr:full":"3 Rochester St Homebush NSW 2140",
    "addr:housenumber":"3",
    "addr:postcode":"2140",
    "addr:street":"Rochester St",
    "iso:country":"AU",
    "sg:address":"3 Rochester St",
    "sg:city":"Homebush",
    "sg:classifiers":[
        {
            "category":"Personal",
            "subcategory":"Beauty Salon",
            "type":"Services"
        }
    ],
    "sg:phone":"+61 2 9764 1002",
    "sg:postcode":"2140",
    "sg:province":"NSW",
    "sg:tags":[
        "hairdresser"
    ],
    "wof:name":"Modern Touch Hair & Beauty",
    "wof:placetype":"venue"
},
  "geometry": {"coordinates":[151.08482360799999,-33.8666419983],"type":"Point"}
}