{
  "type": "Feature",
  "properties": {
    "addr:full":"Leslie St Southern River WA 6110",
    "addr:postcode":"6110",
    "addr:street":"Leslie St",
    "iso:country":"AU",
    "sg:address":"Leslie St",
    "sg:city":"Southern River",
    "sg:classifiers":[
        {
            "category":"Building & Trades",
            "subcategory":"Construction",
            "type":"Services"
        }
    ],
    "sg:phone":"+61 8 9490 8686",
    "sg:postcode":"6110",
    "sg:province":"WA",
    "sg:tags":[
        "waterproofing",
        "contractor"
    ],
    "wof:name":"Waterproof Products (WA)",
    "wof:placetype":"venue"
},
  "geometry": {"coordinates":[115.974372864,-32.0958328247],"type":"Point"}
}