{
  "type": "Feature",
  "properties": {
    "iso:country":"AU",
    "sg:address":"4 A Silicon Pl",
    "sg:city":"Tullamarine",
    "sg:classifiers":[
        {
            "category":"Utilities",
            "subcategory":"Electric",
            "type":"Services"
        }
    ],
    "sg:phone":"+61 3 9330 2276",
    "sg:postcode":"3043",
    "sg:province":"VIC",
    "sg:tags":[
        "electrical",
        "contractor"
    ],
    "wof:name":"Blue Electrical Solutions",
    "wof:placetype":"venue"
},
  "geometry": {"coordinates":[144.873535156,-37.7134971619],"type":"Point"}
}