{
  "type": "Feature",
  "properties": {
    "iso:country":"AU",
    "sg:address":"446 Enoggera Rd",
    "sg:city":"Alderley",
    "sg:classifiers":[
        {
            "category":"Professional",
            "subcategory":"Detective & Security Services",
            "type":"Services"
        }
    ],
    "sg:phone":"+61 7 3856 0771",
    "sg:postcode":"4051",
    "sg:province":"QLD",
    "sg:tags":[
        "consultant",
        "system"
    ],
    "wof:name":"Anthony Langford & Ass.",
    "wof:placetype":"venue"
},
  "geometry": {"coordinates":[153.001831055,-27.4267253876],"type":"Point"}
}