{
  "type": "Feature",
  "properties": {
    "addr:full":"21 Oaklands Rd Somerton Park SA 5044",
    "addr:housenumber":"21",
    "addr:postcode":"5044",
    "addr:street":"Oaklands Rd",
    "iso:country":"AU",
    "sg:address":"21 Oaklands Rd",
    "sg:city":"Somerton Park",
    "sg:classifiers":[
        {
            "category":"Food & Beverages",
            "subcategory":"Bakery",
            "type":"Retail Goods"
        }
    ],
    "sg:phone":"+61 8 8295 4434",
    "sg:postcode":"5044",
    "sg:province":"SA",
    "sg:tags":[
        "baker"
    ],
    "wof:name":"Beck's Bakehouse",
    "wof:placetype":"venue"
},
  "geometry": {"coordinates":[138.52436800000001,-34.99715],"type":"Point"}
}