{
  "type": "Feature",
  "properties": {
    "addr:full":"KGV, Lvl 6 South, Missenden Road Camperdown NSW 2050",
    "addr:housenumber":"6",
    "addr:postcode":"2050",
    "addr:street":"South Missenden Road",
    "iso:country":"AU",
    "sg:address":"KGV, Lvl 6 South, Missenden Road",
    "sg:city":"Camperdown",
    "sg:classifiers":[
        {
            "category":"Communications",
            "type":"Services"
        }
    ],
    "sg:phone":"+61 2 9515 9500",
    "sg:postcode":"2050",
    "sg:province":"NSW",
    "sg:tags":[
        "translation"
    ],
    "wof:name":"Central & South Eastern Sydney Health Care Interpreter",
    "wof:placetype":"venue"
},
  "geometry": {"coordinates":[151.17718500000001,-33.88866],"type":"Point"}
}