{
  "type": "Feature",
  "properties": {
    "iso:country":"AU",
    "sg:address":"264 Junction Rd",
    "sg:city":"Karalee",
    "sg:classifiers":[
        {
            "category":"Utilities",
            "subcategory":"Refuse",
            "type":"Services"
        }
    ],
    "sg:phone":"+61 7 3294 8444",
    "sg:postcode":"4306",
    "sg:province":"QLD",
    "sg:tags":[
        "remover",
        "rubbish"
    ],
    "wof:name":"Super Skips",
    "wof:placetype":"venue"
},
  "geometry": {"coordinates":[152.81559753400001,-27.5672912598],"type":"Point"}
}