{
  "type": "Feature",
  "properties": {
    "iso:country":"AU",
    "sg:address":"24 Long Point St",
    "sg:city":"Potato Point",
    "sg:classifiers":[
        {
            "category":"Health Services",
            "subcategory":"Health Practitioner",
            "type":"Services"
        }
    ],
    "sg:phone":"+61 2 4473 5766",
    "sg:postcode":"2545",
    "sg:province":"NSW",
    "sg:tags":[
        "naturopath"
    ],
    "wof:name":"Snith Maleyrack Noi",
    "wof:placetype":"venue"
},
  "geometry": {"coordinates":[150.13911438,-36.0941810608],"type":"Point"}
}