{
  "type": "Feature",
  "properties": {
    "addr:full":"Unit 12 8- 12 Deadman Rd Moorebank NSW 2170",
    "addr:housenumber":"8 12",
    "addr:postcode":"2170",
    "addr:street":"Deadman Rd",
    "iso:country":"AU",
    "sg:address":"Unit 12 8- 12 Deadman Rd",
    "sg:city":"Moorebank",
    "sg:classifiers":[
        {
            "category":"Utilities",
            "subcategory":"Electric",
            "type":"Services"
        }
    ],
    "sg:phone":"+61 2 9601 2121",
    "sg:postcode":"2170",
    "sg:province":"NSW",
    "sg:tags":[
        "electrical",
        "contractor"
    ],
    "wof:name":"Camden Valley Electrical & Electronic Services",
    "wof:placetype":"venue"
},
  "geometry": {"coordinates":[150.936157227,-33.9325752258],"type":"Point"}
}