{
  "type": "Feature",
  "properties": {
    "iso:country":"AU",
    "sg:address":"2/ 42 Keane St",
    "sg:city":"Townsville",
    "sg:classifiers":[
        {
            "category":"Shopping",
            "subcategory":"Crafts & Fabrics",
            "type":"Retail Goods"
        }
    ],
    "sg:phone":"+61 7 4779 4188",
    "sg:postcode":"4810",
    "sg:province":"QLD",
    "sg:tags":[
        "florist",
        "supply"
    ],
    "wof:name":"North Queensland Florists Supplies",
    "wof:placetype":"venue"
},
  "geometry": {"coordinates":[146.77720600000001,-19.271988],"type":"Point"}
}