{
  "type": "Feature",
  "properties": {
    "iso:country":"AU",
    "sg:address":"Level 1/ 30 Sylvan Rd",
    "sg:city":"Toowong",
    "sg:classifiers":[
        {
            "category":"Professional",
            "subcategory":"Management & Consulting",
            "type":"Services"
        }
    ],
    "sg:phone":"+61 7 3871 1731",
    "sg:postcode":"4066",
    "sg:province":"QLD",
    "sg:tags":[
        "consultant"
    ],
    "wof:name":"Selectus (QLD) Pty Ltd",
    "wof:placetype":"venue"
},
  "geometry": {"coordinates":[152.99378967300001,-27.4816131592],"type":"Point"}
}