{
  "type": "Feature",
  "properties": {
    "addr:full":"2/ 29 Adelaide Rd Gawler SA 5118",
    "addr:housenumber":"/ 29",
    "addr:postcode":"5118",
    "addr:street":"Adelaide Rd",
    "iso:country":"AU",
    "sg:address":"2/ 29 Adelaide Rd",
    "sg:city":"Gawler",
    "sg:classifiers":[
        {
            "category":"Health Services",
            "subcategory":"Medical Lab",
            "type":"Services"
        }
    ],
    "sg:phone":"+61 8 8523 2414",
    "sg:postcode":"5118",
    "sg:province":"SA",
    "sg:tags":[
        "laboratory",
        "pathology"
    ],
    "wof:name":"Gribbles Pathology",
    "wof:placetype":"venue"
},
  "geometry": {"coordinates":[138.744553,-34.606415],"type":"Point"}
}