{
  "type": "Feature",
  "properties": {
    "iso:country":"AU",
    "sg:address":"Lifecare Ashwood Sports Medicine, 330",
    "sg:city":"High Ashwood",
    "sg:classifiers":[
        {
            "category":"Health Services",
            "subcategory":"Health Practitioner",
            "type":"Services"
        }
    ],
    "sg:phone":"+61 3 9885 8961",
    "sg:postcode":"3147",
    "sg:province":"VIC",
    "sg:tags":[
        "physiotherapist"
    ],
    "wof:name":"Surkitt Luke",
    "wof:placetype":"venue"
},
  "geometry": {"coordinates":[145.091140747,-37.8648948669],"type":"Point"}
}