{
  "type": "Feature",
  "properties": {
    "addr:full":"Lot 15 Gilchrist Rd Stawell VIC 3380",
    "addr:postcode":"3380",
    "addr:street":"Gilchrist Rd",
    "iso:country":"AU",
    "sg:address":"Lot 15 Gilchrist Rd",
    "sg:city":"Stawell",
    "sg:classifiers":[
        {
            "category":"Farming",
            "subcategory":"Dairy Farm",
            "type":"Manufacturing & Wholesale Goods"
        }
    ],
    "sg:phone":"+61 3 5358 2103",
    "sg:postcode":"3380",
    "sg:province":"VIC",
    "wof:name":"Stawell Modern Dairy",
    "wof:placetype":"venue"
},
  "geometry": {"coordinates":[142.77279663100001,-37.0773429871],"type":"Point"}
}