{
  "type": "Feature",
  "properties": {
    "addr:full":"PO Box 1935 Bondi Junction NSW 1355",
    "addr:postcode":"1355",
    "iso:country":"AU",
    "sg:address":"PO Box 1935",
    "sg:city":"Bondi Junction",
    "sg:classifiers":[
        {
            "category":"Manufacturing",
            "subcategory":"Jewelry",
            "type":"Manufacturing & Wholesale Goods"
        }
    ],
    "sg:phone":"+61 2 9252 5548",
    "sg:postcode":"1355",
    "sg:province":"NSW",
    "sg:tags":[
        "mfrg",
        "jeweller"
    ],
    "wof:name":"Katz Daniel F",
    "wof:placetype":"venue"
},
  "geometry": {"coordinates":[151.24732971200001,-33.8923187256],"type":"Point"}
}