{
  "type": "Feature",
  "properties": {
    "addr:full":"Unit 1 52 Heathcote Rd Moorebank NSW 2170",
    "addr:housenumber":"52",
    "addr:postcode":"2170",
    "addr:street":"Heathcote Rd",
    "iso:country":"AU",
    "sg:address":"Unit 1 52 Heathcote Rd",
    "sg:city":"Moorebank",
    "sg:classifiers":[
        {
            "category":"Wholesale",
            "subcategory":"Apparel",
            "type":"Manufacturing & Wholesale Goods"
        }
    ],
    "sg:phone":"+61 2 9601 1059",
    "sg:postcode":"2170",
    "sg:province":"NSW",
    "sg:tags":[
        "wholesaler",
        "mfrs",
        "dress"
    ],
    "wof:name":"L-LEMENT & L-LEGANT",
    "wof:placetype":"venue"
},
  "geometry": {"coordinates":[150.94125366200001,-33.940662384],"type":"Point"}
}