{
  "type": "Feature",
  "properties": {
    "addr:full":"Old St Robinvale VIC 3549",
    "addr:postcode":"3549",
    "iso:country":"AU",
    "sg:address":"Old St",
    "sg:city":"Robinvale",
    "sg:classifiers":[
        {
            "category":"Education",
            "subcategory":"Kindergarten",
            "type":"Public Place"
        }
    ],
    "sg:phone":"+61 3 5026 3255",
    "sg:postcode":"3549",
    "sg:province":"VIC",
    "sg:tags":[
        "pre-schools"
    ],
    "wof:name":"M.V.A Kindergarten",
    "wof:placetype":"venue"
},
  "geometry": {"coordinates":[142.77293395999999,-34.5852012634],"type":"Point"}
}