{
  "type": "Feature",
  "properties": {
    "addr:full":"PO Box 2485 Geraldton WA 6530",
    "addr:postcode":"6530",
    "iso:country":"AU",
    "sg:address":"PO Box 2485",
    "sg:city":"Geraldton",
    "sg:classifiers":[
        {
            "category":"Education",
            "subcategory":"Special Training",
            "type":"Public Place"
        }
    ],
    "sg:phone":"+61 1300 557 930",
    "sg:postcode":"6530",
    "sg:province":"WA",
    "sg:tags":[
        "development"
    ],
    "wof:name":"Quality Traffic Management Pty Ltd",
    "wof:placetype":"venue"
},
  "geometry": {"coordinates":[114.64060974100001,-28.7494506836],"type":"Point"}
}