{
  "type": "Feature",
  "properties": {
    "addr:full":"37a Arundel St Glebe NSW 2037",
    "addr:housenumber":"37a",
    "addr:postcode":"2037",
    "addr:street":"Arundel St",
    "iso:country":"AU",
    "sg:address":"37a Arundel St",
    "sg:city":"Glebe",
    "sg:classifiers":[
        {
            "category":"Retail",
            "subcategory":"Auto Repair",
            "type":"Services"
        }
    ],
    "sg:phone":"+61 2 9660 8037",
    "sg:postcode":"2037",
    "sg:province":"NSW",
    "sg:tags":[
        "repairer",
        "motor",
        "engineer"
    ],
    "wof:name":"Cavaco Motors",
    "wof:placetype":"venue"
},
  "geometry": {"coordinates":[151.188995361,-33.8843574524],"type":"Point"}
}