{
  "type": "Feature",
  "properties": {
    "addr:full":"PO Box 188 Maddington Private Box WA 6989",
    "addr:postcode":"6989",
    "iso:country":"AU",
    "sg:address":"PO Box 188",
    "sg:city":"Maddington Private Box",
    "sg:classifiers":[
        {
            "category":"Utilities",
            "subcategory":"Electric",
            "type":"Services"
        }
    ],
    "sg:phone":"+61 8 9493 6966",
    "sg:postcode":"6989",
    "sg:province":"WA",
    "sg:tags":[
        "electrical",
        "contractor"
    ],
    "wof:name":"G.S.E. Electrics Pty Ltd",
    "wof:placetype":"venue"
},
  "geometry": {"coordinates":[115.99276,-32.042908],"type":"Point"}
}