{
  "type": "Feature",
  "properties": {
    "addr:full":"47 Mangrove Rd Narara NSW 2250",
    "addr:housenumber":"47",
    "addr:postcode":"2250",
    "addr:street":"Mangrove Rd",
    "iso:country":"AU",
    "sg:address":"47 Mangrove Rd",
    "sg:city":"Narara",
    "sg:classifiers":[
        {
            "category":"Retail",
            "subcategory":"Repair Shop",
            "type":"Services"
        }
    ],
    "sg:phone":"+61 407 003 064",
    "sg:postcode":"2250",
    "sg:province":"NSW",
    "sg:tags":[
        "mending",
        "clothing",
        "alteration"
    ],
    "wof:name":"J B Of Gosford Home Sewers Help",
    "wof:placetype":"venue"
},
  "geometry": {"coordinates":[151.344024658,-33.3853874207],"type":"Point"}
}