{
  "type": "Feature",
  "properties": {
    "iso:country":"AU",
    "sg:address":"5 Mecoli Crt",
    "sg:city":"Birkdale",
    "sg:classifiers":[
        {
            "category":"Recreation",
            "subcategory":"Fishing",
            "type":"Entertainment"
        }
    ],
    "sg:phone":"+61 7 3822 9527",
    "sg:postcode":"4159",
    "sg:province":"QLD",
    "sg:tags":[
        "trip"
    ],
    "wof:name":"Outlaw Charters",
    "wof:placetype":"venue"
},
  "geometry": {"coordinates":[153.203369141,-27.4973812103],"type":"Point"}
}