{
  "type": "Feature",
  "properties": {
    "addr:full":"14 North Rd Albany WA 6330",
    "addr:housenumber":"14",
    "addr:postcode":"6330",
    "addr:street":"North Rd",
    "iso:country":"AU",
    "sg:address":"14 North Rd",
    "sg:city":"Albany",
    "sg:classifiers":[
        {
            "category":"Freight",
            "type":"Transportation"
        }
    ],
    "sg:phone":"+61 418 948 533",
    "sg:postcode":"6330",
    "sg:province":"WA",
    "sg:tags":[
        "light",
        "carrier"
    ],
    "wof:name":"Jolly Johns",
    "wof:placetype":"venue"
},
  "geometry": {"coordinates":[117.895629883,-35.0121459961],"type":"Point"}
}