{
  "type": "Feature",
  "properties": {
    "addr:full":"221 Kororoit Creek Rd Williamstown VIC 3016",
    "addr:housenumber":"221",
    "addr:postcode":"3016",
    "addr:street":"Kororoit Creek Rd",
    "iso:country":"AU",
    "sg:address":"221 Kororoit Creek Rd",
    "sg:city":"Williamstown",
    "sg:classifiers":[
        {
            "category":"Wholesale",
            "subcategory":"Toys & Hobbies",
            "type":"Manufacturing & Wholesale Goods"
        }
    ],
    "sg:phone":"+61 3 9391 6822",
    "sg:postcode":"3016",
    "sg:province":"VIC",
    "wof:name":"Real Entertainment & Collectables Pty Ltd",
    "wof:placetype":"venue"
},
  "geometry": {"coordinates":[144.85728454599999,-37.8538475037],"type":"Point"}
}