{
  "type": "Feature",
  "properties": {
    "addr:full":"334 Belmore Rd Balwyn East VIC 3129",
    "addr:housenumber":"334",
    "addr:postcode":"3129",
    "addr:street":"Belmore Rd",
    "iso:country":"AU",
    "sg:address":"334 Belmore Rd",
    "sg:city":"Balwyn East",
    "sg:classifiers":[
        {
            "category":"Shopping",
            "subcategory":"Party Supplies",
            "type":"Retail Goods"
        }
    ],
    "sg:phone":"+61 3 9816 3722",
    "sg:postcode":"3129",
    "sg:province":"VIC",
    "sg:tags":[
        "hire",
        "costume"
    ],
    "wof:name":"Incognito Fancy Dress",
    "wof:placetype":"venue"
},
  "geometry": {"coordinates":[145.108886719,-37.8014755249],"type":"Point"}
}