{
  "type": "Feature",
  "properties": {
    "addr:full":"29 Anderson St Chatswood NSW 2067",
    "addr:housenumber":"29",
    "addr:postcode":"2067",
    "addr:street":"Anderson St",
    "iso:country":"AU",
    "sg:address":"29 Anderson St",
    "sg:city":"Chatswood",
    "sg:classifiers":[
        {
            "category":"Health Services",
            "subcategory":"Health Practitioner",
            "type":"Services"
        }
    ],
    "sg:phone":"+61 2 9411 5369",
    "sg:postcode":"2067",
    "sg:province":"NSW",
    "sg:tags":[
        "homoeopath"
    ],
    "wof:name":"House G",
    "wof:placetype":"venue"
},
  "geometry": {"coordinates":[151.18272399899999,-33.7949295044],"type":"Point"}
}