{
  "type": "Feature",
  "properties": {
    "addr:full":"3 Haslam Crt Carindale QLD 4152",
    "addr:housenumber":"3",
    "addr:postcode":"4152",
    "addr:street":"Haslam Crt",
    "iso:country":"AU",
    "sg:address":"3 Haslam Crt",
    "sg:city":"Carindale",
    "sg:classifiers":[
        {
            "category":"Professional",
            "subcategory":"Accounting & Tax Preparation",
            "type":"Services"
        }
    ],
    "sg:phone":"+61 403 837 323",
    "sg:postcode":"4152",
    "sg:province":"QLD",
    "sg:tags":[
        "accountant",
        "auditor"
    ],
    "wof:name":"Dreves G",
    "wof:placetype":"venue"
},
  "geometry": {"coordinates":[153.110595703,-27.5132865906],"type":"Point"}
}