{
  "type": "Feature",
  "properties": {
    "addr:full":"87 York St Launceston TAS 7250",
    "addr:housenumber":"87",
    "addr:postcode":"7250",
    "addr:street":"York St",
    "iso:country":"AU",
    "sg:address":"87 York St",
    "sg:city":"Launceston",
    "sg:classifiers":[
        {
            "category":"Cafe",
            "type":"Food & Drink"
        }
    ],
    "sg:phone":"+61 3 6331 6221",
    "sg:postcode":"7250",
    "sg:province":"TAS",
    "wof:name":"Wanderers Cafe",
    "wof:placetype":"venue"
},
  "geometry": {"coordinates":[147.139282227,-41.4389915466],"type":"Point"}
}