{
  "type": "Feature",
  "properties": {
    "iso:country":"AU",
    "sg:address":"12a Campsie St",
    "sg:city":"Campsie",
    "sg:classifiers":[
        {
            "category":"Health Services",
            "subcategory":"Doctor",
            "type":"Services"
        }
    ],
    "sg:phone":"+61 2 9718 2411",
    "sg:postcode":"2194",
    "sg:province":"NSW",
    "sg:tags":[
        "medical",
        "practitioner"
    ],
    "wof:name":"Finley A Geoffrey",
    "wof:placetype":"venue"
},
  "geometry": {"coordinates":[151.102356,-33.909397],"type":"Point"}
}