{
  "type": "Feature",
  "properties": {
    "addr:full":"Unit 3, 6- 8 Cavendish St Mittagong NSW 2575",
    "addr:housenumber":"6 8",
    "addr:postcode":"2575",
    "addr:street":"Cavendish St",
    "iso:country":"AU",
    "sg:address":"Unit 3, 6- 8 Cavendish St",
    "sg:city":"Mittagong",
    "sg:classifiers":[
        {
            "category":"Wholesale",
            "subcategory":"Machinery & Supplies",
            "type":"Manufacturing & Wholesale Goods"
        }
    ],
    "sg:phone":"+61 2 4871 1249",
    "sg:postcode":"2575",
    "sg:province":"NSW",
    "sg:tags":[
        "engineer"
    ],
    "wof:name":"Southern Highlands Industrial Supplies",
    "wof:placetype":"venue"
},
  "geometry": {"coordinates":[150.433792114,-34.4481010437],"type":"Point"}
}