{
  "type": "Feature",
  "properties": {
    "addr:full":"8 Tilley St Beaudesert QLD 4285",
    "addr:housenumber":"8",
    "addr:postcode":"4285",
    "addr:street":"Tilley St",
    "iso:country":"AU",
    "sg:address":"8 Tilley St",
    "sg:city":"Beaudesert",
    "sg:classifiers":[
        {
            "category":"Building & Trades",
            "subcategory":"Landscaping Services",
            "type":"Services"
        }
    ],
    "sg:phone":"+61 7 5541 1315",
    "sg:postcode":"4285",
    "sg:province":"QLD",
    "sg:tags":[
        "consultant"
    ],
    "wof:name":"Mark McCabe Building Consultancy",
    "wof:placetype":"venue"
},
  "geometry": {"coordinates":[153.0009,-27.989796],"type":"Point"}
}