{
  "type": "Feature",
  "properties": {
    "addr:full":"101 Liverpool St Port Lincoln SA 5606",
    "addr:housenumber":"101",
    "addr:postcode":"5606",
    "addr:street":"Liverpool St",
    "iso:country":"AU",
    "sg:address":"101 Liverpool St",
    "sg:city":"Port Lincoln",
    "sg:classifiers":[
        {
            "category":"Autos & Motor Vehicles",
            "subcategory":"Auto Supplies",
            "type":"Retail Goods"
        }
    ],
    "sg:phone":"+61 8 8683 0655",
    "sg:postcode":"5606",
    "sg:province":"SA",
    "sg:tags":[
        "accessory"
    ],
    "wof:name":"Autopro",
    "wof:placetype":"venue"
},
  "geometry": {"coordinates":[135.86447100000001,-34.724159],"type":"Point"}
}