{
  "type": "Feature",
  "properties": {
    "iso:country":"AU",
    "sg:address":"PO Box 44",
    "sg:city":"Blackmans Bay",
    "sg:classifiers":[
        {
            "category":"Building & Trades",
            "subcategory":"Construction",
            "type":"Services"
        }
    ],
    "sg:phone":"+61 409 977 299",
    "sg:postcode":"7052",
    "sg:province":"TAS",
    "sg:tags":[
        "fencing",
        "contractor"
    ],
    "wof:name":"Pride Fencing",
    "wof:placetype":"venue"
},
  "geometry": {"coordinates":[147.322464,-42.995579],"type":"Point"}
}