{
  "type": "Feature",
  "properties": {
    "addr:full":"455 President Ave Kirrawee NSW 2232",
    "addr:housenumber":"455",
    "addr:postcode":"2232",
    "addr:street":"President Ave",
    "iso:country":"AU",
    "sg:address":"455 President Ave",
    "sg:city":"Kirrawee",
    "sg:classifiers":[
        {
            "category":"Health Services",
            "subcategory":"Doctor",
            "type":"Services"
        }
    ],
    "sg:phone":"+61 2 9521 4526",
    "sg:postcode":"2232",
    "sg:province":"NSW",
    "sg:tags":[
        "medical",
        "practitioner"
    ],
    "wof:name":"Nair-Smith G Dr",
    "wof:placetype":"venue"
},
  "geometry": {"coordinates":[151.07095336899999,-34.0356178284],"type":"Point"}
}