{
  "type": "Feature",
  "properties": {
    "addr:full":"450 George St Sydney NSW 2000",
    "addr:housenumber":"450",
    "addr:postcode":"2000",
    "addr:street":"George St",
    "iso:country":"AU",
    "sg:address":"450 George St",
    "sg:city":"Sydney",
    "sg:classifiers":[
        {
            "category":"Cafe",
            "type":"Food & Drink"
        }
    ],
    "sg:phone":"+61 2 9221 9144",
    "sg:postcode":"2000",
    "sg:province":"NSW",
    "wof:name":"Bogards Cafe & Bar",
    "wof:placetype":"venue"
},
  "geometry": {"coordinates":[151.20716857900001,-33.8706970215],"type":"Point"}
}