{
  "type": "Feature",
  "properties": {
    "iso:country":"AU",
    "sg:address":"176 Furlong Rd",
    "sg:city":"St Albans",
    "sg:classifiers":[
        {
            "category":"Health Services",
            "subcategory":"Doctor",
            "type":"Services"
        }
    ],
    "sg:phone":"+61 3 9365 1257",
    "sg:postcode":"3021",
    "sg:province":"VIC",
    "sg:tags":[
        "nurse",
        "nursing"
    ],
    "wof:name":"Royal District Nursing Service",
    "wof:placetype":"venue"
},
  "geometry": {"coordinates":[144.815826,-37.760647],"type":"Point"}
}