{
  "type": "Feature",
  "properties": {
    "addr:full":"176 Furlong Rd St Albans VIC 3021",
    "addr:housenumber":"176",
    "addr:postcode":"3021",
    "addr:street":"Furlong Rd",
    "iso:country":"AU",
    "sg:address":"176 Furlong Rd",
    "sg:city":"St Albans",
    "sg:classifiers":[
        {
            "category":"Health Services",
            "subcategory":"Doctor",
            "type":"Services"
        }
    ],
    "sg:phone":"+61 3 9365 1257",
    "sg:postcode":"3021",
    "sg:province":"VIC",
    "sg:tags":[
        "nurse",
        "nursing"
    ],
    "wof:name":"Royal District Nursing Service",
    "wof:placetype":"venue"
},
  "geometry": {"coordinates":[144.81582599999999,-37.760647],"type":"Point"}
}