{
  "type": "Feature",
  "properties": {
    "addr:full":"57 Hampton Rd Keswick SA 5035",
    "addr:housenumber":"57",
    "addr:postcode":"5035",
    "addr:street":"Hampton Rd",
    "iso:country":"AU",
    "sg:address":"57 Hampton Rd",
    "sg:city":"Keswick",
    "sg:classifiers":[
        {
            "category":"Wholesale",
            "subcategory":"Toys & Hobbies",
            "type":"Manufacturing & Wholesale Goods"
        }
    ],
    "sg:phone":"+61 8 8297 5388",
    "sg:postcode":"5035",
    "sg:province":"SA",
    "wof:name":"Newberry Imports",
    "wof:placetype":"venue"
},
  "geometry": {"coordinates":[138.57876586899999,-34.945400238],"type":"Point"}
}