{
  "type": "Feature",
  "properties": {
    "iso:country":"AU",
    "sg:address":"56 Poinsettia St",
    "sg:city":"Inala",
    "sg:classifiers":[
        {
            "category":"Organizations",
            "subcategory":"Community Association",
            "type":"Services"
        }
    ],
    "sg:phone":"+61 7 3372 7188",
    "sg:postcode":"4077",
    "sg:province":"QLD",
    "sg:tags":[
        "organisation",
        "family",
        "welfare"
    ],
    "wof:name":"Inala Family Accommodation Project",
    "wof:placetype":"venue"
},
  "geometry": {"coordinates":[152.965744019,-27.5970172882],"type":"Point"}
}