{
  "type": "Feature",
  "properties": {
    "addr:full":"8 Michel St Lowood QLD 4311",
    "addr:housenumber":"8",
    "addr:postcode":"4311",
    "addr:street":"Michel St",
    "iso:country":"AU",
    "sg:address":"8 Michel St",
    "sg:city":"Lowood",
    "sg:classifiers":[
        {
            "category":"Health Services",
            "subcategory":"Medical Lab",
            "type":"Services"
        }
    ],
    "sg:phone":"+61 7 5426 1955",
    "sg:postcode":"4311",
    "sg:province":"QLD",
    "sg:tags":[
        "laboratory",
        "pathology"
    ],
    "wof:name":"Sullivan Nicolaides Pathology",
    "wof:placetype":"venue"
},
  "geometry": {"coordinates":[152.579544067,-27.4636135101],"type":"Point"}
}