{
  "type": "Feature",
  "properties": {
    "iso:country":"AU",
    "sg:address":"1356 Centre Rd",
    "sg:city":"Clayton",
    "sg:classifiers":[
        {
            "category":"Banks & Credit Unions",
            "subcategory":"Investment Brokerage",
            "type":"Services"
        }
    ],
    "sg:phone":"+61 3 9543 3230",
    "sg:postcode":"3168",
    "sg:province":"VIC",
    "sg:tags":[
        "finance",
        "broker"
    ],
    "wof:name":"Quality Finance Pty Ltd",
    "wof:placetype":"venue"
},
  "geometry": {"coordinates":[145.12013244600001,-37.9287986755],"type":"Point"}
}