{
  "type": "Feature",
  "properties": {
    "iso:country":"AU",
    "sg:address":"1/ 12 Seves St",
    "sg:city":"Altona",
    "sg:classifiers":[
        {
            "category":"Shopping",
            "type":"Retail Goods"
        }
    ],
    "sg:phone":"+61 3 9398 4229",
    "sg:postcode":"3018",
    "sg:province":"VIC",
    "sg:tags":[
        "equipment",
        "safety",
        "accessory"
    ],
    "wof:name":"Bean Apron Company",
    "wof:placetype":"venue"
},
  "geometry": {"coordinates":[144.83709716800001,-37.869720459],"type":"Point"}
}