{
  "type": "Feature",
  "properties": {
    "addr:full":"1599 Main Rd Preston TAS 7315",
    "addr:housenumber":"1599",
    "addr:postcode":"7315",
    "addr:street":"Main Rd",
    "iso:country":"AU",
    "sg:address":"1599 Main Rd",
    "sg:city":"Preston",
    "sg:classifiers":[
        {
            "category":"Building & Trades",
            "subcategory":"Construction",
            "type":"Services"
        }
    ],
    "sg:phone":"+61 418 122 446",
    "sg:postcode":"7315",
    "sg:province":"TAS",
    "sg:tags":[
        "renovation",
        "alterations",
        "extension",
        "contractor"
    ],
    "wof:name":"Henk Dikkenberg",
    "wof:placetype":"venue"
},
  "geometry": {"coordinates":[146.19032287600001,-41.1659469604],"type":"Point"}
}