{
  "type": "Feature",
  "properties": {
    "addr:full":"2/ 6 Armstrong Wy Caboolture QLD 4510",
    "addr:housenumber":"/ 6",
    "addr:postcode":"4510",
    "addr:street":"Armstrong Wy",
    "iso:country":"AU",
    "sg:address":"2/ 6 Armstrong Wy",
    "sg:city":"Caboolture",
    "sg:classifiers":[
        {
            "category":"Real Estate",
            "subcategory":"Real Estate Agent",
            "type":"Services"
        }
    ],
    "sg:phone":"+61 7 5499 4200",
    "sg:postcode":"4510",
    "sg:province":"QLD",
    "wof:name":"Caboolture Rentals",
    "wof:placetype":"venue"
},
  "geometry": {"coordinates":[152.95257599999999,-27.084072],"type":"Point"}
}