{
  "type": "Feature",
  "properties": {
    "addr:full":"Shp 6, East Quay Shopng Cntr, 217 Ron Penhaligon Way Robina QLD 4226",
    "addr:housenumber":"6;217",
    "addr:postcode":"4226",
    "addr:street":"East Quay Shopng Cntr;Penhaligon Way",
    "iso:country":"AU",
    "sg:address":"Shp 6, East Quay Shopng Cntr, 217",
    "sg:city":"Ron Penhaligon Way Robina",
    "sg:classifiers":[
        {
            "category":"Health Services",
            "subcategory":"Health Practitioner",
            "type":"Services"
        }
    ],
    "sg:phone":"+61 7 5578 7958",
    "sg:postcode":"4226",
    "sg:province":"QLD",
    "sg:tags":[
        "naturopath"
    ],
    "wof:name":"Oriental Healing Clinic-David Zhang",
    "wof:placetype":"venue"
},
  "geometry": {"coordinates":[153.40492248499999,-28.0647792816],"type":"Point"}
}