{
  "type": "Feature",
  "properties": {
    "addr:full":"Mercy Medical Centre, Suite 2/Level 1, Ellesmere Rd Mt Lawley WA 6050",
    "addr:housenumber":"2;1",
    "addr:postcode":"6050",
    "addr:street":"Ellesmere Rd",
    "iso:country":"AU",
    "sg:address":"Mercy Medical Centre, Suite 2/Level 1, Ellesmere Rd",
    "sg:city":"Mt Lawley",
    "sg:classifiers":[
        {
            "category":"Health Services",
            "subcategory":"Doctor",
            "type":"Services"
        }
    ],
    "sg:phone":"+61 8 9370 9686",
    "sg:postcode":"6050",
    "sg:province":"WA",
    "sg:tags":[
        "medical",
        "practitioner"
    ],
    "wof:name":"Brand Roland Dr",
    "wof:placetype":"venue"
},
  "geometry": {"coordinates":[115.88407135,-31.9377994537],"type":"Point"}
}