{
  "type": "Feature",
  "properties": {
    "addr:full":"Shp132/ 399 Melton Hwy Taylors Lakes VIC 3038",
    "addr:housenumber":"399",
    "addr:postcode":"3038",
    "addr:street":"Melton Hwy",
    "iso:country":"AU",
    "sg:address":"Shp132/ 399 Melton Hwy",
    "sg:city":"Taylors Lakes",
    "sg:classifiers":[
        {
            "category":"Food & Beverages",
            "subcategory":"Fruits & Vegetables",
            "type":"Retail Goods"
        }
    ],
    "sg:phone":"+61 3 8390 7433",
    "sg:postcode":"3038",
    "sg:province":"VIC",
    "sg:tags":[
        "greengrocer",
        "fruiterer"
    ],
    "wof:name":"Nandos Market Gardens",
    "wof:placetype":"venue"
},
  "geometry": {"coordinates":[144.77842699999999,-37.696995],"type":"Point"}
}