{
  "type": "Feature",
  "properties": {
    "iso:country":"AU",
    "sg:address":"42 Hutchinson St",
    "sg:city":"Burleigh Heads",
    "sg:classifiers":[
        {
            "category":"Home & Garden",
            "subcategory":"Garden Supply",
            "type":"Retail Goods"
        }
    ],
    "sg:phone":"+61 7 5593 7425",
    "sg:postcode":"4220",
    "sg:province":"QLD",
    "sg:tags":[
        "landscape"
    ],
    "wof:name":"Burleigh Landscape Supplies",
    "wof:placetype":"venue"
},
  "geometry": {"coordinates":[153.42156982399999,-28.1084766388],"type":"Point"}
}