{
  "type": "Feature",
  "properties": {
    "addr:full":"7 Brockhoff Drv Burwood VIC 3125",
    "addr:housenumber":"7",
    "addr:postcode":"3125",
    "addr:street":"Brockhoff Drv",
    "iso:country":"AU",
    "sg:address":"7 Brockhoff Drv",
    "sg:city":"Burwood",
    "sg:classifiers":[
        {
            "category":"Parking",
            "subcategory":"Garage",
            "type":"Transportation"
        }
    ],
    "sg:phone":"+61 3 9808 1705",
    "sg:postcode":"3125",
    "sg:province":"VIC",
    "sg:tags":[
        "radiographer"
    ],
    "wof:name":"St. Mary's Radiology",
    "wof:placetype":"venue"
},
  "geometry": {"coordinates":[145.11174011200001,-37.8593597412],"type":"Point"}
}