{
  "type": "Feature",
  "properties": {
    "addr:full":"22 Percy St Mordialloc VIC 3195",
    "addr:housenumber":"22",
    "addr:postcode":"3195",
    "addr:street":"Percy St",
    "iso:country":"AU",
    "sg:address":"22 Percy St",
    "sg:city":"Mordialloc",
    "sg:classifiers":[
        {
            "category":"Building & Trades",
            "subcategory":"Plumbing",
            "type":"Services"
        }
    ],
    "sg:phone":"+61 3 9580 0711",
    "sg:postcode":"3195",
    "sg:province":"VIC",
    "sg:tags":[
        "plumber",
        "gasfitters"
    ],
    "wof:name":"Stanley Air Conditioning Pty Ltd",
    "wof:placetype":"venue"
},
  "geometry": {"coordinates":[145.095703125,-38.007610321],"type":"Point"}
}