{
  "type": "Feature",
  "properties": {
    "addr:full":"Ste 1a/Lvl 1, 322 Kingsgrove Rd Kingsgrove NSW 2208",
    "addr:housenumber":"322",
    "addr:postcode":"2208",
    "addr:street":"Kingsgrove Rd",
    "iso:country":"AU",
    "sg:address":"Ste 1a/Lvl 1, 322 Kingsgrove Rd",
    "sg:city":"Kingsgrove",
    "sg:classifiers":[
        {
            "category":"Banks & Credit Unions",
            "subcategory":"Financial Services",
            "type":"Services"
        }
    ],
    "sg:phone":"+61 2 9554 3566",
    "sg:postcode":"2208",
    "sg:province":"NSW",
    "sg:tags":[
        "planning"
    ],
    "wof:name":"Wealth & Lifestyle Financial Planning",
    "wof:placetype":"venue"
},
  "geometry": {"coordinates":[151.10192900000001,-33.943878],"type":"Point"}
}