{
  "type": "Feature",
  "properties": {
    "addr:full":"631 Plenty Rd Preston VIC 3072",
    "addr:housenumber":"631",
    "addr:postcode":"3072",
    "addr:street":"Plenty Rd",
    "iso:country":"AU",
    "sg:address":"631 Plenty Rd",
    "sg:city":"Preston",
    "sg:classifiers":[
        {
            "category":"Manufacturing",
            "subcategory":"Wood Products",
            "type":"Manufacturing & Wholesale Goods"
        }
    ],
    "sg:phone":"+61 3 9471 9888",
    "sg:postcode":"3072",
    "sg:province":"VIC",
    "sg:tags":[
        "polisher",
        "french"
    ],
    "wof:name":"Plenty Road Restorations & French Polishing",
    "wof:placetype":"venue"
},
  "geometry": {"coordinates":[145.10012817399999,-37.7288894653],"type":"Point"}
}