{
  "type": "Feature",
  "properties": {
    "addr:full":"11A Giblett St Manjimup WA 6258",
    "addr:housenumber":"11a",
    "addr:postcode":"6258",
    "addr:street":"Giblett St",
    "iso:country":"AU",
    "sg:address":"11A Giblett St",
    "sg:city":"Manjimup",
    "sg:classifiers":[
        {
            "category":"Food & Beverages",
            "subcategory":"Bakery",
            "type":"Retail Goods"
        }
    ],
    "sg:phone":"+61 8 9777 2270",
    "sg:postcode":"6258",
    "sg:province":"WA",
    "sg:tags":[
        "baker"
    ],
    "wof:name":"Rose's Bakery",
    "wof:placetype":"venue"
},
  "geometry": {"coordinates":[116.145927429,-34.2419815063],"type":"Point"}
}