{
  "type": "Feature",
  "properties": {
    "addr:full":"14 Jubilee Rd Streaky Bay SA 5680",
    "addr:housenumber":"14",
    "addr:postcode":"5680",
    "addr:street":"Jubilee Rd",
    "iso:country":"AU",
    "sg:address":"14 Jubilee Rd",
    "sg:city":"Streaky Bay",
    "sg:classifiers":[
        {
            "category":"Building & Trades",
            "subcategory":"Construction",
            "type":"Services"
        }
    ],
    "sg:phone":"+61 8 8626 1254",
    "sg:postcode":"5680",
    "sg:province":"SA",
    "sg:tags":[
        "contractor"
    ],
    "wof:name":"West Coast Relocatables",
    "wof:placetype":"venue"
},
  "geometry": {"coordinates":[134.222381592,-32.7969741821],"type":"Point"}
}