{
  "type": "Feature",
  "properties": {
    "iso:country":"AU",
    "sg:address":"100 Coulter Rd",
    "sg:city":"Coomera",
    "sg:classifiers":[
        {
            "category":"Building & Trades",
            "subcategory":"Construction",
            "type":"Services"
        }
    ],
    "sg:phone":"+61 7 5549 3062",
    "sg:postcode":"4209",
    "sg:province":"QLD",
    "sg:tags":[
        "home",
        "air conditioning"
    ],
    "wof:name":"JT Air Conditioning Services",
    "wof:placetype":"venue"
},
  "geometry": {"coordinates":[153.28276062,-27.8446674347],"type":"Point"}
}