{
  "type": "Feature",
  "properties": {
    "iso:country":"AU",
    "sg:address":"Factory 3 102 Bell St",
    "sg:city":"Preston",
    "sg:classifiers":[
        {
            "category":"Building & Trades",
            "subcategory":"Construction",
            "type":"Services"
        }
    ],
    "sg:phone":"+61 3 9817 1476",
    "sg:postcode":"3072",
    "sg:province":"VIC",
    "sg:tags":[
        "spouting",
        "guttering"
    ],
    "sg:website":"http://www.melbourneguttering.com.au",
    "wof:name":"The Melbourne Guttering Co",
    "wof:placetype":"venue"
},
  "geometry": {"coordinates":[145.02508544899999,-37.7474555969],"type":"Point"}
}