{
  "type": "Feature",
  "properties": {
    "addr:full":"Lot 2 Cobden-Lavers Hill Rd Simpson VIC 3266",
    "addr:postcode":"3266",
    "addr:street":"Hill Rd",
    "iso:country":"AU",
    "sg:address":"Lot 2 Cobden-Lavers Hill Rd",
    "sg:city":"Simpson",
    "sg:classifiers":[
        {
            "category":"Retail",
            "subcategory":"Auto Repair",
            "type":"Services"
        }
    ],
    "sg:phone":"+61 3 5594 3288",
    "sg:postcode":"3266",
    "sg:province":"VIC",
    "sg:tags":[
        "repairer",
        "motor",
        "engineer"
    ],
    "wof:name":"Vogels Motors",
    "wof:placetype":"venue"
},
  "geometry": {"coordinates":[143.20877075199999,-38.4956512451],"type":"Point"}
}