{
  "type": "Feature",
  "properties": {
    "iso:country":"AU",
    "sg:address":"118 Grote St",
    "sg:city":"Adelaide",
    "sg:classifiers":[
        {
            "category":"Shopping",
            "subcategory":"Antiques",
            "type":"Retail Goods"
        }
    ],
    "sg:phone":"+61 8 8231 0102",
    "sg:postcode":"5000",
    "sg:province":"SA",
    "wof:name":"Quigley Peter Antiques",
    "wof:placetype":"venue"
},
  "geometry": {"coordinates":[138.59466552699999,-34.9286613464],"type":"Point"}
}