{
  "type": "Feature",
  "properties": {
    "addr:full":"Barbagallo Raceway, Wattle Ave Neerabup WA 6031",
    "addr:postcode":"6031",
    "addr:street":"Wattle Ave",
    "iso:country":"AU",
    "sg:address":"Barbagallo Raceway, Wattle Ave",
    "sg:city":"Neerabup",
    "sg:classifiers":[
        {
            "category":"Retail",
            "subcategory":"Auto Repair",
            "type":"Services"
        }
    ],
    "sg:phone":"+61 439 710 069",
    "sg:postcode":"6031",
    "sg:province":"WA",
    "sg:tags":[
        "hire",
        "go-kart"
    ],
    "wof:name":"Ultra Fast Karts",
    "wof:placetype":"venue"
},
  "geometry": {"coordinates":[115.800483704,-31.6628704071],"type":"Point"}
}