{
  "type": "Feature",
  "properties": {
    "addr:full":"7/ 55 Perouse Rd Randwick NSW 2031",
    "addr:housenumber":"/ 55",
    "addr:postcode":"2031",
    "addr:street":"Perouse Rd",
    "iso:country":"AU",
    "sg:address":"7/ 55 Perouse Rd",
    "sg:city":"Randwick",
    "sg:classifiers":[
        {
            "category":"Health Services",
            "subcategory":"Dentist",
            "type":"Services"
        }
    ],
    "sg:phone":"+61 2 9399 7300",
    "sg:postcode":"2031",
    "sg:province":"NSW",
    "wof:name":"Delohery Ray P",
    "wof:placetype":"venue"
},
  "geometry": {"coordinates":[151.242919922,-33.9205207825],"type":"Point"}
}