{
  "type": "Feature",
  "properties": {
    "addr:full":"20- 22 May Rd Lalor VIC 3075",
    "addr:housenumber":"22",
    "addr:postcode":"3075",
    "addr:street":"May Rd",
    "iso:country":"AU",
    "sg:address":"20- 22 May Rd",
    "sg:city":"Lalor",
    "sg:classifiers":[
        {
            "category":"Shopping",
            "subcategory":"Clothing, Apparel, & Fashions",
            "type":"Retail Goods"
        }
    ],
    "sg:phone":"+61 3 9464 4872",
    "sg:postcode":"3075",
    "sg:province":"VIC",
    "sg:tags":[
        "recycled",
        "clothing"
    ],
    "wof:name":"The Salvation Army Family Stores",
    "wof:placetype":"venue"
},
  "geometry": {"coordinates":[145.004562378,-37.84740448],"type":"Point"}
}