{
  "type": "Feature",
  "properties": {
    "iso:country":"AU",
    "sg:address":"2 Toolooma St",
    "sg:city":"Woodridge",
    "sg:classifiers":[
        {
            "category":"Building & Trades",
            "subcategory":"Construction",
            "type":"Services"
        }
    ],
    "sg:phone":"+61 7 3299 2994",
    "sg:postcode":"4114",
    "sg:province":"QLD",
    "sg:tags":[
        "pool",
        "swimming"
    ],
    "wof:name":"Steves Pool Installation & Maintenance",
    "wof:placetype":"venue"
},
  "geometry": {"coordinates":[153.11250305199999,-27.6383457184],"type":"Point"}
}