{
  "type": "Feature",
  "properties": {
    "addr:full":"47 Oroya St Boulder WA 6432",
    "addr:housenumber":"47",
    "addr:postcode":"6432",
    "addr:street":"Oroya St",
    "iso:country":"AU",
    "sg:address":"47 Oroya St",
    "sg:city":"Boulder",
    "sg:classifiers":[
        {
            "category":"Mining & Drilling",
            "type":"Manufacturing & Wholesale Goods"
        }
    ],
    "sg:phone":"+61 8 9093 2972",
    "sg:postcode":"6432",
    "sg:province":"WA",
    "sg:tags":[
        "equipment",
        "quarrying",
        "supply"
    ],
    "wof:name":"Mangelsdorf Engineering Pty Ltd",
    "wof:placetype":"venue"
},
  "geometry": {"coordinates":[121.495323181,-30.7914638519],"type":"Point"}
}