{
  "type": "Feature",
  "properties": {
    "iso:country":"AU",
    "sg:address":"171 Toombul Rd",
    "sg:city":"Northgate",
    "sg:classifiers":[
        {
            "category":"Retail",
            "subcategory":"Auto Repair",
            "type":"Services"
        }
    ],
    "sg:phone":"+61 7 3256 6733",
    "sg:postcode":"4013",
    "sg:province":"QLD",
    "sg:tags":[
        "testing",
        "inspection",
        "motor",
        "vehicle"
    ],
    "wof:name":"B M Serv",
    "wof:placetype":"venue"
},
  "geometry": {"coordinates":[153.071502686,-27.391916275],"type":"Point"}
}