{
  "type": "Feature",
  "properties": {
    "iso:country":"AU",
    "sg:address":"Ste 2/ Level 4/ 460 Church St",
    "sg:city":"North Parramatta",
    "sg:classifiers":[
        {
            "category":"Professional",
            "subcategory":"Accounting & Tax Preparation",
            "type":"Services"
        }
    ],
    "sg:phone":"+61 2 9683 7433",
    "sg:postcode":"2151",
    "sg:province":"NSW",
    "sg:tags":[
        "accountant",
        "auditor"
    ],
    "wof:name":"Behrens Rowley Chartered Accountants",
    "wof:placetype":"venue"
},
  "geometry": {"coordinates":[151.00601196299999,-33.8055000305],"type":"Point"}
}