{
  "type": "Feature",
  "properties": {
    "iso:country":"AU",
    "sg:address":"34 Gledson St",
    "sg:city":"Booval North",
    "sg:classifiers":[
        {
            "category":"Fast Food",
            "type":"Food & Drink"
        }
    ],
    "sg:phone":"+61 7 3282 4557",
    "sg:postcode":"4304",
    "sg:province":"QLD",
    "sg:tags":[
        "away",
        "take"
    ],
    "wof:name":"Carmen's Seafood & Take Away",
    "wof:placetype":"venue"
},
  "geometry": {"coordinates":[152.79515075699999,-27.6047477722],"type":"Point"}
}