{
  "type": "Feature",
  "properties": {
    "addr:full":"19 Maxwell St Ashburton VIC 3147",
    "addr:housenumber":"19",
    "addr:postcode":"3147",
    "addr:street":"Maxwell St",
    "iso:country":"AU",
    "sg:address":"19 Maxwell St",
    "sg:city":"Ashburton",
    "sg:classifiers":[
        {
            "category":"Professional",
            "subcategory":"Testing Lab",
            "type":"Services"
        }
    ],
    "sg:phone":"+61 3 9885 1572",
    "sg:postcode":"3147",
    "sg:province":"VIC",
    "sg:tags":[
        "soil",
        "investigation"
    ],
    "wof:name":"Electric Penetrometer Testing (Aust) Pty Ltd",
    "wof:placetype":"venue"
},
  "geometry": {"coordinates":[145.06712341299999,-37.8693847656],"type":"Point"}
}