{
  "type": "Feature",
  "properties": {
    "iso:country":"AU",
    "sg:address":"635 Sturt St",
    "sg:city":"Townsville",
    "sg:classifiers":[
        {
            "category":"Autos & Motor Vehicles",
            "subcategory":"Auto Supplies",
            "type":"Retail Goods"
        }
    ],
    "sg:phone":"+61 13 61 30",
    "sg:postcode":"4810",
    "sg:province":"QLD",
    "sg:tags":[
        "battery",
        "automotive"
    ],
    "wof:name":"Marshall Batteries",
    "wof:placetype":"venue"
},
  "geometry": {"coordinates":[146.807312,-19.266693],"type":"Point"}
}