{
  "type": "Feature",
  "properties": {
    "iso:country":"AU",
    "sg:address":"Lvl 2/ 414 Hunter St",
    "sg:city":"Newcastle",
    "sg:classifiers":[
        {
            "category":"Health Services",
            "subcategory":"Health Practitioner",
            "type":"Services"
        }
    ],
    "sg:phone":"+61 2 4925 3333",
    "sg:postcode":"2300",
    "sg:province":"NSW",
    "sg:tags":[
        "psychologist"
    ],
    "wof:name":"Brucki Belinda",
    "wof:placetype":"venue"
},
  "geometry": {"coordinates":[151.772705,-32.926777],"type":"Point"}
}