{
  "type": "Feature",
  "properties": {
    "iso:country":"AU",
    "sg:address":"Shop 250",
    "sg:city":"Warringah Mall Brookvale",
    "sg:classifiers":[
        {
            "category":"Shopping",
            "subcategory":"Baby Store",
            "type":"Retail Goods"
        }
    ],
    "sg:phone":"+61 2 9316 6599",
    "sg:postcode":"2100",
    "sg:province":"NSW",
    "sg:tags":[
        "children's",
        "wear"
    ],
    "wof:name":"Oshkosh B&#039;Gosh",
    "wof:placetype":"venue"
},
  "geometry": {"coordinates":[151.25035095199999,-33.7523078918],"type":"Point"}
}