{
  "type": "Feature",
  "properties": {
    "iso:country":"AU",
    "sg:address":"U1/ 32 Green St",
    "sg:city":"Thomastown",
    "sg:classifiers":[
        {
            "category":"Retail",
            "subcategory":"Auto Repair",
            "type":"Services"
        }
    ],
    "sg:phone":"+61 3 9464 5612",
    "sg:postcode":"3074",
    "sg:province":"VIC",
    "sg:tags":[
        "repairer",
        "motor",
        "engineer"
    ],
    "wof:name":"Green Street Motors",
    "wof:placetype":"venue"
},
  "geometry": {"coordinates":[145.03822326700001,-37.6914634705],"type":"Point"}
}