{
  "type": "Feature",
  "properties": {
    "addr:full":"2713 Main Pl Broadbeach QLD 4218",
    "addr:housenumber":"2713",
    "addr:postcode":"4218",
    "addr:street":"Main Pl",
    "iso:country":"AU",
    "sg:address":"2713 Main Pl",
    "sg:city":"Broadbeach",
    "sg:classifiers":[
        {
            "category":"Health Services",
            "subcategory":"Dentist",
            "type":"Services"
        }
    ],
    "sg:phone":"+61 7 5531 5485",
    "sg:postcode":"4218",
    "sg:province":"QLD",
    "wof:name":"Main Place Dental Surgery",
    "wof:placetype":"venue"
},
  "geometry": {"coordinates":[153.43060302699999,-28.0284976959],"type":"Point"}
}