{
  "type": "Feature",
  "properties": {
    "iso:country":"AU",
    "sg:address":"232 High St",
    "sg:city":"Cranbourne",
    "sg:classifiers":[
        {
            "category":"Real Estate",
            "subcategory":"Real Estate Agent",
            "type":"Services"
        }
    ],
    "sg:phone":"+61 3 5996 6088",
    "sg:postcode":"3977",
    "sg:province":"VIC",
    "sg:tags":[
        "handyman's",
        "equipment",
        "hire",
        "builders",
        "contractor"
    ],
    "wof:name":"Better Rentals",
    "wof:placetype":"venue"
},
  "geometry": {"coordinates":[145.283447266,-38.0987854004],"type":"Point"}
}