{
  "type": "Feature",
  "properties": {
    "addr:full":"113 George St Morwell VIC 3840",
    "addr:housenumber":"113",
    "addr:postcode":"3840",
    "addr:street":"George St",
    "iso:country":"AU",
    "sg:address":"113 George St",
    "sg:city":"Morwell",
    "sg:classifiers":[
        {
            "category":"Communications",
            "subcategory":"Film & Video Production",
            "type":"Services"
        }
    ],
    "sg:phone":"+61 3 5134 5227",
    "sg:postcode":"3840",
    "sg:province":"VIC",
    "sg:tags":[
        "dvd",
        "library"
    ],
    "wof:name":"Network Video Morwell",
    "wof:placetype":"venue"
},
  "geometry": {"coordinates":[146.39976501500001,-38.2386512756],"type":"Point"}
}