{
  "type": "Feature",
  "properties": {
    "addr:full":"Level 6, 54 Marcus Clarke St Canberra ACT 2600",
    "addr:housenumber":"54",
    "addr:postcode":"2600",
    "addr:street":"Marcus Clarke St",
    "iso:country":"AU",
    "sg:address":"Level 6, 54 Marcus Clarke St",
    "sg:city":"Canberra",
    "sg:classifiers":[
        {
            "category":"Professional",
            "subcategory":"Employment Agencies",
            "type":"Services"
        }
    ],
    "sg:phone":"+61 2 6229 1555",
    "sg:postcode":"2600",
    "sg:province":"ACT",
    "wof:name":"Hudson Global Resources",
    "wof:placetype":"venue"
},
  "geometry": {"coordinates":[149.126754761,-35.276676178],"type":"Point"}
}