{
  "type": "Feature",
  "properties": {
    "iso:country":"AU",
    "sg:address":"218 Coode St",
    "sg:city":"South Perth",
    "sg:classifiers":[
        {
            "category":"Banks & Credit Unions",
            "subcategory":"Bank",
            "type":"Services"
        }
    ],
    "sg:phone":"+61 8 9474 6104",
    "sg:postcode":"6151",
    "sg:province":"WA",
    "sg:tags":[
        "broker",
        "mortgage"
    ],
    "wof:name":"AAA Credit Solutions",
    "wof:placetype":"venue"
},
  "geometry": {"coordinates":[115.862259,-31.996014],"type":"Point"}
}