{
  "type": "Feature",
  "properties": {
    "addr:full":"Level 10 575 Bourke St Melbourne VIC 3000",
    "addr:housenumber":"575",
    "addr:postcode":"3000",
    "addr:street":"Bourke St",
    "iso:country":"AU",
    "sg:address":"Level 10 575 Bourke St",
    "sg:city":"Melbourne",
    "sg:classifiers":[
        {
            "category":"Professional",
            "subcategory":"Computer Services",
            "type":"Services"
        }
    ],
    "sg:phone":"+61 3 9618 1222",
    "sg:postcode":"3000",
    "sg:province":"VIC",
    "sg:tags":[
        "consultant",
        "system"
    ],
    "wof:name":"PowerServe Pty Ltd",
    "wof:placetype":"venue"
},
  "geometry": {"coordinates":[144.95645141599999,-37.8163032532],"type":"Point"}
}