{
  "type": "Feature",
  "properties": {
    "addr:full":"50 Wade St Crookwell NSW 2583",
    "addr:housenumber":"50",
    "addr:postcode":"2583",
    "addr:street":"Wade St",
    "iso:country":"AU",
    "sg:address":"50 Wade St",
    "sg:city":"Crookwell",
    "sg:classifiers":[
        {
            "category":"Retail",
            "subcategory":"Driving School",
            "type":"Services"
        }
    ],
    "sg:phone":"+61 419 169 775",
    "sg:postcode":"2583",
    "sg:province":"NSW",
    "wof:name":"Dan's Driver Training",
    "wof:placetype":"venue"
},
  "geometry": {"coordinates":[149.470535278,-34.4633178711],"type":"Point"}
}