{
  "type": "Feature",
  "properties": {
    "addr:full":"56 Lake St Loch Sport VIC 3851",
    "addr:housenumber":"56",
    "addr:postcode":"3851",
    "addr:street":"Lake St",
    "iso:country":"AU",
    "sg:address":"56 Lake St",
    "sg:city":"Loch Sport",
    "sg:classifiers":[
        {
            "category":"Real Estate",
            "subcategory":"Real Estate Agent",
            "type":"Services"
        }
    ],
    "sg:phone":"+61 3 5146 0411",
    "sg:postcode":"3851",
    "sg:province":"VIC",
    "wof:name":"Gary Powers Real Estate Pty Ltd",
    "wof:placetype":"venue"
},
  "geometry": {"coordinates":[147.57748413100001,-38.0501708984],"type":"Point"}
}