{
  "type": "Feature",
  "properties": {
    "addr:full":"16 Orchid Ave Surfers Paradise QLD 4217",
    "addr:housenumber":"16",
    "addr:postcode":"4217",
    "addr:street":"Orchid Ave",
    "iso:country":"AU",
    "sg:address":"16 Orchid Ave",
    "sg:city":"Surfers Paradise",
    "sg:classifiers":[
        {
            "category":"Banks & Credit Unions",
            "subcategory":"Bureau De Change",
            "type":"Services"
        }
    ],
    "sg:phone":"+61 7 5538 6626",
    "sg:postcode":"4217",
    "sg:province":"QLD",
    "sg:tags":[
        "currency",
        "exchange",
        "foreign"
    ],
    "wof:name":"Paradise Currency Exchange Pty Ltd",
    "wof:placetype":"venue"
},
  "geometry": {"coordinates":[153.429489136,-28.0009002686],"type":"Point"}
}