{
  "type": "Feature",
  "properties": {
    "addr:full":"Monto Rd Calliope QLD 4680",
    "addr:postcode":"4680",
    "addr:street":"Monto Rd",
    "iso:country":"AU",
    "sg:address":"Monto Rd",
    "sg:city":"Calliope",
    "sg:classifiers":[
        {
            "category":"Farming",
            "subcategory":"Livestock Farm",
            "type":"Manufacturing & Wholesale Goods"
        }
    ],
    "sg:phone":"+61 7 4975 7057",
    "sg:postcode":"4680",
    "sg:province":"QLD",
    "sg:tags":[
        "breeder",
        "horse",
        "stud"
    ],
    "wof:name":"Braid Park Shetland Stud",
    "wof:placetype":"venue"
},
  "geometry": {"coordinates":[151.21209716800001,-23.9871997833],"type":"Point"}
}