{
  "type": "Feature",
  "properties": {
    "iso:country":"AU",
    "sg:address":"Shop 3 72 Yamba Rd",
    "sg:city":"Yamba",
    "sg:classifiers":[
        {
            "category":"Personal",
            "subcategory":"Beauty Salon",
            "type":"Services"
        }
    ],
    "sg:phone":"+61 2 6646 2508",
    "sg:postcode":"2464",
    "sg:province":"NSW",
    "sg:tags":[
        "hairdresser"
    ],
    "wof:name":"Aquarius Hair Studio",
    "wof:placetype":"venue"
},
  "geometry": {"coordinates":[153.32899475100001,-29.4298400879],"type":"Point"}
}