{
  "type": "Feature",
  "properties": {
    "iso:country":"AU",
    "sg:address":"12 Protea Drv",
    "sg:city":"Bongaree",
    "sg:classifiers":[
        {
            "category":"Professional",
            "type":"Services"
        }
    ],
    "sg:phone":"+61 7 5498 9510",
    "sg:postcode":"4507",
    "sg:province":"QLD",
    "sg:tags":[
        "forwarding",
        "agent",
        "transport"
    ],
    "wof:name":"Freight Transfer Pty Ltd",
    "wof:placetype":"venue"
},
  "geometry": {"coordinates":[153.17312622099999,-27.0722637177],"type":"Point"}
}