{
  "type": "Feature",
  "properties": {
    "addr:full":"Shop 2 1257 North East Rd Ridgehaven SA 5097",
    "addr:housenumber":"shop 2 1257",
    "addr:postcode":"5097",
    "addr:street":"North East Rd",
    "iso:country":"AU",
    "sg:address":"Shop 2 1257 North East Rd",
    "sg:city":"Ridgehaven",
    "sg:classifiers":[
        {
            "category":"Personal",
            "subcategory":"Beauty Salon",
            "type":"Services"
        }
    ],
    "sg:phone":"+61 8 8265 2314",
    "sg:postcode":"5097",
    "sg:province":"SA",
    "sg:tags":[
        "hairdresser"
    ],
    "wof:name":"Hair By Joe",
    "wof:placetype":"venue"
},
  "geometry": {"coordinates":[138.71585082999999,-34.8209342957],"type":"Point"}
}