{
  "type": "Feature",
  "properties": {
    "iso:country":"AU",
    "sg:address":"RNSH Pacific Hwy St",
    "sg:city":"Leonards",
    "sg:classifiers":[
        {
            "category":"Health Services",
            "subcategory":"Doctor",
            "type":"Services"
        }
    ],
    "sg:phone":"+61 2 9926 6066",
    "sg:postcode":"1590",
    "sg:province":"NSW",
    "sg:tags":[
        "medical",
        "practitioner"
    ],
    "wof:name":"Pacific Laboratory Medicine Services",
    "wof:placetype":"venue"
},
  "geometry": {"coordinates":[151.195022583,-33.8232727051],"type":"Point"}
}