{
  "type": "Feature",
  "properties": {
    "addr:full":"25 Louise St Lalor VIC 3075",
    "addr:housenumber":"25",
    "addr:postcode":"3075",
    "addr:street":"Louise St",
    "iso:country":"AU",
    "sg:address":"25 Louise St",
    "sg:city":"Lalor",
    "sg:classifiers":[
        {
            "category":"Shopping",
            "subcategory":"Computers & Home Electronics",
            "type":"Retail Goods"
        }
    ],
    "sg:phone":"+61 3 9464 0161",
    "sg:postcode":"3075",
    "sg:province":"VIC",
    "sg:tags":[
        "hardware",
        "equipment"
    ],
    "wof:name":"Computer Frenzy",
    "wof:placetype":"venue"
},
  "geometry": {"coordinates":[145.076004028,-37.7505493164],"type":"Point"}
}