{
  "type": "Feature",
  "properties": {
    "addr:full":"130 Chetwynd St North Melbourne VIC 3051",
    "addr:housenumber":"130",
    "addr:postcode":"3051",
    "addr:street":"Chetwynd St",
    "iso:country":"AU",
    "sg:address":"130 Chetwynd St",
    "sg:city":"North Melbourne",
    "sg:classifiers":[
        {
            "category":"Wholesale",
            "subcategory":"Painting Supplies",
            "type":"Manufacturing & Wholesale Goods"
        }
    ],
    "sg:phone":"+61 3 9329 5554",
    "sg:postcode":"3051",
    "sg:province":"VIC",
    "sg:tags":[
        "product",
        "cleaning"
    ],
    "wof:name":"Central Cleaning Supplies",
    "wof:placetype":"venue"
},
  "geometry": {"coordinates":[144.95254516599999,-37.8045387268],"type":"Point"}
}