{
  "type": "Feature",
  "properties": {
    "addr:full":"2/ 9 Malvern St Bayswater VIC 3153",
    "addr:housenumber":"/ 9",
    "addr:postcode":"3153",
    "addr:street":"Malvern St",
    "iso:country":"AU",
    "sg:address":"2/ 9 Malvern St",
    "sg:city":"Bayswater",
    "sg:classifiers":[
        {
            "category":"Wholesale",
            "subcategory":"Machinery & Supplies",
            "type":"Manufacturing & Wholesale Goods"
        }
    ],
    "sg:phone":"+61 3 9729 7333",
    "sg:postcode":"3153",
    "sg:province":"VIC",
    "sg:tags":[
        "equipment",
        "pneumatic"
    ],
    "wof:name":"Eastern Hydraulics & Pneumatics Pty Ltd",
    "wof:placetype":"venue"
},
  "geometry": {"coordinates":[145.27107238799999,-37.8425216675],"type":"Point"}
}