{
  "type": "Feature",
  "properties": {
    "addr:full":"21 Raleigh Rd Sorrento WA 6020",
    "addr:housenumber":"21",
    "addr:postcode":"6020",
    "addr:street":"Raleigh Rd",
    "iso:country":"AU",
    "sg:address":"21 Raleigh Rd",
    "sg:city":"Sorrento",
    "sg:classifiers":[
        {
            "category":"Professional",
            "subcategory":"Business Services",
            "type":"Services"
        }
    ],
    "sg:phone":"+61 8 9246 3311",
    "sg:postcode":"6020",
    "sg:province":"WA",
    "sg:tags":[
        "consultant",
        "promoter",
        "entertainment"
    ],
    "wof:name":"Fairbridge Festival Incorporated",
    "wof:placetype":"venue"
},
  "geometry": {"coordinates":[115.750961304,-31.8323917389],"type":"Point"}
}