{
  "type": "Feature",
  "properties": {
    "addr:full":"Shop 17, Northgate Shopping Centre, 387 Main Rd Glenorchy TAS 7010",
    "addr:housenumber":"shop 17;387",
    "addr:postcode":"7010",
    "addr:street":"Northgate Shopping;Main Rd",
    "iso:country":"AU",
    "sg:address":"Shop 17, Northgate Shopping Centre, 387 Main Rd",
    "sg:city":"Glenorchy",
    "sg:classifiers":[
        {
            "category":"Shopping",
            "subcategory":"Shoes",
            "type":"Retail Goods"
        }
    ],
    "sg:phone":"+61 3 6273 0822",
    "sg:postcode":"7010",
    "sg:province":"TAS",
    "sg:tags":[
        "footwear"
    ],
    "wof:name":"Payless Shoes",
    "wof:placetype":"venue"
},
  "geometry": {"coordinates":[147.273345947,-42.8325614929],"type":"Point"}
}