{
  "type": "Feature",
  "properties": {
    "iso:country":"AU",
    "sg:address":"Unit 3, 189 Woodville Rd",
    "sg:city":"Villawood",
    "sg:classifiers":[
        {
            "category":"Home & Garden",
            "subcategory":"Building Materials",
            "type":"Retail Goods"
        }
    ],
    "sg:phone":"+61 2 9755 9355",
    "sg:postcode":"2163",
    "sg:province":"NSW",
    "sg:tags":[
        "merchant",
        "glass",
        "glazier"
    ],
    "wof:name":"GGA Glass And Aluminium Pty Ltd",
    "wof:placetype":"venue"
},
  "geometry": {"coordinates":[150.97962951700001,-33.8789215088],"type":"Point"}
}