{
  "type": "Feature",
  "properties": {
    "iso:country":"AU",
    "sg:address":"163 Mollison St",
    "sg:city":"Kyneton",
    "sg:classifiers":[
        {
            "category":"Professional",
            "subcategory":"Accounting & Tax Preparation",
            "type":"Services"
        }
    ],
    "sg:phone":"+61 3 5422 1966",
    "sg:postcode":"3444",
    "sg:province":"VIC",
    "sg:tags":[
        "accountant",
        "auditor"
    ],
    "wof:name":"Keena Jordan & Associates Pty Ltd",
    "wof:placetype":"venue"
},
  "geometry": {"coordinates":[144.45364379899999,-37.2460441589],"type":"Point"}
}