{
  "type": "Feature",
  "properties": {
    "iso:country":"AU",
    "sg:address":"370 Grubb Rd",
    "sg:city":"Wallington",
    "sg:classifiers":[
        {
            "category":"Real Estate",
            "subcategory":"Real Estate Agent",
            "type":"Services"
        }
    ],
    "sg:phone":"+61 3 5250 5483",
    "sg:postcode":"3221",
    "sg:province":"VIC",
    "wof:name":"Wallington Real Estate",
    "wof:placetype":"venue"
},
  "geometry": {"coordinates":[144.542084,-38.225819],"type":"Point"}
}