{
  "type": "Feature",
  "properties": {
    "addr:full":"5 Trafalgar St Wodonga VIC 3690",
    "addr:housenumber":"5",
    "addr:postcode":"3690",
    "addr:street":"Trafalgar St",
    "iso:country":"AU",
    "sg:address":"5 Trafalgar St",
    "sg:city":"Wodonga",
    "sg:classifiers":[
        {
            "category":"Manufacturing",
            "subcategory":"Motor Vehicles & Parts",
            "type":"Manufacturing & Wholesale Goods"
        }
    ],
    "sg:phone":"+61 2 6056 6131",
    "sg:postcode":"3690",
    "sg:province":"VIC",
    "sg:tags":[
        "replacement"
    ],
    "wof:name":"Trafalgar Street Dismantlers",
    "wof:placetype":"venue"
},
  "geometry": {"coordinates":[146.86306762699999,-36.1133041382],"type":"Point"}
}