{
  "type": "Feature",
  "properties": {
    "addr:full":"46 Brentwood Ave Pascoe Vale South VIC 3044",
    "addr:housenumber":"46",
    "addr:postcode":"3044",
    "addr:street":"Brentwood Ave",
    "iso:country":"AU",
    "sg:address":"46 Brentwood Ave",
    "sg:city":"Pascoe Vale South",
    "sg:classifiers":[
        {
            "category":"Building & Trades",
            "subcategory":"Construction",
            "type":"Services"
        }
    ],
    "sg:phone":"+61 3 9386 1796",
    "sg:postcode":"3044",
    "sg:province":"VIC",
    "sg:tags":[
        "polishing",
        "sanding",
        "floor"
    ],
    "wof:name":"Unlimited Floor Finishes Sanding & Polishing",
    "wof:placetype":"venue"
},
  "geometry": {"coordinates":[144.93066406200001,-37.7472763062],"type":"Point"}
}