{
  "type": "Feature",
  "properties": {
    "addr:full":"Mitchell Retail Centre Cnr Brookes & Heffernan Sts Mitchell ACT 2911",
    "addr:postcode":"2911",
    "addr:street":"Cnr",
    "iso:country":"AU",
    "sg:address":"Mitchell Retail Centre Cnr Brookes & Heffernan Sts",
    "sg:city":"Mitchell",
    "sg:classifiers":[
        {
            "category":"Personal",
            "type":"Services"
        }
    ],
    "sg:phone":"+61 1300 662 996",
    "sg:postcode":"2911",
    "sg:province":"ACT",
    "sg:tags":[
        "nappy"
    ],
    "wof:name":"Nappy Factory The",
    "wof:placetype":"venue"
},
  "geometry": {"coordinates":[149.14077758799999,-35.219417572],"type":"Point"}
}