{
  "type": "Feature",
  "properties": {
    "addr:full":"5/ 518 Goodwood Rd Daw Park SA 5041",
    "addr:housenumber":"/ 518",
    "addr:postcode":"5041",
    "addr:street":"Goodwood Rd",
    "iso:country":"AU",
    "sg:address":"5/ 518 Goodwood Rd",
    "sg:city":"Daw Park",
    "sg:classifiers":[
        {
            "category":"Professional",
            "subcategory":"Business Services",
            "type":"Services"
        }
    ],
    "sg:phone":"+61 8 8271 3999",
    "sg:postcode":"5041",
    "sg:province":"SA",
    "sg:tags":[
        "drafting"
    ],
    "wof:name":"Draftech SA Pty Ltd",
    "wof:placetype":"venue"
},
  "geometry": {"coordinates":[138.59153699999999,-34.978252],"type":"Point"}
}