{
  "type": "Feature",
  "properties": {
    "iso:country":"AU",
    "sg:address":"58 Alnwick Rd",
    "sg:city":"Millers Forest",
    "sg:classifiers":[
        {
            "category":"Utilities",
            "subcategory":"Water",
            "type":"Services"
        }
    ],
    "sg:phone":"+61 2 4987 3722",
    "sg:postcode":"2324",
    "sg:province":"NSW",
    "sg:tags":[
        "hot",
        "system"
    ],
    "wof:name":"Bamback Gordon",
    "wof:placetype":"venue"
},
  "geometry": {"coordinates":[151.70668029800001,-32.7759552002],"type":"Point"}
}