{
  "type": "Feature",
  "properties": {
    "addr:full":"Reply Paid 6111 Adelaide SA 5000",
    "addr:housenumber":"6111",
    "addr:postcode":"5000",
    "addr:street":"Paid",
    "iso:country":"AU",
    "sg:address":"Reply Paid 6111",
    "sg:city":"Adelaide",
    "sg:classifiers":[
        {
            "category":"Insurance",
            "subcategory":"Health Insurance",
            "type":"Services"
        }
    ],
    "sg:phone":"+61 1800 603 603",
    "sg:postcode":"5000",
    "sg:province":"SA",
    "wof:name":"Police Health Fund",
    "wof:placetype":"venue"
},
  "geometry": {"coordinates":[138.60076904300001,-34.9256401062],"type":"Point"}
}