{
  "type": "Feature",
  "properties": {
    "addr:full":"174 Pacific Hwy North Coffs Harbour NSW 2450",
    "addr:housenumber":"174",
    "addr:postcode":"2450",
    "addr:street":"Pacific Hwy North",
    "iso:country":"AU",
    "sg:address":"174 Pacific Hwy",
    "sg:city":"North Coffs Harbour",
    "sg:classifiers":[
        {
            "category":"Health Services",
            "subcategory":"Chiropractor",
            "type":"Services"
        }
    ],
    "sg:phone":"+61 2 6652 4025",
    "sg:postcode":"2450",
    "sg:province":"NSW",
    "wof:name":"Patterson Jason",
    "wof:placetype":"venue"
},
  "geometry": {"coordinates":[153.10609400000001,-30.303734],"type":"Point"}
}