{
  "type": "Feature",
  "properties": {
    "addr:full":"31 Spark St Earlwood NSW 2206",
    "addr:housenumber":"31",
    "addr:postcode":"2206",
    "addr:street":"Spark St",
    "iso:country":"AU",
    "sg:address":"31 Spark St",
    "sg:city":"Earlwood",
    "sg:classifiers":[
        {
            "category":"Utilities",
            "type":"Services"
        }
    ],
    "sg:phone":"+61 412 670 217",
    "sg:postcode":"2206",
    "sg:province":"NSW",
    "sg:tags":[
        "refrigeration",
        "industrial",
        "commercial",
        "retail"
    ],
    "wof:name":"Chronakis Peter Refrigeration",
    "wof:placetype":"venue"
},
  "geometry": {"coordinates":[151.119675,-33.923485],"type":"Point"}
}