{
  "type": "Feature",
  "properties": {
    "addr:full":"PO Box 47 Mundaring WA 6073",
    "addr:postcode":"6073",
    "iso:country":"AU",
    "sg:address":"PO Box 47",
    "sg:city":"Mundaring",
    "sg:classifiers":[
        {
            "category":"Personal",
            "type":"Services"
        }
    ],
    "sg:phone":"+61 8 9295 0307",
    "sg:postcode":"6073",
    "sg:province":"WA",
    "sg:tags":[
        "gift"
    ],
    "wof:name":"Mugshots",
    "wof:placetype":"venue"
},
  "geometry": {"coordinates":[116.167037964,-31.921880722],"type":"Point"}
}