{
  "type": "Feature",
  "properties": {
    "iso:country":"AU",
    "sg:address":"417 High St",
    "sg:city":"Maitland",
    "sg:classifiers":[
        {
            "category":"Banks & Credit Unions",
            "subcategory":"Financial Services",
            "type":"Services"
        }
    ],
    "sg:phone":"+61 2 4933 8044",
    "sg:postcode":"2320",
    "sg:province":"NSW",
    "sg:tags":[
        "building",
        "society"
    ],
    "wof:name":"Maitland Mutual Building Society Limited",
    "wof:placetype":"venue"
},
  "geometry": {"coordinates":[151.55458068900001,-32.7317466736],"type":"Point"}
}