{
  "type": "Feature",
  "properties": {
    "addr:full":"89f Hampton Rd Fremantle WA 6160",
    "addr:housenumber":"89f",
    "addr:postcode":"6160",
    "addr:street":"Hampton Rd",
    "iso:country":"AU",
    "sg:address":"89f Hampton Rd",
    "sg:city":"Fremantle",
    "sg:classifiers":[
        {
            "category":"Fast Food",
            "type":"Food & Drink"
        }
    ],
    "sg:phone":"+61 8 9335 7251",
    "sg:postcode":"6160",
    "sg:province":"WA",
    "sg:tags":[
        "away",
        "take"
    ],
    "wof:name":"Domenics Take Away Foods",
    "wof:placetype":"venue"
},
  "geometry": {"coordinates":[115.756248,-32.059006],"type":"Point"}
}