{
  "type": "Feature",
  "properties": {
    "addr:full":"Unit 1/ 2 Deborah Ave Bentleigh East VIC 3165",
    "addr:housenumber":"2",
    "addr:postcode":"3165",
    "addr:street":"Deborah Ave",
    "iso:country":"AU",
    "sg:address":"Unit 1/ 2 Deborah Ave",
    "sg:city":"Bentleigh East",
    "sg:classifiers":[
        {
            "category":"Professional",
            "subcategory":"Accounting & Tax Preparation",
            "type":"Services"
        }
    ],
    "sg:phone":"+61 3 9563 8514",
    "sg:postcode":"3165",
    "sg:province":"VIC",
    "sg:tags":[
        "bookkeeping"
    ],
    "wof:name":"M & P Business Services",
    "wof:placetype":"venue"
},
  "geometry": {"coordinates":[145.05917358400001,-37.9228286743],"type":"Point"}
}