{
  "type": "Feature",
  "properties": {
    "iso:country":"AU",
    "sg:address":"Suite 10/ 17-19 Knox St",
    "sg:city":"Double Bay",
    "sg:classifiers":[
        {
            "category":"Professional",
            "subcategory":"Business Services",
            "type":"Services"
        }
    ],
    "sg:phone":"+61 2 9362 5844",
    "sg:postcode":"2028",
    "sg:province":"NSW",
    "sg:tags":[
        "management",
        "event"
    ],
    "wof:name":"Divine Image",
    "wof:placetype":"venue"
},
  "geometry": {"coordinates":[151.24270629899999,-33.8768806458],"type":"Point"}
}