{
  "type": "Feature",
  "properties": {
    "addr:full":"1 Cadell St Seaview Downs SA 5049",
    "addr:housenumber":"1",
    "addr:postcode":"5049",
    "addr:street":"Cadell St",
    "iso:country":"AU",
    "sg:address":"1 Cadell St",
    "sg:city":"Seaview Downs",
    "sg:classifiers":[
        {
            "category":"Utilities",
            "subcategory":"Natural Gas",
            "type":"Services"
        }
    ],
    "sg:phone":"+61 8 8377 0962",
    "sg:postcode":"5049",
    "sg:province":"SA",
    "sg:tags":[
        "solid",
        "plasterer"
    ],
    "wof:name":"McGovern's Plastering",
    "wof:placetype":"venue"
},
  "geometry": {"coordinates":[138.54184000000001,-35.032162],"type":"Point"}
}