{
  "type": "Feature",
  "properties": {
    "addr:full":"8 Front St Mossman QLD 4873",
    "addr:housenumber":"8",
    "addr:postcode":"4873",
    "addr:street":"Front St",
    "iso:country":"AU",
    "sg:address":"8 Front St",
    "sg:city":"Mossman",
    "sg:classifiers":[
        {
            "category":"Health Services",
            "subcategory":"Health Practitioner",
            "type":"Services"
        }
    ],
    "sg:phone":"+61 7 4098 3379",
    "sg:postcode":"4873",
    "sg:province":"QLD",
    "sg:tags":[
        "naturopath"
    ],
    "wof:name":"J R Wellness and Anti-Ageing Clinic-Roy J Castel",
    "wof:placetype":"venue"
},
  "geometry": {"coordinates":[145.37385559099999,-16.4597625732],"type":"Point"}
}