{
  "type": "Feature",
  "properties": {
    "iso:country":"AU",
    "sg:address":"Level 1, 893 South Rd",
    "sg:city":"Clarence Gardens",
    "sg:classifiers":[
        {
            "category":"Travel",
            "subcategory":"Hotels & Motels",
            "type":"Entertainment"
        }
    ],
    "sg:phone":"+61 8 8293 8702",
    "sg:postcode":"5039",
    "sg:province":"SA",
    "sg:tags":[
        "pub"
    ],
    "wof:name":"Toucan Hotel Group",
    "wof:placetype":"venue"
},
  "geometry": {"coordinates":[138.573654175,-34.9740524292],"type":"Point"}
}