{
  "type": "Feature",
  "properties": {
    "addr:full":"Elizabeth St Korumburra VIC 3950",
    "addr:postcode":"3950",
    "addr:street":"Elizabeth St",
    "iso:country":"AU",
    "sg:address":"Elizabeth St",
    "sg:city":"Korumburra",
    "sg:classifiers":[
        {
            "category":"Sports & Exercise",
            "subcategory":"Sports Center",
            "type":"Entertainment"
        }
    ],
    "sg:phone":"+61 3 5655 2112",
    "sg:postcode":"3950",
    "sg:province":"VIC",
    "sg:tags":[
        "ground"
    ],
    "wof:name":"Korumburra Indoor Recreation Centre",
    "wof:placetype":"venue"
},
  "geometry": {"coordinates":[145.82281494099999,-38.4323501587],"type":"Point"}
}