{
  "type": "Feature",
  "properties": {
    "addr:full":"43 A Lancelot St Five Dock NSW 2046",
    "addr:housenumber":"43 a",
    "addr:postcode":"2046",
    "addr:street":"Lancelot St",
    "iso:country":"AU",
    "sg:address":"43 A Lancelot St",
    "sg:city":"Five Dock",
    "sg:classifiers":[
        {
            "category":"Social Services",
            "subcategory":"Child Care",
            "type":"Services"
        }
    ],
    "sg:phone":"+61 2 9712 1293",
    "sg:postcode":"2046",
    "sg:province":"NSW",
    "wof:name":"Happy Little Campers",
    "wof:placetype":"venue"
},
  "geometry": {"coordinates":[151.12518299999999,-33.867188],"type":"Point"}
}