{
  "type": "Feature",
  "properties": {
    "iso:country":"AU",
    "sg:address":"Shp 3 56 Durlacher St",
    "sg:city":"Geraldton",
    "sg:classifiers":[
        {
            "category":"Fast Food",
            "type":"Food & Drink"
        }
    ],
    "sg:phone":"+61 8 9923 9555",
    "sg:postcode":"6530",
    "sg:province":"WA",
    "sg:tags":[
        "away",
        "take"
    ],
    "wof:name":"Sun City Mexican Italian",
    "wof:placetype":"venue"
},
  "geometry": {"coordinates":[114.612312317,-28.7738323212],"type":"Point"}
}