{
  "type": "Feature",
  "properties": {
    "iso:country":"AU",
    "sg:address":"20 Deblin Drv",
    "sg:city":"Narre Warren",
    "sg:classifiers":[
        {
            "category":"Utilities",
            "subcategory":"Water",
            "type":"Services"
        }
    ],
    "sg:phone":"+61 3 8790 1711",
    "sg:postcode":"3805",
    "sg:province":"VIC",
    "sg:tags":[
        "equipment",
        "treatment"
    ],
    "wof:name":"Clevertek",
    "wof:placetype":"venue"
},
  "geometry": {"coordinates":[145.300217,-38.026653],"type":"Point"}
}