{
  "type": "Feature",
  "properties": {
    "iso:country":"AU",
    "sg:address":"Rp 131457",
    "sg:city":"Highland Park",
    "sg:classifiers":[
        {
            "category":"Retail",
            "subcategory":"Auto Repair",
            "type":"Services"
        }
    ],
    "sg:phone":"+61 7 5500 4758",
    "sg:postcode":"4211",
    "sg:province":"QLD",
    "sg:tags":[
        "camper-trailers",
        "caravan",
        "servicing"
    ],
    "wof:name":"Hinterland Outdoors Pty Ltd",
    "wof:placetype":"venue"
},
  "geometry": {"coordinates":[153.33439636200001,-28.0143604279],"type":"Point"}
}