{
  "type": "Feature",
  "properties": {
    "addr:full":"34 Chalcedony St Eagle Vale NSW 2558",
    "addr:housenumber":"34",
    "addr:postcode":"2558",
    "addr:street":"Chalcedony St",
    "iso:country":"AU",
    "sg:address":"34 Chalcedony St",
    "sg:city":"Eagle Vale",
    "sg:classifiers":[
        {
            "category":"Manufacturing",
            "subcategory":"Paper Products",
            "type":"Manufacturing & Wholesale Goods"
        }
    ],
    "sg:phone":"+61 2 9829 2117",
    "sg:postcode":"2558",
    "sg:province":"NSW",
    "sg:tags":[
        "building",
        "fibre",
        "cement"
    ],
    "wof:name":"GRC Industries Pty Ltd",
    "wof:placetype":"venue"
},
  "geometry": {"coordinates":[150.82032775900001,-34.0371894836],"type":"Point"}
}