{
  "type": "Feature",
  "properties": {
    "iso:country":"AU",
    "sg:address":"40 Albion St",
    "sg:city":"Roselands",
    "sg:classifiers":[
        {
            "category":"Home & Garden",
            "subcategory":"Building Materials",
            "type":"Retail Goods"
        }
    ],
    "sg:phone":"+61 2 9759 6524",
    "sg:postcode":"2196",
    "sg:province":"NSW",
    "sg:tags":[
        "lawn",
        "cutting",
        "maintenance"
    ],
    "wof:name":"Gray L R",
    "wof:placetype":"venue"
},
  "geometry": {"coordinates":[151.077606,-33.93438],"type":"Point"}
}