{
  "type": "Feature",
  "properties": {
    "addr:full":"PO Box 433 Sandy Bay TAS 7006",
    "addr:postcode":"7006",
    "iso:country":"AU",
    "sg:address":"PO Box 433",
    "sg:city":"Sandy Bay",
    "sg:classifiers":[
        {
            "category":"Building & Trades",
            "subcategory":"Landscaping Services",
            "type":"Services"
        }
    ],
    "sg:phone":"+61 418 144 969",
    "sg:postcode":"7006",
    "sg:province":"TAS",
    "sg:tags":[
        "gardener"
    ],
    "wof:name":"Hedge Cutter The",
    "wof:placetype":"venue"
},
  "geometry": {"coordinates":[147.35438537600001,-42.9128265381],"type":"Point"}
}