{
  "type": "Feature",
  "properties": {
    "addr:full":"12 Anthony St Toowoomba QLD 4350",
    "addr:housenumber":"12",
    "addr:postcode":"4350",
    "addr:street":"Anthony St",
    "iso:country":"AU",
    "sg:address":"12 Anthony St",
    "sg:city":"Toowoomba",
    "sg:classifiers":[
        {
            "category":"Autos & Motor Vehicles",
            "subcategory":"Auto Supplies",
            "type":"Retail Goods"
        }
    ],
    "sg:phone":"+61 7 4638 3888",
    "sg:postcode":"4350",
    "sg:province":"QLD",
    "sg:tags":[
        "tyre"
    ],
    "wof:name":"Mr Tyre",
    "wof:placetype":"venue"
},
  "geometry": {"coordinates":[151.95225500000001,-27.568447],"type":"Point"}
}