{
  "type": "Feature",
  "properties": {
    "iso:country":"AU",
    "sg:address":"PO Box 2077",
    "sg:city":"High Wycombe",
    "sg:classifiers":[
        {
            "category":"Farming",
            "subcategory":"Fish & Marine Products",
            "type":"Manufacturing & Wholesale Goods"
        }
    ],
    "sg:phone":"+61 438 130 469",
    "sg:postcode":"6057",
    "sg:province":"WA",
    "sg:tags":[
        "fibre",
        "hemp",
        "oil"
    ],
    "wof:name":"Millennium Clothing",
    "wof:placetype":"venue"
},
  "geometry": {"coordinates":[116.008079529,-31.9469680786],"type":"Point"}
}