{
  "type": "Feature",
  "properties": {
    "addr:full":"38 Crescent Rd Newport NSW 2106",
    "addr:housenumber":"38",
    "addr:postcode":"2106",
    "addr:street":"Crescent Rd",
    "iso:country":"AU",
    "sg:address":"38 Crescent Rd",
    "sg:city":"Newport",
    "sg:classifiers":[
        {
            "category":"Utilities",
            "subcategory":"Electric",
            "type":"Services"
        }
    ],
    "sg:phone":"+61 411 706 259",
    "sg:postcode":"2106",
    "sg:province":"NSW",
    "sg:tags":[
        "electrical",
        "contractor"
    ],
    "wof:name":"De Klerk Paddy",
    "wof:placetype":"venue"
},
  "geometry": {"coordinates":[151.31237793,-33.6683959961],"type":"Point"}
}