{
  "type": "Feature",
  "properties": {
    "addr:full":"19 Railway Pde Kogarah NSW 2217",
    "addr:housenumber":"19",
    "addr:postcode":"2217",
    "addr:street":"Railway Pde",
    "iso:country":"AU",
    "sg:address":"19 Railway Pde",
    "sg:city":"Kogarah",
    "sg:classifiers":[
        {
            "category":"Personal",
            "subcategory":"Beauty Salon",
            "type":"Services"
        }
    ],
    "sg:phone":"+61 2 9587 2118",
    "sg:postcode":"2217",
    "sg:province":"NSW",
    "wof:name":"The Ritz Relaxation and Wellbeing Skin Care Clinic",
    "wof:placetype":"venue"
},
  "geometry": {"coordinates":[151.132553,-33.963112],"type":"Point"}
}