{
  "type": "Feature",
  "properties": {
    "iso:country":"AU",
    "sg:address":"163 Grange Rd",
    "sg:city":"Flinders Park",
    "sg:classifiers":[
        {
            "category":"Banks & Credit Unions",
            "subcategory":"Financial Services",
            "type":"Services"
        }
    ],
    "sg:phone":"+61 8 8224 8499",
    "sg:postcode":"5025",
    "sg:province":"SA",
    "sg:tags":[
        "franchising"
    ],
    "wof:name":"Altura Vending Solutions",
    "wof:placetype":"venue"
},
  "geometry": {"coordinates":[138.54881286599999,-34.9045257568],"type":"Point"}
}