{
  "type": "Feature",
  "properties": {
    "addr:full":"PO Box 371 Kangaroo Ground VIC 3097",
    "addr:postcode":"3097",
    "iso:country":"AU",
    "sg:address":"PO Box 371",
    "sg:city":"Kangaroo Ground",
    "sg:classifiers":[
        {
            "category":"Utilities",
            "subcategory":"Electric",
            "type":"Services"
        }
    ],
    "sg:phone":"+61 417 586 253",
    "sg:postcode":"3097",
    "sg:province":"VIC",
    "sg:tags":[
        "electrical",
        "contractor"
    ],
    "wof:name":"Craig Smith Electrical Services",
    "wof:placetype":"venue"
},
  "geometry": {"coordinates":[145.215667725,-37.6913490295],"type":"Point"}
}