{
  "type": "Feature",
  "properties": {
    "iso:country":"AU",
    "sg:address":"33 Queensport Rd",
    "sg:city":"Murarrie",
    "sg:classifiers":[
        {
            "category":"Food & Beverages",
            "subcategory":"Specialty",
            "type":"Retail Goods"
        }
    ],
    "sg:phone":"+61 7 3890 0015",
    "sg:postcode":"4172",
    "sg:province":"QLD",
    "sg:tags":[
        "delicacy"
    ],
    "wof:name":"Hakka Pty Ltd",
    "wof:placetype":"venue"
},
  "geometry": {"coordinates":[153.10514831500001,-27.4635410309],"type":"Point"}
}