{
  "type": "Feature",
  "properties": {
    "addr:full":"Suite 3 12 Mitford St St Kilda VIC 3182",
    "addr:housenumber":"12",
    "addr:postcode":"3182",
    "addr:street":"Mitford St",
    "iso:country":"AU",
    "sg:address":"Suite 3 12 Mitford St St",
    "sg:city":"Kilda",
    "sg:classifiers":[
        {
            "category":"Professional",
            "subcategory":"Art Services",
            "type":"Services"
        }
    ],
    "sg:phone":"+61 3 9534 5881",
    "sg:postcode":"3182",
    "sg:province":"VIC",
    "sg:tags":[
        "graphic",
        "designer"
    ],
    "wof:name":"Resolution Graphics Pty Ltd",
    "wof:placetype":"venue"
},
  "geometry": {"coordinates":[144.98135375999999,-37.8711662292],"type":"Point"}
}