{
  "type": "Feature",
  "properties": {
    "iso:country":"AU",
    "sg:address":"12 Nerang-Broadbeach Rd",
    "sg:city":"Nerang",
    "sg:classifiers":[
        {
            "category":"Health Services",
            "subcategory":"Dentist",
            "type":"Services"
        }
    ],
    "sg:phone":"+61 7 5596 3299",
    "sg:postcode":"4211",
    "sg:province":"QLD",
    "sg:tags":[
        "dental",
        "emergency"
    ],
    "wof:name":"Absolute Dental Care",
    "wof:placetype":"venue"
},
  "geometry": {"coordinates":[153.343139648,-27.9937229156],"type":"Point"}
}