{
  "type": "Feature",
  "properties": {
    "addr:full":"Shp3/ 85 Albert St Moe VIC 3825",
    "addr:housenumber":"85",
    "addr:postcode":"3825",
    "addr:street":"Albert St",
    "iso:country":"AU",
    "sg:address":"Shp3/ 85 Albert St",
    "sg:city":"Moe",
    "sg:classifiers":[
        {
            "category":"Shopping",
            "subcategory":"Clothing, Apparel, & Fashions",
            "type":"Retail Goods"
        }
    ],
    "sg:phone":"+61 3 5127 8960",
    "sg:postcode":"3825",
    "sg:province":"VIC",
    "sg:tags":[
        "lady",
        "wear"
    ],
    "wof:name":"House of Frocks",
    "wof:placetype":"venue"
},
  "geometry": {"coordinates":[146.260895,-38.174732],"type":"Point"}
}