{
  "type": "Feature",
  "properties": {
    "addr:full":"16 Wagner St Mudgeeraba QLD 4213",
    "addr:housenumber":"16",
    "addr:postcode":"4213",
    "addr:street":"Wagner St",
    "iso:country":"AU",
    "sg:address":"16 Wagner St",
    "sg:city":"Mudgeeraba",
    "sg:classifiers":[
        {
            "category":"Professional",
            "subcategory":"Computer Services",
            "type":"Services"
        }
    ],
    "sg:phone":"+61 7 5559 0500",
    "sg:postcode":"4213",
    "sg:province":"QLD",
    "sg:tags":[
        "equipment",
        "networking",
        "installation"
    ],
    "wof:name":"Foreman Data Pty Ltd",
    "wof:placetype":"venue"
},
  "geometry": {"coordinates":[153.367385864,-28.0893211365],"type":"Point"}
}