{
  "type": "Feature",
  "properties": {
    "addr:full":"20 George St Launceston TAS 7250",
    "addr:housenumber":"20",
    "addr:postcode":"7250",
    "addr:street":"George St",
    "iso:country":"AU",
    "sg:address":"20 George St",
    "sg:city":"Launceston",
    "sg:classifiers":[
        {
            "category":"Communications",
            "subcategory":"Film & Video Production",
            "type":"Services"
        }
    ],
    "sg:phone":"+61 3 6331 9191",
    "sg:postcode":"7250",
    "sg:province":"TAS",
    "sg:tags":[
        "trestle",
        "ladders",
        "steps",
        "accessory"
    ],
    "wof:name":"AM-Boss Access Ladders Pty Ltd",
    "wof:placetype":"venue"
},
  "geometry": {"coordinates":[147.13796997099999,-41.4334487915],"type":"Point"}
}