{
  "type": "Feature",
  "properties": {
    "iso:country":"AU",
    "sg:address":"40 Melville St",
    "sg:city":"Numurkah",
    "sg:classifiers":[
        {
            "category":"Personal",
            "subcategory":"Beauty Salon",
            "type":"Services"
        }
    ],
    "sg:phone":"+61 3 5862 1874",
    "sg:postcode":"3636",
    "sg:province":"VIC",
    "sg:tags":[
        "hairdresser"
    ],
    "wof:name":"Reapers Hairdressing",
    "wof:placetype":"venue"
},
  "geometry": {"coordinates":[145.44224548299999,-36.0897521973],"type":"Point"}
}