{
  "type": "Feature",
  "properties": {
    "addr:full":"233 Union Rd Surrey Hills VIC 3127",
    "addr:housenumber":"233",
    "addr:postcode":"3127",
    "addr:street":"Union Rd",
    "iso:country":"AU",
    "sg:address":"233 Union Rd",
    "sg:city":"Surrey Hills",
    "sg:classifiers":[
        {
            "category":"Professional",
            "subcategory":"Accounting & Tax Preparation",
            "type":"Services"
        }
    ],
    "sg:phone":"+61 3 9899 1466",
    "sg:postcode":"3127",
    "sg:province":"VIC",
    "sg:tags":[
        "consultant",
        "taxation"
    ],
    "wof:name":"James H Walker",
    "wof:placetype":"venue"
},
  "geometry": {"coordinates":[145.099441528,-37.8154907227],"type":"Point"}
}