{
  "type": "Feature",
  "properties": {
    "addr:full":"179 Dandaraga Rd Mirrabooka NSW 2264",
    "addr:housenumber":"179",
    "addr:postcode":"2264",
    "addr:street":"Dandaraga Rd",
    "iso:country":"AU",
    "sg:address":"179 Dandaraga Rd",
    "sg:city":"Mirrabooka",
    "sg:classifiers":[
        {
            "category":"Building & Trades",
            "subcategory":"Pest Control",
            "type":"Services"
        }
    ],
    "sg:phone":"+61 2 4970 5757",
    "sg:postcode":"2264",
    "sg:province":"NSW",
    "wof:name":"Masterkill Pest Control",
    "wof:placetype":"venue"
},
  "geometry": {"coordinates":[151.54997299999999,-33.113567],"type":"Point"}
}