{
  "type": "Feature",
  "properties": {
    "iso:country":"AU",
    "sg:address":"81 Denison St",
    "sg:city":"Tamworth",
    "sg:classifiers":[
        {
            "category":"Social Services",
            "subcategory":"Child Care",
            "type":"Services"
        }
    ],
    "sg:phone":"+61 2 6765 4599",
    "sg:postcode":"2340",
    "sg:province":"NSW",
    "wof:name":"Tamworth Family Day Care",
    "wof:placetype":"venue"
},
  "geometry": {"coordinates":[150.91790771500001,-31.0941314697],"type":"Point"}
}