{
  "type": "Feature",
  "properties": {
    "iso:country":"AU",
    "sg:address":"Wyalong & Dunmore Sts",
    "sg:city":"Woy Woy",
    "sg:classifiers":[
        {
            "category":"Education",
            "subcategory":"Dance Studio",
            "type":"Public Place"
        }
    ],
    "sg:phone":"+61 2 4344 5871",
    "sg:postcode":"2256",
    "sg:province":"NSW",
    "sg:tags":[
        "venue",
        "tuition"
    ],
    "wof:name":"New Moves",
    "wof:placetype":"venue"
},
  "geometry": {"coordinates":[151.32853698700001,-33.502872467],"type":"Point"}
}