{
  "type": "Feature",
  "properties": {
    "iso:country":"AU",
    "sg:address":"PO Box 956",
    "sg:city":"Benalla",
    "sg:classifiers":[
        {
            "category":"Building & Trades",
            "subcategory":"Construction",
            "type":"Services"
        }
    ],
    "sg:phone":"+61 3 5762 3114",
    "sg:postcode":"3672",
    "sg:province":"VIC",
    "sg:tags":[
        "contractor"
    ],
    "wof:name":"GLR Australia",
    "wof:placetype":"venue"
},
  "geometry": {"coordinates":[146.006805,-36.57111],"type":"Point"}
}