{
  "type": "Feature",
  "properties": {
    "iso:country":"AU",
    "sg:address":"28 Leighton Pl",
    "sg:city":"Hornsby",
    "sg:classifiers":[
        {
            "category":"Wholesale",
            "subcategory":"Drugs",
            "type":"Manufacturing & Wholesale Goods"
        }
    ],
    "sg:phone":"+61 2 9477 5560",
    "sg:postcode":"2077",
    "sg:province":"NSW",
    "sg:tags":[
        "wholesaler",
        "pharmaceutical",
        "product",
        "mfrs"
    ],
    "wof:name":"Australian Blister Sealing",
    "wof:placetype":"venue"
},
  "geometry": {"coordinates":[151.11579895,-33.695728302],"type":"Point"}
}