{
  "type": "Feature",
  "properties": {
    "addr:full":"689 Canterbury Rd Surrey Hills VIC 3127",
    "addr:housenumber":"689",
    "addr:postcode":"3127",
    "addr:street":"Canterbury Rd",
    "iso:country":"AU",
    "sg:address":"689 Canterbury Rd",
    "sg:city":"Surrey Hills",
    "sg:classifiers":[
        {
            "category":"Wholesale",
            "subcategory":"Auto Parts",
            "type":"Manufacturing & Wholesale Goods"
        }
    ],
    "sg:phone":"+61 3 9898 0750",
    "sg:postcode":"3127",
    "sg:province":"VIC",
    "sg:tags":[
        "transmission",
        "automotive",
        "truck"
    ],
    "wof:name":"Power Train Products Pty Ltd",
    "wof:placetype":"venue"
},
  "geometry": {"coordinates":[145.10234069800001,-37.8263931274],"type":"Point"}
}