{
  "type": "Feature",
  "properties": {
    "addr:full":"2 / 24 Victory Way Highton VIC 3216",
    "addr:housenumber":"/ 24",
    "addr:postcode":"3216",
    "addr:street":"Victory Way",
    "iso:country":"AU",
    "sg:address":"2 / 24 Victory Way",
    "sg:city":"Highton",
    "sg:classifiers":[
        {
            "category":"Building & Trades",
            "subcategory":"Construction",
            "type":"Services"
        }
    ],
    "sg:phone":"+61 3 5243 2401",
    "sg:postcode":"3216",
    "sg:province":"VIC",
    "sg:tags":[
        "earth",
        "excavating",
        "moving",
        "contractor"
    ],
    "wof:name":"Riverside Drainage",
    "wof:placetype":"venue"
},
  "geometry": {"coordinates":[144.30918884299999,-38.1669425964],"type":"Point"}
}