{
  "type": "Feature",
  "properties": {
    "iso:country":"AU",
    "sg:address":"Suite 4/ 18-28 Skye Rd",
    "sg:city":"Frankston",
    "sg:classifiers":[
        {
            "category":"Organizations",
            "subcategory":"Non-profit Organization",
            "type":"Services"
        }
    ],
    "sg:phone":"+61 3 9783 4866",
    "sg:postcode":"3199",
    "sg:province":"VIC",
    "sg:tags":[
        "support",
        "disability",
        "organisation"
    ],
    "wof:name":"Select Services Victoria Pty Ltd",
    "wof:placetype":"venue"
},
  "geometry": {"coordinates":[145.133102417,-38.1306228638],"type":"Point"}
}