{
  "type": "Feature",
  "properties": {
    "addr:full":"PO Box 1858 Gawler SA 5118",
    "addr:postcode":"5118",
    "iso:country":"AU",
    "sg:address":"PO Box 1858",
    "sg:city":"Gawler",
    "sg:classifiers":[
        {
            "category":"Retail",
            "subcategory":"Funeral Services",
            "type":"Services"
        }
    ],
    "sg:phone":"+61 417 841 966",
    "sg:postcode":"5118",
    "sg:province":"SA",
    "sg:tags":[
        "supply"
    ],
    "wof:name":"Butterfly Memorial Productions",
    "wof:placetype":"venue"
},
  "geometry": {"coordinates":[138.72822600000001,-34.596329],"type":"Point"}
}