{
  "type": "Feature",
  "properties": {
    "addr:full":"Level 1 828 Pacific Hwy Gordon NSW 2072",
    "addr:housenumber":"828",
    "addr:postcode":"2072",
    "addr:street":"Pacific Hwy",
    "iso:country":"AU",
    "sg:address":"Level 1 828 Pacific Hwy",
    "sg:city":"Gordon",
    "sg:classifiers":[
        {
            "category":"Real Estate",
            "subcategory":"Real Estate Agent",
            "type":"Services"
        }
    ],
    "sg:phone":"+61 2 9499 5066",
    "sg:postcode":"2072",
    "sg:province":"NSW",
    "wof:name":"Monarch (Sales) Pty Ltd",
    "wof:placetype":"venue"
},
  "geometry": {"coordinates":[151.151611328,-33.7539215088],"type":"Point"}
}