{
  "type": "Feature",
  "properties": {
    "addr:full":"PO Box 407 Quinns Rocks WA 6030",
    "addr:postcode":"6030",
    "iso:country":"AU",
    "sg:address":"PO Box 407",
    "sg:city":"Quinns Rocks",
    "sg:classifiers":[
        {
            "category":"Commercial Area",
            "type":"Public Place"
        }
    ],
    "sg:phone":"+61 8 9305 2888",
    "sg:postcode":"6030",
    "sg:province":"WA",
    "sg:tags":[
        "heavy",
        "carrier"
    ],
    "wof:name":"Golden Pilots Pty Ltd",
    "wof:placetype":"venue"
},
  "geometry": {"coordinates":[115.70501709,-31.6646404266],"type":"Point"}
}