{
  "type": "Feature",
  "properties": {
    "addr:full":"Unit 12, 60 Langridge St Collingwood VIC 3066",
    "addr:housenumber":"60",
    "addr:postcode":"3066",
    "addr:street":"Langridge St",
    "iso:country":"AU",
    "sg:address":"Unit 12, 60 Langridge St",
    "sg:city":"Collingwood",
    "sg:classifiers":[
        {
            "category":"Professional",
            "subcategory":"Art Services",
            "type":"Services"
        }
    ],
    "sg:phone":"+61 3 9415 6886",
    "sg:postcode":"3066",
    "sg:province":"VIC",
    "sg:tags":[
        "graphic",
        "designer"
    ],
    "wof:name":"Caridi Design",
    "wof:placetype":"venue"
},
  "geometry": {"coordinates":[144.98731994600001,-37.8065605164],"type":"Point"}
}