{
  "type": "Feature",
  "properties": {
    "addr:full":"21 Koala Pl Capalaba QLD 4157",
    "addr:housenumber":"21",
    "addr:postcode":"4157",
    "addr:street":"Koala Pl",
    "iso:country":"AU",
    "sg:address":"21 Koala Pl",
    "sg:city":"Capalaba",
    "sg:classifiers":[
        {
            "category":"Health Services",
            "subcategory":"Doctor",
            "type":"Services"
        }
    ],
    "sg:phone":"+61 7 3245 3010",
    "sg:postcode":"4157",
    "sg:province":"QLD",
    "sg:tags":[
        "reflexology"
    ],
    "wof:name":"Laurie Gilbert",
    "wof:placetype":"venue"
},
  "geometry": {"coordinates":[153.20213317899999,-27.551733017],"type":"Point"}
}