{
  "type": "Feature",
  "properties": {
    "addr:full":"Shop 1 500 Beaufort St Mt Lawley WA 6050",
    "addr:housenumber":"shop 1",
    "addr:postcode":"500;6050",
    "addr:street":"Beaufort St",
    "iso:country":"AU",
    "sg:address":"Shop 1 500 Beaufort St",
    "sg:city":"Mt Lawley",
    "sg:classifiers":[
        {
            "category":"Personal",
            "subcategory":"Beauty Salon",
            "type":"Services"
        }
    ],
    "sg:phone":"+61 8 9227 5797",
    "sg:postcode":"6050",
    "sg:province":"WA",
    "sg:tags":[
        "hairdresser"
    ],
    "wof:name":"Bruno & Alberto's Coiffeur",
    "wof:placetype":"venue"
},
  "geometry": {"coordinates":[115.86962127699999,-31.9386386871],"type":"Point"}
}