{
  "type": "Feature",
  "properties": {
    "addr:full":"PO Box 1224 Warners Bay NSW 2282",
    "addr:postcode":"2282",
    "iso:country":"AU",
    "sg:address":"PO Box 1224",
    "sg:city":"Warners Bay",
    "sg:classifiers":[
        {
            "category":"Building & Trades",
            "subcategory":"Construction",
            "type":"Services"
        }
    ],
    "sg:phone":"+61 1300 552 449",
    "sg:postcode":"2282",
    "sg:province":"NSW",
    "sg:tags":[
        "pool",
        "swimming"
    ],
    "wof:name":"Vision Pools Pty Ltd.",
    "wof:placetype":"venue"
},
  "geometry": {"coordinates":[151.64869689899999,-32.973110199],"type":"Point"}
}