{
  "type": "Feature",
  "properties": {
    "addr:full":"Cnr Dunbar Rd & Rose Ave Traralgon VIC 3844",
    "addr:postcode":"3844",
    "addr:street":"Cnr Dunbar Rd & Rose Ave",
    "iso:country":"AU",
    "sg:address":"Cnr Dunbar Rd & Rose Ave",
    "sg:city":"Traralgon",
    "sg:classifiers":[
        {
            "category":"Personal",
            "subcategory":"Beauty Salon",
            "type":"Services"
        }
    ],
    "sg:phone":"+61 409 504 286",
    "sg:postcode":"3844",
    "sg:province":"VIC",
    "wof:name":"Stephanie's Beauty Within",
    "wof:placetype":"venue"
},
  "geometry": {"coordinates":[146.53057861299999,-38.2071228027],"type":"Point"}
}