{
  "type": "Feature",
  "properties": {
    "addr:full":"66 Hampden Rd Battery Point TAS 7004",
    "addr:housenumber":"66",
    "addr:postcode":"7004",
    "addr:street":"Hampden Rd",
    "iso:country":"AU",
    "sg:address":"66 Hampden Rd",
    "sg:city":"Battery Point",
    "sg:classifiers":[
        {
            "category":"Real Estate",
            "subcategory":"Architect",
            "type":"Services"
        }
    ],
    "sg:phone":"+61 3 6223 2009",
    "sg:postcode":"7004",
    "sg:province":"TAS",
    "wof:name":"Preston Lane Architects",
    "wof:placetype":"venue"
},
  "geometry": {"coordinates":[147.33306884800001,-42.8899002075],"type":"Point"}
}