{
  "type": "Feature",
  "properties": {
    "iso:country":"AU",
    "sg:address":"Oakleigh Market 15 Portman St",
    "sg:city":"Oakleigh",
    "sg:classifiers":[
        {
            "category":"Food & Beverages",
            "subcategory":"Bakery",
            "type":"Retail Goods"
        }
    ],
    "sg:phone":"+61 3 9568 0986",
    "sg:postcode":"3166",
    "sg:province":"VIC",
    "sg:tags":[
        "baker"
    ],
    "wof:name":"Oakleigh Market Bakehouse",
    "wof:placetype":"venue"
},
  "geometry": {"coordinates":[145.08920288100001,-37.8998908997],"type":"Point"}
}