{
  "type": "Feature",
  "properties": {
    "iso:country":"AU",
    "sg:address":"PO Box 171",
    "sg:city":"Park Orchards",
    "sg:classifiers":[
        {
            "category":"Manufacturing",
            "subcategory":"Building Materials",
            "type":"Manufacturing & Wholesale Goods"
        }
    ],
    "sg:phone":"+61 1800 133 135",
    "sg:postcode":"3114",
    "sg:province":"VIC",
    "sg:tags":[
        "stone",
        "product",
        "supply"
    ],
    "wof:name":"Australasian Marble Suppliers",
    "wof:placetype":"venue"
},
  "geometry": {"coordinates":[145.21330261200001,-37.7759590149],"type":"Point"}
}