{
  "type": "Feature",
  "properties": {
    "iso:country":"AU",
    "sg:address":"135 Mitchell St",
    "sg:city":"Bendigo",
    "sg:classifiers":[
        {
            "category":"Personal",
            "subcategory":"Beauty Salon",
            "type":"Services"
        }
    ],
    "sg:phone":"+61 3 5441 5999",
    "sg:postcode":"3550",
    "sg:province":"VIC",
    "wof:name":"Secret Whispers",
    "wof:placetype":"venue"
},
  "geometry": {"coordinates":[144.28501892099999,-36.7663383484],"type":"Point"}
}