{
  "type": "Feature",
  "properties": {
    "addr:full":"40 William St Bowen QLD 4805",
    "addr:housenumber":"40",
    "addr:postcode":"4805",
    "addr:street":"William St",
    "iso:country":"AU",
    "sg:address":"40 William St",
    "sg:city":"Bowen",
    "sg:classifiers":[
        {
            "category":"Travel",
            "subcategory":"Travel Agent",
            "type":"Entertainment"
        }
    ],
    "sg:phone":"+61 7 4786 2835",
    "sg:postcode":"4805",
    "sg:province":"QLD",
    "sg:tags":[
        "consultant"
    ],
    "wof:name":"Bowen Travel",
    "wof:placetype":"venue"
},
  "geometry": {"coordinates":[148.245193481,-20.0141181946],"type":"Point"}
}