{
  "type": "Feature",
  "properties": {
    "addr:full":"Shp3/ 1 Hammett St Currajong QLD 4812",
    "addr:housenumber":"1",
    "addr:postcode":"4812",
    "addr:street":"Hammett St",
    "iso:country":"AU",
    "sg:address":"Shp3/ 1 Hammett St",
    "sg:city":"Currajong",
    "sg:classifiers":[
        {
            "category":"Fast Food",
            "type":"Food & Drink"
        }
    ],
    "sg:phone":"+61 7 4728 8002",
    "sg:postcode":"4812",
    "sg:province":"QLD",
    "sg:tags":[
        "away",
        "take"
    ],
    "wof:name":"Currajong Fish Bar",
    "wof:placetype":"venue"
},
  "geometry": {"coordinates":[146.77075199999999,-19.278006],"type":"Point"}
}