{
  "type": "Feature",
  "properties": {
    "addr:full":"4 Stanley Pde Caulfield North VIC 3161",
    "addr:housenumber":"4",
    "addr:postcode":"3161",
    "addr:street":"Stanley Pde",
    "iso:country":"AU",
    "sg:address":"4 Stanley Pde",
    "sg:city":"Caulfield North",
    "sg:classifiers":[
        {
            "category":"Health Services",
            "subcategory":"Doctor",
            "type":"Services"
        }
    ],
    "sg:phone":"+61 3 9500 2199",
    "sg:postcode":"3161",
    "sg:province":"VIC",
    "sg:tags":[
        "medical",
        "practitioner"
    ],
    "wof:name":"Elton V Dr",
    "wof:placetype":"venue"
},
  "geometry": {"coordinates":[145.022613525,-37.8722457886],"type":"Point"}
}