{
  "type": "Feature",
  "properties": {
    "iso:country":"AU",
    "sg:address":"Shop 5 134 Gladstone Ave",
    "sg:city":"Coniston",
    "sg:classifiers":[
        {
            "category":"Health Services",
            "subcategory":"Medical Lab",
            "type":"Services"
        }
    ],
    "sg:phone":"+61 2 4226 1811",
    "sg:postcode":"2500",
    "sg:province":"NSW",
    "sg:tags":[
        "laboratory",
        "dental"
    ],
    "wof:name":"Just Dentures",
    "wof:placetype":"venue"
},
  "geometry": {"coordinates":[150.885223,-34.436985],"type":"Point"}
}