{
  "type": "Feature",
  "properties": {
    "addr:full":"35 Pullan Pl Greenwood WA 6024",
    "addr:housenumber":"35",
    "addr:postcode":"6024",
    "addr:street":"Pullan Pl",
    "iso:country":"AU",
    "sg:address":"35 Pullan Pl",
    "sg:city":"Greenwood",
    "sg:classifiers":[
        {
            "category":"Organizations",
            "subcategory":"Professional Association",
            "type":"Services"
        }
    ],
    "sg:phone":"+61 8 9203 9444",
    "sg:postcode":"6024",
    "sg:province":"WA",
    "sg:tags":[
        "web",
        "internet"
    ],
    "wof:name":"Davies Publications",
    "wof:placetype":"venue"
},
  "geometry": {"coordinates":[115.80027008099999,-31.8315639496],"type":"Point"}
}