{
  "type": "Feature",
  "properties": {
    "addr:full":"PO Box 102 Drysdale VIC 3222",
    "addr:postcode":"3222",
    "iso:country":"AU",
    "sg:address":"PO Box 102",
    "sg:city":"Drysdale",
    "sg:classifiers":[
        {
            "category":"Retail",
            "subcategory":"Auto Repair",
            "type":"Services"
        }
    ],
    "sg:phone":"+61 3 5255 3884",
    "sg:postcode":"3222",
    "sg:province":"VIC",
    "sg:tags":[
        "repairer",
        "motor",
        "engineer"
    ],
    "wof:name":"Andersons Auto Care",
    "wof:placetype":"venue"
},
  "geometry": {"coordinates":[144.590103,-38.153461],"type":"Point"}
}