{
  "type": "Feature",
  "properties": {
    "iso:country":"AU",
    "sg:address":"Unit 1/ 5 Wenban Pl",
    "sg:city":"Wetherill Park",
    "sg:classifiers":[
        {
            "category":"Professional",
            "subcategory":"Engineering",
            "type":"Services"
        }
    ],
    "sg:phone":"+61 2 9757 1788",
    "sg:postcode":"2164",
    "sg:province":"NSW",
    "sg:tags":[
        "engineer",
        "toolmaker",
        "plastic"
    ],
    "wof:name":"Unique Tooling Pty Ltd",
    "wof:placetype":"venue"
},
  "geometry": {"coordinates":[150.904052734,-33.8378334045],"type":"Point"}
}