{
  "type": "Feature",
  "properties": {
    "addr:full":"18 Old Cougalant Rd Gisborne VIC 3437",
    "addr:housenumber":"18",
    "addr:postcode":"3437",
    "addr:street":"Old Cougalant Rd",
    "iso:country":"AU",
    "sg:address":"18 Old Cougalant Rd",
    "sg:city":"Gisborne",
    "sg:classifiers":[
        {
            "category":"Cafe",
            "type":"Food & Drink"
        }
    ],
    "sg:phone":"+61 3 5428 3565",
    "sg:postcode":"3437",
    "sg:province":"VIC",
    "wof:name":"Cafe Bizanti",
    "wof:placetype":"venue"
},
  "geometry": {"coordinates":[144.59135437,-37.4869995117],"type":"Point"}
}