{
  "type": "Feature",
  "properties": {
    "addr:full":"41-43 Seventh St East Mildura VIC 3500",
    "addr:housenumber":"41-43",
    "addr:postcode":"3500",
    "addr:street":"Seventh St East",
    "iso:country":"AU",
    "sg:address":"41-43 Seventh St East",
    "sg:city":"Mildura",
    "sg:classifiers":[
        {
            "category":"Wholesale",
            "subcategory":"Painting Supplies",
            "type":"Manufacturing & Wholesale Goods"
        }
    ],
    "sg:phone":"+61 3 5021 2722",
    "sg:postcode":"3500",
    "sg:province":"VIC",
    "sg:tags":[
        "equipment",
        "spraying"
    ],
    "wof:name":"Agg-Tech Machinery",
    "wof:placetype":"venue"
},
  "geometry": {"coordinates":[142.154098511,-34.2107391357],"type":"Point"}
}