{
  "type": "Feature",
  "properties": {
    "addr:full":"55 Maud St Fairfield West NSW 2165",
    "addr:housenumber":"55",
    "addr:postcode":"2165",
    "addr:street":"Maud St",
    "iso:country":"AU",
    "sg:address":"55 Maud St",
    "sg:city":"Fairfield West",
    "sg:classifiers":[
        {
            "category":"Retail",
            "subcategory":"Auto Repair",
            "type":"Services"
        }
    ],
    "sg:phone":"+61 2 9604 6504",
    "sg:postcode":"2165",
    "sg:province":"NSW",
    "sg:tags":[
        "body",
        "motor",
        "trimmer"
    ],
    "wof:name":"Denniss Motor Trimmers",
    "wof:placetype":"venue"
},
  "geometry": {"coordinates":[150.93263244600001,-33.8658752441],"type":"Point"}
}