{
  "type": "Feature",
  "properties": {
    "addr:full":"Cnr Southgate Ave & Corporate Drv Cannon Hill QLD 4170",
    "addr:postcode":"4170",
    "addr:street":"Cnr Southgate Ave & Corporate Drv",
    "iso:country":"AU",
    "sg:address":"Cnr Southgate Ave & Corporate Drv",
    "sg:city":"Cannon Hill",
    "sg:classifiers":[
        {
            "category":"Education",
            "subcategory":"Kindergarten",
            "type":"Public Place"
        }
    ],
    "sg:phone":"+61 7 3399 1233",
    "sg:postcode":"4170",
    "sg:province":"QLD",
    "sg:tags":[
        "pre-schools"
    ],
    "wof:name":"Tricia's Playschool",
    "wof:placetype":"venue"
},
  "geometry": {"coordinates":[153.091033936,-27.4659519196],"type":"Point"}
}