{
  "type": "Feature",
  "properties": {
    "iso:country":"AU",
    "sg:address":"1st Floor 24 Wharf St",
    "sg:city":"Port Douglas",
    "sg:classifiers":[
        {
            "category":"Personal",
            "subcategory":"Beauty Salon",
            "type":"Services"
        }
    ],
    "sg:phone":"+61 7 4099 5987",
    "sg:postcode":"4877",
    "sg:province":"QLD",
    "sg:tags":[
        "hairdresser"
    ],
    "wof:name":"The Hair Shop",
    "wof:placetype":"venue"
},
  "geometry": {"coordinates":[145.462036133,-16.4813861847],"type":"Point"}
}