{
  "type": "Feature",
  "properties": {
    "iso:country":"AU",
    "sg:address":"3 Wooraka St",
    "sg:city":"Rochedale South",
    "sg:classifiers":[
        {
            "category":"Home & Garden",
            "subcategory":"Carpets & Floor Coverings",
            "type":"Retail Goods"
        }
    ],
    "sg:phone":"+61 418 755 451",
    "sg:postcode":"4123",
    "sg:province":"QLD",
    "sg:tags":[
        "tile",
        "wall",
        "layer"
    ],
    "wof:name":"A City & Suburbs Tiling Contractors",
    "wof:placetype":"venue"
},
  "geometry": {"coordinates":[153.11997985799999,-27.6022834778],"type":"Point"}
}