{
  "type": "Feature",
  "properties": {
    "addr:full":"227 Elizabeth St Sydney NSW 2000",
    "addr:housenumber":"227",
    "addr:postcode":"2000",
    "addr:street":"Elizabeth St",
    "iso:country":"AU",
    "sg:address":"227 Elizabeth St",
    "sg:city":"Sydney",
    "sg:classifiers":[
        {
            "category":"Retail",
            "subcategory":"Repair Shop",
            "type":"Services"
        }
    ],
    "sg:phone":"+61 2 9261 3935",
    "sg:postcode":"2000",
    "sg:province":"NSW",
    "sg:tags":[
        "mending",
        "clothing",
        "alteration"
    ],
    "wof:name":"Vlada Alteration & Repairs",
    "wof:placetype":"venue"
},
  "geometry": {"coordinates":[151.20968627900001,-33.8744621277],"type":"Point"}
}