{
  "type": "Feature",
  "properties": {
    "addr:full":"U20/ 13 Swaffham Rd Minto NSW 2566",
    "addr:postcode":"2566",
    "addr:street":"/ 13 Swaffham Rd",
    "iso:country":"AU",
    "sg:address":"U20/ 13 Swaffham Rd",
    "sg:city":"Minto",
    "sg:classifiers":[
        {
            "category":"Professional",
            "subcategory":"Detective & Security Services",
            "type":"Services"
        }
    ],
    "sg:phone":"+61 2 9824 5681",
    "sg:postcode":"2566",
    "sg:province":"NSW",
    "sg:tags":[
        "consultant",
        "system"
    ],
    "wof:name":"Exico Connectors",
    "wof:placetype":"venue"
},
  "geometry": {"coordinates":[150.83515930199999,-34.0314903259],"type":"Point"}
}