{
  "type": "Feature",
  "properties": {
    "addr:full":"6- 8 Lyon Park North Ryde NSW 2113",
    "addr:housenumber":"8",
    "addr:postcode":"2113",
    "addr:street":"Lyon Park",
    "iso:country":"AU",
    "sg:address":"6- 8",
    "sg:city":"Lyon Park North Ryde",
    "sg:classifiers":[
        {
            "category":"Professional",
            "subcategory":"Computer Services",
            "type":"Services"
        }
    ],
    "sg:phone":"+61 2 9878 8055",
    "sg:postcode":"2113",
    "sg:province":"NSW",
    "sg:tags":[
        "equipment",
        "networking",
        "installation"
    ],
    "wof:name":"Trane Air Conditioning",
    "wof:placetype":"venue"
},
  "geometry": {"coordinates":[151.12025451700001,-33.7829666138],"type":"Point"}
}