{
  "type": "Feature",
  "properties": {
    "iso:country":"AU",
    "sg:address":"457 Smollett St",
    "sg:city":"Albury",
    "sg:classifiers":[
        {
            "category":"Real Estate",
            "subcategory":"Real Estate Services",
            "type":"Services"
        }
    ],
    "sg:phone":"+61 2 6021 4122",
    "sg:postcode":"2640",
    "sg:province":"NSW",
    "sg:tags":[
        "auctioneer"
    ],
    "wof:name":"Batrouney E D Real Estate",
    "wof:placetype":"venue"
},
  "geometry": {"coordinates":[146.91180419899999,-36.0824546814],"type":"Point"}
}