{
  "type": "Feature",
  "properties": {
    "iso:country":"AU",
    "sg:address":"477 Centre Rd",
    "sg:city":"Bentleigh",
    "sg:classifiers":[
        {
            "category":"Fast Food",
            "type":"Food & Drink"
        }
    ],
    "sg:phone":"+61 3 9557 6904",
    "sg:postcode":"3204",
    "sg:province":"VIC",
    "sg:tags":[
        "away",
        "take"
    ],
    "wof:name":"High Sea's Fish Shop",
    "wof:placetype":"venue"
},
  "geometry": {"coordinates":[145.042038,-37.91872],"type":"Point"}
}