{
  "type": "Feature",
  "properties": {
    "addr:full":"21- 23 Brooke St Mitchell ACT 2911",
    "addr:housenumber":"23",
    "addr:postcode":"2911",
    "addr:street":"Brooke St",
    "iso:country":"AU",
    "sg:address":"21- 23 Brooke St",
    "sg:city":"Mitchell",
    "sg:classifiers":[
        {
            "category":"Home & Garden",
            "subcategory":"Building Materials",
            "type":"Retail Goods"
        }
    ],
    "sg:phone":"+61 2 6242 8684",
    "sg:postcode":"2911",
    "sg:province":"ACT",
    "sg:tags":[
        "fencing"
    ],
    "wof:name":"ARC Fences",
    "wof:placetype":"venue"
},
  "geometry": {"coordinates":[149.14074707,-35.2187767029],"type":"Point"}
}