{
  "type": "Feature",
  "properties": {
    "addr:full":"14- 16 Anglo Rd Campsie NSW 2194",
    "addr:housenumber":"16",
    "addr:postcode":"2194",
    "addr:street":"Anglo Rd",
    "iso:country":"AU",
    "sg:address":"14- 16 Anglo Rd",
    "sg:city":"Campsie",
    "sg:classifiers":[
        {
            "category":"Health Services",
            "subcategory":"Optometrist",
            "type":"Services"
        }
    ],
    "sg:phone":"+61 2 9718 1441",
    "sg:postcode":"2194",
    "sg:province":"NSW",
    "wof:name":"Coad Elwyn",
    "wof:placetype":"venue"
},
  "geometry": {"coordinates":[151.10296600000001,-33.911388],"type":"Point"}
}