{
  "type": "Feature",
  "properties": {
    "addr:full":"10 Carnegie St Sumner Park QLD 4074",
    "addr:housenumber":"10",
    "addr:postcode":"4074",
    "addr:street":"Carnegie St",
    "iso:country":"AU",
    "sg:address":"10 Carnegie St",
    "sg:city":"Sumner Park",
    "sg:classifiers":[
        {
            "category":"Military Area",
            "subcategory":"Coast Guard Base",
            "type":"Public Place"
        }
    ],
    "sg:phone":"+61 1300 882 768",
    "sg:postcode":"4074",
    "sg:province":"QLD",
    "sg:tags":[
        "vessel",
        "pressure",
        "industrial"
    ],
    "wof:name":"ADD",
    "wof:placetype":"venue"
},
  "geometry": {"coordinates":[152.92291259800001,-27.5438308716],"type":"Point"}
}