{
  "type": "Feature",
  "properties": {
    "addr:full":"303 Payneham Rd Royston Park SA 5070",
    "addr:housenumber":"303",
    "addr:postcode":"5070",
    "addr:street":"Payneham Rd",
    "iso:country":"AU",
    "sg:address":"303 Payneham Rd",
    "sg:city":"Royston Park",
    "sg:classifiers":[
        {
            "category":"Shopping",
            "subcategory":"Hobbies, Toys, & Games",
            "type":"Retail Goods"
        }
    ],
    "sg:phone":"+61 8 8362 6936",
    "sg:postcode":"5070",
    "sg:province":"SA",
    "sg:tags":[
        "stamp"
    ],
    "wof:name":"Terman Pty Ltd",
    "wof:placetype":"venue"
},
  "geometry": {"coordinates":[138.63574218799999,-34.9000434875],"type":"Point"}
}