{
  "type": "Feature",
  "properties": {
    "iso:country":"AU",
    "sg:address":"111 Charles St",
    "sg:city":"Prahran",
    "sg:classifiers":[
        {
            "category":"Building & Trades",
            "subcategory":"Construction",
            "type":"Services"
        }
    ],
    "sg:phone":"+61 3 9521 2601",
    "sg:postcode":"3181",
    "sg:province":"VIC",
    "sg:tags":[
        "contractor"
    ],
    "wof:name":"Benett & Moar Pty Ltd",
    "wof:placetype":"venue"
},
  "geometry": {"coordinates":[144.98931884800001,-37.8469657898],"type":"Point"}
}