{
  "type": "Feature",
  "properties": {
    "iso:country":"AU",
    "sg:address":"52- 58 Chetwynd St",
    "sg:city":"West Melbourne",
    "sg:classifiers":[
        {
            "category":"Professional",
            "subcategory":"Computer Services",
            "type":"Services"
        }
    ],
    "sg:phone":"+61 3 9329 0766",
    "sg:postcode":"3003",
    "sg:province":"VIC",
    "sg:tags":[
        "package",
        "software"
    ],
    "wof:name":"Great Plains Dynamics",
    "wof:placetype":"venue"
},
  "geometry": {"coordinates":[144.95217895499999,-37.8066062927],"type":"Point"}
}