{
  "type": "Feature",
  "properties": {
    "addr:full":"6 Illluka St Buderim QLD 4556",
    "addr:housenumber":"6",
    "addr:postcode":"4556",
    "addr:street":"Illluka St",
    "iso:country":"AU",
    "sg:address":"6 Illluka St",
    "sg:city":"Buderim",
    "sg:classifiers":[
        {
            "category":"Building & Trades",
            "subcategory":"Plumbing",
            "type":"Services"
        }
    ],
    "sg:phone":"+61 408 714 531",
    "sg:postcode":"4556",
    "sg:province":"QLD",
    "sg:tags":[
        "plumber",
        "gasfitters"
    ],
    "wof:name":"Campbell David Plumbing",
    "wof:placetype":"venue"
},
  "geometry": {"coordinates":[153.077835083,-26.6897354126],"type":"Point"}
}