{
  "type": "Feature",
  "properties": {
    "addr:full":"2 Cairns Rd Brisbane QLD 4001",
    "addr:housenumber":"2",
    "addr:postcode":"4001",
    "addr:street":"Cairns Rd",
    "iso:country":"AU",
    "sg:address":"2 Cairns Rd",
    "sg:city":"Brisbane",
    "sg:classifiers":[
        {
            "category":"Building & Trades",
            "subcategory":"Pest Control",
            "type":"Services"
        }
    ],
    "sg:phone":"+61 1800 645 553",
    "sg:postcode":"4001",
    "sg:province":"QLD",
    "wof:name":"Organic Pest Control",
    "wof:placetype":"venue"
},
  "geometry": {"coordinates":[152.91551208499999,-27.6327075958],"type":"Point"}
}