{
  "type": "Feature",
  "properties": {
    "addr:full":"19 Dundas St Coogee NSW 2034",
    "addr:housenumber":"19",
    "addr:postcode":"2034",
    "addr:street":"Dundas St",
    "iso:country":"AU",
    "sg:address":"19 Dundas St",
    "sg:city":"Coogee",
    "sg:classifiers":[
        {
            "category":"Organizations",
            "subcategory":"Membership Organization",
            "type":"Services"
        }
    ],
    "sg:phone":"+61 2 9388 1727",
    "sg:postcode":"2034",
    "sg:province":"NSW",
    "sg:tags":[
        "equipment",
        "inter-communication",
        "system"
    ],
    "wof:name":"Electron",
    "wof:placetype":"venue"
},
  "geometry": {"coordinates":[151.25813293499999,-33.9278945923],"type":"Point"}
}