{
  "type": "Feature",
  "properties": {
    "addr:full":"89 Horsley Rd Denmark WA 6333",
    "addr:housenumber":"89",
    "addr:postcode":"6333",
    "addr:street":"Horsley Rd",
    "iso:country":"AU",
    "sg:address":"89 Horsley Rd",
    "sg:city":"Denmark",
    "sg:classifiers":[
        {
            "category":"Retail",
            "subcategory":"Auto Repair",
            "type":"Services"
        }
    ],
    "sg:phone":"+61 8 9848 2170",
    "sg:postcode":"6333",
    "sg:province":"WA",
    "sg:tags":[
        "repairer",
        "motor",
        "engineer"
    ],
    "wof:name":"Mac-S Marine & Mechanical Repairs",
    "wof:placetype":"venue"
},
  "geometry": {"coordinates":[117.352600098,-34.9509162903],"type":"Point"}
}