{
  "type": "Feature",
  "properties": {
    "addr:full":"35 Gilford St Kariong NSW 2250",
    "addr:housenumber":"35",
    "addr:postcode":"2250",
    "addr:street":"Gilford St",
    "iso:country":"AU",
    "sg:address":"35 Gilford St",
    "sg:city":"Kariong",
    "sg:classifiers":[
        {
            "category":"Building & Trades",
            "subcategory":"Construction",
            "type":"Services"
        }
    ],
    "sg:phone":"+61 2 4340 5027",
    "sg:postcode":"2250",
    "sg:province":"NSW",
    "sg:tags":[
        "fencing",
        "contractor"
    ],
    "wof:name":"Fencing We Do Rural & Residential Services",
    "wof:placetype":"venue"
},
  "geometry": {"coordinates":[151.294433594,-33.4422187805],"type":"Point"}
}