{
  "type": "Feature",
  "properties": {
    "iso:country":"AU",
    "sg:address":"153 Sturt St",
    "sg:city":"South Melbourne",
    "sg:classifiers":[
        {
            "category":"Food & Beverages",
            "subcategory":"Groceries & Convenience Stores",
            "type":"Retail Goods"
        }
    ],
    "sg:phone":"+61 3 9686 7755",
    "sg:postcode":"3205",
    "sg:province":"VIC",
    "wof:name":"Sturt Street Convenient Store",
    "wof:placetype":"venue"
},
  "geometry": {"coordinates":[144.966293,-37.827564],"type":"Point"}
}