{
  "type": "Feature",
  "properties": {
    "addr:full":"PO Box 2026 Sunshine Plaza QLD 4558",
    "addr:postcode":"4558",
    "iso:country":"AU",
    "sg:address":"PO Box 2026",
    "sg:city":"Sunshine Plaza",
    "sg:classifiers":[
        {
            "category":"Health Services",
            "subcategory":"Doctor",
            "type":"Services"
        }
    ],
    "sg:phone":"+61 410 889 824",
    "sg:postcode":"4558",
    "sg:province":"QLD",
    "sg:tags":[
        "occupational",
        "safety"
    ],
    "wof:name":"Risk & Safety Management",
    "wof:placetype":"venue"
},
  "geometry": {"coordinates":[153.08903503400001,-26.653219223],"type":"Point"}
}