{
  "type": "Feature",
  "properties": {
    "iso:country":"AU",
    "sg:address":"19 West Boundary Rd",
    "sg:city":"Hamilton",
    "sg:classifiers":[
        {
            "category":"Building & Trades",
            "subcategory":"Cleaning & Sanitation",
            "type":"Services"
        }
    ],
    "sg:phone":"+61 419 679 863",
    "sg:postcode":"3300",
    "sg:province":"VIC",
    "sg:tags":[
        "tank",
        "septic"
    ],
    "wof:name":"Eco Pure Waste Management Systems",
    "wof:placetype":"venue"
},
  "geometry": {"coordinates":[142.021575928,-37.7422294617],"type":"Point"}
}