{
  "type": "Feature",
  "properties": {
    "addr:full":"63 Albion St Surry Hills NSW 2010",
    "addr:housenumber":"63",
    "addr:postcode":"2010",
    "addr:street":"Albion St",
    "iso:country":"AU",
    "sg:address":"63 Albion St",
    "sg:city":"Surry Hills",
    "sg:classifiers":[
        {
            "category":"Government",
            "subcategory":"Court House",
            "type":"Public Place"
        }
    ],
    "sg:phone":"+61 402 428 075",
    "sg:postcode":"2010",
    "sg:province":"NSW",
    "sg:tags":[
        "personal",
        "marriage",
        "family",
        "counselling"
    ],
    "wof:name":"Mary West",
    "wof:placetype":"venue"
},
  "geometry": {"coordinates":[151.211105347,-33.8828964233],"type":"Point"}
}