{
  "type": "Feature",
  "properties": {
    "addr:full":"Unit 2/ 12 Smallwood St Underwood QLD 4119",
    "addr:housenumber":"12",
    "addr:postcode":"4119",
    "addr:street":"Smallwood St",
    "iso:country":"AU",
    "sg:address":"Unit 2/ 12 Smallwood St",
    "sg:city":"Underwood",
    "sg:classifiers":[
        {
            "category":"Wholesale",
            "subcategory":"Machinery & Supplies",
            "type":"Manufacturing & Wholesale Goods"
        }
    ],
    "sg:phone":"+61 7 3341 5601",
    "sg:postcode":"4119",
    "sg:province":"QLD",
    "wof:name":"Queensland Press & Shear Machinery",
    "wof:placetype":"venue"
},
  "geometry": {"coordinates":[153.11422729500001,-27.6084346771],"type":"Point"}
}