{
  "type": "Feature",
  "properties": {
    "addr:full":"Bunyip-Iona Rd Bunyip VIC 3815",
    "addr:postcode":"3815",
    "addr:street":"Bunyip-Iona Rd",
    "iso:country":"AU",
    "sg:address":"Bunyip-Iona Rd",
    "sg:city":"Bunyip",
    "sg:classifiers":[
        {
            "category":"Utilities",
            "subcategory":"Electric",
            "type":"Services"
        }
    ],
    "sg:phone":"+61 3 5629 5375",
    "sg:postcode":"3815",
    "sg:province":"VIC",
    "sg:tags":[
        "electrical",
        "contractor"
    ],
    "wof:name":"Gray T.F. Pty Ltd",
    "wof:placetype":"venue"
},
  "geometry": {"coordinates":[145.70971700000001,-38.119953],"type":"Point"}
}