{
  "type": "Feature",
  "properties": {
    "addr:full":"79 Melbourne St North Adelaide SA 5006",
    "addr:housenumber":"79",
    "addr:postcode":"5006",
    "addr:street":"Melbourne St",
    "iso:country":"AU",
    "sg:address":"79 Melbourne St",
    "sg:city":"North Adelaide",
    "sg:classifiers":[
        {
            "category":"Personal",
            "subcategory":"Beauty Salon",
            "type":"Services"
        }
    ],
    "sg:phone":"+61 8 8267 4044",
    "sg:postcode":"5006",
    "sg:province":"SA",
    "sg:tags":[
        "hairdresser"
    ],
    "wof:name":"Clip Joint Salons",
    "wof:placetype":"venue"
},
  "geometry": {"coordinates":[138.60853576700001,-34.9065437317],"type":"Point"}
}