{
  "type": "Feature",
  "properties": {
    "addr:full":"6 Darnick St Underwood QLD 4119",
    "addr:housenumber":"6",
    "addr:postcode":"4119",
    "addr:street":"Darnick St",
    "iso:country":"AU",
    "sg:address":"6 Darnick St",
    "sg:city":"Underwood",
    "sg:classifiers":[
        {
            "category":"Professional",
            "type":"Services"
        }
    ],
    "sg:phone":"+61 7 3341 2655",
    "sg:postcode":"4119",
    "sg:province":"QLD",
    "sg:tags":[
        "shop",
        "fitting"
    ],
    "wof:name":"Scan-Mac Cabinets",
    "wof:placetype":"venue"
},
  "geometry": {"coordinates":[153.11444091800001,-27.6075572968],"type":"Point"}
}