{
  "type": "Feature",
  "properties": {
    "addr:full":"11 McDougall St Kotara NSW 2289",
    "addr:housenumber":"11",
    "addr:postcode":"2289",
    "addr:street":"Mcdougall St",
    "iso:country":"AU",
    "sg:address":"11 McDougall St",
    "sg:city":"Kotara",
    "sg:classifiers":[
        {
            "category":"Wholesale",
            "subcategory":"Machinery & Supplies",
            "type":"Manufacturing & Wholesale Goods"
        }
    ],
    "sg:phone":"+61 1800 021 083",
    "sg:postcode":"2289",
    "sg:province":"NSW",
    "sg:tags":[
        "equipment",
        "laboratory"
    ],
    "sg:website":"http://www.austscientific.com.au",
    "wof:name":"Australian Scientific Pty Ltd",
    "wof:placetype":"venue"
},
  "geometry": {"coordinates":[151.70477294899999,-32.9403953552],"type":"Point"}
}