{
  "type": "Feature",
  "properties": {
    "addr:full":"89 St John St Launceston TAS 7250",
    "addr:housenumber":"89",
    "addr:postcode":"7250",
    "addr:street":"St John St",
    "iso:country":"AU",
    "sg:address":"89 St John St",
    "sg:city":"Launceston",
    "sg:classifiers":[
        {
            "category":"Manufacturing",
            "subcategory":"Jewelry",
            "type":"Manufacturing & Wholesale Goods"
        }
    ],
    "sg:phone":"+61 3 6331 7880",
    "sg:postcode":"7250",
    "sg:province":"TAS",
    "sg:tags":[
        "mfrg",
        "jeweller"
    ],
    "wof:name":"Alan Whittle Manufacturing Jewellers",
    "wof:placetype":"venue"
},
  "geometry": {"coordinates":[147.13958740199999,-41.4384765625],"type":"Point"}
}