{
  "type": "Feature",
  "properties": {
    "iso:country":"AU",
    "sg:address":"323 Elizabeth St",
    "sg:city":"Melbourne",
    "sg:classifiers":[
        {
            "category":"Banks & Credit Unions",
            "subcategory":"Bureau De Change",
            "type":"Services"
        }
    ],
    "sg:phone":"+61 3 9602 4269",
    "sg:postcode":"3000",
    "sg:province":"VIC",
    "sg:tags":[
        "motorised",
        "scooter"
    ],
    "wof:name":"Bike Barn",
    "wof:placetype":"venue"
},
  "geometry": {"coordinates":[144.96156310999999,-37.8111038208],"type":"Point"}
}