{
  "type": "Feature",
  "properties": {
    "iso:country":"AU",
    "sg:address":"141a Bridge St",
    "sg:city":"Schofields",
    "sg:classifiers":[
        {
            "category":"Structure",
            "subcategory":"Office Building",
            "type":"Public Place"
        }
    ],
    "sg:phone":"+61 2 9627 4764",
    "sg:postcode":"2762",
    "sg:province":"NSW",
    "sg:tags":[
        "slater",
        "tiler",
        "roof"
    ],
    "wof:name":"McLister N G",
    "wof:placetype":"venue"
},
  "geometry": {"coordinates":[150.87066650400001,-33.7007141113],"type":"Point"}
}