{
  "type": "Feature",
  "properties": {
    "addr:full":"2 Crotty St Indooroopilly QLD 4068",
    "addr:housenumber":"2",
    "addr:postcode":"4068",
    "addr:street":"Crotty St",
    "iso:country":"AU",
    "sg:address":"2 Crotty St",
    "sg:city":"Indooroopilly",
    "sg:classifiers":[
        {
            "category":"Personal",
            "subcategory":"Massage",
            "type":"Services"
        }
    ],
    "sg:phone":"+61 409 477 501",
    "sg:postcode":"4068",
    "sg:province":"QLD",
    "sg:tags":[
        "therapy"
    ],
    "wof:name":"Cathy Bell",
    "wof:placetype":"venue"
},
  "geometry": {"coordinates":[152.96330261200001,-27.4957141876],"type":"Point"}
}