{
  "type": "Feature",
  "properties": {
    "addr:full":"Shop 1, 438 Sheridan St Cairns QLD 4870",
    "addr:housenumber":"shop 1 438",
    "addr:postcode":"4870",
    "addr:street":"Sheridan St",
    "iso:country":"AU",
    "sg:address":"Shop 1, 438 Sheridan St",
    "sg:city":"Cairns",
    "sg:classifiers":[
        {
            "category":"Shopping",
            "subcategory":"Bicycles & Sporting Goods",
            "type":"Retail Goods"
        }
    ],
    "sg:phone":"+61 7 4053 7755",
    "sg:postcode":"4870",
    "sg:province":"QLD",
    "sg:tags":[
        "chemical",
        "equipment",
        "pool",
        "swimming"
    ],
    "wof:name":"Swimart Cairns",
    "wof:placetype":"venue"
},
  "geometry": {"coordinates":[145.754364014,-16.895067215],"type":"Point"}
}