{
  "type": "Feature",
  "properties": {
    "addr:full":"75 Justin St Lilyfield NSW 2040",
    "addr:housenumber":"75",
    "addr:postcode":"2040",
    "addr:street":"Justin St",
    "iso:country":"AU",
    "sg:address":"75 Justin St",
    "sg:city":"Lilyfield",
    "sg:classifiers":[
        {
            "category":"Professional",
            "subcategory":"Management & Consulting",
            "type":"Services"
        }
    ],
    "sg:phone":"+61 2 9555 9911",
    "sg:postcode":"2040",
    "sg:province":"NSW",
    "sg:tags":[
        "consultant",
        "energy"
    ],
    "wof:name":"EnergyAdvice",
    "wof:placetype":"venue"
},
  "geometry": {"coordinates":[151.16601600000001,-33.872711],"type":"Point"}
}