{
  "type": "Feature",
  "properties": {
    "addr:full":"25 Colin Jamieson Drv Welshpool WA 6106",
    "addr:housenumber":"25",
    "addr:postcode":"6106",
    "addr:street":"Colin Jamieson Drv",
    "iso:country":"AU",
    "sg:address":"25 Colin Jamieson Drv",
    "sg:city":"Welshpool",
    "sg:classifiers":[
        {
            "category":"Wholesale",
            "subcategory":"Machinery & Supplies",
            "type":"Manufacturing & Wholesale Goods"
        }
    ],
    "sg:phone":"+61 8 9458 6088",
    "sg:postcode":"6106",
    "sg:province":"WA",
    "sg:tags":[
        "equipment",
        "system",
        "elevating",
        "conveying"
    ],
    "wof:name":"Powergrip",
    "wof:placetype":"venue"
},
  "geometry": {"coordinates":[115.93698120099999,-31.9923286438],"type":"Point"}
}