{
  "type": "Feature",
  "properties": {
    "addr:full":"Park Beach Plz Coffs Harbour NSW 2450",
    "addr:postcode":"2450",
    "addr:street":"Beach Plz",
    "iso:country":"AU",
    "sg:address":"Park Beach Plz",
    "sg:city":"Coffs Harbour",
    "sg:classifiers":[
        {
            "category":"Personal",
            "subcategory":"Beauty Salon",
            "type":"Services"
        }
    ],
    "sg:phone":"+61 437 447 339",
    "sg:postcode":"2450",
    "sg:province":"NSW",
    "sg:tags":[
        "hairdresser"
    ],
    "wof:name":"Redz Hairstudio & Cafe",
    "wof:placetype":"venue"
},
  "geometry": {"coordinates":[153.129639,-30.284494],"type":"Point"}
}