{
  "type": "Feature",
  "properties": {
    "iso:country":"AU",
    "sg:address":"1/ 210 Central Coast Hwy",
    "sg:city":"Erina",
    "sg:classifiers":[
        {
            "category":"Real Estate",
            "subcategory":"Real Estate Agent",
            "type":"Services"
        }
    ],
    "sg:phone":"+61 2 4365 2866",
    "sg:postcode":"2250",
    "sg:province":"NSW",
    "wof:name":"Ray White Erina",
    "wof:placetype":"venue"
},
  "geometry": {"coordinates":[151.390823364,-33.4332923889],"type":"Point"}
}