{
  "type": "Feature",
  "properties": {
    "iso:country":"AU",
    "sg:address":"33 Aster Ave",
    "sg:city":"Carrum Downs",
    "sg:classifiers":[
        {
            "category":"Professional",
            "subcategory":"Engineering",
            "type":"Services"
        }
    ],
    "sg:phone":"+61 3 9775 0027",
    "sg:postcode":"3201",
    "sg:province":"VIC",
    "sg:tags":[
        "engineer",
        "toolmaker",
        "plastic"
    ],
    "wof:name":"Infraform Australia Pty Ltd",
    "wof:placetype":"venue"
},
  "geometry": {"coordinates":[145.16551200000001,-38.101685],"type":"Point"}
}