{
  "type": "Feature",
  "properties": {
    "addr:full":"418 Sydney Rd Coburg VIC 3058",
    "addr:housenumber":"418",
    "addr:postcode":"3058",
    "addr:street":"Sydney Rd",
    "iso:country":"AU",
    "sg:address":"418 Sydney Rd",
    "sg:city":"Coburg",
    "sg:classifiers":[
        {
            "category":"Shopping",
            "subcategory":"Clothing, Apparel, & Fashions",
            "type":"Retail Goods"
        }
    ],
    "sg:phone":"+61 3 9354 7898",
    "sg:postcode":"3058",
    "sg:province":"VIC",
    "sg:tags":[
        "lady",
        "wear"
    ],
    "wof:name":"Great Season Pty Ltd",
    "wof:placetype":"venue"
},
  "geometry": {"coordinates":[144.966339111,-37.7435684204],"type":"Point"}
}