{
  "type": "Feature",
  "properties": {
    "iso:country":"AU",
    "sg:address":"Suite 18, Riverside Suites 187 Cambridge St",
    "sg:city":"Maryborough",
    "sg:classifiers":[
        {
            "category":"Professional",
            "subcategory":"Computer Services",
            "type":"Services"
        }
    ],
    "sg:phone":"+61 7 4123 2534",
    "sg:postcode":"4650",
    "sg:province":"QLD",
    "sg:tags":[
        "repairs",
        "upgrade",
        "equipment"
    ],
    "wof:name":"I-Way Business Solutions",
    "wof:placetype":"venue"
},
  "geometry": {"coordinates":[152.723907,-25.546169],"type":"Point"}
}