{
  "type": "Feature",
  "properties": {
    "iso:country":"AU",
    "sg:address":"6 Peace St",
    "sg:city":"Mackay",
    "sg:classifiers":[
        {
            "category":"Professional",
            "type":"Services"
        }
    ],
    "sg:phone":"+61 7 4952 4990",
    "sg:postcode":"4740",
    "sg:province":"QLD",
    "sg:tags":[
        "shop",
        "fitting"
    ],
    "wof:name":"Pioneer Cabinets",
    "wof:placetype":"venue"
},
  "geometry": {"coordinates":[149.172653,-21.172089],"type":"Point"}
}