{
  "type": "Feature",
  "properties": {
    "addr:full":"50 Arnold St Stratford QLD 4870",
    "addr:housenumber":"50",
    "addr:postcode":"4870",
    "addr:street":"Arnold St",
    "iso:country":"AU",
    "sg:address":"50 Arnold St",
    "sg:city":"Stratford",
    "sg:classifiers":[
        {
            "category":"Professional",
            "type":"Services"
        }
    ],
    "sg:phone":"+61 7 4055 2433",
    "sg:postcode":"4870",
    "sg:province":"QLD",
    "sg:tags":[
        "transport"
    ],
    "wof:name":"Barron River Towing",
    "wof:placetype":"venue"
},
  "geometry": {"coordinates":[145.73960876500001,-16.8719120026],"type":"Point"}
}