{
  "type": "Feature",
  "properties": {
    "addr:full":"PO Box 544 Tewantin QLD 4565",
    "addr:postcode":"4565",
    "iso:country":"AU",
    "sg:address":"PO Box 544",
    "sg:city":"Tewantin",
    "sg:classifiers":[
        {
            "category":"Building & Trades",
            "subcategory":"Construction",
            "type":"Services"
        }
    ],
    "sg:phone":"+61 7 5485 3824",
    "sg:postcode":"4565",
    "sg:province":"QLD",
    "sg:tags":[
        "contractor"
    ],
    "wof:name":"Cooke Constructions",
    "wof:placetype":"venue"
},
  "geometry": {"coordinates":[153.02789306599999,-26.3908996582],"type":"Point"}
}