{
  "type": "Feature",
  "properties": {
    "addr:full":"28 Yirrigan Drv Dianella WA 6059",
    "addr:housenumber":"28",
    "addr:postcode":"6059",
    "addr:street":"Yirrigan Drv",
    "iso:country":"AU",
    "sg:address":"28 Yirrigan Drv",
    "sg:city":"Dianella",
    "sg:classifiers":[
        {
            "category":"Shopping",
            "subcategory":"Bridal",
            "type":"Retail Goods"
        }
    ],
    "sg:phone":"+61 8 9344 8393",
    "sg:postcode":"6059",
    "sg:province":"WA",
    "sg:tags":[
        "hire",
        "wear"
    ],
    "wof:name":"Collections By Angie",
    "wof:placetype":"venue"
},
  "geometry": {"coordinates":[115.85849761999999,-31.8716678619],"type":"Point"}
}