{
  "type": "Feature",
  "properties": {
    "addr:full":"51 Murilla St Miles QLD 4415",
    "addr:housenumber":"51",
    "addr:postcode":"4415",
    "addr:street":"Murilla St",
    "iso:country":"AU",
    "sg:address":"51 Murilla St",
    "sg:city":"Miles",
    "sg:classifiers":[
        {
            "category":"Banks & Credit Unions",
            "subcategory":"Financial Services",
            "type":"Services"
        }
    ],
    "sg:phone":"+61 7 4627 2809",
    "sg:postcode":"4415",
    "sg:province":"QLD",
    "sg:tags":[
        "building",
        "society"
    ],
    "wof:name":"Heritage Building Society",
    "wof:placetype":"venue"
},
  "geometry": {"coordinates":[150.186035156,-26.6593780518],"type":"Point"}
}