{
  "type": "Feature",
  "properties": {
    "addr:full":"178 Byrnes St Mareeba QLD 4880",
    "addr:housenumber":"178",
    "addr:postcode":"4880",
    "addr:street":"Byrnes St",
    "iso:country":"AU",
    "sg:address":"178 Byrnes St",
    "sg:city":"Mareeba",
    "sg:classifiers":[
        {
            "category":"Organizations",
            "subcategory":"Professional Association",
            "type":"Services"
        }
    ],
    "sg:phone":"+61 7 4092 3390",
    "sg:postcode":"4880",
    "sg:province":"QLD",
    "sg:tags":[
        "rural",
        "organisation",
        "production",
        "primary"
    ],
    "wof:name":"N.Q. Co-Op LTD",
    "wof:placetype":"venue"
},
  "geometry": {"coordinates":[145.42027282699999,-16.9870605469],"type":"Point"}
}