{
  "type": "Feature",
  "properties": {
    "iso:country":"AU",
    "sg:address":"6 Sapphire Drv",
    "sg:city":"Tarro",
    "sg:classifiers":[
        {
            "category":"Education",
            "subcategory":"Music School",
            "type":"Public Place"
        }
    ],
    "sg:phone":"+61 2 4964 1547",
    "sg:postcode":"2322",
    "sg:province":"NSW",
    "sg:tags":[
        "teacher"
    ],
    "wof:name":"Realm Music",
    "wof:placetype":"venue"
},
  "geometry": {"coordinates":[151.65345764200001,-32.8093414307],"type":"Point"}
}