{
  "type": "Feature",
  "properties": {
    "iso:country":"AU",
    "sg:address":"Berth 7, Port Beach Rd",
    "sg:city":"North Fremantle",
    "sg:classifiers":[
        {
            "category":"Professional",
            "subcategory":"Engineering",
            "type":"Services"
        }
    ],
    "sg:phone":"+61 8 9430 5766",
    "sg:postcode":"6159",
    "sg:province":"WA",
    "sg:tags":[
        "installation",
        "maintenance",
        "engineer"
    ],
    "wof:name":"Port Trans Engineering",
    "wof:placetype":"venue"
},
  "geometry": {"coordinates":[115.745827,-32.035465],"type":"Point"}
}