{
  "type": "Feature",
  "properties": {
    "addr:full":"297 Sydney Rd Brunswick VIC 3056",
    "addr:housenumber":"297",
    "addr:postcode":"3056",
    "addr:street":"Sydney Rd",
    "iso:country":"AU",
    "sg:address":"297 Sydney Rd",
    "sg:city":"Brunswick",
    "sg:classifiers":[
        {
            "category":"Parking",
            "subcategory":"Garage",
            "type":"Transportation"
        }
    ],
    "sg:phone":"+61 3 9387 5000",
    "sg:postcode":"3056",
    "sg:province":"VIC",
    "sg:tags":[
        "radiographer"
    ],
    "wof:name":"Brunswick Medical Imaging Pty Ltd",
    "wof:placetype":"venue"
},
  "geometry": {"coordinates":[144.961334228,-37.7706260681],"type":"Point"}
}