{
  "type": "Feature",
  "properties": {
    "addr:full":"26 Musgrave Ave Chirn Park QLD 4215",
    "addr:housenumber":"26",
    "addr:postcode":"4215",
    "addr:street":"Musgrave Ave Chirn",
    "iso:country":"AU",
    "sg:address":"26 Musgrave Ave",
    "sg:city":"Chirn Park",
    "sg:classifiers":[
        {
            "category":"Real Estate",
            "subcategory":"Real Estate Agent",
            "type":"Services"
        }
    ],
    "sg:phone":"+61 7 5591 4484",
    "sg:postcode":"4215",
    "sg:province":"QLD",
    "wof:name":"Chirn Park Realty",
    "wof:placetype":"venue"
},
  "geometry": {"coordinates":[153.38656616200001,-27.9544792175],"type":"Point"}
}