{
  "type": "Feature",
  "properties": {
    "addr:full":"21 Knight Ave Sunshine North VIC 3020",
    "addr:housenumber":"21",
    "addr:postcode":"3020",
    "addr:street":"Knight Ave",
    "iso:country":"AU",
    "sg:address":"21 Knight Ave",
    "sg:city":"Sunshine North",
    "sg:classifiers":[
        {
            "category":"Manufacturing",
            "subcategory":"Glass & Minerals",
            "type":"Manufacturing & Wholesale Goods"
        }
    ],
    "sg:phone":"+61 3 9310 7682",
    "sg:postcode":"3020",
    "sg:province":"VIC",
    "sg:tags":[
        "merchant",
        "granite",
        "marble"
    ],
    "wof:name":"Blue Marble Pty Ltd",
    "wof:placetype":"venue"
},
  "geometry": {"coordinates":[144.836624,-37.75602],"type":"Point"}
}