{
  "type": "Feature",
  "properties": {
    "addr:full":"89 Grattan St Carlton VIC 3053",
    "addr:housenumber":"89",
    "addr:postcode":"3053",
    "addr:street":"Grattan St",
    "iso:country":"AU",
    "sg:address":"89 Grattan St",
    "sg:city":"Carlton",
    "sg:classifiers":[
        {
            "category":"Retail",
            "subcategory":"Laundry & Dry Cleaning",
            "type":"Services"
        }
    ],
    "sg:phone":"+61 3 9349 4000",
    "sg:postcode":"3053",
    "sg:province":"VIC",
    "sg:tags":[
        "manicurist"
    ],
    "wof:name":"Spoil Me With Nails",
    "wof:placetype":"venue"
},
  "geometry": {"coordinates":[144.96658325199999,-37.8008270264],"type":"Point"}
}