{
  "type": "Feature",
  "properties": {
    "iso:country":"AU",
    "sg:address":"369 Settlement Rd",
    "sg:city":"Thomastown",
    "sg:classifiers":[
        {
            "category":"Farming",
            "subcategory":"Fish & Marine Products",
            "type":"Manufacturing & Wholesale Goods"
        }
    ],
    "sg:phone":"+61 3 9465 2000",
    "sg:postcode":"3074",
    "sg:province":"VIC",
    "sg:tags":[
        "slate"
    ],
    "wof:name":"Martinengo Tiles Pty Ltd",
    "wof:placetype":"venue"
},
  "geometry": {"coordinates":[145.01698303200001,-37.6884078979],"type":"Point"}
}