{
  "type": "Feature",
  "properties": {
    "iso:country":"AU",
    "sg:address":"383 Fullarton Rd",
    "sg:city":"Fullarton",
    "sg:classifiers":[
        {
            "category":"Community Center",
            "subcategory":"Ethnic",
            "type":"Public Place"
        }
    ],
    "sg:phone":"+61 403 169 243",
    "sg:postcode":"5063",
    "sg:province":"SA",
    "sg:tags":[
        "wood",
        "carver"
    ],
    "wof:name":"Hoad Woodcarving Academy",
    "wof:placetype":"venue"
},
  "geometry": {"coordinates":[138.62564086899999,-34.9556159973],"type":"Point"}
}