{
  "type": "Feature",
  "properties": {
    "iso:country":"AU",
    "sg:address":"Shop 70, Clifford Gardens Shopping Centre, CnrJames St & Anzac Ave",
    "sg:city":"Toowoomba",
    "sg:classifiers":[
        {
            "category":"Banks & Credit Unions",
            "subcategory":"Bank",
            "type":"Services"
        }
    ],
    "sg:phone":"+61 7 4634 1737",
    "sg:postcode":"4350",
    "sg:province":"QLD",
    "wof:name":"Queensland Teachers' Credit Union Limited",
    "wof:placetype":"venue"
},
  "geometry": {"coordinates":[151.921722,-27.577253],"type":"Point"}
}