{
  "type": "Feature",
  "properties": {
    "iso:country":"AU",
    "sg:address":"9 Elliot St",
    "sg:city":"Narrabri",
    "sg:classifiers":[
        {
            "category":"Utilities",
            "subcategory":"Electric",
            "type":"Services"
        }
    ],
    "sg:phone":"+61 2 6792 2247",
    "sg:postcode":"2390",
    "sg:province":"NSW",
    "sg:tags":[
        "electrical",
        "contractor"
    ],
    "wof:name":"Percival R C",
    "wof:placetype":"venue"
},
  "geometry": {"coordinates":[149.77961730999999,-30.3399810791],"type":"Point"}
}