{
  "type": "Feature",
  "properties": {
    "iso:country":"AU",
    "sg:address":"5 Lill St",
    "sg:city":"Woody Point",
    "sg:classifiers":[
        {
            "category":"Home & Garden",
            "subcategory":"Carpets & Floor Coverings",
            "type":"Retail Goods"
        }
    ],
    "sg:phone":"+61 7 3883 1514",
    "sg:postcode":"4019",
    "sg:province":"QLD",
    "sg:tags":[
        "layer",
        "planner"
    ],
    "wof:name":"R & G Gillard Pty Ltd",
    "wof:placetype":"venue"
},
  "geometry": {"coordinates":[153.105758667,-27.2615089417],"type":"Point"}
}