{
  "type": "Feature",
  "properties": {
    "iso:country":"AU",
    "sg:address":"Shop 4",
    "sg:city":"Kingsley Shopping Centre Kingsley",
    "sg:classifiers":[
        {
            "category":"Personal",
            "subcategory":"Beauty Salon",
            "type":"Services"
        }
    ],
    "sg:phone":"+61 8 9309 4333",
    "sg:postcode":"6026",
    "sg:province":"WA",
    "wof:name":"La Bella Skin Care Centre",
    "wof:placetype":"venue"
},
  "geometry": {"coordinates":[115.788528442,-31.8000850677],"type":"Point"}
}