{
  "type": "Feature",
  "properties": {
    "iso:country":"AU",
    "sg:address":"135a Nepean Hwy",
    "sg:city":"Aspendale",
    "sg:classifiers":[
        {
            "category":"Retail",
            "subcategory":"Auto Repair",
            "type":"Services"
        }
    ],
    "sg:phone":"+61 3 9587 6188",
    "sg:postcode":"3195",
    "sg:province":"VIC",
    "sg:tags":[
        "repairer",
        "motor",
        "engineer"
    ],
    "wof:name":"K.A.D. Automotive",
    "wof:placetype":"venue"
},
  "geometry": {"coordinates":[145.10115051299999,-38.0263786316],"type":"Point"}
}