{
  "type": "Feature",
  "properties": {
    "addr:full":"90-98 The Lakes Drv Glenmore Park NSW 2745",
    "addr:housenumber":"90-98",
    "addr:postcode":"2745",
    "addr:street":"The Lakes Drv",
    "iso:country":"AU",
    "sg:address":"90-98 The Lakes Drv",
    "sg:city":"Glenmore Park",
    "sg:classifiers":[
        {
            "category":"Education",
            "subcategory":"School",
            "type":"Public Place"
        }
    ],
    "sg:phone":"+61 2 4733 1204",
    "sg:postcode":"2745",
    "sg:province":"NSW",
    "wof:name":"Caroline Chisholm College",
    "wof:placetype":"venue"
},
  "geometry": {"coordinates":[150.67477417000001,-33.7844314575],"type":"Point"}
}