{
  "type": "Feature",
  "properties": {
    "iso:country":"AU",
    "sg:address":"48 Milne St",
    "sg:city":"Crib Point",
    "sg:classifiers":[
        {
            "category":"Farming",
            "subcategory":"Farm & Veterinary Services",
            "type":"Manufacturing & Wholesale Goods"
        }
    ],
    "sg:phone":"+61 425 767 264",
    "sg:postcode":"3919",
    "sg:province":"VIC",
    "sg:tags":[
        "worm"
    ],
    "wof:name":"Browns Compost Worms",
    "wof:placetype":"venue"
},
  "geometry": {"coordinates":[145.202194214,-38.3623313904],"type":"Point"}
}