{
  "type": "Feature",
  "properties": {
    "addr:full":"274 Foreshore Drv Geraldton WA 6530",
    "addr:housenumber":"274",
    "addr:postcode":"6530",
    "addr:street":"Foreshore Drv",
    "iso:country":"AU",
    "sg:address":"274 Foreshore Drv",
    "sg:city":"Geraldton",
    "sg:classifiers":[
        {
            "category":"Insurance",
            "subcategory":"Life Insurance",
            "type":"Services"
        }
    ],
    "sg:phone":"+61 8 9964 1119",
    "sg:postcode":"6530",
    "sg:province":"WA",
    "wof:name":"Great Western Insurance Brokers",
    "wof:placetype":"venue"
},
  "geometry": {"coordinates":[114.613113403,-28.7680969238],"type":"Point"}
}