{
  "type": "Feature",
  "properties": {
    "addr:full":"169 Elgin St Carlton VIC 3053",
    "addr:housenumber":"169",
    "addr:postcode":"3053",
    "addr:street":"Elgin St",
    "iso:country":"AU",
    "sg:address":"169 Elgin St",
    "sg:city":"Carlton",
    "sg:classifiers":[
        {
            "category":"Cafe",
            "type":"Food & Drink"
        }
    ],
    "sg:phone":"+61 3 9347 0111",
    "sg:postcode":"3053",
    "sg:province":"VIC",
    "wof:name":"Rubys Cafe",
    "wof:placetype":"venue"
},
  "geometry": {"coordinates":[144.969146728,-37.7974433899],"type":"Point"}
}