{
  "type": "Feature",
  "properties": {
    "iso:country":"AU",
    "sg:address":"18 Panoramic Drv",
    "sg:city":"Preston",
    "sg:classifiers":[
        {
            "category":"Building & Trades",
            "subcategory":"Landscaping Services",
            "type":"Services"
        }
    ],
    "sg:phone":"+61 7 4615 2466",
    "sg:postcode":"4352",
    "sg:province":"QLD",
    "sg:tags":[
        "consultant"
    ],
    "wof:name":"Nicolson Builders",
    "wof:placetype":"venue"
},
  "geometry": {"coordinates":[151.950821,-27.651752],"type":"Point"}
}