{
  "type": "Feature",
  "properties": {
    "addr:full":"2 Challis Ave Dulwich Hill NSW 2203",
    "addr:housenumber":"2",
    "addr:postcode":"2203",
    "addr:street":"Challis Ave",
    "iso:country":"AU",
    "sg:address":"2 Challis Ave",
    "sg:city":"Dulwich Hill",
    "sg:classifiers":[
        {
            "category":"Building & Trades",
            "subcategory":"Construction",
            "type":"Services"
        }
    ],
    "sg:phone":"+61 2 9573 0333",
    "sg:postcode":"2203",
    "sg:province":"NSW",
    "sg:tags":[
        "contractor"
    ],
    "wof:name":"Sydcon Development Group Pty Ltd",
    "wof:placetype":"venue"
},
  "geometry": {"coordinates":[151.14324999999999,-33.909191],"type":"Point"}
}