{
  "type": "Feature",
  "properties": {
    "addr:full":"299 Prospect Rd Blair Athol SA 5084",
    "addr:housenumber":"299",
    "addr:postcode":"5084",
    "addr:street":"Prospect Rd",
    "iso:country":"AU",
    "sg:address":"299 Prospect Rd",
    "sg:city":"Blair Athol",
    "sg:classifiers":[
        {
            "category":"Transit Center",
            "subcategory":"Freight",
            "type":"Transportation"
        }
    ],
    "sg:phone":"+61 8 8344 8307",
    "sg:postcode":"5084",
    "sg:province":"SA",
    "sg:tags":[
        "honey",
        "merchant"
    ],
    "wof:name":"Guilfoyle John L Pty Ltd",
    "wof:placetype":"venue"
},
  "geometry": {"coordinates":[138.59280395499999,-34.8663482666],"type":"Point"}
}