{
  "type": "Feature",
  "properties": {
    "addr:full":"22 Colebee Crs Hassall Grove NSW 2761",
    "addr:housenumber":"22",
    "addr:postcode":"2761",
    "addr:street":"Colebee Crs",
    "iso:country":"AU",
    "sg:address":"22 Colebee Crs",
    "sg:city":"Hassall Grove",
    "sg:classifiers":[
        {
            "category":"Building & Trades",
            "subcategory":"Plumbing",
            "type":"Services"
        }
    ],
    "sg:phone":"+61 2 9628 6581",
    "sg:postcode":"2761",
    "sg:province":"NSW",
    "sg:tags":[
        "plumber",
        "gasfitters"
    ],
    "wof:name":"Darren Fowler Plumbing",
    "wof:placetype":"venue"
},
  "geometry": {"coordinates":[150.87112400000001,-33.723167],"type":"Point"}
}