{
  "type": "Feature",
  "properties": {
    "addr:full":"Brimbank Shopping Centre Station Rd Deer Park VIC 3023",
    "addr:postcode":"3023",
    "addr:street":"Station Rd",
    "iso:country":"AU",
    "sg:address":"Brimbank Shopping Centre Station Rd",
    "sg:city":"Deer Park",
    "sg:classifiers":[
        {
            "category":"Shopping",
            "subcategory":"Clothing, Apparel, & Fashions",
            "type":"Retail Goods"
        }
    ],
    "sg:phone":"+61 3 9361 1433",
    "sg:postcode":"3023",
    "sg:province":"VIC",
    "sg:tags":[
        "lady",
        "wear"
    ],
    "wof:name":"Central Lane",
    "wof:placetype":"venue"
},
  "geometry": {"coordinates":[144.774857,-37.76955],"type":"Point"}
}