{
  "type": "Feature",
  "properties": {
    "addr:full":"Shp 9/ 1061 D&#039;Aguilar Hwy Wamuran QLD 4512",
    "addr:housenumber":"/ 1061 d",
    "addr:postcode":"qld 4512",
    "addr:street":"Aguilar Hwy",
    "iso:country":"AU",
    "sg:address":"Shp 9/ 1061 D&#039;Aguilar Hwy",
    "sg:city":"Wamuran",
    "sg:classifiers":[
        {
            "category":"Cafe",
            "type":"Food & Drink"
        }
    ],
    "sg:phone":"+61 7 5429 8936",
    "sg:postcode":"4512",
    "sg:province":"QLD",
    "wof:name":"Wam Bam Sandwich Bar",
    "wof:placetype":"venue"
},
  "geometry": {"coordinates":[152.86144999999999,-27.039864],"type":"Point"}
}