{
  "type": "Feature",
  "properties": {
    "addr:full":"57a Browns La Plenty VIC 3090",
    "addr:housenumber":"57a",
    "addr:postcode":"3090",
    "addr:street":"Browns La Plenty",
    "iso:country":"AU",
    "sg:address":"57a Browns La",
    "sg:city":"Plenty",
    "sg:classifiers":[
        {
            "category":"Building & Trades",
            "subcategory":"Plumbing",
            "type":"Services"
        }
    ],
    "sg:phone":"+61 3 9436 1600",
    "sg:postcode":"3090",
    "sg:province":"VIC",
    "sg:tags":[
        "drainers"
    ],
    "wof:name":"Azzona Drainage Contractors",
    "wof:placetype":"venue"
},
  "geometry": {"coordinates":[145.119216919,-37.658000946],"type":"Point"}
}