{
  "type": "Feature",
  "properties": {
    "addr:full":"St Vincent&#039;s Hospital Darlinghurst Darlingh NSW 2010",
    "addr:postcode":"2010",
    "addr:street":"S",
    "iso:country":"AU",
    "sg:address":"St",
    "sg:city":"Vincent&#039;s Hospital Darlinghurst Darlingh",
    "sg:classifiers":[
        {
            "category":"Health Services",
            "subcategory":"Doctor",
            "type":"Services"
        }
    ],
    "sg:phone":"+61 2 8382 2259",
    "sg:postcode":"2010",
    "sg:province":"NSW",
    "sg:tags":[
        "medical",
        "practitioner"
    ],
    "wof:name":"Frommer Dr D J (Gastroenterologist)",
    "wof:placetype":"venue"
},
  "geometry": {"coordinates":[151.22000122099999,-33.8789329529],"type":"Point"}
}