{
  "type": "Feature",
  "properties": {
    "addr:full":"Unit 2, 4 George Rd Salamander Bay NSW 2317",
    "addr:housenumber":"4",
    "addr:postcode":"2317",
    "addr:street":"George Rd",
    "iso:country":"AU",
    "sg:address":"Unit 2, 4 George Rd",
    "sg:city":"Salamander Bay",
    "sg:classifiers":[
        {
            "category":"Autos & Motor Vehicles",
            "subcategory":"Motorcycle Sales",
            "type":"Retail Goods"
        }
    ],
    "sg:phone":"+61 2 4982 7433",
    "sg:postcode":"2317",
    "sg:province":"NSW",
    "sg:tags":[
        "outboard"
    ],
    "wof:name":"Nelson Bay Outboard Services",
    "wof:placetype":"venue"
},
  "geometry": {"coordinates":[152.07498200000001,-32.726559],"type":"Point"}
}