{
  "type": "Feature",
  "properties": {
    "iso:country":"AU",
    "sg:address":"30 Goode Rd",
    "sg:city":"Ceduna",
    "sg:classifiers":[
        {
            "category":"Commercial Area",
            "type":"Public Place"
        }
    ],
    "sg:phone":"+61 8 8625 3366",
    "sg:postcode":"5690",
    "sg:province":"SA",
    "sg:tags":[
        "heavy",
        "carrier"
    ],
    "wof:name":"Ceduna Bulk Hauliers & Earth Movers Pty Ltd",
    "wof:placetype":"venue"
},
  "geometry": {"coordinates":[133.68096923799999,-32.1189842224],"type":"Point"}
}