{
  "type": "Feature",
  "properties": {
    "addr:full":"3/ 26 Arthur St Fairlight NSW 2094",
    "addr:housenumber":"/ 26",
    "addr:postcode":"2094",
    "addr:street":"Arthur St",
    "iso:country":"AU",
    "sg:address":"3/ 26 Arthur St",
    "sg:city":"Fairlight",
    "sg:classifiers":[
        {
            "category":"Building & Trades",
            "subcategory":"Cleaning & Sanitation",
            "type":"Services"
        }
    ],
    "sg:phone":"+61 2 9977 7815",
    "sg:postcode":"2094",
    "sg:province":"NSW",
    "sg:tags":[
        "industrial",
        "commercial",
        "contractor"
    ],
    "wof:name":"Manly Carpet Cleaning",
    "wof:placetype":"venue"
},
  "geometry": {"coordinates":[151.280487061,-33.7917404175],"type":"Point"}
}