{
  "type": "Feature",
  "properties": {
    "iso:country":"AU",
    "sg:address":"6 Edward St",
    "sg:city":"Norwood",
    "sg:classifiers":[
        {
            "category":"Health Services",
            "subcategory":"Health Practitioner",
            "type":"Services"
        }
    ],
    "sg:phone":"+61 8 8362 8369",
    "sg:postcode":"5067",
    "sg:province":"SA",
    "sg:tags":[
        "hypnotherapy"
    ],
    "wof:name":"N-Rich Psychology Services",
    "wof:placetype":"venue"
},
  "geometry": {"coordinates":[138.63414001500001,-34.9153785706],"type":"Point"}
}