{
  "type": "Feature",
  "properties": {
    "addr:full":"2 Rumbalara Rd Mooroopna VIC 3629",
    "addr:housenumber":"2",
    "addr:postcode":"3629",
    "addr:street":"Rumbalara Rd",
    "iso:country":"AU",
    "sg:address":"2 Rumbalara Rd",
    "sg:city":"Mooroopna",
    "sg:classifiers":[
        {
            "category":"Organizations",
            "subcategory":"Professional Association",
            "type":"Services"
        }
    ],
    "sg:phone":"+61 3 5825 3700",
    "sg:postcode":"3629",
    "sg:province":"VIC",
    "sg:tags":[
        "rural",
        "organisation",
        "production",
        "primary"
    ],
    "wof:name":"Northern Victoria Fruitgrowers Association",
    "wof:placetype":"venue"
},
  "geometry": {"coordinates":[145.351806641,-36.4042739868],"type":"Point"}
}