{
  "type": "Feature",
  "properties": {
    "addr:full":"1073 Waterworks Rd The Gap QLD 4061",
    "addr:housenumber":"1073",
    "addr:postcode":"4061",
    "addr:street":"Waterworks Rd",
    "iso:country":"AU",
    "sg:address":"1073 Waterworks Rd",
    "sg:city":"The Gap",
    "sg:classifiers":[
        {
            "category":"Education",
            "subcategory":"Dance Studio",
            "type":"Public Place"
        }
    ],
    "sg:phone":"+61 7 3312 2452",
    "sg:postcode":"4061",
    "sg:province":"QLD",
    "sg:tags":[
        "venue",
        "tuition"
    ],
    "wof:name":"Image Dance Studio",
    "wof:placetype":"venue"
},
  "geometry": {"coordinates":[152.94685363799999,-27.4439048767],"type":"Point"}
}