{
  "type": "Feature",
  "properties": {
    "addr:full":"134 Musgrave St North Rockhampton QLD 4701",
    "addr:housenumber":"134",
    "addr:postcode":"4701",
    "addr:street":"Musgrave St North",
    "iso:country":"AU",
    "sg:address":"134 Musgrave St",
    "sg:city":"North Rockhampton",
    "sg:classifiers":[
        {
            "category":"Autos & Motor Vehicles",
            "subcategory":"Automobile Sales",
            "type":"Retail Goods"
        }
    ],
    "sg:phone":"+61 7 4922 6255",
    "sg:postcode":"4701",
    "sg:province":"QLD",
    "sg:tags":[
        "car",
        "new"
    ],
    "wof:name":"Rockhampton Motor Company",
    "wof:placetype":"venue"
},
  "geometry": {"coordinates":[150.522094727,-23.3647480011],"type":"Point"}
}