{
  "type": "Feature",
  "properties": {
    "addr:full":"4 Terminus St Cobram NSW 3644",
    "addr:housenumber":"4",
    "addr:postcode":"3644",
    "addr:street":"Terminus St",
    "iso:country":"AU",
    "sg:address":"4 Terminus St",
    "sg:city":"Cobram",
    "sg:classifiers":[
        {
            "category":"Professional",
            "subcategory":"Accounting & Tax Preparation",
            "type":"Services"
        }
    ],
    "sg:phone":"+61 3 5872 2900",
    "sg:postcode":"3644",
    "sg:province":"NSW",
    "sg:tags":[
        "accountant",
        "auditor"
    ],
    "wof:name":"Bourke Accounting Pty Ltd",
    "wof:placetype":"venue"
},
  "geometry": {"coordinates":[145.64674377399999,-35.9174118042],"type":"Point"}
}