{
  "type": "Feature",
  "properties": {
    "addr:full":"2/19-21 Coldstream St Yamba NSW 2464",
    "addr:housenumber":"/ 19-21",
    "addr:postcode":"2464",
    "addr:street":"Coldstream St",
    "iso:country":"AU",
    "sg:address":"2/19-21 Coldstream St",
    "sg:city":"Yamba",
    "sg:classifiers":[
        {
            "category":"Professional",
            "subcategory":"Engineering",
            "type":"Services"
        }
    ],
    "sg:phone":"+61 2 6646 9018",
    "sg:postcode":"2464",
    "sg:province":"NSW",
    "sg:tags":[
        "consulting",
        "engineer"
    ],
    "wof:name":"Michael Samms & Associates Pty Ltd",
    "wof:placetype":"venue"
},
  "geometry": {"coordinates":[153.35992431599999,-29.4370765686],"type":"Point"}
}