{
  "type": "Feature",
  "properties": {
    "addr:full":"27 Majestic Drv Emerald VIC 3782",
    "addr:housenumber":"27",
    "addr:postcode":"3782",
    "addr:street":"Majestic Drv",
    "iso:country":"AU",
    "sg:address":"27 Majestic Drv",
    "sg:city":"Emerald",
    "sg:classifiers":[
        {
            "category":"Home & Garden",
            "subcategory":"Carpets & Floor Coverings",
            "type":"Retail Goods"
        }
    ],
    "sg:phone":"+61 417 571 866",
    "sg:postcode":"3782",
    "sg:province":"VIC",
    "sg:tags":[
        "tile",
        "wall",
        "layer"
    ],
    "wof:name":"S & N Tiling",
    "wof:placetype":"venue"
},
  "geometry": {"coordinates":[145.46963500000001,-37.937241],"type":"Point"}
}