{
  "type": "Feature",
  "properties": {
    "addr:full":"82- 86 Fyans St Geelong South VIC 3220",
    "addr:housenumber":"86",
    "addr:postcode":"3220",
    "addr:street":"Fyans St",
    "iso:country":"AU",
    "sg:address":"82- 86 Fyans St",
    "sg:city":"Geelong South",
    "sg:classifiers":[
        {
            "category":"Shopping",
            "subcategory":"Pets & Pet Supplies",
            "type":"Retail Goods"
        }
    ],
    "sg:phone":"+61 3 5222 7900",
    "sg:postcode":"3220",
    "sg:province":"VIC",
    "sg:tags":[
        "food"
    ],
    "wof:name":"Pets For Us",
    "wof:placetype":"venue"
},
  "geometry": {"coordinates":[144.356247,-38.162354],"type":"Point"}
}