{
  "type": "Feature",
  "properties": {
    "iso:country":"AU",
    "sg:address":"26/ 15 Begonia St",
    "sg:city":"Pagewood",
    "sg:classifiers":[
        {
            "category":"Sports & Exercise",
            "subcategory":"Gym",
            "type":"Entertainment"
        }
    ],
    "sg:phone":"+61 402 216 682",
    "sg:postcode":"2035",
    "sg:province":"NSW",
    "sg:tags":[
        "personal",
        "trainer",
        "fitness"
    ],
    "wof:name":"Performance Plus - Fitness & Personal Training",
    "wof:placetype":"venue"
},
  "geometry": {"coordinates":[151.23985290499999,-33.9489631653],"type":"Point"}
}