{
  "type": "Feature",
  "properties": {
    "addr:full":"6/ 144 Camberwell Rd Hawthorn East VIC 3123",
    "addr:housenumber":"/ 144",
    "addr:postcode":"3123",
    "addr:street":"Camberwell Rd",
    "iso:country":"AU",
    "sg:address":"6/ 144 Camberwell Rd",
    "sg:city":"Hawthorn East",
    "sg:classifiers":[
        {
            "category":"Professional",
            "subcategory":"Computer Services",
            "type":"Services"
        }
    ],
    "sg:phone":"+61 3 9813 3000",
    "sg:postcode":"3123",
    "sg:province":"VIC",
    "sg:tags":[
        "package",
        "software"
    ],
    "wof:name":"Acacia Consulting Services Pty Ltd",
    "wof:placetype":"venue"
},
  "geometry": {"coordinates":[145.053756714,-37.8289375305],"type":"Point"}
}