{
  "type": "Feature",
  "properties": {
    "iso:country":"AU",
    "sg:address":"6/ 10 Rodborough Rd",
    "sg:city":"Frenchs Forest",
    "sg:classifiers":[
        {
            "category":"Wholesale",
            "subcategory":"Drugs",
            "type":"Manufacturing & Wholesale Goods"
        }
    ],
    "sg:phone":"+61 2 9975 5666",
    "sg:postcode":"2086",
    "sg:province":"NSW",
    "sg:tags":[
        "wholesaler",
        "pharmaceutical",
        "product",
        "mfrs"
    ],
    "wof:name":"Kirsch Pharma Australia Pty Ltd",
    "wof:placetype":"venue"
},
  "geometry": {"coordinates":[151.24407959000001,-33.7535209656],"type":"Point"}
}