{
  "type": "Feature",
  "properties": {
    "addr:full":"20 Blue Waters Drv Ocean Grove VIC 3226",
    "addr:housenumber":"20",
    "addr:postcode":"3226",
    "addr:street":"Blue Waters Drv",
    "iso:country":"AU",
    "sg:address":"20 Blue Waters Drv",
    "sg:city":"Ocean Grove",
    "sg:classifiers":[
        {
            "category":"Professional",
            "subcategory":"Art Services",
            "type":"Services"
        }
    ],
    "sg:phone":"+61 3 5255 4902",
    "sg:postcode":"3226",
    "sg:province":"VIC",
    "sg:tags":[
        "graphic",
        "designer"
    ],
    "wof:name":"Atomo Pty Ltd",
    "wof:placetype":"venue"
},
  "geometry": {"coordinates":[144.511932,-38.25639],"type":"Point"}
}