{
  "type": "Feature",
  "properties": {
    "iso:country":"AU",
    "sg:address":"Suite 11, 94 Karimbla Rd",
    "sg:city":"Miranda",
    "sg:classifiers":[
        {
            "category":"Health Services",
            "subcategory":"Doctor",
            "type":"Services"
        }
    ],
    "sg:phone":"+61 2 9525 8446",
    "sg:postcode":"2228",
    "sg:province":"NSW",
    "sg:tags":[
        "podiatrist"
    ],
    "wof:name":"Frogley Matthew",
    "wof:placetype":"venue"
},
  "geometry": {"coordinates":[151.102050781,-34.0371856689],"type":"Point"}
}