{
  "type": "Feature",
  "properties": {
    "iso:country":"AU",
    "sg:address":"274 Richardson St",
    "sg:city":"Middle Park",
    "sg:classifiers":[
        {
            "category":"Personal",
            "subcategory":"Beauty Salon",
            "type":"Services"
        }
    ],
    "sg:phone":"+61 3 9699 7299",
    "sg:postcode":"3206",
    "sg:province":"VIC",
    "wof:name":"Scope Beauty & Body Therapy",
    "wof:placetype":"venue"
},
  "geometry": {"coordinates":[144.96336400000001,-37.850433],"type":"Point"}
}