{
  "type": "Feature",
  "properties": {
    "addr:full":"Shop 5, Liverpool La Wodonga NSW 3690",
    "addr:housenumber":"shop 5",
    "addr:postcode":"3690",
    "addr:street":"Liverpool La",
    "iso:country":"AU",
    "sg:address":"Shop 5, Liverpool La",
    "sg:city":"Wodonga",
    "sg:classifiers":[
        {
            "category":"Professional",
            "subcategory":"Art Services",
            "type":"Services"
        }
    ],
    "sg:phone":"+61 2 6024 5621",
    "sg:postcode":"3690",
    "sg:province":"NSW",
    "sg:tags":[
        "picture",
        "frame",
        "framing"
    ],
    "wof:name":"Memorable Hangups",
    "wof:placetype":"venue"
},
  "geometry": {"coordinates":[146.88203430199999,-36.1162872314],"type":"Point"}
}