{
  "type": "Feature",
  "properties": {
    "iso:country":"AU",
    "sg:address":"113 Pyrmont St",
    "sg:city":"Pyrmont",
    "sg:classifiers":[
        {
            "category":"Manufacturing",
            "subcategory":"Apparel",
            "type":"Manufacturing & Wholesale Goods"
        }
    ],
    "sg:phone":"+61 2 9692 0988",
    "sg:postcode":"2009",
    "sg:province":"NSW",
    "sg:tags":[
        "wholesaler",
        "mfrs",
        "lady",
        "suit"
    ],
    "wof:name":"Barometer Pty Ltd",
    "wof:placetype":"venue"
},
  "geometry": {"coordinates":[151.195144653,-33.8699874878],"type":"Point"}
}