{
  "type": "Feature",
  "properties": {
    "addr:full":"8 Riddell St Warialda NSW 2402",
    "addr:housenumber":"8",
    "addr:postcode":"2402",
    "addr:street":"Riddell St",
    "iso:country":"AU",
    "sg:address":"8 Riddell St",
    "sg:city":"Warialda",
    "sg:classifiers":[
        {
            "category":"Military Area",
            "subcategory":"Air Force Base",
            "type":"Public Place"
        }
    ],
    "sg:phone":"+61 2 6729 1249",
    "sg:postcode":"2402",
    "sg:province":"NSW",
    "sg:tags":[
        "windmill"
    ],
    "wof:name":"Hagues Windmills",
    "wof:placetype":"venue"
},
  "geometry": {"coordinates":[150.56617736800001,-29.5382518768],"type":"Point"}
}