{
  "type": "Feature",
  "properties": {
    "iso:country":"AU",
    "sg:address":"49- 51 Stead St",
    "sg:city":"South Melbourne",
    "sg:classifiers":[
        {
            "category":"Professional",
            "subcategory":"Computer Services",
            "type":"Services"
        }
    ],
    "sg:phone":"+61 3 9690 0660",
    "sg:postcode":"3205",
    "sg:province":"VIC",
    "sg:tags":[
        "consultant",
        "system"
    ],
    "wof:name":"Peevee Software Solutions Pty Ltd",
    "wof:placetype":"venue"
},
  "geometry": {"coordinates":[144.96885700000001,-37.835587],"type":"Point"}
}