{
  "type": "Feature",
  "properties": {
    "iso:country":"AU",
    "sg:address":"293 High St",
    "sg:city":"Ashburton",
    "sg:classifiers":[
        {
            "category":"Manufacturing",
            "subcategory":"Furniture",
            "type":"Manufacturing & Wholesale Goods"
        }
    ],
    "sg:phone":"+61 3 9885 9780",
    "sg:postcode":"3147",
    "sg:province":"VIC",
    "sg:tags":[
        "builder",
        "designer",
        "custom"
    ],
    "wof:name":"Mr Pine Furniture",
    "wof:placetype":"venue"
},
  "geometry": {"coordinates":[145.08164977999999,-37.8635139465],"type":"Point"}
}