{
  "type": "Feature",
  "properties": {
    "addr:full":"4/ 34 Avoca Drv Kincumber NSW 2251",
    "addr:housenumber":"/ 34",
    "addr:postcode":"2251",
    "addr:street":"Avoca Drv",
    "iso:country":"AU",
    "sg:address":"4/ 34 Avoca Drv",
    "sg:city":"Kincumber",
    "sg:classifiers":[
        {
            "category":"Shopping",
            "subcategory":"Bicycles & Sporting Goods",
            "type":"Retail Goods"
        }
    ],
    "sg:phone":"+61 2 4369 0090",
    "sg:postcode":"2251",
    "sg:province":"NSW",
    "sg:tags":[
        "chemical",
        "equipment",
        "pool",
        "swimming"
    ],
    "wof:name":"Kincumber Pools Plus",
    "wof:placetype":"venue"
},
  "geometry": {"coordinates":[151.37156677199999,-33.4642753601],"type":"Point"}
}