{
  "type": "Feature",
  "properties": {
    "addr:full":"20 Saltair St Caloundra QLD 4551",
    "addr:housenumber":"20",
    "addr:postcode":"4551",
    "addr:street":"Saltair St",
    "iso:country":"AU",
    "sg:address":"20 Saltair St",
    "sg:city":"Caloundra",
    "sg:classifiers":[
        {
            "category":"Utilities",
            "subcategory":"Refuse",
            "type":"Services"
        }
    ],
    "sg:phone":"+61 7 5492 5363",
    "sg:postcode":"4551",
    "sg:province":"QLD",
    "sg:tags":[
        "remover",
        "rubbish"
    ],
    "wof:name":"Best Value Rubbish Removals",
    "wof:placetype":"venue"
},
  "geometry": {"coordinates":[153.139282227,-26.800409317],"type":"Point"}
}