{
  "type": "Feature",
  "properties": {
    "addr:full":"64 Cranford Ave Brentwood WA 6153",
    "addr:housenumber":"64",
    "addr:postcode":"6153",
    "addr:street":"Cranford Ave",
    "iso:country":"AU",
    "sg:address":"64 Cranford Ave",
    "sg:city":"Brentwood",
    "sg:classifiers":[
        {
            "category":"Government",
            "subcategory":"Post Office",
            "type":"Public Place"
        }
    ],
    "sg:phone":"+61 8 9364 2792",
    "sg:postcode":"6153",
    "sg:province":"WA",
    "sg:tags":[
        "postal"
    ],
    "wof:name":"Australia Post",
    "wof:placetype":"venue"
},
  "geometry": {"coordinates":[115.849632,-32.04092],"type":"Point"}
}