{
  "type": "Feature",
  "properties": {
    "iso:country":"AU",
    "sg:address":"9 Baker St",
    "sg:city":"Kensington",
    "sg:classifiers":[
        {
            "category":"Wholesale",
            "subcategory":"Painting Supplies",
            "type":"Manufacturing & Wholesale Goods"
        }
    ],
    "sg:phone":"+61 2 9663 4676",
    "sg:postcode":"2033",
    "sg:province":"NSW",
    "sg:tags":[
        "product",
        "cleaning"
    ],
    "wof:name":"Amway Of Australia Pty Ltd",
    "wof:placetype":"venue"
},
  "geometry": {"coordinates":[151.21577500000001,-33.907829],"type":"Point"}
}