{
  "type": "Feature",
  "properties": {
    "addr:full":"615 Princess Hwy Blakehurst NSW 2221",
    "addr:housenumber":"615",
    "addr:postcode":"2221",
    "addr:street":"Princess Hwy",
    "iso:country":"AU",
    "sg:address":"615 Princess Hwy",
    "sg:city":"Blakehurst",
    "sg:classifiers":[
        {
            "category":"Real Estate",
            "subcategory":"Real Estate Agent",
            "type":"Services"
        }
    ],
    "sg:phone":"+61 2 9547 1355",
    "sg:postcode":"2221",
    "sg:province":"NSW",
    "wof:name":"L J Hooker",
    "wof:placetype":"venue"
},
  "geometry": {"coordinates":[151.11155700699999,-33.9881401062],"type":"Point"}
}