{
  "type": "Feature",
  "properties": {
    "addr:full":"14 Grevillea Ave Mullumbimby NSW 2482",
    "addr:housenumber":"14",
    "addr:postcode":"2482",
    "addr:street":"Grevillea Ave",
    "iso:country":"AU",
    "sg:address":"14 Grevillea Ave",
    "sg:city":"Mullumbimby",
    "sg:classifiers":[
        {
            "category":"Retail",
            "subcategory":"Repair Shop",
            "type":"Services"
        }
    ],
    "sg:phone":"+61 2 6684 3242",
    "sg:postcode":"2482",
    "sg:province":"NSW",
    "sg:tags":[
        "repairing",
        "piano",
        "tuning"
    ],
    "wof:name":"Appel, Norman",
    "wof:placetype":"venue"
},
  "geometry": {"coordinates":[153.501953125,-28.54920578],"type":"Point"}
}