{
  "type": "Feature",
  "properties": {
    "iso:country":"AU",
    "sg:address":"3/ 30 Charles St",
    "sg:city":"Warners Bay",
    "sg:classifiers":[
        {
            "category":"Health Services",
            "subcategory":"Doctor",
            "type":"Services"
        }
    ],
    "sg:phone":"+61 2 4948 5630",
    "sg:postcode":"2282",
    "sg:province":"NSW",
    "sg:tags":[
        "medical",
        "practitioner"
    ],
    "wof:name":"Best Trevor N",
    "wof:placetype":"venue"
},
  "geometry": {"coordinates":[151.645721436,-32.9718780518],"type":"Point"}
}