{
  "type": "Feature",
  "properties": {
    "iso:country":"AU",
    "sg:address":"4/48 McLeod St",
    "sg:city":"Cairns",
    "sg:classifiers":[
        {
            "category":"Manufacturing",
            "subcategory":"Musical Instruments",
            "type":"Manufacturing & Wholesale Goods"
        }
    ],
    "sg:phone":"+61 419 667 689",
    "sg:postcode":"4870",
    "sg:province":"QLD",
    "sg:tags":[
        "repair",
        "maker"
    ],
    "wof:name":"Austwide Speaker Doctor",
    "wof:placetype":"venue"
},
  "geometry": {"coordinates":[145.77215576200001,-16.9235248566],"type":"Point"}
}