{
  "type": "Feature",
  "properties": {
    "iso:country":"AU",
    "sg:address":"51 Raymond St",
    "sg:city":"Bankstown",
    "sg:classifiers":[
        {
            "category":"Building & Trades",
            "subcategory":"Construction",
            "type":"Services"
        }
    ],
    "sg:phone":"+61 2 9790 3555",
    "sg:postcode":"2200",
    "sg:province":"NSW",
    "sg:tags":[
        "contractor"
    ],
    "wof:name":"Silky Constructions",
    "wof:placetype":"venue"
},
  "geometry": {"coordinates":[151.03627,-33.919586],"type":"Point"}
}