{
  "type": "Feature",
  "properties": {
    "addr:full":"Shed 6/ 94 Nolan St Bendigo VIC 3550",
    "addr:housenumber":"6 / 94",
    "addr:postcode":"3550",
    "addr:street":"Nolan St",
    "iso:country":"AU",
    "sg:address":"Shed 6/ 94 Nolan St",
    "sg:city":"Bendigo",
    "sg:classifiers":[
        {
            "category":"Retail",
            "subcategory":"Car Wash",
            "type":"Services"
        }
    ],
    "sg:phone":"+61 3 5444 3770",
    "sg:postcode":"3550",
    "sg:province":"VIC",
    "sg:tags":[
        "truck",
        "cleaning"
    ],
    "wof:name":"Xlb Detailing",
    "wof:placetype":"venue"
},
  "geometry": {"coordinates":[144.282592773,-36.7406616211],"type":"Point"}
}