{
  "type": "Feature",
  "properties": {
    "iso:country":"AU",
    "sg:address":"32 Bent St St",
    "sg:city":"Marys",
    "sg:classifiers":[
        {
            "category":"Banks & Credit Unions",
            "subcategory":"Atm",
            "type":"Services"
        }
    ],
    "sg:phone":"+61 2 9623 8809",
    "sg:postcode":"2760",
    "sg:province":"NSW",
    "sg:tags":[
        "reconditioners",
        "drum",
        "manufacturers"
    ],
    "wof:name":"Alkem Drums",
    "wof:placetype":"venue"
},
  "geometry": {"coordinates":[150.77142334000001,-33.7492828369],"type":"Point"}
}