{
  "type": "Feature",
  "properties": {
    "iso:country":"AU",
    "sg:address":"28b Isles Drv",
    "sg:city":"Coffs Harbour",
    "sg:classifiers":[
        {
            "category":"Wholesale",
            "subcategory":"Electrical",
            "type":"Manufacturing & Wholesale Goods"
        }
    ],
    "sg:phone":"+61 2 6658 0797",
    "sg:postcode":"2450",
    "sg:province":"NSW",
    "sg:tags":[
        "wholesaler"
    ],
    "wof:name":"CNW Pty Ltd",
    "wof:placetype":"venue"
},
  "geometry": {"coordinates":[153.08813499999999,-30.31572],"type":"Point"}
}