{
  "type": "Feature",
  "properties": {
    "addr:full":"10 Orana Ave Moree NSW 2400",
    "addr:housenumber":"10",
    "addr:postcode":"2400",
    "addr:street":"Orana Ave",
    "iso:country":"AU",
    "sg:address":"10 Orana Ave",
    "sg:city":"Moree",
    "sg:classifiers":[
        {
            "category":"Education",
            "subcategory":"Kindergarten",
            "type":"Public Place"
        }
    ],
    "sg:phone":"+61 2 6752 2225",
    "sg:postcode":"2400",
    "sg:province":"NSW",
    "sg:tags":[
        "pre-schools"
    ],
    "wof:name":"Moree Pre-School (INC)",
    "wof:placetype":"venue"
},
  "geometry": {"coordinates":[149.83770751899999,-29.4531326294],"type":"Point"}
}