{
  "type": "Feature",
  "properties": {
    "addr:full":"Westfield Shopping Centre, Cnr Cross St & Park Rd Hurstville NSW 2220",
    "addr:postcode":"2220",
    "addr:street":"Cnr Cross St & Park Rd",
    "iso:country":"AU",
    "sg:address":"Westfield Shopping Centre, Cnr Cross St & Park Rd",
    "sg:city":"Hurstville",
    "sg:classifiers":[
        {
            "category":"Transit Center",
            "subcategory":"Passenger",
            "type":"Transportation"
        }
    ],
    "sg:phone":"+61 2 9586 2599",
    "sg:postcode":"2220",
    "sg:province":"NSW",
    "sg:tags":[
        "retail",
        "toiletry",
        "perfume"
    ],
    "wof:name":"The Perfume Connection",
    "wof:placetype":"venue"
},
  "geometry": {"coordinates":[151.10418701200001,-33.965965271],"type":"Point"}
}