{
  "type": "Feature",
  "properties": {
    "iso:country":"AU",
    "sg:address":"114 Capel St",
    "sg:city":"North Melbourne",
    "sg:classifiers":[
        {
            "category":"Professional",
            "subcategory":"Art Services",
            "type":"Services"
        }
    ],
    "sg:phone":"+61 3 9486 3215",
    "sg:postcode":"3051",
    "sg:province":"VIC",
    "sg:tags":[
        "product",
        "industrial",
        "designer"
    ],
    "wof:name":"Niche Design Group",
    "wof:placetype":"venue"
},
  "geometry": {"coordinates":[144.95538330100001,-37.8054084778],"type":"Point"}
}