{
  "type": "Feature",
  "properties": {
    "iso:country":"AU",
    "sg:address":"157 Trimmer Pde",
    "sg:city":"Seaton",
    "sg:classifiers":[
        {
            "category":"Shopping",
            "type":"Retail Goods"
        }
    ],
    "sg:phone":"+61 8 8445 8919",
    "sg:postcode":"5023",
    "sg:province":"SA",
    "sg:tags":[
        "produce",
        "grain"
    ],
    "wof:name":"Rapuano's Grain Store",
    "wof:placetype":"venue"
},
  "geometry": {"coordinates":[138.51641845699999,-34.891872406],"type":"Point"}
}