{
  "type": "Feature",
  "properties": {
    "addr:full":"30 Second St Cowell SA 5602",
    "addr:housenumber":"30",
    "addr:postcode":"5602",
    "addr:street":"Second St",
    "iso:country":"AU",
    "sg:address":"30 Second St",
    "sg:city":"Cowell",
    "sg:classifiers":[
        {
            "category":"Retail",
            "subcategory":"Auto Repair",
            "type":"Services"
        }
    ],
    "sg:phone":"+61 8 8629 2626",
    "sg:postcode":"5602",
    "sg:province":"SA",
    "sg:tags":[
        "repairer",
        "motor",
        "engineer"
    ],
    "wof:name":"Inglis Auto Repairs",
    "wof:placetype":"venue"
},
  "geometry": {"coordinates":[136.92283599999999,-33.681953],"type":"Point"}
}