{
  "type": "Feature",
  "properties": {
    "addr:full":"40 Murray St Nuriootpa SA 5355",
    "addr:housenumber":"40",
    "addr:postcode":"5355",
    "addr:street":"Murray St",
    "iso:country":"AU",
    "sg:address":"40 Murray St",
    "sg:city":"Nuriootpa",
    "sg:classifiers":[
        {
            "category":"Food & Beverages",
            "subcategory":"Bakery",
            "type":"Retail Goods"
        }
    ],
    "sg:phone":"+61 8 8562 1129",
    "sg:postcode":"5355",
    "sg:province":"SA",
    "sg:tags":[
        "baker"
    ],
    "wof:name":"Linke's Nuriootpa Bakery & Tearoom",
    "wof:placetype":"venue"
},
  "geometry": {"coordinates":[138.99659729000001,-34.4713020325],"type":"Point"}
}