{
  "type": "Feature",
  "properties": {
    "iso:country":"AU",
    "sg:address":"Cnr Lake & Blackbutt Rd",
    "sg:city":"Port Macquarie",
    "sg:classifiers":[
        {
            "category":"Insurance",
            "subcategory":"Hazard Insurance",
            "type":"Services"
        }
    ],
    "sg:phone":"+61 2 6581 3363",
    "sg:postcode":"2444",
    "sg:province":"NSW",
    "sg:tags":[
        "fire",
        "accident",
        "marine"
    ],
    "wof:name":"Hastings Insurance Centre Pty Ltd",
    "wof:placetype":"venue"
},
  "geometry": {"coordinates":[152.911469,-31.434656],"type":"Point"}
}