{
  "type": "Feature",
  "properties": {
    "addr:full":"PO Box 43 Gracemere QLD 4702",
    "addr:postcode":"4702",
    "iso:country":"AU",
    "sg:address":"PO Box 43",
    "sg:city":"Gracemere",
    "sg:classifiers":[
        {
            "category":"Building & Trades",
            "subcategory":"Construction",
            "type":"Services"
        }
    ],
    "sg:phone":"+61 7 4933 4611",
    "sg:postcode":"4702",
    "sg:province":"QLD",
    "sg:tags":[
        "insulation",
        "contractor"
    ],
    "wof:name":"Capricorn Insulation",
    "wof:placetype":"venue"
},
  "geometry": {"coordinates":[150.452194214,-23.4334201813],"type":"Point"}
}