{
  "type": "Feature",
  "properties": {
    "addr:full":"2215 The Northern Rd Luddenham NSW 2745",
    "addr:housenumber":"2215",
    "addr:postcode":"2745",
    "addr:street":"The Northern Rd",
    "iso:country":"AU",
    "sg:address":"2215 The Northern Rd",
    "sg:city":"Luddenham",
    "sg:classifiers":[
        {
            "category":"Farming",
            "subcategory":"Farm",
            "type":"Manufacturing & Wholesale Goods"
        }
    ],
    "sg:phone":"+61 2 4773 4285",
    "sg:postcode":"2745",
    "sg:province":"NSW",
    "sg:tags":[
        "farmer"
    ],
    "wof:name":"AAA Christmas Tree Farm",
    "wof:placetype":"venue"
},
  "geometry": {"coordinates":[150.69760131800001,-33.8848495483],"type":"Point"}
}