{
  "type": "Feature",
  "properties": {
    "addr:full":"307 Takalvan St Bundaberg QLD 4670",
    "addr:housenumber":"307",
    "addr:postcode":"4670",
    "addr:street":"Takalvan St",
    "iso:country":"AU",
    "sg:address":"307 Takalvan St",
    "sg:city":"Bundaberg",
    "sg:classifiers":[
        {
            "category":"Food & Beverages",
            "subcategory":"Supermarket",
            "type":"Retail Goods"
        }
    ],
    "sg:phone":"+61 7 4152 0077",
    "sg:postcode":"4670",
    "sg:province":"QLD",
    "sg:tags":[
        "grocery",
        "store"
    ],
    "wof:name":"Action Supermarkets",
    "wof:placetype":"venue"
},
  "geometry": {"coordinates":[152.33688354500001,-24.8693504333],"type":"Point"}
}