{
  "type": "Feature",
  "properties": {
    "addr:full":"17 - 19 Spence St Cairns QLD 4870",
    "addr:housenumber":"19",
    "addr:postcode":"4870",
    "addr:street":"Spence St",
    "iso:country":"AU",
    "sg:address":"17 - 19 Spence St",
    "sg:city":"Cairns",
    "sg:classifiers":[
        {
            "category":"Banks & Credit Unions",
            "subcategory":"Bank",
            "type":"Services"
        }
    ],
    "sg:phone":"+61 7 4051 9188",
    "sg:postcode":"4870",
    "sg:province":"QLD",
    "wof:name":"Bank of Queensland",
    "wof:placetype":"venue"
},
  "geometry": {"coordinates":[145.77769470199999,-16.9236545563],"type":"Point"}
}