{
  "type": "Feature",
  "properties": {
    "iso:country":"AU",
    "sg:address":"15 Gaetana St",
    "sg:city":"Avondale Heights",
    "sg:classifiers":[
        {
            "category":"Building & Trades",
            "subcategory":"Construction",
            "type":"Services"
        }
    ],
    "sg:phone":"+61 3 9318 6837",
    "sg:postcode":"3034",
    "sg:province":"VIC",
    "sg:tags":[
        "renovation",
        "alterations",
        "extension",
        "contractor"
    ],
    "wof:name":"Elliott R B Home Extensions & Renovations",
    "wof:placetype":"venue"
},
  "geometry": {"coordinates":[144.866577,-37.769985],"type":"Point"}
}