{
  "type": "Feature",
  "properties": {
    "iso:country":"AU",
    "sg:address":"Level 1, 198- 204 Faraday St",
    "sg:city":"Carlton",
    "sg:classifiers":[
        {
            "category":"Health Services",
            "subcategory":"Health Practitioner",
            "type":"Services"
        }
    ],
    "sg:phone":"+61 3 9347 9600",
    "sg:postcode":"3053",
    "sg:province":"VIC",
    "sg:tags":[
        "physiotherapist"
    ],
    "wof:name":"Energize Physio & Clinical Pilates",
    "wof:placetype":"venue"
},
  "geometry": {"coordinates":[144.967819214,-37.7985801697],"type":"Point"}
}