{
  "type": "Feature",
  "properties": {
    "iso:country":"AU",
    "sg:address":"61 Matthews Ave",
    "sg:city":"Airport West",
    "sg:classifiers":[
        {
            "category":"Wholesale",
            "subcategory":"Electrical",
            "type":"Manufacturing & Wholesale Goods"
        }
    ],
    "sg:phone":"+61 3 9338 3611",
    "sg:postcode":"3042",
    "sg:province":"VIC",
    "sg:tags":[
        "wholesaler"
    ],
    "wof:name":"Middendorp Electric Co Pty Ltd",
    "wof:placetype":"venue"
},
  "geometry": {"coordinates":[144.89007568400001,-37.7288284302],"type":"Point"}
}