{
  "type": "Feature",
  "properties": {
    "addr:full":"46 Wilson St Curtin ACT 2605",
    "addr:housenumber":"46",
    "addr:postcode":"2605",
    "addr:street":"Wilson St",
    "iso:country":"AU",
    "sg:address":"46 Wilson St",
    "sg:city":"Curtin",
    "sg:classifiers":[
        {
            "category":"Building & Trades",
            "subcategory":"Plumbing",
            "type":"Services"
        }
    ],
    "sg:phone":"+61 2 6282 2626",
    "sg:postcode":"2605",
    "sg:province":"ACT",
    "sg:tags":[
        "consultant"
    ],
    "wof:name":"Action Plumbing Pty Ltd",
    "wof:placetype":"venue"
},
  "geometry": {"coordinates":[149.081298828,-35.3241615295],"type":"Point"}
}