{
  "type": "Feature",
  "properties": {
    "addr:full":"140A New England Hwy Rutherford NSW 2320",
    "addr:housenumber":"140a",
    "addr:postcode":"2320",
    "addr:street":"New England Hwy",
    "iso:country":"AU",
    "sg:address":"140A New England Hwy",
    "sg:city":"Rutherford",
    "sg:classifiers":[
        {
            "category":"Retail",
            "subcategory":"Driving School",
            "type":"Services"
        }
    ],
    "sg:phone":"+61 2 4931 9155",
    "sg:postcode":"2320",
    "sg:province":"NSW",
    "sg:website":"http://www.trucklicence.com.au",
    "wof:name":"Steven Beckett Heavy Vehicle Driver Training",
    "wof:placetype":"venue"
},
  "geometry": {"coordinates":[151.53770446799999,-32.720199585],"type":"Point"}
}