{
  "type": "Feature",
  "properties": {
    "iso:country":"AU",
    "sg:address":"5 Nambucca St",
    "sg:city":"Macksville",
    "sg:classifiers":[
        {
            "category":"Retail",
            "subcategory":"Repair Shop",
            "type":"Services"
        }
    ],
    "sg:phone":"+61 2 6568 1238",
    "sg:postcode":"2447",
    "sg:province":"NSW",
    "sg:tags":[
        "windscreen"
    ],
    "wof:name":"Kent Windscreens",
    "wof:placetype":"venue"
},
  "geometry": {"coordinates":[152.92274499999999,-30.707552],"type":"Point"}
}