{
  "type": "Feature",
  "properties": {
    "addr:full":"11 Parer St Reservoir VIC 3073",
    "addr:housenumber":"11",
    "addr:postcode":"3073",
    "addr:street":"Parer St",
    "iso:country":"AU",
    "sg:address":"11 Parer St",
    "sg:city":"Reservoir",
    "sg:classifiers":[
        {
            "category":"Transit Center",
            "subcategory":"Freight",
            "type":"Transportation"
        }
    ],
    "sg:phone":"+61 3 9462 1390",
    "sg:postcode":"3073",
    "sg:province":"VIC",
    "sg:tags":[
        "turner",
        "wood"
    ],
    "wof:name":"GA Brockwell Agencies",
    "wof:placetype":"venue"
},
  "geometry": {"coordinates":[144.98298645,-37.7095985413],"type":"Point"}
}