{
  "type": "Feature",
  "properties": {
    "iso:country":"AU",
    "sg:address":"Unit 3/ 16 Spine St",
    "sg:city":"Sumner Park",
    "sg:classifiers":[
        {
            "category":"Shopping",
            "type":"Retail Goods"
        }
    ],
    "sg:phone":"+61 7 3715 8711",
    "sg:postcode":"4074",
    "sg:province":"QLD",
    "sg:tags":[
        "equipment",
        "safety",
        "accessory"
    ],
    "wof:name":"Extreme Safety",
    "wof:placetype":"venue"
},
  "geometry": {"coordinates":[152.93707275400001,-27.5654983521],"type":"Point"}
}