{
  "type": "Feature",
  "properties": {
    "iso:country":"AU",
    "sg:address":"Shp62/ 235 Forest Lake Blv",
    "sg:city":"Forest Lake",
    "sg:classifiers":[
        {
            "category":"Shopping",
            "subcategory":"Clothing, Apparel, & Fashions",
            "type":"Retail Goods"
        }
    ],
    "sg:phone":"+61 7 3279 9779",
    "sg:postcode":"4078",
    "sg:province":"QLD",
    "sg:tags":[
        "lady",
        "wear"
    ],
    "wof:name":"Hot Ice",
    "wof:placetype":"venue"
},
  "geometry": {"coordinates":[152.96864318900001,-27.6256027222],"type":"Point"}
}