{
  "type": "Feature",
  "properties": {
    "addr:full":"72 Donaldson St Rocklea QLD 4106",
    "addr:housenumber":"72",
    "addr:postcode":"4106",
    "addr:street":"Donaldson St",
    "iso:country":"AU",
    "sg:address":"72 Donaldson St",
    "sg:city":"Rocklea",
    "sg:classifiers":[
        {
            "category":"Professional",
            "type":"Services"
        }
    ],
    "sg:phone":"+61 7 3275 0477",
    "sg:postcode":"4106",
    "sg:province":"QLD",
    "sg:tags":[
        "transport"
    ],
    "wof:name":"Carpentaria Metropoliton Transport",
    "wof:placetype":"venue"
},
  "geometry": {"coordinates":[152.98576355,-27.5392990112],"type":"Point"}
}