{
  "type": "Feature",
  "properties": {
    "iso:country":"AU",
    "sg:address":"PO Box 88",
    "sg:city":"Tambellup",
    "sg:classifiers":[
        {
            "category":"Farming",
            "subcategory":"Farm",
            "type":"Manufacturing & Wholesale Goods"
        }
    ],
    "sg:phone":"+61 8 9825 1121",
    "sg:postcode":"6320",
    "sg:province":"WA",
    "sg:tags":[
        "farmer"
    ],
    "wof:name":"Burridge L H & L",
    "wof:placetype":"venue"
},
  "geometry": {"coordinates":[117.63865661600001,-34.0404510498],"type":"Point"}
}