{
  "type": "Feature",
  "properties": {
    "addr:full":"Shop 58/ 972 Old Princes Hwy Engadine NSW 2233",
    "addr:housenumber":"shop 58 / 972",
    "addr:postcode":"2233",
    "addr:street":"Old Princes Hwy",
    "iso:country":"AU",
    "sg:address":"Shop 58/ 972 Old Princes Hwy",
    "sg:city":"Engadine",
    "sg:classifiers":[
        {
            "category":"Personal",
            "subcategory":"Beauty Salon",
            "type":"Services"
        }
    ],
    "sg:phone":"+61 2 9520 4481",
    "sg:postcode":"2233",
    "sg:province":"NSW",
    "wof:name":"Creative Mantra",
    "wof:placetype":"venue"
},
  "geometry": {"coordinates":[151.01629638700001,-34.0646324158],"type":"Point"}
}