{
  "type": "Feature",
  "properties": {
    "addr:full":"4b Charles St New Norfolk TAS 7140",
    "addr:housenumber":"4b",
    "addr:postcode":"7140",
    "addr:street":"Charles St",
    "iso:country":"AU",
    "sg:address":"4b Charles St",
    "sg:city":"New Norfolk",
    "sg:classifiers":[
        {
            "category":"Personal",
            "subcategory":"Beauty Salon",
            "type":"Services"
        }
    ],
    "sg:phone":"+61 3 6261 2206",
    "sg:postcode":"7140",
    "sg:province":"TAS",
    "sg:tags":[
        "hairdresser"
    ],
    "wof:name":"Talking Heads Of New Norfolk",
    "wof:placetype":"venue"
},
  "geometry": {"coordinates":[147.064087,-42.780701],"type":"Point"}
}