{
  "type": "Feature",
  "properties": {
    "iso:country":"AU",
    "sg:address":"210 Toolborough Rd",
    "sg:city":"Yandina Creek",
    "sg:classifiers":[
        {
            "category":"Building & Trades",
            "subcategory":"Construction",
            "type":"Services"
        }
    ],
    "sg:phone":"+61 7 5446 6033",
    "sg:postcode":"4561",
    "sg:province":"QLD",
    "sg:tags":[
        "fencing",
        "contractor"
    ],
    "wof:name":"Surfside Fencing",
    "wof:placetype":"venue"
},
  "geometry": {"coordinates":[153.02093505900001,-26.5241794586],"type":"Point"}
}