{
  "type": "Feature",
  "properties": {
    "iso:country":"AU",
    "sg:address":"47 Moss St",
    "sg:city":"Slacks Creek",
    "sg:classifiers":[
        {
            "category":"Autos & Motor Vehicles",
            "subcategory":"Auto Supplies",
            "type":"Retail Goods"
        }
    ],
    "sg:phone":"+61 7 3808 3790",
    "sg:postcode":"4127",
    "sg:province":"QLD",
    "sg:tags":[
        "paint",
        "automotive"
    ],
    "wof:name":"Hart's Automotive Paint Supplies",
    "wof:placetype":"venue"
},
  "geometry": {"coordinates":[153.12164306599999,-27.622177124],"type":"Point"}
}