{
  "type": "Feature",
  "properties": {
    "iso:country":"AU",
    "sg:address":"352 King William St",
    "sg:city":"Adelaide",
    "sg:classifiers":[
        {
            "category":"Personal",
            "subcategory":"Beauty Salon",
            "type":"Services"
        }
    ],
    "sg:phone":"+61 8 8212 6630",
    "sg:postcode":"5000",
    "sg:province":"SA",
    "sg:tags":[
        "hairdresser"
    ],
    "wof:name":"Kutz On King",
    "wof:placetype":"venue"
},
  "geometry": {"coordinates":[138.60049438499999,-34.931892395],"type":"Point"}
}