{
  "type": "Feature",
  "properties": {
    "iso:country":"AU",
    "sg:address":"Stones Rd",
    "sg:city":"Ebenezer",
    "sg:classifiers":[
        {
            "category":"Manufacturing",
            "subcategory":"Food",
            "type":"Manufacturing & Wholesale Goods"
        }
    ],
    "sg:phone":"+61 1800 467 987",
    "sg:postcode":"2756",
    "sg:province":"NSW",
    "sg:tags":[
        "function",
        "catering"
    ],
    "wof:name":"Family Affair Catering & Spit Roasts",
    "wof:placetype":"venue"
},
  "geometry": {"coordinates":[150.89378356899999,-33.5198059082],"type":"Point"}
}