{
  "type": "Feature",
  "properties": {
    "addr:full":"Cherrybank Range Rd Mittagong NSW 2575",
    "addr:postcode":"2575",
    "addr:street":"Range Rd",
    "iso:country":"AU",
    "sg:address":"Cherrybank Range Rd",
    "sg:city":"Mittagong",
    "sg:classifiers":[
        {
            "category":"Organizations",
            "subcategory":"Community Association",
            "type":"Services"
        }
    ],
    "sg:phone":"+61 412 216 335",
    "sg:postcode":"2575",
    "sg:province":"NSW",
    "sg:tags":[
        "organisation",
        "family",
        "welfare"
    ],
    "wof:name":"Epilepsy Southern Highlands Support Group",
    "wof:placetype":"venue"
},
  "geometry": {"coordinates":[150.45265197800001,-34.4520797729],"type":"Point"}
}