{
  "type": "Feature",
  "properties": {
    "addr:full":"44 Oxley Ave Woody Point QLD 4019",
    "addr:housenumber":"44",
    "addr:postcode":"4019",
    "addr:street":"Oxley Ave",
    "iso:country":"AU",
    "sg:address":"44 Oxley Ave",
    "sg:city":"Woody Point",
    "sg:classifiers":[
        {
            "category":"Organizations",
            "subcategory":"Community Association",
            "type":"Services"
        }
    ],
    "sg:phone":"+61 7 3284 1891",
    "sg:postcode":"4019",
    "sg:province":"QLD",
    "sg:tags":[
        "organisation",
        "family",
        "welfare"
    ],
    "wof:name":"Save The Children Fund (Qld)",
    "wof:placetype":"venue"
},
  "geometry": {"coordinates":[153.10394287099999,-27.2603988647],"type":"Point"}
}