{
  "type": "Feature",
  "properties": {
    "addr:full":"78 Ardargie St Sunnybank QLD 4109",
    "addr:housenumber":"78",
    "addr:postcode":"4109",
    "addr:street":"Ardargie St",
    "iso:country":"AU",
    "sg:address":"78 Ardargie St",
    "sg:city":"Sunnybank",
    "sg:classifiers":[
        {
            "category":"Social Services",
            "subcategory":"Child Care",
            "type":"Services"
        }
    ],
    "sg:phone":"+61 7 3216 9899",
    "sg:postcode":"4109",
    "sg:province":"QLD",
    "wof:name":"Jacaranda Early Learning Centre",
    "wof:placetype":"venue"
},
  "geometry": {"coordinates":[153.06347656200001,-27.5848350525],"type":"Point"}
}