{
  "type": "Feature",
  "properties": {
    "addr:full":"Lower North East Rd Campbelltown SA 5074",
    "addr:postcode":"5074",
    "addr:street":"Lower North East Rd",
    "iso:country":"AU",
    "sg:address":"Lower North East Rd",
    "sg:city":"Campbelltown",
    "sg:classifiers":[
        {
            "category":"Social Services",
            "subcategory":"Adult Care",
            "type":"Services"
        }
    ],
    "sg:phone":"+61 418 828 372",
    "sg:postcode":"5074",
    "sg:province":"SA",
    "sg:tags":[
        "towing"
    ],
    "wof:name":"Deluxe Towing",
    "wof:placetype":"venue"
},
  "geometry": {"coordinates":[138.66368102999999,-34.8780555725],"type":"Point"}
}