{
  "type": "Feature",
  "properties": {
    "addr:full":"7 Mast Crt Waikiki WA 6169",
    "addr:housenumber":"7",
    "addr:postcode":"6169",
    "addr:street":"Mast Crt",
    "iso:country":"AU",
    "sg:address":"7 Mast Crt",
    "sg:city":"Waikiki",
    "sg:classifiers":[
        {
            "category":"Retail",
            "subcategory":"Laundry & Dry Cleaning",
            "type":"Services"
        }
    ],
    "sg:phone":"+61 8 9528 7808",
    "sg:postcode":"6169",
    "sg:province":"WA",
    "sg:tags":[
        "cloth",
        "supply"
    ],
    "wof:name":"Waikiki Rag Supplies",
    "wof:placetype":"venue"
},
  "geometry": {"coordinates":[115.752602,-32.317089],"type":"Point"}
}