{
  "type": "Feature",
  "properties": {
    "addr:full":"197 High St Cranbourne VIC 3977",
    "addr:housenumber":"197",
    "addr:postcode":"3977",
    "addr:street":"High St",
    "iso:country":"AU",
    "sg:address":"197 High St",
    "sg:city":"Cranbourne",
    "sg:classifiers":[
        {
            "category":"Health Services",
            "subcategory":"Doctor",
            "type":"Services"
        }
    ],
    "sg:phone":"+61 3 5991 1222",
    "sg:postcode":"3977",
    "sg:province":"VIC",
    "sg:tags":[
        "medical",
        "practitioner"
    ],
    "wof:name":"Casey Medical Centre",
    "wof:placetype":"venue"
},
  "geometry": {"coordinates":[145.28189086899999,-38.1037445068],"type":"Point"}
}