{
  "type": "Feature",
  "properties": {
    "iso:country":"AU",
    "sg:address":"Unit 4/ 39 Winton Rd",
    "sg:city":"Joondalup",
    "sg:classifiers":[
        {
            "category":"Professional",
            "subcategory":"Printing & Photocopies",
            "type":"Services"
        }
    ],
    "sg:phone":"+61 8 9300 9722",
    "sg:postcode":"6027",
    "sg:province":"WA",
    "sg:tags":[
        "plaque"
    ],
    "wof:name":"Adform Engraving And Signs",
    "wof:placetype":"venue"
},
  "geometry": {"coordinates":[115.761817932,-31.7494602203],"type":"Point"}
}