{
  "type": "Feature",
  "properties": {
    "iso:country":"AU",
    "sg:address":"18 Beach St",
    "sg:city":"Wollongong",
    "sg:classifiers":[
        {
            "category":"Transit Center",
            "subcategory":"Freight",
            "type":"Transportation"
        }
    ],
    "sg:phone":"+61 2 4226 4050",
    "sg:postcode":"2500",
    "sg:province":"NSW",
    "sg:tags":[
        "stevedore"
    ],
    "wof:name":"P&O Ports",
    "wof:placetype":"venue"
},
  "geometry": {"coordinates":[150.896637,-34.433201],"type":"Point"}
}