{
  "type": "Feature",
  "properties": {
    "iso:country":"AU",
    "sg:address":"13 Cronin St",
    "sg:city":"Manjimup",
    "sg:classifiers":[
        {
            "category":"Building & Trades",
            "subcategory":"Construction",
            "type":"Services"
        }
    ],
    "sg:phone":"+61 418 932 259",
    "sg:postcode":"6258",
    "sg:province":"WA",
    "sg:tags":[
        "earth",
        "excavating",
        "moving",
        "contractor"
    ],
    "wof:name":"Dinis Contractors",
    "wof:placetype":"venue"
},
  "geometry": {"coordinates":[116.13243103000001,-34.2459526062],"type":"Point"}
}