{
  "type": "Feature",
  "properties": {
    "addr:full":"Unit 3, 26 Kitiwah St Lonsdale SA 5160",
    "addr:housenumber":"26",
    "addr:postcode":"5160",
    "addr:street":"Kitiwah St",
    "iso:country":"AU",
    "sg:address":"Unit 3, 26 Kitiwah St",
    "sg:city":"Lonsdale",
    "sg:classifiers":[
        {
            "category":"Arts & Performance",
            "subcategory":"Music",
            "type":"Entertainment"
        }
    ],
    "sg:phone":"+61 8 8326 2866",
    "sg:postcode":"5160",
    "sg:province":"SA",
    "sg:tags":[
        "mobile",
        "jockey",
        "disc"
    ],
    "wof:name":"A.T.O.M. All Types of Music",
    "wof:placetype":"venue"
},
  "geometry": {"coordinates":[138.501556397,-35.1090049744],"type":"Point"}
}