{
  "type": "Feature",
  "properties": {
    "addr:full":"226 Brighton Rd Somerton Park SA 5044",
    "addr:housenumber":"226",
    "addr:postcode":"5044",
    "addr:street":"Brighton Rd",
    "iso:country":"AU",
    "sg:address":"226 Brighton Rd",
    "sg:city":"Somerton Park",
    "sg:classifiers":[
        {
            "category":"Autos & Motor Vehicles",
            "subcategory":"Automobile Sales",
            "type":"Retail Goods"
        }
    ],
    "sg:phone":"+61 8 8294 7205",
    "sg:postcode":"5044",
    "sg:province":"SA",
    "sg:tags":[
        "car",
        "used"
    ],
    "wof:name":"Beetlebest",
    "wof:placetype":"venue"
},
  "geometry": {"coordinates":[138.52166700000001,-34.997437],"type":"Point"}
}