{
  "type": "Feature",
  "properties": {
    "addr:full":"100 Fremantle Rd Gosnells WA 6110",
    "addr:housenumber":"100",
    "addr:postcode":"6110",
    "addr:street":"Fremantle Rd",
    "iso:country":"AU",
    "sg:address":"100 Fremantle Rd",
    "sg:city":"Gosnells",
    "sg:classifiers":[
        {
            "category":"Health Services",
            "subcategory":"Doctor",
            "type":"Services"
        }
    ],
    "sg:phone":"+61 8 9490 1103",
    "sg:postcode":"6110",
    "sg:province":"WA",
    "sg:tags":[
        "podiatrist"
    ],
    "wof:name":"Gosnells Podiatry Centre",
    "wof:placetype":"venue"
},
  "geometry": {"coordinates":[115.99124145499999,-32.0679016113],"type":"Point"}
}