{
  "type": "Feature",
  "properties": {
    "addr:full":"8 Launders Ave Wonga Park VIC 3115",
    "addr:housenumber":"8",
    "addr:postcode":"3115",
    "addr:street":"Launders Ave",
    "iso:country":"AU",
    "sg:address":"8 Launders Ave",
    "sg:city":"Wonga Park",
    "sg:classifiers":[
        {
            "category":"Manufacturing",
            "subcategory":"Motor Vehicles & Parts",
            "type":"Manufacturing & Wholesale Goods"
        }
    ],
    "sg:phone":"+61 3 9722 2842",
    "sg:postcode":"3115",
    "sg:province":"VIC",
    "sg:tags":[
        "replacement"
    ],
    "wof:name":"North Ringwood Auto Parts & Accessories",
    "wof:placetype":"venue"
},
  "geometry": {"coordinates":[145.26922607399999,-37.7383842468],"type":"Point"}
}