{
  "type": "Feature",
  "properties": {
    "iso:country":"AU",
    "sg:address":"40 Wanganui Rd",
    "sg:city":"Shepparton",
    "sg:classifiers":[
        {
            "category":"Autos & Motor Vehicles",
            "subcategory":"Fuel & Gas Station",
            "type":"Retail Goods"
        }
    ],
    "sg:phone":"+61 3 5821 0460",
    "sg:postcode":"3630",
    "sg:province":"VIC",
    "sg:tags":[
        "injection",
        "diesel"
    ],
    "wof:name":"Shepparton Diesel Fuel Injection Service",
    "wof:placetype":"venue"
},
  "geometry": {"coordinates":[145.39756774899999,-36.3474197388],"type":"Point"}
}