{
  "type": "Feature",
  "properties": {
    "iso:country":"AU",
    "sg:address":"10 Beagley St",
    "sg:city":"Kallista",
    "sg:classifiers":[
        {
            "category":"Banks & Credit Unions",
            "subcategory":"Bank",
            "type":"Services"
        }
    ],
    "sg:phone":"+61 3 9755 2617",
    "sg:postcode":"3791",
    "sg:province":"VIC",
    "sg:tags":[
        "line",
        "marking",
        "road"
    ],
    "wof:name":"Horticultural Marketing Services",
    "wof:placetype":"venue"
},
  "geometry": {"coordinates":[145.37022399899999,-37.8777732849],"type":"Point"}
}