{
  "type": "Feature",
  "properties": {
    "iso:country":"AU",
    "sg:address":"35- 37 Chickerell St",
    "sg:city":"Morwell",
    "sg:classifiers":[
        {
            "category":"Professional",
            "subcategory":"Detective & Security Services",
            "type":"Services"
        }
    ],
    "sg:phone":"+61 3 5134 5000",
    "sg:postcode":"3840",
    "sg:province":"VIC",
    "sg:tags":[
        "equipment",
        "window",
        "doors"
    ],
    "wof:name":"Gippsland Doors",
    "wof:placetype":"venue"
},
  "geometry": {"coordinates":[146.43641662600001,-38.2316589355],"type":"Point"}
}