{
  "type": "Feature",
  "properties": {
    "iso:country":"AU",
    "sg:address":"153 Keys Rd",
    "sg:city":"Moorabbin",
    "sg:classifiers":[
        {
            "category":"Professional",
            "subcategory":"Testing Lab",
            "type":"Services"
        }
    ],
    "sg:phone":"+61 3 8552 0600",
    "sg:postcode":"3189",
    "sg:province":"VIC",
    "sg:tags":[
        "inspection"
    ],
    "wof:name":"Marand Precision Engineering Pty Ltd",
    "wof:placetype":"venue"
},
  "geometry": {"coordinates":[145.07278442399999,-37.9738616943],"type":"Point"}
}