{
  "type": "Feature",
  "properties": {
    "iso:country":"AU",
    "sg:address":"Shop 14/ 1 St Quentins Ave",
    "sg:city":"Claremont",
    "sg:classifiers":[
        {
            "category":"Shopping",
            "subcategory":"Clothing, Apparel, & Fashions",
            "type":"Retail Goods"
        }
    ],
    "sg:phone":"+61 8 9385 3767",
    "sg:postcode":"6010",
    "sg:province":"WA",
    "sg:tags":[
        "lady",
        "wear"
    ],
    "wof:name":"Focus Clothing",
    "wof:placetype":"venue"
},
  "geometry": {"coordinates":[115.78109741199999,-31.9823303223],"type":"Point"}
}