{
  "type": "Feature",
  "properties": {
    "iso:country":"AU",
    "sg:address":"8 Booran Drv",
    "sg:city":"Woodridge",
    "sg:classifiers":[
        {
            "category":"Shopping Center",
            "type":"Public Place"
        }
    ],
    "sg:phone":"+61 7 3299 4555",
    "sg:postcode":"4114",
    "sg:province":"QLD",
    "sg:tags":[
        "riveting",
        "equipment",
        "rivet"
    ],
    "wof:name":"Aerofast Australia Pty Ltd",
    "wof:placetype":"venue"
},
  "geometry": {"coordinates":[153.115142822,-27.6231861115],"type":"Point"}
}