{
  "type": "Feature",
  "properties": {
    "iso:country":"AU",
    "sg:address":"83a Edith St",
    "sg:city":"St Peters",
    "sg:classifiers":[
        {
            "category":"Wholesale",
            "subcategory":"Metals & Minerals",
            "type":"Manufacturing & Wholesale Goods"
        }
    ],
    "sg:phone":"+61 2 9557 3507",
    "sg:postcode":"2044",
    "sg:province":"NSW",
    "sg:tags":[
        "steel",
        "stainless",
        "product",
        "equipment"
    ],
    "wof:name":"Wilstain Fabrications Pty Ltd",
    "wof:placetype":"venue"
},
  "geometry": {"coordinates":[151.175797,-33.914909],"type":"Point"}
}