{
  "type": "Feature",
  "properties": {
    "addr:full":"Shop 1/ 5 Turner St Beerwah QLD 4519",
    "addr:housenumber":"shop 1 / 5",
    "addr:postcode":"4519",
    "addr:street":"Turner St",
    "iso:country":"AU",
    "sg:address":"Shop 1/ 5 Turner St",
    "sg:city":"Beerwah",
    "sg:classifiers":[
        {
            "category":"Retail",
            "subcategory":"Self-service Laundry",
            "type":"Services"
        }
    ],
    "sg:phone":"+61 7 5494 0090",
    "sg:postcode":"4519",
    "sg:province":"QLD",
    "wof:name":"Havachat Laundramats",
    "wof:placetype":"venue"
},
  "geometry": {"coordinates":[152.956863,-26.8573],"type":"Point"}
}