{
  "type": "Feature",
  "properties": {
    "iso:country":"AU",
    "sg:address":"Lot 73 Bell Rd",
    "sg:city":"Gingin",
    "sg:classifiers":[
        {
            "category":"Professional",
            "type":"Services"
        }
    ],
    "sg:phone":"+61 417 904 540",
    "sg:postcode":"6503",
    "sg:province":"WA",
    "sg:tags":[
        "transport"
    ],
    "wof:name":"Gingin Cold Freight",
    "wof:placetype":"venue"
},
  "geometry": {"coordinates":[115.771294,-31.310884],"type":"Point"}
}