{
  "type": "Feature",
  "properties": {
    "iso:country":"AU",
    "sg:address":"12 Whitehouse St",
    "sg:city":"Garbutt",
    "sg:classifiers":[
        {
            "category":"Building & Trades",
            "subcategory":"Construction",
            "type":"Services"
        }
    ],
    "sg:phone":"+61 7 4728 5077",
    "sg:postcode":"4814",
    "sg:province":"QLD",
    "sg:tags":[
        "concrete",
        "contractor"
    ],
    "wof:name":"Bolton Concrete Pumping",
    "wof:placetype":"venue"
},
  "geometry": {"coordinates":[146.754593,-19.27096],"type":"Point"}
}