{
  "type": "Feature",
  "properties": {
    "addr:full":"53 Princes Hwy Norlane VIC 3214",
    "addr:housenumber":"53",
    "addr:postcode":"3214",
    "addr:street":"Princes Hwy",
    "iso:country":"AU",
    "sg:address":"53 Princes Hwy",
    "sg:city":"Norlane",
    "sg:classifiers":[
        {
            "category":"Health Services",
            "subcategory":"Health Practitioner",
            "type":"Services"
        }
    ],
    "sg:phone":"+61 425 762 899",
    "sg:postcode":"3214",
    "sg:province":"VIC",
    "sg:tags":[
        "alternative"
    ],
    "wof:name":"Aid from Gottfried Schutz",
    "wof:placetype":"venue"
},
  "geometry": {"coordinates":[144.35565185600001,-38.0937995911],"type":"Point"}
}