{
  "type": "Feature",
  "properties": {
    "addr:full":"10 Meriton Pl Clayton South VIC 3169",
    "addr:housenumber":"10",
    "addr:postcode":"3169",
    "addr:street":"Meriton Pl",
    "iso:country":"AU",
    "sg:address":"10 Meriton Pl",
    "sg:city":"Clayton South",
    "sg:classifiers":[
        {
            "category":"Home & Garden",
            "subcategory":"Carpets & Floor Coverings",
            "type":"Retail Goods"
        }
    ],
    "sg:phone":"+61 3 9545 5355",
    "sg:postcode":"3169",
    "sg:province":"VIC",
    "wof:name":"Floorworld",
    "wof:placetype":"venue"
},
  "geometry": {"coordinates":[145.120803833,-37.9326515198],"type":"Point"}
}