{
  "type": "Feature",
  "properties": {
    "addr:full":"8 Gordon St Bairnsdale VIC 3875",
    "addr:housenumber":"8",
    "addr:postcode":"3875",
    "addr:street":"Gordon St",
    "iso:country":"AU",
    "sg:address":"8 Gordon St",
    "sg:city":"Bairnsdale",
    "sg:classifiers":[
        {
            "category":"Retail",
            "subcategory":"Auto Repair",
            "type":"Services"
        }
    ],
    "sg:phone":"+61 3 5152 6178",
    "sg:postcode":"3875",
    "sg:province":"VIC",
    "sg:tags":[
        "wheel",
        "balancing",
        "alignment"
    ],
    "wof:name":"Greenwood T. & K.",
    "wof:placetype":"venue"
},
  "geometry": {"coordinates":[147.609176636,-37.8346366882],"type":"Point"}
}