{
  "type": "Feature",
  "properties": {
    "iso:country":"AU",
    "sg:address":"11 Vincent St",
    "sg:city":"Coffs Harbour",
    "sg:classifiers":[
        {
            "category":"Travel",
            "subcategory":"Hotels & Motels",
            "type":"Entertainment"
        }
    ],
    "sg:phone":"+61 2 6652 1461",
    "sg:postcode":"2450",
    "sg:province":"NSW",
    "wof:name":"Coral Court Holiday Units",
    "wof:placetype":"venue"
},
  "geometry": {"coordinates":[153.136414,-30.290632],"type":"Point"}
}