{
  "type": "Feature",
  "properties": {
    "addr:full":"82 Asquith St Silverwater NSW 2128",
    "addr:housenumber":"82",
    "addr:postcode":"2128",
    "addr:street":"Asquith St",
    "iso:country":"AU",
    "sg:address":"82 Asquith St",
    "sg:city":"Silverwater",
    "sg:classifiers":[
        {
            "category":"Utilities",
            "subcategory":"Recycling",
            "type":"Services"
        }
    ],
    "sg:phone":"+61 2 9748 1564",
    "sg:postcode":"2128",
    "sg:province":"NSW",
    "wof:name":"Cooke's Metal Recyclers",
    "wof:placetype":"venue"
},
  "geometry": {"coordinates":[151.036743164,-33.8362617493],"type":"Point"}
}