{
  "type": "Feature",
  "properties": {
    "addr:full":"143 Swan St Richmond VIC 3121",
    "addr:housenumber":"143",
    "addr:postcode":"3121",
    "addr:street":"Swan St",
    "iso:country":"AU",
    "sg:address":"143 Swan St",
    "sg:city":"Richmond",
    "sg:classifiers":[
        {
            "category":"Shopping",
            "subcategory":"Music",
            "type":"Retail Goods"
        }
    ],
    "sg:phone":"+61 3 9421 5401",
    "sg:postcode":"3121",
    "sg:province":"VIC",
    "sg:tags":[
        "store"
    ],
    "wof:name":"Toot Records",
    "wof:placetype":"venue"
},
  "geometry": {"coordinates":[144.996002197,-37.8253211975],"type":"Point"}
}