{
  "type": "Feature",
  "properties": {
    "addr:full":"100 Beechboro Rd North Embleton WA 6062",
    "addr:housenumber":"100",
    "addr:postcode":"6062",
    "addr:street":"Beechboro Rd North",
    "iso:country":"AU",
    "sg:address":"100 Beechboro Rd",
    "sg:city":"North Embleton",
    "sg:classifiers":[
        {
            "category":"Home & Garden",
            "subcategory":"Home Furnishings",
            "type":"Retail Goods"
        }
    ],
    "sg:phone":"+61 8 9477 4947",
    "sg:postcode":"6062",
    "sg:province":"WA",
    "sg:tags":[
        "storage",
        "rack",
        "wine"
    ],
    "wof:name":"National Storage",
    "wof:placetype":"venue"
},
  "geometry": {"coordinates":[115.924621582,-31.8695583344],"type":"Point"}
}