{
  "type": "Feature",
  "properties": {
    "addr:full":"224 Campbell St Swan Hill NSW 3585",
    "addr:housenumber":"224",
    "addr:postcode":"3585",
    "addr:street":"Campbell St",
    "iso:country":"AU",
    "sg:address":"224 Campbell St",
    "sg:city":"Swan Hill",
    "sg:classifiers":[
        {
            "category":"Shopping",
            "subcategory":"Clothing, Apparel, & Fashions",
            "type":"Retail Goods"
        }
    ],
    "sg:phone":"+61 3 5032 2636",
    "sg:postcode":"3585",
    "sg:province":"NSW",
    "sg:tags":[
        "lady",
        "wear"
    ],
    "wof:name":"Mixed Emotions",
    "wof:placetype":"venue"
},
  "geometry": {"coordinates":[143.559662,-35.340397],"type":"Point"}
}