{
  "type": "Feature",
  "properties": {
    "addr:full":"28 Dowling St Forbes NSW 2871",
    "addr:housenumber":"28",
    "addr:postcode":"2871",
    "addr:street":"Dowling St",
    "iso:country":"AU",
    "sg:address":"28 Dowling St",
    "sg:city":"Forbes",
    "sg:classifiers":[
        {
            "category":"Autos & Motor Vehicles",
            "subcategory":"Fuel & Gas Station",
            "type":"Retail Goods"
        }
    ],
    "sg:phone":"+61 2 6852 3433",
    "sg:postcode":"2871",
    "sg:province":"NSW",
    "wof:name":"Ampol",
    "wof:placetype":"venue"
},
  "geometry": {"coordinates":[148.01165800000001,-33.380619],"type":"Point"}
}