{
  "type": "Feature",
  "properties": {
    "addr:full":"King St Perth WA 6000",
    "addr:postcode":"6000",
    "addr:street":"King St",
    "iso:country":"AU",
    "sg:address":"King St",
    "sg:city":"Perth",
    "sg:classifiers":[
        {
            "category":"Health Services",
            "subcategory":"Dentist",
            "type":"Services"
        }
    ],
    "sg:phone":"+61 8 9226 5962",
    "sg:postcode":"6000",
    "sg:province":"WA",
    "wof:name":"DentalOSoGentle",
    "wof:placetype":"venue"
},
  "geometry": {"coordinates":[115.854049683,-31.9537448883],"type":"Point"}
}