{
  "type": "Feature",
  "properties": {
    "addr:full":"10/ 478 Maroondah Hwy Lilydale VIC 3140",
    "addr:housenumber":"10 / 478",
    "addr:postcode":"3140",
    "addr:street":"Maroondah Hwy",
    "iso:country":"AU",
    "sg:address":"10/ 478 Maroondah Hwy",
    "sg:city":"Lilydale",
    "sg:classifiers":[
        {
            "category":"Autos & Motor Vehicles",
            "subcategory":"Automobile Sales",
            "type":"Retail Goods"
        }
    ],
    "sg:phone":"+61 3 9735 3661",
    "sg:postcode":"3140",
    "sg:province":"VIC",
    "sg:tags":[
        "car",
        "used"
    ],
    "wof:name":"Maroondah Car Sales",
    "wof:placetype":"venue"
},
  "geometry": {"coordinates":[145.110931397,-37.8649253845],"type":"Point"}
}