{
  "type": "Feature",
  "properties": {
    "addr:full":"26 Merron Ave Charlestown NSW 2290",
    "addr:housenumber":"26",
    "addr:postcode":"2290",
    "addr:street":"Merron Ave",
    "iso:country":"AU",
    "sg:address":"26 Merron Ave",
    "sg:city":"Charlestown",
    "sg:classifiers":[
        {
            "category":"Utilities",
            "subcategory":"Water",
            "type":"Services"
        }
    ],
    "sg:phone":"+61 425 362 243",
    "sg:postcode":"2290",
    "sg:province":"NSW",
    "sg:tags":[
        "hot",
        "system"
    ],
    "wof:name":"Kem4",
    "wof:placetype":"venue"
},
  "geometry": {"coordinates":[151.682495117,-32.9692955017],"type":"Point"}
}