{
  "type": "Feature",
  "properties": {
    "addr:full":"East Feluga Rd Feluga QLD 4854",
    "addr:postcode":"4854",
    "addr:street":"Feluga Rd",
    "iso:country":"AU",
    "sg:address":"East Feluga Rd",
    "sg:city":"Feluga",
    "sg:classifiers":[
        {
            "category":"Farming",
            "subcategory":"Farm",
            "type":"Manufacturing & Wholesale Goods"
        }
    ],
    "sg:phone":"+61 7 4068 6125",
    "sg:postcode":"4854",
    "sg:province":"QLD",
    "sg:tags":[
        "farmer"
    ],
    "wof:name":"O&#039;Kane B & D M",
    "wof:placetype":"venue"
},
  "geometry": {"coordinates":[145.98892211899999,-17.882610321],"type":"Point"}
}