{
  "type": "Feature",
  "properties": {
    "addr:full":"22 Beresford Rd Palmerston NT 0830",
    "addr:housenumber":"22",
    "addr:postcode":"nt 0830",
    "addr:street":"Beresford Rd",
    "iso:country":"AU",
    "sg:address":"22 Beresford Rd",
    "sg:city":"Palmerston",
    "sg:classifiers":[
        {
            "category":"Retail",
            "subcategory":"Auto Repair",
            "type":"Services"
        }
    ],
    "sg:phone":"+61 8 8931 2111",
    "sg:postcode":"0830",
    "sg:province":"NT",
    "sg:tags":[
        "testing",
        "inspection",
        "motor",
        "vehicle"
    ],
    "wof:name":"ATP Power Steering",
    "wof:placetype":"venue"
},
  "geometry": {"coordinates":[130.98745700000001,-12.472409],"type":"Point"}
}