{
  "type": "Feature",
  "properties": {
    "iso:country":"AU",
    "sg:address":"5 Andrews Crt",
    "sg:city":"Padbury",
    "sg:classifiers":[
        {
            "category":"Utilities",
            "subcategory":"Water",
            "type":"Services"
        }
    ],
    "sg:phone":"+61 8 9307 4171",
    "sg:postcode":"6025",
    "sg:province":"WA",
    "sg:tags":[
        "hot",
        "system"
    ],
    "wof:name":"Aztec Plumbing",
    "wof:placetype":"venue"
},
  "geometry": {"coordinates":[115.758201599,-31.8064956665],"type":"Point"}
}