{
  "type": "Feature",
  "properties": {
    "iso:country":"AU",
    "sg:address":"403 Springvale Rd",
    "sg:city":"Forest Hill",
    "sg:classifiers":[
        {
            "category":"Manufacturing",
            "subcategory":"Food",
            "type":"Manufacturing & Wholesale Goods"
        }
    ],
    "sg:phone":"+61 3 9877 7704",
    "sg:postcode":"3131",
    "sg:province":"VIC",
    "sg:tags":[
        "function",
        "catering"
    ],
    "wof:name":"All Occasions Great & Small",
    "wof:placetype":"venue"
},
  "geometry": {"coordinates":[145.17172241200001,-37.8413314819],"type":"Point"}
}