{
  "type": "Feature",
  "properties": {
    "iso:country":"AU",
    "sg:address":"83 Miriyan Drv",
    "sg:city":"Bathurst",
    "sg:classifiers":[
        {
            "category":"Personal",
            "type":"Services"
        }
    ],
    "sg:phone":"+61 2 6331 9482",
    "sg:postcode":"2795",
    "sg:province":"NSW",
    "sg:tags":[
        "dressmaker"
    ],
    "wof:name":"Du Moore Dressmaking",
    "wof:placetype":"venue"
},
  "geometry": {"coordinates":[149.610794067,-33.4118614197],"type":"Point"}
}