{
  "type": "Feature",
  "properties": {
    "iso:country":"AU",
    "sg:address":"69A Spit Rd",
    "sg:city":"Mosman",
    "sg:classifiers":[
        {
            "category":"Utilities",
            "subcategory":"Electric",
            "type":"Services"
        }
    ],
    "sg:phone":"+61 2 9968 4290",
    "sg:postcode":"2088",
    "sg:province":"NSW",
    "sg:tags":[
        "electrical",
        "contractor"
    ],
    "wof:name":"Balmoral Refrigeration",
    "wof:placetype":"venue"
},
  "geometry": {"coordinates":[151.24400329599999,-33.8216438293],"type":"Point"}
}