{
  "type": "Feature",
  "properties": {
    "iso:country":"AU",
    "sg:address":"60 Mt Nebo Rd",
    "sg:city":"The Gap",
    "sg:classifiers":[
        {
            "category":"Conference Center",
            "type":"Public Place"
        }
    ],
    "sg:phone":"+61 7 3300 2558",
    "sg:postcode":"4061",
    "sg:province":"QLD",
    "sg:tags":[
        "venue",
        "convention"
    ],
    "wof:name":"Walkabout Creek Conferences",
    "wof:placetype":"venue"
},
  "geometry": {"coordinates":[152.92689514200001,-27.4402103424],"type":"Point"}
}