{
  "type": "Feature",
  "properties": {
    "addr:full":"16 Philp St Ingham QLD 4850",
    "addr:housenumber":"16",
    "addr:postcode":"4850",
    "addr:street":"Philp St",
    "iso:country":"AU",
    "sg:address":"16 Philp St",
    "sg:city":"Ingham",
    "sg:classifiers":[
        {
            "category":"Building & Trades",
            "subcategory":"Construction",
            "type":"Services"
        }
    ],
    "sg:phone":"+61 417 755 065",
    "sg:postcode":"4850",
    "sg:province":"QLD",
    "sg:tags":[
        "earth",
        "excavating",
        "moving",
        "contractor"
    ],
    "wof:name":"Cavati's Backhoe Hire",
    "wof:placetype":"venue"
},
  "geometry": {"coordinates":[146.15794372600001,-18.6627388],"type":"Point"}
}