{
  "type": "Feature",
  "properties": {
    "addr:full":"Sunnypark Shopping Centre Cnr Mains Rd & McCullough St Sunnybank Sunnybank QLD 4109",
    "addr:postcode":"4109",
    "addr:street":"Cnr Mains Rd & Mccullough St",
    "iso:country":"AU",
    "sg:address":"Sunnypark Shopping Centre Cnr Mains Rd & McCullough St Sunnybank",
    "sg:city":"Sunnybank",
    "sg:classifiers":[
        {
            "category":"Personal",
            "subcategory":"Beauty Salon",
            "type":"Services"
        }
    ],
    "sg:phone":"+61 7 3345 9174",
    "sg:postcode":"4109",
    "sg:province":"QLD",
    "sg:tags":[
        "hairdresser"
    ],
    "wof:name":"Over The Rainbow",
    "wof:placetype":"venue"
},
  "geometry": {"coordinates":[153.06275939899999,-27.5783214569],"type":"Point"}
}