{
  "type": "Feature",
  "properties": {
    "addr:full":"1st Floor, 52 Helena St Midland WA 6056",
    "addr:housenumber":"52",
    "addr:postcode":"6056",
    "addr:street":"Helena St",
    "iso:country":"AU",
    "sg:address":"1st Floor, 52 Helena St",
    "sg:city":"Midland",
    "sg:classifiers":[
        {
            "category":"Arena",
            "subcategory":"Sports Club",
            "type":"Entertainment"
        }
    ],
    "sg:phone":"+61 8 9250 8123",
    "sg:postcode":"6056",
    "sg:province":"WA",
    "sg:tags":[
        "defence",
        "supply",
        "self",
        "instruction",
        "martial art"
    ],
    "wof:name":"Perth Wing Chun Academy",
    "wof:placetype":"venue"
},
  "geometry": {"coordinates":[116.003013611,-31.8892650604],"type":"Point"}
}