{
  "type": "Feature",
  "properties": {
    "addr:full":"243 Bolsover St Rockhampton QLD 4700",
    "addr:housenumber":"243",
    "addr:postcode":"4700",
    "addr:street":"Bolsover St",
    "iso:country":"AU",
    "sg:address":"243 Bolsover St",
    "sg:city":"Rockhampton",
    "sg:classifiers":[
        {
            "category":"Retail",
            "subcategory":"Auto Rental",
            "type":"Services"
        }
    ],
    "sg:phone":"+61 1800 077 353",
    "sg:postcode":"4700",
    "sg:province":"QLD",
    "sg:tags":[
        "car",
        "hire",
        "minibus"
    ],
    "wof:name":"Four Wheel Drive Hire Service",
    "wof:placetype":"venue"
},
  "geometry": {"coordinates":[150.51959228499999,-23.388551712],"type":"Point"}
}