{
  "type": "Feature",
  "properties": {
    "iso:country":"AU",
    "sg:address":"Lvl 2/ 25 Gresham St",
    "sg:city":"Adelaide",
    "sg:classifiers":[
        {
            "category":"Transit Center",
            "subcategory":"Passenger",
            "type":"Transportation"
        }
    ],
    "sg:phone":"+61 8 8410 2771",
    "sg:postcode":"5000",
    "sg:province":"SA",
    "sg:tags":[
        "reading",
        "improvement"
    ],
    "wof:name":"RocketReader",
    "wof:placetype":"venue"
},
  "geometry": {"coordinates":[138.5987854,-34.9227294922],"type":"Point"}
}