{
  "type": "Feature",
  "properties": {
    "addr:full":"142 Russell St Morley WA 6062",
    "addr:housenumber":"142",
    "addr:postcode":"6062",
    "addr:street":"Russell St",
    "iso:country":"AU",
    "sg:address":"142 Russell St",
    "sg:city":"Morley",
    "sg:classifiers":[
        {
            "category":"Building & Trades",
            "subcategory":"Construction",
            "type":"Services"
        }
    ],
    "sg:phone":"+61 8 9375 7500",
    "sg:postcode":"6062",
    "sg:province":"WA",
    "sg:tags":[
        "pool",
        "swimming"
    ],
    "wof:name":"Clark Pools & Spas",
    "wof:placetype":"venue"
},
  "geometry": {"coordinates":[115.89859008800001,-31.8999633789],"type":"Point"}
}