{
  "type": "Feature",
  "properties": {
    "addr:full":"95 Clontarf St Sorrento WA 6020",
    "addr:housenumber":"95",
    "addr:postcode":"6020",
    "addr:street":"Clontarf St",
    "iso:country":"AU",
    "sg:address":"95 Clontarf St",
    "sg:city":"Sorrento",
    "sg:classifiers":[
        {
            "category":"Building & Trades",
            "subcategory":"Construction",
            "type":"Services"
        }
    ],
    "sg:phone":"+61 414 944 456",
    "sg:postcode":"6020",
    "sg:province":"WA",
    "sg:tags":[
        "brick",
        "paving"
    ],
    "wof:name":"T.J.C. Brick Paving Contractors",
    "wof:placetype":"venue"
},
  "geometry": {"coordinates":[115.757881165,-31.8353252411],"type":"Point"}
}