{
  "type": "Feature",
  "properties": {
    "addr:full":"38 Anderson Ave Panania NSW 2213",
    "addr:housenumber":"38",
    "addr:postcode":"2213",
    "addr:street":"Anderson Ave",
    "iso:country":"AU",
    "sg:address":"38 Anderson Ave",
    "sg:city":"Panania",
    "sg:classifiers":[
        {
            "category":"Fast Food",
            "type":"Food & Drink"
        }
    ],
    "sg:phone":"+61 2 9773 0605",
    "sg:postcode":"2213",
    "sg:province":"NSW",
    "sg:tags":[
        "away",
        "take"
    ],
    "wof:name":"Tony's Takeaway & Barbecue Chickens",
    "wof:placetype":"venue"
},
  "geometry": {"coordinates":[150.99854999999999,-33.953293],"type":"Point"}
}