{
  "type": "Feature",
  "properties": {
    "iso:country":"AU",
    "sg:address":"33 Pittwater Rd",
    "sg:city":"Manly",
    "sg:classifiers":[
        {
            "category":"Retail",
            "subcategory":"Auto Rental",
            "type":"Services"
        }
    ],
    "sg:phone":"+61 2 9977 5777",
    "sg:postcode":"2095",
    "sg:province":"NSW",
    "sg:tags":[
        "car",
        "hire",
        "minibus"
    ],
    "wof:name":"Action Car Rentals",
    "wof:placetype":"venue"
},
  "geometry": {"coordinates":[151.28511047399999,-33.7945175171],"type":"Point"}
}