{
  "type": "Feature",
  "properties": {
    "addr:full":"PO Box 5121 Hughesdale VIC 3166",
    "addr:postcode":"3166",
    "iso:country":"AU",
    "sg:address":"PO Box 5121",
    "sg:city":"Hughesdale",
    "sg:classifiers":[
        {
            "category":"Manufacturing",
            "subcategory":"Food",
            "type":"Manufacturing & Wholesale Goods"
        }
    ],
    "sg:phone":"+61 3 9504 3714",
    "sg:postcode":"3166",
    "sg:province":"VIC",
    "sg:tags":[
        "function",
        "catering"
    ],
    "wof:name":"World of Food Catering",
    "wof:placetype":"venue"
},
  "geometry": {"coordinates":[145.080841064,-37.900188446],"type":"Point"}
}