{
  "type": "Feature",
  "properties": {
    "addr:full":"Disher Hill Rd Monarto SA 5254",
    "addr:postcode":"5254",
    "addr:street":"Disher Hill Rd",
    "iso:country":"AU",
    "sg:address":"Disher Hill Rd",
    "sg:city":"Monarto",
    "sg:classifiers":[
        {
            "category":"Real Estate",
            "subcategory":"Architect",
            "type":"Services"
        }
    ],
    "sg:phone":"+61 437 676 842",
    "sg:postcode":"5254",
    "sg:province":"SA",
    "sg:tags":[
        "building",
        "designer"
    ],
    "wof:name":"Dave Vincent",
    "wof:placetype":"venue"
},
  "geometry": {"coordinates":[139.10133361800001,-35.065788269],"type":"Point"}
}