{
  "type": "Feature",
  "properties": {
    "addr:full":"4b Geelong Crt Bibra Lake WA 6163",
    "addr:housenumber":"4b",
    "addr:postcode":"6163",
    "addr:street":"Geelong Crt",
    "iso:country":"AU",
    "sg:address":"4b Geelong Crt",
    "sg:city":"Bibra Lake",
    "sg:classifiers":[
        {
            "category":"Retail",
            "subcategory":"Auto Repair",
            "type":"Services"
        }
    ],
    "sg:phone":"+61 8 9418 1266",
    "sg:postcode":"6163",
    "sg:province":"WA",
    "sg:tags":[
        "repairer",
        "motor",
        "engineer"
    ],
    "wof:name":"Zeds Mechanical",
    "wof:placetype":"venue"
},
  "geometry": {"coordinates":[115.802032,-32.10067],"type":"Point"}
}