{
  "type": "Feature",
  "properties": {
    "addr:full":"14 Amaroo Ave Mt Colah NSW 2079",
    "addr:housenumber":"14",
    "addr:postcode":"2079",
    "addr:street":"Amaroo Ave Mt Colah",
    "iso:country":"AU",
    "sg:address":"14 Amaroo Ave",
    "sg:city":"Mt Colah",
    "sg:classifiers":[
        {
            "category":"Health Services",
            "subcategory":"Health Practitioner",
            "type":"Services"
        }
    ],
    "sg:phone":"+61 2 9476 2235",
    "sg:postcode":"2079",
    "sg:province":"NSW",
    "sg:tags":[
        "alternative"
    ],
    "wof:name":"Australian Society of Teachers of the Alexander Technique (AUSTAT)",
    "wof:placetype":"venue"
},
  "geometry": {"coordinates":[151.10821533199999,-33.6713943481],"type":"Point"}
}