{
  "type": "Feature",
  "properties": {
    "addr:full":"24 Dalgangal Rd Gayndah QLD 4625",
    "addr:housenumber":"24",
    "addr:postcode":"4625",
    "addr:street":"Dalgangal Rd",
    "iso:country":"AU",
    "sg:address":"24 Dalgangal Rd",
    "sg:city":"Gayndah",
    "sg:classifiers":[
        {
            "category":"Autos & Motor Vehicles",
            "subcategory":"Fuel & Gas Station",
            "type":"Retail Goods"
        }
    ],
    "sg:phone":"+61 7 4161 1744",
    "sg:postcode":"4625",
    "sg:province":"QLD",
    "wof:name":"Ampol Markei Garage",
    "wof:placetype":"venue"
},
  "geometry": {"coordinates":[151.60978700000001,-25.620043],"type":"Point"}
}