{
  "type": "Feature",
  "properties": {
    "iso:country":"AU",
    "sg:address":"39 Breed St",
    "sg:city":"Traralgon",
    "sg:classifiers":[
        {
            "category":"Personal",
            "type":"Services"
        }
    ],
    "sg:phone":"+61 3 5174 0399",
    "sg:postcode":"3844",
    "sg:province":"VIC",
    "sg:tags":[
        "career",
        "counselling"
    ],
    "wof:name":"Dalton Consulting Services",
    "wof:placetype":"venue"
},
  "geometry": {"coordinates":[146.53306579599999,-38.1962051392],"type":"Point"}
}