{
  "type": "Feature",
  "properties": {
    "addr:full":"Shop 16 Mount Hutton Plaza, Wilson Rd Mt Hutton NSW 2290",
    "addr:housenumber":"shop 16",
    "addr:postcode":"2290",
    "addr:street":"Wilson Rd",
    "iso:country":"AU",
    "sg:address":"Shop 16 Mount Hutton Plaza, Wilson Rd",
    "sg:city":"Mt Hutton",
    "sg:classifiers":[
        {
            "category":"Manufacturing",
            "subcategory":"Food",
            "type":"Manufacturing & Wholesale Goods"
        }
    ],
    "sg:phone":"+61 2 4947 3214",
    "sg:postcode":"2290",
    "sg:province":"NSW",
    "sg:tags":[
        "function",
        "catering"
    ],
    "wof:name":"Henny Penny Foods",
    "wof:placetype":"venue"
},
  "geometry": {"coordinates":[151.66897582999999,-32.9812812805],"type":"Point"}
}