{
  "type": "Feature",
  "properties": {
    "addr:full":"Lowe Rd Hornsby NSW 2077",
    "addr:postcode":"2077",
    "addr:street":"Lowe Rd",
    "iso:country":"AU",
    "sg:address":"Lowe Rd",
    "sg:city":"Hornsby",
    "sg:classifiers":[
        {
            "category":"Government",
            "subcategory":"Court House",
            "type":"Public Place"
        }
    ],
    "sg:phone":"+61 2 9477 9567",
    "sg:postcode":"2077",
    "sg:province":"NSW",
    "sg:tags":[
        "personal",
        "marriage",
        "family",
        "counselling"
    ],
    "wof:name":"Gambling Counselling Service",
    "wof:placetype":"venue"
},
  "geometry": {"coordinates":[151.11250305199999,-33.7009277344],"type":"Point"}
}