{
  "type": "Feature",
  "properties": {
    "addr:full":"23a Semaphore Rd Semaphore SA 5019",
    "addr:housenumber":"23a",
    "addr:postcode":"5019",
    "addr:street":"Semaphore Rd",
    "iso:country":"AU",
    "sg:address":"23a Semaphore Rd",
    "sg:city":"Semaphore",
    "sg:classifiers":[
        {
            "category":"Fast Food",
            "type":"Food & Drink"
        }
    ],
    "sg:phone":"+61 8 8449 5183",
    "sg:postcode":"5019",
    "sg:province":"SA",
    "sg:tags":[
        "away",
        "take"
    ],
    "wof:name":"Pierre's Pizza & Pasta",
    "wof:placetype":"venue"
},
  "geometry": {"coordinates":[138.482055664,-34.8383026123],"type":"Point"}
}