{
  "type": "Feature",
  "properties": {
    "addr:full":"32 Harris Rd Bicton WA 6157",
    "addr:housenumber":"32",
    "addr:postcode":"6157",
    "addr:street":"Harris Rd",
    "iso:country":"AU",
    "sg:address":"32 Harris Rd",
    "sg:city":"Bicton",
    "sg:classifiers":[
        {
            "category":"Building & Trades",
            "subcategory":"Construction",
            "type":"Services"
        }
    ],
    "sg:phone":"+61 8 9319 1739",
    "sg:postcode":"6157",
    "sg:province":"WA",
    "sg:tags":[
        "window",
        "tinting"
    ],
    "wof:name":"JAS Tint Technology",
    "wof:placetype":"venue"
},
  "geometry": {"coordinates":[115.787407,-32.034794],"type":"Point"}
}