{
  "type": "Feature",
  "properties": {
    "addr:full":"2 Church St Hawthorn VIC 3122",
    "addr:housenumber":"2",
    "addr:postcode":"3122",
    "addr:street":"Church St",
    "iso:country":"AU",
    "sg:address":"2 Church St",
    "sg:city":"Hawthorn",
    "sg:classifiers":[
        {
            "category":"Personal",
            "subcategory":"Beauty Salon",
            "type":"Services"
        }
    ],
    "sg:phone":"+61 3 9853 6118",
    "sg:postcode":"3122",
    "sg:province":"VIC",
    "sg:tags":[
        "hairdresser"
    ],
    "wof:name":"Jila Hair Salon",
    "wof:placetype":"venue"
},
  "geometry": {"coordinates":[145.02328491200001,-37.8131332397],"type":"Point"}
}