{
  "type": "Feature",
  "properties": {
    "addr:full":"165 Johnston St Fitzroy VIC 3065",
    "addr:housenumber":"165",
    "addr:postcode":"3065",
    "addr:street":"Johnston St",
    "iso:country":"AU",
    "sg:address":"165 Johnston St",
    "sg:city":"Fitzroy",
    "sg:classifiers":[
        {
            "category":"Food & Beverages",
            "subcategory":"Liquor & Beverages",
            "type":"Retail Goods"
        }
    ],
    "sg:phone":"+61 3 9417 5089",
    "sg:postcode":"3065",
    "sg:province":"VIC",
    "sg:tags":[
        "store"
    ],
    "wof:name":"McCoppins",
    "wof:placetype":"venue"
},
  "geometry": {"coordinates":[144.98059082,-37.798412323],"type":"Point"}
}