{
  "type": "Feature",
  "properties": {
    "iso:country":"AU",
    "sg:address":"Goughs Bay Rd",
    "sg:city":"Goughs Bay",
    "sg:classifiers":[
        {
            "category":"Food & Beverages",
            "subcategory":"Groceries & Convenience Stores",
            "type":"Retail Goods"
        }
    ],
    "sg:phone":"+61 3 5777 3558",
    "sg:postcode":"3723",
    "sg:province":"VIC",
    "wof:name":"Goughs Bay General Store",
    "wof:placetype":"venue"
},
  "geometry": {"coordinates":[146.070755005,-37.1704788208],"type":"Point"}
}