{
  "type": "Feature",
  "properties": {
    "addr:full":"5 Downing St Planlands QLD 4740",
    "addr:housenumber":"5",
    "addr:postcode":"4740",
    "addr:street":"Downing St Planlands",
    "iso:country":"AU",
    "sg:address":"5 Downing St",
    "sg:city":"Planlands",
    "sg:classifiers":[
        {
            "category":"Professional",
            "subcategory":"Art Services",
            "type":"Services"
        }
    ],
    "sg:phone":"+61 7 4952 3396",
    "sg:postcode":"4740",
    "sg:province":"QLD",
    "sg:tags":[
        "decorator",
        "painter"
    ],
    "wof:name":"Phil Wockner Painting Service",
    "wof:placetype":"venue"
},
  "geometry": {"coordinates":[149.14556899999999,-21.175648],"type":"Point"}
}