{
  "type": "Feature",
  "properties": {
    "iso:country":"AU",
    "sg:address":"52b Erskineville Rd",
    "sg:city":"Erskineville",
    "sg:classifiers":[
        {
            "category":"Home & Garden",
            "subcategory":"Carpets & Floor Coverings",
            "type":"Retail Goods"
        }
    ],
    "sg:phone":"+61 412 216 328",
    "sg:postcode":"2043",
    "sg:province":"NSW",
    "sg:tags":[
        "wood"
    ],
    "wof:name":"Bamboo Floors Direct",
    "wof:placetype":"venue"
},
  "geometry": {"coordinates":[151.182343,-33.898556],"type":"Point"}
}