{
  "type": "Feature",
  "properties": {
    "iso:country":"AU",
    "sg:address":"13 Glenairne St",
    "sg:city":"Wodonga",
    "sg:classifiers":[
        {
            "category":"Mining & Drilling",
            "type":"Manufacturing & Wholesale Goods"
        }
    ],
    "sg:phone":"+61 417 281 956",
    "sg:postcode":"3689",
    "sg:province":"VIC",
    "sg:tags":[
        "concrete",
        "breaking",
        "grinding",
        "sawing"
    ],
    "wof:name":"R & L Concrete Cutting Specialists",
    "wof:placetype":"venue"
},
  "geometry": {"coordinates":[146.872467,-36.116463],"type":"Point"}
}