{
  "type": "Feature",
  "properties": {
    "iso:country":"AU",
    "sg:address":"Ste G4, 1- 15 Barr St",
    "sg:city":"Balmain",
    "sg:classifiers":[
        {
            "category":"Banks & Credit Unions",
            "subcategory":"Financial Services",
            "type":"Services"
        }
    ],
    "sg:phone":"+61 2 9555 2700",
    "sg:postcode":"2041",
    "sg:province":"NSW",
    "sg:tags":[
        "planning"
    ],
    "wof:name":"Count Wealth Accountants",
    "wof:placetype":"venue"
},
  "geometry": {"coordinates":[151.175308,-33.857624],"type":"Point"}
}