{
  "type": "Feature",
  "properties": {
    "addr:full":"13/ 1283 Point Nepean Rd Rosebud VIC 3939",
    "addr:housenumber":"13 / 1283",
    "addr:postcode":"3939",
    "addr:street":"Nepean Rd",
    "iso:country":"AU",
    "sg:address":"13/ 1283 Point Nepean Rd",
    "sg:city":"Rosebud",
    "sg:classifiers":[
        {
            "category":"Shopping",
            "subcategory":"Computers & Home Electronics",
            "type":"Retail Goods"
        }
    ],
    "sg:phone":"+61 3 5986 2984",
    "sg:postcode":"3939",
    "sg:province":"VIC",
    "sg:tags":[
        "hardware",
        "equipment"
    ],
    "wof:name":"PMCT Computers",
    "wof:placetype":"venue"
},
  "geometry": {"coordinates":[144.89468383799999,-38.358669281],"type":"Point"}
}