{
  "type": "Feature",
  "properties": {
    "addr:full":"1 Yarralumla Crs Tomakin NSW 2537",
    "addr:housenumber":"1",
    "addr:postcode":"2537",
    "addr:street":"Yarralumla Crs",
    "iso:country":"AU",
    "sg:address":"1 Yarralumla Crs",
    "sg:city":"Tomakin",
    "sg:classifiers":[
        {
            "category":"Home & Garden",
            "subcategory":"Kitchen Supply",
            "type":"Retail Goods"
        }
    ],
    "sg:phone":"+61 2 4471 7198",
    "sg:postcode":"2537",
    "sg:province":"NSW",
    "sg:tags":[
        "sharpening"
    ],
    "wof:name":"Daly's Saw & Tool Sharpening",
    "wof:placetype":"venue"
},
  "geometry": {"coordinates":[150.188232422,-35.8224105835],"type":"Point"}
}