{
  "type": "Feature",
  "properties": {
    "iso:country":"AU",
    "sg:address":"1A Carrington Rd",
    "sg:city":"Box Hill",
    "sg:classifiers":[
        {
            "category":"Health Services",
            "subcategory":"Dentist",
            "type":"Services"
        }
    ],
    "sg:phone":"+61 3 9897 1174",
    "sg:postcode":"3128",
    "sg:province":"VIC",
    "wof:name":"Adam Frederick Dr",
    "wof:placetype":"venue"
},
  "geometry": {"coordinates":[145.12327575699999,-37.8203277588],"type":"Point"}
}