{
  "type": "Feature",
  "properties": {
    "addr:full":"104 High St Charlton VIC 3525",
    "addr:housenumber":"104",
    "addr:postcode":"3525",
    "addr:street":"High St",
    "iso:country":"AU",
    "sg:address":"104 High St",
    "sg:city":"Charlton",
    "sg:classifiers":[
        {
            "category":"Autos & Motor Vehicles",
            "subcategory":"Auto Supplies",
            "type":"Retail Goods"
        }
    ],
    "sg:phone":"+61 3 5491 1369",
    "sg:postcode":"3525",
    "sg:province":"VIC",
    "sg:tags":[
        "tyre"
    ],
    "wof:name":"Charlton Tyre & Battery",
    "wof:placetype":"venue"
},
  "geometry": {"coordinates":[143.34852599999999,-36.267815],"type":"Point"}
}