{
  "type": "Feature",
  "properties": {
    "iso:country":"AU",
    "sg:address":"Factory 2/ 18 Aranda St",
    "sg:city":"Slacks Creek",
    "sg:classifiers":[
        {
            "category":"Wholesale",
            "subcategory":"Auto Parts",
            "type":"Manufacturing & Wholesale Goods"
        }
    ],
    "sg:phone":"+61 7 3808 1678",
    "sg:postcode":"4127",
    "sg:province":"QLD",
    "sg:tags":[
        "recyclers"
    ],
    "wof:name":"A & B Holden Wreckers",
    "wof:placetype":"venue"
},
  "geometry": {"coordinates":[153.128005981,-27.6309394836],"type":"Point"}
}