{
  "type": "Feature",
  "properties": {
    "addr:full":"Ste322/ Sussex St Haymarket NSW 2000",
    "addr:postcode":"2000",
    "addr:street":"Sussex St",
    "iso:country":"AU",
    "sg:address":"Ste322/ Sussex St",
    "sg:city":"Haymarket",
    "sg:classifiers":[
        {
            "category":"Health Services",
            "subcategory":"Dentist",
            "type":"Services"
        }
    ],
    "sg:phone":"+61 2 9212 2864",
    "sg:postcode":"2000",
    "sg:province":"NSW",
    "sg:tags":[
        "dental",
        "prosthetist"
    ],
    "wof:name":"Dental Pros",
    "wof:placetype":"venue"
},
  "geometry": {"coordinates":[151.20489501899999,-33.8791656494],"type":"Point"}
}