{
  "type": "Feature",
  "properties": {
    "addr:full":"15 Fisher St Silverwater NSW 2128",
    "addr:housenumber":"15",
    "addr:postcode":"2128",
    "addr:street":"Fisher St",
    "iso:country":"AU",
    "sg:address":"15 Fisher St",
    "sg:city":"Silverwater",
    "sg:classifiers":[
        {
            "category":"Manufacturing",
            "subcategory":"Rubber & Plastics",
            "type":"Manufacturing & Wholesale Goods"
        }
    ],
    "sg:phone":"+61 2 9647 2411",
    "sg:postcode":"2128",
    "sg:province":"NSW",
    "sg:tags":[
        "moulders"
    ],
    "wof:name":"Australian Containers (Plastics) Pty Ltd",
    "wof:placetype":"venue"
},
  "geometry": {"coordinates":[151.038574219,-33.8345909119],"type":"Point"}
}