{
  "type": "Feature",
  "properties": {
    "addr:full":"49 Drayton St Nanango QLD 4615",
    "addr:housenumber":"49",
    "addr:postcode":"4615",
    "addr:street":"Drayton St",
    "iso:country":"AU",
    "sg:address":"49 Drayton St",
    "sg:city":"Nanango",
    "sg:classifiers":[
        {
            "category":"Real Estate",
            "subcategory":"Developer",
            "type":"Services"
        }
    ],
    "sg:phone":"+61 7 4163 3044",
    "sg:postcode":"4615",
    "sg:province":"QLD",
    "sg:tags":[
        "development"
    ],
    "wof:name":"Rod Morgan Land Sales",
    "wof:placetype":"venue"
},
  "geometry": {"coordinates":[152.00114440900001,-26.6711940765],"type":"Point"}
}