{
  "type": "Feature",
  "properties": {
    "iso:country":"AU",
    "sg:address":"42 Tallow St",
    "sg:city":"Moulamein",
    "sg:classifiers":[
        {
            "category":"Autos & Motor Vehicles",
            "subcategory":"Auto Supplies",
            "type":"Retail Goods"
        }
    ],
    "sg:phone":"+61 3 5887 5089",
    "sg:postcode":"2733",
    "sg:province":"NSW",
    "sg:tags":[
        "tyre"
    ],
    "wof:name":"Moulamein Tyres, Front-end & Marine",
    "wof:placetype":"venue"
},
  "geometry": {"coordinates":[144.037735,-35.08931],"type":"Point"}
}