{
  "type": "Feature",
  "properties": {
    "iso:country":"AU",
    "sg:address":"11/ 42 Ocean St",
    "sg:city":"Narrabeen",
    "sg:classifiers":[
        {
            "category":"Banks & Credit Unions",
            "subcategory":"Bank",
            "type":"Services"
        }
    ],
    "sg:phone":"+61 433 208 903",
    "sg:postcode":"2101",
    "sg:province":"NSW",
    "sg:tags":[
        "broker",
        "mortgage"
    ],
    "wof:name":"Xcelon Solutions",
    "wof:placetype":"venue"
},
  "geometry": {"coordinates":[151.298615,-33.718201],"type":"Point"}
}