{
  "type": "Feature",
  "properties": {
    "iso:country":"AU",
    "sg:address":"712 Sandgate Rd",
    "sg:city":"Clayfield",
    "sg:classifiers":[
        {
            "category":"Real Estate",
            "subcategory":"Real Estate Agent",
            "type":"Services"
        }
    ],
    "sg:phone":"+61 7 3260 4600",
    "sg:postcode":"4011",
    "sg:province":"QLD",
    "wof:name":"Professionals Clayfield",
    "wof:placetype":"venue"
},
  "geometry": {"coordinates":[153.05517599999999,-27.418533],"type":"Point"}
}