{
  "type": "Feature",
  "properties": {
    "addr:full":"8/ 22 Kenthurst Rd Dural NSW 2158",
    "addr:housenumber":"/ 22",
    "addr:postcode":"2158",
    "addr:street":"Kenthurst Rd",
    "iso:country":"AU",
    "sg:address":"8/ 22 Kenthurst Rd",
    "sg:city":"Dural",
    "sg:classifiers":[
        {
            "category":"Shopping",
            "subcategory":"Antiques",
            "type":"Retail Goods"
        }
    ],
    "sg:phone":"+61 2 9651 2870",
    "sg:postcode":"2158",
    "sg:province":"NSW",
    "wof:name":"Round Corner Antiques & Gifts",
    "wof:placetype":"venue"
},
  "geometry": {"coordinates":[151.01948547399999,-33.6914710999],"type":"Point"}
}