{
  "type": "Feature",
  "properties": {
    "iso:country":"AU",
    "sg:address":"99 King Georges Rd",
    "sg:city":"Wiley Park",
    "sg:classifiers":[
        {
            "category":"Real Estate",
            "subcategory":"Real Estate Services",
            "type":"Services"
        }
    ],
    "sg:phone":"+61 2 9750 6422",
    "sg:postcode":"2195",
    "sg:province":"NSW",
    "sg:tags":[
        "listing"
    ],
    "wof:name":"Latash Real Estate",
    "wof:placetype":"venue"
},
  "geometry": {"coordinates":[151.068695,-33.923546],"type":"Point"}
}