{
  "type": "Feature",
  "properties": {
    "addr:full":"445 Moss Vale Rd Bowral NSW 2576",
    "addr:housenumber":"445",
    "addr:postcode":"2576",
    "addr:street":"Moss Vale Rd",
    "iso:country":"AU",
    "sg:address":"445 Moss Vale Rd",
    "sg:city":"Bowral",
    "sg:classifiers":[
        {
            "category":"Retail",
            "subcategory":"Storage",
            "type":"Services"
        }
    ],
    "sg:phone":"+61 2 4861 0666",
    "sg:postcode":"2576",
    "sg:province":"NSW",
    "wof:name":"Highlands Self Storage",
    "wof:placetype":"venue"
},
  "geometry": {"coordinates":[150.416137695,-34.483997345],"type":"Point"}
}