{
  "type": "Feature",
  "properties": {
    "addr:full":"4 Hornsby Crt Kallaroo WA 6025",
    "addr:housenumber":"4",
    "addr:postcode":"6025",
    "addr:street":"Hornsby Crt",
    "iso:country":"AU",
    "sg:address":"4 Hornsby Crt",
    "sg:city":"Kallaroo",
    "sg:classifiers":[
        {
            "category":"Building & Trades",
            "subcategory":"Plumbing",
            "type":"Services"
        }
    ],
    "sg:phone":"+61 417 184 256",
    "sg:postcode":"6025",
    "sg:province":"WA",
    "sg:tags":[
        "plumber",
        "gasfitters"
    ],
    "wof:name":"D.A.M. Plumbing & Gas",
    "wof:placetype":"venue"
},
  "geometry": {"coordinates":[115.742660523,-31.7861785889],"type":"Point"}
}