{
  "type": "Feature",
  "properties": {
    "addr:full":"195 Nelson Pl Williamstown VIC 3016",
    "addr:housenumber":"195",
    "addr:postcode":"3016",
    "addr:street":"Nelson Pl",
    "iso:country":"AU",
    "sg:address":"195 Nelson Pl",
    "sg:city":"Williamstown",
    "sg:classifiers":[
        {
            "category":"Personal",
            "subcategory":"Beauty Salon",
            "type":"Services"
        }
    ],
    "sg:phone":"+61 3 9397 1967",
    "sg:postcode":"3016",
    "sg:province":"VIC",
    "sg:tags":[
        "hairdresser"
    ],
    "wof:name":"Cagneys Unisex Hairdressing",
    "wof:placetype":"venue"
},
  "geometry": {"coordinates":[144.90275573700001,-37.8623847961],"type":"Point"}
}