{
  "type": "Feature",
  "properties": {
    "iso:country":"AU",
    "sg:address":"16 Industrial Drv",
    "sg:city":"Emerald",
    "sg:classifiers":[
        {
            "category":"Manufacturing",
            "subcategory":"Tools & Machinery",
            "type":"Manufacturing & Wholesale Goods"
        }
    ],
    "sg:phone":"+61 7 4982 0282",
    "sg:postcode":"4720",
    "sg:province":"QLD",
    "sg:tags":[
        "earth",
        "excavating",
        "moving",
        "equipment"
    ],
    "wof:name":"Wildkat Spares (Aust) Pty Ltd",
    "wof:placetype":"venue"
},
  "geometry": {"coordinates":[148.152237,-23.504622],"type":"Point"}
}