{
  "type": "Feature",
  "properties": {
    "addr:full":"22 Josephson St Belconnen ACT 2616",
    "addr:housenumber":"22",
    "addr:postcode":"2616",
    "addr:street":"Josephson St",
    "iso:country":"AU",
    "sg:address":"22 Josephson St",
    "sg:city":"Belconnen",
    "sg:classifiers":[
        {
            "category":"Autos & Motor Vehicles",
            "subcategory":"Automobile Sales",
            "type":"Retail Goods"
        }
    ],
    "sg:phone":"+61 2 6253 3899",
    "sg:postcode":"2616",
    "sg:province":"ACT",
    "sg:tags":[
        "car",
        "used"
    ],
    "wof:name":"Rolfe Honda",
    "wof:placetype":"venue"
},
  "geometry": {"coordinates":[149.06172180199999,-35.241558075],"type":"Point"}
}