{
  "type": "Feature",
  "properties": {
    "addr:full":"PO Box 170 Sandy Bay TAS 7005",
    "addr:postcode":"7005",
    "iso:country":"AU",
    "sg:address":"PO Box 170",
    "sg:city":"Sandy Bay",
    "sg:classifiers":[
        {
            "category":"Professional",
            "subcategory":"Art Services",
            "type":"Services"
        }
    ],
    "sg:phone":"+61 402 825 174",
    "sg:postcode":"7005",
    "sg:province":"TAS",
    "sg:tags":[
        "graphic",
        "designer"
    ],
    "wof:name":"Madeleine Glover",
    "wof:placetype":"venue"
},
  "geometry": {"coordinates":[147.33280944800001,-42.9012489319],"type":"Point"}
}