{
  "type": "Feature",
  "properties": {
    "iso:country":"AU",
    "sg:address":"37 Lalor St",
    "sg:city":"Port Melbourne",
    "sg:classifiers":[
        {
            "category":"Health Services",
            "subcategory":"Health Practitioner",
            "type":"Services"
        }
    ],
    "sg:phone":"+61 3 9645 2863",
    "sg:postcode":"3207",
    "sg:province":"VIC",
    "sg:tags":[
        "psychologist"
    ],
    "wof:name":"Rowlands Alison",
    "wof:placetype":"venue"
},
  "geometry": {"coordinates":[144.942459,-37.837215],"type":"Point"}
}