{
  "type": "Feature",
  "properties": {
    "addr:full":"University Of Western Australia, 35 Stirling Hwy Crawley WA 6009",
    "addr:housenumber":"35",
    "addr:postcode":"6009",
    "addr:street":"Stirling Hwy",
    "iso:country":"AU",
    "sg:address":"University Of Western Australia, 35 Stirling Hwy",
    "sg:city":"Crawley",
    "sg:classifiers":[
        {
            "category":"Manufacturing",
            "subcategory":"Food",
            "type":"Manufacturing & Wholesale Goods"
        }
    ],
    "sg:phone":"+61 8 9380 2315",
    "sg:postcode":"6009",
    "sg:province":"WA",
    "sg:tags":[
        "function",
        "catering"
    ],
    "wof:name":"University Function Caterers",
    "wof:placetype":"venue"
},
  "geometry": {"coordinates":[115.81574999999999,-31.976639],"type":"Point"}
}