{
  "type": "Feature",
  "properties": {
    "addr:full":"Unit 13/33- 39 Railway Ave Werribee VIC 3030",
    "addr:housenumber":"/;39",
    "addr:postcode":"3030",
    "addr:street":"Railway Ave",
    "iso:country":"AU",
    "sg:address":"Unit 13/33- 39 Railway Ave",
    "sg:city":"Werribee",
    "sg:classifiers":[
        {
            "category":"Professional",
            "subcategory":"Detective & Security Services",
            "type":"Services"
        }
    ],
    "sg:phone":"+61 3 9974 2355",
    "sg:postcode":"3030",
    "sg:province":"VIC",
    "sg:tags":[
        "equipment",
        "window",
        "doors"
    ],
    "wof:name":"Western Doors",
    "wof:placetype":"venue"
},
  "geometry": {"coordinates":[144.67645300000001,-37.892887],"type":"Point"}
}