{
  "type": "Feature",
  "properties": {
    "iso:country":"AU",
    "sg:address":"311- 313 Sailors Bay Rd",
    "sg:city":"Northbridge",
    "sg:classifiers":[
        {
            "category":"Home & Garden",
            "subcategory":"Carpets & Floor Coverings",
            "type":"Retail Goods"
        }
    ],
    "sg:phone":"+61 2 9967 0999",
    "sg:postcode":"2063",
    "sg:province":"NSW",
    "sg:tags":[
        "tile",
        "wall"
    ],
    "wof:name":"Homestone",
    "wof:placetype":"venue"
},
  "geometry": {"coordinates":[151.21803283700001,-33.8120498657],"type":"Point"}
}