{
  "type": "Feature",
  "properties": {
    "addr:full":"12 Robson St Warrnambool VIC 3280",
    "addr:housenumber":"12",
    "addr:postcode":"3280",
    "addr:street":"Robson St",
    "iso:country":"AU",
    "sg:address":"12 Robson St",
    "sg:city":"Warrnambool",
    "sg:classifiers":[
        {
            "category":"Freight",
            "type":"Transportation"
        }
    ],
    "sg:phone":"+61 3 5561 2000",
    "sg:postcode":"3280",
    "sg:province":"VIC",
    "sg:tags":[
        "light",
        "carrier"
    ],
    "wof:name":"Allens Freight",
    "wof:placetype":"venue"
},
  "geometry": {"coordinates":[142.45780944800001,-38.3734130859],"type":"Point"}
}