{
  "type": "Feature",
  "properties": {
    "iso:country":"AU",
    "sg:address":"31 Middle St",
    "sg:city":"Cleveland",
    "sg:classifiers":[
        {
            "category":"Banks & Credit Unions",
            "subcategory":"Investment Brokerage",
            "type":"Services"
        }
    ],
    "sg:phone":"+61 7 3286 1266",
    "sg:postcode":"4163",
    "sg:province":"QLD",
    "sg:tags":[
        "management",
        "property"
    ],
    "wof:name":"Professionals Redlands Real Estate",
    "wof:placetype":"venue"
},
  "geometry": {"coordinates":[153.266113281,-27.525932312],"type":"Point"}
}