{
  "type": "Feature",
  "properties": {
    "iso:country":"AU",
    "sg:address":"3/ 23 de Havilland Crs",
    "sg:city":"Ballina",
    "sg:classifiers":[
        {
            "category":"Retail",
            "subcategory":"Auto Rental",
            "type":"Services"
        }
    ],
    "sg:phone":"+61 2 6686 0160",
    "sg:postcode":"2478",
    "sg:province":"NSW",
    "sg:tags":[
        "car",
        "hire",
        "minibus"
    ],
    "wof:name":"Central Ballina Car Rental",
    "wof:placetype":"venue"
},
  "geometry": {"coordinates":[153.5572052,-28.8472175598],"type":"Point"}
}