{
  "type": "Feature",
  "properties": {
    "addr:full":"19 Creek Rd Birkdale QLD 4159",
    "addr:housenumber":"19",
    "addr:postcode":"4159",
    "addr:street":"Creek Rd",
    "iso:country":"AU",
    "sg:address":"19 Creek Rd",
    "sg:city":"Birkdale",
    "sg:classifiers":[
        {
            "category":"Building & Trades",
            "subcategory":"Construction",
            "type":"Services"
        }
    ],
    "sg:phone":"+61 418 418 438",
    "sg:postcode":"4159",
    "sg:province":"QLD",
    "sg:tags":[
        "contractor"
    ],
    "wof:name":"Garden Green Homes",
    "wof:placetype":"venue"
},
  "geometry": {"coordinates":[153.20765685999999,-27.5011405945],"type":"Point"}
}