{
  "type": "Feature",
  "properties": {
    "addr:full":"Unit 3/ 26b Isles Drv Coffs Harbour NSW 2450",
    "addr:housenumber":"/ 26b",
    "addr:postcode":"2450",
    "addr:street":"Isles Drv",
    "iso:country":"AU",
    "sg:address":"Unit 3/ 26b Isles Drv",
    "sg:city":"Coffs Harbour",
    "sg:classifiers":[
        {
            "category":"Building & Trades",
            "subcategory":"Equipment Rental",
            "type":"Services"
        }
    ],
    "sg:phone":"+61 2 6651 9273",
    "sg:postcode":"2450",
    "sg:province":"NSW",
    "sg:tags":[
        "supply",
        "catering"
    ],
    "wof:name":"Coffs Catering Equipment",
    "wof:placetype":"venue"
},
  "geometry": {"coordinates":[153.088257,-30.315748],"type":"Point"}
}