{
  "type": "Feature",
  "properties": {
    "addr:full":"Broken Head Rd Newrybar NSW 2479",
    "addr:postcode":"2479",
    "addr:street":"Head Rd",
    "iso:country":"AU",
    "sg:address":"Broken Head Rd",
    "sg:city":"Newrybar",
    "sg:classifiers":[
        {
            "category":"Farming",
            "subcategory":"Nursery",
            "type":"Manufacturing & Wholesale Goods"
        }
    ],
    "sg:phone":"+61 2 6687 1004",
    "sg:postcode":"2479",
    "sg:province":"NSW",
    "wof:name":"C.A.P.E. Australia",
    "wof:placetype":"venue"
},
  "geometry": {"coordinates":[153.53294372600001,-28.7168655396],"type":"Point"}
}