{
  "type": "Feature",
  "properties": {
    "iso:country":"AU",
    "sg:address":"25- 27 Brisbane St",
    "sg:city":"Tamworth",
    "sg:classifiers":[
        {
            "category":"Personal",
            "subcategory":"Beauty Salon",
            "type":"Services"
        }
    ],
    "sg:phone":"+61 2 6766 7611",
    "sg:postcode":"2340",
    "sg:province":"NSW",
    "sg:tags":[
        "hairdresser"
    ],
    "wof:name":"Scissorhands For Hair",
    "wof:placetype":"venue"
},
  "geometry": {"coordinates":[150.92852783199999,-31.090637207],"type":"Point"}
}