{
  "type": "Feature",
  "properties": {
    "iso:country":"AU",
    "sg:address":"55 Hawthorn Rd",
    "sg:city":"Caulfield North",
    "sg:classifiers":[
        {
            "category":"Fast Food",
            "type":"Food & Drink"
        }
    ],
    "sg:phone":"+61 3 9528 4961",
    "sg:postcode":"3161",
    "sg:province":"VIC",
    "sg:tags":[
        "away",
        "take"
    ],
    "wof:name":"Nostralis Wholemeal Vegetarian Pizza",
    "wof:placetype":"venue"
},
  "geometry": {"coordinates":[145.02484130900001,-37.8728294373],"type":"Point"}
}