{
  "type": "Feature",
  "properties": {
    "addr:full":"189 Wade St Parkhurst QLD 4702",
    "addr:housenumber":"189",
    "addr:postcode":"4702",
    "addr:street":"Wade St",
    "iso:country":"AU",
    "sg:address":"189 Wade St",
    "sg:city":"Parkhurst",
    "sg:classifiers":[
        {
            "category":"Professional",
            "type":"Services"
        }
    ],
    "sg:phone":"+61 7 4936 3885",
    "sg:postcode":"4702",
    "sg:province":"QLD",
    "sg:tags":[
        "valuer"
    ],
    "wof:name":"Tomkins Valuers & Auctioneers",
    "wof:placetype":"venue"
},
  "geometry": {"coordinates":[150.50033569300001,-23.3222732544],"type":"Point"}
}