{
  "type": "Feature",
  "properties": {
    "iso:country":"AU",
    "sg:address":"486 Marrickville Rd",
    "sg:city":"Dulwich Hill",
    "sg:classifiers":[
        {
            "category":"Health Services",
            "subcategory":"Dentist",
            "type":"Services"
        }
    ],
    "sg:phone":"+61 2 9569 2176",
    "sg:postcode":"2203",
    "sg:province":"NSW",
    "wof:name":"Mylona Stella Dr",
    "wof:placetype":"venue"
},
  "geometry": {"coordinates":[151.144485,-33.905537],"type":"Point"}
}