{
  "type": "Feature",
  "properties": {
    "addr:full":"5/ 1 Acacia St Yarrawonga VIC 3730",
    "addr:housenumber":"/ 1",
    "addr:postcode":"3730",
    "addr:street":"Acacia St",
    "iso:country":"AU",
    "sg:address":"5/ 1 Acacia St",
    "sg:city":"Yarrawonga",
    "sg:classifiers":[
        {
            "category":"Retail",
            "subcategory":"Auto Rental",
            "type":"Services"
        }
    ],
    "sg:phone":"+61 3 5743 2775",
    "sg:postcode":"3730",
    "sg:province":"VIC",
    "sg:tags":[
        "car",
        "hire",
        "minibus"
    ],
    "wof:name":"A1 Car Rentals",
    "wof:placetype":"venue"
},
  "geometry": {"coordinates":[145.99842834500001,-36.0265197754],"type":"Point"}
}