{
  "type": "Feature",
  "properties": {
    "iso:country":"AU",
    "sg:address":"Regent St",
    "sg:city":"Coen",
    "sg:classifiers":[
        {
            "category":"Food & Beverages",
            "subcategory":"Groceries & Convenience Stores",
            "type":"Retail Goods"
        }
    ],
    "sg:phone":"+61 7 4060 1144",
    "sg:postcode":"4871",
    "sg:province":"QLD",
    "wof:name":"Clark P & G E",
    "wof:placetype":"venue"
},
  "geometry": {"coordinates":[143.196990967,-13.9455900192],"type":"Point"}
}