{
  "type": "Feature",
  "properties": {
    "addr:full":"Rear of Unit 3/ 227 Hume Hwy Mittagong NSW 2575",
    "addr:housenumber":"rear;3 / 227",
    "addr:postcode":"2575",
    "addr:street":"Hume Hwy",
    "iso:country":"AU",
    "sg:address":"Rear of Unit 3/ 227 Hume Hwy",
    "sg:city":"Mittagong",
    "sg:classifiers":[
        {
            "category":"Government",
            "subcategory":"Fire Station",
            "type":"Public Place"
        }
    ],
    "sg:phone":"+61 2 4872 1990",
    "sg:postcode":"2575",
    "sg:province":"NSW",
    "sg:tags":[
        "spring",
        "shock",
        "absorbers",
        "suspension"
    ],
    "wof:name":"Ray Selby Steering And Suspension Service",
    "wof:placetype":"venue"
},
  "geometry": {"coordinates":[150.447540283,-34.4326248169],"type":"Point"}
}