{
  "type": "Feature",
  "properties": {
    "addr:full":"96 Young St Frankston VIC 3199",
    "addr:housenumber":"96",
    "addr:postcode":"3199",
    "addr:street":"Young St",
    "iso:country":"AU",
    "sg:address":"96 Young St",
    "sg:city":"Frankston",
    "sg:classifiers":[
        {
            "category":"Cafe",
            "type":"Food & Drink"
        }
    ],
    "sg:phone":"+61 3 9770 2114",
    "sg:postcode":"3199",
    "sg:province":"VIC",
    "wof:name":"Brothers On Young",
    "wof:placetype":"venue"
},
  "geometry": {"coordinates":[145.12493896500001,-38.1441917419],"type":"Point"}
}