{
  "type": "Feature",
  "properties": {
    "iso:country":"AU",
    "sg:address":"9 Essex Rd",
    "sg:city":"Mt Waverley",
    "sg:classifiers":[
        {
            "category":"Professional",
            "subcategory":"Accounting & Tax Preparation",
            "type":"Services"
        }
    ],
    "sg:phone":"+61 3 9888 3337",
    "sg:postcode":"3149",
    "sg:province":"VIC",
    "sg:tags":[
        "consultant",
        "taxation"
    ],
    "wof:name":"Bigger Accounting",
    "wof:placetype":"venue"
},
  "geometry": {"coordinates":[145.11343383799999,-37.862449646],"type":"Point"}
}