{
  "type": "Feature",
  "properties": {
    "addr:full":"20 Exceller Ave Bankstown NSW 2200",
    "addr:housenumber":"20",
    "addr:postcode":"2200",
    "addr:street":"Exceller Ave",
    "iso:country":"AU",
    "sg:address":"20 Exceller Ave",
    "sg:city":"Bankstown",
    "sg:classifiers":[
        {
            "category":"Retail",
            "subcategory":"Auto Repair",
            "type":"Services"
        }
    ],
    "sg:phone":"+61 2 9632 0286",
    "sg:postcode":"2200",
    "sg:province":"NSW",
    "sg:tags":[
        "repairer",
        "motor",
        "engineer"
    ],
    "wof:name":"C.N.R. Advance Smash Repairs",
    "wof:placetype":"venue"
},
  "geometry": {"coordinates":[151.035034,-33.933048],"type":"Point"}
}