{
  "type": "Feature",
  "properties": {
    "addr:full":"291 Albert St Brunswick VIC 3056",
    "addr:housenumber":"291",
    "addr:postcode":"3056",
    "addr:street":"Albert St",
    "iso:country":"AU",
    "sg:address":"291 Albert St",
    "sg:city":"Brunswick",
    "sg:classifiers":[
        {
            "category":"Travel",
            "subcategory":"Hotels & Motels",
            "type":"Entertainment"
        }
    ],
    "sg:phone":"+61 3 9380 1493",
    "sg:postcode":"3056",
    "sg:province":"VIC",
    "sg:tags":[
        "pub"
    ],
    "wof:name":"Noise Bar The",
    "wof:placetype":"venue"
},
  "geometry": {"coordinates":[144.95985412600001,-37.7684745789],"type":"Point"}
}