{
  "type": "Feature",
  "properties": {
    "addr:full":"350- 352 Angas St Adelaide SA 5000",
    "addr:housenumber":"350 352",
    "addr:postcode":"5000",
    "addr:street":"Angas St",
    "iso:country":"AU",
    "sg:address":"350- 352 Angas St",
    "sg:city":"Adelaide",
    "sg:classifiers":[
        {
            "category":"Personal",
            "subcategory":"Beauty Salon",
            "type":"Services"
        }
    ],
    "sg:phone":"+61 8 8232 1305",
    "sg:postcode":"5000",
    "sg:province":"SA",
    "wof:name":"Skin Essentials",
    "wof:placetype":"venue"
},
  "geometry": {"coordinates":[138.614044189,-34.9292869568],"type":"Point"}
}