{
  "type": "Feature",
  "properties": {
    "iso:country":"AU",
    "sg:address":"1st Fl, 109 Oxford St",
    "sg:city":"Bondi Junction",
    "sg:classifiers":[
        {
            "category":"Personal",
            "subcategory":"Tanning Parlor",
            "type":"Services"
        }
    ],
    "sg:phone":"+61 2 9389 9077",
    "sg:postcode":"2022",
    "sg:province":"NSW",
    "sg:tags":[
        "solarium"
    ],
    "wof:name":"Sunlounge Tan Studios",
    "wof:placetype":"venue"
},
  "geometry": {"coordinates":[151.24688720699999,-33.8917312622],"type":"Point"}
}