{
  "type": "Feature",
  "properties": {
    "addr:full":"Cairns Corporate Tower Lake St Cairns QLD 4870",
    "addr:postcode":"4870",
    "addr:street":"Lake St",
    "iso:country":"AU",
    "sg:address":"Cairns Corporate Tower Lake St",
    "sg:city":"Cairns",
    "sg:classifiers":[
        {
            "category":"Banks & Credit Unions",
            "subcategory":"Investment Brokerage",
            "type":"Services"
        }
    ],
    "sg:phone":"+61 7 4052 9222",
    "sg:postcode":"4870",
    "sg:province":"QLD",
    "sg:tags":[
        "share",
        "broker",
        "stock"
    ],
    "wof:name":"Morgans Stock Broking",
    "wof:placetype":"venue"
},
  "geometry": {"coordinates":[145.779205322,-16.9260311127],"type":"Point"}
}