{
  "type": "Feature",
  "properties": {
    "addr:full":"PO Box 530 Merrylands NSW 2160",
    "addr:postcode":"2160",
    "iso:country":"AU",
    "sg:address":"PO Box 530",
    "sg:city":"Merrylands",
    "sg:classifiers":[
        {
            "category":"Professional",
            "subcategory":"Management & Consulting",
            "type":"Services"
        }
    ],
    "sg:phone":"+61 2 9475 5030",
    "sg:postcode":"2160",
    "sg:province":"NSW",
    "sg:tags":[
        "consultant",
        "business"
    ],
    "wof:name":"Kylie Moss",
    "wof:placetype":"venue"
},
  "geometry": {"coordinates":[150.98817443900001,-33.83618927],"type":"Point"}
}