{
  "type": "Feature",
  "properties": {
    "addr:full":"45 Captain Cook Drv Caringbah NSW 2229",
    "addr:housenumber":"45",
    "addr:postcode":"2229",
    "addr:street":"Captain Cook Drv",
    "iso:country":"AU",
    "sg:address":"45 Captain Cook Drv",
    "sg:city":"Caringbah",
    "sg:classifiers":[
        {
            "category":"Retail",
            "subcategory":"Auto Repair",
            "type":"Services"
        }
    ],
    "sg:phone":"+61 2 9525 8973",
    "sg:postcode":"2229",
    "sg:province":"NSW",
    "sg:tags":[
        "beater",
        "painter",
        "panel"
    ],
    "wof:name":"Parraweena Smash Repairs Towing",
    "wof:placetype":"venue"
},
  "geometry": {"coordinates":[151.12606811500001,-34.0325813293],"type":"Point"}
}