{
  "type": "Feature",
  "properties": {
    "addr:full":"91 Frenchs Forest Rd Seaforth NSW 2092",
    "addr:housenumber":"91",
    "addr:postcode":"2092",
    "addr:street":"Frenchs Forest Rd",
    "iso:country":"AU",
    "sg:address":"91 Frenchs Forest Rd",
    "sg:city":"Seaforth",
    "sg:classifiers":[
        {
            "category":"Professional",
            "subcategory":"Art Services",
            "type":"Services"
        }
    ],
    "sg:phone":"+61 2 9948 6688",
    "sg:postcode":"2092",
    "sg:province":"NSW",
    "sg:tags":[
        "decorator",
        "painter"
    ],
    "wof:name":"Driessen Pieter & Sons",
    "wof:placetype":"venue"
},
  "geometry": {"coordinates":[151.246017456,-33.7930908203],"type":"Point"}
}