{
  "type": "Feature",
  "properties": {
    "addr:full":"106 Enterprise St Bundaberg QLD 4670",
    "addr:housenumber":"106",
    "addr:postcode":"4670",
    "addr:street":"Enterprise St",
    "iso:country":"AU",
    "sg:address":"106 Enterprise St",
    "sg:city":"Bundaberg",
    "sg:classifiers":[
        {
            "category":"Utilities",
            "type":"Services"
        }
    ],
    "sg:phone":"+61 7 4151 6211",
    "sg:postcode":"4670",
    "sg:province":"QLD",
    "sg:tags":[
        "equipment",
        "towing"
    ],
    "wof:name":"Autokit Accessories",
    "wof:placetype":"venue"
},
  "geometry": {"coordinates":[152.33909606899999,-24.8913154602],"type":"Point"}
}