{
  "type": "Feature",
  "properties": {
    "iso:country":"AU",
    "sg:address":"25 Mason St",
    "sg:city":"Newport",
    "sg:classifiers":[
        {
            "category":"Food & Beverages",
            "subcategory":"Liquor & Beverages",
            "type":"Retail Goods"
        }
    ],
    "sg:phone":"+61 3 9391 1275",
    "sg:postcode":"3015",
    "sg:province":"VIC",
    "sg:tags":[
        "store"
    ],
    "wof:name":"Cheeers Liquor Group",
    "wof:placetype":"venue"
},
  "geometry": {"coordinates":[144.881317139,-37.842502594],"type":"Point"}
}