{
  "type": "Feature",
  "properties": {
    "addr:full":"43 Forster St New Town TAS 7008",
    "addr:housenumber":"43",
    "addr:postcode":"7008",
    "addr:street":"Forster St",
    "iso:country":"AU",
    "sg:address":"43 Forster St",
    "sg:city":"New Town",
    "sg:classifiers":[
        {
            "category":"Food & Beverages",
            "subcategory":"Bakery",
            "type":"Retail Goods"
        }
    ],
    "sg:phone":"+61 3 6228 6367",
    "sg:postcode":"7008",
    "sg:province":"TAS",
    "sg:tags":[
        "baker"
    ],
    "wof:name":"Maypole Foods",
    "wof:placetype":"venue"
},
  "geometry": {"coordinates":[147.303344727,-42.8561401367],"type":"Point"}
}