{
  "type": "Feature",
  "properties": {
    "addr:full":"37-3 Rangeview Rd Mt Evelyn VIC 3796",
    "addr:housenumber":"37-3",
    "addr:postcode":"3796",
    "addr:street":"Rangeview Rd",
    "iso:country":"AU",
    "sg:address":"37-3 Rangeview Rd",
    "sg:city":"Mt Evelyn",
    "sg:classifiers":[
        {
            "category":"Building & Trades",
            "subcategory":"Construction",
            "type":"Services"
        }
    ],
    "sg:phone":"+61 3 9737 0572",
    "sg:postcode":"3796",
    "sg:province":"VIC",
    "sg:tags":[
        "contractor"
    ],
    "wof:name":"A.S.K Builders",
    "wof:placetype":"venue"
},
  "geometry": {"coordinates":[145.382644653,-37.7822685242],"type":"Point"}
}