{
  "type": "Feature",
  "properties": {
    "addr:full":"Burroughs Rd Ramco SA 5322",
    "addr:postcode":"5322",
    "addr:street":"Burroughs Rd",
    "iso:country":"AU",
    "sg:address":"Burroughs Rd",
    "sg:city":"Ramco",
    "sg:classifiers":[
        {
            "category":"Farming",
            "subcategory":"Nursery",
            "type":"Manufacturing & Wholesale Goods"
        }
    ],
    "sg:phone":"+61 8 8541 3644",
    "sg:postcode":"5322",
    "sg:province":"SA",
    "wof:name":"Golden Heights Nurseries",
    "wof:placetype":"venue"
},
  "geometry": {"coordinates":[139.92123413100001,-34.1807594299],"type":"Point"}
}