{
  "type": "Feature",
  "properties": {
    "addr:full":"Lot 7/ Bradshaws La Blampied VIC 3364",
    "addr:housenumber":"7 /",
    "addr:postcode":"3364",
    "addr:street":"La Blampied",
    "iso:country":"AU",
    "sg:address":"Lot 7/ Bradshaws La",
    "sg:city":"Blampied",
    "sg:classifiers":[
        {
            "category":"Mining & Drilling",
            "type":"Manufacturing & Wholesale Goods"
        }
    ],
    "sg:phone":"+61 3 5345 7385",
    "sg:postcode":"3364",
    "sg:province":"VIC",
    "sg:tags":[
        "boring",
        "contractor"
    ],
    "wof:name":"Thrust Drilling Service Pty Ltd",
    "wof:placetype":"venue"
},
  "geometry": {"coordinates":[144.05963134800001,-37.3610877991],"type":"Point"}
}