{
  "type": "Feature",
  "properties": {
    "iso:country":"AU",
    "sg:address":"5 Hasper Pl",
    "sg:city":"Marmion",
    "sg:classifiers":[
        {
            "category":"Home & Garden",
            "subcategory":"Building Materials",
            "type":"Retail Goods"
        }
    ],
    "sg:phone":"+61 8 9246 5731",
    "sg:postcode":"6020",
    "sg:province":"WA",
    "sg:tags":[
        "skylight"
    ],
    "wof:name":"GEL Services",
    "wof:placetype":"venue"
},
  "geometry": {"coordinates":[115.75749206499999,-31.8401584625],"type":"Point"}
}