{
  "type": "Feature",
  "properties": {
    "addr:full":"16 Brasser Ave Dromana VIC 3936",
    "addr:housenumber":"16",
    "addr:postcode":"3936",
    "addr:street":"Brasser Ave",
    "iso:country":"AU",
    "sg:address":"16 Brasser Ave",
    "sg:city":"Dromana",
    "sg:classifiers":[
        {
            "category":"Building & Trades",
            "subcategory":"Construction",
            "type":"Services"
        }
    ],
    "sg:phone":"+61 3 5987 1145",
    "sg:postcode":"3936",
    "sg:province":"VIC",
    "sg:tags":[
        "scaffolding"
    ],
    "wof:name":"Dromana Hire Services Pty Ltd",
    "wof:placetype":"venue"
},
  "geometry": {"coordinates":[144.98731994600001,-38.332359314],"type":"Point"}
}