{
  "type": "Feature",
  "properties": {
    "iso:country":"AU",
    "sg:address":"4 Hawker Rd",
    "sg:city":"Burton",
    "sg:classifiers":[
        {
            "category":"Retail",
            "subcategory":"Auto Repair",
            "type":"Services"
        }
    ],
    "sg:phone":"+61 8 8280 9738",
    "sg:postcode":"5110",
    "sg:province":"SA",
    "sg:tags":[
        "bus",
        "truck"
    ],
    "wof:name":"Macri Motors",
    "wof:placetype":"venue"
},
  "geometry": {"coordinates":[138.59983825699999,-34.733127594],"type":"Point"}
}