{
  "type": "Feature",
  "properties": {
    "addr:full":"6/ 772 Burwood Hwy Ferntree Gully VIC 3156",
    "addr:housenumber":"/ 772",
    "addr:postcode":"3156",
    "addr:street":"Burwood Hwy",
    "iso:country":"AU",
    "sg:address":"6/ 772 Burwood Hwy",
    "sg:city":"Ferntree Gully",
    "sg:classifiers":[
        {
            "category":"Education",
            "subcategory":"Dance Studio",
            "type":"Public Place"
        }
    ],
    "sg:phone":"+61 3 9752 3711",
    "sg:postcode":"3156",
    "sg:province":"VIC",
    "sg:tags":[
        "venue",
        "tuition"
    ],
    "wof:name":"MarShere",
    "wof:placetype":"venue"
},
  "geometry": {"coordinates":[145.30078125,-37.8910865784],"type":"Point"}
}