{
  "type": "Feature",
  "properties": {
    "addr:full":"25 Malbon St Bungendore ACT 2621",
    "addr:housenumber":"25",
    "addr:postcode":"2621",
    "addr:street":"Malbon St",
    "iso:country":"AU",
    "sg:address":"25 Malbon St",
    "sg:city":"Bungendore",
    "sg:classifiers":[
        {
            "category":"Cafe",
            "type":"Food & Drink"
        }
    ],
    "sg:phone":"+61 2 6238 1404",
    "sg:postcode":"2621",
    "sg:province":"ACT",
    "wof:name":"Heritage Pizza",
    "wof:placetype":"venue"
},
  "geometry": {"coordinates":[149.43406677199999,-35.2524909973],"type":"Point"}
}