{
  "type": "Feature",
  "properties": {
    "iso:country":"AU",
    "sg:address":"PO Box 245",
    "sg:city":"Lennox Head",
    "sg:classifiers":[
        {
            "category":"Shopping",
            "subcategory":"Computers & Home Electronics",
            "type":"Retail Goods"
        }
    ],
    "sg:phone":"+61 2 6687 5367",
    "sg:postcode":"2478",
    "sg:province":"NSW",
    "sg:tags":[
        "equipment",
        "multimedia"
    ],
    "wof:name":"11th Hour Group Pty Ltd",
    "wof:placetype":"venue"
},
  "geometry": {"coordinates":[153.592727661,-28.7983398438],"type":"Point"}
}