{
  "type": "Feature",
  "properties": {
    "iso:country":"AU",
    "sg:address":"162 Lygon St",
    "sg:city":"Carlton",
    "sg:classifiers":[
        {
            "category":"Travel",
            "subcategory":"Hotels & Motels",
            "type":"Entertainment"
        }
    ],
    "sg:phone":"+61 3 9662 2009",
    "sg:postcode":"3053",
    "sg:province":"VIC",
    "sg:tags":[
        "accommodation"
    ],
    "wof:name":"Bar Centrale",
    "wof:placetype":"venue"
},
  "geometry": {"coordinates":[144.966629028,-37.8033561707],"type":"Point"}
}