{
  "type": "Feature",
  "properties": {
    "iso:country":"AU",
    "sg:address":"Ste3a/ 98 Longueville Rd",
    "sg:city":"Lane Cove",
    "sg:classifiers":[
        {
            "category":"Building & Trades",
            "subcategory":"Construction",
            "type":"Services"
        }
    ],
    "sg:phone":"+61 2 9420 2939",
    "sg:postcode":"2066",
    "sg:province":"NSW",
    "sg:tags":[
        "contractor"
    ],
    "wof:name":"Nestco Pty Ltd",
    "wof:placetype":"venue"
},
  "geometry": {"coordinates":[151.17005920400001,-33.8141593933],"type":"Point"}
}