{
  "type": "Feature",
  "properties": {
    "iso:country":"AU",
    "sg:address":"869 Knight Rd",
    "sg:city":"Albury North",
    "sg:classifiers":[
        {
            "category":"Shopping",
            "subcategory":"Computers & Home Electronics",
            "type":"Retail Goods"
        }
    ],
    "sg:phone":"+61 2 6049 5656",
    "sg:postcode":"2640",
    "sg:province":"NSW",
    "sg:tags":[
        "hardware",
        "equipment"
    ],
    "wof:name":"Valcore Technology",
    "wof:placetype":"venue"
},
  "geometry": {"coordinates":[146.942703247,-36.0647850037],"type":"Point"}
}