{
  "type": "Feature",
  "properties": {
    "iso:country":"AU",
    "sg:address":"4 Karalta Rd",
    "sg:city":"Erina",
    "sg:classifiers":[
        {
            "category":"Retail",
            "subcategory":"Auto Repair",
            "type":"Services"
        }
    ],
    "sg:phone":"+61 2 4367 7000",
    "sg:postcode":"2250",
    "sg:province":"NSW",
    "sg:tags":[
        "beater",
        "painter",
        "panel"
    ],
    "wof:name":"Adams Smash Repairs",
    "wof:placetype":"venue"
},
  "geometry": {"coordinates":[151.31939697300001,-33.4245109558],"type":"Point"}
}