{
  "type": "Feature",
  "properties": {
    "iso:country":"AU",
    "sg:address":"Long Point Rd",
    "sg:city":"Bodalla",
    "sg:classifiers":[
        {
            "category":"Building & Trades",
            "subcategory":"Construction",
            "type":"Services"
        }
    ],
    "sg:phone":"+61 2 4473 5339",
    "sg:postcode":"2545",
    "sg:province":"NSW",
    "sg:tags":[
        "monumental",
        "mason"
    ],
    "wof:name":"Granit-Bronz Memorial Co",
    "wof:placetype":"venue"
},
  "geometry": {"coordinates":[150.13600158700001,-36.097442627],"type":"Point"}
}