{
  "type": "Feature",
  "properties": {
    "addr:full":"Bradshaw St Latrobe TAS 7307",
    "addr:postcode":"7307",
    "addr:street":"Bradshaw St",
    "iso:country":"AU",
    "sg:address":"Bradshaw St",
    "sg:city":"Latrobe",
    "sg:classifiers":[
        {
            "category":"Social Services",
            "subcategory":"Child Care",
            "type":"Services"
        }
    ],
    "sg:phone":"+61 3 6426 3048",
    "sg:postcode":"7307",
    "sg:province":"TAS",
    "wof:name":"St Patricks Child Care Centre",
    "wof:placetype":"venue"
},
  "geometry": {"coordinates":[146.418655,-41.231434],"type":"Point"}
}