{
  "type": "Feature",
  "properties": {
    "addr:full":"Suite 11, 50 Great North Rd Five Dock NSW 2046",
    "addr:housenumber":"50",
    "addr:postcode":"2046",
    "addr:street":"Great North Rd",
    "iso:country":"AU",
    "sg:address":"Suite 11, 50 Great North Rd",
    "sg:city":"Five Dock",
    "sg:classifiers":[
        {
            "category":"Professional",
            "subcategory":"Engineering",
            "type":"Services"
        }
    ],
    "sg:phone":"+61 2 9712 4700",
    "sg:postcode":"2046",
    "sg:province":"NSW",
    "sg:tags":[
        "consulting",
        "engineer"
    ],
    "wof:name":"Structural Design Solutions",
    "wof:placetype":"venue"
},
  "geometry": {"coordinates":[151.12927199999999,-33.870609],"type":"Point"}
}