{
  "type": "Feature",
  "properties": {
    "addr:full":"PO Box 287 Smithfield NSW 2164",
    "addr:postcode":"2164",
    "iso:country":"AU",
    "sg:address":"PO Box 287",
    "sg:city":"Smithfield",
    "sg:classifiers":[
        {
            "category":"Insurance",
            "subcategory":"Hazard Insurance",
            "type":"Services"
        }
    ],
    "sg:phone":"+61 424 138 164",
    "sg:postcode":"2164",
    "sg:province":"NSW",
    "sg:tags":[
        "loss",
        "adjuster",
        "assessor"
    ],
    "wof:name":"AAA Auto Accident Assessors",
    "wof:placetype":"venue"
},
  "geometry": {"coordinates":[150.93023681599999,-33.8520202637],"type":"Point"}
}