{
  "type": "Feature",
  "properties": {
    "iso:country":"AU",
    "sg:address":"Chevron Renaissance Elkhorn Ave",
    "sg:city":"Surfers Paradise",
    "sg:classifiers":[
        {
            "category":"Health Services",
            "subcategory":"Doctor",
            "type":"Services"
        }
    ],
    "sg:phone":"+61 7 5561 0340",
    "sg:postcode":"4217",
    "sg:province":"QLD",
    "sg:tags":[
        "medical",
        "practitioner"
    ],
    "wof:name":"Chevron Renaissance Medical Centre",
    "wof:placetype":"venue"
},
  "geometry": {"coordinates":[153.42897033700001,-27.9989395142],"type":"Point"}
}