{
  "type": "Feature",
  "properties": {
    "addr:full":"Shp29/ Sunbury Sq Sunbury VIC 3429",
    "addr:postcode":"3429",
    "addr:street":"Sunbury Sq",
    "iso:country":"AU",
    "sg:address":"Shp29/ Sunbury Sq",
    "sg:city":"Sunbury",
    "sg:classifiers":[
        {
            "category":"Shopping",
            "subcategory":"Clothing, Apparel, & Fashions",
            "type":"Retail Goods"
        }
    ],
    "sg:phone":"+61 3 9744 3657",
    "sg:postcode":"3429",
    "sg:province":"VIC",
    "sg:tags":[
        "menswear"
    ],
    "wof:name":"Wye River Clothing",
    "wof:placetype":"venue"
},
  "geometry": {"coordinates":[144.740768433,-37.5834121704],"type":"Point"}
}