{
  "type": "Feature",
  "properties": {
    "addr:full":"371 Black Rd Flagstaff Hill SA 5159",
    "addr:housenumber":"371",
    "addr:postcode":"5159",
    "addr:street":"Black Rd",
    "iso:country":"AU",
    "sg:address":"371 Black Rd",
    "sg:city":"Flagstaff Hill",
    "sg:classifiers":[
        {
            "category":"Building & Trades",
            "subcategory":"Construction",
            "type":"Services"
        }
    ],
    "sg:phone":"+61 8 8270 1899",
    "sg:postcode":"5159",
    "sg:province":"SA",
    "sg:tags":[
        "brick",
        "paving"
    ],
    "wof:name":"Slatex S.A.",
    "wof:placetype":"venue"
},
  "geometry": {"coordinates":[138.61592102,-35.0582962036],"type":"Point"}
}