{
  "type": "Feature",
  "properties": {
    "addr:full":"114- 116 Wyndham St Shepparton VIC 3630",
    "addr:housenumber":"116",
    "addr:postcode":"3630",
    "addr:street":"Wyndham St",
    "iso:country":"AU",
    "sg:address":"114- 116 Wyndham St",
    "sg:city":"Shepparton",
    "sg:classifiers":[
        {
            "category":"Banks & Credit Unions",
            "subcategory":"Investment Brokerage",
            "type":"Services"
        }
    ],
    "sg:phone":"+61 3 5832 0140",
    "sg:postcode":"3630",
    "sg:province":"VIC",
    "wof:name":"Securelife Group",
    "wof:placetype":"venue"
},
  "geometry": {"coordinates":[145.400115967,-36.3764076233],"type":"Point"}
}