{
  "type": "Feature",
  "properties": {
    "iso:country":"AU",
    "sg:address":"Yumborra Rd",
    "sg:city":"Dalby",
    "sg:classifiers":[
        {
            "category":"Home & Garden",
            "subcategory":"Building Materials",
            "type":"Retail Goods"
        }
    ],
    "sg:phone":"+61 7 4662 3355",
    "sg:postcode":"4405",
    "sg:province":"QLD",
    "sg:tags":[
        "pre-mixed",
        "concrete"
    ],
    "wof:name":"Hanson",
    "wof:placetype":"venue"
},
  "geometry": {"coordinates":[151.23831176799999,-27.1808586121],"type":"Point"}
}