{
  "type": "Feature",
  "properties": {
    "iso:country":"AU",
    "sg:address":"3 Sanitarium Drv",
    "sg:city":"Berkeley Vale",
    "sg:classifiers":[
        {
            "category":"Farming",
            "subcategory":"Crops",
            "type":"Manufacturing & Wholesale Goods"
        }
    ],
    "sg:phone":"+61 2 4389 2499",
    "sg:postcode":"2261",
    "sg:province":"NSW",
    "sg:tags":[
        "warehousing"
    ],
    "wof:name":"Mayne Logistics",
    "wof:placetype":"venue"
},
  "geometry": {"coordinates":[151.412811,-33.328728],"type":"Point"}
}