{
  "type": "Feature",
  "properties": {
    "iso:country":"AU",
    "sg:address":"6 Dorothy Rd",
    "sg:city":"Mt Evelyn",
    "sg:classifiers":[
        {
            "category":"Building & Trades",
            "subcategory":"Construction",
            "type":"Services"
        }
    ],
    "sg:phone":"+61 3 9736 2921",
    "sg:postcode":"3796",
    "sg:province":"VIC",
    "sg:tags":[
        "earth",
        "excavating",
        "moving",
        "contractor"
    ],
    "wof:name":"R & J Grader Hire",
    "wof:placetype":"venue"
},
  "geometry": {"coordinates":[145.398681641,-37.8011360168],"type":"Point"}
}