{
  "type": "Feature",
  "properties": {
    "iso:country":"AU",
    "sg:address":"75 Evergreen Ave",
    "sg:city":"Loganlea",
    "sg:classifiers":[
        {
            "category":"Manufacturing",
            "subcategory":"Tools & Machinery",
            "type":"Manufacturing & Wholesale Goods"
        }
    ],
    "sg:phone":"+61 404 812 873",
    "sg:postcode":"4131",
    "sg:province":"QLD",
    "sg:tags":[
        "earth",
        "excavating",
        "moving",
        "equipment"
    ],
    "wof:name":"Mr Makeover",
    "wof:placetype":"venue"
},
  "geometry": {"coordinates":[153.127243042,-27.6867218018],"type":"Point"}
}