{
  "type": "Feature",
  "properties": {
    "addr:full":"17-19 Black St Oakleigh East VIC 3166",
    "addr:housenumber":"17-19",
    "addr:postcode":"3166",
    "addr:street":"Black St",
    "iso:country":"AU",
    "sg:address":"17-19 Black St",
    "sg:city":"Oakleigh East",
    "sg:classifiers":[
        {
            "category":"Shopping",
            "subcategory":"Stationery & Office Supplies",
            "type":"Retail Goods"
        }
    ],
    "sg:phone":"+61 1300 727 118",
    "sg:postcode":"3166",
    "sg:province":"VIC",
    "sg:tags":[
        "equipment",
        "display",
        "exhibition"
    ],
    "wof:name":"SAS",
    "wof:placetype":"venue"
},
  "geometry": {"coordinates":[145.12074279800001,-37.9123954773],"type":"Point"}
}