{
  "type": "Feature",
  "properties": {
    "iso:country":"AU",
    "sg:address":"19 Amethyst Drv",
    "sg:city":"Blackmans Bay",
    "sg:classifiers":[
        {
            "category":"Professional",
            "subcategory":"Art Services",
            "type":"Services"
        }
    ],
    "sg:phone":"+61 3 6229 2728",
    "sg:postcode":"7052",
    "sg:province":"TAS",
    "sg:tags":[
        "decorator",
        "painter"
    ],
    "wof:name":"Proffessional Painting Group",
    "wof:placetype":"venue"
},
  "geometry": {"coordinates":[147.317963,-42.995892],"type":"Point"}
}