{
  "type": "Feature",
  "properties": {
    "addr:full":"128 Hector St West Osborne Park WA 6017",
    "addr:housenumber":"128",
    "addr:postcode":"6017",
    "addr:street":"Hector St West",
    "iso:country":"AU",
    "sg:address":"128 Hector St West",
    "sg:city":"Osborne Park",
    "sg:classifiers":[
        {
            "category":"Retail",
            "subcategory":"Auto Repair",
            "type":"Services"
        }
    ],
    "sg:phone":"+61 8 9444 9863",
    "sg:postcode":"6017",
    "sg:province":"WA",
    "sg:tags":[
        "repairer",
        "motor",
        "engineer"
    ],
    "wof:name":"Cileberti Motors",
    "wof:placetype":"venue"
},
  "geometry": {"coordinates":[115.820617676,-31.9042720795],"type":"Point"}
}