{
  "type": "Feature",
  "properties": {
    "addr:full":"429 Oxley Drv Runaway Bay QLD 4216",
    "addr:housenumber":"429",
    "addr:postcode":"4216",
    "addr:street":"Oxley Drv",
    "iso:country":"AU",
    "sg:address":"429 Oxley Drv",
    "sg:city":"Runaway Bay",
    "sg:classifiers":[
        {
            "category":"Travel",
            "subcategory":"Hotels & Motels",
            "type":"Entertainment"
        }
    ],
    "sg:phone":"+61 7 5537 5555",
    "sg:postcode":"4216",
    "sg:province":"QLD",
    "wof:name":"Golden Chain Runaway Bay Motor Inn",
    "wof:placetype":"venue"
},
  "geometry": {"coordinates":[153.38771057100001,-27.9209537506],"type":"Point"}
}