{
  "type": "Feature",
  "properties": {
    "iso:country":"AU",
    "sg:address":"2 James St",
    "sg:city":"Geelong",
    "sg:classifiers":[
        {
            "category":"Shopping",
            "subcategory":"Antiques",
            "type":"Retail Goods"
        }
    ],
    "sg:phone":"+61 3 5221 8388",
    "sg:postcode":"3220",
    "sg:province":"VIC",
    "wof:name":"Barwon Booksellers Pty Ltd",
    "wof:placetype":"venue"
},
  "geometry": {"coordinates":[144.35862700000001,-38.148167],"type":"Point"}
}