{
  "type": "Feature",
  "properties": {
    "addr:full":"Algerian St Patchewollock VIC 3491",
    "addr:postcode":"3491",
    "iso:country":"AU",
    "sg:address":"Algerian St",
    "sg:city":"Patchewollock",
    "sg:classifiers":[
        {
            "category":"Education",
            "subcategory":"School",
            "type":"Public Place"
        }
    ],
    "sg:phone":"+61 3 5084 1221",
    "sg:postcode":"3491",
    "sg:province":"VIC",
    "sg:tags":[
        "state",
        "except",
        "nsw"
    ],
    "wof:name":"Patchewollock Primary School",
    "wof:placetype":"venue"
},
  "geometry": {"coordinates":[142.19161987300001,-35.3798332214],"type":"Point"}
}