{
  "type": "Feature",
  "properties": {
    "addr:full":"20 Myles Rd Swan View WA 6056",
    "addr:housenumber":"20",
    "addr:postcode":"6056",
    "addr:street":"Myles Rd",
    "iso:country":"AU",
    "sg:address":"20 Myles Rd",
    "sg:city":"Swan View",
    "sg:classifiers":[
        {
            "category":"Health Services",
            "subcategory":"Health Practitioner",
            "type":"Services"
        }
    ],
    "sg:phone":"+61 8 9294 3837",
    "sg:postcode":"6056",
    "sg:province":"WA",
    "sg:tags":[
        "naturopath"
    ],
    "wof:name":"Josephine Digweed",
    "wof:placetype":"venue"
},
  "geometry": {"coordinates":[116.041671753,-31.8836231232],"type":"Point"}
}