{
  "type": "Feature",
  "properties": {
    "iso:country":"AU",
    "sg:address":"44 Brighton Pde",
    "sg:city":"Southport",
    "sg:classifiers":[
        {
            "category":"Professional",
            "subcategory":"Computer Services",
            "type":"Services"
        }
    ],
    "sg:phone":"+61 7 5571 2058",
    "sg:postcode":"4215",
    "sg:province":"QLD",
    "sg:tags":[
        "repairs",
        "upgrade",
        "equipment"
    ],
    "wof:name":"Circle One Marketing",
    "wof:placetype":"venue"
},
  "geometry": {"coordinates":[153.40586852999999,-27.9363689423],"type":"Point"}
}