{
  "type": "Feature",
  "properties": {
    "addr:full":"23 Arthur St Booleroo Centre SA 5482",
    "addr:housenumber":"23",
    "addr:postcode":"5482",
    "addr:street":"Arthur St",
    "iso:country":"AU",
    "sg:address":"23 Arthur St",
    "sg:city":"Booleroo Centre",
    "sg:classifiers":[
        {
            "category":"Government",
            "subcategory":"Post Office",
            "type":"Public Place"
        }
    ],
    "sg:phone":"+61 8 8667 2185",
    "sg:postcode":"5482",
    "sg:province":"SA",
    "sg:tags":[
        "postal"
    ],
    "wof:name":"Australia Post",
    "wof:placetype":"venue"
},
  "geometry": {"coordinates":[138.346024,-32.881832],"type":"Point"}
}