{
  "type": "Feature",
  "properties": {
    "iso:country":"AU",
    "sg:address":"7 Danube Pl St",
    "sg:city":"Clair",
    "sg:classifiers":[
        {
            "category":"Building & Trades",
            "subcategory":"Construction",
            "type":"Services"
        }
    ],
    "sg:phone":"+61 411 874 351",
    "sg:postcode":"2759",
    "sg:province":"NSW",
    "sg:tags":[
        "installation",
        "air conditioning"
    ],
    "wof:name":"James & Scott Air Pty Ltd",
    "wof:placetype":"venue"
},
  "geometry": {"coordinates":[150.78463745100001,-33.7874832153],"type":"Point"}
}