{
  "type": "Feature",
  "properties": {
    "addr:full":"Siegersdorf Rd Nuriootpa SA 5355",
    "addr:postcode":"5355",
    "addr:street":"Siegersdorf Rd",
    "iso:country":"AU",
    "sg:address":"Siegersdorf Rd",
    "sg:city":"Nuriootpa",
    "sg:classifiers":[
        {
            "category":"Home & Garden",
            "subcategory":"Garden Supply",
            "type":"Retail Goods"
        }
    ],
    "sg:phone":"+61 8 8562 2177",
    "sg:postcode":"5355",
    "sg:province":"SA",
    "sg:tags":[
        "equipment"
    ],
    "wof:name":"Kuchel Landscape Supplies",
    "wof:placetype":"venue"
},
  "geometry": {"coordinates":[138.986816406,-34.4985923767],"type":"Point"}
}