{
  "type": "Feature",
  "properties": {
    "addr:full":"47a Willoughby Rd Crows Nest NSW 2065",
    "addr:housenumber":"47a",
    "addr:postcode":"2065",
    "addr:street":"Willoughby Rd",
    "iso:country":"AU",
    "sg:address":"47a Willoughby Rd",
    "sg:city":"Crows Nest",
    "sg:classifiers":[
        {
            "category":"Health Services",
            "subcategory":"Dentist",
            "type":"Services"
        }
    ],
    "sg:phone":"+61 2 9438 4425",
    "sg:postcode":"2065",
    "sg:province":"NSW",
    "wof:name":"Mobbs W R Dr",
    "wof:placetype":"venue"
},
  "geometry": {"coordinates":[151.20103454599999,-33.8260040283],"type":"Point"}
}