{
  "type": "Feature",
  "properties": {
    "addr:full":"1 Hemple Crs Wodonga VIC 3690",
    "addr:housenumber":"1",
    "addr:postcode":"3690",
    "addr:street":"Hemple Crs",
    "iso:country":"AU",
    "sg:address":"1 Hemple Crs",
    "sg:city":"Wodonga",
    "sg:classifiers":[
        {
            "category":"Retail",
            "subcategory":"Car Wash",
            "type":"Services"
        }
    ],
    "sg:phone":"+61 2 6024 7878",
    "sg:postcode":"3690",
    "sg:province":"VIC",
    "sg:tags":[
        "bitumen",
        "spraying"
    ],
    "wof:name":"Lyons Asphalting",
    "wof:placetype":"venue"
},
  "geometry": {"coordinates":[146.84840393100001,-36.1168785095],"type":"Point"}
}