{
  "type": "Feature",
  "properties": {
    "addr:full":"7 Milgate Drv Mornington VIC 3931",
    "addr:housenumber":"7",
    "addr:postcode":"3931",
    "addr:street":"Milgate Drv",
    "iso:country":"AU",
    "sg:address":"7 Milgate Drv",
    "sg:city":"Mornington",
    "sg:classifiers":[
        {
            "category":"Arena",
            "subcategory":"Sports Club",
            "type":"Entertainment"
        }
    ],
    "sg:phone":"+61 3 5975 3252",
    "sg:postcode":"3931",
    "sg:province":"VIC",
    "sg:tags":[
        "defence",
        "supply",
        "self",
        "instruction",
        "martial art"
    ],
    "wof:name":"Lifestyle Kung Fu",
    "wof:placetype":"venue"
},
  "geometry": {"coordinates":[145.06202697800001,-38.2341918945],"type":"Point"}
}