{
  "type": "Feature",
  "properties": {
    "addr:full":"265 Waterworks Rd Ashgrove QLD 4060",
    "addr:housenumber":"265",
    "addr:postcode":"4060",
    "addr:street":"Waterworks Rd",
    "iso:country":"AU",
    "sg:address":"265 Waterworks Rd",
    "sg:city":"Ashgrove",
    "sg:classifiers":[
        {
            "category":"Health Services",
            "subcategory":"Dentist",
            "type":"Services"
        }
    ],
    "sg:phone":"+61 7 3366 0220",
    "sg:postcode":"4060",
    "sg:province":"QLD",
    "sg:tags":[
        "qld",
        "orthodontist"
    ],
    "wof:name":"Ashgrove Orthodontics",
    "wof:placetype":"venue"
},
  "geometry": {"coordinates":[152.99092102,-27.4457492828],"type":"Point"}
}