{
  "type": "Feature",
  "properties": {
    "addr:full":"Shp7/ 53 Tambourine Bay Rd Riverview NSW 2066",
    "addr:postcode":"2066",
    "addr:street":"Tambourine Bay Rd",
    "iso:country":"AU",
    "sg:address":"Shp7/ 53 Tambourine Bay Rd",
    "sg:city":"Riverview",
    "sg:classifiers":[
        {
            "category":"Deli",
            "type":"Food & Drink"
        }
    ],
    "sg:phone":"+61 2 9420 5307",
    "sg:postcode":"2066",
    "sg:province":"NSW",
    "sg:tags":[
        "delicatessen"
    ],
    "wof:name":"Riverview Deli",
    "wof:placetype":"venue"
},
  "geometry": {"coordinates":[151.164627075,-33.820350647],"type":"Point"}
}