{
  "type": "Feature",
  "properties": {
    "iso:country":"AU",
    "sg:address":"15 Massey St",
    "sg:city":"Gladesville",
    "sg:classifiers":[
        {
            "category":"Professional",
            "subcategory":"Art Services",
            "type":"Services"
        }
    ],
    "sg:phone":"+61 2 9817 5754",
    "sg:postcode":"2111",
    "sg:province":"NSW",
    "sg:tags":[
        "graphic",
        "designer"
    ],
    "wof:name":"Dalton Creative Services Pty Ltd",
    "wof:placetype":"venue"
},
  "geometry": {"coordinates":[151.128372192,-33.8304176331],"type":"Point"}
}