{
  "type": "Feature",
  "properties": {
    "iso:country":"AU",
    "sg:address":"4/211- 217 Queen St St",
    "sg:city":"Marys",
    "sg:classifiers":[
        {
            "category":"Health Services",
            "subcategory":"Dentist",
            "type":"Services"
        }
    ],
    "sg:phone":"+61 2 9623 1398",
    "sg:postcode":"2760",
    "sg:province":"NSW",
    "wof:name":"Dental Surgery",
    "wof:placetype":"venue"
},
  "geometry": {"coordinates":[150.77354431099999,-33.7685546875],"type":"Point"}
}