{
  "type": "Feature",
  "properties": {
    "addr:full":"Level 1 340 Ross River Rd Townsville QLD 4810",
    "addr:housenumber":"340",
    "addr:postcode":"4810",
    "addr:street":"Ross River Rd",
    "iso:country":"AU",
    "sg:address":"Level 1 340 Ross River Rd",
    "sg:city":"Townsville",
    "sg:classifiers":[
        {
            "category":"Insurance",
            "subcategory":"Life Insurance",
            "type":"Services"
        }
    ],
    "sg:phone":"+61 7 4779 2803",
    "sg:postcode":"4810",
    "sg:province":"QLD",
    "wof:name":"Elders Financial Planning",
    "wof:placetype":"venue"
},
  "geometry": {"coordinates":[146.760696,-19.298468],"type":"Point"}
}