{
  "type": "Feature",
  "properties": {
    "addr:full":"1247 Howitt St Wendouree VIC 3355",
    "addr:housenumber":"1247",
    "addr:postcode":"3355",
    "addr:street":"Howitt St",
    "iso:country":"AU",
    "sg:address":"1247 Howitt St",
    "sg:city":"Wendouree",
    "sg:classifiers":[
        {
            "category":"Professional",
            "subcategory":"Computer Services",
            "type":"Services"
        }
    ],
    "sg:phone":"+61 3 5339 9335",
    "sg:postcode":"3355",
    "sg:province":"VIC",
    "sg:tags":[
        "repairs",
        "upgrade",
        "equipment"
    ],
    "wof:name":"Corporate Computer EXperts",
    "wof:placetype":"venue"
},
  "geometry": {"coordinates":[143.82609600000001,-37.539749],"type":"Point"}
}