{
  "type": "Feature",
  "properties": {
    "addr:full":"8 / 10 Jijaws St Sumner Park QLD 4074",
    "addr:housenumber":"/ 10",
    "addr:postcode":"4074",
    "addr:street":"Jijaws St",
    "iso:country":"AU",
    "sg:address":"8 / 10 Jijaws St",
    "sg:city":"Sumner Park",
    "sg:classifiers":[
        {
            "category":"Home & Garden",
            "subcategory":"Building Materials",
            "type":"Retail Goods"
        }
    ],
    "sg:phone":"+61 7 3279 5022",
    "sg:postcode":"4074",
    "sg:province":"QLD",
    "sg:tags":[
        "plaster",
        "plasterboard",
        "supply"
    ],
    "wof:name":"Sumner Plaster Shop",
    "wof:placetype":"venue"
},
  "geometry": {"coordinates":[152.94023132300001,-27.5651493073],"type":"Point"}
}