{
  "type": "Feature",
  "properties": {
    "addr:full":"Unit 2/ 5 Ayrshire Crs Sandgate NSW 2304",
    "addr:housenumber":"5",
    "addr:postcode":"2304",
    "addr:street":"Ayrshire Crs",
    "iso:country":"AU",
    "sg:address":"Unit 2/ 5 Ayrshire Crs",
    "sg:city":"Sandgate",
    "sg:classifiers":[
        {
            "category":"Wholesale",
            "subcategory":"Auto Parts",
            "type":"Manufacturing & Wholesale Goods"
        }
    ],
    "sg:phone":"+61 2 4967 6566",
    "sg:postcode":"2304",
    "sg:province":"NSW",
    "sg:tags":[
        "tyre"
    ],
    "wof:name":"Independent Tyre Distributors",
    "wof:placetype":"venue"
},
  "geometry": {"coordinates":[151.704711914,-32.8609695435],"type":"Point"}
}