{
  "type": "Feature",
  "properties": {
    "addr:full":"6 Brooke St Launceston TAS 7250",
    "addr:housenumber":"6",
    "addr:postcode":"7250",
    "addr:street":"Brooke St",
    "iso:country":"AU",
    "sg:address":"6 Brooke St",
    "sg:city":"Launceston",
    "sg:classifiers":[
        {
            "category":"Wholesale",
            "subcategory":"Construction Materials",
            "type":"Manufacturing & Wholesale Goods"
        }
    ],
    "sg:phone":"+61 3 6331 1871",
    "sg:postcode":"7250",
    "sg:province":"TAS",
    "sg:tags":[
        "wholesaler",
        "equipment",
        "bathroom",
        "mfrs",
        "accessory"
    ],
    "wof:name":"Don-El Sales Pty Ltd",
    "wof:placetype":"venue"
},
  "geometry": {"coordinates":[147.18336486800001,-41.4370994568],"type":"Point"}
}