{
  "type": "Feature",
  "properties": {
    "addr:full":"7 Erudina Ave Edwardstown SA 5039",
    "addr:housenumber":"7",
    "addr:postcode":"5039",
    "addr:street":"Erudina Ave",
    "iso:country":"AU",
    "sg:address":"7 Erudina Ave",
    "sg:city":"Edwardstown",
    "sg:classifiers":[
        {
            "category":"Retail",
            "subcategory":"Auto Repair",
            "type":"Services"
        }
    ],
    "sg:phone":"+61 8 8374 1299",
    "sg:postcode":"5039",
    "sg:province":"SA",
    "sg:tags":[
        "repairer",
        "motor",
        "engineer"
    ],
    "wof:name":"Mini Worx Centre",
    "wof:placetype":"venue"
},
  "geometry": {"coordinates":[138.571777344,-34.9909896851],"type":"Point"}
}