{
  "type": "Feature",
  "properties": {
    "addr:full":"273 Waverley Rd Malvern East VIC 3145",
    "addr:housenumber":"273",
    "addr:postcode":"3145",
    "addr:street":"Waverley Rd",
    "iso:country":"AU",
    "sg:address":"273 Waverley Rd",
    "sg:city":"Malvern East",
    "sg:classifiers":[
        {
            "category":"Building & Trades",
            "subcategory":"Landscaping Services",
            "type":"Services"
        }
    ],
    "sg:phone":"+61 3 9563 6246",
    "sg:postcode":"3145",
    "sg:province":"VIC",
    "sg:tags":[
        "consultant"
    ],
    "wof:name":"Buildcheck",
    "wof:placetype":"venue"
},
  "geometry": {"coordinates":[145.0574646,-37.8769454956],"type":"Point"}
}