{
  "type": "Feature",
  "properties": {
    "addr:full":"262 Loch St Derby WA 6728",
    "addr:housenumber":"262",
    "addr:postcode":"6728",
    "addr:street":"Loch St",
    "iso:country":"AU",
    "sg:address":"262 Loch St",
    "sg:city":"Derby",
    "sg:classifiers":[
        {
            "category":"Shopping",
            "type":"Retail Goods"
        }
    ],
    "sg:phone":"+61 8 9191 1808",
    "sg:postcode":"6728",
    "sg:province":"WA",
    "sg:tags":[
        "agent",
        "stock"
    ],
    "wof:name":"Elders Ltd",
    "wof:placetype":"venue"
},
  "geometry": {"coordinates":[123.639686584,-17.3090705872],"type":"Point"}
}