{
  "type": "Feature",
  "properties": {
    "iso:country":"AU",
    "sg:address":"30 Beach Rd",
    "sg:city":"Christies Beach",
    "sg:classifiers":[
        {
            "category":"Banks & Credit Unions",
            "subcategory":"Bank",
            "type":"Services"
        }
    ],
    "sg:phone":"+61 423 036 940",
    "sg:postcode":"5165",
    "sg:province":"SA",
    "sg:tags":[
        "broker",
        "mortgage"
    ],
    "wof:name":"Sharon McAlister",
    "wof:placetype":"venue"
},
  "geometry": {"coordinates":[138.47366332999999,-35.1394462585],"type":"Point"}
}