{
  "type": "Feature",
  "properties": {
    "addr:full":"26 Birdwood Ave Dandenong VIC 3175",
    "addr:housenumber":"26",
    "addr:postcode":"3175",
    "addr:street":"Birdwood Ave",
    "iso:country":"AU",
    "sg:address":"26 Birdwood Ave",
    "sg:city":"Dandenong",
    "sg:classifiers":[
        {
            "category":"Building & Trades",
            "subcategory":"Plumbing",
            "type":"Services"
        }
    ],
    "sg:phone":"+61 409 960 234",
    "sg:postcode":"3175",
    "sg:province":"VIC",
    "sg:tags":[
        "repair",
        "appliance",
        "system",
        "heating"
    ],
    "wof:name":"Dada Climate Systems Pty Ltd",
    "wof:placetype":"venue"
},
  "geometry": {"coordinates":[145.20185852,-37.9808883667],"type":"Point"}
}