{
  "type": "Feature",
  "properties": {
    "addr:full":"1969 Frankford Rd Frankford TAS 7275",
    "addr:housenumber":"1969",
    "addr:postcode":"7275",
    "addr:street":"Frankford Rd",
    "iso:country":"AU",
    "sg:address":"1969 Frankford Rd",
    "sg:city":"Frankford",
    "sg:classifiers":[
        {
            "category":"Cafe",
            "type":"Food & Drink"
        }
    ],
    "sg:phone":"+61 3 6396 1241",
    "sg:postcode":"7275",
    "sg:province":"TAS",
    "wof:name":"Blueberry Barn Cafe",
    "wof:placetype":"venue"
},
  "geometry": {"coordinates":[146.77395629899999,-41.3420562744],"type":"Point"}
}