{
  "type": "Feature",
  "properties": {
    "addr:full":"27 Raws St Hume ACT 2620",
    "addr:housenumber":"27",
    "addr:postcode":"2620",
    "addr:street":"Raws St",
    "iso:country":"AU",
    "sg:address":"27 Raws St",
    "sg:city":"Hume",
    "sg:classifiers":[
        {
            "category":"Home & Garden",
            "subcategory":"Building Materials",
            "type":"Retail Goods"
        }
    ],
    "sg:phone":"+61 2 6260 1822",
    "sg:postcode":"2620",
    "sg:province":"ACT",
    "sg:tags":[
        "fitting",
        "door"
    ],
    "wof:name":"Modernfold (Australia)",
    "wof:placetype":"venue"
},
  "geometry": {"coordinates":[149.146240234,-35.186050415],"type":"Point"}
}