{
  "type": "Feature",
  "properties": {
    "addr:full":"Foxlow St Captains Flat ACT 2623",
    "addr:postcode":"2623",
    "addr:street":"Foxlow St",
    "iso:country":"AU",
    "sg:address":"Foxlow St",
    "sg:city":"Captains Flat",
    "sg:classifiers":[
        {
            "category":"Travel",
            "subcategory":"Hotels & Motels",
            "type":"Entertainment"
        }
    ],
    "sg:phone":"+61 2 6236 6201",
    "sg:postcode":"2623",
    "sg:province":"ACT",
    "sg:tags":[
        "accommodation"
    ],
    "wof:name":"Captains Flat Hotel",
    "wof:placetype":"venue"
},
  "geometry": {"coordinates":[149.44221496599999,-35.5705375671],"type":"Point"}
}