{
  "type": "Feature",
  "properties": {
    "addr:full":"70 - 90 Garden Drv Tullamarine VIC 3043",
    "addr:housenumber":"90",
    "addr:postcode":"3043",
    "addr:street":"Garden Drv",
    "iso:country":"AU",
    "sg:address":"70 - 90 Garden Drv",
    "sg:city":"Tullamarine",
    "sg:classifiers":[
        {
            "category":"Manufacturing",
            "subcategory":"Aerospace",
            "type":"Manufacturing & Wholesale Goods"
        }
    ],
    "sg:phone":"+61 3 8346 2111",
    "sg:postcode":"3043",
    "sg:province":"VIC",
    "sg:tags":[
        "equipment",
        "aircraft",
        "maintenance"
    ],
    "wof:name":"Jet Turbine Services Pty Ltd",
    "wof:placetype":"venue"
},
  "geometry": {"coordinates":[144.87542724599999,-37.6887626648],"type":"Point"}
}