{
  "type": "Feature",
  "properties": {
    "iso:country":"AU",
    "sg:address":"1/ 1712 Gold Coast Hwy",
    "sg:city":"Burleigh Heads",
    "sg:classifiers":[
        {
            "category":"Professional",
            "subcategory":"Management & Consulting",
            "type":"Services"
        }
    ],
    "sg:phone":"+61 7 5535 7255",
    "sg:postcode":"4220",
    "sg:province":"QLD",
    "sg:tags":[
        "consultant",
        "migration"
    ],
    "wof:name":"Whitehead Gupta Lawyers",
    "wof:placetype":"venue"
},
  "geometry": {"coordinates":[153.45130920400001,-28.0886974335],"type":"Point"}
}