{
  "type": "Feature",
  "properties": {
    "iso:country":"AU",
    "sg:address":"165 Melbourne Rd",
    "sg:city":"Wodonga",
    "sg:classifiers":[
        {
            "category":"Retail",
            "subcategory":"Car Wash",
            "type":"Services"
        }
    ],
    "sg:phone":"+61 2 6022 9407",
    "sg:postcode":"3690",
    "sg:province":"VIC",
    "sg:tags":[
        "truck",
        "cleaning"
    ],
    "wof:name":"M. One Group",
    "wof:placetype":"venue"
},
  "geometry": {"coordinates":[146.871780395,-36.1172943115],"type":"Point"}
}