{
  "type": "Feature",
  "properties": {
    "iso:country":"AU",
    "sg:address":"41b Hitchcock Ave",
    "sg:city":"Barwon Heads",
    "sg:classifiers":[
        {
            "category":"Personal",
            "subcategory":"Beauty Salon",
            "type":"Services"
        }
    ],
    "sg:phone":"+61 3 5254 3340",
    "sg:postcode":"3227",
    "sg:province":"VIC",
    "sg:tags":[
        "hairdresser"
    ],
    "wof:name":"Marycheles Hair Studio",
    "wof:placetype":"venue"
},
  "geometry": {"coordinates":[144.49144000000001,-38.282001],"type":"Point"}
}