{
  "type": "Feature",
  "properties": {
    "iso:country":"AU",
    "sg:address":"Strathpine Shopping Town Gympie Rd",
    "sg:city":"Strathpine",
    "sg:classifiers":[
        {
            "category":"Shopping",
            "subcategory":"Department Store",
            "type":"Retail Goods"
        }
    ],
    "sg:phone":"+61 7 3205 6400",
    "sg:postcode":"4500",
    "sg:province":"QLD",
    "wof:name":"Best & Less Pty Ltd",
    "wof:placetype":"venue"
},
  "geometry": {"coordinates":[152.988479614,-27.3020896912],"type":"Point"}
}