{
  "type": "Feature",
  "properties": {
    "iso:country":"AU",
    "sg:address":"1 Turner St",
    "sg:city":"West Bundaberg",
    "sg:classifiers":[
        {
            "category":"Building & Trades",
            "subcategory":"Construction",
            "type":"Services"
        }
    ],
    "sg:phone":"+61 7 4152 3899",
    "sg:postcode":"4670",
    "sg:province":"QLD",
    "sg:tags":[
        "scaffolding"
    ],
    "wof:name":"RMD Australia",
    "wof:placetype":"venue"
},
  "geometry": {"coordinates":[152.319946289,-24.8846359253],"type":"Point"}
}