{
  "type": "Feature",
  "properties": {
    "addr:full":"104 King St East Doncaster VIC 3108",
    "addr:housenumber":"104",
    "addr:postcode":"3108",
    "addr:street":"King St",
    "iso:country":"AU",
    "sg:address":"104 King St East",
    "sg:city":"Doncaster",
    "sg:classifiers":[
        {
            "category":"Professional",
            "subcategory":"Accounting & Tax Preparation",
            "type":"Services"
        }
    ],
    "sg:phone":"+61 3 9841 0588",
    "sg:postcode":"3108",
    "sg:province":"VIC",
    "sg:tags":[
        "bookkeeping"
    ],
    "wof:name":"SK-Data Services",
    "wof:placetype":"venue"
},
  "geometry": {"coordinates":[145.15740966800001,-37.7744865417],"type":"Point"}
}