{
  "type": "Feature",
  "properties": {
    "iso:country":"AU",
    "sg:address":"212 Warrigal Rd",
    "sg:city":"Oakleigh South",
    "sg:classifiers":[
        {
            "category":"Health Services",
            "subcategory":"Health Practitioner",
            "type":"Services"
        }
    ],
    "sg:phone":"+61 3 9570 4316",
    "sg:postcode":"3167",
    "sg:province":"VIC",
    "sg:tags":[
        "acupuncture"
    ],
    "wof:name":"Lall Mahinder",
    "wof:placetype":"venue"
},
  "geometry": {"coordinates":[145.085327148,-37.9102401733],"type":"Point"}
}