{
  "type": "Feature",
  "properties": {
    "addr:full":"19 Fadden Pl Wahroonga NSW 2076",
    "addr:housenumber":"19",
    "addr:postcode":"2076",
    "addr:street":"Fadden Pl",
    "iso:country":"AU",
    "sg:address":"19 Fadden Pl",
    "sg:city":"Wahroonga",
    "sg:classifiers":[
        {
            "category":"Real Estate",
            "subcategory":"Real Estate Services",
            "type":"Services"
        }
    ],
    "sg:phone":"+61 2 9943 0100",
    "sg:postcode":"2076",
    "sg:province":"NSW",
    "sg:tags":[
        "valuer"
    ],
    "wof:name":"Peter Phippen & Associates",
    "wof:placetype":"venue"
},
  "geometry": {"coordinates":[151.12376403799999,-33.6974639893],"type":"Point"}
}