{
  "type": "Feature",
  "properties": {
    "addr:full":"Shop 2, 119 Johnson St Maffra VIC 3860",
    "addr:housenumber":"shop 2 119",
    "addr:postcode":"3860",
    "addr:street":"Johnson St",
    "iso:country":"AU",
    "sg:address":"Shop 2, 119 Johnson St",
    "sg:city":"Maffra",
    "sg:classifiers":[
        {
            "category":"Health Services",
            "subcategory":"Doctor",
            "type":"Services"
        }
    ],
    "sg:phone":"+61 3 5141 1889",
    "sg:postcode":"3860",
    "sg:province":"VIC",
    "sg:tags":[
        "medical",
        "practitioner"
    ],
    "wof:name":"Bvirakare J Dr",
    "wof:placetype":"venue"
},
  "geometry": {"coordinates":[146.976287842,-37.967540741],"type":"Point"}
}