{
  "type": "Feature",
  "properties": {
    "iso:country":"AU",
    "sg:address":"54 Coogee Ave",
    "sg:city":"Frankston Heights",
    "sg:classifiers":[
        {
            "category":"Building & Trades",
            "subcategory":"Construction",
            "type":"Services"
        }
    ],
    "sg:phone":"+61 411 747 227",
    "sg:postcode":"3199",
    "sg:province":"VIC",
    "sg:tags":[
        "polishing",
        "sanding",
        "floor"
    ],
    "wof:name":"Darren Wiggins Floors",
    "wof:placetype":"venue"
},
  "geometry": {"coordinates":[145.14308166500001,-38.1607475281],"type":"Point"}
}