{
  "type": "Feature",
  "properties": {
    "addr:full":"24 Walters Drv Osborne Park WA 6017",
    "addr:housenumber":"24",
    "addr:postcode":"6017",
    "addr:street":"Walters Drv",
    "iso:country":"AU",
    "sg:address":"24 Walters Drv",
    "sg:city":"Osborne Park",
    "sg:classifiers":[
        {
            "category":"Professional",
            "subcategory":"Accounting & Tax Preparation",
            "type":"Services"
        }
    ],
    "sg:phone":"+61 8 9244 2900",
    "sg:postcode":"6017",
    "sg:province":"WA",
    "sg:tags":[
        "accountant",
        "auditor"
    ],
    "wof:name":"Shreeve & Carslake",
    "wof:placetype":"venue"
},
  "geometry": {"coordinates":[115.80847168,-31.9092655182],"type":"Point"}
}