{
  "type": "Feature",
  "properties": {
    "addr:full":"83 Somerset Drv Mt Martha VIC 3934",
    "addr:housenumber":"83",
    "addr:postcode":"3934",
    "addr:street":"Somerset Drv Mt Martha",
    "iso:country":"AU",
    "sg:address":"83 Somerset Drv",
    "sg:city":"Mt Martha",
    "sg:classifiers":[
        {
            "category":"Utilities",
            "subcategory":"Telephone",
            "type":"Services"
        }
    ],
    "sg:phone":"+61 3 5974 2828",
    "sg:postcode":"3934",
    "sg:province":"VIC",
    "sg:tags":[
        "installation",
        "system",
        "maintenance"
    ],
    "wof:name":"Beejay Communications",
    "wof:placetype":"venue"
},
  "geometry": {"coordinates":[145.02000427199999,-38.2839927673],"type":"Point"}
}