{
  "type": "Feature",
  "properties": {
    "addr:full":"3 Weddin St Grenfell NSW 2810",
    "addr:housenumber":"3",
    "addr:postcode":"2810",
    "addr:street":"Weddin St",
    "iso:country":"AU",
    "sg:address":"3 Weddin St",
    "sg:city":"Grenfell",
    "sg:classifiers":[
        {
            "category":"Health Services",
            "subcategory":"Doctor",
            "type":"Services"
        }
    ],
    "sg:phone":"+61 2 6343 2494",
    "sg:postcode":"2810",
    "sg:province":"NSW",
    "sg:tags":[
        "medical",
        "practitioner"
    ],
    "wof:name":"Jayaram Vijay Dr",
    "wof:placetype":"venue"
},
  "geometry": {"coordinates":[148.162765503,-33.8948707581],"type":"Point"}
}