{
  "type": "Feature",
  "properties": {
    "iso:country":"AU",
    "sg:address":"35 Lawley St",
    "sg:city":"North Beach",
    "sg:classifiers":[
        {
            "category":"Education",
            "subcategory":"Dance Studio",
            "type":"Public Place"
        }
    ],
    "sg:phone":"+61 8 9448 6519",
    "sg:postcode":"6020",
    "sg:province":"WA",
    "sg:tags":[
        "instruction",
        "language"
    ],
    "wof:name":"German Language Classes (WA)",
    "wof:placetype":"venue"
},
  "geometry": {"coordinates":[115.75614166299999,-31.8545036316],"type":"Point"}
}