{
  "type": "Feature",
  "properties": {
    "addr:full":"42 Fowler St Moe VIC 3825",
    "addr:housenumber":"42",
    "addr:postcode":"3825",
    "addr:street":"Fowler St",
    "iso:country":"AU",
    "sg:address":"42 Fowler St",
    "sg:city":"Moe",
    "sg:classifiers":[
        {
            "category":"Health Services",
            "subcategory":"Dentist",
            "type":"Services"
        }
    ],
    "sg:phone":"+61 3 5127 5512",
    "sg:postcode":"3825",
    "sg:province":"VIC",
    "wof:name":"Latrobe Community Health Dental Clinic",
    "wof:placetype":"venue"
},
  "geometry": {"coordinates":[146.26132200000001,-38.180054],"type":"Point"}
}