{
  "type": "Feature",
  "properties": {
    "addr:full":"699 Boronia Rd Wantirna VIC 3152",
    "addr:housenumber":"699",
    "addr:postcode":"3152",
    "addr:street":"Boronia Rd",
    "iso:country":"AU",
    "sg:address":"699 Boronia Rd",
    "sg:city":"Wantirna",
    "sg:classifiers":[
        {
            "category":"Autos & Motor Vehicles",
            "subcategory":"Fuel & Gas Station",
            "type":"Retail Goods"
        }
    ],
    "sg:phone":"+61 3 9887 0615",
    "sg:postcode":"3152",
    "sg:province":"VIC",
    "wof:name":"Plus Petrol",
    "wof:placetype":"venue"
},
  "geometry": {"coordinates":[145.2265625,-37.847366333],"type":"Point"}
}