{
  "type": "Feature",
  "properties": {
    "addr:full":"Fact 1/ 145 Victoria St North Geelong VIC 3215",
    "addr:housenumber":"1 / 145",
    "addr:postcode":"3215",
    "addr:street":"Fact;Victoria St",
    "iso:country":"AU",
    "sg:address":"Fact 1/ 145 Victoria St",
    "sg:city":"North Geelong",
    "sg:classifiers":[
        {
            "category":"Building & Trades",
            "subcategory":"Cleaning & Sanitation",
            "type":"Services"
        }
    ],
    "sg:phone":"+61 3 5272 3123",
    "sg:postcode":"3215",
    "sg:province":"VIC",
    "sg:tags":[
        "window"
    ],
    "wof:name":"Clearwater Business Services",
    "wof:placetype":"venue"
},
  "geometry": {"coordinates":[144.34677124000001,-38.1222763062],"type":"Point"}
}