{
  "type": "Feature",
  "properties": {
    "iso:country":"AU",
    "sg:address":"56 Morley St",
    "sg:city":"Coorparoo",
    "sg:classifiers":[
        {
            "category":"Retail",
            "subcategory":"Auto Repair",
            "type":"Services"
        }
    ],
    "sg:phone":"+61 7 3394 1174",
    "sg:postcode":"4151",
    "sg:province":"QLD",
    "sg:tags":[
        "transmission",
        "automotive",
        "car"
    ],
    "wof:name":"Engine & Transmission Centre",
    "wof:placetype":"venue"
},
  "geometry": {"coordinates":[153.05223083499999,-27.4919471741],"type":"Point"}
}