{
  "type": "Feature",
  "properties": {
    "addr:full":"184 Boronia Rd Boronia VIC 3155",
    "addr:housenumber":"184",
    "addr:postcode":"3155",
    "addr:street":"Boronia Rd",
    "iso:country":"AU",
    "sg:address":"184 Boronia Rd",
    "sg:city":"Boronia",
    "sg:classifiers":[
        {
            "category":"Home & Garden",
            "subcategory":"Carpets & Floor Coverings",
            "type":"Retail Goods"
        }
    ],
    "sg:phone":"+61 414 877 897",
    "sg:postcode":"3155",
    "sg:province":"VIC",
    "sg:tags":[
        "tile",
        "wall",
        "layer"
    ],
    "wof:name":"U Beaut Brickworks",
    "wof:placetype":"venue"
},
  "geometry": {"coordinates":[145.27891540499999,-37.8620910645],"type":"Point"}
}