{
  "type": "Feature",
  "properties": {
    "addr:full":"128 Mortimer St Mudgee NSW 2850",
    "addr:housenumber":"128",
    "addr:postcode":"2850",
    "addr:street":"Mortimer St",
    "iso:country":"AU",
    "sg:address":"128 Mortimer St",
    "sg:city":"Mudgee",
    "sg:classifiers":[
        {
            "category":"Social Services",
            "subcategory":"Child Care",
            "type":"Services"
        }
    ],
    "sg:phone":"+61 2 6372 2620",
    "sg:postcode":"2850",
    "sg:province":"NSW",
    "wof:name":"Squeakers Long Day Care Centre",
    "wof:placetype":"venue"
},
  "geometry": {"coordinates":[149.582458,-32.592178],"type":"Point"}
}