{
  "type": "Feature",
  "properties": {
    "iso:country":"AU",
    "sg:address":"16 Junee Rd",
    "sg:city":"Temora",
    "sg:classifiers":[
        {
            "category":"Communications",
            "subcategory":"News Services",
            "type":"Services"
        }
    ],
    "sg:phone":"+61 2 6978 0780",
    "sg:postcode":"2666",
    "sg:province":"NSW",
    "sg:tags":[
        "information",
        "tourist",
        "attractions"
    ],
    "wof:name":"Durham's Coaches",
    "wof:placetype":"venue"
},
  "geometry": {"coordinates":[147.534881592,-34.4553489685],"type":"Point"}
}