{
  "type": "Feature",
  "properties": {
    "addr:full":"265 Heaths Rd Werribee VIC 3030",
    "addr:housenumber":"265",
    "addr:postcode":"3030",
    "addr:street":"Heaths Rd",
    "iso:country":"AU",
    "sg:address":"265 Heaths Rd",
    "sg:city":"Werribee",
    "sg:classifiers":[
        {
            "category":"Health Services",
            "subcategory":"Nursing And Care Facility",
            "type":"Services"
        }
    ],
    "sg:phone":"+61 3 8742 8888",
    "sg:postcode":"3030",
    "sg:province":"VIC",
    "sg:tags":[
        "home"
    ],
    "wof:name":"Orden Hostel",
    "wof:placetype":"venue"
},
  "geometry": {"coordinates":[144.67765800000001,-37.877125],"type":"Point"}
}