{
  "type": "Feature",
  "properties": {
    "addr:full":"Shp 2/ 16 Yeates Ave Boonah QLD 4310",
    "addr:housenumber":"/ 16",
    "addr:postcode":"4310",
    "addr:street":"Yeates Ave Boonah",
    "iso:country":"AU",
    "sg:address":"Shp 2/ 16 Yeates Ave",
    "sg:city":"Boonah",
    "sg:classifiers":[
        {
            "category":"Cafe",
            "type":"Food & Drink"
        }
    ],
    "sg:phone":"+61 7 5463 2000",
    "sg:postcode":"4310",
    "sg:province":"QLD",
    "wof:name":"Boonah Bush Beat Cafe",
    "wof:placetype":"venue"
},
  "geometry": {"coordinates":[152.6822052,-27.9942455292],"type":"Point"}
}