{
  "type": "Feature",
  "properties": {
    "iso:country":"AU",
    "sg:address":"41 Allison St",
    "sg:city":"Mayne",
    "sg:classifiers":[
        {
            "category":"Autos & Motor Vehicles",
            "subcategory":"Auto Supplies",
            "type":"Retail Goods"
        }
    ],
    "sg:phone":"+61 7 3252 3939",
    "sg:postcode":"4006",
    "sg:province":"QLD",
    "sg:tags":[
        "part",
        "cycles",
        "accessory"
    ],
    "wof:name":"Pipemasters Motorcycle Exhausts",
    "wof:placetype":"venue"
},
  "geometry": {"coordinates":[153.04119873100001,-27.439239502],"type":"Point"}
}