{
  "type": "Feature",
  "properties": {
    "iso:country":"AU",
    "sg:address":"19 Heath Rd",
    "sg:city":"Blakehurst",
    "sg:classifiers":[
        {
            "category":"Wholesale",
            "subcategory":"Home Furnishings",
            "type":"Manufacturing & Wholesale Goods"
        }
    ],
    "sg:phone":"+61 2 8558 3500",
    "sg:postcode":"2221",
    "sg:province":"NSW",
    "wof:name":"Materialised Pty Ltd",
    "wof:placetype":"venue"
},
  "geometry": {"coordinates":[151.110870361,-33.9850730896],"type":"Point"}
}