{
  "type": "Feature",
  "properties": {
    "addr:full":"1739 Channel Hwy Margate TAS 7054",
    "addr:housenumber":"1739",
    "addr:postcode":"7054",
    "addr:street":"Channel Hwy",
    "iso:country":"AU",
    "sg:address":"1739 Channel Hwy",
    "sg:city":"Margate",
    "sg:classifiers":[
        {
            "category":"Professional",
            "subcategory":"Art Services",
            "type":"Services"
        }
    ],
    "sg:phone":"+61 409 253 331",
    "sg:postcode":"7054",
    "sg:province":"TAS",
    "sg:tags":[
        "decorator",
        "painter"
    ],
    "wof:name":"Channel Home Improvements",
    "wof:placetype":"venue"
},
  "geometry": {"coordinates":[147.262924,-43.02816],"type":"Point"}
}