{
  "type": "Feature",
  "properties": {
    "iso:country":"AU",
    "sg:address":"Shannon St",
    "sg:city":"Birdwood",
    "sg:classifiers":[
        {
            "category":"Communications",
            "subcategory":"News Services",
            "type":"Services"
        }
    ],
    "sg:phone":"+61 8 8568 5577",
    "sg:postcode":"5234",
    "sg:province":"SA",
    "sg:tags":[
        "information",
        "tourist",
        "attractions"
    ],
    "wof:name":"Birdwood Visitor Information Centre",
    "wof:placetype":"venue"
},
  "geometry": {"coordinates":[138.96368408199999,-34.8186073303],"type":"Point"}
}