{
  "type": "Feature",
  "properties": {
    "addr:full":"45 Bourne Rd Glen Iris VIC 3146",
    "addr:housenumber":"45",
    "addr:postcode":"3146",
    "addr:street":"Bourne Rd",
    "iso:country":"AU",
    "sg:address":"45 Bourne Rd",
    "sg:city":"Glen Iris",
    "sg:classifiers":[
        {
            "category":"Retail",
            "subcategory":"Auto Rental",
            "type":"Services"
        }
    ],
    "sg:phone":"+61 3 9885 8125",
    "sg:postcode":"3146",
    "sg:province":"VIC",
    "sg:tags":[
        "car",
        "wedding"
    ],
    "wof:name":"Classic & Prestige Car Hire",
    "wof:placetype":"venue"
},
  "geometry": {"coordinates":[145.061004639,-37.8569221497],"type":"Point"}
}