{
  "type": "Feature",
  "properties": {
    "addr:full":"12 Expansion St Molendinar QLD 4214",
    "addr:housenumber":"12",
    "addr:postcode":"4214",
    "addr:street":"Expansion St",
    "iso:country":"AU",
    "sg:address":"12 Expansion St",
    "sg:city":"Molendinar",
    "sg:classifiers":[
        {
            "category":"Wholesale",
            "subcategory":"Metals & Minerals",
            "type":"Manufacturing & Wholesale Goods"
        }
    ],
    "sg:phone":"+61 7 5564 6565",
    "sg:postcode":"4214",
    "sg:province":"QLD",
    "sg:tags":[
        "steel",
        "stainless",
        "product",
        "equipment"
    ],
    "wof:name":"Pacific Commercial Catering Equipment",
    "wof:placetype":"venue"
},
  "geometry": {"coordinates":[153.357421875,-27.9760570526],"type":"Point"}
}