{
  "type": "Feature",
  "properties": {
    "addr:full":"38/ 75a Ross St Glebe NSW 2037",
    "addr:housenumber":"38 / 75a",
    "addr:postcode":"2037",
    "addr:street":"Ross St",
    "iso:country":"AU",
    "sg:address":"38/ 75a Ross St",
    "sg:city":"Glebe",
    "sg:classifiers":[
        {
            "category":"Building & Trades",
            "subcategory":"Plumbing",
            "type":"Services"
        }
    ],
    "sg:phone":"+61 407 243 373",
    "sg:postcode":"2037",
    "sg:province":"NSW",
    "sg:tags":[
        "plumber",
        "gasfitters"
    ],
    "wof:name":"Coo-ee Plumbing",
    "wof:placetype":"venue"
},
  "geometry": {"coordinates":[151.18066406200001,-33.8798408508],"type":"Point"}
}