{
  "type": "Feature",
  "properties": {
    "addr:full":"PO Box 1020 Griffith NSW 2680",
    "addr:postcode":"2680",
    "iso:country":"AU",
    "sg:address":"PO Box 1020",
    "sg:city":"Griffith",
    "sg:classifiers":[
        {
            "category":"Professional",
            "subcategory":"Detective & Security Services",
            "type":"Services"
        }
    ],
    "sg:phone":"+61 2 6962 4925",
    "sg:postcode":"2680",
    "sg:province":"NSW",
    "sg:tags":[
        "guard",
        "patrol"
    ],
    "wof:name":"Griffith Security Services",
    "wof:placetype":"venue"
},
  "geometry": {"coordinates":[146.05032299999999,-34.28944],"type":"Point"}
}