{
  "type": "Feature",
  "properties": {
    "iso:country":"AU",
    "sg:address":"34 Wallis St",
    "sg:city":"East Maitland",
    "sg:classifiers":[
        {
            "category":"Building & Trades",
            "subcategory":"Construction",
            "type":"Services"
        }
    ],
    "sg:phone":"+61 417 637 273",
    "sg:postcode":"2323",
    "sg:province":"NSW",
    "sg:tags":[
        "contractor"
    ],
    "wof:name":"McArthur Garry",
    "wof:placetype":"venue"
},
  "geometry": {"coordinates":[151.57850647000001,-32.7545013428],"type":"Point"}
}