{
  "type": "Feature",
  "properties": {
    "iso:country":"AU",
    "sg:address":"Lithgow St",
    "sg:city":"Abbotsford",
    "sg:classifiers":[
        {
            "category":"Education",
            "subcategory":"School",
            "type":"Public Place"
        }
    ],
    "sg:phone":"+61 3 9428 5977",
    "sg:postcode":"3067",
    "sg:province":"VIC",
    "sg:tags":[
        "state",
        "except",
        "nsw"
    ],
    "wof:name":"Abbotsford Primary",
    "wof:placetype":"venue"
},
  "geometry": {"coordinates":[144.998580933,-37.8088989258],"type":"Point"}
}