{
  "type": "Feature",
  "properties": {
    "addr:full":"Cnr Clarke Crs & Joondalup Drv Joondalup WA 6027",
    "addr:postcode":"6027",
    "addr:street":"Cnr Clarke Crs & Joondalup Drv",
    "iso:country":"AU",
    "sg:address":"Cnr Clarke Crs & Joondalup Drv",
    "sg:city":"Joondalup",
    "sg:classifiers":[
        {
            "category":"Shopping",
            "subcategory":"Computers & Home Electronics",
            "type":"Retail Goods"
        }
    ],
    "sg:phone":"+61 8 9301 1366",
    "sg:postcode":"6027",
    "sg:province":"WA",
    "sg:tags":[
        "equipment",
        "part",
        "electronic"
    ],
    "wof:name":"Dick Smith Electronics",
    "wof:placetype":"venue"
},
  "geometry": {"coordinates":[115.76660156200001,-31.7513828278],"type":"Point"}
}