{
  "type": "Feature",
  "properties": {
    "addr:full":"2a Gothic Ave Stonyfell SA 5066",
    "addr:housenumber":"2a",
    "addr:postcode":"5066",
    "addr:street":"Gothic Ave",
    "iso:country":"AU",
    "sg:address":"2a Gothic Ave",
    "sg:city":"Stonyfell",
    "sg:classifiers":[
        {
            "category":"Home & Garden",
            "subcategory":"Building Materials",
            "type":"Retail Goods"
        }
    ],
    "sg:phone":"+61 403 609 086",
    "sg:postcode":"5066",
    "sg:province":"SA",
    "sg:tags":[
        "lawn",
        "cutting",
        "maintenance"
    ],
    "wof:name":"F.J.C",
    "wof:placetype":"venue"
},
  "geometry": {"coordinates":[138.67572021500001,-34.9315490723],"type":"Point"}
}