{
  "type": "Feature",
  "properties": {
    "iso:country":"AU",
    "sg:address":"100 Upper Natone Rd",
    "sg:city":"Natone",
    "sg:classifiers":[
        {
            "category":"Education",
            "subcategory":"School",
            "type":"Public Place"
        }
    ],
    "sg:phone":"+61 3 6436 2166",
    "sg:postcode":"7321",
    "sg:province":"TAS",
    "sg:tags":[
        "state",
        "except",
        "nsw"
    ],
    "wof:name":"Natone Primary School",
    "wof:placetype":"venue"
},
  "geometry": {"coordinates":[145.92279099999999,-41.171238],"type":"Point"}
}