{
  "type": "Feature",
  "properties": {
    "addr:full":"U8/ 74 Malverton Drv Hallam VIC 3803",
    "addr:postcode":"3803",
    "addr:street":"U8 / 74 Malverton Drv",
    "iso:country":"AU",
    "sg:address":"U8/ 74 Malverton Drv",
    "sg:city":"Hallam",
    "sg:classifiers":[
        {
            "category":"Building & Trades",
            "subcategory":"Construction",
            "type":"Services"
        }
    ],
    "sg:phone":"+61 418 101 216",
    "sg:postcode":"3803",
    "sg:province":"VIC",
    "sg:tags":[
        "ceiling"
    ],
    "wof:name":"Construct Ceilings Pty Ltd",
    "wof:placetype":"venue"
},
  "geometry": {"coordinates":[145.27424621599999,-38.0120124817],"type":"Point"}
}