{
  "type": "Feature",
  "properties": {
    "addr:full":"92 Charman Rd Mentone VIC 3194",
    "addr:housenumber":"92",
    "addr:postcode":"3194",
    "addr:street":"Charman Rd",
    "iso:country":"AU",
    "sg:address":"92 Charman Rd",
    "sg:city":"Mentone",
    "sg:classifiers":[
        {
            "category":"Professional",
            "subcategory":"Accounting & Tax Preparation",
            "type":"Services"
        }
    ],
    "sg:phone":"+61 3 9583 4316",
    "sg:postcode":"3194",
    "sg:province":"VIC",
    "sg:tags":[
        "accountant",
        "auditor"
    ],
    "wof:name":"Brendan Buck",
    "wof:placetype":"venue"
},
  "geometry": {"coordinates":[145.05325317399999,-37.9794807434],"type":"Point"}
}