{
  "type": "Feature",
  "properties": {
    "addr:full":"301- 305 Spring St Reservoir VIC 3073",
    "addr:housenumber":"301 305",
    "addr:postcode":"3073",
    "addr:street":"Spring St",
    "iso:country":"AU",
    "sg:address":"301- 305 Spring St",
    "sg:city":"Reservoir",
    "sg:classifiers":[
        {
            "category":"Banks & Credit Unions",
            "subcategory":"Bank",
            "type":"Services"
        }
    ],
    "sg:phone":"+61 13 20 32",
    "sg:postcode":"3073",
    "sg:province":"VIC",
    "wof:name":"Westpac",
    "wof:placetype":"venue"
},
  "geometry": {"coordinates":[145.007446289,-37.7145614624],"type":"Point"}
}