{
  "type": "Feature",
  "properties": {
    "addr:full":"303 Oxley Ave Margate QLD 4019",
    "addr:housenumber":"303",
    "addr:postcode":"4019",
    "addr:street":"Oxley Ave",
    "iso:country":"AU",
    "sg:address":"303 Oxley Ave",
    "sg:city":"Margate",
    "sg:classifiers":[
        {
            "category":"Health Services",
            "subcategory":"Doctor",
            "type":"Services"
        }
    ],
    "sg:phone":"+61 7 3262 2077",
    "sg:postcode":"4019",
    "sg:province":"QLD",
    "sg:tags":[
        "medical",
        "practitioner"
    ],
    "wof:name":"English Kevin P Dr",
    "wof:placetype":"venue"
},
  "geometry": {"coordinates":[153.107055664,-27.2420711517],"type":"Point"}
}