{
  "type": "Feature",
  "properties": {
    "addr:full":"Suite 20, Kingston Trade Cntr, 479 Warrigal Rd Moorabbin VIC 3189",
    "addr:housenumber":"479",
    "addr:postcode":"3189",
    "addr:street":"Warrigal Rd",
    "iso:country":"AU",
    "sg:address":"Suite 20, Kingston Trade Cntr, 479 Warrigal Rd",
    "sg:city":"Moorabbin",
    "sg:classifiers":[
        {
            "category":"Communications",
            "subcategory":"Film & Video Production",
            "type":"Services"
        }
    ],
    "sg:phone":"+61 1800 802 822",
    "sg:postcode":"3189",
    "sg:province":"VIC",
    "sg:tags":[
        "messaging",
        "voice"
    ],
    "wof:name":"M2 Technology Pty Ltd",
    "wof:placetype":"venue"
},
  "geometry": {"coordinates":[145.078216553,-37.9447822571],"type":"Point"}
}