{
  "type": "Feature",
  "properties": {
    "addr:full":"PO Box 199 Innisfail QLD 4860",
    "addr:postcode":"4860",
    "iso:country":"AU",
    "sg:address":"PO Box 199",
    "sg:city":"Innisfail",
    "sg:classifiers":[
        {
            "category":"Utilities",
            "subcategory":"Cable",
            "type":"Services"
        }
    ],
    "sg:phone":"+61 7 4061 1118",
    "sg:postcode":"4860",
    "sg:province":"QLD",
    "sg:tags":[
        "agricultural",
        "aerial"
    ],
    "wof:name":"Heliservices Queensland Pty Ltd",
    "wof:placetype":"venue"
},
  "geometry": {"coordinates":[146.028244019,-17.5247402191],"type":"Point"}
}