{
  "type": "Feature",
  "properties": {
    "iso:country":"AU",
    "sg:address":"PO Box 270",
    "sg:city":"Quakers Hill",
    "sg:classifiers":[
        {
            "category":"Structure",
            "subcategory":"Office Building",
            "type":"Public Place"
        }
    ],
    "sg:phone":"+61 2 9853 3282",
    "sg:postcode":"2763",
    "sg:province":"NSW",
    "sg:tags":[
        "slater",
        "tiler",
        "roof"
    ],
    "wof:name":"Master Tilers Slaters & Shinglers",
    "wof:placetype":"venue"
},
  "geometry": {"coordinates":[150.88661193900001,-33.7264213562],"type":"Point"}
}