{
  "type": "Feature",
  "properties": {
    "addr:full":"422 Old Bundarra Rd Inverell NSW 2360",
    "addr:housenumber":"422",
    "addr:postcode":"2360",
    "addr:street":"Old Bundarra Rd",
    "iso:country":"AU",
    "sg:address":"422 Old Bundarra Rd",
    "sg:city":"Inverell",
    "sg:classifiers":[
        {
            "category":"Building & Trades",
            "subcategory":"Construction",
            "type":"Services"
        }
    ],
    "sg:phone":"+61 439 706 538",
    "sg:postcode":"2360",
    "sg:province":"NSW",
    "sg:tags":[
        "earth",
        "excavating",
        "moving",
        "contractor"
    ],
    "wof:name":"Bolchs Bobcat & Rural Contracting",
    "wof:placetype":"venue"
},
  "geometry": {"coordinates":[151.092697144,-29.812746048],"type":"Point"}
}