{
  "type": "Feature",
  "properties": {
    "iso:country":"AU",
    "sg:address":"745 Gilbert Rd",
    "sg:city":"Reservoir",
    "sg:classifiers":[
        {
            "category":"Health Services",
            "subcategory":"Health Practitioner",
            "type":"Services"
        }
    ],
    "sg:phone":"+61 3 9470 6144",
    "sg:postcode":"3073",
    "sg:province":"VIC",
    "sg:tags":[
        "physiotherapist"
    ],
    "wof:name":"Gilbert Rd Physiotherapy & Acupuncture Centre",
    "wof:placetype":"venue"
},
  "geometry": {"coordinates":[144.992843628,-37.7203102112],"type":"Point"}
}