{
  "type": "Feature",
  "properties": {
    "addr:full":"12 Franklin La Joondalup WA 6027",
    "addr:housenumber":"12",
    "addr:postcode":"6027",
    "addr:street":"Franklin La",
    "iso:country":"AU",
    "sg:address":"12 Franklin La",
    "sg:city":"Joondalup",
    "sg:classifiers":[
        {
            "category":"Retail",
            "subcategory":"Driving School",
            "type":"Services"
        }
    ],
    "sg:phone":"+61 8 9272 3311",
    "sg:postcode":"6027",
    "sg:province":"WA",
    "wof:name":"Alert Motorcycle School",
    "wof:placetype":"venue"
},
  "geometry": {"coordinates":[115.76283264200001,-31.7420730591],"type":"Point"}
}