{
  "type": "Feature",
  "properties": {
    "addr:full":"23 Bank St Molong NSW 2866",
    "addr:housenumber":"23",
    "addr:postcode":"2866",
    "addr:street":"Bank St",
    "iso:country":"AU",
    "sg:address":"23 Bank St",
    "sg:city":"Molong",
    "sg:classifiers":[
        {
            "category":"Personal",
            "subcategory":"Beauty Salon",
            "type":"Services"
        }
    ],
    "sg:phone":"+61 2 6366 8400",
    "sg:postcode":"2866",
    "sg:province":"NSW",
    "sg:tags":[
        "hairdresser"
    ],
    "wof:name":"Rumour Has It Hair Studio",
    "wof:placetype":"venue"
},
  "geometry": {"coordinates":[148.86897300000001,-33.092091],"type":"Point"}
}