{
  "type": "Feature",
  "properties": {
    "addr:full":"PO Box 6246 Halifax St Adelaide SA 5001",
    "addr:postcode":"5001",
    "addr:street":"St",
    "iso:country":"AU",
    "sg:address":"PO Box 6246 Halifax St",
    "sg:city":"Adelaide",
    "sg:classifiers":[
        {
            "category":"Farming",
            "subcategory":"Fish & Marine Products",
            "type":"Manufacturing & Wholesale Goods"
        }
    ],
    "sg:phone":"+61 8 8443 3644",
    "sg:postcode":"5001",
    "sg:province":"SA",
    "sg:tags":[
        "organic"
    ],
    "wof:name":"Organic Products Distributor",
    "wof:placetype":"venue"
},
  "geometry": {"coordinates":[138.599731445,-34.9257698059],"type":"Point"}
}