{
  "type": "Feature",
  "properties": {
    "iso:country":"AU",
    "sg:address":"18 Griffiths Rd",
    "sg:city":"Plympton Park",
    "sg:classifiers":[
        {
            "category":"Professional",
            "subcategory":"Engineering",
            "type":"Services"
        }
    ],
    "sg:phone":"+61 417 893 821",
    "sg:postcode":"5038",
    "sg:province":"SA",
    "sg:tags":[
        "engineer"
    ],
    "wof:name":"ESM Services",
    "wof:placetype":"venue"
},
  "geometry": {"coordinates":[138.549560547,-34.9713554382],"type":"Point"}
}