{
  "type": "Feature",
  "properties": {
    "addr:full":"110 Longueville Rd Lane Cove NSW 2066",
    "addr:housenumber":"110",
    "addr:postcode":"2066",
    "addr:street":"Longueville Rd",
    "iso:country":"AU",
    "sg:address":"110 Longueville Rd",
    "sg:city":"Lane Cove",
    "sg:classifiers":[
        {
            "category":"Fast Food",
            "type":"Food & Drink"
        }
    ],
    "sg:phone":"+61 2 9428 2922",
    "sg:postcode":"2066",
    "sg:province":"NSW",
    "sg:tags":[
        "away",
        "take"
    ],
    "wof:name":"Curry Lane",
    "wof:placetype":"venue"
},
  "geometry": {"coordinates":[151.170043945,-33.8142433167],"type":"Point"}
}