{
  "type": "Feature",
  "properties": {
    "addr:full":"shop 10 Harrington Sq Altona VIC 3018",
    "addr:housenumber":"shop 10",
    "addr:postcode":"3018",
    "addr:street":"Harrington Sq",
    "iso:country":"AU",
    "sg:address":"shop 10",
    "sg:city":"Harrington Sq Altona",
    "sg:classifiers":[
        {
            "category":"Wholesale",
            "subcategory":"Medical Equipment & Supplies",
            "type":"Manufacturing & Wholesale Goods"
        }
    ],
    "sg:phone":"+61 1300 787 353",
    "sg:postcode":"3018",
    "sg:province":"VIC",
    "sg:tags":[
        "aids",
        "hearing"
    ],
    "wof:name":"Audiology Ultra",
    "wof:placetype":"venue"
},
  "geometry": {"coordinates":[144.81361389200001,-37.8644828796],"type":"Point"}
}