{
  "type": "Feature",
  "properties": {
    "iso:country":"AU",
    "sg:address":"Suite 1, 43 Darling Street East",
    "sg:city":"Ipswich",
    "sg:classifiers":[
        {
            "category":"Professional",
            "subcategory":"Accounting & Tax Preparation",
            "type":"Services"
        }
    ],
    "sg:phone":"+61 7 3281 2422",
    "sg:postcode":"4305",
    "sg:province":"QLD",
    "sg:tags":[
        "consultant",
        "taxation"
    ],
    "wof:name":"West Moreton Accounting & Taxation Services",
    "wof:placetype":"venue"
},
  "geometry": {"coordinates":[152.76129150400001,-27.6136989594],"type":"Point"}
}