{
  "type": "Feature",
  "properties": {
    "iso:country":"AU",
    "sg:address":"10 Dorset St",
    "sg:city":"Lonsdale",
    "sg:classifiers":[
        {
            "category":"Building & Trades",
            "subcategory":"Plumbing",
            "type":"Services"
        }
    ],
    "sg:phone":"+61 8 8382 3834",
    "sg:postcode":"5160",
    "sg:province":"SA",
    "sg:tags":[
        "plumber",
        "gasfitters"
    ],
    "wof:name":"Tischendorf N",
    "wof:placetype":"venue"
},
  "geometry": {"coordinates":[138.50328064000001,-35.1151046753],"type":"Point"}
}