{
  "type": "Feature",
  "properties": {
    "addr:full":"157 Shute Harbour Rd Cannonvale QLD 4802",
    "addr:housenumber":"157",
    "addr:postcode":"4802",
    "addr:street":"Shute Harbour Rd",
    "iso:country":"AU",
    "sg:address":"157 Shute Harbour Rd",
    "sg:city":"Cannonvale",
    "sg:classifiers":[
        {
            "category":"Professional",
            "subcategory":"Computer Services",
            "type":"Services"
        }
    ],
    "sg:phone":"+61 7 4948 2788",
    "sg:postcode":"4802",
    "sg:province":"QLD",
    "sg:tags":[
        "repairs",
        "upgrade",
        "equipment"
    ],
    "wof:name":"Cartridge World Whitsunday",
    "wof:placetype":"venue"
},
  "geometry": {"coordinates":[148.70819091800001,-20.2715625763],"type":"Point"}
}