{
  "type": "Feature",
  "properties": {
    "addr:full":"98 Kembla St Wollongong NSW 2500",
    "addr:housenumber":"98",
    "addr:postcode":"2500",
    "addr:street":"Kembla St",
    "iso:country":"AU",
    "sg:address":"98 Kembla St",
    "sg:city":"Wollongong",
    "sg:classifiers":[
        {
            "category":"Professional",
            "subcategory":"Accounting & Tax Preparation",
            "type":"Services"
        }
    ],
    "sg:phone":"+61 2 4229 6477",
    "sg:postcode":"2500",
    "sg:province":"NSW",
    "sg:tags":[
        "accountant",
        "auditor"
    ],
    "wof:name":"Daley & Co",
    "wof:placetype":"venue"
},
  "geometry": {"coordinates":[150.89672899999999,-34.428013],"type":"Point"}
}