{
  "type": "Feature",
  "properties": {
    "addr:full":"50 Kallioota St Greenbank QLD 4124",
    "addr:housenumber":"50",
    "addr:postcode":"4124",
    "addr:street":"Kallioota St",
    "iso:country":"AU",
    "sg:address":"50 Kallioota St",
    "sg:city":"Greenbank",
    "sg:classifiers":[
        {
            "category":"Home & Garden",
            "subcategory":"Household Appliances",
            "type":"Retail Goods"
        }
    ],
    "sg:phone":"+61 413 750 092",
    "sg:postcode":"4124",
    "sg:province":"QLD",
    "sg:tags":[
        "equipment",
        "gas"
    ],
    "wof:name":"H S Gas Services",
    "wof:placetype":"venue"
},
  "geometry": {"coordinates":[153.01498413100001,-27.7049846649],"type":"Point"}
}