{
  "type": "Feature",
  "properties": {
    "addr:full":"14 Len Shield St Mackay QLD 4740",
    "addr:housenumber":"14",
    "addr:postcode":"4740",
    "addr:street":"Len Shield St",
    "iso:country":"AU",
    "sg:address":"14 Len Shield St",
    "sg:city":"Mackay",
    "sg:classifiers":[
        {
            "category":"Real Estate",
            "subcategory":"Real Estate Agent",
            "type":"Services"
        }
    ],
    "sg:phone":"+61 7 4952 6555",
    "sg:postcode":"4740",
    "sg:province":"QLD",
    "sg:tags":[
        "handyman's",
        "equipment",
        "hire",
        "builders",
        "contractor"
    ],
    "wof:name":"Wreckair",
    "wof:placetype":"venue"
},
  "geometry": {"coordinates":[149.16554300000001,-21.177853],"type":"Point"}
}