{
  "type": "Feature",
  "properties": {
    "iso:country":"AU",
    "sg:address":"8 Dimond Ave",
    "sg:city":"Kanahooka",
    "sg:classifiers":[
        {
            "category":"Commercial Area",
            "type":"Public Place"
        }
    ],
    "sg:phone":"+61 412 450 651",
    "sg:postcode":"2530",
    "sg:province":"NSW",
    "sg:tags":[
        "heavy",
        "carrier"
    ],
    "wof:name":"Leffley Couriers",
    "wof:placetype":"venue"
},
  "geometry": {"coordinates":[150.80914306599999,-34.4932136536],"type":"Point"}
}