{
  "type": "Feature",
  "properties": {
    "addr:full":"Thames Pl Seven Hills NSW 2147",
    "addr:postcode":"2147",
    "iso:country":"AU",
    "sg:address":"Thames Pl",
    "sg:city":"Seven Hills",
    "sg:classifiers":[
        {
            "category":"Education",
            "subcategory":"University",
            "type":"Public Place"
        }
    ],
    "sg:phone":"+61 412 412 007",
    "sg:postcode":"2147",
    "sg:province":"NSW",
    "sg:tags":[
        "educational",
        "organisation",
        "cultural"
    ],
    "wof:name":"ASCE Camping",
    "wof:placetype":"venue"
},
  "geometry": {"coordinates":[150.926544189,-33.786151886],"type":"Point"}
}