{
  "type": "Feature",
  "properties": {
    "iso:country":"AU",
    "sg:address":"Suite 16 354 Church St",
    "sg:city":"Parramatta",
    "sg:classifiers":[
        {
            "category":"Professional",
            "subcategory":"Detective & Security Services",
            "type":"Services"
        }
    ],
    "sg:phone":"+61 2 9890 1255",
    "sg:postcode":"2150",
    "sg:province":"NSW",
    "sg:tags":[
        "investigator"
    ],
    "wof:name":"Claims Investigation & Assessment (Australia) Pty Ltd",
    "wof:placetype":"venue"
},
  "geometry": {"coordinates":[151.005325317,-33.8096313477],"type":"Point"}
}