{
  "type": "Feature",
  "properties": {
    "addr:full":"17 Shenton Rd Claremont WA 6010",
    "addr:housenumber":"17",
    "addr:postcode":"6010",
    "addr:street":"Shenton Rd",
    "iso:country":"AU",
    "sg:address":"17 Shenton Rd",
    "sg:city":"Claremont",
    "sg:classifiers":[
        {
            "category":"Building & Trades",
            "subcategory":"Construction",
            "type":"Services"
        }
    ],
    "sg:phone":"+61 8 9385 2388",
    "sg:postcode":"6010",
    "sg:province":"WA",
    "sg:tags":[
        "contractor"
    ],
    "wof:name":"Award Homes",
    "wof:placetype":"venue"
},
  "geometry": {"coordinates":[115.77871704099999,-31.9802742004],"type":"Point"}
}