{
  "type": "Feature",
  "properties": {
    "addr:full":"1/ 78 Glendenning Rd Glendenning NSW 2761",
    "addr:housenumber":"/ 78",
    "addr:postcode":"2761",
    "addr:street":"Glendenning Rd",
    "iso:country":"AU",
    "sg:address":"1/ 78 Glendenning Rd",
    "sg:city":"Glendenning",
    "sg:classifiers":[
        {
            "category":"Building & Trades",
            "subcategory":"Cleaning & Sanitation",
            "type":"Services"
        }
    ],
    "sg:phone":"+61 400 144 228",
    "sg:postcode":"2761",
    "sg:province":"NSW",
    "sg:tags":[
        "cleaner",
        "repairer",
        "roof"
    ],
    "wof:name":"All Seasons Roof Restoration",
    "wof:placetype":"venue"
},
  "geometry": {"coordinates":[150.85316499999999,-33.749332],"type":"Point"}
}