{
  "type": "Feature",
  "properties": {
    "iso:country":"AU",
    "sg:address":"Fcty 7, 50 Camp Rd",
    "sg:city":"Campbellfield",
    "sg:classifiers":[
        {
            "category":"Communications",
            "type":"Services"
        }
    ],
    "sg:phone":"+61 3 9359 5345",
    "sg:postcode":"3061",
    "sg:province":"VIC",
    "sg:tags":[
        "antenna"
    ],
    "wof:name":"Servicetech Australia Pty Ltd",
    "wof:placetype":"venue"
},
  "geometry": {"coordinates":[144.95460510300001,-37.689037323],"type":"Point"}
}