{
  "type": "Feature",
  "properties": {
    "addr:full":"14 Joseph St Sale VIC 3850",
    "addr:housenumber":"14",
    "addr:postcode":"3850",
    "addr:street":"Joseph St",
    "iso:country":"AU",
    "sg:address":"14 Joseph St",
    "sg:city":"Sale",
    "sg:classifiers":[
        {
            "category":"Professional",
            "subcategory":"Testing Lab",
            "type":"Services"
        }
    ],
    "sg:phone":"+61 3 5143 0555",
    "sg:postcode":"3850",
    "sg:province":"VIC",
    "sg:tags":[
        "inspection"
    ],
    "wof:name":"Electrical Inspections Australia",
    "wof:placetype":"venue"
},
  "geometry": {"coordinates":[147.09007263199999,-38.1117630005],"type":"Point"}
}