{
  "type": "Feature",
  "properties": {
    "iso:country":"AU",
    "sg:address":"8 James St",
    "sg:city":"Fremantle",
    "sg:classifiers":[
        {
            "category":"Professional",
            "subcategory":"Art Services",
            "type":"Services"
        }
    ],
    "sg:phone":"+61 8 9335 2500",
    "sg:postcode":"6160",
    "sg:province":"WA",
    "sg:tags":[
        "picture",
        "frame",
        "framing"
    ],
    "wof:name":"Images Art Gallery",
    "wof:placetype":"venue"
},
  "geometry": {"coordinates":[115.752708435,-32.0467948914],"type":"Point"}
}