{
  "type": "Feature",
  "properties": {
    "iso:country":"AU",
    "sg:address":"106 Lyons Rd",
    "sg:city":"Drummoyne",
    "sg:classifiers":[
        {
            "category":"Shopping",
            "subcategory":"Clothing, Apparel, & Fashions",
            "type":"Retail Goods"
        }
    ],
    "sg:phone":"+61 2 9181 1992",
    "sg:postcode":"2047",
    "sg:province":"NSW",
    "sg:tags":[
        "lady",
        "wear"
    ],
    "wof:name":"Gypsy Doll",
    "wof:placetype":"venue"
},
  "geometry": {"coordinates":[151.14961199999999,-33.854126],"type":"Point"}
}