{
  "type": "Feature",
  "properties": {
    "iso:country":"AU",
    "sg:address":"Cnr Tennyson Ave & Eastern Rd",
    "sg:city":"Turramurra",
    "sg:classifiers":[
        {
            "category":"Health Services",
            "subcategory":"Doctor",
            "type":"Services"
        }
    ],
    "sg:phone":"+61 2 9489 0291",
    "sg:postcode":"2074",
    "sg:province":"NSW",
    "sg:tags":[
        "medical",
        "practitioner"
    ],
    "wof:name":"Ludowici D Haskins Jan Sheehan A",
    "wof:placetype":"venue"
},
  "geometry": {"coordinates":[151.134567261,-33.7209510803],"type":"Point"}
}