{
  "type": "Feature",
  "properties": {
    "addr:full":"8 Lalor St Port Melbourne VIC 3207",
    "addr:housenumber":"8",
    "addr:postcode":"3207",
    "addr:street":"Lalor St",
    "iso:country":"AU",
    "sg:address":"8 Lalor St",
    "sg:city":"Port Melbourne",
    "sg:classifiers":[
        {
            "category":"Home & Garden",
            "subcategory":"Garden Supply",
            "type":"Retail Goods"
        }
    ],
    "sg:phone":"+61 3 9646 7142",
    "sg:postcode":"3207",
    "sg:province":"VIC",
    "sg:tags":[
        "equipment"
    ],
    "wof:name":"Sandangel Pty Ltd",
    "wof:placetype":"venue"
},
  "geometry": {"coordinates":[144.94215399999999,-37.838005],"type":"Point"}
}