{
  "type": "Feature",
  "properties": {
    "iso:country":"AU",
    "sg:address":"22 Sangster Pl",
    "sg:city":"Wanniassa",
    "sg:classifiers":[
        {
            "category":"Personal",
            "subcategory":"Beauty Salon",
            "type":"Services"
        }
    ],
    "sg:phone":"+61 2 6296 2388",
    "sg:postcode":"2903",
    "sg:province":"ACT",
    "sg:tags":[
        "hairdresser"
    ],
    "wof:name":"Deboniqu\ufffd Hair Design",
    "wof:placetype":"venue"
},
  "geometry": {"coordinates":[149.086303711,-35.3915672302],"type":"Point"}
}