{
  "type": "Feature",
  "properties": {
    "addr:full":"29 Lancaster Drv Lismore NSW 2480",
    "addr:housenumber":"29",
    "addr:postcode":"2480",
    "addr:street":"Lancaster Drv",
    "iso:country":"AU",
    "sg:address":"29 Lancaster Drv",
    "sg:city":"Lismore",
    "sg:classifiers":[
        {
            "category":"Professional",
            "type":"Services"
        }
    ],
    "sg:phone":"+61 2 6624 2669",
    "sg:postcode":"2480",
    "sg:province":"NSW",
    "sg:tags":[
        "courier"
    ],
    "wof:name":"Fastway Couriers",
    "wof:placetype":"venue"
},
  "geometry": {"coordinates":[153.348052978,-28.8184928894],"type":"Point"}
}