{
  "type": "Feature",
  "properties": {
    "addr:full":"PO Box 69 Pooraka SA 5095",
    "addr:postcode":"5095",
    "iso:country":"AU",
    "sg:address":"PO Box 69",
    "sg:city":"Pooraka",
    "sg:classifiers":[
        {
            "category":"Manufacturing",
            "subcategory":"Rubber & Plastics",
            "type":"Manufacturing & Wholesale Goods"
        }
    ],
    "sg:phone":"+61 8 8162 9001",
    "sg:postcode":"5095",
    "sg:province":"SA",
    "sg:tags":[
        "equipment",
        "card"
    ],
    "wof:name":"Mobile ID Cards",
    "wof:placetype":"venue"
},
  "geometry": {"coordinates":[138.62690734899999,-34.8242683411],"type":"Point"}
}