{
  "type": "Feature",
  "properties": {
    "addr:full":"Unit 2/ 20 Doyle Ave Unanderra NSW 2526",
    "addr:housenumber":"20",
    "addr:postcode":"2526",
    "addr:street":"Doyle Ave",
    "iso:country":"AU",
    "sg:address":"Unit 2/ 20 Doyle Ave",
    "sg:city":"Unanderra",
    "sg:classifiers":[
        {
            "category":"Building & Trades",
            "subcategory":"Construction",
            "type":"Services"
        }
    ],
    "sg:phone":"+61 2 4272 6488",
    "sg:postcode":"2526",
    "sg:province":"NSW",
    "sg:tags":[
        "welding"
    ],
    "wof:name":"DTN Welding & Hydraulics Pty Ltd",
    "wof:placetype":"venue"
},
  "geometry": {"coordinates":[150.83973693900001,-34.4658508301],"type":"Point"}
}