{
  "type": "Feature",
  "properties": {
    "addr:full":"U5/ 40 Edward St Norwood SA 5067",
    "addr:housenumber":"40",
    "addr:postcode":"5067",
    "addr:street":"U5 /;Edward St",
    "iso:country":"AU",
    "sg:address":"U5/ 40 Edward St",
    "sg:city":"Norwood",
    "sg:classifiers":[
        {
            "category":"Professional",
            "subcategory":"Art Services",
            "type":"Services"
        }
    ],
    "sg:phone":"+61 8 7120 2173",
    "sg:postcode":"5067",
    "sg:province":"SA",
    "sg:tags":[
        "graphic",
        "designer"
    ],
    "wof:name":"Perroud Digital Arts",
    "wof:placetype":"venue"
},
  "geometry": {"coordinates":[138.63444519000001,-34.9190406799],"type":"Point"}
}