{
  "type": "Feature",
  "properties": {
    "addr:full":"4 Irwin St North Parramatta NSW 2151",
    "addr:housenumber":"4",
    "addr:postcode":"2151",
    "addr:street":"Irwin St",
    "iso:country":"AU",
    "sg:address":"4 Irwin St",
    "sg:city":"North Parramatta",
    "sg:classifiers":[
        {
            "category":"Professional",
            "subcategory":"Art Services",
            "type":"Services"
        }
    ],
    "sg:phone":"+61 412 126 718",
    "sg:postcode":"2151",
    "sg:province":"NSW",
    "sg:tags":[
        "decorator",
        "painter"
    ],
    "wof:name":"Focus Expressions Painting Services",
    "wof:placetype":"venue"
},
  "geometry": {"coordinates":[151.00552368199999,-33.795211792],"type":"Point"}
}