{
  "type": "Feature",
  "properties": {
    "iso:country":"AU",
    "sg:address":"17 St Elmo Ave",
    "sg:city":"Ferntree Gully",
    "sg:classifiers":[
        {
            "category":"Personal",
            "subcategory":"Massage",
            "type":"Services"
        }
    ],
    "sg:phone":"+61 3 9758 0105",
    "sg:postcode":"3156",
    "sg:province":"VIC",
    "sg:tags":[
        "therapy"
    ],
    "wof:name":"Llewellyn John M.S.C.M.",
    "wof:placetype":"venue"
},
  "geometry": {"coordinates":[145.292526245,-37.8723258972],"type":"Point"}
}