{
  "type": "Feature",
  "properties": {
    "addr:full":"42 Main St North Rockhampton QLD 4701",
    "addr:housenumber":"42",
    "addr:postcode":"4701",
    "addr:street":"Main St North",
    "iso:country":"AU",
    "sg:address":"42 Main St",
    "sg:city":"North Rockhampton",
    "sg:classifiers":[
        {
            "category":"Retail",
            "subcategory":"Event Space",
            "type":"Services"
        }
    ],
    "sg:phone":"+61 438 334 401",
    "sg:postcode":"4701",
    "sg:province":"QLD",
    "sg:tags":[
        "function",
        "organiser"
    ],
    "wof:name":"Stylish Events & Hire",
    "wof:placetype":"venue"
},
  "geometry": {"coordinates":[150.50979614299999,-23.3573150635],"type":"Point"}
}