{
  "type": "Feature",
  "properties": {
    "addr:full":"19 Taylor St Dubbo NSW 2830",
    "addr:housenumber":"19",
    "addr:postcode":"2830",
    "addr:street":"Taylor St",
    "iso:country":"AU",
    "sg:address":"19 Taylor St",
    "sg:city":"Dubbo",
    "sg:classifiers":[
        {
            "category":"Building & Trades",
            "subcategory":"Construction",
            "type":"Services"
        }
    ],
    "sg:phone":"+61 2 6884 1634",
    "sg:postcode":"2830",
    "sg:province":"NSW",
    "sg:tags":[
        "installation",
        "air conditioning"
    ],
    "wof:name":"Anderson D N",
    "wof:placetype":"venue"
},
  "geometry": {"coordinates":[148.61555480999999,-32.2575378418],"type":"Point"}
}