{
  "type": "Feature",
  "properties": {
    "addr:full":"17/ 115 Dollis St Rocklea QLD 4106",
    "addr:housenumber":"17 / 115",
    "addr:postcode":"4106",
    "addr:street":"Dollis St",
    "iso:country":"AU",
    "sg:address":"17/ 115 Dollis St",
    "sg:city":"Rocklea",
    "sg:classifiers":[
        {
            "category":"Manufacturing",
            "subcategory":"Tools & Machinery",
            "type":"Manufacturing & Wholesale Goods"
        }
    ],
    "sg:phone":"+61 7 3277 8439",
    "sg:postcode":"4106",
    "sg:province":"QLD",
    "sg:tags":[
        "toolmaker"
    ],
    "wof:name":"Advance Engineering Pty Ltd",
    "wof:placetype":"venue"
},
  "geometry": {"coordinates":[153.024658203,-27.5571975708],"type":"Point"}
}