{
  "type": "Feature",
  "properties": {
    "addr:full":"2/ 16 Arundel St Cranbourne VIC 3977",
    "addr:housenumber":"/ 16",
    "addr:postcode":"3977",
    "addr:street":"Arundel St",
    "iso:country":"AU",
    "sg:address":"2/ 16 Arundel St",
    "sg:city":"Cranbourne",
    "sg:classifiers":[
        {
            "category":"Retail",
            "subcategory":"Auto Repair",
            "type":"Services"
        }
    ],
    "sg:phone":"+61 3 5995 1096",
    "sg:postcode":"3977",
    "sg:province":"VIC",
    "sg:tags":[
        "muffler",
        "exhaust",
        "system"
    ],
    "wof:name":"Kleenflo Exhaust",
    "wof:placetype":"venue"
},
  "geometry": {"coordinates":[145.284545898,-38.1036682129],"type":"Point"}
}