{
  "type": "Feature",
  "properties": {
    "addr:full":"Unit D3/ 2A Victoria Ave Castle Hill NSW 2154",
    "addr:housenumber":"2a",
    "addr:postcode":"2154",
    "addr:street":"Victoria Ave",
    "iso:country":"AU",
    "sg:address":"Unit D3/ 2A Victoria Ave",
    "sg:city":"Castle Hill",
    "sg:classifiers":[
        {
            "category":"Retail",
            "subcategory":"Auto Repair",
            "type":"Services"
        }
    ],
    "sg:phone":"+61 2 9634 5024",
    "sg:postcode":"2154",
    "sg:province":"NSW",
    "sg:tags":[
        "electrical"
    ],
    "wof:name":"&#039;A &#039; Class Automotives Pty Ltd",
    "wof:placetype":"venue"
},
  "geometry": {"coordinates":[150.981323242,-33.7354278564],"type":"Point"}
}