{
  "type": "Feature",
  "properties": {
    "addr:full":"PO Box 72 Floreat WA 6014",
    "addr:postcode":"6014",
    "iso:country":"AU",
    "sg:address":"PO Box 72",
    "sg:city":"Floreat",
    "sg:classifiers":[
        {
            "category":"Professional",
            "subcategory":"Secretarial Services",
            "type":"Services"
        }
    ],
    "sg:phone":"+61 8 9287 2305",
    "sg:postcode":"6014",
    "sg:province":"WA",
    "sg:tags":[
        "typing"
    ],
    "wof:name":"CV Solutions.",
    "wof:placetype":"venue"
},
  "geometry": {"coordinates":[115.795776367,-31.9442691803],"type":"Point"}
}