{
  "type": "Feature",
  "properties": {
    "addr:full":"Cnr Kularoo Drv & Trades Crt Forster NSW 2428",
    "addr:postcode":"2428",
    "addr:street":"Cnr Kularoo Drv & Trades Crt",
    "iso:country":"AU",
    "sg:address":"Cnr Kularoo Drv & Trades Crt",
    "sg:city":"Forster",
    "sg:classifiers":[
        {
            "category":"Home & Garden",
            "subcategory":"Carpets & Floor Coverings",
            "type":"Retail Goods"
        }
    ],
    "sg:phone":"+61 2 6554 8330",
    "sg:postcode":"2428",
    "sg:province":"NSW",
    "wof:name":"Don's Design Carpets (Forster-Tuncurry)",
    "wof:placetype":"venue"
},
  "geometry": {"coordinates":[152.52375793499999,-32.1967544556],"type":"Point"}
}