{
  "type": "Feature",
  "properties": {
    "addr:full":"246 Flagstone Creek Rd Helidon QLD 4344",
    "addr:housenumber":"246",
    "addr:postcode":"4344",
    "addr:street":"Flagstone Creek Rd",
    "iso:country":"AU",
    "sg:address":"246 Flagstone Creek Rd",
    "sg:city":"Helidon",
    "sg:classifiers":[
        {
            "category":"Professional",
            "subcategory":"Art Services",
            "type":"Services"
        }
    ],
    "sg:phone":"+61 7 4697 6041",
    "sg:postcode":"4344",
    "sg:province":"QLD",
    "sg:tags":[
        "decorator",
        "painter"
    ],
    "wof:name":"Brown RE & RM",
    "wof:placetype":"venue"
},
  "geometry": {"coordinates":[152.142044,-27.579723],"type":"Point"}
}