{
  "type": "Feature",
  "properties": {
    "iso:country":"AU",
    "sg:address":"64 McCoy St",
    "sg:city":"Myaree",
    "sg:classifiers":[
        {
            "category":"Retail",
            "subcategory":"Auto Repair",
            "type":"Services"
        }
    ],
    "sg:phone":"+61 8 9330 7625",
    "sg:postcode":"6154",
    "sg:province":"WA",
    "sg:tags":[
        "electrical"
    ],
    "wof:name":"Southside Auto Electrics",
    "wof:placetype":"venue"
},
  "geometry": {"coordinates":[115.817101,-32.043381],"type":"Point"}
}