{
  "type": "Feature",
  "properties": {
    "addr:full":"615 Goodwood Rd Panorama SA 5041",
    "addr:housenumber":"615",
    "addr:postcode":"5041",
    "addr:street":"Goodwood Rd",
    "iso:country":"AU",
    "sg:address":"615 Goodwood Rd",
    "sg:city":"Panorama",
    "sg:classifiers":[
        {
            "category":"Professional",
            "type":"Services"
        }
    ],
    "sg:phone":"+61 8 8275 0211",
    "sg:postcode":"5041",
    "sg:province":"SA",
    "sg:tags":[
        "packaging",
        "filling",
        "assembling"
    ],
    "sg:website":"http://www.bedfordgroup.com.au",
    "wof:name":"Bedford Packaging",
    "wof:placetype":"venue"
},
  "geometry": {"coordinates":[138.59295700000001,-34.992317],"type":"Point"}
}