{
  "type": "Feature",
  "properties": {
    "iso:country":"AU",
    "sg:address":"21 Beacon Crs",
    "sg:city":"Scarborough",
    "sg:classifiers":[
        {
            "category":"Building & Trades",
            "subcategory":"Construction",
            "type":"Services"
        }
    ],
    "sg:phone":"+61 7 3880 1806",
    "sg:postcode":"4020",
    "sg:province":"QLD",
    "sg:tags":[
        "home",
        "air conditioning"
    ],
    "wof:name":"A JDS Air Conditioning Services",
    "wof:placetype":"venue"
},
  "geometry": {"coordinates":[153.114014,-27.20532],"type":"Point"}
}