{
  "type": "Feature",
  "properties": {
    "addr:full":"177-181 Newton Rd Wetherill Park NSW 2164",
    "addr:housenumber":"177-181",
    "addr:postcode":"2164",
    "addr:street":"Newton Rd",
    "iso:country":"AU",
    "sg:address":"177-181 Newton Rd",
    "sg:city":"Wetherill Park",
    "sg:classifiers":[
        {
            "category":"Home & Garden",
            "subcategory":"Home Furnishings",
            "type":"Retail Goods"
        }
    ],
    "sg:phone":"+61 2 9609 4500",
    "sg:postcode":"2164",
    "sg:province":"NSW",
    "sg:tags":[
        "wicker",
        "cane",
        "furniture"
    ],
    "wof:name":"Islander Imports Pty Ltd",
    "wof:placetype":"venue"
},
  "geometry": {"coordinates":[150.89161682100001,-33.8389549255],"type":"Point"}
}