{
  "type": "Feature",
  "properties": {
    "iso:country":"AU",
    "sg:address":"49- 51 Montagu St",
    "sg:city":"New Norfolk",
    "sg:classifiers":[
        {
            "category":"Travel",
            "subcategory":"Hotels & Motels",
            "type":"Entertainment"
        }
    ],
    "sg:phone":"+61 3 6261 2256",
    "sg:postcode":"7140",
    "sg:province":"TAS",
    "sg:tags":[
        "accommodation"
    ],
    "wof:name":"Bush Inn",
    "wof:placetype":"venue"
},
  "geometry": {"coordinates":[147.06109599999999,-42.778931],"type":"Point"}
}