{
  "type": "Feature",
  "properties": {
    "addr:full":"42- 44 Aldenhoven Rd Lonsdale SA 5160",
    "addr:housenumber":"44",
    "addr:postcode":"5160",
    "addr:street":"Aldenhoven Rd",
    "iso:country":"AU",
    "sg:address":"42- 44 Aldenhoven Rd",
    "sg:city":"Lonsdale",
    "sg:classifiers":[
        {
            "category":"Manufacturing",
            "subcategory":"Motor Vehicles & Parts",
            "type":"Manufacturing & Wholesale Goods"
        }
    ],
    "sg:phone":"+61 8 8384 7211",
    "sg:postcode":"5160",
    "sg:province":"SA",
    "sg:tags":[
        "engine",
        "equipment",
        "diesel"
    ],
    "wof:name":"D & C Fuel Injection Pty Ltd",
    "wof:placetype":"venue"
},
  "geometry": {"coordinates":[138.49720764200001,-35.1159858704],"type":"Point"}
}