{
  "type": "Feature",
  "properties": {
    "addr:full":"308 Pitt St Sydney NSW 2000",
    "addr:housenumber":"308",
    "addr:postcode":"2000",
    "addr:street":"Pitt St",
    "iso:country":"AU",
    "sg:address":"308 Pitt St",
    "sg:city":"Sydney",
    "sg:classifiers":[
        {
            "category":"Professional",
            "subcategory":"Management & Consulting",
            "type":"Services"
        }
    ],
    "sg:phone":"+61 2 9267 4142",
    "sg:postcode":"2000",
    "sg:province":"NSW",
    "sg:tags":[
        "consultant"
    ],
    "wof:name":"Pender Gordon & Co Pty Ltd",
    "wof:placetype":"venue"
},
  "geometry": {"coordinates":[151.20811462399999,-33.8751411438],"type":"Point"}
}