{
  "type": "Feature",
  "properties": {
    "iso:country":"AU",
    "sg:address":"121 Saliors Bay Rd",
    "sg:city":"Northbridge",
    "sg:classifiers":[
        {
            "category":"Fast Food",
            "type":"Food & Drink"
        }
    ],
    "sg:phone":"+61 2 9967 4040",
    "sg:postcode":"2063",
    "sg:province":"NSW",
    "sg:tags":[
        "away",
        "take"
    ],
    "wof:name":"Northbridge Gourmet Chargrill",
    "wof:placetype":"venue"
},
  "geometry": {"coordinates":[151.20956420900001,-33.8104858398],"type":"Point"}
}