{
  "type": "Feature",
  "properties": {
    "iso:country":"AU",
    "sg:address":"40 Huon St",
    "sg:city":"Wahroonga",
    "sg:classifiers":[
        {
            "category":"Professional",
            "subcategory":"Computer Services",
            "type":"Services"
        }
    ],
    "sg:phone":"+61 2 9489 5718",
    "sg:postcode":"2076",
    "sg:province":"NSW",
    "sg:tags":[
        "consultant",
        "system"
    ],
    "wof:name":"Park Computer Consultants Pty Ltd",
    "wof:placetype":"venue"
},
  "geometry": {"coordinates":[151.13929748499999,-33.7055282593],"type":"Point"}
}