{
  "type": "Feature",
  "properties": {
    "iso:country":"AU",
    "sg:address":"Victoria St",
    "sg:city":"Hall",
    "sg:classifiers":[
        {
            "category":"Industrial Area",
            "type":"Public Place"
        }
    ],
    "sg:phone":"+61 2 6230 2060",
    "sg:postcode":"2618",
    "sg:province":"ACT",
    "sg:tags":[
        "rural",
        "shed"
    ],
    "wof:name":"Blue Frame Buildings Canberra",
    "wof:placetype":"venue"
},
  "geometry": {"coordinates":[149.069915772,-35.1702003479],"type":"Point"}
}