{
  "type": "Feature",
  "properties": {
    "iso:country":"AU",
    "sg:address":"9 Roslyn St",
    "sg:city":"Springfield",
    "sg:classifiers":[
        {
            "category":"Building & Trades",
            "subcategory":"Construction",
            "type":"Services"
        }
    ],
    "sg:phone":"+61 2 4324 3327",
    "sg:postcode":"2250",
    "sg:province":"NSW",
    "sg:tags":[
        "insulation",
        "contractor"
    ],
    "wof:name":"Insulation Australia",
    "wof:placetype":"venue"
},
  "geometry": {"coordinates":[151.36720275900001,-33.4272041321],"type":"Point"}
}