{
  "type": "Feature",
  "properties": {
    "iso:country":"AU",
    "sg:address":"88 Gawler Pl",
    "sg:city":"Adelaide",
    "sg:classifiers":[
        {
            "category":"Cafe",
            "type":"Food & Drink"
        }
    ],
    "sg:phone":"+61 8 8224 0882",
    "sg:postcode":"5000",
    "sg:province":"SA",
    "wof:name":"Salad Box",
    "wof:placetype":"venue"
},
  "geometry": {"coordinates":[138.60214233400001,-34.924446106],"type":"Point"}
}