{
  "type": "Feature",
  "properties": {
    "addr:full":"PO Box 1015 Devonport TAS 7310",
    "addr:postcode":"7310",
    "iso:country":"AU",
    "sg:address":"PO Box 1015",
    "sg:city":"Devonport",
    "sg:classifiers":[
        {
            "category":"Building & Trades",
            "subcategory":"Construction",
            "type":"Services"
        }
    ],
    "sg:phone":"+61 3 6424 9600",
    "sg:postcode":"7310",
    "sg:province":"TAS",
    "sg:tags":[
        "contractor"
    ],
    "wof:name":"Jireh Building",
    "wof:placetype":"venue"
},
  "geometry": {"coordinates":[146.36340332,-41.193775177],"type":"Point"}
}