{
  "type": "Feature",
  "properties": {
    "addr:full":"PO Box 995 Kent Town SA 5067",
    "addr:postcode":"5067",
    "iso:country":"AU",
    "sg:address":"PO Box 995",
    "sg:city":"Kent Town",
    "sg:classifiers":[
        {
            "category":"Building & Trades",
            "subcategory":"Construction",
            "type":"Services"
        }
    ],
    "sg:phone":"+61 403 349 006",
    "sg:postcode":"5067",
    "sg:province":"SA",
    "sg:tags":[
        "contractor"
    ],
    "wof:name":"Mark DiMauro",
    "wof:placetype":"venue"
},
  "geometry": {"coordinates":[138.617584228,-34.9208984375],"type":"Point"}
}