{
  "type": "Feature",
  "properties": {
    "addr:full":"376 Johnston St Abbotsford VIC 3067",
    "addr:housenumber":"376",
    "addr:postcode":"3067",
    "addr:street":"Johnston St",
    "iso:country":"AU",
    "sg:address":"376 Johnston St",
    "sg:city":"Abbotsford",
    "sg:classifiers":[
        {
            "category":"Professional",
            "subcategory":"Computer Services",
            "type":"Services"
        }
    ],
    "sg:phone":"+61 3 9419 4477",
    "sg:postcode":"3067",
    "sg:province":"VIC",
    "sg:tags":[
        "package",
        "software"
    ],
    "wof:name":"Tercel",
    "wof:placetype":"venue"
},
  "geometry": {"coordinates":[144.99819946299999,-37.8002052307],"type":"Point"}
}