{
  "type": "Feature",
  "properties": {
    "addr:full":"108 Ridge Rd Engadine NSW 2233",
    "addr:housenumber":"108",
    "addr:postcode":"2233",
    "addr:street":"Ridge Rd",
    "iso:country":"AU",
    "sg:address":"108 Ridge Rd",
    "sg:city":"Engadine",
    "sg:classifiers":[
        {
            "category":"Manufacturing",
            "subcategory":"Motor Vehicles & Parts",
            "type":"Manufacturing & Wholesale Goods"
        }
    ],
    "sg:phone":"+61 2 9520 0022",
    "sg:postcode":"2233",
    "sg:province":"NSW",
    "sg:tags":[
        "engine",
        "equipment",
        "diesel"
    ],
    "wof:name":"Max Toohey",
    "wof:placetype":"venue"
},
  "geometry": {"coordinates":[151.00080871599999,-34.0539550781],"type":"Point"}
}