{
  "type": "Feature",
  "properties": {
    "addr:full":"10 Thomas St Unley SA 5061",
    "addr:housenumber":"10",
    "addr:postcode":"5061",
    "addr:street":"Thomas St",
    "iso:country":"AU",
    "sg:address":"10 Thomas St",
    "sg:city":"Unley",
    "sg:classifiers":[
        {
            "category":"Education",
            "subcategory":"University",
            "type":"Public Place"
        }
    ],
    "sg:phone":"+61 8 8373 5592",
    "sg:postcode":"5061",
    "sg:province":"SA",
    "sg:tags":[
        "educational",
        "organisation",
        "cultural"
    ],
    "wof:name":"Multi-Cultural Youth & Support Education Services Ltd",
    "wof:placetype":"venue"
},
  "geometry": {"coordinates":[138.60618591299999,-34.9520492554],"type":"Point"}
}