{
  "type": "Feature",
  "properties": {
    "addr:full":"3/ 9 Woodbine Crt Wantirna South VIC 3152",
    "addr:housenumber":"/ 9",
    "addr:postcode":"3152",
    "addr:street":"Woodbine Crt",
    "iso:country":"AU",
    "sg:address":"3/ 9 Woodbine Crt",
    "sg:city":"Wantirna South",
    "sg:classifiers":[
        {
            "category":"Retail",
            "subcategory":"Auto Repair",
            "type":"Services"
        }
    ],
    "sg:phone":"+61 3 9801 7782",
    "sg:postcode":"3152",
    "sg:province":"VIC",
    "sg:tags":[
        "automotive",
        "air conditioning"
    ],
    "wof:name":"Ace Auto Electrical Service Pty Ltd",
    "wof:placetype":"venue"
},
  "geometry": {"coordinates":[145.250366211,-37.8701210022],"type":"Point"}
}