{
  "type": "Feature",
  "properties": {
    "addr:full":"Shop 16, Springwood Plaza, Dennis Rd Springwood QLD 4127",
    "addr:housenumber":"shop 16",
    "addr:postcode":"4127",
    "addr:street":"Springwood Plaza Dennis Rd",
    "iso:country":"AU",
    "sg:address":"Shop 16, Springwood Plaza, Dennis Rd",
    "sg:city":"Springwood",
    "sg:classifiers":[
        {
            "category":"Restaurant",
            "type":"Food & Drink"
        }
    ],
    "sg:phone":"+61 7 3808 4988",
    "sg:postcode":"4127",
    "sg:province":"QLD",
    "wof:name":"Ciscos Mexican Restaurant",
    "wof:placetype":"venue"
},
  "geometry": {"coordinates":[153.13206481899999,-27.6174812317],"type":"Point"}
}