{
  "type": "Feature",
  "properties": {
    "addr:full":"6 Lenamont Crt Dunsborough WA 6281",
    "addr:housenumber":"6",
    "addr:postcode":"6281",
    "addr:street":"Lenamont Crt",
    "iso:country":"AU",
    "sg:address":"6 Lenamont Crt",
    "sg:city":"Dunsborough",
    "sg:classifiers":[
        {
            "category":"Retail",
            "subcategory":"Auto Repair",
            "type":"Services"
        }
    ],
    "sg:phone":"+61 418 196 992",
    "sg:postcode":"6281",
    "sg:province":"WA",
    "sg:tags":[
        "bus",
        "truck"
    ],
    "wof:name":"South West Diesel & Hydraulics",
    "wof:placetype":"venue"
},
  "geometry": {"coordinates":[115.1014328,-33.6217803955],"type":"Point"}
}