{
  "type": "Feature",
  "properties": {
    "addr:full":"Shop 106 , Elizabeth Shopping Centre Elizabeth SA 5112",
    "addr:housenumber":"106",
    "addr:postcode":"5112",
    "addr:street":"Elizabeth",
    "iso:country":"AU",
    "sg:address":"Shop 106",
    "sg:city":", Elizabeth Shopping Centre Elizabeth",
    "sg:classifiers":[
        {
            "category":"Manufacturing",
            "subcategory":"Food",
            "type":"Manufacturing & Wholesale Goods"
        }
    ],
    "sg:phone":"+61 439 992 242",
    "sg:postcode":"5112",
    "sg:province":"SA",
    "sg:tags":[
        "function",
        "catering"
    ],
    "wof:name":"Adelaide Yiros Catering",
    "wof:placetype":"venue"
},
  "geometry": {"coordinates":[138.668655395,-34.722530365],"type":"Point"}
}