{
  "type": "Feature",
  "properties": {
    "addr:full":"143 Herald St Cheltenham VIC 3192",
    "addr:housenumber":"143",
    "addr:postcode":"3192",
    "addr:street":"Herald St",
    "iso:country":"AU",
    "sg:address":"143 Herald St",
    "sg:city":"Cheltenham",
    "sg:classifiers":[
        {
            "category":"Building & Trades",
            "subcategory":"Construction",
            "type":"Services"
        }
    ],
    "sg:phone":"+61 3 9532 3600",
    "sg:postcode":"3192",
    "sg:province":"VIC",
    "sg:tags":[
        "tennis court",
        "repair"
    ],
    "wof:name":"Policlay Tennis Courts",
    "wof:placetype":"venue"
},
  "geometry": {"coordinates":[145.073455811,-37.9520568848],"type":"Point"}
}