{
  "type": "Feature",
  "properties": {
    "iso:country":"AU",
    "sg:address":"Morpeth St",
    "sg:city":"Harwood Island",
    "sg:classifiers":[
        {
            "category":"Education",
            "subcategory":"School",
            "type":"Public Place"
        }
    ],
    "sg:phone":"+61 2 6646 4213",
    "sg:postcode":"2465",
    "sg:province":"NSW",
    "sg:tags":[
        "state",
        "-",
        "nsw"
    ],
    "wof:name":"Harwood Island Public School",
    "wof:placetype":"venue"
},
  "geometry": {"coordinates":[153.240142822,-29.4224910736],"type":"Point"}
}