{
  "type": "Feature",
  "properties": {
    "addr:full":"Cnr McManus & Marino Sts Whitfield QLD 4870",
    "addr:postcode":"4870",
    "addr:street":"Cnr;Sts",
    "iso:country":"AU",
    "sg:address":"Cnr McManus & Marino Sts",
    "sg:city":"Whitfield",
    "sg:classifiers":[
        {
            "category":"Education",
            "subcategory":"School",
            "type":"Public Place"
        }
    ],
    "sg:phone":"+61 7 4034 1755",
    "sg:postcode":"4870",
    "sg:province":"QLD",
    "sg:tags":[
        "state",
        "except",
        "nsw"
    ],
    "wof:name":"Whitfield Primary School",
    "wof:placetype":"venue"
},
  "geometry": {"coordinates":[145.72874450699999,-16.9039344788],"type":"Point"}
}