{
  "type": "Feature",
  "properties": {
    "addr:full":"Shop 4/ 22-30 Brighton St Bundeena NSW 2230",
    "addr:housenumber":"shop 4 / 22-30",
    "addr:postcode":"2230",
    "addr:street":"Brighton St",
    "iso:country":"AU",
    "sg:address":"Shop 4/ 22-30 Brighton St",
    "sg:city":"Bundeena",
    "sg:classifiers":[
        {
            "category":"Personal",
            "subcategory":"Beauty Salon",
            "type":"Services"
        }
    ],
    "sg:phone":"+61 2 9527 6887",
    "sg:postcode":"2230",
    "sg:province":"NSW",
    "sg:tags":[
        "hairdresser"
    ],
    "wof:name":"3 Wishes Boutique",
    "wof:placetype":"venue"
},
  "geometry": {"coordinates":[151.151519775,-34.0845603943],"type":"Point"}
}