{
  "type": "Feature",
  "properties": {
    "addr:full":"39 Cardigan St Stanmore NSW 2048",
    "addr:housenumber":"39",
    "addr:postcode":"2048",
    "addr:street":"Cardigan St",
    "iso:country":"AU",
    "sg:address":"39 Cardigan St",
    "sg:city":"Stanmore",
    "sg:classifiers":[
        {
            "category":"Professional",
            "subcategory":"Business Services",
            "type":"Services"
        }
    ],
    "sg:phone":"+61 2 9590 9353",
    "sg:postcode":"2048",
    "sg:province":"NSW",
    "sg:tags":[
        "management",
        "event"
    ],
    "wof:name":"Halcyon Productions",
    "wof:placetype":"venue"
},
  "geometry": {"coordinates":[151.17218,-33.889595],"type":"Point"}
}