{
  "type": "Feature",
  "properties": {
    "addr:full":"3b Junction St Young NSW 2594",
    "addr:housenumber":"3b",
    "addr:postcode":"2594",
    "addr:street":"Junction St",
    "iso:country":"AU",
    "sg:address":"3b Junction St",
    "sg:city":"Young",
    "sg:classifiers":[
        {
            "category":"Health Services",
            "subcategory":"Chiropractor",
            "type":"Services"
        }
    ],
    "sg:phone":"+61 2 6382 2993",
    "sg:postcode":"2594",
    "sg:province":"NSW",
    "wof:name":"Hands On Health Young",
    "wof:placetype":"venue"
},
  "geometry": {"coordinates":[148.30198669399999,-34.3136749268],"type":"Point"}
}