{
  "type": "Feature",
  "properties": {
    "iso:country":"AU",
    "sg:address":"3 Moorooba Crs",
    "sg:city":"Nelson Bay",
    "sg:classifiers":[
        {
            "category":"Health Services",
            "subcategory":"Health Practitioner",
            "type":"Services"
        }
    ],
    "sg:phone":"+61 2 4981 0967",
    "sg:postcode":"2315",
    "sg:province":"NSW",
    "sg:tags":[
        "naturopath"
    ],
    "wof:name":"Nelson Bay Naturopathic Centre",
    "wof:placetype":"venue"
},
  "geometry": {"coordinates":[152.143311,-32.72279],"type":"Point"}
}