{
  "type": "Feature",
  "properties": {
    "addr:full":"Level 6, 781 Pacific Hwy Chatswood NSW 2067",
    "addr:housenumber":"781",
    "addr:postcode":"2067",
    "addr:street":"Pacific Hwy",
    "iso:country":"AU",
    "sg:address":"Level 6, 781 Pacific Hwy",
    "sg:city":"Chatswood",
    "sg:classifiers":[
        {
            "category":"Health Services",
            "subcategory":"Doctor",
            "type":"Services"
        }
    ],
    "sg:phone":"+61 2 9411 4464",
    "sg:postcode":"2067",
    "sg:province":"NSW",
    "sg:tags":[
        "medical",
        "practitioner"
    ],
    "wof:name":"Fogarty P Dr",
    "wof:placetype":"venue"
},
  "geometry": {"coordinates":[151.17814636200001,-33.7962226868],"type":"Point"}
}