{
  "type": "Feature",
  "properties": {
    "iso:country":"AU",
    "sg:address":"14a Walker St",
    "sg:city":"Helensburgh",
    "sg:classifiers":[
        {
            "category":"Personal",
            "subcategory":"Beauty Salon",
            "type":"Services"
        }
    ],
    "sg:phone":"+61 2 4294 1985",
    "sg:postcode":"2508",
    "sg:province":"NSW",
    "sg:tags":[
        "hairdresser"
    ],
    "wof:name":"Lisa Hair Fashions",
    "wof:placetype":"venue"
},
  "geometry": {"coordinates":[150.981674,-34.191952],"type":"Point"}
}