{
  "type": "Feature",
  "properties": {
    "addr:full":"Armidale Road (New England Highway) Tamworth NSW 2340",
    "addr:postcode":"2340",
    "addr:street":"Armidale Road New England Highway",
    "iso:country":"AU",
    "sg:address":"Armidale Road",
    "sg:city":"(New England Highway) Tamworth",
    "sg:classifiers":[
        {
            "category":"Travel",
            "subcategory":"Hotels & Motels",
            "type":"Entertainment"
        }
    ],
    "sg:phone":"+61 2 6766 7000",
    "sg:postcode":"2340",
    "sg:province":"NSW",
    "wof:name":"Quality Hotel Powerhouse",
    "wof:placetype":"venue"
},
  "geometry": {"coordinates":[150.958618164,-31.1122379303],"type":"Point"}
}