{
  "type": "Feature",
  "properties": {
    "addr:full":"Cnr Docklands Hwy & Parker St Footscray VIC 3011",
    "addr:postcode":"3011",
    "addr:street":"Docklands;St",
    "iso:country":"AU",
    "sg:address":"Cnr Docklands Hwy & Parker St",
    "sg:city":"Footscray",
    "sg:classifiers":[
        {
            "category":"Manufacturing",
            "subcategory":"Aerospace",
            "type":"Manufacturing & Wholesale Goods"
        }
    ],
    "sg:phone":"+61 3 9362 0011",
    "sg:postcode":"3011",
    "sg:province":"VIC",
    "sg:tags":[
        "equipment",
        "aircraft",
        "maintenance"
    ],
    "wof:name":"Liferaft Servicing Group",
    "wof:placetype":"venue"
},
  "geometry": {"coordinates":[144.90545654300001,-37.8056602478],"type":"Point"}
}