{
  "type": "Feature",
  "properties": {
    "addr:full":"55 Dalveen Rd Bolwarra NSW 2320",
    "addr:housenumber":"55",
    "addr:postcode":"2320",
    "addr:street":"Dalveen Rd",
    "iso:country":"AU",
    "sg:address":"55 Dalveen Rd",
    "sg:city":"Bolwarra",
    "sg:classifiers":[
        {
            "category":"Utilities",
            "subcategory":"Water",
            "type":"Services"
        }
    ],
    "sg:phone":"+61 439 383 415",
    "sg:postcode":"2320",
    "sg:province":"NSW",
    "sg:tags":[
        "cartage"
    ],
    "wof:name":"Branxton Water Cartage",
    "wof:placetype":"venue"
},
  "geometry": {"coordinates":[151.59370422399999,-32.7034645081],"type":"Point"}
}