{
  "type": "Feature",
  "properties": {
    "addr:full":"27 Linwood Crt Wynn Vale SA 5127",
    "addr:housenumber":"27",
    "addr:postcode":"5127",
    "addr:street":"Linwood Crt",
    "iso:country":"AU",
    "sg:address":"27 Linwood Crt",
    "sg:city":"Wynn Vale",
    "sg:classifiers":[
        {
            "category":"Health Services",
            "subcategory":"Dentist",
            "type":"Services"
        }
    ],
    "sg:phone":"+61 8 8396 2600",
    "sg:postcode":"5127",
    "sg:province":"SA",
    "sg:tags":[
        "technician",
        "dental"
    ],
    "wof:name":"Hall G & S Dental Laboratory",
    "wof:placetype":"venue"
},
  "geometry": {"coordinates":[138.67437744099999,-34.7977828979],"type":"Point"}
}