{
  "type": "Feature",
  "properties": {
    "iso:country":"AU",
    "sg:address":"Unit 2 1263 North East Rd",
    "sg:city":"Ridgehaven",
    "sg:classifiers":[
        {
            "category":"Professional",
            "subcategory":"Accounting & Tax Preparation",
            "type":"Services"
        }
    ],
    "sg:phone":"+61 8 8395 0477",
    "sg:postcode":"5097",
    "sg:province":"SA",
    "sg:tags":[
        "accountant",
        "auditor"
    ],
    "wof:name":"Chan Page & Associates",
    "wof:placetype":"venue"
},
  "geometry": {"coordinates":[138.716705322,-34.8208808899],"type":"Point"}
}