{
  "type": "Feature",
  "properties": {
    "addr:full":"88 Swanson St Erskineville NSW 2043",
    "addr:housenumber":"88",
    "addr:postcode":"2043",
    "addr:street":"Swanson St",
    "iso:country":"AU",
    "sg:address":"88 Swanson St",
    "sg:city":"Erskineville",
    "sg:classifiers":[
        {
            "category":"Organizations",
            "subcategory":"Non-profit Organization",
            "type":"Services"
        }
    ],
    "sg:phone":"+61 2 9557 2097",
    "sg:postcode":"2043",
    "sg:province":"NSW",
    "sg:tags":[
        "support",
        "disability",
        "organisation"
    ],
    "wof:name":"SDN Childrens Services",
    "wof:placetype":"venue"
},
  "geometry": {"coordinates":[151.189911,-33.900314],"type":"Point"}
}