{
  "type": "Feature",
  "properties": {
    "iso:country":"AU",
    "sg:address":"Cnr Beach & Alice Sts",
    "sg:city":"Merimbula",
    "sg:classifiers":[
        {
            "category":"Health Services",
            "subcategory":"Dentist",
            "type":"Services"
        }
    ],
    "sg:phone":"+61 2 6495 1097",
    "sg:postcode":"2548",
    "sg:province":"NSW",
    "wof:name":"Tuckwell William J",
    "wof:placetype":"venue"
},
  "geometry": {"coordinates":[149.911453247,-36.8882293701],"type":"Point"}
}