{
  "type": "Feature",
  "properties": {
    "iso:country":"AU",
    "sg:address":"8/12 Bowers Rd (South)",
    "sg:city":"Everton Hills",
    "sg:classifiers":[
        {
            "category":"Arts & Performance",
            "subcategory":"Comedy Club",
            "type":"Entertainment"
        }
    ],
    "sg:phone":"+61 408 885 420",
    "sg:postcode":"4053",
    "sg:province":"QLD",
    "sg:tags":[
        "piano",
        "removal"
    ],
    "wof:name":"Ron Satterley Piano Removals",
    "wof:placetype":"venue"
},
  "geometry": {"coordinates":[152.97541809099999,-27.3880271912],"type":"Point"}
}