{
  "type": "Feature",
  "properties": {
    "addr:full":"Unit 9, 22 Leighton Pl Hornsby NSW 2077",
    "addr:housenumber":"22",
    "addr:postcode":"2077",
    "addr:street":"Leighton Pl",
    "iso:country":"AU",
    "sg:address":"Unit 9, 22 Leighton Pl",
    "sg:city":"Hornsby",
    "sg:classifiers":[
        {
            "category":"Retail",
            "subcategory":"Laundry & Dry Cleaning",
            "type":"Services"
        }
    ],
    "sg:phone":"+61 2 9476 1273",
    "sg:postcode":"2077",
    "sg:province":"NSW",
    "sg:tags":[
        "equipment",
        "supply"
    ],
    "wof:name":"Forrest Refrigeration & Air Conditioning",
    "wof:placetype":"venue"
},
  "geometry": {"coordinates":[151.11454773,-33.6958808899],"type":"Point"}
}