{
  "type": "Feature",
  "properties": {
    "addr:full":"34 Curlewis St Bondi NSW 2026",
    "addr:housenumber":"34",
    "addr:postcode":"2026",
    "addr:street":"Curlewis St",
    "iso:country":"AU",
    "sg:address":"34 Curlewis St",
    "sg:city":"Bondi",
    "sg:classifiers":[
        {
            "category":"Retail",
            "subcategory":"Auto Repair",
            "type":"Services"
        }
    ],
    "sg:phone":"+61 2 9365 2333",
    "sg:postcode":"2026",
    "sg:province":"NSW",
    "sg:tags":[
        "testing",
        "inspection",
        "motor",
        "vehicle"
    ],
    "wof:name":"Volv Serv",
    "wof:placetype":"venue"
},
  "geometry": {"coordinates":[151.269729614,-33.8857803345],"type":"Point"}
}