{
  "type": "Feature",
  "properties": {
    "addr:full":"151 Durlacher St Geraldton WA 6530",
    "addr:housenumber":"151",
    "addr:postcode":"6530",
    "addr:street":"Durlacher St",
    "iso:country":"AU",
    "sg:address":"151 Durlacher St",
    "sg:city":"Geraldton",
    "sg:classifiers":[
        {
            "category":"Health Services",
            "subcategory":"Doctor",
            "type":"Services"
        }
    ],
    "sg:phone":"+61 8 9921 6099",
    "sg:postcode":"6530",
    "sg:province":"WA",
    "sg:tags":[
        "medical",
        "practitioner"
    ],
    "wof:name":"Pedlow K Dr",
    "wof:placetype":"venue"
},
  "geometry": {"coordinates":[114.617111206,-28.7792892456],"type":"Point"}
}