{
  "type": "Feature",
  "properties": {
    "iso:country":"AU",
    "sg:address":"435 Whitehorse Rd",
    "sg:city":"Balwyn",
    "sg:classifiers":[
        {
            "category":"Home & Garden",
            "subcategory":"Carpets & Floor Coverings",
            "type":"Retail Goods"
        }
    ],
    "sg:phone":"+61 3 9830 4172",
    "sg:postcode":"3103",
    "sg:province":"VIC",
    "wof:name":"Thomas & O'Keeffe Pty Ltd",
    "wof:placetype":"venue"
},
  "geometry": {"coordinates":[145.08497619600001,-37.8131446838],"type":"Point"}
}