{
  "type": "Feature",
  "properties": {
    "addr:full":"286 Darebin Rd Fairfield VIC 3078",
    "addr:housenumber":"286",
    "addr:postcode":"3078",
    "addr:street":"Darebin Rd",
    "iso:country":"AU",
    "sg:address":"286 Darebin Rd",
    "sg:city":"Fairfield",
    "sg:classifiers":[
        {
            "category":"Autos & Motor Vehicles",
            "subcategory":"Automobile Sales",
            "type":"Retail Goods"
        }
    ],
    "sg:phone":"+61 3 9481 7111",
    "sg:postcode":"3078",
    "sg:province":"VIC",
    "sg:tags":[
        "equipment",
        "trailer"
    ],
    "wof:name":"Brown S J Pty Ltd",
    "wof:placetype":"venue"
},
  "geometry": {"coordinates":[145.024734497,-37.7660560608],"type":"Point"}
}