{
  "type": "Feature",
  "properties": {
    "addr:full":"14 Sheppard St Shepparton VIC 3630",
    "addr:housenumber":"14",
    "addr:postcode":"3630",
    "addr:street":"Sheppard St",
    "iso:country":"AU",
    "sg:address":"14 Sheppard St",
    "sg:city":"Shepparton",
    "sg:classifiers":[
        {
            "category":"Wholesale",
            "subcategory":"Machinery & Supplies",
            "type":"Manufacturing & Wholesale Goods"
        }
    ],
    "sg:phone":"+61 3 5821 4693",
    "sg:postcode":"3630",
    "sg:province":"VIC",
    "sg:tags":[
        "agricultural"
    ],
    "wof:name":"Waite G W & M E",
    "wof:placetype":"venue"
},
  "geometry": {"coordinates":[145.39784240700001,-36.3944664001],"type":"Point"}
}