{
  "type": "Feature",
  "properties": {
    "addr:full":"364 Port Hacking Rd Caringbah NSW 2229",
    "addr:housenumber":"364",
    "addr:postcode":"2229",
    "addr:street":"Port Hacking Rd",
    "iso:country":"AU",
    "sg:address":"364 Port Hacking Rd",
    "sg:city":"Caringbah",
    "sg:classifiers":[
        {
            "category":"Shopping",
            "subcategory":"Clothing, Apparel, & Fashions",
            "type":"Retail Goods"
        }
    ],
    "sg:phone":"+61 2 9524 6113",
    "sg:postcode":"2229",
    "sg:province":"NSW",
    "sg:tags":[
        "lady",
        "wear"
    ],
    "wof:name":"Focus Boutique",
    "wof:placetype":"venue"
},
  "geometry": {"coordinates":[151.123535156,-34.0443000793],"type":"Point"}
}