{
  "type": "Feature",
  "properties": {
    "addr:full":"12 Bayside Ave St Leonards VIC 3223",
    "addr:housenumber":"12",
    "addr:postcode":"3223",
    "addr:street":"Bayside Ave",
    "iso:country":"AU",
    "sg:address":"12 Bayside Ave",
    "sg:city":"St Leonards",
    "sg:classifiers":[
        {
            "category":"Utilities",
            "subcategory":"Electric",
            "type":"Services"
        }
    ],
    "sg:phone":"+61 400 827 980",
    "sg:postcode":"3223",
    "sg:province":"VIC",
    "sg:tags":[
        "electrical",
        "contractor"
    ],
    "wof:name":"R H Electrics",
    "wof:placetype":"venue"
},
  "geometry": {"coordinates":[144.71379099999999,-38.180065],"type":"Point"}
}