{
  "type": "Feature",
  "properties": {
    "addr:full":"365e Kensington Rd Kensington Gardens SA 5068",
    "addr:housenumber":"365e",
    "addr:postcode":"5068",
    "addr:street":"Kensington Rd",
    "iso:country":"AU",
    "sg:address":"365e Kensington Rd",
    "sg:city":"Kensington Gardens",
    "sg:classifiers":[
        {
            "category":"Food & Beverages",
            "subcategory":"Fruits & Vegetables",
            "type":"Retail Goods"
        }
    ],
    "sg:phone":"+61 8 8332 2163",
    "sg:postcode":"5068",
    "sg:province":"SA",
    "sg:tags":[
        "greengrocer",
        "fruiterer"
    ],
    "wof:name":"Kensington Gardens Fruit Market",
    "wof:placetype":"venue"
},
  "geometry": {"coordinates":[138.66590881400001,-34.9255523682],"type":"Point"}
}