{
  "type": "Feature",
  "properties": {
    "iso:country":"AU",
    "sg:address":"Units D, 2 Hudson Ave",
    "sg:city":"Castle Hill",
    "sg:classifiers":[
        {
            "category":"Autos & Motor Vehicles",
            "subcategory":"Recreational Vehicle Sales",
            "type":"Retail Goods"
        }
    ],
    "sg:phone":"+61 2 9899 4333",
    "sg:postcode":"2154",
    "sg:province":"NSW",
    "sg:tags":[
        "industrial",
        "sewing",
        "contractor"
    ],
    "wof:name":"Sew-It-Rite",
    "wof:placetype":"venue"
},
  "geometry": {"coordinates":[150.97483825699999,-33.7332496643],"type":"Point"}
}