{
  "type": "Feature",
  "properties": {
    "iso:country":"AU",
    "sg:address":"76 New Settelment Rd",
    "sg:city":"Burpengary",
    "sg:classifiers":[
        {
            "category":"Building & Trades",
            "subcategory":"Construction",
            "type":"Services"
        }
    ],
    "sg:phone":"+61 2 4946 5105",
    "sg:postcode":"4505",
    "sg:province":"QLD",
    "sg:tags":[
        "earth",
        "excavating",
        "moving",
        "contractor"
    ],
    "wof:name":"Mudslingers Earthworx",
    "wof:placetype":"venue"
},
  "geometry": {"coordinates":[152.974533081,-27.1776199341],"type":"Point"}
}