{
  "type": "Feature",
  "properties": {
    "addr:full":"Shp2f/ 42 Railway Pde Burwood NSW 2134",
    "addr:housenumber":"42",
    "addr:postcode":"2134",
    "addr:street":"Railway Pde",
    "iso:country":"AU",
    "sg:address":"Shp2f/ 42 Railway Pde",
    "sg:city":"Burwood",
    "sg:classifiers":[
        {
            "category":"Fast Food",
            "type":"Food & Drink"
        }
    ],
    "sg:phone":"+61 2 9701 0214",
    "sg:postcode":"2134",
    "sg:province":"NSW",
    "sg:tags":[
        "away",
        "take"
    ],
    "wof:name":"Sams Mediterranean Delights",
    "wof:placetype":"venue"
},
  "geometry": {"coordinates":[151.10061645499999,-33.8771095276],"type":"Point"}
}