{
  "type": "Feature",
  "properties": {
    "iso:country":"AU",
    "sg:address":"3 Rina Crt",
    "sg:city":"Varsity Lakes",
    "sg:classifiers":[
        {
            "category":"Military Area",
            "subcategory":"Bunker",
            "type":"Public Place"
        }
    ],
    "sg:phone":"+61 7 5593 5527",
    "sg:postcode":"4227",
    "sg:province":"QLD",
    "sg:tags":[
        "tub",
        "planter"
    ],
    "wof:name":"Coast Concrete Garden Products",
    "wof:placetype":"venue"
},
  "geometry": {"coordinates":[153.41111755399999,-28.1010837555],"type":"Point"}
}