{
  "type": "Feature",
  "properties": {
    "addr:full":"Lvl6/ 147a King St Sydney NSW 2000",
    "addr:housenumber":"147a",
    "addr:postcode":"2000",
    "addr:street":"King St",
    "iso:country":"AU",
    "sg:address":"Lvl6/ 147a King St",
    "sg:city":"Sydney",
    "sg:classifiers":[
        {
            "category":"Travel",
            "subcategory":"Travel Agent",
            "type":"Entertainment"
        }
    ],
    "sg:phone":"+61 2 9232 1982",
    "sg:postcode":"2000",
    "sg:province":"NSW",
    "sg:tags":[
        "consultant"
    ],
    "wof:name":"One Cover Insurance Pty Ltd",
    "wof:placetype":"venue"
},
  "geometry": {"coordinates":[151.20930480999999,-33.8691215515],"type":"Point"}
}