{
  "type": "Feature",
  "properties": {
    "addr:full":"Martley St Porepunkah VIC 3740",
    "addr:postcode":"3740",
    "addr:street":"Martley St",
    "iso:country":"AU",
    "sg:address":"Martley St",
    "sg:city":"Porepunkah",
    "sg:classifiers":[
        {
            "category":"Education",
            "subcategory":"School",
            "type":"Public Place"
        }
    ],
    "sg:phone":"+61 3 5756 2253",
    "sg:postcode":"3740",
    "sg:province":"VIC",
    "sg:tags":[
        "state",
        "except",
        "nsw"
    ],
    "wof:name":"Porepunkah Primary School",
    "wof:placetype":"venue"
},
  "geometry": {"coordinates":[146.91250600000001,-36.697193],"type":"Point"}
}