{
  "type": "Feature",
  "properties": {
    "addr:full":"160 Brunswick St Fortitude Valley QLD 4006",
    "addr:housenumber":"160",
    "addr:postcode":"4006",
    "addr:street":"Brunswick St",
    "iso:country":"AU",
    "sg:address":"160 Brunswick St",
    "sg:city":"Fortitude Valley",
    "sg:classifiers":[
        {
            "category":"Retail",
            "subcategory":"Repair Shop",
            "type":"Services"
        }
    ],
    "sg:phone":"+61 7 3880 1211",
    "sg:postcode":"4006",
    "sg:province":"QLD",
    "sg:tags":[
        "maintenance",
        "pool",
        "swimming"
    ],
    "wof:name":"Cameron Rod",
    "wof:placetype":"venue"
},
  "geometry": {"coordinates":[153.031417847,-27.4558601379],"type":"Point"}
}