{
  "type": "Feature",
  "properties": {
    "addr:full":"Shop 18, Randwick Plz 128 Belmore Rd Randwick NSW 2031",
    "addr:housenumber":"shop 18;128",
    "addr:postcode":"2031",
    "addr:street":"Randwick Plz;Belmore Rd",
    "iso:country":"AU",
    "sg:address":"Shop 18, Randwick Plz 128 Belmore Rd",
    "sg:city":"Randwick",
    "sg:classifiers":[
        {
            "category":"Personal",
            "subcategory":"Beauty Salon",
            "type":"Services"
        }
    ],
    "sg:phone":"+61 2 9398 5576",
    "sg:postcode":"2031",
    "sg:province":"NSW",
    "wof:name":"Champagne Belle Randwick Beauty Salon",
    "wof:placetype":"venue"
},
  "geometry": {"coordinates":[151.24073791500001,-33.9163169861],"type":"Point"}
}