{
  "type": "Feature",
  "properties": {
    "addr:full":"1751 Pittwater Rd Mona Vale NSW 2103",
    "addr:housenumber":"1751",
    "addr:postcode":"2103",
    "addr:street":"Pittwater Rd",
    "iso:country":"AU",
    "sg:address":"1751 Pittwater Rd",
    "sg:city":"Mona Vale",
    "sg:classifiers":[
        {
            "category":"Banks & Credit Unions",
            "subcategory":"Financial Services",
            "type":"Services"
        }
    ],
    "sg:phone":"+61 2 9997 3377",
    "sg:postcode":"2103",
    "sg:province":"NSW",
    "sg:tags":[
        "loan",
        "finance",
        "mortgage"
    ],
    "wof:name":"Wizard",
    "wof:placetype":"venue"
},
  "geometry": {"coordinates":[151.30325317399999,-33.6782684326],"type":"Point"}
}