{
  "type": "Feature",
  "properties": {
    "iso:country":"AU",
    "sg:address":"Gaspard Rd",
    "sg:city":"Quirindi",
    "sg:classifiers":[
        {
            "category":"Building & Trades",
            "subcategory":"Landscaping Services",
            "type":"Services"
        }
    ],
    "sg:phone":"+61 2 6746 1274",
    "sg:postcode":"2343",
    "sg:province":"NSW",
    "sg:tags":[
        "grazier"
    ],
    "wof:name":"Pollock J T",
    "wof:placetype":"venue"
},
  "geometry": {"coordinates":[150.69566345199999,-31.5098934174],"type":"Point"}
}