{
  "type": "Feature",
  "properties": {
    "addr:full":"477 Pitt St Haymarket NSW 2000",
    "addr:housenumber":"477",
    "addr:postcode":"2000",
    "addr:street":"Pitt St",
    "iso:country":"AU",
    "sg:address":"477 Pitt St",
    "sg:city":"Haymarket",
    "sg:classifiers":[
        {
            "category":"Personal",
            "subcategory":"Massage",
            "type":"Services"
        }
    ],
    "sg:phone":"+61 2 9281 2960",
    "sg:postcode":"2000",
    "sg:province":"NSW",
    "sg:tags":[
        "therapy"
    ],
    "wof:name":"Ssage Message Therapy",
    "wof:placetype":"venue"
},
  "geometry": {"coordinates":[151.206542969,-33.8806877136],"type":"Point"}
}