{
  "type": "Feature",
  "properties": {
    "addr:full":"13 Courallie St Moree NSW 2400",
    "addr:housenumber":"13",
    "addr:postcode":"2400",
    "addr:street":"Courallie St",
    "iso:country":"AU",
    "sg:address":"13 Courallie St",
    "sg:city":"Moree",
    "sg:classifiers":[
        {
            "category":"Real Estate",
            "subcategory":"Surveying",
            "type":"Services"
        }
    ],
    "sg:phone":"+61 438 215 393",
    "sg:postcode":"2400",
    "sg:province":"NSW",
    "sg:tags":[
        "surveyor",
        "land"
    ],
    "wof:name":"Quintec Survey Solutions Pty Ltd",
    "wof:placetype":"venue"
},
  "geometry": {"coordinates":[149.821899414,-29.4647216797],"type":"Point"}
}