{
  "type": "Feature",
  "properties": {
    "addr:full":"663 Newcastle St Leederville WA 6007",
    "addr:housenumber":"663",
    "addr:postcode":"6007",
    "addr:street":"Newcastle St",
    "iso:country":"AU",
    "sg:address":"663 Newcastle St",
    "sg:city":"Leederville",
    "sg:classifiers":[
        {
            "category":"Professional",
            "subcategory":"Art Services",
            "type":"Services"
        }
    ],
    "sg:phone":"+61 8 9228 2206",
    "sg:postcode":"6007",
    "sg:province":"WA",
    "sg:tags":[
        "graphic",
        "designer"
    ],
    "wof:name":"Flametree House Pty Ltd",
    "wof:placetype":"venue"
},
  "geometry": {"coordinates":[115.84204864500001,-31.9376754761],"type":"Point"}
}