{
  "type": "Feature",
  "properties": {
    "iso:country":"AU",
    "sg:address":"151 Mark Rd",
    "sg:city":"Caloundra",
    "sg:classifiers":[
        {
            "category":"Home & Garden",
            "subcategory":"Building Materials",
            "type":"Retail Goods"
        }
    ],
    "sg:phone":"+61 7 5491 6377",
    "sg:postcode":"4551",
    "sg:province":"QLD",
    "sg:tags":[
        "fencing"
    ],
    "wof:name":"Abbey Timber & Plywood",
    "wof:placetype":"venue"
},
  "geometry": {"coordinates":[153.11253356899999,-26.792131424],"type":"Point"}
}