{
  "type": "Feature",
  "properties": {
    "iso:country":"AU",
    "sg:address":"19 Turnbull Ave",
    "sg:city":"Toorak",
    "sg:classifiers":[
        {
            "category":"Real Estate",
            "subcategory":"Real Estate Services",
            "type":"Services"
        }
    ],
    "sg:phone":"+61 3 9824 8724",
    "sg:postcode":"3142",
    "sg:province":"VIC",
    "sg:tags":[
        "consultant",
        "property"
    ],
    "wof:name":"Kammoora Group",
    "wof:placetype":"venue"
},
  "geometry": {"coordinates":[145.025268555,-37.8382034302],"type":"Point"}
}