{
  "type": "Feature",
  "properties": {
    "iso:country":"AU",
    "sg:address":"1 Linear Park Crt",
    "sg:city":"Athelstone",
    "sg:classifiers":[
        {
            "category":"Building & Trades",
            "subcategory":"Construction",
            "type":"Services"
        }
    ],
    "sg:phone":"+61 8 8336 4358",
    "sg:postcode":"5076",
    "sg:province":"SA",
    "sg:tags":[
        "contractor"
    ],
    "wof:name":"New Star Homes",
    "wof:placetype":"venue"
},
  "geometry": {"coordinates":[138.70872497600001,-34.8626480103],"type":"Point"}
}