{
  "type": "Feature",
  "properties": {
    "addr:full":"700 George St Haymarket NSW 2000",
    "addr:housenumber":"700",
    "addr:postcode":"2000",
    "addr:street":"George St",
    "iso:country":"AU",
    "sg:address":"700 George St",
    "sg:city":"Haymarket",
    "sg:classifiers":[
        {
            "category":"Real Estate",
            "subcategory":"Architect",
            "type":"Services"
        }
    ],
    "sg:phone":"+61 2 9212 0112",
    "sg:postcode":"2000",
    "sg:province":"NSW",
    "wof:name":"Chrixcl Pty Ltd",
    "wof:placetype":"venue"
},
  "geometry": {"coordinates":[151.205841064,-33.8781776428],"type":"Point"}
}