{
  "type": "Feature",
  "properties": {
    "addr:full":"341 Albany Hwy Victoria Park WA 6100",
    "addr:housenumber":"341",
    "addr:postcode":"6100",
    "addr:street":"Albany Hwy Victoria",
    "iso:country":"AU",
    "sg:address":"341 Albany Hwy",
    "sg:city":"Victoria Park",
    "sg:classifiers":[
        {
            "category":"Shopping",
            "subcategory":"Music",
            "type":"Retail Goods"
        }
    ],
    "sg:phone":"+61 8 9470 1020",
    "sg:postcode":"6100",
    "sg:province":"WA",
    "sg:tags":[
        "instrument",
        "musical"
    ],
    "wof:name":"Drum Dept.",
    "wof:placetype":"venue"
},
  "geometry": {"coordinates":[115.89649963399999,-31.9734287262],"type":"Point"}
}