{
  "type": "Feature",
  "properties": {
    "addr:full":"8 Green St Thomastown VIC 3074",
    "addr:housenumber":"8",
    "addr:postcode":"3074",
    "addr:street":"Green St",
    "iso:country":"AU",
    "sg:address":"8 Green St",
    "sg:city":"Thomastown",
    "sg:classifiers":[
        {
            "category":"Home & Garden",
            "subcategory":"Household Appliances",
            "type":"Retail Goods"
        }
    ],
    "sg:phone":"+61 3 9464 7008",
    "sg:postcode":"3074",
    "sg:province":"VIC",
    "sg:tags":[
        "wholesale",
        "mfrs",
        "air conditioning"
    ],
    "wof:name":"All About Sheetmetal",
    "wof:placetype":"venue"
},
  "geometry": {"coordinates":[145.03828430199999,-37.6910362244],"type":"Point"}
}