{
  "type": "Feature",
  "properties": {
    "addr:full":"476 Wagga Rd Lavington NSW 2641",
    "addr:housenumber":"476",
    "addr:postcode":"2641",
    "addr:street":"Wagga Rd",
    "iso:country":"AU",
    "sg:address":"476 Wagga Rd",
    "sg:city":"Lavington",
    "sg:classifiers":[
        {
            "category":"Travel",
            "subcategory":"Hotels & Motels",
            "type":"Entertainment"
        }
    ],
    "sg:phone":"+61 2 6025 1233",
    "sg:postcode":"2641",
    "sg:province":"NSW",
    "wof:name":"Albury Coach House Motel",
    "wof:placetype":"venue"
},
  "geometry": {"coordinates":[146.95196533199999,-36.042766571],"type":"Point"}
}