{
  "type": "Feature",
  "properties": {
    "addr:full":"Ground Floor, 477 Williamstown Rd Port Melbourne VIC 3207",
    "addr:housenumber":"477",
    "addr:postcode":"3207",
    "addr:street":"Williamstown Rd",
    "iso:country":"AU",
    "sg:address":"Ground Floor, 477 Williamstown Rd",
    "sg:city":"Port Melbourne",
    "sg:classifiers":[
        {
            "category":"Professional",
            "subcategory":"Computer Services",
            "type":"Services"
        }
    ],
    "sg:phone":"+61 1300 361 988",
    "sg:postcode":"3207",
    "sg:province":"VIC",
    "sg:tags":[
        "repairs",
        "upgrade",
        "equipment"
    ],
    "wof:name":"Computelec Pty Ltd",
    "wof:placetype":"venue"
},
  "geometry": {"coordinates":[144.937805,-37.832371],"type":"Point"}
}