{
  "type": "Feature",
  "properties": {
    "iso:country":"AU",
    "sg:address":"35 Sylvan Ave",
    "sg:city":"Medowie",
    "sg:classifiers":[
        {
            "category":"Home & Garden",
            "subcategory":"Carpets & Floor Coverings",
            "type":"Retail Goods"
        }
    ],
    "sg:phone":"+61 2 4981 8338",
    "sg:postcode":"2318",
    "sg:province":"NSW",
    "sg:tags":[
        "tile",
        "wall",
        "layer"
    ],
    "wof:name":"A & M Tisdell",
    "wof:placetype":"venue"
},
  "geometry": {"coordinates":[151.870651,-32.759151],"type":"Point"}
}