{
  "type": "Feature",
  "properties": {
    "iso:country":"AU",
    "sg:address":"299 Burwood Hwy",
    "sg:city":"Burwood East",
    "sg:classifiers":[
        {
            "category":"Retail",
            "subcategory":"Event Space",
            "type":"Services"
        }
    ],
    "sg:phone":"+61 3 9887 9644",
    "sg:postcode":"3151",
    "sg:province":"VIC",
    "sg:tags":[
        "function",
        "organiser"
    ],
    "wof:name":"Smorgys",
    "wof:placetype":"venue"
},
  "geometry": {"coordinates":[145.16094970699999,-37.8534851074],"type":"Point"}
}