{
  "type": "Feature",
  "properties": {
    "addr:full":"17 Blandford Ave Waverley NSW 2024",
    "addr:housenumber":"17",
    "addr:postcode":"2024",
    "addr:street":"Blandford Ave",
    "iso:country":"AU",
    "sg:address":"17 Blandford Ave",
    "sg:city":"Waverley",
    "sg:classifiers":[
        {
            "category":"Health Services",
            "subcategory":"Doctor",
            "type":"Services"
        }
    ],
    "sg:phone":"+61 2 9389 5505",
    "sg:postcode":"2024",
    "sg:province":"NSW",
    "sg:tags":[
        "medical",
        "practitioner"
    ],
    "wof:name":"Ivanov Aksel",
    "wof:placetype":"venue"
},
  "geometry": {"coordinates":[151.25979614299999,-33.8988418579],"type":"Point"}
}