{
  "type": "Feature",
  "properties": {
    "iso:country":"AU",
    "sg:address":"13a Freeman Ave",
    "sg:city":"Tranmere",
    "sg:classifiers":[
        {
            "category":"Building & Trades",
            "subcategory":"Plumbing",
            "type":"Services"
        }
    ],
    "sg:phone":"+61 8 8333 0397",
    "sg:postcode":"5073",
    "sg:province":"SA",
    "sg:tags":[
        "plumber",
        "gasfitters"
    ],
    "wof:name":"Tranmere Plumbing Service",
    "wof:placetype":"venue"
},
  "geometry": {"coordinates":[138.66200256400001,-34.9033699036],"type":"Point"}
}