{
  "type": "Feature",
  "properties": {
    "addr:full":"69 Wellington St Launceston TAS 7250",
    "addr:housenumber":"69",
    "addr:postcode":"7250",
    "addr:street":"Wellington St",
    "iso:country":"AU",
    "sg:address":"69 Wellington St",
    "sg:city":"Launceston",
    "sg:classifiers":[
        {
            "category":"Autos & Motor Vehicles",
            "subcategory":"Fuel & Gas Station",
            "type":"Retail Goods"
        }
    ],
    "sg:phone":"+61 3 6331 4802",
    "sg:postcode":"7250",
    "sg:province":"TAS",
    "wof:name":"El Centro Self Serve",
    "wof:placetype":"venue"
},
  "geometry": {"coordinates":[147.13719177199999,-41.4403076172],"type":"Point"}
}