{
  "type": "Feature",
  "properties": {
    "addr:full":"23 Graham St Milton QLD 4064",
    "addr:housenumber":"23",
    "addr:postcode":"4064",
    "addr:street":"Graham St",
    "iso:country":"AU",
    "sg:address":"23 Graham St",
    "sg:city":"Milton",
    "sg:classifiers":[
        {
            "category":"Building & Trades",
            "subcategory":"Construction",
            "type":"Services"
        }
    ],
    "sg:phone":"+61 7 3511 5555",
    "sg:postcode":"4064",
    "sg:province":"QLD",
    "sg:tags":[
        "management"
    ],
    "wof:name":"Adco Constructions Pty Ltd",
    "wof:placetype":"venue"
},
  "geometry": {"coordinates":[153.004196167,-27.4728355408],"type":"Point"}
}