{
  "type": "Feature",
  "properties": {
    "addr:full":"Murchison Hwy Tullah TAS 7321",
    "addr:postcode":"7321",
    "addr:street":"Murchison Hwy",
    "iso:country":"AU",
    "sg:address":"Murchison Hwy",
    "sg:city":"Tullah",
    "sg:classifiers":[
        {
            "category":"Transit Center",
            "subcategory":"Freight",
            "type":"Transportation"
        }
    ],
    "sg:phone":"+61 3 6473 4344",
    "sg:postcode":"7321",
    "sg:province":"TAS",
    "sg:tags":[
        "turner",
        "wood"
    ],
    "wof:name":"Radford Woodcrafts",
    "wof:placetype":"venue"
},
  "geometry": {"coordinates":[145.61874399999999,-41.741112],"type":"Point"}
}