{
  "type": "Feature",
  "properties": {
    "iso:country":"AU",
    "sg:address":"3/ 323 Darling St",
    "sg:city":"Balmain",
    "sg:classifiers":[
        {
            "category":"Cafe",
            "type":"Food & Drink"
        }
    ],
    "sg:phone":"+61 406 345 389",
    "sg:postcode":"2041",
    "sg:province":"NSW",
    "wof:name":"Rawcasting Cafe",
    "wof:placetype":"venue"
},
  "geometry": {"coordinates":[151.179565,-33.856647],"type":"Point"}
}