{
  "type": "Feature",
  "properties": {
    "iso:country":"AU",
    "sg:address":"242 McKinnon Rd",
    "sg:city":"McKinnon",
    "sg:classifiers":[
        {
            "category":"Retail",
            "subcategory":"Auto Repair",
            "type":"Services"
        }
    ],
    "sg:phone":"+61 3 9578 3533",
    "sg:postcode":"3204",
    "sg:province":"VIC",
    "sg:tags":[
        "testing",
        "inspection",
        "motor",
        "vehicle"
    ],
    "wof:name":"Hold Serv",
    "wof:placetype":"venue"
},
  "geometry": {"coordinates":[145.041946,-37.911633],"type":"Point"}
}