{
  "type": "Feature",
  "properties": {
    "iso:country":"AU",
    "sg:address":"270 Bondi Rd",
    "sg:city":"Bondi",
    "sg:classifiers":[
        {
            "category":"Health Services",
            "subcategory":"Doctor",
            "type":"Services"
        }
    ],
    "sg:phone":"+61 2 9130 5442",
    "sg:postcode":"2026",
    "sg:province":"NSW",
    "sg:tags":[
        "medical",
        "practitioner"
    ],
    "wof:name":"Aurbac Rebecca",
    "wof:placetype":"venue"
},
  "geometry": {"coordinates":[151.26687622099999,-33.8942451477],"type":"Point"}
}