{
  "type": "Feature",
  "properties": {
    "iso:country":"AU",
    "sg:address":"Un 18, 1 Newspaper Pl",
    "sg:city":"Maroochydore",
    "sg:classifiers":[
        {
            "category":"Professional",
            "subcategory":"Employment Agencies",
            "type":"Services"
        }
    ],
    "sg:phone":"+61 7 5451 1119",
    "sg:postcode":"4558",
    "sg:province":"QLD",
    "wof:name":"Frontline Retail",
    "wof:placetype":"venue"
},
  "geometry": {"coordinates":[153.09136962900001,-26.6669864655],"type":"Point"}
}