{
  "type": "Feature",
  "properties": {
    "iso:country":"AU",
    "sg:address":"716 Station St",
    "sg:city":"Box Hill",
    "sg:classifiers":[
        {
            "category":"Health Services",
            "subcategory":"Dentist",
            "type":"Services"
        }
    ],
    "sg:phone":"+61 3 9890 7777",
    "sg:postcode":"3128",
    "sg:province":"VIC",
    "sg:website":"http://www.geoffrossdental.com.au",
    "wof:name":"Dr Geoffrey Ross",
    "wof:placetype":"venue"
},
  "geometry": {"coordinates":[145.124343872,-37.8166236877],"type":"Point"}
}