{
  "type": "Feature",
  "properties": {
    "addr:full":"Tower 2/L20, 500 Oxford St Bondi Junction NSW 2022",
    "addr:housenumber":"500",
    "addr:postcode":"2022",
    "addr:street":"Oxford St",
    "iso:country":"AU",
    "sg:address":"Tower 2/L20, 500 Oxford St",
    "sg:city":"Bondi Junction",
    "sg:classifiers":[
        {
            "category":"Professional",
            "subcategory":"Computer Services",
            "type":"Services"
        }
    ],
    "sg:phone":"+61 2 9386 1777",
    "sg:postcode":"2022",
    "sg:province":"NSW",
    "sg:tags":[
        "package",
        "software"
    ],
    "wof:name":"O4 Corporation",
    "wof:placetype":"venue"
},
  "geometry": {"coordinates":[151.25054931599999,-33.8918571472],"type":"Point"}
}