{
  "type": "Feature",
  "properties": {
    "iso:country":"AU",
    "sg:address":"24 Hollis Rd",
    "sg:city":"Pomona",
    "sg:classifiers":[
        {
            "category":"Personal",
            "subcategory":"Massage",
            "type":"Services"
        }
    ],
    "sg:phone":"+61 7 5485 0362",
    "sg:postcode":"4568",
    "sg:province":"QLD",
    "sg:tags":[
        "therapy"
    ],
    "wof:name":"Adele McClure",
    "wof:placetype":"venue"
},
  "geometry": {"coordinates":[152.84768676799999,-26.3789138794],"type":"Point"}
}