{
  "type": "Feature",
  "properties": {
    "iso:country":"AU",
    "sg:address":"3/ 16 Tarnard Drv",
    "sg:city":"Braeside",
    "sg:classifiers":[
        {
            "category":"Building & Trades",
            "subcategory":"Construction",
            "type":"Services"
        }
    ],
    "sg:phone":"+61 3 9580 6951",
    "sg:postcode":"3195",
    "sg:province":"VIC",
    "sg:tags":[
        "equipment",
        "system",
        "automation"
    ],
    "wof:name":"Competition Systems Pty Ltd",
    "wof:placetype":"venue"
},
  "geometry": {"coordinates":[145.11349487300001,-38.0020332336],"type":"Point"}
}