{
  "type": "Feature",
  "properties": {
    "addr:full":"Unit 2/ 160 Waldron Rd Chester Hill NSW 2162",
    "addr:housenumber":"/ 160",
    "addr:postcode":"2162",
    "addr:street":"Waldron Rd",
    "iso:country":"AU",
    "sg:address":"Unit 2/ 160 Waldron Rd",
    "sg:city":"Chester Hill",
    "sg:classifiers":[
        {
            "category":"Restaurant",
            "type":"Food & Drink"
        }
    ],
    "sg:phone":"+61 2 9738 5900",
    "sg:postcode":"2162",
    "sg:province":"NSW",
    "wof:name":"Best Bamboo Vietnamise & Chinese Restaurant",
    "wof:placetype":"venue"
},
  "geometry": {"coordinates":[151.000488281,-33.8828849792],"type":"Point"}
}