{
  "type": "Feature",
  "properties": {
    "addr:full":"24 Northwood St Narrogin WA 6312",
    "addr:housenumber":"24",
    "addr:postcode":"6312",
    "addr:street":"Northwood St",
    "iso:country":"AU",
    "sg:address":"24 Northwood St",
    "sg:city":"Narrogin",
    "sg:classifiers":[
        {
            "category":"Home & Garden",
            "subcategory":"Carpets & Floor Coverings",
            "type":"Retail Goods"
        }
    ],
    "sg:phone":"+61 8 9881 1447",
    "sg:postcode":"6312",
    "sg:province":"WA",
    "sg:tags":[
        "flooring",
        "parquet"
    ],
    "wof:name":"Southern Sanding",
    "wof:placetype":"venue"
},
  "geometry": {"coordinates":[117.184181213,-32.9301147461],"type":"Point"}
}