{
  "type": "Feature",
  "properties": {
    "iso:country":"AU",
    "sg:address":"Caboolture Medical Centre 13 Hasking St",
    "sg:city":"Caboolture",
    "sg:classifiers":[
        {
            "category":"Health Services",
            "subcategory":"Health Practitioner",
            "type":"Services"
        }
    ],
    "sg:phone":"+61 414 942 298",
    "sg:postcode":"4510",
    "sg:province":"QLD",
    "sg:tags":[
        "acupuncture"
    ],
    "wof:name":"Hatton Christine",
    "wof:placetype":"venue"
},
  "geometry": {"coordinates":[152.95060699999999,-27.083096],"type":"Point"}
}