{
  "type": "Feature",
  "properties": {
    "addr:full":"89 Horne St Campbellfield VIC 3061",
    "addr:housenumber":"89",
    "addr:postcode":"3061",
    "addr:street":"Horne St",
    "iso:country":"AU",
    "sg:address":"89 Horne St",
    "sg:city":"Campbellfield",
    "sg:classifiers":[
        {
            "category":"Manufacturing",
            "subcategory":"Metals",
            "type":"Manufacturing & Wholesale Goods"
        }
    ],
    "sg:phone":"+61 3 9357 2432",
    "sg:postcode":"3061",
    "sg:province":"VIC",
    "sg:tags":[
        "steel",
        "fabricator",
        "mfrs"
    ],
    "wof:name":"Northside Welding Service",
    "wof:placetype":"venue"
},
  "geometry": {"coordinates":[144.96356201200001,-37.6804771423],"type":"Point"}
}