{
  "type": "Feature",
  "properties": {
    "addr:full":"Albert St North Parramatta NSW 2151",
    "addr:postcode":"2151",
    "addr:street":"Albert St",
    "iso:country":"AU",
    "sg:address":"Albert St",
    "sg:city":"North Parramatta",
    "sg:classifiers":[
        {
            "category":"Personal",
            "subcategory":"Adult",
            "type":"Services"
        }
    ],
    "sg:phone":"+61 2 9687 6411",
    "sg:postcode":"2151",
    "sg:province":"NSW",
    "sg:tags":[
        "vic",
        "except",
        "state",
        "escort",
        "social",
        "qld"
    ],
    "wof:name":"Male Encounters",
    "wof:placetype":"venue"
},
  "geometry": {"coordinates":[151.00924682600001,-33.803943634],"type":"Point"}
}