{
  "type": "Feature",
  "properties": {
    "addr:full":"97 Edgecombe St Kyneton VIC 3444",
    "addr:housenumber":"97",
    "addr:postcode":"3444",
    "addr:street":"Edgecombe St",
    "iso:country":"AU",
    "sg:address":"97 Edgecombe St",
    "sg:city":"Kyneton",
    "sg:classifiers":[
        {
            "category":"Professional",
            "subcategory":"Art Services",
            "type":"Services"
        }
    ],
    "sg:phone":"+61 3 5422 2941",
    "sg:postcode":"3444",
    "sg:province":"VIC",
    "sg:tags":[
        "decorator",
        "painter"
    ],
    "wof:name":"Kyneton & Macedon Ranges Painting",
    "wof:placetype":"venue"
},
  "geometry": {"coordinates":[144.46330261200001,-37.2453422546],"type":"Point"}
}