{
  "type": "Feature",
  "properties": {
    "addr:full":"Cnr West Kalgoorlie & Craig Rds West Kalgoorlie WA 6430",
    "addr:postcode":"6430",
    "addr:street":"Cnr West",
    "iso:country":"AU",
    "sg:address":"Cnr West Kalgoorlie & Craig Rds",
    "sg:city":"West Kalgoorlie",
    "sg:classifiers":[
        {
            "category":"Wholesale",
            "subcategory":"Machinery & Supplies",
            "type":"Manufacturing & Wholesale Goods"
        }
    ],
    "sg:phone":"+61 418 965 612",
    "sg:postcode":"6430",
    "sg:province":"WA",
    "wof:name":"CJD Equipment Pty Ltd",
    "wof:placetype":"venue"
},
  "geometry": {"coordinates":[121.427612305,-30.7831516266],"type":"Point"}
}