{
  "type": "Feature",
  "properties": {
    "iso:country":"AU",
    "sg:address":"Ground Floor, 47 Blighs Rd",
    "sg:city":"Cromer",
    "sg:classifiers":[
        {
            "category":"Shopping",
            "subcategory":"Computers & Home Electronics",
            "type":"Retail Goods"
        }
    ],
    "sg:phone":"+61 2 9401 4069",
    "sg:postcode":"2099",
    "sg:province":"NSW",
    "sg:tags":[
        "small",
        "equipment",
        "business"
    ],
    "wof:name":"Tech Data",
    "wof:placetype":"venue"
},
  "geometry": {"coordinates":[151.26557922399999,-33.7301597595],"type":"Point"}
}