{
  "type": "Feature",
  "properties": {
    "addr:full":"Lot 40, Old North Rd Warner QLD 4500",
    "addr:postcode":"4500",
    "addr:street":"North Rd",
    "iso:country":"AU",
    "sg:address":"Lot 40, Old North Rd",
    "sg:city":"Warner",
    "sg:classifiers":[
        {
            "category":"Fast Food",
            "type":"Food & Drink"
        }
    ],
    "sg:phone":"+61 7 3882 2722",
    "sg:postcode":"4500",
    "sg:province":"QLD",
    "sg:tags":[
        "away",
        "take"
    ],
    "wof:name":"Brodies B.B.Q. Chicken & Beef Burgers",
    "wof:placetype":"venue"
},
  "geometry": {"coordinates":[152.961303711,-27.3199977875],"type":"Point"}
}