{
  "type": "Feature",
  "properties": {
    "iso:country":"AU",
    "sg:address":"Level 1 suite 36/ 13 George St",
    "sg:city":"North Strathfield",
    "sg:classifiers":[
        {
            "category":"Professional",
            "subcategory":"Art Services",
            "type":"Services"
        }
    ],
    "sg:phone":"+61 2 8746 0344",
    "sg:postcode":"2137",
    "sg:province":"NSW",
    "sg:tags":[
        "interior",
        "designer"
    ],
    "wof:name":"Genesis Triple Zero",
    "wof:placetype":"venue"
},
  "geometry": {"coordinates":[151.08738708499999,-33.860332489],"type":"Point"}
}