{
  "type": "Feature",
  "properties": {
    "iso:country":"AU",
    "sg:address":"37 Alleyne Ave",
    "sg:city":"Torquay",
    "sg:classifiers":[
        {
            "category":"Professional",
            "subcategory":"Business Services",
            "type":"Services"
        }
    ],
    "sg:phone":"+61 3 5261 2856",
    "sg:postcode":"3228",
    "sg:province":"VIC",
    "sg:tags":[
        "drafting"
    ],
    "wof:name":"Gittings C L",
    "wof:placetype":"venue"
},
  "geometry": {"coordinates":[144.31246899999999,-38.33123],"type":"Point"}
}