{
  "type": "Feature",
  "properties": {
    "addr:full":"Belgrave St Kempsey NSW 2440",
    "addr:postcode":"2440",
    "addr:street":"Belgrave St",
    "iso:country":"AU",
    "sg:address":"Belgrave St",
    "sg:city":"Kempsey",
    "sg:classifiers":[
        {
            "category":"Autos & Motor Vehicles",
            "subcategory":"Fuel & Gas Station",
            "type":"Retail Goods"
        }
    ],
    "sg:phone":"+61 2 6562 4800",
    "sg:postcode":"2440",
    "sg:province":"NSW",
    "wof:name":"Mavin A P",
    "wof:placetype":"venue"
},
  "geometry": {"coordinates":[152.84182699999999,-31.080553],"type":"Point"}
}