{
  "type": "Feature",
  "properties": {
    "iso:country":"AU",
    "sg:address":"Belgrave St",
    "sg:city":"Kempsey",
    "sg:classifiers":[
        {
            "category":"Autos & Motor Vehicles",
            "subcategory":"Fuel & Gas Station",
            "type":"Retail Goods"
        }
    ],
    "sg:phone":"+61 2 6562 4800",
    "sg:postcode":"2440",
    "sg:province":"NSW",
    "wof:name":"Mavin A P",
    "wof:placetype":"venue"
},
  "geometry": {"coordinates":[152.841827,-31.080553],"type":"Point"}
}