{
  "type": "Feature",
  "properties": {
    "iso:country":"AU",
    "sg:address":"94 Railway St",
    "sg:city":"Ayr",
    "sg:classifiers":[
        {
            "category":"Building & Trades",
            "subcategory":"Construction",
            "type":"Services"
        }
    ],
    "sg:phone":"+61 7 4783 1003",
    "sg:postcode":"4807",
    "sg:province":"QLD",
    "sg:tags":[
        "joiner",
        "carpenter"
    ],
    "wof:name":"Ransom K S & J K",
    "wof:placetype":"venue"
},
  "geometry": {"coordinates":[147.39732360799999,-19.5748004913],"type":"Point"}
}