{
  "type": "Feature",
  "properties": {
    "addr:full":"5/ 6 Pacific Hwy Gateshead NSW 2290",
    "addr:housenumber":"/ 6",
    "addr:postcode":"2290",
    "addr:street":"Pacific Hwy",
    "iso:country":"AU",
    "sg:address":"5/ 6 Pacific Hwy",
    "sg:city":"Gateshead",
    "sg:classifiers":[
        {
            "category":"Wholesale",
            "subcategory":"Machinery & Supplies",
            "type":"Manufacturing & Wholesale Goods"
        }
    ],
    "sg:phone":"+61 2 4947 8854",
    "sg:postcode":"2290",
    "sg:province":"NSW",
    "sg:tags":[
        "agricultural"
    ],
    "wof:name":"Rega Pumps Parts & Service Pty Ltd",
    "wof:placetype":"venue"
},
  "geometry": {"coordinates":[151.69140625,-32.9884796143],"type":"Point"}
}