{
  "type": "Feature",
  "properties": {
    "addr:full":"32 King William Crt Wallan VIC 3756",
    "addr:housenumber":"32",
    "addr:postcode":"3756",
    "addr:street":"King William Crt",
    "iso:country":"AU",
    "sg:address":"32 King William Crt",
    "sg:city":"Wallan",
    "sg:classifiers":[
        {
            "category":"Professional",
            "subcategory":"Printing & Photocopies",
            "type":"Services"
        }
    ],
    "sg:phone":"+61 431 813 093",
    "sg:postcode":"3756",
    "sg:province":"VIC",
    "sg:tags":[
        "embroidery"
    ],
    "wof:name":"The Logo Lady",
    "wof:placetype":"venue"
},
  "geometry": {"coordinates":[144.96369899999999,-37.413788],"type":"Point"}
}