{
  "type": "Feature",
  "properties": {
    "addr:full":"1 Sutherland Crt Endeavour Hills VIC 3802",
    "addr:housenumber":"1",
    "addr:postcode":"3802",
    "addr:street":"Sutherland Crt",
    "iso:country":"AU",
    "sg:address":"1 Sutherland Crt",
    "sg:city":"Endeavour Hills",
    "sg:classifiers":[
        {
            "category":"Professional",
            "subcategory":"Computer Services",
            "type":"Services"
        }
    ],
    "sg:phone":"+61 3 9700 1586",
    "sg:postcode":"3802",
    "sg:province":"VIC",
    "sg:tags":[
        "package",
        "software"
    ],
    "wof:name":"Epoch Computer Solutions",
    "wof:placetype":"venue"
},
  "geometry": {"coordinates":[145.25070190400001,-37.9784736633],"type":"Point"}
}