{
  "type": "Feature",
  "properties": {
    "addr:full":"Marsden St Condobolin NSW 2877",
    "addr:postcode":"2877",
    "addr:street":"Marsden St",
    "iso:country":"AU",
    "sg:address":"Marsden St",
    "sg:city":"Condobolin",
    "sg:classifiers":[
        {
            "category":"Home & Garden",
            "subcategory":"Hardware",
            "type":"Retail Goods"
        }
    ],
    "sg:phone":"+61 2 6895 2888",
    "sg:postcode":"2877",
    "sg:province":"NSW",
    "sg:tags":[
        "tarpaulin"
    ],
    "wof:name":"All Tarp Repairs Condobolin",
    "wof:placetype":"venue"
},
  "geometry": {"coordinates":[147.148697,-33.08757],"type":"Point"}
}