{
  "type": "Feature",
  "properties": {
    "addr:full":"31 Bell St The Mall Toowoomba QLD 4350",
    "addr:housenumber":"31",
    "addr:postcode":"4350",
    "addr:street":"Bell St The Mall",
    "iso:country":"AU",
    "sg:address":"31 Bell St The Mall",
    "sg:city":"Toowoomba",
    "sg:classifiers":[
        {
            "category":"Personal",
            "subcategory":"Beauty Salon",
            "type":"Services"
        }
    ],
    "sg:phone":"+61 7 4632 9190",
    "sg:postcode":"4350",
    "sg:province":"QLD",
    "sg:tags":[
        "hairdresser"
    ],
    "wof:name":"Snipettes",
    "wof:placetype":"venue"
},
  "geometry": {"coordinates":[151.95429999999999,-27.559767],"type":"Point"}
}