{
  "type": "Feature",
  "properties": {
    "addr:full":"18 Chapman Pl Eagle Farm QLD 4009",
    "addr:housenumber":"18",
    "addr:postcode":"4009",
    "addr:street":"Chapman Pl",
    "iso:country":"AU",
    "sg:address":"18 Chapman Pl",
    "sg:city":"Eagle Farm",
    "sg:classifiers":[
        {
            "category":"Government",
            "subcategory":"Fire Station",
            "type":"Public Place"
        }
    ],
    "sg:phone":"+61 7 3630 1200",
    "sg:postcode":"4009",
    "sg:province":"QLD",
    "sg:tags":[
        "equipment",
        "protection",
        "consultant"
    ],
    "wof:name":"Matthews Fire Alarm",
    "wof:placetype":"venue"
},
  "geometry": {"coordinates":[153.099853516,-27.433052063],"type":"Point"}
}