{
  "type": "Feature",
  "properties": {
    "addr:full":"4 Langford St Pooraka SA 5095",
    "addr:housenumber":"4",
    "addr:postcode":"5095",
    "addr:street":"Langford St",
    "iso:country":"AU",
    "sg:address":"4 Langford St",
    "sg:city":"Pooraka",
    "sg:classifiers":[
        {
            "category":"Professional",
            "subcategory":"Accounting & Tax Preparation",
            "type":"Services"
        }
    ],
    "sg:phone":"+61 1300 135 005",
    "sg:postcode":"5095",
    "sg:province":"SA",
    "sg:tags":[
        "record",
        "business",
        "destruction"
    ],
    "wof:name":"Green Team Paper",
    "wof:placetype":"venue"
},
  "geometry": {"coordinates":[138.63702392600001,-34.8206939697],"type":"Point"}
}