{
  "type": "Feature",
  "properties": {
    "addr:full":"Railway St Boonah QLD 4310",
    "addr:postcode":"4310",
    "addr:street":"Railway St",
    "iso:country":"AU",
    "sg:address":"Railway St",
    "sg:city":"Boonah",
    "sg:classifiers":[
        {
            "category":"Food & Beverages",
            "subcategory":"Fruits & Vegetables",
            "type":"Retail Goods"
        }
    ],
    "sg:phone":"+61 7 5463 1695",
    "sg:postcode":"4310",
    "sg:province":"QLD",
    "sg:tags":[
        "greengrocer",
        "fruiterer"
    ],
    "wof:name":"Fassifern Valley Markets",
    "wof:placetype":"venue"
},
  "geometry": {"coordinates":[152.68211364699999,-27.9958190918],"type":"Point"}
}