{
  "type": "Feature",
  "properties": {
    "iso:country":"AU",
    "sg:address":"24 Clyde St",
    "sg:city":"Kempsey",
    "sg:classifiers":[
        {
            "category":"Cafe",
            "type":"Food & Drink"
        }
    ],
    "sg:phone":"+61 2 6562 6774",
    "sg:postcode":"2440",
    "sg:province":"NSW",
    "wof:name":"Iguana Blues Cafe",
    "wof:placetype":"venue"
},
  "geometry": {"coordinates":[152.84097299999999,-31.078253],"type":"Point"}
}