{
  "type": "Feature",
  "properties": {
    "iso:country":"AU",
    "sg:address":"75 Webbers Creek Rd",
    "sg:city":"Paterson",
    "sg:classifiers":[
        {
            "category":"Military Area",
            "subcategory":"Air Force Base",
            "type":"Public Place"
        }
    ],
    "sg:phone":"+61 2 4938 5304",
    "sg:postcode":"2421",
    "sg:province":"NSW",
    "sg:tags":[
        "pole",
        "lighting",
        "power"
    ],
    "wof:name":"Power Serve Pty Ltd",
    "wof:placetype":"venue"
},
  "geometry": {"coordinates":[151.614822,-32.600918],"type":"Point"}
}