{
  "type": "Feature",
  "properties": {
    "addr:full":"1072 Gayndah Rd Murgon QLD 4605",
    "addr:housenumber":"1072",
    "addr:postcode":"4605",
    "addr:street":"Gayndah Rd",
    "iso:country":"AU",
    "sg:address":"1072 Gayndah Rd",
    "sg:city":"Murgon",
    "sg:classifiers":[
        {
            "category":"Arena",
            "subcategory":"Bull Ring",
            "type":"Entertainment"
        }
    ],
    "sg:phone":"+61 427 623 253",
    "sg:postcode":"4605",
    "sg:province":"QLD",
    "sg:tags":[
        "breeder",
        "pig"
    ],
    "wof:name":"Shelton Rex",
    "wof:placetype":"venue"
},
  "geometry": {"coordinates":[151.92898600000001,-26.234119],"type":"Point"}
}