{
  "type": "Feature",
  "properties": {
    "iso:country":"AU",
    "sg:address":"35 Cabramatta Rd",
    "sg:city":"Mosman",
    "sg:classifiers":[
        {
            "category":"Utilities",
            "subcategory":"Electric",
            "type":"Services"
        }
    ],
    "sg:phone":"+61 2 9969 7899",
    "sg:postcode":"2088",
    "sg:province":"NSW",
    "sg:tags":[
        "electrical",
        "contractor"
    ],
    "wof:name":"Harrold's Electrical",
    "wof:placetype":"venue"
},
  "geometry": {"coordinates":[151.234817505,-33.8295440674],"type":"Point"}
}