{
  "type": "Feature",
  "properties": {
    "iso:country":"AU",
    "sg:address":"200 Tooradin Station Rd",
    "sg:city":"Tooradin",
    "sg:classifiers":[
        {
            "category":"Professional",
            "subcategory":"Art Services",
            "type":"Services"
        }
    ],
    "sg:phone":"+61 3 5998 3358",
    "sg:postcode":"3980",
    "sg:province":"VIC",
    "sg:tags":[
        "picture",
        "frame",
        "framing"
    ],
    "wof:name":"Picture That",
    "wof:placetype":"venue"
},
  "geometry": {"coordinates":[145.378463745,-38.2124023438],"type":"Point"}
}