{
  "type": "Feature",
  "properties": {
    "iso:country":"AU",
    "sg:address":"30 Burnett St",
    "sg:city":"North Hobart",
    "sg:classifiers":[
        {
            "category":"Organizations",
            "subcategory":"Professional Association",
            "type":"Services"
        }
    ],
    "sg:phone":"+61 3 6236 3600",
    "sg:postcode":"7000",
    "sg:province":"TAS",
    "sg:tags":[
        "organisation",
        "business"
    ],
    "wof:name":"Australian Funeral Directors' Association (Tas Branch)",
    "wof:placetype":"venue"
},
  "geometry": {"coordinates":[147.31999206500001,-42.8732757568],"type":"Point"}
}