{
  "type": "Feature",
  "properties": {
    "addr:full":"1 Mintwood Pl Molendinar QLD 4214",
    "addr:housenumber":"1",
    "addr:postcode":"4214",
    "addr:street":"Mintwood Pl",
    "iso:country":"AU",
    "sg:address":"1 Mintwood Pl",
    "sg:city":"Molendinar",
    "sg:classifiers":[
        {
            "category":"Professional",
            "subcategory":"Management & Consulting",
            "type":"Services"
        }
    ],
    "sg:phone":"+61 7 5539 5889",
    "sg:postcode":"4214",
    "sg:province":"QLD",
    "sg:tags":[
        "consultant",
        "educational"
    ],
    "wof:name":"Ezi Consultanting Pty Ltd",
    "wof:placetype":"venue"
},
  "geometry": {"coordinates":[153.37405395499999,-27.9695701599],"type":"Point"}
}