{
  "type": "Feature",
  "properties": {
    "addr:full":"1/ 8 Colchester Rd Rosebud VIC 3939",
    "addr:housenumber":"/ 8",
    "addr:postcode":"3939",
    "addr:street":"Colchester Rd",
    "iso:country":"AU",
    "sg:address":"1/ 8 Colchester Rd",
    "sg:city":"Rosebud",
    "sg:classifiers":[
        {
            "category":"Autos & Motor Vehicles",
            "subcategory":"Auto Supplies",
            "type":"Retail Goods"
        }
    ],
    "sg:phone":"+61 3 5986 8855",
    "sg:postcode":"3939",
    "sg:province":"VIC",
    "sg:tags":[
        "accessory"
    ],
    "wof:name":"EFI Parts Galore",
    "wof:placetype":"venue"
},
  "geometry": {"coordinates":[144.88710022000001,-38.379108429],"type":"Point"}
}