{
  "type": "Feature",
  "properties": {
    "iso:country":"AU",
    "sg:address":"75 Sir Fred Schonell Drv",
    "sg:city":"St Lucia",
    "sg:classifiers":[
        {
            "category":"Banks & Credit Unions",
            "subcategory":"Investment Brokerage",
            "type":"Services"
        }
    ],
    "sg:phone":"+61 7 3870 2895",
    "sg:postcode":"4067",
    "sg:province":"QLD",
    "wof:name":"Kam Chee Pty Ltd",
    "wof:placetype":"venue"
},
  "geometry": {"coordinates":[152.997772217,-27.4940738678],"type":"Point"}
}