{
  "type": "Feature",
  "properties": {
    "addr:full":"18 George St Heyfield VIC 3858",
    "addr:housenumber":"18",
    "addr:postcode":"3858",
    "addr:street":"George St",
    "iso:country":"AU",
    "sg:address":"18 George St",
    "sg:city":"Heyfield",
    "sg:classifiers":[
        {
            "category":"Food & Beverages",
            "subcategory":"Supermarket",
            "type":"Retail Goods"
        }
    ],
    "sg:phone":"+61 3 5148 2380",
    "sg:postcode":"3858",
    "sg:province":"VIC",
    "sg:tags":[
        "grocery",
        "store"
    ],
    "wof:name":"Tryhorn Supermarket",
    "wof:placetype":"venue"
},
  "geometry": {"coordinates":[146.78640747099999,-37.9806022644],"type":"Point"}
}