{
  "type": "Feature",
  "properties": {
    "addr:full":"311 Gray St Hamilton VIC 3300",
    "addr:housenumber":"311",
    "addr:postcode":"3300",
    "addr:street":"Gray St",
    "iso:country":"AU",
    "sg:address":"311 Gray St",
    "sg:city":"Hamilton",
    "sg:classifiers":[
        {
            "category":"Personal",
            "subcategory":"Massage",
            "type":"Services"
        }
    ],
    "sg:phone":"+61 425 707 949",
    "sg:postcode":"3300",
    "sg:province":"VIC",
    "sg:tags":[
        "therapy"
    ],
    "wof:name":"Suzanne Bickley",
    "wof:placetype":"venue"
},
  "geometry": {"coordinates":[142.03222656200001,-37.7389144897],"type":"Point"}
}