{
  "type": "Feature",
  "properties": {
    "addr:full":"164 Canterbury Rd Heathmont VIC 3135",
    "addr:housenumber":"164",
    "addr:postcode":"3135",
    "addr:street":"Canterbury Rd",
    "iso:country":"AU",
    "sg:address":"164 Canterbury Rd",
    "sg:city":"Heathmont",
    "sg:classifiers":[
        {
            "category":"Food & Beverages",
            "subcategory":"Specialty",
            "type":"Retail Goods"
        }
    ],
    "sg:phone":"+61 3 9729 5028",
    "sg:postcode":"3135",
    "sg:province":"VIC",
    "sg:tags":[
        "product",
        "health"
    ],
    "wof:name":"Just Healthy",
    "wof:placetype":"venue"
},
  "geometry": {"coordinates":[145.247192383,-37.8277587891],"type":"Point"}
}