{
  "type": "Feature",
  "properties": {
    "addr:full":"28 Hardy St Lilydale VIC 3140",
    "addr:housenumber":"28",
    "addr:postcode":"3140",
    "addr:street":"Hardy St",
    "iso:country":"AU",
    "sg:address":"28 Hardy St",
    "sg:city":"Lilydale",
    "sg:classifiers":[
        {
            "category":"Retail",
            "subcategory":"Repair Shop",
            "type":"Services"
        }
    ],
    "sg:phone":"+61 3 9739 7400",
    "sg:postcode":"3140",
    "sg:province":"VIC",
    "sg:tags":[
        "mending",
        "clothing",
        "alteration"
    ],
    "wof:name":"Fashion &#039;N&#039; Fit",
    "wof:placetype":"venue"
},
  "geometry": {"coordinates":[145.352096558,-37.7588119507],"type":"Point"}
}