{
  "type": "Feature",
  "properties": {
    "addr:full":"Trust Building 155 King St Sydney NSW 2000",
    "addr:housenumber":"155",
    "addr:postcode":"2000",
    "addr:street":"King St",
    "iso:country":"AU",
    "sg:address":"Trust Building 155 King St",
    "sg:city":"Sydney",
    "sg:classifiers":[
        {
            "category":"Recreation",
            "subcategory":"Sailing Club",
            "type":"Entertainment"
        }
    ],
    "sg:phone":"+61 2 9232 7672",
    "sg:postcode":"2000",
    "sg:province":"NSW",
    "sg:tags":[
        "merchant",
        "diamond"
    ],
    "wof:name":"Diamonds & Australian Opals Pty Ltd",
    "wof:placetype":"venue"
},
  "geometry": {"coordinates":[151.20982360799999,-33.8691902161],"type":"Point"}
}