{
  "type": "Feature",
  "properties": {
    "addr:full":"1 Diggers Ave Gladesville NSW 2111",
    "addr:housenumber":"1",
    "addr:postcode":"2111",
    "addr:street":"Diggers Ave",
    "iso:country":"AU",
    "sg:address":"1 Diggers Ave",
    "sg:city":"Gladesville",
    "sg:classifiers":[
        {
            "category":"Home & Garden",
            "subcategory":"Building Materials",
            "type":"Retail Goods"
        }
    ],
    "sg:phone":"+61 408 495 082",
    "sg:postcode":"2111",
    "sg:province":"NSW",
    "sg:tags":[
        "lawn",
        "cutting",
        "maintenance"
    ],
    "wof:name":"Terry Lawnmowing Services",
    "wof:placetype":"venue"
},
  "geometry": {"coordinates":[151.12950134299999,-33.8203773499],"type":"Point"}
}