{
  "type": "Feature",
  "properties": {
    "addr:full":"96 Gilles St Adelaide SA 5000",
    "addr:housenumber":"96",
    "addr:postcode":"5000",
    "addr:street":"Gilles St",
    "iso:country":"AU",
    "sg:address":"96 Gilles St",
    "sg:city":"Adelaide",
    "sg:classifiers":[
        {
            "category":"Organizations",
            "subcategory":"Professional Association",
            "type":"Services"
        }
    ],
    "sg:phone":"+61 8 8223 1668",
    "sg:postcode":"5000",
    "sg:province":"SA",
    "sg:tags":[
        "web",
        "internet"
    ],
    "wof:name":"Thewebexpert",
    "wof:placetype":"venue"
},
  "geometry": {"coordinates":[138.60398864699999,-34.9339904785],"type":"Point"}
}