{
  "type": "Feature",
  "properties": {
    "addr:full":"29 Beenong Rd Darlington WA 6070",
    "addr:housenumber":"29",
    "addr:postcode":"6070",
    "addr:street":"Beenong Rd",
    "iso:country":"AU",
    "sg:address":"29 Beenong Rd",
    "sg:city":"Darlington",
    "sg:classifiers":[
        {
            "category":"Shopping",
            "subcategory":"Stationery & Office Supplies",
            "type":"Retail Goods"
        }
    ],
    "sg:phone":"+61 8 9299 7164",
    "sg:postcode":"6070",
    "sg:province":"WA",
    "sg:tags":[
        "equipment",
        "display",
        "exhibition"
    ],
    "wof:name":"Indoor Greenery",
    "wof:placetype":"venue"
},
  "geometry": {"coordinates":[116.07496643099999,-31.9232292175],"type":"Point"}
}