{
  "type": "Feature",
  "properties": {
    "addr:full":"Suite 8, Heritage Plaza Arcade 400 Ruthven St Toowoomba QLD 4350",
    "addr:housenumber":"400",
    "addr:postcode":"4350",
    "addr:street":"Ruthven St",
    "iso:country":"AU",
    "sg:address":"Suite 8, Heritage Plaza Arcade 400 Ruthven St",
    "sg:city":"Toowoomba",
    "sg:classifiers":[
        {
            "category":"Banks & Credit Unions",
            "subcategory":"Financial Services",
            "type":"Services"
        }
    ],
    "sg:phone":"+61 7 4638 2081",
    "sg:postcode":"4350",
    "sg:province":"QLD",
    "sg:tags":[
        "planning"
    ],
    "sg:website":"http://www.aspirefc.com.au",
    "wof:name":"Aspire Financial Consulting Pty Ltd",
    "wof:placetype":"venue"
},
  "geometry": {"coordinates":[151.95228599999999,-27.568256],"type":"Point"}
}