{
  "type": "Feature",
  "properties": {
    "addr:full":"2 Loop Rd Werribee VIC 3030",
    "addr:housenumber":"2",
    "addr:postcode":"3030",
    "addr:street":"Loop Rd",
    "iso:country":"AU",
    "sg:address":"2 Loop Rd",
    "sg:city":"Werribee",
    "sg:classifiers":[
        {
            "category":"Wholesale",
            "subcategory":"Machinery & Supplies",
            "type":"Manufacturing & Wholesale Goods"
        }
    ],
    "sg:phone":"+61 3 9741 8050",
    "sg:postcode":"3030",
    "sg:province":"VIC",
    "sg:tags":[
        "equipment",
        "laboratory"
    ],
    "wof:name":"Designer Flow Controll",
    "wof:placetype":"venue"
},
  "geometry": {"coordinates":[144.66282699999999,-37.915836],"type":"Point"}
}