{
  "type": "Feature",
  "properties": {
    "addr:full":"19 Satinay St Keperra QLD 4054",
    "addr:housenumber":"19",
    "addr:postcode":"4054",
    "addr:street":"Satinay St",
    "iso:country":"AU",
    "sg:address":"19 Satinay St",
    "sg:city":"Keperra",
    "sg:classifiers":[
        {
            "category":"Home & Garden",
            "subcategory":"Building Materials",
            "type":"Retail Goods"
        }
    ],
    "sg:phone":"+61 7 3355 7167",
    "sg:postcode":"4054",
    "sg:province":"QLD",
    "sg:tags":[
        "anti-corrosive",
        "composition",
        "flooring"
    ],
    "wof:name":"Wally's Seamless Flooring",
    "wof:placetype":"venue"
},
  "geometry": {"coordinates":[152.953948975,-27.4140338898],"type":"Point"}
}