{
  "type": "Feature",
  "properties": {
    "addr:full":"Suite 2/ 109 Mathoura Rd Toorak VIC 3142",
    "addr:housenumber":"/ 109",
    "addr:postcode":"3142",
    "addr:street":"Mathoura Rd",
    "iso:country":"AU",
    "sg:address":"Suite 2/ 109 Mathoura Rd",
    "sg:city":"Toorak",
    "sg:classifiers":[
        {
            "category":"Health Services",
            "subcategory":"Doctor",
            "type":"Services"
        }
    ],
    "sg:phone":"+61 3 9827 4204",
    "sg:postcode":"3142",
    "sg:province":"VIC",
    "sg:tags":[
        "medical",
        "practitioner"
    ],
    "wof:name":"Allan Dr Andrew",
    "wof:placetype":"venue"
},
  "geometry": {"coordinates":[145.008010864,-37.8411560059],"type":"Point"}
}