{
  "type": "Feature",
  "properties": {
    "addr:full":"Lot 25 Loftus Pl Forster NSW 2428",
    "addr:postcode":"2428",
    "addr:street":"Pl",
    "iso:country":"AU",
    "sg:address":"Lot 25 Loftus Pl",
    "sg:city":"Forster",
    "sg:classifiers":[
        {
            "category":"Building & Trades",
            "subcategory":"Construction",
            "type":"Services"
        }
    ],
    "sg:phone":"+61 2 6554 7527",
    "sg:postcode":"2428",
    "sg:province":"NSW",
    "sg:tags":[
        "contractor"
    ],
    "wof:name":"Acosta Constructions",
    "wof:placetype":"venue"
},
  "geometry": {"coordinates":[152.51805100000001,-32.197163],"type":"Point"}
}