{
  "type": "Feature",
  "properties": {
    "addr:full":"983 Wellington St West Perth WA 6005",
    "addr:housenumber":"983",
    "addr:postcode":"6005",
    "addr:street":"Wellington St",
    "iso:country":"AU",
    "sg:address":"983 Wellington St",
    "sg:city":"West Perth",
    "sg:classifiers":[
        {
            "category":"Insurance",
            "subcategory":"Insurance Agent",
            "type":"Services"
        }
    ],
    "sg:phone":"+61 8 9321 3204",
    "sg:postcode":"6005",
    "sg:province":"WA",
    "sg:tags":[
        "broker"
    ],
    "wof:name":"Austral Risk Services",
    "wof:placetype":"venue"
},
  "geometry": {"coordinates":[115.84439086899999,-31.9465923309],"type":"Point"}
}