{
  "type": "Feature",
  "properties": {
    "addr:full":"154 Church St Corowa NSW 2646",
    "addr:housenumber":"154",
    "addr:postcode":"2646",
    "addr:street":"Church St",
    "iso:country":"AU",
    "sg:address":"154 Church St",
    "sg:city":"Corowa",
    "sg:classifiers":[
        {
            "category":"Building & Trades",
            "subcategory":"Construction",
            "type":"Services"
        }
    ],
    "sg:phone":"+61 2 6033 4076",
    "sg:postcode":"2646",
    "sg:province":"NSW",
    "sg:tags":[
        "contractor"
    ],
    "wof:name":"M J & K L Carlisle",
    "wof:placetype":"venue"
},
  "geometry": {"coordinates":[146.37403869600001,-36.0217056274],"type":"Point"}
}