{
  "type": "Feature",
  "properties": {
    "iso:country":"AU",
    "sg:address":"PO Box 484",
    "sg:city":"McLaren Vale",
    "sg:classifiers":[
        {
            "category":"Utilities",
            "subcategory":"Water",
            "type":"Services"
        }
    ],
    "sg:phone":"+61 8 8323 8585",
    "sg:postcode":"5171",
    "sg:province":"SA",
    "sg:tags":[
        "hot",
        "system"
    ],
    "wof:name":"McLaren Vale Hot Water & Plumbing",
    "wof:placetype":"venue"
},
  "geometry": {"coordinates":[138.53814697300001,-35.215511322],"type":"Point"}
}