{
  "type": "Feature",
  "properties": {
    "addr:full":"34 fraser Rd Applecross WA 6153",
    "addr:housenumber":"34",
    "addr:postcode":"6153",
    "addr:street":"Fraser Rd",
    "iso:country":"AU",
    "sg:address":"34 fraser Rd",
    "sg:city":"Applecross",
    "sg:classifiers":[
        {
            "category":"Building & Trades",
            "subcategory":"Construction",
            "type":"Services"
        }
    ],
    "sg:phone":"+61 8 9364 8816",
    "sg:postcode":"6153",
    "sg:province":"WA",
    "sg:tags":[
        "contractor"
    ],
    "wof:name":"River Homes & Building Co",
    "wof:placetype":"venue"
},
  "geometry": {"coordinates":[115.83432000000001,-32.009834],"type":"Point"}
}