{
  "type": "Feature",
  "properties": {
    "iso:country":"AU",
    "sg:address":"Unit 3/ 52 Maple Ave",
    "sg:city":"Forestville",
    "sg:classifiers":[
        {
            "category":"Autos & Motor Vehicles",
            "subcategory":"Automobile Sales",
            "type":"Retail Goods"
        }
    ],
    "sg:phone":"+61 8 8297 6777",
    "sg:postcode":"5035",
    "sg:province":"SA",
    "sg:tags":[
        "equipment",
        "trailer"
    ],
    "wof:name":"Trigg Bros Pty Ltd",
    "wof:placetype":"venue"
},
  "geometry": {"coordinates":[138.57925415,-34.9479675293],"type":"Point"}
}