{
  "type": "Feature",
  "properties": {
    "iso:country":"AU",
    "sg:address":"11 Hart St",
    "sg:city":"Lane Cove",
    "sg:classifiers":[
        {
            "category":"Home & Garden",
            "subcategory":"Building Materials",
            "type":"Retail Goods"
        }
    ],
    "sg:phone":"+61 414 642 691",
    "sg:postcode":"2066",
    "sg:province":"NSW",
    "sg:tags":[
        "lawn",
        "cutting",
        "maintenance"
    ],
    "wof:name":"Cutting Edge Property Maintenance",
    "wof:placetype":"venue"
},
  "geometry": {"coordinates":[151.161743164,-33.8034439087],"type":"Point"}
}