{
  "type": "Feature",
  "properties": {
    "addr:full":"552- 554 Botany Rd Alexandria NSW 2015",
    "addr:housenumber":"554",
    "addr:postcode":"2015",
    "addr:street":"Botany Rd",
    "iso:country":"AU",
    "sg:address":"552- 554 Botany Rd",
    "sg:city":"Alexandria",
    "sg:classifiers":[
        {
            "category":"Manufacturing",
            "subcategory":"Metals",
            "type":"Manufacturing & Wholesale Goods"
        }
    ],
    "sg:phone":"+61 2 9667 3003",
    "sg:postcode":"2015",
    "sg:province":"NSW",
    "sg:tags":[
        "casting"
    ],
    "wof:name":"Dintes Non-Ferrous Castings",
    "wof:placetype":"venue"
},
  "geometry": {"coordinates":[151.200515747,-33.9151496887],"type":"Point"}
}