{
  "type": "Feature",
  "properties": {
    "addr:full":"19 Palmer St North Mackay QLD 4740",
    "addr:housenumber":"19",
    "addr:postcode":"4740",
    "addr:street":"Palmer St",
    "iso:country":"AU",
    "sg:address":"19 Palmer St",
    "sg:city":"North Mackay",
    "sg:classifiers":[
        {
            "category":"Health Services",
            "subcategory":"Doctor",
            "type":"Services"
        }
    ],
    "sg:phone":"+61 7 4944 9507",
    "sg:postcode":"4740",
    "sg:province":"QLD",
    "sg:tags":[
        "medical",
        "practitioner"
    ],
    "wof:name":"Anderson C G",
    "wof:placetype":"venue"
},
  "geometry": {"coordinates":[149.166336,-21.15373],"type":"Point"}
}