{
  "type": "Feature",
  "properties": {
    "iso:country":"AU",
    "sg:address":"116 McLachlan St",
    "sg:city":"Orange",
    "sg:classifiers":[
        {
            "category":"Building & Trades",
            "subcategory":"Construction",
            "type":"Services"
        }
    ],
    "sg:phone":"+61 419 416 940",
    "sg:postcode":"2800",
    "sg:province":"NSW",
    "sg:tags":[
        "contractor"
    ],
    "wof:name":"Prestwidge D & V Builder",
    "wof:placetype":"venue"
},
  "geometry": {"coordinates":[149.10752868599999,-33.2870292664],"type":"Point"}
}