{
  "type": "Feature",
  "properties": {
    "addr:full":"199a North Rd Gardenvale VIC 3185",
    "addr:housenumber":"199a",
    "addr:postcode":"3185",
    "addr:street":"North Rd",
    "iso:country":"AU",
    "sg:address":"199a North Rd",
    "sg:city":"Gardenvale",
    "sg:classifiers":[
        {
            "category":"Health Services",
            "subcategory":"Dentist",
            "type":"Services"
        }
    ],
    "sg:phone":"+61 3 9596 8033",
    "sg:postcode":"3185",
    "sg:province":"VIC",
    "wof:name":"Bell A",
    "wof:placetype":"venue"
},
  "geometry": {"coordinates":[145.01139831500001,-37.9002532959],"type":"Point"}
}