{
  "type": "Feature",
  "properties": {
    "addr:full":"30 Arthur St Forestville NSW 2087",
    "addr:housenumber":"30",
    "addr:postcode":"2087",
    "addr:street":"Arthur St",
    "iso:country":"AU",
    "sg:address":"30 Arthur St",
    "sg:city":"Forestville",
    "sg:classifiers":[
        {
            "category":"Professional",
            "subcategory":"Art Services",
            "type":"Services"
        }
    ],
    "sg:phone":"+61 2 9452 4984",
    "sg:postcode":"2087",
    "sg:province":"NSW",
    "sg:tags":[
        "decorator",
        "painter"
    ],
    "wof:name":"Pigott's Painting Service Pty Ltd",
    "wof:placetype":"venue"
},
  "geometry": {"coordinates":[151.20582580600001,-33.7598075867],"type":"Point"}
}