{
  "type": "Feature",
  "properties": {
    "addr:full":"12 Carlisle Crt Hallett Cove SA 5158",
    "addr:housenumber":"12",
    "addr:postcode":"5158",
    "addr:street":"Carlisle Crt",
    "iso:country":"AU",
    "sg:address":"12 Carlisle Crt",
    "sg:city":"Hallett Cove",
    "sg:classifiers":[
        {
            "category":"Food & Beverages",
            "subcategory":"Specialty",
            "type":"Retail Goods"
        }
    ],
    "sg:phone":"+61 8 8384 8816",
    "sg:postcode":"5158",
    "sg:province":"SA",
    "sg:tags":[
        "product",
        "health"
    ],
    "wof:name":"Herbalife Hallett Cove",
    "wof:placetype":"venue"
},
  "geometry": {"coordinates":[138.491790772,-35.0920333862],"type":"Point"}
}