{
  "type": "Feature",
  "properties": {
    "addr:full":"10 Caribou Cl St Clair NSW 2759",
    "addr:housenumber":"10",
    "addr:postcode":"2759",
    "addr:street":"Caribou Cl St",
    "iso:country":"AU",
    "sg:address":"10 Caribou Cl",
    "sg:city":"St Clair",
    "sg:classifiers":[
        {
            "category":"Home & Garden",
            "subcategory":"Carpets & Floor Coverings",
            "type":"Retail Goods"
        }
    ],
    "sg:phone":"+61 412 045 180",
    "sg:postcode":"2759",
    "sg:province":"NSW",
    "sg:tags":[
        "tile",
        "wall",
        "layer"
    ],
    "wof:name":"Prestige Tiling Australia Pty Ltd",
    "wof:placetype":"venue"
},
  "geometry": {"coordinates":[150.77980041500001,-33.7973594666],"type":"Point"}
}