{
  "type": "Feature",
  "properties": {
    "addr:full":"30 Rooks Rd Nunawading VIC 3131",
    "addr:housenumber":"30",
    "addr:postcode":"3131",
    "addr:street":"Rooks Rd",
    "iso:country":"AU",
    "sg:address":"30 Rooks Rd",
    "sg:city":"Nunawading",
    "sg:classifiers":[
        {
            "category":"Retail",
            "subcategory":"Auto Repair",
            "type":"Services"
        }
    ],
    "sg:phone":"+61 3 9873 5571",
    "sg:postcode":"3131",
    "sg:province":"VIC",
    "sg:tags":[
        "bus",
        "truck"
    ],
    "wof:name":"Tandem Drive Truck Suspension Repairs Pty Ltd",
    "wof:placetype":"venue"
},
  "geometry": {"coordinates":[145.185302734,-37.8187713623],"type":"Point"}
}