{
  "type": "Feature",
  "properties": {
    "iso:country":"AU",
    "sg:address":"86 Alfred St",
    "sg:city":"Charleville",
    "sg:classifiers":[
        {
            "category":"Arena",
            "subcategory":"Sports Club",
            "type":"Entertainment"
        }
    ],
    "sg:phone":"+61 7 4654 3208",
    "sg:postcode":"4470",
    "sg:province":"QLD",
    "sg:tags":[
        "organisation",
        "sporting"
    ],
    "wof:name":"Department of Tourism, Sport and Racing",
    "wof:placetype":"venue"
},
  "geometry": {"coordinates":[146.24253845199999,-26.3996772766],"type":"Point"}
}