{
  "type": "Feature",
  "properties": {
    "addr:full":"Pine Rd Riana TAS 7316",
    "addr:postcode":"7316",
    "addr:street":"Pine Rd",
    "iso:country":"AU",
    "sg:address":"Pine Rd",
    "sg:city":"Riana",
    "sg:classifiers":[
        {
            "category":"Building & Trades",
            "subcategory":"Landscaping Services",
            "type":"Services"
        }
    ],
    "sg:phone":"+61 438 324 153",
    "sg:postcode":"7316",
    "sg:province":"TAS",
    "sg:tags":[
        "slashing",
        "contractor"
    ],
    "wof:name":"Graeme's Gardening Services",
    "wof:placetype":"venue"
},
  "geometry": {"coordinates":[146.00012207,-41.1830291748],"type":"Point"}
}