{
  "type": "Feature",
  "properties": {
    "iso:country":"AU",
    "sg:address":"PO Box 33",
    "sg:city":"Cannington",
    "sg:classifiers":[
        {
            "category":"Professional",
            "type":"Services"
        }
    ],
    "sg:phone":"+61 8 9356 7750",
    "sg:postcode":"6987",
    "sg:province":"WA",
    "sg:tags":[
        "control",
        "equipment",
        "traffic"
    ],
    "wof:name":"Carringtons Traffic Services",
    "wof:placetype":"venue"
},
  "geometry": {"coordinates":[115.939201,-32.019459],"type":"Point"}
}