{
  "type": "Feature",
  "properties": {
    "addr:full":"178 Haly St Kingaroy QLD 4610",
    "addr:housenumber":"178",
    "addr:postcode":"4610",
    "addr:street":"Haly St",
    "iso:country":"AU",
    "sg:address":"178 Haly St",
    "sg:city":"Kingaroy",
    "sg:classifiers":[
        {
            "category":"Manufacturing",
            "subcategory":"Motor Vehicles & Parts",
            "type":"Manufacturing & Wholesale Goods"
        }
    ],
    "sg:phone":"+61 7 4162 1611",
    "sg:postcode":"4610",
    "sg:province":"QLD",
    "sg:tags":[
        "replacement"
    ],
    "wof:name":"Max Askews Engine Reconditioning Service",
    "wof:placetype":"venue"
},
  "geometry": {"coordinates":[151.83833313,-26.5390548706],"type":"Point"}
}