{
  "type": "Feature",
  "properties": {
    "addr:full":"9, 28 Albany Hwy Victoria Park WA 6100",
    "addr:housenumber":"28",
    "addr:postcode":"6100",
    "addr:street":"9;Albany Hwy Victoria",
    "iso:country":"AU",
    "sg:address":"9, 28 Albany Hwy",
    "sg:city":"Victoria Park",
    "sg:classifiers":[
        {
            "category":"Social Services",
            "type":"Services"
        }
    ],
    "sg:phone":"+61 8 9354 9099",
    "sg:postcode":"6100",
    "sg:province":"WA",
    "sg:tags":[
        "disabled",
        "person",
        "equipment"
    ],
    "wof:name":"ADS Automation",
    "wof:placetype":"venue"
},
  "geometry": {"coordinates":[115.893379211,-31.9712257385],"type":"Point"}
}