{
  "type": "Feature",
  "properties": {
    "addr:full":"50 Tennyson St Williamstown North VIC 3016",
    "addr:housenumber":"50",
    "addr:postcode":"3016",
    "addr:street":"Tennyson St",
    "iso:country":"AU",
    "sg:address":"50 Tennyson St",
    "sg:city":"Williamstown North",
    "sg:classifiers":[
        {
            "category":"Building & Trades",
            "subcategory":"Plumbing",
            "type":"Services"
        }
    ],
    "sg:phone":"+61 3 9397 3333",
    "sg:postcode":"3016",
    "sg:province":"VIC",
    "sg:tags":[
        "pump",
        "repairer"
    ],
    "wof:name":"W.B. Marine Engineering Services Pty Ltd",
    "wof:placetype":"venue"
},
  "geometry": {"coordinates":[144.86035156200001,-37.8525733948],"type":"Point"}
}