{
  "type": "Feature",
  "properties": {
    "addr:full":"2 Inverness Ave Armadale VIC 3143",
    "addr:housenumber":"2",
    "addr:postcode":"3143",
    "addr:street":"Inverness Ave",
    "iso:country":"AU",
    "sg:address":"2 Inverness Ave",
    "sg:city":"Armadale",
    "sg:classifiers":[
        {
            "category":"Real Estate",
            "subcategory":"Architect",
            "type":"Services"
        }
    ],
    "sg:phone":"+61 3 9509 5746",
    "sg:postcode":"3143",
    "sg:province":"VIC",
    "wof:name":"Burch Ian",
    "wof:placetype":"venue"
},
  "geometry": {"coordinates":[145.02145385700001,-37.858669281],"type":"Point"}
}