{
  "type": "Feature",
  "properties": {
    "iso:country":"AU",
    "sg:address":"2/ 258 Evans Rd",
    "sg:city":"Salisbury",
    "sg:classifiers":[
        {
            "category":"Autos & Motor Vehicles",
            "subcategory":"Auto Supplies",
            "type":"Retail Goods"
        }
    ],
    "sg:phone":"+61 7 3255 5866",
    "sg:postcode":"4107",
    "sg:province":"QLD",
    "sg:tags":[
        "part",
        "cycles",
        "accessory"
    ],
    "wof:name":"Queensland Motorcycle Panel & Paint",
    "wof:placetype":"venue"
},
  "geometry": {"coordinates":[153.037200928,-27.5458049774],"type":"Point"}
}