{
  "type": "Feature",
  "properties": {
    "iso:country":"AU",
    "sg:address":"12 Halifax Drv",
    "sg:city":"Bunbury",
    "sg:classifiers":[
        {
            "category":"Education",
            "subcategory":"Special Training",
            "type":"Public Place"
        }
    ],
    "sg:phone":"+61 8 9725 7211",
    "sg:postcode":"6230",
    "sg:province":"WA",
    "sg:tags":[
        "development"
    ],
    "wof:name":"WA Skills Training",
    "wof:placetype":"venue"
},
  "geometry": {"coordinates":[115.669052,-33.359585],"type":"Point"}
}