{
  "type": "Feature",
  "properties": {
    "addr:full":"168 Chesterville Rd Moorabbin VIC 3189",
    "addr:housenumber":"168",
    "addr:postcode":"3189",
    "addr:street":"Chesterville Rd",
    "iso:country":"AU",
    "sg:address":"168 Chesterville Rd",
    "sg:city":"Moorabbin",
    "sg:classifiers":[
        {
            "category":"Shopping",
            "subcategory":"Clothing, Apparel, & Fashions",
            "type":"Retail Goods"
        }
    ],
    "sg:phone":"+61 3 9532 6010",
    "sg:postcode":"3189",
    "sg:province":"VIC",
    "sg:tags":[
        "accessory"
    ],
    "wof:name":"Australian Ribbon Suppliers Pty Ltd",
    "wof:placetype":"venue"
},
  "geometry": {"coordinates":[145.05894470199999,-37.9486999512],"type":"Point"}
}