{
  "type": "Feature",
  "properties": {
    "iso:country":"AU",
    "sg:address":"89 Sydney St",
    "sg:city":"Mackay",
    "sg:classifiers":[
        {
            "category":"Banks & Credit Unions",
            "subcategory":"Financial Services",
            "type":"Services"
        }
    ],
    "sg:phone":"+61 7 4953 5688",
    "sg:postcode":"4740",
    "sg:province":"QLD",
    "sg:tags":[
        "planning"
    ],
    "wof:name":"RetireInvest",
    "wof:placetype":"venue"
},
  "geometry": {"coordinates":[149.185913,-21.150356],"type":"Point"}
}