{
  "type": "Feature",
  "properties": {
    "addr:full":"34a Synnot St Werribee VIC 3030",
    "addr:housenumber":"34a",
    "addr:postcode":"3030",
    "addr:street":"Synnot St",
    "iso:country":"AU",
    "sg:address":"34a Synnot St",
    "sg:city":"Werribee",
    "sg:classifiers":[
        {
            "category":"Food & Beverages",
            "subcategory":"Specialty",
            "type":"Retail Goods"
        }
    ],
    "sg:phone":"+61 3 9741 0633",
    "sg:postcode":"3030",
    "sg:province":"VIC",
    "sg:tags":[
        "product",
        "health"
    ],
    "wof:name":"Absolutely Gluten Free",
    "wof:placetype":"venue"
},
  "geometry": {"coordinates":[144.66181900000001,-37.902348],"type":"Point"}
}