{
  "type": "Feature",
  "properties": {
    "iso:country":"AU",
    "sg:address":"39 Dickinson St",
    "sg:city":"Charlestown",
    "sg:classifiers":[
        {
            "category":"Travel",
            "subcategory":"Hotels & Motels",
            "type":"Entertainment"
        }
    ],
    "sg:phone":"+61 2 4953 7323",
    "sg:postcode":"2290",
    "sg:province":"NSW",
    "wof:name":"Charlestown Serviced Apartments",
    "wof:placetype":"venue"
},
  "geometry": {"coordinates":[151.698196411,-32.9643630981],"type":"Point"}
}