{
  "type": "Feature",
  "properties": {
    "iso:country":"AU",
    "sg:address":"40 Oroya St",
    "sg:city":"Boulder",
    "sg:classifiers":[
        {
            "category":"Real Estate",
            "subcategory":"Architect",
            "type":"Services"
        }
    ],
    "sg:phone":"+61 8 9093 3332",
    "sg:postcode":"6432",
    "sg:province":"WA",
    "sg:tags":[
        "building",
        "designer"
    ],
    "wof:name":"Design Works",
    "wof:placetype":"venue"
},
  "geometry": {"coordinates":[121.49620819099999,-30.7917251587],"type":"Point"}
}