{
  "type": "Feature",
  "properties": {
    "iso:country":"AU",
    "sg:address":"Suite 7 24 Ocean Rd",
    "sg:city":"Palm Beach",
    "sg:classifiers":[
        {
            "category":"Health Services",
            "subcategory":"Dentist",
            "type":"Services"
        }
    ],
    "sg:phone":"+61 2 9974 1088",
    "sg:postcode":"2108",
    "sg:province":"NSW",
    "wof:name":"Giblin John P",
    "wof:placetype":"venue"
},
  "geometry": {"coordinates":[151.324462891,-33.5982513428],"type":"Point"}
}