{
  "type": "Feature",
  "properties": {
    "addr:full":"Showroom, 302 Moreland Rd Brunswick VIC 3056",
    "addr:housenumber":"302",
    "addr:postcode":"3056",
    "addr:street":"Moreland Rd",
    "iso:country":"AU",
    "sg:address":"Showroom, 302 Moreland Rd",
    "sg:city":"Brunswick",
    "sg:classifiers":[
        {
            "category":"Manufacturing",
            "subcategory":"Furniture",
            "type":"Manufacturing & Wholesale Goods"
        }
    ],
    "sg:phone":"+61 3 9455 2006",
    "sg:postcode":"3056",
    "sg:province":"VIC",
    "sg:tags":[
        "builder",
        "designer",
        "custom"
    ],
    "sg:website":"http://www.christiancolefurniture.com.au",
    "wof:name":"Christian Cole Furniture",
    "wof:placetype":"venue"
},
  "geometry": {"coordinates":[144.955612183,-37.7542724609],"type":"Point"}
}