{
  "type": "Feature",
  "properties": {
    "iso:country":"AU",
    "sg:address":"57 Ashover Rd",
    "sg:city":"Rocklea",
    "sg:classifiers":[
        {
            "category":"Retail",
            "subcategory":"Storage",
            "type":"Services"
        }
    ],
    "sg:phone":"+61 7 3275 3011",
    "sg:postcode":"4106",
    "sg:province":"QLD",
    "wof:name":"Golden Bros",
    "wof:placetype":"venue"
},
  "geometry": {"coordinates":[153.00770568900001,-27.5607204437],"type":"Point"}
}