{
  "type": "Feature",
  "properties": {
    "addr:full":"Cnr Stockton & Donald Sts Nelson Bay NSW 2315",
    "addr:postcode":"2315",
    "addr:street":"Cnr",
    "iso:country":"AU",
    "sg:address":"Cnr Stockton & Donald Sts",
    "sg:city":"Nelson Bay",
    "sg:classifiers":[
        {
            "category":"Health Services",
            "subcategory":"Dentist",
            "type":"Services"
        }
    ],
    "sg:phone":"+61 2 4981 1755",
    "sg:postcode":"2315",
    "sg:province":"NSW",
    "wof:name":"Parsons Andrew",
    "wof:placetype":"venue"
},
  "geometry": {"coordinates":[152.14329499999999,-32.722809],"type":"Point"}
}