{
  "type": "Feature",
  "properties": {
    "iso:country":"AU",
    "sg:address":"\"Worrowing\" The Wool Rd",
    "sg:city":"Old Erowal Bay",
    "sg:classifiers":[
        {
            "category":"Farming",
            "subcategory":"Livestock Farm",
            "type":"Manufacturing & Wholesale Goods"
        }
    ],
    "sg:phone":"+61 2 4443 7174",
    "sg:postcode":"2540",
    "sg:province":"NSW",
    "sg:tags":[
        "agistment"
    ],
    "wof:name":"A & J Robertson",
    "wof:placetype":"venue"
},
  "geometry": {"coordinates":[150.619430542,-35.0916976929],"type":"Point"}
}