{
  "type": "Feature",
  "properties": {
    "addr:full":"RMB 2430 Tol Tol Rd Robinvale VIC 3549",
    "addr:postcode":"3549",
    "addr:street":"Tol Tol Rd",
    "iso:country":"AU",
    "sg:address":"RMB 2430 Tol Tol Rd",
    "sg:city":"Robinvale",
    "sg:classifiers":[
        {
            "category":"Farming",
            "subcategory":"Berry Farm",
            "type":"Manufacturing & Wholesale Goods"
        }
    ],
    "sg:phone":"+61 3 5026 3886",
    "sg:postcode":"3549",
    "sg:province":"VIC",
    "sg:tags":[
        "fruit",
        "grower"
    ],
    "wof:name":"Puleio D",
    "wof:placetype":"venue"
},
  "geometry": {"coordinates":[142.80877685600001,-34.6211929321],"type":"Point"}
}