{
  "type": "Feature",
  "properties": {
    "addr:full":"Boronia Rd Walliston WA 6076",
    "addr:postcode":"6076",
    "addr:street":"Boronia Rd",
    "iso:country":"AU",
    "sg:address":"Boronia Rd",
    "sg:city":"Walliston",
    "sg:classifiers":[
        {
            "category":"Retail",
            "subcategory":"Event Space",
            "type":"Services"
        }
    ],
    "sg:phone":"+61 8 9291 7811",
    "sg:postcode":"6076",
    "sg:province":"WA",
    "sg:tags":[
        "venue",
        "reception",
        "wedding"
    ],
    "wof:name":"Boronia Rooms",
    "wof:placetype":"venue"
},
  "geometry": {"coordinates":[116.075546265,-31.9985694885],"type":"Point"}
}