{
  "type": "Feature",
  "properties": {
    "addr:full":"384 Elizabeth St North Hobart TAS 7000",
    "addr:housenumber":"384",
    "addr:postcode":"7000",
    "addr:street":"Elizabeth St",
    "iso:country":"AU",
    "sg:address":"384 Elizabeth St",
    "sg:city":"North Hobart",
    "sg:classifiers":[
        {
            "category":"Health Services",
            "subcategory":"Health Practitioner",
            "type":"Services"
        }
    ],
    "sg:phone":"+61 3 6234 4530",
    "sg:postcode":"7000",
    "sg:province":"TAS",
    "sg:tags":[
        "reiki"
    ],
    "wof:name":"Ramsdale Pharmacy & Wellbeing Centre",
    "wof:placetype":"venue"
},
  "geometry": {"coordinates":[147.315383911,-42.8732643127],"type":"Point"}
}