{
  "type": "Feature",
  "properties": {
    "iso:country":"AU",
    "sg:address":"14 James St",
    "sg:city":"Windsor",
    "sg:classifiers":[
        {
            "category":"Shopping",
            "subcategory":"Clothing, Apparel, & Fashions",
            "type":"Retail Goods"
        }
    ],
    "sg:phone":"+61 3 9521 3140",
    "sg:postcode":"3181",
    "sg:province":"VIC",
    "sg:tags":[
        "boutique"
    ],
    "wof:name":"Mien Boutique",
    "wof:placetype":"venue"
},
  "geometry": {"coordinates":[144.993896484,-37.8549919128],"type":"Point"}
}