{
  "type": "Feature",
  "properties": {
    "iso:country":"AU",
    "sg:address":"65 Burfitt Rd",
    "sg:city":"Riverstone",
    "sg:classifiers":[
        {
            "category":"Manufacturing",
            "subcategory":"Furniture",
            "type":"Manufacturing & Wholesale Goods"
        }
    ],
    "sg:phone":"+61 416 155 291",
    "sg:postcode":"2765",
    "sg:province":"NSW",
    "sg:tags":[
        "builder",
        "designer",
        "custom"
    ],
    "wof:name":"S & P Cabinets",
    "wof:placetype":"venue"
},
  "geometry": {"coordinates":[150.859207153,-33.6931419373],"type":"Point"}
}