{
  "type": "Feature",
  "properties": {
    "addr:full":"15 Queens Park Rd Highton VIC 3216",
    "addr:housenumber":"15",
    "addr:postcode":"3216",
    "addr:street":"Queens Park Rd",
    "iso:country":"AU",
    "sg:address":"15 Queens Park Rd",
    "sg:city":"Highton",
    "sg:classifiers":[
        {
            "category":"Professional",
            "subcategory":"Computer Services",
            "type":"Services"
        }
    ],
    "sg:phone":"+61 418 762 762",
    "sg:postcode":"3216",
    "sg:province":"VIC",
    "sg:tags":[
        "consultant",
        "system"
    ],
    "wof:name":"Application Software Pty Ltd",
    "wof:placetype":"venue"
},
  "geometry": {"coordinates":[144.317230225,-38.1495933533],"type":"Point"}
}