{
  "type": "Feature",
  "properties": {
    "addr:full":"513 Burwood Hwy Vermont South VIC 3133",
    "addr:housenumber":"513",
    "addr:postcode":"3133",
    "addr:street":"Burwood Hwy",
    "iso:country":"AU",
    "sg:address":"513 Burwood Hwy",
    "sg:city":"Vermont South",
    "sg:classifiers":[
        {
            "category":"Health Services",
            "subcategory":"Doctor",
            "type":"Services"
        }
    ],
    "sg:phone":"+61 3 9803 1911",
    "sg:postcode":"3133",
    "sg:province":"VIC",
    "sg:tags":[
        "medical",
        "practitioner"
    ],
    "wof:name":"Pan Y K",
    "wof:placetype":"venue"
},
  "geometry": {"coordinates":[145.18374633799999,-37.8563652039],"type":"Point"}
}