{
  "type": "Feature",
  "properties": {
    "iso:country":"AU",
    "sg:address":"3 Talbot Rd",
    "sg:city":"Croydon Park",
    "sg:classifiers":[
        {
            "category":"Shopping",
            "subcategory":"Pets & Pet Supplies",
            "type":"Retail Goods"
        }
    ],
    "sg:phone":"+61 8 8346 2752",
    "sg:postcode":"5008",
    "sg:province":"SA",
    "sg:tags":[
        "dog"
    ],
    "wof:name":"Clean Cut Canine The",
    "wof:placetype":"venue"
},
  "geometry": {"coordinates":[138.575378,-34.88372],"type":"Point"}
}