{
  "type": "Feature",
  "properties": {
    "addr:full":"54 Market St Merimbula NSW 2548",
    "addr:housenumber":"54",
    "addr:postcode":"2548",
    "addr:street":"Market St",
    "iso:country":"AU",
    "sg:address":"54 Market St",
    "sg:city":"Merimbula",
    "sg:classifiers":[
        {
            "category":"Personal",
            "subcategory":"Beauty Salon",
            "type":"Services"
        }
    ],
    "sg:phone":"+61 2 6495 1223",
    "sg:postcode":"2548",
    "sg:province":"NSW",
    "sg:tags":[
        "hairdresser"
    ],
    "wof:name":"Top Reflections Hair & Beauty",
    "wof:placetype":"venue"
},
  "geometry": {"coordinates":[149.91046142600001,-36.8884887695],"type":"Point"}
}