{
  "type": "Feature",
  "properties": {
    "addr:full":"Shop 8, 1 Narellan Rd Narellan NSW 2567",
    "addr:housenumber":"shop;1",
    "addr:postcode":"2567",
    "addr:street":"Narellan Rd",
    "iso:country":"AU",
    "sg:address":"Shop 8, 1 Narellan Rd",
    "sg:city":"Narellan",
    "sg:classifiers":[
        {
            "category":"Travel",
            "subcategory":"Hotels & Motels",
            "type":"Entertainment"
        }
    ],
    "sg:phone":"+61 2 4647 3299",
    "sg:postcode":"2567",
    "sg:province":"NSW",
    "sg:tags":[
        "accommodation"
    ],
    "wof:name":"Stockmans Steak House",
    "wof:placetype":"venue"
},
  "geometry": {"coordinates":[150.77935790999999,-34.0576858521],"type":"Point"}
}