{
  "type": "Feature",
  "properties": {
    "addr:full":"46 Highbury Rd Burwood VIC 3125",
    "addr:housenumber":"46",
    "addr:postcode":"3125",
    "addr:street":"Highbury Rd",
    "iso:country":"AU",
    "sg:address":"46 Highbury Rd",
    "sg:city":"Burwood",
    "sg:classifiers":[
        {
            "category":"Retail",
            "subcategory":"Auto Repair",
            "type":"Services"
        }
    ],
    "sg:phone":"+61 3 9808 4066",
    "sg:postcode":"3125",
    "sg:province":"VIC",
    "sg:tags":[
        "repairer",
        "motor",
        "engineer"
    ],
    "wof:name":"Owen Ray Auto Service Pty Ltd",
    "wof:placetype":"venue"
},
  "geometry": {"coordinates":[145.10168457,-37.8542251587],"type":"Point"}
}