{
  "type": "Feature",
  "properties": {
    "addr:full":"Suite 1, 317 Parkway Ave Hamilton NSW 2303",
    "addr:housenumber":"317",
    "addr:postcode":"2303",
    "addr:street":"Parkway Ave",
    "iso:country":"AU",
    "sg:address":"Suite 1, 317 Parkway Ave",
    "sg:city":"Hamilton",
    "sg:classifiers":[
        {
            "category":"Health Services",
            "subcategory":"Doctor",
            "type":"Services"
        }
    ],
    "sg:phone":"+61 2 4962 1410",
    "sg:postcode":"2303",
    "sg:province":"NSW",
    "sg:tags":[
        "medical",
        "practitioner"
    ],
    "wof:name":"Mayne Laverty Pathology Collection Centres",
    "wof:placetype":"venue"
},
  "geometry": {"coordinates":[151.75292999999999,-32.92543],"type":"Point"}
}