{
  "type": "Feature",
  "properties": {
    "addr:full":"27- 37 Rae St Colac VIC 3250",
    "addr:housenumber":"37",
    "addr:postcode":"3250",
    "addr:street":"Rae St",
    "iso:country":"AU",
    "sg:address":"27- 37 Rae St",
    "sg:city":"Colac",
    "sg:classifiers":[
        {
            "category":"Autos & Motor Vehicles",
            "subcategory":"Auto Supplies",
            "type":"Retail Goods"
        }
    ],
    "sg:phone":"+61 3 5231 2655",
    "sg:postcode":"3250",
    "sg:province":"VIC",
    "sg:tags":[
        "tyre"
    ],
    "wof:name":"Yokohama",
    "wof:placetype":"venue"
},
  "geometry": {"coordinates":[143.588303,-38.342155],"type":"Point"}
}