{
  "type": "Feature",
  "properties": {
    "addr:full":"5E3/ 1 Lincoln St Lane Cove NSW 2066",
    "addr:housenumber":"5e3 / 1",
    "addr:postcode":"2066",
    "addr:street":"Lincoln St",
    "iso:country":"AU",
    "sg:address":"5E3/ 1 Lincoln St",
    "sg:city":"Lane Cove",
    "sg:classifiers":[
        {
            "category":"Retail",
            "subcategory":"Auto Repair",
            "type":"Services"
        }
    ],
    "sg:phone":"+61 2 9427 4453",
    "sg:postcode":"2066",
    "sg:province":"NSW",
    "sg:tags":[
        "clutch",
        "brake"
    ],
    "wof:name":"B & A F Automotive Services",
    "wof:placetype":"venue"
},
  "geometry": {"coordinates":[151.14614868199999,-33.8128395081],"type":"Point"}
}