{
  "type": "Feature",
  "properties": {
    "addr:full":"Shop 1, 527 Southpine Rd Everton Park QLD 4053",
    "addr:housenumber":"shop 1",
    "addr:postcode":"527;4053",
    "addr:street":"Southpine Rd",
    "iso:country":"AU",
    "sg:address":"Shop 1, 527 Southpine Rd",
    "sg:city":"Everton Park",
    "sg:classifiers":[
        {
            "category":"Food & Beverages",
            "subcategory":"Specialty",
            "type":"Retail Goods"
        }
    ],
    "sg:phone":"+61 7 3354 1066",
    "sg:postcode":"4053",
    "sg:province":"QLD",
    "sg:tags":[
        "product",
        "health"
    ],
    "wof:name":"AAA Universal Fitness Shop",
    "wof:placetype":"venue"
},
  "geometry": {"coordinates":[152.98692321799999,-27.3994598389],"type":"Point"}
}