{
  "type": "Feature",
  "properties": {
    "iso:country":"AU",
    "sg:address":"617 Bonogin Rd",
    "sg:city":"Bonogin",
    "sg:classifiers":[
        {
            "category":"Wholesale",
            "subcategory":"Apparel",
            "type":"Manufacturing & Wholesale Goods"
        }
    ],
    "sg:phone":"+61 7 5522 8233",
    "sg:postcode":"4213",
    "sg:province":"QLD",
    "sg:tags":[
        "wholesaler",
        "men's",
        "mfrs",
        "sportswear"
    ],
    "wof:name":"Essay Sports",
    "wof:placetype":"venue"
},
  "geometry": {"coordinates":[153.363571167,-28.11460495],"type":"Point"}
}