{
  "type": "Feature",
  "properties": {
    "iso:country":"AU",
    "sg:address":"Newell Hwy",
    "sg:city":"Narrabri",
    "sg:classifiers":[
        {
            "category":"Autos & Motor Vehicles",
            "subcategory":"Auto Supplies",
            "type":"Retail Goods"
        }
    ],
    "sg:phone":"+61 2 6792 2325",
    "sg:postcode":"2390",
    "sg:province":"NSW",
    "sg:tags":[
        "oil",
        "spirit"
    ],
    "wof:name":"Shell Co Of Aust Distributors",
    "wof:placetype":"venue"
},
  "geometry": {"coordinates":[149.76687622099999,-30.3389778137],"type":"Point"}
}