{
  "type": "Feature",
  "properties": {
    "iso:country":"AU",
    "sg:address":"Kenwyn St",
    "sg:city":"Hurstville",
    "sg:classifiers":[
        {
            "category":"Education",
            "subcategory":"School",
            "type":"Public Place"
        }
    ],
    "sg:phone":"+61 2 9587 3199",
    "sg:postcode":"2220",
    "sg:province":"NSW",
    "sg:tags":[
        "boy"
    ],
    "wof:name":"Hurstville Boys' Campus - Georges River College",
    "wof:placetype":"venue"
},
  "geometry": {"coordinates":[151.11117553700001,-33.9629478455],"type":"Point"}
}