{
  "type": "Feature",
  "properties": {
    "addr:full":"28 Jersey Rd Bayswater VIC 3153",
    "addr:housenumber":"28",
    "addr:postcode":"3153",
    "addr:street":"Jersey Rd",
    "iso:country":"AU",
    "sg:address":"28 Jersey Rd",
    "sg:city":"Bayswater",
    "sg:classifiers":[
        {
            "category":"Shopping",
            "type":"Retail Goods"
        }
    ],
    "sg:phone":"+61 3 9720 3877",
    "sg:postcode":"3153",
    "sg:province":"VIC",
    "sg:tags":[
        "equipment",
        "safety",
        "accessory"
    ],
    "wof:name":"Shairzal Pty Ltd",
    "wof:placetype":"venue"
},
  "geometry": {"coordinates":[145.279296875,-37.8421325684],"type":"Point"}
}