{
  "type": "Feature",
  "properties": {
    "addr:full":"16 Hazelwood Pde Ravenswood TAS 7250",
    "addr:housenumber":"16",
    "addr:postcode":"7250",
    "addr:street":"Hazelwood Pde",
    "iso:country":"AU",
    "sg:address":"16 Hazelwood Pde",
    "sg:city":"Ravenswood",
    "sg:classifiers":[
        {
            "category":"Professional",
            "subcategory":"Art Services",
            "type":"Services"
        }
    ],
    "sg:phone":"+61 419 117 364",
    "sg:postcode":"7250",
    "sg:province":"TAS",
    "sg:tags":[
        "decorator",
        "painter"
    ],
    "wof:name":"Allen BW & CD",
    "wof:placetype":"venue"
},
  "geometry": {"coordinates":[147.18089294399999,-41.4171981812],"type":"Point"}
}