{
  "type": "Feature",
  "properties": {
    "addr:full":"24 Merimbula Drv Merimbula NSW 2548",
    "addr:housenumber":"24",
    "addr:postcode":"2548",
    "addr:street":"Merimbula Drv",
    "iso:country":"AU",
    "sg:address":"24 Merimbula Drv",
    "sg:city":"Merimbula",
    "sg:classifiers":[
        {
            "category":"Travel",
            "subcategory":"Hotels & Motels",
            "type":"Entertainment"
        }
    ],
    "sg:phone":"+61 2 6495 3111",
    "sg:postcode":"2548",
    "sg:province":"NSW",
    "wof:name":"Summerhill Motor Inn",
    "wof:placetype":"venue"
},
  "geometry": {"coordinates":[149.90733337399999,-36.888053894],"type":"Point"}
}