{
  "type": "Feature",
  "properties": {
    "iso:country":"AU",
    "sg:address":"3 Mel St",
    "sg:city":"Berrimah",
    "sg:classifiers":[
        {
            "category":"Building & Trades",
            "subcategory":"Construction",
            "type":"Services"
        }
    ],
    "sg:phone":"+61 8 8947 4001",
    "sg:postcode":"0828",
    "sg:province":"NT",
    "sg:tags":[
        "contractor"
    ],
    "wof:name":"Bob Jay Builders",
    "wof:placetype":"venue"
},
  "geometry": {"coordinates":[130.92048645,-12.4392213821],"type":"Point"}
}