{
  "type": "Feature",
  "properties": {
    "iso:country":"AU",
    "sg:address":"Shop 1, 2558 Gold Coast Hwy",
    "sg:city":"Mermaid Beach",
    "sg:classifiers":[
        {
            "category":"Education",
            "subcategory":"Music School",
            "type":"Public Place"
        }
    ],
    "sg:phone":"+61 7 5526 6633",
    "sg:postcode":"4218",
    "sg:province":"QLD",
    "sg:tags":[
        "teacher"
    ],
    "wof:name":"Blue Note Guitars",
    "wof:placetype":"venue"
},
  "geometry": {"coordinates":[153.43341064399999,-28.0396461487],"type":"Point"}
}