{
  "type": "Feature",
  "properties": {
    "addr:full":"42 Ferny Ave Surfers Paradise QLD 4217",
    "addr:housenumber":"42",
    "addr:postcode":"4217",
    "addr:street":"Ferny Ave",
    "iso:country":"AU",
    "sg:address":"42 Ferny Ave",
    "sg:city":"Surfers Paradise",
    "sg:classifiers":[
        {
            "category":"Travel",
            "subcategory":"Hotels & Motels",
            "type":"Entertainment"
        }
    ],
    "sg:phone":"+61 7 5539 0444",
    "sg:postcode":"4217",
    "sg:province":"QLD",
    "sg:tags":[
        "accommodation"
    ],
    "wof:name":"Vibe Hotel Gold Coast",
    "wof:placetype":"venue"
},
  "geometry": {"coordinates":[153.426834106,-27.9993782043],"type":"Point"}
}