{
  "type": "Feature",
  "properties": {
    "addr:full":"59 Carville St Annerley QLD 4103",
    "addr:housenumber":"59",
    "addr:postcode":"4103",
    "addr:street":"Carville St",
    "iso:country":"AU",
    "sg:address":"59 Carville St",
    "sg:city":"Annerley",
    "sg:classifiers":[
        {
            "category":"Building & Trades",
            "subcategory":"Construction",
            "type":"Services"
        }
    ],
    "sg:phone":"+61 7 3391 6660",
    "sg:postcode":"4103",
    "sg:province":"QLD",
    "sg:tags":[
        "contractor"
    ],
    "wof:name":"Ryan M",
    "wof:placetype":"venue"
},
  "geometry": {"coordinates":[153.033935547,-27.5023708344],"type":"Point"}
}