{
  "type": "Feature",
  "properties": {
    "addr:full":"36-38 Old Barrenjoey Rd Avalon NSW 2107",
    "addr:housenumber":"36-38",
    "addr:postcode":"2107",
    "addr:street":"Old Barrenjoey Rd",
    "iso:country":"AU",
    "sg:address":"36-38 Old Barrenjoey Rd",
    "sg:city":"Avalon",
    "sg:classifiers":[
        {
            "category":"Professional",
            "subcategory":"Accounting & Tax Preparation",
            "type":"Services"
        }
    ],
    "sg:phone":"+61 2 9918 2861",
    "sg:postcode":"2107",
    "sg:province":"NSW",
    "sg:tags":[
        "bookkeeping"
    ],
    "wof:name":"KHJ-The Mobile Bookkeeper",
    "wof:placetype":"venue"
},
  "geometry": {"coordinates":[151.328414917,-33.6382751465],"type":"Point"}
}