{
  "type": "Feature",
  "properties": {
    "iso:country":"AU",
    "sg:address":"114 Main Rd",
    "sg:city":"Hepburn Springs",
    "sg:classifiers":[
        {
            "category":"Fast Food",
            "type":"Food & Drink"
        }
    ],
    "sg:phone":"+61 3 5348 1163",
    "sg:postcode":"3461",
    "sg:province":"VIC",
    "sg:tags":[
        "away",
        "take"
    ],
    "wof:name":"Hepburn Jasmine Thai Restaurant",
    "wof:placetype":"venue"
},
  "geometry": {"coordinates":[144.26185607900001,-37.3860321045],"type":"Point"}
}