{
  "type": "Feature",
  "properties": {
    "addr:full":"Palm Ave Millaa Millaa QLD 4886",
    "addr:postcode":"4886",
    "addr:street":"Palm Ave;Millaa",
    "iso:country":"AU",
    "sg:address":"Palm Ave",
    "sg:city":"Millaa Millaa",
    "sg:classifiers":[
        {
            "category":"Education",
            "subcategory":"School",
            "type":"Public Place"
        }
    ],
    "sg:phone":"+61 7 4097 2167",
    "sg:postcode":"4886",
    "sg:province":"QLD",
    "sg:tags":[
        "state",
        "except",
        "nsw"
    ],
    "wof:name":"Millaa Millaa Primary School",
    "wof:placetype":"venue"
},
  "geometry": {"coordinates":[145.61163330100001,-17.5123386383],"type":"Point"}
}