{
  "type": "Feature",
  "properties": {
    "iso:country":"AU",
    "sg:address":"5 Nina Crt",
    "sg:city":"Salisbury Heights",
    "sg:classifiers":[
        {
            "category":"Building & Trades",
            "subcategory":"Cleaning & Sanitation",
            "type":"Services"
        }
    ],
    "sg:phone":"+61 8 8285 4492",
    "sg:postcode":"5109",
    "sg:province":"SA",
    "sg:tags":[
        "cleaner",
        "repairer",
        "roof"
    ],
    "wof:name":"Revell Home Improvements",
    "wof:placetype":"venue"
},
  "geometry": {"coordinates":[138.682495117,-34.7688903809],"type":"Point"}
}