{
  "type": "Feature",
  "properties": {
    "iso:country":"AU",
    "sg:address":"5 Charlton Ave",
    "sg:city":"Chipping Norton",
    "sg:classifiers":[
        {
            "category":"Building & Trades",
            "subcategory":"Plumbing",
            "type":"Services"
        }
    ],
    "sg:phone":"+61 2 9724 9547",
    "sg:postcode":"2170",
    "sg:province":"NSW",
    "sg:tags":[
        "plumber",
        "gasfitters"
    ],
    "wof:name":"Crook Bros Plumbing & Draining",
    "wof:placetype":"venue"
},
  "geometry": {"coordinates":[150.952270508,-33.9139671326],"type":"Point"}
}