{
  "type": "Feature",
  "properties": {
    "addr:full":"Level 1, Commonwealth Centre, 20 Wirraway Pde Inala QLD 4077",
    "addr:housenumber":"20",
    "addr:postcode":"4077",
    "addr:street":"Wirraway Pde",
    "iso:country":"AU",
    "sg:address":"Level 1, Commonwealth Centre, 20 Wirraway Pde",
    "sg:city":"Inala",
    "sg:classifiers":[
        {
            "category":"Professional",
            "subcategory":"Employment Agencies",
            "type":"Services"
        }
    ],
    "sg:phone":"+61 7 3714 6100",
    "sg:postcode":"4077",
    "sg:province":"QLD",
    "wof:name":"Sarina Russo Job Access",
    "wof:placetype":"venue"
},
  "geometry": {"coordinates":[152.974487305,-27.6013889313],"type":"Point"}
}