{
  "type": "Feature",
  "properties": {
    "addr:full":"795 Rathdown St Carlton North VIC 3054",
    "addr:housenumber":"795",
    "addr:postcode":"3054",
    "addr:street":"Rathdown St",
    "iso:country":"AU",
    "sg:address":"795 Rathdown St",
    "sg:city":"Carlton North",
    "sg:classifiers":[
        {
            "category":"Personal",
            "subcategory":"Beauty Salon",
            "type":"Services"
        }
    ],
    "sg:phone":"+61 3 9387 2071",
    "sg:postcode":"3054",
    "sg:province":"VIC",
    "wof:name":"Anna Lee Beauty",
    "wof:placetype":"venue"
},
  "geometry": {"coordinates":[144.97224426299999,-37.7859039307],"type":"Point"}
}