{
  "type": "Feature",
  "properties": {
    "addr:full":"5 Teak Crt Woodvale WA 6026",
    "addr:housenumber":"5",
    "addr:postcode":"6026",
    "addr:street":"Teak Crt",
    "iso:country":"AU",
    "sg:address":"5 Teak Crt",
    "sg:city":"Woodvale",
    "sg:classifiers":[
        {
            "category":"Professional",
            "subcategory":"Computer Services",
            "type":"Services"
        }
    ],
    "sg:phone":"+61 8 9309 2356",
    "sg:postcode":"6026",
    "sg:province":"WA",
    "sg:tags":[
        "equipment",
        "networking",
        "installation"
    ],
    "wof:name":"Computer Accounting Doctor",
    "wof:placetype":"venue"
},
  "geometry": {"coordinates":[115.796188355,-31.7866191864],"type":"Point"}
}