{
  "type": "Feature",
  "properties": {
    "iso:country":"AU",
    "sg:address":"88 Wingfield Rd",
    "sg:city":"Wingfield",
    "sg:classifiers":[
        {
            "category":"Professional",
            "subcategory":"Engineering",
            "type":"Services"
        }
    ],
    "sg:phone":"+61 8 8345 0797",
    "sg:postcode":"5013",
    "sg:province":"SA",
    "sg:tags":[
        "engineer"
    ],
    "wof:name":"Titan Pacific Co",
    "wof:placetype":"venue"
},
  "geometry": {"coordinates":[138.55082702600001,-34.8414344788],"type":"Point"}
}