{
  "type": "Feature",
  "properties": {
    "addr:full":"41 - 47 Fitzroy St Grafton NSW 2460",
    "addr:housenumber":"47",
    "addr:postcode":"2460",
    "addr:street":"Fitzroy St",
    "iso:country":"AU",
    "sg:address":"41 - 47 Fitzroy St",
    "sg:city":"Grafton",
    "sg:classifiers":[
        {
            "category":"Wholesale",
            "subcategory":"Electrical",
            "type":"Manufacturing & Wholesale Goods"
        }
    ],
    "sg:phone":"+61 2 6642 4300",
    "sg:postcode":"2460",
    "sg:province":"NSW",
    "sg:tags":[
        "wholesaler",
        "mfrs",
        "accessory"
    ],
    "wof:name":"Cetnaj Pty Ltd",
    "wof:placetype":"venue"
},
  "geometry": {"coordinates":[152.935745239,-29.692527771],"type":"Point"}
}