{
  "type": "Feature",
  "properties": {
    "addr:full":"42 Abbott St Cairns QLD 4870",
    "addr:housenumber":"42",
    "addr:postcode":"4870",
    "addr:street":"Abbott St",
    "iso:country":"AU",
    "sg:address":"42 Abbott St",
    "sg:city":"Cairns",
    "sg:classifiers":[
        {
            "category":"Professional",
            "type":"Services"
        }
    ],
    "sg:phone":"+61 7 4031 6648",
    "sg:postcode":"4870",
    "sg:province":"QLD",
    "sg:tags":[
        "courier"
    ],
    "wof:name":"U.P.S.",
    "wof:placetype":"venue"
},
  "geometry": {"coordinates":[145.77711486800001,-16.9213428497],"type":"Point"}
}