{
  "type": "Feature",
  "properties": {
    "iso:country":"AU",
    "sg:address":"Shp 2/ 825 Ballarat Rd",
    "sg:city":"Deer Park",
    "sg:classifiers":[
        {
            "category":"Shopping",
            "subcategory":"Party Supplies",
            "type":"Retail Goods"
        }
    ],
    "sg:phone":"+61 3 9449 5372",
    "sg:postcode":"3023",
    "sg:province":"VIC",
    "wof:name":"Lets Party",
    "wof:placetype":"venue"
},
  "geometry": {"coordinates":[144.77250699999999,-37.770222],"type":"Point"}
}