{
  "type": "Feature",
  "properties": {
    "addr:full":"670 Mount Alexander Rd Moonee Ponds VIC 3039",
    "addr:housenumber":"670",
    "addr:postcode":"3039",
    "addr:street":"Mount Alexander Rd",
    "iso:country":"AU",
    "sg:address":"670 Mount Alexander Rd",
    "sg:city":"Moonee Ponds",
    "sg:classifiers":[
        {
            "category":"Organizations",
            "subcategory":"Labor Organization",
            "type":"Services"
        }
    ],
    "sg:phone":"+61 3 9326 0866",
    "sg:postcode":"3039",
    "sg:province":"VIC",
    "sg:tags":[
        "union"
    ],
    "wof:name":"Flight Attendants Association Of Australia",
    "wof:placetype":"venue"
},
  "geometry": {"coordinates":[144.92585800000001,-37.769398],"type":"Point"}
}