{
  "type": "Feature",
  "properties": {
    "addr:full":"Main St Quambatook VIC 3540",
    "addr:postcode":"3540",
    "addr:street":"Main St",
    "iso:country":"AU",
    "sg:address":"Main St",
    "sg:city":"Quambatook",
    "sg:classifiers":[
        {
            "category":"Social Services",
            "subcategory":"Child Care",
            "type":"Services"
        }
    ],
    "sg:phone":"+61 3 5457 1348",
    "sg:postcode":"3540",
    "sg:province":"VIC",
    "sg:tags":[
        "support",
        "health"
    ],
    "wof:name":"Maternal & Child Health Centres",
    "wof:placetype":"venue"
},
  "geometry": {"coordinates":[143.52032470699999,-35.8487510681],"type":"Point"}
}