{
  "type": "Feature",
  "properties": {
    "addr:full":"3rd Floor Winlow House 75 Woods St Darwin NT 0800",
    "addr:housenumber":"75",
    "addr:postcode":"nt 0800",
    "addr:street":"Woods St",
    "iso:country":"AU",
    "sg:address":"3rd Floor Winlow House 75 Woods St",
    "sg:city":"Darwin",
    "sg:classifiers":[
        {
            "category":"Professional",
            "subcategory":"Engineering",
            "type":"Services"
        }
    ],
    "sg:phone":"+61 8 8981 1100",
    "sg:postcode":"0800",
    "sg:province":"NT",
    "sg:tags":[
        "consulting",
        "engineer"
    ],
    "wof:name":"Van Der Meer Consulting",
    "wof:placetype":"venue"
},
  "geometry": {"coordinates":[130.840576172,-12.4581918716],"type":"Point"}
}