{
  "type": "Feature",
  "properties": {
    "addr:full":"21 Driscoll St Rosetta TAS 7010",
    "addr:housenumber":"21",
    "addr:postcode":"7010",
    "addr:street":"Driscoll St",
    "iso:country":"AU",
    "sg:address":"21 Driscoll St",
    "sg:city":"Rosetta",
    "sg:classifiers":[
        {
            "category":"Professional",
            "subcategory":"Management & Consulting",
            "type":"Services"
        }
    ],
    "sg:phone":"+61 3 6273 4742",
    "sg:postcode":"7010",
    "sg:province":"TAS",
    "sg:tags":[
        "consultant",
        "migration"
    ],
    "wof:name":"International Business & Introduction Brokers",
    "wof:placetype":"venue"
},
  "geometry": {"coordinates":[147.255981445,-42.8173828125],"type":"Point"}
}