{
  "type": "Feature",
  "properties": {
    "addr:full":"224 North St Grafton NSW 2460",
    "addr:housenumber":"224",
    "addr:postcode":"2460",
    "addr:street":"North St",
    "iso:country":"AU",
    "sg:address":"224 North St",
    "sg:city":"Grafton",
    "sg:classifiers":[
        {
            "category":"Building & Trades",
            "subcategory":"Plumbing",
            "type":"Services"
        }
    ],
    "sg:phone":"+61 407 254 094",
    "sg:postcode":"2460",
    "sg:province":"NSW",
    "sg:tags":[
        "plumber",
        "gasfitters"
    ],
    "wof:name":"Woods Craig",
    "wof:placetype":"venue"
},
  "geometry": {"coordinates":[152.934036255,-29.6702709198],"type":"Point"}
}