{
  "type": "Feature",
  "properties": {
    "addr:full":"290 North Rd Eastwood NSW 2122",
    "addr:housenumber":"290",
    "addr:postcode":"2122",
    "addr:street":"North Rd",
    "iso:country":"AU",
    "sg:address":"290 North Rd",
    "sg:city":"Eastwood",
    "sg:classifiers":[
        {
            "category":"Real Estate",
            "subcategory":"Real Estate Agent",
            "type":"Services"
        }
    ],
    "sg:phone":"+61 2 9804 1190",
    "sg:postcode":"2122",
    "sg:province":"NSW",
    "wof:name":"Award Group Real Estate",
    "wof:placetype":"venue"
},
  "geometry": {"coordinates":[151.09466552699999,-33.7841720581],"type":"Point"}
}