{
  "type": "Feature",
  "properties": {
    "addr:full":"Cnr Bligh Pl 88 Clovelly Rd Randwick NSW 2031",
    "addr:housenumber":"88",
    "addr:postcode":"2031",
    "addr:street":"Bligh Pl;Clovelly Rd",
    "iso:country":"AU",
    "sg:address":"Cnr Bligh Pl 88 Clovelly Rd",
    "sg:city":"Randwick",
    "sg:classifiers":[
        {
            "category":"Retail",
            "subcategory":"Auto Repair",
            "type":"Services"
        }
    ],
    "sg:phone":"+61 2 9326 4200",
    "sg:postcode":"2031",
    "sg:province":"NSW",
    "sg:tags":[
        "repairer",
        "motor",
        "engineer"
    ],
    "wof:name":"Clovelly Automotive Services Pty Ltd",
    "wof:placetype":"venue"
},
  "geometry": {"coordinates":[151.24830627399999,-33.9087333679],"type":"Point"}
}