{
  "type": "Feature",
  "properties": {
    "addr:full":"171 Wattletree Rd Malvern VIC 3144",
    "addr:housenumber":"171",
    "addr:postcode":"3144",
    "addr:street":"Wattletree Rd",
    "iso:country":"AU",
    "sg:address":"171 Wattletree Rd",
    "sg:city":"Malvern",
    "sg:classifiers":[
        {
            "category":"Social Services",
            "subcategory":"Child Care",
            "type":"Services"
        }
    ],
    "sg:phone":"+61 3 9509 2800",
    "sg:postcode":"3144",
    "sg:province":"VIC",
    "wof:name":"Wattletree House Children's Centre",
    "wof:placetype":"venue"
},
  "geometry": {"coordinates":[145.031906128,-37.8626861572],"type":"Point"}
}