{
  "type": "Feature",
  "properties": {
    "addr:full":"108 William St Bathurst NSW 2795",
    "addr:housenumber":"108",
    "addr:postcode":"2795",
    "addr:street":"William St",
    "iso:country":"AU",
    "sg:address":"108 William St",
    "sg:city":"Bathurst",
    "sg:classifiers":[
        {
            "category":"Personal",
            "subcategory":"Beauty Salon",
            "type":"Services"
        }
    ],
    "sg:phone":"+61 2 6331 1411",
    "sg:postcode":"2795",
    "sg:province":"NSW",
    "sg:tags":[
        "hairdresser"
    ],
    "wof:name":"Royal Hair Studio",
    "wof:placetype":"venue"
},
  "geometry": {"coordinates":[149.57929992699999,-33.4191513062],"type":"Point"}
}