{
  "type": "Feature",
  "properties": {
    "addr:full":"513 Torrens Rd Woodville SA 5011",
    "addr:housenumber":"513",
    "addr:postcode":"5011",
    "addr:street":"Torrens Rd",
    "iso:country":"AU",
    "sg:address":"513 Torrens Rd",
    "sg:city":"Woodville",
    "sg:classifiers":[
        {
            "category":"Education",
            "subcategory":"School",
            "type":"Public Place"
        }
    ],
    "sg:phone":"+61 8 8345 4530",
    "sg:postcode":"5011",
    "sg:province":"SA",
    "sg:tags":[
        "state",
        "except",
        "nsw"
    ],
    "wof:name":"Woodville Special School",
    "wof:placetype":"venue"
},
  "geometry": {"coordinates":[138.54444885300001,-34.8728561401],"type":"Point"}
}