{
  "type": "Feature",
  "properties": {
    "addr:full":"623 High St Kew VIC 3101",
    "addr:housenumber":"623",
    "addr:postcode":"3101",
    "addr:street":"High St",
    "iso:country":"AU",
    "sg:address":"623 High St",
    "sg:city":"Kew",
    "sg:classifiers":[
        {
            "category":"Health Services",
            "subcategory":"Health Practitioner",
            "type":"Services"
        }
    ],
    "sg:phone":"+61 3 9890 7711",
    "sg:postcode":"3101",
    "sg:province":"VIC",
    "sg:tags":[
        "psychologist"
    ],
    "wof:name":"Garnys Halina",
    "wof:placetype":"venue"
},
  "geometry": {"coordinates":[145.02818298299999,-37.8081550598],"type":"Point"}
}