{
  "type": "Feature",
  "properties": {
    "addr:full":"72 Shettleston St Rocklea QLD 4106",
    "addr:housenumber":"72",
    "addr:postcode":"4106",
    "addr:street":"Shettleston St",
    "iso:country":"AU",
    "sg:address":"72 Shettleston St",
    "sg:city":"Rocklea",
    "sg:classifiers":[
        {
            "category":"Retail",
            "subcategory":"Auto Repair",
            "type":"Services"
        }
    ],
    "sg:phone":"+61 7 3277 7087",
    "sg:postcode":"4106",
    "sg:province":"QLD",
    "sg:tags":[
        "repairer",
        "motor",
        "engineer"
    ],
    "wof:name":"Rocklea Radiator Service",
    "wof:placetype":"venue"
},
  "geometry": {"coordinates":[153.00276184099999,-27.5627918243],"type":"Point"}
}