{
  "type": "Feature",
  "properties": {
    "addr:full":"Cnr Aurora Ave & Yass Rd Queanbeyan ACT 2620",
    "addr:postcode":"2620",
    "addr:street":"Cnr Aurora Ave & Yass Rd",
    "iso:country":"AU",
    "sg:address":"Cnr Aurora Ave & Yass Rd",
    "sg:city":"Queanbeyan",
    "sg:classifiers":[
        {
            "category":"Industrial Area",
            "type":"Public Place"
        }
    ],
    "sg:phone":"+61 2 6298 1655",
    "sg:postcode":"2620",
    "sg:province":"ACT",
    "sg:tags":[
        "rural",
        "shed"
    ],
    "wof:name":"Sheds Plus",
    "wof:placetype":"venue"
},
  "geometry": {"coordinates":[149.24307250999999,-35.3393211365],"type":"Point"}
}