{
  "type": "Feature",
  "properties": {
    "addr:full":"138 Castle Hill Rd West Pennant Hills NSW 2125",
    "addr:housenumber":"138",
    "addr:postcode":"2125",
    "addr:street":"Castle Hill Rd",
    "iso:country":"AU",
    "sg:address":"138 Castle Hill Rd",
    "sg:city":"West Pennant Hills",
    "sg:classifiers":[
        {
            "category":"Retail",
            "subcategory":"Veterinary Services",
            "type":"Services"
        }
    ],
    "sg:phone":"+61 2 9484 3004",
    "sg:postcode":"2125",
    "sg:province":"NSW",
    "sg:tags":[
        "surgeon"
    ],
    "wof:name":"West Pennant Hills Veterinary Hospital",
    "wof:placetype":"venue"
},
  "geometry": {"coordinates":[151.03733825699999,-33.7396240234],"type":"Point"}
}