{
  "type": "Feature",
  "properties": {
    "addr:full":"27 Wollongong St Fyshwick ACT 2609",
    "addr:housenumber":"27",
    "addr:postcode":"2609",
    "addr:street":"Wollongong St",
    "iso:country":"AU",
    "sg:address":"27 Wollongong St",
    "sg:city":"Fyshwick",
    "sg:classifiers":[
        {
            "category":"Manufacturing",
            "subcategory":"Paper Products",
            "type":"Manufacturing & Wholesale Goods"
        }
    ],
    "sg:phone":"+61 2 6280 4887",
    "sg:postcode":"2609",
    "sg:province":"ACT",
    "sg:tags":[
        "machine",
        "shredding",
        "cutting"
    ],
    "wof:name":"Amalgamated Business Machines",
    "wof:placetype":"venue"
},
  "geometry": {"coordinates":[149.177734375,-35.3248329163],"type":"Point"}
}