{
  "type": "Feature",
  "properties": {
    "addr:full":"364 Pacific Hwy Belmont NSW 2280",
    "addr:housenumber":"364",
    "addr:postcode":"2280",
    "addr:street":"Pacific Hwy",
    "iso:country":"AU",
    "sg:address":"364 Pacific Hwy",
    "sg:city":"Belmont",
    "sg:classifiers":[
        {
            "category":"Building & Trades",
            "subcategory":"Construction",
            "type":"Services"
        }
    ],
    "sg:phone":"+61 2 4945 0180",
    "sg:postcode":"2280",
    "sg:province":"NSW",
    "sg:tags":[
        "contractor"
    ],
    "wof:name":"Graph Building",
    "wof:placetype":"venue"
},
  "geometry": {"coordinates":[151.660766602,-33.0298957825],"type":"Point"}
}