{
  "type": "Feature",
  "properties": {
    "iso:country":"AU",
    "sg:address":"Bushy La",
    "sg:city":"Southbrook",
    "sg:classifiers":[
        {
            "category":"Farming",
            "subcategory":"Farm",
            "type":"Manufacturing & Wholesale Goods"
        }
    ],
    "sg:phone":"+61 7 4691 0148",
    "sg:postcode":"4352",
    "sg:province":"QLD",
    "sg:tags":[
        "farmer"
    ],
    "wof:name":"Paul C Adams",
    "wof:placetype":"venue"
},
  "geometry": {"coordinates":[151.78270000000001,-27.76819],"type":"Point"}
}