{
  "type": "Feature",
  "properties": {
    "addr:full":"410 Unley Rd Unley Park SA 5061",
    "addr:housenumber":"410",
    "addr:postcode":"5061",
    "addr:street":"Unley Rd",
    "iso:country":"AU",
    "sg:address":"410 Unley Rd",
    "sg:city":"Unley Park",
    "sg:classifiers":[
        {
            "category":"Retail",
            "subcategory":"Laundry & Dry Cleaning",
            "type":"Services"
        }
    ],
    "sg:phone":"+61 8 8172 1277",
    "sg:postcode":"5061",
    "sg:province":"SA",
    "sg:tags":[
        "ironing"
    ],
    "wof:name":"Chehade Karl Dry Cleaning Pty Ltd",
    "wof:placetype":"venue"
},
  "geometry": {"coordinates":[138.60839843799999,-34.9644126892],"type":"Point"}
}