{
  "type": "Feature",
  "properties": {
    "addr:full":"Shp2/ 72 Central Ave Oak Flats NSW 2529",
    "addr:housenumber":"72",
    "addr:postcode":"2529",
    "addr:street":"Central Ave Oak Flats",
    "iso:country":"AU",
    "sg:address":"Shp2/ 72 Central Ave",
    "sg:city":"Oak Flats",
    "sg:classifiers":[
        {
            "category":"Cafe",
            "type":"Food & Drink"
        }
    ],
    "sg:phone":"+61 2 4256 1999",
    "sg:postcode":"2529",
    "sg:province":"NSW",
    "wof:name":"Central Cafe",
    "wof:placetype":"venue"
},
  "geometry": {"coordinates":[150.81932067899999,-34.5634536743],"type":"Point"}
}