{
  "type": "Feature",
  "properties": {
    "addr:full":"James St Gilberton SA 5081",
    "addr:postcode":"5081",
    "addr:street":"James St",
    "iso:country":"AU",
    "sg:address":"James St",
    "sg:city":"Gilberton",
    "sg:classifiers":[
        {
            "category":"Health Services",
            "subcategory":"Health Practitioner",
            "type":"Services"
        }
    ],
    "sg:phone":"+61 1300 763 370",
    "sg:postcode":"5081",
    "sg:province":"SA",
    "sg:tags":[
        "psychologist"
    ],
    "wof:name":"OnPurpose Psychology & Success Coaching",
    "wof:placetype":"venue"
},
  "geometry": {"coordinates":[138.61250305199999,-34.8980979919],"type":"Point"}
}