{
  "type": "Feature",
  "properties": {
    "addr:full":"167 Warnertown Rd Port Pirie SA 5540",
    "addr:housenumber":"167",
    "addr:postcode":"5540",
    "addr:street":"Warnertown Rd",
    "iso:country":"AU",
    "sg:address":"167 Warnertown Rd",
    "sg:city":"Port Pirie",
    "sg:classifiers":[
        {
            "category":"Commercial Area",
            "type":"Public Place"
        }
    ],
    "sg:phone":"+61 8 8633 4577",
    "sg:postcode":"5540",
    "sg:province":"SA",
    "sg:tags":[
        "heavy",
        "carrier"
    ],
    "wof:name":"Irvines Transport",
    "wof:placetype":"venue"
},
  "geometry": {"coordinates":[138.05809020999999,-33.1741676331],"type":"Point"}
}