{
  "type": "Feature",
  "properties": {
    "iso:country":"AU",
    "sg:address":"Renmark Ave",
    "sg:city":"Renmark",
    "sg:classifiers":[
        {
            "category":"Home & Garden",
            "subcategory":"Furniture",
            "type":"Retail Goods"
        }
    ],
    "sg:phone":"+61 8 8586 5696",
    "sg:postcode":"5341",
    "sg:province":"SA",
    "sg:tags":[
        "business"
    ],
    "wof:name":"TJ's Furniture Mart",
    "wof:placetype":"venue"
},
  "geometry": {"coordinates":[140.74586486800001,-34.1748962402],"type":"Point"}
}