{
  "type": "Feature",
  "properties": {
    "addr:full":"266- 268 Summer St Orange NSW 2800",
    "addr:housenumber":"268",
    "addr:postcode":"2800",
    "addr:street":"Summer St",
    "iso:country":"AU",
    "sg:address":"266- 268 Summer St",
    "sg:city":"Orange",
    "sg:classifiers":[
        {
            "category":"Professional",
            "subcategory":"Employment Agencies",
            "type":"Services"
        }
    ],
    "sg:phone":"+61 2 6361 8883",
    "sg:postcode":"2800",
    "sg:province":"NSW",
    "sg:tags":[
        "provider",
        "internet"
    ],
    "wof:name":"Technical Support Solutions",
    "wof:placetype":"venue"
},
  "geometry": {"coordinates":[149.10194397000001,-33.2840042114],"type":"Point"}
}