{
  "type": "Feature",
  "properties": {
    "iso:country":"AU",
    "sg:address":"Running Creek Rd",
    "sg:city":"Rathdowney",
    "sg:classifiers":[
        {
            "category":"Building & Trades",
            "subcategory":"Construction",
            "type":"Services"
        }
    ],
    "sg:phone":"+61 417 401 609",
    "sg:postcode":"4287",
    "sg:province":"QLD",
    "sg:tags":[
        "concrete",
        "contractor"
    ],
    "wof:name":"YP Concrete Co",
    "wof:placetype":"venue"
},
  "geometry": {"coordinates":[152.86547899999999,-28.211151],"type":"Point"}
}