{
  "type": "Feature",
  "properties": {
    "addr:full":"50 Anvil St Greta NSW 2334",
    "addr:housenumber":"50",
    "addr:postcode":"2334",
    "addr:street":"Anvil St",
    "iso:country":"AU",
    "sg:address":"50 Anvil St",
    "sg:city":"Greta",
    "sg:classifiers":[
        {
            "category":"Building & Trades",
            "subcategory":"Construction",
            "type":"Services"
        }
    ],
    "sg:phone":"+61 402 002 265",
    "sg:postcode":"2334",
    "sg:province":"NSW",
    "sg:tags":[
        "earth",
        "excavating",
        "moving",
        "contractor"
    ],
    "wof:name":"Ron's Landscaping",
    "wof:placetype":"venue"
},
  "geometry": {"coordinates":[151.39122009299999,-32.682472229],"type":"Point"}
}