{
  "type": "Feature",
  "properties": {
    "iso:country":"AU",
    "sg:address":"24 Elder St",
    "sg:city":"Clarinda",
    "sg:classifiers":[
        {
            "category":"Building & Trades",
            "subcategory":"Construction",
            "type":"Services"
        }
    ],
    "sg:phone":"+61 3 9544 8594",
    "sg:postcode":"3169",
    "sg:province":"VIC",
    "sg:tags":[
        "earth",
        "excavating",
        "moving",
        "contractor"
    ],
    "wof:name":"Harrop R D",
    "wof:placetype":"venue"
},
  "geometry": {"coordinates":[145.104278564,-37.9289588928],"type":"Point"}
}