{
  "type": "Feature",
  "properties": {
    "addr:full":"Suite 5/ 41 Wason St Milton NSW 2538",
    "addr:housenumber":"41",
    "addr:postcode":"2538",
    "addr:street":"Wason St",
    "iso:country":"AU",
    "sg:address":"Suite 5/ 41 Wason St",
    "sg:city":"Milton",
    "sg:classifiers":[
        {
            "category":"Banks & Credit Unions",
            "subcategory":"Investment Brokerage",
            "type":"Services"
        }
    ],
    "sg:phone":"+61 2 4455 4155",
    "sg:postcode":"2538",
    "sg:province":"NSW",
    "sg:tags":[
        "share",
        "broker",
        "stock"
    ],
    "wof:name":"Coast Financial Planning",
    "wof:placetype":"venue"
},
  "geometry": {"coordinates":[150.435745239,-35.3164596558],"type":"Point"}
}