{
  "type": "Feature",
  "properties": {
    "addr:full":"19 Kimberly Rd Dandenong South VIC 3175",
    "addr:housenumber":"19",
    "addr:postcode":"3175",
    "addr:street":"Kimberly Rd",
    "iso:country":"AU",
    "sg:address":"19 Kimberly Rd",
    "sg:city":"Dandenong South",
    "sg:classifiers":[
        {
            "category":"Professional",
            "subcategory":"Engineering",
            "type":"Services"
        }
    ],
    "sg:phone":"+61 3 9706 5659",
    "sg:postcode":"3175",
    "sg:province":"VIC",
    "sg:tags":[
        "engineer"
    ],
    "wof:name":"Rob Black Australia Pty Ltd",
    "wof:placetype":"venue"
},
  "geometry": {"coordinates":[145.205612183,-38.0311927795],"type":"Point"}
}