{
  "type": "Feature",
  "properties": {
    "iso:country":"AU",
    "sg:address":"84 Addison Rd",
    "sg:city":"Marrickville",
    "sg:classifiers":[
        {
            "category":"Building & Trades",
            "subcategory":"Construction",
            "type":"Services"
        }
    ],
    "sg:phone":"+61 2 9572 7704",
    "sg:postcode":"2204",
    "sg:province":"NSW",
    "sg:tags":[
        "contractor"
    ],
    "wof:name":"Britannia Building Services Pty Ltd",
    "wof:placetype":"venue"
},
  "geometry": {"coordinates":[151.16467299999999,-33.902843],"type":"Point"}
}