{
  "type": "Feature",
  "properties": {
    "addr:full":"30 Egan Rd Dandenong VIC 3175",
    "addr:housenumber":"30",
    "addr:postcode":"3175",
    "addr:street":"Egan Rd",
    "iso:country":"AU",
    "sg:address":"30 Egan Rd",
    "sg:city":"Dandenong",
    "sg:classifiers":[
        {
            "category":"Retail",
            "subcategory":"Auto Repair",
            "type":"Services"
        }
    ],
    "sg:phone":"+61 3 9793 5731",
    "sg:postcode":"3175",
    "sg:province":"VIC",
    "sg:tags":[
        "testing",
        "inspection",
        "motor",
        "vehicle"
    ],
    "wof:name":"Serv Group (AUST)",
    "wof:placetype":"venue"
},
  "geometry": {"coordinates":[145.194458008,-37.9931144714],"type":"Point"}
}