{
  "type": "Feature",
  "properties": {
    "addr:full":"Gillespie Rd St Albans VIC 3021",
    "addr:postcode":"3021",
    "addr:street":"Gillespie Rd",
    "iso:country":"AU",
    "sg:address":"Gillespie Rd",
    "sg:city":"St Albans",
    "sg:classifiers":[
        {
            "category":"Arena",
            "subcategory":"Sports Club",
            "type":"Entertainment"
        }
    ],
    "sg:phone":"+61 3 9367 5956",
    "sg:postcode":"3021",
    "sg:province":"VIC",
    "sg:tags":[
        "australian",
        "football",
        "rule"
    ],
    "wof:name":"St Albans Football & Cricket Clubs",
    "wof:placetype":"venue"
},
  "geometry": {"coordinates":[144.789917,-37.734936],"type":"Point"}
}