{
  "type": "Feature",
  "properties": {
    "addr:full":"Prospect Ave Belmont VIC 3216",
    "addr:postcode":"3216",
    "addr:street":"Prospect Ave",
    "iso:country":"AU",
    "sg:address":"Prospect Ave",
    "sg:city":"Belmont",
    "sg:classifiers":[
        {
            "category":"Health Services",
            "subcategory":"Dentist",
            "type":"Services"
        }
    ],
    "sg:phone":"+61 3 5241 1222",
    "sg:postcode":"3216",
    "sg:province":"VIC",
    "sg:tags":[
        "dental",
        "prosthetist"
    ],
    "wof:name":"Brad McRobb Dental Prosthetist",
    "wof:placetype":"venue"
},
  "geometry": {"coordinates":[144.342453003,-38.1771240234],"type":"Point"}
}