{
  "type": "Feature",
  "properties": {
    "addr:full":"46 Cambridge Rd Bellerive TAS 7018",
    "addr:housenumber":"46",
    "addr:postcode":"7018",
    "addr:street":"Cambridge Rd",
    "iso:country":"AU",
    "sg:address":"46 Cambridge Rd",
    "sg:city":"Bellerive",
    "sg:classifiers":[
        {
            "category":"Health Services",
            "subcategory":"Doctor",
            "type":"Services"
        }
    ],
    "sg:phone":"+61 3 6245 0861",
    "sg:postcode":"7018",
    "sg:province":"TAS",
    "sg:tags":[
        "medical",
        "practitioner"
    ],
    "wof:name":"Hobart Skin Cancer Clinic",
    "wof:placetype":"venue"
},
  "geometry": {"coordinates":[147.36740112300001,-42.8747138977],"type":"Point"}
}