{
  "type": "Feature",
  "properties": {
    "addr:full":"Shop 1 Mt Hutton Shopping Centre Wilsons Rd Mt Hutton NSW 2290",
    "addr:housenumber":"shop 1",
    "addr:postcode":"2290",
    "addr:street":"Mt Hutton;Wilsons Rd",
    "iso:country":"AU",
    "sg:address":"Shop 1 Mt Hutton Shopping Centre Wilsons Rd",
    "sg:city":"Mt Hutton",
    "sg:classifiers":[
        {
            "category":"Communications",
            "subcategory":"Film & Video Production",
            "type":"Services"
        }
    ],
    "sg:phone":"+61 2 4948 9766",
    "sg:postcode":"2290",
    "sg:province":"NSW",
    "sg:tags":[
        "dvd",
        "library"
    ],
    "wof:name":"Video Ezy",
    "wof:placetype":"venue"
},
  "geometry": {"coordinates":[151.668899536,-32.9822387695],"type":"Point"}
}