{
  "type": "Feature",
  "properties": {
    "addr:full":"166 Colin St West Perth WA 6005",
    "addr:housenumber":"166",
    "addr:postcode":"6005",
    "addr:street":"Colin St",
    "iso:country":"AU",
    "sg:address":"166 Colin St",
    "sg:city":"West Perth",
    "sg:classifiers":[
        {
            "category":"Professional",
            "subcategory":"Business Services",
            "type":"Services"
        }
    ],
    "sg:phone":"+61 419 943 000",
    "sg:postcode":"6005",
    "sg:province":"WA",
    "sg:tags":[
        "management",
        "event"
    ],
    "wof:name":"eventFULL entertainment management",
    "wof:placetype":"venue"
},
  "geometry": {"coordinates":[115.84343719500001,-31.9444770813],"type":"Point"}
}