{
  "type": "Feature",
  "properties": {
    "iso:country":"AU",
    "sg:address":"2b Khancoban St",
    "sg:city":"Heckenberg",
    "sg:classifiers":[
        {
            "category":"Personal",
            "subcategory":"Beauty Salon",
            "type":"Services"
        }
    ],
    "sg:phone":"+61 2 9826 0387",
    "sg:postcode":"2168",
    "sg:province":"NSW",
    "sg:tags":[
        "hairdresser"
    ],
    "wof:name":"Heckenberg Sizerz",
    "wof:placetype":"venue"
},
  "geometry": {"coordinates":[150.885162353,-33.9083175659],"type":"Point"}
}