{
  "type": "Feature",
  "properties": {
    "addr:full":"131 Upper Heidelberg Rd Ivanhoe VIC 3079",
    "addr:housenumber":"131",
    "addr:postcode":"3079",
    "addr:street":"Upper Heidelberg Rd",
    "iso:country":"AU",
    "sg:address":"131 Upper Heidelberg Rd",
    "sg:city":"Ivanhoe",
    "sg:classifiers":[
        {
            "category":"Health Services",
            "subcategory":"Doctor",
            "type":"Services"
        }
    ],
    "sg:phone":"+61 3 9497 1644",
    "sg:postcode":"3079",
    "sg:province":"VIC",
    "sg:tags":[
        "medical",
        "practitioner"
    ],
    "wof:name":"Doctors Of Ivanhoe",
    "wof:placetype":"venue"
},
  "geometry": {"coordinates":[145.04222106899999,-37.7687263489],"type":"Point"}
}