{
  "type": "Feature",
  "properties": {
    "addr:full":"24 Dewhurst St Narrabri NSW 2390",
    "addr:housenumber":"24",
    "addr:postcode":"2390",
    "addr:street":"Dewhurst St",
    "iso:country":"AU",
    "sg:address":"24 Dewhurst St",
    "sg:city":"Narrabri",
    "sg:classifiers":[
        {
            "category":"Health Services",
            "subcategory":"Chiropractor",
            "type":"Services"
        }
    ],
    "sg:phone":"+61 2 6792 1232",
    "sg:postcode":"2390",
    "sg:province":"NSW",
    "wof:name":"Woods Paul",
    "wof:placetype":"venue"
},
  "geometry": {"coordinates":[149.789306641,-30.3245449066],"type":"Point"}
}