{
  "type": "Feature",
  "properties": {
    "addr:full":"11 Mile Stuart Hwy Pinelands NT 0829",
    "addr:housenumber":"11",
    "addr:postcode":"nt 0829",
    "addr:street":"Mile Stuart Hwy",
    "iso:country":"AU",
    "sg:address":"11 Mile Stuart Hwy",
    "sg:city":"Pinelands",
    "sg:classifiers":[
        {
            "category":"Home & Garden",
            "subcategory":"Hardware",
            "type":"Retail Goods"
        }
    ],
    "sg:phone":"+61 8 8939 0200",
    "sg:postcode":"0829",
    "sg:province":"NT",
    "sg:tags":[
        "compressor",
        "air"
    ],
    "wof:name":"Airpower (NT) Pty Ltd",
    "wof:placetype":"venue"
},
  "geometry": {"coordinates":[130.96505737300001,-12.4548425674],"type":"Point"}
}