{
  "type": "Feature",
  "properties": {
    "addr:full":"Suite 3/ 225 Forest Rd Hurstville NSW 2220",
    "addr:housenumber":"/ 225",
    "addr:postcode":"2220",
    "addr:street":"Forest Rd",
    "iso:country":"AU",
    "sg:address":"Suite 3/ 225 Forest Rd",
    "sg:city":"Hurstville",
    "sg:classifiers":[
        {
            "category":"Health Services",
            "subcategory":"Dentist",
            "type":"Services"
        }
    ],
    "sg:phone":"+61 2 9570 5648",
    "sg:postcode":"2220",
    "sg:province":"NSW",
    "wof:name":"David G Power, Dr",
    "wof:placetype":"venue"
},
  "geometry": {"coordinates":[151.102752686,-33.9669876099],"type":"Point"}
}