{
  "type": "Feature",
  "properties": {
    "iso:country":"AU",
    "sg:address":"Shop 105, Orange Ave",
    "sg:city":"Mildura",
    "sg:classifiers":[
        {
            "category":"Personal",
            "type":"Services"
        }
    ],
    "sg:phone":"+61 3 5022 1388",
    "sg:postcode":"3500",
    "sg:province":"VIC",
    "sg:tags":[
        "reducing",
        "treatment",
        "weight"
    ],
    "wof:name":"Jenny Craig Weight Loss Centres Pty Ltd",
    "wof:placetype":"venue"
},
  "geometry": {"coordinates":[142.161941528,-34.1890106201],"type":"Point"}
}