{
  "type": "Feature",
  "properties": {
    "addr:full":"7 Kirkcaldy St Bathurst NSW 2795",
    "addr:housenumber":"7",
    "addr:postcode":"2795",
    "addr:street":"Kirkcaldy St",
    "iso:country":"AU",
    "sg:address":"7 Kirkcaldy St",
    "sg:city":"Bathurst",
    "sg:classifiers":[
        {
            "category":"Building & Trades",
            "subcategory":"Construction",
            "type":"Services"
        }
    ],
    "sg:phone":"+61 2 6331 4218",
    "sg:postcode":"2795",
    "sg:province":"NSW",
    "sg:tags":[
        "welding"
    ],
    "wof:name":"Bathurst Welding & Body Works",
    "wof:placetype":"venue"
},
  "geometry": {"coordinates":[149.57908630399999,-33.4385681152],"type":"Point"}
}