{
  "type": "Feature",
  "properties": {
    "iso:country":"AU",
    "sg:address":"23 Port Kembla Drv",
    "sg:city":"Bibra Lake",
    "sg:classifiers":[
        {
            "category":"Real Estate",
            "subcategory":"Real Estate Agent",
            "type":"Services"
        }
    ],
    "sg:phone":"+61 8 9434 3525",
    "sg:postcode":"6163",
    "sg:province":"WA",
    "wof:name":"Harcourts Vision",
    "wof:placetype":"venue"
},
  "geometry": {"coordinates":[115.80120100000001,-32.098721],"type":"Point"}
}