{
  "type": "Feature",
  "properties": {
    "iso:country":"AU",
    "sg:address":"Unit 2, 28 Guthrie St",
    "sg:city":"Osborne Park",
    "sg:classifiers":[
        {
            "category":"Banks & Credit Unions",
            "subcategory":"Investment Brokerage",
            "type":"Services"
        }
    ],
    "sg:phone":"+61 8 9244 2177",
    "sg:postcode":"6017",
    "sg:province":"WA",
    "sg:tags":[
        "shutter",
        "louvre"
    ],
    "wof:name":"Perth Plantation Shutters",
    "wof:placetype":"venue"
},
  "geometry": {"coordinates":[115.81175994900001,-31.9022750854],"type":"Point"}
}