{
  "type": "Feature",
  "properties": {
    "addr:full":"Kalamunda Central Shopng Cntr Railway Rd Kalamunda WA 6076",
    "addr:postcode":"6076",
    "addr:street":"Railway Rd",
    "iso:country":"AU",
    "sg:address":"Kalamunda Central Shopng Cntr Railway Rd",
    "sg:city":"Kalamunda",
    "sg:classifiers":[
        {
            "category":"Personal",
            "subcategory":"Beauty Salon",
            "type":"Services"
        }
    ],
    "sg:phone":"+61 8 9293 0101",
    "sg:postcode":"6076",
    "sg:province":"WA",
    "wof:name":"Central Beauty",
    "wof:placetype":"venue"
},
  "geometry": {"coordinates":[116.060417175,-31.9780216217],"type":"Point"}
}