{
  "type": "Feature",
  "properties": {
    "iso:country":"AU",
    "sg:address":"1567 Point Nepean Rd",
    "sg:city":"Rosebud West",
    "sg:classifiers":[
        {
            "category":"Health Services",
            "subcategory":"Dentist",
            "type":"Services"
        }
    ],
    "sg:phone":"+61 3 5981 2255",
    "sg:postcode":"3940",
    "sg:province":"VIC",
    "sg:tags":[
        "technician",
        "dental"
    ],
    "wof:name":"Embling P",
    "wof:placetype":"venue"
},
  "geometry": {"coordinates":[144.88063049300001,-38.3625946045],"type":"Point"}
}