{
  "type": "Feature",
  "properties": {
    "iso:country":"AU",
    "sg:address":"10 Winten Rd",
    "sg:city":"Glendenning",
    "sg:classifiers":[
        {
            "category":"Utilities",
            "subcategory":"Water",
            "type":"Services"
        }
    ],
    "sg:phone":"+61 2 9677 0700",
    "sg:postcode":"2761",
    "sg:province":"NSW",
    "sg:tags":[
        "hot",
        "system"
    ],
    "wof:name":"A A Abound Emergency Electric And Gas Hot Water System Repairs Replacement And G",
    "wof:placetype":"venue"
},
  "geometry": {"coordinates":[150.854935,-33.74456],"type":"Point"}
}