{
  "type": "Feature",
  "properties": {
    "addr:full":"Mercy Medical Centre Ellesmere Rd Mt Lawley WA 6050",
    "addr:postcode":"6050",
    "addr:street":"Ellesmere Rd",
    "iso:country":"AU",
    "sg:address":"Mercy Medical Centre Ellesmere Rd",
    "sg:city":"Mt Lawley",
    "sg:classifiers":[
        {
            "category":"Health Services",
            "subcategory":"Doctor",
            "type":"Services"
        }
    ],
    "sg:phone":"+61 8 9370 9860",
    "sg:postcode":"6050",
    "sg:province":"WA",
    "sg:tags":[
        "medical",
        "practitioner"
    ],
    "wof:name":"Ghossein Jerard",
    "wof:placetype":"venue"
},
  "geometry": {"coordinates":[115.88269805900001,-31.9363765717],"type":"Point"}
}