{
  "type": "Feature",
  "properties": {
    "addr:full":"147 Station St Fairfield VIC 3078",
    "addr:housenumber":"147",
    "addr:postcode":"3078",
    "addr:street":"Station St",
    "iso:country":"AU",
    "sg:address":"147 Station St",
    "sg:city":"Fairfield",
    "sg:classifiers":[
        {
            "category":"Manufacturing",
            "subcategory":"Wood Products",
            "type":"Manufacturing & Wholesale Goods"
        }
    ],
    "sg:phone":"+61 3 9482 5965",
    "sg:postcode":"3078",
    "sg:province":"VIC",
    "sg:tags":[
        "polisher",
        "french"
    ],
    "wof:name":"Burtons Workshop Antiques",
    "wof:placetype":"venue"
},
  "geometry": {"coordinates":[145.01872253400001,-37.7763328552],"type":"Point"}
}