{
  "type": "Feature",
  "properties": {
    "iso:country":"AU",
    "sg:address":"27 Payne St",
    "sg:city":"Bairnsdale",
    "sg:classifiers":[
        {
            "category":"Retail",
            "subcategory":"Repair Shop",
            "type":"Services"
        }
    ],
    "sg:phone":"+61 407 864 341",
    "sg:postcode":"3875",
    "sg:province":"VIC",
    "sg:tags":[
        "windscreen"
    ],
    "wof:name":"Tint a Car Bairnsdale",
    "wof:placetype":"venue"
},
  "geometry": {"coordinates":[147.60763549800001,-37.8337593079],"type":"Point"}
}