{
  "type": "Feature",
  "properties": {
    "addr:full":"6 Arabin St Altona VIC 3018",
    "addr:housenumber":"6",
    "addr:postcode":"3018",
    "addr:street":"Arabin St",
    "iso:country":"AU",
    "sg:address":"6 Arabin St",
    "sg:city":"Altona",
    "sg:classifiers":[
        {
            "category":"Building & Trades",
            "subcategory":"Plumbing",
            "type":"Services"
        }
    ],
    "sg:phone":"+61 3 9315 0474",
    "sg:postcode":"3018",
    "sg:province":"VIC",
    "sg:tags":[
        "plumber",
        "gasfitters"
    ],
    "wof:name":"Allsub Plumbing & Maintenance",
    "wof:placetype":"venue"
},
  "geometry": {"coordinates":[144.82481384299999,-37.8638114929],"type":"Point"}
}