{
  "type": "Feature",
  "properties": {
    "addr:full":"Bayview Rd Belgrave VIC 3160",
    "addr:postcode":"3160",
    "addr:street":"Bayview Rd",
    "iso:country":"AU",
    "sg:address":"Bayview Rd",
    "sg:city":"Belgrave",
    "sg:classifiers":[
        {
            "category":"Government",
            "subcategory":"City Hall",
            "type":"Public Place"
        }
    ],
    "sg:phone":"+61 3 9754 8702",
    "sg:postcode":"3160",
    "sg:province":"VIC",
    "wof:name":"Masonic Centre",
    "wof:placetype":"venue"
},
  "geometry": {"coordinates":[145.356567383,-37.9089241028],"type":"Point"}
}