{
  "type": "Feature",
  "properties": {
    "addr:full":"178 River St Ballina NSW 2478",
    "addr:housenumber":"178",
    "addr:postcode":"2478",
    "addr:street":"River St",
    "iso:country":"AU",
    "sg:address":"178 River St",
    "sg:city":"Ballina",
    "sg:classifiers":[
        {
            "category":"Ice Cream",
            "type":"Food & Drink"
        }
    ],
    "sg:phone":"+61 2 6686 5783",
    "sg:postcode":"2478",
    "sg:province":"NSW",
    "sg:tags":[
        "retail"
    ],
    "wof:name":"Ballina Ice Creamery Internet Cafe",
    "wof:placetype":"venue"
},
  "geometry": {"coordinates":[153.55891418499999,-28.8699874878],"type":"Point"}
}