{
  "type": "Feature",
  "properties": {
    "addr:full":"426 Pacific Hwy Belmont NSW 2280",
    "addr:housenumber":"426",
    "addr:postcode":"2280",
    "addr:street":"Pacific Hwy",
    "iso:country":"AU",
    "sg:address":"426 Pacific Hwy",
    "sg:city":"Belmont",
    "sg:classifiers":[
        {
            "category":"Retail",
            "subcategory":"Auto Repair",
            "type":"Services"
        }
    ],
    "sg:phone":"+61 2 4945 5037",
    "sg:postcode":"2280",
    "sg:province":"NSW",
    "sg:tags":[
        "bus",
        "truck"
    ],
    "wof:name":"Griffiths Tilt Tray Transport",
    "wof:placetype":"venue"
},
  "geometry": {"coordinates":[151.66079711899999,-33.0297279358],"type":"Point"}
}