{
  "type": "Feature",
  "properties": {
    "iso:country":"AU",
    "sg:address":"323 Lal Lal St",
    "sg:city":"Ballarat",
    "sg:classifiers":[
        {
            "category":"Building & Trades",
            "subcategory":"Construction",
            "type":"Services"
        }
    ],
    "sg:phone":"+61 3 5331 5589",
    "sg:postcode":"3350",
    "sg:province":"VIC",
    "sg:tags":[
        "window",
        "timber"
    ],
    "wof:name":"Townsend Joinery",
    "wof:placetype":"venue"
},
  "geometry": {"coordinates":[143.877899,-37.580521],"type":"Point"}
}