{
  "type": "Feature",
  "properties": {
    "iso:country":"AU",
    "sg:address":"30 Darling St",
    "sg:city":"Hamilton South",
    "sg:classifiers":[
        {
            "category":"Building & Trades",
            "subcategory":"Construction",
            "type":"Services"
        }
    ],
    "sg:phone":"+61 2 4965 4844",
    "sg:postcode":"2303",
    "sg:province":"NSW",
    "sg:tags":[
        "contractor"
    ],
    "wof:name":"Campbell David Constructions",
    "wof:placetype":"venue"
},
  "geometry": {"coordinates":[151.745636,-32.93362],"type":"Point"}
}