{
  "type": "Feature",
  "properties": {
    "iso:country":"AU",
    "sg:address":"4 Lawson St",
    "sg:city":"Emu Plains",
    "sg:classifiers":[
        {
            "category":"Social Services",
            "subcategory":"Child Care",
            "type":"Services"
        }
    ],
    "sg:phone":"+61 2 4735 4511",
    "sg:postcode":"2750",
    "sg:province":"NSW",
    "wof:name":"Emu Village Before & After School Care",
    "wof:placetype":"venue"
},
  "geometry": {"coordinates":[150.66255188,-33.7503471375],"type":"Point"}
}