{
  "type": "Feature",
  "properties": {
    "iso:country":"AU",
    "sg:address":"371 Pitt St",
    "sg:city":"Sydney",
    "sg:classifiers":[
        {
            "category":"Personal",
            "subcategory":"Beauty Salon",
            "type":"Services"
        }
    ],
    "sg:phone":"+61 2 9267 7299",
    "sg:postcode":"2000",
    "sg:province":"NSW",
    "sg:tags":[
        "hairdresser"
    ],
    "wof:name":"Kim Sun Young Hair Design",
    "wof:placetype":"venue"
},
  "geometry": {"coordinates":[151.20770263700001,-33.8761405945],"type":"Point"}
}