{
  "type": "Feature",
  "properties": {
    "iso:country":"AU",
    "sg:address":"191 Jasper Rd",
    "sg:city":"Bentleigh",
    "sg:classifiers":[
        {
            "category":"Health Services",
            "subcategory":"Health Practitioner",
            "type":"Services"
        }
    ],
    "sg:phone":"+61 3 9557 7377",
    "sg:postcode":"3204",
    "sg:province":"VIC",
    "sg:tags":[
        "physiotherapist"
    ],
    "wof:name":"Bentleigh Physiotherapy Centre",
    "wof:placetype":"venue"
},
  "geometry": {"coordinates":[145.041763,-37.917191],"type":"Point"}
}