{
  "type": "Feature",
  "properties": {
    "iso:country":"AU",
    "sg:address":"1- 162 Abbotsford Rd",
    "sg:city":"Albion",
    "sg:classifiers":[
        {
            "category":"Building & Trades",
            "subcategory":"Plumbing",
            "type":"Services"
        }
    ],
    "sg:phone":"+61 7 3235 1133",
    "sg:postcode":"4010",
    "sg:province":"QLD",
    "sg:tags":[
        "plumber",
        "gasfitters"
    ],
    "wof:name":"Nu Flow Pipelines",
    "wof:placetype":"venue"
},
  "geometry": {"coordinates":[153.04066467300001,-27.4382343292],"type":"Point"}
}