{
  "type": "Feature",
  "properties": {
    "iso:country":"AU",
    "sg:address":"60 Queen St",
    "sg:city":"Ayr",
    "sg:classifiers":[
        {
            "category":"Professional",
            "subcategory":"Accounting & Tax Preparation",
            "type":"Services"
        }
    ],
    "sg:phone":"+61 7 4783 3944",
    "sg:postcode":"4807",
    "sg:province":"QLD",
    "sg:tags":[
        "accountant",
        "auditor"
    ],
    "wof:name":"Land McKaig",
    "wof:placetype":"venue"
},
  "geometry": {"coordinates":[147.408370972,-19.5726833344],"type":"Point"}
}