{
  "type": "Feature",
  "properties": {
    "iso:country":"AU",
    "sg:address":"Five Dock Leisure Centre, Cnr Queens Rd & William",
    "sg:city":"Five Dock",
    "sg:classifiers":[
        {
            "category":"Health Services",
            "subcategory":"Health Practitioner",
            "type":"Services"
        }
    ],
    "sg:phone":"+61 2 9744 6880",
    "sg:postcode":"2046",
    "sg:province":"NSW",
    "sg:tags":[
        "physiotherapist"
    ],
    "wof:name":"Dynamic Physiotherapy",
    "wof:placetype":"venue"
},
  "geometry": {"coordinates":[151.128876,-33.870548],"type":"Point"}
}