{
  "type": "Feature",
  "properties": {
    "addr:full":"203 Elgar Rd Box Hill South VIC 3128",
    "addr:housenumber":"203",
    "addr:postcode":"3128",
    "addr:street":"Elgar Rd",
    "iso:country":"AU",
    "sg:address":"203 Elgar Rd",
    "sg:city":"Box Hill South",
    "sg:classifiers":[
        {
            "category":"Fast Food",
            "type":"Food & Drink"
        }
    ],
    "sg:phone":"+61 3 9808 9874",
    "sg:postcode":"3128",
    "sg:province":"VIC",
    "sg:tags":[
        "away",
        "take"
    ],
    "wof:name":"Lazy Larder The",
    "wof:placetype":"venue"
},
  "geometry": {"coordinates":[145.11131286599999,-37.8372077942],"type":"Point"}
}