{
  "type": "Feature",
  "properties": {
    "addr:full":"381 Queen St Brisbane QLD 4000",
    "addr:housenumber":"381",
    "addr:postcode":"4000",
    "addr:street":"Queen St",
    "iso:country":"AU",
    "sg:address":"381 Queen St",
    "sg:city":"Brisbane",
    "sg:classifiers":[
        {
            "category":"Professional",
            "subcategory":"Business Services",
            "type":"Services"
        }
    ],
    "sg:phone":"+61 1800 820 061",
    "sg:postcode":"4000",
    "sg:province":"QLD",
    "sg:tags":[
        "record",
        "management",
        "storage"
    ],
    "wof:name":"Fileman Pty Ltd",
    "wof:placetype":"venue"
},
  "geometry": {"coordinates":[153.030487061,-27.4657306671],"type":"Point"}
}