{
  "type": "Feature",
  "properties": {
    "addr:full":"431 Canning Hwy Melville WA 6156",
    "addr:housenumber":"431",
    "addr:postcode":"6156",
    "addr:street":"Canning Hwy",
    "iso:country":"AU",
    "sg:address":"431 Canning Hwy",
    "sg:city":"Melville",
    "sg:classifiers":[
        {
            "category":"Professional",
            "subcategory":"Management & Consulting",
            "type":"Services"
        }
    ],
    "sg:phone":"+61 8 9317 8279",
    "sg:postcode":"6156",
    "sg:province":"WA",
    "sg:tags":[
        "consultant"
    ],
    "wof:name":"ABV Leisure Consultancy Services",
    "wof:placetype":"venue"
},
  "geometry": {"coordinates":[115.80802199999999,-32.032455],"type":"Point"}
}