{
  "type": "Feature",
  "properties": {
    "iso:country":"AU",
    "sg:address":"PO Box 114",
    "sg:city":"Willetton",
    "sg:classifiers":[
        {
            "category":"Wholesale",
            "subcategory":"Photographic Equipment",
            "type":"Manufacturing & Wholesale Goods"
        }
    ],
    "sg:phone":"+61 1300 785 506",
    "sg:postcode":"6955",
    "sg:province":"WA",
    "sg:tags":[
        "wholesaler",
        "mfrs",
        "supply"
    ],
    "wof:name":"C-Direct",
    "wof:placetype":"venue"
},
  "geometry": {"coordinates":[115.881530762,-32.053150177],"type":"Point"}
}