{
  "type": "Feature",
  "properties": {
    "addr:full":"Unit 6/ 12 Loftus St Bowral NSW 2576",
    "addr:housenumber":"12",
    "addr:postcode":"2576",
    "addr:street":"Loftus St",
    "iso:country":"AU",
    "sg:address":"Unit 6/ 12 Loftus St",
    "sg:city":"Bowral",
    "sg:classifiers":[
        {
            "category":"Retail",
            "subcategory":"Auto Repair",
            "type":"Services"
        }
    ],
    "sg:phone":"+61 2 4861 4770",
    "sg:postcode":"2576",
    "sg:province":"NSW",
    "sg:tags":[
        "automotive",
        "air conditioning"
    ],
    "wof:name":"All About Automotives",
    "wof:placetype":"venue"
},
  "geometry": {"coordinates":[150.411575317,-34.487739563],"type":"Point"}
}