{
  "type": "Feature",
  "properties": {
    "addr:full":"Unit 4, 68 Lilyfield Rd Rozelle NSW 2039",
    "addr:housenumber":"68",
    "addr:postcode":"2039",
    "addr:street":"Lilyfield Rd",
    "iso:country":"AU",
    "sg:address":"Unit 4, 68 Lilyfield Rd",
    "sg:city":"Rozelle",
    "sg:classifiers":[
        {
            "category":"Military Area",
            "subcategory":"Armory",
            "type":"Public Place"
        }
    ],
    "sg:phone":"+61 2 9555 5733",
    "sg:postcode":"2039",
    "sg:province":"NSW",
    "sg:tags":[
        "teleconferencing"
    ],
    "wof:name":"BRE Communications Pty Ltd",
    "wof:placetype":"venue"
},
  "geometry": {"coordinates":[151.170532227,-33.8699989319],"type":"Point"}
}