{
  "type": "Feature",
  "properties": {
    "iso:country":"AU",
    "sg:address":"Lloyd Pl",
    "sg:city":"Otford",
    "sg:classifiers":[
        {
            "category":"Travel",
            "subcategory":"Travel Agent",
            "type":"Entertainment"
        }
    ],
    "sg:phone":"+61 2 4294 1296",
    "sg:postcode":"2508",
    "sg:province":"NSW",
    "sg:tags":[
        "tour",
        "holiday",
        "adventure"
    ],
    "wof:name":"Otford Farm",
    "wof:placetype":"venue"
},
  "geometry": {"coordinates":[150.993958,-34.212025],"type":"Point"}
}