{
  "type": "Feature",
  "properties": {
    "iso:country":"AU",
    "sg:address":"PO Box 127",
    "sg:city":"Dardanup",
    "sg:classifiers":[
        {
            "category":"Building & Trades",
            "subcategory":"Construction",
            "type":"Services"
        }
    ],
    "sg:phone":"+61 8 9728 3106",
    "sg:postcode":"6236",
    "sg:province":"WA",
    "sg:tags":[
        "contractor"
    ],
    "wof:name":"Bunbury Stabilised Earth",
    "wof:placetype":"venue"
},
  "geometry": {"coordinates":[115.75354,-33.401119],"type":"Point"}
}