{
  "type": "Feature",
  "properties": {
    "iso:country":"AU",
    "sg:address":"21a Production Drv",
    "sg:city":"Campbellfield",
    "sg:classifiers":[
        {
            "category":"Home & Garden",
            "subcategory":"Kitchen Supply",
            "type":"Retail Goods"
        }
    ],
    "sg:phone":"+61 3 9357 6468",
    "sg:postcode":"3061",
    "sg:province":"VIC",
    "sg:tags":[
        "traffic",
        "equipment",
        "safety",
        "road"
    ],
    "sg:website":"http://www.jamesluke.com.au",
    "wof:name":"JamesLuke Australia",
    "wof:placetype":"venue"
},
  "geometry": {"coordinates":[144.96954345699999,-37.664024353],"type":"Point"}
}