{
  "type": "Feature",
  "properties": {
    "addr:full":"Factory 2 / 18 Kamholtz Crt Ashmore QLD 4214",
    "addr:housenumber":"/ 18",
    "addr:postcode":"4214",
    "addr:street":"Kamholtz Crt",
    "iso:country":"AU",
    "sg:address":"Factory 2 / 18 Kamholtz Crt",
    "sg:city":"Ashmore",
    "sg:classifiers":[
        {
            "category":"Communications",
            "type":"Services"
        }
    ],
    "sg:phone":"+61 7 5597 4355",
    "sg:postcode":"4214",
    "sg:province":"QLD",
    "sg:tags":[
        "public",
        "system",
        "address"
    ],
    "sg:website":"http://www.multi-image.com.au",
    "wof:name":"Multi Image Productions",
    "wof:placetype":"venue"
},
  "geometry": {"coordinates":[153.358444214,-27.9867076874],"type":"Point"}
}