{
  "type": "Feature",
  "properties": {
    "addr:full":"Wilson St Lawson NSW 2783",
    "addr:postcode":"2783",
    "addr:street":"Wilson St",
    "iso:country":"AU",
    "sg:address":"Wilson St",
    "sg:city":"Lawson",
    "sg:classifiers":[
        {
            "category":"Sports & Exercise",
            "subcategory":"Golf",
            "type":"Entertainment"
        }
    ],
    "sg:phone":"+61 2 4759 1004",
    "sg:postcode":"2783",
    "sg:province":"NSW",
    "sg:tags":[
        "club"
    ],
    "wof:name":"Lawson Golf Club",
    "wof:placetype":"venue"
},
  "geometry": {"coordinates":[150.42868042000001,-33.7225761414],"type":"Point"}
}