{
  "type": "Feature",
  "properties": {
    "iso:country":"AU",
    "sg:address":"16 Union St",
    "sg:city":"Stepney",
    "sg:classifiers":[
        {
            "category":"Building & Trades",
            "subcategory":"Construction",
            "type":"Services"
        }
    ],
    "sg:phone":"+61 8 8362 4682",
    "sg:postcode":"5069",
    "sg:province":"SA",
    "sg:tags":[
        "joinery"
    ],
    "wof:name":"Stepney Joinery",
    "wof:placetype":"venue"
},
  "geometry": {"coordinates":[138.629272461,-34.913608551],"type":"Point"}
}