{
  "type": "Feature",
  "properties": {
    "addr:full":"21 Lemon St Campbells Creek VIC 3451",
    "addr:housenumber":"21",
    "addr:postcode":"3451",
    "addr:street":"Lemon St",
    "iso:country":"AU",
    "sg:address":"21 Lemon St",
    "sg:city":"Campbells Creek",
    "sg:classifiers":[
        {
            "category":"Professional",
            "subcategory":"Engineering",
            "type":"Services"
        }
    ],
    "sg:phone":"+61 3 5472 1589",
    "sg:postcode":"3451",
    "sg:province":"VIC",
    "sg:tags":[
        "engineer"
    ],
    "wof:name":"Golles P & E Engineering",
    "wof:placetype":"venue"
},
  "geometry": {"coordinates":[144.194458008,-37.0845947266],"type":"Point"}
}