{
  "type": "Feature",
  "properties": {
    "addr:full":"70 Graham St Nowra NSW 2540",
    "addr:housenumber":"70",
    "addr:postcode":"2540",
    "addr:street":"Graham St",
    "iso:country":"AU",
    "sg:address":"70 Graham St",
    "sg:city":"Nowra",
    "sg:classifiers":[
        {
            "category":"Professional",
            "subcategory":"Accounting & Tax Preparation",
            "type":"Services"
        }
    ],
    "sg:phone":"+61 2 4421 2345",
    "sg:postcode":"2540",
    "sg:province":"NSW",
    "sg:tags":[
        "accountant",
        "auditor"
    ],
    "wof:name":"Sim David",
    "wof:placetype":"venue"
},
  "geometry": {"coordinates":[150.59585571299999,-35.0912742615],"type":"Point"}
}