{
  "type": "Feature",
  "properties": {
    "addr:full":"1 Whittle Ave Seaforth NSW 2092",
    "addr:housenumber":"1",
    "addr:postcode":"2092",
    "addr:street":"Whittle Ave",
    "iso:country":"AU",
    "sg:address":"1 Whittle Ave",
    "sg:city":"Seaforth",
    "sg:classifiers":[
        {
            "category":"Communications",
            "type":"Services"
        }
    ],
    "sg:phone":"+61 2 9949 1304",
    "sg:postcode":"2092",
    "sg:province":"NSW",
    "sg:tags":[
        "translation"
    ],
    "wof:name":"Access Translations",
    "wof:placetype":"venue"
},
  "geometry": {"coordinates":[151.25282287600001,-33.7977905273],"type":"Point"}
}