{
  "type": "Feature",
  "properties": {
    "addr:full":"PO Box 340 Braidwood NSW 2622",
    "addr:postcode":"2622",
    "iso:country":"AU",
    "sg:address":"PO Box 340",
    "sg:city":"Braidwood",
    "sg:classifiers":[
        {
            "category":"Government",
            "subcategory":"Post Office",
            "type":"Public Place"
        }
    ],
    "sg:phone":"+61 407 237 909",
    "sg:postcode":"2622",
    "sg:province":"NSW",
    "sg:tags":[
        "horse",
        "dentist"
    ],
    "wof:name":"Southern Tablelands Equine Dentistry",
    "wof:placetype":"venue"
},
  "geometry": {"coordinates":[149.79966735799999,-35.4460792542],"type":"Point"}
}