{
  "type": "Feature",
  "properties": {
    "addr:full":"43 Station St Cheltenham VIC 3192",
    "addr:housenumber":"43",
    "addr:postcode":"3192",
    "addr:street":"Station St",
    "iso:country":"AU",
    "sg:address":"43 Station St",
    "sg:city":"Cheltenham",
    "sg:classifiers":[
        {
            "category":"Professional",
            "subcategory":"Accounting & Tax Preparation",
            "type":"Services"
        }
    ],
    "sg:phone":"+61 3 9589 2335",
    "sg:postcode":"3192",
    "sg:province":"VIC",
    "sg:tags":[
        "accountant",
        "auditor"
    ],
    "wof:name":"Shinkfield J B",
    "wof:placetype":"venue"
},
  "geometry": {"coordinates":[145.043457031,-37.9502067566],"type":"Point"}
}