{
  "type": "Feature",
  "properties": {
    "addr:full":"3/ 3 Collins Rd Melton VIC 3337",
    "addr:housenumber":"/ 3",
    "addr:postcode":"3337",
    "addr:street":"Collins Rd",
    "iso:country":"AU",
    "sg:address":"3/ 3 Collins Rd",
    "sg:city":"Melton",
    "sg:classifiers":[
        {
            "category":"Social Services",
            "subcategory":"Adult Care",
            "type":"Services"
        }
    ],
    "sg:phone":"+61 403 338 511",
    "sg:postcode":"3337",
    "sg:province":"VIC",
    "sg:tags":[
        "towing"
    ],
    "wof:name":"Lizards Towing",
    "wof:placetype":"venue"
},
  "geometry": {"coordinates":[144.60136399999999,-37.690361],"type":"Point"}
}