{
  "type": "Feature",
  "properties": {
    "addr:full":"Level 13, 31 Market St Sydney NSW 2000",
    "addr:housenumber":"31",
    "addr:postcode":"2000",
    "addr:street":"Market St",
    "iso:country":"AU",
    "sg:address":"Level 13, 31 Market St",
    "sg:city":"Sydney",
    "sg:classifiers":[
        {
            "category":"Airline",
            "type":"Transportation"
        }
    ],
    "sg:phone":"+61 2 9283 1355",
    "sg:postcode":"2000",
    "sg:province":"NSW",
    "sg:tags":[
        "agent"
    ],
    "wof:name":"Vietnam Airlines",
    "wof:placetype":"venue"
},
  "geometry": {"coordinates":[151.20591735799999,-33.8709983826],"type":"Point"}
}