{
  "type": "Feature",
  "properties": {
    "addr:full":"133 Akexander St Crows Nest NSW 2065",
    "addr:housenumber":"133",
    "addr:postcode":"2065",
    "addr:street":"Akexander St",
    "iso:country":"AU",
    "sg:address":"133 Akexander St",
    "sg:city":"Crows Nest",
    "sg:classifiers":[
        {
            "category":"Professional",
            "subcategory":"Management & Consulting",
            "type":"Services"
        }
    ],
    "sg:phone":"+61 2 9431 5317",
    "sg:postcode":"2065",
    "sg:province":"NSW",
    "sg:tags":[
        "consultant",
        "business"
    ],
    "wof:name":"Infocube Consulting",
    "wof:placetype":"venue"
},
  "geometry": {"coordinates":[151.202835083,-33.8244018555],"type":"Point"}
}