{
  "type": "Feature",
  "properties": {
    "addr:full":"127 Douglas Pde Williamstown VIC 3016",
    "addr:housenumber":"127",
    "addr:postcode":"3016",
    "addr:street":"Douglas Pde",
    "iso:country":"AU",
    "sg:address":"127 Douglas Pde",
    "sg:city":"Williamstown",
    "sg:classifiers":[
        {
            "category":"Sports & Exercise",
            "subcategory":"Ski Resort",
            "type":"Entertainment"
        }
    ],
    "sg:phone":"+61 1300 453 875",
    "sg:postcode":"3016",
    "sg:province":"VIC",
    "sg:tags":[
        "propelled",
        "jet"
    ],
    "sg:website":"http://www.cityjetski.com.au",
    "wof:name":"City Jet Ski",
    "wof:placetype":"venue"
},
  "geometry": {"coordinates":[144.89720153799999,-37.8544387817],"type":"Point"}
}