{
  "type": "Feature",
  "properties": {
    "iso:country":"AU",
    "sg:address":"145 Horton St",
    "sg:city":"Port Macquarie",
    "sg:classifiers":[
        {
            "category":"Real Estate",
            "subcategory":"Real Estate Agent",
            "type":"Services"
        }
    ],
    "sg:phone":"+61 2 6583 2699",
    "sg:postcode":"2444",
    "sg:province":"NSW",
    "wof:name":"Raine & Horne Port Macquarie",
    "wof:placetype":"venue"
},
  "geometry": {"coordinates":[152.908325,-31.433134],"type":"Point"}
}