{
  "type": "Feature",
  "properties": {
    "addr:full":"58 Ridley Rd Bridgeman Downs QLD 4035",
    "addr:housenumber":"58",
    "addr:postcode":"4035",
    "addr:street":"Ridley Rd",
    "iso:country":"AU",
    "sg:address":"58 Ridley Rd",
    "sg:city":"Bridgeman Downs",
    "sg:classifiers":[
        {
            "category":"Organizations",
            "subcategory":"Professional Association",
            "type":"Services"
        }
    ],
    "sg:phone":"+61 410 535 884",
    "sg:postcode":"4035",
    "sg:province":"QLD",
    "sg:tags":[
        "web",
        "internet"
    ],
    "wof:name":"Cybernamix Qld",
    "wof:placetype":"venue"
},
  "geometry": {"coordinates":[153.004547,-27.350233],"type":"Point"}
}