{
  "type": "Feature",
  "properties": {
    "addr:full":"104 Centre St Casino NSW 2470",
    "addr:housenumber":"104",
    "addr:postcode":"2470",
    "addr:street":"Centre St",
    "iso:country":"AU",
    "sg:address":"104 Centre St",
    "sg:city":"Casino",
    "sg:classifiers":[
        {
            "category":"Organizations",
            "subcategory":"Community Association",
            "type":"Services"
        }
    ],
    "sg:phone":"+61 2 6662 6792",
    "sg:postcode":"2470",
    "sg:province":"NSW",
    "sg:tags":[
        "organisation",
        "family",
        "welfare"
    ],
    "wof:name":"Family Support Service",
    "wof:placetype":"venue"
},
  "geometry": {"coordinates":[153.04745483400001,-28.8560276031],"type":"Point"}
}