{
  "type": "Feature",
  "properties": {
    "addr:full":"35 McPherson Rd Wyong NSW 2259",
    "addr:housenumber":"35",
    "addr:postcode":"2259",
    "addr:street":"Mcpherson Rd",
    "iso:country":"AU",
    "sg:address":"35 McPherson Rd",
    "sg:city":"Wyong",
    "sg:classifiers":[
        {
            "category":"Health Services",
            "subcategory":"Nursing And Care Facility",
            "type":"Services"
        }
    ],
    "sg:phone":"+61 2 4353 1733",
    "sg:postcode":"2259",
    "sg:province":"NSW",
    "sg:tags":[
        "home"
    ],
    "wof:name":"Wyong Nursing Home Management Pty Ltd",
    "wof:placetype":"venue"
},
  "geometry": {"coordinates":[151.42083740199999,-33.2889823914],"type":"Point"}
}