{
  "type": "Feature",
  "properties": {
    "addr:full":"27- 29 Collie St Fyshwick ACT 2609",
    "addr:housenumber":"29",
    "addr:postcode":"2609",
    "addr:street":"Collie St",
    "iso:country":"AU",
    "sg:address":"27- 29 Collie St",
    "sg:city":"Fyshwick",
    "sg:classifiers":[
        {
            "category":"Train Station",
            "subcategory":"Rail",
            "type":"Transportation"
        }
    ],
    "sg:phone":"+61 2 6239 2551",
    "sg:postcode":"2609",
    "sg:province":"ACT",
    "sg:tags":[
        "repair",
        "vinyl",
        "welding"
    ],
    "wof:name":"Uticolor Of Canberra",
    "wof:placetype":"venue"
},
  "geometry": {"coordinates":[149.18028259299999,-35.3276748657],"type":"Point"}
}