{
  "type": "Feature",
  "properties": {
    "addr:full":"Suite 9, 1 Bradly Ave Kirribilli NSW 2061",
    "addr:housenumber":"1",
    "addr:postcode":"2061",
    "addr:street":"Bradly Ave",
    "iso:country":"AU",
    "sg:address":"Suite 9, 1 Bradly Ave",
    "sg:city":"Kirribilli",
    "sg:classifiers":[
        {
            "category":"Recreation",
            "subcategory":"Boat Charter",
            "type":"Entertainment"
        }
    ],
    "sg:phone":"+61 1300 883 023",
    "sg:postcode":"2061",
    "sg:province":"NSW",
    "wof:name":"Eastcoast Sailing",
    "wof:placetype":"venue"
},
  "geometry": {"coordinates":[151.214752197,-33.8440208435],"type":"Point"}
}