{
  "type": "Feature",
  "properties": {
    "addr:full":"33 Kenilworth Crs Glen Waverley VIC 3150",
    "addr:housenumber":"33",
    "addr:postcode":"3150",
    "addr:street":"Kenilworth Crs",
    "iso:country":"AU",
    "sg:address":"33 Kenilworth Crs",
    "sg:city":"Glen Waverley",
    "sg:classifiers":[
        {
            "category":"Professional",
            "subcategory":"Computer Services",
            "type":"Services"
        }
    ],
    "sg:phone":"+61 3 9887 9773",
    "sg:postcode":"3150",
    "sg:province":"VIC",
    "sg:tags":[
        "consultant",
        "system"
    ],
    "wof:name":"Stevenson N.E.",
    "wof:placetype":"venue"
},
  "geometry": {"coordinates":[145.176269531,-37.8902015686],"type":"Point"}
}