{
  "type": "Feature",
  "properties": {
    "addr:full":"Shop 42, Woden Plz Woden ACT 2606",
    "addr:housenumber":"shop 42",
    "addr:postcode":"2606",
    "addr:street":"Woden Plz",
    "iso:country":"AU",
    "sg:address":"Shop 42, Woden Plz",
    "sg:city":"Woden",
    "sg:classifiers":[
        {
            "category":"Shopping",
            "subcategory":"Music",
            "type":"Retail Goods"
        }
    ],
    "sg:phone":"+61 1300 787 768",
    "sg:postcode":"2606",
    "sg:province":"ACT",
    "sg:tags":[
        "store"
    ],
    "wof:name":"The Music Shop",
    "wof:placetype":"venue"
},
  "geometry": {"coordinates":[149.081420898,-35.3464202881],"type":"Point"}
}