{
  "type": "Feature",
  "properties": {
    "iso:country":"AU",
    "sg:address":"46 Haynes St",
    "sg:city":"Kalamunda",
    "sg:classifiers":[
        {
            "category":"Real Estate",
            "subcategory":"Real Estate Agent",
            "type":"Services"
        }
    ],
    "sg:phone":"+61 8 9257 1177",
    "sg:postcode":"6076",
    "sg:province":"WA",
    "wof:name":"Kalamunda Properties - Professionals",
    "wof:placetype":"venue"
},
  "geometry": {"coordinates":[116.057502747,-31.9714355469],"type":"Point"}
}