{
  "type": "Feature",
  "properties": {
    "addr:full":"10 Silverbirch Ave Mardi NSW 2259",
    "addr:housenumber":"10",
    "addr:postcode":"2259",
    "addr:street":"Silverbirch Ave",
    "iso:country":"AU",
    "sg:address":"10 Silverbirch Ave",
    "sg:city":"Mardi",
    "sg:classifiers":[
        {
            "category":"Professional",
            "subcategory":"Computer Services",
            "type":"Services"
        }
    ],
    "sg:phone":"+61 2 4353 1055",
    "sg:postcode":"2259",
    "sg:province":"NSW",
    "sg:tags":[
        "consultant",
        "system"
    ],
    "wof:name":"Taylor Hardie Enterprises",
    "wof:placetype":"venue"
},
  "geometry": {"coordinates":[151.41294860799999,-33.2930107117],"type":"Point"}
}