{
  "type": "Feature",
  "properties": {
    "iso:country":"AU",
    "sg:address":"Suite 107/ 53 Phillip St",
    "sg:city":"Parramatta",
    "sg:classifiers":[
        {
            "category":"Professional",
            "subcategory":"Computer Services",
            "type":"Services"
        }
    ],
    "sg:phone":"+61 2 9635 0000",
    "sg:postcode":"2150",
    "sg:province":"NSW",
    "sg:tags":[
        "package",
        "software"
    ],
    "wof:name":"Companion Systems",
    "wof:placetype":"venue"
},
  "geometry": {"coordinates":[150.964569092,-33.8517074585],"type":"Point"}
}