{
  "type": "Feature",
  "properties": {
    "iso:country":"AU",
    "sg:address":"22 Railway Pl",
    "sg:city":"Preston",
    "sg:classifiers":[
        {
            "category":"Retail",
            "subcategory":"Auto Repair",
            "type":"Services"
        }
    ],
    "sg:phone":"+61 3 9480 4555",
    "sg:postcode":"3072",
    "sg:province":"VIC",
    "sg:tags":[
        "repairer",
        "motor",
        "engineer"
    ],
    "wof:name":"Molnar Engineering",
    "wof:placetype":"venue"
},
  "geometry": {"coordinates":[145.00001525900001,-37.7490539551],"type":"Point"}
}