{
  "type": "Feature",
  "properties": {
    "iso:country":"AU",
    "sg:address":"Fisher St",
    "sg:city":"Dee Why",
    "sg:classifiers":[
        {
            "category":"Health Services",
            "subcategory":"Dentist",
            "type":"Services"
        }
    ],
    "sg:phone":"+61 2 9982 8878",
    "sg:postcode":"2099",
    "sg:province":"NSW",
    "wof:name":"Dee Why Child Dental Clinic",
    "wof:placetype":"venue"
},
  "geometry": {"coordinates":[151.28695678700001,-33.7491226196],"type":"Point"}
}