{
  "type": "Feature",
  "properties": {
    "iso:country":"AU",
    "sg:address":"1a Wentworth St",
    "sg:city":"Wagga Wagga",
    "sg:classifiers":[
        {
            "category":"Wholesale",
            "subcategory":"Machinery & Supplies",
            "type":"Manufacturing & Wholesale Goods"
        }
    ],
    "sg:phone":"+61 2 6921 6234",
    "sg:postcode":"2650",
    "sg:province":"NSW",
    "sg:tags":[
        "equipment",
        "hydraulic"
    ],
    "wof:name":"Pirtek",
    "wof:placetype":"venue"
},
  "geometry": {"coordinates":[147.4115448,-35.1283149719],"type":"Point"}
}