{
  "type": "Feature",
  "properties": {
    "addr:full":"Shop 1/ 3 King St Cotton Tree QLD 4558",
    "addr:housenumber":"shop 1 / 3",
    "addr:postcode":"4558",
    "addr:street":"King St Cotton",
    "iso:country":"AU",
    "sg:address":"Shop 1/ 3 King St",
    "sg:city":"Cotton Tree",
    "sg:classifiers":[
        {
            "category":"Health Services",
            "subcategory":"Dentist",
            "type":"Services"
        }
    ],
    "sg:phone":"+61 7 5443 6918",
    "sg:postcode":"4558",
    "sg:province":"QLD",
    "wof:name":"Wynne Leigh C",
    "wof:placetype":"venue"
},
  "geometry": {"coordinates":[153.10061645499999,-26.6543617249],"type":"Point"}
}