{
  "type": "Feature",
  "properties": {
    "iso:country":"AU",
    "sg:address":"330 Belmore Rd",
    "sg:city":"Balwyn",
    "sg:classifiers":[
        {
            "category":"Health Services",
            "subcategory":"Dentist",
            "type":"Services"
        }
    ],
    "sg:phone":"+61 3 9816 3337",
    "sg:postcode":"3103",
    "sg:province":"VIC",
    "sg:tags":[
        "dental",
        "prosthetist"
    ],
    "wof:name":"Andrew Lack",
    "wof:placetype":"venue"
},
  "geometry": {"coordinates":[145.101928711,-37.8040657043],"type":"Point"}
}