{
  "type": "Feature",
  "properties": {
    "addr:full":"26 Stirling Ave Altona VIC 3018",
    "addr:housenumber":"26",
    "addr:postcode":"3018",
    "addr:street":"Stirling Ave",
    "iso:country":"AU",
    "sg:address":"26 Stirling Ave",
    "sg:city":"Altona",
    "sg:classifiers":[
        {
            "category":"Professional",
            "subcategory":"Detective & Security Services",
            "type":"Services"
        }
    ],
    "sg:phone":"+61 438 873 521",
    "sg:postcode":"3018",
    "sg:province":"VIC",
    "sg:tags":[
        "consultant",
        "system"
    ],
    "wof:name":"Watch 24 Security",
    "wof:placetype":"venue"
},
  "geometry": {"coordinates":[144.84359741200001,-37.8634300232],"type":"Point"}
}