{
  "type": "Feature",
  "properties": {
    "addr:full":"PO Box 1099 Cannington WA 6987",
    "addr:postcode":"6987",
    "iso:country":"AU",
    "sg:address":"PO Box 1099",
    "sg:city":"Cannington",
    "sg:classifiers":[
        {
            "category":"Building & Trades",
            "subcategory":"Pest Control",
            "type":"Services"
        }
    ],
    "sg:phone":"+61 8 9258 4244",
    "sg:postcode":"6987",
    "sg:province":"WA",
    "wof:name":"Atkins Pest Control",
    "wof:placetype":"venue"
},
  "geometry": {"coordinates":[115.939201,-32.019459],"type":"Point"}
}