{
  "type": "Feature",
  "properties": {
    "iso:country":"AU",
    "sg:address":"PO Box 80",
    "sg:city":"Silvan",
    "sg:classifiers":[
        {
            "category":"Professional",
            "type":"Services"
        }
    ],
    "sg:phone":"+61 400 334 681",
    "sg:postcode":"3795",
    "sg:province":"VIC",
    "sg:tags":[
        "transport"
    ],
    "wof:name":"D Ferro",
    "wof:placetype":"venue"
},
  "geometry": {"coordinates":[145.42576599099999,-37.8406906128],"type":"Point"}
}