{
  "type": "Feature",
  "properties": {
    "addr:full":"20 Taminga St Regency Park SA 5010",
    "addr:housenumber":"20",
    "addr:postcode":"5010",
    "addr:street":"Taminga St",
    "iso:country":"AU",
    "sg:address":"20 Taminga St",
    "sg:city":"Regency Park",
    "sg:classifiers":[
        {
            "category":"Bus Stop",
            "subcategory":"None",
            "type":"Transportation"
        }
    ],
    "sg:phone":"+61 8 8340 3411",
    "sg:postcode":"5010",
    "sg:province":"SA",
    "sg:tags":[
        "pipe",
        "fitting",
        "metal"
    ],
    "wof:name":"Tyco Water",
    "wof:placetype":"venue"
},
  "geometry": {"coordinates":[138.571899414,-34.8599472046],"type":"Point"}
}