{
  "type": "Feature",
  "properties": {
    "iso:country":"AU",
    "sg:address":"Shop 15/ 19 Stoddart Rd",
    "sg:city":"Prospect",
    "sg:classifiers":[
        {
            "category":"Professional",
            "subcategory":"Detective & Security Services",
            "type":"Services"
        }
    ],
    "sg:phone":"+61 2 9896 6205",
    "sg:postcode":"2148",
    "sg:province":"NSW",
    "sg:tags":[
        "consultant",
        "system"
    ],
    "wof:name":"Robert W Coles Investigation & Security",
    "wof:placetype":"venue"
},
  "geometry": {"coordinates":[150.920166016,-33.799911499],"type":"Point"}
}