{
  "type": "Feature",
  "properties": {
    "addr:full":"4 Barossa Crt Baulkham Hills NSW 2153",
    "addr:housenumber":"4",
    "addr:postcode":"2153",
    "addr:street":"Barossa Crt",
    "iso:country":"AU",
    "sg:address":"4 Barossa Crt",
    "sg:city":"Baulkham Hills",
    "sg:classifiers":[
        {
            "category":"Professional",
            "subcategory":"Accounting & Tax Preparation",
            "type":"Services"
        }
    ],
    "sg:phone":"+61 2 9674 3930",
    "sg:postcode":"2153",
    "sg:province":"NSW",
    "sg:tags":[
        "consultant",
        "taxation"
    ],
    "wof:name":"Florence S. Krattiger",
    "wof:placetype":"venue"
},
  "geometry": {"coordinates":[150.96522522000001,-33.7454223633],"type":"Point"}
}