{
  "type": "Feature",
  "properties": {
    "addr:full":"Shp10/ 68 Victoria St Victor Harbor SA 5211",
    "addr:housenumber":"68",
    "addr:postcode":"5211",
    "addr:street":"Victoria St",
    "iso:country":"AU",
    "sg:address":"Shp10/ 68 Victoria St",
    "sg:city":"Victor Harbor",
    "sg:classifiers":[
        {
            "category":"Shopping",
            "subcategory":"Clothing, Apparel, & Fashions",
            "type":"Retail Goods"
        }
    ],
    "sg:phone":"+61 8 8552 8561",
    "sg:postcode":"5211",
    "sg:province":"SA",
    "sg:tags":[
        "sportswear"
    ],
    "wof:name":"REV Limited Clothing",
    "wof:placetype":"venue"
},
  "geometry": {"coordinates":[138.61660766599999,-35.5574417114],"type":"Point"}
}