{
  "type": "Feature",
  "properties": {
    "addr:full":"16 Coburg St East Cleveland QLD 4163",
    "addr:housenumber":"16",
    "addr:postcode":"4163",
    "addr:street":"Coburg St",
    "iso:country":"AU",
    "sg:address":"16 Coburg St East",
    "sg:city":"Cleveland",
    "sg:classifiers":[
        {
            "category":"Professional",
            "type":"Services"
        }
    ],
    "sg:phone":"+61 7 3286 6811",
    "sg:postcode":"4163",
    "sg:province":"QLD",
    "sg:tags":[
        "transport"
    ],
    "wof:name":"Quad Transport",
    "wof:placetype":"venue"
},
  "geometry": {"coordinates":[153.27952575699999,-27.5326843262],"type":"Point"}
}