{
  "type": "Feature",
  "properties": {
    "iso:country":"AU",
    "sg:address":"Durham Rd",
    "sg:city":"Kilsyth",
    "sg:classifiers":[
        {
            "category":"Education",
            "subcategory":"School",
            "type":"Public Place"
        }
    ],
    "sg:phone":"+61 3 9725 4320",
    "sg:postcode":"3137",
    "sg:province":"VIC",
    "sg:tags":[
        "state",
        "except",
        "nsw"
    ],
    "wof:name":"Kilsyth Primary",
    "wof:placetype":"venue"
},
  "geometry": {"coordinates":[145.3152771,-37.8028068542],"type":"Point"}
}