{
  "type": "Feature",
  "properties": {
    "addr:full":"Brackenridge Plaza Cnr Norris & Telegraph Sts Bracken Ridge QLD 4017",
    "addr:postcode":"4017",
    "addr:street":"Cnr",
    "iso:country":"AU",
    "sg:address":"Brackenridge Plaza Cnr Norris & Telegraph Sts",
    "sg:city":"Bracken Ridge",
    "sg:classifiers":[
        {
            "category":"Food & Beverages",
            "subcategory":"Liquor & Beverages",
            "type":"Retail Goods"
        }
    ],
    "sg:phone":"+61 7 3261 7111",
    "sg:postcode":"4017",
    "sg:province":"QLD",
    "sg:tags":[
        "store"
    ],
    "wof:name":"Ridge Cellars",
    "wof:placetype":"venue"
},
  "geometry": {"coordinates":[153.025314331,-27.3308849335],"type":"Point"}
}