{
  "type": "Feature",
  "properties": {
    "addr:full":"Old Courthouse Isa St Mt Isa QLD 4825",
    "addr:postcode":"4825",
    "addr:street":"Isa St",
    "iso:country":"AU",
    "sg:address":"Old Courthouse Isa St",
    "sg:city":"Mt Isa",
    "sg:classifiers":[
        {
            "category":"Education",
            "subcategory":"University",
            "type":"Public Place"
        }
    ],
    "sg:phone":"+61 7 4749 1948",
    "sg:postcode":"4825",
    "sg:province":"QLD",
    "sg:tags":[
        "college",
        "tertiary"
    ],
    "wof:name":"Deakin University",
    "wof:placetype":"venue"
},
  "geometry": {"coordinates":[139.485657,-20.727497],"type":"Point"}
}