{
  "type": "Feature",
  "properties": {
    "addr:full":"179 Canterbury Rd Middle Park VIC 3206",
    "addr:housenumber":"179",
    "addr:postcode":"3206",
    "addr:street":"Canterbury Rd",
    "iso:country":"AU",
    "sg:address":"179 Canterbury Rd",
    "sg:city":"Middle Park",
    "sg:classifiers":[
        {
            "category":"Health Services",
            "subcategory":"Health Practitioner",
            "type":"Services"
        }
    ],
    "sg:phone":"+61 3 9537 2494",
    "sg:postcode":"3206",
    "sg:province":"VIC",
    "sg:tags":[
        "osteopath"
    ],
    "sg:website":"http://www.osteopathic.com.au",
    "wof:name":"Dr Joshua Brohier",
    "wof:placetype":"venue"
},
  "geometry": {"coordinates":[144.967117,-37.851158],"type":"Point"}
}