{
  "type": "Feature",
  "properties": {
    "iso:country":"AU",
    "sg:address":"30 Watson St",
    "sg:city":"Shepparton",
    "sg:classifiers":[
        {
            "category":"Farming",
            "subcategory":"Crops",
            "type":"Manufacturing & Wholesale Goods"
        }
    ],
    "sg:phone":"+61 3 5820 8777",
    "sg:postcode":"3630",
    "sg:province":"VIC",
    "sg:tags":[
        "warehousing"
    ],
    "wof:name":"Shepparton U Store",
    "wof:placetype":"venue"
},
  "geometry": {"coordinates":[145.41868591299999,-36.3874778748],"type":"Point"}
}