{
  "type": "Feature",
  "properties": {
    "iso:country":"AU",
    "sg:address":"200 Main Rd",
    "sg:city":"Blackwood",
    "sg:classifiers":[
        {
            "category":"Communications",
            "subcategory":"Film & Video Production",
            "type":"Services"
        }
    ],
    "sg:phone":"+61 8 8278 8038",
    "sg:postcode":"5051",
    "sg:province":"SA",
    "sg:tags":[
        "dvd",
        "library"
    ],
    "wof:name":"Video Ezy",
    "wof:placetype":"venue"
},
  "geometry": {"coordinates":[138.616592,-35.016541],"type":"Point"}
}