{
  "type": "Feature",
  "properties": {
    "iso:country":"AU",
    "sg:address":"U2/ 9 Lionel Donovan Drv",
    "sg:city":"Noosaville",
    "sg:classifiers":[
        {
            "category":"Autos & Motor Vehicles",
            "subcategory":"Auto Supplies",
            "type":"Retail Goods"
        }
    ],
    "sg:phone":"+61 7 5474 3985",
    "sg:postcode":"4566",
    "sg:province":"QLD",
    "sg:tags":[
        "camper-trailers",
        "caravan",
        "equipment"
    ],
    "wof:name":"Backtrax",
    "wof:placetype":"venue"
},
  "geometry": {"coordinates":[153.04751586899999,-26.4106140137],"type":"Point"}
}