{
  "type": "Feature",
  "properties": {
    "iso:country":"AU",
    "sg:address":"61 Flinders Rd",
    "sg:city":"Cronulla",
    "sg:classifiers":[
        {
            "category":"Utilities",
            "subcategory":"Electric",
            "type":"Services"
        }
    ],
    "sg:phone":"+61 411 214 955",
    "sg:postcode":"2230",
    "sg:province":"NSW",
    "sg:tags":[
        "electrical",
        "contractor"
    ],
    "wof:name":"Parr Brett Electrical",
    "wof:placetype":"venue"
},
  "geometry": {"coordinates":[151.144287109,-34.0457763672],"type":"Point"}
}