{
  "type": "Feature",
  "properties": {
    "iso:country":"AU",
    "sg:address":"13 Robertson Rd",
    "sg:city":"Killarney Vale",
    "sg:classifiers":[
        {
            "category":"Health Services",
            "subcategory":"Doctor",
            "type":"Services"
        }
    ],
    "sg:phone":"+61 2 4332 5666",
    "sg:postcode":"2261",
    "sg:province":"NSW",
    "sg:tags":[
        "medical",
        "practitioner"
    ],
    "wof:name":"Carroll Dianne, Doukakis Anthony & Burcher David",
    "wof:placetype":"venue"
},
  "geometry": {"coordinates":[151.46371500000001,-33.374134],"type":"Point"}
}