{
  "type": "Feature",
  "properties": {
    "addr:full":"40 Johnston St Fitzroy VIC 3065",
    "addr:housenumber":"40",
    "addr:postcode":"3065",
    "addr:street":"Johnston St",
    "iso:country":"AU",
    "sg:address":"40 Johnston St",
    "sg:city":"Fitzroy",
    "sg:classifiers":[
        {
            "category":"Professional",
            "subcategory":"Printing & Photocopies",
            "type":"Services"
        }
    ],
    "sg:phone":"+61 3 9486 0984",
    "sg:postcode":"3065",
    "sg:province":"VIC",
    "sg:tags":[
        "textile",
        "clothing"
    ],
    "wof:name":"The T-Shirt Takeaway",
    "wof:placetype":"venue"
},
  "geometry": {"coordinates":[144.97624206500001,-37.7981987],"type":"Point"}
}