{
  "type": "Feature",
  "properties": {
    "iso:country":"AU",
    "sg:address":"Unit 1/ 60 Cenrennial Crt",
    "sg:city":"Byron Bay",
    "sg:classifiers":[
        {
            "category":"Banks & Credit Unions",
            "subcategory":"Financial Services",
            "type":"Services"
        }
    ],
    "sg:phone":"+61 2 6639 6466",
    "sg:postcode":"2481",
    "sg:province":"NSW",
    "sg:tags":[
        "planning"
    ],
    "wof:name":"Genesys Wealth Advisers",
    "wof:placetype":"venue"
},
  "geometry": {"coordinates":[153.57853698700001,-28.6369514465],"type":"Point"}
}