{
  "type": "Feature",
  "properties": {
    "addr:full":"562 Seaview Rd Grange SA 5022",
    "addr:housenumber":"562",
    "addr:postcode":"5022",
    "addr:street":"Seaview Rd",
    "iso:country":"AU",
    "sg:address":"562 Seaview Rd",
    "sg:city":"Grange",
    "sg:classifiers":[
        {
            "category":"Organizations",
            "subcategory":"Community Association",
            "type":"Services"
        }
    ],
    "sg:phone":"+61 8 8356 7850",
    "sg:postcode":"5022",
    "sg:province":"SA",
    "sg:tags":[
        "organisation",
        "family",
        "welfare"
    ],
    "wof:name":"International Association Of Infant Message",
    "wof:placetype":"venue"
},
  "geometry": {"coordinates":[138.49053955100001,-34.9038848877],"type":"Point"}
}