{
  "type": "Feature",
  "properties": {
    "iso:country":"AU",
    "sg:address":"Unit 2/ 13 Stanley St",
    "sg:city":"Peakhurst",
    "sg:classifiers":[
        {
            "category":"Professional",
            "subcategory":"Engineering",
            "type":"Services"
        }
    ],
    "sg:phone":"+61 2 9584 1433",
    "sg:postcode":"2210",
    "sg:province":"NSW",
    "sg:tags":[
        "electronic",
        "engineer"
    ],
    "wof:name":"Ruraltronics Pty Ltd",
    "wof:placetype":"venue"
},
  "geometry": {"coordinates":[151.064819,-33.961842],"type":"Point"}
}