{
  "type": "Feature",
  "properties": {
    "iso:country":"AU",
    "sg:address":"1 Upward St",
    "sg:city":"Cairns",
    "sg:classifiers":[
        {
            "category":"Health Services",
            "subcategory":"Doctor",
            "type":"Services"
        }
    ],
    "sg:phone":"+61 7 4052 5271",
    "sg:postcode":"4870",
    "sg:province":"QLD",
    "sg:tags":[
        "medical",
        "practitioner"
    ],
    "wof:name":"Calvary Hospital",
    "wof:placetype":"venue"
},
  "geometry": {"coordinates":[145.7706604,-16.9146556854],"type":"Point"}
}