{
  "type": "Feature",
  "properties": {
    "iso:country":"AU",
    "sg:address":"Shop 2/Glenhaven Court, 78 Glenhaven Rd",
    "sg:city":"Glenhaven",
    "sg:classifiers":[
        {
            "category":"Personal",
            "subcategory":"Beauty Salon",
            "type":"Services"
        }
    ],
    "sg:phone":"+61 2 9680 4035",
    "sg:postcode":"2156",
    "sg:province":"NSW",
    "wof:name":"Glenhaven Beauty",
    "wof:placetype":"venue"
},
  "geometry": {"coordinates":[151.00140380900001,-33.6980209351],"type":"Point"}
}