{
  "type": "Feature",
  "properties": {
    "iso:country":"AU",
    "sg:address":"Princes Hwy",
    "sg:city":"Nowra",
    "sg:classifiers":[
        {
            "category":"Travel",
            "subcategory":"Hotels & Motels",
            "type":"Entertainment"
        }
    ],
    "sg:phone":"+61 2 4421 5222",
    "sg:postcode":"2541",
    "sg:province":"NSW",
    "sg:tags":[
        "accommodation"
    ],
    "wof:name":"Archer Resort & Convention Centre",
    "wof:placetype":"venue"
},
  "geometry": {"coordinates":[150.60472106899999,-34.8779563904],"type":"Point"}
}