{
  "type": "Feature",
  "properties": {
    "addr:full":"112a Kinghorne St Nowra NSW 2541",
    "addr:housenumber":"112a",
    "addr:postcode":"2541",
    "addr:street":"Kinghorne St",
    "iso:country":"AU",
    "sg:address":"112a Kinghorne St",
    "sg:city":"Nowra",
    "sg:classifiers":[
        {
            "category":"Shopping",
            "subcategory":"Antiques",
            "type":"Retail Goods"
        }
    ],
    "sg:phone":"+61 2 4422 9689",
    "sg:postcode":"2541",
    "sg:province":"NSW",
    "wof:name":"All Antiques and Collectables",
    "wof:placetype":"venue"
},
  "geometry": {"coordinates":[150.60267639200001,-34.877204895],"type":"Point"}
}