{
  "type": "Feature",
  "properties": {
    "iso:country":"AU",
    "sg:address":"460 K Rd",
    "sg:city":"Werribee South",
    "sg:classifiers":[
        {
            "category":"Food & Beverages",
            "subcategory":"Fruits & Vegetables",
            "type":"Retail Goods"
        }
    ],
    "sg:phone":"+61 419 919 129",
    "sg:postcode":"3030",
    "sg:province":"VIC",
    "sg:tags":[
        "grower"
    ],
    "wof:name":"Temuskos P A",
    "wof:placetype":"venue"
},
  "geometry": {"coordinates":[144.679138,-37.943638],"type":"Point"}
}