{
  "type": "Feature",
  "properties": {
    "addr:full":"Rear 457 Barkly St Footscray VIC 3011",
    "addr:housenumber":"457",
    "addr:postcode":"3011",
    "addr:street":"Barkly St",
    "iso:country":"AU",
    "sg:address":"Rear 457 Barkly St",
    "sg:city":"Footscray",
    "sg:classifiers":[
        {
            "category":"Retail",
            "subcategory":"Auto Repair",
            "type":"Services"
        }
    ],
    "sg:phone":"+61 3 9689 3211",
    "sg:postcode":"3011",
    "sg:province":"VIC",
    "sg:tags":[
        "engine",
        "reconditioning"
    ],
    "wof:name":"Footscray Engine Reconditioning",
    "wof:placetype":"venue"
},
  "geometry": {"coordinates":[144.883575439,-37.7981948853],"type":"Point"}
}