{
  "type": "Feature",
  "properties": {
    "addr:full":"189 Chesterville Rd Moorabbin VIC 3189",
    "addr:housenumber":"189",
    "addr:postcode":"3189",
    "addr:street":"Chesterville Rd",
    "iso:country":"AU",
    "sg:address":"189 Chesterville Rd",
    "sg:city":"Moorabbin",
    "sg:classifiers":[
        {
            "category":"Professional",
            "subcategory":"Printing & Photocopies",
            "type":"Services"
        }
    ],
    "sg:phone":"+61 3 9532 1180",
    "sg:postcode":"3189",
    "sg:province":"VIC",
    "sg:tags":[
        "photocopying"
    ],
    "wof:name":"Minuteman Press",
    "wof:placetype":"venue"
},
  "geometry": {"coordinates":[145.059448242,-37.9447021484],"type":"Point"}
}