{
  "type": "Feature",
  "properties": {
    "addr:full":"2 Addison Rd Enmore NSW 2042",
    "addr:housenumber":"2",
    "addr:postcode":"2042",
    "addr:street":"Addison Rd",
    "iso:country":"AU",
    "sg:address":"2 Addison Rd",
    "sg:city":"Enmore",
    "sg:classifiers":[
        {
            "category":"Travel",
            "subcategory":"Hotels & Motels",
            "type":"Entertainment"
        }
    ],
    "sg:phone":"+61 2 9557 1448",
    "sg:postcode":"2042",
    "sg:province":"NSW",
    "sg:tags":[
        "accommodation"
    ],
    "wof:name":"Victoria On The Park Hotel",
    "wof:placetype":"venue"
},
  "geometry": {"coordinates":[151.16812100000001,-33.90416],"type":"Point"}
}