{
  "type": "Feature",
  "properties": {
    "iso:country":"AU",
    "sg:address":"33 Foster St",
    "sg:city":"Surry Hills",
    "sg:classifiers":[
        {
            "category":"Utilities",
            "subcategory":"Telephone",
            "type":"Services"
        }
    ],
    "sg:phone":"+61 2 9281 9281",
    "sg:postcode":"2010",
    "sg:province":"NSW",
    "sg:tags":[
        "accessory"
    ],
    "wof:name":"N James Communications",
    "wof:placetype":"venue"
},
  "geometry": {"coordinates":[151.20967102,-33.8802108765],"type":"Point"}
}