{
  "type": "Feature",
  "properties": {
    "addr:full":"525 Main Neerim Rd Drouin West VIC 3818",
    "addr:housenumber":"525",
    "addr:postcode":"3818",
    "addr:street":"Main Neerim Rd",
    "iso:country":"AU",
    "sg:address":"525 Main Neerim Rd",
    "sg:city":"Drouin West",
    "sg:classifiers":[
        {
            "category":"Professional",
            "type":"Services"
        }
    ],
    "sg:phone":"+61 3 5625 2725",
    "sg:postcode":"3818",
    "sg:province":"VIC",
    "sg:tags":[
        "transport"
    ],
    "wof:name":"Suthers Freight & Furniture Removals",
    "wof:placetype":"venue"
},
  "geometry": {"coordinates":[145.87144499999999,-38.087658],"type":"Point"}
}