{
  "type": "Feature",
  "properties": {
    "addr:full":"18 Heath Ave Mt Evelyn VIC 3796",
    "addr:housenumber":"18",
    "addr:postcode":"3796",
    "addr:street":"Heath Ave",
    "iso:country":"AU",
    "sg:address":"18 Heath Ave",
    "sg:city":"Mt Evelyn",
    "sg:classifiers":[
        {
            "category":"Organizations",
            "subcategory":"Professional Association",
            "type":"Services"
        }
    ],
    "sg:phone":"+61 3 9737 0120",
    "sg:postcode":"3796",
    "sg:province":"VIC",
    "sg:tags":[
        "web",
        "internet"
    ],
    "wof:name":"Zion Internet Services",
    "wof:placetype":"venue"
},
  "geometry": {"coordinates":[145.382202148,-37.7791061401],"type":"Point"}
}