{
  "type": "Feature",
  "properties": {
    "addr:full":"Albert Rd Warragul VIC 3820",
    "addr:postcode":"3820",
    "addr:street":"Albert Rd",
    "iso:country":"AU",
    "sg:address":"Albert Rd",
    "sg:city":"Warragul",
    "sg:classifiers":[
        {
            "category":"Farming",
            "subcategory":"Farm",
            "type":"Manufacturing & Wholesale Goods"
        }
    ],
    "sg:phone":"+61 3 5623 2637",
    "sg:postcode":"3820",
    "sg:province":"VIC",
    "sg:tags":[
        "farmer"
    ],
    "wof:name":"Patrick J E C",
    "wof:placetype":"venue"
},
  "geometry": {"coordinates":[145.94078099999999,-38.161549],"type":"Point"}
}