{
  "type": "Feature",
  "properties": {
    "iso:country":"AU",
    "sg:address":"PO Box 327",
    "sg:city":"Gracemere",
    "sg:classifiers":[
        {
            "category":"Farming",
            "subcategory":"Farm & Veterinary Services",
            "type":"Manufacturing & Wholesale Goods"
        }
    ],
    "sg:phone":"+61 429 333 430",
    "sg:postcode":"4702",
    "sg:province":"QLD",
    "sg:tags":[
        "irrigation",
        "reticulation",
        "system"
    ],
    "wof:name":"Hortec Landscaping & Irrigation",
    "wof:placetype":"venue"
},
  "geometry": {"coordinates":[150.452194214,-23.4334201813],"type":"Point"}
}