{
  "type": "Feature",
  "properties": {
    "addr:full":"29 Marshalltown Rd Marshall VIC 3216",
    "addr:housenumber":"29",
    "addr:postcode":"3216",
    "addr:street":"Marshalltown Rd",
    "iso:country":"AU",
    "sg:address":"29 Marshalltown Rd",
    "sg:city":"Marshall",
    "sg:classifiers":[
        {
            "category":"Personal",
            "subcategory":"Beauty Salon",
            "type":"Services"
        }
    ],
    "sg:phone":"+61 3 5241 2105",
    "sg:postcode":"3216",
    "sg:province":"VIC",
    "wof:name":"Irmelas Beauty Care",
    "wof:placetype":"venue"
},
  "geometry": {"coordinates":[144.35934448200001,-38.1973838806],"type":"Point"}
}