{
  "type": "Feature",
  "properties": {
    "addr:full":"PO Box 374 Albion QLD 4010",
    "addr:postcode":"4010",
    "iso:country":"AU",
    "sg:address":"PO Box 374",
    "sg:city":"Albion",
    "sg:classifiers":[
        {
            "category":"Professional",
            "subcategory":"Accounting & Tax Preparation",
            "type":"Services"
        }
    ],
    "sg:phone":"+61 418 154 073",
    "sg:postcode":"4010",
    "sg:province":"QLD",
    "sg:tags":[
        "bookkeeping"
    ],
    "wof:name":"Vivienne Nolan",
    "wof:placetype":"venue"
},
  "geometry": {"coordinates":[153.04165649399999,-27.4302997589],"type":"Point"}
}