{
  "type": "Feature",
  "properties": {
    "addr:full":"6 / 56 Hoskins St Mitchell ACT 2911",
    "addr:housenumber":"/ 56",
    "addr:postcode":"2911",
    "addr:street":"Hoskins St",
    "iso:country":"AU",
    "sg:address":"6 / 56 Hoskins St",
    "sg:city":"Mitchell",
    "sg:classifiers":[
        {
            "category":"Health Services",
            "subcategory":"Doctor",
            "type":"Services"
        }
    ],
    "sg:phone":"+61 2 6241 5011",
    "sg:postcode":"2911",
    "sg:province":"ACT",
    "sg:tags":[
        "occupational",
        "safety"
    ],
    "wof:name":"National Safety Council of Australia",
    "wof:placetype":"venue"
},
  "geometry": {"coordinates":[149.13769531200001,-35.215511322],"type":"Point"}
}