{
  "type": "Feature",
  "properties": {
    "addr:full":"Shop 2120, Westfield Garden City, Cnr Logan & Kess Mt Gravatt QLD 4122",
    "addr:housenumber":"2120",
    "addr:postcode":"4122",
    "addr:street":"Westfield Garden;Cnr",
    "iso:country":"AU",
    "sg:address":"Shop 2120, Westfield Garden City, Cnr Logan & Kess",
    "sg:city":"Mt Gravatt",
    "sg:classifiers":[
        {
            "category":"Shopping",
            "subcategory":"Clothing, Apparel, & Fashions",
            "type":"Retail Goods"
        }
    ],
    "sg:phone":"+61 7 3343 5293",
    "sg:postcode":"4122",
    "sg:province":"QLD",
    "sg:tags":[
        "menswear"
    ],
    "wof:name":"Jag",
    "wof:placetype":"venue"
},
  "geometry": {"coordinates":[153.07232665999999,-27.5301265717],"type":"Point"}
}