{
  "type": "Feature",
  "properties": {
    "addr:full":"Lot 1541 Poincettia Way Kununurra WA 6743",
    "addr:housenumber":"1541",
    "addr:postcode":"6743",
    "addr:street":"Poincettia Way",
    "iso:country":"AU",
    "sg:address":"Lot 1541 Poincettia Way",
    "sg:city":"Kununurra",
    "sg:classifiers":[
        {
            "category":"Building & Trades",
            "subcategory":"Plumbing",
            "type":"Services"
        }
    ],
    "sg:phone":"+61 8 9168 1224",
    "sg:postcode":"6743",
    "sg:province":"WA",
    "sg:tags":[
        "plumber",
        "gasfitters"
    ],
    "wof:name":"East Kimberley Plumbing",
    "wof:placetype":"venue"
},
  "geometry": {"coordinates":[128.74606323200001,-15.7633066177],"type":"Point"}
}