{
  "type": "Feature",
  "properties": {
    "iso:country":"AU",
    "sg:address":"U5/67 67 Talavera Rd",
    "sg:city":"North Ryde",
    "sg:classifiers":[
        {
            "category":"Health Services",
            "subcategory":"Health Practitioner",
            "type":"Services"
        }
    ],
    "sg:phone":"+61 402 333 907",
    "sg:postcode":"2113",
    "sg:province":"NSW",
    "sg:tags":[
        "psychologist"
    ],
    "wof:name":"Dr. Charlotte Morgan",
    "wof:placetype":"venue"
},
  "geometry": {"coordinates":[151.12351989699999,-33.7766265869],"type":"Point"}
}