{
  "type": "Feature",
  "properties": {
    "addr:full":"57 Urquhart St Horsham VIC 3400",
    "addr:housenumber":"57",
    "addr:postcode":"3400",
    "addr:street":"Urquhart St",
    "iso:country":"AU",
    "sg:address":"57 Urquhart St",
    "sg:city":"Horsham",
    "sg:classifiers":[
        {
            "category":"Building & Trades",
            "subcategory":"Construction",
            "type":"Services"
        }
    ],
    "sg:phone":"+61 3 5382 2539",
    "sg:postcode":"3400",
    "sg:province":"VIC",
    "sg:tags":[
        "fencing",
        "contractor"
    ],
    "wof:name":"Strauss Homework P/L",
    "wof:placetype":"venue"
},
  "geometry": {"coordinates":[142.202362061,-36.7208099365],"type":"Point"}
}