{
  "type": "Feature",
  "properties": {
    "addr:full":"PO Box 25 Plumpton NSW 2761",
    "addr:postcode":"2761",
    "iso:country":"AU",
    "sg:address":"PO Box 25",
    "sg:city":"Plumpton",
    "sg:classifiers":[
        {
            "category":"Professional",
            "type":"Services"
        }
    ],
    "sg:phone":"+61 1300 133 076",
    "sg:postcode":"2761",
    "sg:province":"NSW",
    "sg:tags":[
        "courier"
    ],
    "wof:name":"Australia Wide Pilot & Courier Services",
    "wof:placetype":"venue"
},
  "geometry": {"coordinates":[150.83421300000001,-33.747028],"type":"Point"}
}