{
  "type": "Feature",
  "properties": {
    "iso:country":"AU",
    "sg:address":"39 Bellombi St",
    "sg:city":"Campsie",
    "sg:classifiers":[
        {
            "category":"Building & Trades",
            "subcategory":"Construction",
            "type":"Services"
        }
    ],
    "sg:phone":"+61 2 9789 3399",
    "sg:postcode":"2194",
    "sg:province":"NSW",
    "sg:tags":[
        "underpinning"
    ],
    "wof:name":"Waine Mark Underpinning Contractor",
    "wof:placetype":"venue"
},
  "geometry": {"coordinates":[151.110657,-33.908512],"type":"Point"}
}