{
  "type": "Feature",
  "properties": {
    "addr:full":"PO Box 94 Mansfield QLD 4122",
    "addr:postcode":"4122",
    "iso:country":"AU",
    "sg:address":"PO Box 94",
    "sg:city":"Mansfield",
    "sg:classifiers":[
        {
            "category":"Real Estate",
            "subcategory":"Real Estate Services",
            "type":"Services"
        }
    ],
    "sg:phone":"+61 437 399 927",
    "sg:postcode":"4122",
    "sg:province":"QLD",
    "sg:tags":[
        "listing"
    ],
    "wof:name":"Dwelling.com.au",
    "wof:placetype":"venue"
},
  "geometry": {"coordinates":[153.09487915,-27.5326805115],"type":"Point"}
}