{
  "type": "Feature",
  "properties": {
    "addr:full":"63 Kurnall Rd Welshpool WA 6106",
    "addr:housenumber":"63",
    "addr:postcode":"6106",
    "addr:street":"Kurnall Rd",
    "iso:country":"AU",
    "sg:address":"63 Kurnall Rd",
    "sg:city":"Welshpool",
    "sg:classifiers":[
        {
            "category":"Building & Trades",
            "subcategory":"Electrical",
            "type":"Services"
        }
    ],
    "sg:phone":"+61 8 9358 1188",
    "sg:postcode":"6106",
    "sg:province":"WA",
    "sg:tags":[
        "repair",
        "generator",
        "electric",
        "motor"
    ],
    "wof:name":"Downunder Submersible Motors P/L",
    "wof:placetype":"venue"
},
  "geometry": {"coordinates":[115.95767211899999,-31.9925022125],"type":"Point"}
}