{
  "type": "Feature",
  "properties": {
    "iso:country":"AU",
    "sg:address":"Suite 6, 52 Minorie Drv, Busy Bee Complex",
    "sg:city":"Toormina",
    "sg:classifiers":[
        {
            "category":"Shopping",
            "subcategory":"Bicycles & Sporting Goods",
            "type":"Retail Goods"
        }
    ],
    "sg:phone":"+61 418 483 536",
    "sg:postcode":"2452",
    "sg:province":"NSW",
    "sg:tags":[
        "dance",
        "accessory",
        "wear",
        "supply"
    ],
    "wof:name":"Caliente Dance Wear",
    "wof:placetype":"venue"
},
  "geometry": {"coordinates":[153.094391,-30.354893],"type":"Point"}
}