{
  "type": "Feature",
  "properties": {
    "addr:full":"53 Osborne Ave Springvale VIC 3171",
    "addr:housenumber":"53",
    "addr:postcode":"3171",
    "addr:street":"Osborne Ave",
    "iso:country":"AU",
    "sg:address":"53 Osborne Ave",
    "sg:city":"Springvale",
    "sg:classifiers":[
        {
            "category":"Shopping",
            "type":"Retail Goods"
        }
    ],
    "sg:phone":"+61 3 9546 1033",
    "sg:postcode":"3171",
    "sg:province":"VIC",
    "sg:tags":[
        "equipment",
        "safety",
        "accessory"
    ],
    "wof:name":"Talair United Tools P/L",
    "wof:placetype":"venue"
},
  "geometry": {"coordinates":[145.143066406,-37.9461212158],"type":"Point"}
}