{
  "type": "Feature",
  "properties": {
    "iso:country":"AU",
    "sg:address":"284 Greensward Rd",
    "sg:city":"Tamborine",
    "sg:phone":"+61 7 5543 8814",
    "sg:postcode":"4270",
    "sg:province":"QLD",
    "wof:name":"AAA Poly Tanks",
    "wof:placetype":"venue"
},
  "geometry": {"coordinates":[153.111495972,-27.8484745026],"type":"Point"}
}