{
  "type": "Feature",
  "properties": {
    "addr:full":"Shop 1/ 471 Sydney Rd Coburg VIC 3058",
    "addr:housenumber":"shop 1 / 471",
    "addr:postcode":"3058",
    "addr:street":"Sydney Rd",
    "iso:country":"AU",
    "sg:address":"Shop 1/ 471 Sydney Rd",
    "sg:city":"Coburg",
    "sg:classifiers":[
        {
            "category":"Shopping",
            "subcategory":"Clothing, Apparel, & Fashions",
            "type":"Retail Goods"
        }
    ],
    "sg:phone":"+61 3 9354 1381",
    "sg:postcode":"3058",
    "sg:province":"VIC",
    "sg:tags":[
        "jean"
    ],
    "wof:name":"Zippers Jeans",
    "wof:placetype":"venue"
},
  "geometry": {"coordinates":[144.9662323,-37.7421340942],"type":"Point"}
}