{
  "type": "Feature",
  "properties": {
    "iso:country":"AU",
    "sg:address":"968 Wynnum Rd",
    "sg:city":"Cannon Hill",
    "sg:classifiers":[
        {
            "category":"Health Services",
            "subcategory":"Doctor",
            "type":"Services"
        }
    ],
    "sg:phone":"+61 7 3399 7964",
    "sg:postcode":"4170",
    "sg:province":"QLD",
    "sg:tags":[
        "medical",
        "practitioner"
    ],
    "wof:name":"Mason D S",
    "wof:placetype":"venue"
},
  "geometry": {"coordinates":[153.08921814000001,-27.4682254791],"type":"Point"}
}