{
  "type": "Feature",
  "properties": {
    "iso:country":"AU",
    "sg:address":"31 Roberts Rd",
    "sg:city":"Belmont",
    "sg:classifiers":[
        {
            "category":"Personal",
            "subcategory":"Beauty Salon",
            "type":"Services"
        }
    ],
    "sg:phone":"+61 3 5241 1740",
    "sg:postcode":"3216",
    "sg:province":"VIC",
    "sg:tags":[
        "hairdresser"
    ],
    "wof:name":"Ro-Ann Hair Design",
    "wof:placetype":"venue"
},
  "geometry": {"coordinates":[144.33050537099999,-38.1726226807],"type":"Point"}
}