{
  "type": "Feature",
  "properties": {
    "iso:country":"AU",
    "sg:address":"17 Grant Rd",
    "sg:city":"Somerville",
    "sg:classifiers":[
        {
            "category":"Autos & Motor Vehicles",
            "subcategory":"Auto Supplies",
            "type":"Retail Goods"
        }
    ],
    "sg:phone":"+61 3 5977 5571",
    "sg:postcode":"3912",
    "sg:province":"VIC",
    "sg:tags":[
        "tyre"
    ],
    "wof:name":"Somerville Mechanical Repairs",
    "wof:placetype":"venue"
},
  "geometry": {"coordinates":[145.17645263700001,-38.2218551636],"type":"Point"}
}