{
  "type": "Feature",
  "properties": {
    "iso:country":"AU",
    "sg:address":"8 Beach St",
    "sg:city":"Clovelly",
    "sg:classifiers":[
        {
            "category":"Real Estate",
            "subcategory":"Architect",
            "type":"Services"
        }
    ],
    "sg:phone":"+61 2 9664 3180",
    "sg:postcode":"2031",
    "sg:province":"NSW",
    "sg:tags":[
        "building",
        "designer"
    ],
    "wof:name":"Contextual Solutions",
    "wof:placetype":"venue"
},
  "geometry": {"coordinates":[151.259963989,-33.911441803],"type":"Point"}
}