{
  "type": "Feature",
  "properties": {
    "addr:full":"Factory 3, 26 Moresby Ave Seaford VIC 3198",
    "addr:housenumber":"26",
    "addr:postcode":"3198",
    "addr:street":"Moresby Ave",
    "iso:country":"AU",
    "sg:address":"Factory 3, 26 Moresby Ave",
    "sg:city":"Seaford",
    "sg:classifiers":[
        {
            "category":"Manufacturing",
            "subcategory":"Metals",
            "type":"Manufacturing & Wholesale Goods"
        }
    ],
    "sg:phone":"+61 3 9786 2247",
    "sg:postcode":"3198",
    "sg:province":"VIC",
    "sg:tags":[
        "leaf",
        "gold"
    ],
    "wof:name":"Weyermann Nominees Pty Ltd",
    "wof:placetype":"venue"
},
  "geometry": {"coordinates":[145.133575439,-38.1171875],"type":"Point"}
}