{
  "type": "Feature",
  "properties": {
    "iso:country":"AU",
    "sg:address":"107 Jacaranda Ave",
    "sg:city":"Kingston",
    "sg:classifiers":[
        {
            "category":"Building & Trades",
            "subcategory":"Construction",
            "type":"Services"
        }
    ],
    "sg:phone":"+61 7 3209 2185",
    "sg:postcode":"4114",
    "sg:province":"QLD",
    "sg:tags":[
        "earth",
        "excavating",
        "moving",
        "contractor"
    ],
    "wof:name":"Harper's Bobcat Hire",
    "wof:placetype":"venue"
},
  "geometry": {"coordinates":[153.110595703,-27.6512622833],"type":"Point"}
}