{
  "type": "Feature",
  "properties": {
    "addr:full":"San Mateo Ave Mildura VIC 3500",
    "addr:postcode":"3500",
    "addr:street":"San Mateo Ave",
    "iso:country":"AU",
    "sg:address":"San Mateo Ave",
    "sg:city":"Mildura",
    "sg:classifiers":[
        {
            "category":"Wholesale",
            "subcategory":"Machinery & Supplies",
            "type":"Manufacturing & Wholesale Goods"
        }
    ],
    "sg:phone":"+61 3 5021 1933",
    "sg:postcode":"3500",
    "sg:province":"VIC",
    "sg:tags":[
        "agricultural"
    ],
    "wof:name":"Spagnolo Engineering",
    "wof:placetype":"venue"
},
  "geometry": {"coordinates":[142.14712524399999,-34.2062301636],"type":"Point"}
}