{
  "type": "Feature",
  "properties": {
    "addr:full":"88 Pittown Rd McGraths Hill NSW 2756",
    "addr:housenumber":"88",
    "addr:postcode":"2756",
    "addr:street":"Pittown Rd",
    "iso:country":"AU",
    "sg:address":"88 Pittown Rd",
    "sg:city":"McGraths Hill",
    "sg:classifiers":[
        {
            "category":"Building & Trades",
            "subcategory":"Equipment Rental",
            "type":"Services"
        }
    ],
    "sg:phone":"+61 2 4577 5222",
    "sg:postcode":"2756",
    "sg:province":"NSW",
    "sg:tags":[
        "builder",
        "contractor"
    ],
    "wof:name":"Cavalier Homes Northwest Pty Ltd",
    "wof:placetype":"venue"
},
  "geometry": {"coordinates":[150.84251403799999,-33.6123390198],"type":"Point"}
}