{
  "type": "Feature",
  "properties": {
    "addr:full":"10 Earls Crt Calamvale QLD 4116",
    "addr:housenumber":"10",
    "addr:postcode":"4116",
    "addr:street":"Earls Crt",
    "iso:country":"AU",
    "sg:address":"10 Earls Crt",
    "sg:city":"Calamvale",
    "sg:classifiers":[
        {
            "category":"Building & Trades",
            "subcategory":"Cleaning & Sanitation",
            "type":"Services"
        }
    ],
    "sg:phone":"+61 7 3711 6664",
    "sg:postcode":"4116",
    "sg:province":"QLD",
    "sg:tags":[
        "industrial",
        "commercial",
        "contractor"
    ],
    "wof:name":"Wilds Essential Services",
    "wof:placetype":"venue"
},
  "geometry": {"coordinates":[153.04820251500001,-27.6307201385],"type":"Point"}
}