{
  "type": "Feature",
  "properties": {
    "iso:country":"AU",
    "sg:address":"Lot 18 Garema St",
    "sg:city":"Cannonvale",
    "sg:classifiers":[
        {
            "category":"Professional",
            "subcategory":"Detective & Security Services",
            "type":"Services"
        }
    ],
    "sg:phone":"+61 7 4946 4055",
    "sg:postcode":"4802",
    "sg:province":"QLD",
    "sg:tags":[
        "equipment",
        "window",
        "doors"
    ],
    "wof:name":"Airlie Glass & Aluminium",
    "wof:placetype":"venue"
},
  "geometry": {"coordinates":[148.68292236299999,-20.2831268311],"type":"Point"}
}