{
  "type": "Feature",
  "properties": {
    "iso:country":"AU",
    "sg:address":"39 Ninth Ave",
    "sg:city":"Railway Estate",
    "sg:classifiers":[
        {
            "category":"Education",
            "subcategory":"School",
            "type":"Public Place"
        }
    ],
    "sg:phone":"+61 7 4772 3729",
    "sg:postcode":"4810",
    "sg:province":"QLD",
    "sg:tags":[
        "state",
        "except",
        "nsw"
    ],
    "wof:name":"Railway Estate Preschool",
    "wof:placetype":"venue"
},
  "geometry": {"coordinates":[146.816864,-19.275969],"type":"Point"}
}