{
  "type": "Feature",
  "properties": {
    "addr:full":"PO Box 427 Warrnambool VIC 3280",
    "addr:postcode":"3280",
    "iso:country":"AU",
    "sg:address":"PO Box 427",
    "sg:city":"Warrnambool",
    "sg:classifiers":[
        {
            "category":"Building & Trades",
            "subcategory":"Landscaping Services",
            "type":"Services"
        }
    ],
    "sg:phone":"+61 428 999 683",
    "sg:postcode":"3280",
    "sg:province":"VIC",
    "sg:tags":[
        "control",
        "weed"
    ],
    "wof:name":"Spencer's Ag Spray",
    "wof:placetype":"venue"
},
  "geometry": {"coordinates":[142.48323059099999,-38.3842582703],"type":"Point"}
}