{
  "type": "Feature",
  "properties": {
    "addr:full":"PO Box 42256 Casuarina NT 0811",
    "addr:postcode":"nt 0811",
    "iso:country":"AU",
    "sg:address":"PO Box 42256",
    "sg:city":"Casuarina",
    "sg:classifiers":[
        {
            "category":"Communications",
            "type":"Services"
        }
    ],
    "sg:phone":"+61 8 8948 0519",
    "sg:postcode":"0811",
    "sg:province":"NT",
    "sg:tags":[
        "public",
        "system",
        "address"
    ],
    "wof:name":"Audio Technology NT Pty Ltd",
    "wof:placetype":"venue"
},
  "geometry": {"coordinates":[130.858886719,-12.3764762878],"type":"Point"}
}