{
  "type": "Feature",
  "properties": {
    "iso:country":"AU",
    "sg:address":"15 Altona Ave",
    "sg:city":"Forestville",
    "sg:classifiers":[
        {
            "category":"Building & Trades",
            "subcategory":"Plumbing",
            "type":"Services"
        }
    ],
    "sg:phone":"+61 2 9452 2305",
    "sg:postcode":"2087",
    "sg:province":"NSW",
    "sg:tags":[
        "plumber",
        "gasfitters"
    ],
    "wof:name":"Altona Plumbing",
    "wof:placetype":"venue"
},
  "geometry": {"coordinates":[151.21934509299999,-33.7544288635],"type":"Point"}
}