{
  "type": "Feature",
  "properties": {
    "iso:country":"AU",
    "sg:address":"51 Larra St",
    "sg:city":"Yennora",
    "sg:classifiers":[
        {
            "category":"Shopping",
            "subcategory":"Stationery & Office Supplies",
            "type":"Retail Goods"
        }
    ],
    "sg:phone":"+61 2 9892 2233",
    "sg:postcode":"2161",
    "sg:province":"NSW",
    "sg:tags":[
        "packaging",
        "equipment",
        "sealing",
        "filling"
    ],
    "wof:name":"Goodman Packaging",
    "wof:placetype":"venue"
},
  "geometry": {"coordinates":[150.97434997600001,-33.864074707],"type":"Point"}
}