{
  "type": "Feature",
  "properties": {
    "addr:full":"37a Rohini St Turramurra NSW 2074",
    "addr:housenumber":"37a",
    "addr:postcode":"2074",
    "addr:street":"Rohini St",
    "iso:country":"AU",
    "sg:address":"37a Rohini St",
    "sg:city":"Turramurra",
    "sg:classifiers":[
        {
            "category":"Health Services",
            "subcategory":"Health Practitioner",
            "type":"Services"
        }
    ],
    "sg:phone":"+61 2 9440 1631",
    "sg:postcode":"2074",
    "sg:province":"NSW",
    "sg:tags":[
        "naturopath"
    ],
    "wof:name":"All Health Clinic",
    "wof:placetype":"venue"
},
  "geometry": {"coordinates":[151.12887573200001,-33.7319946289],"type":"Point"}
}