{
  "type": "Feature",
  "properties": {
    "addr:full":"Orr St Queenstown TAS 7467",
    "addr:postcode":"7467",
    "addr:street":"Orr St",
    "iso:country":"AU",
    "sg:address":"Orr St",
    "sg:city":"Queenstown",
    "sg:classifiers":[
        {
            "category":"Education",
            "subcategory":"School",
            "type":"Public Place"
        }
    ],
    "sg:phone":"+61 3 6471 1139",
    "sg:postcode":"7467",
    "sg:province":"TAS",
    "sg:tags":[
        "co-educational"
    ],
    "wof:name":"St Joseph",
    "wof:placetype":"venue"
},
  "geometry": {"coordinates":[145.55702209500001,-42.0802192688],"type":"Point"}
}