{
  "type": "Feature",
  "properties": {
    "addr:full":"Suite 74, Chatswood Village, 47 Neridah St Chatswood NSW 2057",
    "addr:housenumber":"47",
    "addr:postcode":"2057",
    "addr:street":"Village;St",
    "iso:country":"AU",
    "sg:address":"Suite 74, Chatswood Village, 47 Neridah St",
    "sg:city":"Chatswood",
    "sg:classifiers":[
        {
            "category":"Health Services",
            "subcategory":"Health Practitioner",
            "type":"Services"
        }
    ],
    "sg:phone":"+61 2 9415 4845",
    "sg:postcode":"2057",
    "sg:province":"NSW",
    "sg:tags":[
        "dietitian"
    ],
    "wof:name":"Northside Nutrition & Dietetics",
    "wof:placetype":"venue"
},
  "geometry": {"coordinates":[151.18768299999999,-33.796474],"type":"Point"}
}