{
  "type": "Feature",
  "properties": {
    "iso:country":"AU",
    "sg:address":"8 Sturt Pl",
    "sg:city":"Taree",
    "sg:classifiers":[
        {
            "category":"Building & Trades",
            "subcategory":"Construction",
            "type":"Services"
        }
    ],
    "sg:phone":"+61 2 6552 2803",
    "sg:postcode":"2430",
    "sg:province":"NSW",
    "sg:tags":[
        "contractor"
    ],
    "wof:name":"Louis S & K",
    "wof:placetype":"venue"
},
  "geometry": {"coordinates":[152.47938500000001,-31.893028],"type":"Point"}
}