{
  "type": "Feature",
  "properties": {
    "addr:full":"91 Clarendon St South Melbourne VIC 3205",
    "addr:housenumber":"91",
    "addr:postcode":"3205",
    "addr:street":"Clarendon St",
    "iso:country":"AU",
    "sg:address":"91 Clarendon St",
    "sg:city":"South Melbourne",
    "sg:classifiers":[
        {
            "category":"Autos & Motor Vehicles",
            "subcategory":"Automobile Sales",
            "type":"Retail Goods"
        }
    ],
    "sg:phone":"+61 3 9696 6633",
    "sg:postcode":"3205",
    "sg:province":"VIC",
    "sg:tags":[
        "car",
        "used"
    ],
    "wof:name":"Tripple S Motors",
    "wof:placetype":"venue"
},
  "geometry": {"coordinates":[144.96270799999999,-37.835869],"type":"Point"}
}