{
  "type": "Feature",
  "properties": {
    "addr:full":"Unit 39 351 Beams Rd Taigum QLD 4018",
    "addr:housenumber":"351",
    "addr:postcode":"4018",
    "addr:street":"Beams Rd",
    "iso:country":"AU",
    "sg:address":"Unit 39 351 Beams Rd",
    "sg:city":"Taigum",
    "sg:classifiers":[
        {
            "category":"Professional",
            "subcategory":"Lawyer & Legal Services",
            "type":"Services"
        }
    ],
    "sg:phone":"+61 7 3865 4944",
    "sg:postcode":"4018",
    "sg:province":"QLD",
    "sg:tags":[
        "process",
        "server"
    ],
    "wof:name":"Bolton David & Associates",
    "wof:placetype":"venue"
},
  "geometry": {"coordinates":[153.039795,-27.350058],"type":"Point"}
}