{
  "type": "Feature",
  "properties": {
    "addr:full":"3 Lorrean Ave Brighton East VIC 3187",
    "addr:housenumber":"3",
    "addr:postcode":"3187",
    "addr:street":"Lorrean Ave",
    "iso:country":"AU",
    "sg:address":"3 Lorrean Ave",
    "sg:city":"Brighton East",
    "sg:classifiers":[
        {
            "category":"Education",
            "subcategory":"Special Training",
            "type":"Public Place"
        }
    ],
    "sg:phone":"+61 3 9578 5637",
    "sg:postcode":"3187",
    "sg:province":"VIC",
    "sg:tags":[
        "tuition-educational"
    ],
    "wof:name":"Accounting Bookkeeping Tuition",
    "wof:placetype":"venue"
},
  "geometry": {"coordinates":[145.02256774899999,-37.9045219421],"type":"Point"}
}