{
  "type": "Feature",
  "properties": {
    "iso:country":"AU",
    "sg:address":"15 Barr Street",
    "sg:city":"Balmain",
    "sg:classifiers":[
        {
            "category":"Professional",
            "subcategory":"Business Services",
            "type":"Services"
        }
    ],
    "sg:postcode":"2010",
    "sg:tags":[
        "p2p",
        "australia",
        "sydney",
        "lending",
        "social-lending",
        "zopa",
        "prosper",
        "funds-management",
        "mutual-fund",
        "online-finance"
    ],
    "sg:website":"http://www.directmoney.com.au",
    "wof:name":"DirectMoney",
    "wof:placetype":"venue"
},
  "geometry": {"coordinates":[151.175409,-33.857834],"type":"Point"}
}