{
  "type": "Feature",
  "properties": {
    "addr:full":"308 Fitzgerald St Perth WA 6000",
    "addr:housenumber":"308",
    "addr:postcode":"6000",
    "addr:street":"Fitzgerald St",
    "iso:country":"AU",
    "sg:address":"308 Fitzgerald St",
    "sg:city":"Perth",
    "sg:classifiers":[
        {
            "category":"Real Estate",
            "subcategory":"Real Estate Agent",
            "type":"Services"
        }
    ],
    "sg:phone":"+61 8 9228 3055",
    "sg:postcode":"6000",
    "sg:province":"WA",
    "wof:name":"Realty Executives Keith Howes & Associates",
    "wof:placetype":"venue"
},
  "geometry": {"coordinates":[115.855911255,-31.9401111603],"type":"Point"}
}