{
  "type": "Feature",
  "properties": {
    "addr:full":"1244 Burwood Hwy Upper Ferntree Gully VIC 3156",
    "addr:housenumber":"1244",
    "addr:postcode":"3156",
    "addr:street":"Burwood Hwy",
    "iso:country":"AU",
    "sg:address":"1244 Burwood Hwy",
    "sg:city":"Upper Ferntree Gully",
    "sg:classifiers":[
        {
            "category":"Health Services",
            "subcategory":"Chiropractor",
            "type":"Services"
        }
    ],
    "sg:phone":"+61 3 9758 0585",
    "sg:postcode":"3156",
    "sg:province":"VIC",
    "wof:name":"Cox Jeanette E.",
    "wof:placetype":"venue"
},
  "geometry": {"coordinates":[145.31138610799999,-37.8937034607],"type":"Point"}
}