{
  "type": "Feature",
  "properties": {
    "iso:country":"AU",
    "sg:address":"4/1 Damaso Pl",
    "sg:city":"Woolner",
    "sg:classifiers":[
        {
            "category":"Shopping",
            "subcategory":"Discount & Variety Stores",
            "type":"Retail Goods"
        }
    ],
    "sg:phone":"+61 8 8941 4434",
    "sg:postcode":"0820",
    "sg:province":"NT",
    "sg:tags":[
        "shop",
        "adult"
    ],
    "wof:name":"Adult World",
    "wof:placetype":"venue"
},
  "geometry": {"coordinates":[130.85516357399999,-12.4319915771],"type":"Point"}
}