{
  "type": "Feature",
  "properties": {
    "addr:full":"23 Anderson Rd Thornbury VIC 3071",
    "addr:housenumber":"23",
    "addr:postcode":"3071",
    "addr:street":"Anderson Rd",
    "iso:country":"AU",
    "sg:address":"23 Anderson Rd",
    "sg:city":"Thornbury",
    "sg:classifiers":[
        {
            "category":"Home & Garden",
            "subcategory":"Building Materials",
            "type":"Retail Goods"
        }
    ],
    "sg:phone":"+61 3 9480 5944",
    "sg:postcode":"3071",
    "sg:province":"VIC",
    "sg:tags":[
        "pre-mixed",
        "concrete"
    ],
    "wof:name":"Boral Concrete",
    "wof:placetype":"venue"
},
  "geometry": {"coordinates":[144.981155395,-37.7541503906],"type":"Point"}
}