{
  "type": "Feature",
  "properties": {
    "addr:full":"Level 11, 157 Walker St North Sydney NSW 2060",
    "addr:housenumber":"157",
    "addr:postcode":"2060",
    "addr:street":"Walker St",
    "iso:country":"AU",
    "sg:address":"Level 11, 157 Walker St",
    "sg:city":"North Sydney",
    "sg:classifiers":[
        {
            "category":"Banks & Credit Unions",
            "subcategory":"Bank",
            "type":"Services"
        }
    ],
    "sg:phone":"+61 1300 130 014",
    "sg:postcode":"2060",
    "sg:province":"NSW",
    "sg:tags":[
        "broker",
        "mortgage"
    ],
    "wof:name":"Discover Home Loans.",
    "wof:placetype":"venue"
},
  "geometry": {"coordinates":[151.20930480999999,-33.8374290466],"type":"Point"}
}