{
  "type": "Feature",
  "properties": {
    "addr:full":"Unit 17-18/25- 33 Alfred Rd Chipping Norton NSW 2170",
    "addr:housenumber":"17-18 / 25 33",
    "addr:postcode":"2170",
    "addr:street":"Alfred Rd",
    "iso:country":"AU",
    "sg:address":"Unit 17-18/25- 33 Alfred Rd",
    "sg:city":"Chipping Norton",
    "sg:classifiers":[
        {
            "category":"Building & Trades",
            "subcategory":"Construction",
            "type":"Services"
        }
    ],
    "sg:phone":"+61 2 9724 9297",
    "sg:postcode":"2170",
    "sg:province":"NSW",
    "sg:tags":[
        "industrial",
        "commercial",
        "air conditioning"
    ],
    "wof:name":"Quality Air Equipment Pty Ltd",
    "wof:placetype":"venue"
},
  "geometry": {"coordinates":[150.96441650400001,-33.9229736328],"type":"Point"}
}