{
  "type": "Feature",
  "properties": {
    "iso:country":"AU",
    "sg:address":"100 Stuart St",
    "sg:city":"Mullumbimby",
    "sg:classifiers":[
        {
            "category":"Health Services",
            "subcategory":"Dentist",
            "type":"Services"
        }
    ],
    "sg:phone":"+61 2 6684 2644",
    "sg:postcode":"2482",
    "sg:province":"NSW",
    "wof:name":"Ackland M",
    "wof:placetype":"venue"
},
  "geometry": {"coordinates":[153.50094604500001,-28.553527832],"type":"Point"}
}