{
  "type": "Feature",
  "properties": {
    "addr:full":"31-33 Alfred St Blackburn VIC 3130",
    "addr:housenumber":"31-33",
    "addr:postcode":"3130",
    "addr:street":"Alfred St",
    "iso:country":"AU",
    "sg:address":"31-33 Alfred St",
    "sg:city":"Blackburn",
    "sg:classifiers":[
        {
            "category":"Home & Garden",
            "subcategory":"Building Materials",
            "type":"Retail Goods"
        }
    ],
    "sg:phone":"+61 3 9877 1555",
    "sg:postcode":"3130",
    "sg:province":"VIC",
    "sg:tags":[
        "fitting",
        "door"
    ],
    "wof:name":"Gainsborough Hardware Industries Ltd",
    "wof:placetype":"venue"
},
  "geometry": {"coordinates":[145.15985107399999,-37.8181495667],"type":"Point"}
}