{
  "type": "Feature",
  "properties": {
    "iso:country":"AU",
    "sg:address":"Bimblebox La",
    "sg:city":"Trangie",
    "sg:classifiers":[
        {
            "category":"Building & Trades",
            "subcategory":"Construction",
            "type":"Services"
        }
    ],
    "sg:phone":"+61 2 6888 7466",
    "sg:postcode":"2823",
    "sg:province":"NSW",
    "sg:tags":[
        "contractor"
    ],
    "wof:name":"Smith Kevin",
    "wof:placetype":"venue"
},
  "geometry": {"coordinates":[147.97474670400001,-32.0269966125],"type":"Point"}
}