{
  "type": "Feature",
  "properties": {
    "addr:full":"49 Neerim Drv Mooloolaba QLD 4557",
    "addr:housenumber":"49",
    "addr:postcode":"4557",
    "addr:street":"Neerim Drv",
    "iso:country":"AU",
    "sg:address":"49 Neerim Drv",
    "sg:city":"Mooloolaba",
    "sg:classifiers":[
        {
            "category":"Shopping",
            "subcategory":"Bicycles & Sporting Goods",
            "type":"Retail Goods"
        }
    ],
    "sg:phone":"+61 7 5452 5000",
    "sg:postcode":"4557",
    "sg:province":"QLD",
    "sg:tags":[
        "chemical",
        "equipment",
        "pool",
        "swimming"
    ],
    "wof:name":"Blakeway Pools Pty Ltd",
    "wof:placetype":"venue"
},
  "geometry": {"coordinates":[153.11651611299999,-26.6945705414],"type":"Point"}
}