{
  "type": "Feature",
  "properties": {
    "addr:full":"U1/ 7 Enterprise Crs Malaga WA 6090",
    "addr:housenumber":"7",
    "addr:postcode":"6090",
    "addr:street":"U1 /;Enterprise Crs",
    "iso:country":"AU",
    "sg:address":"U1/ 7 Enterprise Crs",
    "sg:city":"Malaga",
    "sg:classifiers":[
        {
            "category":"Professional",
            "type":"Services"
        }
    ],
    "sg:phone":"+61 8 9249 9801",
    "sg:postcode":"6090",
    "sg:province":"WA",
    "sg:tags":[
        "shop",
        "fitting"
    ],
    "wof:name":"Granite West Pty Ltd",
    "wof:placetype":"venue"
},
  "geometry": {"coordinates":[115.897476196,-31.8568401337],"type":"Point"}
}