{
  "type": "Feature",
  "properties": {
    "addr:full":"32 Fiona Drv Cranbourne South VIC 3977",
    "addr:housenumber":"32",
    "addr:postcode":"3977",
    "addr:street":"Fiona Drv",
    "iso:country":"AU",
    "sg:address":"32 Fiona Drv",
    "sg:city":"Cranbourne South",
    "sg:classifiers":[
        {
            "category":"Professional",
            "subcategory":"Printing & Photocopies",
            "type":"Services"
        }
    ],
    "sg:phone":"+61 408 535 169",
    "sg:postcode":"3977",
    "sg:province":"VIC",
    "sg:tags":[
        "photocopier"
    ],
    "wof:name":"Westernport Business Machines",
    "wof:placetype":"venue"
},
  "geometry": {"coordinates":[145.27325439399999,-38.1634368896],"type":"Point"}
}