{
  "type": "Feature",
  "properties": {
    "iso:country":"AU",
    "sg:address":"92 Templeton St",
    "sg:city":"Wangaratta",
    "sg:classifiers":[
        {
            "category":"Wholesale",
            "subcategory":"Farm Supplies",
            "type":"Manufacturing & Wholesale Goods"
        }
    ],
    "sg:phone":"+61 3 5722 4366",
    "sg:postcode":"3677",
    "sg:province":"VIC",
    "sg:tags":[
        "feed",
        "supplement",
        "stock"
    ],
    "wof:name":"Pro Beef Australia Pty Ltd",
    "wof:placetype":"venue"
},
  "geometry": {"coordinates":[146.31765747099999,-36.3503913879],"type":"Point"}
}