{
  "type": "Feature",
  "properties": {
    "iso:country":"AU",
    "sg:address":"Suite 502 156 Pacific Hwy",
    "sg:city":"Greenwich",
    "sg:classifiers":[
        {
            "category":"Insurance",
            "subcategory":"Insurance Agent",
            "type":"Services"
        }
    ],
    "sg:phone":"+61 2 9437 9300",
    "sg:postcode":"2065",
    "sg:province":"NSW",
    "wof:name":"Underwriters & Administrators Agents Pty Ltd",
    "wof:placetype":"venue"
},
  "geometry": {"coordinates":[151.18771362300001,-33.824344635],"type":"Point"}
}