{
  "type": "Feature",
  "properties": {
    "addr:full":"2 Salisbury St Watsons Bay NSW 2030",
    "addr:housenumber":"2",
    "addr:postcode":"2030",
    "addr:street":"Salisbury St",
    "iso:country":"AU",
    "sg:address":"2 Salisbury St",
    "sg:city":"Watsons Bay",
    "sg:classifiers":[
        {
            "category":"Shopping",
            "subcategory":"Clothing, Apparel, & Fashions",
            "type":"Retail Goods"
        }
    ],
    "sg:phone":"+61 2 9388 8993",
    "sg:postcode":"2030",
    "sg:province":"NSW",
    "sg:tags":[
        "sportswear"
    ],
    "wof:name":"Between The Flags",
    "wof:placetype":"venue"
},
  "geometry": {"coordinates":[151.28321838400001,-33.8460540771],"type":"Point"}
}