{
  "type": "Feature",
  "properties": {
    "iso:country":"AU",
    "sg:address":"GPO Box 1515",
    "sg:city":"Brisbane",
    "sg:classifiers":[
        {
            "category":"Shopping",
            "subcategory":"Computers & Home Electronics",
            "type":"Retail Goods"
        }
    ],
    "sg:phone":"+61 1300 130 140",
    "sg:postcode":"9000",
    "sg:province":"QLD",
    "sg:tags":[
        "equipment",
        "multimedia"
    ],
    "wof:name":"Enigma Interactive ?",
    "wof:placetype":"venue"
},
  "geometry": {"coordinates":[152.88914489699999,-27.597738266],"type":"Point"}
}