{
  "type": "Feature",
  "properties": {
    "iso:country":"AU",
    "sg:address":"26 Stud Rd",
    "sg:city":"Dandenong",
    "sg:classifiers":[
        {
            "category":"Health Services",
            "subcategory":"Doctor",
            "type":"Services"
        }
    ],
    "sg:phone":"+61 3 9791 9688",
    "sg:postcode":"3175",
    "sg:province":"VIC",
    "sg:tags":[
        "medical",
        "practitioner"
    ],
    "wof:name":"Ngai Thomas Dr",
    "wof:placetype":"venue"
},
  "geometry": {"coordinates":[145.22132873499999,-37.9829597473],"type":"Point"}
}