{
  "type": "Feature",
  "properties": {
    "addr:full":"PO Box 1345 Wangara Private Boxes WA 6947",
    "addr:postcode":"6947",
    "iso:country":"AU",
    "sg:address":"PO Box 1345",
    "sg:city":"Wangara Private Boxes",
    "sg:classifiers":[
        {
            "category":"Professional",
            "subcategory":"Computer Services",
            "type":"Services"
        }
    ],
    "sg:phone":"+61 417 183 208",
    "sg:postcode":"6947",
    "sg:province":"WA",
    "sg:tags":[
        "equipment",
        "networking",
        "installation"
    ],
    "wof:name":"Oswest Communications",
    "wof:placetype":"venue"
},
  "geometry": {"coordinates":[115.83036041299999,-31.7966709137],"type":"Point"}
}