{
  "type": "Feature",
  "properties": {
    "addr:full":"107 Landsbrough Ave Scarborough QLD 4020",
    "addr:housenumber":"107",
    "addr:postcode":"4020",
    "addr:street":"Landsbrough Ave",
    "iso:country":"AU",
    "sg:address":"107 Landsbrough Ave",
    "sg:city":"Scarborough",
    "sg:classifiers":[
        {
            "category":"Building & Trades",
            "subcategory":"Construction",
            "type":"Services"
        }
    ],
    "sg:phone":"+61 7 3880 3199",
    "sg:postcode":"4020",
    "sg:province":"QLD",
    "sg:tags":[
        "contractor"
    ],
    "wof:name":"Sundream Homes",
    "wof:placetype":"venue"
},
  "geometry": {"coordinates":[153.11438000000001,-27.204227],"type":"Point"}
}