{
  "type": "Feature",
  "properties": {
    "addr:full":"133 Hardy Rd Belmont WA 6104",
    "addr:housenumber":"133",
    "addr:postcode":"6104",
    "addr:street":"Hardy Rd",
    "iso:country":"AU",
    "sg:address":"133 Hardy Rd",
    "sg:city":"Belmont",
    "sg:classifiers":[
        {
            "category":"Recreation",
            "subcategory":"Boat Charter",
            "type":"Entertainment"
        }
    ],
    "sg:phone":"+61 408 959 378",
    "sg:postcode":"6104",
    "sg:province":"WA",
    "sg:tags":[
        "canopy",
        "motor"
    ],
    "wof:name":"Steve's Mobile Marine Trim Service",
    "wof:placetype":"venue"
},
  "geometry": {"coordinates":[115.930236816,-31.9434242249],"type":"Point"}
}