{
  "type": "Feature",
  "properties": {
    "addr:full":"62 Skene St Shepparton VIC 3630",
    "addr:housenumber":"62",
    "addr:postcode":"3630",
    "addr:street":"Skene St",
    "iso:country":"AU",
    "sg:address":"62 Skene St",
    "sg:city":"Shepparton",
    "sg:classifiers":[
        {
            "category":"Health Services",
            "subcategory":"Health Practitioner",
            "type":"Services"
        }
    ],
    "sg:phone":"+61 408 054 538",
    "sg:postcode":"3630",
    "sg:province":"VIC",
    "sg:tags":[
        "acupuncture"
    ],
    "wof:name":"Galvin Tanya",
    "wof:placetype":"venue"
},
  "geometry": {"coordinates":[145.408279419,-36.3804168701],"type":"Point"}
}