{
  "type": "Feature",
  "properties": {
    "addr:full":"Princes Hwy Ulladulla NSW 2539",
    "addr:postcode":"2539",
    "addr:street":"Princes Hwy",
    "iso:country":"AU",
    "sg:address":"Princes Hwy",
    "sg:city":"Ulladulla",
    "sg:classifiers":[
        {
            "category":"Professional",
            "subcategory":"Detective & Security Services",
            "type":"Services"
        }
    ],
    "sg:phone":"+61 2 4455 4618",
    "sg:postcode":"2539",
    "sg:province":"NSW",
    "sg:tags":[
        "investigator"
    ],
    "wof:name":"Datalink",
    "wof:placetype":"venue"
},
  "geometry": {"coordinates":[150.47564697300001,-35.3510398865],"type":"Point"}
}