{
  "type": "Feature",
  "properties": {
    "addr:full":"Shop 210 Redbank Plaza Redbank QLD 4301",
    "addr:housenumber":"210",
    "addr:postcode":"4301",
    "addr:street":"Redbank Plaza",
    "iso:country":"AU",
    "sg:address":"Shop 210",
    "sg:city":"Redbank Plaza Redbank",
    "sg:classifiers":[
        {
            "category":"Shopping",
            "subcategory":"Clothing, Apparel, & Fashions",
            "type":"Retail Goods"
        }
    ],
    "sg:phone":"+61 7 3818 0990",
    "sg:postcode":"4301",
    "sg:province":"QLD",
    "sg:tags":[
        "lingerie",
        "hosiery",
        "sleepwear"
    ],
    "wof:name":"Bras &#039;N&#039; Things",
    "wof:placetype":"venue"
},
  "geometry": {"coordinates":[152.83297729500001,-27.6366424561],"type":"Point"}
}