{
  "type": "Feature",
  "properties": {
    "addr:full":"6 Harvey Rd Forest Hill QLD 4342",
    "addr:housenumber":"6",
    "addr:postcode":"4342",
    "addr:street":"Harvey Rd",
    "iso:country":"AU",
    "sg:address":"6 Harvey Rd",
    "sg:city":"Forest Hill",
    "sg:classifiers":[
        {
            "category":"Building & Trades",
            "subcategory":"Construction",
            "type":"Services"
        }
    ],
    "sg:phone":"+61 7 5465 4848",
    "sg:postcode":"4342",
    "sg:province":"QLD",
    "sg:tags":[
        "polishing",
        "sanding",
        "floor"
    ],
    "wof:name":"N B Floors",
    "wof:placetype":"venue"
},
  "geometry": {"coordinates":[152.385375977,-27.5713233948],"type":"Point"}
}