{
  "type": "Feature",
  "properties": {
    "addr:full":"405 Logan Rd Stones Corner QLD 4120",
    "addr:housenumber":"405",
    "addr:postcode":"4120",
    "addr:street":"Logan Rd",
    "iso:country":"AU",
    "sg:address":"405 Logan Rd",
    "sg:city":"Stones Corner",
    "sg:classifiers":[
        {
            "category":"Cafe",
            "type":"Food & Drink"
        }
    ],
    "sg:phone":"+61 7 3397 7211",
    "sg:postcode":"4120",
    "sg:province":"QLD",
    "wof:name":"Caffe Di Moda",
    "wof:placetype":"venue"
},
  "geometry": {"coordinates":[153.04556274399999,-27.5004577637],"type":"Point"}
}