{
  "type": "Feature",
  "properties": {
    "addr:full":"38 Chinbrina St Hope Island QLD 4212",
    "addr:housenumber":"38",
    "addr:postcode":"4212",
    "addr:street":"Chinbrina St",
    "iso:country":"AU",
    "sg:address":"38 Chinbrina St",
    "sg:city":"Hope Island",
    "sg:classifiers":[
        {
            "category":"Recreation",
            "subcategory":"Boat Charter",
            "type":"Entertainment"
        }
    ],
    "sg:phone":"+61 409 727 875",
    "sg:postcode":"4212",
    "sg:province":"QLD",
    "sg:tags":[
        "hire",
        "drive"
    ],
    "wof:name":"Logan River Boat Hire",
    "wof:placetype":"venue"
},
  "geometry": {"coordinates":[153.35038757300001,-27.8561916351],"type":"Point"}
}