{
  "type": "Feature",
  "properties": {
    "iso:country":"AU",
    "sg:address":"8/ 54 Fairford Rd",
    "sg:city":"Bankstown",
    "sg:classifiers":[
        {
            "category":"Home & Garden",
            "subcategory":"Carpets & Floor Coverings",
            "type":"Retail Goods"
        }
    ],
    "sg:phone":"+61 2 9790 2844",
    "sg:postcode":"2200",
    "sg:province":"NSW",
    "wof:name":"Bankstown Carpet Court",
    "wof:placetype":"venue"
},
  "geometry": {"coordinates":[151.03677400000001,-33.935188],"type":"Point"}
}