{
  "type": "Feature",
  "properties": {
    "addr:full":"101 Murray St Pyrmont NSW 2009",
    "addr:housenumber":"101",
    "addr:postcode":"2009",
    "addr:street":"Murray St",
    "iso:country":"AU",
    "sg:address":"101 Murray St",
    "sg:city":"Pyrmont",
    "sg:classifiers":[
        {
            "category":"Real Estate",
            "subcategory":"Developer",
            "type":"Services"
        }
    ],
    "sg:phone":"+61 2 9518 6064",
    "sg:postcode":"2009",
    "sg:province":"NSW",
    "sg:tags":[
        "development"
    ],
    "wof:name":"Landmax Development Pty Ltd",
    "wof:placetype":"venue"
},
  "geometry": {"coordinates":[151.19737243599999,-33.871547699],"type":"Point"}
}