{
  "type": "Feature",
  "properties": {
    "addr:full":"38 - 40 Lysaght St Acacia Ridge QLD 4110",
    "addr:housenumber":"40",
    "addr:postcode":"4110",
    "addr:street":"Lysaght St",
    "iso:country":"AU",
    "sg:address":"38 - 40 Lysaght St",
    "sg:city":"Acacia Ridge",
    "sg:classifiers":[
        {
            "category":"Manufacturing",
            "subcategory":"Glass & Minerals",
            "type":"Manufacturing & Wholesale Goods"
        }
    ],
    "sg:phone":"+61 7 3423 7400",
    "sg:postcode":"4110",
    "sg:province":"QLD",
    "sg:tags":[
        "mfrg",
        "processing"
    ],
    "sg:website":"http://www.lionglass.com",
    "wof:name":"Lion Glass",
    "wof:placetype":"venue"
},
  "geometry": {"coordinates":[153.033813477,-27.5833396912],"type":"Point"}
}