{
  "type": "Feature",
  "properties": {
    "iso:country":"AU",
    "sg:address":"Shop 3, 50 Reservoir St",
    "sg:city":"Surry Hills",
    "sg:classifiers":[
        {
            "category":"Shopping",
            "subcategory":"Computers & Home Electronics",
            "type":"Retail Goods"
        }
    ],
    "sg:phone":"+61 2 9281 3988",
    "sg:postcode":"2010",
    "sg:province":"NSW",
    "sg:tags":[
        "hardware",
        "equipment"
    ],
    "wof:name":"Action Computer Services Pty Ltd",
    "wof:placetype":"venue"
},
  "geometry": {"coordinates":[151.20941162099999,-33.8811035156],"type":"Point"}
}