{
  "type": "Feature",
  "properties": {
    "iso:country":"AU",
    "sg:address":"41 Pine Ave",
    "sg:city":"Leeton",
    "sg:classifiers":[
        {
            "category":"Restaurant",
            "type":"Food & Drink"
        }
    ],
    "sg:phone":"+61 2 6953 2418",
    "sg:postcode":"2705",
    "sg:province":"NSW",
    "wof:name":"Chung Hing Restaurant",
    "wof:placetype":"venue"
},
  "geometry": {"coordinates":[146.40489196799999,-34.5515174866],"type":"Point"}
}