{
  "type": "Feature",
  "properties": {
    "iso:country":"AU",
    "sg:address":"230 Kanahooka Rd",
    "sg:city":"Dapto",
    "sg:classifiers":[
        {
            "category":"Retail",
            "subcategory":"Funeral Services",
            "type":"Services"
        }
    ],
    "sg:phone":"+61 2 4261 1200",
    "sg:postcode":"2530",
    "sg:province":"NSW",
    "sg:tags":[
        "cremation"
    ],
    "wof:name":"Lakeside Memorial Park",
    "wof:placetype":"venue"
},
  "geometry": {"coordinates":[150.81280517600001,-34.4905776978],"type":"Point"}
}