{
  "type": "Feature",
  "properties": {
    "iso:country":"AU",
    "sg:address":"26-28 Whybrow St",
    "sg:city":"Griffith",
    "sg:classifiers":[
        {
            "category":"Manufacturing",
            "subcategory":"Metals",
            "type":"Manufacturing & Wholesale Goods"
        }
    ],
    "sg:phone":"+61 2 6964 3700",
    "sg:postcode":"2680",
    "sg:province":"NSW",
    "sg:tags":[
        "steel",
        "fabricator",
        "mfrs"
    ],
    "wof:name":"Yoogali Engineering",
    "wof:placetype":"venue"
},
  "geometry": {"coordinates":[146.073196,-34.29203],"type":"Point"}
}