{
  "type": "Feature",
  "properties": {
    "iso:country":"AU",
    "sg:address":"143 Abbotsford Rd",
    "sg:city":"Bowen Hills",
    "sg:classifiers":[
        {
            "category":"Education",
            "subcategory":"Special Training",
            "type":"Public Place"
        }
    ],
    "sg:phone":"+61 1800 880 883",
    "sg:postcode":"4006",
    "sg:province":"QLD",
    "sg:tags":[
        "development"
    ],
    "wof:name":"ESP Programme Australia",
    "wof:placetype":"venue"
},
  "geometry": {"coordinates":[153.04046630900001,-27.4396152496],"type":"Point"}
}