{
  "type": "Feature",
  "properties": {
    "iso:country":"AU",
    "sg:address":"Bowna Rd",
    "sg:city":"Table Top",
    "sg:classifiers":[
        {
            "category":"Retail",
            "subcategory":"Auto Rental",
            "type":"Services"
        }
    ],
    "sg:phone":"+61 2 6026 2336",
    "sg:postcode":"2640",
    "sg:province":"NSW",
    "sg:tags":[
        "car",
        "wedding"
    ],
    "wof:name":"Royal Wedding Cars Albury",
    "wof:placetype":"venue"
},
  "geometry": {"coordinates":[147.018707275,-36.014541626],"type":"Point"}
}