{
  "type": "Feature",
  "properties": {
    "addr:full":"62 Jarrah Rd Roleystone WA 6111",
    "addr:housenumber":"62",
    "addr:postcode":"6111",
    "addr:street":"Jarrah Rd",
    "iso:country":"AU",
    "sg:address":"62 Jarrah Rd",
    "sg:city":"Roleystone",
    "sg:classifiers":[
        {
            "category":"Building & Trades",
            "subcategory":"Construction",
            "type":"Services"
        }
    ],
    "sg:phone":"+61 8 9496 0405",
    "sg:postcode":"6111",
    "sg:province":"WA",
    "sg:tags":[
        "spouting",
        "guttering"
    ],
    "wof:name":"Allen Kelly Contracting",
    "wof:placetype":"venue"
},
  "geometry": {"coordinates":[116.06952667199999,-32.1069259644],"type":"Point"}
}