{
  "type": "Feature",
  "properties": {
    "iso:country":"AU",
    "sg:address":"William St",
    "sg:city":"Hebel",
    "sg:classifiers":[
        {
            "category":"Food & Beverages",
            "subcategory":"Groceries & Convenience Stores",
            "type":"Retail Goods"
        }
    ],
    "sg:phone":"+61 7 4625 0920",
    "sg:postcode":"4486",
    "sg:province":"QLD",
    "wof:name":"Hebel Store & Caravan Park",
    "wof:placetype":"venue"
},
  "geometry": {"coordinates":[147.79551696799999,-28.9721164703],"type":"Point"}
}