{
  "type": "Feature",
  "properties": {
    "addr:full":"23 Commercial Drv Dandenong VIC 3175",
    "addr:housenumber":"23",
    "addr:postcode":"3175",
    "addr:street":"Commercial Drv",
    "iso:country":"AU",
    "sg:address":"23 Commercial Drv",
    "sg:city":"Dandenong",
    "sg:classifiers":[
        {
            "category":"Government",
            "subcategory":"Fire Station",
            "type":"Public Place"
        }
    ],
    "sg:phone":"+61 3 9706 6262",
    "sg:postcode":"3175",
    "sg:province":"VIC",
    "sg:tags":[
        "equipment",
        "protection",
        "consultant"
    ],
    "wof:name":"Supafire",
    "wof:placetype":"venue"
},
  "geometry": {"coordinates":[145.22862243599999,-38.0228424072],"type":"Point"}
}