{
  "type": "Feature",
  "properties": {
    "addr:full":"91 Maitland St Gunnedah NSW 2380",
    "addr:housenumber":"91",
    "addr:postcode":"2380",
    "addr:street":"Maitland St",
    "iso:country":"AU",
    "sg:address":"91 Maitland St",
    "sg:city":"Gunnedah",
    "sg:classifiers":[
        {
            "category":"Travel",
            "subcategory":"Hotels & Motels",
            "type":"Entertainment"
        }
    ],
    "sg:phone":"+61 2 6742 1906",
    "sg:postcode":"2380",
    "sg:province":"NSW",
    "wof:name":"Roseneath Manor",
    "wof:placetype":"venue"
},
  "geometry": {"coordinates":[150.25654602,-30.9744167328],"type":"Point"}
}