{
  "type": "Feature",
  "properties": {
    "addr:full":"5 Coral St Tannum Sands QLD 4680",
    "addr:housenumber":"5",
    "addr:postcode":"4680",
    "addr:street":"Coral St",
    "iso:country":"AU",
    "sg:address":"5 Coral St",
    "sg:city":"Tannum Sands",
    "sg:classifiers":[
        {
            "category":"Wholesale",
            "subcategory":"Machinery & Supplies",
            "type":"Manufacturing & Wholesale Goods"
        }
    ],
    "sg:phone":"+61 7 4973 7688",
    "sg:postcode":"4680",
    "sg:province":"QLD",
    "sg:tags":[
        "instrument"
    ],
    "wof:name":"Dittmann Enterprises",
    "wof:placetype":"venue"
},
  "geometry": {"coordinates":[151.37452697800001,-23.9488391876],"type":"Point"}
}