{
  "type": "Feature",
  "properties": {
    "addr:full":"1 Pacific Hwy Bennetts Green NSW 2290",
    "addr:housenumber":"1",
    "addr:postcode":"2290",
    "addr:street":"Pacific Hwy",
    "iso:country":"AU",
    "sg:address":"1 Pacific Hwy",
    "sg:city":"Bennetts Green",
    "sg:classifiers":[
        {
            "category":"Retail",
            "subcategory":"Auto Repair",
            "type":"Services"
        }
    ],
    "sg:phone":"+61 1800 807 700",
    "sg:postcode":"2290",
    "sg:province":"NSW",
    "sg:tags":[
        "repairer",
        "motor",
        "engineer"
    ],
    "wof:name":"Valley Star Prestige Motors",
    "wof:placetype":"venue"
},
  "geometry": {"coordinates":[151.684646606,-33.0061302185],"type":"Point"}
}