{
  "type": "Feature",
  "properties": {
    "addr:full":"Factory St Pomona QLD 4568",
    "addr:postcode":"4568",
    "addr:street":"Factory St",
    "iso:country":"AU",
    "sg:address":"Factory St",
    "sg:city":"Pomona",
    "sg:classifiers":[
        {
            "category":"Shopping",
            "subcategory":"Clothing, Apparel, & Fashions",
            "type":"Retail Goods"
        }
    ],
    "sg:phone":"+61 7 5485 2934",
    "sg:postcode":"4568",
    "sg:province":"QLD",
    "sg:tags":[
        "recycled",
        "clothing"
    ],
    "wof:name":"Australian Red Cross",
    "wof:placetype":"venue"
},
  "geometry": {"coordinates":[152.856658936,-26.3652877808],"type":"Point"}
}