{
  "type": "Feature",
  "properties": {
    "addr:full":"Lwr Ground Floor 7 Bayfield St Rosny Park TAS 7018",
    "addr:housenumber":"7",
    "addr:postcode":"7018",
    "addr:street":"Lwr;Bayfield St",
    "iso:country":"AU",
    "sg:address":"Lwr Ground Floor 7 Bayfield St",
    "sg:city":"Rosny Park",
    "sg:classifiers":[
        {
            "category":"Banks & Credit Unions",
            "subcategory":"Financial Services",
            "type":"Services"
        }
    ],
    "sg:phone":"+61 3 6245 1000",
    "sg:postcode":"7018",
    "sg:province":"TAS",
    "sg:tags":[
        "planning"
    ],
    "wof:name":"Flanagan Paul Pty Ltd",
    "wof:placetype":"venue"
},
  "geometry": {"coordinates":[147.37005615199999,-42.866558075],"type":"Point"}
}