{
  "type": "Feature",
  "properties": {
    "addr:full":"Level 1, Elouera Court, 18 Lonsdale St Braddon ACT 2612",
    "addr:housenumber":"18",
    "addr:postcode":"2612",
    "addr:street":"Lonsdale St",
    "iso:country":"AU",
    "sg:address":"Level 1, Elouera Court, 18 Lonsdale St",
    "sg:city":"Braddon",
    "sg:classifiers":[
        {
            "category":"Banks & Credit Unions",
            "subcategory":"Bank",
            "type":"Services"
        }
    ],
    "sg:phone":"+61 2 6262 7113",
    "sg:postcode":"2612",
    "sg:province":"ACT",
    "sg:tags":[
        "broker",
        "mortgage"
    ],
    "wof:name":"ProMortgage",
    "wof:placetype":"venue"
},
  "geometry": {"coordinates":[149.13287353499999,-35.2737350464],"type":"Point"}
}