{
  "type": "Feature",
  "properties": {
    "iso:country":"AU",
    "sg:address":"313 Flaxton Drv",
    "sg:city":"Flaxton",
    "sg:classifiers":[
        {
            "category":"Farming",
            "subcategory":"Vineyard",
            "type":"Manufacturing & Wholesale Goods"
        }
    ],
    "sg:phone":"+61 7 5478 6766",
    "sg:postcode":"4560",
    "sg:province":"QLD",
    "sg:tags":[
        "winery"
    ],
    "wof:name":"Flaxton Grove Winery",
    "wof:placetype":"venue"
},
  "geometry": {"coordinates":[152.876342773,-26.661359787],"type":"Point"}
}