{
  "type": "Feature",
  "properties": {
    "addr:full":"205 Pitt St Eltham VIC 3095",
    "addr:housenumber":"205",
    "addr:postcode":"3095",
    "addr:street":"Pitt St",
    "iso:country":"AU",
    "sg:address":"205 Pitt St",
    "sg:city":"Eltham",
    "sg:classifiers":[
        {
            "category":"Building & Trades",
            "subcategory":"Construction",
            "type":"Services"
        }
    ],
    "sg:phone":"+61 3 9439 2791",
    "sg:postcode":"3095",
    "sg:province":"VIC",
    "sg:tags":[
        "contractor"
    ],
    "wof:name":"Klaric Built Homes Pty Ltd",
    "wof:placetype":"venue"
},
  "geometry": {"coordinates":[145.16009521500001,-37.7219810486],"type":"Point"}
}