{
  "type": "Feature",
  "properties": {
    "addr:full":"15 Main Rd Boolaroo NSW 2284",
    "addr:housenumber":"15",
    "addr:postcode":"2284",
    "addr:street":"Main Rd",
    "iso:country":"AU",
    "sg:address":"15 Main Rd",
    "sg:city":"Boolaroo",
    "sg:classifiers":[
        {
            "category":"Manufacturing",
            "subcategory":"Watercraft",
            "type":"Manufacturing & Wholesale Goods"
        }
    ],
    "sg:phone":"+61 2 4958 8873",
    "sg:postcode":"2284",
    "sg:province":"NSW",
    "sg:tags":[
        "sail",
        "marine",
        "maker"
    ],
    "wof:name":"Adams Sails",
    "wof:placetype":"venue"
},
  "geometry": {"coordinates":[151.62327575699999,-32.950176239],"type":"Point"}
}