{
  "type": "Feature",
  "properties": {
    "addr:full":"5/ 341 Victoria Ave Chatswood NSW 2067",
    "addr:housenumber":"/ 341",
    "addr:postcode":"2067",
    "addr:street":"Victoria Ave",
    "iso:country":"AU",
    "sg:address":"5/ 341 Victoria Ave",
    "sg:city":"Chatswood",
    "sg:classifiers":[
        {
            "category":"Personal",
            "subcategory":"Beauty Salon",
            "type":"Services"
        }
    ],
    "sg:phone":"+61 2 9904 8761",
    "sg:postcode":"2067",
    "sg:province":"NSW",
    "wof:name":"Kaye Owen Beauty & Massage",
    "wof:placetype":"venue"
},
  "geometry": {"coordinates":[151.187057495,-33.7949523926],"type":"Point"}
}