{
  "type": "Feature",
  "properties": {
    "addr:full":"235 Belmore Rd Riverwood NSW 2210",
    "addr:housenumber":"235",
    "addr:postcode":"2210",
    "addr:street":"Belmore Rd",
    "iso:country":"AU",
    "sg:address":"235 Belmore Rd",
    "sg:city":"Riverwood",
    "sg:classifiers":[
        {
            "category":"Real Estate",
            "subcategory":"Real Estate Agent",
            "type":"Services"
        }
    ],
    "sg:phone":"+61 2 9153 7960",
    "sg:postcode":"2210",
    "sg:province":"NSW",
    "wof:name":"Gil International Real Estate",
    "wof:placetype":"venue"
},
  "geometry": {"coordinates":[151.05154400000001,-33.95348],"type":"Point"}
}