{
  "type": "Feature",
  "properties": {
    "iso:country":"AU",
    "sg:address":"515 Gilbert Rd",
    "sg:city":"Preston",
    "sg:classifiers":[
        {
            "category":"Professional",
            "type":"Services"
        }
    ],
    "sg:phone":"+61 3 9478 5888",
    "sg:postcode":"3072",
    "sg:province":"VIC",
    "sg:tags":[
        "quality",
        "assurance"
    ],
    "wof:name":"QS Systems Engineering",
    "wof:placetype":"venue"
},
  "geometry": {"coordinates":[144.99078369099999,-37.7324638367],"type":"Point"}
}