{
  "type": "Feature",
  "properties": {
    "addr:full":"37 Princes Hwy Dandenong VIC 3175",
    "addr:housenumber":"37",
    "addr:postcode":"3175",
    "addr:street":"Princes Hwy",
    "iso:country":"AU",
    "sg:address":"37 Princes Hwy",
    "sg:city":"Dandenong",
    "sg:classifiers":[
        {
            "category":"Professional",
            "subcategory":"Accounting & Tax Preparation",
            "type":"Services"
        }
    ],
    "sg:phone":"+61 3 9794 0000",
    "sg:postcode":"3175",
    "sg:province":"VIC",
    "sg:tags":[
        "accountant",
        "auditor"
    ],
    "wof:name":"Vincent Mercuri & Associates",
    "wof:placetype":"venue"
},
  "geometry": {"coordinates":[145.212280273,-37.9835166931],"type":"Point"}
}