{
  "type": "Feature",
  "properties": {
    "addr:full":"173 Annesley St Echuca VIC 3564",
    "addr:housenumber":"173",
    "addr:postcode":"3564",
    "addr:street":"Annesley St",
    "iso:country":"AU",
    "sg:address":"173 Annesley St",
    "sg:city":"Echuca",
    "sg:classifiers":[
        {
            "category":"Retail",
            "subcategory":"Event Space",
            "type":"Services"
        }
    ],
    "sg:phone":"+61 3 5482 2000",
    "sg:postcode":"3564",
    "sg:province":"VIC",
    "sg:tags":[
        "function",
        "organiser"
    ],
    "wof:name":"Twin Rivers Receptions",
    "wof:placetype":"venue"
},
  "geometry": {"coordinates":[144.75157165499999,-36.127166748],"type":"Point"}
}