{
  "type": "Feature",
  "properties": {
    "iso:country":"AU",
    "sg:address":"507 Pittwater Rd",
    "sg:city":"Brookvale",
    "sg:classifiers":[
        {
            "category":"Health Services",
            "subcategory":"Health Practitioner",
            "type":"Services"
        }
    ],
    "sg:phone":"+61 2 9905 0048",
    "sg:postcode":"2100",
    "sg:province":"NSW",
    "sg:tags":[
        "physiotherapist"
    ],
    "wof:name":"Aushealth Physiotherapy",
    "wof:placetype":"venue"
},
  "geometry": {"coordinates":[151.271286011,-33.7638626099],"type":"Point"}
}