{
  "type": "Feature",
  "properties": {
    "iso:country":"AU",
    "sg:address":"Shop 11 Padbury Shopng Cntr",
    "sg:city":"Padbury",
    "sg:classifiers":[
        {
            "category":"Food & Beverages",
            "subcategory":"Supermarket",
            "type":"Retail Goods"
        }
    ],
    "sg:phone":"+61 8 9401 7035",
    "sg:postcode":"6025",
    "sg:province":"WA",
    "sg:tags":[
        "grocery",
        "store"
    ],
    "wof:name":"Supa Valu Supermarkets",
    "wof:placetype":"venue"
},
  "geometry": {"coordinates":[115.76679229699999,-31.8050403595],"type":"Point"}
}