{
  "type": "Feature",
  "properties": {
    "addr:full":"1/ 23 Sunset Ave Warilla NSW 2528",
    "addr:housenumber":"/ 23",
    "addr:postcode":"2528",
    "addr:street":"Sunset Ave",
    "iso:country":"AU",
    "sg:address":"1/ 23 Sunset Ave",
    "sg:city":"Warilla",
    "sg:classifiers":[
        {
            "category":"Arena",
            "subcategory":"Sports Club",
            "type":"Entertainment"
        }
    ],
    "sg:phone":"+61 2 4295 5820",
    "sg:postcode":"2528",
    "sg:province":"NSW",
    "sg:tags":[
        "defence",
        "supply",
        "self",
        "instruction",
        "martial art"
    ],
    "wof:name":"South Coast Martial Arts Centre",
    "wof:placetype":"venue"
},
  "geometry": {"coordinates":[150.85882568400001,-34.5579719543],"type":"Point"}
}