{
  "type": "Feature",
  "properties": {
    "addr:full":"14 Musgrave Prm Ridgewood WA 6030",
    "addr:housenumber":"14",
    "addr:postcode":"6030",
    "addr:street":"Musgrave Prm",
    "iso:country":"AU",
    "sg:address":"14 Musgrave Prm",
    "sg:city":"Ridgewood",
    "sg:classifiers":[
        {
            "category":"Building & Trades",
            "subcategory":"Construction",
            "type":"Services"
        }
    ],
    "sg:phone":"+61 408 987 532",
    "sg:postcode":"6030",
    "sg:province":"WA",
    "sg:tags":[
        "brick",
        "paving"
    ],
    "wof:name":"Zac's Landscapes",
    "wof:placetype":"venue"
},
  "geometry": {"coordinates":[115.712059021,-31.6665382385],"type":"Point"}
}