{
  "type": "Feature",
  "properties": {
    "addr:full":"Unit 4, 21 Lyell St Mittagong NSW 2575",
    "addr:housenumber":"21",
    "addr:postcode":"2575",
    "addr:street":"Lyell St",
    "iso:country":"AU",
    "sg:address":"Unit 4, 21 Lyell St",
    "sg:city":"Mittagong",
    "sg:classifiers":[
        {
            "category":"Professional",
            "subcategory":"Detective & Security Services",
            "type":"Services"
        }
    ],
    "sg:phone":"+61 2 4871 2443",
    "sg:postcode":"2575",
    "sg:province":"NSW",
    "sg:tags":[
        "consultant",
        "laser"
    ],
    "wof:name":"Bowral Signs & Screen Printing",
    "wof:placetype":"venue"
},
  "geometry": {"coordinates":[150.43975830100001,-34.4482040405],"type":"Point"}
}