{
  "type": "Feature",
  "properties": {
    "addr:full":"Lvl 4 289 Flinders La Melbourne VIC 3000",
    "addr:housenumber":"289",
    "addr:postcode":"3000",
    "addr:street":"Flinders La",
    "iso:country":"AU",
    "sg:address":"Lvl 4 289 Flinders La",
    "sg:city":"Melbourne",
    "sg:classifiers":[
        {
            "category":"Shopping",
            "subcategory":"Optical Goods",
            "type":"Retail Goods"
        }
    ],
    "sg:phone":"+61 3 9654 7741",
    "sg:postcode":"3000",
    "sg:province":"VIC",
    "sg:tags":[
        "supply"
    ],
    "wof:name":"Optical Services Pty Ltd",
    "wof:placetype":"venue"
},
  "geometry": {"coordinates":[144.96473693900001,-37.8172607422],"type":"Point"}
}