{
  "type": "Feature",
  "properties": {
    "iso:country":"AU",
    "sg:address":"753 Punchbowl Rd",
    "sg:city":"Punchbowl",
    "sg:classifiers":[
        {
            "category":"Food & Beverages",
            "subcategory":"Bakery",
            "type":"Retail Goods"
        }
    ],
    "sg:phone":"+61 2 9790 3495",
    "sg:postcode":"2196",
    "sg:province":"NSW",
    "sg:tags":[
        "baker"
    ],
    "wof:name":"Baalbeck Bakeries",
    "wof:placetype":"venue"
},
  "geometry": {"coordinates":[151.05415300000001,-33.925789],"type":"Point"}
}