{
  "type": "Feature",
  "properties": {
    "iso:country":"AU",
    "sg:address":"163 Main Rd",
    "sg:city":"Blackwood",
    "sg:classifiers":[
        {
            "category":"Insurance",
            "subcategory":"Insurance Agent",
            "type":"Services"
        }
    ],
    "sg:phone":"+61 8 8278 7000",
    "sg:postcode":"5051",
    "sg:province":"SA",
    "sg:tags":[
        "broker"
    ],
    "wof:name":"TCIS Insurance Brokers Pty Ltd",
    "wof:placetype":"venue"
},
  "geometry": {"coordinates":[138.620712,-35.01371],"type":"Point"}
}