{
  "type": "Feature",
  "properties": {
    "addr:full":"326 George Town Rd Rocherlea TAS 7248",
    "addr:housenumber":"326",
    "addr:postcode":"7248",
    "addr:street":"George Town Rd",
    "iso:country":"AU",
    "sg:address":"326 George Town Rd",
    "sg:city":"Rocherlea",
    "sg:classifiers":[
        {
            "category":"Autos & Motor Vehicles",
            "subcategory":"Auto Supplies",
            "type":"Retail Goods"
        }
    ],
    "sg:phone":"+61 3 6326 7912",
    "sg:postcode":"7248",
    "sg:province":"TAS",
    "sg:tags":[
        "tyre"
    ],
    "wof:name":"Dowling McCarthy Tyres",
    "wof:placetype":"venue"
},
  "geometry": {"coordinates":[147.11448669399999,-41.3723945618],"type":"Point"}
}