{
  "type": "Feature",
  "properties": {
    "iso:country":"AU",
    "sg:address":"38 Mandarin Rd",
    "sg:city":"Maddington",
    "sg:classifiers":[
        {
            "category":"Building & Trades",
            "subcategory":"Construction",
            "type":"Services"
        }
    ],
    "sg:phone":"+61 8 9459 2855",
    "sg:postcode":"6109",
    "sg:province":"WA",
    "sg:tags":[
        "earth",
        "excavating",
        "moving",
        "contractor"
    ],
    "wof:name":"Brierty Contractors",
    "wof:placetype":"venue"
},
  "geometry": {"coordinates":[115.989990234,-32.0383682251],"type":"Point"}
}