{
  "type": "Feature",
  "properties": {
    "addr:full":"147 Main South Rd Morphett Vale SA 5162",
    "addr:housenumber":"147",
    "addr:postcode":"5162",
    "addr:street":"Main South Rd",
    "iso:country":"AU",
    "sg:address":"147 Main South Rd",
    "sg:city":"Morphett Vale",
    "sg:classifiers":[
        {
            "category":"Autos & Motor Vehicles",
            "subcategory":"Automobile Sales",
            "type":"Retail Goods"
        }
    ],
    "sg:phone":"+61 8 8382 4000",
    "sg:postcode":"5162",
    "sg:province":"SA",
    "sg:tags":[
        "car",
        "new"
    ],
    "wof:name":"Australian Motors Mitsubishi",
    "wof:placetype":"venue"
},
  "geometry": {"coordinates":[138.52310180699999,-35.1230278015],"type":"Point"}
}