{
  "type": "Feature",
  "properties": {
    "addr:full":"Kiama Leisure Centre Havilah Pl Kiama NSW 2533",
    "addr:postcode":"2533",
    "addr:street":"Havilah Pl",
    "iso:country":"AU",
    "sg:address":"Kiama Leisure Centre Havilah Pl",
    "sg:city":"Kiama",
    "sg:classifiers":[
        {
            "category":"Personal",
            "subcategory":"Massage",
            "type":"Services"
        }
    ],
    "sg:phone":"+61 2 4232 1877",
    "sg:postcode":"2533",
    "sg:province":"NSW",
    "sg:tags":[
        "therapy"
    ],
    "wof:name":"Kay Wall",
    "wof:placetype":"venue"
},
  "geometry": {"coordinates":[150.847564697,-34.6678237915],"type":"Point"}
}