{
  "type": "Feature",
  "properties": {
    "addr:full":"1077 South Rd Melrose Park SA 5039",
    "addr:housenumber":"1077",
    "addr:postcode":"5039",
    "addr:street":"South Rd",
    "iso:country":"AU",
    "sg:address":"1077 South Rd",
    "sg:city":"Melrose Park",
    "sg:classifiers":[
        {
            "category":"Home & Garden",
            "subcategory":"Building Materials",
            "type":"Retail Goods"
        }
    ],
    "sg:phone":"+61 8 8276 9055",
    "sg:postcode":"5039",
    "sg:province":"SA",
    "sg:tags":[
        "skylight"
    ],
    "wof:name":"Velux",
    "wof:placetype":"venue"
},
  "geometry": {"coordinates":[138.57481384299999,-34.9891433716],"type":"Point"}
}