{
  "type": "Feature",
  "properties": {
    "addr:full":"Shop 3/ 20 Stewart Rd Ashgrove QLD 4060",
    "addr:housenumber":"shop 3 / 20",
    "addr:postcode":"4060",
    "addr:street":"Stewart Rd",
    "iso:country":"AU",
    "sg:address":"Shop 3/ 20 Stewart Rd",
    "sg:city":"Ashgrove",
    "sg:classifiers":[
        {
            "category":"Shopping",
            "subcategory":"Shoes",
            "type":"Retail Goods"
        }
    ],
    "sg:phone":"+61 7 3366 2384",
    "sg:postcode":"4060",
    "sg:province":"QLD",
    "sg:tags":[
        "footwear"
    ],
    "wof:name":"Beth & Lou The Shoe Boutique",
    "wof:placetype":"venue"
},
  "geometry": {"coordinates":[152.99151611299999,-27.4447135925],"type":"Point"}
}