{
  "type": "Feature",
  "properties": {
    "addr:full":"14 Lawsons Crt Templestowe VIC 3106",
    "addr:housenumber":"14",
    "addr:postcode":"3106",
    "addr:street":"Lawsons Crt",
    "iso:country":"AU",
    "sg:address":"14 Lawsons Crt",
    "sg:city":"Templestowe",
    "sg:classifiers":[
        {
            "category":"Manufacturing",
            "subcategory":"Food",
            "type":"Manufacturing & Wholesale Goods"
        }
    ],
    "sg:phone":"+61 3 9846 7077",
    "sg:postcode":"3106",
    "sg:province":"VIC",
    "sg:tags":[
        "wholesaler",
        "mfrs",
        "yarn"
    ],
    "wof:name":"Jacobson John L & Associates",
    "wof:placetype":"venue"
},
  "geometry": {"coordinates":[145.16416931099999,-37.7578010559],"type":"Point"}
}