{
  "type": "Feature",
  "properties": {
    "addr:full":"PO Box 6280 Kangaroo Valley NSW 2577",
    "addr:postcode":"2577",
    "iso:country":"AU",
    "sg:address":"PO Box 6280",
    "sg:city":"Kangaroo Valley",
    "sg:classifiers":[
        {
            "category":"Education",
            "subcategory":"Special Training",
            "type":"Public Place"
        }
    ],
    "sg:phone":"+61 1800 813 351",
    "sg:postcode":"2577",
    "sg:province":"NSW",
    "sg:tags":[
        "development"
    ],
    "wof:name":"Outdoor Insights P/L",
    "wof:placetype":"venue"
},
  "geometry": {"coordinates":[150.523239136,-34.7314491272],"type":"Point"}
}