{
  "type": "Feature",
  "properties": {
    "iso:country":"AU",
    "sg:address":"Shop 1/ 198-200 Swan St",
    "sg:city":"Richmond",
    "sg:classifiers":[
        {
            "category":"Food & Beverages",
            "subcategory":"Liquor & Beverages",
            "type":"Retail Goods"
        }
    ],
    "sg:phone":"+61 3 9421 2411",
    "sg:postcode":"3121",
    "sg:province":"VIC",
    "sg:tags":[
        "store"
    ],
    "wof:name":"Australian Cleanskin Group",
    "wof:placetype":"venue"
},
  "geometry": {"coordinates":[144.99708557100001,-37.8257064819],"type":"Point"}
}