{
  "type": "Feature",
  "properties": {
    "iso:country":"AU",
    "sg:address":"22 Queen Elizabeth Drv",
    "sg:city":"Rockhampton",
    "sg:classifiers":[
        {
            "category":"Retail",
            "subcategory":"Storage",
            "type":"Services"
        }
    ],
    "sg:phone":"+61 7 4927 4522",
    "sg:postcode":"4702",
    "sg:province":"QLD",
    "sg:tags":[
        "removal",
        "furniture"
    ],
    "wof:name":"Gormans Removals",
    "wof:placetype":"venue"
},
  "geometry": {"coordinates":[150.43182373100001,-25.0342769623],"type":"Point"}
}