{
  "type": "Feature",
  "properties": {
    "addr:full":"Level 6, 60 Marcus Clarke St Canberra ACT 0230",
    "addr:housenumber":"60",
    "addr:postcode":"0230",
    "addr:street":"Marcus Clarke St",
    "iso:country":"AU",
    "sg:address":"Level 6, 60 Marcus Clarke St",
    "sg:city":"Canberra",
    "sg:classifiers":[
        {
            "category":"Professional",
            "subcategory":"Business Services",
            "type":"Services"
        }
    ],
    "sg:phone":"+61 2 6243 5153",
    "sg:postcode":"0230",
    "sg:province":"ACT",
    "sg:tags":[
        "record",
        "management",
        "storage"
    ],
    "wof:name":"Objective Corporation Ltd",
    "wof:placetype":"venue"
},
  "geometry": {"coordinates":[149.12690734899999,-35.2758331299],"type":"Point"}
}