{
  "type": "Feature",
  "properties": {
    "iso:country":"AU",
    "sg:address":"RPA Medical Centre Suite: 306/ 100 Carillon Ave",
    "sg:city":"Newtown",
    "sg:classifiers":[
        {
            "category":"Health Services",
            "subcategory":"Doctor",
            "type":"Services"
        }
    ],
    "sg:phone":"+61 2 9516 4525",
    "sg:postcode":"2042",
    "sg:province":"NSW",
    "sg:tags":[
        "medical",
        "practitioner"
    ],
    "wof:name":"Griffin Sean P",
    "wof:placetype":"venue"
},
  "geometry": {"coordinates":[151.183304,-33.891499],"type":"Point"}
}