{
  "type": "Feature",
  "properties": {
    "iso:country":"AU",
    "sg:address":"5 Lygon St",
    "sg:city":"Coburg",
    "sg:classifiers":[
        {
            "category":"Shopping",
            "subcategory":"Computers & Home Electronics",
            "type":"Retail Goods"
        }
    ],
    "sg:phone":"+61 419 319 714",
    "sg:postcode":"3058",
    "sg:province":"VIC",
    "sg:tags":[
        "equipment",
        "multimedia"
    ],
    "wof:name":"Computer Media Designs",
    "wof:placetype":"venue"
},
  "geometry": {"coordinates":[144.97349548299999,-37.7551612854],"type":"Point"}
}