{
  "type": "Feature",
  "properties": {
    "iso:country":"AU",
    "sg:address":"18 Orange Ave",
    "sg:city":"Mildura",
    "sg:classifiers":[
        {
            "category":"Building & Trades",
            "subcategory":"Construction",
            "type":"Services"
        }
    ],
    "sg:phone":"+61 3 5022 2434",
    "sg:postcode":"3500",
    "sg:province":"VIC",
    "sg:tags":[
        "roof"
    ],
    "wof:name":"Nu-Look Home Improvements Pty Ltd",
    "wof:placetype":"venue"
},
  "geometry": {"coordinates":[142.16635131800001,-34.1857337952],"type":"Point"}
}