{
  "type": "Feature",
  "properties": {
    "addr:full":"138 Bulcock St Caloundra QLD 4551",
    "addr:housenumber":"138",
    "addr:postcode":"4551",
    "addr:street":"Bulcock St",
    "iso:country":"AU",
    "sg:address":"138 Bulcock St",
    "sg:city":"Caloundra",
    "sg:classifiers":[
        {
            "category":"Banks & Credit Unions",
            "subcategory":"Investment Brokerage",
            "type":"Services"
        }
    ],
    "sg:phone":"+61 7 5491 9933",
    "sg:postcode":"4551",
    "sg:province":"QLD",
    "sg:tags":[
        "sewing",
        "thread"
    ],
    "wof:name":"B'Creative Patchwork & Sewing",
    "wof:placetype":"venue"
},
  "geometry": {"coordinates":[153.126831055,-26.8045310974],"type":"Point"}
}