{
  "type": "Feature",
  "properties": {
    "iso:country":"AU",
    "sg:address":"Wilkes Crs",
    "sg:city":"Tregear",
    "sg:classifiers":[
        {
            "category":"Social Services",
            "subcategory":"Child Care",
            "type":"Services"
        }
    ],
    "sg:phone":"+61 2 9628 0569",
    "sg:postcode":"2770",
    "sg:province":"NSW",
    "sg:tags":[
        "support",
        "health"
    ],
    "wof:name":"Early Childhood Health Centres",
    "wof:placetype":"venue"
},
  "geometry": {"coordinates":[150.79685974099999,-33.7514190674],"type":"Point"}
}