{
  "type": "Feature",
  "properties": {
    "iso:country":"AU",
    "sg:address":"U1/ 25 Geils Crt",
    "sg:city":"Deakin",
    "sg:classifiers":[
        {
            "category":"Real Estate",
            "subcategory":"Real Estate Agent",
            "type":"Services"
        }
    ],
    "sg:phone":"+61 2 6282 0222",
    "sg:postcode":"2600",
    "sg:province":"ACT",
    "wof:name":"Referencelink",
    "wof:placetype":"venue"
},
  "geometry": {"coordinates":[149.09713745100001,-35.3166847229],"type":"Point"}
}