{
  "type": "Feature",
  "properties": {
    "addr:full":"354 Wright Rd Para Vista SA 5093",
    "addr:housenumber":"354",
    "addr:postcode":"5093",
    "addr:street":"Wright Rd Para",
    "iso:country":"AU",
    "sg:address":"354 Wright Rd",
    "sg:city":"Para Vista",
    "sg:classifiers":[
        {
            "category":"Education",
            "subcategory":"School",
            "type":"Public Place"
        }
    ],
    "sg:phone":"+61 8 8269 2177",
    "sg:postcode":"5093",
    "sg:province":"SA",
    "sg:tags":[
        "co-educational"
    ],
    "wof:name":"Seventh Day Adventist",
    "wof:placetype":"venue"
},
  "geometry": {"coordinates":[138.663696289,-34.8346252441],"type":"Point"}
}