{
  "type": "Feature",
  "properties": {
    "iso:country":"AU",
    "sg:address":"Level 1 / 230 Brunswick St",
    "sg:city":"Fitzroy",
    "sg:classifiers":[
        {
            "category":"Arena",
            "subcategory":"Indoor Arena",
            "type":"Entertainment"
        }
    ],
    "sg:phone":"+61 3 9018 9219",
    "sg:postcode":"3065",
    "sg:province":"VIC",
    "sg:tags":[
        "modelmakers"
    ],
    "wof:name":"Architour 3D Interactive Walk-Throughs",
    "wof:placetype":"venue"
},
  "geometry": {"coordinates":[144.97819519000001,-37.8007278442],"type":"Point"}
}