{
  "type": "Feature",
  "properties": {
    "addr:full":"90 Wheatsheaf Rd Glenroy VIC 3046",
    "addr:housenumber":"90",
    "addr:postcode":"3046",
    "addr:street":"Wheatsheaf Rd",
    "iso:country":"AU",
    "sg:address":"90 Wheatsheaf Rd",
    "sg:city":"Glenroy",
    "sg:classifiers":[
        {
            "category":"Shopping",
            "subcategory":"Bicycles & Sporting Goods",
            "type":"Retail Goods"
        }
    ],
    "sg:phone":"+61 3 9306 0099",
    "sg:postcode":"3046",
    "sg:province":"VIC",
    "sg:tags":[
        "dance",
        "accessory",
        "wear",
        "supply"
    ],
    "sg:website":"http://www.thedancewearcompany.com.au",
    "wof:name":"The Dancewear Company",
    "wof:placetype":"venue"
},
  "geometry": {"coordinates":[144.91940307600001,-37.706287384],"type":"Point"}
}