{
  "type": "Feature",
  "properties": {
    "addr:full":"16 Nullaburra Rd Caringbah NSW 2229",
    "addr:housenumber":"16",
    "addr:postcode":"2229",
    "addr:street":"Nullaburra Rd",
    "iso:country":"AU",
    "sg:address":"16 Nullaburra Rd",
    "sg:city":"Caringbah",
    "sg:classifiers":[
        {
            "category":"Professional",
            "subcategory":"Management & Consulting",
            "type":"Services"
        }
    ],
    "sg:phone":"+61 412 772 306",
    "sg:postcode":"2229",
    "sg:province":"NSW",
    "sg:tags":[
        "consultant"
    ],
    "wof:name":"Qualbiz Pty Ltd",
    "wof:placetype":"venue"
},
  "geometry": {"coordinates":[151.13055419899999,-34.041431427],"type":"Point"}
}