{
  "type": "Feature",
  "properties": {
    "iso:country":"AU",
    "sg:address":"Suite 3 Floor 2F 239- 241 Park St",
    "sg:city":"South Melbourne",
    "sg:classifiers":[
        {
            "category":"Sports & Exercise",
            "subcategory":"Gym",
            "type":"Entertainment"
        }
    ],
    "sg:phone":"+61 3 9645 9999",
    "sg:postcode":"3205",
    "sg:province":"VIC",
    "sg:tags":[
        "health",
        "fitness"
    ],
    "wof:name":"Kim Baxter Body Concepts Studio",
    "wof:placetype":"venue"
},
  "geometry": {"coordinates":[144.960022,-37.8358],"type":"Point"}
}