{
  "type": "Feature",
  "properties": {
    "addr:full":"502- 506 Anzac Pde Kingsford NSW 2032",
    "addr:housenumber":"506",
    "addr:postcode":"2032",
    "addr:street":"Anzac Pde",
    "iso:country":"AU",
    "sg:address":"502- 506 Anzac Pde",
    "sg:city":"Kingsford",
    "sg:classifiers":[
        {
            "category":"Shopping",
            "subcategory":"Optical Goods",
            "type":"Retail Goods"
        }
    ],
    "sg:phone":"+61 2 9663 2041",
    "sg:postcode":"2032",
    "sg:province":"NSW",
    "sg:tags":[
        "dispenser",
        "prescription"
    ],
    "wof:name":"Optical Illusions",
    "wof:placetype":"venue"
},
  "geometry": {"coordinates":[151.22752380399999,-33.9231948853],"type":"Point"}
}