{
  "type": "Feature",
  "properties": {
    "iso:country":"AU",
    "sg:address":"116 Wray Ave",
    "sg:city":"Fremantle",
    "sg:classifiers":[
        {
            "category":"Health Services",
            "subcategory":"Health Practitioner",
            "type":"Services"
        }
    ],
    "sg:phone":"+61 8 9430 7999",
    "sg:postcode":"6160",
    "sg:province":"WA",
    "sg:tags":[
        "audiologists"
    ],
    "wof:name":"Western Hearing Services",
    "wof:placetype":"venue"
},
  "geometry": {"coordinates":[115.75721,-32.061802],"type":"Point"}
}