{
  "type": "Feature",
  "properties": {
    "iso:country":"AU",
    "sg:address":"23 Bathurst St",
    "sg:city":"Richmond",
    "sg:classifiers":[
        {
            "category":"Health Services",
            "subcategory":"Doctor",
            "type":"Services"
        }
    ],
    "sg:phone":"+61 3 6260 2169",
    "sg:postcode":"7025",
    "sg:province":"TAS",
    "sg:tags":[
        "medical",
        "practitioner"
    ],
    "wof:name":"Mesch Ute",
    "wof:placetype":"venue"
},
  "geometry": {"coordinates":[147.43707275400001,-42.7372779846],"type":"Point"}
}