{
  "type": "Feature",
  "properties": {
    "addr:full":"142 North St North Albury NSW 2640",
    "addr:housenumber":"142",
    "addr:postcode":"2640",
    "addr:street":"North St North",
    "iso:country":"AU",
    "sg:address":"142 North St",
    "sg:city":"North Albury",
    "sg:classifiers":[
        {
            "category":"Industrial Area",
            "type":"Public Place"
        }
    ],
    "sg:phone":"+61 2 6041 3336",
    "sg:postcode":"2640",
    "sg:province":"NSW",
    "sg:tags":[
        "rural",
        "shed"
    ],
    "wof:name":"Shed Tek Industrial",
    "wof:placetype":"venue"
},
  "geometry": {"coordinates":[146.939697266,-36.0697288513],"type":"Point"}
}