{
  "type": "Feature",
  "properties": {
    "iso:country":"AU",
    "sg:address":"34 Timbercrest Rd",
    "sg:city":"Thornlie",
    "sg:classifiers":[
        {
            "category":"Education",
            "subcategory":"Dance Studio",
            "type":"Public Place"
        }
    ],
    "sg:phone":"+61 8 9452 1250",
    "sg:postcode":"6108",
    "sg:province":"WA",
    "sg:tags":[
        "instruction",
        "language"
    ],
    "wof:name":"Whyte Greg",
    "wof:placetype":"venue"
},
  "geometry": {"coordinates":[115.955383301,-32.0751914978],"type":"Point"}
}