{
  "type": "Feature",
  "properties": {
    "addr:full":"PO Box 739 Niddrie VIC 3042",
    "addr:postcode":"3042",
    "iso:country":"AU",
    "sg:address":"PO Box 739",
    "sg:city":"Niddrie",
    "sg:classifiers":[
        {
            "category":"Shopping",
            "subcategory":"Party Supplies",
            "type":"Retail Goods"
        }
    ],
    "sg:phone":"+61 3 8307 5999",
    "sg:postcode":"3042",
    "sg:province":"VIC",
    "sg:tags":[
        "children's"
    ],
    "wof:name":"Cheeky Face",
    "wof:placetype":"venue"
},
  "geometry": {"coordinates":[144.88703918499999,-37.7300224304],"type":"Point"}
}