{
  "type": "Feature",
  "properties": {
    "addr:full":"572 Station St Box Hill VIC 3128",
    "addr:housenumber":"572",
    "addr:postcode":"3128",
    "addr:street":"Station St",
    "iso:country":"AU",
    "sg:address":"572 Station St",
    "sg:city":"Box Hill",
    "sg:classifiers":[
        {
            "category":"Restaurant",
            "type":"Food & Drink"
        }
    ],
    "sg:phone":"+61 3 9890 3719",
    "sg:postcode":"3128",
    "sg:province":"VIC",
    "wof:name":"Dumpling King",
    "wof:placetype":"venue"
},
  "geometry": {"coordinates":[145.12362670900001,-37.8199882507],"type":"Point"}
}