{
  "type": "Feature",
  "properties": {
    "addr:full":"243a Burnside Rd Stapylton QLD 4207",
    "addr:housenumber":"243a",
    "addr:postcode":"4207",
    "addr:street":"Burnside Rd",
    "iso:country":"AU",
    "sg:address":"243a Burnside Rd",
    "sg:city":"Stapylton",
    "sg:classifiers":[
        {
            "category":"Building & Trades",
            "subcategory":"Construction",
            "type":"Services"
        }
    ],
    "sg:phone":"+61 7 3287 1844",
    "sg:postcode":"4207",
    "sg:province":"QLD",
    "sg:tags":[
        "earth",
        "excavating",
        "moving",
        "contractor"
    ],
    "wof:name":"Coops Drainage & Civil",
    "wof:placetype":"venue"
},
  "geometry": {"coordinates":[153.24107360799999,-27.7547779083],"type":"Point"}
}