{
  "type": "Feature",
  "properties": {
    "addr:full":"Fitzherbert Pl Bruce ACT 2617",
    "addr:postcode":"2617",
    "addr:street":"Fitzherbert Pl",
    "iso:country":"AU",
    "sg:address":"Fitzherbert Pl",
    "sg:city":"Bruce",
    "sg:classifiers":[
        {
            "category":"Health Services",
            "subcategory":"Doctor",
            "type":"Services"
        }
    ],
    "sg:phone":"+61 2 6251 6369",
    "sg:postcode":"2617",
    "sg:province":"ACT",
    "sg:tags":[
        "reflexology"
    ],
    "wof:name":"Deirdre Brocklebank",
    "wof:placetype":"venue"
},
  "geometry": {"coordinates":[149.083618164,-35.250377655],"type":"Point"}
}