{
  "type": "Feature",
  "properties": {
    "addr:full":"Willis Rd Woolgoolga NSW 2456",
    "addr:postcode":"2456",
    "addr:street":"Willis Rd",
    "iso:country":"AU",
    "sg:address":"Willis Rd",
    "sg:city":"Woolgoolga",
    "sg:classifiers":[
        {
            "category":"Home & Garden",
            "subcategory":"Building Materials",
            "type":"Retail Goods"
        }
    ],
    "sg:phone":"+61 2 6654 1466",
    "sg:postcode":"2456",
    "sg:province":"NSW",
    "sg:tags":[
        "merchant",
        "glass",
        "glazier"
    ],
    "wof:name":"AAA David Eggins Woolgoolga Glass Service",
    "wof:placetype":"venue"
},
  "geometry": {"coordinates":[153.19592299999999,-30.126003],"type":"Point"}
}