{
  "type": "Feature",
  "properties": {
    "iso:country":"AU",
    "sg:address":"Unit 4, 2 Cooper Rd",
    "sg:city":"Jandakot",
    "sg:classifiers":[
        {
            "category":"Wholesale",
            "subcategory":"Medical Equipment & Supplies",
            "type":"Manufacturing & Wholesale Goods"
        }
    ],
    "sg:phone":"+61 8 9414 8000",
    "sg:postcode":"6164",
    "sg:province":"WA",
    "sg:tags":[
        "dental"
    ],
    "wof:name":"M & M Interiors",
    "wof:placetype":"venue"
},
  "geometry": {"coordinates":[115.844597,-32.123734],"type":"Point"}
}