{
  "type": "Feature",
  "properties": {
    "addr:full":"97 Wootha Rd Maleny QLD 4552",
    "addr:housenumber":"97",
    "addr:postcode":"4552",
    "addr:street":"Wootha Rd",
    "iso:country":"AU",
    "sg:address":"97 Wootha Rd",
    "sg:city":"Maleny",
    "sg:classifiers":[
        {
            "category":"Professional",
            "subcategory":"Business Services",
            "type":"Services"
        }
    ],
    "sg:phone":"+61 7 5494 2414",
    "sg:postcode":"4552",
    "sg:province":"QLD",
    "sg:tags":[
        "drafting"
    ],
    "wof:name":"Gibson J S",
    "wof:placetype":"venue"
},
  "geometry": {"coordinates":[152.84934997600001,-26.7581195831],"type":"Point"}
}