{
  "type": "Feature",
  "properties": {
    "iso:country":"AU",
    "sg:address":"4 Faraday St",
    "sg:city":"West Hobart",
    "sg:classifiers":[
        {
            "category":"Shopping",
            "subcategory":"Bicycles & Sporting Goods",
            "type":"Retail Goods"
        }
    ],
    "sg:phone":"+61 3 6234 4525",
    "sg:postcode":"7000",
    "sg:province":"TAS",
    "sg:tags":[
        "dance",
        "accessory",
        "wear",
        "supply"
    ],
    "wof:name":"Enchantee",
    "wof:placetype":"venue"
},
  "geometry": {"coordinates":[147.315475464,-42.8848686218],"type":"Point"}
}