{
  "type": "Feature",
  "properties": {
    "addr:full":"102 Grange Rd Glen Huntly VIC 3163",
    "addr:housenumber":"102",
    "addr:postcode":"3163",
    "addr:street":"Grange Rd",
    "iso:country":"AU",
    "sg:address":"102 Grange Rd",
    "sg:city":"Glen Huntly",
    "sg:classifiers":[
        {
            "category":"Education",
            "subcategory":"Special Training",
            "type":"Public Place"
        }
    ],
    "sg:phone":"+61 419 348 992",
    "sg:postcode":"3163",
    "sg:province":"VIC",
    "sg:tags":[
        "development"
    ],
    "wof:name":"el camino#",
    "wof:placetype":"venue"
},
  "geometry": {"coordinates":[145.04547119099999,-37.8887329102],"type":"Point"}
}