{
  "type": "Feature",
  "properties": {
    "iso:country":"AU",
    "sg:address":"Main Rd",
    "sg:city":"Whitfield",
    "sg:classifiers":[
        {
            "category":"Food & Beverages",
            "subcategory":"Groceries & Convenience Stores",
            "type":"Retail Goods"
        }
    ],
    "sg:phone":"+61 3 5729 8237",
    "sg:postcode":"3733",
    "sg:province":"VIC",
    "wof:name":"Whitfield General Store",
    "wof:placetype":"venue"
},
  "geometry": {"coordinates":[146.41418457,-36.7657661438],"type":"Point"}
}