{
  "type": "Feature",
  "properties": {
    "addr:full":"Lvl 1/ 36- Waterloo Rd Macquarie Park NSW 2113",
    "addr:housenumber":"/ 36",
    "addr:postcode":"2113",
    "addr:street":"Waterloo Rd",
    "iso:country":"AU",
    "sg:address":"Lvl 1/ 36- Waterloo Rd",
    "sg:city":"Macquarie Park",
    "sg:classifiers":[
        {
            "category":"Professional",
            "subcategory":"Computer Services",
            "type":"Services"
        }
    ],
    "sg:phone":"+61 1300 666 044",
    "sg:postcode":"2113",
    "sg:province":"NSW",
    "sg:tags":[
        "package",
        "software"
    ],
    "wof:name":"marketboomer Pty Ltd",
    "wof:placetype":"venue"
},
  "geometry": {"coordinates":[151.120635986,-33.7795524597],"type":"Point"}
}