{
  "type": "Feature",
  "properties": {
    "addr:full":"489 Townsend St Albury NSW 2640",
    "addr:housenumber":"489",
    "addr:postcode":"2640",
    "addr:street":"Townsend St",
    "iso:country":"AU",
    "sg:address":"489 Townsend St",
    "sg:city":"Albury",
    "sg:classifiers":[
        {
            "category":"Communications",
            "subcategory":"Film & Video Production",
            "type":"Services"
        }
    ],
    "sg:phone":"+61 2 6021 8522",
    "sg:postcode":"2640",
    "sg:province":"NSW",
    "sg:tags":[
        "dvd",
        "library"
    ],
    "wof:name":"Movieland Albury",
    "wof:placetype":"venue"
},
  "geometry": {"coordinates":[146.91317749000001,-36.080745697],"type":"Point"}
}