{
  "type": "Feature",
  "properties": {
    "addr:full":"1B Kapai Pl South Kalgoorlie WA 6430",
    "addr:housenumber":"1b",
    "addr:postcode":"6430",
    "addr:street":"Kapai Pl South",
    "iso:country":"AU",
    "sg:address":"1B Kapai Pl",
    "sg:city":"South Kalgoorlie",
    "sg:classifiers":[
        {
            "category":"Building & Trades",
            "subcategory":"Plumbing",
            "type":"Services"
        }
    ],
    "sg:phone":"+61 8 9091 6888",
    "sg:postcode":"6430",
    "sg:province":"WA",
    "sg:tags":[
        "equipment",
        "valves"
    ],
    "wof:name":"Advanced Flow Industries Pty Ltd",
    "wof:placetype":"venue"
},
  "geometry": {"coordinates":[121.481117248,-30.7718887329],"type":"Point"}
}