{
  "type": "Feature",
  "properties": {
    "addr:full":"9 Lambeck Drv Tullamarine VIC 3043",
    "addr:housenumber":"9",
    "addr:postcode":"3043",
    "addr:street":"Lambeck Drv",
    "iso:country":"AU",
    "sg:address":"9 Lambeck Drv",
    "sg:city":"Tullamarine",
    "sg:classifiers":[
        {
            "category":"Airline",
            "type":"Transportation"
        }
    ],
    "sg:phone":"+61 3 9334 5727",
    "sg:postcode":"3043",
    "sg:province":"VIC",
    "sg:tags":[
        "aircraft",
        "rental",
        "charter"
    ],
    "wof:name":"Air Cargo Australia Pty Ltd",
    "wof:placetype":"venue"
},
  "geometry": {"coordinates":[144.852096558,-37.7025146484],"type":"Point"}
}