{
  "type": "Feature",
  "properties": {
    "addr:full":"Shop 3/ 130 High St Fremantle WA 6160",
    "addr:housenumber":"shop 3 / 130",
    "addr:postcode":"6160",
    "addr:street":"High St",
    "iso:country":"AU",
    "sg:address":"Shop 3/ 130 High St",
    "sg:city":"Fremantle",
    "sg:classifiers":[
        {
            "category":"Food & Beverages",
            "subcategory":"Specialty",
            "type":"Retail Goods"
        }
    ],
    "sg:phone":"+61 8 9430 9710",
    "sg:postcode":"6160",
    "sg:province":"WA",
    "sg:tags":[
        "delicacy"
    ],
    "wof:name":"Krakus",
    "wof:placetype":"venue"
},
  "geometry": {"coordinates":[115.74945099999999,-32.05341],"type":"Point"}
}