{
  "type": "Feature",
  "properties": {
    "addr:full":"11 Whitehouse St Garbutt QLD 4814",
    "addr:housenumber":"11",
    "addr:postcode":"4814",
    "addr:street":"Whitehouse St",
    "iso:country":"AU",
    "sg:address":"11 Whitehouse St",
    "sg:city":"Garbutt",
    "sg:classifiers":[
        {
            "category":"Building & Trades",
            "subcategory":"Construction",
            "type":"Services"
        }
    ],
    "sg:phone":"+61 7 4779 0544",
    "sg:postcode":"4814",
    "sg:province":"QLD",
    "sg:tags":[
        "scaffolding"
    ],
    "wof:name":"RMD Australia",
    "wof:placetype":"venue"
},
  "geometry": {"coordinates":[146.754807,-19.271378],"type":"Point"}
}