{
  "type": "Feature",
  "properties": {
    "addr:full":"26 Whistlepipe Crt Forrestfield WA 6058",
    "addr:housenumber":"26",
    "addr:postcode":"6058",
    "addr:street":"Whistlepipe Crt",
    "iso:country":"AU",
    "sg:address":"26 Whistlepipe Crt",
    "sg:city":"Forrestfield",
    "sg:classifiers":[
        {
            "category":"Shopping",
            "type":"Retail Goods"
        }
    ],
    "sg:phone":"+61 8 9359 2195",
    "sg:postcode":"6058",
    "sg:province":"WA",
    "sg:tags":[
        "equipment",
        "safety",
        "accessory"
    ],
    "wof:name":"Safety Aerials Australia",
    "wof:placetype":"venue"
},
  "geometry": {"coordinates":[116.026672363,-31.9809970856],"type":"Point"}
}