{
  "type": "Feature",
  "properties": {
    "addr:full":"437 Yaamba Rd Rockhampton QLD 4700",
    "addr:housenumber":"437",
    "addr:postcode":"4700",
    "addr:street":"Yaamba Rd",
    "iso:country":"AU",
    "sg:address":"437 Yaamba Rd",
    "sg:city":"Rockhampton",
    "sg:classifiers":[
        {
            "category":"Home & Garden",
            "subcategory":"Furniture",
            "type":"Retail Goods"
        }
    ],
    "sg:phone":"+61 7 4926 5405",
    "sg:postcode":"4700",
    "sg:province":"QLD",
    "sg:tags":[
        "outdoor"
    ],
    "wof:name":"Barbeques Galore",
    "wof:placetype":"venue"
},
  "geometry": {"coordinates":[150.519897461,-23.3419876099],"type":"Point"}
}