{
  "type": "Feature",
  "properties": {
    "addr:full":"Unit 3, 294 Wickham Rd Moorabbin VIC 3189",
    "addr:housenumber":"294",
    "addr:postcode":"3189",
    "addr:street":"Wickham Rd",
    "iso:country":"AU",
    "sg:address":"Unit 3, 294 Wickham Rd",
    "sg:city":"Moorabbin",
    "sg:classifiers":[
        {
            "category":"Health Services",
            "subcategory":"Doctor",
            "type":"Services"
        }
    ],
    "sg:phone":"+61 3 9591 0733",
    "sg:postcode":"3189",
    "sg:province":"VIC",
    "sg:tags":[
        "occupational",
        "safety"
    ],
    "sg:website":"http://www.jta.net.au",
    "wof:name":"JTA Risk Management",
    "wof:placetype":"venue"
},
  "geometry": {"coordinates":[145.05894470199999,-37.9472961426],"type":"Point"}
}