{
  "type": "Feature",
  "properties": {
    "iso:country":"AU",
    "sg:address":"10 Roydhouse St",
    "sg:city":"Subiaco",
    "sg:classifiers":[
        {
            "category":"Utilities",
            "type":"Services"
        }
    ],
    "sg:phone":"+61 8 9388 3674",
    "sg:postcode":"6008",
    "sg:province":"WA",
    "sg:tags":[
        "refrigeration",
        "industrial",
        "commercial",
        "retail"
    ],
    "sg:website":"http://www.arcus.biz",
    "wof:name":"Arcus Australia Pty Ltd",
    "wof:placetype":"venue"
},
  "geometry": {"coordinates":[115.82215118400001,-31.9430561066],"type":"Point"}
}