{
  "type": "Feature",
  "properties": {
    "addr:full":"21a Raglan St Daylesford VIC 3460",
    "addr:housenumber":"21a",
    "addr:postcode":"3460",
    "addr:street":"Raglan St",
    "iso:country":"AU",
    "sg:address":"21a Raglan St",
    "sg:city":"Daylesford",
    "sg:classifiers":[
        {
            "category":"Manufacturing",
            "subcategory":"Furniture",
            "type":"Manufacturing & Wholesale Goods"
        }
    ],
    "sg:phone":"+61 3 5348 4050",
    "sg:postcode":"3460",
    "sg:province":"VIC",
    "sg:tags":[
        "builder",
        "designer",
        "custom"
    ],
    "wof:name":"The Wood Shed Gallery",
    "wof:placetype":"venue"
},
  "geometry": {"coordinates":[144.15199279800001,-37.3403778076],"type":"Point"}
}