{
  "type": "Feature",
  "properties": {
    "iso:country":"AU",
    "sg:address":"234 Marrickville Rd",
    "sg:city":"Marrickville",
    "sg:classifiers":[
        {
            "category":"Shopping",
            "subcategory":"Clothing, Apparel, & Fashions",
            "type":"Retail Goods"
        }
    ],
    "sg:phone":"+61 2 9569 3001",
    "sg:postcode":"2204",
    "sg:province":"NSW",
    "sg:tags":[
        "lady",
        "wear"
    ],
    "wof:name":"Route 1 Collections",
    "wof:placetype":"venue"
},
  "geometry": {"coordinates":[151.15832499999999,-33.911587],"type":"Point"}
}