{
  "type": "Feature",
  "properties": {
    "iso:country":"AU",
    "sg:address":"28 Mears St",
    "sg:city":"Mysterton",
    "sg:classifiers":[
        {
            "category":"Utilities",
            "subcategory":"Electric",
            "type":"Services"
        }
    ],
    "sg:phone":"+61 418 733 256",
    "sg:postcode":"4812",
    "sg:province":"QLD",
    "sg:tags":[
        "electrical",
        "contractor"
    ],
    "wof:name":"Greg Bimrose Electrical Services",
    "wof:placetype":"venue"
},
  "geometry": {"coordinates":[146.79466199999999,-19.287567],"type":"Point"}
}