{
  "type": "Feature",
  "properties": {
    "addr:full":"Sydney Harbour National Park Cliff St Watsons Bay NSW 2030",
    "addr:postcode":"2030",
    "addr:street":"Cliff St",
    "iso:country":"AU",
    "sg:address":"Sydney Harbour National Park Cliff St",
    "sg:city":"Watsons Bay",
    "sg:classifiers":[
        {
            "category":"Retail",
            "subcategory":"Event Space",
            "type":"Services"
        }
    ],
    "sg:phone":"+61 2 9337 2333",
    "sg:postcode":"2030",
    "sg:province":"NSW",
    "sg:tags":[
        "function",
        "organiser"
    ],
    "wof:name":"Gap Bluff Centre The",
    "wof:placetype":"venue"
},
  "geometry": {"coordinates":[151.28222656200001,-33.8420562744],"type":"Point"}
}