{
  "type": "Feature",
  "properties": {
    "addr:full":"904 South Pine Rd Everton Park QLD 4053",
    "addr:housenumber":"904",
    "addr:postcode":"4053",
    "addr:street":"South Pine Rd",
    "iso:country":"AU",
    "sg:address":"904 South Pine Rd",
    "sg:city":"Everton Park",
    "sg:classifiers":[
        {
            "category":"Retail",
            "subcategory":"Repair Shop",
            "type":"Services"
        }
    ],
    "sg:phone":"+61 7 3355 6754",
    "sg:postcode":"4053",
    "sg:province":"QLD",
    "sg:tags":[
        "maintenance",
        "pool",
        "swimming"
    ],
    "wof:name":"Queensland Pool Painting",
    "wof:placetype":"venue"
},
  "geometry": {"coordinates":[152.97996520999999,-27.3949203491],"type":"Point"}
}