{
  "type": "Feature",
  "properties": {
    "iso:country":"AU",
    "sg:address":"Level 2, Building 61, Fox Stud Driver Ave",
    "sg:city":"Moore Park",
    "sg:classifiers":[
        {
            "category":"Professional",
            "subcategory":"Art Services",
            "type":"Services"
        }
    ],
    "sg:phone":"+61 419 888 877",
    "sg:postcode":"1363",
    "sg:province":"NSW",
    "sg:tags":[
        "arranger",
        "music",
        "composer"
    ],
    "wof:name":"Subsdance Music",
    "wof:placetype":"venue"
},
  "geometry": {"coordinates":[151.220458984,-33.8867950439],"type":"Point"}
}