{
  "type": "Feature",
  "properties": {
    "iso:country":"AU",
    "sg:address":"17 McMahon St",
    "sg:city":"Griffith",
    "sg:classifiers":[
        {
            "category":"Professional",
            "subcategory":"Art Services",
            "type":"Services"
        }
    ],
    "sg:phone":"+61 418 252 309",
    "sg:postcode":"2680",
    "sg:province":"NSW",
    "sg:tags":[
        "decorator",
        "painter"
    ],
    "wof:name":"Favero Lorence & Cheryl",
    "wof:placetype":"venue"
},
  "geometry": {"coordinates":[146.079742,-34.267666],"type":"Point"}
}