{
  "type": "Feature",
  "properties": {
    "addr:full":"201a Beecroft Rd Cheltenham NSW 2119",
    "addr:housenumber":"201a",
    "addr:postcode":"2119",
    "addr:street":"Beecroft Rd",
    "iso:country":"AU",
    "sg:address":"201a Beecroft Rd",
    "sg:city":"Cheltenham",
    "sg:classifiers":[
        {
            "category":"Real Estate",
            "subcategory":"Surveying",
            "type":"Services"
        }
    ],
    "sg:phone":"+61 2 9869 7596",
    "sg:postcode":"2119",
    "sg:province":"NSW",
    "sg:tags":[
        "surveyor",
        "land"
    ],
    "wof:name":"Naughton J M",
    "wof:placetype":"venue"
},
  "geometry": {"coordinates":[151.07696533199999,-33.7588653564],"type":"Point"}
}