{
  "type": "Feature",
  "properties": {
    "addr:full":"1769 Main Rd Great Bay TAS 7150",
    "addr:housenumber":"1769",
    "addr:postcode":"7150",
    "addr:street":"Main Rd",
    "iso:country":"AU",
    "sg:address":"1769 Main Rd",
    "sg:city":"Great Bay",
    "sg:classifiers":[
        {
            "category":"Government",
            "subcategory":"Court House",
            "type":"Public Place"
        }
    ],
    "sg:phone":"+61 427 550 696",
    "sg:postcode":"7150",
    "sg:province":"TAS",
    "sg:tags":[
        "personal",
        "marriage",
        "family",
        "counselling"
    ],
    "wof:name":"Townrow D",
    "wof:placetype":"venue"
},
  "geometry": {"coordinates":[147.19984435999999,-43.0165748596],"type":"Point"}
}