{
  "type": "Feature",
  "properties": {
    "iso:country":"AU",
    "sg:address":"RMB 225 Ramsey Rd",
    "sg:city":"Stratham",
    "sg:classifiers":[
        {
            "category":"Manufacturing",
            "subcategory":"Pottery",
            "type":"Manufacturing & Wholesale Goods"
        }
    ],
    "sg:phone":"+61 8 9795 7478",
    "sg:postcode":"6237",
    "sg:province":"WA",
    "wof:name":"Peppi Pottery",
    "wof:placetype":"venue"
},
  "geometry": {"coordinates":[115.593468,-33.453377],"type":"Point"}
}