{
  "type": "Feature",
  "properties": {
    "addr:full":"322 Blowhole Rd Eaglehawk Neck TAS 7179",
    "addr:housenumber":"322",
    "addr:postcode":"7179",
    "addr:street":"Blowhole Rd",
    "iso:country":"AU",
    "sg:address":"322 Blowhole Rd",
    "sg:city":"Eaglehawk Neck",
    "sg:classifiers":[
        {
            "category":"Recreation",
            "subcategory":"Boat Charter",
            "type":"Entertainment"
        }
    ],
    "sg:phone":"+61 3 6250 3370",
    "sg:postcode":"7179",
    "sg:province":"TAS",
    "wof:name":"Personalised Sea Charters",
    "wof:placetype":"venue"
},
  "geometry": {"coordinates":[147.944854736,-43.0376663208],"type":"Point"}
}