{
  "type": "Feature",
  "properties": {
    "iso:country":"AU",
    "sg:address":"1/ 35 Howard St",
    "sg:city":"Brisbane",
    "sg:classifiers":[
        {
            "category":"Retail",
            "subcategory":"Event Space",
            "type":"Services"
        }
    ],
    "sg:phone":"+61 7 3832 0322",
    "sg:postcode":"4000",
    "sg:province":"QLD",
    "sg:tags":[
        "venue",
        "reception",
        "wedding"
    ],
    "wof:name":"Bubbles & Beans",
    "wof:placetype":"venue"
},
  "geometry": {"coordinates":[153.03228759800001,-27.4634494781],"type":"Point"}
}