{
  "type": "Feature",
  "properties": {
    "addr:full":"13 Resolution Drv Caringbah NSW 2229",
    "addr:housenumber":"13",
    "addr:postcode":"2229",
    "addr:street":"Resolution Drv",
    "iso:country":"AU",
    "sg:address":"13 Resolution Drv",
    "sg:city":"Caringbah",
    "sg:classifiers":[
        {
            "category":"Manufacturing",
            "subcategory":"Metals",
            "type":"Manufacturing & Wholesale Goods"
        }
    ],
    "sg:phone":"+61 2 9525 8719",
    "sg:postcode":"2229",
    "sg:province":"NSW",
    "sg:tags":[
        "steel",
        "fabricator",
        "mfrs"
    ],
    "wof:name":"J M T Engineering & Fabricators Pty Ltd",
    "wof:placetype":"venue"
},
  "geometry": {"coordinates":[151.13262939399999,-34.0331573486],"type":"Point"}
}