{
  "type": "Feature",
  "properties": {
    "addr:full":"Griffith Rd Eastern Heights QLD 4305",
    "addr:postcode":"4305",
    "addr:street":"Griffith Rd",
    "iso:country":"AU",
    "sg:address":"Griffith Rd",
    "sg:city":"Eastern Heights",
    "sg:classifiers":[
        {
            "category":"Retail",
            "subcategory":"Event Space",
            "type":"Services"
        }
    ],
    "sg:phone":"+61 7 3281 2547",
    "sg:postcode":"4305",
    "sg:province":"QLD",
    "sg:tags":[
        "venue",
        "reception",
        "wedding"
    ],
    "wof:name":"Ipswich PCYC and Pulse",
    "wof:placetype":"venue"
},
  "geometry": {"coordinates":[152.77151489299999,-27.6230106354],"type":"Point"}
}