{
  "type": "Feature",
  "properties": {
    "iso:country":"AU",
    "sg:address":"189 Breen St",
    "sg:city":"Bendigo",
    "sg:classifiers":[
        {
            "category":"Shopping",
            "subcategory":"Computers & Home Electronics",
            "type":"Retail Goods"
        }
    ],
    "sg:phone":"+61 3 5444 4477",
    "sg:postcode":"3550",
    "sg:province":"VIC",
    "sg:tags":[
        "hardware",
        "equipment"
    ],
    "wof:name":"IT Warehouse",
    "wof:placetype":"venue"
},
  "geometry": {"coordinates":[144.26809692399999,-36.771270752],"type":"Point"}
}