{
  "type": "Feature",
  "properties": {
    "iso:country":"AU",
    "sg:address":"494 Crisp St",
    "sg:city":"Albury",
    "sg:classifiers":[
        {
            "category":"Health Services",
            "subcategory":"Health Practitioner",
            "type":"Services"
        }
    ],
    "sg:phone":"+61 2 6021 4269",
    "sg:postcode":"2640",
    "sg:province":"NSW",
    "sg:tags":[
        "pathologist",
        "speech"
    ],
    "wof:name":"Interact Speech Pathology Services",
    "wof:placetype":"venue"
},
  "geometry": {"coordinates":[146.92010498100001,-36.0726242065],"type":"Point"}
}