{
  "type": "Feature",
  "properties": {
    "addr:full":"175 Parkers Rd Parkdale VIC 3195",
    "addr:housenumber":"175",
    "addr:postcode":"3195",
    "addr:street":"Parkers Rd",
    "iso:country":"AU",
    "sg:address":"175 Parkers Rd",
    "sg:city":"Parkdale",
    "sg:classifiers":[
        {
            "category":"Autos & Motor Vehicles",
            "subcategory":"Boat Sales",
            "type":"Retail Goods"
        }
    ],
    "sg:phone":"+61 3 9580 1296",
    "sg:postcode":"3195",
    "sg:province":"VIC",
    "sg:tags":[
        "builder",
        "yacht",
        "repairer"
    ],
    "wof:name":"Fritz Meier",
    "wof:placetype":"venue"
},
  "geometry": {"coordinates":[145.080276489,-37.9911460876],"type":"Point"}
}