{
  "type": "Feature",
  "properties": {
    "addr:full":"PO Box 153 Darling VIC 3145",
    "addr:postcode":"3145",
    "iso:country":"AU",
    "sg:address":"PO Box 153",
    "sg:city":"Darling",
    "sg:classifiers":[
        {
            "category":"Building & Trades",
            "subcategory":"Cleaning & Sanitation",
            "type":"Services"
        }
    ],
    "sg:phone":"+61 3 8707 5444",
    "sg:postcode":"3145",
    "sg:province":"VIC",
    "sg:tags":[
        "industrial",
        "commercial",
        "contractor"
    ],
    "wof:name":"Flemingos Cleaning Services",
    "wof:placetype":"venue"
},
  "geometry": {"coordinates":[145.061645508,-37.8699684143],"type":"Point"}
}