{
  "type": "Feature",
  "properties": {
    "addr:full":"43 Formby Rd Devonport TAS 7310",
    "addr:housenumber":"43",
    "addr:postcode":"7310",
    "addr:street":"Formby Rd",
    "iso:country":"AU",
    "sg:address":"43 Formby Rd",
    "sg:city":"Devonport",
    "sg:classifiers":[
        {
            "category":"Banks & Credit Unions",
            "subcategory":"Financial Services",
            "type":"Services"
        }
    ],
    "sg:phone":"+61 3 6423 1944",
    "sg:postcode":"7310",
    "sg:province":"TAS",
    "sg:tags":[
        "planning"
    ],
    "wof:name":"TJH Financial Solutions",
    "wof:placetype":"venue"
},
  "geometry": {"coordinates":[146.361694336,-41.1840209961],"type":"Point"}
}