{
  "type": "Feature",
  "properties": {
    "iso:country":"AU",
    "sg:address":"394 South St",
    "sg:city":"Toowoomba",
    "sg:classifiers":[
        {
            "category":"Home & Garden",
            "subcategory":"Hardware",
            "type":"Retail Goods"
        }
    ],
    "sg:phone":"+61 7 4636 3448",
    "sg:postcode":"4350",
    "sg:province":"QLD",
    "sg:tags":[
        "repair",
        "tool",
        "power"
    ],
    "wof:name":"Total Tools",
    "wof:placetype":"venue"
},
  "geometry": {"coordinates":[151.91137699999999,-27.572554],"type":"Point"}
}