{
  "type": "Feature",
  "properties": {
    "iso:country":"AU",
    "sg:address":"Shop 6",
    "sg:city":"Coliseum Wlk Ballarat",
    "sg:classifiers":[
        {
            "category":"Transit Center",
            "subcategory":"Passenger",
            "type":"Transportation"
        }
    ],
    "sg:phone":"+61 3 5331 1166",
    "sg:postcode":"3350",
    "sg:province":"VIC",
    "sg:tags":[
        "retail",
        "toiletry",
        "perfume"
    ],
    "wof:name":"Perfume Xchange",
    "wof:placetype":"venue"
},
  "geometry": {"coordinates":[143.86142000000001,-37.562717],"type":"Point"}
}