{
  "type": "Feature",
  "properties": {
    "iso:country":"AU",
    "sg:address":"16 Winns Rd",
    "sg:city":"Blackwood",
    "sg:classifiers":[
        {
            "category":"Building & Trades",
            "subcategory":"Cleaning & Sanitation",
            "type":"Services"
        }
    ],
    "sg:phone":"+61 8 8370 2326",
    "sg:postcode":"5051",
    "sg:province":"SA",
    "sg:tags":[
        "window"
    ],
    "wof:name":"Patrick's Window Cleaning",
    "wof:placetype":"venue"
},
  "geometry": {"coordinates":[138.621567,-35.031338],"type":"Point"}
}