{
  "type": "Feature",
  "properties": {
    "iso:country":"AU",
    "sg:address":"Building 7, 443 West Botany St",
    "sg:city":"Rockdale",
    "sg:classifiers":[
        {
            "category":"Transit Center",
            "subcategory":"Freight",
            "type":"Transportation"
        }
    ],
    "sg:phone":"+61 2 9553 9400",
    "sg:postcode":"2216",
    "sg:province":"NSW",
    "sg:tags":[
        "agent",
        "shipping"
    ],
    "wof:name":"Airmark Consolidators",
    "wof:placetype":"venue"
},
  "geometry": {"coordinates":[151.144958,-33.960537],"type":"Point"}
}