{
  "type": "Feature",
  "properties": {
    "addr:full":"24 South St Granville NSW 2142",
    "addr:housenumber":"24",
    "addr:postcode":"2142",
    "addr:street":"South St",
    "iso:country":"AU",
    "sg:address":"24 South St",
    "sg:city":"Granville",
    "sg:classifiers":[
        {
            "category":"Food & Beverages",
            "subcategory":"Liquor & Beverages",
            "type":"Retail Goods"
        }
    ],
    "sg:phone":"+61 2 9637 1633",
    "sg:postcode":"2142",
    "sg:province":"NSW",
    "sg:tags":[
        "store"
    ],
    "wof:name":"Pubmart",
    "wof:placetype":"venue"
},
  "geometry": {"coordinates":[151.010955811,-33.8334350586],"type":"Point"}
}