{
  "type": "Feature",
  "properties": {
    "addr:full":"Shop 1, 44 Boorowa St Young NSW 2594",
    "addr:housenumber":"shop;44",
    "addr:postcode":"2594",
    "addr:street":"Boorowa St",
    "iso:country":"AU",
    "sg:address":"Shop 1, 44 Boorowa St",
    "sg:city":"Young",
    "sg:classifiers":[
        {
            "category":"Insurance",
            "subcategory":"Hazard Insurance",
            "type":"Services"
        }
    ],
    "sg:phone":"+61 2 6382 1766",
    "sg:postcode":"2594",
    "sg:province":"NSW",
    "sg:tags":[
        "fire",
        "accident",
        "marine"
    ],
    "wof:name":"Wesfarmers Federation Insurance",
    "wof:placetype":"venue"
},
  "geometry": {"coordinates":[148.28689575199999,-34.3106575012],"type":"Point"}
}