{
  "type": "Feature",
  "properties": {
    "addr:full":"192 Marius St Tamworth NSW 2340",
    "addr:housenumber":"192",
    "addr:postcode":"2340",
    "addr:street":"Marius St",
    "iso:country":"AU",
    "sg:address":"192 Marius St",
    "sg:city":"Tamworth",
    "sg:classifiers":[
        {
            "category":"Government",
            "subcategory":"Court House",
            "type":"Public Place"
        }
    ],
    "sg:phone":"+61 409 831 317",
    "sg:postcode":"2340",
    "sg:province":"NSW",
    "sg:tags":[
        "personal",
        "marriage",
        "family",
        "counselling"
    ],
    "wof:name":"AJ (Alison) Morrison",
    "wof:placetype":"venue"
},
  "geometry": {"coordinates":[150.935089111,-31.0932292938],"type":"Point"}
}