{
  "type": "Feature",
  "properties": {
    "iso:country":"AU",
    "sg:address":"Lot 263 Burton St",
    "sg:city":"Manjimup",
    "sg:classifiers":[
        {
            "category":"Manufacturing",
            "subcategory":"Metals",
            "type":"Manufacturing & Wholesale Goods"
        }
    ],
    "sg:phone":"+61 8 9777 1400",
    "sg:postcode":"6258",
    "sg:province":"WA",
    "sg:tags":[
        "steel",
        "fabricator",
        "mfrs"
    ],
    "wof:name":"Eastbrook Enterprises",
    "wof:placetype":"venue"
},
  "geometry": {"coordinates":[116.125297546,-34.254573822],"type":"Point"}
}