{
  "type": "Feature",
  "properties": {
    "addr:full":"Chancery St Lansvale NSW 2166",
    "addr:postcode":"2166",
    "addr:street":"Chancery St",
    "iso:country":"AU",
    "sg:address":"Chancery St",
    "sg:city":"Lansvale",
    "sg:classifiers":[
        {
            "category":"Education",
            "subcategory":"School",
            "type":"Public Place"
        }
    ],
    "sg:phone":"+61 2 9724 5252",
    "sg:postcode":"2166",
    "sg:province":"NSW",
    "sg:tags":[
        "state",
        "-",
        "nsw"
    ],
    "wof:name":"Lansvale Public School",
    "wof:placetype":"venue"
},
  "geometry": {"coordinates":[150.95611572300001,-33.8920898438],"type":"Point"}
}