{
  "type": "Feature",
  "properties": {
    "addr:full":"U5/ 1055 South Rd Melrose Park SA 5039",
    "addr:housenumber":"1055",
    "addr:postcode":"5039",
    "addr:street":"U5 /;South Rd",
    "iso:country":"AU",
    "sg:address":"U5/ 1055 South Rd",
    "sg:city":"Melrose Park",
    "sg:classifiers":[
        {
            "category":"Shopping",
            "subcategory":"Shoes",
            "type":"Retail Goods"
        }
    ],
    "sg:phone":"+61 8 8299 0019",
    "sg:postcode":"5039",
    "sg:province":"SA",
    "sg:tags":[
        "footwear"
    ],
    "wof:name":"Factory Direct Shoes",
    "wof:placetype":"venue"
},
  "geometry": {"coordinates":[138.574295044,-34.9877967834],"type":"Point"}
}