{
  "type": "Feature",
  "properties": {
    "addr:full":"Jones Rd Morwell VIC 3840",
    "addr:postcode":"3840",
    "addr:street":"Jones Rd",
    "iso:country":"AU",
    "sg:address":"Jones Rd",
    "sg:city":"Morwell",
    "sg:classifiers":[
        {
            "category":"Building & Trades",
            "subcategory":"Cleaning & Sanitation",
            "type":"Services"
        }
    ],
    "sg:phone":"+61 3 5133 7447",
    "sg:postcode":"3840",
    "sg:province":"VIC",
    "sg:tags":[
        "abrasive",
        "blasting"
    ],
    "wof:name":"Valicote Pty. Ltd.",
    "wof:placetype":"venue"
},
  "geometry": {"coordinates":[146.446044922,-38.2367553711],"type":"Point"}
}