{
  "type": "Feature",
  "properties": {
    "addr:full":"42 Phillip Island Rd Newhaven VIC 3925",
    "addr:housenumber":"42",
    "addr:postcode":"3925",
    "addr:street":"Phillip Island Rd",
    "iso:country":"AU",
    "sg:address":"42 Phillip Island Rd",
    "sg:city":"Newhaven",
    "sg:classifiers":[
        {
            "category":"Retail",
            "subcategory":"Veterinary Services",
            "type":"Services"
        }
    ],
    "sg:phone":"+61 3 5956 7262",
    "sg:postcode":"3925",
    "sg:province":"VIC",
    "sg:tags":[
        "surgeon"
    ],
    "wof:name":"Newhaven & Wonthaggi & Inverloch Veterinary Clinic",
    "wof:placetype":"venue"
},
  "geometry": {"coordinates":[145.35516357399999,-38.5146484375],"type":"Point"}
}