{
  "type": "Feature",
  "properties": {
    "addr:full":"219 Lochinvar Rd Upper Kedron QLD 4055",
    "addr:housenumber":"219",
    "addr:postcode":"4055",
    "addr:street":"Lochinvar Rd",
    "iso:country":"AU",
    "sg:address":"219 Lochinvar Rd",
    "sg:city":"Upper Kedron",
    "sg:classifiers":[
        {
            "category":"Manufacturing",
            "subcategory":"Metals",
            "type":"Manufacturing & Wholesale Goods"
        }
    ],
    "sg:phone":"+61 7 3289 5781",
    "sg:postcode":"4055",
    "sg:province":"QLD",
    "sg:tags":[
        "steel",
        "fabricator",
        "mfrs"
    ],
    "wof:name":"Lochnivar Steel Design",
    "wof:placetype":"venue"
},
  "geometry": {"coordinates":[152.90510559099999,-27.4066085815],"type":"Point"}
}