{
  "type": "Feature",
  "properties": {
    "iso:country":"AU",
    "sg:address":"46 Jedda Rd",
    "sg:city":"Prestons",
    "sg:classifiers":[
        {
            "category":"Professional",
            "subcategory":"Business Services",
            "type":"Services"
        }
    ],
    "sg:phone":"+61 2 8783 9788",
    "sg:postcode":"2170",
    "sg:province":"NSW",
    "sg:tags":[
        "exporter"
    ],
    "wof:name":"UKS Trading Pty Ltd",
    "wof:placetype":"venue"
},
  "geometry": {"coordinates":[150.88752746599999,-33.9348106384],"type":"Point"}
}