{
  "type": "Feature",
  "properties": {
    "addr:full":"641 High St Preston VIC 3072",
    "addr:housenumber":"641",
    "addr:postcode":"3072",
    "addr:street":"High St",
    "iso:country":"AU",
    "sg:address":"641 High St",
    "sg:city":"Preston",
    "sg:classifiers":[
        {
            "category":"Wholesale",
            "subcategory":"Furniture",
            "type":"Manufacturing & Wholesale Goods"
        }
    ],
    "sg:phone":"+61 3 9478 2873",
    "sg:postcode":"3072",
    "sg:province":"VIC",
    "sg:tags":[
        "wholesaler",
        "mfrs"
    ],
    "wof:name":"Makedonia Furniture",
    "wof:placetype":"venue"
},
  "geometry": {"coordinates":[145.00462341299999,-37.7330856323],"type":"Point"}
}