{
  "type": "Feature",
  "properties": {
    "iso:country":"AU",
    "sg:address":"50 Browns Rd",
    "sg:city":"Port Sorell",
    "sg:classifiers":[
        {
            "category":"Building & Trades",
            "subcategory":"Construction",
            "type":"Services"
        }
    ],
    "sg:phone":"+61 419 142 918",
    "sg:postcode":"7307",
    "sg:province":"TAS",
    "sg:tags":[
        "contractor"
    ],
    "wof:name":"Johnson G K & R M R Pty Ltd",
    "wof:placetype":"venue"
},
  "geometry": {"coordinates":[146.521637,-41.172604],"type":"Point"}
}