{
  "type": "Feature",
  "properties": {
    "iso:country":"AU",
    "sg:address":"Suite 4/383-385 Springvale Rd",
    "sg:city":"Springvale",
    "sg:classifiers":[
        {
            "category":"Organizations",
            "subcategory":"Non-profit Organization",
            "type":"Services"
        }
    ],
    "sg:phone":"+61 3 8558 7934",
    "sg:postcode":"3171",
    "sg:province":"VIC",
    "sg:tags":[
        "support",
        "disability",
        "organisation"
    ],
    "wof:name":"Leisure Link Up",
    "wof:placetype":"venue"
},
  "geometry": {"coordinates":[145.15203857399999,-37.9546852112],"type":"Point"}
}