{
  "type": "Feature",
  "properties": {
    "addr:full":"82 Compton Rd Underwood QLD 4119",
    "addr:housenumber":"82",
    "addr:postcode":"4119",
    "addr:street":"Compton Rd",
    "iso:country":"AU",
    "sg:address":"82 Compton Rd",
    "sg:city":"Underwood",
    "sg:classifiers":[
        {
            "category":"Building & Trades",
            "subcategory":"Construction",
            "type":"Services"
        }
    ],
    "sg:phone":"+61 7 3808 3330",
    "sg:postcode":"4119",
    "sg:province":"QLD",
    "sg:tags":[
        "contractor"
    ],
    "wof:name":"Strachan Constructions",
    "wof:placetype":"venue"
},
  "geometry": {"coordinates":[153.107879639,-27.6192588806],"type":"Point"}
}