{
  "type": "Feature",
  "properties": {
    "addr:full":"Unit 1/ 77 Ashley St Braybrook VIC 3019",
    "addr:housenumber":"77",
    "addr:postcode":"3019",
    "addr:street":"Ashley St",
    "iso:country":"AU",
    "sg:address":"Unit 1/ 77 Ashley St",
    "sg:city":"Braybrook",
    "sg:classifiers":[
        {
            "category":"Cafe",
            "type":"Food & Drink"
        }
    ],
    "sg:phone":"+61 3 9687 0877",
    "sg:postcode":"3019",
    "sg:province":"VIC",
    "wof:name":"Woodstocks Cafe",
    "wof:placetype":"venue"
},
  "geometry": {"coordinates":[144.863479614,-37.7909965515],"type":"Point"}
}