{
  "type": "Feature",
  "properties": {
    "iso:country":"AU",
    "sg:address":"88 Stanbel Rd",
    "sg:city":"Salisbury Plain",
    "sg:classifiers":[
        {
            "category":"Building & Trades",
            "subcategory":"Plumbing",
            "type":"Services"
        }
    ],
    "sg:phone":"+61 402 309 228",
    "sg:postcode":"5109",
    "sg:province":"SA",
    "sg:tags":[
        "plumber",
        "gasfitters"
    ],
    "wof:name":"AJEX Plumbing Pty Ltd",
    "wof:placetype":"venue"
},
  "geometry": {"coordinates":[138.66206359899999,-34.7709312439],"type":"Point"}
}