{
  "type": "Feature",
  "properties": {
    "iso:country":"AU",
    "sg:address":"3 Power St",
    "sg:city":"Hawthorn 3122 Hawthorn",
    "sg:classifiers":[
        {
            "category":"Professional",
            "subcategory":"Management & Consulting",
            "type":"Services"
        }
    ],
    "sg:phone":"+61 412 128 211",
    "sg:postcode":"3122",
    "sg:province":"VIC",
    "sg:tags":[
        "consultant",
        "business"
    ],
    "wof:name":"Ng Hubert",
    "wof:placetype":"venue"
},
  "geometry": {"coordinates":[145.027954102,-37.8139572144],"type":"Point"}
}