{
  "type": "Feature",
  "properties": {
    "addr:full":"579 Lygon St Carlton North VIC 3054",
    "addr:housenumber":"579",
    "addr:postcode":"3054",
    "addr:street":"Lygon St",
    "iso:country":"AU",
    "sg:address":"579 Lygon St",
    "sg:city":"Carlton North",
    "sg:classifiers":[
        {
            "category":"Shopping",
            "subcategory":"Baby Store",
            "type":"Retail Goods"
        }
    ],
    "sg:phone":"+61 3 9387 8299",
    "sg:postcode":"3054",
    "sg:province":"VIC",
    "sg:tags":[
        "children's",
        "wear"
    ],
    "wof:name":"Kids Kosmos",
    "wof:placetype":"venue"
},
  "geometry": {"coordinates":[144.96983337399999,-37.7827720642],"type":"Point"}
}