{
  "type": "Feature",
  "properties": {
    "addr:full":"Cnr King & Steel St Newcastle West NSW 2302",
    "addr:postcode":"2302",
    "addr:street":"Cnr",
    "iso:country":"AU",
    "sg:address":"Cnr King & Steel St",
    "sg:city":"Newcastle West",
    "sg:classifiers":[
        {
            "category":"Travel",
            "subcategory":"Travel Agent",
            "type":"Entertainment"
        }
    ],
    "sg:phone":"+61 2 4929 1322",
    "sg:postcode":"2302",
    "sg:province":"NSW",
    "sg:tags":[
        "consultant"
    ],
    "wof:name":"Traveland Pty Ltd",
    "wof:placetype":"venue"
},
  "geometry": {"coordinates":[151.760254,-32.92836],"type":"Point"}
}