{
  "type": "Feature",
  "properties": {
    "addr:full":"1st Floor South Newc. Rugby League Club, 46 Llewel Merewether NSW 2291",
    "addr:housenumber":"46",
    "addr:postcode":"2291",
    "addr:street":"Llewel",
    "iso:country":"AU",
    "sg:address":"1st Floor South Newc. Rugby League Club, 46 Llewel",
    "sg:city":"Merewether",
    "sg:classifiers":[
        {
            "category":"Retail",
            "subcategory":"Event Space",
            "type":"Services"
        }
    ],
    "sg:phone":"+61 2 4963 1120",
    "sg:postcode":"2291",
    "sg:province":"NSW",
    "sg:tags":[
        "venue",
        "reception",
        "wedding"
    ],
    "wof:name":"Winsor Terrace",
    "wof:placetype":"venue"
},
  "geometry": {"coordinates":[151.75135803200001,-32.9417915344],"type":"Point"}
}