{
  "type": "Feature",
  "properties": {
    "iso:country":"AU",
    "sg:address":"Cnr Marine Pde & Military Rd",
    "sg:city":"Watsons Bay",
    "sg:classifiers":[
        {
            "category":"Restaurant",
            "type":"Food & Drink"
        }
    ],
    "sg:phone":"+61 2 9337 1572",
    "sg:postcode":"2030",
    "sg:province":"NSW",
    "wof:name":"Doyles Wharf Restaurant",
    "wof:placetype":"venue"
},
  "geometry": {"coordinates":[151.28158569300001,-33.8423881531],"type":"Point"}
}