{
  "type": "Feature",
  "properties": {
    "addr:full":"Suite 7/ 470 Collins St Melbourne VIC 3000",
    "addr:housenumber":"/ 470",
    "addr:postcode":"3000",
    "addr:street":"Collins St",
    "iso:country":"AU",
    "sg:address":"Suite 7/ 470 Collins St",
    "sg:city":"Melbourne",
    "sg:classifiers":[
        {
            "category":"Banks & Credit Unions",
            "subcategory":"Financial Services",
            "type":"Services"
        }
    ],
    "sg:phone":"+61 3 9629 2777",
    "sg:postcode":"3000",
    "sg:province":"VIC",
    "sg:tags":[
        "planning"
    ],
    "wof:name":"Almond Investors Ltd",
    "wof:placetype":"venue"
},
  "geometry": {"coordinates":[144.96856689399999,-37.8133773804],"type":"Point"}
}