{
  "type": "Feature",
  "properties": {
    "iso:country":"AU",
    "sg:address":"PO Box 5267",
    "sg:city":"Alexandra Hills",
    "sg:classifiers":[
        {
            "category":"Building & Trades",
            "subcategory":"Locksmith",
            "type":"Services"
        }
    ],
    "sg:phone":"+61 7 3824 2292",
    "sg:postcode":"4161",
    "sg:province":"QLD",
    "sg:tags":[
        "lock"
    ],
    "wof:name":"Redlands Locksmiths",
    "wof:placetype":"venue"
},
  "geometry": {"coordinates":[153.22071838400001,-27.5468406677],"type":"Point"}
}