{
  "type": "Feature",
  "properties": {
    "addr:full":"38 Devon Drv Doncaster East VIC 3109",
    "addr:housenumber":"38",
    "addr:postcode":"3109",
    "addr:street":"Devon Drv",
    "iso:country":"AU",
    "sg:address":"38 Devon Drv",
    "sg:city":"Doncaster East",
    "sg:classifiers":[
        {
            "category":"Retail",
            "subcategory":"Auto Rental",
            "type":"Services"
        }
    ],
    "sg:phone":"+61 3 9842 4410",
    "sg:postcode":"3109",
    "sg:province":"VIC",
    "sg:tags":[
        "chauffeur",
        "car",
        "hire",
        "driven",
        "limousine"
    ],
    "wof:name":"Atlas Hire Cars",
    "wof:placetype":"venue"
},
  "geometry": {"coordinates":[145.15628051799999,-37.7934455872],"type":"Point"}
}