{
  "type": "Feature",
  "properties": {
    "addr:full":"200 - 208 Marius St Tamworth NSW 2340",
    "addr:housenumber":"208",
    "addr:postcode":"2340",
    "addr:street":"Marius St",
    "iso:country":"AU",
    "sg:address":"200 - 208 Marius St",
    "sg:city":"Tamworth",
    "sg:classifiers":[
        {
            "category":"Retail",
            "subcategory":"Auto Repair",
            "type":"Services"
        }
    ],
    "sg:phone":"+61 2 6766 1077",
    "sg:postcode":"2340",
    "sg:province":"NSW",
    "sg:tags":[
        "repairer",
        "motor",
        "engineer"
    ],
    "wof:name":"Volkswagen at Tamworth",
    "wof:placetype":"venue"
},
  "geometry": {"coordinates":[150.93473815900001,-31.0922489166],"type":"Point"}
}