{
  "type": "Feature",
  "properties": {
    "addr:full":"8 Bellbird St Canterbury NSW 2193",
    "addr:housenumber":"8",
    "addr:postcode":"2193",
    "addr:street":"Bellbird St",
    "iso:country":"AU",
    "sg:address":"8 Bellbird St",
    "sg:city":"Canterbury",
    "sg:classifiers":[
        {
            "category":"Retail",
            "subcategory":"Auto Repair",
            "type":"Services"
        }
    ],
    "sg:phone":"+61 2 9718 5784",
    "sg:postcode":"2193",
    "sg:province":"NSW",
    "sg:tags":[
        "electrical"
    ],
    "wof:name":"P & H Auto Electrical",
    "wof:placetype":"venue"
},
  "geometry": {"coordinates":[151.11262500000001,-33.921471],"type":"Point"}
}