{
  "type": "Feature",
  "properties": {
    "addr:full":"Church St Briagolong VIC 3860",
    "addr:postcode":"3860",
    "addr:street":"Church St",
    "iso:country":"AU",
    "sg:address":"Church St",
    "sg:city":"Briagolong",
    "sg:classifiers":[
        {
            "category":"Education",
            "subcategory":"School",
            "type":"Public Place"
        }
    ],
    "sg:phone":"+61 3 5145 5260",
    "sg:postcode":"3860",
    "sg:province":"VIC",
    "sg:tags":[
        "state",
        "except",
        "nsw"
    ],
    "wof:name":"Briagolong Primary School",
    "wof:placetype":"venue"
},
  "geometry": {"coordinates":[147.068084717,-37.8428840637],"type":"Point"}
}