{
  "type": "Feature",
  "properties": {
    "iso:country":"AU",
    "sg:address":"1 Killarney Crt",
    "sg:city":"Ormeau",
    "sg:classifiers":[
        {
            "category":"Building & Trades",
            "subcategory":"Landscaping Services",
            "type":"Services"
        }
    ],
    "sg:phone":"+61 431 600 693",
    "sg:postcode":"4208",
    "sg:province":"QLD",
    "sg:tags":[
        "designer",
        "landscape",
        "contractor"
    ],
    "wof:name":"Dun-Rite",
    "wof:placetype":"venue"
},
  "geometry": {"coordinates":[153.264770508,-27.779088974],"type":"Point"}
}