{
  "type": "Feature",
  "properties": {
    "iso:country":"AU",
    "sg:address":"Shp 4",
    "sg:city":", Springfield Medical Centre, Springfield Fai",
    "sg:classifiers":[
        {
            "category":"Health Services",
            "subcategory":"Chiropractor",
            "type":"Services"
        }
    ],
    "sg:phone":"+61 7 3818 0370",
    "sg:postcode":"4300",
    "sg:province":"QLD",
    "wof:name":"Rose Sheree",
    "wof:placetype":"venue"
},
  "geometry": {"coordinates":[152.958374023,-27.6036014557],"type":"Point"}
}