{
  "type": "Feature",
  "properties": {
    "iso:country":"AU",
    "sg:address":"RMB 1285 Yarramalong Rd",
    "sg:city":"Yarramalong",
    "sg:classifiers":[
        {
            "category":"Home & Garden",
            "subcategory":"Garden Supply",
            "type":"Retail Goods"
        }
    ],
    "sg:phone":"+61 2 4356 1119",
    "sg:postcode":"2259",
    "sg:province":"NSW",
    "sg:tags":[
        "equipment"
    ],
    "wof:name":"Kezaray Turf One Stop Turf Shop",
    "wof:placetype":"venue"
},
  "geometry": {"coordinates":[151.27992248499999,-33.2267723083],"type":"Point"}
}