{
  "type": "Feature",
  "properties": {
    "iso:country":"AU",
    "sg:address":"85 Alfred Rd",
    "sg:city":"Stockleigh",
    "sg:classifiers":[
        {
            "category":"Farming",
            "subcategory":"Farm & Veterinary Services",
            "type":"Manufacturing & Wholesale Goods"
        }
    ],
    "sg:phone":"+61 7 5546 3677",
    "sg:postcode":"4280",
    "sg:province":"QLD",
    "sg:tags":[
        "worm"
    ],
    "wof:name":"Jamieson G M",
    "wof:placetype":"venue"
},
  "geometry": {"coordinates":[153.07427999999999,-27.783091],"type":"Point"}
}