{
  "type": "Feature",
  "properties": {
    "iso:country":"AU",
    "sg:address":"9 Martin Pl",
    "sg:city":"Canning Vale",
    "sg:classifiers":[
        {
            "category":"Autos & Motor Vehicles",
            "subcategory":"Auto Supplies",
            "type":"Retail Goods"
        }
    ],
    "sg:phone":"+61 8 9456 4480",
    "sg:postcode":"6155",
    "sg:province":"WA",
    "sg:tags":[
        "wheel",
        "four",
        "equipment",
        "drive",
        "accessory"
    ],
    "wof:name":"K & N Fabrications",
    "wof:placetype":"venue"
},
  "geometry": {"coordinates":[115.916801,-32.059116],"type":"Point"}
}