{
  "type": "Feature",
  "properties": {
    "addr:full":"9 Viola St Glenella QLD 4740",
    "addr:housenumber":"9",
    "addr:postcode":"4740",
    "addr:street":"Viola St",
    "iso:country":"AU",
    "sg:address":"9 Viola St",
    "sg:city":"Glenella",
    "sg:classifiers":[
        {
            "category":"Building & Trades",
            "subcategory":"Construction",
            "type":"Services"
        }
    ],
    "sg:phone":"+61 7 4942 4350",
    "sg:postcode":"4740",
    "sg:province":"QLD",
    "sg:tags":[
        "renovation",
        "alterations",
        "extension",
        "contractor"
    ],
    "wof:name":"J One Enterprises",
    "wof:placetype":"venue"
},
  "geometry": {"coordinates":[149.14759799999999,-21.115177],"type":"Point"}
}