{
  "type": "Feature",
  "properties": {
    "addr:full":"Unit 26 Norberry Terrace 177- 199 Pacific Hwy North Sydney NSW 2060",
    "addr:housenumber":"177 199",
    "addr:postcode":"2060",
    "addr:street":"Norberry;Pacific Hwy",
    "iso:country":"AU",
    "sg:address":"Unit 26 Norberry Terrace 177- 199 Pacific Hwy",
    "sg:city":"North Sydney",
    "sg:classifiers":[
        {
            "category":"Professional",
            "subcategory":"Art Services",
            "type":"Services"
        }
    ],
    "sg:phone":"+61 2 9957 6548",
    "sg:postcode":"2060",
    "sg:province":"NSW",
    "sg:tags":[
        "graphic",
        "designer"
    ],
    "wof:name":"Design Associates",
    "wof:placetype":"venue"
},
  "geometry": {"coordinates":[151.20596313499999,-33.8367195129],"type":"Point"}
}