{
  "type": "Feature",
  "properties": {
    "addr:full":"Crosby Rd Albion QLD 4010",
    "addr:postcode":"4010",
    "addr:street":"Crosby Rd",
    "iso:country":"AU",
    "sg:address":"Crosby Rd",
    "sg:city":"Albion",
    "sg:classifiers":[
        {
            "category":"Restaurant",
            "type":"Food & Drink"
        }
    ],
    "sg:phone":"+61 7 3262 4166",
    "sg:postcode":"4010",
    "sg:province":"QLD",
    "wof:name":"Brothers Community & Sports Club (Brisbane)Limited",
    "wof:placetype":"venue"
},
  "geometry": {"coordinates":[153.042770386,-27.4322395325],"type":"Point"}
}