{
  "type": "Feature",
  "properties": {
    "iso:country":"AU",
    "sg:address":"67 St",
    "sg:city":"Paul&#039;s Tce Spring Hill",
    "sg:classifiers":[
        {
            "category":"Banks & Credit Unions",
            "subcategory":"Financial Services",
            "type":"Services"
        }
    ],
    "sg:phone":"+61 7 3831 3322",
    "sg:postcode":"4000",
    "sg:province":"QLD",
    "sg:tags":[
        "planning"
    ],
    "wof:name":"Moneo Pty Ltd",
    "wof:placetype":"venue"
},
  "geometry": {"coordinates":[153.02386474599999,-27.4625301361],"type":"Point"}
}