{
  "type": "Feature",
  "properties": {
    "addr:full":"29 Brodie St Hughenden QLD 4821",
    "addr:housenumber":"29",
    "addr:postcode":"4821",
    "addr:street":"Brodie St",
    "iso:country":"AU",
    "sg:address":"29 Brodie St",
    "sg:city":"Hughenden",
    "sg:classifiers":[
        {
            "category":"Professional",
            "subcategory":"Accounting & Tax Preparation",
            "type":"Services"
        }
    ],
    "sg:phone":"+61 7 4741 1100",
    "sg:postcode":"4821",
    "sg:province":"QLD",
    "sg:tags":[
        "consultant",
        "taxation"
    ],
    "wof:name":"TCM Partners",
    "wof:placetype":"venue"
},
  "geometry": {"coordinates":[144.195587158,-20.8416461945],"type":"Point"}
}