{
  "type": "Feature",
  "properties": {
    "addr:full":"81 Mayne St Invermay TAS 7248",
    "addr:housenumber":"81",
    "addr:postcode":"7248",
    "addr:street":"Mayne St",
    "iso:country":"AU",
    "sg:address":"81 Mayne St",
    "sg:city":"Invermay",
    "sg:classifiers":[
        {
            "category":"Professional",
            "subcategory":"Engineering",
            "type":"Services"
        }
    ],
    "sg:phone":"+61 3 6326 6277",
    "sg:postcode":"7248",
    "sg:province":"TAS",
    "sg:tags":[
        "manufacturing",
        "engineer"
    ],
    "wof:name":"Precision Engineering & Manufacturing",
    "wof:placetype":"venue"
},
  "geometry": {"coordinates":[147.126785278,-41.4223060608],"type":"Point"}
}