{
  "type": "Feature",
  "properties": {
    "addr:full":"PO Box 121a Porepunkah VIC 3740",
    "addr:postcode":"3740",
    "iso:country":"AU",
    "sg:address":"PO Box 121a",
    "sg:city":"Porepunkah",
    "sg:classifiers":[
        {
            "category":"Travel",
            "subcategory":"Travel Agent",
            "type":"Entertainment"
        }
    ],
    "sg:phone":"+61 3 5756 2624",
    "sg:postcode":"3740",
    "sg:province":"VIC",
    "sg:tags":[
        "tour",
        "holiday",
        "adventure"
    ],
    "wof:name":"Aus Global Soft Adventure",
    "wof:placetype":"venue"
},
  "geometry": {"coordinates":[146.90991199999999,-36.696911],"type":"Point"}
}