{
  "type": "Feature",
  "properties": {
    "iso:country":"AU",
    "sg:address":"Cnr Collingwood St",
    "sg:city":"& Latrobe Tce Paddington",
    "sg:classifiers":[
        {
            "category":"Shopping",
            "subcategory":"Antiques",
            "type":"Retail Goods"
        }
    ],
    "sg:phone":"+61 7 3368 1030",
    "sg:postcode":"4064",
    "sg:province":"QLD",
    "wof:name":"Goldtask Pty Ltd",
    "wof:placetype":"venue"
},
  "geometry": {"coordinates":[152.994415283,-27.4584503174],"type":"Point"}
}