{
  "type": "Feature",
  "properties": {
    "addr:full":"87 Edwards St Ayr QLD 4807",
    "addr:housenumber":"87",
    "addr:postcode":"4807",
    "addr:street":"Edwards St",
    "iso:country":"AU",
    "sg:address":"87 Edwards St",
    "sg:city":"Ayr",
    "sg:classifiers":[
        {
            "category":"Utilities",
            "type":"Services"
        }
    ],
    "sg:phone":"+61 7 4783 5590",
    "sg:postcode":"4807",
    "sg:province":"QLD",
    "sg:tags":[
        "refrigeration",
        "industrial",
        "commercial",
        "retail"
    ],
    "wof:name":"Burdekin Air Conditioning & Electrical Pty Ltd",
    "wof:placetype":"venue"
},
  "geometry": {"coordinates":[147.40000915499999,-19.5691204071],"type":"Point"}
}