{
  "type": "Feature",
  "properties": {
    "addr:full":"1 Rose Crt Turners Beach TAS 7315",
    "addr:housenumber":"1",
    "addr:postcode":"7315",
    "addr:street":"Rose Crt",
    "iso:country":"AU",
    "sg:address":"1 Rose Crt",
    "sg:city":"Turners Beach",
    "sg:classifiers":[
        {
            "category":"Building & Trades",
            "subcategory":"Construction",
            "type":"Services"
        }
    ],
    "sg:phone":"+61 409 973 197",
    "sg:postcode":"7315",
    "sg:province":"TAS",
    "sg:tags":[
        "contractor"
    ],
    "wof:name":"D & M Knowles",
    "wof:placetype":"venue"
},
  "geometry": {"coordinates":[146.22483825699999,-41.1661186218],"type":"Point"}
}