{
  "type": "Feature",
  "properties": {
    "iso:country":"AU",
    "sg:address":"Shp7/ 24 Bashford St",
    "sg:city":"Jurien Bay",
    "sg:classifiers":[
        {
            "category":"Fast Food",
            "type":"Food & Drink"
        }
    ],
    "sg:phone":"+61 8 9652 1343",
    "sg:postcode":"6516",
    "sg:province":"WA",
    "sg:tags":[
        "away",
        "take"
    ],
    "wof:name":"Jurien Bay Pizza's",
    "wof:placetype":"venue"
},
  "geometry": {"coordinates":[115.041748,-30.303564],"type":"Point"}
}