{
  "type": "Feature",
  "properties": {
    "iso:country":"AU",
    "sg:address":"3 Masonite Rd",
    "sg:city":"Heatherbrae",
    "sg:classifiers":[
        {
            "category":"Building & Trades",
            "subcategory":"Equipment Rental",
            "type":"Services"
        }
    ],
    "sg:phone":"+61 2 4987 4495",
    "sg:postcode":"2324",
    "sg:province":"NSW",
    "sg:tags":[
        "renting",
        "trailer"
    ],
    "wof:name":"U-Haul Trailer Rentals",
    "wof:placetype":"venue"
},
  "geometry": {"coordinates":[151.73965454099999,-32.78332901],"type":"Point"}
}