{
  "type": "Feature",
  "properties": {
    "addr:full":"PO Box 5045 Murray Bridge South SA 5253",
    "addr:postcode":"5253",
    "iso:country":"AU",
    "sg:address":"PO Box 5045",
    "sg:city":"Murray Bridge South",
    "sg:classifiers":[
        {
            "category":"Farming",
            "subcategory":"Farm & Veterinary Services",
            "type":"Manufacturing & Wholesale Goods"
        }
    ],
    "sg:phone":"+61 8 8532 5724",
    "sg:postcode":"5253",
    "sg:province":"SA",
    "sg:tags":[
        "shearing",
        "contractor"
    ],
    "wof:name":"Millhouse Shearing Pty Ltd",
    "wof:placetype":"venue"
},
  "geometry": {"coordinates":[139.286575317,-35.1513404846],"type":"Point"}
}