{
  "type": "Feature",
  "properties": {
    "addr:full":"502 Bridge Rd Richmond VIC 3121",
    "addr:housenumber":"502",
    "addr:postcode":"3121",
    "addr:street":"Bridge Rd",
    "iso:country":"AU",
    "sg:address":"502 Bridge Rd",
    "sg:city":"Richmond",
    "sg:classifiers":[
        {
            "category":"Personal",
            "subcategory":"Beauty Salon",
            "type":"Services"
        }
    ],
    "sg:phone":"+61 3 9428 3835",
    "sg:postcode":"3121",
    "sg:province":"VIC",
    "sg:tags":[
        "hairdresser"
    ],
    "wof:name":"Desassi Hair & Co",
    "wof:placetype":"venue"
},
  "geometry": {"coordinates":[145.00860595699999,-37.8196487427],"type":"Point"}
}