{
  "type": "Feature",
  "properties": {
    "addr:full":"585 Tapleys Hill Rd Fulham SA 5024",
    "addr:housenumber":"585",
    "addr:postcode":"5024",
    "addr:street":"Tapleys Hill Rd",
    "iso:country":"AU",
    "sg:address":"585 Tapleys Hill Rd",
    "sg:city":"Fulham",
    "sg:classifiers":[
        {
            "category":"Professional",
            "subcategory":"Accounting & Tax Preparation",
            "type":"Services"
        }
    ],
    "sg:phone":"+61 8 8355 5233",
    "sg:postcode":"5024",
    "sg:province":"SA",
    "sg:tags":[
        "accountant",
        "auditor"
    ],
    "wof:name":"Sunter Management Services",
    "wof:placetype":"venue"
},
  "geometry": {"coordinates":[138.517868042,-34.927822113],"type":"Point"}
}