{
  "type": "Feature",
  "properties": {
    "addr:full":"58 Gahans Rd Bundaberg QLD 4670",
    "addr:housenumber":"58",
    "addr:postcode":"4670",
    "addr:street":"Gahans Rd",
    "iso:country":"AU",
    "sg:address":"58 Gahans Rd",
    "sg:city":"Bundaberg",
    "sg:classifiers":[
        {
            "category":"Building & Trades",
            "subcategory":"Plumbing",
            "type":"Services"
        }
    ],
    "sg:phone":"+61 7 4151 2796",
    "sg:postcode":"4670",
    "sg:province":"QLD",
    "sg:tags":[
        "plumber",
        "gasfitters"
    ],
    "wof:name":"Skytec Enterprises Pty Ltd",
    "wof:placetype":"venue"
},
  "geometry": {"coordinates":[152.385162353,-24.8461151123],"type":"Point"}
}