{
  "type": "Feature",
  "properties": {
    "addr:full":"60 Hunt Rd Beverley WA 6304",
    "addr:housenumber":"60",
    "addr:postcode":"6304",
    "addr:street":"Hunt Rd",
    "iso:country":"AU",
    "sg:address":"60 Hunt Rd",
    "sg:city":"Beverley",
    "sg:classifiers":[
        {
            "category":"Commercial Area",
            "type":"Public Place"
        }
    ],
    "sg:phone":"+61 417 953 968",
    "sg:postcode":"6304",
    "sg:province":"WA",
    "sg:tags":[
        "heavy",
        "carrier"
    ],
    "wof:name":"C & B Southern Run Transport",
    "wof:placetype":"venue"
},
  "geometry": {"coordinates":[116.92328643800001,-32.1094207764],"type":"Point"}
}