{
  "type": "Feature",
  "properties": {
    "iso:country":"AU",
    "sg:address":"2/ 82 Pohlman St",
    "sg:city":"Southport",
    "sg:classifiers":[
        {
            "category":"Personal",
            "subcategory":"Beauty Salon",
            "type":"Services"
        }
    ],
    "sg:phone":"+61 7 5528 1988",
    "sg:postcode":"4215",
    "sg:province":"QLD",
    "sg:website":"http://www.wakeupbeautiful.com.au",
    "wof:name":"Wake Up Beautiful",
    "wof:placetype":"venue"
},
  "geometry": {"coordinates":[153.40284729000001,-27.9724845886],"type":"Point"}
}