{
  "type": "Feature",
  "properties": {
    "addr:full":"13 Laurina Ave Thornton NSW 2322",
    "addr:housenumber":"13",
    "addr:postcode":"2322",
    "addr:street":"Laurina Ave",
    "iso:country":"AU",
    "sg:address":"13 Laurina Ave",
    "sg:city":"Thornton",
    "sg:classifiers":[
        {
            "category":"Government",
            "subcategory":"Court House",
            "type":"Public Place"
        }
    ],
    "sg:phone":"+61 419 278 525",
    "sg:postcode":"2322",
    "sg:province":"NSW",
    "sg:tags":[
        "personal",
        "marriage",
        "family",
        "counselling"
    ],
    "wof:name":"Holistic Counsellor & Life Coach",
    "wof:placetype":"venue"
},
  "geometry": {"coordinates":[151.652069092,-32.7819480896],"type":"Point"}
}