{
  "type": "Feature",
  "properties": {
    "iso:country":"AU",
    "sg:address":"Lot 2 Princess Hwy",
    "sg:city":"East Mt Gambier",
    "sg:classifiers":[
        {
            "category":"Retail",
            "subcategory":"Storage",
            "type":"Services"
        }
    ],
    "sg:phone":"+61 1300 662 292",
    "sg:postcode":"5290",
    "sg:province":"SA",
    "wof:name":"Store House Self Storage",
    "wof:placetype":"venue"
},
  "geometry": {"coordinates":[140.78268399999999,-37.823311],"type":"Point"}
}