{
  "type": "Feature",
  "properties": {
    "addr:full":"Shop 12 Croydon Shopping Cntr Croydon VIC 3136",
    "addr:housenumber":"shop 12",
    "addr:postcode":"3136",
    "addr:street":"Croydon Shopping Cntr",
    "iso:country":"AU",
    "sg:address":"Shop 12",
    "sg:city":"Croydon Shopping Cntr Croydon",
    "sg:classifiers":[
        {
            "category":"Shopping",
            "subcategory":"Clothing, Apparel, & Fashions",
            "type":"Retail Goods"
        }
    ],
    "sg:phone":"+61 3 9724 9357",
    "sg:postcode":"3136",
    "sg:province":"VIC",
    "sg:tags":[
        "lady",
        "wear"
    ],
    "wof:name":"New Attitude Fashion",
    "wof:placetype":"venue"
},
  "geometry": {"coordinates":[145.28192138700001,-37.7931594849],"type":"Point"}
}