{
  "type": "Feature",
  "properties": {
    "addr:full":"3 Gerwaine Crt Old Beach TAS 7017",
    "addr:housenumber":"3",
    "addr:postcode":"7017",
    "addr:street":"Gerwaine Crt Old Beach",
    "iso:country":"AU",
    "sg:address":"3 Gerwaine Crt",
    "sg:city":"Old Beach",
    "sg:classifiers":[
        {
            "category":"Building & Trades",
            "subcategory":"Landscaping Services",
            "type":"Services"
        }
    ],
    "sg:phone":"+61 3 6249 7519",
    "sg:postcode":"7017",
    "sg:province":"TAS",
    "sg:tags":[
        "gardener"
    ],
    "wof:name":"Harrys Complete Gardening Care",
    "wof:placetype":"venue"
},
  "geometry": {"coordinates":[147.279373169,-42.7762794495],"type":"Point"}
}