{
  "type": "Feature",
  "properties": {
    "addr:full":"36 George St Thebarton SA 5031",
    "addr:housenumber":"36",
    "addr:postcode":"5031",
    "addr:street":"George St",
    "iso:country":"AU",
    "sg:address":"36 George St",
    "sg:city":"Thebarton",
    "sg:classifiers":[
        {
            "category":"Professional",
            "subcategory":"Art Services",
            "type":"Services"
        }
    ],
    "sg:phone":"+61 8 8152 0594",
    "sg:postcode":"5031",
    "sg:province":"SA",
    "sg:tags":[
        "sculptor"
    ],
    "wof:name":"Rosella Tony",
    "wof:placetype":"venue"
},
  "geometry": {"coordinates":[138.57612609899999,-34.9185791016],"type":"Point"}
}