{
  "type": "Feature",
  "properties": {
    "addr:full":"Unit 5/ 54 Crocker Drv Malaga WA 6090",
    "addr:housenumber":"54",
    "addr:postcode":"6090",
    "addr:street":"Crocker Drv",
    "iso:country":"AU",
    "sg:address":"Unit 5/ 54 Crocker Drv",
    "sg:city":"Malaga",
    "sg:classifiers":[
        {
            "category":"Education",
            "subcategory":"Junior College",
            "type":"Public Place"
        }
    ],
    "sg:phone":"+61 8 9248 8160",
    "sg:postcode":"6090",
    "sg:province":"WA",
    "sg:tags":[
        "wholesaler",
        "school",
        "mfrs",
        "uniform"
    ],
    "wof:name":"Excel Sportswear",
    "wof:placetype":"venue"
},
  "geometry": {"coordinates":[115.88233184800001,-31.8540325165],"type":"Point"}
}