{
  "type": "Feature",
  "properties": {
    "iso:country":"AU",
    "sg:address":"Shop 7 Fairways Crs",
    "sg:city":"Shearwater",
    "sg:classifiers":[
        {
            "category":"Manufacturing",
            "subcategory":"Food",
            "type":"Manufacturing & Wholesale Goods"
        }
    ],
    "sg:phone":"+61 3 6428 6134",
    "sg:postcode":"7307",
    "sg:province":"TAS",
    "sg:tags":[
        "function",
        "catering"
    ],
    "wof:name":"Freers Restaurant",
    "wof:placetype":"venue"
},
  "geometry": {"coordinates":[146.534409,-41.157669],"type":"Point"}
}