{
  "type": "Feature",
  "properties": {
    "iso:country":"AU",
    "sg:address":"43 Wray Crs",
    "sg:city":"Mt Evelyn",
    "sg:classifiers":[
        {
            "category":"Banks & Credit Unions",
            "subcategory":"Investment Brokerage",
            "type":"Services"
        }
    ],
    "sg:phone":"+61 3 9736 4631",
    "sg:postcode":"3796",
    "sg:province":"VIC",
    "sg:tags":[
        "finance",
        "broker"
    ],
    "wof:name":"Busi-Plan Pty Ltd",
    "wof:placetype":"venue"
},
  "geometry": {"coordinates":[145.38900756800001,-37.7864303589],"type":"Point"}
}