{
  "type": "Feature",
  "properties": {
    "addr:full":"PO Box 2097 Eaglemont VIC 3084",
    "addr:postcode":"3084",
    "iso:country":"AU",
    "sg:address":"PO Box 2097",
    "sg:city":"Eaglemont",
    "sg:classifiers":[
        {
            "category":"Professional",
            "subcategory":"Business Services",
            "type":"Services"
        }
    ],
    "sg:phone":"+61 412 675 106",
    "sg:postcode":"3084",
    "sg:province":"VIC",
    "sg:tags":[
        "management",
        "event"
    ],
    "wof:name":"Coffee Crew Australia",
    "wof:placetype":"venue"
},
  "geometry": {"coordinates":[145.067596436,-37.7642211914],"type":"Point"}
}