{
  "type": "Feature",
  "properties": {
    "iso:country":"AU",
    "sg:address":"18 Church St",
    "sg:city":"Penola",
    "sg:classifiers":[
        {
            "category":"Travel",
            "subcategory":"Hostel",
            "type":"Entertainment"
        }
    ],
    "sg:phone":"+61 8 8737 0700",
    "sg:postcode":"5277",
    "sg:province":"SA",
    "sg:tags":[
        "home"
    ],
    "wof:name":"Pinchunga (Hostel)",
    "wof:placetype":"venue"
},
  "geometry": {"coordinates":[140.837494,-37.382141],"type":"Point"}
}