{
  "type": "Feature",
  "properties": {
    "addr:full":"19 Brunker Rd Broadmeadow NSW 2292",
    "addr:housenumber":"19",
    "addr:postcode":"2292",
    "addr:street":"Brunker Rd",
    "iso:country":"AU",
    "sg:address":"19 Brunker Rd",
    "sg:city":"Broadmeadow",
    "sg:classifiers":[
        {
            "category":"Education",
            "subcategory":"Special Training",
            "type":"Public Place"
        }
    ],
    "sg:phone":"+61 2 4962 4900",
    "sg:postcode":"2292",
    "sg:province":"NSW",
    "sg:tags":[
        "development"
    ],
    "wof:name":"Master Builders Newcastle",
    "wof:placetype":"venue"
},
  "geometry": {"coordinates":[151.73614501899999,-32.9257583618],"type":"Point"}
}