{
  "type": "Feature",
  "properties": {
    "iso:country":"AU",
    "sg:address":"59 Breed St",
    "sg:city":"Traralgon",
    "sg:classifiers":[
        {
            "category":"Organizations",
            "subcategory":"Non-profit Organization",
            "type":"Services"
        }
    ],
    "sg:phone":"+61 1300 303 770",
    "sg:postcode":"3844",
    "sg:province":"VIC",
    "sg:tags":[
        "support",
        "disability",
        "organisation"
    ],
    "wof:name":"Australian Home Care",
    "wof:placetype":"venue"
},
  "geometry": {"coordinates":[146.53346252399999,-38.1936569214],"type":"Point"}
}