{
  "type": "Feature",
  "properties": {
    "addr:full":"Unit 1/ 6 Tombo St Capalaba QLD 4157",
    "addr:postcode":"4157",
    "addr:street":"Tombo St",
    "iso:country":"AU",
    "sg:address":"Unit 1/ 6 Tombo St",
    "sg:city":"Capalaba",
    "sg:classifiers":[
        {
            "category":"Professional",
            "subcategory":"Printing & Photocopies",
            "type":"Services"
        }
    ],
    "sg:phone":"+61 7 3245 7007",
    "sg:postcode":"4157",
    "sg:province":"QLD",
    "sg:tags":[
        "screen",
        "printer"
    ],
    "wof:name":"Marlin Graphics Screen Printing Specialists",
    "wof:placetype":"venue"
},
  "geometry": {"coordinates":[153.20021057100001,-27.5219860077],"type":"Point"}
}