{
  "type": "Feature",
  "properties": {
    "iso:country":"AU",
    "sg:address":"4 Westside Ave",
    "sg:city":"Port Melbourne",
    "sg:classifiers":[
        {
            "category":"Autos & Motor Vehicles",
            "subcategory":"Automobile Sales",
            "type":"Retail Goods"
        }
    ],
    "sg:phone":"+61 1300 792 327",
    "sg:postcode":"3207",
    "sg:province":"VIC",
    "sg:tags":[
        "car",
        "used"
    ],
    "wof:name":"Aussie Car Sales",
    "wof:placetype":"venue"
},
  "geometry": {"coordinates":[144.91799900000001,-37.822548],"type":"Point"}
}