{
  "type": "Feature",
  "properties": {
    "addr:full":"88 Wells St Southbank VIC 3006",
    "addr:housenumber":"88",
    "addr:postcode":"3006",
    "addr:street":"Wells St",
    "iso:country":"AU",
    "sg:address":"88 Wells St",
    "sg:city":"Southbank",
    "sg:classifiers":[
        {
            "category":"Utilities",
            "subcategory":"Telephone",
            "type":"Services"
        }
    ],
    "sg:phone":"+61 3 8810 2222",
    "sg:postcode":"3006",
    "sg:province":"VIC",
    "sg:tags":[
        "accessory"
    ],
    "wof:name":"Blue Communications",
    "wof:placetype":"venue"
},
  "geometry": {"coordinates":[144.96841430699999,-37.8279571533],"type":"Point"}
}