{
  "type": "Feature",
  "properties": {
    "addr:full":"15 Ridge Crs Mt Dandenong VIC 3767",
    "addr:housenumber":"15",
    "addr:postcode":"3767",
    "addr:street":"Ridge Crs Mt",
    "iso:country":"AU",
    "sg:address":"15 Ridge Crs",
    "sg:city":"Mt Dandenong",
    "sg:classifiers":[
        {
            "category":"Health Services",
            "subcategory":"Health Practitioner",
            "type":"Services"
        }
    ],
    "sg:phone":"+61 3 9751 2199",
    "sg:postcode":"3767",
    "sg:province":"VIC",
    "sg:tags":[
        "reiki"
    ],
    "wof:name":"Sherwood Reiki Seminars",
    "wof:placetype":"venue"
},
  "geometry": {"coordinates":[145.36080932600001,-37.8456306458],"type":"Point"}
}