{
  "type": "Feature",
  "properties": {
    "addr:full":"Unit 1/ 67-71 Jersey St Hornsby NSW 2077",
    "addr:housenumber":"/ 67-71",
    "addr:postcode":"2077",
    "addr:street":"Jersey St",
    "iso:country":"AU",
    "sg:address":"Unit 1/ 67-71 Jersey St",
    "sg:city":"Hornsby",
    "sg:classifiers":[
        {
            "category":"Shopping",
            "subcategory":"Bicycles & Sporting Goods",
            "type":"Retail Goods"
        }
    ],
    "sg:phone":"+61 2 9476 1088",
    "sg:postcode":"2077",
    "sg:province":"NSW",
    "sg:tags":[
        "chemical",
        "equipment",
        "pool",
        "swimming"
    ],
    "sg:website":"http://www.hornsbypoolcentre.com.au",
    "wof:name":"Hornsby Pool Centre",
    "wof:placetype":"venue"
},
  "geometry": {"coordinates":[151.10960388199999,-33.6965751648],"type":"Point"}
}