{
  "type": "Feature",
  "properties": {
    "addr:full":"Princes St Port Fairy VIC 3284",
    "addr:postcode":"3284",
    "addr:street":"Princes St",
    "iso:country":"AU",
    "sg:address":"Princes St",
    "sg:city":"Port Fairy",
    "sg:classifiers":[
        {
            "category":"Government",
            "subcategory":"Department Of Motor Vehicles",
            "type":"Public Place"
        }
    ],
    "sg:phone":"+61 3 5568 2600",
    "sg:postcode":"3284",
    "sg:province":"VIC",
    "sg:tags":[
        "organisation",
        "local"
    ],
    "wof:name":"Moyne Shire Council",
    "wof:placetype":"venue"
},
  "geometry": {"coordinates":[142.23806762699999,-38.3853988647],"type":"Point"}
}