{
  "type": "Feature",
  "properties": {
    "iso:country":"AU",
    "sg:address":"25 Harcombe Drv",
    "sg:city":"Sunbury",
    "sg:classifiers":[
        {
            "category":"Donuts",
            "subcategory":"None",
            "type":"Food & Drink"
        }
    ],
    "sg:phone":"+61 3 9744 7779",
    "sg:postcode":"3429",
    "sg:province":"VIC",
    "sg:tags":[
        "die",
        "engraver",
        "sinker"
    ],
    "wof:name":"Jan's Engraving",
    "wof:placetype":"venue"
},
  "geometry": {"coordinates":[144.69508361800001,-37.5741348267],"type":"Point"}
}