{
  "type": "Feature",
  "properties": {
    "addr:full":"5 Bradley St Goulburn NSW 2580",
    "addr:housenumber":"5",
    "addr:postcode":"2580",
    "addr:street":"Bradley St",
    "iso:country":"AU",
    "sg:address":"5 Bradley St",
    "sg:city":"Goulburn",
    "sg:classifiers":[
        {
            "category":"Health Services",
            "subcategory":"Health Practitioner",
            "type":"Services"
        }
    ],
    "sg:phone":"+61 2 4822 2122",
    "sg:postcode":"2580",
    "sg:province":"NSW",
    "sg:tags":[
        "naturopath"
    ],
    "wof:name":"Reardon D J",
    "wof:placetype":"venue"
},
  "geometry": {"coordinates":[149.72505188,-34.7508087158],"type":"Point"}
}