{
  "type": "Feature",
  "properties": {
    "addr:full":"34 Raymond Ave Matraville NSW 2036",
    "addr:housenumber":"34",
    "addr:postcode":"2036",
    "addr:street":"Raymond Ave",
    "iso:country":"AU",
    "sg:address":"34 Raymond Ave",
    "sg:city":"Matraville",
    "sg:classifiers":[
        {
            "category":"Professional",
            "type":"Services"
        }
    ],
    "sg:phone":"+61 2 9666 6363",
    "sg:postcode":"2036",
    "sg:province":"NSW",
    "sg:tags":[
        "spray",
        "painting"
    ],
    "wof:name":"Franklin Smash Repairs",
    "wof:placetype":"venue"
},
  "geometry": {"coordinates":[151.22317504899999,-33.9617958069],"type":"Point"}
}