{
  "type": "Feature",
  "properties": {
    "iso:country":"AU",
    "sg:address":"6 Braidwood St",
    "sg:city":"South Strathfield",
    "sg:classifiers":[
        {
            "category":"Food & Beverages",
            "subcategory":"Bakery",
            "type":"Retail Goods"
        }
    ],
    "sg:phone":"+61 2 9742 5866",
    "sg:postcode":"2136",
    "sg:province":"NSW",
    "sg:tags":[
        "baker"
    ],
    "wof:name":"Etna Bakery Pty Ltd",
    "wof:placetype":"venue"
},
  "geometry": {"coordinates":[151.070846558,-33.8868026733],"type":"Point"}
}