{
  "type": "Feature",
  "properties": {
    "addr:full":"7 Teutonia Crt High Wycombe WA 6057",
    "addr:housenumber":"7",
    "addr:postcode":"6057",
    "addr:street":"Teutonia Crt",
    "iso:country":"AU",
    "sg:address":"7 Teutonia Crt",
    "sg:city":"High Wycombe",
    "sg:classifiers":[
        {
            "category":"Retail",
            "subcategory":"Auto Rental",
            "type":"Services"
        }
    ],
    "sg:phone":"+61 8 9454 4586",
    "sg:postcode":"6057",
    "sg:province":"WA",
    "sg:tags":[
        "chauffeur",
        "car",
        "hire",
        "driven",
        "limousine"
    ],
    "sg:website":"http://www.cadillac10.com.au/",
    "wof:name":"Cadillac Limousine Company",
    "wof:placetype":"venue"
},
  "geometry": {"coordinates":[116.011543274,-31.9497184753],"type":"Point"}
}