{
  "type": "Feature",
  "properties": {
    "addr:full":"Rear 16 Boronia St South Wentworthville NSW 2145",
    "addr:housenumber":"16",
    "addr:postcode":"2145",
    "addr:street":"Boronia St",
    "iso:country":"AU",
    "sg:address":"Rear 16 Boronia St",
    "sg:city":"South Wentworthville",
    "sg:classifiers":[
        {
            "category":"Retail",
            "subcategory":"Repair Shop",
            "type":"Services"
        }
    ],
    "sg:phone":"+61 2 9636 5666",
    "sg:postcode":"2145",
    "sg:province":"NSW",
    "sg:tags":[
        "upholsterer"
    ],
    "wof:name":"A J Classic Upholstery",
    "wof:placetype":"venue"
},
  "geometry": {"coordinates":[150.96815490700001,-33.8188362122],"type":"Point"}
}