{
  "type": "Feature",
  "properties": {
    "addr:full":"31 Whitsunday Drv Currumbin Waters QLD 4223",
    "addr:housenumber":"31",
    "addr:postcode":"4223",
    "addr:street":"Whitsunday Drv",
    "iso:country":"AU",
    "sg:address":"31 Whitsunday Drv",
    "sg:city":"Currumbin Waters",
    "sg:classifiers":[
        {
            "category":"Building & Trades",
            "subcategory":"Construction",
            "type":"Services"
        }
    ],
    "sg:phone":"+61 410 586 264",
    "sg:postcode":"4223",
    "sg:province":"QLD",
    "sg:tags":[
        "contractor"
    ],
    "wof:name":"Glosko J & D A",
    "wof:placetype":"venue"
},
  "geometry": {"coordinates":[153.46473693900001,-28.1565361023],"type":"Point"}
}