{
  "type": "Feature",
  "properties": {
    "addr:full":"4 Wirilda Crt Capalaba QLD 4157",
    "addr:housenumber":"4",
    "addr:postcode":"4157",
    "addr:street":"Wirilda Crt",
    "iso:country":"AU",
    "sg:address":"4 Wirilda Crt",
    "sg:city":"Capalaba",
    "sg:classifiers":[
        {
            "category":"Building & Trades",
            "subcategory":"Construction",
            "type":"Services"
        }
    ],
    "sg:phone":"+61 7 3206 0226",
    "sg:postcode":"4157",
    "sg:province":"QLD",
    "sg:tags":[
        "earth",
        "excavating",
        "moving",
        "contractor"
    ],
    "wof:name":"D & M Plant Hire",
    "wof:placetype":"venue"
},
  "geometry": {"coordinates":[153.22235107399999,-27.5658817291],"type":"Point"}
}