{
  "type": "Feature",
  "properties": {
    "addr:full":"3/ 130 Victoria St Taree NSW 2430",
    "addr:housenumber":"/ 130",
    "addr:postcode":"2430",
    "addr:street":"Victoria St",
    "iso:country":"AU",
    "sg:address":"3/ 130 Victoria St",
    "sg:city":"Taree",
    "sg:classifiers":[
        {
            "category":"Real Estate",
            "subcategory":"Real Estate Services",
            "type":"Services"
        }
    ],
    "sg:phone":"+61 2 6551 3355",
    "sg:postcode":"2430",
    "sg:province":"NSW",
    "sg:tags":[
        "valuer"
    ],
    "wof:name":"Tim Haffner & Associates PTY LTD",
    "wof:placetype":"venue"
},
  "geometry": {"coordinates":[152.46258499999999,-31.912638],"type":"Point"}
}