{
  "type": "Feature",
  "properties": {
    "iso:country":"AU",
    "sg:address":"1 Pintu Drv",
    "sg:city":"Tanah Merah",
    "sg:classifiers":[
        {
            "category":"Home & Garden",
            "subcategory":"Garden Supply",
            "type":"Retail Goods"
        }
    ],
    "sg:phone":"+61 7 3801 2833",
    "sg:postcode":"4128",
    "sg:province":"QLD",
    "sg:tags":[
        "statuary",
        "fountains",
        "sundial"
    ],
    "wof:name":"Old World",
    "wof:placetype":"venue"
},
  "geometry": {"coordinates":[153.172485352,-27.6654472351],"type":"Point"}
}