{
  "type": "Feature",
  "properties": {
    "addr:full":"73 Main St Gembrook VIC 3783",
    "addr:housenumber":"73",
    "addr:postcode":"3783",
    "addr:street":"Main St",
    "iso:country":"AU",
    "sg:address":"73 Main St",
    "sg:city":"Gembrook",
    "sg:classifiers":[
        {
            "category":"Travel",
            "subcategory":"Hotels & Motels",
            "type":"Entertainment"
        }
    ],
    "sg:phone":"+61 3 5968 1220",
    "sg:postcode":"3783",
    "sg:province":"VIC",
    "sg:tags":[
        "accommodation"
    ],
    "wof:name":"Ranges Hotel",
    "wof:placetype":"venue"
},
  "geometry": {"coordinates":[145.548935,-37.952366],"type":"Point"}
}