{
  "type": "Feature",
  "properties": {
    "addr:full":"5 Sidney Nolan St Lanyon Marketplace Cmplx Conder ACT 2906",
    "addr:housenumber":"5",
    "addr:postcode":"2906",
    "addr:street":"Sidney Nolan St",
    "iso:country":"AU",
    "sg:address":"5 Sidney Nolan St Lanyon Marketplace Cmplx",
    "sg:city":"Conder",
    "sg:classifiers":[
        {
            "category":"Communications",
            "subcategory":"Film & Video Production",
            "type":"Services"
        }
    ],
    "sg:phone":"+61 2 6284 8884",
    "sg:postcode":"2906",
    "sg:province":"ACT",
    "sg:tags":[
        "dvd",
        "library"
    ],
    "wof:name":"Video Ezy",
    "wof:placetype":"venue"
},
  "geometry": {"coordinates":[149.092727661,-35.4572944641],"type":"Point"}
}