{
  "type": "Feature",
  "properties": {
    "iso:country":"AU",
    "sg:address":"95 Broadway St",
    "sg:city":"Cobram",
    "sg:classifiers":[
        {
            "category":"Social Services",
            "subcategory":"Adult Care",
            "type":"Services"
        }
    ],
    "sg:phone":"+61 3 5872 1555",
    "sg:postcode":"3644",
    "sg:province":"VIC",
    "sg:tags":[
        "towing"
    ],
    "wof:name":"Cobram Panel Works",
    "wof:placetype":"venue"
},
  "geometry": {"coordinates":[145.64109802199999,-35.9181213379],"type":"Point"}
}