{
  "type": "Feature",
  "properties": {
    "iso:country":"AU",
    "sg:address":"Shop 20 63 Nicholson St",
    "sg:city":"Footscray",
    "sg:classifiers":[
        {
            "category":"Personal",
            "subcategory":"Beauty Salon",
            "type":"Services"
        }
    ],
    "sg:phone":"+61 3 9689 4211",
    "sg:postcode":"3011",
    "sg:province":"VIC",
    "sg:tags":[
        "hairdresser"
    ],
    "wof:name":"Lan Lien Hairdressing Salon",
    "wof:placetype":"venue"
},
  "geometry": {"coordinates":[144.899932861,-37.7986183167],"type":"Point"}
}