{
  "type": "Feature",
  "properties": {
    "addr:full":"44 Maple St Maleny QLD 4552",
    "addr:housenumber":"44",
    "addr:postcode":"4552",
    "addr:street":"Maple St",
    "iso:country":"AU",
    "sg:address":"44 Maple St",
    "sg:city":"Maleny",
    "sg:classifiers":[
        {
            "category":"Professional",
            "subcategory":"Accounting & Tax Preparation",
            "type":"Services"
        }
    ],
    "sg:phone":"+61 7 5494 2315",
    "sg:postcode":"4552",
    "sg:province":"QLD",
    "sg:tags":[
        "accountant",
        "auditor"
    ],
    "wof:name":"Neale K C",
    "wof:placetype":"venue"
},
  "geometry": {"coordinates":[152.84925842300001,-26.7579689026],"type":"Point"}
}