{
  "type": "Feature",
  "properties": {
    "addr:full":"970 Wisemans Ferry Rd Somersby NSW 2250",
    "addr:postcode":"970;2250",
    "addr:street":"Wisemans Ferry Rd",
    "iso:country":"AU",
    "sg:address":"970 Wisemans Ferry Rd",
    "sg:city":"Somersby",
    "sg:classifiers":[
        {
            "category":"Professional",
            "subcategory":"Business Services",
            "type":"Services"
        }
    ],
    "sg:phone":"+61 2 4372 1536",
    "sg:postcode":"2250",
    "sg:province":"NSW",
    "sg:tags":[
        "exporter"
    ],
    "wof:name":"Glen Ayr Kiwi Fruit",
    "wof:placetype":"venue"
},
  "geometry": {"coordinates":[151.288619995,-33.3488388062],"type":"Point"}
}