{
  "type": "Feature",
  "properties": {
    "addr:full":"57 Newland St Riverside TAS 7250",
    "addr:housenumber":"57",
    "addr:postcode":"7250",
    "addr:street":"Newland St",
    "iso:country":"AU",
    "sg:address":"57 Newland St",
    "sg:city":"Riverside",
    "sg:classifiers":[
        {
            "category":"Building & Trades",
            "subcategory":"Construction",
            "type":"Services"
        }
    ],
    "sg:phone":"+61 419 581 819",
    "sg:postcode":"7250",
    "sg:province":"TAS",
    "sg:tags":[
        "joiner",
        "carpenter"
    ],
    "wof:name":"Allen G.B.",
    "wof:placetype":"venue"
},
  "geometry": {"coordinates":[147.11126709000001,-41.4253807068],"type":"Point"}
}