{
  "type": "Feature",
  "properties": {
    "addr:full":"Great Eastern Hwy Belmont WA 6104",
    "addr:postcode":"6104",
    "addr:street":"Eastern Hwy",
    "iso:country":"AU",
    "sg:address":"Great Eastern Hwy",
    "sg:city":"Belmont",
    "sg:classifiers":[
        {
            "category":"Shopping",
            "subcategory":"Computers & Home Electronics",
            "type":"Retail Goods"
        }
    ],
    "sg:phone":"+61 417 175 409",
    "sg:postcode":"6104",
    "sg:province":"WA",
    "sg:tags":[
        "small",
        "equipment",
        "business"
    ],
    "wof:name":"At Home Computer Shop East",
    "wof:placetype":"venue"
},
  "geometry": {"coordinates":[115.93086242699999,-31.938703537],"type":"Point"}
}