{
  "type": "Feature",
  "properties": {
    "addr:full":"24 Murphy St Wangaratta VIC 3677",
    "addr:housenumber":"24",
    "addr:postcode":"3677",
    "addr:street":"Murphy St",
    "iso:country":"AU",
    "sg:address":"24 Murphy St",
    "sg:city":"Wangaratta",
    "sg:classifiers":[
        {
            "category":"Health Services",
            "subcategory":"Dentist",
            "type":"Services"
        }
    ],
    "sg:phone":"+61 3 5721 2086",
    "sg:postcode":"3677",
    "sg:province":"VIC",
    "sg:tags":[
        "state",
        "orthodontist",
        "qld",
        "exc"
    ],
    "wof:name":"Wangaratta Orthodontics",
    "wof:placetype":"venue"
},
  "geometry": {"coordinates":[146.32542419399999,-36.3563766479],"type":"Point"}
}