{
  "type": "Feature",
  "properties": {
    "addr:full":"58 Waltham Crt Bonogin QLD 4213",
    "addr:housenumber":"58",
    "addr:postcode":"4213",
    "addr:street":"Waltham Crt",
    "iso:country":"AU",
    "sg:address":"58 Waltham Crt",
    "sg:city":"Bonogin",
    "sg:classifiers":[
        {
            "category":"Manufacturing",
            "subcategory":"Tools & Machinery",
            "type":"Manufacturing & Wholesale Goods"
        }
    ],
    "sg:phone":"+61 7 5502 2338",
    "sg:postcode":"4213",
    "sg:province":"QLD",
    "sg:tags":[
        "wholesaler",
        "lingerie",
        "mfrs",
        "sleepwear"
    ],
    "wof:name":"Electric Blue Fashion Pty Ltd",
    "wof:placetype":"venue"
},
  "geometry": {"coordinates":[153.32687377900001,-28.1514205933],"type":"Point"}
}