{
  "type": "Feature",
  "properties": {
    "addr:full":"9 Peter John St Raymond Terrace NSW 2324",
    "addr:housenumber":"9",
    "addr:postcode":"2324",
    "addr:street":"Peter John St",
    "iso:country":"AU",
    "sg:address":"9 Peter John St",
    "sg:city":"Raymond Terrace",
    "sg:classifiers":[
        {
            "category":"Utilities",
            "subcategory":"Refuse",
            "type":"Services"
        }
    ],
    "sg:phone":"+61 418 684 304",
    "sg:postcode":"2324",
    "sg:province":"NSW",
    "sg:tags":[
        "remover",
        "rubbish"
    ],
    "wof:name":"Quick-Cat Earthmoving Pty Ltd",
    "wof:placetype":"venue"
},
  "geometry": {"coordinates":[151.74494934099999,-32.7568054199],"type":"Point"}
}