{
  "type": "Feature",
  "properties": {
    "iso:country":"AU",
    "sg:address":"Unit 3 11 Romford Rd",
    "sg:city":"Kings Park",
    "sg:classifiers":[
        {
            "category":"Shopping",
            "subcategory":"Computers & Home Electronics",
            "type":"Retail Goods"
        }
    ],
    "sg:phone":"+61 2 9672 4548",
    "sg:postcode":"2148",
    "sg:province":"NSW",
    "sg:tags":[
        "equipment",
        "supply"
    ],
    "wof:name":"Wiretek Australia Pty Ltd",
    "wof:placetype":"venue"
},
  "geometry": {"coordinates":[150.91494750999999,-33.7491264343],"type":"Point"}
}