{
  "type": "Feature",
  "properties": {
    "iso:country":"AU",
    "sg:address":"High St",
    "sg:city":"Wallumbilla",
    "sg:classifiers":[
        {
            "category":"Farming",
            "subcategory":"Farm",
            "type":"Manufacturing & Wholesale Goods"
        }
    ],
    "sg:phone":"+61 7 4623 4102",
    "sg:postcode":"4428",
    "sg:province":"QLD",
    "sg:tags":[
        "farmer"
    ],
    "wof:name":"Nimmo P V",
    "wof:placetype":"venue"
},
  "geometry": {"coordinates":[149.18731689399999,-26.5836200714],"type":"Point"}
}