{
  "type": "Feature",
  "properties": {
    "addr:full":"81 Kurrajong Ave Leeton NSW 2705",
    "addr:housenumber":"81",
    "addr:postcode":"2705",
    "addr:street":"Kurrajong Ave",
    "iso:country":"AU",
    "sg:address":"81 Kurrajong Ave",
    "sg:city":"Leeton",
    "sg:classifiers":[
        {
            "category":"Health Services",
            "subcategory":"Doctor",
            "type":"Services"
        }
    ],
    "sg:phone":"+61 2 6953 4333",
    "sg:postcode":"2705",
    "sg:province":"NSW",
    "sg:tags":[
        "medical",
        "practitioner"
    ],
    "wof:name":"Byrne R Dr",
    "wof:placetype":"venue"
},
  "geometry": {"coordinates":[146.41029357900001,-34.5554847717],"type":"Point"}
}