{
  "type": "Feature",
  "properties": {
    "addr:full":"1 Greenstone Crt Thomastown VIC 3074",
    "addr:housenumber":"1",
    "addr:postcode":"3074",
    "addr:street":"Greenstone Crt",
    "iso:country":"AU",
    "sg:address":"1 Greenstone Crt",
    "sg:city":"Thomastown",
    "sg:classifiers":[
        {
            "category":"Professional",
            "subcategory":"Computer Services",
            "type":"Services"
        }
    ],
    "sg:phone":"+61 409 251 368",
    "sg:postcode":"3074",
    "sg:province":"VIC",
    "sg:tags":[
        "consultant",
        "system"
    ],
    "wof:name":"VCS Computer Services",
    "wof:placetype":"venue"
},
  "geometry": {"coordinates":[144.99122619600001,-37.6816253662],"type":"Point"}
}