{
  "type": "Feature",
  "properties": {
    "addr:full":"Shop 3, 110 Main Rd Moonah TAS 7009",
    "addr:housenumber":"shop 3 110",
    "addr:postcode":"7009",
    "addr:street":"Main Rd",
    "iso:country":"AU",
    "sg:address":"Shop 3, 110 Main Rd",
    "sg:city":"Moonah",
    "sg:classifiers":[
        {
            "category":"Fast Food",
            "type":"Food & Drink"
        }
    ],
    "sg:phone":"+61 3 6272 7088",
    "sg:postcode":"7009",
    "sg:province":"TAS",
    "sg:tags":[
        "away",
        "take"
    ],
    "wof:name":"Dave's Noodles",
    "wof:placetype":"venue"
},
  "geometry": {"coordinates":[147.29425048799999,-42.8460884094],"type":"Point"}
}