{
  "type": "Feature",
  "properties": {
    "addr:full":"127 Whites Rd Salisbury North SA 5108",
    "addr:housenumber":"127",
    "addr:postcode":"5108",
    "addr:street":"Whites Rd",
    "iso:country":"AU",
    "sg:address":"127 Whites Rd",
    "sg:city":"Salisbury North",
    "sg:classifiers":[
        {
            "category":"Health Services",
            "subcategory":"Doctor",
            "type":"Services"
        }
    ],
    "sg:phone":"+61 8 8258 8988",
    "sg:postcode":"5108",
    "sg:province":"SA",
    "sg:tags":[
        "medical",
        "practitioner"
    ],
    "wof:name":"Groves B G Dr",
    "wof:placetype":"venue"
},
  "geometry": {"coordinates":[138.62464904800001,-34.745426178],"type":"Point"}
}