{
  "type": "Feature",
  "properties": {
    "iso:country":"AU",
    "sg:address":"7 Star Ave",
    "sg:city":"North Plympton",
    "sg:classifiers":[
        {
            "category":"Professional",
            "subcategory":"Engineering",
            "type":"Services"
        }
    ],
    "sg:phone":"+61 8 8294 3899",
    "sg:postcode":"5037",
    "sg:province":"SA",
    "sg:tags":[
        "engineer"
    ],
    "wof:name":"Saxon Engineering Pty Ltd",
    "wof:placetype":"venue"
},
  "geometry": {"coordinates":[138.540084839,-34.9596824646],"type":"Point"}
}