{
  "type": "Feature",
  "properties": {
    "addr:full":"Macathur Square, Gilchrist Drv Ambarvale NSW 2560",
    "addr:postcode":"2560",
    "addr:street":"Gilchrist Drv",
    "iso:country":"AU",
    "sg:address":"Macathur Square, Gilchrist Drv",
    "sg:city":"Ambarvale",
    "sg:classifiers":[
        {
            "category":"Shopping",
            "type":"Retail Goods"
        }
    ],
    "sg:phone":"+61 2 4626 3537",
    "sg:postcode":"2560",
    "sg:province":"NSW",
    "sg:tags":[
        "repair",
        "travel"
    ],
    "wof:name":"Strandbags",
    "wof:placetype":"venue"
},
  "geometry": {"coordinates":[150.847579956,-34.0611419678],"type":"Point"}
}