{
  "type": "Feature",
  "properties": {
    "iso:country":"AU",
    "sg:address":"65 Louisa St",
    "sg:city":"Gympie",
    "sg:classifiers":[
        {
            "category":"Home & Garden",
            "subcategory":"Building Materials",
            "type":"Retail Goods"
        }
    ],
    "sg:phone":"+61 7 5482 7371",
    "sg:postcode":"4570",
    "sg:province":"QLD",
    "sg:tags":[
        "lawn",
        "cutting",
        "maintenance"
    ],
    "wof:name":"Areandem Cleaning & Maintenance",
    "wof:placetype":"venue"
},
  "geometry": {"coordinates":[152.66224670400001,-26.1834220886],"type":"Point"}
}