{
  "type": "Feature",
  "properties": {
    "addr:full":"54 Thomas Drv Chevron Island QLD 4217",
    "addr:housenumber":"54",
    "addr:postcode":"4217",
    "addr:street":"Thomas Drv Chevron",
    "iso:country":"AU",
    "sg:address":"54 Thomas Drv",
    "sg:city":"Chevron Island",
    "sg:classifiers":[
        {
            "category":"Cafe",
            "type":"Food & Drink"
        }
    ],
    "sg:phone":"+61 7 5538 4850",
    "sg:postcode":"4217",
    "sg:province":"QLD",
    "wof:name":"Rendezvous On Chevron",
    "wof:placetype":"venue"
},
  "geometry": {"coordinates":[153.41920471200001,-27.9981155396],"type":"Point"}
}