{
  "type": "Feature",
  "properties": {
    "addr:full":"5 Ironstone Rd Epsom VIC 3551",
    "addr:housenumber":"5",
    "addr:postcode":"3551",
    "addr:street":"Ironstone Rd",
    "iso:country":"AU",
    "sg:address":"5 Ironstone Rd",
    "sg:city":"Epsom",
    "sg:classifiers":[
        {
            "category":"Freight",
            "type":"Transportation"
        }
    ],
    "sg:phone":"+61 3 5448 4044",
    "sg:postcode":"3551",
    "sg:province":"VIC",
    "sg:tags":[
        "light",
        "carrier"
    ],
    "wof:name":"Myers Light Freight",
    "wof:placetype":"venue"
},
  "geometry": {"coordinates":[144.324020386,-36.6966781616],"type":"Point"}
}