{
  "type": "Feature",
  "properties": {
    "addr:full":"41 Second Ave St Peters SA 5069",
    "addr:housenumber":"41",
    "addr:postcode":"5069",
    "addr:street":"Second Ave",
    "iso:country":"AU",
    "sg:address":"41 Second Ave St",
    "sg:city":"Peters",
    "sg:classifiers":[
        {
            "category":"Bars & Pubs",
            "subcategory":"Oxygen Bar",
            "type":"Food & Drink"
        }
    ],
    "sg:phone":"+61 408 816 437",
    "sg:postcode":"5069",
    "sg:province":"SA",
    "sg:tags":[
        "equipment",
        "pump",
        "concrete"
    ],
    "wof:name":"Festival State Concrete Pumping",
    "wof:placetype":"venue"
},
  "geometry": {"coordinates":[138.626052856,-34.9079284668],"type":"Point"}
}