{
  "type": "Feature",
  "properties": {
    "iso:country":"AU",
    "sg:address":"37 Bullara St",
    "sg:city":"Pambula",
    "sg:classifiers":[
        {
            "category":"Manufacturing",
            "subcategory":"Metals",
            "type":"Manufacturing & Wholesale Goods"
        }
    ],
    "sg:phone":"+61 2 6494 3055",
    "sg:postcode":"2549",
    "sg:province":"NSW",
    "sg:tags":[
        "fabricator",
        "aluminium"
    ],
    "wof:name":"Malibu",
    "wof:placetype":"venue"
},
  "geometry": {"coordinates":[149.870040894,-36.9315834045],"type":"Point"}
}