{
  "type": "Feature",
  "properties": {
    "addr:full":"Unit 6, 5 Dowsett St Geelong South VIC 3220",
    "addr:housenumber":"5",
    "addr:postcode":"3220",
    "addr:street":"Dowsett St",
    "iso:country":"AU",
    "sg:address":"Unit 6, 5 Dowsett St",
    "sg:city":"Geelong South",
    "sg:classifiers":[
        {
            "category":"Wholesale",
            "subcategory":"Machinery & Supplies",
            "type":"Manufacturing & Wholesale Goods"
        }
    ],
    "sg:phone":"+61 3 5223 1811",
    "sg:postcode":"3220",
    "sg:province":"VIC",
    "sg:tags":[
        "equipment",
        "laboratory"
    ],
    "wof:name":"Civilab Australia",
    "wof:placetype":"venue"
},
  "geometry": {"coordinates":[144.36769100000001,-38.167297],"type":"Point"}
}