{
  "type": "Feature",
  "properties": {
    "addr:full":"569 Karrinyup Rd Stirling WA 6021",
    "addr:housenumber":"569",
    "addr:postcode":"6021",
    "addr:street":"Karrinyup Rd",
    "iso:country":"AU",
    "sg:address":"569 Karrinyup Rd",
    "sg:city":"Stirling",
    "sg:classifiers":[
        {
            "category":"Personal",
            "subcategory":"Massage",
            "type":"Services"
        }
    ],
    "sg:phone":"+61 8 9446 8322",
    "sg:postcode":"6021",
    "sg:province":"WA",
    "sg:tags":[
        "therapy"
    ],
    "wof:name":"Balinski Craig",
    "wof:placetype":"venue"
},
  "geometry": {"coordinates":[115.809791565,-31.8861865997],"type":"Point"}
}