{
  "type": "Feature",
  "properties": {
    "addr:full":"234 Pier St Perth WA 6000",
    "addr:housenumber":"234",
    "addr:postcode":"6000",
    "addr:street":"Pier St",
    "iso:country":"AU",
    "sg:address":"234 Pier St",
    "sg:city":"Perth",
    "sg:classifiers":[
        {
            "category":"Wholesale",
            "subcategory":"Medical Equipment & Supplies",
            "type":"Manufacturing & Wholesale Goods"
        }
    ],
    "sg:phone":"+61 8 9328 1011",
    "sg:postcode":"6000",
    "sg:province":"WA",
    "sg:tags":[
        "aid",
        "care",
        "health",
        "home"
    ],
    "wof:name":"Nordic Healthcare",
    "wof:placetype":"venue"
},
  "geometry": {"coordinates":[115.86551666299999,-31.9500141144],"type":"Point"}
}