{
  "type": "Feature",
  "properties": {
    "addr:full":"180 Hewins Rd Brombin NSW 2446",
    "addr:housenumber":"180",
    "addr:postcode":"2446",
    "addr:street":"Hewins Rd",
    "iso:country":"AU",
    "sg:address":"180 Hewins Rd",
    "sg:city":"Brombin",
    "sg:classifiers":[
        {
            "category":"Building & Trades",
            "subcategory":"Construction",
            "type":"Services"
        }
    ],
    "sg:phone":"+61 2 6585 6451",
    "sg:postcode":"2446",
    "sg:province":"NSW",
    "sg:tags":[
        "earth",
        "excavating",
        "moving",
        "contractor"
    ],
    "wof:name":"Anytime Anywhere Bobcat & Excavator Hire",
    "wof:placetype":"venue"
},
  "geometry": {"coordinates":[152.64335600000001,-31.470207],"type":"Point"}
}