{
  "type": "Feature",
  "properties": {
    "addr:full":"33 Mary St George Town TAS 7253",
    "addr:housenumber":"33",
    "addr:postcode":"7253",
    "addr:street":"Mary St",
    "iso:country":"AU",
    "sg:address":"33 Mary St",
    "sg:city":"George Town",
    "sg:classifiers":[
        {
            "category":"Utilities",
            "subcategory":"Electric",
            "type":"Services"
        }
    ],
    "sg:phone":"+61 3 6382 1850",
    "sg:postcode":"7253",
    "sg:province":"TAS",
    "sg:tags":[
        "electrical",
        "contractor"
    ],
    "wof:name":"Marron Pat",
    "wof:placetype":"venue"
},
  "geometry": {"coordinates":[146.82695007300001,-41.1159362793],"type":"Point"}
}