{
  "type": "Feature",
  "properties": {
    "iso:country":"AU",
    "sg:address":"134 Military Rd",
    "sg:city":"Guildford",
    "sg:classifiers":[
        {
            "category":"Building & Trades",
            "subcategory":"Construction",
            "type":"Services"
        }
    ],
    "sg:phone":"+61 2 9681 1785",
    "sg:postcode":"2161",
    "sg:province":"NSW",
    "sg:tags":[
        "polishing",
        "sanding",
        "floor"
    ],
    "wof:name":"Holroyd Parquetry Flooring",
    "wof:placetype":"venue"
},
  "geometry": {"coordinates":[150.98373413100001,-33.8547172546],"type":"Point"}
}