{
  "type": "Feature",
  "properties": {
    "addr:full":"3 Howard St Inverell NSW 2360",
    "addr:housenumber":"3",
    "addr:postcode":"2360",
    "addr:street":"Howard St",
    "iso:country":"AU",
    "sg:address":"3 Howard St",
    "sg:city":"Inverell",
    "sg:classifiers":[
        {
            "category":"Building & Trades",
            "subcategory":"Construction",
            "type":"Services"
        }
    ],
    "sg:phone":"+61 2 6722 1053",
    "sg:postcode":"2360",
    "sg:province":"NSW",
    "sg:tags":[
        "ceiling"
    ],
    "wof:name":"ADK Plastering",
    "wof:placetype":"venue"
},
  "geometry": {"coordinates":[151.11260986299999,-29.7694683075],"type":"Point"}
}