{
  "type": "Feature",
  "properties": {
    "iso:country":"AU",
    "sg:address":"5 Breckell Crt",
    "sg:city":"Lamberts Beach",
    "sg:classifiers":[
        {
            "category":"Building & Trades",
            "subcategory":"Construction",
            "type":"Services"
        }
    ],
    "sg:phone":"+61 417 712 953",
    "sg:postcode":"4740",
    "sg:province":"QLD",
    "sg:tags":[
        "fencing",
        "contractor"
    ],
    "wof:name":"L & L Fencing",
    "wof:placetype":"venue"
},
  "geometry": {"coordinates":[149.224304,-21.071848],"type":"Point"}
}