{
  "type": "Feature",
  "properties": {
    "addr:full":"The Niche, 11 Aberdare Rd Nedlands WA 6009",
    "addr:housenumber":"11",
    "addr:postcode":"6009",
    "addr:street":"Aberdare Rd",
    "iso:country":"AU",
    "sg:address":"The Niche, 11 Aberdare Rd",
    "sg:city":"Nedlands",
    "sg:classifiers":[
        {
            "category":"Organizations",
            "subcategory":"Non-profit Organization",
            "type":"Services"
        }
    ],
    "sg:phone":"+61 8 9346 7373",
    "sg:postcode":"6009",
    "sg:province":"WA",
    "sg:tags":[
        "support",
        "disability",
        "organisation"
    ],
    "wof:name":"Parkinson's Western Australia Inc",
    "wof:placetype":"venue"
},
  "geometry": {"coordinates":[115.81697800000001,-31.96452],"type":"Point"}
}