{
  "type": "Feature",
  "properties": {
    "iso:country":"AU",
    "sg:address":"Suite 5/ 34 Talbot Ave",
    "sg:city":"Como",
    "sg:classifiers":[
        {
            "category":"Health Services",
            "subcategory":"Health Practitioner",
            "type":"Services"
        }
    ],
    "sg:phone":"+61 8 9450 1990",
    "sg:postcode":"6152",
    "sg:province":"WA",
    "sg:tags":[
        "physiotherapist"
    ],
    "wof:name":"O&#039;Leary Kim",
    "wof:placetype":"venue"
},
  "geometry": {"coordinates":[115.866676,-32.002716],"type":"Point"}
}