{
  "type": "Feature",
  "properties": {
    "addr:full":"265 - 277-277 Liverpool St Darlinghurst NSW 2010",
    "addr:housenumber":"265 277-277",
    "addr:postcode":"2010",
    "addr:street":"Liverpool St",
    "iso:country":"AU",
    "sg:address":"265 - 277-277 Liverpool St",
    "sg:city":"Darlinghurst",
    "sg:classifiers":[
        {
            "category":"Banks & Credit Unions",
            "subcategory":"Financial Services",
            "type":"Services"
        }
    ],
    "sg:phone":"+61 2 9368 1522",
    "sg:postcode":"2010",
    "sg:province":"NSW",
    "sg:tags":[
        "loan",
        "finance",
        "mortgage"
    ],
    "wof:name":"Deposit Access Pty Ltd",
    "wof:placetype":"venue"
},
  "geometry": {"coordinates":[151.216140747,-33.87758255],"type":"Point"}
}