{
  "type": "Feature",
  "properties": {
    "iso:country":"AU",
    "sg:address":"Unit 11 89- 99 Lower West Burleigh Rd",
    "sg:city":"Burleigh Heads",
    "sg:classifiers":[
        {
            "category":"Retail",
            "subcategory":"Auto Repair",
            "type":"Services"
        }
    ],
    "sg:phone":"+61 7 5535 3871",
    "sg:postcode":"4220",
    "sg:province":"QLD",
    "sg:tags":[
        "repairer",
        "motor",
        "engineer"
    ],
    "sg:website":"http://www.goldcoastbmw.com",
    "wof:name":"Eurotec Auto Services",
    "wof:placetype":"venue"
},
  "geometry": {"coordinates":[153.44325256400001,-28.0932178497],"type":"Point"}
}