{
  "type": "Feature",
  "properties": {
    "addr:full":"Shop 13, Argonaut Shopping Cnt 250 Kingston Rd Slacks Creek QLD 4127",
    "addr:housenumber":"shop 13;250",
    "addr:postcode":"4127",
    "addr:street":"Argonaut Shopping Cnt;Kingston Rd",
    "iso:country":"AU",
    "sg:address":"Shop 13, Argonaut Shopping Cnt 250 Kingston Rd",
    "sg:city":"Slacks Creek",
    "sg:classifiers":[
        {
            "category":"Banks & Credit Unions",
            "subcategory":"Investment Brokerage",
            "type":"Services"
        }
    ],
    "sg:phone":"+61 7 3208 5766",
    "sg:postcode":"4127",
    "sg:province":"QLD",
    "sg:tags":[
        "repairer",
        "typewriter"
    ],
    "wof:name":"Gibson Business Equipment",
    "wof:placetype":"venue"
},
  "geometry": {"coordinates":[153.118865967,-27.6399688721],"type":"Point"}
}