{
  "type": "Feature",
  "properties": {
    "addr:full":"3 Scarborough St Monterey NSW 2217",
    "addr:housenumber":"3",
    "addr:postcode":"2217",
    "addr:street":"Scarborough St",
    "iso:country":"AU",
    "sg:address":"3 Scarborough St",
    "sg:city":"Monterey",
    "sg:classifiers":[
        {
            "category":"Real Estate",
            "subcategory":"Architect",
            "type":"Services"
        }
    ],
    "sg:phone":"+61 2 9553 1875",
    "sg:postcode":"2217",
    "sg:province":"NSW",
    "wof:name":"Studio Miniflex",
    "wof:placetype":"venue"
},
  "geometry": {"coordinates":[151.15008499999999,-33.975231],"type":"Point"}
}