{
  "type": "Feature",
  "properties": {
    "addr:full":"1541 Botany Rd Botany NSW 2019",
    "addr:housenumber":"1541",
    "addr:postcode":"2019",
    "addr:street":"Botany Rd",
    "iso:country":"AU",
    "sg:address":"1541 Botany Rd",
    "sg:city":"Botany",
    "sg:classifiers":[
        {
            "category":"Personal",
            "subcategory":"Shoe Repair & Shine",
            "type":"Services"
        }
    ],
    "sg:phone":"+61 2 9316 8218",
    "sg:postcode":"2019",
    "sg:province":"NSW",
    "sg:tags":[
        "reconditioning",
        "business",
        "furniture"
    ],
    "wof:name":"D.I.A. Furniture (Australia) Pty Ltd / D.I.A Office Seating Pty Ltd",
    "wof:placetype":"venue"
},
  "geometry": {"coordinates":[151.198455811,-33.9509277344],"type":"Point"}
}