{
  "type": "Feature",
  "properties": {
    "addr:full":"290 South Rd Hilton SA 5033",
    "addr:housenumber":"290",
    "addr:postcode":"5033",
    "addr:street":"South Rd",
    "iso:country":"AU",
    "sg:address":"290 South Rd",
    "sg:city":"Hilton",
    "sg:classifiers":[
        {
            "category":"Professional",
            "type":"Services"
        }
    ],
    "sg:phone":"+61 8 8354 8222",
    "sg:postcode":"5033",
    "sg:province":"SA",
    "sg:tags":[
        "industrial",
        "commercial",
        "catering"
    ],
    "wof:name":"Spotless",
    "wof:placetype":"venue"
},
  "geometry": {"coordinates":[138.57012939399999,-34.9324798584],"type":"Point"}
}