{
  "type": "Feature",
  "properties": {
    "addr:full":"Unit 4 183 Bank St East Victoria Park WA 6101",
    "addr:housenumber":"183",
    "addr:postcode":"6101",
    "addr:street":"Bank St",
    "iso:country":"AU",
    "sg:address":"Unit 4 183 Bank St",
    "sg:city":"East Victoria Park",
    "sg:classifiers":[
        {
            "category":"Retail",
            "subcategory":"Auto Repair",
            "type":"Services"
        }
    ],
    "sg:phone":"+61 8 9362 1656",
    "sg:postcode":"6101",
    "sg:province":"WA",
    "sg:tags":[
        "repairer",
        "motor",
        "engineer"
    ],
    "wof:name":"Oakley Engineering",
    "wof:placetype":"venue"
},
  "geometry": {"coordinates":[115.916870117,-31.9894943237],"type":"Point"}
}