{
  "type": "Feature",
  "properties": {
    "addr:full":"Shp2/ 12 Dangar Rd Brooklyn NSW 2083",
    "addr:housenumber":"12",
    "addr:postcode":"2083",
    "addr:street":"Dangar Rd",
    "iso:country":"AU",
    "sg:address":"Shp2/ 12 Dangar Rd",
    "sg:city":"Brooklyn",
    "sg:classifiers":[
        {
            "category":"Cafe",
            "type":"Food & Drink"
        }
    ],
    "sg:phone":"+61 2 9985 8818",
    "sg:postcode":"2083",
    "sg:province":"NSW",
    "wof:name":"All In One Cafe",
    "wof:placetype":"venue"
},
  "geometry": {"coordinates":[151.22763061500001,-33.5469856262],"type":"Point"}
}