{
  "type": "Feature",
  "properties": {
    "addr:full":"81 Goldsmith St South Mackay QLD 4740",
    "addr:housenumber":"81",
    "addr:postcode":"4740",
    "addr:street":"Goldsmith St",
    "iso:country":"AU",
    "sg:address":"81 Goldsmith St",
    "sg:city":"South Mackay",
    "sg:classifiers":[
        {
            "category":"Personal",
            "subcategory":"Beauty Salon",
            "type":"Services"
        }
    ],
    "sg:phone":"+61 7 4953 4566",
    "sg:postcode":"4740",
    "sg:province":"QLD",
    "sg:tags":[
        "hairdresser"
    ],
    "wof:name":"Scissor Snip-Its",
    "wof:placetype":"venue"
},
  "geometry": {"coordinates":[149.191956,-21.161324],"type":"Point"}
}