{
  "type": "Feature",
  "properties": {
    "iso:country":"AU",
    "sg:address":"Cnr Acheron Ave & North Rd",
    "sg:city":"Reservoir",
    "sg:classifiers":[
        {
            "category":"Education",
            "subcategory":"Music School",
            "type":"Public Place"
        }
    ],
    "sg:phone":"+61 3 9029 6879",
    "sg:postcode":"3073",
    "sg:province":"VIC",
    "sg:tags":[
        "teacher"
    ],
    "wof:name":"Music Works-Let's Sing",
    "wof:placetype":"venue"
},
  "geometry": {"coordinates":[145.01756286599999,-37.7200431824],"type":"Point"}
}