{
  "type": "Feature",
  "properties": {
    "addr:full":"Myall St Shpng Cntr 272 Myall St Dubbo NSW 2830",
    "addr:housenumber":"272",
    "addr:postcode":"2830",
    "addr:street":"Myall St",
    "iso:country":"AU",
    "sg:address":"Myall St Shpng Cntr 272 Myall St",
    "sg:city":"Dubbo",
    "sg:classifiers":[
        {
            "category":"Retail",
            "subcategory":"Laundry & Dry Cleaning",
            "type":"Services"
        }
    ],
    "sg:phone":"+61 2 6884 8855",
    "sg:postcode":"2830",
    "sg:province":"NSW",
    "wof:name":"White & Bright Laundrette",
    "wof:placetype":"venue"
},
  "geometry": {"coordinates":[148.630401611,-32.2425880432],"type":"Point"}
}