{
  "type": "Feature",
  "properties": {
    "addr:full":"2c Acacia St Oatley NSW 2223",
    "addr:housenumber":"2c",
    "addr:postcode":"2223",
    "addr:street":"Acacia St",
    "iso:country":"AU",
    "sg:address":"2c Acacia St",
    "sg:city":"Oatley",
    "sg:classifiers":[
        {
            "category":"Education",
            "subcategory":"Music School",
            "type":"Public Place"
        }
    ],
    "sg:phone":"+61 2 9585 2408",
    "sg:postcode":"2223",
    "sg:province":"NSW",
    "sg:tags":[
        "teacher"
    ],
    "wof:name":"St George Players",
    "wof:placetype":"venue"
},
  "geometry": {"coordinates":[151.072463989,-33.975479126],"type":"Point"}
}