{
  "type": "Feature",
  "properties": {
    "iso:country":"AU",
    "sg:address":"132- 134 Fosters Rd",
    "sg:city":"Oakden",
    "sg:classifiers":[
        {
            "category":"Health Services",
            "subcategory":"Doctor",
            "type":"Services"
        }
    ],
    "sg:phone":"+61 8 8266 7788",
    "sg:postcode":"5086",
    "sg:province":"SA",
    "sg:tags":[
        "medical",
        "practitioner"
    ],
    "wof:name":"White Paul Dr",
    "wof:placetype":"venue"
},
  "geometry": {"coordinates":[138.63639831500001,-34.8588981628],"type":"Point"}
}