{
  "type": "Feature",
  "properties": {
    "addr:full":"Suite 3/ 48 Raglan St Manly NSW 2095",
    "addr:housenumber":"48",
    "addr:postcode":"2095",
    "addr:street":"Raglan St",
    "iso:country":"AU",
    "sg:address":"Suite 3/ 48 Raglan St",
    "sg:city":"Manly",
    "sg:classifiers":[
        {
            "category":"Professional",
            "subcategory":"Accounting & Tax Preparation",
            "type":"Services"
        }
    ],
    "sg:phone":"+61 2 9474 1265",
    "sg:postcode":"2095",
    "sg:province":"NSW",
    "sg:tags":[
        "accountant",
        "auditor"
    ],
    "wof:name":"Visa Connections",
    "wof:placetype":"venue"
},
  "geometry": {"coordinates":[151.284545898,-33.7952880859],"type":"Point"}
}