{
  "type": "Feature",
  "properties": {
    "iso:country":"AU",
    "sg:address":"3A Denman Ave",
    "sg:city":"Kootingal",
    "sg:classifiers":[
        {
            "category":"Military Area",
            "subcategory":"Army Base",
            "type":"Public Place"
        }
    ],
    "sg:phone":"+61 408 969 119",
    "sg:postcode":"2352",
    "sg:province":"NSW",
    "sg:tags":[
        "concrete",
        "slab",
        "floor"
    ],
    "wof:name":"Affordable Concreting Tamworth Pty Ltd",
    "wof:placetype":"venue"
},
  "geometry": {"coordinates":[151.05409240700001,-31.0564441681],"type":"Point"}
}