{
  "type": "Feature",
  "properties": {
    "iso:country":"AU",
    "sg:address":"95- 97 Sheridan St",
    "sg:city":"Gundagai",
    "sg:classifiers":[
        {
            "category":"Health Services",
            "subcategory":"Doctor",
            "type":"Services"
        }
    ],
    "sg:phone":"+61 2 6944 3444",
    "sg:postcode":"2722",
    "sg:province":"NSW",
    "sg:tags":[
        "medical",
        "practitioner"
    ],
    "wof:name":"Gundagai Medical Centre",
    "wof:placetype":"venue"
},
  "geometry": {"coordinates":[148.100067,-35.062332],"type":"Point"}
}