{
  "type": "Feature",
  "properties": {
    "addr:full":"Cnr Malaga Drv & Mulgul Rd Malaga WA 6090",
    "addr:postcode":"6090",
    "addr:street":"Cnr Malaga Drv & Mulgul Rd",
    "iso:country":"AU",
    "sg:address":"Cnr Malaga Drv & Mulgul Rd",
    "sg:city":"Malaga",
    "sg:classifiers":[
        {
            "category":"Shopping",
            "subcategory":"Clothing, Apparel, & Fashions",
            "type":"Retail Goods"
        }
    ],
    "sg:phone":"+61 8 9248 4322",
    "sg:postcode":"6090",
    "sg:province":"WA",
    "sg:tags":[
        "uniform"
    ],
    "wof:name":"Oz Wear",
    "wof:placetype":"venue"
},
  "geometry": {"coordinates":[115.89723205599999,-31.8595561981],"type":"Point"}
}