{
  "type": "Feature",
  "properties": {
    "addr:full":"1 Joynton Ave Waterloo NSW 2017",
    "addr:housenumber":"1",
    "addr:postcode":"2017",
    "addr:street":"Joynton Ave",
    "iso:country":"AU",
    "sg:address":"1 Joynton Ave",
    "sg:city":"Waterloo",
    "sg:classifiers":[
        {
            "category":"Building & Trades",
            "subcategory":"Electrical",
            "type":"Services"
        }
    ],
    "sg:phone":"+61 2 9313 7111",
    "sg:postcode":"2017",
    "sg:province":"NSW",
    "sg:tags":[
        "wholesaler",
        "mfrs",
        "appliance"
    ],
    "wof:name":"Palsonic Corp. Lty Ltd",
    "wof:placetype":"venue"
},
  "geometry": {"coordinates":[151.20599365199999,-33.9101829529],"type":"Point"}
}