{
  "type": "Feature",
  "properties": {
    "addr:full":"1- 3 Bath La Ballarat VIC 3350",
    "addr:housenumber":"3",
    "addr:postcode":"3350",
    "addr:street":"Bath La",
    "iso:country":"AU",
    "sg:address":"1- 3 Bath La",
    "sg:city":"Ballarat",
    "sg:classifiers":[
        {
            "category":"Insurance",
            "subcategory":"Hazard Insurance",
            "type":"Services"
        }
    ],
    "sg:phone":"+61 3 5329 4100",
    "sg:postcode":"3350",
    "sg:province":"VIC",
    "sg:tags":[
        "fire",
        "accident",
        "marine"
    ],
    "wof:name":"CGU",
    "wof:placetype":"venue"
},
  "geometry": {"coordinates":[143.85673499999999,-37.562744],"type":"Point"}
}