{
  "type": "Feature",
  "properties": {
    "addr:full":"609 Camberwell Rd Camberwell VIC 3124",
    "addr:housenumber":"609",
    "addr:postcode":"3124",
    "addr:street":"Camberwell Rd",
    "iso:country":"AU",
    "sg:address":"609 Camberwell Rd",
    "sg:city":"Camberwell",
    "sg:classifiers":[
        {
            "category":"Home & Garden",
            "subcategory":"Carpets & Floor Coverings",
            "type":"Retail Goods"
        }
    ],
    "sg:phone":"+61 3 9889 4950",
    "sg:postcode":"3124",
    "sg:province":"VIC",
    "sg:tags":[
        "tile",
        "wall"
    ],
    "wof:name":"Camberwell Potteries Sales Pty Ltd",
    "wof:placetype":"venue"
},
  "geometry": {"coordinates":[145.075149536,-37.8473205566],"type":"Point"}
}