{
  "type": "Feature",
  "properties": {
    "addr:full":"3 Garnet St Rockdale NSW 2216",
    "addr:housenumber":"3",
    "addr:postcode":"2216",
    "addr:street":"Garnet St",
    "iso:country":"AU",
    "sg:address":"3 Garnet St",
    "sg:city":"Rockdale",
    "sg:classifiers":[
        {
            "category":"Manufacturing",
            "subcategory":"Chemicals & Compounds",
            "type":"Manufacturing & Wholesale Goods"
        }
    ],
    "sg:phone":"+61 2 9567 3339",
    "sg:postcode":"2216",
    "sg:province":"NSW",
    "sg:tags":[
        "electroplating"
    ],
    "wof:name":"Vulkan Industries Pty Ltd",
    "wof:placetype":"venue"
},
  "geometry": {"coordinates":[151.14425700000001,-33.95649],"type":"Point"}
}