{
  "type": "Feature",
  "properties": {
    "iso:country":"AU",
    "sg:address":"23 Austin St",
    "sg:city":"Adelaide",
    "sg:classifiers":[
        {
            "category":"Personal",
            "subcategory":"Beauty Salon",
            "type":"Services"
        }
    ],
    "sg:phone":"+61 8 8232 5440",
    "sg:postcode":"5000",
    "sg:province":"SA",
    "sg:tags":[
        "hairdresser"
    ],
    "wof:name":"Gallerie Cutters The",
    "wof:placetype":"venue"
},
  "geometry": {"coordinates":[138.60609435999999,-34.9274749756],"type":"Point"}
}