{
  "type": "Feature",
  "properties": {
    "addr:full":"Shop 2/ 32 Brisbane Rd Bundamba QLD 4304",
    "addr:housenumber":"shop 2 / 32",
    "addr:postcode":"4304",
    "addr:street":"Brisbane Rd",
    "iso:country":"AU",
    "sg:address":"Shop 2/ 32 Brisbane Rd",
    "sg:city":"Bundamba",
    "sg:classifiers":[
        {
            "category":"Home & Garden",
            "subcategory":"Carpets & Floor Coverings",
            "type":"Retail Goods"
        }
    ],
    "sg:phone":"+61 7 3282 4955",
    "sg:postcode":"4304",
    "sg:province":"QLD",
    "wof:name":"Andersens Carpets Ipswich",
    "wof:placetype":"venue"
},
  "geometry": {"coordinates":[152.81112670900001,-27.6082172394],"type":"Point"}
}