{
  "type": "Feature",
  "properties": {
    "iso:country":"AU",
    "sg:address":"24/ 40 Montclair Ave",
    "sg:city":"Glen Waverley",
    "sg:classifiers":[
        {
            "category":"Professional",
            "subcategory":"Employment Agencies",
            "type":"Services"
        }
    ],
    "sg:phone":"+61 3 9574 8893",
    "sg:postcode":"3150",
    "sg:province":"VIC",
    "sg:tags":[
        "hire",
        "labour",
        "contractor"
    ],
    "wof:name":"iTech - Consultancy",
    "wof:placetype":"venue"
},
  "geometry": {"coordinates":[145.161254883,-37.8807945251],"type":"Point"}
}