{
  "type": "Feature",
  "properties": {
    "iso:country":"AU",
    "sg:address":"14 Whitbread Drv",
    "sg:city":"Lemon Tree Passage",
    "sg:classifiers":[
        {
            "category":"Building & Trades",
            "subcategory":"Construction",
            "type":"Services"
        }
    ],
    "sg:phone":"+61 2 4984 5966",
    "sg:postcode":"2319",
    "sg:province":"NSW",
    "sg:tags":[
        "polishing",
        "sanding",
        "floor"
    ],
    "wof:name":"Port Stephens Timber Floors",
    "wof:placetype":"venue"
},
  "geometry": {"coordinates":[152.031937,-32.728416],"type":"Point"}
}