{
  "type": "Feature",
  "properties": {
    "addr:full":"PO Box 151 Nobby Beach QLD 4218",
    "addr:postcode":"4218",
    "iso:country":"AU",
    "sg:address":"PO Box 151",
    "sg:city":"Nobby Beach",
    "sg:classifiers":[
        {
            "category":"Insurance",
            "subcategory":"Hazard Insurance",
            "type":"Services"
        }
    ],
    "sg:phone":"+61 7 5572 4666",
    "sg:postcode":"4218",
    "sg:province":"QLD",
    "sg:tags":[
        "fire",
        "accident",
        "marine"
    ],
    "wof:name":"Austbrokers Coast To Coast",
    "wof:placetype":"venue"
},
  "geometry": {"coordinates":[153.438262939,-28.0588607788],"type":"Point"}
}