{
  "type": "Feature",
  "properties": {
    "iso:country":"AU",
    "sg:address":"PO Box 191",
    "sg:city":"Pine Creek",
    "sg:classifiers":[
        {
            "category":"Mining & Drilling",
            "type":"Manufacturing & Wholesale Goods"
        }
    ],
    "sg:phone":"+61 8 8976 1386",
    "sg:postcode":"0847",
    "sg:province":"NT",
    "sg:tags":[
        "boring",
        "contractor"
    ],
    "wof:name":"Johannsen Drilling Pty Ltd",
    "wof:placetype":"venue"
},
  "geometry": {"coordinates":[131.83229064899999,-13.8142795563],"type":"Point"}
}