{
  "type": "Feature",
  "properties": {
    "addr:full":"1/ 6 Killick St Kunda Park QLD 4556",
    "addr:housenumber":"/ 6",
    "addr:postcode":"4556",
    "addr:street":"Killick St",
    "iso:country":"AU",
    "sg:address":"1/ 6 Killick St",
    "sg:city":"Kunda Park",
    "sg:classifiers":[
        {
            "category":"Wholesale",
            "subcategory":"Machinery & Supplies",
            "type":"Manufacturing & Wholesale Goods"
        }
    ],
    "sg:phone":"+61 7 5476 8566",
    "sg:postcode":"4556",
    "sg:province":"QLD",
    "sg:tags":[
        "bearing",
        "bushing"
    ],
    "wof:name":"Sunstate Bearings",
    "wof:placetype":"venue"
},
  "geometry": {"coordinates":[153.038497925,-26.6634101868],"type":"Point"}
}