{
  "type": "Feature",
  "properties": {
    "addr:full":"Waterford-Tamborine Rd Tamborine QLD 4270",
    "addr:postcode":"4270",
    "addr:street":"Waterford-Tamborine Rd",
    "iso:country":"AU",
    "sg:address":"Waterford-Tamborine Rd",
    "sg:city":"Tamborine",
    "sg:classifiers":[
        {
            "category":"Home & Garden",
            "subcategory":"Garden Supply",
            "type":"Retail Goods"
        }
    ],
    "sg:phone":"+61 7 3807 0008",
    "sg:postcode":"4270",
    "sg:province":"QLD",
    "sg:tags":[
        "landscape"
    ],
    "wof:name":"Superior Soils",
    "wof:placetype":"venue"
},
  "geometry": {"coordinates":[153.124710083,-27.8774280548],"type":"Point"}
}