{
  "type": "Feature",
  "properties": {
    "iso:country":"AU",
    "sg:address":"13 Hillcrest Crt",
    "sg:city":"Donvale",
    "sg:classifiers":[
        {
            "category":"Retail",
            "subcategory":"Auto Rental",
            "type":"Services"
        }
    ],
    "sg:phone":"+61 3 9841 9155",
    "sg:postcode":"3111",
    "sg:province":"VIC",
    "sg:tags":[
        "chauffeur",
        "car",
        "hire",
        "driven",
        "limousine"
    ],
    "sg:website":"http://www.diplomatlimos.com",
    "wof:name":"Diplomat Hire Cars",
    "wof:placetype":"venue"
},
  "geometry": {"coordinates":[145.18550109899999,-37.7733802795],"type":"Point"}
}