{
  "type": "Feature",
  "properties": {
    "addr:full":"Sth Gippsland Hwy Bena VIC 3946",
    "addr:postcode":"3946",
    "addr:street":"Sth Gippsland Hwy Bena",
    "iso:country":"AU",
    "sg:address":"Sth Gippsland Hwy",
    "sg:city":"Bena",
    "sg:classifiers":[
        {
            "category":"Education",
            "subcategory":"School",
            "type":"Public Place"
        }
    ],
    "sg:phone":"+61 3 5657 2263",
    "sg:postcode":"3946",
    "sg:province":"VIC",
    "sg:tags":[
        "state",
        "except",
        "nsw"
    ],
    "wof:name":"Bena Primary School",
    "wof:placetype":"venue"
},
  "geometry": {"coordinates":[145.75517273,-38.4100456238],"type":"Point"}
}