{
  "type": "Feature",
  "properties": {
    "addr:full":"164 Findlay Rd Adelaide River NT 0846",
    "addr:housenumber":"164",
    "addr:postcode":"0846",
    "addr:street":"Findlay Rd",
    "iso:country":"AU",
    "sg:address":"164 Findlay Rd",
    "sg:city":"Adelaide River",
    "sg:classifiers":[
        {
            "category":"Building & Trades",
            "subcategory":"Landscaping Services",
            "type":"Services"
        }
    ],
    "sg:phone":"+61 8 8976 7099",
    "sg:postcode":"0846",
    "sg:province":"NT",
    "sg:tags":[
        "firebreak",
        "clearing",
        "land",
        "contractor"
    ],
    "wof:name":"Ian Rixon",
    "wof:placetype":"venue"
},
  "geometry": {"coordinates":[131.102493286,-13.2378768921],"type":"Point"}
}