{
  "type": "Feature",
  "properties": {
    "addr:full":"3 Beatrice Pl Ferntree Gully VIC 3156",
    "addr:housenumber":"3",
    "addr:postcode":"3156",
    "addr:street":"Beatrice Pl",
    "iso:country":"AU",
    "sg:address":"3 Beatrice Pl",
    "sg:city":"Ferntree Gully",
    "sg:classifiers":[
        {
            "category":"Professional",
            "subcategory":"Computer Services",
            "type":"Services"
        }
    ],
    "sg:phone":"+61 3 9752 2550",
    "sg:postcode":"3156",
    "sg:province":"VIC",
    "sg:tags":[
        "consultant",
        "system"
    ],
    "wof:name":"Leading Edge Computers Pty Ltd",
    "wof:placetype":"venue"
},
  "geometry": {"coordinates":[145.28286743199999,-37.8939819336],"type":"Point"}
}