{
  "type": "Feature",
  "properties": {
    "addr:full":"PO Box 550 Gisborne VIC 3437",
    "addr:postcode":"3437",
    "iso:country":"AU",
    "sg:address":"PO Box 550",
    "sg:city":"Gisborne",
    "sg:classifiers":[
        {
            "category":"Building & Trades",
            "subcategory":"Landscaping Services",
            "type":"Services"
        }
    ],
    "sg:phone":"+61 3 5428 8579",
    "sg:postcode":"3437",
    "sg:province":"VIC",
    "sg:tags":[
        "tour",
        "shopping"
    ],
    "wof:name":"Tartan Tours",
    "wof:placetype":"venue"
},
  "geometry": {"coordinates":[144.59135437,-37.4869995117],"type":"Point"}
}