{
  "type": "Feature",
  "properties": {
    "iso:country":"AU",
    "sg:address":"Level 7 189 Grey St",
    "sg:city":"South Bank",
    "sg:classifiers":[
        {
            "category":"Professional",
            "subcategory":"Engineering",
            "type":"Services"
        }
    ],
    "sg:phone":"+61 7 3121 8500",
    "sg:postcode":"4101",
    "sg:province":"QLD",
    "sg:tags":[
        "engineer",
        "mechanical"
    ],
    "wof:name":"Thiess Pty Ltd",
    "wof:placetype":"venue"
},
  "geometry": {"coordinates":[153.02145385700001,-27.4787120819],"type":"Point"}
}