{
  "type": "Feature",
  "properties": {
    "addr:full":"Lower Ground 102 Longueville Rd Lane Cove NSW 2066",
    "addr:housenumber":"102",
    "addr:postcode":"2066",
    "addr:street":"Longueville Rd",
    "iso:country":"AU",
    "sg:address":"Lower Ground 102 Longueville Rd",
    "sg:city":"Lane Cove",
    "sg:classifiers":[
        {
            "category":"Social Services",
            "type":"Services"
        }
    ],
    "sg:phone":"+61 2 9428 4494",
    "sg:postcode":"2066",
    "sg:province":"NSW",
    "sg:tags":[
        "domestic",
        "help"
    ],
    "wof:name":"Welcome Home Help Agency",
    "wof:placetype":"venue"
},
  "geometry": {"coordinates":[151.16998290999999,-33.8138999939],"type":"Point"}
}