{
  "type": "Feature",
  "properties": {
    "iso:country":"AU",
    "sg:address":"Burt St",
    "sg:city":"Albany",
    "sg:classifiers":[
        {
            "category":"Education",
            "subcategory":"School",
            "type":"Public Place"
        }
    ],
    "sg:phone":"+61 8 9841 2411",
    "sg:postcode":"6330",
    "sg:province":"WA",
    "sg:tags":[
        "state",
        "except",
        "nsw"
    ],
    "wof:name":"Albany Senior High School",
    "wof:placetype":"venue"
},
  "geometry": {"coordinates":[117.89494323700001,-35.0195960999],"type":"Point"}
}