{
  "type": "Feature",
  "properties": {
    "iso:country":"AU",
    "sg:address":"33 Keam Crs",
    "sg:city":"Kingston",
    "sg:classifiers":[
        {
            "category":"Building & Trades",
            "subcategory":"Construction",
            "type":"Services"
        }
    ],
    "sg:phone":"+61 427 866 789",
    "sg:postcode":"7050",
    "sg:province":"TAS",
    "sg:tags":[
        "contractor"
    ],
    "wof:name":"New Life Homes",
    "wof:placetype":"venue"
},
  "geometry": {"coordinates":[147.289917,-42.964359],"type":"Point"}
}