{
  "type": "Feature",
  "properties": {
    "iso:country":"AU",
    "sg:address":"215 Charlies Point Rd",
    "sg:city":"Bargo",
    "sg:classifiers":[
        {
            "category":"Professional",
            "subcategory":"Testing Lab",
            "type":"Services"
        }
    ],
    "sg:phone":"+61 2 4684 1551",
    "sg:postcode":"2574",
    "sg:province":"NSW",
    "sg:tags":[
        "inspection"
    ],
    "wof:name":"Watt- Tel",
    "wof:placetype":"venue"
},
  "geometry": {"coordinates":[150.595428467,-34.2589149475],"type":"Point"}
}