{
  "type": "Feature",
  "properties": {
    "addr:full":"11 Anictomatis Rd Berrimah NT 0828",
    "addr:housenumber":"11",
    "addr:postcode":"nt 0828",
    "addr:street":"Anictomatis Rd",
    "iso:country":"AU",
    "sg:address":"11 Anictomatis Rd",
    "sg:city":"Berrimah",
    "sg:classifiers":[
        {
            "category":"Professional",
            "type":"Services"
        }
    ],
    "sg:phone":"+61 8 8947 2278",
    "sg:postcode":"0828",
    "sg:province":"NT",
    "sg:tags":[
        "transport"
    ],
    "wof:name":"Territory Freight Express",
    "wof:placetype":"venue"
},
  "geometry": {"coordinates":[130.94659423799999,-12.4439315796],"type":"Point"}
}