{
  "type": "Feature",
  "properties": {
    "addr:full":"30 Banksia Ave Cabarita Beach NSW 2488",
    "addr:housenumber":"30",
    "addr:postcode":"2488",
    "addr:street":"Banksia Ave",
    "iso:country":"AU",
    "sg:address":"30 Banksia Ave",
    "sg:city":"Cabarita Beach",
    "sg:classifiers":[
        {
            "category":"Personal",
            "subcategory":"Beauty Salon",
            "type":"Services"
        }
    ],
    "sg:phone":"+61 2 6676 2232",
    "sg:postcode":"2488",
    "sg:province":"NSW",
    "sg:tags":[
        "hairdresser"
    ],
    "wof:name":"Felicity Davis Hairdressing",
    "wof:placetype":"venue"
},
  "geometry": {"coordinates":[153.56660500000001,-28.334173],"type":"Point"}
}