{
  "type": "Feature",
  "properties": {
    "iso:country":"AU",
    "sg:address":"23 Goondoon St",
    "sg:city":"Gladstone",
    "sg:classifiers":[
        {
            "category":"Travel",
            "subcategory":"Hotels & Motels",
            "type":"Entertainment"
        }
    ],
    "sg:phone":"+61 7 4972 3456",
    "sg:postcode":"4680",
    "sg:province":"QLD",
    "wof:name":"Harbour Sails Motor Inn",
    "wof:placetype":"venue"
},
  "geometry": {"coordinates":[151.253372192,-23.8397274017],"type":"Point"}
}