{
  "type": "Feature",
  "properties": {
    "addr:full":"Unit 7, 421a Glenfern Rd Upwey VIC 3158",
    "addr:housenumber":"421a",
    "addr:postcode":"3158",
    "addr:street":"Glenfern Rd",
    "iso:country":"AU",
    "sg:address":"Unit 7, 421a Glenfern Rd",
    "sg:city":"Upwey",
    "sg:classifiers":[
        {
            "category":"Professional",
            "subcategory":"Accounting & Tax Preparation",
            "type":"Services"
        }
    ],
    "sg:phone":"+61 3 9754 8580",
    "sg:postcode":"3158",
    "sg:province":"VIC",
    "sg:tags":[
        "bookkeeping"
    ],
    "wof:name":"Ranges Bookkeeping",
    "wof:placetype":"venue"
},
  "geometry": {"coordinates":[145.33973693900001,-37.910243988],"type":"Point"}
}