{
  "type": "Feature",
  "properties": {
    "addr:full":"1232 Huon Rd Neika TAS 7054",
    "addr:housenumber":"1232",
    "addr:postcode":"7054",
    "addr:street":"Huon Rd",
    "iso:country":"AU",
    "sg:address":"1232 Huon Rd",
    "sg:city":"Neika",
    "sg:classifiers":[
        {
            "category":"Social Services",
            "subcategory":"Retirement Home",
            "type":"Services"
        }
    ],
    "sg:phone":"+61 419 618 749",
    "sg:postcode":"7054",
    "sg:province":"TAS",
    "sg:tags":[
        "environmental",
        "consultant",
        "pollution"
    ],
    "wof:name":"Closed Loop Management",
    "wof:placetype":"venue"
},
  "geometry": {"coordinates":[147.22903400000001,-42.951233],"type":"Point"}
}