{
  "type": "Feature",
  "properties": {
    "addr:full":"170 Lorayln Ave Sanctuary Point NSW 2540",
    "addr:housenumber":"170",
    "addr:postcode":"2540",
    "addr:street":"Lorayln Ave",
    "iso:country":"AU",
    "sg:address":"170 Lorayln Ave",
    "sg:city":"Sanctuary Point",
    "sg:classifiers":[
        {
            "category":"Professional",
            "subcategory":"Engineering",
            "type":"Services"
        }
    ],
    "sg:phone":"+61 2 4443 8621",
    "sg:postcode":"2540",
    "sg:province":"NSW",
    "sg:tags":[
        "engineer",
        "structural"
    ],
    "wof:name":"Hatch Evan D",
    "wof:placetype":"venue"
},
  "geometry": {"coordinates":[150.61338806099999,-35.1008682251],"type":"Point"}
}