{
  "type": "Feature",
  "properties": {
    "addr:full":"3 Cunningham St North Sydney NSW 2060",
    "addr:housenumber":"3",
    "addr:postcode":"2060",
    "addr:street":"Cunningham St",
    "iso:country":"AU",
    "sg:address":"3 Cunningham St",
    "sg:city":"North Sydney",
    "sg:classifiers":[
        {
            "category":"Organizations",
            "subcategory":"Non-profit Organization",
            "type":"Services"
        }
    ],
    "sg:phone":"+61 2 9923 2727",
    "sg:postcode":"2060",
    "sg:province":"NSW",
    "sg:tags":[
        "support",
        "disability",
        "organisation"
    ],
    "wof:name":"Early Education (EarlyEd) Clinic Inc",
    "wof:placetype":"venue"
},
  "geometry": {"coordinates":[151.206130981,-33.8328361511],"type":"Point"}
}