{
  "type": "Feature",
  "properties": {
    "iso:country":"AU",
    "sg:address":"32 Lord St",
    "sg:city":"Port Campbell",
    "sg:classifiers":[
        {
            "category":"Utilities",
            "subcategory":"Fuel Oil & Lpg",
            "type":"Services"
        }
    ],
    "sg:phone":"+61 3 5598 6411",
    "sg:postcode":"3269",
    "sg:province":"VIC",
    "sg:tags":[
        "merchant"
    ],
    "wof:name":"Port Campbell Crayfish & Marine Services",
    "wof:placetype":"venue"
},
  "geometry": {"coordinates":[142.995361328,-38.6196746826],"type":"Point"}
}