{
  "type": "Feature",
  "properties": {
    "addr:full":"17 Murrell Rd Para Hills SA 5096",
    "addr:housenumber":"17",
    "addr:postcode":"5096",
    "addr:street":"Murrell Rd Para",
    "iso:country":"AU",
    "sg:address":"17 Murrell Rd",
    "sg:city":"Para Hills",
    "sg:classifiers":[
        {
            "category":"Building & Trades",
            "subcategory":"Pest Control",
            "type":"Services"
        }
    ],
    "sg:phone":"+61 8 8395 0991",
    "sg:postcode":"5096",
    "sg:province":"SA",
    "wof:name":"CLP Northern Pest & Weed Control",
    "wof:placetype":"venue"
},
  "geometry": {"coordinates":[138.66192626899999,-34.8112983704],"type":"Point"}
}