{
  "type": "Feature",
  "properties": {
    "iso:country":"AU",
    "sg:address":"129 York St",
    "sg:city":"South Melbourne",
    "sg:classifiers":[
        {
            "category":"Professional",
            "subcategory":"Business Services",
            "type":"Services"
        }
    ],
    "sg:phone":"+61 3 9696 9840",
    "sg:postcode":"3205",
    "sg:province":"VIC",
    "sg:tags":[
        "management",
        "event"
    ],
    "wof:name":"Organisation Unlimited",
    "wof:placetype":"venue"
},
  "geometry": {"coordinates":[144.957825,-37.831375],"type":"Point"}
}