{
  "type": "Feature",
  "properties": {
    "iso:country":"AU",
    "sg:address":"Shp1a/ West Pl",
    "sg:city":"Churchill",
    "sg:classifiers":[
        {
            "category":"Retail",
            "subcategory":"Laundry & Dry Cleaning",
            "type":"Services"
        }
    ],
    "sg:phone":"+61 3 5122 1600",
    "sg:postcode":"3842",
    "sg:province":"VIC",
    "wof:name":"Churchill Laundry",
    "wof:placetype":"venue"
},
  "geometry": {"coordinates":[146.42027282699999,-38.3142242432],"type":"Point"}
}