{
  "type": "Feature",
  "properties": {
    "iso:country":"AU",
    "sg:address":"81 Harbord St",
    "sg:city":"Bonnells Bay",
    "sg:classifiers":[
        {
            "category":"Professional",
            "subcategory":"Computer Services",
            "type":"Services"
        }
    ],
    "sg:phone":"+61 2 4970 4178",
    "sg:postcode":"2264",
    "sg:province":"NSW",
    "sg:tags":[
        "repairs",
        "upgrade",
        "equipment"
    ],
    "wof:name":"Bonnells Bay Computer Workz",
    "wof:placetype":"venue"
},
  "geometry": {"coordinates":[151.525635,-33.109463],"type":"Point"}
}