{
  "type": "Feature",
  "properties": {
    "addr:full":"West Balcatta Primary School 215 Cedric St Balcatta WA 6021",
    "addr:housenumber":"215",
    "addr:postcode":"6021",
    "addr:street":"Cedric St",
    "iso:country":"AU",
    "sg:address":"West Balcatta Primary School 215 Cedric St",
    "sg:city":"Balcatta",
    "sg:classifiers":[
        {
            "category":"Education",
            "subcategory":"School",
            "type":"Public Place"
        }
    ],
    "sg:phone":"+61 8 9446 9211",
    "sg:postcode":"6021",
    "sg:province":"WA",
    "sg:tags":[
        "state",
        "except",
        "nsw"
    ],
    "wof:name":"Schools Government (Public)",
    "wof:placetype":"venue"
},
  "geometry": {"coordinates":[115.80970764200001,-31.8823947906],"type":"Point"}
}