{
  "type": "Feature",
  "properties": {
    "addr:full":"3 Glendora Ave Brighton VIC 3186",
    "addr:housenumber":"3",
    "addr:postcode":"3186",
    "addr:street":"Glendora Ave",
    "iso:country":"AU",
    "sg:address":"3 Glendora Ave",
    "sg:city":"Brighton",
    "sg:classifiers":[
        {
            "category":"Professional",
            "subcategory":"Accounting & Tax Preparation",
            "type":"Services"
        }
    ],
    "sg:phone":"+61 3 9528 5883",
    "sg:postcode":"3186",
    "sg:province":"VIC",
    "sg:tags":[
        "bookkeeping"
    ],
    "wof:name":"Glendora Commercial Services",
    "wof:placetype":"venue"
},
  "geometry": {"coordinates":[144.999603272,-37.887966156],"type":"Point"}
}