{
  "type": "Feature",
  "properties": {
    "addr:full":"10 Spring St Elliminyt VIC 3249",
    "addr:housenumber":"10",
    "addr:postcode":"3249",
    "addr:street":"Spring St",
    "iso:country":"AU",
    "sg:address":"10 Spring St",
    "sg:city":"Elliminyt",
    "sg:classifiers":[
        {
            "category":"Building & Trades",
            "subcategory":"Construction",
            "type":"Services"
        }
    ],
    "sg:phone":"+61 3 5231 1372",
    "sg:postcode":"3249",
    "sg:province":"VIC",
    "sg:tags":[
        "joiner",
        "carpenter"
    ],
    "wof:name":"Colbourne D J & C M",
    "wof:placetype":"venue"
},
  "geometry": {"coordinates":[143.576904297,-38.364112854],"type":"Point"}
}