{
  "type": "Feature",
  "properties": {
    "addr:full":"13 Simpson St Mt Isa QLD 4825",
    "addr:housenumber":"13",
    "addr:postcode":"4825",
    "addr:street":"Simpson St",
    "iso:country":"AU",
    "sg:address":"13 Simpson St",
    "sg:city":"Mt Isa",
    "sg:classifiers":[
        {
            "category":"Social Services",
            "subcategory":"Adult Care",
            "type":"Services"
        }
    ],
    "sg:phone":"+61 7 4743 2542",
    "sg:postcode":"4825",
    "sg:province":"QLD",
    "sg:tags":[
        "towing"
    ],
    "wof:name":"Power Automotive(RACQ)",
    "wof:placetype":"venue"
},
  "geometry": {"coordinates":[139.49401900000001,-20.727404],"type":"Point"}
}