{
  "type": "Feature",
  "properties": {
    "addr:full":"Reformed Church Nicholls St Devonport TAS 7310",
    "addr:postcode":"7310",
    "addr:street":"Nicholls St",
    "iso:country":"AU",
    "sg:address":"Reformed Church Nicholls St",
    "sg:city":"Devonport",
    "sg:classifiers":[
        {
            "category":"Education",
            "subcategory":"Dance Studio",
            "type":"Public Place"
        }
    ],
    "sg:phone":"+61 3 6423 2308",
    "sg:postcode":"7310",
    "sg:province":"TAS",
    "sg:tags":[
        "venue",
        "tuition"
    ],
    "wof:name":"Caroline Small School Of Dance",
    "wof:placetype":"venue"
},
  "geometry": {"coordinates":[146.350097656,-41.1702537537],"type":"Point"}
}