{
  "type": "Feature",
  "properties": {
    "addr:full":"36 Chapel St Kogarah NSW 2217",
    "addr:housenumber":"36",
    "addr:postcode":"2217",
    "addr:street":"Chapel St",
    "iso:country":"AU",
    "sg:address":"36 Chapel St",
    "sg:city":"Kogarah",
    "sg:classifiers":[
        {
            "category":"Education",
            "subcategory":"School",
            "type":"Public Place"
        }
    ],
    "sg:phone":"+61 2 9587 8998",
    "sg:postcode":"2217",
    "sg:province":"NSW",
    "wof:name":"St Patrick's Primary School",
    "wof:placetype":"venue"
},
  "geometry": {"coordinates":[151.134995,-33.968861],"type":"Point"}
}