{
  "type": "Feature",
  "properties": {
    "addr:full":"Shop 2/ 32 Ware St Fairfield NSW 2165",
    "addr:housenumber":"shop 2 / 32",
    "addr:postcode":"2165",
    "addr:street":"Ware St",
    "iso:country":"AU",
    "sg:address":"Shop 2/ 32 Ware St",
    "sg:city":"Fairfield",
    "sg:classifiers":[
        {
            "category":"Personal",
            "subcategory":"Beauty Salon",
            "type":"Services"
        }
    ],
    "sg:phone":"+61 2 9727 6817",
    "sg:postcode":"2165",
    "sg:province":"NSW",
    "sg:website":"http://www.sandscosmeticclinic.com.au",
    "wof:name":"Sands Cosmetic Clinic",
    "wof:placetype":"venue"
},
  "geometry": {"coordinates":[150.95513915999999,-33.8712234497],"type":"Point"}
}