{
  "type": "Feature",
  "properties": {
    "addr:full":"Lot 23 Beddingfield Rd Bunbury WA 6230",
    "addr:postcode":"6230",
    "addr:street":"Beddingfield Rd",
    "iso:country":"AU",
    "sg:address":"Lot 23 Beddingfield Rd",
    "sg:city":"Bunbury",
    "sg:classifiers":[
        {
            "category":"Food & Beverages",
            "subcategory":"Bakery",
            "type":"Retail Goods"
        }
    ],
    "sg:phone":"+61 8 9725 4321",
    "sg:postcode":"6230",
    "sg:province":"WA",
    "sg:tags":[
        "baker"
    ],
    "wof:name":"Tip Top Bakeries (South West)",
    "wof:placetype":"venue"
},
  "geometry": {"coordinates":[115.680443,-33.354691],"type":"Point"}
}