{
  "type": "Feature",
  "properties": {
    "addr:full":"9 Fort La Brisbane QLD 4000",
    "addr:housenumber":"9",
    "addr:postcode":"4000",
    "addr:street":"Fort La",
    "iso:country":"AU",
    "sg:address":"9 Fort La",
    "sg:city":"Brisbane",
    "sg:classifiers":[
        {
            "category":"Education",
            "subcategory":"School",
            "type":"Public Place"
        }
    ],
    "sg:phone":"+61 1800 007 295",
    "sg:postcode":"4000",
    "sg:province":"QLD",
    "sg:tags":[
        "supply"
    ],
    "wof:name":"Eckersley's School Division",
    "wof:placetype":"venue"
},
  "geometry": {"coordinates":[153.00491332999999,-27.4719848633],"type":"Point"}
}