{
  "type": "Feature",
  "properties": {
    "iso:country":"AU",
    "sg:address":"1 St Georges Tce",
    "sg:city":"Perth",
    "sg:classifiers":[
        {
            "category":"Restaurant",
            "type":"Food & Drink"
        }
    ],
    "sg:phone":"+61 8 9261 8025",
    "sg:postcode":"6000",
    "sg:province":"WA",
    "sg:website":"http://www.duxton.com",
    "wof:name":"The Grill Duxton Hotel Perth",
    "wof:placetype":"venue"
},
  "geometry": {"coordinates":[115.86521911600001,-31.9577255249],"type":"Point"}
}