{
  "type": "Feature",
  "properties": {
    "addr:full":"3 Tower St Clovelly NSW 2031",
    "addr:housenumber":"3",
    "addr:postcode":"2031",
    "addr:street":"Tower St",
    "iso:country":"AU",
    "sg:address":"3 Tower St",
    "sg:city":"Clovelly",
    "sg:classifiers":[
        {
            "category":"Education",
            "subcategory":"University",
            "type":"Public Place"
        }
    ],
    "sg:phone":"+61 2 9665 8082",
    "sg:postcode":"2031",
    "sg:province":"NSW",
    "sg:tags":[
        "educational",
        "organisation",
        "cultural"
    ],
    "wof:name":"Envirokid Adventures",
    "wof:placetype":"venue"
},
  "geometry": {"coordinates":[151.26243591299999,-33.9140510559],"type":"Point"}
}