{
  "type": "Feature",
  "properties": {
    "iso:country":"AU",
    "sg:address":"33 Claremont St",
    "sg:city":"South Yarra",
    "sg:classifiers":[
        {
            "category":"Shopping",
            "type":"Retail Goods"
        }
    ],
    "sg:phone":"+61 3 9826 8188",
    "sg:postcode":"3141",
    "sg:province":"VIC",
    "sg:tags":[
        "clearance",
        "factory",
        "outlet"
    ],
    "wof:name":"Designer Excess",
    "wof:placetype":"venue"
},
  "geometry": {"coordinates":[144.99380493199999,-37.8370857239],"type":"Point"}
}