{
  "type": "Feature",
  "properties": {
    "iso:country":"AU",
    "sg:address":"61 Hermitage Rd",
    "sg:city":"Maiden Gully",
    "sg:classifiers":[
        {
            "category":"Building & Trades",
            "subcategory":"Cleaning & Sanitation",
            "type":"Services"
        }
    ],
    "sg:phone":"+61 419 327 743",
    "sg:postcode":"3551",
    "sg:province":"VIC",
    "sg:tags":[
        "industrial",
        "commercial",
        "contractor"
    ],
    "wof:name":"Arrow Kleen",
    "wof:placetype":"venue"
},
  "geometry": {"coordinates":[144.182662964,-36.7334060669],"type":"Point"}
}