{
  "type": "Feature",
  "properties": {
    "addr:full":"6 Exford Pl Donvale VIC 3111",
    "addr:housenumber":"6",
    "addr:postcode":"3111",
    "addr:street":"Exford Pl",
    "iso:country":"AU",
    "sg:address":"6 Exford Pl",
    "sg:city":"Donvale",
    "sg:classifiers":[
        {
            "category":"Professional",
            "subcategory":"Computer Services",
            "type":"Services"
        }
    ],
    "sg:phone":"+61 3 9872 5599",
    "sg:postcode":"3111",
    "sg:province":"VIC",
    "sg:tags":[
        "training"
    ],
    "wof:name":"Aztec Computer Training",
    "wof:placetype":"venue"
},
  "geometry": {"coordinates":[145.18463134800001,-37.8003234863],"type":"Point"}
}