{
  "type": "Feature",
  "properties": {
    "iso:country":"AU",
    "sg:address":"Ground Floor, 2 Roy St",
    "sg:city":"Geelong",
    "sg:classifiers":[
        {
            "category":"Education",
            "subcategory":"Special Training",
            "type":"Public Place"
        }
    ],
    "sg:phone":"+61 3 5223 1197",
    "sg:postcode":"3220",
    "sg:province":"VIC",
    "sg:tags":[
        "development"
    ],
    "wof:name":"Leer Institute",
    "wof:placetype":"venue"
},
  "geometry": {"coordinates":[144.36021400000001,-38.146942],"type":"Point"}
}