{
  "type": "Feature",
  "properties": {
    "addr:full":"8 Loch Fyne Crt Sorrento VIC 3943",
    "addr:housenumber":"8",
    "addr:postcode":"3943",
    "addr:street":"Loch Fyne Crt",
    "iso:country":"AU",
    "sg:address":"8 Loch Fyne Crt",
    "sg:city":"Sorrento",
    "sg:classifiers":[
        {
            "category":"Building & Trades",
            "subcategory":"Construction",
            "type":"Services"
        }
    ],
    "sg:phone":"+61 3 5984 5734",
    "sg:postcode":"3943",
    "sg:province":"VIC",
    "sg:tags":[
        "contractor"
    ],
    "wof:name":"Swift & Pie Builders",
    "wof:placetype":"venue"
},
  "geometry": {"coordinates":[144.75103759800001,-38.3504753113],"type":"Point"}
}