{
  "type": "Feature",
  "properties": {
    "iso:country":"AU",
    "sg:address":"33 The Pde",
    "sg:city":"Tumbarumba",
    "sg:classifiers":[
        {
            "category":"Food & Beverages",
            "subcategory":"Bakery",
            "type":"Retail Goods"
        }
    ],
    "sg:phone":"+61 2 6948 2175",
    "sg:postcode":"2653",
    "sg:province":"NSW",
    "sg:tags":[
        "cake",
        "shop",
        "pastry"
    ],
    "wof:name":"Tumbarumba Bakery",
    "wof:placetype":"venue"
},
  "geometry": {"coordinates":[148.00990295400001,-35.7768478394],"type":"Point"}
}