{
  "type": "Feature",
  "properties": {
    "addr:full":"25 Hobart St Riverstone NSW 2765",
    "addr:housenumber":"25",
    "addr:postcode":"2765",
    "addr:street":"Hobart St",
    "iso:country":"AU",
    "sg:address":"25 Hobart St",
    "sg:city":"Riverstone",
    "sg:classifiers":[
        {
            "category":"Wholesale",
            "subcategory":"Electrical",
            "type":"Manufacturing & Wholesale Goods"
        }
    ],
    "sg:phone":"+61 2 9627 5596",
    "sg:postcode":"2765",
    "sg:province":"NSW",
    "sg:tags":[
        "wholesaler"
    ],
    "wof:name":"Smith & Pearce Pty Ltd",
    "wof:placetype":"venue"
},
  "geometry": {"coordinates":[150.858718872,-33.6687011719],"type":"Point"}
}