{
  "type": "Feature",
  "properties": {
    "addr:full":"Shop 12, Mornington Village S/C, 241 Main St Mornington VIC 3931",
    "addr:housenumber":"shop 12;241",
    "addr:postcode":"3931",
    "addr:street":"Mornington Village S / C;Main St",
    "iso:country":"AU",
    "sg:address":"Shop 12, Mornington Village S/C, 241 Main St",
    "sg:city":"Mornington",
    "sg:classifiers":[
        {
            "category":"Professional",
            "subcategory":"Computer Services",
            "type":"Services"
        }
    ],
    "sg:phone":"+61 422 222 833",
    "sg:postcode":"3931",
    "sg:province":"VIC",
    "sg:tags":[
        "repairs",
        "upgrade",
        "equipment"
    ],
    "wof:name":"P.C. Ambulance",
    "wof:placetype":"venue"
},
  "geometry": {"coordinates":[145.040847778,-38.2234840393],"type":"Point"}
}