{
  "type": "Feature",
  "properties": {
    "iso:country":"AU",
    "sg:address":"Head Office 1 Altona St",
    "sg:city":"Bibra Lake",
    "sg:classifiers":[
        {
            "category":"Farming",
            "subcategory":"Farm & Veterinary Services",
            "type":"Manufacturing & Wholesale Goods"
        }
    ],
    "sg:phone":"+61 13 24 11",
    "sg:postcode":"6163",
    "sg:province":"WA",
    "sg:tags":[
        "irrigation",
        "reticulation",
        "system"
    ],
    "sg:website":"http://www.totaleden.com.au",
    "wof:name":"Total Eden Watering Systems - Statewide",
    "wof:placetype":"venue"
},
  "geometry": {"coordinates":[115.80191,-32.094982],"type":"Point"}
}