{
  "type": "Feature",
  "properties": {
    "iso:country":"AU",
    "sg:address":"\"Glenbothy\" 175 Glenwood Rd",
    "sg:city":"Relbia",
    "sg:classifiers":[
        {
            "category":"Farming",
            "subcategory":"Vineyard",
            "type":"Manufacturing & Wholesale Goods"
        }
    ],
    "sg:phone":"+61 3 6343 0773",
    "sg:postcode":"7258",
    "sg:province":"TAS",
    "sg:tags":[
        "winery"
    ],
    "wof:name":"Sharmans",
    "wof:placetype":"venue"
},
  "geometry": {"coordinates":[147.190963745,-41.480758667],"type":"Point"}
}