{
  "type": "Feature",
  "properties": {
    "iso:country":"AU",
    "sg:address":"215 Myrtle St",
    "sg:city":"Myrtleford",
    "sg:classifiers":[
        {
            "category":"Wholesale",
            "subcategory":"Farm Supplies",
            "type":"Manufacturing & Wholesale Goods"
        }
    ],
    "sg:phone":"+61 3 5752 1800",
    "sg:postcode":"3737",
    "sg:province":"VIC",
    "sg:tags":[
        "equipment"
    ],
    "wof:name":"Tafco Rural Supplies",
    "wof:placetype":"venue"
},
  "geometry": {"coordinates":[146.727020264,-36.5628013611],"type":"Point"}
}