{
  "type": "Feature",
  "properties": {
    "addr:full":"PO Box 1096 Newcastle NSW 2300",
    "addr:postcode":"2300",
    "iso:country":"AU",
    "sg:address":"PO Box 1096",
    "sg:city":"Newcastle",
    "sg:classifiers":[
        {
            "category":"Retail",
            "subcategory":"Repair Shop",
            "type":"Services"
        }
    ],
    "sg:phone":"+61 2 4947 6220",
    "sg:postcode":"2300",
    "sg:province":"NSW",
    "sg:tags":[
        "stove",
        "part",
        "range"
    ],
    "wof:name":"J. Hudson",
    "wof:placetype":"venue"
},
  "geometry": {"coordinates":[151.780136,-32.930859],"type":"Point"}
}