{
  "type": "Feature",
  "properties": {
    "addr:full":"83 Roy St Donvale VIC 3111",
    "addr:housenumber":"83",
    "addr:postcode":"3111",
    "addr:street":"Roy St",
    "iso:country":"AU",
    "sg:address":"83 Roy St",
    "sg:city":"Donvale",
    "sg:classifiers":[
        {
            "category":"Health Services",
            "subcategory":"Dentist",
            "type":"Services"
        }
    ],
    "sg:phone":"+61 3 9841 4171",
    "sg:postcode":"3111",
    "sg:province":"VIC",
    "wof:name":"A Abraham Dr",
    "wof:placetype":"venue"
},
  "geometry": {"coordinates":[145.17845153799999,-37.7980995178],"type":"Point"}
}