{
  "type": "Feature",
  "properties": {
    "addr:full":"27 Dudley Rd Kenwick WA 6107",
    "addr:housenumber":"27",
    "addr:postcode":"6107",
    "addr:street":"Dudley Rd",
    "iso:country":"AU",
    "sg:address":"27 Dudley Rd",
    "sg:city":"Kenwick",
    "sg:classifiers":[
        {
            "category":"Health Services",
            "subcategory":"Health Practitioner",
            "type":"Services"
        }
    ],
    "sg:phone":"+61 8 9459 3629",
    "sg:postcode":"6107",
    "sg:province":"WA",
    "sg:tags":[
        "technique",
        "alexander"
    ],
    "wof:name":"Elena Cabrera",
    "wof:placetype":"venue"
},
  "geometry": {"coordinates":[115.964782715,-32.036113739],"type":"Point"}
}