{
  "type": "Feature",
  "properties": {
    "addr:full":"Shp 25 Homeworld Shpgn Ctr Soward Way Tuggeranong ACT 2900",
    "addr:housenumber":"25",
    "addr:postcode":"2900",
    "addr:street":"Homeworld Shpgn;Soward Way",
    "iso:country":"AU",
    "sg:address":"Shp 25 Homeworld Shpgn Ctr Soward Way",
    "sg:city":"Tuggeranong",
    "sg:classifiers":[
        {
            "category":"Shopping",
            "subcategory":"Computers & Home Electronics",
            "type":"Retail Goods"
        }
    ],
    "sg:phone":"+61 2 6293 3399",
    "sg:postcode":"2900",
    "sg:province":"ACT",
    "sg:tags":[
        "equipment",
        "part",
        "electronic"
    ],
    "wof:name":"Dick Smith Electronics",
    "wof:placetype":"venue"
},
  "geometry": {"coordinates":[149.06825256400001,-35.4185905457],"type":"Point"}
}