{
  "type": "Feature",
  "properties": {
    "addr:full":"292 Missigs Rd Haigslea QLD 4306",
    "addr:housenumber":"292",
    "addr:postcode":"4306",
    "addr:street":"Missigs Rd",
    "iso:country":"AU",
    "sg:address":"292 Missigs Rd",
    "sg:city":"Haigslea",
    "sg:classifiers":[
        {
            "category":"Wholesale",
            "subcategory":"Machinery & Supplies",
            "type":"Manufacturing & Wholesale Goods"
        }
    ],
    "sg:phone":"+61 7 5464 4993",
    "sg:postcode":"4306",
    "sg:province":"QLD",
    "sg:tags":[
        "agricultural"
    ],
    "wof:name":"AATI Pty Ltd",
    "wof:placetype":"venue"
},
  "geometry": {"coordinates":[152.6509552,-27.5634021759],"type":"Point"}
}