{
  "type": "Feature",
  "properties": {
    "iso:country":"AU",
    "sg:address":"35 Brockman Ave",
    "sg:city":"Revesby Heights",
    "sg:classifiers":[
        {
            "category":"Professional",
            "subcategory":"Computer Services",
            "type":"Services"
        }
    ],
    "sg:phone":"+61 2 9792 6226",
    "sg:postcode":"2212",
    "sg:province":"NSW",
    "sg:tags":[
        "technical",
        "support"
    ],
    "wof:name":"Gartech",
    "wof:placetype":"venue"
},
  "geometry": {"coordinates":[151.02113299999999,-33.969738],"type":"Point"}
}