{
  "type": "Feature",
  "properties": {
    "addr:full":"Level 3, 468-472 George St Sydney NSW 2000",
    "addr:housenumber":"468-472",
    "addr:postcode":"2000",
    "addr:street":"George St",
    "iso:country":"AU",
    "sg:address":"Level 3, 468-472 George St",
    "sg:city":"Sydney",
    "sg:classifiers":[
        {
            "category":"Health Services",
            "subcategory":"Health Practitioner",
            "type":"Services"
        }
    ],
    "sg:phone":"+61 2 9283 9626",
    "sg:postcode":"2000",
    "sg:province":"NSW",
    "sg:tags":[
        "alternative"
    ],
    "wof:name":"CBD Health Solutions",
    "wof:placetype":"venue"
},
  "geometry": {"coordinates":[151.20715332,-33.8714103699],"type":"Point"}
}