{
  "type": "Feature",
  "properties": {
    "addr:full":"39 Derria St Canley Vale NSW 2166",
    "addr:housenumber":"39",
    "addr:postcode":"2166",
    "addr:street":"Derria St",
    "iso:country":"AU",
    "sg:address":"39 Derria St",
    "sg:city":"Canley Vale",
    "sg:classifiers":[
        {
            "category":"Professional",
            "subcategory":"Printing & Photocopies",
            "type":"Services"
        }
    ],
    "sg:phone":"+61 2 9728 1162",
    "sg:postcode":"2166",
    "sg:province":"NSW",
    "sg:tags":[
        "trophy"
    ],
    "wof:name":"Carratti Club & School Supplies",
    "wof:placetype":"venue"
},
  "geometry": {"coordinates":[150.93113708499999,-33.8875198364],"type":"Point"}
}