{
  "type": "Feature",
  "properties": {
    "addr:full":"31 Stanley St Peakhurst NSW 2210",
    "addr:housenumber":"31",
    "addr:postcode":"2210",
    "addr:street":"Stanley St",
    "iso:country":"AU",
    "sg:address":"31 Stanley St",
    "sg:city":"Peakhurst",
    "sg:classifiers":[
        {
            "category":"Transit Center",
            "subcategory":"Freight",
            "type":"Transportation"
        }
    ],
    "sg:phone":"+61 1800 224 496",
    "sg:postcode":"2210",
    "sg:province":"NSW",
    "sg:tags":[
        "forklift",
        "truck"
    ],
    "wof:name":"Hire Mobile Forklift",
    "wof:placetype":"venue"
},
  "geometry": {"coordinates":[151.06336999999999,-33.962482],"type":"Point"}
}