{
  "type": "Feature",
  "properties": {
    "iso:country":"AU",
    "sg:address":"84 Farm St",
    "sg:city":"Boorowa",
    "sg:classifiers":[
        {
            "category":"Farming",
            "subcategory":"Farm & Veterinary Services",
            "type":"Manufacturing & Wholesale Goods"
        }
    ],
    "sg:phone":"+61 2 6385 3395",
    "sg:postcode":"2586",
    "sg:province":"NSW",
    "sg:tags":[
        "shearing",
        "contractor"
    ],
    "wof:name":"Stephens J & D",
    "wof:placetype":"venue"
},
  "geometry": {"coordinates":[148.72406005900001,-34.4413833618],"type":"Point"}
}