{
  "type": "Feature",
  "properties": {
    "iso:country":"AU",
    "sg:address":"61 Vincent Rd",
    "sg:city":"Wangaratta",
    "sg:classifiers":[
        {
            "category":"Professional",
            "subcategory":"Computer Services",
            "type":"Services"
        }
    ],
    "sg:phone":"+61 3 5721 6655",
    "sg:postcode":"3677",
    "sg:province":"VIC",
    "sg:tags":[
        "training"
    ],
    "wof:name":"Marcom IT",
    "wof:placetype":"venue"
},
  "geometry": {"coordinates":[146.31517028799999,-36.3653717041],"type":"Point"}
}