{
  "type": "Feature",
  "properties": {
    "addr:full":"Courtney Drv Coomera QLD 4209",
    "addr:postcode":"4209",
    "addr:street":"Courtney Drv",
    "iso:country":"AU",
    "sg:address":"Courtney Drv",
    "sg:city":"Coomera",
    "sg:classifiers":[
        {
            "category":"Building & Trades",
            "subcategory":"Construction",
            "type":"Services"
        }
    ],
    "sg:phone":"+61 7 5573 2481",
    "sg:postcode":"4209",
    "sg:province":"QLD",
    "sg:tags":[
        "contractor"
    ],
    "wof:name":"Pezet K J & Co Pty Ltd",
    "wof:placetype":"venue"
},
  "geometry": {"coordinates":[153.280563355,-27.8651790619],"type":"Point"}
}