{
  "type": "Feature",
  "properties": {
    "iso:country":"AU",
    "sg:address":"PO Box 1254",
    "sg:city":"North Sydney",
    "sg:classifiers":[
        {
            "category":"Communications",
            "subcategory":"News Services",
            "type":"Services"
        }
    ],
    "sg:phone":"+61 2 9437 6841",
    "sg:postcode":"2059",
    "sg:province":"NSW",
    "sg:tags":[
        "information",
        "tourist",
        "attractions"
    ],
    "wof:name":"Ezy Guiding Tourism Marketing",
    "wof:placetype":"venue"
},
  "geometry": {"coordinates":[151.206482,-33.838261],"type":"Point"}
}