{
  "type": "Feature",
  "properties": {
    "addr:full":"17 Barvas St Ferny Grove QLD 4055",
    "addr:housenumber":"17",
    "addr:postcode":"4055",
    "addr:street":"Barvas St",
    "iso:country":"AU",
    "sg:address":"17 Barvas St",
    "sg:city":"Ferny Grove",
    "sg:classifiers":[
        {
            "category":"Building & Trades",
            "subcategory":"Cleaning & Sanitation",
            "type":"Services"
        }
    ],
    "sg:phone":"+61 419 789 085",
    "sg:postcode":"4055",
    "sg:province":"QLD",
    "sg:tags":[
        "window"
    ],
    "wof:name":"Glass With Class",
    "wof:placetype":"venue"
},
  "geometry": {"coordinates":[152.93099975600001,-27.3984928131],"type":"Point"}
}