{
  "type": "Feature",
  "properties": {
    "iso:country":"AU",
    "sg:address":"7 Berends Drv",
    "sg:city":"Dandenong South",
    "sg:classifiers":[
        {
            "category":"Shopping",
            "subcategory":"Crafts & Fabrics",
            "type":"Retail Goods"
        }
    ],
    "sg:phone":"+61 3 9706 5448",
    "sg:postcode":"3175",
    "sg:province":"VIC",
    "sg:tags":[
        "adhesive"
    ],
    "wof:name":"Fortis Adhesives & Coatings",
    "wof:placetype":"venue"
},
  "geometry": {"coordinates":[145.201416016,-38.0300064087],"type":"Point"}
}