{
  "type": "Feature",
  "properties": {
    "addr:full":"1038 Sandgate Rd Nundah QLD 4012",
    "addr:housenumber":"1038",
    "addr:postcode":"4012",
    "addr:street":"Sandgate Rd",
    "iso:country":"AU",
    "sg:address":"1038 Sandgate Rd",
    "sg:city":"Nundah",
    "sg:classifiers":[
        {
            "category":"Banks & Credit Unions",
            "subcategory":"Financial Services",
            "type":"Services"
        }
    ],
    "sg:phone":"+61 7 3266 2466",
    "sg:postcode":"4012",
    "sg:province":"QLD",
    "sg:tags":[
        "planning"
    ],
    "wof:name":"Ledger Financial Services",
    "wof:placetype":"venue"
},
  "geometry": {"coordinates":[153.05938720699999,-27.4085998535],"type":"Point"}
}