{
  "type": "Feature",
  "properties": {
    "iso:country":"AU",
    "sg:address":"32 Nicholls St",
    "sg:city":"Warwick Farm",
    "sg:classifiers":[
        {
            "category":"Building & Trades",
            "subcategory":"Construction",
            "type":"Services"
        }
    ],
    "sg:phone":"+61 2 9822 4490",
    "sg:postcode":"2170",
    "sg:province":"NSW",
    "sg:tags":[
        "installation",
        "air conditioning"
    ],
    "wof:name":"South Sea's Air Conditioning & Refridgeration Pty Ltd",
    "wof:placetype":"venue"
},
  "geometry": {"coordinates":[150.93223571799999,-33.9096183777],"type":"Point"}
}