{
  "type": "Feature",
  "properties": {
    "addr:full":"31 Inces Rd Armidale NSW 2350",
    "addr:housenumber":"31",
    "addr:postcode":"2350",
    "addr:street":"Inces Rd",
    "iso:country":"AU",
    "sg:address":"31 Inces Rd",
    "sg:city":"Armidale",
    "sg:classifiers":[
        {
            "category":"Home & Garden",
            "subcategory":"Household Appliances",
            "type":"Retail Goods"
        }
    ],
    "sg:phone":"+61 412 484 846",
    "sg:postcode":"2350",
    "sg:province":"NSW",
    "sg:tags":[
        "equipment",
        "gas"
    ],
    "wof:name":"Pete's Gas & Plumbing Pty Ltd",
    "wof:placetype":"venue"
},
  "geometry": {"coordinates":[151.69906616200001,-30.5219993591],"type":"Point"}
}