{
  "type": "Feature",
  "properties": {
    "iso:country":"AU",
    "sg:address":"3 / 37 - 41 Morayfield Rd",
    "sg:city":"Caboolture",
    "sg:classifiers":[
        {
            "category":"Shopping",
            "subcategory":"Pets & Pet Supplies",
            "type":"Retail Goods"
        }
    ],
    "sg:phone":"+61 7 5432 4811",
    "sg:postcode":"4510",
    "sg:province":"QLD",
    "sg:tags":[
        "equipment",
        "pre-stressing"
    ],
    "wof:name":"Southern Cross Pre Stressing",
    "wof:placetype":"venue"
},
  "geometry": {"coordinates":[152.950027,-27.093185],"type":"Point"}
}