{
  "type": "Feature",
  "properties": {
    "iso:country":"AU",
    "sg:address":"20 Brooman St",
    "sg:city":"Prestons",
    "sg:classifiers":[
        {
            "category":"Retail",
            "subcategory":"Repair Shop",
            "type":"Services"
        }
    ],
    "sg:phone":"+61 2 9826 8999",
    "sg:postcode":"2170",
    "sg:province":"NSW",
    "sg:tags":[
        "maintenance",
        "pool",
        "swimming"
    ],
    "wof:name":"Designer Pools & Spas",
    "wof:placetype":"venue"
},
  "geometry": {"coordinates":[150.85687255900001,-33.9525718689],"type":"Point"}
}