{
  "type": "Feature",
  "properties": {
    "iso:country":"AU",
    "sg:address":"1165 Frankston Dandenong Rd",
    "sg:city":"Carrum Downs",
    "sg:classifiers":[
        {
            "category":"Food & Beverages",
            "subcategory":"Groceries & Convenience Stores",
            "type":"Retail Goods"
        }
    ],
    "sg:phone":"+61 3 9782 8182",
    "sg:postcode":"3201",
    "sg:province":"VIC",
    "wof:name":"Food Quick",
    "wof:placetype":"venue"
},
  "geometry": {"coordinates":[145.177399,-38.094097],"type":"Point"}
}