{
  "type": "Feature",
  "properties": {
    "addr:full":"4/ 856 Leslie Drv North Albury NSW 2640",
    "addr:housenumber":"/ 856",
    "addr:postcode":"2640",
    "addr:street":"Leslie Drv North",
    "iso:country":"AU",
    "sg:address":"4/ 856 Leslie Drv",
    "sg:city":"North Albury",
    "sg:classifiers":[
        {
            "category":"Shopping",
            "type":"Retail Goods"
        }
    ],
    "sg:phone":"+61 407 261 489",
    "sg:postcode":"2640",
    "sg:province":"NSW",
    "sg:tags":[
        "equipment",
        "safety",
        "accessory"
    ],
    "wof:name":"A J Booth & Sons",
    "wof:placetype":"venue"
},
  "geometry": {"coordinates":[146.94432067899999,-36.064743042],"type":"Point"}
}