{
  "type": "Feature",
  "properties": {
    "addr:full":"Shop 2008 Westfield Shoppingtown Moggill Rd Indooroopilly QLD 4068",
    "addr:housenumber":"2008",
    "addr:postcode":"4068",
    "addr:street":"Westfield Shoppingtown Moggill Rd",
    "iso:country":"AU",
    "sg:address":"Shop 2008 Westfield Shoppingtown Moggill Rd",
    "sg:city":"Indooroopilly",
    "sg:classifiers":[
        {
            "category":"Shopping",
            "subcategory":"Clothing, Apparel, & Fashions",
            "type":"Retail Goods"
        }
    ],
    "sg:phone":"+61 7 3878 1219",
    "sg:postcode":"4068",
    "sg:province":"QLD",
    "sg:tags":[
        "lady",
        "wear"
    ],
    "wof:name":"David Lawrence",
    "wof:placetype":"venue"
},
  "geometry": {"coordinates":[152.974487305,-27.4973583221],"type":"Point"}
}