{
  "type": "Feature",
  "properties": {
    "addr:full":"13 fordson Rd Campbellfield VIC 3061",
    "addr:housenumber":"13",
    "addr:postcode":"3061",
    "addr:street":"Fordson Rd",
    "iso:country":"AU",
    "sg:address":"13 fordson Rd",
    "sg:city":"Campbellfield",
    "sg:classifiers":[
        {
            "category":"Home & Garden",
            "subcategory":"Furniture",
            "type":"Retail Goods"
        }
    ],
    "sg:phone":"+61 3 9359 5499",
    "sg:postcode":"3061",
    "sg:province":"VIC",
    "sg:tags":[
        "business"
    ],
    "wof:name":"DKL Australia Pty Ltd",
    "wof:placetype":"venue"
},
  "geometry": {"coordinates":[144.95800781200001,-37.6742362976],"type":"Point"}
}