{
  "type": "Feature",
  "properties": {
    "iso:country":"AU",
    "sg:address":"66 Wyndham St",
    "sg:city":"Roma",
    "sg:classifiers":[
        {
            "category":"Personal",
            "type":"Services"
        }
    ],
    "sg:phone":"+61 7 4622 1004",
    "sg:postcode":"4455",
    "sg:province":"QLD",
    "sg:tags":[
        "gift"
    ],
    "wof:name":"Floral Nook",
    "wof:placetype":"venue"
},
  "geometry": {"coordinates":[148.790817261,-26.5733261108],"type":"Point"}
}