{
  "type": "Feature",
  "properties": {
    "addr:full":"187 Nelson St Annandale NSW 2038",
    "addr:housenumber":"187",
    "addr:postcode":"2038",
    "addr:street":"Nelson St",
    "iso:country":"AU",
    "sg:address":"187 Nelson St",
    "sg:city":"Annandale",
    "sg:classifiers":[
        {
            "category":"Building & Trades",
            "subcategory":"Cleaning & Sanitation",
            "type":"Services"
        }
    ],
    "sg:phone":"+61 2 9660 5937",
    "sg:postcode":"2038",
    "sg:province":"NSW",
    "sg:tags":[
        "asbestos",
        "treatment",
        "removal"
    ],
    "wof:name":"R.O. Steel Roofing Pty Ltd",
    "wof:placetype":"venue"
},
  "geometry": {"coordinates":[151.17427063,-33.881187439],"type":"Point"}
}