{
  "type": "Feature",
  "properties": {
    "iso:country":"AU",
    "sg:address":"47 Kirkwood Rd",
    "sg:city":"Tweed Heads South",
    "sg:classifiers":[
        {
            "category":"Health Services",
            "subcategory":"Dentist",
            "type":"Services"
        }
    ],
    "sg:phone":"+61 7 5523 1666",
    "sg:postcode":"2486",
    "sg:province":"NSW",
    "sg:tags":[
        "dental",
        "emergency"
    ],
    "wof:name":"Leo Wilkinson B.D.S Dental Surgeon",
    "wof:placetype":"venue"
},
  "geometry": {"coordinates":[153.544433594,-28.1984481812],"type":"Point"}
}