{
  "type": "Feature",
  "properties": {
    "iso:country":"AU",
    "sg:address":"288A Cambridge St",
    "sg:city":"Wembley",
    "sg:classifiers":[
        {
            "category":"Shopping",
            "subcategory":"Antiques",
            "type":"Retail Goods"
        }
    ],
    "sg:phone":"+61 8 9473 1111",
    "sg:postcode":"6014",
    "sg:province":"WA",
    "wof:name":"Russells Antique & Collectables",
    "wof:placetype":"venue"
},
  "geometry": {"coordinates":[115.815879822,-31.9406147003],"type":"Point"}
}