{
  "type": "Feature",
  "properties": {
    "iso:country":"AU",
    "sg:address":"PO Box 107",
    "sg:city":"Marden",
    "sg:classifiers":[
        {
            "category":"Personal",
            "subcategory":"Beauty Salon",
            "type":"Services"
        }
    ],
    "sg:phone":"+61 427 805 884",
    "sg:postcode":"5070",
    "sg:province":"SA",
    "sg:tags":[
        "supply",
        "artist",
        "make-up"
    ],
    "wof:name":"Anita Marchesi",
    "wof:placetype":"venue"
},
  "geometry": {"coordinates":[138.63870239299999,-34.8968696594],"type":"Point"}
}