{
  "type": "Feature",
  "properties": {
    "addr:full":"1 Erli Crt Blackburn VIC 3130",
    "addr:housenumber":"1",
    "addr:postcode":"3130",
    "addr:street":"Erli Crt",
    "iso:country":"AU",
    "sg:address":"1 Erli Crt",
    "sg:city":"Blackburn",
    "sg:classifiers":[
        {
            "category":"Banks & Credit Unions",
            "subcategory":"Bank",
            "type":"Services"
        }
    ],
    "sg:phone":"+61 3 9038 8564",
    "sg:postcode":"3130",
    "sg:province":"VIC",
    "sg:tags":[
        "broker",
        "mortgage"
    ],
    "wof:name":"Smartline",
    "wof:placetype":"venue"
},
  "geometry": {"coordinates":[145.15538024899999,-37.814617157],"type":"Point"}
}