{
  "type": "Feature",
  "properties": {
    "addr:full":"1 Murray Valley Hwy Echuca VIC 3564",
    "addr:housenumber":"1",
    "addr:postcode":"3564",
    "addr:street":"Murray Valley Hwy",
    "iso:country":"AU",
    "sg:address":"1 Murray Valley Hwy",
    "sg:city":"Echuca",
    "sg:classifiers":[
        {
            "category":"Building & Trades",
            "subcategory":"Construction",
            "type":"Services"
        }
    ],
    "sg:phone":"+61 3 5482 5186",
    "sg:postcode":"3564",
    "sg:province":"VIC",
    "sg:tags":[
        "pool",
        "swimming"
    ],
    "wof:name":"Naughtons Pools & Spas",
    "wof:placetype":"venue"
},
  "geometry": {"coordinates":[144.72926330600001,-36.1385993958],"type":"Point"}
}