{
  "type": "Feature",
  "properties": {
    "addr:full":"7 Wavehill Ave Windsor Downs NSW 2756",
    "addr:housenumber":"7",
    "addr:postcode":"2756",
    "addr:street":"Wavehill Ave",
    "iso:country":"AU",
    "sg:address":"7 Wavehill Ave",
    "sg:city":"Windsor Downs",
    "sg:classifiers":[
        {
            "category":"Banks & Credit Unions",
            "subcategory":"Financial Services",
            "type":"Services"
        }
    ],
    "sg:phone":"+61 2 4572 0322",
    "sg:postcode":"2756",
    "sg:province":"NSW",
    "sg:tags":[
        "loan",
        "finance",
        "mortgage"
    ],
    "wof:name":"City Mutual Home Loans Pty Ltd",
    "wof:placetype":"venue"
},
  "geometry": {"coordinates":[150.810745239,-33.6630516052],"type":"Point"}
}