{
  "type": "Feature",
  "properties": {
    "addr:full":"36 Unley Rd Unley SA 5061",
    "addr:housenumber":"36",
    "addr:postcode":"5061",
    "addr:street":"Unley Rd",
    "iso:country":"AU",
    "sg:address":"36 Unley Rd",
    "sg:city":"Unley",
    "sg:classifiers":[
        {
            "category":"Banks & Credit Unions",
            "subcategory":"Bank",
            "type":"Services"
        }
    ],
    "sg:phone":"+61 8 8272 4333",
    "sg:postcode":"5061",
    "sg:province":"SA",
    "sg:tags":[
        "broker",
        "mortgage"
    ],
    "wof:name":"Money Supermarket",
    "wof:placetype":"venue"
},
  "geometry": {"coordinates":[138.60679626500001,-34.9430999756],"type":"Point"}
}