{
  "type": "Feature",
  "properties": {
    "addr:full":"PO Box 740 Gordon NSW 2072",
    "addr:postcode":"2072",
    "iso:country":"AU",
    "sg:address":"PO Box 740",
    "sg:city":"Gordon",
    "sg:classifiers":[
        {
            "category":"Professional",
            "subcategory":"Detective & Security Services",
            "type":"Services"
        }
    ],
    "sg:phone":"+61 2 9412 4477",
    "sg:postcode":"2072",
    "sg:province":"NSW",
    "sg:tags":[
        "consultant",
        "system"
    ],
    "wof:name":"Cardax Australia Pty Ltd",
    "wof:placetype":"venue"
},
  "geometry": {"coordinates":[151.155685425,-33.7573509216],"type":"Point"}
}