{
  "type": "Feature",
  "properties": {
    "addr:full":"Apt 13/21- 23 Koorala St Manly Vale NSW 2093",
    "addr:housenumber":"/;23",
    "addr:postcode":"2093",
    "addr:street":"21;St",
    "iso:country":"AU",
    "sg:address":"Apt 13/21- 23 Koorala St",
    "sg:city":"Manly Vale",
    "sg:classifiers":[
        {
            "category":"Education",
            "subcategory":"Dance Studio",
            "type":"Public Place"
        }
    ],
    "sg:phone":"+61 2 9948 9563",
    "sg:postcode":"2093",
    "sg:province":"NSW",
    "sg:tags":[
        "venue",
        "tuition"
    ],
    "wof:name":"Constantine Ballroom Dancing",
    "wof:placetype":"venue"
},
  "geometry": {"coordinates":[151.26864624000001,-33.7856178284],"type":"Point"}
}