{
  "type": "Feature",
  "properties": {
    "addr:full":"43 Burrelli St Wollongong NSW 2500",
    "addr:housenumber":"43",
    "addr:postcode":"2500",
    "addr:street":"Burrelli St",
    "iso:country":"AU",
    "sg:address":"43 Burrelli St",
    "sg:city":"Wollongong",
    "sg:classifiers":[
        {
            "category":"Wholesale",
            "subcategory":"Medical Equipment & Supplies",
            "type":"Manufacturing & Wholesale Goods"
        }
    ],
    "sg:phone":"+61 2 4226 0161",
    "sg:postcode":"2500",
    "sg:province":"NSW",
    "sg:tags":[
        "aids",
        "hearing"
    ],
    "wof:name":"Australian Hearing",
    "wof:placetype":"venue"
},
  "geometry": {"coordinates":[150.89819299999999,-34.426872],"type":"Point"}
}