{
  "type": "Feature",
  "properties": {
    "addr:full":"Wilson Rd Hinchinbrook NSW 2168",
    "addr:postcode":"2168",
    "addr:street":"Wilson Rd",
    "iso:country":"AU",
    "sg:address":"Wilson Rd",
    "sg:city":"Hinchinbrook",
    "sg:classifiers":[
        {
            "category":"Education",
            "subcategory":"School",
            "type":"Public Place"
        }
    ],
    "sg:phone":"+61 2 9607 4222",
    "sg:postcode":"2168",
    "sg:province":"NSW",
    "sg:tags":[
        "state",
        "-",
        "nsw"
    ],
    "wof:name":"Hoxton Park High School",
    "wof:placetype":"venue"
},
  "geometry": {"coordinates":[150.86488342300001,-33.9112243652],"type":"Point"}
}