{
  "type": "Feature",
  "properties": {
    "addr:full":"Cnr Cumberland Hwy & John St Cabramatta NSW 2166",
    "addr:postcode":"2166",
    "addr:street":"Cnr Cumberland Hwy & John St",
    "iso:country":"AU",
    "sg:address":"Cnr Cumberland Hwy & John St",
    "sg:city":"Cabramatta",
    "sg:classifiers":[
        {
            "category":"Food & Beverages",
            "subcategory":"Groceries & Convenience Stores",
            "type":"Retail Goods"
        }
    ],
    "sg:phone":"+61 2 9724 0409",
    "sg:postcode":"2166",
    "sg:province":"NSW",
    "wof:name":"Shell Select",
    "wof:placetype":"venue"
},
  "geometry": {"coordinates":[150.922607422,-33.8926734924],"type":"Point"}
}