{
  "type": "Feature",
  "properties": {
    "iso:country":"AU",
    "sg:address":"High St",
    "sg:city":"Kulin",
    "sg:classifiers":[
        {
            "category":"Wholesale",
            "subcategory":"Farm Supplies",
            "type":"Manufacturing & Wholesale Goods"
        }
    ],
    "sg:phone":"+61 8 9880 1292",
    "sg:postcode":"6365",
    "sg:province":"WA",
    "sg:tags":[
        "equipment"
    ],
    "wof:name":"Landmark",
    "wof:placetype":"venue"
},
  "geometry": {"coordinates":[118.15548699999999,-32.668873],"type":"Point"}
}