{
  "type": "Feature",
  "properties": {
    "addr:full":"Goodes Rd Echunga SA 5153",
    "addr:postcode":"5153",
    "addr:street":"Goodes Rd",
    "iso:country":"AU",
    "sg:address":"Goodes Rd",
    "sg:city":"Echunga",
    "sg:classifiers":[
        {
            "category":"Building & Trades",
            "subcategory":"Plumbing",
            "type":"Services"
        }
    ],
    "sg:phone":"+61 418 824 478",
    "sg:postcode":"5153",
    "sg:province":"SA",
    "sg:tags":[
        "plumber",
        "gasfitters"
    ],
    "wof:name":"Steve Little Plumbing",
    "wof:placetype":"venue"
},
  "geometry": {"coordinates":[138.80796814000001,-35.1124458313],"type":"Point"}
}