{
  "type": "Feature",
  "properties": {
    "iso:country":"AU",
    "sg:address":"2 Bradford St",
    "sg:city":"Mt Lawley",
    "sg:classifiers":[
        {
            "category":"Education",
            "subcategory":"University",
            "type":"Public Place"
        }
    ],
    "sg:phone":"+61 13 43 28",
    "sg:postcode":"6050",
    "sg:province":"WA",
    "sg:tags":[
        "college",
        "tertiary"
    ],
    "wof:name":"Edith Cowan University",
    "wof:placetype":"venue"
},
  "geometry": {"coordinates":[115.866737366,-31.9212703705],"type":"Point"}
}