{
  "type": "Feature",
  "properties": {
    "iso:country":"AU",
    "sg:address":"138 Spit Rd",
    "sg:city":"Mosman",
    "sg:classifiers":[
        {
            "category":"Professional",
            "subcategory":"Art Services",
            "type":"Services"
        }
    ],
    "sg:phone":"+61 2 9969 9859",
    "sg:postcode":"2088",
    "sg:province":"NSW",
    "sg:tags":[
        "interior",
        "decorator"
    ],
    "wof:name":"Stanton Furnishings",
    "wof:placetype":"venue"
},
  "geometry": {"coordinates":[151.24380493199999,-33.8185005188],"type":"Point"}
}