{
  "type": "Feature",
  "properties": {
    "addr:full":"Shop 22, Mt Gravatt Foodworld, Creek Rd Mt Gravatt QLD 4122",
    "addr:housenumber":"shop 22",
    "addr:postcode":"4122",
    "addr:street":"Mt Gravatt;Creek Rd",
    "iso:country":"AU",
    "sg:address":"Shop 22, Mt Gravatt Foodworld, Creek Rd",
    "sg:city":"Mt Gravatt",
    "sg:classifiers":[
        {
            "category":"Food & Beverages",
            "subcategory":"Liquor & Beverages",
            "type":"Retail Goods"
        }
    ],
    "sg:phone":"+61 7 3849 5016",
    "sg:postcode":"4122",
    "sg:province":"QLD",
    "sg:tags":[
        "store"
    ],
    "wof:name":"Holland Park Hotel",
    "wof:placetype":"venue"
},
  "geometry": {"coordinates":[153.08079528799999,-27.5386734009],"type":"Point"}
}