{
  "type": "Feature",
  "properties": {
    "iso:country":"AU",
    "sg:address":"1 Beulah Rd",
    "sg:city":"Norwood",
    "sg:classifiers":[
        {
            "category":"Home & Garden",
            "subcategory":"Home Furnishings",
            "type":"Retail Goods"
        }
    ],
    "sg:phone":"+61 8 8362 8455",
    "sg:postcode":"5067",
    "sg:province":"SA",
    "sg:tags":[
        "candle"
    ],
    "wof:name":"Aussie Imports Pty Ltd",
    "wof:placetype":"venue"
},
  "geometry": {"coordinates":[138.62322998100001,-34.9214897156],"type":"Point"}
}