{
  "type": "Feature",
  "properties": {
    "iso:country":"AU",
    "sg:address":"64 Cunninghame St",
    "sg:city":"Sale",
    "sg:classifiers":[
        {
            "category":"Insurance",
            "subcategory":"Hazard Insurance",
            "type":"Services"
        }
    ],
    "sg:phone":"+61 3 5143 3333",
    "sg:postcode":"3850",
    "sg:province":"VIC",
    "sg:tags":[
        "fire",
        "accident",
        "marine"
    ],
    "wof:name":"GIO General Ltd",
    "wof:placetype":"venue"
},
  "geometry": {"coordinates":[147.06385803200001,-38.1075325012],"type":"Point"}
}