{
  "type": "Feature",
  "properties": {
    "addr:full":"16 Annie St Windsor QLD 4030",
    "addr:housenumber":"16",
    "addr:postcode":"4030",
    "addr:street":"Annie St",
    "iso:country":"AU",
    "sg:address":"16 Annie St",
    "sg:city":"Windsor",
    "sg:classifiers":[
        {
            "category":"Professional",
            "subcategory":"Computer Services",
            "type":"Services"
        }
    ],
    "sg:phone":"+61 7 3861 1902",
    "sg:postcode":"4030",
    "sg:province":"QLD",
    "sg:tags":[
        "consultant",
        "system"
    ],
    "wof:name":"Sweetser Consulting and Technologies Pty Ltd",
    "wof:placetype":"venue"
},
  "geometry": {"coordinates":[153.03402700000001,-27.427088],"type":"Point"}
}