{
  "type": "Feature",
  "properties": {
    "iso:country":"AU",
    "sg:address":"52 Tergur Crs",
    "sg:city":"Caringbah",
    "sg:classifiers":[
        {
            "category":"Professional",
            "type":"Services"
        }
    ],
    "sg:phone":"+61 2 9524 5611",
    "sg:postcode":"2229",
    "sg:province":"NSW",
    "sg:tags":[
        "marine",
        "contractor"
    ],
    "wof:name":"Nautical Electrics",
    "wof:placetype":"venue"
},
  "geometry": {"coordinates":[151.12121582,-34.0429000854],"type":"Point"}
}