{
  "type": "Feature",
  "properties": {
    "iso:country":"AU",
    "sg:address":"Level1/ 55 Foveaux St",
    "sg:city":"Surry Hills",
    "sg:classifiers":[
        {
            "category":"Government",
            "subcategory":"Post Office",
            "type":"Public Place"
        }
    ],
    "sg:phone":"+61 2 9211 4111",
    "sg:postcode":"2010",
    "sg:province":"NSW",
    "sg:tags":[
        "yoga"
    ],
    "sg:website":"http://www.bodymindlife.com",
    "wof:name":"BodyMindLife Yoga",
    "wof:placetype":"venue"
},
  "geometry": {"coordinates":[151.20985412600001,-33.884185791],"type":"Point"}
}