{
  "type": "Feature",
  "properties": {
    "addr:full":"25 Campbell Drv Wahroonga NSW 2076",
    "addr:housenumber":"25",
    "addr:postcode":"2076",
    "addr:street":"Campbell Drv",
    "iso:country":"AU",
    "sg:address":"25 Campbell Drv",
    "sg:city":"Wahroonga",
    "sg:classifiers":[
        {
            "category":"Communications",
            "type":"Services"
        }
    ],
    "sg:phone":"+61 2 9489 8973",
    "sg:postcode":"2076",
    "sg:province":"NSW",
    "sg:tags":[
        "data"
    ],
    "wof:name":"Electrical Data & Fibre Optic Systems Pty Ltd",
    "wof:placetype":"venue"
},
  "geometry": {"coordinates":[151.10644531200001,-33.7320976257],"type":"Point"}
}