{
  "type": "Feature",
  "properties": {
    "iso:country":"AU",
    "sg:address":"Unit 1, 7 Baretta Rd",
    "sg:city":"Wangara",
    "sg:classifiers":[
        {
            "category":"Personal",
            "type":"Services"
        }
    ],
    "sg:phone":"+61 8 9401 6121",
    "sg:postcode":"6065",
    "sg:province":"WA",
    "sg:tags":[
        "gift"
    ],
    "wof:name":"Gifts On The Hop",
    "wof:placetype":"venue"
},
  "geometry": {"coordinates":[115.81649017300001,-31.7919712067],"type":"Point"}
}