{
  "type": "Feature",
  "properties": {
    "iso:country":"AU",
    "sg:address":"171 Murray St",
    "sg:city":"Gawler",
    "sg:classifiers":[
        {
            "category":"Professional",
            "subcategory":"Accounting & Tax Preparation",
            "type":"Services"
        }
    ],
    "sg:phone":"+61 8 8523 5200",
    "sg:postcode":"5118",
    "sg:province":"SA",
    "sg:tags":[
        "consultant",
        "taxation"
    ],
    "wof:name":"Kangaroo Flat Accounting & Taxation Services",
    "wof:placetype":"venue"
},
  "geometry": {"coordinates":[138.74913,-34.594151],"type":"Point"}
}