{
  "type": "Feature",
  "properties": {
    "addr:full":"Derby St Swanbourne WA 6010",
    "addr:postcode":"6010",
    "addr:street":"Derby St",
    "iso:country":"AU",
    "sg:address":"Derby St",
    "sg:city":"Swanbourne",
    "sg:classifiers":[
        {
            "category":"Education",
            "subcategory":"Kindergarten",
            "type":"Public Place"
        }
    ],
    "sg:phone":"+61 8 9385 5033",
    "sg:postcode":"6010",
    "sg:province":"WA",
    "sg:tags":[
        "pre-schools"
    ],
    "wof:name":"Swanbourne Primary School",
    "wof:placetype":"venue"
},
  "geometry": {"coordinates":[115.769309998,-31.9776363373],"type":"Point"}
}