{
  "type": "Feature",
  "properties": {
    "iso:country":"AU",
    "sg:address":"4435 Thomas St",
    "sg:city":"Chidlow",
    "sg:classifiers":[
        {
            "category":"Real Estate",
            "subcategory":"Real Estate Agent",
            "type":"Services"
        }
    ],
    "sg:phone":"+61 8 9572 4113",
    "sg:postcode":"6556",
    "sg:province":"WA",
    "wof:name":"Parkview Real Estate",
    "wof:placetype":"venue"
},
  "geometry": {"coordinates":[116.26719665500001,-31.8624477386],"type":"Point"}
}