{
  "type": "Feature",
  "properties": {
    "addr:full":"14 Burns Crt Middlemount QLD 4746",
    "addr:housenumber":"14",
    "addr:postcode":"4746",
    "addr:street":"Burns Crt",
    "iso:country":"AU",
    "sg:address":"14 Burns Crt",
    "sg:city":"Middlemount",
    "sg:classifiers":[
        {
            "category":"Sports & Exercise",
            "subcategory":"Sports Center",
            "type":"Entertainment"
        }
    ],
    "sg:phone":"+61 7 4985 9358",
    "sg:postcode":"4746",
    "sg:province":"QLD",
    "sg:tags":[
        "ground"
    ],
    "wof:name":"Middlemount Leisure Centre",
    "wof:placetype":"venue"
},
  "geometry": {"coordinates":[148.70164500000001,-22.809156],"type":"Point"}
}