{
  "type": "Feature",
  "properties": {
    "addr:full":"Lot 17 Middle Farm Rd Armidale NSW 2350",
    "addr:postcode":"2350",
    "addr:street":"Farm Rd",
    "iso:country":"AU",
    "sg:address":"Lot 17 Middle Farm Rd",
    "sg:city":"Armidale",
    "sg:classifiers":[
        {
            "category":"Building & Trades",
            "subcategory":"Construction",
            "type":"Services"
        }
    ],
    "sg:phone":"+61 2 6775 3750",
    "sg:postcode":"2350",
    "sg:province":"NSW",
    "sg:tags":[
        "contractor"
    ],
    "wof:name":"Sauer T J & L M",
    "wof:placetype":"venue"
},
  "geometry": {"coordinates":[151.73773193400001,-30.5395908356],"type":"Point"}
}