{
  "type": "Feature",
  "properties": {
    "addr:full":"33 Watagan Forrest Drv Jilliby NSW 2259",
    "addr:housenumber":"33",
    "addr:postcode":"2259",
    "addr:street":"Watagan Forrest Drv",
    "iso:country":"AU",
    "sg:address":"33 Watagan Forrest Drv",
    "sg:city":"Jilliby",
    "sg:classifiers":[
        {
            "category":"Building & Trades",
            "subcategory":"Construction",
            "type":"Services"
        }
    ],
    "sg:phone":"+61 2 4353 9094",
    "sg:postcode":"2259",
    "sg:province":"NSW",
    "sg:tags":[
        "contractor"
    ],
    "wof:name":"Broomfield K M",
    "wof:placetype":"venue"
},
  "geometry": {"coordinates":[151.381393433,-33.2559776306],"type":"Point"}
}