{
  "type": "Feature",
  "properties": {
    "iso:country":"AU",
    "sg:address":"413 George St",
    "sg:city":"Sydney",
    "sg:classifiers":[
        {
            "category":"Shopping",
            "subcategory":"Shoes",
            "type":"Retail Goods"
        }
    ],
    "sg:phone":"+61 2 9262 6380",
    "sg:postcode":"2000",
    "sg:province":"NSW",
    "sg:tags":[
        "footwear"
    ],
    "wof:name":"American Shoe Store Pty Ltd",
    "wof:placetype":"venue"
},
  "geometry": {"coordinates":[151.206832886,-33.8702735901],"type":"Point"}
}