{
  "type": "Feature",
  "properties": {
    "addr:full":"76 Bathurst St Launceston TAS 7250",
    "addr:housenumber":"76",
    "addr:postcode":"7250",
    "addr:street":"Bathurst St",
    "iso:country":"AU",
    "sg:address":"76 Bathurst St",
    "sg:city":"Launceston",
    "sg:classifiers":[
        {
            "category":"Home & Garden",
            "subcategory":"Garden Supply",
            "type":"Retail Goods"
        }
    ],
    "sg:phone":"+61 3 6331 3682",
    "sg:postcode":"7250",
    "sg:province":"TAS",
    "sg:tags":[
        "fertilizer"
    ],
    "wof:name":"Waratah-Launceston Pty Ltd",
    "wof:placetype":"venue"
},
  "geometry": {"coordinates":[147.13619995100001,-41.4425201416],"type":"Point"}
}