{
  "type": "Feature",
  "properties": {
    "iso:country":"AU",
    "sg:address":"184 Little Forest Rd",
    "sg:city":"Milton",
    "sg:classifiers":[
        {
            "category":"Retail",
            "subcategory":"Auto Repair",
            "type":"Services"
        }
    ],
    "sg:phone":"+61 2 4456 4364",
    "sg:postcode":"2538",
    "sg:province":"NSW",
    "sg:tags":[
        "repairer",
        "motor",
        "engineer"
    ],
    "wof:name":"Terry's Automotive Repairs & Rebuilds",
    "wof:placetype":"venue"
},
  "geometry": {"coordinates":[150.39944457999999,-35.2963523865],"type":"Point"}
}