{
  "type": "Feature",
  "properties": {
    "addr:full":"42 Mawby Rd Bentleigh East VIC 3165",
    "addr:housenumber":"42",
    "addr:postcode":"3165",
    "addr:street":"Mawby Rd",
    "iso:country":"AU",
    "sg:address":"42 Mawby Rd",
    "sg:city":"Bentleigh East",
    "sg:classifiers":[
        {
            "category":"Arts & Performance",
            "subcategory":"Theater",
            "type":"Entertainment"
        }
    ],
    "sg:phone":"+61 3 9579 5584",
    "sg:postcode":"3165",
    "sg:province":"VIC",
    "sg:tags":[
        "theatrical",
        "supply"
    ],
    "wof:name":"Imported Theatre Fabrics",
    "wof:placetype":"venue"
},
  "geometry": {"coordinates":[145.05377197300001,-37.9293136597],"type":"Point"}
}