{
  "type": "Feature",
  "properties": {
    "iso:country":"AU",
    "sg:address":"Lot 8 South Western Hwy",
    "sg:city":"Mullalyup",
    "sg:classifiers":[
        {
            "category":"Farming",
            "subcategory":"Berry Farm",
            "type":"Manufacturing & Wholesale Goods"
        }
    ],
    "sg:phone":"+61 8 9764 1117",
    "sg:postcode":"6252",
    "sg:province":"WA",
    "sg:tags":[
        "fruit",
        "grower"
    ],
    "wof:name":"Gubler NK & PG",
    "wof:placetype":"venue"
},
  "geometry": {"coordinates":[115.94468689,-33.7423095703],"type":"Point"}
}