{
  "type": "Feature",
  "properties": {
    "iso:country":"AU",
    "sg:address":"40 Orchard Rd",
    "sg:city":"Brookvale",
    "sg:classifiers":[
        {
            "category":"Industrial Area",
            "type":"Public Place"
        }
    ],
    "sg:phone":"+61 2 9939 1000",
    "sg:postcode":"2100",
    "sg:province":"NSW",
    "sg:tags":[
        "protective",
        "clothing"
    ],
    "wof:name":"BOC",
    "wof:placetype":"venue"
},
  "geometry": {"coordinates":[151.27322387699999,-33.7655181885],"type":"Point"}
}