{
  "type": "Feature",
  "properties": {
    "addr:full":"Shop 5, Woolworths Mall, Mt Barker Road Shop 5 Mt Barker Rd Stirling SA 5152",
    "addr:housenumber":"shop 5;5",
    "addr:postcode":"5152",
    "addr:street":"Mall;Barker;Mt Barker Rd",
    "iso:country":"AU",
    "sg:address":"Shop 5, Woolworths Mall, Mt Barker Road Shop 5 Mt Barker Rd",
    "sg:city":"Stirling",
    "sg:classifiers":[
        {
            "category":"Personal",
            "type":"Services"
        }
    ],
    "sg:phone":"+61 8 8370 1255",
    "sg:postcode":"5152",
    "sg:province":"SA",
    "sg:tags":[
        "gift"
    ],
    "wof:name":"Adelaide Hills Flowers",
    "wof:placetype":"venue"
},
  "geometry": {"coordinates":[138.72251892099999,-35.0080223083],"type":"Point"}
}