{
  "type": "Feature",
  "properties": {
    "addr:full":"Shop 15 John St West Pakenham VIC 3810",
    "addr:housenumber":"shop 15",
    "addr:postcode":"3810",
    "addr:street":"John St West",
    "iso:country":"AU",
    "sg:address":"Shop 15 John St",
    "sg:city":"West Pakenham",
    "sg:classifiers":[
        {
            "category":"Personal",
            "subcategory":"Beauty Salon",
            "type":"Services"
        }
    ],
    "sg:phone":"+61 3 5941 1438",
    "sg:postcode":"3810",
    "sg:province":"VIC",
    "sg:tags":[
        "hairdresser"
    ],
    "wof:name":"Anthony Deanes Coiffure",
    "wof:placetype":"venue"
},
  "geometry": {"coordinates":[145.482574,-38.077003],"type":"Point"}
}