{
  "type": "Feature",
  "properties": {
    "addr:full":"8 Toovis Ave Hope Valley SA 5090",
    "addr:housenumber":"8",
    "addr:postcode":"5090",
    "addr:street":"Toovis Ave",
    "iso:country":"AU",
    "sg:address":"8 Toovis Ave",
    "sg:city":"Hope Valley",
    "sg:classifiers":[
        {
            "category":"Coffee & Tea",
            "type":"Food & Drink"
        }
    ],
    "sg:phone":"+61 417 853 085",
    "sg:postcode":"5090",
    "sg:province":"SA",
    "sg:tags":[
        "kayak",
        "canoe"
    ],
    "wof:name":"Canoe Sport",
    "wof:placetype":"venue"
},
  "geometry": {"coordinates":[138.71443176299999,-34.837688446],"type":"Point"}
}