{
  "type": "Feature",
  "properties": {
    "iso:country":"AU",
    "sg:address":"1730 Main North Rd",
    "sg:city":"Salisbury Plain",
    "sg:classifiers":[
        {
            "category":"Retail",
            "subcategory":"Auto Rental",
            "type":"Services"
        }
    ],
    "sg:phone":"+61 8 8258 6155",
    "sg:postcode":"5109",
    "sg:province":"SA",
    "sg:tags":[
        "bus",
        "truck"
    ],
    "wof:name":"Richard Stevens Hire Pty Ltd",
    "wof:placetype":"venue"
},
  "geometry": {"coordinates":[138.66665649399999,-34.7690811157],"type":"Point"}
}