{
  "type": "Feature",
  "properties": {
    "addr:full":"253 Tapleys Hill Rd Seaton SA 5023",
    "addr:housenumber":"253",
    "addr:postcode":"5023",
    "addr:street":"Tapleys Hill Rd",
    "iso:country":"AU",
    "sg:address":"253 Tapleys Hill Rd",
    "sg:city":"Seaton",
    "sg:classifiers":[
        {
            "category":"Restaurant",
            "type":"Food & Drink"
        }
    ],
    "sg:phone":"+61 8 8345 4645",
    "sg:postcode":"5023",
    "sg:province":"SA",
    "sg:website":"http://www.seatonhotel.com.au",
    "wof:name":"Seaton Hotel",
    "wof:placetype":"venue"
},
  "geometry": {"coordinates":[138.51380920400001,-34.89087677],"type":"Point"}
}