{
  "type": "Feature",
  "properties": {
    "addr:full":"U 6/ 37 Aldenhoven Rd Lonsdale SA 5160",
    "addr:postcode":"5160",
    "addr:street":"37 Aldenhoven Rd",
    "iso:country":"AU",
    "sg:address":"U 6/ 37 Aldenhoven Rd",
    "sg:city":"Lonsdale",
    "sg:classifiers":[
        {
            "category":"Building & Trades",
            "subcategory":"Construction",
            "type":"Services"
        }
    ],
    "sg:phone":"+61 8 8186 4611",
    "sg:postcode":"5160",
    "sg:province":"SA",
    "sg:tags":[
        "window",
        "tinting"
    ],
    "wof:name":"Lonsdale Window Tinting",
    "wof:placetype":"venue"
},
  "geometry": {"coordinates":[138.497192383,-35.1158638],"type":"Point"}
}