{
  "type": "Feature",
  "properties": {
    "iso:country":"AU",
    "sg:address":"191 Burgundy St",
    "sg:city":"Heidelberg",
    "sg:classifiers":[
        {
            "category":"Restaurant",
            "type":"Food & Drink"
        }
    ],
    "sg:phone":"+61 3 9459 3151",
    "sg:postcode":"3084",
    "sg:province":"VIC",
    "wof:name":"Cellini Lounge Bar",
    "wof:placetype":"venue"
},
  "geometry": {"coordinates":[145.063430786,-37.7559928894],"type":"Point"}
}