{
  "type": "Feature",
  "properties": {
    "addr:full":"511 Whitehorse Rd Mitcham VIC 3132",
    "addr:housenumber":"511",
    "addr:postcode":"3132",
    "addr:street":"Whitehorse Rd",
    "iso:country":"AU",
    "sg:address":"511 Whitehorse Rd",
    "sg:city":"Mitcham",
    "sg:classifiers":[
        {
            "category":"Travel",
            "subcategory":"Travel Agent",
            "type":"Entertainment"
        }
    ],
    "sg:phone":"+61 1300 130 840",
    "sg:postcode":"3132",
    "sg:province":"VIC",
    "sg:tags":[
        "consultant"
    ],
    "wof:name":"Alaska Holidays & Vacations",
    "wof:placetype":"venue"
},
  "geometry": {"coordinates":[145.193084717,-37.816116333],"type":"Point"}
}