{
  "type": "Feature",
  "properties": {
    "addr:full":"16 G New St Frankston VIC 3199",
    "addr:housenumber":"16 g",
    "addr:postcode":"3199",
    "addr:street":"New St",
    "iso:country":"AU",
    "sg:address":"16 G New St",
    "sg:city":"Frankston",
    "sg:classifiers":[
        {
            "category":"Professional",
            "subcategory":"Art Services",
            "type":"Services"
        }
    ],
    "sg:phone":"+61 3 9783 2880",
    "sg:postcode":"3199",
    "sg:province":"VIC",
    "sg:tags":[
        "picture",
        "frame",
        "framing"
    ],
    "wof:name":"Artwize Picture Framing",
    "wof:placetype":"venue"
},
  "geometry": {"coordinates":[145.12179565400001,-38.1415710449],"type":"Point"}
}