{
  "type": "Feature",
  "properties": {
    "addr:full":"Mahogany Drv Caboolture QLD 4510",
    "addr:postcode":"4510",
    "addr:street":"Mahogany Drv",
    "iso:country":"AU",
    "sg:address":"Mahogany Drv",
    "sg:city":"Caboolture",
    "sg:classifiers":[
        {
            "category":"Utilities",
            "subcategory":"Water",
            "type":"Services"
        }
    ],
    "sg:phone":"+61 7 5499 0169",
    "sg:postcode":"4510",
    "sg:province":"QLD",
    "sg:tags":[
        "hot",
        "system"
    ],
    "wof:name":"Bill B's Electrical Services",
    "wof:placetype":"venue"
},
  "geometry": {"coordinates":[152.93753100000001,-27.054642],"type":"Point"}
}