{
  "type": "Feature",
  "properties": {
    "addr:full":"164 Colchester Rd Kilsyth VIC 3137",
    "addr:housenumber":"164",
    "addr:postcode":"3137",
    "addr:street":"Colchester Rd",
    "iso:country":"AU",
    "sg:address":"164 Colchester Rd",
    "sg:city":"Kilsyth",
    "sg:classifiers":[
        {
            "category":"Wholesale",
            "subcategory":"Auto Parts",
            "type":"Manufacturing & Wholesale Goods"
        }
    ],
    "sg:phone":"+61 3 9278 2405",
    "sg:postcode":"3137",
    "sg:province":"VIC",
    "sg:tags":[
        "recyclers"
    ],
    "wof:name":"Trucking Supplies Co",
    "wof:placetype":"venue"
},
  "geometry": {"coordinates":[145.30329895,-37.8273544312],"type":"Point"}
}