{
  "type": "Feature",
  "properties": {
    "addr:full":"150 Beatty Rd Archerfield QLD 4108",
    "addr:housenumber":"150",
    "addr:postcode":"4108",
    "addr:street":"Beatty Rd",
    "iso:country":"AU",
    "sg:address":"150 Beatty Rd",
    "sg:city":"Archerfield",
    "sg:classifiers":[
        {
            "category":"Autos & Motor Vehicles",
            "subcategory":"Auto Supplies",
            "type":"Retail Goods"
        }
    ],
    "sg:phone":"+61 7 3274 6046",
    "sg:postcode":"4108",
    "sg:province":"QLD",
    "sg:tags":[
        "equipment",
        "part",
        "truck"
    ],
    "wof:name":"Air Brake Services Trailquip",
    "wof:placetype":"venue"
},
  "geometry": {"coordinates":[153.016021728,-27.5633811951],"type":"Point"}
}