{
  "type": "Feature",
  "properties": {
    "iso:country":"AU",
    "sg:address":"53 Bentick St",
    "sg:city":"Portland",
    "sg:classifiers":[
        {
            "category":"Cafe",
            "type":"Food & Drink"
        }
    ],
    "sg:phone":"+61 3 5523 2175",
    "sg:postcode":"3305",
    "sg:province":"VIC",
    "wof:name":"Harbour Lights Snack Bar",
    "wof:placetype":"venue"
},
  "geometry": {"coordinates":[141.606033325,-38.3501091003],"type":"Point"}
}