{
  "type": "Feature",
  "properties": {
    "addr:full":"PO Box 302 Yarra Junction VIC 3797",
    "addr:postcode":"3797",
    "iso:country":"AU",
    "sg:address":"PO Box 302",
    "sg:city":"Yarra Junction",
    "sg:classifiers":[
        {
            "category":"Utilities",
            "subcategory":"Electric",
            "type":"Services"
        }
    ],
    "sg:phone":"+61 3 5967 3539",
    "sg:postcode":"3797",
    "sg:province":"VIC",
    "sg:tags":[
        "electrical",
        "contractor"
    ],
    "wof:name":"Cutting K M",
    "wof:placetype":"venue"
},
  "geometry": {"coordinates":[145.61239624000001,-37.7815704346],"type":"Point"}
}