{
  "type": "Feature",
  "properties": {
    "addr:full":"16- 18 Reuben Crt Kings Meadows TAS 7249",
    "addr:housenumber":"18",
    "addr:postcode":"7249",
    "addr:street":"Reuben Crt",
    "iso:country":"AU",
    "sg:address":"16- 18 Reuben Crt",
    "sg:city":"Kings Meadows",
    "sg:classifiers":[
        {
            "category":"Shopping",
            "subcategory":"Crafts & Fabrics",
            "type":"Retail Goods"
        }
    ],
    "sg:phone":"+61 1800 030 031",
    "sg:postcode":"7249",
    "sg:province":"TAS",
    "sg:tags":[
        "supply"
    ],
    "wof:name":"Crafty Critters (Aust) Pty Ltd",
    "wof:placetype":"venue"
},
  "geometry": {"coordinates":[147.15826415999999,-41.4663543701],"type":"Point"}
}