{
  "type": "Feature",
  "properties": {
    "addr:full":"5 Charles St South Fremantle WA 6162",
    "addr:housenumber":"5",
    "addr:postcode":"6162",
    "addr:street":"Charles St",
    "iso:country":"AU",
    "sg:address":"5 Charles St",
    "sg:city":"South Fremantle",
    "sg:classifiers":[
        {
            "category":"Professional",
            "subcategory":"Employment Agencies",
            "type":"Services"
        }
    ],
    "sg:phone":"+61 405 922 232",
    "sg:postcode":"6162",
    "sg:province":"WA",
    "sg:tags":[
        "entertainer",
        "agent"
    ],
    "wof:name":"Kym The Krazy Magician Clown",
    "wof:placetype":"venue"
},
  "geometry": {"coordinates":[115.753113,-32.066528],"type":"Point"}
}