{
  "type": "Feature",
  "properties": {
    "iso:country":"AU",
    "sg:address":"Main Rd",
    "sg:city":"Forth",
    "sg:classifiers":[
        {
            "category":"Retail",
            "subcategory":"Auto Repair",
            "type":"Services"
        }
    ],
    "sg:phone":"+61 3 6428 2077",
    "sg:postcode":"7310",
    "sg:province":"TAS",
    "sg:tags":[
        "electrical"
    ],
    "wof:name":"Abela Autos",
    "wof:placetype":"venue"
},
  "geometry": {"coordinates":[146.35578918499999,-41.22290802],"type":"Point"}
}