{
  "type": "Feature",
  "properties": {
    "iso:country":"AU",
    "sg:address":"Unit 3/ 119 Long St",
    "sg:city":"Smithfield",
    "sg:classifiers":[
        {
            "category":"Professional",
            "subcategory":"Engineering",
            "type":"Services"
        }
    ],
    "sg:phone":"+61 2 9609 3307",
    "sg:postcode":"2164",
    "sg:province":"NSW",
    "sg:tags":[
        "engineer"
    ],
    "wof:name":"Treuer Engineering",
    "wof:placetype":"venue"
},
  "geometry": {"coordinates":[150.93280029300001,-33.8410835266],"type":"Point"}
}