{
  "type": "Feature",
  "properties": {
    "addr:full":"Shp 1/ 890 Canning Hwy Applecross WA 6153",
    "addr:housenumber":"/ 890",
    "addr:postcode":"6153",
    "addr:street":"Canning Hwy",
    "iso:country":"AU",
    "sg:address":"Shp 1/ 890 Canning Hwy",
    "sg:city":"Applecross",
    "sg:classifiers":[
        {
            "category":"Personal",
            "subcategory":"Beauty Salon",
            "type":"Services"
        }
    ],
    "sg:phone":"+61 8 9364 2858",
    "sg:postcode":"6153",
    "sg:province":"WA",
    "sg:tags":[
        "hairdresser"
    ],
    "wof:name":"J 9 Hair Lounge",
    "wof:placetype":"venue"
},
  "geometry": {"coordinates":[115.847542,-32.013287],"type":"Point"}
}