{
  "type": "Feature",
  "properties": {
    "addr:full":"PO Box 278 World Trade Centre VIC 8005",
    "addr:housenumber":"trade",
    "addr:postcode":"8005",
    "iso:country":"AU",
    "sg:address":"PO Box 278",
    "sg:city":"World Trade Centre",
    "sg:classifiers":[
        {
            "category":"Real Estate",
            "subcategory":"Real Estate Agent",
            "type":"Services"
        }
    ],
    "sg:phone":"+61 419 364 429",
    "sg:postcode":"8005",
    "sg:province":"VIC",
    "sg:tags":[
        "buyer"
    ],
    "wof:name":"Peter Rogozik Property Consulting",
    "wof:placetype":"venue"
},
  "geometry": {"coordinates":[144.95648193400001,-37.8245315552],"type":"Point"}
}