{
  "type": "Feature",
  "properties": {
    "addr:full":"172 Old Northern Rd Everton Park QLD 4053",
    "addr:housenumber":"172",
    "addr:postcode":"4053",
    "addr:street":"Old Northern Rd",
    "iso:country":"AU",
    "sg:address":"172 Old Northern Rd",
    "sg:city":"Everton Park",
    "sg:classifiers":[
        {
            "category":"Health Services",
            "subcategory":"Doctor",
            "type":"Services"
        }
    ],
    "sg:phone":"+61 7 3353 2422",
    "sg:postcode":"4053",
    "sg:province":"QLD",
    "sg:tags":[
        "medical",
        "practitioner"
    ],
    "wof:name":"Horsnell Kym R",
    "wof:placetype":"venue"
},
  "geometry": {"coordinates":[152.98535156200001,-27.3897247314],"type":"Point"}
}