{
  "type": "Feature",
  "properties": {
    "addr:full":"Level 6/ 88 Foveaux St Surry Hills NSW 2010",
    "addr:housenumber":"/ 88",
    "addr:postcode":"2010",
    "addr:street":"Foveaux St",
    "iso:country":"AU",
    "sg:address":"Level 6/ 88 Foveaux St",
    "sg:city":"Surry Hills",
    "sg:classifiers":[
        {
            "category":"Building & Trades",
            "subcategory":"Cleaning & Sanitation",
            "type":"Services"
        }
    ],
    "sg:phone":"+61 2 9213 5330",
    "sg:postcode":"2010",
    "sg:province":"NSW",
    "sg:tags":[
        "washroom",
        "toilet",
        "equipment"
    ],
    "wof:name":"Liu Australia Pty Ltd",
    "wof:placetype":"venue"
},
  "geometry": {"coordinates":[151.212234497,-33.8846931458],"type":"Point"}
}