{
  "type": "Feature",
  "properties": {
    "iso:country":"AU",
    "sg:address":"405 Princes Hwy",
    "sg:city":"St Peters",
    "sg:classifiers":[
        {
            "category":"Professional",
            "subcategory":"Employment Agencies",
            "type":"Services"
        }
    ],
    "sg:phone":"+61 2 9565 1800",
    "sg:postcode":"2044",
    "sg:province":"NSW",
    "sg:tags":[
        "broker",
        "custom"
    ],
    "wof:name":"Crystal Customs Clearances",
    "wof:placetype":"venue"
},
  "geometry": {"coordinates":[151.17041,-33.918201],"type":"Point"}
}