{
  "type": "Feature",
  "properties": {
    "addr:full":"74 Abbott St Cairns QLD 4870",
    "addr:housenumber":"74",
    "addr:postcode":"4870",
    "addr:street":"Abbott St",
    "iso:country":"AU",
    "sg:address":"74 Abbott St",
    "sg:city":"Cairns",
    "sg:classifiers":[
        {
            "category":"Professional",
            "subcategory":"Accounting & Tax Preparation",
            "type":"Services"
        }
    ],
    "sg:phone":"+61 7 4052 3224",
    "sg:postcode":"4870",
    "sg:province":"QLD",
    "sg:tags":[
        "accountant",
        "auditor"
    ],
    "wof:name":"Pollock Amanda",
    "wof:placetype":"venue"
},
  "geometry": {"coordinates":[145.778808594,-16.9237747192],"type":"Point"}
}