{
  "type": "Feature",
  "properties": {
    "iso:country":"AU",
    "sg:address":"10 Ommanney St",
    "sg:city":"Bunbury",
    "sg:classifiers":[
        {
            "category":"Real Estate",
            "subcategory":"Real Estate Agent",
            "type":"Services"
        }
    ],
    "sg:phone":"+61 8 9721 8888",
    "sg:postcode":"6230",
    "sg:province":"WA",
    "wof:name":"Everyone's Realty South West",
    "wof:placetype":"venue"
},
  "geometry": {"coordinates":[115.637894,-33.319283],"type":"Point"}
}