{
  "type": "Feature",
  "properties": {
    "iso:country":"AU",
    "sg:address":"PO Box 156",
    "sg:city":"Mayfield",
    "sg:classifiers":[
        {
            "category":"Building & Trades",
            "subcategory":"Cleaning & Sanitation",
            "type":"Services"
        }
    ],
    "sg:phone":"+61 2 4960 1415",
    "sg:postcode":"2304",
    "sg:province":"NSW",
    "sg:tags":[
        "commercial",
        "maintenance"
    ],
    "wof:name":"Coastal Property Services",
    "wof:placetype":"venue"
},
  "geometry": {"coordinates":[151.73826599099999,-32.8986282349],"type":"Point"}
}