{
  "type": "Feature",
  "properties": {
    "iso:country":"AU",
    "sg:address":"Sherwood Rd",
    "sg:city":"Sherwood",
    "sg:classifiers":[
        {
            "category":"Food & Beverages",
            "subcategory":"Fruits & Vegetables",
            "type":"Retail Goods"
        }
    ],
    "sg:phone":"+61 7 3379 4134",
    "sg:postcode":"4075",
    "sg:province":"QLD",
    "sg:tags":[
        "wholesale"
    ],
    "wof:name":"Ross & Co Fruit & Vegetables Pty Ltd",
    "wof:placetype":"venue"
},
  "geometry": {"coordinates":[152.98118591299999,-27.5321559906],"type":"Point"}
}