{
  "type": "Feature",
  "properties": {
    "addr:full":"57 Cronulla Ave Mermaid Beach QLD 4218",
    "addr:housenumber":"57",
    "addr:postcode":"4218",
    "addr:street":"Cronulla Ave",
    "iso:country":"AU",
    "sg:address":"57 Cronulla Ave",
    "sg:city":"Mermaid Beach",
    "sg:classifiers":[
        {
            "category":"Communications",
            "subcategory":"Film & Video Production",
            "type":"Services"
        }
    ],
    "sg:phone":"+61 7 5572 1003",
    "sg:postcode":"4218",
    "sg:province":"QLD",
    "sg:tags":[
        "equipment",
        "amplification",
        "music"
    ],
    "wof:name":"Mr Music Man",
    "wof:placetype":"venue"
},
  "geometry": {"coordinates":[153.43280029300001,-28.0400676727],"type":"Point"}
}