{
  "type": "Feature",
  "properties": {
    "addr:full":"91 Sawtell Rd Toormina NSW 2452",
    "addr:housenumber":"91",
    "addr:postcode":"2452",
    "addr:street":"Sawtell Rd",
    "iso:country":"AU",
    "sg:address":"91 Sawtell Rd",
    "sg:city":"Toormina",
    "sg:classifiers":[
        {
            "category":"Utilities",
            "subcategory":"Water",
            "type":"Services"
        }
    ],
    "sg:phone":"+61 2 6653 2021",
    "sg:postcode":"2452",
    "sg:province":"NSW",
    "sg:tags":[
        "hot",
        "system"
    ],
    "wof:name":"Andrews Craig W",
    "wof:placetype":"venue"
},
  "geometry": {"coordinates":[153.098984,-30.351774],"type":"Point"}
}