{
  "type": "Feature",
  "properties": {
    "addr:full":"1100 Dandenong Rd Malvern East VIC 3145",
    "addr:housenumber":"1100",
    "addr:postcode":"3145",
    "addr:street":"Dandenong Rd",
    "iso:country":"AU",
    "sg:address":"1100 Dandenong Rd",
    "sg:city":"Malvern East",
    "sg:classifiers":[
        {
            "category":"Health Services",
            "subcategory":"Health Practitioner",
            "type":"Services"
        }
    ],
    "sg:phone":"+61 3 9569 9448",
    "sg:postcode":"3145",
    "sg:province":"VIC",
    "sg:tags":[
        "physiotherapist"
    ],
    "wof:name":"The Melbourne Golf Injury Clinic",
    "wof:placetype":"venue"
},
  "geometry": {"coordinates":[145.05859375,-37.8842849731],"type":"Point"}
}