{
  "type": "Feature",
  "properties": {
    "addr:full":"PO Box 326 New Lambton NSW 2305",
    "addr:postcode":"2305",
    "iso:country":"AU",
    "sg:address":"PO Box 326",
    "sg:city":"New Lambton",
    "sg:classifiers":[
        {
            "category":"Building & Trades",
            "subcategory":"Plumbing",
            "type":"Services"
        }
    ],
    "sg:phone":"+61 431 128 158",
    "sg:postcode":"2305",
    "sg:province":"NSW",
    "sg:tags":[
        "plumber",
        "gasfitters"
    ],
    "wof:name":"Abet Plumbing Newcastle Pty Ltd",
    "wof:placetype":"venue"
},
  "geometry": {"coordinates":[151.71350100000001,-32.920181],"type":"Point"}
}