{
  "type": "Feature",
  "properties": {
    "addr:full":"22 William St Concord NSW 2137",
    "addr:housenumber":"22",
    "addr:postcode":"2137",
    "addr:street":"William St",
    "iso:country":"AU",
    "sg:address":"22 William St",
    "sg:city":"Concord",
    "sg:classifiers":[
        {
            "category":"Home & Garden",
            "subcategory":"Building Materials",
            "type":"Retail Goods"
        }
    ],
    "sg:phone":"+61 2 9743 4744",
    "sg:postcode":"2137",
    "sg:province":"NSW",
    "sg:tags":[
        "lawn",
        "cutting",
        "maintenance"
    ],
    "wof:name":"Nick The Lawnmower Man",
    "wof:placetype":"venue"
},
  "geometry": {"coordinates":[151.10858154300001,-33.8483810425],"type":"Point"}
}