{
  "type": "Feature",
  "properties": {
    "iso:country":"AU",
    "sg:address":"Unit 11E - 2A Victoria Ave",
    "sg:city":"Castle Hill",
    "sg:classifiers":[
        {
            "category":"Autos & Motor Vehicles",
            "subcategory":"Auto Supplies",
            "type":"Retail Goods"
        }
    ],
    "sg:phone":"+61 2 9894 7777",
    "sg:postcode":"2154",
    "sg:province":"NSW",
    "sg:tags":[
        "tyre"
    ],
    "wof:name":"Michael's Tyrehouse Tyre & Mechanical",
    "wof:placetype":"venue"
},
  "geometry": {"coordinates":[150.981323242,-33.7354278564],"type":"Point"}
}