{
  "type": "Feature",
  "properties": {
    "addr:full":"78 Illyarrie Ave Surrey Downs SA 5126",
    "addr:housenumber":"78",
    "addr:postcode":"5126",
    "addr:street":"Illyarrie Ave",
    "iso:country":"AU",
    "sg:address":"78 Illyarrie Ave",
    "sg:city":"Surrey Downs",
    "sg:classifiers":[
        {
            "category":"Education",
            "subcategory":"Kindergarten",
            "type":"Public Place"
        }
    ],
    "sg:phone":"+61 8 8251 2493",
    "sg:postcode":"5126",
    "sg:province":"SA",
    "sg:tags":[
        "pre-schools"
    ],
    "wof:name":"Surrey Downs Kindergarten & Occasional Care",
    "wof:placetype":"venue"
},
  "geometry": {"coordinates":[138.71098327600001,-34.8017501831],"type":"Point"}
}