{
  "type": "Feature",
  "properties": {
    "iso:country":"AU",
    "sg:address":"56 Carwell Ave",
    "sg:city":"Petrie",
    "sg:classifiers":[
        {
            "category":"Building & Trades",
            "subcategory":"Cleaning & Sanitation",
            "type":"Services"
        }
    ],
    "sg:phone":"+61 408 751 207",
    "sg:postcode":"4502",
    "sg:province":"QLD",
    "sg:tags":[
        "industrial",
        "commercial",
        "contractor"
    ],
    "wof:name":"Superior Domestics",
    "wof:placetype":"venue"
},
  "geometry": {"coordinates":[152.965408325,-27.2569122314],"type":"Point"}
}