{
  "type": "Feature",
  "properties": {
    "iso:country":"AU",
    "sg:address":"10 Cottam Ave",
    "sg:city":"Bankstown",
    "sg:classifiers":[
        {
            "category":"Retail",
            "subcategory":"Auto Repair",
            "type":"Services"
        }
    ],
    "sg:phone":"+61 2 9707 3437",
    "sg:postcode":"2200",
    "sg:province":"NSW",
    "sg:tags":[
        "beater",
        "painter",
        "panel"
    ],
    "wof:name":"All West Auto Body Repairs",
    "wof:placetype":"venue"
},
  "geometry": {"coordinates":[151.033737,-33.933743],"type":"Point"}
}