{
  "type": "Feature",
  "properties": {
    "addr:full":"124 Norton St Leichhardt NSW 2040",
    "addr:housenumber":"124",
    "addr:postcode":"2040",
    "addr:street":"Norton St",
    "iso:country":"AU",
    "sg:address":"124 Norton St",
    "sg:city":"Leichhardt",
    "sg:classifiers":[
        {
            "category":"Shopping",
            "subcategory":"Optical Goods",
            "type":"Retail Goods"
        }
    ],
    "sg:phone":"+61 2 9550 0512",
    "sg:postcode":"2040",
    "sg:province":"NSW",
    "sg:tags":[
        "dispenser",
        "prescription"
    ],
    "wof:name":"Karen Zoellner Optometrist",
    "wof:placetype":"venue"
},
  "geometry": {"coordinates":[151.15687600000001,-33.883633],"type":"Point"}
}