{
  "type": "Feature",
  "properties": {
    "addr:full":"83 Underwood St Paddington NSW 2021",
    "addr:housenumber":"83",
    "addr:postcode":"2021",
    "addr:street":"Underwood St",
    "iso:country":"AU",
    "sg:address":"83 Underwood St",
    "sg:city":"Paddington",
    "sg:classifiers":[
        {
            "category":"Deli",
            "type":"Food & Drink"
        }
    ],
    "sg:phone":"+61 2 9331 1898",
    "sg:postcode":"2021",
    "sg:province":"NSW",
    "sg:tags":[
        "delicatessen"
    ],
    "wof:name":"Underwood Deli",
    "wof:placetype":"venue"
},
  "geometry": {"coordinates":[151.22979736299999,-33.8850402832],"type":"Point"}
}