{
  "type": "Feature",
  "properties": {
    "addr:full":"46 Uki Rd Bray Park NSW 2484",
    "addr:housenumber":"46",
    "addr:postcode":"2484",
    "addr:street":"Uki Rd",
    "iso:country":"AU",
    "sg:address":"46 Uki Rd",
    "sg:city":"Bray Park",
    "sg:classifiers":[
        {
            "category":"Retail",
            "subcategory":"Auto Repair",
            "type":"Services"
        }
    ],
    "sg:phone":"+61 2 6672 4240",
    "sg:postcode":"2484",
    "sg:province":"NSW",
    "sg:tags":[
        "repairer",
        "motor",
        "engineer"
    ],
    "wof:name":"Bray Park Fuel & Mechanical",
    "wof:placetype":"venue"
},
  "geometry": {"coordinates":[153.401412964,-28.3228168488],"type":"Point"}
}