{
  "type": "Feature",
  "properties": {
    "iso:country":"AU",
    "sg:address":"9 Fitton Pl",
    "sg:city":"St Helens Park",
    "sg:classifiers":[
        {
            "category":"Professional",
            "subcategory":"Detective & Security Services",
            "type":"Services"
        }
    ],
    "sg:phone":"+61 2 4621 4777",
    "sg:postcode":"2560",
    "sg:province":"NSW",
    "sg:tags":[
        "inspector",
        "boiler"
    ],
    "wof:name":"ABV Inspections Pty Ltd",
    "wof:placetype":"venue"
},
  "geometry": {"coordinates":[150.79963684099999,-34.1121482849],"type":"Point"}
}