{
  "type": "Feature",
  "properties": {
    "iso:country":"AU",
    "sg:address":"4/ 5 Bessemer St",
    "sg:city":"Blacktown",
    "sg:classifiers":[
        {
            "category":"Wholesale",
            "subcategory":"Metals & Minerals",
            "type":"Manufacturing & Wholesale Goods"
        }
    ],
    "sg:phone":"+61 2 9831 6400",
    "sg:postcode":"2148",
    "sg:province":"NSW",
    "sg:tags":[
        "steel",
        "merchant"
    ],
    "sg:website":"http://www.ezimetal.com.au",
    "wof:name":"EZI Metal",
    "wof:placetype":"venue"
},
  "geometry": {"coordinates":[150.90826415999999,-33.7571754456],"type":"Point"}
}