{
  "type": "Feature",
  "properties": {
    "addr:full":"22S Abbott St Sandringham VIC 3191",
    "addr:housenumber":"22s",
    "addr:postcode":"3191",
    "addr:street":"Abbott St",
    "iso:country":"AU",
    "sg:address":"22S Abbott St",
    "sg:city":"Sandringham",
    "sg:classifiers":[
        {
            "category":"Health Services",
            "subcategory":"Chiropractor",
            "type":"Services"
        }
    ],
    "sg:phone":"+61 3 9598 7811",
    "sg:postcode":"3191",
    "sg:province":"VIC",
    "wof:name":"Vida Chiropractic",
    "wof:placetype":"venue"
},
  "geometry": {"coordinates":[145.003707886,-37.9488296509],"type":"Point"}
}