{
  "type": "Feature",
  "properties": {
    "iso:country":"AU",
    "sg:address":"Lot 3 Southern Amberley Rd",
    "sg:city":"Amberley",
    "sg:classifiers":[
        {
            "category":"Retail",
            "subcategory":"Repair Shop",
            "type":"Services"
        }
    ],
    "sg:phone":"+61 7 5467 3333",
    "sg:postcode":"4306",
    "sg:province":"QLD",
    "sg:tags":[
        "upholsterer"
    ],
    "wof:name":"Brady Magnussen Upholstery",
    "wof:placetype":"venue"
},
  "geometry": {"coordinates":[152.699752808,-27.6448764801],"type":"Point"}
}