{
  "type": "Feature",
  "properties": {
    "addr:full":"2 / 43 Cranwell St Braybrook VIC 3019",
    "addr:housenumber":"/ 43",
    "addr:postcode":"3019",
    "addr:street":"Cranwell St",
    "iso:country":"AU",
    "sg:address":"2 / 43 Cranwell St",
    "sg:city":"Braybrook",
    "sg:classifiers":[
        {
            "category":"Retail",
            "subcategory":"Auto Repair",
            "type":"Services"
        }
    ],
    "sg:phone":"+61 3 9318 6611",
    "sg:postcode":"3019",
    "sg:province":"VIC",
    "sg:tags":[
        "body",
        "motor",
        "trimmer"
    ],
    "wof:name":"Sunshine Motor Trimmers",
    "wof:placetype":"venue"
},
  "geometry": {"coordinates":[144.86192321799999,-37.7787857056],"type":"Point"}
}