{
  "type": "Feature",
  "properties": {
    "iso:country":"AU",
    "sg:address":"42 Fraser St",
    "sg:city":"Airport West",
    "sg:classifiers":[
        {
            "category":"Retail",
            "subcategory":"Auto Repair",
            "type":"Services"
        }
    ],
    "sg:phone":"+61 3 9338 3058",
    "sg:postcode":"3042",
    "sg:province":"VIC",
    "sg:tags":[
        "repairer",
        "motor",
        "engineer"
    ],
    "wof:name":"Blandthorn Motors",
    "wof:placetype":"venue"
},
  "geometry": {"coordinates":[144.88676452600001,-37.7241477966],"type":"Point"}
}