{
  "type": "Feature",
  "properties": {
    "addr:full":"445 Hay St Perth WA 6000",
    "addr:housenumber":"445",
    "addr:postcode":"6000",
    "addr:street":"Hay St",
    "iso:country":"AU",
    "sg:address":"445 Hay St",
    "sg:city":"Perth",
    "sg:classifiers":[
        {
            "category":"Banks & Credit Unions",
            "subcategory":"Financial Services",
            "type":"Services"
        }
    ],
    "sg:phone":"+61 8 9220 7700",
    "sg:postcode":"6000",
    "sg:province":"WA",
    "sg:tags":[
        "loan",
        "finance",
        "mortgage"
    ],
    "wof:name":"CUA UFS Branch",
    "wof:placetype":"venue"
},
  "geometry": {"coordinates":[115.85575103799999,-31.9532680511],"type":"Point"}
}