{
  "type": "Feature",
  "properties": {
    "iso:country":"AU",
    "sg:address":"Cnr Lisbon & Mandarin Sts",
    "sg:city":"Fairfield",
    "sg:classifiers":[
        {
            "category":"Manufacturing",
            "subcategory":"Tools & Machinery",
            "type":"Manufacturing & Wholesale Goods"
        }
    ],
    "sg:phone":"+61 2 9795 8300",
    "sg:postcode":"2165",
    "sg:province":"NSW",
    "sg:tags":[
        "earth",
        "excavating",
        "moving",
        "equipment"
    ],
    "wof:name":"Komatsu Australia Pty Ltd",
    "wof:placetype":"venue"
},
  "geometry": {"coordinates":[150.97366332999999,-33.8706321716],"type":"Point"}
}