{
  "type": "Feature",
  "properties": {
    "addr:full":"88 Harslett Crs Kogarah Bay NSW 2217",
    "addr:housenumber":"88",
    "addr:postcode":"2217",
    "addr:street":"Harslett Crs",
    "iso:country":"AU",
    "sg:address":"88 Harslett Crs",
    "sg:city":"Kogarah Bay",
    "sg:classifiers":[
        {
            "category":"Real Estate",
            "subcategory":"Architect",
            "type":"Services"
        }
    ],
    "sg:phone":"+61 414 577 007",
    "sg:postcode":"2217",
    "sg:province":"NSW",
    "wof:name":"George Elkhoury Architect",
    "wof:placetype":"venue"
},
  "geometry": {"coordinates":[151.12515300000001,-33.980961],"type":"Point"}
}