{
  "type": "Feature",
  "properties": {
    "addr:full":"1/ 33 White St Parkdale VIC 3195",
    "addr:housenumber":"/ 33",
    "addr:postcode":"3195",
    "addr:street":"White St",
    "iso:country":"AU",
    "sg:address":"1/ 33 White St",
    "sg:city":"Parkdale",
    "sg:classifiers":[
        {
            "category":"Professional",
            "subcategory":"Computer Services",
            "type":"Services"
        }
    ],
    "sg:phone":"+61 3 9587 3867",
    "sg:postcode":"3195",
    "sg:province":"VIC",
    "sg:tags":[
        "consultant",
        "system"
    ],
    "wof:name":"Integrated Database Systems",
    "wof:placetype":"venue"
},
  "geometry": {"coordinates":[145.087722778,-37.9986343384],"type":"Point"}
}