{
  "type": "Feature",
  "properties": {
    "addr:full":"275 Nepean Hwy Edithvale VIC 3196",
    "addr:housenumber":"275",
    "addr:postcode":"3196",
    "addr:street":"Nepean Hwy",
    "iso:country":"AU",
    "sg:address":"275 Nepean Hwy",
    "sg:city":"Edithvale",
    "sg:classifiers":[
        {
            "category":"Health Services",
            "subcategory":"Health Practitioner",
            "type":"Services"
        }
    ],
    "sg:phone":"+61 418 899 800",
    "sg:postcode":"3196",
    "sg:province":"VIC",
    "sg:tags":[
        "psychologist"
    ],
    "wof:name":"Andrew G Remenyi Dr",
    "wof:placetype":"venue"
},
  "geometry": {"coordinates":[145.10867309599999,-38.0390586853],"type":"Point"}
}