{
  "type": "Feature",
  "properties": {
    "addr:full":"1/ 89 Cecil Ave Castle Hill NSW 2154",
    "addr:housenumber":"/ 89",
    "addr:postcode":"2154",
    "addr:street":"Cecil Ave",
    "iso:country":"AU",
    "sg:address":"1/ 89 Cecil Ave",
    "sg:city":"Castle Hill",
    "sg:classifiers":[
        {
            "category":"Professional",
            "subcategory":"Employment Agencies",
            "type":"Services"
        }
    ],
    "sg:phone":"+61 2 9634 7111",
    "sg:postcode":"2154",
    "sg:province":"NSW",
    "wof:name":"Science People",
    "wof:placetype":"venue"
},
  "geometry": {"coordinates":[151.001022339,-33.7338294983],"type":"Point"}
}