{
  "type": "Feature",
  "properties": {
    "iso:country":"AU",
    "sg:address":"211 Byng St",
    "sg:city":"Orange",
    "sg:classifiers":[
        {
            "category":"Fast Food",
            "type":"Food & Drink"
        }
    ],
    "sg:phone":"+61 2 6362 7382",
    "sg:postcode":"2800",
    "sg:province":"NSW",
    "sg:tags":[
        "away",
        "take"
    ],
    "wof:name":"Mackies Cafe",
    "wof:placetype":"venue"
},
  "geometry": {"coordinates":[149.108276367,-33.2825241089],"type":"Point"}
}