{
  "type": "Feature",
  "properties": {
    "addr:full":"Iona Rd Home Hill QLD 4806",
    "addr:postcode":"4806",
    "addr:street":"Iona Rd",
    "iso:country":"AU",
    "sg:address":"Iona Rd",
    "sg:city":"Home Hill",
    "sg:classifiers":[
        {
            "category":"Farming",
            "subcategory":"Farm",
            "type":"Manufacturing & Wholesale Goods"
        }
    ],
    "sg:phone":"+61 7 4782 1562",
    "sg:postcode":"4806",
    "sg:province":"QLD",
    "sg:tags":[
        "farmer"
    ],
    "wof:name":"Di Marzio & Son",
    "wof:placetype":"venue"
},
  "geometry": {"coordinates":[147.40692138700001,-19.6803474426],"type":"Point"}
}