{
  "type": "Feature",
  "properties": {
    "addr:full":"392 Hampton St Hampton VIC 3188",
    "addr:housenumber":"392",
    "addr:postcode":"3188",
    "addr:street":"Hampton St",
    "iso:country":"AU",
    "sg:address":"392 Hampton St",
    "sg:city":"Hampton",
    "sg:classifiers":[
        {
            "category":"Shopping",
            "subcategory":"Bridal",
            "type":"Retail Goods"
        }
    ],
    "sg:phone":"+61 3 9597 0644",
    "sg:postcode":"3188",
    "sg:province":"VIC",
    "sg:tags":[
        "hire",
        "wear"
    ],
    "wof:name":"The Madeline Boutique",
    "wof:placetype":"venue"
},
  "geometry": {"coordinates":[145.00236511200001,-37.9390983582],"type":"Point"}
}