{
  "type": "Feature",
  "properties": {
    "addr:full":"Camelia Ave Everton Hills QLD 4053",
    "addr:postcode":"4053",
    "addr:street":"Camelia Ave",
    "iso:country":"AU",
    "sg:address":"Camelia Ave",
    "sg:city":"Everton Hills",
    "sg:classifiers":[
        {
            "category":"Retail",
            "subcategory":"Veterinary Services",
            "type":"Services"
        }
    ],
    "sg:phone":"+61 7 3355 6724",
    "sg:postcode":"4053",
    "sg:province":"QLD",
    "sg:tags":[
        "surgeon"
    ],
    "wof:name":"Field Peter",
    "wof:placetype":"venue"
},
  "geometry": {"coordinates":[152.97201538100001,-27.3956451416],"type":"Point"}
}