{
  "type": "Feature",
  "properties": {
    "iso:country":"AU",
    "sg:address":"55 Ipswich Rd",
    "sg:city":"Woolloongabba",
    "sg:classifiers":[
        {
            "category":"Recreation",
            "subcategory":"Amusement Park",
            "type":"Entertainment"
        }
    ],
    "sg:phone":"+61 7 3891 1031",
    "sg:postcode":"4102",
    "sg:province":"QLD",
    "wof:name":"Laserforce",
    "wof:placetype":"venue"
},
  "geometry": {"coordinates":[153.03573608400001,-27.4890155792],"type":"Point"}
}