{
  "type": "Feature",
  "properties": {
    "addr:full":"Shop 2/ 39 Burrendah Blv Willetton WA 6155",
    "addr:housenumber":"shop 2 / 39",
    "addr:postcode":"6155",
    "addr:street":"Burrendah Blv",
    "iso:country":"AU",
    "sg:address":"Shop 2/ 39 Burrendah Blv",
    "sg:city":"Willetton",
    "sg:classifiers":[
        {
            "category":"Fast Food",
            "type":"Food & Drink"
        }
    ],
    "sg:phone":"+61 8 9322 0922",
    "sg:postcode":"6155",
    "sg:province":"WA",
    "sg:tags":[
        "away",
        "take"
    ],
    "wof:name":"Subway Sandwiches & Salads",
    "wof:placetype":"venue"
},
  "geometry": {"coordinates":[115.880478,-32.056114],"type":"Point"}
}