{
  "type": "Feature",
  "properties": {
    "addr:full":"5 Jones Rd Kenthurst NSW 2156",
    "addr:housenumber":"5",
    "addr:postcode":"2156",
    "addr:street":"Jones Rd",
    "iso:country":"AU",
    "sg:address":"5 Jones Rd",
    "sg:city":"Kenthurst",
    "sg:classifiers":[
        {
            "category":"Health Services",
            "subcategory":"Doctor",
            "type":"Services"
        }
    ],
    "sg:phone":"+61 2 9654 2121",
    "sg:postcode":"2156",
    "sg:province":"NSW",
    "sg:tags":[
        "medical",
        "practitioner"
    ],
    "wof:name":"Howard, Anne",
    "wof:placetype":"venue"
},
  "geometry": {"coordinates":[151.0025177,-33.6657333374],"type":"Point"}
}