{
  "type": "Feature",
  "properties": {
    "addr:full":"142 Haldon St Lakemba NSW 2195",
    "addr:housenumber":"142",
    "addr:postcode":"2195",
    "addr:street":"Haldon St",
    "iso:country":"AU",
    "sg:address":"142 Haldon St",
    "sg:city":"Lakemba",
    "sg:classifiers":[
        {
            "category":"Travel",
            "subcategory":"Travel Agent",
            "type":"Entertainment"
        }
    ],
    "sg:phone":"+61 2 9750 9085",
    "sg:postcode":"2195",
    "sg:province":"NSW",
    "sg:tags":[
        "consultant"
    ],
    "wof:name":"Discount Air Travel-Brokers",
    "wof:placetype":"venue"
},
  "geometry": {"coordinates":[151.07841500000001,-33.922424],"type":"Point"}
}