{
  "type": "Feature",
  "properties": {
    "addr:full":"Unit 12/ 90 Barrier St Fyshwick ACT 2609",
    "addr:housenumber":"/ 90",
    "addr:postcode":"2609",
    "addr:street":"Barrier St",
    "iso:country":"AU",
    "sg:address":"Unit 12/ 90 Barrier St",
    "sg:city":"Fyshwick",
    "sg:classifiers":[
        {
            "category":"Professional",
            "subcategory":"Engineering",
            "type":"Services"
        }
    ],
    "sg:phone":"+61 2 6280 7521",
    "sg:postcode":"2609",
    "sg:province":"ACT",
    "sg:tags":[
        "electronic",
        "engineer"
    ],
    "wof:name":"N.R. Pty Ltd",
    "wof:placetype":"venue"
},
  "geometry": {"coordinates":[149.16856384299999,-35.3264694214],"type":"Point"}
}