{
  "type": "Feature",
  "properties": {
    "addr:full":"Apt 3/ 518 Goodwood Rd Daw Park SA 5041",
    "addr:housenumber":"/ 518",
    "addr:postcode":"5041",
    "addr:street":"Goodwood Rd",
    "iso:country":"AU",
    "sg:address":"Apt 3/ 518 Goodwood Rd",
    "sg:city":"Daw Park",
    "sg:classifiers":[
        {
            "category":"Personal",
            "subcategory":"Beauty Salon",
            "type":"Services"
        }
    ],
    "sg:phone":"+61 8 8271 1377",
    "sg:postcode":"5041",
    "sg:province":"SA",
    "sg:tags":[
        "hairdresser"
    ],
    "wof:name":"La Forbice Hairdressing Salon",
    "wof:placetype":"venue"
},
  "geometry": {"coordinates":[138.59153699999999,-34.978252],"type":"Point"}
}