{
  "type": "Feature",
  "properties": {
    "addr:full":"44 Bendora Ave Queanbeyan ACT 2620",
    "addr:housenumber":"44",
    "addr:postcode":"2620",
    "addr:street":"Bendora Ave",
    "iso:country":"AU",
    "sg:address":"44 Bendora Ave",
    "sg:city":"Queanbeyan",
    "sg:classifiers":[
        {
            "category":"Building & Trades",
            "subcategory":"Construction",
            "type":"Services"
        }
    ],
    "sg:phone":"+61 2 6297 1969",
    "sg:postcode":"2620",
    "sg:province":"ACT",
    "sg:tags":[
        "fencing",
        "contractor"
    ],
    "wof:name":"Michael Harvey",
    "wof:placetype":"venue"
},
  "geometry": {"coordinates":[149.21339416500001,-35.3505172729],"type":"Point"}
}