{
  "type": "Feature",
  "properties": {
    "iso:country":"AU",
    "sg:address":"44 Grasmere Rd",
    "sg:city":"Cremorne",
    "sg:classifiers":[
        {
            "category":"Utilities",
            "subcategory":"Electric",
            "type":"Services"
        }
    ],
    "sg:phone":"+61 2 9953 8591",
    "sg:postcode":"2090",
    "sg:province":"NSW",
    "sg:tags":[
        "electrical",
        "contractor"
    ],
    "wof:name":"APR Electrical Services",
    "wof:placetype":"venue"
},
  "geometry": {"coordinates":[151.22218322800001,-33.8264656067],"type":"Point"}
}