{
  "type": "Feature",
  "properties": {
    "iso:country":"AU",
    "sg:address":"Lynwood Senior High School 436 Metcalf Rd",
    "sg:city":"Parkwood",
    "sg:classifiers":[
        {
            "category":"Education",
            "subcategory":"School",
            "type":"Public Place"
        }
    ],
    "sg:phone":"+61 8 9354 0600",
    "sg:postcode":"6147",
    "sg:province":"WA",
    "sg:tags":[
        "state",
        "except",
        "nsw"
    ],
    "wof:name":"Schools Government (Public)",
    "wof:placetype":"venue"
},
  "geometry": {"coordinates":[115.917778,-32.042259],"type":"Point"}
}