{
  "type": "Feature",
  "properties": {
    "addr:full":"106- 108 Centre St Casino NSW 2470",
    "addr:housenumber":"108",
    "addr:postcode":"2470",
    "addr:street":"Centre St",
    "iso:country":"AU",
    "sg:address":"106- 108 Centre St",
    "sg:city":"Casino",
    "sg:classifiers":[
        {
            "category":"Autos & Motor Vehicles",
            "subcategory":"Automobile Sales",
            "type":"Retail Goods"
        }
    ],
    "sg:phone":"+61 2 6662 5588",
    "sg:postcode":"2470",
    "sg:province":"NSW",
    "sg:tags":[
        "car",
        "used"
    ],
    "wof:name":"Car Warehouse The",
    "wof:placetype":"venue"
},
  "geometry": {"coordinates":[153.04745483400001,-28.8560276031],"type":"Point"}
}