{
  "type": "Feature",
  "properties": {
    "addr:full":"38 Southern Cross Drv Cronin Island QLD 4217",
    "addr:housenumber":"38",
    "addr:postcode":"4217",
    "addr:street":"Southern Cross Drv",
    "iso:country":"AU",
    "sg:address":"38 Southern Cross Drv",
    "sg:city":"Cronin Island",
    "sg:classifiers":[
        {
            "category":"Professional",
            "subcategory":"Business Services",
            "type":"Services"
        }
    ],
    "sg:phone":"+61 7 5538 2588",
    "sg:postcode":"4217",
    "sg:province":"QLD",
    "sg:tags":[
        "fashion",
        "agent"
    ],
    "wof:name":"Raymac Agencies",
    "wof:placetype":"venue"
},
  "geometry": {"coordinates":[153.41786193900001,-27.9936561584],"type":"Point"}
}