{
  "type": "Feature",
  "properties": {
    "iso:country":"AU",
    "sg:address":"19 Commercial Rd",
    "sg:city":"Kingsgrove",
    "sg:classifiers":[
        {
            "category":"Home & Garden",
            "subcategory":"Kitchen Supply",
            "type":"Retail Goods"
        }
    ],
    "sg:phone":"+61 2 9502 1835",
    "sg:postcode":"2208",
    "sg:province":"NSW",
    "sg:tags":[
        "traffic",
        "equipment",
        "safety",
        "road"
    ],
    "wof:name":"Signmark Products Pty Ltd",
    "wof:placetype":"venue"
},
  "geometry": {"coordinates":[151.099426,-33.940315],"type":"Point"}
}