{
  "type": "Feature",
  "properties": {
    "iso:country":"AU",
    "sg:address":"159 Barrenjoey Rd",
    "sg:city":"Newport",
    "sg:classifiers":[
        {
            "category":"Bars & Pubs",
            "subcategory":"Nightclub",
            "type":"Food & Drink"
        }
    ],
    "sg:phone":"+61 2 9979 4848",
    "sg:postcode":"2106",
    "sg:province":"NSW",
    "sg:tags":[
        "karaoke"
    ],
    "wof:name":"Showtime Karaoke",
    "wof:placetype":"venue"
},
  "geometry": {"coordinates":[151.31573486299999,-33.6696472168],"type":"Point"}
}