{
  "type": "Feature",
  "properties": {
    "addr:full":"Suite 6 Edward Court, 8 Edward St Bunbury WA 6230",
    "addr:housenumber":"8",
    "addr:postcode":"6230",
    "addr:street":"Edward;Edward St",
    "iso:country":"AU",
    "sg:address":"Suite 6 Edward Court, 8 Edward St",
    "sg:city":"Bunbury",
    "sg:classifiers":[
        {
            "category":"Banks & Credit Unions",
            "subcategory":"Investment Brokerage",
            "type":"Services"
        }
    ],
    "sg:phone":"+61 1300 136 917",
    "sg:postcode":"6230",
    "sg:province":"WA",
    "sg:tags":[
        "debt",
        "collection"
    ],
    "sg:website":"http://www.bcadebt.com",
    "wof:name":"Bouvard Collection Agency",
    "wof:placetype":"venue"
},
  "geometry": {"coordinates":[115.63780199999999,-33.327957],"type":"Point"}
}