{
  "type": "Feature",
  "properties": {
    "addr:full":"Shop 2 61-63 Dora St Morisset NSW 2264",
    "addr:housenumber":"shop 2",
    "addr:postcode":"61-63;2264",
    "addr:street":"Dora St",
    "iso:country":"AU",
    "sg:address":"Shop 2 61-63 Dora St",
    "sg:city":"Morisset",
    "sg:classifiers":[
        {
            "category":"Personal",
            "subcategory":"Beauty Salon",
            "type":"Services"
        }
    ],
    "sg:phone":"+61 2 4973 1438",
    "sg:postcode":"2264",
    "sg:province":"NSW",
    "sg:tags":[
        "hairdresser"
    ],
    "wof:name":"Muffets Unisex Hair Salon",
    "wof:placetype":"venue"
},
  "geometry": {"coordinates":[151.48983799999999,-33.10759],"type":"Point"}
}