{
  "type": "Feature",
  "properties": {
    "addr:full":"Shop 2, 92 Fernberg Rd Rosalie QLD 4064",
    "addr:housenumber":"shop;92",
    "addr:postcode":"4064",
    "addr:street":"Fernberg Rd",
    "iso:country":"AU",
    "sg:address":"Shop 2, 92 Fernberg Rd",
    "sg:city":"Rosalie",
    "sg:classifiers":[
        {
            "category":"Deli",
            "type":"Food & Drink"
        }
    ],
    "sg:phone":"+61 7 3369 1105",
    "sg:postcode":"4064",
    "sg:province":"QLD",
    "sg:tags":[
        "delicatessen"
    ],
    "wof:name":"Con's Rosalie General Store",
    "wof:placetype":"venue"
},
  "geometry": {"coordinates":[152.996368408,-27.4632568359],"type":"Point"}
}