{
  "type": "Feature",
  "properties": {
    "iso:country":"AU",
    "sg:address":"Yungaburra Rd",
    "sg:city":"Atherton",
    "sg:classifiers":[
        {
            "category":"Farming",
            "subcategory":"Farm",
            "type":"Manufacturing & Wholesale Goods"
        }
    ],
    "sg:phone":"+61 7 4091 3904",
    "sg:postcode":"4883",
    "sg:province":"QLD",
    "sg:tags":[
        "farmer"
    ],
    "wof:name":"Giudice Susan & Warren",
    "wof:placetype":"venue"
},
  "geometry": {"coordinates":[145.474975586,-17.2683391571],"type":"Point"}
}