{
  "type": "Feature",
  "properties": {
    "iso:country":"AU",
    "sg:address":"13 Cunningham St",
    "sg:city":"Moorebank",
    "sg:classifiers":[
        {
            "category":"Wholesale",
            "subcategory":"Auto Parts",
            "type":"Manufacturing & Wholesale Goods"
        }
    ],
    "sg:phone":"+61 2 9600 7066",
    "sg:postcode":"2170",
    "sg:province":"NSW",
    "sg:tags":[
        "recyclers"
    ],
    "wof:name":"Japengines Pty Ltd",
    "wof:placetype":"venue"
},
  "geometry": {"coordinates":[150.93632507300001,-33.9344215393],"type":"Point"}
}