{
  "type": "Feature",
  "properties": {
    "iso:country":"AU",
    "sg:address":"5 Walla Crt",
    "sg:city":"Mudgeeraba",
    "sg:classifiers":[
        {
            "category":"Health Services",
            "subcategory":"Health Practitioner",
            "type":"Services"
        }
    ],
    "sg:phone":"+61 7 5530 3542",
    "sg:postcode":"4213",
    "sg:province":"QLD",
    "sg:tags":[
        "hypnotherapy"
    ],
    "wof:name":"Kaye Murrell",
    "wof:placetype":"venue"
},
  "geometry": {"coordinates":[153.342697144,-28.1013870239],"type":"Point"}
}