{
  "type": "Feature",
  "properties": {
    "iso:country":"AU",
    "sg:address":"7 Douglas St",
    "sg:city":"Taree",
    "sg:classifiers":[
        {
            "category":"Professional",
            "subcategory":"Art Services",
            "type":"Services"
        }
    ],
    "sg:phone":"+61 2 6552 5640",
    "sg:postcode":"2430",
    "sg:province":"NSW",
    "sg:tags":[
        "artist"
    ],
    "wof:name":"Taree Signs",
    "wof:placetype":"venue"
},
  "geometry": {"coordinates":[152.453339,-31.90576],"type":"Point"}
}