{
  "type": "Feature",
  "properties": {
    "iso:country":"AU",
    "sg:address":"116 John St",
    "sg:city":"Singleton",
    "sg:classifiers":[
        {
            "category":"Personal",
            "subcategory":"Beauty Salon",
            "type":"Services"
        }
    ],
    "sg:phone":"+61 2 6572 4805",
    "sg:postcode":"2330",
    "sg:province":"NSW",
    "sg:tags":[
        "hairdresser"
    ],
    "wof:name":"De-Ja-Vu Hair Design",
    "wof:placetype":"venue"
},
  "geometry": {"coordinates":[151.16693100000001,-32.565289],"type":"Point"}
}