{
  "type": "Feature",
  "properties": {
    "addr:full":"Suite 12, 163 Commercial Rd South Yarra VIC 3141",
    "addr:housenumber":"163",
    "addr:postcode":"3141",
    "addr:street":"Commercial Rd",
    "iso:country":"AU",
    "sg:address":"Suite 12, 163 Commercial Rd",
    "sg:city":"South Yarra",
    "sg:classifiers":[
        {
            "category":"Real Estate",
            "subcategory":"Architect",
            "type":"Services"
        }
    ],
    "sg:phone":"+61 3 9826 4844",
    "sg:postcode":"3141",
    "sg:province":"VIC",
    "wof:name":"Buckerfield Pty Ltd",
    "wof:placetype":"venue"
},
  "geometry": {"coordinates":[144.99183654800001,-37.846408844],"type":"Point"}
}