{
  "type": "Feature",
  "properties": {
    "addr:full":"Lot 1110 Bradmill Ave Rutherford NSW 2320",
    "addr:housenumber":"1110",
    "addr:postcode":"2320",
    "addr:street":"Bradmill Ave",
    "iso:country":"AU",
    "sg:address":"Lot 1110 Bradmill Ave",
    "sg:city":"Rutherford",
    "sg:classifiers":[
        {
            "category":"Building & Trades",
            "subcategory":"Construction",
            "type":"Services"
        }
    ],
    "sg:phone":"+61 2 4966 0833",
    "sg:postcode":"2320",
    "sg:province":"NSW",
    "sg:tags":[
        "earth",
        "excavating",
        "moving",
        "contractor"
    ],
    "wof:name":"Pryor Plant Hire",
    "wof:placetype":"venue"
},
  "geometry": {"coordinates":[151.505325317,-32.7127418518],"type":"Point"}
}