{
  "type": "Feature",
  "properties": {
    "iso:country":"AU",
    "sg:address":"Country Club Rd",
    "sg:city":"Lucindale",
    "sg:classifiers":[
        {
            "category":"Sports & Exercise",
            "subcategory":"Golf",
            "type":"Entertainment"
        }
    ],
    "sg:phone":"+61 8 8766 2132",
    "sg:postcode":"5272",
    "sg:province":"SA",
    "sg:tags":[
        "club"
    ],
    "wof:name":"Lucindale Golf Club Incorporated",
    "wof:placetype":"venue"
},
  "geometry": {"coordinates":[140.37027,-36.97121],"type":"Point"}
}