{
  "type": "Feature",
  "properties": {
    "addr:full":"4 Church Rd Moorebank NSW 2170",
    "addr:housenumber":"4",
    "addr:postcode":"2170",
    "addr:street":"Church Rd",
    "iso:country":"AU",
    "sg:address":"4 Church Rd",
    "sg:city":"Moorebank",
    "sg:classifiers":[
        {
            "category":"Retail",
            "subcategory":"Car Wash",
            "type":"Services"
        }
    ],
    "sg:phone":"+61 2 9602 9677",
    "sg:postcode":"2170",
    "sg:province":"NSW",
    "sg:tags":[
        "auction",
        "motor"
    ],
    "wof:name":"Mullers Motor Auction (Retailers)",
    "wof:placetype":"venue"
},
  "geometry": {"coordinates":[150.93377685600001,-33.9356040955],"type":"Point"}
}