{
  "type": "Feature",
  "properties": {
    "iso:country":"AU",
    "sg:address":"888 Canning Hwy",
    "sg:city":"Applecross",
    "sg:classifiers":[
        {
            "category":"Communications",
            "subcategory":"Film & Video Production",
            "type":"Services"
        }
    ],
    "sg:phone":"+61 8 9364 9314",
    "sg:postcode":"6153",
    "sg:province":"WA",
    "sg:tags":[
        "dvd",
        "library"
    ],
    "wof:name":"Civic Video Pty Ltd",
    "wof:placetype":"venue"
},
  "geometry": {"coordinates":[115.847351,-32.01339],"type":"Point"}
}