{
  "type": "Feature",
  "properties": {
    "addr:full":"5 Ludgate Ave Sheidow Park SA 5158",
    "addr:housenumber":"5",
    "addr:postcode":"5158",
    "addr:street":"Ludgate Ave",
    "iso:country":"AU",
    "sg:address":"5 Ludgate Ave",
    "sg:city":"Sheidow Park",
    "sg:classifiers":[
        {
            "category":"Professional",
            "subcategory":"Management & Consulting",
            "type":"Services"
        }
    ],
    "sg:phone":"+61 8 8276 7926",
    "sg:postcode":"5158",
    "sg:province":"SA",
    "sg:tags":[
        "information"
    ],
    "wof:name":"Montessori World Education Institute of S.A. Inc.",
    "wof:placetype":"venue"
},
  "geometry": {"coordinates":[138.53616332999999,-35.0821151733],"type":"Point"}
}