{
  "type": "Feature",
  "properties": {
    "iso:country":"AU",
    "sg:address":"9 Flora St",
    "sg:city":"Sutherland",
    "sg:classifiers":[
        {
            "category":"Autos & Motor Vehicles",
            "subcategory":"Automobile Sales",
            "type":"Retail Goods"
        }
    ],
    "sg:phone":"+61 2 9545 8502",
    "sg:postcode":"2232",
    "sg:province":"NSW",
    "sg:tags":[
        "car",
        "new"
    ],
    "wof:name":"Tynan Kia",
    "wof:placetype":"venue"
},
  "geometry": {"coordinates":[151.074783325,-34.0340270996],"type":"Point"}
}