{
  "type": "Feature",
  "properties": {
    "addr:full":"Bremer Rd Murray Bridge SA 5253",
    "addr:postcode":"5253",
    "addr:street":"Bremer Rd",
    "iso:country":"AU",
    "sg:address":"Bremer Rd",
    "sg:city":"Murray Bridge",
    "sg:classifiers":[
        {
            "category":"Farming",
            "subcategory":"Nursery",
            "type":"Manufacturing & Wholesale Goods"
        }
    ],
    "sg:phone":"+61 8 8539 2105",
    "sg:postcode":"5253",
    "sg:province":"SA",
    "wof:name":"State Flora",
    "wof:placetype":"venue"
},
  "geometry": {"coordinates":[139.24110412600001,-35.1246147156],"type":"Point"}
}