{
  "type": "Feature",
  "properties": {
    "iso:country":"AU",
    "sg:address":"523 Bridge Rd",
    "sg:city":"Para Hills",
    "sg:classifiers":[
        {
            "category":"Retail",
            "subcategory":"Veterinary Services",
            "type":"Services"
        }
    ],
    "sg:phone":"+61 8 8258 4838",
    "sg:postcode":"5096",
    "sg:province":"SA",
    "sg:tags":[
        "surgeon"
    ],
    "wof:name":"Condon M V",
    "wof:placetype":"venue"
},
  "geometry": {"coordinates":[138.656936645,-34.7985038757],"type":"Point"}
}