{
  "type": "Feature",
  "properties": {
    "addr:full":"2 Anne St Stepney SA 5069",
    "addr:housenumber":"2",
    "addr:postcode":"5069",
    "addr:street":"Anne St",
    "iso:country":"AU",
    "sg:address":"2 Anne St",
    "sg:city":"Stepney",
    "sg:classifiers":[
        {
            "category":"Manufacturing",
            "subcategory":"Glass & Minerals",
            "type":"Manufacturing & Wholesale Goods"
        }
    ],
    "sg:phone":"+61 8 8363 5750",
    "sg:postcode":"5069",
    "sg:province":"SA",
    "sg:tags":[
        "blowing"
    ],
    "wof:name":"Blue Pony Studios",
    "wof:placetype":"venue"
},
  "geometry": {"coordinates":[138.63267517099999,-34.9148483276],"type":"Point"}
}