{
  "type": "Feature",
  "properties": {
    "addr:full":"PO Box 379 Narangba QLD 4504",
    "addr:postcode":"4504",
    "iso:country":"AU",
    "sg:address":"PO Box 379",
    "sg:city":"Narangba",
    "sg:classifiers":[
        {
            "category":"Social Services",
            "subcategory":"Retirement Home",
            "type":"Services"
        }
    ],
    "sg:phone":"+61 427 488 400",
    "sg:postcode":"4504",
    "sg:province":"QLD",
    "sg:tags":[
        "environmental",
        "consultant",
        "pollution"
    ],
    "wof:name":"Aquateco Consulting Pty Ltd",
    "wof:placetype":"venue"
},
  "geometry": {"coordinates":[152.92854309099999,-27.1869602203],"type":"Point"}
}