{
  "type": "Feature",
  "properties": {
    "addr:full":"3 Neave St Hawthorn East VIC 3123",
    "addr:housenumber":"3",
    "addr:postcode":"3123",
    "addr:street":"Neave St",
    "iso:country":"AU",
    "sg:address":"3 Neave St",
    "sg:city":"Hawthorn East",
    "sg:classifiers":[
        {
            "category":"Arts & Performance",
            "subcategory":"Art Gallery",
            "type":"Entertainment"
        }
    ],
    "sg:phone":"+61 3 9882 7696",
    "sg:postcode":"3123",
    "sg:province":"VIC",
    "wof:name":"Outback Aboriginal Art",
    "wof:placetype":"venue"
},
  "geometry": {"coordinates":[145.052001953,-37.8400421143],"type":"Point"}
}