{
  "type": "Feature",
  "properties": {
    "addr:full":"91 Main St Mornington VIC 3931",
    "addr:housenumber":"91",
    "addr:postcode":"3931",
    "addr:street":"Main St",
    "iso:country":"AU",
    "sg:address":"91 Main St",
    "sg:city":"Mornington",
    "sg:classifiers":[
        {
            "category":"Shopping",
            "subcategory":"Clothing, Apparel, & Fashions",
            "type":"Retail Goods"
        }
    ],
    "sg:phone":"+61 3 5973 4844",
    "sg:postcode":"3931",
    "sg:province":"VIC",
    "sg:tags":[
        "lady",
        "wear"
    ],
    "wof:name":"Milady",
    "wof:placetype":"venue"
},
  "geometry": {"coordinates":[145.038406372,-38.2195587158],"type":"Point"}
}