{
  "type": "Feature",
  "properties": {
    "addr:full":"Suite 38 &#039;The Anchorage&#039; 20 Masthead Dri Cleveland QLD 4163",
    "addr:housenumber":"20",
    "addr:postcode":"4163",
    "addr:street":"The;Masthead Dri",
    "iso:country":"AU",
    "sg:address":"Suite 38 &#039;The Anchorage&#039; 20 Masthead Dri",
    "sg:city":"Cleveland",
    "sg:classifiers":[
        {
            "category":"Health Services",
            "subcategory":"Health Practitioner",
            "type":"Services"
        }
    ],
    "sg:phone":"+61 7 3286 9444",
    "sg:postcode":"4163",
    "sg:province":"QLD",
    "sg:tags":[
        "physiotherapist"
    ],
    "wof:name":"Cleveland Physiotherapy & Sports Injury Clinic",
    "wof:placetype":"venue"
},
  "geometry": {"coordinates":[153.268432617,-27.5226287842],"type":"Point"}
}