{
  "type": "Feature",
  "properties": {
    "addr:full":"Suite 44/ 64 Sugar Rd Maroochydore QLD 4558",
    "addr:housenumber":"44 / 64",
    "addr:postcode":"4558",
    "addr:street":"Sugar Rd",
    "iso:country":"AU",
    "sg:address":"Suite 44/ 64 Sugar Rd",
    "sg:city":"Maroochydore",
    "sg:classifiers":[
        {
            "category":"Professional",
            "subcategory":"Management & Consulting",
            "type":"Services"
        }
    ],
    "sg:phone":"+61 424 834 344",
    "sg:postcode":"4558",
    "sg:province":"QLD",
    "sg:tags":[
        "consultant",
        "educational"
    ],
    "wof:name":"New Beginnings",
    "wof:placetype":"venue"
},
  "geometry": {"coordinates":[153.093017578,-26.6668109894],"type":"Point"}
}