{
  "type": "Feature",
  "properties": {
    "iso:country":"AU",
    "sg:address":"236 Woodward St",
    "sg:city":"Whitfield",
    "sg:classifiers":[
        {
            "category":"Building & Trades",
            "subcategory":"Construction",
            "type":"Services"
        }
    ],
    "sg:phone":"+61 7 4053 7020",
    "sg:postcode":"4870",
    "sg:province":"QLD",
    "sg:tags":[
        "renovation",
        "alterations",
        "extension",
        "contractor"
    ],
    "wof:name":"G & V Property Maintenance",
    "wof:placetype":"venue"
},
  "geometry": {"coordinates":[145.72943115199999,-16.9000759125],"type":"Point"}
}