{
  "type": "Feature",
  "properties": {
    "addr:full":"6 Greendale Crt Strathpine QLD 4500",
    "addr:housenumber":"6",
    "addr:postcode":"4500",
    "addr:street":"Greendale Crt",
    "iso:country":"AU",
    "sg:address":"6 Greendale Crt",
    "sg:city":"Strathpine",
    "sg:classifiers":[
        {
            "category":"Building & Trades",
            "subcategory":"Construction",
            "type":"Services"
        }
    ],
    "sg:phone":"+61 7 3205 2288",
    "sg:postcode":"4500",
    "sg:province":"QLD",
    "sg:tags":[
        "earth",
        "excavating",
        "moving",
        "contractor"
    ],
    "wof:name":"Winn Raphael Plant Hire",
    "wof:placetype":"venue"
},
  "geometry": {"coordinates":[152.986602783,-27.3054523468],"type":"Point"}
}