{
  "type": "Feature",
  "properties": {
    "addr:full":"Cnr Of Glenroi & Churchill Ave 23 Glenroi Ave Orange NSW 2800",
    "addr:postcode":"2800",
    "addr:street":"Ave 23 Glenroi Ave",
    "iso:country":"AU",
    "sg:address":"Cnr Of Glenroi & Churchill Ave 23 Glenroi Ave",
    "sg:city":"Orange",
    "sg:classifiers":[
        {
            "category":"Organizations",
            "subcategory":"Membership Organization",
            "type":"Services"
        }
    ],
    "sg:phone":"+61 2 6362 6653",
    "sg:postcode":"2800",
    "sg:province":"NSW",
    "sg:tags":[
        "club",
        "bridge"
    ],
    "wof:name":"Orange Bridge Club",
    "wof:placetype":"venue"
},
  "geometry": {"coordinates":[149.110671997,-33.2921562195],"type":"Point"}
}