{
  "type": "Feature",
  "properties": {
    "addr:full":"224 Scarborough Beach Rd Mt Hawthorn WA 6016",
    "addr:housenumber":"224",
    "addr:postcode":"6016",
    "addr:street":"Scarborough Beach Rd",
    "iso:country":"AU",
    "sg:address":"224 Scarborough Beach Rd",
    "sg:city":"Mt Hawthorn",
    "sg:classifiers":[
        {
            "category":"Manufacturing",
            "subcategory":"Glass & Minerals",
            "type":"Manufacturing & Wholesale Goods"
        }
    ],
    "sg:phone":"+61 8 9201 0711",
    "sg:postcode":"6016",
    "sg:province":"WA",
    "sg:tags":[
        "stained"
    ],
    "wof:name":"Goanna Stained Glass",
    "wof:placetype":"venue"
},
  "geometry": {"coordinates":[115.832679748,-31.9163894653],"type":"Point"}
}