{
  "type": "Feature",
  "properties": {
    "addr:full":"11 Rhapis Crt Buderim QLD 4556",
    "addr:housenumber":"11",
    "addr:postcode":"4556",
    "addr:street":"Rhapis Crt",
    "iso:country":"AU",
    "sg:address":"11 Rhapis Crt",
    "sg:city":"Buderim",
    "sg:classifiers":[
        {
            "category":"Building & Trades",
            "subcategory":"Plumbing",
            "type":"Services"
        }
    ],
    "sg:phone":"+61 412 166 726",
    "sg:postcode":"4556",
    "sg:province":"QLD",
    "sg:tags":[
        "plumber",
        "gasfitters"
    ],
    "wof:name":"Callanan Plumbing Services",
    "wof:placetype":"venue"
},
  "geometry": {"coordinates":[153.086837769,-26.6836948395],"type":"Point"}
}