{
  "type": "Feature",
  "properties": {
    "addr:full":"2 Blackman Crs South Windsor NSW 2756",
    "addr:housenumber":"2",
    "addr:postcode":"2756",
    "addr:street":"Blackman Crs",
    "iso:country":"AU",
    "sg:address":"2 Blackman Crs",
    "sg:city":"South Windsor",
    "sg:classifiers":[
        {
            "category":"Home & Garden",
            "subcategory":"Furniture",
            "type":"Retail Goods"
        }
    ],
    "sg:phone":"+61 2 9672 8055",
    "sg:postcode":"2756",
    "sg:province":"NSW",
    "sg:tags":[
        "business"
    ],
    "wof:name":"Abacus Office Furniture Pty Ltd",
    "wof:placetype":"venue"
},
  "geometry": {"coordinates":[150.804412842,-33.621761322],"type":"Point"}
}