{
  "type": "Feature",
  "properties": {
    "addr:full":"55 Sarton Rd Clayton North VIC 3168",
    "addr:housenumber":"55",
    "addr:postcode":"3168",
    "addr:street":"Sarton Rd",
    "iso:country":"AU",
    "sg:address":"55 Sarton Rd",
    "sg:city":"Clayton North",
    "sg:classifiers":[
        {
            "category":"Wholesale",
            "subcategory":"Metals & Minerals",
            "type":"Manufacturing & Wholesale Goods"
        }
    ],
    "sg:phone":"+61 3 9548 7214",
    "sg:postcode":"3168",
    "sg:province":"VIC",
    "sg:tags":[
        "steel",
        "stainless",
        "product",
        "equipment"
    ],
    "wof:name":"Linear Metal Polishers",
    "wof:placetype":"venue"
},
  "geometry": {"coordinates":[145.14355468799999,-37.921962738],"type":"Point"}
}