{
  "type": "Feature",
  "properties": {
    "addr:full":"136 Bannister Rd Canning Vale WA 6155",
    "addr:housenumber":"136",
    "addr:postcode":"6155",
    "addr:street":"Bannister Rd",
    "iso:country":"AU",
    "sg:address":"136 Bannister Rd",
    "sg:city":"Canning Vale",
    "sg:classifiers":[
        {
            "category":"Home & Garden",
            "subcategory":"Hardware",
            "type":"Retail Goods"
        }
    ],
    "sg:phone":"+61 8 9456 4999",
    "sg:postcode":"6155",
    "sg:province":"WA",
    "sg:tags":[
        "repair",
        "tool",
        "power"
    ],
    "wof:name":"Glenfords Discount Tool Centre",
    "wof:placetype":"venue"
},
  "geometry": {"coordinates":[115.915237,-32.058044],"type":"Point"}
}