{
  "type": "Feature",
  "properties": {
    "addr:full":"8 Sleaford Rd Windsor Gardens SA 5087",
    "addr:housenumber":"8",
    "addr:postcode":"5087",
    "addr:street":"Sleaford Rd",
    "iso:country":"AU",
    "sg:address":"8 Sleaford Rd",
    "sg:city":"Windsor Gardens",
    "sg:classifiers":[
        {
            "category":"Building & Trades",
            "subcategory":"Plumbing",
            "type":"Services"
        }
    ],
    "sg:phone":"+61 8 8369 2000",
    "sg:postcode":"5087",
    "sg:province":"SA",
    "sg:tags":[
        "plumber",
        "gasfitters"
    ],
    "wof:name":"G.N.G. Plumbing Services",
    "wof:placetype":"venue"
},
  "geometry": {"coordinates":[138.647415161,-34.8681983948],"type":"Point"}
}