{
  "type": "Feature",
  "properties": {
    "addr:full":"Unit 4, 46 Albert St Busselton WA 6280",
    "addr:housenumber":"46",
    "addr:postcode":"6280",
    "addr:street":"Albert St",
    "iso:country":"AU",
    "sg:address":"Unit 4, 46 Albert St",
    "sg:city":"Busselton",
    "sg:classifiers":[
        {
            "category":"Banks & Credit Unions",
            "subcategory":"Financial Services",
            "type":"Services"
        }
    ],
    "sg:phone":"+61 8 9752 1155",
    "sg:postcode":"6280",
    "sg:province":"WA",
    "sg:tags":[
        "annuity",
        "rollover",
        "superannuation",
        "consultant"
    ],
    "wof:name":"Mike Kearney CFP",
    "wof:placetype":"venue"
},
  "geometry": {"coordinates":[115.346237183,-33.6519889832],"type":"Point"}
}