{
  "type": "Feature",
  "properties": {
    "iso:country":"AU",
    "sg:address":"Shop 11",
    "sg:city":"Westpoint Shopping Centre Browns Plains",
    "sg:classifiers":[
        {
            "category":"Shopping",
            "subcategory":"Stationery & Office Supplies",
            "type":"Retail Goods"
        }
    ],
    "sg:phone":"+61 7 3800 3115",
    "sg:postcode":"4118",
    "sg:province":"QLD",
    "wof:name":"Officesmart",
    "wof:placetype":"venue"
},
  "geometry": {"coordinates":[153.02505493199999,-27.6665706635],"type":"Point"}
}