{
  "type": "Feature",
  "properties": {
    "addr:full":"322 Victoria St Darlinghurst NSW 2010",
    "addr:housenumber":"322",
    "addr:postcode":"2010",
    "addr:street":"Victoria St",
    "iso:country":"AU",
    "sg:address":"322 Victoria St",
    "sg:city":"Darlinghurst",
    "sg:classifiers":[
        {
            "category":"Cafe",
            "type":"Food & Drink"
        }
    ],
    "sg:phone":"+61 2 9380 5420",
    "sg:postcode":"2010",
    "sg:province":"NSW",
    "wof:name":"Coluzzi Bar",
    "wof:placetype":"venue"
},
  "geometry": {"coordinates":[151.221832275,-33.87707901],"type":"Point"}
}