{
  "type": "Feature",
  "properties": {
    "iso:country":"AU",
    "sg:address":"66- 68 Synnott St",
    "sg:city":"Werribee",
    "sg:classifiers":[
        {
            "category":"Social Services",
            "subcategory":"Adult Care",
            "type":"Services"
        }
    ],
    "sg:phone":"+61 3 9741 4466",
    "sg:postcode":"3030",
    "sg:province":"VIC",
    "sg:tags":[
        "towing"
    ],
    "wof:name":"Hoppers Crossing Towing Pty Ltd",
    "wof:placetype":"venue"
},
  "geometry": {"coordinates":[144.65919500000001,-37.903801],"type":"Point"}
}