{
  "type": "Feature",
  "properties": {
    "addr:full":"Cnr Packard & Victoria Aves Castle Hill NSW 2154",
    "addr:postcode":"2154",
    "iso:country":"AU",
    "sg:address":"Cnr Packard & Victoria Aves",
    "sg:city":"Castle Hill",
    "sg:classifiers":[
        {
            "category":"Autos & Motor Vehicles",
            "subcategory":"Automobile Sales",
            "type":"Retail Goods"
        }
    ],
    "sg:phone":"+61 2 8858 0707",
    "sg:postcode":"2154",
    "sg:province":"NSW",
    "sg:tags":[
        "car",
        "new"
    ],
    "sg:website":"http://www.heartlandmitsubishi.com.au",
    "wof:name":"Heartland Mitsubishi",
    "wof:placetype":"venue"
},
  "geometry": {"coordinates":[151.003814697,-33.7317695618],"type":"Point"}
}