{
  "type": "Feature",
  "properties": {
    "iso:country":"AU",
    "sg:address":"2- 4 Mulvihill St",
    "sg:city":"West Ryde",
    "sg:classifiers":[
        {
            "category":"Building & Trades",
            "subcategory":"Equipment Rental",
            "type":"Services"
        }
    ],
    "sg:phone":"+61 2 9808 2081",
    "sg:postcode":"2114",
    "sg:province":"NSW",
    "sg:tags":[
        "hire",
        "catering"
    ],
    "sg:website":"http://www.mobifridge.com.au",
    "wof:name":"Mobi Fridge",
    "wof:placetype":"venue"
},
  "geometry": {"coordinates":[151.093505859,-33.8115234375],"type":"Point"}
}