{
  "type": "Feature",
  "properties": {
    "iso:country":"AU",
    "sg:address":"15 Manildra Ave",
    "sg:city":"Carlingford",
    "sg:classifiers":[
        {
            "category":"Building & Trades",
            "subcategory":"Construction",
            "type":"Services"
        }
    ],
    "sg:phone":"+61 2 9872 5649",
    "sg:postcode":"2118",
    "sg:province":"NSW",
    "sg:tags":[
        "contractor"
    ],
    "wof:name":"Shannon Homes (NSW) Pty Ltd",
    "wof:placetype":"venue"
},
  "geometry": {"coordinates":[151.03361511200001,-33.7764816284],"type":"Point"}
}