{
  "type": "Feature",
  "properties": {
    "iso:country":"AU",
    "sg:address":"98 Onslow Rd",
    "sg:city":"Shenton Park",
    "sg:classifiers":[
        {
            "category":"Health Services",
            "subcategory":"Doctor",
            "type":"Services"
        }
    ],
    "sg:phone":"+61 8 9381 4547",
    "sg:postcode":"6008",
    "sg:province":"WA",
    "sg:tags":[
        "medical",
        "practitioner"
    ],
    "wof:name":"Rogers Sue Dr",
    "wof:placetype":"venue"
},
  "geometry": {"coordinates":[115.816001892,-31.9607467651],"type":"Point"}
}