{
  "type": "Feature",
  "properties": {
    "addr:full":"E 4/ 27- 29 Sariola St Silverwater NSW 2264",
    "addr:housenumber":"/;29",
    "addr:postcode":"2264",
    "addr:street":"E;27;St",
    "iso:country":"AU",
    "sg:address":"E 4/ 27- 29 Sariola St",
    "sg:city":"Silverwater",
    "sg:classifiers":[
        {
            "category":"Professional",
            "subcategory":"Computer Services",
            "type":"Services"
        }
    ],
    "sg:phone":"+61 2 8748 9500",
    "sg:postcode":"2264",
    "sg:province":"NSW",
    "sg:tags":[
        "equipment",
        "networking",
        "installation"
    ],
    "wof:name":"Krone",
    "wof:placetype":"venue"
},
  "geometry": {"coordinates":[151.54377700000001,-33.070957],"type":"Point"}
}