{
  "type": "Feature",
  "properties": {
    "addr:full":"1/ 5 Collingwood St Osborne Park WA 6017",
    "addr:housenumber":"/ 5",
    "addr:postcode":"6017",
    "addr:street":"Collingwood St",
    "iso:country":"AU",
    "sg:address":"1/ 5 Collingwood St",
    "sg:city":"Osborne Park",
    "sg:classifiers":[
        {
            "category":"Building & Trades",
            "subcategory":"Construction",
            "type":"Services"
        }
    ],
    "sg:phone":"+61 8 9244 8882",
    "sg:postcode":"6017",
    "sg:province":"WA",
    "sg:tags":[
        "window",
        "tinting"
    ],
    "wof:name":"Sun Pro",
    "wof:placetype":"venue"
},
  "geometry": {"coordinates":[115.816612244,-31.9042224884],"type":"Point"}
}