{
  "type": "Feature",
  "properties": {
    "addr:full":"U1/ 110 Harris St Harris Park NSW 2150",
    "addr:housenumber":"110",
    "addr:postcode":"2150",
    "addr:street":"U1 /;Harris St",
    "iso:country":"AU",
    "sg:address":"U1/ 110 Harris St",
    "sg:city":"Harris Park",
    "sg:classifiers":[
        {
            "category":"Professional",
            "subcategory":"Detective & Security Services",
            "type":"Services"
        }
    ],
    "sg:phone":"+61 2 9687 7244",
    "sg:postcode":"2150",
    "sg:province":"NSW",
    "sg:tags":[
        "guard",
        "patrol"
    ],
    "wof:name":"Accord Security Services",
    "wof:placetype":"venue"
},
  "geometry": {"coordinates":[151.011154175,-33.8188781738],"type":"Point"}
}