{
  "type": "Feature",
  "properties": {
    "addr:full":"16 Woodland Drv Peregian Beach QLD 4573",
    "addr:housenumber":"16",
    "addr:postcode":"4573",
    "addr:street":"Woodland Drv",
    "iso:country":"AU",
    "sg:address":"16 Woodland Drv",
    "sg:city":"Peregian Beach",
    "sg:classifiers":[
        {
            "category":"Government",
            "subcategory":"Department Of Motor Vehicles",
            "type":"Public Place"
        }
    ],
    "sg:phone":"+61 7 5448 1004",
    "sg:postcode":"4573",
    "sg:province":"QLD",
    "sg:tags":[
        "wholesaler",
        "mfrs",
        "accessory"
    ],
    "wof:name":"Virtual Trak Pty Ltd",
    "wof:placetype":"venue"
},
  "geometry": {"coordinates":[153.09324599999999,-26.47785],"type":"Point"}
}