{
  "type": "Feature",
  "properties": {
    "iso:country":"AU",
    "sg:address":"Unit 3/ 217-219 Mickleham Rd",
    "sg:city":"Tullamarine",
    "sg:classifiers":[
        {
            "category":"Shopping",
            "subcategory":"Gifts & Souvenirs",
            "type":"Retail Goods"
        }
    ],
    "sg:phone":"+61 3 8336 1002",
    "sg:postcode":"3043",
    "sg:province":"VIC",
    "sg:tags":[
        "shop",
        "supply"
    ],
    "wof:name":"Rivergums & Roses",
    "wof:placetype":"venue"
},
  "geometry": {"coordinates":[144.882415772,-37.6852874756],"type":"Point"}
}