{
  "type": "Feature",
  "properties": {
    "iso:country":"AU",
    "sg:address":"48 Railway Pde",
    "sg:city":"Granville",
    "sg:classifiers":[
        {
            "category":"Food & Beverages",
            "subcategory":"Bakery",
            "type":"Retail Goods"
        }
    ],
    "sg:phone":"+61 2 9637 8092",
    "sg:postcode":"2142",
    "sg:province":"NSW",
    "sg:tags":[
        "cake",
        "shop",
        "pastry"
    ],
    "wof:name":"Abla Pastry",
    "wof:placetype":"venue"
},
  "geometry": {"coordinates":[151.00897216800001,-33.8315505981],"type":"Point"}
}