{
  "type": "Feature",
  "properties": {
    "addr:full":"65 Percy St Wellington NSW 2820",
    "addr:housenumber":"65",
    "addr:postcode":"2820",
    "addr:street":"Percy St",
    "iso:country":"AU",
    "sg:address":"65 Percy St",
    "sg:city":"Wellington",
    "sg:classifiers":[
        {
            "category":"Health Services",
            "subcategory":"Health Practitioner",
            "type":"Services"
        }
    ],
    "sg:phone":"+61 427 467 561",
    "sg:postcode":"2820",
    "sg:province":"NSW",
    "sg:tags":[
        "bowen",
        "therapy"
    ],
    "wof:name":"Ian Ponder",
    "wof:placetype":"venue"
},
  "geometry": {"coordinates":[148.94291687,-32.5519714355],"type":"Point"}
}