{
  "type": "Feature",
  "properties": {
    "addr:full":"Unit 4/7- 9 Sheriffs Rd Lonsdale SA 5160",
    "addr:housenumber":"9",
    "addr:postcode":"5160",
    "addr:street":"Sheriffs Rd",
    "iso:country":"AU",
    "sg:address":"Unit 4/7- 9 Sheriffs Rd",
    "sg:city":"Lonsdale",
    "sg:classifiers":[
        {
            "category":"Utilities",
            "subcategory":"Electric",
            "type":"Services"
        }
    ],
    "sg:phone":"+61 8 8322 9840",
    "sg:postcode":"5160",
    "sg:province":"SA",
    "sg:tags":[
        "electrical",
        "contractor"
    ],
    "wof:name":"T.F. Electrical Services",
    "wof:placetype":"venue"
},
  "geometry": {"coordinates":[138.504272461,-35.1060562134],"type":"Point"}
}