{
  "type": "Feature",
  "properties": {
    "addr:full":"43 Brisbane Water Drv Point Clare NSW 2250",
    "addr:housenumber":"43",
    "addr:postcode":"2250",
    "addr:street":"Brisbane Water Drv",
    "iso:country":"AU",
    "sg:address":"43 Brisbane Water Drv",
    "sg:city":"Point Clare",
    "sg:classifiers":[
        {
            "category":"Fast Food",
            "type":"Food & Drink"
        }
    ],
    "sg:phone":"+61 2 4325 3345",
    "sg:postcode":"2250",
    "sg:province":"NSW",
    "sg:tags":[
        "away",
        "take"
    ],
    "wof:name":"Point Clare Chinese Take Away",
    "wof:placetype":"venue"
},
  "geometry": {"coordinates":[151.327728272,-33.4465713501],"type":"Point"}
}