{
  "type": "Feature",
  "properties": {
    "addr:full":"140 Watkins Rd Wangi Wangi NSW 2267",
    "addr:housenumber":"140",
    "addr:postcode":"2267",
    "addr:street":"Watkins Rd",
    "iso:country":"AU",
    "sg:address":"140 Watkins Rd",
    "sg:city":"Wangi Wangi",
    "sg:classifiers":[
        {
            "category":"Utilities",
            "subcategory":"Electric",
            "type":"Services"
        }
    ],
    "sg:phone":"+61 2 4975 1403",
    "sg:postcode":"2267",
    "sg:province":"NSW",
    "sg:tags":[
        "electrical",
        "contractor"
    ],
    "wof:name":"Williams Phil",
    "wof:placetype":"venue"
},
  "geometry": {"coordinates":[151.596756,-33.071426],"type":"Point"}
}