{
  "type": "Feature",
  "properties": {
    "iso:country":"AU",
    "sg:address":"381 Taronga Rd",
    "sg:city":"Hawthorn East",
    "sg:classifiers":[
        {
            "category":"Insurance",
            "subcategory":"Insurance Agent",
            "type":"Services"
        }
    ],
    "sg:phone":"+61 3 9679 0533",
    "sg:postcode":"3123",
    "sg:province":"VIC",
    "sg:tags":[
        "broker"
    ],
    "wof:name":"Your Insurance Group",
    "wof:placetype":"venue"
},
  "geometry": {"coordinates":[145.047409058,-37.8310127258],"type":"Point"}
}