{
  "type": "Feature",
  "properties": {
    "addr:full":"279 Main South Rd Morphett Vale SA 5162",
    "addr:housenumber":"279",
    "addr:postcode":"5162",
    "addr:street":"Main South Rd",
    "iso:country":"AU",
    "sg:address":"279 Main South Rd",
    "sg:city":"Morphett Vale",
    "sg:classifiers":[
        {
            "category":"Wholesale",
            "subcategory":"Painting Supplies",
            "type":"Manufacturing & Wholesale Goods"
        }
    ],
    "sg:phone":"+61 8 8326 0011",
    "sg:postcode":"5162",
    "sg:province":"SA",
    "sg:tags":[
        "wholesaler",
        "paint",
        "mfrs"
    ],
    "wof:name":"Solver Paints",
    "wof:placetype":"venue"
},
  "geometry": {"coordinates":[138.522613525,-35.1163902283],"type":"Point"}
}