{
  "type": "Feature",
  "properties": {
    "iso:country":"AU",
    "sg:address":"48 Brice Ave",
    "sg:city":"Mooroolbark",
    "sg:classifiers":[
        {
            "category":"Real Estate",
            "subcategory":"Real Estate Agent",
            "type":"Services"
        }
    ],
    "sg:phone":"+61 3 9726 8888",
    "sg:postcode":"3138",
    "sg:province":"VIC",
    "wof:name":"Professionals",
    "wof:placetype":"venue"
},
  "geometry": {"coordinates":[145.312988281,-37.7851982117],"type":"Point"}
}