{
  "type": "Feature",
  "properties": {
    "addr:full":"Fact 26, 65 Canterbury Rd Montrose VIC 3765",
    "addr:housenumber":"26 65",
    "addr:postcode":"3765",
    "addr:street":"Fact;Canterbury Rd",
    "iso:country":"AU",
    "sg:address":"Fact 26, 65 Canterbury Rd",
    "sg:city":"Montrose",
    "sg:classifiers":[
        {
            "category":"Retail",
            "subcategory":"Repair Shop",
            "type":"Services"
        }
    ],
    "sg:phone":"+61 3 9761 9044",
    "sg:postcode":"3765",
    "sg:province":"VIC",
    "sg:tags":[
        "machine",
        "repairs",
        "part",
        "dryer",
        "washing"
    ],
    "wof:name":"Jim Mills & Sons Refrigeration",
    "wof:placetype":"venue"
},
  "geometry": {"coordinates":[145.32728576700001,-37.8151245117],"type":"Point"}
}