{
  "type": "Feature",
  "properties": {
    "addr:full":"PO Box 318 Bentleigh VIC 3204",
    "addr:postcode":"3204",
    "iso:country":"AU",
    "sg:address":"PO Box 318",
    "sg:city":"Bentleigh",
    "sg:classifiers":[
        {
            "category":"Home & Garden",
            "subcategory":"Kitchen Supply",
            "type":"Retail Goods"
        }
    ],
    "sg:phone":"+61 3 9553 8114",
    "sg:postcode":"3204",
    "sg:province":"VIC",
    "sg:tags":[
        "traffic",
        "equipment",
        "safety",
        "road"
    ],
    "wof:name":"Roadworx Traffic Solutions",
    "wof:placetype":"venue"
},
  "geometry": {"coordinates":[145.026962,-37.91193],"type":"Point"}
}