{
  "type": "Feature",
  "properties": {
    "addr:full":"15 Wallace St Chermside QLD 4032",
    "addr:housenumber":"15",
    "addr:postcode":"qld 4032",
    "addr:street":"Wallace St",
    "iso:country":"AU",
    "sg:address":"15 Wallace St",
    "sg:city":"Chermside",
    "sg:classifiers":[
        {
            "category":"Health Services",
            "subcategory":"Health Practitioner",
            "type":"Services"
        }
    ],
    "sg:phone":"+61 7 3350 5060",
    "sg:postcode":"4032",
    "sg:province":"QLD",
    "sg:tags":[
        "psychologist"
    ],
    "wof:name":"Diane O&#039;Malley",
    "wof:placetype":"venue"
},
  "geometry": {"coordinates":[153.030563,-27.38953],"type":"Point"}
}