{
  "type": "Feature",
  "properties": {
    "addr:full":"9 Lowana Ave Kirrawee NSW 2232",
    "addr:housenumber":"9",
    "addr:postcode":"2232",
    "addr:street":"Lowana Ave",
    "iso:country":"AU",
    "sg:address":"9 Lowana Ave",
    "sg:city":"Kirrawee",
    "sg:classifiers":[
        {
            "category":"Professional",
            "subcategory":"Accounting & Tax Preparation",
            "type":"Services"
        }
    ],
    "sg:phone":"+61 2 9521 1166",
    "sg:postcode":"2232",
    "sg:province":"NSW",
    "sg:tags":[
        "accountant",
        "auditor"
    ],
    "wof:name":"Harris J E",
    "wof:placetype":"venue"
},
  "geometry": {"coordinates":[151.076080322,-34.0382194519],"type":"Point"}
}