{
  "type": "Feature",
  "properties": {
    "addr:full":"9 Manatunga Crs Greensborough VIC 3088",
    "addr:housenumber":"9",
    "addr:postcode":"3088",
    "addr:street":"Manatunga Crs",
    "iso:country":"AU",
    "sg:address":"9 Manatunga Crs",
    "sg:city":"Greensborough",
    "sg:classifiers":[
        {
            "category":"Real Estate",
            "subcategory":"Architect",
            "type":"Services"
        }
    ],
    "sg:phone":"+61 3 9434 6236",
    "sg:postcode":"3088",
    "sg:province":"VIC",
    "wof:name":"Bo Ronngard",
    "wof:placetype":"venue"
},
  "geometry": {"coordinates":[145.10710144000001,-37.6963996887],"type":"Point"}
}