{
  "type": "Feature",
  "properties": {
    "iso:country":"AU",
    "sg:address":"Churchhill Ave",
    "sg:city":"Subiaco",
    "sg:classifiers":[
        {
            "category":"Shopping",
            "subcategory":"Pets & Pet Supplies",
            "type":"Retail Goods"
        }
    ],
    "sg:phone":"+61 8 9381 7325",
    "sg:postcode":"6008",
    "sg:province":"WA",
    "sg:tags":[
        "food"
    ],
    "wof:name":"Subiaco Birds & Tropical Fish",
    "wof:placetype":"venue"
},
  "geometry": {"coordinates":[115.825439453,-31.947889328],"type":"Point"}
}