{
  "type": "Feature",
  "properties": {
    "addr:full":"Unit2/ 358 Nudgee Rd Hendra QLD 4011",
    "addr:housenumber":"358",
    "addr:postcode":"4011",
    "addr:street":"Nudgee Rd",
    "iso:country":"AU",
    "sg:address":"Unit2/ 358 Nudgee Rd",
    "sg:city":"Hendra",
    "sg:classifiers":[
        {
            "category":"Structure",
            "subcategory":"Tunnel",
            "type":"Public Place"
        }
    ],
    "sg:phone":"+61 7 3868 3773",
    "sg:postcode":"4011",
    "sg:province":"QLD",
    "sg:tags":[
        "cleaner",
        "industrial",
        "vacuum"
    ],
    "sg:website":"http://www.qldcleaning.com",
    "wof:name":"Queensland Cleaning Supplies & Australian Safety Matting",
    "wof:placetype":"venue"
},
  "geometry": {"coordinates":[153.073746,-27.418232],"type":"Point"}
}