{
  "type": "Feature",
  "properties": {
    "addr:full":"Macarthur Rd Elderslie NSW 2570",
    "addr:postcode":"2570",
    "addr:street":"Macarthur Rd",
    "iso:country":"AU",
    "sg:address":"Macarthur Rd",
    "sg:city":"Elderslie",
    "sg:classifiers":[
        {
            "category":"Home & Garden",
            "subcategory":"Garden Supply",
            "type":"Retail Goods"
        }
    ],
    "sg:phone":"+61 2 4658 1666",
    "sg:postcode":"2570",
    "sg:province":"NSW",
    "sg:tags":[
        "turf",
        "lawn"
    ],
    "wof:name":"M. Collins & Sons (Contractors) Pty Limited",
    "wof:placetype":"venue"
},
  "geometry": {"coordinates":[150.713287353,-34.0683135986],"type":"Point"}
}