{
  "type": "Feature",
  "properties": {
    "addr:full":"6 Club Point Drv Chirnside Park VIC 3116",
    "addr:housenumber":"6",
    "addr:postcode":"3116",
    "addr:street":"Club Point Drv",
    "iso:country":"AU",
    "sg:address":"6 Club Point Drv",
    "sg:city":"Chirnside Park",
    "sg:classifiers":[
        {
            "category":"Professional",
            "subcategory":"Management & Consulting",
            "type":"Services"
        }
    ],
    "sg:phone":"+61 3 9727 5241",
    "sg:postcode":"3116",
    "sg:province":"VIC",
    "sg:tags":[
        "consultant"
    ],
    "wof:name":"Derek Stockley",
    "wof:placetype":"venue"
},
  "geometry": {"coordinates":[145.327468872,-37.751750946],"type":"Point"}
}