{
  "type": "Feature",
  "properties": {
    "addr:full":"1st Floor, 43 Comrie St Wanniassa ACT 2903",
    "addr:housenumber":"43",
    "addr:postcode":"2903",
    "addr:street":"Comrie St",
    "iso:country":"AU",
    "sg:address":"1st Floor, 43 Comrie St",
    "sg:city":"Wanniassa",
    "sg:classifiers":[
        {
            "category":"Health Services",
            "subcategory":"Dentist",
            "type":"Services"
        }
    ],
    "sg:phone":"+61 2 6231 0001",
    "sg:postcode":"2903",
    "sg:province":"ACT",
    "wof:name":"Wanniassa Dental Surgery",
    "wof:placetype":"venue"
},
  "geometry": {"coordinates":[149.09959411599999,-35.4029502869],"type":"Point"}
}