{
  "type": "Feature",
  "properties": {
    "addr:full":"Cnr Riseley St & Kearns Crs Ardross WA 6153",
    "addr:postcode":"6153",
    "addr:street":"Cnr Riseley St & Kearns Crs",
    "iso:country":"AU",
    "sg:address":"Cnr Riseley St & Kearns Crs",
    "sg:city":"Ardross",
    "sg:classifiers":[
        {
            "category":"Fast Food",
            "type":"Food & Drink"
        }
    ],
    "sg:phone":"+61 8 9364 5262",
    "sg:postcode":"6153",
    "sg:province":"WA",
    "sg:tags":[
        "away",
        "take"
    ],
    "wof:name":"Red Rooster",
    "wof:placetype":"venue"
},
  "geometry": {"coordinates":[115.834457,-32.020794],"type":"Point"}
}