{
  "type": "Feature",
  "properties": {
    "iso:country":"AU",
    "sg:address":"6 Oxford St",
    "sg:city":"Darlinghurst",
    "sg:classifiers":[
        {
            "category":"Shopping",
            "subcategory":"Clothing, Apparel, & Fashions",
            "type":"Retail Goods"
        }
    ],
    "sg:phone":"+61 2 9380 6365",
    "sg:postcode":"2010",
    "sg:province":"NSW",
    "sg:tags":[
        "menswear"
    ],
    "wof:name":"Scavenge",
    "wof:placetype":"venue"
},
  "geometry": {"coordinates":[151.212692261,-33.8769989014],"type":"Point"}
}