{
  "type": "Feature",
  "properties": {
    "iso:country":"AU",
    "sg:address":"163 Lachlan St",
    "sg:city":"Hay",
    "sg:classifiers":[
        {
            "category":"Education",
            "subcategory":"Special Training",
            "type":"Public Place"
        }
    ],
    "sg:phone":"+61 2 6993 4411",
    "sg:postcode":"2711",
    "sg:province":"NSW",
    "sg:tags":[
        "development"
    ],
    "wof:name":"Murray Mallee Training Company Pty Ltd",
    "wof:placetype":"venue"
},
  "geometry": {"coordinates":[144.84390258799999,-34.5081596375],"type":"Point"}
}