{
  "type": "Feature",
  "properties": {
    "addr:full":"106 Glen Iris Rd Glen Iris VIC 3146",
    "addr:housenumber":"106",
    "addr:postcode":"3146",
    "addr:street":"Glen Iris Rd",
    "iso:country":"AU",
    "sg:address":"106 Glen Iris Rd",
    "sg:city":"Glen Iris",
    "sg:classifiers":[
        {
            "category":"Food & Beverages",
            "subcategory":"Groceries & Convenience Stores",
            "type":"Retail Goods"
        }
    ],
    "sg:phone":"+61 3 9889 7092",
    "sg:postcode":"3146",
    "sg:province":"VIC",
    "wof:name":"Glen Iris Milk Bar",
    "wof:placetype":"venue"
},
  "geometry": {"coordinates":[145.06738281200001,-37.8528747559],"type":"Point"}
}