{
  "type": "Feature",
  "properties": {
    "iso:country":"AU",
    "sg:address":"752 Albany Hwy",
    "sg:city":"Bedfordale",
    "sg:classifiers":[
        {
            "category":"Farming",
            "subcategory":"Livestock Farm",
            "type":"Manufacturing & Wholesale Goods"
        }
    ],
    "sg:phone":"+61 8 9498 2288",
    "sg:postcode":"6112",
    "sg:province":"WA",
    "sg:tags":[
        "agistment"
    ],
    "wof:name":"Balmoral Park Agistment",
    "wof:placetype":"venue"
},
  "geometry": {"coordinates":[116.084587097,-32.1826820374],"type":"Point"}
}