{
  "type": "Feature",
  "properties": {
    "iso:country":"AU",
    "sg:address":"PO Box 2383",
    "sg:city":"Kent Town",
    "sg:classifiers":[
        {
            "category":"Farming",
            "subcategory":"Vineyard",
            "type":"Manufacturing & Wholesale Goods"
        }
    ],
    "sg:phone":"+61 8 8272 6111",
    "sg:postcode":"5067",
    "sg:province":"SA",
    "sg:tags":[
        "winery"
    ],
    "wof:name":"sawine.com.au",
    "wof:placetype":"venue"
},
  "geometry": {"coordinates":[138.617584228,-34.9208984375],"type":"Point"}
}