{
  "type": "Feature",
  "properties": {
    "iso:country":"AU",
    "sg:address":"60 Eastern Rd",
    "sg:city":"South Melbourne",
    "sg:classifiers":[
        {
            "category":"Building & Trades",
            "subcategory":"Construction",
            "type":"Services"
        }
    ],
    "sg:phone":"+61 3 9645 5999",
    "sg:postcode":"3205",
    "sg:province":"VIC",
    "sg:tags":[
        "contractor"
    ],
    "wof:name":"Built Environs Pty Ltd",
    "wof:placetype":"venue"
},
  "geometry": {"coordinates":[144.966644,-37.836014],"type":"Point"}
}