{
  "type": "Feature",
  "properties": {
    "addr:full":"9 Mann Rd Mt Eliza VIC 3930",
    "addr:housenumber":"9",
    "addr:postcode":"3930",
    "addr:street":"Mann Rd",
    "iso:country":"AU",
    "sg:address":"9 Mann Rd",
    "sg:city":"Mt Eliza",
    "sg:classifiers":[
        {
            "category":"Building & Trades",
            "subcategory":"Construction",
            "type":"Services"
        }
    ],
    "sg:phone":"+61 412 266 506",
    "sg:postcode":"3930",
    "sg:province":"VIC",
    "sg:tags":[
        "stonework",
        "stone",
        "mason"
    ],
    "wof:name":"Watts Stone Constructions Pty Ltd",
    "wof:placetype":"venue"
},
  "geometry": {"coordinates":[145.101654053,-38.1716690063],"type":"Point"}
}