{
  "type": "Feature",
  "properties": {
    "addr:full":"Factory 12/ 13 Molan St Ringwood VIC 3134",
    "addr:housenumber":"12 / 13",
    "addr:postcode":"3134",
    "addr:street":"Molan St",
    "iso:country":"AU",
    "sg:address":"Factory 12/ 13 Molan St",
    "sg:city":"Ringwood",
    "sg:classifiers":[
        {
            "category":"Manufacturing",
            "subcategory":"Metals",
            "type":"Manufacturing & Wholesale Goods"
        }
    ],
    "sg:phone":"+61 3 9870 8886",
    "sg:postcode":"3134",
    "sg:province":"VIC",
    "sg:tags":[
        "spinner"
    ],
    "wof:name":"Ablaze Metal Spinning",
    "wof:placetype":"venue"
},
  "geometry": {"coordinates":[145.21783447300001,-37.8193855286],"type":"Point"}
}