{
  "type": "Feature",
  "properties": {
    "addr:full":"49 Reid St Wangaratta VIC 3677",
    "addr:housenumber":"49",
    "addr:postcode":"3677",
    "addr:street":"Reid St",
    "iso:country":"AU",
    "sg:address":"49 Reid St",
    "sg:city":"Wangaratta",
    "sg:classifiers":[
        {
            "category":"Real Estate",
            "subcategory":"Real Estate Agent",
            "type":"Services"
        }
    ],
    "sg:phone":"+61 3 5721 2014",
    "sg:postcode":"3677",
    "sg:province":"VIC",
    "wof:name":"Morris Bros Pty Ltd",
    "wof:placetype":"venue"
},
  "geometry": {"coordinates":[146.32583618199999,-36.3547592163],"type":"Point"}
}