{
  "type": "Feature",
  "properties": {
    "addr:full":"Shop 3/ 153 Rememberance Drv Tahmoor NSW 2573",
    "addr:housenumber":"shop 3 / 153",
    "addr:postcode":"2573",
    "addr:street":"Rememberance Drv",
    "iso:country":"AU",
    "sg:address":"Shop 3/ 153 Rememberance Drv",
    "sg:city":"Tahmoor",
    "sg:classifiers":[
        {
            "category":"Communications",
            "subcategory":"Film & Video Production",
            "type":"Services"
        }
    ],
    "sg:phone":"+61 2 4681 9348",
    "sg:postcode":"2573",
    "sg:province":"NSW",
    "sg:tags":[
        "dvd",
        "library"
    ],
    "wof:name":"Movies 4U",
    "wof:placetype":"venue"
},
  "geometry": {"coordinates":[150.59205627399999,-34.2254867554],"type":"Point"}
}