{
  "type": "Feature",
  "properties": {
    "addr:full":"Unit 7/ 38-40 Tattersall Rd Kings Park NSW 2148",
    "addr:housenumber":"/ 38-40",
    "addr:postcode":"2148",
    "addr:street":"Tattersall Rd",
    "iso:country":"AU",
    "sg:address":"Unit 7/ 38-40 Tattersall Rd",
    "sg:city":"Kings Park",
    "sg:classifiers":[
        {
            "category":"Retail",
            "subcategory":"Auto Repair",
            "type":"Services"
        }
    ],
    "sg:phone":"+61 2 9676 1397",
    "sg:postcode":"2148",
    "sg:province":"NSW",
    "sg:tags":[
        "repairer",
        "motor",
        "engineer"
    ],
    "wof:name":"D R C Automotive Pty Ltd",
    "wof:placetype":"venue"
},
  "geometry": {"coordinates":[150.91175842300001,-33.7486457825],"type":"Point"}
}