{
  "type": "Feature",
  "properties": {
    "addr:full":"115 Green Trees Rd Gympie QLD 4570",
    "addr:housenumber":"115",
    "addr:postcode":"4570",
    "addr:street":"Green Trees Rd",
    "iso:country":"AU",
    "sg:address":"115 Green Trees Rd",
    "sg:city":"Gympie",
    "sg:classifiers":[
        {
            "category":"Commercial Area",
            "type":"Public Place"
        }
    ],
    "sg:phone":"+61 428 711 770",
    "sg:postcode":"4570",
    "sg:province":"QLD",
    "sg:tags":[
        "heavy",
        "carrier"
    ],
    "wof:name":"Rainbow Beach Transport",
    "wof:placetype":"venue"
},
  "geometry": {"coordinates":[152.72250366200001,-26.2242507935],"type":"Point"}
}