{
  "type": "Feature",
  "properties": {
    "addr:full":"Fct 2 / 52 Smith Rd Springvale VIC 3171",
    "addr:housenumber":"2 / 52",
    "addr:postcode":"3171",
    "addr:street":"Fct;Smith Rd",
    "iso:country":"AU",
    "sg:address":"Fct 2 / 52 Smith Rd",
    "sg:city":"Springvale",
    "sg:classifiers":[
        {
            "category":"Utilities",
            "type":"Services"
        }
    ],
    "sg:phone":"+61 3 9574 0030",
    "sg:postcode":"3171",
    "sg:province":"VIC",
    "sg:tags":[
        "refrigeration",
        "industrial",
        "commercial",
        "retail"
    ],
    "wof:name":"A Faire Air Conditioning Services",
    "wof:placetype":"venue"
},
  "geometry": {"coordinates":[145.16990661599999,-37.9407653809],"type":"Point"}
}