{
  "type": "Feature",
  "properties": {
    "addr:full":"Unit 3 35 Cooper Rd Jandakot WA 6164",
    "addr:housenumber":"35",
    "addr:postcode":"6164",
    "addr:street":"Cooper Rd",
    "iso:country":"AU",
    "sg:address":"Unit 3 35 Cooper Rd",
    "sg:city":"Jandakot",
    "sg:classifiers":[
        {
            "category":"Autos & Motor Vehicles",
            "subcategory":"Fuel & Gas Station",
            "type":"Retail Goods"
        }
    ],
    "sg:phone":"+61 418 945 741",
    "sg:postcode":"6164",
    "sg:province":"WA",
    "sg:tags":[
        "petrol",
        "marketing",
        "pump",
        "equipment"
    ],
    "wof:name":"Martin Skinner Petroleum Services",
    "wof:placetype":"venue"
},
  "geometry": {"coordinates":[115.845596,-32.124748],"type":"Point"}
}