{
  "type": "Feature",
  "properties": {
    "iso:country":"AU",
    "sg:address":"RSDE 1356",
    "sg:city":"Ballarat",
    "sg:classifiers":[
        {
            "category":"Home & Garden",
            "subcategory":"Garden Supply",
            "type":"Retail Goods"
        }
    ],
    "sg:phone":"+61 1300 303 239",
    "sg:postcode":"3352",
    "sg:province":"VIC",
    "sg:tags":[
        "equipment"
    ],
    "wof:name":"Amber Garden Products Australia Pty Ltd",
    "wof:placetype":"venue"
},
  "geometry": {"coordinates":[143.891983,-37.435986],"type":"Point"}
}