{
  "type": "Feature",
  "properties": {
    "iso:country":"AU",
    "sg:address":"Suite 5/ 41 Wason St",
    "sg:city":"Milton",
    "sg:classifiers":[
        {
            "category":"Banks & Credit Unions",
            "subcategory":"Bank",
            "type":"Services"
        }
    ],
    "sg:phone":"+61 1300 886 339",
    "sg:postcode":"2538",
    "sg:province":"NSW",
    "sg:tags":[
        "broker",
        "mortgage"
    ],
    "wof:name":"Milton Ulladulla Money",
    "wof:placetype":"venue"
},
  "geometry": {"coordinates":[150.435745239,-35.3164596558],"type":"Point"}
}