{
  "type": "Feature",
  "properties": {
    "addr:full":"Unit 7/ 23 Richland Ave Coopers Plains QLD 4108",
    "addr:postcode":"4108",
    "addr:street":"Richland Ave",
    "iso:country":"AU",
    "sg:address":"Unit 7/ 23 Richland Ave",
    "sg:city":"Coopers Plains",
    "sg:classifiers":[
        {
            "category":"Social Services",
            "subcategory":"Adult Care",
            "type":"Services"
        }
    ],
    "sg:phone":"+61 7 3274 1562",
    "sg:postcode":"4108",
    "sg:province":"QLD",
    "sg:tags":[
        "towing"
    ],
    "wof:name":"Sunnybank Towing",
    "wof:placetype":"venue"
},
  "geometry": {"coordinates":[153.02772522000001,-27.5678787231],"type":"Point"}
}