{
  "type": "Feature",
  "properties": {
    "iso:country":"AU",
    "sg:address":"497 Lutwyche Rd",
    "sg:city":"Lutwyche",
    "sg:classifiers":[
        {
            "category":"Shopping",
            "subcategory":"Clothing, Apparel, & Fashions",
            "type":"Retail Goods"
        }
    ],
    "sg:phone":"+61 7 3357 9846",
    "sg:postcode":"4030",
    "sg:province":"QLD",
    "sg:tags":[
        "lady",
        "wear"
    ],
    "wof:name":"Anna Marias Boutique",
    "wof:placetype":"venue"
},
  "geometry": {"coordinates":[153.033905,-27.422989],"type":"Point"}
}