{
  "type": "Feature",
  "properties": {
    "addr:full":"Shop 3, 1761 Pittwater Rd Mona Vale NSW 2103",
    "addr:housenumber":"shop 3",
    "addr:postcode":"1761;2103",
    "addr:street":"Pittwater Rd",
    "iso:country":"AU",
    "sg:address":"Shop 3, 1761 Pittwater Rd",
    "sg:city":"Mona Vale",
    "sg:classifiers":[
        {
            "category":"Shopping",
            "subcategory":"Shoes",
            "type":"Retail Goods"
        }
    ],
    "sg:phone":"+61 2 9979 4144",
    "sg:postcode":"2103",
    "sg:province":"NSW",
    "sg:tags":[
        "footwear"
    ],
    "wof:name":"Birkenstock By Nature",
    "wof:placetype":"venue"
},
  "geometry": {"coordinates":[151.30361938499999,-33.6770477295],"type":"Point"}
}