{
  "type": "Feature",
  "properties": {
    "addr:full":"150 Mill Point Rd South Perth WA 6151",
    "addr:housenumber":"150",
    "addr:postcode":"6151",
    "addr:street":"Mill Point Rd",
    "iso:country":"AU",
    "sg:address":"150 Mill Point Rd",
    "sg:city":"South Perth",
    "sg:classifiers":[
        {
            "category":"Professional",
            "subcategory":"Business Services",
            "type":"Services"
        }
    ],
    "sg:phone":"+61 8 9367 1426",
    "sg:postcode":"6151",
    "sg:province":"WA",
    "sg:tags":[
        "drafting"
    ],
    "wof:name":"Phil Cross & Associates Drafting Service Pty Ltd",
    "wof:placetype":"venue"
},
  "geometry": {"coordinates":[115.854828,-31.974804],"type":"Point"}
}