{
  "type": "Feature",
  "properties": {
    "iso:country":"AU",
    "sg:address":"7 Blaikie St",
    "sg:city":"Myaree",
    "sg:classifiers":[
        {
            "category":"Shopping",
            "subcategory":"Mobile Phones",
            "type":"Retail Goods"
        }
    ],
    "sg:phone":"+61 8 9330 2500",
    "sg:postcode":"6154",
    "sg:province":"WA",
    "sg:tags":[
        "wholesaler",
        "mfrs",
        "electrical",
        "switchboard"
    ],
    "wof:name":"Keyline Industries Pty Ltd",
    "wof:placetype":"venue"
},
  "geometry": {"coordinates":[115.821327,-32.04232],"type":"Point"}
}