{
  "type": "Feature",
  "properties": {
    "iso:country":"AU",
    "sg:address":"PO Box 420",
    "sg:city":"Buddina",
    "sg:classifiers":[
        {
            "category":"Home & Garden",
            "subcategory":"Carpets & Floor Coverings",
            "type":"Retail Goods"
        }
    ],
    "sg:phone":"+61 7 5493 4688",
    "sg:postcode":"4575",
    "sg:province":"QLD",
    "sg:tags":[
        "tile",
        "wall"
    ],
    "sg:website":"http://www.concepttiles.com.au",
    "wof:name":"Concept Tiles & Surfaces",
    "wof:placetype":"venue"
},
  "geometry": {"coordinates":[153.128891,-26.73254],"type":"Point"}
}