{
  "type": "Feature",
  "properties": {
    "addr:full":"Checker Rd Waikerie SA 5330",
    "addr:postcode":"5330",
    "addr:street":"Checker Rd",
    "iso:country":"AU",
    "sg:address":"Checker Rd",
    "sg:city":"Waikerie",
    "sg:classifiers":[
        {
            "category":"Wholesale",
            "subcategory":"Wine & Distilled Alcoholic Beverages",
            "type":"Manufacturing & Wholesale Goods"
        }
    ],
    "sg:phone":"+61 8 8541 2372",
    "sg:postcode":"5330",
    "sg:province":"SA",
    "sg:tags":[
        "collector",
        "bottle"
    ],
    "wof:name":"Sampson R J",
    "wof:placetype":"venue"
},
  "geometry": {"coordinates":[140.00309753400001,-34.194190979],"type":"Point"}
}