{
  "type": "Feature",
  "properties": {
    "addr:full":"PO Box 269 Wodonga VIC 3690",
    "addr:postcode":"3690",
    "iso:country":"AU",
    "sg:address":"PO Box 269",
    "sg:city":"Wodonga",
    "sg:classifiers":[
        {
            "category":"Building & Trades",
            "subcategory":"Construction",
            "type":"Services"
        }
    ],
    "sg:phone":"+61 423 401 517",
    "sg:postcode":"3690",
    "sg:province":"VIC",
    "sg:tags":[
        "home",
        "air conditioning"
    ],
    "wof:name":"Airtech Plumbing",
    "wof:placetype":"venue"
},
  "geometry": {"coordinates":[146.84840393100001,-36.1168785095],"type":"Point"}
}