{
  "type": "Feature",
  "properties": {
    "addr:full":"338 Homer St Earlwood NSW 2206",
    "addr:housenumber":"338",
    "addr:postcode":"2206",
    "addr:street":"Homer St",
    "iso:country":"AU",
    "sg:address":"338 Homer St",
    "sg:city":"Earlwood",
    "sg:classifiers":[
        {
            "category":"Personal",
            "subcategory":"Tanning Parlor",
            "type":"Services"
        }
    ],
    "sg:phone":"+61 2 9559 4234",
    "sg:postcode":"2206",
    "sg:province":"NSW",
    "sg:tags":[
        "solarium"
    ],
    "wof:name":"Lidia Nova Beauty & Skincare Clinic",
    "wof:placetype":"venue"
},
  "geometry": {"coordinates":[151.125641,-33.926613],"type":"Point"}
}