{
  "type": "Feature",
  "properties": {
    "addr:full":"5 97-103 Anzac Pde Kensington NSW 2033",
    "addr:housenumber":"5 97-103",
    "addr:postcode":"2033",
    "addr:street":"Anzac Pde",
    "iso:country":"AU",
    "sg:address":"5 97-103 Anzac Pde",
    "sg:city":"Kensington",
    "sg:classifiers":[
        {
            "category":"Manufacturing",
            "subcategory":"Food",
            "type":"Manufacturing & Wholesale Goods"
        }
    ],
    "sg:phone":"+61 2 9662 0058",
    "sg:postcode":"2033",
    "sg:province":"NSW",
    "sg:tags":[
        "function",
        "catering"
    ],
    "wof:name":"Packed Lunch",
    "wof:placetype":"venue"
},
  "geometry": {"coordinates":[151.223206,-33.908615],"type":"Point"}
}