{
  "type": "Feature",
  "properties": {
    "iso:country":"AU",
    "sg:address":"Suite 319 & 321 Flemingon Rd",
    "sg:city":"Ringwood",
    "sg:classifiers":[
        {
            "category":"Health Services",
            "subcategory":"Doctor",
            "type":"Services"
        }
    ],
    "sg:phone":"+61 3 8804 4050",
    "sg:postcode":"3134",
    "sg:province":"VIC",
    "sg:tags":[
        "medical",
        "practitioner"
    ],
    "wof:name":"Woodward Alan",
    "wof:placetype":"venue"
},
  "geometry": {"coordinates":[145.22731018100001,-37.8055953979],"type":"Point"}
}