{
  "type": "Feature",
  "properties": {
    "iso:country":"AU",
    "sg:address":"Cnr London & Stevenson Sts",
    "sg:city":"Port Lincoln",
    "sg:classifiers":[
        {
            "category":"Building & Trades",
            "subcategory":"Landscaping Services",
            "type":"Services"
        }
    ],
    "sg:phone":"+61 8 8683 0256",
    "sg:postcode":"5606",
    "sg:province":"SA",
    "sg:tags":[
        "consultant"
    ],
    "wof:name":"Eime Building Design",
    "wof:placetype":"venue"
},
  "geometry": {"coordinates":[135.870575,-34.724491],"type":"Point"}
}