{
  "type": "Feature",
  "properties": {
    "addr:full":"33 Barramundi Drv Hallett Cove SA 5158",
    "addr:housenumber":"33",
    "addr:postcode":"5158",
    "addr:street":"Barramundi Drv",
    "iso:country":"AU",
    "sg:address":"33 Barramundi Drv",
    "sg:city":"Hallett Cove",
    "sg:classifiers":[
        {
            "category":"Fast Food",
            "type":"Food & Drink"
        }
    ],
    "sg:phone":"+61 8 8387 7200",
    "sg:postcode":"5158",
    "sg:province":"SA",
    "sg:tags":[
        "away",
        "take"
    ],
    "wof:name":"Karrara Dial A Pizza",
    "wof:placetype":"venue"
},
  "geometry": {"coordinates":[138.517669678,-35.068069458],"type":"Point"}
}