{
  "type": "Feature",
  "properties": {
    "addr:full":"111- 113 Ipswich Rd Woolloongabba QLD 4102",
    "addr:housenumber":"113",
    "addr:postcode":"4102",
    "addr:street":"Ipswich Rd",
    "iso:country":"AU",
    "sg:address":"111- 113 Ipswich Rd",
    "sg:city":"Woolloongabba",
    "sg:classifiers":[
        {
            "category":"Shopping",
            "subcategory":"Computers & Home Electronics",
            "type":"Retail Goods"
        }
    ],
    "sg:phone":"+61 7 3393 1233",
    "sg:postcode":"4102",
    "sg:province":"QLD",
    "sg:tags":[
        "hi-fi",
        "equipment"
    ],
    "wof:name":"Geoff Musgrave Electronics",
    "wof:placetype":"venue"
},
  "geometry": {"coordinates":[153.03463745100001,-27.4928665161],"type":"Point"}
}