{
  "type": "Feature",
  "properties": {
    "addr:full":"41a Lackey St Summer Hill NSW 2130",
    "addr:housenumber":"41a",
    "addr:postcode":"2130",
    "addr:street":"Lackey St",
    "iso:country":"AU",
    "sg:address":"41a Lackey St",
    "sg:city":"Summer Hill",
    "sg:classifiers":[
        {
            "category":"Professional",
            "subcategory":"Accounting & Tax Preparation",
            "type":"Services"
        }
    ],
    "sg:phone":"+61 2 9716 8255",
    "sg:postcode":"2130",
    "sg:province":"NSW",
    "sg:tags":[
        "accountant",
        "auditor"
    ],
    "wof:name":"Atic Pty Ltd",
    "wof:placetype":"venue"
},
  "geometry": {"coordinates":[151.13795471200001,-33.8916740417],"type":"Point"}
}