{
  "type": "Feature",
  "properties": {
    "iso:country":"AU",
    "sg:address":"Lot 2 Barries Rd",
    "sg:city":"Melton",
    "sg:classifiers":[
        {
            "category":"Home & Garden",
            "subcategory":"Building Materials",
            "type":"Retail Goods"
        }
    ],
    "sg:phone":"+61 3 9743 4856",
    "sg:postcode":"3337",
    "sg:province":"VIC",
    "sg:tags":[
        "fencing"
    ],
    "wof:name":"Western Fencing Supplies",
    "wof:placetype":"venue"
},
  "geometry": {"coordinates":[144.582932,-37.689236],"type":"Point"}
}