{
  "type": "Feature",
  "properties": {
    "addr:full":"38 Brooks Pde Belmont NSW 2280",
    "addr:housenumber":"38",
    "addr:postcode":"2280",
    "addr:street":"Brooks Pde",
    "iso:country":"AU",
    "sg:address":"38 Brooks Pde",
    "sg:city":"Belmont",
    "sg:classifiers":[
        {
            "category":"Shopping",
            "subcategory":"Stationery & Office Supplies",
            "type":"Retail Goods"
        }
    ],
    "sg:phone":"+61 2 4947 7131",
    "sg:postcode":"2280",
    "sg:province":"NSW",
    "sg:tags":[
        "equipment",
        "sailboarding"
    ],
    "wof:name":"Board Crazy",
    "wof:placetype":"venue"
},
  "geometry": {"coordinates":[151.65917968799999,-33.0313339233],"type":"Point"}
}