{
  "type": "Feature",
  "properties": {
    "iso:country":"AU",
    "sg:address":"16 Jackson St",
    "sg:city":"North Fremantle",
    "sg:classifiers":[
        {
            "category":"Professional",
            "subcategory":"Art Services",
            "type":"Services"
        }
    ],
    "sg:phone":"+61 8 9430 5800",
    "sg:postcode":"6159",
    "sg:province":"WA",
    "sg:tags":[
        "decorator",
        "painter"
    ],
    "sg:website":"http://www.erichood.com.au",
    "wof:name":"Eric Hood Pty Ltd",
    "wof:placetype":"venue"
},
  "geometry": {"coordinates":[115.751869,-32.034664],"type":"Point"}
}