{
  "type": "Feature",
  "properties": {
    "iso:country":"AU",
    "sg:address":"20 Danks St",
    "sg:city":"Waterloo",
    "sg:classifiers":[
        {
            "category":"Farming",
            "subcategory":"Farm & Veterinary Services",
            "type":"Manufacturing & Wholesale Goods"
        }
    ],
    "sg:phone":"+61 2 9699 7777",
    "sg:postcode":"2017",
    "sg:province":"NSW",
    "sg:tags":[
        "irrigation",
        "reticulation",
        "system"
    ],
    "wof:name":"Reece Pty Ltd",
    "wof:placetype":"venue"
},
  "geometry": {"coordinates":[151.211624145,-33.8979301453],"type":"Point"}
}