{
  "type": "Feature",
  "properties": {
    "addr:full":"Delatite Rd Seymour VIC 3660",
    "addr:postcode":"3660",
    "addr:street":"Delatite Rd",
    "iso:country":"AU",
    "sg:address":"Delatite Rd",
    "sg:city":"Seymour",
    "sg:classifiers":[
        {
            "category":"Education",
            "subcategory":"School",
            "type":"Public Place"
        }
    ],
    "sg:phone":"+61 3 5799 1705",
    "sg:postcode":"3660",
    "sg:province":"VIC",
    "sg:tags":[
        "state",
        "except",
        "nsw"
    ],
    "wof:name":"Seymour East Primary School",
    "wof:placetype":"venue"
},
  "geometry": {"coordinates":[145.159057617,-37.0097808838],"type":"Point"}
}