{
  "type": "Feature",
  "properties": {
    "iso:country":"AU",
    "sg:address":"Emu Park Rd",
    "sg:city":"Rockhampton",
    "sg:classifiers":[
        {
            "category":"Food & Beverages",
            "subcategory":"Fruits & Vegetables",
            "type":"Retail Goods"
        }
    ],
    "sg:phone":"+61 7 4934 4180",
    "sg:postcode":"4700",
    "sg:province":"QLD",
    "sg:tags":[
        "greengrocer",
        "fruiterer"
    ],
    "wof:name":"Black Stump Fruit Stall",
    "wof:placetype":"venue"
},
  "geometry": {"coordinates":[150.56765747099999,-23.3898849487],"type":"Point"}
}