{
  "type": "Feature",
  "properties": {
    "addr:full":"145 Nyleta St Coopers Plains QLD 4108",
    "addr:housenumber":"145",
    "addr:postcode":"4108",
    "addr:street":"Nyleta St",
    "iso:country":"AU",
    "sg:address":"145 Nyleta St",
    "sg:city":"Coopers Plains",
    "sg:classifiers":[
        {
            "category":"Retail",
            "subcategory":"Auto Repair",
            "type":"Services"
        }
    ],
    "sg:phone":"+61 7 3345 4904",
    "sg:postcode":"4108",
    "sg:province":"QLD",
    "sg:tags":[
        "body",
        "motor",
        "trimmer"
    ],
    "wof:name":"Anderson Bob Motor Trimming",
    "wof:placetype":"venue"
},
  "geometry": {"coordinates":[153.047698975,-27.5635814667],"type":"Point"}
}