{
  "type": "Feature",
  "properties": {
    "addr:full":"14 South St Forster NSW 2428",
    "addr:housenumber":"14",
    "addr:postcode":"2428",
    "addr:street":"South St",
    "iso:country":"AU",
    "sg:address":"14 South St",
    "sg:city":"Forster",
    "sg:classifiers":[
        {
            "category":"Health Services",
            "subcategory":"Dentist",
            "type":"Services"
        }
    ],
    "sg:phone":"+61 2 6555 8732",
    "sg:postcode":"2428",
    "sg:province":"NSW",
    "wof:name":"Reynolds P Feldbusch PRA Jeffree IH & Silbereisen N",
    "wof:placetype":"venue"
},
  "geometry": {"coordinates":[152.51412999999999,-32.189137],"type":"Point"}
}