{
  "type": "Feature",
  "properties": {
    "addr:full":"3/ 217 The Entrance Rd Erina NSW 2250",
    "addr:housenumber":"/ 217",
    "addr:postcode":"2250",
    "addr:street":"The Entrance Rd",
    "iso:country":"AU",
    "sg:address":"3/ 217 The Entrance Rd",
    "sg:city":"Erina",
    "sg:classifiers":[
        {
            "category":"Recreation",
            "subcategory":"Amusement Park",
            "type":"Entertainment"
        }
    ],
    "sg:phone":"+61 2 4365 6202",
    "sg:postcode":"2250",
    "sg:province":"NSW",
    "wof:name":"Party Zone Family Fun Centre",
    "wof:placetype":"venue"
},
  "geometry": {"coordinates":[151.389968872,-33.433506012],"type":"Point"}
}