{
  "type": "Feature",
  "properties": {
    "addr:full":"497 Grimshaw St Bundoora VIC 3083",
    "addr:housenumber":"497",
    "addr:postcode":"3083",
    "addr:street":"Grimshaw St",
    "iso:country":"AU",
    "sg:address":"497 Grimshaw St",
    "sg:city":"Bundoora",
    "sg:classifiers":[
        {
            "category":"Retail",
            "subcategory":"Auto Rental",
            "type":"Services"
        }
    ],
    "sg:phone":"+61 411 639 297",
    "sg:postcode":"3083",
    "sg:province":"VIC",
    "sg:tags":[
        "car",
        "wedding"
    ],
    "wof:name":"Davine Limousines",
    "wof:placetype":"venue"
},
  "geometry": {"coordinates":[145.06874084500001,-37.7010574341],"type":"Point"}
}