{
  "type": "Feature",
  "properties": {
    "addr:full":"22 Farrell St Whyalla SA 5600",
    "addr:housenumber":"22",
    "addr:postcode":"5600",
    "addr:street":"Farrell St",
    "iso:country":"AU",
    "sg:address":"22 Farrell St",
    "sg:city":"Whyalla",
    "sg:classifiers":[
        {
            "category":"Banks & Credit Unions",
            "subcategory":"Financial Services",
            "type":"Services"
        }
    ],
    "sg:phone":"+61 8 8645 0088",
    "sg:postcode":"5600",
    "sg:province":"SA",
    "sg:tags":[
        "financier"
    ],
    "wof:name":"GE Finance and Insurance",
    "wof:placetype":"venue"
},
  "geometry": {"coordinates":[137.57951399999999,-33.037102],"type":"Point"}
}