{
  "type": "Feature",
  "properties": {
    "iso:country":"AU",
    "sg:address":"34 Bedford St",
    "sg:city":"Gillman",
    "sg:classifiers":[
        {
            "category":"Professional",
            "subcategory":"Engineering",
            "type":"Services"
        }
    ],
    "sg:phone":"+61 8 8447 4001",
    "sg:postcode":"5013",
    "sg:province":"SA",
    "sg:tags":[
        "manufacturing",
        "engineer"
    ],
    "wof:name":"Keen Engineering Pty Ltd",
    "wof:placetype":"venue"
},
  "geometry": {"coordinates":[138.526947022,-34.8415374756],"type":"Point"}
}