{
  "type": "Feature",
  "properties": {
    "iso:country":"AU",
    "sg:address":"Shop 1b/ 44 King St",
    "sg:city":"Warrawong",
    "sg:classifiers":[
        {
            "category":"Personal",
            "subcategory":"Beauty Salon",
            "type":"Services"
        }
    ],
    "sg:phone":"+61 2 4274 0004",
    "sg:postcode":"2502",
    "sg:province":"NSW",
    "sg:tags":[
        "hairdresser"
    ],
    "wof:name":"Studio Classic Hair & Beauty",
    "wof:placetype":"venue"
},
  "geometry": {"coordinates":[150.887344,-34.483852],"type":"Point"}
}