{
  "type": "Feature",
  "properties": {
    "addr:full":"15 Rowood Rd Prospect NSW 2148",
    "addr:housenumber":"15",
    "addr:postcode":"2148",
    "addr:street":"Rowood Rd",
    "iso:country":"AU",
    "sg:address":"15 Rowood Rd",
    "sg:city":"Prospect",
    "sg:classifiers":[
        {
            "category":"Commercial Area",
            "type":"Public Place"
        }
    ],
    "sg:phone":"+61 2 9636 7599",
    "sg:postcode":"2148",
    "sg:province":"NSW",
    "sg:tags":[
        "heavy",
        "carrier"
    ],
    "wof:name":"Linehall Australia",
    "wof:placetype":"venue"
},
  "geometry": {"coordinates":[150.92340087900001,-33.8018569946],"type":"Point"}
}