{
  "type": "Feature",
  "properties": {
    "addr:full":"481 Chapel St South Yarra VIC 3141",
    "addr:housenumber":"481",
    "addr:postcode":"3141",
    "addr:street":"Chapel St",
    "iso:country":"AU",
    "sg:address":"481 Chapel St",
    "sg:city":"South Yarra",
    "sg:classifiers":[
        {
            "category":"Cafe",
            "type":"Food & Drink"
        }
    ],
    "sg:phone":"+61 3 9826 6442",
    "sg:postcode":"3141",
    "sg:province":"VIC",
    "wof:name":"Kazbar Cafe Bar",
    "wof:placetype":"venue"
},
  "geometry": {"coordinates":[144.9947052,-37.8431968689],"type":"Point"}
}