{
  "type": "Feature",
  "properties": {
    "iso:country":"AU",
    "sg:address":"470 Paramatta Rd",
    "sg:city":"Petersham",
    "sg:classifiers":[
        {
            "category":"Restaurant",
            "type":"Food & Drink"
        }
    ],
    "sg:phone":"+61 2 9560 0943",
    "sg:postcode":"2049",
    "sg:province":"NSW",
    "wof:name":"La Parrillada",
    "wof:placetype":"venue"
},
  "geometry": {"coordinates":[151.158417,-33.888245],"type":"Point"}
}