{
  "type": "Feature",
  "properties": {
    "addr:full":"293 Campbell St Rockhampton QLD 4700",
    "addr:housenumber":"293",
    "addr:postcode":"4700",
    "addr:street":"Campbell St",
    "iso:country":"AU",
    "sg:address":"293 Campbell St",
    "sg:city":"Rockhampton",
    "sg:classifiers":[
        {
            "category":"Manufacturing",
            "subcategory":"Retail Goods",
            "type":"Manufacturing & Wholesale Goods"
        }
    ],
    "sg:phone":"+61 7 4927 6588",
    "sg:postcode":"4700",
    "sg:province":"QLD",
    "sg:tags":[
        "merchant",
        "pump",
        "mfrs"
    ],
    "wof:name":"Ashton Engineering Pty Ltd",
    "wof:placetype":"venue"
},
  "geometry": {"coordinates":[150.51136779800001,-23.3866062164],"type":"Point"}
}