{
  "type": "Feature",
  "properties": {
    "iso:country":"AU",
    "sg:address":"31 Blackwall Rd",
    "sg:city":"Woy Woy",
    "sg:classifiers":[
        {
            "category":"Government",
            "subcategory":"Customs House",
            "type":"Public Place"
        }
    ],
    "sg:phone":"+61 2 4341 1719",
    "sg:postcode":"2256",
    "sg:province":"NSW",
    "sg:tags":[
        "title",
        "management",
        "stratum"
    ],
    "wof:name":"Pacific Strata Services & Realty",
    "wof:placetype":"venue"
},
  "geometry": {"coordinates":[151.32518005399999,-33.4842147827],"type":"Point"}
}