{
  "type": "Feature",
  "properties": {
    "iso:country":"AU",
    "sg:address":"107- 119 Great Western Hwy",
    "sg:city":"Penrith",
    "sg:classifiers":[
        {
            "category":"Manufacturing",
            "subcategory":"Motor Vehicles & Parts",
            "type":"Manufacturing & Wholesale Goods"
        }
    ],
    "sg:phone":"+61 2 4736 4555",
    "sg:postcode":"2740",
    "sg:province":"NSW",
    "sg:tags":[
        "replacement"
    ],
    "wof:name":"Penrith Daihatsu",
    "wof:placetype":"venue"
},
  "geometry": {"coordinates":[150.671707,-33.747421],"type":"Point"}
}