{
  "type": "Feature",
  "properties": {
    "iso:country":"AU",
    "sg:address":"16 Jarrah St",
    "sg:city":"Blackwater",
    "sg:classifiers":[
        {
            "category":"Manufacturing",
            "subcategory":"Tools & Machinery",
            "type":"Manufacturing & Wholesale Goods"
        }
    ],
    "sg:phone":"+61 7 4986 1105",
    "sg:postcode":"4717",
    "sg:province":"QLD",
    "sg:tags":[
        "earth",
        "excavating",
        "moving",
        "equipment"
    ],
    "wof:name":"Compmech Pty Ltd",
    "wof:placetype":"venue"
},
  "geometry": {"coordinates":[148.88308699999999,-23.593071],"type":"Point"}
}