{
  "type": "Feature",
  "properties": {
    "addr:full":"103 Patterson Rd Bentleigh VIC 3204",
    "addr:housenumber":"103",
    "addr:postcode":"3204",
    "addr:street":"Patterson Rd",
    "iso:country":"AU",
    "sg:address":"103 Patterson Rd",
    "sg:city":"Bentleigh",
    "sg:classifiers":[
        {
            "category":"Building & Trades",
            "subcategory":"Construction",
            "type":"Services"
        }
    ],
    "sg:phone":"+61 3 9557 0769",
    "sg:postcode":"3204",
    "sg:province":"VIC",
    "sg:tags":[
        "joiner",
        "carpenter"
    ],
    "wof:name":"Andrew Martin",
    "wof:placetype":"venue"
},
  "geometry": {"coordinates":[145.04272499999999,-37.926365],"type":"Point"}
}