{
  "type": "Feature",
  "properties": {
    "addr:full":"22 White Ave Fullarton SA 5063",
    "addr:housenumber":"22",
    "addr:postcode":"5063",
    "addr:street":"White Ave",
    "iso:country":"AU",
    "sg:address":"22 White Ave",
    "sg:city":"Fullarton",
    "sg:classifiers":[
        {
            "category":"Building & Trades",
            "subcategory":"Construction",
            "type":"Services"
        }
    ],
    "sg:phone":"+61 8 8373 2344",
    "sg:postcode":"5063",
    "sg:province":"SA",
    "sg:tags":[
        "ceiling"
    ],
    "wof:name":"Fullarton Ceilings",
    "wof:placetype":"venue"
},
  "geometry": {"coordinates":[138.62318420400001,-34.9548492432],"type":"Point"}
}