{
  "type": "Feature",
  "properties": {
    "addr:full":"44 Dumphries Ave Mt Ousley NSW 2519",
    "addr:housenumber":"44",
    "addr:postcode":"2519",
    "addr:street":"Dumphries Ave Mt",
    "iso:country":"AU",
    "sg:address":"44 Dumphries Ave",
    "sg:city":"Mt Ousley",
    "sg:classifiers":[
        {
            "category":"Autos & Motor Vehicles",
            "subcategory":"Boat Sales",
            "type":"Retail Goods"
        }
    ],
    "sg:phone":"+61 2 4225 9954",
    "sg:postcode":"2519",
    "sg:province":"NSW",
    "sg:tags":[
        "yacht"
    ],
    "wof:name":"Synergy Yacht Australia",
    "wof:placetype":"venue"
},
  "geometry": {"coordinates":[150.882339,-34.400856],"type":"Point"}
}