{
  "type": "Feature",
  "properties": {
    "iso:country":"AU",
    "sg:address":"98 Kingston Rd",
    "sg:city":"Underwood",
    "sg:classifiers":[
        {
            "category":"Manufacturing",
            "subcategory":"Motor Vehicles & Parts",
            "type":"Manufacturing & Wholesale Goods"
        }
    ],
    "sg:phone":"+61 7 3808 1006",
    "sg:postcode":"4119",
    "sg:province":"QLD",
    "sg:tags":[
        "replacement"
    ],
    "wof:name":"Underwood Wrecking",
    "wof:placetype":"venue"
},
  "geometry": {"coordinates":[153.11512756400001,-27.6161556244],"type":"Point"}
}