{
  "type": "Feature",
  "properties": {
    "addr:full":"72 Batesford Rd Malvern East VIC 3145",
    "addr:housenumber":"72",
    "addr:postcode":"3145",
    "addr:street":"Batesford Rd",
    "iso:country":"AU",
    "sg:address":"72 Batesford Rd",
    "sg:city":"Malvern East",
    "sg:classifiers":[
        {
            "category":"Communications",
            "subcategory":"Television Station",
            "type":"Services"
        }
    ],
    "sg:phone":"+61 3 9563 0088",
    "sg:postcode":"3145",
    "sg:province":"VIC",
    "sg:tags":[
        "equipment",
        "laser"
    ],
    "wof:name":"Ultimate Positioning",
    "wof:placetype":"venue"
},
  "geometry": {"coordinates":[145.08546447800001,-37.8768920898],"type":"Point"}
}