{
  "type": "Feature",
  "properties": {
    "iso:country":"AU",
    "sg:address":"Suite 14/ 207",
    "sg:city":"The Parade Norwood",
    "sg:classifiers":[
        {
            "category":"Social Services",
            "subcategory":"Retirement Home",
            "type":"Services"
        }
    ],
    "sg:phone":"+61 8 8332 0130",
    "sg:postcode":"5067",
    "sg:province":"SA",
    "sg:tags":[
        "environmental",
        "consultant",
        "pollution"
    ],
    "wof:name":"Parks & Leisure Australia",
    "wof:placetype":"venue"
},
  "geometry": {"coordinates":[138.63276672399999,-34.92137146],"type":"Point"}
}