{
  "type": "Feature",
  "properties": {
    "iso:country":"AU",
    "sg:address":"32 Penrose Drv",
    "sg:city":"Dapto",
    "sg:classifiers":[
        {
            "category":"Building & Trades",
            "subcategory":"Landscaping Services",
            "type":"Services"
        }
    ],
    "sg:phone":"+61 403 240 370",
    "sg:postcode":"2530",
    "sg:province":"NSW",
    "sg:tags":[
        "designer",
        "landscape",
        "contractor"
    ],
    "wof:name":"Adept Landscape Solutions",
    "wof:placetype":"venue"
},
  "geometry": {"coordinates":[150.77748107900001,-34.5124893188],"type":"Point"}
}