{
  "type": "Feature",
  "properties": {
    "addr:full":"10 Foam St Aspendale VIC 3195",
    "addr:housenumber":"10",
    "addr:postcode":"3195",
    "addr:street":"Foam St",
    "iso:country":"AU",
    "sg:address":"10 Foam St",
    "sg:city":"Aspendale",
    "sg:classifiers":[
        {
            "category":"Education",
            "subcategory":"Music School",
            "type":"Public Place"
        }
    ],
    "sg:phone":"+61 3 9580 4752",
    "sg:postcode":"3195",
    "sg:province":"VIC",
    "sg:tags":[
        "choir",
        "bands",
        "orchestra"
    ],
    "wof:name":"Five Star Brass",
    "wof:placetype":"venue"
},
  "geometry": {"coordinates":[145.099334717,-38.0169334412],"type":"Point"}
}