{
  "type": "Feature",
  "properties": {
    "addr:full":"Rear 360 Mann St Gosford NSW 2250",
    "addr:housenumber":"360",
    "addr:postcode":"2250",
    "addr:street":"Mann St",
    "iso:country":"AU",
    "sg:address":"Rear 360 Mann St",
    "sg:city":"Gosford",
    "sg:classifiers":[
        {
            "category":"Retail",
            "subcategory":"Auto Repair",
            "type":"Services"
        }
    ],
    "sg:phone":"+61 2 4324 3822",
    "sg:postcode":"2250",
    "sg:province":"NSW",
    "sg:tags":[
        "repairer",
        "motor",
        "engineer"
    ],
    "wof:name":"Peter Gray Automotive Repairs",
    "wof:placetype":"venue"
},
  "geometry": {"coordinates":[151.34356689399999,-33.4177131653],"type":"Point"}
}