{
  "type": "Feature",
  "properties": {
    "addr:full":"98 Railway Rd Blackburn VIC 3130",
    "addr:housenumber":"98",
    "addr:postcode":"3130",
    "addr:street":"Railway Rd",
    "iso:country":"AU",
    "sg:address":"98 Railway Rd",
    "sg:city":"Blackburn",
    "sg:classifiers":[
        {
            "category":"Professional",
            "subcategory":"Business Services",
            "type":"Services"
        }
    ],
    "sg:phone":"+61 1300 558 199",
    "sg:postcode":"3130",
    "sg:province":"VIC",
    "sg:tags":[
        "small",
        "advisory"
    ],
    "wof:name":"Calculum Pty Ltd",
    "wof:placetype":"venue"
},
  "geometry": {"coordinates":[145.15740966800001,-37.8183174133],"type":"Point"}
}