{
  "type": "Feature",
  "properties": {
    "addr:full":"91 Brisbane St Beaudesert QLD 4285",
    "addr:housenumber":"91",
    "addr:postcode":"4285",
    "addr:street":"Brisbane St",
    "iso:country":"AU",
    "sg:address":"91 Brisbane St",
    "sg:city":"Beaudesert",
    "sg:classifiers":[
        {
            "category":"Professional",
            "subcategory":"Printing & Photocopies",
            "type":"Services"
        }
    ],
    "sg:phone":"+61 7 5541 0380",
    "sg:postcode":"4285",
    "sg:province":"QLD",
    "sg:tags":[
        "photocopying"
    ],
    "wof:name":"Beaudesert Office Smart",
    "wof:placetype":"venue"
},
  "geometry": {"coordinates":[152.996002,-27.987879],"type":"Point"}
}