{
  "type": "Feature",
  "properties": {
    "addr:full":"32 Martinsville Rd Cooranbong NSW 2265",
    "addr:housenumber":"32",
    "addr:postcode":"2265",
    "addr:street":"Martinsville Rd",
    "iso:country":"AU",
    "sg:address":"32 Martinsville Rd",
    "sg:city":"Cooranbong",
    "sg:classifiers":[
        {
            "category":"Retail",
            "subcategory":"Storage",
            "type":"Services"
        }
    ],
    "sg:phone":"+61 2 4977 2582",
    "sg:postcode":"2265",
    "sg:province":"NSW",
    "sg:tags":[
        "shelving",
        "system"
    ],
    "wof:name":"P & M Shelving",
    "wof:placetype":"venue"
},
  "geometry": {"coordinates":[151.44284099999999,-33.078205],"type":"Point"}
}