{
  "type": "Feature",
  "properties": {
    "iso:country":"AU",
    "sg:address":"21/ 181 Church St",
    "sg:city":"Parramatta",
    "sg:classifiers":[
        {
            "category":"Health Services",
            "subcategory":"Health Practitioner",
            "type":"Services"
        }
    ],
    "sg:phone":"+61 2 9633 9919",
    "sg:postcode":"2150",
    "sg:province":"NSW",
    "sg:tags":[
        "acupuncture"
    ],
    "wof:name":"Chen Linda",
    "wof:placetype":"venue"
},
  "geometry": {"coordinates":[150.933395386,-33.7168388367],"type":"Point"}
}