{
  "type": "Feature",
  "properties": {
    "addr:full":"Clark St Wayville SA 5034",
    "addr:postcode":"5034",
    "addr:street":"Clark St",
    "iso:country":"AU",
    "sg:address":"Clark St",
    "sg:city":"Wayville",
    "sg:classifiers":[
        {
            "category":"Communications",
            "subcategory":"News Services",
            "type":"Services"
        }
    ],
    "sg:phone":"+61 8 8274 1101",
    "sg:postcode":"5034",
    "sg:province":"SA",
    "sg:tags":[
        "information",
        "tourist",
        "attractions"
    ],
    "wof:name":"Adelaide Private Tours",
    "wof:placetype":"venue"
},
  "geometry": {"coordinates":[138.596435547,-34.94581604],"type":"Point"}
}