{
  "type": "Feature",
  "properties": {
    "iso:country":"AU",
    "sg:address":"104 Cressy Rd",
    "sg:city":"East Ryde",
    "sg:classifiers":[
        {
            "category":"Personal",
            "type":"Services"
        }
    ],
    "sg:phone":"+61 2 8250 8777",
    "sg:postcode":"2113",
    "sg:province":"NSW",
    "sg:tags":[
        "reducing",
        "treatment",
        "weight"
    ],
    "wof:name":"Herbalife East Ryde",
    "wof:placetype":"venue"
},
  "geometry": {"coordinates":[151.12727355999999,-33.8091087341],"type":"Point"}
}