{
  "type": "Feature",
  "properties": {
    "addr:full":"49 Seven Hills Rd Baulkham Hills NSW 2153",
    "addr:housenumber":"49",
    "addr:postcode":"2153",
    "addr:street":"Seven Hills Rd",
    "iso:country":"AU",
    "sg:address":"49 Seven Hills Rd",
    "sg:city":"Baulkham Hills",
    "sg:classifiers":[
        {
            "category":"Education",
            "subcategory":"Kindergarten",
            "type":"Public Place"
        }
    ],
    "sg:phone":"+61 2 9639 6555",
    "sg:postcode":"2153",
    "sg:province":"NSW",
    "sg:tags":[
        "pre-schools"
    ],
    "wof:name":"Hills Pre-School Kindergarten The",
    "wof:placetype":"venue"
},
  "geometry": {"coordinates":[150.986404419,-33.7624130249],"type":"Point"}
}