{
  "type": "Feature",
  "properties": {
    "addr:full":"84 Garden St North Narrabeen NSW 2101",
    "addr:housenumber":"84",
    "addr:postcode":"2101",
    "addr:street":"Garden St",
    "iso:country":"AU",
    "sg:address":"84 Garden St",
    "sg:city":"North Narrabeen",
    "sg:classifiers":[
        {
            "category":"Retail",
            "subcategory":"Auto Repair",
            "type":"Services"
        }
    ],
    "sg:phone":"+61 2 9913 1177",
    "sg:postcode":"2101",
    "sg:province":"NSW",
    "sg:tags":[
        "beater",
        "painter",
        "panel"
    ],
    "wof:name":"Warriewood Smash Repairs Pty Ltd",
    "wof:placetype":"venue"
},
  "geometry": {"coordinates":[151.29495199999999,-33.700806],"type":"Point"}
}