{
  "type": "Feature",
  "properties": {
    "addr:full":"Grand Ave Forest Lake QLD 4078",
    "addr:postcode":"4078",
    "addr:street":"Grand Ave",
    "iso:country":"AU",
    "sg:address":"Grand Ave",
    "sg:city":"Forest Lake",
    "sg:classifiers":[
        {
            "category":"Social Services",
            "subcategory":"Child Care",
            "type":"Services"
        }
    ],
    "sg:phone":"+61 7 3278 9830",
    "sg:postcode":"4078",
    "sg:province":"QLD",
    "wof:name":"Grand Ave Outside School Hours Care",
    "wof:placetype":"venue"
},
  "geometry": {"coordinates":[152.970901489,-27.6269416809],"type":"Point"}
}