{
  "type": "Feature",
  "properties": {
    "addr:full":"15 Sharkies La Lorn NSW 2320",
    "addr:housenumber":"15",
    "addr:postcode":"2320",
    "addr:street":"Sharkies La Lorn",
    "iso:country":"AU",
    "sg:address":"15 Sharkies La",
    "sg:city":"Lorn",
    "sg:classifiers":[
        {
            "category":"Personal",
            "subcategory":"Massage",
            "type":"Services"
        }
    ],
    "sg:phone":"+61 2 4934 1153",
    "sg:postcode":"2320",
    "sg:province":"NSW",
    "sg:tags":[
        "therapy"
    ],
    "wof:name":"Lorn Massage Clinic",
    "wof:placetype":"venue"
},
  "geometry": {"coordinates":[151.56422424300001,-32.726184845],"type":"Point"}
}