{
  "type": "Feature",
  "properties": {
    "addr:full":"7- 11 Little Buckingham St Surry Hills NSW 2010",
    "addr:housenumber":"11",
    "addr:postcode":"2010",
    "addr:street":"7;Little Buckingham St",
    "iso:country":"AU",
    "sg:address":"7- 11 Little Buckingham St",
    "sg:city":"Surry Hills",
    "sg:classifiers":[
        {
            "category":"Building & Trades",
            "subcategory":"Equipment Rental",
            "type":"Services"
        }
    ],
    "sg:phone":"+61 2 9310 4327",
    "sg:postcode":"2010",
    "sg:province":"NSW",
    "sg:tags":[
        "demolition",
        "contractor"
    ],
    "wof:name":"Delta Group",
    "wof:placetype":"venue"
},
  "geometry": {"coordinates":[151.20755004899999,-33.888092041],"type":"Point"}
}