{
  "type": "Feature",
  "properties": {
    "addr:full":"Lot 1, Flinders St Port Kembla NSW 2505",
    "addr:postcode":"2505",
    "addr:street":"Flinders St",
    "iso:country":"AU",
    "sg:address":"Lot 1, Flinders St",
    "sg:city":"Port Kembla",
    "sg:classifiers":[
        {
            "category":"Building & Trades",
            "subcategory":"Construction",
            "type":"Services"
        }
    ],
    "sg:phone":"+61 2 4276 1359",
    "sg:postcode":"2505",
    "sg:province":"NSW",
    "sg:tags":[
        "management"
    ],
    "wof:name":"Hedden Concrete Constructions Pty. Ltd.",
    "wof:placetype":"venue"
},
  "geometry": {"coordinates":[150.88832099999999,-34.473213],"type":"Point"}
}