{
  "type": "Feature",
  "properties": {
    "addr:full":"30 Peel Rd O'Connor WA 6163",
    "addr:housenumber":"30",
    "addr:postcode":"6163",
    "addr:street":"Peel Rd",
    "iso:country":"AU",
    "sg:address":"30 Peel Rd",
    "sg:city":"O'Connor",
    "sg:classifiers":[
        {
            "category":"Shopping",
            "subcategory":"Bicycles & Sporting Goods",
            "type":"Retail Goods"
        }
    ],
    "sg:phone":"+61 8 9337 9177",
    "sg:postcode":"6163",
    "sg:province":"WA",
    "sg:tags":[
        "chemical",
        "equipment",
        "pool",
        "swimming"
    ],
    "wof:name":"Swimtek O'Connor Pty Ltd",
    "wof:placetype":"venue"
},
  "geometry": {"coordinates":[115.795708,-32.060078],"type":"Point"}
}