{
  "type": "Feature",
  "properties": {
    "addr:full":"57 Pacific Hwy Gosford West NSW 2250",
    "addr:housenumber":"57",
    "addr:postcode":"2250",
    "addr:street":"Pacific Hwy",
    "iso:country":"AU",
    "sg:address":"57 Pacific Hwy",
    "sg:city":"Gosford West",
    "sg:classifiers":[
        {
            "category":"Autos & Motor Vehicles",
            "subcategory":"Fuel & Gas Station",
            "type":"Retail Goods"
        }
    ],
    "sg:phone":"+61 2 4322 5745",
    "sg:postcode":"2250",
    "sg:province":"NSW",
    "wof:name":"Metro Petroleum West Gosford",
    "wof:placetype":"venue"
},
  "geometry": {"coordinates":[151.32737731899999,-33.4269142151],"type":"Point"}
}