{
  "type": "Feature",
  "properties": {
    "iso:country":"AU",
    "sg:address":"Unit 1 / 11 Commercial Drv",
    "sg:city":"Ashmore",
    "sg:classifiers":[
        {
            "category":"Home & Garden",
            "subcategory":"Household Appliances",
            "type":"Retail Goods"
        }
    ],
    "sg:phone":"+61 7 5531 2180",
    "sg:postcode":"4214",
    "sg:province":"QLD",
    "sg:tags":[
        "equipment",
        "gas"
    ],
    "sg:website":"http://www.goldcoastgas.com.au",
    "wof:name":"Gold Coast Gas",
    "wof:placetype":"venue"
},
  "geometry": {"coordinates":[153.389694214,-27.9803085327],"type":"Point"}
}