{
  "type": "Feature",
  "properties": {
    "addr:full":"6 Katya Crt Warrnambool VIC 3280",
    "addr:housenumber":"6",
    "addr:postcode":"3280",
    "addr:street":"Katya Crt",
    "iso:country":"AU",
    "sg:address":"6 Katya Crt",
    "sg:city":"Warrnambool",
    "sg:classifiers":[
        {
            "category":"Building & Trades",
            "subcategory":"Construction",
            "type":"Services"
        }
    ],
    "sg:phone":"+61 418 527 220",
    "sg:postcode":"3280",
    "sg:province":"VIC",
    "sg:tags":[
        "contractor"
    ],
    "wof:name":"Barling Peter J Builder Pty Ltd",
    "wof:placetype":"venue"
},
  "geometry": {"coordinates":[142.50531005900001,-38.3654975891],"type":"Point"}
}