{
  "type": "Feature",
  "properties": {
    "addr:full":"481 Burwood Rd Belmore NSW 2192",
    "addr:housenumber":"481",
    "addr:postcode":"2192",
    "addr:street":"Burwood Rd",
    "iso:country":"AU",
    "sg:address":"481 Burwood Rd",
    "sg:city":"Belmore",
    "sg:classifiers":[
        {
            "category":"Health Services",
            "subcategory":"Doctor",
            "type":"Services"
        }
    ],
    "sg:phone":"+61 2 9740 3211",
    "sg:postcode":"2192",
    "sg:province":"NSW",
    "sg:tags":[
        "medical",
        "practitioner"
    ],
    "wof:name":"Rifi Jamal Dr",
    "wof:placetype":"venue"
},
  "geometry": {"coordinates":[151.09002699999999,-33.920731],"type":"Point"}
}