{
  "type": "Feature",
  "properties": {
    "addr:full":"5 Whitehouse St Garbutt QLD 4814",
    "addr:housenumber":"5",
    "addr:postcode":"4814",
    "addr:street":"Whitehouse St",
    "iso:country":"AU",
    "sg:address":"5 Whitehouse St",
    "sg:city":"Garbutt",
    "sg:classifiers":[
        {
            "category":"Manufacturing",
            "subcategory":"Metals",
            "type":"Manufacturing & Wholesale Goods"
        }
    ],
    "sg:phone":"+61 7 4728 9833",
    "sg:postcode":"4814",
    "sg:province":"QLD",
    "sg:tags":[
        "wholesaler",
        "aluminium",
        "mfrs"
    ],
    "wof:name":"Ullrich Aluminium",
    "wof:placetype":"venue"
},
  "geometry": {"coordinates":[146.754715,-19.272215],"type":"Point"}
}