{
  "type": "Feature",
  "properties": {
    "addr:full":"34 Abernethy Rd Belmont WA 6104",
    "addr:housenumber":"34",
    "addr:postcode":"6104",
    "addr:street":"Abernethy Rd",
    "iso:country":"AU",
    "sg:address":"34 Abernethy Rd",
    "sg:city":"Belmont",
    "sg:classifiers":[
        {
            "category":"Cafe",
            "type":"Food & Drink"
        }
    ],
    "sg:phone":"+61 8 9277 3868",
    "sg:postcode":"6104",
    "sg:province":"WA",
    "wof:name":"Jolis Good Lunches",
    "wof:placetype":"venue"
},
  "geometry": {"coordinates":[115.919746399,-31.9486541748],"type":"Point"}
}