{
  "type": "Feature",
  "properties": {
    "addr:full":"73 Belmore St Yarrawonga VIC 3730",
    "addr:housenumber":"73",
    "addr:postcode":"3730",
    "addr:street":"Belmore St",
    "iso:country":"AU",
    "sg:address":"73 Belmore St",
    "sg:city":"Yarrawonga",
    "sg:classifiers":[
        {
            "category":"Personal",
            "subcategory":"Beauty Salon",
            "type":"Services"
        }
    ],
    "sg:phone":"+61 3 5744 2936",
    "sg:postcode":"3730",
    "sg:province":"VIC",
    "sg:tags":[
        "hairdresser"
    ],
    "wof:name":"Lean Dennis",
    "wof:placetype":"venue"
},
  "geometry": {"coordinates":[146.00422668499999,-36.0118026733],"type":"Point"}
}