{
  "type": "Feature",
  "properties": {
    "addr:full":"Anzac Rd Menai NSW 2234",
    "addr:postcode":"2234",
    "addr:street":"Anzac Rd",
    "iso:country":"AU",
    "sg:address":"Anzac Rd",
    "sg:city":"Menai",
    "sg:classifiers":[
        {
            "category":"Education",
            "subcategory":"School",
            "type":"Public Place"
        }
    ],
    "sg:phone":"+61 2 9543 2614",
    "sg:postcode":"2234",
    "sg:province":"NSW",
    "wof:name":"Holy Family Primary School",
    "wof:placetype":"venue"
},
  "geometry": {"coordinates":[151.022018433,-34.0181732178],"type":"Point"}
}