{
  "type": "Feature",
  "properties": {
    "addr:full":"362-376 King St Caboolture QLD 4510",
    "addr:housenumber":"362-376",
    "addr:postcode":"4510",
    "addr:street":"King St",
    "iso:country":"AU",
    "sg:address":"362-376 King St",
    "sg:city":"Caboolture",
    "sg:classifiers":[
        {
            "category":"Social Services",
            "subcategory":"Retirement Home",
            "type":"Services"
        }
    ],
    "sg:phone":"+61 7 5495 8677",
    "sg:postcode":"4510",
    "sg:province":"QLD",
    "sg:tags":[
        "village"
    ],
    "wof:name":"Sunset Lodge Serviced Apartments",
    "wof:placetype":"venue"
},
  "geometry": {"coordinates":[152.95161400000001,-27.084982],"type":"Point"}
}