{
  "type": "Feature",
  "properties": {
    "addr:full":"169 Monkey Gully Rd Mansfield VIC 3722",
    "addr:housenumber":"169",
    "addr:postcode":"3722",
    "addr:street":"Monkey Gully Rd",
    "iso:country":"AU",
    "sg:address":"169 Monkey Gully Rd",
    "sg:city":"Mansfield",
    "sg:classifiers":[
        {
            "category":"Manufacturing",
            "subcategory":"Tools & Machinery",
            "type":"Manufacturing & Wholesale Goods"
        }
    ],
    "sg:phone":"+61 3 5775 2971",
    "sg:postcode":"3722",
    "sg:province":"VIC",
    "sg:tags":[
        "earth",
        "excavating",
        "moving",
        "equipment"
    ],
    "wof:name":"Mansfield Constructions Pty Ltd",
    "wof:placetype":"venue"
},
  "geometry": {"coordinates":[146.095901489,-37.0438957214],"type":"Point"}
}