{
  "type": "Feature",
  "properties": {
    "addr:full":"82 River Rd Gympie QLD 4570",
    "addr:housenumber":"82",
    "addr:postcode":"4570",
    "addr:street":"River Rd",
    "iso:country":"AU",
    "sg:address":"82 River Rd",
    "sg:city":"Gympie",
    "sg:classifiers":[
        {
            "category":"Professional",
            "subcategory":"Accounting & Tax Preparation",
            "type":"Services"
        }
    ],
    "sg:phone":"+61 7 5482 5544",
    "sg:postcode":"4570",
    "sg:province":"QLD",
    "sg:tags":[
        "consultant",
        "taxation"
    ],
    "wof:name":"Case NJ & Associates",
    "wof:placetype":"venue"
},
  "geometry": {"coordinates":[152.67095947300001,-26.2012443542],"type":"Point"}
}