{
  "type": "Feature",
  "properties": {
    "addr:full":"(off Orman St) 296 Queen St Campbelltown NSW 2560",
    "addr:housenumber":"296",
    "addr:postcode":"2560",
    "addr:street":"Queen St",
    "iso:country":"AU",
    "sg:address":"(off Orman St) 296 Queen St",
    "sg:city":"Campbelltown",
    "sg:classifiers":[
        {
            "category":"Health Services",
            "subcategory":"Doctor",
            "type":"Services"
        }
    ],
    "sg:phone":"+61 2 4628 3777",
    "sg:postcode":"2560",
    "sg:province":"NSW",
    "sg:tags":[
        "medical",
        "practitioner"
    ],
    "wof:name":"Chang Richard",
    "wof:placetype":"venue"
},
  "geometry": {"coordinates":[150.81101989699999,-34.0700950623],"type":"Point"}
}