{
  "type": "Feature",
  "properties": {
    "addr:full":"149 Brebner Drv West Lakes SA 5021",
    "addr:housenumber":"149",
    "addr:postcode":"5021",
    "addr:street":"Brebner Drv",
    "iso:country":"AU",
    "sg:address":"149 Brebner Drv",
    "sg:city":"West Lakes",
    "sg:classifiers":[
        {
            "category":"Health Services",
            "subcategory":"Health Practitioner",
            "type":"Services"
        }
    ],
    "sg:phone":"+61 8 8356 1712",
    "sg:postcode":"5021",
    "sg:province":"SA",
    "sg:tags":[
        "physiotherapist"
    ],
    "wof:name":"Osmond Lisa",
    "wof:placetype":"venue"
},
  "geometry": {"coordinates":[138.48922729500001,-34.8784828186],"type":"Point"}
}