{
  "type": "Feature",
  "properties": {
    "addr:full":"6 Ruby St Guildford NSW 2161",
    "addr:housenumber":"6",
    "addr:postcode":"2161",
    "addr:street":"Ruby St",
    "iso:country":"AU",
    "sg:address":"6 Ruby St",
    "sg:city":"Guildford",
    "sg:classifiers":[
        {
            "category":"Retail",
            "subcategory":"Auto Repair",
            "type":"Services"
        }
    ],
    "sg:phone":"+61 2 9892 2117",
    "sg:postcode":"2161",
    "sg:province":"NSW",
    "sg:tags":[
        "clutch",
        "brake"
    ],
    "wof:name":"Brakepro",
    "wof:placetype":"venue"
},
  "geometry": {"coordinates":[150.99154663100001,-33.8479614258],"type":"Point"}
}