{
  "type": "Feature",
  "properties": {
    "iso:country":"AU",
    "sg:address":"461 Pitt St",
    "sg:city":"Sydney",
    "sg:classifiers":[
        {
            "category":"Health Services",
            "subcategory":"Health Practitioner",
            "type":"Services"
        }
    ],
    "sg:phone":"+61 2 9281 7921",
    "sg:postcode":"2000",
    "sg:province":"NSW",
    "sg:tags":[
        "alternative"
    ],
    "wof:name":"Crystal Soma",
    "wof:placetype":"venue"
},
  "geometry": {"coordinates":[151.20687866200001,-33.879447937],"type":"Point"}
}