{
  "type": "Feature",
  "properties": {
    "addr:full":"U3/ 13 Veronica St Capalaba QLD 4157",
    "addr:housenumber":"13",
    "addr:postcode":"4157",
    "addr:street":"U3 /;Veronica St",
    "iso:country":"AU",
    "sg:address":"U3/ 13 Veronica St",
    "sg:city":"Capalaba",
    "sg:classifiers":[
        {
            "category":"Manufacturing",
            "subcategory":"Metals",
            "type":"Manufacturing & Wholesale Goods"
        }
    ],
    "sg:phone":"+61 7 3823 5108",
    "sg:postcode":"4157",
    "sg:province":"QLD",
    "sg:tags":[
        "wholesaler",
        "aluminium",
        "mfrs"
    ],
    "wof:name":"MBA Productions",
    "wof:placetype":"venue"
},
  "geometry": {"coordinates":[153.19859314000001,-27.5276756287],"type":"Point"}
}