{
  "type": "Feature",
  "properties": {
    "addr:full":"39 Bevan Ave Clayton South VIC 3169",
    "addr:housenumber":"39",
    "addr:postcode":"3169",
    "addr:street":"Bevan Ave",
    "iso:country":"AU",
    "sg:address":"39 Bevan Ave",
    "sg:city":"Clayton South",
    "sg:classifiers":[
        {
            "category":"Communications",
            "subcategory":"Film & Video Production",
            "type":"Services"
        }
    ],
    "sg:phone":"+61 3 9558 5323",
    "sg:postcode":"3169",
    "sg:province":"VIC",
    "sg:tags":[
        "fan",
        "blower"
    ],
    "wof:name":"Fanforce",
    "wof:placetype":"venue"
},
  "geometry": {"coordinates":[145.128372192,-37.9358482361],"type":"Point"}
}