{
  "type": "Feature",
  "properties": {
    "addr:full":"2nd Floor, 166 Maroubra Rd Maroubra NSW 2035",
    "addr:housenumber":"166",
    "addr:postcode":"2035",
    "addr:street":"Maroubra Rd",
    "iso:country":"AU",
    "sg:address":"2nd Floor, 166 Maroubra Rd",
    "sg:city":"Maroubra",
    "sg:classifiers":[
        {
            "category":"Professional",
            "subcategory":"Business Services",
            "type":"Services"
        }
    ],
    "sg:phone":"+61 2 9344 9762",
    "sg:postcode":"2035",
    "sg:province":"NSW",
    "sg:tags":[
        "processing",
        "word"
    ],
    "wof:name":"Maroubra Business Centre",
    "wof:placetype":"venue"
},
  "geometry": {"coordinates":[151.23973083499999,-33.9415054321],"type":"Point"}
}