{
  "type": "Feature",
  "properties": {
    "iso:country":"AU",
    "sg:address":"90 Hotham St",
    "sg:city":"Traralgon",
    "sg:classifiers":[
        {
            "category":"Banks & Credit Unions",
            "subcategory":"Bank",
            "type":"Services"
        }
    ],
    "sg:phone":"+61 13 28 88",
    "sg:postcode":"3844",
    "sg:province":"VIC",
    "wof:name":"Members Australia Credit Union",
    "wof:placetype":"venue"
},
  "geometry": {"coordinates":[146.535598755,-38.1972999573],"type":"Point"}
}