{
  "type": "Feature",
  "properties": {
    "addr:full":"85 Milford Drv Rouse Hill NSW 2155",
    "addr:housenumber":"85",
    "addr:postcode":"2155",
    "addr:street":"Milford Drv",
    "iso:country":"AU",
    "sg:address":"85 Milford Drv",
    "sg:city":"Rouse Hill",
    "sg:classifiers":[
        {
            "category":"Shopping",
            "subcategory":"Computers & Home Electronics",
            "type":"Retail Goods"
        }
    ],
    "sg:phone":"+61 2 8824 3784",
    "sg:postcode":"2155",
    "sg:province":"NSW",
    "sg:tags":[
        "equipment",
        "part",
        "electronic"
    ],
    "wof:name":"Synergy Electronics Pty Ltd",
    "wof:placetype":"venue"
},
  "geometry": {"coordinates":[150.93159484899999,-33.67345047],"type":"Point"}
}