{
  "type": "Feature",
  "properties": {
    "addr:full":"74 Clifton Downs Rd Mandurah WA 6210",
    "addr:housenumber":"74",
    "addr:postcode":"6210",
    "addr:street":"Clifton Downs Rd",
    "iso:country":"AU",
    "sg:address":"74 Clifton Downs Rd",
    "sg:city":"Mandurah",
    "sg:classifiers":[
        {
            "category":"Retail",
            "subcategory":"Auto Rental",
            "type":"Services"
        }
    ],
    "sg:phone":"+61 427 692 023",
    "sg:postcode":"6210",
    "sg:province":"WA",
    "sg:tags":[
        "chauffeur",
        "car",
        "hire",
        "driven",
        "limousine"
    ],
    "wof:name":"A.A. Californian Cruisers",
    "wof:placetype":"venue"
},
  "geometry": {"coordinates":[115.78473700000001,-32.509258],"type":"Point"}
}