{
  "type": "Feature",
  "properties": {
    "addr:full":"2/ 28 Albert St Hornsby NSW 2077",
    "addr:housenumber":"/ 28",
    "addr:postcode":"2077",
    "addr:street":"Albert St",
    "iso:country":"AU",
    "sg:address":"2/ 28 Albert St",
    "sg:city":"Hornsby",
    "sg:classifiers":[
        {
            "category":"Professional",
            "subcategory":"Accounting & Tax Preparation",
            "type":"Services"
        }
    ],
    "sg:phone":"+61 2 9476 2223",
    "sg:postcode":"2077",
    "sg:province":"NSW",
    "sg:tags":[
        "bookkeeping"
    ],
    "wof:name":"Leznar P",
    "wof:placetype":"venue"
},
  "geometry": {"coordinates":[151.102493286,-33.7020645142],"type":"Point"}
}