{
  "type": "Feature",
  "properties": {
    "addr:full":"41 Lyons Rd Waroona WA 6215",
    "addr:housenumber":"41",
    "addr:postcode":"6215",
    "addr:street":"Lyons Rd",
    "iso:country":"AU",
    "sg:address":"41 Lyons Rd",
    "sg:city":"Waroona",
    "sg:classifiers":[
        {
            "category":"Professional",
            "subcategory":"Business Services",
            "type":"Services"
        }
    ],
    "sg:phone":"+61 8 9733 3355",
    "sg:postcode":"6215",
    "sg:province":"WA",
    "sg:tags":[
        "drafting"
    ],
    "wof:name":"Murray Planning & Design",
    "wof:placetype":"venue"
},
  "geometry": {"coordinates":[115.93583700000001,-32.854752],"type":"Point"}
}