{
  "type": "Feature",
  "properties": {
    "addr:full":"16 Hill St Richmond VIC 3121",
    "addr:housenumber":"16",
    "addr:postcode":"3121",
    "addr:street":"Hill St",
    "iso:country":"AU",
    "sg:address":"16 Hill St",
    "sg:city":"Richmond",
    "sg:classifiers":[
        {
            "category":"Professional",
            "subcategory":"Accounting & Tax Preparation",
            "type":"Services"
        }
    ],
    "sg:phone":"+61 3 9428 3855",
    "sg:postcode":"3121",
    "sg:province":"VIC",
    "sg:tags":[
        "accountant",
        "auditor"
    ],
    "wof:name":"Dredge Alan & Co Pty Ltd",
    "wof:placetype":"venue"
},
  "geometry": {"coordinates":[144.996170044,-37.8281021118],"type":"Point"}
}