{
  "type": "Feature",
  "properties": {
    "addr:full":"Cnr Clarke & Lewins St Earlwood NSW 2206",
    "addr:postcode":"2206",
    "addr:street":"Cnr;St",
    "iso:country":"AU",
    "sg:address":"Cnr Clarke & Lewins St",
    "sg:city":"Earlwood",
    "sg:classifiers":[
        {
            "category":"Government",
            "subcategory":"Post Office",
            "type":"Public Place"
        }
    ],
    "sg:phone":"+61 2 9560 6646",
    "sg:postcode":"2206",
    "sg:province":"NSW",
    "sg:tags":[
        "yoga"
    ],
    "wof:name":"Jenny Lowe Enjoy Yoga",
    "wof:placetype":"venue"
},
  "geometry": {"coordinates":[151.12391700000001,-33.92598],"type":"Point"}
}