{
  "type": "Feature",
  "properties": {
    "addr:full":"Suite 1/ 242 Mulgrave Rd Westcourt QLD 4870",
    "addr:housenumber":"/ 242",
    "addr:postcode":"4870",
    "addr:street":"Mulgrave Rd",
    "iso:country":"AU",
    "sg:address":"Suite 1/ 242 Mulgrave Rd",
    "sg:city":"Westcourt",
    "sg:classifiers":[
        {
            "category":"Health Services",
            "subcategory":"Health Practitioner",
            "type":"Services"
        }
    ],
    "sg:phone":"+61 7 4031 8038",
    "sg:postcode":"4870",
    "sg:province":"QLD",
    "sg:tags":[
        "psychologist"
    ],
    "wof:name":"Debra Kapelis",
    "wof:placetype":"venue"
},
  "geometry": {"coordinates":[145.75860595699999,-16.9051265717],"type":"Point"}
}