{
  "type": "Feature",
  "properties": {
    "iso:country":"AU",
    "sg:address":"117- 125 Toogood Rd",
    "sg:city":"Bayview Heights",
    "sg:classifiers":[
        {
            "category":"Retail",
            "subcategory":"Event Space",
            "type":"Services"
        }
    ],
    "sg:phone":"+61 7 4054 3322",
    "sg:postcode":"4868",
    "sg:province":"QLD",
    "sg:tags":[
        "venue",
        "reception",
        "wedding"
    ],
    "wof:name":"Cairns Bowls Club Inc",
    "wof:placetype":"venue"
},
  "geometry": {"coordinates":[145.73492431599999,-16.957780838],"type":"Point"}
}