{
  "type": "Feature",
  "properties": {
    "addr:full":"Shp 1/ 3 Ward Pl Round Corner NSW 2158",
    "addr:housenumber":"/ 3",
    "addr:postcode":"2158",
    "addr:street":"Pl Round",
    "iso:country":"AU",
    "sg:address":"Shp 1/ 3 Ward Pl",
    "sg:city":"Round Corner",
    "sg:classifiers":[
        {
            "category":"Shopping",
            "subcategory":"Beauty & Cosmetics",
            "type":"Retail Goods"
        }
    ],
    "sg:phone":"+61 2 9651 6088",
    "sg:postcode":"2158",
    "sg:province":"NSW",
    "sg:tags":[
        "equipment",
        "salon",
        "supply"
    ],
    "wof:name":"Naturally Skin Deep Beauty Therapies",
    "wof:placetype":"venue"
},
  "geometry": {"coordinates":[151.02024841299999,-33.6924667358],"type":"Point"}
}