{
  "type": "Feature",
  "properties": {
    "addr:full":"9 Nelson Rd Cardiff NSW 2285",
    "addr:housenumber":"9",
    "addr:postcode":"2285",
    "addr:street":"Nelson Rd",
    "iso:country":"AU",
    "sg:address":"9 Nelson Rd",
    "sg:city":"Cardiff",
    "sg:classifiers":[
        {
            "category":"Banks & Credit Unions",
            "subcategory":"Bureau De Change",
            "type":"Services"
        }
    ],
    "sg:phone":"+61 2 4954 7477",
    "sg:postcode":"2285",
    "sg:province":"NSW",
    "sg:tags":[
        "control",
        "consultant",
        "vibration"
    ],
    "wof:name":"Dowding & Mills",
    "wof:placetype":"venue"
},
  "geometry": {"coordinates":[151.6509552,-32.9413261414],"type":"Point"}
}