{
  "type": "Feature",
  "properties": {
    "iso:country":"AU",
    "sg:address":"81 Wattletree Rd",
    "sg:city":"Malvern",
    "sg:classifiers":[
        {
            "category":"Social Services",
            "subcategory":"Child Care",
            "type":"Services"
        }
    ],
    "sg:phone":"+61 3 9576 2232",
    "sg:postcode":"3144",
    "sg:province":"VIC",
    "wof:name":"Little Possums On Wattletree",
    "wof:placetype":"venue"
},
  "geometry": {"coordinates":[145.03526306099999,-37.8632507324],"type":"Point"}
}