{
  "type": "Feature",
  "properties": {
    "addr:full":"3/ 200 Balcatta Rd Balcatta WA 6021",
    "addr:housenumber":"/ 200",
    "addr:postcode":"6021",
    "addr:street":"Balcatta Rd",
    "iso:country":"AU",
    "sg:address":"3/ 200 Balcatta Rd",
    "sg:city":"Balcatta",
    "sg:classifiers":[
        {
            "category":"Structure",
            "subcategory":"Bridge",
            "type":"Public Place"
        }
    ],
    "sg:phone":"+61 8 9344 4748",
    "sg:postcode":"6021",
    "sg:province":"WA",
    "sg:tags":[
        "chainsaw",
        "brushcutters"
    ],
    "wof:name":"Parklands Mowers",
    "wof:placetype":"venue"
},
  "geometry": {"coordinates":[115.817062378,-31.8624343872],"type":"Point"}
}