{
  "type": "Feature",
  "properties": {
    "addr:full":"Panorama Plaza Scenic Drv Tweed Heads West NSW 2485",
    "addr:postcode":"2485",
    "addr:street":"Scenic Drv",
    "iso:country":"AU",
    "sg:address":"Panorama Plaza Scenic Drv",
    "sg:city":"Tweed Heads West",
    "sg:classifiers":[
        {
            "category":"Food & Beverages",
            "subcategory":"Bakery",
            "type":"Retail Goods"
        }
    ],
    "sg:phone":"+61 7 5599 8656",
    "sg:postcode":"2485",
    "sg:province":"NSW",
    "sg:tags":[
        "cake",
        "shop",
        "pastry"
    ],
    "wof:name":"Panorama Plaza Bakery",
    "wof:placetype":"venue"
},
  "geometry": {"coordinates":[153.50709533700001,-28.1949043274],"type":"Point"}
}