{
  "type": "Feature",
  "properties": {
    "iso:country":"AU",
    "sg:address":"6 Whittaker St",
    "sg:city":"Alice Springs",
    "sg:classifiers":[
        {
            "category":"Shopping",
            "subcategory":"Computers & Home Electronics",
            "type":"Retail Goods"
        }
    ],
    "sg:phone":"+61 8 8951 0300",
    "sg:postcode":"0870",
    "sg:province":"NT",
    "sg:tags":[
        "equipment",
        "supply"
    ],
    "wof:name":"Corporate Express",
    "wof:placetype":"venue"
},
  "geometry": {"coordinates":[133.87690734899999,-23.6961078644],"type":"Point"}
}