{
  "type": "Feature",
  "properties": {
    "addr:full":"Bass Hwy The Gurdies VIC 3984",
    "addr:postcode":"3984",
    "addr:street":"Bass Hwy The",
    "iso:country":"AU",
    "sg:address":"Bass Hwy",
    "sg:city":"The Gurdies",
    "sg:classifiers":[
        {
            "category":"Home & Garden",
            "subcategory":"Garden Supply",
            "type":"Retail Goods"
        }
    ],
    "sg:phone":"+61 3 5997 6225",
    "sg:postcode":"3984",
    "sg:province":"VIC",
    "sg:tags":[
        "fertilizer"
    ],
    "wof:name":"Blackney's WGF",
    "wof:placetype":"venue"
},
  "geometry": {"coordinates":[145.563323975,-38.3657188416],"type":"Point"}
}