{
  "type": "Feature",
  "properties": {
    "addr:full":"31 Premier Crt Kawana Waters QLD 4575",
    "addr:housenumber":"31",
    "addr:postcode":"4575",
    "addr:street":"Premier Crt",
    "iso:country":"AU",
    "sg:address":"31 Premier Crt",
    "sg:city":"Kawana Waters",
    "sg:classifiers":[
        {
            "category":"Real Estate",
            "subcategory":"Real Estate Agent",
            "type":"Services"
        }
    ],
    "sg:phone":"+61 7 5437 8111",
    "sg:postcode":"4575",
    "sg:province":"QLD",
    "sg:tags":[
        "handyman's",
        "equipment",
        "hire",
        "builders",
        "contractor"
    ],
    "wof:name":"JC Hire Service",
    "wof:placetype":"venue"
},
  "geometry": {"coordinates":[153.12037699999999,-26.728985],"type":"Point"}
}