{
  "type": "Feature",
  "properties": {
    "addr:full":"Shp B Lot 1040 The Golden Wy Golden Grove SA 5125",
    "addr:housenumber":"1040",
    "addr:postcode":"5125",
    "addr:street":"The Golden Wy",
    "iso:country":"AU",
    "sg:address":"Shp B Lot 1040 The Golden Wy",
    "sg:city":"Golden Grove",
    "sg:classifiers":[
        {
            "category":"Food & Beverages",
            "subcategory":"Liquor & Beverages",
            "type":"Retail Goods"
        }
    ],
    "sg:phone":"+61 8 8251 5631",
    "sg:postcode":"5125",
    "sg:province":"SA",
    "sg:tags":[
        "store"
    ],
    "wof:name":"Liquorland",
    "wof:placetype":"venue"
},
  "geometry": {"coordinates":[138.69323700000001,-34.79261],"type":"Point"}
}