{
  "type": "Feature",
  "properties": {
    "iso:country":"AU",
    "sg:address":"22a Industry Ave",
    "sg:city":"Narromine",
    "sg:classifiers":[
        {
            "category":"Retail",
            "subcategory":"Storage",
            "type":"Services"
        }
    ],
    "sg:phone":"+61 2 6889 7688",
    "sg:postcode":"2821",
    "sg:province":"NSW",
    "wof:name":"Narromine Self Storage",
    "wof:placetype":"venue"
},
  "geometry": {"coordinates":[148.257156372,-32.2385482788],"type":"Point"}
}