{
  "type": "Feature",
  "properties": {
    "iso:country":"AU",
    "sg:address":"Shop 4 Goldman La",
    "sg:city":"Double Bay",
    "sg:classifiers":[
        {
            "category":"Wholesale",
            "subcategory":"Medical Equipment & Supplies",
            "type":"Manufacturing & Wholesale Goods"
        }
    ],
    "sg:phone":"+61 1300 134 327",
    "sg:postcode":"2028",
    "sg:province":"NSW",
    "sg:tags":[
        "aids",
        "hearing"
    ],
    "wof:name":"Hearing & Balance Centre",
    "wof:placetype":"venue"
},
  "geometry": {"coordinates":[151.243087769,-33.8790588379],"type":"Point"}
}