{
  "type": "Feature",
  "properties": {
    "iso:country":"AU",
    "sg:address":"PO Box 4310",
    "sg:city":"Bay Village",
    "sg:classifiers":[
        {
            "category":"Building & Trades",
            "subcategory":"Pest Control",
            "type":"Services"
        }
    ],
    "sg:phone":"+61 2 4385 9055",
    "sg:postcode":"2261",
    "sg:province":"NSW",
    "wof:name":"Pottsy's Pest Protection",
    "wof:placetype":"venue"
},
  "geometry": {"coordinates":[151.473846,-33.37632],"type":"Point"}
}