{
  "type": "Feature",
  "properties": {
    "addr:full":"Level 1, 328 Balcombre Rd Beaumaris VIC 3193",
    "addr:housenumber":"328",
    "addr:postcode":"3193",
    "addr:street":"Balcombre Rd",
    "iso:country":"AU",
    "sg:address":"Level 1, 328 Balcombre Rd",
    "sg:city":"Beaumaris",
    "sg:classifiers":[
        {
            "category":"Professional",
            "subcategory":"Accounting & Tax Preparation",
            "type":"Services"
        }
    ],
    "sg:phone":"+61 3 9589 4599",
    "sg:postcode":"3193",
    "sg:province":"VIC",
    "sg:tags":[
        "accountant",
        "auditor"
    ],
    "wof:name":"Craig Allen & Associates",
    "wof:placetype":"venue"
},
  "geometry": {"coordinates":[145.046417236,-37.9788818359],"type":"Point"}
}