{
  "type": "Feature",
  "properties": {
    "addr:full":"Unit 1, 194 Macquarie Rd Warners Bay NSW 2282",
    "addr:housenumber":"194",
    "addr:postcode":"2282",
    "addr:street":"Macquarie Rd",
    "iso:country":"AU",
    "sg:address":"Unit 1, 194 Macquarie Rd",
    "sg:city":"Warners Bay",
    "sg:classifiers":[
        {
            "category":"Retail",
            "subcategory":"Veterinary Services",
            "type":"Services"
        }
    ],
    "sg:phone":"+61 2 4956 7719",
    "sg:postcode":"2282",
    "sg:province":"NSW",
    "sg:tags":[
        "surgeon"
    ],
    "wof:name":"Macquarie Road Veterinary Hospital",
    "wof:placetype":"venue"
},
  "geometry": {"coordinates":[151.65286254899999,-32.9656410217],"type":"Point"}
}