{
  "type": "Feature",
  "properties": {
    "addr:full":"Unit 21, 7 Lyn Pde Prestons NSW 2170",
    "addr:housenumber":"7",
    "addr:postcode":"2170",
    "addr:street":"Lyn Pde",
    "iso:country":"AU",
    "sg:address":"Unit 21, 7 Lyn Pde",
    "sg:city":"Prestons",
    "sg:classifiers":[
        {
            "category":"Home & Garden",
            "subcategory":"Building Materials",
            "type":"Retail Goods"
        }
    ],
    "sg:phone":"+61 2 9826 0602",
    "sg:postcode":"2170",
    "sg:province":"NSW",
    "sg:tags":[
        "lawn",
        "cutting",
        "maintenance"
    ],
    "wof:name":"Industrial Grass Cutting Service",
    "wof:placetype":"venue"
},
  "geometry": {"coordinates":[150.888275147,-33.9281272888],"type":"Point"}
}