{
  "type": "Feature",
  "properties": {
    "addr:full":"Unit B1, 46-62 Maddox St Alexandria NSW 2015",
    "addr:housenumber":"46-62",
    "addr:postcode":"2015",
    "addr:street":"Maddox St",
    "iso:country":"AU",
    "sg:address":"Unit B1, 46-62 Maddox St",
    "sg:city":"Alexandria",
    "sg:classifiers":[
        {
            "category":"Shopping",
            "type":"Retail Goods"
        }
    ],
    "sg:phone":"+61 2 9690 1999",
    "sg:postcode":"2015",
    "sg:province":"NSW",
    "sg:tags":[
        "clearance",
        "factory",
        "outlet"
    ],
    "wof:name":"Designer Sofas",
    "wof:placetype":"venue"
},
  "geometry": {"coordinates":[151.193634033,-33.9074401855],"type":"Point"}
}