{
  "type": "Feature",
  "properties": {
    "addr:full":"19 John Phillip Drv Bonny Hills NSW 2445",
    "addr:housenumber":"19",
    "addr:postcode":"2445",
    "addr:street":"John Phillip Drv",
    "iso:country":"AU",
    "sg:address":"19 John Phillip Drv",
    "sg:city":"Bonny Hills",
    "sg:classifiers":[
        {
            "category":"Building & Trades",
            "subcategory":"Construction",
            "type":"Services"
        }
    ],
    "sg:phone":"+61 2 6585 5987",
    "sg:postcode":"2445",
    "sg:province":"NSW",
    "sg:tags":[
        "plasterboard",
        "plasterer",
        "fixer"
    ],
    "wof:name":"Hogg Richard",
    "wof:placetype":"venue"
},
  "geometry": {"coordinates":[152.83433500000001,-31.591665],"type":"Point"}
}