{
  "type": "Feature",
  "properties": {
    "addr:full":"175- 183 Mickleham Rd Tullamarine VIC 3043",
    "addr:housenumber":"175 183",
    "addr:postcode":"3043",
    "addr:street":"Mickleham Rd",
    "iso:country":"AU",
    "sg:address":"175- 183 Mickleham Rd",
    "sg:city":"Tullamarine",
    "sg:classifiers":[
        {
            "category":"Retail",
            "subcategory":"Auto Repair",
            "type":"Services"
        }
    ],
    "sg:phone":"+61 3 9330 1237",
    "sg:postcode":"3043",
    "sg:province":"VIC",
    "sg:tags":[
        "repairer",
        "motor",
        "engineer"
    ],
    "wof:name":"Shell Tullamarine Self Serve",
    "wof:placetype":"venue"
},
  "geometry": {"coordinates":[144.88044738799999,-37.6975860596],"type":"Point"}
}