{
  "type": "Feature",
  "properties": {
    "iso:country":"AU",
    "sg:address":"Shop 1/ 6 First Ave",
    "sg:city":"Caloundra",
    "sg:classifiers":[
        {
            "category":"Health Services",
            "subcategory":"Doctor",
            "type":"Services"
        }
    ],
    "sg:phone":"+61 7 5491 7398",
    "sg:postcode":"4551",
    "sg:province":"QLD",
    "sg:tags":[
        "occupational",
        "safety"
    ],
    "wof:name":"Critical First Aid Training and Supplies",
    "wof:placetype":"venue"
},
  "geometry": {"coordinates":[153.123657227,-26.8034286499],"type":"Point"}
}