{
  "type": "Feature",
  "properties": {
    "iso:country":"AU",
    "sg:address":"1839 Frankston Flinders Rd",
    "sg:city":"Hastings",
    "sg:classifiers":[
        {
            "category":"Manufacturing",
            "subcategory":"Lumber",
            "type":"Manufacturing & Wholesale Goods"
        }
    ],
    "sg:phone":"+61 3 5979 7392",
    "sg:postcode":"3915",
    "sg:province":"VIC",
    "sg:tags":[
        "sawmillers"
    ],
    "wof:name":"Australian Reclaimed Timbers",
    "wof:placetype":"venue"
},
  "geometry": {"coordinates":[145.18457031200001,-38.2847328186],"type":"Point"}
}