{
  "type": "Feature",
  "properties": {
    "iso:country":"AU",
    "sg:address":"86 Commercial St East",
    "sg:city":"Mt Gambier",
    "sg:classifiers":[
        {
            "category":"Personal",
            "subcategory":"Beauty Salon",
            "type":"Services"
        }
    ],
    "sg:phone":"+61 8 8723 3448",
    "sg:postcode":"5290",
    "sg:province":"SA",
    "sg:tags":[
        "hairdresser"
    ],
    "wof:name":"The Salon Hair Designers",
    "wof:placetype":"venue"
},
  "geometry": {"coordinates":[140.78066999999999,-37.830753],"type":"Point"}
}