{
  "type": "Feature",
  "properties": {
    "iso:country":"AU",
    "sg:address":"252 Rocky Point Rd",
    "sg:city":"Ramsgate",
    "sg:classifiers":[
        {
            "category":"Health Services",
            "subcategory":"Doctor",
            "type":"Services"
        }
    ],
    "sg:phone":"+61 2 9529 6934",
    "sg:postcode":"2217",
    "sg:province":"NSW",
    "sg:tags":[
        "medical",
        "practitioner"
    ],
    "wof:name":"Jacobi M",
    "wof:placetype":"venue"
},
  "geometry": {"coordinates":[151.13584900000001,-33.985531],"type":"Point"}
}