{
  "type": "Feature",
  "properties": {
    "addr:full":"83 Woodlands Ave Lugarno NSW 2210",
    "addr:housenumber":"83",
    "addr:postcode":"2210",
    "addr:street":"Woodlands Ave",
    "iso:country":"AU",
    "sg:address":"83 Woodlands Ave",
    "sg:city":"Lugarno",
    "sg:classifiers":[
        {
            "category":"Education",
            "subcategory":"Music School",
            "type":"Public Place"
        }
    ],
    "sg:phone":"+61 2 9534 1840",
    "sg:postcode":"2210",
    "sg:province":"NSW",
    "sg:tags":[
        "teacher"
    ],
    "wof:name":"Sinclair Margaret",
    "wof:placetype":"venue"
},
  "geometry": {"coordinates":[151.05238299999999,-33.989578],"type":"Point"}
}