{
  "type": "Feature",
  "properties": {
    "addr:full":"Caswell St Coonamble NSW 2829",
    "addr:postcode":"2829",
    "addr:street":"Caswell St",
    "iso:country":"AU",
    "sg:address":"Caswell St",
    "sg:city":"Coonamble",
    "sg:classifiers":[
        {
            "category":"Sports & Exercise",
            "subcategory":"Golf",
            "type":"Entertainment"
        }
    ],
    "sg:phone":"+61 2 6822 1303",
    "sg:postcode":"2829",
    "sg:province":"NSW",
    "sg:tags":[
        "club"
    ],
    "wof:name":"Coonamble Golf Club",
    "wof:placetype":"venue"
},
  "geometry": {"coordinates":[148.38446044899999,-30.9537200928],"type":"Point"}
}