{
  "type": "Feature",
  "properties": {
    "iso:country":"AU",
    "sg:address":"44 Division St",
    "sg:city":"Welshpool",
    "sg:classifiers":[
        {
            "category":"Professional",
            "type":"Services"
        }
    ],
    "sg:phone":"+61 419 916 900",
    "sg:postcode":"6106",
    "sg:province":"WA",
    "sg:tags":[
        "transport"
    ],
    "wof:name":"Fisher Freighters",
    "wof:placetype":"venue"
},
  "geometry": {"coordinates":[115.932731628,-31.9912071228],"type":"Point"}
}