{
  "type": "Feature",
  "properties": {
    "addr:full":"Southlands Shopng Cntr 37 Burrendah Blv Willetton WA 6155",
    "addr:housenumber":"37",
    "addr:postcode":"6155",
    "addr:street":"Burrendah Blv",
    "iso:country":"AU",
    "sg:address":"Southlands Shopng Cntr 37 Burrendah Blv",
    "sg:city":"Willetton",
    "sg:classifiers":[
        {
            "category":"Ice Cream",
            "type":"Food & Drink"
        }
    ],
    "sg:phone":"+61 8 9332 9228",
    "sg:postcode":"6155",
    "sg:province":"WA",
    "sg:tags":[
        "retail"
    ],
    "wof:name":"Baskin-Robbins Australia Pty Ltd",
    "wof:placetype":"venue"
},
  "geometry": {"coordinates":[115.879158,-32.055462],"type":"Point"}
}