{
  "type": "Feature",
  "properties": {
    "iso:country":"AU",
    "sg:address":"42- 52 Strezlecki Ave",
    "sg:city":"Sunshine",
    "sg:classifiers":[
        {
            "category":"Wholesale",
            "subcategory":"Auto Parts",
            "type":"Manufacturing & Wholesale Goods"
        }
    ],
    "sg:phone":"+61 3 9311 6696",
    "sg:postcode":"3020",
    "sg:province":"VIC",
    "sg:tags":[
        "tyre"
    ],
    "wof:name":"Toyo Tyre & Rubber Aust. Ltd.",
    "wof:placetype":"venue"
},
  "geometry": {"coordinates":[144.82458500000001,-37.808483],"type":"Point"}
}