{
  "type": "Feature",
  "properties": {
    "iso:country":"AU",
    "sg:address":"48 Bradley St",
    "sg:city":"Cobar",
    "sg:classifiers":[
        {
            "category":"Retail",
            "subcategory":"Auto Repair",
            "type":"Services"
        }
    ],
    "sg:phone":"+61 2 6836 3276",
    "sg:postcode":"2835",
    "sg:province":"NSW",
    "sg:tags":[
        "beater",
        "painter",
        "panel"
    ],
    "wof:name":"Piers Brown Towing Services",
    "wof:placetype":"venue"
},
  "geometry": {"coordinates":[145.831604,-31.495108],"type":"Point"}
}