{
  "type": "Feature",
  "properties": {
    "addr:full":"11 Corporate Ave Rowville VIC 3178",
    "addr:housenumber":"11",
    "addr:postcode":"3178",
    "addr:street":"Corporate Ave",
    "iso:country":"AU",
    "sg:address":"11 Corporate Ave",
    "sg:city":"Rowville",
    "sg:classifiers":[
        {
            "category":"Building & Trades",
            "subcategory":"Construction",
            "type":"Services"
        }
    ],
    "sg:phone":"+61 3 9751 4222",
    "sg:postcode":"3178",
    "sg:province":"VIC",
    "sg:tags":[
        "installation",
        "air conditioning"
    ],
    "wof:name":"D & E Airconditioning Pty Ltd",
    "wof:placetype":"venue"
},
  "geometry": {"coordinates":[145.22019958499999,-37.9248123169],"type":"Point"}
}