{
  "type": "Feature",
  "properties": {
    "addr:full":"PO Box 549 Erindale Centre ACT 2903",
    "addr:postcode":"2903",
    "iso:country":"AU",
    "sg:address":"PO Box 549",
    "sg:city":"Erindale Centre",
    "sg:classifiers":[
        {
            "category":"Home & Garden",
            "subcategory":"Building Materials",
            "type":"Retail Goods"
        }
    ],
    "sg:phone":"+61 412 696 958",
    "sg:postcode":"2903",
    "sg:province":"ACT",
    "sg:tags":[
        "shutter",
        "roller",
        "grille"
    ],
    "wof:name":"Independent Roller Doors",
    "wof:placetype":"venue"
},
  "geometry": {"coordinates":[149.08526611299999,-35.4012794495],"type":"Point"}
}