{
  "type": "Feature",
  "properties": {
    "addr:full":"11/199 Balcatta Rd Balcatta WA 6021",
    "addr:housenumber":"11 / 199",
    "addr:postcode":"6021",
    "addr:street":"Balcatta Rd",
    "iso:country":"AU",
    "sg:address":"11/199 Balcatta Rd",
    "sg:city":"Balcatta",
    "sg:classifiers":[
        {
            "category":"Building & Trades",
            "subcategory":"Construction",
            "type":"Services"
        }
    ],
    "sg:phone":"+61 8 9240 1142",
    "sg:postcode":"6021",
    "sg:province":"WA",
    "sg:tags":[
        "contractor"
    ],
    "wof:name":"Artique Homes",
    "wof:placetype":"venue"
},
  "geometry": {"coordinates":[115.813453674,-31.8608722687],"type":"Point"}
}