{
  "type": "Feature",
  "properties": {
    "iso:country":"AU",
    "sg:address":"21 Philippine Pde",
    "sg:city":"Palm Beach",
    "sg:classifiers":[
        {
            "category":"Real Estate",
            "subcategory":"Surveying",
            "type":"Services"
        }
    ],
    "sg:phone":"+61 7 5598 3334",
    "sg:postcode":"4221",
    "sg:province":"QLD",
    "sg:tags":[
        "surveyor",
        "land"
    ],
    "wof:name":"McIntyre Stewart & Assoc",
    "wof:placetype":"venue"
},
  "geometry": {"coordinates":[153.470779419,-28.1253585815],"type":"Point"}
}