{
  "type": "Feature",
  "properties": {
    "addr:full":"Suite 1, 3 rd Floor Strathfield Plz Strathfield NSW 2135",
    "addr:housenumber":"3",
    "addr:postcode":"2135",
    "addr:street":"Rd",
    "iso:country":"AU",
    "sg:address":"Suite 1, 3",
    "sg:city":"rd Floor Strathfield Plz Strathfield",
    "sg:classifiers":[
        {
            "category":"Health Services",
            "subcategory":"Dentist",
            "type":"Services"
        }
    ],
    "sg:phone":"+61 2 9746 6749",
    "sg:postcode":"2135",
    "sg:province":"NSW",
    "wof:name":"Dalton J & Teasdale J",
    "wof:placetype":"venue"
},
  "geometry": {"coordinates":[151.09182739299999,-33.8769302368],"type":"Point"}
}