{
  "type": "Feature",
  "properties": {
    "addr:full":"35 Marryatt St Port Adelaide SA 5015",
    "addr:housenumber":"35",
    "addr:postcode":"5015",
    "addr:street":"Marryatt St",
    "iso:country":"AU",
    "sg:address":"35 Marryatt St",
    "sg:city":"Port Adelaide",
    "sg:classifiers":[
        {
            "category":"Education",
            "subcategory":"Special Training",
            "type":"Public Place"
        }
    ],
    "sg:phone":"+61 8 8447 2477",
    "sg:postcode":"5015",
    "sg:province":"SA",
    "sg:tags":[
        "development"
    ],
    "wof:name":"Enable Consultation Services",
    "wof:placetype":"venue"
},
  "geometry": {"coordinates":[138.50604248100001,-34.8460617065],"type":"Point"}
}