{
  "type": "Feature",
  "properties": {
    "addr:full":"399 Bay St Brighton VIC 3186",
    "addr:housenumber":"399",
    "addr:postcode":"3186",
    "addr:street":"Bay St",
    "iso:country":"AU",
    "sg:address":"399 Bay St",
    "sg:city":"Brighton",
    "sg:classifiers":[
        {
            "category":"Shopping",
            "subcategory":"Clothing, Apparel, & Fashions",
            "type":"Retail Goods"
        }
    ],
    "sg:phone":"+61 3 9596 0675",
    "sg:postcode":"3186",
    "sg:province":"VIC",
    "sg:tags":[
        "lady",
        "wear"
    ],
    "wof:name":"M Store",
    "wof:placetype":"venue"
},
  "geometry": {"coordinates":[145.00517273,-37.9057197571],"type":"Point"}
}