{
  "type": "Feature",
  "properties": {
    "iso:country":"AU",
    "sg:address":"Unit 46, 34 Ralph St",
    "sg:city":"Alexandria",
    "sg:classifiers":[
        {
            "category":"Shopping",
            "subcategory":"Clothing, Apparel, & Fashions",
            "type":"Retail Goods"
        }
    ],
    "sg:phone":"+61 2 8338 0899",
    "sg:postcode":"2015",
    "sg:province":"NSW",
    "sg:tags":[
        "uniform"
    ],
    "wof:name":"Spa & Salon",
    "wof:placetype":"venue"
},
  "geometry": {"coordinates":[151.19818115199999,-33.9179840088],"type":"Point"}
}