{
  "type": "Feature",
  "properties": {
    "addr:full":"5 Albert Hill Rd Lilydale VIC 3140",
    "addr:housenumber":"5",
    "addr:postcode":"3140",
    "addr:street":"Albert Hill Rd",
    "iso:country":"AU",
    "sg:address":"5 Albert Hill Rd",
    "sg:city":"Lilydale",
    "sg:classifiers":[
        {
            "category":"Retail",
            "subcategory":"Laundry & Dry Cleaning",
            "type":"Services"
        }
    ],
    "sg:phone":"+61 418 256 099",
    "sg:postcode":"3140",
    "sg:province":"VIC",
    "wof:name":"Lilydale Coin Laundrettes",
    "wof:placetype":"venue"
},
  "geometry": {"coordinates":[145.34283447300001,-37.755695343],"type":"Point"}
}