{
  "type": "Feature",
  "properties": {
    "addr:full":"Suite G01, 77 Dunning Ave Rosebery NSW 2018",
    "addr:housenumber":"77",
    "addr:postcode":"2018",
    "addr:street":"Dunning Ave",
    "iso:country":"AU",
    "sg:address":"Suite G01, 77 Dunning Ave",
    "sg:city":"Rosebery",
    "sg:classifiers":[
        {
            "category":"Home & Garden",
            "subcategory":"Furniture",
            "type":"Retail Goods"
        }
    ],
    "sg:phone":"+61 2 9662 2322",
    "sg:postcode":"2018",
    "sg:province":"NSW",
    "sg:tags":[
        "business"
    ],
    "wof:name":"Tri Commercial Group Pty Ltd",
    "wof:placetype":"venue"
},
  "geometry": {"coordinates":[151.20278930699999,-33.9152755737],"type":"Point"}
}