{
  "type": "Feature",
  "properties": {
    "addr:full":"Davis Rd Mt Isa QLD 4825",
    "addr:postcode":"4825",
    "addr:street":"Davis Rd",
    "iso:country":"AU",
    "sg:address":"Davis Rd",
    "sg:city":"Mt Isa",
    "sg:classifiers":[
        {
            "category":"Arena",
            "subcategory":"Sports Club",
            "type":"Entertainment"
        }
    ],
    "sg:phone":"+61 7 4743 7788",
    "sg:postcode":"4825",
    "sg:province":"QLD",
    "sg:tags":[
        "defence",
        "supply",
        "self",
        "instruction",
        "martial art"
    ],
    "wof:name":"Mija Judo Academy Inc",
    "wof:placetype":"venue"
},
  "geometry": {"coordinates":[139.492355,-20.701447],"type":"Point"}
}