{
  "type": "Feature",
  "properties": {
    "addr:full":"585 South Rd Regency Park SA 5010",
    "addr:housenumber":"585",
    "addr:postcode":"5010",
    "addr:street":"South Rd",
    "iso:country":"AU",
    "sg:address":"585 South Rd",
    "sg:city":"Regency Park",
    "sg:classifiers":[
        {
            "category":"Home & Garden",
            "subcategory":"Hardware",
            "type":"Retail Goods"
        }
    ],
    "sg:phone":"+61 8 8345 4022",
    "sg:postcode":"5010",
    "sg:province":"SA",
    "sg:tags":[
        "pumping",
        "contractor"
    ],
    "wof:name":"Allight",
    "wof:placetype":"venue"
},
  "geometry": {"coordinates":[138.56517028799999,-34.8540229797],"type":"Point"}
}