{
  "type": "Feature",
  "properties": {
    "addr:full":"9 Vella Drv Sunshine West VIC 3020",
    "addr:housenumber":"9",
    "addr:postcode":"3020",
    "addr:street":"Vella Drv",
    "iso:country":"AU",
    "sg:address":"9 Vella Drv",
    "sg:city":"Sunshine West",
    "sg:classifiers":[
        {
            "category":"Utilities",
            "subcategory":"Sewage",
            "type":"Services"
        }
    ],
    "sg:phone":"+61 3 9311 5766",
    "sg:postcode":"3020",
    "sg:province":"VIC",
    "sg:tags":[
        "water",
        "waste",
        "treatment"
    ],
    "wof:name":"Advanced Water Technologies Pty Ltd",
    "wof:placetype":"venue"
},
  "geometry": {"coordinates":[144.83154300000001,-37.806038],"type":"Point"}
}