{
  "type": "Feature",
  "properties": {
    "iso:country":"AU",
    "sg:address":"170 Main Rd",
    "sg:city":"Blackwood",
    "sg:classifiers":[
        {
            "category":"Professional",
            "subcategory":"Secretarial Services",
            "type":"Services"
        }
    ],
    "sg:phone":"+61 8 8278 9600",
    "sg:postcode":"5051",
    "sg:province":"SA",
    "sg:tags":[
        "typing"
    ],
    "wof:name":"Mitcham Smart Biz",
    "wof:placetype":"venue"
},
  "geometry": {"coordinates":[138.619095,-35.014259],"type":"Point"}
}