{
  "type": "Feature",
  "properties": {
    "addr:full":"73 Twynam St Narrandera NSW 2700",
    "addr:housenumber":"73",
    "addr:postcode":"2700",
    "addr:street":"Twynam St",
    "iso:country":"AU",
    "sg:address":"73 Twynam St",
    "sg:city":"Narrandera",
    "sg:classifiers":[
        {
            "category":"Building & Trades",
            "subcategory":"Construction",
            "type":"Services"
        }
    ],
    "sg:phone":"+61 2 6959 2808",
    "sg:postcode":"2700",
    "sg:province":"NSW",
    "sg:tags":[
        "contractor"
    ],
    "wof:name":"Nielsen M J",
    "wof:placetype":"venue"
},
  "geometry": {"coordinates":[146.54583740199999,-34.7458534241],"type":"Point"}
}