{
  "type": "Feature",
  "properties": {
    "addr:full":"70 Shop 8 Spearwood Rd Alice Springs NT 0870",
    "addr:housenumber":"70 shop 8",
    "addr:postcode":"nt 0870",
    "addr:street":"Spearwood Rd",
    "iso:country":"AU",
    "sg:address":"70 Shop 8 Spearwood Rd",
    "sg:city":"Alice Springs",
    "sg:classifiers":[
        {
            "category":"Professional",
            "subcategory":"Management & Consulting",
            "type":"Services"
        }
    ],
    "sg:phone":"+61 8 8952 0160",
    "sg:postcode":"0870",
    "sg:province":"NT",
    "sg:tags":[
        "consultant",
        "educational"
    ],
    "wof:name":"Kip Mcgrath Education Centre",
    "wof:placetype":"venue"
},
  "geometry": {"coordinates":[133.902542114,-23.695854187],"type":"Point"}
}