{
  "type": "Feature",
  "properties": {
    "addr:full":"14 Eldridge Rd Bankstown NSW 2200",
    "addr:housenumber":"14",
    "addr:postcode":"2200",
    "addr:street":"Eldridge Rd",
    "iso:country":"AU",
    "sg:address":"14 Eldridge Rd",
    "sg:city":"Bankstown",
    "sg:classifiers":[
        {
            "category":"Health Services",
            "subcategory":"Health Practitioner",
            "type":"Services"
        }
    ],
    "sg:phone":"+61 2 9707 7826",
    "sg:postcode":"2200",
    "sg:province":"NSW",
    "sg:tags":[
        "dietitian"
    ],
    "wof:name":"Mann David Dr",
    "wof:placetype":"venue"
},
  "geometry": {"coordinates":[151.02642800000001,-33.932655],"type":"Point"}
}