{
  "type": "Feature",
  "properties": {
    "addr:full":"Shellharbour City Plaza Unit 1, Lot 5, Burra Pl Shellharbour NSW 2529",
    "addr:housenumber":"lot 5",
    "addr:postcode":"2529",
    "addr:street":"Pl",
    "iso:country":"AU",
    "sg:address":"Shellharbour City Plaza Unit 1, Lot 5, Burra Pl",
    "sg:city":"Shellharbour",
    "sg:classifiers":[
        {
            "category":"Sports & Exercise",
            "subcategory":"Ski Slope",
            "type":"Entertainment"
        }
    ],
    "sg:phone":"+61 2 4297 5100",
    "sg:postcode":"2529",
    "sg:province":"NSW",
    "sg:tags":[
        "equipment",
        "hire",
        "retail",
        "snow"
    ],
    "wof:name":"Rebel Sport",
    "wof:placetype":"venue"
},
  "geometry": {"coordinates":[150.836425781,-34.5630912781],"type":"Point"}
}