{
  "type": "Feature",
  "properties": {
    "iso:country":"AU",
    "sg:address":"2 Gowrie Ave",
    "sg:city":"Frankston South",
    "sg:classifiers":[
        {
            "category":"Home & Garden",
            "subcategory":"Building Materials",
            "type":"Retail Goods"
        }
    ],
    "sg:phone":"+61 3 9783 2134",
    "sg:postcode":"3199",
    "sg:province":"VIC",
    "sg:tags":[
        "concrete",
        "gutter",
        "kerb"
    ],
    "wof:name":"Best Concrete Services",
    "wof:placetype":"venue"
},
  "geometry": {"coordinates":[145.11497497600001,-38.1621932983],"type":"Point"}
}