{
  "type": "Feature",
  "properties": {
    "addr:full":"96 Constitution Rd Windsor QLD 4030",
    "addr:housenumber":"96",
    "addr:postcode":"4030",
    "addr:street":"Constitution Rd",
    "iso:country":"AU",
    "sg:address":"96 Constitution Rd",
    "sg:city":"Windsor",
    "sg:classifiers":[
        {
            "category":"Utilities",
            "subcategory":"Telephone",
            "type":"Services"
        }
    ],
    "sg:phone":"+61 7 3357 7301",
    "sg:postcode":"4030",
    "sg:province":"QLD",
    "sg:tags":[
        "installation",
        "system",
        "maintenance"
    ],
    "wof:name":"Rablin Communications Pty Ltd",
    "wof:placetype":"venue"
},
  "geometry": {"coordinates":[153.02720600000001,-27.430696],"type":"Point"}
}