{
  "type": "Feature",
  "properties": {
    "addr:full":"Unit 1a Gillott St Belconnen ACT 2617",
    "addr:housenumber":"unit 1a",
    "addr:postcode":"2617",
    "addr:street":"Gillott St",
    "iso:country":"AU",
    "sg:address":"Unit 1a Gillott St",
    "sg:city":"Belconnen",
    "sg:classifiers":[
        {
            "category":"Retail",
            "subcategory":"Auto Repair",
            "type":"Services"
        }
    ],
    "sg:phone":"+61 2 6251 3115",
    "sg:postcode":"2617",
    "sg:province":"ACT",
    "sg:tags":[
        "repairer",
        "motor",
        "engineer"
    ],
    "wof:name":"Total Traction Services",
    "wof:placetype":"venue"
},
  "geometry": {"coordinates":[149.06158447300001,-35.2390098572],"type":"Point"}
}