{
  "type": "Feature",
  "properties": {
    "addr:full":"10 Mundon Pl West Pennant Hills NSW 2125",
    "addr:housenumber":"10",
    "addr:postcode":"2125",
    "addr:street":"Pl",
    "iso:country":"AU",
    "sg:address":"10 Mundon Pl",
    "sg:city":"West Pennant Hills",
    "sg:classifiers":[
        {
            "category":"Building & Trades",
            "subcategory":"Cleaning & Sanitation",
            "type":"Services"
        }
    ],
    "sg:phone":"+61 2 9872 8501",
    "sg:postcode":"2125",
    "sg:province":"NSW",
    "sg:tags":[
        "industrial",
        "commercial",
        "contractor"
    ],
    "wof:name":"Ozone Industries",
    "wof:placetype":"venue"
},
  "geometry": {"coordinates":[151.041778564,-33.7583503723],"type":"Point"}
}