{
  "type": "Feature",
  "properties": {
    "addr:full":"441 Liverpool Rd Ashfield NSW 2131",
    "addr:housenumber":"441",
    "addr:postcode":"2131",
    "addr:street":"Liverpool Rd",
    "iso:country":"AU",
    "sg:address":"441 Liverpool Rd",
    "sg:city":"Ashfield",
    "sg:classifiers":[
        {
            "category":"Restaurant",
            "type":"Food & Drink"
        }
    ],
    "sg:phone":"+61 2 9716 9966",
    "sg:postcode":"2131",
    "sg:province":"NSW",
    "wof:name":"El Rincon Quindiano",
    "wof:placetype":"venue"
},
  "geometry": {"coordinates":[151.117095947,-33.888381958],"type":"Point"}
}