{
  "type": "Feature",
  "properties": {
    "iso:country":"AU",
    "sg:address":"5 Muir St",
    "sg:city":"Highett",
    "sg:classifiers":[
        {
            "category":"Building & Trades",
            "subcategory":"Cleaning & Sanitation",
            "type":"Services"
        }
    ],
    "sg:phone":"+61 3 9555 4414",
    "sg:postcode":"3190",
    "sg:province":"VIC",
    "sg:tags":[
        "cleaner",
        "repairer",
        "roof"
    ],
    "wof:name":"Mayfair Roof Restoration",
    "wof:placetype":"venue"
},
  "geometry": {"coordinates":[145.03538513199999,-37.9456062317],"type":"Point"}
}