{
  "type": "Feature",
  "properties": {
    "addr:full":"1/ 38 Jubilee St Mt Waverley VIC 3149",
    "addr:housenumber":"/ 38",
    "addr:postcode":"3149",
    "addr:street":"Jubilee St Mt",
    "iso:country":"AU",
    "sg:address":"1/ 38 Jubilee St",
    "sg:city":"Mt Waverley",
    "sg:classifiers":[
        {
            "category":"Health Services",
            "subcategory":"Health Practitioner",
            "type":"Services"
        }
    ],
    "sg:phone":"+61 3 9888 0087",
    "sg:postcode":"3149",
    "sg:province":"VIC",
    "sg:tags":[
        "psychologist"
    ],
    "wof:name":"Milo-Ashley Patricia",
    "wof:placetype":"venue"
},
  "geometry": {"coordinates":[145.12515258799999,-37.8602828979],"type":"Point"}
}