{
  "type": "Feature",
  "properties": {
    "iso:country":"AU",
    "sg:address":"38a Duncan St",
    "sg:city":"Roselands",
    "sg:classifiers":[
        {
            "category":"Professional",
            "subcategory":"Accounting & Tax Preparation",
            "type":"Services"
        }
    ],
    "sg:phone":"+61 2 9750 7624",
    "sg:postcode":"2196",
    "sg:province":"NSW",
    "sg:tags":[
        "accountant",
        "auditor"
    ],
    "wof:name":"S.N.C. Office Services",
    "wof:placetype":"venue"
},
  "geometry": {"coordinates":[151.059402,-33.931473],"type":"Point"}
}