{
  "type": "Feature",
  "properties": {
    "addr:full":"37- 41 Oxford St Oakleigh QLD 4060",
    "addr:housenumber":"41",
    "addr:postcode":"4060",
    "addr:street":"Oxford St",
    "iso:country":"AU",
    "sg:address":"37- 41 Oxford St",
    "sg:city":"Oakleigh",
    "sg:classifiers":[
        {
            "category":"Manufacturing",
            "subcategory":"Tools & Machinery",
            "type":"Manufacturing & Wholesale Goods"
        }
    ],
    "sg:phone":"+61 3 9568 3627",
    "sg:postcode":"4060",
    "sg:province":"QLD",
    "wof:name":"Mansfield Tools",
    "wof:placetype":"venue"
},
  "geometry": {"coordinates":[152.99659729000001,-27.459602356],"type":"Point"}
}