{
  "type": "Feature",
  "properties": {
    "addr:full":"6 Kingston Ave Richmond SA 5033",
    "addr:housenumber":"6",
    "addr:postcode":"5033",
    "addr:street":"Kingston Ave",
    "iso:country":"AU",
    "sg:address":"6 Kingston Ave",
    "sg:city":"Richmond",
    "sg:classifiers":[
        {
            "category":"Professional",
            "type":"Services"
        }
    ],
    "sg:phone":"+61 8 8234 0033",
    "sg:postcode":"5033",
    "sg:province":"SA",
    "sg:tags":[
        "shop",
        "fitting"
    ],
    "wof:name":"Hamilton Kennedy",
    "wof:placetype":"venue"
},
  "geometry": {"coordinates":[138.56794738799999,-34.9394760132],"type":"Point"}
}