{
  "type": "Feature",
  "properties": {
    "addr:full":"215 Euroa Rd Shepparton East VIC 3631",
    "addr:housenumber":"215",
    "addr:postcode":"3631",
    "addr:street":"Euroa Rd",
    "iso:country":"AU",
    "sg:address":"215 Euroa Rd",
    "sg:city":"Shepparton East",
    "sg:classifiers":[
        {
            "category":"Shopping",
            "subcategory":"Crafts & Fabrics",
            "type":"Retail Goods"
        }
    ],
    "sg:phone":"+61 3 5827 1321",
    "sg:postcode":"3631",
    "sg:province":"VIC",
    "sg:tags":[
        "wool",
        "classers"
    ],
    "wof:name":"Durling C L",
    "wof:placetype":"venue"
},
  "geometry": {"coordinates":[145.479049683,-36.4015693665],"type":"Point"}
}