{
  "type": "Feature",
  "properties": {
    "addr:full":"Cnr Compton & Ewing Rds Logan QLD 4114",
    "addr:postcode":"4114",
    "addr:street":"Cnr Compton & Ewing Rds",
    "iso:country":"AU",
    "sg:address":"Cnr Compton & Ewing Rds",
    "sg:city":"Logan",
    "sg:classifiers":[
        {
            "category":"Retail",
            "subcategory":"Auto Rental",
            "type":"Services"
        }
    ],
    "sg:phone":"+61 7 3808 7131",
    "sg:postcode":"4114",
    "sg:province":"QLD",
    "sg:tags":[
        "bus",
        "truck"
    ],
    "wof:name":"Thrifty Truck Rental",
    "wof:placetype":"venue"
},
  "geometry": {"coordinates":[153.111206055,-27.6194992065],"type":"Point"}
}