{
  "type": "Feature",
  "properties": {
    "addr:full":"216 Creswick Rd Ballarat VIC 3350",
    "addr:housenumber":"216",
    "addr:postcode":"3350",
    "addr:street":"Creswick Rd",
    "iso:country":"AU",
    "sg:address":"216 Creswick Rd",
    "sg:city":"Ballarat",
    "sg:classifiers":[
        {
            "category":"Professional",
            "subcategory":"Accounting & Tax Preparation",
            "type":"Services"
        }
    ],
    "sg:phone":"+61 3 5331 1678",
    "sg:postcode":"3350",
    "sg:province":"VIC",
    "sg:tags":[
        "accountant",
        "auditor"
    ],
    "wof:name":"John Seery & Associates",
    "wof:placetype":"venue"
},
  "geometry": {"coordinates":[143.84977699999999,-37.539658],"type":"Point"}
}