{
  "type": "Feature",
  "properties": {
    "iso:country":"AU",
    "sg:address":"Shop 4 22 Weringa Ave",
    "sg:city":"Lake Heights",
    "sg:classifiers":[
        {
            "category":"Government",
            "subcategory":"Post Office",
            "type":"Public Place"
        }
    ],
    "sg:phone":"+61 2 4274 1579",
    "sg:postcode":"2502",
    "sg:province":"NSW",
    "sg:tags":[
        "postal"
    ],
    "wof:name":"Australia Post",
    "wof:placetype":"venue"
},
  "geometry": {"coordinates":[150.87231399999999,-34.479599],"type":"Point"}
}