{
  "type": "Feature",
  "properties": {
    "addr:full":"307- 309 Illawarra Rd Marrickville NSW 2204",
    "addr:housenumber":"309",
    "addr:postcode":"2204",
    "addr:street":"Illawarra Rd",
    "iso:country":"AU",
    "sg:address":"307- 309 Illawarra Rd",
    "sg:city":"Marrickville",
    "sg:classifiers":[
        {
            "category":"Food & Beverages",
            "subcategory":"Supermarket",
            "type":"Retail Goods"
        }
    ],
    "sg:phone":"+61 2 9558 3087",
    "sg:postcode":"2204",
    "sg:province":"NSW",
    "sg:tags":[
        "grocery",
        "store"
    ],
    "wof:name":"Golden Star Supermarket",
    "wof:placetype":"venue"
},
  "geometry": {"coordinates":[151.15965299999999,-33.907204],"type":"Point"}
}