{
  "type": "Feature",
  "properties": {
    "addr:full":"58 Greenhill Rd Wayville SA 5034",
    "addr:housenumber":"58",
    "addr:postcode":"5034",
    "addr:street":"Greenhill Rd",
    "iso:country":"AU",
    "sg:address":"58 Greenhill Rd",
    "sg:city":"Wayville",
    "sg:classifiers":[
        {
            "category":"Professional",
            "subcategory":"Accounting & Tax Preparation",
            "type":"Services"
        }
    ],
    "sg:phone":"+61 8 8373 5902",
    "sg:postcode":"5034",
    "sg:province":"SA",
    "sg:tags":[
        "accountant",
        "auditor"
    ],
    "wof:name":"Aylett Boydin",
    "wof:placetype":"venue"
},
  "geometry": {"coordinates":[138.59315490700001,-34.9418373108],"type":"Point"}
}