{
  "type": "Feature",
  "properties": {
    "addr:full":"PO Box 155 Cleve SA 5640",
    "addr:postcode":"5640",
    "iso:country":"AU",
    "sg:address":"PO Box 155",
    "sg:city":"Cleve",
    "sg:classifiers":[
        {
            "category":"Food & Beverages",
            "subcategory":"Meat & Fish",
            "type":"Retail Goods"
        }
    ],
    "sg:phone":"+61 8 8628 2855",
    "sg:postcode":"5640",
    "sg:province":"SA",
    "sg:tags":[
        "aquaculture"
    ],
    "wof:name":"Story Engineering",
    "wof:placetype":"venue"
},
  "geometry": {"coordinates":[136.48971557600001,-33.7015953064],"type":"Point"}
}