{
  "type": "Feature",
  "properties": {
    "iso:country":"AU",
    "sg:address":"289 Mulgrave Rd",
    "sg:city":"Cairns",
    "sg:classifiers":[
        {
            "category":"Wholesale",
            "subcategory":"Painting Supplies",
            "type":"Manufacturing & Wholesale Goods"
        }
    ],
    "sg:phone":"+61 7 4031 1655",
    "sg:postcode":"4870",
    "sg:province":"QLD",
    "sg:tags":[
        "painter"
    ],
    "wof:name":"Bristol Paint & Decorator Centres",
    "wof:placetype":"venue"
},
  "geometry": {"coordinates":[145.74331665,-16.9400558472],"type":"Point"}
}