{
  "type": "Feature",
  "properties": {
    "addr:full":"Shop 11, 1 Lancaster Ave Cecil Hills NSW 2171",
    "addr:housenumber":"shop 11 1",
    "addr:postcode":"2171",
    "addr:street":"Lancaster Ave Cecil",
    "iso:country":"AU",
    "sg:address":"Shop 11, 1 Lancaster Ave",
    "sg:city":"Cecil Hills",
    "sg:classifiers":[
        {
            "category":"Health Services",
            "subcategory":"Dentist",
            "type":"Services"
        }
    ],
    "sg:phone":"+61 2 9822 9111",
    "sg:postcode":"2171",
    "sg:province":"NSW",
    "wof:name":"Arguedas Luis Dr",
    "wof:placetype":"venue"
},
  "geometry": {"coordinates":[150.847946167,-33.8868293762],"type":"Point"}
}