{
  "type": "Feature",
  "properties": {
    "addr:full":"Shop 4/ 80 Main St Alstonville NSW 2477",
    "addr:housenumber":"shop 4 / 80",
    "addr:postcode":"2477",
    "addr:street":"Main St",
    "iso:country":"AU",
    "sg:address":"Shop 4/ 80 Main St",
    "sg:city":"Alstonville",
    "sg:classifiers":[
        {
            "category":"Fast Food",
            "type":"Food & Drink"
        }
    ],
    "sg:phone":"+61 2 6628 6886",
    "sg:postcode":"2477",
    "sg:province":"NSW",
    "sg:tags":[
        "away",
        "take"
    ],
    "wof:name":"F&#039;Foodies Village Pantry",
    "wof:placetype":"venue"
},
  "geometry": {"coordinates":[153.435913086,-28.8379936218],"type":"Point"}
}