{
  "type": "Feature",
  "properties": {
    "addr:full":"190 Military Rd Neutral Bay NSW 2089",
    "addr:housenumber":"190",
    "addr:postcode":"2089",
    "addr:street":"Military Rd",
    "iso:country":"AU",
    "sg:address":"190 Military Rd",
    "sg:city":"Neutral Bay",
    "sg:classifiers":[
        {
            "category":"Shopping",
            "subcategory":"Jewelry",
            "type":"Retail Goods"
        }
    ],
    "sg:phone":"+61 2 9953 6519",
    "sg:postcode":"2089",
    "sg:province":"NSW",
    "sg:tags":[
        "jeweller"
    ],
    "wof:name":"Baumann Pearson Jewellers",
    "wof:placetype":"venue"
},
  "geometry": {"coordinates":[151.222122192,-33.831287384],"type":"Point"}
}