{
  "type": "Feature",
  "properties": {
    "iso:country":"AU",
    "sg:address":"36 Ocean Keys Blv",
    "sg:city":"Clarkson",
    "sg:classifiers":[
        {
            "category":"Personal",
            "subcategory":"Beauty Salon",
            "type":"Services"
        }
    ],
    "sg:phone":"+61 8 9407 8588",
    "sg:postcode":"6030",
    "sg:province":"WA",
    "wof:name":"Tonique Health & Beauty Salon",
    "wof:placetype":"venue"
},
  "geometry": {"coordinates":[115.71710967999999,-31.6897106171],"type":"Point"}
}