{
  "type": "Feature",
  "properties": {
    "addr:full":"Lot 15 Lock St Smythesdale VIC 3351",
    "addr:postcode":"3351",
    "addr:street":"Lock St",
    "iso:country":"AU",
    "sg:address":"Lot 15 Lock St",
    "sg:city":"Smythesdale",
    "sg:classifiers":[
        {
            "category":"Building & Trades",
            "subcategory":"Construction",
            "type":"Services"
        }
    ],
    "sg:phone":"+61 3 5342 8228",
    "sg:postcode":"3351",
    "sg:province":"VIC",
    "sg:tags":[
        "contractor"
    ],
    "wof:name":"V.W.J. Contractors",
    "wof:placetype":"venue"
},
  "geometry": {"coordinates":[143.682816,-37.651863],"type":"Point"}
}