{
  "type": "Feature",
  "properties": {
    "iso:country":"AU",
    "sg:address":"12 Illawong Shopng Cntr Fowler Rd",
    "sg:city":"Illawong",
    "sg:classifiers":[
        {
            "category":"Banks & Credit Unions",
            "subcategory":"Bank",
            "type":"Services"
        }
    ],
    "sg:phone":"+61 2 9543 5622",
    "sg:postcode":"2234",
    "sg:province":"NSW",
    "wof:name":"Colonial State Bank Of NSW Limited Customer Service Centres",
    "wof:placetype":"venue"
},
  "geometry": {"coordinates":[151.04199218799999,-33.998626709],"type":"Point"}
}