{
  "type": "Feature",
  "properties": {
    "addr:full":"18 Boord St Semaphore South SA 5019",
    "addr:housenumber":"18",
    "addr:postcode":"5019",
    "addr:street":"Boord St",
    "iso:country":"AU",
    "sg:address":"18 Boord St",
    "sg:city":"Semaphore South",
    "sg:classifiers":[
        {
            "category":"Autos & Motor Vehicles",
            "subcategory":"Automobile Sales",
            "type":"Retail Goods"
        }
    ],
    "sg:phone":"+61 412 807 325",
    "sg:postcode":"5019",
    "sg:province":"SA",
    "sg:tags":[
        "car",
        "used"
    ],
    "wof:name":"Best Image Care Sales",
    "wof:placetype":"venue"
},
  "geometry": {"coordinates":[138.478881836,-34.8489379883],"type":"Point"}
}