{
  "type": "Feature",
  "properties": {
    "addr:full":"Corner Smith & Albert Sts Warragul VIC 3820",
    "addr:postcode":"3820",
    "iso:country":"AU",
    "sg:address":"Corner Smith & Albert Sts",
    "sg:city":"Warragul",
    "sg:classifiers":[
        {
            "category":"Fast Food",
            "type":"Food & Drink"
        }
    ],
    "sg:phone":"+61 3 5622 1822",
    "sg:postcode":"3820",
    "sg:province":"VIC",
    "sg:tags":[
        "away",
        "take"
    ],
    "wof:name":"Jade Chinese Cuisine",
    "wof:placetype":"venue"
},
  "geometry": {"coordinates":[145.938614,-38.143978],"type":"Point"}
}