{
  "type": "Feature",
  "properties": {
    "iso:country":"AU",
    "sg:address":"Shop 21 Cessnock Plaza, Keene St",
    "sg:city":"Cessnock",
    "sg:classifiers":[
        {
            "category":"Health Services",
            "subcategory":"Health Practitioner",
            "type":"Services"
        }
    ],
    "sg:phone":"+61 2 4990 6055",
    "sg:postcode":"2325",
    "sg:province":"NSW",
    "sg:tags":[
        "naturopath"
    ],
    "wof:name":"Go Vita Cessnock",
    "wof:placetype":"venue"
},
  "geometry": {"coordinates":[151.35406494099999,-32.8343925476],"type":"Point"}
}