{
  "type": "Feature",
  "properties": {
    "addr:full":"Shop 163 Hare St Echuca VIC 3564",
    "addr:housenumber":"163",
    "addr:postcode":"3564",
    "addr:street":"Hare St",
    "iso:country":"AU",
    "sg:address":"Shop 163 Hare St",
    "sg:city":"Echuca",
    "sg:classifiers":[
        {
            "category":"Shopping",
            "subcategory":"Clothing, Apparel, & Fashions",
            "type":"Retail Goods"
        }
    ],
    "sg:phone":"+61 3 5480 2680",
    "sg:postcode":"3564",
    "sg:province":"VIC",
    "sg:tags":[
        "lady",
        "wear"
    ],
    "wof:name":"Rockmans Stores Pty Limited",
    "wof:placetype":"venue"
},
  "geometry": {"coordinates":[144.74911499000001,-36.1268196106],"type":"Point"}
}