{
  "type": "Feature",
  "properties": {
    "addr:full":"257a Hector St Sefton NSW 2162",
    "addr:housenumber":"257a",
    "addr:postcode":"2162",
    "addr:street":"Hector St",
    "iso:country":"AU",
    "sg:address":"257a Hector St",
    "sg:city":"Sefton",
    "sg:classifiers":[
        {
            "category":"Personal",
            "subcategory":"Beauty Salon",
            "type":"Services"
        }
    ],
    "sg:phone":"+61 2 9644 1386",
    "sg:postcode":"2162",
    "sg:province":"NSW",
    "sg:tags":[
        "hairdresser"
    ],
    "wof:name":"Yousef Hair & Beauty",
    "wof:placetype":"venue"
},
  "geometry": {"coordinates":[151.00454711899999,-33.8956451416],"type":"Point"}
}