{
  "type": "Feature",
  "properties": {
    "iso:country":"AU",
    "sg:address":"Room 7 513 Toorak Rd",
    "sg:city":"Toorak",
    "sg:classifiers":[
        {
            "category":"Retail",
            "subcategory":"Repair Shop",
            "type":"Services"
        }
    ],
    "sg:phone":"+61 3 9826 3783",
    "sg:postcode":"3142",
    "sg:province":"VIC",
    "sg:tags":[
        "mending",
        "clothing",
        "alteration"
    ],
    "wof:name":"Boag Robyn",
    "wof:placetype":"venue"
},
  "geometry": {"coordinates":[145.00973510700001,-37.8410263062],"type":"Point"}
}