{
  "type": "Feature",
  "properties": {
    "iso:country":"AU",
    "sg:address":"2 Minsky Crt",
    "sg:city":"Mt Low",
    "sg:classifiers":[
        {
            "category":"Personal",
            "subcategory":"Massage",
            "type":"Services"
        }
    ],
    "sg:phone":"+61 7 4788 0198",
    "sg:postcode":"4818",
    "sg:province":"QLD",
    "sg:tags":[
        "therapy"
    ],
    "wof:name":"Northern Natural HEaling",
    "wof:placetype":"venue"
},
  "geometry": {"coordinates":[146.672531,-19.23658],"type":"Point"}
}