{
  "type": "Feature",
  "properties": {
    "addr:full":"285 Shute Harbour Rd Airlie Beach QLD 4802",
    "addr:housenumber":"285",
    "addr:postcode":"4802",
    "addr:street":"Shute Harbour Rd",
    "iso:country":"AU",
    "sg:address":"285 Shute Harbour Rd",
    "sg:city":"Airlie Beach",
    "sg:classifiers":[
        {
            "category":"Shopping",
            "subcategory":"Clothing, Apparel, & Fashions",
            "type":"Retail Goods"
        }
    ],
    "sg:phone":"+61 7 4946 6708",
    "sg:postcode":"4802",
    "sg:province":"QLD",
    "sg:tags":[
        "lady",
        "wear"
    ],
    "wof:name":"Beach Shack",
    "wof:placetype":"venue"
},
  "geometry": {"coordinates":[148.718994141,-20.2687683105],"type":"Point"}
}