{
  "type": "Feature",
  "properties": {
    "addr:full":"48 Guthrie St Shepparton VIC 3630",
    "addr:housenumber":"48",
    "addr:postcode":"3630",
    "addr:street":"Guthrie St",
    "iso:country":"AU",
    "sg:address":"48 Guthrie St",
    "sg:city":"Shepparton",
    "sg:classifiers":[
        {
            "category":"Personal",
            "subcategory":"Beauty Salon",
            "type":"Services"
        }
    ],
    "sg:phone":"+61 3 5821 8417",
    "sg:postcode":"3630",
    "sg:province":"VIC",
    "sg:tags":[
        "hairdresser"
    ],
    "wof:name":"Bright Eyes Hair & Beauty",
    "wof:placetype":"venue"
},
  "geometry": {"coordinates":[145.39021301299999,-36.3983917236],"type":"Point"}
}