{
  "type": "Feature",
  "properties": {
    "addr:full":"200 Greenhill Rd Eastwood SA 5063",
    "addr:housenumber":"200",
    "addr:postcode":"5063",
    "addr:street":"Greenhill Rd",
    "iso:country":"AU",
    "sg:address":"200 Greenhill Rd",
    "sg:city":"Eastwood",
    "sg:classifiers":[
        {
            "category":"Professional",
            "subcategory":"Employment Agencies",
            "type":"Services"
        }
    ],
    "sg:phone":"+61 8 8172 7733",
    "sg:postcode":"5063",
    "sg:province":"SA",
    "wof:name":"Entec",
    "wof:placetype":"venue"
},
  "geometry": {"coordinates":[138.618606567,-34.9405784607],"type":"Point"}
}