{
  "type": "Feature",
  "properties": {
    "addr:full":"Lvl 1/ 696 New South Head Rd Rose Bay NSW 2029",
    "addr:housenumber":"/ 696",
    "addr:postcode":"2029",
    "addr:street":"New South Head Rd",
    "iso:country":"AU",
    "sg:address":"Lvl 1/ 696 New South Head Rd",
    "sg:city":"Rose Bay",
    "sg:classifiers":[
        {
            "category":"Government",
            "subcategory":"Post Office",
            "type":"Public Place"
        }
    ],
    "sg:phone":"+61 2 9371 3628",
    "sg:postcode":"2029",
    "sg:province":"NSW",
    "sg:tags":[
        "yoga"
    ],
    "wof:name":"Rose Bay Yoga Room",
    "wof:placetype":"venue"
},
  "geometry": {"coordinates":[151.26930236800001,-33.8697967529],"type":"Point"}
}