{
  "type": "Feature",
  "properties": {
    "addr:full":"Lytton St Cammeray NSW 2062",
    "addr:postcode":"2062",
    "addr:street":"Lytton St",
    "iso:country":"AU",
    "sg:address":"Lytton St",
    "sg:city":"Cammeray",
    "sg:classifiers":[
        {
            "category":"Shopping",
            "subcategory":"Musical Instruments",
            "type":"Retail Goods"
        }
    ],
    "sg:phone":"+61 2 9956 6281",
    "sg:postcode":"2062",
    "sg:province":"NSW",
    "sg:tags":[
        "musician",
        "agent"
    ],
    "wof:name":"Musicians Placement Service",
    "wof:placetype":"venue"
},
  "geometry": {"coordinates":[151.21124267600001,-33.8274536133],"type":"Point"}
}