{
  "type": "Feature",
  "properties": {
    "iso:country":"AU",
    "sg:address":"16 Boyd St",
    "sg:city":"Geraldton",
    "sg:classifiers":[
        {
            "category":"Retail",
            "subcategory":"Auto Repair",
            "type":"Services"
        }
    ],
    "sg:phone":"+61 8 9923 0999",
    "sg:postcode":"6530",
    "sg:province":"WA",
    "sg:tags":[
        "repairer",
        "motor",
        "engineer"
    ],
    "wof:name":"Bonehams Towing Service",
    "wof:placetype":"venue"
},
  "geometry": {"coordinates":[114.632263184,-28.7526359558],"type":"Point"}
}