{
  "type": "Feature",
  "properties": {
    "addr:full":"3 Pacific Ave Tannum Sands QLD 4680",
    "addr:housenumber":"3",
    "addr:postcode":"4680",
    "addr:street":"Pacific Ave",
    "iso:country":"AU",
    "sg:address":"3 Pacific Ave",
    "sg:city":"Tannum Sands",
    "sg:classifiers":[
        {
            "category":"Fast Food",
            "type":"Food & Drink"
        }
    ],
    "sg:phone":"+61 7 4973 7467",
    "sg:postcode":"4680",
    "sg:province":"QLD",
    "sg:tags":[
        "away",
        "take"
    ],
    "wof:name":"Tannum Sands Fish Shop",
    "wof:placetype":"venue"
},
  "geometry": {"coordinates":[151.373947144,-23.947889328],"type":"Point"}
}