{
  "type": "Feature",
  "properties": {
    "addr:full":"AutoPark 2 Lionel Donovan Drv Noosaville QLD 4566",
    "addr:housenumber":"2",
    "addr:postcode":"4566",
    "addr:street":"Lionel Donovan Drv",
    "iso:country":"AU",
    "sg:address":"AutoPark 2 Lionel Donovan Drv",
    "sg:city":"Noosaville",
    "sg:classifiers":[
        {
            "category":"Manufacturing",
            "subcategory":"Motor Vehicles & Parts",
            "type":"Manufacturing & Wholesale Goods"
        }
    ],
    "sg:phone":"+61 7 5480 5566",
    "sg:postcode":"4566",
    "sg:province":"QLD",
    "sg:tags":[
        "replacement"
    ],
    "wof:name":"A1 Auto And Accessories-Toyota",
    "wof:placetype":"venue"
},
  "geometry": {"coordinates":[153.04701232900001,-26.4111747742],"type":"Point"}
}