{
  "type": "Feature",
  "properties": {
    "iso:country":"AU",
    "sg:address":"Shp3/ 335 Chapel Rd",
    "sg:city":"Bankstown",
    "sg:classifiers":[
        {
            "category":"Personal",
            "subcategory":"Beauty Salon",
            "type":"Services"
        }
    ],
    "sg:phone":"+61 2 9708 4133",
    "sg:postcode":"2200",
    "sg:province":"NSW",
    "sg:tags":[
        "hairdresser"
    ],
    "wof:name":"Phuong Lyn Hair Design",
    "wof:placetype":"venue"
},
  "geometry": {"coordinates":[151.032471,-33.918598],"type":"Point"}
}