{
  "type": "Feature",
  "properties": {
    "iso:country":"AU",
    "sg:address":"57 Yurong St",
    "sg:city":"Darlinghurst",
    "sg:classifiers":[
        {
            "category":"Professional",
            "subcategory":"Art Services",
            "type":"Services"
        }
    ],
    "sg:phone":"+61 2 9357 3351",
    "sg:postcode":"2010",
    "sg:province":"NSW",
    "sg:tags":[
        "arranger",
        "music",
        "composer"
    ],
    "wof:name":"Purple",
    "wof:placetype":"venue"
},
  "geometry": {"coordinates":[151.21369934099999,-33.8768768311],"type":"Point"}
}