{
  "type": "Feature",
  "properties": {
    "iso:country":"AU",
    "sg:address":"PO Box 1567",
    "sg:city":"Wangara",
    "sg:classifiers":[
        {
            "category":"Utilities",
            "subcategory":"Telephone",
            "type":"Services"
        }
    ],
    "sg:phone":"+61 412 440 755",
    "sg:postcode":"6065",
    "sg:province":"WA",
    "sg:tags":[
        "installation",
        "system",
        "maintenance"
    ],
    "wof:name":"Wall 2 Wall Communications",
    "wof:placetype":"venue"
},
  "geometry": {"coordinates":[115.830238342,-31.7956504822],"type":"Point"}
}