{
  "type": "Feature",
  "properties": {
    "addr:full":"20 Lawrence St Inverell NSW 2360",
    "addr:housenumber":"20",
    "addr:postcode":"2360",
    "addr:street":"Lawrence St",
    "iso:country":"AU",
    "sg:address":"20 Lawrence St",
    "sg:city":"Inverell",
    "sg:classifiers":[
        {
            "category":"Food & Beverages",
            "subcategory":"Bakery",
            "type":"Retail Goods"
        }
    ],
    "sg:phone":"+61 2 6722 3665",
    "sg:postcode":"2360",
    "sg:province":"NSW",
    "sg:tags":[
        "baker"
    ],
    "wof:name":"MacIntyre Hot Bread Shop",
    "wof:placetype":"venue"
},
  "geometry": {"coordinates":[151.11416625999999,-29.7712917328],"type":"Point"}
}