{
  "type": "Feature",
  "properties": {
    "addr:full":"Gruner St Weston ACT 2611",
    "addr:postcode":"2611",
    "addr:street":"Gruner St",
    "iso:country":"AU",
    "sg:address":"Gruner St",
    "sg:city":"Weston",
    "sg:classifiers":[
        {
            "category":"Education",
            "subcategory":"Music School",
            "type":"Public Place"
        }
    ],
    "sg:phone":"+61 2 6288 3348",
    "sg:postcode":"2611",
    "sg:province":"ACT",
    "sg:tags":[
        "therapy",
        "relaxation"
    ],
    "wof:name":"Christine Hill-Trayner",
    "wof:placetype":"venue"
},
  "geometry": {"coordinates":[149.055084228,-35.3347854614],"type":"Point"}
}