{
  "type": "Feature",
  "properties": {
    "addr:full":"29 Meeks Rd Marrickville NSW 2204",
    "addr:housenumber":"29",
    "addr:postcode":"2204",
    "addr:street":"Meeks Rd",
    "iso:country":"AU",
    "sg:address":"29 Meeks Rd",
    "sg:city":"Marrickville",
    "sg:classifiers":[
        {
            "category":"Wholesale",
            "subcategory":"Construction Materials",
            "type":"Manufacturing & Wholesale Goods"
        }
    ],
    "sg:phone":"+61 2 9557 7755",
    "sg:postcode":"2204",
    "sg:province":"NSW",
    "sg:tags":[
        "lift"
    ],
    "wof:name":"Link Elevator Co Pty Ltd",
    "wof:placetype":"venue"
},
  "geometry": {"coordinates":[151.162216,-33.911407],"type":"Point"}
}