{
  "type": "Feature",
  "properties": {
    "addr:full":"23 Khalil Ave Dandenong North VIC 3175",
    "addr:housenumber":"23",
    "addr:postcode":"3175",
    "addr:street":"Khalil Ave",
    "iso:country":"AU",
    "sg:address":"23 Khalil Ave",
    "sg:city":"Dandenong North",
    "sg:classifiers":[
        {
            "category":"Retail",
            "subcategory":"Repair Shop",
            "type":"Services"
        }
    ],
    "sg:phone":"+61 3 9793 3095",
    "sg:postcode":"3175",
    "sg:province":"VIC",
    "sg:tags":[
        "machine",
        "repairs",
        "part",
        "dryer",
        "washing"
    ],
    "wof:name":"Chaddy Appliance Service",
    "wof:placetype":"venue"
},
  "geometry": {"coordinates":[145.226806641,-37.9702033997],"type":"Point"}
}