{
  "type": "Feature",
  "properties": {
    "addr:full":"128 Old Southern Rd Worrigee NSW 2540",
    "addr:housenumber":"128",
    "addr:postcode":"2540",
    "addr:street":"Old Southern Rd",
    "iso:country":"AU",
    "sg:address":"128 Old Southern Rd",
    "sg:city":"Worrigee",
    "sg:classifiers":[
        {
            "category":"Utilities",
            "subcategory":"Electric",
            "type":"Services"
        }
    ],
    "sg:phone":"+61 2 4423 1858",
    "sg:postcode":"2540",
    "sg:province":"NSW",
    "sg:tags":[
        "electrical",
        "contractor"
    ],
    "wof:name":"Watt I B Electrical",
    "wof:placetype":"venue"
},
  "geometry": {"coordinates":[150.61843872099999,-34.8996276855],"type":"Point"}
}