{
  "type": "Feature",
  "properties": {
    "iso:country":"AU",
    "sg:address":"Shop 1, 106 Sutton St",
    "sg:city":"Redcliffe",
    "sg:classifiers":[
        {
            "category":"Government",
            "subcategory":"Customs House",
            "type":"Public Place"
        }
    ],
    "sg:phone":"+61 7 3883 4638",
    "sg:postcode":"4020",
    "sg:province":"QLD",
    "sg:tags":[
        "title",
        "management",
        "stratum"
    ],
    "wof:name":"Redcliffe Body Corporate",
    "wof:placetype":"venue"
},
  "geometry": {"coordinates":[153.11451700000001,-27.228451],"type":"Point"}
}