{
  "type": "Feature",
  "properties": {
    "iso:country":"AU",
    "sg:address":"Lake Barrine Rd",
    "sg:city":"Malanda",
    "sg:classifiers":[
        {
            "category":"Professional",
            "subcategory":"Computer Services",
            "type":"Services"
        }
    ],
    "sg:phone":"+61 7 4096 5858",
    "sg:postcode":"4885",
    "sg:province":"QLD",
    "sg:tags":[
        "repairs",
        "upgrade",
        "equipment"
    ],
    "wof:name":"Pennells Technology Pty Ltd",
    "wof:placetype":"venue"
},
  "geometry": {"coordinates":[145.61723327600001,-17.3398456573],"type":"Point"}
}