{
  "type": "Feature",
  "properties": {
    "addr:full":"1 Hattersley St Arncliffe NSW 2205",
    "addr:housenumber":"1",
    "addr:postcode":"2205",
    "addr:street":"Hattersley St",
    "iso:country":"AU",
    "sg:address":"1 Hattersley St",
    "sg:city":"Arncliffe",
    "sg:classifiers":[
        {
            "category":"Wholesale",
            "subcategory":"Drugs",
            "type":"Manufacturing & Wholesale Goods"
        }
    ],
    "sg:phone":"+61 2 9567 4792",
    "sg:postcode":"2205",
    "sg:province":"NSW",
    "sg:tags":[
        "wholesaler",
        "pharmaceutical",
        "product",
        "mfrs"
    ],
    "wof:name":"Syncor Australia Pty Ltd",
    "wof:placetype":"venue"
},
  "geometry": {"coordinates":[151.14439400000001,-33.941624],"type":"Point"}
}