{
  "type": "Feature",
  "properties": {
    "addr:full":"58 Dunsford St Lancefield VIC 3435",
    "addr:housenumber":"58",
    "addr:postcode":"3435",
    "addr:street":"Dunsford St",
    "iso:country":"AU",
    "sg:address":"58 Dunsford St",
    "sg:city":"Lancefield",
    "sg:classifiers":[
        {
            "category":"Building & Trades",
            "subcategory":"Construction",
            "type":"Services"
        }
    ],
    "sg:phone":"+61 409 434 449",
    "sg:postcode":"3435",
    "sg:province":"VIC",
    "sg:tags":[
        "fencing",
        "contractor"
    ],
    "wof:name":"Danny Ryan Rural Fencing Pty Ltd",
    "wof:placetype":"venue"
},
  "geometry": {"coordinates":[144.72767639200001,-37.2768211365],"type":"Point"}
}