{
  "type": "Feature",
  "properties": {
    "addr:full":"10 Hotham St Moonee Ponds VIC 3039",
    "addr:housenumber":"10",
    "addr:postcode":"3039",
    "addr:street":"Hotham St",
    "iso:country":"AU",
    "sg:address":"10 Hotham St",
    "sg:city":"Moonee Ponds",
    "sg:classifiers":[
        {
            "category":"Building & Trades",
            "subcategory":"Construction",
            "type":"Services"
        }
    ],
    "sg:phone":"+61 3 9326 2743",
    "sg:postcode":"3039",
    "sg:province":"VIC",
    "sg:tags":[
        "plasterboard",
        "plasterer",
        "fixer"
    ],
    "wof:name":"City West Plastering",
    "wof:placetype":"venue"
},
  "geometry": {"coordinates":[144.912857,-37.770584],"type":"Point"}
}