{
  "type": "Feature",
  "properties": {
    "addr:full":"Shed 5/ 18b Goggs St Toowoomba QLD 4350",
    "addr:housenumber":"5 / 18b",
    "addr:postcode":"4350",
    "addr:street":"Goggs St",
    "iso:country":"AU",
    "sg:address":"Shed 5/ 18b Goggs St",
    "sg:city":"Toowoomba",
    "sg:classifiers":[
        {
            "category":"Building & Trades",
            "subcategory":"Construction",
            "type":"Services"
        }
    ],
    "sg:phone":"+61 7 4638 8252",
    "sg:postcode":"4350",
    "sg:province":"QLD",
    "sg:tags":[
        "welding"
    ],
    "wof:name":"Full Fab",
    "wof:placetype":"venue"
},
  "geometry": {"coordinates":[151.94528199999999,-27.566341],"type":"Point"}
}