{
  "type": "Feature",
  "properties": {
    "addr:full":"89 Good St Granville NSW 2142",
    "addr:housenumber":"89",
    "addr:postcode":"2142",
    "addr:street":"Good St",
    "iso:country":"AU",
    "sg:address":"89 Good St",
    "sg:city":"Granville",
    "sg:classifiers":[
        {
            "category":"Social Services",
            "subcategory":"Child Care",
            "type":"Services"
        }
    ],
    "sg:phone":"+61 2 9682 5200",
    "sg:postcode":"2142",
    "sg:province":"NSW",
    "wof:name":"Peters Playland Childcare Centre",
    "wof:placetype":"venue"
},
  "geometry": {"coordinates":[151.01272582999999,-33.8287200928],"type":"Point"}
}