{
  "type": "Feature",
  "properties": {
    "addr:full":"81 Violet St Revesby NSW 2212",
    "addr:housenumber":"81",
    "addr:postcode":"2212",
    "addr:street":"Violet St",
    "iso:country":"AU",
    "sg:address":"81 Violet St",
    "sg:city":"Revesby",
    "sg:classifiers":[
        {
            "category":"Fast Food",
            "type":"Food & Drink"
        }
    ],
    "sg:phone":"+61 2 9792 4160",
    "sg:postcode":"2212",
    "sg:province":"NSW",
    "sg:tags":[
        "away",
        "take"
    ],
    "wof:name":"Revesby Cantina",
    "wof:placetype":"venue"
},
  "geometry": {"coordinates":[151.005447,-33.93956],"type":"Point"}
}