{
  "type": "Feature",
  "properties": {
    "addr:full":"485 Ruthven St Toowoomba QLD 4350",
    "addr:housenumber":"485",
    "addr:postcode":"4350",
    "addr:street":"Ruthven St",
    "iso:country":"AU",
    "sg:address":"485 Ruthven St",
    "sg:city":"Toowoomba",
    "sg:classifiers":[
        {
            "category":"Shopping",
            "subcategory":"Jewelry",
            "type":"Retail Goods"
        }
    ],
    "sg:phone":"+61 7 4632 1055",
    "sg:postcode":"4350",
    "sg:province":"QLD",
    "sg:tags":[
        "jeweller"
    ],
    "wof:name":"Harneys Jewellery & Gifts",
    "wof:placetype":"venue"
},
  "geometry": {"coordinates":[151.95230100000001,-27.568167],"type":"Point"}
}