{
  "type": "Feature",
  "properties": {
    "iso:country":"AU",
    "sg:address":"126 Alexander Ave",
    "sg:city":"Thomastown",
    "sg:classifiers":[
        {
            "category":"Food & Beverages",
            "subcategory":"Liquor & Beverages",
            "type":"Retail Goods"
        }
    ],
    "sg:phone":"+61 3 9465 3109",
    "sg:postcode":"3074",
    "sg:province":"VIC",
    "sg:tags":[
        "store"
    ],
    "wof:name":"Thomastown Licensed Supermarket",
    "wof:placetype":"venue"
},
  "geometry": {"coordinates":[145.02528381400001,-37.6813621521],"type":"Point"}
}