{
  "type": "Feature",
  "properties": {
    "addr:full":"Woodlands Shopping Centre Rosewood Ave Woodlands WA 6018",
    "addr:postcode":"6018",
    "addr:street":"Rosewood Ave",
    "iso:country":"AU",
    "sg:address":"Woodlands Shopping Centre Rosewood Ave",
    "sg:city":"Woodlands",
    "sg:classifiers":[
        {
            "category":"Personal",
            "subcategory":"Beauty Salon",
            "type":"Services"
        }
    ],
    "sg:phone":"+61 8 9244 3998",
    "sg:postcode":"6018",
    "sg:province":"WA",
    "wof:name":"Skin + Beauty @ Woodlands",
    "wof:placetype":"venue"
},
  "geometry": {"coordinates":[115.789100647,-31.908613205],"type":"Point"}
}