{
  "type": "Feature",
  "properties": {
    "addr:full":"2385 Point Nepean Rd Rye VIC 3941",
    "addr:housenumber":"2385",
    "addr:postcode":"3941",
    "addr:street":"Point Nepean Rd",
    "iso:country":"AU",
    "sg:address":"2385 Point Nepean Rd",
    "sg:city":"Rye",
    "sg:classifiers":[
        {
            "category":"Education",
            "subcategory":"Vocational School",
            "type":"Public Place"
        }
    ],
    "sg:phone":"+61 1800 466 750",
    "sg:postcode":"3941",
    "sg:province":"VIC",
    "sg:tags":[
        "boating"
    ],
    "wof:name":"Aquatic Adventures",
    "wof:placetype":"venue"
},
  "geometry": {"coordinates":[144.82231140100001,-38.3703804016],"type":"Point"}
}