{
  "type": "Feature",
  "properties": {
    "addr:full":"10 Cobley Ave Tamworth NSW 2340",
    "addr:housenumber":"10",
    "addr:postcode":"2340",
    "addr:street":"Cobley Ave",
    "iso:country":"AU",
    "sg:address":"10 Cobley Ave",
    "sg:city":"Tamworth",
    "sg:classifiers":[
        {
            "category":"Building & Trades",
            "subcategory":"Construction",
            "type":"Services"
        }
    ],
    "sg:phone":"+61 419 800 265",
    "sg:postcode":"2340",
    "sg:province":"NSW",
    "sg:tags":[
        "earth",
        "excavating",
        "moving",
        "contractor"
    ],
    "wof:name":"Auscoast Dingos",
    "wof:placetype":"venue"
},
  "geometry": {"coordinates":[150.92210388199999,-31.1149234772],"type":"Point"}
}