{
  "type": "Feature",
  "properties": {
    "addr:full":"21 Daking St North Parramatta NSW 2151",
    "addr:housenumber":"21",
    "addr:postcode":"2151",
    "addr:street":"Daking St",
    "iso:country":"AU",
    "sg:address":"21 Daking St",
    "sg:city":"North Parramatta",
    "sg:classifiers":[
        {
            "category":"Autos & Motor Vehicles",
            "subcategory":"Auto Supplies",
            "type":"Retail Goods"
        }
    ],
    "sg:phone":"+61 2 9630 3838",
    "sg:postcode":"2151",
    "sg:province":"NSW",
    "sg:tags":[
        "automotive",
        "stereo",
        "radio"
    ],
    "wof:name":"Aus Audio Warehouse",
    "wof:placetype":"venue"
},
  "geometry": {"coordinates":[151.00120544399999,-33.79429245],"type":"Point"}
}