{
  "type": "Feature",
  "properties": {
    "iso:country":"AU",
    "sg:address":"397 Townsend St",
    "sg:city":"South Albury",
    "sg:classifiers":[
        {
            "category":"Fast Food",
            "type":"Food & Drink"
        }
    ],
    "sg:phone":"+61 2 6021 3105",
    "sg:postcode":"2640",
    "sg:province":"NSW",
    "sg:tags":[
        "away",
        "take"
    ],
    "wof:name":"Lunch Box Albury",
    "wof:placetype":"venue"
},
  "geometry": {"coordinates":[146.91180419899999,-36.0864639282],"type":"Point"}
}