{
  "type": "Feature",
  "properties": {
    "iso:country":"AU",
    "sg:address":"SEH 39 Wallace St",
    "sg:city":"Beaconsfield",
    "sg:classifiers":[
        {
            "category":"Government",
            "subcategory":"Court House",
            "type":"Public Place"
        }
    ],
    "sg:phone":"+61 3 9768 9797",
    "sg:postcode":"3807",
    "sg:province":"VIC",
    "sg:tags":[
        "personal",
        "marriage",
        "family",
        "counselling"
    ],
    "wof:name":"Kerry McKennie Counselling Services",
    "wof:placetype":"venue"
},
  "geometry": {"coordinates":[145.36856079099999,-38.0457458496],"type":"Point"}
}