{
  "type": "Feature",
  "properties": {
    "addr:full":"11 Duff St Cranbourne VIC 3977",
    "addr:housenumber":"11",
    "addr:postcode":"3977",
    "addr:street":"Duff St",
    "iso:country":"AU",
    "sg:address":"11 Duff St",
    "sg:city":"Cranbourne",
    "sg:classifiers":[
        {
            "category":"Retail",
            "subcategory":"Repair Shop",
            "type":"Services"
        }
    ],
    "sg:phone":"+61 3 5995 3237",
    "sg:postcode":"3977",
    "sg:province":"VIC",
    "sg:tags":[
        "mending",
        "clothing",
        "alteration"
    ],
    "wof:name":"The Real Me",
    "wof:placetype":"venue"
},
  "geometry": {"coordinates":[145.280685425,-38.1013526917],"type":"Point"}
}