{
  "type": "Feature",
  "properties": {
    "addr:full":"Shop 8 Salisbury Arcade, 49 John St Salisbury SA 5108",
    "addr:housenumber":"shop 8;49",
    "addr:postcode":"5108",
    "addr:street":"Salisbury Arcade;John St",
    "iso:country":"AU",
    "sg:address":"Shop 8 Salisbury Arcade, 49 John St",
    "sg:city":"Salisbury",
    "sg:classifiers":[
        {
            "category":"Shopping",
            "subcategory":"Pets & Pet Supplies",
            "type":"Retail Goods"
        }
    ],
    "sg:phone":"+61 8 8250 5680",
    "sg:postcode":"5108",
    "sg:province":"SA",
    "sg:tags":[
        "shop",
        "supplier"
    ],
    "wof:name":"Aquaruims &#039;N More",
    "wof:placetype":"venue"
},
  "geometry": {"coordinates":[138.64503479000001,-34.7625846863],"type":"Point"}
}