{
  "type": "Feature",
  "properties": {
    "addr:full":"165 Dorset Rd Croydon VIC 3136",
    "addr:housenumber":"165",
    "addr:postcode":"3136",
    "addr:street":"Dorset Rd",
    "iso:country":"AU",
    "sg:address":"165 Dorset Rd",
    "sg:city":"Croydon",
    "sg:classifiers":[
        {
            "category":"Building & Trades",
            "subcategory":"Construction",
            "type":"Services"
        }
    ],
    "sg:phone":"+61 3 9723 3538",
    "sg:postcode":"3136",
    "sg:province":"VIC",
    "sg:tags":[
        "earth",
        "excavating",
        "moving",
        "contractor"
    ],
    "wof:name":"Dig Deep Backhoe Hire",
    "wof:placetype":"venue"
},
  "geometry": {"coordinates":[145.29284668,-37.7850914001],"type":"Point"}
}