{
  "type": "Feature",
  "properties": {
    "addr:full":"55 Macalister St Park Avenue QLD 4701",
    "addr:housenumber":"55",
    "addr:postcode":"4701",
    "addr:street":"Macalister St Park Avenue",
    "iso:country":"AU",
    "sg:address":"55 Macalister St",
    "sg:city":"Park Avenue",
    "sg:classifiers":[
        {
            "category":"Fast Food",
            "type":"Food & Drink"
        }
    ],
    "sg:phone":"+61 7 4922 1308",
    "sg:postcode":"4701",
    "sg:province":"QLD",
    "sg:tags":[
        "away",
        "take"
    ],
    "wof:name":"Little Aussie Take Away",
    "wof:placetype":"venue"
},
  "geometry": {"coordinates":[150.504760742,-23.3564720154],"type":"Point"}
}