{
  "type": "Feature",
  "properties": {
    "addr:full":"Apartment 2, 14 Irving Ave Prahran VIC 3181",
    "addr:housenumber":"14",
    "addr:postcode":"3181",
    "addr:street":"Irving Ave",
    "iso:country":"AU",
    "sg:address":"Apartment 2, 14 Irving Ave",
    "sg:city":"Prahran",
    "sg:classifiers":[
        {
            "category":"Professional",
            "subcategory":"Printing & Photocopies",
            "type":"Services"
        }
    ],
    "sg:phone":"+61 3 9529 2093",
    "sg:postcode":"3181",
    "sg:province":"VIC",
    "sg:tags":[
        "publishing",
        "desktop"
    ],
    "wof:name":"Lucas 21st Century Film Pty Ltd",
    "wof:placetype":"venue"
},
  "geometry": {"coordinates":[145.00717163100001,-37.8586654663],"type":"Point"}
}