{
  "type": "Feature",
  "properties": {
    "iso:country":"AU",
    "sg:address":"45 Paisley St",
    "sg:city":"Footscray",
    "sg:classifiers":[
        {
            "category":"Food & Beverages",
            "subcategory":"Bakery",
            "type":"Retail Goods"
        }
    ],
    "sg:phone":"+61 3 9689 8635",
    "sg:postcode":"3011",
    "sg:province":"VIC",
    "sg:tags":[
        "baker"
    ],
    "wof:name":"Breadhouse Cafe",
    "wof:placetype":"venue"
},
  "geometry": {"coordinates":[144.898803711,-37.8009338379],"type":"Point"}
}