{
  "type": "Feature",
  "properties": {
    "addr:full":"Brook St Towong NSW 3707",
    "addr:postcode":"3707",
    "addr:street":"Brook St",
    "iso:country":"AU",
    "sg:address":"Brook St",
    "sg:city":"Towong",
    "sg:classifiers":[
        {
            "category":"Building & Trades",
            "subcategory":"Landscaping Services",
            "type":"Services"
        }
    ],
    "sg:phone":"+61 2 6076 8232",
    "sg:postcode":"3707",
    "sg:province":"NSW",
    "sg:tags":[
        "control",
        "weed"
    ],
    "wof:name":"Kevs Farm Service",
    "wof:placetype":"venue"
},
  "geometry": {"coordinates":[147.995269775,-36.1236457825],"type":"Point"}
}