{
  "type": "Feature",
  "properties": {
    "addr:full":"2 Chaston St Wagga Wagga NSW 2650",
    "addr:housenumber":"2",
    "addr:postcode":"2650",
    "addr:street":"Chaston St",
    "iso:country":"AU",
    "sg:address":"2 Chaston St",
    "sg:city":"Wagga Wagga",
    "sg:classifiers":[
        {
            "category":"Home & Garden",
            "subcategory":"Hardware",
            "type":"Retail Goods"
        }
    ],
    "sg:phone":"+61 2 6925 1800",
    "sg:postcode":"2650",
    "sg:province":"NSW",
    "sg:tags":[
        "plumber",
        "supply"
    ],
    "wof:name":"Tradelink Plumbing Centres",
    "wof:placetype":"venue"
},
  "geometry": {"coordinates":[147.355072022,-35.1218719482],"type":"Point"}
}