{
  "type": "Feature",
  "properties": {
    "addr:full":"Shp 2/ 142 Macquarie St Liverpool NSW 2170",
    "addr:housenumber":"/ 142",
    "addr:postcode":"2170",
    "addr:street":"Macquarie St",
    "iso:country":"AU",
    "sg:address":"Shp 2/ 142 Macquarie St",
    "sg:city":"Liverpool",
    "sg:classifiers":[
        {
            "category":"Retail",
            "subcategory":"Repair Shop",
            "type":"Services"
        }
    ],
    "sg:phone":"+61 2 9824 0092",
    "sg:postcode":"2170",
    "sg:province":"NSW",
    "sg:tags":[
        "handbag"
    ],
    "wof:name":"Jewellery & Leathergoods",
    "wof:placetype":"venue"
},
  "geometry": {"coordinates":[150.924224853,-33.9206085205],"type":"Point"}
}