{
  "type": "Feature",
  "properties": {
    "iso:country":"AU",
    "sg:address":"60 Irvine Drv",
    "sg:city":"Malaga",
    "sg:classifiers":[
        {
            "category":"Professional",
            "subcategory":"Engineering",
            "type":"Services"
        }
    ],
    "sg:phone":"+61 8 9209 3244",
    "sg:postcode":"6090",
    "sg:province":"WA",
    "sg:tags":[
        "engineer"
    ],
    "wof:name":"Symplistic Engineering Pty Ltd",
    "wof:placetype":"venue"
},
  "geometry": {"coordinates":[115.885391235,-31.8560237885],"type":"Point"}
}