{
  "type": "Feature",
  "properties": {
    "addr:full":"633 Lores Bonney Drv Archerfield QLD 4108",
    "addr:housenumber":"633",
    "addr:postcode":"4108",
    "addr:street":"Lores Bonney Drv",
    "iso:country":"AU",
    "sg:address":"633 Lores Bonney Drv",
    "sg:city":"Archerfield",
    "sg:classifiers":[
        {
            "category":"Retail",
            "subcategory":"Auto Repair",
            "type":"Services"
        }
    ],
    "sg:phone":"+61 7 3274 5333",
    "sg:postcode":"4108",
    "sg:province":"QLD",
    "sg:tags":[
        "repairer",
        "motor",
        "engineer"
    ],
    "wof:name":"KTC Automotive",
    "wof:placetype":"venue"
},
  "geometry": {"coordinates":[153.01057434099999,-27.5772800446],"type":"Point"}
}