{
  "type": "Feature",
  "properties": {
    "addr:full":"18 Carbeen St Kununurra WA 6743",
    "addr:housenumber":"18",
    "addr:postcode":"6743",
    "addr:street":"Carbeen St",
    "iso:country":"AU",
    "sg:address":"18 Carbeen St",
    "sg:city":"Kununurra",
    "sg:classifiers":[
        {
            "category":"Taxi",
            "type":"Transportation"
        }
    ],
    "sg:phone":"+61 8 9168 2553",
    "sg:postcode":"6743",
    "sg:province":"WA",
    "sg:tags":[
        "cab"
    ],
    "wof:name":"Spud's Taxis",
    "wof:placetype":"venue"
},
  "geometry": {"coordinates":[128.746490478,-15.7769651413],"type":"Point"}
}