{
  "type": "Feature",
  "properties": {
    "addr:full":"26 Lincoln St Laverton North VIC 3026",
    "addr:housenumber":"26",
    "addr:postcode":"3026",
    "addr:street":"Lincoln St",
    "iso:country":"AU",
    "sg:address":"26 Lincoln St",
    "sg:city":"Laverton North",
    "sg:classifiers":[
        {
            "category":"Personal",
            "subcategory":"Skin Care",
            "type":"Services"
        }
    ],
    "sg:phone":"+61 3 9369 4755",
    "sg:postcode":"3026",
    "sg:province":"VIC",
    "sg:tags":[
        "merchant",
        "hide"
    ],
    "wof:name":"Knox International Trading Company",
    "wof:placetype":"venue"
},
  "geometry": {"coordinates":[144.81516999999999,-37.822113],"type":"Point"}
}