{
  "type": "Feature",
  "properties": {
    "addr:full":"35 Ronald St Padstow NSW 2211",
    "addr:housenumber":"35",
    "addr:postcode":"2211",
    "addr:street":"Ronald St",
    "iso:country":"AU",
    "sg:address":"35 Ronald St",
    "sg:city":"Padstow",
    "sg:classifiers":[
        {
            "category":"Building & Trades",
            "subcategory":"Landscaping Services",
            "type":"Services"
        }
    ],
    "sg:phone":"+61 410 458 555",
    "sg:postcode":"2211",
    "sg:province":"NSW",
    "sg:tags":[
        "designer",
        "landscape",
        "contractor"
    ],
    "wof:name":"T W Churchill & Son Landscapes",
    "wof:placetype":"venue"
},
  "geometry": {"coordinates":[151.02641299999999,-33.944363],"type":"Point"}
}