{
  "type": "Feature",
  "properties": {
    "iso:country":"AU",
    "sg:address":"5 Mount Vue Rd",
    "sg:city":"Healesville",
    "sg:classifiers":[
        {
            "category":"Real Estate",
            "subcategory":"Real Estate Agent",
            "type":"Services"
        }
    ],
    "sg:phone":"+61 3 5962 4695",
    "sg:postcode":"3777",
    "sg:province":"VIC",
    "wof:name":"Kennedy Athol J",
    "wof:placetype":"venue"
},
  "geometry": {"coordinates":[145.48999,-37.652489],"type":"Point"}
}