{
  "type": "Feature",
  "properties": {
    "iso:country":"AU",
    "sg:address":"186 Macquarie St",
    "sg:city":"Liverpool",
    "sg:classifiers":[
        {
            "category":"Shopping",
            "subcategory":"Clothing, Apparel, & Fashions",
            "type":"Retail Goods"
        }
    ],
    "sg:phone":"+61 2 9824 0365",
    "sg:postcode":"2170",
    "sg:province":"NSW",
    "sg:tags":[
        "lady",
        "wear"
    ],
    "wof:name":"Esprit De Corp Pty Ltd",
    "wof:placetype":"venue"
},
  "geometry": {"coordinates":[150.92401123100001,-33.9218597412],"type":"Point"}
}