{
  "type": "Feature",
  "properties": {
    "addr:full":"6 Sondralena Drv Parkhurst QLD 4702",
    "addr:housenumber":"6",
    "addr:postcode":"4702",
    "addr:street":"Sondralena Drv",
    "iso:country":"AU",
    "sg:address":"6 Sondralena Drv",
    "sg:city":"Parkhurst",
    "sg:classifiers":[
        {
            "category":"Professional",
            "subcategory":"Employment Agencies",
            "type":"Services"
        }
    ],
    "sg:phone":"+61 7 4936 2731",
    "sg:postcode":"4702",
    "sg:province":"QLD",
    "sg:tags":[
        "provider",
        "internet"
    ],
    "wof:name":"9th Planet X Web Design",
    "wof:placetype":"venue"
},
  "geometry": {"coordinates":[150.514434814,-23.304889679],"type":"Point"}
}