{
  "type": "Feature",
  "properties": {
    "iso:country":"AU",
    "sg:address":"C/- Myer, 49 - 51 Albert Ave",
    "sg:city":"Chatswood",
    "sg:classifiers":[
        {
            "category":"Shopping",
            "subcategory":"Clothing, Apparel, & Fashions",
            "type":"Retail Goods"
        }
    ],
    "sg:phone":"+61 2 9412 0525",
    "sg:postcode":"2067",
    "sg:province":"NSW",
    "sg:tags":[
        "hire",
        "men's",
        "wear",
        "formal"
    ],
    "wof:name":"Lords Formalwear",
    "wof:placetype":"venue"
},
  "geometry": {"coordinates":[151.18357849099999,-33.7977371216],"type":"Point"}
}