{
  "type": "Feature",
  "properties": {
    "addr:full":"Bulgun Rd Tully QLD 4854",
    "addr:postcode":"4854",
    "addr:street":"Bulgun Rd",
    "iso:country":"AU",
    "sg:address":"Bulgun Rd",
    "sg:city":"Tully",
    "sg:classifiers":[
        {
            "category":"Farming",
            "subcategory":"Farm",
            "type":"Manufacturing & Wholesale Goods"
        }
    ],
    "sg:phone":"+61 7 4068 1041",
    "sg:postcode":"4854",
    "sg:province":"QLD",
    "sg:tags":[
        "farmer"
    ],
    "wof:name":"Madden T P",
    "wof:placetype":"venue"
},
  "geometry": {"coordinates":[145.93258667000001,-17.9088859558],"type":"Point"}
}