{
  "type": "Feature",
  "properties": {
    "addr:full":"38 Ross Ave Sorrento WA 6020",
    "addr:housenumber":"38",
    "addr:postcode":"6020",
    "addr:street":"Ross Ave",
    "iso:country":"AU",
    "sg:address":"38 Ross Ave",
    "sg:city":"Sorrento",
    "sg:classifiers":[
        {
            "category":"Utilities",
            "subcategory":"Refuse",
            "type":"Services"
        }
    ],
    "sg:phone":"+61 8 9246 1620",
    "sg:postcode":"6020",
    "sg:province":"WA",
    "sg:tags":[
        "remover",
        "rubbish"
    ],
    "wof:name":"Duncraig Garden Bags",
    "wof:placetype":"venue"
},
  "geometry": {"coordinates":[115.753509522,-31.8345756531],"type":"Point"}
}