{
  "type": "Feature",
  "properties": {
    "iso:country":"AU",
    "sg:address":"1082 Lower North East Rd",
    "sg:city":"Highbury",
    "sg:classifiers":[
        {
            "category":"Shopping",
            "subcategory":"Antiques",
            "type":"Retail Goods"
        }
    ],
    "sg:phone":"+61 8 8263 7779",
    "sg:postcode":"5089",
    "sg:province":"SA",
    "wof:name":"Cash For Collectables",
    "wof:placetype":"venue"
},
  "geometry": {"coordinates":[138.70735168499999,-34.8527755737],"type":"Point"}
}