{
  "type": "Feature",
  "properties": {
    "addr:full":"Shop 1 / 2 East Circular Qy Sydney NSW 2000",
    "addr:housenumber":"shop 1 / 2",
    "addr:postcode":"2000",
    "addr:street":"East Circular Qy",
    "iso:country":"AU",
    "sg:address":"Shop 1 / 2 East Circular Qy",
    "sg:city":"Sydney",
    "sg:classifiers":[
        {
            "category":"Restaurant",
            "type":"Food & Drink"
        }
    ],
    "sg:phone":"+61 2 9251 0122",
    "sg:postcode":"2000",
    "sg:province":"NSW",
    "sg:website":"http://www.quaysidecafe.com.au",
    "wof:name":"Quayside Brasserie",
    "wof:placetype":"venue"
},
  "geometry": {"coordinates":[151.210006714,-33.8695793152],"type":"Point"}
}