{
  "type": "Feature",
  "properties": {
    "addr:full":"9 Undurra Drv Glenfield Park NSW 2650",
    "addr:housenumber":"9",
    "addr:postcode":"2650",
    "addr:street":"Undurra Drv",
    "iso:country":"AU",
    "sg:address":"9 Undurra Drv",
    "sg:city":"Glenfield Park",
    "sg:classifiers":[
        {
            "category":"Building & Trades",
            "subcategory":"Construction",
            "type":"Services"
        }
    ],
    "sg:phone":"+61 2 6971 3917",
    "sg:postcode":"2650",
    "sg:province":"NSW",
    "sg:tags":[
        "joiner",
        "carpenter"
    ],
    "wof:name":"Parnwell John",
    "wof:placetype":"venue"
},
  "geometry": {"coordinates":[147.337722778,-35.1400413513],"type":"Point"}
}