{
  "type": "Feature",
  "properties": {
    "iso:country":"AU",
    "sg:address":"77 Magnus St",
    "sg:city":"Nelson Bay",
    "sg:classifiers":[
        {
            "category":"Shopping",
            "subcategory":"Clothing, Apparel, & Fashions",
            "type":"Retail Goods"
        }
    ],
    "sg:phone":"+61 2 4981 4388",
    "sg:postcode":"2315",
    "sg:province":"NSW",
    "sg:tags":[
        "jean"
    ],
    "wof:name":"Jean Shop The",
    "wof:placetype":"venue"
},
  "geometry": {"coordinates":[152.144485,-32.721481],"type":"Point"}
}