{
  "type": "Feature",
  "properties": {
    "addr:full":"Suite 11, 31- 33 Price St Nerang QLD 4211",
    "addr:housenumber":"31 33",
    "addr:postcode":"4211",
    "addr:street":"Price St",
    "iso:country":"AU",
    "sg:address":"Suite 11, 31- 33 Price St",
    "sg:city":"Nerang",
    "sg:classifiers":[
        {
            "category":"Professional",
            "subcategory":"Accounting & Tax Preparation",
            "type":"Services"
        }
    ],
    "sg:phone":"+61 7 5500 4177",
    "sg:postcode":"4211",
    "sg:province":"QLD",
    "sg:tags":[
        "consultant",
        "taxation"
    ],
    "wof:name":"Hetheringtons Business Accountants",
    "wof:placetype":"venue"
},
  "geometry": {"coordinates":[153.33596801799999,-27.9898719788],"type":"Point"}
}