{
  "type": "Feature",
  "properties": {
    "addr:full":"Shop 20, Beenleigh Market, George St Beenleigh QLD 4207",
    "addr:housenumber":"shop 20",
    "addr:postcode":"4207",
    "addr:street":"Beenleigh Market George St",
    "iso:country":"AU",
    "sg:address":"Shop 20, Beenleigh Market, George St",
    "sg:city":"Beenleigh",
    "sg:classifiers":[
        {
            "category":"Food & Beverages",
            "subcategory":"Liquor & Beverages",
            "type":"Retail Goods"
        }
    ],
    "sg:phone":"+61 7 3287 4875",
    "sg:postcode":"4207",
    "sg:province":"QLD",
    "sg:tags":[
        "store"
    ],
    "wof:name":"Beenleigh Market Place",
    "wof:placetype":"venue"
},
  "geometry": {"coordinates":[153.19346618599999,-27.7148361206],"type":"Point"}
}