{
  "type": "Feature",
  "properties": {
    "iso:country":"AU",
    "sg:address":"97 Camberwell Rd",
    "sg:city":"Hawthorn East",
    "sg:classifiers":[
        {
            "category":"Professional",
            "subcategory":"Engineering",
            "type":"Services"
        }
    ],
    "sg:phone":"+61 3 9813 3122",
    "sg:postcode":"3123",
    "sg:province":"VIC",
    "sg:tags":[
        "consulting",
        "engineer"
    ],
    "wof:name":"Adams Consulting Engineers Pty Ltd",
    "wof:placetype":"venue"
},
  "geometry": {"coordinates":[145.052536011,-37.827507019],"type":"Point"}
}