{
  "type": "Feature",
  "properties": {
    "iso:country":"AU",
    "sg:address":"320 Rossiter Rd",
    "sg:city":"Koo Wee Rup",
    "sg:classifiers":[
        {
            "category":"Health Services",
            "subcategory":"Dentist",
            "type":"Services"
        }
    ],
    "sg:phone":"+61 3 5997 1280",
    "sg:postcode":"3981",
    "sg:province":"VIC",
    "wof:name":"Koo Wee Rup Dental Surgery",
    "wof:placetype":"venue"
},
  "geometry": {"coordinates":[145.49237060600001,-38.1988372803],"type":"Point"}
}