{
  "type": "Feature",
  "properties": {
    "addr:full":"335 Wattle Tree Rd Holgate NSW 2250",
    "addr:housenumber":"335",
    "addr:postcode":"2250",
    "addr:street":"Wattle Tree Rd",
    "iso:country":"AU",
    "sg:address":"335 Wattle Tree Rd",
    "sg:city":"Holgate",
    "sg:classifiers":[
        {
            "category":"Home & Garden",
            "subcategory":"Household Appliances",
            "type":"Retail Goods"
        }
    ],
    "sg:phone":"+61 2 4367 3371",
    "sg:postcode":"2250",
    "sg:province":"NSW",
    "sg:tags":[
        "heating",
        "system"
    ],
    "wof:name":"Yarra Fires - Central Coast",
    "wof:placetype":"venue"
},
  "geometry": {"coordinates":[151.40855407699999,-33.4009437561],"type":"Point"}
}