{
  "type": "Feature",
  "properties": {
    "addr:full":"35 Lake Haven Drv Sussex Inlet NSW 2540",
    "addr:housenumber":"35",
    "addr:postcode":"2540",
    "addr:street":"Lake Haven Drv",
    "iso:country":"AU",
    "sg:address":"35 Lake Haven Drv",
    "sg:city":"Sussex Inlet",
    "sg:classifiers":[
        {
            "category":"Utilities",
            "subcategory":"Recycling",
            "type":"Services"
        }
    ],
    "sg:phone":"+61 2 4441 1924",
    "sg:postcode":"2540",
    "sg:province":"NSW",
    "wof:name":"Bay City Recyclers",
    "wof:placetype":"venue"
},
  "geometry": {"coordinates":[150.585494995,-35.1703796387],"type":"Point"}
}