{
  "type": "Feature",
  "properties": {
    "addr:full":"96 Mort St Toowoomba QLD 4350",
    "addr:housenumber":"96",
    "addr:postcode":"4350",
    "addr:street":"Mort St",
    "iso:country":"AU",
    "sg:address":"96 Mort St",
    "sg:city":"Toowoomba",
    "sg:classifiers":[
        {
            "category":"Autos & Motor Vehicles",
            "subcategory":"Auto Supplies",
            "type":"Retail Goods"
        }
    ],
    "sg:phone":"+61 7 4639 4888",
    "sg:postcode":"4350",
    "sg:province":"QLD",
    "sg:tags":[
        "battery",
        "automotive"
    ],
    "wof:name":"Alco Battery Sales (Aust) Pty Ltd",
    "wof:placetype":"venue"
},
  "geometry": {"coordinates":[151.95045500000001,-27.551313],"type":"Point"}
}