{
  "type": "Feature",
  "properties": {
    "iso:country":"AU",
    "sg:address":"47 Grafton St",
    "sg:city":"Coffs Harbour",
    "sg:classifiers":[
        {
            "category":"Professional",
            "type":"Services"
        }
    ],
    "sg:phone":"+61 2 6651 1849",
    "sg:postcode":"2450",
    "sg:province":"NSW",
    "sg:tags":[
        "valuer"
    ],
    "wof:name":"North Coast Valuation Service Pty Ltd",
    "wof:placetype":"venue"
},
  "geometry": {"coordinates":[153.112915,-30.297565],"type":"Point"}
}