{
  "type": "Feature",
  "properties": {
    "addr:full":"Hawthorne, Brisbane 4171 Hawthorne QLD 4171",
    "addr:postcode":"4171;4171",
    "iso:country":"AU",
    "sg:address":"Hawthorne, Brisbane 4171",
    "sg:city":"Hawthorne",
    "sg:classifiers":[
        {
            "category":"Organizations",
            "subcategory":"Professional Association",
            "type":"Services"
        }
    ],
    "sg:phone":"+61 415 412 934",
    "sg:postcode":"4171",
    "sg:province":"QLD",
    "sg:tags":[
        "web",
        "internet"
    ],
    "wof:name":"Ocean Breeze Web Design",
    "wof:placetype":"venue"
},
  "geometry": {"coordinates":[153.05963134800001,-27.4660491943],"type":"Point"}
}