{
  "type": "Feature",
  "properties": {
    "addr:full":"16 Brady Pl Somerset TAS 7322",
    "addr:housenumber":"16",
    "addr:postcode":"7322",
    "addr:street":"Brady Pl",
    "iso:country":"AU",
    "sg:address":"16 Brady Pl",
    "sg:city":"Somerset",
    "sg:classifiers":[
        {
            "category":"Building & Trades",
            "subcategory":"Pest Control",
            "type":"Services"
        }
    ],
    "sg:phone":"+61 3 6435 0446",
    "sg:postcode":"7322",
    "sg:province":"TAS",
    "sg:tags":[
        "breastfeeding",
        "support"
    ],
    "wof:name":"Australian Breastfeeding Association",
    "wof:placetype":"venue"
},
  "geometry": {"coordinates":[145.82782,-41.046581],"type":"Point"}
}