{
  "type": "Feature",
  "properties": {
    "addr:full":"5/ 2320 Silverdale Rd Silverdale NSW 2752",
    "addr:housenumber":"/ 2320",
    "addr:postcode":"2752",
    "addr:street":"Silverdale Rd",
    "iso:country":"AU",
    "sg:address":"5/ 2320 Silverdale Rd",
    "sg:city":"Silverdale",
    "sg:classifiers":[
        {
            "category":"Health Services",
            "subcategory":"Doctor",
            "type":"Services"
        }
    ],
    "sg:phone":"+61 2 4774 0008",
    "sg:postcode":"2752",
    "sg:province":"NSW",
    "sg:tags":[
        "medical",
        "practitioner"
    ],
    "wof:name":"Silverdale Medical Centre",
    "wof:placetype":"venue"
},
  "geometry": {"coordinates":[150.618682861,-33.8903121948],"type":"Point"}
}