{
  "type": "Feature",
  "properties": {
    "addr:full":"15 Roseby Crt Caboolture QLD 4510",
    "addr:housenumber":"15",
    "addr:postcode":"4510",
    "addr:street":"Roseby Crt",
    "iso:country":"AU",
    "sg:address":"15 Roseby Crt",
    "sg:city":"Caboolture",
    "sg:classifiers":[
        {
            "category":"Shopping",
            "type":"Retail Goods"
        }
    ],
    "sg:phone":"+61 7 5499 1111",
    "sg:postcode":"4510",
    "sg:province":"QLD",
    "sg:tags":[
        "product",
        "plastic"
    ],
    "wof:name":"Price Plastics Pty Ltd",
    "wof:placetype":"venue"
},
  "geometry": {"coordinates":[152.98127700000001,-27.088678],"type":"Point"}
}