{
  "type": "Feature",
  "properties": {
    "addr:full":"L2/ 23 Adelaide Tce East Perth WA 6004",
    "addr:housenumber":"l2 / 23",
    "addr:postcode":"6004",
    "addr:street":"Adelaide Tce East",
    "iso:country":"AU",
    "sg:address":"L2/ 23 Adelaide Tce",
    "sg:city":"East Perth",
    "sg:classifiers":[
        {
            "category":"Government",
            "subcategory":"Court House",
            "type":"Public Place"
        }
    ],
    "sg:phone":"+61 1800 812 511",
    "sg:postcode":"6004",
    "sg:province":"WA",
    "sg:tags":[
        "personal",
        "marriage",
        "family",
        "counselling"
    ],
    "wof:name":"Kinway",
    "wof:placetype":"venue"
},
  "geometry": {"coordinates":[115.876091003,-31.9612960815],"type":"Point"}
}