{
  "type": "Feature",
  "properties": {
    "addr:full":"1 Herbert St Bedourie QLD 4829",
    "addr:housenumber":"1",
    "addr:postcode":"4829",
    "addr:street":"Herbert St",
    "iso:country":"AU",
    "sg:address":"1 Herbert St",
    "sg:city":"Bedourie",
    "sg:classifiers":[
        {
            "category":"Travel",
            "subcategory":"Hotels & Motels",
            "type":"Entertainment"
        }
    ],
    "sg:phone":"+61 7 4746 1277",
    "sg:postcode":"4829",
    "sg:province":"QLD",
    "wof:name":"Simpson Desert Oasis",
    "wof:placetype":"venue"
},
  "geometry": {"coordinates":[139.471024,-24.360216],"type":"Point"}
}