{
  "type": "Feature",
  "properties": {
    "addr:full":"Tarcombe Rd Seymour VIC 3660",
    "addr:postcode":"3660",
    "addr:street":"Tarcombe Rd",
    "iso:country":"AU",
    "sg:address":"Tarcombe Rd",
    "sg:city":"Seymour",
    "sg:classifiers":[
        {
            "category":"Organizations",
            "subcategory":"Non-profit Organization",
            "type":"Services"
        }
    ],
    "sg:phone":"+61 3 5792 3192",
    "sg:postcode":"3660",
    "sg:province":"VIC",
    "sg:tags":[
        "support",
        "disability",
        "organisation"
    ],
    "wof:name":"Goulburn Options Incorporated",
    "wof:placetype":"venue"
},
  "geometry": {"coordinates":[145.14683532699999,-37.0191688538],"type":"Point"}
}