{
  "type": "Feature",
  "properties": {
    "iso:country":"AU",
    "sg:address":"101 Burnley St",
    "sg:city":"Richmond",
    "sg:classifiers":[
        {
            "category":"Health Services",
            "subcategory":"Doctor",
            "type":"Services"
        }
    ],
    "sg:phone":"+61 3 9428 1645",
    "sg:postcode":"3121",
    "sg:province":"VIC",
    "sg:tags":[
        "medical",
        "practitioner"
    ],
    "wof:name":"Bella Freeman",
    "wof:placetype":"venue"
},
  "geometry": {"coordinates":[145.00918579099999,-37.8155555725],"type":"Point"}
}