{
  "type": "Feature",
  "properties": {
    "addr:full":"29 Camp St Beechworth VIC 3747",
    "addr:housenumber":"29",
    "addr:postcode":"3747",
    "addr:street":"Camp St",
    "iso:country":"AU",
    "sg:address":"29 Camp St",
    "sg:city":"Beechworth",
    "sg:classifiers":[
        {
            "category":"Personal",
            "subcategory":"Beauty Salon",
            "type":"Services"
        }
    ],
    "sg:phone":"+61 3 5728 1557",
    "sg:postcode":"3747",
    "sg:province":"VIC",
    "sg:tags":[
        "hairdresser"
    ],
    "wof:name":"Jeanine's Beauty Salon",
    "wof:placetype":"venue"
},
  "geometry": {"coordinates":[146.686646,-36.359303],"type":"Point"}
}