{
  "type": "Feature",
  "properties": {
    "addr:full":"111 Lloyd St Moe VIC 3825",
    "addr:housenumber":"111",
    "addr:postcode":"3825",
    "addr:street":"Lloyd St",
    "iso:country":"AU",
    "sg:address":"111 Lloyd St",
    "sg:city":"Moe",
    "sg:classifiers":[
        {
            "category":"Recreation",
            "subcategory":"Water Park",
            "type":"Entertainment"
        }
    ],
    "sg:phone":"+61 417 371 213",
    "sg:postcode":"3825",
    "sg:province":"VIC",
    "sg:tags":[
        "control",
        "seepage"
    ],
    "wof:name":"All Surface Coating (Aust) Pty Ltd",
    "wof:placetype":"venue"
},
  "geometry": {"coordinates":[146.25355500000001,-38.179119],"type":"Point"}
}