{
  "type": "Feature",
  "properties": {
    "iso:country":"AU",
    "sg:address":"75 Albany St",
    "sg:city":"Coffs Harbour",
    "sg:classifiers":[
        {
            "category":"Health Services",
            "subcategory":"Health Practitioner",
            "type":"Services"
        }
    ],
    "sg:phone":"+61 2 6652 2876",
    "sg:postcode":"2450",
    "sg:province":"NSW",
    "sg:tags":[
        "alternative"
    ],
    "wof:name":"Elaine Hall",
    "wof:placetype":"venue"
},
  "geometry": {"coordinates":[153.116364,-30.300825],"type":"Point"}
}