{
  "type": "Feature",
  "properties": {
    "iso:country":"AU",
    "sg:address":"17 Zeally Bay Rd",
    "sg:city":"Torquay",
    "sg:classifiers":[
        {
            "category":"Home & Garden",
            "subcategory":"Building Materials",
            "type":"Retail Goods"
        }
    ],
    "sg:phone":"+61 438 020 332",
    "sg:postcode":"3228",
    "sg:province":"VIC",
    "sg:tags":[
        "lawn",
        "cutting",
        "maintenance"
    ],
    "wof:name":"Zeally Bay Home & Garden Maintenance",
    "wof:placetype":"venue"
},
  "geometry": {"coordinates":[144.32278400000001,-38.330467],"type":"Point"}
}