{
  "type": "Feature",
  "properties": {
    "iso:country":"AU",
    "sg:address":"20b Murphy St",
    "sg:city":"Invermay",
    "sg:classifiers":[
        {
            "category":"Food & Beverages",
            "subcategory":"Bakery",
            "type":"Retail Goods"
        }
    ],
    "sg:phone":"+61 3 6334 3355",
    "sg:postcode":"7248",
    "sg:province":"TAS",
    "sg:tags":[
        "baker"
    ],
    "wof:name":"Country Bake",
    "wof:placetype":"venue"
},
  "geometry": {"coordinates":[147.125564575,-41.4251060486],"type":"Point"}
}