{
  "type": "Feature",
  "properties": {
    "addr:full":"Shop 1 891 Hay St Perth WA 6000",
    "addr:housenumber":"shop 1 891",
    "addr:postcode":"6000",
    "addr:street":"Hay St",
    "iso:country":"AU",
    "sg:address":"Shop 1 891 Hay St",
    "sg:city":"Perth",
    "sg:classifiers":[
        {
            "category":"Professional",
            "subcategory":"Computer Services",
            "type":"Services"
        }
    ],
    "sg:phone":"+61 1300 308 883",
    "sg:postcode":"6000",
    "sg:province":"WA",
    "sg:tags":[
        "equipment",
        "networking",
        "installation"
    ],
    "wof:name":"Hardware House Computer Shop",
    "wof:placetype":"venue"
},
  "geometry": {"coordinates":[115.851356506,-31.9518318176],"type":"Point"}
}