{
  "type": "Feature",
  "properties": {
    "iso:country":"AU",
    "sg:address":"47 Yarmouth St",
    "sg:city":"Brighton",
    "sg:classifiers":[
        {
            "category":"Building & Trades",
            "subcategory":"Construction",
            "type":"Services"
        }
    ],
    "sg:phone":"+61 8 8377 0722",
    "sg:postcode":"5048",
    "sg:province":"SA",
    "sg:tags":[
        "management"
    ],
    "wof:name":"Noble Projects Pty Ltd",
    "wof:placetype":"venue"
},
  "geometry": {"coordinates":[138.528976,-35.024105],"type":"Point"}
}