{
  "type": "Feature",
  "properties": {
    "addr:full":"43 Westminster St Oakleigh VIC 3166",
    "addr:housenumber":"43",
    "addr:postcode":"3166",
    "addr:street":"Westminster St",
    "iso:country":"AU",
    "sg:address":"43 Westminster St",
    "sg:city":"Oakleigh",
    "sg:classifiers":[
        {
            "category":"Manufacturing",
            "subcategory":"Rubber & Plastics",
            "type":"Manufacturing & Wholesale Goods"
        }
    ],
    "sg:phone":"+61 3 9569 9344",
    "sg:postcode":"3166",
    "sg:province":"VIC",
    "sg:tags":[
        "knitted",
        "wholesaler",
        "mfrs"
    ],
    "wof:name":"Top Cat Trimmings",
    "wof:placetype":"venue"
},
  "geometry": {"coordinates":[145.09507751500001,-37.9029960632],"type":"Point"}
}