{
  "type": "Feature",
  "properties": {
    "addr:full":"64 Epsom Rd Rosebery NSW 2018",
    "addr:housenumber":"64",
    "addr:postcode":"2018",
    "addr:street":"Epsom Rd",
    "iso:country":"AU",
    "sg:address":"64 Epsom Rd",
    "sg:city":"Rosebery",
    "sg:classifiers":[
        {
            "category":"Retail",
            "subcategory":"Auto Repair",
            "type":"Services"
        }
    ],
    "sg:phone":"+61 2 9697 0699",
    "sg:postcode":"2018",
    "sg:province":"NSW",
    "sg:tags":[
        "muffler",
        "exhaust",
        "system"
    ],
    "wof:name":"Toughy Toned Mufferler Brakes & Mechanical Services",
    "wof:placetype":"venue"
},
  "geometry": {"coordinates":[151.20504760700001,-33.9103622437],"type":"Point"}
}