{
  "type": "Feature",
  "properties": {
    "addr:full":"Suite 5, Level 2, 38 President Ave Caringbah NSW 2229",
    "addr:housenumber":"38",
    "addr:postcode":"2229",
    "addr:street":"President Ave",
    "iso:country":"AU",
    "sg:address":"Suite 5, Level 2, 38 President Ave",
    "sg:city":"Caringbah",
    "sg:classifiers":[
        {
            "category":"Shopping",
            "subcategory":"Bicycles & Sporting Goods",
            "type":"Retail Goods"
        }
    ],
    "sg:phone":"+61 2 9524 0817",
    "sg:postcode":"2229",
    "sg:province":"NSW",
    "sg:tags":[
        "dance",
        "accessory",
        "wear",
        "supply"
    ],
    "wof:name":"Airy Fairy Dancewear",
    "wof:placetype":"venue"
},
  "geometry": {"coordinates":[151.12121582,-34.0430107117],"type":"Point"}
}