{
  "type": "Feature",
  "properties": {
    "addr:full":"138 Morphett Rd Glengowrie SA 5044",
    "addr:housenumber":"138",
    "addr:postcode":"5044",
    "addr:street":"Morphett Rd",
    "iso:country":"AU",
    "sg:address":"138 Morphett Rd",
    "sg:city":"Glengowrie",
    "sg:classifiers":[
        {
            "category":"Travel",
            "subcategory":"Hotels & Motels",
            "type":"Entertainment"
        }
    ],
    "sg:phone":"+61 8 8295 8371",
    "sg:postcode":"5044",
    "sg:province":"SA",
    "wof:name":"Morphett Arms Hotel",
    "wof:placetype":"venue"
},
  "geometry": {"coordinates":[138.53892500000001,-34.992901],"type":"Point"}
}