{
  "type": "Feature",
  "properties": {
    "iso:country":"AU",
    "sg:address":"138 Morphett Rd",
    "sg:city":"Glengowrie",
    "sg:classifiers":[
        {
            "category":"Travel",
            "subcategory":"Hotels & Motels",
            "type":"Entertainment"
        }
    ],
    "sg:phone":"+61 8 8295 8371",
    "sg:postcode":"5044",
    "sg:province":"SA",
    "wof:name":"Morphett Arms Hotel",
    "wof:placetype":"venue"
},
  "geometry": {"coordinates":[138.538925,-34.992901],"type":"Point"}
}