{
  "type": "Feature",
  "properties": {
    "addr:full":"30 Carmody Rd St Lucia QLD 4067",
    "addr:housenumber":"30",
    "addr:postcode":"4067",
    "addr:street":"Carmody Rd St",
    "iso:country":"AU",
    "sg:address":"30 Carmody Rd",
    "sg:city":"St Lucia",
    "sg:classifiers":[
        {
            "category":"Home & Garden",
            "subcategory":"Garden Supply",
            "type":"Retail Goods"
        }
    ],
    "sg:phone":"+61 408 190 839",
    "sg:postcode":"4067",
    "sg:province":"QLD",
    "sg:tags":[
        "turf",
        "lawn"
    ],
    "wof:name":"Aussieturf",
    "wof:placetype":"venue"
},
  "geometry": {"coordinates":[152.994415283,-27.496919632],"type":"Point"}
}