{
  "type": "Feature",
  "properties": {
    "addr:full":"33 Bellambi La Bellambi NSW 2518",
    "addr:housenumber":"33",
    "addr:postcode":"2518",
    "addr:street":"Bellambi La Bellambi",
    "iso:country":"AU",
    "sg:address":"33 Bellambi La",
    "sg:city":"Bellambi",
    "sg:classifiers":[
        {
            "category":"Autos & Motor Vehicles",
            "subcategory":"Auto Supplies",
            "type":"Retail Goods"
        }
    ],
    "sg:phone":"+61 2 4283 1180",
    "sg:postcode":"2518",
    "sg:province":"NSW",
    "sg:tags":[
        "part",
        "cycles",
        "accessory"
    ],
    "wof:name":"Daytona Motor Cycle Painting",
    "wof:placetype":"venue"
},
  "geometry": {"coordinates":[150.90623500000001,-34.361969],"type":"Point"}
}