{
  "type": "Feature",
  "properties": {
    "iso:country":"AU",
    "sg:address":"35 - 37 Kennedy St",
    "sg:city":"Kingston",
    "sg:classifiers":[
        {
            "category":"Building & Trades",
            "subcategory":"Landscaping Services",
            "type":"Services"
        }
    ],
    "sg:phone":"+61 2 6232 6311",
    "sg:postcode":"2604",
    "sg:province":"ACT",
    "sg:tags":[
        "consultant"
    ],
    "wof:name":"TT Architecture",
    "wof:placetype":"venue"
},
  "geometry": {"coordinates":[149.141357422,-35.3167304993],"type":"Point"}
}