{
  "type": "Feature",
  "properties": {
    "addr:full":"Lot 5 39 Simon Pl Moss Vale NSW 2577",
    "addr:housenumber":"39",
    "addr:postcode":"2577",
    "addr:street":"Simon Pl Moss Vale",
    "iso:country":"AU",
    "sg:address":"Lot 5 39 Simon Pl",
    "sg:city":"Moss Vale",
    "sg:classifiers":[
        {
            "category":"Shopping",
            "subcategory":"Beauty & Cosmetics",
            "type":"Retail Goods"
        }
    ],
    "sg:phone":"+61 2 4868 3455",
    "sg:postcode":"2577",
    "sg:province":"NSW",
    "sg:tags":[
        "equipment",
        "salon",
        "supply"
    ],
    "wof:name":"Australian Hair & Beauty",
    "wof:placetype":"venue"
},
  "geometry": {"coordinates":[150.37730407699999,-34.5374794006],"type":"Point"}
}