{
  "type": "Feature",
  "properties": {
    "addr:full":"Osborne Ave Springvale VIC 3171",
    "addr:postcode":"3171",
    "addr:street":"Osborne Ave",
    "iso:country":"AU",
    "sg:address":"Osborne Ave",
    "sg:city":"Springvale",
    "sg:classifiers":[
        {
            "category":"Building & Trades",
            "subcategory":"Construction",
            "type":"Services"
        }
    ],
    "sg:phone":"+61 3 9549 7217",
    "sg:postcode":"3171",
    "sg:province":"VIC",
    "sg:tags":[
        "window",
        "timber"
    ],
    "wof:name":"Homeview Windows",
    "wof:placetype":"venue"
},
  "geometry": {"coordinates":[145.148727417,-37.9469795227],"type":"Point"}
}