{
  "type": "Feature",
  "properties": {
    "addr:full":"Unit 8 / 40 Ricketts Rd Mt Waverley VIC 3149",
    "addr:housenumber":"40",
    "addr:postcode":"3149",
    "addr:street":"Ricketts Rd",
    "iso:country":"AU",
    "sg:address":"Unit 8 / 40 Ricketts Rd",
    "sg:city":"Mt Waverley",
    "sg:classifiers":[
        {
            "category":"Utilities",
            "subcategory":"Water",
            "type":"Services"
        }
    ],
    "sg:phone":"+61 1300 369 580",
    "sg:postcode":"3149",
    "sg:province":"VIC",
    "sg:tags":[
        "hot",
        "system"
    ],
    "wof:name":"Pulbrook Air",
    "wof:placetype":"venue"
},
  "geometry": {"coordinates":[145.14280700699999,-37.8999481201],"type":"Point"}
}