{
  "type": "Feature",
  "properties": {
    "addr:full":"99 Glenwood Drv Thornton NSW 2322",
    "addr:housenumber":"99",
    "addr:postcode":"2322",
    "addr:street":"Glenwood Drv",
    "iso:country":"AU",
    "sg:address":"99 Glenwood Drv",
    "sg:city":"Thornton",
    "sg:classifiers":[
        {
            "category":"Retail",
            "subcategory":"Auto Repair",
            "type":"Services"
        }
    ],
    "sg:phone":"+61 2 4966 1838",
    "sg:postcode":"2322",
    "sg:province":"NSW",
    "sg:tags":[
        "repairer",
        "motor",
        "engineer"
    ],
    "wof:name":"BBR Mechanical",
    "wof:placetype":"venue"
},
  "geometry": {"coordinates":[151.62660217300001,-32.7856445312],"type":"Point"}
}