{
  "type": "Feature",
  "properties": {
    "iso:country":"AU",
    "sg:address":"120 Clarence St",
    "sg:city":"Sydney",
    "sg:classifiers":[
        {
            "category":"Professional",
            "subcategory":"Art Services",
            "type":"Services"
        }
    ],
    "sg:phone":"+61 2 9290 3639",
    "sg:postcode":"2000",
    "sg:province":"NSW",
    "wof:name":"Jinta Desert Art Gallery",
    "wof:placetype":"venue"
},
  "geometry": {"coordinates":[151.20545959500001,-33.868850708],"type":"Point"}
}