{
  "type": "Feature",
  "properties": {
    "iso:country":"AU",
    "sg:address":"2a Marco Ave",
    "sg:city":"Revesby",
    "sg:classifiers":[
        {
            "category":"Professional",
            "subcategory":"Art Services",
            "type":"Services"
        }
    ],
    "sg:phone":"+61 2 9772 1403",
    "sg:postcode":"2212",
    "sg:province":"NSW",
    "sg:tags":[
        "picture",
        "frame",
        "framing"
    ],
    "wof:name":"Aus Frames",
    "wof:placetype":"venue"
},
  "geometry": {"coordinates":[151.01696799999999,-33.952019],"type":"Point"}
}