{
  "type": "Feature",
  "properties": {
    "addr:full":"330B Darebin Rd Fairfield VIC 3078",
    "addr:housenumber":"330b",
    "addr:postcode":"3078",
    "addr:street":"Darebin Rd",
    "iso:country":"AU",
    "sg:address":"330B Darebin Rd",
    "sg:city":"Fairfield",
    "sg:classifiers":[
        {
            "category":"Communications",
            "type":"Services"
        }
    ],
    "sg:phone":"+61 3 9497 3344",
    "sg:postcode":"3078",
    "sg:province":"VIC",
    "sg:tags":[
        "data"
    ],
    "wof:name":"John R. Turk",
    "wof:placetype":"venue"
},
  "geometry": {"coordinates":[145.02699279800001,-37.766292572],"type":"Point"}
}