{
  "type": "Feature",
  "properties": {
    "addr:full":"41 Alison Ave Lennox Head NSW 2478",
    "addr:housenumber":"41",
    "addr:postcode":"2478",
    "addr:street":"Alison Ave Lennox",
    "iso:country":"AU",
    "sg:address":"41 Alison Ave",
    "sg:city":"Lennox Head",
    "sg:classifiers":[
        {
            "category":"Personal",
            "subcategory":"Beauty Salon",
            "type":"Services"
        }
    ],
    "sg:phone":"+61 402 675 970",
    "sg:postcode":"2478",
    "sg:province":"NSW",
    "wof:name":"Lennox Beauty",
    "wof:placetype":"venue"
},
  "geometry": {"coordinates":[153.58819580100001,-28.7871284485],"type":"Point"}
}