{
  "type": "Feature",
  "properties": {
    "addr:full":"2a Riverstone Pde Riverstone NSW 2765",
    "addr:housenumber":"2a",
    "addr:postcode":"2765",
    "addr:street":"Riverstone Pde",
    "iso:country":"AU",
    "sg:address":"2a Riverstone Pde",
    "sg:city":"Riverstone",
    "sg:classifiers":[
        {
            "category":"Banks & Credit Unions",
            "subcategory":"Financial Services",
            "type":"Services"
        }
    ],
    "sg:phone":"+61 2 9838 3033",
    "sg:postcode":"2765",
    "sg:province":"NSW",
    "sg:tags":[
        "financier"
    ],
    "wof:name":"City Finance Loans & Cash Solutions",
    "wof:placetype":"venue"
},
  "geometry": {"coordinates":[150.85842895499999,-33.6732788086],"type":"Point"}
}