{
  "type": "Feature",
  "properties": {
    "addr:full":"6 Sydenham Rd Marrickville NSW 2204",
    "addr:housenumber":"6",
    "addr:postcode":"2204",
    "addr:street":"Sydenham Rd",
    "iso:country":"AU",
    "sg:address":"6 Sydenham Rd",
    "sg:city":"Marrickville",
    "sg:classifiers":[
        {
            "category":"Utilities",
            "subcategory":"Electric",
            "type":"Services"
        }
    ],
    "sg:phone":"+61 2 9517 2299",
    "sg:postcode":"2204",
    "sg:province":"NSW",
    "sg:tags":[
        "electrical",
        "contractor"
    ],
    "wof:name":"Powerdata Pty Ltd",
    "wof:placetype":"venue"
},
  "geometry": {"coordinates":[151.16627500000001,-33.913002],"type":"Point"}
}