{
  "type": "Feature",
  "properties": {
    "iso:country":"AU",
    "sg:address":"35 Finnie Rd",
    "sg:city":"Deagon",
    "sg:classifiers":[
        {
            "category":"Building & Trades",
            "subcategory":"Cleaning & Sanitation",
            "type":"Services"
        }
    ],
    "sg:phone":"+61 7 3269 3256",
    "sg:postcode":"4017",
    "sg:province":"QLD",
    "sg:tags":[
        "cleaner",
        "repairer",
        "roof"
    ],
    "sg:website":"http://www.stylelineroofing.com.au",
    "wof:name":"Styleline Roofing & Repairs",
    "wof:placetype":"venue"
},
  "geometry": {"coordinates":[153.063064575,-27.3317737579],"type":"Point"}
}