{
  "type": "Feature",
  "properties": {
    "addr:full":"Suite 2c, 9 Burwood Rd Burwood NSW 2134",
    "addr:housenumber":"9",
    "addr:postcode":"2134",
    "addr:street":"Burwood Rd",
    "iso:country":"AU",
    "sg:address":"Suite 2c, 9 Burwood Rd",
    "sg:city":"Burwood",
    "sg:classifiers":[
        {
            "category":"Professional",
            "subcategory":"Employment Agencies",
            "type":"Services"
        }
    ],
    "sg:phone":"+61 2 9747 0177",
    "sg:postcode":"2134",
    "sg:province":"NSW",
    "wof:name":"MEGT (Australia) Ltd.",
    "wof:placetype":"venue"
},
  "geometry": {"coordinates":[151.105010986,-33.869884491],"type":"Point"}
}