{
  "type": "Feature",
  "properties": {
    "iso:country":"AU",
    "sg:address":"20 Angler St",
    "sg:city":"Noosa Heads",
    "sg:classifiers":[
        {
            "category":"Communications",
            "subcategory":"News Services",
            "type":"Services"
        }
    ],
    "sg:phone":"+61 1800 001 386",
    "sg:postcode":"4567",
    "sg:province":"QLD",
    "sg:tags":[
        "information",
        "tourist",
        "attractions"
    ],
    "wof:name":"Oceanrider",
    "wof:placetype":"venue"
},
  "geometry": {"coordinates":[153.09220886200001,-26.3934593201],"type":"Point"}
}