{
  "type": "Feature",
  "properties": {
    "addr:full":"47 Moil Crs Moil NT 0810",
    "addr:housenumber":"47",
    "addr:postcode":"nt 0810",
    "addr:street":"Moil Crs",
    "iso:country":"AU",
    "sg:address":"47 Moil Crs",
    "sg:city":"Moil",
    "sg:classifiers":[
        {
            "category":"Building & Trades",
            "subcategory":"Plumbing",
            "type":"Services"
        }
    ],
    "sg:phone":"+61 8 8927 9191",
    "sg:postcode":"0810",
    "sg:province":"NT",
    "sg:tags":[
        "plumber",
        "gasfitters"
    ],
    "wof:name":"G & T Plumbing Pty Ltd",
    "wof:placetype":"venue"
},
  "geometry": {"coordinates":[130.88163757300001,-12.3906602859],"type":"Point"}
}