{
  "type": "Feature",
  "properties": {
    "iso:country":"AU",
    "sg:address":"A Suite 3, 123 Colin St",
    "sg:city":"West Perth",
    "sg:classifiers":[
        {
            "category":"Professional",
            "subcategory":"Engineering",
            "type":"Services"
        }
    ],
    "sg:phone":"+61 8 9481 1900",
    "sg:postcode":"6005",
    "sg:province":"WA",
    "sg:tags":[
        "consulting",
        "engineer"
    ],
    "wof:name":"Development Engineering Consultants Pty Ltd",
    "wof:placetype":"venue"
},
  "geometry": {"coordinates":[115.843360901,-31.9456748962],"type":"Point"}
}