{
  "type": "Feature",
  "properties": {
    "iso:country":"AU",
    "sg:address":"Unit 1, 189 Lakeside Drv",
    "sg:city":"Joondalup",
    "sg:classifiers":[
        {
            "category":"Health Services",
            "subcategory":"Chiropractor",
            "type":"Services"
        }
    ],
    "sg:phone":"+61 8 9300 1132",
    "sg:postcode":"6027",
    "sg:province":"WA",
    "sg:website":"http://www.chiropractors.asn.au",
    "wof:name":"Joondalup Chiropractic Clinic",
    "wof:placetype":"venue"
},
  "geometry": {"coordinates":[115.773841858,-31.7423839569],"type":"Point"}
}