{
  "type": "Feature",
  "properties": {
    "addr:full":"13 Bates Drv Bundaberg QLD 4670",
    "addr:housenumber":"13",
    "addr:postcode":"4670",
    "addr:street":"Bates Drv",
    "iso:country":"AU",
    "sg:address":"13 Bates Drv",
    "sg:city":"Bundaberg",
    "sg:classifiers":[
        {
            "category":"Retail",
            "subcategory":"Auto Repair",
            "type":"Services"
        }
    ],
    "sg:phone":"+61 7 4159 9143",
    "sg:postcode":"4670",
    "sg:province":"QLD",
    "sg:tags":[
        "car",
        "restoration",
        "supply"
    ],
    "wof:name":"John Handley Restorations",
    "wof:placetype":"venue"
},
  "geometry": {"coordinates":[152.30563354500001,-24.8441848755],"type":"Point"}
}