{
  "type": "Feature",
  "properties": {
    "iso:country":"AU",
    "sg:address":"2033 Sangate Rd",
    "sg:city":"Virginia",
    "sg:classifiers":[
        {
            "category":"Retail",
            "subcategory":"Auto Rental",
            "type":"Services"
        }
    ],
    "sg:phone":"+61 7 3216 5155",
    "sg:postcode":"4014",
    "sg:province":"QLD",
    "sg:tags":[
        "home",
        "hire",
        "motor",
        "campervans"
    ],
    "wof:name":"Camper Rentals",
    "wof:placetype":"venue"
},
  "geometry": {"coordinates":[153.062423706,-27.3693389893],"type":"Point"}
}