{
  "type": "Feature",
  "properties": {
    "addr:full":"72 Coolamon St Ariah Park NSW 2665",
    "addr:housenumber":"72",
    "addr:postcode":"2665",
    "addr:street":"Coolamon St",
    "iso:country":"AU",
    "sg:address":"72 Coolamon St",
    "sg:city":"Ariah Park",
    "sg:classifiers":[
        {
            "category":"Wholesale",
            "subcategory":"Farm Supplies",
            "type":"Manufacturing & Wholesale Goods"
        }
    ],
    "sg:phone":"+61 2 6974 1154",
    "sg:postcode":"2665",
    "sg:province":"NSW",
    "sg:tags":[
        "equipment"
    ],
    "wof:name":"Tidd & Horan Rural",
    "wof:placetype":"venue"
},
  "geometry": {"coordinates":[147.22105407699999,-34.3461723328],"type":"Point"}
}