{
  "type": "Feature",
  "properties": {
    "addr:full":"Shop 18 Jetty Village Shopping Centre Coffs Harbour Jetty NSW 2450",
    "addr:housenumber":"shop 18 jetty",
    "addr:postcode":"2450",
    "iso:country":"AU",
    "sg:address":"Shop 18 Jetty Village Shopping Centre",
    "sg:city":"Coffs Harbour Jetty",
    "sg:classifiers":[
        {
            "category":"Retail",
            "subcategory":"Laundry & Dry Cleaning",
            "type":"Services"
        }
    ],
    "sg:phone":"+61 2 6652 1574",
    "sg:postcode":"2450",
    "sg:province":"NSW",
    "wof:name":"Jetty Village Laundrette",
    "wof:placetype":"venue"
},
  "geometry": {"coordinates":[153.13870199999999,-30.305031],"type":"Point"}
}