{
  "type": "Feature",
  "properties": {
    "iso:country":"AU",
    "sg:address":"27 Babarra St",
    "sg:city":"Stafford",
    "sg:classifiers":[
        {
            "category":"Home & Garden",
            "subcategory":"Carpets & Floor Coverings",
            "type":"Retail Goods"
        }
    ],
    "sg:phone":"+61 7 3856 2699",
    "sg:postcode":"4053",
    "sg:province":"QLD",
    "sg:tags":[
        "tile",
        "wall"
    ],
    "wof:name":"United Ceramic Imports",
    "wof:placetype":"venue"
},
  "geometry": {"coordinates":[153.017486572,-27.4147758484],"type":"Point"}
}