{
  "type": "Feature",
  "properties": {
    "iso:country":"AU",
    "sg:address":"Bay 8/ 2 Clare Mace Crs",
    "sg:city":"Berkeley Vale",
    "sg:classifiers":[
        {
            "category":"Building & Trades",
            "subcategory":"Construction",
            "type":"Services"
        }
    ],
    "sg:phone":"+61 2 4388 4990",
    "sg:postcode":"2261",
    "sg:province":"NSW",
    "sg:tags":[
        "joinery"
    ],
    "wof:name":"Berkeley Vale Kitchens",
    "wof:placetype":"venue"
},
  "geometry": {"coordinates":[151.500137,-33.348278],"type":"Point"}
}