{
  "type": "Feature",
  "properties": {
    "addr:full":"2 Ferguson Rd Leopold VIC 3224",
    "addr:housenumber":"2",
    "addr:postcode":"3224",
    "addr:street":"Ferguson Rd",
    "iso:country":"AU",
    "sg:address":"2 Ferguson Rd",
    "sg:city":"Leopold",
    "sg:classifiers":[
        {
            "category":"Health Services",
            "subcategory":"Dentist",
            "type":"Services"
        }
    ],
    "sg:phone":"+61 3 5250 2722",
    "sg:postcode":"3224",
    "sg:province":"VIC",
    "wof:name":"Roberts Campbell Dr",
    "wof:placetype":"venue"
},
  "geometry": {"coordinates":[144.46397400000001,-38.189308],"type":"Point"}
}