{
  "type": "Feature",
  "properties": {
    "addr:full":"16c Rawson Ave Tamworth NSW 2340",
    "addr:housenumber":"16c",
    "addr:postcode":"2340",
    "addr:street":"Rawson Ave",
    "iso:country":"AU",
    "sg:address":"16c Rawson Ave",
    "sg:city":"Tamworth",
    "sg:classifiers":[
        {
            "category":"Building & Trades",
            "subcategory":"Construction",
            "type":"Services"
        }
    ],
    "sg:phone":"+61 2 6766 1177",
    "sg:postcode":"2340",
    "sg:province":"NSW",
    "sg:tags":[
        "contractor"
    ],
    "wof:name":"Matt Salter Constructions",
    "wof:placetype":"venue"
},
  "geometry": {"coordinates":[150.93699645999999,-31.0983829498],"type":"Point"}
}