{
  "type": "Feature",
  "properties": {
    "addr:full":"44- 46 Cox Ave Kingswood NSW 2747",
    "addr:housenumber":"46",
    "addr:postcode":"2747",
    "addr:street":"Cox Ave",
    "iso:country":"AU",
    "sg:address":"44- 46 Cox Ave",
    "sg:city":"Kingswood",
    "sg:classifiers":[
        {
            "category":"Wholesale",
            "subcategory":"Machinery & Supplies",
            "type":"Manufacturing & Wholesale Goods"
        }
    ],
    "sg:phone":"+61 2 4722 8499",
    "sg:postcode":"2747",
    "sg:province":"NSW",
    "sg:tags":[
        "equipment",
        "system",
        "elevating",
        "conveying"
    ],
    "wof:name":"Endless Belt Service Pty Ltd",
    "wof:placetype":"venue"
},
  "geometry": {"coordinates":[150.719116211,-33.7572364807],"type":"Point"}
}