{
  "type": "Feature",
  "properties": {
    "addr:full":"37 Habib Drv South Lismore NSW 2480",
    "addr:housenumber":"37",
    "addr:postcode":"2480",
    "addr:street":"Habib Drv South",
    "iso:country":"AU",
    "sg:address":"37 Habib Drv",
    "sg:city":"South Lismore",
    "sg:classifiers":[
        {
            "category":"Recreation",
            "subcategory":"Boat Charter",
            "type":"Entertainment"
        }
    ],
    "sg:phone":"+61 1300 655 799",
    "sg:postcode":"2480",
    "sg:province":"NSW",
    "sg:tags":[
        "canopy",
        "motor"
    ],
    "wof:name":"Carryboy Canopies",
    "wof:placetype":"venue"
},
  "geometry": {"coordinates":[153.262817383,-28.825056076],"type":"Point"}
}