{
  "type": "Feature",
  "properties": {
    "iso:country":"AU",
    "sg:address":"8 Rangeview Rd",
    "sg:city":"Diamond Creek",
    "sg:classifiers":[
        {
            "category":"Building & Trades",
            "subcategory":"Construction",
            "type":"Services"
        }
    ],
    "sg:phone":"+61 3 9438 1570",
    "sg:postcode":"3089",
    "sg:province":"VIC",
    "sg:tags":[
        "joiner",
        "carpenter"
    ],
    "wof:name":"S & S Manning Carpentry",
    "wof:placetype":"venue"
},
  "geometry": {"coordinates":[145.16047699999999,-37.669754],"type":"Point"}
}