{
  "type": "Feature",
  "properties": {
    "addr:full":"48 Moore St Moe VIC 3825",
    "addr:housenumber":"48",
    "addr:postcode":"3825",
    "addr:street":"Moore St",
    "iso:country":"AU",
    "sg:address":"48 Moore St",
    "sg:city":"Moe",
    "sg:classifiers":[
        {
            "category":"Travel",
            "subcategory":"Travel Agent",
            "type":"Entertainment"
        }
    ],
    "sg:phone":"+61 3 5127 3388",
    "sg:postcode":"3825",
    "sg:province":"VIC",
    "sg:tags":[
        "consultant"
    ],
    "wof:name":"Jetset",
    "wof:placetype":"venue"
},
  "geometry": {"coordinates":[146.26132200000001,-38.173565],"type":"Point"}
}