{
  "type": "Feature",
  "properties": {
    "addr:full":"7 Dunmore St Croydon Park NSW 2133",
    "addr:housenumber":"7",
    "addr:postcode":"2133",
    "addr:street":"Dunmore St",
    "iso:country":"AU",
    "sg:address":"7 Dunmore St",
    "sg:city":"Croydon Park",
    "sg:classifiers":[
        {
            "category":"Military Area",
            "subcategory":"Air Force Base",
            "type":"Public Place"
        }
    ],
    "sg:phone":"+61 2 9798 3481",
    "sg:postcode":"2133",
    "sg:province":"NSW",
    "sg:tags":[
        "men's",
        "tailor"
    ],
    "wof:name":"Thomas Tailoring",
    "wof:placetype":"venue"
},
  "geometry": {"coordinates":[151.10704040499999,-33.8962440491],"type":"Point"}
}