{
  "type": "Feature",
  "properties": {
    "iso:country":"AU",
    "sg:address":"4/ 39 Clarence St",
    "sg:city":"Malvern East",
    "sg:classifiers":[
        {
            "category":"Home & Garden",
            "subcategory":"Carpets & Floor Coverings",
            "type":"Retail Goods"
        }
    ],
    "sg:phone":"+61 408 988 592",
    "sg:postcode":"3145",
    "sg:province":"VIC",
    "sg:tags":[
        "tile",
        "wall"
    ],
    "wof:name":"Owen Mullaney",
    "wof:placetype":"venue"
},
  "geometry": {"coordinates":[145.04188537600001,-37.8718833923],"type":"Point"}
}