{
  "type": "Feature",
  "properties": {
    "addr:full":"Units 5 & 6/ 18 O'Shea Drv Nerang QLD 4211",
    "addr:housenumber":"units 5 & 6 / 18",
    "addr:postcode":"4211",
    "addr:street":"O'Shea Drv",
    "iso:country":"AU",
    "sg:address":"Units 5 & 6/ 18 O'Shea Drv",
    "sg:city":"Nerang",
    "sg:classifiers":[
        {
            "category":"Shopping",
            "type":"Retail Goods"
        }
    ],
    "sg:phone":"+61 7 5596 2844",
    "sg:postcode":"4211",
    "sg:province":"QLD",
    "sg:tags":[
        "equipment",
        "safety",
        "accessory"
    ],
    "wof:name":"Novatek International Pty Ltd",
    "wof:placetype":"venue"
},
  "geometry": {"coordinates":[153.344284058,-27.9996376038],"type":"Point"}
}