{
  "type": "Feature",
  "properties": {
    "addr:full":"34 Dumaresq St Gordon NSW 2072",
    "addr:housenumber":"34",
    "addr:postcode":"2072",
    "addr:street":"Dumaresq St",
    "iso:country":"AU",
    "sg:address":"34 Dumaresq St",
    "sg:city":"Gordon",
    "sg:classifiers":[
        {
            "category":"Professional",
            "subcategory":"Art Services",
            "type":"Services"
        }
    ],
    "sg:phone":"+61 2 9418 2999",
    "sg:postcode":"2072",
    "sg:province":"NSW",
    "sg:tags":[
        "decorator",
        "painter"
    ],
    "wof:name":"Brushcorp Maintenance Pty Ltd",
    "wof:placetype":"venue"
},
  "geometry": {"coordinates":[151.148681641,-33.7554359436],"type":"Point"}
}