{
  "type": "Feature",
  "properties": {
    "addr:full":"Murray Ave Renmark SA 5341",
    "addr:postcode":"5341",
    "addr:street":"Murray Ave",
    "iso:country":"AU",
    "sg:address":"Murray Ave",
    "sg:city":"Renmark",
    "sg:classifiers":[
        {
            "category":"Freight",
            "type":"Transportation"
        }
    ],
    "sg:phone":"+61 8 8586 6468",
    "sg:postcode":"5341",
    "sg:province":"SA",
    "sg:tags":[
        "light",
        "carrier"
    ],
    "wof:name":"Stateliner Coachfreight",
    "wof:placetype":"venue"
},
  "geometry": {"coordinates":[140.750442505,-34.1731529236],"type":"Point"}
}