{
  "type": "Feature",
  "properties": {
    "iso:country":"AU",
    "sg:address":"Suite 6 / 72 Willoughby Rd",
    "sg:city":"Crows Nest",
    "sg:classifiers":[
        {
            "category":"Government",
            "subcategory":"Court House",
            "type":"Public Place"
        }
    ],
    "sg:phone":"+61 404 256 858",
    "sg:postcode":"2065",
    "sg:province":"NSW",
    "sg:tags":[
        "personal",
        "marriage",
        "family",
        "counselling"
    ],
    "wof:name":"Kim Warwick - Counselling & Psychotherapy",
    "wof:placetype":"venue"
},
  "geometry": {"coordinates":[151.200714111,-33.8253707886],"type":"Point"}
}