{
  "type": "Feature",
  "properties": {
    "iso:country":"AU",
    "sg:address":"34 Armstrong St",
    "sg:city":"Ballarat",
    "sg:classifiers":[
        {
            "category":"Professional",
            "subcategory":"Accounting & Tax Preparation",
            "type":"Services"
        }
    ],
    "sg:phone":"+61 3 5334 4699",
    "sg:postcode":"3350",
    "sg:province":"VIC",
    "sg:tags":[
        "accountant",
        "auditor"
    ],
    "wof:name":"Webb-Ervin Accountants",
    "wof:placetype":"venue"
},
  "geometry": {"coordinates":[143.859589,-37.561852],"type":"Point"}
}