{
  "type": "Feature",
  "properties": {
    "addr:full":"169 Ducats Rd Tallebudgera Valley QLD 4228",
    "addr:housenumber":"169",
    "addr:postcode":"4228",
    "addr:street":"Ducats Rd",
    "iso:country":"AU",
    "sg:address":"169 Ducats Rd",
    "sg:city":"Tallebudgera Valley",
    "sg:classifiers":[
        {
            "category":"Professional",
            "subcategory":"Art Services",
            "type":"Services"
        }
    ],
    "sg:phone":"+61 7 5533 8245",
    "sg:postcode":"4228",
    "sg:province":"QLD",
    "sg:tags":[
        "artist"
    ],
    "wof:name":"Steven Hall Designer / Maker",
    "wof:placetype":"venue"
},
  "geometry": {"coordinates":[153.40414428700001,-28.1728572845],"type":"Point"}
}