{
  "type": "Feature",
  "properties": {
    "addr:full":"71 Tenant St Fyshwick ACT 2609",
    "addr:housenumber":"71",
    "addr:postcode":"2609",
    "addr:street":"Tenant St",
    "iso:country":"AU",
    "sg:address":"71 Tenant St",
    "sg:city":"Fyshwick",
    "sg:classifiers":[
        {
            "category":"Retail",
            "subcategory":"Auto Repair",
            "type":"Services"
        }
    ],
    "sg:phone":"+61 2 6280 6838",
    "sg:postcode":"2609",
    "sg:province":"ACT",
    "sg:tags":[
        "repairer",
        "motor",
        "engineer"
    ],
    "wof:name":"Toyo Serv",
    "wof:placetype":"venue"
},
  "geometry": {"coordinates":[149.18739318900001,-35.3296165466],"type":"Point"}
}