{
  "type": "Feature",
  "properties": {
    "iso:country":"AU",
    "sg:address":"Lattas Point",
    "sg:city":"Batemans Bay",
    "sg:classifiers":[
        {
            "category":"Farming",
            "subcategory":"Fish & Marine Products",
            "type":"Manufacturing & Wholesale Goods"
        }
    ],
    "sg:phone":"+61 2 4472 7435",
    "sg:postcode":"2536",
    "sg:province":"NSW",
    "sg:tags":[
        "supplier",
        "oyster",
        "farmer"
    ],
    "wof:name":"Clyde River Oyster Marketing Pty Ltd",
    "wof:placetype":"venue"
},
  "geometry": {"coordinates":[150.17732238799999,-35.7084007263],"type":"Point"}
}