{
  "type": "Feature",
  "properties": {
    "addr:full":"95 Drummond Rd Shepparton VIC 3630",
    "addr:housenumber":"95",
    "addr:postcode":"3630",
    "addr:street":"Drummond Rd",
    "iso:country":"AU",
    "sg:address":"95 Drummond Rd",
    "sg:city":"Shepparton",
    "sg:classifiers":[
        {
            "category":"Retail",
            "subcategory":"Auto Repair",
            "type":"Services"
        }
    ],
    "sg:phone":"+61 3 5831 5222",
    "sg:postcode":"3630",
    "sg:province":"VIC",
    "sg:tags":[
        "repairer",
        "motor",
        "engineer"
    ],
    "wof:name":"C & M Automotive Pty Ltd",
    "wof:placetype":"venue"
},
  "geometry": {"coordinates":[145.42314148,-36.3761024475],"type":"Point"}
}