{
  "type": "Feature",
  "properties": {
    "addr:full":"65 Horsley Rd Oak Flats NSW 2529",
    "addr:housenumber":"65",
    "addr:postcode":"2529",
    "addr:street":"Horsley Rd",
    "iso:country":"AU",
    "sg:address":"65 Horsley Rd",
    "sg:city":"Oak Flats",
    "sg:classifiers":[
        {
            "category":"Retail",
            "subcategory":"Driving School",
            "type":"Services"
        }
    ],
    "sg:phone":"+61 2 4257 6565",
    "sg:postcode":"2529",
    "sg:province":"NSW",
    "wof:name":"Ezy-Azz Learn 2 Drive",
    "wof:placetype":"venue"
},
  "geometry": {"coordinates":[150.81254577600001,-34.5586166382],"type":"Point"}
}