{
  "type": "Feature",
  "properties": {
    "addr:full":"165-171 Holloway Rd Chambers Flat QLD 4133",
    "addr:housenumber":"165-171",
    "addr:postcode":"4133",
    "addr:street":"Holloway Rd",
    "iso:country":"AU",
    "sg:address":"165-171 Holloway Rd",
    "sg:city":"Chambers Flat",
    "sg:classifiers":[
        {
            "category":"Professional",
            "subcategory":"Secretarial Services",
            "type":"Services"
        }
    ],
    "sg:phone":"+61 7 5547 0774",
    "sg:postcode":"4133",
    "sg:province":"QLD",
    "sg:tags":[
        "typing"
    ],
    "wof:name":"The Bush Secretary",
    "wof:placetype":"venue"
},
  "geometry": {"coordinates":[153.084274292,-27.746301651],"type":"Point"}
}