{
  "type": "Feature",
  "properties": {
    "addr:full":"341 Smith St Fitzroy VIC 3065",
    "addr:housenumber":"341",
    "addr:postcode":"3065",
    "addr:street":"Smith St",
    "iso:country":"AU",
    "sg:address":"341 Smith St",
    "sg:city":"Fitzroy",
    "sg:classifiers":[
        {
            "category":"Shopping",
            "subcategory":"Clothing, Apparel, & Fashions",
            "type":"Retail Goods"
        }
    ],
    "sg:phone":"+61 3 9486 0599",
    "sg:postcode":"3065",
    "sg:province":"VIC",
    "sg:tags":[
        "lady",
        "wear"
    ],
    "wof:name":"Kisetsu Trading Pty Ltd",
    "wof:placetype":"venue"
},
  "geometry": {"coordinates":[144.984130859,-37.7987213135],"type":"Point"}
}