{
  "type": "Feature",
  "properties": {
    "iso:country":"AU",
    "sg:address":"Unit 15/ 45-47 Whyalla Pl",
    "sg:city":"Prestons",
    "sg:classifiers":[
        {
            "category":"Building & Trades",
            "subcategory":"Construction",
            "type":"Services"
        }
    ],
    "sg:phone":"+61 2 9608 6663",
    "sg:postcode":"2170",
    "sg:province":"NSW",
    "sg:tags":[
        "window",
        "aluminium"
    ],
    "wof:name":"HMS Glass & Glazing Pty Ltd",
    "wof:placetype":"venue"
},
  "geometry": {"coordinates":[150.87977600100001,-33.9288749695],"type":"Point"}
}