{
  "type": "Feature",
  "properties": {
    "addr:full":"4/ 13 Rocla Crt Toowoomba QLD 4350",
    "addr:housenumber":"/ 13",
    "addr:postcode":"4350",
    "addr:street":"Rocla Crt",
    "iso:country":"AU",
    "sg:address":"4/ 13 Rocla Crt",
    "sg:city":"Toowoomba",
    "sg:classifiers":[
        {
            "category":"Professional",
            "subcategory":"Engineering",
            "type":"Services"
        }
    ],
    "sg:phone":"+61 7 4696 9764",
    "sg:postcode":"4350",
    "sg:province":"QLD",
    "sg:tags":[
        "engineer"
    ],
    "wof:name":"Macfab Pty Ltd",
    "wof:placetype":"venue"
},
  "geometry": {"coordinates":[151.91021699999999,-27.553934],"type":"Point"}
}