{
  "type": "Feature",
  "properties": {
    "iso:country":"AU",
    "sg:address":"101 Williamson Rd",
    "sg:city":"Ingleburn",
    "sg:classifiers":[
        {
            "category":"Education",
            "subcategory":"School",
            "type":"Public Place"
        }
    ],
    "sg:phone":"+61 1300 764 191",
    "sg:postcode":"2565",
    "sg:province":"NSW",
    "sg:tags":[
        "supply"
    ],
    "wof:name":"Endura Bags",
    "wof:placetype":"venue"
},
  "geometry": {"coordinates":[150.84991455100001,-33.9982833862],"type":"Point"}
}