{
  "type": "Feature",
  "properties": {
    "iso:country":"AU",
    "sg:address":"90 Mayona Rd",
    "sg:city":"Montmorency",
    "sg:classifiers":[
        {
            "category":"Education",
            "subcategory":"School",
            "type":"Public Place"
        }
    ],
    "sg:phone":"+61 3 9435 8474",
    "sg:postcode":"3094",
    "sg:province":"VIC",
    "sg:tags":[
        "co-educational"
    ],
    "wof:name":"St Francis Xavier's Primary",
    "wof:placetype":"venue"
},
  "geometry": {"coordinates":[145.12669372600001,-37.7154273987],"type":"Point"}
}