{
  "type": "Feature",
  "properties": {
    "iso:country":"AU",
    "sg:address":"139 March St",
    "sg:city":"Orange",
    "sg:classifiers":[
        {
            "category":"Travel",
            "subcategory":"Hostel",
            "type":"Entertainment"
        }
    ],
    "sg:phone":"+61 2 6362 9266",
    "sg:postcode":"2800",
    "sg:province":"NSW",
    "sg:tags":[
        "home"
    ],
    "wof:name":"Orange Community Accommodation Service",
    "wof:placetype":"venue"
},
  "geometry": {"coordinates":[149.10179138199999,-33.2796936035],"type":"Point"}
}