{
  "type": "Feature",
  "properties": {
    "addr:full":"12 Dewer Ave Ridgehaven SA 5097",
    "addr:housenumber":"12",
    "addr:postcode":"5097",
    "addr:street":"Dewer Ave",
    "iso:country":"AU",
    "sg:address":"12 Dewer Ave",
    "sg:city":"Ridgehaven",
    "sg:classifiers":[
        {
            "category":"Retail",
            "subcategory":"Auto Repair",
            "type":"Services"
        }
    ],
    "sg:phone":"+61 8 8264 7023",
    "sg:postcode":"5097",
    "sg:province":"SA",
    "sg:tags":[
        "repairer",
        "motor",
        "engineer"
    ],
    "wof:name":"Golden Grove Motors",
    "wof:placetype":"venue"
},
  "geometry": {"coordinates":[138.695770264,-34.8252792358],"type":"Point"}
}