{
  "type": "Feature",
  "properties": {
    "addr:full":"76 Elizabeth Bay Rd Elizabeth Bay NSW 2011",
    "addr:housenumber":"76",
    "addr:postcode":"2011",
    "addr:street":"Elizabeth Bay Rd",
    "iso:country":"AU",
    "sg:address":"76 Elizabeth Bay Rd",
    "sg:city":"Elizabeth Bay",
    "sg:classifiers":[
        {
            "category":"Deli",
            "type":"Food & Drink"
        }
    ],
    "sg:phone":"+61 2 9358 4304",
    "sg:postcode":"2011",
    "sg:province":"NSW",
    "sg:tags":[
        "delicatessen"
    ],
    "wof:name":"Elizabeth Bay Deli",
    "wof:placetype":"venue"
},
  "geometry": {"coordinates":[151.22836303700001,-33.8719940186],"type":"Point"}
}