{
  "type": "Feature",
  "properties": {
    "iso:country":"AU",
    "sg:address":"132 Auburn Rd",
    "sg:city":"Birrong",
    "sg:classifiers":[
        {
            "category":"Social Services",
            "subcategory":"Child Care",
            "type":"Services"
        }
    ],
    "sg:phone":"+61 2 9645 2895",
    "sg:postcode":"2143",
    "sg:province":"NSW",
    "wof:name":"Birrong After School Centre Inc",
    "wof:placetype":"venue"
},
  "geometry": {"coordinates":[151.02107238799999,-33.8956947327],"type":"Point"}
}