{
  "type": "Feature",
  "properties": {
    "addr:full":"1- 9 Bennett St Bacchus Marsh VIC 3340",
    "addr:housenumber":"9",
    "addr:postcode":"3340",
    "addr:street":"Bennett St",
    "iso:country":"AU",
    "sg:address":"1- 9 Bennett St",
    "sg:city":"Bacchus Marsh",
    "sg:classifiers":[
        {
            "category":"Food & Beverages",
            "subcategory":"Supermarket",
            "type":"Retail Goods"
        }
    ],
    "sg:phone":"+61 3 5367 3388",
    "sg:postcode":"3340",
    "sg:province":"VIC",
    "sg:tags":[
        "grocery",
        "store"
    ],
    "wof:name":"Bacchus Marsh Foodworks Mega Fresh",
    "wof:placetype":"venue"
},
  "geometry": {"coordinates":[144.438751,-37.674091],"type":"Point"}
}