{
  "type": "Feature",
  "properties": {
    "iso:country":"AU",
    "sg:address":"181 Lawson St",
    "sg:city":"Redfern",
    "sg:classifiers":[
        {
            "category":"Wholesale",
            "subcategory":"Furniture",
            "type":"Manufacturing & Wholesale Goods"
        }
    ],
    "sg:phone":"+61 2 9698 7555",
    "sg:postcode":"2016",
    "sg:province":"NSW",
    "sg:tags":[
        "wholesaler",
        "mfrs"
    ],
    "wof:name":"PGR Furniture",
    "wof:placetype":"venue"
},
  "geometry": {"coordinates":[151.19664001500001,-33.8911132812],"type":"Point"}
}