{
  "type": "Feature",
  "properties": {
    "addr:full":"602 Gilston Rd Gilston QLD 4211",
    "addr:housenumber":"602",
    "addr:postcode":"4211",
    "addr:street":"Gilston Rd",
    "iso:country":"AU",
    "sg:address":"602 Gilston Rd",
    "sg:city":"Gilston",
    "sg:classifiers":[
        {
            "category":"Building & Trades",
            "subcategory":"Landscaping Services",
            "type":"Services"
        }
    ],
    "sg:phone":"+61 414 533 302",
    "sg:postcode":"4211",
    "sg:province":"QLD",
    "sg:tags":[
        "horticultural",
        "consultant"
    ],
    "wof:name":"Beth Cooling Horticulture Services",
    "wof:placetype":"venue"
},
  "geometry": {"coordinates":[153.30726623499999,-28.0312786102],"type":"Point"}
}