{
  "type": "Feature",
  "properties": {
    "addr:full":"32 Charles St South Perth WA 6151",
    "addr:housenumber":"32",
    "addr:postcode":"6151",
    "addr:street":"Charles St South",
    "iso:country":"AU",
    "sg:address":"32 Charles St",
    "sg:city":"South Perth",
    "sg:classifiers":[
        {
            "category":"Professional",
            "subcategory":"Accounting & Tax Preparation",
            "type":"Services"
        }
    ],
    "sg:phone":"+61 8 9367 6588",
    "sg:postcode":"6151",
    "sg:province":"WA",
    "sg:tags":[
        "accountant",
        "auditor"
    ],
    "wof:name":"Morris A C & Co",
    "wof:placetype":"venue"
},
  "geometry": {"coordinates":[115.85173,-31.976446],"type":"Point"}
}