{
  "type": "Feature",
  "properties": {
    "addr:full":"186 Gipps St Gwynneville NSW 2500",
    "addr:housenumber":"186",
    "addr:postcode":"2500",
    "addr:street":"Gipps St",
    "iso:country":"AU",
    "sg:address":"186 Gipps St",
    "sg:city":"Gwynneville",
    "sg:classifiers":[
        {
            "category":"Government",
            "subcategory":"Post Office",
            "type":"Public Place"
        }
    ],
    "sg:phone":"+61 2 4229 4190",
    "sg:postcode":"2500",
    "sg:province":"NSW",
    "sg:tags":[
        "postal"
    ],
    "wof:name":"Australia Post",
    "wof:placetype":"venue"
},
  "geometry": {"coordinates":[150.886673,-34.416077],"type":"Point"}
}