{
  "type": "Feature",
  "properties": {
    "addr:full":"Bay 2/15 Advantage Ave Gateway Industrial Park Morisset NSW 2264",
    "addr:housenumber":"/ 15",
    "addr:postcode":"2264",
    "addr:street":"Advantage Ave;Industrial",
    "iso:country":"AU",
    "sg:address":"Bay 2/15 Advantage Ave",
    "sg:city":"Gateway Industrial Park Morisset",
    "sg:classifiers":[
        {
            "category":"Retail",
            "subcategory":"Auto Repair",
            "type":"Services"
        }
    ],
    "sg:phone":"+61 2 4973 1212",
    "sg:postcode":"2264",
    "sg:province":"NSW",
    "sg:tags":[
        "muffler",
        "exhaust",
        "system"
    ],
    "wof:name":"Grant Roberts Automotive",
    "wof:placetype":"venue"
},
  "geometry": {"coordinates":[151.471451,-33.118099],"type":"Point"}
}