{
  "type": "Feature",
  "properties": {
    "iso:country":"AU",
    "sg:address":"Factory 14, No. 41 Bennet St",
    "sg:city":"Dandenong",
    "sg:classifiers":[
        {
            "category":"Wholesale",
            "subcategory":"Machinery & Supplies",
            "type":"Manufacturing & Wholesale Goods"
        }
    ],
    "sg:phone":"+61 3 9793 7033",
    "sg:postcode":"3175",
    "sg:province":"VIC",
    "sg:tags":[
        "rigging",
        "equipment",
        "hoisting"
    ],
    "wof:name":"Command Cranes Pty Ltd",
    "wof:placetype":"venue"
},
  "geometry": {"coordinates":[145.19943237300001,-37.9881896973],"type":"Point"}
}