{
  "type": "Feature",
  "properties": {
    "addr:full":"529 Whitehorse Rd Surrey Hills VIC 3127",
    "addr:housenumber":"529",
    "addr:postcode":"3127",
    "addr:street":"Whitehorse Rd",
    "iso:country":"AU",
    "sg:address":"529 Whitehorse Rd",
    "sg:city":"Surrey Hills",
    "sg:classifiers":[
        {
            "category":"Building & Trades",
            "subcategory":"Construction",
            "type":"Services"
        }
    ],
    "sg:phone":"+61 3 9888 5635",
    "sg:postcode":"3127",
    "sg:province":"VIC",
    "sg:tags":[
        "polishing",
        "sanding",
        "floor"
    ],
    "wof:name":"Riband Floors",
    "wof:placetype":"venue"
},
  "geometry": {"coordinates":[145.091873169,-37.8139572144],"type":"Point"}
}