{
  "type": "Feature",
  "properties": {
    "addr:full":"Unit 7/ 1 Casey St Aitkenvale QLD 4814",
    "addr:housenumber":"1",
    "addr:postcode":"4814",
    "addr:street":"Casey St",
    "iso:country":"AU",
    "sg:address":"Unit 7/ 1 Casey St",
    "sg:city":"Aitkenvale",
    "sg:classifiers":[
        {
            "category":"Education",
            "subcategory":"University",
            "type":"Public Place"
        }
    ],
    "sg:phone":"+61 7 4779 0550",
    "sg:postcode":"4814",
    "sg:province":"QLD",
    "sg:tags":[
        "educational",
        "organisation",
        "cultural"
    ],
    "wof:name":"University Of The Third Age",
    "wof:placetype":"venue"
},
  "geometry": {"coordinates":[146.767517,-19.294844],"type":"Point"}
}