{
  "type": "Feature",
  "properties": {
    "iso:country":"AU",
    "sg:address":"3 Darnley St",
    "sg:city":"East Gordon",
    "sg:classifiers":[
        {
            "category":"Professional",
            "subcategory":"Management & Consulting",
            "type":"Services"
        }
    ],
    "sg:phone":"+61 2 9418 2623",
    "sg:postcode":"2072",
    "sg:province":"NSW",
    "sg:tags":[
        "consultant",
        "business"
    ],
    "wof:name":"Valufacture Solutions Pty Ltd",
    "wof:placetype":"venue"
},
  "geometry": {"coordinates":[151.15777587900001,-33.7478218079],"type":"Point"}
}