{
  "type": "Feature",
  "properties": {
    "addr:full":"Cnr Cemetary & Whitehill Rds Raceview QLD 4305",
    "addr:postcode":"4305",
    "iso:country":"AU",
    "sg:address":"Cnr Cemetary & Whitehill Rds",
    "sg:city":"Raceview",
    "sg:classifiers":[
        {
            "category":"Professional",
            "subcategory":"Engineering",
            "type":"Services"
        }
    ],
    "sg:phone":"+61 7 3812 1341",
    "sg:postcode":"4305",
    "sg:province":"QLD",
    "sg:tags":[
        "engineer",
        "mechanical"
    ],
    "wof:name":"Ipswich City Mechanical",
    "wof:placetype":"venue"
},
  "geometry": {"coordinates":[152.786834717,-27.6423206329],"type":"Point"}
}