{
  "type": "Feature",
  "properties": {
    "addr:full":"8 Greet St West End QLD 4101",
    "addr:housenumber":"8",
    "addr:postcode":"4101",
    "addr:street":"Greet St",
    "iso:country":"AU",
    "sg:address":"8 Greet St",
    "sg:city":"West End",
    "sg:classifiers":[
        {
            "category":"Home & Garden",
            "subcategory":"Building Materials",
            "type":"Retail Goods"
        }
    ],
    "sg:phone":"+61 7 3844 6457",
    "sg:postcode":"4101",
    "sg:province":"QLD",
    "sg:tags":[
        "lawn",
        "cutting",
        "maintenance"
    ],
    "wof:name":"Eaton Property Maintenance",
    "wof:placetype":"venue"
},
  "geometry": {"coordinates":[153.003448486,-27.4813232422],"type":"Point"}
}