{
  "type": "Feature",
  "properties": {
    "iso:country":"AU",
    "sg:address":"9 Lees Rd",
    "sg:city":"Kingsgrove",
    "sg:classifiers":[
        {
            "category":"Professional",
            "subcategory":"Art Services",
            "type":"Services"
        }
    ],
    "sg:phone":"+61 2 9740 3362",
    "sg:postcode":"2208",
    "sg:province":"NSW",
    "sg:tags":[
        "graphic",
        "designer"
    ],
    "wof:name":"Lang Graphix",
    "wof:placetype":"venue"
},
  "geometry": {"coordinates":[151.085892,-33.936459],"type":"Point"}
}