{
  "type": "Feature",
  "properties": {
    "addr:full":"258 Wallarah Rd Kanwal NSW 2259",
    "addr:housenumber":"258",
    "addr:postcode":"2259",
    "addr:street":"Wallarah Rd",
    "iso:country":"AU",
    "sg:address":"258 Wallarah Rd",
    "sg:city":"Kanwal",
    "sg:classifiers":[
        {
            "category":"Communications",
            "subcategory":"Film & Video Production",
            "type":"Services"
        }
    ],
    "sg:phone":"+61 2 4393 1211",
    "sg:postcode":"2259",
    "sg:province":"NSW",
    "sg:tags":[
        "dvd",
        "library"
    ],
    "wof:name":"Kanwal Video",
    "wof:placetype":"venue"
},
  "geometry": {"coordinates":[151.48989868199999,-33.2523651123],"type":"Point"}
}