{
  "type": "Feature",
  "properties": {
    "addr:full":"Municipal Buildings Sussex St Linton VIC 3360",
    "addr:postcode":"3360",
    "addr:street":"Sussex St",
    "iso:country":"AU",
    "sg:address":"Municipal Buildings Sussex St",
    "sg:city":"Linton",
    "sg:classifiers":[
        {
            "category":"Social Services",
            "subcategory":"Child Care",
            "type":"Services"
        }
    ],
    "sg:phone":"+61 3 5344 7201",
    "sg:postcode":"3360",
    "sg:province":"VIC",
    "sg:tags":[
        "support",
        "health"
    ],
    "wof:name":"Maternal & Child Health Centres",
    "wof:placetype":"venue"
},
  "geometry": {"coordinates":[143.56536865199999,-37.6829223633],"type":"Point"}
}