{
  "type": "Feature",
  "properties": {
    "iso:country":"AU",
    "sg:address":"196 Grays Point Rd",
    "sg:city":"Grays Point",
    "sg:classifiers":[
        {
            "category":"Utilities",
            "subcategory":"Electric",
            "type":"Services"
        }
    ],
    "sg:phone":"+61 418 113 320",
    "sg:postcode":"2232",
    "sg:province":"NSW",
    "sg:tags":[
        "electrical",
        "contractor"
    ],
    "wof:name":"Dare Mark Electrical Pty Ltd",
    "wof:placetype":"venue"
},
  "geometry": {"coordinates":[151.07342529300001,-34.0586891174],"type":"Point"}
}