{
  "type": "Feature",
  "properties": {
    "iso:country":"AU",
    "sg:address":"811 Gympie Rd",
    "sg:city":"Chermside",
    "sg:classifiers":[
        {
            "category":"Real Estate",
            "subcategory":"Real Estate Agent",
            "type":"Services"
        }
    ],
    "sg:phone":"+61 7 3350 9888",
    "sg:postcode":"4032",
    "sg:province":"QLD",
    "wof:name":"RE/MAX Premier",
    "wof:placetype":"venue"
},
  "geometry": {"coordinates":[153.031403,-27.387369],"type":"Point"}
}