{
  "type": "Feature",
  "properties": {
    "addr:full":"17 Keatley Crt Mirrabooka WA 6061",
    "addr:housenumber":"17",
    "addr:postcode":"6061",
    "addr:street":"Keatley Crt",
    "iso:country":"AU",
    "sg:address":"17 Keatley Crt",
    "sg:city":"Mirrabooka",
    "sg:classifiers":[
        {
            "category":"Utilities",
            "subcategory":"Refuse",
            "type":"Services"
        }
    ],
    "sg:phone":"+61 8 9399 8860",
    "sg:postcode":"6061",
    "sg:province":"WA",
    "sg:tags":[
        "remover",
        "rubbish"
    ],
    "wof:name":"Russell's Rubbish & Garden Bags",
    "wof:placetype":"venue"
},
  "geometry": {"coordinates":[115.876152039,-31.8571128845],"type":"Point"}
}