{
  "type": "Feature",
  "properties": {
    "addr:full":"70 High St Cundletown NSW 2430",
    "addr:housenumber":"70",
    "addr:postcode":"2430",
    "addr:street":"High St",
    "iso:country":"AU",
    "sg:address":"70 High St",
    "sg:city":"Cundletown",
    "sg:classifiers":[
        {
            "category":"Personal",
            "subcategory":"Beauty Salon",
            "type":"Services"
        }
    ],
    "sg:phone":"+61 2 6553 9787",
    "sg:postcode":"2430",
    "sg:province":"NSW",
    "sg:tags":[
        "hairdresser"
    ],
    "wof:name":"Economy Cut Hair Salon",
    "wof:placetype":"venue"
},
  "geometry": {"coordinates":[152.458313,-31.909136],"type":"Point"}
}