{
  "type": "Feature",
  "properties": {
    "addr:full":"10 Marine Pde Southport QLD 4215",
    "addr:housenumber":"10",
    "addr:postcode":"4215",
    "addr:street":"Marine Pde",
    "iso:country":"AU",
    "sg:address":"10 Marine Pde",
    "sg:city":"Southport",
    "sg:classifiers":[
        {
            "category":"Recreation",
            "subcategory":"Water Park",
            "type":"Entertainment"
        }
    ],
    "sg:phone":"+61 412 114 106",
    "sg:postcode":"4215",
    "sg:province":"QLD",
    "sg:tags":[
        "resort",
        "skiing"
    ],
    "wof:name":"Rogers J G",
    "wof:placetype":"venue"
},
  "geometry": {"coordinates":[153.41793823200001,-27.9715976715],"type":"Point"}
}