{
  "type": "Feature",
  "properties": {
    "addr:full":"53 Volute St Geraldton WA 6530",
    "addr:housenumber":"53",
    "addr:postcode":"6530",
    "addr:street":"Volute St",
    "iso:country":"AU",
    "sg:address":"53 Volute St",
    "sg:city":"Geraldton",
    "sg:classifiers":[
        {
            "category":"Professional",
            "subcategory":"Business Services",
            "type":"Services"
        }
    ],
    "sg:phone":"+61 8 9938 2063",
    "sg:postcode":"6530",
    "sg:province":"WA",
    "sg:tags":[
        "drafting"
    ],
    "wof:name":"Sunset Design & Drafting",
    "wof:placetype":"venue"
},
  "geometry": {"coordinates":[114.620643616,-28.7216777802],"type":"Point"}
}