{
  "type": "Feature",
  "properties": {
    "iso:country":"AU",
    "sg:address":"76 Banyule Rd",
    "sg:city":"Rosanna",
    "sg:classifiers":[
        {
            "category":"Building & Trades",
            "subcategory":"Construction",
            "type":"Services"
        }
    ],
    "sg:phone":"+61 401 757 185",
    "sg:postcode":"3084",
    "sg:province":"VIC",
    "sg:tags":[
        "bitumen",
        "paving",
        "asphalt"
    ],
    "wof:name":"Enviro Pave",
    "wof:placetype":"venue"
},
  "geometry": {"coordinates":[145.080245972,-37.7423553467],"type":"Point"}
}