{
  "type": "Feature",
  "properties": {
    "addr:full":"Four Mile Rd Brae-Meadows QLD 4850",
    "addr:postcode":"4850",
    "addr:street":"Mile Rd",
    "iso:country":"AU",
    "sg:address":"Four Mile Rd",
    "sg:city":"Brae-Meadows",
    "sg:classifiers":[
        {
            "category":"Farming",
            "subcategory":"Farm",
            "type":"Manufacturing & Wholesale Goods"
        }
    ],
    "sg:phone":"+61 7 4777 7214",
    "sg:postcode":"4850",
    "sg:province":"QLD",
    "sg:tags":[
        "farmer"
    ],
    "wof:name":"Cardillo A & J M",
    "wof:placetype":"venue"
},
  "geometry": {"coordinates":[146.20782470699999,-18.651676178],"type":"Point"}
}