{
  "type": "Feature",
  "properties": {
    "iso:country":"AU",
    "sg:address":"188 Torrens Rd",
    "sg:city":"Croydon",
    "sg:classifiers":[
        {
            "category":"Health Services",
            "subcategory":"Health Practitioner",
            "type":"Services"
        }
    ],
    "sg:phone":"+61 8 8346 3495",
    "sg:postcode":"5008",
    "sg:province":"SA",
    "sg:tags":[
        "physiotherapist"
    ],
    "wof:name":"Supple, Brendon",
    "wof:placetype":"venue"
},
  "geometry": {"coordinates":[138.570099,-34.888084],"type":"Point"}
}