{
  "type": "Feature",
  "properties": {
    "iso:country":"AU",
    "sg:address":"Cnr Throssel & Forrest Circle Rds",
    "sg:city":"South Hedland",
    "sg:classifiers":[
        {
            "category":"Retail",
            "subcategory":"Auto Repair",
            "type":"Services"
        }
    ],
    "sg:phone":"+61 8 9172 1680",
    "sg:postcode":"6722",
    "sg:province":"WA",
    "sg:tags":[
        "repairer",
        "motor",
        "engineer"
    ],
    "wof:name":"BP Car Care",
    "wof:placetype":"venue"
},
  "geometry": {"coordinates":[118.601318359,-20.4082012177],"type":"Point"}
}