{
  "type": "Feature",
  "properties": {
    "iso:country":"AU",
    "sg:address":"Unit 1, 160 Station St",
    "sg:city":"Penrith",
    "sg:classifiers":[
        {
            "category":"Autos & Motor Vehicles",
            "subcategory":"Auto Supplies",
            "type":"Retail Goods"
        }
    ],
    "sg:phone":"+61 2 4731 3277",
    "sg:postcode":"2750",
    "sg:province":"NSW",
    "sg:tags":[
        "wheel",
        "automotive",
        "rim"
    ],
    "wof:name":"JAXQuickfit Tyres",
    "wof:placetype":"venue"
},
  "geometry": {"coordinates":[150.673065186,-33.7462005615],"type":"Point"}
}