{
  "type": "Feature",
  "properties": {
    "iso:country":"AU",
    "sg:address":"13 Arnott St",
    "sg:city":"Edgeworth",
    "sg:classifiers":[
        {
            "category":"Professional",
            "subcategory":"Accounting & Tax Preparation",
            "type":"Services"
        }
    ],
    "sg:phone":"+61 2 4922 4200",
    "sg:postcode":"2285",
    "sg:province":"NSW",
    "sg:tags":[
        "consultant",
        "taxation"
    ],
    "wof:name":"Taggart Partners",
    "wof:placetype":"venue"
},
  "geometry": {"coordinates":[151.622589111,-32.924747467],"type":"Point"}
}