{
  "type": "Feature",
  "properties": {
    "addr:full":"Unit 3, 8 Collins Pl Rapid Creek NT 0810",
    "addr:housenumber":"8",
    "addr:postcode":"nt 0810",
    "addr:street":"Collins Pl",
    "iso:country":"AU",
    "sg:address":"Unit 3, 8 Collins Pl",
    "sg:city":"Rapid Creek",
    "sg:classifiers":[
        {
            "category":"Real Estate",
            "subcategory":"Real Estate Agent",
            "type":"Services"
        }
    ],
    "sg:phone":"+61 8 8948 3167",
    "sg:postcode":"0810",
    "sg:province":"NT",
    "sg:tags":[
        "export"
    ],
    "wof:name":"Jonathon Jampinjimpa Moses Imports Exports",
    "wof:placetype":"venue"
},
  "geometry": {"coordinates":[130.857589722,-12.3832998276],"type":"Point"}
}