{
  "type": "Feature",
  "properties": {
    "addr:full":"PO Box 806 Inverell NSW 2360",
    "addr:postcode":"2360",
    "iso:country":"AU",
    "sg:address":"PO Box 806",
    "sg:city":"Inverell",
    "sg:classifiers":[
        {
            "category":"Real Estate",
            "subcategory":"Real Estate Services",
            "type":"Services"
        }
    ],
    "sg:phone":"+61 2 6722 3221",
    "sg:postcode":"2360",
    "sg:province":"NSW",
    "sg:tags":[
        "valuer"
    ],
    "wof:name":"David W King Valuations",
    "wof:placetype":"venue"
},
  "geometry": {"coordinates":[151.113555908,-29.776309967],"type":"Point"}
}