{
  "type": "Feature",
  "properties": {
    "addr:full":"269 Great Eastern Hwy Belmont WA 6104",
    "addr:housenumber":"269",
    "addr:postcode":"6104",
    "addr:street":"Great Eastern Hwy",
    "iso:country":"AU",
    "sg:address":"269 Great Eastern Hwy",
    "sg:city":"Belmont",
    "sg:classifiers":[
        {
            "category":"Professional",
            "subcategory":"Printing & Photocopies",
            "type":"Services"
        }
    ],
    "sg:phone":"+61 8 9479 3558",
    "sg:postcode":"6104",
    "sg:province":"WA",
    "sg:tags":[
        "photocopier"
    ],
    "wof:name":"A A Copymate Rentals",
    "wof:placetype":"venue"
},
  "geometry": {"coordinates":[115.92936706499999,-31.9397697449],"type":"Point"}
}