{
  "type": "Feature",
  "properties": {
    "addr:full":"29 Lyons St Rosedale VIC 3847",
    "addr:housenumber":"29",
    "addr:postcode":"3847",
    "addr:street":"Lyons St",
    "iso:country":"AU",
    "sg:address":"29 Lyons St",
    "sg:city":"Rosedale",
    "sg:classifiers":[
        {
            "category":"Travel",
            "subcategory":"Hotels & Motels",
            "type":"Entertainment"
        }
    ],
    "sg:phone":"+61 3 5199 2504",
    "sg:postcode":"3847",
    "sg:province":"VIC",
    "sg:tags":[
        "accommodation"
    ],
    "wof:name":"Rosedale Hotel",
    "wof:placetype":"venue"
},
  "geometry": {"coordinates":[146.789794922,-38.1520881653],"type":"Point"}
}