{
  "type": "Feature",
  "properties": {
    "iso:country":"AU",
    "sg:address":"89e Briggs St",
    "sg:city":"Welshpool",
    "sg:classifiers":[
        {
            "category":"Professional",
            "subcategory":"Detective & Security Services",
            "type":"Services"
        }
    ],
    "sg:phone":"+61 414 440 798",
    "sg:postcode":"6106",
    "sg:province":"WA",
    "sg:tags":[
        "consultant",
        "system"
    ],
    "wof:name":"Logic Electrics Cranes & Hoists",
    "wof:placetype":"venue"
},
  "geometry": {"coordinates":[115.927032471,-31.9834880829],"type":"Point"}
}