{
  "type": "Feature",
  "properties": {
    "addr:full":"10/ 601 Upper Heidelberg Rd Heidelberg VIC 3084",
    "addr:housenumber":"10 / 601",
    "addr:postcode":"3084",
    "addr:street":"Upper Heidelberg Rd",
    "iso:country":"AU",
    "sg:address":"10/ 601 Upper Heidelberg Rd",
    "sg:city":"Heidelberg",
    "sg:classifiers":[
        {
            "category":"Health Services",
            "subcategory":"Chiropractor",
            "type":"Services"
        }
    ],
    "sg:phone":"+61 409 273 680",
    "sg:postcode":"3084",
    "sg:province":"VIC",
    "wof:name":"Discover Chiropractic",
    "wof:placetype":"venue"
},
  "geometry": {"coordinates":[145.057769775,-37.7469825745],"type":"Point"}
}