{
  "type": "Feature",
  "properties": {
    "addr:full":"172 Margaret St Toowoomba QLD 4350",
    "addr:housenumber":"172",
    "addr:postcode":"4350",
    "addr:street":"Margaret St",
    "iso:country":"AU",
    "sg:address":"172 Margaret St",
    "sg:city":"Toowoomba",
    "sg:classifiers":[
        {
            "category":"Travel",
            "subcategory":"Travel Agent",
            "type":"Entertainment"
        }
    ],
    "sg:phone":"+61 7 4632 4522",
    "sg:postcode":"4350",
    "sg:province":"QLD",
    "sg:tags":[
        "consultant"
    ],
    "wof:name":"Darling Downs Travel Travelscene American Express Travel Services",
    "wof:placetype":"venue"
},
  "geometry": {"coordinates":[151.95463599999999,-27.561287],"type":"Point"}
}