{
  "type": "Feature",
  "properties": {
    "addr:full":"51-53 Evans St Sunbury VIC 3429",
    "addr:housenumber":"51-53",
    "addr:postcode":"3429",
    "addr:street":"Evans St",
    "iso:country":"AU",
    "sg:address":"51-53 Evans St",
    "sg:city":"Sunbury",
    "sg:classifiers":[
        {
            "category":"Professional",
            "subcategory":"Employment Agencies",
            "type":"Services"
        }
    ],
    "sg:phone":"+61 3 9306 6699",
    "sg:postcode":"3429",
    "sg:province":"VIC",
    "wof:name":"Youth Project Employment & Training Services",
    "wof:placetype":"venue"
},
  "geometry": {"coordinates":[144.72857665999999,-37.5805053711],"type":"Point"}
}