{
  "type": "Feature",
  "properties": {
    "addr:full":"Belmont Private Hospital 1220 Creek Rd Carina QLD 4152",
    "addr:housenumber":"1220",
    "addr:postcode":"4152",
    "addr:street":"Creek Rd",
    "iso:country":"AU",
    "sg:address":"Belmont Private Hospital 1220 Creek Rd",
    "sg:city":"Carina",
    "sg:classifiers":[
        {
            "category":"Health Services",
            "subcategory":"Doctor",
            "type":"Services"
        }
    ],
    "sg:phone":"+61 411 516 313",
    "sg:postcode":"4152",
    "sg:province":"QLD",
    "sg:tags":[
        "medical",
        "practitioner"
    ],
    "wof:name":"Martin M J",
    "wof:placetype":"venue"
},
  "geometry": {"coordinates":[153.10061645499999,-27.4985122681],"type":"Point"}
}