{
  "type": "Feature",
  "properties": {
    "addr:full":"3 Patrick St Bothwell TAS 7030",
    "addr:housenumber":"3",
    "addr:postcode":"7030",
    "addr:street":"Patrick St",
    "iso:country":"AU",
    "sg:address":"3 Patrick St",
    "sg:city":"Bothwell",
    "sg:classifiers":[
        {
            "category":"Government",
            "subcategory":"Post Office",
            "type":"Public Place"
        }
    ],
    "sg:phone":"+61 3 6259 5609",
    "sg:postcode":"7030",
    "sg:province":"TAS",
    "sg:tags":[
        "postal"
    ],
    "wof:name":"Australia Post Offices",
    "wof:placetype":"venue"
},
  "geometry": {"coordinates":[147.00527954099999,-42.3819770813],"type":"Point"}
}