{
  "type": "Feature",
  "properties": {
    "addr:full":"PO Box 824 Wangaratta VIC 3677",
    "addr:postcode":"3677",
    "iso:country":"AU",
    "sg:address":"PO Box 824",
    "sg:city":"Wangaratta",
    "sg:classifiers":[
        {
            "category":"Home & Garden",
            "subcategory":"Household Appliances",
            "type":"Retail Goods"
        }
    ],
    "sg:phone":"+61 418 372 228",
    "sg:postcode":"3677",
    "sg:province":"VIC",
    "sg:tags":[
        "equipment",
        "gas"
    ],
    "wof:name":"Riverina Boiler & Combustion Service Pty Ltd",
    "wof:placetype":"venue"
},
  "geometry": {"coordinates":[146.318527222,-36.3704109192],"type":"Point"}
}