{
  "type": "Feature",
  "properties": {
    "addr:full":"Hopkins St Footscray VIC 3011",
    "addr:postcode":"3011",
    "addr:street":"Hopkins St",
    "iso:country":"AU",
    "sg:address":"Hopkins St",
    "sg:city":"Footscray",
    "sg:classifiers":[
        {
            "category":"Building & Trades",
            "subcategory":"Landscaping Services",
            "type":"Services"
        }
    ],
    "sg:phone":"+61 3 9687 1205",
    "sg:postcode":"3011",
    "sg:province":"VIC",
    "sg:tags":[
        "market"
    ],
    "wof:name":"Footscray Market",
    "wof:placetype":"venue"
},
  "geometry": {"coordinates":[144.89970398,-37.7997970581],"type":"Point"}
}