{
  "type": "Feature",
  "properties": {
    "addr:full":"Unit 5, 25 Alliance Ave Morisset NSW 2264",
    "addr:housenumber":"25",
    "addr:postcode":"2264",
    "addr:street":"Alliance Ave",
    "iso:country":"AU",
    "sg:address":"Unit 5, 25 Alliance Ave",
    "sg:city":"Morisset",
    "sg:classifiers":[
        {
            "category":"Transit Center",
            "subcategory":"Freight",
            "type":"Transportation"
        }
    ],
    "sg:phone":"+61 2 4973 5352",
    "sg:postcode":"2264",
    "sg:province":"NSW",
    "sg:tags":[
        "forklift",
        "truck"
    ],
    "wof:name":"Lake Macquarie Forklift Services",
    "wof:placetype":"venue"
},
  "geometry": {"coordinates":[151.531082,-33.113358],"type":"Point"}
}