{
  "type": "Feature",
  "properties": {
    "iso:country":"AU",
    "sg:address":"57 Indi Ave",
    "sg:city":"Red Cliffs",
    "sg:classifiers":[
        {
            "category":"Professional",
            "subcategory":"Computer Services",
            "type":"Services"
        }
    ],
    "sg:phone":"+61 3 5024 3072",
    "sg:postcode":"3496",
    "sg:province":"VIC",
    "sg:tags":[
        "repairs",
        "upgrade",
        "equipment"
    ],
    "wof:name":"Red Cliffs Technology Services",
    "wof:placetype":"venue"
},
  "geometry": {"coordinates":[142.189056397,-34.3069458008],"type":"Point"}
}