{
  "type": "Feature",
  "properties": {
    "addr:full":"Suite 10/ 169 Unley Rd Unley SA 5061",
    "addr:housenumber":"10 / 169",
    "addr:postcode":"5061",
    "addr:street":"Unley Rd",
    "iso:country":"AU",
    "sg:address":"Suite 10/ 169 Unley Rd",
    "sg:city":"Unley",
    "sg:classifiers":[
        {
            "category":"Health Services",
            "subcategory":"Dentist",
            "type":"Services"
        }
    ],
    "sg:phone":"+61 8 8271 0039",
    "sg:postcode":"5061",
    "sg:province":"SA",
    "wof:name":"The Smile Whitening Centre",
    "wof:placetype":"venue"
},
  "geometry": {"coordinates":[138.607543945,-34.9503364563],"type":"Point"}
}