{
  "type": "Feature",
  "properties": {
    "iso:country":"AU",
    "sg:address":"18 Daniel St",
    "sg:city":"Caloundra",
    "sg:classifiers":[
        {
            "category":"Retail",
            "subcategory":"Repair Shop",
            "type":"Services"
        }
    ],
    "sg:phone":"+61 7 5491 4852",
    "sg:postcode":"4551",
    "sg:province":"QLD",
    "sg:tags":[
        "windscreen"
    ],
    "wof:name":"Caloundra Crash Repairs",
    "wof:placetype":"venue"
},
  "geometry": {"coordinates":[153.10905456500001,-26.7936973572],"type":"Point"}
}