{
  "type": "Feature",
  "properties": {
    "iso:country":"AU",
    "sg:address":"303 Murray St",
    "sg:city":"Colac",
    "sg:classifiers":[
        {
            "category":"Autos & Motor Vehicles",
            "subcategory":"Fuel & Gas Station",
            "type":"Retail Goods"
        }
    ],
    "sg:phone":"+61 3 5231 3000",
    "sg:postcode":"3250",
    "sg:province":"VIC",
    "wof:name":"Mobil Enstop",
    "wof:placetype":"venue"
},
  "geometry": {"coordinates":[143.57933,-38.338593],"type":"Point"}
}