{
  "type": "Feature",
  "properties": {
    "addr:full":"171 Barker St Castlemaine VIC 3450",
    "addr:housenumber":"171",
    "addr:postcode":"3450",
    "addr:street":"Barker St",
    "iso:country":"AU",
    "sg:address":"171 Barker St",
    "sg:city":"Castlemaine",
    "sg:classifiers":[
        {
            "category":"Professional",
            "subcategory":"Accounting & Tax Preparation",
            "type":"Services"
        }
    ],
    "sg:phone":"+61 3 5472 2415",
    "sg:postcode":"3450",
    "sg:province":"VIC",
    "sg:tags":[
        "accountant",
        "auditor"
    ],
    "wof:name":"Timmins J B",
    "wof:placetype":"venue"
},
  "geometry": {"coordinates":[144.22198486299999,-37.0486412048],"type":"Point"}
}