{
  "type": "Feature",
  "properties": {
    "addr:full":"Clunes-Learmonth Rd Coghills Creek VIC 3364",
    "addr:postcode":"3364",
    "addr:street":"Clunes-Learmonth Rd",
    "iso:country":"AU",
    "sg:address":"Clunes-Learmonth Rd",
    "sg:city":"Coghills Creek",
    "sg:classifiers":[
        {
            "category":"Farming",
            "subcategory":"Vineyard",
            "type":"Manufacturing & Wholesale Goods"
        }
    ],
    "sg:phone":"+61 3 5343 4245",
    "sg:postcode":"3364",
    "sg:province":"VIC",
    "sg:tags":[
        "winery"
    ],
    "wof:name":"Eastern Peake Vineyard",
    "wof:placetype":"venue"
},
  "geometry": {"coordinates":[143.86375427199999,-37.3807983398],"type":"Point"}
}