{
  "type": "Feature",
  "properties": {
    "iso:country":"AU",
    "sg:address":"251 Gold Coast Hwy",
    "sg:city":"Labrador",
    "sg:classifiers":[
        {
            "category":"Farming",
            "subcategory":"Dairy Farm",
            "type":"Manufacturing & Wholesale Goods"
        }
    ],
    "sg:phone":"+61 7 5594 0581",
    "sg:postcode":"4215",
    "sg:province":"QLD",
    "sg:tags":[
        "wholesaler",
        "product",
        "mfrs"
    ],
    "wof:name":"T.R. Dairy Product Distributors",
    "wof:placetype":"venue"
},
  "geometry": {"coordinates":[153.41903686500001,-27.9703407288],"type":"Point"}
}