{
  "type": "Feature",
  "properties": {
    "iso:country":"AU",
    "sg:address":"Belconnen Community Centre Swanson Crt",
    "sg:city":"Belconnen",
    "sg:classifiers":[
        {
            "category":"Arts & Performance",
            "subcategory":"Theater",
            "type":"Entertainment"
        }
    ],
    "sg:phone":"+61 2 6264 0232",
    "sg:postcode":"2616",
    "sg:province":"ACT",
    "sg:tags":[
        "theatre"
    ],
    "wof:name":"Belconnen Theatre",
    "wof:placetype":"venue"
},
  "geometry": {"coordinates":[149.069015503,-35.2388839722],"type":"Point"}
}