{
  "type": "Feature",
  "properties": {
    "addr:full":"52 Claremont Ave Greenacre NSW 2190",
    "addr:housenumber":"52",
    "addr:postcode":"2190",
    "addr:street":"Claremont Ave",
    "iso:country":"AU",
    "sg:address":"52 Claremont Ave",
    "sg:city":"Greenacre",
    "sg:classifiers":[
        {
            "category":"Landmark",
            "subcategory":"Scenic View",
            "type":"Public Place"
        }
    ],
    "sg:phone":"+61 2 9559 4586",
    "sg:postcode":"2190",
    "sg:province":"NSW",
    "sg:tags":[
        "staircase",
        "handrail"
    ],
    "wof:name":"ABC Balustrade",
    "wof:placetype":"venue"
},
  "geometry": {"coordinates":[151.038467,-33.901554],"type":"Point"}
}