{
  "type": "Feature",
  "properties": {
    "addr:full":"11 Aristoc Rd Glen Waverley VIC 3150",
    "addr:housenumber":"11",
    "addr:postcode":"3150",
    "addr:street":"Aristoc Rd",
    "iso:country":"AU",
    "sg:address":"11 Aristoc Rd",
    "sg:city":"Glen Waverley",
    "sg:classifiers":[
        {
            "category":"Wholesale",
            "subcategory":"Machinery & Supplies",
            "type":"Manufacturing & Wholesale Goods"
        }
    ],
    "sg:phone":"+61 3 9545 0555",
    "sg:postcode":"3150",
    "sg:province":"VIC",
    "sg:tags":[
        "rigging",
        "equipment",
        "hoisting"
    ],
    "wof:name":"McLellands Lifting Equipment Hire & Sales",
    "wof:placetype":"venue"
},
  "geometry": {"coordinates":[145.15788269000001,-37.8857383728],"type":"Point"}
}