{
  "type": "Feature",
  "properties": {
    "addr:full":"6 Darcy Pl Orange NSW 2800",
    "addr:housenumber":"6",
    "addr:postcode":"2800",
    "addr:street":"Darcy Pl",
    "iso:country":"AU",
    "sg:address":"6 Darcy Pl",
    "sg:city":"Orange",
    "sg:classifiers":[
        {
            "category":"Building & Trades",
            "subcategory":"Landscaping Services",
            "type":"Services"
        }
    ],
    "sg:phone":"+61 2 6360 2001",
    "sg:postcode":"2800",
    "sg:province":"NSW",
    "sg:tags":[
        "designer",
        "landscape",
        "contractor"
    ],
    "wof:name":"Steve Morgan Paving Plus",
    "wof:placetype":"venue"
},
  "geometry": {"coordinates":[149.104568481,-33.2621612549],"type":"Point"}
}