{
  "type": "Feature",
  "properties": {
    "addr:full":"2/57 Elizabeth Bay Rd Elizabeth Bay NSW 2011",
    "addr:housenumber":"/ 57",
    "addr:postcode":"2011",
    "addr:street":"Elizabeth Bay Rd",
    "iso:country":"AU",
    "sg:address":"2/57 Elizabeth Bay Rd",
    "sg:city":"Elizabeth Bay",
    "sg:classifiers":[
        {
            "category":"Personal",
            "subcategory":"Massage",
            "type":"Services"
        }
    ],
    "sg:phone":"+61 2 9368 0287",
    "sg:postcode":"2011",
    "sg:province":"NSW",
    "sg:tags":[
        "therapy"
    ],
    "wof:name":"Life Support Intergrated Therapys",
    "wof:placetype":"venue"
},
  "geometry": {"coordinates":[151.22903442399999,-33.8724136353],"type":"Point"}
}