{
  "type": "Feature",
  "properties": {
    "addr:full":"195 Waverley Rd Malvern East VIC 3145",
    "addr:housenumber":"195",
    "addr:postcode":"3145",
    "addr:street":"Waverley Rd",
    "iso:country":"AU",
    "sg:address":"195 Waverley Rd",
    "sg:city":"Malvern East",
    "sg:classifiers":[
        {
            "category":"Personal",
            "subcategory":"Beauty Salon",
            "type":"Services"
        }
    ],
    "sg:phone":"+61 3 9571 5068",
    "sg:postcode":"3145",
    "sg:province":"VIC",
    "sg:tags":[
        "hairdresser"
    ],
    "wof:name":"Joanne's Hair Fashions",
    "wof:placetype":"venue"
},
  "geometry": {"coordinates":[145.051605225,-37.8762054443],"type":"Point"}
}