{
  "type": "Feature",
  "properties": {
    "addr:full":"18 O'Callaghan Pde Horsham VIC 3400",
    "addr:housenumber":"18",
    "addr:postcode":"3400",
    "addr:street":"O'Callaghan Pde",
    "iso:country":"AU",
    "sg:address":"18 O'Callaghan Pde",
    "sg:city":"Horsham",
    "sg:classifiers":[
        {
            "category":"Fast Food",
            "type":"Food & Drink"
        }
    ],
    "sg:phone":"+61 3 5382 3922",
    "sg:postcode":"3400",
    "sg:province":"VIC",
    "sg:tags":[
        "away",
        "take"
    ],
    "wof:name":"Horsham Charcoal Chickens",
    "wof:placetype":"venue"
},
  "geometry": {"coordinates":[142.19619750999999,-36.7172393799],"type":"Point"}
}