{
  "type": "Feature",
  "properties": {
    "addr:full":"15 Henry St Horsham VIC 3400",
    "addr:housenumber":"15",
    "addr:postcode":"3400",
    "addr:street":"Henry St",
    "iso:country":"AU",
    "sg:address":"15 Henry St",
    "sg:city":"Horsham",
    "sg:classifiers":[
        {
            "category":"Building & Trades",
            "subcategory":"Plumbing",
            "type":"Services"
        }
    ],
    "sg:phone":"+61 408 504 265",
    "sg:postcode":"3400",
    "sg:province":"VIC",
    "sg:tags":[
        "plumber",
        "gasfitters"
    ],
    "wof:name":"Steve Panozzo Plumbing & Gasfitting",
    "wof:placetype":"venue"
},
  "geometry": {"coordinates":[142.19798278799999,-36.7096176147],"type":"Point"}
}