{
  "type": "Feature",
  "properties": {
    "addr:full":"55 Jerningham St North Adelaide SA 5006",
    "addr:housenumber":"55",
    "addr:postcode":"5006",
    "addr:street":"Jerningham St",
    "iso:country":"AU",
    "sg:address":"55 Jerningham St",
    "sg:city":"North Adelaide",
    "sg:classifiers":[
        {
            "category":"Professional",
            "subcategory":"Accounting & Tax Preparation",
            "type":"Services"
        }
    ],
    "sg:phone":"+61 8 8161 1000",
    "sg:postcode":"5006",
    "sg:province":"SA",
    "sg:tags":[
        "consultant",
        "taxation"
    ],
    "wof:name":"McCormack Reynolds",
    "wof:placetype":"venue"
},
  "geometry": {"coordinates":[138.60568237300001,-34.9077224731],"type":"Point"}
}