{
  "type": "Feature",
  "properties": {
    "addr:full":"5 School Rd Yeronga QLD 4104",
    "addr:housenumber":"5",
    "addr:postcode":"4104",
    "addr:street":"School Rd",
    "iso:country":"AU",
    "sg:address":"5 School Rd",
    "sg:city":"Yeronga",
    "sg:classifiers":[
        {
            "category":"Professional",
            "subcategory":"Research",
            "type":"Services"
        }
    ],
    "sg:phone":"+61 7 3392 7978",
    "sg:postcode":"4104",
    "sg:province":"QLD",
    "sg:tags":[
        "market"
    ],
    "wof:name":"Deborah Wilson Consulting Services Pty Ltd",
    "wof:placetype":"venue"
},
  "geometry": {"coordinates":[153.025314331,-27.5218582153],"type":"Point"}
}