{
  "type": "Feature",
  "properties": {
    "addr:full":"PO Box 4263 Raceview QLD 4305",
    "addr:postcode":"4305",
    "iso:country":"AU",
    "sg:address":"PO Box 4263",
    "sg:city":"Raceview",
    "sg:classifiers":[
        {
            "category":"Train Station",
            "subcategory":"Light Rail",
            "type":"Transportation"
        }
    ],
    "sg:phone":"+61 7 3288 9855",
    "sg:postcode":"4305",
    "sg:province":"QLD",
    "sg:tags":[
        "equipment",
        "energy",
        "solar"
    ],
    "wof:name":"New Energy Systems",
    "wof:placetype":"venue"
},
  "geometry": {"coordinates":[152.786834717,-27.6423206329],"type":"Point"}
}