{
  "type": "Feature",
  "properties": {
    "addr:full":"156 Morayfield Rd Caboolture QLD 4510",
    "addr:housenumber":"156",
    "addr:postcode":"4510",
    "addr:street":"Morayfield Rd",
    "iso:country":"AU",
    "sg:address":"156 Morayfield Rd",
    "sg:city":"Caboolture",
    "sg:classifiers":[
        {
            "category":"Shopping",
            "subcategory":"Crafts & Fabrics",
            "type":"Retail Goods"
        }
    ],
    "sg:phone":"+61 7 5495 6433",
    "sg:postcode":"4510",
    "sg:province":"QLD",
    "sg:tags":[
        "merchant",
        "cork"
    ],
    "wof:name":"House Of Carpets",
    "wof:placetype":"venue"
},
  "geometry": {"coordinates":[152.95030199999999,-27.091728],"type":"Point"}
}