{
  "type": "Feature",
  "properties": {
    "addr:full":"10 John St Dandenong VIC 3175",
    "addr:housenumber":"10",
    "addr:postcode":"3175",
    "addr:street":"John St",
    "iso:country":"AU",
    "sg:address":"10 John St",
    "sg:city":"Dandenong",
    "sg:classifiers":[
        {
            "category":"Banks & Credit Unions",
            "subcategory":"Financial Services",
            "type":"Services"
        }
    ],
    "sg:phone":"+61 3 9791 2322",
    "sg:postcode":"3175",
    "sg:province":"VIC",
    "sg:tags":[
        "wholesaler",
        "mfrs",
        "gear"
    ],
    "sg:website":"http://www.gearcutting.com.au",
    "wof:name":"Gear Cutting & Manufacturing (Aust) Pty. Ltd.",
    "wof:placetype":"venue"
},
  "geometry": {"coordinates":[145.21720886200001,-37.9995422363],"type":"Point"}
}