{
  "type": "Feature",
  "properties": {
    "iso:country":"AU",
    "sg:address":"350a King William St",
    "sg:city":"Adelaide",
    "sg:classifiers":[
        {
            "category":"Social Services",
            "subcategory":"Job Training",
            "type":"Services"
        }
    ],
    "sg:phone":"+61 8 8211 8661",
    "sg:postcode":"5000",
    "sg:province":"SA",
    "sg:tags":[
        "hire",
        "computer",
        "leasing"
    ],
    "sg:website":"http://www.allneeds.com.au",
    "wof:name":"Allneeds Computers",
    "wof:placetype":"venue"
},
  "geometry": {"coordinates":[138.60049438499999,-34.9319648743],"type":"Point"}
}