{
  "type": "Feature",
  "properties": {
    "iso:country":"AU",
    "sg:address":"31 Charlotte St",
    "sg:city":"Smithfield",
    "sg:classifiers":[
        {
            "category":"Manufacturing",
            "subcategory":"Furniture",
            "type":"Manufacturing & Wholesale Goods"
        }
    ],
    "sg:phone":"+61 8 8284 5444",
    "sg:postcode":"5114",
    "sg:province":"SA",
    "sg:tags":[
        "builder",
        "designer",
        "custom"
    ],
    "wof:name":"Hoffmann's Furniture",
    "wof:placetype":"venue"
},
  "geometry": {"coordinates":[138.688995361,-34.681854248],"type":"Point"}
}