{
  "type": "Feature",
  "properties": {
    "iso:country":"AU",
    "sg:address":"29 Mein St",
    "sg:city":"Spring Hill",
    "sg:classifiers":[
        {
            "category":"Health Services",
            "subcategory":"Doctor",
            "type":"Services"
        }
    ],
    "sg:phone":"+61 1300 302 838",
    "sg:postcode":"4000",
    "sg:province":"QLD",
    "sg:tags":[
        "medical",
        "practitioner"
    ],
    "wof:name":"MLRSA",
    "wof:placetype":"venue"
},
  "geometry": {"coordinates":[153.02684020999999,-27.4644565582],"type":"Point"}
}