{
  "type": "Feature",
  "properties": {
    "addr:full":"33 Gordon Rd Long Jetty NSW 2261",
    "addr:housenumber":"33",
    "addr:postcode":"2261",
    "addr:street":"Gordon Rd",
    "iso:country":"AU",
    "sg:address":"33 Gordon Rd",
    "sg:city":"Long Jetty",
    "sg:classifiers":[
        {
            "category":"Travel",
            "subcategory":"Hotels & Motels",
            "type":"Entertainment"
        }
    ],
    "sg:phone":"+61 2 4332 3692",
    "sg:postcode":"2261",
    "sg:province":"NSW",
    "wof:name":"Coachman Motor Inn The",
    "wof:placetype":"venue"
},
  "geometry": {"coordinates":[151.48689300000001,-33.353752],"type":"Point"}
}