{
  "type": "Feature",
  "properties": {
    "addr:full":"Shop 13 Northlake South St Kardinya WA 6163",
    "addr:housenumber":"shop 13",
    "addr:postcode":"6163",
    "addr:street":"South St",
    "iso:country":"AU",
    "sg:address":"Shop 13 Northlake South St",
    "sg:city":"Kardinya",
    "sg:classifiers":[
        {
            "category":"Shopping",
            "subcategory":"Jewelry",
            "type":"Retail Goods"
        }
    ],
    "sg:phone":"+61 8 9331 4377",
    "sg:postcode":"6163",
    "sg:province":"WA",
    "sg:tags":[
        "jeweller"
    ],
    "wof:name":"Edments",
    "wof:placetype":"venue"
},
  "geometry": {"coordinates":[115.82058000000001,-32.068523],"type":"Point"}
}