{
  "type": "Feature",
  "properties": {
    "addr:full":"PO Box 11 Woodville SA 5011",
    "addr:postcode":"5011",
    "iso:country":"AU",
    "sg:address":"PO Box 11",
    "sg:city":"Woodville",
    "sg:classifiers":[
        {
            "category":"Utilities",
            "subcategory":"Electric",
            "type":"Services"
        }
    ],
    "sg:phone":"+61 8 8347 4575",
    "sg:postcode":"5011",
    "sg:province":"SA",
    "sg:tags":[
        "electrical",
        "contractor"
    ],
    "wof:name":"Electrical Enterprises",
    "wof:placetype":"venue"
},
  "geometry": {"coordinates":[138.537384033,-34.8784294128],"type":"Point"}
}