{
  "type": "Feature",
  "properties": {
    "addr:full":"1 Brinkley Rd Murray Bridge SA 5253",
    "addr:housenumber":"1",
    "addr:postcode":"5253",
    "addr:street":"Brinkley Rd",
    "iso:country":"AU",
    "sg:address":"1 Brinkley Rd",
    "sg:city":"Murray Bridge",
    "sg:classifiers":[
        {
            "category":"Professional",
            "type":"Services"
        }
    ],
    "sg:phone":"+61 415 827 900",
    "sg:postcode":"5253",
    "sg:province":"SA",
    "sg:tags":[
        "courier"
    ],
    "wof:name":"V.I.P. Couriers",
    "wof:placetype":"venue"
},
  "geometry": {"coordinates":[139.268066406,-35.139881134],"type":"Point"}
}