{
  "type": "Feature",
  "properties": {
    "addr:full":"2839 Cadell Valley Rd Waikerie SA 5330",
    "addr:postcode":"2839;5330",
    "addr:street":"Valley Rd",
    "iso:country":"AU",
    "sg:address":"2839 Cadell Valley Rd",
    "sg:city":"Waikerie",
    "sg:classifiers":[
        {
            "category":"Professional",
            "subcategory":"Engineering",
            "type":"Services"
        }
    ],
    "sg:phone":"+61 8 8541 2384",
    "sg:postcode":"5330",
    "sg:province":"SA",
    "sg:tags":[
        "engineer"
    ],
    "wof:name":"Hall R F & B J",
    "wof:placetype":"venue"
},
  "geometry": {"coordinates":[139.931838989,-34.1693992615],"type":"Point"}
}