{
  "type": "Feature",
  "properties": {
    "addr:full":"PO Box 102 Legana TAS 7277",
    "addr:postcode":"7277",
    "iso:country":"AU",
    "sg:address":"PO Box 102",
    "sg:city":"Legana",
    "sg:classifiers":[
        {
            "category":"Home & Garden",
            "subcategory":"Building Materials",
            "type":"Retail Goods"
        }
    ],
    "sg:phone":"+61 439 373 089",
    "sg:postcode":"7277",
    "sg:province":"TAS",
    "sg:tags":[
        "retaining",
        "wall"
    ],
    "wof:name":"C & M Specialised Concrete Pty Ltd",
    "wof:placetype":"venue"
},
  "geometry": {"coordinates":[147.051055908,-41.3433113098],"type":"Point"}
}