{
  "type": "Feature",
  "properties": {
    "addr:full":"53 Mann St Gosford NSW 2250",
    "addr:housenumber":"53",
    "addr:postcode":"2250",
    "addr:street":"Mann St",
    "iso:country":"AU",
    "sg:address":"53 Mann St",
    "sg:city":"Gosford",
    "sg:classifiers":[
        {
            "category":"Social Services",
            "subcategory":"Child Care",
            "type":"Services"
        }
    ],
    "sg:phone":"+61 2 4325 8352",
    "sg:postcode":"2250",
    "sg:province":"NSW",
    "sg:website":"http://www.gosford.nsw.gov.au",
    "wof:name":"Gosford City Council Childrens Services",
    "wof:placetype":"venue"
},
  "geometry": {"coordinates":[151.341674805,-33.428478241],"type":"Point"}
}