{
  "type": "Feature",
  "properties": {
    "iso:country":"AU",
    "sg:address":"7 Leschenault St",
    "sg:city":"Albany",
    "sg:classifiers":[
        {
            "category":"Education",
            "subcategory":"School",
            "type":"Public Place"
        }
    ],
    "sg:phone":"+61 8 9841 3144",
    "sg:postcode":"6330",
    "sg:province":"WA",
    "sg:tags":[
        "state",
        "except",
        "nsw"
    ],
    "wof:name":"Lockyer Pre-School",
    "wof:placetype":"venue"
},
  "geometry": {"coordinates":[117.861152649,-35.0041503906],"type":"Point"}
}