{
  "type": "Feature",
  "properties": {
    "addr:full":"Mitchell Rd Roma QLD 4455",
    "addr:postcode":"4455",
    "addr:street":"Mitchell Rd",
    "iso:country":"AU",
    "sg:address":"Mitchell Rd",
    "sg:city":"Roma",
    "sg:classifiers":[
        {
            "category":"Home & Garden",
            "subcategory":"Hardware",
            "type":"Retail Goods"
        }
    ],
    "sg:phone":"+61 7 4622 4333",
    "sg:postcode":"4455",
    "sg:province":"QLD",
    "sg:tags":[
        "repair",
        "tool",
        "power"
    ],
    "wof:name":"Banks Bolts & Fasteners",
    "wof:placetype":"venue"
},
  "geometry": {"coordinates":[148.78732299800001,-26.5734291077],"type":"Point"}
}