{
  "type": "Feature",
  "properties": {
    "iso:country":"AU",
    "sg:address":"9 Coral Ave",
    "sg:city":"Pacific Haven",
    "sg:classifiers":[
        {
            "category":"Shopping",
            "subcategory":"Bicycles & Sporting Goods",
            "type":"Retail Goods"
        }
    ],
    "sg:phone":"+61 7 4129 0154",
    "sg:postcode":"4659",
    "sg:province":"QLD",
    "sg:tags":[
        "trampoline"
    ],
    "wof:name":"TJ's Trampolines",
    "wof:placetype":"venue"
},
  "geometry": {"coordinates":[152.53418,-25.260065],"type":"Point"}
}