{
  "type": "Feature",
  "properties": {
    "iso:country":"AU",
    "sg:address":"57 Emmett St",
    "sg:city":"Smithton",
    "sg:classifiers":[
        {
            "category":"Shopping",
            "subcategory":"Clothing, Apparel, & Fashions",
            "type":"Retail Goods"
        }
    ],
    "sg:phone":"+61 3 6452 1015",
    "sg:postcode":"7330",
    "sg:province":"TAS",
    "sg:tags":[
        "boutique"
    ],
    "wof:name":"Lindi Lou Ladies Wear",
    "wof:placetype":"venue"
},
  "geometry": {"coordinates":[145.126114,-40.841015],"type":"Point"}
}