{
  "type": "Feature",
  "properties": {
    "iso:country":"AU",
    "sg:address":"Unit 1/ 158 Browns Rd",
    "sg:city":"Noble Park",
    "sg:classifiers":[
        {
            "category":"Shopping",
            "type":"Retail Goods"
        }
    ],
    "sg:phone":"+61 3 9790 6333",
    "sg:postcode":"3174",
    "sg:province":"VIC",
    "sg:tags":[
        "repair",
        "travel"
    ],
    "wof:name":"Victoria Station",
    "wof:placetype":"venue"
},
  "geometry": {"coordinates":[145.18467712399999,-37.950378418],"type":"Point"}
}