{
  "type": "Feature",
  "properties": {
    "addr:full":"197 Conadilly St Gunnedah NSW 2380",
    "addr:housenumber":"197",
    "addr:postcode":"2380",
    "addr:street":"Conadilly St",
    "iso:country":"AU",
    "sg:address":"197 Conadilly St",
    "sg:city":"Gunnedah",
    "sg:classifiers":[
        {
            "category":"Cafe",
            "type":"Food & Drink"
        }
    ],
    "sg:phone":"+61 2 6742 1965",
    "sg:postcode":"2380",
    "sg:province":"NSW",
    "wof:name":"Monterey Cafe Narrabri",
    "wof:placetype":"venue"
},
  "geometry": {"coordinates":[150.252807617,-30.9774475098],"type":"Point"}
}