{
  "type": "Feature",
  "properties": {
    "addr:full":"33 Maryvale Drv Warrnambool VIC 3280",
    "addr:housenumber":"33",
    "addr:postcode":"3280",
    "addr:street":"Maryvale Drv",
    "iso:country":"AU",
    "sg:address":"33 Maryvale Drv",
    "sg:city":"Warrnambool",
    "sg:classifiers":[
        {
            "category":"Professional",
            "subcategory":"Business Services",
            "type":"Services"
        }
    ],
    "sg:phone":"+61 428 523 340",
    "sg:postcode":"3280",
    "sg:province":"VIC",
    "sg:tags":[
        "livestock",
        "transport"
    ],
    "wof:name":"Levett R J",
    "wof:placetype":"venue"
},
  "geometry": {"coordinates":[142.48323059099999,-38.3842582703],"type":"Point"}
}