{
  "type": "Feature",
  "properties": {
    "addr:full":"Lot 2, South Western Hwy Mundijong WA 6123",
    "addr:postcode":"6123",
    "addr:street":"South Western Hwy",
    "iso:country":"AU",
    "sg:address":"Lot 2, South Western Hwy",
    "sg:city":"Mundijong",
    "sg:classifiers":[
        {
            "category":"Home & Garden",
            "subcategory":"Building Materials",
            "type":"Retail Goods"
        }
    ],
    "sg:phone":"+61 8 9525 1144",
    "sg:postcode":"6123",
    "sg:province":"WA",
    "sg:tags":[
        "wall",
        "frame",
        "truss",
        "roof"
    ],
    "wof:name":"Colli Truss And Frame",
    "wof:placetype":"venue"
},
  "geometry": {"coordinates":[116.01091003400001,-32.2943916321],"type":"Point"}
}