{
  "type": "Feature",
  "properties": {
    "addr:full":"355 New Dookie Rd Shepparton VIC 3630",
    "addr:housenumber":"355",
    "addr:postcode":"3630",
    "addr:street":"New Dookie Rd",
    "iso:country":"AU",
    "sg:address":"355 New Dookie Rd",
    "sg:city":"Shepparton",
    "sg:classifiers":[
        {
            "category":"Building & Trades",
            "subcategory":"Cleaning & Sanitation",
            "type":"Services"
        }
    ],
    "sg:phone":"+61 3 5829 9391",
    "sg:postcode":"3630",
    "sg:province":"VIC",
    "sg:tags":[
        "tank",
        "septic"
    ],
    "wof:name":"Maw. E.J. & G.M.",
    "wof:placetype":"venue"
},
  "geometry": {"coordinates":[145.454223633,-36.3645591736],"type":"Point"}
}