{
  "type": "Feature",
  "properties": {
    "addr:full":"Shop 10, 9 Ocean St Maroochydore QLD 4558",
    "addr:housenumber":"shop 10 9",
    "addr:postcode":"4558",
    "addr:street":"Ocean St",
    "iso:country":"AU",
    "sg:address":"Shop 10, 9 Ocean St",
    "sg:city":"Maroochydore",
    "sg:classifiers":[
        {
            "category":"Personal",
            "subcategory":"Massage",
            "type":"Services"
        }
    ],
    "sg:phone":"+61 7 5479 6729",
    "sg:postcode":"4558",
    "sg:province":"QLD",
    "sg:tags":[
        "therapy"
    ],
    "wof:name":"Sunshine Coast Myotherapy & Massage Clinic",
    "wof:placetype":"venue"
},
  "geometry": {"coordinates":[153.0909729,-26.6519374847],"type":"Point"}
}