{
  "type": "Feature",
  "properties": {
    "iso:country":"AU",
    "sg:address":"Nell St",
    "sg:city":"Greensborough",
    "sg:classifiers":[
        {
            "category":"Education",
            "subcategory":"School",
            "type":"Public Place"
        }
    ],
    "sg:phone":"+61 3 9433 2666",
    "sg:postcode":"3088",
    "sg:province":"VIC",
    "sg:tags":[
        "state",
        "except",
        "nsw"
    ],
    "wof:name":"Greensborough College",
    "wof:placetype":"venue"
},
  "geometry": {"coordinates":[145.100830078,-37.7093048096],"type":"Point"}
}