{
  "type": "Feature",
  "properties": {
    "addr:full":"41 Princess Hwy Dandenong VIC 3175",
    "addr:housenumber":"41",
    "addr:postcode":"3175",
    "addr:street":"Princess Hwy",
    "iso:country":"AU",
    "sg:address":"41 Princess Hwy",
    "sg:city":"Dandenong",
    "sg:classifiers":[
        {
            "category":"Personal",
            "subcategory":"Massage",
            "type":"Services"
        }
    ],
    "sg:phone":"+61 3 8794 9351",
    "sg:postcode":"3175",
    "sg:province":"VIC",
    "sg:tags":[
        "therapy"
    ],
    "wof:name":"Moods College of Massage & Natural Therapies Clinic",
    "wof:placetype":"venue"
},
  "geometry": {"coordinates":[145.145095825,-37.9505462646],"type":"Point"}
}