{
  "type": "Feature",
  "properties": {
    "addr:full":"141 Magnesium Drv Crestmead QLD 4132",
    "addr:housenumber":"141",
    "addr:postcode":"4132",
    "addr:street":"Magnesium Drv",
    "iso:country":"AU",
    "sg:address":"141 Magnesium Drv",
    "sg:city":"Crestmead",
    "sg:classifiers":[
        {
            "category":"Manufacturing",
            "subcategory":"Metals",
            "type":"Manufacturing & Wholesale Goods"
        }
    ],
    "sg:phone":"+61 7 3803 4411",
    "sg:postcode":"4132",
    "sg:province":"QLD",
    "sg:tags":[
        "wholesaler",
        "aluminium",
        "mfrs"
    ],
    "wof:name":"Rapid Aluminium Qld",
    "wof:placetype":"venue"
},
  "geometry": {"coordinates":[153.07612609899999,-27.6880817413],"type":"Point"}
}