{
  "type": "Feature",
  "properties": {
    "addr:full":"10 Kellaway Pl Wetherill Park NSW 2164",
    "addr:housenumber":"10",
    "addr:postcode":"2164",
    "addr:street":"Kellaway Pl",
    "iso:country":"AU",
    "sg:address":"10 Kellaway Pl",
    "sg:city":"Wetherill Park",
    "sg:classifiers":[
        {
            "category":"Wholesale",
            "subcategory":"Non-durable Goods",
            "type":"Manufacturing & Wholesale Goods"
        }
    ],
    "sg:phone":"+61 2 9604 6177",
    "sg:postcode":"2164",
    "sg:province":"NSW",
    "sg:tags":[
        "wholesaler",
        "mfrs",
        "cosmetic"
    ],
    "wof:name":"Jean Charles Cosmetics Pty Ltd",
    "wof:placetype":"venue"
},
  "geometry": {"coordinates":[150.90507507300001,-33.8400268555],"type":"Point"}
}