{
  "type": "Feature",
  "properties": {
    "iso:country":"AU",
    "sg:address":"63 Ann St",
    "sg:city":"Surry Hills",
    "sg:classifiers":[
        {
            "category":"Shopping",
            "subcategory":"Computers & Home Electronics",
            "type":"Retail Goods"
        }
    ],
    "sg:phone":"+61 2 9324 9500",
    "sg:postcode":"2010",
    "sg:province":"NSW",
    "sg:tags":[
        "hire",
        "video",
        "game"
    ],
    "wof:name":"Sony Computer Entertainment Aust Pty Limited",
    "wof:placetype":"venue"
},
  "geometry": {"coordinates":[151.21290588400001,-33.8824539185],"type":"Point"}
}