{
  "type": "Feature",
  "properties": {
    "addr:full":"Unit 13, 66 Ashford Ave Milperra NSW 2214",
    "addr:housenumber":"66",
    "addr:postcode":"2214",
    "addr:street":"Ashford Ave",
    "iso:country":"AU",
    "sg:address":"Unit 13, 66 Ashford Ave",
    "sg:city":"Milperra",
    "sg:classifiers":[
        {
            "category":"Building & Trades",
            "subcategory":"Equipment Rental",
            "type":"Services"
        }
    ],
    "sg:phone":"+61 2 9792 1239",
    "sg:postcode":"2214",
    "sg:province":"NSW",
    "sg:tags":[
        "saw"
    ],
    "wof:name":"Milperra Saw Works Pty. Ltd.",
    "wof:placetype":"venue"
},
  "geometry": {"coordinates":[150.989532,-33.935692],"type":"Point"}
}