{
  "type": "Feature",
  "properties": {
    "iso:country":"AU",
    "sg:address":"5 Hope St",
    "sg:city":"Invermay",
    "sg:classifiers":[
        {
            "category":"Professional",
            "type":"Services"
        }
    ],
    "sg:phone":"+61 3 6326 9007",
    "sg:postcode":"7248",
    "sg:province":"TAS",
    "sg:tags":[
        "coating",
        "powder"
    ],
    "wof:name":"Launceston Powder Coating",
    "wof:placetype":"venue"
},
  "geometry": {"coordinates":[147.13163757300001,-41.4115219116],"type":"Point"}
}