{
  "type": "Feature",
  "properties": {
    "iso:country":"AU",
    "sg:address":"Shop 2, 1118 Oxley Rd",
    "sg:city":"Oxley",
    "sg:classifiers":[
        {
            "category":"Fast Food",
            "type":"Food & Drink"
        }
    ],
    "sg:phone":"+61 7 3379 1880",
    "sg:postcode":"4075",
    "sg:province":"QLD",
    "sg:tags":[
        "away",
        "take"
    ],
    "wof:name":"Oxley Fish And Chips",
    "wof:placetype":"venue"
},
  "geometry": {"coordinates":[152.978393555,-27.5602741241],"type":"Point"}
}