{
  "type": "Feature",
  "properties": {
    "addr:full":"122 North West Coastal Hwy Geraldton WA 6530",
    "addr:housenumber":"122",
    "addr:postcode":"6530",
    "addr:street":"North West Coastal Hwy",
    "iso:country":"AU",
    "sg:address":"122 North West Coastal Hwy",
    "sg:city":"Geraldton",
    "sg:classifiers":[
        {
            "category":"Retail",
            "subcategory":"Funeral Services",
            "type":"Services"
        }
    ],
    "sg:phone":"+61 8 9964 3767",
    "sg:postcode":"6530",
    "sg:province":"WA",
    "sg:tags":[
        "director"
    ],
    "wof:name":"Bethany Funeral Home",
    "wof:placetype":"venue"
},
  "geometry": {"coordinates":[114.624900818,-28.7687854767],"type":"Point"}
}