{
  "type": "Feature",
  "properties": {
    "addr:full":"193 Herbert St Doubleview WA 6018",
    "addr:housenumber":"193",
    "addr:postcode":"6018",
    "addr:street":"Herbert St",
    "iso:country":"AU",
    "sg:address":"193 Herbert St",
    "sg:city":"Doubleview",
    "sg:classifiers":[
        {
            "category":"Retail",
            "subcategory":"Repair Shop",
            "type":"Services"
        }
    ],
    "sg:phone":"+61 8 9446 3040",
    "sg:postcode":"6018",
    "sg:province":"WA",
    "sg:tags":[
        "machine",
        "repairs",
        "part",
        "dryer",
        "washing"
    ],
    "wof:name":"Andy's Washer Repair Service",
    "wof:placetype":"venue"
},
  "geometry": {"coordinates":[115.777610779,-31.8910903931],"type":"Point"}
}