{
  "type": "Feature",
  "properties": {
    "iso:country":"AU",
    "sg:address":"310 Boundary St",
    "sg:city":"South Townsville",
    "sg:classifiers":[
        {
            "category":"Ferry",
            "type":"Transportation"
        }
    ],
    "sg:phone":"+61 7 4721 3166",
    "sg:postcode":"4810",
    "sg:province":"QLD",
    "sg:tags":[
        "barge"
    ],
    "wof:name":"Palm Island Barge Services",
    "wof:placetype":"venue"
},
  "geometry": {"coordinates":[146.83407600000001,-19.267698],"type":"Point"}
}