{
  "type": "Feature",
  "properties": {
    "addr:full":"164- 172 Marrickville Rd Marrickville NSW 2204",
    "addr:housenumber":"172",
    "addr:postcode":"2204",
    "addr:street":"Marrickville Rd",
    "iso:country":"AU",
    "sg:address":"164- 172 Marrickville Rd",
    "sg:city":"Marrickville",
    "sg:classifiers":[
        {
            "category":"Health Services",
            "subcategory":"Health Practitioner",
            "type":"Services"
        }
    ],
    "sg:phone":"+61 2 9560 7478",
    "sg:postcode":"2204",
    "sg:province":"NSW",
    "sg:tags":[
        "consultant",
        "conservation",
        "hearing"
    ],
    "wof:name":"Comfort Hearing Aids",
    "wof:placetype":"venue"
},
  "geometry": {"coordinates":[151.16061400000001,-33.912663],"type":"Point"}
}