{
  "type": "Feature",
  "properties": {
    "addr:full":"220 Balcatta Rd Balcatta WA 6021",
    "addr:housenumber":"220",
    "addr:postcode":"6021",
    "addr:street":"Balcatta Rd",
    "iso:country":"AU",
    "sg:address":"220 Balcatta Rd",
    "sg:city":"Balcatta",
    "sg:classifiers":[
        {
            "category":"Personal",
            "subcategory":"Beauty Salon",
            "type":"Services"
        }
    ],
    "sg:phone":"+61 8 9344 6515",
    "sg:postcode":"6021",
    "sg:province":"WA",
    "sg:tags":[
        "hairdresser"
    ],
    "wof:name":"Regal Hair & Beauty",
    "wof:placetype":"venue"
},
  "geometry": {"coordinates":[115.81758117699999,-31.8626365662],"type":"Point"}
}