{
  "type": "Feature",
  "properties": {
    "iso:country":"AU",
    "sg:address":"106 Buckley St",
    "sg:city":"Footscray",
    "sg:classifiers":[
        {
            "category":"Professional",
            "subcategory":"Employment Agencies",
            "type":"Services"
        }
    ],
    "sg:phone":"+61 1300 302 696",
    "sg:postcode":"3011",
    "sg:province":"VIC",
    "sg:tags":[
        "hire",
        "labour",
        "contractor"
    ],
    "wof:name":"ab Group of Recruitment Companies",
    "wof:placetype":"venue"
},
  "geometry": {"coordinates":[144.89346313499999,-37.8033256531],"type":"Point"}
}