{
  "type": "Feature",
  "properties": {
    "iso:country":"AU",
    "sg:address":"Shop 1, Cnr Sandgate Rd & Boyd St",
    "sg:city":"Nundah",
    "sg:classifiers":[
        {
            "category":"Food & Beverages",
            "subcategory":"Bakery",
            "type":"Retail Goods"
        }
    ],
    "sg:phone":"+61 7 3256 8667",
    "sg:postcode":"4012",
    "sg:province":"QLD",
    "sg:tags":[
        "cake",
        "shop",
        "pastry"
    ],
    "wof:name":"Cream Patisserie",
    "wof:placetype":"venue"
},
  "geometry": {"coordinates":[153.06004333499999,-27.4020195007],"type":"Point"}
}