{
  "type": "Feature",
  "properties": {
    "addr:full":"Shop 9 Urangan Central Boat Harbour Drv Urangan QLD 4655",
    "addr:housenumber":"shop 9",
    "addr:postcode":"4655",
    "addr:street":"Boat Harbour Drv",
    "iso:country":"AU",
    "sg:address":"Shop 9 Urangan Central Boat Harbour Drv",
    "sg:city":"Urangan",
    "sg:classifiers":[
        {
            "category":"Personal",
            "subcategory":"Beauty Salon",
            "type":"Services"
        }
    ],
    "sg:phone":"+61 7 4124 9191",
    "sg:postcode":"4655",
    "sg:province":"QLD",
    "sg:tags":[
        "hairdresser"
    ],
    "wof:name":"Hair Snipets",
    "wof:placetype":"venue"
},
  "geometry": {"coordinates":[152.89634699999999,-25.29294],"type":"Point"}
}