{
  "type": "Feature",
  "properties": {
    "addr:full":"3 Alma St Gympie QLD 4570",
    "addr:housenumber":"3",
    "addr:postcode":"4570",
    "addr:street":"Alma St",
    "iso:country":"AU",
    "sg:address":"3 Alma St",
    "sg:city":"Gympie",
    "sg:classifiers":[
        {
            "category":"Education",
            "subcategory":"Kindergarten",
            "type":"Public Place"
        }
    ],
    "sg:phone":"+61 7 5482 1960",
    "sg:postcode":"4570",
    "sg:province":"QLD",
    "sg:tags":[
        "pre-schools"
    ],
    "wof:name":"Gympie Community Kindergarten & Pre School Inc The",
    "wof:placetype":"venue"
},
  "geometry": {"coordinates":[152.666213989,-26.1897296906],"type":"Point"}
}