{
  "type": "Feature",
  "properties": {
    "iso:country":"AU",
    "sg:address":"56 Tarnard Drive",
    "sg:city":"Braeside",
    "sg:classifiers":[
        {
            "category":"Communications",
            "subcategory":"Film & Video Production",
            "type":"Services"
        }
    ],
    "sg:phone":"+61 3 9580 7790",
    "sg:postcode":"3195",
    "sg:province":"VIC",
    "sg:tags":[
        "fan",
        "blower"
    ],
    "sg:website":"http://www.cfmfans.com.au",
    "wof:name":"CFM Fans",
    "wof:placetype":"venue"
},
  "geometry": {"coordinates":[145.115524292,-37.9897003174],"type":"Point"}
}