{
  "type": "Feature",
  "properties": {
    "addr:full":"PO Box 384 Burnside SA 5066",
    "addr:postcode":"5066",
    "iso:country":"AU",
    "sg:address":"PO Box 384",
    "sg:city":"Burnside",
    "sg:classifiers":[
        {
            "category":"Organizations",
            "subcategory":"Professional Association",
            "type":"Services"
        }
    ],
    "sg:phone":"+61 8 8333 3515",
    "sg:postcode":"5066",
    "sg:province":"SA",
    "sg:tags":[
        "web",
        "internet"
    ],
    "wof:name":"The Factory Digital Media",
    "wof:placetype":"venue"
},
  "geometry": {"coordinates":[138.65997314399999,-34.9359016418],"type":"Point"}
}