{
  "type": "Feature",
  "properties": {
    "iso:country":"AU",
    "sg:address":"King St",
    "sg:city":"Cotton Tree",
    "sg:classifiers":[
        {
            "category":"Health Services",
            "subcategory":"Doctor",
            "type":"Services"
        }
    ],
    "sg:phone":"+61 1300 550 911",
    "sg:postcode":"4558",
    "sg:province":"QLD",
    "sg:tags":[
        "medical",
        "practitioner"
    ],
    "wof:name":"Chester Andrew",
    "wof:placetype":"venue"
},
  "geometry": {"coordinates":[153.100708008,-26.6547050476],"type":"Point"}
}