{
  "type": "Feature",
  "properties": {
    "addr:full":"395 Chandler Rd Keysborough VIC 3173",
    "addr:housenumber":"395",
    "addr:postcode":"3173",
    "addr:street":"Chandler Rd",
    "iso:country":"AU",
    "sg:address":"395 Chandler Rd",
    "sg:city":"Keysborough",
    "sg:classifiers":[
        {
            "category":"Food & Beverages",
            "subcategory":"Groceries & Convenience Stores",
            "type":"Retail Goods"
        }
    ],
    "sg:phone":"+61 3 9798 1719",
    "sg:postcode":"3173",
    "sg:province":"VIC",
    "wof:name":"Tang Hai Mei",
    "wof:placetype":"venue"
},
  "geometry": {"coordinates":[145.18281555199999,-37.9904785156],"type":"Point"}
}