{
  "type": "Feature",
  "properties": {
    "addr:full":"7 Yamba Crt Salisbury Heights SA 5109",
    "addr:housenumber":"7",
    "addr:postcode":"5109",
    "addr:street":"Yamba Crt",
    "iso:country":"AU",
    "sg:address":"7 Yamba Crt",
    "sg:city":"Salisbury Heights",
    "sg:classifiers":[
        {
            "category":"Professional",
            "subcategory":"Accounting & Tax Preparation",
            "type":"Services"
        }
    ],
    "sg:phone":"+61 8 8250 0746",
    "sg:postcode":"5109",
    "sg:province":"SA",
    "sg:tags":[
        "consultant",
        "taxation"
    ],
    "wof:name":"Vidovich Janice",
    "wof:placetype":"venue"
},
  "geometry": {"coordinates":[138.68646240199999,-34.7619857788],"type":"Point"}
}