{
  "type": "Feature",
  "properties": {
    "iso:country":"AU",
    "sg:address":"38 Darling St",
    "sg:city":"Carrington",
    "sg:classifiers":[
        {
            "category":"Wholesale",
            "subcategory":"Painting Supplies",
            "type":"Manufacturing & Wholesale Goods"
        }
    ],
    "sg:phone":"+61 1300 308 052",
    "sg:postcode":"2294",
    "sg:province":"NSW",
    "sg:tags":[
        "product",
        "polyurethane"
    ],
    "wof:name":"Hi Qual Solutions",
    "wof:placetype":"venue"
},
  "geometry": {"coordinates":[151.76898193400001,-32.9095077515],"type":"Point"}
}