{
  "type": "Feature",
  "properties": {
    "iso:country":"AU",
    "sg:address":"152 Sturt St",
    "sg:city":"South Melbourne",
    "sg:classifiers":[
        {
            "category":"Manufacturing",
            "subcategory":"Motor Vehicles & Parts",
            "type":"Manufacturing & Wholesale Goods"
        }
    ],
    "sg:phone":"+61 3 9686 3951",
    "sg:postcode":"3205",
    "sg:province":"VIC",
    "sg:tags":[
        "replacement"
    ],
    "wof:name":"Collins Mitsubishi",
    "wof:placetype":"venue"
},
  "geometry": {"coordinates":[144.966568,-37.825577],"type":"Point"}
}