{
  "type": "Feature",
  "properties": {
    "addr:full":"Suite 4, 23 Haynes St Kalamunda WA 6076",
    "addr:housenumber":"23",
    "addr:postcode":"6076",
    "addr:street":"Haynes St",
    "iso:country":"AU",
    "sg:address":"Suite 4, 23 Haynes St",
    "sg:city":"Kalamunda",
    "sg:classifiers":[
        {
            "category":"Professional",
            "subcategory":"Engineering",
            "type":"Services"
        }
    ],
    "sg:phone":"+61 8 9257 2695",
    "sg:postcode":"6076",
    "sg:province":"WA",
    "sg:tags":[
        "consulting",
        "engineer"
    ],
    "wof:name":"Yenem Engineering Services",
    "wof:placetype":"venue"
},
  "geometry": {"coordinates":[116.058319092,-31.9714355469],"type":"Point"}
}