{
  "type": "Feature",
  "properties": {
    "iso:country":"AU",
    "sg:address":"182 High St",
    "sg:city":"Bendigo",
    "sg:classifiers":[
        {
            "category":"Travel",
            "subcategory":"Hotels & Motels",
            "type":"Entertainment"
        }
    ],
    "sg:phone":"+61 3 5443 0591",
    "sg:postcode":"3550",
    "sg:province":"VIC",
    "wof:name":"Bendigo National Motor Inn",
    "wof:placetype":"venue"
},
  "geometry": {"coordinates":[144.268997192,-36.7646903992],"type":"Point"}
}