{
  "type": "Feature",
  "properties": {
    "addr:full":"160- 162 Newton Rd Wetherill Park NSW 2164",
    "addr:housenumber":"160 162",
    "addr:postcode":"2164",
    "addr:street":"Newton Rd",
    "iso:country":"AU",
    "sg:address":"160- 162 Newton Rd",
    "sg:city":"Wetherill Park",
    "sg:classifiers":[
        {
            "category":"Professional",
            "subcategory":"Accounting & Tax Preparation",
            "type":"Services"
        }
    ],
    "sg:phone":"+61 2 9609 2555",
    "sg:postcode":"2164",
    "sg:province":"NSW",
    "sg:tags":[
        "distributor",
        "lock",
        "mfrs"
    ],
    "wof:name":"Doric Products",
    "wof:placetype":"venue"
},
  "geometry": {"coordinates":[150.891357422,-33.8389167786],"type":"Point"}
}