{
  "type": "Feature",
  "properties": {
    "addr:full":"6 Webber Pde Keilor East VIC 3033",
    "addr:housenumber":"6",
    "addr:postcode":"3033",
    "addr:street":"Webber Pde",
    "iso:country":"AU",
    "sg:address":"6 Webber Pde",
    "sg:city":"Keilor East",
    "sg:classifiers":[
        {
            "category":"Bars & Pubs",
            "subcategory":"Lounge",
            "type":"Food & Drink"
        }
    ],
    "sg:phone":"+61 1300 662 221",
    "sg:postcode":"3033",
    "sg:province":"VIC",
    "sg:tags":[
        "water",
        "filter",
        "drinking"
    ],
    "sg:website":"http://www.showerscreens.com.au",
    "wof:name":"Designer Homewares",
    "wof:placetype":"venue"
},
  "geometry": {"coordinates":[144.853836,-37.737419],"type":"Point"}
}