{
  "type": "Feature",
  "properties": {
    "iso:country":"AU",
    "sg:address":"3 Ocean View Pde",
    "sg:city":"Caves Beach",
    "sg:classifiers":[
        {
            "category":"Professional",
            "subcategory":"Management & Consulting",
            "type":"Services"
        }
    ],
    "sg:phone":"+61 2 4972 1927",
    "sg:postcode":"2281",
    "sg:province":"NSW",
    "sg:tags":[
        "consultant",
        "business"
    ],
    "wof:name":"Penrith John Total Concept Marketing",
    "wof:placetype":"venue"
},
  "geometry": {"coordinates":[151.642303467,-33.1100883484],"type":"Point"}
}