{
  "type": "Feature",
  "properties": {
    "iso:country":"AU",
    "sg:address":"Unit 1, 3 Cobbler Pl",
    "sg:city":"Mirrabooka",
    "sg:classifiers":[
        {
            "category":"Shopping",
            "subcategory":"Party Supplies",
            "type":"Retail Goods"
        }
    ],
    "sg:phone":"+61 8 9344 2277",
    "sg:postcode":"6061",
    "sg:province":"WA",
    "sg:tags":[
        "equipment",
        "laminating"
    ],
    "wof:name":"Starleaton Digital Solutions",
    "wof:placetype":"venue"
},
  "geometry": {"coordinates":[115.862129211,-31.8737316132],"type":"Point"}
}