{
  "type": "Feature",
  "properties": {
    "iso:country":"AU",
    "sg:address":"Bellbrae Resort, Woodlands Rd",
    "sg:city":"Bellbrae",
    "sg:classifiers":[
        {
            "category":"Travel",
            "subcategory":"Resort",
            "type":"Entertainment"
        }
    ],
    "sg:phone":"+61 3 5261 5167",
    "sg:postcode":"3228",
    "sg:province":"VIC",
    "sg:tags":[
        "consultant",
        "timesharing"
    ],
    "wof:name":"Bellbrae Country Club",
    "wof:placetype":"venue"
},
  "geometry": {"coordinates":[144.26260400000001,-38.339062],"type":"Point"}
}