{
  "type": "Feature",
  "properties": {
    "addr:full":"Shop 7/ 239 Hamilton Rd Coogee WA 6166",
    "addr:housenumber":"shop 7 / 239",
    "addr:postcode":"6166",
    "addr:street":"Hamilton Rd",
    "iso:country":"AU",
    "sg:address":"Shop 7/ 239 Hamilton Rd",
    "sg:city":"Coogee",
    "sg:classifiers":[
        {
            "category":"Fast Food",
            "type":"Food & Drink"
        }
    ],
    "sg:phone":"+61 8 9494 1122",
    "sg:postcode":"6166",
    "sg:province":"WA",
    "sg:tags":[
        "away",
        "take"
    ],
    "wof:name":"Coogee Plaza Fish & Chips",
    "wof:placetype":"venue"
},
  "geometry": {"coordinates":[115.774849,-32.112553],"type":"Point"}
}