{
  "type": "Feature",
  "properties": {
    "addr:full":"Unit 5, 377 Hector St Yokine WA 6060",
    "addr:housenumber":"377",
    "addr:postcode":"6060",
    "addr:street":"Hector St",
    "iso:country":"AU",
    "sg:address":"Unit 5, 377 Hector St",
    "sg:city":"Yokine",
    "sg:classifiers":[
        {
            "category":"Health Services",
            "subcategory":"Doctor",
            "type":"Services"
        }
    ],
    "sg:phone":"+61 8 9443 5726",
    "sg:postcode":"6060",
    "sg:province":"WA",
    "sg:tags":[
        "reflexology"
    ],
    "wof:name":"Gary Jackson",
    "wof:placetype":"venue"
},
  "geometry": {"coordinates":[115.849113464,-31.904384613],"type":"Point"}
}