{
  "type": "Feature",
  "properties": {
    "iso:country":"AU",
    "sg:address":"13 Sun Crs",
    "sg:city":"Sunshine",
    "sg:classifiers":[
        {
            "category":"Personal",
            "subcategory":"Beauty Salon",
            "type":"Services"
        }
    ],
    "sg:phone":"+61 3 9311 4849",
    "sg:postcode":"3020",
    "sg:province":"VIC",
    "sg:tags":[
        "hairdresser"
    ],
    "wof:name":"Crescent Hair Stylist Pty Ltd",
    "wof:placetype":"venue"
},
  "geometry": {"coordinates":[144.832458,-37.787601],"type":"Point"}
}