{
  "type": "Feature",
  "properties": {
    "addr:full":"89 Wallace St Colac VIC 3250",
    "addr:housenumber":"89",
    "addr:postcode":"3250",
    "addr:street":"Wallace St",
    "iso:country":"AU",
    "sg:address":"89 Wallace St",
    "sg:city":"Colac",
    "sg:classifiers":[
        {
            "category":"Real Estate",
            "subcategory":"Real Estate Operator",
            "type":"Services"
        }
    ],
    "sg:phone":"+61 3 5232 1377",
    "sg:postcode":"3250",
    "sg:province":"VIC",
    "sg:tags":[
        "concrete",
        "pumping"
    ],
    "wof:name":"Colac Concrete Pumping",
    "wof:placetype":"venue"
},
  "geometry": {"coordinates":[143.60185200000001,-38.340683],"type":"Point"}
}