{
  "type": "Feature",
  "properties": {
    "addr:full":"13 Wharf St Port Douglas QLD 4877",
    "addr:housenumber":"13",
    "addr:postcode":"4877",
    "addr:street":"Wharf St",
    "iso:country":"AU",
    "sg:address":"13 Wharf St",
    "sg:city":"Port Douglas",
    "sg:classifiers":[
        {
            "category":"Communications",
            "subcategory":"News Services",
            "type":"Services"
        }
    ],
    "sg:phone":"+61 7 4084 2635",
    "sg:postcode":"4877",
    "sg:province":"QLD",
    "sg:tags":[
        "information",
        "tourist",
        "attractions"
    ],
    "wof:name":"Sun Palm Tours",
    "wof:placetype":"venue"
},
  "geometry": {"coordinates":[145.46232605,-16.4809837341],"type":"Point"}
}