{
  "type": "Feature",
  "properties": {
    "iso:country":"AU",
    "sg:address":"Bruce Hwy",
    "sg:city":"Rollingstone",
    "sg:classifiers":[
        {
            "category":"Travel",
            "subcategory":"Hotels & Motels",
            "type":"Entertainment"
        }
    ],
    "sg:phone":"+61 7 4770 7344",
    "sg:postcode":"4816",
    "sg:province":"QLD",
    "sg:tags":[
        "accommodation"
    ],
    "wof:name":"Rollingstone Hotel",
    "wof:placetype":"venue"
},
  "geometry": {"coordinates":[146.39186100000001,-19.04751],"type":"Point"}
}