{
  "type": "Feature",
  "properties": {
    "addr:full":"68 Garden St Narrabeen NSW 2101",
    "addr:housenumber":"68",
    "addr:postcode":"2101",
    "addr:street":"Garden St",
    "iso:country":"AU",
    "sg:address":"68 Garden St",
    "sg:city":"Narrabeen",
    "sg:classifiers":[
        {
            "category":"Autos & Motor Vehicles",
            "subcategory":"Automobile Sales",
            "type":"Retail Goods"
        }
    ],
    "sg:phone":"+61 2 9999 9000",
    "sg:postcode":"2101",
    "sg:province":"NSW",
    "sg:tags":[
        "car",
        "new"
    ],
    "wof:name":"Ward Mitsubishi",
    "wof:placetype":"venue"
},
  "geometry": {"coordinates":[151.29531900000001,-33.701691],"type":"Point"}
}