{
  "type": "Feature",
  "properties": {
    "iso:country":"AU",
    "sg:address":"45 Apps Ave",
    "sg:city":"Turramurra",
    "sg:classifiers":[
        {
            "category":"Health Services",
            "subcategory":"Doctor",
            "type":"Services"
        }
    ],
    "sg:phone":"+61 2 9402 9393",
    "sg:postcode":"2074",
    "sg:province":"NSW",
    "sg:tags":[
        "nurse",
        "nursing"
    ],
    "wof:name":"Quality Medical Nursing Services",
    "wof:placetype":"venue"
},
  "geometry": {"coordinates":[151.14837646500001,-33.7202339172],"type":"Point"}
}