{
  "type": "Feature",
  "properties": {
    "addr:full":"26 Norman St St Albans VIC 3021",
    "addr:housenumber":"26",
    "addr:postcode":"3021",
    "addr:street":"Norman St",
    "iso:country":"AU",
    "sg:address":"26 Norman St",
    "sg:city":"St Albans",
    "sg:classifiers":[
        {
            "category":"Building & Trades",
            "subcategory":"Construction",
            "type":"Services"
        }
    ],
    "sg:phone":"+61 3 9367 4787",
    "sg:postcode":"3021",
    "sg:province":"VIC",
    "sg:tags":[
        "window",
        "aluminium"
    ],
    "wof:name":"Ollurac Pty Ltd",
    "wof:placetype":"venue"
},
  "geometry": {"coordinates":[144.81573499999999,-37.735325],"type":"Point"}
}