{
  "type": "Feature",
  "properties": {
    "addr:full":"Shop 113 Reading Newmarket 400 Newmarket Rd Newmarket QLD 4051",
    "addr:housenumber":"113;400",
    "addr:postcode":"4051",
    "addr:street":"Reading Newmarket;Newmarket Rd",
    "iso:country":"AU",
    "sg:address":"Shop 113 Reading Newmarket 400 Newmarket Rd",
    "sg:city":"Newmarket",
    "sg:classifiers":[
        {
            "category":"Travel",
            "subcategory":"Travel Agent",
            "type":"Entertainment"
        }
    ],
    "sg:phone":"+61 13 18 66",
    "sg:postcode":"4051",
    "sg:province":"QLD",
    "sg:tags":[
        "consultant"
    ],
    "wof:name":"Flight Centre",
    "wof:placetype":"venue"
},
  "geometry": {"coordinates":[153.00823974599999,-27.4366436005],"type":"Point"}
}