{
  "type": "Feature",
  "properties": {
    "addr:full":"20 Rudloc Rd Morley WA 6062",
    "addr:housenumber":"20",
    "addr:postcode":"6062",
    "addr:street":"Rudloc Rd",
    "iso:country":"AU",
    "sg:address":"20 Rudloc Rd",
    "sg:city":"Morley",
    "sg:classifiers":[
        {
            "category":"Retail",
            "subcategory":"Veterinary Services",
            "type":"Services"
        }
    ],
    "sg:phone":"+61 8 9275 3000",
    "sg:postcode":"6062",
    "sg:province":"WA",
    "sg:tags":[
        "surgeon"
    ],
    "sg:website":"http://www.vetcentre.com.au",
    "wof:name":"Morley Vet Centre",
    "wof:placetype":"venue"
},
  "geometry": {"coordinates":[115.896949768,-31.9018001556],"type":"Point"}
}