{
  "type": "Feature",
  "properties": {
    "addr:full":"Hampton Drv Tannum Sands QLD 4680",
    "addr:postcode":"4680",
    "addr:street":"Hampton Drv",
    "iso:country":"AU",
    "sg:address":"Hampton Drv",
    "sg:city":"Tannum Sands",
    "sg:classifiers":[
        {
            "category":"Fast Food",
            "type":"Food & Drink"
        }
    ],
    "sg:phone":"+61 7 4973 2476",
    "sg:postcode":"4680",
    "sg:province":"QLD",
    "sg:tags":[
        "away",
        "take"
    ],
    "wof:name":"KFC",
    "wof:placetype":"venue"
},
  "geometry": {"coordinates":[151.370239258,-23.9520626068],"type":"Point"}
}