{
  "type": "Feature",
  "properties": {
    "iso:country":"AU",
    "sg:address":"Square 3 Holm Pl",
    "sg:city":"Shellharbour",
    "sg:classifiers":[
        {
            "category":"Banks & Credit Unions",
            "subcategory":"Bank",
            "type":"Services"
        }
    ],
    "sg:phone":"+61 13 20 32",
    "sg:postcode":"2529",
    "sg:province":"NSW",
    "wof:name":"Westpac Banking Corporation",
    "wof:placetype":"venue"
},
  "geometry": {"coordinates":[150.837402344,-34.5632476807],"type":"Point"}
}