{
  "type": "Feature",
  "properties": {
    "addr:full":"8a/ 39 Lawrence Drv Nerang QLD 4211",
    "addr:housenumber":"8a / 39",
    "addr:postcode":"4211",
    "addr:street":"Lawrence Drv",
    "iso:country":"AU",
    "sg:address":"8a/ 39 Lawrence Drv",
    "sg:city":"Nerang",
    "sg:classifiers":[
        {
            "category":"Real Estate",
            "subcategory":"Real Estate Agent",
            "type":"Services"
        }
    ],
    "sg:phone":"+61 7 5500 4700",
    "sg:postcode":"4211",
    "sg:province":"QLD",
    "wof:name":"Go Gecko",
    "wof:placetype":"venue"
},
  "geometry": {"coordinates":[153.34681701700001,-27.997177124],"type":"Point"}
}