{
  "type": "Feature",
  "properties": {
    "iso:country":"AU",
    "sg:address":"Jack Hore Pl",
    "sg:city":"Wodonga",
    "sg:classifiers":[
        {
            "category":"Government",
            "subcategory":"City Hall",
            "type":"Public Place"
        }
    ],
    "sg:phone":"+61 2 6056 2452",
    "sg:postcode":"3690",
    "sg:province":"VIC",
    "wof:name":"Wodonga Masonic Centre",
    "wof:placetype":"venue"
},
  "geometry": {"coordinates":[146.88851928700001,-36.1207122803],"type":"Point"}
}