{
  "type": "Feature",
  "properties": {
    "addr:full":"108 High St Marmion WA 6020",
    "addr:housenumber":"108",
    "addr:postcode":"6020",
    "addr:street":"High St",
    "iso:country":"AU",
    "sg:address":"108 High St",
    "sg:city":"Marmion",
    "sg:classifiers":[
        {
            "category":"Education",
            "subcategory":"Kindergarten",
            "type":"Public Place"
        }
    ],
    "sg:phone":"+61 8 9448 9541",
    "sg:postcode":"6020",
    "sg:province":"WA",
    "sg:tags":[
        "pre-schools"
    ],
    "wof:name":"Marmion Kindergarten",
    "wof:placetype":"venue"
},
  "geometry": {"coordinates":[115.759529114,-31.8366851807],"type":"Point"}
}