{
  "type": "Feature",
  "properties": {
    "iso:country":"AU",
    "sg:address":"59- 61 Goulbourn St",
    "sg:city":"Sydney",
    "sg:classifiers":[
        {
            "category":"Organizations",
            "subcategory":"Professional Association",
            "type":"Services"
        }
    ],
    "sg:phone":"+61 2 9274 1400",
    "sg:postcode":"2000",
    "sg:province":"NSW",
    "sg:tags":[
        "organisation",
        "business"
    ],
    "wof:name":"New South Wales Minerals Council Ltd",
    "wof:placetype":"venue"
},
  "geometry": {"coordinates":[151.20698547399999,-33.8781242371],"type":"Point"}
}