{
  "type": "Feature",
  "properties": {
    "addr:full":"7 Welbourne St Mitcham SA 5062",
    "addr:housenumber":"7",
    "addr:postcode":"5062",
    "addr:street":"Welbourne St",
    "iso:country":"AU",
    "sg:address":"7 Welbourne St",
    "sg:city":"Mitcham",
    "sg:classifiers":[
        {
            "category":"Real Estate",
            "subcategory":"Real Estate Agent",
            "type":"Services"
        }
    ],
    "sg:phone":"+61 8 8271 5333",
    "sg:postcode":"5062",
    "sg:province":"SA",
    "wof:name":"Dowling City Country",
    "wof:placetype":"venue"
},
  "geometry": {"coordinates":[138.620635986,-34.9782066345],"type":"Point"}
}