{
  "type": "Feature",
  "properties": {
    "addr:full":"38 Finsbury St Newmarket QLD 4051",
    "addr:housenumber":"38",
    "addr:postcode":"4051",
    "addr:street":"Finsbury St",
    "iso:country":"AU",
    "sg:address":"38 Finsbury St",
    "sg:city":"Newmarket",
    "sg:classifiers":[
        {
            "category":"Transit Center",
            "subcategory":"Freight",
            "type":"Transportation"
        }
    ],
    "sg:phone":"+61 7 3852 6000",
    "sg:postcode":"4051",
    "sg:province":"QLD",
    "sg:tags":[
        "transfer",
        "emblem"
    ],
    "wof:name":"Wearable Words",
    "wof:placetype":"venue"
},
  "geometry": {"coordinates":[153.01422119099999,-27.4375514984],"type":"Point"}
}