{
  "type": "Feature",
  "properties": {
    "addr:full":"U2/ 3 Cullen Pl Smithfield NSW 2164",
    "addr:housenumber":"3",
    "addr:postcode":"2164",
    "addr:street":"U2 /",
    "iso:country":"AU",
    "sg:address":"U2/ 3 Cullen Pl",
    "sg:city":"Smithfield",
    "sg:classifiers":[
        {
            "category":"Banks & Credit Unions",
            "subcategory":"Financial Services",
            "type":"Services"
        }
    ],
    "sg:phone":"+61 404 039 172",
    "sg:postcode":"2164",
    "sg:province":"NSW",
    "sg:tags":[
        "wholesaler",
        "mfrs",
        "gear"
    ],
    "wof:name":"Cut & Grind Precision Gears",
    "wof:placetype":"venue"
},
  "geometry": {"coordinates":[150.95010375999999,-33.8416900635],"type":"Point"}
}