{
  "type": "Feature",
  "properties": {
    "addr:full":"L1, 21 Willoughby Rd Crows Nest NSW 2065",
    "addr:housenumber":"21",
    "addr:postcode":"2065",
    "addr:street":"L1;Willoughby Rd",
    "iso:country":"AU",
    "sg:address":"L1, 21 Willoughby Rd",
    "sg:city":"Crows Nest",
    "sg:classifiers":[
        {
            "category":"Real Estate",
            "subcategory":"Architect",
            "type":"Services"
        }
    ],
    "sg:phone":"+61 2 9437 5444",
    "sg:postcode":"2065",
    "sg:province":"NSW",
    "wof:name":"Melinz Kim & Associates Pty Ltd",
    "wof:placetype":"venue"
},
  "geometry": {"coordinates":[151.20103454599999,-33.8269996643],"type":"Point"}
}