{
  "type": "Feature",
  "properties": {
    "addr:full":"Level 1, 541 Pittwater Rd Brookvale NSW 2100",
    "addr:housenumber":"541",
    "addr:postcode":"2100",
    "addr:street":"Pittwater Rd",
    "iso:country":"AU",
    "sg:address":"Level 1, 541 Pittwater Rd",
    "sg:city":"Brookvale",
    "sg:classifiers":[
        {
            "category":"Organizations",
            "subcategory":"Professional Association",
            "type":"Services"
        }
    ],
    "sg:phone":"+61 2 9939 4545",
    "sg:postcode":"2100",
    "sg:province":"NSW",
    "sg:tags":[
        "web",
        "internet"
    ],
    "wof:name":"Epic MultiMedia",
    "wof:placetype":"venue"
},
  "geometry": {"coordinates":[151.275466919,-33.7611351013],"type":"Point"}
}