{
  "type": "Feature",
  "properties": {
    "iso:country":"AU",
    "sg:address":"390 Brighton Rd",
    "sg:city":"Hove",
    "sg:classifiers":[
        {
            "category":"Health Services",
            "subcategory":"Doctor",
            "type":"Services"
        }
    ],
    "sg:phone":"+61 8 8296 8336",
    "sg:postcode":"5048",
    "sg:province":"SA",
    "sg:tags":[
        "medical",
        "practitioner"
    ],
    "wof:name":"Duguid Phillip Dr",
    "wof:placetype":"venue"
},
  "geometry": {"coordinates":[138.522385,-35.011616],"type":"Point"}
}