{
  "type": "Feature",
  "properties": {
    "addr:full":"200 Bessie Creek Rd Nar Nar Goon VIC 3812",
    "addr:housenumber":"200",
    "addr:postcode":"3812",
    "addr:street":"Bessie Creek Rd",
    "iso:country":"AU",
    "sg:address":"200 Bessie Creek Rd",
    "sg:city":"Nar Nar Goon",
    "sg:classifiers":[
        {
            "category":"Banks & Credit Unions",
            "subcategory":"Investment Brokerage",
            "type":"Services"
        }
    ],
    "sg:phone":"+61 3 5942 5512",
    "sg:postcode":"3812",
    "sg:province":"VIC",
    "sg:tags":[
        "builder",
        "coach",
        "carriage"
    ],
    "wof:name":"Dingle's Coachworks",
    "wof:placetype":"venue"
},
  "geometry": {"coordinates":[145.56880200000001,-38.05098],"type":"Point"}
}