{
  "type": "Feature",
  "properties": {
    "addr:full":"25 MacGregor Drv Birkdale QLD 4159",
    "addr:housenumber":"25",
    "addr:postcode":"4159",
    "addr:street":"Macgregor Drv",
    "iso:country":"AU",
    "sg:address":"25 MacGregor Drv",
    "sg:city":"Birkdale",
    "sg:classifiers":[
        {
            "category":"Health Services",
            "subcategory":"Nursing And Care Facility",
            "type":"Services"
        }
    ],
    "sg:phone":"+61 7 3207 5666",
    "sg:postcode":"4159",
    "sg:province":"QLD",
    "sg:tags":[
        "home"
    ],
    "wof:name":"Regis Grange Wellington Point",
    "wof:placetype":"venue"
},
  "geometry": {"coordinates":[153.22601318400001,-27.4922142029],"type":"Point"}
}