{
  "type": "Feature",
  "properties": {
    "addr:full":"15 St Marks Crs Figtree NSW 2525",
    "addr:housenumber":"15",
    "addr:postcode":"2525",
    "addr:street":"St Marks Crs",
    "iso:country":"AU",
    "sg:address":"15 St Marks Crs",
    "sg:city":"Figtree",
    "sg:classifiers":[
        {
            "category":"Home & Garden",
            "subcategory":"Carpets & Floor Coverings",
            "type":"Retail Goods"
        }
    ],
    "sg:phone":"+61 2 4228 9235",
    "sg:postcode":"2525",
    "sg:province":"NSW",
    "sg:tags":[
        "tile",
        "wall",
        "layer"
    ],
    "wof:name":"Giusti A",
    "wof:placetype":"venue"
},
  "geometry": {"coordinates":[150.850097656,-34.430519104],"type":"Point"}
}