{
  "type": "Feature",
  "properties": {
    "addr:full":"1 Allen Drv Irymple VIC 3498",
    "addr:housenumber":"1",
    "addr:postcode":"3498",
    "addr:street":"Allen Drv",
    "iso:country":"AU",
    "sg:address":"1 Allen Drv",
    "sg:city":"Irymple",
    "sg:classifiers":[
        {
            "category":"Government",
            "subcategory":"Fire Station",
            "type":"Public Place"
        }
    ],
    "sg:phone":"+61 3 5024 7112",
    "sg:postcode":"3498",
    "sg:province":"VIC",
    "sg:tags":[
        "box",
        "case",
        "wood",
        "secondhand"
    ],
    "wof:name":"Carter Holt Harvey Corrugated Packaging",
    "wof:placetype":"venue"
},
  "geometry": {"coordinates":[142.16481018100001,-34.2399139404],"type":"Point"}
}