{
  "type": "Feature",
  "properties": {
    "iso:country":"AU",
    "sg:address":"7053 Dartmoor Hamilton Rd",
    "sg:city":"Hamilton",
    "sg:classifiers":[
        {
            "category":"Commercial Area",
            "type":"Public Place"
        }
    ],
    "sg:phone":"+61 3 5572 3877",
    "sg:postcode":"3300",
    "sg:province":"VIC",
    "sg:tags":[
        "heavy",
        "carrier"
    ],
    "wof:name":"Ross Fitzgerald Concrete Construction",
    "wof:placetype":"venue"
},
  "geometry": {"coordinates":[141.98292541500001,-37.7443199158],"type":"Point"}
}