{
  "type": "Feature",
  "properties": {
    "addr:full":"25 Hamilton St Oakleigh VIC 3166",
    "addr:housenumber":"25",
    "addr:postcode":"3166",
    "addr:street":"Hamilton St",
    "iso:country":"AU",
    "sg:address":"25 Hamilton St",
    "sg:city":"Oakleigh",
    "sg:classifiers":[
        {
            "category":"Shopping",
            "subcategory":"Party Supplies",
            "type":"Retail Goods"
        }
    ],
    "sg:phone":"+61 1300 669 201",
    "sg:postcode":"3166",
    "sg:province":"VIC",
    "sg:website":"http://www.hartspartyhire.com.au",
    "wof:name":"Harts Party Hire",
    "wof:placetype":"venue"
},
  "geometry": {"coordinates":[145.10044860799999,-37.9084739685],"type":"Point"}
}