{
  "type": "Feature",
  "properties": {
    "addr:full":"Shop 1171 Westfield Geelong VIC 3220",
    "addr:housenumber":"1171",
    "addr:postcode":"3220",
    "iso:country":"AU",
    "sg:address":"Shop 1171 Westfield",
    "sg:city":"Geelong",
    "sg:classifiers":[
        {
            "category":"Manufacturing",
            "subcategory":"Jewelry",
            "type":"Manufacturing & Wholesale Goods"
        }
    ],
    "sg:phone":"+61 3 5229 5555",
    "sg:postcode":"3220",
    "sg:province":"VIC",
    "sg:tags":[
        "mfrg",
        "jeweller"
    ],
    "wof:name":"Duffs Jewellers",
    "wof:placetype":"venue"
},
  "geometry": {"coordinates":[144.35992400000001,-38.148674],"type":"Point"}
}