{
  "type": "Feature",
  "properties": {
    "iso:country":"AU",
    "sg:address":"Quin Rd",
    "sg:city":"Gingin West",
    "sg:classifiers":[
        {
            "category":"Food & Beverages",
            "subcategory":"Fruits & Vegetables",
            "type":"Retail Goods"
        }
    ],
    "sg:phone":"+61 418 669 799",
    "sg:postcode":"6503",
    "sg:province":"WA",
    "sg:tags":[
        "grower"
    ],
    "wof:name":"Western Waterchestnuts",
    "wof:placetype":"venue"
},
  "geometry": {"coordinates":[115.75054900000001,-31.322235],"type":"Point"}
}