{
  "type": "Feature",
  "properties": {
    "addr:full":"2 Highlands Rd Thomastown VIC 3074",
    "addr:housenumber":"2",
    "addr:postcode":"3074",
    "addr:street":"Highlands Rd",
    "iso:country":"AU",
    "sg:address":"2 Highlands Rd",
    "sg:city":"Thomastown",
    "sg:classifiers":[
        {
            "category":"Health Services",
            "subcategory":"Doctor",
            "type":"Services"
        }
    ],
    "sg:phone":"+61 3 9465 0186",
    "sg:postcode":"3074",
    "sg:province":"VIC",
    "sg:tags":[
        "medical",
        "practitioner"
    ],
    "wof:name":"Highlands Medical Clinic",
    "wof:placetype":"venue"
},
  "geometry": {"coordinates":[145.013793945,-37.6790237427],"type":"Point"}
}