{
  "type": "Feature",
  "properties": {
    "iso:country":"AU",
    "sg:address":"Shop 4, 215 Waterworks Rd",
    "sg:city":"Ashgrove",
    "sg:classifiers":[
        {
            "category":"Professional",
            "subcategory":"Printing & Photocopies",
            "type":"Services"
        }
    ],
    "sg:phone":"+61 7 3366 0455",
    "sg:postcode":"4060",
    "sg:province":"QLD",
    "sg:tags":[
        "laminating"
    ],
    "wof:name":"Ashgrove Fast Photos",
    "wof:placetype":"venue"
},
  "geometry": {"coordinates":[152.99200439399999,-27.445684433],"type":"Point"}
}