{
  "type": "Feature",
  "properties": {
    "addr:full":"201 High St Thomastown VIC 3074",
    "addr:housenumber":"201",
    "addr:postcode":"3074",
    "addr:street":"High St",
    "iso:country":"AU",
    "sg:address":"201 High St",
    "sg:city":"Thomastown",
    "sg:classifiers":[
        {
            "category":"Real Estate",
            "subcategory":"Real Estate Agent",
            "type":"Services"
        }
    ],
    "sg:phone":"+61 3 9465 2133",
    "sg:postcode":"3074",
    "sg:province":"VIC",
    "wof:name":"Love Real Estate",
    "wof:placetype":"venue"
},
  "geometry": {"coordinates":[145.01365661599999,-37.6803131104],"type":"Point"}
}