{
  "type": "Feature",
  "properties": {
    "addr:full":"46 Country Club Dr Chirnside Park VIC 3116",
    "addr:housenumber":"46",
    "addr:postcode":"3116",
    "addr:street":"Country Club Dr",
    "iso:country":"AU",
    "sg:address":"46 Country Club Dr",
    "sg:city":"Chirnside Park",
    "sg:classifiers":[
        {
            "category":"Professional",
            "subcategory":"Accounting & Tax Preparation",
            "type":"Services"
        }
    ],
    "sg:phone":"+61 3 9777 0505",
    "sg:postcode":"3116",
    "sg:province":"VIC",
    "sg:tags":[
        "bookkeeping"
    ],
    "wof:name":"Award Bookkeeping Company (Lilydale)",
    "wof:placetype":"venue"
},
  "geometry": {"coordinates":[145.324752808,-37.7548789978],"type":"Point"}
}