{
  "type": "Feature",
  "properties": {
    "iso:country":"AU",
    "sg:address":"PO Box 3067",
    "sg:city":"Rundle Mall",
    "sg:classifiers":[
        {
            "category":"Autos & Motor Vehicles",
            "subcategory":"Boat Sales",
            "type":"Retail Goods"
        }
    ],
    "sg:phone":"+61 407 447 884",
    "sg:postcode":"5000",
    "sg:province":"SA",
    "sg:tags":[
        "dictating",
        "machine"
    ],
    "wof:name":"dictationshop.com.au",
    "wof:placetype":"venue"
},
  "geometry": {"coordinates":[138.59693908700001,-34.922908783],"type":"Point"}
}