{
  "type": "Feature",
  "properties": {
    "addr:full":"85-91 Commercial Rd Yarram VIC 3971",
    "addr:housenumber":"85-91",
    "addr:postcode":"3971",
    "addr:street":"Commercial Rd",
    "iso:country":"AU",
    "sg:address":"85-91 Commercial Rd",
    "sg:city":"Yarram",
    "sg:classifiers":[
        {
            "category":"Health Services",
            "subcategory":"Doctor",
            "type":"Services"
        }
    ],
    "sg:phone":"+61 3 5182 0333",
    "sg:postcode":"3971",
    "sg:province":"VIC",
    "sg:tags":[
        "medical",
        "practitioner"
    ],
    "wof:name":"Yarram Medical Centre",
    "wof:placetype":"venue"
},
  "geometry": {"coordinates":[146.67747497600001,-38.5576553345],"type":"Point"}
}