{
  "type": "Feature",
  "properties": {
    "iso:country":"AU",
    "sg:address":"171 Bateau Bay Rd",
    "sg:city":"Bateau Bay",
    "sg:classifiers":[
        {
            "category":"Building & Trades",
            "subcategory":"Construction",
            "type":"Services"
        }
    ],
    "sg:phone":"+61 412 515 788",
    "sg:postcode":"2261",
    "sg:province":"NSW",
    "sg:tags":[
        "contractor"
    ],
    "wof:name":"P.A. & J.M. Reynolds Pty Ltd",
    "wof:placetype":"venue"
},
  "geometry": {"coordinates":[151.477097,-33.386536],"type":"Point"}
}