{
  "type": "Feature",
  "properties": {
    "iso:country":"AU",
    "sg:address":"43 Kurrajong Rd",
    "sg:city":"Safety Bay",
    "sg:classifiers":[
        {
            "category":"Retail",
            "subcategory":"Auto Repair",
            "type":"Services"
        }
    ],
    "sg:phone":"+61 8 9527 9315",
    "sg:postcode":"6169",
    "sg:province":"WA",
    "sg:tags":[
        "repairer",
        "motor",
        "engineer"
    ],
    "wof:name":"D B's Decarbon Service",
    "wof:placetype":"venue"
},
  "geometry": {"coordinates":[115.73111,-32.29911],"type":"Point"}
}