{
  "type": "Feature",
  "properties": {
    "addr:full":"118 Mentone Pde Mentone VIC 3194",
    "addr:housenumber":"118",
    "addr:postcode":"3194",
    "addr:street":"Mentone Pde",
    "iso:country":"AU",
    "sg:address":"118 Mentone Pde",
    "sg:city":"Mentone",
    "sg:classifiers":[
        {
            "category":"Education",
            "subcategory":"School",
            "type":"Public Place"
        }
    ],
    "sg:phone":"+61 3 9584 7766",
    "sg:postcode":"3194",
    "sg:province":"VIC",
    "sg:tags":[
        "girl"
    ],
    "wof:name":"Kilbreda College",
    "wof:placetype":"venue"
},
  "geometry": {"coordinates":[145.064987183,-37.9838104248],"type":"Point"}
}