{
  "type": "Feature",
  "properties": {
    "addr:full":"2 Castlereagh St Penrith NSW 2750",
    "addr:housenumber":"2",
    "addr:postcode":"2750",
    "addr:street":"Castlereagh St",
    "iso:country":"AU",
    "sg:address":"2 Castlereagh St",
    "sg:city":"Penrith",
    "sg:classifiers":[
        {
            "category":"Professional",
            "subcategory":"Accounting & Tax Preparation",
            "type":"Services"
        }
    ],
    "sg:phone":"+61 2 4721 2198",
    "sg:postcode":"2750",
    "sg:province":"NSW",
    "sg:tags":[
        "consultant",
        "taxation"
    ],
    "wof:name":"Nepean & Rossmore Taxation Services",
    "wof:placetype":"venue"
},
  "geometry": {"coordinates":[150.86148071299999,-33.6805686951],"type":"Point"}
}