{
  "type": "Feature",
  "properties": {
    "addr:full":"PMB 63 Streaky Bay 5680 Nunjikompita SA 5680",
    "addr:housenumber":"63;5680",
    "addr:postcode":"5680",
    "addr:street":"Streaky Bay",
    "iso:country":"AU",
    "sg:address":"PMB 63 Streaky Bay 5680",
    "sg:city":"Nunjikompita",
    "sg:classifiers":[
        {
            "category":"Farming",
            "subcategory":"Farm",
            "type":"Manufacturing & Wholesale Goods"
        }
    ],
    "sg:phone":"+61 8 8625 4020",
    "sg:postcode":"5680",
    "sg:province":"SA",
    "sg:tags":[
        "farmer"
    ],
    "wof:name":"Ryan G A & S F",
    "wof:placetype":"venue"
},
  "geometry": {"coordinates":[134.21116638199999,-32.7962875366],"type":"Point"}
}