{
  "type": "Feature",
  "properties": {
    "addr:full":"204 Yarmouth Pl Narellan NSW 2567",
    "addr:housenumber":"204",
    "addr:postcode":"2567",
    "addr:street":"Yarmouth Pl",
    "iso:country":"AU",
    "sg:address":"204 Yarmouth Pl",
    "sg:city":"Narellan",
    "sg:classifiers":[
        {
            "category":"Autos & Motor Vehicles",
            "subcategory":"Automobile Sales",
            "type":"Retail Goods"
        }
    ],
    "sg:phone":"+61 2 4648 3800",
    "sg:postcode":"2567",
    "sg:province":"NSW",
    "sg:tags":[
        "car",
        "new"
    ],
    "wof:name":"Bell Automotive",
    "wof:placetype":"venue"
},
  "geometry": {"coordinates":[150.75071716299999,-34.0410346985],"type":"Point"}
}