{
  "type": "Feature",
  "properties": {
    "addr:full":"2 Bartley St Moyhu VIC 3732",
    "addr:housenumber":"2",
    "addr:postcode":"3732",
    "addr:street":"Bartley St",
    "iso:country":"AU",
    "sg:address":"2 Bartley St",
    "sg:city":"Moyhu",
    "sg:classifiers":[
        {
            "category":"Professional",
            "type":"Services"
        }
    ],
    "sg:phone":"+61 3 5727 9417",
    "sg:postcode":"3732",
    "sg:province":"VIC",
    "sg:tags":[
        "shop",
        "fitting"
    ],
    "wof:name":"G.V. Mobile Furniture & Shelving",
    "wof:placetype":"venue"
},
  "geometry": {"coordinates":[146.37826538100001,-36.5779914856],"type":"Point"}
}