{
  "type": "Feature",
  "properties": {
    "addr:full":"31 Victory Rd Airport West VIC 3042",
    "addr:housenumber":"31",
    "addr:postcode":"3042",
    "addr:street":"Victory Rd",
    "iso:country":"AU",
    "sg:address":"31 Victory Rd",
    "sg:city":"Airport West",
    "sg:classifiers":[
        {
            "category":"Retail",
            "subcategory":"Auto Repair",
            "type":"Services"
        }
    ],
    "sg:phone":"+61 3 9338 0618",
    "sg:postcode":"3042",
    "sg:province":"VIC",
    "sg:tags":[
        "beater",
        "painter",
        "panel"
    ],
    "wof:name":"Body Corp Airport West",
    "wof:placetype":"venue"
},
  "geometry": {"coordinates":[144.88908386200001,-37.7185745239],"type":"Point"}
}