{
  "type": "Feature",
  "properties": {
    "addr:full":"Old South Rd Yankalilla SA 5203",
    "addr:postcode":"5203",
    "addr:street":"Old South Rd",
    "iso:country":"AU",
    "sg:address":"Old South Rd",
    "sg:city":"Yankalilla",
    "sg:classifiers":[
        {
            "category":"Arena",
            "subcategory":"Sports Club",
            "type":"Entertainment"
        }
    ],
    "sg:phone":"+61 428 136 091",
    "sg:postcode":"5203",
    "sg:province":"SA",
    "sg:tags":[
        "defence",
        "supply",
        "self",
        "instruction",
        "martial art"
    ],
    "wof:name":"JKA Karate",
    "wof:placetype":"venue"
},
  "geometry": {"coordinates":[138.33190918,-35.4534683228],"type":"Point"}
}