{
  "type": "Feature",
  "properties": {
    "iso:country":"AU",
    "sg:address":"2 Elvie St",
    "sg:city":"Doncaster East",
    "sg:classifiers":[
        {
            "category":"Health Services",
            "subcategory":"Dentist",
            "type":"Services"
        }
    ],
    "sg:phone":"+61 3 9842 6671",
    "sg:postcode":"3109",
    "sg:province":"VIC",
    "wof:name":"Wood M T & G Drs",
    "wof:placetype":"venue"
},
  "geometry": {"coordinates":[145.169311523,-37.7902336121],"type":"Point"}
}