{
  "type": "Feature",
  "properties": {
    "iso:country":"AU",
    "sg:address":"29 Quandong Pkwy",
    "sg:city":"Halls Head",
    "sg:classifiers":[
        {
            "category":"Real Estate",
            "subcategory":"Real Estate Agent",
            "type":"Services"
        }
    ],
    "sg:phone":"+61 8 9535 6355",
    "sg:postcode":"6210",
    "sg:province":"WA",
    "sg:website":"http://www.russellberry.com.au",
    "wof:name":"Russell Berry Team Realty",
    "wof:placetype":"venue"
},
  "geometry": {"coordinates":[115.684196,-32.552471],"type":"Point"}
}