{
  "type": "Feature",
  "properties": {
    "addr:full":"116 Garsed St Bendigo VIC 3550",
    "addr:housenumber":"116",
    "addr:postcode":"3550",
    "addr:street":"Garsed St",
    "iso:country":"AU",
    "sg:address":"116 Garsed St",
    "sg:city":"Bendigo",
    "sg:classifiers":[
        {
            "category":"Building & Trades",
            "subcategory":"Construction",
            "type":"Services"
        }
    ],
    "sg:phone":"+61 3 5442 3100",
    "sg:postcode":"3550",
    "sg:province":"VIC",
    "sg:tags":[
        "roof"
    ],
    "wof:name":"Pilcher Home Improvements",
    "wof:placetype":"venue"
},
  "geometry": {"coordinates":[144.276687622,-36.7668647766],"type":"Point"}
}