{
  "type": "Feature",
  "properties": {
    "iso:country":"AU",
    "sg:address":"PO Box 1105 MDC",
    "sg:city":"Narre Warren Delivery Cntr",
    "sg:classifiers":[
        {
            "category":"Building & Trades",
            "subcategory":"Construction",
            "type":"Services"
        }
    ],
    "sg:phone":"+61 418 350 480",
    "sg:postcode":"3805",
    "sg:province":"VIC",
    "sg:tags":[
        "polishing",
        "sanding",
        "floor"
    ],
    "wof:name":"Dingley Floor Sanding Pty Ltd",
    "wof:placetype":"venue"
},
  "geometry": {"coordinates":[145.306976,-38.026012],"type":"Point"}
}