{
  "type": "Feature",
  "properties": {
    "iso:country":"AU",
    "sg:address":"Presto Ave",
    "sg:city":"Mackay",
    "sg:classifiers":[
        {
            "category":"Professional",
            "subcategory":"Engineering",
            "type":"Services"
        }
    ],
    "sg:phone":"+61 7 4955 8200",
    "sg:postcode":"4740",
    "sg:province":"QLD",
    "sg:tags":[
        "engineer"
    ],
    "wof:name":"REB Engineering Pty Ltd",
    "wof:placetype":"venue"
},
  "geometry": {"coordinates":[149.21170000000001,-21.109825],"type":"Point"}
}