{
  "type": "Feature",
  "properties": {
    "addr:full":"77 Sutherland St Jannali NSW 2226",
    "addr:housenumber":"77",
    "addr:postcode":"2226",
    "addr:street":"Sutherland St",
    "iso:country":"AU",
    "sg:address":"77 Sutherland St",
    "sg:city":"Jannali",
    "sg:classifiers":[
        {
            "category":"Wholesale",
            "subcategory":"Scrap",
            "type":"Manufacturing & Wholesale Goods"
        }
    ],
    "sg:phone":"+61 418 235 820",
    "sg:postcode":"2226",
    "sg:province":"NSW",
    "sg:tags":[
        "merchant",
        "metal"
    ],
    "wof:name":"R & J Scrap Metal",
    "wof:placetype":"venue"
},
  "geometry": {"coordinates":[151.06228637699999,-34.0146560669],"type":"Point"}
}