{
  "type": "Feature",
  "properties": {
    "iso:country":"AU",
    "sg:address":"Shop 1, Glen St",
    "sg:city":"Belrose",
    "sg:classifiers":[
        {
            "category":"Food & Beverages",
            "subcategory":"Liquor & Beverages",
            "type":"Retail Goods"
        }
    ],
    "sg:phone":"+61 2 9452 2294",
    "sg:postcode":"2085",
    "sg:province":"NSW",
    "sg:tags":[
        "store"
    ],
    "wof:name":"Sheargold Cellars Belrose",
    "wof:placetype":"venue"
},
  "geometry": {"coordinates":[151.219314575,-33.7391357422],"type":"Point"}
}