{
  "type": "Feature",
  "properties": {
    "iso:country":"AU",
    "sg:address":"168 West St",
    "sg:city":"Umina",
    "sg:classifiers":[
        {
            "category":"Retail",
            "subcategory":"Veterinary Services",
            "type":"Services"
        }
    ],
    "sg:phone":"+61 2 4341 6659",
    "sg:postcode":"2257",
    "sg:province":"NSW",
    "sg:tags":[
        "surgeon"
    ],
    "wof:name":"Pelling R J & Whight W R & Moules C",
    "wof:placetype":"venue"
},
  "geometry": {"coordinates":[151.325881958,-33.5223731995],"type":"Point"}
}