{
  "type": "Feature",
  "properties": {
    "addr:full":"42 Wattlepark Ave Moolap VIC 3221",
    "addr:housenumber":"42",
    "addr:postcode":"3221",
    "addr:street":"Wattlepark Ave",
    "iso:country":"AU",
    "sg:address":"42 Wattlepark Ave",
    "sg:city":"Moolap",
    "sg:classifiers":[
        {
            "category":"Retail",
            "subcategory":"Auto Repair",
            "type":"Services"
        }
    ],
    "sg:phone":"+61 3 5248 2692",
    "sg:postcode":"3221",
    "sg:province":"VIC",
    "sg:tags":[
        "electrical"
    ],
    "wof:name":"Mega Automotive Services",
    "wof:placetype":"venue"
},
  "geometry": {"coordinates":[144.40875199999999,-38.166523],"type":"Point"}
}