{
  "type": "Feature",
  "properties": {
    "iso:country":"AU",
    "sg:address":"638 Canterbury Rd",
    "sg:city":"Belmore",
    "sg:classifiers":[
        {
            "category":"Fast Food",
            "type":"Food & Drink"
        }
    ],
    "sg:phone":"+61 2 9718 3735",
    "sg:postcode":"2192",
    "sg:province":"NSW",
    "sg:tags":[
        "away",
        "take"
    ],
    "wof:name":"Golden Pizza & Pasta Takeaway Food",
    "wof:placetype":"venue"
},
  "geometry": {"coordinates":[151.09414699999999,-33.922707],"type":"Point"}
}