{
  "type": "Feature",
  "properties": {
    "addr:full":"6 Reid Ave North Curl Curl NSW 2099",
    "addr:housenumber":"6",
    "addr:postcode":"2099",
    "addr:street":"Reid Ave North",
    "iso:country":"AU",
    "sg:address":"6 Reid Ave",
    "sg:city":"North Curl Curl",
    "sg:classifiers":[
        {
            "category":"Home & Garden",
            "subcategory":"Garden Supply",
            "type":"Retail Goods"
        }
    ],
    "sg:phone":"+61 414 606 024",
    "sg:postcode":"2099",
    "sg:province":"NSW",
    "sg:tags":[
        "turf",
        "lawn"
    ],
    "wof:name":"Above All Turf Supplies",
    "wof:placetype":"venue"
},
  "geometry": {"coordinates":[151.289962769,-33.7613525391],"type":"Point"}
}