{
  "type": "Feature",
  "properties": {
    "addr:full":"43 Mulloway Rd Chain Valley Bay NSW 2259",
    "addr:housenumber":"43",
    "addr:postcode":"2259",
    "addr:street":"Mulloway Rd",
    "iso:country":"AU",
    "sg:address":"43 Mulloway Rd",
    "sg:city":"Chain Valley Bay",
    "sg:classifiers":[
        {
            "category":"Retail",
            "subcategory":"Storage",
            "type":"Services"
        }
    ],
    "sg:phone":"+61 412 922 607",
    "sg:postcode":"2259",
    "sg:province":"NSW",
    "sg:tags":[
        "removal",
        "furniture"
    ],
    "wof:name":"Jeff. A. Furniture Transport",
    "wof:placetype":"venue"
},
  "geometry": {"coordinates":[151.569946289,-33.1725502014],"type":"Point"}
}