{
  "type": "Feature",
  "properties": {
    "iso:country":"AU",
    "sg:address":"32 Leichhardt St",
    "sg:city":"Toowoomba",
    "sg:classifiers":[
        {
            "category":"Building & Trades",
            "subcategory":"Construction",
            "type":"Services"
        }
    ],
    "sg:phone":"+61 7 4635 3328",
    "sg:postcode":"4350",
    "sg:province":"QLD",
    "sg:tags":[
        "joiner",
        "carpenter"
    ],
    "wof:name":"Fry RJ",
    "wof:placetype":"venue"
},
  "geometry": {"coordinates":[151.96380600000001,-27.585413],"type":"Point"}
}