{
  "type": "Feature",
  "properties": {
    "addr:full":"Timor Rd Bet Bet VIC 3472",
    "addr:postcode":"3472",
    "addr:street":"Timor Rd",
    "iso:country":"AU",
    "sg:address":"Timor Rd",
    "sg:city":"Bet Bet",
    "sg:classifiers":[
        {
            "category":"Arena",
            "subcategory":"Bull Ring",
            "type":"Entertainment"
        }
    ],
    "sg:phone":"+61 3 5468 7245",
    "sg:postcode":"3472",
    "sg:province":"VIC",
    "sg:tags":[
        "breeder",
        "pig"
    ],
    "wof:name":"Primeat Corporation",
    "wof:placetype":"venue"
},
  "geometry": {"coordinates":[143.756149292,-36.9242515564],"type":"Point"}
}