{
  "type": "Feature",
  "properties": {
    "iso:country":"AU",
    "sg:address":"109 Musgrave Ave",
    "sg:city":"(Cnr Kumbari Ave) Southport",
    "sg:classifiers":[
        {
            "category":"Health Services",
            "subcategory":"Chiropractor",
            "type":"Services"
        }
    ],
    "sg:phone":"+61 7 5528 2899",
    "sg:postcode":"4215",
    "sg:province":"QLD",
    "wof:name":"Ron Twergo Dr",
    "wof:placetype":"venue"
},
  "geometry": {"coordinates":[153.38978576700001,-27.9546737671],"type":"Point"}
}