{
  "type": "Feature",
  "properties": {
    "iso:country":"AU",
    "sg:address":"Ste303-304/ 30-40 Harcourt Pde",
    "sg:city":"Rosebery",
    "sg:classifiers":[
        {
            "category":"Building & Trades",
            "subcategory":"Construction",
            "type":"Services"
        }
    ],
    "sg:phone":"+61 2 9669 4108",
    "sg:postcode":"2018",
    "sg:province":"NSW",
    "sg:tags":[
        "contractor"
    ],
    "wof:name":"Siemsen Building Services",
    "wof:placetype":"venue"
},
  "geometry": {"coordinates":[151.20143127399999,-33.9199562073],"type":"Point"}
}