{
  "type": "Feature",
  "properties": {
    "addr:full":"PO Box 557 Penrith NSW 2751",
    "addr:postcode":"2751",
    "iso:country":"AU",
    "sg:address":"PO Box 557",
    "sg:city":"Penrith",
    "sg:classifiers":[
        {
            "category":"Professional",
            "subcategory":"Art Services",
            "type":"Services"
        }
    ],
    "sg:phone":"+61 2 4730 2402",
    "sg:postcode":"2751",
    "sg:province":"NSW",
    "sg:tags":[
        "interior",
        "decorator"
    ],
    "wof:name":"Complete InsideOut Designs",
    "wof:placetype":"venue"
},
  "geometry": {"coordinates":[150.69601440400001,-33.7440681458],"type":"Point"}
}