{
  "type": "Feature",
  "properties": {
    "iso:country":"AU",
    "sg:address":"534 Upper Orara Rd",
    "sg:city":"Upper Orara",
    "sg:classifiers":[
        {
            "category":"Building & Trades",
            "subcategory":"Plumbing",
            "type":"Services"
        }
    ],
    "sg:phone":"+61 2 6653 8810",
    "sg:postcode":"2450",
    "sg:province":"NSW",
    "sg:tags":[
        "plumber",
        "gasfitters"
    ],
    "wof:name":"Murphy J L",
    "wof:placetype":"venue"
},
  "geometry": {"coordinates":[153.007111,-30.276382],"type":"Point"}
}