{
  "type": "Feature",
  "properties": {
    "addr:full":"PO Box 695 Redcliffe QLD 4020",
    "addr:postcode":"4020",
    "iso:country":"AU",
    "sg:address":"PO Box 695",
    "sg:city":"Redcliffe",
    "sg:classifiers":[
        {
            "category":"Home & Garden",
            "subcategory":"Furniture",
            "type":"Retail Goods"
        }
    ],
    "sg:phone":"+61 413 871 531",
    "sg:postcode":"4020",
    "sg:province":"QLD",
    "sg:tags":[
        "repair",
        "restoration"
    ],
    "wof:name":"Furniture Fixer",
    "wof:placetype":"venue"
},
  "geometry": {"coordinates":[153.107224,-27.22217],"type":"Point"}
}