{
  "type": "Feature",
  "properties": {
    "iso:country":"AU",
    "sg:address":"Rooty Hill Rd",
    "sg:city":"Eastern Creek",
    "sg:classifiers":[
        {
            "category":"Government",
            "subcategory":"Fire Station",
            "type":"Public Place"
        }
    ],
    "sg:phone":"+61 2 9832 4433",
    "sg:postcode":"2766",
    "sg:province":"NSW",
    "sg:tags":[
        "brigade"
    ],
    "wof:name":"Rooty Hill Bush Fire Brigade",
    "wof:placetype":"venue"
},
  "geometry": {"coordinates":[150.843383789,-33.7708053589],"type":"Point"}
}