{
  "type": "Feature",
  "properties": {
    "addr:full":"124 High St Maryborough VIC 3465",
    "addr:housenumber":"124",
    "addr:postcode":"3465",
    "addr:street":"High St",
    "iso:country":"AU",
    "sg:address":"124 High St",
    "sg:city":"Maryborough",
    "sg:classifiers":[
        {
            "category":"Shopping",
            "subcategory":"Crafts & Fabrics",
            "type":"Retail Goods"
        }
    ],
    "sg:phone":"+61 3 5461 4934",
    "sg:postcode":"3465",
    "sg:province":"VIC",
    "sg:tags":[
        "wool",
        "knitting",
        "accessory"
    ],
    "wof:name":"Coverdale's Cane & Craft",
    "wof:placetype":"venue"
},
  "geometry": {"coordinates":[143.73713684099999,-37.0474128723],"type":"Point"}
}