{
  "type": "Feature",
  "properties": {
    "iso:country":"AU",
    "sg:address":"7 Capital Drv",
    "sg:city":"Dandenong",
    "sg:classifiers":[
        {
            "category":"Wholesale",
            "subcategory":"Photographic Equipment",
            "type":"Manufacturing & Wholesale Goods"
        }
    ],
    "sg:phone":"+61 3 9791 9848",
    "sg:postcode":"3175",
    "sg:province":"VIC",
    "sg:tags":[
        "machinery",
        "plastic"
    ],
    "wof:name":"Plastimac",
    "wof:placetype":"venue"
},
  "geometry": {"coordinates":[145.223220825,-38.0165634155],"type":"Point"}
}