{
  "type": "Feature",
  "properties": {
    "addr:full":"755- 757 Marion Rd Ascot Park SA 5043",
    "addr:housenumber":"755 757",
    "addr:postcode":"5043",
    "addr:street":"Marion Rd",
    "iso:country":"AU",
    "sg:address":"755- 757 Marion Rd",
    "sg:city":"Ascot Park",
    "sg:classifiers":[
        {
            "category":"Personal",
            "subcategory":"Beauty Salon",
            "type":"Services"
        }
    ],
    "sg:phone":"+61 8 8276 1727",
    "sg:postcode":"5043",
    "sg:province":"SA",
    "sg:tags":[
        "hairdresser"
    ],
    "wof:name":"Emfasis Hair",
    "wof:placetype":"venue"
},
  "geometry": {"coordinates":[138.55703700000001,-34.991692],"type":"Point"}
}