{
  "type": "Feature",
  "properties": {
    "addr:full":"Shop 8 Town Centre Arcade Katoomba NSW 2780",
    "addr:housenumber":"shop 8",
    "addr:postcode":"2780",
    "addr:street":"Town",
    "iso:country":"AU",
    "sg:address":"Shop 8",
    "sg:city":"Town Centre Arcade Katoomba",
    "sg:classifiers":[
        {
            "category":"Manufacturing",
            "subcategory":"Food",
            "type":"Manufacturing & Wholesale Goods"
        }
    ],
    "sg:phone":"+61 2 4782 2439",
    "sg:postcode":"2780",
    "sg:province":"NSW",
    "sg:tags":[
        "function",
        "catering"
    ],
    "wof:name":"Olifants Cafe & Catering",
    "wof:placetype":"venue"
},
  "geometry": {"coordinates":[150.31053161599999,-33.7118186951],"type":"Point"}
}