{
  "type": "Feature",
  "properties": {
    "iso:country":"AU",
    "sg:address":"9 Fir St",
    "sg:city":"Dingley",
    "sg:classifiers":[
        {
            "category":"Wholesale",
            "subcategory":"Music Publishers",
            "type":"Manufacturing & Wholesale Goods"
        }
    ],
    "sg:phone":"+61 3 9558 1137",
    "sg:postcode":"3172",
    "sg:province":"VIC",
    "sg:tags":[
        "wholesaler",
        "dvd",
        "mfrs",
        "cd"
    ],
    "wof:name":"CD Laboratories Pty Ltd",
    "wof:placetype":"venue"
},
  "geometry": {"coordinates":[145.11448669399999,-37.978515625],"type":"Point"}
}