{
  "type": "Feature",
  "properties": {
    "addr:full":"98 Union Rd Surrey Hills VIC 3127",
    "addr:housenumber":"98",
    "addr:postcode":"3127",
    "addr:street":"Union Rd",
    "iso:country":"AU",
    "sg:address":"98 Union Rd",
    "sg:city":"Surrey Hills",
    "sg:classifiers":[
        {
            "category":"Organizations",
            "subcategory":"Community Association",
            "type":"Services"
        }
    ],
    "sg:phone":"+61 3 9830 5603",
    "sg:postcode":"3127",
    "sg:province":"VIC",
    "sg:tags":[
        "organisation",
        "family",
        "welfare"
    ],
    "wof:name":"St Vincent De Paul Centres",
    "wof:placetype":"venue"
},
  "geometry": {"coordinates":[145.097122192,-37.8256645203],"type":"Point"}
}