{
  "type": "Feature",
  "properties": {
    "addr:full":"3 Mokana St Kerang VIC 3579",
    "addr:housenumber":"3",
    "addr:postcode":"3579",
    "addr:street":"Mokana St",
    "iso:country":"AU",
    "sg:address":"3 Mokana St",
    "sg:city":"Kerang",
    "sg:classifiers":[
        {
            "category":"Building & Trades",
            "subcategory":"Construction",
            "type":"Services"
        }
    ],
    "sg:phone":"+61 3 5452 2525",
    "sg:postcode":"3579",
    "sg:province":"VIC",
    "sg:tags":[
        "contractor"
    ],
    "wof:name":"Stubbs David",
    "wof:placetype":"venue"
},
  "geometry": {"coordinates":[143.926223755,-35.7383651733],"type":"Point"}
}