{
  "type": "Feature",
  "properties": {
    "addr:full":"20 Wilson St South Yarra VIC 3141",
    "addr:housenumber":"20",
    "addr:postcode":"3141",
    "addr:street":"Wilson St",
    "iso:country":"AU",
    "sg:address":"20 Wilson St",
    "sg:city":"South Yarra",
    "sg:classifiers":[
        {
            "category":"Wholesale",
            "subcategory":"Non-durable Goods",
            "type":"Manufacturing & Wholesale Goods"
        }
    ],
    "sg:phone":"+61 3 9826 5777",
    "sg:postcode":"3141",
    "sg:province":"VIC",
    "sg:tags":[
        "wholesaler",
        "mfrs",
        "cosmetic"
    ],
    "wof:name":"Thalgo Australia",
    "wof:placetype":"venue"
},
  "geometry": {"coordinates":[144.99603271500001,-37.8439445496],"type":"Point"}
}