{
  "type": "Feature",
  "properties": {
    "iso:country":"AU",
    "sg:address":"36 Endeavour Ave",
    "sg:city":"Bull Creek",
    "sg:classifiers":[
        {
            "category":"Home & Garden",
            "subcategory":"Building Materials",
            "type":"Retail Goods"
        }
    ],
    "sg:phone":"+61 1800 251 960",
    "sg:postcode":"6149",
    "sg:province":"WA",
    "sg:tags":[
        "skylight"
    ],
    "wof:name":"Velux",
    "wof:placetype":"venue"
},
  "geometry": {"coordinates":[115.85234800000001,-32.058998],"type":"Point"}
}