{
  "type": "Feature",
  "properties": {
    "addr:full":"PO Box 72 Cardiff NSW 2285",
    "addr:postcode":"2285",
    "iso:country":"AU",
    "sg:address":"PO Box 72",
    "sg:city":"Cardiff",
    "sg:classifiers":[
        {
            "category":"Marine",
            "type":"Transportation"
        }
    ],
    "sg:phone":"+61 2 4954 2142",
    "sg:postcode":"2285",
    "sg:province":"NSW",
    "sg:tags":[
        "flagpole",
        "mast"
    ],
    "wof:name":"Better Bunting",
    "wof:placetype":"venue"
},
  "geometry": {"coordinates":[151.650024414,-32.9429397583],"type":"Point"}
}