{
  "type": "Feature",
  "properties": {
    "iso:country":"AU",
    "sg:address":"10 Bungarribee Rd",
    "sg:city":"Blacktown",
    "sg:classifiers":[
        {
            "category":"Fast Food",
            "type":"Food & Drink"
        }
    ],
    "sg:phone":"+61 2 9831 2300",
    "sg:postcode":"2148",
    "sg:province":"NSW",
    "sg:tags":[
        "away",
        "take"
    ],
    "wof:name":"La Porchetta",
    "wof:placetype":"venue"
},
  "geometry": {"coordinates":[150.897583008,-33.7762451172],"type":"Point"}
}