{
  "type": "Feature",
  "properties": {
    "addr:full":"64 Glasshouse Rocks Rd Narooma NSW 2546",
    "addr:housenumber":"64",
    "addr:postcode":"2546",
    "addr:street":"Glasshouse Rocks Rd",
    "iso:country":"AU",
    "sg:address":"64 Glasshouse Rocks Rd",
    "sg:city":"Narooma",
    "sg:classifiers":[
        {
            "category":"Professional",
            "subcategory":"Detective & Security Services",
            "type":"Services"
        }
    ],
    "sg:phone":"+61 2 4476 4031",
    "sg:postcode":"2546",
    "sg:province":"NSW",
    "sg:tags":[
        "equipment",
        "window",
        "doors"
    ],
    "wof:name":"Narooma Glass & House Supplies",
    "wof:placetype":"venue"
},
  "geometry": {"coordinates":[150.13160705600001,-36.2318153381],"type":"Point"}
}