{
  "type": "Feature",
  "properties": {
    "addr:full":"26 Holland St Northgate QLD 4013",
    "addr:housenumber":"26",
    "addr:postcode":"4013",
    "addr:street":"Holland St",
    "iso:country":"AU",
    "sg:address":"26 Holland St",
    "sg:city":"Northgate",
    "sg:classifiers":[
        {
            "category":"Wholesale",
            "subcategory":"Metals & Minerals",
            "type":"Manufacturing & Wholesale Goods"
        }
    ],
    "sg:phone":"+61 7 3256 6226",
    "sg:postcode":"4013",
    "sg:province":"QLD",
    "sg:tags":[
        "steel",
        "stainless",
        "product",
        "equipment"
    ],
    "wof:name":"Oakwood Sheet Metal Work",
    "wof:placetype":"venue"
},
  "geometry": {"coordinates":[153.07115173299999,-27.3925361633],"type":"Point"}
}