{
  "type": "Feature",
  "properties": {
    "addr:full":"216 Victoria Rd Largs Bay SA 5016",
    "addr:housenumber":"216",
    "addr:postcode":"5016",
    "addr:street":"Victoria Rd",
    "iso:country":"AU",
    "sg:address":"216 Victoria Rd",
    "sg:city":"Largs Bay",
    "sg:classifiers":[
        {
            "category":"Building & Trades",
            "subcategory":"Construction",
            "type":"Services"
        }
    ],
    "sg:phone":"+61 1800 659 850",
    "sg:postcode":"5016",
    "sg:province":"SA",
    "sg:tags":[
        "pipe",
        "concrete"
    ],
    "wof:name":"James Hardie FRC Pipes",
    "wof:placetype":"venue"
},
  "geometry": {"coordinates":[138.50025939899999,-34.8249168396],"type":"Point"}
}