{
  "type": "Feature",
  "properties": {
    "addr:full":"1264- 1266 High St Armadale VIC 3143",
    "addr:housenumber":"1264 1266",
    "addr:postcode":"3143",
    "addr:street":"High St",
    "iso:country":"AU",
    "sg:address":"1264- 1266 High St",
    "sg:city":"Armadale",
    "sg:classifiers":[
        {
            "category":"Government",
            "subcategory":"Customs House",
            "type":"Public Place"
        }
    ],
    "sg:phone":"+61 3 9509 7887",
    "sg:postcode":"3143",
    "sg:province":"VIC",
    "sg:tags":[
        "title",
        "management",
        "stratum"
    ],
    "wof:name":"Gough Partners Body Corporate Services",
    "wof:placetype":"venue"
},
  "geometry": {"coordinates":[145.02874755900001,-37.8566474915],"type":"Point"}
}