{
  "type": "Feature",
  "properties": {
    "addr:full":"7/ 63 Annerley Rd South Brisbane QLD 4101",
    "addr:housenumber":"/ 63",
    "addr:postcode":"4101",
    "addr:street":"Annerley Rd",
    "iso:country":"AU",
    "sg:address":"7/ 63 Annerley Rd",
    "sg:city":"South Brisbane",
    "sg:classifiers":[
        {
            "category":"Real Estate",
            "subcategory":"Architect",
            "type":"Services"
        }
    ],
    "sg:phone":"+61 7 3844 6755",
    "sg:postcode":"4101",
    "sg:province":"QLD",
    "wof:name":"Philip Gough & Associates Pty Ltd",
    "wof:placetype":"venue"
},
  "geometry": {"coordinates":[153.02767944300001,-27.4890213013],"type":"Point"}
}