{
  "type": "Feature",
  "properties": {
    "addr:full":"First Floor- 2 McCauley St Thirroul NSW 2515",
    "addr:postcode":"2515",
    "addr:street":"Floor;Mccauley St",
    "iso:country":"AU",
    "sg:address":"First Floor- 2 McCauley St",
    "sg:city":"Thirroul",
    "sg:classifiers":[
        {
            "category":"Education",
            "subcategory":"Dance Studio",
            "type":"Public Place"
        }
    ],
    "sg:phone":"+61 2 4268 3247",
    "sg:postcode":"2515",
    "sg:province":"NSW",
    "sg:tags":[
        "venue",
        "tuition"
    ],
    "wof:name":"Thirroul Dance Academy",
    "wof:placetype":"venue"
},
  "geometry": {"coordinates":[150.92280600000001,-34.315674],"type":"Point"}
}