{
  "type": "Feature",
  "properties": {
    "addr:full":"61 Elizabeth St Moss Vale NSW 2577",
    "addr:housenumber":"61",
    "addr:postcode":"2577",
    "addr:street":"Elizabeth St",
    "iso:country":"AU",
    "sg:address":"61 Elizabeth St",
    "sg:city":"Moss Vale",
    "sg:classifiers":[
        {
            "category":"Health Services",
            "subcategory":"Doctor",
            "type":"Services"
        }
    ],
    "sg:phone":"+61 2 4868 1500",
    "sg:postcode":"2577",
    "sg:province":"NSW",
    "sg:tags":[
        "medical",
        "practitioner"
    ],
    "wof:name":"Moss Vale Medical Centre",
    "wof:placetype":"venue"
},
  "geometry": {"coordinates":[150.37518310600001,-34.5479736328],"type":"Point"}
}