{
  "type": "Feature",
  "properties": {
    "iso:country":"AU",
    "sg:address":"35 Penguin Head Rd",
    "sg:city":"Culburra Beach",
    "sg:classifiers":[
        {
            "category":"Building & Trades",
            "subcategory":"Pest Control",
            "type":"Services"
        }
    ],
    "sg:phone":"+61 2 4447 2025",
    "sg:postcode":"2540",
    "sg:province":"NSW",
    "wof:name":"C & F Pest Control",
    "wof:placetype":"venue"
},
  "geometry": {"coordinates":[150.76475524899999,-34.928478241],"type":"Point"}
}