{
  "type": "Feature",
  "properties": {
    "addr:full":"3/ 19 Brooks Ave Wyoming NSW 2250",
    "addr:housenumber":"/ 19",
    "addr:postcode":"2250",
    "addr:street":"Brooks Ave",
    "iso:country":"AU",
    "sg:address":"3/ 19 Brooks Ave",
    "sg:city":"Wyoming",
    "sg:classifiers":[
        {
            "category":"Professional",
            "subcategory":"Detective & Security Services",
            "type":"Services"
        }
    ],
    "sg:phone":"+61 2 4328 2822",
    "sg:postcode":"2250",
    "sg:province":"NSW",
    "sg:tags":[
        "protective",
        "rustproofing"
    ],
    "wof:name":"Infinity Auto Protection Pty Ltd",
    "wof:placetype":"venue"
},
  "geometry": {"coordinates":[151.34806823700001,-33.4016456604],"type":"Point"}
}