{
  "type": "Feature",
  "properties": {
    "iso:country":"AU",
    "sg:address":"112 Campbell St",
    "sg:city":"Oakey",
    "sg:classifiers":[
        {
            "category":"Retail",
            "subcategory":"Storage",
            "type":"Services"
        }
    ],
    "sg:phone":"+61 7 4691 1797",
    "sg:postcode":"4401",
    "sg:province":"QLD",
    "wof:name":"Oakey Mini Storage",
    "wof:placetype":"venue"
},
  "geometry": {"coordinates":[151.72067260700001,-27.4316654205],"type":"Point"}
}