{
  "type": "Feature",
  "properties": {
    "iso:country":"AU",
    "sg:address":"57 Murphy Rd",
    "sg:city":"Nar Nar Goon North",
    "sg:classifiers":[
        {
            "category":"Building & Trades",
            "subcategory":"Landscaping Services",
            "type":"Services"
        }
    ],
    "sg:phone":"+61 419 338 680",
    "sg:postcode":"3812",
    "sg:province":"VIC",
    "sg:tags":[
        "stump",
        "tree",
        "felling",
        "removal"
    ],
    "wof:name":"Aaron Mitchell",
    "wof:placetype":"venue"
},
  "geometry": {"coordinates":[145.571426,-38.069092],"type":"Point"}
}