{
  "type": "Feature",
  "properties": {
    "iso:country":"AU",
    "sg:address":"Shop 1, 105 Murray St",
    "sg:city":"Gawler",
    "sg:classifiers":[
        {
            "category":"Airline",
            "type":"Transportation"
        }
    ],
    "sg:phone":"+61 8 8523 0055",
    "sg:postcode":"5118",
    "sg:province":"SA",
    "sg:tags":[
        "agent"
    ],
    "wof:name":"Harvey World Travel",
    "wof:placetype":"venue"
},
  "geometry": {"coordinates":[138.749237,-34.596661],"type":"Point"}
}