{
  "type": "Feature",
  "properties": {
    "iso:country":"AU",
    "sg:address":"410 City Rd",
    "sg:city":"South Melbourne",
    "sg:classifiers":[
        {
            "category":"Retail",
            "subcategory":"Car Wash",
            "type":"Services"
        }
    ],
    "sg:phone":"+61 3 9696 9467",
    "sg:postcode":"3205",
    "sg:province":"VIC",
    "sg:tags":[
        "truck",
        "cleaning"
    ],
    "wof:name":"Caffin M Car Detailing",
    "wof:placetype":"venue"
},
  "geometry": {"coordinates":[144.955826,-37.829372],"type":"Point"}
}