{
  "type": "Feature",
  "properties": {
    "addr:full":"25 Osborne St Wollongong NSW 2500",
    "addr:housenumber":"25",
    "addr:postcode":"2500",
    "addr:street":"Osborne St",
    "iso:country":"AU",
    "sg:address":"25 Osborne St",
    "sg:city":"Wollongong",
    "sg:classifiers":[
        {
            "category":"Health Services",
            "subcategory":"Doctor",
            "type":"Services"
        }
    ],
    "sg:phone":"+61 2 4226 3088",
    "sg:postcode":"2500",
    "sg:province":"NSW",
    "sg:tags":[
        "medical",
        "practitioner"
    ],
    "wof:name":"Salmon Robert Dr",
    "wof:placetype":"venue"
},
  "geometry": {"coordinates":[150.884827,-34.427315],"type":"Point"}
}