{
  "type": "Feature",
  "properties": {
    "iso:country":"AU",
    "sg:address":"Cnr Hindley & King William Sts",
    "sg:city":"Adelaide",
    "sg:classifiers":[
        {
            "category":"Fast Food",
            "type":"Food & Drink"
        }
    ],
    "sg:phone":"+61 8 8231 0121",
    "sg:postcode":"5000",
    "sg:province":"SA",
    "sg:tags":[
        "away",
        "take"
    ],
    "wof:name":"Wokinabox",
    "wof:placetype":"venue"
},
  "geometry": {"coordinates":[138.59939575199999,-34.9230003357],"type":"Point"}
}