{
  "type": "Feature",
  "properties": {
    "addr:full":"Cnr Ballina Rd & Jubilee Ave Goonellabah NSW 2480",
    "addr:postcode":"2480",
    "addr:street":"Ballina Rd & Jubilee Ave",
    "iso:country":"AU",
    "sg:address":"Cnr Ballina Rd & Jubilee Ave",
    "sg:city":"Goonellabah",
    "sg:classifiers":[
        {
            "category":"Education",
            "subcategory":"School",
            "type":"Public Place"
        }
    ],
    "sg:phone":"+61 2 6624 1444",
    "sg:postcode":"2480",
    "sg:province":"NSW",
    "sg:tags":[
        "state",
        "-",
        "nsw"
    ],
    "wof:name":"Goonellabah Public School",
    "wof:placetype":"venue"
},
  "geometry": {"coordinates":[153.33558654800001,-28.8171920776],"type":"Point"}
}