{
  "type": "Feature",
  "properties": {
    "addr:full":"8 Nelson St Coorparoo QLD 4151",
    "addr:housenumber":"8",
    "addr:postcode":"4151",
    "addr:street":"Nelson St",
    "iso:country":"AU",
    "sg:address":"8 Nelson St",
    "sg:city":"Coorparoo",
    "sg:classifiers":[
        {
            "category":"Shopping",
            "subcategory":"Bicycles & Sporting Goods",
            "type":"Retail Goods"
        }
    ],
    "sg:phone":"+61 411 425 951",
    "sg:postcode":"4151",
    "sg:province":"QLD",
    "sg:tags":[
        "chemical",
        "equipment",
        "pool",
        "swimming"
    ],
    "wof:name":"Houghton Pool Services",
    "wof:placetype":"venue"
},
  "geometry": {"coordinates":[153.05450439399999,-27.5014705658],"type":"Point"}
}