{
  "type": "Feature",
  "properties": {
    "addr:full":"12 Caribbean Crt Deception Bay QLD 4508",
    "addr:housenumber":"12",
    "addr:postcode":"4508",
    "addr:street":"Caribbean Crt",
    "iso:country":"AU",
    "sg:address":"12 Caribbean Crt",
    "sg:city":"Deception Bay",
    "sg:classifiers":[
        {
            "category":"Utilities",
            "subcategory":"Telephone",
            "type":"Services"
        }
    ],
    "sg:phone":"+61 7 3203 0999",
    "sg:postcode":"4508",
    "sg:province":"QLD",
    "sg:tags":[
        "installation",
        "system",
        "maintenance"
    ],
    "wof:name":"Cable & Data Communications",
    "wof:placetype":"venue"
},
  "geometry": {"coordinates":[153.021850586,-27.1687545776],"type":"Point"}
}