{
  "type": "Feature",
  "properties": {
    "addr:full":"Cnr Great Eastern Hwy & Bilgoman Rd Glen Forrest WA 6071",
    "addr:postcode":"6071",
    "addr:street":"Cnr Great Eastern Hwy & Bilgoman Rd",
    "iso:country":"AU",
    "sg:address":"Cnr Great Eastern Hwy & Bilgoman Rd",
    "sg:city":"Glen Forrest",
    "sg:classifiers":[
        {
            "category":"Retail",
            "subcategory":"Auto Repair",
            "type":"Services"
        }
    ],
    "sg:phone":"+61 8 9298 8107",
    "sg:postcode":"6071",
    "sg:province":"WA",
    "sg:tags":[
        "beater",
        "painter",
        "panel"
    ],
    "wof:name":"Sola Smash Repairs Pty Ltd",
    "wof:placetype":"venue"
},
  "geometry": {"coordinates":[116.105026245,-31.9030513763],"type":"Point"}
}