{
  "type": "Feature",
  "properties": {
    "addr:full":"Ste 20/ 126 Beardy St Armidale NSW 2350",
    "addr:housenumber":"/ 126",
    "addr:postcode":"2350",
    "addr:street":"Beardy St",
    "iso:country":"AU",
    "sg:address":"Ste 20/ 126 Beardy St",
    "sg:city":"Armidale",
    "sg:classifiers":[
        {
            "category":"Real Estate",
            "subcategory":"Real Estate Agent",
            "type":"Services"
        }
    ],
    "sg:phone":"+61 2 6772 9955",
    "sg:postcode":"2350",
    "sg:province":"NSW",
    "wof:name":"Philip Jarvis & Associates",
    "wof:placetype":"venue"
},
  "geometry": {"coordinates":[151.66026306099999,-30.511838913],"type":"Point"}
}