{
  "type": "Feature",
  "properties": {
    "iso:country":"AU",
    "sg:address":"PO Box 250",
    "sg:city":"Yarra Glen",
    "sg:classifiers":[
        {
            "category":"Building & Trades",
            "subcategory":"Construction",
            "type":"Services"
        }
    ],
    "sg:phone":"+61 3 5966 9817",
    "sg:postcode":"3775",
    "sg:province":"VIC",
    "sg:tags":[
        "waterproofing",
        "contractor"
    ],
    "wof:name":"Concrete Waterproofing Gippsland",
    "wof:placetype":"venue"
},
  "geometry": {"coordinates":[145.376266,-37.652431],"type":"Point"}
}