{
  "type": "Feature",
  "properties": {
    "addr:full":"3/ 54 Valley Rd Hope Valley SA 5090",
    "addr:housenumber":"/ 54",
    "addr:postcode":"5090",
    "addr:street":"Valley Rd",
    "iso:country":"AU",
    "sg:address":"3/ 54 Valley Rd",
    "sg:city":"Hope Valley",
    "sg:classifiers":[
        {
            "category":"Building & Trades",
            "subcategory":"Landscaping Services",
            "type":"Services"
        }
    ],
    "sg:phone":"+61 413 912 725",
    "sg:postcode":"5090",
    "sg:province":"SA",
    "sg:tags":[
        "designer",
        "landscape",
        "contractor"
    ],
    "wof:name":"Gardens For You",
    "wof:placetype":"venue"
},
  "geometry": {"coordinates":[138.701828003,-34.8474273682],"type":"Point"}
}