{
  "type": "Feature",
  "properties": {
    "addr:full":"20 Coulter St Newcomb VIC 3219",
    "addr:housenumber":"20",
    "addr:postcode":"3219",
    "addr:street":"Coulter St",
    "iso:country":"AU",
    "sg:address":"20 Coulter St",
    "sg:city":"Newcomb",
    "sg:classifiers":[
        {
            "category":"Professional",
            "subcategory":"Accounting & Tax Preparation",
            "type":"Services"
        }
    ],
    "sg:phone":"+61 3 5248 1588",
    "sg:postcode":"3219",
    "sg:province":"VIC",
    "sg:tags":[
        "bookkeeping"
    ],
    "wof:name":"Add Books Bookkeeping",
    "wof:placetype":"venue"
},
  "geometry": {"coordinates":[144.40127563499999,-38.1684646606],"type":"Point"}
}