{
  "type": "Feature",
  "properties": {
    "addr:full":"75 Beach Rd Christies Beach SA 5165",
    "addr:housenumber":"75",
    "addr:postcode":"5165",
    "addr:street":"Beach Rd",
    "iso:country":"AU",
    "sg:address":"75 Beach Rd",
    "sg:city":"Christies Beach",
    "sg:classifiers":[
        {
            "category":"Insurance",
            "subcategory":"Insurance Agent",
            "type":"Services"
        }
    ],
    "sg:phone":"+61 8 8382 2222",
    "sg:postcode":"5165",
    "sg:province":"SA",
    "wof:name":"South Coast Insurance Brokers",
    "wof:placetype":"venue"
},
  "geometry": {"coordinates":[138.47882080100001,-35.1389083862],"type":"Point"}
}