{
  "type": "Feature",
  "properties": {
    "addr:full":"36 Marlborough St Rutherford NSW 2320",
    "addr:housenumber":"36",
    "addr:postcode":"2320",
    "addr:street":"Marlborough St",
    "iso:country":"AU",
    "sg:address":"36 Marlborough St",
    "sg:city":"Rutherford",
    "sg:classifiers":[
        {
            "category":"Professional",
            "subcategory":"Detective & Security Services",
            "type":"Services"
        }
    ],
    "sg:phone":"+61 2 4932 0461",
    "sg:postcode":"2320",
    "sg:province":"NSW",
    "sg:tags":[
        "equipment",
        "window",
        "doors"
    ],
    "wof:name":"Hunter Valley Security Doors - Maitland",
    "wof:placetype":"venue"
},
  "geometry": {"coordinates":[151.51614379899999,-32.7189216614],"type":"Point"}
}