{
  "type": "Feature",
  "properties": {
    "iso:country":"AU",
    "sg:address":"Hunter Rd",
    "sg:city":"Narembeen East",
    "sg:classifiers":[
        {
            "category":"Farming",
            "subcategory":"Farm",
            "type":"Manufacturing & Wholesale Goods"
        }
    ],
    "sg:phone":"+61 8 9061 8017",
    "sg:postcode":"6369",
    "sg:province":"WA",
    "sg:tags":[
        "farmer"
    ],
    "wof:name":"Smoker D I",
    "wof:placetype":"venue"
},
  "geometry": {"coordinates":[118.39566,-32.090343],"type":"Point"}
}