{
  "type": "Feature",
  "properties": {
    "addr:full":"Sydney St Tarcutta NSW 2652",
    "addr:postcode":"2652",
    "addr:street":"Sydney St",
    "iso:country":"AU",
    "sg:address":"Sydney St",
    "sg:city":"Tarcutta",
    "sg:classifiers":[
        {
            "category":"Travel",
            "subcategory":"Hotels & Motels",
            "type":"Entertainment"
        }
    ],
    "sg:phone":"+61 2 6928 7203",
    "sg:postcode":"2652",
    "sg:province":"NSW",
    "sg:tags":[
        "accommodation"
    ],
    "wof:name":"Tarcutta Hotel",
    "wof:placetype":"venue"
},
  "geometry": {"coordinates":[147.73951721200001,-35.2755508423],"type":"Point"}
}