{
  "type": "Feature",
  "properties": {
    "addr:full":"Shp 102 Lakehaven Shopng Cntr Gorokan NSW 2263",
    "addr:housenumber":"102",
    "addr:postcode":"2263",
    "addr:street":"Lakehaven Shopng Cntr",
    "iso:country":"AU",
    "sg:address":"Shp 102",
    "sg:city":"Lakehaven Shopng Cntr Gorokan",
    "sg:classifiers":[
        {
            "category":"Banks & Credit Unions",
            "subcategory":"Bank",
            "type":"Services"
        }
    ],
    "sg:phone":"+61 13 20 32",
    "sg:postcode":"2263",
    "sg:province":"NSW",
    "wof:name":"Westpac",
    "wof:placetype":"venue"
},
  "geometry": {"coordinates":[151.50355500000001,-33.254799],"type":"Point"}
}