{
  "type": "Feature",
  "properties": {
    "addr:full":"80 Berry St Spring Hill QLD 4000",
    "addr:housenumber":"80",
    "addr:postcode":"4000",
    "addr:street":"Berry St",
    "iso:country":"AU",
    "sg:address":"80 Berry St",
    "sg:city":"Spring Hill",
    "sg:classifiers":[
        {
            "category":"Organizations",
            "subcategory":"Professional Association",
            "type":"Services"
        }
    ],
    "sg:phone":"+61 7 3831 9111",
    "sg:postcode":"4000",
    "sg:province":"QLD",
    "sg:tags":[
        "web",
        "internet"
    ],
    "wof:name":"Webhost.com.au",
    "wof:placetype":"venue"
},
  "geometry": {"coordinates":[153.023727417,-27.463514328],"type":"Point"}
}