{
  "type": "Feature",
  "properties": {
    "addr:full":"270 Meade St Glen Innes NSW 2370",
    "addr:housenumber":"270",
    "addr:postcode":"2370",
    "addr:street":"Meade St",
    "iso:country":"AU",
    "sg:address":"270 Meade St",
    "sg:city":"Glen Innes",
    "sg:classifiers":[
        {
            "category":"Professional",
            "subcategory":"Engineering",
            "type":"Services"
        }
    ],
    "sg:phone":"+61 2 6732 2738",
    "sg:postcode":"2370",
    "sg:province":"NSW",
    "sg:tags":[
        "consulting",
        "engineer"
    ],
    "wof:name":"Kieran Byrne & Associates Pty Ltd",
    "wof:placetype":"venue"
},
  "geometry": {"coordinates":[151.73338317899999,-29.7366504669],"type":"Point"}
}