{
  "type": "Feature",
  "properties": {
    "addr:full":"25 Post Office Pl Traralgon VIC 3844",
    "addr:housenumber":"25",
    "addr:postcode":"3844",
    "addr:street":"Post Office Pl",
    "iso:country":"AU",
    "sg:address":"25 Post Office Pl",
    "sg:city":"Traralgon",
    "sg:classifiers":[
        {
            "category":"Professional",
            "subcategory":"Art Services",
            "type":"Services"
        }
    ],
    "sg:phone":"+61 3 5174 7311",
    "sg:postcode":"3844",
    "sg:province":"VIC",
    "sg:tags":[
        "picture",
        "frame",
        "framing"
    ],
    "wof:name":"Timeless Framing",
    "wof:placetype":"venue"
},
  "geometry": {"coordinates":[146.539520264,-38.1952781677],"type":"Point"}
}