{
  "type": "Feature",
  "properties": {
    "iso:country":"AU",
    "sg:address":"Campbell St (cnr Bowen Bridge Rd)",
    "sg:city":"Bowen Hills",
    "sg:classifiers":[
        {
            "category":"Insurance",
            "subcategory":"Hazard Insurance",
            "type":"Services"
        }
    ],
    "sg:phone":"+61 7 3854 1821",
    "sg:postcode":"4006",
    "sg:province":"QLD",
    "sg:tags":[
        "motor",
        "vehicle"
    ],
    "wof:name":"Accident Insurance Mutual Holdings Ltd",
    "wof:placetype":"venue"
},
  "geometry": {"coordinates":[153.03706359899999,-27.4476299286],"type":"Point"}
}