{
  "type": "Feature",
  "properties": {
    "addr:full":"Sheridan St Gundagai NSW 2722",
    "addr:postcode":"2722",
    "addr:street":"Sheridan St",
    "iso:country":"AU",
    "sg:address":"Sheridan St",
    "sg:city":"Gundagai",
    "sg:classifiers":[
        {
            "category":"Education",
            "subcategory":"School",
            "type":"Public Place"
        }
    ],
    "sg:phone":"+61 2 6944 1085",
    "sg:postcode":"2722",
    "sg:province":"NSW",
    "sg:tags":[
        "co-educational"
    ],
    "wof:name":"St Patricks Primary School",
    "wof:placetype":"venue"
},
  "geometry": {"coordinates":[148.101822,-35.063145],"type":"Point"}
}