{
  "type": "Feature",
  "properties": {
    "addr:full":"52 Bridge St Benalla VIC 3672",
    "addr:housenumber":"52",
    "addr:postcode":"3672",
    "addr:street":"Bridge St",
    "iso:country":"AU",
    "sg:address":"52 Bridge St",
    "sg:city":"Benalla",
    "sg:classifiers":[
        {
            "category":"Real Estate",
            "subcategory":"Real Estate Agent",
            "type":"Services"
        }
    ],
    "sg:phone":"+61 3 5762 1000",
    "sg:postcode":"3672",
    "sg:province":"VIC",
    "wof:name":"L J Hooker",
    "wof:placetype":"venue"
},
  "geometry": {"coordinates":[145.984467,-36.551655],"type":"Point"}
}