{
  "type": "Feature",
  "properties": {
    "addr:full":"118 Station St Fairfield VIC 3078",
    "addr:housenumber":"118",
    "addr:postcode":"3078",
    "addr:street":"Station St",
    "iso:country":"AU",
    "sg:address":"118 Station St",
    "sg:city":"Fairfield",
    "sg:classifiers":[
        {
            "category":"Shopping",
            "subcategory":"Clothing, Apparel, & Fashions",
            "type":"Retail Goods"
        }
    ],
    "sg:phone":"+61 3 9489 5940",
    "sg:postcode":"3078",
    "sg:province":"VIC",
    "sg:tags":[
        "lady",
        "wear"
    ],
    "wof:name":"Moda In Fashion",
    "wof:placetype":"venue"
},
  "geometry": {"coordinates":[145.01852417000001,-37.7776794434],"type":"Point"}
}