{
  "type": "Feature",
  "properties": {
    "iso:country":"AU",
    "sg:address":"187 Jefferson La",
    "sg:city":"Palm Beach",
    "sg:classifiers":[
        {
            "category":"Professional",
            "type":"Services"
        }
    ],
    "sg:phone":"+61 419 955 055",
    "sg:postcode":"4221",
    "sg:province":"QLD",
    "sg:tags":[
        "shop",
        "fitting"
    ],
    "wof:name":"Creating Hospitality",
    "wof:placetype":"venue"
},
  "geometry": {"coordinates":[153.46969604500001,-28.1151638031],"type":"Point"}
}