{
  "type": "Feature",
  "properties": {
    "addr:full":"7 Badenoch Ave Glenhaven NSW 2156",
    "addr:housenumber":"7",
    "addr:postcode":"2156",
    "addr:street":"Badenoch Ave",
    "iso:country":"AU",
    "sg:address":"7 Badenoch Ave",
    "sg:city":"Glenhaven",
    "sg:classifiers":[
        {
            "category":"Professional",
            "subcategory":"Accounting & Tax Preparation",
            "type":"Services"
        }
    ],
    "sg:phone":"+61 2 9899 6600",
    "sg:postcode":"2156",
    "sg:province":"NSW",
    "sg:tags":[
        "accountant",
        "auditor"
    ],
    "wof:name":"Acclaim Management Accounting & Taxation Services",
    "wof:placetype":"venue"
},
  "geometry": {"coordinates":[151.004302978,-33.7136688232],"type":"Point"}
}