{
  "type": "Feature",
  "properties": {
    "addr:full":"258 Milperra Rd Milperra NSW 2214",
    "addr:housenumber":"258",
    "addr:postcode":"2214",
    "addr:street":"Milperra Rd",
    "iso:country":"AU",
    "sg:address":"258 Milperra Rd",
    "sg:city":"Milperra",
    "sg:classifiers":[
        {
            "category":"Wholesale",
            "subcategory":"Construction Materials",
            "type":"Manufacturing & Wholesale Goods"
        }
    ],
    "sg:phone":"+61 2 9774 3755",
    "sg:postcode":"2214",
    "sg:province":"NSW",
    "sg:tags":[
        "wholesaler",
        "equipment",
        "bathroom",
        "mfrs",
        "accessory"
    ],
    "wof:name":"Australian Dispenser",
    "wof:placetype":"venue"
},
  "geometry": {"coordinates":[150.99453700000001,-33.93895],"type":"Point"}
}