{
  "type": "Feature",
  "properties": {
    "addr:full":"701 Glenhuntly Rd Caulfield VIC 3162",
    "addr:housenumber":"701",
    "addr:postcode":"3162",
    "addr:street":"Glenhuntly Rd",
    "iso:country":"AU",
    "sg:address":"701 Glenhuntly Rd",
    "sg:city":"Caulfield",
    "sg:classifiers":[
        {
            "category":"Sports & Exercise",
            "subcategory":"Gym",
            "type":"Entertainment"
        }
    ],
    "sg:phone":"+61 3 9532 7800",
    "sg:postcode":"3162",
    "sg:province":"VIC",
    "sg:tags":[
        "personal",
        "trainer",
        "fitness"
    ],
    "wof:name":"Australian Fitness Academy",
    "wof:placetype":"venue"
},
  "geometry": {"coordinates":[145.018768311,-37.8863487244],"type":"Point"}
}