{
  "type": "Feature",
  "properties": {
    "addr:full":"4/11- 15 McMillan Ave Dolls Point NSW 2219",
    "addr:housenumber":"/;15",
    "addr:postcode":"2219",
    "addr:street":"11;Mcmillan Ave",
    "iso:country":"AU",
    "sg:address":"4/11- 15 McMillan Ave",
    "sg:city":"Dolls Point",
    "sg:classifiers":[
        {
            "category":"Professional",
            "subcategory":"Detective & Security Services",
            "type":"Services"
        }
    ],
    "sg:phone":"+61 2 9214 0158",
    "sg:postcode":"2219",
    "sg:province":"NSW",
    "sg:tags":[
        "guard",
        "patrol"
    ],
    "wof:name":"Botany Mascot Security Services",
    "wof:placetype":"venue"
},
  "geometry": {"coordinates":[151.14103700000001,-33.994877],"type":"Point"}
}