{
  "type": "Feature",
  "properties": {
    "addr:full":"158 Mount Darragh Rd Pambula South NSW 2549",
    "addr:housenumber":"158",
    "addr:postcode":"2549",
    "addr:street":"Mount Darragh Rd",
    "iso:country":"AU",
    "sg:address":"158 Mount Darragh Rd",
    "sg:city":"Pambula South",
    "sg:classifiers":[
        {
            "category":"Fast Food",
            "type":"Food & Drink"
        }
    ],
    "sg:phone":"+61 2 6495 7799",
    "sg:postcode":"2549",
    "sg:province":"NSW",
    "sg:tags":[
        "away",
        "take"
    ],
    "wof:name":"Tea Tree Cafe",
    "wof:placetype":"venue"
},
  "geometry": {"coordinates":[149.84703064000001,-36.9444541931],"type":"Point"}
}