{
  "type": "Feature",
  "properties": {
    "addr:full":"23 Friarbird Drv Narangba QLD 4504",
    "addr:housenumber":"23",
    "addr:postcode":"4504",
    "addr:street":"Friarbird Drv",
    "iso:country":"AU",
    "sg:address":"23 Friarbird Drv",
    "sg:city":"Narangba",
    "sg:classifiers":[
        {
            "category":"Professional",
            "subcategory":"Accounting & Tax Preparation",
            "type":"Services"
        }
    ],
    "sg:phone":"+61 7 3385 7986",
    "sg:postcode":"4504",
    "sg:province":"QLD",
    "sg:tags":[
        "bookkeeping"
    ],
    "wof:name":"My Business Bookkeeping",
    "wof:placetype":"venue"
},
  "geometry": {"coordinates":[152.93234252900001,-27.1824092865],"type":"Point"}
}