{
  "type": "Feature",
  "properties": {
    "addr:full":"121 Kinghorne St Nowra NSW 2541",
    "addr:housenumber":"121",
    "addr:postcode":"2541",
    "addr:street":"Kinghorne St",
    "iso:country":"AU",
    "sg:address":"121 Kinghorne St",
    "sg:city":"Nowra",
    "sg:classifiers":[
        {
            "category":"Health Services",
            "subcategory":"Chiropractor",
            "type":"Services"
        }
    ],
    "sg:phone":"+61 2 4421 3461",
    "sg:postcode":"2541",
    "sg:province":"NSW",
    "wof:name":"Nowra Chiropractic Centre",
    "wof:placetype":"venue"
},
  "geometry": {"coordinates":[150.601272583,-34.8823127747],"type":"Point"}
}