{
  "type": "Feature",
  "properties": {
    "addr:full":"Utley Rd Serpentine WA 6125",
    "addr:postcode":"6125",
    "addr:street":"Utley Rd",
    "iso:country":"AU",
    "sg:address":"Utley Rd",
    "sg:city":"Serpentine",
    "sg:classifiers":[
        {
            "category":"Farming",
            "subcategory":"Livestock Farm",
            "type":"Manufacturing & Wholesale Goods"
        }
    ],
    "sg:phone":"+61 8 9525 2181",
    "sg:postcode":"6125",
    "sg:province":"WA",
    "sg:tags":[
        "agistment"
    ],
    "wof:name":"Barridale Agistment Park",
    "wof:placetype":"venue"
},
  "geometry": {"coordinates":[115.977661133,-32.3993492126],"type":"Point"}
}