{
  "type": "Feature",
  "properties": {
    "addr:full":"44 Victoria St Forest Creek QLD 4873",
    "addr:housenumber":"44",
    "addr:postcode":"4873",
    "addr:street":"Victoria St",
    "iso:country":"AU",
    "sg:address":"44 Victoria St",
    "sg:city":"Forest Creek",
    "sg:classifiers":[
        {
            "category":"Social Services",
            "subcategory":"Child Care",
            "type":"Services"
        }
    ],
    "sg:phone":"+61 7 5465 4063",
    "sg:postcode":"4873",
    "sg:province":"QLD",
    "wof:name":"Little Friends On Forest",
    "wof:placetype":"venue"
},
  "geometry": {"coordinates":[145.36567688,-16.2463092804],"type":"Point"}
}