{
  "type": "Feature",
  "properties": {
    "addr:full":"2/ 268 South Pine Rd Enoggera QLD 4051",
    "addr:housenumber":"/ 268",
    "addr:postcode":"4051",
    "addr:street":"South Pine Rd",
    "iso:country":"AU",
    "sg:address":"2/ 268 South Pine Rd",
    "sg:city":"Enoggera",
    "sg:classifiers":[
        {
            "category":"Retail",
            "subcategory":"Auto Repair",
            "type":"Services"
        }
    ],
    "sg:phone":"+61 7 3855 2588",
    "sg:postcode":"4051",
    "sg:province":"QLD",
    "sg:tags":[
        "repairer",
        "motor",
        "engineer"
    ],
    "wof:name":"Aussie Automotive Services Enoggera",
    "wof:placetype":"venue"
},
  "geometry": {"coordinates":[152.993240356,-27.4174613953],"type":"Point"}
}