{
  "type": "Feature",
  "properties": {
    "addr:full":"19 Carrington St Queanbeyan ACT 2620",
    "addr:housenumber":"19",
    "addr:postcode":"2620",
    "addr:street":"Carrington St",
    "iso:country":"AU",
    "sg:address":"19 Carrington St",
    "sg:city":"Queanbeyan",
    "sg:classifiers":[
        {
            "category":"Manufacturing",
            "subcategory":"Metals",
            "type":"Manufacturing & Wholesale Goods"
        }
    ],
    "sg:phone":"+61 2 6299 5817",
    "sg:postcode":"2620",
    "sg:province":"ACT",
    "sg:tags":[
        "wholesaler",
        "aluminium",
        "mfrs"
    ],
    "wof:name":"Aluform Interior Supplies",
    "wof:placetype":"venue"
},
  "geometry": {"coordinates":[149.241653442,-35.3412246704],"type":"Point"}
}