{
  "type": "Feature",
  "properties": {
    "iso:country":"AU",
    "sg:address":"4 St Davids Cl",
    "sg:city":"Kirwan",
    "sg:classifiers":[
        {
            "category":"Retail",
            "subcategory":"Repair Shop",
            "type":"Services"
        }
    ],
    "sg:phone":"+61 7 4773 2439",
    "sg:postcode":"4817",
    "sg:province":"QLD",
    "sg:tags":[
        "stove",
        "part",
        "range"
    ],
    "wof:name":"Rogl's Electrical Pty Ltd",
    "wof:placetype":"venue"
},
  "geometry": {"coordinates":[146.73516799999999,-19.30369],"type":"Point"}
}