{
  "type": "Feature",
  "properties": {
    "addr:full":"Suite 3, 2 Elliot St Bundall QLD 4217",
    "addr:housenumber":"2",
    "addr:postcode":"4217",
    "addr:street":"Elliot St",
    "iso:country":"AU",
    "sg:address":"Suite 3, 2 Elliot St",
    "sg:city":"Bundall",
    "sg:classifiers":[
        {
            "category":"Professional",
            "subcategory":"Management & Consulting",
            "type":"Services"
        }
    ],
    "sg:phone":"+61 7 5592 1088",
    "sg:postcode":"4217",
    "sg:province":"QLD",
    "sg:tags":[
        "consultant",
        "migration"
    ],
    "wof:name":"Jiang Liu Consultancy Services",
    "wof:placetype":"venue"
},
  "geometry": {"coordinates":[153.41233825699999,-28.0108089447],"type":"Point"}
}