{
  "type": "Feature",
  "properties": {
    "iso:country":"AU",
    "sg:address":"1/ 504 Marmion St",
    "sg:city":"Booragoon",
    "sg:classifiers":[
        {
            "category":"Education",
            "subcategory":"School",
            "type":"Public Place"
        }
    ],
    "sg:phone":"+61 8 9330 6422",
    "sg:postcode":"6154",
    "sg:province":"WA",
    "sg:tags":[
        "correspondence"
    ],
    "wof:name":"Australian Islamic College",
    "wof:placetype":"venue"
},
  "geometry": {"coordinates":[115.824837,-32.03973],"type":"Point"}
}