{
  "type": "Feature",
  "properties": {
    "addr:full":"11/ 16 National Cct Barton ACT 2600",
    "addr:housenumber":"11 / 16",
    "addr:postcode":"2600",
    "addr:street":"National Cct",
    "iso:country":"AU",
    "sg:address":"11/ 16 National Cct",
    "sg:city":"Barton",
    "sg:classifiers":[
        {
            "category":"Organizations",
            "subcategory":"Professional Association",
            "type":"Services"
        }
    ],
    "sg:phone":"+61 2 6273 4694",
    "sg:postcode":"2600",
    "sg:province":"ACT",
    "sg:tags":[
        "organisation",
        "business"
    ],
    "wof:name":"ClubsACT",
    "wof:placetype":"venue"
},
  "geometry": {"coordinates":[149.133499145,-35.3084983826],"type":"Point"}
}