{
  "type": "Feature",
  "properties": {
    "addr:full":"83 Pacific Hwy Roseville NSW 2069",
    "addr:housenumber":"83",
    "addr:postcode":"2069",
    "addr:street":"Pacific Hwy",
    "iso:country":"AU",
    "sg:address":"83 Pacific Hwy",
    "sg:city":"Roseville",
    "sg:classifiers":[
        {
            "category":"Professional",
            "subcategory":"Employment Agencies",
            "type":"Services"
        }
    ],
    "sg:phone":"+61 2 9495 4444",
    "sg:postcode":"2069",
    "sg:province":"NSW",
    "wof:name":"HTN",
    "wof:placetype":"venue"
},
  "geometry": {"coordinates":[151.17747497600001,-33.7847633362],"type":"Point"}
}