{
  "type": "Feature",
  "properties": {
    "addr:full":"1a Castlereagh St Penrith NSW 2750",
    "addr:housenumber":"1a",
    "addr:postcode":"2750",
    "addr:street":"Castlereagh St",
    "iso:country":"AU",
    "sg:address":"1a Castlereagh St",
    "sg:city":"Penrith",
    "sg:classifiers":[
        {
            "category":"Shopping",
            "subcategory":"Bridal",
            "type":"Retail Goods"
        }
    ],
    "sg:phone":"+61 2 4722 4488",
    "sg:postcode":"2750",
    "sg:province":"NSW",
    "sg:tags":[
        "hire",
        "wear"
    ],
    "wof:name":"The Village Dry Cleaners",
    "wof:placetype":"venue"
},
  "geometry": {"coordinates":[150.86163330100001,-33.6807861328],"type":"Point"}
}