{
  "type": "Feature",
  "properties": {
    "addr:full":"76 Cutler Rd Jandakot WA 6164",
    "addr:housenumber":"76",
    "addr:postcode":"6164",
    "addr:street":"Cutler Rd",
    "iso:country":"AU",
    "sg:address":"76 Cutler Rd",
    "sg:city":"Jandakot",
    "sg:classifiers":[
        {
            "category":"Professional",
            "type":"Services"
        }
    ],
    "sg:phone":"+61 8 9414 7715",
    "sg:postcode":"6164",
    "sg:province":"WA",
    "sg:tags":[
        "transport"
    ],
    "wof:name":"Award Logistics",
    "wof:placetype":"venue"
},
  "geometry": {"coordinates":[115.867271,-32.120319],"type":"Point"}
}