{
  "type": "Feature",
  "properties": {
    "iso:country":"AU",
    "sg:address":"46A Albert St",
    "sg:city":"Warragul",
    "sg:classifiers":[
        {
            "category":"Health Services",
            "subcategory":"Doctor",
            "type":"Services"
        }
    ],
    "sg:phone":"+61 3 5622 2973",
    "sg:postcode":"3820",
    "sg:province":"VIC",
    "sg:tags":[
        "medical",
        "practitioner"
    ],
    "wof:name":"Kerbi, Trish Dr.",
    "wof:placetype":"venue"
},
  "geometry": {"coordinates":[145.93331900000001,-38.159866],"type":"Point"}
}