{
  "type": "Feature",
  "properties": {
    "iso:country":"AU",
    "sg:address":"8 Marchesi St",
    "sg:city":"Kewdale",
    "sg:classifiers":[
        {
            "category":"Utilities",
            "subcategory":"Natural Gas",
            "type":"Services"
        }
    ],
    "sg:phone":"+61 8 9353 7500",
    "sg:postcode":"6105",
    "sg:province":"WA",
    "sg:tags":[
        "supplier"
    ],
    "wof:name":"Parmelia Pipeline",
    "wof:placetype":"venue"
},
  "geometry": {"coordinates":[115.960403442,-31.9780464172],"type":"Point"}
}