{
  "type": "Feature",
  "properties": {
    "addr:full":"49 Powderworks Rd Narrabeen NSW 2101",
    "addr:housenumber":"49",
    "addr:postcode":"2101",
    "addr:street":"Powderworks Rd",
    "iso:country":"AU",
    "sg:address":"49 Powderworks Rd",
    "sg:city":"Narrabeen",
    "sg:classifiers":[
        {
            "category":"Building & Trades",
            "subcategory":"Construction",
            "type":"Services"
        }
    ],
    "sg:phone":"+61 414 441 667",
    "sg:postcode":"2101",
    "sg:province":"NSW",
    "sg:tags":[
        "rigging",
        "erection",
        "contractor"
    ],
    "wof:name":"All Over Rigging Pty Ltd",
    "wof:placetype":"venue"
},
  "geometry": {"coordinates":[151.290131,-33.701237],"type":"Point"}
}