{
  "type": "Feature",
  "properties": {
    "addr:full":"Shop 020, Supa Centa Patty's Pl Penrith NSW 2750",
    "addr:housenumber":"020",
    "addr:postcode":"2750",
    "addr:street":"Supa Centa Patty'S Pl",
    "iso:country":"AU",
    "sg:address":"Shop 020, Supa Centa Patty's Pl",
    "sg:city":"Penrith",
    "sg:classifiers":[
        {
            "category":"Retail",
            "subcategory":"Repair Shop",
            "type":"Services"
        }
    ],
    "sg:phone":"+61 2 4721 3332",
    "sg:postcode":"2750",
    "sg:province":"NSW",
    "sg:tags":[
        "machine",
        "sewing"
    ],
    "wof:name":"Penrith Creative Sewing Centre",
    "wof:placetype":"venue"
},
  "geometry": {"coordinates":[150.68374633799999,-33.7659645081],"type":"Point"}
}