{
  "type": "Feature",
  "properties": {
    "iso:country":"AU",
    "sg:address":"PO Box 667",
    "sg:city":"Frankston",
    "sg:classifiers":[
        {
            "category":"Professional",
            "subcategory":"Employment Agencies",
            "type":"Services"
        }
    ],
    "sg:phone":"+61 3 9776 5485",
    "sg:postcode":"8856",
    "sg:province":"VIC",
    "sg:tags":[
        "entertainer",
        "agent"
    ],
    "wof:name":"Face Painting For Parties",
    "wof:placetype":"venue"
},
  "geometry": {"coordinates":[145.121796,-38.141571],"type":"Point"}
}