{
  "type": "Feature",
  "properties": {
    "addr:full":"31 Hercules Crs Albany WA 6330",
    "addr:housenumber":"31",
    "addr:postcode":"6330",
    "addr:street":"Hercules Crs",
    "iso:country":"AU",
    "sg:address":"31 Hercules Crs",
    "sg:city":"Albany",
    "sg:classifiers":[
        {
            "category":"Manufacturing",
            "subcategory":"Furniture",
            "type":"Manufacturing & Wholesale Goods"
        }
    ],
    "sg:phone":"+61 8 9842 8555",
    "sg:postcode":"6330",
    "sg:province":"WA",
    "sg:tags":[
        "builder",
        "designer",
        "custom"
    ],
    "wof:name":"Albany Fine Furniture",
    "wof:placetype":"venue"
},
  "geometry": {"coordinates":[117.87899017300001,-35.0121574402],"type":"Point"}
}