{
  "type": "Feature",
  "properties": {
    "addr:full":"73 York St Sydney NSW 2000",
    "addr:housenumber":"73",
    "addr:postcode":"2000",
    "addr:street":"York St",
    "iso:country":"AU",
    "sg:address":"73 York St",
    "sg:city":"Sydney",
    "sg:classifiers":[
        {
            "category":"Insurance",
            "subcategory":"Health Insurance",
            "type":"Services"
        }
    ],
    "sg:phone":"+61 2 9657 1200",
    "sg:postcode":"2000",
    "sg:province":"NSW",
    "wof:name":"HBA",
    "wof:placetype":"venue"
},
  "geometry": {"coordinates":[151.20585632300001,-33.8683853149],"type":"Point"}
}