{
  "type": "Feature",
  "properties": {
    "addr:full":"Unit 4/7- 9 Streiff Rd Wingfield SA 5013",
    "addr:housenumber":"9",
    "addr:postcode":"5013",
    "addr:street":"Streiff Rd",
    "iso:country":"AU",
    "sg:address":"Unit 4/7- 9 Streiff Rd",
    "sg:city":"Wingfield",
    "sg:classifiers":[
        {
            "category":"Shopping",
            "subcategory":"Bicycles & Sporting Goods",
            "type":"Retail Goods"
        }
    ],
    "sg:phone":"+61 1800 688 552",
    "sg:postcode":"5013",
    "sg:province":"SA",
    "sg:tags":[
        "chemical",
        "equipment",
        "pool",
        "swimming"
    ],
    "wof:name":"Clearwater",
    "wof:placetype":"venue"
},
  "geometry": {"coordinates":[138.56625366200001,-34.8487892151],"type":"Point"}
}