{
  "type": "Feature",
  "properties": {
    "iso:country":"AU",
    "sg:address":"1/ 1A Elizabeth St",
    "sg:city":"Mt Gambier",
    "sg:classifiers":[
        {
            "category":"Personal",
            "subcategory":"Beauty Salon",
            "type":"Services"
        }
    ],
    "sg:phone":"+61 8 8725 9368",
    "sg:postcode":"5290",
    "sg:province":"SA",
    "wof:name":"Fuss Massage & Beauty",
    "wof:placetype":"venue"
},
  "geometry": {"coordinates":[140.777725,-37.824478],"type":"Point"}
}