{
  "type": "Feature",
  "properties": {
    "addr:full":"Lot 11 McLean Rd Birdwood SA 5234",
    "addr:postcode":"5234",
    "addr:street":"Mclean Rd",
    "iso:country":"AU",
    "sg:address":"Lot 11 McLean Rd",
    "sg:city":"Birdwood",
    "sg:classifiers":[
        {
            "category":"Farming",
            "subcategory":"Livestock Farm",
            "type":"Manufacturing & Wholesale Goods"
        }
    ],
    "sg:phone":"+61 8 8568 1828",
    "sg:postcode":"5234",
    "sg:province":"SA",
    "sg:tags":[
        "breeder",
        "horse",
        "stud"
    ],
    "wof:name":"Glenbeigh Thoroughbreds",
    "wof:placetype":"venue"
},
  "geometry": {"coordinates":[139.01071167000001,-34.8096885681],"type":"Point"}
}