{
  "type": "Feature",
  "properties": {
    "iso:country":"AU",
    "sg:address":"43- 45 Vinter Ave",
    "sg:city":"Croydon",
    "sg:classifiers":[
        {
            "category":"Building & Trades",
            "subcategory":"Construction",
            "type":"Services"
        }
    ],
    "sg:phone":"+61 3 9723 2439",
    "sg:postcode":"3136",
    "sg:province":"VIC",
    "sg:tags":[
        "home",
        "air conditioning"
    ],
    "wof:name":"Outer Eastern Heating & Cooling",
    "wof:placetype":"venue"
},
  "geometry": {"coordinates":[145.278564453,-37.8058891296],"type":"Point"}
}