{
  "type": "Feature",
  "properties": {
    "addr:full":"PO Box 330 Gulgong NSW 2852",
    "addr:postcode":"2852",
    "iso:country":"AU",
    "sg:address":"PO Box 330",
    "sg:city":"Gulgong",
    "sg:classifiers":[
        {
            "category":"Professional",
            "subcategory":"Computer Services",
            "type":"Services"
        }
    ],
    "sg:phone":"+61 2 6374 1179",
    "sg:postcode":"2852",
    "sg:province":"NSW",
    "sg:tags":[
        "repairs",
        "upgrade",
        "equipment"
    ],
    "wof:name":"Roberts Mobile Computer Services",
    "wof:placetype":"venue"
},
  "geometry": {"coordinates":[149.529404,-32.36274],"type":"Point"}
}