{
  "type": "Feature",
  "properties": {
    "addr:full":"139a Great North Rd Five Dock NSW 2046",
    "addr:housenumber":"139a",
    "addr:postcode":"2046",
    "addr:street":"Great North Rd",
    "iso:country":"AU",
    "sg:address":"139a Great North Rd",
    "sg:city":"Five Dock",
    "sg:classifiers":[
        {
            "category":"Personal",
            "subcategory":"Beauty Salon",
            "type":"Services"
        }
    ],
    "sg:phone":"+61 2 9713 5606",
    "sg:postcode":"2046",
    "sg:province":"NSW",
    "sg:tags":[
        "hairdresser"
    ],
    "wof:name":"Over The Top Hair Design",
    "wof:placetype":"venue"
},
  "geometry": {"coordinates":[151.12957800000001,-33.868038],"type":"Point"}
}