{
  "type": "Feature",
  "properties": {
    "iso:country":"AU",
    "sg:address":"Freeman Drv",
    "sg:city":"Lochinvar",
    "sg:classifiers":[
        {
            "category":"Wholesale",
            "subcategory":"Machinery & Supplies",
            "type":"Manufacturing & Wholesale Goods"
        }
    ],
    "sg:phone":"+61 414 234 841",
    "sg:postcode":"2321",
    "sg:province":"NSW",
    "sg:tags":[
        "agricultural"
    ],
    "wof:name":"Lawrence's Ag & Machinery Repairs",
    "wof:placetype":"venue"
},
  "geometry": {"coordinates":[151.45127868599999,-32.7024765015],"type":"Point"}
}