{
  "type": "Feature",
  "properties": {
    "addr:full":"1418a Centre Rd Clayton VIC 3168",
    "addr:housenumber":"1418a",
    "addr:postcode":"3168",
    "addr:street":"Centre Rd",
    "iso:country":"AU",
    "sg:address":"1418a Centre Rd",
    "sg:city":"Clayton",
    "sg:classifiers":[
        {
            "category":"Building & Trades",
            "subcategory":"Equipment Rental",
            "type":"Services"
        }
    ],
    "sg:phone":"+61 3 9543 1611",
    "sg:postcode":"3168",
    "sg:province":"VIC",
    "sg:tags":[
        "supply",
        "catering"
    ],
    "sg:website":"http://www.cfmvic.com.au",
    "wof:name":"Commercial Food Machinery Vic Pty Ltd",
    "wof:placetype":"venue"
},
  "geometry": {"coordinates":[145.12620544399999,-37.9295196533],"type":"Point"}
}