{
  "type": "Feature",
  "properties": {
    "iso:country":"AU",
    "sg:address":"Cnr Boundary & Racecourse Rds",
    "sg:city":"Flemington",
    "sg:classifiers":[
        {
            "category":"Food & Beverages",
            "subcategory":"Groceries & Convenience Stores",
            "type":"Retail Goods"
        }
    ],
    "sg:phone":"+61 3 9329 7603",
    "sg:postcode":"3031",
    "sg:province":"VIC",
    "wof:name":"7-Eleven Stores Pty Ltd",
    "wof:placetype":"venue"
},
  "geometry": {"coordinates":[144.940033,-37.789185],"type":"Point"}
}