{
  "type": "Feature",
  "properties": {
    "iso:country":"AU",
    "sg:address":"Unit 1, 390 Stuart Hwy",
    "sg:city":"Winnellie",
    "sg:classifiers":[
        {
            "category":"Home & Garden",
            "subcategory":"Building Materials",
            "type":"Retail Goods"
        }
    ],
    "sg:phone":"+61 8 8984 4220",
    "sg:postcode":"0820",
    "sg:province":"NT",
    "sg:tags":[
        "fitting",
        "door"
    ],
    "wof:name":"Folding Doors & Walls By Lotus",
    "wof:placetype":"venue"
},
  "geometry": {"coordinates":[130.870803833,-12.4255065918],"type":"Point"}
}