{
  "type": "Feature",
  "properties": {
    "addr:full":"38 Ballard St Yarraville VIC 3013",
    "addr:housenumber":"38",
    "addr:postcode":"3013",
    "addr:street":"Ballard St",
    "iso:country":"AU",
    "sg:address":"38 Ballard St",
    "sg:city":"Yarraville",
    "sg:classifiers":[
        {
            "category":"Professional",
            "subcategory":"Computer Services",
            "type":"Services"
        }
    ],
    "sg:phone":"+61 3 9314 7270",
    "sg:postcode":"3013",
    "sg:province":"VIC",
    "sg:tags":[
        "training"
    ],
    "wof:name":"Kerri Ogden & Assoc",
    "wof:placetype":"venue"
},
  "geometry": {"coordinates":[144.86744689899999,-37.8159484863],"type":"Point"}
}