{
  "type": "Feature",
  "properties": {
    "iso:country":"AU",
    "sg:address":"Unit 2/22- 24 Norman St",
    "sg:city":"Peakhurst",
    "sg:classifiers":[
        {
            "category":"Health Services",
            "subcategory":"Clinic",
            "type":"Services"
        }
    ],
    "sg:phone":"+61 2 9534 4077",
    "sg:postcode":"2210",
    "sg:province":"NSW",
    "sg:tags":[
        "aromatherapy"
    ],
    "wof:name":"Sasy N Savy Pty Ltd",
    "wof:placetype":"venue"
},
  "geometry": {"coordinates":[151.064606,-33.964359],"type":"Point"}
}