{
  "type": "Feature",
  "properties": {
    "addr:full":"97 Herbert St Gulgong NSW 2852",
    "addr:housenumber":"97",
    "addr:postcode":"2852",
    "addr:street":"Herbert St",
    "iso:country":"AU",
    "sg:address":"97 Herbert St",
    "sg:city":"Gulgong",
    "sg:classifiers":[
        {
            "category":"Travel",
            "subcategory":"Hotels & Motels",
            "type":"Entertainment"
        }
    ],
    "sg:phone":"+61 2 6374 1031",
    "sg:postcode":"2852",
    "sg:province":"NSW",
    "sg:tags":[
        "accommodation"
    ],
    "wof:name":"Post Office Hotel",
    "wof:placetype":"venue"
},
  "geometry": {"coordinates":[149.53349299999999,-32.363297],"type":"Point"}
}