{
  "type": "Feature",
  "properties": {
    "addr:full":"37 Ryde Rd Pymble NSW 2073",
    "addr:housenumber":"37",
    "addr:postcode":"2073",
    "addr:street":"Ryde Rd",
    "iso:country":"AU",
    "sg:address":"37 Ryde Rd",
    "sg:city":"Pymble",
    "sg:classifiers":[
        {
            "category":"Professional",
            "subcategory":"Engineering",
            "type":"Services"
        }
    ],
    "sg:phone":"+61 2 9418 1444",
    "sg:postcode":"2073",
    "sg:province":"NSW",
    "sg:tags":[
        "consulting",
        "engineer"
    ],
    "wof:name":"Barry Webb & Associates (NSW) Pty Ltd",
    "wof:placetype":"venue"
},
  "geometry": {"coordinates":[151.14236450199999,-33.7528800964],"type":"Point"}
}