{
  "type": "Feature",
  "properties": {
    "iso:country":"AU",
    "sg:address":"102 Byng St",
    "sg:city":"Orange",
    "sg:classifiers":[
        {
            "category":"Shopping",
            "subcategory":"Clothing, Apparel, & Fashions",
            "type":"Retail Goods"
        }
    ],
    "sg:phone":"+61 2 6362 2655",
    "sg:postcode":"2800",
    "sg:province":"NSW",
    "sg:tags":[
        "lady",
        "wear"
    ],
    "wof:name":"Kezz Brett",
    "wof:placetype":"venue"
},
  "geometry": {"coordinates":[149.094604492,-33.2808151245],"type":"Point"}
}