{
  "type": "Feature",
  "properties": {
    "addr:full":"7/ 95 Hay St Subiaco WA 6008",
    "addr:housenumber":"/ 95",
    "addr:postcode":"6008",
    "addr:street":"Hay St",
    "iso:country":"AU",
    "sg:address":"7/ 95 Hay St",
    "sg:city":"Subiaco",
    "sg:classifiers":[
        {
            "category":"Professional",
            "subcategory":"Detective & Security Services",
            "type":"Services"
        }
    ],
    "sg:phone":"+61 8 9381 3111",
    "sg:postcode":"6008",
    "sg:province":"WA",
    "sg:tags":[
        "consultant",
        "system"
    ],
    "wof:name":"Frontline Security Systems",
    "wof:placetype":"venue"
},
  "geometry": {"coordinates":[115.834632873,-31.9472026825],"type":"Point"}
}