{
  "type": "Feature",
  "properties": {
    "addr:full":"Jamison Rd Penrith NSW 2750",
    "addr:postcode":"2750",
    "addr:street":"Jamison Rd",
    "iso:country":"AU",
    "sg:address":"Jamison Rd",
    "sg:city":"Penrith",
    "sg:classifiers":[
        {
            "category":"Education",
            "subcategory":"School",
            "type":"Public Place"
        }
    ],
    "sg:phone":"+61 2 4721 3160",
    "sg:postcode":"2750",
    "sg:province":"NSW",
    "sg:tags":[
        "state",
        "-",
        "nsw"
    ],
    "wof:name":"Penrith South Public School",
    "wof:placetype":"venue"
},
  "geometry": {"coordinates":[150.676345825,-33.7596931458],"type":"Point"}
}