{
  "type": "Feature",
  "properties": {
    "iso:country":"AU",
    "sg:address":"Unit 5, 70A Christian Rd",
    "sg:city":"Punchbowl",
    "sg:classifiers":[
        {
            "category":"Building & Trades",
            "subcategory":"Cleaning & Sanitation",
            "type":"Services"
        }
    ],
    "sg:phone":"+61 2 9758 5331",
    "sg:postcode":"2196",
    "sg:province":"NSW",
    "sg:tags":[
        "asbestos",
        "treatment",
        "removal"
    ],
    "wof:name":"Allstate Asbestos & Demolition P/L",
    "wof:placetype":"venue"
},
  "geometry": {"coordinates":[151.058609,-33.936993],"type":"Point"}
}