{
  "type": "Feature",
  "properties": {
    "addr:full":"60 Pitt St Sydney NSW 2000",
    "addr:housenumber":"60",
    "addr:postcode":"2000",
    "addr:street":"Pitt St",
    "iso:country":"AU",
    "sg:address":"60 Pitt St",
    "sg:city":"Sydney",
    "sg:classifiers":[
        {
            "category":"Professional",
            "subcategory":"Accounting & Tax Preparation",
            "type":"Services"
        }
    ],
    "sg:phone":"+61 2 9232 7466",
    "sg:postcode":"2000",
    "sg:province":"NSW",
    "sg:tags":[
        "accountant",
        "auditor"
    ],
    "wof:name":"Ellis John E",
    "wof:placetype":"venue"
},
  "geometry": {"coordinates":[151.208984375,-33.8643836975],"type":"Point"}
}