{
  "type": "Feature",
  "properties": {
    "addr:full":"Goddard La Westdale NSW 2340",
    "addr:postcode":"2340",
    "addr:street":"Goddard La Westdale",
    "iso:country":"AU",
    "sg:address":"Goddard La",
    "sg:city":"Westdale",
    "sg:classifiers":[
        {
            "category":"Shopping",
            "type":"Retail Goods"
        }
    ],
    "sg:phone":"+61 2 6760 7108",
    "sg:postcode":"2340",
    "sg:province":"NSW",
    "sg:tags":[
        "agent",
        "stock"
    ],
    "wof:name":"Tamworth Regional Livestock Marketing Centre",
    "wof:placetype":"venue"
},
  "geometry": {"coordinates":[150.853805542,-31.0801830292],"type":"Point"}
}