{
  "type": "Feature",
  "properties": {
    "iso:country":"AU",
    "sg:address":"Store E 53, Adelaide Produce Market, Diagonal Rd",
    "sg:city":"Pooraka",
    "sg:classifiers":[
        {
            "category":"Food & Beverages",
            "subcategory":"Fruits & Vegetables",
            "type":"Retail Goods"
        }
    ],
    "sg:phone":"+61 8 8349 5065",
    "sg:postcode":"5095",
    "sg:province":"SA",
    "sg:tags":[
        "greengrocer",
        "fruiterer"
    ],
    "wof:name":"Quality Lines",
    "wof:placetype":"venue"
},
  "geometry": {"coordinates":[138.61585998499999,-34.8260993958],"type":"Point"}
}