{
  "type": "Feature",
  "properties": {
    "addr:full":"PO Box 263 Mosman Park PO Boxes WA 6912",
    "addr:postcode":"6912",
    "iso:country":"AU",
    "sg:address":"PO Box 263",
    "sg:city":"Mosman Park PO Boxes",
    "sg:classifiers":[
        {
            "category":"Shopping",
            "subcategory":"Computers & Home Electronics",
            "type":"Retail Goods"
        }
    ],
    "sg:phone":"+61 8 6461 4216",
    "sg:postcode":"6912",
    "sg:province":"WA",
    "sg:tags":[
        "equipment",
        "part",
        "electronic"
    ],
    "wof:name":"ASMD Electronics",
    "wof:placetype":"venue"
},
  "geometry": {"coordinates":[115.76226043699999,-32.0069694519],"type":"Point"}
}