{
  "type": "Feature",
  "properties": {
    "addr:full":"78 Garsed St Bendigo VIC 3550",
    "addr:housenumber":"78",
    "addr:postcode":"3550",
    "addr:street":"Garsed St",
    "iso:country":"AU",
    "sg:address":"78 Garsed St",
    "sg:city":"Bendigo",
    "sg:classifiers":[
        {
            "category":"Retail",
            "subcategory":"Car Wash",
            "type":"Services"
        }
    ],
    "sg:phone":"+61 3 5442 8666",
    "sg:postcode":"3550",
    "sg:province":"VIC",
    "sg:tags":[
        "truck",
        "cleaning"
    ],
    "wof:name":"Bendigo Detailing Specialists",
    "wof:placetype":"venue"
},
  "geometry": {"coordinates":[144.278244019,-36.7657203674],"type":"Point"}
}