{
  "type": "Feature",
  "properties": {
    "addr:full":"11 Taylor St Kempsey NSW 2440",
    "addr:housenumber":"11",
    "addr:postcode":"2440",
    "addr:street":"Taylor St",
    "iso:country":"AU",
    "sg:address":"11 Taylor St",
    "sg:city":"Kempsey",
    "sg:classifiers":[
        {
            "category":"Building & Trades",
            "subcategory":"Equipment Rental",
            "type":"Services"
        }
    ],
    "sg:phone":"+61 2 6563 1155",
    "sg:postcode":"2440",
    "sg:province":"NSW",
    "sg:tags":[
        "party",
        "hire"
    ],
    "wof:name":"Big Event Hire",
    "wof:placetype":"venue"
},
  "geometry": {"coordinates":[152.82577499999999,-31.088335],"type":"Point"}
}