{
  "type": "Feature",
  "properties": {
    "addr:full":"8 Downes St Winnellie NT 0820",
    "addr:housenumber":"8",
    "addr:postcode":"nt 0820",
    "addr:street":"Downes St",
    "iso:country":"AU",
    "sg:address":"8 Downes St",
    "sg:city":"Winnellie",
    "sg:classifiers":[
        {
            "category":"Professional",
            "subcategory":"Detective & Security Services",
            "type":"Services"
        }
    ],
    "sg:phone":"+61 8 8947 0190",
    "sg:postcode":"0820",
    "sg:province":"NT",
    "sg:tags":[
        "equipment",
        "window",
        "doors"
    ],
    "wof:name":"Service On Security Screens",
    "wof:placetype":"venue"
},
  "geometry": {"coordinates":[130.88143920900001,-12.4285736084],"type":"Point"}
}