{
  "type": "Feature",
  "properties": {
    "iso:country":"AU",
    "sg:address":"75 Great Ocean Rd",
    "sg:city":"Aireys Inlet",
    "sg:classifiers":[
        {
            "category":"Communications",
            "subcategory":"Film & Video Production",
            "type":"Services"
        }
    ],
    "sg:phone":"+61 3 5289 7344",
    "sg:postcode":"3231",
    "sg:province":"VIC",
    "sg:tags":[
        "dvd",
        "library"
    ],
    "wof:name":"Lighthouse View Books & Videos",
    "wof:placetype":"venue"
},
  "geometry": {"coordinates":[144.09992980999999,-38.464641571],"type":"Point"}
}