{
  "type": "Feature",
  "properties": {
    "iso:country":"AU",
    "sg:address":"134 Pine Creek Cct",
    "sg:city":"St Clair",
    "sg:classifiers":[
        {
            "category":"Wholesale",
            "subcategory":"Machinery & Supplies",
            "type":"Manufacturing & Wholesale Goods"
        }
    ],
    "sg:phone":"+61 2 9834 6027",
    "sg:postcode":"2759",
    "sg:province":"NSW",
    "sg:tags":[
        "engineer"
    ],
    "wof:name":"ASTEG Sales Pty Ltd",
    "wof:placetype":"venue"
},
  "geometry": {"coordinates":[150.775924683,-33.8084716797],"type":"Point"}
}