{
  "type": "Feature",
  "properties": {
    "addr:full":"5/ 501 Olive St Albury NSW 2640",
    "addr:housenumber":"/ 501",
    "addr:postcode":"2640",
    "addr:street":"Olive St",
    "iso:country":"AU",
    "sg:address":"5/ 501 Olive St",
    "sg:city":"Albury",
    "sg:classifiers":[
        {
            "category":"Manufacturing",
            "subcategory":"Food",
            "type":"Manufacturing & Wholesale Goods"
        }
    ],
    "sg:phone":"+61 417 437 984",
    "sg:postcode":"2640",
    "sg:province":"NSW",
    "sg:tags":[
        "function",
        "catering"
    ],
    "wof:name":"Coffee Mamma",
    "wof:placetype":"venue"
},
  "geometry": {"coordinates":[146.918243408,-36.08152771],"type":"Point"}
}