{
  "type": "Feature",
  "properties": {
    "iso:country":"AU",
    "sg:address":"33 Princes Hwy",
    "sg:city":"Bairnsdale",
    "sg:classifiers":[
        {
            "category":"Retail",
            "subcategory":"Auto Repair",
            "type":"Services"
        }
    ],
    "sg:phone":"+61 3 5152 5041",
    "sg:postcode":"3875",
    "sg:province":"VIC",
    "sg:tags":[
        "repairer",
        "motor",
        "engineer"
    ],
    "wof:name":"Automotive Templar",
    "wof:placetype":"venue"
},
  "geometry": {"coordinates":[147.64671325699999,-37.8226013184],"type":"Point"}
}