{
  "type": "Feature",
  "properties": {
    "addr:full":"14 Manufacturer Drv Molendinar QLD 4214",
    "addr:housenumber":"14",
    "addr:postcode":"4214",
    "addr:street":"Manufacturer Drv",
    "iso:country":"AU",
    "sg:address":"14 Manufacturer Drv",
    "sg:city":"Molendinar",
    "sg:classifiers":[
        {
            "category":"Home & Garden",
            "subcategory":"Hardware",
            "type":"Retail Goods"
        }
    ],
    "sg:phone":"+61 7 5594 9607",
    "sg:postcode":"4214",
    "sg:province":"QLD",
    "sg:tags":[
        "pumping",
        "contractor"
    ],
    "wof:name":"Australian Dewatering Systems Pty Ltd",
    "wof:placetype":"venue"
},
  "geometry": {"coordinates":[153.36448669399999,-27.9655017853],"type":"Point"}
}