{
  "type": "Feature",
  "properties": {
    "addr:full":"88- 90 Lara Way Campbellfield VIC 3061",
    "addr:housenumber":"90",
    "addr:postcode":"3061",
    "addr:street":"Lara Way",
    "iso:country":"AU",
    "sg:address":"88- 90",
    "sg:city":"Lara Way Campbellfield",
    "sg:classifiers":[
        {
            "category":"Mining & Drilling",
            "type":"Manufacturing & Wholesale Goods"
        }
    ],
    "sg:phone":"+61 3 9357 5033",
    "sg:postcode":"3061",
    "sg:province":"VIC",
    "sg:tags":[
        "boring",
        "contractor"
    ],
    "wof:name":"Metrobore Australia",
    "wof:placetype":"venue"
},
  "geometry": {"coordinates":[144.96760559099999,-37.6679954529],"type":"Point"}
}