{
  "type": "Feature",
  "properties": {
    "addr:full":"Kangertong Rd Hawkesdale VIC 3287",
    "addr:postcode":"3287",
    "addr:street":"Kangertong Rd",
    "iso:country":"AU",
    "sg:address":"Kangertong Rd",
    "sg:city":"Hawkesdale",
    "sg:classifiers":[
        {
            "category":"Manufacturing",
            "subcategory":"Metals",
            "type":"Manufacturing & Wholesale Goods"
        }
    ],
    "sg:phone":"+61 3 5560 7321",
    "sg:postcode":"3287",
    "sg:province":"VIC",
    "sg:tags":[
        "steel",
        "fabricator",
        "mfrs"
    ],
    "wof:name":"Hawkesdale Steel Fabrication",
    "wof:placetype":"venue"
},
  "geometry": {"coordinates":[142.257369995,-38.093120575],"type":"Point"}
}