{
  "type": "Feature",
  "properties": {
    "addr:full":"31- 35 Johnson St Keon Park VIC 3073",
    "addr:housenumber":"35",
    "addr:postcode":"3073",
    "addr:street":"Johnson St",
    "iso:country":"AU",
    "sg:address":"31- 35 Johnson St",
    "sg:city":"Keon Park",
    "sg:classifiers":[
        {
            "category":"Building & Trades",
            "subcategory":"Equipment Rental",
            "type":"Services"
        }
    ],
    "sg:phone":"+61 3 9469 3555",
    "sg:postcode":"3073",
    "sg:province":"VIC",
    "sg:tags":[
        "renting",
        "trailer"
    ],
    "wof:name":"Premier Trailer Hire",
    "wof:placetype":"venue"
},
  "geometry": {"coordinates":[145.012374878,-37.6961288452],"type":"Point"}
}