{
  "type": "Feature",
  "properties": {
    "addr:full":"PO Box 1519 Ballina NSW 2478",
    "addr:postcode":"2478",
    "iso:country":"AU",
    "sg:address":"PO Box 1519",
    "sg:city":"Ballina",
    "sg:classifiers":[
        {
            "category":"Professional",
            "subcategory":"Testing Lab",
            "type":"Services"
        }
    ],
    "sg:phone":"+61 2 6687 4650",
    "sg:postcode":"2478",
    "sg:province":"NSW",
    "sg:tags":[
        "soil",
        "investigation"
    ],
    "wof:name":"Environmental Earth Sciences Pty Ltd",
    "wof:placetype":"venue"
},
  "geometry": {"coordinates":[153.554962158,-28.8678798676],"type":"Point"}
}