{
  "type": "Feature",
  "properties": {
    "addr:full":"59 Park St South Melbourne VIC 3205",
    "addr:housenumber":"59",
    "addr:postcode":"3205",
    "addr:street":"Park St",
    "iso:country":"AU",
    "sg:address":"59 Park St",
    "sg:city":"South Melbourne",
    "sg:classifiers":[
        {
            "category":"Professional",
            "subcategory":"Engineering",
            "type":"Services"
        }
    ],
    "sg:phone":"+61 3 9696 5155",
    "sg:postcode":"3205",
    "sg:province":"VIC",
    "sg:tags":[
        "consulting",
        "engineer"
    ],
    "wof:name":"Lucci Lighting Solutions",
    "wof:placetype":"venue"
},
  "geometry": {"coordinates":[144.96820099999999,-37.83342],"type":"Point"}
}