{
  "type": "Feature",
  "properties": {
    "iso:country":"AU",
    "sg:address":"6/ Building 2",
    "sg:city":"Warners Bay",
    "sg:classifiers":[
        {
            "category":"Shopping",
            "subcategory":"Bicycles & Sporting Goods",
            "type":"Retail Goods"
        }
    ],
    "sg:phone":"+61 2 4954 4115",
    "sg:postcode":"2282",
    "sg:province":"NSW",
    "sg:tags":[
        "dance",
        "accessory",
        "wear",
        "supply"
    ],
    "wof:name":"D Direct & KPR Design",
    "wof:placetype":"venue"
},
  "geometry": {"coordinates":[151.64674377399999,-32.9819068909],"type":"Point"}
}