{
  "type": "Feature",
  "properties": {
    "addr:full":"71 Comur St Yass ACT 2582",
    "addr:housenumber":"71",
    "addr:postcode":"2582",
    "addr:street":"Comur St",
    "iso:country":"AU",
    "sg:address":"71 Comur St",
    "sg:city":"Yass",
    "sg:classifiers":[
        {
            "category":"Personal",
            "subcategory":"Beauty Salon",
            "type":"Services"
        }
    ],
    "sg:phone":"+61 2 6226 3446",
    "sg:postcode":"2582",
    "sg:province":"ACT",
    "wof:name":"Beauty On Comur",
    "wof:placetype":"venue"
},
  "geometry": {"coordinates":[148.91195678700001,-34.8426856995],"type":"Point"}
}