{
  "type": "Feature",
  "properties": {
    "addr:full":"8 Kirkfell Crt Berwick VIC 3806",
    "addr:housenumber":"8",
    "addr:postcode":"3806",
    "addr:street":"Kirkfell Crt",
    "iso:country":"AU",
    "sg:address":"8 Kirkfell Crt",
    "sg:city":"Berwick",
    "sg:classifiers":[
        {
            "category":"Professional",
            "subcategory":"Engineering",
            "type":"Services"
        }
    ],
    "sg:phone":"+61 3 9707 3110",
    "sg:postcode":"3806",
    "sg:province":"VIC",
    "sg:tags":[
        "consulting",
        "engineer"
    ],
    "wof:name":"Explosion Protection Technology",
    "wof:placetype":"venue"
},
  "geometry": {"coordinates":[145.33505249000001,-38.0308914185],"type":"Point"}
}