{
  "type": "Feature",
  "properties": {
    "addr:full":"73 Gardyne St Bronte NSW 2024",
    "addr:housenumber":"73",
    "addr:postcode":"2024",
    "addr:street":"Gardyne St",
    "iso:country":"AU",
    "sg:address":"73 Gardyne St",
    "sg:city":"Bronte",
    "sg:classifiers":[
        {
            "category":"Professional",
            "subcategory":"Employment Agencies",
            "type":"Services"
        }
    ],
    "sg:phone":"+61 2 9387 6660",
    "sg:postcode":"2024",
    "sg:province":"NSW",
    "sg:tags":[
        "entertainer",
        "agent"
    ],
    "wof:name":"Guitar Magic With Leonard",
    "wof:placetype":"venue"
},
  "geometry": {"coordinates":[151.265167236,-33.9060287476],"type":"Point"}
}