{
  "type": "Feature",
  "properties": {
    "iso:country":"AU",
    "sg:address":"496 Boundary Rd",
    "sg:city":"Archerfield",
    "sg:classifiers":[
        {
            "category":"Autos & Motor Vehicles",
            "subcategory":"Auto Supplies",
            "type":"Retail Goods"
        }
    ],
    "sg:phone":"+61 7 3875 1599",
    "sg:postcode":"4108",
    "sg:province":"QLD",
    "sg:tags":[
        "tyre"
    ],
    "wof:name":"Tyrecorp Australia, Qld",
    "wof:placetype":"venue"
},
  "geometry": {"coordinates":[153.01632690400001,-27.5670223236],"type":"Point"}
}