{
  "type": "Feature",
  "properties": {
    "iso:country":"AU",
    "sg:address":"14 Lightwood Crt",
    "sg:city":"South Morang",
    "sg:classifiers":[
        {
            "category":"Personal",
            "subcategory":"Beauty Salon",
            "type":"Services"
        }
    ],
    "sg:phone":"+61 402 816 868",
    "sg:postcode":"3752",
    "sg:province":"VIC",
    "wof:name":"Ultimate Body Essentials",
    "wof:placetype":"venue"
},
  "geometry": {"coordinates":[145.098877,-37.655697],"type":"Point"}
}