{
  "type": "Feature",
  "properties": {
    "iso:country":"AU",
    "sg:address":"251 Queensberry St",
    "sg:city":"Carlton South",
    "sg:classifiers":[
        {
            "category":"Organizations",
            "subcategory":"Labor Organization",
            "type":"Services"
        }
    ],
    "sg:phone":"+61 3 9230 5700",
    "sg:postcode":"3053",
    "sg:province":"VIC",
    "sg:tags":[
        "union"
    ],
    "wof:name":"Australian Manufacturing Workers' Union",
    "wof:placetype":"venue"
},
  "geometry": {"coordinates":[144.960250855,-37.8043632507],"type":"Point"}
}