{
  "type": "Feature",
  "properties": {
    "addr:full":"240 Spence St Cairns QLD 4870",
    "addr:housenumber":"240",
    "addr:postcode":"4870",
    "addr:street":"Spence St",
    "iso:country":"AU",
    "sg:address":"240 Spence St",
    "sg:city":"Cairns",
    "sg:classifiers":[
        {
            "category":"Home & Garden",
            "subcategory":"Kitchen Supply",
            "type":"Retail Goods"
        }
    ],
    "sg:phone":"+61 7 4031 6610",
    "sg:postcode":"4870",
    "sg:province":"QLD",
    "sg:tags":[
        "equipment",
        "surveyor"
    ],
    "wof:name":"Suncoast Optical",
    "wof:placetype":"venue"
},
  "geometry": {"coordinates":[145.75445556599999,-16.941318512],"type":"Point"}
}