{
  "type": "Feature",
  "properties": {
    "iso:country":"AU",
    "sg:address":"22 Grey St",
    "sg:city":"Terang",
    "sg:classifiers":[
        {
            "category":"Professional",
            "subcategory":"Art Services",
            "type":"Services"
        }
    ],
    "sg:phone":"+61 3 5592 1005",
    "sg:postcode":"3264",
    "sg:province":"VIC",
    "sg:tags":[
        "decorator",
        "painter"
    ],
    "wof:name":"Always Already 24 Hour Commercial & Residential Painting Services",
    "wof:placetype":"venue"
},
  "geometry": {"coordinates":[142.91659545900001,-38.2384490967],"type":"Point"}
}