{
  "type": "Feature",
  "properties": {
    "iso:country":"AU",
    "sg:address":"882 Ramsden Drv",
    "sg:city":"North Albury",
    "sg:classifiers":[
        {
            "category":"Organizations",
            "subcategory":"Non-profit Organization",
            "type":"Services"
        }
    ],
    "sg:phone":"+61 2 6040 2522",
    "sg:postcode":"2640",
    "sg:province":"NSW",
    "sg:tags":[
        "support",
        "disability",
        "organisation"
    ],
    "wof:name":"Twin City Laundry (Supported Employment)",
    "wof:placetype":"venue"
},
  "geometry": {"coordinates":[146.945602417,-36.0649223328],"type":"Point"}
}