{
  "type": "Feature",
  "properties": {
    "iso:country":"AU",
    "sg:address":"PO Box 62",
    "sg:city":"Mt Barker",
    "sg:classifiers":[
        {
            "category":"Professional",
            "type":"Services"
        }
    ],
    "sg:phone":"+61 1800 796 936",
    "sg:postcode":"6324",
    "sg:province":"WA",
    "sg:tags":[
        "courier"
    ],
    "wof:name":"Zen Couriers",
    "wof:placetype":"venue"
},
  "geometry": {"coordinates":[117.66284942599999,-34.6296806335],"type":"Point"}
}