{
  "type": "Feature",
  "properties": {
    "iso:country":"AU",
    "sg:address":"Unit 3/ 51 Riverside Pl",
    "sg:city":"Morningside",
    "sg:classifiers":[
        {
            "category":"Government",
            "subcategory":"Fire Station",
            "type":"Public Place"
        }
    ],
    "sg:phone":"+61 7 3395 7977",
    "sg:postcode":"4170",
    "sg:province":"QLD",
    "sg:tags":[
        "equipment",
        "protection",
        "consultant"
    ],
    "wof:name":"Statewide Fire Installations",
    "wof:placetype":"venue"
},
  "geometry": {"coordinates":[153.07882690400001,-27.4544811249],"type":"Point"}
}