{
  "type": "Feature",
  "properties": {
    "addr:full":"Steley St Howard QLD 4659",
    "addr:postcode":"4659",
    "addr:street":"St",
    "iso:country":"AU",
    "sg:address":"Steley St",
    "sg:city":"Howard",
    "sg:classifiers":[
        {
            "category":"Retail",
            "subcategory":"Event Space",
            "type":"Services"
        }
    ],
    "sg:phone":"+61 7 4129 0996",
    "sg:postcode":"4659",
    "sg:province":"QLD",
    "sg:tags":[
        "venue",
        "reception",
        "wedding"
    ],
    "wof:name":"The Burrum District Community Centre",
    "wof:placetype":"venue"
},
  "geometry": {"coordinates":[152.563705,-25.31852],"type":"Point"}
}