{
  "type": "Feature",
  "properties": {
    "addr:full":"143 Marshall St Goondiwindi QLD 4390",
    "addr:housenumber":"143",
    "addr:postcode":"4390",
    "addr:street":"Marshall St",
    "iso:country":"AU",
    "sg:address":"143 Marshall St",
    "sg:city":"Goondiwindi",
    "sg:classifiers":[
        {
            "category":"Autos & Motor Vehicles",
            "subcategory":"Auto Supplies",
            "type":"Retail Goods"
        }
    ],
    "sg:phone":"+61 7 4671 2388",
    "sg:postcode":"4390",
    "sg:province":"QLD",
    "sg:tags":[
        "part",
        "cycles",
        "accessory"
    ],
    "wof:name":"Peco Motorcycles",
    "wof:placetype":"venue"
},
  "geometry": {"coordinates":[150.30973815900001,-28.5471839905],"type":"Point"}
}