{
  "type": "Feature",
  "properties": {
    "addr:full":"Cnr New England Hwy & Glen Rd Warwick QLD 4370",
    "addr:postcode":"4370",
    "addr:street":"Cnr New England Hwy & Glen Rd",
    "iso:country":"AU",
    "sg:address":"Cnr New England Hwy & Glen Rd",
    "sg:city":"Warwick",
    "sg:classifiers":[
        {
            "category":"Travel",
            "subcategory":"Hotels & Motels",
            "type":"Entertainment"
        }
    ],
    "sg:phone":"+61 7 4661 5588",
    "sg:postcode":"4370",
    "sg:province":"QLD",
    "wof:name":"McNevins Gunyah Motel",
    "wof:placetype":"venue"
},
  "geometry": {"coordinates":[152.01889038100001,-28.2258205414],"type":"Point"}
}