{
  "type": "Feature",
  "properties": {
    "iso:country":"AU",
    "sg:address":"565 Baxter-Tooradin Rd",
    "sg:city":"Pearcedale",
    "sg:classifiers":[
        {
            "category":"Farming",
            "subcategory":"Nursery",
            "type":"Manufacturing & Wholesale Goods"
        }
    ],
    "sg:phone":"+61 3 5978 6421",
    "sg:postcode":"3912",
    "sg:province":"VIC",
    "wof:name":"Shones Nursery",
    "wof:placetype":"venue"
},
  "geometry": {"coordinates":[145.21246337900001,-38.1999931335],"type":"Point"}
}