{
  "type": "Feature",
  "properties": {
    "addr:full":"Level 1/ Knox Towerpoint 2 B Capital City Blv Wantirna South VIC 3152",
    "addr:housenumber":"/;2 b",
    "addr:postcode":"3152",
    "addr:street":"Towerpoint;City Blv",
    "iso:country":"AU",
    "sg:address":"Level 1/ Knox Towerpoint 2",
    "sg:city":"B Capital City Blv Wantirna South",
    "sg:classifiers":[
        {
            "category":"Education",
            "subcategory":"Special Training",
            "type":"Public Place"
        }
    ],
    "sg:phone":"+61 3 9800 0455",
    "sg:postcode":"3152",
    "sg:province":"VIC",
    "sg:tags":[
        "development"
    ],
    "wof:name":"Key Solutions-Apprenticeships Melbourne",
    "wof:placetype":"venue"
},
  "geometry": {"coordinates":[145.24417114299999,-37.8713264465],"type":"Point"}
}