{
  "type": "Feature",
  "properties": {
    "addr:full":"122 Charters Towers Rd Hermit Park QLD 4812",
    "addr:housenumber":"122",
    "addr:postcode":"4812",
    "addr:street":"Charters Towers Rd",
    "iso:country":"AU",
    "sg:address":"122 Charters Towers Rd",
    "sg:city":"Hermit Park",
    "sg:classifiers":[
        {
            "category":"Utilities",
            "subcategory":"Telephone",
            "type":"Services"
        }
    ],
    "sg:phone":"+61 7 4724 2799",
    "sg:postcode":"4812",
    "sg:province":"QLD",
    "sg:tags":[
        "equipment",
        "system"
    ],
    "wof:name":"North Queensland Telecom",
    "wof:placetype":"venue"
},
  "geometry": {"coordinates":[146.800095,-19.277212],"type":"Point"}
}