{
  "type": "Feature",
  "properties": {
    "addr:full":"1 Point St Fremantle WA 6160",
    "addr:housenumber":"1",
    "addr:postcode":"6160",
    "addr:street":"Point St",
    "iso:country":"AU",
    "sg:address":"1 Point St",
    "sg:city":"Fremantle",
    "sg:classifiers":[
        {
            "category":"Health Services",
            "subcategory":"Health Practitioner",
            "type":"Services"
        }
    ],
    "sg:phone":"+61 8 9430 8867",
    "sg:postcode":"6160",
    "sg:province":"WA",
    "sg:tags":[
        "acupuncture"
    ],
    "wof:name":"Michetti Sono",
    "wof:placetype":"venue"
},
  "geometry": {"coordinates":[115.748047,-32.051636],"type":"Point"}
}