{
  "type": "Feature",
  "properties": {
    "addr:full":"58 Benalla Rd (Cnr Watson St) Shepparton VIC 3630",
    "addr:housenumber":"58",
    "addr:postcode":"3630",
    "addr:street":"Benalla Rd Cnr Watson St",
    "iso:country":"AU",
    "sg:address":"58 Benalla Rd",
    "sg:city":"(Cnr Watson St) Shepparton",
    "sg:classifiers":[
        {
            "category":"Retail",
            "subcategory":"Repair Shop",
            "type":"Services"
        }
    ],
    "sg:phone":"+61 3 5821 9333",
    "sg:postcode":"3630",
    "sg:province":"VIC",
    "sg:tags":[
        "windscreen"
    ],
    "wof:name":"O&#039;Brien",
    "wof:placetype":"venue"
},
  "geometry": {"coordinates":[145.41914367699999,-36.3850631714],"type":"Point"}
}