{
  "type": "Feature",
  "properties": {
    "addr:full":"13 Mount Barker Rd Mt Barker SA 5251",
    "addr:housenumber":"13",
    "addr:postcode":"5251",
    "addr:street":"Mount Barker Rd",
    "iso:country":"AU",
    "sg:address":"13 Mount Barker Rd",
    "sg:city":"Mt Barker",
    "sg:classifiers":[
        {
            "category":"Home & Garden",
            "subcategory":"Carpets & Floor Coverings",
            "type":"Retail Goods"
        }
    ],
    "sg:phone":"+61 8 8391 2365",
    "sg:postcode":"5251",
    "sg:province":"SA",
    "sg:tags":[
        "mattress"
    ],
    "wof:name":"Dreamland Bedding Specialists",
    "wof:placetype":"venue"
},
  "geometry": {"coordinates":[138.84808349599999,-35.0535087585],"type":"Point"}
}