{
  "type": "Feature",
  "properties": {
    "addr:full":"1102 Botany Rd Botany NSW 2019",
    "addr:housenumber":"1102",
    "addr:postcode":"2019",
    "addr:street":"Botany Rd",
    "iso:country":"AU",
    "sg:address":"1102 Botany Rd",
    "sg:city":"Botany",
    "sg:classifiers":[
        {
            "category":"Food & Beverages",
            "subcategory":"Liquor & Beverages",
            "type":"Retail Goods"
        }
    ],
    "sg:phone":"+61 2 9666 5555",
    "sg:postcode":"2019",
    "sg:province":"NSW",
    "sg:tags":[
        "store"
    ],
    "wof:name":"Endeavour Hotel",
    "wof:placetype":"venue"
},
  "geometry": {"coordinates":[151.19595336899999,-33.9440002441],"type":"Point"}
}