{
  "type": "Feature",
  "properties": {
    "addr:full":"1095 Pittwater Rd Collaroy NSW 2097",
    "addr:housenumber":"1095",
    "addr:postcode":"2097",
    "addr:street":"Pittwater Rd",
    "iso:country":"AU",
    "sg:address":"1095 Pittwater Rd",
    "sg:city":"Collaroy",
    "sg:classifiers":[
        {
            "category":"Restaurant",
            "type":"Food & Drink"
        }
    ],
    "sg:phone":"+61 2 9972 9696",
    "sg:postcode":"2097",
    "sg:province":"NSW",
    "wof:name":"Alimento Pizza Cafe",
    "wof:placetype":"venue"
},
  "geometry": {"coordinates":[151.301391602,-33.733001709],"type":"Point"}
}