{
  "type": "Feature",
  "properties": {
    "iso:country":"AU",
    "sg:address":"35 Mayne St",
    "sg:city":"Gulgong",
    "sg:classifiers":[
        {
            "category":"Building & Trades",
            "subcategory":"Plumbing",
            "type":"Services"
        }
    ],
    "sg:phone":"+61 2 6374 1249",
    "sg:postcode":"2852",
    "sg:province":"NSW",
    "sg:tags":[
        "plumber",
        "gasfitters"
    ],
    "wof:name":"Waite R J",
    "wof:placetype":"venue"
},
  "geometry": {"coordinates":[149.53247099999999,-32.362705],"type":"Point"}
}