{
  "type": "Feature",
  "properties": {
    "addr:full":"3 Burrhill Crt Berwick VIC 3806",
    "addr:housenumber":"3",
    "addr:postcode":"3806",
    "addr:street":"Burrhill Crt",
    "iso:country":"AU",
    "sg:address":"3 Burrhill Crt",
    "sg:city":"Berwick",
    "sg:classifiers":[
        {
            "category":"Building & Trades",
            "subcategory":"Construction",
            "type":"Services"
        }
    ],
    "sg:phone":"+61 3 9796 1848",
    "sg:postcode":"3806",
    "sg:province":"VIC",
    "sg:tags":[
        "contractor"
    ],
    "wof:name":"Wilde J A C Builders Pty Ltd",
    "wof:placetype":"venue"
},
  "geometry": {"coordinates":[145.35418701200001,-38.0289001465],"type":"Point"}
}