{
  "type": "Feature",
  "properties": {
    "addr:full":"Unit 2, 22a Tone Road Wangaratta VIC 3677",
    "addr:housenumber":"22a",
    "addr:postcode":"3677",
    "addr:street":"Tone Road",
    "iso:country":"AU",
    "sg:address":"Unit 2, 22a Tone Road",
    "sg:city":"Wangaratta",
    "sg:classifiers":[
        {
            "category":"Shopping",
            "type":"Retail Goods"
        }
    ],
    "sg:phone":"+61 3 5722 3111",
    "sg:postcode":"3677",
    "sg:province":"VIC",
    "sg:tags":[
        "equipment",
        "safety",
        "accessory"
    ],
    "wof:name":"North East Bearings",
    "wof:placetype":"venue"
},
  "geometry": {"coordinates":[146.31121826200001,-36.3599128723],"type":"Point"}
}