{
  "type": "Feature",
  "properties": {
    "iso:country":"AU",
    "sg:address":"6 Royston St",
    "sg:city":"View Bank",
    "sg:classifiers":[
        {
            "category":"Building & Trades",
            "subcategory":"Plumbing",
            "type":"Services"
        }
    ],
    "sg:phone":"+61 3 9459 2015",
    "sg:postcode":"3084",
    "sg:province":"VIC",
    "sg:tags":[
        "plumber",
        "gasfitters"
    ],
    "wof:name":"Hamilton Roy J",
    "wof:placetype":"venue"
},
  "geometry": {"coordinates":[145.09175109899999,-37.7407836914],"type":"Point"}
}