{
  "type": "Feature",
  "properties": {
    "addr:full":"6 Beach Rd Surfers Paradise QLD 4217",
    "addr:housenumber":"6",
    "addr:postcode":"4217",
    "addr:street":"Beach Rd",
    "iso:country":"AU",
    "sg:address":"6 Beach Rd",
    "sg:city":"Surfers Paradise",
    "sg:classifiers":[
        {
            "category":"Travel",
            "subcategory":"Hotels & Motels",
            "type":"Entertainment"
        }
    ],
    "sg:phone":"+61 7 5538 8000",
    "sg:postcode":"4217",
    "sg:province":"QLD",
    "sg:tags":[
        "accommodation"
    ],
    "wof:name":"Islander Resort Hotel",
    "wof:placetype":"venue"
},
  "geometry": {"coordinates":[153.42759704599999,-28.0027198792],"type":"Point"}
}