{
  "type": "Feature",
  "properties": {
    "addr:full":"Shop 4 Tudor Arcade 205 Jull St Armadale WA 6112",
    "addr:housenumber":"shop 4;205",
    "addr:postcode":"6112",
    "addr:street":"Tudor Arcade;St",
    "iso:country":"AU",
    "sg:address":"Shop 4 Tudor Arcade 205 Jull St",
    "sg:city":"Armadale",
    "sg:classifiers":[
        {
            "category":"Professional",
            "subcategory":"Accounting & Tax Preparation",
            "type":"Services"
        }
    ],
    "sg:phone":"+61 8 9497 4187",
    "sg:postcode":"6112",
    "sg:province":"WA",
    "sg:tags":[
        "consultant",
        "taxation"
    ],
    "wof:name":"ITP The Income Tax Professionals",
    "wof:placetype":"venue"
},
  "geometry": {"coordinates":[116.020568848,-32.150226593],"type":"Point"}
}