{
  "type": "Feature",
  "properties": {
    "addr:full":"16 Beecher St Tinonee NSW 2430",
    "addr:housenumber":"16",
    "addr:postcode":"2430",
    "addr:street":"Beecher St",
    "iso:country":"AU",
    "sg:address":"16 Beecher St",
    "sg:city":"Tinonee",
    "sg:classifiers":[
        {
            "category":"Social Services",
            "subcategory":"Child Care",
            "type":"Services"
        }
    ],
    "sg:phone":"+61 2 6553 1424",
    "sg:postcode":"2430",
    "sg:province":"NSW",
    "wof:name":"Earth Angels Child Care Centre",
    "wof:placetype":"venue"
},
  "geometry": {"coordinates":[152.41181900000001,-31.93944],"type":"Point"}
}