{
  "type": "Feature",
  "properties": {
    "addr:full":"44 Pearson St Wagga Wagga NSW 2650",
    "addr:housenumber":"44",
    "addr:postcode":"2650",
    "addr:street":"Pearson St",
    "iso:country":"AU",
    "sg:address":"44 Pearson St",
    "sg:city":"Wagga Wagga",
    "sg:classifiers":[
        {
            "category":"Retail",
            "subcategory":"Auto Repair",
            "type":"Services"
        }
    ],
    "sg:phone":"+61 2 6925 3188",
    "sg:postcode":"2650",
    "sg:province":"NSW",
    "sg:tags":[
        "repairer",
        "motor",
        "engineer"
    ],
    "wof:name":"Ultra Tune",
    "wof:placetype":"venue"
},
  "geometry": {"coordinates":[147.34486389200001,-35.1177482605],"type":"Point"}
}