{
  "type": "Feature",
  "properties": {
    "iso:country":"AU",
    "sg:address":"78 O.G. Rd",
    "sg:city":"Klemzig",
    "sg:classifiers":[
        {
            "category":"Health Services",
            "subcategory":"Doctor",
            "type":"Services"
        }
    ],
    "sg:phone":"+61 8 8369 0444",
    "sg:postcode":"5087",
    "sg:province":"SA",
    "sg:tags":[
        "medical",
        "practitioner"
    ],
    "wof:name":"Cameron Peter Dr",
    "wof:placetype":"venue"
},
  "geometry": {"coordinates":[138.63667297399999,-34.8815956116],"type":"Point"}
}