{
  "type": "Feature",
  "properties": {
    "addr:full":"Shp 8/ Niddrie Central Shopng Cntr Essendon North VIC 3041",
    "addr:housenumber":"/ niddrie",
    "addr:postcode":"3041",
    "iso:country":"AU",
    "sg:address":"Shp 8/ Niddrie Central Shopng Cntr",
    "sg:city":"Essendon North",
    "sg:classifiers":[
        {
            "category":"Deli",
            "type":"Food & Drink"
        }
    ],
    "sg:phone":"+61 3 9379 0299",
    "sg:postcode":"3041",
    "sg:province":"VIC",
    "sg:tags":[
        "delicatessen"
    ],
    "wof:name":"Aldente Deli",
    "wof:placetype":"venue"
},
  "geometry": {"coordinates":[144.89601135300001,-37.7387313843],"type":"Point"}
}