{
  "type": "Feature",
  "properties": {
    "iso:country":"AU",
    "sg:address":"32 Bayswater Rd",
    "sg:city":"Kings Cross",
    "sg:classifiers":[
        {
            "category":"Restaurant",
            "type":"Food & Drink"
        }
    ],
    "sg:phone":"+61 2 9357 2177",
    "sg:postcode":"2011",
    "sg:province":"NSW",
    "wof:name":"Bayswater Brasserie",
    "wof:placetype":"venue"
},
  "geometry": {"coordinates":[151.22410583499999,-33.8749389648],"type":"Point"}
}