{
  "type": "Feature",
  "properties": {
    "iso:country":"AU",
    "sg:address":"176 Walker St",
    "sg:city":"North Sydney",
    "sg:classifiers":[
        {
            "category":"Education",
            "subcategory":"School",
            "type":"Public Place"
        }
    ],
    "sg:phone":"+61 2 9955 3000",
    "sg:postcode":"2060",
    "sg:province":"NSW",
    "sg:tags":[
        "girl"
    ],
    "wof:name":"Wenona School Ltd",
    "wof:placetype":"venue"
},
  "geometry": {"coordinates":[151.20956420900001,-33.8345222473],"type":"Point"}
}