{
  "type": "Feature",
  "properties": {
    "iso:country":"AU",
    "sg:address":"Shp 79 Warringah Mall Shopng Cntr, Condermine St",
    "sg:city":"Warringah Mall",
    "sg:classifiers":[
        {
            "category":"Shopping",
            "subcategory":"Mobile Phones",
            "type":"Retail Goods"
        }
    ],
    "sg:phone":"+61 2 9905 9344",
    "sg:postcode":"2100",
    "sg:province":"NSW",
    "sg:tags":[
        "telephone",
        "accessory"
    ],
    "wof:name":"Optus World",
    "wof:placetype":"venue"
},
  "geometry": {"coordinates":[151.24876403799999,-33.752117157],"type":"Point"}
}