{
  "type": "Feature",
  "properties": {
    "addr:full":"1072 Raglan Pde Warrnambool VIC 3280",
    "addr:housenumber":"1072",
    "addr:postcode":"3280",
    "addr:street":"Raglan Pde",
    "iso:country":"AU",
    "sg:address":"1072 Raglan Pde",
    "sg:city":"Warrnambool",
    "sg:classifiers":[
        {
            "category":"Wholesale",
            "subcategory":"Electrical",
            "type":"Manufacturing & Wholesale Goods"
        }
    ],
    "sg:phone":"+61 3 5560 5677",
    "sg:postcode":"3280",
    "sg:province":"VIC",
    "sg:tags":[
        "wholesaler"
    ],
    "wof:name":"Middendorp Electric Co Pty Ltd",
    "wof:placetype":"venue"
},
  "geometry": {"coordinates":[142.45758056599999,-38.3627243042],"type":"Point"}
}