{
  "type": "Feature",
  "properties": {
    "iso:country":"AU",
    "sg:address":"Cnr John & North Sts",
    "sg:city":"Maryborough",
    "sg:classifiers":[
        {
            "category":"Fast Food",
            "type":"Food & Drink"
        }
    ],
    "sg:phone":"+61 7 4123 0011",
    "sg:postcode":"4650",
    "sg:province":"QLD",
    "sg:tags":[
        "away",
        "take"
    ],
    "wof:name":"Golden Chicken",
    "wof:placetype":"venue"
},
  "geometry": {"coordinates":[152.724075,-25.536734],"type":"Point"}
}