{
  "type": "Feature",
  "properties": {
    "addr:full":"3/ 6 Fern Pl Byron Bay NSW 2481",
    "addr:housenumber":"/ 6",
    "addr:postcode":"2481",
    "addr:street":"Fern Pl",
    "iso:country":"AU",
    "sg:address":"3/ 6 Fern Pl",
    "sg:city":"Byron Bay",
    "sg:classifiers":[
        {
            "category":"Personal",
            "subcategory":"Tanning Parlor",
            "type":"Services"
        }
    ],
    "sg:phone":"+61 432 533 680",
    "sg:postcode":"2481",
    "sg:province":"NSW",
    "sg:tags":[
        "solarium"
    ],
    "wof:name":"Bronzed Byron Babes",
    "wof:placetype":"venue"
},
  "geometry": {"coordinates":[153.58700561500001,-28.6356277466],"type":"Point"}
}