{
  "type": "Feature",
  "properties": {
    "iso:country":"AU",
    "sg:address":"Level 1/ 70 Macquarie St",
    "sg:city":"Parramatta",
    "sg:classifiers":[
        {
            "category":"Banks & Credit Unions",
            "subcategory":"Investment Brokerage",
            "type":"Services"
        }
    ],
    "sg:phone":"+61 2 9683 5059",
    "sg:postcode":"2150",
    "sg:province":"NSW",
    "sg:tags":[
        "management",
        "property"
    ],
    "wof:name":"Moxhams Real Estate Pty Ltd",
    "wof:placetype":"venue"
},
  "geometry": {"coordinates":[151.06219482399999,-33.9103012085],"type":"Point"}
}