{
  "type": "Feature",
  "properties": {
    "addr:full":"40-42 Cambro Rd Clayton North VIC 3168",
    "addr:housenumber":"40-42",
    "addr:postcode":"3168",
    "addr:street":"Cambro Rd",
    "iso:country":"AU",
    "sg:address":"40-42 Cambro Rd",
    "sg:city":"Clayton North",
    "sg:classifiers":[
        {
            "category":"Wholesale",
            "subcategory":"Home Furnishings",
            "type":"Manufacturing & Wholesale Goods"
        }
    ],
    "sg:phone":"+61 3 9543 7800",
    "sg:postcode":"3168",
    "sg:province":"VIC",
    "sg:tags":[
        "wholesaler",
        "curtain",
        "mfrs"
    ],
    "wof:name":"Fabric Conversions",
    "wof:placetype":"venue"
},
  "geometry": {"coordinates":[145.14186096200001,-37.9206619263],"type":"Point"}
}