{
  "type": "Feature",
  "properties": {
    "iso:country":"AU",
    "sg:address":"107 Edward St",
    "sg:city":"Ayr",
    "sg:classifiers":[
        {
            "category":"Fast Food",
            "type":"Food & Drink"
        }
    ],
    "sg:phone":"+61 7 4783 2363",
    "sg:postcode":"4807",
    "sg:province":"QLD",
    "sg:tags":[
        "away",
        "take"
    ],
    "wof:name":"Scotch Corner",
    "wof:placetype":"venue"
},
  "geometry": {"coordinates":[147.40275573700001,-19.5713615417],"type":"Point"}
}