{
  "type": "Feature",
  "properties": {
    "addr:full":"5 Tennyson St Hamilton VIC 3300",
    "addr:housenumber":"5",
    "addr:postcode":"3300",
    "addr:street":"Tennyson St",
    "iso:country":"AU",
    "sg:address":"5 Tennyson St",
    "sg:city":"Hamilton",
    "sg:classifiers":[
        {
            "category":"Wholesale",
            "subcategory":"Scrap",
            "type":"Manufacturing & Wholesale Goods"
        }
    ],
    "sg:phone":"+61 3 5572 3726",
    "sg:postcode":"3300",
    "sg:province":"VIC",
    "sg:tags":[
        "merchant",
        "metal"
    ],
    "wof:name":"Linnets Metals",
    "wof:placetype":"venue"
},
  "geometry": {"coordinates":[142.0128479,-37.7396888733],"type":"Point"}
}