{
  "type": "Feature",
  "properties": {
    "iso:country":"AU",
    "sg:address":"42 Wattle Ave",
    "sg:city":"Carramar",
    "sg:classifiers":[
        {
            "category":"Utilities",
            "subcategory":"Electric",
            "type":"Services"
        }
    ],
    "sg:phone":"+61 419 443 124",
    "sg:postcode":"2163",
    "sg:province":"NSW",
    "sg:tags":[
        "electrical",
        "contractor"
    ],
    "wof:name":"Beaverwood Electric",
    "wof:placetype":"venue"
},
  "geometry": {"coordinates":[150.96934509299999,-33.8832015991],"type":"Point"}
}