{
  "type": "Feature",
  "properties": {
    "iso:country":"AU",
    "sg:address":"33 Boonar St",
    "sg:city":"Hawks Nest",
    "sg:classifiers":[
        {
            "category":"Food & Beverages",
            "subcategory":"Supermarket",
            "type":"Retail Goods"
        }
    ],
    "sg:phone":"+61 2 4997 0377",
    "sg:postcode":"2324",
    "sg:province":"NSW",
    "sg:tags":[
        "grocery",
        "store"
    ],
    "wof:name":"Hawks Nest Supermarket",
    "wof:placetype":"venue"
},
  "geometry": {"coordinates":[152.17510986299999,-32.6722106934],"type":"Point"}
}