{
  "type": "Feature",
  "properties": {
    "addr:full":"Prahran Central, Commercial Rd Prahran VIC 3181",
    "addr:postcode":"3181",
    "addr:street":"Commercial Rd",
    "iso:country":"AU",
    "sg:address":"Prahran Central, Commercial Rd",
    "sg:city":"Prahran",
    "sg:classifiers":[
        {
            "category":"Insurance",
            "subcategory":"Health Insurance",
            "type":"Services"
        }
    ],
    "sg:phone":"+61 13 23 31",
    "sg:postcode":"3181",
    "sg:province":"VIC",
    "wof:name":"Medibank Private",
    "wof:placetype":"venue"
},
  "geometry": {"coordinates":[144.99400329599999,-37.8468322754],"type":"Point"}
}