{
  "type": "Feature",
  "properties": {
    "addr:full":"51 Grand Pde Parrearra QLD 4575",
    "addr:housenumber":"51",
    "addr:postcode":"4575",
    "addr:street":"Grand Pde",
    "iso:country":"AU",
    "sg:address":"51 Grand Pde",
    "sg:city":"Parrearra",
    "sg:classifiers":[
        {
            "category":"Banks & Credit Unions",
            "subcategory":"Investment Brokerage",
            "type":"Services"
        }
    ],
    "sg:phone":"+61 7 5493 4444",
    "sg:postcode":"4575",
    "sg:province":"QLD",
    "sg:tags":[
        "management",
        "property"
    ],
    "wof:name":"Island Life Property Management & Sales",
    "wof:placetype":"venue"
},
  "geometry": {"coordinates":[153.124146,-26.720001],"type":"Point"}
}