{
  "type": "Feature",
  "properties": {
    "addr:full":"40 Camuglia St Garbutt QLD 4814",
    "addr:housenumber":"40",
    "addr:postcode":"4814",
    "addr:street":"Camuglia St",
    "iso:country":"AU",
    "sg:address":"40 Camuglia St",
    "sg:city":"Garbutt",
    "sg:classifiers":[
        {
            "category":"Mining & Drilling",
            "type":"Manufacturing & Wholesale Goods"
        }
    ],
    "sg:phone":"+61 7 4774 7088",
    "sg:postcode":"4814",
    "sg:province":"QLD",
    "sg:tags":[
        "boring",
        "contractor"
    ],
    "wof:name":"Straitline Australia Pty Ltd",
    "wof:placetype":"venue"
},
  "geometry": {"coordinates":[146.74934400000001,-19.269402],"type":"Point"}
}