{
  "type": "Feature",
  "properties": {
    "addr:full":"7 Snowgum Drv Kilsyth VIC 3137",
    "addr:housenumber":"7",
    "addr:postcode":"3137",
    "addr:street":"Snowgum Drv",
    "iso:country":"AU",
    "sg:address":"7 Snowgum Drv",
    "sg:city":"Kilsyth",
    "sg:classifiers":[
        {
            "category":"Personal",
            "type":"Services"
        }
    ],
    "sg:phone":"+61 3 9445 9466",
    "sg:postcode":"3137",
    "sg:province":"VIC",
    "sg:tags":[
        "reducing",
        "treatment",
        "weight"
    ],
    "wof:name":"Herbalife Australasia",
    "wof:placetype":"venue"
},
  "geometry": {"coordinates":[145.31671142600001,-37.8226203918],"type":"Point"}
}