{
  "type": "Feature",
  "properties": {
    "addr:full":"PO Box 276 Tuart Hill WA 6938",
    "addr:postcode":"6938",
    "iso:country":"AU",
    "sg:address":"PO Box 276",
    "sg:city":"Tuart Hill",
    "sg:classifiers":[
        {
            "category":"Government",
            "subcategory":"Customs House",
            "type":"Public Place"
        }
    ],
    "sg:phone":"+61 8 9349 9874",
    "sg:postcode":"6938",
    "sg:province":"WA",
    "sg:tags":[
        "title",
        "management",
        "stratum"
    ],
    "wof:name":"Strata Personal Management",
    "wof:placetype":"venue"
},
  "geometry": {"coordinates":[115.836967468,-31.9022293091],"type":"Point"}
}