{
  "type": "Feature",
  "properties": {
    "addr:full":"55-59 Westwood Drv Deer Park VIC 3023",
    "addr:housenumber":"55-59",
    "addr:postcode":"3023",
    "addr:street":"Westwood Drv",
    "iso:country":"AU",
    "sg:address":"55-59 Westwood Drv",
    "sg:city":"Deer Park",
    "sg:classifiers":[
        {
            "category":"Professional",
            "subcategory":"Engineering",
            "type":"Services"
        }
    ],
    "sg:phone":"+61 3 9360 4977",
    "sg:postcode":"3023",
    "sg:province":"VIC",
    "sg:tags":[
        "consulting",
        "engineer"
    ],
    "wof:name":"Leigh Findlay & Associates",
    "wof:placetype":"venue"
},
  "geometry": {"coordinates":[144.75524899999999,-37.758987],"type":"Point"}
}