{
  "type": "Feature",
  "properties": {
    "addr:full":"6 Woodsiana St Robertson QLD 4109",
    "addr:housenumber":"6",
    "addr:postcode":"4109",
    "addr:street":"Woodsiana St",
    "iso:country":"AU",
    "sg:address":"6 Woodsiana St",
    "sg:city":"Robertson",
    "sg:classifiers":[
        {
            "category":"Health Services",
            "subcategory":"Doctor",
            "type":"Services"
        }
    ],
    "sg:phone":"+61 7 3323 3888",
    "sg:postcode":"4109",
    "sg:province":"QLD",
    "sg:tags":[
        "medical",
        "practitioner"
    ],
    "wof:name":"Sim Lo Tan Dr",
    "wof:placetype":"venue"
},
  "geometry": {"coordinates":[153.06275939899999,-27.5783214569],"type":"Point"}
}