{
  "type": "Feature",
  "properties": {
    "addr:full":"Airport Road, Weipa Airport Weipa QLD 4874",
    "addr:postcode":"4874",
    "addr:street":"Airport Road",
    "iso:country":"AU",
    "sg:address":"Airport Road, Weipa Airport",
    "sg:city":"Weipa",
    "sg:classifiers":[
        {
            "category":"Retail",
            "subcategory":"Auto Rental",
            "type":"Services"
        }
    ],
    "sg:phone":"+61 7 4069 7311",
    "sg:postcode":"4874",
    "sg:province":"QLD",
    "sg:tags":[
        "car",
        "hire",
        "minibus"
    ],
    "wof:name":"Weipa Rent-A-Car",
    "wof:placetype":"venue"
},
  "geometry": {"coordinates":[141.87167358400001,-12.6334495544],"type":"Point"}
}