{
  "type": "Feature",
  "properties": {
    "iso:country":"AU",
    "sg:address":"972 Range Rd",
    "sg:city":"Albury",
    "sg:classifiers":[
        {
            "category":"Government",
            "subcategory":"Post Office",
            "type":"Public Place"
        }
    ],
    "sg:phone":"+61 2 6025 3767",
    "sg:postcode":"2640",
    "sg:province":"NSW",
    "sg:tags":[
        "yoga"
    ],
    "wof:name":"Robyn's School Of Yoga",
    "wof:placetype":"venue"
},
  "geometry": {"coordinates":[146.91038513199999,-36.0557556152],"type":"Point"}
}