{
  "type": "Feature",
  "properties": {
    "iso:country":"AU",
    "sg:address":"Factory Showroom Unit 5/ 3 Pullman Pl",
    "sg:city":"Emu Plains",
    "sg:classifiers":[
        {
            "category":"Retail",
            "subcategory":"Repair Shop",
            "type":"Services"
        }
    ],
    "sg:phone":"+61 2 4735 4697",
    "sg:postcode":"2750",
    "sg:province":"NSW",
    "sg:tags":[
        "repairing",
        "piano",
        "tuning"
    ],
    "wof:name":"David Mansfield",
    "wof:placetype":"venue"
},
  "geometry": {"coordinates":[150.655197144,-33.7460899353],"type":"Point"}
}