{
  "type": "Feature",
  "properties": {
    "addr:full":"93 Princes Hwy Albion Park Rail NSW 2527",
    "addr:housenumber":"93",
    "addr:postcode":"2527",
    "addr:street":"Princes Hwy Albion",
    "iso:country":"AU",
    "sg:address":"93 Princes Hwy",
    "sg:city":"Albion Park Rail",
    "sg:classifiers":[
        {
            "category":"Autos & Motor Vehicles",
            "subcategory":"Automobile Sales",
            "type":"Retail Goods"
        }
    ],
    "sg:phone":"+61 2 4257 2800",
    "sg:postcode":"2527",
    "sg:province":"NSW",
    "sg:tags":[
        "car",
        "new"
    ],
    "wof:name":"Airport Hyundai",
    "wof:placetype":"venue"
},
  "geometry": {"coordinates":[150.80816650400001,-34.5687141418],"type":"Point"}
}