{
  "type": "Feature",
  "properties": {
    "addr:full":"41 Binnie St Bordertown SA 5268",
    "addr:housenumber":"41",
    "addr:postcode":"5268",
    "addr:street":"Binnie St",
    "iso:country":"AU",
    "sg:address":"41 Binnie St",
    "sg:city":"Bordertown",
    "sg:classifiers":[
        {
            "category":"Wholesale",
            "subcategory":"Machinery & Supplies",
            "type":"Manufacturing & Wholesale Goods"
        }
    ],
    "sg:phone":"+61 8 8752 1755",
    "sg:postcode":"5268",
    "sg:province":"SA",
    "sg:tags":[
        "agricultural"
    ],
    "wof:name":"Wickham Flower & Co Pty Ltd",
    "wof:placetype":"venue"
},
  "geometry": {"coordinates":[140.772614,-36.310154],"type":"Point"}
}