{
  "type": "Feature",
  "properties": {
    "addr:full":"23 Sheldon Rd Chadwick WA 6450",
    "addr:housenumber":"23",
    "addr:postcode":"6450",
    "addr:street":"Sheldon Rd",
    "iso:country":"AU",
    "sg:address":"23 Sheldon Rd",
    "sg:city":"Chadwick",
    "sg:classifiers":[
        {
            "category":"Fast Food",
            "type":"Food & Drink"
        }
    ],
    "sg:phone":"+61 8 9071 2604",
    "sg:postcode":"6450",
    "sg:province":"WA",
    "sg:tags":[
        "away",
        "take"
    ],
    "wof:name":"Esperance Lunch Box",
    "wof:placetype":"venue"
},
  "geometry": {"coordinates":[121.88739776600001,-33.8379516602],"type":"Point"}
}