{
  "type": "Feature",
  "properties": {
    "iso:country":"AU",
    "sg:address":"Lvl 1/ 441 South Rd",
    "sg:city":"Moorabbin",
    "sg:classifiers":[
        {
            "category":"Structure",
            "subcategory":"Office Building",
            "type":"Public Place"
        }
    ],
    "sg:phone":"+61 3 9556 5400",
    "sg:postcode":"3189",
    "sg:province":"VIC",
    "sg:tags":[
        "serviced"
    ],
    "sg:website":"http://www.baysidebc.com.au",
    "wof:name":"Bayside Business Centre",
    "wof:placetype":"venue"
},
  "geometry": {"coordinates":[145.036865234,-37.9330787659],"type":"Point"}
}