{
  "type": "Feature",
  "properties": {
    "iso:country":"AU",
    "sg:address":"247 Jasper Rd",
    "sg:city":"McKinnon",
    "sg:classifiers":[
        {
            "category":"Wholesale",
            "subcategory":"Electrical",
            "type":"Manufacturing & Wholesale Goods"
        }
    ],
    "sg:phone":"+61 3 9563 9299",
    "sg:postcode":"3204",
    "sg:province":"VIC",
    "sg:tags":[
        "wholesaler"
    ],
    "wof:name":"AWM Electrical",
    "wof:placetype":"venue"
},
  "geometry": {"coordinates":[145.042587,-37.912292],"type":"Point"}
}