{
  "type": "Feature",
  "properties": {
    "iso:country":"AU",
    "sg:address":"339 Windsor Rd",
    "sg:city":"Vineyard",
    "sg:classifiers":[
        {
            "category":"Professional",
            "type":"Services"
        }
    ],
    "sg:phone":"+61 2 4577 5944",
    "sg:postcode":"2765",
    "sg:province":"NSW",
    "sg:tags":[
        "transport"
    ],
    "wof:name":"Kimbo Transport Pty Ltd",
    "wof:placetype":"venue"
},
  "geometry": {"coordinates":[150.86573791500001,-33.6516494751],"type":"Point"}
}