{
  "type": "Feature",
  "properties": {
    "addr:full":"1002 Anzac Ave Petrie QLD 4502",
    "addr:housenumber":"1002",
    "addr:postcode":"4502",
    "addr:street":"Anzac Ave",
    "iso:country":"AU",
    "sg:address":"1002 Anzac Ave",
    "sg:city":"Petrie",
    "sg:classifiers":[
        {
            "category":"Health Services",
            "subcategory":"Dentist",
            "type":"Services"
        }
    ],
    "sg:phone":"+61 7 3285 7256",
    "sg:postcode":"4502",
    "sg:province":"QLD",
    "sg:website":"http://www.indental.com.au",
    "wof:name":"Indental",
    "wof:placetype":"venue"
},
  "geometry": {"coordinates":[152.98077392600001,-27.2670707703],"type":"Point"}
}