{
  "type": "Feature",
  "properties": {
    "addr:full":"18 Joseph St Woonona NSW 2517",
    "addr:housenumber":"18",
    "addr:postcode":"2517",
    "addr:street":"Joseph St",
    "iso:country":"AU",
    "sg:address":"18 Joseph St",
    "sg:city":"Woonona",
    "sg:classifiers":[
        {
            "category":"Building & Trades",
            "subcategory":"Construction",
            "type":"Services"
        }
    ],
    "sg:phone":"+61 2 4284 2249",
    "sg:postcode":"2517",
    "sg:province":"NSW",
    "sg:tags":[
        "brick",
        "paving"
    ],
    "wof:name":"Simon Szwec T/A S & U Bricklaying",
    "wof:placetype":"venue"
},
  "geometry": {"coordinates":[150.898087,-34.33744],"type":"Point"}
}