{
  "type": "Feature",
  "properties": {
    "addr:full":"PO Box 8010 Rivett ACT 2611",
    "addr:postcode":"2611",
    "iso:country":"AU",
    "sg:address":"PO Box 8010",
    "sg:city":"Rivett",
    "sg:classifiers":[
        {
            "category":"Building & Trades",
            "subcategory":"Cleaning & Sanitation",
            "type":"Services"
        }
    ],
    "sg:phone":"+61 422 813 033",
    "sg:postcode":"2611",
    "sg:province":"ACT",
    "sg:tags":[
        "cleaner",
        "repairer",
        "roof"
    ],
    "wof:name":"T Wilson & Sons Roofing",
    "wof:placetype":"venue"
},
  "geometry": {"coordinates":[149.03692626899999,-35.3473396301],"type":"Point"}
}