{
  "type": "Feature",
  "properties": {
    "addr:full":"64 Haversham Ave Wheelers Hill VIC 3150",
    "addr:housenumber":"64",
    "addr:postcode":"3150",
    "addr:street":"Haversham Ave",
    "iso:country":"AU",
    "sg:address":"64 Haversham Ave",
    "sg:city":"Wheelers Hill",
    "sg:classifiers":[
        {
            "category":"Utilities",
            "subcategory":"Telephone",
            "type":"Services"
        }
    ],
    "sg:phone":"+61 3 9561 2259",
    "sg:postcode":"3150",
    "sg:province":"VIC",
    "sg:tags":[
        "installation",
        "system",
        "maintenance"
    ],
    "wof:name":"Toshiba Telephone Systems",
    "wof:placetype":"venue"
},
  "geometry": {"coordinates":[145.20245361299999,-37.9143295288],"type":"Point"}
}