{
  "type": "Feature",
  "properties": {
    "addr:full":"PO Box 287 Alstonville NSW 2477",
    "addr:postcode":"2477",
    "iso:country":"AU",
    "sg:address":"PO Box 287",
    "sg:city":"Alstonville",
    "sg:classifiers":[
        {
            "category":"Professional",
            "subcategory":"Detective & Security Services",
            "type":"Services"
        }
    ],
    "sg:phone":"+61 2 6628 7530",
    "sg:postcode":"2477",
    "sg:province":"NSW",
    "sg:tags":[
        "consultant",
        "system"
    ],
    "wof:name":"Technical Security Services",
    "wof:placetype":"venue"
},
  "geometry": {"coordinates":[153.44003295900001,-28.8416900635],"type":"Point"}
}