{
  "type": "Feature",
  "properties": {
    "addr:full":"11 Saligna Drv Tullamarine VIC 3043",
    "addr:housenumber":"11",
    "addr:postcode":"3043",
    "addr:street":"Saligna Drv",
    "iso:country":"AU",
    "sg:address":"11 Saligna Drv",
    "sg:city":"Tullamarine",
    "sg:classifiers":[
        {
            "category":"Food & Beverages",
            "subcategory":"Specialty",
            "type":"Retail Goods"
        }
    ],
    "sg:phone":"+61 3 9338 9711",
    "sg:postcode":"3043",
    "sg:province":"VIC",
    "sg:tags":[
        "delicacy"
    ],
    "wof:name":"Unique Smallgoods",
    "wof:placetype":"venue"
},
  "geometry": {"coordinates":[144.86361694300001,-37.711971283],"type":"Point"}
}