{
  "type": "Feature",
  "properties": {
    "iso:country":"AU",
    "sg:address":"1508 Brisbane Valley Hwy",
    "sg:city":"Fernvale",
    "sg:classifiers":[
        {
            "category":"Retail",
            "subcategory":"Funeral Services",
            "type":"Services"
        }
    ],
    "sg:phone":"+61 7 5426 7777",
    "sg:postcode":"4306",
    "sg:province":"QLD",
    "sg:tags":[
        "cremation"
    ],
    "wof:name":"Stitt & St George Funeral Directors",
    "wof:placetype":"venue"
},
  "geometry": {"coordinates":[152.6509552,-27.4538288116],"type":"Point"}
}