{
  "type": "Feature",
  "properties": {
    "addr:full":"Lower Ground Flr, 2 Pearl St Hurstville NSW 2220",
    "addr:housenumber":"2",
    "addr:postcode":"2220",
    "addr:street":"Pearl St",
    "iso:country":"AU",
    "sg:address":"Lower Ground Flr, 2 Pearl St",
    "sg:city":"Hurstville",
    "sg:classifiers":[
        {
            "category":"Health Services",
            "subcategory":"Health Practitioner",
            "type":"Services"
        }
    ],
    "sg:phone":"+61 2 9580 0188",
    "sg:postcode":"2220",
    "sg:province":"NSW",
    "sg:tags":[
        "physiotherapist"
    ],
    "wof:name":"St George Sports Injury Centre",
    "wof:placetype":"venue"
},
  "geometry": {"coordinates":[151.09649658199999,-33.9627304077],"type":"Point"}
}