{
  "type": "Feature",
  "properties": {
    "iso:country":"AU",
    "sg:address":"221 Concord Rd",
    "sg:city":"North Strathfield",
    "sg:classifiers":[
        {
            "category":"Health Services",
            "subcategory":"Doctor",
            "type":"Services"
        }
    ],
    "sg:phone":"+61 2 9743 1404",
    "sg:postcode":"2137",
    "sg:province":"NSW",
    "sg:tags":[
        "podiatrist"
    ],
    "wof:name":"Duncan Rhiann",
    "wof:placetype":"venue"
},
  "geometry": {"coordinates":[151.091888428,-33.8566551208],"type":"Point"}
}