{
  "type": "Feature",
  "properties": {
    "iso:country":"AU",
    "sg:address":"Cnr Moggill & Station Rds",
    "sg:city":"Indooroopilly",
    "sg:classifiers":[
        {
            "category":"Health Services",
            "subcategory":"Health Practitioner",
            "type":"Services"
        }
    ],
    "sg:phone":"+61 7 3878 9011",
    "sg:postcode":"4068",
    "sg:province":"QLD",
    "sg:tags":[
        "physiotherapist"
    ],
    "wof:name":"Wunsch Rebecca",
    "wof:placetype":"venue"
},
  "geometry": {"coordinates":[152.974487305,-27.4973583221],"type":"Point"}
}