{
  "type": "Feature",
  "properties": {
    "addr:full":"15 Old Menangle Rd Campbelltown NSW 2560",
    "addr:housenumber":"15",
    "addr:postcode":"2560",
    "addr:street":"Old Menangle Rd",
    "iso:country":"AU",
    "sg:address":"15 Old Menangle Rd",
    "sg:city":"Campbelltown",
    "sg:classifiers":[
        {
            "category":"Communications",
            "subcategory":"News Services",
            "type":"Services"
        }
    ],
    "sg:phone":"+61 2 4645 4921",
    "sg:postcode":"2560",
    "sg:province":"NSW",
    "sg:tags":[
        "information",
        "tourist",
        "attractions"
    ],
    "wof:name":"Campbelltown Visitor Information Centre Quondong",
    "wof:placetype":"venue"
},
  "geometry": {"coordinates":[150.80744934099999,-34.0728607178],"type":"Point"}
}