{
  "type": "Feature",
  "properties": {
    "iso:country":"AU",
    "sg:address":"Level 3 113 Canberra Ave",
    "sg:city":"Griffith",
    "sg:classifiers":[
        {
            "category":"Insurance",
            "subcategory":"Life Insurance",
            "type":"Services"
        }
    ],
    "sg:phone":"+61 2 6295 9700",
    "sg:postcode":"2603",
    "sg:province":"ACT",
    "wof:name":"Matrix Planning Solutions",
    "wof:placetype":"venue"
},
  "geometry": {"coordinates":[149.14219665499999,-35.3214225769],"type":"Point"}
}