{
  "type": "Feature",
  "properties": {
    "addr:full":"397 Newbridge Rd Liverpool NSW 2170",
    "addr:housenumber":"397",
    "addr:postcode":"2170",
    "addr:street":"Newbridge Rd",
    "iso:country":"AU",
    "sg:address":"397 Newbridge Rd",
    "sg:city":"Liverpool",
    "sg:classifiers":[
        {
            "category":"Autos & Motor Vehicles",
            "subcategory":"Auto Supplies",
            "type":"Retail Goods"
        }
    ],
    "sg:phone":"+61 2 9821 1677",
    "sg:postcode":"2170",
    "sg:province":"NSW",
    "sg:tags":[
        "part",
        "cycles",
        "accessory"
    ],
    "sg:website":"http://www.aitkens.com.au",
    "wof:name":"Aitkens Motorcycle World",
    "wof:placetype":"venue"
},
  "geometry": {"coordinates":[150.93153381400001,-33.9281425476],"type":"Point"}
}