{
  "type": "Feature",
  "properties": {
    "iso:country":"AU",
    "sg:address":"17 Merrigal Crt",
    "sg:city":"Frankston South",
    "sg:classifiers":[
        {
            "category":"Home & Garden",
            "subcategory":"Building Materials",
            "type":"Retail Goods"
        }
    ],
    "sg:phone":"+61 3 9783 5223",
    "sg:postcode":"3199",
    "sg:province":"VIC",
    "sg:tags":[
        "merchant",
        "glass",
        "glazier"
    ],
    "wof:name":"All Glass & Mirrors (Vic) Pty Ltd",
    "wof:placetype":"venue"
},
  "geometry": {"coordinates":[145.11029052699999,-38.1753959656],"type":"Point"}
}