{
  "type": "Feature",
  "properties": {
    "addr:full":"63 George St Bowen QLD 4805",
    "addr:housenumber":"63",
    "addr:postcode":"4805",
    "addr:street":"George St",
    "iso:country":"AU",
    "sg:address":"63 George St",
    "sg:city":"Bowen",
    "sg:classifiers":[
        {
            "category":"Building & Trades",
            "subcategory":"Construction",
            "type":"Services"
        }
    ],
    "sg:phone":"+61 7 4786 2133",
    "sg:postcode":"4805",
    "sg:province":"QLD",
    "sg:tags":[
        "window",
        "aluminium"
    ],
    "wof:name":"Bill Dreger Glass & Aluminium",
    "wof:placetype":"venue"
},
  "geometry": {"coordinates":[148.24244689899999,-20.0175457001],"type":"Point"}
}