{
  "type": "Feature",
  "properties": {
    "iso:country":"AU",
    "sg:address":"113 Union St (Cnr Union & Kyogle St's)",
    "sg:city":"South Lismore",
    "sg:classifiers":[
        {
            "category":"Autos & Motor Vehicles",
            "subcategory":"Auto Supplies",
            "type":"Retail Goods"
        }
    ],
    "sg:phone":"+61 2 6622 3000",
    "sg:postcode":"2480",
    "sg:province":"NSW",
    "sg:tags":[
        "battery",
        "automotive"
    ],
    "wof:name":"Northern Rivers Discount Batteries",
    "wof:placetype":"venue"
},
  "geometry": {"coordinates":[153.27537536599999,-28.803899765],"type":"Point"}
}