{
  "type": "Feature",
  "properties": {
    "addr:full":"19 Grandview Pde Moolap VIC 3221",
    "addr:housenumber":"19",
    "addr:postcode":"3221",
    "addr:street":"Grandview Pde",
    "iso:country":"AU",
    "sg:address":"19 Grandview Pde",
    "sg:city":"Moolap",
    "sg:classifiers":[
        {
            "category":"Retail",
            "subcategory":"Auto Repair",
            "type":"Services"
        }
    ],
    "sg:phone":"+61 3 5248 5737",
    "sg:postcode":"3221",
    "sg:province":"VIC",
    "sg:tags":[
        "repairer",
        "motor",
        "engineer"
    ],
    "wof:name":"Mawson Motors",
    "wof:placetype":"venue"
},
  "geometry": {"coordinates":[144.41932700000001,-38.167751],"type":"Point"}
}