{
  "type": "Feature",
  "properties": {
    "iso:country":"AU",
    "sg:address":"Bilwon Rd",
    "sg:city":"Biboohra",
    "sg:classifiers":[
        {
            "category":"Retail",
            "subcategory":"Car Wash",
            "type":"Services"
        }
    ],
    "sg:phone":"+61 7 4093 2545",
    "sg:postcode":"4880",
    "sg:province":"QLD",
    "sg:tags":[
        "merchant",
        "oil",
        "refiner"
    ],
    "wof:name":"Ampol Petroleum (Qld) Pty Ltd",
    "wof:placetype":"venue"
},
  "geometry": {"coordinates":[145.42112731899999,-16.9168567657],"type":"Point"}
}