{
  "type": "Feature",
  "properties": {
    "iso:country":"AU",
    "sg:address":"Suite 702/ 155 Castlereagh St",
    "sg:city":"Sydney",
    "sg:classifiers":[
        {
            "category":"Recreation",
            "subcategory":"Sailing Club",
            "type":"Entertainment"
        }
    ],
    "sg:phone":"+61 2 9267 6771",
    "sg:postcode":"2000",
    "sg:province":"NSW",
    "sg:tags":[
        "merchant",
        "diamond"
    ],
    "wof:name":"Sparkle Impex Pty Ltd",
    "wof:placetype":"venue"
},
  "geometry": {"coordinates":[151.20916748100001,-33.8720703125],"type":"Point"}
}