{
  "type": "Feature",
  "properties": {
    "iso:country":"AU",
    "sg:address":"32- 34 Gladstone Rd",
    "sg:city":"Rockhampton",
    "sg:classifiers":[
        {
            "category":"Home & Garden",
            "subcategory":"Hardware",
            "type":"Retail Goods"
        }
    ],
    "sg:phone":"+61 7 4927 5833",
    "sg:postcode":"4700",
    "sg:province":"QLD",
    "sg:tags":[
        "repair",
        "tool",
        "power"
    ],
    "wof:name":"A Mans Toy Shop",
    "wof:placetype":"venue"
},
  "geometry": {"coordinates":[150.50674438499999,-23.388469696],"type":"Point"}
}