{
  "type": "Feature",
  "properties": {
    "addr:full":"134 Lansdowne Rd Kensington WA 6151",
    "addr:housenumber":"134",
    "addr:postcode":"6151",
    "addr:street":"Lansdowne Rd",
    "iso:country":"AU",
    "sg:address":"134 Lansdowne Rd",
    "sg:city":"Kensington",
    "sg:classifiers":[
        {
            "category":"Building & Trades",
            "subcategory":"Cleaning & Sanitation",
            "type":"Services"
        }
    ],
    "sg:phone":"+61 417 095 367",
    "sg:postcode":"6151",
    "sg:province":"WA",
    "sg:tags":[
        "window"
    ],
    "wof:name":"Kenkleen Kardinya",
    "wof:placetype":"venue"
},
  "geometry": {"coordinates":[115.889427,-31.982716],"type":"Point"}
}