{
  "type": "Feature",
  "properties": {
    "addr:full":"34 Denison St Tamworth NSW 2340",
    "addr:housenumber":"34",
    "addr:postcode":"2340",
    "addr:street":"Denison St",
    "iso:country":"AU",
    "sg:address":"34 Denison St",
    "sg:city":"Tamworth",
    "sg:classifiers":[
        {
            "category":"Utilities",
            "subcategory":"Electric",
            "type":"Services"
        }
    ],
    "sg:phone":"+61 2 6765 8859",
    "sg:postcode":"2340",
    "sg:province":"NSW",
    "sg:tags":[
        "electrical",
        "contractor"
    ],
    "wof:name":"Shanahans Electrical Pty Ltd",
    "wof:placetype":"venue"
},
  "geometry": {"coordinates":[150.91615295400001,-31.0889167786],"type":"Point"}
}