{
  "type": "Feature",
  "properties": {
    "iso:country":"AU",
    "sg:address":"22 Farrell St",
    "sg:city":"Yandina",
    "sg:classifiers":[
        {
            "category":"Home & Garden",
            "subcategory":"Garden Supply",
            "type":"Retail Goods"
        }
    ],
    "sg:phone":"+61 7 5446 8588",
    "sg:postcode":"4561",
    "sg:province":"QLD",
    "sg:tags":[
        "equipment"
    ],
    "wof:name":"Emmos Hardware",
    "wof:placetype":"venue"
},
  "geometry": {"coordinates":[152.95639038100001,-26.5611553192],"type":"Point"}
}