{
  "type": "Feature",
  "properties": {
    "iso:country":"AU",
    "sg:address":"76 Helicia St",
    "sg:city":"Algester",
    "sg:classifiers":[
        {
            "category":"Professional",
            "subcategory":"Art Services",
            "type":"Services"
        }
    ],
    "sg:phone":"+61 7 3272 0917",
    "sg:postcode":"4115",
    "sg:province":"QLD",
    "sg:tags":[
        "decorator",
        "painter"
    ],
    "wof:name":"PJ & SS Morgan Painting Services",
    "wof:placetype":"venue"
},
  "geometry": {"coordinates":[153.026046753,-27.6208515167],"type":"Point"}
}