{
  "type": "Feature",
  "properties": {
    "iso:country":"AU",
    "sg:address":"PO Box 3381",
    "sg:city":"Bluff Point",
    "sg:classifiers":[
        {
            "category":"Building & Trades",
            "subcategory":"Construction",
            "type":"Services"
        }
    ],
    "sg:phone":"+61 8 9938 3250",
    "sg:postcode":"6530",
    "sg:province":"WA",
    "sg:tags":[
        "earth",
        "excavating",
        "moving",
        "contractor"
    ],
    "wof:name":"Ivey Contracting",
    "wof:placetype":"venue"
},
  "geometry": {"coordinates":[114.625366211,-28.7391891479],"type":"Point"}
}