{
  "type": "Feature",
  "properties": {
    "iso:country":"AU",
    "sg:address":"3/ 329 Pakington St",
    "sg:city":"Newtown",
    "sg:classifiers":[
        {
            "category":"Shopping",
            "subcategory":"Shoes",
            "type":"Retail Goods"
        }
    ],
    "sg:phone":"+61 3 5223 3833",
    "sg:postcode":"3220",
    "sg:province":"VIC",
    "sg:tags":[
        "footwear"
    ],
    "wof:name":"A Matter Of Shoes",
    "wof:placetype":"venue"
},
  "geometry": {"coordinates":[144.345169,-38.156403],"type":"Point"}
}