{
  "type": "Feature",
  "properties": {
    "iso:country":"AU",
    "sg:address":"Factory 7/ 2 Barry St",
    "sg:city":"Bayswater",
    "sg:classifiers":[
        {
            "category":"Retail",
            "subcategory":"Auto Repair",
            "type":"Services"
        }
    ],
    "sg:phone":"+61 3 9720 5257",
    "sg:postcode":"3153",
    "sg:province":"VIC",
    "sg:tags":[
        "repairer",
        "motor",
        "engineer"
    ],
    "wof:name":"S M C Automotive Repairs",
    "wof:placetype":"venue"
},
  "geometry": {"coordinates":[145.274124145,-37.846988678],"type":"Point"}
}