{
  "type": "Feature",
  "properties": {
    "addr:full":"33 Bayview Tce Deception Bay QLD 4508",
    "addr:housenumber":"33",
    "addr:postcode":"4508",
    "addr:street":"Bayview Tce",
    "iso:country":"AU",
    "sg:address":"33 Bayview Tce",
    "sg:city":"Deception Bay",
    "sg:classifiers":[
        {
            "category":"Education",
            "subcategory":"Kindergarten",
            "type":"Public Place"
        }
    ],
    "sg:phone":"+61 7 3203 2093",
    "sg:postcode":"4508",
    "sg:province":"QLD",
    "sg:tags":[
        "pre-schools"
    ],
    "wof:name":"C&K Bayview Community Kindergarten & Preschool",
    "wof:placetype":"venue"
},
  "geometry": {"coordinates":[153.02598571799999,-27.1838054657],"type":"Point"}
}