{
  "type": "Feature",
  "properties": {
    "addr:full":"6 University Rd Townsville QLD 4810",
    "addr:housenumber":"6",
    "addr:postcode":"4810",
    "addr:street":"University Rd",
    "iso:country":"AU",
    "sg:address":"6 University Rd",
    "sg:city":"Townsville",
    "sg:classifiers":[
        {
            "category":"Autos & Motor Vehicles",
            "subcategory":"Fuel & Gas Station",
            "type":"Retail Goods"
        }
    ],
    "sg:phone":"+61 7 4778 2470",
    "sg:postcode":"4810",
    "sg:province":"QLD",
    "wof:name":"Mobil Walkabout Palms Roadhouse",
    "wof:placetype":"venue"
},
  "geometry": {"coordinates":[146.81272899999999,-19.317612],"type":"Point"}
}