{
  "type": "Feature",
  "properties": {
    "addr:full":"25 Albion St Warwick QLD 4370",
    "addr:housenumber":"25",
    "addr:postcode":"4370",
    "addr:street":"Albion St",
    "iso:country":"AU",
    "sg:address":"25 Albion St",
    "sg:city":"Warwick",
    "sg:classifiers":[
        {
            "category":"Retail",
            "subcategory":"Auto Repair",
            "type":"Services"
        }
    ],
    "sg:phone":"+61 7 4661 1852",
    "sg:postcode":"4370",
    "sg:province":"QLD",
    "sg:tags":[
        "electrical"
    ],
    "wof:name":"Allgear Auto Electrics",
    "wof:placetype":"venue"
},
  "geometry": {"coordinates":[152.03558349599999,-28.2121086121],"type":"Point"}
}