{
  "type": "Feature",
  "properties": {
    "addr:full":"20 Kitawah St Lonsdale SA 5160",
    "addr:housenumber":"20",
    "addr:postcode":"5160",
    "addr:street":"Kitawah St",
    "iso:country":"AU",
    "sg:address":"20 Kitawah St",
    "sg:city":"Lonsdale",
    "sg:classifiers":[
        {
            "category":"Shopping",
            "subcategory":"Crafts & Fabrics",
            "type":"Retail Goods"
        }
    ],
    "sg:phone":"+61 8 8186 0588",
    "sg:postcode":"5160",
    "sg:province":"SA",
    "sg:tags":[
        "adhesive"
    ],
    "wof:name":"Advance Hardware Supplies",
    "wof:placetype":"venue"
},
  "geometry": {"coordinates":[138.500396728,-35.1090888977],"type":"Point"}
}