{
  "type": "Feature",
  "properties": {
    "addr:full":"15 Jenkins St Lidcombe NSW 2141",
    "addr:housenumber":"15",
    "addr:postcode":"2141",
    "addr:street":"Jenkins St",
    "iso:country":"AU",
    "sg:address":"15 Jenkins St",
    "sg:city":"Lidcombe",
    "sg:classifiers":[
        {
            "category":"Government",
            "subcategory":"Fire Station",
            "type":"Public Place"
        }
    ],
    "sg:phone":"+61 2 9643 2236",
    "sg:postcode":"2141",
    "sg:province":"NSW",
    "sg:tags":[
        "equipment",
        "protection",
        "consultant"
    ],
    "wof:name":"Action Fire Extinguisher Sales & Service",
    "wof:placetype":"venue"
},
  "geometry": {"coordinates":[151.027435303,-33.8767623901],"type":"Point"}
}