{
  "type": "Feature",
  "properties": {
    "addr:full":"515 Riversdale Rd Camberwell VIC 3124",
    "addr:housenumber":"515",
    "addr:postcode":"3124",
    "addr:street":"Riversdale Rd",
    "iso:country":"AU",
    "sg:address":"515 Riversdale Rd",
    "sg:city":"Camberwell",
    "sg:classifiers":[
        {
            "category":"Food & Beverages",
            "subcategory":"Bakery",
            "type":"Retail Goods"
        }
    ],
    "sg:phone":"+61 3 9882 5593",
    "sg:postcode":"3124",
    "sg:province":"VIC",
    "sg:tags":[
        "baker"
    ],
    "wof:name":"Bakers Delight Ltd",
    "wof:placetype":"venue"
},
  "geometry": {"coordinates":[145.05751037600001,-37.8313064575],"type":"Point"}
}