{
  "type": "Feature",
  "properties": {
    "iso:country":"AU",
    "sg:address":"50 George St",
    "sg:city":"Mudgee",
    "sg:classifiers":[
        {
            "category":"Building & Trades",
            "subcategory":"Equipment Rental",
            "type":"Services"
        }
    ],
    "sg:phone":"+61 2 6372 1785",
    "sg:postcode":"2850",
    "sg:province":"NSW",
    "sg:tags":[
        "crane",
        "hire"
    ],
    "wof:name":"Furney's Building & Plumbing Supplies Pty Ltd",
    "wof:placetype":"venue"
},
  "geometry": {"coordinates":[149.594482,-32.600513],"type":"Point"}
}