{
  "type": "Feature",
  "properties": {
    "addr:full":"Bright Rd Eurobin VIC 3739",
    "addr:postcode":"3739",
    "addr:street":"Bright Rd",
    "iso:country":"AU",
    "sg:address":"Bright Rd",
    "sg:city":"Eurobin",
    "sg:classifiers":[
        {
            "category":"Farming",
            "subcategory":"Farm",
            "type":"Manufacturing & Wholesale Goods"
        }
    ],
    "sg:phone":"+61 3 5752 1734",
    "sg:postcode":"3739",
    "sg:province":"VIC",
    "sg:tags":[
        "farmer"
    ],
    "wof:name":"Borsi A",
    "wof:placetype":"venue"
},
  "geometry": {"coordinates":[146.84979248100001,-36.6359405518],"type":"Point"}
}