{
  "type": "Feature",
  "properties": {
    "addr:full":"375 springvale Rd Springvale VIC 3171",
    "addr:housenumber":"375",
    "addr:postcode":"3171",
    "addr:street":"Springvale Rd",
    "iso:country":"AU",
    "sg:address":"375 springvale Rd",
    "sg:city":"Springvale",
    "sg:classifiers":[
        {
            "category":"Banks & Credit Unions",
            "subcategory":"Bank",
            "type":"Services"
        }
    ],
    "sg:phone":"+61 3 9547 9976",
    "sg:postcode":"3171",
    "sg:province":"VIC",
    "sg:tags":[
        "broker",
        "mortgage"
    ],
    "wof:name":"e-morgage wise",
    "wof:placetype":"venue"
},
  "geometry": {"coordinates":[145.15220642099999,-37.9538116455],"type":"Point"}
}