{
  "type": "Feature",
  "properties": {
    "addr:full":"178 Main St Lilydale VIC 3140",
    "addr:housenumber":"178",
    "addr:postcode":"3140",
    "addr:street":"Main St",
    "iso:country":"AU",
    "sg:address":"178 Main St",
    "sg:city":"Lilydale",
    "sg:classifiers":[
        {
            "category":"Fast Food",
            "type":"Food & Drink"
        }
    ],
    "sg:phone":"+61 3 9739 7313",
    "sg:postcode":"3140",
    "sg:province":"VIC",
    "sg:tags":[
        "away",
        "take"
    ],
    "wof:name":"Senis Pizza",
    "wof:placetype":"venue"
},
  "geometry": {"coordinates":[145.28083801299999,-37.7979812622],"type":"Point"}
}