{
  "type": "Feature",
  "properties": {
    "addr:full":"280 Bannister Rd Canning Vale WA 6155",
    "addr:housenumber":"280",
    "addr:postcode":"6155",
    "addr:street":"Bannister Rd",
    "iso:country":"AU",
    "sg:address":"280 Bannister Rd",
    "sg:city":"Canning Vale",
    "sg:classifiers":[
        {
            "category":"Health Services",
            "subcategory":"Doctor",
            "type":"Services"
        }
    ],
    "sg:phone":"+61 1800 338 568",
    "sg:postcode":"6155",
    "sg:province":"WA",
    "sg:tags":[
        "nurse",
        "nursing"
    ],
    "wof:name":"O&#039;Grady Peyton International",
    "wof:placetype":"venue"
},
  "geometry": {"coordinates":[115.89559199999999,-32.070065],"type":"Point"}
}