{
  "type": "Feature",
  "properties": {
    "addr:full":"30- 40 Hurtle Sq Adelaide SA 5000",
    "addr:housenumber":"40",
    "addr:postcode":"5000",
    "addr:street":"Hurtle Sq",
    "iso:country":"AU",
    "sg:address":"30- 40 Hurtle Sq",
    "sg:city":"Adelaide",
    "sg:classifiers":[
        {
            "category":"Organizations",
            "subcategory":"Labor Organization",
            "type":"Services"
        }
    ],
    "sg:phone":"+61 8 8232 5999",
    "sg:postcode":"5000",
    "sg:province":"SA",
    "sg:tags":[
        "union"
    ],
    "wof:name":"CEPU",
    "wof:placetype":"venue"
},
  "geometry": {"coordinates":[138.607254028,-34.9322166443],"type":"Point"}
}