{
  "type": "Feature",
  "properties": {
    "addr:full":"24 Salvado Rd Wembley WA 6014",
    "addr:housenumber":"24",
    "addr:postcode":"6014",
    "addr:street":"Salvado Rd",
    "iso:country":"AU",
    "sg:address":"24 Salvado Rd",
    "sg:city":"Wembley",
    "sg:classifiers":[
        {
            "category":"Health Services",
            "subcategory":"Doctor",
            "type":"Services"
        }
    ],
    "sg:phone":"+61 8 9381 5655",
    "sg:postcode":"6014",
    "sg:province":"WA",
    "sg:tags":[
        "medical",
        "practitioner"
    ],
    "wof:name":"Perth Radiation Oncology",
    "wof:placetype":"venue"
},
  "geometry": {"coordinates":[115.822891235,-31.9419345856],"type":"Point"}
}