{
  "type": "Feature",
  "properties": {
    "addr:full":"Bruce Hwy Wallaville QLD 4671",
    "addr:postcode":"4671",
    "addr:street":"Bruce Hwy",
    "iso:country":"AU",
    "sg:address":"Bruce Hwy",
    "sg:city":"Wallaville",
    "sg:classifiers":[
        {
            "category":"Farming",
            "subcategory":"Orchard",
            "type":"Manufacturing & Wholesale Goods"
        }
    ],
    "sg:phone":"+61 7 4157 6245",
    "sg:postcode":"4671",
    "sg:province":"QLD",
    "sg:tags":[
        "citrus",
        "fruit",
        "grower"
    ],
    "wof:name":"MacLennan Nominees Pty Ltd",
    "wof:placetype":"venue"
},
  "geometry": {"coordinates":[151.977417,-25.095163],"type":"Point"}
}