{
  "type": "Feature",
  "properties": {
    "addr:full":"425 Pacific Hwy Crows Nest NSW 2065",
    "addr:housenumber":"425",
    "addr:postcode":"2065",
    "addr:street":"Pacific Hwy",
    "iso:country":"AU",
    "sg:address":"425 Pacific Hwy",
    "sg:city":"Crows Nest",
    "sg:classifiers":[
        {
            "category":"Health Services",
            "subcategory":"Doctor",
            "type":"Services"
        }
    ],
    "sg:phone":"+61 2 9436 2992",
    "sg:postcode":"2065",
    "sg:province":"NSW",
    "sg:tags":[
        "medical",
        "practitioner"
    ],
    "wof:name":"Thermography Mediscreen Pty Ltd",
    "wof:placetype":"venue"
},
  "geometry": {"coordinates":[151.198608398,-33.825214386],"type":"Point"}
}