{
  "type": "Feature",
  "properties": {
    "addr:full":"82 High St Preston VIC 3072",
    "addr:housenumber":"82",
    "addr:postcode":"3072",
    "addr:street":"High St",
    "iso:country":"AU",
    "sg:address":"82 High St",
    "sg:city":"Preston",
    "sg:classifiers":[
        {
            "category":"Retail",
            "subcategory":"Auto Repair",
            "type":"Services"
        }
    ],
    "sg:phone":"+61 3 9480 5625",
    "sg:postcode":"3072",
    "sg:province":"VIC",
    "sg:tags":[
        "repairer",
        "motor",
        "engineer"
    ],
    "wof:name":"Mmw Auto Service",
    "wof:placetype":"venue"
},
  "geometry": {"coordinates":[145.00494384800001,-37.7332344055],"type":"Point"}
}