{
  "type": "Feature",
  "properties": {
    "addr:full":"44 Erumba St Alice Springs NT 0870",
    "addr:housenumber":"44",
    "addr:postcode":"nt 0870",
    "addr:street":"Erumba St",
    "iso:country":"AU",
    "sg:address":"44 Erumba St",
    "sg:city":"Alice Springs",
    "sg:classifiers":[
        {
            "category":"Building & Trades",
            "subcategory":"Cleaning & Sanitation",
            "type":"Services"
        }
    ],
    "sg:phone":"+61 408 819 896",
    "sg:postcode":"0870",
    "sg:province":"NT",
    "sg:tags":[
        "window"
    ],
    "wof:name":"I Do Windows",
    "wof:placetype":"venue"
},
  "geometry": {"coordinates":[133.872314453,-23.6764736176],"type":"Point"}
}