{
  "type": "Feature",
  "properties": {
    "addr:full":"Griffin Appartments Jardine St Kingston ACT 2604",
    "addr:postcode":"2604",
    "addr:street":"Jardine St",
    "iso:country":"AU",
    "sg:address":"Griffin Appartments Jardine St",
    "sg:city":"Kingston",
    "sg:classifiers":[
        {
            "category":"Personal",
            "subcategory":"Beauty Salon",
            "type":"Services"
        }
    ],
    "sg:phone":"+61 2 6295 2170",
    "sg:postcode":"2604",
    "sg:province":"ACT",
    "sg:tags":[
        "hairdresser"
    ],
    "wof:name":"Lush Hair",
    "wof:placetype":"venue"
},
  "geometry": {"coordinates":[149.142288208,-35.3159561157],"type":"Point"}
}