{
  "type": "Feature",
  "properties": {
    "iso:country":"AU",
    "sg:address":"204 Belmore Rd",
    "sg:city":"Riverwood",
    "sg:classifiers":[
        {
            "category":"Real Estate",
            "subcategory":"Real Estate Agent",
            "type":"Services"
        }
    ],
    "sg:phone":"+61 2 9584 2577",
    "sg:postcode":"2210",
    "sg:province":"NSW",
    "wof:name":"Golby R T (Since 1924)",
    "wof:placetype":"venue"
},
  "geometry": {"coordinates":[151.052277,-33.952656],"type":"Point"}
}