{
  "type": "Feature",
  "properties": {
    "iso:country":"AU",
    "sg:address":"427 Chapman Rd",
    "sg:city":"Geraldton",
    "sg:classifiers":[
        {
            "category":"Health Services",
            "subcategory":"Health Practitioner",
            "type":"Services"
        }
    ],
    "sg:phone":"+61 8 9923 0304",
    "sg:postcode":"6530",
    "sg:province":"WA",
    "sg:tags":[
        "physiotherapist"
    ],
    "wof:name":"Bluff Point Physiotherapy Clinic",
    "wof:placetype":"venue"
},
  "geometry": {"coordinates":[114.62423706,-28.7378768921],"type":"Point"}
}