{
  "type": "Feature",
  "properties": {
    "addr:full":"54 Gordon Rd West Dianella WA 6059",
    "addr:housenumber":"54",
    "addr:postcode":"6059",
    "addr:street":"Gordon Rd West",
    "iso:country":"AU",
    "sg:address":"54 Gordon Rd West",
    "sg:city":"Dianella",
    "sg:classifiers":[
        {
            "category":"Professional",
            "subcategory":"Detective & Security Services",
            "type":"Services"
        }
    ],
    "sg:phone":"+61 8 9275 7331",
    "sg:postcode":"6059",
    "sg:province":"WA",
    "sg:tags":[
        "consultant",
        "system"
    ],
    "wof:name":"C & S Security Services",
    "wof:placetype":"venue"
},
  "geometry": {"coordinates":[115.876251221,-31.8796482086],"type":"Point"}
}