{
  "type": "Feature",
  "properties": {
    "addr:full":"7 Murray St Collector NSW 2581",
    "addr:housenumber":"7",
    "addr:postcode":"2581",
    "addr:street":"Murray St",
    "iso:country":"AU",
    "sg:address":"7 Murray St",
    "sg:city":"Collector",
    "sg:classifiers":[
        {
            "category":"Food & Beverages",
            "subcategory":"Supermarket",
            "type":"Retail Goods"
        }
    ],
    "sg:phone":"+61 2 4848 0003",
    "sg:postcode":"2581",
    "sg:province":"NSW",
    "sg:tags":[
        "grocery",
        "store"
    ],
    "wof:name":"Collector Inn Gereral Store",
    "wof:placetype":"venue"
},
  "geometry": {"coordinates":[149.42808532699999,-34.9130401611],"type":"Point"}
}