{
  "type": "Feature",
  "properties": {
    "addr:full":"130 Canterbury Rd Heathmont VIC 3135",
    "addr:housenumber":"130",
    "addr:postcode":"3135",
    "addr:street":"Canterbury Rd",
    "iso:country":"AU",
    "sg:address":"130 Canterbury Rd",
    "sg:city":"Heathmont",
    "sg:classifiers":[
        {
            "category":"Shopping",
            "subcategory":"Bridal",
            "type":"Retail Goods"
        }
    ],
    "sg:phone":"+61 3 9729 5989",
    "sg:postcode":"3135",
    "sg:province":"VIC",
    "sg:tags":[
        "hire",
        "wear"
    ],
    "wof:name":"Kris K Bridal",
    "wof:placetype":"venue"
},
  "geometry": {"coordinates":[145.246551514,-37.828502655],"type":"Point"}
}