{
  "type": "Feature",
  "properties": {
    "addr:full":"5 East Pl Kambah ACT 2902",
    "addr:housenumber":"5",
    "addr:postcode":"2902",
    "addr:street":"East Pl",
    "iso:country":"AU",
    "sg:address":"5 East Pl",
    "sg:city":"Kambah",
    "sg:classifiers":[
        {
            "category":"Shopping",
            "subcategory":"Jewelry",
            "type":"Retail Goods"
        }
    ],
    "sg:phone":"+61 2 6231 7742",
    "sg:postcode":"2902",
    "sg:province":"ACT",
    "sg:tags":[
        "jeweller"
    ],
    "wof:name":"Design Underground",
    "wof:placetype":"venue"
},
  "geometry": {"coordinates":[149.05593872099999,-35.3861312866],"type":"Point"}
}