{
  "type": "Feature",
  "properties": {
    "addr:full":"34 Union St Kogarah NSW 2217",
    "addr:housenumber":"34",
    "addr:postcode":"2217",
    "addr:street":"Union St",
    "iso:country":"AU",
    "sg:address":"34 Union St",
    "sg:city":"Kogarah",
    "sg:classifiers":[
        {
            "category":"Sports & Exercise",
            "subcategory":"Gym",
            "type":"Entertainment"
        }
    ],
    "sg:phone":"+61 2 9553 0622",
    "sg:postcode":"2217",
    "sg:province":"NSW",
    "sg:tags":[
        "health",
        "fitness"
    ],
    "wof:name":"City Living Swim & Fitness Clinic",
    "wof:placetype":"venue"
},
  "geometry": {"coordinates":[151.12806699999999,-33.964691],"type":"Point"}
}