{
  "type": "Feature",
  "properties": {
    "addr:full":"37 Southern Rd Heidelberg Heights VIC 3081",
    "addr:housenumber":"37",
    "addr:postcode":"3081",
    "addr:street":"Southern Rd",
    "iso:country":"AU",
    "sg:address":"37 Southern Rd",
    "sg:city":"Heidelberg Heights",
    "sg:classifiers":[
        {
            "category":"Farming",
            "subcategory":"Fish & Marine Products",
            "type":"Manufacturing & Wholesale Goods"
        }
    ],
    "sg:phone":"+61 3 9458 2227",
    "sg:postcode":"3081",
    "sg:province":"VIC",
    "sg:tags":[
        "organic"
    ],
    "wof:name":"Flowers, Gifts & Organics",
    "wof:placetype":"venue"
},
  "geometry": {"coordinates":[145.05329895,-37.7425193787],"type":"Point"}
}