{
  "type": "Feature",
  "properties": {
    "addr:full":"Cnr Abernethy and Alexander Rds Belmont WA 6104",
    "addr:postcode":"6104",
    "addr:street":"Cnr Abernethy",
    "iso:country":"AU",
    "sg:address":"Cnr Abernethy and Alexander Rds",
    "sg:city":"Belmont",
    "sg:classifiers":[
        {
            "category":"Sports & Exercise",
            "subcategory":"Gym",
            "type":"Entertainment"
        }
    ],
    "sg:phone":"+61 8 9277 1622",
    "sg:postcode":"6104",
    "sg:province":"WA",
    "sg:tags":[
        "health",
        "fitness"
    ],
    "wof:name":"Belmont Oasis Leisure Centre",
    "wof:placetype":"venue"
},
  "geometry": {"coordinates":[115.92198944099999,-31.9503250122],"type":"Point"}
}