{
  "type": "Feature",
  "properties": {
    "addr:full":"499 Park Rd Park Orchards VIC 3114",
    "addr:housenumber":"499",
    "addr:postcode":"3114",
    "addr:street":"Park Rd",
    "iso:country":"AU",
    "sg:address":"499 Park Rd",
    "sg:city":"Park Orchards",
    "sg:classifiers":[
        {
            "category":"Building & Trades",
            "subcategory":"Construction",
            "type":"Services"
        }
    ],
    "sg:phone":"+61 408 002 066",
    "sg:postcode":"3114",
    "sg:province":"VIC",
    "sg:tags":[
        "stonework",
        "stone",
        "mason"
    ],
    "wof:name":"Samrac Masonry",
    "wof:placetype":"venue"
},
  "geometry": {"coordinates":[145.210403442,-37.7810401917],"type":"Point"}
}