{
  "type": "Feature",
  "properties": {
    "iso:country":"AU",
    "sg:address":"2/30 Clifford St",
    "sg:city":"Huntingdale",
    "sg:classifiers":[
        {
            "category":"Retail",
            "subcategory":"Auto Repair",
            "type":"Services"
        }
    ],
    "sg:phone":"+61 3 9562 7448",
    "sg:postcode":"3166",
    "sg:province":"VIC",
    "sg:tags":[
        "repairer",
        "motor",
        "engineer"
    ],
    "wof:name":"G & C Motors",
    "wof:placetype":"venue"
},
  "geometry": {"coordinates":[145.10768127399999,-37.9097938538],"type":"Point"}
}