{
  "type": "Feature",
  "properties": {
    "iso:country":"AU",
    "sg:address":"15 George St",
    "sg:city":"Granville",
    "sg:classifiers":[
        {
            "category":"Wholesale",
            "subcategory":"Painting Supplies",
            "type":"Manufacturing & Wholesale Goods"
        }
    ],
    "sg:phone":"+61 2 9645 2514",
    "sg:postcode":"2142",
    "sg:province":"NSW",
    "sg:tags":[
        "equipment",
        "spraying"
    ],
    "wof:name":"Epac Productions",
    "wof:placetype":"venue"
},
  "geometry": {"coordinates":[151.01719665499999,-33.8341255188],"type":"Point"}
}