{
  "type": "Feature",
  "properties": {
    "addr:full":"43 Sanford Rd Albany WA 6330",
    "addr:housenumber":"43",
    "addr:postcode":"6330",
    "addr:street":"Sanford Rd",
    "iso:country":"AU",
    "sg:address":"43 Sanford Rd",
    "sg:city":"Albany",
    "sg:classifiers":[
        {
            "category":"Manufacturing",
            "subcategory":"Retail Goods",
            "type":"Manufacturing & Wholesale Goods"
        }
    ],
    "sg:phone":"+61 8 9841 8264",
    "sg:postcode":"6330",
    "sg:province":"WA",
    "sg:tags":[
        "merchant",
        "pump",
        "mfrs"
    ],
    "wof:name":"Southern Electrics",
    "wof:placetype":"venue"
},
  "geometry": {"coordinates":[117.88121032700001,-35.0135421753],"type":"Point"}
}