{
  "type": "Feature",
  "properties": {
    "addr:full":"204 Malabar Rd Coogee NSW 2034",
    "addr:housenumber":"204",
    "addr:postcode":"2034",
    "addr:street":"Malabar Rd",
    "iso:country":"AU",
    "sg:address":"204 Malabar Rd",
    "sg:city":"Coogee",
    "sg:classifiers":[
        {
            "category":"Building & Trades",
            "subcategory":"Plumbing",
            "type":"Services"
        }
    ],
    "sg:phone":"+61 2 9344 5642",
    "sg:postcode":"2034",
    "sg:province":"NSW",
    "sg:tags":[
        "plumber",
        "gasfitters"
    ],
    "wof:name":"Williams Water Works Pty Ltd",
    "wof:placetype":"venue"
},
  "geometry": {"coordinates":[151.25779724099999,-33.9335021973],"type":"Point"}
}