{
  "type": "Feature",
  "properties": {
    "addr:full":"10 Templestowe Rd Bulleen VIC 3105",
    "addr:housenumber":"10",
    "addr:postcode":"3105",
    "addr:street":"Templestowe Rd",
    "iso:country":"AU",
    "sg:address":"10 Templestowe Rd",
    "sg:city":"Bulleen",
    "sg:classifiers":[
        {
            "category":"Fast Food",
            "type":"Food & Drink"
        }
    ],
    "sg:phone":"+61 3 9852 0711",
    "sg:postcode":"3105",
    "sg:province":"VIC",
    "sg:tags":[
        "away",
        "take"
    ],
    "wof:name":"Lucia's Pizzeria",
    "wof:placetype":"venue"
},
  "geometry": {"coordinates":[145.08412170400001,-37.7600440979],"type":"Point"}
}