{
  "type": "Feature",
  "properties": {
    "iso:country":"AU",
    "sg:address":"340 Orrong Rd",
    "sg:city":"Carlisle",
    "sg:classifiers":[
        {
            "category":"Sports & Exercise",
            "subcategory":"Gym",
            "type":"Entertainment"
        }
    ],
    "sg:phone":"+61 8 9361 3193",
    "sg:postcode":"6101",
    "sg:province":"WA",
    "sg:tags":[
        "health",
        "fitness"
    ],
    "wof:name":"Fuller Fitness",
    "wof:placetype":"venue"
},
  "geometry": {"coordinates":[115.926811218,-31.978307724],"type":"Point"}
}