{
  "type": "Feature",
  "properties": {
    "iso:country":"AU",
    "sg:address":"4 Comrie St",
    "sg:city":"Wanniassa",
    "sg:classifiers":[
        {
            "category":"Health Services",
            "subcategory":"Doctor",
            "type":"Services"
        }
    ],
    "sg:phone":"+61 2 6296 2266",
    "sg:postcode":"2903",
    "sg:province":"ACT",
    "sg:tags":[
        "medical",
        "practitioner"
    ],
    "wof:name":"Erindale Immediate Health Care",
    "wof:placetype":"venue"
},
  "geometry": {"coordinates":[149.09892273,-35.4021835327],"type":"Point"}
}