{
  "type": "Feature",
  "properties": {
    "addr:full":"598- 600 Princes Hwy Rockdale NSW 2216",
    "addr:housenumber":"600",
    "addr:postcode":"2216",
    "addr:street":"Princes Hwy",
    "iso:country":"AU",
    "sg:address":"598- 600 Princes Hwy",
    "sg:city":"Rockdale",
    "sg:classifiers":[
        {
            "category":"Autos & Motor Vehicles",
            "subcategory":"Automobile Sales",
            "type":"Retail Goods"
        }
    ],
    "sg:phone":"+61 2 9567 6562",
    "sg:postcode":"2216",
    "sg:province":"NSW",
    "sg:tags":[
        "car",
        "used"
    ],
    "wof:name":"Highway Wholesale Automobiles",
    "wof:placetype":"venue"
},
  "geometry": {"coordinates":[151.137878,-33.955791],"type":"Point"}
}