{
  "type": "Feature",
  "properties": {
    "addr:full":"1/ 490 Mahoneys Rd Campbellfield VIC 3061",
    "addr:housenumber":"/ 490",
    "addr:postcode":"3061",
    "addr:street":"Mahoneys Rd",
    "iso:country":"AU",
    "sg:address":"1/ 490 Mahoneys Rd",
    "sg:city":"Campbellfield",
    "sg:classifiers":[
        {
            "category":"Home & Garden",
            "subcategory":"Building Materials",
            "type":"Retail Goods"
        }
    ],
    "sg:phone":"+61 3 9359 1444",
    "sg:postcode":"3061",
    "sg:province":"VIC",
    "sg:tags":[
        "supply"
    ],
    "wof:name":"Plaster Wholesalers",
    "wof:placetype":"venue"
},
  "geometry": {"coordinates":[144.96409606899999,-37.6903915405],"type":"Point"}
}