{
  "type": "Feature",
  "properties": {
    "iso:country":"AU",
    "sg:address":"20 Cherry St",
    "sg:city":"Wellington Point",
    "sg:classifiers":[
        {
            "category":"Building & Trades",
            "subcategory":"Plumbing",
            "type":"Services"
        }
    ],
    "sg:phone":"+61 7 3822 5060",
    "sg:postcode":"4160",
    "sg:province":"QLD",
    "sg:tags":[
        "plumber",
        "gasfitters"
    ],
    "wof:name":"Jensen Plumbing Service",
    "wof:placetype":"venue"
},
  "geometry": {"coordinates":[153.23353576700001,-27.5151824951],"type":"Point"}
}