{
  "type": "Feature",
  "properties": {
    "iso:country":"AU",
    "sg:address":"Suite 1 302 Windsor St",
    "sg:city":"Richmond",
    "sg:classifiers":[
        {
            "category":"Health Services",
            "subcategory":"Dentist",
            "type":"Services"
        }
    ],
    "sg:phone":"+61 2 4578 2325",
    "sg:postcode":"2753",
    "sg:province":"NSW",
    "wof:name":"Moreira Alan",
    "wof:placetype":"venue"
},
  "geometry": {"coordinates":[150.74981689399999,-33.5964050293],"type":"Point"}
}