{
  "type": "Feature",
  "properties": {
    "addr:full":"Suite 4, 191 Riversdale Rd Hawthorn VIC 3122",
    "addr:housenumber":"191",
    "addr:postcode":"3122",
    "addr:street":"Riversdale Rd",
    "iso:country":"AU",
    "sg:address":"Suite 4, 191 Riversdale Rd",
    "sg:city":"Hawthorn",
    "sg:classifiers":[
        {
            "category":"Insurance",
            "subcategory":"Hazard Insurance",
            "type":"Services"
        }
    ],
    "sg:phone":"+61 3 9818 3499",
    "sg:postcode":"3122",
    "sg:province":"VIC",
    "sg:tags":[
        "fire",
        "accident",
        "marine"
    ],
    "wof:name":"Freight Insurance Services International",
    "wof:placetype":"venue"
},
  "geometry": {"coordinates":[145.042114258,-37.8295211792],"type":"Point"}
}