{
  "type": "Feature",
  "properties": {
    "addr:full":"139 Streisand Drv McDowall QLD 4053",
    "addr:housenumber":"139",
    "addr:postcode":"4053",
    "addr:street":"Streisand Drv",
    "iso:country":"AU",
    "sg:address":"139 Streisand Drv",
    "sg:city":"McDowall",
    "sg:classifiers":[
        {
            "category":"Home & Garden",
            "subcategory":"Carpets & Floor Coverings",
            "type":"Retail Goods"
        }
    ],
    "sg:phone":"+61 7 3353 3269",
    "sg:postcode":"4053",
    "sg:province":"QLD",
    "sg:tags":[
        "tile",
        "wall",
        "layer"
    ],
    "wof:name":"Fresta V & G",
    "wof:placetype":"venue"
},
  "geometry": {"coordinates":[152.98516845699999,-27.3733215332],"type":"Point"}
}