{
  "type": "Feature",
  "properties": {
    "addr:full":"10 Tudor St Burwood VIC 3125",
    "addr:housenumber":"10",
    "addr:postcode":"3125",
    "addr:street":"Tudor St",
    "iso:country":"AU",
    "sg:address":"10 Tudor St",
    "sg:city":"Burwood",
    "sg:classifiers":[
        {
            "category":"Government",
            "subcategory":"Fire Station",
            "type":"Public Place"
        }
    ],
    "sg:phone":"+61 3 9808 8711",
    "sg:postcode":"3125",
    "sg:province":"VIC",
    "sg:tags":[
        "equipment",
        "protection",
        "consultant"
    ],
    "sg:website":"http://www.klinefire.com.au",
    "wof:name":"Kline Fire Equipment & Services",
    "wof:placetype":"venue"
},
  "geometry": {"coordinates":[145.10737609899999,-37.8541641235],"type":"Point"}
}