{
  "type": "Feature",
  "properties": {
    "addr:full":"13 Export Drv Ulverstone TAS 7315",
    "addr:housenumber":"13",
    "addr:postcode":"7315",
    "addr:street":"Export Drv",
    "iso:country":"AU",
    "sg:address":"13 Export Drv",
    "sg:city":"Ulverstone",
    "sg:classifiers":[
        {
            "category":"Professional",
            "subcategory":"Art Services",
            "type":"Services"
        }
    ],
    "sg:phone":"+61 3 6425 9372",
    "sg:postcode":"7315",
    "sg:province":"TAS",
    "sg:tags":[
        "decorator",
        "painter"
    ],
    "wof:name":"Smiths Painting & Sign Service",
    "wof:placetype":"venue"
},
  "geometry": {"coordinates":[146.202468872,-41.1557197571],"type":"Point"}
}