{
  "type": "Feature",
  "properties": {
    "addr:full":"PO Box 1127 Tuggeranong ACT 2901",
    "addr:postcode":"2901",
    "iso:country":"AU",
    "sg:address":"PO Box 1127",
    "sg:city":"Tuggeranong",
    "sg:classifiers":[
        {
            "category":"Building & Trades",
            "subcategory":"Construction",
            "type":"Services"
        }
    ],
    "sg:phone":"+61 2 6292 7552",
    "sg:postcode":"2901",
    "sg:province":"ACT",
    "sg:tags":[
        "earth",
        "excavating",
        "moving",
        "contractor"
    ],
    "wof:name":"Mino's Concreting & Excavation",
    "wof:placetype":"venue"
},
  "geometry": {"coordinates":[149.05650329599999,-35.4157295227],"type":"Point"}
}