{
  "type": "Feature",
  "properties": {
    "addr:full":"PO Box 32 Condong NSW 2484",
    "addr:postcode":"2484",
    "iso:country":"AU",
    "sg:address":"PO Box 32",
    "sg:city":"Condong",
    "sg:classifiers":[
        {
            "category":"Utilities",
            "subcategory":"Electric",
            "type":"Services"
        }
    ],
    "sg:phone":"+61 402 865 234",
    "sg:postcode":"2484",
    "sg:province":"NSW",
    "sg:tags":[
        "electrical",
        "contractor"
    ],
    "wof:name":"Ray Hobbs",
    "wof:placetype":"venue"
},
  "geometry": {"coordinates":[153.43702697800001,-28.3118591309],"type":"Point"}
}