{
  "type": "Feature",
  "properties": {
    "addr:full":"47 Idlewild Ave Aberfoyle Park SA 5159",
    "addr:housenumber":"47",
    "addr:postcode":"5159",
    "addr:street":"Idlewild Ave",
    "iso:country":"AU",
    "sg:address":"47 Idlewild Ave",
    "sg:city":"Aberfoyle Park",
    "sg:classifiers":[
        {
            "category":"Building & Trades",
            "subcategory":"Plumbing",
            "type":"Services"
        }
    ],
    "sg:phone":"+61 439 998 695",
    "sg:postcode":"5159",
    "sg:province":"SA",
    "sg:tags":[
        "plumber",
        "gasfitters"
    ],
    "wof:name":"WaterProof Plumbing",
    "wof:placetype":"venue"
},
  "geometry": {"coordinates":[138.588165283,-35.0771446228],"type":"Point"}
}