{
  "type": "Feature",
  "properties": {
    "iso:country":"AU",
    "sg:address":"Unit 1 95 Dorset Rd",
    "sg:city":"Ferntree Gully",
    "sg:classifiers":[
        {
            "category":"Wholesale",
            "subcategory":"Machinery & Supplies",
            "type":"Manufacturing & Wholesale Goods"
        }
    ],
    "sg:phone":"+61 3 9417 0086",
    "sg:postcode":"3156",
    "sg:province":"VIC",
    "sg:tags":[
        "chemist"
    ],
    "wof:name":"Chem-Pharm Wholesale Distributors",
    "wof:placetype":"venue"
},
  "geometry": {"coordinates":[145.28480529800001,-37.8744049072],"type":"Point"}
}