{
  "type": "Feature",
  "properties": {
    "addr:full":"22 Mandible St Alexandria NSW 2015",
    "addr:housenumber":"22",
    "addr:postcode":"2015",
    "addr:street":"Mandible St",
    "iso:country":"AU",
    "sg:address":"22 Mandible St",
    "sg:city":"Alexandria",
    "sg:classifiers":[
        {
            "category":"Professional",
            "subcategory":"Printing & Photocopies",
            "type":"Services"
        }
    ],
    "sg:phone":"+61 2 9310 4244",
    "sg:postcode":"2015",
    "sg:province":"NSW",
    "sg:tags":[
        "screen",
        "printer"
    ],
    "wof:name":"The Signboard Company",
    "wof:placetype":"venue"
},
  "geometry": {"coordinates":[151.19927978499999,-33.9051170349],"type":"Point"}
}