{
  "type": "Feature",
  "properties": {
    "addr:full":"21 Longfield St Stawell VIC 3380",
    "addr:housenumber":"21",
    "addr:postcode":"3380",
    "addr:street":"Longfield St",
    "iso:country":"AU",
    "sg:address":"21 Longfield St",
    "sg:city":"Stawell",
    "sg:classifiers":[
        {
            "category":"Travel",
            "subcategory":"Hotels & Motels",
            "type":"Entertainment"
        }
    ],
    "sg:phone":"+61 3 5358 2041",
    "sg:postcode":"3380",
    "sg:province":"VIC",
    "wof:name":"Motel Stawell",
    "wof:placetype":"venue"
},
  "geometry": {"coordinates":[142.761154175,-37.0624465942],"type":"Point"}
}