{
  "type": "Feature",
  "properties": {
    "iso:country":"AU",
    "sg:address":"Ariah St",
    "sg:city":"Ardlethan",
    "sg:classifiers":[
        {
            "category":"Travel",
            "subcategory":"Hotels & Motels",
            "type":"Entertainment"
        }
    ],
    "sg:phone":"+61 2 6978 2005",
    "sg:postcode":"2665",
    "sg:province":"NSW",
    "sg:tags":[
        "accommodation"
    ],
    "wof:name":"Palace Hotel",
    "wof:placetype":"venue"
},
  "geometry": {"coordinates":[146.90443420400001,-34.3581466675],"type":"Point"}
}