{
  "type": "Feature",
  "properties": {
    "iso:country":"AU",
    "sg:address":"26a George St",
    "sg:city":"Moe",
    "sg:classifiers":[
        {
            "category":"Building & Trades",
            "subcategory":"Construction",
            "type":"Services"
        }
    ],
    "sg:phone":"+61 3 5126 4320",
    "sg:postcode":"3825",
    "sg:province":"VIC",
    "sg:tags":[
        "contractor"
    ],
    "wof:name":"G & G Power Constructions Pty Ltd",
    "wof:placetype":"venue"
},
  "geometry": {"coordinates":[146.262924,-38.176159],"type":"Point"}
}