{
  "type": "Feature",
  "properties": {
    "addr:full":"Lower Parriwi Rd The Spit NSW 2088",
    "addr:postcode":"2088",
    "addr:street":"Parriwi Rd",
    "iso:country":"AU",
    "sg:address":"Lower Parriwi Rd",
    "sg:city":"The Spit",
    "sg:classifiers":[
        {
            "category":"Professional",
            "type":"Services"
        }
    ],
    "sg:phone":"+61 2 9969 0736",
    "sg:postcode":"2088",
    "sg:province":"NSW",
    "sg:tags":[
        "industrial",
        "commercial",
        "catering"
    ],
    "wof:name":"The Spit Harbourside Catering",
    "wof:placetype":"venue"
},
  "geometry": {"coordinates":[151.24710082999999,-33.8070030212],"type":"Point"}
}