{
  "type": "Feature",
  "properties": {
    "iso:country":"AU",
    "sg:address":"24 George St",
    "sg:city":"Moe",
    "sg:classifiers":[
        {
            "category":"Shopping",
            "subcategory":"Clothing, Apparel, & Fashions",
            "type":"Retail Goods"
        }
    ],
    "sg:phone":"+61 3 5127 5088",
    "sg:postcode":"3825",
    "sg:province":"VIC",
    "sg:tags":[
        "lady",
        "wear"
    ],
    "wof:name":"Marigold Boutique",
    "wof:placetype":"venue"
},
  "geometry": {"coordinates":[146.26312300000001,-38.176178],"type":"Point"}
}