{
  "type": "Feature",
  "properties": {
    "addr:full":"7 Wordie Pl Padstow NSW 2211",
    "addr:housenumber":"7",
    "addr:postcode":"2211",
    "addr:street":"Wordie Pl",
    "iso:country":"AU",
    "sg:address":"7 Wordie Pl",
    "sg:city":"Padstow",
    "sg:classifiers":[
        {
            "category":"Manufacturing",
            "subcategory":"Metals",
            "type":"Manufacturing & Wholesale Goods"
        }
    ],
    "sg:phone":"+61 2 9709 3522",
    "sg:postcode":"2211",
    "sg:province":"NSW",
    "sg:tags":[
        "steel",
        "fabricator",
        "mfrs"
    ],
    "wof:name":"Proline Steel Pty Ltd",
    "wof:placetype":"venue"
},
  "geometry": {"coordinates":[151.034424,-33.939198],"type":"Point"}
}