{
  "type": "Feature",
  "properties": {
    "iso:country":"AU",
    "sg:address":"291 Deception Bay Rd",
    "sg:city":"Deception Bay",
    "sg:classifiers":[
        {
            "category":"Retail",
            "subcategory":"Funeral Services",
            "type":"Services"
        }
    ],
    "sg:phone":"+61 7 3204 0617",
    "sg:postcode":"4508",
    "sg:province":"QLD",
    "sg:tags":[
        "director"
    ],
    "wof:name":"First Forest Funerals",
    "wof:placetype":"venue"
},
  "geometry": {"coordinates":[153.013748169,-27.18866539],"type":"Point"}
}