{
  "type": "Feature",
  "properties": {
    "addr:full":"Murray Valley Hwy Yarrawonga VIC 3730",
    "addr:postcode":"3730",
    "addr:street":"Valley Hwy",
    "iso:country":"AU",
    "sg:address":"Murray Valley Hwy",
    "sg:city":"Yarrawonga",
    "sg:classifiers":[
        {
            "category":"Food & Beverages",
            "subcategory":"Fruits & Vegetables",
            "type":"Retail Goods"
        }
    ],
    "sg:phone":"+61 3 5748 4291",
    "sg:postcode":"3730",
    "sg:province":"VIC",
    "sg:tags":[
        "grower"
    ],
    "wof:name":"Kelly Bros",
    "wof:placetype":"venue"
},
  "geometry": {"coordinates":[146.015533447,-36.014339447],"type":"Point"}
}