{
  "type": "Feature",
  "properties": {
    "addr:full":"246 Glen Osmond Rd Fullarton SA 5063",
    "addr:housenumber":"246",
    "addr:postcode":"5063",
    "addr:street":"Glen Osmond Rd",
    "iso:country":"AU",
    "sg:address":"246 Glen Osmond Rd",
    "sg:city":"Fullarton",
    "sg:classifiers":[
        {
            "category":"Insurance",
            "subcategory":"Hazard Insurance",
            "type":"Services"
        }
    ],
    "sg:phone":"+61 8 8379 5158",
    "sg:postcode":"5063",
    "sg:province":"SA",
    "sg:tags":[
        "fire",
        "accident",
        "marine"
    ],
    "wof:name":"Australian Aviation Underwriting Pool Pty Ltd",
    "wof:placetype":"venue"
},
  "geometry": {"coordinates":[138.63304138199999,-34.9510765076],"type":"Point"}
}