{
  "type": "Feature",
  "properties": {
    "addr:full":"245 Marion St Leichhardt NSW 2040",
    "addr:housenumber":"245",
    "addr:postcode":"2040",
    "addr:street":"Marion St",
    "iso:country":"AU",
    "sg:address":"245 Marion St",
    "sg:city":"Leichhardt",
    "sg:classifiers":[
        {
            "category":"Autos & Motor Vehicles",
            "subcategory":"Automobile Sales",
            "type":"Retail Goods"
        }
    ],
    "sg:phone":"+61 2 9568 0333",
    "sg:postcode":"2040",
    "sg:province":"NSW",
    "sg:tags":[
        "car",
        "new"
    ],
    "wof:name":"AMR Mazda",
    "wof:placetype":"venue"
},
  "geometry": {"coordinates":[151.14877300000001,-33.889263],"type":"Point"}
}