{
  "type": "Feature",
  "properties": {
    "addr:full":"Bldg J, Hawkesbury Rd Westmead NSW 2145",
    "addr:postcode":"2145",
    "addr:street":"Hawkesbury Rd",
    "iso:country":"AU",
    "sg:address":"Bldg J, Hawkesbury Rd",
    "sg:city":"Westmead",
    "sg:classifiers":[
        {
            "category":"Organizations",
            "subcategory":"Community Association",
            "type":"Services"
        }
    ],
    "sg:phone":"+61 2 9633 1988",
    "sg:postcode":"2145",
    "sg:province":"NSW",
    "sg:tags":[
        "organisation",
        "family",
        "welfare"
    ],
    "wof:name":"Association For The Welfare of Child Health",
    "wof:placetype":"venue"
},
  "geometry": {"coordinates":[150.98712158199999,-33.8080253601],"type":"Point"}
}