{
  "type": "Feature",
  "properties": {
    "iso:country":"AU",
    "sg:address":"3/ 10 Shoobra Rd",
    "sg:city":"Elsternwick",
    "sg:classifiers":[
        {
            "category":"Building & Trades",
            "subcategory":"Cleaning & Sanitation",
            "type":"Services"
        }
    ],
    "sg:phone":"+61 500 880 018",
    "sg:postcode":"3185",
    "sg:province":"VIC",
    "sg:tags":[
        "industrial",
        "commercial",
        "contractor"
    ],
    "wof:name":"Enviro-Serve Pty Ltd",
    "wof:placetype":"venue"
},
  "geometry": {"coordinates":[145.00831604000001,-37.8861694336],"type":"Point"}
}