{
  "type": "Feature",
  "properties": {
    "iso:country":"AU",
    "sg:address":"27 Glenelg Ave",
    "sg:city":"Mermaid Beach",
    "sg:classifiers":[
        {
            "category":"Building & Trades",
            "subcategory":"Construction",
            "type":"Services"
        }
    ],
    "sg:phone":"+61 7 5572 6535",
    "sg:postcode":"4218",
    "sg:province":"QLD",
    "sg:tags":[
        "waterproofing",
        "contractor"
    ],
    "wof:name":"Watson Waterproofing",
    "wof:placetype":"venue"
},
  "geometry": {"coordinates":[153.43328857399999,-28.0451507568],"type":"Point"}
}