{
  "type": "Feature",
  "properties": {
    "iso:country":"AU",
    "sg:address":"66- 84 High St",
    "sg:city":"Melton",
    "sg:classifiers":[
        {
            "category":"Government",
            "subcategory":"Department Of Motor Vehicles",
            "type":"Public Place"
        }
    ],
    "sg:phone":"+61 1300 651 888",
    "sg:postcode":"3337",
    "sg:province":"VIC",
    "sg:tags":[
        "wholesaler",
        "mfrs",
        "accessory"
    ],
    "wof:name":"MHG Plastic Industries (VIC) Pty Ltd",
    "wof:placetype":"venue"
},
  "geometry": {"coordinates":[144.587418,-37.682785],"type":"Point"}
}