{
  "type": "Feature",
  "properties": {
    "addr:full":"248 Williams Rd Toorak VIC 3142",
    "addr:housenumber":"248",
    "addr:postcode":"3142",
    "addr:street":"Williams Rd",
    "iso:country":"AU",
    "sg:address":"248 Williams Rd",
    "sg:city":"Toorak",
    "sg:classifiers":[
        {
            "category":"Professional",
            "subcategory":"Employment Agencies",
            "type":"Services"
        }
    ],
    "sg:phone":"+61 3 9827 7753",
    "sg:postcode":"3142",
    "sg:province":"VIC",
    "sg:tags":[
        "occupational",
        "therapist"
    ],
    "wof:name":"Bishop E A",
    "wof:placetype":"venue"
},
  "geometry": {"coordinates":[145.004364014,-37.8431282043],"type":"Point"}
}