{
  "type": "Feature",
  "properties": {
    "addr:full":"726 Darling St Rozelle NSW 2039",
    "addr:housenumber":"726",
    "addr:postcode":"2039",
    "addr:street":"Darling St",
    "iso:country":"AU",
    "sg:address":"726 Darling St",
    "sg:city":"Rozelle",
    "sg:classifiers":[
        {
            "category":"Travel",
            "subcategory":"Hotels & Motels",
            "type":"Entertainment"
        }
    ],
    "sg:phone":"+61 2 9555 7933",
    "sg:postcode":"2039",
    "sg:province":"NSW",
    "sg:tags":[
        "accommodation"
    ],
    "wof:name":"Red Lion Hotel",
    "wof:placetype":"venue"
},
  "geometry": {"coordinates":[151.16874694800001,-33.8648719788],"type":"Point"}
}