{
  "type": "Feature",
  "properties": {
    "addr:full":"385 Abercrombie St Darlington NSW 2008",
    "addr:housenumber":"385",
    "addr:postcode":"2008",
    "addr:street":"Abercrombie St",
    "iso:country":"AU",
    "sg:address":"385 Abercrombie St",
    "sg:city":"Darlington",
    "sg:classifiers":[
        {
            "category":"Education",
            "subcategory":"University",
            "type":"Public Place"
        }
    ],
    "sg:phone":"+61 2 9518 7596",
    "sg:postcode":"2008",
    "sg:province":"NSW",
    "sg:tags":[
        "educational",
        "organisation",
        "cultural"
    ],
    "wof:name":"Australian Jewish Historical Society The",
    "wof:placetype":"venue"
},
  "geometry": {"coordinates":[151.19041442899999,-33.8927764893],"type":"Point"}
}