{
  "type": "Feature",
  "properties": {
    "addr:full":"Lot 12 516 Forestry Rd Myalup WA 6220",
    "addr:housenumber":"516",
    "addr:postcode":"6220",
    "addr:street":"Forestry Rd",
    "iso:country":"AU",
    "sg:address":"Lot 12 516 Forestry Rd",
    "sg:city":"Myalup",
    "sg:classifiers":[
        {
            "category":"Home & Garden",
            "subcategory":"Garden Supply",
            "type":"Retail Goods"
        }
    ],
    "sg:phone":"+61 418 958 646",
    "sg:postcode":"6220",
    "sg:province":"WA",
    "sg:tags":[
        "turf",
        "lawn"
    ],
    "wof:name":"Coastal Green Turf Farm",
    "wof:placetype":"venue"
},
  "geometry": {"coordinates":[115.778839,-33.065643],"type":"Point"}
}