{
  "type": "Feature",
  "properties": {
    "iso:country":"AU",
    "sg:address":"40 Annerley Rd",
    "sg:city":"Woolloongabba",
    "sg:classifiers":[
        {
            "category":"Health Services",
            "subcategory":"Doctor",
            "type":"Services"
        }
    ],
    "sg:phone":"+61 7 3844 3239",
    "sg:postcode":"4102",
    "sg:province":"QLD",
    "sg:tags":[
        "medical",
        "practitioner"
    ],
    "wof:name":"Michaelides Chrys",
    "wof:placetype":"venue"
},
  "geometry": {"coordinates":[153.02882385300001,-27.4878559113],"type":"Point"}
}