{
  "type": "Feature",
  "properties": {
    "addr:full":"6 Cronulla Crt Slacks Creek QLD 4127",
    "addr:housenumber":"6",
    "addr:postcode":"4127",
    "addr:street":"Cronulla Crt",
    "iso:country":"AU",
    "sg:address":"6 Cronulla Crt",
    "sg:city":"Slacks Creek",
    "sg:classifiers":[
        {
            "category":"Government",
            "subcategory":"Department Of Motor Vehicles",
            "type":"Public Place"
        }
    ],
    "sg:phone":"+61 7 3808 1986",
    "sg:postcode":"4127",
    "sg:province":"QLD",
    "sg:tags":[
        "wholesaler",
        "mfrs",
        "accessory"
    ],
    "wof:name":"Performance Wholesale Australia Pty Ltd",
    "wof:placetype":"venue"
},
  "geometry": {"coordinates":[153.12059020999999,-27.6182327271],"type":"Point"}
}