{
  "type": "Feature",
  "properties": {
    "iso:country":"AU",
    "sg:address":"Hunsdon House 11 Council Ave",
    "sg:city":"Rockingham",
    "sg:classifiers":[
        {
            "category":"Health Services",
            "subcategory":"Dentist",
            "type":"Services"
        }
    ],
    "sg:phone":"+61 8 9592 2210",
    "sg:postcode":"6168",
    "sg:province":"WA",
    "wof:name":"Haines Amani",
    "wof:placetype":"venue"
},
  "geometry": {"coordinates":[115.74443100000001,-32.290882],"type":"Point"}
}