{
  "type": "Feature",
  "properties": {
    "addr:full":"46 Amy St Regents Park NSW 2143",
    "addr:housenumber":"46",
    "addr:postcode":"2143",
    "addr:street":"Amy St",
    "iso:country":"AU",
    "sg:address":"46 Amy St",
    "sg:city":"Regents Park",
    "sg:classifiers":[
        {
            "category":"Professional",
            "subcategory":"Accounting & Tax Preparation",
            "type":"Services"
        }
    ],
    "sg:phone":"+61 2 9644 2355",
    "sg:postcode":"2143",
    "sg:province":"NSW",
    "sg:tags":[
        "accountant",
        "auditor"
    ],
    "wof:name":"Raymond L Thompson & Co Pty Ltd",
    "wof:placetype":"venue"
},
  "geometry": {"coordinates":[151.02691650400001,-33.8840942383],"type":"Point"}
}