{
  "type": "Feature",
  "properties": {
    "iso:country":"AU",
    "sg:address":"PO Box 520",
    "sg:city":"Padstow",
    "sg:classifiers":[
        {
            "category":"Building & Trades",
            "subcategory":"Plumbing",
            "type":"Services"
        }
    ],
    "sg:phone":"+61 419 605 000",
    "sg:postcode":"2211",
    "sg:province":"NSW",
    "sg:tags":[
        "plumber",
        "gasfitters"
    ],
    "wof:name":"Lloyd White Plumbing",
    "wof:placetype":"venue"
},
  "geometry": {"coordinates":[151.032394,-33.952171],"type":"Point"}
}