{
  "type": "Feature",
  "properties": {
    "addr:full":"5 Begonia Crt Parafield Gardens SA 5107",
    "addr:housenumber":"5",
    "addr:postcode":"5107",
    "addr:street":"Begonia Crt",
    "iso:country":"AU",
    "sg:address":"5 Begonia Crt",
    "sg:city":"Parafield Gardens",
    "sg:classifiers":[
        {
            "category":"Home & Garden",
            "subcategory":"Garden Supply",
            "type":"Retail Goods"
        }
    ],
    "sg:phone":"+61 8 8258 8154",
    "sg:postcode":"5107",
    "sg:province":"SA",
    "sg:tags":[
        "equipment"
    ],
    "wof:name":"S.A. Latex Mould Makers",
    "wof:placetype":"venue"
},
  "geometry": {"coordinates":[138.61428832999999,-34.7778205872],"type":"Point"}
}