{
  "type": "Feature",
  "properties": {
    "iso:country":"AU",
    "sg:address":"33 Waverley Rd",
    "sg:city":"Malvern East",
    "sg:classifiers":[
        {
            "category":"Shopping",
            "subcategory":"Department Store",
            "type":"Retail Goods"
        }
    ],
    "sg:phone":"+61 3 9572 0319",
    "sg:postcode":"3145",
    "sg:province":"VIC",
    "sg:tags":[
        "wool"
    ],
    "wof:name":"Martas Yarns",
    "wof:placetype":"venue"
},
  "geometry": {"coordinates":[145.04354858400001,-37.8752632141],"type":"Point"}
}