{
  "type": "Feature",
  "properties": {
    "iso:country":"AU",
    "sg:address":"94 Ayr St",
    "sg:city":"Jamestown",
    "sg:classifiers":[
        {
            "category":"Building & Trades",
            "subcategory":"Pest Control",
            "type":"Services"
        }
    ],
    "sg:phone":"+61 8 8664 1479",
    "sg:postcode":"5491",
    "sg:province":"SA",
    "wof:name":"Northern Animal & Plant Control Board",
    "wof:placetype":"venue"
},
  "geometry": {"coordinates":[138.60253906200001,-33.2053985596],"type":"Point"}
}