{
  "type": "Feature",
  "properties": {
    "addr:full":"1131 Botany Rd Mascot NSW 2020",
    "addr:housenumber":"1131",
    "addr:postcode":"2020",
    "addr:street":"Botany Rd",
    "iso:country":"AU",
    "sg:address":"1131 Botany Rd",
    "sg:city":"Mascot",
    "sg:classifiers":[
        {
            "category":"Fast Food",
            "type":"Food & Drink"
        }
    ],
    "sg:phone":"+61 2 9317 4246",
    "sg:postcode":"2020",
    "sg:province":"NSW",
    "sg:tags":[
        "away",
        "take"
    ],
    "wof:name":"Ogalo Mascot",
    "wof:placetype":"venue"
},
  "geometry": {"coordinates":[151.194824219,-33.9294891357],"type":"Point"}
}