{
  "type": "Feature",
  "properties": {
    "iso:country":"AU",
    "sg:address":"185 Wakefield St",
    "sg:city":"Adelaide",
    "sg:classifiers":[
        {
            "category":"Banks & Credit Unions",
            "subcategory":"Financial Services",
            "type":"Services"
        }
    ],
    "sg:phone":"+61 8 8232 1645",
    "sg:postcode":"5000",
    "sg:province":"SA",
    "sg:tags":[
        "planning"
    ],
    "wof:name":"Future Link Financial Services",
    "wof:placetype":"venue"
},
  "geometry": {"coordinates":[138.60777282699999,-34.9284667969],"type":"Point"}
}