{
  "type": "Feature",
  "properties": {
    "iso:country":"AU",
    "sg:address":"128-130 Keys Road",
    "sg:city":"Moorabbin",
    "sg:classifiers":[
        {
            "category":"Manufacturing",
            "subcategory":"Motor Vehicles & Parts",
            "type":"Manufacturing & Wholesale Goods"
        }
    ],
    "sg:phone":"+61 3 9553 5969",
    "sg:postcode":"3189",
    "sg:province":"VIC",
    "sg:tags":[
        "replacement"
    ],
    "wof:name":"Lord Teds Automotive",
    "wof:placetype":"venue"
},
  "geometry": {"coordinates":[145.07496643100001,-37.9496536255],"type":"Point"}
}