{
  "type": "Feature",
  "properties": {
    "addr:full":"PO Box 461 Sylvania NSW 2224",
    "addr:postcode":"2224",
    "iso:country":"AU",
    "sg:address":"PO Box 461",
    "sg:city":"Sylvania",
    "sg:classifiers":[
        {
            "category":"Military Area",
            "subcategory":"Air Force Base",
            "type":"Public Place"
        }
    ],
    "sg:phone":"+61 2 9588 9960",
    "sg:postcode":"2224",
    "sg:province":"NSW",
    "sg:tags":[
        "box",
        "case",
        "wood"
    ],
    "wof:name":"Sydney Crating Service",
    "wof:placetype":"venue"
},
  "geometry": {"coordinates":[151.095993042,-34.0087585449],"type":"Point"}
}