{
  "type": "Feature",
  "properties": {
    "iso:country":"AU",
    "sg:address":"10 Gibraltar St",
    "sg:city":"Bungendore",
    "sg:classifiers":[
        {
            "category":"Arts & Performance",
            "subcategory":"Art Gallery",
            "type":"Entertainment"
        }
    ],
    "sg:phone":"+61 2 6238 1971",
    "sg:postcode":"2621",
    "sg:province":"NSW",
    "wof:name":"Kiku Arts",
    "wof:placetype":"venue"
},
  "geometry": {"coordinates":[149.43948364299999,-35.2538146973],"type":"Point"}
}