{
  "type": "Feature",
  "properties": {
    "addr:full":"69 Westmacott St Esperance WA 6450",
    "addr:housenumber":"69",
    "addr:postcode":"6450",
    "addr:street":"Westmacott St",
    "iso:country":"AU",
    "sg:address":"69 Westmacott St",
    "sg:city":"Esperance",
    "sg:classifiers":[
        {
            "category":"Autos & Motor Vehicles",
            "subcategory":"Fuel & Gas Station",
            "type":"Retail Goods"
        }
    ],
    "sg:phone":"+61 8 9071 2394",
    "sg:postcode":"6450",
    "sg:province":"WA",
    "wof:name":"Ampol",
    "wof:placetype":"venue"
},
  "geometry": {"coordinates":[121.91066741900001,-33.8380584717],"type":"Point"}
}