{
  "type": "Feature",
  "properties": {
    "addr:full":"Unit 5 Lucia Crt 3-5 Deakin St Brendale QLD 4500",
    "addr:housenumber":"3-5",
    "addr:postcode":"4500",
    "addr:street":"Lucia;Deakin St",
    "iso:country":"AU",
    "sg:address":"Unit 5 Lucia Crt 3-5 Deakin St",
    "sg:city":"Brendale",
    "sg:classifiers":[
        {
            "category":"Manufacturing",
            "subcategory":"Rubber & Plastics",
            "type":"Manufacturing & Wholesale Goods"
        }
    ],
    "sg:phone":"+61 7 3817 8100",
    "sg:postcode":"4500",
    "sg:province":"QLD",
    "sg:tags":[
        "moulders"
    ],
    "wof:name":"ACMA Industries Pty Ltd",
    "wof:placetype":"venue"
},
  "geometry": {"coordinates":[152.99154663100001,-27.3227043152],"type":"Point"}
}