{
  "type": "Feature",
  "properties": {
    "addr:full":"Shop 8, 24 Subiaco Square Rd Subiaco WA 6008",
    "addr:housenumber":"shop;24",
    "addr:postcode":"6008",
    "addr:street":"Subiaco Square Rd",
    "iso:country":"AU",
    "sg:address":"Shop 8, 24 Subiaco Square Rd",
    "sg:city":"Subiaco",
    "sg:classifiers":[
        {
            "category":"Personal",
            "subcategory":"Beauty Salon",
            "type":"Services"
        }
    ],
    "sg:phone":"+61 8 9381 7373",
    "sg:postcode":"6008",
    "sg:province":"WA",
    "sg:website":"http://www.stripwaxing.com.au",
    "wof:name":"Strip Womens Waxing Clinic",
    "wof:placetype":"venue"
},
  "geometry": {"coordinates":[115.824920654,-31.9463157654],"type":"Point"}
}