{
  "type": "Feature",
  "properties": {
    "iso:country":"AU",
    "sg:address":"17 Sunnyridge Rd",
    "sg:city":"Arcadia",
    "sg:classifiers":[
        {
            "category":"Building & Trades",
            "subcategory":"Construction",
            "type":"Services"
        }
    ],
    "sg:phone":"+61 2 9653 2130",
    "sg:postcode":"2159",
    "sg:province":"NSW",
    "sg:tags":[
        "contractor"
    ],
    "wof:name":"Leeuw Peter",
    "wof:placetype":"venue"
},
  "geometry": {"coordinates":[151.040405273,-33.6074829102],"type":"Point"}
}