{
  "type": "Feature",
  "properties": {
    "addr:full":"2/ 11 Monarch Crs Valentine NSW 2280",
    "addr:housenumber":"/ 11",
    "addr:postcode":"2280",
    "addr:street":"Monarch Crs",
    "iso:country":"AU",
    "sg:address":"2/ 11 Monarch Crs",
    "sg:city":"Valentine",
    "sg:classifiers":[
        {
            "category":"Building & Trades",
            "subcategory":"Construction",
            "type":"Services"
        }
    ],
    "sg:phone":"+61 404 028 478",
    "sg:postcode":"2280",
    "sg:province":"NSW",
    "sg:tags":[
        "rendering",
        "cement"
    ],
    "wof:name":"East Coast Coatings",
    "wof:placetype":"venue"
},
  "geometry": {"coordinates":[151.644287109,-33.0118789673],"type":"Point"}
}