{
  "type": "Feature",
  "properties": {
    "addr:full":"64 Kalaroo Rd Redhead NSW 2290",
    "addr:housenumber":"64",
    "addr:postcode":"2290",
    "addr:street":"Kalaroo Rd",
    "iso:country":"AU",
    "sg:address":"64 Kalaroo Rd",
    "sg:city":"Redhead",
    "sg:classifiers":[
        {
            "category":"Home & Garden",
            "subcategory":"Garden Supply",
            "type":"Retail Goods"
        }
    ],
    "sg:phone":"+61 2 4944 9355",
    "sg:postcode":"2290",
    "sg:province":"NSW",
    "sg:tags":[
        "landscape"
    ],
    "wof:name":"Drinkwater's Landscape Centre Pty Ltd",
    "wof:placetype":"venue"
},
  "geometry": {"coordinates":[151.69889831500001,-33.0167312622],"type":"Point"}
}