{
  "type": "Feature",
  "properties": {
    "addr:full":"99 East St Rockhampton QLD 4700",
    "addr:housenumber":"99",
    "addr:postcode":"4700",
    "addr:street":"East St",
    "iso:country":"AU",
    "sg:address":"99 East St",
    "sg:city":"Rockhampton",
    "sg:classifiers":[
        {
            "category":"Banks & Credit Unions",
            "subcategory":"Financial Services",
            "type":"Services"
        }
    ],
    "sg:phone":"+61 7 4922 8710",
    "sg:postcode":"4700",
    "sg:province":"QLD",
    "sg:tags":[
        "annuity",
        "rollover",
        "superannuation",
        "consultant"
    ],
    "wof:name":"Jeff Peers",
    "wof:placetype":"venue"
},
  "geometry": {"coordinates":[150.521286011,-23.3891086578],"type":"Point"}
}