{
  "type": "Feature",
  "properties": {
    "addr:full":"6 Norris Crt Moe VIC 3825",
    "addr:housenumber":"6",
    "addr:postcode":"3825",
    "addr:street":"Norris Crt",
    "iso:country":"AU",
    "sg:address":"6 Norris Crt",
    "sg:city":"Moe",
    "sg:classifiers":[
        {
            "category":"Professional",
            "subcategory":"Accounting & Tax Preparation",
            "type":"Services"
        }
    ],
    "sg:phone":"+61 3 5127 8545",
    "sg:postcode":"3825",
    "sg:province":"VIC",
    "sg:tags":[
        "accountant",
        "auditor"
    ],
    "wof:name":"Camtech Financial Services Pty Ltd",
    "wof:placetype":"venue"
},
  "geometry": {"coordinates":[146.28161600000001,-38.175724],"type":"Point"}
}