{
  "type": "Feature",
  "properties": {
    "addr:full":"15 Titanium Crt Crestmead QLD 4132",
    "addr:housenumber":"15",
    "addr:postcode":"4132",
    "addr:street":"Titanium Crt",
    "iso:country":"AU",
    "sg:address":"15 Titanium Crt",
    "sg:city":"Crestmead",
    "sg:classifiers":[
        {
            "category":"Manufacturing",
            "subcategory":"Tools & Machinery",
            "type":"Manufacturing & Wholesale Goods"
        }
    ],
    "sg:phone":"+61 7 3803 6222",
    "sg:postcode":"4132",
    "sg:province":"QLD",
    "sg:tags":[
        "toolmaker"
    ],
    "wof:name":"Marco Engineering Pty Ltd",
    "wof:placetype":"venue"
},
  "geometry": {"coordinates":[153.073654175,-27.6810150146],"type":"Point"}
}