{
  "type": "Feature",
  "properties": {
    "iso:country":"AU",
    "sg:address":"Waples Rd",
    "sg:city":"Farmborough Heights",
    "sg:classifiers":[
        {
            "category":"Education",
            "subcategory":"School",
            "type":"Public Place"
        }
    ],
    "sg:phone":"+61 2 4271 8124",
    "sg:postcode":"2526",
    "sg:province":"NSW",
    "sg:tags":[
        "co-educational"
    ],
    "wof:name":"Cedars Christian College",
    "wof:placetype":"venue"
},
  "geometry": {"coordinates":[150.81791687,-34.4536705017],"type":"Point"}
}