{
  "type": "Feature",
  "properties": {
    "addr:full":"1E Cullen St Cohuna VIC 3568",
    "addr:housenumber":"1e",
    "addr:postcode":"3568",
    "addr:street":"Cullen St",
    "iso:country":"AU",
    "sg:address":"1E Cullen St",
    "sg:city":"Cohuna",
    "sg:classifiers":[
        {
            "category":"Banks & Credit Unions",
            "subcategory":"Bank",
            "type":"Services"
        }
    ],
    "sg:phone":"+61 3 5456 2569",
    "sg:postcode":"3568",
    "sg:province":"VIC",
    "wof:name":"Bendigo Bank",
    "wof:placetype":"venue"
},
  "geometry": {"coordinates":[144.22027587900001,-35.8091621399],"type":"Point"}
}