{
  "type": "Feature",
  "properties": {
    "addr:full":"9 - 11 Traders Way Mt Isa QLD 4825",
    "addr:housenumber":"11",
    "addr:postcode":"4825",
    "addr:street":"9;Traders Way",
    "iso:country":"AU",
    "sg:address":"9 - 11 Traders Way",
    "sg:city":"Mt Isa",
    "sg:classifiers":[
        {
            "category":"Transit Center",
            "subcategory":"Freight",
            "type":"Transportation"
        }
    ],
    "sg:phone":"+61 7 4743 0322",
    "sg:postcode":"4825",
    "sg:province":"QLD",
    "sg:tags":[
        "forklift",
        "truck"
    ],
    "wof:name":"Outback Forklifts",
    "wof:placetype":"venue"
},
  "geometry": {"coordinates":[139.50256300000001,-20.705542],"type":"Point"}
}