{
  "type": "Feature",
  "properties": {
    "addr:full":"PO Box 544 Round Corner NSW 2158",
    "addr:postcode":"2158",
    "iso:country":"AU",
    "sg:address":"PO Box 544",
    "sg:city":"Round Corner",
    "sg:classifiers":[
        {
            "category":"Real Estate",
            "subcategory":"Developer",
            "type":"Services"
        }
    ],
    "sg:phone":"+61 2 9653 9082",
    "sg:postcode":"2158",
    "sg:province":"NSW",
    "sg:tags":[
        "development"
    ],
    "wof:name":"Lorebray",
    "wof:placetype":"venue"
},
  "geometry": {"coordinates":[151.01791381800001,-33.695098877],"type":"Point"}
}