{
  "type": "Feature",
  "properties": {
    "addr:full":"17 Sudbury St Darra QLD 4076",
    "addr:housenumber":"17",
    "addr:postcode":"4076",
    "addr:street":"Sudbury St",
    "iso:country":"AU",
    "sg:address":"17 Sudbury St",
    "sg:city":"Darra",
    "sg:classifiers":[
        {
            "category":"Shopping",
            "subcategory":"Computers & Home Electronics",
            "type":"Retail Goods"
        }
    ],
    "sg:phone":"+61 1800 628 258",
    "sg:postcode":"4076",
    "sg:province":"QLD",
    "sg:tags":[
        "hardware",
        "equipment"
    ],
    "wof:name":"DataComm Wholesale",
    "wof:placetype":"venue"
},
  "geometry": {"coordinates":[152.94578552199999,-27.5620536804],"type":"Point"}
}