{
  "type": "Feature",
  "properties": {
    "addr:full":"Cnr Hamel & Meadows Rds Mt Pritchard NSW 2170",
    "addr:postcode":"2170",
    "addr:street":"Cnr",
    "iso:country":"AU",
    "sg:address":"Cnr Hamel & Meadows Rds",
    "sg:city":"Mt Pritchard",
    "sg:classifiers":[
        {
            "category":"Health Services",
            "subcategory":"Doctor",
            "type":"Services"
        }
    ],
    "sg:phone":"+61 2 9823 9441",
    "sg:postcode":"2170",
    "sg:province":"NSW",
    "sg:tags":[
        "medical",
        "practitioner"
    ],
    "wof:name":"Ramanathan M S",
    "wof:placetype":"venue"
},
  "geometry": {"coordinates":[150.89544677699999,-33.9032058716],"type":"Point"}
}