{
  "type": "Feature",
  "properties": {
    "addr:full":"7/ 51 Kalman Drv Boronia VIC 3155",
    "addr:housenumber":"/ 51",
    "addr:postcode":"3155",
    "addr:street":"Kalman Drv",
    "iso:country":"AU",
    "sg:address":"7/ 51 Kalman Drv",
    "sg:city":"Boronia",
    "sg:classifiers":[
        {
            "category":"Community Center",
            "type":"Public Place"
        }
    ],
    "sg:phone":"+61 3 9729 5000",
    "sg:postcode":"3155",
    "sg:province":"VIC",
    "sg:tags":[
        "interference",
        "frequency",
        "radio",
        "screening"
    ],
    "sg:website":"http://www.faradayshielding.biz",
    "wof:name":"Faraday Shielding & Design",
    "wof:placetype":"venue"
},
  "geometry": {"coordinates":[145.29434204099999,-37.8352813721],"type":"Point"}
}