{
  "type": "Feature",
  "properties": {
    "addr:full":"Marina Mall Urangan QLD 4655",
    "addr:postcode":"4655",
    "iso:country":"AU",
    "sg:address":"Marina Mall",
    "sg:city":"Urangan",
    "sg:classifiers":[
        {
            "category":"Real Estate",
            "subcategory":"Real Estate Agent",
            "type":"Services"
        }
    ],
    "sg:phone":"+61 7 4125 2600",
    "sg:postcode":"4655",
    "sg:province":"QLD",
    "wof:name":"SeaSide Real Estate Pty Ltd",
    "wof:placetype":"venue"
},
  "geometry": {"coordinates":[152.908646,-25.293362],"type":"Point"}
}