{
  "type": "Feature",
  "properties": {
    "addr:full":"117 High St Lismore Heights NSW 2480",
    "addr:housenumber":"117",
    "addr:postcode":"2480",
    "addr:street":"High St",
    "iso:country":"AU",
    "sg:address":"117 High St",
    "sg:city":"Lismore Heights",
    "sg:classifiers":[
        {
            "category":"Fast Food",
            "type":"Food & Drink"
        }
    ],
    "sg:phone":"+61 2 6624 6544",
    "sg:postcode":"2480",
    "sg:province":"NSW",
    "sg:tags":[
        "away",
        "take"
    ],
    "wof:name":"The Cottage Stop",
    "wof:placetype":"venue"
},
  "geometry": {"coordinates":[153.294845581,-28.8031272888],"type":"Point"}
}