{
  "type": "Feature",
  "properties": {
    "addr:full":"4350 Midland Hwy Meredith VIC 3333",
    "addr:housenumber":"4350",
    "addr:postcode":"3333",
    "addr:street":"Midland Hwy",
    "iso:country":"AU",
    "sg:address":"4350 Midland Hwy",
    "sg:city":"Meredith",
    "sg:classifiers":[
        {
            "category":"Wholesale",
            "subcategory":"Farm Supplies",
            "type":"Manufacturing & Wholesale Goods"
        }
    ],
    "sg:phone":"+61 3 5286 1223",
    "sg:postcode":"3333",
    "sg:province":"VIC",
    "sg:tags":[
        "equipment"
    ],
    "wof:name":"Woolabrai P/L",
    "wof:placetype":"venue"
},
  "geometry": {"coordinates":[144.07749939000001,-37.8723907471],"type":"Point"}
}