{
  "type": "Feature",
  "properties": {
    "addr:full":"Unit 6 484 Graham St Port Melbourne VIC 3207",
    "addr:housenumber":"484",
    "addr:postcode":"3207",
    "addr:street":"Graham St",
    "iso:country":"AU",
    "sg:address":"Unit 6 484 Graham St",
    "sg:city":"Port Melbourne",
    "sg:classifiers":[
        {
            "category":"Wholesale",
            "subcategory":"Construction Materials",
            "type":"Manufacturing & Wholesale Goods"
        }
    ],
    "sg:phone":"+61 3 9646 5765",
    "sg:postcode":"3207",
    "sg:province":"VIC",
    "sg:tags":[
        "lift"
    ],
    "wof:name":"Senior Elevator Consultants",
    "wof:placetype":"venue"
},
  "geometry": {"coordinates":[144.932343,-37.831406],"type":"Point"}
}