{
  "type": "Feature",
  "properties": {
    "addr:full":"31 Bolewski St Bundaberg QLD 4670",
    "addr:housenumber":"31",
    "addr:postcode":"4670",
    "addr:street":"Bolewski St",
    "iso:country":"AU",
    "sg:address":"31 Bolewski St",
    "sg:city":"Bundaberg",
    "sg:classifiers":[
        {
            "category":"Retail",
            "subcategory":"Auto Repair",
            "type":"Services"
        }
    ],
    "sg:phone":"+61 7 4152 4477",
    "sg:postcode":"4670",
    "sg:province":"QLD",
    "sg:tags":[
        "beater",
        "painter",
        "panel"
    ],
    "wof:name":"Terry O'Shea Smash Repairs",
    "wof:placetype":"venue"
},
  "geometry": {"coordinates":[152.32131957999999,-24.8852596283],"type":"Point"}
}