{
  "type": "Feature",
  "properties": {
    "iso:country":"AU",
    "sg:address":"Lot 12 Union Rd",
    "sg:city":"Wandin North",
    "sg:classifiers":[
        {
            "category":"Health Services",
            "subcategory":"Doctor",
            "type":"Services"
        }
    ],
    "sg:phone":"+61 3 5964 2700",
    "sg:postcode":"3139",
    "sg:province":"VIC",
    "sg:tags":[
        "medical",
        "practitioner"
    ],
    "wof:name":"Chesney David Dr",
    "wof:placetype":"venue"
},
  "geometry": {"coordinates":[145.42741394000001,-37.7816238403],"type":"Point"}
}