{
  "type": "Feature",
  "properties": {
    "addr:full":"PO Box 3006 West Ipswich QLD 4305",
    "addr:postcode":"4305",
    "addr:street":"West",
    "iso:country":"AU",
    "sg:address":"PO Box 3006",
    "sg:city":"West Ipswich",
    "sg:phone":"+61 7 5460 9111",
    "sg:postcode":"4305",
    "sg:province":"QLD",
    "wof:name":"Smart Sewage Solutions Pty Ltd",
    "wof:placetype":"venue"
},
  "geometry": {"coordinates":[152.74986267099999,-27.6179790497],"type":"Point"}
}