{
  "type": "Feature",
  "properties": {
    "iso:country":"AU",
    "sg:address":"PO Box 1098",
    "sg:city":"Woodford",
    "sg:classifiers":[
        {
            "category":"Organizations",
            "subcategory":"Labor Organization",
            "type":"Services"
        }
    ],
    "sg:phone":"+61 7 5496 1998",
    "sg:postcode":"4514",
    "sg:province":"QLD",
    "sg:tags":[
        "dust",
        "fume",
        "control",
        "equipment"
    ],
    "wof:name":"Fume Extraction Services",
    "wof:placetype":"venue"
},
  "geometry": {"coordinates":[152.774216,-26.948231],"type":"Point"}
}