{
  "type": "Feature",
  "properties": {
    "iso:country":"AU",
    "sg:address":"65 Brewer St",
    "sg:city":"Perth",
    "sg:classifiers":[
        {
            "category":"Professional",
            "subcategory":"Accounting & Tax Preparation",
            "type":"Services"
        }
    ],
    "sg:phone":"+61 8 9328 6644",
    "sg:postcode":"6000",
    "sg:province":"WA",
    "sg:tags":[
        "broom",
        "brush"
    ],
    "wof:name":"Hodge E F & Co",
    "wof:placetype":"venue"
},
  "geometry": {"coordinates":[115.867988586,-31.9462203979],"type":"Point"}
}