{
  "type": "Feature",
  "properties": {
    "addr:full":"26 Precision St Salisbury QLD 4107",
    "addr:housenumber":"26",
    "addr:postcode":"4107",
    "addr:street":"Precision St",
    "iso:country":"AU",
    "sg:address":"26 Precision St",
    "sg:city":"Salisbury",
    "sg:classifiers":[
        {
            "category":"Shopping",
            "subcategory":"Gifts & Souvenirs",
            "type":"Retail Goods"
        }
    ],
    "sg:phone":"+61 7 3275 2558",
    "sg:postcode":"4107",
    "sg:province":"QLD",
    "sg:tags":[
        "shop",
        "supply"
    ],
    "wof:name":"Sasando Traders",
    "wof:placetype":"venue"
},
  "geometry": {"coordinates":[153.02940368599999,-27.5464801788],"type":"Point"}
}