{
  "type": "Feature",
  "properties": {
    "iso:country":"AU",
    "sg:address":"16 King Edward Rd",
    "sg:city":"Osborne Park",
    "sg:classifiers":[
        {
            "category":"Bars & Pubs",
            "subcategory":"Lounge",
            "type":"Food & Drink"
        }
    ],
    "sg:phone":"+61 8 9244 4486",
    "sg:postcode":"6017",
    "sg:province":"WA",
    "sg:tags":[
        "water",
        "filter",
        "drinking"
    ],
    "sg:website":"http://www.sinkwarehouse.com.au",
    "wof:name":"The Sink Warehouse",
    "wof:placetype":"venue"
},
  "geometry": {"coordinates":[115.81098938,-31.9114570618],"type":"Point"}
}