{
  "type": "Feature",
  "properties": {
    "addr:full":"287 Pennant Hills Rd Carlingford NSW 2118",
    "addr:housenumber":"287",
    "addr:postcode":"2118",
    "addr:street":"Pennant Hills Rd",
    "iso:country":"AU",
    "sg:address":"287 Pennant Hills Rd",
    "sg:city":"Carlingford",
    "sg:classifiers":[
        {
            "category":"Utilities",
            "subcategory":"Electric",
            "type":"Services"
        }
    ],
    "sg:phone":"+61 2 9873 4699",
    "sg:postcode":"2118",
    "sg:province":"NSW",
    "sg:tags":[
        "electrical",
        "contractor"
    ],
    "wof:name":"M J B Electrical Pty Ltd",
    "wof:placetype":"venue"
},
  "geometry": {"coordinates":[151.05213928200001,-33.7794685364],"type":"Point"}
}