{
  "type": "Feature",
  "properties": {
    "addr:full":"6 Corella St Doncaster VIC 3108",
    "addr:housenumber":"6",
    "addr:postcode":"3108",
    "addr:street":"Corella St",
    "iso:country":"AU",
    "sg:address":"6 Corella St",
    "sg:city":"Doncaster",
    "sg:classifiers":[
        {
            "category":"Professional",
            "subcategory":"Engineering",
            "type":"Services"
        }
    ],
    "sg:phone":"+61 3 9848 2751",
    "sg:postcode":"3108",
    "sg:province":"VIC",
    "sg:tags":[
        "consulting",
        "engineer"
    ],
    "wof:name":"HVAC Consultants Pty Ltd",
    "wof:placetype":"venue"
},
  "geometry": {"coordinates":[145.13546752900001,-37.7810592651],"type":"Point"}
}