{
  "type": "Feature",
  "properties": {
    "iso:country":"AU",
    "sg:address":"7 Howard Rd",
    "sg:city":"Padstow",
    "sg:classifiers":[
        {
            "category":"Health Services",
            "subcategory":"Chiropractor",
            "type":"Services"
        }
    ],
    "sg:phone":"+61 2 9792 3135",
    "sg:postcode":"2211",
    "sg:province":"NSW",
    "wof:name":"Padstow Chiropractic Centre",
    "wof:placetype":"venue"
},
  "geometry": {"coordinates":[151.03421,-33.953159],"type":"Point"}
}