{
  "type": "Feature",
  "properties": {
    "addr:full":"22 Jarick St Wagga Wagga NSW 2650",
    "addr:housenumber":"22",
    "addr:postcode":"2650",
    "addr:street":"Jarick St",
    "iso:country":"AU",
    "sg:address":"22 Jarick St",
    "sg:city":"Wagga Wagga",
    "sg:classifiers":[
        {
            "category":"Retail",
            "subcategory":"Repair Shop",
            "type":"Services"
        }
    ],
    "sg:phone":"+61 412 573 033",
    "sg:postcode":"2650",
    "sg:province":"NSW",
    "sg:tags":[
        "stove",
        "part",
        "range"
    ],
    "wof:name":"Wayne Cottrill Electrical",
    "wof:placetype":"venue"
},
  "geometry": {"coordinates":[147.36033630399999,-35.1244506836],"type":"Point"}
}