{
  "type": "Feature",
  "properties": {
    "addr:full":"268 Prospect Rd Prospect SA 5082",
    "addr:housenumber":"268",
    "addr:postcode":"5082",
    "addr:street":"Prospect Rd",
    "iso:country":"AU",
    "sg:address":"268 Prospect Rd",
    "sg:city":"Prospect",
    "sg:classifiers":[
        {
            "category":"Wholesale",
            "subcategory":"Construction Materials",
            "type":"Manufacturing & Wholesale Goods"
        }
    ],
    "sg:phone":"+61 8 8269 5744",
    "sg:postcode":"5082",
    "sg:province":"SA",
    "sg:tags":[
        "wholesaler",
        "lighting",
        "mfrs",
        "accessory"
    ],
    "wof:name":"Tranden Holdings Pty Ltd",
    "wof:placetype":"venue"
},
  "geometry": {"coordinates":[138.593063355,-34.8752746582],"type":"Point"}
}