{
  "type": "Feature",
  "properties": {
    "iso:country":"AU",
    "sg:address":"256 Main Rd",
    "sg:city":"McLaren Vale",
    "sg:classifiers":[
        {
            "category":"Wholesale",
            "subcategory":"Farm Supplies",
            "type":"Manufacturing & Wholesale Goods"
        }
    ],
    "sg:phone":"+61 8 8323 9144",
    "sg:postcode":"5171",
    "sg:province":"SA",
    "sg:tags":[
        "feed",
        "supplement",
        "stock"
    ],
    "wof:name":"Walkers McLaren Vale Saddlery, Stock Feeds & Pet Supplies",
    "wof:placetype":"venue"
},
  "geometry": {"coordinates":[138.530426025,-35.2095489502],"type":"Point"}
}