{
  "type": "Feature",
  "properties": {
    "iso:country":"AU",
    "sg:address":"278 Illawarra Rd",
    "sg:city":"Marrickville",
    "sg:classifiers":[
        {
            "category":"Food & Beverages",
            "subcategory":"Supermarket",
            "type":"Retail Goods"
        }
    ],
    "sg:phone":"+61 2 9559 7495",
    "sg:postcode":"2204",
    "sg:province":"NSW",
    "sg:tags":[
        "grocery",
        "store"
    ],
    "wof:name":"Crazy Coffee & Nuts",
    "wof:placetype":"venue"
},
  "geometry": {"coordinates":[151.155014,-33.911713],"type":"Point"}
}