{
  "type": "Feature",
  "properties": {
    "addr:full":"Shop 25 Broadway Fair Nedlands WA 6009",
    "addr:housenumber":"shop 25",
    "addr:postcode":"6009",
    "addr:street":"Broadway Fair",
    "iso:country":"AU",
    "sg:address":"Shop 25 Broadway Fair",
    "sg:city":"Nedlands",
    "sg:classifiers":[
        {
            "category":"Health Services",
            "subcategory":"Optometrist",
            "type":"Services"
        }
    ],
    "sg:phone":"+61 8 9386 8581",
    "sg:postcode":"6009",
    "sg:province":"WA",
    "wof:name":"Lourie Julie",
    "wof:placetype":"venue"
},
  "geometry": {"coordinates":[115.81392700000001,-31.978102],"type":"Point"}
}