{
  "type": "Feature",
  "properties": {
    "iso:country":"AU",
    "sg:address":"552 Victoria St",
    "sg:city":"North Melbourne",
    "sg:classifiers":[
        {
            "category":"Organizations",
            "subcategory":"Non-profit Organization",
            "type":"Services"
        }
    ],
    "sg:phone":"+61 1800 685 105",
    "sg:postcode":"3051",
    "sg:province":"VIC",
    "sg:tags":[
        "support",
        "disability",
        "organisation"
    ],
    "sg:website":"http://www.wiseemployment.com.au",
    "wof:name":"WISE Employment",
    "wof:placetype":"venue"
},
  "geometry": {"coordinates":[144.94447326700001,-37.8002243042],"type":"Point"}
}