{
  "type": "Feature",
  "properties": {
    "addr:full":"21 Bobuck Drv Thredbo Village NSW 2625",
    "addr:housenumber":"21",
    "addr:postcode":"2625",
    "addr:street":"Bobuck Drv",
    "iso:country":"AU",
    "sg:address":"21 Bobuck Drv",
    "sg:city":"Thredbo Village",
    "sg:classifiers":[
        {
            "category":"Sports & Exercise",
            "subcategory":"Ski Slope",
            "type":"Entertainment"
        }
    ],
    "sg:phone":"+61 2 6457 6252",
    "sg:postcode":"2625",
    "sg:province":"NSW",
    "sg:tags":[
        "equipment",
        "hire",
        "retail",
        "snow"
    ],
    "wof:name":"Michelles Apartments",
    "wof:placetype":"venue"
},
  "geometry": {"coordinates":[148.30940246599999,-36.5033073425],"type":"Point"}
}