{
  "type": "Feature",
  "properties": {
    "addr:full":"3 Charles St Camperdown VIC 3260",
    "addr:housenumber":"3",
    "addr:postcode":"3260",
    "addr:street":"Charles St",
    "iso:country":"AU",
    "sg:address":"3 Charles St",
    "sg:city":"Camperdown",
    "sg:classifiers":[
        {
            "category":"Home & Garden",
            "subcategory":"Building Materials",
            "type":"Retail Goods"
        }
    ],
    "sg:phone":"+61 419 584 765",
    "sg:postcode":"3260",
    "sg:province":"VIC",
    "sg:tags":[
        "lawn",
        "cutting",
        "maintenance"
    ],
    "wof:name":"Dingle Eric W",
    "wof:placetype":"venue"
},
  "geometry": {"coordinates":[143.14523315400001,-38.242767334],"type":"Point"}
}