{
  "type": "Feature",
  "properties": {
    "addr:full":"211a Invermay Rd Invermay TAS 7248",
    "addr:housenumber":"211a",
    "addr:postcode":"7248",
    "addr:street":"Invermay Rd",
    "iso:country":"AU",
    "sg:address":"211a Invermay Rd",
    "sg:city":"Invermay",
    "sg:classifiers":[
        {
            "category":"Professional",
            "subcategory":"Accounting & Tax Preparation",
            "type":"Services"
        }
    ],
    "sg:phone":"+61 3 6326 6255",
    "sg:postcode":"7248",
    "sg:province":"TAS",
    "sg:tags":[
        "consultant",
        "taxation"
    ],
    "wof:name":"Cradix Business Managers and Accountants",
    "wof:placetype":"venue"
},
  "geometry": {"coordinates":[147.13458251899999,-41.4189605713],"type":"Point"}
}