{
  "type": "Feature",
  "properties": {
    "addr:full":"Shop 2/ 34 Oatley Ave Oatley NSW 2223",
    "addr:housenumber":"shop 2 / 34",
    "addr:postcode":"2223",
    "addr:street":"Oatley Ave",
    "iso:country":"AU",
    "sg:address":"Shop 2/ 34 Oatley Ave",
    "sg:city":"Oatley",
    "sg:classifiers":[
        {
            "category":"Food & Beverages",
            "subcategory":"Bakery",
            "type":"Retail Goods"
        }
    ],
    "sg:phone":"+61 2 9580 4133",
    "sg:postcode":"2223",
    "sg:province":"NSW",
    "sg:tags":[
        "cake",
        "shop",
        "pastry"
    ],
    "wof:name":"Oatley Village Pie Shop",
    "wof:placetype":"venue"
},
  "geometry": {"coordinates":[151.08033752399999,-33.9817695618],"type":"Point"}
}