{
  "type": "Feature",
  "properties": {
    "addr:full":"Central West Business Park Building 24, South Rd Braybrook VIC 3019",
    "addr:housenumber":"24",
    "addr:postcode":"3019",
    "addr:street":"South Rd",
    "iso:country":"AU",
    "sg:address":"Central West Business Park Building 24, South Rd",
    "sg:city":"Braybrook",
    "sg:classifiers":[
        {
            "category":"Retail",
            "subcategory":"Auto Rental",
            "type":"Services"
        }
    ],
    "sg:phone":"+61 1800 331 454",
    "sg:postcode":"3019",
    "sg:province":"VIC",
    "sg:tags":[
        "car",
        "hire",
        "minibus"
    ],
    "wof:name":"Britz Campervan, Car & 4WD Rentals",
    "wof:placetype":"venue"
},
  "geometry": {"coordinates":[144.85942077600001,-37.7921676636],"type":"Point"}
}