{
  "type": "Feature",
  "properties": {
    "iso:country":"AU",
    "sg:address":"180 Main St",
    "sg:city":"Proserpine",
    "sg:classifiers":[
        {
            "category":"Retail",
            "subcategory":"Repair Shop",
            "type":"Services"
        }
    ],
    "sg:phone":"+61 7 4945 1199",
    "sg:postcode":"4800",
    "sg:province":"QLD",
    "sg:tags":[
        "windscreen"
    ],
    "wof:name":"Advanced Windscreens",
    "wof:placetype":"venue"
},
  "geometry": {"coordinates":[148.59109497099999,-20.4044628143],"type":"Point"}
}