{
  "type": "Feature",
  "properties": {
    "addr:full":"70 Froude St Banyo QLD 4014",
    "addr:housenumber":"70",
    "addr:postcode":"4014",
    "addr:street":"Froude St",
    "iso:country":"AU",
    "sg:address":"70 Froude St",
    "sg:city":"Banyo",
    "sg:classifiers":[
        {
            "category":"Utilities",
            "subcategory":"Water",
            "type":"Services"
        }
    ],
    "sg:phone":"+61 7 3267 6952",
    "sg:postcode":"4014",
    "sg:province":"QLD",
    "sg:tags":[
        "hot",
        "system"
    ],
    "wof:name":"Denaro E J & Sons",
    "wof:placetype":"venue"
},
  "geometry": {"coordinates":[153.07354736299999,-27.3725852966],"type":"Point"}
}