{
  "type": "Feature",
  "properties": {
    "iso:country":"AU",
    "sg:address":"Level 1 75 Doncaster Rd",
    "sg:city":"Balwyn North",
    "sg:classifiers":[
        {
            "category":"Retail",
            "subcategory":"Auto Repair",
            "type":"Services"
        }
    ],
    "sg:phone":"+61 3 9850 8074",
    "sg:postcode":"3104",
    "sg:province":"VIC",
    "sg:tags":[
        "beater",
        "painter",
        "panel"
    ],
    "wof:name":"Complete Collision Bulleen",
    "wof:placetype":"venue"
},
  "geometry": {"coordinates":[145.071212769,-37.7925682068],"type":"Point"}
}