{
  "type": "Feature",
  "properties": {
    "addr:full":"14 King St Prospect SA 5082",
    "addr:housenumber":"14",
    "addr:postcode":"5082",
    "addr:street":"King St",
    "iso:country":"AU",
    "sg:address":"14 King St",
    "sg:city":"Prospect",
    "sg:classifiers":[
        {
            "category":"Building & Trades",
            "subcategory":"Construction",
            "type":"Services"
        }
    ],
    "sg:phone":"+61 412 719 303",
    "sg:postcode":"5082",
    "sg:province":"SA",
    "sg:tags":[
        "joiner",
        "carpenter"
    ],
    "wof:name":"Page Robert J",
    "wof:placetype":"venue"
},
  "geometry": {"coordinates":[138.58651733400001,-34.8766784668],"type":"Point"}
}