{
  "type": "Feature",
  "properties": {
    "addr:full":"Cnr Mary St and Gibson Rd Noosaville QLD 4566",
    "addr:postcode":"4566",
    "addr:street":"Cnr Mary St;Gibson Rd",
    "iso:country":"AU",
    "sg:address":"Cnr Mary St and Gibson Rd",
    "sg:city":"Noosaville",
    "sg:classifiers":[
        {
            "category":"Retail",
            "subcategory":"Event Space",
            "type":"Services"
        }
    ],
    "sg:phone":"+61 7 5430 5555",
    "sg:postcode":"4566",
    "sg:province":"QLD",
    "sg:tags":[
        "venue",
        "reception",
        "wedding"
    ],
    "wof:name":"Villa Noosa Hotel",
    "wof:placetype":"venue"
},
  "geometry": {"coordinates":[153.06246948200001,-26.3998737335],"type":"Point"}
}