{
  "type": "Feature",
  "properties": {
    "addr:full":"51 Ninth Ave St Lucia QLD 4067",
    "addr:housenumber":"51",
    "addr:postcode":"4067",
    "addr:street":"Ninth Ave",
    "iso:country":"AU",
    "sg:address":"51 Ninth Ave",
    "sg:city":"St Lucia",
    "sg:classifiers":[
        {
            "category":"Health Services",
            "subcategory":"Health Practitioner",
            "type":"Services"
        }
    ],
    "sg:phone":"+61 7 3371 6987",
    "sg:postcode":"4067",
    "sg:province":"QLD",
    "sg:tags":[
        "consultant",
        "conservation",
        "hearing"
    ],
    "wof:name":"Rintel Derek",
    "wof:placetype":"venue"
},
  "geometry": {"coordinates":[152.99974060100001,-27.5019302368],"type":"Point"}
}