{
  "type": "Feature",
  "properties": {
    "addr:full":"62 Leak St Forrestdale WA 6112",
    "addr:housenumber":"62",
    "addr:postcode":"6112",
    "addr:street":"Leak St",
    "iso:country":"AU",
    "sg:address":"62 Leak St",
    "sg:city":"Forrestdale",
    "sg:classifiers":[
        {
            "category":"Farming",
            "subcategory":"Farm & Veterinary Services",
            "type":"Manufacturing & Wholesale Goods"
        }
    ],
    "sg:phone":"+61 8 9397 2255",
    "sg:postcode":"6112",
    "sg:province":"WA",
    "sg:tags":[
        "blacksmith",
        "farrier"
    ],
    "wof:name":"Linden Maney",
    "wof:placetype":"venue"
},
  "geometry": {"coordinates":[115.947662353,-32.1507415771],"type":"Point"}
}