{
  "type": "Feature",
  "properties": {
    "iso:country":"AU",
    "sg:address":"282 Bridge Rd",
    "sg:city":"Richmond",
    "sg:classifiers":[
        {
            "category":"Fast Food",
            "type":"Food & Drink"
        }
    ],
    "sg:phone":"+61 3 9429 9649",
    "sg:postcode":"3121",
    "sg:province":"VIC",
    "sg:tags":[
        "away",
        "take"
    ],
    "wof:name":"Palm Sugar Royal Thai",
    "wof:placetype":"venue"
},
  "geometry": {"coordinates":[145.00050354000001,-37.8187980652],"type":"Point"}
}