{
  "type": "Feature",
  "properties": {
    "iso:country":"AU",
    "sg:address":"1211 Binni Creek Rd",
    "sg:city":"Cowra",
    "sg:classifiers":[
        {
            "category":"Shopping",
            "type":"Retail Goods"
        }
    ],
    "sg:phone":"+61 2 6342 8413",
    "sg:postcode":"2794",
    "sg:province":"NSW",
    "sg:tags":[
        "agent",
        "stock"
    ],
    "wof:name":"Clements G A",
    "wof:placetype":"venue"
},
  "geometry": {"coordinates":[148.692306519,-33.8278236389],"type":"Point"}
}