{
  "type": "Feature",
  "properties": {
    "addr:full":"11 Coulthard Crt Alice Springs NT 0870",
    "addr:housenumber":"11",
    "addr:postcode":"nt 0870",
    "addr:street":"Coulthard Crt",
    "iso:country":"AU",
    "sg:address":"11 Coulthard Crt",
    "sg:city":"Alice Springs",
    "sg:classifiers":[
        {
            "category":"Building & Trades",
            "subcategory":"Construction",
            "type":"Services"
        }
    ],
    "sg:phone":"+61 8 8952 0399",
    "sg:postcode":"0870",
    "sg:province":"NT",
    "sg:tags":[
        "joiner",
        "carpenter"
    ],
    "wof:name":"Prestige Cabinets Pty Ltd",
    "wof:placetype":"venue"
},
  "geometry": {"coordinates":[133.866363525,-23.6948242188],"type":"Point"}
}