{
  "type": "Feature",
  "properties": {
    "iso:country":"AU",
    "sg:address":"8 Fleming St",
    "sg:city":"Oberon",
    "sg:classifiers":[
        {
            "category":"Professional",
            "subcategory":"Engineering",
            "type":"Services"
        }
    ],
    "sg:phone":"+61 2 6336 0003",
    "sg:postcode":"2787",
    "sg:province":"NSW",
    "sg:tags":[
        "engineer"
    ],
    "wof:name":"MRD Engineering",
    "wof:placetype":"venue"
},
  "geometry": {"coordinates":[149.855636597,-33.7042121887],"type":"Point"}
}