{
  "type": "Feature",
  "properties": {
    "addr:full":"Shop 2-107 Mount St North Sydney NSW 2060",
    "addr:housenumber":"2-107",
    "addr:postcode":"2060",
    "addr:street":"Mount St",
    "iso:country":"AU",
    "sg:address":"Shop 2-107 Mount St",
    "sg:city":"North Sydney",
    "sg:classifiers":[
        {
            "category":"Personal",
            "subcategory":"Beauty Salon",
            "type":"Services"
        }
    ],
    "sg:phone":"+61 2 9955 4068",
    "sg:postcode":"2060",
    "sg:province":"NSW",
    "sg:tags":[
        "hairdresser"
    ],
    "wof:name":"Pyramidz Hair & Beauty",
    "wof:placetype":"venue"
},
  "geometry": {"coordinates":[151.20451355,-33.8386077881],"type":"Point"}
}