{
  "type": "Feature",
  "properties": {
    "iso:country":"AU",
    "sg:address":"1 Drummond Pl",
    "sg:city":"West Perth",
    "sg:classifiers":[
        {
            "category":"Professional",
            "subcategory":"Business Services",
            "type":"Services"
        }
    ],
    "sg:phone":"+61 8 9328 4888",
    "sg:postcode":"6005",
    "sg:province":"WA",
    "sg:tags":[
        "record",
        "management",
        "storage"
    ],
    "wof:name":"CTI Records Management",
    "wof:placetype":"venue"
},
  "geometry": {"coordinates":[115.84677886999999,-31.9409503937],"type":"Point"}
}