{
  "type": "Feature",
  "properties": {
    "addr:full":"Von Bibra's Rd Gawler TAS 7315",
    "addr:postcode":"7315",
    "addr:street":"Von Bibra'S Rd",
    "iso:country":"AU",
    "sg:address":"Von Bibra's Rd",
    "sg:city":"Gawler",
    "sg:classifiers":[
        {
            "category":"Commercial Area",
            "type":"Public Place"
        }
    ],
    "sg:phone":"+61 3 6425 2163",
    "sg:postcode":"7315",
    "sg:province":"TAS",
    "sg:tags":[
        "heavy",
        "carrier"
    ],
    "wof:name":"Wright R J & A J",
    "wof:placetype":"venue"
},
  "geometry": {"coordinates":[146.158493042,-41.1527328491],"type":"Point"}
}