{
  "type": "Feature",
  "properties": {
    "addr:full":"U4/ 14 Nello Pl Wetherill Park NSW 2164",
    "addr:housenumber":"14",
    "addr:postcode":"2164",
    "addr:street":"U4 /;Pl",
    "iso:country":"AU",
    "sg:address":"U4/ 14 Nello Pl",
    "sg:city":"Wetherill Park",
    "sg:classifiers":[
        {
            "category":"Shopping",
            "subcategory":"Stationery & Office Supplies",
            "type":"Retail Goods"
        }
    ],
    "sg:phone":"+61 2 9604 4950",
    "sg:postcode":"2164",
    "sg:province":"NSW",
    "sg:tags":[
        "packaging",
        "material"
    ],
    "sg:website":"http://www.netpak.com.au",
    "wof:name":"Netpak Pty Ltd",
    "wof:placetype":"venue"
},
  "geometry": {"coordinates":[150.89378356899999,-33.8504104614],"type":"Point"}
}