{
  "type": "Feature",
  "properties": {
    "addr:full":"Shop 1 / Kootingal NSW 2352",
    "addr:housenumber":"shop 1 /",
    "addr:postcode":"2352",
    "iso:country":"AU",
    "sg:address":"Shop 1",
    "sg:city":"/ Kootingal",
    "sg:classifiers":[
        {
            "category":"Fast Food",
            "type":"Food & Drink"
        }
    ],
    "sg:phone":"+61 2 6760 5080",
    "sg:postcode":"2352",
    "sg:province":"NSW",
    "sg:tags":[
        "away",
        "take"
    ],
    "wof:name":"Kootingal Tucker Box",
    "wof:placetype":"venue"
},
  "geometry": {"coordinates":[151.04945373499999,-31.0528793335],"type":"Point"}
}