{
  "type": "Feature",
  "properties": {
    "addr:full":"Factory 2 Pentecost Rd Mornington VIC 3931",
    "addr:housenumber":"2",
    "addr:postcode":"3931",
    "addr:street":"Pentecost Rd",
    "iso:country":"AU",
    "sg:address":"Factory 2 Pentecost Rd",
    "sg:city":"Mornington",
    "sg:classifiers":[
        {
            "category":"Home & Garden",
            "subcategory":"Building Materials",
            "type":"Retail Goods"
        }
    ],
    "sg:phone":"+61 3 5975 5088",
    "sg:postcode":"3931",
    "sg:province":"VIC",
    "sg:tags":[
        "plaster",
        "plasterboard",
        "supply"
    ],
    "wof:name":"Stewart's Plaster",
    "wof:placetype":"venue"
},
  "geometry": {"coordinates":[145.04905700699999,-38.2275276184],"type":"Point"}
}