{
  "type": "Feature",
  "properties": {
    "addr:full":"26 Sleigh Pl Wetherill Park NSW 2164",
    "addr:housenumber":"26",
    "addr:postcode":"2164",
    "addr:street":"Sleigh Pl",
    "iso:country":"AU",
    "sg:address":"26 Sleigh Pl",
    "sg:city":"Wetherill Park",
    "sg:classifiers":[
        {
            "category":"Transit Center",
            "subcategory":"Freight",
            "type":"Transportation"
        }
    ],
    "sg:phone":"+61 2 9756 0050",
    "sg:postcode":"2164",
    "sg:province":"NSW",
    "sg:tags":[
        "forklift",
        "truck"
    ],
    "wof:name":"Solid Servce Pty Ltd",
    "wof:placetype":"venue"
},
  "geometry": {"coordinates":[150.881317139,-33.8505134583],"type":"Point"}
}