{
  "type": "Feature",
  "properties": {
    "addr:full":"Rear Dock, CCA Building 52 -54 Newbridge St, South Lismore NSW 2480",
    "addr:housenumber":"-54",
    "addr:postcode":"2480",
    "addr:street":"Newbridge St South",
    "iso:country":"AU",
    "sg:address":"Rear Dock, CCA Building 52",
    "sg:city":"-54 Newbridge St, South Lismore",
    "sg:classifiers":[
        {
            "category":"Wholesale",
            "subcategory":"Apparel",
            "type":"Manufacturing & Wholesale Goods"
        }
    ],
    "sg:phone":"+61 2 6622 3465",
    "sg:postcode":"2480",
    "sg:province":"NSW",
    "sg:tags":[
        "wholesaler",
        "mfrs",
        "cap",
        "hat"
    ],
    "wof:name":"Sunbuster Australia Pty Ltd",
    "wof:placetype":"venue"
},
  "geometry": {"coordinates":[153.26197814899999,-28.8131046295],"type":"Point"}
}