{
  "type": "Feature",
  "properties": {
    "addr:full":"406A Hampton St Hampton VIC 3188",
    "addr:housenumber":"406a",
    "addr:postcode":"3188",
    "addr:street":"Hampton St",
    "iso:country":"AU",
    "sg:address":"406A Hampton St",
    "sg:city":"Hampton",
    "sg:classifiers":[
        {
            "category":"Shopping",
            "subcategory":"Baby Store",
            "type":"Retail Goods"
        }
    ],
    "sg:phone":"+61 3 9533 1200",
    "sg:postcode":"3188",
    "sg:province":"VIC",
    "sg:tags":[
        "children's",
        "wear"
    ],
    "wof:name":"Kounia-Bella",
    "wof:placetype":"venue"
},
  "geometry": {"coordinates":[145.00250244099999,-37.9382019043],"type":"Point"}
}