{
  "type": "Feature",
  "properties": {
    "addr:full":"Shop 12, Eagle Vale Market Place Gould Rd Eagle Vale NSW 2558",
    "addr:housenumber":"shop 12",
    "addr:postcode":"2558",
    "addr:street":"Market Place Gould Rd",
    "iso:country":"AU",
    "sg:address":"Shop 12, Eagle Vale Market Place Gould Rd",
    "sg:city":"Eagle Vale",
    "sg:classifiers":[
        {
            "category":"Health Services",
            "subcategory":"Doctor",
            "type":"Services"
        }
    ],
    "sg:phone":"+61 2 9820 8984",
    "sg:postcode":"2558",
    "sg:province":"NSW",
    "sg:tags":[
        "medical",
        "practitioner"
    ],
    "wof:name":"SDS Pathology",
    "wof:placetype":"venue"
},
  "geometry": {"coordinates":[150.81800842300001,-34.0324287415],"type":"Point"}
}