{
  "type": "Feature",
  "properties": {
    "addr:full":"106 Oberon St Oberon NSW 2787",
    "addr:housenumber":"106",
    "addr:postcode":"2787",
    "addr:street":"Oberon St",
    "iso:country":"AU",
    "sg:address":"106 Oberon St",
    "sg:city":"Oberon",
    "sg:classifiers":[
        {
            "category":"Wholesale",
            "subcategory":"Non-durable Goods",
            "type":"Manufacturing & Wholesale Goods"
        }
    ],
    "sg:phone":"+61 2 6336 0885",
    "sg:postcode":"2787",
    "sg:province":"NSW",
    "sg:tags":[
        "wholesaler",
        "craft",
        "mfrs"
    ],
    "wof:name":"Oberon Wood Gallery",
    "wof:placetype":"venue"
},
  "geometry": {"coordinates":[149.858612061,-33.7044067383],"type":"Point"}
}