{
  "type": "Feature",
  "properties": {
    "addr:full":"1st Floor 330 Penshurst St Willoughby NSW 2068",
    "addr:housenumber":"330",
    "addr:postcode":"2068",
    "addr:street":"Penshurst St",
    "iso:country":"AU",
    "sg:address":"1st Floor 330 Penshurst St",
    "sg:city":"Willoughby",
    "sg:classifiers":[
        {
            "category":"Professional",
            "subcategory":"Accounting & Tax Preparation",
            "type":"Services"
        }
    ],
    "sg:phone":"+61 2 9417 7444",
    "sg:postcode":"2068",
    "sg:province":"NSW",
    "sg:tags":[
        "accountant",
        "auditor"
    ],
    "wof:name":"Partell & Associates",
    "wof:placetype":"venue"
},
  "geometry": {"coordinates":[151.195999145,-33.7939186096],"type":"Point"}
}