{
  "type": "Feature",
  "properties": {
    "addr:full":"2 Kitchener Rd Cherrybrook NSW 2126",
    "addr:housenumber":"2",
    "addr:postcode":"2126",
    "addr:street":"Kitchener Rd",
    "iso:country":"AU",
    "sg:address":"2 Kitchener Rd",
    "sg:city":"Cherrybrook",
    "sg:classifiers":[
        {
            "category":"Social Services",
            "subcategory":"Retirement Home",
            "type":"Services"
        }
    ],
    "sg:phone":"+61 2 9481 8842",
    "sg:postcode":"2126",
    "sg:province":"NSW",
    "sg:tags":[
        "village"
    ],
    "wof:name":"Woodlands Retirement Village Limited",
    "wof:placetype":"venue"
},
  "geometry": {"coordinates":[151.0572052,-33.7304916382],"type":"Point"}
}