{
  "type": "Feature",
  "properties": {
    "addr:full":"Harbour Rd Brooklyn NSW 2083",
    "addr:postcode":"2083",
    "addr:street":"Harbour Rd",
    "iso:country":"AU",
    "sg:address":"Harbour Rd",
    "sg:city":"Brooklyn",
    "sg:classifiers":[
        {
            "category":"Manufacturing",
            "subcategory":"Motor Vehicles & Parts",
            "type":"Manufacturing & Wholesale Goods"
        }
    ],
    "sg:phone":"+61 2 9985 7885",
    "sg:postcode":"2083",
    "sg:province":"NSW",
    "sg:tags":[
        "engine",
        "equipment",
        "diesel"
    ],
    "wof:name":"Stuart Pearce Marine Engineering",
    "wof:placetype":"venue"
},
  "geometry": {"coordinates":[151.215576172,-33.6229400635],"type":"Point"}
}