{
  "type": "Feature",
  "properties": {
    "iso:country":"AU",
    "sg:address":"82 Cobra St",
    "sg:city":"Dubbo",
    "sg:classifiers":[
        {
            "category":"Home & Garden",
            "subcategory":"Building Materials",
            "type":"Retail Goods"
        }
    ],
    "sg:phone":"+61 2 6885 4231",
    "sg:postcode":"2830",
    "sg:province":"NSW",
    "sg:tags":[
        "lawn",
        "cutting",
        "maintenance"
    ],
    "wof:name":"D & D Lawn Mowing",
    "wof:placetype":"venue"
},
  "geometry": {"coordinates":[148.60078430199999,-32.253036499],"type":"Point"}
}