{
  "type": "Feature",
  "properties": {
    "iso:country":"AU",
    "sg:address":"12 Della Torre Rd",
    "sg:city":"Moe",
    "sg:classifiers":[
        {
            "category":"Wholesale",
            "subcategory":"Auto Parts",
            "type":"Manufacturing & Wholesale Goods"
        }
    ],
    "sg:phone":"+61 3 5127 2122",
    "sg:postcode":"3825",
    "sg:province":"VIC",
    "sg:tags":[
        "recyclers"
    ],
    "wof:name":"Moe Motorcycles",
    "wof:placetype":"venue"
},
  "geometry": {"coordinates":[146.260056,-38.167542],"type":"Point"}
}