{
  "type": "Feature",
  "properties": {
    "iso:country":"AU",
    "sg:address":"481 Macaulay Rd",
    "sg:city":"Kensington",
    "sg:classifiers":[
        {
            "category":"Health Services",
            "subcategory":"Dentist",
            "type":"Services"
        }
    ],
    "sg:phone":"+61 3 9376 3573",
    "sg:postcode":"3031",
    "sg:province":"VIC",
    "wof:name":"Navakas Andrew Dr",
    "wof:placetype":"venue"
},
  "geometry": {"coordinates":[144.93012999999999,-37.794537],"type":"Point"}
}