{
  "type": "Feature",
  "properties": {
    "iso:country":"AU",
    "sg:address":"Shp 7",
    "sg:city":"Metro Quays Townsville",
    "sg:classifiers":[
        {
            "category":"Fast Food",
            "type":"Food & Drink"
        }
    ],
    "sg:phone":"+61 7 4772 1333",
    "sg:postcode":"4810",
    "sg:province":"QLD",
    "sg:tags":[
        "away",
        "take"
    ],
    "wof:name":"Sun Sushi",
    "wof:placetype":"venue"
},
  "geometry": {"coordinates":[146.75546299999999,-19.2351],"type":"Point"}
}