{
  "type": "Feature",
  "properties": {
    "iso:country":"AU",
    "sg:address":"Shop T276 North Terrace Bankstown Square Lady Cutler Drive",
    "sg:city":"Bankstown",
    "sg:classifiers":[
        {
            "category":"Travel",
            "subcategory":"Travel Agent",
            "type":"Entertainment"
        }
    ],
    "sg:phone":"+61 2 9707 4900",
    "sg:postcode":"2200",
    "sg:province":"NSW",
    "sg:tags":[
        "consultant"
    ],
    "wof:name":"Harvey World Travel",
    "wof:placetype":"venue"
},
  "geometry": {"coordinates":[151.034164,-33.914791],"type":"Point"}
}