{
  "type": "Feature",
  "properties": {
    "addr:full":"58 Church St Gloucester NSW 2422",
    "addr:housenumber":"58",
    "addr:postcode":"2422",
    "addr:street":"Church St",
    "iso:country":"AU",
    "sg:address":"58 Church St",
    "sg:city":"Gloucester",
    "sg:classifiers":[
        {
            "category":"Personal",
            "subcategory":"Beauty Salon",
            "type":"Services"
        }
    ],
    "sg:phone":"+61 2 6558 1333",
    "sg:postcode":"2422",
    "sg:province":"NSW",
    "sg:tags":[
        "hairdresser"
    ],
    "wof:name":"Milady Hairdressing Salon",
    "wof:placetype":"venue"
},
  "geometry": {"coordinates":[151.95848100000001,-32.007168],"type":"Point"}
}