{
  "type": "Feature",
  "properties": {
    "addr:full":"34 Roseberry St Ascot Vale VIC 3032",
    "addr:housenumber":"34",
    "addr:postcode":"3032",
    "addr:street":"Roseberry St",
    "iso:country":"AU",
    "sg:address":"34 Roseberry St",
    "sg:city":"Ascot Vale",
    "sg:classifiers":[
        {
            "category":"Education",
            "subcategory":"Kindergarten",
            "type":"Public Place"
        }
    ],
    "sg:phone":"+61 3 9370 5895",
    "sg:postcode":"3032",
    "sg:province":"VIC",
    "sg:tags":[
        "pre-schools"
    ],
    "wof:name":"Coronation Pre School",
    "wof:placetype":"venue"
},
  "geometry": {"coordinates":[144.913589,-37.774506],"type":"Point"}
}