{
  "type": "Feature",
  "properties": {
    "addr:full":"47 Maitland St Bingara NSW 2404",
    "addr:housenumber":"47",
    "addr:postcode":"2404",
    "addr:street":"Maitland St",
    "iso:country":"AU",
    "sg:address":"47 Maitland St",
    "sg:city":"Bingara",
    "sg:classifiers":[
        {
            "category":"Shopping",
            "subcategory":"Clothing, Apparel, & Fashions",
            "type":"Retail Goods"
        }
    ],
    "sg:phone":"+61 2 6724 1499",
    "sg:postcode":"2404",
    "sg:province":"NSW",
    "sg:tags":[
        "boutique"
    ],
    "wof:name":"Ritter's Of Bingara",
    "wof:placetype":"venue"
},
  "geometry": {"coordinates":[150.57135009800001,-29.8677940369],"type":"Point"}
}