{
  "type": "Feature",
  "properties": {
    "addr:full":"Uni 2, 366 Boundary Rd Dingley VIC 3172",
    "addr:housenumber":"366",
    "addr:postcode":"3172",
    "addr:street":"Boundary Rd",
    "iso:country":"AU",
    "sg:address":"Uni 2, 366 Boundary Rd",
    "sg:city":"Dingley",
    "sg:classifiers":[
        {
            "category":"Home & Garden",
            "subcategory":"Building Materials",
            "type":"Retail Goods"
        }
    ],
    "sg:phone":"+61 3 9558 2177",
    "sg:postcode":"3172",
    "sg:province":"VIC",
    "sg:tags":[
        "ventilating",
        "equipment",
        "system"
    ],
    "wof:name":"Rexel Australia Electrical Supplies",
    "wof:placetype":"venue"
},
  "geometry": {"coordinates":[145.11175537099999,-37.9740715027],"type":"Point"}
}