{
  "type": "Feature",
  "properties": {
    "addr:full":"375 Inkerman St Balaclava VIC 3183",
    "addr:housenumber":"375",
    "addr:postcode":"3183",
    "addr:street":"Inkerman St",
    "iso:country":"AU",
    "sg:address":"375 Inkerman St",
    "sg:city":"Balaclava",
    "sg:classifiers":[
        {
            "category":"Travel",
            "subcategory":"Hotels & Motels",
            "type":"Entertainment"
        }
    ],
    "sg:phone":"+61 3 9527 2176",
    "sg:postcode":"3183",
    "sg:province":"VIC",
    "sg:tags":[
        "accommodation"
    ],
    "wof:name":"Inkerman Hotel",
    "wof:placetype":"venue"
},
  "geometry": {"coordinates":[144.99815368599999,-37.8663291931],"type":"Point"}
}