{
  "type": "Feature",
  "properties": {
    "addr:full":"3/24- 28 Glennie St West Gosford North NSW 2250",
    "addr:housenumber":"/;28",
    "addr:postcode":"2250",
    "addr:street":"24;Glennie St West",
    "iso:country":"AU",
    "sg:address":"3/24- 28 Glennie St",
    "sg:city":"West Gosford North",
    "sg:classifiers":[
        {
            "category":"Home & Garden",
            "subcategory":"Hardware",
            "type":"Retail Goods"
        }
    ],
    "sg:phone":"+61 2 4325 4216",
    "sg:postcode":"2250",
    "sg:province":"NSW",
    "sg:tags":[
        "nut",
        "bolt"
    ],
    "wof:name":"Gosford Bolts & Bearings",
    "wof:placetype":"venue"
},
  "geometry": {"coordinates":[151.34048461899999,-33.4116134644],"type":"Point"}
}