{
  "type": "Feature",
  "properties": {
    "iso:country":"AU",
    "sg:address":"4/ 68 Lexton Rd",
    "sg:city":"Box Hill",
    "sg:classifiers":[
        {
            "category":"Manufacturing",
            "subcategory":"Tools & Machinery",
            "type":"Manufacturing & Wholesale Goods"
        }
    ],
    "sg:phone":"+61 3 9897 3433",
    "sg:postcode":"3128",
    "sg:province":"VIC",
    "wof:name":"Lowe F & Co Pty Ltd",
    "wof:placetype":"venue"
},
  "geometry": {"coordinates":[145.139160156,-37.8125114441],"type":"Point"}
}