{
  "type": "Feature",
  "properties": {
    "addr:full":"PO Box 1429 Berri SA 5343",
    "addr:postcode":"5343",
    "iso:country":"AU",
    "sg:address":"PO Box 1429",
    "sg:city":"Berri",
    "sg:classifiers":[
        {
            "category":"Building & Trades",
            "subcategory":"Cleaning & Sanitation",
            "type":"Services"
        }
    ],
    "sg:phone":"+61 428 840 451",
    "sg:postcode":"5343",
    "sg:province":"SA",
    "sg:tags":[
        "asbestos",
        "treatment",
        "removal"
    ],
    "wof:name":"Riverland Building Services & Asbestos Removal",
    "wof:placetype":"venue"
},
  "geometry": {"coordinates":[140.598846436,-34.2817192078],"type":"Point"}
}