{
  "type": "Feature",
  "properties": {
    "iso:country":"AU",
    "sg:address":"Level 6, 235 Pyrmont St",
    "sg:city":"Pyrmont",
    "sg:classifiers":[
        {
            "category":"Building & Trades",
            "subcategory":"Construction",
            "type":"Services"
        }
    ],
    "sg:phone":"+61 2 9552 4288",
    "sg:postcode":"2009",
    "sg:province":"NSW",
    "sg:tags":[
        "management"
    ],
    "wof:name":"John Holland Pty Ltd",
    "wof:placetype":"venue"
},
  "geometry": {"coordinates":[151.19700622600001,-33.8733558655],"type":"Point"}
}