{
  "type": "Feature",
  "properties": {
    "iso:country":"AU",
    "sg:address":"36 Mansion Point Rd",
    "sg:city":"Grays Point",
    "sg:classifiers":[
        {
            "category":"Manufacturing",
            "subcategory":"Building Materials",
            "type":"Manufacturing & Wholesale Goods"
        }
    ],
    "sg:phone":"+61 2 9524 1546",
    "sg:postcode":"2232",
    "sg:province":"NSW",
    "sg:tags":[
        "equipment",
        "handling"
    ],
    "wof:name":"Bulk Materials Handling Pty Ltd",
    "wof:placetype":"venue"
},
  "geometry": {"coordinates":[151.088256836,-34.0606155396],"type":"Point"}
}