{
  "type": "Feature",
  "properties": {
    "addr:full":"397a Belmore Rd Balwyn VIC 3103",
    "addr:housenumber":"397a",
    "addr:postcode":"3103",
    "addr:street":"Belmore Rd",
    "iso:country":"AU",
    "sg:address":"397a Belmore Rd",
    "sg:city":"Balwyn",
    "sg:classifiers":[
        {
            "category":"Food & Beverages",
            "subcategory":"Liquor & Beverages",
            "type":"Retail Goods"
        }
    ],
    "sg:phone":"+61 3 9857 8320",
    "sg:postcode":"3103",
    "sg:province":"VIC",
    "sg:tags":[
        "store"
    ],
    "wof:name":"Estate Cellars",
    "wof:placetype":"venue"
},
  "geometry": {"coordinates":[145.102127075,-37.8033409119],"type":"Point"}
}