{
  "type": "Feature",
  "properties": {
    "addr:full":"8 Charles Rd Beverley SA 5009",
    "addr:housenumber":"8",
    "addr:postcode":"5009",
    "addr:street":"Charles Rd",
    "iso:country":"AU",
    "sg:address":"8 Charles Rd",
    "sg:city":"Beverley",
    "sg:classifiers":[
        {
            "category":"Autos & Motor Vehicles",
            "subcategory":"Automobile Sales",
            "type":"Retail Goods"
        }
    ],
    "sg:phone":"+61 8 8244 7942",
    "sg:postcode":"5009",
    "sg:province":"SA",
    "sg:tags":[
        "equipment",
        "trailer"
    ],
    "wof:name":"Beverley Trailers",
    "wof:placetype":"venue"
},
  "geometry": {"coordinates":[138.54600524899999,-34.8890914917],"type":"Point"}
}