{
  "type": "Feature",
  "properties": {
    "iso:country":"AU",
    "sg:address":"104 Fredrick St",
    "sg:city":"Yeronga",
    "sg:classifiers":[
        {
            "category":"Food & Beverages",
            "subcategory":"Liquor & Beverages",
            "type":"Retail Goods"
        }
    ],
    "sg:phone":"+61 7 3848 3215",
    "sg:postcode":"4104",
    "sg:province":"QLD",
    "sg:tags":[
        "store"
    ],
    "wof:name":"Liquor Legends",
    "wof:placetype":"venue"
},
  "geometry": {"coordinates":[153.026611328,-27.5176753998],"type":"Point"}
}