{
  "type": "Feature",
  "properties": {
    "addr:full":"PO Box 268 Stirling SA 5152",
    "addr:postcode":"5152",
    "iso:country":"AU",
    "sg:address":"PO Box 268",
    "sg:city":"Stirling",
    "sg:classifiers":[
        {
            "category":"Building & Trades",
            "subcategory":"Plumbing",
            "type":"Services"
        }
    ],
    "sg:phone":"+61 412 815 606",
    "sg:postcode":"5152",
    "sg:province":"SA",
    "sg:tags":[
        "drainers"
    ],
    "wof:name":"Hann R A Contractors",
    "wof:placetype":"venue"
},
  "geometry": {"coordinates":[138.72253418,-35.0080490112],"type":"Point"}
}