{
  "type": "Feature",
  "properties": {
    "addr:full":"Benalla Rd Shepparton East VIC 3631",
    "addr:postcode":"3631",
    "addr:street":"Benalla Rd",
    "iso:country":"AU",
    "sg:address":"Benalla Rd",
    "sg:city":"Shepparton East",
    "sg:classifiers":[
        {
            "category":"Education",
            "subcategory":"School",
            "type":"Public Place"
        }
    ],
    "sg:phone":"+61 3 5829 2426",
    "sg:postcode":"3631",
    "sg:province":"VIC",
    "sg:tags":[
        "state",
        "except",
        "nsw"
    ],
    "wof:name":"Shepparton East Primary School",
    "wof:placetype":"venue"
},
  "geometry": {"coordinates":[145.43011474599999,-36.387840271],"type":"Point"}
}