{
  "type": "Feature",
  "properties": {
    "iso:country":"AU",
    "sg:address":"Upstairs 43 Brierly St",
    "sg:city":"Weston",
    "sg:classifiers":[
        {
            "category":"Health Services",
            "subcategory":"Chiropractor",
            "type":"Services"
        }
    ],
    "sg:phone":"+61 2 6288 6711",
    "sg:postcode":"2611",
    "sg:province":"ACT",
    "wof:name":"Farrugia Mark",
    "wof:placetype":"venue"
},
  "geometry": {"coordinates":[149.052124023,-35.3407516479],"type":"Point"}
}