{
  "type": "Feature",
  "properties": {
    "iso:country":"AU",
    "sg:address":"12 Chrome St",
    "sg:city":"Salisbury",
    "sg:classifiers":[
        {
            "category":"Home & Garden",
            "subcategory":"Furniture",
            "type":"Retail Goods"
        }
    ],
    "sg:phone":"+61 7 3277 3377",
    "sg:postcode":"4107",
    "sg:province":"QLD",
    "sg:tags":[
        "repair",
        "restoration"
    ],
    "wof:name":"Regal Caneware",
    "wof:placetype":"venue"
},
  "geometry": {"coordinates":[153.029373169,-27.543264389],"type":"Point"}
}