{
  "type": "Feature",
  "properties": {
    "addr:full":"Shop 4-5 8 Rainbow Beach Rd Rainbow Beach QLD 4581",
    "addr:housenumber":"shop 4-5 8",
    "addr:postcode":"4581",
    "addr:street":"Rainbow Beach Rd",
    "iso:country":"AU",
    "sg:address":"Shop 4-5 8 Rainbow Beach Rd",
    "sg:city":"Rainbow Beach",
    "sg:classifiers":[
        {
            "category":"Fast Food",
            "type":"Food & Drink"
        }
    ],
    "sg:phone":"+61 7 5486 3143",
    "sg:postcode":"4581",
    "sg:province":"QLD",
    "sg:tags":[
        "away",
        "take"
    ],
    "wof:name":"Rainbow Beach Coloured Sands Cafe",
    "wof:placetype":"venue"
},
  "geometry": {"coordinates":[153.09165954599999,-25.9025592804],"type":"Point"}
}