{
  "type": "Feature",
  "properties": {
    "addr:full":"Burns Bay Rd Lane Cove NSW 2066",
    "addr:postcode":"2066",
    "addr:street":"Burns Bay Rd",
    "iso:country":"AU",
    "sg:address":"Burns Bay Rd",
    "sg:city":"Lane Cove",
    "sg:classifiers":[
        {
            "category":"Food & Beverages",
            "subcategory":"Supermarket",
            "type":"Retail Goods"
        }
    ],
    "sg:phone":"+61 2 9428 3135",
    "sg:postcode":"2066",
    "sg:province":"NSW",
    "sg:tags":[
        "grocery",
        "store"
    ],
    "wof:name":"Franklins Limited",
    "wof:placetype":"venue"
},
  "geometry": {"coordinates":[151.16403198200001,-33.8145294189],"type":"Point"}
}