{
  "type": "Feature",
  "properties": {
    "addr:full":"23 Keppel St Shepparton VIC 3630",
    "addr:housenumber":"23",
    "addr:postcode":"3630",
    "addr:street":"Keppel St",
    "iso:country":"AU",
    "sg:address":"23 Keppel St",
    "sg:city":"Shepparton",
    "sg:classifiers":[
        {
            "category":"Farming",
            "subcategory":"Farm & Veterinary Services",
            "type":"Manufacturing & Wholesale Goods"
        }
    ],
    "sg:phone":"+61 3 5821 2021",
    "sg:postcode":"3630",
    "sg:province":"VIC",
    "sg:tags":[
        "agricultural",
        "advisory"
    ],
    "wof:name":"Agrisearch Services Pty Ltd",
    "wof:placetype":"venue"
},
  "geometry": {"coordinates":[145.41447448700001,-36.3861541748],"type":"Point"}
}