{
  "type": "Feature",
  "properties": {
    "iso:country":"AU",
    "sg:address":"35 Western Crs",
    "sg:city":"Westleigh",
    "sg:classifiers":[
        {
            "category":"Utilities",
            "subcategory":"Electric",
            "type":"Services"
        }
    ],
    "sg:phone":"+61 417 667 473",
    "sg:postcode":"2120",
    "sg:province":"NSW",
    "sg:tags":[
        "electrical",
        "contractor"
    ],
    "wof:name":"Electrical Power Installations Pty Ltd",
    "wof:placetype":"venue"
},
  "geometry": {"coordinates":[151.06840515100001,-33.7193603516],"type":"Point"}
}