{
  "type": "Feature",
  "properties": {
    "iso:country":"AU",
    "sg:address":"258 Main Rd East",
    "sg:city":"St Albans",
    "sg:classifiers":[
        {
            "category":"Health Services",
            "subcategory":"Doctor",
            "type":"Services"
        }
    ],
    "sg:phone":"+61 3 9366 2022",
    "sg:postcode":"3021",
    "sg:province":"VIC",
    "sg:tags":[
        "medical",
        "practitioner"
    ],
    "wof:name":"Medical Centre St Albans Pty Ltd",
    "wof:placetype":"venue"
},
  "geometry": {"coordinates":[144.80573999999999,-37.74477],"type":"Point"}
}