{
  "type": "Feature",
  "properties": {
    "iso:country":"AU",
    "sg:address":"11 Holts Rd",
    "sg:city":"Beaconsfield",
    "sg:classifiers":[
        {
            "category":"Banks & Credit Unions",
            "subcategory":"Bureau De Change",
            "type":"Services"
        }
    ],
    "sg:phone":"+61 419 113 410",
    "sg:postcode":"4740",
    "sg:province":"QLD",
    "sg:tags":[
        "escort",
        "transport",
        "pilot"
    ],
    "wof:name":"Ross Ohl Pilot Service",
    "wof:placetype":"venue"
},
  "geometry": {"coordinates":[149.16554300000001,-21.100599],"type":"Point"}
}