{
  "type": "Feature",
  "properties": {
    "iso:country":"AU",
    "sg:address":"43 Imperial Drv",
    "sg:city":"Berkeley",
    "sg:classifiers":[
        {
            "category":"Professional",
            "subcategory":"Business Services",
            "type":"Services"
        }
    ],
    "sg:phone":"+61 413 510 942",
    "sg:postcode":"2506",
    "sg:province":"NSW",
    "sg:tags":[
        "small",
        "advisory"
    ],
    "wof:name":"Precision Records",
    "wof:placetype":"venue"
},
  "geometry": {"coordinates":[150.856247,-34.477436],"type":"Point"}
}