{
  "type": "Feature",
  "properties": {
    "iso:country":"AU",
    "sg:address":"PO Box 1193",
    "sg:city":"Swan Hill",
    "sg:classifiers":[
        {
            "category":"Building & Trades",
            "subcategory":"Plumbing",
            "type":"Services"
        }
    ],
    "sg:phone":"+61 3 5032 9080",
    "sg:postcode":"3585",
    "sg:province":"NSW",
    "sg:tags":[
        "pipe",
        "line",
        "contractor"
    ],
    "wof:name":"Torileigh Excavations",
    "wof:placetype":"venue"
},
  "geometry": {"coordinates":[143.561554,-35.340969],"type":"Point"}
}