{
  "type": "Feature",
  "properties": {
    "iso:country":"AU",
    "sg:address":"PO Box 2036",
    "sg:city":"Ellenbrook",
    "sg:classifiers":[
        {
            "category":"Home & Garden",
            "subcategory":"Building Materials",
            "type":"Retail Goods"
        }
    ],
    "sg:phone":"+61 439 033 998",
    "sg:postcode":"6069",
    "sg:province":"WA",
    "sg:tags":[
        "anti-corrosive",
        "composition",
        "flooring"
    ],
    "wof:name":"PM Spray On Paving",
    "wof:placetype":"venue"
},
  "geometry": {"coordinates":[115.97013855,-31.7888202667],"type":"Point"}
}