{
  "type": "Feature",
  "properties": {
    "addr:full":"LVl 6 100 Albert Rd South Melbourne VIC 3205",
    "addr:housenumber":"100",
    "addr:postcode":"3205",
    "addr:street":"Albert Rd",
    "iso:country":"AU",
    "sg:address":"LVl 6 100 Albert Rd",
    "sg:city":"South Melbourne",
    "sg:classifiers":[
        {
            "category":"Transit Center",
            "subcategory":"Freight",
            "type":"Transportation"
        }
    ],
    "sg:phone":"+61 3 9682 2488",
    "sg:postcode":"3205",
    "sg:province":"VIC",
    "sg:tags":[
        "agent",
        "shipping"
    ],
    "wof:name":"Adsteam Agency Pty Limited",
    "wof:placetype":"venue"
},
  "geometry": {"coordinates":[144.97013899999999,-37.835659],"type":"Point"}
}