{
  "type": "Feature",
  "properties": {
    "addr:full":"Cnr Leach Hwy & Welshpool Rd Welshpool WA 6106",
    "addr:postcode":"6106",
    "addr:street":"Cnr Leach Hwy & Welshpool Rd",
    "iso:country":"AU",
    "sg:address":"Cnr Leach Hwy & Welshpool Rd",
    "sg:city":"Welshpool",
    "sg:classifiers":[
        {
            "category":"Retail",
            "subcategory":"Storage",
            "type":"Services"
        }
    ],
    "sg:phone":"+61 8 9451 3456",
    "sg:postcode":"6106",
    "sg:province":"WA",
    "wof:name":"Castle Self Storage Welshpool",
    "wof:placetype":"venue"
},
  "geometry": {"coordinates":[115.929229736,-31.9943599701],"type":"Point"}
}