{
  "type": "Feature",
  "properties": {
    "iso:country":"AU",
    "sg:address":"16 Abrahams Crt",
    "sg:city":"Malak",
    "sg:classifiers":[
        {
            "category":"Home & Garden",
            "subcategory":"Garden Supply",
            "type":"Retail Goods"
        }
    ],
    "sg:phone":"+61 403 185 854",
    "sg:postcode":"0812",
    "sg:province":"NT",
    "sg:tags":[
        "equipment"
    ],
    "wof:name":"All About Gardening",
    "wof:placetype":"venue"
},
  "geometry": {"coordinates":[130.907593,-12.392852],"type":"Point"}
}