{
  "type": "Feature",
  "properties": {
    "addr:full":"103 York St Devonport TAS 7310",
    "addr:housenumber":"103",
    "addr:postcode":"7310",
    "addr:street":"York St",
    "iso:country":"AU",
    "sg:address":"103 York St",
    "sg:city":"Devonport",
    "sg:classifiers":[
        {
            "category":"Professional",
            "subcategory":"Detective & Security Services",
            "type":"Services"
        }
    ],
    "sg:phone":"+61 3 6423 5300",
    "sg:postcode":"7310",
    "sg:province":"TAS",
    "sg:tags":[
        "equipment",
        "window",
        "doors"
    ],
    "wof:name":"Phil's Glass & Blinds",
    "wof:placetype":"venue"
},
  "geometry": {"coordinates":[146.35845947300001,-41.1899223328],"type":"Point"}
}