{
  "type": "Feature",
  "properties": {
    "addr:full":"PO Box 528 Montacute SA 5134",
    "addr:postcode":"5134",
    "iso:country":"AU",
    "sg:address":"PO Box 528",
    "sg:city":"Montacute",
    "sg:classifiers":[
        {
            "category":"Building & Trades",
            "subcategory":"Construction",
            "type":"Services"
        }
    ],
    "sg:phone":"+61 409 842 223",
    "sg:postcode":"5134",
    "sg:province":"SA",
    "sg:tags":[
        "contractor"
    ],
    "wof:name":"Paul Craig Building",
    "wof:placetype":"venue"
},
  "geometry": {"coordinates":[138.73959350600001,-34.8905792236],"type":"Point"}
}