{
  "type": "Feature",
  "properties": {
    "addr:full":"21 Esmond Ave Jerrabomberra NSW 2619",
    "addr:housenumber":"21",
    "addr:postcode":"2619",
    "addr:street":"Esmond Ave",
    "iso:country":"AU",
    "sg:address":"21 Esmond Ave",
    "sg:city":"Jerrabomberra",
    "sg:classifiers":[
        {
            "category":"Building & Trades",
            "subcategory":"Construction",
            "type":"Services"
        }
    ],
    "sg:phone":"+61 2 6297 5544",
    "sg:postcode":"2619",
    "sg:province":"NSW",
    "sg:tags":[
        "fencing",
        "contractor"
    ],
    "wof:name":"Monaro Fencing",
    "wof:placetype":"venue"
},
  "geometry": {"coordinates":[149.19984435999999,-35.3749351501],"type":"Point"}
}