{
  "type": "Feature",
  "properties": {
    "addr:full":"Blantyre Farm Meckering Rd Dowerin WA 6461",
    "addr:postcode":"6461",
    "addr:street":"Meckering Rd",
    "iso:country":"AU",
    "sg:address":"Blantyre Farm Meckering Rd",
    "sg:city":"Dowerin",
    "sg:classifiers":[
        {
            "category":"Professional",
            "subcategory":"Business Services",
            "type":"Services"
        }
    ],
    "sg:phone":"+61 8 9634 1015",
    "sg:postcode":"6461",
    "sg:province":"WA",
    "sg:tags":[
        "livestock",
        "transport"
    ],
    "wof:name":"Hagboom L G & F",
    "wof:placetype":"venue"
},
  "geometry": {"coordinates":[117.036811829,-31.1957798004],"type":"Point"}
}