{
  "type": "Feature",
  "properties": {
    "iso:country":"AU",
    "sg:address":"19 - 21 Yuille St",
    "sg:city":"Ballarat",
    "sg:classifiers":[
        {
            "category":"Retail",
            "subcategory":"Auto Repair",
            "type":"Services"
        }
    ],
    "sg:phone":"+61 3 5338 8626",
    "sg:postcode":"3350",
    "sg:province":"VIC",
    "sg:tags":[
        "testing",
        "inspection",
        "motor",
        "vehicle"
    ],
    "wof:name":"Ballarat Motors",
    "wof:placetype":"venue"
},
  "geometry": {"coordinates":[143.85408000000001,-37.557514],"type":"Point"}
}