{
  "type": "Feature",
  "properties": {
    "addr:full":"5 Keating St Maroubra NSW 2035",
    "addr:housenumber":"5",
    "addr:postcode":"2035",
    "addr:street":"Keating St",
    "iso:country":"AU",
    "sg:address":"5 Keating St",
    "sg:city":"Maroubra",
    "sg:classifiers":[
        {
            "category":"Social Services",
            "subcategory":"Adult Care",
            "type":"Services"
        }
    ],
    "sg:phone":"+61 424 076 161",
    "sg:postcode":"2035",
    "sg:province":"NSW",
    "sg:tags":[
        "towing"
    ],
    "wof:name":"All Up Towing Service",
    "wof:placetype":"venue"
},
  "geometry": {"coordinates":[151.24310302699999,-33.9366378784],"type":"Point"}
}