{
  "type": "Feature",
  "properties": {
    "iso:country":"AU",
    "sg:address":"453 Schaefer St",
    "sg:city":"Lavington",
    "sg:classifiers":[
        {
            "category":"Fast Food",
            "type":"Food & Drink"
        }
    ],
    "sg:phone":"+61 2 6025 8866",
    "sg:postcode":"2641",
    "sg:province":"NSW",
    "sg:tags":[
        "away",
        "take"
    ],
    "wof:name":"Lucky Dragon Chinese Restaurant",
    "wof:placetype":"venue"
},
  "geometry": {"coordinates":[146.94000244099999,-36.0357055664],"type":"Point"}
}