{
  "type": "Feature",
  "properties": {
    "iso:country":"AU",
    "sg:address":"Ste1/16- 18 Windsor Ave",
    "sg:city":"Springvale",
    "sg:classifiers":[
        {
            "category":"Health Services",
            "subcategory":"Doctor",
            "type":"Services"
        }
    ],
    "sg:phone":"+61 3 9574 1717",
    "sg:postcode":"3171",
    "sg:province":"VIC",
    "sg:tags":[
        "medical",
        "practitioner"
    ],
    "wof:name":"Chea L",
    "wof:placetype":"venue"
},
  "geometry": {"coordinates":[145.149337769,-37.9516639709],"type":"Point"}
}