{
  "type": "Feature",
  "properties": {
    "addr:full":"7 Finlayson St Wollongong NSW 2520",
    "addr:housenumber":"7",
    "addr:postcode":"2520",
    "addr:street":"Finlayson St",
    "iso:country":"AU",
    "sg:address":"7 Finlayson St",
    "sg:city":"Wollongong",
    "sg:classifiers":[
        {
            "category":"Shopping",
            "subcategory":"Computers & Home Electronics",
            "type":"Retail Goods"
        }
    ],
    "sg:phone":"+61 2 4228 8455",
    "sg:postcode":"2520",
    "sg:province":"NSW",
    "sg:tags":[
        "equipment",
        "multimedia"
    ],
    "wof:name":"Xanderproductions",
    "wof:placetype":"venue"
},
  "geometry": {"coordinates":[150.89805602999999,-34.4241485596],"type":"Point"}
}