{
  "type": "Feature",
  "properties": {
    "iso:country":"AU",
    "sg:address":"110 Army Rd",
    "sg:city":"Pakenham",
    "sg:classifiers":[
        {
            "category":"Retail",
            "subcategory":"Storage",
            "type":"Services"
        }
    ],
    "sg:phone":"+61 3 5941 2279",
    "sg:postcode":"3810",
    "sg:province":"VIC",
    "sg:tags":[
        "cold"
    ],
    "wof:name":"Pakenham Cold Storage",
    "wof:placetype":"venue"
},
  "geometry": {"coordinates":[145.497345,-38.059757],"type":"Point"}
}