{
  "type": "Feature",
  "properties": {
    "iso:country":"AU",
    "sg:address":"38 Orchard Rd",
    "sg:city":"Brookvale",
    "sg:classifiers":[
        {
            "category":"Retail",
            "subcategory":"Repair Shop",
            "type":"Services"
        }
    ],
    "sg:phone":"+61 2 9939 6214",
    "sg:postcode":"2100",
    "sg:province":"NSW",
    "sg:tags":[
        "upholsterer"
    ],
    "wof:name":"Wall T. & Sons",
    "wof:placetype":"venue"
},
  "geometry": {"coordinates":[151.273147583,-33.7655067444],"type":"Point"}
}