{
  "type": "Feature",
  "properties": {
    "iso:country":"AU",
    "sg:address":"3/ 37 Devlan St",
    "sg:city":"Mansfield",
    "sg:classifiers":[
        {
            "category":"Building & Trades",
            "subcategory":"Construction",
            "type":"Services"
        }
    ],
    "sg:phone":"+61 1800 330 473",
    "sg:postcode":"4122",
    "sg:province":"QLD",
    "sg:tags":[
        "industrial",
        "commercial",
        "air conditioning"
    ],
    "wof:name":"Astle Air",
    "wof:placetype":"venue"
},
  "geometry": {"coordinates":[153.09835815400001,-27.5277843475],"type":"Point"}
}