{
  "type": "Feature",
  "properties": {
    "iso:country":"AU",
    "sg:address":"29a Slater Pde",
    "sg:city":"Keilor East",
    "sg:classifiers":[
        {
            "category":"Retail",
            "subcategory":"Auto Repair",
            "type":"Services"
        }
    ],
    "sg:phone":"+61 3 9331 7676",
    "sg:postcode":"3033",
    "sg:province":"VIC",
    "sg:tags":[
        "repairer",
        "motor",
        "engineer"
    ],
    "wof:name":"Motortech Auto Repairs",
    "wof:placetype":"venue"
},
  "geometry": {"coordinates":[144.853622,-37.735935],"type":"Point"}
}