{
  "type": "Feature",
  "properties": {
    "addr:full":"33 Addison Crt Morayfield QLD 4506",
    "addr:housenumber":"33",
    "addr:postcode":"4506",
    "addr:street":"Addison Crt",
    "iso:country":"AU",
    "sg:address":"33 Addison Crt",
    "sg:city":"Morayfield",
    "sg:classifiers":[
        {
            "category":"Retail",
            "subcategory":"Storage",
            "type":"Services"
        }
    ],
    "sg:phone":"+61 7 5498 7684",
    "sg:postcode":"4506",
    "sg:province":"QLD",
    "sg:tags":[
        "removal",
        "furniture"
    ],
    "wof:name":"Careful & Courteous Removals",
    "wof:placetype":"venue"
},
  "geometry": {"coordinates":[152.928863525,-27.1424598694],"type":"Point"}
}