{
  "type": "Feature",
  "properties": {
    "iso:country":"AU",
    "sg:address":"38 King St",
    "sg:city":"Prahran",
    "sg:classifiers":[
        {
            "category":"Shopping",
            "subcategory":"Discount & Variety Stores",
            "type":"Retail Goods"
        }
    ],
    "sg:phone":"+61 3 9529 3177",
    "sg:postcode":"3181",
    "sg:province":"VIC",
    "sg:tags":[
        "recording",
        "equipment",
        "supply"
    ],
    "wof:name":"Quantegy Australia",
    "wof:placetype":"venue"
},
  "geometry": {"coordinates":[144.99621582,-37.8501853943],"type":"Point"}
}