{
  "type": "Feature",
  "properties": {
    "addr:full":"101 Bakers Rd Coburg North VIC 3058",
    "addr:housenumber":"101",
    "addr:postcode":"3058",
    "addr:street":"Bakers Rd",
    "iso:country":"AU",
    "sg:address":"101 Bakers Rd",
    "sg:city":"Coburg North",
    "sg:classifiers":[
        {
            "category":"Professional",
            "subcategory":"Art Services",
            "type":"Services"
        }
    ],
    "sg:phone":"+61 3 9354 6955",
    "sg:postcode":"3058",
    "sg:province":"VIC",
    "sg:tags":[
        "picture",
        "frame",
        "framing"
    ],
    "wof:name":"Custom Framing Specialists",
    "wof:placetype":"venue"
},
  "geometry": {"coordinates":[144.957427978,-37.7267951965],"type":"Point"}
}