{
  "type": "Feature",
  "properties": {
    "addr:full":"34 Abbotsford Rd Homebush NSW 2140",
    "addr:housenumber":"34",
    "addr:postcode":"2140",
    "addr:street":"Abbotsford Rd",
    "iso:country":"AU",
    "sg:address":"34 Abbotsford Rd",
    "sg:city":"Homebush",
    "sg:classifiers":[
        {
            "category":"Health Services",
            "subcategory":"Doctor",
            "type":"Services"
        }
    ],
    "sg:phone":"+61 2 9746 6051",
    "sg:postcode":"2140",
    "sg:province":"NSW",
    "sg:tags":[
        "medical",
        "practitioner"
    ],
    "wof:name":"Bilinsky Chrystina",
    "wof:placetype":"venue"
},
  "geometry": {"coordinates":[151.08372497600001,-33.868938446],"type":"Point"}
}