{
  "type": "Feature",
  "properties": {
    "addr:full":"Hervey Bay Marina Buccaneer Drv Urangan QLD 4655",
    "addr:postcode":"4655",
    "addr:street":"Buccaneer Drv",
    "iso:country":"AU",
    "sg:address":"Hervey Bay Marina Buccaneer Drv",
    "sg:city":"Urangan",
    "sg:classifiers":[
        {
            "category":"Recreation",
            "subcategory":"Boat Charter",
            "type":"Entertainment"
        }
    ],
    "sg:phone":"+61 1800 800 862",
    "sg:postcode":"4655",
    "sg:province":"QLD",
    "wof:name":"Whale Planet",
    "wof:placetype":"venue"
},
  "geometry": {"coordinates":[152.908646,-25.293362],"type":"Point"}
}