{
  "type": "Feature",
  "properties": {
    "addr:full":"Anne St Moree NSW 2400",
    "addr:postcode":"2400",
    "addr:street":"Anne St",
    "iso:country":"AU",
    "sg:address":"Anne St",
    "sg:city":"Moree",
    "sg:classifiers":[
        {
            "category":"Health Services",
            "subcategory":"Doctor",
            "type":"Services"
        }
    ],
    "sg:phone":"+61 2 6752 1099",
    "sg:postcode":"2400",
    "sg:province":"NSW",
    "sg:tags":[
        "medical",
        "practitioner"
    ],
    "wof:name":"Pius X Aboriginal Corporation",
    "wof:placetype":"venue"
},
  "geometry": {"coordinates":[149.84127807600001,-29.4737148285],"type":"Point"}
}