{
  "type": "Feature",
  "properties": {
    "addr:full":"108 Foster St Sale VIC 3850",
    "addr:housenumber":"108",
    "addr:postcode":"3850",
    "addr:street":"Foster St",
    "iso:country":"AU",
    "sg:address":"108 Foster St",
    "sg:city":"Sale",
    "sg:classifiers":[
        {
            "category":"Personal",
            "subcategory":"Beauty Salon",
            "type":"Services"
        }
    ],
    "sg:phone":"+61 3 5144 3404",
    "sg:postcode":"3850",
    "sg:province":"VIC",
    "sg:tags":[
        "hairdresser"
    ],
    "wof:name":"Elvas",
    "wof:placetype":"venue"
},
  "geometry": {"coordinates":[147.065948486,-38.1116828918],"type":"Point"}
}