{
  "type": "Feature",
  "properties": {
    "iso:country":"AU",
    "sg:address":"10-12 Dunstans Crt",
    "sg:city":"Keon Park",
    "sg:classifiers":[
        {
            "category":"Manufacturing",
            "subcategory":"Furniture",
            "type":"Manufacturing & Wholesale Goods"
        }
    ],
    "sg:phone":"+61 3 9462 1999",
    "sg:postcode":"3073",
    "sg:province":"VIC",
    "sg:tags":[
        "mfrs",
        "supply"
    ],
    "wof:name":"Easiform Drawer Systems",
    "wof:placetype":"venue"
},
  "geometry": {"coordinates":[145.02142334000001,-37.693321228],"type":"Point"}
}