{
  "type": "Feature",
  "properties": {
    "addr:full":"53- 55 Grosvenor St South Yarra VIC 3141",
    "addr:housenumber":"55",
    "addr:postcode":"3141",
    "addr:street":"Grosvenor St",
    "iso:country":"AU",
    "sg:address":"53- 55 Grosvenor St",
    "sg:city":"South Yarra",
    "sg:classifiers":[
        {
            "category":"Social Services",
            "subcategory":"Child Care",
            "type":"Services"
        }
    ],
    "sg:phone":"+61 3 8290 8201",
    "sg:postcode":"3141",
    "sg:province":"VIC",
    "wof:name":"Grosvenor St. Occasional Care Centre",
    "wof:placetype":"venue"
},
  "geometry": {"coordinates":[144.99398803700001,-37.8443450928],"type":"Point"}
}