{
  "type": "Feature",
  "properties": {
    "addr:full":"Lot 2 Cnr Western Hwy & Ring Rd Ballarat VIC 3350",
    "addr:housenumber":"cnr",
    "addr:postcode":"3350",
    "addr:street":"Western Hwy & Ring Rd",
    "iso:country":"AU",
    "sg:address":"Lot 2 Cnr Western Hwy & Ring Rd",
    "sg:city":"Ballarat",
    "sg:classifiers":[
        {
            "category":"Professional",
            "subcategory":"Engineering",
            "type":"Services"
        }
    ],
    "sg:phone":"+61 3 5334 3116",
    "sg:postcode":"3350",
    "sg:province":"VIC",
    "sg:tags":[
        "consulting",
        "engineer"
    ],
    "wof:name":"Building Contracts & Services Pty Ltd",
    "wof:placetype":"venue"
},
  "geometry": {"coordinates":[143.797012,-37.546509],"type":"Point"}
}