{
  "type": "Feature",
  "properties": {
    "addr:full":"25 Louise St Atherton QLD 4883",
    "addr:housenumber":"25",
    "addr:postcode":"4883",
    "addr:street":"Louise St",
    "iso:country":"AU",
    "sg:address":"25 Louise St",
    "sg:city":"Atherton",
    "sg:classifiers":[
        {
            "category":"Health Services",
            "subcategory":"Doctor",
            "type":"Services"
        }
    ],
    "sg:phone":"+61 7 4091 1444",
    "sg:postcode":"4883",
    "sg:province":"QLD",
    "sg:tags":[
        "medical",
        "practitioner"
    ],
    "wof:name":"Ruscoe Michael",
    "wof:placetype":"venue"
},
  "geometry": {"coordinates":[145.48182678200001,-17.2675228119],"type":"Point"}
}