{
  "type": "Feature",
  "properties": {
    "addr:full":"24 Topham St Rose Bay TAS 7015",
    "addr:housenumber":"24",
    "addr:postcode":"7015",
    "addr:street":"Topham St",
    "iso:country":"AU",
    "sg:address":"24 Topham St",
    "sg:city":"Rose Bay",
    "sg:classifiers":[
        {
            "category":"Building & Trades",
            "subcategory":"Construction",
            "type":"Services"
        }
    ],
    "sg:phone":"+61 3 6243 0555",
    "sg:postcode":"7015",
    "sg:province":"TAS",
    "sg:tags":[
        "contractor"
    ],
    "wof:name":"Cusick D J & L M",
    "wof:placetype":"venue"
},
  "geometry": {"coordinates":[147.35389709500001,-42.859752655],"type":"Point"}
}