{
  "type": "Feature",
  "properties": {
    "addr:full":"Shop 2, 31 Cole St Sorell TAS 7172",
    "addr:housenumber":"shop;31",
    "addr:postcode":"7172",
    "addr:street":"Cole St",
    "iso:country":"AU",
    "sg:address":"Shop 2, 31 Cole St",
    "sg:city":"Sorell",
    "sg:classifiers":[
        {
            "category":"Fast Food",
            "type":"Food & Drink"
        }
    ],
    "sg:phone":"+61 3 6265 1511",
    "sg:postcode":"7172",
    "sg:province":"TAS",
    "sg:tags":[
        "away",
        "take"
    ],
    "wof:name":"Geppetto's Restaurant",
    "wof:placetype":"venue"
},
  "geometry": {"coordinates":[147.56317138700001,-42.7813796997],"type":"Point"}
}