{
  "type": "Feature",
  "properties": {
    "addr:full":"42 Edwin St Mortlake NSW 2137",
    "addr:housenumber":"42",
    "addr:postcode":"2137",
    "addr:street":"Edwin St",
    "iso:country":"AU",
    "sg:address":"42 Edwin St",
    "sg:city":"Mortlake",
    "sg:classifiers":[
        {
            "category":"Marine",
            "type":"Transportation"
        }
    ],
    "sg:phone":"+61 2 9743 5821",
    "sg:postcode":"2137",
    "sg:province":"NSW",
    "sg:tags":[
        "flagpole",
        "mast"
    ],
    "wof:name":"A Academy Flagpoles",
    "wof:placetype":"venue"
},
  "geometry": {"coordinates":[151.107299805,-33.8417625427],"type":"Point"}
}