{
  "type": "Feature",
  "properties": {
    "iso:country":"AU",
    "sg:address":"7 Churchill St",
    "sg:city":"Jamberoo",
    "sg:classifiers":[
        {
            "category":"Building & Trades",
            "subcategory":"Construction",
            "type":"Services"
        }
    ],
    "sg:phone":"+61 408 361 188",
    "sg:postcode":"2533",
    "sg:province":"NSW",
    "sg:tags":[
        "contractor"
    ],
    "wof:name":"Alan Jurd Building",
    "wof:placetype":"venue"
},
  "geometry": {"coordinates":[150.77301025400001,-34.6423187256],"type":"Point"}
}