{
  "type": "Feature",
  "properties": {
    "addr:full":"Garden City Shopping Centre Logan Rd Upper Mt Gravatt QLD 4122",
    "addr:postcode":"4122",
    "addr:street":"Logan Rd Upper",
    "iso:country":"AU",
    "sg:address":"Garden City Shopping Centre Logan Rd",
    "sg:city":"Upper Mt Gravatt",
    "sg:classifiers":[
        {
            "category":"Travel",
            "subcategory":"Travel Agent",
            "type":"Entertainment"
        }
    ],
    "sg:phone":"+61 7 3247 1677",
    "sg:postcode":"4122",
    "sg:province":"QLD",
    "sg:tags":[
        "consultant"
    ],
    "wof:name":"Student Flights",
    "wof:placetype":"venue"
},
  "geometry": {"coordinates":[153.08169555699999,-27.5645084381],"type":"Point"}
}