{
  "type": "Feature",
  "properties": {
    "iso:country":"AU",
    "sg:address":"131 Urana St",
    "sg:city":"The Rock",
    "sg:classifiers":[
        {
            "category":"Utilities",
            "subcategory":"Telephone",
            "type":"Services"
        }
    ],
    "sg:phone":"+61 2 6920 2388",
    "sg:postcode":"2655",
    "sg:province":"NSW",
    "sg:tags":[
        "installation",
        "system",
        "maintenance"
    ],
    "wof:name":"TES Pty Ltd",
    "wof:placetype":"venue"
},
  "geometry": {"coordinates":[147.11813354500001,-35.2708625793],"type":"Point"}
}