{
  "type": "Feature",
  "properties": {
    "addr:full":"27 Treforest Drv Clayton VIC 3168",
    "addr:housenumber":"27",
    "addr:postcode":"3168",
    "addr:street":"Treforest Drv",
    "iso:country":"AU",
    "sg:address":"27 Treforest Drv",
    "sg:city":"Clayton",
    "sg:classifiers":[
        {
            "category":"Conference Center",
            "type":"Public Place"
        }
    ],
    "sg:phone":"+61 3 9562 6277",
    "sg:postcode":"3168",
    "sg:province":"VIC",
    "sg:tags":[
        "dryer",
        "electric",
        "hand"
    ],
    "wof:name":"Starmix Hair & Hand Dryers",
    "wof:placetype":"venue"
},
  "geometry": {"coordinates":[145.13377380399999,-37.9226531982],"type":"Point"}
}