{
  "type": "Feature",
  "properties": {
    "iso:country":"AU",
    "sg:address":"47 Aberdeen St",
    "sg:city":"Albany",
    "sg:classifiers":[
        {
            "category":"Banks & Credit Unions",
            "subcategory":"Financial Services",
            "type":"Services"
        }
    ],
    "sg:phone":"+61 8 9842 1437",
    "sg:postcode":"6330",
    "sg:province":"WA",
    "sg:tags":[
        "settlement",
        "nt",
        "agent",
        "wa"
    ],
    "wof:name":"HR Settlements",
    "wof:placetype":"venue"
},
  "geometry": {"coordinates":[117.88527679400001,-35.0230445862],"type":"Point"}
}