{
  "type": "Feature",
  "properties": {
    "addr:full":"17- 19 Charles St Yeppoon QLD 4703",
    "addr:housenumber":"19",
    "addr:postcode":"4703",
    "addr:street":"Charles St",
    "iso:country":"AU",
    "sg:address":"17- 19 Charles St",
    "sg:city":"Yeppoon",
    "sg:classifiers":[
        {
            "category":"Retail",
            "subcategory":"Auto Repair",
            "type":"Services"
        }
    ],
    "sg:phone":"+61 7 4939 5744",
    "sg:postcode":"4703",
    "sg:province":"QLD",
    "sg:tags":[
        "repairer",
        "motor",
        "engineer"
    ],
    "wof:name":"J P Automotive",
    "wof:placetype":"venue"
},
  "geometry": {"coordinates":[150.73899841299999,-23.1352462769],"type":"Point"}
}