{
  "type": "Feature",
  "properties": {
    "addr:full":"341 Barker Rd Subiaco WA 6008",
    "addr:housenumber":"341",
    "addr:postcode":"6008",
    "addr:street":"Barker Rd",
    "iso:country":"AU",
    "sg:address":"341 Barker Rd",
    "sg:city":"Subiaco",
    "sg:classifiers":[
        {
            "category":"Health Services",
            "subcategory":"Health Practitioner",
            "type":"Services"
        }
    ],
    "sg:phone":"+61 8 9381 2790",
    "sg:postcode":"6008",
    "sg:province":"WA",
    "sg:tags":[
        "herbalist"
    ],
    "wof:name":"Fortune Acupuncture Chinese Medical Clinic",
    "wof:placetype":"venue"
},
  "geometry": {"coordinates":[115.822990417,-31.9488506317],"type":"Point"}
}