{
  "type": "Feature",
  "properties": {
    "iso:country":"AU",
    "sg:address":"497 North Rd",
    "sg:city":"Ormond",
    "sg:classifiers":[
        {
            "category":"Professional",
            "subcategory":"Art Services",
            "type":"Services"
        }
    ],
    "sg:phone":"+61 3 9578 2093",
    "sg:postcode":"3204",
    "sg:province":"VIC",
    "sg:tags":[
        "picture",
        "frame",
        "framing"
    ],
    "wof:name":"Ormond Frames & Gifts",
    "wof:placetype":"venue"
},
  "geometry": {"coordinates":[145.04028299999999,-37.903828],"type":"Point"}
}