{
  "type": "Feature",
  "properties": {
    "iso:country":"AU",
    "sg:address":"74 Lissiman St",
    "sg:city":"Gosnells",
    "sg:classifiers":[
        {
            "category":"Health Services",
            "subcategory":"Nursing And Care Facility",
            "type":"Services"
        }
    ],
    "sg:phone":"+61 8 9398 7722",
    "sg:postcode":"6110",
    "sg:province":"WA",
    "sg:tags":[
        "home"
    ],
    "wof:name":"Amaroo Village McMahon Caring Centre",
    "wof:placetype":"venue"
},
  "geometry": {"coordinates":[115.99736785899999,-32.0682792664],"type":"Point"}
}