{
  "type": "Feature",
  "properties": {
    "addr:full":"First Floor 36 Eton St Sutherland NSW 2232",
    "addr:housenumber":"36",
    "addr:postcode":"2232",
    "addr:street":"Floor;Eton St",
    "iso:country":"AU",
    "sg:address":"First Floor 36 Eton St",
    "sg:city":"Sutherland",
    "sg:classifiers":[
        {
            "category":"Home & Garden",
            "subcategory":"Building Materials",
            "type":"Retail Goods"
        }
    ],
    "sg:phone":"+61 2 9545 6111",
    "sg:postcode":"2232",
    "sg:province":"NSW",
    "sg:tags":[
        "pre-mixed",
        "concrete"
    ],
    "wof:name":"Concrite Pty Limited",
    "wof:placetype":"venue"
},
  "geometry": {"coordinates":[151.059036255,-34.0317497253],"type":"Point"}
}