{
  "type": "Feature",
  "properties": {
    "addr:full":"25 Pitt St Colac VIC 3250",
    "addr:housenumber":"25",
    "addr:postcode":"3250",
    "addr:street":"Pitt St",
    "iso:country":"AU",
    "sg:address":"25 Pitt St",
    "sg:city":"Colac",
    "sg:classifiers":[
        {
            "category":"Building & Trades",
            "subcategory":"Construction",
            "type":"Services"
        }
    ],
    "sg:phone":"+61 419 554 676",
    "sg:postcode":"3250",
    "sg:province":"VIC",
    "sg:tags":[
        "plasterboard",
        "plasterer",
        "fixer"
    ],
    "wof:name":"Nowell K L & J M",
    "wof:placetype":"venue"
},
  "geometry": {"coordinates":[143.60179099999999,-38.335838],"type":"Point"}
}