{
  "type": "Feature",
  "properties": {
    "addr:full":"Shop 19/ 1150 Beaudesert Rd Acacia Ridge QLD 4110",
    "addr:housenumber":"shop 19 / 1150",
    "addr:postcode":"4110",
    "addr:street":"Beaudesert Rd",
    "iso:country":"AU",
    "sg:address":"Shop 19/ 1150 Beaudesert Rd",
    "sg:city":"Acacia Ridge",
    "sg:classifiers":[
        {
            "category":"Utilities",
            "subcategory":"Mobile Phone",
            "type":"Services"
        }
    ],
    "sg:phone":"+61 7 3277 8078",
    "sg:postcode":"4110",
    "sg:province":"QLD",
    "sg:tags":[
        "repair",
        "telephone"
    ],
    "wof:name":"Red Hot Digital Pty Ltd",
    "wof:placetype":"venue"
},
  "geometry": {"coordinates":[153.02926635700001,-27.5915794373],"type":"Point"}
}