{
  "type": "Feature",
  "properties": {
    "addr:full":"Unit 7 89- 91 Tennant St Fyshwick ACT 2609",
    "addr:housenumber":"89 91",
    "addr:postcode":"2609",
    "addr:street":"Tennant St",
    "iso:country":"AU",
    "sg:address":"Unit 7 89- 91 Tennant St",
    "sg:city":"Fyshwick",
    "sg:classifiers":[
        {
            "category":"Retail",
            "subcategory":"Auto Repair",
            "type":"Services"
        }
    ],
    "sg:phone":"+61 411 519 688",
    "sg:postcode":"2609",
    "sg:province":"ACT",
    "sg:tags":[
        "electrical"
    ],
    "wof:name":"Wheels Auto Electrics",
    "wof:placetype":"venue"
},
  "geometry": {"coordinates":[149.18652343799999,-35.3268051147],"type":"Point"}
}