{
  "type": "Feature",
  "properties": {
    "addr:full":"10/ 25 Lathlain St Belconnen ACT 2617",
    "addr:housenumber":"10 / 25",
    "addr:postcode":"2617",
    "addr:street":"Lathlain St",
    "iso:country":"AU",
    "sg:address":"10/ 25 Lathlain St",
    "sg:city":"Belconnen",
    "sg:classifiers":[
        {
            "category":"Sports & Exercise",
            "subcategory":"Gym",
            "type":"Entertainment"
        }
    ],
    "sg:phone":"+61 2 6251 5161",
    "sg:postcode":"2617",
    "sg:province":"ACT",
    "sg:tags":[
        "pilate",
        "method"
    ],
    "wof:name":"Vital Action Pilates Studio",
    "wof:placetype":"venue"
},
  "geometry": {"coordinates":[149.06410217300001,-35.2420501709],"type":"Point"}
}