{
  "type": "Feature",
  "properties": {
    "addr:full":"73 Harding St Coburg VIC 3058",
    "addr:housenumber":"73",
    "addr:postcode":"3058",
    "addr:street":"Harding St",
    "iso:country":"AU",
    "sg:address":"73 Harding St",
    "sg:city":"Coburg",
    "sg:classifiers":[
        {
            "category":"Retail",
            "subcategory":"Auto Repair",
            "type":"Services"
        }
    ],
    "sg:phone":"+61 3 9354 8899",
    "sg:postcode":"3058",
    "sg:province":"VIC",
    "sg:tags":[
        "electrical"
    ],
    "wof:name":"Blue Star Auto Electrical Service",
    "wof:placetype":"venue"
},
  "geometry": {"coordinates":[144.97363281200001,-37.745639801],"type":"Point"}
}