{
  "type": "Feature",
  "properties": {
    "iso:country":"AU",
    "sg:address":"1/ 22 Church St",
    "sg:city":"Whittlesea",
    "sg:classifiers":[
        {
            "category":"Real Estate",
            "subcategory":"Real Estate Agent",
            "type":"Services"
        }
    ],
    "sg:phone":"+61 3 9716 2302",
    "sg:postcode":"3757",
    "sg:province":"VIC",
    "wof:name":"L J Hooker",
    "wof:placetype":"venue"
},
  "geometry": {"coordinates":[145.11795000000001,-37.513412],"type":"Point"}
}