{
  "type": "Feature",
  "properties": {
    "addr:full":"Safeway Arc Shp 9/ Campbell St Swan Hill VIC 3585",
    "addr:housenumber":"9 /",
    "addr:postcode":"3585",
    "addr:street":"Campbell St",
    "iso:country":"AU",
    "sg:address":"Safeway Arc Shp 9/ Campbell St",
    "sg:city":"Swan Hill",
    "sg:classifiers":[
        {
            "category":"Personal",
            "subcategory":"Beauty Salon",
            "type":"Services"
        }
    ],
    "sg:phone":"+61 3 5032 1399",
    "sg:postcode":"3585",
    "sg:province":"VIC",
    "sg:tags":[
        "hairdresser"
    ],
    "wof:name":"Salon 197",
    "wof:placetype":"venue"
},
  "geometry": {"coordinates":[143.560089,-35.339996],"type":"Point"}
}