{
  "type": "Feature",
  "properties": {
    "addr:full":"Barwell Ave Seacliff SA 5049",
    "addr:postcode":"5049",
    "addr:street":"Barwell Ave",
    "iso:country":"AU",
    "sg:address":"Barwell Ave",
    "sg:city":"Seacliff",
    "sg:classifiers":[
        {
            "category":"Education",
            "subcategory":"School",
            "type":"Public Place"
        }
    ],
    "sg:phone":"+61 8 8296 5222",
    "sg:postcode":"5049",
    "sg:province":"SA",
    "sg:tags":[
        "state",
        "except",
        "nsw"
    ],
    "wof:name":"Sturt Cottage Craft",
    "wof:placetype":"venue"
},
  "geometry": {"coordinates":[138.52224699999999,-35.037212],"type":"Point"}
}