{
  "type": "Feature",
  "properties": {
    "iso:country":"AU",
    "sg:address":"69 Daisy Hill Rd",
    "sg:city":"Daisy Hill",
    "sg:classifiers":[
        {
            "category":"Retail",
            "subcategory":"Laundry & Dry Cleaning",
            "type":"Services"
        }
    ],
    "sg:phone":"+61 1300 303 549",
    "sg:postcode":"4127",
    "sg:province":"QLD",
    "sg:tags":[
        "machine",
        "commercial",
        "industrial",
        "washing"
    ],
    "wof:name":"Brisbane Laundry Rentals",
    "wof:placetype":"venue"
},
  "geometry": {"coordinates":[153.154693603,-27.6365032196],"type":"Point"}
}