{
  "type": "Feature",
  "properties": {
    "addr:full":"Lot 2 Alidenes Rd Mullumbimby NSW 2482",
    "addr:postcode":"2482",
    "addr:street":"Alidenes Rd",
    "iso:country":"AU",
    "sg:address":"Lot 2 Alidenes Rd",
    "sg:city":"Mullumbimby",
    "sg:classifiers":[
        {
            "category":"Building & Trades",
            "subcategory":"Pest Control",
            "type":"Services"
        }
    ],
    "sg:phone":"+61 2 6684 6062",
    "sg:postcode":"2482",
    "sg:province":"NSW",
    "wof:name":"Hermitage Building & Pest Management",
    "wof:placetype":"venue"
},
  "geometry": {"coordinates":[153.456375122,-28.5697231293],"type":"Point"}
}