{
  "type": "Feature",
  "properties": {
    "addr:full":"154 Limestone Ridges Rd Peak Crossing QLD 4306",
    "addr:housenumber":"154",
    "addr:postcode":"4306",
    "addr:street":"Limestone Ridges Rd",
    "iso:country":"AU",
    "sg:address":"154 Limestone Ridges Rd",
    "sg:city":"Peak Crossing",
    "sg:classifiers":[
        {
            "category":"Government",
            "subcategory":"Fire Station",
            "type":"Public Place"
        }
    ],
    "sg:phone":"+61 7 3288 8172",
    "sg:postcode":"4306",
    "sg:province":"QLD",
    "sg:tags":[
        "equipment",
        "protection",
        "consultant"
    ],
    "wof:name":"Ipswich & District Fire Equipment Services Pty Ltd",
    "wof:placetype":"venue"
},
  "geometry": {"coordinates":[152.72914123499999,-27.8302230835],"type":"Point"}
}