{
  "type": "Feature",
  "properties": {
    "addr:full":"243 Princes Drv Morwell VIC 3840",
    "addr:housenumber":"243",
    "addr:postcode":"3840",
    "addr:street":"Princes Drv",
    "iso:country":"AU",
    "sg:address":"243 Princes Drv",
    "sg:city":"Morwell",
    "sg:classifiers":[
        {
            "category":"Restaurant",
            "type":"Food & Drink"
        }
    ],
    "sg:phone":"+61 3 5133 7488",
    "sg:postcode":"3840",
    "sg:province":"VIC",
    "wof:name":"Dragon Place Chinese Restaurant",
    "wof:placetype":"venue"
},
  "geometry": {"coordinates":[146.401580811,-38.2374458313],"type":"Point"}
}