{
  "type": "Feature",
  "properties": {
    "iso:country":"AU",
    "sg:address":"PO Box 99",
    "sg:city":"Highett",
    "sg:classifiers":[
        {
            "category":"Health Services",
            "subcategory":"Doctor",
            "type":"Services"
        }
    ],
    "sg:phone":"+61 413 319 584",
    "sg:postcode":"3190",
    "sg:province":"VIC",
    "sg:tags":[
        "nurse",
        "nursing"
    ],
    "wof:name":"Health Care Solutions",
    "wof:placetype":"venue"
},
  "geometry": {"coordinates":[145.04006957999999,-37.9506187439],"type":"Point"}
}