{
  "type": "Feature",
  "properties": {
    "addr:full":"PO Box 47 St Pauls NSW 2031",
    "addr:postcode":"2031",
    "iso:country":"AU",
    "sg:address":"PO Box 47",
    "sg:city":"St Pauls",
    "sg:classifiers":[
        {
            "category":"Professional",
            "subcategory":"Computer Services",
            "type":"Services"
        }
    ],
    "sg:phone":"+61 2 9340 7676",
    "sg:postcode":"2031",
    "sg:province":"NSW",
    "sg:tags":[
        "equipment",
        "networking",
        "installation"
    ],
    "wof:name":"Blue Sphere Technology Pty Ltd",
    "wof:placetype":"venue"
},
  "geometry": {"coordinates":[151.24269104000001,-33.9202308655],"type":"Point"}
}