{
  "type": "Feature",
  "properties": {
    "addr:full":"Fifth St Nichols Point VIC 3501",
    "addr:postcode":"3501",
    "addr:street":"Fifth St",
    "iso:country":"AU",
    "sg:address":"Fifth St",
    "sg:city":"Nichols Point",
    "sg:classifiers":[
        {
            "category":"Government",
            "subcategory":"Post Office",
            "type":"Public Place"
        }
    ],
    "sg:phone":"+61 3 5023 3255",
    "sg:postcode":"3501",
    "sg:province":"VIC",
    "sg:tags":[
        "postal"
    ],
    "wof:name":"Nichols Point Post Office",
    "wof:placetype":"venue"
},
  "geometry": {"coordinates":[142.19099426299999,-34.2002334595],"type":"Point"}
}