{
  "type": "Feature",
  "properties": {
    "addr:full":"35 Parker St Bega NSW 2550",
    "addr:housenumber":"35",
    "addr:postcode":"2550",
    "addr:street":"Parker St",
    "iso:country":"AU",
    "sg:address":"35 Parker St",
    "sg:city":"Bega",
    "sg:classifiers":[
        {
            "category":"Health Services",
            "subcategory":"Doctor",
            "type":"Services"
        }
    ],
    "sg:phone":"+61 2 6492 2433",
    "sg:postcode":"2550",
    "sg:province":"NSW",
    "sg:tags":[
        "medical",
        "practitioner"
    ],
    "wof:name":"Christoph Ahrens MD",
    "wof:placetype":"venue"
},
  "geometry": {"coordinates":[149.845626831,-36.6741600037],"type":"Point"}
}