{
  "type": "Feature",
  "properties": {
    "addr:full":"Shp 58C Inglefarm Shopping Cntr, Montague Rd Ingle Farm SA 5098",
    "addr:housenumber":"58c",
    "addr:postcode":"5098",
    "addr:street":"Inglefarm Shopping Cntr Montague Rd",
    "iso:country":"AU",
    "sg:address":"Shp 58C Inglefarm Shopping Cntr, Montague Rd",
    "sg:city":"Ingle Farm",
    "sg:classifiers":[
        {
            "category":"Professional",
            "subcategory":"Accounting & Tax Preparation",
            "type":"Services"
        }
    ],
    "sg:phone":"+61 8 8395 0413",
    "sg:postcode":"5098",
    "sg:province":"SA",
    "sg:tags":[
        "consultant",
        "taxation"
    ],
    "wof:name":"H & R Block",
    "wof:placetype":"venue"
},
  "geometry": {"coordinates":[138.650756836,-34.828704834],"type":"Point"}
}