{
  "type": "Feature",
  "properties": {
    "iso:country":"AU",
    "sg:address":"Suite 1a 21- 23 Burwood Rd",
    "sg:city":"Burwood",
    "sg:classifiers":[
        {
            "category":"Professional",
            "subcategory":"Business Services",
            "type":"Services"
        }
    ],
    "sg:phone":"+61 2 9745 2658",
    "sg:postcode":"2134",
    "sg:province":"NSW",
    "sg:tags":[
        "drafting"
    ],
    "wof:name":"Sydney Drafting Service",
    "wof:placetype":"venue"
},
  "geometry": {"coordinates":[151.104812622,-33.8708457947],"type":"Point"}
}