{
  "type": "Feature",
  "properties": {
    "addr:full":"108 Hampden Rd Artarmon NSW 2064",
    "addr:housenumber":"108",
    "addr:postcode":"2064",
    "addr:street":"Hampden Rd",
    "iso:country":"AU",
    "sg:address":"108 Hampden Rd",
    "sg:city":"Artarmon",
    "sg:classifiers":[
        {
            "category":"Cafe",
            "type":"Food & Drink"
        }
    ],
    "sg:phone":"+61 2 9411 5226",
    "sg:postcode":"2064",
    "sg:province":"NSW",
    "wof:name":"Artarmon Gourmet",
    "wof:placetype":"venue"
},
  "geometry": {"coordinates":[151.18409729000001,-33.8086166382],"type":"Point"}
}