{
  "type": "Feature",
  "properties": {
    "addr:full":"Labrador Medical Centre 32 Central St Labrador QLD 4215",
    "addr:housenumber":"32",
    "addr:postcode":"4215",
    "addr:street":"Central St",
    "iso:country":"AU",
    "sg:address":"Labrador Medical Centre 32 Central St",
    "sg:city":"Labrador",
    "sg:classifiers":[
        {
            "category":"Health Services",
            "subcategory":"Doctor",
            "type":"Services"
        }
    ],
    "sg:phone":"+61 7 5532 1822",
    "sg:postcode":"4215",
    "sg:province":"QLD",
    "sg:tags":[
        "medical",
        "practitioner"
    ],
    "wof:name":"Thompson W",
    "wof:placetype":"venue"
},
  "geometry": {"coordinates":[153.40625,-27.9492206573],"type":"Point"}
}