{
  "type": "Feature",
  "properties": {
    "iso:country":"AU",
    "sg:address":"55 Lavender St",
    "sg:city":"Milsons Point",
    "sg:classifiers":[
        {
            "category":"Professional",
            "subcategory":"Management & Consulting",
            "type":"Services"
        }
    ],
    "sg:phone":"+61 2 8925 5300",
    "sg:postcode":"2061",
    "sg:province":"NSW",
    "sg:tags":[
        "consultant"
    ],
    "wof:name":"Right Management Consultants",
    "wof:placetype":"venue"
},
  "geometry": {"coordinates":[151.20970153799999,-33.8435440063],"type":"Point"}
}