{
  "type": "Feature",
  "properties": {
    "addr:full":"U2/ 126 Kurrajong Ave Mt Druitt NSW 2770",
    "addr:housenumber":"126",
    "addr:postcode":"2770",
    "addr:street":"U2 /;Kurrajong Ave Mt",
    "iso:country":"AU",
    "sg:address":"U2/ 126 Kurrajong Ave",
    "sg:city":"Mt Druitt",
    "sg:classifiers":[
        {
            "category":"Autos & Motor Vehicles",
            "subcategory":"Automobile Sales",
            "type":"Retail Goods"
        }
    ],
    "sg:phone":"+61 2 9677 9661",
    "sg:postcode":"2770",
    "sg:province":"NSW",
    "sg:tags":[
        "equipment",
        "trailer"
    ],
    "wof:name":"Gal Trailers",
    "wof:placetype":"venue"
},
  "geometry": {"coordinates":[150.80317688,-33.7632904053],"type":"Point"}
}