{
  "type": "Feature",
  "properties": {
    "addr:full":"U2/ 19 Hotham Pde Artarmon NSW 2064",
    "addr:housenumber":"19",
    "addr:postcode":"2064",
    "addr:street":"U2 /;Hotham Pde",
    "iso:country":"AU",
    "sg:address":"U2/ 19 Hotham Pde",
    "sg:city":"Artarmon",
    "sg:classifiers":[
        {
            "category":"Communications",
            "type":"Services"
        }
    ],
    "sg:phone":"+61 2 9438 2588",
    "sg:postcode":"2064",
    "sg:province":"NSW",
    "sg:tags":[
        "equipment",
        "radio"
    ],
    "wof:name":"Defcon Technologies Pty Ltd",
    "wof:placetype":"venue"
},
  "geometry": {"coordinates":[151.183197022,-33.8139152527],"type":"Point"}
}