{
  "type": "Feature",
  "properties": {
    "addr:full":"PO Box 1120 Millicent SA 5280",
    "addr:postcode":"5280",
    "iso:country":"AU",
    "sg:address":"PO Box 1120",
    "sg:city":"Millicent",
    "sg:classifiers":[
        {
            "category":"Wholesale",
            "subcategory":"Scrap",
            "type":"Manufacturing & Wholesale Goods"
        }
    ],
    "sg:phone":"+61 8 8733 4845",
    "sg:postcode":"5280",
    "sg:province":"SA",
    "sg:tags":[
        "merchant",
        "metal"
    ],
    "wof:name":"J & A Valcarcel-Fuentes & Sons Pty Ltd",
    "wof:placetype":"venue"
},
  "geometry": {"coordinates":[140.35133400000001,-37.593342],"type":"Point"}
}