{
  "type": "Feature",
  "properties": {
    "addr:full":"4 Australia St Camperdown NSW 2050",
    "addr:postcode":"2050",
    "addr:street":"Australia St",
    "iso:country":"AU",
    "sg:address":"4 Australia St",
    "sg:city":"Camperdown",
    "sg:classifiers":[
        {
            "category":"Food & Beverages",
            "subcategory":"Specialty",
            "type":"Retail Goods"
        }
    ],
    "sg:phone":"+61 2 9550 5477",
    "sg:postcode":"2050",
    "sg:province":"NSW",
    "sg:tags":[
        "delicacy"
    ],
    "wof:name":"Essential Ingredient The",
    "wof:placetype":"venue"
},
  "geometry": {"coordinates":[151.17489599999999,-33.888275],"type":"Point"}
}