{
  "type": "Feature",
  "properties": {
    "iso:country":"AU",
    "sg:address":"400 Albany Hwy",
    "sg:city":"Albany",
    "sg:classifiers":[
        {
            "category":"Autos & Motor Vehicles",
            "subcategory":"Automobile Sales",
            "type":"Retail Goods"
        }
    ],
    "sg:phone":"+61 1800 442 468",
    "sg:postcode":"6330",
    "sg:province":"WA",
    "sg:tags":[
        "car",
        "new"
    ],
    "wof:name":"Albany Hyundai",
    "wof:placetype":"venue"
},
  "geometry": {"coordinates":[117.860969544,-34.9982643127],"type":"Point"}
}