{
  "type": "Feature",
  "properties": {
    "iso:country":"AU",
    "sg:address":"Unit 8/ 4 Pinacle St",
    "sg:city":"Brendale",
    "sg:classifiers":[
        {
            "category":"Shopping",
            "subcategory":"Stationery & Office Supplies",
            "type":"Retail Goods"
        }
    ],
    "sg:phone":"+61 7 3205 9416",
    "sg:postcode":"4500",
    "sg:province":"QLD",
    "sg:tags":[
        "equipment",
        "display",
        "exhibition"
    ],
    "wof:name":"Versatile Signs",
    "wof:placetype":"venue"
},
  "geometry": {"coordinates":[152.976730347,-27.3172721863],"type":"Point"}
}