{
  "type": "Feature",
  "properties": {
    "iso:country":"AU",
    "sg:address":"254 East St",
    "sg:city":"Rockhampton",
    "sg:classifiers":[
        {
            "category":"Travel",
            "subcategory":"Hotels & Motels",
            "type":"Entertainment"
        }
    ],
    "sg:phone":"+61 7 4922 2660",
    "sg:postcode":"4700",
    "sg:province":"QLD",
    "sg:tags":[
        "accommodation"
    ],
    "wof:name":"Pioneer Hotel",
    "wof:placetype":"venue"
},
  "geometry": {"coordinates":[150.52182006800001,-23.3898582458],"type":"Point"}
}