{
  "type": "Feature",
  "properties": {
    "addr:full":"436 George St Deniliquin NSW 2710",
    "addr:housenumber":"436",
    "addr:postcode":"2710",
    "addr:street":"George St",
    "iso:country":"AU",
    "sg:address":"436 George St",
    "sg:city":"Deniliquin",
    "sg:classifiers":[
        {
            "category":"Professional",
            "subcategory":"Accounting & Tax Preparation",
            "type":"Services"
        }
    ],
    "sg:phone":"+61 3 5881 7113",
    "sg:postcode":"2710",
    "sg:province":"NSW",
    "sg:tags":[
        "accountant",
        "auditor"
    ],
    "wof:name":"Jennings Brian Accounting Services",
    "wof:placetype":"venue"
},
  "geometry": {"coordinates":[144.959716797,-35.5235671997],"type":"Point"}
}