{
  "type": "Feature",
  "properties": {
    "iso:country":"AU",
    "sg:address":"54 Anzac Ave",
    "sg:city":"Hillcrest",
    "sg:classifiers":[
        {
            "category":"Retail",
            "subcategory":"Event Space",
            "type":"Services"
        }
    ],
    "sg:phone":"+61 7 3800 7746",
    "sg:postcode":"4118",
    "sg:province":"QLD",
    "sg:tags":[
        "venue",
        "reception",
        "wedding"
    ],
    "wof:name":"Greenbank R.S.L. Services Club",
    "wof:placetype":"venue"
},
  "geometry": {"coordinates":[153.03225707999999,-27.6681365967],"type":"Point"}
}