{
  "type": "Feature",
  "properties": {
    "iso:country":"AU",
    "sg:address":"17 Magdalena Pl",
    "sg:city":"Rowville",
    "sg:classifiers":[
        {
            "category":"Personal",
            "subcategory":"Massage",
            "type":"Services"
        }
    ],
    "sg:phone":"+61 3 9755 6128",
    "sg:postcode":"3178",
    "sg:province":"VIC",
    "sg:tags":[
        "therapy"
    ],
    "wof:name":"Magenta Healing",
    "wof:placetype":"venue"
},
  "geometry": {"coordinates":[145.24534606899999,-37.9314002991],"type":"Point"}
}