{
  "type": "Feature",
  "properties": {
    "iso:country":"AU",
    "sg:address":"Muirillup Rd",
    "sg:city":"Northcliffe",
    "sg:classifiers":[
        {
            "category":"Farming",
            "subcategory":"Vineyard",
            "type":"Manufacturing & Wholesale Goods"
        }
    ],
    "sg:phone":"+61 8 9776 7145",
    "sg:postcode":"6262",
    "sg:province":"WA",
    "sg:tags":[
        "winery"
    ],
    "wof:name":"Petrene Estate",
    "wof:placetype":"venue"
},
  "geometry": {"coordinates":[116.124511719,-34.6330833435],"type":"Point"}
}