{
  "type": "Feature",
  "properties": {
    "iso:country":"AU",
    "sg:address":"36 Beringarra Ave",
    "sg:city":"Malaga",
    "sg:classifiers":[
        {
            "category":"Building & Trades",
            "subcategory":"Construction",
            "type":"Services"
        }
    ],
    "sg:phone":"+61 8 9249 0850",
    "sg:postcode":"6090",
    "sg:province":"WA",
    "sg:tags":[
        "installation",
        "air conditioning"
    ],
    "wof:name":"Testcom Engineering",
    "wof:placetype":"venue"
},
  "geometry": {"coordinates":[115.896682739,-31.8635864258],"type":"Point"}
}