{
  "type": "Feature",
  "properties": {
    "addr:full":"Woolworths Complex Murray Bridge SA 5253",
    "addr:postcode":"5253",
    "iso:country":"AU",
    "sg:address":"Woolworths Complex",
    "sg:city":"Murray Bridge",
    "sg:classifiers":[
        {
            "category":"Shopping",
            "subcategory":"Computers & Home Electronics",
            "type":"Retail Goods"
        }
    ],
    "sg:phone":"+61 8 8531 0445",
    "sg:postcode":"5253",
    "sg:province":"SA",
    "sg:tags":[
        "equipment",
        "part",
        "electronic"
    ],
    "wof:name":"Tandy Electronics",
    "wof:placetype":"venue"
},
  "geometry": {"coordinates":[139.38796997099999,-35.1085395813],"type":"Point"}
}