{
  "type": "Feature",
  "properties": {
    "addr:full":"27 Goenoeng Drv Tanah Merah QLD 4128",
    "addr:housenumber":"27",
    "addr:postcode":"4128",
    "addr:street":"Goenoeng Drv",
    "iso:country":"AU",
    "sg:address":"27 Goenoeng Drv",
    "sg:city":"Tanah Merah",
    "sg:classifiers":[
        {
            "category":"Health Services",
            "subcategory":"Health Practitioner",
            "type":"Services"
        }
    ],
    "sg:phone":"+61 7 3209 8611",
    "sg:postcode":"4128",
    "sg:province":"QLD",
    "sg:tags":[
        "naturopath"
    ],
    "wof:name":"Caring Natural Therapies",
    "wof:placetype":"venue"
},
  "geometry": {"coordinates":[153.17132568400001,-27.6686420441],"type":"Point"}
}