{
  "type": "Feature",
  "properties": {
    "iso:country":"AU",
    "sg:address":"Box 14, Mount Pleasant, SA, 5235",
    "sg:city":"Mt Pleasant",
    "sg:classifiers":[
        {
            "category":"Farming",
            "subcategory":"Vineyard",
            "type":"Manufacturing & Wholesale Goods"
        }
    ],
    "sg:phone":"+61 8 8568 2470",
    "sg:postcode":"5235",
    "sg:province":"SA",
    "sg:tags":[
        "winery"
    ],
    "wof:name":"Patalunga Vineyard",
    "wof:placetype":"venue"
},
  "geometry": {"coordinates":[139.039672852,-34.7788200378],"type":"Point"}
}