{
  "type": "Feature",
  "properties": {
    "addr:full":"Shop 10a Wallaceway Endeavour St Chatswood NSW 2067",
    "addr:housenumber":"10a",
    "addr:postcode":"2067",
    "addr:street":"Wallaceway Endeavour St",
    "iso:country":"AU",
    "sg:address":"Shop 10a Wallaceway Endeavour St",
    "sg:city":"Chatswood",
    "sg:classifiers":[
        {
            "category":"Communications",
            "subcategory":"Film & Video Production",
            "type":"Services"
        }
    ],
    "sg:phone":"+61 2 9413 3454",
    "sg:postcode":"2067",
    "sg:province":"NSW",
    "sg:tags":[
        "dvd",
        "library"
    ],
    "wof:name":"Korean Video Shop",
    "wof:placetype":"venue"
},
  "geometry": {"coordinates":[151.18205261200001,-33.7958335876],"type":"Point"}
}