{
  "type": "Feature",
  "properties": {
    "addr:full":"Ste 16, 885 Albany Hwy East Victoria Park WA 6101",
    "addr:housenumber":"885",
    "addr:postcode":"6101",
    "addr:street":"Albany Hwy",
    "iso:country":"AU",
    "sg:address":"Ste 16, 885 Albany Hwy",
    "sg:city":"East Victoria Park",
    "sg:classifiers":[
        {
            "category":"Banks & Credit Unions",
            "subcategory":"Bank",
            "type":"Services"
        }
    ],
    "sg:phone":"+61 8 9472 0211",
    "sg:postcode":"6101",
    "sg:province":"WA",
    "sg:tags":[
        "broker",
        "mortgage"
    ],
    "wof:name":"Mortgage Choice",
    "wof:placetype":"venue"
},
  "geometry": {"coordinates":[115.903991699,-31.9861850739],"type":"Point"}
}