{
  "type": "Feature",
  "properties": {
    "addr:full":"Playgroup House 3 Echunpa St Alice Springs NT 0870",
    "addr:housenumber":"3",
    "addr:postcode":"nt 0870",
    "addr:street":"Echunpa St",
    "iso:country":"AU",
    "sg:address":"Playgroup House 3 Echunpa St",
    "sg:city":"Alice Springs",
    "sg:classifiers":[
        {
            "category":"Recreation",
            "type":"Entertainment"
        }
    ],
    "sg:phone":"+61 8 8953 4496",
    "sg:postcode":"0870",
    "sg:province":"NT",
    "sg:tags":[
        "children's",
        "play",
        "programme"
    ],
    "wof:name":"Playground Association Of N.T. Incorporated",
    "wof:placetype":"venue"
},
  "geometry": {"coordinates":[133.870483398,-23.7158432007],"type":"Point"}
}