{
  "type": "Feature",
  "properties": {
    "addr:full":"207 High St Northcote VIC 3070",
    "addr:housenumber":"207",
    "addr:postcode":"3070",
    "addr:street":"High St",
    "iso:country":"AU",
    "sg:address":"207 High St",
    "sg:city":"Northcote",
    "sg:classifiers":[
        {
            "category":"Real Estate",
            "subcategory":"Real Estate Services",
            "type":"Services"
        }
    ],
    "sg:phone":"+61 3 9489 8046",
    "sg:postcode":"3070",
    "sg:province":"VIC",
    "sg:tags":[
        "valuer"
    ],
    "wof:name":"Raine & Horne Valuations (VIC)",
    "wof:placetype":"venue"
},
  "geometry": {"coordinates":[144.99787900000001,-37.774117],"type":"Point"}
}