{
  "type": "Feature",
  "properties": {
    "iso:country":"AU",
    "sg:address":"38 Aitken St",
    "sg:city":"Gisborne",
    "sg:classifiers":[
        {
            "category":"Shopping",
            "subcategory":"Clothing, Apparel, & Fashions",
            "type":"Retail Goods"
        }
    ],
    "sg:phone":"+61 3 5428 4186",
    "sg:postcode":"3437",
    "sg:province":"VIC",
    "sg:tags":[
        "lady",
        "wear"
    ],
    "wof:name":"Ellie B Fashions",
    "wof:placetype":"venue"
},
  "geometry": {"coordinates":[144.59088134800001,-37.4873352051],"type":"Point"}
}