{
  "type": "Feature",
  "properties": {
    "addr:full":"PO Box 339 Kew East VIC 3102",
    "addr:postcode":"3102",
    "iso:country":"AU",
    "sg:address":"PO Box 339",
    "sg:city":"Kew East",
    "sg:classifiers":[
        {
            "category":"Professional",
            "subcategory":"Art Services",
            "type":"Services"
        }
    ],
    "sg:phone":"+61 410 592 620",
    "sg:postcode":"3102",
    "sg:province":"VIC",
    "sg:tags":[
        "decorator",
        "painter"
    ],
    "wof:name":"Glenferrie Painting",
    "wof:placetype":"venue"
},
  "geometry": {"coordinates":[145.05108642600001,-37.7905311584],"type":"Point"}
}