{
  "type": "Feature",
  "properties": {
    "addr:full":"2 Chapel St Marrickville NSW 2204",
    "addr:housenumber":"2",
    "addr:postcode":"2204",
    "addr:street":"Chapel St",
    "iso:country":"AU",
    "sg:address":"2 Chapel St",
    "sg:city":"Marrickville",
    "sg:classifiers":[
        {
            "category":"Retail",
            "subcategory":"Storage",
            "type":"Services"
        }
    ],
    "sg:phone":"+61 1300 657 447",
    "sg:postcode":"2204",
    "sg:province":"NSW",
    "sg:tags":[
        "shelving",
        "system"
    ],
    "wof:name":"Access Office Systems",
    "wof:placetype":"venue"
},
  "geometry": {"coordinates":[151.16645800000001,-33.908592],"type":"Point"}
}