{
  "type": "Feature",
  "properties": {
    "addr:full":"104 Granard Rd Rocklea QLD 4106",
    "addr:housenumber":"104",
    "addr:postcode":"4106",
    "addr:street":"Granard Rd",
    "iso:country":"AU",
    "sg:address":"104 Granard Rd",
    "sg:city":"Rocklea",
    "sg:classifiers":[
        {
            "category":"Fast Food",
            "type":"Food & Drink"
        }
    ],
    "sg:phone":"+61 7 3272 7512",
    "sg:postcode":"4106",
    "sg:province":"QLD",
    "sg:tags":[
        "away",
        "take"
    ],
    "wof:name":"Hungry Jacks",
    "wof:placetype":"venue"
},
  "geometry": {"coordinates":[153.01661682100001,-27.5580806732],"type":"Point"}
}