{
  "type": "Feature",
  "properties": {
    "addr:full":"19 Ayrshire St Busby NSW 2168",
    "addr:housenumber":"19",
    "addr:postcode":"2168",
    "addr:street":"Ayrshire St",
    "iso:country":"AU",
    "sg:address":"19 Ayrshire St",
    "sg:city":"Busby",
    "sg:classifiers":[
        {
            "category":"Building & Trades",
            "subcategory":"Construction",
            "type":"Services"
        }
    ],
    "sg:phone":"+61 414 444 442",
    "sg:postcode":"2168",
    "sg:province":"NSW",
    "sg:tags":[
        "contractor"
    ],
    "wof:name":"Nouvo Remodelling",
    "wof:placetype":"venue"
},
  "geometry": {"coordinates":[150.885375977,-33.9140548706],"type":"Point"}
}