{
  "type": "Feature",
  "properties": {
    "addr:full":"9 O'Neil St Unanderra NSW 2526",
    "addr:housenumber":"9",
    "addr:postcode":"2526",
    "addr:street":"O'Neil St",
    "iso:country":"AU",
    "sg:address":"9 O'Neil St",
    "sg:city":"Unanderra",
    "sg:classifiers":[
        {
            "category":"Manufacturing",
            "subcategory":"Tools & Machinery",
            "type":"Manufacturing & Wholesale Goods"
        }
    ],
    "sg:phone":"+61 1800 686 411",
    "sg:postcode":"2526",
    "sg:province":"NSW",
    "sg:tags":[
        "earth",
        "excavating",
        "moving",
        "equipment"
    ],
    "wof:name":"Avant Mini Loaders",
    "wof:placetype":"venue"
},
  "geometry": {"coordinates":[150.85151672399999,-34.4493331909],"type":"Point"}
}