{
  "type": "Feature",
  "properties": {
    "iso:country":"AU",
    "sg:address":"Unit 1 42 Bacon St",
    "sg:city":"Hindmarsh",
    "sg:classifiers":[
        {
            "category":"Recreation",
            "subcategory":"Fishing",
            "type":"Entertainment"
        }
    ],
    "sg:phone":"+61 8 8346 8088",
    "sg:postcode":"5007",
    "sg:province":"SA",
    "sg:tags":[
        "tackle"
    ],
    "wof:name":"Top Shot Tackle (Aust)",
    "wof:placetype":"venue"
},
  "geometry": {"coordinates":[138.566680908,-34.9081611633],"type":"Point"}
}