{
  "type": "Feature",
  "properties": {
    "addr:full":"147- 149 Regency Rd Croydon Park SA 5008",
    "addr:housenumber":"149",
    "addr:postcode":"5008",
    "addr:street":"Regency Rd",
    "iso:country":"AU",
    "sg:address":"147- 149 Regency Rd",
    "sg:city":"Croydon Park",
    "sg:phone":"+61 8 8346 6288",
    "sg:postcode":"5008",
    "sg:province":"SA",
    "wof:name":"Australian Glass Fusion",
    "wof:placetype":"venue"
},
  "geometry": {"coordinates":[138.56857299999999,-34.875343],"type":"Point"}
}