{
  "type": "Feature",
  "properties": {
    "iso:country":"AU",
    "sg:address":"147- 149 Regency Rd",
    "sg:city":"Croydon Park",
    "sg:phone":"+61 8 8346 6288",
    "sg:postcode":"5008",
    "sg:province":"SA",
    "wof:name":"Australian Glass Fusion",
    "wof:placetype":"venue"
},
  "geometry": {"coordinates":[138.568573,-34.875343],"type":"Point"}
}