{
  "type": "Feature",
  "properties": {
    "addr:full":"20 Kareena Rd Miranda NSW 2228",
    "addr:housenumber":"20",
    "addr:postcode":"2228",
    "addr:street":"Kareena Rd",
    "iso:country":"AU",
    "sg:address":"20 Kareena Rd",
    "sg:city":"Miranda",
    "sg:classifiers":[
        {
            "category":"Train Station",
            "subcategory":"Rail",
            "type":"Transportation"
        }
    ],
    "sg:phone":"+61 2 9540 9979",
    "sg:postcode":"2228",
    "sg:province":"NSW",
    "sg:tags":[
        "marine",
        "engineer"
    ],
    "wof:name":"Botany Bay Marine Service Pty Ltd",
    "wof:placetype":"venue"
},
  "geometry": {"coordinates":[151.114868164,-34.0290222168],"type":"Point"}
}