{
  "type": "Feature",
  "properties": {
    "addr:full":"914- 918 Pacific Hwy Chatswood NSW 2067",
    "addr:housenumber":"918",
    "addr:postcode":"2067",
    "addr:street":"Pacific Hwy",
    "iso:country":"AU",
    "sg:address":"914- 918 Pacific Hwy",
    "sg:city":"Chatswood",
    "sg:classifiers":[
        {
            "category":"Food & Beverages",
            "subcategory":"Liquor & Beverages",
            "type":"Retail Goods"
        }
    ],
    "sg:phone":"+61 2 9419 2790",
    "sg:postcode":"2067",
    "sg:province":"NSW",
    "sg:tags":[
        "store"
    ],
    "wof:name":"Vintage Cellars",
    "wof:placetype":"venue"
},
  "geometry": {"coordinates":[151.180053711,-33.7893066406],"type":"Point"}
}