{
  "type": "Feature",
  "properties": {
    "iso:country":"AU",
    "sg:address":"Nexus Industry Park Building 2 43-47 Lyn Pde",
    "sg:city":"Prestons",
    "sg:classifiers":[
        {
            "category":"Banks & Credit Unions",
            "subcategory":"Bank",
            "type":"Services"
        }
    ],
    "sg:phone":"+61 2 9723 6700",
    "sg:postcode":"2170",
    "sg:province":"NSW",
    "sg:tags":[
        "concrete",
        "reinforcement"
    ],
    "wof:name":"EW Reinforcement",
    "wof:placetype":"venue"
},
  "geometry": {"coordinates":[150.88760375999999,-33.931098938],"type":"Point"}
}