{
  "type": "Feature",
  "properties": {
    "addr:full":"Unit 5 Bronwyn St Caloundra QLD 4551",
    "addr:postcode":"4551",
    "addr:street":"Bronwyn St",
    "iso:country":"AU",
    "sg:address":"Unit 5 Bronwyn St",
    "sg:city":"Caloundra",
    "sg:classifiers":[
        {
            "category":"Retail",
            "subcategory":"Auto Repair",
            "type":"Services"
        }
    ],
    "sg:phone":"+61 7 5491 5966",
    "sg:postcode":"4551",
    "sg:province":"QLD",
    "sg:tags":[
        "transmission",
        "automotive",
        "car"
    ],
    "wof:name":"Performance Torque Converters",
    "wof:placetype":"venue"
},
  "geometry": {"coordinates":[153.11129760700001,-26.7937831879],"type":"Point"}
}