{
  "type": "Feature",
  "properties": {
    "addr:full":"16 High St Toronto NSW 2283",
    "addr:housenumber":"16",
    "addr:postcode":"2283",
    "addr:street":"High St",
    "iso:country":"AU",
    "sg:address":"16 High St",
    "sg:city":"Toronto",
    "sg:classifiers":[
        {
            "category":"Shopping",
            "subcategory":"Stationery & Office Supplies",
            "type":"Retail Goods"
        }
    ],
    "sg:phone":"+61 2 4950 5999",
    "sg:postcode":"2283",
    "sg:province":"NSW",
    "sg:tags":[
        "packaging",
        "material"
    ],
    "wof:name":"Pelican Packaging",
    "wof:placetype":"venue"
},
  "geometry": {"coordinates":[151.57362365700001,-33.0023574829],"type":"Point"}
}