{
  "type": "Feature",
  "properties": {
    "addr:full":"4/ 99 Dora St Morisset NSW 2264",
    "addr:housenumber":"/ 99",
    "addr:postcode":"2264",
    "addr:street":"Dora St",
    "iso:country":"AU",
    "sg:address":"4/ 99 Dora St",
    "sg:city":"Morisset",
    "sg:classifiers":[
        {
            "category":"Real Estate",
            "subcategory":"Real Estate Agent",
            "type":"Services"
        }
    ],
    "sg:phone":"+61 2 4970 5411",
    "sg:postcode":"2264",
    "sg:province":"NSW",
    "wof:name":"Ray White Morisset",
    "wof:placetype":"venue"
},
  "geometry": {"coordinates":[151.486221,-33.10936],"type":"Point"}
}