{
  "type": "Feature",
  "properties": {
    "iso:country":"AU",
    "sg:address":"21 Spring St",
    "sg:city":"Padstow",
    "sg:classifiers":[
        {
            "category":"Landmark",
            "subcategory":"Scenic View",
            "type":"Public Place"
        }
    ],
    "sg:phone":"+61 408 492 950",
    "sg:postcode":"2211",
    "sg:province":"NSW",
    "sg:tags":[
        "staircase",
        "handrail"
    ],
    "wof:name":"OneStep Carpentry",
    "wof:placetype":"venue"
},
  "geometry": {"coordinates":[151.026367,-33.954247],"type":"Point"}
}