{
  "type": "Feature",
  "properties": {
    "addr:full":"169 Tannery Rd Cambewarra NSW 2540",
    "addr:housenumber":"169",
    "addr:postcode":"2540",
    "addr:street":"Tannery Rd",
    "iso:country":"AU",
    "sg:address":"169 Tannery Rd",
    "sg:city":"Cambewarra",
    "sg:classifiers":[
        {
            "category":"Commercial Area",
            "type":"Public Place"
        }
    ],
    "sg:phone":"+61 2 4446 0209",
    "sg:postcode":"2540",
    "sg:province":"NSW",
    "sg:tags":[
        "heavy",
        "carrier"
    ],
    "wof:name":"Murray Smith & Sons Heavy Haulage",
    "wof:placetype":"venue"
},
  "geometry": {"coordinates":[150.56260681099999,-34.8085823059],"type":"Point"}
}