{
  "type": "Feature",
  "properties": {
    "iso:country":"AU",
    "sg:address":"82 Berry St",
    "sg:city":"Yamanto",
    "sg:classifiers":[
        {
            "category":"Manufacturing",
            "subcategory":"Glass & Minerals",
            "type":"Manufacturing & Wholesale Goods"
        }
    ],
    "sg:phone":"+61 7 3281 9759",
    "sg:postcode":"4305",
    "sg:province":"QLD",
    "sg:tags":[
        "fabricator",
        "fibreglass"
    ],
    "wof:name":"Stella Manufacturing",
    "wof:placetype":"venue"
},
  "geometry": {"coordinates":[152.743896484,-27.6482753754],"type":"Point"}
}