{
  "type": "Feature",
  "properties": {
    "iso:country":"AU",
    "sg:address":"4 Walter St",
    "sg:city":"Glenroy",
    "sg:classifiers":[
        {
            "category":"Bars & Pubs",
            "subcategory":"Gay Bar",
            "type":"Food & Drink"
        }
    ],
    "sg:phone":"+61 3 9304 9615",
    "sg:postcode":"3046",
    "sg:province":"VIC",
    "sg:tags":[
        "plywood",
        "veneer"
    ],
    "wof:name":"Amerind Pty Ltd",
    "wof:placetype":"venue"
},
  "geometry": {"coordinates":[144.945388794,-37.7122802734],"type":"Point"}
}