{
  "type": "Feature",
  "properties": {
    "iso:country":"AU",
    "sg:address":"Shp 1/ 48 Owen St",
    "sg:city":"Huskisson",
    "sg:classifiers":[
        {
            "category":"Restaurant",
            "type":"Food & Drink"
        }
    ],
    "sg:phone":"+61 2 4441 7070",
    "sg:postcode":"2540",
    "sg:province":"NSW",
    "wof:name":"Caffe Motza",
    "wof:placetype":"venue"
},
  "geometry": {"coordinates":[150.66928100600001,-35.0387077332],"type":"Point"}
}