{
  "type": "Feature",
  "properties": {
    "addr:full":"R.M.B 1309 Buffalo Creek Rd Myrtleford VIC 3737",
    "addr:housenumber":"1309",
    "addr:postcode":"3737",
    "addr:street":"R.M.B;Buffalo Creek Rd",
    "iso:country":"AU",
    "sg:address":"R.M.B 1309 Buffalo Creek Rd",
    "sg:city":"Myrtleford",
    "sg:classifiers":[
        {
            "category":"Professional",
            "subcategory":"Engineering",
            "type":"Services"
        }
    ],
    "sg:phone":"+61 3 5752 1652",
    "sg:postcode":"3737",
    "sg:province":"VIC",
    "sg:tags":[
        "engineer"
    ],
    "wof:name":"G S M Mobile Engineering Pty. Ltd.",
    "wof:placetype":"venue"
},
  "geometry": {"coordinates":[146.762405395,-36.6389312744],"type":"Point"}
}