{
  "type": "Feature",
  "properties": {
    "addr:full":"Settlement City 1 Bay St Port Macquarie NSW 2444",
    "addr:housenumber":"1",
    "addr:postcode":"2444",
    "addr:street":"Bay St",
    "iso:country":"AU",
    "sg:address":"Settlement City 1 Bay St",
    "sg:city":"Port Macquarie",
    "sg:classifiers":[
        {
            "category":"Organizations",
            "subcategory":"Membership Organization",
            "type":"Services"
        }
    ],
    "sg:phone":"+61 2 6582 3023",
    "sg:postcode":"2444",
    "sg:province":"NSW",
    "sg:tags":[
        "club",
        "bridge"
    ],
    "wof:name":"Port Macquarie RSL Bridge Club",
    "wof:placetype":"venue"
},
  "geometry": {"coordinates":[152.89323400000001,-31.429144],"type":"Point"}
}