{
  "type": "Feature",
  "properties": {
    "iso:country":"AU",
    "sg:address":"293 Crown St",
    "sg:city":"Wollongong",
    "sg:classifiers":[
        {
            "category":"Shopping",
            "subcategory":"Bridal",
            "type":"Retail Goods"
        }
    ],
    "sg:phone":"+61 2 4225 0044",
    "sg:postcode":"2500",
    "sg:province":"NSW",
    "sg:tags":[
        "hire",
        "wear"
    ],
    "sg:website":"http://www.trenzboutique.com.au",
    "wof:name":"Trenz Boutique Bridal & Formal Wear",
    "wof:placetype":"venue"
},
  "geometry": {"coordinates":[150.890381,-34.425648],"type":"Point"}
}