{
  "type": "Feature",
  "properties": {
    "addr:full":"Lvl 2/ 28 Foveaux St Surry Hills NSW 2010",
    "addr:housenumber":"/ 28",
    "addr:postcode":"2010",
    "addr:street":"Foveaux St",
    "iso:country":"AU",
    "sg:address":"Lvl 2/ 28 Foveaux St",
    "sg:city":"Surry Hills",
    "sg:classifiers":[
        {
            "category":"Education",
            "subcategory":"School",
            "type":"Public Place"
        }
    ],
    "sg:phone":"+61 2 9212 0504",
    "sg:postcode":"2010",
    "sg:province":"NSW",
    "wof:name":"Cornell Institute Of Business & Technology",
    "wof:placetype":"venue"
},
  "geometry": {"coordinates":[151.209915161,-33.8839302063],"type":"Point"}
}