{
  "type": "Feature",
  "properties": {
    "iso:country":"AU",
    "sg:address":"53 Industral Ave",
    "sg:city":"Hoppers Crossing",
    "sg:classifiers":[
        {
            "category":"Building & Trades",
            "subcategory":"Construction",
            "type":"Services"
        }
    ],
    "sg:phone":"+61 3 9749 1644",
    "sg:postcode":"3029",
    "sg:province":"VIC",
    "sg:tags":[
        "insulation",
        "contractor"
    ],
    "wof:name":"Lombardo Insulation Pty Ltd",
    "wof:placetype":"venue"
},
  "geometry": {"coordinates":[144.732086,-37.867664],"type":"Point"}
}