{
  "type": "Feature",
  "properties": {
    "iso:country":"AU",
    "sg:address":"22 Mills St",
    "sg:city":"Cheltenham",
    "sg:classifiers":[
        {
            "category":"Autos & Motor Vehicles",
            "subcategory":"Auto Supplies",
            "type":"Retail Goods"
        }
    ],
    "sg:phone":"+61 3 9585 0636",
    "sg:postcode":"3192",
    "sg:province":"VIC",
    "sg:tags":[
        "part",
        "cycles",
        "accessory"
    ],
    "wof:name":"Moorabbin Motorcycle Engineering",
    "wof:placetype":"venue"
},
  "geometry": {"coordinates":[145.074493408,-37.9564552307],"type":"Point"}
}