{
  "type": "Feature",
  "properties": {
    "addr:full":"85 Waterway Drv Coomera QLD 4209",
    "addr:housenumber":"85",
    "addr:postcode":"4209",
    "addr:street":"Waterway Drv",
    "iso:country":"AU",
    "sg:address":"85 Waterway Drv",
    "sg:city":"Coomera",
    "sg:classifiers":[
        {
            "category":"Autos & Motor Vehicles",
            "subcategory":"Boat Sales",
            "type":"Retail Goods"
        }
    ],
    "sg:phone":"+61 7 5556 1900",
    "sg:postcode":"4209",
    "sg:province":"QLD",
    "sg:tags":[
        "yacht"
    ],
    "wof:name":"Mariner",
    "wof:placetype":"venue"
},
  "geometry": {"coordinates":[153.33282470699999,-27.8681316376],"type":"Point"}
}