{
  "type": "Feature",
  "properties": {
    "iso:country":"AU",
    "sg:address":"Suite 4/ 105 Keira St",
    "sg:city":"Wollongong",
    "sg:classifiers":[
        {
            "category":"Education",
            "subcategory":"Special Training",
            "type":"Public Place"
        }
    ],
    "sg:phone":"+61 2 4229 6650",
    "sg:postcode":"2500",
    "sg:province":"NSW",
    "sg:tags":[
        "tuition-educational"
    ],
    "wof:name":"James An Coaching College",
    "wof:placetype":"venue"
},
  "geometry": {"coordinates":[150.893967,-34.421665],"type":"Point"}
}