{
  "type": "Feature",
  "properties": {
    "iso:country":"AU",
    "sg:address":"20 Stanley St",
    "sg:city":"Randwick",
    "sg:classifiers":[
        {
            "category":"Education",
            "subcategory":"School",
            "type":"Public Place"
        }
    ],
    "sg:phone":"+61 2 9398 8388",
    "sg:postcode":"2031",
    "sg:province":"NSW",
    "sg:tags":[
        "co-educational"
    ],
    "wof:name":"Emanuel School",
    "wof:placetype":"venue"
},
  "geometry": {"coordinates":[151.24325561500001,-33.907497406],"type":"Point"}
}