{
  "type": "Feature",
  "properties": {
    "addr:full":"18 Milham St St Marys NSW 2760",
    "addr:housenumber":"18",
    "addr:postcode":"2760",
    "addr:street":"Milham St",
    "iso:country":"AU",
    "sg:address":"18 Milham St",
    "sg:city":"St Marys",
    "sg:classifiers":[
        {
            "category":"Building & Trades",
            "subcategory":"Construction",
            "type":"Services"
        }
    ],
    "sg:phone":"+61 412 404 540",
    "sg:postcode":"2760",
    "sg:province":"NSW",
    "sg:tags":[
        "contractor"
    ],
    "wof:name":"Stafford Constructions Pty Ltd",
    "wof:placetype":"venue"
},
  "geometry": {"coordinates":[150.77633667000001,-33.7778663635],"type":"Point"}
}