{
  "type": "Feature",
  "properties": {
    "addr:full":"2055 Rowlands Rd (LIA) Collie WA 6225",
    "addr:housenumber":"2055",
    "addr:postcode":"6225",
    "addr:street":"Rowlands Rd",
    "iso:country":"AU",
    "sg:address":"2055 Rowlands Rd (LIA)",
    "sg:city":"Collie",
    "sg:classifiers":[
        {
            "category":"Retail",
            "subcategory":"Auto Repair",
            "type":"Services"
        }
    ],
    "sg:phone":"+61 8 9734 3500",
    "sg:postcode":"6225",
    "sg:province":"WA",
    "sg:tags":[
        "repairer",
        "motor",
        "engineer"
    ],
    "wof:name":"Von Bibra Motors",
    "wof:placetype":"venue"
},
  "geometry": {"coordinates":[116.141533,-33.346706],"type":"Point"}
}