{
  "type": "Feature",
  "properties": {
    "addr:full":"89 Main Rd Clayton South VIC 3169",
    "addr:housenumber":"89",
    "addr:postcode":"3169",
    "addr:street":"Main Rd",
    "iso:country":"AU",
    "sg:address":"89 Main Rd",
    "sg:city":"Clayton South",
    "sg:classifiers":[
        {
            "category":"Autos & Motor Vehicles",
            "subcategory":"Auto Supplies",
            "type":"Retail Goods"
        }
    ],
    "sg:phone":"+61 3 9547 9994",
    "sg:postcode":"3169",
    "sg:province":"VIC",
    "sg:tags":[
        "garage",
        "equipment"
    ],
    "wof:name":"Abbott Engineering",
    "wof:placetype":"venue"
},
  "geometry": {"coordinates":[145.126464844,-37.9409980774],"type":"Point"}
}