{
  "type": "Feature",
  "properties": {
    "iso:country":"AU",
    "sg:address":"76 Hallett Rd",
    "sg:city":"Burnside",
    "sg:classifiers":[
        {
            "category":"Food & Beverages",
            "subcategory":"Bakery",
            "type":"Retail Goods"
        }
    ],
    "sg:phone":"+61 8 8431 2883",
    "sg:postcode":"5066",
    "sg:province":"SA",
    "sg:tags":[
        "cake",
        "shop",
        "pastry"
    ],
    "wof:name":"R & I Cakes",
    "wof:placetype":"venue"
},
  "geometry": {"coordinates":[138.66920471200001,-34.9369659424],"type":"Point"}
}