{
  "type": "Feature",
  "properties": {
    "iso:country":"AU",
    "sg:address":"1062 Westfield Shopngtwn St",
    "sg:city":"Miranda",
    "sg:classifiers":[
        {
            "category":"Fast Food",
            "type":"Food & Drink"
        }
    ],
    "sg:phone":"+61 2 9540 5677",
    "sg:postcode":"2228",
    "sg:province":"NSW",
    "sg:tags":[
        "away",
        "take"
    ],
    "wof:name":"KFC",
    "wof:placetype":"venue"
},
  "geometry": {"coordinates":[151.102493286,-34.033908844],"type":"Point"}
}