{
  "type": "Feature",
  "properties": {
    "iso:country":"AU",
    "sg:address":"39 Kernot St",
    "sg:city":"Spotswood",
    "sg:classifiers":[
        {
            "category":"Personal",
            "subcategory":"Massage",
            "type":"Services"
        }
    ],
    "sg:phone":"+61 3 9399 4997",
    "sg:postcode":"3015",
    "sg:province":"VIC",
    "sg:tags":[
        "therapy"
    ],
    "wof:name":"Petran Stelian",
    "wof:placetype":"venue"
},
  "geometry": {"coordinates":[144.873046875,-37.8295097351],"type":"Point"}
}