{
  "type": "Feature",
  "properties": {
    "addr:full":"18 Clements Ave Bundoora VIC 3083",
    "addr:housenumber":"18",
    "addr:postcode":"3083",
    "addr:street":"Clements Ave",
    "iso:country":"AU",
    "sg:address":"18 Clements Ave",
    "sg:city":"Bundoora",
    "sg:classifiers":[
        {
            "category":"Retail",
            "subcategory":"Auto Repair",
            "type":"Services"
        }
    ],
    "sg:phone":"+61 3 9467 4588",
    "sg:postcode":"3083",
    "sg:province":"VIC",
    "sg:tags":[
        "beater",
        "painter",
        "panel"
    ],
    "wof:name":"Watsmith Panel Repair Service",
    "wof:placetype":"venue"
},
  "geometry": {"coordinates":[145.07322692899999,-37.7018280029],"type":"Point"}
}