{
  "type": "Feature",
  "properties": {
    "addr:full":"Unit 4, 191 Hedley Ave Hendra QLD 4011",
    "addr:housenumber":"191",
    "addr:postcode":"4011",
    "addr:street":"Hedley Ave",
    "iso:country":"AU",
    "sg:address":"Unit 4, 191 Hedley Ave",
    "sg:city":"Hendra",
    "sg:classifiers":[
        {
            "category":"Wholesale",
            "subcategory":"Electrical",
            "type":"Manufacturing & Wholesale Goods"
        }
    ],
    "sg:phone":"+61 7 3623 0300",
    "sg:postcode":"4011",
    "sg:province":"QLD",
    "sg:tags":[
        "wholesaler",
        "mfrs",
        "accessory"
    ],
    "wof:name":"Dulmison / Utilux",
    "wof:placetype":"venue"
},
  "geometry": {"coordinates":[153.07371499999999,-27.413883],"type":"Point"}
}