{
  "type": "Feature",
  "properties": {
    "addr:full":"299 Toorak Rd South Yarra VIC 3141",
    "addr:housenumber":"299",
    "addr:postcode":"3141",
    "addr:street":"Toorak Rd",
    "iso:country":"AU",
    "sg:address":"299 Toorak Rd",
    "sg:city":"South Yarra",
    "sg:classifiers":[
        {
            "category":"Restaurant",
            "type":"Food & Drink"
        }
    ],
    "sg:phone":"+61 3 9826 2277",
    "sg:postcode":"3141",
    "sg:province":"VIC",
    "wof:name":"Bizzarri Restaurant Two",
    "wof:placetype":"venue"
},
  "geometry": {"coordinates":[144.99740600600001,-37.8395729065],"type":"Point"}
}