{
  "type": "Feature",
  "properties": {
    "addr:full":"150 Edgecliff Rd Woollahra NSW 2025",
    "addr:housenumber":"150",
    "addr:postcode":"2025",
    "addr:street":"Edgecliff Rd",
    "iso:country":"AU",
    "sg:address":"150 Edgecliff Rd",
    "sg:city":"Woollahra",
    "sg:classifiers":[
        {
            "category":"Professional",
            "subcategory":"Art Services",
            "type":"Services"
        }
    ],
    "sg:phone":"+61 2 9369 5407",
    "sg:postcode":"2025",
    "sg:province":"NSW",
    "sg:tags":[
        "interior",
        "designer"
    ],
    "wof:name":"Estelle Coxall Interiors",
    "wof:placetype":"venue"
},
  "geometry": {"coordinates":[151.24203491200001,-33.8848152161],"type":"Point"}
}