{
  "type": "Feature",
  "properties": {
    "addr:full":"15 Burwood Ave Woodville North SA 5012",
    "addr:housenumber":"15",
    "addr:postcode":"5012",
    "addr:street":"Burwood Ave",
    "iso:country":"AU",
    "sg:address":"15 Burwood Ave",
    "sg:city":"Woodville North",
    "sg:classifiers":[
        {
            "category":"Landmark",
            "subcategory":"Fountain",
            "type":"Public Place"
        }
    ],
    "sg:phone":"+61 8 8345 1770",
    "sg:postcode":"5012",
    "sg:province":"SA",
    "sg:tags":[
        "wholesaler",
        "spring",
        "mfrs"
    ],
    "wof:name":"CITY SPRINGS",
    "wof:placetype":"venue"
},
  "geometry": {"coordinates":[138.539352417,-34.8678359985],"type":"Point"}
}