{
  "type": "Feature",
  "properties": {
    "addr:full":"95 Queen St Ulverstone West TAS 7315",
    "addr:housenumber":"95",
    "addr:postcode":"7315",
    "addr:street":"Queen St",
    "iso:country":"AU",
    "sg:address":"95 Queen St",
    "sg:city":"Ulverstone West",
    "sg:classifiers":[
        {
            "category":"Professional",
            "subcategory":"Art Services",
            "type":"Services"
        }
    ],
    "sg:phone":"+61 418 142 974",
    "sg:postcode":"7315",
    "sg:province":"TAS",
    "sg:tags":[
        "decorator",
        "painter"
    ],
    "wof:name":"Compagne John Pty Ltd",
    "wof:placetype":"venue"
},
  "geometry": {"coordinates":[146.161056519,-41.1456947327],"type":"Point"}
}