{
  "type": "Feature",
  "properties": {
    "iso:country":"AU",
    "sg:address":"185 Payneham Rd",
    "sg:city":"St Peters",
    "sg:classifiers":[
        {
            "category":"Health Services",
            "subcategory":"Doctor",
            "type":"Services"
        }
    ],
    "sg:phone":"+61 8 8363 7433",
    "sg:postcode":"5069",
    "sg:province":"SA",
    "sg:tags":[
        "medical",
        "practitioner"
    ],
    "wof:name":"Sidhu Shireen Dr",
    "wof:placetype":"venue"
},
  "geometry": {"coordinates":[138.629806519,-34.9070510864],"type":"Point"}
}