{
  "type": "Feature",
  "properties": {
    "addr:full":"Durkin Rd Kambalda WA 6442",
    "addr:postcode":"6442",
    "addr:street":"Durkin Rd",
    "iso:country":"AU",
    "sg:address":"Durkin Rd",
    "sg:city":"Kambalda",
    "sg:classifiers":[
        {
            "category":"Professional",
            "type":"Services"
        }
    ],
    "sg:phone":"+61 8 9027 1696",
    "sg:postcode":"6442",
    "sg:province":"WA",
    "sg:tags":[
        "industrial",
        "commercial",
        "catering"
    ],
    "wof:name":"ESS Support Services Worldwide",
    "wof:placetype":"venue"
},
  "geometry": {"coordinates":[121.652931213,-31.1984405518],"type":"Point"}
}