{
  "type": "Feature",
  "properties": {
    "addr:full":"Building D2 350-374 Parramatta Rd Homebush NSW 2140",
    "addr:housenumber":"350-374",
    "addr:postcode":"2140",
    "addr:street":"Parramatta Rd",
    "iso:country":"AU",
    "sg:address":"Building D2 350-374 Parramatta Rd",
    "sg:city":"Homebush",
    "sg:classifiers":[
        {
            "category":"Manufacturing",
            "subcategory":"Signs",
            "type":"Manufacturing & Wholesale Goods"
        }
    ],
    "sg:phone":"+61 1300 768 899",
    "sg:postcode":"2140",
    "sg:province":"NSW",
    "sg:tags":[
        "traffic",
        "safety"
    ],
    "wof:name":"De Neefe Signs",
    "wof:placetype":"venue"
},
  "geometry": {"coordinates":[151.06439209000001,-33.8564796448],"type":"Point"}
}