{
  "type": "Feature",
  "properties": {
    "addr:full":"36 David St Turner ACT 2612",
    "addr:housenumber":"36",
    "addr:postcode":"2612",
    "addr:street":"David St",
    "iso:country":"AU",
    "sg:address":"36 David St",
    "sg:city":"Turner",
    "sg:classifiers":[
        {
            "category":"Health Services",
            "subcategory":"Chiropractor",
            "type":"Services"
        }
    ],
    "sg:phone":"+61 2 6257 9400",
    "sg:postcode":"2612",
    "sg:province":"ACT",
    "wof:name":"David St Family Chiropractic",
    "wof:placetype":"venue"
},
  "geometry": {"coordinates":[149.12574768100001,-35.2635726929],"type":"Point"}
}