{
  "type": "Feature",
  "properties": {
    "addr:full":"52b Anderson Ave Panania NSW 2213",
    "addr:housenumber":"52b",
    "addr:postcode":"2213",
    "addr:street":"Anderson Ave",
    "iso:country":"AU",
    "sg:address":"52b Anderson Ave",
    "sg:city":"Panania",
    "sg:classifiers":[
        {
            "category":"Organizations",
            "subcategory":"Membership Organization",
            "type":"Services"
        }
    ],
    "sg:phone":"+61 2 9774 3334",
    "sg:postcode":"2213",
    "sg:province":"NSW",
    "sg:tags":[
        "club",
        "car"
    ],
    "wof:name":"Corvettes NSW Corvettes Unlimited",
    "wof:placetype":"venue"
},
  "geometry": {"coordinates":[150.99850499999999,-33.953571],"type":"Point"}
}