{
  "type": "Feature",
  "properties": {
    "iso:country":"AU",
    "sg:address":"4 Haydock St",
    "sg:city":"Bunbury",
    "sg:classifiers":[
        {
            "category":"Manufacturing",
            "subcategory":"Metals",
            "type":"Manufacturing & Wholesale Goods"
        }
    ],
    "sg:phone":"+61 8 9792 4698",
    "sg:postcode":"6230",
    "sg:province":"WA",
    "sg:tags":[
        "merchant"
    ],
    "wof:name":"M & L Connop Services",
    "wof:placetype":"venue"
},
  "geometry": {"coordinates":[115.63606299999999,-33.317104],"type":"Point"}
}