{
  "type": "Feature",
  "properties": {
    "addr:full":"U12/ 30 Raubers Rd Northgate QLD 4013",
    "addr:postcode":"4013",
    "addr:street":"/ 30 Raubers Rd",
    "iso:country":"AU",
    "sg:address":"U12/ 30 Raubers Rd",
    "sg:city":"Northgate",
    "sg:classifiers":[
        {
            "category":"Fast Food",
            "type":"Food & Drink"
        }
    ],
    "sg:phone":"+61 7 3267 5188",
    "sg:postcode":"4013",
    "sg:province":"QLD",
    "sg:tags":[
        "away",
        "take"
    ],
    "wof:name":"Zac's Place",
    "wof:placetype":"venue"
},
  "geometry": {"coordinates":[153.085205078,-27.3908653259],"type":"Point"}
}