{
  "type": "Feature",
  "properties": {
    "addr:full":"2 Lyton St Blacktown NSW 2148",
    "addr:housenumber":"2",
    "addr:postcode":"2148",
    "addr:street":"Lyton St",
    "iso:country":"AU",
    "sg:address":"2 Lyton St",
    "sg:city":"Blacktown",
    "sg:classifiers":[
        {
            "category":"Fast Food",
            "type":"Food & Drink"
        }
    ],
    "sg:phone":"+61 2 9622 2596",
    "sg:postcode":"2148",
    "sg:province":"NSW",
    "sg:tags":[
        "away",
        "take"
    ],
    "wof:name":"Red Rooster",
    "wof:placetype":"venue"
},
  "geometry": {"coordinates":[150.89431762699999,-33.7575950623],"type":"Point"}
}