{
  "type": "Feature",
  "properties": {
    "iso:country":"AU",
    "sg:address":"66 Lindsay St",
    "sg:city":"Toowoomba",
    "sg:classifiers":[
        {
            "category":"Government",
            "subcategory":"Court House",
            "type":"Public Place"
        }
    ],
    "sg:phone":"+61 7 4639 3367",
    "sg:postcode":"4350",
    "sg:province":"QLD",
    "sg:tags":[
        "personal",
        "marriage",
        "family",
        "counselling"
    ],
    "sg:website":"http://www.magnoliahousepysch.com.au",
    "wof:name":"Magnolia House",
    "wof:placetype":"venue"
},
  "geometry": {"coordinates":[151.964127,-27.561832],"type":"Point"}
}