{
  "type": "Feature",
  "properties": {
    "addr:full":"Cnr Beryl St & Empire Lane Tweed Heads NSW 2485",
    "addr:postcode":"2485",
    "addr:street":"Cnr Beryl St & Empire Lane",
    "iso:country":"AU",
    "sg:address":"Cnr Beryl St & Empire Lane",
    "sg:city":"Tweed Heads",
    "sg:classifiers":[
        {
            "category":"Shopping",
            "subcategory":"Clothing, Apparel, & Fashions",
            "type":"Retail Goods"
        }
    ],
    "sg:phone":"+61 7 5536 5536",
    "sg:postcode":"2485",
    "sg:province":"NSW",
    "sg:tags":[
        "recycled",
        "clothing"
    ],
    "wof:name":"Lifeline Gold Coast",
    "wof:placetype":"venue"
},
  "geometry": {"coordinates":[153.54112243599999,-28.1744289398],"type":"Point"}
}