{
  "type": "Feature",
  "properties": {
    "iso:country":"AU",
    "sg:address":"114 Tiger St",
    "sg:city":"Maryborough",
    "sg:classifiers":[
        {
            "category":"Home & Garden",
            "subcategory":"Garden Supply",
            "type":"Retail Goods"
        }
    ],
    "sg:phone":"+61 7 4121 0251",
    "sg:postcode":"4650",
    "sg:province":"QLD",
    "sg:tags":[
        "equipment",
        "hydroponics"
    ],
    "wof:name":"D & D Horticultural & Hydroponics Supplies",
    "wof:placetype":"venue"
},
  "geometry": {"coordinates":[152.713043,-25.544682],"type":"Point"}
}