{
  "type": "Feature",
  "properties": {
    "addr:full":"3 Earls Crt Oakey QLD 4401",
    "addr:housenumber":"3",
    "addr:postcode":"4401",
    "addr:street":"Earls Crt",
    "iso:country":"AU",
    "sg:address":"3 Earls Crt",
    "sg:city":"Oakey",
    "sg:classifiers":[
        {
            "category":"Building & Trades",
            "subcategory":"Cleaning & Sanitation",
            "type":"Services"
        }
    ],
    "sg:phone":"+61 7 4691 1812",
    "sg:postcode":"4401",
    "sg:province":"QLD",
    "sg:tags":[
        "industrial",
        "commercial",
        "contractor"
    ],
    "wof:name":"Hursts Cleaning Service",
    "wof:placetype":"venue"
},
  "geometry": {"coordinates":[151.72253418,-27.4418201447],"type":"Point"}
}