{
  "type": "Feature",
  "properties": {
    "addr:full":"Level 1,Shop 29,Bridgepoint,1- 3 Brady St Mosman NSW 2088",
    "addr:housenumber":"shop 29;1 3",
    "addr:postcode":"2088",
    "addr:street":"Bridgepoint;Brady St",
    "iso:country":"AU",
    "sg:address":"Level 1,Shop 29,Bridgepoint,1- 3 Brady St",
    "sg:city":"Mosman",
    "sg:classifiers":[
        {
            "category":"Personal",
            "subcategory":"Beauty Salon",
            "type":"Services"
        }
    ],
    "sg:phone":"+61 2 9968 2911",
    "sg:postcode":"2088",
    "sg:province":"NSW",
    "sg:tags":[
        "hairdresser"
    ],
    "wof:name":"Sharp Image Hair Studio",
    "wof:placetype":"venue"
},
  "geometry": {"coordinates":[151.24055480999999,-33.8225517273],"type":"Point"}
}