{
  "type": "Feature",
  "properties": {
    "addr:full":"2 Old Waratah Rd Fish Creek VIC 3959",
    "addr:housenumber":"2",
    "addr:postcode":"3959",
    "addr:street":"Old Waratah Rd",
    "iso:country":"AU",
    "sg:address":"2 Old Waratah Rd",
    "sg:city":"Fish Creek",
    "sg:classifiers":[
        {
            "category":"Fast Food",
            "type":"Food & Drink"
        }
    ],
    "sg:phone":"+61 3 5683 2207",
    "sg:postcode":"3959",
    "sg:province":"VIC",
    "sg:tags":[
        "away",
        "take"
    ],
    "wof:name":"Gateway Take Away",
    "wof:placetype":"venue"
},
  "geometry": {"coordinates":[146.082122803,-38.6945915222],"type":"Point"}
}