{
  "type": "Feature",
  "properties": {
    "iso:country":"AU",
    "sg:address":"35 Model La",
    "sg:city":"Port Fairy",
    "sg:classifiers":[
        {
            "category":"Building & Trades",
            "subcategory":"Construction",
            "type":"Services"
        }
    ],
    "sg:phone":"+61 419 386 323",
    "sg:postcode":"3284",
    "sg:province":"VIC",
    "sg:tags":[
        "contractor"
    ],
    "wof:name":"BA Building Services",
    "wof:placetype":"venue"
},
  "geometry": {"coordinates":[142.227127075,-38.3846092224],"type":"Point"}
}