{
  "type": "Feature",
  "properties": {
    "addr:full":"56 Moss St Slacks Creek QLD 4127",
    "addr:housenumber":"56",
    "addr:postcode":"4127",
    "addr:street":"Moss St",
    "iso:country":"AU",
    "sg:address":"56 Moss St",
    "sg:city":"Slacks Creek",
    "sg:classifiers":[
        {
            "category":"Fast Food",
            "type":"Food & Drink"
        }
    ],
    "sg:phone":"+61 7 3208 8135",
    "sg:postcode":"4127",
    "sg:province":"QLD",
    "sg:tags":[
        "away",
        "take"
    ],
    "wof:name":"Hungry Tummy Snack Bar",
    "wof:placetype":"venue"
},
  "geometry": {"coordinates":[153.12203979500001,-27.6218070984],"type":"Point"}
}