{
  "type": "Feature",
  "properties": {
    "addr:full":"Dougherty Cntr 7 Victor St Chatswood NSW 2067",
    "addr:housenumber":"7",
    "addr:postcode":"2067",
    "addr:street":"Cntr;Victor St",
    "iso:country":"AU",
    "sg:address":"Dougherty Cntr 7 Victor St",
    "sg:city":"Chatswood",
    "sg:classifiers":[
        {
            "category":"Health Services",
            "subcategory":"Doctor",
            "type":"Services"
        }
    ],
    "sg:phone":"+61 2 9777 7810",
    "sg:postcode":"2067",
    "sg:province":"NSW",
    "sg:tags":[
        "podiatrist"
    ],
    "wof:name":"Collins G, Hinchliffe N, Manning N",
    "wof:placetype":"venue"
},
  "geometry": {"coordinates":[151.183151245,-33.7990722656],"type":"Point"}
}