{
  "type": "Feature",
  "properties": {
    "addr:full":"63 Bosanquet Ave Prospect SA 5082",
    "addr:housenumber":"63",
    "addr:postcode":"5082",
    "addr:street":"Bosanquet Ave",
    "iso:country":"AU",
    "sg:address":"63 Bosanquet Ave",
    "sg:city":"Prospect",
    "sg:classifiers":[
        {
            "category":"Building & Trades",
            "subcategory":"Construction",
            "type":"Services"
        }
    ],
    "sg:phone":"+61 412 805 144",
    "sg:postcode":"5082",
    "sg:province":"SA",
    "sg:tags":[
        "ceiling"
    ],
    "wof:name":"A1 Mark's Ceilings",
    "wof:placetype":"venue"
},
  "geometry": {"coordinates":[138.587722778,-34.8832130432],"type":"Point"}
}