{
  "type": "Feature",
  "properties": {
    "addr:full":"622 Ferntree Gully Rd Wheelers Hill VIC 3150",
    "addr:housenumber":"622",
    "addr:postcode":"3150",
    "addr:street":"Ferntree Gully Rd",
    "iso:country":"AU",
    "sg:address":"622 Ferntree Gully Rd",
    "sg:city":"Wheelers Hill",
    "sg:classifiers":[
        {
            "category":"Insurance",
            "subcategory":"Insurance Agent",
            "type":"Services"
        }
    ],
    "sg:phone":"+61 3 9562 2244",
    "sg:postcode":"3150",
    "sg:province":"VIC",
    "sg:tags":[
        "broker"
    ],
    "wof:name":"Insurance Advisernet Australia Pty Limited",
    "wof:placetype":"venue"
},
  "geometry": {"coordinates":[145.16346740700001,-37.9036026001],"type":"Point"}
}