{
  "type": "Feature",
  "properties": {
    "addr:full":"15 Tweed Crt Wattlegrove NSW 2625",
    "addr:housenumber":"15",
    "addr:postcode":"2625",
    "addr:street":"Tweed Crt",
    "iso:country":"AU",
    "sg:address":"15 Tweed Crt",
    "sg:city":"Wattlegrove",
    "sg:classifiers":[
        {
            "category":"Professional",
            "subcategory":"Accounting & Tax Preparation",
            "type":"Services"
        }
    ],
    "sg:phone":"+61 2 9825 1838",
    "sg:postcode":"2625",
    "sg:province":"NSW",
    "sg:tags":[
        "bookkeeping"
    ],
    "wof:name":"MIM Accounting & Bookkeeping Services",
    "wof:placetype":"venue"
},
  "geometry": {"coordinates":[148.30847168,-36.5016517639],"type":"Point"}
}