{
  "type": "Feature",
  "properties": {
    "addr:full":"223 Buckley St Essendon VIC 3040",
    "addr:housenumber":"223",
    "addr:postcode":"3040",
    "addr:street":"Buckley St",
    "iso:country":"AU",
    "sg:address":"223 Buckley St",
    "sg:city":"Essendon",
    "sg:classifiers":[
        {
            "category":"Shopping",
            "subcategory":"Bridal",
            "type":"Retail Goods"
        }
    ],
    "sg:phone":"+61 3 9337 6685",
    "sg:postcode":"3040",
    "sg:province":"VIC",
    "sg:tags":[
        "hire",
        "wear"
    ],
    "wof:name":"Brides On Buckley",
    "wof:placetype":"venue"
},
  "geometry": {"coordinates":[144.907714844,-37.7561454773],"type":"Point"}
}