{
  "type": "Feature",
  "properties": {
    "addr:full":"226 Scott St Cairns QLD 4870",
    "addr:housenumber":"226",
    "addr:postcode":"4870",
    "addr:street":"Scott St",
    "iso:country":"AU",
    "sg:address":"226 Scott St",
    "sg:city":"Cairns",
    "sg:classifiers":[
        {
            "category":"Wholesale",
            "subcategory":"Electrical",
            "type":"Manufacturing & Wholesale Goods"
        }
    ],
    "sg:phone":"+61 7 4033 1299",
    "sg:postcode":"4870",
    "sg:province":"QLD",
    "sg:tags":[
        "wholesaler"
    ],
    "wof:name":"Haymans Electrical",
    "wof:placetype":"venue"
},
  "geometry": {"coordinates":[145.75083923299999,-16.9411582947],"type":"Point"}
}