{
  "type": "Feature",
  "properties": {
    "addr:full":"2 Midland Hwy Elmore VIC 3558",
    "addr:housenumber":"2",
    "addr:postcode":"3558",
    "addr:street":"Midland Hwy",
    "iso:country":"AU",
    "sg:address":"2 Midland Hwy",
    "sg:city":"Elmore",
    "sg:classifiers":[
        {
            "category":"Utilities",
            "subcategory":"Fuel Oil & Lpg",
            "type":"Services"
        }
    ],
    "sg:phone":"+61 3 5432 6087",
    "sg:postcode":"3558",
    "sg:province":"VIC",
    "sg:tags":[
        "olive"
    ],
    "wof:name":"Campaspe Grove",
    "wof:placetype":"venue"
},
  "geometry": {"coordinates":[144.61131286599999,-36.4985160828],"type":"Point"}
}