{
  "type": "Feature",
  "properties": {
    "addr:full":"Shop 19a 655 Merrrylands Rd Greystanes NSW 2145",
    "addr:housenumber":"19a",
    "addr:postcode":"655;2145",
    "addr:street":"Merrrylands Rd",
    "iso:country":"AU",
    "sg:address":"Shop 19a 655 Merrrylands Rd",
    "sg:city":"Greystanes",
    "sg:classifiers":[
        {
            "category":"Personal",
            "subcategory":"Beauty Salon",
            "type":"Services"
        }
    ],
    "sg:phone":"+61 2 9769 0243",
    "sg:postcode":"2145",
    "sg:province":"NSW",
    "wof:name":"Cosmo Nails & Beauty",
    "wof:placetype":"venue"
},
  "geometry": {"coordinates":[150.939819336,-33.8285293579],"type":"Point"}
}