{
  "type": "Feature",
  "properties": {
    "addr:full":"Suite 6 24 Brown Rd Broadmeadow NSW 2292",
    "addr:housenumber":"24",
    "addr:postcode":"2292",
    "addr:street":"Brown Rd",
    "iso:country":"AU",
    "sg:address":"Suite 6 24 Brown Rd",
    "sg:city":"Broadmeadow",
    "sg:classifiers":[
        {
            "category":"Health Services",
            "subcategory":"Doctor",
            "type":"Services"
        }
    ],
    "sg:phone":"+61 2 4961 6966",
    "sg:postcode":"2292",
    "sg:province":"NSW",
    "sg:tags":[
        "medical",
        "practitioner"
    ],
    "wof:name":"Verheul Richard",
    "wof:placetype":"venue"
},
  "geometry": {"coordinates":[151.73362731899999,-32.9230194092],"type":"Point"}
}