{
  "type": "Feature",
  "properties": {
    "addr:full":"39 Bambil St Crestmead QLD 4132",
    "addr:housenumber":"39",
    "addr:postcode":"4132",
    "addr:street":"Bambil St",
    "iso:country":"AU",
    "sg:address":"39 Bambil St",
    "sg:city":"Crestmead",
    "sg:classifiers":[
        {
            "category":"Professional",
            "subcategory":"Computer Services",
            "type":"Services"
        }
    ],
    "sg:phone":"+61 7 3200 5282",
    "sg:postcode":"4132",
    "sg:province":"QLD",
    "sg:tags":[
        "tele-communications",
        "consultant"
    ],
    "wof:name":"Oztech Communications",
    "wof:placetype":"venue"
},
  "geometry": {"coordinates":[153.097412109,-27.6826343536],"type":"Point"}
}