{
  "type": "Feature",
  "properties": {
    "addr:full":"72 Johnson Pde Blackwood SA 5051",
    "addr:housenumber":"72",
    "addr:postcode":"5051",
    "addr:street":"Johnson Pde",
    "iso:country":"AU",
    "sg:address":"72 Johnson Pde",
    "sg:city":"Blackwood",
    "sg:classifiers":[
        {
            "category":"Food & Beverages",
            "subcategory":"Specialty",
            "type":"Retail Goods"
        }
    ],
    "sg:phone":"+61 8 8370 3320",
    "sg:postcode":"5051",
    "sg:province":"SA",
    "sg:tags":[
        "product",
        "health"
    ],
    "wof:name":"Natures Sunshine Products",
    "wof:placetype":"venue"
},
  "geometry": {"coordinates":[138.61053466800001,-35.0259780884],"type":"Point"}
}