{
  "type": "Feature",
  "properties": {
    "addr:full":"Shp 9, Burton St Vincentia NSW 2540",
    "addr:housenumber":"9",
    "addr:postcode":"2540",
    "addr:street":"Burton St",
    "iso:country":"AU",
    "sg:address":"Shp 9, Burton St",
    "sg:city":"Vincentia",
    "sg:classifiers":[
        {
            "category":"Banks & Credit Unions",
            "subcategory":"Bank",
            "type":"Services"
        }
    ],
    "sg:phone":"+61 13 20 32",
    "sg:postcode":"2540",
    "sg:province":"NSW",
    "wof:name":"Westpac",
    "wof:placetype":"venue"
},
  "geometry": {"coordinates":[150.675216675,-35.0707321167],"type":"Point"}
}