{
  "type": "Feature",
  "properties": {
    "iso:country":"AU",
    "sg:address":"PO Box 170",
    "sg:city":"Georges Hall",
    "sg:classifiers":[
        {
            "category":"Professional",
            "subcategory":"Detective & Security Services",
            "type":"Services"
        }
    ],
    "sg:phone":"+61 419 626 362",
    "sg:postcode":"2198",
    "sg:province":"NSW",
    "sg:tags":[
        "investigator"
    ],
    "wof:name":"Victoria Jay Investigations & Security",
    "wof:placetype":"venue"
},
  "geometry": {"coordinates":[150.98924299999999,-33.907829],"type":"Point"}
}