{
  "type": "Feature",
  "properties": {
    "addr:full":"68 Bond St West Mordialloc VIC 3195",
    "addr:housenumber":"68",
    "addr:postcode":"3195",
    "addr:street":"Bond St West",
    "iso:country":"AU",
    "sg:address":"68 Bond St West",
    "sg:city":"Mordialloc",
    "sg:classifiers":[
        {
            "category":"Professional",
            "subcategory":"Research",
            "type":"Services"
        }
    ],
    "sg:phone":"+61 3 9587 2266",
    "sg:postcode":"3195",
    "sg:province":"VIC",
    "sg:tags":[
        "industrial",
        "scientific"
    ],
    "wof:name":"McConnell Research Enterprises Pty Ltd",
    "wof:placetype":"venue"
},
  "geometry": {"coordinates":[145.09872436500001,-37.9917640686],"type":"Point"}
}