{
  "type": "Feature",
  "properties": {
    "addr:full":"5 Sutton St Spotswood VIC 3015",
    "addr:housenumber":"5",
    "addr:postcode":"3015",
    "addr:street":"Sutton St",
    "iso:country":"AU",
    "sg:address":"5 Sutton St",
    "sg:city":"Spotswood",
    "sg:classifiers":[
        {
            "category":"Wholesale",
            "subcategory":"Machinery & Supplies",
            "type":"Manufacturing & Wholesale Goods"
        }
    ],
    "sg:phone":"+61 3 9391 1522",
    "sg:postcode":"3015",
    "sg:province":"VIC",
    "sg:tags":[
        "equipment",
        "laboratory"
    ],
    "wof:name":"Able",
    "wof:placetype":"venue"
},
  "geometry": {"coordinates":[144.87631225600001,-37.8338813782],"type":"Point"}
}