{
  "type": "Feature",
  "properties": {
    "addr:full":"U2/ 6 Christie St St Marys NSW 2760",
    "addr:housenumber":"6",
    "addr:postcode":"2760",
    "addr:street":"U2 /;Christie St",
    "iso:country":"AU",
    "sg:address":"U2/ 6 Christie St",
    "sg:city":"St Marys",
    "sg:classifiers":[
        {
            "category":"Building & Trades",
            "subcategory":"Construction",
            "type":"Services"
        }
    ],
    "sg:phone":"+61 406 787 449",
    "sg:postcode":"2760",
    "sg:province":"NSW",
    "sg:tags":[
        "welding"
    ],
    "wof:name":"S.I.T.E Steel",
    "wof:placetype":"venue"
},
  "geometry": {"coordinates":[150.77580261200001,-33.7477302551],"type":"Point"}
}