{
  "type": "Feature",
  "properties": {
    "addr:full":"Chapel La Baulkham Hills NSW 2153",
    "addr:postcode":"2153",
    "addr:street":"Chapel La",
    "iso:country":"AU",
    "sg:address":"Chapel La",
    "sg:city":"Baulkham Hills",
    "sg:classifiers":[
        {
            "category":"Education",
            "subcategory":"School",
            "type":"Public Place"
        }
    ],
    "sg:phone":"+61 2 9639 0518",
    "sg:postcode":"2153",
    "sg:province":"NSW",
    "wof:name":"St Michael's School",
    "wof:placetype":"venue"
},
  "geometry": {"coordinates":[151.03805542000001,-33.732585907],"type":"Point"}
}