{
  "type": "Feature",
  "properties": {
    "iso:country":"AU",
    "sg:address":"18 Cook St",
    "sg:city":"Yamba",
    "sg:classifiers":[
        {
            "category":"Real Estate",
            "subcategory":"Surveying",
            "type":"Services"
        }
    ],
    "sg:phone":"+61 412 618 168",
    "sg:postcode":"2464",
    "sg:province":"NSW",
    "sg:tags":[
        "surveyor",
        "land"
    ],
    "wof:name":"Steve Brailsford Surveying",
    "wof:placetype":"venue"
},
  "geometry": {"coordinates":[153.342697144,-29.4372406006],"type":"Point"}
}