{
  "type": "Feature",
  "properties": {
    "addr:full":"10 Landy Rd Jacana VIC 3047",
    "addr:housenumber":"10",
    "addr:postcode":"3047",
    "addr:street":"Landy Rd",
    "iso:country":"AU",
    "sg:address":"10 Landy Rd",
    "sg:city":"Jacana",
    "sg:classifiers":[
        {
            "category":"Commercial Area",
            "type":"Public Place"
        }
    ],
    "sg:phone":"+61 3 9302 1340",
    "sg:postcode":"3047",
    "sg:province":"VIC",
    "sg:tags":[
        "heavy",
        "carrier"
    ],
    "wof:name":"Lawman Haulage",
    "wof:placetype":"venue"
},
  "geometry": {"coordinates":[144.91354370100001,-37.6902084351],"type":"Point"}
}