{
  "type": "Feature",
  "properties": {
    "addr:full":"Shp 1/ 92 Charles St Seddon VIC 3011",
    "addr:housenumber":"/ 92",
    "addr:postcode":"3011",
    "addr:street":"Charles St",
    "iso:country":"AU",
    "sg:address":"Shp 1/ 92 Charles St",
    "sg:city":"Seddon",
    "sg:classifiers":[
        {
            "category":"Food & Beverages",
            "subcategory":"Fruits & Vegetables",
            "type":"Retail Goods"
        }
    ],
    "sg:phone":"+61 3 9689 0039",
    "sg:postcode":"3011",
    "sg:province":"VIC",
    "sg:tags":[
        "consultant",
        "catering"
    ],
    "wof:name":"Your Friend in the Kitchen",
    "wof:placetype":"venue"
},
  "geometry": {"coordinates":[144.890625,-37.8063774109],"type":"Point"}
}