{
  "type": "Feature",
  "properties": {
    "iso:country":"AU",
    "sg:address":"Oro Rd",
    "sg:city":"Dwellingup",
    "sg:classifiers":[
        {
            "category":"Farming",
            "subcategory":"Berry Farm",
            "type":"Manufacturing & Wholesale Goods"
        }
    ],
    "sg:phone":"+61 8 9538 1015",
    "sg:postcode":"6213",
    "sg:province":"WA",
    "sg:tags":[
        "fruit",
        "grower"
    ],
    "wof:name":"Oro Farms",
    "wof:placetype":"venue"
},
  "geometry": {"coordinates":[116.044296,-32.723789],"type":"Point"}
}