{
  "type": "Feature",
  "properties": {
    "addr:full":"129 Hobart Rd Kings Meadows TAS 7249",
    "addr:housenumber":"129",
    "addr:postcode":"7249",
    "addr:street":"Hobart Rd",
    "iso:country":"AU",
    "sg:address":"129 Hobart Rd",
    "sg:city":"Kings Meadows",
    "sg:classifiers":[
        {
            "category":"Fast Food",
            "type":"Food & Drink"
        }
    ],
    "sg:phone":"+61 3 6344 4068",
    "sg:postcode":"7249",
    "sg:province":"TAS",
    "sg:tags":[
        "away",
        "take"
    ],
    "wof:name":"Kings Meadows Seafood",
    "wof:placetype":"venue"
},
  "geometry": {"coordinates":[147.16004943900001,-41.4665603638],"type":"Point"}
}