{
  "type": "Feature",
  "properties": {
    "iso:country":"AU",
    "sg:address":"424- 426 King St",
    "sg:city":"Newtown",
    "sg:classifiers":[
        {
            "category":"Retail",
            "subcategory":"Auto Repair",
            "type":"Services"
        }
    ],
    "sg:phone":"+61 2 9550 3088",
    "sg:postcode":"2042",
    "sg:province":"NSW",
    "sg:tags":[
        "repairer",
        "motor",
        "engineer"
    ],
    "wof:name":"King Street Autos",
    "wof:placetype":"venue"
},
  "geometry": {"coordinates":[151.178314,-33.900288],"type":"Point"}
}