{
  "type": "Feature",
  "properties": {
    "addr:full":"46 Bowen St Moonee Ponds VIC 3039",
    "addr:housenumber":"46",
    "addr:postcode":"3039",
    "addr:street":"Bowen St",
    "iso:country":"AU",
    "sg:address":"46 Bowen St",
    "sg:city":"Moonee Ponds",
    "sg:classifiers":[
        {
            "category":"Health Services",
            "subcategory":"Health Practitioner",
            "type":"Services"
        }
    ],
    "sg:phone":"+61 3 9326 1641",
    "sg:postcode":"3039",
    "sg:province":"VIC",
    "sg:tags":[
        "naturopath"
    ],
    "wof:name":"Chrysalis Natural Therapies",
    "wof:placetype":"venue"
},
  "geometry": {"coordinates":[144.91004899999999,-37.76683],"type":"Point"}
}