{
  "type": "Feature",
  "properties": {
    "addr:full":"Bldg 3/ 130 Fauntleroy Ave Perth Airport WA 6105",
    "addr:housenumber":"130",
    "addr:postcode":"6105",
    "addr:street":"Fauntleroy Ave",
    "iso:country":"AU",
    "sg:address":"Bldg 3/ 130 Fauntleroy Ave",
    "sg:city":"Perth Airport",
    "sg:classifiers":[
        {
            "category":"Professional",
            "type":"Services"
        }
    ],
    "sg:phone":"+61 8 9479 3399",
    "sg:postcode":"6105",
    "sg:province":"WA",
    "sg:tags":[
        "courier"
    ],
    "wof:name":"Austmail Worldwide Express Couriers",
    "wof:placetype":"venue"
},
  "geometry": {"coordinates":[115.94947052000001,-31.9240379333],"type":"Point"}
}