{
  "type": "Feature",
  "properties": {
    "iso:country":"AU",
    "sg:address":"Cnr Of Parrmatta Rd & Missenden Rd",
    "sg:city":"Camperdown",
    "sg:classifiers":[
        {
            "category":"Autos & Motor Vehicles",
            "subcategory":"Fuel & Gas Station",
            "type":"Retail Goods"
        }
    ],
    "sg:phone":"+61 2 9519 6330",
    "sg:postcode":"2050",
    "sg:province":"NSW",
    "wof:name":"BP Australia Pty Ltd",
    "wof:placetype":"venue"
},
  "geometry": {"coordinates":[151.177185,-33.88866],"type":"Point"}
}