{
  "type": "Feature",
  "properties": {
    "addr:full":"56 Queen Elizabeth Drv Rockhampton QLD 4700",
    "addr:housenumber":"56",
    "addr:postcode":"4700",
    "addr:street":"Queen Elizabeth Drv",
    "iso:country":"AU",
    "sg:address":"56 Queen Elizabeth Drv",
    "sg:city":"Rockhampton",
    "sg:classifiers":[
        {
            "category":"Autos & Motor Vehicles",
            "subcategory":"Automobile Sales",
            "type":"Retail Goods"
        }
    ],
    "sg:phone":"+61 7 4922 3602",
    "sg:postcode":"4700",
    "sg:province":"QLD",
    "sg:tags":[
        "equipment",
        "trailer"
    ],
    "wof:name":"O&#039;Maras Camper Trailers",
    "wof:placetype":"venue"
},
  "geometry": {"coordinates":[150.52053832999999,-23.3689308167],"type":"Point"}
}