{
  "type": "Feature",
  "properties": {
    "addr:full":"5 Rose Crt Reservoir VIC 3073",
    "addr:housenumber":"5",
    "addr:postcode":"3073",
    "addr:street":"Rose Crt",
    "iso:country":"AU",
    "sg:address":"5 Rose Crt",
    "sg:city":"Reservoir",
    "sg:classifiers":[
        {
            "category":"Professional",
            "subcategory":"Detective & Security Services",
            "type":"Services"
        }
    ],
    "sg:phone":"+61 411 192 846",
    "sg:postcode":"3073",
    "sg:province":"VIC",
    "sg:tags":[
        "domestic",
        "alarm",
        "commercial",
        "burglar"
    ],
    "wof:name":"Insecurity Alarm Installations",
    "wof:placetype":"venue"
},
  "geometry": {"coordinates":[144.99977111800001,-37.7222671509],"type":"Point"}
}