{
  "type": "Feature",
  "properties": {
    "addr:full":"1/ 58 The Strand North Ward QLD 4810",
    "addr:housenumber":"/ 58",
    "addr:postcode":"4810",
    "addr:street":"The Strand",
    "iso:country":"AU",
    "sg:address":"1/ 58 The Strand",
    "sg:city":"North Ward",
    "sg:classifiers":[
        {
            "category":"Fast Food",
            "type":"Food & Drink"
        }
    ],
    "sg:phone":"+61 7 4721 1388",
    "sg:postcode":"4810",
    "sg:province":"QLD",
    "sg:tags":[
        "away",
        "take"
    ],
    "wof:name":"Eagle Boys Pizza North Ward",
    "wof:placetype":"venue"
},
  "geometry": {"coordinates":[146.814774,-19.249828],"type":"Point"}
}