{
  "type": "Feature",
  "properties": {
    "addr:full":"Lot 14 Prospect Rd Bendigo VIC 3550",
    "addr:postcode":"3550",
    "addr:street":"Prospect Rd",
    "iso:country":"AU",
    "sg:address":"Lot 14 Prospect Rd",
    "sg:city":"Bendigo",
    "sg:classifiers":[
        {
            "category":"Manufacturing",
            "subcategory":"Metals",
            "type":"Manufacturing & Wholesale Goods"
        }
    ],
    "sg:phone":"+61 3 5442 1542",
    "sg:postcode":"3550",
    "sg:province":"VIC",
    "sg:tags":[
        "sheet",
        "worker"
    ],
    "wof:name":"Strathfieldsaye Engineering & Sheet Metal",
    "wof:placetype":"venue"
},
  "geometry": {"coordinates":[144.31346130399999,-36.7430686951],"type":"Point"}
}