{
  "type": "Feature",
  "properties": {
    "addr:full":"Shop 38 Bonnyrigg Plaza Bonnyrigg Ave Bonnyrigg NSW 2177",
    "addr:housenumber":"shop 38",
    "addr:postcode":"2177",
    "addr:street":"Bonnyrigg Plaza Bonnyrigg Ave",
    "iso:country":"AU",
    "sg:address":"Shop 38 Bonnyrigg Plaza Bonnyrigg Ave",
    "sg:city":"Bonnyrigg",
    "sg:classifiers":[
        {
            "category":"Real Estate",
            "subcategory":"Real Estate Agent",
            "type":"Services"
        }
    ],
    "sg:phone":"+61 2 9610 5566",
    "sg:postcode":"2177",
    "sg:province":"NSW",
    "wof:name":"L J Hooker",
    "wof:placetype":"venue"
},
  "geometry": {"coordinates":[150.885223389,-33.8903961182],"type":"Point"}
}