{
  "type": "Feature",
  "properties": {
    "addr:full":"45 Buckland St Alexandria NSW 2015",
    "addr:housenumber":"45",
    "addr:postcode":"2015",
    "addr:street":"Buckland St",
    "iso:country":"AU",
    "sg:address":"45 Buckland St",
    "sg:city":"Alexandria",
    "sg:classifiers":[
        {
            "category":"Shopping",
            "subcategory":"Jewelry",
            "type":"Retail Goods"
        }
    ],
    "sg:phone":"+61 408 733 392",
    "sg:postcode":"2015",
    "sg:province":"NSW",
    "sg:tags":[
        "jeweller"
    ],
    "wof:name":"The Origami People",
    "wof:placetype":"venue"
},
  "geometry": {"coordinates":[151.19760131800001,-33.8991317749],"type":"Point"}
}