{
  "type": "Feature",
  "properties": {
    "addr:full":"22 Bannister St Fremantle WA 6160",
    "addr:housenumber":"22",
    "addr:postcode":"6160",
    "addr:street":"Bannister St",
    "iso:country":"AU",
    "sg:address":"22 Bannister St",
    "sg:city":"Fremantle",
    "sg:classifiers":[
        {
            "category":"Retail",
            "subcategory":"Event Space",
            "type":"Services"
        }
    ],
    "sg:phone":"+61 8 9335 7277",
    "sg:postcode":"6160",
    "sg:province":"WA",
    "sg:tags":[
        "venue",
        "reception",
        "wedding"
    ],
    "wof:name":"Paesano's Function Centre",
    "wof:placetype":"venue"
},
  "geometry": {"coordinates":[115.74653600000001,-32.055134],"type":"Point"}
}