{
  "type": "Feature",
  "properties": {
    "iso:country":"AU",
    "sg:address":"22 Bannister St",
    "sg:city":"Fremantle",
    "sg:classifiers":[
        {
            "category":"Retail",
            "subcategory":"Event Space",
            "type":"Services"
        }
    ],
    "sg:phone":"+61 8 9335 7277",
    "sg:postcode":"6160",
    "sg:province":"WA",
    "sg:tags":[
        "venue",
        "reception",
        "wedding"
    ],
    "wof:name":"Paesano's Function Centre",
    "wof:placetype":"venue"
},
  "geometry": {"coordinates":[115.746536,-32.055134],"type":"Point"}
}