{
  "type": "Feature",
  "properties": {
    "addr:full":"Tamarind Pl Wickham WA 6720",
    "addr:postcode":"6720",
    "addr:street":"Pl",
    "iso:country":"AU",
    "sg:address":"Tamarind Pl",
    "sg:city":"Wickham",
    "sg:classifiers":[
        {
            "category":"Education",
            "subcategory":"School",
            "type":"Public Place"
        }
    ],
    "sg:phone":"+61 8 9187 1717",
    "sg:postcode":"6720",
    "sg:province":"WA",
    "sg:tags":[
        "state",
        "except",
        "nsw"
    ],
    "wof:name":"Wickham District High School",
    "wof:placetype":"venue"
},
  "geometry": {"coordinates":[117.142921448,-20.6798400879],"type":"Point"}
}