{
  "type": "Feature",
  "properties": {
    "addr:full":"PO Box 171 Young NSW 2594",
    "addr:postcode":"2594",
    "iso:country":"AU",
    "sg:address":"PO Box 171",
    "sg:city":"Young",
    "sg:classifiers":[
        {
            "category":"Social Services",
            "subcategory":"Adult Care",
            "type":"Services"
        }
    ],
    "sg:phone":"+61 418 160 812",
    "sg:postcode":"2594",
    "sg:province":"NSW",
    "sg:tags":[
        "towing"
    ],
    "wof:name":"Young Towing Service",
    "wof:placetype":"venue"
},
  "geometry": {"coordinates":[148.29434204099999,-34.3139686584],"type":"Point"}
}