{
  "type": "Feature",
  "properties": {
    "iso:country":"AU",
    "sg:address":"9 Euphemia St",
    "sg:city":"Jimboomba",
    "sg:classifiers":[
        {
            "category":"Retail",
            "subcategory":"Storage",
            "type":"Services"
        }
    ],
    "sg:phone":"+61 7 3806 9861",
    "sg:postcode":"4280",
    "sg:province":"QLD",
    "wof:name":"Jimboomba Self Storage",
    "wof:placetype":"venue"
},
  "geometry": {"coordinates":[153.03093000000001,-27.823494],"type":"Point"}
}