{
  "type": "Feature",
  "properties": {
    "iso:country":"AU",
    "sg:address":"264 Rosslyn St",
    "sg:city":"West Melbourne",
    "sg:classifiers":[
        {
            "category":"Shopping",
            "subcategory":"Computers & Home Electronics",
            "type":"Retail Goods"
        }
    ],
    "sg:phone":"+61 3 9249 9249",
    "sg:postcode":"3003",
    "sg:province":"VIC",
    "sg:tags":[
        "equipment",
        "supply"
    ],
    "wof:name":"A.AALC IT Solutions",
    "wof:placetype":"venue"
},
  "geometry": {"coordinates":[144.94648742699999,-37.8105163574],"type":"Point"}
}