{
  "type": "Feature",
  "properties": {
    "addr:full":"Davis Rd Werribee VIC 3030",
    "addr:postcode":"3030",
    "addr:street":"Davis Rd",
    "iso:country":"AU",
    "sg:address":"Davis Rd",
    "sg:city":"Werribee",
    "sg:classifiers":[
        {
            "category":"Farming",
            "subcategory":"Livestock Farm",
            "type":"Manufacturing & Wholesale Goods"
        }
    ],
    "sg:phone":"+61 3 9741 3972",
    "sg:postcode":"3030",
    "sg:province":"VIC",
    "sg:tags":[
        "breeder",
        "horse",
        "stud"
    ],
    "wof:name":"Riversdale Stud",
    "wof:placetype":"venue"
},
  "geometry": {"coordinates":[144.647873,-37.862907],"type":"Point"}
}