{
  "type": "Feature",
  "properties": {
    "addr:full":"94- 96 Pacific Hwy Coffs Harbour NSW 2450",
    "addr:housenumber":"96",
    "addr:postcode":"2450",
    "addr:street":"Pacific Hwy",
    "iso:country":"AU",
    "sg:address":"94- 96 Pacific Hwy",
    "sg:city":"Coffs Harbour",
    "sg:classifiers":[
        {
            "category":"Travel",
            "subcategory":"Hotels & Motels",
            "type":"Entertainment"
        }
    ],
    "sg:phone":"+61 2 6652 2566",
    "sg:postcode":"2450",
    "sg:province":"NSW",
    "wof:name":"Bentleigh Motor Inn",
    "wof:placetype":"venue"
},
  "geometry": {"coordinates":[153.09002699999999,-30.318611],"type":"Point"}
}