{
  "type": "Feature",
  "properties": {
    "addr:full":"PO Box 5464 Maroochydore South QLD 4558",
    "addr:postcode":"4558",
    "iso:country":"AU",
    "sg:address":"PO Box 5464",
    "sg:city":"Maroochydore South",
    "sg:classifiers":[
        {
            "category":"Building & Trades",
            "subcategory":"Cleaning & Sanitation",
            "type":"Services"
        }
    ],
    "sg:phone":"+61 416 390 117",
    "sg:postcode":"4558",
    "sg:province":"QLD",
    "sg:tags":[
        "industrial",
        "commercial",
        "contractor"
    ],
    "wof:name":"Purssell Commercial Cleaners",
    "wof:placetype":"venue"
},
  "geometry": {"coordinates":[153.07473754899999,-26.6551475525],"type":"Point"}
}