{
  "type": "Feature",
  "properties": {
    "addr:full":"11 Iris Pl Acacia Ridge QLD 4110",
    "addr:housenumber":"11",
    "addr:postcode":"4110",
    "addr:street":"Iris Pl",
    "iso:country":"AU",
    "sg:address":"11 Iris Pl",
    "sg:city":"Acacia Ridge",
    "sg:classifiers":[
        {
            "category":"Wholesale",
            "subcategory":"Machinery & Supplies",
            "type":"Manufacturing & Wholesale Goods"
        }
    ],
    "sg:phone":"+61 7 3711 4004",
    "sg:postcode":"4110",
    "sg:province":"QLD",
    "sg:tags":[
        "equipment",
        "hydraulic"
    ],
    "wof:name":"Seal Imports Pty Ltd",
    "wof:placetype":"venue"
},
  "geometry": {"coordinates":[153.028762817,-27.595451355],"type":"Point"}
}