{
  "type": "Feature",
  "properties": {
    "iso:country":"AU",
    "sg:address":"59 Church St",
    "sg:city":"Hawthorn",
    "sg:classifiers":[
        {
            "category":"Shopping",
            "subcategory":"Antiques",
            "type":"Retail Goods"
        }
    ],
    "sg:phone":"+61 3 9818 1474",
    "sg:postcode":"3122",
    "sg:province":"VIC",
    "wof:name":"Architectural Antiques",
    "wof:placetype":"venue"
},
  "geometry": {"coordinates":[145.02195739699999,-37.8148803711],"type":"Point"}
}