{
  "type": "Feature",
  "properties": {
    "iso:country":"AU",
    "sg:address":"99 George St",
    "sg:city":"Launceston",
    "sg:classifiers":[
        {
            "category":"Professional",
            "subcategory":"Computer Services",
            "type":"Services"
        }
    ],
    "sg:phone":"+61 3 6334 6116",
    "sg:postcode":"7250",
    "sg:province":"TAS",
    "sg:tags":[
        "package",
        "software"
    ],
    "wof:name":"Adobe Channel Partner Tasmania TheMac Shop",
    "wof:placetype":"venue"
},
  "geometry": {"coordinates":[147.141113281,-41.4368095398],"type":"Point"}
}