{
  "type": "Feature",
  "properties": {
    "iso:country":"AU",
    "sg:address":"39 Trethowan Ave",
    "sg:city":"Melton West",
    "sg:classifiers":[
        {
            "category":"Retail",
            "subcategory":"Repair Shop",
            "type":"Services"
        }
    ],
    "sg:phone":"+61 408 366 541",
    "sg:postcode":"3337",
    "sg:province":"VIC",
    "sg:tags":[
        "leadlights"
    ],
    "wof:name":"Superb Leadlights And Doors",
    "wof:placetype":"venue"
},
  "geometry": {"coordinates":[144.55050700000001,-37.68364],"type":"Point"}
}