{
  "type": "Feature",
  "properties": {
    "iso:country":"AU",
    "sg:address":"PO Box 699",
    "sg:city":"Katoomba",
    "sg:classifiers":[
        {
            "category":"Arena",
            "subcategory":"Sports Club",
            "type":"Entertainment"
        }
    ],
    "sg:phone":"+61 2 4782 6645",
    "sg:postcode":"2780",
    "sg:province":"NSW",
    "sg:tags":[
        "defence",
        "supply",
        "self",
        "instruction",
        "martial art"
    ],
    "wof:name":"Anthony Hughes Building Maintenance",
    "wof:placetype":"venue"
},
  "geometry": {"coordinates":[150.31053161599999,-33.7118186951],"type":"Point"}
}