{
  "type": "Feature",
  "properties": {
    "addr:full":"178 Old Burrawa Rd Malua Bay NSW 2536",
    "addr:housenumber":"178",
    "addr:postcode":"2536",
    "addr:street":"Old Burrawa Rd",
    "iso:country":"AU",
    "sg:address":"178 Old Burrawa Rd",
    "sg:city":"Malua Bay",
    "sg:classifiers":[
        {
            "category":"Building & Trades",
            "subcategory":"Plumbing",
            "type":"Services"
        }
    ],
    "sg:phone":"+61 2 4471 1210",
    "sg:postcode":"2536",
    "sg:province":"NSW",
    "sg:tags":[
        "plumber",
        "gasfitters"
    ],
    "wof:name":"Bay Plumbers",
    "wof:placetype":"venue"
},
  "geometry": {"coordinates":[150.22846984899999,-35.7909202576],"type":"Point"}
}