{
  "type": "Feature",
  "properties": {
    "iso:country":"AU",
    "sg:address":"1730 Albany Hwy",
    "sg:city":"Kenwick",
    "sg:classifiers":[
        {
            "category":"Professional",
            "type":"Services"
        }
    ],
    "sg:phone":"+61 8 9452 1300",
    "sg:postcode":"6107",
    "sg:province":"WA",
    "sg:tags":[
        "auctioneer"
    ],
    "wof:name":"WWA Australia Pty Ltd",
    "wof:placetype":"venue"
},
  "geometry": {"coordinates":[115.97078704800001,-32.0395317078],"type":"Point"}
}