{
  "type": "Feature",
  "properties": {
    "addr:full":"4 Skoda St Port Willunga SA 5173",
    "addr:housenumber":"4",
    "addr:postcode":"5173",
    "addr:street":"Skoda St",
    "iso:country":"AU",
    "sg:address":"4 Skoda St",
    "sg:city":"Port Willunga",
    "sg:classifiers":[
        {
            "category":"Building & Trades",
            "subcategory":"Construction",
            "type":"Services"
        }
    ],
    "sg:phone":"+61 417 892 119",
    "sg:postcode":"5173",
    "sg:province":"SA",
    "sg:tags":[
        "earth",
        "excavating",
        "moving",
        "contractor"
    ],
    "wof:name":"ADDCAT Earthmoving",
    "wof:placetype":"venue"
},
  "geometry": {"coordinates":[138.463912964,-35.2668991089],"type":"Point"}
}