{
  "type": "Feature",
  "properties": {
    "addr:full":"Unit 2/ 1 Minchin Way Margaret River WA 6285",
    "addr:postcode":"6285",
    "addr:street":"Minchin Way",
    "iso:country":"AU",
    "sg:address":"Unit 2/ 1",
    "sg:city":"Minchin Way Margaret River",
    "sg:classifiers":[
        {
            "category":"Professional",
            "subcategory":"Printing & Photocopies",
            "type":"Services"
        }
    ],
    "sg:phone":"+61 8 9758 8934",
    "sg:postcode":"6285",
    "sg:province":"WA",
    "sg:tags":[
        "embroidery"
    ],
    "wof:name":"Ningaloo Coastal Images",
    "wof:placetype":"venue"
},
  "geometry": {"coordinates":[115.06784057599999,-33.9669418335],"type":"Point"}
}