{
  "type": "Feature",
  "properties": {
    "addr:full":"76 View St Clayton VIC 3168",
    "addr:housenumber":"76",
    "addr:postcode":"3168",
    "addr:street":"View St",
    "iso:country":"AU",
    "sg:address":"76 View St",
    "sg:city":"Clayton",
    "sg:classifiers":[
        {
            "category":"Home & Garden",
            "subcategory":"Building Materials",
            "type":"Retail Goods"
        }
    ],
    "sg:phone":"+61 3 9543 8900",
    "sg:postcode":"3168",
    "sg:province":"VIC",
    "sg:tags":[
        "lawn",
        "cutting",
        "maintenance"
    ],
    "wof:name":"Lawns And All",
    "wof:placetype":"venue"
},
  "geometry": {"coordinates":[145.109741211,-37.925327301],"type":"Point"}
}