{
  "type": "Feature",
  "properties": {
    "addr:full":"26 New St Frankston VIC 3199",
    "addr:housenumber":"26",
    "addr:postcode":"3199",
    "addr:street":"New St",
    "iso:country":"AU",
    "sg:address":"26 New St",
    "sg:city":"Frankston",
    "sg:classifiers":[
        {
            "category":"Building & Trades",
            "subcategory":"Construction",
            "type":"Services"
        }
    ],
    "sg:phone":"+61 3 9783 4818",
    "sg:postcode":"3199",
    "sg:province":"VIC",
    "sg:tags":[
        "window",
        "tinting"
    ],
    "wof:name":"ARMA Protection Systems",
    "wof:placetype":"venue"
},
  "geometry": {"coordinates":[144.99395751899999,-37.9295692444],"type":"Point"}
}