{
  "type": "Feature",
  "properties": {
    "iso:country":"AU",
    "sg:address":"8 Pacific Hwy",
    "sg:city":"Banora Point",
    "sg:classifiers":[
        {
            "category":"Freight",
            "type":"Transportation"
        }
    ],
    "sg:phone":"+61 411 506 462",
    "sg:postcode":"2486",
    "sg:province":"NSW",
    "sg:tags":[
        "transport",
        "refrigerated"
    ],
    "wof:name":"Specific Distribution",
    "wof:placetype":"venue"
},
  "geometry": {"coordinates":[153.54685974099999,-28.2234268188],"type":"Point"}
}