{
  "type": "Feature",
  "properties": {
    "addr:full":"U4/ 18 Thurso Rd Myaree WA 6154",
    "addr:housenumber":"18",
    "addr:postcode":"6154",
    "addr:street":"U4 /;Thurso Rd",
    "iso:country":"AU",
    "sg:address":"U4/ 18 Thurso Rd",
    "sg:city":"Myaree",
    "sg:classifiers":[
        {
            "category":"Autos & Motor Vehicles",
            "subcategory":"Automobile Sales",
            "type":"Retail Goods"
        }
    ],
    "sg:phone":"+61 8 9330 8377",
    "sg:postcode":"6154",
    "sg:province":"WA",
    "sg:tags":[
        "car",
        "used"
    ],
    "wof:name":"Melville Auto Imports",
    "wof:placetype":"venue"
},
  "geometry": {"coordinates":[115.815567,-32.041382],"type":"Point"}
}