{
  "type": "Feature",
  "properties": {
    "addr:full":"Level 8 139 Macquarie St Sydney NSW 2000",
    "addr:housenumber":"139",
    "addr:postcode":"2000",
    "addr:street":"Macquarie St",
    "iso:country":"AU",
    "sg:address":"Level 8 139 Macquarie St",
    "sg:city":"Sydney",
    "sg:classifiers":[
        {
            "category":"Banks & Credit Unions",
            "subcategory":"Investment Brokerage",
            "type":"Services"
        }
    ],
    "sg:phone":"+61 2 9251 6400",
    "sg:postcode":"2000",
    "sg:province":"NSW",
    "wof:name":"Rhetford Group",
    "wof:placetype":"venue"
},
  "geometry": {"coordinates":[151.212600708,-33.8644866943],"type":"Point"}
}