{
  "type": "Feature",
  "properties": {
    "iso:country":"AU",
    "sg:address":"5 Robwald Ave",
    "sg:city":"Coniston",
    "sg:classifiers":[
        {
            "category":"Government",
            "subcategory":"Court House",
            "type":"Public Place"
        }
    ],
    "sg:phone":"+61 2 4227 1208",
    "sg:postcode":"2500",
    "sg:province":"NSW",
    "sg:tags":[
        "personal",
        "marriage",
        "family",
        "counselling"
    ],
    "wof:name":"Julie Gorrell",
    "wof:placetype":"venue"
},
  "geometry": {"coordinates":[150.87837200000001,-34.434925],"type":"Point"}
}