{
  "type": "Feature",
  "properties": {
    "iso:country":"AU",
    "sg:address":"62 Lyndale Ave",
    "sg:city":"Parkwood",
    "sg:classifiers":[
        {
            "category":"Building & Trades",
            "subcategory":"Construction",
            "type":"Services"
        }
    ],
    "sg:phone":"+61 412 998 831",
    "sg:postcode":"6147",
    "sg:province":"WA",
    "sg:tags":[
        "roof"
    ],
    "wof:name":"C & K Roof Plumbing",
    "wof:placetype":"venue"
},
  "geometry": {"coordinates":[115.911102,-32.050156],"type":"Point"}
}