{
  "type": "Feature",
  "properties": {
    "iso:country":"AU",
    "sg:address":"258 Great Western Hwy",
    "sg:city":"Wentworthville",
    "sg:classifiers":[
        {
            "category":"Farming",
            "subcategory":"Poultry Farm",
            "type":"Manufacturing & Wholesale Goods"
        }
    ],
    "sg:phone":"+61 2 9635 0598",
    "sg:postcode":"2145",
    "sg:province":"NSW",
    "sg:tags":[
        "breeder",
        "bird"
    ],
    "wof:name":"Ace Colony Aviaries",
    "wof:placetype":"venue"
},
  "geometry": {"coordinates":[150.974411011,-33.8163871765],"type":"Point"}
}