{
  "type": "Feature",
  "properties": {
    "addr:full":"PO Box 113 Berridale NSW 2628",
    "addr:postcode":"2628",
    "iso:country":"AU",
    "sg:address":"PO Box 113",
    "sg:city":"Berridale",
    "sg:classifiers":[
        {
            "category":"Autos & Motor Vehicles",
            "subcategory":"Auto Supplies",
            "type":"Retail Goods"
        }
    ],
    "sg:phone":"+61 2 6456 4100",
    "sg:postcode":"2628",
    "sg:province":"NSW",
    "sg:tags":[
        "wheel",
        "four",
        "equipment",
        "drive",
        "accessory"
    ],
    "wof:name":"Skyjacker",
    "wof:placetype":"venue"
},
  "geometry": {"coordinates":[148.82591247600001,-36.3664512634],"type":"Point"}
}