{
  "type": "Feature",
  "properties": {
    "addr:full":"PO Box 394 Abbotsford VIC 3067",
    "addr:postcode":"3067",
    "iso:country":"AU",
    "sg:address":"PO Box 394",
    "sg:city":"Abbotsford",
    "sg:classifiers":[
        {
            "category":"Shopping",
            "subcategory":"Stationery & Office Supplies",
            "type":"Retail Goods"
        }
    ],
    "sg:phone":"+61 3 9417 1220",
    "sg:postcode":"3067",
    "sg:province":"VIC",
    "sg:tags":[
        "equipment",
        "badge",
        "making"
    ],
    "wof:name":"Custom Merchandise",
    "wof:placetype":"venue"
},
  "geometry": {"coordinates":[145.00360107399999,-37.8037185669],"type":"Point"}
}