{
  "type": "Feature",
  "properties": {
    "addr:full":"3/ 182 Hartley Rd Smeaton Grange NSW 2567",
    "addr:housenumber":"/ 182",
    "addr:postcode":"2567",
    "addr:street":"Hartley Rd",
    "iso:country":"AU",
    "sg:address":"3/ 182 Hartley Rd",
    "sg:city":"Smeaton Grange",
    "sg:classifiers":[
        {
            "category":"Building & Trades",
            "subcategory":"Construction",
            "type":"Services"
        }
    ],
    "sg:phone":"+61 2 4648 1320",
    "sg:postcode":"2567",
    "sg:province":"NSW",
    "sg:tags":[
        "window",
        "aluminium"
    ],
    "wof:name":"Camden Windows & Doors",
    "wof:placetype":"venue"
},
  "geometry": {"coordinates":[150.75331115700001,-34.0366172791],"type":"Point"}
}