{
  "type": "Feature",
  "properties": {
    "addr:full":"Bridge St Tamworth NSW 2340",
    "addr:postcode":"2340",
    "addr:street":"Bridge St",
    "iso:country":"AU",
    "sg:address":"Bridge St",
    "sg:city":"Tamworth",
    "sg:classifiers":[
        {
            "category":"Professional",
            "subcategory":"Art Services",
            "type":"Services"
        }
    ],
    "sg:phone":"+61 2 6762 1311",
    "sg:postcode":"2340",
    "sg:province":"NSW",
    "sg:tags":[
        "interior",
        "decorator"
    ],
    "wof:name":"Gemini Furnishings",
    "wof:placetype":"venue"
},
  "geometry": {"coordinates":[150.92652893100001,-31.091293335],"type":"Point"}
}