{
  "type": "Feature",
  "properties": {
    "addr:full":"7 Blairgowie St North Parramatta NSW 2151",
    "addr:housenumber":"7",
    "addr:postcode":"2151",
    "addr:street":"Blairgowie St",
    "iso:country":"AU",
    "sg:address":"7 Blairgowie St",
    "sg:city":"North Parramatta",
    "sg:classifiers":[
        {
            "category":"Building & Trades",
            "subcategory":"Construction",
            "type":"Services"
        }
    ],
    "sg:phone":"+61 2 9630 1976",
    "sg:postcode":"2151",
    "sg:province":"NSW",
    "sg:tags":[
        "contractor"
    ],
    "wof:name":"Stanton G & P Pty Ltd",
    "wof:placetype":"venue"
},
  "geometry": {"coordinates":[151.02005004899999,-33.7965126038],"type":"Point"}
}