{
  "type": "Feature",
  "properties": {
    "iso:country":"AU",
    "sg:address":"115 Silverwater Rd",
    "sg:city":"Silverwater",
    "sg:classifiers":[
        {
            "category":"Professional",
            "subcategory":"Art Services",
            "type":"Services"
        }
    ],
    "sg:phone":"+61 2 9648 1118",
    "sg:postcode":"2128",
    "sg:province":"NSW",
    "sg:tags":[
        "picture",
        "frame",
        "framing"
    ],
    "wof:name":"Champas Picart",
    "wof:placetype":"venue"
},
  "geometry": {"coordinates":[151.04835510300001,-33.8333625793],"type":"Point"}
}