{
  "type": "Feature",
  "properties": {
    "addr:full":"40 Bell St Heidelberg Heights VIC 3081",
    "addr:housenumber":"40",
    "addr:postcode":"3081",
    "addr:street":"Bell St",
    "iso:country":"AU",
    "sg:address":"40 Bell St",
    "sg:city":"Heidelberg Heights",
    "sg:classifiers":[
        {
            "category":"Health Services",
            "subcategory":"Dentist",
            "type":"Services"
        }
    ],
    "sg:phone":"+61 3 9457 3770",
    "sg:postcode":"3081",
    "sg:province":"VIC",
    "wof:name":"Ang W S & K M",
    "wof:placetype":"venue"
},
  "geometry": {"coordinates":[145.05523681599999,-37.7544364929],"type":"Point"}
}