{
  "type": "Feature",
  "properties": {
    "iso:country":"AU",
    "sg:address":"3 Gordon St",
    "sg:city":"Brighton",
    "sg:classifiers":[
        {
            "category":"Building & Trades",
            "subcategory":"Construction",
            "type":"Services"
        }
    ],
    "sg:phone":"+61 7 3269 6317",
    "sg:postcode":"4017",
    "sg:province":"QLD",
    "sg:tags":[
        "concrete",
        "contractor"
    ],
    "wof:name":"Nete-Crete Concreting",
    "wof:placetype":"venue"
},
  "geometry": {"coordinates":[153.046783447,-27.306930542],"type":"Point"}
}