{
  "type": "Feature",
  "properties": {
    "addr:full":"161 Turf St Grafton NSW 2460",
    "addr:housenumber":"161",
    "addr:postcode":"2460",
    "addr:street":"Turf St",
    "iso:country":"AU",
    "sg:address":"161 Turf St",
    "sg:city":"Grafton",
    "sg:classifiers":[
        {
            "category":"Food & Beverages",
            "subcategory":"Groceries & Convenience Stores",
            "type":"Retail Goods"
        }
    ],
    "sg:phone":"+61 2 6642 6434",
    "sg:postcode":"2460",
    "sg:province":"NSW",
    "wof:name":"Turf Street Shop",
    "wof:placetype":"venue"
},
  "geometry": {"coordinates":[152.93389892600001,-29.674200058],"type":"Point"}
}