{
  "type": "Feature",
  "properties": {
    "iso:country":"AU",
    "sg:address":"247 Oxford St",
    "sg:city":"Leederville",
    "sg:classifiers":[
        {
            "category":"Real Estate",
            "subcategory":"Real Estate Agent",
            "type":"Services"
        }
    ],
    "sg:phone":"+61 8 9208 1999",
    "sg:postcode":"6007",
    "sg:province":"WA",
    "wof:name":"Property People",
    "wof:placetype":"venue"
},
  "geometry": {"coordinates":[115.841072083,-31.9323272705],"type":"Point"}
}