{
  "type": "Feature",
  "properties": {
    "iso:country":"AU",
    "sg:address":"Unit 4, 660 Lorimer St",
    "sg:city":"Port Melbourne",
    "sg:classifiers":[
        {
            "category":"Banks & Credit Unions",
            "subcategory":"Investment Brokerage",
            "type":"Services"
        }
    ],
    "sg:phone":"+61 13 26 79",
    "sg:postcode":"3207",
    "sg:province":"VIC",
    "sg:tags":[
        "machine",
        "duplicating",
        "supply"
    ],
    "wof:name":"Riso",
    "wof:placetype":"venue"
},
  "geometry": {"coordinates":[144.922333,-37.820946],"type":"Point"}
}