{
  "type": "Feature",
  "properties": {
    "addr:full":"122- 134 Dougharty Rd Heidelberg West VIC 3081",
    "addr:housenumber":"134",
    "addr:postcode":"3081",
    "addr:street":"Dougharty Rd",
    "iso:country":"AU",
    "sg:address":"122- 134 Dougharty Rd",
    "sg:city":"Heidelberg West",
    "sg:classifiers":[
        {
            "category":"Manufacturing",
            "subcategory":"Tools & Machinery",
            "type":"Manufacturing & Wholesale Goods"
        }
    ],
    "sg:phone":"+61 3 9459 8911",
    "sg:postcode":"3081",
    "sg:province":"VIC",
    "sg:tags":[
        "wholesaler",
        "mfrs",
        "hosiery"
    ],
    "wof:name":"Scallywags",
    "wof:placetype":"venue"
},
  "geometry": {"coordinates":[145.04719543499999,-37.7341003418],"type":"Point"}
}