{
  "type": "Feature",
  "properties": {
    "addr:full":"Unit 3, 3 Vuko Pl Warriewood NSW 2102",
    "addr:housenumber":"3",
    "addr:postcode":"2102",
    "addr:street":"Vuko Pl",
    "iso:country":"AU",
    "sg:address":"Unit 3, 3 Vuko Pl",
    "sg:city":"Warriewood",
    "sg:classifiers":[
        {
            "category":"Communications",
            "subcategory":"Film & Video Production",
            "type":"Services"
        }
    ],
    "sg:phone":"+61 2 9913 8800",
    "sg:postcode":"2102",
    "sg:province":"NSW",
    "sg:tags":[
        "fan",
        "blower"
    ],
    "wof:name":"Odour Vac",
    "wof:placetype":"venue"
},
  "geometry": {"coordinates":[151.30169699999999,-33.693005],"type":"Point"}
}