{
  "type": "Feature",
  "properties": {
    "iso:country":"AU",
    "sg:address":"16 Bayley St",
    "sg:city":"Geelong",
    "sg:classifiers":[
        {
            "category":"Retail",
            "subcategory":"Laundry & Dry Cleaning",
            "type":"Services"
        }
    ],
    "sg:phone":"+61 3 5223 1122",
    "sg:postcode":"3220",
    "sg:province":"VIC",
    "wof:name":"Bay City Laundry",
    "wof:placetype":"venue"
},
  "geometry": {"coordinates":[144.358505,-38.144932],"type":"Point"}
}