{
  "type": "Feature",
  "properties": {
    "addr:full":"280 Stafford Rd Stafford QLD 4053",
    "addr:housenumber":"280",
    "addr:postcode":"4053",
    "addr:street":"Stafford Rd",
    "iso:country":"AU",
    "sg:address":"280 Stafford Rd",
    "sg:city":"Stafford",
    "sg:classifiers":[
        {
            "category":"Sports & Exercise",
            "subcategory":"Sports Center",
            "type":"Entertainment"
        }
    ],
    "sg:phone":"+61 7 3357 4444",
    "sg:postcode":"4053",
    "sg:province":"QLD",
    "sg:tags":[
        "ground"
    ],
    "wof:name":"Stafford Skate Centre",
    "wof:placetype":"venue"
},
  "geometry": {"coordinates":[153.01881408700001,-27.4108352661],"type":"Point"}
}