{
  "type": "Feature",
  "properties": {
    "iso:country":"AU",
    "sg:address":"32 Fitzroy St",
    "sg:city":"Walcha",
    "sg:classifiers":[
        {
            "category":"Professional",
            "subcategory":"Secretarial Services",
            "type":"Services"
        }
    ],
    "sg:phone":"+61 2 6777 1111",
    "sg:postcode":"2354",
    "sg:province":"NSW",
    "sg:tags":[
        "typing"
    ],
    "wof:name":"Walcha Telecottage The",
    "wof:placetype":"venue"
},
  "geometry": {"coordinates":[151.5859375,-30.9838886261],"type":"Point"}
}