{
  "type": "Feature",
  "properties": {
    "iso:country":"AU",
    "sg:address":"PO Box 103",
    "sg:city":"Athelstone",
    "sg:classifiers":[
        {
            "category":"Building & Trades",
            "subcategory":"Pest Control",
            "type":"Services"
        }
    ],
    "sg:phone":"+61 8 8336 1033",
    "sg:postcode":"5076",
    "sg:province":"SA",
    "wof:name":"Ashendens Pest Control Pty Ltd",
    "wof:placetype":"venue"
},
  "geometry": {"coordinates":[138.70384216299999,-34.869468689],"type":"Point"}
}