{
  "type": "Feature",
  "properties": {
    "addr:full":"64 Sydney Pde Geelong VIC 3220",
    "addr:housenumber":"64",
    "addr:postcode":"3220",
    "addr:street":"Sydney Pde",
    "iso:country":"AU",
    "sg:address":"64 Sydney Pde",
    "sg:city":"Geelong",
    "sg:classifiers":[
        {
            "category":"Health Services",
            "subcategory":"Doctor",
            "type":"Services"
        }
    ],
    "sg:phone":"+61 3 5222 4445",
    "sg:postcode":"3220",
    "sg:province":"VIC",
    "sg:tags":[
        "medical",
        "practitioner"
    ],
    "wof:name":"Huffam W H",
    "wof:placetype":"venue"
},
  "geometry": {"coordinates":[144.36859100000001,-38.152813],"type":"Point"}
}