{
  "type": "Feature",
  "properties": {
    "addr:full":"59 Kelly St Wodonga VIC 3689",
    "addr:housenumber":"59",
    "addr:postcode":"3689",
    "addr:street":"Kelly St",
    "iso:country":"AU",
    "sg:address":"59 Kelly St",
    "sg:city":"Wodonga",
    "sg:classifiers":[
        {
            "category":"Shopping",
            "subcategory":"Pets & Pet Supplies",
            "type":"Retail Goods"
        }
    ],
    "sg:phone":"+61 2 6055 5200",
    "sg:postcode":"3689",
    "sg:province":"VIC",
    "sg:tags":[
        "food"
    ],
    "wof:name":"Uncle Bens",
    "wof:placetype":"venue"
},
  "geometry": {"coordinates":[146.875381,-36.114273],"type":"Point"}
}