{
  "type": "Feature",
  "properties": {
    "addr:full":"Lot 1 Urana St Boree Creek NSW 2652",
    "addr:postcode":"2652",
    "addr:street":"Urana St",
    "iso:country":"AU",
    "sg:address":"Lot 1 Urana St",
    "sg:city":"Boree Creek",
    "sg:classifiers":[
        {
            "category":"Travel",
            "subcategory":"Hotels & Motels",
            "type":"Entertainment"
        }
    ],
    "sg:phone":"+61 2 6927 1407",
    "sg:postcode":"2652",
    "sg:province":"NSW",
    "sg:tags":[
        "accommodation"
    ],
    "wof:name":"Boree Creek Hotel/Motel",
    "wof:placetype":"venue"
},
  "geometry": {"coordinates":[146.71693420400001,-35.2187347412],"type":"Point"}
}