{
  "type": "Feature",
  "properties": {
    "iso:country":"AU",
    "sg:address":"928 Anzac Pde",
    "sg:city":"Maroubra",
    "sg:classifiers":[
        {
            "category":"Shopping",
            "subcategory":"Pawn Shop",
            "type":"Retail Goods"
        }
    ],
    "sg:phone":"+61 2 9314 3355",
    "sg:postcode":"2035",
    "sg:province":"NSW",
    "sg:tags":[
        "pawnbroker"
    ],
    "wof:name":"Cash Converters",
    "wof:placetype":"venue"
},
  "geometry": {"coordinates":[151.24012756400001,-33.9430274963],"type":"Point"}
}