{
  "type": "Feature",
  "properties": {
    "addr:full":"2 Fleet St St Somerton VIC 3062",
    "addr:housenumber":"2",
    "addr:postcode":"3062",
    "addr:street":"Fleet St St",
    "iso:country":"AU",
    "sg:address":"2 Fleet St St",
    "sg:city":"Somerton",
    "sg:classifiers":[
        {
            "category":"Autos & Motor Vehicles",
            "subcategory":"Auto Supplies",
            "type":"Retail Goods"
        }
    ],
    "sg:phone":"+61 3 9308 7000",
    "sg:postcode":"3062",
    "sg:province":"VIC",
    "sg:tags":[
        "transmission",
        "equipment",
        "power"
    ],
    "wof:name":"BSC Motion Technology",
    "wof:placetype":"venue"
},
  "geometry": {"coordinates":[144.963546753,-37.6431427002],"type":"Point"}
}