{
  "type": "Feature",
  "properties": {
    "addr:full":"1 Mabel St North Perth WA 6006",
    "addr:housenumber":"1",
    "addr:postcode":"6006",
    "addr:street":"Mabel St",
    "iso:country":"AU",
    "sg:address":"1 Mabel St",
    "sg:city":"North Perth",
    "sg:classifiers":[
        {
            "category":"Arts & Performance",
            "subcategory":"Dance",
            "type":"Entertainment"
        }
    ],
    "sg:phone":"+61 8 9444 6457",
    "sg:postcode":"6006",
    "sg:province":"WA",
    "sg:tags":[
        "theatrical",
        "ballet",
        "tuition"
    ],
    "sg:website":"http://www.tcbc.com.au",
    "wof:name":"Terri Charlesworth Ballet Centre",
    "wof:placetype":"venue"
},
  "geometry": {"coordinates":[115.859039307,-31.9241027832],"type":"Point"}
}