{
  "type": "Feature",
  "properties": {
    "addr:full":"377 Sussex St Sydney NSW 2000",
    "addr:housenumber":"377",
    "addr:postcode":"2000",
    "addr:street":"Sussex St",
    "iso:country":"AU",
    "sg:address":"377 Sussex St",
    "sg:city":"Sydney",
    "sg:classifiers":[
        {
            "category":"Health Services",
            "subcategory":"Dentist",
            "type":"Services"
        }
    ],
    "sg:phone":"+61 2 9267 7174",
    "sg:postcode":"2000",
    "sg:province":"NSW",
    "wof:name":"Tsang Victor",
    "wof:placetype":"venue"
},
  "geometry": {"coordinates":[151.20443725600001,-33.8766212463],"type":"Point"}
}