{
  "type": "Feature",
  "properties": {
    "addr:full":"626 Bruce Hwy Woree QLD 4868",
    "addr:housenumber":"626",
    "addr:postcode":"4868",
    "addr:street":"Bruce Hwy",
    "iso:country":"AU",
    "sg:address":"626 Bruce Hwy",
    "sg:city":"Woree",
    "sg:classifiers":[
        {
            "category":"Real Estate",
            "subcategory":"Real Estate Agent",
            "type":"Services"
        }
    ],
    "sg:phone":"+61 7 4045 4455",
    "sg:postcode":"4868",
    "sg:province":"QLD",
    "wof:name":"Croft Realty Sales & Rentals",
    "wof:placetype":"venue"
},
  "geometry": {"coordinates":[145.74661254899999,-16.9546108246],"type":"Point"}
}