{
  "type": "Feature",
  "properties": {
    "addr:full":"231 Osborne St Clayton South VIC 3169",
    "addr:housenumber":"231",
    "addr:postcode":"3169",
    "addr:street":"Osborne St",
    "iso:country":"AU",
    "sg:address":"231 Osborne St",
    "sg:city":"Clayton South",
    "sg:classifiers":[
        {
            "category":"Autos & Motor Vehicles",
            "subcategory":"Auto Supplies",
            "type":"Retail Goods"
        }
    ],
    "sg:phone":"+61 3 9360 0799",
    "sg:postcode":"3169",
    "sg:province":"VIC",
    "sg:tags":[
        "tyre"
    ],
    "wof:name":"Western Bandag",
    "wof:placetype":"venue"
},
  "geometry": {"coordinates":[145.11686706500001,-37.942855835],"type":"Point"}
}