{
  "type": "Feature",
  "properties": {
    "addr:full":"PO Box 599 Scarborough PLB WA 6922",
    "addr:postcode":"6922",
    "iso:country":"AU",
    "sg:address":"PO Box 599",
    "sg:city":"Scarborough PLB",
    "sg:classifiers":[
        {
            "category":"Building & Trades",
            "subcategory":"Construction",
            "type":"Services"
        }
    ],
    "sg:phone":"+61 410 507 813",
    "sg:postcode":"6922",
    "sg:province":"WA",
    "sg:tags":[
        "fencing",
        "contractor"
    ],
    "wof:name":"Fensitup Pty Ltd",
    "wof:placetype":"venue"
},
  "geometry": {"coordinates":[115.760162353,-31.8943595886],"type":"Point"}
}