{
  "type": "Feature",
  "properties": {
    "iso:country":"AU",
    "sg:address":"Wisemans Ferry Rd",
    "sg:city":"Spencer",
    "sg:classifiers":[
        {
            "category":"Home & Garden",
            "subcategory":"Building Materials",
            "type":"Retail Goods"
        }
    ],
    "sg:phone":"+61 2 4377 1246",
    "sg:postcode":"2775",
    "sg:province":"NSW",
    "sg:tags":[
        "lawn",
        "cutting",
        "maintenance"
    ],
    "wof:name":"Wood Rob Garden Service",
    "wof:placetype":"venue"
},
  "geometry": {"coordinates":[151.14730835,-33.4582519531],"type":"Point"}
}