{
  "type": "Feature",
  "properties": {
    "addr:full":"2- 10 Decor Drv Hallam VIC 3803",
    "addr:housenumber":"10",
    "addr:postcode":"3803",
    "addr:street":"2;Decor Drv",
    "iso:country":"AU",
    "sg:address":"2- 10 Decor Drv",
    "sg:city":"Hallam",
    "sg:classifiers":[
        {
            "category":"Building & Trades",
            "subcategory":"Construction",
            "type":"Services"
        }
    ],
    "sg:phone":"+61 3 9702 3344",
    "sg:postcode":"3803",
    "sg:province":"VIC",
    "sg:tags":[
        "equipment",
        "balancing"
    ],
    "wof:name":"Truckline Truck & Trailer Parts",
    "wof:placetype":"venue"
},
  "geometry": {"coordinates":[145.26263427699999,-38.0067558289],"type":"Point"}
}