{
  "type": "Feature",
  "properties": {
    "addr:full":"56 Kanangra St Stafford QLD 4053",
    "addr:housenumber":"56",
    "addr:postcode":"4053",
    "addr:street":"Kanangra St",
    "iso:country":"AU",
    "sg:address":"56 Kanangra St",
    "sg:city":"Stafford",
    "sg:classifiers":[
        {
            "category":"Building & Trades",
            "subcategory":"Cleaning & Sanitation",
            "type":"Services"
        }
    ],
    "sg:phone":"+61 417 776 350",
    "sg:postcode":"4053",
    "sg:province":"QLD",
    "sg:tags":[
        "cleaner",
        "repairer",
        "roof"
    ],
    "wof:name":"Robert Jones Roof Maintenance",
    "wof:placetype":"venue"
},
  "geometry": {"coordinates":[153.00517273,-27.4043331146],"type":"Point"}
}