{
  "type": "Feature",
  "properties": {
    "iso:country":"AU",
    "sg:address":"24 Broadfoot St",
    "sg:city":"Toowoomba",
    "sg:classifiers":[
        {
            "category":"Professional",
            "type":"Services"
        }
    ],
    "sg:phone":"+61 7 4635 8477",
    "sg:postcode":"4350",
    "sg:province":"QLD",
    "sg:tags":[
        "transport"
    ],
    "wof:name":"Schaumburg L R & H J",
    "wof:placetype":"venue"
},
  "geometry": {"coordinates":[151.938126,-27.59524],"type":"Point"}
}