{
  "type": "Feature",
  "properties": {
    "iso:country":"AU",
    "sg:address":"Cnr Monterey & Kitchen Rds",
    "sg:city":"Dandenong",
    "sg:classifiers":[
        {
            "category":"Professional",
            "type":"Services"
        }
    ],
    "sg:phone":"+61 3 9706 4600",
    "sg:postcode":"3175",
    "sg:province":"VIC",
    "sg:tags":[
        "coating",
        "powder"
    ],
    "wof:name":"Coating Services Australia Pty Ltd",
    "wof:placetype":"venue"
},
  "geometry": {"coordinates":[145.21351623499999,-38.0237808228],"type":"Point"}
}