{
  "type": "Feature",
  "properties": {
    "addr:full":"32 Angus St Hadfield VIC 3046",
    "addr:housenumber":"32",
    "addr:postcode":"3046",
    "addr:street":"Angus St",
    "iso:country":"AU",
    "sg:address":"32 Angus St",
    "sg:city":"Hadfield",
    "sg:classifiers":[
        {
            "category":"Education",
            "subcategory":"School",
            "type":"Public Place"
        }
    ],
    "sg:phone":"+61 3 9304 1606",
    "sg:postcode":"3046",
    "sg:province":"VIC",
    "wof:name":"St Thomas Mores Hadfield Before & After School Care Program",
    "wof:placetype":"venue"
},
  "geometry": {"coordinates":[144.94464111299999,-37.7077598572],"type":"Point"}
}