{
  "type": "Feature",
  "properties": {
    "iso:country":"AU",
    "sg:address":"69 Baylis St",
    "sg:city":"Wagga Wagga",
    "sg:classifiers":[
        {
            "category":"Fast Food",
            "type":"Food & Drink"
        }
    ],
    "sg:phone":"+61 2 6921 7714",
    "sg:postcode":"2650",
    "sg:province":"NSW",
    "sg:tags":[
        "away",
        "take"
    ],
    "wof:name":"Flame Grill Chicken Original",
    "wof:placetype":"venue"
},
  "geometry": {"coordinates":[147.36944580100001,-35.1163139343],"type":"Point"}
}