{
  "type": "Feature",
  "properties": {
    "iso:country":"AU",
    "sg:address":"75 Magil Rd",
    "sg:city":"Stepney",
    "sg:classifiers":[
        {
            "category":"Utilities",
            "subcategory":"Telephone",
            "type":"Services"
        }
    ],
    "sg:phone":"+61 8 8362 1833",
    "sg:postcode":"5069",
    "sg:province":"SA",
    "sg:tags":[
        "accessory"
    ],
    "wof:name":"Alcatel",
    "wof:placetype":"venue"
},
  "geometry": {"coordinates":[138.62904357900001,-34.9152488708],"type":"Point"}
}