{
  "type": "Feature",
  "properties": {
    "addr:full":"Campbell St Delegate NSW 2633",
    "addr:postcode":"2633",
    "addr:street":"St",
    "iso:country":"AU",
    "sg:address":"Campbell St",
    "sg:city":"Delegate",
    "sg:classifiers":[
        {
            "category":"Education",
            "subcategory":"School",
            "type":"Public Place"
        }
    ],
    "sg:phone":"+61 2 6458 8183",
    "sg:postcode":"2633",
    "sg:province":"NSW",
    "sg:tags":[
        "state",
        "-",
        "nsw"
    ],
    "wof:name":"Delegate Public School",
    "wof:placetype":"venue"
},
  "geometry": {"coordinates":[148.93861389200001,-37.0436592102],"type":"Point"}
}