{
  "type": "Feature",
  "properties": {
    "addr:full":"Lot2/ 1 Aspley Crt Blue Haven NSW 2262",
    "addr:housenumber":"/ 1",
    "addr:postcode":"2262",
    "addr:street":"Aspley Crt",
    "iso:country":"AU",
    "sg:address":"Lot2/ 1 Aspley Crt",
    "sg:city":"Blue Haven",
    "sg:classifiers":[
        {
            "category":"Social Services",
            "subcategory":"Child Care",
            "type":"Services"
        }
    ],
    "sg:phone":"+61 2 4399 2242",
    "sg:postcode":"2262",
    "sg:province":"NSW",
    "wof:name":"San Remo After School Care Centre",
    "wof:placetype":"venue"
},
  "geometry": {"coordinates":[151.50495900000001,-33.212559],"type":"Point"}
}