{
  "type": "Feature",
  "properties": {
    "addr:full":"Terraces Professional Centre, 2 Kable St Windsor NSW 2756",
    "addr:housenumber":"2",
    "addr:postcode":"2756",
    "addr:street":"Kable St",
    "iso:country":"AU",
    "sg:address":"Terraces Professional Centre, 2 Kable St",
    "sg:city":"Windsor",
    "sg:classifiers":[
        {
            "category":"Health Services",
            "subcategory":"Optometrist",
            "type":"Services"
        }
    ],
    "sg:phone":"+61 2 4577 5638",
    "sg:postcode":"2756",
    "sg:province":"NSW",
    "wof:name":"N & S Hall Optometrists",
    "wof:placetype":"venue"
},
  "geometry": {"coordinates":[150.820602417,-33.6047210693],"type":"Point"}
}