{
  "type": "Feature",
  "properties": {
    "addr:full":"Shop 12 City Arcade 120 Hunter St Newcastle NSW 2300",
    "addr:housenumber":"shop 12;120",
    "addr:postcode":"2300",
    "addr:street":"City Arcade;Hunter St",
    "iso:country":"AU",
    "sg:address":"Shop 12 City Arcade 120 Hunter St",
    "sg:city":"Newcastle",
    "sg:classifiers":[
        {
            "category":"Social Services",
            "subcategory":"Adult Care",
            "type":"Services"
        }
    ],
    "sg:phone":"+61 2 4929 4878",
    "sg:postcode":"2300",
    "sg:province":"NSW",
    "sg:tags":[
        "aged"
    ],
    "wof:name":"Pat's Stitchery",
    "wof:placetype":"venue"
},
  "geometry": {"coordinates":[151.78230300000001,-32.927193],"type":"Point"}
}