{
  "type": "Feature",
  "properties": {
    "addr:full":"406 South Rd Richmond SA 5033",
    "addr:housenumber":"406",
    "addr:postcode":"5033",
    "addr:street":"South Rd",
    "iso:country":"AU",
    "sg:address":"406 South Rd",
    "sg:city":"Richmond",
    "sg:classifiers":[
        {
            "category":"Building & Trades",
            "subcategory":"Equipment Rental",
            "type":"Services"
        }
    ],
    "sg:phone":"+61 1300 368 170",
    "sg:postcode":"5033",
    "sg:province":"SA",
    "sg:tags":[
        "saw"
    ],
    "wof:name":"Silky Saws",
    "wof:placetype":"venue"
},
  "geometry": {"coordinates":[138.57081604000001,-34.9416389465],"type":"Point"}
}