{
  "type": "Feature",
  "properties": {
    "addr:full":"10 Scarborough Pl Beacon Hill NSW 2100",
    "addr:housenumber":"10",
    "addr:postcode":"2100",
    "addr:street":"Pl",
    "iso:country":"AU",
    "sg:address":"10 Scarborough Pl",
    "sg:city":"Beacon Hill",
    "sg:classifiers":[
        {
            "category":"Utilities",
            "subcategory":"Electric",
            "type":"Services"
        }
    ],
    "sg:phone":"+61 2 9452 2070",
    "sg:postcode":"2100",
    "sg:province":"NSW",
    "sg:tags":[
        "electrical",
        "contractor"
    ],
    "wof:name":"Spark Doctor Pty Ltd The",
    "wof:placetype":"venue"
},
  "geometry": {"coordinates":[151.2578125,-33.7450218201],"type":"Point"}
}