{
  "type": "Feature",
  "properties": {
    "iso:country":"AU",
    "sg:address":"294 Torrens Rd",
    "sg:city":"Croydon Park",
    "sg:classifiers":[
        {
            "category":"Shopping",
            "subcategory":"Computers & Home Electronics",
            "type":"Retail Goods"
        }
    ],
    "sg:phone":"+61 8 8346 2822",
    "sg:postcode":"5008",
    "sg:province":"SA",
    "sg:tags":[
        "hardware",
        "equipment"
    ],
    "wof:name":"Latestcom Computer Shop",
    "wof:placetype":"venue"
},
  "geometry": {"coordinates":[138.562332,-34.883434],"type":"Point"}
}