{
  "type": "Feature",
  "properties": {
    "addr:full":"58 Boulder Rd Kalgoorlie WA 6430",
    "addr:housenumber":"58",
    "addr:postcode":"6430",
    "addr:street":"Boulder Rd",
    "iso:country":"AU",
    "sg:address":"58 Boulder Rd",
    "sg:city":"Kalgoorlie",
    "sg:classifiers":[
        {
            "category":"Retail",
            "subcategory":"Auto Repair",
            "type":"Services"
        }
    ],
    "sg:phone":"+61 8 9021 4711",
    "sg:postcode":"6430",
    "sg:province":"WA",
    "sg:tags":[
        "repairer",
        "motor",
        "engineer"
    ],
    "wof:name":"Goldfields Toyota",
    "wof:placetype":"venue"
},
  "geometry": {"coordinates":[121.47618866000001,-30.7479743958],"type":"Point"}
}