{
  "type": "Feature",
  "properties": {
    "addr:full":"1 Sulphur St Narangba QLD 4504",
    "addr:housenumber":"1",
    "addr:postcode":"4504",
    "addr:street":"Sulphur St",
    "iso:country":"AU",
    "sg:address":"1 Sulphur St",
    "sg:city":"Narangba",
    "sg:classifiers":[
        {
            "category":"Manufacturing",
            "subcategory":"Tools & Machinery",
            "type":"Manufacturing & Wholesale Goods"
        }
    ],
    "sg:phone":"+61 7 3888 1555",
    "sg:postcode":"4504",
    "sg:province":"QLD",
    "sg:tags":[
        "earth",
        "excavating",
        "moving",
        "equipment"
    ],
    "wof:name":"Hydrapower Pty Ltd",
    "wof:placetype":"venue"
},
  "geometry": {"coordinates":[152.987060547,-27.1978378296],"type":"Point"}
}