{
  "type": "Feature",
  "properties": {
    "addr:full":"149 New South Head Rd Vaucluse NSW 2030",
    "addr:housenumber":"149",
    "addr:postcode":"2030",
    "addr:street":"New South Head Rd",
    "iso:country":"AU",
    "sg:address":"149 New South Head Rd",
    "sg:city":"Vaucluse",
    "sg:classifiers":[
        {
            "category":"Personal",
            "subcategory":"Beauty Salon",
            "type":"Services"
        }
    ],
    "sg:phone":"+61 2 9337 3016",
    "sg:postcode":"2030",
    "sg:province":"NSW",
    "wof:name":"Mardi Skin Therapy",
    "wof:placetype":"venue"
},
  "geometry": {"coordinates":[151.28167724599999,-33.8571243286],"type":"Point"}
}