{
  "type": "Feature",
  "properties": {
    "addr:full":"Hyatt Business Centre Suite 17, 23 Plain St East Perth WA 6004",
    "addr:housenumber":"23",
    "addr:postcode":"6004",
    "addr:street":"Plain St East",
    "iso:country":"AU",
    "sg:address":"Hyatt Business Centre Suite 17, 23 Plain St",
    "sg:city":"East Perth",
    "sg:classifiers":[
        {
            "category":"Real Estate",
            "subcategory":"Real Estate Agent",
            "type":"Services"
        }
    ],
    "sg:phone":"+61 8 9221 8121",
    "sg:postcode":"6004",
    "sg:province":"WA",
    "wof:name":"Century 21 Australia Pty Ltd",
    "wof:placetype":"venue"
},
  "geometry": {"coordinates":[115.874206543,-31.9612293243],"type":"Point"}
}