{
  "type": "Feature",
  "properties": {
    "addr:full":"37b Anslow St Woodend VIC 3442",
    "addr:housenumber":"37b",
    "addr:postcode":"3442",
    "addr:street":"Anslow St",
    "iso:country":"AU",
    "sg:address":"37b Anslow St",
    "sg:city":"Woodend",
    "sg:classifiers":[
        {
            "category":"Personal",
            "subcategory":"Beauty Salon",
            "type":"Services"
        }
    ],
    "sg:phone":"+61 3 5427 4925",
    "sg:postcode":"3442",
    "sg:province":"VIC",
    "sg:tags":[
        "hairdresser"
    ],
    "wof:name":"Quick Snips Barber",
    "wof:placetype":"venue"
},
  "geometry": {"coordinates":[144.52792358400001,-37.3567352295],"type":"Point"}
}