{
  "type": "Feature",
  "properties": {
    "addr:full":"3 Princess St Macksville NSW 2447",
    "addr:housenumber":"3",
    "addr:postcode":"2447",
    "addr:street":"Princess St",
    "iso:country":"AU",
    "sg:address":"3 Princess St",
    "sg:city":"Macksville",
    "sg:classifiers":[
        {
            "category":"Shopping",
            "subcategory":"Baby Store",
            "type":"Retail Goods"
        }
    ],
    "sg:phone":"+61 2 6568 1231",
    "sg:postcode":"2447",
    "sg:province":"NSW",
    "sg:tags":[
        "wear"
    ],
    "wof:name":"Kids Shop The",
    "wof:placetype":"venue"
},
  "geometry": {"coordinates":[152.919479,-30.707104],"type":"Point"}
}