{
  "type": "Feature",
  "properties": {
    "addr:full":"14 Cookworthy St Geographe WA 6280",
    "addr:housenumber":"14",
    "addr:postcode":"6280",
    "addr:street":"Cookworthy St",
    "iso:country":"AU",
    "sg:address":"14 Cookworthy St",
    "sg:city":"Geographe",
    "sg:classifiers":[
        {
            "category":"Home & Garden",
            "subcategory":"Building Materials",
            "type":"Retail Goods"
        }
    ],
    "sg:phone":"+61 8 9752 4685",
    "sg:postcode":"6280",
    "sg:province":"WA",
    "sg:tags":[
        "lawn",
        "cutting",
        "maintenance"
    ],
    "wof:name":"Busselton Lawnmowing Service",
    "wof:placetype":"venue"
},
  "geometry": {"coordinates":[115.36141204800001,-33.6449661255],"type":"Point"}
}