{
  "type": "Feature",
  "properties": {
    "addr:full":"6/ 42 Burgess Rd Bayswater North VIC 3153",
    "addr:housenumber":"/ 42",
    "addr:postcode":"3153",
    "addr:street":"Burgess Rd",
    "iso:country":"AU",
    "sg:address":"6/ 42 Burgess Rd",
    "sg:city":"Bayswater North",
    "sg:classifiers":[
        {
            "category":"Utilities",
            "subcategory":"Sewage",
            "type":"Services"
        }
    ],
    "sg:phone":"+61 3 9720 3866",
    "sg:postcode":"3153",
    "sg:province":"VIC",
    "sg:tags":[
        "water",
        "waste",
        "treatment"
    ],
    "wof:name":"Diston Sewage Purification Pty Ltd",
    "wof:placetype":"venue"
},
  "geometry": {"coordinates":[145.28907775900001,-37.8211708069],"type":"Point"}
}