{
  "type": "Feature",
  "properties": {
    "addr:full":"136 William St Granville NSW 2142",
    "addr:housenumber":"136",
    "addr:postcode":"2142",
    "addr:street":"William St",
    "iso:country":"AU",
    "sg:address":"136 William St",
    "sg:city":"Granville",
    "sg:classifiers":[
        {
            "category":"Education",
            "subcategory":"Vocational School",
            "type":"Public Place"
        }
    ],
    "sg:phone":"+61 2 9682 0222",
    "sg:postcode":"2142",
    "sg:province":"NSW",
    "sg:tags":[
        "tafe",
        "college",
        "training"
    ],
    "wof:name":"TAFE NSW - South Western Sydney Institute Granville College",
    "wof:placetype":"venue"
},
  "geometry": {"coordinates":[151.00491332999999,-33.8351593018],"type":"Point"}
}