{
  "type": "Feature",
  "properties": {
    "iso:country":"AU",
    "sg:address":"30 Market St",
    "sg:city":"Adelaide",
    "sg:classifiers":[
        {
            "category":"Professional",
            "subcategory":"Lawyer & Legal Services",
            "type":"Services"
        }
    ],
    "sg:phone":"+61 8 8237 0522",
    "sg:postcode":"5000",
    "sg:province":"SA",
    "sg:tags":[
        "wills",
        "probate",
        "estate"
    ],
    "wof:name":"Richard Gardner",
    "wof:placetype":"venue"
},
  "geometry": {"coordinates":[138.59764099099999,-34.9311332703],"type":"Point"}
}