{
  "type": "Feature",
  "properties": {
    "addr:full":"Shop 7/93 Cnr Aplin St & The Esplanade Cairns QLD 4870",
    "addr:housenumber":"shop 7 / 93",
    "addr:postcode":"4870",
    "addr:street":"Cnr Aplin St & The Esplanade",
    "iso:country":"AU",
    "sg:address":"Shop 7/93 Cnr Aplin St & The Esplanade",
    "sg:city":"Cairns",
    "sg:classifiers":[
        {
            "category":"Restaurant",
            "type":"Food & Drink"
        }
    ],
    "sg:phone":"+61 7 4041 2624",
    "sg:postcode":"4870",
    "sg:province":"QLD",
    "wof:name":"Cafe Thailand",
    "wof:placetype":"venue"
},
  "geometry": {"coordinates":[145.76951599099999,-16.9241733551],"type":"Point"}
}