{
  "type": "Feature",
  "properties": {
    "iso:country":"AU",
    "sg:address":"Keane St East",
    "sg:city":"Mt Helena",
    "sg:classifiers":[
        {
            "category":"Education",
            "subcategory":"School",
            "type":"Public Place"
        }
    ],
    "sg:phone":"+61 8 9295 2722",
    "sg:postcode":"6082",
    "sg:province":"WA",
    "sg:tags":[
        "state",
        "except",
        "nsw"
    ],
    "wof:name":"Eastern Hills Senior High School",
    "wof:placetype":"venue"
},
  "geometry": {"coordinates":[116.21082305900001,-31.8779315948],"type":"Point"}
}