{
  "type": "Feature",
  "properties": {
    "addr:full":"287 Forest Rd Bexley NSW 2207",
    "addr:housenumber":"287",
    "addr:postcode":"2207",
    "addr:street":"Forest Rd",
    "iso:country":"AU",
    "sg:address":"287 Forest Rd",
    "sg:city":"Bexley",
    "sg:classifiers":[
        {
            "category":"Food & Beverages",
            "subcategory":"Liquor & Beverages",
            "type":"Retail Goods"
        }
    ],
    "sg:phone":"+61 2 9599 0255",
    "sg:postcode":"2207",
    "sg:province":"NSW",
    "sg:tags":[
        "store"
    ],
    "wof:name":"Porter's Liquor",
    "wof:placetype":"venue"
},
  "geometry": {"coordinates":[151.12475599999999,-33.951515],"type":"Point"}
}