{
  "type": "Feature",
  "properties": {
    "addr:full":"164 Piccadilly St Kalgoorlie WA 6430",
    "addr:housenumber":"164",
    "addr:postcode":"6430",
    "addr:street":"Piccadilly St",
    "iso:country":"AU",
    "sg:address":"164 Piccadilly St",
    "sg:city":"Kalgoorlie",
    "sg:classifiers":[
        {
            "category":"Travel",
            "subcategory":"Hotels & Motels",
            "type":"Entertainment"
        }
    ],
    "sg:phone":"+61 8 9021 2109",
    "sg:postcode":"6430",
    "sg:province":"WA",
    "sg:tags":[
        "accommodation"
    ],
    "wof:name":"Piccadilly Hotel",
    "wof:placetype":"venue"
},
  "geometry": {"coordinates":[121.464752197,-30.7441673279],"type":"Point"}
}