{
  "type": "Feature",
  "properties": {
    "iso:country":"AU",
    "sg:address":"2 Gailey Rd",
    "sg:city":"St Lucia",
    "sg:classifiers":[
        {
            "category":"Travel",
            "subcategory":"Hotels & Motels",
            "type":"Entertainment"
        }
    ],
    "sg:phone":"+61 7 3870 7644",
    "sg:postcode":"4067",
    "sg:province":"QLD",
    "wof:name":"St Lucia Gardens Apartments",
    "wof:placetype":"venue"
},
  "geometry": {"coordinates":[152.99447631800001,-27.4908103943],"type":"Point"}
}