{
  "type": "Feature",
  "properties": {
    "addr:full":"Lot 4, Cnr Angle Vale & Taylors Rd Penfield Gardens SA 5121",
    "addr:housenumber":"cnr",
    "addr:postcode":"5121",
    "addr:street":"Angle Vale & Taylors Rd",
    "iso:country":"AU",
    "sg:address":"Lot 4, Cnr Angle Vale & Taylors Rd",
    "sg:city":"Penfield Gardens",
    "sg:classifiers":[
        {
            "category":"Social Services",
            "subcategory":"Retirement Home",
            "type":"Services"
        }
    ],
    "sg:phone":"+61 8 8284 8283",
    "sg:postcode":"5121",
    "sg:province":"SA",
    "sg:tags":[
        "accommodation",
        "special"
    ],
    "wof:name":"Salisbury & Elizabeth Caravan Hire",
    "wof:placetype":"venue"
},
  "geometry": {"coordinates":[138.61497497600001,-34.6456489563],"type":"Point"}
}