{
  "type": "Feature",
  "properties": {
    "addr:full":"Suite 105/10- 16 Kenrick St The Junction NSW 2291",
    "addr:housenumber":"/;16",
    "addr:postcode":"2291",
    "addr:street":"10;Kenrick St",
    "iso:country":"AU",
    "sg:address":"Suite 105/10- 16 Kenrick St",
    "sg:city":"The Junction",
    "sg:classifiers":[
        {
            "category":"Health Services",
            "subcategory":"Health Practitioner",
            "type":"Services"
        }
    ],
    "sg:phone":"+61 2 4962 4976",
    "sg:postcode":"2291",
    "sg:province":"NSW",
    "sg:tags":[
        "naturopath"
    ],
    "wof:name":"Beeston Julieanne",
    "wof:placetype":"venue"
},
  "geometry": {"coordinates":[151.76031494099999,-32.9382209778],"type":"Point"}
}