{
  "type": "Feature",
  "properties": {
    "addr:full":"51 Main Rd Claremont TAS 7011",
    "addr:housenumber":"51",
    "addr:postcode":"7011",
    "addr:street":"Main Rd",
    "iso:country":"AU",
    "sg:address":"51 Main Rd",
    "sg:city":"Claremont",
    "sg:classifiers":[
        {
            "category":"Fast Food",
            "type":"Food & Drink"
        }
    ],
    "sg:phone":"+61 3 6249 8181",
    "sg:postcode":"7011",
    "sg:province":"TAS",
    "sg:tags":[
        "away",
        "take"
    ],
    "wof:name":"Pasta On The Run",
    "wof:placetype":"venue"
},
  "geometry": {"coordinates":[147.25369262699999,-42.7897796631],"type":"Point"}
}