{
  "type": "Feature",
  "properties": {
    "iso:country":"AU",
    "sg:address":"11 Blackwood Drv",
    "sg:city":"Rocherlea",
    "sg:classifiers":[
        {
            "category":"Social Services",
            "subcategory":"Child Care",
            "type":"Services"
        }
    ],
    "sg:phone":"+61 3 6326 6786",
    "sg:postcode":"7248",
    "sg:province":"TAS",
    "wof:name":"Li-Lea Pad Child care Centre",
    "wof:placetype":"venue"
},
  "geometry": {"coordinates":[147.13800048799999,-41.3753051758],"type":"Point"}
}