{
  "type": "Feature",
  "properties": {
    "addr:full":"24 Grenfell Ave North Narrabeen NSW 2101",
    "addr:housenumber":"24",
    "addr:postcode":"2101",
    "addr:street":"Grenfell Ave",
    "iso:country":"AU",
    "sg:address":"24 Grenfell Ave",
    "sg:city":"North Narrabeen",
    "sg:classifiers":[
        {
            "category":"Autos & Motor Vehicles",
            "subcategory":"Boat Sales",
            "type":"Retail Goods"
        }
    ],
    "sg:phone":"+61 414 424 207",
    "sg:postcode":"2101",
    "sg:province":"NSW",
    "sg:tags":[
        "builder",
        "yacht",
        "repairer"
    ],
    "wof:name":"G S Shipwright Service",
    "wof:placetype":"venue"
},
  "geometry": {"coordinates":[151.29359400000001,-33.709938],"type":"Point"}
}