{
  "type": "Feature",
  "properties": {
    "addr:full":"Unit 2/ 133 High Rd Willetton WA 6155",
    "addr:housenumber":"/ 133",
    "addr:postcode":"6155",
    "addr:street":"High Rd",
    "iso:country":"AU",
    "sg:address":"Unit 2/ 133 High Rd",
    "sg:city":"Willetton",
    "sg:classifiers":[
        {
            "category":"Manufacturing",
            "subcategory":"Furniture",
            "type":"Manufacturing & Wholesale Goods"
        }
    ],
    "sg:phone":"+61 8 9259 5988",
    "sg:postcode":"6155",
    "sg:province":"WA",
    "sg:tags":[
        "builder",
        "designer",
        "custom"
    ],
    "wof:name":"The Timber Box",
    "wof:placetype":"venue"
},
  "geometry": {"coordinates":[115.879929,-32.038815],"type":"Point"}
}