{
  "type": "Feature",
  "properties": {
    "addr:full":"37-38/ 62 Hume Hwy Lansvale NSW 2166",
    "addr:housenumber":"37-38 / 62",
    "addr:postcode":"2166",
    "addr:street":"Hume Hwy",
    "iso:country":"AU",
    "sg:address":"37-38/ 62 Hume Hwy",
    "sg:city":"Lansvale",
    "sg:classifiers":[
        {
            "category":"Building & Trades",
            "subcategory":"Construction",
            "type":"Services"
        }
    ],
    "sg:phone":"+61 2 9755 0909",
    "sg:postcode":"2166",
    "sg:province":"NSW",
    "sg:tags":[
        "home",
        "air conditioning"
    ],
    "wof:name":"Blue Star Air Conditioning",
    "wof:placetype":"venue"
},
  "geometry": {"coordinates":[150.96389770499999,-33.891872406],"type":"Point"}
}