{
  "type": "Feature",
  "properties": {
    "addr:full":"3/ 181 Miller St North Sydney NSW 2060",
    "addr:housenumber":"/ 181",
    "addr:postcode":"2060",
    "addr:street":"Miller St",
    "iso:country":"AU",
    "sg:address":"3/ 181 Miller St",
    "sg:city":"North Sydney",
    "sg:classifiers":[
        {
            "category":"Personal",
            "type":"Services"
        }
    ],
    "sg:phone":"+61 2 9922 3575",
    "sg:postcode":"2060",
    "sg:province":"NSW",
    "sg:tags":[
        "dressmaker"
    ],
    "wof:name":"Paria Dress Making",
    "wof:placetype":"venue"
},
  "geometry": {"coordinates":[151.207321167,-33.8372688293],"type":"Point"}
}