{
  "type": "Feature",
  "properties": {
    "addr:full":"Shop 2/ 4 Ballantine St Gladstone QLD 4680",
    "addr:housenumber":"shop 2 / 4",
    "addr:postcode":"4680",
    "addr:street":"Ballantine St",
    "iso:country":"AU",
    "sg:address":"Shop 2/ 4 Ballantine St",
    "sg:city":"Gladstone",
    "sg:classifiers":[
        {
            "category":"Personal",
            "subcategory":"Beauty Salon",
            "type":"Services"
        }
    ],
    "sg:phone":"+61 7 4972 3622",
    "sg:postcode":"4680",
    "sg:province":"QLD",
    "wof:name":"Passion Hair & Beauty Studio",
    "wof:placetype":"venue"
},
  "geometry": {"coordinates":[151.25477600100001,-23.8413600922],"type":"Point"}
}