{
  "type": "Feature",
  "properties": {
    "iso:country":"AU",
    "sg:address":"PO Box 456",
    "sg:city":"Berri",
    "sg:classifiers":[
        {
            "category":"Professional",
            "subcategory":"Art Services",
            "type":"Services"
        }
    ],
    "sg:phone":"+61 8 8583 5165",
    "sg:postcode":"5343",
    "sg:province":"SA",
    "sg:tags":[
        "decorator",
        "painter"
    ],
    "wof:name":"A G & J A Lowery",
    "wof:placetype":"venue"
},
  "geometry": {"coordinates":[140.598846436,-34.2817192078],"type":"Point"}
}