{
  "type": "Feature",
  "properties": {
    "addr:full":"Lvl 6/ 35 Grafton St Bondi Junction NSW 2022",
    "addr:housenumber":"/ 35",
    "addr:postcode":"2022",
    "addr:street":"Grafton St",
    "iso:country":"AU",
    "sg:address":"Lvl 6/ 35 Grafton St",
    "sg:city":"Bondi Junction",
    "sg:classifiers":[
        {
            "category":"Professional",
            "subcategory":"Computer Services",
            "type":"Services"
        }
    ],
    "sg:phone":"+61 2 9386 2900",
    "sg:postcode":"2022",
    "sg:province":"NSW",
    "sg:tags":[
        "technical",
        "support"
    ],
    "wof:name":"Systemnet Pty Ltd",
    "wof:placetype":"venue"
},
  "geometry": {"coordinates":[151.244903564,-33.8902549744],"type":"Point"}
}