{
  "type": "Feature",
  "properties": {
    "addr:full":"63 Shannon Crt Kaleen ACT 2617",
    "addr:housenumber":"63",
    "addr:postcode":"2617",
    "addr:street":"Shannon Crt",
    "iso:country":"AU",
    "sg:address":"63 Shannon Crt",
    "sg:city":"Kaleen",
    "sg:classifiers":[
        {
            "category":"Retail",
            "subcategory":"Storage",
            "type":"Services"
        }
    ],
    "sg:phone":"+61 2 6242 4386",
    "sg:postcode":"2617",
    "sg:province":"ACT",
    "sg:tags":[
        "equipment",
        "computer",
        "secondhand"
    ],
    "wof:name":"Katalinic Computers",
    "wof:placetype":"venue"
},
  "geometry": {"coordinates":[149.103393555,-35.2378540039],"type":"Point"}
}