{
  "type": "Feature",
  "properties": {
    "addr:full":"Shop 88, 116- 136 Cecil St South Melbourne VIC 3205",
    "addr:housenumber":"shop 88 116 136",
    "addr:postcode":"3205",
    "addr:street":"Cecil St",
    "iso:country":"AU",
    "sg:address":"Shop 88, 116- 136 Cecil St",
    "sg:city":"South Melbourne",
    "sg:classifiers":[
        {
            "category":"Fast Food",
            "type":"Food & Drink"
        }
    ],
    "sg:phone":"+61 3 9682 2752",
    "sg:postcode":"3205",
    "sg:province":"VIC",
    "sg:tags":[
        "away",
        "take"
    ],
    "wof:name":"Sushi Sushi",
    "wof:placetype":"venue"
},
  "geometry": {"coordinates":[144.957367,-37.832405],"type":"Point"}
}