{
  "type": "Feature",
  "properties": {
    "addr:full":"87 Mary St Gympie QLD 4570",
    "addr:housenumber":"87",
    "addr:postcode":"4570",
    "addr:street":"Mary St",
    "iso:country":"AU",
    "sg:address":"87 Mary St",
    "sg:city":"Gympie",
    "sg:classifiers":[
        {
            "category":"Banks & Credit Unions",
            "subcategory":"Bank",
            "type":"Services"
        }
    ],
    "sg:phone":"+61 7 5482 2845",
    "sg:postcode":"4570",
    "sg:province":"QLD",
    "wof:name":"Credit Union Australia",
    "wof:placetype":"venue"
},
  "geometry": {"coordinates":[152.663131714,-26.1900501251],"type":"Point"}
}