{
  "type": "Feature",
  "properties": {
    "addr:full":"32 Greens Rd Dandenong VIC 3175",
    "addr:housenumber":"32",
    "addr:postcode":"3175",
    "addr:street":"Greens Rd",
    "iso:country":"AU",
    "sg:address":"32 Greens Rd",
    "sg:city":"Dandenong",
    "sg:classifiers":[
        {
            "category":"Utilities",
            "subcategory":"Cable",
            "type":"Services"
        }
    ],
    "sg:phone":"+61 3 9791 3255",
    "sg:postcode":"3175",
    "sg:province":"VIC",
    "sg:tags":[
        "equipment",
        "meters"
    ],
    "wof:name":"Acme Fluid Handling Pty Ltd",
    "wof:placetype":"venue"
},
  "geometry": {"coordinates":[145.22012329099999,-38.0153999329],"type":"Point"}
}