{
  "type": "Feature",
  "properties": {
    "iso:country":"AU",
    "sg:address":"Level 6 STE 6001/ 376 Bay St",
    "sg:city":"Brighton-le-Sands",
    "sg:classifiers":[
        {
            "category":"Banks & Credit Unions",
            "subcategory":"Financial Services",
            "type":"Services"
        }
    ],
    "sg:phone":"+61 1300 888 924",
    "sg:postcode":"2216",
    "sg:province":"NSW",
    "sg:tags":[
        "loan",
        "finance",
        "mortgage"
    ],
    "wof:name":"Finance Store Direct",
    "wof:placetype":"venue"
},
  "geometry": {"coordinates":[151.156128,-33.960987],"type":"Point"}
}