{
  "type": "Feature",
  "properties": {
    "addr:full":"1405 Main North Rd Para Hills West SA 5096",
    "addr:housenumber":"1405",
    "addr:postcode":"5096",
    "addr:street":"Main North Rd Para Hills West",
    "iso:country":"AU",
    "sg:address":"1405 Main North Rd",
    "sg:city":"Para Hills West",
    "sg:phone":"+61 8 8281 9624",
    "sg:postcode":"5096",
    "sg:province":"SA",
    "wof:name":"Town & Country Tanks",
    "wof:placetype":"venue"
},
  "geometry": {"coordinates":[138.64341735799999,-34.7963600159],"type":"Point"}
}