{
  "type": "Feature",
  "properties": {
    "addr:full":"Ste44/ 1 Ricketts Rd Narre Warren VIC 3805",
    "addr:postcode":"3805",
    "addr:street":"Ricketts Rd",
    "iso:country":"AU",
    "sg:address":"Ste44/ 1 Ricketts Rd",
    "sg:city":"Narre Warren",
    "sg:classifiers":[
        {
            "category":"Professional",
            "subcategory":"Computer Services",
            "type":"Services"
        }
    ],
    "sg:phone":"+61 1300 730 548",
    "sg:postcode":"3805",
    "sg:province":"VIC",
    "sg:tags":[
        "equipment",
        "networking",
        "installation"
    ],
    "wof:name":"Network Neighborhood Pty Ltd",
    "wof:placetype":"venue"
},
  "geometry": {"coordinates":[145.305588,-38.02042],"type":"Point"}
}