{
  "type": "Feature",
  "properties": {
    "addr:full":"1st Floor 211 Main St Osborne Park WA 6017",
    "addr:housenumber":"211",
    "addr:postcode":"6017",
    "addr:street":"Main St",
    "iso:country":"AU",
    "sg:address":"1st Floor 211 Main St",
    "sg:city":"Osborne Park",
    "sg:classifiers":[
        {
            "category":"Professional",
            "subcategory":"Detective & Security Services",
            "type":"Services"
        }
    ],
    "sg:phone":"+61 8 9344 2067",
    "sg:postcode":"6017",
    "sg:province":"WA",
    "sg:tags":[
        "investigator"
    ],
    "wof:name":"Perth Detective Agency",
    "wof:placetype":"venue"
},
  "geometry": {"coordinates":[115.828102112,-31.8973274231],"type":"Point"}
}