{
  "type": "Feature",
  "properties": {
    "iso:country":"AU",
    "sg:address":"15 Sargood St",
    "sg:city":"O'Connor",
    "sg:classifiers":[
        {
            "category":"Health Services",
            "subcategory":"Doctor",
            "type":"Services"
        }
    ],
    "sg:phone":"+61 2 6248 7878",
    "sg:postcode":"2602",
    "sg:province":"ACT",
    "sg:tags":[
        "medical",
        "practitioner"
    ],
    "wof:name":"Mills I A",
    "wof:placetype":"venue"
},
  "geometry": {"coordinates":[149.12309265100001,-35.2644081116],"type":"Point"}
}