{
  "type": "Feature",
  "properties": {
    "iso:country":"AU",
    "sg:address":"1 Kobyboyn Rd",
    "sg:city":"Seymour",
    "sg:classifiers":[
        {
            "category":"Home & Garden",
            "subcategory":"Garden Supply",
            "type":"Retail Goods"
        }
    ],
    "sg:phone":"+61 3 5792 1053",
    "sg:postcode":"3660",
    "sg:province":"VIC",
    "sg:tags":[
        "fertilizer"
    ],
    "wof:name":"Handley J K",
    "wof:placetype":"venue"
},
  "geometry": {"coordinates":[145.159332275,-37.0376586914],"type":"Point"}
}