{
  "type": "Feature",
  "properties": {
    "addr:full":"7 Ferngrove Pl Chester Hill NSW 2162",
    "addr:housenumber":"7",
    "addr:postcode":"2162",
    "addr:street":"Ferngrove Pl",
    "iso:country":"AU",
    "sg:address":"7 Ferngrove Pl",
    "sg:city":"Chester Hill",
    "sg:classifiers":[
        {
            "category":"Shopping",
            "subcategory":"Stationery & Office Supplies",
            "type":"Retail Goods"
        }
    ],
    "sg:phone":"+61 2 9743 8133",
    "sg:postcode":"2162",
    "sg:province":"NSW",
    "sg:tags":[
        "packaging",
        "equipment",
        "sealing",
        "filling"
    ],
    "wof:name":"Sam Owl",
    "wof:placetype":"venue"
},
  "geometry": {"coordinates":[151.00502014200001,-33.8720092773],"type":"Point"}
}