{
  "type": "Feature",
  "properties": {
    "iso:country":"AU",
    "sg:address":"10 Isaacs Ave",
    "sg:city":"Yackandandah",
    "sg:classifiers":[
        {
            "category":"Education",
            "subcategory":"Special Training",
            "type":"Public Place"
        }
    ],
    "sg:phone":"+61 2 6027 1005",
    "sg:postcode":"3749",
    "sg:province":"VIC",
    "sg:tags":[
        "development"
    ],
    "wof:name":"TTP Communication & Training Pty Ltd",
    "wof:placetype":"venue"
},
  "geometry": {"coordinates":[146.84356700000001,-36.311611],"type":"Point"}
}