{
  "type": "Feature",
  "properties": {
    "addr:full":"144 Anzac Hwy Glandore SA 5037",
    "addr:housenumber":"144",
    "addr:postcode":"5037",
    "addr:street":"Anzac Hwy",
    "iso:country":"AU",
    "sg:address":"144 Anzac Hwy",
    "sg:city":"Glandore",
    "sg:classifiers":[
        {
            "category":"Personal",
            "subcategory":"Beauty Salon",
            "type":"Services"
        }
    ],
    "sg:phone":"+61 8 8293 8588",
    "sg:postcode":"5037",
    "sg:province":"SA",
    "wof:name":"Invigorating Body Care",
    "wof:placetype":"venue"
},
  "geometry": {"coordinates":[138.56802368199999,-34.9556655884],"type":"Point"}
}