{
  "type": "Feature",
  "properties": {
    "iso:country":"AU",
    "sg:address":"PO Box 8042",
    "sg:city":"Toowoomba South",
    "sg:classifiers":[
        {
            "category":"Building & Trades",
            "subcategory":"Construction",
            "type":"Services"
        }
    ],
    "sg:phone":"+61 407 117 207",
    "sg:postcode":"4350",
    "sg:province":"QLD",
    "sg:tags":[
        "concrete",
        "contractor"
    ],
    "wof:name":"Stirling Pallier Concreting",
    "wof:placetype":"venue"
},
  "geometry": {"coordinates":[151.875641,-27.55761],"type":"Point"}
}