{
  "type": "Feature",
  "properties": {
    "iso:country":"AU",
    "sg:address":"Brimbank Central Shopping Centre Neale Rd",
    "sg:city":"Deer Park",
    "sg:classifiers":[
        {
            "category":"Health Services",
            "subcategory":"Doctor",
            "type":"Services"
        }
    ],
    "sg:phone":"+61 3 9363 6101",
    "sg:postcode":"3023",
    "sg:province":"VIC",
    "sg:tags":[
        "medical",
        "practitioner"
    ],
    "wof:name":"O&#039;Sullivan K A Dr",
    "wof:placetype":"venue"
},
  "geometry": {"coordinates":[144.776657,-37.752533],"type":"Point"}
}