{
  "type": "Feature",
  "properties": {
    "addr:full":"78 Neptune St Umina NSW 2257",
    "addr:housenumber":"78",
    "addr:postcode":"2257",
    "addr:street":"Neptune St",
    "iso:country":"AU",
    "sg:address":"78 Neptune St",
    "sg:city":"Umina",
    "sg:classifiers":[
        {
            "category":"Building & Trades",
            "subcategory":"Construction",
            "type":"Services"
        }
    ],
    "sg:phone":"+61 2 4342 1091",
    "sg:postcode":"2257",
    "sg:province":"NSW",
    "sg:tags":[
        "joiner",
        "carpenter"
    ],
    "wof:name":"Gary M Matthews",
    "wof:placetype":"venue"
},
  "geometry": {"coordinates":[151.31939697300001,-33.5150413513],"type":"Point"}
}