{
  "type": "Feature",
  "properties": {
    "iso:country":"AU",
    "sg:address":"Suite 80",
    "sg:city":"/ Middlemount Shpng Ctr Middlemount",
    "sg:classifiers":[
        {
            "category":"Health Services",
            "subcategory":"Dentist",
            "type":"Services"
        }
    ],
    "sg:phone":"+61 7 4985 7638",
    "sg:postcode":"4746",
    "sg:province":"QLD",
    "wof:name":"Chan Pui Kwan & Wong Janis",
    "wof:placetype":"venue"
},
  "geometry": {"coordinates":[148.713455,-22.819771],"type":"Point"}
}