{
  "type": "Feature",
  "properties": {
    "addr:full":"25 Fairlands St Culburra Beach NSW 2540",
    "addr:housenumber":"25",
    "addr:postcode":"2540",
    "addr:street":"Fairlands St",
    "iso:country":"AU",
    "sg:address":"25 Fairlands St",
    "sg:city":"Culburra Beach",
    "sg:classifiers":[
        {
            "category":"Home & Garden",
            "subcategory":"Building Materials",
            "type":"Retail Goods"
        }
    ],
    "sg:phone":"+61 2 4447 2656",
    "sg:postcode":"2540",
    "sg:province":"NSW",
    "sg:tags":[
        "fitting",
        "door"
    ],
    "wof:name":"Maverick Locksmithing & Screens",
    "wof:placetype":"venue"
},
  "geometry": {"coordinates":[150.759643555,-34.9327354431],"type":"Point"}
}