{
  "type": "Feature",
  "properties": {
    "addr:full":"375 Scarborough Beach Rd Innaloo WA 6018",
    "addr:housenumber":"375",
    "addr:postcode":"6018",
    "addr:street":"Scarborough Beach Rd",
    "iso:country":"AU",
    "sg:address":"375 Scarborough Beach Rd",
    "sg:city":"Innaloo",
    "sg:classifiers":[
        {
            "category":"Ice Cream",
            "type":"Food & Drink"
        }
    ],
    "sg:phone":"+61 8 9204 1177",
    "sg:postcode":"6018",
    "sg:province":"WA",
    "sg:tags":[
        "retail"
    ],
    "wof:name":"Baskin-Robbins Australia Pty Ltd",
    "wof:placetype":"venue"
},
  "geometry": {"coordinates":[115.79672241199999,-31.9024505615],"type":"Point"}
}