{
  "type": "Feature",
  "properties": {
    "iso:country":"AU",
    "sg:address":"PO Box 123",
    "sg:city":"Gisborne",
    "sg:classifiers":[
        {
            "category":"Building & Trades",
            "subcategory":"Plumbing",
            "type":"Services"
        }
    ],
    "sg:phone":"+61 3 5428 2772",
    "sg:postcode":"3437",
    "sg:province":"VIC",
    "sg:tags":[
        "plumber",
        "gasfitters"
    ],
    "wof:name":"Gisborne Plumbing Pty Ltd",
    "wof:placetype":"venue"
},
  "geometry": {"coordinates":[144.59135437,-37.4869995117],"type":"Point"}
}