{
  "type": "Feature",
  "properties": {
    "iso:country":"AU",
    "sg:address":"PO Box 1112",
    "sg:city":"Waikerie",
    "sg:classifiers":[
        {
            "category":"Building & Trades",
            "subcategory":"Construction",
            "type":"Services"
        }
    ],
    "sg:phone":"+61 411 174 629",
    "sg:postcode":"5330",
    "sg:province":"SA",
    "sg:tags":[
        "earth",
        "excavating",
        "moving",
        "contractor"
    ],
    "wof:name":"Francis Jeff",
    "wof:placetype":"venue"
},
  "geometry": {"coordinates":[140.00225830100001,-34.1883811951],"type":"Point"}
}