{
  "type": "Feature",
  "properties": {
    "addr:full":"2/ 61 O&#039;Sullivan Beach Rd Lonsdale SA 5160",
    "addr:housenumber":"/ 61 o",
    "addr:postcode":"5160",
    "addr:street":"Sullivan Beach Rd",
    "iso:country":"AU",
    "sg:address":"2/ 61 O&#039;Sullivan Beach Rd",
    "sg:city":"Lonsdale",
    "sg:classifiers":[
        {
            "category":"Shopping",
            "subcategory":"Bicycles & Sporting Goods",
            "type":"Retail Goods"
        }
    ],
    "sg:phone":"+61 8 8186 6911",
    "sg:postcode":"5160",
    "sg:province":"SA",
    "sg:tags":[
        "water",
        "equipment",
        "skiing"
    ],
    "wof:name":"Camero Water Sports",
    "wof:placetype":"venue"
},
  "geometry": {"coordinates":[138.50384521500001,-35.1168632507],"type":"Point"}
}