{
  "type": "Feature",
  "properties": {
    "addr:full":"Cnr Victoria & Little Sts Smithfield NSW 2164",
    "addr:postcode":"2164",
    "addr:street":"Cnr",
    "iso:country":"AU",
    "sg:address":"Cnr Victoria & Little Sts",
    "sg:city":"Smithfield",
    "sg:classifiers":[
        {
            "category":"Retail",
            "subcategory":"Auto Repair",
            "type":"Services"
        }
    ],
    "sg:phone":"+61 2 9725 5330",
    "sg:postcode":"2164",
    "sg:province":"NSW",
    "sg:tags":[
        "wheel",
        "balancing",
        "alignment"
    ],
    "wof:name":"Pro-Axle",
    "wof:placetype":"venue"
},
  "geometry": {"coordinates":[150.94158935600001,-33.8510856628],"type":"Point"}
}