{
  "type": "Feature",
  "properties": {
    "addr:full":"PO Box 221 Hall ACT 2618",
    "addr:postcode":"2618",
    "iso:country":"AU",
    "sg:address":"PO Box 221",
    "sg:city":"Hall",
    "sg:classifiers":[
        {
            "category":"Personal",
            "subcategory":"Beauty Salon",
            "type":"Services"
        }
    ],
    "sg:phone":"+61 2 6230 9220",
    "sg:postcode":"2618",
    "sg:province":"ACT",
    "wof:name":"Geranium House for Women",
    "wof:placetype":"venue"
},
  "geometry": {"coordinates":[149.06988525400001,-35.1702308655],"type":"Point"}
}