{
  "type": "Feature",
  "properties": {
    "addr:full":"86 Glenmore Rd Park Avenue QLD 4701",
    "addr:housenumber":"86",
    "addr:postcode":"4701",
    "addr:street":"Glenmore Rd Park",
    "iso:country":"AU",
    "sg:address":"86 Glenmore Rd",
    "sg:city":"Park Avenue",
    "sg:classifiers":[
        {
            "category":"Fast Food",
            "type":"Food & Drink"
        }
    ],
    "sg:phone":"+61 7 4921 2006",
    "sg:postcode":"4701",
    "sg:province":"QLD",
    "sg:tags":[
        "away",
        "take"
    ],
    "wof:name":"J J's On Glenmore",
    "wof:placetype":"venue"
},
  "geometry": {"coordinates":[150.507247925,-23.3618278503],"type":"Point"}
}