{
  "type": "Feature",
  "properties": {
    "addr:full":"35 Harris St Fairfield NSW 2165",
    "addr:housenumber":"35",
    "addr:postcode":"2165",
    "addr:street":"Harris St",
    "iso:country":"AU",
    "sg:address":"35 Harris St",
    "sg:city":"Fairfield",
    "sg:classifiers":[
        {
            "category":"Banks & Credit Unions",
            "subcategory":"Financial Services",
            "type":"Services"
        }
    ],
    "sg:phone":"+61 2 9755 7477",
    "sg:postcode":"2165",
    "sg:province":"NSW",
    "sg:tags":[
        "loan",
        "finance",
        "mortgage"
    ],
    "wof:name":"Platinum Home Loans",
    "wof:placetype":"venue"
},
  "geometry": {"coordinates":[150.9480896,-33.8717536926],"type":"Point"}
}