{
  "type": "Feature",
  "properties": {
    "addr:full":"Numurkah Rd Shepparton VIC 3630",
    "addr:postcode":"3630",
    "addr:street":"Numurkah Rd",
    "iso:country":"AU",
    "sg:address":"Numurkah Rd",
    "sg:city":"Shepparton",
    "sg:classifiers":[
        {
            "category":"Autos & Motor Vehicles",
            "subcategory":"Fuel & Gas Station",
            "type":"Retail Goods"
        }
    ],
    "sg:phone":"+61 3 5821 5869",
    "sg:postcode":"3630",
    "sg:province":"VIC",
    "wof:name":"BP Australia Limited",
    "wof:placetype":"venue"
},
  "geometry": {"coordinates":[145.40231323200001,-36.3664627075],"type":"Point"}
}