{
  "type": "Feature",
  "properties": {
    "iso:country":"AU",
    "sg:address":"80 Koornang Rd",
    "sg:city":"Carnegie",
    "sg:classifiers":[
        {
            "category":"Health Services",
            "subcategory":"Optometrist",
            "type":"Services"
        }
    ],
    "sg:phone":"+61 3 9569 9609",
    "sg:postcode":"3163",
    "sg:province":"VIC",
    "wof:name":"EYEdentity Carnegie",
    "wof:placetype":"venue"
},
  "geometry": {"coordinates":[145.05760192899999,-37.8871879578],"type":"Point"}
}