{
  "type": "Feature",
  "properties": {
    "iso:country":"AU",
    "sg:address":"26 A Walker St",
    "sg:city":"Turrella",
    "sg:classifiers":[
        {
            "category":"Autos & Motor Vehicles",
            "subcategory":"Auto Supplies",
            "type":"Retail Goods"
        }
    ],
    "sg:phone":"+61 417 700 079",
    "sg:postcode":"2205",
    "sg:province":"NSW",
    "sg:tags":[
        "car",
        "alarm"
    ],
    "wof:name":"Ultimate Car Installations",
    "wof:placetype":"venue"
},
  "geometry": {"coordinates":[151.14520300000001,-33.930779],"type":"Point"}
}