{
  "type": "Feature",
  "properties": {
    "addr:full":"127 Hawker St Ridleyton SA 5008",
    "addr:housenumber":"127",
    "addr:postcode":"5008",
    "addr:street":"Hawker St",
    "iso:country":"AU",
    "sg:address":"127 Hawker St",
    "sg:city":"Ridleyton",
    "sg:classifiers":[
        {
            "category":"Real Estate",
            "subcategory":"Architect",
            "type":"Services"
        }
    ],
    "sg:phone":"+61 8 8346 9338",
    "sg:postcode":"5008",
    "sg:province":"SA",
    "sg:tags":[
        "building",
        "designer"
    ],
    "wof:name":"Peter Robertson Design/Drafting",
    "wof:placetype":"venue"
},
  "geometry": {"coordinates":[138.56950399999999,-34.892582],"type":"Point"}
}