{
  "type": "Feature",
  "properties": {
    "addr:full":"30 Boronia Rd Vermont VIC 3133",
    "addr:housenumber":"30",
    "addr:postcode":"3133",
    "addr:street":"Boronia Rd",
    "iso:country":"AU",
    "sg:address":"30 Boronia Rd",
    "sg:city":"Vermont",
    "sg:classifiers":[
        {
            "category":"Health Services",
            "subcategory":"Health Practitioner",
            "type":"Services"
        }
    ],
    "sg:phone":"+61 3 9874 5962",
    "sg:postcode":"3133",
    "sg:province":"VIC",
    "sg:tags":[
        "alternative"
    ],
    "wof:name":"Genesis Festivals & Fairs",
    "wof:placetype":"venue"
},
  "geometry": {"coordinates":[145.19729614299999,-37.8380393982],"type":"Point"}
}