{
  "type": "Feature",
  "properties": {
    "addr:full":"75 Talavera Rd Macquarie Park NSW 2113",
    "addr:housenumber":"75",
    "addr:postcode":"2113",
    "addr:street":"Talavera Rd",
    "iso:country":"AU",
    "sg:address":"75 Talavera Rd",
    "sg:city":"Macquarie Park",
    "sg:classifiers":[
        {
            "category":"Food & Beverages",
            "subcategory":"Bakery",
            "type":"Retail Goods"
        }
    ],
    "sg:phone":"+61 2 8874 7300",
    "sg:postcode":"2113",
    "sg:province":"NSW",
    "sg:tags":[
        "baker"
    ],
    "wof:name":"Buttercup Bakeries",
    "wof:placetype":"venue"
},
  "geometry": {"coordinates":[151.123245239,-33.7764434814],"type":"Point"}
}