{
  "type": "Feature",
  "properties": {
    "addr:full":"55 tarwin St Boolarra VIC 3870",
    "addr:housenumber":"55",
    "addr:postcode":"3870",
    "addr:street":"Tarwin St",
    "iso:country":"AU",
    "sg:address":"55 tarwin St",
    "sg:city":"Boolarra",
    "sg:classifiers":[
        {
            "category":"Health Services",
            "subcategory":"Health Practitioner",
            "type":"Services"
        }
    ],
    "sg:phone":"+61 3 5169 6355",
    "sg:postcode":"3870",
    "sg:province":"VIC",
    "sg:tags":[
        "homoeopath"
    ],
    "wof:name":"Marietta Herni",
    "wof:placetype":"venue"
},
  "geometry": {"coordinates":[146.268966675,-38.3827934265],"type":"Point"}
}