{
  "type": "Feature",
  "properties": {
    "addr:full":"Shop 14, 65- 71 Barrabool Rd Highton VIC 3216",
    "addr:housenumber":"shop 14 65 71",
    "addr:postcode":"3216",
    "addr:street":"Barrabool Rd",
    "iso:country":"AU",
    "sg:address":"Shop 14, 65- 71 Barrabool Rd",
    "sg:city":"Highton",
    "sg:classifiers":[
        {
            "category":"Travel",
            "subcategory":"Travel Agent",
            "type":"Entertainment"
        }
    ],
    "sg:phone":"+61 13 18 66",
    "sg:postcode":"3216",
    "sg:province":"VIC",
    "sg:tags":[
        "consultant"
    ],
    "wof:name":"Flight Centre",
    "wof:placetype":"venue"
},
  "geometry": {"coordinates":[144.32485961899999,-38.1713790894],"type":"Point"}
}