{
  "type": "Feature",
  "properties": {
    "iso:country":"AU",
    "sg:address":"Reinbott Rd",
    "sg:city":"Kenilworth",
    "sg:classifiers":[
        {
            "category":"Farming",
            "subcategory":"Livestock Farm",
            "type":"Manufacturing & Wholesale Goods"
        }
    ],
    "sg:phone":"+61 7 5446 0160",
    "sg:postcode":"4574",
    "sg:province":"QLD",
    "sg:tags":[
        "agistment"
    ],
    "wof:name":"Craiglea Thoroughbred Spelling",
    "wof:placetype":"venue"
},
  "geometry": {"coordinates":[152.72747799999999,-26.59549],"type":"Point"}
}