{
  "type": "Feature",
  "properties": {
    "addr:full":"P.O Box 493 Sandgate QLD 4017 Sandgate QLD 4017",
    "addr:postcode":"4017;4017",
    "iso:country":"AU",
    "sg:address":"P.O Box 493 Sandgate QLD 4017",
    "sg:city":"Sandgate",
    "sg:classifiers":[
        {
            "category":"Building & Trades",
            "subcategory":"Construction",
            "type":"Services"
        }
    ],
    "sg:phone":"+61 7 3269 2945",
    "sg:postcode":"4017",
    "sg:province":"QLD",
    "sg:tags":[
        "repairing",
        "window"
    ],
    "wof:name":"Abode Windows Pty/Ltd",
    "wof:placetype":"venue"
},
  "geometry": {"coordinates":[153.059494019,-27.33618927],"type":"Point"}
}