{
  "type": "Feature",
  "properties": {
    "addr:full":"375 Stirling St Perth WA 6000",
    "addr:housenumber":"375",
    "addr:postcode":"6000",
    "addr:street":"Stirling St",
    "iso:country":"AU",
    "sg:address":"375 Stirling St",
    "sg:city":"Perth",
    "sg:classifiers":[
        {
            "category":"Education",
            "subcategory":"Special Training",
            "type":"Public Place"
        }
    ],
    "sg:phone":"+61 8 9227 9888",
    "sg:postcode":"6000",
    "sg:province":"WA",
    "sg:tags":[
        "tuition-educational"
    ],
    "wof:name":"St. Mark's International College",
    "wof:placetype":"venue"
},
  "geometry": {"coordinates":[115.871200562,-31.9383106232],"type":"Point"}
}