{
  "type": "Feature",
  "properties": {
    "iso:country":"AU",
    "sg:address":"2 Ballow Rd",
    "sg:city":"Dunwich",
    "sg:classifiers":[
        {
            "category":"Food & Beverages",
            "subcategory":"Fruits & Vegetables",
            "type":"Retail Goods"
        }
    ],
    "sg:phone":"+61 7 3409 9026",
    "sg:postcode":"4183",
    "sg:province":"QLD",
    "sg:tags":[
        "consultant",
        "catering"
    ],
    "wof:name":"Sharks Tooth Kitchen",
    "wof:placetype":"venue"
},
  "geometry": {"coordinates":[153.40296935999999,-27.5000839233],"type":"Point"}
}