{
  "type": "Feature",
  "properties": {
    "iso:country":"AU",
    "sg:address":"17 Bren Cl",
    "sg:city":"St Clair",
    "sg:classifiers":[
        {
            "category":"Professional",
            "subcategory":"Art Services",
            "type":"Services"
        }
    ],
    "sg:phone":"+61 1300 789 458",
    "sg:postcode":"2759",
    "sg:province":"NSW",
    "sg:tags":[
        "decorator",
        "painter"
    ],
    "sg:website":"http://www.improvements.net.au",
    "wof:name":"A & I Improvements Pty Ltd",
    "wof:placetype":"venue"
},
  "geometry": {"coordinates":[150.77980041500001,-33.7973594666],"type":"Point"}
}