{
  "type": "Feature",
  "properties": {
    "addr:full":"27 Normac Rd Girraween NSW 2145",
    "addr:housenumber":"27",
    "addr:postcode":"2145",
    "addr:street":"Normac Rd",
    "iso:country":"AU",
    "sg:address":"27 Normac Rd",
    "sg:city":"Girraween",
    "sg:classifiers":[
        {
            "category":"Building & Trades",
            "subcategory":"Construction",
            "type":"Services"
        }
    ],
    "sg:phone":"+61 2 9863 3883",
    "sg:postcode":"2145",
    "sg:province":"NSW",
    "sg:tags":[
        "waterproofing",
        "contractor"
    ],
    "wof:name":"Impact Waterproofing",
    "wof:placetype":"venue"
},
  "geometry": {"coordinates":[150.945480347,-33.7979888916],"type":"Point"}
}