{
  "type": "Feature",
  "properties": {
    "addr:full":"15 Creswell St Newstead QLD 4006",
    "addr:housenumber":"15",
    "addr:postcode":"4006",
    "addr:street":"Creswell St",
    "iso:country":"AU",
    "sg:address":"15 Creswell St",
    "sg:city":"Newstead",
    "sg:classifiers":[
        {
            "category":"Education",
            "subcategory":"School",
            "type":"Public Place"
        }
    ],
    "sg:phone":"+61 7 3252 5817",
    "sg:postcode":"4006",
    "sg:province":"QLD",
    "sg:tags":[
        "supply"
    ],
    "wof:name":"A Scott & Co (Wsale) Pty Ltd",
    "wof:placetype":"venue"
},
  "geometry": {"coordinates":[153.04312133799999,-27.4473743439],"type":"Point"}
}