{
  "type": "Feature",
  "properties": {
    "addr:full":"42 Barnes St Tamworth NSW 2340",
    "addr:housenumber":"42",
    "addr:postcode":"2340",
    "addr:street":"Barnes St",
    "iso:country":"AU",
    "sg:address":"42 Barnes St",
    "sg:city":"Tamworth",
    "sg:classifiers":[
        {
            "category":"Retail",
            "subcategory":"Repair Shop",
            "type":"Services"
        }
    ],
    "sg:phone":"+61 2 6761 3374",
    "sg:postcode":"2340",
    "sg:province":"NSW",
    "sg:tags":[
        "handbag"
    ],
    "wof:name":"Cee Bee Souvenirs",
    "wof:placetype":"venue"
},
  "geometry": {"coordinates":[150.91270446799999,-31.0911483765],"type":"Point"}
}