{
  "type": "Feature",
  "properties": {
    "addr:full":"Impey St Murchison VIC 3610",
    "addr:postcode":"3610",
    "addr:street":"St",
    "iso:country":"AU",
    "sg:address":"Impey St",
    "sg:city":"Murchison",
    "sg:classifiers":[
        {
            "category":"Farming",
            "subcategory":"Farm",
            "type":"Manufacturing & Wholesale Goods"
        }
    ],
    "sg:phone":"+61 3 5826 2460",
    "sg:postcode":"3610",
    "sg:province":"VIC",
    "sg:tags":[
        "farmer"
    ],
    "wof:name":"Deane M",
    "wof:placetype":"venue"
},
  "geometry": {"coordinates":[145.21302795400001,-36.6196937561],"type":"Point"}
}