{
  "type": "Feature",
  "properties": {
    "iso:country":"AU",
    "sg:address":"8a Oaks Ave",
    "sg:city":"Dee Why",
    "sg:classifiers":[
        {
            "category":"Health Services",
            "subcategory":"Health Practitioner",
            "type":"Services"
        }
    ],
    "sg:phone":"+61 2 9972 1024",
    "sg:postcode":"2099",
    "sg:province":"NSW",
    "sg:tags":[
        "naturopath"
    ],
    "wof:name":"Twindley Ernie",
    "wof:placetype":"venue"
},
  "geometry": {"coordinates":[151.286453247,-33.7534370422],"type":"Point"}
}