{
  "type": "Feature",
  "properties": {
    "addr:full":"Wyndham Village Medical Centre 380 Sayers Rd Tarneit VIC 3029",
    "addr:housenumber":"380",
    "addr:postcode":"3029",
    "addr:street":"Sayers Rd",
    "iso:country":"AU",
    "sg:address":"Wyndham Village Medical Centre 380 Sayers Rd",
    "sg:city":"Tarneit",
    "sg:classifiers":[
        {
            "category":"Health Services",
            "subcategory":"Health Practitioner",
            "type":"Services"
        }
    ],
    "sg:phone":"+61 427 418 470",
    "sg:postcode":"3029",
    "sg:province":"VIC",
    "sg:tags":[
        "psychologist"
    ],
    "wof:name":"Diana Whale",
    "wof:placetype":"venue"
},
  "geometry": {"coordinates":[144.70631399999999,-37.850231],"type":"Point"}
}