{
  "type": "Feature",
  "properties": {
    "iso:country":"AU",
    "sg:address":"Cnr Balcatta & Erindale Rds",
    "sg:city":"Balcatta",
    "sg:classifiers":[
        {
            "category":"Manufacturing",
            "subcategory":"Tools & Machinery",
            "type":"Manufacturing & Wholesale Goods"
        }
    ],
    "sg:phone":"+61 8 9345 3460",
    "sg:postcode":"6021",
    "sg:province":"WA",
    "sg:tags":[
        "earth",
        "excavating",
        "moving",
        "equipment"
    ],
    "wof:name":"Kennards Earthmoving Equipment Hire",
    "wof:placetype":"venue"
},
  "geometry": {"coordinates":[115.827850342,-31.8637199402],"type":"Point"}
}