{
  "type": "Feature",
  "properties": {
    "addr:full":"195 Calulu Rd Bairnsdale VIC 3875",
    "addr:housenumber":"195",
    "addr:postcode":"3875",
    "addr:street":"Calulu Rd",
    "iso:country":"AU",
    "sg:address":"195 Calulu Rd",
    "sg:city":"Bairnsdale",
    "sg:classifiers":[
        {
            "category":"Building & Trades",
            "subcategory":"Construction",
            "type":"Services"
        }
    ],
    "sg:phone":"+61 3 5156 9373",
    "sg:postcode":"3875",
    "sg:province":"VIC",
    "sg:tags":[
        "contractor"
    ],
    "wof:name":"Zagami J M & S M",
    "wof:placetype":"venue"
},
  "geometry": {"coordinates":[147.61129760700001,-37.8314208984],"type":"Point"}
}