{
  "type": "Feature",
  "properties": {
    "addr:full":"Suite 101 Bnkstwn Hosp Med Cntr Cnr Eldridge & Gallipolli S Bankstown NSW 2200",
    "addr:postcode":"2200",
    "iso:country":"AU",
    "sg:address":"Suite 101 Bnkstwn Hosp Med Cntr Cnr Eldridge & Gallipolli S",
    "sg:city":"Bankstown",
    "sg:classifiers":[
        {
            "category":"Health Services",
            "subcategory":"Doctor",
            "type":"Services"
        }
    ],
    "sg:phone":"+61 2 9793 2170",
    "sg:postcode":"2200",
    "sg:province":"NSW",
    "sg:tags":[
        "medical",
        "practitioner"
    ],
    "wof:name":"Merrett N, PROF.",
    "wof:placetype":"venue"
},
  "geometry": {"coordinates":[151.00895700000001,-33.930393],"type":"Point"}
}