{
  "type": "Feature",
  "properties": {
    "addr:full":"1185 Stoneville Rd Mundaring WA 6073",
    "addr:postcode":"1185;6073",
    "addr:street":"Stoneville Rd",
    "iso:country":"AU",
    "sg:address":"1185 Stoneville Rd",
    "sg:city":"Mundaring",
    "sg:classifiers":[
        {
            "category":"Manufacturing",
            "subcategory":"Tools & Machinery",
            "type":"Manufacturing & Wholesale Goods"
        }
    ],
    "sg:phone":"+61 408 953 676",
    "sg:postcode":"6073",
    "sg:province":"WA",
    "sg:tags":[
        "earth",
        "excavating",
        "moving",
        "equipment"
    ],
    "wof:name":"Wallabys Earthmoving & Bobcat Hire",
    "wof:placetype":"venue"
},
  "geometry": {"coordinates":[116.168212891,-31.9016399384],"type":"Point"}
}