{
  "type": "Feature",
  "properties": {
    "iso:country":"AU",
    "sg:address":"60 Moores Rd",
    "sg:city":"Clyde",
    "sg:classifiers":[
        {
            "category":"Food & Beverages",
            "subcategory":"Fruits & Vegetables",
            "type":"Retail Goods"
        }
    ],
    "sg:phone":"+61 3 5998 5228",
    "sg:postcode":"3978",
    "sg:province":"VIC",
    "sg:tags":[
        "grower"
    ],
    "wof:name":"Schreurs L & T",
    "wof:placetype":"venue"
},
  "geometry": {"coordinates":[145.32667541500001,-38.148273468],"type":"Point"}
}