{
  "type": "Feature",
  "properties": {
    "addr:full":"20 Blackwood Pl Oatlands NSW 2117",
    "addr:housenumber":"20",
    "addr:postcode":"2117",
    "addr:street":"Blackwood Pl",
    "iso:country":"AU",
    "sg:address":"20 Blackwood Pl",
    "sg:city":"Oatlands",
    "sg:classifiers":[
        {
            "category":"Professional",
            "subcategory":"Computer Services",
            "type":"Services"
        }
    ],
    "sg:phone":"+61 2 9890 2339",
    "sg:postcode":"2117",
    "sg:province":"NSW",
    "sg:tags":[
        "package",
        "software"
    ],
    "wof:name":"Alchemex Pty Ltd",
    "wof:placetype":"venue"
},
  "geometry": {"coordinates":[151.01654052699999,-33.7955856323],"type":"Point"}
}