{
  "type": "Feature",
  "properties": {
    "addr:full":"14 Chalet Rd Kellyville NSW 2155",
    "addr:housenumber":"14",
    "addr:postcode":"2155",
    "addr:street":"Chalet Rd",
    "iso:country":"AU",
    "sg:address":"14 Chalet Rd",
    "sg:city":"Kellyville",
    "sg:classifiers":[
        {
            "category":"Personal",
            "subcategory":"Nail Salon",
            "type":"Services"
        }
    ],
    "sg:phone":"+61 2 9836 2755",
    "sg:postcode":"2155",
    "sg:province":"NSW",
    "sg:tags":[
        "artificial"
    ],
    "wof:name":"Nail Shack at Kellyville The",
    "wof:placetype":"venue"
},
  "geometry": {"coordinates":[150.95803832999999,-33.7094688416],"type":"Point"}
}