{
  "type": "Feature",
  "properties": {
    "addr:full":"19 Murrawal Rd Wyongah NSW 2259",
    "addr:housenumber":"19",
    "addr:postcode":"2259",
    "addr:street":"Murrawal Rd",
    "iso:country":"AU",
    "sg:address":"19 Murrawal Rd",
    "sg:city":"Wyongah",
    "sg:classifiers":[
        {
            "category":"Building & Trades",
            "subcategory":"Plumbing",
            "type":"Services"
        }
    ],
    "sg:phone":"+61 2 4392 0444",
    "sg:postcode":"2259",
    "sg:province":"NSW",
    "sg:tags":[
        "plumber",
        "gasfitters"
    ],
    "wof:name":"Central Coast Backflow Specialists.",
    "wof:placetype":"venue"
},
  "geometry": {"coordinates":[151.48576355,-33.2740364075],"type":"Point"}
}