{
  "type": "Feature",
  "properties": {
    "iso:country":"AU",
    "sg:address":"45 Kethel Rd",
    "sg:city":"Cheltenham",
    "sg:classifiers":[
        {
            "category":"Professional",
            "subcategory":"Computer Services",
            "type":"Services"
        }
    ],
    "sg:phone":"+61 2 9481 7478",
    "sg:postcode":"2119",
    "sg:province":"NSW",
    "sg:tags":[
        "repairs",
        "upgrade",
        "equipment"
    ],
    "wof:name":"NDN Technology",
    "wof:placetype":"venue"
},
  "geometry": {"coordinates":[151.077362061,-33.7512550354],"type":"Point"}
}