{
  "type": "Feature",
  "properties": {
    "addr:full":"161 Bayswater Rd Hyde Park QLD 4812",
    "addr:housenumber":"161",
    "addr:postcode":"4812",
    "addr:street":"Bayswater Rd",
    "iso:country":"AU",
    "sg:address":"161 Bayswater Rd",
    "sg:city":"Hyde Park",
    "sg:classifiers":[
        {
            "category":"Retail",
            "subcategory":"Storage",
            "type":"Services"
        }
    ],
    "sg:phone":"+61 7 4728 8400",
    "sg:postcode":"4812",
    "sg:province":"QLD",
    "wof:name":"Hyde Park Self Storage",
    "wof:placetype":"venue"
},
  "geometry": {"coordinates":[146.78050200000001,-19.275223],"type":"Point"}
}