{
  "type": "Feature",
  "properties": {
    "iso:country":"AU",
    "sg:address":"24 Anglesen St",
    "sg:city":"Bondi",
    "sg:classifiers":[
        {
            "category":"Professional",
            "subcategory":"Art Services",
            "type":"Services"
        }
    ],
    "sg:phone":"+61 2 9386 9830",
    "sg:postcode":"2026",
    "sg:province":"NSW",
    "sg:tags":[
        "graphic",
        "designer"
    ],
    "wof:name":"Hey D Design Pty Ltd",
    "wof:placetype":"venue"
},
  "geometry": {"coordinates":[151.260498047,-33.890750885],"type":"Point"}
}