{
  "type": "Feature",
  "properties": {
    "iso:country":"AU",
    "sg:address":"106 New Town Rd",
    "sg:city":"New Town",
    "sg:classifiers":[
        {
            "category":"Professional",
            "subcategory":"Computer Services",
            "type":"Services"
        }
    ],
    "sg:phone":"+61 3 6228 1400",
    "sg:postcode":"7008",
    "sg:province":"TAS",
    "sg:tags":[
        "consultant",
        "system"
    ],
    "wof:name":"FACIT IT Solutions",
    "wof:placetype":"venue"
},
  "geometry": {"coordinates":[147.309326172,-42.8614349365],"type":"Point"}
}