{
  "type": "Feature",
  "properties": {
    "addr:full":"Lvl 1, Suite 2, 8 Edgeworth David Av Hornsby NSW 2077",
    "addr:housenumber":"8",
    "addr:postcode":"2077",
    "addr:street":"Edgeworth David Av",
    "iso:country":"AU",
    "sg:address":"Lvl 1, Suite 2, 8 Edgeworth David Av",
    "sg:city":"Hornsby",
    "sg:classifiers":[
        {
            "category":"Banks & Credit Unions",
            "subcategory":"Financial Services",
            "type":"Services"
        }
    ],
    "sg:phone":"+61 2 9482 8333",
    "sg:postcode":"2077",
    "sg:province":"NSW",
    "sg:tags":[
        "financier"
    ],
    "wof:name":"The Small Loan Company",
    "wof:placetype":"venue"
},
  "geometry": {"coordinates":[151.10466003400001,-33.7062644958],"type":"Point"}
}