{
  "type": "Feature",
  "properties": {
    "iso:country":"AU",
    "sg:address":"Ste 10/ 246 Dorset Rd",
    "sg:city":"Boronia",
    "sg:classifiers":[
        {
            "category":"Health Services",
            "subcategory":"Health Practitioner",
            "type":"Services"
        }
    ],
    "sg:phone":"+61 3 9762 6093",
    "sg:postcode":"3155",
    "sg:province":"VIC",
    "sg:tags":[
        "naturopath"
    ],
    "wof:name":"Gozlan Christine-Essential Health",
    "wof:placetype":"venue"
},
  "geometry": {"coordinates":[145.285888672,-37.8606567383],"type":"Point"}
}