{
  "type": "Feature",
  "properties": {
    "addr:full":"Level 1/ 213 Commercial Rd Morwell VIC 3840",
    "addr:housenumber":"/ 213",
    "addr:postcode":"3840",
    "addr:street":"Commercial Rd",
    "iso:country":"AU",
    "sg:address":"Level 1/ 213 Commercial Rd",
    "sg:city":"Morwell",
    "sg:classifiers":[
        {
            "category":"Professional",
            "subcategory":"Computer Services",
            "type":"Services"
        }
    ],
    "sg:phone":"+61 3 5133 0274",
    "sg:postcode":"3840",
    "sg:province":"VIC",
    "sg:tags":[
        "consultant",
        "system"
    ],
    "wof:name":"DataCommand Pty Ltd",
    "wof:placetype":"venue"
},
  "geometry": {"coordinates":[146.39744567899999,-38.2371711731],"type":"Point"}
}