{
  "type": "Feature",
  "properties": {
    "addr:full":"4 Villiers St Bassendean WA 6054",
    "addr:housenumber":"4",
    "addr:postcode":"6054",
    "addr:street":"Villiers St",
    "iso:country":"AU",
    "sg:address":"4 Villiers St",
    "sg:city":"Bassendean",
    "sg:classifiers":[
        {
            "category":"Professional",
            "subcategory":"Management & Consulting",
            "type":"Services"
        }
    ],
    "sg:phone":"+61 1300 553 351",
    "sg:postcode":"6054",
    "sg:province":"WA",
    "sg:tags":[
        "consultant"
    ],
    "wof:name":"Full Circle Feedback",
    "wof:placetype":"venue"
},
  "geometry": {"coordinates":[115.952423096,-31.9190673828],"type":"Point"}
}