{
  "type": "Feature",
  "properties": {
    "addr:full":"239 Collier Rd Bayswater WA 6053",
    "addr:housenumber":"239",
    "addr:postcode":"6053",
    "addr:street":"Collier Rd",
    "iso:country":"AU",
    "sg:address":"239 Collier Rd",
    "sg:city":"Bayswater",
    "sg:classifiers":[
        {
            "category":"Conference Center",
            "type":"Public Place"
        }
    ],
    "sg:phone":"+61 8 9271 8455",
    "sg:postcode":"6053",
    "sg:province":"WA",
    "sg:tags":[
        "dryer",
        "electric",
        "hand"
    ],
    "wof:name":"J D MACDONALD",
    "wof:placetype":"venue"
},
  "geometry": {"coordinates":[115.91680145300001,-31.9043178558],"type":"Point"}
}