{
  "type": "Feature",
  "properties": {
    "addr:full":"Lot 3 Sandy Creek Rd Maffra VIC 3860",
    "addr:postcode":"3860",
    "addr:street":"Sandy Creek Rd",
    "iso:country":"AU",
    "sg:address":"Lot 3 Sandy Creek Rd",
    "sg:city":"Maffra",
    "sg:classifiers":[
        {
            "category":"Home & Garden",
            "subcategory":"Hardware",
            "type":"Retail Goods"
        }
    ],
    "sg:phone":"+61 3 5141 1800",
    "sg:postcode":"3860",
    "sg:province":"VIC",
    "sg:tags":[
        "repair",
        "tool",
        "power"
    ],
    "wof:name":"Vicquip Sales & Service",
    "wof:placetype":"venue"
},
  "geometry": {"coordinates":[146.98916625999999,-37.9427146912],"type":"Point"}
}