{
  "type": "Feature",
  "properties": {
    "addr:full":"8 Whiters St Lakes Entrance VIC 3909",
    "addr:housenumber":"8",
    "addr:postcode":"3909",
    "addr:street":"Whiters St",
    "iso:country":"AU",
    "sg:address":"8 Whiters St",
    "sg:city":"Lakes Entrance",
    "sg:classifiers":[
        {
            "category":"Health Services",
            "subcategory":"Doctor",
            "type":"Services"
        }
    ],
    "sg:phone":"+61 3 5155 2300",
    "sg:postcode":"3909",
    "sg:province":"VIC",
    "sg:tags":[
        "medical",
        "practitioner"
    ],
    "wof:name":"Broom Ian",
    "wof:placetype":"venue"
},
  "geometry": {"coordinates":[148.00001525900001,-37.8759269714],"type":"Point"}
}