{
  "type": "Feature",
  "properties": {
    "addr:full":"49 Carribean Ave Forster NSW 2428",
    "addr:housenumber":"49",
    "addr:postcode":"2428",
    "addr:street":"Carribean Ave",
    "iso:country":"AU",
    "sg:address":"49 Carribean Ave",
    "sg:city":"Forster",
    "sg:classifiers":[
        {
            "category":"Professional",
            "subcategory":"Art Services",
            "type":"Services"
        }
    ],
    "sg:phone":"+61 2 6555 7749",
    "sg:postcode":"2428",
    "sg:province":"NSW",
    "sg:tags":[
        "decorator",
        "painter"
    ],
    "wof:name":"Ken Morgan Painting Services",
    "wof:placetype":"venue"
},
  "geometry": {"coordinates":[152.52870200000001,-32.218262],"type":"Point"}
}