{
  "type": "Feature",
  "properties": {
    "iso:country":"AU",
    "sg:address":"3 Folkestone Crt",
    "sg:city":"Wellington Point",
    "sg:classifiers":[
        {
            "category":"Government",
            "subcategory":"Court House",
            "type":"Public Place"
        }
    ],
    "sg:phone":"+61 414 778 476",
    "sg:postcode":"4160",
    "sg:province":"QLD",
    "sg:tags":[
        "personal",
        "marriage",
        "family",
        "counselling"
    ],
    "wof:name":"Zoe Slater Counselling",
    "wof:placetype":"venue"
},
  "geometry": {"coordinates":[153.23794555699999,-27.5156517029],"type":"Point"}
}