{
  "type": "Feature",
  "properties": {
    "iso:country":"AU",
    "sg:address":"559 Logan Rd",
    "sg:city":"Greenslopes",
    "sg:classifiers":[
        {
            "category":"Education",
            "subcategory":"School",
            "type":"Public Place"
        }
    ],
    "sg:phone":"+61 7 3397 2200",
    "sg:postcode":"4120",
    "sg:province":"QLD",
    "sg:tags":[
        "state",
        "except",
        "nsw"
    ],
    "wof:name":"Greenslopes Primary",
    "wof:placetype":"venue"
},
  "geometry": {"coordinates":[153.049758911,-27.5066623688],"type":"Point"}
}