{
  "type": "Feature",
  "properties": {
    "iso:country":"AU",
    "sg:address":"Suite 1, 55 Talavera Rd",
    "sg:city":"North Ryde",
    "sg:classifiers":[
        {
            "category":"Utilities",
            "subcategory":"Electric",
            "type":"Services"
        }
    ],
    "sg:phone":"+61 1300 134 844",
    "sg:postcode":"2113",
    "sg:province":"NSW",
    "sg:tags":[
        "electrical",
        "contractor"
    ],
    "wof:name":"Allied Technologies",
    "wof:placetype":"venue"
},
  "geometry": {"coordinates":[151.12411499000001,-33.7773475647],"type":"Point"}
}