{
  "type": "Feature",
  "properties": {
    "iso:country":"AU",
    "sg:address":"13 Old Coach Rd",
    "sg:city":"Aldinga",
    "sg:classifiers":[
        {
            "category":"Deli",
            "type":"Food & Drink"
        }
    ],
    "sg:phone":"+61 8 8556 5043",
    "sg:postcode":"5173",
    "sg:province":"SA",
    "sg:tags":[
        "delicatessen"
    ],
    "wof:name":"Aldinga General Store",
    "wof:placetype":"venue"
},
  "geometry": {"coordinates":[138.48310852,-35.2667922974],"type":"Point"}
}