{
  "type": "Feature",
  "properties": {
    "addr:full":"21 Resevoir Rd Glendale NSW 2285",
    "addr:housenumber":"21",
    "addr:postcode":"2285",
    "addr:street":"Resevoir Rd",
    "iso:country":"AU",
    "sg:address":"21 Resevoir Rd",
    "sg:city":"Glendale",
    "sg:classifiers":[
        {
            "category":"Organizations",
            "subcategory":"Professional Association",
            "type":"Services"
        }
    ],
    "sg:phone":"+61 2 4954 8912",
    "sg:postcode":"2285",
    "sg:province":"NSW",
    "sg:tags":[
        "web",
        "internet"
    ],
    "wof:name":"Apana Incorporated t/a Hunter Apana",
    "wof:placetype":"venue"
},
  "geometry": {"coordinates":[151.654495239,-32.9245071411],"type":"Point"}
}