{
  "type": "Feature",
  "properties": {
    "addr:full":"194 Westridge Rd Penguin TAS 7316",
    "addr:housenumber":"194",
    "addr:postcode":"7316",
    "addr:street":"Westridge Rd",
    "iso:country":"AU",
    "sg:address":"194 Westridge Rd",
    "sg:city":"Penguin",
    "sg:classifiers":[
        {
            "category":"Manufacturing",
            "subcategory":"Lumber",
            "type":"Manufacturing & Wholesale Goods"
        }
    ],
    "sg:phone":"+61 407 371 837",
    "sg:postcode":"7316",
    "sg:province":"TAS",
    "sg:tags":[
        "sawmillers"
    ],
    "wof:name":"Lisk Steve",
    "wof:placetype":"venue"
},
  "geometry": {"coordinates":[146.06695556599999,-41.1111183167],"type":"Point"}
}