{
  "type": "Feature",
  "properties": {
    "iso:country":"AU",
    "sg:address":"288 Queen St",
    "sg:city":"Campbelltown",
    "sg:classifiers":[
        {
            "category":"Health Services",
            "subcategory":"Health Practitioner",
            "type":"Services"
        }
    ],
    "sg:phone":"+61 2 4627 2792",
    "sg:postcode":"2560",
    "sg:province":"NSW",
    "sg:tags":[
        "naturopath"
    ],
    "wof:name":"Benevolent Society Centre For Women's Health",
    "wof:placetype":"venue"
},
  "geometry": {"coordinates":[150.81192016599999,-34.069519043],"type":"Point"}
}