{
  "type": "Feature",
  "properties": {
    "addr:full":"3/ 179 Currumburra Rd Ashmore QLD 4214",
    "addr:housenumber":"/ 179",
    "addr:postcode":"4214",
    "addr:street":"Currumburra Rd",
    "iso:country":"AU",
    "sg:address":"3/ 179 Currumburra Rd",
    "sg:city":"Ashmore",
    "sg:classifiers":[
        {
            "category":"Home & Garden",
            "subcategory":"Furniture",
            "type":"Retail Goods"
        }
    ],
    "sg:phone":"+61 7 5597 1718",
    "sg:postcode":"4214",
    "sg:province":"QLD",
    "sg:tags":[
        "repair",
        "restoration"
    ],
    "wof:name":"The Gloss Works",
    "wof:placetype":"venue"
},
  "geometry": {"coordinates":[153.38211059599999,-27.9794311523],"type":"Point"}
}