{
  "type": "Feature",
  "properties": {
    "addr:full":"19 Surfside Ave Clovelly NSW 2031",
    "addr:housenumber":"19",
    "addr:postcode":"2031",
    "addr:street":"Surfside Ave",
    "iso:country":"AU",
    "sg:address":"19 Surfside Ave",
    "sg:city":"Clovelly",
    "sg:classifiers":[
        {
            "category":"Building & Trades",
            "subcategory":"Landscaping Services",
            "type":"Services"
        }
    ],
    "sg:phone":"+61 2 9665 1036",
    "sg:postcode":"2031",
    "sg:province":"NSW",
    "sg:tags":[
        "architect",
        "landscape"
    ],
    "wof:name":"Barbara Schaffer Landscape Architect",
    "wof:placetype":"venue"
},
  "geometry": {"coordinates":[151.26531982399999,-33.9120750427],"type":"Point"}
}