{
  "type": "Feature",
  "properties": {
    "addr:full":"5 Maycock Pl Orelia WA 6167",
    "addr:housenumber":"5",
    "addr:postcode":"6167",
    "addr:street":"Maycock Pl Orelia",
    "iso:country":"AU",
    "sg:address":"5 Maycock Pl",
    "sg:city":"Orelia",
    "sg:classifiers":[
        {
            "category":"Professional",
            "subcategory":"Accounting & Tax Preparation",
            "type":"Services"
        }
    ],
    "sg:phone":"+61 8 9368 5428",
    "sg:postcode":"6167",
    "sg:province":"WA",
    "sg:tags":[
        "accountant",
        "auditor"
    ],
    "wof:name":"Mobile Business Services",
    "wof:placetype":"venue"
},
  "geometry": {"coordinates":[115.823669,-32.239235],"type":"Point"}
}