{
  "type": "Feature",
  "properties": {
    "addr:full":"77 Poinciana Ave Tewantin QLD 4565",
    "addr:housenumber":"77",
    "addr:postcode":"4565",
    "addr:street":"Poinciana Ave",
    "iso:country":"AU",
    "sg:address":"77 Poinciana Ave",
    "sg:city":"Tewantin",
    "sg:classifiers":[
        {
            "category":"Building & Trades",
            "subcategory":"Construction",
            "type":"Services"
        }
    ],
    "sg:phone":"+61 401 842 986",
    "sg:postcode":"4565",
    "sg:province":"QLD",
    "sg:tags":[
        "fencing",
        "contractor"
    ],
    "wof:name":"damm fine fencing",
    "wof:placetype":"venue"
},
  "geometry": {"coordinates":[153.035644531,-26.3914928436],"type":"Point"}
}