{
  "type": "Feature",
  "properties": {
    "addr:full":"5 Maroni Pl St Clair NSW 2759",
    "addr:housenumber":"5",
    "addr:postcode":"2759",
    "addr:street":"Maroni Pl St",
    "iso:country":"AU",
    "sg:address":"5 Maroni Pl",
    "sg:city":"St Clair",
    "sg:classifiers":[
        {
            "category":"Retail",
            "subcategory":"Repair Shop",
            "type":"Services"
        }
    ],
    "sg:phone":"+61 418 618 817",
    "sg:postcode":"2759",
    "sg:province":"NSW",
    "sg:tags":[
        "machine",
        "sewing"
    ],
    "wof:name":"A & D Sewing Machine Service",
    "wof:placetype":"venue"
},
  "geometry": {"coordinates":[150.76968383799999,-33.8002967834],"type":"Point"}
}