{
  "type": "Feature",
  "properties": {
    "iso:country":"AU",
    "sg:address":"350 Dowling St",
    "sg:city":"Wendouree",
    "sg:classifiers":[
        {
            "category":"Wholesale",
            "subcategory":"Metals & Minerals",
            "type":"Manufacturing & Wholesale Goods"
        }
    ],
    "sg:phone":"+61 3 5339 6555",
    "sg:postcode":"3355",
    "sg:province":"VIC",
    "sg:tags":[
        "steel",
        "stainless",
        "product",
        "equipment"
    ],
    "wof:name":"Greg Harris Sheet Metal",
    "wof:placetype":"venue"
},
  "geometry": {"coordinates":[143.84231600000001,-37.529881],"type":"Point"}
}