{
  "type": "Feature",
  "properties": {
    "addr:full":"14 Constitution Rd Ryde NSW 2112",
    "addr:housenumber":"14",
    "addr:postcode":"2112",
    "addr:street":"Constitution Rd",
    "iso:country":"AU",
    "sg:address":"14 Constitution Rd",
    "sg:city":"Ryde",
    "sg:classifiers":[
        {
            "category":"Professional",
            "type":"Services"
        }
    ],
    "sg:phone":"+61 1300 736 972",
    "sg:postcode":"2112",
    "sg:province":"NSW",
    "sg:tags":[
        "transport"
    ],
    "wof:name":"Universal Express Australia Pty Ltd",
    "wof:placetype":"venue"
},
  "geometry": {"coordinates":[151.095535278,-33.8187026978],"type":"Point"}
}