{
  "type": "Feature",
  "properties": {
    "iso:country":"AU",
    "sg:address":"3/ 219 Broome St",
    "sg:city":"Cottesloe",
    "sg:classifiers":[
        {
            "category":"Professional",
            "subcategory":"Accounting & Tax Preparation",
            "type":"Services"
        }
    ],
    "sg:phone":"+61 8 9384 8199",
    "sg:postcode":"6011",
    "sg:province":"WA",
    "sg:tags":[
        "accountant",
        "auditor"
    ],
    "wof:name":"Mercury Business Solutions",
    "wof:placetype":"venue"
},
  "geometry": {"coordinates":[115.75601196300001,-31.9841365814],"type":"Point"}
}