{
  "type": "Feature",
  "properties": {
    "iso:country":"AU",
    "sg:address":"27 Aruma Pl",
    "sg:city":"Cardiff",
    "sg:classifiers":[
        {
            "category":"Commercial Area",
            "type":"Public Place"
        }
    ],
    "sg:phone":"+61 2 4956 5690",
    "sg:postcode":"2285",
    "sg:province":"NSW",
    "sg:tags":[
        "heavy",
        "carrier"
    ],
    "wof:name":"Kbt Overnight Express Pty Ltd",
    "wof:placetype":"venue"
},
  "geometry": {"coordinates":[151.639602661,-32.9401893616],"type":"Point"}
}