{
  "type": "Feature",
  "properties": {
    "addr:full":"17 Colebrook Ave Moorooka QLD 4105",
    "addr:housenumber":"17",
    "addr:postcode":"4105",
    "addr:street":"Colebrook Ave",
    "iso:country":"AU",
    "sg:address":"17 Colebrook Ave",
    "sg:city":"Moorooka",
    "sg:classifiers":[
        {
            "category":"Retail",
            "subcategory":"Auto Repair",
            "type":"Services"
        }
    ],
    "sg:phone":"+61 7 3892 5568",
    "sg:postcode":"4105",
    "sg:province":"QLD",
    "sg:tags":[
        "electrical"
    ],
    "wof:name":"Toppin Auto Electrical",
    "wof:placetype":"venue"
},
  "geometry": {"coordinates":[153.02206420900001,-27.5271167755],"type":"Point"}
}