{
  "type": "Feature",
  "properties": {
    "iso:country":"AU",
    "sg:address":"326 Macquarie St",
    "sg:city":"Hobart",
    "sg:classifiers":[
        {
            "category":"Real Estate",
            "subcategory":"Real Estate Agent",
            "type":"Services"
        }
    ],
    "sg:phone":"+61 3 6224 3622",
    "sg:postcode":"7000",
    "sg:province":"TAS",
    "wof:name":"Macquarie Real Estate",
    "wof:placetype":"venue"
},
  "geometry": {"coordinates":[147.317825317,-42.8921928406],"type":"Point"}
}