{
  "type": "Feature",
  "properties": {
    "addr:full":"93 Anderson Rd Fawkner VIC 3060",
    "addr:housenumber":"93",
    "addr:postcode":"3060",
    "addr:street":"Anderson Rd",
    "iso:country":"AU",
    "sg:address":"93 Anderson Rd",
    "sg:city":"Fawkner",
    "sg:classifiers":[
        {
            "category":"Food & Beverages",
            "subcategory":"Fruits & Vegetables",
            "type":"Retail Goods"
        }
    ],
    "sg:phone":"+61 3 9357 4415",
    "sg:postcode":"3060",
    "sg:province":"VIC",
    "sg:tags":[
        "greengrocer",
        "fruiterer"
    ],
    "wof:name":"Italo Nardone Fruiterer",
    "wof:placetype":"venue"
},
  "geometry": {"coordinates":[144.968353272,-37.6959114075],"type":"Point"}
}