{
  "type": "Feature",
  "properties": {
    "iso:country":"AU",
    "sg:address":"3-5 Bensted St",
    "sg:city":"Gladstone",
    "sg:classifiers":[
        {
            "category":"Professional",
            "subcategory":"Engineering",
            "type":"Services"
        }
    ],
    "sg:phone":"+61 7 4976 7000",
    "sg:postcode":"4680",
    "sg:province":"QLD",
    "sg:tags":[
        "engineer"
    ],
    "wof:name":"Downer EDI Engineering",
    "wof:placetype":"venue"
},
  "geometry": {"coordinates":[151.22596740700001,-23.854467392],"type":"Point"}
}