{
  "type": "Feature",
  "properties": {
    "iso:country":"AU",
    "sg:address":"480 Argent St",
    "sg:city":"Broken Hill",
    "sg:classifiers":[
        {
            "category":"Home & Garden",
            "subcategory":"Household Appliances",
            "type":"Retail Goods"
        }
    ],
    "sg:phone":"+61 8 8088 4422",
    "sg:postcode":"2880",
    "sg:province":"NSW",
    "sg:tags":[
        "equipment",
        "gas"
    ],
    "wof:name":"Reece Plumbing Supplies",
    "wof:placetype":"venue"
},
  "geometry": {"coordinates":[141.47108459500001,-31.9547748566],"type":"Point"}
}