{
  "type": "Feature",
  "properties": {
    "addr:full":"8 Wentworth Ave Surry Hills NSW 2010",
    "addr:housenumber":"8",
    "addr:postcode":"2010",
    "addr:street":"Wentworth Ave",
    "iso:country":"AU",
    "sg:address":"8 Wentworth Ave",
    "sg:city":"Surry Hills",
    "sg:classifiers":[
        {
            "category":"Commercial Area",
            "type":"Public Place"
        }
    ],
    "sg:phone":"+61 2 9261 0022",
    "sg:postcode":"2010",
    "sg:province":"NSW",
    "sg:tags":[
        "bar",
        "domestic"
    ],
    "wof:name":"Greenlight Lounge",
    "wof:placetype":"venue"
},
  "geometry": {"coordinates":[151.21194457999999,-33.87758255],"type":"Point"}
}