{
  "type": "Feature",
  "properties": {
    "iso:country":"AU",
    "sg:address":"Bruce Crt",
    "sg:city":"Humpty Doo",
    "sg:classifiers":[
        {
            "category":"Food & Beverages",
            "subcategory":"Specialty",
            "type":"Retail Goods"
        }
    ],
    "sg:phone":"+61 8 8988 2065",
    "sg:postcode":"0836",
    "sg:province":"NT",
    "sg:tags":[
        "product",
        "health"
    ],
    "wof:name":"Herbalife Independent Distributor",
    "wof:placetype":"venue"
},
  "geometry": {"coordinates":[131.09435999999999,-12.559777],"type":"Point"}
}