{
  "type": "Feature",
  "properties": {
    "addr:full":"49 Campell Pde Bondi NSW 2026",
    "addr:housenumber":"49",
    "addr:postcode":"2026",
    "addr:street":"Campell Pde",
    "iso:country":"AU",
    "sg:address":"49 Campell Pde",
    "sg:city":"Bondi",
    "sg:classifiers":[
        {
            "category":"Food & Beverages",
            "subcategory":"Liquor & Beverages",
            "type":"Retail Goods"
        }
    ],
    "sg:phone":"+61 2 9130 2094",
    "sg:postcode":"2026",
    "sg:province":"NSW",
    "sg:tags":[
        "store"
    ],
    "wof:name":"Ben Buckler Cellars",
    "wof:placetype":"venue"
},
  "geometry": {"coordinates":[151.27284240700001,-33.8934593201],"type":"Point"}
}