{
  "type": "Feature",
  "properties": {
    "iso:country":"AU",
    "sg:address":"154 Caulfield Ave",
    "sg:city":"Clarence Gardens",
    "sg:classifiers":[
        {
            "category":"Farming",
            "subcategory":"Dairy Farm",
            "type":"Manufacturing & Wholesale Goods"
        }
    ],
    "sg:phone":"+61 8 8292 7777",
    "sg:postcode":"5039",
    "sg:province":"SA",
    "sg:tags":[
        "wholesaler",
        "product",
        "mfrs"
    ],
    "wof:name":"Dairy Farmers",
    "wof:placetype":"venue"
},
  "geometry": {"coordinates":[138.57400512699999,-34.9770965576],"type":"Point"}
}