{
  "type": "Feature",
  "properties": {
    "addr:full":"1254 Canterbury Rd Punchbowl NSW 2196",
    "addr:housenumber":"1254",
    "addr:postcode":"2196",
    "addr:street":"Canterbury Rd",
    "iso:country":"AU",
    "sg:address":"1254 Canterbury Rd",
    "sg:city":"Punchbowl",
    "sg:classifiers":[
        {
            "category":"Health Services",
            "subcategory":"Doctor",
            "type":"Services"
        }
    ],
    "sg:phone":"+61 2 9759 6484",
    "sg:postcode":"2196",
    "sg:province":"NSW",
    "sg:tags":[
        "medical",
        "practitioner"
    ],
    "wof:name":"Banerjee Basudeb",
    "wof:placetype":"venue"
},
  "geometry": {"coordinates":[151.06359900000001,-33.931404],"type":"Point"}
}