{
  "type": "Feature",
  "properties": {
    "addr:full":"PO Box 782 Hillarys WA 6923",
    "addr:postcode":"6923",
    "iso:country":"AU",
    "sg:address":"PO Box 782",
    "sg:city":"Hillarys",
    "sg:classifiers":[
        {
            "category":"Building & Trades",
            "subcategory":"Construction",
            "type":"Services"
        }
    ],
    "sg:phone":"+61 407 198 384",
    "sg:postcode":"6923",
    "sg:province":"WA",
    "sg:tags":[
        "installation",
        "air conditioning"
    ],
    "wof:name":"Chilltech Refrigeration",
    "wof:placetype":"venue"
},
  "geometry": {"coordinates":[115.741539002,-31.809419632],"type":"Point"}
}