{
  "type": "Feature",
  "properties": {
    "iso:country":"AU",
    "sg:address":"20 Glenn Ave",
    "sg:city":"Northmead",
    "sg:classifiers":[
        {
            "category":"Retail",
            "subcategory":"Auto Rental",
            "type":"Services"
        }
    ],
    "sg:phone":"+61 402 069 640",
    "sg:postcode":"2152",
    "sg:province":"NSW",
    "sg:tags":[
        "car",
        "wedding"
    ],
    "wof:name":"Kerry's Stretch Limousine Wedding Car Service",
    "wof:placetype":"venue"
},
  "geometry": {"coordinates":[150.990142822,-33.7920036316],"type":"Point"}
}