{
  "type": "Feature",
  "properties": {
    "iso:country":"AU",
    "sg:address":"35 Brissett St",
    "sg:city":"Inverell",
    "sg:classifiers":[
        {
            "category":"Farming",
            "subcategory":"Berry Farm",
            "type":"Manufacturing & Wholesale Goods"
        }
    ],
    "sg:phone":"+61 2 6721 2727",
    "sg:postcode":"2360",
    "sg:province":"NSW",
    "sg:tags":[
        "fruit",
        "grower"
    ],
    "wof:name":"Gwydir Olives Pty Ltd",
    "wof:placetype":"venue"
},
  "geometry": {"coordinates":[151.125488281,-29.7646083832],"type":"Point"}
}