{
  "type": "Feature",
  "properties": {
    "iso:country":"AU",
    "sg:address":"7 Acrylon Rd",
    "sg:city":"Salisbury South",
    "sg:classifiers":[
        {
            "category":"Retail",
            "subcategory":"Auto Repair",
            "type":"Services"
        }
    ],
    "sg:phone":"+61 8 8258 1509",
    "sg:postcode":"5106",
    "sg:province":"SA",
    "sg:tags":[
        "repairer",
        "motor",
        "engineer"
    ],
    "wof:name":"Dave Armstrong Motors",
    "wof:placetype":"venue"
},
  "geometry": {"coordinates":[138.641724,-34.781467],"type":"Point"}
}