{
  "type": "Feature",
  "properties": {
    "addr:full":"3- 9 Lt Howard St North Melbourne VIC 3051",
    "addr:housenumber":"9",
    "addr:postcode":"3051",
    "addr:street":"Howard St",
    "iso:country":"AU",
    "sg:address":"3- 9 Lt Howard St",
    "sg:city":"North Melbourne",
    "sg:classifiers":[
        {
            "category":"Wholesale",
            "subcategory":"Painting Supplies",
            "type":"Manufacturing & Wholesale Goods"
        }
    ],
    "sg:phone":"+61 3 9329 7968",
    "sg:postcode":"3051",
    "sg:province":"VIC",
    "sg:tags":[
        "product",
        "cleaning"
    ],
    "wof:name":"Kaplan Distributors Pty Ltd",
    "wof:placetype":"venue"
},
  "geometry": {"coordinates":[144.954177856,-37.8028144836],"type":"Point"}
}