{
  "type": "Feature",
  "properties": {
    "addr:full":"Bluegum Drv Glenella QLD 4740",
    "addr:postcode":"4740",
    "addr:street":"Bluegum Drv",
    "iso:country":"AU",
    "sg:address":"Bluegum Drv",
    "sg:city":"Glenella",
    "sg:classifiers":[
        {
            "category":"Banks & Credit Unions",
            "subcategory":"Financial Services",
            "type":"Services"
        }
    ],
    "sg:phone":"+61 7 4942 4081",
    "sg:postcode":"4740",
    "sg:province":"QLD",
    "sg:tags":[
        "wholesaler",
        "mfrs",
        "gear"
    ],
    "wof:name":"Glenella Engineering",
    "wof:placetype":"venue"
},
  "geometry": {"coordinates":[149.137451,-21.115294],"type":"Point"}
}