{
  "type": "Feature",
  "properties": {
    "addr:full":"344 Victoria Rd Thornbury VIC 3071",
    "addr:housenumber":"344",
    "addr:postcode":"3071",
    "addr:street":"Victoria Rd",
    "iso:country":"AU",
    "sg:address":"344 Victoria Rd",
    "sg:city":"Thornbury",
    "sg:classifiers":[
        {
            "category":"Health Services",
            "subcategory":"Health Practitioner",
            "type":"Services"
        }
    ],
    "sg:phone":"+61 3 9443 8240",
    "sg:postcode":"3071",
    "sg:province":"VIC",
    "sg:tags":[
        "naturopath"
    ],
    "wof:name":"Linda Cotone",
    "wof:placetype":"venue"
},
  "geometry": {"coordinates":[145.01362609899999,-37.7576141357],"type":"Point"}
}