{
  "type": "Feature",
  "properties": {
    "addr:full":"5 Coates Pl Wetherill Park NSW 2164",
    "addr:housenumber":"5",
    "addr:postcode":"2164",
    "addr:street":"Coates Pl",
    "iso:country":"AU",
    "sg:address":"5 Coates Pl",
    "sg:city":"Wetherill Park",
    "sg:classifiers":[
        {
            "category":"Farming",
            "subcategory":"Fish & Marine Products",
            "type":"Manufacturing & Wholesale Goods"
        }
    ],
    "sg:phone":"+61 2 9756 4011",
    "sg:postcode":"2164",
    "sg:province":"NSW",
    "sg:tags":[
        "lead",
        "supply"
    ],
    "wof:name":"Consolidated Alloys",
    "wof:placetype":"venue"
},
  "geometry": {"coordinates":[150.8853302,-33.8396224976],"type":"Point"}
}