{
  "type": "Feature",
  "properties": {
    "addr:full":"Shop 5 Karl Complex Eastern Drv Gatton QLD 4343",
    "addr:housenumber":"shop 5",
    "addr:postcode":"4343",
    "addr:street":"Karl Complex Eastern Drv",
    "iso:country":"AU",
    "sg:address":"Shop 5 Karl Complex Eastern Drv",
    "sg:city":"Gatton",
    "sg:phone":"+61 7 5462 8886",
    "sg:postcode":"4343",
    "sg:province":"QLD",
    "wof:name":"Vandy's Water Solutions Pty Ltd",
    "wof:placetype":"venue"
},
  "geometry": {"coordinates":[152.26986694300001,-27.7063407898],"type":"Point"}
}