{
  "type": "Feature",
  "properties": {
    "addr:full":"133 Patrick St Laidley QLD 4341",
    "addr:housenumber":"133",
    "addr:postcode":"4341",
    "addr:street":"Patrick St",
    "iso:country":"AU",
    "sg:address":"133 Patrick St",
    "sg:city":"Laidley",
    "sg:classifiers":[
        {
            "category":"Fast Food",
            "type":"Food & Drink"
        }
    ],
    "sg:phone":"+61 7 5465 1282",
    "sg:postcode":"4341",
    "sg:province":"QLD",
    "sg:tags":[
        "away",
        "take"
    ],
    "wof:name":"Kelli's Diner",
    "wof:placetype":"venue"
},
  "geometry": {"coordinates":[152.393844605,-27.6306724548],"type":"Point"}
}