{
  "type": "Feature",
  "properties": {
    "addr:full":"155 Abernethy Rd Belmont WA 6104",
    "addr:housenumber":"155",
    "addr:postcode":"6104",
    "addr:street":"Abernethy Rd",
    "iso:country":"AU",
    "sg:address":"155 Abernethy Rd",
    "sg:city":"Belmont",
    "sg:classifiers":[
        {
            "category":"Retail",
            "subcategory":"Auto Repair",
            "type":"Services"
        }
    ],
    "sg:phone":"+61 8 9277 3622",
    "sg:postcode":"6104",
    "sg:province":"WA",
    "sg:tags":[
        "repairer",
        "motor",
        "engineer"
    ],
    "wof:name":"Ford",
    "wof:placetype":"venue"
},
  "geometry": {"coordinates":[115.92738342299999,-31.9547042847],"type":"Point"}
}