{
  "type": "Feature",
  "properties": {
    "addr:full":"16b Baldwyn St Frankston VIC 3199",
    "addr:housenumber":"16b",
    "addr:postcode":"3199",
    "addr:street":"Baldwyn St",
    "iso:country":"AU",
    "sg:address":"16b Baldwyn St",
    "sg:city":"Frankston",
    "sg:classifiers":[
        {
            "category":"Retail",
            "subcategory":"Repair Shop",
            "type":"Services"
        }
    ],
    "sg:phone":"+61 418 990 440",
    "sg:postcode":"3199",
    "sg:province":"VIC",
    "sg:tags":[
        "windscreen"
    ],
    "wof:name":"Allabout Windscreens",
    "wof:placetype":"venue"
},
  "geometry": {"coordinates":[145.12886047399999,-38.1314811707],"type":"Point"}
}