{
  "type": "Feature",
  "properties": {
    "addr:full":"Level 15/ 120 Collins St Melbourne VIC 3000",
    "addr:housenumber":"/ 120",
    "addr:postcode":"3000",
    "addr:street":"Collins St",
    "iso:country":"AU",
    "sg:address":"Level 15/ 120 Collins St",
    "sg:city":"Melbourne",
    "sg:classifiers":[
        {
            "category":"Banks & Credit Unions",
            "subcategory":"Investment Brokerage",
            "type":"Services"
        }
    ],
    "sg:phone":"+61 3 8643 9300",
    "sg:postcode":"3000",
    "sg:province":"VIC",
    "wof:name":"Smith Barney",
    "wof:placetype":"venue"
},
  "geometry": {"coordinates":[144.96966552699999,-37.8144378662],"type":"Point"}
}