{
  "type": "Feature",
  "properties": {
    "addr:full":"Ste 336 South Place+ 29 Milton Pde Malvern VIC 3144",
    "addr:housenumber":"29",
    "addr:postcode":"3144",
    "addr:street":"South Place+;Milton Pde",
    "iso:country":"AU",
    "sg:address":"Ste 336 South Place+ 29 Milton Pde",
    "sg:city":"Malvern",
    "sg:classifiers":[
        {
            "category":"Professional",
            "subcategory":"Accounting & Tax Preparation",
            "type":"Services"
        }
    ],
    "sg:phone":"+61 3 9832 0800",
    "sg:postcode":"3144",
    "sg:province":"VIC",
    "sg:tags":[
        "accountant",
        "auditor"
    ],
    "wof:name":"Rundle John B Chartered Accountants",
    "wof:placetype":"venue"
},
  "geometry": {"coordinates":[145.03907775900001,-37.8463401794],"type":"Point"}
}