{
  "type": "Feature",
  "properties": {
    "iso:country":"AU",
    "sg:address":"16a Jumal Pl",
    "sg:city":"Smithfield",
    "sg:classifiers":[
        {
            "category":"Manufacturing",
            "subcategory":"Metals",
            "type":"Manufacturing & Wholesale Goods"
        }
    ],
    "sg:phone":"+61 2 9632 2411",
    "sg:postcode":"2164",
    "sg:province":"NSW",
    "sg:tags":[
        "steel",
        "fabricator",
        "mfrs"
    ],
    "wof:name":"Aardvark Steel Constructions",
    "wof:placetype":"venue"
},
  "geometry": {"coordinates":[150.95121765100001,-33.8402824402],"type":"Point"}
}