{
  "type": "Feature",
  "properties": {
    "iso:country":"AU",
    "sg:address":"41 Bonwick St",
    "sg:city":"Fawkner",
    "sg:classifiers":[
        {
            "category":"Deli",
            "type":"Food & Drink"
        }
    ],
    "sg:phone":"+61 3 9359 1473",
    "sg:postcode":"3060",
    "sg:province":"VIC",
    "sg:tags":[
        "delicatessen"
    ],
    "wof:name":"Frankie's Family Deli",
    "wof:placetype":"venue"
},
  "geometry": {"coordinates":[144.96531677199999,-37.7025794983],"type":"Point"}
}