{
  "type": "Feature",
  "properties": {
    "iso:country":"AU",
    "sg:address":"PO Box 343",
    "sg:city":"Tuncurry",
    "sg:classifiers":[
        {
            "category":"Professional",
            "subcategory":"Art Services",
            "type":"Services"
        }
    ],
    "sg:phone":"+61 2 6554 3355",
    "sg:postcode":"2428",
    "sg:province":"NSW",
    "sg:tags":[
        "graphic",
        "designer"
    ],
    "wof:name":"Dancing Croc Design",
    "wof:placetype":"venue"
},
  "geometry": {"coordinates":[152.499664,-32.175468],"type":"Point"}
}