{
  "type": "Feature",
  "properties": {
    "addr:full":"322 Station St Lalor VIC 3075",
    "addr:housenumber":"322",
    "addr:postcode":"3075",
    "addr:street":"Station St",
    "iso:country":"AU",
    "sg:address":"322 Station St",
    "sg:city":"Lalor",
    "sg:classifiers":[
        {
            "category":"Banks & Credit Unions",
            "subcategory":"Bank",
            "type":"Services"
        }
    ],
    "sg:phone":"+61 13 20 32",
    "sg:postcode":"3075",
    "sg:province":"VIC",
    "wof:name":"Westpac",
    "wof:placetype":"venue"
},
  "geometry": {"coordinates":[145.02020263700001,-37.7656936646],"type":"Point"}
}