{
  "type": "Feature",
  "properties": {
    "addr:full":"Upper Level 371 Darling St Balmain NSW 2041",
    "addr:housenumber":"371",
    "addr:postcode":"2041",
    "addr:street":"Darling St",
    "iso:country":"AU",
    "sg:address":"Upper Level 371 Darling St",
    "sg:city":"Balmain",
    "sg:classifiers":[
        {
            "category":"Personal",
            "subcategory":"Beauty Salon",
            "type":"Services"
        }
    ],
    "sg:phone":"+61 2 9810 9999",
    "sg:postcode":"2041",
    "sg:province":"NSW",
    "wof:name":"Planet Beauty",
    "wof:placetype":"venue"
},
  "geometry": {"coordinates":[151.17770400000001,-33.856251],"type":"Point"}
}