{
  "type": "Feature",
  "properties": {
    "addr:full":"17 Leader St Campbellfield VIC 3061",
    "addr:housenumber":"17",
    "addr:postcode":"3061",
    "addr:street":"Leader St",
    "iso:country":"AU",
    "sg:address":"17 Leader St",
    "sg:city":"Campbellfield",
    "sg:classifiers":[
        {
            "category":"Utilities",
            "subcategory":"Electric",
            "type":"Services"
        }
    ],
    "sg:phone":"+61 3 9308 0200",
    "sg:postcode":"3061",
    "sg:province":"VIC",
    "sg:tags":[
        "electrical",
        "contractor"
    ],
    "wof:name":"R.C.S. Electrical Services Pty Ltd",
    "wof:placetype":"venue"
},
  "geometry": {"coordinates":[144.941894531,-37.6431808472],"type":"Point"}
}