{
  "type": "Feature",
  "properties": {
    "iso:country":"AU",
    "sg:address":"Rivergate Marina Unit 21/ 17 Rivergate Pl",
    "sg:city":"Murarrie",
    "sg:classifiers":[
        {
            "category":"Autos & Motor Vehicles",
            "subcategory":"Boat Sales",
            "type":"Retail Goods"
        }
    ],
    "sg:phone":"+61 1800 679 867",
    "sg:postcode":"4172",
    "sg:province":"QLD",
    "sg:tags":[
        "yacht"
    ],
    "wof:name":"Boating4U.com.au",
    "wof:placetype":"venue"
},
  "geometry": {"coordinates":[153.10523986800001,-27.4467258453],"type":"Point"}
}