{
  "type": "Feature",
  "properties": {
    "iso:country":"AU",
    "sg:address":"Lot 1 Sproules La",
    "sg:city":"Glenquarie",
    "sg:classifiers":[
        {
            "category":"Utilities",
            "subcategory":"Electric",
            "type":"Services"
        }
    ],
    "sg:phone":"+61 417 682 989",
    "sg:postcode":"2564",
    "sg:province":"NSW",
    "sg:tags":[
        "electrical",
        "contractor"
    ],
    "wof:name":"McRae Paul Electrical",
    "wof:placetype":"venue"
},
  "geometry": {"coordinates":[150.893966675,-33.9996871948],"type":"Point"}
}