{
  "type": "Feature",
  "properties": {
    "addr:full":"Archbold Rd Roseville NSW 2069",
    "addr:postcode":"2069",
    "addr:street":"Archbold Rd",
    "iso:country":"AU",
    "sg:address":"Archbold Rd",
    "sg:city":"Roseville",
    "sg:classifiers":[
        {
            "category":"Professional",
            "subcategory":"Management & Consulting",
            "type":"Services"
        }
    ],
    "sg:phone":"+61 2 9417 0466",
    "sg:postcode":"2069",
    "sg:province":"NSW",
    "sg:tags":[
        "consultant"
    ],
    "wof:name":"Tucker & Associates Pty Ltd",
    "wof:placetype":"venue"
},
  "geometry": {"coordinates":[151.18475341800001,-33.7782363892],"type":"Point"}
}