{
  "type": "Feature",
  "properties": {
    "addr:full":"746 Glenferrie Rd Hawthorn VIC 3122",
    "addr:housenumber":"746",
    "addr:postcode":"3122",
    "addr:street":"Glenferrie Rd",
    "iso:country":"AU",
    "sg:address":"746 Glenferrie Rd",
    "sg:city":"Hawthorn",
    "sg:classifiers":[
        {
            "category":"Food & Beverages",
            "subcategory":"Fruits & Vegetables",
            "type":"Retail Goods"
        }
    ],
    "sg:phone":"+61 3 9819 3725",
    "sg:postcode":"3122",
    "sg:province":"VIC",
    "sg:tags":[
        "greengrocer",
        "fruiterer"
    ],
    "wof:name":"Fine Fruits of Hawthorn",
    "wof:placetype":"venue"
},
  "geometry": {"coordinates":[145.03614807100001,-37.8191337585],"type":"Point"}
}