{
  "type": "Feature",
  "properties": {
    "addr:full":"86 McIvor Rd Bendigo VIC 3550",
    "addr:housenumber":"86",
    "addr:postcode":"3550",
    "addr:street":"Mcivor Rd",
    "iso:country":"AU",
    "sg:address":"86 McIvor Rd",
    "sg:city":"Bendigo",
    "sg:classifiers":[
        {
            "category":"Health Services",
            "subcategory":"Health Practitioner",
            "type":"Services"
        }
    ],
    "sg:phone":"+61 3 5443 5411",
    "sg:postcode":"3550",
    "sg:province":"VIC",
    "sg:tags":[
        "alternative"
    ],
    "wof:name":"Bendigo Natural Medicine",
    "wof:placetype":"venue"
},
  "geometry": {"coordinates":[144.29742431599999,-36.7584533691],"type":"Point"}
}