{
  "type": "Feature",
  "properties": {
    "iso:country":"AU",
    "sg:address":"41 Margaret St",
    "sg:city":"Toowoomba",
    "sg:classifiers":[
        {
            "category":"Travel",
            "subcategory":"Hotels & Motels",
            "type":"Entertainment"
        }
    ],
    "sg:phone":"+61 7 4632 2088",
    "sg:postcode":"4350",
    "sg:province":"QLD",
    "wof:name":"Applegum Inn",
    "wof:placetype":"venue"
},
  "geometry": {"coordinates":[151.95521500000001,-27.561083],"type":"Point"}
}