{
  "type": "Feature",
  "properties": {
    "addr:full":"Level 10/ 56 Berry St North Sydney NSW 2060",
    "addr:housenumber":"/ 56",
    "addr:postcode":"2060",
    "addr:street":"Berry St",
    "iso:country":"AU",
    "sg:address":"Level 10/ 56 Berry St",
    "sg:city":"North Sydney",
    "sg:classifiers":[
        {
            "category":"Education",
            "subcategory":"Special Training",
            "type":"Public Place"
        }
    ],
    "sg:phone":"+61 2 9955 3333",
    "sg:postcode":"2060",
    "sg:province":"NSW",
    "sg:tags":[
        "development"
    ],
    "wof:name":"IBT International",
    "wof:placetype":"venue"
},
  "geometry": {"coordinates":[151.207855225,-33.8367729187],"type":"Point"}
}