{
  "type": "Feature",
  "properties": {
    "iso:country":"AU",
    "sg:address":"Jacobs Well Rd",
    "sg:city":"Woongoolba",
    "sg:classifiers":[
        {
            "category":"Education",
            "subcategory":"Kindergarten",
            "type":"Public Place"
        }
    ],
    "sg:phone":"+61 7 5546 2246",
    "sg:postcode":"4207",
    "sg:province":"QLD",
    "sg:tags":[
        "pre-schools"
    ],
    "wof:name":"Bethlehem Lutheran Kindergarten & Pre-School",
    "wof:placetype":"venue"
},
  "geometry": {"coordinates":[153.318283081,-27.7451400757],"type":"Point"}
}