{
  "type": "Feature",
  "properties": {
    "addr:full":"6 Robinson St North Mackay QLD 4740",
    "addr:housenumber":"6",
    "addr:postcode":"4740",
    "addr:street":"Robinson St",
    "iso:country":"AU",
    "sg:address":"6 Robinson St",
    "sg:city":"North Mackay",
    "sg:classifiers":[
        {
            "category":"Mining & Drilling",
            "type":"Manufacturing & Wholesale Goods"
        }
    ],
    "sg:phone":"+61 7 4957 6025",
    "sg:postcode":"4740",
    "sg:province":"QLD",
    "sg:tags":[
        "geologist"
    ],
    "wof:name":"Cherry K C",
    "wof:placetype":"venue"
},
  "geometry": {"coordinates":[149.19352699999999,-21.119982],"type":"Point"}
}