{
  "type": "Feature",
  "properties": {
    "addr:full":"Clinton Drv Narellan NSW 2567",
    "addr:postcode":"2567",
    "addr:street":"Clinton Drv",
    "iso:country":"AU",
    "sg:address":"Clinton Drv",
    "sg:city":"Narellan",
    "sg:classifiers":[
        {
            "category":"Home & Garden",
            "subcategory":"Furniture",
            "type":"Retail Goods"
        }
    ],
    "sg:phone":"+61 2 4647 1255",
    "sg:postcode":"2567",
    "sg:province":"NSW",
    "sg:tags":[
        "repair",
        "restoration"
    ],
    "wof:name":"Camden Valley Antiques",
    "wof:placetype":"venue"
},
  "geometry": {"coordinates":[150.74333190900001,-34.0449638367],"type":"Point"}
}