{
  "type": "Feature",
  "properties": {
    "addr:full":"180 Payneham Rd Evandale SA 5069",
    "addr:housenumber":"180",
    "addr:postcode":"5069",
    "addr:street":"Payneham Rd",
    "iso:country":"AU",
    "sg:address":"180 Payneham Rd",
    "sg:city":"Evandale",
    "sg:classifiers":[
        {
            "category":"Manufacturing",
            "subcategory":"Glass & Minerals",
            "type":"Manufacturing & Wholesale Goods"
        }
    ],
    "sg:phone":"+61 8 8363 4511",
    "sg:postcode":"5069",
    "sg:province":"SA",
    "sg:tags":[
        "stained"
    ],
    "wof:name":"Alpha Leadlight",
    "wof:placetype":"venue"
},
  "geometry": {"coordinates":[138.63163757300001,-34.9053344727],"type":"Point"}
}