{
  "type": "Feature",
  "properties": {
    "iso:country":"AU",
    "sg:address":"37 Bay St",
    "sg:city":"Double Bay",
    "sg:classifiers":[
        {
            "category":"Cafe",
            "type":"Food & Drink"
        }
    ],
    "sg:phone":"+61 2 9326 1602",
    "sg:postcode":"2028",
    "sg:province":"NSW",
    "wof:name":"Courtyard Cafe",
    "wof:placetype":"venue"
},
  "geometry": {"coordinates":[151.24168395999999,-33.877532959],"type":"Point"}
}