{
  "type": "Feature",
  "properties": {
    "addr:full":"28 Melbourne Rd St Arnaud VIC 3478",
    "addr:housenumber":"28",
    "addr:postcode":"3478",
    "addr:street":"Melbourne Rd",
    "iso:country":"AU",
    "sg:address":"28 Melbourne Rd",
    "sg:city":"St Arnaud",
    "sg:classifiers":[
        {
            "category":"Manufacturing",
            "subcategory":"Jewelry",
            "type":"Manufacturing & Wholesale Goods"
        }
    ],
    "sg:phone":"+61 3 5495 2663",
    "sg:postcode":"3478",
    "sg:province":"VIC",
    "sg:tags":[
        "mfrg",
        "jeweller"
    ],
    "wof:name":"D. A Russ Silversmith",
    "wof:placetype":"venue"
},
  "geometry": {"coordinates":[143.26399230999999,-36.6244621277],"type":"Point"}
}