{
  "type": "Feature",
  "properties": {
    "addr:full":"Shp58-60/193- 195-195 Pitt St Sydney NSW 2000",
    "addr:housenumber":"195-195",
    "addr:postcode":"2000",
    "addr:street":"Pitt St",
    "iso:country":"AU",
    "sg:address":"Shp58-60/193- 195-195 Pitt St",
    "sg:city":"Sydney",
    "sg:classifiers":[
        {
            "category":"Shopping",
            "subcategory":"Clothing, Apparel, & Fashions",
            "type":"Retail Goods"
        }
    ],
    "sg:phone":"+61 2 9221 7277",
    "sg:postcode":"2000",
    "sg:province":"NSW",
    "sg:tags":[
        "lady",
        "wear"
    ],
    "wof:name":"Leona Edmiston Pty Ltd",
    "wof:placetype":"venue"
},
  "geometry": {"coordinates":[151.208084106,-33.8695335388],"type":"Point"}
}