{
  "type": "Feature",
  "properties": {
    "iso:country":"AU",
    "sg:address":"4- 8 Instow St",
    "sg:city":"Toowoomba",
    "sg:classifiers":[
        {
            "category":"Retail",
            "subcategory":"Auto Repair",
            "type":"Services"
        }
    ],
    "sg:phone":"+61 7 4638 0011",
    "sg:postcode":"4350",
    "sg:province":"QLD",
    "sg:tags":[
        "beater",
        "painter",
        "panel"
    ],
    "wof:name":"Wilkie Col",
    "wof:placetype":"venue"
},
  "geometry": {"coordinates":[151.951355,-27.565332],"type":"Point"}
}