{
  "type": "Feature",
  "properties": {
    "addr:full":"5 Carnsworth Ave Kew VIC 3101",
    "addr:housenumber":"5",
    "addr:postcode":"3101",
    "addr:street":"Carnsworth Ave",
    "iso:country":"AU",
    "sg:address":"5 Carnsworth Ave",
    "sg:city":"Kew",
    "sg:classifiers":[
        {
            "category":"Real Estate",
            "subcategory":"Architect",
            "type":"Services"
        }
    ],
    "sg:phone":"+61 3 9853 1340",
    "sg:postcode":"3101",
    "sg:province":"VIC",
    "wof:name":"Fink L",
    "wof:placetype":"venue"
},
  "geometry": {"coordinates":[145.023605347,-37.803691864],"type":"Point"}
}