{
  "type": "Feature",
  "properties": {
    "iso:country":"AU",
    "sg:address":"Unit 3/ 24",
    "sg:city":"Yampi Way Willetton",
    "sg:classifiers":[
        {
            "category":"Retail",
            "subcategory":"Auto Repair",
            "type":"Services"
        }
    ],
    "sg:phone":"+61 8 9457 8844",
    "sg:postcode":"6155",
    "sg:province":"WA",
    "sg:tags":[
        "engine",
        "reconditioning"
    ],
    "wof:name":"GTS Motors",
    "wof:placetype":"venue"
},
  "geometry": {"coordinates":[115.885948,-32.042461],"type":"Point"}
}