{
  "type": "Feature",
  "properties": {
    "iso:country":"AU",
    "sg:address":"The Training Network Building 19 Second St",
    "sg:city":"Katherine",
    "sg:classifiers":[
        {
            "category":"Organizations",
            "subcategory":"Non-profit Organization",
            "type":"Services"
        }
    ],
    "sg:phone":"+61 8 8971 0027",
    "sg:postcode":"0850",
    "sg:province":"NT",
    "sg:tags":[
        "support",
        "disability",
        "organisation"
    ],
    "wof:name":"Sponsor Family Association Inc",
    "wof:placetype":"venue"
},
  "geometry": {"coordinates":[132.26341199999999,-14.461677],"type":"Point"}
}