{
  "type": "Feature",
  "properties": {
    "addr:full":"62 Sheilds St Cairns QLD 4870",
    "addr:housenumber":"62",
    "addr:postcode":"4870",
    "addr:street":"Sheilds St",
    "iso:country":"AU",
    "sg:address":"62 Sheilds St",
    "sg:city":"Cairns",
    "sg:classifiers":[
        {
            "category":"Cafe",
            "type":"Food & Drink"
        }
    ],
    "sg:phone":"+61 7 4051 1883",
    "sg:postcode":"4870",
    "sg:province":"QLD",
    "wof:name":"The Victory On Sheilds",
    "wof:placetype":"venue"
},
  "geometry": {"coordinates":[145.773925781,-16.9233798981],"type":"Point"}
}