{
  "type": "Feature",
  "properties": {
    "iso:country":"AU",
    "sg:address":"U 5/ 27 Anvil Rd",
    "sg:city":"Seven Hills",
    "sg:classifiers":[
        {
            "category":"Manufacturing",
            "subcategory":"Rubber & Plastics",
            "type":"Manufacturing & Wholesale Goods"
        }
    ],
    "sg:phone":"+61 2 9674 8090",
    "sg:postcode":"2147",
    "sg:province":"NSW",
    "sg:tags":[
        "wholesaler",
        "product",
        "mfrs"
    ],
    "wof:name":"Activity Products Pty Ltd",
    "wof:placetype":"venue"
},
  "geometry": {"coordinates":[150.958374023,-33.7786369324],"type":"Point"}
}