{
  "type": "Feature",
  "properties": {
    "iso:country":"AU",
    "sg:address":"26 Haig St",
    "sg:city":"Bexley",
    "sg:classifiers":[
        {
            "category":"Building & Trades",
            "subcategory":"Equipment Rental",
            "type":"Services"
        }
    ],
    "sg:phone":"+61 2 9587 9414",
    "sg:postcode":"2207",
    "sg:province":"NSW",
    "sg:tags":[
        "renting",
        "trailer"
    ],
    "wof:name":"Allens Car Trailers",
    "wof:placetype":"venue"
},
  "geometry": {"coordinates":[151.11319,-33.957771],"type":"Point"}
}