{
  "type": "Feature",
  "properties": {
    "addr:full":"10 Waratah St Balgowlah NSW 2093",
    "addr:housenumber":"10",
    "addr:postcode":"2093",
    "addr:street":"Waratah St",
    "iso:country":"AU",
    "sg:address":"10 Waratah St",
    "sg:city":"Balgowlah",
    "sg:classifiers":[
        {
            "category":"Real Estate",
            "subcategory":"Real Estate Agent",
            "type":"Services"
        }
    ],
    "sg:phone":"+61 2 9948 4518",
    "sg:postcode":"2093",
    "sg:province":"NSW",
    "wof:name":"Manly Cove Property Consultants Pty Ltd",
    "wof:placetype":"venue"
},
  "geometry": {"coordinates":[151.26829528799999,-33.7946205139],"type":"Point"}
}