{
  "type": "Feature",
  "properties": {
    "iso:country":"AU",
    "sg:address":"Unit 2 60 Barrier St",
    "sg:city":"Fyshwick",
    "sg:classifiers":[
        {
            "category":"Professional",
            "subcategory":"Printing & Photocopies",
            "type":"Services"
        }
    ],
    "sg:phone":"+61 1300 663 623",
    "sg:postcode":"2609",
    "sg:province":"ACT",
    "sg:tags":[
        "equipment",
        "plan"
    ],
    "wof:name":"Oce-Australia Limited",
    "wof:placetype":"venue"
},
  "geometry": {"coordinates":[149.17338562,-35.3290939331],"type":"Point"}
}