{
  "type": "Feature",
  "properties": {
    "iso:country":"AU",
    "sg:address":"1st Floor/ 67 Watton St",
    "sg:city":"Werribee",
    "sg:classifiers":[
        {
            "category":"Professional",
            "subcategory":"Accounting & Tax Preparation",
            "type":"Services"
        }
    ],
    "sg:phone":"+61 3 9974 4300",
    "sg:postcode":"3030",
    "sg:province":"VIC",
    "sg:tags":[
        "accountant",
        "auditor"
    ],
    "wof:name":"Kennedy Peter M & Associates",
    "wof:placetype":"venue"
},
  "geometry": {"coordinates":[144.661484,-37.90136],"type":"Point"}
}