{
  "type": "Feature",
  "properties": {
    "addr:full":"186 Hume Hwy Lansvale NSW 2166",
    "addr:housenumber":"186",
    "addr:postcode":"2166",
    "addr:street":"Hume Hwy",
    "iso:country":"AU",
    "sg:address":"186 Hume Hwy",
    "sg:city":"Lansvale",
    "sg:classifiers":[
        {
            "category":"Farming",
            "subcategory":"Farm & Veterinary Services",
            "type":"Manufacturing & Wholesale Goods"
        }
    ],
    "sg:phone":"+61 414 551 191",
    "sg:postcode":"2166",
    "sg:province":"NSW",
    "sg:tags":[
        "poultry",
        "processing",
        "supply"
    ],
    "wof:name":"Table Talk (NSW) Pty Ltd",
    "wof:placetype":"venue"
},
  "geometry": {"coordinates":[150.954879761,-33.8960456848],"type":"Point"}
}