{
  "type": "Feature",
  "properties": {
    "addr:full":"69 Thuringowa Drv Kirwan QLD 4817",
    "addr:housenumber":"69",
    "addr:postcode":"4817",
    "addr:street":"Thuringowa Drv",
    "iso:country":"AU",
    "sg:address":"69 Thuringowa Drv",
    "sg:city":"Kirwan",
    "sg:classifiers":[
        {
            "category":"Health Services",
            "subcategory":"Dentist",
            "type":"Services"
        }
    ],
    "sg:phone":"+61 1800 356 560",
    "sg:postcode":"4817",
    "sg:province":"QLD",
    "wof:name":"James Brian E",
    "wof:placetype":"venue"
},
  "geometry": {"coordinates":[146.73333700000001,-19.307331],"type":"Point"}
}