{
  "type": "Feature",
  "properties": {
    "iso:country":"AU",
    "sg:address":"104 Canterbury Rd",
    "sg:city":"Blackburn South",
    "sg:classifiers":[
        {
            "category":"Personal",
            "subcategory":"Beauty Salon",
            "type":"Services"
        }
    ],
    "sg:phone":"+61 3 9877 3908",
    "sg:postcode":"3130",
    "sg:province":"VIC",
    "sg:tags":[
        "hairdresser"
    ],
    "wof:name":"Hocus Pocus Hair Design",
    "wof:placetype":"venue"
},
  "geometry": {"coordinates":[145.14720153799999,-37.8319206238],"type":"Point"}
}