{
  "type": "Feature",
  "properties": {
    "addr:full":"239 Archer St Shepparton VIC 3630",
    "addr:housenumber":"239",
    "addr:postcode":"3630",
    "addr:street":"Archer St",
    "iso:country":"AU",
    "sg:address":"239 Archer St",
    "sg:city":"Shepparton",
    "sg:classifiers":[
        {
            "category":"Autos & Motor Vehicles",
            "subcategory":"Automobile Sales",
            "type":"Retail Goods"
        }
    ],
    "sg:phone":"+61 3 5821 5433",
    "sg:postcode":"3630",
    "sg:province":"VIC",
    "sg:tags":[
        "car",
        "used"
    ],
    "wof:name":"Shepparton Autos Pty Ltd",
    "wof:placetype":"venue"
},
  "geometry": {"coordinates":[145.41018676799999,-36.3967552185],"type":"Point"}
}