{
  "type": "Feature",
  "properties": {
    "addr:full":"8 Marvel St Byron Bay NSW 2481",
    "addr:housenumber":"8",
    "addr:postcode":"2481",
    "addr:street":"Marvel St",
    "iso:country":"AU",
    "sg:address":"8 Marvel St",
    "sg:city":"Byron Bay",
    "sg:classifiers":[
        {
            "category":"Health Services",
            "subcategory":"Health Practitioner",
            "type":"Services"
        }
    ],
    "sg:phone":"+61 432 653 255",
    "sg:postcode":"2481",
    "sg:province":"NSW",
    "sg:tags":[
        "acupuncture"
    ],
    "wof:name":"Baxter, Philip Brian",
    "wof:placetype":"venue"
},
  "geometry": {"coordinates":[153.614105225,-28.6454277039],"type":"Point"}
}