{
  "type": "Feature",
  "properties": {
    "addr:full":"15 Massey St Evatt ACT 2617",
    "addr:housenumber":"15",
    "addr:postcode":"2617",
    "addr:street":"Massey St",
    "iso:country":"AU",
    "sg:address":"15 Massey St",
    "sg:city":"Evatt",
    "sg:classifiers":[
        {
            "category":"Professional",
            "subcategory":"Art Services",
            "type":"Services"
        }
    ],
    "sg:phone":"+61 412 563 195",
    "sg:postcode":"2617",
    "sg:province":"ACT",
    "sg:tags":[
        "decorator",
        "painter"
    ],
    "wof:name":"Rainbow Painters & Decorators",
    "wof:placetype":"venue"
},
  "geometry": {"coordinates":[149.07994079599999,-35.2091712952],"type":"Point"}
}