{
  "type": "Feature",
  "properties": {
    "iso:country":"AU",
    "sg:address":"121 Newcastle St",
    "sg:city":"Fyshwick",
    "sg:classifiers":[
        {
            "category":"Retail",
            "subcategory":"Auto Repair",
            "type":"Services"
        }
    ],
    "sg:phone":"+61 2 6280 6555",
    "sg:postcode":"2609",
    "sg:province":"ACT",
    "sg:tags":[
        "beater",
        "painter",
        "panel"
    ],
    "wof:name":"Morris Athol",
    "wof:placetype":"venue"
},
  "geometry": {"coordinates":[149.17686462399999,-35.32787323],"type":"Point"}
}