{
  "type": "Feature",
  "properties": {
    "addr:full":"36a Clements Ave Bundoora VIC 3083",
    "addr:housenumber":"36a",
    "addr:postcode":"3083",
    "addr:street":"Clements Ave",
    "iso:country":"AU",
    "sg:address":"36a Clements Ave",
    "sg:city":"Bundoora",
    "sg:classifiers":[
        {
            "category":"Arts & Performance",
            "subcategory":"Theater",
            "type":"Entertainment"
        }
    ],
    "sg:phone":"+61 3 9465 7666",
    "sg:postcode":"3083",
    "sg:province":"VIC",
    "sg:tags":[
        "theatrical",
        "supply"
    ],
    "wof:name":"Coemar Desisti Aust Pty Ltd",
    "wof:placetype":"venue"
},
  "geometry": {"coordinates":[145.07342529300001,-37.703666687],"type":"Point"}
}