{
  "type": "Feature",
  "properties": {
    "iso:country":"AU",
    "sg:address":"30 Old Northern Rd",
    "sg:city":"Everton Park",
    "sg:classifiers":[
        {
            "category":"Building & Trades",
            "subcategory":"Pest Control",
            "type":"Services"
        }
    ],
    "sg:phone":"+61 7 3356 6087",
    "sg:postcode":"4053",
    "sg:province":"QLD",
    "wof:name":"Bird Possum Rat & Pigeon Removalist",
    "wof:placetype":"venue"
},
  "geometry": {"coordinates":[152.98597717300001,-27.3990345001],"type":"Point"}
}