{
  "type": "Feature",
  "properties": {
    "iso:country":"AU",
    "sg:address":"39 Mortimer St",
    "sg:city":"Kalbarri",
    "sg:classifiers":[
        {
            "category":"Farming",
            "subcategory":"Fish & Marine Products",
            "type":"Manufacturing & Wholesale Goods"
        }
    ],
    "sg:phone":"+61 8 9937 1053",
    "sg:postcode":"6536",
    "sg:province":"WA",
    "sg:tags":[
        "fisherman"
    ],
    "wof:name":"Ross J A & L A",
    "wof:placetype":"venue"
},
  "geometry": {"coordinates":[114.16928100600001,-27.7059688568],"type":"Point"}
}