{
  "type": "Feature",
  "properties": {
    "addr:full":"8 Gould Drv Glass House Mountains QLD 4518",
    "addr:housenumber":"8",
    "addr:postcode":"4518",
    "addr:street":"Gould Drv",
    "iso:country":"AU",
    "sg:address":"8 Gould Drv",
    "sg:city":"Glass House Mountains",
    "sg:classifiers":[
        {
            "category":"Health Services",
            "subcategory":"Health Practitioner",
            "type":"Services"
        }
    ],
    "sg:phone":"+61 7 5493 0040",
    "sg:postcode":"4518",
    "sg:province":"QLD",
    "sg:tags":[
        "alternative"
    ],
    "wof:name":"Glasshouse Kinesiology",
    "wof:placetype":"venue"
},
  "geometry": {"coordinates":[152.922973633,-26.8935909271],"type":"Point"}
}