{
  "type": "Feature",
  "properties": {
    "addr:full":"PO Box 45 Wavell Heights North QLD 4012",
    "addr:postcode":"4012",
    "iso:country":"AU",
    "sg:address":"PO Box 45",
    "sg:city":"Wavell Heights North",
    "sg:classifiers":[
        {
            "category":"Manufacturing",
            "subcategory":"Food",
            "type":"Manufacturing & Wholesale Goods"
        }
    ],
    "sg:phone":"+61 414 674 696",
    "sg:postcode":"4012",
    "sg:province":"QLD",
    "sg:tags":[
        "function",
        "catering"
    ],
    "wof:name":"Food FX",
    "wof:placetype":"venue"
},
  "geometry": {"coordinates":[153.04986572300001,-27.389749527],"type":"Point"}
}