{
  "type": "Feature",
  "properties": {
    "addr:full":"Level 5, The Works, 6- 8 Musk Ave Kelvin Grove QLD 4059",
    "addr:housenumber":"6 8",
    "addr:postcode":"4059",
    "addr:street":"Musk Ave",
    "iso:country":"AU",
    "sg:address":"Level 5, The Works, 6- 8 Musk Ave",
    "sg:city":"Kelvin Grove",
    "sg:classifiers":[
        {
            "category":"Arts & Performance",
            "subcategory":"Theater",
            "type":"Entertainment"
        }
    ],
    "sg:phone":"+61 7 3007 8600",
    "sg:postcode":"4059",
    "sg:province":"QLD",
    "sg:tags":[
        "theatre"
    ],
    "wof:name":"La Boite Theatre Company",
    "wof:placetype":"venue"
},
  "geometry": {"coordinates":[153.013595581,-27.4555969238],"type":"Point"}
}