{
  "type": "Feature",
  "properties": {
    "iso:country":"AU",
    "sg:address":"Suite 5 Cnr King & Box St",
    "sg:city":"Buderim",
    "sg:classifiers":[
        {
            "category":"Health Services",
            "subcategory":"Doctor",
            "type":"Services"
        }
    ],
    "sg:phone":"+61 7 5456 1011",
    "sg:postcode":"4556",
    "sg:province":"QLD",
    "sg:tags":[
        "medical",
        "practitioner"
    ],
    "wof:name":"Buderim Medical Centre",
    "wof:placetype":"venue"
},
  "geometry": {"coordinates":[153.06068420400001,-26.6829013824],"type":"Point"}
}