{
  "type": "Feature",
  "properties": {
    "addr:full":"2770 Warburton Hwy Wesburn VIC 3799",
    "addr:housenumber":"2770",
    "addr:postcode":"3799",
    "addr:street":"Warburton Hwy",
    "iso:country":"AU",
    "sg:address":"2770 Warburton Hwy",
    "sg:city":"Wesburn",
    "sg:classifiers":[
        {
            "category":"Retail",
            "subcategory":"Auto Repair",
            "type":"Services"
        }
    ],
    "sg:phone":"+61 418 395 072",
    "sg:postcode":"3799",
    "sg:province":"VIC",
    "sg:tags":[
        "bus",
        "truck"
    ],
    "wof:name":"D & L Diesel Services",
    "wof:placetype":"venue"
},
  "geometry": {"coordinates":[145.64552307100001,-37.7670555115],"type":"Point"}
}