{
  "type": "Feature",
  "properties": {
    "addr:full":"16 Stortford Ave Ivanhoe VIC 3079",
    "addr:housenumber":"16",
    "addr:postcode":"3079",
    "addr:street":"Stortford Ave",
    "iso:country":"AU",
    "sg:address":"16 Stortford Ave",
    "sg:city":"Ivanhoe",
    "sg:classifiers":[
        {
            "category":"Building & Trades",
            "subcategory":"Plumbing",
            "type":"Services"
        }
    ],
    "sg:phone":"+61 3 9499 8222",
    "sg:postcode":"3079",
    "sg:province":"VIC",
    "sg:tags":[
        "plumber",
        "gasfitters"
    ],
    "wof:name":"Woolleys Plumbing Pty Ltd",
    "wof:placetype":"venue"
},
  "geometry": {"coordinates":[145.033004761,-37.7626800537],"type":"Point"}
}