{
  "type": "Feature",
  "properties": {
    "addr:full":"Victory Rd Langwarrin VIC 3910",
    "addr:postcode":"3910",
    "addr:street":"Victory Rd",
    "iso:country":"AU",
    "sg:address":"Victory Rd",
    "sg:city":"Langwarrin",
    "sg:classifiers":[
        {
            "category":"Utilities",
            "subcategory":"Electric",
            "type":"Services"
        }
    ],
    "sg:phone":"+61 3 5978 6777",
    "sg:postcode":"3910",
    "sg:province":"VIC",
    "sg:tags":[
        "electrical",
        "contractor"
    ],
    "wof:name":"Smale B M",
    "wof:placetype":"venue"
},
  "geometry": {"coordinates":[145.21087646500001,-38.1823577881],"type":"Point"}
}