{
  "type": "Feature",
  "properties": {
    "addr:full":"144 Edward St Ayr QLD 4807",
    "addr:housenumber":"144",
    "addr:postcode":"4807",
    "addr:street":"Edward St",
    "iso:country":"AU",
    "sg:address":"144 Edward St",
    "sg:city":"Ayr",
    "sg:classifiers":[
        {
            "category":"Shopping",
            "subcategory":"Beauty & Cosmetics",
            "type":"Retail Goods"
        }
    ],
    "sg:phone":"+61 7 4783 1719",
    "sg:postcode":"4807",
    "sg:province":"QLD",
    "wof:name":"Julie's Pharmacy",
    "wof:placetype":"venue"
},
  "geometry": {"coordinates":[147.4087677,-19.5759410858],"type":"Point"}
}