{
  "type": "Feature",
  "properties": {
    "addr:full":"15 Somerset Pl Nemingha NSW 2340",
    "addr:housenumber":"15",
    "addr:postcode":"2340",
    "addr:street":"Somerset Pl",
    "iso:country":"AU",
    "sg:address":"15 Somerset Pl",
    "sg:city":"Nemingha",
    "sg:classifiers":[
        {
            "category":"Building & Trades",
            "subcategory":"Landscaping Services",
            "type":"Services"
        }
    ],
    "sg:phone":"+61 428 609 435",
    "sg:postcode":"2340",
    "sg:province":"NSW",
    "sg:tags":[
        "slashing",
        "contractor"
    ],
    "wof:name":"Tamworth Small Farm Care",
    "wof:placetype":"venue"
},
  "geometry": {"coordinates":[150.98419189399999,-31.1228294373],"type":"Point"}
}