{
  "type": "Feature",
  "properties": {
    "addr:full":"94b Wentworth St South Hobart TAS 7004",
    "addr:housenumber":"94b",
    "addr:postcode":"7004",
    "addr:street":"Wentworth St",
    "iso:country":"AU",
    "sg:address":"94b Wentworth St",
    "sg:city":"South Hobart",
    "sg:classifiers":[
        {
            "category":"Personal",
            "subcategory":"Massage",
            "type":"Services"
        }
    ],
    "sg:phone":"+61 3 6224 9660",
    "sg:postcode":"7004",
    "sg:province":"TAS",
    "sg:tags":[
        "therapy"
    ],
    "wof:name":"Gentle Touch Infant Massage",
    "wof:placetype":"venue"
},
  "geometry": {"coordinates":[147.30801391599999,-42.8958473206],"type":"Point"}
}