{
  "type": "Feature",
  "properties": {
    "iso:country":"AU",
    "sg:address":"13 Clement St",
    "sg:city":"Ayr",
    "sg:classifiers":[
        {
            "category":"Building & Trades",
            "subcategory":"Landscaping Services",
            "type":"Services"
        }
    ],
    "sg:phone":"+61 7 4783 2728",
    "sg:postcode":"4807",
    "sg:province":"QLD",
    "sg:tags":[
        "stump",
        "tree",
        "felling",
        "removal"
    ],
    "wof:name":"Burdekin Woodchipping Services",
    "wof:placetype":"venue"
},
  "geometry": {"coordinates":[147.39590454099999,-19.5976467133],"type":"Point"}
}