{
  "type": "Feature",
  "properties": {
    "iso:country":"AU",
    "sg:address":"PO Box 2165",
    "sg:city":"Malaga",
    "sg:classifiers":[
        {
            "category":"Organizations",
            "subcategory":"Professional Association",
            "type":"Services"
        }
    ],
    "sg:phone":"+61 8 9249 3646",
    "sg:postcode":"6090",
    "sg:province":"WA",
    "sg:tags":[
        "web",
        "internet"
    ],
    "sg:website":"http://www.hostaway.net.au",
    "wof:name":"Hostitaway",
    "wof:placetype":"venue"
},
  "geometry": {"coordinates":[115.892311096,-31.8608016968],"type":"Point"}
}