{
  "type": "Feature",
  "properties": {
    "addr:full":"PO Box 493 Caloundra QLD 4551",
    "addr:postcode":"4551",
    "iso:country":"AU",
    "sg:address":"PO Box 493",
    "sg:city":"Caloundra",
    "sg:classifiers":[
        {
            "category":"Professional",
            "subcategory":"Accounting & Tax Preparation",
            "type":"Services"
        }
    ],
    "sg:phone":"+61 7 5499 6786",
    "sg:postcode":"4551",
    "sg:province":"QLD",
    "sg:tags":[
        "consultant",
        "taxation"
    ],
    "wof:name":"Frank W Redpath",
    "wof:placetype":"venue"
},
  "geometry": {"coordinates":[153.124755859,-26.7936191559],"type":"Point"}
}