{
  "type": "Feature",
  "properties": {
    "addr:full":"52 River St Maclean NSW 2463",
    "addr:housenumber":"52",
    "addr:postcode":"2463",
    "addr:street":"River St",
    "iso:country":"AU",
    "sg:address":"52 River St",
    "sg:city":"Maclean",
    "sg:classifiers":[
        {
            "category":"Health Services",
            "subcategory":"Doctor",
            "type":"Services"
        }
    ],
    "sg:phone":"+61 2 6645 4477",
    "sg:postcode":"2463",
    "sg:province":"NSW",
    "sg:tags":[
        "medical",
        "practitioner"
    ],
    "wof:name":"Clarence Valley Imaging",
    "wof:placetype":"venue"
},
  "geometry": {"coordinates":[153.202850342,-29.447845459],"type":"Point"}
}