{
  "type": "Feature",
  "properties": {
    "addr:full":"99 Royal St East Perth WA 6004",
    "addr:housenumber":"99",
    "addr:postcode":"6004",
    "addr:street":"Royal St East",
    "iso:country":"AU",
    "sg:address":"99 Royal St",
    "sg:city":"East Perth",
    "sg:classifiers":[
        {
            "category":"Professional",
            "subcategory":"Employment Agencies",
            "type":"Services"
        }
    ],
    "sg:phone":"+61 8 9221 8122",
    "sg:postcode":"6004",
    "sg:province":"WA",
    "wof:name":"Wood Recruitment",
    "wof:placetype":"venue"
},
  "geometry": {"coordinates":[115.876403809,-31.9533233643],"type":"Point"}
}