{
  "type": "Feature",
  "properties": {
    "addr:full":"Fairfield Park Drv Fairfield VIC 3078",
    "addr:postcode":"3078",
    "addr:street":"Fairfield Park Drv",
    "iso:country":"AU",
    "sg:address":"Fairfield Park Drv",
    "sg:city":"Fairfield",
    "sg:classifiers":[
        {
            "category":"Restaurant",
            "type":"Food & Drink"
        }
    ],
    "sg:phone":"+61 3 9486 1501",
    "sg:postcode":"3078",
    "sg:province":"VIC",
    "wof:name":"AAAAFairfield Park Boathouse & Tea Gardens",
    "wof:placetype":"venue"
},
  "geometry": {"coordinates":[145.01344299300001,-37.7881202698],"type":"Point"}
}