{
  "type": "Feature",
  "properties": {
    "addr:full":"18 Lakes Drv Tweed Heads NSW 2485",
    "addr:housenumber":"18",
    "addr:postcode":"2485",
    "addr:street":"Lakes Drv",
    "iso:country":"AU",
    "sg:address":"18 Lakes Drv",
    "sg:city":"Tweed Heads",
    "sg:classifiers":[
        {
            "category":"Landmark",
            "subcategory":"Scenic View",
            "type":"Public Place"
        }
    ],
    "sg:phone":"+61 424 710 875",
    "sg:postcode":"2485",
    "sg:province":"NSW",
    "sg:tags":[
        "staircase",
        "handrail"
    ],
    "wof:name":"Stair Solutions",
    "wof:placetype":"venue"
},
  "geometry": {"coordinates":[153.51756286599999,-28.1832504272],"type":"Point"}
}