{
  "type": "Feature",
  "properties": {
    "addr:full":"30 Ellis St Oatlands NSW 2117",
    "addr:housenumber":"30",
    "addr:postcode":"2117",
    "addr:street":"Ellis St",
    "iso:country":"AU",
    "sg:address":"30 Ellis St",
    "sg:city":"Oatlands",
    "sg:classifiers":[
        {
            "category":"Real Estate",
            "subcategory":"Surveying",
            "type":"Services"
        }
    ],
    "sg:phone":"+61 414 504 070",
    "sg:postcode":"2117",
    "sg:province":"NSW",
    "sg:tags":[
        "surveyor",
        "quantity"
    ],
    "wof:name":"Wahbe Q.S.Services Pty Ltd",
    "wof:placetype":"venue"
},
  "geometry": {"coordinates":[151.024902344,-33.7918968201],"type":"Point"}
}