{
  "type": "Feature",
  "properties": {
    "iso:country":"AU",
    "sg:address":"15 Trent St",
    "sg:city":"Charlestown",
    "sg:classifiers":[
        {
            "category":"Building & Trades",
            "subcategory":"Construction",
            "type":"Services"
        }
    ],
    "sg:phone":"+61 2 4942 5504",
    "sg:postcode":"2290",
    "sg:province":"NSW",
    "sg:tags":[
        "concrete",
        "contractor"
    ],
    "wof:name":"Gizzi J & L Pty Ltd",
    "wof:placetype":"venue"
},
  "geometry": {"coordinates":[151.68513488799999,-32.9683074951],"type":"Point"}
}