{
  "type": "Feature",
  "properties": {
    "iso:country":"AU",
    "sg:address":"400 Portarlington Rd",
    "sg:city":"Moolap",
    "sg:classifiers":[
        {
            "category":"Retail",
            "subcategory":"Event Space",
            "type":"Services"
        }
    ],
    "sg:phone":"+61 3 5248 2535",
    "sg:postcode":"3221",
    "sg:province":"VIC",
    "sg:tags":[
        "venue",
        "reception",
        "wedding"
    ],
    "wof:name":"La Maiella",
    "wof:placetype":"venue"
},
  "geometry": {"coordinates":[144.42039500000001,-38.166019],"type":"Point"}
}