{
  "type": "Feature",
  "properties": {
    "iso:country":"AU",
    "sg:address":"6 Millennium Crt",
    "sg:city":"Silverwater",
    "sg:classifiers":[
        {
            "category":"Manufacturing",
            "subcategory":"Paper Products",
            "type":"Manufacturing & Wholesale Goods"
        }
    ],
    "sg:phone":"+61 2 9748 1842",
    "sg:postcode":"2128",
    "sg:province":"NSW",
    "sg:tags":[
        "building",
        "fibre",
        "cement"
    ],
    "wof:name":"Decor Systems",
    "wof:placetype":"venue"
},
  "geometry": {"coordinates":[151.04063415499999,-33.8330917358],"type":"Point"}
}