{
  "type": "Feature",
  "properties": {
    "addr:full":"4/ 394 Barkly Elwood VIC 3184",
    "addr:housenumber":"/ 394",
    "addr:postcode":"3184",
    "addr:street":"Barkly",
    "iso:country":"AU",
    "sg:address":"4/ 394 Barkly",
    "sg:city":"Elwood",
    "sg:classifiers":[
        {
            "category":"Professional",
            "subcategory":"Art Services",
            "type":"Services"
        }
    ],
    "sg:phone":"+61 3 9531 4112",
    "sg:postcode":"3184",
    "sg:province":"VIC",
    "sg:tags":[
        "interior",
        "decorator"
    ],
    "wof:name":"Sandi Bird & Associates",
    "wof:placetype":"venue"
},
  "geometry": {"coordinates":[144.97866821299999,-37.8811683655],"type":"Point"}
}