{
  "type": "Feature",
  "properties": {
    "iso:country":"AU",
    "sg:address":"36 Mason St",
    "sg:city":"Newport",
    "sg:classifiers":[
        {
            "category":"Health Services",
            "subcategory":"Dentist",
            "type":"Services"
        }
    ],
    "sg:phone":"+61 3 9391 9999",
    "sg:postcode":"3015",
    "sg:province":"VIC",
    "sg:tags":[
        "dental",
        "prosthetist"
    ],
    "wof:name":"Goran Sabotkoski",
    "wof:placetype":"venue"
},
  "geometry": {"coordinates":[144.879592895,-37.84192276],"type":"Point"}
}