{
  "type": "Feature",
  "properties": {
    "iso:country":"AU",
    "sg:address":"269 Bronte Rd",
    "sg:city":"Waverley",
    "sg:classifiers":[
        {
            "category":"Health Services",
            "subcategory":"Health Practitioner",
            "type":"Services"
        }
    ],
    "sg:phone":"+61 2 9369 5509",
    "sg:postcode":"2024",
    "sg:province":"NSW",
    "sg:tags":[
        "naturopath"
    ],
    "wof:name":"Sonsa Healing Space",
    "wof:placetype":"venue"
},
  "geometry": {"coordinates":[151.25437927199999,-33.9019775391],"type":"Point"}
}