{
  "type": "Feature",
  "properties": {
    "addr:full":"Shop 6, 59- 61 Queen St Busselton WA 6280",
    "addr:housenumber":"shop;59 61",
    "addr:postcode":"6280",
    "addr:street":"Queen St",
    "iso:country":"AU",
    "sg:address":"Shop 6, 59- 61 Queen St",
    "sg:city":"Busselton",
    "sg:classifiers":[
        {
            "category":"Fast Food",
            "type":"Food & Drink"
        }
    ],
    "sg:phone":"+61 8 9754 2066",
    "sg:postcode":"6280",
    "sg:province":"WA",
    "sg:tags":[
        "away",
        "take"
    ],
    "wof:name":"Busselton Pizza Bar",
    "wof:placetype":"venue"
},
  "geometry": {"coordinates":[115.34465789799999,-33.6497459412],"type":"Point"}
}