{
  "type": "Feature",
  "properties": {
    "addr:full":"8 Deakin Crt Shepparton VIC 3630",
    "addr:housenumber":"8",
    "addr:postcode":"3630",
    "addr:street":"Deakin Crt",
    "iso:country":"AU",
    "sg:address":"8 Deakin Crt",
    "sg:city":"Shepparton",
    "sg:classifiers":[
        {
            "category":"Education",
            "subcategory":"Special Training",
            "type":"Public Place"
        }
    ],
    "sg:phone":"+61 3 5821 8998",
    "sg:postcode":"3630",
    "sg:province":"VIC",
    "sg:tags":[
        "tuition-educational"
    ],
    "wof:name":"Tutorial Solutions",
    "wof:placetype":"venue"
},
  "geometry": {"coordinates":[145.37789917000001,-36.3564453125],"type":"Point"}
}