{
  "type": "Feature",
  "properties": {
    "addr:full":"31 Sylvan St Sylvania NSW 2224",
    "addr:housenumber":"31",
    "addr:postcode":"2224",
    "addr:street":"Sylvan St",
    "iso:country":"AU",
    "sg:address":"31 Sylvan St",
    "sg:city":"Sylvania",
    "sg:classifiers":[
        {
            "category":"Retail",
            "subcategory":"Auto Repair",
            "type":"Services"
        }
    ],
    "sg:phone":"+61 2 9522 3111",
    "sg:postcode":"2224",
    "sg:province":"NSW",
    "sg:tags":[
        "beater",
        "painter",
        "panel"
    ],
    "wof:name":"Glenn Eric Pty Ltd",
    "wof:placetype":"venue"
},
  "geometry": {"coordinates":[151.095245361,-34.0126876831],"type":"Point"}
}