{
  "type": "Feature",
  "properties": {
    "iso:country":"AU",
    "sg:address":"U24/ 1 Short St",
    "sg:city":"Chatswood",
    "sg:classifiers":[
        {
            "category":"Home & Garden",
            "subcategory":"Building Materials",
            "type":"Retail Goods"
        }
    ],
    "sg:phone":"+61 2 9417 0164",
    "sg:postcode":"2067",
    "sg:province":"NSW",
    "sg:tags":[
        "fencing"
    ],
    "wof:name":"Prestige Pool Fencing",
    "wof:placetype":"venue"
},
  "geometry": {"coordinates":[151.19781494099999,-33.7858695984],"type":"Point"}
}