{
  "type": "Feature",
  "properties": {
    "iso:country":"AU",
    "sg:address":"29 Unwins Bridge Rd",
    "sg:city":"St Peters",
    "sg:classifiers":[
        {
            "category":"Retail",
            "subcategory":"Auto Repair",
            "type":"Services"
        }
    ],
    "sg:phone":"+61 2 9557 0355",
    "sg:postcode":"2044",
    "sg:province":"NSW",
    "sg:tags":[
        "beater",
        "painter",
        "panel"
    ],
    "wof:name":"Topp Smash City",
    "wof:placetype":"venue"
},
  "geometry": {"coordinates":[151.168747,-33.914696],"type":"Point"}
}