{
  "type": "Feature",
  "properties": {
    "addr:full":"PO Box 249 Chirnside Park VIC 3116",
    "addr:postcode":"3116",
    "iso:country":"AU",
    "sg:address":"PO Box 249",
    "sg:city":"Chirnside Park",
    "sg:classifiers":[
        {
            "category":"Home & Garden",
            "subcategory":"Building Materials",
            "type":"Retail Goods"
        }
    ],
    "sg:phone":"+61 425 727 639",
    "sg:postcode":"3116",
    "sg:province":"VIC",
    "sg:tags":[
        "lawn",
        "cutting",
        "maintenance"
    ],
    "wof:name":"ACCENT GARDEN CARE",
    "wof:placetype":"venue"
},
  "geometry": {"coordinates":[145.31483459500001,-37.7397918701],"type":"Point"}
}