{
  "type": "Feature",
  "properties": {
    "addr:full":"Suite 2, 115 Nerang St Southport QLD 4215",
    "addr:housenumber":"115",
    "addr:postcode":"4215",
    "addr:street":"Nerang St",
    "iso:country":"AU",
    "sg:address":"Suite 2, 115 Nerang St",
    "sg:city":"Southport",
    "sg:classifiers":[
        {
            "category":"Health Services",
            "subcategory":"Health Practitioner",
            "type":"Services"
        }
    ],
    "sg:phone":"+61 7 5532 3288",
    "sg:postcode":"4215",
    "sg:province":"QLD",
    "sg:tags":[
        "physiotherapist"
    ],
    "wof:name":"Daniels, Adam",
    "wof:placetype":"venue"
},
  "geometry": {"coordinates":[153.4087677,-27.9703159332],"type":"Point"}
}