{
  "type": "Feature",
  "properties": {
    "iso:country":"AU",
    "sg:address":"PO Box 1093",
    "sg:city":"Batemans Bay",
    "sg:classifiers":[
        {
            "category":"Building & Trades",
            "subcategory":"Construction",
            "type":"Services"
        }
    ],
    "sg:phone":"+61 2 4478 1215",
    "sg:postcode":"2536",
    "sg:province":"NSW",
    "sg:tags":[
        "home",
        "air conditioning"
    ],
    "wof:name":"Airfridge Mobile Services",
    "wof:placetype":"venue"
},
  "geometry": {"coordinates":[150.17732238799999,-35.7084007263],"type":"Point"}
}