{
  "type": "Feature",
  "properties": {
    "iso:country":"AU",
    "sg:address":"5 Paul Crt",
    "sg:city":"Baulkham Hills",
    "sg:classifiers":[
        {
            "category":"Health Services",
            "subcategory":"Health Practitioner",
            "type":"Services"
        }
    ],
    "sg:phone":"+61 2 9688 7136",
    "sg:postcode":"2153",
    "sg:province":"NSW",
    "sg:tags":[
        "herbalist"
    ],
    "wof:name":"Sandra Walton",
    "wof:placetype":"venue"
},
  "geometry": {"coordinates":[150.98971557600001,-33.7690124512],"type":"Point"}
}