{
  "type": "Feature",
  "properties": {
    "addr:full":"15b Tooloon St Coonamble NSW 2829",
    "addr:housenumber":"15b",
    "addr:postcode":"2829",
    "addr:street":"Tooloon St",
    "iso:country":"AU",
    "sg:address":"15b Tooloon St",
    "sg:city":"Coonamble",
    "sg:classifiers":[
        {
            "category":"Professional",
            "subcategory":"Accounting & Tax Preparation",
            "type":"Services"
        }
    ],
    "sg:phone":"+61 2 6822 2427",
    "sg:postcode":"2829",
    "sg:province":"NSW",
    "sg:tags":[
        "accountant",
        "auditor"
    ],
    "wof:name":"Secombe & Co",
    "wof:placetype":"venue"
},
  "geometry": {"coordinates":[148.38771057100001,-30.951833725],"type":"Point"}
}