{
  "type": "Feature",
  "properties": {
    "iso:country":"AU",
    "sg:address":"26 Rooty Hill Rd South",
    "sg:city":"Rooty Hill",
    "sg:classifiers":[
        {
            "category":"Retail",
            "subcategory":"Veterinary Services",
            "type":"Services"
        }
    ],
    "sg:phone":"+61 2 9625 0499",
    "sg:postcode":"2766",
    "sg:province":"NSW",
    "sg:tags":[
        "surgeon"
    ],
    "wof:name":"Rooty Hill Veterinary Surgery",
    "wof:placetype":"venue"
},
  "geometry": {"coordinates":[150.844146728,-33.7722969055],"type":"Point"}
}