{
  "type": "Feature",
  "properties": {
    "addr:full":"15 Newbridge Rd Moorebank NSW 2170",
    "addr:housenumber":"15",
    "addr:postcode":"2170",
    "addr:street":"Newbridge Rd",
    "iso:country":"AU",
    "sg:address":"15 Newbridge Rd",
    "sg:city":"Moorebank",
    "sg:classifiers":[
        {
            "category":"Social Services",
            "subcategory":"Adult Care",
            "type":"Services"
        }
    ],
    "sg:phone":"+61 2 9822 2833",
    "sg:postcode":"2170",
    "sg:province":"NSW",
    "sg:tags":[
        "towing"
    ],
    "wof:name":"Western Suburbs Syndicate Towing (WSST)",
    "wof:placetype":"venue"
},
  "geometry": {"coordinates":[150.94085693400001,-33.9294128418],"type":"Point"}
}