{
  "type": "Feature",
  "properties": {
    "addr:full":"Shop 1 221 Queen St Melbourne VIC 3000",
    "addr:housenumber":"shop 1 221",
    "addr:postcode":"3000",
    "addr:street":"Queen St",
    "iso:country":"AU",
    "sg:address":"Shop 1 221 Queen St",
    "sg:city":"Melbourne",
    "sg:classifiers":[
        {
            "category":"Cafe",
            "type":"Food & Drink"
        }
    ],
    "sg:phone":"+61 3 9600 0384",
    "sg:postcode":"3000",
    "sg:province":"VIC",
    "wof:name":"Cafe X-Presso",
    "wof:placetype":"venue"
},
  "geometry": {"coordinates":[144.95985412600001,-37.813457489],"type":"Point"}
}