{
  "type": "Feature",
  "properties": {
    "iso:country":"AU",
    "sg:address":"PO Box 596",
    "sg:city":"Hamilton",
    "sg:classifiers":[
        {
            "category":"Building & Trades",
            "subcategory":"Landscaping Services",
            "type":"Services"
        }
    ],
    "sg:phone":"+61 2 4969 8444",
    "sg:postcode":"2303",
    "sg:province":"NSW",
    "sg:tags":[
        "consultant"
    ],
    "wof:name":"Inspecta Homes",
    "wof:placetype":"venue"
},
  "geometry": {"coordinates":[151.746994,-32.923489],"type":"Point"}
}