{
  "type": "Feature",
  "properties": {
    "addr:full":"Shop 1/ 495 Pacific Hwy Belmont NSW 2280",
    "addr:housenumber":"shop 1 / 495",
    "addr:postcode":"2280",
    "addr:street":"Pacific Hwy",
    "iso:country":"AU",
    "sg:address":"Shop 1/ 495 Pacific Hwy",
    "sg:city":"Belmont",
    "sg:classifiers":[
        {
            "category":"Shopping",
            "subcategory":"Discount & Variety Stores",
            "type":"Retail Goods"
        }
    ],
    "sg:phone":"+61 2 4947 9000",
    "sg:postcode":"2280",
    "sg:province":"NSW",
    "sg:tags":[
        "shop",
        "adult"
    ],
    "wof:name":"Nauti & Nice Adult Megastores",
    "wof:placetype":"venue"
},
  "geometry": {"coordinates":[151.66107177699999,-33.0321273804],"type":"Point"}
}