{
  "type": "Feature",
  "properties": {
    "addr:full":"1090 Kingsford Smith Drv Eagle Farm QLD 4009",
    "addr:housenumber":"1090",
    "addr:postcode":"4009",
    "addr:street":"Kingsford Smith Drv",
    "iso:country":"AU",
    "sg:address":"1090 Kingsford Smith Drv",
    "sg:city":"Eagle Farm",
    "sg:classifiers":[
        {
            "category":"Wholesale",
            "subcategory":"Furniture",
            "type":"Manufacturing & Wholesale Goods"
        }
    ],
    "sg:phone":"+61 7 3868 1422",
    "sg:postcode":"4009",
    "sg:province":"QLD",
    "sg:tags":[
        "wholesaler",
        "mfrs"
    ],
    "sg:website":"http://www.canecargo.com.au",
    "wof:name":"Cane Cargo",
    "wof:placetype":"venue"
},
  "geometry": {"coordinates":[153.09588623100001,-27.4290485382],"type":"Point"}
}