{
  "type": "Feature",
  "properties": {
    "addr:full":"623 Darling St Rozelle NSW 2039",
    "addr:housenumber":"623",
    "addr:postcode":"2039",
    "addr:street":"Darling St",
    "iso:country":"AU",
    "sg:address":"623 Darling St",
    "sg:city":"Rozelle",
    "sg:classifiers":[
        {
            "category":"Personal",
            "subcategory":"Beauty Salon",
            "type":"Services"
        }
    ],
    "sg:phone":"+61 2 9818 2687",
    "sg:postcode":"2039",
    "sg:province":"NSW",
    "sg:tags":[
        "hairdresser"
    ],
    "wof:name":"Tom's Hairdressing For Men",
    "wof:placetype":"venue"
},
  "geometry": {"coordinates":[151.17123413100001,-33.8615608215],"type":"Point"}
}