{
  "type": "Feature",
  "properties": {
    "addr:full":"162 Dunmore St Wentworthville NSW 2145",
    "addr:housenumber":"162",
    "addr:postcode":"2145",
    "addr:street":"Dunmore St",
    "iso:country":"AU",
    "sg:address":"162 Dunmore St",
    "sg:city":"Wentworthville",
    "sg:classifiers":[
        {
            "category":"Mining & Drilling",
            "type":"Manufacturing & Wholesale Goods"
        }
    ],
    "sg:phone":"+61 2 9636 6398",
    "sg:postcode":"2145",
    "sg:province":"NSW",
    "sg:tags":[
        "concrete",
        "breaking",
        "grinding",
        "sawing"
    ],
    "wof:name":"Ace of Diamonds",
    "wof:placetype":"venue"
},
  "geometry": {"coordinates":[150.96333313,-33.8059196472],"type":"Point"}
}