{
  "type": "Feature",
  "properties": {
    "addr:full":"85 Bedford Rd Ringwood East VIC 3135",
    "addr:housenumber":"85",
    "addr:postcode":"3135",
    "addr:street":"Bedford Rd",
    "iso:country":"AU",
    "sg:address":"85 Bedford Rd",
    "sg:city":"Ringwood East",
    "sg:classifiers":[
        {
            "category":"Personal",
            "subcategory":"Beauty Salon",
            "type":"Services"
        }
    ],
    "sg:phone":"+61 3 9870 7743",
    "sg:postcode":"3135",
    "sg:province":"VIC",
    "sg:tags":[
        "wig",
        "hairpiece"
    ],
    "wof:name":"Head Complements",
    "wof:placetype":"venue"
},
  "geometry": {"coordinates":[145.243286133,-37.8187103271],"type":"Point"}
}