{
  "type": "Feature",
  "properties": {
    "iso:country":"AU",
    "sg:address":"19 Bourke St",
    "sg:city":"Woolloongabba",
    "sg:classifiers":[
        {
            "category":"Education",
            "subcategory":"Dance Studio",
            "type":"Public Place"
        }
    ],
    "sg:phone":"+61 1300 790 837",
    "sg:postcode":"4102",
    "sg:province":"QLD",
    "sg:tags":[
        "venue",
        "tuition"
    ],
    "wof:name":"Smooth Latin Groove",
    "wof:placetype":"venue"
},
  "geometry": {"coordinates":[153.03208923299999,-27.4943180084],"type":"Point"}
}