{
  "type": "Feature",
  "properties": {
    "iso:country":"AU",
    "sg:address":"54 Sandy Bay Rd",
    "sg:city":"Battery Point",
    "sg:classifiers":[
        {
            "category":"Real Estate",
            "subcategory":"Real Estate Agent",
            "type":"Services"
        }
    ],
    "sg:phone":"+61 419 138 633",
    "sg:postcode":"7004",
    "sg:province":"TAS",
    "wof:name":"Hobden Michael",
    "wof:placetype":"venue"
},
  "geometry": {"coordinates":[147.329055786,-42.890537262],"type":"Point"}
}