{
  "type": "Feature",
  "properties": {
    "iso:country":"AU",
    "sg:address":"31 Ellendon St",
    "sg:city":"Bungendore",
    "sg:classifiers":[
        {
            "category":"Cafe",
            "type":"Food & Drink"
        }
    ],
    "sg:phone":"+61 2 6238 0700",
    "sg:postcode":"2621",
    "sg:province":"NSW",
    "wof:name":"Bardy's Cafe",
    "wof:placetype":"venue"
},
  "geometry": {"coordinates":[149.44061279300001,-35.254524231],"type":"Point"}
}