{
  "type": "Feature",
  "properties": {
    "addr:full":"38 Roberts St Jannali NSW 2226",
    "addr:housenumber":"38",
    "addr:postcode":"2226",
    "addr:street":"Roberts St",
    "iso:country":"AU",
    "sg:address":"38 Roberts St",
    "sg:city":"Jannali",
    "sg:classifiers":[
        {
            "category":"Social Services",
            "subcategory":"Child Care",
            "type":"Services"
        }
    ],
    "sg:phone":"+61 2 9589 0199",
    "sg:postcode":"2226",
    "sg:province":"NSW",
    "wof:name":"Jannali Kinder Care 2",
    "wof:placetype":"venue"
},
  "geometry": {"coordinates":[151.06617736800001,-34.0194473267],"type":"Point"}
}