{
  "type": "Feature",
  "properties": {
    "addr:full":"541 Old Hawkesbury Rd Vineyard NSW 2765",
    "addr:housenumber":"541",
    "addr:postcode":"2765",
    "addr:street":"Old Hawkesbury Rd",
    "iso:country":"AU",
    "sg:address":"541 Old Hawkesbury Rd",
    "sg:city":"Vineyard",
    "sg:classifiers":[
        {
            "category":"Building & Trades",
            "subcategory":"Equipment Rental",
            "type":"Services"
        }
    ],
    "sg:phone":"+61 2 9627 5486",
    "sg:postcode":"2765",
    "sg:province":"NSW",
    "sg:tags":[
        "saw"
    ],
    "wof:name":"Henry Bros. Saws Pty Ltd",
    "wof:placetype":"venue"
},
  "geometry": {"coordinates":[150.859375,-33.6439361572],"type":"Point"}
}