{
  "type": "Feature",
  "properties": {
    "addr:full":"22 Cumberland Drv Alexandra Hills QLD 4161",
    "addr:housenumber":"22",
    "addr:postcode":"4161",
    "addr:street":"Cumberland Drv",
    "iso:country":"AU",
    "sg:address":"22 Cumberland Drv",
    "sg:city":"Alexandra Hills",
    "sg:classifiers":[
        {
            "category":"Building & Trades",
            "subcategory":"Construction",
            "type":"Services"
        }
    ],
    "sg:phone":"+61 7 3824 6420",
    "sg:postcode":"4161",
    "sg:province":"QLD",
    "sg:tags":[
        "joiner",
        "carpenter"
    ],
    "wof:name":"Tissington H P",
    "wof:placetype":"venue"
},
  "geometry": {"coordinates":[153.21975707999999,-27.5273933411],"type":"Point"}
}