{
  "type": "Feature",
  "properties": {
    "addr:full":"30 Kalyan Ave Bradbury NSW 2560",
    "addr:housenumber":"30",
    "addr:postcode":"2560",
    "addr:street":"Kalyan Ave",
    "iso:country":"AU",
    "sg:address":"30 Kalyan Ave",
    "sg:city":"Bradbury",
    "sg:classifiers":[
        {
            "category":"Health Services",
            "subcategory":"Health Practitioner",
            "type":"Services"
        }
    ],
    "sg:phone":"+61 408 411 804",
    "sg:postcode":"2560",
    "sg:province":"NSW",
    "sg:tags":[
        "psychologist"
    ],
    "wof:name":"Maddern Robyn Dr",
    "wof:placetype":"venue"
},
  "geometry": {"coordinates":[150.81477355999999,-34.0955848694],"type":"Point"}
}