{
  "type": "Feature",
  "properties": {
    "addr:full":"43 Dunstan St Clayton VIC 3168",
    "addr:housenumber":"43",
    "addr:postcode":"3168",
    "addr:street":"Dunstan St",
    "iso:country":"AU",
    "sg:address":"43 Dunstan St",
    "sg:city":"Clayton",
    "sg:classifiers":[
        {
            "category":"Personal",
            "subcategory":"Beauty Salon",
            "type":"Services"
        }
    ],
    "sg:phone":"+61 3 9544 9480",
    "sg:postcode":"3168",
    "sg:province":"VIC",
    "sg:tags":[
        "hairdresser"
    ],
    "wof:name":"Hair Revolution",
    "wof:placetype":"venue"
},
  "geometry": {"coordinates":[145.119384766,-37.9252738953],"type":"Point"}
}