{
  "type": "Feature",
  "properties": {
    "iso:country":"AU",
    "sg:address":"398 Great Eastern Hwy",
    "sg:city":"Redcliffe",
    "sg:classifiers":[
        {
            "category":"Professional",
            "subcategory":"Accounting & Tax Preparation",
            "type":"Services"
        }
    ],
    "sg:phone":"+61 8 9475 2100",
    "sg:postcode":"6104",
    "sg:province":"WA",
    "sg:tags":[
        "accountant",
        "auditor"
    ],
    "wof:name":"Midland Secretarial Services",
    "wof:placetype":"venue"
},
  "geometry": {"coordinates":[115.94539642300001,-31.9294681549],"type":"Point"}
}