{
  "type": "Feature",
  "properties": {
    "iso:country":"AU",
    "sg:address":"8 Woodsame St",
    "sg:city":"Mt Lawley",
    "sg:classifiers":[
        {
            "category":"Health Services",
            "subcategory":"Health Practitioner",
            "type":"Services"
        }
    ],
    "sg:phone":"+61 8 9271 5481",
    "sg:postcode":"6050",
    "sg:province":"WA",
    "sg:tags":[
        "alternative"
    ],
    "wof:name":"Lifestyles",
    "wof:placetype":"venue"
},
  "geometry": {"coordinates":[115.865638733,-31.9263896942],"type":"Point"}
}