{
  "type": "Feature",
  "properties": {
    "iso:country":"AU",
    "sg:address":"501-505 Sherwood Rd",
    "sg:city":"Rocklea",
    "sg:classifiers":[
        {
            "category":"Professional",
            "type":"Services"
        }
    ],
    "sg:phone":"+61 7 3278 4933",
    "sg:postcode":"4106",
    "sg:province":"QLD",
    "sg:tags":[
        "transport"
    ],
    "wof:name":"Bill Nortons Transport Pty Ltd",
    "wof:placetype":"venue"
},
  "geometry": {"coordinates":[152.98794555699999,-27.534116745],"type":"Point"}
}