{
  "type": "Feature",
  "properties": {
    "addr:full":"Clinton Rd Maitland SA 5573",
    "addr:postcode":"5573",
    "addr:street":"Clinton Rd",
    "iso:country":"AU",
    "sg:address":"Clinton Rd",
    "sg:city":"Maitland",
    "sg:classifiers":[
        {
            "category":"Farming",
            "subcategory":"Farm",
            "type":"Manufacturing & Wholesale Goods"
        }
    ],
    "sg:phone":"+61 8 8832 2964",
    "sg:postcode":"5573",
    "sg:province":"SA",
    "sg:tags":[
        "farmer"
    ],
    "wof:name":"Smith Jamie & Helen",
    "wof:placetype":"venue"
},
  "geometry": {"coordinates":[137.675292969,-34.3698692322],"type":"Point"}
}