{
  "type": "Feature",
  "properties": {
    "addr:full":"20 Anglo Rd Campsie NSW 2194",
    "addr:housenumber":"20",
    "addr:postcode":"2194",
    "addr:street":"Anglo Rd",
    "iso:country":"AU",
    "sg:address":"20 Anglo Rd",
    "sg:city":"Campsie",
    "sg:classifiers":[
        {
            "category":"Food & Beverages",
            "subcategory":"Specialty",
            "type":"Retail Goods"
        }
    ],
    "sg:phone":"+61 2 9789 4006",
    "sg:postcode":"2194",
    "sg:province":"NSW",
    "sg:tags":[
        "product",
        "health"
    ],
    "wof:name":"Juicy Delight",
    "wof:placetype":"venue"
},
  "geometry": {"coordinates":[151.10287500000001,-33.911427],"type":"Point"}
}