{
  "type": "Feature",
  "properties": {
    "addr:full":"Beaudesrt Rd Calamvale QLD 4116",
    "addr:postcode":"4116",
    "addr:street":"Beaudesrt Rd",
    "iso:country":"AU",
    "sg:address":"Beaudesrt Rd",
    "sg:city":"Calamvale",
    "sg:classifiers":[
        {
            "category":"Real Estate",
            "subcategory":"Real Estate Agent",
            "type":"Services"
        }
    ],
    "sg:phone":"+61 7 3272 3722",
    "sg:postcode":"4116",
    "sg:province":"QLD",
    "wof:name":"Calamvale Realty",
    "wof:placetype":"venue"
},
  "geometry": {"coordinates":[153.049438477,-27.6217956543],"type":"Point"}
}