{
  "type": "Feature",
  "properties": {
    "addr:full":"150 Edenbrooke Drv Seventeen Mile Rocks QLD 4073",
    "addr:housenumber":"150",
    "addr:postcode":"4073",
    "addr:street":"Edenbrooke Drv",
    "iso:country":"AU",
    "sg:address":"150 Edenbrooke Drv",
    "sg:city":"Seventeen Mile Rocks",
    "sg:classifiers":[
        {
            "category":"Real Estate",
            "subcategory":"Developer",
            "type":"Services"
        }
    ],
    "sg:phone":"+61 7 3712 0566",
    "sg:postcode":"4073",
    "sg:province":"QLD",
    "sg:tags":[
        "development"
    ],
    "wof:name":"Urban Pacific Limited",
    "wof:placetype":"venue"
},
  "geometry": {"coordinates":[152.95472717300001,-27.5496616364],"type":"Point"}
}