{
  "type": "Feature",
  "properties": {
    "addr:full":"Unit 12/ 429 The Boulevard Kirrawee NSW 2232",
    "addr:housenumber":"/ 429",
    "addr:postcode":"2232",
    "addr:street":"The Boulevard",
    "iso:country":"AU",
    "sg:address":"Unit 12/ 429",
    "sg:city":"The Boulevard Kirrawee",
    "sg:classifiers":[
        {
            "category":"Autos & Motor Vehicles",
            "subcategory":"Auto Supplies",
            "type":"Retail Goods"
        }
    ],
    "sg:phone":"+61 2 9545 1841",
    "sg:postcode":"2232",
    "sg:province":"NSW",
    "sg:tags":[
        "transmission",
        "equipment",
        "power"
    ],
    "wof:name":"Kelmar-Benzler",
    "wof:placetype":"venue"
},
  "geometry": {"coordinates":[151.089752197,-34.0134506226],"type":"Point"}
}