{
  "type": "Feature",
  "properties": {
    "iso:country":"AU",
    "sg:address":"Unit 12, 20 George St",
    "sg:city":"Sandringham",
    "sg:classifiers":[
        {
            "category":"Retail",
            "subcategory":"Auto Repair",
            "type":"Services"
        }
    ],
    "sg:phone":"+61 3 9597 0387",
    "sg:postcode":"3191",
    "sg:province":"VIC",
    "sg:tags":[
        "engine",
        "reconditioning"
    ],
    "wof:name":"Woodys Engine Services",
    "wof:placetype":"venue"
},
  "geometry": {"coordinates":[145.02862548799999,-37.9613723755],"type":"Point"}
}