{
  "type": "Feature",
  "properties": {
    "addr:full":"112 Webster St Bongaree QLD 4507",
    "addr:housenumber":"112",
    "addr:postcode":"4507",
    "addr:street":"Webster St",
    "iso:country":"AU",
    "sg:address":"112 Webster St",
    "sg:city":"Bongaree",
    "sg:classifiers":[
        {
            "category":"Home & Garden",
            "subcategory":"Building Materials",
            "type":"Retail Goods"
        }
    ],
    "sg:phone":"+61 7 3410 1217",
    "sg:postcode":"4507",
    "sg:province":"QLD",
    "sg:tags":[
        "lawn",
        "cutting",
        "maintenance"
    ],
    "wof:name":"BC Lawnmowing & Gardening",
    "wof:placetype":"venue"
},
  "geometry": {"coordinates":[153.17036438,-27.0835895538],"type":"Point"}
}