{
  "type": "Feature",
  "properties": {
    "addr:full":"10 Della Torre Rd Moe VIC 3825",
    "addr:postcode":"3825",
    "addr:street":"10 Della Torre Rd",
    "iso:country":"AU",
    "sg:address":"10 Della Torre Rd",
    "sg:city":"Moe",
    "sg:classifiers":[
        {
            "category":"Retail",
            "subcategory":"Auto Repair",
            "type":"Services"
        }
    ],
    "sg:phone":"+61 3 5126 1116",
    "sg:postcode":"3825",
    "sg:province":"VIC",
    "sg:tags":[
        "repairer",
        "motor",
        "engineer"
    ],
    "wof:name":"Moe Mechanical & Alignment Centre",
    "wof:placetype":"venue"
},
  "geometry": {"coordinates":[146.26054400000001,-38.16761],"type":"Point"}
}