{
  "type": "Feature",
  "properties": {
    "addr:full":"693 Old Princes Hwy Sutherland NSW 2232",
    "addr:housenumber":"693",
    "addr:postcode":"2232",
    "addr:street":"Old Princes Hwy",
    "iso:country":"AU",
    "sg:address":"693 Old Princes Hwy",
    "sg:city":"Sutherland",
    "sg:classifiers":[
        {
            "category":"Manufacturing",
            "subcategory":"Motor Vehicles & Parts",
            "type":"Manufacturing & Wholesale Goods"
        }
    ],
    "sg:phone":"+61 2 9542 1005",
    "sg:postcode":"2232",
    "sg:province":"NSW",
    "sg:tags":[
        "replacement"
    ],
    "wof:name":"C & N Radiators",
    "wof:placetype":"venue"
},
  "geometry": {"coordinates":[151.05880737300001,-34.0299224854],"type":"Point"}
}