{
  "type": "Feature",
  "properties": {
    "addr:full":"2/ 110 Aumuller St Cairns QLD 4870",
    "addr:housenumber":"/ 110",
    "addr:postcode":"4870",
    "addr:street":"Aumuller St",
    "iso:country":"AU",
    "sg:address":"2/ 110 Aumuller St",
    "sg:city":"Cairns",
    "sg:classifiers":[
        {
            "category":"Professional",
            "subcategory":"Engineering",
            "type":"Services"
        }
    ],
    "sg:phone":"+61 7 4035 1544",
    "sg:postcode":"4870",
    "sg:province":"QLD",
    "sg:tags":[
        "consulting",
        "engineer"
    ],
    "wof:name":"BMD Consulting Pty Ltd",
    "wof:placetype":"venue"
},
  "geometry": {"coordinates":[145.764129639,-16.9372081757],"type":"Point"}
}