{
  "type": "Feature",
  "properties": {
    "addr:full":"11 Ray St Carseldine QLD 4034",
    "addr:housenumber":"11",
    "addr:postcode":"4034",
    "addr:street":"Ray St",
    "iso:country":"AU",
    "sg:address":"11 Ray St",
    "sg:city":"Carseldine",
    "sg:classifiers":[
        {
            "category":"Shopping",
            "subcategory":"Computers & Home Electronics",
            "type":"Retail Goods"
        }
    ],
    "sg:phone":"+61 7 3863 0500",
    "sg:postcode":"4034",
    "sg:province":"QLD",
    "sg:tags":[
        "equipment",
        "supply"
    ],
    "wof:name":"Saitch Technology",
    "wof:placetype":"venue"
},
  "geometry": {"coordinates":[153.02285800000001,-27.342072],"type":"Point"}
}