{
  "type": "Feature",
  "properties": {
    "addr:full":"37- 45 Webb St Port Adelaide SA 5015",
    "addr:housenumber":"45",
    "addr:postcode":"5015",
    "addr:street":"Webb St",
    "iso:country":"AU",
    "sg:address":"37- 45 Webb St",
    "sg:city":"Port Adelaide",
    "sg:classifiers":[
        {
            "category":"Manufacturing",
            "subcategory":"Metals",
            "type":"Manufacturing & Wholesale Goods"
        }
    ],
    "sg:phone":"+61 8 8447 7022",
    "sg:postcode":"5015",
    "sg:province":"SA",
    "sg:tags":[
        "steel",
        "fabricator",
        "mfrs"
    ],
    "wof:name":"Lincoln Engineers Pty Ltd",
    "wof:placetype":"venue"
},
  "geometry": {"coordinates":[138.50584411599999,-34.8564033508],"type":"Point"}
}