{
  "type": "Feature",
  "properties": {
    "iso:country":"AU",
    "sg:address":"PO Box 376",
    "sg:city":"Scarborough",
    "sg:classifiers":[
        {
            "category":"Coffee & Tea",
            "type":"Food & Drink"
        }
    ],
    "sg:phone":"+61 8 9401 3287",
    "sg:postcode":"6019",
    "sg:province":"WA",
    "sg:tags":[
        "kayak",
        "canoe"
    ],
    "wof:name":"Western PaddleSports",
    "wof:placetype":"venue"
},
  "geometry": {"coordinates":[115.761146545,-31.8980808258],"type":"Point"}
}