{
  "type": "Feature",
  "properties": {
    "iso:country":"AU",
    "sg:address":"83 Red Hill Rd",
    "sg:city":"Red Hill",
    "sg:classifiers":[
        {
            "category":"Personal",
            "subcategory":"Massage",
            "type":"Services"
        }
    ],
    "sg:phone":"+61 3 5989 2707",
    "sg:postcode":"3937",
    "sg:province":"VIC",
    "sg:tags":[
        "therapy"
    ],
    "wof:name":"Lee-Anne Allen",
    "wof:placetype":"venue"
},
  "geometry": {"coordinates":[145.02865600600001,-38.3791618347],"type":"Point"}
}