{
  "type": "Feature",
  "properties": {
    "iso:country":"AU",
    "sg:address":"3/ 117 Foster St",
    "sg:city":"Leichhardt",
    "sg:classifiers":[
        {
            "category":"Professional",
            "subcategory":"Management & Consulting",
            "type":"Services"
        }
    ],
    "sg:phone":"+61 2 8021 1015",
    "sg:postcode":"2040",
    "sg:province":"NSW",
    "sg:tags":[
        "consultant",
        "economic"
    ],
    "wof:name":"Thema Consulting Pty Ltd",
    "wof:placetype":"venue"
},
  "geometry": {"coordinates":[151.14764400000001,-33.882866],"type":"Point"}
}