{
  "type": "Feature",
  "properties": {
    "addr:full":"1 Allan St Rydalmere NSW 2116",
    "addr:housenumber":"1",
    "addr:postcode":"2116",
    "addr:street":"Allan St",
    "iso:country":"AU",
    "sg:address":"1 Allan St",
    "sg:city":"Rydalmere",
    "sg:classifiers":[
        {
            "category":"Utilities",
            "subcategory":"Water",
            "type":"Services"
        }
    ],
    "sg:phone":"+61 13 10 31",
    "sg:postcode":"2116",
    "sg:province":"NSW",
    "sg:tags":[
        "hot",
        "system"
    ],
    "wof:name":"Raypak Pool Heater Service",
    "wof:placetype":"venue"
},
  "geometry": {"coordinates":[151.038619995,-33.8698959351],"type":"Point"}
}