{
  "type": "Feature",
  "properties": {
    "iso:country":"AU",
    "sg:address":"26 Stansbury Rd",
    "sg:city":"Yorketown",
    "sg:classifiers":[
        {
            "category":"Utilities",
            "subcategory":"Electric",
            "type":"Services"
        }
    ],
    "sg:phone":"+61 412 288 387",
    "sg:postcode":"5576",
    "sg:province":"SA",
    "sg:tags":[
        "electrical",
        "contractor"
    ],
    "wof:name":"Simon Anderson Electrical",
    "wof:placetype":"venue"
},
  "geometry": {"coordinates":[137.60867309599999,-35.0186233521],"type":"Point"}
}