{
  "type": "Feature",
  "properties": {
    "addr:full":"PO Box 37 Milsons Point NSW 1565",
    "addr:postcode":"1565",
    "iso:country":"AU",
    "sg:address":"PO Box 37",
    "sg:city":"Milsons Point",
    "sg:classifiers":[
        {
            "category":"Communications",
            "type":"Services"
        }
    ],
    "sg:phone":"+61 2 9954 5784",
    "sg:postcode":"1565",
    "sg:province":"NSW",
    "sg:tags":[
        "translation"
    ],
    "wof:name":"Bob Desiatnik",
    "wof:placetype":"venue"
},
  "geometry": {"coordinates":[151.21270751899999,-33.8462715149],"type":"Point"}
}