{
  "type": "Feature",
  "properties": {
    "iso:country":"AU",
    "sg:address":"175 Dampier Ave",
    "sg:city":"Kallaroo",
    "sg:classifiers":[
        {
            "category":"Social Services",
            "subcategory":"Retirement Home",
            "type":"Services"
        }
    ],
    "sg:phone":"+61 8 9307 1211",
    "sg:postcode":"6025",
    "sg:province":"WA",
    "sg:tags":[
        "village"
    ],
    "wof:name":"St Ives Development Pty Ltd",
    "wof:placetype":"venue"
},
  "geometry": {"coordinates":[115.746101379,-31.7923641205],"type":"Point"}
}