{
  "type": "Feature",
  "properties": {
    "addr:full":"Ste 2 Lvl 1 159 Northumberland St Liverpool NSW 2170",
    "addr:housenumber":"159",
    "addr:postcode":"2170",
    "addr:street":"Northumberland St",
    "iso:country":"AU",
    "sg:address":"Ste 2 Lvl 1 159 Northumberland St",
    "sg:city":"Liverpool",
    "sg:classifiers":[
        {
            "category":"Health Services",
            "subcategory":"Chiropractor",
            "type":"Services"
        }
    ],
    "sg:phone":"+61 2 9601 3859",
    "sg:postcode":"2170",
    "sg:province":"NSW",
    "wof:name":"Hennig Shane",
    "wof:placetype":"venue"
},
  "geometry": {"coordinates":[150.922531128,-33.9212760925],"type":"Point"}
}