{
  "type": "Feature",
  "properties": {
    "addr:full":"Mona Vale Rd Terrey Hills NSW 2084",
    "addr:postcode":"2084",
    "addr:street":"Mona Vale Rd",
    "iso:country":"AU",
    "sg:address":"Mona Vale Rd",
    "sg:city":"Terrey Hills",
    "sg:classifiers":[
        {
            "category":"Farming",
            "subcategory":"Farm & Veterinary Services",
            "type":"Manufacturing & Wholesale Goods"
        }
    ],
    "sg:phone":"+61 2 9450 2888",
    "sg:postcode":"2084",
    "sg:province":"NSW",
    "sg:tags":[
        "irrigation",
        "reticulation",
        "system"
    ],
    "wof:name":"Sprinkler City Controlled Irrigation Systems",
    "wof:placetype":"venue"
},
  "geometry": {"coordinates":[151.23101806599999,-33.68384552],"type":"Point"}
}