{
  "type": "Feature",
  "properties": {
    "addr:full":"24 Station Rd Indooroopilly QLD 4068",
    "addr:housenumber":"24",
    "addr:postcode":"4068",
    "addr:street":"Station Rd",
    "iso:country":"AU",
    "sg:address":"24 Station Rd",
    "sg:city":"Indooroopilly",
    "sg:classifiers":[
        {
            "category":"Health Services",
            "subcategory":"Dentist",
            "type":"Services"
        }
    ],
    "sg:phone":"+61 7 3878 3522",
    "sg:postcode":"4068",
    "sg:province":"QLD",
    "sg:tags":[
        "qld",
        "orthodontist"
    ],
    "wof:name":"Mewing John R Orthodontist",
    "wof:placetype":"venue"
},
  "geometry": {"coordinates":[152.974517822,-27.502204895],"type":"Point"}
}