{
  "type": "Feature",
  "properties": {
    "addr:full":"60 Zipfs Rd Redland Bay QLD 4165",
    "addr:housenumber":"60",
    "addr:postcode":"4165",
    "addr:street":"Zipfs Rd",
    "iso:country":"AU",
    "sg:address":"60 Zipfs Rd",
    "sg:city":"Redland Bay",
    "sg:classifiers":[
        {
            "category":"Professional",
            "subcategory":"Engineering",
            "type":"Services"
        }
    ],
    "sg:phone":"+61 403 040 000",
    "sg:postcode":"4165",
    "sg:province":"QLD",
    "sg:tags":[
        "engineer",
        "structural"
    ],
    "wof:name":"Carbon Fibre Technologies",
    "wof:placetype":"venue"
},
  "geometry": {"coordinates":[153.307373047,-27.6927280426],"type":"Point"}
}