{
  "type": "Feature",
  "properties": {
    "addr:full":"Cnr Westall & Centre Rds Clayton VIC 3168",
    "addr:postcode":"3168",
    "addr:street":"Cnr",
    "iso:country":"AU",
    "sg:address":"Cnr Westall & Centre Rds",
    "sg:city":"Clayton",
    "sg:classifiers":[
        {
            "category":"Wholesale",
            "subcategory":"Vending Machines",
            "type":"Manufacturing & Wholesale Goods"
        }
    ],
    "sg:phone":"+61 3 9544 8900",
    "sg:postcode":"3168",
    "sg:province":"VIC",
    "sg:tags":[
        "engraving",
        "accessory"
    ],
    "wof:name":"Gravograph New Hermes Australia",
    "wof:placetype":"venue"
},
  "geometry": {"coordinates":[145.12937927199999,-37.9023933411],"type":"Point"}
}