{
  "type": "Feature",
  "properties": {
    "addr:full":"Cnr Chelmsford Drv & Metford Rd Metford NSW 2323",
    "addr:postcode":"2323",
    "addr:street":"Cnr Chelmsford Drv & Metford Rd",
    "iso:country":"AU",
    "sg:address":"Cnr Chelmsford Drv & Metford Rd",
    "sg:city":"Metford",
    "sg:classifiers":[
        {
            "category":"Health Services",
            "subcategory":"Health Practitioner",
            "type":"Services"
        }
    ],
    "sg:phone":"+61 2 4933 1088",
    "sg:postcode":"2323",
    "sg:province":"NSW",
    "sg:tags":[
        "alternative"
    ],
    "wof:name":"Maitland Natural Therapy Centre",
    "wof:placetype":"venue"
},
  "geometry": {"coordinates":[151.60093689000001,-32.7607345581],"type":"Point"}
}