{
  "type": "Feature",
  "properties": {
    "iso:country":"AU",
    "sg:address":"PO Box 110",
    "sg:city":"Chelsea",
    "sg:classifiers":[
        {
            "category":"Home & Garden",
            "subcategory":"Household Appliances",
            "type":"Retail Goods"
        }
    ],
    "sg:phone":"+61 418 540 560",
    "sg:postcode":"3196",
    "sg:province":"VIC",
    "sg:tags":[
        "equipment",
        "gas"
    ],
    "wof:name":"Hi Tech Gas & Air Conditioning Service Pty Ltd",
    "wof:placetype":"venue"
},
  "geometry": {"coordinates":[145.113937378,-38.0481185913],"type":"Point"}
}