{
  "type": "Feature",
  "properties": {
    "addr:full":"63 Princes Hwy St Peters NSW 2044",
    "addr:housenumber":"63",
    "addr:postcode":"2044",
    "addr:street":"Princes Hwy",
    "iso:country":"AU",
    "sg:address":"63 Princes Hwy",
    "sg:city":"St Peters",
    "sg:classifiers":[
        {
            "category":"Sports & Exercise",
            "subcategory":"Playing Field",
            "type":"Entertainment"
        }
    ],
    "sg:phone":"+61 2 9557 2251",
    "sg:postcode":"2044",
    "sg:province":"NSW",
    "sg:tags":[
        "repair",
        "walking",
        "retail",
        "umbrella",
        "stick"
    ],
    "wof:name":"Architectural Shades",
    "wof:placetype":"venue"
},
  "geometry": {"coordinates":[151.180206,-33.910591],"type":"Point"}
}