{
  "type": "Feature",
  "properties": {
    "iso:country":"AU",
    "sg:address":"16 Punt Rd",
    "sg:city":"Gladesville",
    "sg:classifiers":[
        {
            "category":"Travel",
            "subcategory":"Hostel",
            "type":"Entertainment"
        }
    ],
    "sg:phone":"+61 2 9817 0722",
    "sg:postcode":"2111",
    "sg:province":"NSW",
    "sg:tags":[
        "home"
    ],
    "wof:name":"Warrigal Care",
    "wof:placetype":"venue"
},
  "geometry": {"coordinates":[151.12826538100001,-33.8373794556],"type":"Point"}
}