{
  "type": "Feature",
  "properties": {
    "iso:country":"AU",
    "sg:address":"776 Hunter St",
    "sg:city":"Newcastle West",
    "sg:classifiers":[
        {
            "category":"Shopping",
            "subcategory":"Computers & Home Electronics",
            "type":"Retail Goods"
        }
    ],
    "sg:phone":"+61 2 4969 4969",
    "sg:postcode":"2302",
    "sg:province":"NSW",
    "sg:tags":[
        "equipment",
        "supply"
    ],
    "wof:name":"Hunter Business Equipment",
    "wof:placetype":"venue"
},
  "geometry": {"coordinates":[151.760956,-32.925739],"type":"Point"}
}