{
  "type": "Feature",
  "properties": {
    "iso:country":"AU",
    "sg:address":"985 Mate St",
    "sg:city":"Albury North",
    "sg:classifiers":[
        {
            "category":"Government",
            "subcategory":"Fire Station",
            "type":"Public Place"
        }
    ],
    "sg:phone":"+61 2 6023 2946",
    "sg:postcode":"2640",
    "sg:province":"NSW",
    "sg:tags":[
        "equipment",
        "protection",
        "consultant"
    ],
    "wof:name":"Albury-Wodonga Fire Protection",
    "wof:placetype":"venue"
},
  "geometry": {"coordinates":[146.93241882300001,-36.0578765869],"type":"Point"}
}