{
  "type": "Feature",
  "properties": {
    "addr:full":"33 Rankins Rd Trafalgar VIC 3824",
    "addr:housenumber":"33",
    "addr:postcode":"3824",
    "addr:street":"Rankins Rd",
    "iso:country":"AU",
    "sg:address":"33 Rankins Rd",
    "sg:city":"Trafalgar",
    "sg:classifiers":[
        {
            "category":"Farming",
            "subcategory":"Nursery",
            "type":"Manufacturing & Wholesale Goods"
        }
    ],
    "sg:phone":"+61 3 5633 1354",
    "sg:postcode":"3824",
    "sg:province":"VIC",
    "wof:name":"Rose & Fuchsia Fram Gippsland",
    "wof:placetype":"venue"
},
  "geometry": {"coordinates":[146.12820400000001,-38.212063],"type":"Point"}
}