{
  "type": "Feature",
  "properties": {
    "addr:full":"477 High St Melton VIC 3337",
    "addr:housenumber":"477",
    "addr:postcode":"3337",
    "addr:street":"High St",
    "iso:country":"AU",
    "sg:address":"477 High St",
    "sg:city":"Melton",
    "sg:classifiers":[
        {
            "category":"Health Services",
            "subcategory":"Chiropractor",
            "type":"Services"
        }
    ],
    "sg:phone":"+61 3 9743 7932",
    "sg:postcode":"3337",
    "sg:province":"VIC",
    "wof:name":"Melton Chiropractic Centre",
    "wof:placetype":"venue"
},
  "geometry": {"coordinates":[144.5728,-37.684105],"type":"Point"}
}