{
  "type": "Feature",
  "properties": {
    "addr:full":"3/ 32 Seton Rd Moorebank NSW 2170",
    "addr:housenumber":"/ 32",
    "addr:postcode":"2170",
    "addr:street":"Seton Rd",
    "iso:country":"AU",
    "sg:address":"3/ 32 Seton Rd",
    "sg:city":"Moorebank",
    "sg:classifiers":[
        {
            "category":"Manufacturing",
            "subcategory":"Metals",
            "type":"Manufacturing & Wholesale Goods"
        }
    ],
    "sg:phone":"+61 403 491 575",
    "sg:postcode":"2170",
    "sg:province":"NSW",
    "sg:tags":[
        "steel",
        "fabricator",
        "mfrs"
    ],
    "wof:name":"Saliba Steel Pty Ltd",
    "wof:placetype":"venue"
},
  "geometry": {"coordinates":[150.93893432600001,-33.9369773865],"type":"Point"}
}