{
  "type": "Feature",
  "properties": {
    "addr:full":"40 Harold Rd Springvale South VIC 3172",
    "addr:housenumber":"40",
    "addr:postcode":"3172",
    "addr:street":"Harold Rd",
    "iso:country":"AU",
    "sg:address":"40 Harold Rd",
    "sg:city":"Springvale South",
    "sg:classifiers":[
        {
            "category":"Professional",
            "subcategory":"Accounting & Tax Preparation",
            "type":"Services"
        }
    ],
    "sg:phone":"+61 3 9540 8543",
    "sg:postcode":"3172",
    "sg:province":"VIC",
    "sg:tags":[
        "accountant",
        "auditor"
    ],
    "wof:name":"Buzza Ros",
    "wof:placetype":"venue"
},
  "geometry": {"coordinates":[145.152786255,-37.9756240845],"type":"Point"}
}