{
  "type": "Feature",
  "properties": {
    "iso:country":"AU",
    "sg:address":"Shop 2/ 31 Charlotte St",
    "sg:city":"Smithfield",
    "sg:classifiers":[
        {
            "category":"Shopping",
            "subcategory":"Party Supplies",
            "type":"Retail Goods"
        }
    ],
    "sg:phone":"+61 8 8284 3403",
    "sg:postcode":"5114",
    "sg:province":"SA",
    "sg:tags":[
        "hire",
        "costume"
    ],
    "wof:name":"Alakazam Costume Hire",
    "wof:placetype":"venue"
},
  "geometry": {"coordinates":[138.688995361,-34.681854248],"type":"Point"}
}