{
  "type": "Feature",
  "properties": {
    "addr:full":"90 Morley Drv East Morley WA 6062",
    "addr:housenumber":"90",
    "addr:postcode":"6062",
    "addr:street":"Morley Drv East",
    "iso:country":"AU",
    "sg:address":"90 Morley Drv",
    "sg:city":"East Morley",
    "sg:classifiers":[
        {
            "category":"Personal",
            "type":"Services"
        }
    ],
    "sg:phone":"+61 8 9279 4824",
    "sg:postcode":"6062",
    "sg:province":"WA",
    "sg:tags":[
        "dressmaker"
    ],
    "wof:name":"Fantasy Bridal",
    "wof:placetype":"venue"
},
  "geometry": {"coordinates":[115.924430847,-31.8891563416],"type":"Point"}
}