{
  "type": "Feature",
  "properties": {
    "addr:full":"PO Box 314 Aspley QLD 4034",
    "addr:postcode":"4034",
    "iso:country":"AU",
    "sg:address":"PO Box 314",
    "sg:city":"Aspley",
    "sg:classifiers":[
        {
            "category":"Professional",
            "subcategory":"Computer Services",
            "type":"Services"
        }
    ],
    "sg:phone":"+61 7 3261 2296",
    "sg:postcode":"4034",
    "sg:province":"QLD",
    "sg:tags":[
        "package",
        "software"
    ],
    "wof:name":"On Tick Systems",
    "wof:placetype":"venue"
},
  "geometry": {"coordinates":[153.01965300000001,-27.36422],"type":"Point"}
}