{
  "type": "Feature",
  "properties": {
    "iso:country":"AU",
    "sg:address":"14/ 162 Winton Rd",
    "sg:city":"Joondalup",
    "sg:classifiers":[
        {
            "category":"Manufacturing",
            "subcategory":"Rubber & Plastics",
            "type":"Manufacturing & Wholesale Goods"
        }
    ],
    "sg:phone":"+61 8 9301 5194",
    "sg:postcode":"6027",
    "sg:province":"WA",
    "sg:tags":[
        "product",
        "retail"
    ],
    "wof:name":"Clark Rubber",
    "wof:placetype":"venue"
},
  "geometry": {"coordinates":[115.762916565,-31.7417182922],"type":"Point"}
}