{
  "type": "Feature",
  "properties": {
    "iso:country":"AU",
    "sg:address":"Kitchener Park Picnic Pde",
    "sg:city":"Ettalong Beach",
    "sg:classifiers":[
        {
            "category":"Education",
            "subcategory":"Special Training",
            "type":"Public Place"
        }
    ],
    "sg:phone":"+61 2 4360 1673",
    "sg:postcode":"2257",
    "sg:province":"NSW",
    "sg:tags":[
        "school",
        "art"
    ],
    "wof:name":"Ettalong Beach Arts & Craft Centre",
    "wof:placetype":"venue"
},
  "geometry": {"coordinates":[151.33775329599999,-33.509311676],"type":"Point"}
}