{
  "type": "Feature",
  "properties": {
    "iso:country":"AU",
    "sg:address":"32b Pacific Hwy",
    "sg:city":"Gosford West",
    "sg:classifiers":[
        {
            "category":"Autos & Motor Vehicles",
            "subcategory":"Auto Supplies",
            "type":"Retail Goods"
        }
    ],
    "sg:phone":"+61 2 4324 5550",
    "sg:postcode":"2250",
    "sg:province":"NSW",
    "sg:tags":[
        "tyre"
    ],
    "wof:name":"Yokohama",
    "wof:placetype":"venue"
},
  "geometry": {"coordinates":[151.325073242,-33.427696228],"type":"Point"}
}