{
  "type": "Feature",
  "properties": {
    "iso:country":"AU",
    "sg:address":"75 Lantana Drv",
    "sg:city":"Parafield Gardens",
    "sg:classifiers":[
        {
            "category":"Retail",
            "subcategory":"Driving School",
            "type":"Services"
        }
    ],
    "sg:phone":"+61 8 8250 4452",
    "sg:postcode":"5107",
    "sg:province":"SA",
    "wof:name":"Roadrunner Driver Education",
    "wof:placetype":"venue"
},
  "geometry": {"coordinates":[138.60455322300001,-34.7909088135],"type":"Point"}
}