{
  "type": "Feature",
  "properties": {
    "addr:full":"Suite 1. Lvl 17/ 25 Bligh St Sydney NSW 2000",
    "addr:housenumber":"/ 25",
    "addr:postcode":"2000",
    "addr:street":"Bligh St",
    "iso:country":"AU",
    "sg:address":"Suite 1. Lvl 17/ 25 Bligh St",
    "sg:city":"Sydney",
    "sg:classifiers":[
        {
            "category":"Banks & Credit Unions",
            "subcategory":"Bank",
            "type":"Services"
        }
    ],
    "sg:phone":"+61 2 9232 7233",
    "sg:postcode":"2000",
    "sg:province":"NSW",
    "wof:name":"Wachovia Bank",
    "wof:placetype":"venue"
},
  "geometry": {"coordinates":[151.210113525,-33.8655700684],"type":"Point"}
}