{
  "type": "Feature",
  "properties": {
    "addr:full":"PO Box 2070 Southport Business Centre QLD 4215",
    "addr:postcode":"4215",
    "iso:country":"AU",
    "sg:address":"PO Box 2070",
    "sg:city":"Southport Business Centre",
    "sg:classifiers":[
        {
            "category":"Building & Trades",
            "subcategory":"Plumbing",
            "type":"Services"
        }
    ],
    "sg:phone":"+61 419 023 434",
    "sg:postcode":"4215",
    "sg:province":"QLD",
    "sg:tags":[
        "plumber",
        "gasfitters"
    ],
    "wof:name":"Gray Plumbing",
    "wof:placetype":"venue"
},
  "geometry": {"coordinates":[153.39855957,-27.9664897919],"type":"Point"}
}