{
  "type": "Feature",
  "properties": {
    "addr:full":"39 Winnellie Rd Winnellie NT 0820",
    "addr:housenumber":"39",
    "addr:postcode":"nt 0820",
    "addr:street":"Winnellie Rd",
    "iso:country":"AU",
    "sg:address":"39 Winnellie Rd",
    "sg:city":"Winnellie",
    "sg:classifiers":[
        {
            "category":"Building & Trades",
            "subcategory":"Construction",
            "type":"Services"
        }
    ],
    "sg:phone":"+61 8 8984 3019",
    "sg:postcode":"0820",
    "sg:province":"NT",
    "sg:tags":[
        "monumental",
        "mason"
    ],
    "wof:name":"Granite & Marble Factory",
    "wof:placetype":"venue"
},
  "geometry": {"coordinates":[130.87525939899999,-12.4264888763],"type":"Point"}
}