{
  "type": "Feature",
  "properties": {
    "addr:full":"285- 297 Lane Cove Rd North Ryde NSW 2113",
    "addr:housenumber":"297",
    "addr:postcode":"2113",
    "addr:street":"Lane Cove Rd",
    "iso:country":"AU",
    "sg:address":"285- 297 Lane Cove Rd",
    "sg:city":"North Ryde",
    "sg:classifiers":[
        {
            "category":"Health Services",
            "subcategory":"Dentist",
            "type":"Services"
        }
    ],
    "sg:phone":"+61 2 9888 6066",
    "sg:postcode":"2113",
    "sg:province":"NSW",
    "wof:name":"Haber-Sissons Dr Patrycja",
    "wof:placetype":"venue"
},
  "geometry": {"coordinates":[151.11883544899999,-33.7937545776],"type":"Point"}
}