{
  "type": "Feature",
  "properties": {
    "iso:country":"AU",
    "sg:address":"Veness Rd",
    "sg:city":"Dimbulah",
    "sg:classifiers":[
        {
            "category":"Farming",
            "subcategory":"Farm",
            "type":"Manufacturing & Wholesale Goods"
        }
    ],
    "sg:phone":"+61 7 4093 5128",
    "sg:postcode":"4872",
    "sg:province":"QLD",
    "sg:tags":[
        "farmer"
    ],
    "wof:name":"Palumbo A",
    "wof:placetype":"venue"
},
  "geometry": {"coordinates":[145.099807739,-17.1649932861],"type":"Point"}
}