{
  "type": "Feature",
  "properties": {
    "addr:full":"94 Spencer St Bunbury WA 6230",
    "addr:housenumber":"94",
    "addr:postcode":"6230",
    "addr:street":"Spencer St",
    "iso:country":"AU",
    "sg:address":"94 Spencer St",
    "sg:city":"Bunbury",
    "sg:classifiers":[
        {
            "category":"Retail",
            "subcategory":"Self-service Laundry",
            "type":"Services"
        }
    ],
    "sg:phone":"+61 8 9721 7466",
    "sg:postcode":"6230",
    "sg:province":"WA",
    "wof:name":"Plaza Laundrette",
    "wof:placetype":"venue"
},
  "geometry": {"coordinates":[115.64157899999999,-33.346607],"type":"Point"}
}