{
  "type": "Feature",
  "properties": {
    "iso:country":"AU",
    "sg:address":"45 Diosma Drv",
    "sg:city":"Glen Waverley",
    "sg:classifiers":[
        {
            "category":"Farming",
            "subcategory":"Farm & Veterinary Services",
            "type":"Manufacturing & Wholesale Goods"
        }
    ],
    "sg:phone":"+61 419 204 460",
    "sg:postcode":"3150",
    "sg:province":"VIC",
    "sg:tags":[
        "deer",
        "farmer"
    ],
    "wof:name":"J.G. & J.K. French",
    "wof:placetype":"venue"
},
  "geometry": {"coordinates":[145.16517639200001,-37.8991508484],"type":"Point"}
}