{
  "type": "Feature",
  "properties": {
    "addr:full":"Sunshine Coast Private Hospital, Elisa Wilson Drv Buderim QLD 4556",
    "addr:postcode":"4556",
    "addr:street":"Sunshine;Wilson Drv",
    "iso:country":"AU",
    "sg:address":"Sunshine Coast Private Hospital, Elisa Wilson Drv",
    "sg:city":"Buderim",
    "sg:classifiers":[
        {
            "category":"Health Services",
            "subcategory":"Medical Lab",
            "type":"Services"
        }
    ],
    "sg:phone":"+61 7 5444 6852",
    "sg:postcode":"4556",
    "sg:province":"QLD",
    "sg:tags":[
        "laboratory",
        "pathology"
    ],
    "wof:name":"Sullivan Nicolaides Pathology",
    "wof:placetype":"venue"
},
  "geometry": {"coordinates":[153.08071899399999,-26.6554775238],"type":"Point"}
}