{
  "type": "Feature",
  "properties": {
    "addr:full":"301 High St Ashburton VIC 3147",
    "addr:housenumber":"301",
    "addr:postcode":"3147",
    "addr:street":"High St",
    "iso:country":"AU",
    "sg:address":"301 High St",
    "sg:city":"Ashburton",
    "sg:classifiers":[
        {
            "category":"Personal",
            "subcategory":"Massage",
            "type":"Services"
        }
    ],
    "sg:phone":"+61 412 677 732",
    "sg:postcode":"3147",
    "sg:province":"VIC",
    "sg:tags":[
        "therapy"
    ],
    "wof:name":"Renay Ymer Myotherapist",
    "wof:placetype":"venue"
},
  "geometry": {"coordinates":[145.08200073200001,-37.8635482788],"type":"Point"}
}