{
  "type": "Feature",
  "properties": {
    "addr:full":"34-36 Kertes Rd Camira QLD 4300",
    "addr:housenumber":"34-36",
    "addr:postcode":"4300",
    "addr:street":"Kertes Rd",
    "iso:country":"AU",
    "sg:address":"34-36 Kertes Rd",
    "sg:city":"Camira",
    "sg:classifiers":[
        {
            "category":"Professional",
            "subcategory":"Business Services",
            "type":"Services"
        }
    ],
    "sg:phone":"+61 7 3288 3028",
    "sg:postcode":"4300",
    "sg:province":"QLD",
    "sg:tags":[
        "drafting"
    ],
    "wof:name":"Campbell R J & L V",
    "wof:placetype":"venue"
},
  "geometry": {"coordinates":[152.921142578,-27.6442222595],"type":"Point"}
}