{
  "type": "Feature",
  "properties": {
    "addr:full":"25 Sweet Gum Ave Narre Warren VIC 3805",
    "addr:housenumber":"25",
    "addr:postcode":"3805",
    "addr:street":"Sweet Gum Ave",
    "iso:country":"AU",
    "sg:address":"25 Sweet Gum Ave",
    "sg:city":"Narre Warren",
    "sg:classifiers":[
        {
            "category":"Autos & Motor Vehicles",
            "subcategory":"Auto Supplies",
            "type":"Retail Goods"
        }
    ],
    "sg:phone":"+61 3 9703 2604",
    "sg:postcode":"3805",
    "sg:province":"VIC",
    "sg:tags":[
        "accessory"
    ],
    "wof:name":"Historic Car Covers",
    "wof:placetype":"venue"
},
  "geometry": {"coordinates":[145.29664600000001,-38.009972],"type":"Point"}
}