{
  "type": "Feature",
  "properties": {
    "addr:full":"5- 7 Carlton St Prahran VIC 3181",
    "addr:housenumber":"7",
    "addr:postcode":"3181",
    "addr:street":"Carlton St",
    "iso:country":"AU",
    "sg:address":"5- 7 Carlton St",
    "sg:city":"Prahran",
    "sg:classifiers":[
        {
            "category":"Building & Trades",
            "subcategory":"Equipment Rental",
            "type":"Services"
        }
    ],
    "sg:phone":"+61 3 9368 2400",
    "sg:postcode":"3181",
    "sg:province":"VIC",
    "sg:tags":[
        "supply",
        "catering"
    ],
    "wof:name":"Reward Distribution",
    "wof:placetype":"venue"
},
  "geometry": {"coordinates":[144.99461364699999,-37.8477020264],"type":"Point"}
}