{
  "type": "Feature",
  "properties": {
    "iso:country":"AU",
    "sg:address":"1/ 41 Musgrave Ave",
    "sg:city":"Chirn Park",
    "sg:classifiers":[
        {
            "category":"Health Services",
            "subcategory":"Optometrist",
            "type":"Services"
        }
    ],
    "sg:phone":"+61 7 5571 1569",
    "sg:postcode":"4215",
    "sg:province":"QLD",
    "wof:name":"Reynolds Geoffrey",
    "wof:placetype":"venue"
},
  "geometry": {"coordinates":[153.38702392600001,-27.9545345306],"type":"Point"}
}