{
  "type": "Feature",
  "properties": {
    "addr:full":"253 Kensington Rd Kensington Park SA 5068",
    "addr:housenumber":"253",
    "addr:postcode":"5068",
    "addr:street":"Kensington Rd",
    "iso:country":"AU",
    "sg:address":"253 Kensington Rd",
    "sg:city":"Kensington Park",
    "sg:classifiers":[
        {
            "category":"Shopping",
            "subcategory":"Clothing, Apparel, & Fashions",
            "type":"Retail Goods"
        }
    ],
    "sg:phone":"+61 8 8361 3733",
    "sg:postcode":"5068",
    "sg:province":"SA",
    "sg:tags":[
        "maternity",
        "wear"
    ],
    "wof:name":"Mondays Child",
    "wof:placetype":"venue"
},
  "geometry": {"coordinates":[138.65545654300001,-34.9260864258],"type":"Point"}
}