{
  "type": "Feature",
  "properties": {
    "addr:full":"62 Geordie St Lithgow NSW 2790",
    "addr:housenumber":"62",
    "addr:postcode":"2790",
    "addr:street":"Geordie St",
    "iso:country":"AU",
    "sg:address":"62 Geordie St",
    "sg:city":"Lithgow",
    "sg:classifiers":[
        {
            "category":"Building & Trades",
            "subcategory":"Equipment Rental",
            "type":"Services"
        }
    ],
    "sg:phone":"+61 2 6351 3221",
    "sg:postcode":"2790",
    "sg:province":"NSW",
    "sg:tags":[
        "platform",
        "hire",
        "work",
        "elevating"
    ],
    "wof:name":"Central Booms & Scissor Lifts Pty Ltd",
    "wof:placetype":"venue"
},
  "geometry": {"coordinates":[150.139602661,-33.478477478],"type":"Point"}
}