{
  "type": "Feature",
  "properties": {
    "iso:country":"AU",
    "sg:address":"7 Riviera Crs",
    "sg:city":"Peregian Beach",
    "sg:classifiers":[
        {
            "category":"Professional",
            "subcategory":"Employment Agencies",
            "type":"Services"
        }
    ],
    "sg:phone":"+61 7 5448 3254",
    "sg:postcode":"4573",
    "sg:province":"QLD",
    "sg:tags":[
        "entertainer",
        "agent"
    ],
    "wof:name":"Free Style Entertainment",
    "wof:placetype":"venue"
},
  "geometry": {"coordinates":[153.095215,-26.47817],"type":"Point"}
}