{
  "type": "Feature",
  "properties": {
    "iso:country":"AU",
    "sg:address":"U5/ 43 Burlington St",
    "sg:city":"Naval Base",
    "sg:classifiers":[
        {
            "category":"Real Estate",
            "subcategory":"Architect",
            "type":"Services"
        }
    ],
    "sg:phone":"+61 8 9437 1319",
    "sg:postcode":"6165",
    "sg:province":"WA",
    "sg:tags":[
        "naval"
    ],
    "wof:name":"Global Marine Design Pty Ltd",
    "wof:placetype":"venue"
},
  "geometry": {"coordinates":[115.784943,-32.200138],"type":"Point"}
}