{
  "type": "Feature",
  "properties": {
    "addr:full":"PO Box 151 Ferny Creek VIC 3786",
    "addr:postcode":"3786",
    "iso:country":"AU",
    "sg:address":"PO Box 151",
    "sg:city":"Ferny Creek",
    "sg:classifiers":[
        {
            "category":"Education",
            "subcategory":"Dance Studio",
            "type":"Public Place"
        }
    ],
    "sg:phone":"+61 3 9755 3772",
    "sg:postcode":"3786",
    "sg:province":"VIC",
    "sg:tags":[
        "venue",
        "tuition"
    ],
    "wof:name":"Imperial Society Of Teachers Of Dancing Victoria",
    "wof:placetype":"venue"
},
  "geometry": {"coordinates":[145.342896,-37.875191],"type":"Point"}
}