{
  "type": "Feature",
  "properties": {
    "iso:country":"AU",
    "sg:address":"36 Old Cleveland Rd",
    "sg:city":"Capalaba",
    "sg:classifiers":[
        {
            "category":"Shopping",
            "subcategory":"Pets & Pet Supplies",
            "type":"Retail Goods"
        }
    ],
    "sg:phone":"+61 7 3390 1498",
    "sg:postcode":"4157",
    "sg:province":"QLD",
    "sg:tags":[
        "food"
    ],
    "wof:name":"Capalaba Pet Food",
    "wof:placetype":"venue"
},
  "geometry": {"coordinates":[153.197555542,-27.5210933685],"type":"Point"}
}