{
  "type": "Feature",
  "properties": {
    "iso:country":"AU",
    "sg:address":"621 Ruthven St",
    "sg:city":"Toowoomba",
    "sg:classifiers":[
        {
            "category":"Food & Beverages",
            "subcategory":"Bakery",
            "type":"Retail Goods"
        }
    ],
    "sg:phone":"+61 7 4632 6144",
    "sg:postcode":"4350",
    "sg:province":"QLD",
    "sg:tags":[
        "cake",
        "shop",
        "pastry"
    ],
    "wof:name":"Nikkys Bikkys",
    "wof:placetype":"venue"
},
  "geometry": {"coordinates":[151.952332,-27.568024],"type":"Point"}
}