{
  "type": "Feature",
  "properties": {
    "iso:country":"AU",
    "sg:address":"537 Main St",
    "sg:city":"Mordialloc",
    "sg:classifiers":[
        {
            "category":"Shopping",
            "subcategory":"Clothing, Apparel, & Fashions",
            "type":"Retail Goods"
        }
    ],
    "sg:phone":"+61 3 9580 8622",
    "sg:postcode":"3195",
    "sg:province":"VIC",
    "sg:tags":[
        "lady",
        "wear"
    ],
    "wof:name":"Shibuki",
    "wof:placetype":"venue"
},
  "geometry": {"coordinates":[145.087768555,-38.0077476501],"type":"Point"}
}