{
  "type": "Feature",
  "properties": {
    "addr:full":"3 Cadby Crt Warragul VIC 3820",
    "addr:housenumber":"3",
    "addr:postcode":"3820",
    "addr:street":"Cadby Crt",
    "iso:country":"AU",
    "sg:address":"3 Cadby Crt",
    "sg:city":"Warragul",
    "sg:classifiers":[
        {
            "category":"Home & Garden",
            "subcategory":"Building Materials",
            "type":"Retail Goods"
        }
    ],
    "sg:phone":"+61 3 5623 6893",
    "sg:postcode":"3820",
    "sg:province":"VIC",
    "sg:tags":[
        "supply"
    ],
    "wof:name":"Gippsland Insulation & Building Supplies Pty Ltd",
    "wof:placetype":"venue"
},
  "geometry": {"coordinates":[145.939697,-38.162868],"type":"Point"}
}