{
  "type": "Feature",
  "properties": {
    "iso:country":"AU",
    "sg:address":"Matilda Hwy",
    "sg:city":"Normanton",
    "sg:classifiers":[
        {
            "category":"Travel",
            "subcategory":"Hotels & Motels",
            "type":"Entertainment"
        }
    ],
    "sg:phone":"+61 7 4742 5909",
    "sg:postcode":"4890",
    "sg:province":"QLD",
    "wof:name":"Burke & Wills Roadhouse",
    "wof:placetype":"venue"
},
  "geometry": {"coordinates":[141.07344055199999,-17.6732120514],"type":"Point"}
}