{
  "type": "Feature",
  "properties": {
    "iso:country":"AU",
    "sg:address":"19 Catalano Rd",
    "sg:city":"Canning Vale",
    "sg:classifiers":[
        {
            "category":"Mining & Drilling",
            "type":"Manufacturing & Wholesale Goods"
        }
    ],
    "sg:phone":"+61 8 9456 4480",
    "sg:postcode":"6155",
    "sg:province":"WA",
    "sg:tags":[
        "equipment",
        "quarrying",
        "supply"
    ],
    "sg:website":"http://www.kn4wd.com",
    "wof:name":"K & N 4WD",
    "wof:placetype":"venue"
},
  "geometry": {"coordinates":[115.90315200000001,-32.060246],"type":"Point"}
}