{
  "type": "Feature",
  "properties": {
    "addr:full":"26 High St Yea VIC 3717",
    "addr:housenumber":"26",
    "addr:postcode":"3717",
    "addr:street":"High St",
    "iso:country":"AU",
    "sg:address":"26 High St",
    "sg:city":"Yea",
    "sg:classifiers":[
        {
            "category":"Banks & Credit Unions",
            "subcategory":"Bank",
            "type":"Services"
        }
    ],
    "sg:phone":"+61 13 20 32",
    "sg:postcode":"3717",
    "sg:province":"VIC",
    "wof:name":"Westpac",
    "wof:placetype":"venue"
},
  "geometry": {"coordinates":[145.42582702600001,-37.2106819153],"type":"Point"}
}