{
  "type": "Feature",
  "properties": {
    "addr:full":"141 Acland St St Kilda VIC 3182",
    "addr:housenumber":"141",
    "addr:postcode":"3182",
    "addr:street":"Acland St",
    "iso:country":"AU",
    "sg:address":"141 Acland St",
    "sg:city":"St Kilda",
    "sg:classifiers":[
        {
            "category":"Fast Food",
            "type":"Food & Drink"
        }
    ],
    "sg:phone":"+61 3 9534 1917",
    "sg:postcode":"3182",
    "sg:province":"VIC",
    "sg:tags":[
        "away",
        "take"
    ],
    "wof:name":"Clamms Fast Fish",
    "wof:placetype":"venue"
},
  "geometry": {"coordinates":[144.979858398,-37.8688621521],"type":"Point"}
}