{
  "type": "Feature",
  "properties": {
    "addr:full":"66 Vine St Magill SA 5072",
    "addr:housenumber":"66",
    "addr:postcode":"5072",
    "addr:street":"Vine St",
    "iso:country":"AU",
    "sg:address":"66 Vine St",
    "sg:city":"Magill",
    "sg:classifiers":[
        {
            "category":"Personal",
            "subcategory":"Beauty Salon",
            "type":"Services"
        }
    ],
    "sg:phone":"+61 8 8331 8610",
    "sg:postcode":"5072",
    "sg:province":"SA",
    "sg:tags":[
        "hairdresser"
    ],
    "wof:name":"Hair For All",
    "wof:placetype":"venue"
},
  "geometry": {"coordinates":[138.67999267600001,-34.9072532654],"type":"Point"}
}