{
  "type": "Feature",
  "properties": {
    "addr:full":"40 Abbotsford Rd Bowen Hills QLD 4006",
    "addr:housenumber":"40",
    "addr:postcode":"4006",
    "addr:street":"Abbotsford Rd",
    "iso:country":"AU",
    "sg:address":"40 Abbotsford Rd",
    "sg:city":"Bowen Hills",
    "sg:classifiers":[
        {
            "category":"Retail",
            "subcategory":"Auto Rental",
            "type":"Services"
        }
    ],
    "sg:phone":"+61 7 3852 2079",
    "sg:postcode":"4006",
    "sg:province":"QLD",
    "sg:tags":[
        "car",
        "hire",
        "minibus"
    ],
    "wof:name":"Apple Rental Cars",
    "wof:placetype":"venue"
},
  "geometry": {"coordinates":[153.03805542000001,-27.4453449249],"type":"Point"}
}