{
  "type": "Feature",
  "properties": {
    "iso:country":"AU",
    "sg:address":"85 Miskin St",
    "sg:city":"Toowong",
    "sg:classifiers":[
        {
            "category":"Restaurant",
            "type":"Food & Drink"
        }
    ],
    "sg:phone":"+61 7 3371 4558",
    "sg:postcode":"4066",
    "sg:province":"QLD",
    "wof:name":"Brents The Dining Experience",
    "wof:placetype":"venue"
},
  "geometry": {"coordinates":[152.98321533199999,-27.4857635498],"type":"Point"}
}