{
  "type": "Feature",
  "properties": {
    "addr:full":"4 West End St Delacombe VIC 3356",
    "addr:housenumber":"4",
    "addr:postcode":"3356",
    "addr:street":"West;St",
    "iso:country":"AU",
    "sg:address":"4 West End St",
    "sg:city":"Delacombe",
    "sg:classifiers":[
        {
            "category":"Building & Trades",
            "subcategory":"Construction",
            "type":"Services"
        }
    ],
    "sg:phone":"+61 409 168 554",
    "sg:postcode":"3356",
    "sg:province":"VIC",
    "sg:tags":[
        "concrete",
        "contractor"
    ],
    "wof:name":"Pro-line Concreters",
    "wof:placetype":"venue"
},
  "geometry": {"coordinates":[143.80625900000001,-37.578136],"type":"Point"}
}