{
  "type": "Feature",
  "properties": {
    "iso:country":"AU",
    "sg:address":"Level 2 47 Colin St",
    "sg:city":"West Perth",
    "sg:classifiers":[
        {
            "category":"Banks & Credit Unions",
            "subcategory":"Financial Services",
            "type":"Services"
        }
    ],
    "sg:phone":"+61 8 9321 3514",
    "sg:postcode":"6005",
    "sg:province":"WA",
    "sg:tags":[
        "planning"
    ],
    "wof:name":"ORD Financial Services",
    "wof:placetype":"venue"
},
  "geometry": {"coordinates":[115.841499329,-31.9498138428],"type":"Point"}
}