{
  "type": "Feature",
  "properties": {
    "addr:full":"28 George St Moe VIC 3825",
    "addr:housenumber":"28",
    "addr:postcode":"3825",
    "addr:street":"George St",
    "iso:country":"AU",
    "sg:address":"28 George St",
    "sg:city":"Moe",
    "sg:classifiers":[
        {
            "category":"Health Services",
            "subcategory":"Doctor",
            "type":"Services"
        }
    ],
    "sg:phone":"+61 3 5126 1344",
    "sg:postcode":"3825",
    "sg:province":"VIC",
    "sg:tags":[
        "medical",
        "practitioner"
    ],
    "wof:name":"Tanjil Place Medical",
    "wof:placetype":"venue"
},
  "geometry": {"coordinates":[146.26274100000001,-38.17614],"type":"Point"}
}