{
  "type": "Feature",
  "properties": {
    "addr:full":"6/8 Carrol St Port Denison WA 6525",
    "addr:housenumber":"/ 8",
    "addr:postcode":"6525",
    "addr:street":"Carrol St",
    "iso:country":"AU",
    "sg:address":"6/8 Carrol St",
    "sg:city":"Port Denison",
    "sg:classifiers":[
        {
            "category":"Autos & Motor Vehicles",
            "subcategory":"Boat Sales",
            "type":"Retail Goods"
        }
    ],
    "sg:phone":"+61 8 9927 2840",
    "sg:postcode":"6525",
    "sg:province":"WA",
    "sg:tags":[
        "yacht"
    ],
    "wof:name":"SRM Custom Marine",
    "wof:placetype":"venue"
},
  "geometry": {"coordinates":[114.925109863,-29.2720527649],"type":"Point"}
}