{
  "type": "Feature",
  "properties": {
    "addr:full":"25 The Grand Pde Brighton-le-Sands NSW 2216",
    "addr:housenumber":"25",
    "addr:postcode":"2216",
    "addr:street":"The Grand Pde",
    "iso:country":"AU",
    "sg:address":"25 The Grand Pde",
    "sg:city":"Brighton-le-Sands",
    "sg:classifiers":[
        {
            "category":"Government",
            "subcategory":"Court House",
            "type":"Public Place"
        }
    ],
    "sg:phone":"+61 2 9597 7779",
    "sg:postcode":"2216",
    "sg:province":"NSW",
    "sg:tags":[
        "personal",
        "marriage",
        "family",
        "counselling"
    ],
    "wof:name":"Gary Green",
    "wof:placetype":"venue"
},
  "geometry": {"coordinates":[151.160248,-33.954411],"type":"Point"}
}