{
  "type": "Feature",
  "properties": {
    "iso:country":"AU",
    "sg:address":"6 Gould St",
    "sg:city":"Osborne Park",
    "sg:classifiers":[
        {
            "category":"Building & Trades",
            "subcategory":"Construction",
            "type":"Services"
        }
    ],
    "sg:phone":"+61 8 9202 5222",
    "sg:postcode":"6017",
    "sg:province":"WA",
    "sg:tags":[
        "contractor"
    ],
    "wof:name":"Content Living - The Home Builders",
    "wof:placetype":"venue"
},
  "geometry": {"coordinates":[115.814582825,-31.9146900177],"type":"Point"}
}