{
  "type": "Feature",
  "properties": {
    "iso:country":"AU",
    "sg:address":"Unit 1, 3 Tanning Rd",
    "sg:city":"Kalamunda",
    "sg:classifiers":[
        {
            "category":"Fast Food",
            "type":"Food & Drink"
        }
    ],
    "sg:phone":"+61 8 9293 0266",
    "sg:postcode":"6076",
    "sg:province":"WA",
    "sg:tags":[
        "away",
        "take"
    ],
    "wof:name":"Kala Kebabs",
    "wof:placetype":"venue"
},
  "geometry": {"coordinates":[116.043067932,-31.990858078],"type":"Point"}
}