{
  "type": "Feature",
  "properties": {
    "iso:country":"AU",
    "sg:address":"Mt Murchison Rd",
    "sg:city":"Mt Murchison",
    "sg:classifiers":[
        {
            "category":"Farming",
            "subcategory":"Farm",
            "type":"Manufacturing & Wholesale Goods"
        }
    ],
    "sg:phone":"+61 7 4992 2257",
    "sg:postcode":"4715",
    "sg:province":"QLD",
    "sg:tags":[
        "farmer"
    ],
    "wof:name":"Cridland P",
    "wof:placetype":"venue"
},
  "geometry": {"coordinates":[150.511993408,-24.3951625824],"type":"Point"}
}