{
  "type": "Feature",
  "properties": {
    "iso:country":"AU",
    "sg:address":"9 Yabsley Ave",
    "sg:city":"Marrickville",
    "sg:classifiers":[
        {
            "category":"Professional",
            "subcategory":"Research",
            "type":"Services"
        }
    ],
    "sg:phone":"+61 2 9590 4718",
    "sg:postcode":"2204",
    "sg:province":"NSW",
    "sg:tags":[
        "market"
    ],
    "wof:name":"Jane Fowler Coding & Editing",
    "wof:placetype":"venue"
},
  "geometry": {"coordinates":[151.155396,-33.906826],"type":"Point"}
}