{
  "type": "Feature",
  "properties": {
    "addr:full":"PO Box 9182 Pacific Paradise QLD 4564",
    "addr:postcode":"4564",
    "iso:country":"AU",
    "sg:address":"PO Box 9182",
    "sg:city":"Pacific Paradise",
    "sg:classifiers":[
        {
            "category":"Building & Trades",
            "subcategory":"Construction",
            "type":"Services"
        }
    ],
    "sg:phone":"+61 412 863 550",
    "sg:postcode":"4564",
    "sg:province":"QLD",
    "sg:tags":[
        "pool",
        "swimming"
    ],
    "wof:name":"Pool Creations",
    "wof:placetype":"venue"
},
  "geometry": {"coordinates":[153.070404053,-26.6245994568],"type":"Point"}
}