{
  "type": "Feature",
  "properties": {
    "addr:full":"62 Woodville Pl Annerley QLD 4103",
    "addr:housenumber":"62",
    "addr:postcode":"4103",
    "addr:street":"Woodville Pl",
    "iso:country":"AU",
    "sg:address":"62 Woodville Pl",
    "sg:city":"Annerley",
    "sg:classifiers":[
        {
            "category":"Real Estate",
            "subcategory":"Surveying",
            "type":"Services"
        }
    ],
    "sg:phone":"+61 7 3217 1084",
    "sg:postcode":"4103",
    "sg:province":"QLD",
    "sg:tags":[
        "building",
        "surveyor"
    ],
    "wof:name":"M & G Engineering and Town Planning",
    "wof:placetype":"venue"
},
  "geometry": {"coordinates":[153.033569336,-27.5233421326],"type":"Point"}
}