{
  "type": "Feature",
  "properties": {
    "addr:full":"76 North St Glenroy VIC 3046",
    "addr:housenumber":"76",
    "addr:postcode":"3046",
    "addr:street":"North St",
    "iso:country":"AU",
    "sg:address":"76 North St",
    "sg:city":"Glenroy",
    "sg:classifiers":[
        {
            "category":"Health Services",
            "subcategory":"Doctor",
            "type":"Services"
        }
    ],
    "sg:phone":"+61 3 9359 9513",
    "sg:postcode":"3046",
    "sg:province":"VIC",
    "sg:tags":[
        "medical",
        "practitioner"
    ],
    "wof:name":"Long Robert",
    "wof:placetype":"venue"
},
  "geometry": {"coordinates":[144.94378662099999,-37.7048339844],"type":"Point"}
}