{
  "type": "Feature",
  "properties": {
    "iso:country":"AU",
    "sg:address":"3/ 10 Hunter St",
    "sg:city":"Parramatta",
    "sg:classifiers":[
        {
            "category":"Organizations",
            "subcategory":"Community Association",
            "type":"Services"
        }
    ],
    "sg:phone":"+61 2 9635 5293",
    "sg:postcode":"2150",
    "sg:province":"NSW",
    "sg:tags":[
        "organisation",
        "family",
        "welfare"
    ],
    "wof:name":"Parramatta Meals On Wheels Service",
    "wof:placetype":"venue"
},
  "geometry": {"coordinates":[151.03501892099999,-33.8426322937],"type":"Point"}
}