{
  "type": "Feature",
  "properties": {
    "addr:full":"10 Eulbertie Ave Warrawee NSW 2074",
    "addr:housenumber":"10",
    "addr:postcode":"2074",
    "addr:street":"Eulbertie Ave",
    "iso:country":"AU",
    "sg:address":"10 Eulbertie Ave",
    "sg:city":"Warrawee",
    "sg:classifiers":[
        {
            "category":"Professional",
            "subcategory":"Employment Agencies",
            "type":"Services"
        }
    ],
    "sg:phone":"+61 2 9487 6655",
    "sg:postcode":"2074",
    "sg:province":"NSW",
    "wof:name":"Frontier Consulting",
    "wof:placetype":"venue"
},
  "geometry": {"coordinates":[151.12188720699999,-33.7272491455],"type":"Point"}
}