{
  "type": "Feature",
  "properties": {
    "iso:country":"AU",
    "sg:address":"25 Kirksway Pl",
    "sg:city":"Battery Point",
    "sg:classifiers":[
        {
            "category":"Home & Garden",
            "subcategory":"Building Materials",
            "type":"Retail Goods"
        }
    ],
    "sg:phone":"+61 3 6224 5373",
    "sg:postcode":"7004",
    "sg:province":"TAS",
    "sg:tags":[
        "concrete",
        "panel",
        "pre-cast"
    ],
    "wof:name":"JMK Construction Group",
    "wof:placetype":"venue"
},
  "geometry": {"coordinates":[147.33029174800001,-42.8877220154],"type":"Point"}
}