{
  "type": "Feature",
  "properties": {
    "addr:full":"16c Calais Rd Scarborough WA 6019",
    "addr:housenumber":"16c",
    "addr:postcode":"6019",
    "addr:street":"Calais Rd",
    "iso:country":"AU",
    "sg:address":"16c Calais Rd",
    "sg:city":"Scarborough",
    "sg:classifiers":[
        {
            "category":"Government",
            "subcategory":"Post Office",
            "type":"Public Place"
        }
    ],
    "sg:phone":"+61 8 9245 3950",
    "sg:postcode":"6019",
    "sg:province":"WA",
    "sg:tags":[
        "yoga"
    ],
    "wof:name":"Finding Yoga",
    "wof:placetype":"venue"
},
  "geometry": {"coordinates":[115.76799011200001,-31.8995571136],"type":"Point"}
}