{
  "type": "Feature",
  "properties": {
    "addr:full":"Level 1 1 Dairy Rd Fyshwick ACT 0253",
    "addr:housenumber":"1",
    "addr:postcode":"0253",
    "addr:street":"Dairy Rd",
    "iso:country":"AU",
    "sg:address":"Level 1 1 Dairy Rd",
    "sg:city":"Fyshwick",
    "sg:classifiers":[
        {
            "category":"Professional",
            "subcategory":"Management & Consulting",
            "type":"Services"
        }
    ],
    "sg:phone":"+61 2 6230 6727",
    "sg:postcode":"0253",
    "sg:province":"ACT",
    "sg:tags":[
        "consultant",
        "economic"
    ],
    "wof:name":"Tony Beck Consulting Services Pty Ltd",
    "wof:placetype":"venue"
},
  "geometry": {"coordinates":[149.166015625,-35.3212966919],"type":"Point"}
}