{
  "type": "Feature",
  "properties": {
    "addr:full":"60 Vale Rd Bathurst NSW 2795",
    "addr:housenumber":"60",
    "addr:postcode":"2795",
    "addr:street":"Vale Rd",
    "iso:country":"AU",
    "sg:address":"60 Vale Rd",
    "sg:city":"Bathurst",
    "sg:classifiers":[
        {
            "category":"Farming",
            "subcategory":"Vineyard",
            "type":"Manufacturing & Wholesale Goods"
        }
    ],
    "sg:phone":"+61 2 6331 3089",
    "sg:postcode":"2795",
    "sg:province":"NSW",
    "sg:tags":[
        "saleyards"
    ],
    "wof:name":"Bathurst Saleyards",
    "wof:placetype":"venue"
},
  "geometry": {"coordinates":[149.56922912600001,-33.4669532776],"type":"Point"}
}