{
  "type": "Feature",
  "properties": {
    "addr:full":"20 Tandara St Rochedale QLD 4123",
    "addr:housenumber":"20",
    "addr:postcode":"4123",
    "addr:street":"Tandara St",
    "iso:country":"AU",
    "sg:address":"20 Tandara St",
    "sg:city":"Rochedale",
    "sg:classifiers":[
        {
            "category":"Professional",
            "subcategory":"Business Services",
            "type":"Services"
        }
    ],
    "sg:phone":"+61 7 3341 1462",
    "sg:postcode":"4123",
    "sg:province":"QLD",
    "sg:tags":[
        "drafting"
    ],
    "wof:name":"J T Drafting Services Pty Ltd",
    "wof:placetype":"venue"
},
  "geometry": {"coordinates":[153.140136719,-27.5934791565],"type":"Point"}
}