{
  "type": "Feature",
  "properties": {
    "iso:country":"AU",
    "sg:address":"Rear 542 High St",
    "sg:city":"Penrith",
    "sg:classifiers":[
        {
            "category":"Health Services",
            "subcategory":"Dentist",
            "type":"Services"
        }
    ],
    "sg:phone":"+61 2 4731 4843",
    "sg:postcode":"2750",
    "sg:province":"NSW",
    "sg:tags":[
        "technician",
        "dental"
    ],
    "wof:name":"Bruce Mackay",
    "wof:placetype":"venue"
},
  "geometry": {"coordinates":[150.91554260300001,-33.8950538635],"type":"Point"}
}