{
  "type": "Feature",
  "properties": {
    "addr:full":"805 Cleveland Rd Carina QLD 4152",
    "addr:housenumber":"805",
    "addr:postcode":"4152",
    "addr:street":"Cleveland Rd",
    "iso:country":"AU",
    "sg:address":"805 Cleveland Rd",
    "sg:city":"Carina",
    "sg:classifiers":[
        {
            "category":"Personal",
            "type":"Services"
        }
    ],
    "sg:phone":"+61 7 3843 2597",
    "sg:postcode":"4152",
    "sg:province":"QLD",
    "sg:tags":[
        "reducing",
        "treatment",
        "weight"
    ],
    "wof:name":"Jenny Craig Weight Loss Centres",
    "wof:placetype":"venue"
},
  "geometry": {"coordinates":[153.100006103,-27.4898204803],"type":"Point"}
}