{
  "type": "Feature",
  "properties": {
    "iso:country":"AU",
    "sg:address":"Cnr Mair & Peel Sts",
    "sg:city":"Ballarat",
    "sg:classifiers":[
        {
            "category":"Manufacturing",
            "subcategory":"Motor Vehicles & Parts",
            "type":"Manufacturing & Wholesale Goods"
        }
    ],
    "sg:phone":"+61 3 5332 1188",
    "sg:postcode":"3350",
    "sg:province":"VIC",
    "sg:tags":[
        "replacement"
    ],
    "wof:name":"Quick Fix",
    "wof:placetype":"venue"
},
  "geometry": {"coordinates":[143.861969,-37.5602],"type":"Point"}
}