{
  "type": "Feature",
  "properties": {
    "addr:full":"180 Victoria Rd Northcote VIC 3070",
    "addr:housenumber":"180",
    "addr:postcode":"3070",
    "addr:street":"Victoria Rd",
    "iso:country":"AU",
    "sg:address":"180 Victoria Rd",
    "sg:city":"Northcote",
    "sg:classifiers":[
        {
            "category":"Health Services",
            "subcategory":"Health Practitioner",
            "type":"Services"
        }
    ],
    "sg:phone":"+61 3 9486 7200",
    "sg:postcode":"3070",
    "sg:province":"VIC",
    "sg:tags":[
        "physiotherapist"
    ],
    "wof:name":"Geoffrey F. Bell",
    "wof:placetype":"venue"
},
  "geometry": {"coordinates":[145.01179500000001,-37.768913],"type":"Point"}
}