{
  "type": "Feature",
  "properties": {
    "iso:country":"AU",
    "sg:address":"3- 13 Cressall Rd",
    "sg:city":"Balcatta",
    "sg:classifiers":[
        {
            "category":"Retail",
            "subcategory":"Auto Repair",
            "type":"Services"
        }
    ],
    "sg:phone":"+61 8 9240 6030",
    "sg:postcode":"6021",
    "sg:province":"WA",
    "sg:tags":[
        "repairer",
        "motor",
        "engineer"
    ],
    "wof:name":"C.V. Joint",
    "wof:placetype":"venue"
},
  "geometry": {"coordinates":[115.811668396,-31.8615875244],"type":"Point"}
}