{
  "type": "Feature",
  "properties": {
    "addr:full":"9 Sorell St George Town TAS 7253",
    "addr:housenumber":"9",
    "addr:postcode":"7253",
    "addr:street":"Sorell St",
    "iso:country":"AU",
    "sg:address":"9 Sorell St",
    "sg:city":"George Town",
    "sg:classifiers":[
        {
            "category":"Health Services",
            "subcategory":"Health Practitioner",
            "type":"Services"
        }
    ],
    "sg:phone":"+61 3 6382 2170",
    "sg:postcode":"7253",
    "sg:province":"TAS",
    "sg:tags":[
        "physiotherapist"
    ],
    "wof:name":"George Town Physiotherapy Centre",
    "wof:placetype":"venue"
},
  "geometry": {"coordinates":[146.8253479,-41.1069374084],"type":"Point"}
}