{
  "type": "Feature",
  "properties": {
    "iso:country":"AU",
    "sg:address":"1 Houston St",
    "sg:city":"Donald",
    "sg:classifiers":[
        {
            "category":"Education",
            "subcategory":"Kindergarten",
            "type":"Public Place"
        }
    ],
    "sg:phone":"+61 3 5497 1465",
    "sg:postcode":"3480",
    "sg:province":"VIC",
    "sg:tags":[
        "pre-schools"
    ],
    "wof:name":"Donald Kindergarten",
    "wof:placetype":"venue"
},
  "geometry": {"coordinates":[142.982589722,-36.3674507141],"type":"Point"}
}