{
  "type": "Feature",
  "properties": {
    "addr:full":"54 Sunds Rd Marysville VIC 3779",
    "addr:housenumber":"54",
    "addr:postcode":"3779",
    "addr:street":"Sunds Rd",
    "iso:country":"AU",
    "sg:address":"54 Sunds Rd",
    "sg:city":"Marysville",
    "sg:classifiers":[
        {
            "category":"Utilities",
            "subcategory":"Natural Gas",
            "type":"Services"
        }
    ],
    "sg:phone":"+61 3 5963 4038",
    "sg:postcode":"3779",
    "sg:province":"VIC",
    "sg:tags":[
        "supplier"
    ],
    "wof:name":"Triangle Gas Supplies",
    "wof:placetype":"venue"
},
  "geometry": {"coordinates":[145.73814400000001,-37.507248],"type":"Point"}
}