{
  "type": "Feature",
  "properties": {
    "addr:full":"Evans St Inverell NSW 2360",
    "addr:postcode":"2360",
    "addr:street":"Evans St",
    "iso:country":"AU",
    "sg:address":"Evans St",
    "sg:city":"Inverell",
    "sg:classifiers":[
        {
            "category":"Government",
            "subcategory":"Fire Station",
            "type":"Public Place"
        }
    ],
    "sg:phone":"+61 2 6721 0015",
    "sg:postcode":"2360",
    "sg:province":"NSW",
    "sg:tags":[
        "brigade"
    ],
    "wof:name":"Fire Brigades-NSW",
    "wof:placetype":"venue"
},
  "geometry": {"coordinates":[151.11268615700001,-29.7758216858],"type":"Point"}
}