{
  "type": "Feature",
  "properties": {
    "iso:country":"AU",
    "sg:address":"62 Station St",
    "sg:city":"Pakenham",
    "sg:classifiers":[
        {
            "category":"Home & Garden",
            "subcategory":"Household Appliances",
            "type":"Retail Goods"
        }
    ],
    "sg:phone":"+61 3 5941 1844",
    "sg:postcode":"3810",
    "sg:province":"VIC",
    "sg:tags":[
        "chemical",
        "equipment",
        "steam",
        "cleaning",
        "pressure"
    ],
    "wof:name":"Karcher",
    "wof:placetype":"venue"
},
  "geometry": {"coordinates":[145.486313,-38.079475],"type":"Point"}
}