{
  "type": "Feature",
  "properties": {
    "addr:full":"Shp7/ 153 Trappers Drv Woodvale WA 6026",
    "addr:housenumber":"153",
    "addr:postcode":"6026",
    "addr:street":"Trappers Drv",
    "iso:country":"AU",
    "sg:address":"Shp7/ 153 Trappers Drv",
    "sg:city":"Woodvale",
    "sg:classifiers":[
        {
            "category":"Shopping",
            "subcategory":"Clothing, Apparel, & Fashions",
            "type":"Retail Goods"
        }
    ],
    "sg:phone":"+61 8 9409 3191",
    "sg:postcode":"6026",
    "sg:province":"WA",
    "sg:tags":[
        "recycled",
        "clothing"
    ],
    "wof:name":"Second Image",
    "wof:placetype":"venue"
},
  "geometry": {"coordinates":[115.787757873,-31.7824707031],"type":"Point"}
}