{
  "type": "Feature",
  "properties": {
    "addr:full":"Eugene St Bellbird Park QLD 4300",
    "addr:postcode":"4300",
    "addr:street":"Eugene St",
    "iso:country":"AU",
    "sg:address":"Eugene St",
    "sg:city":"Bellbird Park",
    "sg:classifiers":[
        {
            "category":"Real Estate",
            "subcategory":"Developer",
            "type":"Services"
        }
    ],
    "sg:phone":"+61 7 3818 6855",
    "sg:postcode":"4300",
    "sg:province":"QLD",
    "sg:tags":[
        "development"
    ],
    "wof:name":"C.B. Developments Australia Pty Ltd",
    "wof:placetype":"venue"
},
  "geometry": {"coordinates":[152.89881897000001,-27.634098053],"type":"Point"}
}