{
  "type": "Feature",
  "properties": {
    "addr:full":"26 Sylvan St Sylvania Heights NSW 2224",
    "addr:housenumber":"26",
    "addr:postcode":"2224",
    "addr:street":"Sylvan St",
    "iso:country":"AU",
    "sg:address":"26 Sylvan St",
    "sg:city":"Sylvania Heights",
    "sg:classifiers":[
        {
            "category":"Building & Trades",
            "subcategory":"Construction",
            "type":"Services"
        }
    ],
    "sg:phone":"+61 418 677 448",
    "sg:postcode":"2224",
    "sg:province":"NSW",
    "sg:tags":[
        "earth",
        "excavating",
        "moving",
        "contractor"
    ],
    "wof:name":"A M Excavations Pty Ltd",
    "wof:placetype":"venue"
},
  "geometry": {"coordinates":[151.09559631400001,-34.0124969482],"type":"Point"}
}