{
  "type": "Feature",
  "properties": {
    "iso:country":"AU",
    "sg:address":"Cnr Morack & East Rds",
    "sg:city":"Vermont South",
    "sg:classifiers":[
        {
            "category":"Sports & Exercise",
            "subcategory":"Golf",
            "type":"Entertainment"
        }
    ],
    "sg:phone":"+61 3 9801 4479",
    "sg:postcode":"3133",
    "sg:province":"VIC",
    "sg:tags":[
        "club"
    ],
    "wof:name":"Morack Public Golf Course & Driving Range",
    "wof:placetype":"venue"
},
  "geometry": {"coordinates":[145.198028564,-37.858089447],"type":"Point"}
}