{
  "type": "Feature",
  "properties": {
    "addr:full":"U1/ 375 Warnbro Sound Ave Port Kennedy WA 6172",
    "addr:housenumber":"375",
    "addr:postcode":"6172",
    "addr:street":"U1 /;Sound Ave",
    "iso:country":"AU",
    "sg:address":"U1/ 375 Warnbro Sound Ave",
    "sg:city":"Port Kennedy",
    "sg:classifiers":[
        {
            "category":"Fast Food",
            "type":"Food & Drink"
        }
    ],
    "sg:phone":"+61 8 9524 5181",
    "sg:postcode":"6172",
    "sg:province":"WA",
    "sg:tags":[
        "away",
        "take"
    ],
    "wof:name":"Yibbada Yibbada Seafood Shack",
    "wof:placetype":"venue"
},
  "geometry": {"coordinates":[115.75608800000001,-32.36647],"type":"Point"}
}