{
  "type": "Feature",
  "properties": {
    "iso:country":"AU",
    "sg:address":"263a Princes Hwy",
    "sg:city":"Ulladulla",
    "sg:phone":"+61 2 4455 1693",
    "sg:postcode":"2539",
    "sg:province":"NSW",
    "wof:name":"Premier Linings",
    "wof:placetype":"venue"
},
  "geometry": {"coordinates":[150.467086792,-35.371673584],"type":"Point"}
}