{
  "type": "Feature",
  "properties": {
    "addr:full":"Lvl 10 / 135 King St Sydney NSW 2000",
    "addr:housenumber":"/ 135",
    "addr:postcode":"2000",
    "addr:street":"King St",
    "iso:country":"AU",
    "sg:address":"Lvl 10 / 135 King St",
    "sg:city":"Sydney",
    "sg:classifiers":[
        {
            "category":"Insurance",
            "subcategory":"Title Insurance",
            "type":"Services"
        }
    ],
    "sg:phone":"+61 2 9231 0122",
    "sg:postcode":"2000",
    "sg:province":"NSW",
    "sg:tags":[
        "searcher"
    ],
    "wof:name":"LegalStream Australia P/L",
    "wof:placetype":"venue"
},
  "geometry": {"coordinates":[151.208908081,-33.8690719604],"type":"Point"}
}