{
  "type": "Feature",
  "properties": {
    "iso:country":"AU",
    "sg:address":"Fy 6/ 7 Greaves St",
    "sg:city":"Dandenong",
    "sg:classifiers":[
        {
            "category":"Retail",
            "subcategory":"Auto Repair",
            "type":"Services"
        }
    ],
    "sg:phone":"+61 3 9793 9250",
    "sg:postcode":"3175",
    "sg:province":"VIC",
    "sg:tags":[
        "repairer",
        "motor",
        "engineer"
    ],
    "wof:name":"Volks-Delux Restorations",
    "wof:placetype":"venue"
},
  "geometry": {"coordinates":[145.207885742,-37.9919509888],"type":"Point"}
}