{
  "type": "Feature",
  "properties": {
    "addr:full":"13 Mein St Scarborough QLD 4020",
    "addr:housenumber":"13",
    "addr:postcode":"4020",
    "addr:street":"Mein St",
    "iso:country":"AU",
    "sg:address":"13 Mein St",
    "sg:city":"Scarborough",
    "sg:classifiers":[
        {
            "category":"Professional",
            "subcategory":"Art Services",
            "type":"Services"
        }
    ],
    "sg:phone":"+61 7 3880 0700",
    "sg:postcode":"4020",
    "sg:province":"QLD",
    "sg:tags":[
        "interior",
        "decorator"
    ],
    "wof:name":"Pamela Pappin Interior Designer",
    "wof:placetype":"venue"
},
  "geometry": {"coordinates":[153.11286899999999,-27.203993],"type":"Point"}
}