{
  "type": "Feature",
  "properties": {
    "iso:country":"AU",
    "sg:address":"Reekara Rd",
    "sg:city":"Yambacoona",
    "sg:classifiers":[
        {
            "category":"Building & Trades",
            "subcategory":"Landscaping Services",
            "type":"Services"
        }
    ],
    "sg:phone":"+61 3 6463 1154",
    "sg:postcode":"7256",
    "sg:province":"TAS",
    "sg:tags":[
        "grazier"
    ],
    "wof:name":"Terry D R",
    "wof:placetype":"venue"
},
  "geometry": {"coordinates":[143.94578552199999,-39.7548294067],"type":"Point"}
}