{
  "type": "Feature",
  "properties": {
    "addr:full":"Shop 7 141 Walker St North Sydney NSW 2060",
    "addr:housenumber":"shop 7 141",
    "addr:postcode":"2060",
    "addr:street":"Walker St",
    "iso:country":"AU",
    "sg:address":"Shop 7 141 Walker St",
    "sg:city":"North Sydney",
    "sg:classifiers":[
        {
            "category":"Travel",
            "subcategory":"Travel Agent",
            "type":"Entertainment"
        }
    ],
    "sg:phone":"+61 2 9966 1100",
    "sg:postcode":"2060",
    "sg:province":"NSW",
    "sg:tags":[
        "consultant"
    ],
    "wof:name":"Travelworld North Sydney",
    "wof:placetype":"venue"
},
  "geometry": {"coordinates":[151.20919799800001,-33.8379745483],"type":"Point"}
}