{
  "type": "Feature",
  "properties": {
    "iso:country":"AU",
    "sg:address":"261 William St",
    "sg:city":"Melbourne",
    "sg:classifiers":[
        {
            "category":"Fast Food",
            "type":"Food & Drink"
        }
    ],
    "sg:phone":"+61 3 9670 1454",
    "sg:postcode":"3000",
    "sg:province":"VIC",
    "sg:tags":[
        "away",
        "take"
    ],
    "wof:name":"Maya's Kitchen",
    "wof:placetype":"venue"
},
  "geometry": {"coordinates":[144.95681762699999,-37.8129615784],"type":"Point"}
}