{
  "type": "Feature",
  "properties": {
    "iso:country":"AU",
    "sg:address":"82 Meeks Rd",
    "sg:city":"Marrickville",
    "sg:classifiers":[
        {
            "category":"Manufacturing",
            "subcategory":"Building Materials",
            "type":"Manufacturing & Wholesale Goods"
        }
    ],
    "sg:phone":"+61 2 9519 6060",
    "sg:postcode":"2204",
    "sg:province":"NSW",
    "sg:tags":[
        "equipment",
        "handling"
    ],
    "wof:name":"Batcor Industries Pty Ltd",
    "wof:placetype":"venue"
},
  "geometry": {"coordinates":[151.160202,-33.913521],"type":"Point"}
}