{
  "type": "Feature",
  "properties": {
    "iso:country":"AU",
    "sg:address":"Suite 3 Level 1 27 Bower St",
    "sg:city":"Maitland",
    "sg:classifiers":[
        {
            "category":"Professional",
            "subcategory":"Employment Agencies",
            "type":"Services"
        }
    ],
    "sg:phone":"+61 2 4931 6911",
    "sg:postcode":"2320",
    "sg:province":"NSW",
    "wof:name":"Wesley Uniting Employment",
    "wof:placetype":"venue"
},
  "geometry": {"coordinates":[151.570114136,-32.7078857422],"type":"Point"}
}