{
  "type": "Feature",
  "properties": {
    "addr:full":"192 Raglan St Mosman NSW 2088",
    "addr:housenumber":"192",
    "addr:postcode":"2088",
    "addr:street":"Raglan St",
    "iso:country":"AU",
    "sg:address":"192 Raglan St",
    "sg:city":"Mosman",
    "sg:classifiers":[
        {
            "category":"Health Services",
            "subcategory":"Doctor",
            "type":"Services"
        }
    ],
    "sg:phone":"+61 2 9968 3232",
    "sg:postcode":"2088",
    "sg:province":"NSW",
    "sg:tags":[
        "medical",
        "practitioner"
    ],
    "wof:name":"Dunn Joseph",
    "wof:placetype":"venue"
},
  "geometry": {"coordinates":[151.24537658700001,-33.83070755],"type":"Point"}
}