{
  "type": "Feature",
  "properties": {
    "addr:full":"PO Box 375 Port Melbourne VIC 3207",
    "addr:postcode":"3207",
    "iso:country":"AU",
    "sg:address":"PO Box 375",
    "sg:city":"Port Melbourne",
    "sg:classifiers":[
        {
            "category":"Professional",
            "subcategory":"Art Services",
            "type":"Services"
        }
    ],
    "sg:phone":"+61 409 301 275",
    "sg:postcode":"3207",
    "sg:province":"VIC",
    "sg:tags":[
        "interior",
        "decorator"
    ],
    "wof:name":"Camilla Molders Design",
    "wof:placetype":"venue"
},
  "geometry": {"coordinates":[144.92337000000001,-37.83424],"type":"Point"}
}