{
  "type": "Feature",
  "properties": {
    "addr:full":"28 Buckingham Ave Springvale VIC 3171",
    "addr:housenumber":"28",
    "addr:postcode":"3171",
    "addr:street":"Buckingham Ave",
    "iso:country":"AU",
    "sg:address":"28 Buckingham Ave",
    "sg:city":"Springvale",
    "sg:classifiers":[
        {
            "category":"Food & Beverages",
            "subcategory":"Bakery",
            "type":"Retail Goods"
        }
    ],
    "sg:phone":"+61 3 9540 3551",
    "sg:postcode":"3171",
    "sg:province":"VIC",
    "sg:tags":[
        "cake",
        "shop",
        "pastry"
    ],
    "wof:name":"Yawtay",
    "wof:placetype":"venue"
},
  "geometry": {"coordinates":[145.15135192899999,-37.9490509033],"type":"Point"}
}