{
  "type": "Feature",
  "properties": {
    "addr:full":"224 Springvale Rd Springvale NSW 2650",
    "addr:housenumber":"224",
    "addr:postcode":"2650",
    "addr:street":"Springvale Rd",
    "iso:country":"AU",
    "sg:address":"224 Springvale Rd",
    "sg:city":"Springvale",
    "sg:classifiers":[
        {
            "category":"Casinos & Gambling",
            "type":"Entertainment"
        }
    ],
    "sg:phone":"+61 2 9546 8407",
    "sg:postcode":"2650",
    "sg:province":"NSW",
    "sg:tags":[
        "lottery",
        "agent"
    ],
    "wof:name":"The Lotto Shop Springvale",
    "wof:placetype":"venue"
},
  "geometry": {"coordinates":[147.35325622600001,-35.168800354],"type":"Point"}
}