{
  "type": "Feature",
  "properties": {
    "addr:full":"Langlands Park, Main Ave Coorparoo QLD 4151",
    "addr:postcode":"4151",
    "addr:street":"Main Ave",
    "iso:country":"AU",
    "sg:address":"Langlands Park, Main Ave",
    "sg:city":"Coorparoo",
    "sg:classifiers":[
        {
            "category":"Retail",
            "subcategory":"Event Space",
            "type":"Services"
        }
    ],
    "sg:phone":"+61 7 3397 8885",
    "sg:postcode":"4151",
    "sg:province":"QLD",
    "sg:tags":[
        "function",
        "organiser"
    ],
    "wof:name":"Easts Leagues Club",
    "wof:placetype":"venue"
},
  "geometry": {"coordinates":[153.050704956,-27.4985198975],"type":"Point"}
}