{
  "type": "Feature",
  "properties": {
    "iso:country":"AU",
    "sg:address":"Tuggeranong Pool Anketell St",
    "sg:city":"Greenway",
    "sg:classifiers":[
        {
            "category":"Cafe",
            "type":"Food & Drink"
        }
    ],
    "sg:phone":"+61 2 6293 3302",
    "sg:postcode":"2900",
    "sg:province":"ACT",
    "wof:name":"Lakeside Cafe",
    "wof:placetype":"venue"
},
  "geometry": {"coordinates":[149.069015503,-35.417427063],"type":"Point"}
}