{
  "type": "Feature",
  "properties": {
    "addr:full":"12 Jindabyne St Frenchs Forest NSW 2086",
    "addr:housenumber":"12",
    "addr:postcode":"2086",
    "addr:street":"Jindabyne St",
    "iso:country":"AU",
    "sg:address":"12 Jindabyne St",
    "sg:city":"Frenchs Forest",
    "sg:classifiers":[
        {
            "category":"Professional",
            "subcategory":"Art Services",
            "type":"Services"
        }
    ],
    "sg:phone":"+61 2 9453 2384",
    "sg:postcode":"2086",
    "sg:province":"NSW",
    "sg:tags":[
        "interior",
        "designer"
    ],
    "wof:name":"Biba Design",
    "wof:placetype":"venue"
},
  "geometry": {"coordinates":[151.22807312,-33.7403411865],"type":"Point"}
}