{
  "type": "Feature",
  "properties": {
    "iso:country":"AU",
    "sg:address":"145 Victoria Ave",
    "sg:city":"Chatswood",
    "sg:classifiers":[
        {
            "category":"Communications",
            "subcategory":"Film & Video Production",
            "type":"Services"
        }
    ],
    "sg:phone":"+61 2 9417 8572",
    "sg:postcode":"2067",
    "sg:province":"NSW",
    "sg:tags":[
        "dvd",
        "library"
    ],
    "wof:name":"Janets Art Supplies Pty Ltd",
    "wof:placetype":"venue"
},
  "geometry": {"coordinates":[151.195220947,-33.7923812866],"type":"Point"}
}