{
  "type": "Feature",
  "properties": {
    "addr:full":"54 Belmore Rd Lorn NSW 2320",
    "addr:housenumber":"54",
    "addr:postcode":"2320",
    "addr:street":"Belmore Rd",
    "iso:country":"AU",
    "sg:address":"54 Belmore Rd",
    "sg:city":"Lorn",
    "sg:classifiers":[
        {
            "category":"Retail",
            "subcategory":"Repair Shop",
            "type":"Services"
        }
    ],
    "sg:phone":"+61 2 4933 3720",
    "sg:postcode":"2320",
    "sg:province":"NSW",
    "sg:tags":[
        "mending",
        "clothing",
        "alteration"
    ],
    "wof:name":"Frances Norrie",
    "wof:placetype":"venue"
},
  "geometry": {"coordinates":[151.55946350100001,-32.7270507812],"type":"Point"}
}