{
  "type": "Feature",
  "properties": {
    "addr:full":"27 Robinson St Riverstone NSW 2765",
    "addr:housenumber":"27",
    "addr:postcode":"2765",
    "addr:street":"Robinson St",
    "iso:country":"AU",
    "sg:address":"27 Robinson St",
    "sg:city":"Riverstone",
    "sg:classifiers":[
        {
            "category":"Building & Trades",
            "subcategory":"Construction",
            "type":"Services"
        }
    ],
    "sg:phone":"+61 2 9627 6244",
    "sg:postcode":"2765",
    "sg:province":"NSW",
    "sg:tags":[
        "contractor"
    ],
    "wof:name":"Bula Constructions Pty Ltd",
    "wof:placetype":"venue"
},
  "geometry": {"coordinates":[150.865631103,-33.6838264465],"type":"Point"}
}