{
  "type": "Feature",
  "properties": {
    "addr:full":"Shp 7/ 1 Mudgeeraba Rd Worongary QLD 4213",
    "addr:housenumber":"/ 1",
    "addr:postcode":"4213",
    "addr:street":"Mudgeeraba Rd",
    "iso:country":"AU",
    "sg:address":"Shp 7/ 1 Mudgeeraba Rd",
    "sg:city":"Worongary",
    "sg:classifiers":[
        {
            "category":"Personal",
            "subcategory":"Beauty Salon",
            "type":"Services"
        }
    ],
    "sg:phone":"+61 7 5522 8509",
    "sg:postcode":"4213",
    "sg:province":"QLD",
    "sg:tags":[
        "hairdresser"
    ],
    "wof:name":"Karma In Hair",
    "wof:placetype":"venue"
},
  "geometry": {"coordinates":[153.35496520999999,-28.0528259277],"type":"Point"}
}