{
  "type": "Feature",
  "properties": {
    "addr:full":"59 Church St Brighton VIC 3186",
    "addr:housenumber":"59",
    "addr:postcode":"3186",
    "addr:street":"Church St",
    "iso:country":"AU",
    "sg:address":"59 Church St",
    "sg:city":"Brighton",
    "sg:classifiers":[
        {
            "category":"Shopping",
            "subcategory":"Clothing, Apparel, & Fashions",
            "type":"Retail Goods"
        }
    ],
    "sg:phone":"+61 3 9592 8772",
    "sg:postcode":"3186",
    "sg:province":"VIC",
    "sg:tags":[
        "boutique"
    ],
    "wof:name":"Silver Boutique",
    "wof:placetype":"venue"
},
  "geometry": {"coordinates":[144.99449157699999,-37.9137382507],"type":"Point"}
}