{
  "type": "Feature",
  "properties": {
    "addr:full":"1/ 75 Teatree Ave Leeton NSW 2705",
    "addr:housenumber":"/ 75",
    "addr:postcode":"2705",
    "addr:street":"Teatree Ave",
    "iso:country":"AU",
    "sg:address":"1/ 75 Teatree Ave",
    "sg:city":"Leeton",
    "sg:classifiers":[
        {
            "category":"Home & Garden",
            "subcategory":"Hardware",
            "type":"Retail Goods"
        }
    ],
    "sg:phone":"+61 2 6953 7911",
    "sg:postcode":"2705",
    "sg:province":"NSW",
    "sg:tags":[
        "tarpaulin"
    ],
    "wof:name":"Mahers Tarps",
    "wof:placetype":"venue"
},
  "geometry": {"coordinates":[146.39784240700001,-34.5499992371],"type":"Point"}
}