{
  "type": "Feature",
  "properties": {
    "addr:full":"Freeman Rd Richlands QLD 4077",
    "addr:postcode":"4077",
    "addr:street":"Freeman Rd",
    "iso:country":"AU",
    "sg:address":"Freeman Rd",
    "sg:city":"Richlands",
    "sg:classifiers":[
        {
            "category":"Professional",
            "type":"Services"
        }
    ],
    "sg:phone":"+61 7 3375 3176",
    "sg:postcode":"4077",
    "sg:province":"QLD",
    "sg:tags":[
        "forwarding",
        "agent",
        "transport"
    ],
    "wof:name":"Murphy E & Sons Pty Ltd",
    "wof:placetype":"venue"
},
  "geometry": {"coordinates":[152.95428466800001,-27.5964202881],"type":"Point"}
}