{
  "type": "Feature",
  "properties": {
    "addr:full":"38 Prospect St Box Hill VIC 3128",
    "addr:housenumber":"38",
    "addr:postcode":"3128",
    "addr:street":"Prospect St",
    "iso:country":"AU",
    "sg:address":"38 Prospect St",
    "sg:city":"Box Hill",
    "sg:classifiers":[
        {
            "category":"Professional",
            "subcategory":"Engineering",
            "type":"Services"
        }
    ],
    "sg:phone":"+61 3 9899 8299",
    "sg:postcode":"3128",
    "sg:province":"VIC",
    "sg:tags":[
        "engineer",
        "designing"
    ],
    "wof:name":"Robertson Consulting Group Pty Ltd",
    "wof:placetype":"venue"
},
  "geometry": {"coordinates":[145.11656189000001,-37.8178062439],"type":"Point"}
}