{
  "type": "Feature",
  "properties": {
    "iso:country":"AU",
    "sg:address":"16 Northcote St",
    "sg:city":"Bellingen",
    "sg:classifiers":[
        {
            "category":"Retail",
            "subcategory":"Auto Rental",
            "type":"Services"
        }
    ],
    "sg:phone":"+61 2 6655 0270",
    "sg:postcode":"2454",
    "sg:province":"NSW",
    "sg:tags":[
        "chauffeur",
        "car",
        "hire",
        "driven",
        "limousine"
    ],
    "wof:name":"Fairytale Carriages",
    "wof:placetype":"venue"
},
  "geometry": {"coordinates":[152.896469,-30.45677],"type":"Point"}
}