{
  "type": "Feature",
  "properties": {
    "iso:country":"AU",
    "sg:address":"Res 47 Biala St",
    "sg:city":"Gunning",
    "sg:classifiers":[
        {
            "category":"Health Services",
            "subcategory":"Health Practitioner",
            "type":"Services"
        }
    ],
    "sg:phone":"+61 428 261 080",
    "sg:postcode":"2581",
    "sg:province":"NSW",
    "sg:tags":[
        "alternative"
    ],
    "wof:name":"A New Day Natural Healing",
    "wof:placetype":"venue"
},
  "geometry": {"coordinates":[149.26307678200001,-34.7814674377],"type":"Point"}
}