{
  "type": "Feature",
  "properties": {
    "iso:country":"AU",
    "sg:address":"Shop 3/ 14 Distribution Ave",
    "sg:city":"Molendinar",
    "sg:classifiers":[
        {
            "category":"Building & Trades",
            "subcategory":"Construction",
            "type":"Services"
        }
    ],
    "sg:phone":"+61 7 5564 6616",
    "sg:postcode":"4214",
    "sg:province":"QLD",
    "sg:tags":[
        "welding"
    ],
    "wof:name":"Gold Coast Welding Supplies",
    "wof:placetype":"venue"
},
  "geometry": {"coordinates":[153.35699462900001,-27.9776382446],"type":"Point"}
}