{
  "type": "Feature",
  "properties": {
    "iso:country":"AU",
    "sg:address":"725 Point Nepean Rd",
    "sg:city":"Rosebud",
    "sg:classifiers":[
        {
            "category":"Retail",
            "subcategory":"Auto Repair",
            "type":"Services"
        }
    ],
    "sg:phone":"+61 3 5986 1533",
    "sg:postcode":"3939",
    "sg:province":"VIC",
    "sg:tags":[
        "repairer",
        "motor",
        "engineer"
    ],
    "wof:name":"Two-Way Motors (Vic) Pty Ltd",
    "wof:placetype":"venue"
},
  "geometry": {"coordinates":[144.92326355,-38.3507003784],"type":"Point"}
}