{
  "type": "Feature",
  "properties": {
    "addr:full":"Gallery 2/ 792 Pacific Pde Currumbin Beach QLD 4223",
    "addr:housenumber":"2 / 792",
    "addr:postcode":"4223",
    "addr:street":"Pacific Pde Currumbin",
    "iso:country":"AU",
    "sg:address":"Gallery 2/ 792 Pacific Pde",
    "sg:city":"Currumbin Beach",
    "sg:classifiers":[
        {
            "category":"Professional",
            "subcategory":"Art Services",
            "type":"Services"
        }
    ],
    "sg:phone":"+61 7 5534 1530",
    "sg:postcode":"4223",
    "sg:province":"QLD",
    "sg:tags":[
        "interior",
        "decorator"
    ],
    "wof:name":"The Way of Design - Currumbin",
    "wof:placetype":"venue"
},
  "geometry": {"coordinates":[153.48793029800001,-28.1310043335],"type":"Point"}
}