{
  "type": "Feature",
  "properties": {
    "addr:full":"31 Pavers Crcle Malaga WA 6090",
    "addr:housenumber":"31",
    "addr:postcode":"6090",
    "addr:street":"Pavers Crcle",
    "iso:country":"AU",
    "sg:address":"31 Pavers Crcle",
    "sg:city":"Malaga",
    "sg:classifiers":[
        {
            "category":"Professional",
            "subcategory":"Engineering",
            "type":"Services"
        }
    ],
    "sg:phone":"+61 8 9249 4900",
    "sg:postcode":"6090",
    "sg:province":"WA",
    "sg:tags":[
        "engineer"
    ],
    "wof:name":"Swedeweld Pty Ltd",
    "wof:placetype":"venue"
},
  "geometry": {"coordinates":[115.897476196,-31.8568401337],"type":"Point"}
}