{
  "type": "Feature",
  "properties": {
    "addr:full":"14 Spencer St Tumby Bay SA 5605",
    "addr:housenumber":"14",
    "addr:postcode":"5605",
    "addr:street":"Spencer St",
    "iso:country":"AU",
    "sg:address":"14 Spencer St",
    "sg:city":"Tumby Bay",
    "sg:classifiers":[
        {
            "category":"Shopping",
            "type":"Retail Goods"
        }
    ],
    "sg:phone":"+61 8 8688 2206",
    "sg:postcode":"5605",
    "sg:province":"SA",
    "sg:tags":[
        "agent",
        "stock"
    ],
    "wof:name":"Elders Limited",
    "wof:placetype":"venue"
},
  "geometry": {"coordinates":[136.10169999999999,-34.375996],"type":"Point"}
}