{
  "type": "Feature",
  "properties": {
    "addr:full":"96 Epping Rd North Ryde NSW 2113",
    "addr:housenumber":"96",
    "addr:postcode":"2113",
    "addr:street":"Epping Rd",
    "iso:country":"AU",
    "sg:address":"96 Epping Rd",
    "sg:city":"North Ryde",
    "sg:classifiers":[
        {
            "category":"Donuts",
            "subcategory":"None",
            "type":"Food & Drink"
        }
    ],
    "sg:phone":"+61 2 9888 6063",
    "sg:postcode":"2113",
    "sg:province":"NSW",
    "sg:tags":[
        "die",
        "engraver",
        "sinker"
    ],
    "wof:name":"Kim Engraving Services",
    "wof:placetype":"venue"
},
  "geometry": {"coordinates":[151.126785278,-33.7887649536],"type":"Point"}
}