{
  "type": "Feature",
  "properties": {
    "addr:full":"15a George St Warilla NSW 2528",
    "addr:housenumber":"15a",
    "addr:postcode":"2528",
    "addr:street":"George St",
    "iso:country":"AU",
    "sg:address":"15a George St",
    "sg:city":"Warilla",
    "sg:classifiers":[
        {
            "category":"Health Services",
            "subcategory":"Doctor",
            "type":"Services"
        }
    ],
    "sg:phone":"+61 2 4296 6922",
    "sg:postcode":"2528",
    "sg:province":"NSW",
    "sg:tags":[
        "medical",
        "practitioner"
    ],
    "wof:name":"Mayne Laverty Pathology Collection Centres",
    "wof:placetype":"venue"
},
  "geometry": {"coordinates":[150.861602783,-34.5524520874],"type":"Point"}
}