{
  "type": "Feature",
  "properties": {
    "iso:country":"AU",
    "sg:address":"632 Princes Hwy",
    "sg:city":"Tempe",
    "sg:classifiers":[
        {
            "category":"Retail",
            "subcategory":"Storage",
            "type":"Services"
        }
    ],
    "sg:phone":"+61 2 9559 5588",
    "sg:postcode":"2044",
    "sg:province":"NSW",
    "wof:name":"Kennards Self Storage",
    "wof:placetype":"venue"
},
  "geometry": {"coordinates":[151.165497,-33.921368],"type":"Point"}
}