{
  "type": "Feature",
  "properties": {
    "iso:country":"AU",
    "sg:address":"39 Noble St",
    "sg:city":"Rodd Point",
    "sg:classifiers":[
        {
            "category":"Building & Trades",
            "subcategory":"Plumbing",
            "type":"Services"
        }
    ],
    "sg:phone":"+61 2 9712 5717",
    "sg:postcode":"2046",
    "sg:province":"NSW",
    "sg:tags":[
        "plumber",
        "gasfitters"
    ],
    "wof:name":"Scandinavian Plumbing",
    "wof:placetype":"venue"
},
  "geometry": {"coordinates":[151.13786300000001,-33.865269],"type":"Point"}
}