{
  "type": "Feature",
  "properties": {
    "iso:country":"AU",
    "sg:address":"210 Bell St",
    "sg:city":"Preston",
    "sg:classifiers":[
        {
            "category":"Retail",
            "subcategory":"Auto Repair",
            "type":"Services"
        }
    ],
    "sg:phone":"+61 3 9484 7977",
    "sg:postcode":"3072",
    "sg:province":"VIC",
    "sg:tags":[
        "beater",
        "painter",
        "panel"
    ],
    "wof:name":"Bubbles Car Care & Cafe",
    "wof:placetype":"venue"
},
  "geometry": {"coordinates":[145.01620483400001,-37.7464485168],"type":"Point"}
}