{
  "type": "Feature",
  "properties": {
    "iso:country":"AU",
    "sg:address":"83 Lather Rd",
    "sg:city":"Bellbowrie",
    "sg:classifiers":[
        {
            "category":"Professional",
            "subcategory":"Employment Agencies",
            "type":"Services"
        }
    ],
    "sg:phone":"+61 7 3202 9499",
    "sg:postcode":"4070",
    "sg:province":"QLD",
    "sg:tags":[
        "entertainer",
        "agent"
    ],
    "wof:name":"Top Entertainment Promotions",
    "wof:placetype":"venue"
},
  "geometry": {"coordinates":[152.89848327600001,-27.5576286316],"type":"Point"}
}