{
  "type": "Feature",
  "properties": {
    "addr:full":"87 Main Rd Yankalilla SA 5203",
    "addr:housenumber":"87",
    "addr:postcode":"5203",
    "addr:street":"Main Rd",
    "iso:country":"AU",
    "sg:address":"87 Main Rd",
    "sg:city":"Yankalilla",
    "sg:classifiers":[
        {
            "category":"Shopping",
            "subcategory":"Party Supplies",
            "type":"Retail Goods"
        }
    ],
    "sg:phone":"+61 8 8558 3804",
    "sg:postcode":"5203",
    "sg:province":"SA",
    "sg:tags":[
        "hire",
        "costume"
    ],
    "wof:name":"Yankalilla Trading Store",
    "wof:placetype":"venue"
},
  "geometry": {"coordinates":[138.33192443900001,-35.4533843994],"type":"Point"}
}