{
  "type": "Feature",
  "properties": {
    "addr:full":"16-18 Beaumont St Hamilton NSW 2303",
    "addr:housenumber":"16-18",
    "addr:postcode":"2303",
    "addr:street":"Beaumont St",
    "iso:country":"AU",
    "sg:address":"16-18 Beaumont St",
    "sg:city":"Hamilton",
    "sg:classifiers":[
        {
            "category":"Building & Trades",
            "subcategory":"Locksmith",
            "type":"Services"
        }
    ],
    "sg:phone":"+61 2 4969 5809",
    "sg:postcode":"2303",
    "sg:province":"NSW",
    "sg:tags":[
        "lock"
    ],
    "wof:name":"Hamilton All Hours Locksmiths",
    "wof:placetype":"venue"
},
  "geometry": {"coordinates":[151.747345,-32.921066],"type":"Point"}
}