{
  "type": "Feature",
  "properties": {
    "addr:full":"24 Erin St Richmond VIC 3121",
    "addr:housenumber":"24",
    "addr:postcode":"3121",
    "addr:street":"Erin St",
    "iso:country":"AU",
    "sg:address":"24 Erin St",
    "sg:city":"Richmond",
    "sg:classifiers":[
        {
            "category":"Health Services",
            "subcategory":"Doctor",
            "type":"Services"
        }
    ],
    "sg:phone":"+61 3 9429 1629",
    "sg:postcode":"3121",
    "sg:province":"VIC",
    "sg:tags":[
        "medical",
        "practitioner"
    ],
    "wof:name":"Leeton John",
    "wof:placetype":"venue"
},
  "geometry": {"coordinates":[144.991790772,-37.8165779114],"type":"Point"}
}