{
  "type": "Feature",
  "properties": {
    "addr:full":"505 Luxford Rd Shalvey NSW 2770",
    "addr:housenumber":"505",
    "addr:postcode":"2770",
    "addr:street":"Luxford Rd",
    "iso:country":"AU",
    "sg:address":"505 Luxford Rd",
    "sg:city":"Shalvey",
    "sg:classifiers":[
        {
            "category":"Building & Trades",
            "subcategory":"Construction",
            "type":"Services"
        }
    ],
    "sg:phone":"+61 2 9628 0620",
    "sg:postcode":"2770",
    "sg:province":"NSW",
    "sg:tags":[
        "concrete",
        "contractor"
    ],
    "wof:name":"Twin Cut Enterprise Concrete Cutting Specialists Pty Ltd",
    "wof:placetype":"venue"
},
  "geometry": {"coordinates":[150.807006836,-33.7294845581],"type":"Point"}
}