{
  "type": "Feature",
  "properties": {
    "addr:full":"32 Cessna Drv Caboolture QLD 4510",
    "addr:housenumber":"32",
    "addr:postcode":"4510",
    "addr:street":"Cessna Drv",
    "iso:country":"AU",
    "sg:address":"32 Cessna Drv",
    "sg:city":"Caboolture",
    "sg:classifiers":[
        {
            "category":"Home & Garden",
            "subcategory":"Garden Supply",
            "type":"Retail Goods"
        }
    ],
    "sg:phone":"+61 7 5499 3282",
    "sg:postcode":"4510",
    "sg:province":"QLD",
    "sg:tags":[
        "equipment"
    ],
    "wof:name":"Yardquip",
    "wof:placetype":"venue"
},
  "geometry": {"coordinates":[152.98477199999999,-27.085558],"type":"Point"}
}