{
  "type": "Feature",
  "properties": {
    "addr:full":"3 Morris St Mayfield West NSW 2304",
    "addr:housenumber":"3",
    "addr:postcode":"2304",
    "addr:street":"Morris St",
    "iso:country":"AU",
    "sg:address":"3 Morris St",
    "sg:city":"Mayfield West",
    "sg:classifiers":[
        {
            "category":"Utilities",
            "subcategory":"Refuse",
            "type":"Services"
        }
    ],
    "sg:phone":"+61 1300 763 540",
    "sg:postcode":"2304",
    "sg:province":"NSW",
    "sg:tags":[
        "remover",
        "rubbish"
    ],
    "wof:name":"Bagmor Group Pty Ltd",
    "wof:placetype":"venue"
},
  "geometry": {"coordinates":[151.72032165499999,-32.8921508789],"type":"Point"}
}