{
  "type": "Feature",
  "properties": {
    "addr:full":"4/ 40 Station St Bayswater VIC 3153",
    "addr:housenumber":"/ 40",
    "addr:postcode":"3153",
    "addr:street":"Station St",
    "iso:country":"AU",
    "sg:address":"4/ 40 Station St",
    "sg:city":"Bayswater",
    "sg:classifiers":[
        {
            "category":"Building & Trades",
            "subcategory":"Cleaning & Sanitation",
            "type":"Services"
        }
    ],
    "sg:phone":"+61 1300 365 155",
    "sg:postcode":"3153",
    "sg:province":"VIC",
    "sg:tags":[
        "duct"
    ],
    "wof:name":"Dust King",
    "wof:placetype":"venue"
},
  "geometry": {"coordinates":[145.266357422,-37.8410949707],"type":"Point"}
}