{
  "type": "Feature",
  "properties": {
    "addr:full":"11 Jealous Rd Bundaberg QLD 4670",
    "addr:housenumber":"11",
    "addr:postcode":"4670",
    "addr:street":"Jealous Rd",
    "iso:country":"AU",
    "sg:address":"11 Jealous Rd",
    "sg:city":"Bundaberg",
    "sg:classifiers":[
        {
            "category":"Retail",
            "subcategory":"Storage",
            "type":"Services"
        }
    ],
    "sg:phone":"+61 7 4153 3606",
    "sg:postcode":"4670",
    "sg:province":"QLD",
    "wof:name":"Jealous Road Storage",
    "wof:placetype":"venue"
},
  "geometry": {"coordinates":[152.37652587900001,-24.8512020111],"type":"Point"}
}