{
  "type": "Feature",
  "properties": {
    "addr:full":"20 Quinlan Ave St Marys SA 5042",
    "addr:housenumber":"20",
    "addr:postcode":"5042",
    "addr:street":"Quinlan Ave",
    "iso:country":"AU",
    "sg:address":"20 Quinlan Ave",
    "sg:city":"St Marys",
    "sg:classifiers":[
        {
            "category":"Home & Garden",
            "subcategory":"Building Materials",
            "type":"Retail Goods"
        }
    ],
    "sg:phone":"+61 8 8276 6314",
    "sg:postcode":"5042",
    "sg:province":"SA",
    "sg:tags":[
        "shutter",
        "roller",
        "grille"
    ],
    "wof:name":"The Shutter House",
    "wof:placetype":"venue"
},
  "geometry": {"coordinates":[138.57957500000001,-35.006042],"type":"Point"}
}