{
  "type": "Feature",
  "properties": {
    "addr:full":"14 Cadow St Pymble NSW 2073",
    "addr:housenumber":"14",
    "addr:postcode":"2073",
    "addr:street":"Cadow St",
    "iso:country":"AU",
    "sg:address":"14 Cadow St",
    "sg:city":"Pymble",
    "sg:classifiers":[
        {
            "category":"Building & Trades",
            "subcategory":"Pest Control",
            "type":"Services"
        }
    ],
    "sg:phone":"+61 2 9498 2335",
    "sg:postcode":"2073",
    "sg:province":"NSW",
    "sg:tags":[
        "controller",
        "automatic"
    ],
    "wof:name":"Enlog Systems",
    "wof:placetype":"venue"
},
  "geometry": {"coordinates":[151.135894775,-33.7581329346],"type":"Point"}
}