{
  "type": "Feature",
  "properties": {
    "iso:country":"AU",
    "sg:address":"636a Wyndham St",
    "sg:city":"Shepparton",
    "sg:classifiers":[
        {
            "category":"Real Estate",
            "subcategory":"Real Estate Agent",
            "type":"Services"
        }
    ],
    "sg:phone":"+61 3 5831 4600",
    "sg:postcode":"3630",
    "sg:province":"VIC",
    "wof:name":"Settlers Realty Pty Ltd",
    "wof:placetype":"venue"
},
  "geometry": {"coordinates":[145.394805908,-36.4003181458],"type":"Point"}
}