{
  "type": "Feature",
  "properties": {
    "iso:country":"AU",
    "sg:address":"366 High St",
    "sg:city":"Kangaroo Flat",
    "sg:classifiers":[
        {
            "category":"Autos & Motor Vehicles",
            "subcategory":"Auto Supplies",
            "type":"Retail Goods"
        }
    ],
    "sg:phone":"+61 3 5447 2694",
    "sg:postcode":"3555",
    "sg:province":"VIC",
    "sg:tags":[
        "camper-trailers",
        "caravan",
        "equipment"
    ],
    "wof:name":"Central Victorian Caravan Services",
    "wof:placetype":"venue"
},
  "geometry": {"coordinates":[144.24418640100001,-36.7957687378],"type":"Point"}
}