{
  "type": "Feature",
  "properties": {
    "addr:full":"5 Sturt St Ballarat VIC 3350",
    "addr:housenumber":"5",
    "addr:postcode":"3350",
    "addr:street":"Sturt St",
    "iso:country":"AU",
    "sg:address":"5 Sturt St",
    "sg:city":"Ballarat",
    "sg:classifiers":[
        {
            "category":"Food & Beverages",
            "subcategory":"Bakery",
            "type":"Retail Goods"
        }
    ],
    "sg:phone":"+61 3 5333 3688",
    "sg:postcode":"3350",
    "sg:province":"VIC",
    "sg:tags":[
        "cake",
        "shop",
        "pastry"
    ],
    "wof:name":"King Hot Bread",
    "wof:placetype":"venue"
},
  "geometry": {"coordinates":[143.86029099999999,-37.56255],"type":"Point"}
}