{
  "type": "Feature",
  "properties": {
    "iso:country":"AU",
    "sg:address":"22 Angus Ave",
    "sg:city":"Kandos",
    "sg:classifiers":[
        {
            "category":"Cafe",
            "type":"Food & Drink"
        }
    ],
    "sg:phone":"+61 2 6379 4258",
    "sg:postcode":"2848",
    "sg:province":"NSW",
    "wof:name":"Mountain View Bakery & Coffee",
    "wof:placetype":"venue"
},
  "geometry": {"coordinates":[149.97267199999999,-32.858929],"type":"Point"}
}