{
  "type": "Feature",
  "properties": {
    "addr:full":"695 The Horsley Drv Smithfield NSW 2164",
    "addr:housenumber":"695",
    "addr:postcode":"2164",
    "addr:street":"The Horsley Drv",
    "iso:country":"AU",
    "sg:address":"695 The Horsley Drv",
    "sg:city":"Smithfield",
    "sg:classifiers":[
        {
            "category":"Professional",
            "subcategory":"Printing & Photocopies",
            "type":"Services"
        }
    ],
    "sg:phone":"+61 2 9604 3800",
    "sg:postcode":"2164",
    "sg:province":"NSW",
    "sg:tags":[
        "rubber",
        "stamp",
        "metal"
    ],
    "wof:name":"Reliable Stationery & Art Supplies",
    "wof:placetype":"venue"
},
  "geometry": {"coordinates":[150.938842773,-33.8530960083],"type":"Point"}
}