{
  "type": "Feature",
  "properties": {
    "iso:country":"AU",
    "sg:address":"13 Cowper Rd",
    "sg:city":"Sorrento",
    "sg:classifiers":[
        {
            "category":"Home & Garden",
            "subcategory":"Building Materials",
            "type":"Retail Goods"
        }
    ],
    "sg:phone":"+61 8 9447 3960",
    "sg:postcode":"6020",
    "sg:province":"WA",
    "sg:tags":[
        "lawn",
        "cutting",
        "maintenance"
    ],
    "wof:name":"Jones B T & M K",
    "wof:placetype":"venue"
},
  "geometry": {"coordinates":[115.75389099100001,-31.8316707611],"type":"Point"}
}