{
  "type": "Feature",
  "properties": {
    "iso:country":"AU",
    "sg:address":"20 Marine Pde",
    "sg:city":"Port Vincent",
    "sg:classifiers":[
        {
            "category":"Fast Food",
            "type":"Food & Drink"
        }
    ],
    "sg:phone":"+61 8 8853 7008",
    "sg:postcode":"5581",
    "sg:province":"SA",
    "sg:tags":[
        "away",
        "take"
    ],
    "wof:name":"Port Vincent Kiosk",
    "wof:placetype":"venue"
},
  "geometry": {"coordinates":[137.85939025900001,-34.7757568359],"type":"Point"}
}