{
  "type": "Feature",
  "properties": {
    "iso:country":"AU",
    "sg:address":"PO Box 1123",
    "sg:city":"Newcastle",
    "sg:classifiers":[
        {
            "category":"Mining & Drilling",
            "type":"Manufacturing & Wholesale Goods"
        }
    ],
    "sg:phone":"+61 1800 654 943",
    "sg:postcode":"2300",
    "sg:province":"NSW",
    "sg:tags":[
        "boring",
        "contractor"
    ],
    "wof:name":"Blueprint Built",
    "wof:placetype":"venue"
},
  "geometry": {"coordinates":[151.780136,-32.930859],"type":"Point"}
}