{
  "type": "Feature",
  "properties": {
    "iso:country":"AU",
    "sg:address":"Shop 127T Bay City Plz Moorabool St",
    "sg:city":"Geelong",
    "sg:classifiers":[
        {
            "category":"Food & Beverages",
            "subcategory":"Bakery",
            "type":"Retail Goods"
        }
    ],
    "sg:phone":"+61 3 5229 7482",
    "sg:postcode":"3220",
    "sg:province":"VIC",
    "sg:tags":[
        "baker"
    ],
    "wof:name":"Brumbys",
    "wof:placetype":"venue"
},
  "geometry": {"coordinates":[144.35479699999999,-38.160118],"type":"Point"}
}