{
  "type": "Feature",
  "properties": {
    "addr:full":"10 Speedwell Pl South Windsor NSW 2756",
    "addr:housenumber":"10",
    "addr:postcode":"2756",
    "addr:street":"Speedwell Pl",
    "iso:country":"AU",
    "sg:address":"10 Speedwell Pl",
    "sg:city":"South Windsor",
    "sg:phone":"+61 2 4578 1558",
    "sg:postcode":"2756",
    "sg:province":"NSW",
    "wof:name":"Richmond Tank Works",
    "wof:placetype":"venue"
},
  "geometry": {"coordinates":[150.815719605,-33.6283988953],"type":"Point"}
}