{
  "type": "Feature",
  "properties": {
    "addr:full":"4/ 43 Booner St Hawks Nest NSW 2324",
    "addr:housenumber":"/ 43",
    "addr:postcode":"2324",
    "addr:street":"Booner St",
    "iso:country":"AU",
    "sg:address":"4/ 43 Booner St",
    "sg:city":"Hawks Nest",
    "sg:classifiers":[
        {
            "category":"Banks & Credit Unions",
            "subcategory":"Bank",
            "type":"Services"
        }
    ],
    "sg:phone":"+61 2 4997 1434",
    "sg:postcode":"2324",
    "sg:province":"NSW",
    "sg:tags":[
        "broker",
        "mortgage"
    ],
    "wof:name":"Smartline",
    "wof:placetype":"venue"
},
  "geometry": {"coordinates":[152.17778015100001,-32.6728668213],"type":"Point"}
}