{
  "type": "Feature",
  "properties": {
    "iso:country":"AU",
    "sg:address":"154 Greville St",
    "sg:city":"Prahran",
    "sg:classifiers":[
        {
            "category":"Shopping",
            "subcategory":"Clothing, Apparel, & Fashions",
            "type":"Retail Goods"
        }
    ],
    "sg:phone":"+61 3 9510 5700",
    "sg:postcode":"3181",
    "sg:province":"VIC",
    "sg:tags":[
        "lady",
        "wear"
    ],
    "wof:name":"Renegade Cyberstore Clothing",
    "wof:placetype":"venue"
},
  "geometry": {"coordinates":[144.99176025400001,-37.8494377136],"type":"Point"}
}