{
  "type": "Feature",
  "properties": {
    "iso:country":"AU",
    "sg:address":"U4/ 219 Brisbane Water Drv",
    "sg:city":"Point Clare",
    "sg:classifiers":[
        {
            "category":"Wholesale",
            "subcategory":"Painting Supplies",
            "type":"Manufacturing & Wholesale Goods"
        }
    ],
    "sg:phone":"+61 2 4322 6353",
    "sg:postcode":"2250",
    "sg:province":"NSW",
    "sg:tags":[
        "product",
        "cleaning"
    ],
    "wof:name":"Starklean",
    "wof:placetype":"venue"
},
  "geometry": {"coordinates":[151.319122314,-33.4361343384],"type":"Point"}
}