{
  "type": "Feature",
  "properties": {
    "addr:full":"26 Murdo Rd Clayton North VIC 3168",
    "addr:housenumber":"26",
    "addr:postcode":"3168",
    "addr:street":"Murdo Rd",
    "iso:country":"AU",
    "sg:address":"26 Murdo Rd",
    "sg:city":"Clayton North",
    "sg:classifiers":[
        {
            "category":"Utilities",
            "subcategory":"Electric",
            "type":"Services"
        }
    ],
    "sg:phone":"+61 3 9545 5252",
    "sg:postcode":"3168",
    "sg:province":"VIC",
    "sg:tags":[
        "electrical",
        "contractor"
    ],
    "wof:name":"G C Electrical Services",
    "wof:placetype":"venue"
},
  "geometry": {"coordinates":[145.14105224599999,-37.9188346863],"type":"Point"}
}