{
  "type": "Feature",
  "properties": {
    "addr:full":"134 Sydney Rd Fairlight NSW 2094",
    "addr:housenumber":"134",
    "addr:postcode":"2094",
    "addr:street":"Sydney Rd",
    "iso:country":"AU",
    "sg:address":"134 Sydney Rd",
    "sg:city":"Fairlight",
    "sg:classifiers":[
        {
            "category":"Personal",
            "subcategory":"Beauty Salon",
            "type":"Services"
        }
    ],
    "sg:phone":"+61 2 9949 5572",
    "sg:postcode":"2094",
    "sg:province":"NSW",
    "sg:tags":[
        "hairdresser"
    ],
    "wof:name":"The Snip Inn",
    "wof:placetype":"venue"
},
  "geometry": {"coordinates":[151.27703857399999,-33.7958183289],"type":"Point"}
}