{
  "type": "Feature",
  "properties": {
    "addr:full":"Next Generation Memorial Drv North Adelaide SA 5006",
    "addr:postcode":"5006",
    "addr:street":"Memorial Drv",
    "iso:country":"AU",
    "sg:address":"Next Generation Memorial Drv",
    "sg:city":"North Adelaide",
    "sg:classifiers":[
        {
            "category":"Health Services",
            "subcategory":"Health Practitioner",
            "type":"Services"
        }
    ],
    "sg:phone":"+61 8 8231 1034",
    "sg:postcode":"5006",
    "sg:province":"SA",
    "sg:tags":[
        "naturopath"
    ],
    "wof:name":"Thosona Wellness & Lifestyle Sanctuaries",
    "wof:placetype":"venue"
},
  "geometry": {"coordinates":[138.59492492699999,-34.9090194702],"type":"Point"}
}