{
  "type": "Feature",
  "properties": {
    "iso:country":"AU",
    "sg:address":"1a Elden St",
    "sg:city":"Toukley",
    "sg:classifiers":[
        {
            "category":"Health Services",
            "subcategory":"Doctor",
            "type":"Services"
        }
    ],
    "sg:phone":"+61 2 4396 5266",
    "sg:postcode":"2263",
    "sg:province":"NSW",
    "sg:tags":[
        "medical",
        "practitioner"
    ],
    "wof:name":"Suri Rahul",
    "wof:placetype":"venue"
},
  "geometry": {"coordinates":[151.540024,-33.263123],"type":"Point"}
}