{
  "type": "Feature",
  "properties": {
    "addr:full":"99 Pittwater Rd Gladesville NSW 2111",
    "addr:housenumber":"99",
    "addr:postcode":"2111",
    "addr:street":"Pittwater Rd",
    "iso:country":"AU",
    "sg:address":"99 Pittwater Rd",
    "sg:city":"Gladesville",
    "sg:classifiers":[
        {
            "category":"Personal",
            "subcategory":"Beauty Salon",
            "type":"Services"
        }
    ],
    "sg:phone":"+61 2 9817 8481",
    "sg:postcode":"2111",
    "sg:province":"NSW",
    "sg:tags":[
        "hairdresser"
    ],
    "wof:name":"Rant n Rave",
    "wof:placetype":"venue"
},
  "geometry": {"coordinates":[151.13418579099999,-33.8224487305],"type":"Point"}
}