{
  "type": "Feature",
  "properties": {
    "addr:full":"Cnr Abbotts Rd & England St Dandenong South VIC 3164",
    "addr:postcode":"3164",
    "addr:street":"Cnr Abbotts Rd & England St",
    "iso:country":"AU",
    "sg:address":"Cnr Abbotts Rd & England St",
    "sg:city":"Dandenong South",
    "sg:classifiers":[
        {
            "category":"Utilities",
            "subcategory":"Refuse",
            "type":"Services"
        }
    ],
    "sg:phone":"+61 3 9706 5443",
    "sg:postcode":"3164",
    "sg:province":"VIC",
    "sg:tags":[
        "disposal",
        "reduction",
        "waste"
    ],
    "wof:name":"Tyre-A-Way",
    "wof:placetype":"venue"
},
  "geometry": {"coordinates":[145.21859741200001,-38.0324211121],"type":"Point"}
}