{
  "type": "Feature",
  "properties": {
    "addr:full":"9 Terence Crt Doncaster VIC 3108",
    "addr:housenumber":"9",
    "addr:postcode":"3108",
    "addr:street":"Terence Crt",
    "iso:country":"AU",
    "sg:address":"9 Terence Crt",
    "sg:city":"Doncaster",
    "sg:classifiers":[
        {
            "category":"Professional",
            "subcategory":"Computer Services",
            "type":"Services"
        }
    ],
    "sg:phone":"+61 3 9840 1525",
    "sg:postcode":"3108",
    "sg:province":"VIC",
    "sg:tags":[
        "consultant",
        "system"
    ],
    "wof:name":"PBP Pty Ltd",
    "wof:placetype":"venue"
},
  "geometry": {"coordinates":[145.12112426799999,-37.7800331116],"type":"Point"}
}