{
  "type": "Feature",
  "properties": {
    "iso:country":"AU",
    "sg:address":"Un 2205, 120 Mary St",
    "sg:city":"Brisbane",
    "sg:classifiers":[
        {
            "category":"Professional",
            "subcategory":"Management & Consulting",
            "type":"Services"
        }
    ],
    "sg:phone":"+61 7 3210 0386",
    "sg:postcode":"4000",
    "sg:province":"QLD",
    "sg:tags":[
        "project"
    ],
    "wof:name":"Ryan Group Consulting Qld Pty Ltd",
    "wof:placetype":"venue"
},
  "geometry": {"coordinates":[153.02828979500001,-27.4710998535],"type":"Point"}
}