{
  "type": "Feature",
  "properties": {
    "addr:full":"79 Bayview St Williamstown VIC 3016",
    "addr:housenumber":"79",
    "addr:postcode":"3016",
    "addr:street":"Bayview St",
    "iso:country":"AU",
    "sg:address":"79 Bayview St",
    "sg:city":"Williamstown",
    "sg:classifiers":[
        {
            "category":"Professional",
            "subcategory":"Management & Consulting",
            "type":"Services"
        }
    ],
    "sg:phone":"+61 3 9397 0175",
    "sg:postcode":"3016",
    "sg:province":"VIC",
    "sg:tags":[
        "consultant"
    ],
    "wof:name":"Silent Partners Learning Services",
    "wof:placetype":"venue"
},
  "geometry": {"coordinates":[144.88612365700001,-37.8615150452],"type":"Point"}
}