{
  "type": "Feature",
  "properties": {
    "addr:full":"347 Riversdale Rd Hawthorn East VIC 3123",
    "addr:housenumber":"347",
    "addr:postcode":"3123",
    "addr:street":"Riversdale Rd",
    "iso:country":"AU",
    "sg:address":"347 Riversdale Rd",
    "sg:city":"Hawthorn East",
    "sg:classifiers":[
        {
            "category":"Banks & Credit Unions",
            "subcategory":"Investment Brokerage",
            "type":"Services"
        }
    ],
    "sg:phone":"+61 3 9882 9699",
    "sg:postcode":"3123",
    "sg:province":"VIC",
    "wof:name":"Campbell R.L.",
    "wof:placetype":"venue"
},
  "geometry": {"coordinates":[145.04997253400001,-37.8304252625],"type":"Point"}
}