{
  "type": "Feature",
  "properties": {
    "iso:country":"AU",
    "sg:address":"Hanger58 Anderson Drv",
    "sg:city":"Parafield Airport",
    "sg:classifiers":[
        {
            "category":"Manufacturing",
            "subcategory":"Aerospace",
            "type":"Manufacturing & Wholesale Goods"
        }
    ],
    "sg:phone":"+61 8 8258 2209",
    "sg:postcode":"5106",
    "sg:province":"SA",
    "sg:tags":[
        "equipment",
        "aircraft",
        "maintenance"
    ],
    "wof:name":"Riverina Airmotive Pty Ltd",
    "wof:placetype":"venue"
},
  "geometry": {"coordinates":[138.637466,-34.787701],"type":"Point"}
}