{
  "type": "Feature",
  "properties": {
    "addr:full":"Level 1, 379 Victoria Ave Chatswood NSW 2067",
    "addr:housenumber":"379",
    "addr:postcode":"2067",
    "addr:street":"Victoria Ave",
    "iso:country":"AU",
    "sg:address":"Level 1, 379 Victoria Ave",
    "sg:city":"Chatswood",
    "sg:classifiers":[
        {
            "category":"Health Services",
            "subcategory":"Optometrist",
            "type":"Services"
        }
    ],
    "sg:phone":"+61 2 9412 4596",
    "sg:postcode":"2067",
    "sg:province":"NSW",
    "wof:name":"Chandler Leonie",
    "wof:placetype":"venue"
},
  "geometry": {"coordinates":[151.18539428700001,-33.795463562],"type":"Point"}
}