{
  "type": "Feature",
  "properties": {
    "iso:country":"AU",
    "sg:address":"Shp7/ 55 Central Rd",
    "sg:city":"Rossmoyne",
    "sg:classifiers":[
        {
            "category":"Cafe",
            "type":"Food & Drink"
        }
    ],
    "sg:phone":"+61 8 9259 5555",
    "sg:postcode":"6148",
    "sg:province":"WA",
    "wof:name":"Flames Cafe",
    "wof:placetype":"venue"
},
  "geometry": {"coordinates":[115.867912,-32.038723],"type":"Point"}
}