{
  "type": "Feature",
  "properties": {
    "iso:country":"AU",
    "sg:address":"Lysander Crs",
    "sg:city":"North Haven",
    "sg:classifiers":[
        {
            "category":"Metro Station",
            "type":"Transportation"
        }
    ],
    "sg:phone":"+61 408 829 752",
    "sg:postcode":"5018",
    "sg:province":"SA",
    "sg:tags":[
        "consultant",
        "marine"
    ],
    "wof:name":"Mensforth Media Pty Ltd",
    "wof:placetype":"venue"
},
  "geometry": {"coordinates":[138.49134826700001,-34.7935714722],"type":"Point"}
}