{
  "type": "Feature",
  "properties": {
    "addr:full":"37 Stratford Pde Stratford QLD 4870",
    "addr:housenumber":"37",
    "addr:postcode":"4870",
    "addr:street":"Stratford Pde",
    "iso:country":"AU",
    "sg:address":"37 Stratford Pde",
    "sg:city":"Stratford",
    "sg:classifiers":[
        {
            "category":"Restaurant",
            "type":"Food & Drink"
        }
    ],
    "sg:phone":"+61 7 4055 1213",
    "sg:postcode":"4870",
    "sg:province":"QLD",
    "wof:name":"Barron River Hotel",
    "wof:placetype":"venue"
},
  "geometry": {"coordinates":[145.734619141,-16.8753223419],"type":"Point"}
}