{
  "type": "Feature",
  "properties": {
    "addr:full":"15 Attenborough St Dandenong VIC 3175",
    "addr:housenumber":"15",
    "addr:postcode":"3175",
    "addr:street":"Attenborough St",
    "iso:country":"AU",
    "sg:address":"15 Attenborough St",
    "sg:city":"Dandenong",
    "sg:classifiers":[
        {
            "category":"Home & Garden",
            "subcategory":"Furniture",
            "type":"Retail Goods"
        }
    ],
    "sg:phone":"+61 3 9791 9500",
    "sg:postcode":"3175",
    "sg:province":"VIC",
    "sg:tags":[
        "business"
    ],
    "wof:name":"Precision",
    "wof:placetype":"venue"
},
  "geometry": {"coordinates":[145.20278930699999,-37.9873886108],"type":"Point"}
}