{
  "type": "Feature",
  "properties": {
    "iso:country":"AU",
    "sg:address":"44 Fennell St",
    "sg:city":"Parramatta",
    "sg:classifiers":[
        {
            "category":"Professional",
            "subcategory":"Detective & Security Services",
            "type":"Services"
        }
    ],
    "sg:phone":"+61 2 9613 3700",
    "sg:postcode":"2150",
    "sg:province":"NSW",
    "sg:tags":[
        "domestic",
        "alarm",
        "commercial",
        "burglar"
    ],
    "wof:name":"KBT Alarm System",
    "wof:placetype":"venue"
},
  "geometry": {"coordinates":[151.009643555,-33.805973053],"type":"Point"}
}