{
  "type": "Feature",
  "properties": {
    "iso:country":"AU",
    "sg:address":"22 Bennett St",
    "sg:city":"Dee Why",
    "sg:classifiers":[
        {
            "category":"Wholesale",
            "subcategory":"Painting Supplies",
            "type":"Manufacturing & Wholesale Goods"
        }
    ],
    "sg:phone":"+61 2 9981 4273",
    "sg:postcode":"2099",
    "sg:province":"NSW",
    "sg:tags":[
        "equipment",
        "drawing",
        "drafting"
    ],
    "wof:name":"M2 Tech Products",
    "wof:placetype":"venue"
},
  "geometry": {"coordinates":[151.28279113799999,-33.7486915588],"type":"Point"}
}