{
  "type": "Feature",
  "properties": {
    "addr:full":"56 Oxford St Sydney NSW 2000",
    "addr:housenumber":"56",
    "addr:postcode":"2000",
    "addr:street":"Oxford St",
    "iso:country":"AU",
    "sg:address":"56 Oxford St",
    "sg:city":"Sydney",
    "sg:classifiers":[
        {
            "category":"Communications",
            "subcategory":"Film & Video Production",
            "type":"Services"
        }
    ],
    "sg:phone":"+61 2 9331 3675",
    "sg:postcode":"2000",
    "sg:province":"NSW",
    "sg:tags":[
        "made",
        "clothing",
        "custom"
    ],
    "wof:name":"Zink G.A. & Sons",
    "wof:placetype":"venue"
},
  "geometry": {"coordinates":[151.21449279800001,-33.8784866333],"type":"Point"}
}