{
  "type": "Feature",
  "properties": {
    "addr:full":"5 Lachlan Ave Sylvania NSW 2224",
    "addr:housenumber":"5",
    "addr:postcode":"2224",
    "addr:street":"Lachlan Ave",
    "iso:country":"AU",
    "sg:address":"5 Lachlan Ave",
    "sg:city":"Sylvania",
    "sg:classifiers":[
        {
            "category":"Insurance",
            "subcategory":"Insurance Agent",
            "type":"Services"
        }
    ],
    "sg:phone":"+61 2 9522 9999",
    "sg:postcode":"2224",
    "sg:province":"NSW",
    "wof:name":"Stephens Integrated Solutions",
    "wof:placetype":"venue"
},
  "geometry": {"coordinates":[151.11651611299999,-34.0132827759],"type":"Point"}
}