{
  "type": "Feature",
  "properties": {
    "addr:full":"10 Tandara Pl Forster NSW 2428",
    "addr:housenumber":"10",
    "addr:postcode":"2428",
    "addr:street":"Tandara Pl",
    "iso:country":"AU",
    "sg:address":"10 Tandara Pl",
    "sg:city":"Forster",
    "sg:classifiers":[
        {
            "category":"Building & Trades",
            "subcategory":"Plumbing",
            "type":"Services"
        }
    ],
    "sg:phone":"+61 2 6555 2859",
    "sg:postcode":"2428",
    "sg:province":"NSW",
    "sg:tags":[
        "plumber",
        "gasfitters"
    ],
    "wof:name":"A.G. McCarthy & Sons Plumbing",
    "wof:placetype":"venue"
},
  "geometry": {"coordinates":[152.532791,-32.211445],"type":"Point"}
}