{
  "type": "Feature",
  "properties": {
    "addr:full":"123 Mitchell Drv Glossodia NSW 2756",
    "addr:housenumber":"123",
    "addr:postcode":"2756",
    "addr:street":"Mitchell Drv",
    "iso:country":"AU",
    "sg:address":"123 Mitchell Drv",
    "sg:city":"Glossodia",
    "sg:classifiers":[
        {
            "category":"Building & Trades",
            "subcategory":"Construction",
            "type":"Services"
        }
    ],
    "sg:phone":"+61 438 750 229",
    "sg:postcode":"2756",
    "sg:province":"NSW",
    "sg:tags":[
        "contractor"
    ],
    "wof:name":"Adlyn Constructions",
    "wof:placetype":"venue"
},
  "geometry": {"coordinates":[150.78120422399999,-33.5259284973],"type":"Point"}
}