{
  "type": "Feature",
  "properties": {
    "addr:full":"62 Towong Rd Corryong VIC 3707",
    "addr:housenumber":"62",
    "addr:postcode":"3707",
    "addr:street":"Towong Rd",
    "iso:country":"AU",
    "sg:address":"62 Towong Rd",
    "sg:city":"Corryong",
    "sg:classifiers":[
        {
            "category":"Retail",
            "subcategory":"Auto Repair",
            "type":"Services"
        }
    ],
    "sg:phone":"+61 2 6076 1267",
    "sg:postcode":"3707",
    "sg:province":"VIC",
    "sg:tags":[
        "repairer",
        "motor",
        "engineer"
    ],
    "wof:name":"Damm's Auto & Diesel Repairs P/L",
    "wof:placetype":"venue"
},
  "geometry": {"coordinates":[147.91169738799999,-36.1907119751],"type":"Point"}
}