{
  "type": "Feature",
  "properties": {
    "addr:full":"U3/ 68 Secam St Mansfield QLD 4122",
    "addr:postcode":"4122",
    "addr:street":"U3 / 68 Secam St",
    "iso:country":"AU",
    "sg:address":"U3/ 68 Secam St",
    "sg:city":"Mansfield",
    "sg:classifiers":[
        {
            "category":"Wholesale",
            "subcategory":"Non-durable Goods",
            "type":"Manufacturing & Wholesale Goods"
        }
    ],
    "sg:phone":"+61 7 3849 2269",
    "sg:postcode":"4122",
    "sg:province":"QLD",
    "sg:tags":[
        "textile"
    ],
    "wof:name":"Glitter And Dance Fabric Specialists",
    "wof:placetype":"venue"
},
  "geometry": {"coordinates":[153.09869384800001,-27.5287017822],"type":"Point"}
}