{
  "type": "Feature",
  "properties": {
    "addr:full":"24 Moorindil St Tewantin QLD 4565",
    "addr:housenumber":"24",
    "addr:postcode":"4565",
    "addr:street":"Moorindil St",
    "iso:country":"AU",
    "sg:address":"24 Moorindil St",
    "sg:city":"Tewantin",
    "sg:classifiers":[
        {
            "category":"Health Services",
            "subcategory":"Doctor",
            "type":"Services"
        }
    ],
    "sg:phone":"+61 7 5482 6140",
    "sg:postcode":"4565",
    "sg:province":"QLD",
    "sg:tags":[
        "podiatrist"
    ],
    "wof:name":"Janet Morgan",
    "wof:placetype":"venue"
},
  "geometry": {"coordinates":[153.034881592,-26.3903636932],"type":"Point"}
}