{
  "type": "Feature",
  "properties": {
    "addr:full":"126 Mason St Mareeba QLD 4880",
    "addr:housenumber":"126",
    "addr:postcode":"4880",
    "addr:street":"Mason St",
    "iso:country":"AU",
    "sg:address":"126 Mason St",
    "sg:city":"Mareeba",
    "sg:classifiers":[
        {
            "category":"Professional",
            "subcategory":"Employment Agencies",
            "type":"Services"
        }
    ],
    "sg:phone":"+61 7 4092 3128",
    "sg:postcode":"4880",
    "sg:province":"QLD",
    "sg:tags":[
        "consultant",
        "corrosion"
    ],
    "wof:name":"Power Blasting",
    "wof:placetype":"venue"
},
  "geometry": {"coordinates":[145.42010498100001,-17.0064678192],"type":"Point"}
}