{
  "type": "Feature",
  "properties": {
    "addr:full":"29 Cressy St Malvern VIC 3144",
    "addr:housenumber":"29",
    "addr:postcode":"3144",
    "addr:street":"Cressy St",
    "iso:country":"AU",
    "sg:address":"29 Cressy St",
    "sg:city":"Malvern",
    "sg:classifiers":[
        {
            "category":"Professional",
            "subcategory":"Employment Agencies",
            "type":"Services"
        }
    ],
    "sg:phone":"+61 3 9822 2896",
    "sg:postcode":"3144",
    "sg:province":"VIC",
    "wof:name":"The Recruitment Firm",
    "wof:placetype":"venue"
},
  "geometry": {"coordinates":[145.04127502399999,-37.8509483337],"type":"Point"}
}