{
  "type": "Feature",
  "properties": {
    "iso:country":"AU",
    "sg:address":"79 Bradley St",
    "sg:city":"Goulburn",
    "sg:phone":"+61 431 388 363",
    "sg:postcode":"2580",
    "sg:province":"NSW",
    "wof:name":"Goulburn Pumps",
    "wof:placetype":"venue"
},
  "geometry": {"coordinates":[149.72000122099999,-34.7481575012],"type":"Point"}
}