{
  "type": "Feature",
  "properties": {
    "addr:full":"363 Lang St Kurri Kurri NSW 2327",
    "addr:housenumber":"363",
    "addr:postcode":"2327",
    "addr:street":"Lang St",
    "iso:country":"AU",
    "sg:address":"363 Lang St",
    "sg:city":"Kurri Kurri",
    "sg:classifiers":[
        {
            "category":"Organizations",
            "subcategory":"Professional Association",
            "type":"Services"
        }
    ],
    "sg:phone":"+61 2 4936 2995",
    "sg:postcode":"2327",
    "sg:province":"NSW",
    "sg:tags":[
        "web",
        "internet"
    ],
    "wof:name":"Our Town Web Design",
    "wof:placetype":"venue"
},
  "geometry": {"coordinates":[151.47239685100001,-32.8221740723],"type":"Point"}
}