{
  "type": "Feature",
  "properties": {
    "iso:country":"AU",
    "sg:address":"49 Pascoe Rd",
    "sg:city":"Ormeau",
    "sg:classifiers":[
        {
            "category":"Utilities",
            "subcategory":"Electric",
            "type":"Services"
        }
    ],
    "sg:phone":"+61 7 5549 3558",
    "sg:postcode":"4208",
    "sg:province":"QLD",
    "sg:tags":[
        "electrical",
        "contractor"
    ],
    "wof:name":"Icp Electrical",
    "wof:placetype":"venue"
},
  "geometry": {"coordinates":[153.230834961,-27.7713375092],"type":"Point"}
}