{
  "type": "Feature",
  "properties": {
    "addr:full":"82 McDowall St Roma QLD 4455",
    "addr:housenumber":"82",
    "addr:postcode":"4455",
    "addr:street":"Mcdowall St",
    "iso:country":"AU",
    "sg:address":"82 McDowall St",
    "sg:city":"Roma",
    "sg:classifiers":[
        {
            "category":"Home & Garden",
            "subcategory":"Carpets & Floor Coverings",
            "type":"Retail Goods"
        }
    ],
    "sg:phone":"+61 7 4622 1999",
    "sg:postcode":"4455",
    "sg:province":"QLD",
    "sg:tags":[
        "mattress"
    ],
    "wof:name":"Homemakers Furniture and Bedding",
    "wof:placetype":"venue"
},
  "geometry": {"coordinates":[148.78973388700001,-26.5717735291],"type":"Point"}
}