{
  "type": "Feature",
  "properties": {
    "iso:country":"AU",
    "sg:address":"14 Brecon St",
    "sg:city":"Lockleys",
    "sg:classifiers":[
        {
            "category":"Building & Trades",
            "subcategory":"Plumbing",
            "type":"Services"
        }
    ],
    "sg:phone":"+61 408 284 947",
    "sg:postcode":"5032",
    "sg:province":"SA",
    "sg:tags":[
        "plumber",
        "gasfitters"
    ],
    "wof:name":"The Pipe Cleaner",
    "wof:placetype":"venue"
},
  "geometry": {"coordinates":[138.52050781200001,-34.9323768616],"type":"Point"}
}