{
  "type": "Feature",
  "properties": {
    "addr:full":"16/ 223 Hartley St Portsmith QLD 4870",
    "addr:housenumber":"16 / 223",
    "addr:postcode":"4870",
    "addr:street":"Hartley St Portsmith",
    "iso:country":"AU",
    "sg:address":"16/ 223 Hartley St",
    "sg:city":"Portsmith",
    "sg:classifiers":[
        {
            "category":"Building & Trades",
            "subcategory":"Construction",
            "type":"Services"
        }
    ],
    "sg:phone":"+61 7 4035 4433",
    "sg:postcode":"4870",
    "sg:province":"QLD",
    "sg:tags":[
        "industrial",
        "commercial",
        "air conditioning"
    ],
    "wof:name":"Trane Australia",
    "wof:placetype":"venue"
},
  "geometry": {"coordinates":[145.76214599599999,-16.9391765594],"type":"Point"}
}