{
  "type": "Feature",
  "properties": {
    "iso:country":"AU",
    "sg:address":"Cnr North Albany & William Sts",
    "sg:city":"Gosford",
    "sg:classifiers":[
        {
            "category":"Health Services",
            "subcategory":"Chiropractor",
            "type":"Services"
        }
    ],
    "sg:phone":"+61 2 4324 2346",
    "sg:postcode":"2250",
    "sg:province":"NSW",
    "wof:name":"Flynn John & Tuchin Peter",
    "wof:placetype":"venue"
},
  "geometry": {"coordinates":[151.32798767099999,-33.4495162964],"type":"Point"}
}