{
  "type": "Feature",
  "properties": {
    "addr:full":"69 Racecourse Rd Riddells Creek VIC 3431",
    "addr:housenumber":"69",
    "addr:postcode":"3431",
    "addr:street":"Racecourse Rd",
    "iso:country":"AU",
    "sg:address":"69 Racecourse Rd",
    "sg:city":"Riddells Creek",
    "sg:classifiers":[
        {
            "category":"Building & Trades",
            "subcategory":"Plumbing",
            "type":"Services"
        }
    ],
    "sg:phone":"+61 3 5428 6974",
    "sg:postcode":"3431",
    "sg:province":"VIC",
    "sg:tags":[
        "plumber",
        "gasfitters"
    ],
    "wof:name":"Dunny Divers",
    "wof:placetype":"venue"
},
  "geometry": {"coordinates":[144.68772888199999,-37.455947876],"type":"Point"}
}