{
  "type": "Feature",
  "properties": {
    "iso:country":"AU",
    "sg:address":"Cnr Pappas Drv & Berriman Drv",
    "sg:city":"Wangara",
    "sg:classifiers":[
        {
            "category":"Building & Trades",
            "subcategory":"Construction",
            "type":"Services"
        }
    ],
    "sg:phone":"+61 8 9302 1488",
    "sg:postcode":"6065",
    "sg:province":"WA",
    "sg:tags":[
        "contractor"
    ],
    "wof:name":"Allstyle Homes",
    "wof:placetype":"venue"
},
  "geometry": {"coordinates":[115.82624054,-31.7931785583],"type":"Point"}
}