{
  "type": "Feature",
  "properties": {
    "addr:full":"Suite 101 Promenade Mews 137 Laver Drv Robina QLD 4226",
    "addr:housenumber":"137",
    "addr:postcode":"4226",
    "addr:street":"Promenade Mews;Laver Drv",
    "iso:country":"AU",
    "sg:address":"Suite 101 Promenade Mews 137 Laver Drv",
    "sg:city":"Robina",
    "sg:classifiers":[
        {
            "category":"Personal",
            "subcategory":"Beauty Salon",
            "type":"Services"
        }
    ],
    "sg:phone":"+61 7 5578 7988",
    "sg:postcode":"4226",
    "sg:province":"QLD",
    "wof:name":"Java Nails",
    "wof:placetype":"venue"
},
  "geometry": {"coordinates":[153.378829956,-28.0739021301],"type":"Point"}
}