{
  "type": "Feature",
  "properties": {
    "addr:full":"37 Heather Drv Ridgehaven SA 5097",
    "addr:housenumber":"37",
    "addr:postcode":"5097",
    "addr:street":"Heather Drv",
    "iso:country":"AU",
    "sg:address":"37 Heather Drv",
    "sg:city":"Ridgehaven",
    "sg:classifiers":[
        {
            "category":"Real Estate",
            "subcategory":"Real Estate Agent",
            "type":"Services"
        }
    ],
    "sg:phone":"+61 8 8396 1700",
    "sg:postcode":"5097",
    "sg:province":"SA",
    "wof:name":"Lind Real Estate",
    "wof:placetype":"venue"
},
  "geometry": {"coordinates":[138.708984375,-34.8179130554],"type":"Point"}
}