{
  "type": "Feature",
  "properties": {
    "addr:full":"Unit 1, 133 Coreen Ave Penrith NSW 2750",
    "addr:housenumber":"133",
    "addr:postcode":"2750",
    "addr:street":"Coreen Ave",
    "iso:country":"AU",
    "sg:address":"Unit 1, 133 Coreen Ave",
    "sg:city":"Penrith",
    "sg:classifiers":[
        {
            "category":"Building & Trades",
            "subcategory":"Plumbing",
            "type":"Services"
        }
    ],
    "sg:phone":"+61 2 4731 2005",
    "sg:postcode":"2750",
    "sg:province":"NSW",
    "sg:tags":[
        "fitting",
        "hose",
        "supply"
    ],
    "wof:name":"Metropolitan Industrial Supplies",
    "wof:placetype":"venue"
},
  "geometry": {"coordinates":[150.697265625,-33.7440681458],"type":"Point"}
}