{
  "type": "Feature",
  "properties": {
    "iso:country":"AU",
    "sg:address":"23 Brough St",
    "sg:city":"Cobar",
    "sg:classifiers":[
        {
            "category":"Taxi",
            "type":"Transportation"
        }
    ],
    "sg:phone":"+61 2 6836 2423",
    "sg:postcode":"2835",
    "sg:province":"NSW",
    "sg:tags":[
        "cab"
    ],
    "wof:name":"A1 Taxi Cobar",
    "wof:placetype":"venue"
},
  "geometry": {"coordinates":[145.83389299999999,-31.492939],"type":"Point"}
}