{
  "type": "Feature",
  "properties": {
    "iso:country":"AU",
    "sg:address":"Cnr Burnett St & Townsend Rd",
    "sg:city":"Buderim",
    "sg:classifiers":[
        {
            "category":"Social Services",
            "subcategory":"Retirement Home",
            "type":"Services"
        }
    ],
    "sg:phone":"+61 1300 731 202",
    "sg:postcode":"4556",
    "sg:province":"QLD",
    "sg:tags":[
        "village"
    ],
    "wof:name":"EdenLea On Buderim",
    "wof:placetype":"venue"
},
  "geometry": {"coordinates":[153.04881286599999,-26.6876907349],"type":"Point"}
}