{
  "type": "Feature",
  "properties": {
    "addr:full":"34A Archibald St Willagee WA 6156",
    "addr:housenumber":"34a",
    "addr:postcode":"6156",
    "addr:street":"Archibald St",
    "iso:country":"AU",
    "sg:address":"34A Archibald St",
    "sg:city":"Willagee",
    "sg:classifiers":[
        {
            "category":"Health Services",
            "subcategory":"Health Practitioner",
            "type":"Services"
        }
    ],
    "sg:phone":"+61 8 9337 8994",
    "sg:postcode":"6156",
    "sg:province":"WA",
    "sg:tags":[
        "bowen",
        "therapy"
    ],
    "wof:name":"Gail Marlow",
    "wof:placetype":"venue"
},
  "geometry": {"coordinates":[115.81079099999999,-32.053101],"type":"Point"}
}