{
  "type": "Feature",
  "properties": {
    "addr:full":"Hogan Rd Nairne SA 5252",
    "addr:postcode":"5252",
    "addr:street":"Hogan Rd",
    "iso:country":"AU",
    "sg:address":"Hogan Rd",
    "sg:city":"Nairne",
    "sg:classifiers":[
        {
            "category":"Retail",
            "subcategory":"Laundry & Dry Cleaning",
            "type":"Services"
        }
    ],
    "sg:phone":"+61 8 8388 6609",
    "sg:postcode":"5252",
    "sg:province":"SA",
    "sg:tags":[
        "breeder",
        "alpaca",
        "llama"
    ],
    "wof:name":"Stonegate Alpaca",
    "wof:placetype":"venue"
},
  "geometry": {"coordinates":[138.926315308,-35.0416946411],"type":"Point"}
}