{
  "type": "Feature",
  "properties": {
    "addr:full":"Glebe Rd Merewether NSW 2291",
    "addr:postcode":"2291",
    "addr:street":"Glebe Rd",
    "iso:country":"AU",
    "sg:address":"Glebe Rd",
    "sg:city":"Merewether",
    "sg:classifiers":[
        {
            "category":"Building & Trades",
            "subcategory":"Construction",
            "type":"Services"
        }
    ],
    "sg:phone":"+61 421 372 851",
    "sg:postcode":"2291",
    "sg:province":"NSW",
    "sg:tags":[
        "polishing",
        "sanding",
        "floor"
    ],
    "wof:name":"Phoenix Floor Sanding",
    "wof:placetype":"venue"
},
  "geometry": {"coordinates":[151.75050354000001,-32.9380302429],"type":"Point"}
}