{
  "type": "Feature",
  "properties": {
    "addr:full":"8 Comet Ave Netley SA 5037",
    "addr:housenumber":"8",
    "addr:postcode":"5037",
    "addr:street":"Comet Ave",
    "iso:country":"AU",
    "sg:address":"8 Comet Ave",
    "sg:city":"Netley",
    "sg:classifiers":[
        {
            "category":"Home & Garden",
            "subcategory":"Carpets & Floor Coverings",
            "type":"Retail Goods"
        }
    ],
    "sg:phone":"+61 411 334 975",
    "sg:postcode":"5037",
    "sg:province":"SA",
    "sg:tags":[
        "tile",
        "wall",
        "layer"
    ],
    "wof:name":"Austiling",
    "wof:placetype":"venue"
},
  "geometry": {"coordinates":[138.545944214,-34.9544067383],"type":"Point"}
}