{
  "type": "Feature",
  "properties": {
    "iso:country":"AU",
    "sg:address":"193a Bay St",
    "sg:city":"Brighton",
    "sg:classifiers":[
        {
            "category":"Organizations",
            "subcategory":"Community Association",
            "type":"Services"
        }
    ],
    "sg:phone":"+61 3 9596 3922",
    "sg:postcode":"3186",
    "sg:province":"VIC",
    "sg:tags":[
        "cheese",
        "product"
    ],
    "wof:name":"Rogers & Company Foods",
    "wof:placetype":"venue"
},
  "geometry": {"coordinates":[144.998504639,-37.9048347473],"type":"Point"}
}