{
  "type": "Feature",
  "properties": {
    "iso:country":"AU",
    "sg:address":"22 Bourke St",
    "sg:city":"Blacks Beach",
    "sg:classifiers":[
        {
            "category":"Farming",
            "subcategory":"Farm",
            "type":"Manufacturing & Wholesale Goods"
        }
    ],
    "sg:phone":"+61 7 4954 9117",
    "sg:postcode":"4740",
    "sg:province":"QLD",
    "sg:tags":[
        "farmer"
    ],
    "wof:name":"Windsor H C",
    "wof:placetype":"venue"
},
  "geometry": {"coordinates":[149.189728,-21.054089],"type":"Point"}
}