{
  "type": "Feature",
  "properties": {
    "addr:full":"Old Buchan Rd Buchan VIC 3885",
    "addr:postcode":"3885",
    "addr:street":"Buchan Rd",
    "iso:country":"AU",
    "sg:address":"Old Buchan Rd",
    "sg:city":"Buchan",
    "sg:classifiers":[
        {
            "category":"Building & Trades",
            "subcategory":"Construction",
            "type":"Services"
        }
    ],
    "sg:phone":"+61 3 5155 9330",
    "sg:postcode":"3885",
    "sg:province":"VIC",
    "sg:tags":[
        "contractor"
    ],
    "wof:name":"Wheeler C C",
    "wof:placetype":"venue"
},
  "geometry": {"coordinates":[148.169265747,-37.504573822],"type":"Point"}
}