{
  "type": "Feature",
  "properties": {
    "iso:country":"AU",
    "sg:address":"1032 Heidelberg Rd",
    "sg:city":"Ivanhoe",
    "sg:classifiers":[
        {
            "category":"Sports & Exercise",
            "subcategory":"Gym",
            "type":"Entertainment"
        }
    ],
    "sg:phone":"+61 3 9499 4145",
    "sg:postcode":"3079",
    "sg:province":"VIC",
    "sg:tags":[
        "personal",
        "trainer",
        "fitness"
    ],
    "wof:name":"Northern Exposure Personal Training",
    "wof:placetype":"venue"
},
  "geometry": {"coordinates":[145.03924560600001,-37.7753448486],"type":"Point"}
}