{
  "type": "Feature",
  "properties": {
    "addr:full":"15 Vangeli St Arndell Park NSW 2148",
    "addr:housenumber":"15",
    "addr:postcode":"2148",
    "addr:street":"Vangeli St",
    "iso:country":"AU",
    "sg:address":"15 Vangeli St",
    "sg:city":"Arndell Park",
    "sg:classifiers":[
        {
            "category":"Farming",
            "subcategory":"Farm & Veterinary Services",
            "type":"Manufacturing & Wholesale Goods"
        }
    ],
    "sg:phone":"+61 2 9831 6080",
    "sg:postcode":"2148",
    "sg:province":"NSW",
    "sg:tags":[
        "poultry",
        "processing",
        "supply"
    ],
    "wof:name":"Myella Chickens",
    "wof:placetype":"venue"
},
  "geometry": {"coordinates":[150.88328552199999,-33.7912101746],"type":"Point"}
}