{
  "type": "Feature",
  "properties": {
    "addr:full":"Lvl 3 2a Lord St Botany NSW 2019",
    "addr:housenumber":"2a",
    "addr:postcode":"2019",
    "addr:street":"Lord St",
    "iso:country":"AU",
    "sg:address":"Lvl 3 2a Lord St",
    "sg:city":"Botany",
    "sg:classifiers":[
        {
            "category":"Professional",
            "subcategory":"Detective & Security Services",
            "type":"Services"
        }
    ],
    "sg:phone":"+61 2 8336 6100",
    "sg:postcode":"2019",
    "sg:province":"NSW",
    "sg:tags":[
        "consultant",
        "system"
    ],
    "wof:name":"CSI Pacific (AUST) PTY LTD",
    "wof:placetype":"venue"
},
  "geometry": {"coordinates":[151.195220947,-33.9405937195],"type":"Point"}
}