{
  "type": "Feature",
  "properties": {
    "addr:full":"1 Barry Rd Dianella WA 6059",
    "addr:housenumber":"1",
    "addr:postcode":"6059",
    "addr:street":"Barry Rd",
    "iso:country":"AU",
    "sg:address":"1 Barry Rd",
    "sg:city":"Dianella",
    "sg:classifiers":[
        {
            "category":"Building & Trades",
            "subcategory":"Construction",
            "type":"Services"
        }
    ],
    "sg:phone":"+61 8 9276 1778",
    "sg:postcode":"6059",
    "sg:province":"WA",
    "sg:tags":[
        "contractor"
    ],
    "wof:name":"Bianchini M & Sons",
    "wof:placetype":"venue"
},
  "geometry": {"coordinates":[115.86000824,-31.8908901215],"type":"Point"}
}