{
  "type": "Feature",
  "properties": {
    "addr:full":"30 Clayton St Bellevue WA 6056",
    "addr:housenumber":"30",
    "addr:postcode":"6056",
    "addr:street":"Clayton St",
    "iso:country":"AU",
    "sg:address":"30 Clayton St",
    "sg:city":"Bellevue",
    "sg:classifiers":[
        {
            "category":"Home & Garden",
            "subcategory":"Building Materials",
            "type":"Retail Goods"
        }
    ],
    "sg:phone":"+61 8 9274 8077",
    "sg:postcode":"6056",
    "sg:province":"WA",
    "sg:tags":[
        "wall",
        "frame",
        "truss",
        "roof"
    ],
    "wof:name":"Midland Timber Co",
    "wof:placetype":"venue"
},
  "geometry": {"coordinates":[116.01638031,-31.8978061676],"type":"Point"}
}