{
  "type": "Feature",
  "properties": {
    "addr:full":"29 Jansz Crs Griffith ACT 2603",
    "addr:housenumber":"29",
    "addr:postcode":"2603",
    "addr:street":"Jansz Crs",
    "iso:country":"AU",
    "sg:address":"29 Jansz Crs",
    "sg:city":"Griffith",
    "sg:classifiers":[
        {
            "category":"Building & Trades",
            "subcategory":"Construction",
            "type":"Services"
        }
    ],
    "sg:phone":"+61 2 6295 2129",
    "sg:postcode":"2603",
    "sg:province":"ACT",
    "sg:tags":[
        "installation",
        "air conditioning"
    ],
    "wof:name":"Iberia Heating & Airconditioning",
    "wof:placetype":"venue"
},
  "geometry": {"coordinates":[149.14610290499999,-35.3248291016],"type":"Point"}
}