{
  "type": "Feature",
  "properties": {
    "addr:full":"30 Alison Rd Randwick NSW 2031",
    "addr:housenumber":"30",
    "addr:postcode":"2031",
    "addr:street":"Alison Rd",
    "iso:country":"AU",
    "sg:address":"30 Alison Rd",
    "sg:city":"Randwick",
    "sg:classifiers":[
        {
            "category":"Professional",
            "subcategory":"Printing & Photocopies",
            "type":"Services"
        }
    ],
    "sg:phone":"+61 413 803 987",
    "sg:postcode":"2031",
    "sg:province":"NSW",
    "sg:tags":[
        "publishing",
        "desktop"
    ],
    "wof:name":"Future Digital Image",
    "wof:placetype":"venue"
},
  "geometry": {"coordinates":[151.233276367,-33.9073295593],"type":"Point"}
}