{
  "type": "Feature",
  "properties": {
    "addr:full":"355 Scarborough Beach Rd Osborne Park WA 6017",
    "addr:housenumber":"355",
    "addr:postcode":"6017",
    "addr:street":"Scarborough Beach Rd",
    "iso:country":"AU",
    "sg:address":"355 Scarborough Beach Rd",
    "sg:city":"Osborne Park",
    "sg:classifiers":[
        {
            "category":"Banks & Credit Unions",
            "subcategory":"Financial Services",
            "type":"Services"
        }
    ],
    "sg:phone":"+61 8 9208 1450",
    "sg:postcode":"6017",
    "sg:province":"WA",
    "sg:tags":[
        "advisory",
        "planning",
        "retirement"
    ],
    "wof:name":"Cameron Walshe",
    "wof:placetype":"venue"
},
  "geometry": {"coordinates":[115.807891846,-31.9051990509],"type":"Point"}
}