{
  "type": "Feature",
  "properties": {
    "iso:country":"AU",
    "sg:address":"6 Bernadotte St",
    "sg:city":"Riverwood",
    "sg:classifiers":[
        {
            "category":"Social Services",
            "subcategory":"Adult Care",
            "type":"Services"
        }
    ],
    "sg:phone":"+61 418 618 905",
    "sg:postcode":"2210",
    "sg:province":"NSW",
    "sg:tags":[
        "towing"
    ],
    "wof:name":"Reid H & Sons",
    "wof:placetype":"venue"
},
  "geometry": {"coordinates":[151.061539,-33.950722],"type":"Point"}
}