{
  "type": "Feature",
  "properties": {
    "iso:country":"AU",
    "sg:address":"8 Beatty St",
    "sg:city":"Whyalla Playford",
    "sg:classifiers":[
        {
            "category":"Personal",
            "subcategory":"Beauty Salon",
            "type":"Services"
        }
    ],
    "sg:phone":"+61 428 810 025",
    "sg:postcode":"5600",
    "sg:province":"SA",
    "wof:name":"Beauty Enhancement",
    "wof:placetype":"venue"
},
  "geometry": {"coordinates":[137.556534,-33.019676],"type":"Point"}
}