{
  "type": "Feature",
  "properties": {
    "addr:full":"Shop 2 42 Ben Lomond Rd Minto NSW 2566",
    "addr:housenumber":"shop;42",
    "addr:postcode":"2566",
    "addr:street":"Ben Lomond Rd",
    "iso:country":"AU",
    "sg:address":"Shop 2 42 Ben Lomond Rd",
    "sg:city":"Minto",
    "sg:classifiers":[
        {
            "category":"Travel",
            "subcategory":"Travel Agent",
            "type":"Entertainment"
        }
    ],
    "sg:phone":"+61 2 9820 3902",
    "sg:postcode":"2566",
    "sg:province":"NSW",
    "sg:tags":[
        "consultant"
    ],
    "wof:name":"World Wide Travel",
    "wof:placetype":"venue"
},
  "geometry": {"coordinates":[150.848342895,-34.0319061279],"type":"Point"}
}