{
  "type": "Feature",
  "properties": {
    "iso:country":"AU",
    "sg:address":"Suite 11, 177- 199 Pacific Hwy",
    "sg:city":"North Sydney",
    "sg:classifiers":[
        {
            "category":"Health Services",
            "subcategory":"Health Practitioner",
            "type":"Services"
        }
    ],
    "sg:phone":"+61 406 048 448",
    "sg:postcode":"2055",
    "sg:province":"NSW",
    "sg:tags":[
        "naturopath"
    ],
    "wof:name":"Brigit Piekarek",
    "wof:placetype":"venue"
},
  "geometry": {"coordinates":[151.205963,-33.83672],"type":"Point"}
}