{
  "type": "Feature",
  "properties": {
    "iso:country":"AU",
    "sg:address":"1 Eckersley Ave",
    "sg:city":"Buderim",
    "sg:classifiers":[
        {
            "category":"Health Services",
            "subcategory":"Doctor",
            "type":"Services"
        }
    ],
    "sg:phone":"+61 7 5476 9477",
    "sg:postcode":"4556",
    "sg:province":"QLD",
    "sg:tags":[
        "medical",
        "practitioner"
    ],
    "wof:name":"Burr Allan",
    "wof:placetype":"venue"
},
  "geometry": {"coordinates":[153.070846558,-26.6838817596],"type":"Point"}
}