{
  "type": "Feature",
  "properties": {
    "iso:country":"AU",
    "sg:address":"38 Firebrace St",
    "sg:city":"Horsham",
    "sg:classifiers":[
        {
            "category":"Travel",
            "subcategory":"Travel Agent",
            "type":"Entertainment"
        }
    ],
    "sg:phone":"+61 3 5382 6699",
    "sg:postcode":"3400",
    "sg:province":"VIC",
    "sg:tags":[
        "consultant"
    ],
    "wof:name":"Harvey World Travel",
    "wof:placetype":"venue"
},
  "geometry": {"coordinates":[142.199905395,-36.7133598328],"type":"Point"}
}