{
  "type": "Feature",
  "properties": {
    "iso:country":"AU",
    "sg:address":"2925 He Rd",
    "sg:city":"Whittlesea",
    "sg:classifiers":[
        {
            "category":"Farming",
            "subcategory":"Nursery",
            "type":"Manufacturing & Wholesale Goods"
        }
    ],
    "sg:phone":"+61 3 5786 1520",
    "sg:postcode":"3757",
    "sg:province":"VIC",
    "wof:name":"Antique Perennials",
    "wof:placetype":"venue"
},
  "geometry": {"coordinates":[145.118118,-37.511532],"type":"Point"}
}