{
  "type": "Feature",
  "properties": {
    "iso:country":"AU",
    "sg:address":"31 Overseas Drv",
    "sg:city":"Noble Park",
    "sg:classifiers":[
        {
            "category":"Professional",
            "type":"Services"
        }
    ],
    "sg:phone":"+61 3 9790 1566",
    "sg:postcode":"3174",
    "sg:province":"VIC",
    "sg:tags":[
        "transport"
    ],
    "wof:name":"N.P. Distribution",
    "wof:placetype":"venue"
},
  "geometry": {"coordinates":[145.18797302199999,-37.9527015686],"type":"Point"}
}