{
  "type": "Feature",
  "properties": {
    "addr:full":"340 Police Rd Noble Park North VIC 3174",
    "addr:housenumber":"340",
    "addr:postcode":"3174",
    "addr:street":"Police Rd",
    "iso:country":"AU",
    "sg:address":"340 Police Rd",
    "sg:city":"Noble Park North",
    "sg:classifiers":[
        {
            "category":"Health Services",
            "subcategory":"Chiropractor",
            "type":"Services"
        }
    ],
    "sg:phone":"+61 3 9795 1136",
    "sg:postcode":"3174",
    "sg:province":"VIC",
    "wof:name":"Police Rd Chiro Clinic",
    "wof:placetype":"venue"
},
  "geometry": {"coordinates":[145.18986511200001,-37.9372825623],"type":"Point"}
}