{
  "type": "Feature",
  "properties": {
    "addr:full":"48 Melville St Numurkah VIC 3636",
    "addr:housenumber":"48",
    "addr:postcode":"3636",
    "addr:street":"Melville St",
    "iso:country":"AU",
    "sg:address":"48 Melville St",
    "sg:city":"Numurkah",
    "sg:classifiers":[
        {
            "category":"Cafe",
            "type":"Food & Drink"
        }
    ],
    "sg:phone":"+61 3 5862 2505",
    "sg:postcode":"3636",
    "sg:province":"VIC",
    "wof:name":"Brostace Country Kitchen",
    "wof:placetype":"venue"
},
  "geometry": {"coordinates":[145.442260742,-36.0900802612],"type":"Point"}
}