{
  "type": "Feature",
  "properties": {
    "addr:full":"61 Baile Rd Canning Vale WA 6155",
    "addr:housenumber":"61",
    "addr:postcode":"6155",
    "addr:street":"Baile Rd",
    "iso:country":"AU",
    "sg:address":"61 Baile Rd",
    "sg:city":"Canning Vale",
    "sg:classifiers":[
        {
            "category":"Manufacturing",
            "subcategory":"Metals",
            "type":"Manufacturing & Wholesale Goods"
        }
    ],
    "sg:phone":"+61 8 9256 4486",
    "sg:postcode":"6155",
    "sg:province":"WA",
    "sg:tags":[
        "steel",
        "fabricator",
        "mfrs"
    ],
    "wof:name":"Transfloor Truss WA",
    "wof:placetype":"venue"
},
  "geometry": {"coordinates":[115.91100299999999,-32.067368],"type":"Point"}
}