{
  "type": "Feature",
  "properties": {
    "iso:country":"AU",
    "sg:address":"31a Crombie Ave",
    "sg:city":"Bundall",
    "sg:classifiers":[
        {
            "category":"Organizations",
            "subcategory":"Community Association",
            "type":"Services"
        }
    ],
    "sg:phone":"+61 7 5574 0296",
    "sg:postcode":"4217",
    "sg:province":"QLD",
    "sg:tags":[
        "organisation",
        "family",
        "welfare"
    ],
    "wof:name":"Greek Respite Centre",
    "wof:placetype":"venue"
},
  "geometry": {"coordinates":[153.412200928,-28.0029468536],"type":"Point"}
}