{
  "type": "Feature",
  "properties": {
    "addr:full":"115 Glenayr Ave Bondi NSW 2026",
    "addr:housenumber":"115",
    "addr:postcode":"2026",
    "addr:street":"Glenayr Ave",
    "iso:country":"AU",
    "sg:address":"115 Glenayr Ave",
    "sg:city":"Bondi",
    "sg:classifiers":[
        {
            "category":"Education",
            "subcategory":"Kindergarten",
            "type":"Public Place"
        }
    ],
    "sg:phone":"+61 2 9130 1979",
    "sg:postcode":"2026",
    "sg:province":"NSW",
    "sg:tags":[
        "pre-schools"
    ],
    "wof:name":"Moriah College Pre-School",
    "wof:placetype":"venue"
},
  "geometry": {"coordinates":[151.27243042000001,-33.8866653442],"type":"Point"}
}