{
  "type": "Feature",
  "properties": {
    "addr:full":"\"Tunthun\" Racecourse Rd Holbrook NSW 2644",
    "addr:postcode":"2644",
    "addr:street":"Racecourse Rd",
    "iso:country":"AU",
    "sg:address":"\"Tunthun\" Racecourse Rd",
    "sg:city":"Holbrook",
    "sg:classifiers":[
        {
            "category":"Professional",
            "subcategory":"Business Services",
            "type":"Services"
        }
    ],
    "sg:phone":"+61 2 6036 2213",
    "sg:postcode":"2644",
    "sg:province":"NSW",
    "sg:tags":[
        "livestock",
        "transport"
    ],
    "wof:name":"Strong CH & EJ",
    "wof:placetype":"venue"
},
  "geometry": {"coordinates":[147.32911682100001,-35.7083320618],"type":"Point"}
}