{
  "type": "Feature",
  "properties": {
    "iso:country":"AU",
    "sg:address":"1297 South Rd St",
    "sg:city":"Marys",
    "sg:classifiers":[
        {
            "category":"Autos & Motor Vehicles",
            "subcategory":"Automobile Sales",
            "type":"Retail Goods"
        }
    ],
    "sg:phone":"+61 8 8277 1009",
    "sg:postcode":"5042",
    "sg:province":"SA",
    "sg:tags":[
        "car",
        "used"
    ],
    "wof:name":"Ian Hocking Used Car Sales",
    "wof:placetype":"venue"
},
  "geometry": {"coordinates":[138.576126,-35.006886],"type":"Point"}
}