{
  "type": "Feature",
  "properties": {
    "iso:country":"AU",
    "sg:address":"Unit 1/ 2 Norval Crt",
    "sg:city":"Maroochydore",
    "sg:classifiers":[
        {
            "category":"Recreation",
            "type":"Entertainment"
        }
    ],
    "sg:phone":"+61 7 5479 5333",
    "sg:postcode":"4558",
    "sg:province":"QLD",
    "sg:tags":[
        "children's",
        "play",
        "programme"
    ],
    "wof:name":"Maze Mania 4 Kids",
    "wof:placetype":"venue"
},
  "geometry": {"coordinates":[153.094360352,-26.6647262573],"type":"Point"}
}