{
  "type": "Feature",
  "properties": {
    "iso:country":"AU",
    "sg:address":"60 Baroona Rd",
    "sg:city":"Milton",
    "sg:classifiers":[
        {
            "category":"Real Estate",
            "subcategory":"Developer",
            "type":"Services"
        }
    ],
    "sg:phone":"+61 407 676 286",
    "sg:postcode":"4064",
    "sg:province":"QLD",
    "sg:tags":[
        "development"
    ],
    "wof:name":"Terstep Pty Ltd",
    "wof:placetype":"venue"
},
  "geometry": {"coordinates":[153.001098633,-27.4668312073],"type":"Point"}
}