{
  "type": "Feature",
  "properties": {
    "iso:country":"AU",
    "sg:address":"62 Pym St",
    "sg:city":"Dudley Park",
    "sg:classifiers":[
        {
            "category":"Home & Garden",
            "subcategory":"Hardware",
            "type":"Retail Goods"
        }
    ],
    "sg:phone":"+61 8 8340 7488",
    "sg:postcode":"5008",
    "sg:province":"SA",
    "sg:tags":[
        "plumber",
        "supply"
    ],
    "wof:name":"Northern Plumbing Supplies",
    "wof:placetype":"venue"
},
  "geometry": {"coordinates":[138.57772800000001,-34.882065],"type":"Point"}
}