{
  "type": "Feature",
  "properties": {
    "addr:full":"101 Talbragar St Dubbo NSW 2830",
    "addr:housenumber":"101",
    "addr:postcode":"2830",
    "addr:street":"Talbragar St",
    "iso:country":"AU",
    "sg:address":"101 Talbragar St",
    "sg:city":"Dubbo",
    "sg:classifiers":[
        {
            "category":"Professional",
            "subcategory":"Printing & Photocopies",
            "type":"Services"
        }
    ],
    "sg:phone":"+61 2 6882 8230",
    "sg:postcode":"2830",
    "sg:province":"NSW",
    "sg:tags":[
        "embroidery"
    ],
    "sg:website":"http://www.kcprint.com.au",
    "wof:name":"K C Print Shop",
    "wof:placetype":"venue"
},
  "geometry": {"coordinates":[148.60215759299999,-32.2450294495],"type":"Point"}
}