{
  "type": "Feature",
  "properties": {
    "addr:full":"22 Forestway St Frenchs Forest NSW 2086",
    "addr:housenumber":"22",
    "addr:postcode":"2086",
    "addr:street":"Forestway St",
    "iso:country":"AU",
    "sg:address":"22 Forestway St",
    "sg:city":"Frenchs Forest",
    "sg:classifiers":[
        {
            "category":"Health Services",
            "subcategory":"Doctor",
            "type":"Services"
        }
    ],
    "sg:phone":"+61 2 9452 4648",
    "sg:postcode":"2086",
    "sg:province":"NSW",
    "sg:tags":[
        "medical",
        "practitioner"
    ],
    "wof:name":"Lee C G F Dr",
    "wof:placetype":"venue"
},
  "geometry": {"coordinates":[151.23475647000001,-33.7508201599],"type":"Point"}
}