{
  "type": "Feature",
  "properties": {
    "iso:country":"AU",
    "sg:address":"68 Esmond St",
    "sg:city":"Emerald",
    "sg:classifiers":[
        {
            "category":"Building & Trades",
            "subcategory":"Pest Control",
            "type":"Services"
        }
    ],
    "sg:phone":"+61 7 4982 0286",
    "sg:postcode":"4720",
    "sg:province":"QLD",
    "wof:name":"Can Do Pest Control",
    "wof:placetype":"venue"
},
  "geometry": {"coordinates":[148.163834,-23.520006],"type":"Point"}
}