{
  "type": "Feature",
  "properties": {
    "iso:country":"AU",
    "sg:address":"6/ 3",
    "sg:city":"Mertonvale Cct Kingston",
    "sg:classifiers":[
        {
            "category":"Building & Trades",
            "subcategory":"Construction",
            "type":"Services"
        }
    ],
    "sg:phone":"+61 3 6229 1443",
    "sg:postcode":"7050",
    "sg:province":"TAS",
    "sg:tags":[
        "mural"
    ],
    "wof:name":"Guy Richards",
    "wof:placetype":"venue"
},
  "geometry": {"coordinates":[147.294647,-42.981415],"type":"Point"}
}