{
  "type": "Feature",
  "properties": {
    "addr:full":"66 Ryan St Footscray VIC 3011",
    "addr:housenumber":"66",
    "addr:postcode":"3011",
    "addr:street":"Ryan St",
    "iso:country":"AU",
    "sg:address":"66 Ryan St",
    "sg:city":"Footscray",
    "sg:classifiers":[
        {
            "category":"Health Services",
            "subcategory":"Dentist",
            "type":"Services"
        }
    ],
    "sg:phone":"+61 3 9689 8852",
    "sg:postcode":"3011",
    "sg:province":"VIC",
    "wof:name":"Nguyen Tung Dr",
    "wof:placetype":"venue"
},
  "geometry": {"coordinates":[144.90139770499999,-37.7984352112],"type":"Point"}
}