{
  "type": "Feature",
  "properties": {
    "addr:full":"566 Mt Alexander Rd Moonee Ponds VIC 3039",
    "addr:housenumber":"566",
    "addr:postcode":"3039",
    "addr:street":"Mt Alexander Rd",
    "iso:country":"AU",
    "sg:address":"566 Mt Alexander Rd",
    "sg:city":"Moonee Ponds",
    "sg:classifiers":[
        {
            "category":"Communications",
            "subcategory":"Film & Video Production",
            "type":"Services"
        }
    ],
    "sg:phone":"+61 3 9370 5454",
    "sg:postcode":"3039",
    "sg:province":"VIC",
    "sg:tags":[
        "dvd",
        "library"
    ],
    "wof:name":"Video Ezy",
    "wof:placetype":"venue"
},
  "geometry": {"coordinates":[144.9254,-37.769062],"type":"Point"}
}