{
  "type": "Feature",
  "properties": {
    "addr:full":"39a Bank St Port Fairy VIC 3284",
    "addr:housenumber":"39a",
    "addr:postcode":"3284",
    "addr:street":"Bank St",
    "iso:country":"AU",
    "sg:address":"39a Bank St",
    "sg:city":"Port Fairy",
    "sg:classifiers":[
        {
            "category":"Arts & Performance",
            "subcategory":"Art Gallery",
            "type":"Entertainment"
        }
    ],
    "sg:phone":"+61 3 5568 2855",
    "sg:postcode":"3284",
    "sg:province":"VIC",
    "wof:name":"Whale Bone Gallery",
    "wof:placetype":"venue"
},
  "geometry": {"coordinates":[142.234573364,-38.3833045959],"type":"Point"}
}