{
  "type": "Feature",
  "properties": {
    "iso:country":"AU",
    "sg:address":"Marshall St",
    "sg:city":"Bungalow",
    "sg:classifiers":[
        {
            "category":"Building & Trades",
            "subcategory":"Locksmith",
            "type":"Services"
        }
    ],
    "sg:phone":"+61 7 4033 0386",
    "sg:postcode":"4870",
    "sg:province":"QLD",
    "sg:tags":[
        "equipment",
        "operating",
        "door",
        "gate"
    ],
    "wof:name":"Roll-Tech Doors",
    "wof:placetype":"venue"
},
  "geometry": {"coordinates":[145.75033569300001,-16.9397888184],"type":"Point"}
}