{
  "type": "Feature",
  "properties": {
    "iso:country":"AU",
    "sg:address":"63 Bungower Rd",
    "sg:city":"Somerville",
    "sg:classifiers":[
        {
            "category":"Food & Beverages",
            "subcategory":"Fruits & Vegetables",
            "type":"Retail Goods"
        }
    ],
    "sg:phone":"+61 3 5977 8921",
    "sg:postcode":"3912",
    "sg:province":"VIC",
    "sg:tags":[
        "grower"
    ],
    "wof:name":"Gazzola L & G & Sons Pty Ltd",
    "wof:placetype":"venue"
},
  "geometry": {"coordinates":[145.211227417,-38.2387046814],"type":"Point"}
}