{
  "type": "Feature",
  "properties": {
    "iso:country":"AU",
    "sg:address":"2 Mair Crt",
    "sg:city":"Barmera",
    "sg:classifiers":[
        {
            "category":"Retail",
            "subcategory":"Auto Repair",
            "type":"Services"
        }
    ],
    "sg:phone":"+61 8 8588 1457",
    "sg:postcode":"5345",
    "sg:province":"SA",
    "sg:tags":[
        "repairer",
        "motor",
        "engineer"
    ],
    "wof:name":"Draper Dennis",
    "wof:placetype":"venue"
},
  "geometry": {"coordinates":[140.473556519,-34.2526779175],"type":"Point"}
}