{
  "type": "Feature",
  "properties": {
    "addr:full":"26 Commissioner St Cooma NSW 2630",
    "addr:housenumber":"26",
    "addr:postcode":"2630",
    "addr:street":"Commissioner St",
    "iso:country":"AU",
    "sg:address":"26 Commissioner St",
    "sg:city":"Cooma",
    "sg:classifiers":[
        {
            "category":"Health Services",
            "subcategory":"Health Practitioner",
            "type":"Services"
        }
    ],
    "sg:phone":"+61 2 6452 6898",
    "sg:postcode":"2630",
    "sg:province":"NSW",
    "sg:tags":[
        "osteopath"
    ],
    "wof:name":"Graham Dalglish",
    "wof:placetype":"venue"
},
  "geometry": {"coordinates":[149.132354736,-36.2334671021],"type":"Point"}
}