{
  "type": "Feature",
  "properties": {
    "iso:country":"AU",
    "sg:address":"PO Box 412",
    "sg:city":"Bathurst",
    "sg:classifiers":[
        {
            "category":"Building & Trades",
            "subcategory":"Construction",
            "type":"Services"
        }
    ],
    "sg:phone":"+61 418 635 001",
    "sg:postcode":"2795",
    "sg:province":"NSW",
    "sg:tags":[
        "contractor"
    ],
    "wof:name":"Gillbanks Building",
    "wof:placetype":"venue"
},
  "geometry": {"coordinates":[149.573974609,-33.41979599],"type":"Point"}
}