{
  "type": "Feature",
  "properties": {
    "addr:full":"2nd Level 109/ 108 Albert St Brisbane QLD 4000",
    "addr:housenumber":"109 / 108",
    "addr:postcode":"4000",
    "addr:street":"Albert St",
    "iso:country":"AU",
    "sg:address":"2nd Level 109/ 108 Albert St",
    "sg:city":"Brisbane",
    "sg:classifiers":[
        {
            "category":"Personal",
            "subcategory":"Beauty Salon",
            "type":"Services"
        }
    ],
    "sg:phone":"+61 7 3503 2500",
    "sg:postcode":"4000",
    "sg:province":"QLD",
    "sg:tags":[
        "hairdresser"
    ],
    "sg:website":"http://www.gwprivateroom.com.au",
    "wof:name":"GW-Private Room",
    "wof:placetype":"venue"
},
  "geometry": {"coordinates":[153.02719116200001,-27.4718017578],"type":"Point"}
}