{
  "type": "Feature",
  "properties": {
    "addr:full":"Shop 1, 273 Charters Towers Rd Mysterton QLD 4812",
    "addr:housenumber":"shop 1 273",
    "addr:postcode":"4812",
    "addr:street":"Charters Towers Rd",
    "iso:country":"AU",
    "sg:address":"Shop 1, 273 Charters Towers Rd",
    "sg:city":"Mysterton",
    "sg:classifiers":[
        {
            "category":"Education",
            "subcategory":"Vocational School",
            "type":"Public Place"
        }
    ],
    "sg:phone":"+61 7 4755 2977",
    "sg:postcode":"4812",
    "sg:province":"QLD",
    "sg:tags":[
        "beauty"
    ],
    "wof:name":"Katrinas School Of Beauty",
    "wof:placetype":"venue"
},
  "geometry": {"coordinates":[146.796143,-19.289703],"type":"Point"}
}