{
  "type": "Feature",
  "properties": {
    "addr:full":"9 Kinkaid Ave North Plympton SA 5037",
    "addr:housenumber":"9",
    "addr:postcode":"5037",
    "addr:street":"Kinkaid Ave North",
    "iso:country":"AU",
    "sg:address":"9 Kinkaid Ave",
    "sg:city":"North Plympton",
    "sg:classifiers":[
        {
            "category":"Manufacturing",
            "subcategory":"Glass & Minerals",
            "type":"Manufacturing & Wholesale Goods"
        }
    ],
    "sg:phone":"+61 8 8371 3426",
    "sg:postcode":"5037",
    "sg:province":"SA",
    "sg:tags":[
        "case",
        "counter",
        "show"
    ],
    "wof:name":"Showfront",
    "wof:placetype":"venue"
},
  "geometry": {"coordinates":[138.54400634800001,-34.9584617615],"type":"Point"}
}