{
  "type": "Feature",
  "properties": {
    "iso:country":"AU",
    "sg:address":"568 Kessels Rd",
    "sg:city":"MacGregor",
    "sg:classifiers":[
        {
            "category":"Health Services",
            "subcategory":"Health Practitioner",
            "type":"Services"
        }
    ],
    "sg:phone":"+61 7 3343 5494",
    "sg:postcode":"4109",
    "sg:province":"QLD",
    "sg:tags":[
        "physiotherapist"
    ],
    "wof:name":"Bofinger Steven",
    "wof:placetype":"venue"
},
  "geometry": {"coordinates":[153.07142639200001,-27.5615272522],"type":"Point"}
}