{
  "type": "Feature",
  "properties": {
    "iso:country":"AU",
    "sg:address":"76 Rooneys Rd",
    "sg:city":"Warrnambool",
    "sg:classifiers":[
        {
            "category":"Home & Garden",
            "subcategory":"Building Materials",
            "type":"Retail Goods"
        }
    ],
    "sg:phone":"+61 3 5561 4311",
    "sg:postcode":"3280",
    "sg:province":"VIC",
    "sg:tags":[
        "pre-mixed",
        "concrete"
    ],
    "wof:name":"Scotts Concrete Pty. Ltd.",
    "wof:placetype":"venue"
},
  "geometry": {"coordinates":[142.45391845699999,-38.3689651489],"type":"Point"}
}