{
  "type": "Feature",
  "properties": {
    "addr:full":"112 Shute Harbour Rd Cannonvale QLD 4802",
    "addr:housenumber":"112",
    "addr:postcode":"4802",
    "addr:street":"Shute Harbour Rd",
    "iso:country":"AU",
    "sg:address":"112 Shute Harbour Rd",
    "sg:city":"Cannonvale",
    "sg:classifiers":[
        {
            "category":"Recreation",
            "subcategory":"Fishing",
            "type":"Entertainment"
        }
    ],
    "sg:phone":"+61 7 4948 0311",
    "sg:postcode":"4802",
    "sg:province":"QLD",
    "sg:tags":[
        "tackle"
    ],
    "wof:name":"Whitsundays Fishing World",
    "wof:placetype":"venue"
},
  "geometry": {"coordinates":[148.690750122,-20.280714035],"type":"Point"}
}