{
  "type": "Feature",
  "properties": {
    "addr:full":"15 Canham Way Greenwood WA 6024",
    "addr:housenumber":"15",
    "addr:postcode":"6024",
    "addr:street":"Canham Way",
    "iso:country":"AU",
    "sg:address":"15 Canham Way",
    "sg:city":"Greenwood",
    "sg:classifiers":[
        {
            "category":"Professional",
            "subcategory":"Accounting & Tax Preparation",
            "type":"Services"
        }
    ],
    "sg:phone":"+61 8 9342 8899",
    "sg:postcode":"6024",
    "sg:province":"WA",
    "sg:tags":[
        "consultant",
        "taxation"
    ],
    "wof:name":"Tax-Aid",
    "wof:placetype":"venue"
},
  "geometry": {"coordinates":[115.817802429,-31.8210468292],"type":"Point"}
}