{
  "type": "Feature",
  "properties": {
    "addr:full":"838 Beaudesen Rd Coopers Plains QLD 4108",
    "addr:housenumber":"838",
    "addr:postcode":"4108",
    "addr:street":"Beaudesen Rd",
    "iso:country":"AU",
    "sg:address":"838 Beaudesen Rd",
    "sg:city":"Coopers Plains",
    "sg:classifiers":[
        {
            "category":"Autos & Motor Vehicles",
            "subcategory":"Auto Supplies",
            "type":"Retail Goods"
        }
    ],
    "sg:phone":"+61 7 3277 4622",
    "sg:postcode":"4108",
    "sg:province":"QLD",
    "sg:tags":[
        "battery",
        "automotive"
    ],
    "wof:name":"Beaurepaires",
    "wof:placetype":"venue"
},
  "geometry": {"coordinates":[153.02192688,-27.5604763031],"type":"Point"}
}