{
  "type": "Feature",
  "properties": {
    "addr:full":"123- 125 Maroondah Hwy Ringwood VIC 3134",
    "addr:housenumber":"125",
    "addr:postcode":"3134",
    "addr:street":"Maroondah Hwy",
    "iso:country":"AU",
    "sg:address":"123- 125 Maroondah Hwy",
    "sg:city":"Ringwood",
    "sg:classifiers":[
        {
            "category":"Travel",
            "subcategory":"Hotels & Motels",
            "type":"Entertainment"
        }
    ],
    "sg:phone":"+61 3 9870 4211",
    "sg:postcode":"3134",
    "sg:province":"VIC",
    "sg:tags":[
        "accommodation"
    ],
    "wof:name":"Ringwood Saloon Bar The",
    "wof:placetype":"venue"
},
  "geometry": {"coordinates":[145.22630310100001,-37.8160591125],"type":"Point"}
}