{
  "type": "Feature",
  "properties": {
    "addr:full":"62 epping Drv Frenchs Forest NSW 2086",
    "addr:housenumber":"62",
    "addr:postcode":"2086",
    "addr:street":"Epping Drv",
    "iso:country":"AU",
    "sg:address":"62 epping Drv",
    "sg:city":"Frenchs Forest",
    "sg:classifiers":[
        {
            "category":"Sports & Exercise",
            "subcategory":"Gym",
            "type":"Entertainment"
        }
    ],
    "sg:phone":"+61 2 9453 0340",
    "sg:postcode":"2086",
    "sg:province":"NSW",
    "sg:tags":[
        "pilate",
        "method"
    ],
    "wof:name":"The Pilates Room",
    "wof:placetype":"venue"
},
  "geometry": {"coordinates":[151.23219299300001,-33.7468528748],"type":"Point"}
}