{
  "type": "Feature",
  "properties": {
    "addr:full":"U6/ 41 The Strand Rockdale NSW 2216",
    "addr:housenumber":"41",
    "addr:postcode":"2216",
    "addr:street":"U6 /;The Strand",
    "iso:country":"AU",
    "sg:address":"U6/ 41 The Strand",
    "sg:city":"Rockdale",
    "sg:classifiers":[
        {
            "category":"Shopping",
            "subcategory":"Beauty & Cosmetics",
            "type":"Retail Goods"
        }
    ],
    "sg:phone":"+61 2 9599 1569",
    "sg:postcode":"2216",
    "sg:province":"NSW",
    "sg:tags":[
        "equipment",
        "salon",
        "supply"
    ],
    "wof:name":"Sydney Beauty Supplies",
    "wof:placetype":"venue"
},
  "geometry": {"coordinates":[151.15176399999999,-33.960049],"type":"Point"}
}