{
  "type": "Feature",
  "properties": {
    "addr:full":"228a Glenmore Rd Paddington NSW 2021",
    "addr:housenumber":"228a",
    "addr:postcode":"2021",
    "addr:street":"Glenmore Rd",
    "iso:country":"AU",
    "sg:address":"228a Glenmore Rd",
    "sg:city":"Paddington",
    "sg:classifiers":[
        {
            "category":"Health Services",
            "subcategory":"Dentist",
            "type":"Services"
        }
    ],
    "sg:phone":"+61 2 9331 1692",
    "sg:postcode":"2021",
    "sg:province":"NSW",
    "wof:name":"Venclovas Marcus",
    "wof:placetype":"venue"
},
  "geometry": {"coordinates":[151.228424072,-33.8821258545],"type":"Point"}
}