{
  "type": "Feature",
  "properties": {
    "iso:country":"AU",
    "sg:address":"271 Rouse St",
    "sg:city":"Tenterfield",
    "sg:classifiers":[
        {
            "category":"Shopping",
            "subcategory":"Crafts & Fabrics",
            "type":"Retail Goods"
        }
    ],
    "sg:phone":"+61 2 6736 1233",
    "sg:postcode":"2372",
    "sg:province":"NSW",
    "sg:tags":[
        "draper"
    ],
    "wof:name":"Quirks Drapery",
    "wof:placetype":"venue"
},
  "geometry": {"coordinates":[152.01921081500001,-29.0538864136],"type":"Point"}
}