{
  "type": "Feature",
  "properties": {
    "addr:full":"Unit 1/ 29-33 Boland Ave Springwood NSW 2777",
    "addr:housenumber":"/ 29-33",
    "addr:postcode":"2777",
    "addr:street":"Boland Ave",
    "iso:country":"AU",
    "sg:address":"Unit 1/ 29-33 Boland Ave",
    "sg:city":"Springwood",
    "sg:classifiers":[
        {
            "category":"Real Estate",
            "subcategory":"Architect",
            "type":"Services"
        }
    ],
    "sg:phone":"+61 2 4751 8500",
    "sg:postcode":"2777",
    "sg:province":"NSW",
    "sg:tags":[
        "building",
        "designer"
    ],
    "wof:name":"Michael Wiegmann Design Service",
    "wof:placetype":"venue"
},
  "geometry": {"coordinates":[150.566162109,-33.6990470886],"type":"Point"}
}