{
  "type": "Feature",
  "properties": {
    "addr:full":"24 Ellis St Greenslopes QLD 4120",
    "addr:housenumber":"24",
    "addr:postcode":"4120",
    "addr:street":"Ellis St",
    "iso:country":"AU",
    "sg:address":"24 Ellis St",
    "sg:city":"Greenslopes",
    "sg:classifiers":[
        {
            "category":"Building & Trades",
            "subcategory":"Construction",
            "type":"Services"
        }
    ],
    "sg:phone":"+61 7 3324 0694",
    "sg:postcode":"4120",
    "sg:province":"QLD",
    "sg:tags":[
        "industrial",
        "commercial",
        "air conditioning"
    ],
    "wof:name":"D & K Plumbing & Airconditioning Pty Ltd",
    "wof:placetype":"venue"
},
  "geometry": {"coordinates":[153.04742431599999,-27.4997787476],"type":"Point"}
}