{
  "type": "Feature",
  "properties": {
    "addr:full":"145- 151 Arthur St Homebush West NSW 2140",
    "addr:housenumber":"151",
    "addr:postcode":"2140",
    "addr:street":"Arthur St",
    "iso:country":"AU",
    "sg:address":"145- 151 Arthur St",
    "sg:city":"Homebush West",
    "sg:classifiers":[
        {
            "category":"Professional",
            "subcategory":"Computer Services",
            "type":"Services"
        }
    ],
    "sg:phone":"+61 1800 022 178",
    "sg:postcode":"2140",
    "sg:province":"NSW",
    "sg:tags":[
        "repairs",
        "upgrade",
        "equipment"
    ],
    "wof:name":"AWA Limited",
    "wof:placetype":"venue"
},
  "geometry": {"coordinates":[151.06291198700001,-33.8670730591],"type":"Point"}
}