{
  "type": "Feature",
  "properties": {
    "iso:country":"AU",
    "sg:address":"21 Summer La",
    "sg:city":"Ringwood",
    "sg:classifiers":[
        {
            "category":"Building & Trades",
            "subcategory":"Construction",
            "type":"Services"
        }
    ],
    "sg:phone":"+61 3 9870 3011",
    "sg:postcode":"3134",
    "sg:province":"VIC",
    "sg:tags":[
        "pool",
        "swimming"
    ],
    "wof:name":"Albatross Swimming Pools (Aust) Pty Ltd",
    "wof:placetype":"venue"
},
  "geometry": {"coordinates":[145.21905517600001,-37.8234367371],"type":"Point"}
}