{
  "type": "Feature",
  "properties": {
    "iso:country":"AU",
    "sg:address":"2990 Frankston-Flinders Rd",
    "sg:city":"Balnarring",
    "sg:classifiers":[
        {
            "category":"Wholesale",
            "subcategory":"Farm Supplies",
            "type":"Manufacturing & Wholesale Goods"
        }
    ],
    "sg:phone":"+61 3 5983 5150",
    "sg:postcode":"3926",
    "sg:province":"VIC",
    "sg:tags":[
        "feed",
        "supplement",
        "stock"
    ],
    "wof:name":"Balnarring Stock Feeds",
    "wof:placetype":"venue"
},
  "geometry": {"coordinates":[145.127349853,-38.3734741211],"type":"Point"}
}