{
  "type": "Feature",
  "properties": {
    "iso:country":"AU",
    "sg:address":"96 Wellington Pde",
    "sg:city":"East Melbourne",
    "sg:classifiers":[
        {
            "category":"Insurance",
            "subcategory":"Insurance Agent",
            "type":"Services"
        }
    ],
    "sg:phone":"+61 3 9417 6944",
    "sg:postcode":"3002",
    "sg:province":"VIC",
    "sg:tags":[
        "broker"
    ],
    "wof:name":"Small Business Insurance Services Pty Ltd",
    "wof:placetype":"venue"
},
  "geometry": {"coordinates":[144.98670959500001,-37.816368103],"type":"Point"}
}