{
  "type": "Feature",
  "properties": {
    "iso:country":"AU",
    "sg:address":"113 High Rd",
    "sg:city":"Willetton",
    "sg:classifiers":[
        {
            "category":"Building & Trades",
            "subcategory":"Construction",
            "type":"Services"
        }
    ],
    "sg:phone":"+61 8 9354 2428",
    "sg:postcode":"6155",
    "sg:province":"WA",
    "sg:tags":[
        "home",
        "air conditioning"
    ],
    "wof:name":"Jeff Mouritz GAS&AIR",
    "wof:placetype":"venue"
},
  "geometry": {"coordinates":[115.890411,-32.038761],"type":"Point"}
}