{
  "type": "Feature",
  "properties": {
    "iso:country":"AU",
    "sg:address":"202 Lambeth St",
    "sg:city":"Picnic Point",
    "sg:classifiers":[
        {
            "category":"Building & Trades",
            "subcategory":"Landscaping Services",
            "type":"Services"
        }
    ],
    "sg:phone":"+61 2 9773 7247",
    "sg:postcode":"2213",
    "sg:province":"NSW",
    "sg:tags":[
        "designer",
        "landscape",
        "contractor"
    ],
    "wof:name":"Green & Growing Landscaping",
    "wof:placetype":"venue"
},
  "geometry": {"coordinates":[150.99649,-33.96909],"type":"Point"}
}