{
  "type": "Feature",
  "properties": {
    "addr:full":"4059--4061 Pacific Hwy Loganholme QLD 4129",
    "addr:housenumber":"4059--4061",
    "addr:postcode":"4129",
    "addr:street":"Pacific Hwy",
    "iso:country":"AU",
    "sg:address":"4059--4061 Pacific Hwy",
    "sg:city":"Loganholme",
    "sg:classifiers":[
        {
            "category":"Building & Trades",
            "subcategory":"Construction",
            "type":"Services"
        }
    ],
    "sg:phone":"+61 1300 307 903",
    "sg:postcode":"4129",
    "sg:province":"QLD",
    "sg:tags":[
        "installation",
        "air conditioning"
    ],
    "wof:name":"Ozyair.com",
    "wof:placetype":"venue"
},
  "geometry": {"coordinates":[153.17984008799999,-27.6705970764],"type":"Point"}
}