{
  "type": "Feature",
  "properties": {
    "addr:full":"415 Central Ave Shepparton East VIC 3631",
    "addr:housenumber":"415",
    "addr:postcode":"3631",
    "addr:street":"Central Ave",
    "iso:country":"AU",
    "sg:address":"415 Central Ave",
    "sg:city":"Shepparton East",
    "sg:classifiers":[
        {
            "category":"Home & Garden",
            "subcategory":"Garden Supply",
            "type":"Retail Goods"
        }
    ],
    "sg:phone":"+61 3 5829 2715",
    "sg:postcode":"3631",
    "sg:province":"VIC",
    "sg:tags":[
        "equipment",
        "hydroponics"
    ],
    "wof:name":"Gv Hydroponics",
    "wof:placetype":"venue"
},
  "geometry": {"coordinates":[145.46209716800001,-36.3993225098],"type":"Point"}
}