{
  "type": "Feature",
  "properties": {
    "addr:full":"Park Avenue La Coffs Harbour NSW 2450",
    "addr:postcode":"2450",
    "addr:street":"Park Avenue",
    "iso:country":"AU",
    "sg:address":"Park Avenue La",
    "sg:city":"Coffs Harbour",
    "sg:classifiers":[
        {
            "category":"Shopping",
            "subcategory":"Antiques",
            "type":"Retail Goods"
        }
    ],
    "sg:phone":"+61 2 6656 2828",
    "sg:postcode":"2450",
    "sg:province":"NSW",
    "sg:tags":[
        "restoration",
        "reproduction"
    ],
    "wof:name":"Coffs Polishing",
    "wof:placetype":"venue"
},
  "geometry": {"coordinates":[153.11483799999999,-30.297539],"type":"Point"}
}