{
  "type": "Feature",
  "properties": {
    "addr:full":"11 Gloria Ave Dandenong VIC 3175",
    "addr:housenumber":"11",
    "addr:postcode":"3175",
    "addr:street":"Gloria Ave",
    "iso:country":"AU",
    "sg:address":"11 Gloria Ave",
    "sg:city":"Dandenong",
    "sg:classifiers":[
        {
            "category":"Professional",
            "subcategory":"Art Services",
            "type":"Services"
        }
    ],
    "sg:phone":"+61 412 391 574",
    "sg:postcode":"3175",
    "sg:province":"VIC",
    "sg:tags":[
        "caricaturist",
        "cartoonist"
    ],
    "wof:name":"Caselin Peter",
    "wof:placetype":"venue"
},
  "geometry": {"coordinates":[145.21446227999999,-37.9680709839],"type":"Point"}
}