{
  "type": "Feature",
  "properties": {
    "iso:country":"AU",
    "sg:address":"23 Willcock St",
    "sg:city":"Ardross",
    "sg:classifiers":[
        {
            "category":"Banks & Credit Unions",
            "subcategory":"Financial Services",
            "type":"Services"
        }
    ],
    "sg:phone":"+61 8 9364 6111",
    "sg:postcode":"6153",
    "sg:province":"WA",
    "sg:tags":[
        "planning"
    ],
    "wof:name":"Count Wealth Accountants",
    "wof:placetype":"venue"
},
  "geometry": {"coordinates":[115.834419,-32.022434],"type":"Point"}
}