{
  "type": "Feature",
  "properties": {
    "addr:full":"22 Vista Drv Parkerville WA 6081",
    "addr:housenumber":"22",
    "addr:postcode":"6081",
    "addr:street":"Vista Drv",
    "iso:country":"AU",
    "sg:address":"22 Vista Drv",
    "sg:city":"Parkerville",
    "sg:classifiers":[
        {
            "category":"Train Station",
            "subcategory":"Rail",
            "type":"Transportation"
        }
    ],
    "sg:phone":"+61 8 9295 5556",
    "sg:postcode":"6081",
    "sg:province":"WA",
    "sg:tags":[
        "marine",
        "engineer"
    ],
    "wof:name":"Beejay Marine & Engine Service",
    "wof:placetype":"venue"
},
  "geometry": {"coordinates":[116.147476196,-31.8701839447],"type":"Point"}
}