{
  "type": "Feature",
  "properties": {
    "addr:full":"23 Burra St Port Wakefield SA 5550",
    "addr:housenumber":"23",
    "addr:postcode":"5550",
    "addr:street":"Burra St Port",
    "iso:country":"AU",
    "sg:address":"23 Burra St",
    "sg:city":"Port Wakefield",
    "sg:classifiers":[
        {
            "category":"Travel",
            "subcategory":"Hotels & Motels",
            "type":"Entertainment"
        }
    ],
    "sg:phone":"+61 8 8867 1016",
    "sg:postcode":"5550",
    "sg:province":"SA",
    "sg:tags":[
        "accommodation"
    ],
    "wof:name":"Port Wakefield Hotel",
    "wof:placetype":"venue"
},
  "geometry": {"coordinates":[138.15272522000001,-34.1864204407],"type":"Point"}
}