{
  "type": "Feature",
  "properties": {
    "addr:full":"Shop 1089, Westfield Marion, 297 Diagonal Rd Oaklands Park SA 5046",
    "addr:housenumber":"1089;297",
    "addr:postcode":"5046",
    "addr:street":"Marion;Diagonal Rd",
    "iso:country":"AU",
    "sg:address":"Shop 1089, Westfield Marion, 297 Diagonal Rd",
    "sg:city":"Oaklands Park",
    "sg:classifiers":[
        {
            "category":"Personal",
            "subcategory":"Beauty Salon",
            "type":"Services"
        }
    ],
    "sg:phone":"+61 8 8296 0711",
    "sg:postcode":"5046",
    "sg:province":"SA",
    "wof:name":"Essential Beauty",
    "wof:placetype":"venue"
},
  "geometry": {"coordinates":[138.53732299999999,-35.002277],"type":"Point"}
}