{
  "type": "Feature",
  "properties": {
    "addr:full":"Palm Plaza 131 Beaudesert Rd Moorooka QLD 4105",
    "addr:housenumber":"131",
    "addr:postcode":"4105",
    "addr:street":"Beaudesert Rd",
    "iso:country":"AU",
    "sg:address":"Palm Plaza 131 Beaudesert Rd",
    "sg:city":"Moorooka",
    "sg:classifiers":[
        {
            "category":"Real Estate",
            "subcategory":"Real Estate Agent",
            "type":"Services"
        }
    ],
    "sg:phone":"+61 7 3892 1444",
    "sg:postcode":"4105",
    "sg:province":"QLD",
    "wof:name":"Ray White Moorooka",
    "wof:placetype":"venue"
},
  "geometry": {"coordinates":[153.023803711,-27.5313873291],"type":"Point"}
}