{
  "type": "Feature",
  "properties": {
    "addr:full":"30 Park St Northcote VIC 3070",
    "addr:housenumber":"30",
    "addr:postcode":"3070",
    "addr:street":"Park St",
    "iso:country":"AU",
    "sg:address":"30 Park St",
    "sg:city":"Northcote",
    "sg:classifiers":[
        {
            "category":"Real Estate",
            "subcategory":"Architect",
            "type":"Services"
        }
    ],
    "sg:phone":"+61 417 504 568",
    "sg:postcode":"3070",
    "sg:province":"VIC",
    "wof:name":"Mina Architects Pty Ltd",
    "wof:placetype":"venue"
},
  "geometry": {"coordinates":[144.993134,-37.77457],"type":"Point"}
}