{
  "type": "Feature",
  "properties": {
    "addr:full":"Shp4/ 1 Kellicar Rd Campbelltown NSW 2560",
    "addr:postcode":"2560",
    "addr:street":"Kellicar Rd",
    "iso:country":"AU",
    "sg:address":"Shp4/ 1 Kellicar Rd",
    "sg:city":"Campbelltown",
    "sg:classifiers":[
        {
            "category":"Fast Food",
            "type":"Food & Drink"
        }
    ],
    "sg:phone":"+61 2 4620 6688",
    "sg:postcode":"2560",
    "sg:province":"NSW",
    "sg:tags":[
        "away",
        "take"
    ],
    "wof:name":"Joy's Thai Takeaway",
    "wof:placetype":"venue"
},
  "geometry": {"coordinates":[150.80166625999999,-34.0731925964],"type":"Point"}
}