{
  "type": "Feature",
  "properties": {
    "iso:country":"AU",
    "sg:address":"1st Floor 119 Bloomfield St",
    "sg:city":"Cleveland",
    "sg:classifiers":[
        {
            "category":"Banks & Credit Unions",
            "subcategory":"Financial Services",
            "type":"Services"
        }
    ],
    "sg:phone":"+61 7 3286 9499",
    "sg:postcode":"4163",
    "sg:province":"QLD",
    "sg:tags":[
        "advisory",
        "planning",
        "retirement"
    ],
    "wof:name":"Western Pacific Portfolio Planning Pty Ltd",
    "wof:placetype":"venue"
},
  "geometry": {"coordinates":[153.26687622099999,-27.5277423859],"type":"Point"}
}