{
  "type": "Feature",
  "properties": {
    "iso:country":"AU",
    "sg:address":"1584 - 1600 Canterbury Rd",
    "sg:city":"Punchbowl",
    "sg:classifiers":[
        {
            "category":"Autos & Motor Vehicles",
            "subcategory":"Automobile Sales",
            "type":"Retail Goods"
        }
    ],
    "sg:phone":"+61 2 9709 4400",
    "sg:postcode":"2196",
    "sg:province":"NSW",
    "sg:tags":[
        "car",
        "used"
    ],
    "wof:name":"Bankstown Subaru",
    "wof:placetype":"venue"
},
  "geometry": {"coordinates":[151.04289199999999,-33.932587],"type":"Point"}
}