{
  "type": "Feature",
  "properties": {
    "addr:full":"3 Searcy St Darwin NT 0800",
    "addr:housenumber":"3",
    "addr:postcode":"nt 0800",
    "addr:street":"Searcy St",
    "iso:country":"AU",
    "sg:address":"3 Searcy St",
    "sg:city":"Darwin",
    "sg:classifiers":[
        {
            "category":"Banks & Credit Unions",
            "subcategory":"Financial Services",
            "type":"Services"
        }
    ],
    "sg:phone":"+61 13 13 21",
    "sg:postcode":"0800",
    "sg:province":"NT",
    "sg:tags":[
        "financier"
    ],
    "wof:name":"Australian Central Credit Union",
    "wof:placetype":"venue"
},
  "geometry": {"coordinates":[130.840606689,-12.4613752365],"type":"Point"}
}