{
  "type": "Feature",
  "properties": {
    "addr:full":"34 Birkley Rd Manly NSW 2095",
    "addr:housenumber":"34",
    "addr:postcode":"2095",
    "addr:street":"Birkley Rd",
    "iso:country":"AU",
    "sg:address":"34 Birkley Rd",
    "sg:city":"Manly",
    "sg:classifiers":[
        {
            "category":"Health Services",
            "subcategory":"Health Practitioner",
            "type":"Services"
        }
    ],
    "sg:phone":"+61 2 9977 0008",
    "sg:postcode":"2095",
    "sg:province":"NSW",
    "sg:tags":[
        "pathologist",
        "speech"
    ],
    "wof:name":"Bongarzoni E M",
    "wof:placetype":"venue"
},
  "geometry": {"coordinates":[151.28086852999999,-33.7942314148],"type":"Point"}
}