{
  "type": "Feature",
  "properties": {
    "addr:full":"335 Bong Bong St Bowral NSW 2576",
    "addr:housenumber":"335",
    "addr:postcode":"2576",
    "addr:street":"Bong Bong St",
    "iso:country":"AU",
    "sg:address":"335 Bong Bong St",
    "sg:city":"Bowral",
    "sg:classifiers":[
        {
            "category":"Shopping",
            "subcategory":"Luggage & Leather Goods",
            "type":"Retail Goods"
        }
    ],
    "sg:phone":"+61 2 4861 7133",
    "sg:postcode":"2576",
    "sg:province":"NSW",
    "wof:name":"Bags On Bong Bong",
    "wof:placetype":"venue"
},
  "geometry": {"coordinates":[150.41746520999999,-34.4799842834],"type":"Point"}
}