{
  "type": "Feature",
  "properties": {
    "addr:full":"Shop LG24 (Lower Ground) Queens Plaza, 226 Queen St Brisbane QLD 4000",
    "addr:housenumber":"lg24;226",
    "addr:postcode":"4000",
    "addr:street":"Queen St",
    "iso:country":"AU",
    "sg:address":"Shop LG24 (Lower Ground) Queens Plaza, 226 Queen St",
    "sg:city":"Brisbane",
    "sg:classifiers":[
        {
            "category":"Shopping",
            "subcategory":"Shoes",
            "type":"Retail Goods"
        }
    ],
    "sg:phone":"+61 7 3220 2000",
    "sg:postcode":"4000",
    "sg:province":"QLD",
    "sg:tags":[
        "footwear"
    ],
    "sg:website":"http://www.footgear.com.au",
    "wof:name":"Footgear - Queens Plaza",
    "wof:placetype":"venue"
},
  "geometry": {"coordinates":[153.027175903,-27.4679489136],"type":"Point"}
}