{
  "type": "Feature",
  "properties": {
    "addr:full":"277 Alma Rd Caulfield North VIC 3161",
    "addr:housenumber":"277",
    "addr:postcode":"3161",
    "addr:street":"Alma Rd",
    "iso:country":"AU",
    "sg:address":"277 Alma Rd",
    "sg:city":"Caulfield North",
    "sg:classifiers":[
        {
            "category":"Social Services",
            "subcategory":"Adult Care",
            "type":"Services"
        }
    ],
    "sg:phone":"+61 3 9527 2991",
    "sg:postcode":"3161",
    "sg:province":"VIC",
    "sg:tags":[
        "aged"
    ],
    "wof:name":"Practical Help Seniors Support",
    "wof:placetype":"venue"
},
  "geometry": {"coordinates":[145.01734924300001,-37.8647994995],"type":"Point"}
}