{
  "type": "Feature",
  "properties": {
    "addr:full":"42 Cobham St Kings Park NSW 2148",
    "addr:housenumber":"42",
    "addr:postcode":"2148",
    "addr:street":"Cobham St",
    "iso:country":"AU",
    "sg:address":"42 Cobham St",
    "sg:city":"Kings Park",
    "sg:classifiers":[
        {
            "category":"Home & Garden",
            "subcategory":"Building Materials",
            "type":"Retail Goods"
        }
    ],
    "sg:phone":"+61 1800 244 410",
    "sg:postcode":"2148",
    "sg:province":"NSW",
    "sg:tags":[
        "lawn",
        "cutting",
        "maintenance"
    ],
    "wof:name":"Graeme's Home Care Service",
    "wof:placetype":"venue"
},
  "geometry": {"coordinates":[150.901443481,-33.7437019348],"type":"Point"}
}