{
  "type": "Feature",
  "properties": {
    "addr:full":"Level 1,35 Cotham Rd Vic 3101 Kew VIC 3101",
    "addr:housenumber":"1,35",
    "addr:postcode":"3101;3101",
    "addr:street":"Cotham Rd",
    "iso:country":"AU",
    "sg:address":"Level 1,35 Cotham Rd",
    "sg:city":"Vic 3101 Kew",
    "sg:classifiers":[
        {
            "category":"Shopping",
            "subcategory":"Computers & Home Electronics",
            "type":"Retail Goods"
        }
    ],
    "sg:phone":"+61 1800 036 186",
    "sg:postcode":"3101",
    "sg:province":"VIC",
    "sg:tags":[
        "equipment",
        "multimedia"
    ],
    "wof:name":"CPD News",
    "wof:placetype":"venue"
},
  "geometry": {"coordinates":[145.03323364299999,-37.8069953918],"type":"Point"}
}