{
  "type": "Feature",
  "properties": {
    "addr:full":"115 Paisley St Footscray VIC 3011",
    "addr:housenumber":"115",
    "addr:postcode":"3011",
    "addr:street":"Paisley St",
    "iso:country":"AU",
    "sg:address":"115 Paisley St",
    "sg:city":"Footscray",
    "sg:classifiers":[
        {
            "category":"Health Services",
            "subcategory":"Dentist",
            "type":"Services"
        }
    ],
    "sg:phone":"+61 3 9689 1131",
    "sg:postcode":"3011",
    "sg:province":"VIC",
    "wof:name":"Togias Michael",
    "wof:placetype":"venue"
},
  "geometry": {"coordinates":[144.893997192,-37.8003463745],"type":"Point"}
}