{
  "type": "Feature",
  "properties": {
    "addr:full":"73 High St Berwick VIC 3806",
    "addr:housenumber":"73",
    "addr:postcode":"3806",
    "addr:street":"High St",
    "iso:country":"AU",
    "sg:address":"73 High St",
    "sg:city":"Berwick",
    "sg:classifiers":[
        {
            "category":"Banks & Credit Unions",
            "subcategory":"Financial Services",
            "type":"Services"
        }
    ],
    "sg:phone":"+61 3 9707 3144",
    "sg:postcode":"3806",
    "sg:province":"VIC",
    "sg:tags":[
        "loan",
        "finance",
        "mortgage"
    ],
    "wof:name":"Resi Berwick",
    "wof:placetype":"venue"
},
  "geometry": {"coordinates":[145.34739685100001,-38.0310516357],"type":"Point"}
}