{
  "type": "Feature",
  "properties": {
    "addr:full":"343- 345 Barrenjoey Rd Newport Beach NSW 2106",
    "addr:housenumber":"345",
    "addr:postcode":"2106",
    "addr:street":"Barrenjoey Rd",
    "iso:country":"AU",
    "sg:address":"343- 345 Barrenjoey Rd",
    "sg:city":"Newport Beach",
    "sg:classifiers":[
        {
            "category":"Banks & Credit Unions",
            "subcategory":"Bank",
            "type":"Services"
        }
    ],
    "sg:phone":"+61 13 13 14",
    "sg:postcode":"2106",
    "sg:province":"NSW",
    "wof:name":"ANZ",
    "wof:placetype":"venue"
},
  "geometry": {"coordinates":[151.319946289,-33.6552200317],"type":"Point"}
}