{
  "type": "Feature",
  "properties": {
    "iso:country":"AU",
    "sg:address":"PO Box 512",
    "sg:city":"Moruya",
    "sg:classifiers":[
        {
            "category":"Home & Garden",
            "subcategory":"Household Appliances",
            "type":"Retail Goods"
        }
    ],
    "sg:phone":"+61 2 4474 2900",
    "sg:postcode":"2537",
    "sg:province":"NSW",
    "sg:tags":[
        "equipment",
        "gas"
    ],
    "wof:name":"Eurobodalla Plumbing Services",
    "wof:placetype":"venue"
},
  "geometry": {"coordinates":[150.080688477,-35.9107589722],"type":"Point"}
}