{
  "type": "Feature",
  "properties": {
    "addr:full":"15 Waterloo St Queanbeyan NSW 2620",
    "addr:housenumber":"15",
    "addr:postcode":"2620",
    "addr:street":"Waterloo St",
    "iso:country":"AU",
    "sg:address":"15 Waterloo St",
    "sg:city":"Queanbeyan",
    "sg:classifiers":[
        {
            "category":"Military Area",
            "subcategory":"Coast Guard Base",
            "type":"Public Place"
        }
    ],
    "sg:phone":"+61 2 6299 1861",
    "sg:postcode":"2620",
    "sg:province":"NSW",
    "sg:tags":[
        "worker",
        "metal",
        "machinery",
        "sheet"
    ],
    "wof:name":"Truform Pty Ltd",
    "wof:placetype":"venue"
},
  "geometry": {"coordinates":[149.24058532699999,-35.3423881531],"type":"Point"}
}