{
  "type": "Feature",
  "properties": {
    "addr:full":"Cnr Union & Mitchell Sts Merewether NSW 2291",
    "addr:postcode":"2291",
    "iso:country":"AU",
    "sg:address":"Cnr Union & Mitchell Sts",
    "sg:city":"Merewether",
    "sg:classifiers":[
        {
            "category":"Building & Trades",
            "subcategory":"Locksmith",
            "type":"Services"
        }
    ],
    "sg:phone":"+61 2 4963 7666",
    "sg:postcode":"2291",
    "sg:province":"NSW",
    "sg:tags":[
        "lock"
    ],
    "wof:name":"Newcastle Security Solutions",
    "wof:placetype":"venue"
},
  "geometry": {"coordinates":[151.75210571299999,-32.9460411072],"type":"Point"}
}