{
  "type": "Feature",
  "properties": {
    "iso:country":"AU",
    "sg:address":"Unit 4, 8 Boag Pl",
    "sg:city":"Morley",
    "sg:classifiers":[
        {
            "category":"Retail",
            "subcategory":"Auto Repair",
            "type":"Services"
        }
    ],
    "sg:phone":"+61 8 9275 8778",
    "sg:postcode":"6062",
    "sg:province":"WA",
    "sg:tags":[
        "electrical"
    ],
    "wof:name":"Acclaim Auto Electrics",
    "wof:placetype":"venue"
},
  "geometry": {"coordinates":[115.89398956300001,-31.8984069824],"type":"Point"}
}