{
  "type": "Feature",
  "properties": {
    "addr:full":"PO Box 210 Glen Iris VIC 3146",
    "addr:postcode":"3146",
    "iso:country":"AU",
    "sg:address":"PO Box 210",
    "sg:city":"Glen Iris",
    "sg:classifiers":[
        {
            "category":"Health Services",
            "subcategory":"Doctor",
            "type":"Services"
        }
    ],
    "sg:phone":"+61 3 9885 1771",
    "sg:postcode":"3146",
    "sg:province":"VIC",
    "sg:tags":[
        "occupational",
        "safety"
    ],
    "wof:name":"Georgia Sinclair Consulting",
    "wof:placetype":"venue"
},
  "geometry": {"coordinates":[145.067626953,-37.8564682007],"type":"Point"}
}