{
  "type": "Feature",
  "properties": {
    "iso:country":"AU",
    "sg:address":"63 Buckingham Drv",
    "sg:city":"Wangara",
    "sg:classifiers":[
        {
            "category":"Professional",
            "subcategory":"Detective & Security Services",
            "type":"Services"
        }
    ],
    "sg:phone":"+61 13 13 15",
    "sg:postcode":"6065",
    "sg:province":"WA",
    "sg:tags":[
        "equipment",
        "window",
        "doors"
    ],
    "wof:name":"ABC blinds. curtains. security.",
    "wof:placetype":"venue"
},
  "geometry": {"coordinates":[115.82453155499999,-31.7873020172],"type":"Point"}
}