{
  "type": "Feature",
  "properties": {
    "addr:full":"PO Box 54 Machans Beach QLD 4878",
    "addr:postcode":"4878",
    "iso:country":"AU",
    "sg:address":"PO Box 54",
    "sg:city":"Machans Beach",
    "sg:classifiers":[
        {
            "category":"Shopping",
            "subcategory":"Luggage & Leather Goods",
            "type":"Retail Goods"
        }
    ],
    "sg:phone":"+61 7 4055 0909",
    "sg:postcode":"4878",
    "sg:province":"QLD",
    "wof:name":"Hungerfords",
    "wof:placetype":"venue"
},
  "geometry": {"coordinates":[145.74435424800001,-16.852809906],"type":"Point"}
}