{
  "type": "Feature",
  "properties": {
    "addr:full":"Level 1, Suite 3 16 Duncan St West End QLD 4101",
    "addr:housenumber":"16",
    "addr:postcode":"4101",
    "addr:street":"Duncan St",
    "iso:country":"AU",
    "sg:address":"Level 1, Suite 3 16 Duncan St",
    "sg:city":"West End",
    "sg:classifiers":[
        {
            "category":"Professional",
            "subcategory":"Computer Services",
            "type":"Services"
        }
    ],
    "sg:phone":"+61 7 3844 4131",
    "sg:postcode":"4101",
    "sg:province":"QLD",
    "sg:tags":[
        "package",
        "software"
    ],
    "wof:name":"Heritage Accounting Systems Pty Ltd",
    "wof:placetype":"venue"
},
  "geometry": {"coordinates":[153.00097656200001,-27.4829082489],"type":"Point"}
}