{
  "type": "Feature",
  "properties": {
    "iso:country":"AU",
    "sg:address":"PO Box 1751",
    "sg:city":"Geelong",
    "sg:classifiers":[
        {
            "category":"Utilities",
            "subcategory":"Electric",
            "type":"Services"
        }
    ],
    "sg:phone":"+61 419 384 825",
    "sg:postcode":"3220",
    "sg:province":"VIC",
    "sg:tags":[
        "electrical",
        "contractor"
    ],
    "wof:name":"Schultz Wayne Electrical",
    "wof:placetype":"venue"
},
  "geometry": {"coordinates":[144.373077,-38.14843],"type":"Point"}
}