{
  "type": "Feature",
  "properties": {
    "iso:country":"AU",
    "sg:address":"20 Dundilla Rd",
    "sg:city":"Frenchs Forest",
    "sg:classifiers":[
        {
            "category":"Real Estate",
            "subcategory":"Architect",
            "type":"Services"
        }
    ],
    "sg:phone":"+61 2 9452 6245",
    "sg:postcode":"2086",
    "sg:province":"NSW",
    "wof:name":"Crick Guy",
    "wof:placetype":"venue"
},
  "geometry": {"coordinates":[151.224685669,-33.7438659668],"type":"Point"}
}