{
  "type": "Feature",
  "properties": {
    "iso:country":"AU",
    "sg:address":"2 Corporation Pl",
    "sg:city":"Orange",
    "sg:classifiers":[
        {
            "category":"Manufacturing",
            "subcategory":"Glass & Minerals",
            "type":"Manufacturing & Wholesale Goods"
        }
    ],
    "sg:phone":"+61 2 6361 4700",
    "sg:postcode":"2800",
    "sg:province":"NSW",
    "sg:tags":[
        "exploration"
    ],
    "wof:name":"Ytc Resources",
    "wof:placetype":"venue"
},
  "geometry": {"coordinates":[149.10757446299999,-33.3132286072],"type":"Point"}
}