{
  "type": "Feature",
  "properties": {
    "addr:full":"Unit 5 1 Buttle St Queanbeyan ACT 2620",
    "addr:housenumber":"1",
    "addr:postcode":"2620",
    "addr:street":"Buttle St",
    "iso:country":"AU",
    "sg:address":"Unit 5 1 Buttle St",
    "sg:city":"Queanbeyan",
    "sg:classifiers":[
        {
            "category":"Professional",
            "subcategory":"Business Services",
            "type":"Services"
        }
    ],
    "sg:phone":"+61 2 6299 5855",
    "sg:postcode":"2620",
    "sg:province":"ACT",
    "sg:tags":[
        "consultant",
        "leasing"
    ],
    "wof:name":"Linray Finance & Leasing",
    "wof:placetype":"venue"
},
  "geometry": {"coordinates":[149.24334716800001,-35.349609375],"type":"Point"}
}