{
  "type": "Feature",
  "properties": {
    "addr:full":"50 Arizona Rd Warnervale NSW 2259",
    "addr:housenumber":"50",
    "addr:postcode":"2259",
    "addr:street":"Arizona Rd",
    "iso:country":"AU",
    "sg:address":"50 Arizona Rd",
    "sg:city":"Warnervale",
    "sg:classifiers":[
        {
            "category":"Building & Trades",
            "subcategory":"Construction",
            "type":"Services"
        }
    ],
    "sg:phone":"+61 2 4392 3972",
    "sg:postcode":"2259",
    "sg:province":"NSW",
    "sg:tags":[
        "brick",
        "paving"
    ],
    "wof:name":"Central Coast Bushrock Supplies",
    "wof:placetype":"venue"
},
  "geometry": {"coordinates":[151.49163818400001,-33.2361564636],"type":"Point"}
}