{
  "type": "Feature",
  "properties": {
    "addr:full":"369 Stud Rd Wantirna VIC 3152",
    "addr:housenumber":"369",
    "addr:postcode":"3152",
    "addr:street":"Stud Rd",
    "iso:country":"AU",
    "sg:address":"369 Stud Rd",
    "sg:city":"Wantirna",
    "sg:classifiers":[
        {
            "category":"Social Services",
            "subcategory":"Child Care",
            "type":"Services"
        }
    ],
    "sg:phone":"+61 3 9887 1564",
    "sg:postcode":"3152",
    "sg:province":"VIC",
    "wof:name":"Swinburne Children's Centre",
    "wof:placetype":"venue"
},
  "geometry": {"coordinates":[145.233184814,-37.8737564087],"type":"Point"}
}