{
  "type": "Feature",
  "properties": {
    "addr:full":"54 Delhi Rd North Ryde NSW 2113",
    "addr:housenumber":"54",
    "addr:postcode":"2113",
    "addr:street":"Delhi Rd",
    "iso:country":"AU",
    "sg:address":"54 Delhi Rd",
    "sg:city":"North Ryde",
    "sg:classifiers":[
        {
            "category":"Building & Trades",
            "subcategory":"Construction",
            "type":"Services"
        }
    ],
    "sg:phone":"+61 2 9888 6274",
    "sg:postcode":"2113",
    "sg:province":"NSW",
    "sg:tags":[
        "contractor"
    ],
    "wof:name":"Dolores S",
    "wof:placetype":"venue"
},
  "geometry": {"coordinates":[151.14338684099999,-33.7953529358],"type":"Point"}
}