{
  "type": "Feature",
  "properties": {
    "addr:full":"523a Old South Head Rd Rose Bay NSW 2029",
    "addr:housenumber":"523a",
    "addr:postcode":"2029",
    "addr:street":"Old South Head Rd",
    "iso:country":"AU",
    "sg:address":"523a Old South Head Rd",
    "sg:city":"Rose Bay",
    "sg:classifiers":[
        {
            "category":"Shopping",
            "subcategory":"Baby Store",
            "type":"Retail Goods"
        }
    ],
    "sg:phone":"+61 2 9371 9831",
    "sg:postcode":"2029",
    "sg:province":"NSW",
    "sg:tags":[
        "children's",
        "wear"
    ],
    "wof:name":"Something Special Kids & Mums",
    "wof:placetype":"venue"
},
  "geometry": {"coordinates":[151.27354431099999,-33.8737831116],"type":"Point"}
}