{
  "type": "Feature",
  "properties": {
    "addr:full":"436 Burwood Hwy Wantirna South VIC 3152",
    "addr:housenumber":"436",
    "addr:postcode":"3152",
    "addr:street":"Burwood Hwy",
    "iso:country":"AU",
    "sg:address":"436 Burwood Hwy",
    "sg:city":"Wantirna South",
    "sg:classifiers":[
        {
            "category":"Professional",
            "subcategory":"Computer Services",
            "type":"Services"
        }
    ],
    "sg:phone":"+61 3 9887 1788",
    "sg:postcode":"3152",
    "sg:province":"VIC",
    "sg:tags":[
        "repairs",
        "upgrade",
        "equipment"
    ],
    "wof:name":"@ Tech Computer",
    "wof:placetype":"venue"
},
  "geometry": {"coordinates":[145.23846435600001,-37.870388031],"type":"Point"}
}