{
  "type": "Feature",
  "properties": {
    "addr:full":"Lvl1, 724 Botany Rd Mascot NSW 2020",
    "addr:housenumber":"724",
    "addr:postcode":"2020",
    "addr:street":"Botany Rd",
    "iso:country":"AU",
    "sg:address":"Lvl1, 724 Botany Rd",
    "sg:city":"Mascot",
    "sg:classifiers":[
        {
            "category":"Retail",
            "subcategory":"Auto Repair",
            "type":"Services"
        }
    ],
    "sg:phone":"+61 1300 881 500",
    "sg:postcode":"2020",
    "sg:province":"NSW",
    "sg:tags":[
        "aluminium"
    ],
    "sg:website":"http://www.windowline.com.au",
    "wof:name":"Windowline Pty Ltd",
    "wof:placetype":"venue"
},
  "geometry": {"coordinates":[151.19427490199999,-33.9353485107],"type":"Point"}
}