{
  "type": "Feature",
  "properties": {
    "addr:full":"18 Fitzroy St Clayfield QLD 4011",
    "addr:housenumber":"18",
    "addr:postcode":"4011",
    "addr:street":"Fitzroy St",
    "iso:country":"AU",
    "sg:address":"18 Fitzroy St",
    "sg:city":"Clayfield",
    "sg:classifiers":[
        {
            "category":"Professional",
            "subcategory":"Art Services",
            "type":"Services"
        }
    ],
    "sg:phone":"+61 7 3357 7920",
    "sg:postcode":"4011",
    "sg:province":"QLD",
    "sg:tags":[
        "interior",
        "decorator"
    ],
    "wof:name":"Brush Brothers Pty Ltd",
    "wof:placetype":"venue"
},
  "geometry": {"coordinates":[153.052719,-27.411369],"type":"Point"}
}