{
  "type": "Feature",
  "properties": {
    "iso:country":"AU",
    "sg:address":"Unit 8 31 Black St",
    "sg:city":"Milton",
    "sg:classifiers":[
        {
            "category":"Banks & Credit Unions",
            "subcategory":"Bank",
            "type":"Services"
        }
    ],
    "sg:phone":"+61 7 3514 9000",
    "sg:postcode":"4064",
    "sg:province":"QLD",
    "sg:tags":[
        "society"
    ],
    "wof:name":"Autocard Australia",
    "wof:placetype":"venue"
},
  "geometry": {"coordinates":[153.00770568900001,-27.4666728973],"type":"Point"}
}