{
  "type": "Feature",
  "properties": {
    "addr:full":"105 Unley Rd Unley SA 5061",
    "addr:housenumber":"105",
    "addr:postcode":"5061",
    "addr:street":"Unley Rd",
    "iso:country":"AU",
    "sg:address":"105 Unley Rd",
    "sg:city":"Unley",
    "sg:classifiers":[
        {
            "category":"Shopping",
            "subcategory":"Crafts & Fabrics",
            "type":"Retail Goods"
        }
    ],
    "sg:phone":"+61 8 8272 5518",
    "sg:postcode":"5061",
    "sg:province":"SA",
    "sg:tags":[
        "supply"
    ],
    "wof:name":"Beads Indeed",
    "wof:placetype":"venue"
},
  "geometry": {"coordinates":[138.60812377900001,-34.9563903809],"type":"Point"}
}