{
  "type": "Feature",
  "properties": {
    "addr:full":"Cnr Young & Waite St Blackwood SA 5051",
    "addr:postcode":"5051",
    "addr:street":"Cnr;St",
    "iso:country":"AU",
    "sg:address":"Cnr Young & Waite St",
    "sg:city":"Blackwood",
    "sg:classifiers":[
        {
            "category":"Education",
            "subcategory":"Dance Studio",
            "type":"Public Place"
        }
    ],
    "sg:phone":"+61 8 8270 4214",
    "sg:postcode":"5051",
    "sg:province":"SA",
    "sg:tags":[
        "venue",
        "tuition"
    ],
    "wof:name":"Panache Dance Studio",
    "wof:placetype":"venue"
},
  "geometry": {"coordinates":[138.611435,-35.020821],"type":"Point"}
}