{
  "type": "Feature",
  "properties": {
    "addr:full":"PO Box 382 Winston Hills NSW 2153",
    "addr:postcode":"2153",
    "iso:country":"AU",
    "sg:address":"PO Box 382",
    "sg:city":"Winston Hills",
    "sg:classifiers":[
        {
            "category":"Professional",
            "subcategory":"Detective & Security Services",
            "type":"Services"
        }
    ],
    "sg:phone":"+61 2 9838 8177",
    "sg:postcode":"2153",
    "sg:province":"NSW",
    "sg:tags":[
        "consultant",
        "system"
    ],
    "wof:name":"Hypertech Security",
    "wof:placetype":"venue"
},
  "geometry": {"coordinates":[150.97482299800001,-33.7780990601],"type":"Point"}
}