{
  "type": "Feature",
  "properties": {
    "addr:full":"93 Monument St Mosman Park WA 6012",
    "addr:housenumber":"93",
    "addr:postcode":"6012",
    "addr:street":"Monument St",
    "iso:country":"AU",
    "sg:address":"93 Monument St",
    "sg:city":"Mosman Park",
    "sg:classifiers":[
        {
            "category":"Building & Trades",
            "subcategory":"Plumbing",
            "type":"Services"
        }
    ],
    "sg:phone":"+61 8 9384 6660",
    "sg:postcode":"6012",
    "sg:province":"WA",
    "sg:tags":[
        "plumber",
        "gasfitters"
    ],
    "wof:name":"Smith C A",
    "wof:placetype":"venue"
},
  "geometry": {"coordinates":[115.76109314,-32.0127944946],"type":"Point"}
}