{
  "type": "Feature",
  "properties": {
    "addr:full":"44 Vale St Cooma NSW 2630",
    "addr:housenumber":"44",
    "addr:postcode":"2630",
    "addr:street":"Vale St",
    "iso:country":"AU",
    "sg:address":"44 Vale St",
    "sg:city":"Cooma",
    "sg:classifiers":[
        {
            "category":"Shopping",
            "subcategory":"Jewelry",
            "type":"Retail Goods"
        }
    ],
    "sg:phone":"+61 2 6452 2130",
    "sg:postcode":"2630",
    "sg:province":"NSW",
    "sg:tags":[
        "jeweller"
    ],
    "wof:name":"Estreich Jewellers",
    "wof:placetype":"venue"
},
  "geometry": {"coordinates":[149.12422180199999,-36.2345657349],"type":"Point"}
}