{
  "type": "Feature",
  "properties": {
    "addr:full":"Shop 1/ 35 Brookes St Mitchell ACT 2911",
    "addr:housenumber":"shop 1 / 35",
    "addr:postcode":"2911",
    "addr:street":"Brookes St",
    "iso:country":"AU",
    "sg:address":"Shop 1/ 35 Brookes St",
    "sg:city":"Mitchell",
    "sg:classifiers":[
        {
            "category":"Cafe",
            "type":"Food & Drink"
        }
    ],
    "sg:phone":"+61 2 6242 8050",
    "sg:postcode":"2911",
    "sg:province":"ACT",
    "wof:name":"Joy Industry Lic'd Cafe The",
    "wof:placetype":"venue"
},
  "geometry": {"coordinates":[149.140914917,-35.2179794312],"type":"Point"}
}