{
  "type": "Feature",
  "properties": {
    "addr:full":"69 Umong St Tottenham NSW 2873",
    "addr:housenumber":"69",
    "addr:postcode":"2873",
    "addr:street":"Umong St",
    "iso:country":"AU",
    "sg:address":"69 Umong St",
    "sg:city":"Tottenham",
    "sg:classifiers":[
        {
            "category":"Government",
            "subcategory":"Post Office",
            "type":"Public Place"
        }
    ],
    "sg:phone":"+61 2 6892 4020",
    "sg:postcode":"2873",
    "sg:province":"NSW",
    "sg:tags":[
        "postal"
    ],
    "wof:name":"Australia Post",
    "wof:placetype":"venue"
},
  "geometry": {"coordinates":[147.354828,-32.243706],"type":"Point"}
}