{
  "type": "Feature",
  "properties": {
    "addr:full":"154 Parker St Cootamundra NSW 2590",
    "addr:housenumber":"154",
    "addr:postcode":"2590",
    "addr:street":"Parker St",
    "iso:country":"AU",
    "sg:address":"154 Parker St",
    "sg:city":"Cootamundra",
    "sg:classifiers":[
        {
            "category":"Communications",
            "subcategory":"Film & Video Production",
            "type":"Services"
        }
    ],
    "sg:phone":"+61 2 6942 3840",
    "sg:postcode":"2590",
    "sg:province":"NSW",
    "sg:tags":[
        "dvd",
        "library"
    ],
    "wof:name":"Video Ezy",
    "wof:placetype":"venue"
},
  "geometry": {"coordinates":[148.02192688,-34.6411056519],"type":"Point"}
}