{
  "type": "Feature",
  "properties": {
    "addr:full":"1834 Sandgate Rd Virginia QLD 4014",
    "addr:housenumber":"1834",
    "addr:postcode":"4014",
    "addr:street":"Sandgate Rd",
    "iso:country":"AU",
    "sg:address":"1834 Sandgate Rd",
    "sg:city":"Virginia",
    "sg:classifiers":[
        {
            "category":"Shopping",
            "subcategory":"Pets & Pet Supplies",
            "type":"Retail Goods"
        }
    ],
    "sg:phone":"+61 7 3865 3967",
    "sg:postcode":"4014",
    "sg:province":"QLD",
    "sg:tags":[
        "food"
    ],
    "wof:name":"Pet Hypermarket",
    "wof:placetype":"venue"
},
  "geometry": {"coordinates":[153.062255859,-27.3736019135],"type":"Point"}
}