{
  "type": "Feature",
  "properties": {
    "addr:full":"42 Marsh Rd Silverdale NSW 2752",
    "addr:housenumber":"42",
    "addr:postcode":"2752",
    "addr:street":"Marsh Rd",
    "iso:country":"AU",
    "sg:address":"42 Marsh Rd",
    "sg:city":"Silverdale",
    "sg:classifiers":[
        {
            "category":"Personal",
            "type":"Services"
        }
    ],
    "sg:phone":"+61 2 4774 2626",
    "sg:postcode":"2752",
    "sg:province":"NSW",
    "sg:tags":[
        "dressmaker"
    ],
    "wof:name":"Kastarra Klothing",
    "wof:placetype":"venue"
},
  "geometry": {"coordinates":[150.60505676299999,-33.9055252075],"type":"Point"}
}