{
  "type": "Feature",
  "properties": {
    "addr:full":"25 Macsfield Rd Wallan VIC 3756",
    "addr:housenumber":"25",
    "addr:postcode":"3756",
    "addr:street":"Macsfield Rd",
    "iso:country":"AU",
    "sg:address":"25 Macsfield Rd",
    "sg:city":"Wallan",
    "sg:classifiers":[
        {
            "category":"Shopping",
            "subcategory":"Crafts & Fabrics",
            "type":"Retail Goods"
        }
    ],
    "sg:phone":"+61 3 5783 1622",
    "sg:postcode":"3756",
    "sg:province":"VIC",
    "sg:tags":[
        "adhesive"
    ],
    "wof:name":"Multiquip Wholesale",
    "wof:placetype":"venue"
},
  "geometry": {"coordinates":[144.98135375999999,-37.4351081848],"type":"Point"}
}