{
  "type": "Feature",
  "properties": {
    "iso:country":"AU",
    "sg:address":"14 Andrew St",
    "sg:city":"Esperance",
    "sg:classifiers":[
        {
            "category":"Travel",
            "subcategory":"Hotels & Motels",
            "type":"Entertainment"
        }
    ],
    "sg:phone":"+61 8 9071 1555",
    "sg:postcode":"6450",
    "sg:province":"WA",
    "wof:name":"Esperance Motor Hotel",
    "wof:placetype":"venue"
},
  "geometry": {"coordinates":[121.89232635499999,-33.8617362976],"type":"Point"}
}