{
  "type": "Feature",
  "properties": {
    "iso:country":"AU",
    "sg:address":"\"Tomar\", Boxwood Road",
    "sg:city":"Berrigan",
    "sg:classifiers":[
        {
            "category":"Arena",
            "subcategory":"Bull Ring",
            "type":"Entertainment"
        }
    ],
    "sg:phone":"+61 3 5885 2122",
    "sg:postcode":"2712",
    "sg:province":"NSW",
    "sg:tags":[
        "breeder",
        "pig"
    ],
    "wof:name":"Tomar Free Range Pigs",
    "wof:placetype":"venue"
},
  "geometry": {"coordinates":[145.79432678200001,-35.700668335],"type":"Point"}
}