{
  "type": "Feature",
  "properties": {
    "addr:full":"Cnr Coonawarra Rd & Bowen St Winnellie NT 0820",
    "addr:postcode":"nt 0820",
    "addr:street":"Cnr Coonawarra Rd & Bowen St",
    "iso:country":"AU",
    "sg:address":"Cnr Coonawarra Rd & Bowen St",
    "sg:city":"Winnellie",
    "sg:classifiers":[
        {
            "category":"Professional",
            "type":"Services"
        }
    ],
    "sg:phone":"+61 8 8947 1155",
    "sg:postcode":"0820",
    "sg:province":"NT",
    "sg:tags":[
        "transport"
    ],
    "wof:name":"City Wreckers",
    "wof:placetype":"venue"
},
  "geometry": {"coordinates":[130.892501831,-12.430847168],"type":"Point"}
}