{
  "type": "Feature",
  "properties": {
    "iso:country":"AU",
    "sg:address":"Lot 63 Lukin Rd",
    "sg:city":"Clackline",
    "sg:classifiers":[
        {
            "category":"Donuts",
            "subcategory":"None",
            "type":"Food & Drink"
        }
    ],
    "sg:phone":"+61 8 9574 1304",
    "sg:postcode":"6564",
    "sg:province":"WA",
    "sg:tags":[
        "die",
        "engraver",
        "sinker"
    ],
    "wof:name":"Cutline Engraving",
    "wof:placetype":"venue"
},
  "geometry": {"coordinates":[116.520241,-31.700905],"type":"Point"}
}