{
  "type": "Feature",
  "properties": {
    "addr:full":"21 Strahan St South Burnie TAS 7320",
    "addr:housenumber":"21",
    "addr:postcode":"7320",
    "addr:street":"Strahan St",
    "iso:country":"AU",
    "sg:address":"21 Strahan St",
    "sg:city":"South Burnie",
    "sg:classifiers":[
        {
            "category":"Shopping",
            "type":"Retail Goods"
        }
    ],
    "sg:phone":"+61 3 6431 9292",
    "sg:postcode":"7320",
    "sg:province":"TAS",
    "sg:tags":[
        "equipment",
        "safety",
        "accessory"
    ],
    "wof:name":"Weldquip",
    "wof:placetype":"venue"
},
  "geometry": {"coordinates":[145.90992700000001,-41.060528],"type":"Point"}
}