{
  "type": "Feature",
  "properties": {
    "addr:full":"10 Say St East Wagga Wagga NSW 2650",
    "addr:housenumber":"10",
    "addr:postcode":"2650",
    "addr:street":"Say St East",
    "iso:country":"AU",
    "sg:address":"10 Say St",
    "sg:city":"East Wagga Wagga",
    "sg:classifiers":[
        {
            "category":"Home & Garden",
            "subcategory":"Building Materials",
            "type":"Retail Goods"
        }
    ],
    "sg:phone":"+61 2 6971 8255",
    "sg:postcode":"2650",
    "sg:province":"NSW",
    "sg:tags":[
        "fencing"
    ],
    "wof:name":"Steel Supplies",
    "wof:placetype":"venue"
},
  "geometry": {"coordinates":[147.417800903,-35.1291618347],"type":"Point"}
}