{
  "type": "Feature",
  "properties": {
    "iso:country":"AU",
    "sg:address":"PO Box 14125",
    "sg:city":"Mt Sheridan",
    "sg:classifiers":[
        {
            "category":"Health Services",
            "subcategory":"Health Practitioner",
            "type":"Services"
        }
    ],
    "sg:phone":"+61 410 530 247",
    "sg:postcode":"4868",
    "sg:province":"QLD",
    "sg:tags":[
        "dietitian"
    ],
    "wof:name":"S & S Medical",
    "wof:placetype":"venue"
},
  "geometry": {"coordinates":[145.74195861800001,-16.9764003754],"type":"Point"}
}