{
  "type": "Feature",
  "properties": {
    "addr:full":"7 Chesterville Rd Cheltenham VIC 3192",
    "addr:housenumber":"7",
    "addr:postcode":"3192",
    "addr:street":"Chesterville Rd",
    "iso:country":"AU",
    "sg:address":"7 Chesterville Rd",
    "sg:city":"Cheltenham",
    "sg:classifiers":[
        {
            "category":"Health Services",
            "subcategory":"Doctor",
            "type":"Services"
        }
    ],
    "sg:phone":"+61 3 9584 6122",
    "sg:postcode":"3192",
    "sg:province":"VIC",
    "sg:tags":[
        "medical",
        "practitioner"
    ],
    "wof:name":"Cheltenham Eye Centre",
    "wof:placetype":"venue"
},
  "geometry": {"coordinates":[145.05622863799999,-37.9617614746],"type":"Point"}
}