{
  "type": "Feature",
  "properties": {
    "addr:full":"10 Landau Crt Taylors Lakes VIC 3038",
    "addr:housenumber":"10",
    "addr:postcode":"3038",
    "addr:street":"Landau Crt",
    "iso:country":"AU",
    "sg:address":"10 Landau Crt",
    "sg:city":"Taylors Lakes",
    "sg:classifiers":[
        {
            "category":"Building & Trades",
            "subcategory":"Cleaning & Sanitation",
            "type":"Services"
        }
    ],
    "sg:phone":"+61 3 9390 2027",
    "sg:postcode":"3038",
    "sg:province":"VIC",
    "sg:tags":[
        "industrial",
        "commercial",
        "contractor"
    ],
    "wof:name":"Ramos Cleaning Service",
    "wof:placetype":"venue"
},
  "geometry": {"coordinates":[144.78923,-37.693398],"type":"Point"}
}