{
  "type": "Feature",
  "properties": {
    "addr:full":"274a Canterbury Rd Surrey Hills VIC 3127",
    "addr:housenumber":"274a",
    "addr:postcode":"3127",
    "addr:street":"Canterbury Rd",
    "iso:country":"AU",
    "sg:address":"274a Canterbury Rd",
    "sg:city":"Surrey Hills",
    "sg:classifiers":[
        {
            "category":"Professional",
            "subcategory":"Employment Agencies",
            "type":"Services"
        }
    ],
    "sg:phone":"+61 3 9836 7888",
    "sg:postcode":"3127",
    "sg:province":"VIC",
    "sg:tags":[
        "hire",
        "labour",
        "contractor"
    ],
    "wof:name":"Essential Personnel Pty Ltd",
    "wof:placetype":"venue"
},
  "geometry": {"coordinates":[145.08836364699999,-37.8249664307],"type":"Point"}
}