{
  "type": "Feature",
  "properties": {
    "addr:full":"24 Vauxhall St Virginia QLD 4014",
    "addr:housenumber":"24",
    "addr:postcode":"4014",
    "addr:street":"Vauxhall St",
    "iso:country":"AU",
    "sg:address":"24 Vauxhall St",
    "sg:city":"Virginia",
    "sg:classifiers":[
        {
            "category":"Home & Garden",
            "subcategory":"Carpets & Floor Coverings",
            "type":"Retail Goods"
        }
    ],
    "sg:phone":"+61 7 3865 2333",
    "sg:postcode":"4014",
    "sg:province":"QLD",
    "sg:tags":[
        "tile",
        "wall"
    ],
    "wof:name":"Queensland Tile Distributors",
    "wof:placetype":"venue"
},
  "geometry": {"coordinates":[153.063232422,-27.3703899384],"type":"Point"}
}