{
  "type": "Feature",
  "properties": {
    "addr:full":"3 Jorgensen St Highfields QLD 4352",
    "addr:housenumber":"3",
    "addr:postcode":"4352",
    "addr:street":"Jorgensen St",
    "iso:country":"AU",
    "sg:address":"3 Jorgensen St",
    "sg:city":"Highfields",
    "sg:classifiers":[
        {
            "category":"Building & Trades",
            "subcategory":"Construction",
            "type":"Services"
        }
    ],
    "sg:phone":"+61 7 4696 8486",
    "sg:postcode":"4352",
    "sg:province":"QLD",
    "sg:tags":[
        "contractor"
    ],
    "wof:name":"J G Williams",
    "wof:placetype":"venue"
},
  "geometry": {"coordinates":[151.93190000000001,-27.470734],"type":"Point"}
}