{
  "type": "Feature",
  "properties": {
    "addr:full":"70 Tugrah Rd Devonport TAS 7310",
    "addr:housenumber":"70",
    "addr:postcode":"7310",
    "addr:street":"Tugrah Rd",
    "iso:country":"AU",
    "sg:address":"70 Tugrah Rd",
    "sg:city":"Devonport",
    "sg:classifiers":[
        {
            "category":"Building & Trades",
            "subcategory":"Construction",
            "type":"Services"
        }
    ],
    "sg:phone":"+61 419 394 244",
    "sg:postcode":"7310",
    "sg:province":"TAS",
    "sg:tags":[
        "decking",
        "contractor"
    ],
    "wof:name":"Smith Roger",
    "wof:placetype":"venue"
},
  "geometry": {"coordinates":[146.37591552699999,-41.2035179138],"type":"Point"}
}