{
  "type": "Feature",
  "properties": {
    "addr:full":"17 Keppler Cct Seaford VIC 3198",
    "addr:housenumber":"17",
    "addr:postcode":"3198",
    "addr:street":"Keppler Cct",
    "iso:country":"AU",
    "sg:address":"17 Keppler Cct",
    "sg:city":"Seaford",
    "sg:classifiers":[
        {
            "category":"Professional",
            "subcategory":"Management & Consulting",
            "type":"Services"
        }
    ],
    "sg:phone":"+61 3 9770 8121",
    "sg:postcode":"3198",
    "sg:province":"VIC",
    "sg:tags":[
        "consultant"
    ],
    "sg:website":"http://www.westlinkgroup.com.au",
    "wof:name":"Westlink Air Charter & Fleet Management",
    "wof:placetype":"venue"
},
  "geometry": {"coordinates":[145.15034484899999,-38.0967597961],"type":"Point"}
}