{
  "type": "Feature",
  "properties": {
    "addr:full":"55 Main St Pakenham VIC 3810",
    "addr:housenumber":"55",
    "addr:postcode":"3810",
    "addr:street":"Main St",
    "iso:country":"AU",
    "sg:address":"55 Main St",
    "sg:city":"Pakenham",
    "sg:classifiers":[
        {
            "category":"Shopping",
            "subcategory":"Party Supplies",
            "type":"Retail Goods"
        }
    ],
    "sg:phone":"+61 3 5941 9888",
    "sg:postcode":"3810",
    "sg:province":"VIC",
    "wof:name":"Pakenham Party Company",
    "wof:placetype":"venue"
},
  "geometry": {"coordinates":[145.48022499999999,-38.076347],"type":"Point"}
}