{
  "type": "Feature",
  "properties": {
    "addr:full":"29 Lincoln St Lindisfarne TAS 7015",
    "addr:housenumber":"29",
    "addr:postcode":"7015",
    "addr:street":"Lincoln St",
    "iso:country":"AU",
    "sg:address":"29 Lincoln St",
    "sg:city":"Lindisfarne",
    "sg:classifiers":[
        {
            "category":"Retail",
            "subcategory":"Laundry & Dry Cleaning",
            "type":"Services"
        }
    ],
    "sg:phone":"+61 3 6243 0495",
    "sg:postcode":"7015",
    "sg:province":"TAS",
    "wof:name":"Over-All Industrial Dry Cleaners & Launderers",
    "wof:placetype":"venue"
},
  "geometry": {"coordinates":[147.35319519000001,-42.8477668762],"type":"Point"}
}