{
  "type": "Feature",
  "properties": {
    "addr:full":"31 Bundeera Rd Caulfield South VIC 3162",
    "addr:housenumber":"31",
    "addr:postcode":"3162",
    "addr:street":"Bundeera Rd",
    "iso:country":"AU",
    "sg:address":"31 Bundeera Rd",
    "sg:city":"Caulfield South",
    "sg:classifiers":[
        {
            "category":"Building & Trades",
            "subcategory":"Landscaping Services",
            "type":"Services"
        }
    ],
    "sg:phone":"+61 417 576 968",
    "sg:postcode":"3162",
    "sg:province":"VIC",
    "sg:tags":[
        "stump",
        "tree",
        "felling",
        "removal"
    ],
    "wof:name":"Global Tree Services",
    "wof:placetype":"venue"
},
  "geometry": {"coordinates":[145.031448364,-37.8949546814],"type":"Point"}
}