{
  "type": "Feature",
  "properties": {
    "addr:full":"140 Princes Hwy St Peters NSW 2044",
    "addr:housenumber":"140",
    "addr:postcode":"2044",
    "addr:street":"Princes Hwy",
    "iso:country":"AU",
    "sg:address":"140 Princes Hwy",
    "sg:city":"St Peters",
    "sg:classifiers":[
        {
            "category":"Autos & Motor Vehicles",
            "subcategory":"Auto Supplies",
            "type":"Retail Goods"
        }
    ],
    "sg:phone":"+61 2 9557 1610",
    "sg:postcode":"2044",
    "sg:province":"NSW",
    "sg:tags":[
        "part",
        "cycles",
        "accessory"
    ],
    "wof:name":"Tom Byrne Motorcycles",
    "wof:placetype":"venue"
},
  "geometry": {"coordinates":[151.17880199999999,-33.913242],"type":"Point"}
}