{
  "type": "Feature",
  "properties": {
    "addr:full":"10 Albert Ave Broadbeach QLD 4218",
    "addr:housenumber":"10",
    "addr:postcode":"4218",
    "addr:street":"Albert Ave",
    "iso:country":"AU",
    "sg:address":"10 Albert Ave",
    "sg:city":"Broadbeach",
    "sg:classifiers":[
        {
            "category":"Professional",
            "subcategory":"Business Services",
            "type":"Services"
        }
    ],
    "sg:phone":"+61 7 5584 3900",
    "sg:postcode":"4218",
    "sg:province":"QLD",
    "sg:tags":[
        "broker"
    ],
    "wof:name":"LJ Hooker Business Broking Gold Coast",
    "wof:placetype":"venue"
},
  "geometry": {"coordinates":[153.43333435100001,-28.0280914307],"type":"Point"}
}