{
  "type": "Feature",
  "properties": {
    "iso:country":"AU",
    "sg:address":"Sir Donald Bradman Drv",
    "sg:city":"Brooklyn Park",
    "sg:classifiers":[
        {
            "category":"Autos & Motor Vehicles",
            "subcategory":"Boat Sales",
            "type":"Retail Goods"
        }
    ],
    "sg:phone":"+61 8 8238 3423",
    "sg:postcode":"5032",
    "sg:province":"SA",
    "sg:tags":[
        "machine",
        "dishwashing"
    ],
    "wof:name":"Eswood (Australia) Pty Ltd",
    "wof:placetype":"venue"
},
  "geometry": {"coordinates":[138.550582886,-34.9322319031],"type":"Point"}
}