{
  "type": "Feature",
  "properties": {
    "addr:full":"Unit 2 579 Kessels Rd MacGregor QLD 4109",
    "addr:housenumber":"579",
    "addr:postcode":"4109",
    "addr:street":"Kessels Rd",
    "iso:country":"AU",
    "sg:address":"Unit 2 579 Kessels Rd",
    "sg:city":"MacGregor",
    "sg:classifiers":[
        {
            "category":"Shopping",
            "subcategory":"Bicycles & Sporting Goods",
            "type":"Retail Goods"
        }
    ],
    "sg:phone":"+61 7 3343 7209",
    "sg:postcode":"4109",
    "sg:province":"QLD",
    "sg:tags":[
        "chemical",
        "equipment",
        "pool",
        "swimming"
    ],
    "wof:name":"Hasslefree Pool Delivery",
    "wof:placetype":"venue"
},
  "geometry": {"coordinates":[153.07232665999999,-27.5620536804],"type":"Point"}
}