{
  "type": "Feature",
  "properties": {
    "addr:full":"PO Box 7193 Wilberforce NSW 2756",
    "addr:postcode":"2756",
    "iso:country":"AU",
    "sg:address":"PO Box 7193",
    "sg:city":"Wilberforce",
    "sg:classifiers":[
        {
            "category":"Utilities",
            "subcategory":"Water",
            "type":"Services"
        }
    ],
    "sg:phone":"+61 2 4572 8874",
    "sg:postcode":"2756",
    "sg:province":"NSW",
    "sg:tags":[
        "equipment",
        "treatment"
    ],
    "wof:name":"Australian Water Treatment Pty Ltd",
    "wof:placetype":"venue"
},
  "geometry": {"coordinates":[150.83720398,-33.5579986572],"type":"Point"}
}