{
  "type": "Feature",
  "properties": {
    "iso:country":"AU",
    "sg:address":"1438 Wynnum Rd",
    "sg:city":"Tingalpa",
    "sg:classifiers":[
        {
            "category":"Personal",
            "subcategory":"Beauty Salon",
            "type":"Services"
        }
    ],
    "sg:phone":"+61 7 3890 8088",
    "sg:postcode":"4173",
    "sg:province":"QLD",
    "sg:tags":[
        "hairdresser"
    ],
    "wof:name":"Loveshack Hair Studio",
    "wof:placetype":"venue"
},
  "geometry": {"coordinates":[153.11958313,-27.4743041992],"type":"Point"}
}