{
  "type": "Feature",
  "properties": {
    "addr:full":"National Mutual House 43 Gordon St Coffs Harbour NSW 2450",
    "addr:housenumber":"43",
    "addr:postcode":"2450",
    "addr:street":"Gordon St",
    "iso:country":"AU",
    "sg:address":"National Mutual House 43 Gordon St",
    "sg:city":"Coffs Harbour",
    "sg:classifiers":[
        {
            "category":"Professional",
            "subcategory":"Employment Agencies",
            "type":"Services"
        }
    ],
    "sg:phone":"+61 2 6651 7433",
    "sg:postcode":"2450",
    "sg:province":"NSW",
    "wof:name":"Work Directions Australia",
    "wof:placetype":"venue"
},
  "geometry": {"coordinates":[153.11833200000001,-30.295698],"type":"Point"}
}