{
  "type": "Feature",
  "properties": {
    "addr:full":"20 Glenister St Archerfield QLD 4108",
    "addr:housenumber":"20",
    "addr:postcode":"4108",
    "addr:street":"Glenister St",
    "iso:country":"AU",
    "sg:address":"20 Glenister St",
    "sg:city":"Archerfield",
    "sg:classifiers":[
        {
            "category":"Manufacturing",
            "subcategory":"Metals",
            "type":"Manufacturing & Wholesale Goods"
        }
    ],
    "sg:phone":"+61 7 3255 6065",
    "sg:postcode":"4108",
    "sg:province":"QLD",
    "sg:tags":[
        "sheet",
        "worker"
    ],
    "wof:name":"Specialised Stainless Fabrication",
    "wof:placetype":"venue"
},
  "geometry": {"coordinates":[153.01835632300001,-27.565536499],"type":"Point"}
}