{
  "type": "Feature",
  "properties": {
    "iso:country":"AU",
    "sg:address":"Catamaran Road",
    "sg:city":"Fountaindale",
    "sg:classifiers":[
        {
            "category":"Education",
            "subcategory":"School",
            "type":"Public Place"
        }
    ],
    "sg:phone":"+61 2 4362 3400",
    "sg:postcode":"2259",
    "sg:province":"NSW",
    "wof:name":"Central Coast Rudolf Steiner School",
    "wof:placetype":"venue"
},
  "geometry": {"coordinates":[151.42291259800001,-33.1819992065],"type":"Point"}
}