{
  "type": "Feature",
  "properties": {
    "addr:full":"Factory 2 50 Healey Rd Dandenong VIC 3175",
    "addr:housenumber":"50",
    "addr:postcode":"3175",
    "addr:street":"Healey Rd",
    "iso:country":"AU",
    "sg:address":"Factory 2 50 Healey Rd",
    "sg:city":"Dandenong",
    "sg:classifiers":[
        {
            "category":"Building & Trades",
            "subcategory":"Equipment Rental",
            "type":"Services"
        }
    ],
    "sg:phone":"+61 3 9768 4444",
    "sg:postcode":"3175",
    "sg:province":"VIC",
    "sg:tags":[
        "platform",
        "hire",
        "work",
        "elevating"
    ],
    "sg:website":"http://www.giantaccess.com",
    "wof:name":"Giant Access",
    "wof:placetype":"venue"
},
  "geometry": {"coordinates":[145.22706604000001,-38.0279846191],"type":"Point"}
}