{
  "type": "Feature",
  "properties": {
    "addr:full":"PO Box 144 Brompton SA 5007",
    "addr:postcode":"5007",
    "iso:country":"AU",
    "sg:address":"PO Box 144",
    "sg:city":"Brompton",
    "sg:classifiers":[
        {
            "category":"Professional",
            "subcategory":"Detective & Security Services",
            "type":"Services"
        }
    ],
    "sg:phone":"+61 417 839 700",
    "sg:postcode":"5007",
    "sg:province":"SA",
    "sg:tags":[
        "guard",
        "patrol"
    ],
    "wof:name":"Auswide Protective Services Australia",
    "wof:placetype":"venue"
},
  "geometry": {"coordinates":[138.57681274399999,-34.8988304138],"type":"Point"}
}