{
  "type": "Feature",
  "properties": {
    "addr:full":"17 Richardson St Katanning WA 6317",
    "addr:housenumber":"17",
    "addr:postcode":"6317",
    "addr:street":"Richardson St",
    "iso:country":"AU",
    "sg:address":"17 Richardson St",
    "sg:city":"Katanning",
    "sg:classifiers":[
        {
            "category":"Professional",
            "subcategory":"Accounting & Tax Preparation",
            "type":"Services"
        }
    ],
    "sg:phone":"+61 8 9821 1311",
    "sg:postcode":"6317",
    "sg:province":"WA",
    "sg:tags":[
        "accountant",
        "auditor"
    ],
    "wof:name":"Hepworth D.J. & Associates",
    "wof:placetype":"venue"
},
  "geometry": {"coordinates":[117.553726196,-33.6879997253],"type":"Point"}
}