{
  "type": "Feature",
  "properties": {
    "addr:full":"180 Camberwell Rd Camberwell VIC 3124",
    "addr:housenumber":"180",
    "addr:postcode":"3124",
    "addr:street":"Camberwell Rd",
    "iso:country":"AU",
    "sg:address":"180 Camberwell Rd",
    "sg:city":"Camberwell",
    "sg:classifiers":[
        {
            "category":"Retail",
            "subcategory":"Repair Shop",
            "type":"Services"
        }
    ],
    "sg:phone":"+61 3 9882 1618",
    "sg:postcode":"3124",
    "sg:province":"VIC",
    "sg:tags":[
        "mending",
        "clothing",
        "alteration"
    ],
    "wof:name":"Butler Dry Cleaners The",
    "wof:placetype":"venue"
},
  "geometry": {"coordinates":[145.05543518100001,-37.830406189],"type":"Point"}
}