{
  "type": "Feature",
  "properties": {
    "addr:full":"13 Harvie St Glen Waverley VIC 3150",
    "addr:housenumber":"13",
    "addr:postcode":"3150",
    "addr:street":"Harvie St",
    "iso:country":"AU",
    "sg:address":"13 Harvie St",
    "sg:city":"Glen Waverley",
    "sg:classifiers":[
        {
            "category":"Retail",
            "subcategory":"Repair Shop",
            "type":"Services"
        }
    ],
    "sg:phone":"+61 3 9802 5143",
    "sg:postcode":"3150",
    "sg:province":"VIC",
    "sg:tags":[
        "machine",
        "repairs",
        "part",
        "dryer",
        "washing"
    ],
    "wof:name":"Monash Appliance Repairs",
    "wof:placetype":"venue"
},
  "geometry": {"coordinates":[145.170013428,-37.8734283447],"type":"Point"}
}