{
  "type": "Feature",
  "properties": {
    "addr:full":"317 Albany Hwy Victoria Park WA 6100",
    "addr:housenumber":"317",
    "addr:postcode":"6100",
    "addr:street":"Albany Hwy Victoria",
    "iso:country":"AU",
    "sg:address":"317 Albany Hwy",
    "sg:city":"Victoria Park",
    "sg:classifiers":[
        {
            "category":"Restaurant",
            "type":"Food & Drink"
        }
    ],
    "sg:phone":"+61 8 9472 6881",
    "sg:postcode":"6100",
    "sg:province":"WA",
    "wof:name":"Bellas Cafe",
    "wof:placetype":"venue"
},
  "geometry": {"coordinates":[115.89617157000001,-31.9726657867],"type":"Point"}
}