{
  "type": "Feature",
  "properties": {
    "addr:full":"408 Mona Vale Rd St Ives NSW 2075",
    "addr:housenumber":"408",
    "addr:postcode":"2075",
    "addr:street":"Mona Vale Rd",
    "iso:country":"AU",
    "sg:address":"408 Mona Vale Rd",
    "sg:city":"St Ives",
    "sg:classifiers":[
        {
            "category":"Health Services",
            "subcategory":"Doctor",
            "type":"Services"
        }
    ],
    "sg:phone":"+61 2 9144 6638",
    "sg:postcode":"2075",
    "sg:province":"NSW",
    "sg:tags":[
        "medical",
        "practitioner"
    ],
    "wof:name":"George Prof C.R.P.",
    "wof:placetype":"venue"
},
  "geometry": {"coordinates":[151.17449951200001,-33.710105896],"type":"Point"}
}