{
  "type": "Feature",
  "properties": {
    "iso:country":"AU",
    "sg:address":"PO Box 610",
    "sg:city":"Top Ryde",
    "sg:classifiers":[
        {
            "category":"Health Services",
            "subcategory":"Doctor",
            "type":"Services"
        }
    ],
    "sg:phone":"+61 2 9808 1381",
    "sg:postcode":"2112",
    "sg:province":"NSW",
    "sg:tags":[
        "medical",
        "practitioner"
    ],
    "wof:name":"Rizzo, A",
    "wof:placetype":"venue"
},
  "geometry": {"coordinates":[151.11233520499999,-33.8131599426],"type":"Point"}
}