{
  "type": "Feature",
  "properties": {
    "iso:country":"AU",
    "sg:address":"6/ 7 Apprentice Drv",
    "sg:city":"Berkeley Vale",
    "sg:classifiers":[
        {
            "category":"Professional",
            "subcategory":"Engineering",
            "type":"Services"
        }
    ],
    "sg:phone":"+61 2 4388 5899",
    "sg:postcode":"2261",
    "sg:province":"NSW",
    "sg:tags":[
        "electrical",
        "engineer"
    ],
    "wof:name":"Electrical Switchgear Services Pty Ltd",
    "wof:placetype":"venue"
},
  "geometry": {"coordinates":[151.42497299999999,-33.328617],"type":"Point"}
}