{
  "type": "Feature",
  "properties": {
    "addr:full":"457 High St Kew VIC 3101",
    "addr:housenumber":"457",
    "addr:postcode":"3101",
    "addr:street":"High St",
    "iso:country":"AU",
    "sg:address":"457 High St",
    "sg:city":"Kew",
    "sg:classifiers":[
        {
            "category":"Health Services",
            "subcategory":"Dentist",
            "type":"Services"
        }
    ],
    "sg:phone":"+61 3 9855 1636",
    "sg:postcode":"3101",
    "sg:province":"VIC",
    "wof:name":"Kew East Dental Group",
    "wof:placetype":"venue"
},
  "geometry": {"coordinates":[145.039718628,-37.8035850525],"type":"Point"}
}