{
  "type": "Feature",
  "properties": {
    "addr:full":"Balcatta Senior High School Poincare St Balcatta WA 6021",
    "addr:postcode":"6021",
    "addr:street":"Poincare St",
    "iso:country":"AU",
    "sg:address":"Balcatta Senior High School Poincare St",
    "sg:city":"Balcatta",
    "sg:classifiers":[
        {
            "category":"Education",
            "subcategory":"School",
            "type":"Public Place"
        }
    ],
    "sg:phone":"+61 8 9345 8200",
    "sg:postcode":"6021",
    "sg:province":"WA",
    "sg:tags":[
        "state",
        "except",
        "nsw"
    ],
    "wof:name":"Schools Government (Public)",
    "wof:placetype":"venue"
},
  "geometry": {"coordinates":[115.819488525,-31.8763999939],"type":"Point"}
}