{
  "type": "Feature",
  "properties": {
    "addr:full":"Unit D, 65 - 69 Strelly St Busselton WA 6280",
    "addr:housenumber":"69",
    "addr:postcode":"6280",
    "addr:street":"Strelly St",
    "iso:country":"AU",
    "sg:address":"Unit D, 65 - 69 Strelly St",
    "sg:city":"Busselton",
    "sg:classifiers":[
        {
            "category":"Sports & Exercise",
            "subcategory":"Playing Field",
            "type":"Entertainment"
        }
    ],
    "sg:phone":"+61 8 9754 3404",
    "sg:postcode":"6280",
    "sg:province":"WA",
    "sg:tags":[
        "net",
        "netting"
    ],
    "wof:name":"Southwest Crop Protection",
    "wof:placetype":"venue"
},
  "geometry": {"coordinates":[115.349639893,-33.6615333557],"type":"Point"}
}