{
  "type": "Feature",
  "properties": {
    "iso:country":"AU",
    "sg:address":"Level 1/14 Dumaresq St",
    "sg:city":"Campbelltown",
    "sg:classifiers":[
        {
            "category":"Professional",
            "subcategory":"Engineering",
            "type":"Services"
        }
    ],
    "sg:phone":"+61 2 4640 8222",
    "sg:postcode":"2560",
    "sg:province":"NSW",
    "sg:tags":[
        "consulting",
        "engineer"
    ],
    "wof:name":"Lean & Hayward Pty Ltd",
    "wof:placetype":"venue"
},
  "geometry": {"coordinates":[150.812576294,-34.0672531128],"type":"Point"}
}