{
  "type": "Feature",
  "properties": {
    "iso:country":"AU",
    "sg:address":"40 Wentworth St",
    "sg:city":"Port Kembla",
    "sg:classifiers":[
        {
            "category":"Professional",
            "subcategory":"Detective & Security Services",
            "type":"Services"
        }
    ],
    "sg:phone":"+61 2 4274 3009",
    "sg:postcode":"2505",
    "sg:province":"NSW",
    "sg:tags":[
        "equipment",
        "window",
        "doors"
    ],
    "wof:name":"Distinctive Glass & Aluminium",
    "wof:placetype":"venue"
},
  "geometry": {"coordinates":[150.900436,-34.479889],"type":"Point"}
}