{
  "type": "Feature",
  "properties": {
    "addr:full":"25 Illyarrie Ave Surrey Downs SA 5126",
    "addr:housenumber":"25",
    "addr:postcode":"5126",
    "addr:street":"Illyarrie Ave",
    "iso:country":"AU",
    "sg:address":"25 Illyarrie Ave",
    "sg:city":"Surrey Downs",
    "sg:classifiers":[
        {
            "category":"Home & Garden",
            "subcategory":"Building Materials",
            "type":"Retail Goods"
        }
    ],
    "sg:phone":"+61 8 8289 3210",
    "sg:postcode":"5126",
    "sg:province":"SA",
    "sg:tags":[
        "lawn",
        "cutting",
        "maintenance"
    ],
    "wof:name":"O&#039;Range J P & J E",
    "wof:placetype":"venue"
},
  "geometry": {"coordinates":[138.70603942899999,-34.8047218323],"type":"Point"}
}