{
  "type": "Feature",
  "properties": {
    "addr:full":"Shop 76 Lakehaven Shopping Cntr Lake Haven NSW 2263",
    "addr:housenumber":"shop 76",
    "addr:postcode":"2263",
    "addr:street":"Lakehaven Shopping Cntr Lake",
    "iso:country":"AU",
    "sg:address":"Shop 76 Lakehaven Shopping Cntr",
    "sg:city":"Lake Haven",
    "sg:classifiers":[
        {
            "category":"Deli",
            "type":"Food & Drink"
        }
    ],
    "sg:phone":"+61 2 4392 7959",
    "sg:postcode":"2263",
    "sg:province":"NSW",
    "sg:tags":[
        "delicatessen"
    ],
    "wof:name":"Slices Delicatessen Lake Haven",
    "wof:placetype":"venue"
},
  "geometry": {"coordinates":[151.500137,-33.243938],"type":"Point"}
}