{
  "type": "Feature",
  "properties": {
    "iso:country":"AU",
    "sg:address":"Shop 5 The Crescent",
    "sg:city":"Fairfield",
    "sg:classifiers":[
        {
            "category":"Shopping",
            "subcategory":"Clothing, Apparel, & Fashions",
            "type":"Retail Goods"
        }
    ],
    "sg:phone":"+61 2 9723 9035",
    "sg:postcode":"2165",
    "sg:province":"NSW",
    "sg:tags":[
        "boutique"
    ],
    "wof:name":"Elegance Boutique",
    "wof:placetype":"venue"
},
  "geometry": {"coordinates":[150.954910278,-33.8733215332],"type":"Point"}
}