{
  "type": "Feature",
  "properties": {
    "iso:country":"AU",
    "sg:address":"32 Main St",
    "sg:city":"Lilydale",
    "sg:classifiers":[
        {
            "category":"Autos & Motor Vehicles",
            "subcategory":"Auto Supplies",
            "type":"Retail Goods"
        }
    ],
    "sg:phone":"+61 3 9735 0188",
    "sg:postcode":"3140",
    "sg:province":"VIC",
    "sg:tags":[
        "tyre"
    ],
    "wof:name":"Widetread Tyre Stores",
    "wof:placetype":"venue"
},
  "geometry": {"coordinates":[145.28239440900001,-37.7946929932],"type":"Point"}
}