{
  "type": "Feature",
  "properties": {
    "addr:full":"34 George St Reservoir VIC 3073",
    "addr:housenumber":"34",
    "addr:postcode":"3073",
    "addr:street":"George St",
    "iso:country":"AU",
    "sg:address":"34 George St",
    "sg:city":"Reservoir",
    "sg:classifiers":[
        {
            "category":"Education",
            "subcategory":"Kindergarten",
            "type":"Public Place"
        }
    ],
    "sg:phone":"+61 3 9460 5708",
    "sg:postcode":"3073",
    "sg:province":"VIC",
    "sg:tags":[
        "pre-schools"
    ],
    "wof:name":"Kookaburra Kindergarten Inc",
    "wof:placetype":"venue"
},
  "geometry": {"coordinates":[145.00054931599999,-37.7161941528],"type":"Point"}
}