{
  "type": "Feature",
  "properties": {
    "iso:country":"AU",
    "sg:address":"Fairfield Rd",
    "sg:city":"Boggabri",
    "sg:classifiers":[
        {
            "category":"Education",
            "subcategory":"School",
            "type":"Public Place"
        }
    ],
    "sg:phone":"+61 2 6743 6528",
    "sg:postcode":"2382",
    "sg:province":"NSW",
    "sg:tags":[
        "state",
        "-",
        "nsw"
    ],
    "wof:name":"Willala Public School",
    "wof:placetype":"venue"
},
  "geometry": {"coordinates":[150.04176330600001,-30.7106208801],"type":"Point"}
}