{
  "type": "Feature",
  "properties": {
    "addr:full":"Gregory Hwy Emerald QLD 4720",
    "addr:postcode":"4720",
    "addr:street":"Gregory Hwy",
    "iso:country":"AU",
    "sg:address":"Gregory Hwy",
    "sg:city":"Emerald",
    "sg:classifiers":[
        {
            "category":"Retail",
            "subcategory":"Auto Repair",
            "type":"Services"
        }
    ],
    "sg:phone":"+61 7 4982 1791",
    "sg:postcode":"4720",
    "sg:province":"QLD",
    "sg:tags":[
        "beater",
        "painter",
        "panel"
    ],
    "wof:name":"A 1 Panel & Paint",
    "wof:placetype":"venue"
},
  "geometry": {"coordinates":[148.155518,-23.510698],"type":"Point"}
}