{
  "type": "Feature",
  "properties": {
    "addr:full":"20 Henderson Pl High Wycombe WA 6057",
    "addr:housenumber":"20",
    "addr:postcode":"6057",
    "addr:street":"Henderson Pl",
    "iso:country":"AU",
    "sg:address":"20 Henderson Pl",
    "sg:city":"High Wycombe",
    "sg:classifiers":[
        {
            "category":"Utilities",
            "type":"Services"
        }
    ],
    "sg:phone":"+61 418 923 275",
    "sg:postcode":"6057",
    "sg:province":"WA",
    "sg:tags":[
        "refrigeration",
        "industrial",
        "commercial",
        "retail"
    ],
    "wof:name":"G.P.H. Refrigeration",
    "wof:placetype":"venue"
},
  "geometry": {"coordinates":[116.015449524,-31.9398040771],"type":"Point"}
}