{
  "type": "Feature",
  "properties": {
    "iso:country":"AU",
    "sg:address":"Cnr Ross & Durong Sts",
    "sg:city":"Newstead",
    "sg:classifiers":[
        {
            "category":"Professional",
            "subcategory":"Printing & Photocopies",
            "type":"Services"
        }
    ],
    "sg:phone":"+61 7 3257 1109",
    "sg:postcode":"4006",
    "sg:province":"QLD",
    "sg:tags":[
        "textile",
        "clothing"
    ],
    "wof:name":"Universal Apparel",
    "wof:placetype":"venue"
},
  "geometry": {"coordinates":[153.044158936,-27.4419288635],"type":"Point"}
}