{
  "type": "Feature",
  "properties": {
    "addr:full":"16B Williams St Inverloch VIC 3996",
    "addr:housenumber":"16b",
    "addr:postcode":"3996",
    "addr:street":"Williams St",
    "iso:country":"AU",
    "sg:address":"16B Williams St",
    "sg:city":"Inverloch",
    "sg:classifiers":[
        {
            "category":"Retail",
            "subcategory":"Veterinary Services",
            "type":"Services"
        }
    ],
    "sg:phone":"+61 3 5674 2408",
    "sg:postcode":"3996",
    "sg:province":"VIC",
    "sg:tags":[
        "surgeon"
    ],
    "wof:name":"Inverloch Veterinary Clinic",
    "wof:placetype":"venue"
},
  "geometry": {"coordinates":[145.729874,-38.632668],"type":"Point"}
}