{
  "type": "Feature",
  "properties": {
    "addr:full":"7 Sunnyside St Mayfield NSW 2304",
    "addr:housenumber":"7",
    "addr:postcode":"2304",
    "addr:street":"Sunnyside St",
    "iso:country":"AU",
    "sg:address":"7 Sunnyside St",
    "sg:city":"Mayfield",
    "sg:classifiers":[
        {
            "category":"Building & Trades",
            "subcategory":"Construction",
            "type":"Services"
        }
    ],
    "sg:phone":"+61 2 4968 4532",
    "sg:postcode":"2304",
    "sg:province":"NSW",
    "sg:tags":[
        "pool",
        "swimming"
    ],
    "wof:name":"Wade Smith Concreting",
    "wof:placetype":"venue"
},
  "geometry": {"coordinates":[151.73060607900001,-32.9002494812],"type":"Point"}
}