{
  "type": "Feature",
  "properties": {
    "addr:full":"1a Barber Ave Kingswood NSW 2747",
    "addr:housenumber":"1a",
    "addr:postcode":"2747",
    "addr:street":"Barber Ave",
    "iso:country":"AU",
    "sg:address":"1a Barber Ave",
    "sg:city":"Kingswood",
    "sg:classifiers":[
        {
            "category":"Health Services",
            "subcategory":"Doctor",
            "type":"Services"
        }
    ],
    "sg:phone":"+61 2 4722 5550",
    "sg:postcode":"2747",
    "sg:province":"NSW",
    "sg:tags":[
        "medical",
        "practitioner"
    ],
    "wof:name":"Keegan A/Prof Andrew D",
    "wof:placetype":"venue"
},
  "geometry": {"coordinates":[150.7134552,-33.7581634521],"type":"Point"}
}