{
  "type": "Feature",
  "properties": {
    "iso:country":"AU",
    "sg:address":"817 Canning Hwy",
    "sg:city":"Applecross",
    "sg:classifiers":[
        {
            "category":"Real Estate",
            "subcategory":"Real Estate Agent",
            "type":"Services"
        }
    ],
    "sg:phone":"+61 8 9316 2900",
    "sg:postcode":"6153",
    "sg:province":"WA",
    "wof:name":"Key West Realty",
    "wof:placetype":"venue"
},
  "geometry": {"coordinates":[115.838562,-32.01799],"type":"Point"}
}