{
  "type": "Feature",
  "properties": {
    "iso:country":"AU",
    "sg:address":"Suite 2 Unit 5 221- 223 O&#039;Riordan St",
    "sg:city":"Kingston",
    "sg:classifiers":[
        {
            "category":"Airline",
            "type":"Transportation"
        }
    ],
    "sg:phone":"+61 1300 650 532",
    "sg:postcode":"7050",
    "sg:province":"TAS",
    "sg:tags":[
        "aircraft",
        "rental",
        "charter"
    ],
    "wof:name":"Astra Jetshare",
    "wof:placetype":"venue"
},
  "geometry": {"coordinates":[147.289917,-42.964359],"type":"Point"}
}