{
  "type": "Feature",
  "properties": {
    "addr:full":"Unit 3, 14 Penrith St Penrith NSW 2750",
    "addr:housenumber":"14",
    "addr:postcode":"2750",
    "addr:street":"Penrith St",
    "iso:country":"AU",
    "sg:address":"Unit 3, 14 Penrith St",
    "sg:city":"Penrith",
    "sg:classifiers":[
        {
            "category":"Retail",
            "subcategory":"Auto Repair",
            "type":"Services"
        }
    ],
    "sg:phone":"+61 2 4731 5754",
    "sg:postcode":"2750",
    "sg:province":"NSW",
    "sg:tags":[
        "repairer",
        "motor",
        "engineer"
    ],
    "wof:name":"Nepean E.F.I.",
    "wof:placetype":"venue"
},
  "geometry": {"coordinates":[150.68374633799999,-33.7668762207],"type":"Point"}
}