{
  "type": "Feature",
  "properties": {
    "iso:country":"AU",
    "sg:address":"Taylorville Rd",
    "sg:city":"Waikerie",
    "sg:classifiers":[
        {
            "category":"Food & Beverages",
            "subcategory":"Fruits & Vegetables",
            "type":"Retail Goods"
        }
    ],
    "sg:phone":"+61 8 8541 2697",
    "sg:postcode":"5330",
    "sg:province":"SA",
    "sg:tags":[
        "grower"
    ],
    "wof:name":"Mackereth T J & A M",
    "wof:placetype":"venue"
},
  "geometry": {"coordinates":[140.00225830100001,-34.1883811951],"type":"Point"}
}