{
  "type": "Feature",
  "properties": {
    "addr:full":"Heaslip Rd Angle Vale SA 5117",
    "addr:postcode":"5117",
    "addr:street":"Heaslip Rd",
    "iso:country":"AU",
    "sg:address":"Heaslip Rd",
    "sg:city":"Angle Vale",
    "sg:classifiers":[
        {
            "category":"Autos & Motor Vehicles",
            "subcategory":"Fuel & Gas Station",
            "type":"Retail Goods"
        }
    ],
    "sg:phone":"+61 8 8284 7225",
    "sg:postcode":"5117",
    "sg:province":"SA",
    "wof:name":"Mobil Oil Australia Pty Ltd",
    "wof:placetype":"venue"
},
  "geometry": {"coordinates":[138.64659118599999,-34.6392250061],"type":"Point"}
}