{
  "type": "Feature",
  "properties": {
    "iso:country":"AU",
    "sg:address":"Albion Rd",
    "sg:city":"Clovelly",
    "sg:classifiers":[
        {
            "category":"Autos & Motor Vehicles",
            "subcategory":"Fuel & Gas Station",
            "type":"Retail Goods"
        }
    ],
    "sg:phone":"+61 2 9314 7746",
    "sg:postcode":"2031",
    "sg:province":"NSW",
    "wof:name":"OTO Gas",
    "wof:placetype":"venue"
},
  "geometry": {"coordinates":[151.253463745,-33.9061088562],"type":"Point"}
}