{
  "type": "Feature",
  "properties": {
    "iso:country":"AU",
    "sg:address":"12 Arthur St",
    "sg:city":"Croydon",
    "sg:classifiers":[
        {
            "category":"Personal",
            "subcategory":"Beauty Salon",
            "type":"Services"
        }
    ],
    "sg:phone":"+61 439 963 963",
    "sg:postcode":"2132",
    "sg:province":"NSW",
    "sg:tags":[
        "supply",
        "artist",
        "make-up"
    ],
    "wof:name":"Makeup By Zoe",
    "wof:placetype":"venue"
},
  "geometry": {"coordinates":[151.11730957,-33.8913764954],"type":"Point"}
}