{
  "type": "Feature",
  "properties": {
    "iso:country":"AU",
    "sg:address":"187 Wakefield St",
    "sg:city":"Adelaide",
    "sg:classifiers":[
        {
            "category":"Professional",
            "subcategory":"Accounting & Tax Preparation",
            "type":"Services"
        }
    ],
    "sg:phone":"+61 8 8232 1133",
    "sg:postcode":"5000",
    "sg:province":"SA",
    "sg:tags":[
        "accountant",
        "auditor"
    ],
    "wof:name":"Le Cornu Graham D",
    "wof:placetype":"venue"
},
  "geometry": {"coordinates":[138.60784912099999,-34.9284591675],"type":"Point"}
}