{
  "type": "Feature",
  "properties": {
    "addr:full":"3 Lyondon St Nollamara WA 6061",
    "addr:housenumber":"3",
    "addr:postcode":"6061",
    "addr:street":"Lyondon St",
    "iso:country":"AU",
    "sg:address":"3 Lyondon St",
    "sg:city":"Nollamara",
    "sg:classifiers":[
        {
            "category":"Building & Trades",
            "subcategory":"Construction",
            "type":"Services"
        }
    ],
    "sg:phone":"+61 438 700 803",
    "sg:postcode":"6061",
    "sg:province":"WA",
    "sg:tags":[
        "joiner",
        "carpenter"
    ],
    "wof:name":"Ewen Construction",
    "wof:placetype":"venue"
},
  "geometry": {"coordinates":[115.838546753,-31.8868751526],"type":"Point"}
}