{
  "type": "Feature",
  "properties": {
    "addr:full":"2 Pegwell Pl Currimundi QLD 4551",
    "addr:housenumber":"2",
    "addr:postcode":"4551",
    "addr:street":"Pegwell Pl",
    "iso:country":"AU",
    "sg:address":"2 Pegwell Pl",
    "sg:city":"Currimundi",
    "sg:classifiers":[
        {
            "category":"Professional",
            "subcategory":"Computer Services",
            "type":"Services"
        }
    ],
    "sg:phone":"+61 7 5438 0911",
    "sg:postcode":"4551",
    "sg:province":"QLD",
    "sg:tags":[
        "consultant",
        "system"
    ],
    "wof:name":"Independant Network Administration",
    "wof:placetype":"venue"
},
  "geometry": {"coordinates":[153.112823486,-26.7726860046],"type":"Point"}
}