{
  "type": "Feature",
  "properties": {
    "addr:full":"Boomerang Rd Meadows SA 5201",
    "addr:postcode":"5201",
    "addr:street":"Boomerang Rd",
    "iso:country":"AU",
    "sg:address":"Boomerang Rd",
    "sg:city":"Meadows",
    "sg:classifiers":[
        {
            "category":"Building & Trades",
            "subcategory":"Construction",
            "type":"Services"
        }
    ],
    "sg:phone":"+61 414 633 893",
    "sg:postcode":"5201",
    "sg:province":"SA",
    "sg:tags":[
        "earth",
        "excavating",
        "moving",
        "contractor"
    ],
    "wof:name":"G R & D L Ferguson",
    "wof:placetype":"venue"
},
  "geometry": {"coordinates":[138.74766540499999,-35.1866493225],"type":"Point"}
}