{
  "type": "Feature",
  "properties": {
    "iso:country":"AU",
    "sg:address":"16 Welch St",
    "sg:city":"Southport",
    "sg:classifiers":[
        {
            "category":"Banks & Credit Unions",
            "subcategory":"Investment Brokerage",
            "type":"Services"
        }
    ],
    "sg:phone":"+61 7 5564 0009",
    "sg:postcode":"4215",
    "sg:province":"QLD",
    "wof:name":"Financial Gain Australia",
    "wof:placetype":"venue"
},
  "geometry": {"coordinates":[153.41328430199999,-27.9644298553],"type":"Point"}
}