{
  "type": "Feature",
  "properties": {
    "addr:full":"17 Breed St Traralgon VIC 3844",
    "addr:housenumber":"17",
    "addr:postcode":"3844",
    "addr:street":"Breed St",
    "iso:country":"AU",
    "sg:address":"17 Breed St",
    "sg:city":"Traralgon",
    "sg:classifiers":[
        {
            "category":"Banks & Credit Unions",
            "subcategory":"Investment Brokerage",
            "type":"Services"
        }
    ],
    "sg:phone":"+61 3 5174 9111",
    "sg:postcode":"3844",
    "sg:province":"VIC",
    "sg:tags":[
        "share",
        "broker",
        "stock"
    ],
    "wof:name":"D.J. Grigg Pty. Ltd.",
    "wof:placetype":"venue"
},
  "geometry": {"coordinates":[146.533813477,-38.1908683777],"type":"Point"}
}