{
  "type": "Feature",
  "properties": {
    "iso:country":"AU",
    "sg:address":"350 Brunswick St",
    "sg:city":"Fitzroy",
    "sg:classifiers":[
        {
            "category":"Restaurant",
            "type":"Food & Drink"
        }
    ],
    "sg:phone":"+61 3 9419 5244",
    "sg:postcode":"3065",
    "sg:province":"VIC",
    "wof:name":"Grill'd (Healthy Burgers)",
    "wof:placetype":"venue"
},
  "geometry": {"coordinates":[144.97856140100001,-37.79662323],"type":"Point"}
}