{
  "type": "Feature",
  "properties": {
    "addr:full":"1 Hamilton Pl Bowen Hills QLD 4006",
    "addr:housenumber":"1",
    "addr:postcode":"4006",
    "addr:street":"Hamilton Pl",
    "iso:country":"AU",
    "sg:address":"1 Hamilton Pl",
    "sg:city":"Bowen Hills",
    "sg:classifiers":[
        {
            "category":"Utilities",
            "subcategory":"Electric",
            "type":"Services"
        }
    ],
    "sg:phone":"+61 7 3854 1494",
    "sg:postcode":"4006",
    "sg:province":"QLD",
    "sg:tags":[
        "electrical",
        "contractor"
    ],
    "wof:name":"Avtel Industries",
    "wof:placetype":"venue"
},
  "geometry": {"coordinates":[153.03530883799999,-27.4479560852],"type":"Point"}
}