{
  "type": "Feature",
  "properties": {
    "addr:full":"59 Queen St Marburg QLD 4346",
    "addr:housenumber":"59",
    "addr:postcode":"4346",
    "addr:street":"Queen St",
    "iso:country":"AU",
    "sg:address":"59 Queen St",
    "sg:city":"Marburg",
    "sg:classifiers":[
        {
            "category":"Manufacturing",
            "subcategory":"Metals",
            "type":"Manufacturing & Wholesale Goods"
        }
    ],
    "sg:phone":"+61 7 5464 4168",
    "sg:postcode":"4346",
    "sg:province":"QLD",
    "sg:tags":[
        "polisher"
    ],
    "wof:name":"Red's Metal Polishing & Mechanicals",
    "wof:placetype":"venue"
},
  "geometry": {"coordinates":[152.59701538100001,-27.5702533722],"type":"Point"}
}