{
  "type": "Feature",
  "properties": {
    "addr:full":"19 Airlie Ave Dandenong VIC 3175",
    "addr:housenumber":"19",
    "addr:postcode":"3175",
    "addr:street":"Airlie Ave",
    "iso:country":"AU",
    "sg:address":"19 Airlie Ave",
    "sg:city":"Dandenong",
    "sg:classifiers":[
        {
            "category":"Building & Trades",
            "subcategory":"Construction",
            "type":"Services"
        }
    ],
    "sg:phone":"+61 3 9769 2522",
    "sg:postcode":"3175",
    "sg:province":"VIC",
    "sg:tags":[
        "concrete",
        "contractor"
    ],
    "wof:name":"AHDD Directional Drilling Pty Ltd",
    "wof:placetype":"venue"
},
  "geometry": {"coordinates":[145.203857422,-37.9725227356],"type":"Point"}
}