{
  "type": "Feature",
  "properties": {
    "iso:country":"AU",
    "sg:address":"Johnson Rd",
    "sg:city":"Gracemere",
    "sg:classifiers":[
        {
            "category":"Education",
            "subcategory":"School",
            "type":"Public Place"
        }
    ],
    "sg:phone":"+61 7 4931 7817",
    "sg:postcode":"4702",
    "sg:province":"QLD",
    "sg:tags":[
        "state",
        "except",
        "nsw"
    ],
    "wof:name":"Waraburra Preschool",
    "wof:placetype":"venue"
},
  "geometry": {"coordinates":[150.45419311500001,-23.4430332184],"type":"Point"}
}