{
  "type": "Feature",
  "properties": {
    "iso:country":"AU",
    "sg:address":"100 Scenic Drv",
    "sg:city":"Lewisham",
    "sg:classifiers":[
        {
            "category":"Building & Trades",
            "subcategory":"Construction",
            "type":"Services"
        }
    ],
    "sg:phone":"+61 412 200 768",
    "sg:postcode":"7173",
    "sg:province":"TAS",
    "sg:tags":[
        "contractor"
    ],
    "wof:name":"Clarke Building & Constructions",
    "wof:placetype":"venue"
},
  "geometry": {"coordinates":[147.61610412600001,-42.8364181519],"type":"Point"}
}