{
  "type": "Feature",
  "properties": {
    "iso:country":"AU",
    "sg:address":"193 Carlisle St",
    "sg:city":"St Kilda East",
    "sg:classifiers":[
        {
            "category":"Fast Food",
            "type":"Food & Drink"
        }
    ],
    "sg:phone":"+61 3 9531 1282",
    "sg:postcode":"3183",
    "sg:province":"VIC",
    "sg:tags":[
        "away",
        "take"
    ],
    "wof:name":"Cica Chinese Take Away",
    "wof:placetype":"venue"
},
  "geometry": {"coordinates":[144.993377686,-37.8688545227],"type":"Point"}
}