{
  "type": "Feature",
  "properties": {
    "iso:country":"AU",
    "sg:address":"2 Bells Rd",
    "sg:city":"Somerton Park",
    "sg:classifiers":[
        {
            "category":"Building & Trades",
            "subcategory":"Construction",
            "type":"Services"
        }
    ],
    "sg:phone":"+61 418 828 946",
    "sg:postcode":"5044",
    "sg:province":"SA",
    "sg:tags":[
        "installation",
        "air conditioning"
    ],
    "wof:name":"Randall Jolly Airconditioning",
    "wof:placetype":"venue"
},
  "geometry": {"coordinates":[138.528854,-34.991455],"type":"Point"}
}