{
  "type": "Feature",
  "properties": {
    "addr:full":"Unit 10 1a Coulson St Erskineville NSW 2043",
    "addr:housenumber":"1a",
    "addr:postcode":"2043",
    "addr:street":"Coulson St",
    "iso:country":"AU",
    "sg:address":"Unit 10 1a Coulson St",
    "sg:city":"Erskineville",
    "sg:classifiers":[
        {
            "category":"Wholesale",
            "subcategory":"Apparel",
            "type":"Manufacturing & Wholesale Goods"
        }
    ],
    "sg:phone":"+61 2 9565 1652",
    "sg:postcode":"2043",
    "sg:province":"NSW",
    "sg:tags":[
        "wholesaler",
        "mfrs",
        "dress"
    ],
    "wof:name":"Andiamo Design",
    "wof:placetype":"venue"
},
  "geometry": {"coordinates":[151.18550099999999,-33.905586],"type":"Point"}
}