{
  "type": "Feature",
  "properties": {
    "iso:country":"AU",
    "sg:address":"126 Brighton Ave",
    "sg:city":"Toronto",
    "sg:classifiers":[
        {
            "category":"Health Services",
            "subcategory":"Dentist",
            "type":"Services"
        }
    ],
    "sg:phone":"+61 2 4950 4311",
    "sg:postcode":"2283",
    "sg:province":"NSW",
    "wof:name":"Buddee David R",
    "wof:placetype":"venue"
},
  "geometry": {"coordinates":[151.59539794899999,-33.0147361755],"type":"Point"}
}