{
  "type": "Feature",
  "properties": {
    "addr:full":"U 9/ 21 Sydney Rd Manly NSW 2095",
    "addr:postcode":"2095",
    "addr:street":"Sydney Rd",
    "iso:country":"AU",
    "sg:address":"U 9/ 21 Sydney Rd",
    "sg:city":"Manly",
    "sg:classifiers":[
        {
            "category":"Shopping",
            "subcategory":"Computers & Home Electronics",
            "type":"Retail Goods"
        }
    ],
    "sg:phone":"+61 2 9976 2982",
    "sg:postcode":"2095",
    "sg:province":"NSW",
    "sg:tags":[
        "hardware",
        "equipment"
    ],
    "wof:name":"Touch Screen Solutions",
    "wof:placetype":"venue"
},
  "geometry": {"coordinates":[151.2862854,-33.7972068787],"type":"Point"}
}