{
  "type": "Feature",
  "properties": {
    "iso:country":"AU",
    "sg:address":"20 Wood St",
    "sg:city":"Beechworth",
    "sg:classifiers":[
        {
            "category":"Health Services",
            "subcategory":"Health Practitioner",
            "type":"Services"
        }
    ],
    "sg:phone":"+61 3 5728 1319",
    "sg:postcode":"3747",
    "sg:province":"VIC",
    "sg:tags":[
        "homoeopath"
    ],
    "wof:name":"Milne L",
    "wof:placetype":"venue"
},
  "geometry": {"coordinates":[146.683685,-36.355732],"type":"Point"}
}