{
  "type": "Feature",
  "properties": {
    "addr:full":"Lot 21/ Victoria Falls Rd Cobungra VIC 3898",
    "addr:housenumber":"/",
    "addr:postcode":"3898",
    "addr:street":"Victoria Falls Rd",
    "iso:country":"AU",
    "sg:address":"Lot 21/ Victoria Falls Rd",
    "sg:city":"Cobungra",
    "sg:classifiers":[
        {
            "category":"Building & Trades",
            "subcategory":"Construction",
            "type":"Services"
        }
    ],
    "sg:phone":"+61 3 5159 1417",
    "sg:postcode":"3898",
    "sg:province":"VIC",
    "sg:tags":[
        "management"
    ],
    "wof:name":"R & R Van Heek Pty Ltd",
    "wof:placetype":"venue"
},
  "geometry": {"coordinates":[147.44659423799999,-37.0906829834],"type":"Point"}
}