{
  "type": "Feature",
  "properties": {
    "addr:full":"Shop 1/ 13- 15 Mutu St Woy Woy NSW 2256",
    "addr:housenumber":"shop 1 / 13 15",
    "addr:postcode":"2256",
    "addr:street":"Mutu St",
    "iso:country":"AU",
    "sg:address":"Shop 1/ 13- 15 Mutu St",
    "sg:city":"Woy Woy",
    "sg:classifiers":[
        {
            "category":"Retail",
            "subcategory":"Repair Shop",
            "type":"Services"
        }
    ],
    "sg:phone":"+61 2 4342 3538",
    "sg:postcode":"2256",
    "sg:province":"NSW",
    "sg:tags":[
        "machine",
        "repairs",
        "part",
        "dryer",
        "washing"
    ],
    "wof:name":"Jayars Appliance Service Pty Ltd",
    "wof:placetype":"venue"
},
  "geometry": {"coordinates":[151.31964111299999,-33.4931297302],"type":"Point"}
}