{
  "type": "Feature",
  "properties": {
    "addr:full":"49 Regent St Mittagong NSW 2575",
    "addr:housenumber":"49",
    "addr:postcode":"2575",
    "addr:street":"Regent St",
    "iso:country":"AU",
    "sg:address":"49 Regent St",
    "sg:city":"Mittagong",
    "sg:classifiers":[
        {
            "category":"Retail",
            "subcategory":"Veterinary Services",
            "type":"Services"
        }
    ],
    "sg:phone":"+61 2 4872 1499",
    "sg:postcode":"2575",
    "sg:province":"NSW",
    "sg:tags":[
        "surgeon"
    ],
    "wof:name":"Hazzard Philip",
    "wof:placetype":"venue"
},
  "geometry": {"coordinates":[150.44644165,-34.4523963928],"type":"Point"}
}