{
  "type": "Feature",
  "properties": {
    "iso:country":"AU",
    "sg:address":"6 Chelmsford Rd",
    "sg:city":"Asquith",
    "sg:classifiers":[
        {
            "category":"Professional",
            "subcategory":"Management & Consulting",
            "type":"Services"
        }
    ],
    "sg:phone":"+61 2 9940 4646",
    "sg:postcode":"2077",
    "sg:province":"NSW",
    "sg:tags":[
        "consultant",
        "business"
    ],
    "wof:name":"Red Elephant Business Solutions",
    "wof:placetype":"venue"
},
  "geometry": {"coordinates":[151.11651611299999,-33.6883277893],"type":"Point"}
}