{
  "type": "Feature",
  "properties": {
    "addr:full":"Level 1, Cnr Gailey Rd & Indooroopilly Rd Taringa QLD 4068",
    "addr:housenumber":"cnr",
    "addr:postcode":"4068",
    "addr:street":"Gailey Rd & Indooroopilly Rd",
    "iso:country":"AU",
    "sg:address":"Level 1, Cnr Gailey Rd & Indooroopilly Rd",
    "sg:city":"Taringa",
    "sg:classifiers":[
        {
            "category":"Health Services",
            "subcategory":"Dentist",
            "type":"Services"
        }
    ],
    "sg:phone":"+61 7 3870 1100",
    "sg:postcode":"4068",
    "sg:province":"QLD",
    "wof:name":"Fiveways Taringa Dental Practice",
    "wof:placetype":"venue"
},
  "geometry": {"coordinates":[152.99118042000001,-27.4963531494],"type":"Point"}
}