{
  "type": "Feature",
  "properties": {
    "iso:country":"AU",
    "sg:address":"Ste 307 Strand Arc Pitt St",
    "sg:city":"Sydney",
    "sg:classifiers":[
        {
            "category":"Health Services",
            "subcategory":"Health Practitioner",
            "type":"Services"
        }
    ],
    "sg:phone":"+61 2 9233 5362",
    "sg:postcode":"2000",
    "sg:province":"NSW",
    "sg:tags":[
        "naturopath"
    ],
    "wof:name":"Beim Mim",
    "wof:placetype":"venue"
},
  "geometry": {"coordinates":[151.20826721200001,-33.8694496155],"type":"Point"}
}