{
  "type": "Feature",
  "properties": {
    "iso:country":"AU",
    "sg:address":"35 Parramatta Rd",
    "sg:city":"Five Dock",
    "sg:classifiers":[
        {
            "category":"Retail",
            "subcategory":"Auto Repair",
            "type":"Services"
        }
    ],
    "sg:phone":"+61 2 9716 7690",
    "sg:postcode":"2046",
    "sg:province":"NSW",
    "sg:tags":[
        "repairer",
        "motor",
        "engineer"
    ],
    "wof:name":"Ric Shaw Performance",
    "wof:placetype":"venue"
},
  "geometry": {"coordinates":[151.124664,-33.871868],"type":"Point"}
}