{
  "type": "Feature",
  "properties": {
    "addr:full":"Murtha Drv Elanora QLD 4221",
    "addr:postcode":"4221",
    "addr:street":"Murtha Drv",
    "iso:country":"AU",
    "sg:address":"Murtha Drv",
    "sg:city":"Elanora",
    "sg:classifiers":[
        {
            "category":"Education",
            "subcategory":"Music School",
            "type":"Public Place"
        }
    ],
    "sg:phone":"+61 7 5534 7583",
    "sg:postcode":"4221",
    "sg:province":"QLD",
    "sg:tags":[
        "therapy",
        "relaxation"
    ],
    "wof:name":"Hydroflexology Therapies",
    "wof:placetype":"venue"
},
  "geometry": {"coordinates":[153.46287536599999,-28.1286869049],"type":"Point"}
}