{
  "type": "Feature",
  "properties": {
    "iso:country":"AU",
    "sg:address":"Suite 10 NCYC Commercial Centre 91 Hannell St",
    "sg:city":"Wickham",
    "sg:classifiers":[
        {
            "category":"Transit Center",
            "subcategory":"Freight",
            "type":"Transportation"
        }
    ],
    "sg:phone":"+61 2 4969 7988",
    "sg:postcode":"2293",
    "sg:province":"NSW",
    "sg:tags":[
        "agent",
        "shipping"
    ],
    "wof:name":"A.A.L. Shipping Agencies Pty Ltd",
    "wof:placetype":"venue"
},
  "geometry": {"coordinates":[151.76002502399999,-32.9203796387],"type":"Point"}
}