{
  "type": "Feature",
  "properties": {
    "iso:country":"AU",
    "sg:address":"PO Box 80",
    "sg:city":"Mission Beach",
    "sg:classifiers":[
        {
            "category":"Real Estate",
            "subcategory":"Real Estate Agent",
            "type":"Services"
        }
    ],
    "sg:phone":"+61 427 628 273",
    "sg:postcode":"4852",
    "sg:province":"QLD",
    "sg:tags":[
        "handyman's",
        "equipment",
        "hire",
        "builders",
        "contractor"
    ],
    "wof:name":"Tropical Coast Plant Hire",
    "wof:placetype":"venue"
},
  "geometry": {"coordinates":[146.10650634800001,-17.8687000275],"type":"Point"}
}