{
  "type": "Feature",
  "properties": {
    "addr:full":"11 Florence St Burwood VIC 3125",
    "addr:housenumber":"11",
    "addr:postcode":"3125",
    "addr:street":"Florence St",
    "iso:country":"AU",
    "sg:address":"11 Florence St",
    "sg:city":"Burwood",
    "sg:classifiers":[
        {
            "category":"Military Area",
            "subcategory":"Armory",
            "type":"Public Place"
        }
    ],
    "sg:phone":"+61 3 9888 8987",
    "sg:postcode":"3125",
    "sg:province":"VIC",
    "sg:tags":[
        "teleconferencing"
    ],
    "wof:name":"IBS Audio Visual",
    "wof:placetype":"venue"
},
  "geometry": {"coordinates":[145.11187744099999,-37.8582038879],"type":"Point"}
}