{
  "type": "Feature",
  "properties": {
    "addr:full":"Newells Hwy Parkes NSW 2870",
    "addr:postcode":"2870",
    "addr:street":"Newells Hwy",
    "iso:country":"AU",
    "sg:address":"Newells Hwy",
    "sg:city":"Parkes",
    "sg:classifiers":[
        {
            "category":"Professional",
            "subcategory":"Computer Services",
            "type":"Services"
        }
    ],
    "sg:phone":"+61 2 6862 4365",
    "sg:postcode":"2870",
    "sg:province":"NSW",
    "sg:tags":[
        "information"
    ],
    "wof:name":"Tourist Information Centre",
    "wof:placetype":"venue"
},
  "geometry": {"coordinates":[148.17463699999999,-33.136883],"type":"Point"}
}