{
  "type": "Feature",
  "properties": {
    "addr:full":"Saleyards Rd Harden NSW 2587",
    "addr:postcode":"2587",
    "addr:street":"Saleyards Rd",
    "iso:country":"AU",
    "sg:address":"Saleyards Rd",
    "sg:city":"Harden",
    "sg:classifiers":[
        {
            "category":"Banks & Credit Unions",
            "subcategory":"Investment Brokerage",
            "type":"Services"
        }
    ],
    "sg:phone":"+61 2 6386 4051",
    "sg:postcode":"2587",
    "sg:province":"NSW",
    "sg:tags":[
        "mfrg",
        "wholesale",
        "product",
        "sheepskin"
    ],
    "wof:name":"Skinmaster Australia Pty Ltd",
    "wof:placetype":"venue"
},
  "geometry": {"coordinates":[148.37025451700001,-34.5462341309],"type":"Point"}
}