{
  "type": "Feature",
  "properties": {
    "addr:full":"Windaroo Shopping Village 2 Carl Heck Blv Windaroo QLD 4207",
    "addr:housenumber":"2",
    "addr:postcode":"4207",
    "addr:street":"Carl Heck Blv",
    "iso:country":"AU",
    "sg:address":"Windaroo Shopping Village 2",
    "sg:city":"Carl Heck Blv Windaroo",
    "sg:classifiers":[
        {
            "category":"Health Services",
            "subcategory":"Doctor",
            "type":"Services"
        }
    ],
    "sg:phone":"+61 7 3804 1188",
    "sg:postcode":"4207",
    "sg:province":"QLD",
    "sg:tags":[
        "medical",
        "practitioner"
    ],
    "wof:name":"Kumar J Dr",
    "wof:placetype":"venue"
},
  "geometry": {"coordinates":[153.19204711899999,-27.7410507202],"type":"Point"}
}