{
  "type": "Feature",
  "properties": {
    "iso:country":"AU",
    "sg:address":"Unit 3, 23 Gibberd Rd",
    "sg:city":"Balcatta",
    "sg:classifiers":[
        {
            "category":"Utilities",
            "subcategory":"Refuse",
            "type":"Services"
        }
    ],
    "sg:phone":"+61 8 9240 1187",
    "sg:postcode":"6021",
    "sg:province":"WA",
    "sg:tags":[
        "remover",
        "rubbish"
    ],
    "wof:name":"All Scrap Removals",
    "wof:placetype":"venue"
},
  "geometry": {"coordinates":[115.813072205,-31.8645019531],"type":"Point"}
}