{
  "type": "Feature",
  "properties": {
    "addr:full":"Shop 1 Lansell Plaza High St Kangaroo Flat VIC 3555",
    "addr:housenumber":"shop 1",
    "addr:postcode":"3555",
    "addr:street":"Lansell Plaza High St",
    "iso:country":"AU",
    "sg:address":"Shop 1 Lansell Plaza High St",
    "sg:city":"Kangaroo Flat",
    "sg:classifiers":[
        {
            "category":"Shopping",
            "subcategory":"Clothing, Apparel, & Fashions",
            "type":"Retail Goods"
        }
    ],
    "sg:phone":"+61 3 5447 9420",
    "sg:postcode":"3555",
    "sg:province":"VIC",
    "sg:tags":[
        "lady",
        "wear"
    ],
    "wof:name":"Suzanne Grae",
    "wof:placetype":"venue"
},
  "geometry": {"coordinates":[144.24418640100001,-36.7957687378],"type":"Point"}
}