{
  "type": "Feature",
  "properties": {
    "addr:full":"26 Tedder Ave Main Beach QLD 4217",
    "addr:housenumber":"26",
    "addr:postcode":"4217",
    "addr:street":"Tedder Ave",
    "iso:country":"AU",
    "sg:address":"26 Tedder Ave",
    "sg:city":"Main Beach",
    "sg:classifiers":[
        {
            "category":"Personal",
            "subcategory":"Beauty Salon",
            "type":"Services"
        }
    ],
    "sg:phone":"+61 7 5526 4644",
    "sg:postcode":"4217",
    "sg:province":"QLD",
    "sg:tags":[
        "hairdresser"
    ],
    "wof:name":"Bohemian Hair",
    "wof:placetype":"venue"
},
  "geometry": {"coordinates":[153.42489624000001,-27.97864151],"type":"Point"}
}