{
  "type": "Feature",
  "properties": {
    "iso:country":"AU",
    "sg:address":"20 Hugh St",
    "sg:city":"Pinkenba",
    "sg:classifiers":[
        {
            "category":"Home & Garden",
            "subcategory":"Garden Supply",
            "type":"Retail Goods"
        }
    ],
    "sg:phone":"+61 7 3860 3120",
    "sg:postcode":"4008",
    "sg:province":"QLD",
    "sg:tags":[
        "fertilizer"
    ],
    "wof:name":"Neutrog Fertilisers QLD#",
    "wof:placetype":"venue"
},
  "geometry": {"coordinates":[153.111984253,-27.4291820526],"type":"Point"}
}