{
  "type": "Feature",
  "properties": {
    "addr:full":"46 Rocky Passage Rd Redland Bay QLD 4165",
    "addr:housenumber":"46",
    "addr:postcode":"4165",
    "addr:street":"Rocky Passage Rd",
    "iso:country":"AU",
    "sg:address":"46 Rocky Passage Rd",
    "sg:city":"Redland Bay",
    "sg:classifiers":[
        {
            "category":"Retail",
            "subcategory":"Auto Repair",
            "type":"Services"
        }
    ],
    "sg:phone":"+61 7 3829 0322",
    "sg:postcode":"4165",
    "sg:province":"QLD",
    "sg:tags":[
        "beater",
        "painter",
        "panel"
    ],
    "wof:name":"Redland Bay Smash Repairs",
    "wof:placetype":"venue"
},
  "geometry": {"coordinates":[153.30130004899999,-27.6873397827],"type":"Point"}
}