{
  "type": "Feature",
  "properties": {
    "iso:country":"AU",
    "sg:address":"9 George St",
    "sg:city":"Sorrento",
    "sg:classifiers":[
        {
            "category":"Travel",
            "subcategory":"Travel Agent",
            "type":"Entertainment"
        }
    ],
    "sg:phone":"+61 3 5984 3366",
    "sg:postcode":"3943",
    "sg:province":"VIC",
    "sg:tags":[
        "consultant"
    ],
    "wof:name":"Sorrento Beach Travel",
    "wof:placetype":"venue"
},
  "geometry": {"coordinates":[144.73963928200001,-38.3396835327],"type":"Point"}
}