{
  "type": "Feature",
  "properties": {
    "addr:full":"Brunswick Pl Samford QLD 4520",
    "addr:postcode":"4520",
    "iso:country":"AU",
    "sg:address":"Brunswick Pl",
    "sg:city":"Samford",
    "sg:classifiers":[
        {
            "category":"Utilities",
            "subcategory":"Electric",
            "type":"Services"
        }
    ],
    "sg:phone":"+61 7 3289 1085",
    "sg:postcode":"4520",
    "sg:province":"QLD",
    "sg:tags":[
        "electrical",
        "contractor"
    ],
    "wof:name":"Telfar G G & M",
    "wof:placetype":"venue"
},
  "geometry": {"coordinates":[152.84599299999999,-27.381922],"type":"Point"}
}