{
  "type": "Feature",
  "properties": {
    "iso:country":"AU",
    "sg:address":"544 Sturt St",
    "sg:city":"Townsville",
    "sg:classifiers":[
        {
            "category":"Professional",
            "subcategory":"Art Services",
            "type":"Services"
        }
    ],
    "sg:phone":"+61 7 4795 8887",
    "sg:postcode":"4810",
    "sg:province":"QLD",
    "sg:tags":[
        "picture",
        "frame",
        "framing"
    ],
    "wof:name":"Artistique Framing Artworks Gallery",
    "wof:placetype":"venue"
},
  "geometry": {"coordinates":[146.80857800000001,-19.266356],"type":"Point"}
}