{
  "type": "Feature",
  "properties": {
    "iso:country":"AU",
    "sg:address":"Parramatta Rd",
    "sg:city":"Burwood",
    "sg:classifiers":[
        {
            "category":"Communications",
            "subcategory":"Film & Video Production",
            "type":"Services"
        }
    ],
    "sg:phone":"+61 2 9316 6088",
    "sg:postcode":"2134",
    "sg:province":"NSW",
    "sg:tags":[
        "mirror"
    ],
    "wof:name":"O&#039;Ryans Glass Service",
    "wof:placetype":"venue"
},
  "geometry": {"coordinates":[151.10609435999999,-33.8690223694],"type":"Point"}
}