{
  "type": "Feature",
  "properties": {
    "addr:full":"27 Queen St Williamstown SA 5351",
    "addr:housenumber":"27",
    "addr:postcode":"5351",
    "addr:street":"Queen St",
    "iso:country":"AU",
    "sg:address":"27 Queen St",
    "sg:city":"Williamstown",
    "sg:classifiers":[
        {
            "category":"Health Services",
            "subcategory":"Doctor",
            "type":"Services"
        }
    ],
    "sg:phone":"+61 8 8524 6122",
    "sg:postcode":"5351",
    "sg:province":"SA",
    "sg:tags":[
        "medical",
        "practitioner"
    ],
    "wof:name":"Brewerton K",
    "wof:placetype":"venue"
},
  "geometry": {"coordinates":[138.89015197800001,-34.6707458496],"type":"Point"}
}