{
  "type": "Feature",
  "properties": {
    "iso:country":"AU",
    "sg:address":"96 Bellflower Rd",
    "sg:city":"Chancellor Park",
    "sg:classifiers":[
        {
            "category":"Home & Garden",
            "subcategory":"Garden Supply",
            "type":"Retail Goods"
        }
    ],
    "sg:phone":"+61 7 5476 7372",
    "sg:postcode":"4556",
    "sg:province":"QLD",
    "sg:tags":[
        "equipment"
    ],
    "wof:name":"Garden Trends",
    "wof:placetype":"venue"
},
  "geometry": {"coordinates":[153.05528259299999,-26.7267189026],"type":"Point"}
}