{
  "type": "Feature",
  "properties": {
    "addr:full":"Lot 16 Derby Hwy Derby WA 6728",
    "addr:postcode":"6728",
    "addr:street":"Derby Hwy",
    "iso:country":"AU",
    "sg:address":"Lot 16 Derby Hwy",
    "sg:city":"Derby",
    "sg:classifiers":[
        {
            "category":"Real Estate",
            "subcategory":"Real Estate Agent",
            "type":"Services"
        }
    ],
    "sg:phone":"+61 8 9191 1635",
    "sg:postcode":"6728",
    "sg:province":"WA",
    "sg:tags":[
        "handyman's",
        "equipment",
        "hire",
        "builders",
        "contractor"
    ],
    "wof:name":"Kimberley Hire",
    "wof:placetype":"venue"
},
  "geometry": {"coordinates":[123.68047332800001,-17.3743972778],"type":"Point"}
}