{
  "type": "Feature",
  "properties": {
    "iso:country":"AU",
    "sg:address":"Salisbury Rd",
    "sg:city":"Stanmore",
    "sg:classifiers":[
        {
            "category":"Education",
            "subcategory":"Kindergarten",
            "type":"Public Place"
        }
    ],
    "sg:phone":"+61 2 9550 2446",
    "sg:postcode":"2048",
    "sg:province":"NSW",
    "sg:tags":[
        "pre-schools"
    ],
    "wof:name":"Stanmore Kindergarten",
    "wof:placetype":"venue"
},
  "geometry": {"coordinates":[151.165649,-33.892899],"type":"Point"}
}