{
  "type": "Feature",
  "properties": {
    "addr:full":"10 Duffy St Bundaberg QLD 4670",
    "addr:housenumber":"10",
    "addr:postcode":"4670",
    "addr:street":"Duffy St",
    "iso:country":"AU",
    "sg:address":"10 Duffy St",
    "sg:city":"Bundaberg",
    "sg:classifiers":[
        {
            "category":"Social Services",
            "subcategory":"Adult Care",
            "type":"Services"
        }
    ],
    "sg:phone":"+61 7 4153 6044",
    "sg:postcode":"4670",
    "sg:province":"QLD",
    "sg:tags":[
        "towing"
    ],
    "wof:name":"Bundaberg Towing Service",
    "wof:placetype":"venue"
},
  "geometry": {"coordinates":[152.31890869099999,-24.8723773956],"type":"Point"}
}