{
  "type": "Feature",
  "properties": {
    "addr:full":"1535 Centre Rd Clayton VIC 3168",
    "addr:housenumber":"1535",
    "addr:postcode":"3168",
    "addr:street":"Centre Rd",
    "iso:country":"AU",
    "sg:address":"1535 Centre Rd",
    "sg:city":"Clayton",
    "sg:classifiers":[
        {
            "category":"Sports & Exercise",
            "subcategory":"Gym",
            "type":"Entertainment"
        }
    ],
    "sg:phone":"+61 3 9544 4261",
    "sg:postcode":"3168",
    "sg:province":"VIC",
    "sg:tags":[
        "health",
        "fitness"
    ],
    "wof:name":"Body @ Work At Work Health & Fitness",
    "wof:placetype":"venue"
},
  "geometry": {"coordinates":[145.135620117,-37.9304542542],"type":"Point"}
}