{
  "type": "Feature",
  "properties": {
    "addr:full":"Lot 3 Deering St Yamba NSW 2464",
    "addr:postcode":"2464",
    "addr:street":"Deering St",
    "iso:country":"AU",
    "sg:address":"Lot 3 Deering St",
    "sg:city":"Yamba",
    "sg:classifiers":[
        {
            "category":"Autos & Motor Vehicles",
            "subcategory":"Automobile Sales",
            "type":"Retail Goods"
        }
    ],
    "sg:phone":"+61 2 6646 2690",
    "sg:postcode":"2464",
    "sg:province":"NSW",
    "sg:tags":[
        "car",
        "used"
    ],
    "wof:name":"M.A.T. Motors Pty Ltd",
    "wof:placetype":"venue"
},
  "geometry": {"coordinates":[153.341705322,-29.4375591278],"type":"Point"}
}