{
  "type": "Feature",
  "properties": {
    "iso:country":"AU",
    "sg:address":"76 Croudace Rd",
    "sg:city":"Elermore Vale",
    "sg:classifiers":[
        {
            "category":"Personal",
            "subcategory":"Beauty Salon",
            "type":"Services"
        }
    ],
    "sg:phone":"+61 2 4951 2414",
    "sg:postcode":"2287",
    "sg:province":"NSW",
    "sg:tags":[
        "hairdresser"
    ],
    "wof:name":"Elletes Mobile Hair & Make-Up",
    "wof:placetype":"venue"
},
  "geometry": {"coordinates":[151.66958618199999,-32.9146270752],"type":"Point"}
}