{
  "type": "Feature",
  "properties": {
    "addr:full":"39 Camilleri Ave Quakers Hill NSW 2763",
    "addr:housenumber":"39",
    "addr:postcode":"2763",
    "addr:street":"Camilleri Ave",
    "iso:country":"AU",
    "sg:address":"39 Camilleri Ave",
    "sg:city":"Quakers Hill",
    "sg:classifiers":[
        {
            "category":"Personal",
            "subcategory":"Beauty Salon",
            "type":"Services"
        }
    ],
    "sg:phone":"+61 2 9626 6718",
    "sg:postcode":"2763",
    "sg:province":"NSW",
    "sg:tags":[
        "supply",
        "artist",
        "make-up"
    ],
    "wof:name":"Bliss Wedding Consultants",
    "wof:placetype":"venue"
},
  "geometry": {"coordinates":[150.88284301799999,-33.7122344971],"type":"Point"}
}