{
  "type": "Feature",
  "properties": {
    "addr:full":"74a Bundock St Belgian Gardens QLD 4810",
    "addr:housenumber":"74a",
    "addr:postcode":"4810",
    "addr:street":"Bundock St",
    "iso:country":"AU",
    "sg:address":"74a Bundock St",
    "sg:city":"Belgian Gardens",
    "sg:classifiers":[
        {
            "category":"Deli",
            "type":"Food & Drink"
        }
    ],
    "sg:phone":"+61 7 4724 2929",
    "sg:postcode":"4810",
    "sg:province":"QLD",
    "sg:tags":[
        "delicatessen"
    ],
    "wof:name":"Essentially Fresh",
    "wof:placetype":"venue"
},
  "geometry": {"coordinates":[146.79333500000001,-19.246586],"type":"Point"}
}