{
  "type": "Feature",
  "properties": {
    "addr:full":"37 Bedford St Collingwood VIC 3066",
    "addr:housenumber":"37",
    "addr:postcode":"3066",
    "addr:street":"Bedford St",
    "iso:country":"AU",
    "sg:address":"37 Bedford St",
    "sg:city":"Collingwood",
    "sg:classifiers":[
        {
            "category":"Organizations",
            "subcategory":"Community Association",
            "type":"Services"
        }
    ],
    "sg:phone":"+61 3 9419 8355",
    "sg:postcode":"3066",
    "sg:province":"VIC",
    "sg:tags":[
        "organisation",
        "family",
        "welfare"
    ],
    "wof:name":"Bedford Street Outreach Services Inc",
    "wof:placetype":"venue"
},
  "geometry": {"coordinates":[144.98452758799999,-37.8010177612],"type":"Point"}
}