{
  "type": "Feature",
  "properties": {
    "iso:country":"AU",
    "sg:address":"30 Tile St",
    "sg:city":"Wacol",
    "sg:classifiers":[
        {
            "category":"Transit Center",
            "subcategory":"Freight",
            "type":"Transportation"
        }
    ],
    "sg:phone":"+61 7 3379 9403",
    "sg:postcode":"4076",
    "sg:province":"QLD",
    "sg:tags":[
        "honey",
        "merchant"
    ],
    "wof:name":"Lazo Krkobabic",
    "wof:placetype":"venue"
},
  "geometry": {"coordinates":[152.933349609,-27.6041030884],"type":"Point"}
}