{
  "type": "Feature",
  "properties": {
    "iso:country":"AU",
    "sg:address":"29 Carcoola St",
    "sg:city":"Chigwell",
    "sg:classifiers":[
        {
            "category":"Government",
            "subcategory":"Post Office",
            "type":"Public Place"
        }
    ],
    "sg:phone":"+61 3 6249 2525",
    "sg:postcode":"7011",
    "sg:province":"TAS",
    "sg:tags":[
        "equipment",
        "hole",
        "contractor"
    ],
    "wof:name":"Greg Hooper",
    "wof:placetype":"venue"
},
  "geometry": {"coordinates":[147.24400329599999,-42.8133468628],"type":"Point"}
}