{
  "type": "Feature",
  "properties": {
    "iso:country":"AU",
    "sg:address":"124 Nelson St",
    "sg:city":"Wallsend",
    "sg:classifiers":[
        {
            "category":"Health Services",
            "subcategory":"Doctor",
            "type":"Services"
        }
    ],
    "sg:phone":"+61 2 4955 8341",
    "sg:postcode":"2287",
    "sg:province":"NSW",
    "sg:tags":[
        "medical",
        "practitioner"
    ],
    "wof:name":"Arain Zia Dr",
    "wof:placetype":"venue"
},
  "geometry": {"coordinates":[151.66966247600001,-32.9017944336],"type":"Point"}
}