{
  "type": "Feature",
  "properties": {
    "iso:country":"AU",
    "sg:address":"61 Liverpool St",
    "sg:city":"Cowra",
    "sg:classifiers":[
        {
            "category":"Professional",
            "subcategory":"Accounting & Tax Preparation",
            "type":"Services"
        }
    ],
    "sg:phone":"+61 2 6341 1513",
    "sg:postcode":"2794",
    "sg:province":"NSW",
    "sg:tags":[
        "bookkeeping"
    ],
    "wof:name":"Deborah J Freebairn Computer Accounting and Training",
    "wof:placetype":"venue"
},
  "geometry": {"coordinates":[148.69630432100001,-33.8333282471],"type":"Point"}
}