{
  "type": "Feature",
  "properties": {
    "addr:full":"17- 23 Hoskins Rd Landsdale WA 6065",
    "addr:housenumber":"23",
    "addr:postcode":"6065",
    "addr:street":"Hoskins Rd",
    "iso:country":"AU",
    "sg:address":"17- 23 Hoskins Rd",
    "sg:city":"Landsdale",
    "sg:classifiers":[
        {
            "category":"Home & Garden",
            "subcategory":"Hardware",
            "type":"Retail Goods"
        }
    ],
    "sg:phone":"+61 8 9309 1303",
    "sg:postcode":"6065",
    "sg:province":"WA",
    "sg:tags":[
        "plumber",
        "supply"
    ],
    "wof:name":"Combined Metal Industries",
    "wof:placetype":"venue"
},
  "geometry": {"coordinates":[115.83833313,-31.8035697937],"type":"Point"}
}