{
  "type": "Feature",
  "properties": {
    "iso:country":"AU",
    "sg:address":"135 Nicholson St",
    "sg:city":"Abbotsford",
    "sg:classifiers":[
        {
            "category":"Fast Food",
            "type":"Food & Drink"
        }
    ],
    "sg:phone":"+61 3 9419 7459",
    "sg:postcode":"3067",
    "sg:province":"VIC",
    "sg:tags":[
        "away",
        "take"
    ],
    "wof:name":"Quick-Bite",
    "wof:placetype":"venue"
},
  "geometry": {"coordinates":[144.996536255,-37.805316925],"type":"Point"}
}