{
  "type": "Feature",
  "properties": {
    "addr:full":"U1 / 1 Steele St Winnellie NT 0820",
    "addr:housenumber":"1",
    "addr:postcode":"nt 0820",
    "addr:street":"U1 /;St",
    "iso:country":"AU",
    "sg:address":"U1 / 1 Steele St",
    "sg:city":"Winnellie",
    "sg:classifiers":[
        {
            "category":"Retail",
            "subcategory":"Auto Repair",
            "type":"Services"
        }
    ],
    "sg:phone":"+61 8 8947 0522",
    "sg:postcode":"0820",
    "sg:province":"NT",
    "sg:tags":[
        "electrical"
    ],
    "wof:name":"Chriss Automotive & Marine Electric",
    "wof:placetype":"venue"
},
  "geometry": {"coordinates":[130.86302185100001,-12.4296092987],"type":"Point"}
}