{
  "type": "Feature",
  "properties": {
    "addr:full":"7 Brown St Tennant Creek NT 0861",
    "addr:housenumber":"7",
    "addr:postcode":"nt 0861",
    "addr:street":"Brown St",
    "iso:country":"AU",
    "sg:address":"7 Brown St",
    "sg:city":"Tennant Creek",
    "sg:classifiers":[
        {
            "category":"Manufacturing",
            "subcategory":"Glass & Minerals",
            "type":"Manufacturing & Wholesale Goods"
        }
    ],
    "sg:phone":"+61 8 8962 2337",
    "sg:postcode":"0861",
    "sg:province":"NT",
    "sg:tags":[
        "exploration"
    ],
    "wof:name":"Arnhem Exploration Services",
    "wof:placetype":"venue"
},
  "geometry": {"coordinates":[134.18141199999999,-19.653204],"type":"Point"}
}