{
  "type": "Feature",
  "properties": {
    "addr:full":"Unit 6 49 Garden Drv Tullamarine VIC 3043",
    "addr:housenumber":"49",
    "addr:postcode":"3043",
    "addr:street":"Garden Drv",
    "iso:country":"AU",
    "sg:address":"Unit 6 49 Garden Drv",
    "sg:city":"Tullamarine",
    "sg:classifiers":[
        {
            "category":"Professional",
            "subcategory":"Business Services",
            "type":"Services"
        }
    ],
    "sg:phone":"+61 3 9335 1300",
    "sg:postcode":"3043",
    "sg:province":"VIC",
    "sg:tags":[
        "exporter"
    ],
    "wof:name":"Bemco (Aust) Pty Ltd",
    "wof:placetype":"venue"
},
  "geometry": {"coordinates":[144.87738037099999,-37.690536499],"type":"Point"}
}