{
  "type": "Feature",
  "properties": {
    "addr:full":"313 Middleborough Rd Box Hill VIC 3128",
    "addr:housenumber":"313",
    "addr:postcode":"3128",
    "addr:street":"Middleborough Rd",
    "iso:country":"AU",
    "sg:address":"313 Middleborough Rd",
    "sg:city":"Box Hill",
    "sg:classifiers":[
        {
            "category":"Manufacturing",
            "subcategory":"Chemicals & Compounds",
            "type":"Manufacturing & Wholesale Goods"
        }
    ],
    "sg:phone":"+61 1800 814 740",
    "sg:postcode":"3128",
    "sg:province":"VIC",
    "sg:tags":[
        "industrial"
    ],
    "wof:name":"Albright & Wilson (Australia) Limited",
    "wof:placetype":"venue"
},
  "geometry": {"coordinates":[145.136627197,-37.8292655945],"type":"Point"}
}