{
  "type": "Feature",
  "properties": {
    "iso:country":"AU",
    "sg:address":"377 Punt Rd",
    "sg:city":"Richmond",
    "sg:classifiers":[
        {
            "category":"Real Estate",
            "subcategory":"Real Estate Services",
            "type":"Services"
        }
    ],
    "sg:phone":"+61 3 9428 2842",
    "sg:postcode":"3121",
    "sg:province":"VIC",
    "sg:tags":[
        "consultant",
        "property"
    ],
    "wof:name":"Nicholas W Gilbert Pty Ltd",
    "wof:placetype":"venue"
},
  "geometry": {"coordinates":[144.99009704599999,-37.8172149658],"type":"Point"}
}