{
  "type": "Feature",
  "properties": {
    "addr:full":"Shp2/ 82 Condamine St Runcorn QLD 4113",
    "addr:postcode":"4113",
    "addr:street":"Condamine St",
    "iso:country":"AU",
    "sg:address":"Shp2/ 82 Condamine St",
    "sg:city":"Runcorn",
    "sg:classifiers":[
        {
            "category":"Fast Food",
            "type":"Food & Drink"
        }
    ],
    "sg:phone":"+61 7 3272 2966",
    "sg:postcode":"4113",
    "sg:province":"QLD",
    "sg:tags":[
        "away",
        "take"
    ],
    "wof:name":"Oriental Inn Chinese Take-Away",
    "wof:placetype":"venue"
},
  "geometry": {"coordinates":[153.06663513199999,-27.6100559235],"type":"Point"}
}