{
  "type": "Feature",
  "properties": {
    "iso:country":"AU",
    "sg:address":"Shop 201",
    "sg:city":"A Charlestown Sq Charlestown",
    "sg:classifiers":[
        {
            "category":"Insurance",
            "subcategory":"Health Insurance",
            "type":"Services"
        }
    ],
    "sg:phone":"+61 2 4942 2237",
    "sg:postcode":"2290",
    "sg:province":"NSW",
    "wof:name":"Hospitals Contribution Fund Of Australia Limited. The",
    "wof:placetype":"venue"
},
  "geometry": {"coordinates":[151.68634033199999,-32.9560890198],"type":"Point"}
}