{
  "type": "Feature",
  "properties": {
    "addr:full":"5 Ralph St Alexandria NSW 2015",
    "addr:housenumber":"5",
    "addr:postcode":"2015",
    "addr:street":"Ralph St",
    "iso:country":"AU",
    "sg:address":"5 Ralph St",
    "sg:city":"Alexandria",
    "sg:classifiers":[
        {
            "category":"Utilities",
            "subcategory":"Water",
            "type":"Services"
        }
    ],
    "sg:phone":"+61 2 9669 0263",
    "sg:postcode":"2015",
    "sg:province":"NSW",
    "sg:tags":[
        "equipment",
        "treatment"
    ],
    "wof:name":"Aqua Plus",
    "wof:placetype":"venue"
},
  "geometry": {"coordinates":[151.199783325,-33.9144325256],"type":"Point"}
}