{
  "type": "Feature",
  "properties": {
    "iso:country":"AU",
    "sg:address":"42 The Lakes Drv",
    "sg:city":"Glenmore Park",
    "sg:classifiers":[
        {
            "category":"Health Services",
            "subcategory":"Chiropractor",
            "type":"Services"
        }
    ],
    "sg:phone":"+61 2 4733 5588",
    "sg:postcode":"2745",
    "sg:province":"NSW",
    "wof:name":"Glenmore Park Chiropractic Centre",
    "wof:placetype":"venue"
},
  "geometry": {"coordinates":[150.68080139200001,-33.7851982117],"type":"Point"}
}