{
  "type": "Feature",
  "properties": {
    "iso:country":"AU",
    "sg:address":"Suite 26/ 58 Riverwalk Ave",
    "sg:city":"Robina",
    "sg:classifiers":[
        {
            "category":"Professional",
            "subcategory":"Engineering",
            "type":"Services"
        }
    ],
    "sg:phone":"+61 7 5562 5377",
    "sg:postcode":"4230",
    "sg:province":"QLD",
    "sg:tags":[
        "consulting",
        "engineer"
    ],
    "wof:name":"Bitzios Consulting",
    "wof:placetype":"venue"
},
  "geometry": {"coordinates":[153.381790161,-28.079662323],"type":"Point"}
}