{
  "type": "Feature",
  "properties": {
    "iso:country":"AU",
    "sg:address":"27 Auckland St",
    "sg:city":"Bega",
    "sg:classifiers":[
        {
            "category":"Education",
            "subcategory":"School",
            "type":"Public Place"
        }
    ],
    "sg:phone":"+61 2 6492 1280",
    "sg:postcode":"2550",
    "sg:province":"NSW",
    "sg:tags":[
        "state",
        "-",
        "nsw"
    ],
    "wof:name":"Bega Primary School",
    "wof:placetype":"venue"
},
  "geometry": {"coordinates":[149.699462891,-36.7650489807],"type":"Point"}
}