{
  "type": "Feature",
  "properties": {
    "addr:full":"89 Piper St Kyneton VIC 3444",
    "addr:housenumber":"89",
    "addr:postcode":"3444",
    "addr:street":"Piper St",
    "iso:country":"AU",
    "sg:address":"89 Piper St",
    "sg:city":"Kyneton",
    "sg:classifiers":[
        {
            "category":"Shopping",
            "subcategory":"Party Supplies",
            "type":"Retail Goods"
        }
    ],
    "sg:phone":"+61 3 5422 2311",
    "sg:postcode":"3444",
    "sg:province":"VIC",
    "sg:tags":[
        "toilet",
        "portable"
    ],
    "wof:name":"Kyneton Equipment & Party Hire",
    "wof:placetype":"venue"
},
  "geometry": {"coordinates":[144.446655273,-37.2439308167],"type":"Point"}
}