{
  "type": "Feature",
  "properties": {
    "iso:country":"AU",
    "sg:address":"9 Stanley Rd",
    "sg:city":"Devon Meadows",
    "sg:classifiers":[
        {
            "category":"Professional",
            "subcategory":"Business Services",
            "type":"Services"
        }
    ],
    "sg:phone":"+61 3 5998 2833",
    "sg:postcode":"3977",
    "sg:province":"VIC",
    "sg:tags":[
        "drafting"
    ],
    "wof:name":"Glenkeith Design&Associates Pty Ltd",
    "wof:placetype":"venue"
},
  "geometry": {"coordinates":[145.29185485799999,-38.1683998108],"type":"Point"}
}