{
  "type": "Feature",
  "properties": {
    "addr:full":"43 Beddi Rd Duncraig WA 6023",
    "addr:housenumber":"43",
    "addr:postcode":"6023",
    "addr:street":"Beddi Rd",
    "iso:country":"AU",
    "sg:address":"43 Beddi Rd",
    "sg:city":"Duncraig",
    "sg:classifiers":[
        {
            "category":"Social Services",
            "subcategory":"Child Care",
            "type":"Services"
        }
    ],
    "sg:phone":"+61 8 9246 2991",
    "sg:postcode":"6023",
    "sg:province":"WA",
    "wof:name":"Duncraig Child Care Centre",
    "wof:placetype":"venue"
},
  "geometry": {"coordinates":[115.765869141,-31.837518692],"type":"Point"}
}