{
  "type": "Feature",
  "properties": {
    "addr:full":"141 Bulla Rd Bulla VIC 3428",
    "addr:housenumber":"141",
    "addr:postcode":"3428",
    "addr:street":"Bulla Rd",
    "iso:country":"AU",
    "sg:address":"141 Bulla Rd",
    "sg:city":"Bulla",
    "sg:classifiers":[
        {
            "category":"Building & Trades",
            "subcategory":"Equipment Rental",
            "type":"Services"
        }
    ],
    "sg:phone":"+61 418 390 235",
    "sg:postcode":"3428",
    "sg:province":"VIC",
    "sg:tags":[
        "demolition",
        "contractor"
    ],
    "wof:name":"Essendon Demolition",
    "wof:placetype":"venue"
},
  "geometry": {"coordinates":[144.801345825,-37.6341209412],"type":"Point"}
}