{
  "type": "Feature",
  "properties": {
    "addr:full":"122 Beatrice St Balgowlah Heights NSW 2093",
    "addr:housenumber":"122",
    "addr:postcode":"2093",
    "addr:street":"Beatrice St",
    "iso:country":"AU",
    "sg:address":"122 Beatrice St",
    "sg:city":"Balgowlah Heights",
    "sg:classifiers":[
        {
            "category":"Deli",
            "type":"Food & Drink"
        }
    ],
    "sg:phone":"+61 2 9949 3969",
    "sg:postcode":"2093",
    "sg:province":"NSW",
    "sg:tags":[
        "delicatessen"
    ],
    "wof:name":"Balgowlah Heights Deli",
    "wof:placetype":"venue"
},
  "geometry": {"coordinates":[151.25746154800001,-33.8010864258],"type":"Point"}
}