{
  "type": "Feature",
  "properties": {
    "addr:full":"Shop 3 Alice St Merimbula NSW 2548",
    "addr:housenumber":"shop 3",
    "addr:postcode":"2548",
    "addr:street":"Alice St",
    "iso:country":"AU",
    "sg:address":"Shop 3 Alice St",
    "sg:city":"Merimbula",
    "sg:classifiers":[
        {
            "category":"Food & Beverages",
            "subcategory":"Meat & Fish",
            "type":"Retail Goods"
        }
    ],
    "sg:phone":"+61 2 6495 3844",
    "sg:postcode":"2548",
    "sg:province":"NSW",
    "sg:tags":[
        "seafood"
    ],
    "wof:name":"Surfside Seafoods",
    "wof:placetype":"venue"
},
  "geometry": {"coordinates":[149.9112854,-36.8882369995],"type":"Point"}
}