{
  "type": "Feature",
  "properties": {
    "addr:full":"16 Okines Rd Dodges Ferry TAS 7173",
    "addr:housenumber":"16",
    "addr:postcode":"7173",
    "addr:street":"Okines Rd",
    "iso:country":"AU",
    "sg:address":"16 Okines Rd",
    "sg:city":"Dodges Ferry",
    "sg:classifiers":[
        {
            "category":"Personal",
            "subcategory":"Beauty Salon",
            "type":"Services"
        }
    ],
    "sg:phone":"+61 3 6265 9595",
    "sg:postcode":"7173",
    "sg:province":"TAS",
    "sg:tags":[
        "hairdresser"
    ],
    "wof:name":"Hair On Okines",
    "wof:placetype":"venue"
},
  "geometry": {"coordinates":[147.63406372099999,-42.8477516174],"type":"Point"}
}