{
  "type": "Feature",
  "properties": {
    "iso:country":"AU",
    "sg:address":"34 Amax Ave",
    "sg:city":"Girraween",
    "sg:classifiers":[
        {
            "category":"Wholesale",
            "subcategory":"Seafood",
            "type":"Manufacturing & Wholesale Goods"
        }
    ],
    "sg:phone":"+61 2 9636 5455",
    "sg:postcode":"2145",
    "sg:province":"NSW",
    "sg:tags":[
        "fish"
    ],
    "wof:name":"Meridian Seafoods Pty Ltd",
    "wof:placetype":"venue"
},
  "geometry": {"coordinates":[150.93792724599999,-33.8056526184],"type":"Point"}
}