{
  "type": "Feature",
  "properties": {
    "iso:country":"AU",
    "sg:address":"65 Oramzi Rd",
    "sg:city":"Girraween",
    "sg:classifiers":[
        {
            "category":"Retail",
            "subcategory":"Storage",
            "type":"Services"
        }
    ],
    "sg:phone":"+61 2 9863 4817",
    "sg:postcode":"2145",
    "sg:province":"NSW",
    "sg:tags":[
        "removal",
        "furniture"
    ],
    "wof:name":"Norwest Furniture Removals & Storage",
    "wof:placetype":"venue"
},
  "geometry": {"coordinates":[150.94851684599999,-33.795211792],"type":"Point"}
}