{
  "type": "Feature",
  "properties": {
    "addr:full":"3 Perrett St Brunswick West VIC 3055",
    "addr:housenumber":"3",
    "addr:postcode":"3055",
    "addr:street":"Perrett St",
    "iso:country":"AU",
    "sg:address":"3 Perrett St",
    "sg:city":"Brunswick West",
    "sg:classifiers":[
        {
            "category":"Home & Garden",
            "subcategory":"Carpets & Floor Coverings",
            "type":"Retail Goods"
        }
    ],
    "sg:phone":"+61 403 199 961",
    "sg:postcode":"3055",
    "sg:province":"VIC",
    "sg:tags":[
        "tile",
        "wall"
    ],
    "wof:name":"Bellaire Tiling",
    "wof:placetype":"venue"
},
  "geometry": {"coordinates":[144.95123290999999,-37.7542037964],"type":"Point"}
}