{
  "type": "Feature",
  "properties": {
    "addr:full":"14 Rio St Bayswater WA 6053",
    "addr:housenumber":"14",
    "addr:postcode":"6053",
    "addr:street":"Rio St",
    "iso:country":"AU",
    "sg:address":"14 Rio St",
    "sg:city":"Bayswater",
    "sg:classifiers":[
        {
            "category":"Professional",
            "type":"Services"
        }
    ],
    "sg:phone":"+61 8 9371 0077",
    "sg:postcode":"6053",
    "sg:province":"WA",
    "sg:tags":[
        "shop",
        "fitting"
    ],
    "wof:name":"Ascot Sign Company",
    "wof:placetype":"venue"
},
  "geometry": {"coordinates":[115.92208862299999,-31.9109783173],"type":"Point"}
}