{
  "type": "Feature",
  "properties": {
    "addr:full":"U 5/ 301 Hill Borought Rd Warners Bay NSW 2282",
    "addr:housenumber":"/ 301",
    "addr:postcode":"2282",
    "addr:street":"Hill Borought Rd",
    "iso:country":"AU",
    "sg:address":"U 5/ 301 Hill Borought Rd",
    "sg:city":"Warners Bay",
    "sg:classifiers":[
        {
            "category":"Food & Beverages",
            "subcategory":"Liquor & Beverages",
            "type":"Retail Goods"
        }
    ],
    "sg:phone":"+61 418 609 279",
    "sg:postcode":"2282",
    "sg:province":"NSW",
    "sg:tags":[
        "merchant",
        "spirit",
        "wine"
    ],
    "wof:name":"New Meat Pty Ltd",
    "wof:placetype":"venue"
},
  "geometry": {"coordinates":[151.657546997,-32.9650726318],"type":"Point"}
}