{
  "type": "Feature",
  "properties": {
    "iso:country":"AU",
    "sg:address":"4 Sickles Drv",
    "sg:city":"Grasmere",
    "sg:classifiers":[
        {
            "category":"Professional",
            "type":"Services"
        }
    ],
    "sg:phone":"+61 2 4655 2233",
    "sg:postcode":"2570",
    "sg:province":"NSW",
    "sg:tags":[
        "overlocking",
        "rug",
        "carpet"
    ],
    "wof:name":"D.R. Sidman & Co.",
    "wof:placetype":"venue"
},
  "geometry": {"coordinates":[150.663162231,-34.0530548096],"type":"Point"}
}