{
  "type": "Feature",
  "properties": {
    "addr:full":"37 Hall St Bondi Beach NSW 2026",
    "addr:housenumber":"37",
    "addr:postcode":"2026",
    "addr:street":"Hall St",
    "iso:country":"AU",
    "sg:address":"37 Hall St",
    "sg:city":"Bondi Beach",
    "sg:classifiers":[
        {
            "category":"Internet Cafe",
            "subcategory":"None",
            "type":"Food & Drink"
        }
    ],
    "sg:phone":"+61 2 9365 4811",
    "sg:postcode":"2026",
    "sg:province":"NSW",
    "wof:name":"Global Gossip Australia Pty Ltd",
    "wof:placetype":"venue"
},
  "geometry": {"coordinates":[151.27279663100001,-33.8903198242],"type":"Point"}
}