{
  "type": "Feature",
  "properties": {
    "addr:full":"330 Anzac Ave Toowoomba QLD 4350",
    "addr:housenumber":"330",
    "addr:postcode":"4350",
    "addr:street":"Anzac Ave",
    "iso:country":"AU",
    "sg:address":"330 Anzac Ave",
    "sg:city":"Toowoomba",
    "sg:classifiers":[
        {
            "category":"Building & Trades",
            "subcategory":"Construction",
            "type":"Services"
        }
    ],
    "sg:phone":"+61 7 4630 2700",
    "sg:postcode":"4350",
    "sg:province":"QLD",
    "sg:tags":[
        "contractor"
    ],
    "wof:name":"Elmes Construction Group Pty Ltd",
    "wof:placetype":"venue"
},
  "geometry": {"coordinates":[151.91772499999999,-27.585487],"type":"Point"}
}