{
  "type": "Feature",
  "properties": {
    "iso:country":"AU",
    "sg:address":"Beischer St",
    "sg:city":"Bendigo",
    "sg:classifiers":[
        {
            "category":"Retail",
            "subcategory":"Auto Repair",
            "type":"Services"
        }
    ],
    "sg:phone":"+61 3 5443 3812",
    "sg:postcode":"3550",
    "sg:province":"VIC",
    "sg:tags":[
        "recapping",
        "repairing",
        "retreading",
        "tyre"
    ],
    "wof:name":"Bandag",
    "wof:placetype":"venue"
},
  "geometry": {"coordinates":[144.308303833,-36.7589836121],"type":"Point"}
}