{
  "type": "Feature",
  "properties": {
    "addr:full":"4 Howe St Airport West VIC 3042",
    "addr:housenumber":"4",
    "addr:postcode":"3042",
    "addr:street":"Howe St",
    "iso:country":"AU",
    "sg:address":"4 Howe St",
    "sg:city":"Airport West",
    "sg:classifiers":[
        {
            "category":"Manufacturing",
            "subcategory":"Rubber & Plastics",
            "type":"Manufacturing & Wholesale Goods"
        }
    ],
    "sg:phone":"+61 3 9338 2344",
    "sg:postcode":"3042",
    "sg:province":"VIC",
    "sg:tags":[
        "wholesaler",
        "product",
        "mfrs"
    ],
    "wof:name":"A S Industrial Supplies Pty Ltd",
    "wof:placetype":"venue"
},
  "geometry": {"coordinates":[144.88984680199999,-37.7155990601],"type":"Point"}
}