{
  "type": "Feature",
  "properties": {
    "addr:full":"49 Bridge Rd Nowra NSW 2541",
    "addr:housenumber":"49",
    "addr:postcode":"2541",
    "addr:street":"Bridge Rd",
    "iso:country":"AU",
    "sg:address":"49 Bridge Rd",
    "sg:city":"Nowra",
    "sg:classifiers":[
        {
            "category":"Real Estate",
            "subcategory":"Architect",
            "type":"Services"
        }
    ],
    "sg:phone":"+61 2 4421 6822",
    "sg:postcode":"2541",
    "sg:province":"NSW",
    "wof:name":"Jones Mark",
    "wof:placetype":"venue"
},
  "geometry": {"coordinates":[150.601074219,-34.8692932129],"type":"Point"}
}