{
  "type": "Feature",
  "properties": {
    "iso:country":"AU",
    "sg:address":"339 King William St",
    "sg:city":"Adelaide",
    "sg:classifiers":[
        {
            "category":"Insurance",
            "subcategory":"Health Insurance",
            "type":"Services"
        }
    ],
    "sg:phone":"+61 8 8112 7000",
    "sg:postcode":"5000",
    "sg:province":"SA",
    "wof:name":"Police Health Fund",
    "wof:placetype":"venue"
},
  "geometry": {"coordinates":[138.599975586,-34.9322929382],"type":"Point"}
}