{
  "type": "Feature",
  "properties": {
    "addr:full":"42 Thomasina St Bentleigh East VIC 3165",
    "addr:housenumber":"42",
    "addr:postcode":"3165",
    "addr:street":"Thomasina St",
    "iso:country":"AU",
    "sg:address":"42 Thomasina St",
    "sg:city":"Bentleigh East",
    "sg:classifiers":[
        {
            "category":"Personal",
            "subcategory":"Massage",
            "type":"Services"
        }
    ],
    "sg:phone":"+61 3 9563 8201",
    "sg:postcode":"3165",
    "sg:province":"VIC",
    "sg:tags":[
        "therapy"
    ],
    "wof:name":"Hindell Robert",
    "wof:placetype":"venue"
},
  "geometry": {"coordinates":[145.060424805,-37.9123344421],"type":"Point"}
}