{
  "type": "Feature",
  "properties": {
    "iso:country":"AU",
    "sg:address":"25 Fowler Rd",
    "sg:city":"Dandenong South",
    "sg:classifiers":[
        {
            "category":"Retail",
            "subcategory":"Auto Repair",
            "type":"Services"
        }
    ],
    "sg:phone":"+61 3 9791 2522",
    "sg:postcode":"3175",
    "sg:province":"VIC",
    "sg:tags":[
        "bus",
        "truck"
    ],
    "wof:name":"Transport Fabrications",
    "wof:placetype":"venue"
},
  "geometry": {"coordinates":[145.23228454599999,-38.0057182312],"type":"Point"}
}