{
  "type": "Feature",
  "properties": {
    "addr:full":"791 Welshpool Rd Wattle Grove WA 6107",
    "addr:housenumber":"791",
    "addr:postcode":"6107",
    "addr:street":"Welshpool Rd",
    "iso:country":"AU",
    "sg:address":"791 Welshpool Rd",
    "sg:city":"Wattle Grove",
    "sg:classifiers":[
        {
            "category":"Retail",
            "subcategory":"Veterinary Services",
            "type":"Services"
        }
    ],
    "sg:phone":"+61 8 9453 6655",
    "sg:postcode":"6107",
    "sg:province":"WA",
    "sg:tags":[
        "surgeon"
    ],
    "wof:name":"Avian Veterinarian",
    "wof:placetype":"venue"
},
  "geometry": {"coordinates":[115.970542908,-32.0025939941],"type":"Point"}
}