{
  "type": "Feature",
  "properties": {
    "addr:full":"3 Elizabeth St Wyoming NSW 2250",
    "addr:housenumber":"3",
    "addr:postcode":"2250",
    "addr:street":"Elizabeth St",
    "iso:country":"AU",
    "sg:address":"3 Elizabeth St",
    "sg:city":"Wyoming",
    "sg:classifiers":[
        {
            "category":"Building & Trades",
            "subcategory":"Construction",
            "type":"Services"
        }
    ],
    "sg:phone":"+61 2 4328 2924",
    "sg:postcode":"2250",
    "sg:province":"NSW",
    "sg:tags":[
        "contractor"
    ],
    "wof:name":"Consullink",
    "wof:placetype":"venue"
},
  "geometry": {"coordinates":[151.359863281,-33.4031829834],"type":"Point"}
}