{
  "type": "Feature",
  "properties": {
    "iso:country":"AU",
    "sg:address":"C3-Store Main Rd",
    "sg:city":"Cudlee Creek",
    "sg:classifiers":[
        {
            "category":"Building & Trades",
            "subcategory":"Construction",
            "type":"Services"
        }
    ],
    "sg:phone":"+61 8 8389 2238",
    "sg:postcode":"5232",
    "sg:province":"SA",
    "sg:tags":[
        "equipment",
        "system",
        "automation"
    ],
    "wof:name":"Advanced Lab Automation P/L",
    "wof:placetype":"venue"
},
  "geometry": {"coordinates":[138.81478881800001,-34.8403091431],"type":"Point"}
}