{
  "type": "Feature",
  "properties": {
    "iso:country":"AU",
    "sg:address":"29 William St",
    "sg:city":"Alexandria",
    "sg:classifiers":[
        {
            "category":"Retail",
            "subcategory":"Auto Repair",
            "type":"Services"
        }
    ],
    "sg:phone":"+61 2 9699 3120",
    "sg:postcode":"2015",
    "sg:province":"NSW",
    "sg:tags":[
        "repairer",
        "motor",
        "engineer"
    ],
    "wof:name":"Raco Motor Repairs",
    "wof:placetype":"venue"
},
  "geometry": {"coordinates":[151.19859314000001,-33.9121208191],"type":"Point"}
}