{
  "type": "Feature",
  "properties": {
    "addr:full":"26 Walters Drv Osborne Park WA 6017",
    "addr:housenumber":"26",
    "addr:postcode":"6017",
    "addr:street":"Walters Drv",
    "iso:country":"AU",
    "sg:address":"26 Walters Drv",
    "sg:city":"Osborne Park",
    "sg:classifiers":[
        {
            "category":"Industrial Area",
            "type":"Public Place"
        }
    ],
    "sg:phone":"+61 1300 656 636",
    "sg:postcode":"6017",
    "sg:province":"WA",
    "sg:tags":[
        "protective",
        "clothing"
    ],
    "wof:name":"RS Components Pty Limited",
    "wof:placetype":"venue"
},
  "geometry": {"coordinates":[115.808776855,-31.9094219208],"type":"Point"}
}