{
  "type": "Feature",
  "properties": {
    "addr:full":"14 Surfside Drv Port Kembla NSW 2505",
    "addr:housenumber":"14",
    "addr:postcode":"2505",
    "addr:street":"Surfside Drv",
    "iso:country":"AU",
    "sg:address":"14 Surfside Drv",
    "sg:city":"Port Kembla",
    "sg:classifiers":[
        {
            "category":"Health Services",
            "subcategory":"Health Practitioner",
            "type":"Services"
        }
    ],
    "sg:phone":"+61 2 4274 2250",
    "sg:postcode":"2505",
    "sg:province":"NSW",
    "sg:tags":[
        "naturopath"
    ],
    "sg:website":"http://www.atms.com.au",
    "wof:name":"Alison Princic - Naturopath",
    "wof:placetype":"venue"
},
  "geometry": {"coordinates":[150.905396,-34.490444],"type":"Point"}
}