{
  "type": "Feature",
  "properties": {
    "iso:country":"AU",
    "sg:address":"23 Fifth Ave",
    "sg:city":"Blacktown",
    "sg:classifiers":[
        {
            "category":"Building & Trades",
            "subcategory":"Electrical",
            "type":"Services"
        }
    ],
    "sg:phone":"+61 2 9622 0218",
    "sg:postcode":"2148",
    "sg:province":"NSW",
    "sg:tags":[
        "wholesaler",
        "mfrs",
        "appliance"
    ],
    "wof:name":"Xing Ye Enterprises Pty Ltd",
    "wof:placetype":"venue"
},
  "geometry": {"coordinates":[150.91142273,-33.763004303],"type":"Point"}
}