{
  "type": "Feature",
  "properties": {
    "addr:full":"490 The Pocket Rd Billinudgel NSW 2483",
    "addr:housenumber":"490",
    "addr:postcode":"2483",
    "addr:street":"Rd",
    "iso:country":"AU",
    "sg:address":"490 The Pocket Rd",
    "sg:city":"Billinudgel",
    "sg:classifiers":[
        {
            "category":"Farming",
            "subcategory":"Nursery",
            "type":"Manufacturing & Wholesale Goods"
        }
    ],
    "sg:phone":"+61 2 6684 5203",
    "sg:postcode":"2483",
    "sg:province":"NSW",
    "wof:name":"Sayers Strelitzia Nursery",
    "wof:placetype":"venue"
},
  "geometry": {"coordinates":[153.48158264200001,-28.5053539276],"type":"Point"}
}