{
  "type": "Feature",
  "properties": {
    "addr:full":"Suite 4/ 77 Albert Ave Chatswood NSW 2067",
    "addr:housenumber":"77",
    "addr:postcode":"2067",
    "addr:street":"Albert Ave",
    "iso:country":"AU",
    "sg:address":"Suite 4/ 77 Albert Ave",
    "sg:city":"Chatswood",
    "sg:classifiers":[
        {
            "category":"Education",
            "subcategory":"Special Training",
            "type":"Public Place"
        }
    ],
    "sg:phone":"+61 2 9419 8866",
    "sg:postcode":"2067",
    "sg:province":"NSW",
    "sg:tags":[
        "development"
    ],
    "wof:name":"Corpfit Training Solutions Pty Ltd",
    "wof:placetype":"venue"
},
  "geometry": {"coordinates":[151.18698120100001,-33.7966537476],"type":"Point"}
}