{
  "type": "Feature",
  "properties": {
    "addr:full":"Level 22 AAP Centre 259 George St Sydney NSW 2000",
    "addr:housenumber":"259",
    "addr:postcode":"2000",
    "addr:street":"George St",
    "iso:country":"AU",
    "sg:address":"Level 22 AAP Centre 259 George St",
    "sg:city":"Sydney",
    "sg:classifiers":[
        {
            "category":"Government",
            "subcategory":"Court House",
            "type":"Public Place"
        }
    ],
    "sg:phone":"+61 2 9966 7908",
    "sg:postcode":"2000",
    "sg:province":"NSW",
    "sg:tags":[
        "personal",
        "marriage",
        "family",
        "counselling"
    ],
    "wof:name":"Dietrich Jennifer",
    "wof:placetype":"venue"
},
  "geometry": {"coordinates":[151.207305908,-33.8637084961],"type":"Point"}
}