{
  "type": "Feature",
  "properties": {
    "addr:full":"84 Eclipse St Springsure QLD 4722",
    "addr:housenumber":"84",
    "addr:postcode":"4722",
    "addr:street":"Eclipse St",
    "iso:country":"AU",
    "sg:address":"84 Eclipse St",
    "sg:city":"Springsure",
    "sg:classifiers":[
        {
            "category":"Fast Food",
            "type":"Food & Drink"
        }
    ],
    "sg:phone":"+61 7 4984 1555",
    "sg:postcode":"4722",
    "sg:province":"QLD",
    "sg:tags":[
        "away",
        "take"
    ],
    "wof:name":"Springsure Convenience & Takeaway",
    "wof:placetype":"venue"
},
  "geometry": {"coordinates":[148.08897400000001,-24.113344],"type":"Point"}
}