{
  "type": "Feature",
  "properties": {
    "iso:country":"AU",
    "sg:address":"39 Clements Ave",
    "sg:city":"Bundoora",
    "sg:classifiers":[
        {
            "category":"Sports & Exercise",
            "subcategory":"Sports Center",
            "type":"Entertainment"
        }
    ],
    "sg:phone":"+61 3 9467 2422",
    "sg:postcode":"3083",
    "sg:province":"VIC",
    "sg:tags":[
        "ground"
    ],
    "wof:name":"Action Indoor Sports Stadiums",
    "wof:placetype":"venue"
},
  "geometry": {"coordinates":[145.07359314000001,-37.702495575],"type":"Point"}
}