{
  "type": "Feature",
  "properties": {
    "addr:full":"Unit 4, 275 Marmion St Melville WA 6156",
    "addr:housenumber":"275",
    "addr:postcode":"6156",
    "addr:street":"Marmion St",
    "iso:country":"AU",
    "sg:address":"Unit 4, 275 Marmion St",
    "sg:city":"Melville",
    "sg:classifiers":[
        {
            "category":"Professional",
            "subcategory":"Employment Agencies",
            "type":"Services"
        }
    ],
    "sg:phone":"+61 8 9317 3155",
    "sg:postcode":"6156",
    "sg:province":"WA",
    "wof:name":"South Metropolitan Personnel Inc",
    "wof:placetype":"venue"
},
  "geometry": {"coordinates":[115.794456,-32.046886],"type":"Point"}
}