{
  "type": "Feature",
  "properties": {
    "addr:full":"Vimy House Private Hospital, 5 Sudley Ave Kew VIC 3101",
    "addr:housenumber":"5",
    "addr:postcode":"3101",
    "addr:street":"Sudley Ave",
    "iso:country":"AU",
    "sg:address":"Vimy House Private Hospital, 5 Sudley Ave",
    "sg:city":"Kew",
    "sg:classifiers":[
        {
            "category":"Health Services",
            "subcategory":"Dentist",
            "type":"Services"
        }
    ],
    "sg:phone":"+61 3 9654 3799",
    "sg:postcode":"3101",
    "sg:province":"VIC",
    "wof:name":"Dimitroulis George Dr",
    "wof:placetype":"venue"
},
  "geometry": {"coordinates":[145.02403259299999,-37.8066749573],"type":"Point"}
}