{
  "type": "Feature",
  "properties": {
    "addr:full":"PO Box 183 Carina QLD 4152",
    "addr:postcode":"4152",
    "iso:country":"AU",
    "sg:address":"PO Box 183",
    "sg:city":"Carina",
    "sg:classifiers":[
        {
            "category":"Education",
            "subcategory":"Special Training",
            "type":"Public Place"
        }
    ],
    "sg:phone":"+61 7 3343 3808",
    "sg:postcode":"4152",
    "sg:province":"QLD",
    "sg:tags":[
        "development"
    ],
    "wof:name":"Life Couching Australia",
    "wof:placetype":"venue"
},
  "geometry": {"coordinates":[153.100006103,-27.4898204803],"type":"Point"}
}