{
  "type": "Feature",
  "properties": {
    "addr:full":"171 Arden St North Melbourne VIC 3051",
    "addr:housenumber":"171",
    "addr:postcode":"3051",
    "addr:street":"Arden St",
    "iso:country":"AU",
    "sg:address":"171 Arden St",
    "sg:city":"North Melbourne",
    "sg:classifiers":[
        {
            "category":"Freight",
            "type":"Transportation"
        }
    ],
    "sg:phone":"+61 3 9329 2277",
    "sg:postcode":"3051",
    "sg:province":"VIC",
    "sg:tags":[
        "car",
        "carrier",
        "transporting"
    ],
    "wof:name":"Ace Car Freighters",
    "wof:placetype":"venue"
},
  "geometry": {"coordinates":[144.94309997600001,-37.8003005981],"type":"Point"}
}