{
  "type": "Feature",
  "properties": {
    "addr:full":"58 Clovelly Rd Randwick NSW 2031",
    "addr:housenumber":"58",
    "addr:postcode":"2031",
    "addr:street":"Clovelly Rd",
    "iso:country":"AU",
    "sg:address":"58 Clovelly Rd",
    "sg:city":"Randwick",
    "sg:classifiers":[
        {
            "category":"Food & Beverages",
            "subcategory":"Specialty",
            "type":"Retail Goods"
        }
    ],
    "sg:phone":"+61 2 9314 5194",
    "sg:postcode":"2031",
    "sg:province":"NSW",
    "sg:tags":[
        "product",
        "health"
    ],
    "wof:name":"Freshwater & Cottage",
    "wof:placetype":"venue"
},
  "geometry": {"coordinates":[151.25013732900001,-33.9099082947],"type":"Point"}
}