{
  "type": "Feature",
  "properties": {
    "addr:full":"41 Bavarde Ave Batemans Bay NSW 2536",
    "addr:housenumber":"41",
    "addr:postcode":"2536",
    "addr:street":"Bavarde Ave",
    "iso:country":"AU",
    "sg:address":"41 Bavarde Ave",
    "sg:city":"Batemans Bay",
    "sg:classifiers":[
        {
            "category":"Utilities",
            "subcategory":"Electric",
            "type":"Services"
        }
    ],
    "sg:phone":"+61 414 289 898",
    "sg:postcode":"2536",
    "sg:province":"NSW",
    "sg:tags":[
        "electrical",
        "contractor"
    ],
    "wof:name":"Stocks Electrical",
    "wof:placetype":"venue"
},
  "geometry": {"coordinates":[150.18275451700001,-35.7169685364],"type":"Point"}
}