{
  "type": "Feature",
  "properties": {
    "iso:country":"AU",
    "sg:address":"Unit 5 10 O'Connor Way",
    "sg:city":"Wangara",
    "sg:classifiers":[
        {
            "category":"Home & Garden",
            "subcategory":"Garden Supply",
            "type":"Retail Goods"
        }
    ],
    "sg:phone":"+61 8 9309 5516",
    "sg:postcode":"6065",
    "sg:province":"WA",
    "sg:tags":[
        "equipment"
    ],
    "wof:name":"Sana Pty Ltd",
    "wof:placetype":"venue"
},
  "geometry": {"coordinates":[115.813316345,-31.7859249115],"type":"Point"}
}