{
  "type": "Feature",
  "properties": {
    "addr:full":"749 Anzac Pde Maroubra Junction NSW 2035",
    "addr:housenumber":"749",
    "addr:postcode":"2035",
    "addr:street":"Anzac Pde",
    "iso:country":"AU",
    "sg:address":"749 Anzac Pde",
    "sg:city":"Maroubra Junction",
    "sg:classifiers":[
        {
            "category":"Banks & Credit Unions",
            "subcategory":"Bank",
            "type":"Services"
        }
    ],
    "sg:phone":"+61 2 9314 1833",
    "sg:postcode":"2035",
    "sg:province":"NSW",
    "wof:name":"ANZ",
    "wof:placetype":"venue"
},
  "geometry": {"coordinates":[151.238845825,-33.9409370422],"type":"Point"}
}