{
  "type": "Feature",
  "properties": {
    "iso:country":"AU",
    "sg:address":"40 Bluff Rd",
    "sg:city":"Black Rock",
    "sg:classifiers":[
        {
            "category":"Communications",
            "subcategory":"Film & Video Production",
            "type":"Services"
        }
    ],
    "sg:phone":"+61 3 9589 1176",
    "sg:postcode":"3193",
    "sg:province":"VIC",
    "sg:tags":[
        "dvd",
        "library"
    ],
    "wof:name":"Video Ezy",
    "wof:placetype":"venue"
},
  "geometry": {"coordinates":[145.01661682100001,-37.9739875793],"type":"Point"}
}