{
  "type": "Feature",
  "properties": {
    "addr:full":"19 Lakeview St Mariginiup WA 6065",
    "addr:housenumber":"19",
    "addr:postcode":"6065",
    "addr:street":"Lakeview St",
    "iso:country":"AU",
    "sg:address":"19 Lakeview St",
    "sg:city":"Mariginiup",
    "sg:classifiers":[
        {
            "category":"Building & Trades",
            "subcategory":"Construction",
            "type":"Services"
        }
    ],
    "sg:phone":"+61 8 9306 5205",
    "sg:postcode":"6065",
    "sg:province":"WA",
    "sg:tags":[
        "earth",
        "excavating",
        "moving",
        "contractor"
    ],
    "wof:name":"Prunster R M & B M",
    "wof:placetype":"venue"
},
  "geometry": {"coordinates":[115.83450317400001,-31.7229614258],"type":"Point"}
}