{
  "type": "Feature",
  "properties": {
    "addr:full":"Anzac Pde Kensington NSW 2033",
    "addr:postcode":"2033",
    "addr:street":"Anzac",
    "iso:country":"AU",
    "sg:address":"Anzac Pde",
    "sg:city":"Kensington",
    "sg:classifiers":[
        {
            "category":"Health Services",
            "subcategory":"Optometrist",
            "type":"Services"
        }
    ],
    "sg:phone":"+61 2 9385 4627",
    "sg:postcode":"2033",
    "sg:province":"NSW",
    "wof:name":"University Of NSW School Of Optometry",
    "wof:placetype":"venue"
},
  "geometry": {"coordinates":[151.22387699999999,-33.91243],"type":"Point"}
}