{
  "type": "Feature",
  "properties": {
    "addr:full":"Shop 4,The Slater Building Cnr Church & Burelli Sts Wollongong NSW 2500",
    "addr:housenumber":"shop 4",
    "addr:postcode":"2500",
    "addr:street":"The;Cnr",
    "iso:country":"AU",
    "sg:address":"Shop 4,The Slater Building Cnr Church & Burelli Sts",
    "sg:city":"Wollongong",
    "sg:classifiers":[
        {
            "category":"Travel",
            "subcategory":"Travel Agent",
            "type":"Entertainment"
        }
    ],
    "sg:phone":"+61 2 4227 2991",
    "sg:postcode":"2500",
    "sg:province":"NSW",
    "sg:tags":[
        "consultant"
    ],
    "wof:name":"Jetset Travel",
    "wof:placetype":"venue"
},
  "geometry": {"coordinates":[150.890289,-34.426338],"type":"Point"}
}