{
  "type": "Feature",
  "properties": {
    "iso:country":"AU",
    "sg:address":"Shop 62 Colonnades Shopping Centre Beach Rd",
    "sg:city":"Noarlunga Centre",
    "sg:classifiers":[
        {
            "category":"Personal",
            "type":"Services"
        }
    ],
    "sg:phone":"+61 8 8384 3953",
    "sg:postcode":"5168",
    "sg:province":"SA",
    "sg:tags":[
        "gift"
    ],
    "wof:name":"Colonnades Florist",
    "wof:placetype":"venue"
},
  "geometry": {"coordinates":[138.49281310999999,-35.1405487061],"type":"Point"}
}