{
  "type": "Feature",
  "properties": {
    "iso:country":"AU",
    "sg:address":"557 Sandfly Rd",
    "sg:city":"Sandfly",
    "sg:classifiers":[
        {
            "category":"Farming",
            "subcategory":"Fish & Marine Products",
            "type":"Manufacturing & Wholesale Goods"
        }
    ],
    "sg:phone":"+61 418 122 013",
    "sg:postcode":"7150",
    "sg:province":"TAS",
    "sg:tags":[
        "asphalt",
        "supply"
    ],
    "wof:name":"O'Donnell Contracting",
    "wof:placetype":"venue"
},
  "geometry": {"coordinates":[147.21711730999999,-42.993057251],"type":"Point"}
}