{
  "type": "Feature",
  "properties": {
    "addr:full":"31 Shedden St Pascoe Vale VIC 3044",
    "addr:housenumber":"31",
    "addr:postcode":"3044",
    "addr:street":"Shedden St",
    "iso:country":"AU",
    "sg:address":"31 Shedden St",
    "sg:city":"Pascoe Vale",
    "sg:classifiers":[
        {
            "category":"Health Services",
            "subcategory":"Dentist",
            "type":"Services"
        }
    ],
    "sg:phone":"+61 407 326 674",
    "sg:postcode":"3044",
    "sg:province":"VIC",
    "sg:tags":[
        "dental",
        "prosthetist"
    ],
    "wof:name":"Complete Denture Care",
    "wof:placetype":"venue"
},
  "geometry": {"coordinates":[144.946212769,-37.7332344055],"type":"Point"}
}