{
  "type": "Feature",
  "properties": {
    "addr:full":"Isabella St Malvern VIC 3144",
    "addr:postcode":"3144",
    "addr:street":"Isabella St",
    "iso:country":"AU",
    "sg:address":"Isabella St",
    "sg:city":"Malvern",
    "sg:classifiers":[
        {
            "category":"Health Services",
            "subcategory":"Doctor",
            "type":"Services"
        }
    ],
    "sg:phone":"+61 3 9509 0427",
    "sg:postcode":"3144",
    "sg:province":"VIC",
    "sg:tags":[
        "medical",
        "practitioner"
    ],
    "wof:name":"Fagan E.T.",
    "wof:placetype":"venue"
},
  "geometry": {"coordinates":[145.03277587900001,-37.8609466553],"type":"Point"}
}