{
  "type": "Feature",
  "properties": {
    "iso:country":"AU",
    "sg:address":"Shop 2/ 75 Fryar Rd",
    "sg:city":"Eagleby",
    "sg:classifiers":[
        {
            "category":"Personal",
            "subcategory":"Beauty Salon",
            "type":"Services"
        }
    ],
    "sg:phone":"+61 7 3807 5334",
    "sg:postcode":"4207",
    "sg:province":"QLD",
    "wof:name":"Beauty On Fryar",
    "wof:placetype":"venue"
},
  "geometry": {"coordinates":[153.21211242699999,-27.7082614899],"type":"Point"}
}