{
  "type": "Feature",
  "properties": {
    "addr:full":"2- 4 Barnes Ave Earlwood NSW 2206",
    "addr:housenumber":"4",
    "addr:postcode":"2206",
    "addr:street":"Barnes Ave",
    "iso:country":"AU",
    "sg:address":"2- 4 Barnes Ave",
    "sg:city":"Earlwood",
    "sg:classifiers":[
        {
            "category":"Shopping",
            "subcategory":"Musical Instruments",
            "type":"Retail Goods"
        }
    ],
    "sg:phone":"+61 2 9787 9900",
    "sg:postcode":"2206",
    "sg:province":"NSW",
    "sg:tags":[
        "music",
        "background"
    ],
    "wof:name":"North Supply Communications Group",
    "wof:placetype":"venue"
},
  "geometry": {"coordinates":[151.11882,-33.919434],"type":"Point"}
}