{
  "type": "Feature",
  "properties": {
    "addr:full":"Cnr Brown & Linnett Sts Rockhampton QLD 4700",
    "addr:postcode":"4700",
    "addr:street":"Cnr",
    "iso:country":"AU",
    "sg:address":"Cnr Brown & Linnett Sts",
    "sg:city":"Rockhampton",
    "sg:classifiers":[
        {
            "category":"Professional",
            "type":"Services"
        }
    ],
    "sg:phone":"+61 7 4927 2844",
    "sg:postcode":"4700",
    "sg:province":"QLD",
    "sg:tags":[
        "courier"
    ],
    "wof:name":"Busfreight",
    "wof:placetype":"venue"
},
  "geometry": {"coordinates":[150.51869201700001,-23.3716144562],"type":"Point"}
}