{
  "type": "Feature",
  "properties": {
    "iso:country":"AU",
    "sg:address":"204 New Town Rd",
    "sg:city":"New Town",
    "sg:classifiers":[
        {
            "category":"Travel",
            "subcategory":"Travel Agent",
            "type":"Entertainment"
        }
    ],
    "sg:phone":"+61 3 6234 4951",
    "sg:postcode":"7008",
    "sg:province":"TAS",
    "sg:tags":[
        "tour",
        "holiday",
        "adventure"
    ],
    "wof:name":"Under Down Under Tours",
    "wof:placetype":"venue"
},
  "geometry": {"coordinates":[147.303634644,-42.856590271],"type":"Point"}
}