{
  "type": "Feature",
  "properties": {
    "iso:country":"AU",
    "sg:address":"Shop 22 Lygon Crt 380 Lygon St",
    "sg:city":"Carlton",
    "sg:classifiers":[
        {
            "category":"Shopping",
            "subcategory":"Clothing, Apparel, & Fashions",
            "type":"Retail Goods"
        }
    ],
    "sg:phone":"+61 3 9349 5200",
    "sg:postcode":"3053",
    "sg:province":"VIC",
    "sg:tags":[
        "lady",
        "wear"
    ],
    "wof:name":"Kamikaze",
    "wof:placetype":"venue"
},
  "geometry": {"coordinates":[144.96757507300001,-37.7978782654],"type":"Point"}
}