{
  "type": "Feature",
  "properties": {
    "addr:full":"PO Box 296 Narellan NSW 2567",
    "addr:postcode":"2567",
    "iso:country":"AU",
    "sg:address":"PO Box 296",
    "sg:city":"Narellan",
    "sg:classifiers":[
        {
            "category":"Professional",
            "subcategory":"Computer Services",
            "type":"Services"
        }
    ],
    "sg:phone":"+61 1300 654 276",
    "sg:postcode":"2567",
    "sg:province":"NSW",
    "sg:tags":[
        "equipment",
        "networking",
        "installation"
    ],
    "wof:name":"MayTek IT Solutions",
    "wof:placetype":"venue"
},
  "geometry": {"coordinates":[150.73526000999999,-34.0400390625],"type":"Point"}
}