{
  "type": "Feature",
  "properties": {
    "addr:full":"PO Box 61 Glass House Mountains QLD 4518",
    "addr:postcode":"4518",
    "iso:country":"AU",
    "sg:address":"PO Box 61",
    "sg:city":"Glass House Mountains",
    "sg:classifiers":[
        {
            "category":"Mining & Drilling",
            "type":"Manufacturing & Wholesale Goods"
        }
    ],
    "sg:phone":"+61 407 626 704",
    "sg:postcode":"4518",
    "sg:province":"QLD",
    "sg:tags":[
        "boring",
        "contractor"
    ],
    "wof:name":"Drillsure Pty Ltd",
    "wof:placetype":"venue"
},
  "geometry": {"coordinates":[152.959060669,-26.8959293365],"type":"Point"}
}