{
  "type": "Feature",
  "properties": {
    "addr:full":"32 Tyrell St Wallsend NSW 2287",
    "addr:housenumber":"32",
    "addr:postcode":"2287",
    "addr:street":"Tyrell St",
    "iso:country":"AU",
    "sg:address":"32 Tyrell St",
    "sg:city":"Wallsend",
    "sg:classifiers":[
        {
            "category":"Professional",
            "subcategory":"Printing & Photocopies",
            "type":"Services"
        }
    ],
    "sg:phone":"+61 2 4955 0225",
    "sg:postcode":"2287",
    "sg:province":"NSW",
    "sg:tags":[
        "photocopying"
    ],
    "wof:name":"Wallsend Copy Service",
    "wof:placetype":"venue"
},
  "geometry": {"coordinates":[151.66795349099999,-32.9009437561],"type":"Point"}
}