{
  "type": "Feature",
  "properties": {
    "addr:full":"169 Salisbury Hwy Salisbury SA 5108",
    "addr:housenumber":"169",
    "addr:postcode":"5108",
    "addr:street":"Salisbury Hwy",
    "iso:country":"AU",
    "sg:address":"169 Salisbury Hwy",
    "sg:city":"Salisbury",
    "sg:classifiers":[
        {
            "category":"Social Services",
            "subcategory":"Child Care",
            "type":"Services"
        }
    ],
    "sg:phone":"+61 8 8281 1745",
    "sg:postcode":"5108",
    "sg:province":"SA",
    "wof:name":"Highway Out Of Hours School Care",
    "wof:placetype":"venue"
},
  "geometry": {"coordinates":[138.63543701200001,-34.7687644958],"type":"Point"}
}