{
  "type": "Feature",
  "properties": {
    "iso:country":"AU",
    "sg:address":"shop 3 130 High St",
    "sg:city":"Woodend",
    "sg:classifiers":[
        {
            "category":"Health Services",
            "subcategory":"Optometrist",
            "type":"Services"
        }
    ],
    "sg:phone":"+61 3 5427 4577",
    "sg:postcode":"3442",
    "sg:province":"VIC",
    "wof:name":"Kosmac & Clemens Optometrists",
    "wof:placetype":"venue"
},
  "geometry": {"coordinates":[144.52963256800001,-37.3551635742],"type":"Point"}
}