{
  "type": "Feature",
  "properties": {
    "addr:full":"476 Bridge Rd Richmond VIC 3121",
    "addr:housenumber":"476",
    "addr:postcode":"3121",
    "addr:street":"Bridge Rd",
    "iso:country":"AU",
    "sg:address":"476 Bridge Rd",
    "sg:city":"Richmond",
    "sg:classifiers":[
        {
            "category":"Shopping",
            "subcategory":"Computers & Home Electronics",
            "type":"Retail Goods"
        }
    ],
    "sg:phone":"+61 3 9429 9677",
    "sg:postcode":"3121",
    "sg:province":"VIC",
    "sg:tags":[
        "small",
        "equipment",
        "business"
    ],
    "wof:name":"Digital Arts Computers (Aust) Pty Ltd",
    "wof:placetype":"venue"
},
  "geometry": {"coordinates":[145.00755310100001,-37.8195457458],"type":"Point"}
}