{
  "type": "Feature",
  "properties": {
    "addr:full":"Shop 7 Town Square Moranbah QLD 4744",
    "addr:housenumber":"shop 7",
    "addr:postcode":"4744",
    "addr:street":"Town Square",
    "iso:country":"AU",
    "sg:address":"Shop 7 Town Square",
    "sg:city":"Moranbah",
    "sg:classifiers":[
        {
            "category":"Food & Beverages",
            "subcategory":"Bakery",
            "type":"Retail Goods"
        }
    ],
    "sg:phone":"+61 7 4941 5924",
    "sg:postcode":"4744",
    "sg:province":"QLD",
    "sg:tags":[
        "cake",
        "shop",
        "pastry"
    ],
    "wof:name":"Moranbah Hot Bread Shop",
    "wof:placetype":"venue"
},
  "geometry": {"coordinates":[148.09439086899999,-22.1004600525],"type":"Point"}
}