{
  "type": "Feature",
  "properties": {
    "addr:full":"138 Gipps St Gwynneville NSW 2500",
    "addr:housenumber":"138",
    "addr:postcode":"2500",
    "addr:street":"Gipps St",
    "iso:country":"AU",
    "sg:address":"138 Gipps St",
    "sg:city":"Gwynneville",
    "sg:classifiers":[
        {
            "category":"Building & Trades",
            "subcategory":"Construction",
            "type":"Services"
        }
    ],
    "sg:phone":"+61 417 203 323",
    "sg:postcode":"2500",
    "sg:province":"NSW",
    "sg:tags":[
        "rendering",
        "cement"
    ],
    "wof:name":"Vule Cement Rendering",
    "wof:placetype":"venue"
},
  "geometry": {"coordinates":[150.887314,-34.416058],"type":"Point"}
}