{
  "type": "Feature",
  "properties": {
    "iso:country":"AU",
    "sg:address":"U2/ 15 Administration Rd",
    "sg:city":"Murarrie",
    "sg:classifiers":[
        {
            "category":"Shopping",
            "subcategory":"Stationery & Office Supplies",
            "type":"Retail Goods"
        }
    ],
    "sg:phone":"+61 7 3890 3327",
    "sg:postcode":"4172",
    "sg:province":"QLD",
    "sg:tags":[
        "packaging",
        "equipment",
        "sealing",
        "filling"
    ],
    "wof:name":"Flatwrap",
    "wof:placetype":"venue"
},
  "geometry": {"coordinates":[153.105026245,-27.4520511627],"type":"Point"}
}