{
  "type": "Feature",
  "properties": {
    "iso:country":"AU",
    "sg:address":"502- 506 Parramatta Rd",
    "sg:city":"Ashfield",
    "sg:classifiers":[
        {
            "category":"Building & Trades",
            "subcategory":"Construction",
            "type":"Services"
        }
    ],
    "sg:phone":"+61 2 9798 7899",
    "sg:postcode":"2131",
    "sg:province":"NSW",
    "sg:tags":[
        "joinery"
    ],
    "wof:name":"Ashfield Detail Joinery",
    "wof:placetype":"venue"
},
  "geometry": {"coordinates":[151.12960815400001,-33.8771438599],"type":"Point"}
}