{
  "type": "Feature",
  "properties": {
    "iso:country":"AU",
    "sg:address":"321 Belmore Rd",
    "sg:city":"Riverwood",
    "sg:classifiers":[
        {
            "category":"Health Services",
            "subcategory":"Health Practitioner",
            "type":"Services"
        }
    ],
    "sg:phone":"+61 2 9534 3817",
    "sg:postcode":"2210",
    "sg:province":"NSW",
    "sg:tags":[
        "osteopath"
    ],
    "wof:name":"Carter P",
    "wof:placetype":"venue"
},
  "geometry": {"coordinates":[151.05229199999999,-33.94997],"type":"Point"}
}