{
  "type": "Feature",
  "properties": {
    "addr:full":"7 Clavering Rd Bayswater WA 6053",
    "addr:housenumber":"7",
    "addr:postcode":"6053",
    "addr:street":"Clavering Rd",
    "iso:country":"AU",
    "sg:address":"7 Clavering Rd",
    "sg:city":"Bayswater",
    "sg:classifiers":[
        {
            "category":"Retail",
            "subcategory":"Laundry & Dry Cleaning",
            "type":"Services"
        }
    ],
    "sg:phone":"+61 8 9370 4277",
    "sg:postcode":"6053",
    "sg:province":"WA",
    "sg:tags":[
        "equipment",
        "supply"
    ],
    "wof:name":"Westralian Laundries & Linen Services",
    "wof:placetype":"venue"
},
  "geometry": {"coordinates":[115.921600342,-31.9170417786],"type":"Point"}
}