{
  "type": "Feature",
  "properties": {
    "iso:country":"AU",
    "sg:address":"3 Martin St",
    "sg:city":"Heathmont",
    "sg:classifiers":[
        {
            "category":"Communications",
            "subcategory":"Television Station",
            "type":"Services"
        }
    ],
    "sg:phone":"+61 3 9720 8886",
    "sg:postcode":"3135",
    "sg:province":"VIC",
    "sg:tags":[
        "equipment",
        "radio"
    ],
    "wof:name":"Total Tech Support",
    "wof:placetype":"venue"
},
  "geometry": {"coordinates":[145.254730225,-37.8332672119],"type":"Point"}
}