{
  "type": "Feature",
  "properties": {
    "addr:full":"Unit 1/ 288 Victoria Rd Malaga WA 6090",
    "addr:housenumber":"/ 288",
    "addr:postcode":"6090",
    "addr:street":"Victoria Rd",
    "iso:country":"AU",
    "sg:address":"Unit 1/ 288 Victoria Rd",
    "sg:city":"Malaga",
    "sg:classifiers":[
        {
            "category":"Real Estate",
            "subcategory":"Surveying",
            "type":"Services"
        }
    ],
    "sg:phone":"+61 8 9209 3070",
    "sg:postcode":"6090",
    "sg:province":"WA",
    "sg:tags":[
        "geophysicist"
    ],
    "wof:name":"Geoforce",
    "wof:placetype":"venue"
},
  "geometry": {"coordinates":[115.88951110799999,-31.8616752625],"type":"Point"}
}