{
  "type": "Feature",
  "properties": {
    "addr:full":"24 Miles Rd Kewdale WA 6105",
    "addr:housenumber":"24",
    "addr:postcode":"6105",
    "addr:street":"Miles Rd",
    "iso:country":"AU",
    "sg:address":"24 Miles Rd",
    "sg:city":"Kewdale",
    "sg:classifiers":[
        {
            "category":"Taxi",
            "type":"Transportation"
        }
    ],
    "sg:phone":"+61 8 9352 5100",
    "sg:postcode":"6105",
    "sg:province":"WA",
    "sg:tags":[
        "truck"
    ],
    "wof:name":"Executive Couriers & Taxi Trucks",
    "wof:placetype":"venue"
},
  "geometry": {"coordinates":[115.953422546,-31.982919693],"type":"Point"}
}