{
  "type": "Feature",
  "properties": {
    "iso:country":"AU",
    "sg:address":"7 Northwood St",
    "sg:city":"Camperdown",
    "sg:classifiers":[
        {
            "category":"Shopping",
            "subcategory":"Musical Instruments",
            "type":"Retail Goods"
        }
    ],
    "sg:phone":"+61 2 9557 3000",
    "sg:postcode":"2050",
    "sg:province":"NSW",
    "sg:tags":[
        "musician",
        "agent"
    ],
    "wof:name":"Smash Artist Service",
    "wof:placetype":"venue"
},
  "geometry": {"coordinates":[151.178619,-33.891266],"type":"Point"}
}