{
  "type": "Feature",
  "properties": {
    "addr:full":"11 Queens Rd Melbourne VIC 3000",
    "addr:housenumber":"11",
    "addr:postcode":"3000",
    "addr:street":"Queens Rd",
    "iso:country":"AU",
    "sg:address":"11 Queens Rd",
    "sg:city":"Melbourne",
    "sg:classifiers":[
        {
            "category":"Professional",
            "subcategory":"Computer Services",
            "type":"Services"
        }
    ],
    "sg:phone":"+61 3 9820 0500",
    "sg:postcode":"3000",
    "sg:province":"VIC",
    "sg:tags":[
        "package",
        "software"
    ],
    "wof:name":"Advanced Solutions International",
    "wof:placetype":"venue"
},
  "geometry": {"coordinates":[144.97398376500001,-37.8380279541],"type":"Point"}
}