{
  "type": "Feature",
  "properties": {
    "addr:full":"96 Elizabeth St Launceston TAS 7250",
    "addr:housenumber":"96",
    "addr:postcode":"7250",
    "addr:street":"Elizabeth St",
    "iso:country":"AU",
    "sg:address":"96 Elizabeth St",
    "sg:city":"Launceston",
    "sg:classifiers":[
        {
            "category":"Autos & Motor Vehicles",
            "subcategory":"Automobile Sales",
            "type":"Retail Goods"
        }
    ],
    "sg:phone":"+61 3 6332 9130",
    "sg:postcode":"7250",
    "sg:province":"TAS",
    "sg:tags":[
        "car",
        "new"
    ],
    "wof:name":"Hyundai",
    "wof:placetype":"venue"
},
  "geometry": {"coordinates":[147.138580322,-41.4404602051],"type":"Point"}
}