{
  "type": "Feature",
  "properties": {
    "iso:country":"AU",
    "sg:address":"4 Sycamore Pde",
    "sg:city":"Victoria Point",
    "sg:classifiers":[
        {
            "category":"Building & Trades",
            "subcategory":"Landscaping Services",
            "type":"Services"
        }
    ],
    "sg:phone":"+61 7 3207 8394",
    "sg:postcode":"4165",
    "sg:province":"QLD",
    "sg:tags":[
        "designer",
        "landscape",
        "contractor"
    ],
    "wof:name":"Moreton Bay Landscapes",
    "wof:placetype":"venue"
},
  "geometry": {"coordinates":[153.28315734899999,-27.589389801],"type":"Point"}
}