{
  "type": "Feature",
  "properties": {
    "addr:full":"Trenayr Rd Junction Hill NSW 2460",
    "addr:postcode":"2460",
    "addr:street":"Trenayr Rd",
    "iso:country":"AU",
    "sg:address":"Trenayr Rd",
    "sg:city":"Junction Hill",
    "sg:classifiers":[
        {
            "category":"Home & Garden",
            "subcategory":"Carpets & Floor Coverings",
            "type":"Retail Goods"
        }
    ],
    "sg:phone":"+61 2 6644 0900",
    "sg:postcode":"2460",
    "sg:province":"NSW",
    "sg:tags":[
        "wood"
    ],
    "wof:name":"Big River Timbers Pty Ltd",
    "wof:placetype":"venue"
},
  "geometry": {"coordinates":[152.93211364699999,-29.6416568756],"type":"Point"}
}