{
  "type": "Feature",
  "properties": {
    "addr:full":"78a Berowra Waters Rd Berowra NSW 2081",
    "addr:housenumber":"78a",
    "addr:postcode":"2081",
    "addr:street":"Berowra Waters Rd",
    "iso:country":"AU",
    "sg:address":"78a Berowra Waters Rd",
    "sg:city":"Berowra",
    "sg:classifiers":[
        {
            "category":"Home & Garden",
            "subcategory":"Building Materials",
            "type":"Retail Goods"
        }
    ],
    "sg:phone":"+61 2 9456 1486",
    "sg:postcode":"2081",
    "sg:province":"NSW",
    "sg:tags":[
        "merchant",
        "glass",
        "glazier"
    ],
    "wof:name":"Berowra Glass & Glazing",
    "wof:placetype":"venue"
},
  "geometry": {"coordinates":[151.14401245100001,-33.6172828674],"type":"Point"}
}