{
  "type": "Feature",
  "properties": {
    "addr:full":"PO Box 6005 Gosford West NSW 2250",
    "addr:postcode":"2250",
    "iso:country":"AU",
    "sg:address":"PO Box 6005",
    "sg:city":"Gosford West",
    "sg:classifiers":[
        {
            "category":"Building & Trades",
            "subcategory":"Pest Control",
            "type":"Services"
        }
    ],
    "sg:phone":"+61 2 4322 8771",
    "sg:postcode":"2250",
    "sg:province":"NSW",
    "wof:name":"Pest Control Services",
    "wof:placetype":"venue"
},
  "geometry": {"coordinates":[151.32734680199999,-33.4264717102],"type":"Point"}
}