{
  "type": "Feature",
  "properties": {
    "iso:country":"AU",
    "sg:address":"15- 17 William St",
    "sg:city":"Alexandria",
    "sg:classifiers":[
        {
            "category":"Professional",
            "subcategory":"Computer Services",
            "type":"Services"
        }
    ],
    "sg:phone":"+61 2 8594 5666",
    "sg:postcode":"2015",
    "sg:province":"NSW",
    "sg:tags":[
        "on-line",
        "provider"
    ],
    "wof:name":"Braenet",
    "wof:placetype":"venue"
},
  "geometry": {"coordinates":[151.19871520999999,-33.9124832153],"type":"Point"}
}