{
  "type": "Feature",
  "properties": {
    "addr:full":"10 Whiteside Rd Clayton VIC 3168",
    "addr:housenumber":"10",
    "addr:postcode":"3168",
    "addr:street":"Whiteside Rd",
    "iso:country":"AU",
    "sg:address":"10 Whiteside Rd",
    "sg:city":"Clayton",
    "sg:classifiers":[
        {
            "category":"Manufacturing",
            "subcategory":"Tools & Machinery",
            "type":"Manufacturing & Wholesale Goods"
        }
    ],
    "sg:phone":"+61 3 9562 9181",
    "sg:postcode":"3168",
    "sg:province":"VIC",
    "sg:tags":[
        "toolmaker"
    ],
    "wof:name":"Ritosi Pty Ltd",
    "wof:placetype":"venue"
},
  "geometry": {"coordinates":[145.124755859,-37.899181366],"type":"Point"}
}