{
  "type": "Feature",
  "properties": {
    "iso:country":"AU",
    "sg:address":"4 / 190 Invermay Rd",
    "sg:city":"Launceston",
    "sg:classifiers":[
        {
            "category":"Home & Garden",
            "subcategory":"Building Materials",
            "type":"Retail Goods"
        }
    ],
    "sg:phone":"+61 1300 666 232",
    "sg:postcode":"7900",
    "sg:province":"TAS",
    "sg:tags":[
        "fitting",
        "door"
    ],
    "wof:name":"Albany Nomafa",
    "wof:placetype":"venue"
},
  "geometry": {"coordinates":[147.13255310100001,-41.4106903076],"type":"Point"}
}