{
  "type": "Feature",
  "properties": {
    "addr:full":"Shop 1, 112-126 City Rd Beenleigh QLD 4207",
    "addr:housenumber":"shop 1",
    "addr:postcode":"112-126;4207",
    "addr:street":"City Rd",
    "iso:country":"AU",
    "sg:address":"Shop 1, 112-126 City Rd",
    "sg:city":"Beenleigh",
    "sg:classifiers":[
        {
            "category":"Airline",
            "type":"Transportation"
        }
    ],
    "sg:phone":"+61 7 3287 2504",
    "sg:postcode":"4207",
    "sg:province":"QLD",
    "sg:tags":[
        "agent"
    ],
    "wof:name":"Harvey World Travel Beenleigh",
    "wof:placetype":"venue"
},
  "geometry": {"coordinates":[153.20225524899999,-27.7157440186],"type":"Point"}
}