{
  "type": "Feature",
  "properties": {
    "addr:full":"PO Box 131 Seaford SA 5169",
    "addr:postcode":"5169",
    "iso:country":"AU",
    "sg:address":"PO Box 131",
    "sg:city":"Seaford",
    "sg:classifiers":[
        {
            "category":"Health Services",
            "subcategory":"Health Practitioner",
            "type":"Services"
        }
    ],
    "sg:phone":"+61 417 104 250",
    "sg:postcode":"5169",
    "sg:province":"SA",
    "sg:tags":[
        "pathologist",
        "speech"
    ],
    "wof:name":"Fleurieu Speech Pathology",
    "wof:placetype":"venue"
},
  "geometry": {"coordinates":[138.477050781,-35.1855392456],"type":"Point"}
}