{
  "type": "Feature",
  "properties": {
    "addr:full":"25 Caldwell St Merewether NSW 2291",
    "addr:housenumber":"25",
    "addr:postcode":"2291",
    "addr:street":"Caldwell St",
    "iso:country":"AU",
    "sg:address":"25 Caldwell St",
    "sg:city":"Merewether",
    "sg:classifiers":[
        {
            "category":"Education",
            "subcategory":"Kindergarten",
            "type":"Public Place"
        }
    ],
    "sg:phone":"+61 2 4963 1590",
    "sg:postcode":"2291",
    "sg:province":"NSW",
    "sg:tags":[
        "pre-schools"
    ],
    "wof:name":"Merewether KU Pre-School",
    "wof:placetype":"venue"
},
  "geometry": {"coordinates":[151.75032043499999,-32.9428672791],"type":"Point"}
}