{
  "type": "Feature",
  "properties": {
    "addr:full":"123 Commercial Rd Port Adelaide SA 5015",
    "addr:housenumber":"123",
    "addr:postcode":"5015",
    "addr:street":"Commercial Rd",
    "iso:country":"AU",
    "sg:address":"123 Commercial Rd",
    "sg:city":"Port Adelaide",
    "sg:classifiers":[
        {
            "category":"Professional",
            "subcategory":"Accounting & Tax Preparation",
            "type":"Services"
        }
    ],
    "sg:phone":"+61 8 8415 2288",
    "sg:postcode":"5015",
    "sg:province":"SA",
    "sg:tags":[
        "consultant",
        "taxation"
    ],
    "wof:name":"I.T.P. The Income Tax Professionals",
    "wof:placetype":"venue"
},
  "geometry": {"coordinates":[138.50663757300001,-34.8457984924],"type":"Point"}
}