{
  "type": "Feature",
  "properties": {
    "addr:full":"Unit 2 , Jeffries Place, Gowrie Shops Gowrie ACT 2904",
    "addr:postcode":"2904",
    "addr:street":"Jeffries Place",
    "iso:country":"AU",
    "sg:address":"Unit 2",
    "sg:city":", Jeffries Place, Gowrie Shops Gowrie",
    "sg:classifiers":[
        {
            "category":"Personal",
            "subcategory":"Massage",
            "type":"Services"
        }
    ],
    "sg:phone":"+61 2 6291 7970",
    "sg:postcode":"2904",
    "sg:province":"ACT",
    "sg:tags":[
        "therapy"
    ],
    "wof:name":"Kennedy Verlie",
    "wof:placetype":"venue"
},
  "geometry": {"coordinates":[149.10963439899999,-35.4137954712],"type":"Point"}
}