{
  "type": "Feature",
  "properties": {
    "iso:country":"AU",
    "sg:address":"19 Donald Drv",
    "sg:city":"Safety Bay",
    "sg:classifiers":[
        {
            "category":"Building & Trades",
            "subcategory":"Plumbing",
            "type":"Services"
        }
    ],
    "sg:phone":"+61 8 9592 2177",
    "sg:postcode":"6169",
    "sg:province":"WA",
    "sg:tags":[
        "plumber",
        "gasfitters"
    ],
    "wof:name":"Morrison Rod Nominees Pty Ltd",
    "wof:placetype":"venue"
},
  "geometry": {"coordinates":[115.727409,-32.306328],"type":"Point"}
}