{
  "type": "Feature",
  "properties": {
    "iso:country":"AU",
    "sg:address":"7 Henry Parkes Drv",
    "sg:city":"Kiama Downs",
    "sg:classifiers":[
        {
            "category":"Professional",
            "subcategory":"Engineering",
            "type":"Services"
        }
    ],
    "sg:phone":"+61 2 4237 7255",
    "sg:postcode":"2533",
    "sg:province":"NSW",
    "sg:tags":[
        "consulting",
        "engineer"
    ],
    "wof:name":"Balance Research & Development",
    "wof:placetype":"venue"
},
  "geometry": {"coordinates":[150.84025573700001,-34.6456642151],"type":"Point"}
}