{
  "type": "Feature",
  "properties": {
    "addr:full":"43 Haydens Rd Kingaroy QLD 4610",
    "addr:housenumber":"43",
    "addr:postcode":"4610",
    "addr:street":"Haydens Rd",
    "iso:country":"AU",
    "sg:address":"43 Haydens Rd",
    "sg:city":"Kingaroy",
    "sg:classifiers":[
        {
            "category":"Building & Trades",
            "subcategory":"Landscaping Services",
            "type":"Services"
        }
    ],
    "sg:phone":"+61 7 4162 2812",
    "sg:postcode":"4610",
    "sg:province":"QLD",
    "sg:tags":[
        "fertilizer",
        "spreading",
        "insecticide"
    ],
    "wof:name":"C V & L M Thomasson",
    "wof:placetype":"venue"
},
  "geometry": {"coordinates":[151.88127136200001,-26.5042953491],"type":"Point"}
}