{
  "type": "Feature",
  "properties": {
    "addr:full":"Shop 1 427 The Esp Hervey Bay QLD 4655",
    "addr:housenumber":"shop 1 427",
    "addr:postcode":"4655",
    "addr:street":"The Esp",
    "iso:country":"AU",
    "sg:address":"Shop 1 427 The Esp",
    "sg:city":"Hervey Bay",
    "sg:classifiers":[
        {
            "category":"Food & Beverages",
            "subcategory":"Specialty",
            "type":"Retail Goods"
        }
    ],
    "sg:phone":"+61 7 4194 6712",
    "sg:postcode":"4655",
    "sg:province":"QLD",
    "sg:tags":[
        "product",
        "health"
    ],
    "wof:name":"Go Natural Foods",
    "wof:placetype":"venue"
},
  "geometry": {"coordinates":[152.87146000000001,-25.284332],"type":"Point"}
}