{
  "type": "Feature",
  "properties": {
    "iso:country":"AU",
    "sg:address":"2 Margot Crs",
    "sg:city":"Forster",
    "sg:classifiers":[
        {
            "category":"Wholesale",
            "subcategory":"Painting Supplies",
            "type":"Manufacturing & Wholesale Goods"
        }
    ],
    "sg:phone":"+61 2 6555 2816",
    "sg:postcode":"2428",
    "sg:province":"NSW",
    "sg:tags":[
        "product",
        "cleaning"
    ],
    "wof:name":"Amway Of Australia Pty Ltd",
    "wof:placetype":"venue"
},
  "geometry": {"coordinates":[152.516083,-32.18552],"type":"Point"}
}