{
  "type": "Feature",
  "properties": {
    "addr:full":"44 Cliff St Merimbula NSW 2548",
    "addr:housenumber":"44",
    "addr:postcode":"2548",
    "addr:street":"Cliff St",
    "iso:country":"AU",
    "sg:address":"44 Cliff St",
    "sg:city":"Merimbula",
    "sg:classifiers":[
        {
            "category":"Government",
            "subcategory":"Post Office",
            "type":"Public Place"
        }
    ],
    "sg:phone":"+61 2 6495 1213",
    "sg:postcode":"2548",
    "sg:province":"NSW",
    "sg:tags":[
        "yoga"
    ],
    "wof:name":"Meredith Dolan",
    "wof:placetype":"venue"
},
  "geometry": {"coordinates":[149.90544128400001,-36.8844566345],"type":"Point"}
}