{
  "type": "Feature",
  "properties": {
    "iso:country":"AU",
    "sg:address":"Shop 58 The Mall",
    "sg:city":"Heidelberg West",
    "sg:classifiers":[
        {
            "category":"Personal",
            "subcategory":"Beauty Salon",
            "type":"Services"
        }
    ],
    "sg:phone":"+61 3 9459 0306",
    "sg:postcode":"3081",
    "sg:province":"VIC",
    "sg:tags":[
        "hairdresser"
    ],
    "wof:name":"Gends Hair & Beauty Salon",
    "wof:placetype":"venue"
},
  "geometry": {"coordinates":[145.04301452600001,-37.7484359741],"type":"Point"}
}