{
  "type": "Feature",
  "properties": {
    "addr:full":"Main St Orroroo SA 5431",
    "addr:postcode":"5431",
    "addr:street":"Main St",
    "iso:country":"AU",
    "sg:address":"Main St",
    "sg:city":"Orroroo",
    "sg:classifiers":[
        {
            "category":"Cafe",
            "type":"Food & Drink"
        }
    ],
    "sg:phone":"+61 8 8658 1351",
    "sg:postcode":"5431",
    "sg:province":"SA",
    "wof:name":"Maggies Rendezvous",
    "wof:placetype":"venue"
},
  "geometry": {"coordinates":[138.49571227999999,-32.721660614],"type":"Point"}
}