{
  "type": "Feature",
  "properties": {
    "iso:country":"AU",
    "sg:address":"Blanchview Rd",
    "sg:city":"Withcott",
    "sg:classifiers":[
        {
            "category":"Professional",
            "subcategory":"Art Services",
            "type":"Services"
        }
    ],
    "sg:phone":"+61 418 584 663",
    "sg:postcode":"4352",
    "sg:province":"QLD",
    "sg:tags":[
        "decorator",
        "painter"
    ],
    "wof:name":"Crosbys Painting Service",
    "wof:placetype":"venue"
},
  "geometry": {"coordinates":[152.041458,-27.562931],"type":"Point"}
}