{
  "type": "Feature",
  "properties": {
    "addr:full":"19 Targo St Bundaberg QLD 4670",
    "addr:housenumber":"19",
    "addr:postcode":"4670",
    "addr:street":"Targo St",
    "iso:country":"AU",
    "sg:address":"19 Targo St",
    "sg:city":"Bundaberg",
    "sg:classifiers":[
        {
            "category":"Banks & Credit Unions",
            "subcategory":"Financial Services",
            "type":"Services"
        }
    ],
    "sg:phone":"+61 7 4151 4222",
    "sg:postcode":"4670",
    "sg:province":"QLD",
    "sg:tags":[
        "planning"
    ],
    "sg:website":"http://www.retireinvest.com.au",
    "wof:name":"RetireInvest",
    "wof:placetype":"venue"
},
  "geometry": {"coordinates":[152.352493286,-24.8703632355],"type":"Point"}
}