{
  "type": "Feature",
  "properties": {
    "addr:full":"9 Honour Ave Lawson NSW 2783",
    "addr:housenumber":"9",
    "addr:postcode":"2783",
    "addr:street":"Honour Ave",
    "iso:country":"AU",
    "sg:address":"9 Honour Ave",
    "sg:city":"Lawson",
    "sg:classifiers":[
        {
            "category":"Home & Garden",
            "subcategory":"Hardware",
            "type":"Retail Goods"
        }
    ],
    "sg:phone":"+61 2 4759 1426",
    "sg:postcode":"2783",
    "sg:province":"NSW",
    "sg:tags":[
        "repair",
        "tool",
        "power"
    ],
    "wof:name":"Skinner's Hardware",
    "wof:placetype":"venue"
},
  "geometry": {"coordinates":[150.43095398,-33.7198028564],"type":"Point"}
}