{
  "type": "Feature",
  "properties": {
    "iso:country":"AU",
    "sg:address":"37 Beulah Rd",
    "sg:city":"Norwood",
    "sg:classifiers":[
        {
            "category":"Professional",
            "subcategory":"Business Services",
            "type":"Services"
        }
    ],
    "sg:phone":"+61 8 8363 0848",
    "sg:postcode":"5067",
    "sg:province":"SA",
    "sg:tags":[
        "fashion",
        "agent"
    ],
    "wof:name":"Hensel Agencies Pty Ltd",
    "wof:placetype":"venue"
},
  "geometry": {"coordinates":[138.63140869099999,-34.9181747437],"type":"Point"}
}