{
  "type": "Feature",
  "properties": {
    "addr:full":"193 Ryans Rd Globe Derby Park SA 5110",
    "addr:housenumber":"193",
    "addr:postcode":"5110",
    "addr:street":"Ryans Rd",
    "iso:country":"AU",
    "sg:address":"193 Ryans Rd",
    "sg:city":"Globe Derby Park",
    "sg:classifiers":[
        {
            "category":"Building & Trades",
            "subcategory":"Landscaping Services",
            "type":"Services"
        }
    ],
    "sg:phone":"+61 8 8182 5963",
    "sg:postcode":"5110",
    "sg:province":"SA",
    "sg:tags":[
        "stump",
        "tree",
        "felling",
        "removal"
    ],
    "wof:name":"IM Limmer",
    "wof:placetype":"venue"
},
  "geometry": {"coordinates":[138.590606689,-34.7840042114],"type":"Point"}
}