{
  "type": "Feature",
  "properties": {
    "iso:country":"AU",
    "sg:address":"76 Planthurst Rd",
    "sg:city":"Carlton",
    "sg:classifiers":[
        {
            "category":"Manufacturing",
            "subcategory":"Wood Products",
            "type":"Manufacturing & Wholesale Goods"
        }
    ],
    "sg:phone":"+61 2 9546 6793",
    "sg:postcode":"2218",
    "sg:province":"NSW",
    "sg:tags":[
        "machinist"
    ],
    "wof:name":"M & M Patternmaking Pty Ltd",
    "wof:placetype":"venue"
},
  "geometry": {"coordinates":[151.114563,-33.978909],"type":"Point"}
}