{
  "type": "Feature",
  "properties": {
    "addr:full":"Clarkes La Wangaratta VIC 3677",
    "addr:postcode":"3677",
    "iso:country":"AU",
    "sg:address":"Clarkes La",
    "sg:city":"Wangaratta",
    "sg:classifiers":[
        {
            "category":"Building & Trades",
            "subcategory":"Landscaping Services",
            "type":"Services"
        }
    ],
    "sg:phone":"+61 3 5721 6428",
    "sg:postcode":"3677",
    "sg:province":"VIC",
    "sg:tags":[
        "gardener"
    ],
    "wof:name":"Marshall's Garden Care",
    "wof:placetype":"venue"
},
  "geometry": {"coordinates":[146.32354736299999,-36.3889541626],"type":"Point"}
}