{
  "type": "Feature",
  "properties": {
    "addr:full":"54 Mary St Unley SA 5061",
    "addr:housenumber":"54",
    "addr:postcode":"5061",
    "addr:street":"Mary St",
    "iso:country":"AU",
    "sg:address":"54 Mary St",
    "sg:city":"Unley",
    "sg:classifiers":[
        {
            "category":"Social Services",
            "subcategory":"Retirement Home",
            "type":"Services"
        }
    ],
    "sg:phone":"+61 8 8271 0322",
    "sg:postcode":"5061",
    "sg:province":"SA",
    "sg:tags":[
        "environmental",
        "consultant",
        "pollution"
    ],
    "wof:name":"Environmental Ground Water & Air Consultants Pty Ltd",
    "wof:placetype":"venue"
},
  "geometry": {"coordinates":[138.60337829599999,-34.9483566284],"type":"Point"}
}