{
  "type": "Feature",
  "properties": {
    "addr:full":"U1/ 252 Clovelly Rd Clovelly NSW 2031",
    "addr:housenumber":"252",
    "addr:postcode":"2031",
    "addr:street":"U1 /;Clovelly Rd",
    "iso:country":"AU",
    "sg:address":"U1/ 252 Clovelly Rd",
    "sg:city":"Clovelly",
    "sg:classifiers":[
        {
            "category":"Building & Trades",
            "subcategory":"Cleaning & Sanitation",
            "type":"Services"
        }
    ],
    "sg:phone":"+61 425 282 219",
    "sg:postcode":"2031",
    "sg:province":"NSW",
    "sg:tags":[
        "window"
    ],
    "wof:name":"Glowing Panes",
    "wof:placetype":"venue"
},
  "geometry": {"coordinates":[151.25697326700001,-33.9120178223],"type":"Point"}
}