{
  "type": "Feature",
  "properties": {
    "addr:full":"26 Duporth Ave Maroochydore QLD 4558",
    "addr:housenumber":"26",
    "addr:postcode":"4558",
    "addr:street":"Duporth Ave",
    "iso:country":"AU",
    "sg:address":"26 Duporth Ave",
    "sg:city":"Maroochydore",
    "sg:classifiers":[
        {
            "category":"Banks & Credit Unions",
            "subcategory":"Investment Brokerage",
            "type":"Services"
        }
    ],
    "sg:phone":"+61 7 5443 4088",
    "sg:postcode":"4558",
    "sg:province":"QLD",
    "wof:name":"AJ Cassel & Co",
    "wof:placetype":"venue"
},
  "geometry": {"coordinates":[153.089385986,-26.6498432159],"type":"Point"}
}