{
  "type": "Feature",
  "properties": {
    "addr:full":"33 Clivia Crs Daisy Hill QLD 4127",
    "addr:housenumber":"33",
    "addr:postcode":"4127",
    "addr:street":"Clivia Crs",
    "iso:country":"AU",
    "sg:address":"33 Clivia Crs",
    "sg:city":"Daisy Hill",
    "sg:classifiers":[
        {
            "category":"Health Services",
            "subcategory":"Health Practitioner",
            "type":"Services"
        }
    ],
    "sg:phone":"+61 7 3290 0876",
    "sg:postcode":"4127",
    "sg:province":"QLD",
    "sg:tags":[
        "consultant",
        "conservation",
        "hearing"
    ],
    "wof:name":"Protac Passtop Hearing Protection",
    "wof:placetype":"venue"
},
  "geometry": {"coordinates":[153.15470886200001,-27.6364803314],"type":"Point"}
}