{
  "type": "Feature",
  "properties": {
    "iso:country":"AU",
    "sg:address":"Gainsborough Rd",
    "sg:city":"Narromine",
    "sg:classifiers":[
        {
            "category":"Farming",
            "subcategory":"Farm & Veterinary Services",
            "type":"Manufacturing & Wholesale Goods"
        }
    ],
    "sg:phone":"+61 2 6889 2888",
    "sg:postcode":"2821",
    "sg:province":"NSW",
    "sg:tags":[
        "drying",
        "seed",
        "cleaning",
        "grading"
    ],
    "wof:name":"Deltapine Australia Pty Ltd",
    "wof:placetype":"venue"
},
  "geometry": {"coordinates":[148.238739014,-32.2564506531],"type":"Point"}
}