{
  "type": "Feature",
  "properties": {
    "addr:full":"Tasker St Condobolin NSW 2877",
    "addr:postcode":"2877",
    "addr:street":"Tasker St",
    "iso:country":"AU",
    "sg:address":"Tasker St",
    "sg:city":"Condobolin",
    "sg:classifiers":[
        {
            "category":"Sports & Exercise",
            "subcategory":"Golf",
            "type":"Entertainment"
        }
    ],
    "sg:phone":"+61 2 6895 2465",
    "sg:postcode":"2877",
    "sg:province":"NSW",
    "sg:tags":[
        "club"
    ],
    "wof:name":"Condobolin Golf Club Ltd",
    "wof:placetype":"venue"
},
  "geometry": {"coordinates":[147.141144,-33.086216],"type":"Point"}
}