{
  "type": "Feature",
  "properties": {
    "addr:full":"98 Onkaparinga Rd Bridgewater SA 5155",
    "addr:housenumber":"98",
    "addr:postcode":"5155",
    "addr:street":"Onkaparinga Rd",
    "iso:country":"AU",
    "sg:address":"98 Onkaparinga Rd",
    "sg:city":"Bridgewater",
    "sg:classifiers":[
        {
            "category":"Health Services",
            "subcategory":"Health Practitioner",
            "type":"Services"
        }
    ],
    "sg:phone":"+61 8 8339 7258",
    "sg:postcode":"5155",
    "sg:province":"SA",
    "sg:tags":[
        "naturopath"
    ],
    "wof:name":"Aligned With Nature",
    "wof:placetype":"venue"
},
  "geometry": {"coordinates":[138.76963806099999,-35.0057678223],"type":"Point"}
}