{
  "type": "Feature",
  "properties": {
    "addr:full":"23- 25 Alfred St South Melbourne VIC 3205",
    "addr:housenumber":"25",
    "addr:postcode":"3205",
    "addr:street":"Alfred St",
    "iso:country":"AU",
    "sg:address":"23- 25 Alfred St",
    "sg:city":"South Melbourne",
    "sg:classifiers":[
        {
            "category":"Recreation",
            "subcategory":"Amusement Park",
            "type":"Entertainment"
        }
    ],
    "sg:phone":"+61 3 9888 8999",
    "sg:postcode":"3205",
    "sg:province":"VIC",
    "wof:name":"Bingovic",
    "wof:placetype":"venue"
},
  "geometry": {"coordinates":[144.95001199999999,-37.832325],"type":"Point"}
}