{
  "type": "Feature",
  "properties": {
    "addr:full":"Shop 10/ 95 Marine Pde San Remo VIC 3925",
    "addr:housenumber":"shop 10 / 95",
    "addr:postcode":"3925",
    "addr:street":"Marine Pde",
    "iso:country":"AU",
    "sg:address":"Shop 10/ 95 Marine Pde",
    "sg:city":"San Remo",
    "sg:classifiers":[
        {
            "category":"Wholesale",
            "subcategory":"Electrical",
            "type":"Manufacturing & Wholesale Goods"
        }
    ],
    "sg:phone":"+61 3 5678 5361",
    "sg:postcode":"3925",
    "sg:province":"VIC",
    "sg:tags":[
        "wholesaler"
    ],
    "wof:name":"Shorelec Electrical Wholesales",
    "wof:placetype":"venue"
},
  "geometry": {"coordinates":[145.372650147,-38.5206947327],"type":"Point"}
}