{
  "type": "Feature",
  "properties": {
    "addr:full":"27 Adelaide Crs Middleton Beach WA 6330",
    "addr:housenumber":"27",
    "addr:postcode":"6330",
    "addr:street":"Adelaide Crs",
    "iso:country":"AU",
    "sg:address":"27 Adelaide Crs",
    "sg:city":"Middleton Beach",
    "sg:classifiers":[
        {
            "category":"Travel",
            "subcategory":"Hotels & Motels",
            "type":"Entertainment"
        }
    ],
    "sg:phone":"+61 8 9842 2877",
    "sg:postcode":"6330",
    "sg:province":"WA",
    "wof:name":"Balneaire Seaside Resort",
    "wof:placetype":"venue"
},
  "geometry": {"coordinates":[117.862457275,-34.986995697],"type":"Point"}
}