{
  "type": "Feature",
  "properties": {
    "addr:full":"8 River St South Yarra VIC 3141",
    "addr:housenumber":"8",
    "addr:postcode":"3141",
    "addr:street":"River St",
    "iso:country":"AU",
    "sg:address":"8 River St",
    "sg:city":"South Yarra",
    "sg:classifiers":[
        {
            "category":"Manufacturing",
            "subcategory":"Food",
            "type":"Manufacturing & Wholesale Goods"
        }
    ],
    "sg:phone":"+61 3 9825 0000",
    "sg:postcode":"3141",
    "sg:province":"VIC",
    "sg:tags":[
        "function",
        "catering"
    ],
    "wof:name":"Peter Rowland Catering",
    "wof:placetype":"venue"
},
  "geometry": {"coordinates":[144.99745178200001,-37.8389968872],"type":"Point"}
}