{
  "type": "Feature",
  "properties": {
    "addr:full":"65 Ellavale Drv Traralgon VIC 3844",
    "addr:housenumber":"65",
    "addr:postcode":"3844",
    "addr:street":"Ellavale Drv",
    "iso:country":"AU",
    "sg:address":"65 Ellavale Drv",
    "sg:city":"Traralgon",
    "sg:classifiers":[
        {
            "category":"Professional",
            "subcategory":"Engineering",
            "type":"Services"
        }
    ],
    "sg:phone":"+61 408 513 847",
    "sg:postcode":"3844",
    "sg:province":"VIC",
    "sg:tags":[
        "consulting",
        "engineer"
    ],
    "wof:name":"Gippsland Civil Consultants Pty Ltd",
    "wof:placetype":"venue"
},
  "geometry": {"coordinates":[146.569824219,-38.1952362061],"type":"Point"}
}