{
  "type": "Feature",
  "properties": {
    "addr:full":"Cnr Martin St & Harrison La Fortitude Valley QLD 4006",
    "addr:postcode":"4006",
    "addr:street":"Cnr Martin St & Harrison",
    "iso:country":"AU",
    "sg:address":"Cnr Martin St & Harrison La",
    "sg:city":"Fortitude Valley",
    "sg:classifiers":[
        {
            "category":"Health Services",
            "subcategory":"Doctor",
            "type":"Services"
        }
    ],
    "sg:phone":"+61 7 3358 3668",
    "sg:postcode":"4006",
    "sg:province":"QLD",
    "sg:tags":[
        "medical",
        "practitioner"
    ],
    "wof:name":"Aedonna",
    "wof:placetype":"venue"
},
  "geometry": {"coordinates":[153.036621094,-27.4602851868],"type":"Point"}
}