{
  "type": "Feature",
  "properties": {
    "addr:full":"8618 New England Hwy Hampton QLD 4352",
    "addr:housenumber":"8618",
    "addr:postcode":"4352",
    "addr:street":"New England Hwy",
    "iso:country":"AU",
    "sg:address":"8618 New England Hwy",
    "sg:city":"Hampton",
    "sg:classifiers":[
        {
            "category":"Cafe",
            "type":"Food & Drink"
        }
    ],
    "sg:phone":"+61 7 4697 9393",
    "sg:postcode":"4352",
    "sg:province":"QLD",
    "wof:name":"Rainbow Threads",
    "wof:placetype":"venue"
},
  "geometry": {"coordinates":[151.901443,-28.709553],"type":"Point"}
}