{
  "type": "Feature",
  "properties": {
    "addr:full":"Level 9, 6 Underwood St Circular Quay NSW 2000",
    "addr:housenumber":"6",
    "addr:postcode":"2000",
    "addr:street":"Underwood St Circular Quay",
    "iso:country":"AU",
    "sg:address":"Level 9, 6 Underwood St",
    "sg:city":"Circular Quay",
    "sg:classifiers":[
        {
            "category":"Professional",
            "subcategory":"Employment Agencies",
            "type":"Services"
        }
    ],
    "sg:phone":"+61 2 9247 3600",
    "sg:postcode":"2000",
    "sg:province":"NSW",
    "wof:name":"Taking Care Of Business Australia",
    "wof:placetype":"venue"
},
  "geometry": {"coordinates":[151.208862305,-33.8626060486],"type":"Point"}
}