{
  "type": "Feature",
  "properties": {
    "iso:country":"AU",
    "sg:address":"21 Longford Crt",
    "sg:city":"Springvale",
    "sg:classifiers":[
        {
            "category":"Communications",
            "subcategory":"Newspaper",
            "type":"Services"
        }
    ],
    "sg:phone":"+61 1300 886 587",
    "sg:postcode":"3171",
    "sg:province":"VIC",
    "sg:tags":[
        "whiteboards",
        "chalkboard"
    ],
    "wof:name":"Comprador Pacific Pty Ltd",
    "wof:placetype":"venue"
},
  "geometry": {"coordinates":[145.14793395999999,-37.9288673401],"type":"Point"}
}