{
  "type": "Feature",
  "properties": {
    "addr:full":"79 Formation St Wacol QLD 4076",
    "addr:housenumber":"79",
    "addr:postcode":"4076",
    "addr:street":"Formation St",
    "iso:country":"AU",
    "sg:address":"79 Formation St",
    "sg:city":"Wacol",
    "sg:classifiers":[
        {
            "category":"Retail",
            "subcategory":"Storage",
            "type":"Services"
        }
    ],
    "sg:phone":"+61 7 3271 2277",
    "sg:postcode":"4076",
    "sg:province":"QLD",
    "sg:tags":[
        "removal",
        "furniture"
    ],
    "wof:name":"A.F. Palmer (Removalist) South Queensland Pty Ltd",
    "wof:placetype":"venue"
},
  "geometry": {"coordinates":[152.92713928200001,-27.6035957336],"type":"Point"}
}