{
  "type": "Feature",
  "properties": {
    "addr:full":"1a King St Rockdale NSW 2216",
    "addr:housenumber":"1a",
    "addr:postcode":"2216",
    "addr:street":"King St",
    "iso:country":"AU",
    "sg:address":"1a King St",
    "sg:city":"Rockdale",
    "sg:classifiers":[
        {
            "category":"Real Estate",
            "subcategory":"Real Estate Agent",
            "type":"Services"
        }
    ],
    "sg:phone":"+61 2 9599 9990",
    "sg:postcode":"2216",
    "sg:province":"NSW",
    "wof:name":"Raine & Horne Rockdale",
    "wof:placetype":"venue"
},
  "geometry": {"coordinates":[151.13841199999999,-33.952454],"type":"Point"}
}