{
  "type": "Feature",
  "properties": {
    "iso:country":"AU",
    "sg:address":"9 Oaks Ave",
    "sg:city":"Cremorne",
    "sg:classifiers":[
        {
            "category":"Building & Trades",
            "subcategory":"Construction",
            "type":"Services"
        }
    ],
    "sg:phone":"+61 2 9909 1552",
    "sg:postcode":"2090",
    "sg:province":"NSW",
    "sg:tags":[
        "joiner",
        "carpenter"
    ],
    "wof:name":"Sarkissian K",
    "wof:placetype":"venue"
},
  "geometry": {"coordinates":[151.218215942,-33.8280410767],"type":"Point"}
}