{
  "type": "Feature",
  "properties": {
    "iso:country":"AU",
    "sg:address":"12 Cambridge Rd",
    "sg:city":"Bellerive",
    "sg:classifiers":[
        {
            "category":"Home & Garden",
            "subcategory":"Carpets & Floor Coverings",
            "type":"Retail Goods"
        }
    ],
    "sg:phone":"+61 3 6244 7474",
    "sg:postcode":"7018",
    "sg:province":"TAS",
    "sg:tags":[
        "wood"
    ],
    "wof:name":"Wonders of Wood Floors",
    "wof:placetype":"venue"
},
  "geometry": {"coordinates":[147.366134644,-42.8744773865],"type":"Point"}
}