{
  "type": "Feature",
  "properties": {
    "iso:country":"AU",
    "sg:address":"PO Box 5431",
    "sg:city":"Falcon",
    "sg:classifiers":[
        {
            "category":"Building & Trades",
            "subcategory":"Equipment Rental",
            "type":"Services"
        }
    ],
    "sg:phone":"+61 419 192 726",
    "sg:postcode":"6210",
    "sg:province":"WA",
    "sg:tags":[
        "crane",
        "hire"
    ],
    "wof:name":"Delta Australasia",
    "wof:placetype":"venue"
},
  "geometry": {"coordinates":[115.662193,-32.581299],"type":"Point"}
}