{
  "type": "Feature",
  "properties": {
    "addr:full":"943 King Georges Rd Blakehurst NSW 2221",
    "addr:housenumber":"943",
    "addr:postcode":"2221",
    "addr:street":"King Georges Rd",
    "iso:country":"AU",
    "sg:address":"943 King Georges Rd",
    "sg:city":"Blakehurst",
    "sg:classifiers":[
        {
            "category":"Health Services",
            "subcategory":"Doctor",
            "type":"Services"
        }
    ],
    "sg:phone":"+61 2 9546 1892",
    "sg:postcode":"2221",
    "sg:province":"NSW",
    "sg:tags":[
        "medical",
        "practitioner"
    ],
    "wof:name":"Hampton Stephen",
    "wof:placetype":"venue"
},
  "geometry": {"coordinates":[151.10963439899999,-33.9855918884],"type":"Point"}
}