{
  "type": "Feature",
  "properties": {
    "addr:full":"1 Airlie Ave Prahran East VIC 3181",
    "addr:housenumber":"1",
    "addr:postcode":"3181",
    "addr:street":"Airlie Ave",
    "iso:country":"AU",
    "sg:address":"1 Airlie Ave",
    "sg:city":"Prahran East",
    "sg:classifiers":[
        {
            "category":"Health Services",
            "subcategory":"Dentist",
            "type":"Services"
        }
    ],
    "sg:phone":"+61 3 9509 8662",
    "sg:postcode":"3181",
    "sg:province":"VIC",
    "wof:name":"Minc Richard Charles",
    "wof:placetype":"venue"
},
  "geometry": {"coordinates":[145.008575439,-37.8545608521],"type":"Point"}
}