{
  "type": "Feature",
  "properties": {
    "iso:country":"AU",
    "sg:address":"109 Albury St",
    "sg:city":"Holbrook",
    "sg:classifiers":[
        {
            "category":"Social Services",
            "subcategory":"Child Care",
            "type":"Services"
        }
    ],
    "sg:phone":"+61 2 6036 3149",
    "sg:postcode":"2644",
    "sg:province":"NSW",
    "sg:tags":[
        "breeding",
        "artificial"
    ],
    "wof:name":"Holbrook Breeders Australia",
    "wof:placetype":"venue"
},
  "geometry": {"coordinates":[147.31758117699999,-35.7186012268],"type":"Point"}
}