{
  "type": "Feature",
  "properties": {
    "iso:country":"AU",
    "sg:address":"Unit 5, 20 Russell St",
    "sg:city":"Werribee",
    "sg:classifiers":[
        {
            "category":"Home & Garden",
            "subcategory":"Carpets & Floor Coverings",
            "type":"Retail Goods"
        }
    ],
    "sg:phone":"+61 412 338 539",
    "sg:postcode":"3030",
    "sg:province":"VIC",
    "sg:tags":[
        "layer",
        "planner"
    ],
    "wof:name":"Jerman John",
    "wof:placetype":"venue"
},
  "geometry": {"coordinates":[144.663864,-37.909004],"type":"Point"}
}