{
  "type": "Feature",
  "properties": {
    "addr:full":"7 Chesterman St Moonah TAS 7009",
    "addr:housenumber":"7",
    "addr:postcode":"7009",
    "addr:street":"Chesterman St",
    "iso:country":"AU",
    "sg:address":"7 Chesterman St",
    "sg:city":"Moonah",
    "sg:classifiers":[
        {
            "category":"Wholesale",
            "subcategory":"Machinery & Supplies",
            "type":"Manufacturing & Wholesale Goods"
        }
    ],
    "sg:phone":"+61 3 6216 1500",
    "sg:postcode":"7009",
    "sg:province":"TAS",
    "sg:tags":[
        "instrument",
        "scientific"
    ],
    "wof:name":"Imbros Pty Ltd",
    "wof:placetype":"venue"
},
  "geometry": {"coordinates":[147.29547119099999,-42.8393821716],"type":"Point"}
}