{
  "type": "Feature",
  "properties": {
    "addr:full":"48 Station St Penrith NSW 2750",
    "addr:housenumber":"48",
    "addr:postcode":"2750",
    "addr:street":"Station St",
    "iso:country":"AU",
    "sg:address":"48 Station St",
    "sg:city":"Penrith",
    "sg:classifiers":[
        {
            "category":"Shopping",
            "subcategory":"Pawn Shop",
            "type":"Retail Goods"
        }
    ],
    "sg:phone":"+61 2 4732 3471",
    "sg:postcode":"2750",
    "sg:province":"NSW",
    "sg:tags":[
        "pawnbroker"
    ],
    "wof:name":"Penrith Loan Office",
    "wof:placetype":"venue"
},
  "geometry": {"coordinates":[150.673065186,-33.7462005615],"type":"Point"}
}