{
  "type": "Feature",
  "properties": {
    "addr:full":"211 George St Windsor NSW 2756",
    "addr:housenumber":"211",
    "addr:postcode":"2756",
    "addr:street":"George St",
    "iso:country":"AU",
    "sg:address":"211 George St",
    "sg:city":"Windsor",
    "sg:classifiers":[
        {
            "category":"Real Estate",
            "subcategory":"Real Estate Agent",
            "type":"Services"
        }
    ],
    "sg:phone":"+61 2 4587 7877",
    "sg:postcode":"2756",
    "sg:province":"NSW",
    "wof:name":"PRDnationwide Windsor",
    "wof:placetype":"venue"
},
  "geometry": {"coordinates":[150.81983947800001,-33.6070594788],"type":"Point"}
}