{
  "type": "Feature",
  "properties": {
    "addr:full":"56 Senorita Pde Urangan QLD 4655",
    "addr:housenumber":"56",
    "addr:postcode":"4655",
    "addr:street":"Senorita Pde",
    "iso:country":"AU",
    "sg:address":"56 Senorita Pde",
    "sg:city":"Urangan",
    "sg:classifiers":[
        {
            "category":"Food & Beverages",
            "subcategory":"Meat & Fish",
            "type":"Retail Goods"
        }
    ],
    "sg:phone":"+61 7 4125 3548",
    "sg:postcode":"4655",
    "sg:province":"QLD",
    "sg:tags":[
        "aquaculture"
    ],
    "wof:name":"Australian Aquatic Technology",
    "wof:placetype":"venue"
},
  "geometry": {"coordinates":[152.87785299999999,-25.303545],"type":"Point"}
}