{
  "type": "Feature",
  "properties": {
    "iso:country":"AU",
    "sg:address":"56 Senorita Pde",
    "sg:city":"Urangan",
    "sg:classifiers":[
        {
            "category":"Food & Beverages",
            "subcategory":"Meat & Fish",
            "type":"Retail Goods"
        }
    ],
    "sg:phone":"+61 7 4125 3548",
    "sg:postcode":"4655",
    "sg:province":"QLD",
    "sg:tags":[
        "aquaculture"
    ],
    "wof:name":"Australian Aquatic Technology",
    "wof:placetype":"venue"
},
  "geometry": {"coordinates":[152.877853,-25.303545],"type":"Point"}
}