{
  "type": "Feature",
  "properties": {
    "iso:country":"AU",
    "sg:address":"58 Riverside Drv",
    "sg:city":"Fulham",
    "sg:classifiers":[
        {
            "category":"Home & Garden",
            "subcategory":"Building Materials",
            "type":"Retail Goods"
        }
    ],
    "sg:phone":"+61 8 8355 4472",
    "sg:postcode":"5024",
    "sg:province":"SA",
    "sg:tags":[
        "lawn",
        "cutting",
        "maintenance"
    ],
    "wof:name":"Barnes Yards",
    "wof:placetype":"venue"
},
  "geometry": {"coordinates":[138.510955811,-34.9221343994],"type":"Point"}
}