{
  "type": "Feature",
  "properties": {
    "addr:full":"Cnr Eugarie St & Sunshine Beach Rd Noosa Heads QLD 4567",
    "addr:postcode":"4567",
    "addr:street":"Cnr Eugarie St &;Beach Rd",
    "iso:country":"AU",
    "sg:address":"Cnr Eugarie St & Sunshine Beach Rd",
    "sg:city":"Noosa Heads",
    "sg:classifiers":[
        {
            "category":"Shopping",
            "subcategory":"Clothing, Apparel, & Fashions",
            "type":"Retail Goods"
        }
    ],
    "sg:phone":"+61 7 5440 8866",
    "sg:postcode":"4567",
    "sg:province":"QLD",
    "sg:tags":[
        "textile",
        "designer"
    ],
    "wof:name":"Affirmative Designs",
    "wof:placetype":"venue"
},
  "geometry": {"coordinates":[153.09304809599999,-26.3981742859],"type":"Point"}
}