{
  "type": "Feature",
  "properties": {
    "iso:country":"AU",
    "sg:address":"2 - 6 Williams Cct",
    "sg:city":"Pooraka",
    "sg:classifiers":[
        {
            "category":"Professional",
            "type":"Services"
        }
    ],
    "sg:phone":"+61 8 8262 6269",
    "sg:postcode":"5095",
    "sg:province":"SA",
    "sg:tags":[
        "transport"
    ],
    "sg:website":"http://www.yellowcorporation.com.au",
    "wof:name":"Aussiefast Transport Solutions",
    "wof:placetype":"venue"
},
  "geometry": {"coordinates":[138.62690734899999,-34.8242683411],"type":"Point"}
}