{
  "type": "Feature",
  "properties": {
    "addr:full":"Shp 1/ 141 Waverley Rd Malvern East VIC 3145",
    "addr:housenumber":"/ 141",
    "addr:postcode":"3145",
    "addr:street":"Waverley Rd",
    "iso:country":"AU",
    "sg:address":"Shp 1/ 141 Waverley Rd",
    "sg:city":"Malvern East",
    "sg:classifiers":[
        {
            "category":"Cafe",
            "type":"Food & Drink"
        }
    ],
    "sg:phone":"+61 3 9571 1188",
    "sg:postcode":"3145",
    "sg:province":"VIC",
    "wof:name":"Cafe Tosh",
    "wof:placetype":"venue"
},
  "geometry": {"coordinates":[145.04942321799999,-37.8759613037],"type":"Point"}
}