{
  "type": "Feature",
  "properties": {
    "addr:full":"4 Wilma Crt Beaconsfield VIC 3807",
    "addr:housenumber":"4",
    "addr:postcode":"3807",
    "addr:street":"Wilma Crt",
    "iso:country":"AU",
    "sg:address":"4 Wilma Crt",
    "sg:city":"Beaconsfield",
    "sg:classifiers":[
        {
            "category":"Building & Trades",
            "subcategory":"Landscaping Services",
            "type":"Services"
        }
    ],
    "sg:phone":"+61 409 417 910",
    "sg:postcode":"3807",
    "sg:province":"VIC",
    "sg:tags":[
        "stump",
        "tree",
        "felling",
        "removal"
    ],
    "wof:name":"Beaconsfield Tree Services",
    "wof:placetype":"venue"
},
  "geometry": {"coordinates":[145.37515258799999,-38.0453605652],"type":"Point"}
}