{
  "type": "Feature",
  "properties": {
    "addr:full":"8 Hugh St Belmore NSW 2192",
    "addr:housenumber":"8",
    "addr:postcode":"2192",
    "addr:street":"Hugh St",
    "iso:country":"AU",
    "sg:address":"8 Hugh St",
    "sg:city":"Belmore",
    "sg:classifiers":[
        {
            "category":"Building & Trades",
            "subcategory":"Equipment Rental",
            "type":"Services"
        }
    ],
    "sg:phone":"+61 2 9703 2015",
    "sg:postcode":"2192",
    "sg:province":"NSW",
    "sg:tags":[
        "party",
        "hire"
    ],
    "wof:name":"Funtime Disco",
    "wof:placetype":"venue"
},
  "geometry": {"coordinates":[151.08132900000001,-33.909119],"type":"Point"}
}