{
  "type": "Feature",
  "properties": {
    "iso:country":"AU",
    "sg:address":"1- 4 Tangerine Crt",
    "sg:city":"Mt Martha",
    "sg:classifiers":[
        {
            "category":"Travel",
            "subcategory":"Hostel",
            "type":"Entertainment"
        }
    ],
    "sg:phone":"+61 3 5973 6499",
    "sg:postcode":"3934",
    "sg:province":"VIC",
    "sg:tags":[
        "home"
    ],
    "wof:name":"Camellia Court",
    "wof:placetype":"venue"
},
  "geometry": {"coordinates":[145.054885864,-38.2553062439],"type":"Point"}
}