{
  "type": "Feature",
  "properties": {
    "addr:full":"PO Box 119 Kurrajong NSW 2758",
    "addr:postcode":"2758",
    "iso:country":"AU",
    "sg:address":"PO Box 119",
    "sg:city":"Kurrajong",
    "sg:classifiers":[
        {
            "category":"Utilities",
            "subcategory":"Water",
            "type":"Services"
        }
    ],
    "sg:phone":"+61 2 4573 1948",
    "sg:postcode":"2758",
    "sg:province":"NSW",
    "sg:tags":[
        "hot",
        "system"
    ],
    "wof:name":"Terry Oehm Plumbing Services",
    "wof:placetype":"venue"
},
  "geometry": {"coordinates":[150.66041564899999,-33.5519294739],"type":"Point"}
}