{
  "type": "Feature",
  "properties": {
    "iso:country":"AU",
    "sg:address":"26 Windsor Rd",
    "sg:city":"Cronulla",
    "sg:classifiers":[
        {
            "category":"Professional",
            "type":"Services"
        }
    ],
    "sg:phone":"+61 411 519 353",
    "sg:postcode":"2230",
    "sg:province":"NSW",
    "sg:tags":[
        "valuer"
    ],
    "wof:name":"Casemore Valuations Pty Ltd",
    "wof:placetype":"venue"
},
  "geometry": {"coordinates":[151.14932250999999,-34.0635681152],"type":"Point"}
}