{
  "type": "Feature",
  "properties": {
    "iso:country":"AU",
    "sg:address":"29 Commercial Drv",
    "sg:city":"Thomastown",
    "sg:classifiers":[
        {
            "category":"Manufacturing",
            "subcategory":"Tools & Machinery",
            "type":"Manufacturing & Wholesale Goods"
        }
    ],
    "sg:phone":"+61 3 9466 2229",
    "sg:postcode":"3074",
    "sg:province":"VIC",
    "sg:tags":[
        "toolmaker"
    ],
    "wof:name":"Nord Engineering Pty Ltd",
    "wof:placetype":"venue"
},
  "geometry": {"coordinates":[145.041946411,-37.6913490295],"type":"Point"}
}