{
  "type": "Feature",
  "properties": {
    "addr:full":"8 Hearne St Mortdale NSW 2223",
    "addr:housenumber":"8",
    "addr:postcode":"2223",
    "addr:street":"Hearne St",
    "iso:country":"AU",
    "sg:address":"8 Hearne St",
    "sg:city":"Mortdale",
    "sg:classifiers":[
        {
            "category":"Banks & Credit Unions",
            "subcategory":"Bureau De Change",
            "type":"Services"
        }
    ],
    "sg:phone":"+61 2 9584 9278",
    "sg:postcode":"2223",
    "sg:province":"NSW",
    "sg:tags":[
        "repairs",
        "part",
        "appliance",
        "electrical"
    ],
    "wof:name":"Electrical Maintenance Services",
    "wof:placetype":"venue"
},
  "geometry": {"coordinates":[151.067825317,-33.965007782],"type":"Point"}
}