{
  "type": "Feature",
  "properties": {
    "addr:full":"480 Reservoir Rd Pettavel VIC 3221",
    "addr:housenumber":"480",
    "addr:postcode":"3221",
    "addr:street":"Reservoir Rd",
    "iso:country":"AU",
    "sg:address":"480 Reservoir Rd",
    "sg:city":"Pettavel",
    "sg:classifiers":[
        {
            "category":"Building & Trades",
            "subcategory":"Landscaping Services",
            "type":"Services"
        }
    ],
    "sg:phone":"+61 3 5266 1376",
    "sg:postcode":"3221",
    "sg:province":"VIC",
    "sg:tags":[
        "grazier"
    ],
    "wof:name":"Emmerson H G & J A",
    "wof:placetype":"venue"
},
  "geometry": {"coordinates":[144.24641399999999,-38.209587],"type":"Point"}
}