{
  "type": "Feature",
  "properties": {
    "addr:full":"Unit 1, 3 Techno Park Drv Williamstown VIC 3016",
    "addr:housenumber":"3",
    "addr:postcode":"3016",
    "addr:street":"Techno Park Drv",
    "iso:country":"AU",
    "sg:address":"Unit 1, 3 Techno Park Drv",
    "sg:city":"Williamstown",
    "sg:classifiers":[
        {
            "category":"Professional",
            "subcategory":"Testing Lab",
            "type":"Services"
        }
    ],
    "sg:phone":"+61 3 9397 3888",
    "sg:postcode":"3016",
    "sg:province":"VIC",
    "sg:tags":[
        "inspection"
    ],
    "wof:name":"PNDT",
    "wof:placetype":"venue"
},
  "geometry": {"coordinates":[144.858276367,-37.8553237915],"type":"Point"}
}