{
  "type": "Feature",
  "properties": {
    "addr:full":"60a Leather St Breakwater VIC 3219",
    "addr:housenumber":"60a",
    "addr:postcode":"3219",
    "addr:street":"Leather St",
    "iso:country":"AU",
    "sg:address":"60a Leather St",
    "sg:city":"Breakwater",
    "sg:classifiers":[
        {
            "category":"Home & Garden",
            "subcategory":"Building Materials",
            "type":"Retail Goods"
        }
    ],
    "sg:phone":"+61 3 5248 7759",
    "sg:postcode":"3219",
    "sg:province":"VIC",
    "sg:tags":[
        "plaster",
        "plasterboard",
        "supply"
    ],
    "wof:name":"Northern Cornice",
    "wof:placetype":"venue"
},
  "geometry": {"coordinates":[144.37886047399999,-38.1861572266],"type":"Point"}
}