{
  "type": "Feature",
  "properties": {
    "iso:country":"AU",
    "sg:address":"Windsor Rd",
    "sg:city":"Clarendon",
    "sg:classifiers":[
        {
            "category":"Communications",
            "subcategory":"News Services",
            "type":"Services"
        }
    ],
    "sg:phone":"+61 2 4588 5896",
    "sg:postcode":"2756",
    "sg:province":"NSW",
    "sg:tags":[
        "information",
        "tourist",
        "attractions"
    ],
    "wof:name":"Hawkesbury Valley Visitors Centre",
    "wof:placetype":"venue"
},
  "geometry": {"coordinates":[150.78659057600001,-33.6073265076],"type":"Point"}
}