{
  "type": "Feature",
  "properties": {
    "iso:country":"AU",
    "sg:address":"75 Mount Barker Rd",
    "sg:city":"Stirling",
    "sg:classifiers":[
        {
            "category":"Fast Food",
            "type":"Food & Drink"
        }
    ],
    "sg:phone":"+61 8 8339 5735",
    "sg:postcode":"5152",
    "sg:province":"SA",
    "sg:tags":[
        "away",
        "take"
    ],
    "wof:name":"Stirling Chickens",
    "wof:placetype":"venue"
},
  "geometry": {"coordinates":[138.722122192,-35.0080032349],"type":"Point"}
}