{
  "type": "Feature",
  "properties": {
    "addr:full":"86 Conway St Lismore NSW 2480",
    "addr:housenumber":"86",
    "addr:postcode":"2480",
    "addr:street":"Conway St",
    "iso:country":"AU",
    "sg:address":"86 Conway St",
    "sg:city":"Lismore",
    "sg:classifiers":[
        {
            "category":"Structure",
            "subcategory":"Bridge",
            "type":"Public Place"
        }
    ],
    "sg:phone":"+61 2 6621 5981",
    "sg:postcode":"2480",
    "sg:province":"NSW",
    "sg:tags":[
        "chainsaw",
        "brushcutters"
    ],
    "wof:name":"Ongmac",
    "wof:placetype":"venue"
},
  "geometry": {"coordinates":[153.280395508,-28.8134422302],"type":"Point"}
}