{
  "type": "Feature",
  "properties": {
    "addr:full":"Unit 31 18 Buckleys Rd Winston Hills NSW 2153",
    "addr:housenumber":"18",
    "addr:postcode":"2153",
    "addr:street":"Buckleys Rd",
    "iso:country":"AU",
    "sg:address":"Unit 31 18 Buckleys Rd",
    "sg:city":"Winston Hills",
    "sg:classifiers":[
        {
            "category":"Building & Trades",
            "subcategory":"Cleaning & Sanitation",
            "type":"Services"
        }
    ],
    "sg:phone":"+61 2 9620 4364",
    "sg:postcode":"2153",
    "sg:province":"NSW",
    "sg:tags":[
        "grease",
        "trap"
    ],
    "wof:name":"Coates Domestic Grease Trap Cleaning",
    "wof:placetype":"venue"
},
  "geometry": {"coordinates":[150.970794678,-33.776424408],"type":"Point"}
}