{
  "type": "Feature",
  "properties": {
    "iso:country":"AU",
    "sg:address":"64 Bronte Rd",
    "sg:city":"Bondi Junction",
    "sg:classifiers":[
        {
            "category":"Home & Garden",
            "subcategory":"Carpets & Floor Coverings",
            "type":"Retail Goods"
        }
    ],
    "sg:phone":"+61 2 9387 3588",
    "sg:postcode":"2022",
    "sg:province":"NSW",
    "sg:tags":[
        "layer",
        "planner"
    ],
    "wof:name":"Univers Carpet Wholesalers",
    "wof:placetype":"venue"
},
  "geometry": {"coordinates":[151.25030517600001,-33.8945960999],"type":"Point"}
}