{
  "type": "Feature",
  "properties": {
    "addr:full":"18 Strabane Ave Box Hill North VIC 3129",
    "addr:housenumber":"18",
    "addr:postcode":"3129",
    "addr:street":"Strabane Ave",
    "iso:country":"AU",
    "sg:address":"18 Strabane Ave",
    "sg:city":"Box Hill North",
    "sg:classifiers":[
        {
            "category":"Building & Trades",
            "subcategory":"Landscaping Services",
            "type":"Services"
        }
    ],
    "sg:phone":"+61 412 884 835",
    "sg:postcode":"3129",
    "sg:province":"VIC",
    "sg:tags":[
        "designer",
        "landscape",
        "contractor"
    ],
    "wof:name":"Generally Gardens",
    "wof:placetype":"venue"
},
  "geometry": {"coordinates":[145.11346435600001,-37.8072319031],"type":"Point"}
}