{
  "type": "Feature",
  "properties": {
    "addr:full":"89 St Leonards Rd St Leonards TAS 7250",
    "addr:housenumber":"89",
    "addr:postcode":"7250",
    "addr:street":"St Leonards Rd",
    "iso:country":"AU",
    "sg:address":"89 St Leonards Rd",
    "sg:city":"St Leonards",
    "sg:classifiers":[
        {
            "category":"Building & Trades",
            "subcategory":"Equipment Rental",
            "type":"Services"
        }
    ],
    "sg:phone":"+61 3 6339 4554",
    "sg:postcode":"7250",
    "sg:province":"TAS",
    "sg:tags":[
        "renting",
        "trailer"
    ],
    "wof:name":"SC Trailer Hire",
    "wof:placetype":"venue"
},
  "geometry": {"coordinates":[147.18281555199999,-41.4437561035],"type":"Point"}
}