{
  "type": "Feature",
  "properties": {
    "iso:country":"AU",
    "sg:address":"2/ 8 Hornet Pl",
    "sg:city":"Burleigh",
    "sg:classifiers":[
        {
            "category":"Retail",
            "subcategory":"Auto Repair",
            "type":"Services"
        }
    ],
    "sg:phone":"+61 7 5522 0924",
    "sg:postcode":"4220",
    "sg:province":"QLD",
    "sg:tags":[
        "body",
        "builder",
        "motor"
    ],
    "wof:name":"GPT Truck Bodies",
    "wof:placetype":"venue"
},
  "geometry": {"coordinates":[153.41827392600001,-28.1041984558],"type":"Point"}
}