{
  "type": "Feature",
  "properties": {
    "addr:full":"6 Tang St Coconut Grove NT 0810",
    "addr:housenumber":"6",
    "addr:postcode":"0810",
    "addr:street":"Tang St",
    "iso:country":"AU",
    "sg:address":"6 Tang St",
    "sg:city":"Coconut Grove",
    "sg:classifiers":[
        {
            "category":"Professional",
            "subcategory":"Detective & Security Services",
            "type":"Services"
        }
    ],
    "sg:phone":"+61 8 8948 2441",
    "sg:postcode":"0810",
    "sg:province":"NT",
    "sg:tags":[
        "equipment",
        "window",
        "doors"
    ],
    "wof:name":"System Homes Pty Ltd",
    "wof:placetype":"venue"
},
  "geometry": {"coordinates":[130.85333251899999,-12.3995952606],"type":"Point"}
}