{
  "type": "Feature",
  "properties": {
    "addr:full":"PO Box 110 Highgate SA 5063",
    "addr:postcode":"5063",
    "iso:country":"AU",
    "sg:address":"PO Box 110",
    "sg:city":"Highgate",
    "sg:classifiers":[
        {
            "category":"Professional",
            "subcategory":"Management & Consulting",
            "type":"Services"
        }
    ],
    "sg:phone":"+61 8 8370 2855",
    "sg:postcode":"5063",
    "sg:province":"SA",
    "sg:tags":[
        "consultant",
        "relocation"
    ],
    "wof:name":"Expat International",
    "wof:placetype":"venue"
},
  "geometry": {"coordinates":[138.62623596200001,-34.9617004395],"type":"Point"}
}