{
  "type": "Feature",
  "properties": {
    "iso:country":"AU",
    "sg:address":"25 Evelyn St",
    "sg:city":"Newstead",
    "sg:classifiers":[
        {
            "category":"Insurance",
            "subcategory":"Insurance Agent",
            "type":"Services"
        }
    ],
    "sg:phone":"+61 7 3000 5555",
    "sg:postcode":"4006",
    "sg:province":"QLD",
    "sg:tags":[
        "broker"
    ],
    "wof:name":"Jardine Lloyd Thompson Pty Ltd",
    "wof:placetype":"venue"
},
  "geometry": {"coordinates":[153.04411315900001,-27.4472179413],"type":"Point"}
}