{
  "type": "Feature",
  "properties": {
    "addr:full":"Shp2/ 84 Cemetery Rd Eastern Heights QLD 4305",
    "addr:housenumber":"84",
    "addr:postcode":"4305",
    "addr:street":"Cemetery Rd",
    "iso:country":"AU",
    "sg:address":"Shp2/ 84 Cemetery Rd",
    "sg:city":"Eastern Heights",
    "sg:classifiers":[
        {
            "category":"Fast Food",
            "type":"Food & Drink"
        }
    ],
    "sg:phone":"+61 7 3281 4886",
    "sg:postcode":"4305",
    "sg:province":"QLD",
    "sg:tags":[
        "away",
        "take"
    ],
    "wof:name":"Eastern Suburbs Snack Bar",
    "wof:placetype":"venue"
},
  "geometry": {"coordinates":[152.772537231,-27.632686615],"type":"Point"}
}