{
  "type": "Feature",
  "properties": {
    "iso:country":"AU",
    "sg:address":"4/ 21 Rowe St",
    "sg:city":"Eastwood",
    "sg:classifiers":[
        {
            "category":"Professional",
            "subcategory":"Engineering",
            "type":"Services"
        }
    ],
    "sg:phone":"+61 2 9858 4408",
    "sg:postcode":"2122",
    "sg:province":"NSW",
    "sg:tags":[
        "consulting",
        "engineer"
    ],
    "wof:name":"Alexelen Pty Ltd",
    "wof:placetype":"venue"
},
  "geometry": {"coordinates":[151.08534240700001,-33.7905464172],"type":"Point"}
}