{
  "type": "Feature",
  "properties": {
    "addr:full":"45- 47 Hunter St Hornsby NSW 2077",
    "addr:housenumber":"47",
    "addr:postcode":"2077",
    "addr:street":"Hunter St",
    "iso:country":"AU",
    "sg:address":"45- 47 Hunter St",
    "sg:city":"Hornsby",
    "sg:classifiers":[
        {
            "category":"Shopping",
            "subcategory":"Optical Goods",
            "type":"Retail Goods"
        }
    ],
    "sg:phone":"+61 2 9489 4480",
    "sg:postcode":"2077",
    "sg:province":"NSW",
    "sg:tags":[
        "supply"
    ],
    "wof:name":"Mirage Eyewear Pty Ltd",
    "wof:placetype":"venue"
},
  "geometry": {"coordinates":[151.100799561,-33.702091217],"type":"Point"}
}