{
  "type": "Feature",
  "properties": {
    "addr:full":"Shop 1073a Westfield Helensvale Shopping Centre, Town Centre Dve Helensvale QLD 4212",
    "addr:housenumber":"1073a",
    "addr:postcode":"4212",
    "addr:street":"Westfield;Town Centre Dve",
    "iso:country":"AU",
    "sg:address":"Shop 1073a Westfield Helensvale Shopping Centre, Town Centre Dve",
    "sg:city":"Helensvale",
    "sg:classifiers":[
        {
            "category":"Travel",
            "subcategory":"Travel Agent",
            "type":"Entertainment"
        }
    ],
    "sg:phone":"+61 7 5573 7237",
    "sg:postcode":"4212",
    "sg:province":"QLD",
    "sg:tags":[
        "consultant"
    ],
    "wof:name":"Escape Travel",
    "wof:placetype":"venue"
},
  "geometry": {"coordinates":[153.338256836,-27.9241104126],"type":"Point"}
}