{
  "type": "Feature",
  "properties": {
    "addr:full":"119 Victoria St Taree NSW 2430",
    "addr:housenumber":"119",
    "addr:postcode":"2430",
    "addr:street":"Victoria St",
    "iso:country":"AU",
    "sg:address":"119 Victoria St",
    "sg:city":"Taree",
    "sg:classifiers":[
        {
            "category":"Personal",
            "subcategory":"Barber",
            "type":"Services"
        }
    ],
    "sg:phone":"+61 2 6552 2556",
    "sg:postcode":"2430",
    "sg:province":"NSW",
    "wof:name":"Love's Hairdressing",
    "wof:placetype":"venue"
},
  "geometry": {"coordinates":[152.46229600000001,-31.912502],"type":"Point"}
}