{
  "type": "Feature",
  "properties": {
    "addr:full":"62 Radnor St Camberwell VIC 3124",
    "addr:housenumber":"62",
    "addr:postcode":"3124",
    "addr:street":"Radnor St",
    "iso:country":"AU",
    "sg:address":"62 Radnor St",
    "sg:city":"Camberwell",
    "sg:classifiers":[
        {
            "category":"Professional",
            "subcategory":"Computer Services",
            "type":"Services"
        }
    ],
    "sg:phone":"+61 3 9809 4250",
    "sg:postcode":"3124",
    "sg:province":"VIC",
    "sg:tags":[
        "package",
        "software"
    ],
    "wof:name":"Software Systems Technology",
    "wof:placetype":"venue"
},
  "geometry": {"coordinates":[145.061035156,-37.8440437317],"type":"Point"}
}