{
  "type": "Feature",
  "properties": {
    "addr:full":"134 Tarleton St Devonport East TAS 7310",
    "addr:housenumber":"134",
    "addr:postcode":"7310",
    "addr:street":"Tarleton St",
    "iso:country":"AU",
    "sg:address":"134 Tarleton St",
    "sg:city":"Devonport East",
    "sg:classifiers":[
        {
            "category":"Wholesale",
            "subcategory":"Seafood",
            "type":"Manufacturing & Wholesale Goods"
        }
    ],
    "sg:phone":"+61 3 6427 9033",
    "sg:postcode":"7310",
    "sg:province":"TAS",
    "sg:tags":[
        "fish"
    ],
    "wof:name":"Petuna Seafoods",
    "wof:placetype":"venue"
},
  "geometry": {"coordinates":[146.37159729000001,-41.1851959229],"type":"Point"}
}