{
  "type": "Feature",
  "properties": {
    "iso:country":"AU",
    "sg:address":"10 The Outlook Rd",
    "sg:city":"Surfside",
    "sg:classifiers":[
        {
            "category":"Professional",
            "subcategory":"Art Services",
            "type":"Services"
        }
    ],
    "sg:phone":"+61 2 4472 7731",
    "sg:postcode":"2536",
    "sg:province":"NSW",
    "sg:tags":[
        "interior",
        "decorator"
    ],
    "wof:name":"Kloos Peter",
    "wof:placetype":"venue"
},
  "geometry": {"coordinates":[150.19369506800001,-35.6918983459],"type":"Point"}
}