{
  "type": "Feature",
  "properties": {
    "addr:full":"5258 Wattle Tree Rd Holgate NSW 2250",
    "addr:postcode":"5258;2250",
    "addr:street":"Wattle Tree Rd",
    "iso:country":"AU",
    "sg:address":"5258 Wattle Tree Rd",
    "sg:city":"Holgate",
    "sg:classifiers":[
        {
            "category":"Farming",
            "subcategory":"Vineyard",
            "type":"Manufacturing & Wholesale Goods"
        }
    ],
    "sg:phone":"+61 2 4365 0768",
    "sg:postcode":"2250",
    "sg:province":"NSW",
    "sg:tags":[
        "winery"
    ],
    "wof:name":"Firescreek Winery",
    "wof:placetype":"venue"
},
  "geometry": {"coordinates":[151.40887451200001,-33.4050064087],"type":"Point"}
}