{
  "type": "Feature",
  "properties": {
    "addr:full":"35 Redden St Portsmith QLD 4870",
    "addr:housenumber":"35",
    "addr:postcode":"4870",
    "addr:street":"Redden St Portsmith",
    "iso:country":"AU",
    "sg:address":"35 Redden St",
    "sg:city":"Portsmith",
    "sg:classifiers":[
        {
            "category":"Autos & Motor Vehicles",
            "subcategory":"Automobile Sales",
            "type":"Retail Goods"
        }
    ],
    "sg:phone":"+61 7 4035 1644",
    "sg:postcode":"4870",
    "sg:province":"QLD",
    "sg:tags":[
        "bus",
        "used",
        "truck"
    ],
    "wof:name":"Tropical Trucks & Trailers",
    "wof:placetype":"venue"
},
  "geometry": {"coordinates":[145.76968383799999,-16.9431343079],"type":"Point"}
}