{
  "type": "Feature",
  "properties": {
    "iso:country":"AU",
    "sg:address":"PO Box 335",
    "sg:city":"Park Holme",
    "sg:classifiers":[
        {
            "category":"Retail",
            "subcategory":"Driving School",
            "type":"Services"
        }
    ],
    "sg:phone":"+61 413 949 871",
    "sg:postcode":"5043",
    "sg:province":"SA",
    "wof:name":"Recommended Driver Training",
    "wof:placetype":"venue"
},
  "geometry": {"coordinates":[138.556793,-34.990849],"type":"Point"}
}