{
  "type": "Feature",
  "properties": {
    "addr:full":"215 Sixth Ave Austral NSW 2171",
    "addr:housenumber":"215",
    "addr:postcode":"2171",
    "addr:street":"Sixth Ave Austral",
    "iso:country":"AU",
    "sg:address":"215 Sixth Ave",
    "sg:city":"Austral",
    "sg:classifiers":[
        {
            "category":"Real Estate",
            "subcategory":"Developer",
            "type":"Services"
        }
    ],
    "sg:phone":"+61 2 9606 9970",
    "sg:postcode":"2171",
    "sg:province":"NSW",
    "sg:tags":[
        "development"
    ],
    "wof:name":"Dhillon Developments",
    "wof:placetype":"venue"
},
  "geometry": {"coordinates":[150.808502197,-33.9441833496],"type":"Point"}
}