{
  "type": "Feature",
  "properties": {
    "addr:full":"7 Stafford St Thargomindah QLD 4492",
    "addr:housenumber":"7",
    "addr:postcode":"4492",
    "addr:street":"Stafford St",
    "iso:country":"AU",
    "sg:address":"7 Stafford St",
    "sg:city":"Thargomindah",
    "sg:classifiers":[
        {
            "category":"Commercial Area",
            "type":"Public Place"
        }
    ],
    "sg:phone":"+61 7 4655 3300",
    "sg:postcode":"4492",
    "sg:province":"QLD",
    "sg:tags":[
        "heavy",
        "carrier"
    ],
    "wof:name":"Hatch Cattle Transport",
    "wof:placetype":"venue"
},
  "geometry": {"coordinates":[143.822433472,-27.9925384521],"type":"Point"}
}