{
  "type": "Feature",
  "properties": {
    "addr:full":"Unit 2/ 40 Kremzow Rd Brendale QLD 4500",
    "addr:housenumber":"40",
    "addr:postcode":"4500",
    "addr:street":"Kremzow Rd",
    "iso:country":"AU",
    "sg:address":"Unit 2/ 40 Kremzow Rd",
    "sg:city":"Brendale",
    "sg:classifiers":[
        {
            "category":"Professional",
            "subcategory":"Computer Services",
            "type":"Services"
        }
    ],
    "sg:phone":"+61 7 3205 8444",
    "sg:postcode":"4500",
    "sg:province":"QLD",
    "sg:tags":[
        "repairs",
        "upgrade",
        "equipment"
    ],
    "wof:name":"Datashield",
    "wof:placetype":"venue"
},
  "geometry": {"coordinates":[152.98475647000001,-27.3178653717],"type":"Point"}
}