{
  "type": "Feature",
  "properties": {
    "iso:country":"AU",
    "sg:address":"Oceana Walk 55 Lake St",
    "sg:city":"Cairns",
    "sg:classifiers":[
        {
            "category":"Personal",
            "subcategory":"Beauty Salon",
            "type":"Services"
        }
    ],
    "sg:phone":"+61 7 4051 2185",
    "sg:postcode":"4870",
    "sg:province":"QLD",
    "sg:tags":[
        "hairdresser"
    ],
    "wof:name":"Jo's Scissors Of Gold Salon",
    "wof:placetype":"venue"
},
  "geometry": {"coordinates":[145.77679443400001,-16.9234466553],"type":"Point"}
}