{
  "type": "Feature",
  "properties": {
    "iso:country":"AU",
    "sg:address":"15 Herbert St",
    "sg:city":"Invermay",
    "sg:classifiers":[
        {
            "category":"Professional",
            "subcategory":"Detective & Security Services",
            "type":"Services"
        }
    ],
    "sg:phone":"+61 3 6331 9246",
    "sg:postcode":"7248",
    "sg:province":"TAS",
    "sg:tags":[
        "equipment",
        "window",
        "doors"
    ],
    "wof:name":"R.I.H. Screens",
    "wof:placetype":"venue"
},
  "geometry": {"coordinates":[147.14125060999999,-41.4208526611],"type":"Point"}
}