{
  "type": "Feature",
  "properties": {
    "addr:full":"Cnr Yarrara & Ramsay Rds Pennant Hills NSW 2120",
    "addr:postcode":"2120",
    "addr:street":"Cnr Yarrara & Ramsay Rds",
    "iso:country":"AU",
    "sg:address":"Cnr Yarrara & Ramsay Rds",
    "sg:city":"Pennant Hills",
    "sg:classifiers":[
        {
            "category":"Education",
            "subcategory":"Dance Studio",
            "type":"Public Place"
        }
    ],
    "sg:phone":"+61 2 9557 7751",
    "sg:postcode":"2120",
    "sg:province":"NSW",
    "sg:tags":[
        "venue",
        "tuition"
    ],
    "wof:name":"Latin Motion Dance Academy",
    "wof:placetype":"venue"
},
  "geometry": {"coordinates":[151.07182312,-33.7382545471],"type":"Point"}
}