{
  "type": "Feature",
  "properties": {
    "iso:country":"AU",
    "sg:address":"55 Wavehill Ave",
    "sg:city":"Windsor Downs",
    "sg:classifiers":[
        {
            "category":"Building & Trades",
            "subcategory":"Plumbing",
            "type":"Services"
        }
    ],
    "sg:phone":"+61 2 4572 5509",
    "sg:postcode":"2756",
    "sg:province":"NSW",
    "sg:tags":[
        "plumber",
        "gasfitters"
    ],
    "wof:name":"Hawks View Plumbing Pty Ltd",
    "wof:placetype":"venue"
},
  "geometry": {"coordinates":[150.80589294399999,-33.6639785767],"type":"Point"}
}