{
  "type": "Feature",
  "properties": {
    "iso:country":"AU",
    "sg:address":"298 Chapman Rd",
    "sg:city":"Geraldton",
    "sg:classifiers":[
        {
            "category":"Food & Beverages",
            "subcategory":"Liquor & Beverages",
            "type":"Retail Goods"
        }
    ],
    "sg:phone":"+61 8 9921 2544",
    "sg:postcode":"6530",
    "sg:province":"WA",
    "sg:tags":[
        "store"
    ],
    "wof:name":"Route 66 Drive-Ins",
    "wof:placetype":"venue"
},
  "geometry": {"coordinates":[114.62680053699999,-28.7188224792],"type":"Point"}
}