{
  "type": "Feature",
  "properties": {
    "addr:full":"191 St Georges Tce Perth WA 6000",
    "addr:housenumber":"191",
    "addr:postcode":"6000",
    "addr:street":"St Georges Tce",
    "iso:country":"AU",
    "sg:address":"191 St",
    "sg:city":"Georges Tce Perth",
    "sg:classifiers":[
        {
            "category":"Shopping",
            "subcategory":"Antiques",
            "type":"Retail Goods"
        }
    ],
    "sg:phone":"+61 8 9481 6022",
    "sg:postcode":"6000",
    "sg:province":"WA",
    "sg:tags":[
        "collectable",
        "memorabilia"
    ],
    "wof:name":"The Gallereum",
    "wof:placetype":"venue"
},
  "geometry": {"coordinates":[115.853172302,-31.9536991119],"type":"Point"}
}