{
  "type": "Feature",
  "properties": {
    "iso:country":"AU",
    "sg:address":"Shop 8/ Cnr Gooding Drive & Jura Pde",
    "sg:city":"Carrara",
    "sg:classifiers":[
        {
            "category":"Personal",
            "subcategory":"Beauty Salon",
            "type":"Services"
        }
    ],
    "sg:phone":"+61 7 5525 3211",
    "sg:postcode":"4211",
    "sg:province":"QLD",
    "sg:tags":[
        "hairdresser"
    ],
    "wof:name":"Merridown Hair & Beauty",
    "wof:placetype":"venue"
},
  "geometry": {"coordinates":[153.38107299800001,-28.0342235565],"type":"Point"}
}