{
  "type": "Feature",
  "properties": {
    "iso:country":"AU",
    "sg:address":"8 Langton St",
    "sg:city":"Garbutt",
    "sg:classifiers":[
        {
            "category":"Manufacturing",
            "subcategory":"Motor Vehicles & Parts",
            "type":"Manufacturing & Wholesale Goods"
        }
    ],
    "sg:phone":"+61 7 4728 6836",
    "sg:postcode":"4814",
    "sg:province":"QLD",
    "sg:tags":[
        "replacement"
    ],
    "wof:name":"Stengels Crash Repairs",
    "wof:placetype":"venue"
},
  "geometry": {"coordinates":[146.771851,-19.266306],"type":"Point"}
}