{
  "type": "Feature",
  "properties": {
    "iso:country":"AU",
    "sg:address":"246 Dumaresq St",
    "sg:city":"Armidale",
    "sg:classifiers":[
        {
            "category":"Professional",
            "subcategory":"Computer Services",
            "type":"Services"
        }
    ],
    "sg:phone":"+61 2 6772 6274",
    "sg:postcode":"2350",
    "sg:province":"NSW",
    "sg:tags":[
        "repairs",
        "upgrade",
        "equipment"
    ],
    "wof:name":"Rob Dell Computers",
    "wof:placetype":"venue"
},
  "geometry": {"coordinates":[151.653839111,-30.5082263947],"type":"Point"}
}