{
  "type": "Feature",
  "properties": {
    "addr:full":"Level 4, Parkes St Parramatta NSW 2150",
    "addr:postcode":"2150",
    "addr:street":"St",
    "iso:country":"AU",
    "sg:address":"Level 4, Parkes St",
    "sg:city":"Parramatta",
    "sg:classifiers":[
        {
            "category":"Social Services",
            "type":"Services"
        }
    ],
    "sg:phone":"+61 2 9689 3620",
    "sg:postcode":"2150",
    "sg:province":"NSW",
    "sg:tags":[
        "domestic",
        "help"
    ],
    "wof:name":"Home Care Service Of N.S.W.",
    "wof:placetype":"venue"
},
  "geometry": {"coordinates":[150.97250366200001,-33.8492355347],"type":"Point"}
}