{
  "type": "Feature",
  "properties": {
    "iso:country":"AU",
    "sg:address":"2/ 5 Fulham Rd",
    "sg:city":"Rowville",
    "sg:classifiers":[
        {
            "category":"Social Services",
            "subcategory":"Job Training",
            "type":"Services"
        }
    ],
    "sg:phone":"+61 3 9763 9101",
    "sg:postcode":"3178",
    "sg:province":"VIC",
    "sg:tags":[
        "sport"
    ],
    "wof:name":"Prestige Personal Training & Massage",
    "wof:placetype":"venue"
},
  "geometry": {"coordinates":[145.239944458,-37.9190216064],"type":"Point"}
}