{
  "type": "Feature",
  "properties": {
    "addr:full":"PO Box 2039 Rozelle DC NSW 2039",
    "addr:postcode":"2039",
    "iso:country":"AU",
    "sg:address":"PO Box 2039",
    "sg:city":"Rozelle DC",
    "sg:classifiers":[
        {
            "category":"Social Services",
            "subcategory":"Adult Care",
            "type":"Services"
        }
    ],
    "sg:phone":"+61 1300 767 616",
    "sg:postcode":"2039",
    "sg:province":"NSW",
    "sg:tags":[
        "aged"
    ],
    "wof:name":"Doctors Safety Line",
    "wof:placetype":"venue"
},
  "geometry": {"coordinates":[151.174316406,-33.8644981384],"type":"Point"}
}