{
  "type": "Feature",
  "properties": {
    "addr:full":"2/ 12 High St Mansfield VIC 3722",
    "addr:housenumber":"/ 12",
    "addr:postcode":"3722",
    "addr:street":"High St",
    "iso:country":"AU",
    "sg:address":"2/ 12 High St",
    "sg:city":"Mansfield",
    "sg:classifiers":[
        {
            "category":"Health Services",
            "subcategory":"Doctor",
            "type":"Services"
        }
    ],
    "sg:phone":"+61 3 5775 2141",
    "sg:postcode":"3722",
    "sg:province":"VIC",
    "sg:tags":[
        "podiatrist"
    ],
    "wof:name":"Joan T. Carey",
    "wof:placetype":"venue"
},
  "geometry": {"coordinates":[146.092407227,-37.0529632568],"type":"Point"}
}