{
  "type": "Feature",
  "properties": {
    "addr:full":"79 Abernethy Rd Belmont WA 6104",
    "addr:housenumber":"79",
    "addr:postcode":"6104",
    "addr:street":"Abernethy Rd",
    "iso:country":"AU",
    "sg:address":"79 Abernethy Rd",
    "sg:city":"Belmont",
    "sg:classifiers":[
        {
            "category":"Wholesale",
            "subcategory":"Apparel",
            "type":"Manufacturing & Wholesale Goods"
        }
    ],
    "sg:phone":"+61 8 9477 2227",
    "sg:postcode":"6104",
    "sg:province":"WA",
    "sg:tags":[
        "wholesaler",
        "mfrs",
        "uniform"
    ],
    "wof:name":"Embroiderers International",
    "wof:placetype":"venue"
},
  "geometry": {"coordinates":[115.923439026,-31.9513759613],"type":"Point"}
}