{
  "type": "Feature",
  "properties": {
    "addr:full":"141 Kensington Rd Norwood SA 5067",
    "addr:housenumber":"141",
    "addr:postcode":"5067",
    "addr:street":"Kensington Rd",
    "iso:country":"AU",
    "sg:address":"141 Kensington Rd",
    "sg:city":"Norwood",
    "sg:classifiers":[
        {
            "category":"Wholesale",
            "subcategory":"Drugs",
            "type":"Manufacturing & Wholesale Goods"
        }
    ],
    "sg:phone":"+61 8 8362 4855",
    "sg:postcode":"5067",
    "sg:province":"SA",
    "sg:tags":[
        "wholesaler",
        "pharmaceutical",
        "product",
        "mfrs"
    ],
    "wof:name":"Amfac Pty Ltd",
    "wof:placetype":"venue"
},
  "geometry": {"coordinates":[138.64120483400001,-34.92710495],"type":"Point"}
}