{
  "type": "Feature",
  "properties": {
    "addr:full":"55 Chute St Diamond Creek VIC 3089",
    "addr:housenumber":"55",
    "addr:postcode":"3089",
    "addr:street":"Chute St",
    "iso:country":"AU",
    "sg:address":"55 Chute St",
    "sg:city":"Diamond Creek",
    "sg:classifiers":[
        {
            "category":"Cafe",
            "type":"Food & Drink"
        }
    ],
    "sg:phone":"+61 3 9438 5502",
    "sg:postcode":"3089",
    "sg:province":"VIC",
    "wof:name":"Diamond Creek Coffee &#034;n&#034; Crafts",
    "wof:placetype":"venue"
},
  "geometry": {"coordinates":[145.15237400000001,-37.672897],"type":"Point"}
}