{
  "type": "Feature",
  "properties": {
    "iso:country":"AU",
    "sg:address":"Main St",
    "sg:city":"Beenleigh",
    "sg:classifiers":[
        {
            "category":"Food & Beverages",
            "subcategory":"Fruits & Vegetables",
            "type":"Retail Goods"
        }
    ],
    "sg:phone":"+61 7 3287 4483",
    "sg:postcode":"4207",
    "sg:province":"QLD",
    "sg:tags":[
        "greengrocer",
        "fruiterer"
    ],
    "wof:name":"Fresh as Fruit & Veg",
    "wof:placetype":"venue"
},
  "geometry": {"coordinates":[153.20216369600001,-27.7162704468],"type":"Point"}
}