{
  "type": "Feature",
  "properties": {
    "addr:full":"134- 138 Aberdeen St Northbridge WA 6003",
    "addr:housenumber":"138",
    "addr:postcode":"6003",
    "addr:street":"Aberdeen St",
    "iso:country":"AU",
    "sg:address":"134- 138 Aberdeen St",
    "sg:city":"Northbridge",
    "sg:classifiers":[
        {
            "category":"Professional",
            "subcategory":"Computer Services",
            "type":"Services"
        }
    ],
    "sg:phone":"+61 1300 552 055",
    "sg:postcode":"6003",
    "sg:province":"WA",
    "sg:tags":[
        "repairs",
        "upgrade",
        "equipment"
    ],
    "wof:name":"Computer Cybershop",
    "wof:placetype":"venue"
},
  "geometry": {"coordinates":[115.860412598,-31.9470291138],"type":"Point"}
}