{
  "type": "Feature",
  "properties": {
    "addr:full":"40 Raymond St Bankstown NSW 2200",
    "addr:housenumber":"40",
    "addr:postcode":"2200",
    "addr:street":"Raymond St",
    "iso:country":"AU",
    "sg:address":"40 Raymond St",
    "sg:city":"Bankstown",
    "sg:classifiers":[
        {
            "category":"Health Services",
            "subcategory":"Doctor",
            "type":"Services"
        }
    ],
    "sg:phone":"+61 2 9796 7311",
    "sg:postcode":"2200",
    "sg:province":"NSW",
    "sg:tags":[
        "medical",
        "practitioner"
    ],
    "wof:name":"McHugh G",
    "wof:placetype":"venue"
},
  "geometry": {"coordinates":[151.036057,-33.919811],"type":"Point"}
}