{
  "type": "Feature",
  "properties": {
    "iso:country":"AU",
    "sg:address":"257 Wittons Rd",
    "sg:city":"Murgon",
    "sg:classifiers":[
        {
            "category":"Building & Trades",
            "subcategory":"Construction",
            "type":"Services"
        }
    ],
    "sg:phone":"+61 7 4168 1191",
    "sg:postcode":"4605",
    "sg:province":"QLD",
    "sg:tags":[
        "contractor"
    ],
    "wof:name":"Rewald Sel",
    "wof:placetype":"venue"
},
  "geometry": {"coordinates":[151.98550399999999,-26.232414],"type":"Point"}
}