{
  "type": "Feature",
  "properties": {
    "iso:country":"AU",
    "sg:address":"328 Bong Bong St",
    "sg:city":"Bowral",
    "sg:classifiers":[
        {
            "category":"Shopping",
            "subcategory":"Clothing, Apparel, & Fashions",
            "type":"Retail Goods"
        }
    ],
    "sg:phone":"+61 2 4861 2368",
    "sg:postcode":"2576",
    "sg:province":"NSW",
    "sg:tags":[
        "lady",
        "wear"
    ],
    "wof:name":"Snellings Pty Ltd",
    "wof:placetype":"venue"
},
  "geometry": {"coordinates":[150.41784668,-34.4797363281],"type":"Point"}
}