{
  "type": "Feature",
  "properties": {
    "iso:country":"AU",
    "sg:address":"2 Harbourne Rd",
    "sg:city":"Kingsford",
    "sg:classifiers":[
        {
            "category":"Shopping",
            "subcategory":"Computers & Home Electronics",
            "type":"Retail Goods"
        }
    ],
    "sg:phone":"+61 412 129 713",
    "sg:postcode":"2032",
    "sg:province":"NSW",
    "sg:tags":[
        "hardware",
        "equipment"
    ],
    "wof:name":"Simmtek Pty Ltd",
    "wof:placetype":"venue"
},
  "geometry": {"coordinates":[151.22793579099999,-33.9199676514],"type":"Point"}
}