{
  "type": "Feature",
  "properties": {
    "iso:country":"AU",
    "sg:address":"17 Kimberly Rd",
    "sg:city":"Dandenong South",
    "sg:classifiers":[
        {
            "category":"Professional",
            "type":"Services"
        }
    ],
    "sg:phone":"+61 3 9706 4575",
    "sg:postcode":"3175",
    "sg:province":"VIC",
    "sg:tags":[
        "coating",
        "powder"
    ],
    "wof:name":"Excite Powder Coating Services",
    "wof:placetype":"venue"
},
  "geometry": {"coordinates":[145.205245972,-38.0311584473],"type":"Point"}
}