{
  "type": "Feature",
  "properties": {
    "addr:full":"414 High St Northcote VIC 3070",
    "addr:housenumber":"414",
    "addr:postcode":"3070",
    "addr:street":"High St",
    "iso:country":"AU",
    "sg:address":"414 High St",
    "sg:city":"Northcote",
    "sg:classifiers":[
        {
            "category":"Health Services",
            "subcategory":"Doctor",
            "type":"Services"
        }
    ],
    "sg:phone":"+61 3 9482 4211",
    "sg:postcode":"3070",
    "sg:province":"VIC",
    "sg:tags":[
        "medical",
        "practitioner"
    ],
    "wof:name":"Jaimangal Bhim Dr",
    "wof:placetype":"venue"
},
  "geometry": {"coordinates":[144.999359,-37.767612],"type":"Point"}
}