{
  "type": "Feature",
  "properties": {
    "addr:full":"10 Livingstone St Lawson NSW 2783",
    "addr:housenumber":"10",
    "addr:postcode":"2783",
    "addr:street":"Livingstone St",
    "iso:country":"AU",
    "sg:address":"10 Livingstone St",
    "sg:city":"Lawson",
    "sg:classifiers":[
        {
            "category":"Social Services",
            "subcategory":"Adult Care",
            "type":"Services"
        }
    ],
    "sg:phone":"+61 2 4759 1841",
    "sg:postcode":"2783",
    "sg:province":"NSW",
    "sg:tags":[
        "towing"
    ],
    "wof:name":"Mid Mountains Smash Repairs",
    "wof:placetype":"venue"
},
  "geometry": {"coordinates":[150.43951415999999,-33.7264480591],"type":"Point"}
}