{
  "type": "Feature",
  "properties": {
    "addr:full":"13 Inglewood Crt Mill Park VIC 3082",
    "addr:housenumber":"13",
    "addr:postcode":"3082",
    "addr:street":"Inglewood Crt",
    "iso:country":"AU",
    "sg:address":"13 Inglewood Crt",
    "sg:city":"Mill Park",
    "sg:classifiers":[
        {
            "category":"Building & Trades",
            "subcategory":"Construction",
            "type":"Services"
        }
    ],
    "sg:phone":"+61 419 565 701",
    "sg:postcode":"3082",
    "sg:province":"VIC",
    "sg:tags":[
        "joiner",
        "carpenter"
    ],
    "wof:name":"Its All Carpentry: Framer, Lock-Up, Fix",
    "wof:placetype":"venue"
},
  "geometry": {"coordinates":[145.08348083499999,-37.6634864807],"type":"Point"}
}