{
  "type": "Feature",
  "properties": {
    "addr:full":"278- 288 Brighton Rd Glenelg SA 5045",
    "addr:housenumber":"288",
    "addr:postcode":"5045",
    "addr:street":"Brighton Rd",
    "iso:country":"AU",
    "sg:address":"278- 288 Brighton Rd",
    "sg:city":"Glenelg",
    "sg:classifiers":[
        {
            "category":"Autos & Motor Vehicles",
            "subcategory":"Automobile Sales",
            "type":"Retail Goods"
        }
    ],
    "sg:phone":"+61 8 8296 4866",
    "sg:postcode":"5045",
    "sg:province":"SA",
    "sg:tags":[
        "car",
        "new"
    ],
    "wof:name":"HSV",
    "wof:placetype":"venue"
},
  "geometry": {"coordinates":[138.52020300000001,-34.979958],"type":"Point"}
}