{
  "type": "Feature",
  "properties": {
    "addr:full":"Shop 19 Diana Drv Blackburn North VIC 3130",
    "addr:housenumber":"shop 19",
    "addr:postcode":"3130",
    "addr:street":"Diana Drv",
    "iso:country":"AU",
    "sg:address":"Shop 19 Diana Drv",
    "sg:city":"Blackburn North",
    "sg:classifiers":[
        {
            "category":"Home & Garden",
            "subcategory":"Home Furnishings",
            "type":"Retail Goods"
        }
    ],
    "sg:phone":"+61 3 9878 1089",
    "sg:postcode":"3130",
    "sg:province":"VIC",
    "sg:tags":[
        "wicker",
        "cane",
        "furniture"
    ],
    "wof:name":"Soula's Upholstery",
    "wof:placetype":"venue"
},
  "geometry": {"coordinates":[145.163604736,-37.808429718],"type":"Point"}
}