{
  "type": "Feature",
  "properties": {
    "iso:country":"AU",
    "sg:address":"15 Acapulco Rd",
    "sg:city":"Safety Bay",
    "sg:classifiers":[
        {
            "category":"Home & Garden",
            "subcategory":"Building Materials",
            "type":"Retail Goods"
        }
    ],
    "sg:phone":"+61 8 9528 1569",
    "sg:postcode":"6169",
    "sg:province":"WA",
    "sg:tags":[
        "merchant",
        "glass",
        "glazier"
    ],
    "wof:name":"Bayside Glass",
    "wof:placetype":"venue"
},
  "geometry": {"coordinates":[115.736679,-32.300663],"type":"Point"}
}