{
  "type": "Feature",
  "properties": {
    "addr:full":"22 Minnie St Cairns QLD 4870",
    "addr:housenumber":"22",
    "addr:postcode":"4870",
    "addr:street":"Minnie St",
    "iso:country":"AU",
    "sg:address":"22 Minnie St",
    "sg:city":"Cairns",
    "sg:classifiers":[
        {
            "category":"Health Services",
            "subcategory":"Dentist",
            "type":"Services"
        }
    ],
    "sg:phone":"+61 7 4031 2351",
    "sg:postcode":"4870",
    "sg:province":"QLD",
    "wof:name":"Martin Peter E",
    "wof:placetype":"venue"
},
  "geometry": {"coordinates":[145.76805114699999,-16.9195613861],"type":"Point"}
}