{
  "type": "Feature",
  "properties": {
    "iso:country":"AU",
    "sg:address":"22 Zuhara St",
    "sg:city":"Rochedale South",
    "sg:classifiers":[
        {
            "category":"Banks & Credit Unions",
            "subcategory":"Bureau De Change",
            "type":"Services"
        }
    ],
    "sg:phone":"+61 7 3841 1616",
    "sg:postcode":"4123",
    "sg:province":"QLD",
    "sg:tags":[
        "repairs",
        "part",
        "appliance",
        "electrical"
    ],
    "wof:name":"Ali's Electrical Repairs",
    "wof:placetype":"venue"
},
  "geometry": {"coordinates":[153.129364014,-27.5987129211],"type":"Point"}
}