{
  "type": "Feature",
  "properties": {
    "addr:full":"Unit 1, 34 Stockdale St Dickson ACT 2602",
    "addr:housenumber":"34",
    "addr:postcode":"2602",
    "addr:street":"Stockdale St",
    "iso:country":"AU",
    "sg:address":"Unit 1, 34 Stockdale St",
    "sg:city":"Dickson",
    "sg:classifiers":[
        {
            "category":"Professional",
            "subcategory":"Management & Consulting",
            "type":"Services"
        }
    ],
    "sg:phone":"+61 412 723 708",
    "sg:postcode":"2602",
    "sg:province":"ACT",
    "sg:tags":[
        "consultant",
        "business"
    ],
    "wof:name":"Acies",
    "wof:placetype":"venue"
},
  "geometry": {"coordinates":[149.13723754899999,-35.2570915222],"type":"Point"}
}