{
  "type": "Feature",
  "properties": {
    "addr:full":"37 East St Daylesford VIC 3460",
    "addr:housenumber":"37",
    "addr:postcode":"3460",
    "addr:street":"East St",
    "iso:country":"AU",
    "sg:address":"37 East St",
    "sg:city":"Daylesford",
    "sg:classifiers":[
        {
            "category":"Home & Garden",
            "subcategory":"Garden Supply",
            "type":"Retail Goods"
        }
    ],
    "sg:phone":"+61 3 5348 4414",
    "sg:postcode":"3460",
    "sg:province":"VIC",
    "sg:tags":[
        "landscape"
    ],
    "wof:name":"Daylesford Garden Supply",
    "wof:placetype":"venue"
},
  "geometry": {"coordinates":[144.155029297,-37.3466148376],"type":"Point"}
}