{
  "type": "Feature",
  "properties": {
    "addr:full":"337 Canning Hwy Palmyra WA 6157",
    "addr:housenumber":"337",
    "addr:postcode":"6157",
    "addr:street":"Canning Hwy",
    "iso:country":"AU",
    "sg:address":"337 Canning Hwy",
    "sg:city":"Palmyra",
    "sg:classifiers":[
        {
            "category":"Personal",
            "subcategory":"Beauty Salon",
            "type":"Services"
        }
    ],
    "sg:phone":"+61 8 9319 2297",
    "sg:postcode":"6157",
    "sg:province":"WA",
    "wof:name":"New York Nails",
    "wof:placetype":"venue"
},
  "geometry": {"coordinates":[115.783432,-32.036659],"type":"Point"}
}