{
  "type": "Feature",
  "properties": {
    "addr:full":"19 Martha Mews Lavington NSW 2641",
    "addr:housenumber":"19",
    "addr:postcode":"2641",
    "addr:street":"Martha Mews",
    "iso:country":"AU",
    "sg:address":"19 Martha Mews",
    "sg:city":"Lavington",
    "sg:classifiers":[
        {
            "category":"Retail",
            "subcategory":"Event Space",
            "type":"Services"
        }
    ],
    "sg:phone":"+61 2 6025 8622",
    "sg:postcode":"2641",
    "sg:province":"NSW",
    "sg:tags":[
        "venue",
        "reception",
        "wedding"
    ],
    "wof:name":"Mirambeena",
    "wof:placetype":"venue"
},
  "geometry": {"coordinates":[146.938156128,-36.0512809753],"type":"Point"}
}