{
  "type": "Feature",
  "properties": {
    "addr:full":"1 Kittyhawk Ave Inala QLD 4077",
    "addr:housenumber":"1",
    "addr:postcode":"4077",
    "addr:street":"Kittyhawk Ave Inala",
    "iso:country":"AU",
    "sg:address":"1 Kittyhawk Ave",
    "sg:city":"Inala",
    "sg:classifiers":[
        {
            "category":"Communications",
            "subcategory":"Film & Video Production",
            "type":"Services"
        }
    ],
    "sg:phone":"+61 7 3372 8177",
    "sg:postcode":"4077",
    "sg:province":"QLD",
    "sg:tags":[
        "dvd",
        "library"
    ],
    "wof:name":"Video Ezy",
    "wof:placetype":"venue"
},
  "geometry": {"coordinates":[152.972946167,-27.6007709503],"type":"Point"}
}