{
  "type": "Feature",
  "properties": {
    "addr:full":"6 King St Bayswater WA 6053",
    "addr:housenumber":"6",
    "addr:postcode":"6053",
    "addr:street":"King St",
    "iso:country":"AU",
    "sg:address":"6 King St",
    "sg:city":"Bayswater",
    "sg:classifiers":[
        {
            "category":"Food & Beverages",
            "subcategory":"Supermarket",
            "type":"Retail Goods"
        }
    ],
    "sg:phone":"+61 8 9371 8288",
    "sg:postcode":"6053",
    "sg:province":"WA",
    "sg:tags":[
        "grocery",
        "store"
    ],
    "wof:name":"Lam's Oriental Supermarket",
    "wof:placetype":"venue"
},
  "geometry": {"coordinates":[115.918861389,-31.9078845978],"type":"Point"}
}