{
  "type": "Feature",
  "properties": {
    "addr:full":"25 Chard Rd Brookvale NSW 2100",
    "addr:housenumber":"25",
    "addr:postcode":"2100",
    "addr:street":"Chard Rd",
    "iso:country":"AU",
    "sg:address":"25 Chard Rd",
    "sg:city":"Brookvale",
    "sg:classifiers":[
        {
            "category":"Building & Trades",
            "subcategory":"Cleaning & Sanitation",
            "type":"Services"
        }
    ],
    "sg:phone":"+61 2 9905 2297",
    "sg:postcode":"2100",
    "sg:province":"NSW",
    "sg:tags":[
        "commercial",
        "maintenance"
    ],
    "wof:name":"Brookvale Industrial Maintenance Pty Ltd",
    "wof:placetype":"venue"
},
  "geometry": {"coordinates":[151.27424621599999,-33.7634353638],"type":"Point"}
}