{
  "type": "Feature",
  "properties": {
    "addr:full":"45 Vaughan Drv Ormeau QLD 4208",
    "addr:housenumber":"45",
    "addr:postcode":"4208",
    "addr:street":"Vaughan Drv",
    "iso:country":"AU",
    "sg:address":"45 Vaughan Drv",
    "sg:city":"Ormeau",
    "sg:classifiers":[
        {
            "category":"Manufacturing",
            "subcategory":"Building Materials",
            "type":"Manufacturing & Wholesale Goods"
        }
    ],
    "sg:phone":"+61 7 5546 6049",
    "sg:postcode":"4208",
    "sg:province":"QLD",
    "sg:tags":[
        "stone",
        "product",
        "supply"
    ],
    "wof:name":"Feature Stone",
    "wof:placetype":"venue"
},
  "geometry": {"coordinates":[153.24562072800001,-27.7769565582],"type":"Point"}
}