{
  "type": "Feature",
  "properties": {
    "addr:full":"Unit 1/ 126 Pacific Hwy Tuggerah NSW 2259",
    "addr:housenumber":"/ 126",
    "addr:postcode":"2259",
    "addr:street":"Pacific Hwy",
    "iso:country":"AU",
    "sg:address":"Unit 1/ 126 Pacific Hwy",
    "sg:city":"Tuggerah",
    "sg:classifiers":[
        {
            "category":"Industrial Area",
            "type":"Public Place"
        }
    ],
    "sg:phone":"+61 2 4351 0213",
    "sg:postcode":"2259",
    "sg:province":"NSW",
    "sg:tags":[
        "rural",
        "shed"
    ],
    "wof:name":"Sheds Plus",
    "wof:placetype":"venue"
},
  "geometry": {"coordinates":[151.411865234,-33.3158302307],"type":"Point"}
}