{
  "type": "Feature",
  "properties": {
    "addr:full":"43 Old Bittern-Dromana Rd Merricks North VIC 3926",
    "addr:housenumber":"43",
    "addr:postcode":"3926",
    "addr:street":"Old Bittern-Dromana Rd",
    "iso:country":"AU",
    "sg:address":"43 Old Bittern-Dromana Rd",
    "sg:city":"Merricks North",
    "sg:classifiers":[
        {
            "category":"Train Station",
            "subcategory":"Rail",
            "type":"Transportation"
        }
    ],
    "sg:phone":"+61 3 5989 7257",
    "sg:postcode":"3926",
    "sg:province":"VIC",
    "sg:tags":[
        "marine",
        "engineer"
    ],
    "wof:name":"Merricks North Auto & Marine",
    "wof:placetype":"venue"
},
  "geometry": {"coordinates":[145.08148193400001,-38.3530235291],"type":"Point"}
}