{
  "type": "Feature",
  "properties": {
    "iso:country":"AU",
    "sg:address":"100 Maryborough St",
    "sg:city":"Fyshwick",
    "sg:classifiers":[
        {
            "category":"Retail",
            "subcategory":"Auto Repair",
            "type":"Services"
        }
    ],
    "sg:phone":"+61 2 6280 6002",
    "sg:postcode":"2609",
    "sg:province":"ACT",
    "sg:tags":[
        "repairer",
        "motor",
        "engineer"
    ],
    "wof:name":"All Service Motors",
    "wof:placetype":"venue"
},
  "geometry": {"coordinates":[149.17298889200001,-35.3243141174],"type":"Point"}
}