{
  "type": "Feature",
  "properties": {
    "addr:full":"1/ 42 Mileham St Windsor NSW 2756",
    "addr:housenumber":"/ 42",
    "addr:postcode":"2756",
    "addr:street":"Mileham St",
    "iso:country":"AU",
    "sg:address":"1/ 42 Mileham St",
    "sg:city":"Windsor",
    "sg:classifiers":[
        {
            "category":"Cafe",
            "type":"Food & Drink"
        }
    ],
    "sg:phone":"+61 2 4577 8135",
    "sg:postcode":"2756",
    "sg:province":"NSW",
    "wof:name":"Munchies On Mileham",
    "wof:placetype":"venue"
},
  "geometry": {"coordinates":[150.81442260700001,-33.6147155762],"type":"Point"}
}