{
  "type": "Feature",
  "properties": {
    "iso:country":"AU",
    "sg:address":"Ste 5,Lvl 5 14 Queens Rd",
    "sg:city":"Melbourne",
    "sg:classifiers":[
        {
            "category":"Banks & Credit Unions",
            "subcategory":"Financial Services",
            "type":"Services"
        }
    ],
    "sg:phone":"+61 3 9820 4300",
    "sg:postcode":"3004",
    "sg:province":"VIC",
    "sg:tags":[
        "planning"
    ],
    "wof:name":"Will Charlton",
    "wof:placetype":"venue"
},
  "geometry": {"coordinates":[144.97430419899999,-37.8388252258],"type":"Point"}
}