{
  "type": "Feature",
  "properties": {
    "addr:full":"65 West Rd Pearcedale VIC 3912",
    "addr:housenumber":"65",
    "addr:postcode":"3912",
    "addr:street":"West Rd",
    "iso:country":"AU",
    "sg:address":"65 West Rd",
    "sg:city":"Pearcedale",
    "sg:classifiers":[
        {
            "category":"Farming",
            "subcategory":"Nursery",
            "type":"Manufacturing & Wholesale Goods"
        }
    ],
    "sg:phone":"+61 3 5978 7288",
    "sg:postcode":"3912",
    "sg:province":"VIC",
    "wof:name":"Westgreen Nursery",
    "wof:placetype":"venue"
},
  "geometry": {"coordinates":[145.20614624000001,-38.1935119629],"type":"Point"}
}