{
  "type": "Feature",
  "properties": {
    "addr:full":"33 Discovery Dr Bibra Lake WA 6163",
    "addr:housenumber":"33",
    "addr:postcode":"6163",
    "addr:street":"Discovery Dr",
    "iso:country":"AU",
    "sg:address":"33 Discovery Dr",
    "sg:city":"Bibra Lake",
    "sg:classifiers":[
        {
            "category":"Manufacturing",
            "subcategory":"Glass & Minerals",
            "type":"Manufacturing & Wholesale Goods"
        }
    ],
    "sg:phone":"+61 8 9331 4833",
    "sg:postcode":"6163",
    "sg:province":"WA",
    "sg:tags":[
        "merchant",
        "granite",
        "marble"
    ],
    "wof:name":"M G Creations Pty Ltd",
    "wof:placetype":"venue"
},
  "geometry": {"coordinates":[115.81240099999999,-32.08992],"type":"Point"}
}