{
  "type": "Feature",
  "properties": {
    "addr:full":"2/ 2 Betty Cuthbert Ave Ermington NSW 2115",
    "addr:housenumber":"/ 2",
    "addr:postcode":"2115",
    "addr:street":"Betty Cuthbert Ave",
    "iso:country":"AU",
    "sg:address":"2/ 2 Betty Cuthbert Ave",
    "sg:city":"Ermington",
    "sg:classifiers":[
        {
            "category":"Professional",
            "subcategory":"Accounting & Tax Preparation",
            "type":"Services"
        }
    ],
    "sg:phone":"+61 2 9898 1144",
    "sg:postcode":"2115",
    "sg:province":"NSW",
    "sg:tags":[
        "consultant",
        "taxation"
    ],
    "wof:name":"Addersons Accounting",
    "wof:placetype":"venue"
},
  "geometry": {"coordinates":[151.053924561,-33.8143959045],"type":"Point"}
}