{
  "type": "Feature",
  "properties": {
    "addr:full":"16 Annandale St Annandale NSW 2038",
    "addr:housenumber":"16",
    "addr:postcode":"2038",
    "addr:street":"Annandale St",
    "iso:country":"AU",
    "sg:address":"16 Annandale St",
    "sg:city":"Annandale",
    "sg:classifiers":[
        {
            "category":"Health Services",
            "subcategory":"Chiropractor",
            "type":"Services"
        }
    ],
    "sg:phone":"+61 2 9518 3628",
    "sg:postcode":"2038",
    "sg:province":"NSW",
    "wof:name":"Inner West Chiropractic",
    "wof:placetype":"venue"
},
  "geometry": {"coordinates":[151.16648864699999,-33.8867149353],"type":"Point"}
}