{
  "type": "Feature",
  "properties": {
    "iso:country":"AU",
    "sg:address":"272 Enmore Rd",
    "sg:city":"Marrickville",
    "sg:classifiers":[
        {
            "category":"Banks & Credit Unions",
            "subcategory":"Investment Brokerage",
            "type":"Services"
        }
    ],
    "sg:phone":"+61 2 9517 4484",
    "sg:postcode":"2204",
    "sg:province":"NSW",
    "sg:tags":[
        "paint",
        "supply",
        "removal"
    ],
    "wof:name":"Enzo Paint And Decorating",
    "wof:placetype":"venue"
},
  "geometry": {"coordinates":[151.169815,-33.901814],"type":"Point"}
}