{
  "type": "Feature",
  "properties": {
    "addr:full":"41 Henshall Rd Strathmore VIC 3041",
    "addr:housenumber":"41",
    "addr:postcode":"3041",
    "addr:street":"Henshall Rd",
    "iso:country":"AU",
    "sg:address":"41 Henshall Rd",
    "sg:city":"Strathmore",
    "sg:classifiers":[
        {
            "category":"Real Estate",
            "subcategory":"Architect",
            "type":"Services"
        }
    ],
    "sg:phone":"+61 3 9379 0500",
    "sg:postcode":"3041",
    "sg:province":"VIC",
    "sg:tags":[
        "raw",
        "material",
        "plastic"
    ],
    "wof:name":"Plummer Trading & Consulting Pty Ltd",
    "wof:placetype":"venue"
},
  "geometry": {"coordinates":[144.91532898,-37.7375411987],"type":"Point"}
}