{
  "type": "Feature",
  "properties": {
    "addr:full":"11-13 Bowyer Rd Wingfield SA 5013",
    "addr:housenumber":"11-13",
    "addr:postcode":"5013",
    "addr:street":"Bowyer Rd",
    "iso:country":"AU",
    "sg:address":"11-13 Bowyer Rd",
    "sg:city":"Wingfield",
    "sg:classifiers":[
        {
            "category":"Wholesale",
            "subcategory":"Machinery & Supplies",
            "type":"Manufacturing & Wholesale Goods"
        }
    ],
    "sg:phone":"+61 417 910 678",
    "sg:postcode":"5013",
    "sg:province":"SA",
    "sg:tags":[
        "engineer"
    ],
    "wof:name":"Teravin Tools Pty Ltd",
    "wof:placetype":"venue"
},
  "geometry": {"coordinates":[138.55503845199999,-34.8442344666],"type":"Point"}
}