{
  "type": "Feature",
  "properties": {
    "iso:country":"AU",
    "sg:address":"U 3/ 7 Cunningham St",
    "sg:city":"Moorebank",
    "sg:classifiers":[
        {
            "category":"Wholesale",
            "subcategory":"Machinery & Supplies",
            "type":"Manufacturing & Wholesale Goods"
        }
    ],
    "sg:phone":"+61 2 9601 1213",
    "sg:postcode":"2170",
    "sg:province":"NSW",
    "sg:tags":[
        "machine",
        "tool",
        "engineer"
    ],
    "wof:name":"S F Manufacturing Pty Ltd",
    "wof:placetype":"venue"
},
  "geometry": {"coordinates":[150.93760681099999,-33.9343795776],"type":"Point"}
}