{
  "type": "Feature",
  "properties": {
    "addr:full":"10 Windsor Ave Mt Waverley VIC 3149",
    "addr:housenumber":"10",
    "addr:postcode":"3149",
    "addr:street":"Windsor Ave Mt",
    "iso:country":"AU",
    "sg:address":"10 Windsor Ave",
    "sg:city":"Mt Waverley",
    "sg:classifiers":[
        {
            "category":"Professional",
            "subcategory":"Engineering",
            "type":"Services"
        }
    ],
    "sg:phone":"+61 3 9807 1611",
    "sg:postcode":"3149",
    "sg:province":"VIC",
    "sg:tags":[
        "electrical",
        "engineer"
    ],
    "wof:name":"O&#039;Shea T H&Associates Pty Ltd",
    "wof:placetype":"venue"
},
  "geometry": {"coordinates":[145.11268615700001,-37.8742332458],"type":"Point"}
}