{
  "type": "Feature",
  "properties": {
    "addr:full":"30 Bywaters Rd Murray Bridge SA 5253",
    "addr:housenumber":"30",
    "addr:postcode":"5253",
    "addr:street":"Bywaters Rd",
    "iso:country":"AU",
    "sg:address":"30 Bywaters Rd",
    "sg:city":"Murray Bridge",
    "sg:classifiers":[
        {
            "category":"Professional",
            "type":"Services"
        }
    ],
    "sg:phone":"+61 8 8531 0678",
    "sg:postcode":"5253",
    "sg:province":"SA",
    "sg:tags":[
        "transport"
    ],
    "wof:name":"Penta Transport",
    "wof:placetype":"venue"
},
  "geometry": {"coordinates":[139.257446289,-35.1389923096],"type":"Point"}
}