{
  "type": "Feature",
  "properties": {
    "iso:country":"AU",
    "sg:address":"130 Victoria Pde",
    "sg:city":"Rockhampton",
    "sg:classifiers":[
        {
            "category":"Insurance",
            "subcategory":"Life Insurance",
            "type":"Services"
        }
    ],
    "sg:phone":"+61 7 4923 7142",
    "sg:postcode":"4700",
    "sg:province":"QLD",
    "wof:name":"Plan 2 Prosper",
    "wof:placetype":"venue"
},
  "geometry": {"coordinates":[150.51239013700001,-23.3754482269],"type":"Point"}
}