{
  "type": "Feature",
  "properties": {
    "addr:full":"30 Auburn St Goulburn NSW 2580",
    "addr:housenumber":"30",
    "addr:postcode":"2580",
    "addr:street":"Auburn St",
    "iso:country":"AU",
    "sg:address":"30 Auburn St",
    "sg:city":"Goulburn",
    "sg:classifiers":[
        {
            "category":"Food & Beverages",
            "subcategory":"Groceries & Convenience Stores",
            "type":"Retail Goods"
        }
    ],
    "sg:phone":"+61 2 4821 2359",
    "sg:postcode":"2580",
    "sg:province":"NSW",
    "wof:name":"Hogan G & K",
    "wof:placetype":"venue"
},
  "geometry": {"coordinates":[149.71910095199999,-34.7535972595],"type":"Point"}
}