{
  "type": "Feature",
  "properties": {
    "addr:full":"746 Kingsway Rd Gymea NSW 2227",
    "addr:housenumber":"746",
    "addr:postcode":"2227",
    "addr:street":"Kingsway Rd",
    "iso:country":"AU",
    "sg:address":"746 Kingsway Rd",
    "sg:city":"Gymea",
    "sg:classifiers":[
        {
            "category":"Health Services",
            "subcategory":"Doctor",
            "type":"Services"
        }
    ],
    "sg:phone":"+61 2 9524 7262",
    "sg:postcode":"2227",
    "sg:province":"NSW",
    "sg:tags":[
        "medical",
        "practitioner"
    ],
    "wof:name":"Coverdale M E, Glendinning C J & Vicki Chan",
    "wof:placetype":"venue"
},
  "geometry": {"coordinates":[151.08691406200001,-34.0328979492],"type":"Point"}
}