{
  "type": "Feature",
  "properties": {
    "iso:country":"AU",
    "sg:address":"364 Brighton Rd",
    "sg:city":"Hove",
    "sg:classifiers":[
        {
            "category":"Personal",
            "subcategory":"Beauty Salon",
            "type":"Services"
        }
    ],
    "sg:phone":"+61 8 8298 7310",
    "sg:postcode":"5048",
    "sg:province":"SA",
    "sg:tags":[
        "hairdresser"
    ],
    "wof:name":"Studio 5",
    "wof:placetype":"venue"
},
  "geometry": {"coordinates":[138.522598,-35.010067],"type":"Point"}
}