{
  "type": "Feature",
  "properties": {
    "addr:full":"5 Tweed Rd Wanneroo WA 6065",
    "addr:housenumber":"5",
    "addr:postcode":"6065",
    "addr:street":"Tweed Rd",
    "iso:country":"AU",
    "sg:address":"5 Tweed Rd",
    "sg:city":"Wanneroo",
    "sg:classifiers":[
        {
            "category":"Building & Trades",
            "subcategory":"Construction",
            "type":"Services"
        }
    ],
    "sg:phone":"+61 8 9405 7909",
    "sg:postcode":"6065",
    "sg:province":"WA",
    "sg:tags":[
        "fencing",
        "contractor"
    ],
    "wof:name":"Abode Fencing",
    "wof:placetype":"venue"
},
  "geometry": {"coordinates":[115.80522918699999,-31.7746067047],"type":"Point"}
}