{
  "type": "Feature",
  "properties": {
    "iso:country":"AU",
    "sg:address":"Barmedman Rd",
    "sg:city":"Temora",
    "sg:classifiers":[
        {
            "category":"Building & Trades",
            "subcategory":"Construction",
            "type":"Services"
        }
    ],
    "sg:phone":"+61 428 771 679",
    "sg:postcode":"2666",
    "sg:province":"NSW",
    "sg:tags":[
        "contractor"
    ],
    "wof:name":"Cartwright M D",
    "wof:placetype":"venue"
},
  "geometry": {"coordinates":[147.53408813499999,-34.4467506409],"type":"Point"}
}