{
  "type": "Feature",
  "properties": {
    "addr:full":"11 Gordon St Bairnsdale VIC 3875",
    "addr:housenumber":"11",
    "addr:postcode":"3875",
    "addr:street":"Gordon St",
    "iso:country":"AU",
    "sg:address":"11 Gordon St",
    "sg:city":"Bairnsdale",
    "sg:classifiers":[
        {
            "category":"Building & Trades",
            "subcategory":"Construction",
            "type":"Services"
        }
    ],
    "sg:phone":"+61 427 967 405",
    "sg:postcode":"3875",
    "sg:province":"VIC",
    "sg:tags":[
        "home",
        "air conditioning"
    ],
    "wof:name":"ABL Refrigeration & Airconditioning Services Pty Ltd",
    "wof:placetype":"venue"
},
  "geometry": {"coordinates":[147.61253356899999,-37.8266029358],"type":"Point"}
}