{
  "type": "Feature",
  "properties": {
    "addr:full":"Cnr Cary & James Sts Toronto NSW 2283",
    "addr:postcode":"2283",
    "addr:street":"Cnr",
    "iso:country":"AU",
    "sg:address":"Cnr Cary & James Sts",
    "sg:city":"Toronto",
    "sg:classifiers":[
        {
            "category":"Communications",
            "subcategory":"Film & Video Production",
            "type":"Services"
        }
    ],
    "sg:phone":"+61 2 4959 1520",
    "sg:postcode":"2283",
    "sg:province":"NSW",
    "sg:tags":[
        "dvd",
        "library"
    ],
    "wof:name":"Video Ezy",
    "wof:placetype":"venue"
},
  "geometry": {"coordinates":[151.59327697800001,-33.0127296448],"type":"Point"}
}