{
  "type": "Feature",
  "properties": {
    "addr:full":"23 Llewelyn St Oatley NSW 2223",
    "addr:housenumber":"23",
    "addr:postcode":"2223",
    "addr:street":"Llewelyn St",
    "iso:country":"AU",
    "sg:address":"23 Llewelyn St",
    "sg:city":"Oatley",
    "sg:classifiers":[
        {
            "category":"Building & Trades",
            "subcategory":"Plumbing",
            "type":"Services"
        }
    ],
    "sg:phone":"+61 2 9570 4030",
    "sg:postcode":"2223",
    "sg:province":"NSW",
    "sg:tags":[
        "plumber",
        "gasfitters"
    ],
    "wof:name":"A Weber Plumbing",
    "wof:placetype":"venue"
},
  "geometry": {"coordinates":[151.073532105,-33.9874916077],"type":"Point"}
}