{
  "type": "Feature",
  "properties": {
    "iso:country":"AU",
    "sg:address":"5 Huntington St",
    "sg:city":"Clontarf",
    "sg:classifiers":[
        {
            "category":"Banks & Credit Unions",
            "subcategory":"Atm",
            "type":"Services"
        }
    ],
    "sg:phone":"+61 7 3284 4033",
    "sg:postcode":"4019",
    "sg:province":"QLD",
    "sg:tags":[
        "control",
        "soil",
        "erosion",
        "stabilisation"
    ],
    "sg:website":"http://www.groutech.com.au",
    "wof:name":"Groutech",
    "wof:placetype":"venue"
},
  "geometry": {"coordinates":[153.08102417000001,-27.2407131195],"type":"Point"}
}