{
  "type": "Feature",
  "properties": {
    "addr:full":"7 Cavendish St Pennant Hills NSW 2120",
    "addr:housenumber":"7",
    "addr:postcode":"2120",
    "addr:street":"Cavendish St",
    "iso:country":"AU",
    "sg:address":"7 Cavendish St",
    "sg:city":"Pennant Hills",
    "sg:classifiers":[
        {
            "category":"Building & Trades",
            "subcategory":"Construction",
            "type":"Services"
        }
    ],
    "sg:phone":"+61 411 185 633",
    "sg:postcode":"2120",
    "sg:province":"NSW",
    "sg:tags":[
        "contractor"
    ],
    "wof:name":"Ined Pty Ltd",
    "wof:placetype":"venue"
},
  "geometry": {"coordinates":[151.07862854000001,-33.7354621887],"type":"Point"}
}