{
  "type": "Feature",
  "properties": {
    "iso:country":"AU",
    "sg:address":"Shp2/ 42 Warranwood Rd",
    "sg:city":"Warranwood",
    "sg:classifiers":[
        {
            "category":"Fast Food",
            "type":"Food & Drink"
        }
    ],
    "sg:phone":"+61 3 9876 4414",
    "sg:postcode":"3134",
    "sg:province":"VIC",
    "sg:tags":[
        "away",
        "take"
    ],
    "wof:name":"Fish Tub",
    "wof:placetype":"venue"
},
  "geometry": {"coordinates":[145.250442505,-37.7773323059],"type":"Point"}
}