{
  "type": "Feature",
  "properties": {
    "addr:full":"104 Flinders St Adelaide SA 5000",
    "addr:housenumber":"104",
    "addr:postcode":"5000",
    "addr:street":"Flinders St",
    "iso:country":"AU",
    "sg:address":"104 Flinders St",
    "sg:city":"Adelaide",
    "sg:classifiers":[
        {
            "category":"Restaurant",
            "type":"Food & Drink"
        }
    ],
    "sg:phone":"+61 8 8223 2036",
    "sg:postcode":"5000",
    "sg:province":"SA",
    "wof:name":"Botticelli Restaurant",
    "wof:placetype":"venue"
},
  "geometry": {"coordinates":[138.604125977,-34.9268074036],"type":"Point"}
}