{
  "type": "Feature",
  "properties": {
    "iso:country":"AU",
    "sg:address":"76 Temple St",
    "sg:city":"Heyfield",
    "sg:classifiers":[
        {
            "category":"Retail",
            "subcategory":"Funeral Services",
            "type":"Services"
        }
    ],
    "sg:phone":"+61 3 5148 2877",
    "sg:postcode":"3858",
    "sg:province":"VIC",
    "sg:tags":[
        "director"
    ],
    "wof:name":"Heyfield Funeral Services",
    "wof:placetype":"venue"
},
  "geometry": {"coordinates":[146.78448486299999,-37.9845352173],"type":"Point"}
}