{
  "type": "Feature",
  "properties": {
    "addr:full":"19 Warwick St North Ryde NSW 2113",
    "addr:housenumber":"19",
    "addr:postcode":"2113",
    "addr:street":"Warwick St",
    "iso:country":"AU",
    "sg:address":"19 Warwick St",
    "sg:city":"North Ryde",
    "sg:classifiers":[
        {
            "category":"Banks & Credit Unions",
            "subcategory":"Financial Services",
            "type":"Services"
        }
    ],
    "sg:phone":"+61 1300 363 095",
    "sg:postcode":"2113",
    "sg:province":"NSW",
    "sg:tags":[
        "loan",
        "finance",
        "mortgage"
    ],
    "wof:name":"Secure Finance",
    "wof:placetype":"venue"
},
  "geometry": {"coordinates":[151.13690185600001,-33.799621582],"type":"Point"}
}