{
  "type": "Feature",
  "properties": {
    "iso:country":"AU",
    "sg:address":"197 Flinders La",
    "sg:city":"Melbourne",
    "sg:classifiers":[
        {
            "category":"Retail",
            "subcategory":"Event Space",
            "type":"Services"
        }
    ],
    "sg:phone":"+61 3 9639 3999",
    "sg:postcode":"3000",
    "sg:province":"VIC",
    "sg:tags":[
        "venue",
        "reception",
        "wedding"
    ],
    "wof:name":"The Chapter House - St Pauls Cathedral",
    "wof:placetype":"venue"
},
  "geometry": {"coordinates":[144.967926025,-37.8163337708],"type":"Point"}
}