{
  "type": "Feature",
  "properties": {
    "addr:full":"77 Felix St Wooloowin QLD 4030",
    "addr:housenumber":"77",
    "addr:postcode":"4030",
    "addr:street":"Felix St",
    "iso:country":"AU",
    "sg:address":"77 Felix St",
    "sg:city":"Wooloowin",
    "sg:classifiers":[
        {
            "category":"Professional",
            "subcategory":"Management & Consulting",
            "type":"Services"
        }
    ],
    "sg:phone":"+61 7 3357 4400",
    "sg:postcode":"4030",
    "sg:province":"QLD",
    "sg:tags":[
        "consultant"
    ],
    "wof:name":"Response Consulting Australia Pty Ltd",
    "wof:placetype":"venue"
},
  "geometry": {"coordinates":[153.03938299999999,-27.420424],"type":"Point"}
}