{
  "type": "Feature",
  "properties": {
    "addr:full":"PO Box 298 Lismore NSW 2480",
    "addr:postcode":"2480",
    "iso:country":"AU",
    "sg:address":"PO Box 298",
    "sg:city":"Lismore",
    "sg:classifiers":[
        {
            "category":"Professional",
            "subcategory":"Computer Services",
            "type":"Services"
        }
    ],
    "sg:phone":"+61 1800 658 998",
    "sg:postcode":"2480",
    "sg:province":"NSW",
    "sg:tags":[
        "consultant",
        "system"
    ],
    "wof:name":"Ag IT",
    "wof:placetype":"venue"
},
  "geometry": {"coordinates":[153.27818298299999,-28.8139896393],"type":"Point"}
}