{
  "type": "Feature",
  "properties": {
    "iso:country":"AU",
    "sg:address":"Vannam Drv",
    "sg:city":"Ashwood",
    "sg:classifiers":[
        {
            "category":"Education",
            "subcategory":"School",
            "type":"Public Place"
        }
    ],
    "sg:phone":"+61 3 9807 1333",
    "sg:postcode":"3147",
    "sg:province":"VIC",
    "sg:tags":[
        "state",
        "except",
        "nsw"
    ],
    "wof:name":"Ashwood College",
    "wof:placetype":"venue"
},
  "geometry": {"coordinates":[145.10273742699999,-37.8664054871],"type":"Point"}
}