{
  "type": "Feature",
  "properties": {
    "addr:full":"471 Brunswick St Fitzroy North VIC 3068",
    "addr:housenumber":"471",
    "addr:postcode":"3068",
    "addr:street":"Brunswick St",
    "iso:country":"AU",
    "sg:address":"471 Brunswick St",
    "sg:city":"Fitzroy North",
    "sg:classifiers":[
        {
            "category":"Personal",
            "subcategory":"Massage",
            "type":"Services"
        }
    ],
    "sg:phone":"+61 414 502 319",
    "sg:postcode":"3068",
    "sg:province":"VIC",
    "sg:tags":[
        "therapy"
    ],
    "wof:name":"Marcus Sinfield",
    "wof:placetype":"venue"
},
  "geometry": {"coordinates":[144.979248047,-37.792591095],"type":"Point"}
}