{
  "type": "Feature",
  "properties": {
    "addr:full":"5/ 33 Orient St Batemans Bay NSW 2536",
    "addr:housenumber":"/ 33",
    "addr:postcode":"2536",
    "addr:street":"Orient St",
    "iso:country":"AU",
    "sg:address":"5/ 33 Orient St",
    "sg:city":"Batemans Bay",
    "sg:classifiers":[
        {
            "category":"Education",
            "subcategory":"Special Training",
            "type":"Public Place"
        }
    ],
    "sg:phone":"+61 2 4472 9930",
    "sg:postcode":"2536",
    "sg:province":"NSW",
    "sg:tags":[
        "diving",
        "school",
        "scuba"
    ],
    "wof:name":"National Diving Academy",
    "wof:placetype":"venue"
},
  "geometry": {"coordinates":[150.17784118599999,-35.7080230713],"type":"Point"}
}