{
  "type": "Feature",
  "properties": {
    "addr:full":"Unit 2/ 5 Monterey Rd Dandenong VIC 3175",
    "addr:housenumber":"5",
    "addr:postcode":"3175",
    "addr:street":"Monterey Rd",
    "iso:country":"AU",
    "sg:address":"Unit 2/ 5 Monterey Rd",
    "sg:city":"Dandenong",
    "sg:classifiers":[
        {
            "category":"Manufacturing",
            "subcategory":"Motor Vehicles & Parts",
            "type":"Manufacturing & Wholesale Goods"
        }
    ],
    "sg:phone":"+61 1300 662 766",
    "sg:postcode":"3175",
    "sg:province":"VIC",
    "sg:tags":[
        "replacement"
    ],
    "wof:name":"Nason Engine Parts",
    "wof:placetype":"venue"
},
  "geometry": {"coordinates":[145.21607971200001,-38.0241622925],"type":"Point"}
}