{
  "type": "Feature",
  "properties": {
    "addr:full":"292 Brisbane Rd Labrador QLD 4215",
    "addr:housenumber":"292",
    "addr:postcode":"4215",
    "addr:street":"Brisbane Rd",
    "iso:country":"AU",
    "sg:address":"292 Brisbane Rd",
    "sg:city":"Labrador",
    "sg:classifiers":[
        {
            "category":"Building & Trades",
            "subcategory":"Construction",
            "type":"Services"
        }
    ],
    "sg:phone":"+61 413 661 889",
    "sg:postcode":"4215",
    "sg:province":"QLD",
    "sg:tags":[
        "fencing",
        "contractor"
    ],
    "wof:name":"Tilt Up Fencing",
    "wof:placetype":"venue"
},
  "geometry": {"coordinates":[153.40724182100001,-27.9381504059],"type":"Point"}
}