{
  "type": "Feature",
  "properties": {
    "addr:full":"Lvl 9/ 60 Pitt St Sydney NSW 2000",
    "addr:housenumber":"/ 60",
    "addr:postcode":"2000",
    "addr:street":"Pitt St",
    "iso:country":"AU",
    "sg:address":"Lvl 9/ 60 Pitt St",
    "sg:city":"Sydney",
    "sg:classifiers":[
        {
            "category":"Health Services",
            "subcategory":"Health Practitioner",
            "type":"Services"
        }
    ],
    "sg:phone":"+61 2 9247 8500",
    "sg:postcode":"2000",
    "sg:province":"NSW",
    "sg:tags":[
        "homoeopath"
    ],
    "wof:name":"Sydney Homoeopathic Centre",
    "wof:placetype":"venue"
},
  "geometry": {"coordinates":[151.208984375,-33.8643836975],"type":"Point"}
}