{
  "type": "Feature",
  "properties": {
    "addr:full":"New England Hwy Scone NSW 2337",
    "addr:postcode":"2337",
    "addr:street":"England Hwy",
    "iso:country":"AU",
    "sg:address":"New England Hwy",
    "sg:city":"Scone",
    "sg:classifiers":[
        {
            "category":"Government",
            "subcategory":"Post Office",
            "type":"Public Place"
        }
    ],
    "sg:phone":"+61 2 6545 0156",
    "sg:postcode":"2337",
    "sg:province":"NSW",
    "sg:tags":[
        "equipment",
        "hole",
        "contractor"
    ],
    "wof:name":"Millgate S & C",
    "wof:placetype":"venue"
},
  "geometry": {"coordinates":[150.86781310999999,-32.0457267761],"type":"Point"}
}