{
  "type": "Feature",
  "properties": {
    "addr:full":"15 John St Avalon NSW 2107",
    "addr:housenumber":"15",
    "addr:postcode":"2107",
    "addr:street":"John St",
    "iso:country":"AU",
    "sg:address":"15 John St",
    "sg:city":"Avalon",
    "sg:classifiers":[
        {
            "category":"Education",
            "subcategory":"Kindergarten",
            "type":"Public Place"
        }
    ],
    "sg:phone":"+61 2 9918 8303",
    "sg:postcode":"2107",
    "sg:province":"NSW",
    "sg:tags":[
        "pre-schools"
    ],
    "wof:name":"Kindy Child Care Centre The",
    "wof:placetype":"venue"
},
  "geometry": {"coordinates":[151.33128356899999,-33.6246109009],"type":"Point"}
}