{
  "type": "Feature",
  "properties": {
    "addr:full":"31 Hansford Rd Coombabah QLD 4216",
    "addr:housenumber":"31",
    "addr:postcode":"4216",
    "addr:street":"Hansford Rd",
    "iso:country":"AU",
    "sg:address":"31 Hansford Rd",
    "sg:city":"Coombabah",
    "sg:classifiers":[
        {
            "category":"Health Services",
            "subcategory":"Doctor",
            "type":"Services"
        }
    ],
    "sg:phone":"+61 7 5577 4811",
    "sg:postcode":"4216",
    "sg:province":"QLD",
    "sg:tags":[
        "medical",
        "practitioner"
    ],
    "wof:name":"Khoo David",
    "wof:placetype":"venue"
},
  "geometry": {"coordinates":[153.38510131800001,-27.8997497559],"type":"Point"}
}