{
  "type": "Feature",
  "properties": {
    "addr:full":"Lvl 2B/ 181 Elizabeth St Brisbane QLD 4000",
    "addr:housenumber":"/ 181",
    "addr:postcode":"4000",
    "addr:street":"Elizabeth St",
    "iso:country":"AU",
    "sg:address":"Lvl 2B/ 181 Elizabeth St",
    "sg:city":"Brisbane",
    "sg:classifiers":[
        {
            "category":"Health Services",
            "subcategory":"Dentist",
            "type":"Services"
        }
    ],
    "sg:phone":"+61 7 3210 2144",
    "sg:postcode":"4000",
    "sg:province":"QLD",
    "wof:name":"Khatri Karuna B.D.Sc.",
    "wof:placetype":"venue"
},
  "geometry": {"coordinates":[153.027099609,-27.4697093964],"type":"Point"}
}