{
  "type": "Feature",
  "properties": {
    "addr:full":"41 Elimatta Rd Mona Vale NSW 2103",
    "addr:housenumber":"41",
    "addr:postcode":"2103",
    "addr:street":"Elimatta Rd",
    "iso:country":"AU",
    "sg:address":"41 Elimatta Rd",
    "sg:city":"Mona Vale",
    "sg:classifiers":[
        {
            "category":"Education",
            "subcategory":"Dance Studio",
            "type":"Public Place"
        }
    ],
    "sg:phone":"+61 2 9979 7331",
    "sg:postcode":"2103",
    "sg:province":"NSW",
    "sg:tags":[
        "venue",
        "tuition"
    ],
    "wof:name":"Twocan Dance",
    "wof:placetype":"venue"
},
  "geometry": {"coordinates":[151.303009033,-33.6853981018],"type":"Point"}
}