{
  "type": "Feature",
  "properties": {
    "iso:country":"AU",
    "sg:address":"23 Blackburn Rd",
    "sg:city":"Blackburn",
    "sg:classifiers":[
        {
            "category":"Health Services",
            "subcategory":"Dentist",
            "type":"Services"
        }
    ],
    "sg:phone":"+61 3 9878 1411",
    "sg:postcode":"3130",
    "sg:province":"VIC",
    "wof:name":"Blackburn Dental Group",
    "wof:placetype":"venue"
},
  "geometry": {"coordinates":[145.15292358400001,-37.8211631775],"type":"Point"}
}