{
  "type": "Feature",
  "properties": {
    "addr:full":"Lockwood Rd Mareeba QLD 4880",
    "addr:postcode":"4880",
    "addr:street":"Lockwood Rd",
    "iso:country":"AU",
    "sg:address":"Lockwood Rd",
    "sg:city":"Mareeba",
    "sg:classifiers":[
        {
            "category":"Farming",
            "subcategory":"Farm",
            "type":"Manufacturing & Wholesale Goods"
        }
    ],
    "sg:phone":"+61 7 4092 4867",
    "sg:postcode":"4880",
    "sg:province":"QLD",
    "sg:tags":[
        "farmer"
    ],
    "wof:name":"Tomerini M P & C L",
    "wof:placetype":"venue"
},
  "geometry": {"coordinates":[145.454544067,-17.0579032898],"type":"Point"}
}