{
  "type": "Feature",
  "properties": {
    "addr:full":"27 Carmarthen St Menai NSW 2234",
    "addr:housenumber":"27",
    "addr:postcode":"2234",
    "addr:street":"Carmarthen St",
    "iso:country":"AU",
    "sg:address":"27 Carmarthen St",
    "sg:city":"Menai",
    "sg:classifiers":[
        {
            "category":"Professional",
            "subcategory":"Accounting & Tax Preparation",
            "type":"Services"
        }
    ],
    "sg:phone":"+61 414 887 042",
    "sg:postcode":"2234",
    "sg:province":"NSW",
    "sg:tags":[
        "bookkeeping"
    ],
    "wof:name":"Beta Bookkeeping Services Pty Ltd",
    "wof:placetype":"venue"
},
  "geometry": {"coordinates":[151.01580810600001,-34.0085296631],"type":"Point"}
}