{
  "type": "Feature",
  "properties": {
    "addr:full":"21 Main St Lithgow NSW 2790",
    "addr:housenumber":"21",
    "addr:postcode":"2790",
    "addr:street":"Main St",
    "iso:country":"AU",
    "sg:address":"21 Main St",
    "sg:city":"Lithgow",
    "sg:classifiers":[
        {
            "category":"Professional",
            "subcategory":"Accounting & Tax Preparation",
            "type":"Services"
        }
    ],
    "sg:phone":"+61 2 6352 3152",
    "sg:postcode":"2790",
    "sg:province":"NSW",
    "sg:tags":[
        "accountant",
        "auditor"
    ],
    "wof:name":"Rodwell Shelley June",
    "wof:placetype":"venue"
},
  "geometry": {"coordinates":[150.15447998100001,-33.4822311401],"type":"Point"}
}