{
  "type": "Feature",
  "properties": {
    "addr:full":"90 Goodwood Pde Burswood WA 6100",
    "addr:housenumber":"90",
    "addr:postcode":"6100",
    "addr:street":"Goodwood Pde",
    "iso:country":"AU",
    "sg:address":"90 Goodwood Pde",
    "sg:city":"Burswood",
    "sg:classifiers":[
        {
            "category":"Professional",
            "subcategory":"Business Services",
            "type":"Services"
        }
    ],
    "sg:phone":"+61 413 453 453",
    "sg:postcode":"6100",
    "sg:province":"WA",
    "sg:tags":[
        "small",
        "advisory"
    ],
    "wof:name":"Action International",
    "wof:placetype":"venue"
},
  "geometry": {"coordinates":[115.900627136,-31.9588394165],"type":"Point"}
}