{
  "type": "Feature",
  "properties": {
    "iso:country":"AU",
    "sg:address":"24 Church St",
    "sg:city":"Dubbo",
    "sg:classifiers":[
        {
            "category":"Personal",
            "subcategory":"Massage",
            "type":"Services"
        }
    ],
    "sg:phone":"+61 417 077 983",
    "sg:postcode":"2830",
    "sg:province":"NSW",
    "sg:tags":[
        "therapy"
    ],
    "wof:name":"April Southward",
    "wof:placetype":"venue"
},
  "geometry": {"coordinates":[148.60226440400001,-32.2468948364],"type":"Point"}
}