{
  "type": "Feature",
  "properties": {
    "addr:full":"207 Mary St Gympie QLD 4570",
    "addr:housenumber":"207",
    "addr:postcode":"4570",
    "addr:street":"Mary St",
    "iso:country":"AU",
    "sg:address":"207 Mary St",
    "sg:city":"Gympie",
    "sg:classifiers":[
        {
            "category":"Personal",
            "subcategory":"Beauty Salon",
            "type":"Services"
        }
    ],
    "sg:phone":"+61 7 5482 6665",
    "sg:postcode":"4570",
    "sg:province":"QLD",
    "sg:tags":[
        "wig",
        "hairpiece"
    ],
    "wof:name":"Hair Review",
    "wof:placetype":"venue"
},
  "geometry": {"coordinates":[152.65968322800001,-26.1889324188],"type":"Point"}
}