{
  "type": "Feature",
  "properties": {
    "addr:full":"3 Sydney St Willoughby NSW 2068",
    "addr:housenumber":"3",
    "addr:postcode":"2068",
    "addr:street":"Sydney St",
    "iso:country":"AU",
    "sg:address":"3 Sydney St",
    "sg:city":"Willoughby",
    "sg:classifiers":[
        {
            "category":"Building & Trades",
            "subcategory":"Landscaping Services",
            "type":"Services"
        }
    ],
    "sg:phone":"+61 2 9958 8502",
    "sg:postcode":"2068",
    "sg:province":"NSW",
    "sg:tags":[
        "gardener"
    ],
    "wof:name":"Mick The Gardener",
    "wof:placetype":"venue"
},
  "geometry": {"coordinates":[151.19294738799999,-33.8078613281],"type":"Point"}
}