{
  "type": "Feature",
  "properties": {
    "addr:full":"2/ 2 Charlotte St Ashfield NSW 2131",
    "addr:housenumber":"/ 2",
    "addr:postcode":"2131",
    "addr:street":"Charlotte St",
    "iso:country":"AU",
    "sg:address":"2/ 2 Charlotte St",
    "sg:city":"Ashfield",
    "sg:classifiers":[
        {
            "category":"Education",
            "subcategory":"Special Training",
            "type":"Public Place"
        }
    ],
    "sg:phone":"+61 2 9797 1799",
    "sg:postcode":"2131",
    "sg:province":"NSW",
    "sg:tags":[
        "tuition-educational"
    ],
    "wof:name":"Kip McGrath Education Centres",
    "wof:placetype":"venue"
},
  "geometry": {"coordinates":[151.125457764,-33.8870697021],"type":"Point"}
}