{
  "type": "Feature",
  "properties": {
    "addr:full":"10-16 Peel St Garbutt QLD 4814",
    "addr:housenumber":"10-16",
    "addr:postcode":"4814",
    "addr:street":"Peel St",
    "iso:country":"AU",
    "sg:address":"10-16 Peel St",
    "sg:city":"Garbutt",
    "sg:classifiers":[
        {
            "category":"Travel",
            "subcategory":"Hotels & Motels",
            "type":"Entertainment"
        }
    ],
    "sg:phone":"+61 7 4775 1170",
    "sg:postcode":"4814",
    "sg:province":"QLD",
    "wof:name":"Townsville Palms Lodge",
    "wof:placetype":"venue"
},
  "geometry": {"coordinates":[146.776871,-19.263422],"type":"Point"}
}