{
  "type": "Feature",
  "properties": {
    "addr:full":"PO Box 258 Robina Delivery Centre QLD 4226",
    "addr:postcode":"4226",
    "iso:country":"AU",
    "sg:address":"PO Box 258",
    "sg:city":"Robina Delivery Centre",
    "sg:classifiers":[
        {
            "category":"Shopping",
            "subcategory":"Bicycles & Sporting Goods",
            "type":"Retail Goods"
        }
    ],
    "sg:phone":"+61 413 543 558",
    "sg:postcode":"4226",
    "sg:province":"QLD",
    "sg:tags":[
        "chemical",
        "equipment",
        "pool",
        "swimming"
    ],
    "wof:name":"AAA Pool Care",
    "wof:placetype":"venue"
},
  "geometry": {"coordinates":[153.39210510300001,-28.0869750977],"type":"Point"}
}