{
  "type": "Feature",
  "properties": {
    "addr:full":"90 a Newlands Rd Reservoir VIC 3073",
    "addr:housenumber":"90 a",
    "addr:postcode":"3073",
    "addr:street":"Newlands Rd",
    "iso:country":"AU",
    "sg:address":"90 a Newlands Rd",
    "sg:city":"Reservoir",
    "sg:classifiers":[
        {
            "category":"Shopping",
            "subcategory":"Clothing, Apparel, & Fashions",
            "type":"Retail Goods"
        }
    ],
    "sg:phone":"+61 3 9462 0033",
    "sg:postcode":"3073",
    "sg:province":"VIC",
    "sg:tags":[
        "boutique"
    ],
    "wof:name":"Fashion Clearance City",
    "wof:placetype":"venue"
},
  "geometry": {"coordinates":[144.983642578,-37.7143630981],"type":"Point"}
}