{
  "type": "Feature",
  "properties": {
    "addr:full":"42 Barton St Everton Park QLD 4053",
    "addr:housenumber":"42",
    "addr:postcode":"4053",
    "addr:street":"Barton St",
    "iso:country":"AU",
    "sg:address":"42 Barton St",
    "sg:city":"Everton Park",
    "sg:classifiers":[
        {
            "category":"Building & Trades",
            "subcategory":"Plumbing",
            "type":"Services"
        }
    ],
    "sg:phone":"+61 7 3355 1367",
    "sg:postcode":"4053",
    "sg:province":"QLD",
    "sg:tags":[
        "plumber",
        "gasfitters"
    ],
    "wof:name":"Discount Drain Cleaning",
    "wof:placetype":"venue"
},
  "geometry": {"coordinates":[152.983886719,-27.4003067017],"type":"Point"}
}