{
  "type": "Feature",
  "properties": {
    "addr:full":"5a Mobbs La Carlingford NSW 2118",
    "addr:housenumber":"5a",
    "addr:postcode":"2118",
    "addr:street":"Mobbs La",
    "iso:country":"AU",
    "sg:address":"5a Mobbs La",
    "sg:city":"Carlingford",
    "sg:classifiers":[
        {
            "category":"Fast Food",
            "type":"Food & Drink"
        }
    ],
    "sg:phone":"+61 2 9804 0883",
    "sg:postcode":"2118",
    "sg:province":"NSW",
    "sg:tags":[
        "away",
        "take"
    ],
    "wof:name":"Golden Bowl Kitchen",
    "wof:placetype":"venue"
},
  "geometry": {"coordinates":[151.062057495,-33.7861938477],"type":"Point"}
}