{
  "type": "Feature",
  "properties": {
    "iso:country":"AU",
    "sg:address":"53 Aitken St",
    "sg:city":"Williamstown",
    "sg:classifiers":[
        {
            "category":"Coffee & Tea",
            "type":"Food & Drink"
        }
    ],
    "sg:phone":"+61 3 9399 9009",
    "sg:postcode":"3016",
    "sg:province":"VIC",
    "sg:tags":[
        "kayak",
        "canoe"
    ],
    "wof:name":"Addicted To Fun",
    "wof:placetype":"venue"
},
  "geometry": {"coordinates":[144.90628051799999,-37.8649330139],"type":"Point"}
}