{
  "type": "Feature",
  "properties": {
    "iso:country":"AU",
    "sg:address":"Mt George Rd",
    "sg:city":"George Town",
    "sg:classifiers":[
        {
            "category":"Social Services",
            "subcategory":"Adult Care",
            "type":"Services"
        }
    ],
    "sg:phone":"+61 3 6382 1329",
    "sg:postcode":"7253",
    "sg:province":"TAS",
    "sg:tags":[
        "towing"
    ],
    "wof:name":"Mt George Auto Wreckers",
    "wof:placetype":"venue"
},
  "geometry": {"coordinates":[146.84490966800001,-41.1095237732],"type":"Point"}
}