{
  "type": "Feature",
  "properties": {
    "iso:country":"AU",
    "sg:address":"10 Dellview Crt",
    "sg:city":"Donvale",
    "sg:classifiers":[
        {
            "category":"Personal",
            "type":"Services"
        }
    ],
    "sg:phone":"+61 3 9841 9393",
    "sg:postcode":"3111",
    "sg:province":"VIC",
    "sg:tags":[
        "counselling",
        "alcohol",
        "drug"
    ],
    "wof:name":"AAA Access Awareness",
    "wof:placetype":"venue"
},
  "geometry": {"coordinates":[145.18504333499999,-37.774143219],"type":"Point"}
}