{
  "type": "Feature",
  "properties": {
    "addr:full":"917 Main Rd Eltham VIC 3095",
    "addr:housenumber":"917",
    "addr:postcode":"3095",
    "addr:street":"Main Rd",
    "iso:country":"AU",
    "sg:address":"917 Main Rd",
    "sg:city":"Eltham",
    "sg:classifiers":[
        {
            "category":"Health Services",
            "subcategory":"Dentist",
            "type":"Services"
        }
    ],
    "sg:phone":"+61 1300 360 054",
    "sg:postcode":"3095",
    "sg:province":"VIC",
    "wof:name":"School Dental Service",
    "wof:placetype":"venue"
},
  "geometry": {"coordinates":[145.147994995,-37.7146492004],"type":"Point"}
}