{
  "type": "Feature",
  "properties": {
    "addr:full":"562 Kalamunda Rd High Wycombe WA 6057",
    "addr:housenumber":"562",
    "addr:postcode":"6057",
    "addr:street":"Kalamunda Rd",
    "iso:country":"AU",
    "sg:address":"562 Kalamunda Rd",
    "sg:city":"High Wycombe",
    "sg:classifiers":[
        {
            "category":"Utilities",
            "subcategory":"Electric",
            "type":"Services"
        }
    ],
    "sg:phone":"+61 419 045 440",
    "sg:postcode":"6057",
    "sg:province":"WA",
    "sg:tags":[
        "hoist"
    ],
    "wof:name":"Capizzi Contracting & Mobile Breakdown Services",
    "wof:placetype":"venue"
},
  "geometry": {"coordinates":[116.00176239,-31.9343261719],"type":"Point"}
}