{
  "type": "Feature",
  "properties": {
    "addr:full":"Shop 18 Dog Swamp Shopping Centre, Wanneroo Rd Yokine WA 6060",
    "addr:housenumber":"shop 18",
    "addr:postcode":"6060",
    "addr:street":"Dog;Wanneroo Rd",
    "iso:country":"AU",
    "sg:address":"Shop 18 Dog Swamp Shopping Centre, Wanneroo Rd",
    "sg:city":"Yokine",
    "sg:classifiers":[
        {
            "category":"Travel",
            "subcategory":"Travel Agent",
            "type":"Entertainment"
        }
    ],
    "sg:phone":"+61 13 18 66",
    "sg:postcode":"6060",
    "sg:province":"WA",
    "sg:tags":[
        "consultant"
    ],
    "wof:name":"Flight Centre",
    "wof:placetype":"venue"
},
  "geometry": {"coordinates":[115.843482971,-31.903635025],"type":"Point"}
}