{
  "type": "Feature",
  "properties": {
    "addr:full":"PO Box 326 Penrith NSW 2751",
    "addr:postcode":"2751",
    "iso:country":"AU",
    "sg:address":"PO Box 326",
    "sg:city":"Penrith",
    "sg:classifiers":[
        {
            "category":"Building & Trades",
            "subcategory":"Equipment Rental",
            "type":"Services"
        }
    ],
    "sg:phone":"+61 2 9677 2739",
    "sg:postcode":"2751",
    "sg:province":"NSW",
    "sg:tags":[
        "crane",
        "hire"
    ],
    "wof:name":"PC Cranes",
    "wof:placetype":"venue"
},
  "geometry": {"coordinates":[150.69601440400001,-33.7440681458],"type":"Point"}
}