{
  "type": "Feature",
  "properties": {
    "addr:full":"Hobart Gastrointestinal Centre, Suite 6 Hobart Pri Hobart TAS 7000",
    "addr:postcode":"7000",
    "iso:country":"AU",
    "sg:address":"Hobart Gastrointestinal Centre, Suite 6 Hobart Pri",
    "sg:city":"Hobart",
    "sg:classifiers":[
        {
            "category":"Health Services",
            "subcategory":"Doctor",
            "type":"Services"
        }
    ],
    "sg:phone":"+61 3 6214 3593",
    "sg:postcode":"7000",
    "sg:province":"TAS",
    "sg:tags":[
        "medical",
        "practitioner"
    ],
    "wof:name":"Hobart Gastrointestinal Centre",
    "wof:placetype":"venue"
},
  "geometry": {"coordinates":[147.330566406,-42.8816184998],"type":"Point"}
}