{
  "type": "Feature",
  "properties": {
    "addr:full":"165 Whitehorse Rd Balwyn VIC 3103",
    "addr:housenumber":"165",
    "addr:postcode":"3103",
    "addr:street":"Whitehorse Rd",
    "iso:country":"AU",
    "sg:address":"165 Whitehorse Rd",
    "sg:city":"Balwyn",
    "sg:classifiers":[
        {
            "category":"Personal",
            "type":"Services"
        }
    ],
    "sg:phone":"+61 3 9528 4213",
    "sg:postcode":"3103",
    "sg:province":"VIC",
    "sg:tags":[
        "wallpapering",
        "wallcovering"
    ],
    "wof:name":"Walter Kay",
    "wof:placetype":"venue"
},
  "geometry": {"coordinates":[145.06880188,-37.8111915588],"type":"Point"}
}