{
  "type": "Feature",
  "properties": {
    "addr:full":"94 Blechynden St Bridgetown WA 6255",
    "addr:housenumber":"94",
    "addr:postcode":"6255",
    "addr:street":"Blechynden St",
    "iso:country":"AU",
    "sg:address":"94 Blechynden St",
    "sg:city":"Bridgetown",
    "sg:classifiers":[
        {
            "category":"Building & Trades",
            "subcategory":"Construction",
            "type":"Services"
        }
    ],
    "sg:phone":"+61 8 9761 2991",
    "sg:postcode":"6255",
    "sg:province":"WA",
    "sg:tags":[
        "contractor"
    ],
    "wof:name":"Bridgetown Residential Contractors",
    "wof:placetype":"venue"
},
  "geometry": {"coordinates":[116.153373718,-33.9611740112],"type":"Point"}
}