{
  "type": "Feature",
  "properties": {
    "addr:full":"1 Cadell St Dubbo NSW 2830",
    "addr:housenumber":"1",
    "addr:postcode":"2830",
    "addr:street":"Cadell St",
    "iso:country":"AU",
    "sg:address":"1 Cadell St",
    "sg:city":"Dubbo",
    "sg:classifiers":[
        {
            "category":"Government",
            "subcategory":"Court House",
            "type":"Public Place"
        }
    ],
    "sg:phone":"+61 2 6882 9014",
    "sg:postcode":"2830",
    "sg:province":"NSW",
    "sg:tags":[
        "personal",
        "marriage",
        "family",
        "counselling"
    ],
    "wof:name":"Gamblers Anonymous",
    "wof:placetype":"venue"
},
  "geometry": {"coordinates":[148.60578918499999,-32.2530174255],"type":"Point"}
}