{
  "type": "Feature",
  "properties": {
    "addr:full":"Level 2, 52-58 William St East Sydney NSW 2010",
    "addr:housenumber":"52-58",
    "addr:postcode":"2010",
    "addr:street":"William St East",
    "iso:country":"AU",
    "sg:address":"Level 2, 52-58 William St",
    "sg:city":"East Sydney",
    "sg:classifiers":[
        {
            "category":"Building & Trades",
            "subcategory":"Landscaping Services",
            "type":"Services"
        }
    ],
    "sg:phone":"+61 2 8244 8900",
    "sg:postcode":"2010",
    "sg:province":"NSW",
    "sg:tags":[
        "architect",
        "landscape"
    ],
    "wof:name":"Context Landscape Design",
    "wof:placetype":"venue"
},
  "geometry": {"coordinates":[151.21525573700001,-33.8739433289],"type":"Point"}
}