{
  "type": "Feature",
  "properties": {
    "iso:country":"AU",
    "sg:address":"Floor 1 Atwell Arc",
    "sg:city":"Fremantle",
    "sg:classifiers":[
        {
            "category":"Shopping",
            "subcategory":"Jewelry",
            "type":"Retail Goods"
        }
    ],
    "sg:phone":"+61 8 9430 4558",
    "sg:postcode":"6160",
    "sg:province":"WA",
    "sg:tags":[
        "jeweller"
    ],
    "wof:name":"Asteroid Gems",
    "wof:placetype":"venue"
},
  "geometry": {"coordinates":[115.746788,-32.053967],"type":"Point"}
}