{
  "type": "Feature",
  "properties": {
    "addr:full":"25 Coondoo St Kuranda QLD 4872",
    "addr:housenumber":"25",
    "addr:postcode":"4872",
    "addr:street":"Coondoo St",
    "iso:country":"AU",
    "sg:address":"25 Coondoo St",
    "sg:city":"Kuranda",
    "sg:classifiers":[
        {
            "category":"Cafe",
            "type":"Food & Drink"
        }
    ],
    "sg:phone":"+61 7 4093 9466",
    "sg:postcode":"4872",
    "sg:province":"QLD",
    "wof:name":"Windmill Cafe",
    "wof:placetype":"venue"
},
  "geometry": {"coordinates":[145.63583374000001,-16.819480896],"type":"Point"}
}