{
  "type": "Feature",
  "properties": {
    "addr:full":"Unit 4, 3 Gatwick Rd Bayswater North VIC 3153",
    "addr:housenumber":"3",
    "addr:postcode":"3153",
    "addr:street":"Gatwick Rd",
    "iso:country":"AU",
    "sg:address":"Unit 4, 3 Gatwick Rd",
    "sg:city":"Bayswater North",
    "sg:classifiers":[
        {
            "category":"Wholesale",
            "subcategory":"Medical Equipment & Supplies",
            "type":"Manufacturing & Wholesale Goods"
        }
    ],
    "sg:phone":"+61 3 9761 6336",
    "sg:postcode":"3153",
    "sg:province":"VIC",
    "sg:tags":[
        "aid",
        "care",
        "health",
        "home"
    ],
    "wof:name":"Healthcare Lifting Specialists",
    "wof:placetype":"venue"
},
  "geometry": {"coordinates":[145.296340942,-37.8232650757],"type":"Point"}
}