{
  "type": "Feature",
  "properties": {
    "addr:full":"PO Box 79 Red Hill South VIC 3937",
    "addr:postcode":"3937",
    "iso:country":"AU",
    "sg:address":"PO Box 79",
    "sg:city":"Red Hill South",
    "sg:classifiers":[
        {
            "category":"Personal",
            "subcategory":"Massage",
            "type":"Services"
        }
    ],
    "sg:phone":"+61 412 036 010",
    "sg:postcode":"3937",
    "sg:province":"VIC",
    "sg:tags":[
        "therapy"
    ],
    "wof:name":"Glynis Elkins",
    "wof:placetype":"venue"
},
  "geometry": {"coordinates":[145.043655395,-38.3980789185],"type":"Point"}
}