{
  "type": "Feature",
  "properties": {
    "iso:country":"AU",
    "sg:address":"Unit 3 11 Richardson St",
    "sg:city":"South Perth",
    "sg:classifiers":[
        {
            "category":"Professional",
            "subcategory":"Management & Consulting",
            "type":"Services"
        }
    ],
    "sg:phone":"+61 8 9474 3111",
    "sg:postcode":"6151",
    "sg:province":"WA",
    "sg:tags":[
        "consultant"
    ],
    "wof:name":"Carney & Associates",
    "wof:placetype":"venue"
},
  "geometry": {"coordinates":[115.850243,-31.977629],"type":"Point"}
}