{
  "type": "Feature",
  "properties": {
    "iso:country":"AU",
    "sg:address":"11 Victoria St",
    "sg:city":"Wollongong",
    "sg:classifiers":[
        {
            "category":"Real Estate",
            "subcategory":"Real Estate Agent",
            "type":"Services"
        }
    ],
    "sg:phone":"+61 2 4228 8445",
    "sg:postcode":"2500",
    "sg:province":"NSW",
    "wof:name":"Estate Agents Co-operative Ltd",
    "wof:placetype":"venue"
},
  "geometry": {"coordinates":[150.892014,-34.422276],"type":"Point"}
}