{
  "type": "Feature",
  "properties": {
    "addr:full":"11 Victoria St Wollongong NSW 2500",
    "addr:housenumber":"11",
    "addr:postcode":"2500",
    "addr:street":"Victoria St",
    "iso:country":"AU",
    "sg:address":"11 Victoria St",
    "sg:city":"Wollongong",
    "sg:classifiers":[
        {
            "category":"Real Estate",
            "subcategory":"Real Estate Agent",
            "type":"Services"
        }
    ],
    "sg:phone":"+61 2 4228 8445",
    "sg:postcode":"2500",
    "sg:province":"NSW",
    "wof:name":"Estate Agents Co-operative Ltd",
    "wof:placetype":"venue"
},
  "geometry": {"coordinates":[150.89201399999999,-34.422276],"type":"Point"}
}