{
  "type": "Feature",
  "properties": {
    "addr:full":"3 McDonald St Mortlake NSW 2137",
    "addr:housenumber":"3",
    "addr:postcode":"2137",
    "addr:street":"Mcdonald St",
    "iso:country":"AU",
    "sg:address":"3 McDonald St",
    "sg:city":"Mortlake",
    "sg:classifiers":[
        {
            "category":"Manufacturing",
            "subcategory":"Furniture",
            "type":"Manufacturing & Wholesale Goods"
        }
    ],
    "sg:phone":"+61 2 9743 2540",
    "sg:postcode":"2137",
    "sg:province":"NSW",
    "sg:tags":[
        "builder",
        "designer",
        "custom"
    ],
    "wof:name":"Casadei Furniture",
    "wof:placetype":"venue"
},
  "geometry": {"coordinates":[151.107421875,-33.8422813416],"type":"Point"}
}