{
  "type": "Feature",
  "properties": {
    "addr:full":"1 Burwood Hwy Wantirna VIC 3152",
    "addr:housenumber":"1",
    "addr:postcode":"3152",
    "addr:street":"Burwood Hwy",
    "iso:country":"AU",
    "sg:address":"1 Burwood Hwy",
    "sg:city":"Wantirna",
    "sg:classifiers":[
        {
            "category":"Freight",
            "type":"Transportation"
        }
    ],
    "sg:phone":"+61 3 9801 2366",
    "sg:postcode":"3152",
    "sg:province":"VIC",
    "sg:tags":[
        "cargo",
        "container"
    ],
    "wof:name":"Geta Container",
    "wof:placetype":"venue"
},
  "geometry": {"coordinates":[145.20574951200001,-37.8593826294],"type":"Point"}
}