{
  "type": "Feature",
  "properties": {
    "addr:full":"Unit 16 100 Belmore Rd Riverwood NSW 2210",
    "addr:housenumber":"100",
    "addr:postcode":"2210",
    "addr:street":"Belmore Rd",
    "iso:country":"AU",
    "sg:address":"Unit 16 100 Belmore Rd",
    "sg:city":"Riverwood",
    "sg:classifiers":[
        {
            "category":"Banks & Credit Unions",
            "subcategory":"Investment Brokerage",
            "type":"Services"
        }
    ],
    "sg:phone":"+61 2 8525 7555",
    "sg:postcode":"2210",
    "sg:province":"NSW",
    "sg:tags":[
        "equipment",
        "spray",
        "painting",
        "supply"
    ],
    "wof:name":"ITW Finishing",
    "wof:placetype":"venue"
},
  "geometry": {"coordinates":[151.05174299999999,-33.954739],"type":"Point"}
}