{
  "type": "Feature",
  "properties": {
    "addr:full":"Unit 6 11 Cullen Pl Smithfield NSW 2164",
    "addr:housenumber":"11",
    "addr:postcode":"2164",
    "addr:street":"Cullen Pl",
    "iso:country":"AU",
    "sg:address":"Unit 6 11 Cullen Pl",
    "sg:city":"Smithfield",
    "sg:classifiers":[
        {
            "category":"Utilities",
            "subcategory":"Water",
            "type":"Services"
        }
    ],
    "sg:phone":"+61 2 9725 5590",
    "sg:postcode":"2164",
    "sg:province":"NSW",
    "sg:tags":[
        "hot",
        "system"
    ],
    "wof:name":"Raypak Australia Pty Ltd",
    "wof:placetype":"venue"
},
  "geometry": {"coordinates":[150.94992065400001,-33.84167099],"type":"Point"}
}