{
  "type": "Feature",
  "properties": {
    "addr:full":"282 City Rd Southbank VIC 3006",
    "addr:housenumber":"282",
    "addr:postcode":"3006",
    "addr:street":"City Rd",
    "iso:country":"AU",
    "sg:address":"282 City Rd",
    "sg:city":"Southbank",
    "sg:classifiers":[
        {
            "category":"Real Estate",
            "subcategory":"Real Estate Agent",
            "type":"Services"
        }
    ],
    "sg:phone":"+61 3 9695 5999",
    "sg:postcode":"3006",
    "sg:province":"VIC",
    "wof:name":"Rosin Smyth & Partners",
    "wof:placetype":"venue"
},
  "geometry": {"coordinates":[144.95909118599999,-37.8266029358],"type":"Point"}
}