{
  "type": "Feature",
  "properties": {
    "iso:country":"AU",
    "sg:address":"Lot 59 Beaufort St",
    "sg:city":"Toodyay",
    "sg:classifiers":[
        {
            "category":"Travel",
            "subcategory":"Hotels & Motels",
            "type":"Entertainment"
        }
    ],
    "sg:phone":"+61 8 9574 2636",
    "sg:postcode":"6566",
    "sg:province":"WA",
    "wof:name":"Pecan Hill B & B",
    "wof:placetype":"venue"
},
  "geometry": {"coordinates":[116.429253,-31.530561],"type":"Point"}
}