{
  "type": "Feature",
  "properties": {
    "iso:country":"AU",
    "sg:address":"851B Beaufort St",
    "sg:city":"Inglewood",
    "sg:classifiers":[
        {
            "category":"Personal",
            "subcategory":"Tattoo Parlor",
            "type":"Services"
        }
    ],
    "sg:phone":"+61 8 9370 3255",
    "sg:postcode":"6052",
    "sg:province":"WA",
    "sg:tags":[
        "tattooing"
    ],
    "wof:name":"Tattooing By Colette",
    "wof:placetype":"venue"
},
  "geometry": {"coordinates":[115.88398742699999,-31.9228172302],"type":"Point"}
}