{
  "type": "Feature",
  "properties": {
    "iso:country":"AU",
    "sg:address":"4 Darley St",
    "sg:city":"South Perth",
    "sg:classifiers":[
        {
            "category":"Real Estate",
            "subcategory":"Real Estate Agent",
            "type":"Services"
        }
    ],
    "sg:phone":"+61 8 9474 6244",
    "sg:postcode":"6151",
    "sg:province":"WA",
    "wof:name":"Landwest Estate Agency",
    "wof:placetype":"venue"
},
  "geometry": {"coordinates":[115.853912,-31.973757],"type":"Point"}
}