{
  "type": "Feature",
  "properties": {
    "iso:country":"AU",
    "sg:address":"Sharp St",
    "sg:city":"Donnybrook",
    "sg:classifiers":[
        {
            "category":"Wholesale",
            "subcategory":"Farm Supplies",
            "type":"Manufacturing & Wholesale Goods"
        }
    ],
    "sg:phone":"+61 8 9731 1308",
    "sg:postcode":"6239",
    "sg:province":"WA",
    "sg:tags":[
        "equipment"
    ],
    "wof:name":"Donnybrook Farm Service",
    "wof:placetype":"venue"
},
  "geometry": {"coordinates":[115.82428,-33.570553],"type":"Point"}
}