{
  "type": "Feature",
  "properties": {
    "iso:country":"AU",
    "sg:address":"524- 526 Lygon St",
    "sg:city":"Brunswick East",
    "sg:classifiers":[
        {
            "category":"Shopping",
            "subcategory":"Clothing, Apparel, & Fashions",
            "type":"Retail Goods"
        }
    ],
    "sg:phone":"+61 3 9386 0172",
    "sg:postcode":"3057",
    "sg:province":"VIC",
    "sg:tags":[
        "textile",
        "designer"
    ],
    "wof:name":"De Charmaine",
    "wof:placetype":"venue"
},
  "geometry": {"coordinates":[144.973510742,-37.7623786926],"type":"Point"}
}