{
  "type": "Feature",
  "properties": {
    "addr:full":"Lvl 5/ 14 Mt Gravatt-Capalaba Rd Upper Mt Gravatt QLD 4122",
    "addr:housenumber":"/ 14",
    "addr:postcode":"4122",
    "addr:street":"Mt Gravatt-Capalaba Rd Upper",
    "iso:country":"AU",
    "sg:address":"Lvl 5/ 14 Mt Gravatt-Capalaba Rd",
    "sg:city":"Upper Mt Gravatt",
    "sg:classifiers":[
        {
            "category":"Personal",
            "subcategory":"Skin Care",
            "type":"Services"
        }
    ],
    "sg:phone":"+61 7 3347 0900",
    "sg:postcode":"4122",
    "sg:province":"QLD",
    "sg:tags":[
        "information",
        "treatment",
        "smoker"
    ],
    "wof:name":"Matrix Laser Clinics",
    "wof:placetype":"venue"
},
  "geometry": {"coordinates":[153.081787109,-27.5594844818],"type":"Point"}
}