{
  "type": "Feature",
  "properties": {
    "iso:country":"AU",
    "sg:address":"Suite 17 178 Queen St St",
    "sg:city":"Marys",
    "sg:classifiers":[
        {
            "category":"Health Services",
            "subcategory":"Doctor",
            "type":"Services"
        }
    ],
    "sg:phone":"+61 2 9623 6244",
    "sg:postcode":"2760",
    "sg:province":"NSW",
    "sg:tags":[
        "nurse",
        "nursing"
    ],
    "sg:website":"http://premiercare.citysearch.com.au",
    "wof:name":"Premier Care Pty Ltd",
    "wof:placetype":"venue"
},
  "geometry": {"coordinates":[150.774002075,-33.7678031921],"type":"Point"}
}