{
  "type": "Feature",
  "properties": {
    "addr:full":"60 Miskin St Toowong QLD 4066",
    "addr:housenumber":"60",
    "addr:postcode":"4066",
    "addr:street":"Miskin St",
    "iso:country":"AU",
    "sg:address":"60 Miskin St",
    "sg:city":"Toowong",
    "sg:classifiers":[
        {
            "category":"Wholesale",
            "subcategory":"Office Equipment",
            "type":"Manufacturing & Wholesale Goods"
        }
    ],
    "sg:phone":"+61 7 3870 5876",
    "sg:postcode":"4066",
    "sg:province":"QLD",
    "sg:tags":[
        "packaging",
        "consultant"
    ],
    "wof:name":"Perceptions Design Pty Ltd",
    "wof:placetype":"venue"
},
  "geometry": {"coordinates":[152.98405456500001,-27.4833927155],"type":"Point"}
}