{
  "type": "Feature",
  "properties": {
    "addr:full":"2 Tudor Crt Glen Waverley VIC 3150",
    "addr:housenumber":"2",
    "addr:postcode":"3150",
    "addr:street":"Tudor Crt",
    "iso:country":"AU",
    "sg:address":"2 Tudor Crt",
    "sg:city":"Glen Waverley",
    "sg:classifiers":[
        {
            "category":"Professional",
            "subcategory":"Art Services",
            "type":"Services"
        }
    ],
    "sg:phone":"+61 417 563 133",
    "sg:postcode":"3150",
    "sg:province":"VIC",
    "sg:tags":[
        "decorator",
        "painter"
    ],
    "wof:name":"Frank's Painting Service",
    "wof:placetype":"venue"
},
  "geometry": {"coordinates":[145.145263672,-37.8989334106],"type":"Point"}
}