{
  "type": "Feature",
  "properties": {
    "addr:full":"122 Gilbert St Latrobe TAS 7307",
    "addr:housenumber":"122",
    "addr:postcode":"7307",
    "addr:street":"Gilbert St",
    "iso:country":"AU",
    "sg:address":"122 Gilbert St",
    "sg:city":"Latrobe",
    "sg:classifiers":[
        {
            "category":"Personal",
            "subcategory":"Beauty Salon",
            "type":"Services"
        }
    ],
    "sg:phone":"+61 3 6426 1213",
    "sg:postcode":"7307",
    "sg:province":"TAS",
    "sg:tags":[
        "hairdresser"
    ],
    "wof:name":"Latrobe Hair Designs",
    "wof:placetype":"venue"
},
  "geometry": {"coordinates":[146.41172800000001,-41.23571],"type":"Point"}
}