{
  "type": "Feature",
  "properties": {
    "addr:full":"PO Box 141 Preston VIC 3072",
    "addr:postcode":"3072",
    "iso:country":"AU",
    "sg:address":"PO Box 141",
    "sg:city":"Preston",
    "sg:classifiers":[
        {
            "category":"Coffee & Tea",
            "type":"Food & Drink"
        }
    ],
    "sg:phone":"+61 3 9478 3310",
    "sg:postcode":"3072",
    "sg:province":"VIC",
    "sg:tags":[
        "kayak",
        "canoe"
    ],
    "wof:name":"Paddle Sports Australia Whitewater Rafting Equipment",
    "wof:placetype":"venue"
},
  "geometry": {"coordinates":[145.00909423799999,-37.7416496277],"type":"Point"}
}