{
  "type": "Feature",
  "properties": {
    "iso:country":"AU",
    "sg:address":"126 Sturt St",
    "sg:city":"Townsville",
    "sg:classifiers":[
        {
            "category":"Food & Beverages",
            "subcategory":"Supermarket",
            "type":"Retail Goods"
        }
    ],
    "sg:phone":"+61 7 4772 6677",
    "sg:postcode":"4810",
    "sg:province":"QLD",
    "sg:tags":[
        "grocery",
        "store"
    ],
    "wof:name":"Woolworths Limited",
    "wof:placetype":"venue"
},
  "geometry": {"coordinates":[146.814178,-19.261408],"type":"Point"}
}