{
  "type": "Feature",
  "properties": {
    "iso:country":"AU",
    "sg:address":"78 Stewart Ave",
    "sg:city":"Hamilton South",
    "sg:classifiers":[
        {
            "category":"Organizations",
            "subcategory":"Community Association",
            "type":"Services"
        }
    ],
    "sg:phone":"+61 2 4969 3171",
    "sg:postcode":"2303",
    "sg:province":"NSW",
    "sg:tags":[
        "organisation",
        "family",
        "welfare"
    ],
    "wof:name":"SIDS & Kids",
    "wof:placetype":"venue"
},
  "geometry": {"coordinates":[151.75329600000001,-32.931469],"type":"Point"}
}