{
  "type": "Feature",
  "properties": {
    "addr:full":"PO Box 555 Ocean Grove VIC 3226",
    "addr:postcode":"3226",
    "iso:country":"AU",
    "sg:address":"PO Box 555",
    "sg:city":"Ocean Grove",
    "sg:classifiers":[
        {
            "category":"Building & Trades",
            "subcategory":"Construction",
            "type":"Services"
        }
    ],
    "sg:phone":"+61 410 659 469",
    "sg:postcode":"3226",
    "sg:province":"VIC",
    "sg:tags":[
        "plasterboard",
        "plasterer",
        "fixer"
    ],
    "wof:name":"Precision Plastering (VIC) PTY LTD",
    "wof:placetype":"venue"
},
  "geometry": {"coordinates":[144.53810100000001,-38.265339],"type":"Point"}
}