{
  "type": "Feature",
  "properties": {
    "addr:full":"Punchbowl Rd San Remo VIC 3925",
    "addr:postcode":"3925",
    "addr:street":"Punchbowl Rd",
    "iso:country":"AU",
    "sg:address":"Punchbowl Rd",
    "sg:city":"San Remo",
    "sg:classifiers":[
        {
            "category":"Building & Trades",
            "subcategory":"Equipment Rental",
            "type":"Services"
        }
    ],
    "sg:phone":"+61 3 5678 5276",
    "sg:postcode":"3925",
    "sg:province":"VIC",
    "sg:tags":[
        "demolition",
        "contractor"
    ],
    "wof:name":"Labounty Equipment",
    "wof:placetype":"venue"
},
  "geometry": {"coordinates":[145.40818786599999,-38.5297279358],"type":"Point"}
}