{
  "type": "Feature",
  "properties": {
    "iso:country":"AU",
    "sg:address":"Shop 11",
    "sg:city":"Woodlake Village Shopping Centre Ellenbrook",
    "sg:classifiers":[
        {
            "category":"Real Estate",
            "subcategory":"Real Estate Agent",
            "type":"Services"
        }
    ],
    "sg:phone":"+61 8 9296 7788",
    "sg:postcode":"6069",
    "sg:province":"WA",
    "wof:name":"Active Realty (W A)",
    "wof:placetype":"venue"
},
  "geometry": {"coordinates":[115.97013855,-31.7888202667],"type":"Point"}
}