{
  "type": "Feature",
  "properties": {
    "iso:country":"AU",
    "sg:address":"28 Shettleston St",
    "sg:city":"Rocklea",
    "sg:classifiers":[
        {
            "category":"Professional",
            "type":"Services"
        }
    ],
    "sg:phone":"+61 7 3274 1138",
    "sg:postcode":"4106",
    "sg:province":"QLD",
    "sg:tags":[
        "transport"
    ],
    "wof:name":"DTC Pty Ltd",
    "wof:placetype":"venue"
},
  "geometry": {"coordinates":[153.000289917,-27.561832428],"type":"Point"}
}