{
  "type": "Feature",
  "properties": {
    "iso:country":"AU",
    "sg:address":"Smith St",
    "sg:city":"Parndana",
    "sg:classifiers":[
        {
            "category":"Health Services",
            "subcategory":"Doctor",
            "type":"Services"
        }
    ],
    "sg:phone":"+61 8 8559 6166",
    "sg:postcode":"5220",
    "sg:province":"SA",
    "sg:tags":[
        "medical",
        "practitioner"
    ],
    "wof:name":"Parndana Health Centre",
    "wof:placetype":"venue"
},
  "geometry": {"coordinates":[137.25889587399999,-35.785785675],"type":"Point"}
}