{
  "type": "Feature",
  "properties": {
    "addr:full":"PO Box 5382 Maroochydore BC QLD 4558",
    "addr:postcode":"qld 4558",
    "iso:country":"AU",
    "sg:address":"PO Box 5382",
    "sg:city":"Maroochydore BC",
    "sg:classifiers":[
        {
            "category":"Professional",
            "subcategory":"Detective & Security Services",
            "type":"Services"
        }
    ],
    "sg:phone":"+61 408 730 786",
    "sg:postcode":"4558",
    "sg:province":"QLD",
    "sg:tags":[
        "guard",
        "patrol"
    ],
    "wof:name":"Gotcha Investigations",
    "wof:placetype":"venue"
},
  "geometry": {"coordinates":[153.09274292000001,-26.6657295227],"type":"Point"}
}