{
  "type": "Feature",
  "properties": {
    "addr:full":"530 Empire Bay Drv Bensville NSW 2251",
    "addr:housenumber":"530",
    "addr:postcode":"2251",
    "addr:street":"Empire Bay Drv",
    "iso:country":"AU",
    "sg:address":"530 Empire Bay Drv",
    "sg:city":"Bensville",
    "sg:classifiers":[
        {
            "category":"Professional",
            "subcategory":"Detective & Security Services",
            "type":"Services"
        }
    ],
    "sg:phone":"+61 2 4368 4207",
    "sg:postcode":"2251",
    "sg:province":"NSW",
    "sg:tags":[
        "consultant",
        "system"
    ],
    "wof:name":"Peak NSW Pty Ltd",
    "wof:placetype":"venue"
},
  "geometry": {"coordinates":[151.38557434099999,-33.5038146973],"type":"Point"}
}