{
  "type": "Feature",
  "properties": {
    "addr:full":"Tol Tol Rd Robinvale VIC 3549",
    "addr:postcode":"3549",
    "addr:street":"Tol Tol Rd",
    "iso:country":"AU",
    "sg:address":"Tol Tol Rd",
    "sg:city":"Robinvale",
    "sg:classifiers":[
        {
            "category":"Farming",
            "subcategory":"Orchard",
            "type":"Manufacturing & Wholesale Goods"
        }
    ],
    "sg:phone":"+61 3 5026 3867",
    "sg:postcode":"3549",
    "sg:province":"VIC",
    "sg:tags":[
        "citrus",
        "fruit",
        "grower"
    ],
    "wof:name":"Payne P G & C A",
    "wof:placetype":"venue"
},
  "geometry": {"coordinates":[142.80877685600001,-34.6211929321],"type":"Point"}
}