{
  "type": "Feature",
  "properties": {
    "addr:full":"52 Bourke St Tamworth NSW 2340",
    "addr:housenumber":"52",
    "addr:postcode":"2340",
    "addr:street":"Bourke St",
    "iso:country":"AU",
    "sg:address":"52 Bourke St",
    "sg:city":"Tamworth",
    "sg:classifiers":[
        {
            "category":"Utilities",
            "subcategory":"Electric",
            "type":"Services"
        }
    ],
    "sg:phone":"+61 2 6766 8579",
    "sg:postcode":"2340",
    "sg:province":"NSW",
    "sg:tags":[
        "electrical",
        "contractor"
    ],
    "wof:name":"Berthaly D A & A E Electrical Contractors",
    "wof:placetype":"venue"
},
  "geometry": {"coordinates":[150.932983398,-31.0847702026],"type":"Point"}
}