{
  "type": "Feature",
  "properties": {
    "iso:country":"AU",
    "sg:address":"168 Willarong Rd",
    "sg:city":"Caringbah",
    "sg:classifiers":[
        {
            "category":"Professional",
            "subcategory":"Secretarial Services",
            "type":"Services"
        }
    ],
    "sg:phone":"+61 2 9526 2331",
    "sg:postcode":"2229",
    "sg:province":"NSW",
    "sg:tags":[
        "typing"
    ],
    "wof:name":"Business Express",
    "wof:placetype":"venue"
},
  "geometry": {"coordinates":[151.12068176299999,-34.0396080017],"type":"Point"}
}