{
  "type": "Feature",
  "properties": {
    "addr:full":"19 Price St Alice Springs NT 0870",
    "addr:housenumber":"19",
    "addr:postcode":"nt 0870",
    "addr:street":"Price St",
    "iso:country":"AU",
    "sg:address":"19 Price St",
    "sg:city":"Alice Springs",
    "sg:classifiers":[
        {
            "category":"Building & Trades",
            "subcategory":"Equipment Rental",
            "type":"Services"
        }
    ],
    "sg:phone":"+61 8 8953 5900",
    "sg:postcode":"0870",
    "sg:province":"NT",
    "sg:tags":[
        "crane",
        "hire"
    ],
    "wof:name":"Russell Dehne Crane Hire",
    "wof:placetype":"venue"
},
  "geometry": {"coordinates":[133.86924743599999,-23.6956253052],"type":"Point"}
}