{
  "type": "Feature",
  "properties": {
    "addr:full":"60 Park Rd Camperdown VIC 3260",
    "addr:housenumber":"60",
    "addr:postcode":"3260",
    "addr:street":"Park Rd",
    "iso:country":"AU",
    "sg:address":"60 Park Rd",
    "sg:city":"Camperdown",
    "sg:classifiers":[
        {
            "category":"Utilities",
            "subcategory":"Electric",
            "type":"Services"
        }
    ],
    "sg:phone":"+61 408 502 926",
    "sg:postcode":"3260",
    "sg:province":"VIC",
    "sg:tags":[
        "electrical",
        "contractor"
    ],
    "wof:name":"Andrew Taylor Electrical Contractor",
    "wof:placetype":"venue"
},
  "geometry": {"coordinates":[143.11776733400001,-38.2307929993],"type":"Point"}
}