{
  "type": "Feature",
  "properties": {
    "addr:full":"42 Mons Ave West Ryde NSW 2114",
    "addr:housenumber":"42",
    "addr:postcode":"2114",
    "addr:street":"Mons Ave",
    "iso:country":"AU",
    "sg:address":"42 Mons Ave",
    "sg:city":"West Ryde",
    "sg:classifiers":[
        {
            "category":"Social Services",
            "subcategory":"Child Care",
            "type":"Services"
        }
    ],
    "sg:phone":"+61 2 9858 5333",
    "sg:postcode":"2114",
    "sg:province":"NSW",
    "wof:name":"Eikoh Seminar Australia Pty Ltd",
    "wof:placetype":"venue"
},
  "geometry": {"coordinates":[151.08515930199999,-33.8106536865],"type":"Point"}
}