{
  "type": "Feature",
  "properties": {
    "addr:full":"Cnr Crown & Dowsett St Geelong South VIC 3220",
    "addr:postcode":"3220",
    "addr:street":"Cnr",
    "iso:country":"AU",
    "sg:address":"Cnr Crown & Dowsett St",
    "sg:city":"Geelong South",
    "sg:classifiers":[
        {
            "category":"Banks & Credit Unions",
            "subcategory":"Bureau De Change",
            "type":"Services"
        }
    ],
    "sg:phone":"+61 3 5223 2299",
    "sg:postcode":"3220",
    "sg:province":"VIC",
    "sg:tags":[
        "supply",
        "equipment",
        "beating",
        "panel"
    ],
    "wof:name":"Stork Industrial Equipment Pty Ltd",
    "wof:placetype":"venue"
},
  "geometry": {"coordinates":[144.36785900000001,-38.167473],"type":"Point"}
}