{
  "type": "Feature",
  "properties": {
    "addr:full":"115 Campbellfield Ave Bradbury NSW 2560",
    "addr:housenumber":"115",
    "addr:postcode":"2560",
    "addr:street":"Campbellfield Ave",
    "iso:country":"AU",
    "sg:address":"115 Campbellfield Ave",
    "sg:city":"Bradbury",
    "sg:classifiers":[
        {
            "category":"Home & Garden",
            "subcategory":"Building Materials",
            "type":"Retail Goods"
        }
    ],
    "sg:phone":"+61 2 4627 2490",
    "sg:postcode":"2560",
    "sg:province":"NSW",
    "sg:tags":[
        "merchant",
        "glass",
        "glazier"
    ],
    "wof:name":"Chriss Glass & Glazing",
    "wof:placetype":"venue"
},
  "geometry": {"coordinates":[150.809692383,-34.0841407776],"type":"Point"}
}