{
  "type": "Feature",
  "properties": {
    "addr:full":"Unit 3/41- 43 Moorong St Wagga Wagga NSW 2650",
    "addr:housenumber":"43",
    "addr:postcode":"2650",
    "addr:street":"Moorong St",
    "iso:country":"AU",
    "sg:address":"Unit 3/41- 43 Moorong St",
    "sg:city":"Wagga Wagga",
    "sg:classifiers":[
        {
            "category":"Manufacturing",
            "subcategory":"Retail Goods",
            "type":"Manufacturing & Wholesale Goods"
        }
    ],
    "sg:phone":"+61 2 6971 0210",
    "sg:postcode":"2650",
    "sg:province":"NSW",
    "sg:tags":[
        "merchant",
        "pump",
        "mfrs"
    ],
    "sg:website":"http://www.bidgeepumps.com.au",
    "wof:name":"Bidgee Pumps & Irrigation",
    "wof:placetype":"venue"
},
  "geometry": {"coordinates":[147.34788513199999,-35.1078605652],"type":"Point"}
}