{
  "type": "Feature",
  "properties": {
    "iso:country":"AU",
    "sg:address":"237 Victoria Rd",
    "sg:city":"Gladesville",
    "sg:classifiers":[
        {
            "category":"Shopping",
            "subcategory":"Optical Goods",
            "type":"Retail Goods"
        }
    ],
    "sg:phone":"+61 2 9879 7600",
    "sg:postcode":"2111",
    "sg:province":"NSW",
    "sg:tags":[
        "dispenser",
        "prescription"
    ],
    "wof:name":"Eyeland Optical",
    "wof:placetype":"venue"
},
  "geometry": {"coordinates":[151.127044678,-33.8314437866],"type":"Point"}
}