{
  "type": "Feature",
  "properties": {
    "iso:country":"AU",
    "sg:address":"153D Henley Beach Rd",
    "sg:city":"Torrensville",
    "sg:classifiers":[
        {
            "category":"Shopping",
            "subcategory":"Clothing, Apparel, & Fashions",
            "type":"Retail Goods"
        }
    ],
    "sg:phone":"+61 8 8234 6007",
    "sg:postcode":"5031",
    "sg:province":"SA",
    "sg:tags":[
        "lady",
        "wear"
    ],
    "wof:name":"World Wide Women",
    "wof:placetype":"venue"
},
  "geometry": {"coordinates":[138.56309509299999,-34.9242591858],"type":"Point"}
}