{
  "type": "Feature",
  "properties": {
    "iso:country":"AU",
    "sg:address":"Shop 2, Springwood Plaza, 15 Dennis Rd",
    "sg:city":"Springwood",
    "sg:classifiers":[
        {
            "category":"Food & Beverages",
            "subcategory":"Specialty",
            "type":"Retail Goods"
        }
    ],
    "sg:phone":"+61 7 3209 1900",
    "sg:postcode":"4127",
    "sg:province":"QLD",
    "sg:tags":[
        "product",
        "health"
    ],
    "wof:name":"The Supplement Den",
    "wof:placetype":"venue"
},
  "geometry": {"coordinates":[153.129074097,-27.620721817],"type":"Point"}
}