{
  "type": "Feature",
  "properties": {
    "addr:full":"31 Skiddaw Crs Warrnambool VIC 3280",
    "addr:housenumber":"31",
    "addr:postcode":"3280",
    "addr:street":"Skiddaw Crs",
    "iso:country":"AU",
    "sg:address":"31 Skiddaw Crs",
    "sg:city":"Warrnambool",
    "sg:classifiers":[
        {
            "category":"Utilities",
            "subcategory":"Electric",
            "type":"Services"
        }
    ],
    "sg:phone":"+61 3 5561 3361",
    "sg:postcode":"3280",
    "sg:province":"VIC",
    "sg:tags":[
        "electrical",
        "contractor"
    ],
    "wof:name":"Armitstead A E & G M",
    "wof:placetype":"venue"
},
  "geometry": {"coordinates":[142.48323059099999,-38.3842582703],"type":"Point"}
}