{
  "type": "Feature",
  "properties": {
    "addr:full":"10 O'Neil St Unanderra NSW 2526",
    "addr:housenumber":"10",
    "addr:postcode":"2526",
    "addr:street":"O'Neil St",
    "iso:country":"AU",
    "sg:address":"10 O'Neil St",
    "sg:city":"Unanderra",
    "sg:classifiers":[
        {
            "category":"Wholesale",
            "subcategory":"Electrical",
            "type":"Manufacturing & Wholesale Goods"
        }
    ],
    "sg:phone":"+61 1800 728 866",
    "sg:postcode":"2526",
    "sg:province":"NSW",
    "sg:tags":[
        "wholesaler"
    ],
    "wof:name":"Amplex Industries",
    "wof:placetype":"venue"
},
  "geometry": {"coordinates":[150.85151672399999,-34.4493331909],"type":"Point"}
}