{
  "type": "Feature",
  "properties": {
    "addr:full":"1st Floor, 94 Pacific Hwy Tuggerah NSW 2259",
    "addr:housenumber":"94",
    "addr:postcode":"2259",
    "addr:street":"Pacific Hwy",
    "iso:country":"AU",
    "sg:address":"1st Floor, 94 Pacific Hwy",
    "sg:city":"Tuggerah",
    "sg:classifiers":[
        {
            "category":"Health Services",
            "subcategory":"Dentist",
            "type":"Services"
        }
    ],
    "sg:phone":"+61 2 4352 1577",
    "sg:postcode":"2259",
    "sg:province":"NSW",
    "wof:name":"Geoffrey R G Squires Dr",
    "wof:placetype":"venue"
},
  "geometry": {"coordinates":[151.41995239299999,-33.3062782288],"type":"Point"}
}