{
  "type": "Feature",
  "properties": {
    "iso:country":"AU",
    "sg:address":"126 Oxford Rd",
    "sg:city":"Cambridge Park",
    "sg:classifiers":[
        {
            "category":"Real Estate",
            "subcategory":"Real Estate Agent",
            "type":"Services"
        }
    ],
    "sg:phone":"+61 2 4722 2711",
    "sg:postcode":"2747",
    "sg:province":"NSW",
    "wof:name":"Harcourts NSW",
    "wof:placetype":"venue"
},
  "geometry": {"coordinates":[150.72096252399999,-33.7477073669],"type":"Point"}
}