{
  "type": "Feature",
  "properties": {
    "addr:full":"115 Hampton St Bridgetown WA 6255",
    "addr:housenumber":"115",
    "addr:postcode":"6255",
    "addr:street":"Hampton St",
    "iso:country":"AU",
    "sg:address":"115 Hampton St",
    "sg:city":"Bridgetown",
    "sg:classifiers":[
        {
            "category":"Utilities",
            "subcategory":"Recycling",
            "type":"Services"
        }
    ],
    "sg:phone":"+61 8 9761 2878",
    "sg:postcode":"6255",
    "sg:province":"WA",
    "wof:name":"Bridgetown Preloved Clothing",
    "wof:placetype":"venue"
},
  "geometry": {"coordinates":[116.137046814,-33.9577255249],"type":"Point"}
}