{
  "type": "Feature",
  "properties": {
    "iso:country":"AU",
    "sg:address":"13 Mitchell St",
    "sg:city":"Nyora",
    "sg:classifiers":[
        {
            "category":"Food & Beverages",
            "subcategory":"Groceries & Convenience Stores",
            "type":"Retail Goods"
        }
    ],
    "sg:phone":"+61 3 5659 6303",
    "sg:postcode":"3987",
    "sg:province":"VIC",
    "wof:name":"Nyora General Store",
    "wof:placetype":"venue"
},
  "geometry": {"coordinates":[145.67086792000001,-38.3340568542],"type":"Point"}
}