{
  "type": "Feature",
  "properties": {
    "addr:full":"110 Teven Rd Ballina NSW 2478",
    "addr:housenumber":"110",
    "addr:postcode":"2478",
    "addr:street":"Teven Rd",
    "iso:country":"AU",
    "sg:address":"110 Teven Rd",
    "sg:city":"Ballina",
    "sg:classifiers":[
        {
            "category":"Wholesale",
            "subcategory":"Machinery & Supplies",
            "type":"Manufacturing & Wholesale Goods"
        }
    ],
    "sg:phone":"+61 427 834 890",
    "sg:postcode":"2478",
    "sg:province":"NSW",
    "sg:tags":[
        "equipment",
        "hydraulic"
    ],
    "wof:name":"Paul Nielsen Hydraulic Hoses And Repairs",
    "wof:placetype":"venue"
},
  "geometry": {"coordinates":[153.521560669,-28.8527889252],"type":"Point"}
}