{
  "type": "Feature",
  "properties": {
    "addr:full":"20 Hodgson Way Kewdale WA 6105",
    "addr:housenumber":"20",
    "addr:postcode":"6105",
    "addr:street":"Hodgson Way",
    "iso:country":"AU",
    "sg:address":"20 Hodgson Way",
    "sg:city":"Kewdale",
    "sg:classifiers":[
        {
            "category":"Building & Trades",
            "subcategory":"Construction",
            "type":"Services"
        }
    ],
    "sg:phone":"+61 8 9353 6033",
    "sg:postcode":"6105",
    "sg:province":"WA",
    "sg:tags":[
        "insulation",
        "contractor"
    ],
    "wof:name":"Thermacon Insulation",
    "wof:placetype":"venue"
},
  "geometry": {"coordinates":[115.95201110799999,-31.9777030945],"type":"Point"}
}