{
  "type": "Feature",
  "properties": {
    "addr:full":"25 Nyngan Pl Miranda NSW 2228",
    "addr:housenumber":"25",
    "addr:postcode":"2228",
    "addr:street":"Nyngan Pl Miranda",
    "iso:country":"AU",
    "sg:address":"25 Nyngan Pl",
    "sg:city":"Miranda",
    "sg:classifiers":[
        {
            "category":"Professional",
            "subcategory":"Accounting & Tax Preparation",
            "type":"Services"
        }
    ],
    "sg:phone":"+61 438 258 882",
    "sg:postcode":"2228",
    "sg:province":"NSW",
    "sg:tags":[
        "bookkeeping"
    ],
    "wof:name":"Miranda Bookkeeping Services",
    "wof:placetype":"venue"
},
  "geometry": {"coordinates":[151.10824585,-34.0274353027],"type":"Point"}
}