{
  "type": "Feature",
  "properties": {
    "addr:full":"69 Franklin Rd Chipping Norton NSW 2170",
    "addr:housenumber":"69",
    "addr:postcode":"2170",
    "addr:street":"Franklin Rd",
    "iso:country":"AU",
    "sg:address":"69 Franklin Rd",
    "sg:city":"Chipping Norton",
    "sg:classifiers":[
        {
            "category":"Freight",
            "type":"Transportation"
        }
    ],
    "sg:phone":"+61 412 677 420",
    "sg:postcode":"2170",
    "sg:province":"NSW",
    "sg:tags":[
        "light",
        "carrier"
    ],
    "wof:name":"Slater P & P Pty Ltd",
    "wof:placetype":"venue"
},
  "geometry": {"coordinates":[150.94917297399999,-33.9273490906],"type":"Point"}
}