{
  "type": "Feature",
  "properties": {
    "addr:full":"76 York St Launceston TAS 7250",
    "addr:housenumber":"76",
    "addr:postcode":"7250",
    "addr:street":"York St",
    "iso:country":"AU",
    "sg:address":"76 York St",
    "sg:city":"Launceston",
    "sg:classifiers":[
        {
            "category":"Professional",
            "subcategory":"Computer Services",
            "type":"Services"
        }
    ],
    "sg:phone":"+61 3 6334 9142",
    "sg:postcode":"7250",
    "sg:province":"TAS",
    "sg:tags":[
        "tele-communications",
        "consultant"
    ],
    "wof:name":"Australian Cable & Telephony Pty Ltd",
    "wof:placetype":"venue"
},
  "geometry": {"coordinates":[147.14187622099999,-41.4371261597],"type":"Point"}
}