{
  "type": "Feature",
  "properties": {
    "addr:full":"Shop 9 Mudgeeraba Market Shopping Centre Mudgeeraba QLD 4213",
    "addr:housenumber":"shop 9",
    "addr:postcode":"4213",
    "iso:country":"AU",
    "sg:address":"Shop 9 Mudgeeraba Market Shopping Centre",
    "sg:city":"Mudgeeraba",
    "sg:classifiers":[
        {
            "category":"Health Services",
            "subcategory":"Optometrist",
            "type":"Services"
        }
    ],
    "sg:phone":"+61 7 5530 2322",
    "sg:postcode":"4213",
    "sg:province":"QLD",
    "wof:name":"Mudgeeraba Optical",
    "wof:placetype":"venue"
},
  "geometry": {"coordinates":[153.355026245,-28.052936554],"type":"Point"}
}