{
  "type": "Feature",
  "properties": {
    "addr:full":"Level 3/ 293 Camberwell Rd Camberwell VIC 3124",
    "addr:housenumber":"/ 293",
    "addr:postcode":"3124",
    "addr:street":"Camberwell Rd",
    "iso:country":"AU",
    "sg:address":"Level 3/ 293 Camberwell Rd",
    "sg:city":"Camberwell",
    "sg:classifiers":[
        {
            "category":"Professional",
            "subcategory":"Accounting & Tax Preparation",
            "type":"Services"
        }
    ],
    "sg:phone":"+61 3 9882 6699",
    "sg:postcode":"3124",
    "sg:province":"VIC",
    "sg:tags":[
        "accountant",
        "auditor"
    ],
    "wof:name":"WHK Smith Read Prescott",
    "wof:placetype":"venue"
},
  "geometry": {"coordinates":[145.058425903,-37.8325462341],"type":"Point"}
}