{
  "type": "Feature",
  "properties": {
    "addr:full":"Shop 1 (Rear), 72 Church St Brighton VIC 3186",
    "addr:housenumber":"shop 1;72",
    "addr:postcode":"3186",
    "addr:street":"Church St",
    "iso:country":"AU",
    "sg:address":"Shop 1 (Rear), 72 Church St",
    "sg:city":"Brighton",
    "sg:classifiers":[
        {
            "category":"Professional",
            "subcategory":"Printing & Photocopies",
            "type":"Services"
        }
    ],
    "sg:phone":"+61 3 9592 9093",
    "sg:postcode":"3186",
    "sg:province":"VIC",
    "sg:tags":[
        "photocopying"
    ],
    "wof:name":"Bizworks Printing & Copy Centre",
    "wof:placetype":"venue"
},
  "geometry": {"coordinates":[144.994995117,-37.9145812988],"type":"Point"}
}