{
  "type": "Feature",
  "properties": {
    "iso:country":"AU",
    "sg:address":"356 Ingham Rd",
    "sg:city":"Townsville",
    "sg:classifiers":[
        {
            "category":"Building & Trades",
            "subcategory":"Construction",
            "type":"Services"
        }
    ],
    "sg:phone":"+61 7 4775 4077",
    "sg:postcode":"4810",
    "sg:province":"QLD",
    "sg:tags":[
        "bitumen",
        "paving",
        "asphalt"
    ],
    "wof:name":"Pioneer Road Services Pty Ltd",
    "wof:placetype":"venue"
},
  "geometry": {"coordinates":[146.751175,-19.261934],"type":"Point"}
}