{
  "type": "Feature",
  "properties": {
    "addr:full":"66 Glenard Drv Eaglemont VIC 3084",
    "addr:housenumber":"66",
    "addr:postcode":"3084",
    "addr:street":"Glenard Drv",
    "iso:country":"AU",
    "sg:address":"66 Glenard Drv",
    "sg:city":"Eaglemont",
    "sg:classifiers":[
        {
            "category":"Professional",
            "subcategory":"Art Services",
            "type":"Services"
        }
    ],
    "sg:phone":"+61 3 9459 1097",
    "sg:postcode":"3084",
    "sg:province":"VIC",
    "sg:tags":[
        "interior",
        "designer"
    ],
    "wof:name":"Design Providence M.D.I.A.",
    "wof:placetype":"venue"
},
  "geometry": {"coordinates":[145.07090759299999,-37.7614440918],"type":"Point"}
}