{
  "type": "Feature",
  "properties": {
    "addr:full":"18 Saxby Rd Howard Springs NT 0835",
    "addr:housenumber":"18",
    "addr:postcode":"nt 0835",
    "addr:street":"Saxby Rd",
    "iso:country":"AU",
    "sg:address":"18 Saxby Rd",
    "sg:city":"Howard Springs",
    "sg:classifiers":[
        {
            "category":"Professional",
            "type":"Services"
        }
    ],
    "sg:phone":"+61 8 8983 2424",
    "sg:postcode":"0835",
    "sg:province":"NT",
    "sg:tags":[
        "transport"
    ],
    "wof:name":"McKay P & D (Haulage Contractors)",
    "wof:placetype":"venue"
},
  "geometry": {"coordinates":[131.03434799999999,-12.531143],"type":"Point"}
}