{
  "type": "Feature",
  "properties": {
    "iso:country":"AU",
    "sg:address":"19 Fulcher Rd",
    "sg:city":"Red Hill",
    "sg:classifiers":[
        {
            "category":"Social Services",
            "subcategory":"Child Care",
            "type":"Services"
        }
    ],
    "sg:phone":"+61 7 3366 2411",
    "sg:postcode":"4059",
    "sg:province":"QLD",
    "wof:name":"Kindyworld Red Hill",
    "wof:placetype":"venue"
},
  "geometry": {"coordinates":[152.99635314899999,-27.4467163086],"type":"Point"}
}