{
  "type": "Feature",
  "properties": {
    "iso:country":"AU",
    "sg:address":"PO Box 325",
    "sg:city":"Narrabeen",
    "sg:classifiers":[
        {
            "category":"Home & Garden",
            "subcategory":"Household Appliances",
            "type":"Retail Goods"
        }
    ],
    "sg:phone":"+61 2 9997 7840",
    "sg:postcode":"2101",
    "sg:province":"NSW",
    "sg:tags":[
        "heating",
        "system"
    ],
    "wof:name":"Floor Heat Australia",
    "wof:placetype":"venue"
},
  "geometry": {"coordinates":[151.298416,-33.720211],"type":"Point"}
}