{
  "type": "Feature",
  "properties": {
    "addr:full":"Centenary Shopng Cntr 171 Dandenong Rd Mt Ommaney QLD 4074",
    "addr:housenumber":"171",
    "addr:postcode":"4074",
    "addr:street":"Dandenong Rd;Ommaney",
    "iso:country":"AU",
    "sg:address":"Centenary Shopng Cntr 171 Dandenong Rd",
    "sg:city":"Mt Ommaney",
    "sg:classifiers":[
        {
            "category":"Fast Food",
            "type":"Food & Drink"
        }
    ],
    "sg:phone":"+61 7 3892 1111",
    "sg:postcode":"4074",
    "sg:province":"QLD",
    "sg:tags":[
        "away",
        "take"
    ],
    "wof:name":"Pizza Hut",
    "wof:placetype":"venue"
},
  "geometry": {"coordinates":[152.93754577600001,-27.5480537415],"type":"Point"}
}