{
  "type": "Feature",
  "properties": {
    "iso:country":"AU",
    "sg:address":"5 Nabilla Pl",
    "sg:city":"Middle Park",
    "sg:classifiers":[
        {
            "category":"Building & Trades",
            "subcategory":"Construction",
            "type":"Services"
        }
    ],
    "sg:phone":"+61 7 3376 8913",
    "sg:postcode":"4074",
    "sg:province":"QLD",
    "sg:tags":[
        "joiner",
        "carpenter"
    ],
    "wof:name":"Masterfix Carpentry Services",
    "wof:placetype":"venue"
},
  "geometry": {"coordinates":[152.91732788100001,-27.5572319031],"type":"Point"}
}