{
  "type": "Feature",
  "properties": {
    "addr:full":"Unit 5, 21 Weatherburn Way Kardinya WA 6163",
    "addr:housenumber":"21",
    "addr:postcode":"6163",
    "addr:street":"Weatherburn Way",
    "iso:country":"AU",
    "sg:address":"Unit 5, 21",
    "sg:city":"Weatherburn Way Kardinya",
    "sg:classifiers":[
        {
            "category":"Building & Trades",
            "subcategory":"Construction",
            "type":"Services"
        }
    ],
    "sg:phone":"+61 8 9314 1829",
    "sg:postcode":"6163",
    "sg:province":"WA",
    "sg:tags":[
        "roof"
    ],
    "sg:website":"http://www.aceroofing.com.au",
    "wof:name":"Ace Roofing WA Pty Ltd",
    "wof:placetype":"venue"
},
  "geometry": {"coordinates":[115.80474100000001,-32.059196],"type":"Point"}
}