{
  "type": "Feature",
  "properties": {
    "addr:full":"Cameron St Traralgon VIC 3844",
    "addr:postcode":"3844",
    "addr:street":"Cameron St",
    "iso:country":"AU",
    "sg:address":"Cameron St",
    "sg:city":"Traralgon",
    "sg:classifiers":[
        {
            "category":"Social Services",
            "subcategory":"Child Care",
            "type":"Services"
        }
    ],
    "sg:phone":"+61 3 5176 3622",
    "sg:postcode":"3844",
    "sg:province":"VIC",
    "sg:tags":[
        "support",
        "health"
    ],
    "wof:name":"Maternal & Child Health Centres",
    "wof:placetype":"venue"
},
  "geometry": {"coordinates":[146.55584716800001,-38.2027320862],"type":"Point"}
}