{
  "type": "Feature",
  "properties": {
    "addr:full":"10 Lennox St Bellevue Hill NSW 2023",
    "addr:housenumber":"10",
    "addr:postcode":"2023",
    "addr:street":"Lennox St",
    "iso:country":"AU",
    "sg:address":"10 Lennox St",
    "sg:city":"Bellevue Hill",
    "sg:classifiers":[
        {
            "category":"Building & Trades",
            "subcategory":"Locksmith",
            "type":"Services"
        }
    ],
    "sg:phone":"+61 2 9362 3568",
    "sg:postcode":"2023",
    "sg:province":"NSW",
    "sg:tags":[
        "lock"
    ],
    "wof:name":"J & D Locksmiths",
    "wof:placetype":"venue"
},
  "geometry": {"coordinates":[151.25697326700001,-33.8844604492],"type":"Point"}
}