{
  "type": "Feature",
  "properties": {
    "iso:country":"AU",
    "sg:address":"Suite 4/ 105 Broadway",
    "sg:city":"Nedlands",
    "sg:classifiers":[
        {
            "category":"Wholesale",
            "subcategory":"Construction Materials",
            "type":"Manufacturing & Wholesale Goods"
        }
    ],
    "sg:phone":"+61 8 6389 2100",
    "sg:postcode":"6009",
    "sg:province":"WA",
    "sg:tags":[
        "protective",
        "coating"
    ],
    "wof:name":"Guardian Protective Coatings Pty Ltd",
    "wof:placetype":"venue"
},
  "geometry": {"coordinates":[115.814369,-31.983871],"type":"Point"}
}