{
  "type": "Feature",
  "properties": {
    "addr:full":"320 Crown St Surry Hills NSW 2010",
    "addr:housenumber":"320",
    "addr:postcode":"2010",
    "addr:street":"Crown St",
    "iso:country":"AU",
    "sg:address":"320 Crown St",
    "sg:city":"Surry Hills",
    "sg:classifiers":[
        {
            "category":"Restaurant",
            "type":"Food & Drink"
        }
    ],
    "sg:phone":"+61 2 9332 2344",
    "sg:postcode":"2010",
    "sg:province":"NSW",
    "wof:name":"Bently Restaurant & Bar",
    "wof:placetype":"venue"
},
  "geometry": {"coordinates":[151.21505737300001,-33.8807525635],"type":"Point"}
}