{
  "type": "Feature",
  "properties": {
    "addr:full":"Rice Rd Redbank Plains QLD 4301",
    "addr:postcode":"4301",
    "addr:street":"Rice Rd",
    "iso:country":"AU",
    "sg:address":"Rice Rd",
    "sg:city":"Redbank Plains",
    "sg:classifiers":[
        {
            "category":"Autos & Motor Vehicles",
            "subcategory":"Boat Sales",
            "type":"Retail Goods"
        }
    ],
    "sg:phone":"+61 418 744 367",
    "sg:postcode":"4301",
    "sg:province":"QLD",
    "sg:tags":[
        "equipment",
        "yacht"
    ],
    "wof:name":"Lasers 4 Sale.com",
    "wof:placetype":"venue"
},
  "geometry": {"coordinates":[152.84010314899999,-27.6457099915],"type":"Point"}
}