{
  "type": "Feature",
  "properties": {
    "addr:full":"111 Springfield Rd Blackburn North VIC 3130",
    "addr:housenumber":"111",
    "addr:postcode":"3130",
    "addr:street":"Springfield Rd",
    "iso:country":"AU",
    "sg:address":"111 Springfield Rd",
    "sg:city":"Blackburn North",
    "sg:classifiers":[
        {
            "category":"Health Services",
            "subcategory":"Dentist",
            "type":"Services"
        }
    ],
    "sg:phone":"+61 3 9894 3347",
    "sg:postcode":"3130",
    "sg:province":"VIC",
    "wof:name":"Blackburn North Dental",
    "wof:placetype":"venue"
},
  "geometry": {"coordinates":[145.15246582,-37.810295105],"type":"Point"}
}