{
  "type": "Feature",
  "properties": {
    "addr:full":"79 Breakspear St Gracemere QLD 4702",
    "addr:housenumber":"79",
    "addr:postcode":"4702",
    "addr:street":"Breakspear St",
    "iso:country":"AU",
    "sg:address":"79 Breakspear St",
    "sg:city":"Gracemere",
    "sg:classifiers":[
        {
            "category":"Social Services",
            "subcategory":"Child Care",
            "type":"Services"
        }
    ],
    "sg:phone":"+61 7 4933 2223",
    "sg:postcode":"4702",
    "sg:province":"QLD",
    "wof:name":"ABC Gracemere",
    "wof:placetype":"venue"
},
  "geometry": {"coordinates":[150.462692261,-23.4496173859],"type":"Point"}
}