{
  "type": "Feature",
  "properties": {
    "iso:country":"AU",
    "sg:address":"Dubbo St",
    "sg:city":"Elong Elong",
    "sg:classifiers":[
        {
            "category":"Shopping",
            "type":"Retail Goods"
        }
    ],
    "sg:phone":"+61 2 6886 6128",
    "sg:postcode":"2831",
    "sg:province":"NSW",
    "sg:tags":[
        "agent",
        "stock"
    ],
    "wof:name":"G Walters & Co Pty Ltd",
    "wof:placetype":"venue"
},
  "geometry": {"coordinates":[149.03741455100001,-32.111541748],"type":"Point"}
}