{
  "type": "Feature",
  "properties": {
    "addr:full":"PO Box 3539 West Tamworth NSW 2340",
    "addr:postcode":"2340",
    "iso:country":"AU",
    "sg:address":"PO Box 3539",
    "sg:city":"West Tamworth",
    "sg:classifiers":[
        {
            "category":"Professional",
            "subcategory":"Accounting & Tax Preparation",
            "type":"Services"
        }
    ],
    "sg:phone":"+61 2 6760 5889",
    "sg:postcode":"2340",
    "sg:province":"NSW",
    "sg:tags":[
        "bookkeeping"
    ],
    "wof:name":"PMC Bookkeeping Services",
    "wof:placetype":"venue"
},
  "geometry": {"coordinates":[150.90530395499999,-31.1000595093],"type":"Point"}
}