{
  "type": "Feature",
  "properties": {
    "addr:full":"10 Lancaster St Ingleburn NSW 2565",
    "addr:housenumber":"10",
    "addr:postcode":"2565",
    "addr:street":"Lancaster St",
    "iso:country":"AU",
    "sg:address":"10 Lancaster St",
    "sg:city":"Ingleburn",
    "sg:phone":"+61 2 9618 4100",
    "sg:postcode":"2565",
    "sg:province":"NSW",
    "wof:name":"AES Environmental Pty Ltd",
    "wof:placetype":"venue"
},
  "geometry": {"coordinates":[150.86564636200001,-33.9907493591],"type":"Point"}
}