{
  "type": "Feature",
  "properties": {
    "addr:full":"Shop 12 Ocean Plaza Scarborough WA 6019",
    "addr:housenumber":"shop 12",
    "addr:postcode":"6019",
    "addr:street":"Ocean Plaza",
    "iso:country":"AU",
    "sg:address":"Shop 12",
    "sg:city":"Ocean Plaza Scarborough",
    "sg:classifiers":[
        {
            "category":"Building & Trades",
            "subcategory":"Landscaping Services",
            "type":"Services"
        }
    ],
    "sg:phone":"+61 8 9245 1670",
    "sg:postcode":"6019",
    "sg:province":"WA",
    "sg:tags":[
        "market"
    ],
    "wof:name":"Ocean Plaza",
    "wof:placetype":"venue"
},
  "geometry": {"coordinates":[115.761146545,-31.8980808258],"type":"Point"}
}