{
  "type": "Feature",
  "properties": {
    "addr:full":"841 Tenbirink St Albury NSW 2640",
    "addr:housenumber":"841",
    "addr:postcode":"2640",
    "addr:street":"Tenbirink St",
    "iso:country":"AU",
    "sg:address":"841 Tenbirink St",
    "sg:city":"Albury",
    "sg:classifiers":[
        {
            "category":"Building & Trades",
            "subcategory":"Construction",
            "type":"Services"
        }
    ],
    "sg:phone":"+61 2 6025 1041",
    "sg:postcode":"2640",
    "sg:province":"NSW",
    "sg:tags":[
        "management"
    ],
    "wof:name":"The Old Albury Co",
    "wof:placetype":"venue"
},
  "geometry": {"coordinates":[146.910400391,-36.0606498718],"type":"Point"}
}