{
  "type": "Feature",
  "properties": {
    "iso:country":"AU",
    "sg:address":"419 Gardeners Rd",
    "sg:city":"Rosebery",
    "sg:classifiers":[
        {
            "category":"Health Services",
            "subcategory":"Doctor",
            "type":"Services"
        }
    ],
    "sg:phone":"+61 2 9667 3672",
    "sg:postcode":"2018",
    "sg:province":"NSW",
    "sg:tags":[
        "medical",
        "practitioner"
    ],
    "wof:name":"Johnson Lindsay A",
    "wof:placetype":"venue"
},
  "geometry": {"coordinates":[151.201248169,-33.9222602844],"type":"Point"}
}