{
  "type": "Feature",
  "properties": {
    "addr:full":"148 Watton St Werribee VIC 3030",
    "addr:housenumber":"148",
    "addr:postcode":"3030",
    "addr:street":"Watton St",
    "iso:country":"AU",
    "sg:address":"148 Watton St",
    "sg:city":"Werribee",
    "sg:classifiers":[
        {
            "category":"Fast Food",
            "type":"Food & Drink"
        }
    ],
    "sg:phone":"+61 3 9741 9394",
    "sg:postcode":"3030",
    "sg:province":"VIC",
    "sg:tags":[
        "away",
        "take"
    ],
    "wof:name":"Hungry Jacks Pty Ltd",
    "wof:placetype":"venue"
},
  "geometry": {"coordinates":[144.655563,-37.9044],"type":"Point"}
}