{
  "type": "Feature",
  "properties": {
    "addr:full":"37 Rowland St Slacks Creek QLD 4127",
    "addr:housenumber":"37",
    "addr:postcode":"4127",
    "addr:street":"Rowland St",
    "iso:country":"AU",
    "sg:address":"37 Rowland St",
    "sg:city":"Slacks Creek",
    "sg:classifiers":[
        {
            "category":"Retail",
            "subcategory":"Auto Repair",
            "type":"Services"
        }
    ],
    "sg:phone":"+61 7 3299 5500",
    "sg:postcode":"4127",
    "sg:province":"QLD",
    "sg:tags":[
        "repairer",
        "motor",
        "engineer"
    ],
    "wof:name":"Burton Motors",
    "wof:placetype":"venue"
},
  "geometry": {"coordinates":[153.126663208,-27.6309204102],"type":"Point"}
}