{
  "type": "Feature",
  "properties": {
    "addr:full":"495 Willoughby Rd Willoughby NSW 2068",
    "addr:housenumber":"495",
    "addr:postcode":"2068",
    "addr:street":"Willoughby Rd",
    "iso:country":"AU",
    "sg:address":"495 Willoughby Rd",
    "sg:city":"Willoughby",
    "sg:classifiers":[
        {
            "category":"Shopping",
            "subcategory":"Mobile Phones",
            "type":"Retail Goods"
        }
    ],
    "sg:phone":"+61 2 9967 0977",
    "sg:postcode":"2068",
    "sg:province":"NSW",
    "sg:tags":[
        "telephone",
        "accessory"
    ],
    "wof:name":"Pacific Bell Communications",
    "wof:placetype":"venue"
},
  "geometry": {"coordinates":[151.19960022000001,-33.8077278137],"type":"Point"}
}