{
  "type": "Feature",
  "properties": {
    "addr:full":"PO Box 767 Jindabyne NSW 2627",
    "addr:postcode":"2627",
    "iso:country":"AU",
    "sg:address":"PO Box 767",
    "sg:city":"Jindabyne",
    "sg:classifiers":[
        {
            "category":"Home & Garden",
            "subcategory":"Carpets & Floor Coverings",
            "type":"Retail Goods"
        }
    ],
    "sg:phone":"+61 2 6457 2004",
    "sg:postcode":"2627",
    "sg:province":"NSW",
    "sg:tags":[
        "tile",
        "wall",
        "layer"
    ],
    "wof:name":"Bob Pratt",
    "wof:placetype":"venue"
},
  "geometry": {"coordinates":[148.60859680199999,-36.4327316284],"type":"Point"}
}