{
  "type": "Feature",
  "properties": {
    "addr:full":"27 Springfield St Guildford NSW 2161",
    "addr:housenumber":"27",
    "addr:postcode":"2161",
    "addr:street":"Springfield St",
    "iso:country":"AU",
    "sg:address":"27 Springfield St",
    "sg:city":"Guildford",
    "sg:classifiers":[
        {
            "category":"Shopping",
            "subcategory":"Pets & Pet Supplies",
            "type":"Retail Goods"
        }
    ],
    "sg:phone":"+61 2 8720 2485",
    "sg:postcode":"2161",
    "sg:province":"NSW",
    "sg:tags":[
        "dog"
    ],
    "wof:name":"Staunch Industries",
    "wof:placetype":"venue"
},
  "geometry": {"coordinates":[150.987091064,-33.8632698059],"type":"Point"}
}