{
  "type": "Feature",
  "properties": {
    "iso:country":"AU",
    "sg:address":"21 Gray St",
    "sg:city":"Mt Gambier",
    "sg:classifiers":[
        {
            "category":"Health Services",
            "subcategory":"Doctor",
            "type":"Services"
        }
    ],
    "sg:phone":"+61 8 8723 2799",
    "sg:postcode":"5290",
    "sg:province":"SA",
    "sg:tags":[
        "medical",
        "practitioner"
    ],
    "wof:name":"Gribbles Pathology Mount Gambier Pty Ltd",
    "wof:placetype":"venue"
},
  "geometry": {"coordinates":[140.77758800000001,-37.829426],"type":"Point"}
}