{
  "type": "Feature",
  "properties": {
    "addr:full":"Eureka Medical Centre, 14 Albert St Ballarat VIC 3350",
    "addr:housenumber":"14",
    "addr:postcode":"3350",
    "addr:street":"Albert St",
    "iso:country":"AU",
    "sg:address":"Eureka Medical Centre, 14 Albert St",
    "sg:city":"Ballarat",
    "sg:classifiers":[
        {
            "category":"Health Services",
            "subcategory":"Health Practitioner",
            "type":"Services"
        }
    ],
    "sg:phone":"+61 3 5309 1140",
    "sg:postcode":"3350",
    "sg:province":"VIC",
    "sg:tags":[
        "naturopath"
    ],
    "wof:name":"Jacqui Fernandez",
    "wof:placetype":"venue"
},
  "geometry": {"coordinates":[143.85870399999999,-37.56403],"type":"Point"}
}