{
  "type": "Feature",
  "properties": {
    "addr:full":"70 Underwood St Paddington NSW 2021",
    "addr:housenumber":"70",
    "addr:postcode":"2021",
    "addr:street":"Underwood St",
    "iso:country":"AU",
    "sg:address":"70 Underwood St",
    "sg:city":"Paddington",
    "sg:classifiers":[
        {
            "category":"Shopping",
            "subcategory":"Department Store",
            "type":"Retail Goods"
        }
    ],
    "sg:phone":"+61 2 9360 9999",
    "sg:postcode":"2021",
    "sg:province":"NSW",
    "sg:tags":[
        "towel",
        "supply"
    ],
    "wof:name":"Ben Sherman Bathrobes Pty Ltd",
    "wof:placetype":"venue"
},
  "geometry": {"coordinates":[151.22952270499999,-33.8851966858],"type":"Point"}
}