{
  "type": "Feature",
  "properties": {
    "iso:country":"AU",
    "sg:address":"Unit 1/ 25 Buckingham Drv",
    "sg:city":"Wangara",
    "sg:classifiers":[
        {
            "category":"Building & Trades",
            "subcategory":"Equipment Rental",
            "type":"Services"
        }
    ],
    "sg:phone":"+61 8 9309 1550",
    "sg:postcode":"6065",
    "sg:province":"WA",
    "sg:tags":[
        "party",
        "hire"
    ],
    "wof:name":"Red Back Juke Box Hire",
    "wof:placetype":"venue"
},
  "geometry": {"coordinates":[115.816497803,-31.7869262695],"type":"Point"}
}