{
  "type": "Feature",
  "properties": {
    "addr:full":"(opp loftus st) 729 Windsor Rd Box Hill NSW 2765",
    "addr:housenumber":"729",
    "addr:postcode":"2765",
    "addr:street":"Loftus;Windsor Rd",
    "iso:country":"AU",
    "sg:address":"(opp loftus st) 729 Windsor Rd",
    "sg:city":"Box Hill",
    "sg:classifiers":[
        {
            "category":"Wholesale",
            "subcategory":"Machinery & Supplies",
            "type":"Manufacturing & Wholesale Goods"
        }
    ],
    "sg:phone":"+61 2 9627 5580",
    "sg:postcode":"2765",
    "sg:province":"NSW",
    "sg:tags":[
        "agricultural"
    ],
    "wof:name":"Vineyard Engineering",
    "wof:placetype":"venue"
},
  "geometry": {"coordinates":[150.91368102999999,-33.6798667908],"type":"Point"}
}