{
  "type": "Feature",
  "properties": {
    "addr:full":"81 Charlotte St Newport VIC 3015",
    "addr:housenumber":"81",
    "addr:postcode":"3015",
    "addr:street":"Charlotte St",
    "iso:country":"AU",
    "sg:address":"81 Charlotte St",
    "sg:city":"Newport",
    "sg:classifiers":[
        {
            "category":"Retail",
            "subcategory":"Storage",
            "type":"Services"
        }
    ],
    "sg:phone":"+61 401 586 339",
    "sg:postcode":"3015",
    "sg:province":"VIC",
    "sg:tags":[
        "removal",
        "furniture"
    ],
    "wof:name":"A Stress Free Moves",
    "wof:placetype":"venue"
},
  "geometry": {"coordinates":[144.86643981899999,-37.8337059021],"type":"Point"}
}