{
  "type": "Feature",
  "properties": {
    "addr:full":"Shp 4/ 41 High St Willunga SA 5172",
    "addr:housenumber":"/ 41",
    "addr:postcode":"5172",
    "addr:street":"High St",
    "iso:country":"AU",
    "sg:address":"Shp 4/ 41 High St",
    "sg:city":"Willunga",
    "sg:classifiers":[
        {
            "category":"Professional",
            "subcategory":"Employment Agencies",
            "type":"Services"
        }
    ],
    "sg:phone":"+61 8 8556 2033",
    "sg:postcode":"5172",
    "sg:province":"SA",
    "sg:tags":[
        "entertainer",
        "agent"
    ],
    "wof:name":"Jamae Raw Productions",
    "wof:placetype":"venue"
},
  "geometry": {"coordinates":[138.55804443400001,-35.2737808228],"type":"Point"}
}