{
  "type": "Feature",
  "properties": {
    "addr:full":"Hannant Rd Hatton Vale QLD 4341",
    "addr:postcode":"4341",
    "addr:street":"Hannant Rd",
    "iso:country":"AU",
    "sg:address":"Hannant Rd",
    "sg:city":"Hatton Vale",
    "sg:classifiers":[
        {
            "category":"Education",
            "subcategory":"School",
            "type":"Public Place"
        }
    ],
    "sg:phone":"+61 7 5460 4355",
    "sg:postcode":"4341",
    "sg:province":"QLD",
    "sg:tags":[
        "state",
        "except",
        "nsw"
    ],
    "wof:name":"Hatton Vale Preschool",
    "wof:placetype":"venue"
},
  "geometry": {"coordinates":[152.47793579099999,-27.5443553925],"type":"Point"}
}