{
  "type": "Feature",
  "properties": {
    "addr:full":"PO Box 31 Dernancourt SA 5075",
    "addr:postcode":"5075",
    "iso:country":"AU",
    "sg:address":"PO Box 31",
    "sg:city":"Dernancourt",
    "sg:classifiers":[
        {
            "category":"Building & Trades",
            "subcategory":"Plumbing",
            "type":"Services"
        }
    ],
    "sg:phone":"+61 413 224 000",
    "sg:postcode":"5075",
    "sg:province":"SA",
    "sg:tags":[
        "plumber",
        "gasfitters"
    ],
    "wof:name":"Gary Tye Plumbing",
    "wof:placetype":"venue"
},
  "geometry": {"coordinates":[138.683792114,-34.8610191345],"type":"Point"}
}