{
  "type": "Feature",
  "properties": {
    "iso:country":"AU",
    "sg:address":"Shop 7-8 Caincross Cnr",
    "sg:city":"Maleny",
    "sg:classifiers":[
        {
            "category":"Arts & Performance",
            "subcategory":"Art Gallery",
            "type":"Entertainment"
        }
    ],
    "sg:phone":"+61 7 5429 6404",
    "sg:postcode":"4552",
    "sg:province":"QLD",
    "wof:name":"Caraffi's Cairncross Arts Gallery",
    "wof:placetype":"venue"
},
  "geometry": {"coordinates":[152.84934997600001,-26.7581195831],"type":"Point"}
}