{
  "type": "Feature",
  "properties": {
    "addr:full":"320 Military Rd Vaucluse NSW 2030",
    "addr:housenumber":"320",
    "addr:postcode":"2030",
    "addr:street":"Military Rd",
    "iso:country":"AU",
    "sg:address":"320 Military Rd",
    "sg:city":"Vaucluse",
    "sg:classifiers":[
        {
            "category":"Utilities",
            "subcategory":"Electric",
            "type":"Services"
        }
    ],
    "sg:phone":"+61 2 9337 4182",
    "sg:postcode":"2030",
    "sg:province":"NSW",
    "sg:tags":[
        "electrical",
        "contractor"
    ],
    "wof:name":"Wiederman W K & J",
    "wof:placetype":"venue"
},
  "geometry": {"coordinates":[151.28074645999999,-33.8645553589],"type":"Point"}
}