{
  "type": "Feature",
  "properties": {
    "addr:full":"381 Port Hacking Rd Caringbah NSW 2229",
    "addr:housenumber":"381",
    "addr:postcode":"2229",
    "addr:street":"Port Hacking Rd",
    "iso:country":"AU",
    "sg:address":"381 Port Hacking Rd",
    "sg:city":"Caringbah",
    "sg:classifiers":[
        {
            "category":"Professional",
            "subcategory":"Accounting & Tax Preparation",
            "type":"Services"
        }
    ],
    "sg:phone":"+61 2 9524 1000",
    "sg:postcode":"2229",
    "sg:province":"NSW",
    "sg:tags":[
        "accountant",
        "auditor"
    ],
    "wof:name":"Forrest & Associates",
    "wof:placetype":"venue"
},
  "geometry": {"coordinates":[151.12309265100001,-34.0450744629],"type":"Point"}
}