{
  "type": "Feature",
  "properties": {
    "addr:full":"77 Buckingham Drv Wangara WA 6065",
    "addr:housenumber":"77",
    "addr:postcode":"6065",
    "addr:street":"Buckingham Drv",
    "iso:country":"AU",
    "sg:address":"77 Buckingham Drv",
    "sg:city":"Wangara",
    "sg:classifiers":[
        {
            "category":"Government",
            "subcategory":"Department Of Motor Vehicles",
            "type":"Public Place"
        }
    ],
    "sg:phone":"+61 8 9309 3144",
    "sg:postcode":"6065",
    "sg:province":"WA",
    "sg:tags":[
        "car",
        "conversion",
        "seat"
    ],
    "wof:name":"Wangara Cars & Commercials.",
    "wof:placetype":"venue"
},
  "geometry": {"coordinates":[115.81503295900001,-31.7872848511],"type":"Point"}
}