{
  "type": "Feature",
  "properties": {
    "addr:full":"188 Princes Hwy Corrimal NSW 2518",
    "addr:housenumber":"188",
    "addr:postcode":"2518",
    "addr:street":"Princes Hwy",
    "iso:country":"AU",
    "sg:address":"188 Princes Hwy",
    "sg:city":"Corrimal",
    "sg:classifiers":[
        {
            "category":"Professional",
            "subcategory":"Employment Agencies",
            "type":"Services"
        }
    ],
    "sg:phone":"+61 2 4251 5555",
    "sg:postcode":"2518",
    "sg:province":"NSW",
    "wof:name":"Campbell Page",
    "wof:placetype":"venue"
},
  "geometry": {"coordinates":[150.89657600000001,-34.373745],"type":"Point"}
}