{
  "type": "Feature",
  "properties": {
    "addr:full":"14 Young St Annerley QLD 4103",
    "addr:housenumber":"14",
    "addr:postcode":"4103",
    "addr:street":"Young St",
    "iso:country":"AU",
    "sg:address":"14 Young St",
    "sg:city":"Annerley",
    "sg:classifiers":[
        {
            "category":"Autos & Motor Vehicles",
            "subcategory":"Boat Sales",
            "type":"Retail Goods"
        }
    ],
    "sg:phone":"+61 7 3393 0934",
    "sg:postcode":"4103",
    "sg:province":"QLD",
    "sg:tags":[
        "equipment",
        "yacht"
    ],
    "wof:name":"Jobson's Pty Ltd",
    "wof:placetype":"venue"
},
  "geometry": {"coordinates":[153.03155517600001,-27.5025730133],"type":"Point"}
}