{
  "type": "Feature",
  "properties": {
    "addr:full":"261 Bulleen Rd Bulleen VIC 3105",
    "addr:housenumber":"261",
    "addr:postcode":"3105",
    "addr:street":"Bulleen Rd",
    "iso:country":"AU",
    "sg:address":"261 Bulleen Rd",
    "sg:city":"Bulleen",
    "sg:classifiers":[
        {
            "category":"Building & Trades",
            "subcategory":"Construction",
            "type":"Services"
        }
    ],
    "sg:phone":"+61 3 9850 4311",
    "sg:postcode":"3105",
    "sg:province":"VIC",
    "sg:tags":[
        "contractor"
    ],
    "sg:website":"http://www.grollohomes.com.au",
    "wof:name":"Grollo Homes",
    "wof:placetype":"venue"
},
  "geometry": {"coordinates":[145.083526611,-37.7609786987],"type":"Point"}
}