{
  "type": "Feature",
  "properties": {
    "addr:full":"539 Jamberoo Rd Jamberoo NSW 2533",
    "addr:housenumber":"539",
    "addr:postcode":"2533",
    "addr:street":"Jamberoo Rd",
    "iso:country":"AU",
    "sg:address":"539 Jamberoo Rd",
    "sg:city":"Jamberoo",
    "sg:classifiers":[
        {
            "category":"Home & Garden",
            "subcategory":"Building Materials",
            "type":"Retail Goods"
        }
    ],
    "sg:phone":"+61 2 4236 0639",
    "sg:postcode":"2533",
    "sg:province":"NSW",
    "sg:tags":[
        "lawn",
        "cutting",
        "maintenance"
    ],
    "wof:name":"Four Seasons",
    "wof:placetype":"venue"
},
  "geometry": {"coordinates":[150.80328369099999,-34.6524887085],"type":"Point"}
}