{
  "type": "Feature",
  "properties": {
    "addr:full":"115 Derby St Kew VIC 3101",
    "addr:housenumber":"115",
    "addr:postcode":"3101",
    "addr:street":"Derby St",
    "iso:country":"AU",
    "sg:address":"115 Derby St",
    "sg:city":"Kew",
    "sg:classifiers":[
        {
            "category":"Professional",
            "subcategory":"Employment Agencies",
            "type":"Services"
        }
    ],
    "sg:phone":"+61 419 514 754",
    "sg:postcode":"3101",
    "sg:province":"VIC",
    "sg:tags":[
        "provider",
        "internet"
    ],
    "wof:name":"MC2 Consulting Pty Ltd",
    "wof:placetype":"venue"
},
  "geometry": {"coordinates":[145.03781127900001,-37.7988624573],"type":"Point"}
}