{
  "type": "Feature",
  "properties": {
    "iso:country":"AU",
    "sg:address":"Mason Rd",
    "sg:city":"Kwinana",
    "sg:classifiers":[
        {
            "category":"Farming",
            "subcategory":"Fish & Marine Products",
            "type":"Manufacturing & Wholesale Goods"
        }
    ],
    "sg:phone":"+61 8 9419 9820",
    "sg:postcode":"6167",
    "sg:province":"WA",
    "sg:tags":[
        "bitumen"
    ],
    "wof:name":"BP Bitumen",
    "wof:placetype":"venue"
},
  "geometry": {"coordinates":[115.778923,-32.232109],"type":"Point"}
}