{
  "type": "Feature",
  "properties": {
    "iso:country":"AU",
    "sg:address":"10 Alderson St",
    "sg:city":"Pinjarra",
    "sg:classifiers":[
        {
            "category":"Social Services",
            "subcategory":"Adult Care",
            "type":"Services"
        }
    ],
    "sg:phone":"+61 419 241 574",
    "sg:postcode":"6208",
    "sg:province":"WA",
    "sg:tags":[
        "towing"
    ],
    "wof:name":"Dubbos Towing Service",
    "wof:placetype":"venue"
},
  "geometry": {"coordinates":[115.862312,-32.631222],"type":"Point"}
}