{
  "type": "Feature",
  "properties": {
    "addr:full":"PO Box 3353 Victoria Point QLD 4165",
    "addr:postcode":"4165",
    "iso:country":"AU",
    "sg:address":"PO Box 3353",
    "sg:city":"Victoria Point",
    "sg:classifiers":[
        {
            "category":"Building & Trades",
            "subcategory":"Construction",
            "type":"Services"
        }
    ],
    "sg:phone":"+61 7 3829 1233",
    "sg:postcode":"4165",
    "sg:province":"QLD",
    "sg:tags":[
        "earth",
        "excavating",
        "moving",
        "contractor"
    ],
    "wof:name":"Total Tipping Services",
    "wof:placetype":"venue"
},
  "geometry": {"coordinates":[153.28512573200001,-27.595079422],"type":"Point"}
}