{
  "type": "Feature",
  "properties": {
    "iso:country":"AU",
    "sg:address":"52 Edward St",
    "sg:city":"Barrack Heights",
    "sg:classifiers":[
        {
            "category":"Building & Trades",
            "subcategory":"Construction",
            "type":"Services"
        }
    ],
    "sg:phone":"+61 404 079 104",
    "sg:postcode":"2528",
    "sg:province":"NSW",
    "sg:tags":[
        "contractor"
    ],
    "wof:name":"Roach R & K Carpentry Services",
    "wof:placetype":"venue"
},
  "geometry": {"coordinates":[150.86109924300001,-34.5649223328],"type":"Point"}
}