{
  "type": "Feature",
  "properties": {
    "iso:country":"AU",
    "sg:address":"350 Keilor Rd",
    "sg:city":"Niddrie",
    "sg:classifiers":[
        {
            "category":"Travel",
            "subcategory":"Travel Agent",
            "type":"Entertainment"
        }
    ],
    "sg:phone":"+61 3 9379 9445",
    "sg:postcode":"3042",
    "sg:province":"VIC",
    "sg:tags":[
        "consultant"
    ],
    "wof:name":"Essendon Travel (Vic) Pty Ltd",
    "wof:placetype":"venue"
},
  "geometry": {"coordinates":[144.89080810600001,-37.7365493774],"type":"Point"}
}