{
  "type": "Feature",
  "properties": {
    "addr:full":"Top Level, Milton Business Cen 340 Coronation Drv Milton QLD 4064",
    "addr:housenumber":"340",
    "addr:postcode":"4064",
    "addr:street":"Coronation Drv",
    "iso:country":"AU",
    "sg:address":"Top Level, Milton Business Cen 340 Coronation Drv",
    "sg:city":"Milton",
    "sg:classifiers":[
        {
            "category":"Social Services",
            "subcategory":"Retirement Home",
            "type":"Services"
        }
    ],
    "sg:phone":"+61 7 3842 3120",
    "sg:postcode":"4064",
    "sg:province":"QLD",
    "sg:tags":[
        "environmental",
        "consultant",
        "pollution"
    ],
    "wof:name":"Environmental Risk Solutions (ERS)",
    "wof:placetype":"venue"
},
  "geometry": {"coordinates":[153.00291442899999,-27.4751014709],"type":"Point"}
}