{
  "type": "Feature",
  "properties": {
    "addr:full":"PO Box 880 Burleigh Heads QLD 4220",
    "addr:postcode":"4220",
    "iso:country":"AU",
    "sg:address":"PO Box 880",
    "sg:city":"Burleigh Heads",
    "sg:classifiers":[
        {
            "category":"Organizations",
            "subcategory":"Non-profit Organization",
            "type":"Services"
        }
    ],
    "sg:phone":"+61 7 5578 6224",
    "sg:postcode":"4220",
    "sg:province":"QLD",
    "sg:tags":[
        "environmental",
        "organisation",
        "conservation"
    ],
    "wof:name":"Sunfish Gold Coast Branch",
    "wof:placetype":"venue"
},
  "geometry": {"coordinates":[153.449752808,-28.0879096985],"type":"Point"}
}