{
  "type": "Feature",
  "properties": {
    "iso:country":"AU",
    "sg:address":"32 Thanet St",
    "sg:city":"Malvern",
    "sg:classifiers":[
        {
            "category":"Professional",
            "subcategory":"Management & Consulting",
            "type":"Services"
        }
    ],
    "sg:phone":"+61 3 9576 1039",
    "sg:postcode":"3144",
    "sg:province":"VIC",
    "sg:tags":[
        "consultant"
    ],
    "wof:name":"Jaffe Consulting Pty Ltd",
    "wof:placetype":"venue"
},
  "geometry": {"coordinates":[145.03602600100001,-37.8617324829],"type":"Point"}
}