{
  "type": "Feature",
  "properties": {
    "addr:full":"18 Tottenham Pde West Footscray VIC 3012",
    "addr:housenumber":"18",
    "addr:postcode":"3012",
    "addr:street":"Tottenham Pde",
    "iso:country":"AU",
    "sg:address":"18 Tottenham Pde",
    "sg:city":"West Footscray",
    "sg:classifiers":[
        {
            "category":"Retail",
            "subcategory":"Auto Repair",
            "type":"Services"
        }
    ],
    "sg:phone":"+61 3 9318 9196",
    "sg:postcode":"3012",
    "sg:province":"VIC",
    "sg:tags":[
        "repairer",
        "motor",
        "engineer"
    ],
    "wof:name":"Suzzuki Specialists",
    "wof:placetype":"venue"
},
  "geometry": {"coordinates":[144.86044311500001,-37.810798645],"type":"Point"}
}