{
  "type": "Feature",
  "properties": {
    "addr:full":"38 Graffin Crs Winnellie NT 0820",
    "addr:housenumber":"38",
    "addr:postcode":"nt 0820",
    "addr:street":"Graffin Crs",
    "iso:country":"AU",
    "sg:address":"38 Graffin Crs",
    "sg:city":"Winnellie",
    "sg:classifiers":[
        {
            "category":"Autos & Motor Vehicles",
            "subcategory":"Automobile Sales",
            "type":"Retail Goods"
        }
    ],
    "sg:phone":"+61 8 8947 0882",
    "sg:postcode":"0820",
    "sg:province":"NT",
    "sg:tags":[
        "equipment",
        "trailer"
    ],
    "wof:name":"Sunshine Trailers",
    "wof:placetype":"venue"
},
  "geometry": {"coordinates":[130.87161254899999,-12.4264669418],"type":"Point"}
}