{
  "type": "Feature",
  "properties": {
    "iso:country":"AU",
    "sg:address":"20 Gardners Rd",
    "sg:city":"Kingsford",
    "sg:classifiers":[
        {
            "category":"Professional",
            "subcategory":"Art Services",
            "type":"Services"
        }
    ],
    "sg:phone":"+61 2 9663 2960",
    "sg:postcode":"2032",
    "sg:province":"NSW",
    "sg:tags":[
        "picture",
        "frame",
        "framing"
    ],
    "wof:name":"Kingsford Picture Framing",
    "wof:placetype":"venue"
},
  "geometry": {"coordinates":[151.22689819300001,-33.9249343872],"type":"Point"}
}