{
  "type": "Feature",
  "properties": {
    "addr:full":"103 Hobart Rd Kings Meadows TAS 7249",
    "addr:housenumber":"103",
    "addr:postcode":"7249",
    "addr:street":"Hobart Rd",
    "iso:country":"AU",
    "sg:address":"103 Hobart Rd",
    "sg:city":"Kings Meadows",
    "sg:classifiers":[
        {
            "category":"Fast Food",
            "type":"Food & Drink"
        }
    ],
    "sg:phone":"+61 3 6344 7597",
    "sg:postcode":"7249",
    "sg:province":"TAS",
    "sg:tags":[
        "away",
        "take"
    ],
    "wof:name":"Donati's Pizza Bar",
    "wof:placetype":"venue"
},
  "geometry": {"coordinates":[147.15914917000001,-41.4649734497],"type":"Point"}
}