{
  "type": "Feature",
  "properties": {
    "addr:full":"10 Beaumaris Drv Menai NSW 2234",
    "addr:housenumber":"10",
    "addr:postcode":"2234",
    "addr:street":"Beaumaris Drv",
    "iso:country":"AU",
    "sg:address":"10 Beaumaris Drv",
    "sg:city":"Menai",
    "sg:classifiers":[
        {
            "category":"Organizations",
            "subcategory":"Professional Association",
            "type":"Services"
        }
    ],
    "sg:phone":"+61 2 9532 1217",
    "sg:postcode":"2234",
    "sg:province":"NSW",
    "sg:tags":[
        "web",
        "internet"
    ],
    "wof:name":"Access International",
    "wof:placetype":"venue"
},
  "geometry": {"coordinates":[151.01286315900001,-34.0094108582],"type":"Point"}
}