{
  "type": "Feature",
  "properties": {
    "addr:full":"5 Mayleen St Clontarf QLD 4019",
    "addr:housenumber":"5",
    "addr:postcode":"4019",
    "addr:street":"Mayleen St",
    "iso:country":"AU",
    "sg:address":"5 Mayleen St",
    "sg:city":"Clontarf",
    "sg:classifiers":[
        {
            "category":"Health Services",
            "subcategory":"Doctor",
            "type":"Services"
        }
    ],
    "sg:phone":"+61 7 3284 7468",
    "sg:postcode":"4019",
    "sg:province":"QLD",
    "sg:tags":[
        "medical",
        "practitioner"
    ],
    "wof:name":"Ho C",
    "wof:placetype":"venue"
},
  "geometry": {"coordinates":[153.088134766,-27.2454166412],"type":"Point"}
}