{
  "type": "Feature",
  "properties": {
    "addr:full":"Clarke St Ripley QLD 4306",
    "addr:postcode":"4306",
    "addr:street":"Clarke St",
    "iso:country":"AU",
    "sg:address":"Clarke St",
    "sg:city":"Ripley",
    "sg:classifiers":[
        {
            "category":"Shopping",
            "subcategory":"Musical Instruments",
            "type":"Retail Goods"
        }
    ],
    "sg:phone":"+61 414 480 468",
    "sg:postcode":"4306",
    "sg:province":"QLD",
    "sg:tags":[
        "musician",
        "agent"
    ],
    "wof:name":"Bagpipe Tuition & Supplies",
    "wof:placetype":"venue"
},
  "geometry": {"coordinates":[152.78436279300001,-27.6657238007],"type":"Point"}
}