{
  "type": "Feature",
  "properties": {
    "iso:country":"AU",
    "sg:address":"103 Macquarie St",
    "sg:city":"Parramatta",
    "sg:classifiers":[
        {
            "category":"Personal",
            "subcategory":"Beauty Salon",
            "type":"Services"
        }
    ],
    "sg:phone":"+61 2 9633 1263",
    "sg:postcode":"2150",
    "sg:province":"NSW",
    "sg:tags":[
        "hairdresser"
    ],
    "wof:name":"Stella`s Hair & Body Cream Surprise",
    "wof:placetype":"venue"
},
  "geometry": {"coordinates":[151.060302734,-33.9097633362],"type":"Point"}
}