{
  "type": "Feature",
  "properties": {
    "addr:full":"Blackett Child Care, 25 Bolderwood Rd Blackett NSW 2770",
    "addr:housenumber":"25",
    "addr:postcode":"2770",
    "addr:street":"Bolderwood Rd",
    "iso:country":"AU",
    "sg:address":"Blackett Child Care, 25 Bolderwood Rd",
    "sg:city":"Blackett",
    "sg:classifiers":[
        {
            "category":"Banks & Credit Unions",
            "subcategory":"Investment Brokerage",
            "type":"Services"
        }
    ],
    "sg:phone":"+61 2 9628 3812",
    "sg:postcode":"2770",
    "sg:province":"NSW",
    "sg:tags":[
        "care",
        "day",
        "family",
        "child"
    ],
    "wof:name":"Blacktown City Council",
    "wof:placetype":"venue"
},
  "geometry": {"coordinates":[150.81727600100001,-33.7374839783],"type":"Point"}
}