{
  "type": "Feature",
  "properties": {
    "iso:country":"AU",
    "sg:address":"43 Industrial Drv",
    "sg:city":"Sunshine",
    "sg:classifiers":[
        {
            "category":"Organizations",
            "subcategory":"Professional Association",
            "type":"Services"
        }
    ],
    "sg:phone":"+61 3 9240 6300",
    "sg:postcode":"3020",
    "sg:province":"VIC",
    "sg:tags":[
        "call"
    ],
    "sg:website":"http://www.coghlan.com.au",
    "wof:name":"Coghlan Pty Ltd",
    "wof:placetype":"venue"
},
  "geometry": {"coordinates":[144.81094400000001,-37.810516],"type":"Point"}
}