{
  "type": "Feature",
  "properties": {
    "addr:full":"Lot 3241 77 Wellington Pde Alawa NT 0810",
    "addr:housenumber":"77",
    "addr:postcode":"nt 0810",
    "addr:street":"Wellington Pde",
    "iso:country":"AU",
    "sg:address":"Lot 3241 77 Wellington Pde",
    "sg:city":"Alawa",
    "sg:classifiers":[
        {
            "category":"Food & Beverages",
            "subcategory":"Liquor & Beverages",
            "type":"Retail Goods"
        }
    ],
    "sg:phone":"+61 411 519 021",
    "sg:postcode":"0810",
    "sg:province":"NT",
    "sg:tags":[
        "merchant",
        "spirit",
        "wine"
    ],
    "wof:name":"Suntory (Aust) Pty Ltd",
    "wof:placetype":"venue"
},
  "geometry": {"coordinates":[130.87229919399999,-12.3778162003],"type":"Point"}
}