{
  "type": "Feature",
  "properties": {
    "addr:full":"Unit 12 Birubi Chmbrs Hawker ACT 2614",
    "addr:postcode":"2614",
    "iso:country":"AU",
    "sg:address":"Unit 12 Birubi Chmbrs",
    "sg:city":"Hawker",
    "sg:classifiers":[
        {
            "category":"Education",
            "subcategory":"Special Training",
            "type":"Public Place"
        }
    ],
    "sg:phone":"+61 2 6255 2083",
    "sg:postcode":"2614",
    "sg:province":"ACT",
    "sg:tags":[
        "tuition-educational"
    ],
    "sg:website":"http://www.commonsensetutoring.com.au",
    "wof:name":"Commonsense Tutoring",
    "wof:placetype":"venue"
},
  "geometry": {"coordinates":[149.03636169399999,-35.2476997375],"type":"Point"}
}