{
  "type": "Feature",
  "properties": {
    "addr:full":"PO Box 445 Penguin TAS 7316",
    "addr:postcode":"7316",
    "iso:country":"AU",
    "sg:address":"PO Box 445",
    "sg:city":"Penguin",
    "sg:classifiers":[
        {
            "category":"Retail",
            "subcategory":"Car Wash",
            "type":"Services"
        }
    ],
    "sg:phone":"+61 3 6425 3958",
    "sg:postcode":"7316",
    "sg:province":"TAS",
    "sg:tags":[
        "merchant",
        "oil",
        "refiner"
    ],
    "wof:name":"Independent Oils",
    "wof:placetype":"venue"
},
  "geometry": {"coordinates":[146.06695556599999,-41.1111183167],"type":"Point"}
}