{
  "type": "Feature",
  "properties": {
    "addr:full":"5 Addison Rd Marrickville NSW 2204",
    "addr:housenumber":"5",
    "addr:postcode":"2204",
    "addr:street":"Addison Rd",
    "iso:country":"AU",
    "sg:address":"5 Addison Rd",
    "sg:city":"Marrickville",
    "sg:classifiers":[
        {
            "category":"Professional",
            "subcategory":"Business Services",
            "type":"Services"
        }
    ],
    "sg:phone":"+61 2 9519 0975",
    "sg:postcode":"2204",
    "sg:province":"NSW",
    "sg:tags":[
        "drafting"
    ],
    "wof:name":"GAP Designers Pty Ltd",
    "wof:placetype":"venue"
},
  "geometry": {"coordinates":[151.168137,-33.903896],"type":"Point"}
}