{
  "type": "Feature",
  "properties": {
    "addr:full":"Cnr Boundary Rd & Rosedale St Coopers Plains QLD 4108",
    "addr:postcode":"4108",
    "addr:street":"Cnr Boundary Rd & Rosedale St",
    "iso:country":"AU",
    "sg:address":"Cnr Boundary Rd & Rosedale St",
    "sg:city":"Coopers Plains",
    "sg:classifiers":[
        {
            "category":"Real Estate",
            "subcategory":"Real Estate Agent",
            "type":"Services"
        }
    ],
    "sg:phone":"+61 7 3345 2133",
    "sg:postcode":"4108",
    "sg:province":"QLD",
    "wof:name":"L.J. Hooker Coopers Plains",
    "wof:placetype":"venue"
},
  "geometry": {"coordinates":[153.03790283199999,-27.5703372955],"type":"Point"}
}