{
  "type": "Feature",
  "properties": {
    "addr:full":". St Braddon ACT 2612",
    "addr:postcode":"2612",
    "addr:street":"St",
    "iso:country":"AU",
    "sg:address":". St",
    "sg:city":"Braddon",
    "sg:classifiers":[
        {
            "category":"Organizations",
            "subcategory":"Professional Association",
            "type":"Services"
        }
    ],
    "sg:phone":"+61 2 6248 0639",
    "sg:postcode":"2612",
    "sg:province":"ACT",
    "sg:tags":[
        "organisation",
        "business"
    ],
    "wof:name":"Law Council Of Australia",
    "wof:placetype":"venue"
},
  "geometry": {"coordinates":[149.125686645,-35.3039398193],"type":"Point"}
}