{
  "type": "Feature",
  "properties": {
    "addr:full":"81 Adelaide Rd Mannum SA 5238",
    "addr:housenumber":"81",
    "addr:postcode":"5238",
    "addr:street":"Adelaide Rd",
    "iso:country":"AU",
    "sg:address":"81 Adelaide Rd",
    "sg:city":"Mannum",
    "sg:classifiers":[
        {
            "category":"Home & Garden",
            "subcategory":"Furniture",
            "type":"Retail Goods"
        }
    ],
    "sg:phone":"+61 8 8569 1813",
    "sg:postcode":"5238",
    "sg:province":"SA",
    "sg:tags":[
        "outdoor"
    ],
    "wof:name":"Mannum Outdoor Furniture",
    "wof:placetype":"venue"
},
  "geometry": {"coordinates":[139.30519104000001,-34.9156684875],"type":"Point"}
}