{
  "type": "Feature",
  "properties": {
    "addr:full":"40 Elder Ave Baulkham Hills NSW 2153",
    "addr:housenumber":"40",
    "addr:postcode":"2153",
    "addr:street":"Elder Ave",
    "iso:country":"AU",
    "sg:address":"40 Elder Ave",
    "sg:city":"Baulkham Hills",
    "sg:classifiers":[
        {
            "category":"Building & Trades",
            "subcategory":"Construction",
            "type":"Services"
        }
    ],
    "sg:phone":"+61 2 9639 1166",
    "sg:postcode":"2153",
    "sg:province":"NSW",
    "sg:tags":[
        "fencing",
        "contractor"
    ],
    "wof:name":"Fury J & D",
    "wof:placetype":"venue"
},
  "geometry": {"coordinates":[150.983154297,-33.7490882874],"type":"Point"}
}