{
  "type": "Feature",
  "properties": {
    "addr:full":"PO Box 269 Northbridge NSW 2063",
    "addr:postcode":"2063",
    "iso:country":"AU",
    "sg:address":"PO Box 269",
    "sg:city":"Northbridge",
    "sg:classifiers":[
        {
            "category":"Education",
            "subcategory":"Music School",
            "type":"Public Place"
        }
    ],
    "sg:phone":"+61 2 9958 6809",
    "sg:postcode":"2063",
    "sg:province":"NSW",
    "sg:tags":[
        "teacher"
    ],
    "wof:name":"Dalcroze Society Of NSW",
    "wof:placetype":"venue"
},
  "geometry": {"coordinates":[151.218383789,-33.8112602234],"type":"Point"}
}