{
  "type": "Feature",
  "properties": {
    "addr:full":"81 Braun St Deagon QLD 4017",
    "addr:housenumber":"81",
    "addr:postcode":"4017",
    "addr:street":"Braun St",
    "iso:country":"AU",
    "sg:address":"81 Braun St",
    "sg:city":"Deagon",
    "sg:classifiers":[
        {
            "category":"Fast Food",
            "type":"Food & Drink"
        }
    ],
    "sg:phone":"+61 7 3269 7442",
    "sg:postcode":"4017",
    "sg:province":"QLD",
    "sg:tags":[
        "away",
        "take"
    ],
    "wof:name":"KFC",
    "wof:placetype":"venue"
},
  "geometry": {"coordinates":[153.05792236299999,-27.3305912018],"type":"Point"}
}