{
  "type": "Feature",
  "properties": {
    "addr:full":"319 Payneham Rd Royston Park SA 5070",
    "addr:housenumber":"319",
    "addr:postcode":"5070",
    "addr:street":"Payneham Rd",
    "iso:country":"AU",
    "sg:address":"319 Payneham Rd",
    "sg:city":"Royston Park",
    "sg:classifiers":[
        {
            "category":"Food & Beverages",
            "subcategory":"Liquor & Beverages",
            "type":"Retail Goods"
        }
    ],
    "sg:phone":"+61 8 8362 1495",
    "sg:postcode":"5070",
    "sg:province":"SA",
    "sg:tags":[
        "store"
    ],
    "wof:name":"Liquorsmart Pty Ltd",
    "wof:placetype":"venue"
},
  "geometry": {"coordinates":[138.63674926799999,-34.8988761902],"type":"Point"}
}