{
  "type": "Feature",
  "properties": {
    "addr:full":"2 Main St Mornington VIC 3931",
    "addr:housenumber":"2",
    "addr:postcode":"3931",
    "addr:street":"Main St",
    "iso:country":"AU",
    "sg:address":"2 Main St",
    "sg:city":"Mornington",
    "sg:classifiers":[
        {
            "category":"Organizations",
            "subcategory":"Professional Association",
            "type":"Services"
        }
    ],
    "sg:phone":"+61 3 5975 4522",
    "sg:postcode":"3931",
    "sg:province":"VIC",
    "sg:tags":[
        "organisation",
        "business"
    ],
    "wof:name":"Mornington Chamber Of Commerce",
    "wof:placetype":"venue"
},
  "geometry": {"coordinates":[145.0365448,-38.2161483765],"type":"Point"}
}