{
  "type": "Feature",
  "properties": {
    "addr:full":"23 Bell St Yarra Glen VIC 3775",
    "addr:housenumber":"23",
    "addr:postcode":"3775",
    "addr:street":"Bell St",
    "iso:country":"AU",
    "sg:address":"23 Bell St",
    "sg:city":"Yarra Glen",
    "sg:classifiers":[
        {
            "category":"Shopping",
            "subcategory":"Clothing, Apparel, & Fashions",
            "type":"Retail Goods"
        }
    ],
    "sg:phone":"+61 3 9730 2022",
    "sg:postcode":"3775",
    "sg:province":"VIC",
    "sg:tags":[
        "boutique"
    ],
    "wof:name":"Cloth Art",
    "wof:placetype":"venue"
},
  "geometry": {"coordinates":[145.37449599999999,-37.658634],"type":"Point"}
}