{
  "type": "Feature",
  "properties": {
    "addr:full":"Level 7, 55 Currie St Adelaide SA 5000",
    "addr:housenumber":"55",
    "addr:postcode":"5000",
    "addr:street":"Currie St",
    "iso:country":"AU",
    "sg:address":"Level 7, 55 Currie St",
    "sg:city":"Adelaide",
    "sg:classifiers":[
        {
            "category":"Organizations",
            "subcategory":"Professional Association",
            "type":"Services"
        }
    ],
    "sg:phone":"+61 8 8212 7155",
    "sg:postcode":"5000",
    "sg:province":"SA",
    "sg:tags":[
        "organisation",
        "business"
    ],
    "wof:name":"Institute Of Public Administration Australia (SA) Division",
    "wof:placetype":"venue"
},
  "geometry": {"coordinates":[138.59678649899999,-34.9247207642],"type":"Point"}
}