{
  "type": "Feature",
  "properties": {
    "addr:full":"4 Newlands Crt Box Hill South VIC 3128",
    "addr:housenumber":"4",
    "addr:postcode":"3128",
    "addr:street":"Newlands Crt",
    "iso:country":"AU",
    "sg:address":"4 Newlands Crt",
    "sg:city":"Box Hill South",
    "sg:classifiers":[
        {
            "category":"Real Estate",
            "subcategory":"Architect",
            "type":"Services"
        }
    ],
    "sg:phone":"+61 3 9808 7720",
    "sg:postcode":"3128",
    "sg:province":"VIC",
    "wof:name":"Rice Nettle Pty Ltd",
    "wof:placetype":"venue"
},
  "geometry": {"coordinates":[145.11703491200001,-37.8384437561],"type":"Point"}
}