{
  "type": "Feature",
  "properties": {
    "addr:full":"PO Box 449 North Melbourne VIC 3051",
    "addr:postcode":"3051",
    "iso:country":"AU",
    "sg:address":"PO Box 449",
    "sg:city":"North Melbourne",
    "sg:classifiers":[
        {
            "category":"Professional",
            "subcategory":"Accounting & Tax Preparation",
            "type":"Services"
        }
    ],
    "sg:phone":"+61 3 9326 9229",
    "sg:postcode":"3051",
    "sg:province":"VIC",
    "sg:tags":[
        "accountant",
        "auditor"
    ],
    "wof:name":"Dudley & Associates",
    "wof:placetype":"venue"
},
  "geometry": {"coordinates":[144.946868897,-37.7967987061],"type":"Point"}
}