{
  "type": "Feature",
  "properties": {
    "addr:full":"58 Sugarloaf Crs Middle Cove NSW 2068",
    "addr:housenumber":"58",
    "addr:postcode":"2068",
    "addr:street":"Sugarloaf Crs",
    "iso:country":"AU",
    "sg:address":"58 Sugarloaf Crs",
    "sg:city":"Middle Cove",
    "sg:classifiers":[
        {
            "category":"Professional",
            "subcategory":"Business Services",
            "type":"Services"
        }
    ],
    "sg:phone":"+61 2 9958 7452",
    "sg:postcode":"2068",
    "sg:province":"NSW",
    "sg:tags":[
        "exporter"
    ],
    "wof:name":"Export Action Pty Ltd",
    "wof:placetype":"venue"
},
  "geometry": {"coordinates":[151.20758056599999,-33.7932090759],"type":"Point"}
}