{
  "type": "Feature",
  "properties": {
    "addr:full":"58 Sherwood Rd Rocklea QLD 4106",
    "addr:housenumber":"58",
    "addr:postcode":"4106",
    "addr:street":"Sherwood Rd",
    "iso:country":"AU",
    "sg:address":"58 Sherwood Rd",
    "sg:city":"Rocklea",
    "sg:classifiers":[
        {
            "category":"Manufacturing",
            "subcategory":"Building Materials",
            "type":"Manufacturing & Wholesale Goods"
        }
    ],
    "sg:phone":"+61 7 3892 5046",
    "sg:postcode":"4106",
    "sg:province":"QLD",
    "sg:tags":[
        "equipment",
        "handling"
    ],
    "wof:name":"R Gartner Contractor",
    "wof:placetype":"venue"
},
  "geometry": {"coordinates":[153.008712769,-27.5406188965],"type":"Point"}
}