{
  "type": "Feature",
  "properties": {
    "addr:full":"Myall Medical Practice 40 Archibald St Dalby QLD 4405",
    "addr:housenumber":"40",
    "addr:postcode":"4405",
    "addr:street":"Archibald St",
    "iso:country":"AU",
    "sg:address":"Myall Medical Practice 40 Archibald St",
    "sg:city":"Dalby",
    "sg:classifiers":[
        {
            "category":"Health Services",
            "subcategory":"Doctor",
            "type":"Services"
        }
    ],
    "sg:phone":"+61 7 4662 2433",
    "sg:postcode":"4405",
    "sg:province":"QLD",
    "sg:tags":[
        "medical",
        "practitioner"
    ],
    "wof:name":"Lynch K",
    "wof:placetype":"venue"
},
  "geometry": {"coordinates":[151.26411438,-27.1811103821],"type":"Point"}
}