{
  "type": "Feature",
  "properties": {
    "addr:full":"371 High St Maitland NSW 2320",
    "addr:housenumber":"371",
    "addr:postcode":"2320",
    "addr:street":"High St",
    "iso:country":"AU",
    "sg:address":"371 High St",
    "sg:city":"Maitland",
    "sg:classifiers":[
        {
            "category":"Insurance",
            "subcategory":"Health Insurance",
            "type":"Services"
        }
    ],
    "sg:phone":"+61 2 4933 3211",
    "sg:postcode":"2320",
    "sg:province":"NSW",
    "wof:name":"NIB Health Funds",
    "wof:placetype":"venue"
},
  "geometry": {"coordinates":[151.55723571799999,-32.7334823608],"type":"Point"}
}