{
  "type": "Feature",
  "properties": {
    "iso:country":"AU",
    "sg:address":"110 Pateena St",
    "sg:city":"Stafford",
    "sg:classifiers":[
        {
            "category":"Personal",
            "subcategory":"Beauty Salon",
            "type":"Services"
        }
    ],
    "sg:phone":"+61 7 3352 5681",
    "sg:postcode":"4053",
    "sg:province":"QLD",
    "sg:tags":[
        "hairdresser"
    ],
    "wof:name":"Flavas Hair Beauty",
    "wof:placetype":"venue"
},
  "geometry": {"coordinates":[153.01138305699999,-27.4068775177],"type":"Point"}
}