{
  "type": "Feature",
  "properties": {
    "addr:full":"Cnr Wellington & Jacksons Rd Mulgrave VIC 3170",
    "addr:postcode":"3170",
    "addr:street":"Cnr Wellington & Jacksons Rd",
    "iso:country":"AU",
    "sg:address":"Cnr Wellington & Jacksons Rd",
    "sg:city":"Mulgrave",
    "sg:classifiers":[
        {
            "category":"Shopping",
            "subcategory":"Beauty & Cosmetics",
            "type":"Retail Goods"
        }
    ],
    "sg:phone":"+61 3 9565 0500",
    "sg:postcode":"3170",
    "sg:province":"VIC",
    "wof:name":"The Body Shop",
    "wof:placetype":"venue"
},
  "geometry": {"coordinates":[145.165924072,-37.9197616577],"type":"Point"}
}