{
  "type": "Feature",
  "properties": {
    "addr:full":"Shp 17 Huon Village Main Rd Huonville TAS 7109",
    "addr:housenumber":"17",
    "addr:postcode":"7109",
    "addr:street":"Huon Village Main Rd",
    "iso:country":"AU",
    "sg:address":"Shp 17 Huon Village Main Rd",
    "sg:city":"Huonville",
    "sg:classifiers":[
        {
            "category":"Manufacturing",
            "subcategory":"Jewelry",
            "type":"Manufacturing & Wholesale Goods"
        }
    ],
    "sg:phone":"+61 3 6264 1088",
    "sg:postcode":"7109",
    "sg:province":"TAS",
    "sg:tags":[
        "designer",
        "jewellery"
    ],
    "wof:name":"Huon Valley Jewellers",
    "wof:placetype":"venue"
},
  "geometry": {"coordinates":[147.03364563,-43.0093955994],"type":"Point"}
}