{
  "type": "Feature",
  "properties": {
    "addr:full":"Shp1/ 107 Alexander St Crows Nest NSW 2065",
    "addr:housenumber":"107",
    "addr:postcode":"2065",
    "addr:street":"Alexander St",
    "iso:country":"AU",
    "sg:address":"Shp1/ 107 Alexander St",
    "sg:city":"Crows Nest",
    "sg:classifiers":[
        {
            "category":"Cafe",
            "type":"Food & Drink"
        }
    ],
    "sg:phone":"+61 2 9460 8485",
    "sg:postcode":"2065",
    "sg:province":"NSW",
    "wof:name":"Cafe 107",
    "wof:placetype":"venue"
},
  "geometry": {"coordinates":[151.20262145999999,-33.8253593445],"type":"Point"}
}