{
  "type": "Feature",
  "properties": {
    "iso:country":"AU",
    "sg:address":"1304 High Street Rd",
    "sg:city":"Wantirna South",
    "sg:classifiers":[
        {
            "category":"Food & Beverages",
            "subcategory":"Bakery",
            "type":"Retail Goods"
        }
    ],
    "sg:phone":"+61 3 9801 6962",
    "sg:postcode":"3152",
    "sg:province":"VIC",
    "sg:tags":[
        "baker"
    ],
    "wof:name":"One Stop Bakery",
    "wof:placetype":"venue"
},
  "geometry": {"coordinates":[145.22134399399999,-37.8771324158],"type":"Point"}
}