{
  "type": "Feature",
  "properties": {
    "iso:country":"AU",
    "sg:address":"1 Station Street",
    "sg:city":"Ferntree Gully",
    "sg:classifiers":[
        {
            "category":"Social Services",
            "subcategory":"Retirement Home",
            "type":"Services"
        }
    ],
    "sg:phone":"+61 3 9753 1999",
    "sg:postcode":"3156",
    "sg:province":"VIC",
    "sg:tags":[
        "village"
    ],
    "wof:name":"Lifestyle Apartments At Ferntree",
    "wof:placetype":"venue"
},
  "geometry": {"coordinates":[145.29142761200001,-37.8883094788],"type":"Point"}
}