{
  "type": "Feature",
  "properties": {
    "addr:full":"27 Lavinia St Athol Park SA 5012",
    "addr:housenumber":"27",
    "addr:postcode":"5012",
    "addr:street":"Lavinia St",
    "iso:country":"AU",
    "sg:address":"27 Lavinia St",
    "sg:city":"Athol Park",
    "sg:classifiers":[
        {
            "category":"Building & Trades",
            "subcategory":"Construction",
            "type":"Services"
        }
    ],
    "sg:phone":"+61 8 8447 2822",
    "sg:postcode":"5012",
    "sg:province":"SA",
    "sg:tags":[
        "insulation",
        "contractor"
    ],
    "wof:name":"Auspoly Pty Ltd",
    "wof:placetype":"venue"
},
  "geometry": {"coordinates":[138.54045105,-34.8544158936],"type":"Point"}
}