{
  "type": "Feature",
  "properties": {
    "addr:full":"39 Ocean Beach Rd Sorrento VIC 3943",
    "addr:housenumber":"39",
    "addr:postcode":"3943",
    "addr:street":"Ocean Beach Rd",
    "iso:country":"AU",
    "sg:address":"39 Ocean Beach Rd",
    "sg:city":"Sorrento",
    "sg:classifiers":[
        {
            "category":"Real Estate",
            "subcategory":"Real Estate Agent",
            "type":"Services"
        }
    ],
    "sg:phone":"+61 3 5984 0999",
    "sg:postcode":"3943",
    "sg:province":"VIC",
    "wof:name":"Beach House Realty",
    "wof:placetype":"venue"
},
  "geometry": {"coordinates":[144.74075317399999,-38.339214325],"type":"Point"}
}