{
  "type": "Feature",
  "properties": {
    "addr:full":"1f Cowell St Gladesville NSW 2111",
    "addr:housenumber":"1f",
    "addr:postcode":"2111",
    "addr:street":"Cowell St",
    "iso:country":"AU",
    "sg:address":"1f Cowell St",
    "sg:city":"Gladesville",
    "sg:classifiers":[
        {
            "category":"Fast Food",
            "type":"Food & Drink"
        }
    ],
    "sg:phone":"+61 2 9879 3941",
    "sg:postcode":"2111",
    "sg:province":"NSW",
    "sg:tags":[
        "away",
        "take"
    ],
    "wof:name":"Gourmet Pizza Pantry",
    "wof:placetype":"venue"
},
  "geometry": {"coordinates":[151.12718200699999,-33.8329124451],"type":"Point"}
}