{
  "type": "Feature",
  "properties": {
    "addr:full":"4 Front St Mossman QLD 4873",
    "addr:housenumber":"4",
    "addr:postcode":"4873",
    "addr:street":"Front St",
    "iso:country":"AU",
    "sg:address":"4 Front St",
    "sg:city":"Mossman",
    "sg:classifiers":[
        {
            "category":"Health Services",
            "subcategory":"Medical Lab",
            "type":"Services"
        }
    ],
    "sg:phone":"+61 7 4098 1054",
    "sg:postcode":"4873",
    "sg:province":"QLD",
    "sg:tags":[
        "laboratory",
        "pathology"
    ],
    "wof:name":"Sullivan Nicolaides Pathology Laboratories",
    "wof:placetype":"venue"
},
  "geometry": {"coordinates":[145.373809814,-16.4594478607],"type":"Point"}
}