{
  "type": "Feature",
  "properties": {
    "addr:full":"5 Copernicur Rd Christies Beach SA 5165",
    "addr:housenumber":"5",
    "addr:postcode":"5165",
    "addr:street":"Copernicur Rd",
    "iso:country":"AU",
    "sg:address":"5 Copernicur Rd",
    "sg:city":"Christies Beach",
    "sg:classifiers":[
        {
            "category":"Retail",
            "subcategory":"Auto Repair",
            "type":"Services"
        }
    ],
    "sg:phone":"+61 1300 130 035",
    "sg:postcode":"5165",
    "sg:province":"SA",
    "sg:tags":[
        "testing",
        "inspection",
        "motor",
        "vehicle"
    ],
    "wof:name":"Motacheck Vehicle Inspection Service",
    "wof:placetype":"venue"
},
  "geometry": {"coordinates":[138.48712158199999,-35.1248893738],"type":"Point"}
}