{
  "type": "Feature",
  "properties": {
    "addr:full":"62 Clifford St Goulburn NSW 2580",
    "addr:housenumber":"62",
    "addr:postcode":"2580",
    "addr:street":"Clifford St",
    "iso:country":"AU",
    "sg:address":"62 Clifford St",
    "sg:city":"Goulburn",
    "sg:classifiers":[
        {
            "category":"Retail",
            "subcategory":"Veterinary Services",
            "type":"Services"
        }
    ],
    "sg:phone":"+61 2 4821 1966",
    "sg:postcode":"2580",
    "sg:province":"NSW",
    "sg:tags":[
        "surgeon"
    ],
    "wof:name":"Ian Hayes",
    "wof:placetype":"venue"
},
  "geometry": {"coordinates":[149.718353272,-34.7521591187],"type":"Point"}
}