{
  "type": "Feature",
  "properties": {
    "addr:full":"1 Park Rd Rydalmere NSW 2116",
    "addr:housenumber":"1",
    "addr:postcode":"2116",
    "addr:street":"Park Rd",
    "iso:country":"AU",
    "sg:address":"1 Park Rd",
    "sg:city":"Rydalmere",
    "sg:classifiers":[
        {
            "category":"Autos & Motor Vehicles",
            "subcategory":"Automobile Sales",
            "type":"Retail Goods"
        }
    ],
    "sg:phone":"+61 2 9684 6179",
    "sg:postcode":"2116",
    "sg:province":"NSW",
    "sg:tags":[
        "car",
        "used"
    ],
    "wof:name":"Budget Auto Wholesale",
    "wof:placetype":"venue"
},
  "geometry": {"coordinates":[151.031005859,-33.8488044739],"type":"Point"}
}