{
  "type": "Feature",
  "properties": {
    "addr:full":"37 Cawarra Rd Caringbah NSW 2229",
    "addr:housenumber":"37",
    "addr:postcode":"2229",
    "addr:street":"Cawarra Rd",
    "iso:country":"AU",
    "sg:address":"37 Cawarra Rd",
    "sg:city":"Caringbah",
    "sg:classifiers":[
        {
            "category":"Professional",
            "type":"Services"
        }
    ],
    "sg:phone":"+61 2 9540 3333",
    "sg:postcode":"2229",
    "sg:province":"NSW",
    "sg:tags":[
        "spray",
        "painting"
    ],
    "wof:name":"Cawarra Smash Repairs",
    "wof:placetype":"venue"
},
  "geometry": {"coordinates":[151.126052856,-34.0285453796],"type":"Point"}
}