{
  "type": "Feature",
  "properties": {
    "iso:country":"AU",
    "sg:address":"1032 Port Rd",
    "sg:city":"Albert Park",
    "sg:classifiers":[
        {
            "category":"Retail",
            "subcategory":"Auto Repair",
            "type":"Services"
        }
    ],
    "sg:phone":"+61 8 8445 7422",
    "sg:postcode":"5014",
    "sg:province":"SA",
    "sg:tags":[
        "repairer",
        "motor",
        "engineer"
    ],
    "wof:name":"Portside Mitsubishi",
    "wof:placetype":"venue"
},
  "geometry": {"coordinates":[138.52096557600001,-34.8717384338],"type":"Point"}
}