{
  "type": "Feature",
  "properties": {
    "iso:country":"AU",
    "sg:address":"Hepburn St",
    "sg:city":"Mt Magnet",
    "sg:classifiers":[
        {
            "category":"Travel",
            "subcategory":"Hotels & Motels",
            "type":"Entertainment"
        }
    ],
    "sg:phone":"+61 8 9963 4110",
    "sg:postcode":"6638",
    "sg:province":"WA",
    "sg:tags":[
        "accommodation"
    ],
    "wof:name":"Grand Hotel-Motel",
    "wof:placetype":"venue"
},
  "geometry": {"coordinates":[117.849006653,-28.0640220642],"type":"Point"}
}