{
  "type": "Feature",
  "properties": {
    "iso:country":"AU",
    "sg:address":"Park St",
    "sg:city":"Millthorpe",
    "sg:classifiers":[
        {
            "category":"Education",
            "subcategory":"School",
            "type":"Public Place"
        }
    ],
    "sg:phone":"+61 2 6366 3104",
    "sg:postcode":"2798",
    "sg:province":"NSW",
    "sg:tags":[
        "state",
        "-",
        "nsw"
    ],
    "wof:name":"Millthorpe Public School",
    "wof:placetype":"venue"
},
  "geometry": {"coordinates":[149.185302734,-33.4468727112],"type":"Point"}
}