{
  "type": "Feature",
  "properties": {
    "addr:full":"5 Cabbage Tree Point Rd Steiglitz QLD 4207",
    "addr:housenumber":"5",
    "addr:postcode":"4207",
    "addr:street":"Cabbage Tree Point Rd",
    "iso:country":"AU",
    "sg:address":"5 Cabbage Tree Point Rd",
    "sg:city":"Steiglitz",
    "sg:classifiers":[
        {
            "category":"Cafe",
            "type":"Food & Drink"
        }
    ],
    "sg:phone":"+61 7 5546 2224",
    "sg:postcode":"4207",
    "sg:province":"QLD",
    "wof:name":"Anchorage Cafe The",
    "wof:placetype":"venue"
},
  "geometry": {"coordinates":[153.33644104000001,-27.7475643158],"type":"Point"}
}