{
  "type": "Feature",
  "properties": {
    "addr:full":"1/9 Nilson Ave Hillsdale NSW 2036",
    "addr:housenumber":"/ 9",
    "addr:postcode":"2036",
    "addr:street":"Nilson Ave",
    "iso:country":"AU",
    "sg:address":"1/9 Nilson Ave",
    "sg:city":"Hillsdale",
    "sg:classifiers":[
        {
            "category":"Professional",
            "subcategory":"Management & Consulting",
            "type":"Services"
        }
    ],
    "sg:phone":"+61 2 9661 9728",
    "sg:postcode":"2036",
    "sg:province":"NSW",
    "sg:tags":[
        "consultant",
        "migration"
    ],
    "wof:name":"A Chen & Associates",
    "wof:placetype":"venue"
},
  "geometry": {"coordinates":[151.22482299800001,-33.9546279907],"type":"Point"}
}