{
  "type": "Feature",
  "properties": {
    "addr:full":"PO Box 2004 Caroline Springs VIC 3023",
    "addr:postcode":"3023",
    "iso:country":"AU",
    "sg:address":"PO Box 2004",
    "sg:city":"Caroline Springs",
    "sg:classifiers":[
        {
            "category":"Building & Trades",
            "subcategory":"Construction",
            "type":"Services"
        }
    ],
    "sg:phone":"+61 3 9360 4627",
    "sg:postcode":"3023",
    "sg:province":"VIC",
    "sg:tags":[
        "bitumen",
        "paving",
        "asphalt"
    ],
    "wof:name":"Chapman Civil Industries",
    "wof:placetype":"venue"
},
  "geometry": {"coordinates":[144.73519899999999,-37.744961],"type":"Point"}
}