{
  "type": "Feature",
  "properties": {
    "addr:full":"1159 South Rd St Marys SA 5042",
    "addr:housenumber":"1159",
    "addr:postcode":"5042",
    "addr:street":"South Rd",
    "iso:country":"AU",
    "sg:address":"1159 South Rd St",
    "sg:city":"Marys",
    "sg:classifiers":[
        {
            "category":"Wholesale",
            "subcategory":"Non-durable Goods",
            "type":"Manufacturing & Wholesale Goods"
        }
    ],
    "sg:phone":"+61 8 8263 4144",
    "sg:postcode":"5042",
    "sg:province":"SA",
    "sg:tags":[
        "wholesaler",
        "mfrs",
        "cosmetic"
    ],
    "wof:name":"Elixir Body Care",
    "wof:placetype":"venue"
},
  "geometry": {"coordinates":[138.57545500000001,-34.997684],"type":"Point"}
}