{
  "type": "Feature",
  "properties": {
    "addr:full":"4 Export Drv Ulverstone TAS 7315",
    "addr:housenumber":"4",
    "addr:postcode":"7315",
    "addr:street":"Export Drv",
    "iso:country":"AU",
    "sg:address":"4 Export Drv",
    "sg:city":"Ulverstone",
    "sg:classifiers":[
        {
            "category":"Industrial Area",
            "type":"Public Place"
        }
    ],
    "sg:phone":"+61 3 6425 3333",
    "sg:postcode":"7315",
    "sg:province":"TAS",
    "sg:tags":[
        "rural",
        "shed"
    ],
    "wof:name":"Sheds-R-Us",
    "wof:placetype":"venue"
},
  "geometry": {"coordinates":[146.20175170900001,-41.1553916931],"type":"Point"}
}