{
  "type": "Feature",
  "properties": {
    "addr:full":"191 Stanley St West Melbourne VIC 3003",
    "addr:housenumber":"191",
    "addr:postcode":"3003",
    "addr:street":"Stanley St",
    "iso:country":"AU",
    "sg:address":"191 Stanley St",
    "sg:city":"West Melbourne",
    "sg:classifiers":[
        {
            "category":"Professional",
            "subcategory":"Employment Agencies",
            "type":"Services"
        }
    ],
    "sg:phone":"+61 418 179 901",
    "sg:postcode":"3003",
    "sg:province":"VIC",
    "sg:tags":[
        "broker",
        "custom"
    ],
    "wof:name":"Gibson Customs & Forwarding",
    "wof:placetype":"venue"
},
  "geometry": {"coordinates":[144.946075439,-37.8102340698],"type":"Point"}
}