{
  "type": "Feature",
  "properties": {
    "addr:full":"13 Lalor St Portland VIC 3305",
    "addr:housenumber":"13",
    "addr:postcode":"3305",
    "addr:street":"Lalor St",
    "iso:country":"AU",
    "sg:address":"13 Lalor St",
    "sg:city":"Portland",
    "sg:classifiers":[
        {
            "category":"Communications",
            "type":"Services"
        }
    ],
    "sg:phone":"+61 3 5523 4485",
    "sg:postcode":"3305",
    "sg:province":"VIC",
    "sg:tags":[
        "translation"
    ],
    "wof:name":"Bowyer John",
    "wof:placetype":"venue"
},
  "geometry": {"coordinates":[141.58169555699999,-38.3443641663],"type":"Point"}
}