{
  "type": "Feature",
  "properties": {
    "addr:full":"128 Glider Ave Shellharbour NSW 2529",
    "addr:housenumber":"128",
    "addr:postcode":"2529",
    "addr:street":"Glider Ave",
    "iso:country":"AU",
    "sg:address":"128 Glider Ave",
    "sg:city":"Shellharbour",
    "sg:classifiers":[
        {
            "category":"Building & Trades",
            "subcategory":"Cleaning & Sanitation",
            "type":"Services"
        }
    ],
    "sg:phone":"+61 2 4295 5530",
    "sg:postcode":"2529",
    "sg:province":"NSW",
    "sg:tags":[
        "industrial",
        "commercial",
        "contractor"
    ],
    "wof:name":"Moon Raider Pty Ltd",
    "wof:placetype":"venue"
},
  "geometry": {"coordinates":[150.840286255,-34.573261261],"type":"Point"}
}