{
  "type": "Feature",
  "properties": {
    "addr:full":"Shop 31 a/ Forest Way Frenchs Forest NSW 2086",
    "addr:housenumber":"shop 31 a /",
    "addr:postcode":"2086",
    "addr:street":"Forest Way",
    "iso:country":"AU",
    "sg:address":"Shop 31",
    "sg:city":"a/ Forest Way Frenchs Forest",
    "sg:classifiers":[
        {
            "category":"Fast Food",
            "type":"Food & Drink"
        }
    ],
    "sg:phone":"+61 2 9975 1115",
    "sg:postcode":"2086",
    "sg:province":"NSW",
    "sg:tags":[
        "away",
        "take"
    ],
    "wof:name":"Kebab City",
    "wof:placetype":"venue"
},
  "geometry": {"coordinates":[151.223190308,-33.7466697693],"type":"Point"}
}