{
  "type": "Feature",
  "properties": {
    "addr:full":"Baddaginnie Rd Benalla VIC 3672",
    "addr:postcode":"3672",
    "addr:street":"Baddaginnie Rd",
    "iso:country":"AU",
    "sg:address":"Baddaginnie Rd",
    "sg:city":"Benalla",
    "sg:classifiers":[
        {
            "category":"Autos & Motor Vehicles",
            "subcategory":"Fuel & Gas Station",
            "type":"Retail Goods"
        }
    ],
    "sg:phone":"+61 3 5762 1179",
    "sg:postcode":"3672",
    "sg:province":"VIC",
    "wof:name":"BP Australia Limited",
    "wof:placetype":"venue"
},
  "geometry": {"coordinates":[146.00680500000001,-36.57111],"type":"Point"}
}