{
  "type": "Feature",
  "properties": {
    "addr:full":"4 Railway Ave Oakleigh VIC 3166",
    "addr:housenumber":"4",
    "addr:postcode":"3166",
    "addr:street":"Railway Ave",
    "iso:country":"AU",
    "sg:address":"4 Railway Ave",
    "sg:city":"Oakleigh",
    "sg:classifiers":[
        {
            "category":"Recreation",
            "type":"Entertainment"
        }
    ],
    "sg:phone":"+61 3 9568 7000",
    "sg:postcode":"3166",
    "sg:province":"VIC",
    "sg:tags":[
        "children's",
        "play",
        "programme"
    ],
    "wof:name":"Playdays",
    "wof:placetype":"venue"
},
  "geometry": {"coordinates":[145.10118102999999,-37.9093208313],"type":"Point"}
}