{
  "type": "Feature",
  "properties": {
    "addr:full":"(RMB 917) Narrogin WA 6312",
    "addr:postcode":"6312",
    "iso:country":"AU",
    "sg:address":"(RMB 917)",
    "sg:city":"Narrogin",
    "sg:classifiers":[
        {
            "category":"Farming",
            "subcategory":"Farm",
            "type":"Manufacturing & Wholesale Goods"
        }
    ],
    "sg:phone":"+61 8 9884 5247",
    "sg:postcode":"6312",
    "sg:province":"WA",
    "sg:tags":[
        "farmer"
    ],
    "wof:name":"Bradford K D & Y M",
    "wof:placetype":"venue"
},
  "geometry": {"coordinates":[117.17830658,-32.931388855],"type":"Point"}
}