{
  "type": "Feature",
  "properties": {
    "addr:full":"66- 68 Mahogany Drv Halls Head WA 6210",
    "addr:housenumber":"68",
    "addr:postcode":"6210",
    "addr:street":"Mahogany Drv",
    "iso:country":"AU",
    "sg:address":"66- 68 Mahogany Drv",
    "sg:city":"Halls Head",
    "sg:classifiers":[
        {
            "category":"Health Services",
            "subcategory":"Doctor",
            "type":"Services"
        }
    ],
    "sg:phone":"+61 8 9535 2400",
    "sg:postcode":"6210",
    "sg:province":"WA",
    "sg:tags":[
        "medical",
        "practitioner"
    ],
    "wof:name":"Skincheck",
    "wof:placetype":"venue"
},
  "geometry": {"coordinates":[115.699532,-32.549931],"type":"Point"}
}