{
  "type": "Feature",
  "properties": {
    "addr:full":"41 Phillip Island Rd Newhaven VIC 3925",
    "addr:housenumber":"41",
    "addr:postcode":"3925",
    "addr:street":"Phillip Island Rd",
    "iso:country":"AU",
    "sg:address":"41 Phillip Island Rd",
    "sg:city":"Newhaven",
    "sg:classifiers":[
        {
            "category":"Health Services",
            "subcategory":"Doctor",
            "type":"Services"
        }
    ],
    "sg:phone":"+61 3 5956 7881",
    "sg:postcode":"3925",
    "sg:province":"VIC",
    "sg:tags":[
        "medical",
        "practitioner"
    ],
    "wof:name":"Khong J",
    "wof:placetype":"venue"
},
  "geometry": {"coordinates":[145.35516357399999,-38.5146484375],"type":"Point"}
}