{
  "type": "Feature",
  "properties": {
    "iso:country":"AU",
    "sg:address":"Shop 4, Tirana City Walk Wyndham St",
    "sg:city":"Shepparton",
    "sg:classifiers":[
        {
            "category":"Wholesale",
            "subcategory":"Furniture",
            "type":"Manufacturing & Wholesale Goods"
        }
    ],
    "sg:phone":"+61 3 5821 9482",
    "sg:postcode":"3630",
    "sg:province":"VIC",
    "sg:tags":[
        "wholesaler",
        "mfrs"
    ],
    "wof:name":"Creative Wooden Ideas",
    "wof:placetype":"venue"
},
  "geometry": {"coordinates":[145.394241333,-36.4055709839],"type":"Point"}
}