{
  "type": "Feature",
  "properties": {
    "addr:full":"1&2/ 164a Park Tce Salisbury Plain SA 5109",
    "addr:housenumber":"164a",
    "addr:postcode":"5109",
    "addr:street":"Park Tce",
    "iso:country":"AU",
    "sg:address":"1&2/ 164a Park Tce",
    "sg:city":"Salisbury Plain",
    "sg:classifiers":[
        {
            "category":"Autos & Motor Vehicles",
            "subcategory":"Auto Supplies",
            "type":"Retail Goods"
        }
    ],
    "sg:phone":"+61 8 8285 8380",
    "sg:postcode":"5109",
    "sg:province":"SA",
    "sg:tags":[
        "camper-trailers",
        "caravan",
        "equipment"
    ],
    "wof:name":"Adventura Caravans Pty Ltd",
    "wof:placetype":"venue"
},
  "geometry": {"coordinates":[138.667434692,-34.7683906555],"type":"Point"}
}