{
  "type": "Feature",
  "properties": {
    "addr:full":"85 Henry&#039;s Rd Cambooya QLD 4358",
    "addr:housenumber":"85",
    "addr:postcode":"4358",
    "addr:street":"Henry &;039 S Rd",
    "iso:country":"AU",
    "sg:address":"85 Henry&#039;s Rd",
    "sg:city":"Cambooya",
    "sg:classifiers":[
        {
            "category":"Building & Trades",
            "subcategory":"Plumbing",
            "type":"Services"
        }
    ],
    "sg:phone":"+61 7 4696 1266",
    "sg:postcode":"4358",
    "sg:province":"QLD",
    "sg:tags":[
        "repair",
        "appliance",
        "system",
        "heating"
    ],
    "wof:name":"Minnikin D J & L",
    "wof:placetype":"venue"
},
  "geometry": {"coordinates":[151.873627,-27.708389],"type":"Point"}
}