{
  "type": "Feature",
  "properties": {
    "iso:country":"AU",
    "sg:address":"268 Bickley Rd",
    "sg:city":"Kenwick",
    "sg:classifiers":[
        {
            "category":"Freight",
            "type":"Transportation"
        }
    ],
    "sg:phone":"+61 8 9459 5933",
    "sg:postcode":"6107",
    "sg:province":"WA",
    "sg:tags":[
        "cargo",
        "container"
    ],
    "wof:name":"W.A. Container Services",
    "wof:placetype":"venue"
},
  "geometry": {"coordinates":[115.975791931,-32.0223426819],"type":"Point"}
}