{
  "type": "Feature",
  "properties": {
    "addr:full":"Suite 1, First Floor 246 Bridge Rd Richmond VIC 3121",
    "addr:housenumber":"first floor 246",
    "addr:postcode":"3121",
    "addr:street":"Bridge Rd",
    "iso:country":"AU",
    "sg:address":"Suite 1, First Floor 246 Bridge Rd",
    "sg:city":"Richmond",
    "sg:classifiers":[
        {
            "category":"Personal",
            "subcategory":"Massage",
            "type":"Services"
        }
    ],
    "sg:phone":"+61 3 9427 8848",
    "sg:postcode":"3121",
    "sg:province":"VIC",
    "sg:tags":[
        "therapy"
    ],
    "wof:name":"Mavis Ian",
    "wof:placetype":"venue"
},
  "geometry": {"coordinates":[144.99905395499999,-37.8187065125],"type":"Point"}
}