{
  "type": "Feature",
  "properties": {
    "addr:full":"Shop 12 202 Military Rd Neutral Bay NSW 2089",
    "addr:housenumber":"shop 12 202",
    "addr:postcode":"2089",
    "addr:street":"Military Rd",
    "iso:country":"AU",
    "sg:address":"Shop 12 202 Military Rd",
    "sg:city":"Neutral Bay",
    "sg:classifiers":[
        {
            "category":"Shopping",
            "subcategory":"Clothing, Apparel, & Fashions",
            "type":"Retail Goods"
        }
    ],
    "sg:phone":"+61 2 9953 4128",
    "sg:postcode":"2089",
    "sg:province":"NSW",
    "sg:tags":[
        "lady",
        "wear"
    ],
    "wof:name":"L.A. Look",
    "wof:placetype":"venue"
},
  "geometry": {"coordinates":[151.22259521500001,-33.8314056396],"type":"Point"}
}