{
  "type": "Feature",
  "properties": {
    "addr:full":"Shop 2, 48- 62 Majors Bay Rd Concord NSW 2137",
    "addr:housenumber":"shop;48 62",
    "addr:postcode":"2137",
    "addr:street":"Majors Bay Rd",
    "iso:country":"AU",
    "sg:address":"Shop 2, 48- 62 Majors Bay Rd",
    "sg:city":"Concord",
    "sg:classifiers":[
        {
            "category":"Food & Beverages",
            "subcategory":"Bakery",
            "type":"Retail Goods"
        }
    ],
    "sg:phone":"+61 2 8765 0977",
    "sg:postcode":"2137",
    "sg:province":"NSW",
    "sg:tags":[
        "baker"
    ],
    "wof:name":"Bakers Delight Ltd",
    "wof:placetype":"venue"
},
  "geometry": {"coordinates":[151.10325622600001,-33.8570594788],"type":"Point"}
}