{
  "type": "Feature",
  "properties": {
    "iso:country":"AU",
    "sg:address":"205/b Wright St",
    "sg:city":"Belmont",
    "sg:classifiers":[
        {
            "category":"Health Services",
            "subcategory":"Dentist",
            "type":"Services"
        }
    ],
    "sg:phone":"+61 8 9479 1970",
    "sg:postcode":"6104",
    "sg:province":"WA",
    "wof:name":"Cassettai Rose",
    "wof:placetype":"venue"
},
  "geometry": {"coordinates":[115.933372498,-31.941619873],"type":"Point"}
}