{
  "type": "Feature",
  "properties": {
    "iso:country":"AU",
    "sg:address":"48 New St",
    "sg:city":"Ringwood",
    "sg:classifiers":[
        {
            "category":"Retail",
            "subcategory":"Auto Repair",
            "type":"Services"
        }
    ],
    "sg:phone":"+61 3 9879 3377",
    "sg:postcode":"3134",
    "sg:province":"VIC",
    "sg:tags":[
        "beater",
        "painter",
        "panel"
    ],
    "wof:name":"Ringwood Smash Repairs",
    "wof:placetype":"venue"
},
  "geometry": {"coordinates":[145.220306397,-37.814868927],"type":"Point"}
}