{
  "type": "Feature",
  "properties": {
    "iso:country":"AU",
    "sg:address":"179 Normanby Rd",
    "sg:city":"South Melbourne",
    "sg:classifiers":[
        {
            "category":"Railroad",
            "type":"Transportation"
        }
    ],
    "sg:phone":"+61 3 9233 8888",
    "sg:postcode":"3205",
    "sg:province":"VIC",
    "sg:tags":[
        "equipment",
        "railway",
        "construction",
        "material"
    ],
    "wof:name":"Westinghouse Signals Australia",
    "wof:placetype":"venue"
},
  "geometry": {"coordinates":[144.949738,-37.835861],"type":"Point"}
}