{
  "type": "Feature",
  "properties": {
    "addr:full":"88 Freight Drv Somerton VIC 3062",
    "addr:postcode":"3062",
    "addr:street":"Freight Drv",
    "iso:country":"AU",
    "sg:address":"88 Freight Drv",
    "sg:city":"Somerton",
    "sg:classifiers":[
        {
            "category":"Building & Trades",
            "subcategory":"Construction",
            "type":"Services"
        }
    ],
    "sg:phone":"+61 3 9308 5600",
    "sg:postcode":"3062",
    "sg:province":"VIC",
    "sg:tags":[
        "earth",
        "excavating",
        "moving",
        "contractor"
    ],
    "wof:name":"Cornfoot Brothers Earthmoving Pty Ltd",
    "wof:placetype":"venue"
},
  "geometry": {"coordinates":[144.96330261200001,-37.6379508972],"type":"Point"}
}