{
  "type": "Feature",
  "properties": {
    "iso:country":"AU",
    "sg:address":"4 Valley Drv",
    "sg:city":"Oak Valley",
    "sg:classifiers":[
        {
            "category":"Commercial Area",
            "type":"Public Place"
        }
    ],
    "sg:phone":"+61 7 4778 1923",
    "sg:postcode":"4811",
    "sg:province":"QLD",
    "sg:tags":[
        "heavy",
        "carrier"
    ],
    "wof:name":"Anderson Transport Services (NQ) Pty Ltd",
    "wof:placetype":"venue"
},
  "geometry": {"coordinates":[146.831985,-19.401447],"type":"Point"}
}