{
  "type": "Feature",
  "properties": {
    "addr:full":"24 Somerset Crs Mansfield VIC 3722",
    "addr:housenumber":"24",
    "addr:postcode":"3722",
    "addr:street":"Somerset Crs",
    "iso:country":"AU",
    "sg:address":"24 Somerset Crs",
    "sg:city":"Mansfield",
    "sg:classifiers":[
        {
            "category":"Building & Trades",
            "subcategory":"Construction",
            "type":"Services"
        }
    ],
    "sg:phone":"+61 3 5775 1738",
    "sg:postcode":"3722",
    "sg:province":"VIC",
    "sg:tags":[
        "plasterboard",
        "plasterer",
        "fixer"
    ],
    "wof:name":"Mitch's Plaster Service Pty Ltd",
    "wof:placetype":"venue"
},
  "geometry": {"coordinates":[146.15074157699999,-37.0491905212],"type":"Point"}
}