{
  "type": "Feature",
  "properties": {
    "addr:full":"38 Meriel St Sans Souci NSW 2219",
    "addr:housenumber":"38",
    "addr:postcode":"2219",
    "addr:street":"Meriel St",
    "iso:country":"AU",
    "sg:address":"38 Meriel St",
    "sg:city":"Sans Souci",
    "sg:classifiers":[
        {
            "category":"Health Services",
            "subcategory":"Health Practitioner",
            "type":"Services"
        }
    ],
    "sg:phone":"+61 2 9529 4228",
    "sg:postcode":"2219",
    "sg:province":"NSW",
    "sg:tags":[
        "hypnotherapy"
    ],
    "wof:name":"Achim Schenk",
    "wof:placetype":"venue"
},
  "geometry": {"coordinates":[151.13029499999999,-34.002701],"type":"Point"}
}