{
  "type": "Feature",
  "properties": {
    "addr:full":"4 Pine St Rydalmere NSW 2116",
    "addr:housenumber":"4",
    "addr:postcode":"2116",
    "addr:street":"Pine St",
    "iso:country":"AU",
    "sg:address":"4 Pine St",
    "sg:city":"Rydalmere",
    "sg:classifiers":[
        {
            "category":"Utilities",
            "type":"Services"
        }
    ],
    "sg:phone":"+61 2 9214 1144",
    "sg:postcode":"2116",
    "sg:province":"NSW",
    "sg:tags":[
        "refrigeration",
        "industrial",
        "commercial",
        "retail"
    ],
    "wof:name":"Cold-Rite Refrigeration & Air Conditioning Pty Ltd",
    "wof:placetype":"venue"
},
  "geometry": {"coordinates":[151.04905700699999,-33.8124504089],"type":"Point"}
}