{
  "type": "Feature",
  "properties": {
    "addr:full":"38- 42 Gaine Rd Dandenong South VIC 3175",
    "addr:housenumber":"42",
    "addr:postcode":"3175",
    "addr:street":"Gaine Rd",
    "iso:country":"AU",
    "sg:address":"38- 42 Gaine Rd",
    "sg:city":"Dandenong South",
    "sg:classifiers":[
        {
            "category":"Manufacturing",
            "subcategory":"Electronics",
            "type":"Manufacturing & Wholesale Goods"
        }
    ],
    "sg:phone":"+61 3 8787 4747",
    "sg:postcode":"3175",
    "sg:province":"VIC",
    "sg:tags":[
        "wholesaler",
        "equipment",
        "part",
        "mfrs",
        "refrigeration"
    ],
    "wof:name":"Williams Refrigeration Australia Pty Ltd",
    "wof:placetype":"venue"
},
  "geometry": {"coordinates":[145.24079895,-38.0331993103],"type":"Point"}
}