{
  "type": "Feature",
  "properties": {
    "iso:country":"AU",
    "sg:address":"15 Kerria Rd",
    "sg:city":"Risdon Vale",
    "sg:classifiers":[
        {
            "category":"Retail",
            "subcategory":"Auto Repair",
            "type":"Services"
        }
    ],
    "sg:phone":"+61 3 6243 7831",
    "sg:postcode":"7016",
    "sg:province":"TAS",
    "sg:tags":[
        "clutch",
        "brake"
    ],
    "wof:name":"Graves Auto Repairs",
    "wof:placetype":"venue"
},
  "geometry": {"coordinates":[147.34735107399999,-42.8097305298],"type":"Point"}
}