{
  "type": "Feature",
  "properties": {
    "addr:full":"55 George St Parramatta NSW 2150",
    "addr:housenumber":"55",
    "addr:postcode":"2150",
    "addr:street":"George St",
    "iso:country":"AU",
    "sg:address":"55 George St",
    "sg:city":"Parramatta",
    "sg:classifiers":[
        {
            "category":"Shopping",
            "subcategory":"Computers & Home Electronics",
            "type":"Retail Goods"
        }
    ],
    "sg:phone":"+61 2 9898 3433",
    "sg:postcode":"2150",
    "sg:province":"NSW",
    "sg:tags":[
        "equipment",
        "supply"
    ],
    "wof:name":"John Maggs Computer Supplies",
    "wof:placetype":"venue"
},
  "geometry": {"coordinates":[151.01885986299999,-33.8317871094],"type":"Point"}
}