{
  "type": "Feature",
  "properties": {
    "addr:full":"Unit 2/ 115-119 Parkes St Helensburgh NSW 2508",
    "addr:housenumber":"/ 115-119",
    "addr:postcode":"2508",
    "addr:street":"Parkes St",
    "iso:country":"AU",
    "sg:address":"Unit 2/ 115-119 Parkes St",
    "sg:city":"Helensburgh",
    "sg:classifiers":[
        {
            "category":"Retail",
            "subcategory":"Auto Repair",
            "type":"Services"
        }
    ],
    "sg:phone":"+61 2 4294 3885",
    "sg:postcode":"2508",
    "sg:province":"NSW",
    "sg:tags":[
        "electrical"
    ],
    "wof:name":"Mobile Sparks",
    "wof:placetype":"venue"
},
  "geometry": {"coordinates":[150.98262,-34.190586],"type":"Point"}
}