{
  "type": "Feature",
  "properties": {
    "iso:country":"AU",
    "sg:address":"1111 Howitt St",
    "sg:city":"Ballarat",
    "sg:classifiers":[
        {
            "category":"Health Services",
            "subcategory":"Doctor",
            "type":"Services"
        }
    ],
    "sg:phone":"+61 3 5339 3366",
    "sg:postcode":"3350",
    "sg:province":"VIC",
    "sg:tags":[
        "podiatrist"
    ],
    "wof:name":"Chris Vaughan",
    "wof:placetype":"venue"
},
  "geometry": {"coordinates":[143.83284,-37.540577],"type":"Point"}
}