{
  "type": "Feature",
  "properties": {
    "addr:full":"38 Province St Abbotsbury NSW 2176",
    "addr:housenumber":"38",
    "addr:postcode":"2176",
    "addr:street":"Province St",
    "iso:country":"AU",
    "sg:address":"38 Province St",
    "sg:city":"Abbotsbury",
    "sg:classifiers":[
        {
            "category":"Building & Trades",
            "subcategory":"Construction",
            "type":"Services"
        }
    ],
    "sg:phone":"+61 2 9610 5296",
    "sg:postcode":"2176",
    "sg:province":"NSW",
    "sg:tags":[
        "contractor"
    ],
    "wof:name":"Cav Homes Pty Ltd",
    "wof:placetype":"venue"
},
  "geometry": {"coordinates":[150.86184692399999,-33.871673584],"type":"Point"}
}