{
  "type": "Feature",
  "properties": {
    "iso:country":"AU",
    "sg:address":"Level 1 Crown Tower 200 Crown St",
    "sg:city":"Wollongong",
    "sg:classifiers":[
        {
            "category":"Health Services",
            "subcategory":"Doctor",
            "type":"Services"
        }
    ],
    "sg:phone":"+61 2 4229 8688",
    "sg:postcode":"2500",
    "sg:province":"NSW",
    "sg:tags":[
        "occupational",
        "safety"
    ],
    "wof:name":"Konekt Australia Pty Ltd",
    "wof:placetype":"venue"
},
  "geometry": {"coordinates":[150.871735,-34.425396],"type":"Point"}
}