{
  "type": "Feature",
  "properties": {
    "iso:country":"AU",
    "sg:address":"Ferry St",
    "sg:city":"Kangaroo Point",
    "sg:classifiers":[
        {
            "category":"Restaurant",
            "type":"Food & Drink"
        }
    ],
    "sg:phone":"+61 7 3262 7308",
    "sg:postcode":"4169",
    "sg:province":"QLD",
    "wof:name":"Comedy Dockside Bar",
    "wof:placetype":"venue"
},
  "geometry": {"coordinates":[153.037353516,-27.4724178314],"type":"Point"}
}