{
  "type": "Feature",
  "properties": {
    "iso:country":"AU",
    "sg:address":"9 Main St",
    "sg:city":"Eildon",
    "sg:classifiers":[
        {
            "category":"Food & Beverages",
            "subcategory":"Bakery",
            "type":"Retail Goods"
        }
    ],
    "sg:phone":"+61 3 5774 2362",
    "sg:postcode":"3713",
    "sg:province":"VIC",
    "sg:tags":[
        "baker"
    ],
    "wof:name":"Eildon Bakery",
    "wof:placetype":"venue"
},
  "geometry": {"coordinates":[145.909057617,-37.2332763672],"type":"Point"}
}