{
  "type": "Feature",
  "properties": {
    "addr:full":"182 Logan Rd Woolloongabba QLD 4102",
    "addr:housenumber":"182",
    "addr:postcode":"4102",
    "addr:street":"Logan Rd",
    "iso:country":"AU",
    "sg:address":"182 Logan Rd",
    "sg:city":"Woolloongabba",
    "sg:classifiers":[
        {
            "category":"Shopping",
            "subcategory":"Stationery & Office Supplies",
            "type":"Retail Goods"
        }
    ],
    "sg:phone":"+61 7 3891 6036",
    "sg:postcode":"4102",
    "sg:province":"QLD",
    "sg:tags":[
        "equipment",
        "display",
        "exhibition"
    ],
    "wof:name":"Adaptable Displays",
    "wof:placetype":"venue"
},
  "geometry": {"coordinates":[153.04153442399999,-27.4944267273],"type":"Point"}
}