{
  "type": "Feature",
  "properties": {
    "iso:country":"AU",
    "sg:address":"81 Kalinda Rd",
    "sg:city":"Ringwood North",
    "sg:classifiers":[
        {
            "category":"Building & Trades",
            "subcategory":"Construction",
            "type":"Services"
        }
    ],
    "sg:phone":"+61 3 9876 7676",
    "sg:postcode":"3134",
    "sg:province":"VIC",
    "sg:tags":[
        "spouting",
        "guttering"
    ],
    "wof:name":"Leaves Gutters Clear",
    "wof:placetype":"venue"
},
  "geometry": {"coordinates":[145.255325317,-37.7857894897],"type":"Point"}
}