{
  "type": "Feature",
  "properties": {
    "addr:full":"4/24 McLean St Bundaberg QLD 4670",
    "addr:housenumber":"/ 24",
    "addr:postcode":"4670",
    "addr:street":"Mclean St",
    "iso:country":"AU",
    "sg:address":"4/24 McLean St",
    "sg:city":"Bundaberg",
    "sg:classifiers":[
        {
            "category":"Arena",
            "subcategory":"Sports Club",
            "type":"Entertainment"
        }
    ],
    "sg:phone":"+61 7 4151 7258",
    "sg:postcode":"4670",
    "sg:province":"QLD",
    "sg:tags":[
        "defence",
        "supply",
        "self",
        "instruction",
        "martial art"
    ],
    "wof:name":"Vipers Martial Arts",
    "wof:placetype":"venue"
},
  "geometry": {"coordinates":[152.347259522,-24.8732566833],"type":"Point"}
}