{
  "type": "Feature",
  "properties": {
    "addr:full":"721 Canterbury Rd Surrey Hills VIC 3127",
    "addr:housenumber":"721",
    "addr:postcode":"3127",
    "addr:street":"Canterbury Rd",
    "iso:country":"AU",
    "sg:address":"721 Canterbury Rd",
    "sg:city":"Surrey Hills",
    "sg:classifiers":[
        {
            "category":"Health Services",
            "subcategory":"Health Practitioner",
            "type":"Services"
        }
    ],
    "sg:phone":"+61 3 9899 2598",
    "sg:postcode":"3127",
    "sg:province":"VIC",
    "sg:tags":[
        "alternative"
    ],
    "wof:name":"Professor Wang's Chinese Natural Healing",
    "wof:placetype":"venue"
},
  "geometry": {"coordinates":[145.10504150400001,-37.8266792297],"type":"Point"}
}