{
  "type": "Feature",
  "properties": {
    "addr:full":"Jondel Stud M/S 861 Willowbank QLD 4306",
    "addr:housenumber":"861",
    "addr:postcode":"4306",
    "addr:street":"Willowbank",
    "iso:country":"AU",
    "sg:address":"Jondel Stud M/S 861",
    "sg:city":"Willowbank",
    "sg:classifiers":[
        {
            "category":"Farming",
            "subcategory":"Livestock Farm",
            "type":"Manufacturing & Wholesale Goods"
        }
    ],
    "sg:phone":"+61 7 5467 3321",
    "sg:postcode":"4306",
    "sg:province":"QLD",
    "sg:tags":[
        "breeder",
        "horse",
        "stud"
    ],
    "wof:name":"Bauer J V & A R",
    "wof:placetype":"venue"
},
  "geometry": {"coordinates":[152.69374084500001,-27.6609802246],"type":"Point"}
}