{
  "type": "Feature",
  "properties": {
    "addr:full":"18 Hopfields Rd Margate TAS 7054",
    "addr:housenumber":"18",
    "addr:postcode":"7054",
    "addr:street":"Hopfields Rd",
    "iso:country":"AU",
    "sg:address":"18 Hopfields Rd",
    "sg:city":"Margate",
    "sg:classifiers":[
        {
            "category":"Building & Trades",
            "subcategory":"Pest Control",
            "type":"Services"
        }
    ],
    "sg:phone":"+61 3 6267 1880",
    "sg:postcode":"7054",
    "sg:province":"TAS",
    "wof:name":"Walker Paul",
    "wof:placetype":"venue"
},
  "geometry": {"coordinates":[147.25921600000001,-43.020412],"type":"Point"}
}