{
  "type": "Feature",
  "properties": {
    "addr:full":"25 McKenzie Crs Hoppers Crossing VIC 3029",
    "addr:housenumber":"25",
    "addr:postcode":"3029",
    "addr:street":"Mckenzie Crs",
    "iso:country":"AU",
    "sg:address":"25 McKenzie Crs",
    "sg:city":"Hoppers Crossing",
    "sg:classifiers":[
        {
            "category":"Communications",
            "type":"Services"
        }
    ],
    "sg:phone":"+61 3 9748 7751",
    "sg:postcode":"3029",
    "sg:province":"VIC",
    "sg:tags":[
        "translation"
    ],
    "wof:name":"David Deck",
    "wof:placetype":"venue"
},
  "geometry": {"coordinates":[144.674103,-37.874302],"type":"Point"}
}