{
  "type": "Feature",
  "properties": {
    "iso:country":"AU",
    "sg:address":"42 Hattersley St",
    "sg:city":"Arncliffe",
    "sg:classifiers":[
        {
            "category":"Home & Garden",
            "subcategory":"Household Appliances",
            "type":"Retail Goods"
        }
    ],
    "sg:phone":"+61 2 9599 1759",
    "sg:postcode":"2205",
    "sg:province":"NSW",
    "sg:tags":[
        "heating",
        "system"
    ],
    "wof:name":"T & D Engineering",
    "wof:placetype":"venue"
},
  "geometry": {"coordinates":[151.14224200000001,-33.943134],"type":"Point"}
}