{
  "type": "Feature",
  "properties": {
    "addr:full":"16 Browning St Portland VIC 3305",
    "addr:housenumber":"16",
    "addr:postcode":"3305",
    "addr:street":"Browning St",
    "iso:country":"AU",
    "sg:address":"16 Browning St",
    "sg:city":"Portland",
    "sg:classifiers":[
        {
            "category":"Fast Food",
            "type":"Food & Drink"
        }
    ],
    "sg:phone":"+61 3 5523 6326",
    "sg:postcode":"3305",
    "sg:province":"VIC",
    "sg:tags":[
        "away",
        "take"
    ],
    "wof:name":"Jofflyn's Take Away Food",
    "wof:placetype":"venue"
},
  "geometry": {"coordinates":[141.59257507300001,-38.3395996094],"type":"Point"}
}