{
  "type": "Feature",
  "properties": {
    "iso:country":"AU",
    "sg:address":"91 Crowe St",
    "sg:city":"Mt Gravatt",
    "sg:classifiers":[
        {
            "category":"Social Services",
            "subcategory":"Retirement Home",
            "type":"Services"
        }
    ],
    "sg:phone":"+61 7 3422 1032",
    "sg:postcode":"4122",
    "sg:province":"QLD",
    "sg:tags":[
        "decoration",
        "supplier",
        "contractor"
    ],
    "wof:name":"Captivating Moments.",
    "wof:placetype":"venue"
},
  "geometry": {"coordinates":[153.072723389,-27.5303192139],"type":"Point"}
}