{
  "type": "Feature",
  "properties": {
    "iso:country":"AU",
    "sg:address":"6 Drummond St",
    "sg:city":"Redcliffe",
    "sg:classifiers":[
        {
            "category":"Health Services",
            "subcategory":"Nursing And Care Facility",
            "type":"Services"
        }
    ],
    "sg:phone":"+61 8 9262 9100",
    "sg:postcode":"6104",
    "sg:province":"WA",
    "sg:tags":[
        "home"
    ],
    "wof:name":"Aegis - Parkview Aged Care",
    "wof:placetype":"venue"
},
  "geometry": {"coordinates":[115.941551209,-31.938627243],"type":"Point"}
}