{
  "type": "Feature",
  "properties": {
    "addr:full":"60 King William St Kent Town SA 5067",
    "addr:housenumber":"60",
    "addr:postcode":"5067",
    "addr:street":"King William St",
    "iso:country":"AU",
    "sg:address":"60 King William St",
    "sg:city":"Kent Town",
    "sg:classifiers":[
        {
            "category":"Fast Food",
            "type":"Food & Drink"
        }
    ],
    "sg:phone":"+61 8 8362 8001",
    "sg:postcode":"5067",
    "sg:province":"SA",
    "sg:tags":[
        "away",
        "take"
    ],
    "wof:name":"Full On Aces Snack Bar",
    "wof:placetype":"venue"
},
  "geometry": {"coordinates":[138.618896484,-34.9190864563],"type":"Point"}
}