{
  "type": "Feature",
  "properties": {
    "addr:full":"164 Stanley St Townsville QLD 4810",
    "addr:housenumber":"164",
    "addr:postcode":"4810",
    "addr:street":"Stanley St",
    "iso:country":"AU",
    "sg:address":"164 Stanley St",
    "sg:city":"Townsville",
    "sg:classifiers":[
        {
            "category":"Insurance",
            "subcategory":"Title Insurance",
            "type":"Services"
        }
    ],
    "sg:phone":"+61 1300 305 205",
    "sg:postcode":"4810",
    "sg:province":"QLD",
    "sg:tags":[
        "searcher"
    ],
    "wof:name":"Legalco.",
    "wof:placetype":"venue"
},
  "geometry": {"coordinates":[146.81440699999999,-19.260542],"type":"Point"}
}