{
  "type": "Feature",
  "properties": {
    "iso:country":"AU",
    "sg:address":"3056 Albany Hwy",
    "sg:city":"Armadale",
    "sg:classifiers":[
        {
            "category":"Health Services",
            "subcategory":"Doctor",
            "type":"Services"
        }
    ],
    "sg:phone":"+61 8 9391 2912",
    "sg:postcode":"6112",
    "sg:province":"WA",
    "sg:tags":[
        "medical",
        "practitioner"
    ],
    "wof:name":"Jayasundera, Mohan Mr",
    "wof:placetype":"venue"
},
  "geometry": {"coordinates":[116.017753601,-32.1389656067],"type":"Point"}
}