{
  "type": "Feature",
  "properties": {
    "addr:full":"Shed 7 Block O Brisbane Markets Sherwood Rd Rocklea QLD 4106",
    "addr:housenumber":"7 block o",
    "addr:postcode":"4106",
    "addr:street":"Sherwood Rd",
    "iso:country":"AU",
    "sg:address":"Shed 7 Block O Brisbane Markets Sherwood Rd",
    "sg:city":"Rocklea",
    "sg:classifiers":[
        {
            "category":"Professional",
            "subcategory":"Business Services",
            "type":"Services"
        }
    ],
    "sg:phone":"+61 413 738 811",
    "sg:postcode":"4106",
    "sg:province":"QLD",
    "sg:tags":[
        "exporter"
    ],
    "wof:name":"Bunning's Fresh Australasian Food Pty Ltd",
    "wof:placetype":"venue"
},
  "geometry": {"coordinates":[153.01252746599999,-27.5415802002],"type":"Point"}
}