{
  "type": "Feature",
  "properties": {
    "addr:full":"3 Bridge St Granville NSW 2142",
    "addr:housenumber":"3",
    "addr:postcode":"2142",
    "addr:street":"Bridge St",
    "iso:country":"AU",
    "sg:address":"3 Bridge St",
    "sg:city":"Granville",
    "sg:classifiers":[
        {
            "category":"Organizations",
            "subcategory":"Professional Association",
            "type":"Services"
        }
    ],
    "sg:phone":"+61 2 9682 7788",
    "sg:postcode":"2142",
    "sg:province":"NSW",
    "sg:tags":[
        "organisation",
        "business"
    ],
    "wof:name":"Commercial Travellers Guild",
    "wof:placetype":"venue"
},
  "geometry": {"coordinates":[151.012329102,-33.8324394226],"type":"Point"}
}