{
  "type": "Feature",
  "properties": {
    "iso:country":"AU",
    "sg:address":"19 Louis St",
    "sg:city":"Stepney",
    "sg:classifiers":[
        {
            "category":"Professional",
            "type":"Services"
        }
    ],
    "sg:phone":"+61 8 8362 2185",
    "sg:postcode":"5069",
    "sg:province":"SA",
    "sg:tags":[
        "coating",
        "powder"
    ],
    "wof:name":"F R Payne & Son",
    "wof:placetype":"venue"
},
  "geometry": {"coordinates":[138.630371094,-34.9144210815],"type":"Point"}
}