{
  "type": "Feature",
  "properties": {
    "addr:full":"13 Lyrebird Drv Carrum Downs VIC 3201",
    "addr:housenumber":"13",
    "addr:postcode":"3201",
    "addr:street":"Lyrebird Drv",
    "iso:country":"AU",
    "sg:address":"13 Lyrebird Drv",
    "sg:city":"Carrum Downs",
    "sg:classifiers":[
        {
            "category":"Government",
            "subcategory":"Fire Station",
            "type":"Public Place"
        }
    ],
    "sg:phone":"+61 3 9766 9665",
    "sg:postcode":"3201",
    "sg:province":"VIC",
    "sg:tags":[
        "equipment",
        "protection",
        "consultant"
    ],
    "sg:website":"http://www.assetfiresystems.com.au",
    "wof:name":"Asset Fire Systems Pty Ltd",
    "wof:placetype":"venue"
},
  "geometry": {"coordinates":[145.169678,-38.113033],"type":"Point"}
}