{
  "type": "Feature",
  "properties": {
    "addr:full":"Suite 3 / 75 Johson St Byron Bay NSW 2481",
    "addr:postcode":"2481",
    "addr:street":"75 Johson St",
    "iso:country":"AU",
    "sg:address":"Suite 3 / 75 Johson St",
    "sg:city":"Byron Bay",
    "sg:classifiers":[
        {
            "category":"Health Services",
            "subcategory":"Health Practitioner",
            "type":"Services"
        }
    ],
    "sg:phone":"+61 2 6685 5056",
    "sg:postcode":"2481",
    "sg:province":"NSW",
    "sg:tags":[
        "hypnotherapy"
    ],
    "wof:name":"Hypnotix",
    "wof:placetype":"venue"
},
  "geometry": {"coordinates":[153.61286926299999,-28.6482620239],"type":"Point"}
}