{
  "type": "Feature",
  "properties": {
    "iso:country":"AU",
    "sg:address":"37 Granadilla Drv",
    "sg:city":"Earlville",
    "sg:classifiers":[
        {
            "category":"Manufacturing",
            "subcategory":"Petroleum Products",
            "type":"Manufacturing & Wholesale Goods"
        }
    ],
    "sg:phone":"+61 408 774 767",
    "sg:postcode":"4870",
    "sg:province":"QLD",
    "sg:tags":[
        "fuel",
        "oil",
        "additive"
    ],
    "wof:name":"Fuel Solutions (FNQ)",
    "wof:placetype":"venue"
},
  "geometry": {"coordinates":[145.73106384299999,-16.9511909485],"type":"Point"}
}