{
  "type": "Feature",
  "properties": {
    "addr:full":"32a Hardy St Lilydale VIC 3140",
    "addr:housenumber":"32a",
    "addr:postcode":"3140",
    "addr:street":"Hardy St",
    "iso:country":"AU",
    "sg:address":"32a Hardy St",
    "sg:city":"Lilydale",
    "sg:classifiers":[
        {
            "category":"Personal",
            "subcategory":"Massage",
            "type":"Services"
        }
    ],
    "sg:phone":"+61 3 9735 2033",
    "sg:postcode":"3140",
    "sg:province":"VIC",
    "sg:tags":[
        "therapy"
    ],
    "wof:name":"Lilydale & Yarra Valley Acupuncture & Massage",
    "wof:placetype":"venue"
},
  "geometry": {"coordinates":[145.35168457,-37.7588310242],"type":"Point"}
}