{
  "type": "Feature",
  "properties": {
    "addr:full":"21 Harriet St Horsham VIC 3400",
    "addr:housenumber":"21",
    "addr:postcode":"3400",
    "addr:street":"Harriet St",
    "iso:country":"AU",
    "sg:address":"21 Harriet St",
    "sg:city":"Horsham",
    "sg:classifiers":[
        {
            "category":"Professional",
            "subcategory":"Detective & Security Services",
            "type":"Services"
        }
    ],
    "sg:phone":"+61 3 5382 1514",
    "sg:postcode":"3400",
    "sg:province":"VIC",
    "sg:tags":[
        "consultant",
        "system"
    ],
    "wof:name":"Cec. Hopper & Sons",
    "wof:placetype":"venue"
},
  "geometry": {"coordinates":[142.204544067,-36.7088432312],"type":"Point"}
}