{
  "type": "Feature",
  "properties": {
    "iso:country":"AU",
    "sg:address":"PO Box 3111",
    "sg:city":"Shelley",
    "sg:classifiers":[
        {
            "category":"Personal",
            "subcategory":"Skin Care",
            "type":"Services"
        }
    ],
    "sg:phone":"+61 8 9259 6456",
    "sg:postcode":"6148",
    "sg:province":"WA",
    "sg:tags":[
        "treatment"
    ],
    "wof:name":"The Light Touch Clinic",
    "wof:placetype":"venue"
},
  "geometry": {"coordinates":[115.881927,-32.034382],"type":"Point"}
}