{
  "type": "Feature",
  "properties": {
    "addr:full":"455 Varley St Yorkeys Knob QLD 4878",
    "addr:housenumber":"455",
    "addr:postcode":"4878",
    "addr:street":"Varley St",
    "iso:country":"AU",
    "sg:address":"455 Varley St",
    "sg:city":"Yorkeys Knob",
    "sg:classifiers":[
        {
            "category":"Real Estate",
            "subcategory":"Real Estate Agent",
            "type":"Services"
        }
    ],
    "sg:phone":"+61 7 4081 0810",
    "sg:postcode":"4878",
    "sg:province":"QLD",
    "wof:name":"Harcourts Cairns Beaches (Yorkeys Knob)",
    "wof:placetype":"venue"
},
  "geometry": {"coordinates":[145.720703125,-16.8115997314],"type":"Point"}
}