{
  "type": "Feature",
  "properties": {
    "iso:country":"AU",
    "sg:address":"Unit 1 2 Phipps Pl",
    "sg:city":"Deakin",
    "sg:classifiers":[
        {
            "category":"Arena",
            "subcategory":"Sports Club",
            "type":"Entertainment"
        }
    ],
    "sg:phone":"+61 2 6281 1303",
    "sg:postcode":"2600",
    "sg:province":"ACT",
    "sg:tags":[
        "organisation",
        "sporting"
    ],
    "wof:name":"Pistol Australia Inc",
    "wof:placetype":"venue"
},
  "geometry": {"coordinates":[149.09536743199999,-35.326084137],"type":"Point"}
}