{
  "type": "Feature",
  "properties": {
    "addr:full":"PO Box 381 Toukley NSW 2263",
    "addr:postcode":"2263",
    "iso:country":"AU",
    "sg:address":"PO Box 381",
    "sg:city":"Toukley",
    "sg:classifiers":[
        {
            "category":"Shopping",
            "subcategory":"Musical Instruments",
            "type":"Retail Goods"
        }
    ],
    "sg:phone":"+61 2 4392 1322",
    "sg:postcode":"2263",
    "sg:province":"NSW",
    "sg:tags":[
        "musician",
        "agent"
    ],
    "wof:name":"Amelia Skinner-Flute Plus",
    "wof:placetype":"venue"
},
  "geometry": {"coordinates":[151.542877,-33.26408],"type":"Point"}
}