{
  "type": "Feature",
  "properties": {
    "addr:full":"25/ 22 Hudson Ave Castle Hill NSW 2154",
    "addr:housenumber":"25 / 22",
    "addr:postcode":"2154",
    "addr:street":"Hudson Ave",
    "iso:country":"AU",
    "sg:address":"25/ 22 Hudson Ave",
    "sg:city":"Castle Hill",
    "sg:classifiers":[
        {
            "category":"Building & Trades",
            "subcategory":"Construction",
            "type":"Services"
        }
    ],
    "sg:phone":"+61 2 9659 0754",
    "sg:postcode":"2154",
    "sg:province":"NSW",
    "sg:tags":[
        "fencing",
        "contractor"
    ],
    "wof:name":"Fence Factory Hills District",
    "wof:placetype":"venue"
},
  "geometry": {"coordinates":[150.97456359899999,-33.7289047241],"type":"Point"}
}