{
  "type": "Feature",
  "properties": {
    "addr:full":"133 Queen St Cleveland QLD 4163",
    "addr:housenumber":"133",
    "addr:postcode":"4163",
    "addr:street":"Queen St",
    "iso:country":"AU",
    "sg:address":"133 Queen St",
    "sg:city":"Cleveland",
    "sg:classifiers":[
        {
            "category":"Social Services",
            "subcategory":"Retirement Home",
            "type":"Services"
        }
    ],
    "sg:phone":"+61 7 3286 3000",
    "sg:postcode":"4163",
    "sg:province":"QLD",
    "sg:tags":[
        "village"
    ],
    "wof:name":"The Manor Group",
    "wof:placetype":"venue"
},
  "geometry": {"coordinates":[153.26661682100001,-27.5280647278],"type":"Point"}
}