{
  "type": "Feature",
  "properties": {
    "addr:full":"Toddler Kindy GymbaROO 142 Cotham Rd Kew VIC 3101",
    "addr:housenumber":"142",
    "addr:postcode":"3101",
    "addr:street":"Cotham Rd",
    "iso:country":"AU",
    "sg:address":"Toddler Kindy GymbaROO 142 Cotham Rd",
    "sg:city":"Kew",
    "sg:classifiers":[
        {
            "category":"Recreation",
            "type":"Entertainment"
        }
    ],
    "sg:phone":"+61 3 9850 9910",
    "sg:postcode":"3101",
    "sg:province":"VIC",
    "sg:tags":[
        "children's",
        "play",
        "programme"
    ],
    "wof:name":"GymbaROO",
    "wof:placetype":"venue"
},
  "geometry": {"coordinates":[145.03924560600001,-37.8079452515],"type":"Point"}
}