{
  "type": "Feature",
  "properties": {
    "addr:full":"105 High St Northcote VIC 3070",
    "addr:housenumber":"105",
    "addr:postcode":"3070",
    "addr:street":"High St",
    "iso:country":"AU",
    "sg:address":"105 High St",
    "sg:city":"Northcote",
    "sg:classifiers":[
        {
            "category":"Cafe",
            "type":"Food & Drink"
        }
    ],
    "sg:phone":"+61 3 9482 3999",
    "sg:postcode":"3070",
    "sg:province":"VIC",
    "wof:name":"Silly Yaks Bakery Cafe",
    "wof:placetype":"venue"
},
  "geometry": {"coordinates":[144.99681100000001,-37.779488],"type":"Point"}
}