{
  "type": "Feature",
  "properties": {
    "iso:country":"AU",
    "sg:address":"246 Hoxton Park Rd",
    "sg:city":"Lurnea",
    "sg:classifiers":[
        {
            "category":"Manufacturing",
            "subcategory":"Rubber & Plastics",
            "type":"Manufacturing & Wholesale Goods"
        }
    ],
    "sg:phone":"+61 2 9826 7304",
    "sg:postcode":"2170",
    "sg:province":"NSW",
    "sg:tags":[
        "moulders"
    ],
    "wof:name":"Jalco Plastics Pty Ltd",
    "wof:placetype":"venue"
},
  "geometry": {"coordinates":[150.905059814,-33.9273490906],"type":"Point"}
}