{
  "type": "Feature",
  "properties": {
    "iso:country":"AU",
    "sg:address":"10 Gordon St",
    "sg:city":"Armidale",
    "sg:classifiers":[
        {
            "category":"Education",
            "subcategory":"School",
            "type":"Public Place"
        }
    ],
    "sg:phone":"+61 2 6772 6873",
    "sg:postcode":"2350",
    "sg:province":"NSW",
    "sg:tags":[
        "supply"
    ],
    "wof:name":"One Stop Educational Supplies",
    "wof:placetype":"venue"
},
  "geometry": {"coordinates":[151.67831420900001,-30.4955387115],"type":"Point"}
}