{
  "type": "Feature",
  "properties": {
    "iso:country":"AU",
    "sg:address":"235 South Rd",
    "sg:city":"Croydon",
    "sg:classifiers":[
        {
            "category":"Fast Food",
            "type":"Food & Drink"
        }
    ],
    "sg:phone":"+61 8 8340 7966",
    "sg:postcode":"5008",
    "sg:province":"SA",
    "sg:tags":[
        "away",
        "take"
    ],
    "wof:name":"Subway",
    "wof:placetype":"venue"
},
  "geometry": {"coordinates":[138.569794,-34.889931],"type":"Point"}
}