{
  "type": "Feature",
  "properties": {
    "addr:full":"84 Beatrice St Balgowlah NSW 2093",
    "addr:housenumber":"84",
    "addr:postcode":"2093",
    "addr:street":"Beatrice St",
    "iso:country":"AU",
    "sg:address":"84 Beatrice St",
    "sg:city":"Balgowlah",
    "sg:classifiers":[
        {
            "category":"Professional",
            "subcategory":"Art Services",
            "type":"Services"
        }
    ],
    "sg:phone":"+61 411 722 448",
    "sg:postcode":"2093",
    "sg:province":"NSW",
    "sg:tags":[
        "decorator",
        "painter"
    ],
    "wof:name":"Morton Stephen P",
    "wof:placetype":"venue"
},
  "geometry": {"coordinates":[151.256881714,-33.8022880554],"type":"Point"}
}