{
  "type": "Feature",
  "properties": {
    "addr:full":"Shop 10 Katherine Oasis Shpng Cntr Katherine NT 0850",
    "addr:housenumber":"shop 10",
    "addr:postcode":"nt 0850",
    "addr:street":"Katherine Oasis Shpng Cntr",
    "iso:country":"AU",
    "sg:address":"Shop 10",
    "sg:city":"Katherine Oasis Shpng Cntr Katherine",
    "sg:classifiers":[
        {
            "category":"Education",
            "subcategory":"School",
            "type":"Public Place"
        }
    ],
    "sg:phone":"+61 8 8972 2530",
    "sg:postcode":"0850",
    "sg:province":"NT",
    "sg:tags":[
        "supply"
    ],
    "wof:name":"Katherine Books",
    "wof:placetype":"venue"
},
  "geometry": {"coordinates":[132.264633,-14.466663],"type":"Point"}
}