{
  "type": "Feature",
  "properties": {
    "addr:full":"17 Prospect Rd Bendigo VIC 3550",
    "addr:housenumber":"17",
    "addr:postcode":"3550",
    "addr:street":"Prospect Rd",
    "iso:country":"AU",
    "sg:address":"17 Prospect Rd",
    "sg:city":"Bendigo",
    "sg:classifiers":[
        {
            "category":"Home & Garden",
            "subcategory":"Hardware",
            "type":"Retail Goods"
        }
    ],
    "sg:phone":"+61 3 5441 1022",
    "sg:postcode":"3550",
    "sg:province":"VIC",
    "sg:tags":[
        "compressor",
        "air"
    ],
    "wof:name":"Calair Pipe Systems (NVIC)",
    "wof:placetype":"venue"
},
  "geometry": {"coordinates":[144.313186645,-36.7428016663],"type":"Point"}
}