{
  "type": "Feature",
  "properties": {
    "addr:full":"40 White St Kilmore VIC 3764",
    "addr:housenumber":"40",
    "addr:postcode":"3764",
    "addr:street":"White St",
    "iso:country":"AU",
    "sg:address":"40 White St",
    "sg:city":"Kilmore",
    "sg:classifiers":[
        {
            "category":"Education",
            "subcategory":"School",
            "type":"Public Place"
        }
    ],
    "sg:phone":"+61 3 5782 2211",
    "sg:postcode":"3764",
    "sg:province":"VIC",
    "wof:name":"Kilmore International School The",
    "wof:placetype":"venue"
},
  "geometry": {"coordinates":[144.952926636,-37.3010215759],"type":"Point"}
}