{
  "type": "Feature",
  "properties": {
    "iso:country":"AU",
    "sg:address":"21 Rodgers St",
    "sg:city":"Yarram",
    "sg:classifiers":[
        {
            "category":"Farming",
            "subcategory":"Dairy Farm",
            "type":"Manufacturing & Wholesale Goods"
        }
    ],
    "sg:phone":"+61 3 5182 5392",
    "sg:postcode":"3971",
    "sg:province":"VIC",
    "wof:name":"Cloverlea Dairy",
    "wof:placetype":"venue"
},
  "geometry": {"coordinates":[146.675125122,-38.5611572266],"type":"Point"}
}