{
  "type": "Feature",
  "properties": {
    "iso:country":"AU",
    "sg:address":"214 Clarence St",
    "sg:city":"Howrah",
    "sg:classifiers":[
        {
            "category":"Health Services",
            "subcategory":"Doctor",
            "type":"Services"
        }
    ],
    "sg:phone":"+61 3 6244 1155",
    "sg:postcode":"7018",
    "sg:province":"TAS",
    "sg:tags":[
        "podiatrist"
    ],
    "wof:name":"Julian Hurst",
    "wof:placetype":"venue"
},
  "geometry": {"coordinates":[147.393188477,-42.876991272],"type":"Point"}
}