{
  "type": "Feature",
  "properties": {
    "iso:country":"AU",
    "sg:address":"PO Box 1067",
    "sg:city":"Mt Waverley",
    "sg:classifiers":[
        {
            "category":"Professional",
            "subcategory":"Engineering",
            "type":"Services"
        }
    ],
    "sg:phone":"+61 3 9886 3475",
    "sg:postcode":"3149",
    "sg:province":"VIC",
    "sg:tags":[
        "engineer",
        "toolmaker",
        "plastic"
    ],
    "wof:name":"Plasquip Sales Pty Ltd",
    "wof:placetype":"venue"
},
  "geometry": {"coordinates":[145.12962341299999,-37.88489151],"type":"Point"}
}