{
  "type": "Feature",
  "properties": {
    "addr:full":"Cnr White & Welchman Sts Dubbo NSW 2830",
    "addr:postcode":"2830",
    "addr:street":"Cnr White & Welchman Sts",
    "iso:country":"AU",
    "sg:address":"Cnr White & Welchman Sts",
    "sg:city":"Dubbo",
    "sg:classifiers":[
        {
            "category":"Professional",
            "type":"Services"
        }
    ],
    "sg:phone":"+61 2 6882 2377",
    "sg:postcode":"2830",
    "sg:province":"NSW",
    "sg:tags":[
        "valuer"
    ],
    "wof:name":"Rundles Auctions",
    "wof:placetype":"venue"
},
  "geometry": {"coordinates":[148.62419128400001,-32.2462081909],"type":"Point"}
}