{
  "type": "Feature",
  "properties": {
    "addr:full":"401 Townsend St Albury NSW 2640",
    "addr:housenumber":"401",
    "addr:postcode":"2640",
    "addr:street":"Townsend St",
    "iso:country":"AU",
    "sg:address":"401 Townsend St",
    "sg:city":"Albury",
    "sg:classifiers":[
        {
            "category":"Professional",
            "subcategory":"Accounting & Tax Preparation",
            "type":"Services"
        }
    ],
    "sg:phone":"+61 2 6021 1699",
    "sg:postcode":"2640",
    "sg:province":"NSW",
    "sg:tags":[
        "broom",
        "brush"
    ],
    "wof:name":"Reward Distribution",
    "wof:placetype":"venue"
},
  "geometry": {"coordinates":[146.912872314,-36.0807113647],"type":"Point"}
}