{
  "type": "Feature",
  "properties": {
    "addr:full":"138 King St Clarence Town NSW 2321",
    "addr:housenumber":"138",
    "addr:postcode":"2321",
    "addr:street":"King St",
    "iso:country":"AU",
    "sg:address":"138 King St",
    "sg:city":"Clarence Town",
    "sg:classifiers":[
        {
            "category":"Recreation",
            "subcategory":"Water Park",
            "type":"Entertainment"
        }
    ],
    "sg:phone":"+61 2 4996 4300",
    "sg:postcode":"2321",
    "sg:province":"NSW",
    "sg:tags":[
        "resort",
        "skiing"
    ],
    "wof:name":"Flyin' High Wakeboard & Ski School",
    "wof:placetype":"venue"
},
  "geometry": {"coordinates":[151.78318786599999,-32.5893974304],"type":"Point"}
}