{
  "type": "Feature",
  "properties": {
    "iso:country":"AU",
    "sg:address":"2 Lowe St",
    "sg:city":"Nambour",
    "sg:classifiers":[
        {
            "category":"Shopping",
            "subcategory":"Gifts & Souvenirs",
            "type":"Retail Goods"
        }
    ],
    "sg:phone":"+61 7 5441 7322",
    "sg:postcode":"4560",
    "sg:province":"QLD",
    "sg:tags":[
        "print",
        "poster",
        "pictures"
    ],
    "wof:name":"V.I.P. Picture Framing",
    "wof:placetype":"venue"
},
  "geometry": {"coordinates":[152.960403442,-26.6258125305],"type":"Point"}
}