{
  "type": "Feature",
  "properties": {
    "iso:country":"AU",
    "sg:address":"Brandsmart Shopping Centre Shop T30 286 Whitehorse Rd",
    "sg:city":"Nunawading",
    "sg:classifiers":[
        {
            "category":"Shopping",
            "type":"Retail Goods"
        }
    ],
    "sg:phone":"+61 3 9877 6769",
    "sg:postcode":"3131",
    "sg:province":"VIC",
    "sg:tags":[
        "repair",
        "travel"
    ],
    "wof:name":"Victoria Station Travel Goods & Handbags",
    "wof:placetype":"venue"
},
  "geometry": {"coordinates":[145.171707153,-37.8186531067],"type":"Point"}
}