{
  "type": "Feature",
  "properties": {
    "addr:full":"Unit 5 / 72 Clavering Rd Bayswater WA 6053",
    "addr:housenumber":"72",
    "addr:postcode":"6053",
    "addr:street":"Clavering Rd",
    "iso:country":"AU",
    "sg:address":"Unit 5 / 72 Clavering Rd",
    "sg:city":"Bayswater",
    "sg:classifiers":[
        {
            "category":"Home & Garden",
            "subcategory":"Furniture",
            "type":"Retail Goods"
        }
    ],
    "sg:phone":"+61 8 9370 1233",
    "sg:postcode":"6053",
    "sg:province":"WA",
    "sg:tags":[
        "business"
    ],
    "wof:name":"Office Plus",
    "wof:placetype":"venue"
},
  "geometry": {"coordinates":[115.918067932,-31.9132099152],"type":"Point"}
}