{
  "type": "Feature",
  "properties": {
    "iso:country":"AU",
    "sg:address":"Unit 8 Franklin La",
    "sg:city":"Joondalup",
    "sg:classifiers":[
        {
            "category":"Professional",
            "subcategory":"Employment Agencies",
            "type":"Services"
        }
    ],
    "sg:phone":"+61 1800 682 552",
    "sg:postcode":"6027",
    "sg:province":"WA",
    "sg:tags":[
        "model"
    ],
    "wof:name":"Metro Modelling Academy",
    "wof:placetype":"venue"
},
  "geometry": {"coordinates":[115.762908935,-31.742067337],"type":"Point"}
}