{
  "type": "Feature",
  "properties": {
    "addr:full":"Cnr Vahland & High Rds Willetton WA 6155",
    "addr:postcode":"6155",
    "addr:street":"Cnr",
    "iso:country":"AU",
    "sg:address":"Cnr Vahland & High Rds",
    "sg:city":"Willetton",
    "sg:classifiers":[
        {
            "category":"Autos & Motor Vehicles",
            "subcategory":"Fuel & Gas Station",
            "type":"Retail Goods"
        }
    ],
    "sg:phone":"+61 8 9457 9055",
    "sg:postcode":"6155",
    "sg:province":"WA",
    "wof:name":"Shell Select Willetton",
    "wof:placetype":"venue"
},
  "geometry": {"coordinates":[115.89083100000001,-32.05069],"type":"Point"}
}