{
  "type": "Feature",
  "properties": {
    "iso:country":"AU",
    "sg:address":"Ivanhoe Specialist Centre 61 Livingstone St",
    "sg:city":"Ivanhoe",
    "sg:classifiers":[
        {
            "category":"Wholesale",
            "subcategory":"Medical Equipment & Supplies",
            "type":"Manufacturing & Wholesale Goods"
        }
    ],
    "sg:phone":"+61 3 9499 4094",
    "sg:postcode":"3079",
    "sg:province":"VIC",
    "sg:tags":[
        "aids",
        "hearing"
    ],
    "wof:name":"Hearing Professionals",
    "wof:placetype":"venue"
},
  "geometry": {"coordinates":[145.036254883,-37.7670135498],"type":"Point"}
}