{
  "type": "Feature",
  "properties": {
    "iso:country":"AU",
    "sg:address":"Commercial Ave",
    "sg:city":"Bohle",
    "sg:classifiers":[
        {
            "category":"Bus Stop",
            "subcategory":"None",
            "type":"Transportation"
        }
    ],
    "sg:phone":"+61 7 4774 8333",
    "sg:postcode":"4818",
    "sg:province":"QLD",
    "sg:tags":[
        "galvanising",
        "tinning"
    ],
    "wof:name":"Industrial Galvanizers",
    "wof:placetype":"venue"
},
  "geometry": {"coordinates":[146.71250900000001,-19.258245],"type":"Point"}
}