{
  "type": "Feature",
  "properties": {
    "iso:country":"AU",
    "sg:address":"41 Cobden St",
    "sg:city":"North Melbourne",
    "sg:classifiers":[
        {
            "category":"Real Estate",
            "subcategory":"Real Estate Agent",
            "type":"Services"
        }
    ],
    "sg:phone":"+61 3 9328 5133",
    "sg:postcode":"3051",
    "sg:province":"VIC",
    "sg:tags":[
        "consultant",
        "heritage"
    ],
    "wof:name":"Heritage Alliance",
    "wof:placetype":"venue"
},
  "geometry": {"coordinates":[144.957229614,-37.8043746948],"type":"Point"}
}