{
  "type": "Feature",
  "properties": {
    "addr:full":"Mt Barker Rd Mt Barker SA 5251",
    "addr:postcode":"5251",
    "addr:street":"Barker Rd",
    "iso:country":"AU",
    "sg:address":"Mt Barker Rd",
    "sg:city":"Mt Barker",
    "sg:classifiers":[
        {
            "category":"Building & Trades",
            "subcategory":"Plumbing",
            "type":"Services"
        }
    ],
    "sg:phone":"+61 8 8398 2450",
    "sg:postcode":"5251",
    "sg:province":"SA",
    "sg:tags":[
        "pump",
        "repairer"
    ],
    "wof:name":"Mt Barker Pump Sales & Service",
    "wof:placetype":"venue"
},
  "geometry": {"coordinates":[138.85264587399999,-35.0546073914],"type":"Point"}
}