{
  "type": "Feature",
  "properties": {
    "addr:full":"Oberne Rd Tarcutta NSW 2652",
    "addr:postcode":"2652",
    "addr:street":"Oberne Rd",
    "iso:country":"AU",
    "sg:address":"Oberne Rd",
    "sg:city":"Tarcutta",
    "sg:classifiers":[
        {
            "category":"Professional",
            "type":"Services"
        }
    ],
    "sg:phone":"+61 2 6928 7297",
    "sg:postcode":"2652",
    "sg:province":"NSW",
    "sg:tags":[
        "transport"
    ],
    "wof:name":"Lucas Transport",
    "wof:placetype":"venue"
},
  "geometry": {"coordinates":[147.768035889,-35.3034286499],"type":"Point"}
}