{
  "type": "Feature",
  "properties": {
    "iso:country":"AU",
    "sg:address":"37 Kitchener St",
    "sg:city":"Broadmeadows",
    "sg:classifiers":[
        {
            "category":"Travel",
            "subcategory":"Travel Agent",
            "type":"Entertainment"
        }
    ],
    "sg:phone":"+61 3 9309 6799",
    "sg:postcode":"3047",
    "sg:province":"VIC",
    "sg:tags":[
        "consultant"
    ],
    "wof:name":"Sky Link Travel & Tours",
    "wof:placetype":"venue"
},
  "geometry": {"coordinates":[144.93318176299999,-37.6841621399],"type":"Point"}
}