{
  "type": "Feature",
  "properties": {
    "addr:full":"334 Burns Bay Rd Lane Cove NSW 2066",
    "addr:housenumber":"334",
    "addr:postcode":"2066",
    "addr:street":"Burns Bay Rd",
    "iso:country":"AU",
    "sg:address":"334 Burns Bay Rd",
    "sg:city":"Lane Cove",
    "sg:classifiers":[
        {
            "category":"Communications",
            "subcategory":"News Services",
            "type":"Services"
        }
    ],
    "sg:phone":"+61 2 9428 1364",
    "sg:postcode":"2066",
    "sg:province":"NSW",
    "sg:tags":[
        "information",
        "tourist",
        "attractions"
    ],
    "wof:name":"Carisbrook",
    "wof:placetype":"venue"
},
  "geometry": {"coordinates":[151.14982605,-33.8224716187],"type":"Point"}
}