{
  "type": "Feature",
  "properties": {
    "iso:country":"AU",
    "sg:address":"1811 Portland Rd",
    "sg:city":"Heywood",
    "sg:classifiers":[
        {
            "category":"Retail",
            "subcategory":"Auto Repair",
            "type":"Services"
        }
    ],
    "sg:phone":"+61 429 110 675",
    "sg:postcode":"3304",
    "sg:province":"VIC",
    "sg:tags":[
        "beater",
        "painter",
        "panel"
    ],
    "wof:name":"C & J Panelmasters",
    "wof:placetype":"venue"
},
  "geometry": {"coordinates":[141.90667724599999,-38.1882171631],"type":"Point"}
}