{
  "type": "Feature",
  "properties": {
    "addr:full":"88a Grant St Alexandra VIC 3714",
    "addr:housenumber":"88a",
    "addr:postcode":"3714",
    "addr:street":"Grant St",
    "iso:country":"AU",
    "sg:address":"88a Grant St",
    "sg:city":"Alexandra",
    "sg:classifiers":[
        {
            "category":"Food & Beverages",
            "subcategory":"Bakery",
            "type":"Retail Goods"
        }
    ],
    "sg:phone":"+61 3 5772 1003",
    "sg:postcode":"3714",
    "sg:province":"VIC",
    "sg:tags":[
        "baker"
    ],
    "wof:name":"Wynne's Bakery",
    "wof:placetype":"venue"
},
  "geometry": {"coordinates":[145.70970153799999,-37.192035675],"type":"Point"}
}