{
  "type": "Feature",
  "properties": {
    "addr:full":"134 Queen St Woollahra NSW 2025",
    "addr:housenumber":"134",
    "addr:postcode":"2025",
    "addr:street":"Queen St",
    "iso:country":"AU",
    "sg:address":"134 Queen St",
    "sg:city":"Woollahra",
    "sg:classifiers":[
        {
            "category":"Fast Food",
            "type":"Food & Drink"
        }
    ],
    "sg:phone":"+61 2 9327 1008",
    "sg:postcode":"2025",
    "sg:province":"NSW",
    "sg:tags":[
        "away",
        "take"
    ],
    "wof:name":"Chargrill Charlie's",
    "wof:placetype":"venue"
},
  "geometry": {"coordinates":[151.23809814399999,-33.888130188],"type":"Point"}
}