{
  "type": "Feature",
  "properties": {
    "addr:full":"100 - 104 Mornington Rd Mornington TAS 7018",
    "addr:housenumber":"104",
    "addr:postcode":"7018",
    "addr:street":"Mornington Rd",
    "iso:country":"AU",
    "sg:address":"100 - 104 Mornington Rd",
    "sg:city":"Mornington",
    "sg:classifiers":[
        {
            "category":"Wholesale",
            "subcategory":"Seafood",
            "type":"Manufacturing & Wholesale Goods"
        }
    ],
    "sg:phone":"+61 1300 660 491",
    "sg:postcode":"7018",
    "sg:province":"TAS",
    "sg:tags":[
        "fish"
    ],
    "wof:name":"Tassal Operations Pty Ltd",
    "wof:placetype":"venue"
},
  "geometry": {"coordinates":[147.40266418499999,-42.861328125],"type":"Point"}
}