{
  "type": "Feature",
  "properties": {
    "addr:full":"19 Eric Ave Port Lincoln SA 5606",
    "addr:housenumber":"19",
    "addr:postcode":"5606",
    "addr:street":"Eric Ave",
    "iso:country":"AU",
    "sg:address":"19 Eric Ave",
    "sg:city":"Port Lincoln",
    "sg:classifiers":[
        {
            "category":"Utilities",
            "subcategory":"Electric",
            "type":"Services"
        }
    ],
    "sg:phone":"+61 8 8683 0926",
    "sg:postcode":"5606",
    "sg:province":"SA",
    "sg:tags":[
        "electrical",
        "contractor"
    ],
    "wof:name":"Pierik B A & E M",
    "wof:placetype":"venue"
},
  "geometry": {"coordinates":[135.843369,-34.712685],"type":"Point"}
}