{
  "type": "Feature",
  "properties": {
    "addr:full":"Old Gympie Rd Glass House Mountains QLD 4518",
    "addr:postcode":"4518",
    "addr:street":"Gympie Rd",
    "iso:country":"AU",
    "sg:address":"Old Gympie Rd",
    "sg:city":"Glass House Mountains",
    "sg:classifiers":[
        {
            "category":"Utilities",
            "subcategory":"Electric",
            "type":"Services"
        }
    ],
    "sg:phone":"+61 409 889 350",
    "sg:postcode":"4518",
    "sg:province":"QLD",
    "sg:tags":[
        "electrical",
        "contractor"
    ],
    "wof:name":"Keast Electrical Pty Ltd",
    "wof:placetype":"venue"
},
  "geometry": {"coordinates":[152.922149658,-26.8984603882],"type":"Point"}
}