{
  "type": "Feature",
  "properties": {
    "addr:full":"232 Cape St Tuart Hill WA 6060",
    "addr:housenumber":"232",
    "addr:postcode":"6060",
    "addr:street":"Cape St",
    "iso:country":"AU",
    "sg:address":"232 Cape St",
    "sg:city":"Tuart Hill",
    "sg:classifiers":[
        {
            "category":"Social Services",
            "subcategory":"Child Care",
            "type":"Services"
        }
    ],
    "sg:phone":"+61 8 9345 2211",
    "sg:postcode":"6060",
    "sg:province":"WA",
    "wof:name":"Mulberry Tree Childcare",
    "wof:placetype":"venue"
},
  "geometry": {"coordinates":[115.840377808,-31.9023551941],"type":"Point"}
}