{
  "type": "Feature",
  "properties": {
    "addr:full":"23 Claremont Ave Adamstown Heights NSW 2289",
    "addr:housenumber":"23",
    "addr:postcode":"2289",
    "addr:street":"Claremont Ave Adamstown",
    "iso:country":"AU",
    "sg:address":"23 Claremont Ave",
    "sg:city":"Adamstown Heights",
    "sg:classifiers":[
        {
            "category":"Building & Trades",
            "subcategory":"Construction",
            "type":"Services"
        }
    ],
    "sg:phone":"+61 412 492 511",
    "sg:postcode":"2289",
    "sg:province":"NSW",
    "sg:tags":[
        "concrete",
        "contractor"
    ],
    "wof:name":"Rutledge Peter Concreting",
    "wof:placetype":"venue"
},
  "geometry": {"coordinates":[151.71925354000001,-32.945400238],"type":"Point"}
}