{
  "type": "Feature",
  "properties": {
    "addr:full":"13 Grant St Bacchus Marsh VIC 3340",
    "addr:housenumber":"13",
    "addr:postcode":"3340",
    "addr:street":"Grant St",
    "iso:country":"AU",
    "sg:address":"13 Grant St",
    "sg:city":"Bacchus Marsh",
    "sg:classifiers":[
        {
            "category":"Home & Garden",
            "subcategory":"Building Materials",
            "type":"Retail Goods"
        }
    ],
    "sg:phone":"+61 3 5367 2089",
    "sg:postcode":"3340",
    "sg:province":"VIC",
    "sg:tags":[
        "supply"
    ],
    "wof:name":"Wilsons Hardware & Building Supplies",
    "wof:placetype":"venue"
},
  "geometry": {"coordinates":[144.43495200000001,-37.676674],"type":"Point"}
}