{
  "type": "Feature",
  "properties": {
    "addr:full":"20 Faunce St Queanbeyan NSW 2620",
    "addr:housenumber":"20",
    "addr:postcode":"2620",
    "addr:street":"Faunce St",
    "iso:country":"AU",
    "sg:address":"20 Faunce St",
    "sg:city":"Queanbeyan",
    "sg:classifiers":[
        {
            "category":"Wholesale",
            "subcategory":"Chemicals & Plastics",
            "type":"Manufacturing & Wholesale Goods"
        }
    ],
    "sg:phone":"+61 2 6299 3611",
    "sg:postcode":"2620",
    "sg:province":"NSW",
    "sg:tags":[
        "extruders"
    ],
    "wof:name":"Australian Plastic Profiles Pty Ltd",
    "wof:placetype":"venue"
},
  "geometry": {"coordinates":[149.24964904800001,-35.3413772583],"type":"Point"}
}