{
  "type": "Feature",
  "properties": {
    "addr:full":"2 Mitchell Ave Currumbin QLD 4223",
    "addr:housenumber":"2",
    "addr:postcode":"4223",
    "addr:street":"Mitchell Ave",
    "iso:country":"AU",
    "sg:address":"2 Mitchell Ave",
    "sg:city":"Currumbin",
    "sg:classifiers":[
        {
            "category":"Social Services",
            "subcategory":"Child Care",
            "type":"Services"
        }
    ],
    "sg:phone":"+61 7 5534 3311",
    "sg:postcode":"4223",
    "sg:province":"QLD",
    "wof:name":"Currumbin Child Care Centre",
    "wof:placetype":"venue"
},
  "geometry": {"coordinates":[153.475738525,-28.1375732422],"type":"Point"}
}