{
  "type": "Feature",
  "properties": {
    "addr:full":"Shop 2 63 Penguin Rd Safety Bay WA 6169",
    "addr:housenumber":"shop;63",
    "addr:postcode":"6169",
    "addr:street":"Penguin Rd",
    "iso:country":"AU",
    "sg:address":"Shop 2 63 Penguin Rd",
    "sg:city":"Safety Bay",
    "sg:classifiers":[
        {
            "category":"Shopping",
            "subcategory":"Clothing, Apparel, & Fashions",
            "type":"Retail Goods"
        }
    ],
    "sg:phone":"+61 411 060 381",
    "sg:postcode":"6169",
    "sg:province":"WA",
    "sg:tags":[
        "recycled",
        "clothing"
    ],
    "wof:name":"White Wave",
    "wof:placetype":"venue"
},
  "geometry": {"coordinates":[115.711021,-32.303318],"type":"Point"}
}