{
  "type": "Feature",
  "properties": {
    "addr:full":"18- 58 Ridley Gr Woodville Gardens SA 5012",
    "addr:housenumber":"58",
    "addr:postcode":"5012",
    "addr:street":"Ridley Gr",
    "iso:country":"AU",
    "sg:address":"18- 58 Ridley Gr",
    "sg:city":"Woodville Gardens",
    "sg:classifiers":[
        {
            "category":"Education",
            "subcategory":"Kindergarten",
            "type":"Public Place"
        }
    ],
    "sg:phone":"+61 8 8445 6555",
    "sg:postcode":"5012",
    "sg:province":"SA",
    "sg:tags":[
        "pre-schools"
    ],
    "wof:name":"Woodville Gardens Pre-School",
    "wof:placetype":"venue"
},
  "geometry": {"coordinates":[138.551635742,-34.8639526367],"type":"Point"}
}