{
  "type": "Feature",
  "properties": {
    "addr:full":"36 Smith St Alice Springs NT 0870",
    "addr:housenumber":"36",
    "addr:postcode":"nt 0870",
    "addr:street":"Smith St",
    "iso:country":"AU",
    "sg:address":"36 Smith St",
    "sg:city":"Alice Springs",
    "sg:classifiers":[
        {
            "category":"Retail",
            "subcategory":"Auto Repair",
            "type":"Services"
        }
    ],
    "sg:phone":"+61 8 8953 4779",
    "sg:postcode":"0870",
    "sg:province":"NT",
    "sg:tags":[
        "repairer",
        "motor",
        "engineer"
    ],
    "wof:name":"Classic Cars & Bikes",
    "wof:placetype":"venue"
},
  "geometry": {"coordinates":[133.867385864,-23.6912765503],"type":"Point"}
}