{
  "type": "Feature",
  "properties": {
    "iso:country":"AU",
    "sg:address":"82 McCarrs Creek Rd",
    "sg:city":"Church Point",
    "sg:classifiers":[
        {
            "category":"Education",
            "subcategory":"Music School",
            "type":"Public Place"
        }
    ],
    "sg:phone":"+61 2 9999 3315",
    "sg:postcode":"2105",
    "sg:province":"NSW",
    "sg:tags":[
        "singing",
        "teacher"
    ],
    "wof:name":"Gwenda Gilligan",
    "wof:placetype":"venue"
},
  "geometry": {"coordinates":[151.280823,-33.652546],"type":"Point"}
}