{
  "type": "Feature",
  "properties": {
    "addr:full":"39 Putnam Ave Bendigo VIC 3539",
    "addr:housenumber":"39",
    "addr:postcode":"3539",
    "addr:street":"Putnam Ave",
    "iso:country":"AU",
    "sg:address":"39 Putnam Ave",
    "sg:city":"Bendigo",
    "sg:classifiers":[
        {
            "category":"Personal",
            "subcategory":"Massage",
            "type":"Services"
        }
    ],
    "sg:phone":"+61 3 5442 2524",
    "sg:postcode":"3539",
    "sg:province":"VIC",
    "sg:tags":[
        "therapy"
    ],
    "wof:name":"Geoff Waldron",
    "wof:placetype":"venue"
},
  "geometry": {"coordinates":[144.30981399999999,-36.762894],"type":"Point"}
}