{
  "type": "Feature",
  "properties": {
    "addr:full":"South Hedland Shopping Centre Throssell Rd South Hedland WA 6722",
    "addr:postcode":"6722",
    "addr:street":"Throssell Rd",
    "iso:country":"AU",
    "sg:address":"South Hedland Shopping Centre Throssell Rd",
    "sg:city":"South Hedland",
    "sg:classifiers":[
        {
            "category":"Social Services",
            "subcategory":"Child Care",
            "type":"Services"
        }
    ],
    "sg:phone":"+61 8 9172 1000",
    "sg:postcode":"6722",
    "sg:province":"WA",
    "sg:tags":[
        "childbirth"
    ],
    "wof:name":"Parent Information Centre",
    "wof:placetype":"venue"
},
  "geometry": {"coordinates":[118.601753235,-20.4093589783],"type":"Point"}
}