{
  "type": "Feature",
  "properties": {
    "addr:full":"1221 Stud Rd Rowville VIC 3178",
    "addr:housenumber":"1221",
    "addr:postcode":"3178",
    "addr:street":"Stud Rd",
    "iso:country":"AU",
    "sg:address":"1221 Stud Rd",
    "sg:city":"Rowville",
    "sg:classifiers":[
        {
            "category":"Fast Food",
            "type":"Food & Drink"
        }
    ],
    "sg:phone":"+61 3 9764 3634",
    "sg:postcode":"3178",
    "sg:province":"VIC",
    "sg:tags":[
        "away",
        "take"
    ],
    "wof:name":"Rowville Pizza",
    "wof:placetype":"venue"
},
  "geometry": {"coordinates":[145.23300170900001,-37.9297370911],"type":"Point"}
}