{
  "type": "Feature",
  "properties": {
    "addr:full":"1 Monbulk Rd Mt Evelyn VIC 3796",
    "addr:housenumber":"1",
    "addr:postcode":"3796",
    "addr:street":"Monbulk Rd",
    "iso:country":"AU",
    "sg:address":"1 Monbulk Rd",
    "sg:city":"Mt Evelyn",
    "sg:classifiers":[
        {
            "category":"Autos & Motor Vehicles",
            "subcategory":"Fuel & Gas Station",
            "type":"Retail Goods"
        }
    ],
    "sg:phone":"+61 3 9737 1099",
    "sg:postcode":"3796",
    "sg:province":"VIC",
    "wof:name":"Fast Fuel",
    "wof:placetype":"venue"
},
  "geometry": {"coordinates":[145.382247925,-37.7859611511],"type":"Point"}
}