{
  "type": "Feature",
  "properties": {
    "addr:full":"Unit 2 30- 36 James St Bellevue WA 6056",
    "addr:housenumber":"30 36",
    "addr:postcode":"6056",
    "addr:street":"James St",
    "iso:country":"AU",
    "sg:address":"Unit 2 30- 36 James St",
    "sg:city":"Bellevue",
    "sg:classifiers":[
        {
            "category":"Utilities",
            "type":"Services"
        }
    ],
    "sg:phone":"+61 8 9274 4236",
    "sg:postcode":"6056",
    "sg:province":"WA",
    "sg:tags":[
        "equipment",
        "towing"
    ],
    "wof:name":"Midland Towbars & Towbar City Midland",
    "wof:placetype":"venue"
},
  "geometry": {"coordinates":[116.025527954,-31.8948097229],"type":"Point"}
}