{
  "type": "Feature",
  "properties": {
    "iso:country":"AU",
    "sg:address":"342 Cambridge St",
    "sg:city":"Wembley",
    "sg:classifiers":[
        {
            "category":"Fast Food",
            "type":"Food & Drink"
        }
    ],
    "sg:phone":"+61 8 9387 1288",
    "sg:postcode":"6014",
    "sg:province":"WA",
    "sg:tags":[
        "away",
        "take"
    ],
    "wof:name":"Alexanders Lunch Bar",
    "wof:placetype":"venue"
},
  "geometry": {"coordinates":[115.81056213399999,-31.9406147003],"type":"Point"}
}