{
  "type": "Feature",
  "properties": {
    "addr:full":"193 Brighton Rd Somerton Park SA 5044",
    "addr:housenumber":"193",
    "addr:postcode":"5044",
    "addr:street":"Brighton Rd",
    "iso:country":"AU",
    "sg:address":"193 Brighton Rd",
    "sg:city":"Somerton Park",
    "sg:classifiers":[
        {
            "category":"Health Services",
            "subcategory":"Clinic",
            "type":"Services"
        }
    ],
    "sg:phone":"+61 407 454 080",
    "sg:postcode":"5044",
    "sg:province":"SA",
    "sg:tags":[
        "aid",
        "dental"
    ],
    "wof:name":"Designer Mouthguards",
    "wof:placetype":"venue"
},
  "geometry": {"coordinates":[138.521118,-34.993885],"type":"Point"}
}