{
  "type": "Feature",
  "properties": {
    "addr:full":"16 Grey St St George QLD 4487",
    "addr:housenumber":"16",
    "addr:postcode":"4487",
    "addr:street":"Grey St",
    "iso:country":"AU",
    "sg:address":"16 Grey St",
    "sg:city":"St George",
    "sg:classifiers":[
        {
            "category":"Retail",
            "subcategory":"Auto Repair",
            "type":"Services"
        }
    ],
    "sg:phone":"+61 7 4625 3582",
    "sg:postcode":"4487",
    "sg:province":"QLD",
    "sg:tags":[
        "muffler",
        "exhaust",
        "system"
    ],
    "wof:name":"St George Radiator & Exhaust",
    "wof:placetype":"venue"
},
  "geometry": {"coordinates":[148.579467773,-28.0362224579],"type":"Point"}
}