{
  "type": "Feature",
  "properties": {
    "addr:full":"82 Barkley St Mornington VIC 3931",
    "addr:housenumber":"82",
    "addr:postcode":"3931",
    "addr:street":"Barkley St",
    "iso:country":"AU",
    "sg:address":"82 Barkley St",
    "sg:city":"Mornington",
    "sg:classifiers":[
        {
            "category":"Arena",
            "subcategory":"Sports Club",
            "type":"Entertainment"
        }
    ],
    "sg:phone":"+61 419 392 006",
    "sg:postcode":"3931",
    "sg:province":"VIC",
    "sg:tags":[
        "defence",
        "supply",
        "self",
        "instruction",
        "martial art"
    ],
    "wof:name":"M.C.A. Martial Arts Centre",
    "wof:placetype":"venue"
},
  "geometry": {"coordinates":[145.04196167000001,-38.2197113037],"type":"Point"}
}