{
  "type": "Feature",
  "properties": {
    "addr:full":"207 Williams Rd South Yarra VIC 3141",
    "addr:housenumber":"207",
    "addr:postcode":"3141",
    "addr:street":"Williams Rd",
    "iso:country":"AU",
    "sg:address":"207 Williams Rd",
    "sg:city":"South Yarra",
    "sg:classifiers":[
        {
            "category":"Health Services",
            "subcategory":"Dentist",
            "type":"Services"
        }
    ],
    "sg:phone":"+61 3 9827 3314",
    "sg:postcode":"3141",
    "sg:province":"VIC",
    "wof:name":"Sanderson L E",
    "wof:placetype":"venue"
},
  "geometry": {"coordinates":[145.00349426299999,-37.8458328247],"type":"Point"}
}