{
  "type": "Feature",
  "properties": {
    "addr:full":"22 Railway St Southport QLD 4215",
    "addr:housenumber":"22",
    "addr:postcode":"4215",
    "addr:street":"Railway St",
    "iso:country":"AU",
    "sg:address":"22 Railway St",
    "sg:city":"Southport",
    "sg:classifiers":[
        {
            "category":"Personal",
            "subcategory":"Beauty Salon",
            "type":"Services"
        }
    ],
    "sg:phone":"+61 7 5532 8676",
    "sg:postcode":"4215",
    "sg:province":"QLD",
    "sg:tags":[
        "hairdresser"
    ],
    "wof:name":"Mondo Hair",
    "wof:placetype":"venue"
},
  "geometry": {"coordinates":[153.41152954099999,-27.9631919861],"type":"Point"}
}