{
  "type": "Feature",
  "properties": {
    "iso:country":"AU",
    "sg:address":"20/ 7 Salisbury Rd",
    "sg:city":"Castle Hill",
    "sg:classifiers":[
        {
            "category":"Professional",
            "subcategory":"Art Services",
            "type":"Services"
        }
    ],
    "sg:phone":"+61 2 8850 5455",
    "sg:postcode":"2154",
    "sg:province":"NSW",
    "sg:tags":[
        "graphic",
        "designer"
    ],
    "wof:name":"IMS Intergrated Marketing Solutions Pty Ltd",
    "wof:placetype":"venue"
},
  "geometry": {"coordinates":[150.97572326700001,-33.729434967],"type":"Point"}
}