{
  "type": "Feature",
  "properties": {
    "addr:full":"8 Regent St Port Pirie SA 5540",
    "addr:housenumber":"8",
    "addr:postcode":"5540",
    "addr:street":"Regent St",
    "iso:country":"AU",
    "sg:address":"8 Regent St",
    "sg:city":"Port Pirie",
    "sg:classifiers":[
        {
            "category":"Communications",
            "type":"Services"
        }
    ],
    "sg:phone":"+61 8 8633 2628",
    "sg:postcode":"5540",
    "sg:province":"SA",
    "sg:tags":[
        "equipment",
        "radio"
    ],
    "wof:name":"Flinders Radio",
    "wof:placetype":"venue"
},
  "geometry": {"coordinates":[137.998901367,-33.1976280212],"type":"Point"}
}