{
  "type": "Feature",
  "properties": {
    "iso:country":"AU",
    "sg:address":"135 Collins Rd",
    "sg:city":"Willetton",
    "sg:classifiers":[
        {
            "category":"Retail",
            "subcategory":"Auto Repair",
            "type":"Services"
        }
    ],
    "sg:phone":"+61 8 9259 1831",
    "sg:postcode":"6155",
    "sg:province":"WA",
    "sg:tags":[
        "repairer",
        "motor",
        "engineer"
    ],
    "wof:name":"Auto net Collins Rd",
    "wof:placetype":"venue"
},
  "geometry": {"coordinates":[115.894753,-32.055222],"type":"Point"}
}