{
  "type": "Feature",
  "properties": {
    "addr:full":"364 Rawdon Island Rd Rawdon Island NSW 2446",
    "addr:housenumber":"364",
    "addr:postcode":"2446",
    "addr:street":"Rawdon Island Rd",
    "iso:country":"AU",
    "sg:address":"364 Rawdon Island Rd",
    "sg:city":"Rawdon Island",
    "sg:classifiers":[
        {
            "category":"Building & Trades",
            "subcategory":"Electrical",
            "type":"Services"
        }
    ],
    "sg:phone":"+61 2 6585 9278",
    "sg:postcode":"2446",
    "sg:province":"NSW",
    "sg:tags":[
        "wholesaler",
        "equipment",
        "magnetic",
        "mfrs"
    ],
    "wof:name":"Magswitch Technologies",
    "wof:placetype":"venue"
},
  "geometry": {"coordinates":[152.78121899999999,-31.434055],"type":"Point"}
}