{
  "type": "Feature",
  "properties": {
    "iso:country":"AU",
    "sg:address":"364 Rawdon Island Rd",
    "sg:city":"Rawdon Island",
    "sg:classifiers":[
        {
            "category":"Building & Trades",
            "subcategory":"Electrical",
            "type":"Services"
        }
    ],
    "sg:phone":"+61 2 6585 9278",
    "sg:postcode":"2446",
    "sg:province":"NSW",
    "sg:tags":[
        "wholesaler",
        "equipment",
        "magnetic",
        "mfrs"
    ],
    "wof:name":"Magswitch Technologies",
    "wof:placetype":"venue"
},
  "geometry": {"coordinates":[152.781219,-31.434055],"type":"Point"}
}