{
  "type": "Feature",
  "properties": {
    "addr:full":"Level 1 /Unit 5, 20 Smallwood Pl Murarrie QLD 4172",
    "addr:housenumber":"unit;20",
    "addr:postcode":"4172",
    "addr:street":"Smallwood Pl",
    "iso:country":"AU",
    "sg:address":"Level 1 /Unit 5, 20 Smallwood Pl",
    "sg:city":"Murarrie",
    "sg:classifiers":[
        {
            "category":"Professional",
            "subcategory":"Accounting & Tax Preparation",
            "type":"Services"
        }
    ],
    "sg:phone":"+61 7 3395 5444",
    "sg:postcode":"4172",
    "sg:province":"QLD",
    "sg:tags":[
        "consultant",
        "taxation"
    ],
    "wof:name":"Balanced Business Accounting",
    "wof:placetype":"venue"
},
  "geometry": {"coordinates":[153.10253906200001,-27.454492569],"type":"Point"}
}