{
  "type": "Feature",
  "properties": {
    "addr:full":"25 Ferny Ridge Crt Mudgeeraba QLD 4213",
    "addr:housenumber":"25",
    "addr:postcode":"4213",
    "addr:street":"Ferny Ridge Crt",
    "iso:country":"AU",
    "sg:address":"25 Ferny Ridge Crt",
    "sg:city":"Mudgeeraba",
    "sg:classifiers":[
        {
            "category":"Utilities",
            "subcategory":"Sewage",
            "type":"Services"
        }
    ],
    "sg:phone":"+61 7 5522 9686",
    "sg:postcode":"4213",
    "sg:province":"QLD",
    "sg:tags":[
        "water",
        "waste",
        "treatment"
    ],
    "wof:name":"A And A Worm Farm Waste Systems",
    "wof:placetype":"venue"
},
  "geometry": {"coordinates":[153.326904297,-28.1429023743],"type":"Point"}
}