{
  "type": "Feature",
  "properties": {
    "iso:country":"AU",
    "sg:address":"Kemps House, 21",
    "sg:city":"Hindmarsh Square Adelaide",
    "sg:classifiers":[
        {
            "category":"Banks & Credit Unions",
            "subcategory":"Investment Brokerage",
            "type":"Services"
        }
    ],
    "sg:phone":"+61 8 8223 6200",
    "sg:postcode":"5000",
    "sg:province":"SA",
    "sg:tags":[
        "debt",
        "collection"
    ],
    "wof:name":"Kemps Mercantile Agency Australia Pty Ltd",
    "wof:placetype":"venue"
},
  "geometry": {"coordinates":[138.60618591299999,-34.9232902527],"type":"Point"}
}