{
  "type": "Feature",
  "properties": {
    "addr:full":"43a Ballarat St Yarraville VIC 3013",
    "addr:housenumber":"43a",
    "addr:postcode":"3013",
    "addr:street":"Ballarat St",
    "iso:country":"AU",
    "sg:address":"43a Ballarat St",
    "sg:city":"Yarraville",
    "sg:classifiers":[
        {
            "category":"Home & Garden",
            "subcategory":"Garden Supply",
            "type":"Retail Goods"
        }
    ],
    "sg:phone":"+61 3 9687 7302",
    "sg:postcode":"3013",
    "sg:province":"VIC",
    "sg:tags":[
        "fertilizer"
    ],
    "wof:name":"Thrive-Ag Pty Ltd",
    "wof:placetype":"venue"
},
  "geometry": {"coordinates":[144.890823364,-37.8179473877],"type":"Point"}
}