{
  "type": "Feature",
  "properties": {
    "addr:full":"36 Ayr St Doncaster VIC 3108",
    "addr:housenumber":"36",
    "addr:postcode":"3108",
    "addr:street":"Ayr St",
    "iso:country":"AU",
    "sg:address":"36 Ayr St",
    "sg:city":"Doncaster",
    "sg:classifiers":[
        {
            "category":"Communications",
            "type":"Services"
        }
    ],
    "sg:phone":"+61 3 9816 3060",
    "sg:postcode":"3108",
    "sg:province":"VIC",
    "sg:tags":[
        "equipment",
        "radio"
    ],
    "wof:name":"Credable Connection",
    "wof:placetype":"venue"
},
  "geometry": {"coordinates":[145.10281372099999,-37.7837104797],"type":"Point"}
}