{
  "type": "Feature",
  "properties": {
    "iso:country":"AU",
    "sg:address":"3 Solander Rd",
    "sg:city":"Avoca Beach",
    "sg:classifiers":[
        {
            "category":"Home & Garden",
            "subcategory":"Building Materials",
            "type":"Retail Goods"
        }
    ],
    "sg:phone":"+61 2 4381 0889",
    "sg:postcode":"2251",
    "sg:province":"NSW",
    "sg:tags":[
        "retaining",
        "wall"
    ],
    "wof:name":"Chris Martin Excavations",
    "wof:placetype":"venue"
},
  "geometry": {"coordinates":[151.43255615199999,-33.4785003662],"type":"Point"}
}