{
  "type": "Feature",
  "properties": {
    "addr:full":"68 Victoria St Carlton VIC 3053",
    "addr:housenumber":"68",
    "addr:postcode":"3053",
    "addr:street":"Victoria St",
    "iso:country":"AU",
    "sg:address":"68 Victoria St",
    "sg:city":"Carlton",
    "sg:classifiers":[
        {
            "category":"Fast Food",
            "type":"Food & Drink"
        }
    ],
    "sg:phone":"+61 3 9663 3016",
    "sg:postcode":"3053",
    "sg:province":"VIC",
    "sg:tags":[
        "away",
        "take"
    ],
    "wof:name":"Carlton Megabytes",
    "wof:placetype":"venue"
},
  "geometry": {"coordinates":[144.972488403,-37.7930717468],"type":"Point"}
}