{
  "type": "Feature",
  "properties": {
    "addr:full":"55 Progress St Tahmoor NSW 2573",
    "addr:housenumber":"55",
    "addr:postcode":"2573",
    "addr:street":"Progress St",
    "iso:country":"AU",
    "sg:address":"55 Progress St",
    "sg:city":"Tahmoor",
    "sg:classifiers":[
        {
            "category":"Travel",
            "subcategory":"Travel Agent",
            "type":"Entertainment"
        }
    ],
    "sg:phone":"+61 2 4681 9432",
    "sg:postcode":"2573",
    "sg:province":"NSW",
    "sg:tags":[
        "consultant"
    ],
    "wof:name":"Bronzewing Tours",
    "wof:placetype":"venue"
},
  "geometry": {"coordinates":[150.597457886,-34.2271194458],"type":"Point"}
}