{
  "type": "Feature",
  "properties": {
    "addr:full":"50- 54 Bay Rd Arcadia NSW 2159",
    "addr:housenumber":"54",
    "addr:postcode":"2159",
    "addr:street":"Bay Rd",
    "iso:country":"AU",
    "sg:address":"50- 54 Bay Rd",
    "sg:city":"Arcadia",
    "sg:classifiers":[
        {
            "category":"Farming",
            "subcategory":"Livestock Farm",
            "type":"Manufacturing & Wholesale Goods"
        }
    ],
    "sg:phone":"+61 2 9655 1500",
    "sg:postcode":"2159",
    "sg:province":"NSW",
    "sg:tags":[
        "agistment"
    ],
    "wof:name":"Sunflower",
    "wof:placetype":"venue"
},
  "geometry": {"coordinates":[151.086502075,-33.6182060242],"type":"Point"}
}