{
  "type": "Feature",
  "properties": {
    "addr:full":"75 Emmett St Smithton TAS 7330",
    "addr:housenumber":"75",
    "addr:postcode":"7330",
    "addr:street":"Emmett St",
    "iso:country":"AU",
    "sg:address":"75 Emmett St",
    "sg:city":"Smithton",
    "sg:classifiers":[
        {
            "category":"Fast Food",
            "type":"Food & Drink"
        }
    ],
    "sg:phone":"+61 3 6452 1604",
    "sg:postcode":"7330",
    "sg:province":"TAS",
    "sg:tags":[
        "away",
        "take"
    ],
    "wof:name":"Duck Inn Cafe & Take Away",
    "wof:placetype":"venue"
},
  "geometry": {"coordinates":[145.12626599999999,-40.840363],"type":"Point"}
}