{
  "type": "Feature",
  "properties": {
    "addr:full":"35 The Point Rd Woolwich NSW 2110",
    "addr:housenumber":"35",
    "addr:postcode":"2110",
    "addr:street":"The Point Rd",
    "iso:country":"AU",
    "sg:address":"35 The Point Rd",
    "sg:city":"Woolwich",
    "sg:classifiers":[
        {
            "category":"Real Estate",
            "subcategory":"Real Estate Services",
            "type":"Services"
        }
    ],
    "sg:phone":"+61 2 9817 4657",
    "sg:postcode":"2110",
    "sg:province":"NSW",
    "sg:tags":[
        "consultant",
        "property"
    ],
    "wof:name":"Circosta S & A",
    "wof:placetype":"venue"
},
  "geometry": {"coordinates":[151.176025391,-33.8376045227],"type":"Point"}
}