{
  "type": "Feature",
  "properties": {
    "addr:full":"31 Church St Penola SA 5277",
    "addr:housenumber":"31",
    "addr:postcode":"5277",
    "addr:street":"Church St",
    "iso:country":"AU",
    "sg:address":"31 Church St",
    "sg:city":"Penola",
    "sg:classifiers":[
        {
            "category":"Food & Beverages",
            "subcategory":"Liquor & Beverages",
            "type":"Retail Goods"
        }
    ],
    "sg:phone":"+61 8 8737 2322",
    "sg:postcode":"5277",
    "sg:province":"SA",
    "sg:tags":[
        "store"
    ],
    "wof:name":"Heywards Royal Oak Hotel & Cellars",
    "wof:placetype":"venue"
},
  "geometry": {"coordinates":[140.837143,-37.378399],"type":"Point"}
}