{
  "type": "Feature",
  "properties": {
    "addr:full":"Lesley Ave Caboolture QLD 4510",
    "addr:postcode":"4510",
    "addr:street":"Lesley Ave",
    "iso:country":"AU",
    "sg:address":"Lesley Ave",
    "sg:city":"Caboolture",
    "sg:classifiers":[
        {
            "category":"Retail",
            "subcategory":"Event Space",
            "type":"Services"
        }
    ],
    "sg:phone":"+61 7 5495 1452",
    "sg:postcode":"4510",
    "sg:province":"QLD",
    "sg:tags":[
        "venue",
        "reception",
        "wedding"
    ],
    "wof:name":"Caboolture Golf Club",
    "wof:placetype":"venue"
},
  "geometry": {"coordinates":[152.926605,-27.074966],"type":"Point"}
}