{
  "type": "Feature",
  "properties": {
    "addr:full":"3rd Floor London Crt Perth WA 6000",
    "addr:postcode":"6000",
    "iso:country":"AU",
    "sg:address":"3rd Floor London Crt",
    "sg:city":"Perth",
    "sg:classifiers":[
        {
            "category":"Personal",
            "subcategory":"Beauty Salon",
            "type":"Services"
        }
    ],
    "sg:phone":"+61 8 9325 2054",
    "sg:postcode":"6000",
    "sg:province":"WA",
    "sg:tags":[
        "hairdresser"
    ],
    "wof:name":"Zena Hair Fashions",
    "wof:placetype":"venue"
},
  "geometry": {"coordinates":[115.858818054,-31.9548225403],"type":"Point"}
}