{
  "type": "Feature",
  "properties": {
    "iso:country":"AU",
    "sg:address":"26 Highland Ave",
    "sg:city":"Rostrevor",
    "sg:classifiers":[
        {
            "category":"Professional",
            "subcategory":"Business Services",
            "type":"Services"
        }
    ],
    "sg:phone":"+61 8 8337 3270",
    "sg:postcode":"5073",
    "sg:province":"SA",
    "sg:tags":[
        "drafting"
    ],
    "wof:name":"Boyle Michael D",
    "wof:placetype":"venue"
},
  "geometry": {"coordinates":[138.68699645999999,-34.8965454102],"type":"Point"}
}