{
  "type": "Feature",
  "properties": {
    "addr:full":"U9c/ 32 Frederick St Oatley NSW 2223",
    "addr:housenumber":"32",
    "addr:postcode":"2223",
    "addr:street":"Frederick St",
    "iso:country":"AU",
    "sg:address":"U9c/ 32 Frederick St",
    "sg:city":"Oatley",
    "sg:classifiers":[
        {
            "category":"Building & Trades",
            "subcategory":"Construction",
            "type":"Services"
        }
    ],
    "sg:phone":"+61 2 9570 6987",
    "sg:postcode":"2223",
    "sg:province":"NSW",
    "sg:tags":[
        "industrial",
        "commercial",
        "air conditioning"
    ],
    "wof:name":"Help U Software",
    "wof:placetype":"venue"
},
  "geometry": {"coordinates":[151.081756592,-33.9811210632],"type":"Point"}
}