{
  "type": "Feature",
  "properties": {
    "addr:full":"Apt l, 1 Alfred St Prahran VIC 3181",
    "addr:housenumber":"1",
    "addr:postcode":"3181",
    "addr:street":"Alfred St",
    "iso:country":"AU",
    "sg:address":"Apt l, 1 Alfred St",
    "sg:city":"Prahran",
    "sg:classifiers":[
        {
            "category":"Professional",
            "subcategory":"Management & Consulting",
            "type":"Services"
        }
    ],
    "sg:phone":"+61 3 9510 9505",
    "sg:postcode":"3181",
    "sg:province":"VIC",
    "sg:tags":[
        "consultant",
        "educational"
    ],
    "wof:name":"Educational Personal & Child Consulting Service",
    "wof:placetype":"venue"
},
  "geometry": {"coordinates":[144.98507690400001,-37.8506317139],"type":"Point"}
}