{
  "type": "Feature",
  "properties": {
    "addr:full":"PO Box 157 Woollahra NSW 1350",
    "addr:postcode":"1350",
    "iso:country":"AU",
    "sg:address":"PO Box 157",
    "sg:city":"Woollahra",
    "sg:classifiers":[
        {
            "category":"Building & Trades",
            "subcategory":"Construction",
            "type":"Services"
        }
    ],
    "sg:phone":"+61 419 444 402",
    "sg:postcode":"1350",
    "sg:province":"NSW",
    "sg:tags":[
        "earth",
        "excavating",
        "moving",
        "contractor"
    ],
    "wof:name":"Ross Earthmoving",
    "wof:placetype":"venue"
},
  "geometry": {"coordinates":[151.23716735799999,-33.8884391785],"type":"Point"}
}