{
  "type": "Feature",
  "properties": {
    "addr:full":"6 Elizabeth St Charters Towers QLD 4820",
    "addr:housenumber":"6",
    "addr:postcode":"4820",
    "addr:street":"Elizabeth St",
    "iso:country":"AU",
    "sg:address":"6 Elizabeth St",
    "sg:city":"Charters Towers",
    "sg:classifiers":[
        {
            "category":"Health Services",
            "subcategory":"Health Practitioner",
            "type":"Services"
        }
    ],
    "sg:phone":"+61 7 4787 4622",
    "sg:postcode":"4820",
    "sg:province":"QLD",
    "sg:tags":[
        "naturopath"
    ],
    "wof:name":"Hamilton Rose",
    "wof:placetype":"venue"
},
  "geometry": {"coordinates":[146.25105300000001,-20.073217],"type":"Point"}
}