{
  "type": "Feature",
  "properties": {
    "iso:country":"AU",
    "sg:address":"180 Barridale Drv",
    "sg:city":"Kingsley",
    "sg:classifiers":[
        {
            "category":"Education",
            "subcategory":"Special Training",
            "type":"Public Place"
        }
    ],
    "sg:phone":"+61 2 8206 7800",
    "sg:postcode":"6026",
    "sg:province":"WA",
    "sg:tags":[
        "development"
    ],
    "wof:name":"Mentor Management",
    "wof:placetype":"venue"
},
  "geometry": {"coordinates":[115.797912598,-31.8046073914],"type":"Point"}
}