{
  "type": "Feature",
  "properties": {
    "iso:country":"AU",
    "sg:address":"18 Torrens Rd",
    "sg:city":"Murray Bridge",
    "sg:classifiers":[
        {
            "category":"Building & Trades",
            "subcategory":"Construction",
            "type":"Services"
        }
    ],
    "sg:phone":"+61 417 870 693",
    "sg:postcode":"5253",
    "sg:province":"SA",
    "sg:tags":[
        "contractor"
    ],
    "wof:name":"Grundy Stuart",
    "wof:placetype":"venue"
},
  "geometry": {"coordinates":[139.30155944800001,-35.09815979],"type":"Point"}
}