{
  "type": "Feature",
  "properties": {
    "iso:country":"AU",
    "sg:address":"864 Burke Rd",
    "sg:city":"Canterbury",
    "sg:classifiers":[
        {
            "category":"Health Services",
            "subcategory":"Health Practitioner",
            "type":"Services"
        }
    ],
    "sg:phone":"+61 3 9882 6798",
    "sg:postcode":"3126",
    "sg:province":"VIC",
    "sg:tags":[
        "acupuncture"
    ],
    "wof:name":"Dr A.D. Winter",
    "wof:placetype":"venue"
},
  "geometry": {"coordinates":[145.05909729000001,-37.819606781],"type":"Point"}
}