{
  "type": "Feature",
  "properties": {
    "addr:full":"U 2/ 2938 Logan Rd Underwood QLD 4119",
    "addr:housenumber":"/ 2938",
    "addr:postcode":"4119",
    "addr:street":"Logan Rd",
    "iso:country":"AU",
    "sg:address":"U 2/ 2938 Logan Rd",
    "sg:city":"Underwood",
    "sg:classifiers":[
        {
            "category":"Retail",
            "subcategory":"Repair Shop",
            "type":"Services"
        }
    ],
    "sg:phone":"+61 7 3341 2663",
    "sg:postcode":"4119",
    "sg:province":"QLD",
    "sg:tags":[
        "machine",
        "repairs",
        "part",
        "dryer",
        "washing"
    ],
    "wof:name":"Mt Gravatt Washing Machine Centre",
    "wof:placetype":"venue"
},
  "geometry": {"coordinates":[153.11343383799999,-27.6090888977],"type":"Point"}
}