{
  "type": "Feature",
  "properties": {
    "iso:country":"AU",
    "sg:address":"15 Armidale St",
    "sg:city":"Norwood",
    "sg:classifiers":[
        {
            "category":"Organizations",
            "subcategory":"Membership Organization",
            "type":"Services"
        }
    ],
    "sg:phone":"+61 3 6343 1561",
    "sg:postcode":"7250",
    "sg:province":"TAS",
    "sg:tags":[
        "club",
        "car"
    ],
    "wof:name":"Jaguar Car Club of Tasmania",
    "wof:placetype":"venue"
},
  "geometry": {"coordinates":[147.17964172399999,-41.4600334167],"type":"Point"}
}