{
  "type": "Feature",
  "properties": {
    "addr:full":"Shop P3 Springfield Fair, 16 Springfield Parkway, Springfield QLD 4300",
    "addr:housenumber":"16",
    "addr:postcode":"4300",
    "addr:street":"Fair;Springfield Parkway",
    "iso:country":"AU",
    "sg:address":"Shop P3 Springfield Fair, 16",
    "sg:city":"Springfield Parkway, Springfield",
    "sg:classifiers":[
        {
            "category":"Banks & Credit Unions",
            "subcategory":"Financial Services",
            "type":"Services"
        }
    ],
    "sg:phone":"+61 7 3818 8277",
    "sg:postcode":"4300",
    "sg:province":"QLD",
    "sg:tags":[
        "loan",
        "finance",
        "mortgage"
    ],
    "wof:name":"Wizard",
    "wof:placetype":"venue"
},
  "geometry": {"coordinates":[152.91900634800001,-27.6539802551],"type":"Point"}
}