{
  "type": "Feature",
  "properties": {
    "addr:full":"1 Moore Rd Airport West VIC 3042",
    "addr:housenumber":"1",
    "addr:postcode":"3042",
    "addr:street":"Moore Rd",
    "iso:country":"AU",
    "sg:address":"1 Moore Rd",
    "sg:city":"Airport West",
    "sg:classifiers":[
        {
            "category":"Retail",
            "subcategory":"Auto Repair",
            "type":"Services"
        }
    ],
    "sg:phone":"+61 3 9338 7779",
    "sg:postcode":"3042",
    "sg:province":"VIC",
    "sg:tags":[
        "beater",
        "painter",
        "panel"
    ],
    "wof:name":"Drome Smash Repairs",
    "wof:placetype":"venue"
},
  "geometry": {"coordinates":[144.89190673799999,-37.7171401978],"type":"Point"}
}