{
  "type": "Feature",
  "properties": {
    "addr:full":"198 Paradise Rd Willawong QLD 4110",
    "addr:housenumber":"198",
    "addr:postcode":"4110",
    "addr:street":"Paradise Rd",
    "iso:country":"AU",
    "sg:address":"198 Paradise Rd",
    "sg:city":"Willawong",
    "sg:classifiers":[
        {
            "category":"Utilities",
            "type":"Services"
        }
    ],
    "sg:phone":"+61 7 3273 2999",
    "sg:postcode":"4110",
    "sg:province":"QLD",
    "sg:tags":[
        "refrigeration",
        "industrial",
        "commercial",
        "retail"
    ],
    "wof:name":"Koldtek Australia",
    "wof:placetype":"venue"
},
  "geometry": {"coordinates":[153.02687072800001,-27.6038513184],"type":"Point"}
}