{
  "type": "Feature",
  "properties": {
    "addr:full":"370 Victoria Ave Chatswood NSW 2067",
    "addr:housenumber":"370",
    "addr:postcode":"2067",
    "addr:street":"Victoria Ave",
    "iso:country":"AU",
    "sg:address":"370 Victoria Ave",
    "sg:city":"Chatswood",
    "sg:classifiers":[
        {
            "category":"Personal",
            "subcategory":"Beauty Salon",
            "type":"Services"
        }
    ],
    "sg:phone":"+61 2 9412 3392",
    "sg:postcode":"2067",
    "sg:province":"NSW",
    "sg:tags":[
        "hairdresser"
    ],
    "wof:name":"Ivans Hairdressers",
    "wof:placetype":"venue"
},
  "geometry": {"coordinates":[151.18354797399999,-33.7962760925],"type":"Point"}
}