{
  "type": "Feature",
  "properties": {
    "addr:full":"Shop 2/ 85 Barney St Barney Point QLD 4680",
    "addr:housenumber":"shop 2 / 85",
    "addr:postcode":"4680",
    "addr:street":"Barney St",
    "iso:country":"AU",
    "sg:address":"Shop 2/ 85 Barney St",
    "sg:city":"Barney Point",
    "sg:classifiers":[
        {
            "category":"Food & Beverages",
            "subcategory":"Fruits & Vegetables",
            "type":"Retail Goods"
        }
    ],
    "sg:phone":"+61 7 4972 3873",
    "sg:postcode":"4680",
    "sg:province":"QLD",
    "sg:tags":[
        "greengrocer",
        "fruiterer"
    ],
    "wof:name":"Gladstone Fruit Shop",
    "wof:placetype":"venue"
},
  "geometry": {"coordinates":[151.27265930199999,-23.8501548767],"type":"Point"}
}