{
  "type": "Feature",
  "properties": {
    "addr:full":"45 Ryhill Rd Sunnybank Hills QLD 4109",
    "addr:housenumber":"45",
    "addr:postcode":"4109",
    "addr:street":"Ryhill Rd",
    "iso:country":"AU",
    "sg:address":"45 Ryhill Rd",
    "sg:city":"Sunnybank Hills",
    "sg:classifiers":[
        {
            "category":"Professional",
            "subcategory":"Accounting & Tax Preparation",
            "type":"Services"
        }
    ],
    "sg:phone":"+61 7 3345 8426",
    "sg:postcode":"4109",
    "sg:province":"QLD",
    "sg:tags":[
        "bookkeeping"
    ],
    "wof:name":"Milne Office Management",
    "wof:placetype":"venue"
},
  "geometry": {"coordinates":[153.041183472,-27.5790157318],"type":"Point"}
}