{
  "type": "Feature",
  "properties": {
    "addr:full":"2 Ivanhoe Pl North Parramatta NSW 2151",
    "addr:housenumber":"2",
    "addr:postcode":"2151",
    "addr:street":"Ivanhoe Pl",
    "iso:country":"AU",
    "sg:address":"2 Ivanhoe Pl",
    "sg:city":"North Parramatta",
    "sg:classifiers":[
        {
            "category":"Education",
            "subcategory":"Special Training",
            "type":"Public Place"
        }
    ],
    "sg:phone":"+61 2 9630 4850",
    "sg:postcode":"2151",
    "sg:province":"NSW",
    "sg:tags":[
        "development"
    ],
    "wof:name":"Strategos Pty Ltd",
    "wof:placetype":"venue"
},
  "geometry": {"coordinates":[151.018112183,-33.7969169617],"type":"Point"}
}