{
  "type": "Feature",
  "properties": {
    "addr:full":"Mt Warren Blv Mt Warren Park QLD 4207",
    "addr:postcode":"4207",
    "addr:street":"Warren Blv Mt Warren",
    "iso:country":"AU",
    "sg:address":"Mt Warren Blv",
    "sg:city":"Mt Warren Park",
    "sg:classifiers":[
        {
            "category":"Fast Food",
            "type":"Food & Drink"
        }
    ],
    "sg:phone":"+61 7 3807 4658",
    "sg:postcode":"4207",
    "sg:province":"QLD",
    "sg:tags":[
        "away",
        "take"
    ],
    "wof:name":"Brodies B.B.Q. Chicken & Beef Burgers",
    "wof:placetype":"venue"
},
  "geometry": {"coordinates":[153.133499145,-27.6790904999],"type":"Point"}
}