{
  "type": "Feature",
  "properties": {
    "addr:full":"111 High St Wauchope NSW 2446",
    "addr:housenumber":"111",
    "addr:postcode":"2446",
    "addr:street":"High St",
    "iso:country":"AU",
    "sg:address":"111 High St",
    "sg:city":"Wauchope",
    "sg:classifiers":[
        {
            "category":"Fast Food",
            "type":"Food & Drink"
        }
    ],
    "sg:phone":"+61 2 6585 3273",
    "sg:postcode":"2446",
    "sg:province":"NSW",
    "sg:tags":[
        "away",
        "take"
    ],
    "wof:name":"Wauchope Country Kitchen",
    "wof:placetype":"venue"
},
  "geometry": {"coordinates":[152.72306800000001,-31.461878],"type":"Point"}
}