{
  "type": "Feature",
  "properties": {
    "iso:country":"AU",
    "sg:address":"6 Ollerton Ave",
    "sg:city":"Moe",
    "sg:classifiers":[
        {
            "category":"Retail",
            "subcategory":"Funeral Services",
            "type":"Services"
        }
    ],
    "sg:phone":"+61 3 5126 1111",
    "sg:postcode":"3825",
    "sg:province":"VIC",
    "sg:tags":[
        "director"
    ],
    "wof:name":"Leckey John F",
    "wof:placetype":"venue"
},
  "geometry": {"coordinates":[146.27803,-38.182709],"type":"Point"}
}