{
  "type": "Feature",
  "properties": {
    "iso:country":"AU",
    "sg:address":"Unit 1, 40 Douglas St",
    "sg:city":"Milton",
    "sg:classifiers":[
        {
            "category":"Utilities",
            "subcategory":"Telephone",
            "type":"Services"
        }
    ],
    "sg:phone":"+61 7 3369 5111",
    "sg:postcode":"4064",
    "sg:province":"QLD",
    "wof:name":"GAP Telecoms",
    "wof:placetype":"venue"
},
  "geometry": {"coordinates":[153.00367736800001,-27.4718093872],"type":"Point"}
}