{
  "type": "Feature",
  "properties": {
    "iso:country":"AU",
    "sg:address":"63 Plant St",
    "sg:city":"Charters Towers",
    "sg:classifiers":[
        {
            "category":"Health Services",
            "subcategory":"Health Practitioner",
            "type":"Services"
        }
    ],
    "sg:phone":"+61 412 776 992",
    "sg:postcode":"4820",
    "sg:province":"QLD",
    "sg:tags":[
        "alternative"
    ],
    "wof:name":"Morris Olive L",
    "wof:placetype":"venue"
},
  "geometry": {"coordinates":[146.260391,-20.068369],"type":"Point"}
}