{
  "type": "Feature",
  "properties": {
    "iso:country":"AU",
    "sg:address":"Level 16 Chancery House 37 St Georges Tce",
    "sg:city":"Perth",
    "sg:classifiers":[
        {
            "category":"Professional",
            "subcategory":"Computer Services",
            "type":"Services"
        }
    ],
    "sg:phone":"+61 8 9220 4000",
    "sg:postcode":"6000",
    "sg:province":"WA",
    "sg:tags":[
        "consultant",
        "system"
    ],
    "wof:name":"Logical Systems (Aust) Pty Ltd",
    "wof:placetype":"venue"
},
  "geometry": {"coordinates":[115.859542847,-31.9558258057],"type":"Point"}
}