{
  "type": "Feature",
  "properties": {
    "iso:country":"AU",
    "sg:address":"Shop 4/ 77A Scarborough St",
    "sg:city":"Southport",
    "sg:classifiers":[
        {
            "category":"Personal",
            "subcategory":"Beauty Salon",
            "type":"Services"
        }
    ],
    "sg:phone":"+61 7 5591 8288",
    "sg:postcode":"4215",
    "sg:province":"QLD",
    "sg:tags":[
        "hairdresser"
    ],
    "wof:name":"Structcha",
    "wof:placetype":"venue"
},
  "geometry": {"coordinates":[153.41464233400001,-27.9682788849],"type":"Point"}
}