{
  "type": "Feature",
  "properties": {
    "addr:full":"28 Logan Rd Woolloongabba QLD 4102",
    "addr:housenumber":"28",
    "addr:postcode":"4102",
    "addr:street":"Logan Rd",
    "iso:country":"AU",
    "sg:address":"28 Logan Rd",
    "sg:city":"Woolloongabba",
    "sg:classifiers":[
        {
            "category":"Personal",
            "subcategory":"Beauty Salon",
            "type":"Services"
        }
    ],
    "sg:phone":"+61 7 3391 1220",
    "sg:postcode":"4102",
    "sg:province":"QLD",
    "sg:tags":[
        "hairdresser"
    ],
    "wof:name":"Directors Cut The",
    "wof:placetype":"venue"
},
  "geometry": {"coordinates":[153.03808593799999,-27.4885864258],"type":"Point"}
}