{
  "type": "Feature",
  "properties": {
    "iso:country":"AU",
    "sg:address":"Shp6/ 44 Third Ave",
    "sg:city":"Marsden",
    "sg:classifiers":[
        {
            "category":"Food & Beverages",
            "subcategory":"Groceries & Convenience Stores",
            "type":"Retail Goods"
        }
    ],
    "sg:phone":"+61 7 3803 2136",
    "sg:postcode":"4132",
    "sg:province":"QLD",
    "wof:name":"Yi Asian Grocery & Video Store",
    "wof:placetype":"venue"
},
  "geometry": {"coordinates":[153.08921814000001,-27.6773147583],"type":"Point"}
}