{
  "type": "Feature",
  "properties": {
    "iso:country":"AU",
    "sg:address":"U 4/ 3 Industry Pl",
    "sg:city":"Capalaba",
    "sg:classifiers":[
        {
            "category":"Food & Beverages",
            "subcategory":"Groceries & Convenience Stores",
            "type":"Retail Goods"
        }
    ],
    "sg:phone":"+61 7 3823 5167",
    "sg:postcode":"4157",
    "sg:province":"QLD",
    "wof:name":"Good Nuts",
    "wof:placetype":"venue"
},
  "geometry": {"coordinates":[153.20681762699999,-27.5323810577],"type":"Point"}
}