{
  "type": "Feature",
  "properties": {
    "iso:country":"AU",
    "sg:address":"88 Colebee Crs",
    "sg:city":"Hassall Grove",
    "sg:classifiers":[
        {
            "category":"Wholesale",
            "subcategory":"Medical Equipment & Supplies",
            "type":"Manufacturing & Wholesale Goods"
        }
    ],
    "sg:phone":"+61 413 500 181",
    "sg:postcode":"2761",
    "sg:province":"NSW",
    "sg:tags":[
        "mfrs",
        "footwear"
    ],
    "wof:name":"Osy's leather machines service & sales",
    "wof:placetype":"venue"
},
  "geometry": {"coordinates":[150.871124,-33.723167],"type":"Point"}
}