{
  "type": "Feature",
  "properties": {
    "addr:full":"944 North Rd Bentleigh East VIC 3165",
    "addr:housenumber":"944",
    "addr:postcode":"3165",
    "addr:street":"North Rd",
    "iso:country":"AU",
    "sg:address":"944 North Rd",
    "sg:city":"Bentleigh East",
    "sg:classifiers":[
        {
            "category":"Retail",
            "subcategory":"Auto Repair",
            "type":"Services"
        }
    ],
    "sg:phone":"+61 3 9563 8877",
    "sg:postcode":"3165",
    "sg:province":"VIC",
    "sg:tags":[
        "beater",
        "painter",
        "panel"
    ],
    "wof:name":"Bernie Mack Motor Body Repairs",
    "wof:placetype":"venue"
},
  "geometry": {"coordinates":[145.06410217300001,-37.9069519043],"type":"Point"}
}