{
  "type": "Feature",
  "properties": {
    "addr:full":"57 Gawain Rd Bracken Ridge QLD 4017",
    "addr:housenumber":"57",
    "addr:postcode":"4017",
    "addr:street":"Gawain Rd",
    "iso:country":"AU",
    "sg:address":"57 Gawain Rd",
    "sg:city":"Bracken Ridge",
    "sg:classifiers":[
        {
            "category":"Health Services",
            "subcategory":"Dentist",
            "type":"Services"
        }
    ],
    "sg:phone":"+61 7 3261 4222",
    "sg:postcode":"4017",
    "sg:province":"QLD",
    "wof:name":"Garske Phil",
    "wof:placetype":"venue"
},
  "geometry": {"coordinates":[153.033081055,-27.3151931763],"type":"Point"}
}