{
  "type": "Feature",
  "properties": {
    "iso:country":"AU",
    "sg:address":"82 Griffith St",
    "sg:city":"Coolangatta",
    "sg:classifiers":[
        {
            "category":"Real Estate",
            "subcategory":"Real Estate Agent",
            "type":"Services"
        }
    ],
    "sg:phone":"+61 7 5599 5222",
    "sg:postcode":"4225",
    "sg:province":"QLD",
    "wof:name":"DJ Stringer Property Services",
    "wof:placetype":"venue"
},
  "geometry": {"coordinates":[153.538574219,-28.1686401367],"type":"Point"}
}