{
  "type": "Feature",
  "properties": {
    "iso:country":"AU",
    "sg:address":"35a Murray St",
    "sg:city":"Nuriootpa",
    "sg:classifiers":[
        {
            "category":"Shopping",
            "subcategory":"Computers & Home Electronics",
            "type":"Retail Goods"
        }
    ],
    "sg:phone":"+61 8 8562 1130",
    "sg:postcode":"5355",
    "sg:province":"SA",
    "sg:tags":[
        "equipment",
        "part",
        "electronic"
    ],
    "wof:name":"Super Snaps",
    "wof:placetype":"venue"
},
  "geometry": {"coordinates":[138.99623107900001,-34.4713935852],"type":"Point"}
}