{
  "type": "Feature",
  "properties": {
    "iso:country":"AU",
    "sg:address":"472 Sydney Rd",
    "sg:city":"Balgowlah",
    "sg:classifiers":[
        {
            "category":"Social Services",
            "subcategory":"Child Care",
            "type":"Services"
        }
    ],
    "sg:phone":"+61 2 9907 0877",
    "sg:postcode":"2093",
    "sg:province":"NSW",
    "wof:name":"Eco Preschools Balgowlah",
    "wof:placetype":"venue"
},
  "geometry": {"coordinates":[151.25697326700001,-33.7946891785],"type":"Point"}
}