{
  "type": "Feature",
  "properties": {
    "iso:country":"AU",
    "sg:address":"11 Brisbane St",
    "sg:city":"Bowen",
    "sg:classifiers":[
        {
            "category":"Social Services",
            "subcategory":"Child Care",
            "type":"Services"
        }
    ],
    "sg:phone":"+61 7 4786 1399",
    "sg:postcode":"4805",
    "sg:province":"QLD",
    "wof:name":"Bowen-Collinsville Family Day Care Association Inc.",
    "wof:placetype":"venue"
},
  "geometry": {"coordinates":[148.243377686,-20.0041561127],"type":"Point"}
}