{
  "type": "Feature",
  "properties": {
    "addr:full":"209 Watsons Rd Kettering TAS 7155",
    "addr:housenumber":"209",
    "addr:postcode":"7155",
    "addr:street":"Watsons Rd",
    "iso:country":"AU",
    "sg:address":"209 Watsons Rd",
    "sg:city":"Kettering",
    "sg:classifiers":[
        {
            "category":"Manufacturing",
            "subcategory":"Rubber & Plastics",
            "type":"Manufacturing & Wholesale Goods"
        }
    ],
    "sg:phone":"+61 3 6267 4404",
    "sg:postcode":"7155",
    "sg:province":"TAS",
    "sg:tags":[
        "moulders"
    ],
    "wof:name":"Roto Plas",
    "wof:placetype":"venue"
},
  "geometry": {"coordinates":[147.224319458,-43.1180534363],"type":"Point"}
}