{
  "type": "Feature",
  "properties": {
    "iso:country":"AU",
    "sg:address":"17 Ryans Crt",
    "sg:city":"Warragul",
    "sg:classifiers":[
        {
            "category":"Organizations",
            "subcategory":"Community Association",
            "type":"Services"
        }
    ],
    "sg:phone":"+61 3 5622 3887",
    "sg:postcode":"3820",
    "sg:province":"VIC",
    "sg:tags":[
        "cheese",
        "product"
    ],
    "wof:name":"Gippsland Cheese",
    "wof:placetype":"venue"
},
  "geometry": {"coordinates":[145.921906,-38.156979],"type":"Point"}
}