{
  "type": "Feature",
  "properties": {
    "iso:country":"AU",
    "sg:address":"2 Cran St",
    "sg:city":"Ashmore",
    "sg:classifiers":[
        {
            "category":"Organizations",
            "subcategory":"Professional Association",
            "type":"Services"
        }
    ],
    "sg:phone":"+61 7 5539 6116",
    "sg:postcode":"4214",
    "sg:province":"QLD",
    "sg:tags":[
        "web",
        "internet"
    ],
    "sg:website":"http://www.insane.net.au",
    "wof:name":"Insane Technologies",
    "wof:placetype":"venue"
},
  "geometry": {"coordinates":[153.37852477999999,-27.9803333282],"type":"Point"}
}