{
  "type": "Feature",
  "properties": {
    "addr:full":"88 Auburn Rd Auburn NSW 2144",
    "addr:housenumber":"88",
    "addr:postcode":"2144",
    "addr:street":"Auburn Rd",
    "iso:country":"AU",
    "sg:address":"88 Auburn Rd",
    "sg:city":"Auburn",
    "sg:classifiers":[
        {
            "category":"Fast Food",
            "type":"Food & Drink"
        }
    ],
    "sg:phone":"+61 2 9649 5553",
    "sg:postcode":"2144",
    "sg:province":"NSW",
    "sg:tags":[
        "away",
        "take"
    ],
    "wof:name":"Jamal Take Away Food",
    "wof:placetype":"venue"
},
  "geometry": {"coordinates":[151.03182983400001,-33.8564682007],"type":"Point"}
}