{
  "type": "Feature",
  "properties": {
    "iso:country":"AU",
    "sg:address":"10 -11 Livingstone Rd",
    "sg:city":"Rockingham",
    "sg:classifiers":[
        {
            "category":"Autos & Motor Vehicles",
            "subcategory":"Auto Supplies",
            "type":"Retail Goods"
        }
    ],
    "sg:phone":"+61 8 9527 4501",
    "sg:postcode":"6168",
    "sg:province":"WA",
    "sg:tags":[
        "accessory"
    ],
    "wof:name":"Autopro",
    "wof:placetype":"venue"
},
  "geometry": {"coordinates":[115.740646,-32.286602],"type":"Point"}
}