{
  "type": "Feature",
  "properties": {
    "iso:country":"AU",
    "sg:address":"Suite 3 333 King St",
    "sg:city":"Newtown",
    "sg:classifiers":[
        {
            "category":"Real Estate",
            "subcategory":"Architect",
            "type":"Services"
        }
    ],
    "sg:phone":"+61 2 9519 6299",
    "sg:postcode":"2042",
    "sg:province":"NSW",
    "sg:tags":[
        "building",
        "designer"
    ],
    "wof:name":"Nikita Designs",
    "wof:placetype":"venue"
},
  "geometry": {"coordinates":[151.178223,-33.898117],"type":"Point"}
}