{
  "type": "Feature",
  "properties": {
    "addr:full":"420 Joondalup Drv Joondalup WA 6027",
    "addr:housenumber":"420",
    "addr:postcode":"6027",
    "addr:street":"Joondalup Drv",
    "iso:country":"AU",
    "sg:address":"420 Joondalup Drv",
    "sg:city":"Joondalup",
    "sg:classifiers":[
        {
            "category":"Insurance",
            "subcategory":"Health Insurance",
            "type":"Services"
        }
    ],
    "sg:phone":"+61 13 23 31",
    "sg:postcode":"6027",
    "sg:province":"WA",
    "wof:name":"Medibank Private",
    "wof:placetype":"venue"
},
  "geometry": {"coordinates":[115.78199768099999,-31.7720222473],"type":"Point"}
}