{
  "type": "Feature",
  "properties": {
    "addr:full":"58 - 74 Station St Nunawading VIC 3131",
    "addr:housenumber":"74",
    "addr:postcode":"3131",
    "addr:street":"Station St",
    "iso:country":"AU",
    "sg:address":"58 - 74 Station St",
    "sg:city":"Nunawading",
    "sg:classifiers":[
        {
            "category":"Home & Garden",
            "subcategory":"Carpets & Floor Coverings",
            "type":"Retail Goods"
        }
    ],
    "sg:phone":"+61 3 9875 3000",
    "sg:postcode":"3131",
    "sg:province":"VIC",
    "sg:tags":[
        "tile",
        "wall"
    ],
    "sg:website":"http://www.danielrobertson.com.au",
    "wof:name":"Daniel Robertson Australia Pty Ltd",
    "wof:placetype":"venue"
},
  "geometry": {"coordinates":[145.17973327600001,-37.8201560974],"type":"Point"}
}