{
  "type": "Feature",
  "properties": {
    "addr:full":"Shop 17, Booval Fair Shopping Centre, Brisbane Rd Booval QLD 4304",
    "addr:housenumber":"shop 17",
    "addr:postcode":"4304",
    "addr:street":"Brisbane Rd",
    "iso:country":"AU",
    "sg:address":"Shop 17, Booval Fair Shopping Centre, Brisbane Rd",
    "sg:city":"Booval",
    "sg:classifiers":[
        {
            "category":"Food & Beverages",
            "subcategory":"Liquor & Beverages",
            "type":"Retail Goods"
        }
    ],
    "sg:phone":"+61 7 3202 4266",
    "sg:postcode":"4304",
    "sg:province":"QLD",
    "sg:tags":[
        "store"
    ],
    "wof:name":"Booval Fair",
    "wof:placetype":"venue"
},
  "geometry": {"coordinates":[152.78590393100001,-27.6139144897],"type":"Point"}
}