{
  "type": "Feature",
  "properties": {
    "iso:country":"AU",
    "sg:address":"Silverdale Rd",
    "sg:city":"Werombi",
    "sg:classifiers":[
        {
            "category":"Farming",
            "subcategory":"Livestock Farm",
            "type":"Manufacturing & Wholesale Goods"
        }
    ],
    "sg:phone":"+61 2 4653 1470",
    "sg:postcode":"2570",
    "sg:province":"NSW",
    "sg:tags":[
        "agistment"
    ],
    "wof:name":"Suncherry Stud",
    "wof:placetype":"venue"
},
  "geometry": {"coordinates":[150.57179260300001,-33.9808273315],"type":"Point"}
}