{
  "type": "Feature",
  "properties": {
    "iso:country":"AU",
    "sg:address":"101 Pelias St",
    "sg:city":"Exmouth",
    "sg:classifiers":[
        {
            "category":"Retail",
            "subcategory":"Auto Repair",
            "type":"Services"
        }
    ],
    "sg:phone":"+61 8 9949 2262",
    "sg:postcode":"6707",
    "sg:province":"WA",
    "sg:tags":[
        "electrical"
    ],
    "wof:name":"Exmouth Autoelectrics",
    "wof:placetype":"venue"
},
  "geometry": {"coordinates":[114.128547669,-21.9378452301],"type":"Point"}
}