{
  "type": "Feature",
  "properties": {
    "addr:full":"PO Box 330 Bassendean WA 6054",
    "addr:postcode":"6054",
    "iso:country":"AU",
    "sg:address":"PO Box 330",
    "sg:city":"Bassendean",
    "sg:classifiers":[
        {
            "category":"Real Estate",
            "subcategory":"Architect",
            "type":"Services"
        }
    ],
    "sg:phone":"+61 416 162 092",
    "sg:postcode":"6054",
    "sg:province":"WA",
    "sg:tags":[
        "building",
        "designer"
    ],
    "wof:name":"Macleod Design",
    "wof:placetype":"venue"
},
  "geometry": {"coordinates":[115.942138672,-31.9080696106],"type":"Point"}
}