{
  "type": "Feature",
  "properties": {
    "iso:country":"AU",
    "sg:address":"115 Kiora Rd",
    "sg:city":"Miranda",
    "sg:classifiers":[
        {
            "category":"Banks & Credit Unions",
            "subcategory":"Financial Services",
            "type":"Services"
        }
    ],
    "sg:phone":"+61 2 9526 1692",
    "sg:postcode":"2228",
    "sg:province":"NSW",
    "sg:tags":[
        "finance",
        "factoring"
    ],
    "wof:name":"M.B.R. Financial Services Pty Ltd",
    "wof:placetype":"venue"
},
  "geometry": {"coordinates":[151.100952148,-34.0395584106],"type":"Point"}
}