{
  "type": "Feature",
  "properties": {
    "iso:country":"AU",
    "sg:address":"218 Huntingdale St",
    "sg:city":"Pullenvale",
    "sg:classifiers":[
        {
            "category":"Shopping",
            "subcategory":"Bicycles & Sporting Goods",
            "type":"Retail Goods"
        }
    ],
    "sg:phone":"+61 7 3374 3681",
    "sg:postcode":"4069",
    "sg:province":"QLD",
    "sg:tags":[
        "chemical",
        "equipment",
        "pool",
        "swimming"
    ],
    "wof:name":"Poolskim Australia Pty Ltd",
    "wof:placetype":"venue"
},
  "geometry": {"coordinates":[152.896575928,-27.5202045441],"type":"Point"}
}