{
  "type": "Feature",
  "properties": {
    "addr:full":"94 Wyee Rd Wyee NSW 2259",
    "addr:housenumber":"94",
    "addr:postcode":"2259",
    "addr:street":"Wyee Rd",
    "iso:country":"AU",
    "sg:address":"94 Wyee Rd",
    "sg:city":"Wyee",
    "sg:classifiers":[
        {
            "category":"Building & Trades",
            "subcategory":"Construction",
            "type":"Services"
        }
    ],
    "sg:phone":"+61 429 668 305",
    "sg:postcode":"2259",
    "sg:province":"NSW",
    "sg:tags":[
        "earth",
        "excavating",
        "moving",
        "contractor"
    ],
    "wof:name":"Tight Spots",
    "wof:placetype":"venue"
},
  "geometry": {"coordinates":[151.47767639200001,-33.1714859009],"type":"Point"}
}