{
  "type": "Feature",
  "properties": {
    "addr:full":"31 Enterprise St Caloundra QLD 4551",
    "addr:housenumber":"31",
    "addr:postcode":"4551",
    "addr:street":"Enterprise St",
    "iso:country":"AU",
    "sg:address":"31 Enterprise St",
    "sg:city":"Caloundra",
    "sg:classifiers":[
        {
            "category":"Bus Stop",
            "subcategory":"None",
            "type":"Transportation"
        }
    ],
    "sg:phone":"+61 7 5492 7122",
    "sg:postcode":"4551",
    "sg:province":"QLD",
    "sg:tags":[
        "metallizing"
    ],
    "wof:name":"Hyqual Australia",
    "wof:placetype":"venue"
},
  "geometry": {"coordinates":[153.115325928,-26.7951889038],"type":"Point"}
}