{
  "type": "Feature",
  "properties": {
    "iso:country":"AU",
    "sg:address":"1 Duckworth St",
    "sg:city":"Garbutt",
    "sg:classifiers":[
        {
            "category":"Professional",
            "type":"Services"
        }
    ],
    "sg:phone":"+61 7 4725 5500",
    "sg:postcode":"4814",
    "sg:province":"QLD",
    "sg:tags":[
        "transport"
    ],
    "wof:name":"LW & PJ Foster",
    "wof:placetype":"venue"
},
  "geometry": {"coordinates":[146.76048299999999,-19.264479],"type":"Point"}
}