{
  "type": "Feature",
  "properties": {
    "addr:full":"593 Briggs Rd Brighton TAS 7030",
    "addr:housenumber":"593",
    "addr:postcode":"7030",
    "addr:street":"Briggs Rd",
    "iso:country":"AU",
    "sg:address":"593 Briggs Rd",
    "sg:city":"Brighton",
    "sg:classifiers":[
        {
            "category":"Park",
            "subcategory":"County",
            "type":"Public Place"
        }
    ],
    "sg:phone":"+61 3 6268 1184",
    "sg:postcode":"7030",
    "sg:province":"TAS",
    "sg:tags":[
        "sanctuary",
        "zoos",
        "animal"
    ],
    "wof:name":"Bonorong Wildlife Park",
    "wof:placetype":"venue"
},
  "geometry": {"coordinates":[147.268600464,-42.701084137],"type":"Point"}
}