{
  "type": "Feature",
  "properties": {
    "addr:full":"Shop 201a Level 2 2 Quay St Haymarket NSW 2000",
    "addr:housenumber":"201a level;2",
    "addr:postcode":"2000",
    "addr:street":"Quay St",
    "iso:country":"AU",
    "sg:address":"Shop 201a Level 2 2 Quay St",
    "sg:city":"Haymarket",
    "sg:classifiers":[
        {
            "category":"Shopping",
            "subcategory":"Clothing, Apparel, & Fashions",
            "type":"Retail Goods"
        }
    ],
    "sg:phone":"+61 2 9281 9431",
    "sg:postcode":"2000",
    "sg:province":"NSW",
    "sg:tags":[
        "menswear"
    ],
    "wof:name":"Baymen Menswear",
    "wof:placetype":"venue"
},
  "geometry": {"coordinates":[151.202957153,-33.8806610107],"type":"Point"}
}