{
  "type": "Feature",
  "properties": {
    "addr:full":"18 Minerva Ave Mooroobool QLD 4870",
    "addr:housenumber":"18",
    "addr:postcode":"4870",
    "addr:street":"Minerva Ave",
    "iso:country":"AU",
    "sg:address":"18 Minerva Ave",
    "sg:city":"Mooroobool",
    "sg:classifiers":[
        {
            "category":"Professional",
            "subcategory":"Accounting & Tax Preparation",
            "type":"Services"
        }
    ],
    "sg:phone":"+61 7 4054 5938",
    "sg:postcode":"4870",
    "sg:province":"QLD",
    "sg:tags":[
        "consultant",
        "taxation"
    ],
    "wof:name":"Kochan Irene",
    "wof:placetype":"venue"
},
  "geometry": {"coordinates":[145.72430419899999,-16.941783905],"type":"Point"}
}