{
  "type": "Feature",
  "properties": {
    "addr:full":"64 Island View Rd The Gurdies VIC 3984",
    "addr:housenumber":"64",
    "addr:postcode":"3984",
    "addr:street":"Island View Rd",
    "iso:country":"AU",
    "sg:address":"64 Island View Rd",
    "sg:city":"The Gurdies",
    "sg:classifiers":[
        {
            "category":"Wholesale",
            "subcategory":"Toys & Hobbies",
            "type":"Manufacturing & Wholesale Goods"
        }
    ],
    "sg:phone":"+61 3 5997 6256",
    "sg:postcode":"3984",
    "sg:province":"VIC",
    "wof:name":"Retro Skill Products",
    "wof:placetype":"venue"
},
  "geometry": {"coordinates":[145.571655273,-38.3702201843],"type":"Point"}
}