{
  "type": "Feature",
  "properties": {
    "addr:full":"PO Box 16 West Pennant Hills 2125 West Pennant Hills NSW 2125",
    "addr:housenumber":"2125",
    "addr:postcode":"2125",
    "iso:country":"AU",
    "sg:address":"PO Box 16 West Pennant Hills 2125",
    "sg:city":"West Pennant Hills",
    "sg:classifiers":[
        {
            "category":"Building & Trades",
            "subcategory":"Landscaping Services",
            "type":"Services"
        }
    ],
    "sg:phone":"+61 2 9836 2999",
    "sg:postcode":"2125",
    "sg:province":"NSW",
    "sg:tags":[
        "designer",
        "landscape",
        "contractor"
    ],
    "wof:name":"Rob Turner Fencing",
    "wof:placetype":"venue"
},
  "geometry": {"coordinates":[151.04940795900001,-33.7487258911],"type":"Point"}
}