{
  "type": "Feature",
  "properties": {
    "addr:full":"Shp 3c/ 42 Spine St Sumner Park QLD 4074",
    "addr:housenumber":"3c / 42",
    "addr:postcode":"4074",
    "addr:street":"Spine St",
    "iso:country":"AU",
    "sg:address":"Shp 3c/ 42 Spine St",
    "sg:city":"Sumner Park",
    "sg:phone":"+61 7 3712 0622",
    "sg:postcode":"4074",
    "sg:province":"QLD",
    "wof:name":"Pottery Plus Australia",
    "wof:placetype":"venue"
},
  "geometry": {"coordinates":[152.935272217,-27.5624370575],"type":"Point"}
}