{
  "type": "Feature",
  "properties": {
    "addr:full":"112- 118 Carbrook Rd Cornubia QLD 4130",
    "addr:housenumber":"118",
    "addr:postcode":"4130",
    "addr:street":"Carbrook Rd",
    "iso:country":"AU",
    "sg:address":"112- 118 Carbrook Rd",
    "sg:city":"Cornubia",
    "sg:classifiers":[
        {
            "category":"Health Services",
            "subcategory":"Health Practitioner",
            "type":"Services"
        }
    ],
    "sg:phone":"+61 7 3287 6599",
    "sg:postcode":"4130",
    "sg:province":"QLD",
    "sg:tags":[
        "hypnotherapy"
    ],
    "wof:name":"Hellene Demos Hypnosis Clinic",
    "wof:placetype":"venue"
},
  "geometry": {"coordinates":[153.22177124000001,-27.6684589386],"type":"Point"}
}