{
  "type": "Feature",
  "properties": {
    "iso:country":"AU",
    "sg:address":"6 Brandy Creek Rd",
    "sg:city":"Warragul",
    "sg:classifiers":[
        {
            "category":"Social Services",
            "type":"Services"
        }
    ],
    "sg:phone":"+61 3 5623 1685",
    "sg:postcode":"3820",
    "sg:province":"VIC",
    "sg:tags":[
        "kinesiology"
    ],
    "wof:name":"Warragul Kinesiology Centre",
    "wof:placetype":"venue"
},
  "geometry": {"coordinates":[145.93542500000001,-38.15173],"type":"Point"}
}