{
  "type": "Feature",
  "properties": {
    "iso:country":"AU",
    "sg:address":"71 Clarkson Rd",
    "sg:city":"Morley",
    "sg:classifiers":[
        {
            "category":"Professional",
            "subcategory":"Detective & Security Services",
            "type":"Services"
        }
    ],
    "sg:phone":"+61 8 9375 1722",
    "sg:postcode":"6062",
    "sg:province":"WA",
    "sg:tags":[
        "domestic",
        "alarm",
        "commercial",
        "burglar"
    ],
    "wof:name":"Alarm Batteries Changed, Service & Monitoring",
    "wof:placetype":"venue"
},
  "geometry": {"coordinates":[115.896888733,-31.8942699432],"type":"Point"}
}