{
  "type": "Feature",
  "properties": {
    "iso:country":"AU",
    "sg:address":"Deepwater Plaza Shop 34 Railway St",
    "sg:city":"Woy Woy",
    "sg:classifiers":[
        {
            "category":"Shopping",
            "type":"Retail Goods"
        }
    ],
    "sg:phone":"+61 2 4342 8366",
    "sg:postcode":"2256",
    "sg:province":"NSW",
    "sg:tags":[
        "repair",
        "travel"
    ],
    "wof:name":"Strandbags",
    "wof:placetype":"venue"
},
  "geometry": {"coordinates":[151.303665161,-33.4978981018],"type":"Point"}
}