{
  "type": "Feature",
  "properties": {
    "iso:country":"AU",
    "sg:address":"Prince St",
    "sg:city":"Port Pirie",
    "sg:classifiers":[
        {
            "category":"Education",
            "subcategory":"Kindergarten",
            "type":"Public Place"
        }
    ],
    "sg:phone":"+61 8 8632 3800",
    "sg:postcode":"5540",
    "sg:province":"SA",
    "sg:tags":[
        "pre-schools"
    ],
    "wof:name":"Solomontown Kindergarten",
    "wof:placetype":"venue"
},
  "geometry": {"coordinates":[138.014526367,-33.186340332],"type":"Point"}
}