{
  "type": "Feature",
  "properties": {
    "addr:full":"Lot 238 Industrial Cl Muswellbrook NSW 2333",
    "addr:postcode":"2333",
    "addr:street":"Industrial",
    "iso:country":"AU",
    "sg:address":"Lot 238",
    "sg:city":"Industrial Cl Muswellbrook",
    "sg:classifiers":[
        {
            "category":"Retail",
            "subcategory":"Repair Shop",
            "type":"Services"
        }
    ],
    "sg:phone":"+61 2 6541 5200",
    "sg:postcode":"2333",
    "sg:province":"NSW",
    "sg:tags":[
        "leadlights"
    ],
    "wof:name":"Valley Leadlights",
    "wof:placetype":"venue"
},
  "geometry": {"coordinates":[150.88752746599999,-32.2689208984],"type":"Point"}
}