{
  "type": "Feature",
  "properties": {
    "addr:full":"41 Kialla Lakes Drv Kialla VIC 3631",
    "addr:housenumber":"41",
    "addr:postcode":"3631",
    "addr:street":"Kialla Lakes Drv",
    "iso:country":"AU",
    "sg:address":"41 Kialla Lakes Drv",
    "sg:city":"Kialla",
    "sg:classifiers":[
        {
            "category":"Building & Trades",
            "subcategory":"Landscaping Services",
            "type":"Services"
        }
    ],
    "sg:phone":"+61 3 5823 2209",
    "sg:postcode":"3631",
    "sg:province":"VIC",
    "sg:tags":[
        "stump",
        "tree",
        "felling",
        "removal"
    ],
    "wof:name":"Mark Jeffery Tree Stump Removal",
    "wof:placetype":"venue"
},
  "geometry": {"coordinates":[145.39910888700001,-36.4144172668],"type":"Point"}
}