{
  "type": "Feature",
  "properties": {
    "addr:full":"Lvl 3 Comalco Place Brisbane QLD 4000",
    "addr:postcode":"4000",
    "addr:street":"Place",
    "iso:country":"AU",
    "sg:address":"Lvl 3",
    "sg:city":"Comalco Place Brisbane",
    "sg:classifiers":[
        {
            "category":"Insurance",
            "subcategory":"Insurance Agent",
            "type":"Services"
        }
    ],
    "sg:phone":"+61 7 3246 7590",
    "sg:postcode":"4000",
    "sg:province":"QLD",
    "sg:tags":[
        "broker"
    ],
    "wof:name":"Jardine Lloyd Thompson Pty Ltd",
    "wof:placetype":"venue"
},
  "geometry": {"coordinates":[153.02276611299999,-27.4651203156],"type":"Point"}
}