{
  "type": "Feature",
  "properties": {
    "addr:full":"Kiosk 106 Airport West Shopng Cntr 23 Louis St Airport West VIC 3042",
    "addr:housenumber":"106;23",
    "addr:postcode":"3042",
    "addr:street":"Cntr;Louis St",
    "iso:country":"AU",
    "sg:address":"Kiosk 106 Airport West Shopng Cntr 23 Louis St",
    "sg:city":"Airport West",
    "sg:classifiers":[
        {
            "category":"Food & Beverages",
            "subcategory":"Bakery",
            "type":"Retail Goods"
        }
    ],
    "sg:phone":"+61 3 9330 2661",
    "sg:postcode":"3042",
    "sg:province":"VIC",
    "sg:tags":[
        "cake",
        "shop",
        "pastry"
    ],
    "wof:name":"Michel's Patisserie",
    "wof:placetype":"venue"
},
  "geometry": {"coordinates":[144.888305664,-37.7149581909],"type":"Point"}
}