{
  "type": "Feature",
  "properties": {
    "iso:country":"AU",
    "sg:address":"31 Outrigger Drv",
    "sg:city":"Inverloch",
    "sg:classifiers":[
        {
            "category":"Real Estate",
            "subcategory":"Surveying",
            "type":"Services"
        }
    ],
    "sg:phone":"+61 3 9707 4117",
    "sg:postcode":"3996",
    "sg:province":"VIC",
    "sg:tags":[
        "surveyor",
        "land"
    ],
    "wof:name":"M.J. Reddie Surveys Pty Ltd",
    "wof:placetype":"venue"
},
  "geometry": {"coordinates":[145.705933,-38.641182],"type":"Point"}
}