{
  "type": "Feature",
  "properties": {
    "addr:full":"Cnr Fleming St & Kirkdale Rd Chapel Hill QLD 4069",
    "addr:postcode":"4069",
    "addr:street":"Cnr Fleming St & Kirkdale Rd",
    "iso:country":"AU",
    "sg:address":"Cnr Fleming St & Kirkdale Rd",
    "sg:city":"Chapel Hill",
    "sg:classifiers":[
        {
            "category":"Food & Beverages",
            "subcategory":"Supermarket",
            "type":"Retail Goods"
        }
    ],
    "sg:phone":"+61 7 3878 6344",
    "sg:postcode":"4069",
    "sg:province":"QLD",
    "sg:tags":[
        "grocery",
        "store"
    ],
    "wof:name":"IGA X-Press",
    "wof:placetype":"venue"
},
  "geometry": {"coordinates":[152.94563293499999,-27.496761322],"type":"Point"}
}