{
  "type": "Feature",
  "properties": {
    "addr:full":"160 Bridge Rd Richmond VIC 3121",
    "addr:housenumber":"160",
    "addr:postcode":"3121",
    "addr:street":"Bridge Rd",
    "iso:country":"AU",
    "sg:address":"160 Bridge Rd",
    "sg:city":"Richmond",
    "sg:classifiers":[
        {
            "category":"Shopping",
            "subcategory":"Shoes",
            "type":"Retail Goods"
        }
    ],
    "sg:phone":"+61 3 9429 9660",
    "sg:postcode":"3121",
    "sg:province":"VIC",
    "sg:tags":[
        "footwear"
    ],
    "wof:name":"Emco Shoes",
    "wof:placetype":"venue"
},
  "geometry": {"coordinates":[144.995895386,-37.8183364868],"type":"Point"}
}