{
  "type": "Feature",
  "properties": {
    "iso:country":"AU",
    "sg:address":"3 Oakleigh Rd",
    "sg:city":"Darlington",
    "sg:classifiers":[
        {
            "category":"Professional",
            "subcategory":"Management & Consulting",
            "type":"Services"
        }
    ],
    "sg:phone":"+61 8 9299 8484",
    "sg:postcode":"6070",
    "sg:province":"WA",
    "sg:tags":[
        "consultant",
        "educational"
    ],
    "wof:name":"Snedden Clare",
    "wof:placetype":"venue"
},
  "geometry": {"coordinates":[116.08561706499999,-31.9298706055],"type":"Point"}
}