{
  "type": "Feature",
  "properties": {
    "addr:full":"Sunshine Plaza, Horton Pde Maroochydore QLD 4558",
    "addr:postcode":"4558",
    "addr:street":"Horton Pde",
    "iso:country":"AU",
    "sg:address":"Sunshine Plaza, Horton Pde",
    "sg:city":"Maroochydore",
    "sg:classifiers":[
        {
            "category":"Utilities",
            "subcategory":"Telephone",
            "type":"Services"
        }
    ],
    "sg:phone":"+61 13 80 00",
    "sg:postcode":"4558",
    "sg:province":"QLD",
    "sg:tags":[
        "accessory"
    ],
    "wof:name":"Allphones",
    "wof:placetype":"venue"
},
  "geometry": {"coordinates":[153.089675903,-26.6531066895],"type":"Point"}
}