{
  "type": "Feature",
  "properties": {
    "addr:full":"50 Stuart Hwy Stuart Park NT 0820",
    "addr:housenumber":"50",
    "addr:postcode":"nt 0820",
    "addr:street":"Stuart Hwy Stuart",
    "iso:country":"AU",
    "sg:address":"50 Stuart Hwy",
    "sg:city":"Stuart Park",
    "sg:classifiers":[
        {
            "category":"Banks & Credit Unions",
            "subcategory":"Atm",
            "type":"Services"
        }
    ],
    "sg:phone":"+61 8 8981 3449",
    "sg:postcode":"0820",
    "sg:province":"NT",
    "sg:tags":[
        "wholesaler",
        "mfrs",
        "envelope"
    ],
    "wof:name":"Darwin Printing",
    "wof:placetype":"venue"
},
  "geometry": {"coordinates":[130.84124755900001,-12.4458866119],"type":"Point"}
}