{
  "type": "Feature",
  "properties": {
    "addr:full":"Unit 10 2 Ethel Rd Kirrawee NSW 2232",
    "addr:housenumber":"2",
    "addr:postcode":"2232",
    "addr:street":"Ethel Rd",
    "iso:country":"AU",
    "sg:address":"Unit 10 2 Ethel Rd",
    "sg:city":"Kirrawee",
    "sg:classifiers":[
        {
            "category":"Professional",
            "subcategory":"Engineering",
            "type":"Services"
        }
    ],
    "sg:phone":"+61 2 9545 1500",
    "sg:postcode":"2232",
    "sg:province":"NSW",
    "sg:tags":[
        "engineer"
    ],
    "wof:name":"Stevenson J W & A Pty Ltd",
    "wof:placetype":"venue"
},
  "geometry": {"coordinates":[151.08116149899999,-34.0243110657],"type":"Point"}
}