{
  "type": "Feature",
  "properties": {
    "addr:full":"27 Ilana View Drv Diamond Creek VIC 3089",
    "addr:housenumber":"27",
    "addr:postcode":"3089",
    "addr:street":"Ilana View Drv",
    "iso:country":"AU",
    "sg:address":"27 Ilana View Drv",
    "sg:city":"Diamond Creek",
    "sg:classifiers":[
        {
            "category":"Utilities",
            "subcategory":"Electric",
            "type":"Services"
        }
    ],
    "sg:phone":"+61 3 9438 5115",
    "sg:postcode":"3089",
    "sg:province":"VIC",
    "sg:tags":[
        "electrical",
        "contractor"
    ],
    "wof:name":"Bedurke Electrics",
    "wof:placetype":"venue"
},
  "geometry": {"coordinates":[145.172516,-37.669949],"type":"Point"}
}