{
  "type": "Feature",
  "properties": {
    "addr:full":"Herveys Range Rd Condon QLD 4815",
    "addr:postcode":"4815",
    "addr:street":"Range Rd",
    "iso:country":"AU",
    "sg:address":"Herveys Range Rd",
    "sg:city":"Condon",
    "sg:classifiers":[
        {
            "category":"Fast Food",
            "type":"Food & Drink"
        }
    ],
    "sg:phone":"+61 7 4755 1377",
    "sg:postcode":"4815",
    "sg:province":"QLD",
    "sg:tags":[
        "away",
        "take"
    ],
    "wof:name":"Giardini Pizza & Pasta Bar",
    "wof:placetype":"venue"
},
  "geometry": {"coordinates":[146.71949799999999,-19.319809],"type":"Point"}
}