{
  "type": "Feature",
  "properties": {
    "addr:full":"86 Collins St Hobart TAS 7000",
    "addr:housenumber":"86",
    "addr:postcode":"7000",
    "addr:street":"Collins St",
    "iso:country":"AU",
    "sg:address":"86 Collins St",
    "sg:city":"Hobart",
    "sg:classifiers":[
        {
            "category":"Cafe",
            "type":"Food & Drink"
        }
    ],
    "sg:phone":"+61 3 6234 4181",
    "sg:postcode":"7000",
    "sg:province":"TAS",
    "wof:name":"Cafe On Collins",
    "wof:placetype":"venue"
},
  "geometry": {"coordinates":[147.32951355,-42.8818130493],"type":"Point"}
}