{
  "type": "Feature",
  "properties": {
    "addr:full":"7 Denver Rd Erskine Park NSW 2759",
    "addr:housenumber":"7",
    "addr:postcode":"2759",
    "addr:street":"Denver Rd",
    "iso:country":"AU",
    "sg:address":"7 Denver Rd",
    "sg:city":"Erskine Park",
    "sg:classifiers":[
        {
            "category":"Freight",
            "type":"Transportation"
        }
    ],
    "sg:phone":"+61 2 9834 3392",
    "sg:postcode":"2759",
    "sg:province":"NSW",
    "sg:tags":[
        "transport",
        "refrigerated"
    ],
    "wof:name":"Crosstran Pty Ltd",
    "wof:placetype":"venue"
},
  "geometry": {"coordinates":[150.799926758,-33.7935256958],"type":"Point"}
}