{
  "type": "Feature",
  "properties": {
    "addr:full":"23 Quandong Crs Arana Hills QLD 4054",
    "addr:housenumber":"23",
    "addr:postcode":"4054",
    "addr:street":"Quandong Crs",
    "iso:country":"AU",
    "sg:address":"23 Quandong Crs",
    "sg:city":"Arana Hills",
    "sg:classifiers":[
        {
            "category":"Professional",
            "subcategory":"Detective & Security Services",
            "type":"Services"
        }
    ],
    "sg:phone":"+61 7 3851 3591",
    "sg:postcode":"4054",
    "sg:province":"QLD",
    "sg:tags":[
        "guard",
        "patrol"
    ],
    "wof:name":"BKC Security & Alarms",
    "wof:placetype":"venue"
},
  "geometry": {"coordinates":[153.002410889,-27.4365310669],"type":"Point"}
}