{
  "type": "Feature",
  "properties": {
    "iso:country":"AU",
    "sg:address":"Unit 3, 16 Yarramann Pl",
    "sg:city":"Virginia",
    "sg:classifiers":[
        {
            "category":"Freight",
            "type":"Transportation"
        }
    ],
    "sg:phone":"+61 402 790 764",
    "sg:postcode":"4014",
    "sg:province":"QLD",
    "sg:tags":[
        "car",
        "carrier",
        "transporting"
    ],
    "wof:name":"Carways Qld Pty Ltd.",
    "wof:placetype":"venue"
},
  "geometry": {"coordinates":[153.05816650400001,-27.3750782013],"type":"Point"}
}