{
  "type": "Feature",
  "properties": {
    "addr:full":"8 Colonsay St Templestowe VIC 3106",
    "addr:housenumber":"8",
    "addr:postcode":"3106",
    "addr:street":"Colonsay St",
    "iso:country":"AU",
    "sg:address":"8 Colonsay St",
    "sg:city":"Templestowe",
    "sg:classifiers":[
        {
            "category":"Shopping",
            "subcategory":"Computers & Home Electronics",
            "type":"Retail Goods"
        }
    ],
    "sg:phone":"+61 3 9846 5826",
    "sg:postcode":"3106",
    "sg:province":"VIC",
    "sg:tags":[
        "hardware",
        "equipment"
    ],
    "wof:name":"Data Image",
    "wof:placetype":"venue"
},
  "geometry": {"coordinates":[145.129272461,-37.7601356506],"type":"Point"}
}