{
  "type": "Feature",
  "properties": {
    "addr:full":"1A Diamond St Cooroy QLD 4563",
    "addr:housenumber":"1a",
    "addr:postcode":"4563",
    "addr:street":"Diamond St",
    "iso:country":"AU",
    "sg:address":"1A Diamond St",
    "sg:city":"Cooroy",
    "sg:classifiers":[
        {
            "category":"Recreation",
            "subcategory":"Fishing",
            "type":"Entertainment"
        }
    ],
    "sg:phone":"+61 7 5447 6308",
    "sg:postcode":"4563",
    "sg:province":"QLD",
    "sg:tags":[
        "tackle"
    ],
    "wof:name":"Cooroy Sports & Leisure",
    "wof:placetype":"venue"
},
  "geometry": {"coordinates":[152.91166687,-26.416595459],"type":"Point"}
}