{
  "type": "Feature",
  "properties": {
    "addr:full":"15 Mary St Pakenham VIC 3810",
    "addr:housenumber":"15",
    "addr:postcode":"3810",
    "addr:street":"Mary St",
    "iso:country":"AU",
    "sg:address":"15 Mary St",
    "sg:city":"Pakenham",
    "sg:classifiers":[
        {
            "category":"Building & Trades",
            "subcategory":"Construction",
            "type":"Services"
        }
    ],
    "sg:phone":"+61 3 5941 2718",
    "sg:postcode":"3810",
    "sg:province":"VIC",
    "sg:tags":[
        "roof"
    ],
    "wof:name":"Country Truss Pty Ltd",
    "wof:placetype":"venue"
},
  "geometry": {"coordinates":[145.45959500000001,-38.060402],"type":"Point"}
}