{
  "type": "Feature",
  "properties": {
    "addr:full":"15 Wilmot St Burnie TAS 7320",
    "addr:housenumber":"15",
    "addr:postcode":"7320",
    "addr:street":"Wilmot St",
    "iso:country":"AU",
    "sg:address":"15 Wilmot St",
    "sg:city":"Burnie",
    "sg:classifiers":[
        {
            "category":"Banks & Credit Unions",
            "subcategory":"Financial Services",
            "type":"Services"
        }
    ],
    "sg:phone":"+61 3 6432 2929",
    "sg:postcode":"7320",
    "sg:province":"TAS",
    "sg:tags":[
        "advisory",
        "planning",
        "retirement"
    ],
    "wof:name":"Burn Ellen",
    "wof:placetype":"venue"
},
  "geometry": {"coordinates":[145.907578,-41.051193],"type":"Point"}
}