{
  "type": "Feature",
  "properties": {
    "addr:full":"Shop 2, 170 Burwood Rd Burwood NSW 2134",
    "addr:housenumber":"shop 2 170",
    "addr:postcode":"2134",
    "addr:street":"Burwood Rd",
    "iso:country":"AU",
    "sg:address":"Shop 2, 170 Burwood Rd",
    "sg:city":"Burwood",
    "sg:classifiers":[
        {
            "category":"Personal",
            "subcategory":"Massage",
            "type":"Services"
        }
    ],
    "sg:phone":"+61 2 9744 7515",
    "sg:postcode":"2134",
    "sg:province":"NSW",
    "sg:tags":[
        "therapy"
    ],
    "wof:name":"Ceragem Burwood",
    "wof:placetype":"venue"
},
  "geometry": {"coordinates":[151.10403442399999,-33.8764801025],"type":"Point"}
}