{
  "type": "Feature",
  "properties": {
    "addr:full":"Factory 13/ 11 Brand Drv Thomastown VIC 3074",
    "addr:housenumber":"13 / 11",
    "addr:postcode":"3074",
    "addr:street":"Brand Drv",
    "iso:country":"AU",
    "sg:address":"Factory 13/ 11 Brand Drv",
    "sg:city":"Thomastown",
    "sg:classifiers":[
        {
            "category":"Home & Garden",
            "subcategory":"Hardware",
            "type":"Retail Goods"
        }
    ],
    "sg:phone":"+61 3 9464 5099",
    "sg:postcode":"3074",
    "sg:province":"VIC",
    "sg:tags":[
        "trolley",
        "truck",
        "hand"
    ],
    "wof:name":"Effective Supermarket Services",
    "wof:placetype":"venue"
},
  "geometry": {"coordinates":[145.03414917000001,-37.6916160583],"type":"Point"}
}