{
  "type": "Feature",
  "properties": {
    "iso:country":"AU",
    "sg:address":"21 Gunyah Rd",
    "sg:city":"Blackburn North",
    "sg:classifiers":[
        {
            "category":"Personal",
            "subcategory":"Massage",
            "type":"Services"
        }
    ],
    "sg:phone":"+61 408 038 717",
    "sg:postcode":"3130",
    "sg:province":"VIC",
    "sg:tags":[
        "therapy"
    ],
    "wof:name":"Annes Studio Remedial & Mobile Massge",
    "wof:placetype":"venue"
},
  "geometry": {"coordinates":[145.16529846200001,-37.8092536926],"type":"Point"}
}