{
  "type": "Feature",
  "properties": {
    "addr:full":"485 Smithfield Rd Prairiewood NSW 2176",
    "addr:housenumber":"485",
    "addr:postcode":"2176",
    "addr:street":"Smithfield Rd",
    "iso:country":"AU",
    "sg:address":"485 Smithfield Rd",
    "sg:city":"Prairiewood",
    "sg:classifiers":[
        {
            "category":"Retail",
            "subcategory":"Auto Rental",
            "type":"Services"
        }
    ],
    "sg:phone":"+61 2 9725 5808",
    "sg:postcode":"2176",
    "sg:province":"NSW",
    "sg:tags":[
        "car",
        "hire",
        "minibus"
    ],
    "wof:name":"A & AA Able Utes",
    "wof:placetype":"venue"
},
  "geometry": {"coordinates":[150.90335082999999,-33.8703117371],"type":"Point"}
}