{
  "type": "Feature",
  "properties": {
    "iso:country":"AU",
    "sg:address":"395 Pacific Hwy",
    "sg:city":"Artarmon",
    "sg:classifiers":[
        {
            "category":"Autos & Motor Vehicles",
            "subcategory":"Fuel & Gas Station",
            "type":"Retail Goods"
        }
    ],
    "sg:phone":"+61 2 9439 8994",
    "sg:postcode":"2064",
    "sg:province":"NSW",
    "wof:name":"Liberty Oil Pty Ltd",
    "wof:placetype":"venue"
},
  "geometry": {"coordinates":[151.178497314,-33.8156394958],"type":"Point"}
}