{
  "type": "Feature",
  "properties": {
    "iso:country":"AU",
    "sg:address":"Unit 3, 15 Liddelow St",
    "sg:city":"Kenwick",
    "sg:classifiers":[
        {
            "category":"Retail",
            "subcategory":"Auto Repair",
            "type":"Services"
        }
    ],
    "sg:phone":"+61 8 9493 1432",
    "sg:postcode":"6107",
    "sg:province":"WA",
    "sg:tags":[
        "repairer",
        "motor",
        "engineer"
    ],
    "wof:name":"Abbas Radiator Repairs",
    "wof:placetype":"venue"
},
  "geometry": {"coordinates":[115.970466614,-32.0421981812],"type":"Point"}
}