{
  "type": "Feature",
  "properties": {
    "iso:country":"AU",
    "sg:address":"255B Herries St",
    "sg:city":"Toowoomba",
    "sg:classifiers":[
        {
            "category":"Health Services",
            "subcategory":"Health Practitioner",
            "type":"Services"
        }
    ],
    "sg:phone":"+61 7 4638 4252",
    "sg:postcode":"4350",
    "sg:province":"QLD",
    "sg:tags":[
        "naturopath"
    ],
    "wof:name":"Newtown Total Health Centre",
    "wof:placetype":"venue"
},
  "geometry": {"coordinates":[151.93425,-27.561798],"type":"Point"}
}