{
  "type": "Feature",
  "properties": {
    "iso:country":"AU",
    "sg:address":"6/18 Carrington St",
    "sg:city":"Lismore",
    "sg:classifiers":[
        {
            "category":"Personal",
            "subcategory":"Beauty Salon",
            "type":"Services"
        }
    ],
    "sg:phone":"+61 2 6622 4388",
    "sg:postcode":"2480",
    "sg:province":"NSW",
    "sg:tags":[
        "hairdresser"
    ],
    "wof:name":"Winks Hairdressing",
    "wof:placetype":"venue"
},
  "geometry": {"coordinates":[153.27702331500001,-28.8086719513],"type":"Point"}
}