{
  "type": "Feature",
  "properties": {
    "iso:country":"AU",
    "sg:address":"19/ 21 McCabe St",
    "sg:city":"North Fremantle",
    "sg:classifiers":[
        {
            "category":"Home & Garden",
            "subcategory":"Building Materials",
            "type":"Retail Goods"
        }
    ],
    "sg:phone":"+61 13 15 46",
    "sg:postcode":"6159",
    "sg:province":"WA",
    "sg:tags":[
        "lawn",
        "cutting",
        "maintenance"
    ],
    "wof:name":"Jims Mowing",
    "wof:placetype":"venue"
},
  "geometry": {"coordinates":[115.754539,-32.0233],"type":"Point"}
}