{
  "type": "Feature",
  "properties": {
    "addr:full":"12 Akma Crt Taylors Lakes VIC 3038",
    "addr:housenumber":"12",
    "addr:postcode":"3038",
    "addr:street":"Akma Crt",
    "iso:country":"AU",
    "sg:address":"12 Akma Crt",
    "sg:city":"Taylors Lakes",
    "sg:classifiers":[
        {
            "category":"Professional",
            "subcategory":"Business Services",
            "type":"Services"
        }
    ],
    "sg:phone":"+61 3 9390 1425",
    "sg:postcode":"3038",
    "sg:province":"VIC",
    "sg:tags":[
        "drafting"
    ],
    "wof:name":"Calder Drafting Service Pty Ltd",
    "wof:placetype":"venue"
},
  "geometry": {"coordinates":[144.797302,-37.707191],"type":"Point"}
}