{
  "type": "Feature",
  "properties": {
    "addr:full":"17 Glebe St Hobart TAS 7000",
    "addr:housenumber":"17",
    "addr:postcode":"7000",
    "addr:street":"Glebe St",
    "iso:country":"AU",
    "sg:address":"17 Glebe St",
    "sg:city":"Hobart",
    "sg:classifiers":[
        {
            "category":"Social Services",
            "subcategory":"Retirement Home",
            "type":"Services"
        }
    ],
    "sg:phone":"+61 3 6234 1590",
    "sg:postcode":"7000",
    "sg:province":"TAS",
    "sg:tags":[
        "decoration",
        "supplier",
        "contractor"
    ],
    "wof:name":"Crucial Displays",
    "wof:placetype":"venue"
},
  "geometry": {"coordinates":[147.32817077600001,-42.874912262],"type":"Point"}
}