{
  "type": "Feature",
  "properties": {
    "addr:full":"436 Hume Hwy Yagoona NSW 2199",
    "addr:housenumber":"436",
    "addr:postcode":"2199",
    "addr:street":"Hume Hwy",
    "iso:country":"AU",
    "sg:address":"436 Hume Hwy",
    "sg:city":"Yagoona",
    "sg:classifiers":[
        {
            "category":"Utilities",
            "subcategory":"Refuse",
            "type":"Services"
        }
    ],
    "sg:phone":"+61 2 9790 1235",
    "sg:postcode":"2199",
    "sg:province":"NSW",
    "sg:tags":[
        "leather",
        "retail",
        "clothing"
    ],
    "wof:name":"D.B.T. Leathers",
    "wof:placetype":"venue"
},
  "geometry": {"coordinates":[151.02714499999999,-33.907791],"type":"Point"}
}