{
  "type": "Feature",
  "properties": {
    "addr:full":"Shop 3/ 125 Colburn Ave Victoria Point QLD 4165",
    "addr:housenumber":"shop 3 / 125",
    "addr:postcode":"4165",
    "addr:street":"Colburn Ave",
    "iso:country":"AU",
    "sg:address":"Shop 3/ 125 Colburn Ave",
    "sg:city":"Victoria Point",
    "sg:classifiers":[
        {
            "category":"Personal",
            "subcategory":"Beauty Salon",
            "type":"Services"
        }
    ],
    "sg:phone":"+61 7 3207 7711",
    "sg:postcode":"4165",
    "sg:province":"QLD",
    "sg:tags":[
        "hairdresser"
    ],
    "wof:name":"Colburn's Hair",
    "wof:placetype":"venue"
},
  "geometry": {"coordinates":[153.30659484899999,-27.5862045288],"type":"Point"}
}