{
  "type": "Feature",
  "properties": {
    "iso:country":"AU",
    "sg:address":"3/ 36 Seton Rd",
    "sg:city":"Moorebank",
    "sg:classifiers":[
        {
            "category":"Retail",
            "subcategory":"Auto Repair",
            "type":"Services"
        }
    ],
    "sg:phone":"+61 2 9602 5382",
    "sg:postcode":"2170",
    "sg:province":"NSW",
    "sg:tags":[
        "bus",
        "truck"
    ],
    "wof:name":"Liverpool Mechanical Repairs Pty Ltd",
    "wof:placetype":"venue"
},
  "geometry": {"coordinates":[150.939208984,-33.9361000061],"type":"Point"}
}