{
  "type": "Feature",
  "properties": {
    "addr:full":"Shop 6, Charnwood Shopping Centre Charnwood ACT 2615",
    "addr:housenumber":"shop 6",
    "addr:postcode":"2615",
    "addr:street":"Charnwood Shopping",
    "iso:country":"AU",
    "sg:address":"Shop 6, Charnwood Shopping Centre",
    "sg:city":"Charnwood",
    "sg:classifiers":[
        {
            "category":"Professional",
            "subcategory":"Computer Services",
            "type":"Services"
        }
    ],
    "sg:phone":"+61 2 6253 2668",
    "sg:postcode":"2615",
    "sg:province":"ACT",
    "sg:tags":[
        "consultant",
        "system"
    ],
    "wof:name":"EBM Computers",
    "wof:placetype":"venue"
},
  "geometry": {"coordinates":[149.03390502900001,-35.2054290771],"type":"Point"}
}