{
  "type": "Feature",
  "properties": {
    "iso:country":"AU",
    "sg:address":"116 Elizabeth St",
    "sg:city":"Launceston",
    "sg:classifiers":[
        {
            "category":"Education",
            "subcategory":"Special Training",
            "type":"Public Place"
        }
    ],
    "sg:phone":"+61 3 6333 3030",
    "sg:postcode":"7250",
    "sg:province":"TAS",
    "sg:tags":[
        "development"
    ],
    "wof:name":"A.P.W. Training (A division of Anglicare)",
    "wof:placetype":"venue"
},
  "geometry": {"coordinates":[147.13795471200001,-41.4407157898],"type":"Point"}
}