{
  "type": "Feature",
  "properties": {
    "addr:full":"11 Bell St Montrose VIC 3765",
    "addr:housenumber":"11",
    "addr:postcode":"3765",
    "addr:street":"Bell St",
    "iso:country":"AU",
    "sg:address":"11 Bell St",
    "sg:city":"Montrose",
    "sg:classifiers":[
        {
            "category":"Health Services",
            "subcategory":"Health Practitioner",
            "type":"Services"
        }
    ],
    "sg:phone":"+61 3 9728 4706",
    "sg:postcode":"3765",
    "sg:province":"VIC",
    "sg:tags":[
        "psychologist"
    ],
    "wof:name":"Tanya Clarke",
    "wof:placetype":"venue"
},
  "geometry": {"coordinates":[145.345504761,-37.8063278198],"type":"Point"}
}