{
  "type": "Feature",
  "properties": {
    "iso:country":"AU",
    "sg:address":"5- 9 Bridges Rd",
    "sg:city":"Moorebank",
    "sg:classifiers":[
        {
            "category":"Manufacturing",
            "subcategory":"Furniture",
            "type":"Manufacturing & Wholesale Goods"
        }
    ],
    "sg:phone":"+61 2 9821 8755",
    "sg:postcode":"2170",
    "sg:province":"NSW",
    "sg:tags":[
        "mfrs",
        "supply"
    ],
    "wof:name":"Joyce Foam Products",
    "wof:placetype":"venue"
},
  "geometry": {"coordinates":[150.93397522000001,-33.9263000488],"type":"Point"}
}