{
  "type": "Feature",
  "properties": {
    "iso:country":"AU",
    "sg:address":"37 Acacia Rd",
    "sg:city":"Ferntree Gully",
    "sg:classifiers":[
        {
            "category":"Building & Trades",
            "subcategory":"Construction",
            "type":"Services"
        }
    ],
    "sg:phone":"+61 417 552 587",
    "sg:postcode":"3156",
    "sg:province":"VIC",
    "sg:tags":[
        "ceiling"
    ],
    "wof:name":"Metro Ceilings Pty Ltd",
    "wof:placetype":"venue"
},
  "geometry": {"coordinates":[145.296676636,-37.8971672058],"type":"Point"}
}