{
  "type": "Feature",
  "properties": {
    "iso:country":"AU",
    "sg:address":"146 Donohue St",
    "sg:city":"Kings Park",
    "sg:classifiers":[
        {
            "category":"Train Station",
            "subcategory":"Light Rail",
            "type":"Transportation"
        }
    ],
    "sg:phone":"+61 2 9837 3033",
    "sg:postcode":"2148",
    "sg:province":"NSW",
    "sg:tags":[
        "equipment",
        "energy",
        "solar"
    ],
    "wof:name":"No. 1 Sydney Solar",
    "wof:placetype":"venue"
},
  "geometry": {"coordinates":[150.897949219,-33.736618042],"type":"Point"}
}