{
  "type": "Feature",
  "properties": {
    "iso:country":"AU",
    "sg:address":"151 Canley Vale Rd",
    "sg:city":"Canley Heights",
    "sg:classifiers":[
        {
            "category":"Professional",
            "subcategory":"Employment Agencies",
            "type":"Services"
        }
    ],
    "sg:phone":"+61 2 9723 5041",
    "sg:postcode":"2166",
    "sg:province":"NSW",
    "sg:tags":[
        "model"
    ],
    "wof:name":"Vanity Management",
    "wof:placetype":"venue"
},
  "geometry": {"coordinates":[150.926879883,-33.8841514587],"type":"Point"}
}