{
  "type": "Feature",
  "properties": {
    "iso:country":"AU",
    "sg:address":"126 Chapel St",
    "sg:city":"St Kilda",
    "sg:classifiers":[
        {
            "category":"Wholesale",
            "subcategory":"Drugs",
            "type":"Manufacturing & Wholesale Goods"
        }
    ],
    "sg:phone":"+61 3 9525 6550",
    "sg:postcode":"3182",
    "sg:province":"VIC",
    "sg:tags":[
        "wholesaler",
        "pharmaceutical",
        "product",
        "mfrs"
    ],
    "wof:name":"Ultra Mix (Aust) Pty Ltd",
    "wof:placetype":"venue"
},
  "geometry": {"coordinates":[144.99319457999999,-37.8536834717],"type":"Point"}
}