{
  "type": "Feature",
  "properties": {
    "addr:full":"50 Burwood Rd Burwood NSW 2134",
    "addr:housenumber":"50",
    "addr:postcode":"2134",
    "addr:street":"Burwood Rd",
    "iso:country":"AU",
    "sg:address":"50 Burwood Rd",
    "sg:city":"Burwood",
    "sg:classifiers":[
        {
            "category":"Shopping",
            "subcategory":"Clothing, Apparel, & Fashions",
            "type":"Retail Goods"
        }
    ],
    "sg:phone":"+61 2 9744 1970",
    "sg:postcode":"2134",
    "sg:province":"NSW",
    "sg:tags":[
        "sportswear"
    ],
    "wof:name":"Jackie's Bowls Shop",
    "wof:placetype":"venue"
},
  "geometry": {"coordinates":[151.10488891599999,-33.8720703125],"type":"Point"}
}