{
  "type": "Feature",
  "properties": {
    "addr:full":"67 Richland Ave Coopers Plains QLD 4108",
    "addr:housenumber":"67",
    "addr:postcode":"4108",
    "addr:street":"Richland Ave",
    "iso:country":"AU",
    "sg:address":"67 Richland Ave",
    "sg:city":"Coopers Plains",
    "sg:classifiers":[
        {
            "category":"Banks & Credit Unions",
            "subcategory":"Bureau De Change",
            "type":"Services"
        }
    ],
    "sg:phone":"+61 7 3275 2403",
    "sg:postcode":"4108",
    "sg:province":"QLD",
    "sg:tags":[
        "repairs",
        "part",
        "appliance",
        "electrical"
    ],
    "wof:name":"Mohammed's Electrical Repairs",
    "wof:placetype":"venue"
},
  "geometry": {"coordinates":[153.02809143100001,-27.5658760071],"type":"Point"}
}