{
  "type": "Feature",
  "properties": {
    "addr:full":"PO Box 292 Port Lincoln SA 5606",
    "addr:postcode":"5606",
    "iso:country":"AU",
    "sg:address":"PO Box 292",
    "sg:city":"Port Lincoln",
    "sg:classifiers":[
        {
            "category":"Retail",
            "subcategory":"Car Wash",
            "type":"Services"
        }
    ],
    "sg:phone":"+61 8 8683 3644",
    "sg:postcode":"5606",
    "sg:province":"SA",
    "sg:tags":[
        "truck",
        "cleaning"
    ],
    "wof:name":"Mav's Detailing",
    "wof:placetype":"venue"
},
  "geometry": {"coordinates":[135.85438500000001,-34.733974],"type":"Point"}
}