{
  "type": "Feature",
  "properties": {
    "addr:full":"Unit 3 52 Wigram Rd Glebe NSW 2037",
    "addr:housenumber":"52",
    "addr:postcode":"2037",
    "addr:street":"Wigram Rd",
    "iso:country":"AU",
    "sg:address":"Unit 3 52 Wigram Rd",
    "sg:city":"Glebe",
    "sg:classifiers":[
        {
            "category":"Building & Trades",
            "subcategory":"Landscaping Services",
            "type":"Services"
        }
    ],
    "sg:phone":"+61 416 578 495",
    "sg:postcode":"2037",
    "sg:province":"NSW",
    "sg:tags":[
        "designer",
        "landscape",
        "contractor"
    ],
    "wof:name":"Airloom Garden Design",
    "wof:placetype":"venue"
},
  "geometry": {"coordinates":[151.18215942399999,-33.8788986206],"type":"Point"}
}