{
  "type": "Feature",
  "properties": {
    "addr:full":"Mallard Rd Pittsworth QLD 4356",
    "addr:postcode":"4356",
    "addr:street":"Mallard Rd",
    "iso:country":"AU",
    "sg:address":"Mallard Rd",
    "sg:city":"Pittsworth",
    "sg:classifiers":[
        {
            "category":"Social Services",
            "subcategory":"Adult Care",
            "type":"Services"
        }
    ],
    "sg:phone":"+61 412 622 168",
    "sg:postcode":"4356",
    "sg:province":"QLD",
    "sg:tags":[
        "towing"
    ],
    "wof:name":"Pittsworth Towing Service",
    "wof:placetype":"venue"
},
  "geometry": {"coordinates":[151.62460300000001,-27.718498],"type":"Point"}
}