{
  "type": "Feature",
  "properties": {
    "addr:full":"Shop 2, Brisbane Crt, 76 Brisbane St Launceston TAS 7250",
    "addr:housenumber":"shop 2;76",
    "addr:postcode":"7250",
    "addr:street":"Brisbane Crt;Brisbane St",
    "iso:country":"AU",
    "sg:address":"Shop 2, Brisbane Crt, 76 Brisbane St",
    "sg:city":"Launceston",
    "sg:classifiers":[
        {
            "category":"Shopping",
            "subcategory":"Jewelry",
            "type":"Retail Goods"
        }
    ],
    "sg:phone":"+61 3 6334 1574",
    "sg:postcode":"7250",
    "sg:province":"TAS",
    "sg:tags":[
        "jeweller"
    ],
    "wof:name":"Launceston Precision Jewellers",
    "wof:placetype":"venue"
},
  "geometry": {"coordinates":[147.13987731899999,-41.4365653992],"type":"Point"}
}