{
  "type": "Feature",
  "properties": {
    "addr:full":"12 Cribb St Milton QLD 4064",
    "addr:housenumber":"12",
    "addr:postcode":"4064",
    "addr:street":"Cribb St",
    "iso:country":"AU",
    "sg:address":"12 Cribb St",
    "sg:city":"Milton",
    "sg:classifiers":[
        {
            "category":"Professional",
            "subcategory":"Engineering",
            "type":"Services"
        }
    ],
    "sg:phone":"+61 7 3858 6700",
    "sg:postcode":"4064",
    "sg:province":"QLD",
    "sg:tags":[
        "consulting",
        "engineer"
    ],
    "wof:name":"Maunsell Australia",
    "wof:placetype":"venue"
},
  "geometry": {"coordinates":[153.00813293499999,-27.4701881409],"type":"Point"}
}