{
  "type": "Feature",
  "properties": {
    "addr:full":"80a Mitchell St Bendigo VIC 3550",
    "addr:housenumber":"80a",
    "addr:postcode":"3550",
    "addr:street":"Mitchell St",
    "iso:country":"AU",
    "sg:address":"80a Mitchell St",
    "sg:city":"Bendigo",
    "sg:classifiers":[
        {
            "category":"Health Services",
            "subcategory":"Health Practitioner",
            "type":"Services"
        }
    ],
    "sg:phone":"+61 3 5443 9323",
    "sg:postcode":"3550",
    "sg:province":"VIC",
    "sg:tags":[
        "hypnotherapy"
    ],
    "wof:name":"Cindy Brasen",
    "wof:placetype":"venue"
},
  "geometry": {"coordinates":[144.281326294,-36.7623214722],"type":"Point"}
}