{
  "type": "Feature",
  "properties": {
    "addr:full":"U1/ 110 Flinders St Lawson NSW 2783",
    "addr:housenumber":"110",
    "addr:postcode":"2783",
    "addr:street":"U1 /;Flinders St",
    "iso:country":"AU",
    "sg:address":"U1/ 110 Flinders St",
    "sg:city":"Lawson",
    "sg:classifiers":[
        {
            "category":"Professional",
            "subcategory":"Engineering",
            "type":"Services"
        }
    ],
    "sg:phone":"+61 2 4759 1118",
    "sg:postcode":"2783",
    "sg:province":"NSW",
    "sg:tags":[
        "manufacturing",
        "engineer"
    ],
    "wof:name":"Automated Solutions Pty Ltd",
    "wof:placetype":"venue"
},
  "geometry": {"coordinates":[150.44354248100001,-33.7261581421],"type":"Point"}
}