{
  "type": "Feature",
  "properties": {
    "iso:country":"AU",
    "sg:address":"65 Redcliffe Pde",
    "sg:city":"Redcliffe",
    "sg:classifiers":[
        {
            "category":"Health Services",
            "subcategory":"Doctor",
            "type":"Services"
        }
    ],
    "sg:phone":"+61 7 3284 5739",
    "sg:postcode":"4020",
    "sg:province":"QLD",
    "sg:tags":[
        "medical",
        "practitioner"
    ],
    "wof:name":"Edwards James",
    "wof:placetype":"venue"
},
  "geometry": {"coordinates":[153.115295,-27.228279],"type":"Point"}
}