{
  "type": "Feature",
  "properties": {
    "addr:full":"Bridge St Lawrence NSW 2460",
    "addr:postcode":"2460",
    "addr:street":"Bridge St",
    "iso:country":"AU",
    "sg:address":"Bridge St",
    "sg:city":"Lawrence",
    "sg:classifiers":[
        {
            "category":"Autos & Motor Vehicles",
            "subcategory":"Fuel & Gas Station",
            "type":"Retail Goods"
        }
    ],
    "sg:phone":"+61 2 6647 7130",
    "sg:postcode":"2460",
    "sg:province":"NSW",
    "wof:name":"B P Lawrence Service Station",
    "wof:placetype":"venue"
},
  "geometry": {"coordinates":[152.94137573200001,-29.6932582855],"type":"Point"}
}