{
  "type": "Feature",
  "properties": {
    "addr:full":"501 Sherwood Rd Sherwood QLD 4075",
    "addr:housenumber":"501",
    "addr:postcode":"4075",
    "addr:street":"Sherwood Rd",
    "iso:country":"AU",
    "sg:address":"501 Sherwood Rd",
    "sg:city":"Sherwood",
    "sg:classifiers":[
        {
            "category":"Food & Beverages",
            "subcategory":"Fruits & Vegetables",
            "type":"Retail Goods"
        }
    ],
    "sg:phone":"+61 7 3379 5628",
    "sg:postcode":"4075",
    "sg:province":"QLD",
    "sg:tags":[
        "greengrocer",
        "fruiterer"
    ],
    "wof:name":"Organic & Biodynamic Produce Retailers",
    "wof:placetype":"venue"
},
  "geometry": {"coordinates":[152.988647461,-27.533121109],"type":"Point"}
}