{
  "type": "Feature",
  "properties": {
    "addr:full":"82 Coleman St Wagga Wagga NSW 2650",
    "addr:housenumber":"82",
    "addr:postcode":"2650",
    "addr:street":"Coleman St",
    "iso:country":"AU",
    "sg:address":"82 Coleman St",
    "sg:city":"Wagga Wagga",
    "sg:classifiers":[
        {
            "category":"Education",
            "subcategory":"Kindergarten",
            "type":"Public Place"
        }
    ],
    "sg:phone":"+61 2 6925 2669",
    "sg:postcode":"2650",
    "sg:province":"NSW",
    "sg:tags":[
        "pre-schools"
    ],
    "wof:name":"KU Kookaburra Preschool",
    "wof:placetype":"venue"
},
  "geometry": {"coordinates":[147.359817505,-35.1225967407],"type":"Point"}
}