{
  "type": "Feature",
  "properties": {
    "addr:full":"2/ 1032 Old Princes Hwy Engadine NSW 2233",
    "addr:housenumber":"/ 1032",
    "addr:postcode":"2233",
    "addr:street":"Old Princes Hwy",
    "iso:country":"AU",
    "sg:address":"2/ 1032 Old Princes Hwy",
    "sg:city":"Engadine",
    "sg:classifiers":[
        {
            "category":"Real Estate",
            "subcategory":"Real Estate Agent",
            "type":"Services"
        }
    ],
    "sg:phone":"+61 2 9520 3399",
    "sg:postcode":"2233",
    "sg:province":"NSW",
    "wof:name":"Century 21 Exclusive Realty",
    "wof:placetype":"venue"
},
  "geometry": {"coordinates":[151.01324462900001,-34.065284729],"type":"Point"}
}