{
  "type": "Feature",
  "properties": {
    "iso:country":"AU",
    "sg:address":"Kiosk 10, Westfield Shopping Town, 29 Louis St",
    "sg:city":"Airport West",
    "sg:classifiers":[
        {
            "category":"Shopping",
            "subcategory":"Mobile Phones",
            "type":"Retail Goods"
        }
    ],
    "sg:phone":"+61 3 9077 5866",
    "sg:postcode":"3042",
    "sg:province":"VIC",
    "sg:tags":[
        "telephone",
        "accessory"
    ],
    "wof:name":"TeleChoice",
    "wof:placetype":"venue"
},
  "geometry": {"coordinates":[144.887619019,-37.7126998901],"type":"Point"}
}