{
  "type": "Feature",
  "properties": {
    "addr:full":"Lot 7 Rich Pl Dardanup WA 6236",
    "addr:postcode":"6236",
    "addr:street":"Pl",
    "iso:country":"AU",
    "sg:address":"Lot 7 Rich Pl",
    "sg:city":"Dardanup",
    "sg:classifiers":[
        {
            "category":"Building & Trades",
            "subcategory":"Cleaning & Sanitation",
            "type":"Services"
        }
    ],
    "sg:phone":"+61 8 9728 1313",
    "sg:postcode":"6236",
    "sg:province":"WA",
    "sg:tags":[
        "sweeping",
        "machine"
    ],
    "wof:name":"Broadsweep",
    "wof:placetype":"venue"
},
  "geometry": {"coordinates":[115.738091,-33.390533],"type":"Point"}
}