{
  "type": "Feature",
  "properties": {
    "iso:country":"AU",
    "sg:address":"198 Star St",
    "sg:city":"Welshpool",
    "sg:classifiers":[
        {
            "category":"Home & Garden",
            "subcategory":"Building Materials",
            "type":"Retail Goods"
        }
    ],
    "sg:phone":"+61 8 9470 3118",
    "sg:postcode":"6106",
    "sg:province":"WA",
    "sg:tags":[
        "merchant",
        "glass",
        "glazier"
    ],
    "wof:name":"Premier Glass & Mirrors",
    "wof:placetype":"venue"
},
  "geometry": {"coordinates":[115.926239014,-31.9846096039],"type":"Point"}
}