{
  "type": "Feature",
  "properties": {
    "iso:country":"AU",
    "sg:address":"87 Costello Rd",
    "sg:city":"Tungamull",
    "sg:classifiers":[
        {
            "category":"Building & Trades",
            "subcategory":"Construction",
            "type":"Services"
        }
    ],
    "sg:phone":"+61 7 4934 4608",
    "sg:postcode":"4702",
    "sg:province":"QLD",
    "sg:tags":[
        "contractor"
    ],
    "wof:name":"McGuire M J Building Contractor",
    "wof:placetype":"venue"
},
  "geometry": {"coordinates":[150.695144653,-23.2926559448],"type":"Point"}
}