{
  "type": "Feature",
  "properties": {
    "addr:full":"41 Lindsay Rd Lonsdale SA 5160",
    "addr:housenumber":"41",
    "addr:postcode":"5160",
    "addr:street":"Lindsay Rd",
    "iso:country":"AU",
    "sg:address":"41 Lindsay Rd",
    "sg:city":"Lonsdale",
    "sg:classifiers":[
        {
            "category":"Professional",
            "type":"Services"
        }
    ],
    "sg:phone":"+61 8 8322 5200",
    "sg:postcode":"5160",
    "sg:province":"SA",
    "sg:tags":[
        "coating",
        "powder"
    ],
    "wof:name":"Southern Powder Coaters",
    "wof:placetype":"venue"
},
  "geometry": {"coordinates":[138.50216674800001,-35.1030082703],"type":"Point"}
}