{
  "type": "Feature",
  "properties": {
    "iso:country":"AU",
    "sg:address":"536 Main Rd",
    "sg:city":"Wellington Point",
    "sg:classifiers":[
        {
            "category":"Autos & Motor Vehicles",
            "subcategory":"Fuel & Gas Station",
            "type":"Retail Goods"
        }
    ],
    "sg:phone":"+61 7 3207 4527",
    "sg:postcode":"4160",
    "sg:province":"QLD",
    "wof:name":"SEQ Fuel Wellington Point",
    "wof:placetype":"venue"
},
  "geometry": {"coordinates":[153.23968505900001,-27.4960212708],"type":"Point"}
}