{
  "type": "Feature",
  "properties": {
    "addr:full":"166 Foster St Dandenong VIC 3175",
    "addr:housenumber":"166",
    "addr:postcode":"3175",
    "addr:street":"Foster St",
    "iso:country":"AU",
    "sg:address":"166 Foster St",
    "sg:city":"Dandenong",
    "sg:classifiers":[
        {
            "category":"Health Services",
            "subcategory":"Health Practitioner",
            "type":"Services"
        }
    ],
    "sg:phone":"+61 3 9706 9486",
    "sg:postcode":"3175",
    "sg:province":"VIC",
    "sg:tags":[
        "acupuncture"
    ],
    "wof:name":"Qian Shanshan (Susan)",
    "wof:placetype":"venue"
},
  "geometry": {"coordinates":[145.218505859,-37.9885101318],"type":"Point"}
}