{
  "type": "Feature",
  "properties": {
    "addr:full":"99 Talavera Rd North Ryde NSW 2113",
    "addr:housenumber":"99",
    "addr:postcode":"2113",
    "addr:street":"Talavera Rd",
    "iso:country":"AU",
    "sg:address":"99 Talavera Rd",
    "sg:city":"North Ryde",
    "sg:classifiers":[
        {
            "category":"Travel",
            "subcategory":"Hotels & Motels",
            "type":"Entertainment"
        }
    ],
    "sg:phone":"+61 2 9850 9300",
    "sg:postcode":"2113",
    "sg:province":"NSW",
    "sg:tags":[
        "accommodation"
    ],
    "sg:website":"http://www.hotel.mgsm.com.au",
    "wof:name":"MGSM Executive Hotel & Conference Centre",
    "wof:placetype":"venue"
},
  "geometry": {"coordinates":[151.12246704099999,-33.7758903503],"type":"Point"}
}