{
  "type": "Feature",
  "properties": {
    "addr:full":"951 Plenty Rd Kingsbury VIC 3083",
    "addr:housenumber":"951",
    "addr:postcode":"3083",
    "addr:street":"Plenty Rd",
    "iso:country":"AU",
    "sg:address":"951 Plenty Rd",
    "sg:city":"Kingsbury",
    "sg:classifiers":[
        {
            "category":"Fast Food",
            "type":"Food & Drink"
        }
    ],
    "sg:phone":"+61 3 9478 6575",
    "sg:postcode":"3083",
    "sg:province":"VIC",
    "sg:tags":[
        "away",
        "take"
    ],
    "wof:name":"Kingsbury Fish Shop",
    "wof:placetype":"venue"
},
  "geometry": {"coordinates":[145.04301452600001,-37.7166252136],"type":"Point"}
}