{
  "type": "Feature",
  "properties": {
    "iso:country":"AU",
    "sg:address":"157 Beresford Rd",
    "sg:city":"Lilydale",
    "sg:classifiers":[
        {
            "category":"Personal",
            "subcategory":"Beauty Salon",
            "type":"Services"
        }
    ],
    "sg:phone":"+61 3 9735 1663",
    "sg:postcode":"3140",
    "sg:province":"VIC",
    "wof:name":"Bodyfx Nail & Beauty",
    "wof:placetype":"venue"
},
  "geometry": {"coordinates":[145.35140991200001,-37.7512435913],"type":"Point"}
}