{
  "type": "Feature",
  "properties": {
    "addr:full":"1 Nelson Pl Williamstown VIC 3016",
    "addr:housenumber":"1",
    "addr:postcode":"3016",
    "addr:street":"Nelson Pl",
    "iso:country":"AU",
    "sg:address":"1 Nelson Pl",
    "sg:city":"Williamstown",
    "sg:classifiers":[
        {
            "category":"Restaurant",
            "type":"Food & Drink"
        }
    ],
    "sg:phone":"+61 3 9397 5101",
    "sg:postcode":"3016",
    "sg:province":"VIC",
    "sg:tags":[
        "theatre"
    ],
    "wof:name":"Titanic Entertainments",
    "wof:placetype":"venue"
},
  "geometry": {"coordinates":[144.91009521500001,-37.8650054932],"type":"Point"}
}