{
  "type": "Feature",
  "properties": {
    "addr:full":"Suite 2, 69 King St Caboolture QLD 4510",
    "addr:housenumber":"69",
    "addr:postcode":"4510",
    "addr:street":"King St",
    "iso:country":"AU",
    "sg:address":"Suite 2, 69 King St",
    "sg:city":"Caboolture",
    "sg:classifiers":[
        {
            "category":"Health Services",
            "subcategory":"Doctor",
            "type":"Services"
        }
    ],
    "sg:phone":"+61 7 5431 7900",
    "sg:postcode":"4510",
    "sg:province":"QLD",
    "sg:tags":[
        "nurse",
        "nursing"
    ],
    "wof:name":"Spiritus Care Services",
    "wof:placetype":"venue"
},
  "geometry": {"coordinates":[152.94935599999999,-27.084467],"type":"Point"}
}