{
  "type": "Feature",
  "properties": {
    "iso:country":"AU",
    "sg:address":"Collins St",
    "sg:city":"Kangaroo Flat",
    "sg:classifiers":[
        {
            "category":"Building & Trades",
            "subcategory":"Construction",
            "type":"Services"
        }
    ],
    "sg:phone":"+61 3 5447 1411",
    "sg:postcode":"3555",
    "sg:province":"VIC",
    "sg:tags":[
        "contractor"
    ],
    "wof:name":"Rapid Steel Homes",
    "wof:placetype":"venue"
},
  "geometry": {"coordinates":[144.23440551799999,-36.7931861877],"type":"Point"}
}