{
  "type": "Feature",
  "properties": {
    "iso:country":"AU",
    "sg:address":"339 Heidelberg Rd",
    "sg:city":"Northcote",
    "sg:classifiers":[
        {
            "category":"Health Services",
            "subcategory":"Doctor",
            "type":"Services"
        }
    ],
    "sg:phone":"+61 3 9481 5744",
    "sg:postcode":"3070",
    "sg:province":"VIC",
    "sg:tags":[
        "medical",
        "practitioner"
    ],
    "wof:name":"Shawdon Anik",
    "wof:placetype":"venue"
},
  "geometry": {"coordinates":[145.012466,-37.783913],"type":"Point"}
}