{
  "type": "Feature",
  "properties": {
    "addr:full":"4 King William St Bayswater WA 6053",
    "addr:housenumber":"4",
    "addr:postcode":"6053",
    "addr:street":"King William St",
    "iso:country":"AU",
    "sg:address":"4 King William St",
    "sg:city":"Bayswater",
    "sg:classifiers":[
        {
            "category":"Fast Food",
            "type":"Food & Drink"
        }
    ],
    "sg:phone":"+61 8 9271 1052",
    "sg:postcode":"6053",
    "sg:province":"WA",
    "sg:tags":[
        "away",
        "take"
    ],
    "wof:name":"Pat's Seafoods",
    "wof:placetype":"venue"
},
  "geometry": {"coordinates":[115.911888123,-31.9190044403],"type":"Point"}
}