{
  "type": "Feature",
  "properties": {
    "addr:full":"Unit 13/ 75 Welsby St New Farm QLD 4005",
    "addr:housenumber":"/ 75",
    "addr:postcode":"4005",
    "addr:street":"Welsby St",
    "iso:country":"AU",
    "sg:address":"Unit 13/ 75 Welsby St",
    "sg:city":"New Farm",
    "sg:classifiers":[
        {
            "category":"Professional",
            "subcategory":"Management & Consulting",
            "type":"Services"
        }
    ],
    "sg:phone":"+61 7 3254 1431",
    "sg:postcode":"4005",
    "sg:province":"QLD",
    "sg:tags":[
        "consultant",
        "educational"
    ],
    "wof:name":"Vetnetwork Australia",
    "wof:placetype":"venue"
},
  "geometry": {"coordinates":[153.04997253400001,-27.46509552],"type":"Point"}
}