{
  "type": "Feature",
  "properties": {
    "iso:country":"AU",
    "sg:address":"1 Cullens La",
    "sg:city":"Hunters Hill",
    "sg:classifiers":[
        {
            "category":"Professional",
            "subcategory":"Detective & Security Services",
            "type":"Services"
        }
    ],
    "sg:phone":"+61 2 9879 4800",
    "sg:postcode":"2110",
    "sg:province":"NSW",
    "sg:tags":[
        "consultant",
        "system"
    ],
    "wof:name":"Kenden Security",
    "wof:placetype":"venue"
},
  "geometry": {"coordinates":[151.151153564,-33.8339958191],"type":"Point"}
}