{
  "type": "Feature",
  "properties": {
    "iso:country":"AU",
    "sg:address":"20 Wentworth St",
    "sg:city":"Parramatta",
    "sg:classifiers":[
        {
            "category":"Organizations",
            "subcategory":"Non-profit Organization",
            "type":"Services"
        }
    ],
    "sg:phone":"+61 2 9891 1248",
    "sg:postcode":"2150",
    "sg:province":"NSW",
    "sg:tags":[
        "support",
        "disability",
        "organisation"
    ],
    "wof:name":"Disability Resources Inc",
    "wof:placetype":"venue"
},
  "geometry": {"coordinates":[151.022583008,-33.8313484192],"type":"Point"}
}