{
  "type": "Feature",
  "properties": {
    "iso:country":"AU",
    "sg:address":"22 Cameron St",
    "sg:city":"Wonthaggi",
    "sg:classifiers":[
        {
            "category":"Building & Trades",
            "subcategory":"Pest Control",
            "type":"Services"
        }
    ],
    "sg:phone":"+61 417 030 033",
    "sg:postcode":"3995",
    "sg:province":"VIC",
    "wof:name":"Wonthaggi Pest Control",
    "wof:placetype":"venue"
},
  "geometry": {"coordinates":[145.585632,-38.610512],"type":"Point"}
}