{
  "type": "Feature",
  "properties": {
    "addr:full":"89 Main St Bridport TAS 7262",
    "addr:housenumber":"89",
    "addr:postcode":"7262",
    "addr:street":"Main St",
    "iso:country":"AU",
    "sg:address":"89 Main St",
    "sg:city":"Bridport",
    "sg:classifiers":[
        {
            "category":"Cafe",
            "type":"Food & Drink"
        }
    ],
    "sg:phone":"+61 3 6356 0057",
    "sg:postcode":"7262",
    "sg:province":"TAS",
    "wof:name":"Bridport Coffee Shop",
    "wof:placetype":"venue"
},
  "geometry": {"coordinates":[147.393494,-41.002468],"type":"Point"}
}