{
  "type": "Feature",
  "properties": {
    "iso:country":"AU",
    "sg:address":"82- 86 Bolsover St",
    "sg:city":"Rockhampton",
    "sg:classifiers":[
        {
            "category":"Personal",
            "type":"Services"
        }
    ],
    "sg:phone":"+61 7 4920 6900",
    "sg:postcode":"4700",
    "sg:province":"QLD",
    "sg:tags":[
        "counselling",
        "alcohol",
        "drug"
    ],
    "wof:name":"Alcohol Tobacco & Other Drugs Service",
    "wof:placetype":"venue"
},
  "geometry": {"coordinates":[150.516357422,-23.3845787048],"type":"Point"}
}