{
  "type": "Feature",
  "properties": {
    "iso:country":"AU",
    "sg:address":"86 Hawthorne Rd",
    "sg:city":"Hawthorne",
    "sg:classifiers":[
        {
            "category":"Education",
            "subcategory":"School",
            "type":"Public Place"
        }
    ],
    "sg:phone":"+61 7 3399 8888",
    "sg:postcode":"4171",
    "sg:province":"QLD",
    "sg:tags":[
        "girl"
    ],
    "wof:name":"Lourdes Hill College",
    "wof:placetype":"venue"
},
  "geometry": {"coordinates":[153.059051514,-27.4684085846],"type":"Point"}
}