{
  "type": "Feature",
  "properties": {
    "addr:full":"6/ 2 Spencer Rd Nerang QLD 4211",
    "addr:housenumber":"/ 2",
    "addr:postcode":"4211",
    "addr:street":"Spencer Rd",
    "iso:country":"AU",
    "sg:address":"6/ 2 Spencer Rd",
    "sg:city":"Nerang",
    "sg:classifiers":[
        {
            "category":"Retail",
            "subcategory":"Auto Repair",
            "type":"Services"
        }
    ],
    "sg:phone":"+61 7 5596 6333",
    "sg:postcode":"4211",
    "sg:province":"QLD",
    "sg:tags":[
        "bus",
        "truck"
    ],
    "wof:name":"A 1 Nerang Auto Care",
    "wof:placetype":"venue"
},
  "geometry": {"coordinates":[153.34048461899999,-27.9969177246],"type":"Point"}
}