{
  "type": "Feature",
  "properties": {
    "addr:full":"Suite 210 566 St Kilda Rd Melbourne VIC 3004",
    "addr:housenumber":"566",
    "addr:postcode":"3004",
    "addr:street":"St Kilda Rd",
    "iso:country":"AU",
    "sg:address":"Suite 210 566 St Kilda Rd",
    "sg:city":"Melbourne",
    "sg:classifiers":[
        {
            "category":"Travel",
            "subcategory":"Hotels & Motels",
            "type":"Entertainment"
        }
    ],
    "sg:phone":"+61 3 9521 7667",
    "sg:postcode":"3004",
    "sg:province":"VIC",
    "sg:tags":[
        "accommodation"
    ],
    "wof:name":"Millennium Hotels & Resorts",
    "wof:placetype":"venue"
},
  "geometry": {"coordinates":[144.97903442399999,-37.8467979431],"type":"Point"}
}