{
  "type": "Feature",
  "properties": {
    "addr:full":"95 Norelle Crs Kangaroo Flat VIC 3555",
    "addr:housenumber":"95",
    "addr:postcode":"3555",
    "addr:street":"Norelle Crs",
    "iso:country":"AU",
    "sg:address":"95 Norelle Crs",
    "sg:city":"Kangaroo Flat",
    "sg:classifiers":[
        {
            "category":"Building & Trades",
            "subcategory":"Construction",
            "type":"Services"
        }
    ],
    "sg:phone":"+61 3 5447 9385",
    "sg:postcode":"3555",
    "sg:province":"VIC",
    "sg:tags":[
        "contractor"
    ],
    "wof:name":"Jones & McGregor Builders",
    "wof:placetype":"venue"
},
  "geometry": {"coordinates":[144.24417114299999,-36.795791626],"type":"Point"}
}