{
  "type": "Feature",
  "properties": {
    "addr:full":"23 Gill St Charters Towers QLD 4820",
    "addr:housenumber":"23",
    "addr:postcode":"4820",
    "addr:street":"Gill St",
    "iso:country":"AU",
    "sg:address":"23 Gill St",
    "sg:city":"Charters Towers",
    "sg:classifiers":[
        {
            "category":"Shopping",
            "subcategory":"Clothing, Apparel, & Fashions",
            "type":"Retail Goods"
        }
    ],
    "sg:phone":"+61 7 4787 7080",
    "sg:postcode":"4820",
    "sg:province":"QLD",
    "sg:tags":[
        "style",
        "clothing",
        "western",
        "accessory"
    ],
    "wof:name":"Outback Traders Australia",
    "wof:placetype":"venue"
},
  "geometry": {"coordinates":[146.25810200000001,-20.075996],"type":"Point"}
}