{
  "type": "Feature",
  "properties": {
    "addr:full":"603 Canterbury Rd Vermont VIC 3133",
    "addr:housenumber":"603",
    "addr:postcode":"3133",
    "addr:street":"Canterbury Rd",
    "iso:country":"AU",
    "sg:address":"603 Canterbury Rd",
    "sg:city":"Vermont",
    "sg:classifiers":[
        {
            "category":"Fast Food",
            "type":"Food & Drink"
        }
    ],
    "sg:phone":"+61 3 9874 8700",
    "sg:postcode":"3133",
    "sg:province":"VIC",
    "sg:tags":[
        "away",
        "take"
    ],
    "wof:name":"Pizza Fever",
    "wof:placetype":"venue"
},
  "geometry": {"coordinates":[145.20823669399999,-37.8331108093],"type":"Point"}
}