{
  "type": "Feature",
  "properties": {
    "addr:full":"Shop 6 & 7, 10 Miltiadis Street Acacia Ridge QLD 4110",
    "addr:housenumber":"shop 6 &;10",
    "addr:postcode":"4110",
    "addr:street":"7;Miltiadis Street",
    "iso:country":"AU",
    "sg:address":"Shop 6 & 7, 10 Miltiadis Street",
    "sg:city":"Acacia Ridge",
    "sg:classifiers":[
        {
            "category":"Building & Trades",
            "subcategory":"Equipment Rental",
            "type":"Services"
        }
    ],
    "sg:phone":"+61 1300 132 281",
    "sg:postcode":"4110",
    "sg:province":"QLD",
    "sg:tags":[
        "fitness"
    ],
    "wof:name":"GymWorks Australia",
    "wof:placetype":"venue"
},
  "geometry": {"coordinates":[153.026885986,-27.5856990814],"type":"Point"}
}