{
  "type": "Feature",
  "properties": {
    "addr:full":"6 Mt Berryman Rd Blenheim QLD 4341",
    "addr:housenumber":"6",
    "addr:postcode":"4341",
    "addr:street":"Mt Berryman Rd",
    "iso:country":"AU",
    "sg:address":"6 Mt Berryman Rd",
    "sg:city":"Blenheim",
    "sg:classifiers":[
        {
            "category":"Farming",
            "subcategory":"Farm",
            "type":"Manufacturing & Wholesale Goods"
        }
    ],
    "sg:phone":"+61 7 5466 4222",
    "sg:postcode":"4341",
    "sg:province":"QLD",
    "sg:tags":[
        "farmer"
    ],
    "wof:name":"Lawson W & V C",
    "wof:placetype":"venue"
},
  "geometry": {"coordinates":[152.32638549800001,-27.6576690674],"type":"Point"}
}