{
  "type": "Feature",
  "properties": {
    "addr:full":"88 Kippax St Surry Hills NSW 2010",
    "addr:housenumber":"88",
    "addr:postcode":"2010",
    "addr:street":"Kippax St",
    "iso:country":"AU",
    "sg:address":"88 Kippax St",
    "sg:city":"Surry Hills",
    "sg:classifiers":[
        {
            "category":"Farming",
            "subcategory":"Orchard",
            "type":"Manufacturing & Wholesale Goods"
        }
    ],
    "sg:phone":"+61 2 9281 2739",
    "sg:postcode":"2010",
    "sg:province":"NSW",
    "sg:tags":[
        "wholesaler",
        "jean",
        "mfrs"
    ],
    "wof:name":"Bubblegum",
    "wof:placetype":"venue"
},
  "geometry": {"coordinates":[151.210647583,-33.8850135803],"type":"Point"}
}