{
  "type": "Feature",
  "properties": {
    "addr:full":"31 Filmer St Clontarf QLD 4019",
    "addr:housenumber":"31",
    "addr:postcode":"4019",
    "addr:street":"Filmer St",
    "iso:country":"AU",
    "sg:address":"31 Filmer St",
    "sg:city":"Clontarf",
    "sg:classifiers":[
        {
            "category":"Banks & Credit Unions",
            "subcategory":"Bureau De Change",
            "type":"Services"
        }
    ],
    "sg:phone":"+61 7 3283 2847",
    "sg:postcode":"4019",
    "sg:province":"QLD",
    "sg:tags":[
        "supply",
        "equipment",
        "beating",
        "panel"
    ],
    "wof:name":"Seetal Spray Booth Pty Ltd",
    "wof:placetype":"venue"
},
  "geometry": {"coordinates":[153.08346557600001,-27.234746933],"type":"Point"}
}