{
  "type": "Feature",
  "properties": {
    "iso:country":"AU",
    "sg:address":"Shop 12 Safeway Arc",
    "sg:city":"Swan Hill",
    "sg:classifiers":[
        {
            "category":"Personal",
            "subcategory":"Beauty Salon",
            "type":"Services"
        }
    ],
    "sg:phone":"+61 3 5033 1702",
    "sg:postcode":"3585",
    "sg:province":"VIC",
    "sg:tags":[
        "hairdresser"
    ],
    "wof:name":"Pips Cutting Room",
    "wof:placetype":"venue"
},
  "geometry": {"coordinates":[143.561554,-35.340969],"type":"Point"}
}