{
  "type": "Feature",
  "properties": {
    "addr:full":"50 Alexander Ave Kallangur QLD 4503",
    "addr:housenumber":"50",
    "addr:postcode":"4503",
    "addr:street":"Alexander Ave",
    "iso:country":"AU",
    "sg:address":"50 Alexander Ave",
    "sg:city":"Kallangur",
    "sg:classifiers":[
        {
            "category":"Communications",
            "type":"Services"
        }
    ],
    "sg:phone":"+61 7 3491 9773",
    "sg:postcode":"4503",
    "sg:province":"QLD",
    "sg:tags":[
        "equipment",
        "satellite"
    ],
    "wof:name":"Jdcom",
    "wof:placetype":"venue"
},
  "geometry": {"coordinates":[152.98580932600001,-27.2411289215],"type":"Point"}
}