{
  "type": "Feature",
  "properties": {
    "addr:full":"Shop 6 Adelaide Arc Adelaide SA 5000",
    "addr:housenumber":"shop 6",
    "addr:postcode":"5000",
    "addr:street":"Arc",
    "iso:country":"AU",
    "sg:address":"Shop 6 Adelaide Arc",
    "sg:city":"Adelaide",
    "sg:classifiers":[
        {
            "category":"Personal",
            "subcategory":"Beauty Salon",
            "type":"Services"
        }
    ],
    "sg:phone":"+61 8 8223 5594",
    "sg:postcode":"5000",
    "sg:province":"SA",
    "sg:tags":[
        "hair",
        "treatment",
        "replacement"
    ],
    "wof:name":"Bonnie Wigs",
    "wof:placetype":"venue"
},
  "geometry": {"coordinates":[138.603683472,-34.9234390259],"type":"Point"}
}