{
  "type": "Feature",
  "properties": {
    "addr:full":"71 Albert Rd Moonah TAS 7009",
    "addr:housenumber":"71",
    "addr:postcode":"7009",
    "addr:street":"Albert Rd",
    "iso:country":"AU",
    "sg:address":"71 Albert Rd",
    "sg:city":"Moonah",
    "sg:classifiers":[
        {
            "category":"Wholesale",
            "subcategory":"Painting Supplies",
            "type":"Manufacturing & Wholesale Goods"
        }
    ],
    "sg:phone":"+61 3 6228 5588",
    "sg:postcode":"7009",
    "sg:province":"TAS",
    "sg:tags":[
        "equipment",
        "spraying"
    ],
    "wof:name":"Ardern's Crash Supplies",
    "wof:placetype":"venue"
},
  "geometry": {"coordinates":[147.300247192,-42.8479423523],"type":"Point"}
}