{
  "type": "Feature",
  "properties": {
    "addr:full":"3 Devon Crt Casino NSW 2470",
    "addr:housenumber":"3",
    "addr:postcode":"2470",
    "addr:street":"Devon Crt",
    "iso:country":"AU",
    "sg:address":"3 Devon Crt",
    "sg:city":"Casino",
    "sg:classifiers":[
        {
            "category":"Building & Trades",
            "subcategory":"Cleaning & Sanitation",
            "type":"Services"
        }
    ],
    "sg:phone":"+61 412 794 357",
    "sg:postcode":"2470",
    "sg:province":"NSW",
    "sg:tags":[
        "grease",
        "trap"
    ],
    "wof:name":"Grelie Waste Services",
    "wof:placetype":"venue"
},
  "geometry": {"coordinates":[153.01373290999999,-28.8642883301],"type":"Point"}
}