{
  "type": "Feature",
  "properties": {
    "addr:full":"6 Alice La Newtown NSW 2042",
    "addr:housenumber":"6",
    "addr:postcode":"2042",
    "addr:street":"Alice La",
    "iso:country":"AU",
    "sg:address":"6 Alice La",
    "sg:city":"Newtown",
    "sg:classifiers":[
        {
            "category":"Manufacturing",
            "subcategory":"Furniture",
            "type":"Manufacturing & Wholesale Goods"
        }
    ],
    "sg:phone":"+61 2 9557 7616",
    "sg:postcode":"2042",
    "sg:province":"NSW",
    "sg:tags":[
        "builder",
        "designer",
        "custom"
    ],
    "wof:name":"Alice Lane Interiors-Furniture",
    "wof:placetype":"venue"
},
  "geometry": {"coordinates":[151.17887899999999,-33.903713],"type":"Point"}
}