{
  "type": "Feature",
  "properties": {
    "addr:full":"6 Bottle Forest Rd Heathcote NSW 2233",
    "addr:housenumber":"6",
    "addr:postcode":"2233",
    "addr:street":"Bottle Forest Rd",
    "iso:country":"AU",
    "sg:address":"6 Bottle Forest Rd",
    "sg:city":"Heathcote",
    "sg:classifiers":[
        {
            "category":"Professional",
            "subcategory":"Art Services",
            "type":"Services"
        }
    ],
    "sg:phone":"+61 2 9520 4250",
    "sg:postcode":"2233",
    "sg:province":"NSW",
    "sg:tags":[
        "graphic",
        "designer"
    ],
    "wof:name":"Dekrank Design",
    "wof:placetype":"venue"
},
  "geometry": {"coordinates":[151.01885986299999,-34.085811615],"type":"Point"}
}