{
  "type": "Feature",
  "properties": {
    "addr:full":"9 Churchill St Williamstown VIC 3016",
    "addr:housenumber":"9",
    "addr:postcode":"3016",
    "addr:street":"Churchill St",
    "iso:country":"AU",
    "sg:address":"9 Churchill St",
    "sg:city":"Williamstown",
    "sg:classifiers":[
        {
            "category":"Manufacturing",
            "subcategory":"Retail Goods",
            "type":"Manufacturing & Wholesale Goods"
        }
    ],
    "sg:phone":"+61 3 9397 0192",
    "sg:postcode":"3016",
    "sg:province":"VIC",
    "sg:tags":[
        "merchant",
        "pump",
        "mfrs"
    ],
    "wof:name":"Australian Fluid Handling",
    "wof:placetype":"venue"
},
  "geometry": {"coordinates":[144.862380981,-37.853477478],"type":"Point"}
}