{
  "type": "Feature",
  "properties": {
    "addr:full":"Target Shopping Centre, Tapleys Hill Rd Fulham Gardens SA 5024",
    "addr:postcode":"5024",
    "addr:street":"Tapleys Hill Rd",
    "iso:country":"AU",
    "sg:address":"Target Shopping Centre, Tapleys Hill Rd",
    "sg:city":"Fulham Gardens",
    "sg:classifiers":[
        {
            "category":"Fast Food",
            "type":"Food & Drink"
        }
    ],
    "sg:phone":"+61 8 8355 4004",
    "sg:postcode":"5024",
    "sg:province":"SA",
    "sg:tags":[
        "away",
        "take"
    ],
    "wof:name":"Noodle Box",
    "wof:placetype":"venue"
},
  "geometry": {"coordinates":[138.51495361299999,-34.9204673767],"type":"Point"}
}