{
  "type": "Feature",
  "properties": {
    "addr:full":"27 Riverview Crs Eumemmerring VIC 3177",
    "addr:housenumber":"27",
    "addr:postcode":"3177",
    "addr:street":"Riverview Crs",
    "iso:country":"AU",
    "sg:address":"27 Riverview Crs",
    "sg:city":"Eumemmerring",
    "sg:classifiers":[
        {
            "category":"Home & Garden",
            "subcategory":"Building Materials",
            "type":"Retail Goods"
        }
    ],
    "sg:phone":"+61 3 9791 8184",
    "sg:postcode":"3177",
    "sg:province":"VIC",
    "sg:tags":[
        "merchant",
        "glass",
        "glazier"
    ],
    "wof:name":"Doveton Glass",
    "wof:placetype":"venue"
},
  "geometry": {"coordinates":[145.249908447,-37.9995613098],"type":"Point"}
}