{
  "type": "Feature",
  "properties": {
    "addr:full":"Shop 1, 653 Old South Head Rd Vaucluse NSW 2030",
    "addr:housenumber":"shop 1 653",
    "addr:postcode":"2030",
    "addr:street":"Old South Head Rd",
    "iso:country":"AU",
    "sg:address":"Shop 1, 653 Old South Head Rd",
    "sg:city":"Vaucluse",
    "sg:classifiers":[
        {
            "category":"Health Services",
            "subcategory":"Doctor",
            "type":"Services"
        }
    ],
    "sg:phone":"+61 2 9371 7677",
    "sg:postcode":"2030",
    "sg:province":"NSW",
    "sg:tags":[
        "podiatrist"
    ],
    "wof:name":"Ahead In Podiatry",
    "wof:placetype":"venue"
},
  "geometry": {"coordinates":[151.27835082999999,-33.8653373718],"type":"Point"}
}