{
  "type": "Feature",
  "properties": {
    "iso:country":"AU",
    "sg:address":"PO Box 96",
    "sg:city":"Willetton",
    "sg:classifiers":[
        {
            "category":"Personal",
            "subcategory":"Tattoo Parlor",
            "type":"Services"
        }
    ],
    "sg:phone":"+61 8 9310 8533",
    "sg:postcode":"6155",
    "sg:province":"WA",
    "sg:tags":[
        "resume"
    ],
    "wof:name":"Burnan Pty. Ltd.",
    "wof:placetype":"venue"
},
  "geometry": {"coordinates":[115.88915299999999,-32.052361],"type":"Point"}
}