{
  "type": "Feature",
  "properties": {
    "addr:full":"1 Main St Penong SA 5690",
    "addr:housenumber":"1",
    "addr:postcode":"5690",
    "addr:street":"Main St",
    "iso:country":"AU",
    "sg:address":"1 Main St",
    "sg:city":"Penong",
    "sg:classifiers":[
        {
            "category":"Travel",
            "subcategory":"Hotels & Motels",
            "type":"Entertainment"
        }
    ],
    "sg:phone":"+61 8 8625 1050",
    "sg:postcode":"5690",
    "sg:province":"SA",
    "sg:tags":[
        "accommodation"
    ],
    "wof:name":"Penong Hotel",
    "wof:placetype":"venue"
},
  "geometry": {"coordinates":[133.57789611800001,-32.1010665894],"type":"Point"}
}