{
  "type": "Feature",
  "properties": {
    "addr:full":"55 Lake St Cairns QLD 4870",
    "addr:housenumber":"55",
    "addr:postcode":"4870",
    "addr:street":"Lake St",
    "iso:country":"AU",
    "sg:address":"55 Lake St",
    "sg:city":"Cairns",
    "sg:classifiers":[
        {
            "category":"Organizations",
            "subcategory":"Community Association",
            "type":"Services"
        }
    ],
    "sg:phone":"+61 7 4051 1028",
    "sg:postcode":"4870",
    "sg:province":"QLD",
    "sg:tags":[
        "organisation",
        "family",
        "welfare"
    ],
    "wof:name":"Queensland AIDS Council",
    "wof:placetype":"venue"
},
  "geometry": {"coordinates":[145.77679443400001,-16.9234466553],"type":"Point"}
}