{
  "type": "Feature",
  "properties": {
    "iso:country":"AU",
    "sg:address":"Maitland St",
    "sg:city":"Narrabri",
    "sg:classifiers":[
        {
            "category":"Social Services",
            "type":"Services"
        }
    ],
    "sg:phone":"+61 2 6792 4471",
    "sg:postcode":"2390",
    "sg:province":"NSW",
    "sg:tags":[
        "domestic",
        "help"
    ],
    "wof:name":"Namoi Ironing Service",
    "wof:placetype":"venue"
},
  "geometry": {"coordinates":[149.78642273,-30.3310527802],"type":"Point"}
}