{
  "type": "Feature",
  "properties": {
    "addr:full":"Fcty 5/ 24 Longstaff Rd Bayswater VIC 3153",
    "addr:housenumber":"/ 24",
    "addr:postcode":"3153",
    "addr:street":"Longstaff Rd",
    "iso:country":"AU",
    "sg:address":"Fcty 5/ 24 Longstaff Rd",
    "sg:city":"Bayswater",
    "sg:classifiers":[
        {
            "category":"Building & Trades",
            "subcategory":"Construction",
            "type":"Services"
        }
    ],
    "sg:phone":"+61 412 340 090",
    "sg:postcode":"3153",
    "sg:province":"VIC",
    "sg:tags":[
        "contractor"
    ],
    "wof:name":"American Homes",
    "wof:placetype":"venue"
},
  "geometry": {"coordinates":[145.28355407699999,-37.835559845],"type":"Point"}
}