{
  "type": "Feature",
  "properties": {
    "addr:full":"12 Abbott Rd Seven Hills NSW 2147",
    "addr:housenumber":"12",
    "addr:postcode":"2147",
    "addr:street":"Abbott Rd",
    "iso:country":"AU",
    "sg:address":"12 Abbott Rd",
    "sg:city":"Seven Hills",
    "sg:classifiers":[
        {
            "category":"Manufacturing",
            "subcategory":"Metals",
            "type":"Manufacturing & Wholesale Goods"
        }
    ],
    "sg:phone":"+61 2 9624 2775",
    "sg:postcode":"2147",
    "sg:province":"NSW",
    "sg:tags":[
        "steel",
        "fabricator",
        "mfrs"
    ],
    "wof:name":"A & J Barber Enterprises",
    "wof:placetype":"venue"
},
  "geometry": {"coordinates":[150.947723389,-33.7676010132],"type":"Point"}
}