{
  "type": "Feature",
  "properties": {
    "addr:full":"Newton Village Shopping Centre, Cnr Newton & Gorge Rds Newton SA 5074",
    "addr:postcode":"5074",
    "addr:street":"Cnr Newton & Gorge Rds",
    "iso:country":"AU",
    "sg:address":"Newton Village Shopping Centre, Cnr Newton & Gorge Rds",
    "sg:city":"Newton",
    "sg:classifiers":[
        {
            "category":"Health Services",
            "subcategory":"Optometrist",
            "type":"Services"
        }
    ],
    "sg:phone":"+61 8 8336 4733",
    "sg:postcode":"5074",
    "sg:province":"SA",
    "wof:name":"National Pharmacies Optical",
    "wof:placetype":"venue"
},
  "geometry": {"coordinates":[138.673706055,-34.8809318542],"type":"Point"}
}