{
  "type": "Feature",
  "properties": {
    "iso:country":"AU",
    "sg:address":"Banksia Drv",
    "sg:city":"Byron Bay",
    "sg:classifiers":[
        {
            "category":"Shopping",
            "subcategory":"Shoes",
            "type":"Retail Goods"
        }
    ],
    "sg:phone":"+61 2 6685 7147",
    "sg:postcode":"2481",
    "sg:province":"NSW",
    "sg:tags":[
        "footwear"
    ],
    "wof:name":"Lois Lane Shoes",
    "wof:placetype":"venue"
},
  "geometry": {"coordinates":[153.58607482900001,-28.6370162964],"type":"Point"}
}