{
  "type": "Feature",
  "properties": {
    "addr:full":"Shop 101 Dolphin Centre 3113 Surfers Paradise Blv Surfers Paradise QLD 4217",
    "addr:housenumber":"101;3113",
    "addr:postcode":"4217",
    "addr:street":"Dolphin Centre;Surfers Paradise Blv",
    "iso:country":"AU",
    "sg:address":"Shop 101 Dolphin Centre 3113",
    "sg:city":"Surfers Paradise Blv Surfers Paradise",
    "sg:classifiers":[
        {
            "category":"Real Estate",
            "subcategory":"Real Estate Agent",
            "type":"Services"
        }
    ],
    "sg:phone":"+61 7 5531 5582",
    "sg:postcode":"4217",
    "sg:province":"QLD",
    "wof:name":"Surf City Realtors",
    "wof:placetype":"venue"
},
  "geometry": {"coordinates":[153.42852783199999,-28.0015106201],"type":"Point"}
}