{
  "type": "Feature",
  "properties": {
    "iso:country":"AU",
    "sg:address":"Shop 2 &#034;The Pembers&#034; Wingecarribee St",
    "sg:city":"Bowral",
    "sg:classifiers":[
        {
            "category":"Cafe",
            "type":"Food & Drink"
        }
    ],
    "sg:phone":"+61 2 4861 6620",
    "sg:postcode":"2576",
    "sg:province":"NSW",
    "wof:name":"Onesta Restaurant",
    "wof:placetype":"venue"
},
  "geometry": {"coordinates":[150.41880798299999,-34.4787712097],"type":"Point"}
}