{
  "type": "Feature",
  "properties": {
    "iso:country":"AU",
    "sg:address":"424 The Esplanade",
    "sg:city":"St Leonards",
    "sg:classifiers":[
        {
            "category":"Food & Beverages",
            "subcategory":"Farmers Market",
            "type":"Retail Goods"
        }
    ],
    "sg:phone":"+61 3 5257 3167",
    "sg:postcode":"3223",
    "sg:province":"VIC",
    "sg:tags":[
        "beekeeper"
    ],
    "wof:name":"Aris Seitanidis",
    "wof:placetype":"venue"
},
  "geometry": {"coordinates":[144.71560700000001,-38.15723],"type":"Point"}
}