{
  "type": "Feature",
  "properties": {
    "iso:country":"AU",
    "sg:address":"13 Clarke St",
    "sg:city":"Warwick",
    "sg:classifiers":[
        {
            "category":"Home & Garden",
            "subcategory":"Building Materials",
            "type":"Retail Goods"
        }
    ],
    "sg:phone":"+61 417 708 905",
    "sg:postcode":"4370",
    "sg:province":"QLD",
    "sg:tags":[
        "fencing"
    ],
    "wof:name":"Get Fenced",
    "wof:placetype":"venue"
},
  "geometry": {"coordinates":[152.01260375999999,-28.2201347351],"type":"Point"}
}