{
  "type": "Feature",
  "properties": {
    "iso:country":"AU",
    "sg:address":"Cavell St",
    "sg:city":"Rockhampton",
    "sg:classifiers":[
        {
            "category":"Organizations",
            "subcategory":"Non-profit Organization",
            "type":"Services"
        }
    ],
    "sg:phone":"+61 7 4927 6383",
    "sg:postcode":"4700",
    "sg:province":"QLD",
    "sg:tags":[
        "support",
        "disability",
        "organisation"
    ],
    "wof:name":"Home Support Association Inc",
    "wof:placetype":"venue"
},
  "geometry": {"coordinates":[150.49740600600001,-23.367357254],"type":"Point"}
}