{
  "type": "Feature",
  "properties": {
    "addr:full":"1 Elizabeth St Maitland SA 5573",
    "addr:housenumber":"1",
    "addr:postcode":"5573",
    "addr:street":"Elizabeth St",
    "iso:country":"AU",
    "sg:address":"1 Elizabeth St",
    "sg:city":"Maitland",
    "sg:classifiers":[
        {
            "category":"Autos & Motor Vehicles",
            "subcategory":"Fuel & Gas Station",
            "type":"Retail Goods"
        }
    ],
    "sg:phone":"+61 8 8832 2383",
    "sg:postcode":"5573",
    "sg:province":"SA",
    "wof:name":"Landts Bob",
    "wof:placetype":"venue"
},
  "geometry": {"coordinates":[137.676055908,-34.3747749329],"type":"Point"}
}