{
  "type": "Feature",
  "properties": {
    "iso:country":"AU",
    "sg:address":"22 Mine St",
    "sg:city":"Port Wakefield",
    "sg:classifiers":[
        {
            "category":"Education",
            "subcategory":"School",
            "type":"Public Place"
        }
    ],
    "sg:phone":"+61 8 8867 1012",
    "sg:postcode":"5550",
    "sg:province":"SA",
    "sg:tags":[
        "state",
        "except",
        "nsw"
    ],
    "wof:name":"Port Wakefield Primary School",
    "wof:placetype":"venue"
},
  "geometry": {"coordinates":[138.147415161,-34.1873855591],"type":"Point"}
}