{
  "type": "Feature",
  "properties": {
    "addr:full":"1400 Bellarine Hwy Wallington VIC 3221",
    "addr:housenumber":"1400",
    "addr:postcode":"3221",
    "addr:street":"Bellarine Hwy",
    "iso:country":"AU",
    "sg:address":"1400 Bellarine Hwy",
    "sg:city":"Wallington",
    "sg:classifiers":[
        {
            "category":"Personal",
            "subcategory":"Beauty Salon",
            "type":"Services"
        }
    ],
    "sg:phone":"+61 3 5250 4825",
    "sg:postcode":"3221",
    "sg:province":"VIC",
    "wof:name":"Wax to the Max",
    "wof:placetype":"venue"
},
  "geometry": {"coordinates":[144.52848800000001,-38.218658],"type":"Point"}
}