{
  "type": "Feature",
  "properties": {
    "iso:country":"AU",
    "sg:address":"3/ 115 Myers St",
    "sg:city":"Geelong",
    "sg:classifiers":[
        {
            "category":"Shopping",
            "subcategory":"Computers & Home Electronics",
            "type":"Retail Goods"
        }
    ],
    "sg:phone":"+61 3 5226 9600",
    "sg:postcode":"3220",
    "sg:province":"VIC",
    "sg:tags":[
        "equipment",
        "multimedia"
    ],
    "wof:name":"Dzign Diezel Group",
    "wof:placetype":"venue"
},
  "geometry": {"coordinates":[144.359604,-38.151424],"type":"Point"}
}