{
  "type": "Feature",
  "properties": {
    "addr:full":"17 Bronwyn St Caloundra QLD 4551",
    "addr:housenumber":"17",
    "addr:postcode":"4551",
    "addr:street":"Bronwyn St",
    "iso:country":"AU",
    "sg:address":"17 Bronwyn St",
    "sg:city":"Caloundra",
    "sg:classifiers":[
        {
            "category":"Autos & Motor Vehicles",
            "subcategory":"Automobile Sales",
            "type":"Retail Goods"
        }
    ],
    "sg:phone":"+61 7 5491 9484",
    "sg:postcode":"4551",
    "sg:province":"QLD",
    "sg:tags":[
        "car",
        "used"
    ],
    "wof:name":"Pelican Motors",
    "wof:placetype":"venue"
},
  "geometry": {"coordinates":[153.12672424300001,-26.8042621613],"type":"Point"}
}