{
  "type": "Feature",
  "properties": {
    "addr:full":"191 Edward Rd Geraldton WA 6530",
    "addr:housenumber":"191",
    "addr:postcode":"6530",
    "addr:street":"Edward Rd",
    "iso:country":"AU",
    "sg:address":"191 Edward Rd",
    "sg:city":"Geraldton",
    "sg:classifiers":[
        {
            "category":"Building & Trades",
            "subcategory":"Landscaping Services",
            "type":"Services"
        }
    ],
    "sg:phone":"+61 408 404 477",
    "sg:postcode":"6530",
    "sg:province":"WA",
    "sg:tags":[
        "stump",
        "tree",
        "felling",
        "removal"
    ],
    "wof:name":"Down To Earth Tree Lopping",
    "wof:placetype":"venue"
},
  "geometry": {"coordinates":[114.656852722,-28.7808074951],"type":"Point"}
}