{
  "type": "Feature",
  "properties": {
    "addr:full":"Third Ave Narromine NSW 2821",
    "addr:postcode":"2821",
    "addr:street":"Third Ave",
    "iso:country":"AU",
    "sg:address":"Third Ave",
    "sg:city":"Narromine",
    "sg:classifiers":[
        {
            "category":"Autos & Motor Vehicles",
            "subcategory":"Fuel & Gas Station",
            "type":"Retail Goods"
        }
    ],
    "sg:phone":"+61 2 6889 1323",
    "sg:postcode":"2821",
    "sg:province":"NSW",
    "wof:name":"BP Australia Limited",
    "wof:placetype":"venue"
},
  "geometry": {"coordinates":[148.24449157699999,-32.2355308533],"type":"Point"}
}