{
  "type": "Feature",
  "properties": {
    "addr:full":"88 Barwon Heads Rd Geelong VIC 3220",
    "addr:housenumber":"88",
    "addr:postcode":"3220",
    "addr:street":"Barwon Heads Rd",
    "iso:country":"AU",
    "sg:address":"88 Barwon Heads Rd",
    "sg:city":"Geelong",
    "sg:classifiers":[
        {
            "category":"Insurance",
            "subcategory":"Hazard Insurance",
            "type":"Services"
        }
    ],
    "sg:phone":"+61 3 5241 6966",
    "sg:postcode":"3220",
    "sg:province":"VIC",
    "sg:tags":[
        "fire",
        "accident",
        "marine"
    ],
    "wof:name":"Geelong Boating Centre",
    "wof:placetype":"venue"
},
  "geometry": {"coordinates":[144.36646999999999,-38.170532],"type":"Point"}
}