{
  "type": "Feature",
  "properties": {
    "addr:full":"89 Renwick Rd Redfern NSW 2016",
    "addr:housenumber":"89",
    "addr:postcode":"2016",
    "addr:street":"Renwick Rd",
    "iso:country":"AU",
    "sg:address":"89 Renwick Rd",
    "sg:city":"Redfern",
    "sg:classifiers":[
        {
            "category":"Organizations",
            "subcategory":"Labor Organization",
            "type":"Services"
        }
    ],
    "sg:phone":"+61 2 9319 2022",
    "sg:postcode":"2016",
    "sg:province":"NSW",
    "sg:tags":[
        "union"
    ],
    "wof:name":"A.F.U.L.D.",
    "wof:placetype":"venue"
},
  "geometry": {"coordinates":[151.20173645,-33.8916397095],"type":"Point"}
}