{
  "type": "Feature",
  "properties": {
    "addr:full":"Barossa Valley Hwy Lyndoch SA 5351",
    "addr:postcode":"5351",
    "addr:street":"Valley Hwy",
    "iso:country":"AU",
    "sg:address":"Barossa Valley Hwy",
    "sg:city":"Lyndoch",
    "sg:classifiers":[
        {
            "category":"Farming",
            "subcategory":"Vineyard",
            "type":"Manufacturing & Wholesale Goods"
        }
    ],
    "sg:phone":"+61 8 8524 4511",
    "sg:postcode":"5351",
    "sg:province":"SA",
    "sg:tags":[
        "winery"
    ],
    "wof:name":"Woodlands Vineyard",
    "wof:placetype":"venue"
},
  "geometry": {"coordinates":[138.888946533,-34.5996894836],"type":"Point"}
}