{
  "type": "Feature",
  "properties": {
    "addr:full":"Unit 8 Edale Way Balga WA 6061",
    "addr:postcode":"6061",
    "addr:street":"Edale Way",
    "iso:country":"AU",
    "sg:address":"Unit 8",
    "sg:city":"Edale Way Balga",
    "sg:classifiers":[
        {
            "category":"Professional",
            "type":"Services"
        }
    ],
    "sg:phone":"+61 8 9388 2590",
    "sg:postcode":"6061",
    "sg:province":"WA",
    "sg:tags":[
        "courier"
    ],
    "wof:name":"Dog Swamp Delivery Service",
    "wof:placetype":"venue"
},
  "geometry": {"coordinates":[115.848892212,-31.86901474],"type":"Point"}
}