{
  "type": "Feature",
  "properties": {
    "addr:full":"Unit 1 8 Cornwell Rd Ingleburn NSW 2565",
    "addr:housenumber":"8",
    "addr:postcode":"2565",
    "addr:street":"Cornwell Rd",
    "iso:country":"AU",
    "sg:address":"Unit 1 8 Cornwell Rd",
    "sg:city":"Ingleburn",
    "sg:classifiers":[
        {
            "category":"Home & Garden",
            "subcategory":"Building Materials",
            "type":"Retail Goods"
        }
    ],
    "sg:phone":"+61 2 9605 3609",
    "sg:postcode":"2565",
    "sg:province":"NSW",
    "sg:tags":[
        "fire",
        "resistant",
        "supply"
    ],
    "wof:name":"AB Radiant Enterprise Pty Ltd",
    "wof:placetype":"venue"
},
  "geometry": {"coordinates":[150.85870361299999,-34.0007667542],"type":"Point"}
}