{
  "type": "Feature",
  "properties": {
    "addr:full":"88 Hiller St Devonport TAS 7310",
    "addr:housenumber":"88",
    "addr:postcode":"7310",
    "addr:street":"Hiller St",
    "iso:country":"AU",
    "sg:address":"88 Hiller St",
    "sg:city":"Devonport",
    "sg:classifiers":[
        {
            "category":"Communications",
            "subcategory":"Film & Video Production",
            "type":"Services"
        }
    ],
    "sg:phone":"+61 1800 234 616",
    "sg:postcode":"7310",
    "sg:province":"TAS",
    "sg:tags":[
        "consultant",
        "material",
        "handling"
    ],
    "wof:name":"Harris Hygenie Handling & Storage",
    "wof:placetype":"venue"
},
  "geometry": {"coordinates":[146.35675048799999,-41.1900024414],"type":"Point"}
}