{
  "type": "Feature",
  "properties": {
    "addr:full":"1st flr, 520 Anzac Hwy Glenelg East SA 5045",
    "addr:housenumber":"520",
    "addr:postcode":"5045",
    "addr:street":"Anzac Hwy Glenelg East",
    "iso:country":"AU",
    "sg:address":"1st flr, 520 Anzac Hwy",
    "sg:city":"Glenelg East",
    "sg:classifiers":[
        {
            "category":"Health Services",
            "subcategory":"Doctor",
            "type":"Services"
        }
    ],
    "sg:phone":"+61 8 8376 9766",
    "sg:postcode":"5045",
    "sg:province":"SA",
    "sg:tags":[
        "podiatrist"
    ],
    "wof:name":"Healthy Feet Podiatry",
    "wof:placetype":"venue"
},
  "geometry": {"coordinates":[138.53758199999999,-34.97538],"type":"Point"}
}