{
  "type": "Feature",
  "properties": {
    "iso:country":"AU",
    "sg:address":"70 Shaw Rd",
    "sg:city":"Bohle",
    "sg:classifiers":[
        {
            "category":"Home & Garden",
            "subcategory":"Building Materials",
            "type":"Retail Goods"
        }
    ],
    "sg:phone":"+61 7 4774 8100",
    "sg:postcode":"4818",
    "sg:province":"QLD",
    "sg:tags":[
        "pre-mixed",
        "concrete"
    ],
    "wof:name":"Townsville Concrete",
    "wof:placetype":"venue"
},
  "geometry": {"coordinates":[146.70280500000001,-19.261656],"type":"Point"}
}