{
  "type": "Feature",
  "properties": {
    "iso:country":"AU",
    "sg:address":"184 Main South Rd",
    "sg:city":"Morphett Vale",
    "sg:classifiers":[
        {
            "category":"Health Services",
            "subcategory":"Dentist",
            "type":"Services"
        }
    ],
    "sg:phone":"+61 8 8382 2436",
    "sg:postcode":"5162",
    "sg:province":"SA",
    "wof:name":"Hollfelder Tanja Dr",
    "wof:placetype":"venue"
},
  "geometry": {"coordinates":[138.523803711,-35.1251029968],"type":"Point"}
}