{
  "type": "Feature",
  "properties": {
    "iso:country":"AU",
    "sg:address":"9 Captains La",
    "sg:city":"Fremantle",
    "sg:classifiers":[
        {
            "category":"Arts & Performance",
            "subcategory":"Art Gallery",
            "type":"Entertainment"
        }
    ],
    "sg:phone":"+61 418 944 147",
    "sg:postcode":"6160",
    "sg:province":"WA",
    "wof:name":"Carter Studios",
    "wof:placetype":"venue"
},
  "geometry": {"coordinates":[115.74894,-32.05341],"type":"Point"}
}