{
  "type": "Feature",
  "properties": {
    "addr:full":"Lot 6 West St Bowen QLD 4805",
    "addr:postcode":"4805",
    "addr:street":"St",
    "iso:country":"AU",
    "sg:address":"Lot 6 West St",
    "sg:city":"Bowen",
    "sg:classifiers":[
        {
            "category":"Retail",
            "subcategory":"Auto Repair",
            "type":"Services"
        }
    ],
    "sg:phone":"+61 7 4786 2226",
    "sg:postcode":"4805",
    "sg:province":"QLD",
    "sg:tags":[
        "electrical"
    ],
    "wof:name":"Tim Warren Auto Airconditioning & Electrical",
    "wof:placetype":"venue"
},
  "geometry": {"coordinates":[148.23089599599999,-20.0021076202],"type":"Point"}
}