{
  "type": "Feature",
  "properties": {
    "addr:full":"114 High St Avoca VIC 3467",
    "addr:housenumber":"114",
    "addr:postcode":"3467",
    "addr:street":"High St",
    "iso:country":"AU",
    "sg:address":"114 High St",
    "sg:city":"Avoca",
    "sg:classifiers":[
        {
            "category":"Food & Beverages",
            "subcategory":"Bakery",
            "type":"Retail Goods"
        }
    ],
    "sg:phone":"+61 3 5465 3388",
    "sg:postcode":"3467",
    "sg:province":"VIC",
    "sg:tags":[
        "baker"
    ],
    "wof:name":"Parkview Bakery",
    "wof:placetype":"venue"
},
  "geometry": {"coordinates":[143.47462463400001,-37.0892944336],"type":"Point"}
}