{
  "type": "Feature",
  "properties": {
    "iso:country":"AU",
    "sg:address":"129 Brisbane St",
    "sg:city":"Tamworth",
    "sg:classifiers":[
        {
            "category":"Real Estate",
            "subcategory":"Architect",
            "type":"Services"
        }
    ],
    "sg:phone":"+61 2 6766 1691",
    "sg:postcode":"2340",
    "sg:province":"NSW",
    "wof:name":"Hunter M J",
    "wof:placetype":"venue"
},
  "geometry": {"coordinates":[150.93389892600001,-31.0871429443],"type":"Point"}
}