{
  "type": "Feature",
  "properties": {
    "iso:country":"AU",
    "sg:address":"33 Beryl St",
    "sg:city":"Tweed Heads",
    "sg:classifiers":[
        {
            "category":"Health Services",
            "subcategory":"Doctor",
            "type":"Services"
        }
    ],
    "sg:phone":"+61 7 5599 2988",
    "sg:postcode":"2485",
    "sg:province":"NSW",
    "sg:tags":[
        "medical",
        "practitioner"
    ],
    "wof:name":"Chambers Richard Dr",
    "wof:placetype":"venue"
},
  "geometry": {"coordinates":[153.54106140100001,-28.1742362976],"type":"Point"}
}