{
  "type": "Feature",
  "properties": {
    "iso:country":"AU",
    "sg:address":"19 Strahan St",
    "sg:city":"Burnie South",
    "sg:classifiers":[
        {
            "category":"Parking",
            "subcategory":"Bicycle",
            "type":"Transportation"
        }
    ],
    "sg:phone":"+61 3 6431 5044",
    "sg:postcode":"7320",
    "sg:province":"TAS",
    "sg:tags":[
        "sprocket"
    ],
    "wof:name":"BSC Motion Technology",
    "wof:placetype":"venue"
},
  "geometry": {"coordinates":[145.909821,-41.060432],"type":"Point"}
}