{
  "type": "Feature",
  "properties": {
    "addr:full":"8 Raglan St Sale VIC 3850",
    "addr:housenumber":"8",
    "addr:postcode":"3850",
    "addr:street":"Raglan St",
    "iso:country":"AU",
    "sg:address":"8 Raglan St",
    "sg:city":"Sale",
    "sg:classifiers":[
        {
            "category":"Building & Trades",
            "subcategory":"Landscaping Services",
            "type":"Services"
        }
    ],
    "sg:phone":"+61 418 517 272",
    "sg:postcode":"3850",
    "sg:province":"VIC",
    "sg:tags":[
        "designer",
        "landscape",
        "contractor"
    ],
    "wof:name":"Filmer Liz Landscaping",
    "wof:placetype":"venue"
},
  "geometry": {"coordinates":[147.06095886200001,-38.0976486206],"type":"Point"}
}