{
  "type": "Feature",
  "properties": {
    "addr:full":"7 Inala Ave Tugun QLD 4224",
    "addr:housenumber":"7",
    "addr:postcode":"4224",
    "addr:street":"Inala Ave",
    "iso:country":"AU",
    "sg:address":"7 Inala Ave",
    "sg:city":"Tugun",
    "sg:classifiers":[
        {
            "category":"Building & Trades",
            "subcategory":"Plumbing",
            "type":"Services"
        }
    ],
    "sg:phone":"+61 418 374 186",
    "sg:postcode":"4224",
    "sg:province":"QLD",
    "sg:tags":[
        "plumber",
        "gasfitters"
    ],
    "wof:name":"Tugun Plumbing Services Pty Ltd",
    "wof:placetype":"venue"
},
  "geometry": {"coordinates":[153.48793029800001,-28.1431274414],"type":"Point"}
}