{
  "type": "Feature",
  "properties": {
    "addr:full":"79 Benenlong Rd Cremorne NSW 2090",
    "addr:housenumber":"79",
    "addr:postcode":"2090",
    "addr:street":"Benenlong Rd",
    "iso:country":"AU",
    "sg:address":"79 Benenlong Rd",
    "sg:city":"Cremorne",
    "sg:classifiers":[
        {
            "category":"Building & Trades",
            "subcategory":"Construction",
            "type":"Services"
        }
    ],
    "sg:phone":"+61 2 9953 7582",
    "sg:postcode":"2090",
    "sg:province":"NSW",
    "sg:tags":[
        "contractor"
    ],
    "wof:name":"Bontom Pty Ltd",
    "wof:placetype":"venue"
},
  "geometry": {"coordinates":[151.229248047,-33.8264465332],"type":"Point"}
}