{
  "type": "Feature",
  "properties": {
    "iso:country":"AU",
    "sg:address":"Unit 9, 17 Tile St",
    "sg:city":"Wacol",
    "sg:classifiers":[
        {
            "category":"Wholesale",
            "subcategory":"Machinery & Supplies",
            "type":"Manufacturing & Wholesale Goods"
        }
    ],
    "sg:phone":"+61 1300 793 712",
    "sg:postcode":"4076",
    "sg:province":"QLD",
    "sg:tags":[
        "rigging",
        "equipment",
        "hoisting"
    ],
    "wof:name":"Specialised Stage Engineering Pty Ltd",
    "wof:placetype":"venue"
},
  "geometry": {"coordinates":[152.93252563499999,-27.6040019989],"type":"Point"}
}