{
  "type": "Feature",
  "properties": {
    "addr:full":"12 Monger St Perth WA 6000",
    "addr:housenumber":"12",
    "addr:postcode":"6000",
    "addr:street":"Monger St",
    "iso:country":"AU",
    "sg:address":"12 Monger St",
    "sg:city":"Perth",
    "sg:classifiers":[
        {
            "category":"Social Services",
            "subcategory":"Retirement Home",
            "type":"Services"
        }
    ],
    "sg:phone":"+61 8 9227 9355",
    "sg:postcode":"6000",
    "sg:province":"WA",
    "sg:tags":[
        "environmental",
        "consultant",
        "pollution"
    ],
    "wof:name":"Syrinx Environmental Pty Ltd",
    "wof:placetype":"venue"
},
  "geometry": {"coordinates":[115.86402893099999,-31.9451065063],"type":"Point"}
}