{
  "type": "Feature",
  "properties": {
    "addr:full":"3A Nixon Street Shepparton VIC 3630",
    "addr:housenumber":"3a",
    "addr:postcode":"3630",
    "addr:street":"Nixon Street",
    "iso:country":"AU",
    "sg:address":"3A Nixon Street",
    "sg:city":"Shepparton",
    "sg:classifiers":[
        {
            "category":"Health Services",
            "subcategory":"Health Practitioner",
            "type":"Services"
        }
    ],
    "sg:phone":"+61 3 5831 5400",
    "sg:postcode":"3630",
    "sg:province":"VIC",
    "sg:tags":[
        "myotherapy"
    ],
    "wof:name":"Shepparton Myotherapy",
    "wof:placetype":"venue"
},
  "geometry": {"coordinates":[145.40330505399999,-36.3782997131],"type":"Point"}
}