{
  "type": "Feature",
  "properties": {
    "addr:full":"Shop 3 1223 Ross River Rd Rasmussen QLD 4815",
    "addr:housenumber":"shop 3 1223",
    "addr:postcode":"4815",
    "addr:street":"Ross River Rd",
    "iso:country":"AU",
    "sg:address":"Shop 3 1223 Ross River Rd",
    "sg:city":"Rasmussen",
    "sg:classifiers":[
        {
            "category":"Food & Beverages",
            "subcategory":"Bakery",
            "type":"Retail Goods"
        }
    ],
    "sg:phone":"+61 7 4789 2727",
    "sg:postcode":"4815",
    "sg:province":"QLD",
    "sg:tags":[
        "baker"
    ],
    "wof:name":"Brumbys Bakeries",
    "wof:placetype":"venue"
},
  "geometry": {"coordinates":[146.731674,-19.364025],"type":"Point"}
}