{
  "type": "Feature",
  "properties": {
    "addr:full":"PO Box 119 Bairnsdale VIC 3875",
    "addr:postcode":"3875",
    "iso:country":"AU",
    "sg:address":"PO Box 119",
    "sg:city":"Bairnsdale",
    "sg:classifiers":[
        {
            "category":"Professional",
            "subcategory":"Art Services",
            "type":"Services"
        }
    ],
    "sg:phone":"+61 3 5156 0777",
    "sg:postcode":"3875",
    "sg:province":"VIC",
    "sg:tags":[
        "interior",
        "decorator"
    ],
    "wof:name":"Barb Brownlow Interior Design",
    "wof:placetype":"venue"
},
  "geometry": {"coordinates":[147.61129760700001,-37.8314208984],"type":"Point"}
}