{
  "type": "Feature",
  "properties": {
    "iso:country":"AU",
    "sg:address":"Hassall & James Ruse Dr",
    "sg:city":"Rosehill",
    "sg:classifiers":[
        {
            "category":"Autos & Motor Vehicles",
            "subcategory":"Fuel & Gas Station",
            "type":"Retail Goods"
        }
    ],
    "sg:phone":"+61 2 9689 2342",
    "sg:postcode":"2142",
    "sg:province":"NSW",
    "wof:name":"BP Australia Pty Ltd",
    "wof:placetype":"venue"
},
  "geometry": {"coordinates":[151.02180480999999,-33.8191642761],"type":"Point"}
}