{
  "type": "Feature",
  "properties": {
    "iso:country":"AU",
    "sg:address":"27 Decaux Ave",
    "sg:city":"Port Willunga",
    "sg:classifiers":[
        {
            "category":"Utilities",
            "subcategory":"Water",
            "type":"Services"
        }
    ],
    "sg:phone":"+61 428 837 534",
    "sg:postcode":"5173",
    "sg:province":"SA",
    "sg:tags":[
        "hot",
        "system"
    ],
    "wof:name":"Hentschke Jeff",
    "wof:placetype":"venue"
},
  "geometry": {"coordinates":[138.45588684099999,-35.2667732239],"type":"Point"}
}