{
  "type": "Feature",
  "properties": {
    "addr:full":"671 High St Thornbury VIC 3071",
    "addr:housenumber":"671",
    "addr:postcode":"3071",
    "addr:street":"High St",
    "iso:country":"AU",
    "sg:address":"671 High St",
    "sg:city":"Thornbury",
    "sg:classifiers":[
        {
            "category":"Food & Beverages",
            "subcategory":"Supermarket",
            "type":"Retail Goods"
        }
    ],
    "sg:phone":"+61 3 9484 6886",
    "sg:postcode":"3071",
    "sg:province":"VIC",
    "sg:tags":[
        "grocery",
        "store"
    ],
    "wof:name":"IGA Friendly Grocers",
    "wof:placetype":"venue"
},
  "geometry": {"coordinates":[145.000091553,-37.7606544495],"type":"Point"}
}