{
  "type": "Feature",
  "properties": {
    "iso:country":"AU",
    "sg:address":"77 Salmon St",
    "sg:city":"Port Melbourne",
    "sg:classifiers":[
        {
            "category":"Building & Trades",
            "subcategory":"Construction",
            "type":"Services"
        }
    ],
    "sg:phone":"+61 1800 505 047",
    "sg:postcode":"3207",
    "sg:province":"VIC",
    "sg:tags":[
        "industrial",
        "commercial",
        "air conditioning"
    ],
    "wof:name":"Evap-Air Hire",
    "wof:placetype":"venue"
},
  "geometry": {"coordinates":[144.923996,-37.832153],"type":"Point"}
}