{
  "type": "Feature",
  "properties": {
    "addr:full":"5 Nairana St Invermay TAS 7248",
    "addr:housenumber":"5",
    "addr:postcode":"7248",
    "addr:street":"Nairana St",
    "iso:country":"AU",
    "sg:address":"5 Nairana St",
    "sg:city":"Invermay",
    "sg:classifiers":[
        {
            "category":"Autos & Motor Vehicles",
            "subcategory":"Automobile Sales",
            "type":"Retail Goods"
        }
    ],
    "sg:phone":"+61 3 6331 5809",
    "sg:postcode":"7248",
    "sg:province":"TAS",
    "sg:tags":[
        "bus",
        "truck",
        "new"
    ],
    "wof:name":"Burt & Campbell",
    "wof:placetype":"venue"
},
  "geometry": {"coordinates":[147.126663208,-41.4251403809],"type":"Point"}
}