{
  "type": "Feature",
  "properties": {
    "addr:full":"2 Hely St Gosford NSW 2250",
    "addr:housenumber":"2",
    "addr:postcode":"2250",
    "addr:street":"Hely St",
    "iso:country":"AU",
    "sg:address":"2 Hely St",
    "sg:city":"Gosford",
    "sg:classifiers":[
        {
            "category":"Travel",
            "subcategory":"Hotels & Motels",
            "type":"Entertainment"
        }
    ],
    "sg:phone":"+61 2 4324 6266",
    "sg:postcode":"2250",
    "sg:province":"NSW",
    "sg:tags":[
        "pub"
    ],
    "wof:name":"The Settlers Tavern",
    "wof:placetype":"venue"
},
  "geometry": {"coordinates":[151.34251403799999,-33.4237251282],"type":"Point"}
}