{
  "type": "Feature",
  "properties": {
    "iso:country":"AU",
    "sg:address":"56 Eaglemount Rd",
    "sg:city":"Andergrove",
    "sg:classifiers":[
        {
            "category":"Building & Trades",
            "subcategory":"Landscaping Services",
            "type":"Services"
        }
    ],
    "sg:phone":"+61 7 4955 2782",
    "sg:postcode":"4740",
    "sg:province":"QLD",
    "sg:tags":[
        "inspection"
    ],
    "wof:name":"Frank Gorman",
    "wof:placetype":"venue"
},
  "geometry": {"coordinates":[149.17584199999999,-21.09218],"type":"Point"}
}