{
  "type": "Feature",
  "properties": {
    "iso:country":"AU",
    "sg:address":"299 Beamish St",
    "sg:city":"Campsie",
    "sg:classifiers":[
        {
            "category":"Restaurant",
            "type":"Food & Drink"
        }
    ],
    "sg:phone":"+61 2 9789 2335",
    "sg:postcode":"2194",
    "sg:province":"NSW",
    "wof:name":"Asiana Restaurant",
    "wof:placetype":"venue"
},
  "geometry": {"coordinates":[151.104248,-33.913277],"type":"Point"}
}