{
  "type": "Feature",
  "properties": {
    "iso:country":"AU",
    "sg:address":"Main St",
    "sg:city":"Minlaton",
    "sg:classifiers":[
        {
            "category":"Health Services",
            "subcategory":"Dentist",
            "type":"Services"
        }
    ],
    "sg:phone":"+61 419 846 267",
    "sg:postcode":"5575",
    "sg:province":"SA",
    "wof:name":"Minlaton Dental",
    "wof:placetype":"venue"
},
  "geometry": {"coordinates":[137.595977783,-34.7704429626],"type":"Point"}
}