{
  "type": "Feature",
  "properties": {
    "addr:full":"Licola Rd Jamieson VIC 3723",
    "addr:postcode":"3723",
    "addr:street":"Licola Rd",
    "iso:country":"AU",
    "sg:address":"Licola Rd",
    "sg:city":"Jamieson",
    "sg:classifiers":[
        {
            "category":"Banks & Credit Unions",
            "subcategory":"Investment Brokerage",
            "type":"Services"
        }
    ],
    "sg:phone":"+61 3 5777 0645",
    "sg:postcode":"3723",
    "sg:province":"VIC",
    "sg:tags":[
        "share",
        "broker",
        "stock"
    ],
    "wof:name":"Goldsmith J D",
    "wof:placetype":"venue"
},
  "geometry": {"coordinates":[146.631103516,-37.636806488],"type":"Point"}
}