{
  "type": "Feature",
  "properties": {
    "addr:full":"Bass Hwy Grantville VIC 3984",
    "addr:postcode":"3984",
    "addr:street":"Bass Hwy",
    "iso:country":"AU",
    "sg:address":"Bass Hwy",
    "sg:city":"Grantville",
    "sg:classifiers":[
        {
            "category":"Social Services",
            "subcategory":"Adult Care",
            "type":"Services"
        }
    ],
    "sg:phone":"+61 3 5623 2888",
    "sg:postcode":"3984",
    "sg:province":"VIC",
    "sg:tags":[
        "towing"
    ],
    "wof:name":"The Gurdies Towing",
    "wof:placetype":"venue"
},
  "geometry": {"coordinates":[145.53062439000001,-38.4075088501],"type":"Point"}
}