{
  "type": "Feature",
  "properties": {
    "addr:full":"Suite 17, 6- 8 Old Castle Hill Rd Castle Hill NSW 2154",
    "addr:housenumber":"6 8",
    "addr:postcode":"2154",
    "addr:street":"Old Castle Hill Rd",
    "iso:country":"AU",
    "sg:address":"Suite 17, 6- 8 Old Castle Hill Rd",
    "sg:city":"Castle Hill",
    "sg:classifiers":[
        {
            "category":"Insurance",
            "subcategory":"Hazard Insurance",
            "type":"Services"
        }
    ],
    "sg:phone":"+61 2 9899 8155",
    "sg:postcode":"2154",
    "sg:province":"NSW",
    "sg:tags":[
        "motor",
        "vehicle"
    ],
    "wof:name":"Berkrey Insurance Consultants Pty Ltd",
    "wof:placetype":"venue"
},
  "geometry": {"coordinates":[151.00833129899999,-33.7307128906],"type":"Point"}
}