{
  "type": "Feature",
  "properties": {
    "iso:country":"AU",
    "sg:address":"35 Robertson Ave",
    "sg:city":"Margate",
    "sg:classifiers":[
        {
            "category":"Building & Trades",
            "subcategory":"Construction",
            "type":"Services"
        }
    ],
    "sg:phone":"+61 7 3889 3138",
    "sg:postcode":"4019",
    "sg:province":"QLD",
    "sg:tags":[
        "concrete",
        "contractor"
    ],
    "wof:name":"Home Concreting",
    "wof:placetype":"venue"
},
  "geometry": {"coordinates":[153.109573364,-27.2399578094],"type":"Point"}
}