{
  "type": "Feature",
  "properties": {
    "addr:full":"99 Denham St (On Highway) Rockhampton QLD 4700",
    "addr:housenumber":"99",
    "addr:postcode":"4700",
    "addr:street":"Denham St",
    "iso:country":"AU",
    "sg:address":"99 Denham St",
    "sg:city":"(On Highway) Rockhampton",
    "sg:classifiers":[
        {
            "category":"Recreation",
            "subcategory":"Fishing",
            "type":"Entertainment"
        }
    ],
    "sg:phone":"+61 7 4922 4833",
    "sg:postcode":"4700",
    "sg:province":"QLD",
    "sg:tags":[
        "tackle"
    ],
    "wof:name":"Barra Jacks Tackleworld",
    "wof:placetype":"venue"
},
  "geometry": {"coordinates":[150.498535156,-23.3876800537],"type":"Point"}
}