{
  "type": "Feature",
  "properties": {
    "addr:full":"35 Rainbow St Sandgate QLD 4017",
    "addr:housenumber":"35",
    "addr:postcode":"4017",
    "addr:street":"Rainbow St",
    "iso:country":"AU",
    "sg:address":"35 Rainbow St",
    "sg:city":"Sandgate",
    "sg:classifiers":[
        {
            "category":"Fast Food",
            "type":"Food & Drink"
        }
    ],
    "sg:phone":"+61 7 3269 5333",
    "sg:postcode":"4017",
    "sg:province":"QLD",
    "sg:tags":[
        "away",
        "take"
    ],
    "wof:name":"Rainbow Takeaway",
    "wof:placetype":"venue"
},
  "geometry": {"coordinates":[153.06646728499999,-27.3212394714],"type":"Point"}
}