{
  "type": "Feature",
  "properties": {
    "iso:country":"AU",
    "sg:address":"11 Keppel St",
    "sg:city":"Bathurst",
    "sg:classifiers":[
        {
            "category":"Wholesale",
            "subcategory":"Farm Supplies",
            "type":"Manufacturing & Wholesale Goods"
        }
    ],
    "sg:phone":"+61 2 6331 2844",
    "sg:postcode":"2795",
    "sg:province":"NSW",
    "sg:tags":[
        "feed",
        "supplement",
        "stock"
    ],
    "wof:name":"Bedwells Feed Barn & Produce Merchants",
    "wof:placetype":"venue"
},
  "geometry": {"coordinates":[149.58058166500001,-33.4231376648],"type":"Point"}
}