{
  "type": "Feature",
  "properties": {
    "addr:full":"155 Alfred St Narraweena NSW 2099",
    "addr:housenumber":"155",
    "addr:postcode":"2099",
    "addr:street":"Alfred St",
    "iso:country":"AU",
    "sg:address":"155 Alfred St",
    "sg:city":"Narraweena",
    "sg:classifiers":[
        {
            "category":"Personal",
            "subcategory":"Massage",
            "type":"Services"
        }
    ],
    "sg:phone":"+61 409 876 015",
    "sg:postcode":"2099",
    "sg:province":"NSW",
    "sg:tags":[
        "therapy"
    ],
    "wof:name":"Northern Beaches Sports & Remedial Massage",
    "wof:placetype":"venue"
},
  "geometry": {"coordinates":[151.27601623499999,-33.7460861206],"type":"Point"}
}