{
  "type": "Feature",
  "properties": {
    "iso:country":"AU",
    "sg:address":"763 Hunter St",
    "sg:city":"Newcastle",
    "sg:classifiers":[
        {
            "category":"Professional",
            "subcategory":"Business Services",
            "type":"Services"
        }
    ],
    "sg:phone":"+61 2 4965 4277",
    "sg:postcode":"2300",
    "sg:province":"NSW",
    "sg:tags":[
        "consultant",
        "system"
    ],
    "wof:name":"Business Thinking Systems",
    "wof:placetype":"venue"
},
  "geometry": {"coordinates":[151.759903,-32.925556],"type":"Point"}
}