{
  "type": "Feature",
  "properties": {
    "iso:country":"AU",
    "sg:address":"152 Semaphore Rd",
    "sg:city":"Exeter",
    "sg:classifiers":[
        {
            "category":"Travel",
            "subcategory":"Hotels & Motels",
            "type":"Entertainment"
        }
    ],
    "sg:phone":"+61 8 8449 6716",
    "sg:postcode":"5019",
    "sg:province":"SA",
    "sg:tags":[
        "pub"
    ],
    "wof:name":"Exeter Hotel",
    "wof:placetype":"venue"
},
  "geometry": {"coordinates":[138.49105835,-34.8399543762],"type":"Point"}
}