{
  "type": "Feature",
  "properties": {
    "iso:country":"AU",
    "sg:address":"49 The Northern Rd",
    "sg:city":"Narellan",
    "sg:classifiers":[
        {
            "category":"Autos & Motor Vehicles",
            "subcategory":"Auto Supplies",
            "type":"Retail Goods"
        }
    ],
    "sg:phone":"+61 2 4648 1555",
    "sg:postcode":"2567",
    "sg:province":"NSW",
    "sg:tags":[
        "tyre"
    ],
    "wof:name":"Yokohama",
    "wof:placetype":"venue"
},
  "geometry": {"coordinates":[150.735305786,-34.0403556824],"type":"Point"}
}