{
  "type": "Feature",
  "properties": {
    "addr:full":"43 Grove St Eltham VIC 3095",
    "addr:housenumber":"43",
    "addr:postcode":"3095",
    "addr:street":"Grove St",
    "iso:country":"AU",
    "sg:address":"43 Grove St",
    "sg:city":"Eltham",
    "sg:classifiers":[
        {
            "category":"Real Estate",
            "subcategory":"Architect",
            "type":"Services"
        }
    ],
    "sg:phone":"+61 3 9439 4413",
    "sg:postcode":"3095",
    "sg:province":"VIC",
    "wof:name":"Grove Design",
    "wof:placetype":"venue"
},
  "geometry": {"coordinates":[145.157104492,-37.7112083435],"type":"Point"}
}