{
  "type": "Feature",
  "properties": {
    "iso:country":"AU",
    "sg:address":"145 Stirling Hwy",
    "sg:city":"Nedlands",
    "sg:classifiers":[
        {
            "category":"Health Services",
            "subcategory":"Chiropractor",
            "type":"Services"
        }
    ],
    "sg:phone":"+61 8 9389 6060",
    "sg:postcode":"6009",
    "sg:province":"WA",
    "wof:name":"Longevity Wellness Centre",
    "wof:placetype":"venue"
},
  "geometry": {"coordinates":[115.815811,-31.976608],"type":"Point"}
}