{
  "type": "Feature",
  "properties": {
    "addr:full":"4/ 23 Avalon Pde Avalon NSW 2107",
    "addr:housenumber":"/ 23",
    "addr:postcode":"2107",
    "addr:street":"Avalon Pde",
    "iso:country":"AU",
    "sg:address":"4/ 23 Avalon Pde",
    "sg:city":"Avalon",
    "sg:classifiers":[
        {
            "category":"Education",
            "subcategory":"Special Training",
            "type":"Public Place"
        }
    ],
    "sg:phone":"+61 2 9918 7614",
    "sg:postcode":"2107",
    "sg:province":"NSW",
    "sg:tags":[
        "feldenkrais"
    ],
    "wof:name":"Feldenkrais Method",
    "wof:placetype":"venue"
},
  "geometry": {"coordinates":[151.329544067,-33.6366577148],"type":"Point"}
}