{
  "type": "Feature",
  "properties": {
    "addr:full":"3-4/ 398 Elizabeth St Melbourne VIC 3000",
    "addr:housenumber":"3-4 / 398",
    "addr:postcode":"3000",
    "addr:street":"Elizabeth St",
    "iso:country":"AU",
    "sg:address":"3-4/ 398 Elizabeth St",
    "sg:city":"Melbourne",
    "sg:classifiers":[
        {
            "category":"Professional",
            "subcategory":"Computer Services",
            "type":"Services"
        }
    ],
    "sg:phone":"+61 1300 725 944",
    "sg:postcode":"3000",
    "sg:province":"VIC",
    "sg:tags":[
        "package",
        "software"
    ],
    "wof:name":"Mail Order Software Australia",
    "wof:placetype":"venue"
},
  "geometry": {"coordinates":[144.96107482900001,-37.8092880249],"type":"Point"}
}