{
  "type": "Feature",
  "properties": {
    "iso:country":"AU",
    "sg:address":"586 Sydney Rd",
    "sg:city":"Brunswick",
    "sg:classifiers":[
        {
            "category":"Shopping",
            "subcategory":"Bridal",
            "type":"Retail Goods"
        }
    ],
    "sg:phone":"+61 3 9380 6276",
    "sg:postcode":"3056",
    "sg:province":"VIC",
    "sg:tags":[
        "hire",
        "wear"
    ],
    "wof:name":"Formal Wear Of Melbourne",
    "wof:placetype":"venue"
},
  "geometry": {"coordinates":[144.962768555,-37.7639579773],"type":"Point"}
}