{
  "type": "Feature",
  "properties": {
    "iso:country":"AU",
    "sg:address":"57 Tasman Rd",
    "sg:city":"Avalon",
    "sg:classifiers":[
        {
            "category":"Manufacturing",
            "subcategory":"Retail Goods",
            "type":"Manufacturing & Wholesale Goods"
        }
    ],
    "sg:phone":"+61 415 899 462",
    "sg:postcode":"2107",
    "sg:province":"NSW",
    "sg:tags":[
        "merchant",
        "pump",
        "mfrs"
    ],
    "wof:name":"Stuart McMaster Electrical",
    "wof:placetype":"venue"
},
  "geometry": {"coordinates":[151.33627319300001,-33.6276283264],"type":"Point"}
}