{
  "type": "Feature",
  "properties": {
    "iso:country":"AU",
    "sg:address":"Iden Rd",
    "sg:city":"Bagdad",
    "sg:classifiers":[
        {
            "category":"Retail",
            "subcategory":"Animal Services",
            "type":"Services"
        }
    ],
    "sg:phone":"+61 3 6268 6154",
    "sg:postcode":"7030",
    "sg:province":"TAS",
    "sg:tags":[
        "breeder",
        "sheep",
        "stud",
        "cattle"
    ],
    "wof:name":"Iden Murray Grey Cattle Stud",
    "wof:placetype":"venue"
},
  "geometry": {"coordinates":[147.218261719,-42.6039352417],"type":"Point"}
}