{
  "type": "Feature",
  "properties": {
    "iso:country":"AU",
    "sg:address":"69 Mawson Pde",
    "sg:city":"Chifley",
    "sg:classifiers":[
        {
            "category":"Building & Trades",
            "subcategory":"Construction",
            "type":"Services"
        }
    ],
    "sg:phone":"+61 2 9661 1133",
    "sg:postcode":"2036",
    "sg:province":"NSW",
    "sg:tags":[
        "scaffolding"
    ],
    "wof:name":"Couda Scaffolds Pty Ltd",
    "wof:placetype":"venue"
},
  "geometry": {"coordinates":[151.24156189000001,-33.9744110107],"type":"Point"}
}