{
  "type": "Feature",
  "properties": {
    "addr:full":"Suite 1, 223 High St Thomastown VIC 3074",
    "addr:housenumber":"223",
    "addr:postcode":"3074",
    "addr:street":"High St",
    "iso:country":"AU",
    "sg:address":"Suite 1, 223 High St",
    "sg:city":"Thomastown",
    "sg:classifiers":[
        {
            "category":"Real Estate",
            "subcategory":"Real Estate Agent",
            "type":"Services"
        }
    ],
    "sg:phone":"+61 3 9466 2222",
    "sg:postcode":"3074",
    "sg:province":"VIC",
    "wof:name":"Thomas Moreland Real Estate Pty Ltd",
    "wof:placetype":"venue"
},
  "geometry": {"coordinates":[145.01377868599999,-37.6796455383],"type":"Point"}
}