{
  "type": "Feature",
  "properties": {
    "addr:full":"12 Chapel St St Kilda VIC 3182",
    "addr:housenumber":"12",
    "addr:postcode":"3182",
    "addr:street":"Chapel St",
    "iso:country":"AU",
    "sg:address":"12 Chapel St",
    "sg:city":"St Kilda",
    "sg:classifiers":[
        {
            "category":"Personal",
            "type":"Services"
        }
    ],
    "sg:phone":"+61 3 9521 2770",
    "sg:postcode":"3182",
    "sg:province":"VIC",
    "sg:tags":[
        "counselling",
        "alcohol",
        "drug"
    ],
    "wof:name":"The Bridge Centre",
    "wof:placetype":"venue"
},
  "geometry": {"coordinates":[144.991897583,-37.8608512878],"type":"Point"}
}