{
  "type": "Feature",
  "properties": {
    "addr:full":"45 Cameron St Traralgon VIC 3844",
    "addr:housenumber":"45",
    "addr:postcode":"3844",
    "addr:street":"Cameron St",
    "iso:country":"AU",
    "sg:address":"45 Cameron St",
    "sg:city":"Traralgon",
    "sg:classifiers":[
        {
            "category":"Food & Beverages",
            "subcategory":"Groceries & Convenience Stores",
            "type":"Retail Goods"
        }
    ],
    "sg:phone":"+61 3 5176 6601",
    "sg:postcode":"3844",
    "sg:province":"VIC",
    "wof:name":"Cameron St Four Square Mini Mart",
    "wof:placetype":"venue"
},
  "geometry": {"coordinates":[146.55601501500001,-38.207359314],"type":"Point"}
}