{
  "type": "Feature",
  "properties": {
    "addr:full":"Unit 6/ 2 Armiger Crt Holden Hill SA 5088",
    "addr:housenumber":"2",
    "addr:postcode":"5088",
    "addr:street":"Armiger Crt",
    "iso:country":"AU",
    "sg:address":"Unit 6/ 2 Armiger Crt",
    "sg:city":"Holden Hill",
    "sg:classifiers":[
        {
            "category":"Retail",
            "subcategory":"Auto Repair",
            "type":"Services"
        }
    ],
    "sg:phone":"+61 8 8396 1780",
    "sg:postcode":"5088",
    "sg:province":"SA",
    "sg:tags":[
        "beater",
        "painter",
        "panel"
    ],
    "wof:name":"Obahn Crash Repair",
    "wof:placetype":"venue"
},
  "geometry": {"coordinates":[138.67918395999999,-34.8475532532],"type":"Point"}
}