{
  "type": "Feature",
  "properties": {
    "iso:country":"AU",
    "sg:address":"94 Garden St",
    "sg:city":"Narrabeen",
    "sg:classifiers":[
        {
            "category":"Building & Trades",
            "subcategory":"Pest Control",
            "type":"Services"
        }
    ],
    "sg:phone":"+61 2 9913 8898",
    "sg:postcode":"2101",
    "sg:province":"NSW",
    "wof:name":"Struk G A",
    "wof:placetype":"venue"
},
  "geometry": {"coordinates":[151.294724,-33.700249],"type":"Point"}
}