{
  "type": "Feature",
  "properties": {
    "addr:full":"PO Box 475 Nundah QLD 4012",
    "addr:postcode":"4012",
    "iso:country":"AU",
    "sg:address":"PO Box 475",
    "sg:city":"Nundah",
    "sg:classifiers":[
        {
            "category":"Building & Trades",
            "subcategory":"Construction",
            "type":"Services"
        }
    ],
    "sg:phone":"+61 414 228 110",
    "sg:postcode":"4012",
    "sg:province":"QLD",
    "sg:tags":[
        "renovation",
        "alterations",
        "extension",
        "contractor"
    ],
    "wof:name":"ADA Renovations Pty Ltd",
    "wof:placetype":"venue"
},
  "geometry": {"coordinates":[153.05999755900001,-27.4019603729],"type":"Point"}
}