{
  "type": "Feature",
  "properties": {
    "iso:country":"AU",
    "sg:address":"Lvl 2/ 11 Queens Rd",
    "sg:city":"Melbourne",
    "sg:classifiers":[
        {
            "category":"Wholesale",
            "subcategory":"Electrical",
            "type":"Manufacturing & Wholesale Goods"
        }
    ],
    "sg:phone":"+61 3 9867 7033",
    "sg:postcode":"3004",
    "sg:province":"VIC",
    "sg:tags":[
        "wholesaler",
        "mfrs",
        "accessory"
    ],
    "wof:name":"Muchison Holdings Ltd",
    "wof:placetype":"venue"
},
  "geometry": {"coordinates":[144.97398376500001,-37.8380279541],"type":"Point"}
}