{
  "type": "Feature",
  "properties": {
    "addr:full":"357 Grey St Glen Innes NSW 2370",
    "addr:housenumber":"357",
    "addr:postcode":"2370",
    "addr:street":"Grey St",
    "iso:country":"AU",
    "sg:address":"357 Grey St",
    "sg:city":"Glen Innes",
    "sg:classifiers":[
        {
            "category":"Utilities",
            "subcategory":"Electric",
            "type":"Services"
        }
    ],
    "sg:phone":"+61 2 6732 1455",
    "sg:postcode":"2370",
    "sg:province":"NSW",
    "sg:tags":[
        "electrical",
        "contractor"
    ],
    "wof:name":"Thom & Pollock Installations",
    "wof:placetype":"venue"
},
  "geometry": {"coordinates":[151.73622131400001,-29.7356090546],"type":"Point"}
}