{
  "type": "Feature",
  "properties": {
    "addr:full":"24 View St Wooloowin QLD 4030",
    "addr:housenumber":"24",
    "addr:postcode":"4030",
    "addr:street":"View St",
    "iso:country":"AU",
    "sg:address":"24 View St",
    "sg:city":"Wooloowin",
    "sg:classifiers":[
        {
            "category":"Real Estate",
            "subcategory":"Surveying",
            "type":"Services"
        }
    ],
    "sg:phone":"+61 7 3262 4267",
    "sg:postcode":"4030",
    "sg:province":"QLD",
    "sg:tags":[
        "surveyor",
        "quantity"
    ],
    "wof:name":"MDH Consultants",
    "wof:placetype":"venue"
},
  "geometry": {"coordinates":[153.04657,-27.418179],"type":"Point"}
}