{
  "type": "Feature",
  "properties": {
    "iso:country":"AU",
    "sg:address":"Suite 5, 1533 Point Nepean Rd",
    "sg:city":"Rosebud West",
    "sg:classifiers":[
        {
            "category":"Health Services",
            "subcategory":"Health Practitioner",
            "type":"Services"
        }
    ],
    "sg:phone":"+61 1300 101 020",
    "sg:postcode":"3940",
    "sg:province":"VIC",
    "sg:tags":[
        "osteopath"
    ],
    "wof:name":"Head To Toe Healthcare",
    "wof:placetype":"venue"
},
  "geometry": {"coordinates":[144.883712769,-38.3617095947],"type":"Point"}
}