{
  "type": "Feature",
  "properties": {
    "iso:country":"AU",
    "sg:address":"Shop 6/7 Rose City Shoppingworld",
    "sg:city":"Warwick",
    "sg:classifiers":[
        {
            "category":"Shopping",
            "subcategory":"Clothing, Apparel, & Fashions",
            "type":"Retail Goods"
        }
    ],
    "sg:phone":"+61 7 4661 7033",
    "sg:postcode":"4370",
    "sg:province":"QLD",
    "sg:tags":[
        "menswear"
    ],
    "wof:name":"Lowes Menswear",
    "wof:placetype":"venue"
},
  "geometry": {"coordinates":[152.03465270999999,-28.2181301117],"type":"Point"}
}