{
  "type": "Feature",
  "properties": {
    "addr:full":"927 Drummond St Carlton VIC 3053",
    "addr:housenumber":"927",
    "addr:postcode":"3053",
    "addr:street":"Drummond St",
    "iso:country":"AU",
    "sg:address":"927 Drummond St",
    "sg:city":"Carlton",
    "sg:classifiers":[
        {
            "category":"Industrial Area",
            "type":"Public Place"
        }
    ],
    "sg:phone":"+61 3 9380 2830",
    "sg:postcode":"3053",
    "sg:province":"VIC",
    "sg:tags":[
        "consulting",
        "chemist"
    ],
    "wof:name":"Hart Analytical Pty Ltd",
    "wof:placetype":"venue"
},
  "geometry": {"coordinates":[144.96751403799999,-37.8037872314],"type":"Point"}
}