{
  "type": "Feature",
  "properties": {
    "addr:full":"4 Fern St Ardeer VIC 3022",
    "addr:housenumber":"4",
    "addr:postcode":"3022",
    "addr:street":"Fern St",
    "iso:country":"AU",
    "sg:address":"4 Fern St",
    "sg:city":"Ardeer",
    "sg:classifiers":[
        {
            "category":"Banks & Credit Unions",
            "subcategory":"Bank",
            "type":"Services"
        }
    ],
    "sg:phone":"+61 3 9360 4696",
    "sg:postcode":"3022",
    "sg:province":"VIC",
    "sg:tags":[
        "leather",
        "cutting",
        "fabric",
        "plastic"
    ],
    "wof:name":"Viet Trung Welding",
    "wof:placetype":"venue"
},
  "geometry": {"coordinates":[144.79894999999999,-37.78487],"type":"Point"}
}