{
  "type": "Feature",
  "properties": {
    "addr:full":"Cnr Horizon Drv & Riverhills Rd Middle Park QLD 4074",
    "addr:postcode":"4074",
    "addr:street":"Cnr Horizon Drv & Riverhills Rd",
    "iso:country":"AU",
    "sg:address":"Cnr Horizon Drv & Riverhills Rd",
    "sg:city":"Middle Park",
    "sg:classifiers":[
        {
            "category":"Health Services",
            "subcategory":"Doctor",
            "type":"Services"
        }
    ],
    "sg:phone":"+61 7 3376 5743",
    "sg:postcode":"4074",
    "sg:province":"QLD",
    "sg:tags":[
        "podiatrist"
    ],
    "wof:name":"Elwell-Sutton Robyn",
    "wof:placetype":"venue"
},
  "geometry": {"coordinates":[152.92379760700001,-27.5552577972],"type":"Point"}
}