{
  "type": "Feature",
  "properties": {
    "addr:full":"176 Watts Rd Wilson WA 6107",
    "addr:housenumber":"176",
    "addr:postcode":"6107",
    "addr:street":"Watts Rd",
    "iso:country":"AU",
    "sg:address":"176 Watts Rd",
    "sg:city":"Wilson",
    "sg:classifiers":[
        {
            "category":"Home & Garden",
            "subcategory":"Carpets & Floor Coverings",
            "type":"Retail Goods"
        }
    ],
    "sg:phone":"+61 419 867 985",
    "sg:postcode":"6107",
    "sg:province":"WA",
    "sg:tags":[
        "tile",
        "wall",
        "layer"
    ],
    "wof:name":"New Tile Tiling Service",
    "wof:placetype":"venue"
},
  "geometry": {"coordinates":[115.908538818,-32.0257148743],"type":"Point"}
}