{
  "type": "Feature",
  "properties": {
    "addr:full":"265 Victoria Rd Rydalmere NSW 2116",
    "addr:housenumber":"265",
    "addr:postcode":"2116",
    "addr:street":"Victoria Rd",
    "iso:country":"AU",
    "sg:address":"265 Victoria Rd",
    "sg:city":"Rydalmere",
    "sg:classifiers":[
        {
            "category":"Food & Beverages",
            "subcategory":"Supermarket",
            "type":"Retail Goods"
        }
    ],
    "sg:phone":"+61 2 9684 4998",
    "sg:postcode":"2116",
    "sg:province":"NSW",
    "sg:tags":[
        "grocery",
        "store"
    ],
    "wof:name":"Food Plus Ltd",
    "wof:placetype":"venue"
},
  "geometry": {"coordinates":[151.16090393100001,-33.9110908508],"type":"Point"}
}