{
  "type": "Feature",
  "properties": {
    "iso:country":"AU",
    "sg:address":"40 Parramatta Rd",
    "sg:city":"Summer Hill",
    "sg:classifiers":[
        {
            "category":"Autos & Motor Vehicles",
            "subcategory":"Boat Sales",
            "type":"Retail Goods"
        }
    ],
    "sg:phone":"+61 2 9716 8555",
    "sg:postcode":"2130",
    "sg:province":"NSW",
    "sg:tags":[
        "yacht"
    ],
    "wof:name":"Nordik",
    "wof:placetype":"venue"
},
  "geometry": {"coordinates":[151.14224243199999,-33.8880195618],"type":"Point"}
}