{
  "type": "Feature",
  "properties": {
    "addr:full":"117 Melon St Braybrook VIC 3019",
    "addr:housenumber":"117",
    "addr:postcode":"3019",
    "addr:street":"Melon St",
    "iso:country":"AU",
    "sg:address":"117 Melon St",
    "sg:city":"Braybrook",
    "sg:classifiers":[
        {
            "category":"Utilities",
            "type":"Services"
        }
    ],
    "sg:phone":"+61 3 9318 3505",
    "sg:postcode":"3019",
    "sg:province":"VIC",
    "sg:tags":[
        "refrigeration",
        "industrial",
        "commercial",
        "retail"
    ],
    "wof:name":"Miles Ice Refrigeration & Airconditioning",
    "wof:placetype":"venue"
},
  "geometry": {"coordinates":[144.859375,-37.7815322876],"type":"Point"}
}