{
  "type": "Feature",
  "properties": {
    "addr:full":"PO Box 107 Frenchs Forest NSW 2086",
    "addr:postcode":"2086",
    "iso:country":"AU",
    "sg:address":"PO Box 107",
    "sg:city":"Frenchs Forest",
    "sg:classifiers":[
        {
            "category":"Wholesale",
            "subcategory":"Construction Materials",
            "type":"Manufacturing & Wholesale Goods"
        }
    ],
    "sg:phone":"+61 2 9907 2044",
    "sg:postcode":"2086",
    "sg:province":"NSW",
    "sg:tags":[
        "lift"
    ],
    "wof:name":"Elevator Services Group Pty Ltd",
    "wof:placetype":"venue"
},
  "geometry": {"coordinates":[151.23475647000001,-33.7508201599],"type":"Point"}
}