{
  "type": "Feature",
  "properties": {
    "iso:country":"AU",
    "sg:address":"53A Vincent Rd",
    "sg:city":"Wangaratta",
    "sg:classifiers":[
        {
            "category":"Food & Beverages",
            "subcategory":"Specialty",
            "type":"Retail Goods"
        }
    ],
    "sg:phone":"+61 3 5722 4980",
    "sg:postcode":"3677",
    "sg:province":"VIC",
    "sg:tags":[
        "delicacy"
    ],
    "wof:name":"Foodshed The",
    "wof:placetype":"venue"
},
  "geometry": {"coordinates":[146.31590270999999,-36.3654594421],"type":"Point"}
}