{
  "type": "Feature",
  "properties": {
    "addr:full":"12 Parkhurst Drv Knoxfield VIC 3180",
    "addr:housenumber":"12",
    "addr:postcode":"3180",
    "addr:street":"Parkhurst Drv",
    "iso:country":"AU",
    "sg:address":"12 Parkhurst Drv",
    "sg:city":"Knoxfield",
    "sg:classifiers":[
        {
            "category":"Shopping",
            "subcategory":"Stationery & Office Supplies",
            "type":"Retail Goods"
        }
    ],
    "sg:phone":"+61 3 9887 3600",
    "sg:postcode":"3180",
    "sg:province":"VIC",
    "sg:tags":[
        "packaging",
        "material"
    ],
    "wof:name":"APR Trading",
    "wof:placetype":"venue"
},
  "geometry": {"coordinates":[145.25263977,-37.8734855652],"type":"Point"}
}