{
  "type": "Feature",
  "properties": {
    "addr:full":"672 Waterworks Rd Ashgrove QLD 4060",
    "addr:housenumber":"672",
    "addr:postcode":"4060",
    "addr:street":"Waterworks Rd",
    "iso:country":"AU",
    "sg:address":"672 Waterworks Rd",
    "sg:city":"Ashgrove",
    "sg:classifiers":[
        {
            "category":"Personal",
            "subcategory":"Beauty Salon",
            "type":"Services"
        }
    ],
    "sg:phone":"+61 7 3366 2577",
    "sg:postcode":"4060",
    "sg:province":"QLD",
    "wof:name":"Beauty Enhancement by Brigitte",
    "wof:placetype":"venue"
},
  "geometry": {"coordinates":[152.96885681099999,-27.4485874176],"type":"Point"}
}