{
  "type": "Feature",
  "properties": {
    "addr:full":"71 Tulip St Cheltenham VIC 3192",
    "addr:housenumber":"71",
    "addr:postcode":"3192",
    "addr:street":"Tulip St",
    "iso:country":"AU",
    "sg:address":"71 Tulip St",
    "sg:city":"Cheltenham",
    "sg:classifiers":[
        {
            "category":"Home & Garden",
            "subcategory":"Building Materials",
            "type":"Retail Goods"
        }
    ],
    "sg:phone":"+61 3 9584 4833",
    "sg:postcode":"3192",
    "sg:province":"VIC",
    "sg:tags":[
        "merchant",
        "glass",
        "glazier"
    ],
    "wof:name":"Euroglaze (Aust) Pty Ltd",
    "wof:placetype":"venue"
},
  "geometry": {"coordinates":[145.03114318900001,-37.9632949829],"type":"Point"}
}