{
  "type": "Feature",
  "properties": {
    "iso:country":"AU",
    "sg:address":"Iredale Spawater Rd",
    "sg:city":"Via Withcott",
    "sg:classifiers":[
        {
            "category":"Conference Center",
            "type":"Public Place"
        }
    ],
    "sg:phone":"+61 7 4638 3466",
    "sg:postcode":"4352",
    "sg:province":"QLD",
    "sg:tags":[
        "venue",
        "convention"
    ],
    "wof:name":"Clewleys Country Haven",
    "wof:placetype":"venue"
},
  "geometry": {"coordinates":[152.02394100000001,-27.553061],"type":"Point"}
}