{
  "type": "Feature",
  "properties": {
    "iso:country":"AU",
    "sg:address":"100 Harold St",
    "sg:city":"Wantirna",
    "sg:classifiers":[
        {
            "category":"Health Services",
            "subcategory":"Nursing And Care Facility",
            "type":"Services"
        }
    ],
    "sg:phone":"+61 3 9837 6555",
    "sg:postcode":"3152",
    "sg:province":"VIC",
    "sg:tags":[
        "home"
    ],
    "wof:name":"Salford Park",
    "wof:placetype":"venue"
},
  "geometry": {"coordinates":[145.22810363799999,-37.854637146],"type":"Point"}
}