{
  "type": "Feature",
  "properties": {
    "iso:country":"AU",
    "sg:address":"60- 62 Jardine St",
    "sg:city":"Fairy Meadow",
    "sg:classifiers":[
        {
            "category":"Industrial Area",
            "type":"Public Place"
        }
    ],
    "sg:phone":"+61 2 4283 3222",
    "sg:postcode":"2519",
    "sg:province":"NSW",
    "sg:tags":[
        "protective",
        "clothing"
    ],
    "wof:name":"Clobber Leather",
    "wof:placetype":"venue"
},
  "geometry": {"coordinates":[150.89343299999999,-34.387726],"type":"Point"}
}