{
  "type": "Feature",
  "properties": {
    "iso:country":"AU",
    "sg:address":"42 High St",
    "sg:city":"Rutherglen",
    "sg:classifiers":[
        {
            "category":"Building & Trades",
            "subcategory":"Construction",
            "type":"Services"
        }
    ],
    "sg:phone":"+61 2 6032 9099",
    "sg:postcode":"3685",
    "sg:province":"VIC",
    "sg:tags":[
        "earth",
        "excavating",
        "moving",
        "contractor"
    ],
    "wof:name":"Gascon Earthmoving",
    "wof:placetype":"venue"
},
  "geometry": {"coordinates":[146.46429443400001,-36.047870636],"type":"Point"}
}