{
  "type": "Feature",
  "properties": {
    "addr:full":"Cnr Ninth St & Orange Ave Mildura VIC 3500",
    "addr:postcode":"3500",
    "addr:street":"Cnr Ninth St & Orange Ave",
    "iso:country":"AU",
    "sg:address":"Cnr Ninth St & Orange Ave",
    "sg:city":"Mildura",
    "sg:classifiers":[
        {
            "category":"Retail",
            "subcategory":"Auto Repair",
            "type":"Services"
        }
    ],
    "sg:phone":"+61 3 5023 0581",
    "sg:postcode":"3500",
    "sg:province":"VIC",
    "sg:tags":[
        "clutch",
        "brake"
    ],
    "wof:name":"Goodyear Autocare",
    "wof:placetype":"venue"
},
  "geometry": {"coordinates":[142.169754028,-34.1954841614],"type":"Point"}
}