{
  "type": "Feature",
  "properties": {
    "addr:full":"50 Washington Dr Mildura VIC 3500",
    "addr:housenumber":"50",
    "addr:postcode":"3500",
    "addr:street":"Washington Dr",
    "iso:country":"AU",
    "sg:address":"50 Washington Dr",
    "sg:city":"Mildura",
    "sg:classifiers":[
        {
            "category":"Utilities",
            "subcategory":"Electric",
            "type":"Services"
        }
    ],
    "sg:phone":"+61 419 333 570",
    "sg:postcode":"3500",
    "sg:province":"VIC",
    "sg:tags":[
        "electrical",
        "contractor"
    ],
    "wof:name":"Beechey Electrical & Airconditioning",
    "wof:placetype":"venue"
},
  "geometry": {"coordinates":[142.150924683,-34.1722984314],"type":"Point"}
}