{
  "type": "Feature",
  "properties": {
    "addr:full":"Cnr Bridge & Baillie Sts North Lismore NSW 2480",
    "addr:postcode":"2480",
    "addr:street":"Cnr Bridge & Baillie Sts North",
    "iso:country":"AU",
    "sg:address":"Cnr Bridge & Baillie Sts",
    "sg:city":"North Lismore",
    "sg:classifiers":[
        {
            "category":"Manufacturing",
            "subcategory":"Glass & Minerals",
            "type":"Manufacturing & Wholesale Goods"
        }
    ],
    "sg:phone":"+61 2 6621 5497",
    "sg:postcode":"2480",
    "sg:province":"NSW",
    "sg:tags":[
        "merchant",
        "granite",
        "marble"
    ],
    "wof:name":"Beckinsales Monumental Masons Pty Ltd",
    "wof:placetype":"venue"
},
  "geometry": {"coordinates":[153.277267456,-28.8035869598],"type":"Point"}
}