{
  "type": "Feature",
  "properties": {
    "addr:full":"121 Scarborough Beach Rd Mt Hawthorn WA 6016",
    "addr:housenumber":"121",
    "addr:postcode":"6016",
    "addr:street":"Scarborough Beach Rd",
    "iso:country":"AU",
    "sg:address":"121 Scarborough Beach Rd",
    "sg:city":"Mt Hawthorn",
    "sg:classifiers":[
        {
            "category":"Retail",
            "subcategory":"Driving School",
            "type":"Services"
        }
    ],
    "sg:phone":"+61 8 9201 1577",
    "sg:postcode":"6016",
    "sg:province":"WA",
    "wof:name":"Vincent Driving School",
    "wof:placetype":"venue"
},
  "geometry": {"coordinates":[115.84236908,-31.9228897095],"type":"Point"}
}