{
  "type": "Feature",
  "properties": {
    "iso:country":"AU",
    "sg:address":"261 Tapleys Hill Rd",
    "sg:city":"Seaton",
    "sg:classifiers":[
        {
            "category":"Autos & Motor Vehicles",
            "subcategory":"Boat Sales",
            "type":"Retail Goods"
        }
    ],
    "sg:phone":"+61 8 8244 8007",
    "sg:postcode":"5023",
    "sg:province":"SA",
    "sg:tags":[
        "yacht"
    ],
    "wof:name":"Blue Water Boats Pty Ltd",
    "wof:placetype":"venue"
},
  "geometry": {"coordinates":[138.51388549800001,-34.8915290833],"type":"Point"}
}