{
  "type": "Feature",
  "properties": {
    "addr:full":"12 Hamley St Morphettville SA 5043",
    "addr:housenumber":"12",
    "addr:postcode":"5043",
    "addr:street":"Hamley St",
    "iso:country":"AU",
    "sg:address":"12 Hamley St",
    "sg:city":"Morphettville",
    "sg:classifiers":[
        {
            "category":"Home & Garden",
            "subcategory":"Building Materials",
            "type":"Retail Goods"
        }
    ],
    "sg:phone":"+61 8 8277 2271",
    "sg:postcode":"5043",
    "sg:province":"SA",
    "sg:tags":[
        "lawn",
        "cutting",
        "maintenance"
    ],
    "wof:name":"Mow Me Down Lawn Service",
    "wof:placetype":"venue"
},
  "geometry": {"coordinates":[138.546997,-34.994675],"type":"Point"}
}