{
  "type": "Feature",
  "properties": {
    "addr:full":"64 Robey St Mascot NSW 2020",
    "addr:housenumber":"64",
    "addr:postcode":"2020",
    "addr:street":"Robey St",
    "iso:country":"AU",
    "sg:address":"64 Robey St",
    "sg:city":"Mascot",
    "sg:classifiers":[
        {
            "category":"Retail",
            "subcategory":"Auto Repair",
            "type":"Services"
        }
    ],
    "sg:phone":"+61 2 9667 2386",
    "sg:postcode":"2020",
    "sg:province":"NSW",
    "sg:tags":[
        "beater",
        "painter",
        "panel"
    ],
    "wof:name":"Robey Smash Repairs",
    "wof:placetype":"venue"
},
  "geometry": {"coordinates":[151.190353394,-33.9312934875],"type":"Point"}
}