{
  "type": "Feature",
  "properties": {
    "addr:full":"Thew Pde Dee Why NSW 2099",
    "addr:postcode":"2099",
    "iso:country":"AU",
    "sg:address":"Thew Pde",
    "sg:city":"Dee Why",
    "sg:classifiers":[
        {
            "category":"Communications",
            "subcategory":"Television Station",
            "type":"Services"
        }
    ],
    "sg:phone":"+61 2 9931 7100",
    "sg:postcode":"2099",
    "sg:province":"NSW",
    "sg:tags":[
        "wholesaler",
        "wire",
        "mfrs",
        "electric",
        "cable"
    ],
    "wof:name":"Prysmian Cables & Systems",
    "wof:placetype":"venue"
},
  "geometry": {"coordinates":[151.28302001899999,-33.7359199524],"type":"Point"}
}