{
  "type": "Feature",
  "properties": {
    "addr:full":"Everinghams La Frederickton NSW 2440",
    "addr:postcode":"2440",
    "iso:country":"AU",
    "sg:address":"Everinghams La",
    "sg:city":"Frederickton",
    "sg:classifiers":[
        {
            "category":"Building & Trades",
            "subcategory":"Construction",
            "type":"Services"
        }
    ],
    "sg:phone":"+61 2 6566 8962",
    "sg:postcode":"2440",
    "sg:province":"NSW",
    "sg:tags":[
        "contractor"
    ],
    "wof:name":"Ashley Elford",
    "wof:placetype":"venue"
},
  "geometry": {"coordinates":[152.855209,-31.030956],"type":"Point"}
}