{
  "type": "Feature",
  "properties": {
    "addr:full":"71 Coglin St Brompton SA 5007",
    "addr:housenumber":"71",
    "addr:postcode":"5007",
    "addr:street":"Coglin St",
    "iso:country":"AU",
    "sg:address":"71 Coglin St",
    "sg:city":"Brompton",
    "sg:classifiers":[
        {
            "category":"Retail",
            "subcategory":"Laundry & Dry Cleaning",
            "type":"Services"
        }
    ],
    "sg:phone":"+61 8 8340 3309",
    "sg:postcode":"5007",
    "sg:province":"SA",
    "wof:name":"Five Star Linen Service",
    "wof:placetype":"venue"
},
  "geometry": {"coordinates":[138.57267761200001,-34.8993911743],"type":"Point"}
}