{
  "type": "Feature",
  "properties": {
    "iso:country":"AU",
    "sg:address":"2 Notar Drv",
    "sg:city":"Ormeau",
    "sg:classifiers":[
        {
            "category":"Building & Trades",
            "subcategory":"Construction",
            "type":"Services"
        }
    ],
    "sg:phone":"+61 7 5546 6219",
    "sg:postcode":"4208",
    "sg:province":"QLD",
    "sg:tags":[
        "earth",
        "excavating",
        "moving",
        "contractor"
    ],
    "wof:name":"Peachey Constructions",
    "wof:placetype":"venue"
},
  "geometry": {"coordinates":[153.24848938,-27.7589607239],"type":"Point"}
}