{
  "type": "Feature",
  "properties": {
    "iso:country":"AU",
    "sg:address":"Selma Rd",
    "sg:city":"Emerald",
    "sg:classifiers":[
        {
            "category":"Farming",
            "subcategory":"Farm",
            "type":"Manufacturing & Wholesale Goods"
        }
    ],
    "sg:phone":"+61 7 4982 0011",
    "sg:postcode":"4720",
    "sg:province":"QLD",
    "sg:tags":[
        "farmer"
    ],
    "wof:name":"2PH Farms",
    "wof:placetype":"venue"
},
  "geometry": {"coordinates":[148.147217,-23.528637],"type":"Point"}
}