{
  "type": "Feature",
  "properties": {
    "addr:full":"PO Box 875N Cairns North QLD 4870",
    "addr:postcode":"4870",
    "iso:country":"AU",
    "sg:address":"PO Box 875N",
    "sg:city":"Cairns North",
    "sg:classifiers":[
        {
            "category":"Building & Trades",
            "subcategory":"Landscaping Services",
            "type":"Services"
        }
    ],
    "sg:phone":"+61 412 582 953",
    "sg:postcode":"4870",
    "sg:province":"QLD",
    "sg:tags":[
        "designer",
        "landscape",
        "contractor"
    ],
    "wof:name":"R.C.M. Earthmoving",
    "wof:placetype":"venue"
},
  "geometry": {"coordinates":[145.759002686,-16.9041805267],"type":"Point"}
}