{
  "type": "Feature",
  "properties": {
    "addr:full":"Cooma Landfill, Monaro Hwy Cooma NSW 2630",
    "addr:postcode":"2630",
    "addr:street":"Monaro Hwy",
    "iso:country":"AU",
    "sg:address":"Cooma Landfill, Monaro Hwy",
    "sg:city":"Cooma",
    "sg:classifiers":[
        {
            "category":"Wholesale",
            "subcategory":"Scrap",
            "type":"Manufacturing & Wholesale Goods"
        }
    ],
    "sg:phone":"+61 1300 767 033",
    "sg:postcode":"2630",
    "sg:province":"NSW",
    "sg:tags":[
        "merchant",
        "metal"
    ],
    "wof:name":"GRI Pty Ltd",
    "wof:placetype":"venue"
},
  "geometry": {"coordinates":[149.13156127900001,-36.2323455811],"type":"Point"}
}