{
  "type": "Feature",
  "properties": {
    "addr:full":"12 - 14 Second Ave Blacktown NSW 2148",
    "addr:housenumber":"14",
    "addr:postcode":"2148",
    "addr:street":"Second Ave",
    "iso:country":"AU",
    "sg:address":"12 - 14 Second Ave",
    "sg:city":"Blacktown",
    "sg:classifiers":[
        {
            "category":"Home & Garden",
            "subcategory":"Hardware",
            "type":"Retail Goods"
        }
    ],
    "sg:phone":"+61 2 9621 5855",
    "sg:postcode":"2148",
    "sg:province":"NSW",
    "sg:tags":[
        "plumber",
        "supply"
    ],
    "wof:name":"Tradelink Plumbing Centres",
    "wof:placetype":"venue"
},
  "geometry": {"coordinates":[150.91152954099999,-33.7670783997],"type":"Point"}
}