{
  "type": "Feature",
  "properties": {
    "iso:country":"AU",
    "sg:address":"Cnr Main Rd",
    "sg:city":"& Macquarie Cardiff",
    "sg:classifiers":[
        {
            "category":"Food & Beverages",
            "subcategory":"Supermarket",
            "type":"Retail Goods"
        }
    ],
    "sg:phone":"+61 2 4954 0655",
    "sg:postcode":"2285",
    "sg:province":"NSW",
    "sg:tags":[
        "grocery",
        "store"
    ],
    "wof:name":"Food For Less",
    "wof:placetype":"venue"
},
  "geometry": {"coordinates":[151.66458129899999,-32.9420318604],"type":"Point"}
}