{
  "type": "Feature",
  "properties": {
    "iso:country":"AU",
    "sg:address":"40 Sisely Ave",
    "sg:city":"Wangaratta",
    "sg:classifiers":[
        {
            "category":"Wholesale",
            "subcategory":"Farm Supplies",
            "type":"Manufacturing & Wholesale Goods"
        }
    ],
    "sg:phone":"+61 3 5721 3533",
    "sg:postcode":"3677",
    "sg:province":"VIC",
    "sg:tags":[
        "equipment"
    ],
    "wof:name":"Complete Engineering Wangaratta Pty Ltd",
    "wof:placetype":"venue"
},
  "geometry": {"coordinates":[146.30357360799999,-36.3595161438],"type":"Point"}
}