{
  "type": "Feature",
  "properties": {
    "addr:full":"7a Cope St Redfern NSW 2016",
    "addr:housenumber":"7a",
    "addr:postcode":"2016",
    "addr:street":"Cope St",
    "iso:country":"AU",
    "sg:address":"7a Cope St",
    "sg:city":"Redfern",
    "sg:classifiers":[
        {
            "category":"Professional",
            "subcategory":"Employment Agencies",
            "type":"Services"
        }
    ],
    "sg:phone":"+61 2 9319 7475",
    "sg:postcode":"2016",
    "sg:province":"NSW",
    "sg:tags":[
        "theatrical",
        "managers",
        "agent",
        "producer"
    ],
    "wof:name":"School Performance Tours",
    "wof:placetype":"venue"
},
  "geometry": {"coordinates":[151.20069885300001,-33.8926467896],"type":"Point"}
}