{
  "type": "Feature",
  "properties": {
    "iso:country":"AU",
    "sg:address":"44 Barry Pde",
    "sg:city":"Fortitude Valley",
    "sg:classifiers":[
        {
            "category":"Autos & Motor Vehicles",
            "subcategory":"Fuel & Gas Station",
            "type":"Retail Goods"
        }
    ],
    "sg:phone":"+61 7 3832 1130",
    "sg:postcode":"4006",
    "sg:province":"QLD",
    "wof:name":"Barry Parade Cab Centre",
    "wof:placetype":"venue"
},
  "geometry": {"coordinates":[153.03106689399999,-27.4607181549],"type":"Point"}
}