{
  "type": "Feature",
  "properties": {
    "iso:country":"AU",
    "sg:address":"163 Pound St",
    "sg:city":"Grafton",
    "sg:classifiers":[
        {
            "category":"Health Services",
            "subcategory":"Doctor",
            "type":"Services"
        }
    ],
    "sg:phone":"+61 2 6643 1744",
    "sg:postcode":"2460",
    "sg:province":"NSW",
    "sg:tags":[
        "medical",
        "practitioner"
    ],
    "wof:name":"Jacaranda Medical Centre",
    "wof:placetype":"venue"
},
  "geometry": {"coordinates":[152.93148803700001,-29.6876182556],"type":"Point"}
}