{
  "type": "Feature",
  "properties": {
    "addr:full":"Suite 2/ 338 Main St Mornington VIC 3931",
    "addr:housenumber":"/ 338",
    "addr:postcode":"3931",
    "addr:street":"Main St",
    "iso:country":"AU",
    "sg:address":"Suite 2/ 338 Main St",
    "sg:city":"Mornington",
    "sg:classifiers":[
        {
            "category":"Professional",
            "subcategory":"Accounting & Tax Preparation",
            "type":"Services"
        }
    ],
    "sg:phone":"+61 3 5977 1211",
    "sg:postcode":"3931",
    "sg:province":"VIC",
    "sg:tags":[
        "consultant",
        "taxation"
    ],
    "wof:name":"David Brown & Associates",
    "wof:placetype":"venue"
},
  "geometry": {"coordinates":[145.043334961,-38.2267837524],"type":"Point"}
}