{
  "type": "Feature",
  "properties": {
    "iso:country":"AU",
    "sg:address":"515 Middleborough Rd",
    "sg:city":"Box Hill North",
    "sg:classifiers":[
        {
            "category":"Casinos & Gambling",
            "type":"Entertainment"
        }
    ],
    "sg:phone":"+61 3 9898 1450",
    "sg:postcode":"3129",
    "sg:province":"VIC",
    "sg:tags":[
        "lottery",
        "agent"
    ],
    "wof:name":"Vickers J S & E B",
    "wof:placetype":"venue"
},
  "geometry": {"coordinates":[145.14021301299999,-37.808971405],"type":"Point"}
}