{
  "type": "Feature",
  "properties": {
    "addr:full":"PO Box 932 Double Bay NSW 1362",
    "addr:postcode":"1362",
    "iso:country":"AU",
    "sg:address":"PO Box 932",
    "sg:city":"Double Bay",
    "sg:classifiers":[
        {
            "category":"Professional",
            "subcategory":"Computer Services",
            "type":"Services"
        }
    ],
    "sg:phone":"+61 402 424 300",
    "sg:postcode":"1362",
    "sg:province":"NSW",
    "sg:tags":[
        "consultant",
        "system"
    ],
    "wof:name":"BRX Solutions",
    "wof:placetype":"venue"
},
  "geometry": {"coordinates":[151.24400329599999,-33.8773117065],"type":"Point"}
}