{
  "type": "Feature",
  "properties": {
    "iso:country":"AU",
    "sg:address":"43 Erina Valley Rd",
    "sg:city":"Erina",
    "sg:classifiers":[
        {
            "category":"Building & Trades",
            "subcategory":"Plumbing",
            "type":"Services"
        }
    ],
    "sg:phone":"+61 2 4365 3000",
    "sg:postcode":"2250",
    "sg:province":"NSW",
    "sg:tags":[
        "plumber",
        "gasfitters"
    ],
    "wof:name":"Erina Plumbing Pty Ltd",
    "wof:placetype":"venue"
},
  "geometry": {"coordinates":[151.408493042,-33.4315948486],"type":"Point"}
}