{
  "type": "Feature",
  "properties": {
    "iso:country":"AU",
    "sg:address":"1 Havelock St",
    "sg:city":"West Perth",
    "sg:classifiers":[
        {
            "category":"Professional",
            "subcategory":"Accounting & Tax Preparation",
            "type":"Services"
        }
    ],
    "sg:phone":"+61 8 9481 3188",
    "sg:postcode":"6005",
    "sg:province":"WA",
    "sg:tags":[
        "accountant",
        "auditor"
    ],
    "wof:name":"Institute Of Internal Auditors-Australia (W.A. Branch)",
    "wof:placetype":"venue"
},
  "geometry": {"coordinates":[115.84249115,-31.9531402588],"type":"Point"}
}