{
  "type": "Feature",
  "properties": {
    "addr:full":"155 Dora St Hurstville NSW 2220",
    "addr:housenumber":"155",
    "addr:postcode":"2220",
    "addr:street":"Dora St",
    "iso:country":"AU",
    "sg:address":"155 Dora St",
    "sg:city":"Hurstville",
    "sg:classifiers":[
        {
            "category":"Organizations",
            "subcategory":"Non-profit Organization",
            "type":"Services"
        }
    ],
    "sg:phone":"+61 2 9580 7634",
    "sg:postcode":"2220",
    "sg:province":"NSW",
    "sg:tags":[
        "support",
        "disability",
        "organisation"
    ],
    "wof:name":"SDN Childrens Services",
    "wof:placetype":"venue"
},
  "geometry": {"coordinates":[151.09603881800001,-33.9589958191],"type":"Point"}
}