{
  "type": "Feature",
  "properties": {
    "addr:full":"538 Grange Rd Grange SA 5022",
    "addr:housenumber":"538",
    "addr:postcode":"5022",
    "addr:street":"Grange Rd",
    "iso:country":"AU",
    "sg:address":"538 Grange Rd",
    "sg:city":"Grange",
    "sg:classifiers":[
        {
            "category":"Food & Beverages",
            "subcategory":"Supermarket",
            "type":"Retail Goods"
        }
    ],
    "sg:phone":"+61 8 8219 8000",
    "sg:postcode":"5022",
    "sg:province":"SA",
    "sg:tags":[
        "grocery",
        "store"
    ],
    "wof:name":"Foodland Supermarkets",
    "wof:placetype":"venue"
},
  "geometry": {"coordinates":[138.504272461,-34.906993866],"type":"Point"}
}