{
  "type": "Feature",
  "properties": {
    "addr:full":"29 Stanlake Ave St Marys SA 5042",
    "addr:housenumber":"29",
    "addr:postcode":"5042",
    "addr:street":"Stanlake Ave",
    "iso:country":"AU",
    "sg:address":"29 Stanlake Ave",
    "sg:city":"St Marys",
    "sg:classifiers":[
        {
            "category":"Home & Garden",
            "subcategory":"Carpets & Floor Coverings",
            "type":"Retail Goods"
        }
    ],
    "sg:phone":"+61 8 8277 6870",
    "sg:postcode":"5042",
    "sg:province":"SA",
    "sg:tags":[
        "tile",
        "wall",
        "layer"
    ],
    "wof:name":"Crolla Rob Tiling Craftsman",
    "wof:placetype":"venue"
},
  "geometry": {"coordinates":[138.58279400000001,-35.008785],"type":"Point"}
}