{
  "type": "Feature",
  "properties": {
    "addr:full":"8 Railway Ave Ringwood East VIC 3135",
    "addr:housenumber":"8",
    "addr:postcode":"3135",
    "addr:street":"Railway Ave",
    "iso:country":"AU",
    "sg:address":"8 Railway Ave",
    "sg:city":"Ringwood East",
    "sg:classifiers":[
        {
            "category":"Shopping",
            "subcategory":"Clothing, Apparel, & Fashions",
            "type":"Retail Goods"
        }
    ],
    "sg:phone":"+61 3 9870 3837",
    "sg:postcode":"3135",
    "sg:province":"VIC",
    "sg:tags":[
        "hire",
        "men's",
        "wear",
        "formal"
    ],
    "wof:name":"Sew Quick",
    "wof:placetype":"venue"
},
  "geometry": {"coordinates":[145.25192260700001,-37.8117408752],"type":"Point"}
}