{
  "type": "Feature",
  "properties": {
    "iso:country":"AU",
    "sg:address":"Blue Orchid Crt",
    "sg:city":"Yallingup",
    "sg:classifiers":[
        {
            "category":"Arts & Performance",
            "subcategory":"Art Gallery",
            "type":"Entertainment"
        }
    ],
    "sg:phone":"+61 8 9755 2582",
    "sg:postcode":"6282",
    "sg:province":"WA",
    "wof:name":"Purist Gallery",
    "wof:placetype":"venue"
},
  "geometry": {"coordinates":[115.054481506,-33.6496887207],"type":"Point"}
}