{
  "type": "Feature",
  "properties": {
    "addr:full":"31 Edgehill Ave Botany NSW 2019",
    "addr:housenumber":"31",
    "addr:postcode":"2019",
    "addr:street":"Edgehill Ave",
    "iso:country":"AU",
    "sg:address":"31 Edgehill Ave",
    "sg:city":"Botany",
    "sg:classifiers":[
        {
            "category":"Health Services",
            "subcategory":"Nursing And Care Facility",
            "type":"Services"
        }
    ],
    "sg:phone":"+61 2 9316 9544",
    "sg:postcode":"2019",
    "sg:province":"NSW",
    "sg:tags":[
        "home"
    ],
    "wof:name":"Sir Joseph Banks Aged Care",
    "wof:placetype":"venue"
},
  "geometry": {"coordinates":[151.19903564399999,-33.9530830383],"type":"Point"}
}