{
  "type": "Feature",
  "properties": {
    "addr:full":"36 Lawson Rd Happy Valley SA 5159",
    "addr:housenumber":"36",
    "addr:postcode":"5159",
    "addr:street":"Lawson Rd",
    "iso:country":"AU",
    "sg:address":"36 Lawson Rd",
    "sg:city":"Happy Valley",
    "sg:classifiers":[
        {
            "category":"Building & Trades",
            "subcategory":"Cleaning & Sanitation",
            "type":"Services"
        }
    ],
    "sg:phone":"+61 418 831 415",
    "sg:postcode":"5159",
    "sg:province":"SA",
    "sg:tags":[
        "industrial",
        "commercial",
        "contractor"
    ],
    "wof:name":"A Abbott Cleaning Services",
    "wof:placetype":"venue"
},
  "geometry": {"coordinates":[138.57115173299999,-35.0868988037],"type":"Point"}
}