{
  "type": "Feature",
  "properties": {
    "addr:full":"134 Elizabeth St Melbourne VIC 3000",
    "addr:housenumber":"134",
    "addr:postcode":"3000",
    "addr:street":"Elizabeth St",
    "iso:country":"AU",
    "sg:address":"134 Elizabeth St",
    "sg:city":"Melbourne",
    "sg:classifiers":[
        {
            "category":"Shopping",
            "subcategory":"Mobile Phones",
            "type":"Retail Goods"
        }
    ],
    "sg:phone":"+61 3 9650 5222",
    "sg:postcode":"3000",
    "sg:province":"VIC",
    "sg:tags":[
        "telephone",
        "accessory"
    ],
    "wof:name":"Fone Zone",
    "wof:placetype":"venue"
},
  "geometry": {"coordinates":[144.96363830600001,-37.8149261475],"type":"Point"}
}