{
  "type": "Feature",
  "properties": {
    "addr:full":"56- 58 Elizabeth St Wetherill Park NSW 2164",
    "addr:housenumber":"58",
    "addr:postcode":"2164",
    "addr:street":"Elizabeth St",
    "iso:country":"AU",
    "sg:address":"56- 58 Elizabeth St",
    "sg:city":"Wetherill Park",
    "sg:classifiers":[
        {
            "category":"Home & Garden",
            "subcategory":"Home Furnishings",
            "type":"Retail Goods"
        }
    ],
    "sg:phone":"+61 2 9612 1000",
    "sg:postcode":"2164",
    "sg:province":"NSW",
    "sg:tags":[
        "shower",
        "screen"
    ],
    "wof:name":"Sydney Shower Screens & Wardrobes",
    "wof:placetype":"venue"
},
  "geometry": {"coordinates":[150.90000915499999,-33.8468742371],"type":"Point"}
}