{
  "type": "Feature",
  "properties": {
    "iso:country":"AU",
    "sg:address":"51 Thuringowa Drv",
    "sg:city":"Kirwan",
    "sg:classifiers":[
        {
            "category":"Professional",
            "subcategory":"Accounting & Tax Preparation",
            "type":"Services"
        }
    ],
    "sg:phone":"+61 7 4755 1111",
    "sg:postcode":"4817",
    "sg:province":"QLD",
    "sg:tags":[
        "consultant",
        "taxation"
    ],
    "wof:name":"Happy Tax",
    "wof:placetype":"venue"
},
  "geometry": {"coordinates":[146.733734,-19.306578],"type":"Point"}
}