{
  "type": "Feature",
  "properties": {
    "iso:country":"AU",
    "sg:address":"29 Daintree Crs",
    "sg:city":"Kaleen",
    "sg:classifiers":[
        {
            "category":"Personal",
            "subcategory":"Massage",
            "type":"Services"
        }
    ],
    "sg:phone":"+61 400 906 388",
    "sg:postcode":"2617",
    "sg:province":"ACT",
    "sg:tags":[
        "therapy"
    ],
    "wof:name":"WISEA",
    "wof:placetype":"venue"
},
  "geometry": {"coordinates":[149.10270690900001,-35.2194709778],"type":"Point"}
}