{
  "type": "Feature",
  "properties": {
    "iso:country":"AU",
    "sg:address":"Unit 2 74 Townsville St",
    "sg:city":"Fyshwick",
    "sg:classifiers":[
        {
            "category":"Professional",
            "subcategory":"Engineering",
            "type":"Services"
        }
    ],
    "sg:phone":"+61 2 6280 6250",
    "sg:postcode":"2609",
    "sg:province":"ACT",
    "sg:tags":[
        "engineer"
    ],
    "wof:name":"Amtech Precision Engineering Pty Ltd",
    "wof:placetype":"venue"
},
  "geometry": {"coordinates":[149.18359375,-35.3310203552],"type":"Point"}
}