{
  "type": "Feature",
  "properties": {
    "addr:full":"331 Hampton St Hampton VIC 3188",
    "addr:housenumber":"331",
    "addr:postcode":"3188",
    "addr:street":"Hampton St",
    "iso:country":"AU",
    "sg:address":"331 Hampton St",
    "sg:city":"Hampton",
    "sg:classifiers":[
        {
            "category":"Food & Beverages",
            "subcategory":"Fruits & Vegetables",
            "type":"Retail Goods"
        }
    ],
    "sg:phone":"+61 3 9597 0785",
    "sg:postcode":"3188",
    "sg:province":"VIC",
    "sg:tags":[
        "greengrocer",
        "fruiterer"
    ],
    "wof:name":"Hampton Fruit Centre",
    "wof:placetype":"venue"
},
  "geometry": {"coordinates":[145.00227355999999,-37.9377822876],"type":"Point"}
}