{
  "type": "Feature",
  "properties": {
    "addr:full":"31 Bundemar St Warren NSW 2824",
    "addr:housenumber":"31",
    "addr:postcode":"2824",
    "addr:street":"Bundemar St",
    "iso:country":"AU",
    "sg:address":"31 Bundemar St",
    "sg:city":"Warren",
    "sg:classifiers":[
        {
            "category":"Building & Trades",
            "subcategory":"Construction",
            "type":"Services"
        }
    ],
    "sg:phone":"+61 2 6847 4489",
    "sg:postcode":"2824",
    "sg:province":"NSW",
    "sg:tags":[
        "renovation",
        "alterations",
        "extension",
        "contractor"
    ],
    "wof:name":"Leach G W",
    "wof:placetype":"venue"
},
  "geometry": {"coordinates":[147.832595825,-31.7012252808],"type":"Point"}
}