{
  "type": "Feature",
  "properties": {
    "addr:full":"3 Poate Rd Centennial Park NSW 2021",
    "addr:housenumber":"3",
    "addr:postcode":"2021",
    "addr:street":"Poate Rd",
    "iso:country":"AU",
    "sg:address":"3 Poate Rd",
    "sg:city":"Centennial Park",
    "sg:classifiers":[
        {
            "category":"Professional",
            "subcategory":"Employment Agencies",
            "type":"Services"
        }
    ],
    "sg:phone":"+61 2 9362 9299",
    "sg:postcode":"2021",
    "sg:province":"NSW",
    "sg:tags":[
        "entertainer",
        "agent"
    ],
    "wof:name":"Wilkinson Barnett Agency The",
    "wof:placetype":"venue"
},
  "geometry": {"coordinates":[151.22877502399999,-33.8898925781],"type":"Point"}
}