{
  "type": "Feature",
  "properties": {
    "addr:full":"540 Kessels Rd MacGregor QLD 4109",
    "addr:housenumber":"540",
    "addr:postcode":"4109",
    "addr:street":"Kessels Rd",
    "iso:country":"AU",
    "sg:address":"540 Kessels Rd",
    "sg:city":"MacGregor",
    "sg:classifiers":[
        {
            "category":"Home & Garden",
            "subcategory":"Furniture",
            "type":"Retail Goods"
        }
    ],
    "sg:phone":"+61 7 3343 1311",
    "sg:postcode":"4109",
    "sg:province":"QLD",
    "sg:tags":[
        "outdoor"
    ],
    "wof:name":"Super AMart Outdoor Furniture",
    "wof:placetype":"venue"
},
  "geometry": {"coordinates":[153.07032775900001,-27.5613918304],"type":"Point"}
}