{
  "type": "Feature",
  "properties": {
    "iso:country":"AU",
    "sg:address":"119 Scotchmer St",
    "sg:city":"Fitzroy North",
    "sg:classifiers":[
        {
            "category":"Retail",
            "subcategory":"Auto Repair",
            "type":"Services"
        }
    ],
    "sg:phone":"+61 3 9482 6409",
    "sg:postcode":"3068",
    "sg:province":"VIC",
    "sg:tags":[
        "repairer",
        "motor",
        "engineer"
    ],
    "wof:name":"Scotchmer Automotive",
    "wof:placetype":"venue"
},
  "geometry": {"coordinates":[144.982955933,-37.7830619812],"type":"Point"}
}