{
  "type": "Feature",
  "properties": {
    "addr:full":"Unit 13/ 66 Kembla St Wollongong NSW 2500",
    "addr:housenumber":"/ 66",
    "addr:postcode":"2500",
    "addr:street":"Kembla St",
    "iso:country":"AU",
    "sg:address":"Unit 13/ 66 Kembla St",
    "sg:city":"Wollongong",
    "sg:classifiers":[
        {
            "category":"Professional",
            "subcategory":"Accounting & Tax Preparation",
            "type":"Services"
        }
    ],
    "sg:phone":"+61 2 4226 6987",
    "sg:postcode":"2500",
    "sg:province":"NSW",
    "sg:tags":[
        "accountant",
        "auditor"
    ],
    "wof:name":"AAA Accounting Pty Ltd",
    "wof:placetype":"venue"
},
  "geometry": {"coordinates":[150.880112,-34.439251],"type":"Point"}
}