{
  "type": "Feature",
  "properties": {
    "iso:country":"AU",
    "sg:address":"Adam St",
    "sg:city":"Coraki",
    "sg:classifiers":[
        {
            "category":"Education",
            "subcategory":"School",
            "type":"Public Place"
        }
    ],
    "sg:phone":"+61 2 6683 2073",
    "sg:postcode":"2471",
    "sg:province":"NSW",
    "sg:tags":[
        "state",
        "-",
        "nsw"
    ],
    "wof:name":"Coraki Public School",
    "wof:placetype":"venue"
},
  "geometry": {"coordinates":[153.28842163100001,-28.9904098511],"type":"Point"}
}