{
  "type": "Feature",
  "properties": {
    "addr:full":"50 Bond St Mordialloc VIC 3195",
    "addr:housenumber":"50",
    "addr:postcode":"3195",
    "addr:street":"Bond St",
    "iso:country":"AU",
    "sg:address":"50 Bond St",
    "sg:city":"Mordialloc",
    "sg:classifiers":[
        {
            "category":"Shopping",
            "subcategory":"Stationery & Office Supplies",
            "type":"Retail Goods"
        }
    ],
    "sg:phone":"+61 3 9588 2229",
    "sg:postcode":"3195",
    "sg:province":"VIC",
    "sg:tags":[
        "packaging",
        "material"
    ],
    "wof:name":"J M P Holdings",
    "wof:placetype":"venue"
},
  "geometry": {"coordinates":[145.10067749000001,-37.9919891357],"type":"Point"}
}