{
  "type": "Feature",
  "properties": {
    "iso:country":"AU",
    "sg:address":"36 Bannick Crt",
    "sg:city":"Canning Vale",
    "sg:classifiers":[
        {
            "category":"Government",
            "subcategory":"Fire Station",
            "type":"Public Place"
        }
    ],
    "sg:phone":"+61 8 9229 9900",
    "sg:postcode":"6155",
    "sg:province":"WA",
    "sg:tags":[
        "equipment",
        "protection",
        "consultant"
    ],
    "wof:name":"Quell Fire & Safety",
    "wof:placetype":"venue"
},
  "geometry": {"coordinates":[115.92186,-32.062687],"type":"Point"}
}