{
  "type": "Feature",
  "properties": {
    "addr:full":"56 Rosebank Ave Clayton South VIC 3169",
    "addr:housenumber":"56",
    "addr:postcode":"3169",
    "addr:street":"Rosebank Ave",
    "iso:country":"AU",
    "sg:address":"56 Rosebank Ave",
    "sg:city":"Clayton South",
    "sg:classifiers":[
        {
            "category":"Government",
            "subcategory":"Post Office",
            "type":"Public Place"
        }
    ],
    "sg:phone":"+61 3 9253 3770",
    "sg:postcode":"3169",
    "sg:province":"VIC",
    "sg:tags":[
        "postal"
    ],
    "wof:name":"Australia Post",
    "wof:placetype":"venue"
},
  "geometry": {"coordinates":[145.132415772,-37.9396247864],"type":"Point"}
}