{
  "type": "Feature",
  "properties": {
    "iso:country":"AU",
    "sg:address":"Suite 4 Kingsley Professional Centre, 56 Creaney Drv",
    "sg:city":"Kingsley",
    "sg:classifiers":[
        {
            "category":"Building & Trades",
            "subcategory":"Construction",
            "type":"Services"
        }
    ],
    "sg:phone":"+61 8 9409 9855",
    "sg:postcode":"6026",
    "sg:province":"WA",
    "sg:tags":[
        "contractor"
    ],
    "wof:name":"Studio 8 Builders & Designers",
    "wof:placetype":"venue"
},
  "geometry": {"coordinates":[115.790412903,-31.8077640533],"type":"Point"}
}