{
  "type": "Feature",
  "properties": {
    "addr:full":"Shop 4/ 83 Mount St North Sydney NSW 2060",
    "addr:housenumber":"shop 4 / 83",
    "addr:postcode":"2060",
    "addr:street":"Mount St",
    "iso:country":"AU",
    "sg:address":"Shop 4/ 83 Mount St",
    "sg:city":"North Sydney",
    "sg:classifiers":[
        {
            "category":"Health Services",
            "subcategory":"Health Practitioner",
            "type":"Services"
        }
    ],
    "sg:phone":"+61 2 9955 5400",
    "sg:postcode":"2060",
    "sg:province":"NSW",
    "sg:tags":[
        "acupuncture"
    ],
    "wof:name":"Rodrigues Dianah",
    "wof:placetype":"venue"
},
  "geometry": {"coordinates":[151.20791625999999,-33.8390922546],"type":"Point"}
}