{
  "type": "Feature",
  "properties": {
    "iso:country":"AU",
    "sg:address":"71 Beethoven St",
    "sg:city":"Seven Hills",
    "sg:classifiers":[
        {
            "category":"Personal",
            "subcategory":"Beauty Salon",
            "type":"Services"
        }
    ],
    "sg:phone":"+61 408 422 541",
    "sg:postcode":"2147",
    "sg:province":"NSW",
    "sg:tags":[
        "supply",
        "artist",
        "make-up"
    ],
    "wof:name":"Allie Clark Make Up",
    "wof:placetype":"venue"
},
  "geometry": {"coordinates":[150.95651245100001,-33.7617149353],"type":"Point"}
}