{
  "type": "Feature",
  "properties": {
    "addr:full":"Shp1/ 27 Harris St Fairfield NSW 2165",
    "addr:housenumber":"27",
    "addr:postcode":"2165",
    "addr:street":"Harris St",
    "iso:country":"AU",
    "sg:address":"Shp1/ 27 Harris St",
    "sg:city":"Fairfield",
    "sg:classifiers":[
        {
            "category":"Shopping",
            "subcategory":"Mobile Phones",
            "type":"Retail Goods"
        }
    ],
    "sg:phone":"+61 2 9727 6261",
    "sg:postcode":"2165",
    "sg:province":"NSW",
    "sg:tags":[
        "telephone",
        "accessory"
    ],
    "wof:name":"Oj Communications",
    "wof:placetype":"venue"
},
  "geometry": {"coordinates":[150.948287964,-33.871761322],"type":"Point"}
}