{
  "type": "Feature",
  "properties": {
    "addr:full":"PO Box 117 Thursday Island QLD 4875",
    "addr:postcode":"4875",
    "iso:country":"AU",
    "sg:address":"PO Box 117",
    "sg:city":"Thursday Island",
    "sg:classifiers":[
        {
            "category":"Education",
            "subcategory":"University",
            "type":"Public Place"
        }
    ],
    "sg:phone":"+61 7 4069 2718",
    "sg:postcode":"4875",
    "sg:province":"QLD",
    "sg:tags":[
        "college",
        "tertiary"
    ],
    "wof:name":"Remote Area Teacher Education Program",
    "wof:placetype":"venue"
},
  "geometry": {"coordinates":[142.22085571299999,-10.5806503296],"type":"Point"}
}