{
  "type": "Feature",
  "properties": {
    "addr:full":"24 Fairview Drv Kingston TAS 7050",
    "addr:housenumber":"24",
    "addr:postcode":"7050",
    "addr:street":"Fairview Drv",
    "iso:country":"AU",
    "sg:address":"24 Fairview Drv",
    "sg:city":"Kingston",
    "sg:classifiers":[
        {
            "category":"Professional",
            "subcategory":"Art Services",
            "type":"Services"
        }
    ],
    "sg:phone":"+61 427 040 571",
    "sg:postcode":"7050",
    "sg:province":"TAS",
    "sg:tags":[
        "decorator",
        "painter"
    ],
    "wof:name":"Peter Hong",
    "wof:placetype":"venue"
},
  "geometry": {"coordinates":[147.31016500000001,-42.983425],"type":"Point"}
}