{
  "type": "Feature",
  "properties": {
    "addr:full":"169 Lygon St Brunswick East VIC 3057",
    "addr:housenumber":"169",
    "addr:postcode":"3057",
    "addr:street":"Lygon St",
    "iso:country":"AU",
    "sg:address":"169 Lygon St",
    "sg:city":"Brunswick East",
    "sg:classifiers":[
        {
            "category":"Cafe",
            "type":"Food & Drink"
        }
    ],
    "sg:phone":"+61 3 9387 2396",
    "sg:postcode":"3057",
    "sg:province":"VIC",
    "wof:name":"Poached",
    "wof:placetype":"venue"
},
  "geometry": {"coordinates":[144.97128295900001,-37.7729530334],"type":"Point"}
}