{
  "type": "Feature",
  "properties": {
    "iso:country":"AU",
    "sg:address":"173 Garretts Rd",
    "sg:city":"Sarina",
    "sg:classifiers":[
        {
            "category":"Home & Garden",
            "subcategory":"Building Materials",
            "type":"Retail Goods"
        }
    ],
    "sg:phone":"+61 7 4943 0904",
    "sg:postcode":"4737",
    "sg:province":"QLD",
    "sg:tags":[
        "lawn",
        "cutting",
        "maintenance"
    ],
    "wof:name":"4DEEZE MOWING SERVICES",
    "wof:placetype":"venue"
},
  "geometry": {"coordinates":[149.22828699999999,-21.368021],"type":"Point"}
}