{
  "type": "Feature",
  "properties": {
    "addr:full":"1051 Raglan Pde Warrnambool VIC 3280",
    "addr:housenumber":"1051",
    "addr:postcode":"3280",
    "addr:street":"Raglan Pde",
    "iso:country":"AU",
    "sg:address":"1051 Raglan Pde",
    "sg:city":"Warrnambool",
    "sg:classifiers":[
        {
            "category":"Professional",
            "subcategory":"Accounting & Tax Preparation",
            "type":"Services"
        }
    ],
    "sg:phone":"+61 3 5561 8618",
    "sg:postcode":"3280",
    "sg:province":"VIC",
    "sg:tags":[
        "accountant",
        "auditor"
    ],
    "wof:name":"Hughson Gary",
    "wof:placetype":"venue"
},
  "geometry": {"coordinates":[142.46653747600001,-38.3687744141],"type":"Point"}
}