{
  "type": "Feature",
  "properties": {
    "addr:full":"101a Mount Barker Rd Stirling SA 5152",
    "addr:housenumber":"101a",
    "addr:postcode":"5152",
    "addr:street":"Mount Barker Rd",
    "iso:country":"AU",
    "sg:address":"101a Mount Barker Rd",
    "sg:city":"Stirling",
    "sg:classifiers":[
        {
            "category":"Health Services",
            "subcategory":"Health Practitioner",
            "type":"Services"
        }
    ],
    "sg:phone":"+61 8 8339 4322",
    "sg:postcode":"5152",
    "sg:province":"SA",
    "sg:tags":[
        "physiotherapist"
    ],
    "wof:name":"Elford Mark",
    "wof:placetype":"venue"
},
  "geometry": {"coordinates":[138.72233581500001,-35.0080833435],"type":"Point"}
}