{
  "type": "Feature",
  "properties": {
    "addr:full":"456 Guildford Rd Bayswater WA 6053",
    "addr:housenumber":"456",
    "addr:postcode":"6053",
    "addr:street":"Guildford Rd",
    "iso:country":"AU",
    "sg:address":"456 Guildford Rd",
    "sg:city":"Bayswater",
    "sg:classifiers":[
        {
            "category":"Social Services",
            "subcategory":"Child Care",
            "type":"Services"
        }
    ],
    "sg:phone":"+61 8 9471 7822",
    "sg:postcode":"6053",
    "sg:province":"WA",
    "wof:name":"Jacaranda Childcare and Pre School",
    "wof:placetype":"venue"
},
  "geometry": {"coordinates":[115.91848754900001,-31.9243030548],"type":"Point"}
}