{
  "type": "Feature",
  "properties": {
    "addr:full":"36 Reschke Crt Laverton VIC 3028",
    "addr:housenumber":"36",
    "addr:postcode":"3028",
    "addr:street":"Reschke Crt",
    "iso:country":"AU",
    "sg:address":"36 Reschke Crt",
    "sg:city":"Laverton",
    "sg:classifiers":[
        {
            "category":"Utilities",
            "subcategory":"Electric",
            "type":"Services"
        }
    ],
    "sg:phone":"+61 412 343 330",
    "sg:postcode":"3028",
    "sg:province":"VIC",
    "sg:tags":[
        "advisory",
        "lighting",
        "power"
    ],
    "wof:name":"Electrical Auditing & Testing Pty Ltd",
    "wof:placetype":"venue"
},
  "geometry": {"coordinates":[144.77427700000001,-37.865009],"type":"Point"}
}