{
  "type": "Feature",
  "properties": {
    "addr:full":"145 Lang St Kurri Kurri NSW 2327",
    "addr:housenumber":"145",
    "addr:postcode":"2327",
    "addr:street":"Lang St",
    "iso:country":"AU",
    "sg:address":"145 Lang St",
    "sg:city":"Kurri Kurri",
    "sg:classifiers":[
        {
            "category":"Real Estate",
            "subcategory":"Real Estate Agent",
            "type":"Services"
        }
    ],
    "sg:phone":"+61 2 4936 1722",
    "sg:postcode":"2327",
    "sg:province":"NSW",
    "wof:name":"Cameron Kathryn Real Estate",
    "wof:placetype":"venue"
},
  "geometry": {"coordinates":[151.479736328,-32.819278717],"type":"Point"}
}