{
  "type": "Feature",
  "properties": {
    "addr:full":"8 Chris Bang Crs Vaucluse NSW 2030",
    "addr:housenumber":"8",
    "addr:postcode":"2030",
    "addr:street":"Chris Bang Crs",
    "iso:country":"AU",
    "sg:address":"8 Chris Bang Crs",
    "sg:city":"Vaucluse",
    "sg:classifiers":[
        {
            "category":"Professional",
            "subcategory":"Accounting & Tax Preparation",
            "type":"Services"
        }
    ],
    "sg:phone":"+61 2 9337 6184",
    "sg:postcode":"2030",
    "sg:province":"NSW",
    "sg:tags":[
        "accountant",
        "auditor"
    ],
    "wof:name":"Abeshouse David",
    "wof:placetype":"venue"
},
  "geometry": {"coordinates":[151.28192138700001,-33.8597106934],"type":"Point"}
}