{
  "type": "Feature",
  "properties": {
    "addr:full":"Shop 106 a Myer Centre Brisbane QLD 4000",
    "addr:housenumber":"106 a;centre",
    "addr:postcode":"4000",
    "iso:country":"AU",
    "sg:address":"Shop 106",
    "sg:city":"a Myer Centre Brisbane",
    "sg:classifiers":[
        {
            "category":"Health Services",
            "subcategory":"Optometrist",
            "type":"Services"
        }
    ],
    "sg:phone":"+61 7 3003 1112",
    "sg:postcode":"4000",
    "sg:province":"QLD",
    "wof:name":"Merringtons",
    "wof:placetype":"venue"
},
  "geometry": {"coordinates":[153.02276611299999,-27.4651203156],"type":"Point"}
}