{
  "type": "Feature",
  "properties": {
    "addr:full":"Sturt Hwy via Wagga Wagga NSW 2650",
    "addr:postcode":"2650",
    "addr:street":"Sturt Hwy Via Wagga Wagga",
    "iso:country":"AU",
    "sg:address":"Sturt Hwy",
    "sg:city":"via Wagga Wagga",
    "sg:classifiers":[
        {
            "category":"Education",
            "subcategory":"School",
            "type":"Public Place"
        }
    ],
    "sg:phone":"+61 2 6922 7285",
    "sg:postcode":"2650",
    "sg:province":"NSW",
    "sg:tags":[
        "state",
        "-",
        "nsw"
    ],
    "wof:name":"Gumly Gumly Public School",
    "wof:placetype":"venue"
},
  "geometry": {"coordinates":[147.370437622,-35.1057472229],"type":"Point"}
}