{
  "type": "Feature",
  "properties": {
    "addr:full":"72 Poath Rd Hughesdale VIC 3166",
    "addr:housenumber":"72",
    "addr:postcode":"3166",
    "addr:street":"Poath Rd",
    "iso:country":"AU",
    "sg:address":"72 Poath Rd",
    "sg:city":"Hughesdale",
    "sg:classifiers":[
        {
            "category":"Personal",
            "subcategory":"Beauty Salon",
            "type":"Services"
        }
    ],
    "sg:phone":"+61 3 9569 1360",
    "sg:postcode":"3166",
    "sg:province":"VIC",
    "wof:name":"Bask Beauty",
    "wof:placetype":"venue"
},
  "geometry": {"coordinates":[145.07708740199999,-37.8936004639],"type":"Point"}
}