{
  "type": "Feature",
  "properties": {
    "iso:country":"AU",
    "sg:address":"254 Canning Hwy",
    "sg:city":"East Fremantle",
    "sg:classifiers":[
        {
            "category":"Health Services",
            "subcategory":"Dentist",
            "type":"Services"
        }
    ],
    "sg:phone":"+61 8 9339 2948",
    "sg:postcode":"6158",
    "sg:province":"WA",
    "wof:name":"East Fremantle Dental Centre",
    "wof:placetype":"venue"
},
  "geometry": {"coordinates":[115.763397,-32.0411],"type":"Point"}
}