{
  "type": "Feature",
  "properties": {
    "iso:country":"AU",
    "sg:address":"GPO Box 1558",
    "sg:city":"Brisbane",
    "sg:classifiers":[
        {
            "category":"Professional",
            "subcategory":"Computer Services",
            "type":"Services"
        }
    ],
    "sg:phone":"+61 411 078 382",
    "sg:postcode":"4001",
    "sg:province":"QLD",
    "sg:tags":[
        "consultant",
        "system"
    ],
    "wof:name":"Interactive Resource Communications",
    "wof:placetype":"venue"
},
  "geometry": {"coordinates":[152.88911438,-27.5977325439],"type":"Point"}
}