{
  "type": "Feature",
  "properties": {
    "iso:country":"AU",
    "sg:address":"12 Kingfisher Rd",
    "sg:city":"Mt Cotton",
    "sg:classifiers":[
        {
            "category":"Home & Garden",
            "subcategory":"Building Materials",
            "type":"Retail Goods"
        }
    ],
    "sg:phone":"+61 7 3829 9388",
    "sg:postcode":"4165",
    "sg:province":"QLD",
    "sg:tags":[
        "wall",
        "frame",
        "truss",
        "roof"
    ],
    "wof:name":"Whisper Frames & Trusses",
    "wof:placetype":"venue"
},
  "geometry": {"coordinates":[153.25938415499999,-27.5989570618],"type":"Point"}
}