{
  "type": "Feature",
  "properties": {
    "addr:full":"81 Erroll St North Melbourne VIC 3051",
    "addr:housenumber":"81",
    "addr:postcode":"3051",
    "addr:street":"Erroll St",
    "iso:country":"AU",
    "sg:address":"81 Erroll St",
    "sg:city":"North Melbourne",
    "sg:classifiers":[
        {
            "category":"Manufacturing",
            "subcategory":"Food",
            "type":"Manufacturing & Wholesale Goods"
        }
    ],
    "sg:phone":"+61 3 9328 3994",
    "sg:postcode":"3051",
    "sg:province":"VIC",
    "sg:tags":[
        "function",
        "catering"
    ],
    "wof:name":"Snax Deli",
    "wof:placetype":"venue"
},
  "geometry": {"coordinates":[144.949462891,-37.8031692505],"type":"Point"}
}