{
  "type": "Feature",
  "properties": {
    "addr:full":"6 Hamilton Pl Mt Waverley VIC 3149",
    "addr:housenumber":"6",
    "addr:postcode":"3149",
    "addr:street":"Hamilton Pl Mt",
    "iso:country":"AU",
    "sg:address":"6 Hamilton Pl",
    "sg:city":"Mt Waverley",
    "sg:classifiers":[
        {
            "category":"Building & Trades",
            "subcategory":"Construction",
            "type":"Services"
        }
    ],
    "sg:phone":"+61 418 320 377",
    "sg:postcode":"3149",
    "sg:province":"VIC",
    "sg:tags":[
        "contractor"
    ],
    "wof:name":"Stewart Stirling Pty Ltd",
    "wof:placetype":"venue"
},
  "geometry": {"coordinates":[145.12792968799999,-37.875705719],"type":"Point"}
}