{
  "type": "Feature",
  "properties": {
    "addr:full":"3 Rothbury St Maryland NSW 2287",
    "addr:housenumber":"3",
    "addr:postcode":"2287",
    "addr:street":"Rothbury St",
    "iso:country":"AU",
    "sg:address":"3 Rothbury St",
    "sg:city":"Maryland",
    "sg:classifiers":[
        {
            "category":"Professional",
            "subcategory":"Art Services",
            "type":"Services"
        }
    ],
    "sg:phone":"+61 414 370 119",
    "sg:postcode":"2287",
    "sg:province":"NSW",
    "sg:tags":[
        "decorator",
        "painter"
    ],
    "wof:name":"Anthony Dippolito",
    "wof:placetype":"venue"
},
  "geometry": {"coordinates":[151.662277222,-32.8831329346],"type":"Point"}
}