{
  "type": "Feature",
  "properties": {
    "iso:country":"AU",
    "sg:address":"1b Armstrong St",
    "sg:city":"Parkes",
    "sg:classifiers":[
        {
            "category":"Building & Trades",
            "subcategory":"Construction",
            "type":"Services"
        }
    ],
    "sg:phone":"+61 2 6862 2203",
    "sg:postcode":"2870",
    "sg:province":"NSW",
    "sg:tags":[
        "joinery"
    ],
    "wof:name":"B.D.N. Kitchens & Joinery",
    "wof:placetype":"venue"
},
  "geometry": {"coordinates":[148.170776,-33.1371],"type":"Point"}
}