{
  "type": "Feature",
  "properties": {
    "addr:full":"39 Looker Rd Montmorency VIC 3094",
    "addr:housenumber":"39",
    "addr:postcode":"3094",
    "addr:street":"Looker Rd",
    "iso:country":"AU",
    "sg:address":"39 Looker Rd",
    "sg:city":"Montmorency",
    "sg:classifiers":[
        {
            "category":"Building & Trades",
            "subcategory":"Construction",
            "type":"Services"
        }
    ],
    "sg:phone":"+61 418 330 355",
    "sg:postcode":"3094",
    "sg:province":"VIC",
    "sg:tags":[
        "repair",
        "maintenance",
        "contractor"
    ],
    "wof:name":"Barrenong Building Services",
    "wof:placetype":"venue"
},
  "geometry": {"coordinates":[145.12391662600001,-37.7209358215],"type":"Point"}
}