{
  "type": "Feature",
  "properties": {
    "addr:full":"201 Chapel St Prahran VIC 3181",
    "addr:housenumber":"201",
    "addr:postcode":"3181",
    "addr:street":"Chapel St",
    "iso:country":"AU",
    "sg:address":"201 Chapel St",
    "sg:city":"Prahran",
    "sg:classifiers":[
        {
            "category":"Shopping",
            "subcategory":"Shoes",
            "type":"Retail Goods"
        }
    ],
    "sg:phone":"+61 3 9510 1099",
    "sg:postcode":"3181",
    "sg:province":"VIC",
    "sg:tags":[
        "footwear"
    ],
    "wof:name":"Ghetto Sport & Street",
    "wof:placetype":"venue"
},
  "geometry": {"coordinates":[144.993286133,-37.8512611389],"type":"Point"}
}