{
  "type": "Feature",
  "properties": {
    "addr:full":"Essendon Airport Bristol St Essendon VIC 3040",
    "addr:postcode":"3040",
    "addr:street":"St",
    "iso:country":"AU",
    "sg:address":"Essendon Airport Bristol St",
    "sg:city":"Essendon",
    "sg:classifiers":[
        {
            "category":"Health Services",
            "subcategory":"Doctor",
            "type":"Services"
        }
    ],
    "sg:phone":"+61 3 9379 4847",
    "sg:postcode":"3040",
    "sg:province":"VIC",
    "sg:tags":[
        "flying"
    ],
    "wof:name":"Royal Flying Doctor Service of Australia (South Eastern Section)",
    "wof:placetype":"venue"
},
  "geometry": {"coordinates":[144.90951538100001,-37.7515411377],"type":"Point"}
}