{
  "type": "Feature",
  "properties": {
    "iso:country":"AU",
    "sg:address":"94 Railway St",
    "sg:city":"Rockdale",
    "sg:classifiers":[
        {
            "category":"Real Estate",
            "subcategory":"Real Estate Agent",
            "type":"Services"
        }
    ],
    "sg:phone":"+61 2 9567 6797",
    "sg:postcode":"2216",
    "sg:province":"NSW",
    "wof:name":"Nationwide Realty Tome Bros",
    "wof:placetype":"venue"
},
  "geometry": {"coordinates":[151.13595599999999,-33.952343],"type":"Point"}
}