{
  "type": "Feature",
  "properties": {
    "addr:full":"Level 1, 12 Spit Rd Spit Junction NSW 2088",
    "addr:housenumber":"12",
    "addr:postcode":"2088",
    "addr:street":"Spit Rd",
    "iso:country":"AU",
    "sg:address":"Level 1, 12 Spit Rd",
    "sg:city":"Spit Junction",
    "sg:classifiers":[
        {
            "category":"Education",
            "subcategory":"Special Training",
            "type":"Public Place"
        }
    ],
    "sg:phone":"+61 2 9968 1233",
    "sg:postcode":"2088",
    "sg:province":"NSW",
    "sg:tags":[
        "school",
        "art"
    ],
    "wof:name":"Northshore School Of Art",
    "wof:placetype":"venue"
},
  "geometry": {"coordinates":[151.241088867,-33.8242111206],"type":"Point"}
}