{
  "type": "Feature",
  "properties": {
    "iso:country":"AU",
    "sg:address":"65 Fennell St",
    "sg:city":"Port Melbourne",
    "sg:classifiers":[
        {
            "category":"Professional",
            "type":"Services"
        }
    ],
    "sg:phone":"+61 13 32 78",
    "sg:postcode":"3207",
    "sg:province":"VIC",
    "sg:tags":[
        "courier"
    ],
    "wof:name":"Toll Fast",
    "wof:placetype":"venue"
},
  "geometry": {"coordinates":[144.931763,-37.831219],"type":"Point"}
}