{
  "type": "Feature",
  "properties": {
    "iso:country":"AU",
    "sg:address":"1359 Pacific Hwy",
    "sg:city":"Kundabung",
    "sg:classifiers":[
        {
            "category":"Food & Beverages",
            "subcategory":"Meat & Fish",
            "type":"Retail Goods"
        }
    ],
    "sg:phone":"+61 2 6561 5133",
    "sg:postcode":"2441",
    "sg:province":"NSW",
    "sg:tags":[
        "aquaculture"
    ],
    "wof:name":"A & D Hambly Silver Perch Farm & Native Fish Hatchery",
    "wof:placetype":"venue"
},
  "geometry": {"coordinates":[152.823456,-31.1922],"type":"Point"}
}