{
  "type": "Feature",
  "properties": {
    "addr:full":"34 Forge St Blacktown NSW 2148",
    "addr:housenumber":"34",
    "addr:postcode":"2148",
    "addr:street":"Forge St",
    "iso:country":"AU",
    "sg:address":"34 Forge St",
    "sg:city":"Blacktown",
    "sg:classifiers":[
        {
            "category":"Utilities",
            "type":"Services"
        }
    ],
    "sg:phone":"+61 2 9676 1888",
    "sg:postcode":"2148",
    "sg:province":"NSW",
    "sg:tags":[
        "refrigeration",
        "industrial",
        "commercial",
        "retail"
    ],
    "wof:name":"Recom Engineering Pty Ltd",
    "wof:placetype":"venue"
},
  "geometry": {"coordinates":[150.90992736800001,-33.7540855408],"type":"Point"}
}