{
  "type": "Feature",
  "properties": {
    "iso:country":"AU",
    "sg:address":"Level 7 BNZ House 109 Banister Rd",
    "sg:city":"Canning Vale",
    "sg:classifiers":[
        {
            "category":"Military Area",
            "subcategory":"Air Force Base",
            "type":"Public Place"
        }
    ],
    "sg:phone":"+61 8 9455 9400",
    "sg:postcode":"6155",
    "sg:province":"WA",
    "sg:tags":[
        "equipment",
        "speed",
        "variation"
    ],
    "wof:name":"ABB Australia Pty Ltd",
    "wof:placetype":"venue"
},
  "geometry": {"coordinates":[115.917717,-32.057671],"type":"Point"}
}