{
  "type": "Feature",
  "properties": {
    "addr:full":"38 Iona Ave Belmont VIC 3216",
    "addr:housenumber":"38",
    "addr:postcode":"3216",
    "addr:street":"Iona Ave",
    "iso:country":"AU",
    "sg:address":"38 Iona Ave",
    "sg:city":"Belmont",
    "sg:classifiers":[
        {
            "category":"Manufacturing",
            "subcategory":"Food",
            "type":"Manufacturing & Wholesale Goods"
        }
    ],
    "sg:phone":"+61 3 5241 2268",
    "sg:postcode":"3216",
    "sg:province":"VIC",
    "sg:tags":[
        "function",
        "catering"
    ],
    "wof:name":"Paella Pan",
    "wof:placetype":"venue"
},
  "geometry": {"coordinates":[144.32464599599999,-38.1781463623],"type":"Point"}
}