{
  "type": "Feature",
  "properties": {
    "addr:full":"39 Rutherford St Charters Towers QLD 4820",
    "addr:housenumber":"39",
    "addr:postcode":"4820",
    "addr:street":"Rutherford St",
    "iso:country":"AU",
    "sg:address":"39 Rutherford St",
    "sg:city":"Charters Towers",
    "sg:classifiers":[
        {
            "category":"Manufacturing",
            "subcategory":"Metals",
            "type":"Manufacturing & Wholesale Goods"
        }
    ],
    "sg:phone":"+61 7 4787 1671",
    "sg:postcode":"4820",
    "sg:province":"QLD",
    "sg:tags":[
        "steel",
        "fabricator",
        "mfrs"
    ],
    "wof:name":"Steel Frabrication & Poly Welding",
    "wof:placetype":"venue"
},
  "geometry": {"coordinates":[146.25237999999999,-20.076199],"type":"Point"}
}