{
  "type": "Feature",
  "properties": {
    "addr:full":"884 Canterbury Rd Lakemba NSW 2195",
    "addr:housenumber":"884",
    "addr:postcode":"2195",
    "addr:street":"Canterbury Rd",
    "iso:country":"AU",
    "sg:address":"884 Canterbury Rd",
    "sg:city":"Lakemba",
    "sg:classifiers":[
        {
            "category":"Autos & Motor Vehicles",
            "subcategory":"Automobile Sales",
            "type":"Retail Goods"
        }
    ],
    "sg:phone":"+61 2 9740 6131",
    "sg:postcode":"2195",
    "sg:province":"NSW",
    "sg:tags":[
        "car",
        "used"
    ],
    "wof:name":"R L Motors Pty Ltd",
    "wof:placetype":"venue"
},
  "geometry": {"coordinates":[151.08165,-33.927094],"type":"Point"}
}