{
  "type": "Feature",
  "properties": {
    "iso:country":"AU",
    "sg:address":"10 Charles St",
    "sg:city":"South Perth",
    "sg:classifiers":[
        {
            "category":"Professional",
            "subcategory":"Accounting & Tax Preparation",
            "type":"Services"
        }
    ],
    "sg:phone":"+61 8 9474 3477",
    "sg:postcode":"6151",
    "sg:province":"WA",
    "sg:tags":[
        "accountant",
        "auditor"
    ],
    "wof:name":"Hyatt & Co Pty Ltd",
    "wof:placetype":"venue"
},
  "geometry": {"coordinates":[115.84963999999999,-31.977077],"type":"Point"}
}