{
  "type": "Feature",
  "properties": {
    "iso:country":"AU",
    "sg:address":"265a Bambra Rd",
    "sg:city":"Caulfield South",
    "sg:classifiers":[
        {
            "category":"Health Services",
            "subcategory":"Doctor",
            "type":"Services"
        }
    ],
    "sg:phone":"+61 3 9523 7179",
    "sg:postcode":"3162",
    "sg:province":"VIC",
    "sg:tags":[
        "medical",
        "practitioner"
    ],
    "wof:name":"Bambra Clinic",
    "wof:placetype":"venue"
},
  "geometry": {"coordinates":[145.02777099599999,-37.8922653198],"type":"Point"}
}