{
  "type": "Feature",
  "properties": {
    "iso:country":"AU",
    "sg:address":"225 Nelson St",
    "sg:city":"Annandale",
    "sg:classifiers":[
        {
            "category":"Professional",
            "subcategory":"Management & Consulting",
            "type":"Services"
        }
    ],
    "sg:phone":"+61 2 9566 4575",
    "sg:postcode":"2038",
    "sg:province":"NSW",
    "sg:tags":[
        "consultant",
        "business"
    ],
    "wof:name":"6e Leadership Coaching",
    "wof:placetype":"venue"
},
  "geometry": {"coordinates":[151.17469787600001,-33.8802108765],"type":"Point"}
}