{
  "type": "Feature",
  "properties": {
    "addr:full":"10 Fifth St Cessnock NSW 2325",
    "addr:housenumber":"10",
    "addr:postcode":"2325",
    "addr:street":"Fifth St",
    "iso:country":"AU",
    "sg:address":"10 Fifth St",
    "sg:city":"Cessnock",
    "sg:classifiers":[
        {
            "category":"Professional",
            "subcategory":"Employment Agencies",
            "type":"Services"
        }
    ],
    "sg:phone":"+61 2 4990 5939",
    "sg:postcode":"2325",
    "sg:province":"NSW",
    "sg:tags":[
        "entertainer",
        "agent"
    ],
    "wof:name":"Funtime Toys & Novelties",
    "wof:placetype":"venue"
},
  "geometry": {"coordinates":[151.359542847,-32.8471565247],"type":"Point"}
}