{
  "type": "Feature",
  "properties": {
    "iso:country":"AU",
    "sg:address":"11/ 14 Ramsay St",
    "sg:city":"Collaroy",
    "sg:classifiers":[
        {
            "category":"Retail",
            "subcategory":"Repair Shop",
            "type":"Services"
        }
    ],
    "sg:phone":"+61 2 9982 8281",
    "sg:postcode":"2097",
    "sg:province":"NSW",
    "sg:tags":[
        "stove",
        "part",
        "range"
    ],
    "wof:name":"Bernard Doran J",
    "wof:placetype":"venue"
},
  "geometry": {"coordinates":[151.29885864299999,-33.7272834778],"type":"Point"}
}