{
  "type": "Feature",
  "properties": {
    "iso:country":"AU",
    "sg:address":"Village Green, Shop 4, 30 Canton Beach Rd",
    "sg:city":"Toukley",
    "sg:classifiers":[
        {
            "category":"Airline",
            "type":"Transportation"
        }
    ],
    "sg:phone":"+61 2 4396 5555",
    "sg:postcode":"2263",
    "sg:province":"NSW",
    "sg:tags":[
        "agent"
    ],
    "wof:name":"Travel Co Pty Ltd",
    "wof:placetype":"venue"
},
  "geometry": {"coordinates":[151.540756,-33.264404],"type":"Point"}
}