{
  "type": "Feature",
  "properties": {
    "addr:full":"Unit 10 2 Brand Drv Thomastown VIC 3074",
    "addr:housenumber":"2",
    "addr:postcode":"3074",
    "addr:street":"Brand Drv",
    "iso:country":"AU",
    "sg:address":"Unit 10 2 Brand Drv",
    "sg:city":"Thomastown",
    "sg:classifiers":[
        {
            "category":"Manufacturing",
            "subcategory":"Rubber & Plastics",
            "type":"Manufacturing & Wholesale Goods"
        }
    ],
    "sg:phone":"+61 3 9464 1010",
    "sg:postcode":"3074",
    "sg:province":"VIC",
    "sg:tags":[
        "moulders"
    ],
    "wof:name":"Salter Plastics",
    "wof:placetype":"venue"
},
  "geometry": {"coordinates":[145.03416442899999,-37.6936187744],"type":"Point"}
}