{
  "type": "Feature",
  "properties": {
    "addr:full":"(Cnr Cumberland Hwy) 391 The Great Western Hwy Wentworthville NSW 2145",
    "addr:postcode":"2145",
    "addr:street":"Cnr Cumberland Hwy 391 The Great;Hwy",
    "iso:country":"AU",
    "sg:address":"(Cnr Cumberland Hwy) 391 The Great Western Hwy",
    "sg:city":"Wentworthville",
    "sg:classifiers":[
        {
            "category":"Retail",
            "subcategory":"Auto Repair",
            "type":"Services"
        }
    ],
    "sg:phone":"+61 2 9632 8188",
    "sg:postcode":"2145",
    "sg:province":"NSW",
    "sg:tags":[
        "repairer",
        "motor",
        "engineer"
    ],
    "wof:name":"Sydney's Family Car Centre",
    "wof:placetype":"venue"
},
  "geometry": {"coordinates":[150.967926025,-33.8151016235],"type":"Point"}
}