{
  "type": "Feature",
  "properties": {
    "addr:full":"Tomahawk Creek Rd Simpson VIC 3266",
    "addr:postcode":"3266",
    "addr:street":"Creek Rd",
    "iso:country":"AU",
    "sg:address":"Tomahawk Creek Rd",
    "sg:city":"Simpson",
    "sg:classifiers":[
        {
            "category":"Farming",
            "subcategory":"Farm",
            "type":"Manufacturing & Wholesale Goods"
        }
    ],
    "sg:phone":"+61 3 5594 3368",
    "sg:postcode":"3266",
    "sg:province":"VIC",
    "sg:tags":[
        "farmer"
    ],
    "wof:name":"Stinchcombe R E & B J",
    "wof:placetype":"venue"
},
  "geometry": {"coordinates":[143.20854187,-38.4941368103],"type":"Point"}
}