{
  "type": "Feature",
  "properties": {
    "iso:country":"AU",
    "sg:address":"44 Parliament Pl",
    "sg:city":"West Perth",
    "sg:classifiers":[
        {
            "category":"Personal",
            "subcategory":"Beauty Salon",
            "type":"Services"
        }
    ],
    "sg:phone":"+61 8 9322 1200",
    "sg:postcode":"6005",
    "sg:province":"WA",
    "sg:tags":[
        "hair",
        "treatment",
        "replacement"
    ],
    "wof:name":"Ashley & Martin",
    "wof:placetype":"venue"
},
  "geometry": {"coordinates":[115.846458435,-31.9512119293],"type":"Point"}
}