{
  "type": "Feature",
  "properties": {
    "addr:full":"343 Barnard St Bendigo VIC 3550",
    "addr:housenumber":"343",
    "addr:postcode":"3550",
    "addr:street":"Barnard St",
    "iso:country":"AU",
    "sg:address":"343 Barnard St",
    "sg:city":"Bendigo",
    "sg:classifiers":[
        {
            "category":"Personal",
            "subcategory":"Beauty Salon",
            "type":"Services"
        }
    ],
    "sg:phone":"+61 3 5441 1313",
    "sg:postcode":"3550",
    "sg:province":"VIC",
    "wof:name":"Alexanders For Beauty",
    "wof:placetype":"venue"
},
  "geometry": {"coordinates":[144.266647339,-36.7593307495],"type":"Point"}
}