{
  "type": "Feature",
  "properties": {
    "addr:full":"57 Wellington St Riverstone NSW 2765",
    "addr:housenumber":"57",
    "addr:postcode":"2765",
    "addr:street":"Wellington St",
    "iso:country":"AU",
    "sg:address":"57 Wellington St",
    "sg:city":"Riverstone",
    "sg:classifiers":[
        {
            "category":"Building & Trades",
            "subcategory":"Construction",
            "type":"Services"
        }
    ],
    "sg:phone":"+61 2 9627 4272",
    "sg:postcode":"2765",
    "sg:province":"NSW",
    "sg:tags":[
        "worker",
        "metal"
    ],
    "wof:name":"Alufab Ind Pty Ltd",
    "wof:placetype":"venue"
},
  "geometry": {"coordinates":[150.86289977999999,-33.6653137207],"type":"Point"}
}