{
  "type": "Feature",
  "properties": {
    "addr:full":"32 Achilles Drv Springwood QLD 4127",
    "addr:housenumber":"32",
    "addr:postcode":"4127",
    "addr:street":"Achilles Drv",
    "iso:country":"AU",
    "sg:address":"32 Achilles Drv",
    "sg:city":"Springwood",
    "sg:classifiers":[
        {
            "category":"Education",
            "subcategory":"Special Training",
            "type":"Public Place"
        }
    ],
    "sg:phone":"+61 7 3209 3597",
    "sg:postcode":"4127",
    "sg:province":"QLD",
    "sg:tags":[
        "equipment",
        "driving",
        "facility"
    ],
    "wof:name":"Choice Driver Training",
    "wof:placetype":"venue"
},
  "geometry": {"coordinates":[153.14169311500001,-27.6306800842],"type":"Point"}
}