{
  "type": "Feature",
  "properties": {
    "addr:full":"7 Villiers Drv Currumbin QLD 4223",
    "addr:housenumber":"7",
    "addr:postcode":"4223",
    "addr:street":"Villiers Drv",
    "iso:country":"AU",
    "sg:address":"7 Villiers Drv",
    "sg:city":"Currumbin",
    "sg:classifiers":[
        {
            "category":"Home & Garden",
            "subcategory":"Building Materials",
            "type":"Retail Goods"
        }
    ],
    "sg:phone":"+61 7 5598 3339",
    "sg:postcode":"4223",
    "sg:province":"QLD",
    "sg:tags":[
        "merchant",
        "glass",
        "glazier"
    ],
    "wof:name":"Amalgamated Glass",
    "wof:placetype":"venue"
},
  "geometry": {"coordinates":[153.47122192399999,-28.1506919861],"type":"Point"}
}