{
  "type": "Feature",
  "properties": {
    "iso:country":"AU",
    "sg:address":"31 Leland St",
    "sg:city":"Penrith",
    "sg:classifiers":[
        {
            "category":"Professional",
            "type":"Services"
        }
    ],
    "sg:phone":"+61 2 4731 3086",
    "sg:postcode":"2750",
    "sg:province":"NSW",
    "sg:tags":[
        "packaging",
        "filling",
        "assembling"
    ],
    "wof:name":"S & G Packaging",
    "wof:placetype":"venue"
},
  "geometry": {"coordinates":[150.69128418,-33.7312164307],"type":"Point"}
}