{
  "type": "Feature",
  "properties": {
    "addr:full":"4421 Main Rd Beauty Point TAS 7270",
    "addr:housenumber":"4421",
    "addr:postcode":"7270",
    "addr:street":"Main Rd",
    "iso:country":"AU",
    "sg:address":"4421 Main Rd",
    "sg:city":"Beauty Point",
    "sg:classifiers":[
        {
            "category":"Retail",
            "subcategory":"Event Space",
            "type":"Services"
        }
    ],
    "sg:phone":"+61 3 6383 4375",
    "sg:postcode":"7270",
    "sg:province":"TAS",
    "sg:tags":[
        "venue",
        "reception",
        "wedding"
    ],
    "wof:name":"Beauty Point Tamar Cove Motel & Restaurant",
    "wof:placetype":"venue"
},
  "geometry": {"coordinates":[146.826705933,-41.1059379578],"type":"Point"}
}