{
  "type": "Feature",
  "properties": {
    "iso:country":"AU",
    "sg:address":"2 Carrington St",
    "sg:city":"Singleton",
    "sg:classifiers":[
        {
            "category":"Home & Garden",
            "subcategory":"Garden Supply",
            "type":"Retail Goods"
        }
    ],
    "sg:phone":"+61 2 6571 5537",
    "sg:postcode":"2330",
    "sg:province":"NSW",
    "sg:tags":[
        "landscape"
    ],
    "wof:name":"Aussie Trees",
    "wof:placetype":"venue"
},
  "geometry": {"coordinates":[151.19392400000001,-32.589611],"type":"Point"}
}