{
  "type": "Feature",
  "properties": {
    "addr:full":"Ste123/ 20 Lexington Drv Bella Vista NSW 2153",
    "addr:housenumber":"20",
    "addr:postcode":"2153",
    "addr:street":"Lexington Drv",
    "iso:country":"AU",
    "sg:address":"Ste123/ 20 Lexington Drv",
    "sg:city":"Bella Vista",
    "sg:classifiers":[
        {
            "category":"Professional",
            "subcategory":"Art Services",
            "type":"Services"
        }
    ],
    "sg:phone":"+61 2 8883 1761",
    "sg:postcode":"2153",
    "sg:province":"NSW",
    "sg:tags":[
        "interior",
        "designer"
    ],
    "wof:name":"The Great Aussie Pub Company",
    "wof:placetype":"venue"
},
  "geometry": {"coordinates":[150.94644165,-33.7348747253],"type":"Point"}
}