{
  "type": "Feature",
  "properties": {
    "addr:full":"Ste9/ 24 St Quentin Ave Claremont WA 6010",
    "addr:housenumber":"24",
    "addr:postcode":"6010",
    "addr:street":"St Quentin Ave",
    "iso:country":"AU",
    "sg:address":"Ste9/ 24 St Quentin Ave",
    "sg:city":"Claremont",
    "sg:classifiers":[
        {
            "category":"Personal",
            "subcategory":"Hair Removal",
            "type":"Services"
        }
    ],
    "sg:phone":"+61 8 9384 7859",
    "sg:postcode":"6010",
    "sg:province":"WA",
    "wof:name":"Hair Free",
    "wof:placetype":"venue"
},
  "geometry": {"coordinates":[115.779586792,-31.9828796387],"type":"Point"}
}