{
  "type": "Feature",
  "properties": {
    "iso:country":"AU",
    "sg:address":"Level 2, 8- 10 Loftus St",
    "sg:city":"Sydney",
    "sg:classifiers":[
        {
            "category":"Manufacturing",
            "subcategory":"Food",
            "type":"Manufacturing & Wholesale Goods"
        }
    ],
    "sg:phone":"+61 2 8274 0111",
    "sg:postcode":"2000",
    "sg:province":"NSW",
    "sg:tags":[
        "function",
        "catering"
    ],
    "wof:name":"Truffle Group Catering The",
    "wof:placetype":"venue"
},
  "geometry": {"coordinates":[151.21061706500001,-33.8625717163],"type":"Point"}
}