{
  "type": "Feature",
  "properties": {
    "addr:full":"Shop 23, 1 North Beach Rd North Beach WA 6020",
    "addr:housenumber":"shop 23 1",
    "addr:postcode":"6020",
    "addr:street":"North Beach Rd",
    "iso:country":"AU",
    "sg:address":"Shop 23, 1 North Beach Rd",
    "sg:city":"North Beach",
    "sg:classifiers":[
        {
            "category":"Cafe",
            "type":"Food & Drink"
        }
    ],
    "sg:phone":"+61 8 9448 9399",
    "sg:postcode":"6020",
    "sg:province":"WA",
    "wof:name":"Pelican Sports Cafe",
    "wof:placetype":"venue"
},
  "geometry": {"coordinates":[115.753219605,-31.8609142303],"type":"Point"}
}