{
  "type": "Feature",
  "properties": {
    "iso:country":"AU",
    "sg:address":"10 Pomona St",
    "sg:city":"Pennant Hills",
    "sg:classifiers":[
        {
            "category":"Building & Trades",
            "subcategory":"Plumbing",
            "type":"Services"
        }
    ],
    "sg:phone":"+61 412 100 646",
    "sg:postcode":"2120",
    "sg:province":"NSW",
    "sg:tags":[
        "plumber",
        "gasfitters"
    ],
    "wof:name":"Clearflow Plumbing Services",
    "wof:placetype":"venue"
},
  "geometry": {"coordinates":[151.07807922399999,-33.7356681824],"type":"Point"}
}