{
  "type": "Feature",
  "properties": {
    "addr:full":"40 Scahill St Campsie NSW 2194",
    "addr:housenumber":"40",
    "addr:postcode":"2194",
    "addr:street":"Scahill St",
    "iso:country":"AU",
    "sg:address":"40 Scahill St",
    "sg:city":"Campsie",
    "sg:classifiers":[
        {
            "category":"Professional",
            "subcategory":"Accounting & Tax Preparation",
            "type":"Services"
        }
    ],
    "sg:phone":"+61 2 9718 8777",
    "sg:postcode":"2194",
    "sg:province":"NSW",
    "sg:tags":[
        "accountant",
        "auditor"
    ],
    "wof:name":"Moses J & Associates",
    "wof:placetype":"venue"
},
  "geometry": {"coordinates":[151.10751300000001,-33.920265],"type":"Point"}
}