{
  "type": "Feature",
  "properties": {
    "addr:full":"31 Chadlington Drv Padbury WA 6025",
    "addr:housenumber":"31",
    "addr:postcode":"6025",
    "addr:street":"Chadlington Drv",
    "iso:country":"AU",
    "sg:address":"31 Chadlington Drv",
    "sg:city":"Padbury",
    "sg:classifiers":[
        {
            "category":"Conference Center",
            "type":"Public Place"
        }
    ],
    "sg:phone":"+61 8 9307 5000",
    "sg:postcode":"6025",
    "sg:province":"WA",
    "sg:tags":[
        "venue",
        "convention"
    ],
    "wof:name":"NorthCity Conference Centre",
    "wof:placetype":"venue"
},
  "geometry": {"coordinates":[115.777587891,-31.8155040741],"type":"Point"}
}