{
  "type": "Feature",
  "properties": {
    "addr:full":"342- 346 Pacific Hwy Crows Nest NSW 2065",
    "addr:housenumber":"346",
    "addr:postcode":"2065",
    "addr:street":"Pacific Hwy",
    "iso:country":"AU",
    "sg:address":"342- 346 Pacific Hwy",
    "sg:city":"Crows Nest",
    "sg:classifiers":[
        {
            "category":"Restaurant",
            "type":"Food & Drink"
        }
    ],
    "sg:phone":"+61 2 9439 8466",
    "sg:postcode":"2065",
    "sg:province":"NSW",
    "wof:name":"Chopsticks Seafood Restaurant",
    "wof:placetype":"venue"
},
  "geometry": {"coordinates":[151.19972229000001,-33.8268356323],"type":"Point"}
}