{
  "type": "Feature",
  "properties": {
    "addr:full":"7 Ellenbrook Shopng Cntr Cnr Promenade & Pinaster Rds Ellenbrook WA 6069",
    "addr:housenumber":"7",
    "addr:postcode":"6069",
    "addr:street":"Cnr Promenade & Pinaster Rds",
    "iso:country":"AU",
    "sg:address":"7 Ellenbrook Shopng Cntr Cnr Promenade & Pinaster Rds",
    "sg:city":"Ellenbrook",
    "sg:classifiers":[
        {
            "category":"Food & Beverages",
            "subcategory":"Bakery",
            "type":"Retail Goods"
        }
    ],
    "sg:phone":"+61 8 9296 7763",
    "sg:postcode":"6069",
    "sg:province":"WA",
    "sg:tags":[
        "baker"
    ],
    "wof:name":"Brumby's WA & NT",
    "wof:placetype":"venue"
},
  "geometry": {"coordinates":[115.973907471,-31.7902736664],"type":"Point"}
}