{
  "type": "Feature",
  "properties": {
    "iso:country":"AU",
    "sg:address":"4 Elder Pl",
    "sg:city":"Padbury",
    "sg:classifiers":[
        {
            "category":"Health Services",
            "subcategory":"Health Practitioner",
            "type":"Services"
        }
    ],
    "sg:phone":"+61 408 930 312",
    "sg:postcode":"6025",
    "sg:province":"WA",
    "sg:tags":[
        "naturopath"
    ],
    "wof:name":"Wehland Cornelia",
    "wof:placetype":"venue"
},
  "geometry": {"coordinates":[115.759140015,-31.8023338318],"type":"Point"}
}