{
  "type": "Feature",
  "properties": {
    "addr:full":"Cnr Bendigo & Ballarat Rds St Arnaud VIC 3478",
    "addr:postcode":"3478",
    "addr:street":"Cnr;Rds",
    "iso:country":"AU",
    "sg:address":"Cnr Bendigo & Ballarat Rds",
    "sg:city":"St Arnaud",
    "sg:classifiers":[
        {
            "category":"Travel",
            "subcategory":"Hotels & Motels",
            "type":"Entertainment"
        }
    ],
    "sg:phone":"+61 3 5495 2255",
    "sg:postcode":"3478",
    "sg:province":"VIC",
    "wof:name":"Country Road Motel St Arnaud",
    "wof:placetype":"venue"
},
  "geometry": {"coordinates":[143.25793457,-36.6163482666],"type":"Point"}
}