{
  "type": "Feature",
  "properties": {
    "iso:country":"AU",
    "sg:address":"139 Henley Beach Rd",
    "sg:city":"Mile End",
    "sg:classifiers":[
        {
            "category":"Food & Beverages",
            "subcategory":"Liquor & Beverages",
            "type":"Retail Goods"
        }
    ],
    "sg:phone":"+61 8 8234 8901",
    "sg:postcode":"5031",
    "sg:province":"SA",
    "sg:tags":[
        "store"
    ],
    "wof:name":"First Estate Wine Merchants",
    "wof:placetype":"venue"
},
  "geometry": {"coordinates":[138.56443786599999,-34.9241943359],"type":"Point"}
}