{
  "type": "Feature",
  "properties": {
    "addr:full":"26 Zouch St Young NSW 2594",
    "addr:housenumber":"26",
    "addr:postcode":"2594",
    "addr:street":"Zouch St",
    "iso:country":"AU",
    "sg:address":"26 Zouch St",
    "sg:city":"Young",
    "sg:classifiers":[
        {
            "category":"Cafe",
            "type":"Food & Drink"
        }
    ],
    "sg:phone":"+61 2 6382 2775",
    "sg:postcode":"2594",
    "sg:province":"NSW",
    "wof:name":"Zouch Cafe & Restaurant",
    "wof:placetype":"venue"
},
  "geometry": {"coordinates":[148.300247192,-34.31483078],"type":"Point"}
}