{
  "type": "Feature",
  "properties": {
    "addr:full":"Warner St Warwick QLD 4370",
    "addr:postcode":"4370",
    "addr:street":"Warner St",
    "iso:country":"AU",
    "sg:address":"Warner St",
    "sg:city":"Warwick",
    "sg:classifiers":[
        {
            "category":"Utilities",
            "subcategory":"Mobile Phone",
            "type":"Services"
        }
    ],
    "sg:phone":"+61 7 4661 2833",
    "sg:postcode":"4370",
    "sg:province":"QLD",
    "sg:tags":[
        "aviation",
        "consultant"
    ],
    "wof:name":"Keogh R J & K J",
    "wof:placetype":"venue"
},
  "geometry": {"coordinates":[152.00198364299999,-28.2233047485],"type":"Point"}
}