{
  "type": "Feature",
  "properties": {
    "iso:country":"AU",
    "sg:address":"13 Fenton Pl",
    "sg:city":"Wongan Hills",
    "sg:classifiers":[
        {
            "category":"Shopping",
            "subcategory":"Department Store",
            "type":"Retail Goods"
        }
    ],
    "sg:phone":"+61 8 9671 1922",
    "sg:postcode":"6603",
    "sg:province":"WA",
    "wof:name":"Country Choice",
    "wof:placetype":"venue"
},
  "geometry": {"coordinates":[116.717948914,-30.8939170837],"type":"Point"}
}