{
  "type": "Feature",
  "properties": {
    "iso:country":"AU",
    "sg:address":"39 Melverton Drv",
    "sg:city":"Hallam",
    "sg:classifiers":[
        {
            "category":"Bars & Pubs",
            "subcategory":"Biergarten",
            "type":"Food & Drink"
        }
    ],
    "sg:phone":"+61 3 9796 4833",
    "sg:postcode":"3803",
    "sg:province":"VIC",
    "sg:tags":[
        "eucalyptus",
        "oil",
        "tree",
        "essential",
        "tea"
    ],
    "sg:website":"http://www.auroma.com.au",
    "wof:name":"Australian Botanical Products Pty Ltd",
    "wof:placetype":"venue"
},
  "geometry": {"coordinates":[145.274780273,-38.0114250183],"type":"Point"}
}