{
  "type": "Feature",
  "properties": {
    "iso:country":"AU",
    "sg:address":"116B Anstruther Rd",
    "sg:city":"Mandurah",
    "sg:classifiers":[
        {
            "category":"Professional",
            "subcategory":"Accounting & Tax Preparation",
            "type":"Services"
        }
    ],
    "sg:phone":"+61 8 9535 8955",
    "sg:postcode":"6210",
    "sg:province":"WA",
    "sg:tags":[
        "accountant",
        "auditor"
    ],
    "wof:name":"Timark Accounting Pty Ltd",
    "wof:placetype":"venue"
},
  "geometry": {"coordinates":[115.731682,-32.520905],"type":"Point"}
}