{
  "type": "Feature",
  "properties": {
    "addr:full":"11 Enterprise Cl Gosford West NSW 2250",
    "addr:housenumber":"11",
    "addr:postcode":"2250",
    "addr:street":"Enterprise Cl Gosford West",
    "iso:country":"AU",
    "sg:address":"11 Enterprise Cl",
    "sg:city":"Gosford West",
    "sg:classifiers":[
        {
            "category":"Retail",
            "subcategory":"Auto Repair",
            "type":"Services"
        }
    ],
    "sg:phone":"+61 2 4325 3568",
    "sg:postcode":"2250",
    "sg:province":"NSW",
    "sg:tags":[
        "transmission",
        "automotive",
        "car"
    ],
    "wof:name":"Central Coast Automatics",
    "wof:placetype":"venue"
},
  "geometry": {"coordinates":[151.38240051299999,-33.3466453552],"type":"Point"}
}