{
  "type": "Feature",
  "properties": {
    "addr:full":"5 Delma Ave Cairnlea VIC 3023",
    "addr:housenumber":"5",
    "addr:postcode":"3023",
    "addr:street":"Delma Ave",
    "iso:country":"AU",
    "sg:address":"5 Delma Ave",
    "sg:city":"Cairnlea",
    "sg:classifiers":[
        {
            "category":"Building & Trades",
            "subcategory":"Construction",
            "type":"Services"
        }
    ],
    "sg:phone":"+61 3 8361 8031",
    "sg:postcode":"3023",
    "sg:province":"VIC",
    "sg:tags":[
        "roof"
    ],
    "wof:name":"Sunrise Roofing",
    "wof:placetype":"venue"
},
  "geometry": {"coordinates":[144.785706,-37.751915],"type":"Point"}
}