{
  "type": "Feature",
  "properties": {
    "addr:full":"Cnr Merthyr Rd & Brunswick St New Farm QLD 4005",
    "addr:postcode":"4005",
    "addr:street":"Cnr Merthyr Rd & Brunswick St",
    "iso:country":"AU",
    "sg:address":"Cnr Merthyr Rd & Brunswick St",
    "sg:city":"New Farm",
    "sg:classifiers":[
        {
            "category":"Health Services",
            "subcategory":"Health Practitioner",
            "type":"Services"
        }
    ],
    "sg:phone":"+61 7 3358 5481",
    "sg:postcode":"4005",
    "sg:province":"QLD",
    "sg:tags":[
        "physiotherapist"
    ],
    "wof:name":"New Farm Physiotherapy",
    "wof:placetype":"venue"
},
  "geometry": {"coordinates":[153.04612731899999,-27.4671821594],"type":"Point"}
}