{
  "type": "Feature",
  "properties": {
    "addr:full":"14 Namatjira Crt Taylors Lakes VIC 3038",
    "addr:housenumber":"14",
    "addr:postcode":"3038",
    "addr:street":"Namatjira Crt",
    "iso:country":"AU",
    "sg:address":"14 Namatjira Crt",
    "sg:city":"Taylors Lakes",
    "sg:classifiers":[
        {
            "category":"Utilities",
            "subcategory":"Electric",
            "type":"Services"
        }
    ],
    "sg:phone":"+61 3 9449 1964",
    "sg:postcode":"3038",
    "sg:province":"VIC",
    "sg:tags":[
        "electrical",
        "contractor"
    ],
    "wof:name":"Jacogan Electrics Pty Ltd",
    "wof:placetype":"venue"
},
  "geometry": {"coordinates":[144.78132600000001,-37.696911],"type":"Point"}
}