{
  "type": "Feature",
  "properties": {
    "addr:full":"52 Real Ave Norman Park QLD 4170",
    "addr:housenumber":"52",
    "addr:postcode":"4170",
    "addr:street":"Real Ave",
    "iso:country":"AU",
    "sg:address":"52 Real Ave",
    "sg:city":"Norman Park",
    "sg:classifiers":[
        {
            "category":"Building & Trades",
            "subcategory":"Construction",
            "type":"Services"
        }
    ],
    "sg:phone":"+61 7 3843 2554",
    "sg:postcode":"4170",
    "sg:province":"QLD",
    "sg:tags":[
        "renovation",
        "alterations",
        "extension",
        "contractor"
    ],
    "wof:name":"A 1 Restumping Service",
    "wof:placetype":"venue"
},
  "geometry": {"coordinates":[153.06637573200001,-27.4852256775],"type":"Point"}
}