{
  "type": "Feature",
  "properties": {
    "iso:country":"AU",
    "sg:address":"Level 4 36 York St",
    "sg:city":"Sydney",
    "sg:classifiers":[
        {
            "category":"Professional",
            "subcategory":"Employment Agencies",
            "type":"Services"
        }
    ],
    "sg:phone":"+61 2 9279 2733",
    "sg:postcode":"2000",
    "sg:province":"NSW",
    "wof:name":"I.T. Matters Recruitment Services Pty Ltd",
    "wof:placetype":"venue"
},
  "geometry": {"coordinates":[151.20625305199999,-33.8689880371],"type":"Point"}
}