{
  "type": "Feature",
  "properties": {
    "iso:country":"AU",
    "sg:address":"4 Fourth Ave",
    "sg:city":"Seaton",
    "sg:classifiers":[
        {
            "category":"Professional",
            "subcategory":"Art Services",
            "type":"Services"
        }
    ],
    "sg:phone":"+61 413 888 812",
    "sg:postcode":"5023",
    "sg:province":"SA",
    "sg:tags":[
        "decorator",
        "painter"
    ],
    "wof:name":"Night Sky Ceilings",
    "wof:placetype":"venue"
},
  "geometry": {"coordinates":[138.51640319800001,-34.8831291199],"type":"Point"}
}