{
  "type": "Feature",
  "properties": {
    "iso:country":"AU",
    "sg:address":"243 Bay St",
    "sg:city":"Brighton-le-Sands",
    "sg:classifiers":[
        {
            "category":"Health Services",
            "subcategory":"Chiropractor",
            "type":"Services"
        }
    ],
    "sg:phone":"+61 2 9567 2755",
    "sg:postcode":"2216",
    "sg:province":"NSW",
    "wof:name":"Brighton Chiropractic Centre",
    "wof:placetype":"venue"
},
  "geometry": {"coordinates":[151.15164200000001,-33.959061],"type":"Point"}
}