{
  "type": "Feature",
  "properties": {
    "addr:full":"Shop 6, Enterprise Way Mitcham VIC 3132",
    "addr:housenumber":"shop 6",
    "addr:postcode":"3132",
    "addr:street":"Enterprise Way",
    "iso:country":"AU",
    "sg:address":"Shop 6, Enterprise Way",
    "sg:city":"Mitcham",
    "sg:classifiers":[
        {
            "category":"Professional",
            "subcategory":"Accounting & Tax Preparation",
            "type":"Services"
        }
    ],
    "sg:phone":"+61 3 9874 4886",
    "sg:postcode":"3132",
    "sg:province":"VIC",
    "sg:tags":[
        "consultant",
        "taxation"
    ],
    "wof:name":"Stolarek Accounting Services",
    "wof:placetype":"venue"
},
  "geometry": {"coordinates":[145.192016602,-37.816028595],"type":"Point"}
}