{
  "type": "Feature",
  "properties": {
    "addr:full":"1 Bouvard Drv Bouvard WA 6210",
    "addr:housenumber":"1",
    "addr:postcode":"6210",
    "addr:street":"Bouvard Drv",
    "iso:country":"AU",
    "sg:address":"1 Bouvard Drv",
    "sg:city":"Bouvard",
    "sg:classifiers":[
        {
            "category":"Health Services",
            "subcategory":"Health Practitioner",
            "type":"Services"
        }
    ],
    "sg:phone":"+61 403 718 355",
    "sg:postcode":"6210",
    "sg:province":"WA",
    "sg:tags":[
        "hypnotherapy"
    ],
    "wof:name":"Steinbock Laura",
    "wof:placetype":"venue"
},
  "geometry": {"coordinates":[115.78473700000001,-32.509258],"type":"Point"}
}