{
  "type": "Feature",
  "properties": {
    "addr:full":"2 Vaughan St Sunbury VIC 3429",
    "addr:housenumber":"2",
    "addr:postcode":"3429",
    "addr:street":"Vaughan St",
    "iso:country":"AU",
    "sg:address":"2 Vaughan St",
    "sg:city":"Sunbury",
    "sg:classifiers":[
        {
            "category":"Farming",
            "subcategory":"Dairy Farm",
            "type":"Manufacturing & Wholesale Goods"
        }
    ],
    "sg:phone":"+61 418 389 491",
    "sg:postcode":"3429",
    "sg:province":"VIC",
    "wof:name":"McMahon's Milk",
    "wof:placetype":"venue"
},
  "geometry": {"coordinates":[144.73939514200001,-37.5800590515],"type":"Point"}
}