{
  "type": "Feature",
  "properties": {
    "addr:full":"20 Dennistoun St Sunnybank Hills QLD 4109",
    "addr:housenumber":"20",
    "addr:postcode":"4109",
    "addr:street":"Dennistoun St",
    "iso:country":"AU",
    "sg:address":"20 Dennistoun St",
    "sg:city":"Sunnybank Hills",
    "sg:classifiers":[
        {
            "category":"Building & Trades",
            "subcategory":"Construction",
            "type":"Services"
        }
    ],
    "sg:phone":"+61 7 3345 4201",
    "sg:postcode":"4109",
    "sg:province":"QLD",
    "sg:tags":[
        "rendering",
        "cement"
    ],
    "wof:name":"Vit Plastering Co",
    "wof:placetype":"venue"
},
  "geometry": {"coordinates":[153.059249878,-27.5891742706],"type":"Point"}
}