{
  "type": "Feature",
  "properties": {
    "addr:full":"Rutleys Rd Vales Point NSW 2259",
    "addr:postcode":"2259",
    "addr:street":"Rutleys Rd",
    "iso:country":"AU",
    "sg:address":"Rutleys Rd",
    "sg:city":"Vales Point",
    "sg:classifiers":[
        {
            "category":"Building & Trades",
            "subcategory":"Construction",
            "type":"Services"
        }
    ],
    "sg:phone":"+61 2 4359 1988",
    "sg:postcode":"2259",
    "sg:province":"NSW",
    "sg:tags":[
        "earth",
        "excavating",
        "moving",
        "contractor"
    ],
    "wof:name":"Erinbrook Pty Ltd",
    "wof:placetype":"venue"
},
  "geometry": {"coordinates":[151.53379821799999,-33.1645393372],"type":"Point"}
}