{
  "type": "Feature",
  "properties": {
    "iso:country":"AU",
    "sg:address":"83 Church St",
    "sg:city":"Mudgee",
    "sg:classifiers":[
        {
            "category":"Health Services",
            "subcategory":"Doctor",
            "type":"Services"
        }
    ],
    "sg:phone":"+61 2 6372 6544",
    "sg:postcode":"2850",
    "sg:province":"NSW",
    "sg:tags":[
        "medical",
        "practitioner"
    ],
    "wof:name":"Mudgee Radiology",
    "wof:placetype":"venue"
},
  "geometry": {"coordinates":[149.58526599999999,-32.607056],"type":"Point"}
}