{
  "type": "Feature",
  "properties": {
    "addr:full":"201/ 79 Grafton St Bondi Junction NSW 2022",
    "addr:housenumber":"201 / 79",
    "addr:postcode":"2022",
    "addr:street":"Grafton St",
    "iso:country":"AU",
    "sg:address":"201/ 79 Grafton St",
    "sg:city":"Bondi Junction",
    "sg:classifiers":[
        {
            "category":"Personal",
            "subcategory":"Massage",
            "type":"Services"
        }
    ],
    "sg:phone":"+61 402 797 894",
    "sg:postcode":"2022",
    "sg:province":"NSW",
    "sg:tags":[
        "therapy"
    ],
    "wof:name":"Karinas Holistic Massage",
    "wof:placetype":"venue"
},
  "geometry": {"coordinates":[151.24707031200001,-33.8907814026],"type":"Point"}
}