{
  "type": "Feature",
  "properties": {
    "addr:full":"17 Green St Doveton VIC 3177",
    "addr:housenumber":"17",
    "addr:postcode":"3177",
    "addr:street":"Green St",
    "iso:country":"AU",
    "sg:address":"17 Green St",
    "sg:city":"Doveton",
    "sg:classifiers":[
        {
            "category":"Social Services",
            "subcategory":"Job Training",
            "type":"Services"
        }
    ],
    "sg:phone":"+61 3 9793 2340",
    "sg:postcode":"3177",
    "sg:province":"VIC",
    "sg:tags":[
        "control",
        "equipment",
        "noise"
    ],
    "wof:name":"dB# Acoustics Pty. Ltd.",
    "wof:placetype":"venue"
},
  "geometry": {"coordinates":[145.231689453,-37.9985160828],"type":"Point"}
}