{
  "type": "Feature",
  "properties": {
    "addr:full":"Bankstown Square 1 North Tce Bankstown NSW 1885",
    "addr:housenumber":"1",
    "addr:postcode":"1885",
    "addr:street":"North Tce",
    "iso:country":"AU",
    "sg:address":"Bankstown Square 1",
    "sg:city":"North Tce Bankstown",
    "sg:classifiers":[
        {
            "category":"Shopping",
            "subcategory":"Music",
            "type":"Retail Goods"
        }
    ],
    "sg:phone":"+61 2 9708 3999",
    "sg:postcode":"1885",
    "sg:province":"NSW",
    "sg:tags":[
        "store"
    ],
    "wof:name":"JB HI-FI",
    "wof:placetype":"venue"
},
  "geometry": {"coordinates":[151.034912109,-33.9195404053],"type":"Point"}
}