{
  "type": "Feature",
  "properties": {
    "iso:country":"AU",
    "sg:address":"Unit 2, 6-8 Mitchell Rd",
    "sg:city":"Moorebank",
    "sg:classifiers":[
        {
            "category":"Building & Trades",
            "subcategory":"Pest Control",
            "type":"Services"
        }
    ],
    "sg:phone":"+61 2 9734 7444",
    "sg:postcode":"2170",
    "sg:province":"NSW",
    "sg:tags":[
        "wholesaler",
        "mfrs",
        "diary"
    ],
    "sg:website":"http://www.corporateimpressions.com.au",
    "wof:name":"Corporate Impressions Australia",
    "wof:placetype":"venue"
},
  "geometry": {"coordinates":[150.937255859,-33.9358253479],"type":"Point"}
}