{
  "type": "Feature",
  "properties": {
    "addr:full":"Level 20 99 Walker St North Sydney NSW 2060",
    "addr:housenumber":"99",
    "addr:postcode":"2060",
    "addr:street":"Walker St",
    "iso:country":"AU",
    "sg:address":"Level 20 99 Walker St",
    "sg:city":"North Sydney",
    "sg:classifiers":[
        {
            "category":"Manufacturing",
            "subcategory":"Food",
            "type":"Manufacturing & Wholesale Goods"
        }
    ],
    "sg:phone":"+61 2 9923 2001",
    "sg:postcode":"2060",
    "sg:province":"NSW",
    "sg:tags":[
        "function",
        "catering"
    ],
    "wof:name":"Tesa Advertising",
    "wof:placetype":"venue"
},
  "geometry": {"coordinates":[151.208786011,-33.8398933411],"type":"Point"}
}