{
  "type": "Feature",
  "properties": {
    "iso:country":"AU",
    "sg:address":"Drummond St",
    "sg:city":"Drummond",
    "sg:classifiers":[
        {
            "category":"Building & Trades",
            "subcategory":"Locksmith",
            "type":"Services"
        }
    ],
    "sg:phone":"+61 407 335 911",
    "sg:postcode":"3461",
    "sg:province":"VIC",
    "sg:tags":[
        "lock"
    ],
    "wof:name":"Absolute Locksmiths Dayelsford",
    "wof:placetype":"venue"
},
  "geometry": {"coordinates":[144.31951904300001,-37.3938789368],"type":"Point"}
}