{
  "type": "Feature",
  "properties": {
    "addr:full":"46 Bouverie St Mundubbera QLD 4626",
    "addr:housenumber":"46",
    "addr:postcode":"4626",
    "addr:street":"Bouverie St",
    "iso:country":"AU",
    "sg:address":"46 Bouverie St",
    "sg:city":"Mundubbera",
    "sg:classifiers":[
        {
            "category":"Wholesale",
            "subcategory":"Farm Supplies",
            "type":"Manufacturing & Wholesale Goods"
        }
    ],
    "sg:phone":"+61 7 4165 4233",
    "sg:postcode":"4626",
    "sg:province":"QLD",
    "sg:tags":[
        "equipment"
    ],
    "wof:name":"Gayndah Rural & Veterinary Supplies",
    "wof:placetype":"venue"
},
  "geometry": {"coordinates":[151.30014,-25.586548],"type":"Point"}
}