{
  "type": "Feature",
  "properties": {
    "addr:full":"165 Shambrook Ave Armidale NSW 2350",
    "addr:housenumber":"165",
    "addr:postcode":"2350",
    "addr:street":"Shambrook Ave",
    "iso:country":"AU",
    "sg:address":"165 Shambrook Ave",
    "sg:city":"Armidale",
    "sg:classifiers":[
        {
            "category":"Utilities",
            "subcategory":"Water",
            "type":"Services"
        }
    ],
    "sg:phone":"+61 2 6772 1624",
    "sg:postcode":"2350",
    "sg:province":"NSW",
    "sg:tags":[
        "cartage"
    ],
    "wof:name":"McFayden Wayne",
    "wof:placetype":"venue"
},
  "geometry": {"coordinates":[151.64581298799999,-30.5096187592],"type":"Point"}
}