{
  "type": "Feature",
  "properties": {
    "iso:country":"AU",
    "sg:address":"235 Lonsdale St",
    "sg:city":"Dandenong",
    "sg:classifiers":[
        {
            "category":"Shopping",
            "subcategory":"Bridal",
            "type":"Retail Goods"
        }
    ],
    "sg:phone":"+61 3 9792 4051",
    "sg:postcode":"3175",
    "sg:province":"VIC",
    "sg:tags":[
        "hire",
        "wear"
    ],
    "wof:name":"Merino Club",
    "wof:placetype":"venue"
},
  "geometry": {"coordinates":[145.214187622,-37.9884109497],"type":"Point"}
}