{
  "type": "Feature",
  "properties": {
    "addr:full":"1391 Sandgate Rd Nundah QLD 4012",
    "addr:housenumber":"1391",
    "addr:postcode":"4012",
    "addr:street":"Sandgate Rd",
    "iso:country":"AU",
    "sg:address":"1391 Sandgate Rd",
    "sg:city":"Nundah",
    "sg:phone":"+61 1300 882 783",
    "sg:postcode":"4012",
    "sg:province":"QLD",
    "wof:name":"Aquatap Rainwater Tanks",
    "wof:placetype":"venue"
},
  "geometry": {"coordinates":[153.05934143100001,-27.3985404968],"type":"Point"}
}