{
  "type": "Feature",
  "properties": {
    "iso:country":"AU",
    "sg:address":"12 Sewell Ave",
    "sg:city":"Padstow Heights",
    "sg:classifiers":[
        {
            "category":"Banks & Credit Unions",
            "subcategory":"Investment Brokerage",
            "type":"Services"
        }
    ],
    "sg:phone":"+61 417 277 164",
    "sg:postcode":"2211",
    "sg:province":"NSW",
    "sg:tags":[
        "finance",
        "broker"
    ],
    "wof:name":"Garry F. Scott",
    "wof:placetype":"venue"
},
  "geometry": {"coordinates":[151.03265400000001,-33.96946],"type":"Point"}
}