{
  "type": "Feature",
  "properties": {
    "addr:full":"110 Wakefield St Adelaide SA 5000",
    "addr:housenumber":"110",
    "addr:postcode":"5000",
    "addr:street":"Wakefield St",
    "iso:country":"AU",
    "sg:address":"110 Wakefield St",
    "sg:city":"Adelaide",
    "sg:classifiers":[
        {
            "category":"Autos & Motor Vehicles",
            "subcategory":"Auto Supplies",
            "type":"Retail Goods"
        }
    ],
    "sg:phone":"+61 8 8232 5622",
    "sg:postcode":"5000",
    "sg:province":"SA",
    "sg:tags":[
        "tyre"
    ],
    "wof:name":"Kevin Kenny Tyres",
    "wof:placetype":"venue"
},
  "geometry": {"coordinates":[138.604812622,-34.9281463623],"type":"Point"}
}