{
  "type": "Feature",
  "properties": {
    "iso:country":"AU",
    "sg:address":"8 Wood Rd",
    "sg:city":"Paradise",
    "sg:classifiers":[
        {
            "category":"Building & Trades",
            "subcategory":"Construction",
            "type":"Services"
        }
    ],
    "sg:phone":"+61 8 8337 7904",
    "sg:postcode":"5075",
    "sg:province":"SA",
    "sg:tags":[
        "concrete",
        "contractor"
    ],
    "wof:name":"Beatrice N",
    "wof:placetype":"venue"
},
  "geometry": {"coordinates":[138.68153381400001,-34.8704452515],"type":"Point"}
}