{
  "type": "Feature",
  "properties": {
    "addr:full":"Shop 1/ 253 Oxford St Bondi Junction NSW 2022",
    "addr:housenumber":"shop 1 / 253",
    "addr:postcode":"2022",
    "addr:street":"Oxford St",
    "iso:country":"AU",
    "sg:address":"Shop 1/ 253 Oxford St",
    "sg:city":"Bondi Junction",
    "sg:classifiers":[
        {
            "category":"Retail",
            "subcategory":"Laundry & Dry Cleaning",
            "type":"Services"
        }
    ],
    "sg:phone":"+61 2 9387 4504",
    "sg:postcode":"2022",
    "sg:province":"NSW",
    "sg:tags":[
        "manicurist"
    ],
    "wof:name":"Australian Beauty & Nails",
    "wof:placetype":"venue"
},
  "geometry": {"coordinates":[151.252563477,-33.8913955688],"type":"Point"}
}