{
  "type": "Feature",
  "properties": {
    "addr:full":"Emporium, Shop 25 / 1000 Ann St Fortitude Valley QLD 4006",
    "addr:housenumber":"25 / 1000",
    "addr:postcode":"4006",
    "addr:street":"Ann St",
    "iso:country":"AU",
    "sg:address":"Emporium, Shop 25 / 1000 Ann St",
    "sg:city":"Fortitude Valley",
    "sg:classifiers":[
        {
            "category":"Personal",
            "subcategory":"Beauty Salon",
            "type":"Services"
        }
    ],
    "sg:phone":"+61 7 3252 3884",
    "sg:postcode":"4006",
    "sg:province":"QLD",
    "wof:name":"A Bodi Studio",
    "wof:placetype":"venue"
},
  "geometry": {"coordinates":[153.039627075,-27.4535961151],"type":"Point"}
}