{
  "type": "Feature",
  "properties": {
    "iso:country":"AU",
    "sg:address":"103 Plunkett St",
    "sg:city":"Nowra",
    "sg:classifiers":[
        {
            "category":"Wholesale",
            "subcategory":"Electrical",
            "type":"Manufacturing & Wholesale Goods"
        }
    ],
    "sg:phone":"+61 2 4423 1232",
    "sg:postcode":"2541",
    "sg:province":"NSW",
    "sg:tags":[
        "wholesaler"
    ],
    "wof:name":"TLE Electrical",
    "wof:placetype":"venue"
},
  "geometry": {"coordinates":[150.60255432100001,-34.8787727356],"type":"Point"}
}