{
  "type": "Feature",
  "properties": {
    "iso:country":"AU",
    "sg:address":"Shp 7/ 475 Payneham Rd",
    "sg:city":"Felixstow",
    "sg:classifiers":[
        {
            "category":"Fast Food",
            "type":"Food & Drink"
        }
    ],
    "sg:phone":"+61 8 8336 3777",
    "sg:postcode":"5070",
    "sg:province":"SA",
    "sg:tags":[
        "away",
        "take"
    ],
    "wof:name":"Bella Piatto",
    "wof:placetype":"venue"
},
  "geometry": {"coordinates":[138.65498352,-34.8899040222],"type":"Point"}
}