{
  "type": "Feature",
  "properties": {
    "addr:full":"2f Cochrane St Mitcham VIC 3132",
    "addr:housenumber":"2f",
    "addr:postcode":"3132",
    "addr:street":"Cochrane St",
    "iso:country":"AU",
    "sg:address":"2f Cochrane St",
    "sg:city":"Mitcham",
    "sg:classifiers":[
        {
            "category":"Wholesale",
            "subcategory":"Apparel",
            "type":"Manufacturing & Wholesale Goods"
        }
    ],
    "sg:phone":"+61 3 9872 4388",
    "sg:postcode":"3132",
    "sg:province":"VIC",
    "sg:tags":[
        "wholesaler",
        "mfrs",
        "uniform"
    ],
    "wof:name":"K & M Trading Pty Ltd",
    "wof:placetype":"venue"
},
  "geometry": {"coordinates":[145.202224731,-37.8170509338],"type":"Point"}
}