{
  "type": "Feature",
  "properties": {
    "addr:full":"108 Gillles St Adelaide SA 5000",
    "addr:housenumber":"108",
    "addr:postcode":"5000",
    "addr:street":"Gillles St",
    "iso:country":"AU",
    "sg:address":"108 Gillles St",
    "sg:city":"Adelaide",
    "sg:classifiers":[
        {
            "category":"Real Estate",
            "subcategory":"Surveying",
            "type":"Services"
        }
    ],
    "sg:phone":"+61 8 8223 6366",
    "sg:postcode":"5000",
    "sg:province":"SA",
    "sg:tags":[
        "surveyor",
        "land"
    ],
    "wof:name":"Smith & Higgins & Associates",
    "wof:placetype":"venue"
},
  "geometry": {"coordinates":[138.60435485799999,-34.9339637756],"type":"Point"}
}