{
  "type": "Feature",
  "properties": {
    "addr:full":"162 Mary St Gympie QLD 4570",
    "addr:housenumber":"162",
    "addr:postcode":"4570",
    "addr:street":"Mary St",
    "iso:country":"AU",
    "sg:address":"162 Mary St",
    "sg:city":"Gympie",
    "sg:classifiers":[
        {
            "category":"Shopping",
            "subcategory":"Clothing, Apparel, & Fashions",
            "type":"Retail Goods"
        }
    ],
    "sg:phone":"+61 7 5482 1668",
    "sg:postcode":"4570",
    "sg:province":"QLD",
    "sg:tags":[
        "lady",
        "wear"
    ],
    "wof:name":"Rockmans Stores Pty Limited",
    "wof:placetype":"venue"
},
  "geometry": {"coordinates":[152.660980225,-26.1897163391],"type":"Point"}
}