{
  "type": "Feature",
  "properties": {
    "addr:full":"Pack Rd Marysville VIC 3779",
    "addr:postcode":"3779",
    "addr:street":"Pack Rd",
    "iso:country":"AU",
    "sg:address":"Pack Rd",
    "sg:city":"Marysville",
    "sg:classifiers":[
        {
            "category":"Social Services",
            "subcategory":"Child Care",
            "type":"Services"
        }
    ],
    "sg:phone":"+61 3 5963 3330",
    "sg:postcode":"3779",
    "sg:province":"VIC",
    "sg:tags":[
        "support",
        "health"
    ],
    "wof:name":"Maternal & Child Health Centres",
    "wof:placetype":"venue"
},
  "geometry": {"coordinates":[145.747421,-37.510498],"type":"Point"}
}