{
  "type": "Feature",
  "properties": {
    "addr:full":"3rd Floor, A Block, QEII Medical Centre Verdun St Nedlands WA 6009",
    "addr:housenumber":"a",
    "addr:postcode":"6009",
    "addr:street":"Block Qeii;Verdun St",
    "iso:country":"AU",
    "sg:address":"3rd Floor, A Block, QEII Medical Centre Verdun St",
    "sg:city":"Nedlands",
    "sg:classifiers":[
        {
            "category":"Wholesale",
            "subcategory":"Medical Equipment & Supplies",
            "type":"Manufacturing & Wholesale Goods"
        }
    ],
    "sg:phone":"+61 8 9346 3071",
    "sg:postcode":"6009",
    "sg:province":"WA",
    "sg:tags":[
        "aids",
        "hearing"
    ],
    "wof:name":"Lions Ear And Hearing Institute",
    "wof:placetype":"venue"
},
  "geometry": {"coordinates":[115.807678,-31.967211],"type":"Point"}
}