{
  "type": "Feature",
  "properties": {
    "addr:full":"183 Brisbane St Dubbo NSW 2830",
    "addr:housenumber":"183",
    "addr:postcode":"2830",
    "addr:street":"Brisbane St",
    "iso:country":"AU",
    "sg:address":"183 Brisbane St",
    "sg:city":"Dubbo",
    "sg:classifiers":[
        {
            "category":"Health Services",
            "subcategory":"Doctor",
            "type":"Services"
        }
    ],
    "sg:phone":"+61 2 6882 4244",
    "sg:postcode":"2830",
    "sg:province":"NSW",
    "sg:tags":[
        "medical",
        "practitioner"
    ],
    "wof:name":"Prof Drew Fitzpatrick",
    "wof:placetype":"venue"
},
  "geometry": {"coordinates":[148.603057861,-32.2504348755],"type":"Point"}
}