{
  "type": "Feature",
  "properties": {
    "addr:full":"12 Lorraine Ave Marcoola Beach QLD 4564",
    "addr:housenumber":"12",
    "addr:postcode":"4564",
    "addr:street":"Lorraine Ave Marcoola",
    "iso:country":"AU",
    "sg:address":"12 Lorraine Ave",
    "sg:city":"Marcoola Beach",
    "sg:classifiers":[
        {
            "category":"Fast Food",
            "type":"Food & Drink"
        }
    ],
    "sg:phone":"+61 7 5448 7131",
    "sg:postcode":"4564",
    "sg:province":"QLD",
    "sg:tags":[
        "away",
        "take"
    ],
    "wof:name":"Marcoola Beach Takeaway",
    "wof:placetype":"venue"
},
  "geometry": {"coordinates":[153.095993042,-26.584280014],"type":"Point"}
}