{
  "type": "Feature",
  "properties": {
    "addr:full":"487- 489 Pacific Hwy Artarmon NSW 2064",
    "addr:housenumber":"489",
    "addr:postcode":"2064",
    "addr:street":"Pacific Hwy",
    "iso:country":"AU",
    "sg:address":"487- 489 Pacific Hwy",
    "sg:city":"Artarmon",
    "sg:classifiers":[
        {
            "category":"Autos & Motor Vehicles",
            "subcategory":"Auto Supplies",
            "type":"Retail Goods"
        }
    ],
    "sg:phone":"+61 2 9428 2900",
    "sg:postcode":"2064",
    "sg:province":"NSW",
    "sg:tags":[
        "tyre"
    ],
    "wof:name":"Bob Jane T-Marts",
    "wof:placetype":"venue"
},
  "geometry": {"coordinates":[151.17811584500001,-33.8097190857],"type":"Point"}
}