{
  "type": "Feature",
  "properties": {
    "iso:country":"AU",
    "sg:address":"Suite 4 28 Orlando St",
    "sg:city":"Coffs Harbour",
    "sg:classifiers":[
        {
            "category":"Insurance",
            "subcategory":"Insurance Agent",
            "type":"Services"
        }
    ],
    "sg:phone":"+61 2 6650 9208",
    "sg:postcode":"2450",
    "sg:province":"NSW",
    "sg:tags":[
        "broker"
    ],
    "wof:name":"Insurance Advisernet Australia Pty Limited",
    "wof:placetype":"venue"
},
  "geometry": {"coordinates":[153.136414,-30.296909],"type":"Point"}
}