{
  "type": "Feature",
  "properties": {
    "addr:full":"Suite 21 21- 25 Knox St Double Bay NSW 2028",
    "addr:housenumber":"21 25",
    "addr:postcode":"2028",
    "addr:street":"Knox St",
    "iso:country":"AU",
    "sg:address":"Suite 21 21- 25 Knox St",
    "sg:city":"Double Bay",
    "sg:classifiers":[
        {
            "category":"Banks & Credit Unions",
            "subcategory":"Financial Services",
            "type":"Services"
        }
    ],
    "sg:phone":"+61 2 9328 1120",
    "sg:postcode":"2028",
    "sg:province":"NSW",
    "sg:tags":[
        "financier"
    ],
    "wof:name":"SciCapitol Pty Ltd",
    "wof:placetype":"venue"
},
  "geometry": {"coordinates":[151.242553711,-33.8767852783],"type":"Point"}
}