{
  "type": "Feature",
  "properties": {
    "iso:country":"AU",
    "sg:address":"87 Macquarie St",
    "sg:city":"George Town",
    "sg:classifiers":[
        {
            "category":"Shopping",
            "subcategory":"Computers & Home Electronics",
            "type":"Retail Goods"
        }
    ],
    "sg:phone":"+61 3 6382 4885",
    "sg:postcode":"7253",
    "sg:province":"TAS",
    "sg:tags":[
        "hardware",
        "equipment"
    ],
    "wof:name":"Tassie Mart",
    "wof:placetype":"venue"
},
  "geometry": {"coordinates":[146.82554626500001,-41.1059455872],"type":"Point"}
}