{
  "type": "Feature",
  "properties": {
    "addr:full":"1 Leila St Prahran VIC 3181",
    "addr:housenumber":"1",
    "addr:postcode":"3181",
    "addr:street":"Leila St",
    "iso:country":"AU",
    "sg:address":"1 Leila St",
    "sg:city":"Prahran",
    "sg:classifiers":[
        {
            "category":"Health Services",
            "subcategory":"Doctor",
            "type":"Services"
        }
    ],
    "sg:phone":"+61 3 9529 5833",
    "sg:postcode":"3181",
    "sg:province":"VIC",
    "sg:tags":[
        "medical",
        "practitioner"
    ],
    "wof:name":"McCarthy P G",
    "wof:placetype":"venue"
},
  "geometry": {"coordinates":[144.99986267099999,-37.8499984741],"type":"Point"}
}