{
  "type": "Feature",
  "properties": {
    "addr:full":"113 Woodland St Balgowlah Heights NSW 2093",
    "addr:housenumber":"113",
    "addr:postcode":"2093",
    "addr:street":"Woodland St",
    "iso:country":"AU",
    "sg:address":"113 Woodland St",
    "sg:city":"Balgowlah Heights",
    "sg:classifiers":[
        {
            "category":"Professional",
            "subcategory":"Management & Consulting",
            "type":"Services"
        }
    ],
    "sg:phone":"+61 418 942 152",
    "sg:postcode":"2093",
    "sg:province":"NSW",
    "sg:tags":[
        "consultant"
    ],
    "wof:name":"Hull Daryll",
    "wof:placetype":"venue"
},
  "geometry": {"coordinates":[151.261276245,-33.800151825],"type":"Point"}
}