{
  "type": "Feature",
  "properties": {
    "iso:country":"AU",
    "sg:address":"145A Industrial Rd",
    "sg:city":"Oak Flats",
    "sg:classifiers":[
        {
            "category":"Building & Trades",
            "subcategory":"Construction",
            "type":"Services"
        }
    ],
    "sg:phone":"+61 2 4256 6622",
    "sg:postcode":"2529",
    "sg:province":"NSW",
    "sg:tags":[
        "concrete",
        "contractor"
    ],
    "wof:name":"Always Better Concreting",
    "wof:placetype":"venue"
},
  "geometry": {"coordinates":[150.80535888700001,-34.5653076172],"type":"Point"}
}