{
  "type": "Feature",
  "properties": {
    "addr:full":"24 Radford Rd Reservoir VIC 3073",
    "addr:housenumber":"24",
    "addr:postcode":"3073",
    "addr:street":"Radford Rd",
    "iso:country":"AU",
    "sg:address":"24 Radford Rd",
    "sg:city":"Reservoir",
    "sg:classifiers":[
        {
            "category":"Retail",
            "subcategory":"Auto Repair",
            "type":"Services"
        }
    ],
    "sg:phone":"+61 3 9469 3889",
    "sg:postcode":"3073",
    "sg:province":"VIC",
    "sg:tags":[
        "beater",
        "painter",
        "panel"
    ],
    "wof:name":"Mister Body Repairs",
    "wof:placetype":"venue"
},
  "geometry": {"coordinates":[144.982666016,-37.7109870911],"type":"Point"}
}