{
  "type": "Feature",
  "properties": {
    "addr:full":"3 Wahroonga Ave Wahroonga NSW 2076",
    "addr:housenumber":"3",
    "addr:postcode":"2076",
    "addr:street":"Wahroonga Ave",
    "iso:country":"AU",
    "sg:address":"3 Wahroonga Ave",
    "sg:city":"Wahroonga",
    "sg:classifiers":[
        {
            "category":"Health Services",
            "subcategory":"Doctor",
            "type":"Services"
        }
    ],
    "sg:phone":"+61 2 9487 1671",
    "sg:postcode":"2076",
    "sg:province":"NSW",
    "sg:tags":[
        "medical",
        "practitioner"
    ],
    "wof:name":"Gill J E M",
    "wof:placetype":"venue"
},
  "geometry": {"coordinates":[151.12623596200001,-33.7131729126],"type":"Point"}
}