{
  "type": "Feature",
  "properties": {
    "addr:full":"56a Clydesdale Ave Glenorchy TAS 7010",
    "addr:housenumber":"56a",
    "addr:postcode":"7010",
    "addr:street":"Clydesdale Ave",
    "iso:country":"AU",
    "sg:address":"56a Clydesdale Ave",
    "sg:city":"Glenorchy",
    "sg:classifiers":[
        {
            "category":"Home & Garden",
            "subcategory":"Garden Supply",
            "type":"Retail Goods"
        }
    ],
    "sg:phone":"+61 3 6272 9866",
    "sg:postcode":"7010",
    "sg:province":"TAS",
    "sg:tags":[
        "landscape"
    ],
    "wof:name":"Atkinson A.G. & Son Pty Ltd",
    "wof:placetype":"venue"
},
  "geometry": {"coordinates":[147.27618408199999,-42.8417358398],"type":"Point"}
}