{
  "type": "Feature",
  "properties": {
    "addr:full":"29 Mittabah Rd Hornsby NSW 2077",
    "addr:housenumber":"29",
    "addr:postcode":"2077",
    "addr:street":"Mittabah Rd",
    "iso:country":"AU",
    "sg:address":"29 Mittabah Rd",
    "sg:city":"Hornsby",
    "sg:classifiers":[
        {
            "category":"Professional",
            "subcategory":"Computer Services",
            "type":"Services"
        }
    ],
    "sg:phone":"+61 408 250 063",
    "sg:postcode":"2077",
    "sg:province":"NSW",
    "sg:tags":[
        "consultant",
        "system"
    ],
    "wof:name":"Zamofite Pty Ltd",
    "wof:placetype":"venue"
},
  "geometry": {"coordinates":[151.105194092,-33.6831092834],"type":"Point"}
}