{
  "type": "Feature",
  "properties": {
    "addr:full":"20 Hill St Richmond VIC 3121",
    "addr:housenumber":"20",
    "addr:postcode":"3121",
    "addr:street":"Hill St",
    "iso:country":"AU",
    "sg:address":"20 Hill St",
    "sg:city":"Richmond",
    "sg:classifiers":[
        {
            "category":"Farming",
            "subcategory":"Orchard",
            "type":"Manufacturing & Wholesale Goods"
        }
    ],
    "sg:phone":"+61 3 9428 7117",
    "sg:postcode":"3121",
    "sg:province":"VIC",
    "sg:tags":[
        "wholesaler",
        "jean",
        "mfrs"
    ],
    "wof:name":"Buffalo Jeans",
    "wof:placetype":"venue"
},
  "geometry": {"coordinates":[144.99623107900001,-37.8281097412],"type":"Point"}
}