{
  "type": "Feature",
  "properties": {
    "addr:full":"155 Crown St Wollongong NSW 2500",
    "addr:housenumber":"155",
    "addr:postcode":"2500",
    "addr:street":"Crown St",
    "iso:country":"AU",
    "sg:address":"155 Crown St",
    "sg:city":"Wollongong",
    "sg:classifiers":[
        {
            "category":"Travel",
            "subcategory":"Travel Agent",
            "type":"Entertainment"
        }
    ],
    "sg:phone":"+61 13 18 66",
    "sg:postcode":"2500",
    "sg:province":"NSW",
    "sg:tags":[
        "consultant"
    ],
    "wof:name":"Flight Centre",
    "wof:placetype":"venue"
},
  "geometry": {"coordinates":[150.898743,-34.425823],"type":"Point"}
}