{
  "type": "Feature",
  "properties": {
    "addr:full":"Ste901/ 1 Chandos St St Leonards NSW 2065",
    "addr:housenumber":"1",
    "addr:postcode":"2065",
    "addr:street":"Chandos St",
    "iso:country":"AU",
    "sg:address":"Ste901/ 1 Chandos St",
    "sg:city":"St Leonards",
    "sg:classifiers":[
        {
            "category":"Professional",
            "subcategory":"Computer Services",
            "type":"Services"
        }
    ],
    "sg:phone":"+61 2 9437 1100",
    "sg:postcode":"2065",
    "sg:province":"NSW",
    "sg:tags":[
        "consultant",
        "system"
    ],
    "wof:name":"Cubewise",
    "wof:placetype":"venue"
},
  "geometry": {"coordinates":[151.195755005,-33.8237457275],"type":"Point"}
}