{
  "type": "Feature",
  "properties": {
    "iso:country":"AU",
    "sg:address":"6 Sewell Street,",
    "sg:city":"Mont Albert North",
    "sg:classifiers":[
        {
            "category":"Professional",
            "subcategory":"Management & Consulting",
            "type":"Services"
        }
    ],
    "sg:phone":"+61 3 9890 2257",
    "sg:postcode":"3129",
    "sg:province":"VIC",
    "sg:tags":[
        "project"
    ],
    "wof:name":"Gerard Coutts Pty Ltd",
    "wof:placetype":"venue"
},
  "geometry": {"coordinates":[145.110473633,-37.7998313904],"type":"Point"}
}