{
  "type": "Feature",
  "properties": {
    "addr:full":"2/ 3 Trade St Ormiston QLD 4160",
    "addr:housenumber":"/ 3",
    "addr:postcode":"4160",
    "addr:street":"Trade St",
    "iso:country":"AU",
    "sg:address":"2/ 3 Trade St",
    "sg:city":"Ormiston",
    "sg:classifiers":[
        {
            "category":"Utilities",
            "subcategory":"Water",
            "type":"Services"
        }
    ],
    "sg:phone":"+61 7 3286 5557",
    "sg:postcode":"4160",
    "sg:province":"QLD",
    "sg:tags":[
        "equipment",
        "treatment"
    ],
    "wof:name":"Environmental Separator Maintenance",
    "wof:placetype":"venue"
},
  "geometry": {"coordinates":[153.25730895999999,-27.5216255188],"type":"Point"}
}