{
  "type": "Feature",
  "properties": {
    "iso:country":"AU",
    "sg:address":"6 Montrose Crt",
    "sg:city":"Sydenham",
    "sg:classifiers":[
        {
            "category":"Home & Garden",
            "subcategory":"Building Materials",
            "type":"Retail Goods"
        }
    ],
    "sg:phone":"+61 421 840 309",
    "sg:postcode":"3037",
    "sg:province":"VIC",
    "sg:tags":[
        "lawn",
        "cutting",
        "maintenance"
    ],
    "wof:name":"Western Property Maintenance",
    "wof:placetype":"venue"
},
  "geometry": {"coordinates":[144.758636,-37.692558],"type":"Point"}
}