{
  "type": "Feature",
  "properties": {
    "addr:full":"11 Fowler Rd Merrylands West NSW 2160",
    "addr:housenumber":"11",
    "addr:postcode":"2160",
    "addr:street":"Fowler Rd",
    "iso:country":"AU",
    "sg:address":"11 Fowler Rd",
    "sg:city":"Merrylands West",
    "sg:classifiers":[
        {
            "category":"Retail",
            "subcategory":"Auto Repair",
            "type":"Services"
        }
    ],
    "sg:phone":"+61 2 9897 3148",
    "sg:postcode":"2160",
    "sg:province":"NSW",
    "sg:tags":[
        "repairer",
        "motor",
        "engineer"
    ],
    "wof:name":"Whitey's Workshop",
    "wof:placetype":"venue"
},
  "geometry": {"coordinates":[150.97671508799999,-33.8349494934],"type":"Point"}
}