{
  "type": "Feature",
  "properties": {
    "addr:full":"152 Victoria Rd Lilydale VIC 3140",
    "addr:housenumber":"152",
    "addr:postcode":"3140",
    "addr:street":"Victoria Rd",
    "iso:country":"AU",
    "sg:address":"152 Victoria Rd",
    "sg:city":"Lilydale",
    "sg:classifiers":[
        {
            "category":"Building & Trades",
            "subcategory":"Construction",
            "type":"Services"
        }
    ],
    "sg:phone":"+61 3 9735 1924",
    "sg:postcode":"3140",
    "sg:province":"VIC",
    "sg:tags":[
        "contractor"
    ],
    "wof:name":"Nesway Contractors Pty Ltd",
    "wof:placetype":"venue"
},
  "geometry": {"coordinates":[145.33729553200001,-37.7449951172],"type":"Point"}
}