{
  "type": "Feature",
  "properties": {
    "iso:country":"AU",
    "sg:address":"96 Newcastle St",
    "sg:city":"Fyshwick",
    "sg:classifiers":[
        {
            "category":"Autos & Motor Vehicles",
            "subcategory":"Automobile Sales",
            "type":"Retail Goods"
        }
    ],
    "sg:phone":"+61 2 6280 5600",
    "sg:postcode":"2609",
    "sg:province":"ACT",
    "sg:tags":[
        "car",
        "used"
    ],
    "sg:website":"http://www.endeavourmotors.com.au",
    "wof:name":"Endeavour Motors",
    "wof:placetype":"venue"
},
  "geometry": {"coordinates":[149.183792114,-35.3259887695],"type":"Point"}
}