{
  "type": "Feature",
  "properties": {
    "iso:country":"AU",
    "sg:address":"Cnr Newnham & Wishart Rds",
    "sg:city":"Wishart",
    "sg:classifiers":[
        {
            "category":"Health Services",
            "subcategory":"Health Practitioner",
            "type":"Services"
        }
    ],
    "sg:phone":"+61 7 3849 3099",
    "sg:postcode":"4122",
    "sg:province":"QLD",
    "sg:tags":[
        "physiotherapist"
    ],
    "sg:website":"http://www.physiotherapy.asn.au",
    "wof:name":"Mansfield PhysioWorks",
    "wof:placetype":"venue"
},
  "geometry": {"coordinates":[153.09031677199999,-27.5550174713],"type":"Point"}
}