{
  "type": "Feature",
  "properties": {
    "iso:country":"AU",
    "sg:address":"Alma St",
    "sg:city":"Burren Junction",
    "sg:classifiers":[
        {
            "category":"Education",
            "subcategory":"School",
            "type":"Public Place"
        }
    ],
    "sg:phone":"+61 2 6796 1464",
    "sg:postcode":"2386",
    "sg:province":"NSW",
    "sg:tags":[
        "state",
        "-",
        "nsw"
    ],
    "wof:name":"Burren Junction",
    "wof:placetype":"venue"
},
  "geometry": {"coordinates":[148.96975707999999,-30.1039924622],"type":"Point"}
}