{
  "type": "Feature",
  "properties": {
    "addr:full":"17 Plantation St Mildura VIC 3500",
    "addr:housenumber":"17",
    "addr:postcode":"3500",
    "addr:street":"Plantation St",
    "iso:country":"AU",
    "sg:address":"17 Plantation St",
    "sg:city":"Mildura",
    "sg:classifiers":[
        {
            "category":"Building & Trades",
            "subcategory":"Construction",
            "type":"Services"
        }
    ],
    "sg:phone":"+61 3 5021 5228",
    "sg:postcode":"3500",
    "sg:province":"VIC",
    "sg:tags":[
        "contractor"
    ],
    "wof:name":"Jeff Muller Homes",
    "wof:placetype":"venue"
},
  "geometry": {"coordinates":[142.134674072,-34.2026901245],"type":"Point"}
}