{
  "type": "Feature",
  "properties": {
    "iso:country":"AU",
    "sg:address":"6/ 1 Acacia St",
    "sg:city":"Yarrawonga",
    "sg:classifiers":[
        {
            "category":"Retail",
            "subcategory":"Auto Repair",
            "type":"Services"
        }
    ],
    "sg:phone":"+61 3 5743 3223",
    "sg:postcode":"3730",
    "sg:province":"VIC",
    "sg:tags":[
        "repairer",
        "motor",
        "engineer"
    ],
    "wof:name":"R.A.C.E Autos",
    "wof:placetype":"venue"
},
  "geometry": {"coordinates":[145.99842834500001,-36.0265197754],"type":"Point"}
}