{
  "type": "Feature",
  "properties": {
    "addr:full":"Macquarie St Hawkesbury NSW 2777",
    "addr:postcode":"2777",
    "addr:street":"Macquarie St",
    "iso:country":"AU",
    "sg:address":"Macquarie St",
    "sg:city":"Hawkesbury",
    "sg:classifiers":[
        {
            "category":"Professional",
            "subcategory":"Computer Services",
            "type":"Services"
        }
    ],
    "sg:phone":"+61 1300 661 099",
    "sg:postcode":"2777",
    "sg:province":"NSW",
    "sg:tags":[
        "repairs",
        "upgrade",
        "equipment"
    ],
    "wof:name":"Computer Troubleshooters",
    "wof:placetype":"venue"
},
  "geometry": {"coordinates":[150.57484435999999,-33.7031745911],"type":"Point"}
}