{
  "type": "Feature",
  "properties": {
    "addr:full":"11 Holdway St Kenmore QLD 4069",
    "addr:housenumber":"11",
    "addr:postcode":"4069",
    "addr:street":"Holdway St",
    "iso:country":"AU",
    "sg:address":"11 Holdway St",
    "sg:city":"Kenmore",
    "sg:classifiers":[
        {
            "category":"Professional",
            "subcategory":"Art Services",
            "type":"Services"
        }
    ],
    "sg:phone":"+61 411 325 283",
    "sg:postcode":"4069",
    "sg:province":"QLD",
    "sg:tags":[
        "decorator",
        "painter"
    ],
    "wof:name":"Clayton & Cosier Painters Pty Ltd",
    "wof:placetype":"venue"
},
  "geometry": {"coordinates":[152.94578552199999,-27.5124053955],"type":"Point"}
}