{
  "type": "Feature",
  "properties": {
    "addr:full":"22 Toogood Rd Woree QLD 4868",
    "addr:housenumber":"22",
    "addr:postcode":"4868",
    "addr:street":"Toogood Rd",
    "iso:country":"AU",
    "sg:address":"22 Toogood Rd",
    "sg:city":"Woree",
    "sg:classifiers":[
        {
            "category":"Food & Beverages",
            "subcategory":"Liquor & Beverages",
            "type":"Retail Goods"
        }
    ],
    "sg:phone":"+61 7 4033 0671",
    "sg:postcode":"4868",
    "sg:province":"QLD",
    "sg:tags":[
        "store"
    ],
    "wof:name":"Woree Bottleshop",
    "wof:placetype":"venue"
},
  "geometry": {"coordinates":[145.742675781,-16.953496933],"type":"Point"}
}