{
  "type": "Feature",
  "properties": {
    "addr:full":"Foster St Niangala NSW 2354",
    "addr:postcode":"2354",
    "addr:street":"Foster St",
    "iso:country":"AU",
    "sg:address":"Foster St",
    "sg:city":"Niangala",
    "sg:classifiers":[
        {
            "category":"Education",
            "subcategory":"School",
            "type":"Public Place"
        }
    ],
    "sg:phone":"+61 2 6769 2254",
    "sg:postcode":"2354",
    "sg:province":"NSW",
    "sg:tags":[
        "state",
        "-",
        "nsw"
    ],
    "wof:name":"Niangala Public School",
    "wof:placetype":"venue"
},
  "geometry": {"coordinates":[151.408035278,-31.2976131439],"type":"Point"}
}