{
  "type": "Feature",
  "properties": {
    "iso:country":"AU",
    "sg:address":"2 Boat Harbour Drv",
    "sg:city":"Hervey Bay",
    "sg:classifiers":[
        {
            "category":"Autos & Motor Vehicles",
            "subcategory":"Automobile Sales",
            "type":"Retail Goods"
        }
    ],
    "sg:phone":"+61 7 4125 9977",
    "sg:postcode":"4655",
    "sg:province":"QLD",
    "sg:tags":[
        "car",
        "new"
    ],
    "wof:name":"Tarrants Hyundai",
    "wof:placetype":"venue"
},
  "geometry": {"coordinates":[152.819031,-25.285404],"type":"Point"}
}