{
  "type": "Feature",
  "properties": {
    "addr:full":"406 Burke Rd Camberwell VIC 3124",
    "addr:housenumber":"406",
    "addr:postcode":"3124",
    "addr:street":"Burke Rd",
    "iso:country":"AU",
    "sg:address":"406 Burke Rd",
    "sg:city":"Camberwell",
    "sg:classifiers":[
        {
            "category":"Arts & Performance",
            "subcategory":"Art Gallery",
            "type":"Entertainment"
        }
    ],
    "sg:phone":"+61 3 9809 0060",
    "sg:postcode":"3124",
    "sg:province":"VIC",
    "wof:name":"Martin Gallon Fine Art Pty Ltd",
    "wof:placetype":"venue"
},
  "geometry": {"coordinates":[145.054229736,-37.8452033997],"type":"Point"}
}