{
  "type": "Feature",
  "properties": {
    "addr:full":"1308 Sandgate Rd Nundah QLD 4012",
    "addr:housenumber":"1308",
    "addr:postcode":"4012",
    "addr:street":"Sandgate Rd",
    "iso:country":"AU",
    "sg:address":"1308 Sandgate Rd",
    "sg:city":"Nundah",
    "sg:classifiers":[
        {
            "category":"Autos & Motor Vehicles",
            "subcategory":"Automobile Sales",
            "type":"Retail Goods"
        }
    ],
    "sg:phone":"+61 7 3635 5100",
    "sg:postcode":"4012",
    "sg:province":"QLD",
    "sg:tags":[
        "car",
        "new"
    ],
    "wof:name":"Norris Motor Group Honda, Mitsubishi",
    "wof:placetype":"venue"
},
  "geometry": {"coordinates":[153.05856323200001,-27.4001903534],"type":"Point"}
}