{
  "type": "Feature",
  "properties": {
    "addr:full":"14 Sanderling Crt Rosebud West VIC 3940",
    "addr:housenumber":"14",
    "addr:postcode":"3940",
    "addr:street":"Sanderling Crt",
    "iso:country":"AU",
    "sg:address":"14 Sanderling Crt",
    "sg:city":"Rosebud West",
    "sg:classifiers":[
        {
            "category":"Health Services",
            "subcategory":"Medical Lab",
            "type":"Services"
        }
    ],
    "sg:phone":"+61 3 5986 3377",
    "sg:postcode":"3940",
    "sg:province":"VIC",
    "sg:tags":[
        "laboratory",
        "dental"
    ],
    "wof:name":"Rosebud Dental Laboratory",
    "wof:placetype":"venue"
},
  "geometry": {"coordinates":[144.882522583,-38.3768806458],"type":"Point"}
}