{
  "type": "Feature",
  "properties": {
    "addr:full":"Cnr Ilford Rd & Lloyd Ave Kandos NSW 2848",
    "addr:postcode":"2848",
    "addr:street":"Cnr Ilford Rd & Lloyd Ave",
    "iso:country":"AU",
    "sg:address":"Cnr Ilford Rd & Lloyd Ave",
    "sg:city":"Kandos",
    "sg:classifiers":[
        {
            "category":"Social Services",
            "subcategory":"Adult Care",
            "type":"Services"
        }
    ],
    "sg:phone":"+61 429 794 381",
    "sg:postcode":"2848",
    "sg:province":"NSW",
    "sg:tags":[
        "towing"
    ],
    "wof:name":"Lewis Towing & Repairs",
    "wof:placetype":"venue"
},
  "geometry": {"coordinates":[149.96972700000001,-32.85603],"type":"Point"}
}