{
  "type": "Feature",
  "properties": {
    "addr:full":"172 Jones Rd Bellbird Park QLD 4300",
    "addr:housenumber":"172",
    "addr:postcode":"4300",
    "addr:street":"Jones Rd",
    "iso:country":"AU",
    "sg:address":"172 Jones Rd",
    "sg:city":"Bellbird Park",
    "sg:classifiers":[
        {
            "category":"Utilities",
            "subcategory":"Telephone",
            "type":"Services"
        }
    ],
    "sg:phone":"+61 7 3818 1848",
    "sg:postcode":"4300",
    "sg:province":"QLD",
    "sg:tags":[
        "installation",
        "system",
        "maintenance"
    ],
    "wof:name":"Buz-Com",
    "wof:placetype":"venue"
},
  "geometry": {"coordinates":[152.8828125,-27.6380691528],"type":"Point"}
}