{
  "type": "Feature",
  "properties": {
    "addr:full":"19- 21 Saywell Rd Macquarie Fields NSW 2564",
    "addr:housenumber":"21",
    "addr:postcode":"2564",
    "addr:street":"Saywell Rd",
    "iso:country":"AU",
    "sg:address":"19- 21 Saywell Rd",
    "sg:city":"Macquarie Fields",
    "sg:classifiers":[
        {
            "category":"Social Services",
            "subcategory":"Child Care",
            "type":"Services"
        }
    ],
    "sg:phone":"+61 2 9618 1467",
    "sg:postcode":"2564",
    "sg:province":"NSW",
    "wof:name":"Little Learners Academy",
    "wof:placetype":"venue"
},
  "geometry": {"coordinates":[150.88783264200001,-33.9932365417],"type":"Point"}
}