{
  "type": "Feature",
  "properties": {
    "addr:full":"73 Cowper St Wallsend NSW 2287",
    "addr:housenumber":"73",
    "addr:postcode":"2287",
    "addr:street":"Cowper St",
    "iso:country":"AU",
    "sg:address":"73 Cowper St",
    "sg:city":"Wallsend",
    "sg:classifiers":[
        {
            "category":"Manufacturing",
            "subcategory":"Motor Vehicles & Parts",
            "type":"Manufacturing & Wholesale Goods"
        }
    ],
    "sg:phone":"+61 2 4955 0047",
    "sg:postcode":"2287",
    "sg:province":"NSW",
    "sg:tags":[
        "wholesaler",
        "cycle",
        "mfrs",
        "accessory"
    ],
    "wof:name":"Hole Shot",
    "wof:placetype":"venue"
},
  "geometry": {"coordinates":[151.67022705100001,-32.9029541016],"type":"Point"}
}