{
  "type": "Feature",
  "properties": {
    "addr:full":"Murarrie Rd Murarrie QLD 4172",
    "addr:postcode":"4172",
    "addr:street":"Murarrie Rd",
    "iso:country":"AU",
    "sg:address":"Murarrie Rd",
    "sg:city":"Murarrie",
    "sg:classifiers":[
        {
            "category":"Retail",
            "subcategory":"Auto Repair",
            "type":"Services"
        }
    ],
    "sg:phone":"+61 7 3390 6424",
    "sg:postcode":"4172",
    "sg:province":"QLD",
    "sg:tags":[
        "body",
        "builder",
        "motor"
    ],
    "wof:name":"Queensland Aluminium Van Repairs",
    "wof:placetype":"venue"
},
  "geometry": {"coordinates":[153.10179138199999,-27.4652404785],"type":"Point"}
}