{
  "type": "Feature",
  "properties": {
    "iso:country":"AU",
    "sg:address":"Shed 1, 80- 84 Tucker St",
    "sg:city":"Breakwater",
    "sg:classifiers":[
        {
            "category":"Building & Trades",
            "subcategory":"Construction",
            "type":"Services"
        }
    ],
    "sg:phone":"+61 402 092 756",
    "sg:postcode":"3219",
    "sg:province":"VIC",
    "sg:tags":[
        "rendering",
        "cement"
    ],
    "wof:name":"ART Renovations",
    "wof:placetype":"venue"
},
  "geometry": {"coordinates":[144.366424561,-38.1834373474],"type":"Point"}
}