{
  "type": "Feature",
  "properties": {
    "addr:full":"99 Imveroona Rd Bowen QLD 4805",
    "addr:housenumber":"99",
    "addr:postcode":"4805",
    "addr:street":"Imveroona Rd",
    "iso:country":"AU",
    "sg:address":"99 Imveroona Rd",
    "sg:city":"Bowen",
    "sg:classifiers":[
        {
            "category":"Building & Trades",
            "subcategory":"Construction",
            "type":"Services"
        }
    ],
    "sg:phone":"+61 408 182 526",
    "sg:postcode":"4805",
    "sg:province":"QLD",
    "sg:tags":[
        "earth",
        "excavating",
        "moving",
        "contractor"
    ],
    "wof:name":"Graham Waters Backhoe Hire",
    "wof:placetype":"venue"
},
  "geometry": {"coordinates":[148.219573975,-19.9865016937],"type":"Point"}
}