{
  "type": "Feature",
  "properties": {
    "addr:full":"364 Gilston Rd Gilston QLD 4211",
    "addr:housenumber":"364",
    "addr:postcode":"4211",
    "addr:street":"Gilston Rd",
    "iso:country":"AU",
    "sg:address":"364 Gilston Rd",
    "sg:city":"Gilston",
    "sg:classifiers":[
        {
            "category":"Sports & Exercise",
            "subcategory":"Golf",
            "type":"Entertainment"
        }
    ],
    "sg:phone":"+61 7 5596 0400",
    "sg:postcode":"4211",
    "sg:province":"QLD",
    "sg:tags":[
        "club"
    ],
    "wof:name":"Grand Golf Club Ltd",
    "wof:placetype":"venue"
},
  "geometry": {"coordinates":[153.31179809599999,-28.0175533295],"type":"Point"}
}