{
  "type": "Feature",
  "properties": {
    "addr:full":"21 Winbourne Rd Mt Waverley VIC 3149",
    "addr:housenumber":"21",
    "addr:postcode":"3149",
    "addr:street":"Winbourne Rd",
    "iso:country":"AU",
    "sg:address":"21 Winbourne Rd",
    "sg:city":"Mt Waverley",
    "sg:classifiers":[
        {
            "category":"Professional",
            "subcategory":"Accounting & Tax Preparation",
            "type":"Services"
        }
    ],
    "sg:phone":"+61 3 9807 1695",
    "sg:postcode":"3149",
    "sg:province":"VIC",
    "sg:tags":[
        "accountant",
        "auditor"
    ],
    "wof:name":"Sutton G L",
    "wof:placetype":"venue"
},
  "geometry": {"coordinates":[145.122116089,-37.876411438],"type":"Point"}
}