{
  "type": "Feature",
  "properties": {
    "addr:full":"3 Jacinta Ave Beecroft NSW 2119",
    "addr:housenumber":"3",
    "addr:postcode":"2119",
    "addr:street":"Jacinta Ave",
    "iso:country":"AU",
    "sg:address":"3 Jacinta Ave",
    "sg:city":"Beecroft",
    "sg:classifiers":[
        {
            "category":"Professional",
            "subcategory":"Engineering",
            "type":"Services"
        }
    ],
    "sg:phone":"+61 2 9484 7166",
    "sg:postcode":"2119",
    "sg:province":"NSW",
    "sg:tags":[
        "consulting",
        "engineer"
    ],
    "wof:name":"Kingsleen Pty Ltd",
    "wof:placetype":"venue"
},
  "geometry": {"coordinates":[151.06112670900001,-33.7451095581],"type":"Point"}
}