{
  "type": "Feature",
  "properties": {
    "iso:country":"AU",
    "sg:address":"Cnr Ryrie & Swanston Sts",
    "sg:city":"Geelong",
    "sg:classifiers":[
        {
            "category":"Food & Beverages",
            "subcategory":"Groceries & Convenience Stores",
            "type":"Retail Goods"
        }
    ],
    "sg:phone":"+61 3 5223 1259",
    "sg:postcode":"3220",
    "sg:province":"VIC",
    "wof:name":"7-Eleven Stores Pty Ltd",
    "wof:placetype":"venue"
},
  "geometry": {"coordinates":[144.367523,-38.151791],"type":"Point"}
}