{
  "type": "Feature",
  "properties": {
    "addr:full":"25 Deborah St Bendigo VIC 3550",
    "addr:housenumber":"25",
    "addr:postcode":"3550",
    "addr:street":"Deborah St",
    "iso:country":"AU",
    "sg:address":"25 Deborah St",
    "sg:city":"Bendigo",
    "sg:classifiers":[
        {
            "category":"Building & Trades",
            "subcategory":"Construction",
            "type":"Services"
        }
    ],
    "sg:phone":"+61 3 5443 1411",
    "sg:postcode":"3550",
    "sg:province":"VIC",
    "sg:tags":[
        "contractor"
    ],
    "sg:website":"http://www.moreyandhurford.com.au",
    "wof:name":"Morey & Hurford Pty Ltd",
    "wof:placetype":"venue"
},
  "geometry": {"coordinates":[144.272613525,-36.7751121521],"type":"Point"}
}