{
  "type": "Feature",
  "properties": {
    "iso:country":"AU",
    "sg:address":"Unit 35/ 7 Anella Ave",
    "sg:city":"Castle Hill",
    "sg:classifiers":[
        {
            "category":"Professional",
            "subcategory":"Engineering",
            "type":"Services"
        }
    ],
    "sg:phone":"+61 2 9634 6311",
    "sg:postcode":"2154",
    "sg:province":"NSW",
    "sg:tags":[
        "civil",
        "engineer"
    ],
    "wof:name":"Appleyard Forrest Consulting Engineers Pty Ltd",
    "wof:placetype":"venue"
},
  "geometry": {"coordinates":[150.97848510700001,-33.7265663147],"type":"Point"}
}