{
  "type": "Feature",
  "properties": {
    "addr:full":"South Western Hwy Benger WA 6223",
    "addr:postcode":"6223",
    "addr:street":"South Western Hwy",
    "iso:country":"AU",
    "sg:address":"South Western Hwy",
    "sg:city":"Benger",
    "sg:classifiers":[
        {
            "category":"Farming",
            "subcategory":"Farm",
            "type":"Manufacturing & Wholesale Goods"
        }
    ],
    "sg:phone":"+61 8 9726 9268",
    "sg:postcode":"6223",
    "sg:province":"WA",
    "sg:tags":[
        "farmer"
    ],
    "wof:name":"Tartaglia G & G",
    "wof:placetype":"venue"
},
  "geometry": {"coordinates":[115.860558,-33.180424],"type":"Point"}
}