{
  "type": "Feature",
  "properties": {
    "addr:full":"2 Rutherford Rd Seaford VIC 3198",
    "addr:housenumber":"2",
    "addr:postcode":"3198",
    "addr:street":"Rutherford Rd",
    "iso:country":"AU",
    "sg:address":"2 Rutherford Rd",
    "sg:city":"Seaford",
    "sg:classifiers":[
        {
            "category":"Structure",
            "subcategory":"Office Building",
            "type":"Public Place"
        }
    ],
    "sg:phone":"+61 3 9775 0655",
    "sg:postcode":"3198",
    "sg:province":"VIC",
    "sg:tags":[
        "tie",
        "concrete",
        "formwork",
        "form",
        "accessory"
    ],
    "wof:name":"S & J Formwork Pty Ltd",
    "wof:placetype":"venue"
},
  "geometry": {"coordinates":[145.151687622,-38.0990982056],"type":"Point"}
}