{
  "type": "Feature",
  "properties": {
    "addr:full":"12 Breene Pl Morningside QLD 4170",
    "addr:housenumber":"12",
    "addr:postcode":"4170",
    "addr:street":"Breene Pl",
    "iso:country":"AU",
    "sg:address":"12 Breene Pl",
    "sg:city":"Morningside",
    "sg:classifiers":[
        {
            "category":"Farming",
            "subcategory":"Fish & Marine Products",
            "type":"Manufacturing & Wholesale Goods"
        }
    ],
    "sg:phone":"+61 7 3906 3501",
    "sg:postcode":"4170",
    "sg:province":"QLD",
    "sg:tags":[
        "wire"
    ],
    "wof:name":"J & G Trading Pty Ltd",
    "wof:placetype":"venue"
},
  "geometry": {"coordinates":[153.08514404300001,-27.4576301575],"type":"Point"}
}