{
  "type": "Feature",
  "properties": {
    "addr:full":"275 Ocean Drv Bunbury WA 6230",
    "addr:housenumber":"275",
    "addr:postcode":"6230",
    "addr:street":"Ocean Drv",
    "iso:country":"AU",
    "sg:address":"275 Ocean Drv",
    "sg:city":"Bunbury",
    "sg:classifiers":[
        {
            "category":"Professional",
            "subcategory":"Employment Agencies",
            "type":"Services"
        }
    ],
    "sg:phone":"+61 412 450 827",
    "sg:postcode":"6230",
    "sg:province":"WA",
    "sg:tags":[
        "provider",
        "internet"
    ],
    "wof:name":"W.W.W.Pages",
    "wof:placetype":"venue"
},
  "geometry": {"coordinates":[115.62576300000001,-33.369854],"type":"Point"}
}