{
  "type": "Feature",
  "properties": {
    "iso:country":"AU",
    "sg:address":"Unit 5/ 355 Brighton Rd",
    "sg:city":"Hove",
    "sg:classifiers":[
        {
            "category":"Shopping",
            "subcategory":"Crafts & Fabrics",
            "type":"Retail Goods"
        }
    ],
    "sg:phone":"+61 8 8298 3911",
    "sg:postcode":"5048",
    "sg:province":"SA",
    "sg:tags":[
        "upholstering",
        "supply"
    ],
    "wof:name":"Kinch Trading Pty Ltd",
    "wof:placetype":"venue"
},
  "geometry": {"coordinates":[138.522186,-35.009029],"type":"Point"}
}