{
  "type": "Feature",
  "properties": {
    "addr:full":"51 Nimmo St Essendon VIC 3040",
    "addr:housenumber":"51",
    "addr:postcode":"3040",
    "addr:street":"Nimmo St",
    "iso:country":"AU",
    "sg:address":"51 Nimmo St",
    "sg:city":"Essendon",
    "sg:classifiers":[
        {
            "category":"Utilities",
            "subcategory":"Electric",
            "type":"Services"
        }
    ],
    "sg:phone":"+61 3 9331 0985",
    "sg:postcode":"3040",
    "sg:province":"VIC",
    "sg:tags":[
        "electrical",
        "contractor"
    ],
    "wof:name":"Complete Electrical Pty Ltd",
    "wof:placetype":"venue"
},
  "geometry": {"coordinates":[144.89593505900001,-37.749332428],"type":"Point"}
}