{
  "type": "Feature",
  "properties": {
    "iso:country":"AU",
    "sg:address":"28 Avondale St",
    "sg:city":"Hampton",
    "sg:classifiers":[
        {
            "category":"Professional",
            "subcategory":"Accounting & Tax Preparation",
            "type":"Services"
        }
    ],
    "sg:phone":"+61 425 782 590",
    "sg:postcode":"3188",
    "sg:province":"VIC",
    "sg:tags":[
        "bookkeeping"
    ],
    "wof:name":"Bookkeeping By the Bay",
    "wof:placetype":"venue"
},
  "geometry": {"coordinates":[145.00250244099999,-37.9317817688],"type":"Point"}
}