{
  "type": "Feature",
  "properties": {
    "iso:country":"AU",
    "sg:address":"23 Mackays Rd",
    "sg:city":"Coffs Harbour",
    "sg:classifiers":[
        {
            "category":"Banks & Credit Unions",
            "subcategory":"Financial Services",
            "type":"Services"
        }
    ],
    "sg:phone":"+61 1300 558 517",
    "sg:postcode":"2450",
    "sg:province":"NSW",
    "sg:tags":[
        "loan",
        "finance",
        "mortgage"
    ],
    "wof:name":"anythingmoney.com",
    "wof:placetype":"venue"
},
  "geometry": {"coordinates":[153.10351600000001,-30.280561],"type":"Point"}
}