{
  "type": "Feature",
  "properties": {
    "addr:full":"35 Smith St Fitzroy VIC 3065",
    "addr:housenumber":"35",
    "addr:postcode":"3065",
    "addr:street":"Smith St",
    "iso:country":"AU",
    "sg:address":"35 Smith St",
    "sg:city":"Fitzroy",
    "sg:classifiers":[
        {
            "category":"Organizations",
            "subcategory":"Professional Association",
            "type":"Services"
        }
    ],
    "sg:phone":"+61 3 9416 0899",
    "sg:postcode":"3065",
    "sg:province":"VIC",
    "sg:tags":[
        "organisation",
        "business"
    ],
    "wof:name":"Victorian Alcohol & Drug Association (VAADA)",
    "wof:placetype":"venue"
},
  "geometry": {"coordinates":[144.98263549800001,-37.8074684143],"type":"Point"}
}