{
  "type": "Feature",
  "properties": {
    "addr:full":"442 Auburn Rd (Suites 2521-2523, The Uni Of Melbou Hawthorn VIC 3122",
    "addr:housenumber":"442",
    "addr:postcode":"2521-2523;3122",
    "addr:street":"Auburn Rd",
    "iso:country":"AU",
    "sg:address":"442 Auburn Rd (Suites 2521-2523, The Uni Of Melbou",
    "sg:city":"Hawthorn",
    "sg:classifiers":[
        {
            "category":"Education",
            "subcategory":"Special Training",
            "type":"Public Place"
        }
    ],
    "sg:phone":"+61 1300 296 633",
    "sg:postcode":"3122",
    "sg:province":"VIC",
    "sg:tags":[
        "tuition-educational"
    ],
    "wof:name":"Axon Education Centres",
    "wof:placetype":"venue"
},
  "geometry": {"coordinates":[145.04200744600001,-37.8379402161],"type":"Point"}
}