{
  "type": "Feature",
  "properties": {
    "iso:country":"AU",
    "sg:address":"204 Melbourne St",
    "sg:city":"North Adelaide",
    "sg:classifiers":[
        {
            "category":"Professional",
            "subcategory":"Accounting & Tax Preparation",
            "type":"Services"
        }
    ],
    "sg:phone":"+61 8 8267 5666",
    "sg:postcode":"5006",
    "sg:province":"SA",
    "sg:tags":[
        "accountant",
        "auditor"
    ],
    "wof:name":"SP Accountants & Business Advisors",
    "wof:placetype":"venue"
},
  "geometry": {"coordinates":[138.604446411,-34.9084968567],"type":"Point"}
}