{
  "type": "Feature",
  "properties": {
    "iso:country":"AU",
    "sg:address":"5 Fairbridge Crs",
    "sg:city":"Ainslie",
    "sg:classifiers":[
        {
            "category":"Retail",
            "subcategory":"Auto Repair",
            "type":"Services"
        }
    ],
    "sg:phone":"+61 2 6248 8096",
    "sg:postcode":"2602",
    "sg:province":"ACT",
    "sg:tags":[
        "repairer",
        "motor",
        "engineer"
    ],
    "wof:name":"J G's Automotive Services",
    "wof:placetype":"venue"
},
  "geometry": {"coordinates":[149.14654540999999,-35.2622108459],"type":"Point"}
}