{
  "type": "Feature",
  "properties": {
    "iso:country":"AU",
    "sg:address":"85 Mason St",
    "sg:city":"Campbellfield",
    "sg:classifiers":[
        {
            "category":"Manufacturing",
            "subcategory":"Metals",
            "type":"Manufacturing & Wholesale Goods"
        }
    ],
    "sg:phone":"+61 3 9357 7151",
    "sg:postcode":"3061",
    "sg:province":"VIC",
    "sg:tags":[
        "sheet",
        "worker"
    ],
    "wof:name":"TIGIT",
    "wof:placetype":"venue"
},
  "geometry": {"coordinates":[144.967407227,-37.6685447693],"type":"Point"}
}