{
  "type": "Feature",
  "properties": {
    "addr:full":"3/28- 30 Eurora St Kingston QLD 4114",
    "addr:housenumber":"/;30",
    "addr:postcode":"4114",
    "addr:street":"28;St",
    "iso:country":"AU",
    "sg:address":"3/28- 30 Eurora St",
    "sg:city":"Kingston",
    "sg:classifiers":[
        {
            "category":"Manufacturing",
            "subcategory":"Glass & Minerals",
            "type":"Manufacturing & Wholesale Goods"
        }
    ],
    "sg:phone":"+61 7 3208 7283",
    "sg:postcode":"4114",
    "sg:province":"QLD",
    "sg:tags":[
        "mfrg",
        "processing"
    ],
    "wof:name":"Hypersonic Glass Pty Ltd",
    "wof:placetype":"venue"
},
  "geometry": {"coordinates":[153.11778259299999,-27.6648139954],"type":"Point"}
}