{
  "type": "Feature",
  "properties": {
    "addr:full":"Shop 22, Centre Arcade 3131 Gold Coast QLD 4217",
    "addr:housenumber":"shop 22 centre;3131",
    "addr:postcode":"4217",
    "addr:street":"Arcade",
    "iso:country":"AU",
    "sg:address":"Shop 22, Centre Arcade 3131",
    "sg:city":"Gold Coast",
    "sg:classifiers":[
        {
            "category":"Banks & Credit Unions",
            "subcategory":"Bureau De Change",
            "type":"Services"
        }
    ],
    "sg:phone":"+61 7 5538 2995",
    "sg:postcode":"4217",
    "sg:province":"QLD",
    "sg:tags":[
        "currency",
        "exchange",
        "foreign"
    ],
    "wof:name":"UAE Exchange Australia Pty Ltd",
    "wof:placetype":"venue"
},
  "geometry": {"coordinates":[153.42953491200001,-28.0110912323],"type":"Point"}
}