{
  "type": "Feature",
  "properties": {
    "addr:full":"U3/ 235 Mona Vale Rd St Ives NSW 2075",
    "addr:housenumber":"235",
    "addr:postcode":"2075",
    "addr:street":"U3 /;Mona Vale Rd",
    "iso:country":"AU",
    "sg:address":"U3/ 235 Mona Vale Rd St",
    "sg:city":"Ives",
    "sg:classifiers":[
        {
            "category":"Sports & Exercise",
            "subcategory":"Gym",
            "type":"Entertainment"
        }
    ],
    "sg:phone":"+61 2 9440 0000",
    "sg:postcode":"2075",
    "sg:province":"NSW",
    "sg:tags":[
        "health",
        "fitness"
    ],
    "wof:name":"Contours Express St Ives",
    "wof:placetype":"venue"
},
  "geometry": {"coordinates":[151.16180419899999,-33.7297935486],"type":"Point"}
}