{
  "type": "Feature",
  "properties": {
    "iso:country":"AU",
    "sg:address":"PO Box 196",
    "sg:city":"Wurtulla",
    "sg:classifiers":[
        {
            "category":"Utilities",
            "subcategory":"Refuse",
            "type":"Services"
        }
    ],
    "sg:phone":"+61 411 816 311",
    "sg:postcode":"4575",
    "sg:province":"QLD",
    "sg:tags":[
        "remover",
        "rubbish"
    ],
    "wof:name":"All Areas Palm Tree Lopping",
    "wof:placetype":"venue"
},
  "geometry": {"coordinates":[153.124146,-26.760639],"type":"Point"}
}