{
  "type": "Feature",
  "properties": {
    "iso:country":"AU",
    "sg:address":"2 Crana St St",
    "sg:city":"Marys",
    "sg:classifiers":[
        {
            "category":"Health Services",
            "subcategory":"Health Practitioner",
            "type":"Services"
        }
    ],
    "sg:phone":"+61 2 9673 3733",
    "sg:postcode":"2760",
    "sg:province":"NSW",
    "sg:tags":[
        "naturopath"
    ],
    "wof:name":"St Marys Naturopathic Centre+",
    "wof:placetype":"venue"
},
  "geometry": {"coordinates":[150.77366638199999,-33.7674102783],"type":"Point"}
}