{
  "type": "Feature",
  "properties": {
    "addr:full":"64 George St Bundaberg QLD 4670",
    "addr:housenumber":"64",
    "addr:postcode":"4670",
    "addr:street":"George St",
    "iso:country":"AU",
    "sg:address":"64 George St",
    "sg:city":"Bundaberg",
    "sg:classifiers":[
        {
            "category":"Structure",
            "subcategory":"Bridge",
            "type":"Public Place"
        }
    ],
    "sg:phone":"+61 7 4152 1763",
    "sg:postcode":"4670",
    "sg:province":"QLD",
    "sg:tags":[
        "chainsaw",
        "brushcutters"
    ],
    "wof:name":"Rum City Mowers & Saws",
    "wof:placetype":"venue"
},
  "geometry": {"coordinates":[152.35516357399999,-24.8712387085],"type":"Point"}
}