{
  "type": "Feature",
  "properties": {
    "addr:full":"22 Victory Pde Toronto NSW 2283",
    "addr:housenumber":"22",
    "addr:postcode":"2283",
    "addr:street":"Victory Pde",
    "iso:country":"AU",
    "sg:address":"22 Victory Pde",
    "sg:city":"Toronto",
    "sg:classifiers":[
        {
            "category":"Ice Cream",
            "type":"Food & Drink"
        }
    ],
    "sg:phone":"+61 2 4959 7455",
    "sg:postcode":"2283",
    "sg:province":"NSW",
    "sg:tags":[
        "retail"
    ],
    "wof:name":"Great Australian Ice Creamery The",
    "wof:placetype":"venue"
},
  "geometry": {"coordinates":[151.597091675,-33.0127639771],"type":"Point"}
}