{
  "type": "Feature",
  "properties": {
    "iso:country":"AU",
    "sg:address":"Cnr Old Coast Rd & Peelwood Pde",
    "sg:city":"Halls Head",
    "sg:classifiers":[
        {
            "category":"Travel",
            "subcategory":"Travel Agent",
            "type":"Entertainment"
        }
    ],
    "sg:phone":"+61 8 9535 9902",
    "sg:postcode":"6210",
    "sg:province":"WA",
    "sg:tags":[
        "consultant"
    ],
    "wof:name":"Travelscene",
    "wof:placetype":"venue"
},
  "geometry": {"coordinates":[115.70166,-32.551109],"type":"Point"}
}