{
  "type": "Feature",
  "properties": {
    "addr:full":"8 Miller St Yea VIC 3717",
    "addr:housenumber":"8",
    "addr:postcode":"3717",
    "addr:street":"Miller St",
    "iso:country":"AU",
    "sg:address":"8 Miller St",
    "sg:city":"Yea",
    "sg:classifiers":[
        {
            "category":"Travel",
            "subcategory":"Hotels & Motels",
            "type":"Entertainment"
        }
    ],
    "sg:phone":"+61 3 5797 2660",
    "sg:postcode":"3717",
    "sg:province":"VIC",
    "wof:name":"Yea Motel",
    "wof:placetype":"venue"
},
  "geometry": {"coordinates":[145.430374145,-37.2121391296],"type":"Point"}
}