{
  "type": "Feature",
  "properties": {
    "addr:full":"165 Seventh Ave Inglewood WA 6052",
    "addr:housenumber":"165",
    "addr:postcode":"6052",
    "addr:street":"Seventh Ave",
    "iso:country":"AU",
    "sg:address":"165 Seventh Ave",
    "sg:city":"Inglewood",
    "sg:classifiers":[
        {
            "category":"Insurance",
            "subcategory":"Insurance Agent",
            "type":"Services"
        }
    ],
    "sg:phone":"+61 8 9471 1511",
    "sg:postcode":"6052",
    "sg:province":"WA",
    "sg:tags":[
        "broker"
    ],
    "wof:name":"Terri Scheer Insurance Brokers Pty Ltd",
    "wof:placetype":"venue"
},
  "geometry": {"coordinates":[115.884033203,-31.9237213135],"type":"Point"}
}