{
  "type": "Feature",
  "properties": {
    "iso:country":"AU",
    "sg:address":"Peel St",
    "sg:city":"Tamworth",
    "sg:classifiers":[
        {
            "category":"Food & Beverages",
            "subcategory":"Supermarket",
            "type":"Retail Goods"
        }
    ],
    "sg:phone":"+61 2 6766 3488",
    "sg:postcode":"2340",
    "sg:province":"NSW",
    "sg:tags":[
        "grocery",
        "store"
    ],
    "wof:name":"Bi-Lo Pty Ltd",
    "wof:placetype":"venue"
},
  "geometry": {"coordinates":[150.93011474599999,-31.0908851624],"type":"Point"}
}