{
  "type": "Feature",
  "properties": {
    "addr:full":"Cnr Parramatta & Concord Rds Concord NSW 2137",
    "addr:postcode":"2137",
    "iso:country":"AU",
    "sg:address":"Cnr Parramatta & Concord Rds",
    "sg:city":"Concord",
    "sg:classifiers":[
        {
            "category":"Retail",
            "subcategory":"Auto Repair",
            "type":"Services"
        }
    ],
    "sg:phone":"+61 2 9746 0202",
    "sg:postcode":"2137",
    "sg:province":"NSW",
    "sg:tags":[
        "repairer",
        "motor",
        "engineer"
    ],
    "wof:name":"Nissan",
    "wof:placetype":"venue"
},
  "geometry": {"coordinates":[151.10160827600001,-33.8684120178],"type":"Point"}
}