{
  "type": "Feature",
  "properties": {
    "addr:full":"32 Hastings St Noosa Heads QLD 4567",
    "addr:housenumber":"32",
    "addr:postcode":"4567",
    "addr:street":"Hastings St",
    "iso:country":"AU",
    "sg:address":"32 Hastings St",
    "sg:city":"Noosa Heads",
    "sg:classifiers":[
        {
            "category":"Cafe",
            "type":"Food & Drink"
        }
    ],
    "sg:phone":"+61 7 5474 9788",
    "sg:postcode":"4567",
    "sg:province":"QLD",
    "wof:name":"Aromas",
    "wof:placetype":"venue"
},
  "geometry": {"coordinates":[153.08982849099999,-26.3866539001],"type":"Point"}
}