{
  "type": "Feature",
  "properties": {
    "addr:full":"8 Everitt St Glenroy VIC 3046",
    "addr:housenumber":"8",
    "addr:postcode":"3046",
    "addr:street":"Everitt St",
    "iso:country":"AU",
    "sg:address":"8 Everitt St",
    "sg:city":"Glenroy",
    "sg:classifiers":[
        {
            "category":"Building & Trades",
            "subcategory":"Plumbing",
            "type":"Services"
        }
    ],
    "sg:phone":"+61 3 9306 5474",
    "sg:postcode":"3046",
    "sg:province":"VIC",
    "sg:tags":[
        "plumber",
        "gasfitters"
    ],
    "wof:name":"Woodhead J P & Son Pty Ltd",
    "wof:placetype":"venue"
},
  "geometry": {"coordinates":[144.941497803,-37.7137145996],"type":"Point"}
}