{
  "type": "Feature",
  "properties": {
    "iso:country":"AU",
    "sg:address":"47 Forrest St",
    "sg:city":"Boyup Brook",
    "sg:classifiers":[
        {
            "category":"Shopping",
            "subcategory":"Computers & Home Electronics",
            "type":"Retail Goods"
        }
    ],
    "sg:phone":"+61 417 940 269",
    "sg:postcode":"6244",
    "sg:province":"WA",
    "sg:tags":[
        "hardware",
        "equipment"
    ],
    "wof:name":"Boyup Brook Computer Service",
    "wof:placetype":"venue"
},
  "geometry": {"coordinates":[116.391853333,-33.833820343],"type":"Point"}
}