{
  "type": "Feature",
  "properties": {
    "addr:full":"48 Macquarie Rd Cardiff NSW 2285",
    "addr:housenumber":"48",
    "addr:postcode":"2285",
    "addr:street":"Macquarie Rd",
    "iso:country":"AU",
    "sg:address":"48 Macquarie Rd",
    "sg:city":"Cardiff",
    "sg:classifiers":[
        {
            "category":"Retail",
            "subcategory":"Auto Repair",
            "type":"Services"
        }
    ],
    "sg:phone":"+61 2 4954 4464",
    "sg:postcode":"2285",
    "sg:province":"NSW",
    "sg:tags":[
        "repairer",
        "motor",
        "engineer"
    ],
    "wof:name":"V & C Body Repairs",
    "wof:placetype":"venue"
},
  "geometry": {"coordinates":[151.65815734899999,-32.9421844482],"type":"Point"}
}