{
  "type": "Feature",
  "properties": {
    "iso:country":"AU",
    "sg:address":"66 Gatton Creek Rd",
    "sg:city":"Withcott",
    "sg:classifiers":[
        {
            "category":"Professional",
            "subcategory":"Printing & Photocopies",
            "type":"Services"
        }
    ],
    "sg:phone":"+61 7 4630 3077",
    "sg:postcode":"4352",
    "sg:province":"QLD",
    "sg:tags":[
        "screen",
        "printer"
    ],
    "wof:name":"Lockyer Signs",
    "wof:placetype":"venue"
},
  "geometry": {"coordinates":[152.041901,-27.546276],"type":"Point"}
}