{
  "type": "Feature",
  "properties": {
    "addr:full":"Tura Drv Tura NSW 2548",
    "addr:postcode":"2548",
    "addr:street":"Tura Drv",
    "iso:country":"AU",
    "sg:address":"Tura Drv",
    "sg:city":"Tura",
    "sg:classifiers":[
        {
            "category":"Home & Garden",
            "subcategory":"Building Materials",
            "type":"Retail Goods"
        }
    ],
    "sg:phone":"+61 1800 666 437",
    "sg:postcode":"2548",
    "sg:province":"NSW",
    "sg:tags":[
        "tile",
        "roofing"
    ],
    "wof:name":"Monier Wunderlich",
    "wof:placetype":"venue"
},
  "geometry": {"coordinates":[149.92564392099999,-36.8689422607],"type":"Point"}
}