{
  "type": "Feature",
  "properties": {
    "addr:full":"58 Cowell St Carindale QLD 4152",
    "addr:housenumber":"58",
    "addr:postcode":"4152",
    "addr:street":"Cowell St",
    "iso:country":"AU",
    "sg:address":"58 Cowell St",
    "sg:city":"Carindale",
    "sg:classifiers":[
        {
            "category":"Building & Trades",
            "subcategory":"Construction",
            "type":"Services"
        }
    ],
    "sg:phone":"+61 402 791 155",
    "sg:postcode":"4152",
    "sg:province":"QLD",
    "sg:tags":[
        "home",
        "air conditioning"
    ],
    "wof:name":"Professional Filter Cleaning",
    "wof:placetype":"venue"
},
  "geometry": {"coordinates":[153.115356445,-27.527381897],"type":"Point"}
}