{
  "type": "Feature",
  "properties": {
    "addr:full":"Shop 98 Brookside Shopping Centre, 156 Osbourne Rd Mitchelton QLD 4053",
    "addr:housenumber":"shop 98;156",
    "addr:postcode":"4053",
    "addr:street":"Brookside Shopping;Osbourne Rd",
    "iso:country":"AU",
    "sg:address":"Shop 98 Brookside Shopping Centre, 156 Osbourne Rd",
    "sg:city":"Mitchelton",
    "sg:classifiers":[
        {
            "category":"Shopping",
            "subcategory":"Mobile Phones",
            "type":"Retail Goods"
        }
    ],
    "sg:phone":"+61 7 3355 0006",
    "sg:postcode":"4053",
    "sg:province":"QLD",
    "sg:tags":[
        "telephone",
        "accessory"
    ],
    "wof:name":"Telstra Shop",
    "wof:placetype":"venue"
},
  "geometry": {"coordinates":[152.97825622600001,-27.4067153931],"type":"Point"}
}