{
  "type": "Feature",
  "properties": {
    "iso:country":"AU",
    "sg:address":"42 Leyland St",
    "sg:city":"Garbutt",
    "sg:classifiers":[
        {
            "category":"Manufacturing",
            "subcategory":"Aerospace",
            "type":"Manufacturing & Wholesale Goods"
        }
    ],
    "sg:phone":"+61 7 4775 1699",
    "sg:postcode":"4814",
    "sg:province":"QLD",
    "sg:tags":[
        "equipment",
        "aircraft",
        "maintenance"
    ],
    "wof:name":"Aero Plastics & Structures",
    "wof:placetype":"venue"
},
  "geometry": {"coordinates":[146.764725,-19.272429],"type":"Point"}
}