{
  "type": "Feature",
  "properties": {
    "addr:full":"13 Grice Ave Paradise Point QLD 4216",
    "addr:housenumber":"13",
    "addr:postcode":"4216",
    "addr:street":"Grice Ave",
    "iso:country":"AU",
    "sg:address":"13 Grice Ave",
    "sg:city":"Paradise Point",
    "sg:classifiers":[
        {
            "category":"Shopping",
            "subcategory":"Pets & Pet Supplies",
            "type":"Retail Goods"
        }
    ],
    "sg:phone":"+61 7 5577 4325",
    "sg:postcode":"4216",
    "sg:province":"QLD",
    "sg:tags":[
        "dog"
    ],
    "wof:name":"Paradise Dog Grooming",
    "wof:placetype":"venue"
},
  "geometry": {"coordinates":[153.39466857900001,-27.8855018616],"type":"Point"}
}