{
  "type": "Feature",
  "properties": {
    "addr:full":"Cleveland Showgrounds Long St Cleveland QLD 4163",
    "addr:postcode":"4163",
    "addr:street":"Long St",
    "iso:country":"AU",
    "sg:address":"Cleveland Showgrounds Long St",
    "sg:city":"Cleveland",
    "sg:classifiers":[
        {
            "category":"Retail",
            "subcategory":"Event Space",
            "type":"Services"
        }
    ],
    "sg:phone":"+61 7 3286 5841",
    "sg:postcode":"4163",
    "sg:province":"QLD",
    "sg:tags":[
        "venue",
        "reception",
        "wedding"
    ],
    "wof:name":"Redlands Touch Association Inc",
    "wof:placetype":"venue"
},
  "geometry": {"coordinates":[153.265823364,-27.5362968445],"type":"Point"}
}