{
  "type": "Feature",
  "properties": {
    "addr:full":"17a James St Burleigh Heads QLD 4220",
    "addr:housenumber":"17a",
    "addr:postcode":"4220",
    "addr:street":"James St",
    "iso:country":"AU",
    "sg:address":"17a James St",
    "sg:city":"Burleigh Heads",
    "sg:classifiers":[
        {
            "category":"Personal",
            "subcategory":"Beauty Salon",
            "type":"Services"
        }
    ],
    "sg:phone":"+61 7 5576 5395",
    "sg:postcode":"4220",
    "sg:province":"QLD",
    "sg:tags":[
        "hairdresser"
    ],
    "wof:name":"Riot Hairdressing",
    "wof:placetype":"venue"
},
  "geometry": {"coordinates":[153.451416016,-28.0892314911],"type":"Point"}
}