{
  "type": "Feature",
  "properties": {
    "addr:full":"1/115 Darby St Cooks Hill NSW 2300",
    "addr:housenumber":"/ 115",
    "addr:postcode":"2300",
    "addr:street":"Darby St",
    "iso:country":"AU",
    "sg:address":"1/115 Darby St",
    "sg:city":"Cooks Hill",
    "sg:classifiers":[
        {
            "category":"Shopping",
            "subcategory":"Clothing, Apparel, & Fashions",
            "type":"Retail Goods"
        }
    ],
    "sg:phone":"+61 2 4926 1273",
    "sg:postcode":"2300",
    "sg:province":"NSW",
    "sg:tags":[
        "lady",
        "wear"
    ],
    "wof:name":"Guanabana",
    "wof:placetype":"venue"
},
  "geometry": {"coordinates":[151.769058,-32.934135],"type":"Point"}
}