{
  "type": "Feature",
  "properties": {
    "iso:country":"AU",
    "sg:address":"37 Seabrook Crs",
    "sg:city":"Doonside",
    "sg:classifiers":[
        {
            "category":"Professional",
            "type":"Services"
        }
    ],
    "sg:phone":"+61 418 217 744",
    "sg:postcode":"2767",
    "sg:province":"NSW",
    "sg:tags":[
        "transport"
    ],
    "wof:name":"Pema Transport",
    "wof:placetype":"venue"
},
  "geometry": {"coordinates":[150.86932373100001,-33.7645606995],"type":"Point"}
}