{
  "type": "Feature",
  "properties": {
    "addr:full":"Shop 5, 519 Old South Head Rd Rose Bay NSW 2029",
    "addr:housenumber":"shop 5 519",
    "addr:postcode":"2029",
    "addr:street":"Old South Head Rd",
    "iso:country":"AU",
    "sg:address":"Shop 5, 519 Old South Head Rd",
    "sg:city":"Rose Bay",
    "sg:classifiers":[
        {
            "category":"Fast Food",
            "type":"Food & Drink"
        }
    ],
    "sg:phone":"+61 2 9371 8259",
    "sg:postcode":"2029",
    "sg:province":"NSW",
    "sg:tags":[
        "away",
        "take"
    ],
    "wof:name":"Gourmet Shop The",
    "wof:placetype":"venue"
},
  "geometry": {"coordinates":[151.27339172399999,-33.8740196228],"type":"Point"}
}