{
  "type": "Feature",
  "properties": {
    "addr:full":"82 Flinders St Adelaide SA 5000",
    "addr:housenumber":"82",
    "addr:postcode":"5000",
    "addr:street":"Flinders St",
    "iso:country":"AU",
    "sg:address":"82 Flinders St",
    "sg:city":"Adelaide",
    "sg:classifiers":[
        {
            "category":"Professional",
            "subcategory":"Computer Services",
            "type":"Services"
        }
    ],
    "sg:phone":"+61 8 8228 8228",
    "sg:postcode":"5000",
    "sg:province":"SA",
    "sg:tags":[
        "repairs",
        "upgrade",
        "equipment"
    ],
    "wof:name":"Bakas I.T. Solutions",
    "wof:placetype":"venue"
},
  "geometry": {"coordinates":[138.60336303700001,-34.9268493652],"type":"Point"}
}