{
  "type": "Feature",
  "properties": {
    "iso:country":"AU",
    "sg:address":"132 Cary St",
    "sg:city":"Toronto",
    "sg:classifiers":[
        {
            "category":"Autos & Motor Vehicles",
            "subcategory":"Auto Supplies",
            "type":"Retail Goods"
        }
    ],
    "sg:phone":"+61 2 4950 4666",
    "sg:postcode":"2283",
    "sg:province":"NSW",
    "sg:tags":[
        "tyre"
    ],
    "wof:name":"Coopers Tyre-Mart",
    "wof:placetype":"venue"
},
  "geometry": {"coordinates":[151.59361267099999,-33.0116729736],"type":"Point"}
}