{
  "type": "Feature",
  "properties": {
    "addr:full":"200 Old Gympie Rd Caboolture QLD 4510",
    "addr:housenumber":"200",
    "addr:postcode":"4510",
    "addr:street":"Old Gympie Rd",
    "iso:country":"AU",
    "sg:address":"200 Old Gympie Rd",
    "sg:city":"Caboolture",
    "sg:classifiers":[
        {
            "category":"Education",
            "subcategory":"Kindergarten",
            "type":"Public Place"
        }
    ],
    "sg:phone":"+61 7 5495 5877",
    "sg:postcode":"4510",
    "sg:province":"QLD",
    "sg:tags":[
        "pre-schools"
    ],
    "wof:name":"Harmony Montessori Childrens House",
    "wof:placetype":"venue"
},
  "geometry": {"coordinates":[152.93907200000001,-27.054121],"type":"Point"}
}