{
  "type": "Feature",
  "properties": {
    "addr:full":"PO Box 288 Belconnen ACT 2617",
    "addr:postcode":"2617",
    "iso:country":"AU",
    "sg:address":"PO Box 288",
    "sg:city":"Belconnen",
    "sg:classifiers":[
        {
            "category":"Home & Garden",
            "subcategory":"Carpets & Floor Coverings",
            "type":"Retail Goods"
        }
    ],
    "sg:phone":"+61 421 673 703",
    "sg:postcode":"2617",
    "sg:province":"ACT",
    "sg:tags":[
        "tile",
        "wall"
    ],
    "wof:name":"Timber & Tiling Services",
    "wof:placetype":"venue"
},
  "geometry": {"coordinates":[149.06353759800001,-35.239730835],"type":"Point"}
}