{
  "type": "Feature",
  "properties": {
    "iso:country":"AU",
    "sg:address":"48 Yarra Ave",
    "sg:city":"Reservoir",
    "sg:classifiers":[
        {
            "category":"Building & Trades",
            "subcategory":"Construction",
            "type":"Services"
        }
    ],
    "sg:phone":"+61 3 9478 0016",
    "sg:postcode":"3073",
    "sg:province":"VIC",
    "sg:tags":[
        "contractor"
    ],
    "wof:name":"Arraman Construction Pty Ltd",
    "wof:placetype":"venue"
},
  "geometry": {"coordinates":[145.019332886,-37.7189674377],"type":"Point"}
}