{
  "type": "Feature",
  "properties": {
    "addr:full":"Cnr Logan & Harris Rds Underwood QLD 4119",
    "addr:postcode":"4119",
    "addr:street":"Cnr",
    "iso:country":"AU",
    "sg:address":"Cnr Logan & Harris Rds",
    "sg:city":"Underwood",
    "sg:classifiers":[
        {
            "category":"Shopping",
            "subcategory":"Clothing, Apparel, & Fashions",
            "type":"Retail Goods"
        }
    ],
    "sg:phone":"+61 7 3841 1173",
    "sg:postcode":"4119",
    "sg:province":"QLD",
    "sg:tags":[
        "maternity",
        "wear"
    ],
    "wof:name":"Maternity Discount Fashions",
    "wof:placetype":"venue"
},
  "geometry": {"coordinates":[153.11097717300001,-27.6066799164],"type":"Point"}
}