{
  "type": "Feature",
  "properties": {
    "addr:full":"20 Barnett Pl Molendinar QLD 4214",
    "addr:housenumber":"20",
    "addr:postcode":"4214",
    "addr:street":"Barnett Pl",
    "iso:country":"AU",
    "sg:address":"20 Barnett Pl",
    "sg:city":"Molendinar",
    "sg:classifiers":[
        {
            "category":"Professional",
            "subcategory":"Engineering",
            "type":"Services"
        }
    ],
    "sg:phone":"+61 7 5571 6760",
    "sg:postcode":"4214",
    "sg:province":"QLD",
    "sg:tags":[
        "manufacturing",
        "engineer"
    ],
    "wof:name":"Krebs Engineers Pty Ltd",
    "wof:placetype":"venue"
},
  "geometry": {"coordinates":[153.358474731,-27.9649505615],"type":"Point"}
}