{
  "type": "Feature",
  "properties": {
    "iso:country":"AU",
    "sg:address":"780 Merritts Creek Rd",
    "sg:city":"Merritts Creek",
    "sg:classifiers":[
        {
            "category":"Health Services",
            "subcategory":"Health Practitioner",
            "type":"Services"
        }
    ],
    "sg:phone":"+61 7 4697 9204",
    "sg:postcode":"4352",
    "sg:province":"QLD",
    "sg:tags":[
        "naturopath"
    ],
    "wof:name":"Absolute Vitality",
    "wof:placetype":"venue"
},
  "geometry": {"coordinates":[152.025253,-27.375109],"type":"Point"}
}