{
  "type": "Feature",
  "properties": {
    "iso:country":"AU",
    "sg:address":"7a Ashburner St",
    "sg:city":"Manly",
    "sg:classifiers":[
        {
            "category":"Health Services",
            "subcategory":"Health Practitioner",
            "type":"Services"
        }
    ],
    "sg:phone":"+61 2 9977 3291",
    "sg:postcode":"2095",
    "sg:province":"NSW",
    "sg:tags":[
        "psychologist"
    ],
    "wof:name":"Elspeth Hawkins",
    "wof:placetype":"venue"
},
  "geometry": {"coordinates":[151.28752136200001,-33.801235199],"type":"Point"}
}