{
  "type": "Feature",
  "properties": {
    "addr:full":"1586 Burwood Hwy Belgrave VIC 3160",
    "addr:housenumber":"1586",
    "addr:postcode":"3160",
    "addr:street":"Burwood Hwy",
    "iso:country":"AU",
    "sg:address":"1586 Burwood Hwy",
    "sg:city":"Belgrave",
    "sg:classifiers":[
        {
            "category":"Government",
            "subcategory":"Court House",
            "type":"Public Place"
        }
    ],
    "sg:phone":"+61 3 9754 8066",
    "sg:postcode":"3160",
    "sg:province":"VIC",
    "sg:tags":[
        "personal",
        "marriage",
        "family",
        "counselling"
    ],
    "wof:name":"Dedovic Zineta",
    "wof:placetype":"venue"
},
  "geometry": {"coordinates":[145.35174560600001,-37.9084625244],"type":"Point"}
}