{
  "type": "Feature",
  "properties": {
    "addr:full":"44 Jijaws St Sumner Park QLD 4074",
    "addr:housenumber":"44",
    "addr:postcode":"4074",
    "addr:street":"Jijaws St",
    "iso:country":"AU",
    "sg:address":"44 Jijaws St",
    "sg:city":"Sumner Park",
    "sg:classifiers":[
        {
            "category":"Building & Trades",
            "subcategory":"Cleaning & Sanitation",
            "type":"Services"
        }
    ],
    "sg:phone":"+61 7 3376 7488",
    "sg:postcode":"4074",
    "sg:province":"QLD",
    "sg:tags":[
        "sweeping",
        "machine"
    ],
    "wof:name":"MLA Holdings Pty Ltd",
    "wof:placetype":"venue"
},
  "geometry": {"coordinates":[152.93922424300001,-27.5630111694],"type":"Point"}
}