{
  "type": "Feature",
  "properties": {
    "addr:full":"53 Rohini St Turramurra NSW 2074",
    "addr:housenumber":"53",
    "addr:postcode":"2074",
    "addr:street":"Rohini St",
    "iso:country":"AU",
    "sg:address":"53 Rohini St",
    "sg:city":"Turramurra",
    "sg:classifiers":[
        {
            "category":"Social Services",
            "subcategory":"Retirement Home",
            "type":"Services"
        }
    ],
    "sg:phone":"+61 2 9449 5099",
    "sg:postcode":"2074",
    "sg:province":"NSW",
    "sg:tags":[
        "village"
    ],
    "wof:name":"Rohini Village",
    "wof:placetype":"venue"
},
  "geometry": {"coordinates":[151.127716064,-33.7307548523],"type":"Point"}
}