{
  "type": "Feature",
  "properties": {
    "addr:full":"Shop 11 Easy T Centre, Cnr Scottsdale Dr & Christine Ave Robina QLD 4226",
    "addr:housenumber":"shop 11",
    "addr:postcode":"4226",
    "addr:street":"Easy T;Cnr Scottsdale Dr;Ave",
    "iso:country":"AU",
    "sg:address":"Shop 11 Easy T Centre, Cnr Scottsdale Dr & Christine Ave",
    "sg:city":"Robina",
    "sg:classifiers":[
        {
            "category":"Restaurant",
            "type":"Food & Drink"
        }
    ],
    "sg:phone":"+61 7 5580 8080",
    "sg:postcode":"4226",
    "sg:province":"QLD",
    "wof:name":"Tuk Tuk Thai",
    "wof:placetype":"venue"
},
  "geometry": {"coordinates":[153.38949585,-28.079580307],"type":"Point"}
}