{
  "type": "Feature",
  "properties": {
    "addr:full":"48a Elizabeth St Edenhope VIC 3318",
    "addr:housenumber":"48a",
    "addr:postcode":"3318",
    "addr:street":"Elizabeth St",
    "iso:country":"AU",
    "sg:address":"48a Elizabeth St",
    "sg:city":"Edenhope",
    "sg:classifiers":[
        {
            "category":"Wholesale",
            "subcategory":"Farm Supplies",
            "type":"Manufacturing & Wholesale Goods"
        }
    ],
    "sg:phone":"+61 3 5585 1975",
    "sg:postcode":"3318",
    "sg:province":"VIC",
    "sg:tags":[
        "equipment"
    ],
    "wof:name":"West Wimmera Rural Services",
    "wof:placetype":"venue"
},
  "geometry": {"coordinates":[141.29925537099999,-37.0359611511],"type":"Point"}
}