{
  "type": "Feature",
  "properties": {
    "addr:full":"87 Planthurst Rd Carlton NSW 2218",
    "addr:housenumber":"87",
    "addr:postcode":"2218",
    "addr:street":"Planthurst Rd",
    "iso:country":"AU",
    "sg:address":"87 Planthurst Rd",
    "sg:city":"Carlton",
    "sg:classifiers":[
        {
            "category":"Banks & Credit Unions",
            "subcategory":"Financial Services",
            "type":"Services"
        }
    ],
    "sg:phone":"+61 2 8515 0155",
    "sg:postcode":"2218",
    "sg:province":"NSW",
    "sg:tags":[
        "financier"
    ],
    "wof:name":"Smash Repairers Factoring Company",
    "wof:placetype":"venue"
},
  "geometry": {"coordinates":[151.115387,-33.979679],"type":"Point"}
}