{
  "type": "Feature",
  "properties": {
    "iso:country":"AU",
    "sg:address":"North St (Extended)",
    "sg:city":"West Rockhampton",
    "sg:classifiers":[
        {
            "category":"Education",
            "subcategory":"School",
            "type":"Public Place"
        }
    ],
    "sg:phone":"+61 7 4999 3333",
    "sg:postcode":"4700",
    "sg:province":"QLD",
    "sg:tags":[
        "state",
        "except",
        "nsw"
    ],
    "wof:name":"Crescent Lagoon Primary School",
    "wof:placetype":"venue"
},
  "geometry": {"coordinates":[150.49339294399999,-23.3790664673],"type":"Point"}
}