{
  "type": "Feature",
  "properties": {
    "iso:country":"AU",
    "sg:address":"186 Williamson St",
    "sg:city":"Bendigo",
    "sg:classifiers":[
        {
            "category":"Personal",
            "subcategory":"Beauty Salon",
            "type":"Services"
        }
    ],
    "sg:phone":"+61 3 5442 2958",
    "sg:postcode":"3550",
    "sg:province":"VIC",
    "sg:tags":[
        "hairdresser"
    ],
    "wof:name":"Helen's Hair Care",
    "wof:placetype":"venue"
},
  "geometry": {"coordinates":[144.291473389,-36.7687492371],"type":"Point"}
}