{
  "type": "Feature",
  "properties": {
    "addr:full":"3 Bateman St Strathalbyn SA 5255",
    "addr:housenumber":"3",
    "addr:postcode":"5255",
    "addr:street":"Bateman St",
    "iso:country":"AU",
    "sg:address":"3 Bateman St",
    "sg:city":"Strathalbyn",
    "sg:classifiers":[
        {
            "category":"Organizations",
            "subcategory":"Professional Association",
            "type":"Services"
        }
    ],
    "sg:phone":"+61 422 239 133",
    "sg:postcode":"5255",
    "sg:province":"SA",
    "sg:tags":[
        "web",
        "internet"
    ],
    "wof:name":"Tek Gear",
    "wof:placetype":"venue"
},
  "geometry": {"coordinates":[138.90286254899999,-35.2493057251],"type":"Point"}
}