{
  "type": "Feature",
  "properties": {
    "addr:full":"119 Cromer Rd Beaumaris VIC 3193",
    "addr:housenumber":"119",
    "addr:postcode":"3193",
    "addr:street":"Cromer Rd",
    "iso:country":"AU",
    "sg:address":"119 Cromer Rd",
    "sg:city":"Beaumaris",
    "sg:classifiers":[
        {
            "category":"Health Services",
            "subcategory":"Doctor",
            "type":"Services"
        }
    ],
    "sg:phone":"+61 3 9584 4444",
    "sg:postcode":"3193",
    "sg:province":"VIC",
    "sg:tags":[
        "medical",
        "practitioner"
    ],
    "wof:name":"Lett Irwin",
    "wof:placetype":"venue"
},
  "geometry": {"coordinates":[145.04591369600001,-37.9793319702],"type":"Point"}
}