{
  "type": "Feature",
  "properties": {
    "addr:full":"105 Bourke St Goulburn NSW 2580",
    "addr:housenumber":"105",
    "addr:postcode":"2580",
    "addr:street":"Bourke St",
    "iso:country":"AU",
    "sg:address":"105 Bourke St",
    "sg:city":"Goulburn",
    "sg:classifiers":[
        {
            "category":"Health Services",
            "subcategory":"Health Practitioner",
            "type":"Services"
        }
    ],
    "sg:phone":"+61 2 4821 5544",
    "sg:postcode":"2580",
    "sg:province":"NSW",
    "sg:tags":[
        "physiotherapist"
    ],
    "wof:name":"Goulburn Physiotherapy Centre",
    "wof:placetype":"venue"
},
  "geometry": {"coordinates":[149.71693420400001,-34.7528762817],"type":"Point"}
}