{
  "type": "Feature",
  "properties": {
    "addr:full":"Second Ave Onslow WA 6710",
    "addr:postcode":"6710",
    "addr:street":"Second Ave Onslow",
    "iso:country":"AU",
    "sg:address":"Second Ave",
    "sg:city":"Onslow",
    "sg:classifiers":[
        {
            "category":"Food & Beverages",
            "subcategory":"Groceries & Convenience Stores",
            "type":"Retail Goods"
        }
    ],
    "sg:phone":"+61 8 9184 6003",
    "sg:postcode":"6710",
    "sg:province":"WA",
    "wof:name":"Onslow General Store",
    "wof:placetype":"venue"
},
  "geometry": {"coordinates":[115.112846374,-21.6369075775],"type":"Point"}
}