{
  "type": "Feature",
  "properties": {
    "addr:full":"19 Vernon St Spotswood VIC 3015",
    "addr:housenumber":"19",
    "addr:postcode":"3015",
    "addr:street":"Vernon St",
    "iso:country":"AU",
    "sg:address":"19 Vernon St",
    "sg:city":"Spotswood",
    "sg:classifiers":[
        {
            "category":"Health Services",
            "subcategory":"Health Practitioner",
            "type":"Services"
        }
    ],
    "sg:phone":"+61 3 9391 6777",
    "sg:postcode":"3015",
    "sg:province":"VIC",
    "sg:tags":[
        "acupuncture"
    ],
    "wof:name":"Ferrigno Peter",
    "wof:placetype":"venue"
},
  "geometry": {"coordinates":[144.87210082999999,-37.8291740417],"type":"Point"}
}