{
  "type": "Feature",
  "properties": {
    "addr:full":"100 Old Princes Hwy Beaconsfield VIC 3807",
    "addr:housenumber":"100",
    "addr:postcode":"3807",
    "addr:street":"Old Princes Hwy",
    "iso:country":"AU",
    "sg:address":"100 Old Princes Hwy",
    "sg:city":"Beaconsfield",
    "sg:classifiers":[
        {
            "category":"Home & Garden",
            "subcategory":"Garden Supply",
            "type":"Retail Goods"
        }
    ],
    "sg:phone":"+61 3 9707 5144",
    "sg:postcode":"3807",
    "sg:province":"VIC",
    "sg:tags":[
        "equipment"
    ],
    "wof:name":"Beaconsfield Garden Supplies",
    "wof:placetype":"venue"
},
  "geometry": {"coordinates":[145.36799621599999,-38.0455284119],"type":"Point"}
}