{
  "type": "Feature",
  "properties": {
    "addr:full":"53 Wises Rd Maroochydore QLD 4558",
    "addr:housenumber":"53",
    "addr:postcode":"4558",
    "addr:street":"Wises Rd",
    "iso:country":"AU",
    "sg:address":"53 Wises Rd",
    "sg:city":"Maroochydore",
    "sg:classifiers":[
        {
            "category":"Home & Garden",
            "subcategory":"Hardware",
            "type":"Retail Goods"
        }
    ],
    "sg:phone":"+61 7 5479 2955",
    "sg:postcode":"4558",
    "sg:province":"QLD",
    "sg:tags":[
        "trolley",
        "truck",
        "hand"
    ],
    "wof:name":"Vetner Sunshine Coast",
    "wof:placetype":"venue"
},
  "geometry": {"coordinates":[153.08555602999999,-26.6713409424],"type":"Point"}
}