{
  "type": "Feature",
  "properties": {
    "addr:full":"6 Duncan St Vincentia NSW 2540",
    "addr:housenumber":"6",
    "addr:postcode":"2540",
    "addr:street":"Duncan St",
    "iso:country":"AU",
    "sg:address":"6 Duncan St",
    "sg:city":"Vincentia",
    "sg:classifiers":[
        {
            "category":"Building & Trades",
            "subcategory":"Construction",
            "type":"Services"
        }
    ],
    "sg:phone":"+61 2 4441 5948",
    "sg:postcode":"2540",
    "sg:province":"NSW",
    "sg:tags":[
        "brick",
        "paving"
    ],
    "wof:name":"Colbert Stephen",
    "wof:placetype":"venue"
},
  "geometry": {"coordinates":[150.673339844,-35.0541763306],"type":"Point"}
}