{
  "type": "Feature",
  "properties": {
    "iso:country":"AU",
    "sg:address":"38 Sunset Crs",
    "sg:city":"Torquay",
    "sg:classifiers":[
        {
            "category":"Personal",
            "subcategory":"Massage",
            "type":"Services"
        }
    ],
    "sg:phone":"+61 7 4124 9989",
    "sg:postcode":"4655",
    "sg:province":"QLD",
    "sg:tags":[
        "therapy"
    ],
    "wof:name":"Graham Forrest",
    "wof:placetype":"venue"
},
  "geometry": {"coordinates":[152.869263,-25.291929],"type":"Point"}
}