{
  "type": "Feature",
  "properties": {
    "addr:full":"Unit 1/ 63-65 Dover Drv Burleigh Heads QLD 4220",
    "addr:housenumber":"/ 63-65",
    "addr:postcode":"4220",
    "addr:street":"Dover Drv",
    "iso:country":"AU",
    "sg:address":"Unit 1/ 63-65 Dover Drv",
    "sg:city":"Burleigh Heads",
    "sg:classifiers":[
        {
            "category":"Building & Trades",
            "subcategory":"Construction",
            "type":"Services"
        }
    ],
    "sg:phone":"+61 7 5535 4477",
    "sg:postcode":"4220",
    "sg:province":"QLD",
    "sg:tags":[
        "window",
        "aluminium"
    ],
    "wof:name":"Wintec Aluminium Pty Ltd",
    "wof:placetype":"venue"
},
  "geometry": {"coordinates":[153.42628479000001,-28.1063327789],"type":"Point"}
}