{
  "type": "Feature",
  "properties": {
    "addr:full":"15 Goodwin House 69 South Pine Rd Brendale QLD 4500",
    "addr:housenumber":"15;house 69",
    "addr:postcode":"4500",
    "addr:street":"Goodwin;South Pine Rd",
    "iso:country":"AU",
    "sg:address":"15 Goodwin House 69 South Pine Rd",
    "sg:city":"Brendale",
    "sg:classifiers":[
        {
            "category":"Retail",
            "subcategory":"Auto Repair",
            "type":"Services"
        }
    ],
    "sg:phone":"+61 7 3205 1277",
    "sg:postcode":"4500",
    "sg:province":"QLD",
    "sg:tags":[
        "electrical"
    ],
    "wof:name":"M & F Auto Electrics",
    "wof:placetype":"venue"
},
  "geometry": {"coordinates":[152.98379516599999,-27.3268680573],"type":"Point"}
}