{
  "type": "Feature",
  "properties": {
    "addr:full":"27 Field St Whyalla Playford SA 5600",
    "addr:housenumber":"27",
    "addr:postcode":"5600",
    "addr:street":"Field St",
    "iso:country":"AU",
    "sg:address":"27 Field St",
    "sg:city":"Whyalla Playford",
    "sg:classifiers":[
        {
            "category":"Organizations",
            "subcategory":"Community Association",
            "type":"Services"
        }
    ],
    "sg:phone":"+61 8 8645 0952",
    "sg:postcode":"5600",
    "sg:province":"SA",
    "sg:tags":[
        "club",
        "senior",
        "citizen"
    ],
    "wof:name":"Whyalla Senior Citizens Club",
    "wof:placetype":"venue"
},
  "geometry": {"coordinates":[137.561905,-33.024479],"type":"Point"}
}