{
  "type": "Feature",
  "properties": {
    "iso:country":"AU",
    "sg:address":"1293 Gympie Rd",
    "sg:city":"Aspley",
    "sg:classifiers":[
        {
            "category":"Shopping",
            "subcategory":"Shoes",
            "type":"Retail Goods"
        }
    ],
    "sg:phone":"+61 7 3263 2166",
    "sg:postcode":"4034",
    "sg:province":"QLD",
    "sg:tags":[
        "footwear"
    ],
    "wof:name":"Greg Grant Saddlery Pty Ltd",
    "wof:placetype":"venue"
},
  "geometry": {"coordinates":[153.017471,-27.3652],"type":"Point"}
}