{
  "type": "Feature",
  "properties": {
    "iso:country":"AU",
    "sg:address":"3/88 Moreton St",
    "sg:city":"New Farm",
    "sg:classifiers":[
        {
            "category":"Building & Trades",
            "subcategory":"Construction",
            "type":"Services"
        }
    ],
    "sg:phone":"+61 410 647 732",
    "sg:postcode":"4005",
    "sg:province":"QLD",
    "sg:tags":[
        "decking",
        "contractor"
    ],
    "wof:name":"B Plus B Deck Designs",
    "wof:placetype":"venue"
},
  "geometry": {"coordinates":[153.04315185600001,-27.4685516357],"type":"Point"}
}