{
  "type": "Feature",
  "properties": {
    "addr:full":"3 Johnson St Leongatha VIC 3953",
    "addr:housenumber":"3",
    "addr:postcode":"3953",
    "addr:street":"Johnson St",
    "iso:country":"AU",
    "sg:address":"3 Johnson St",
    "sg:city":"Leongatha",
    "sg:classifiers":[
        {
            "category":"Health Services",
            "subcategory":"Health Practitioner",
            "type":"Services"
        }
    ],
    "sg:phone":"+61 3 5662 5036",
    "sg:postcode":"3953",
    "sg:province":"VIC",
    "sg:tags":[
        "alternative"
    ],
    "wof:name":"Haven Of Health",
    "wof:placetype":"venue"
},
  "geometry": {"coordinates":[145.93940734899999,-38.4823074341],"type":"Point"}
}