{
  "type": "Feature",
  "properties": {
    "iso:country":"AU",
    "sg:address":"244 Riley St",
    "sg:city":"Surry Hills",
    "sg:classifiers":[
        {
            "category":"Personal",
            "subcategory":"Beauty Salon",
            "type":"Services"
        }
    ],
    "sg:phone":"+61 2 9280 2511",
    "sg:postcode":"2010",
    "sg:province":"NSW",
    "sg:tags":[
        "hairdresser"
    ],
    "wof:name":"Scout Hair",
    "wof:placetype":"venue"
},
  "geometry": {"coordinates":[151.213500977,-33.8822479248],"type":"Point"}
}