{
  "type": "Feature",
  "properties": {
    "addr:full":"32A Bashford St Jurien Bay WA 6516",
    "addr:housenumber":"32a",
    "addr:postcode":"6516",
    "addr:street":"Bashford St",
    "iso:country":"AU",
    "sg:address":"32A Bashford St",
    "sg:city":"Jurien Bay",
    "sg:classifiers":[
        {
            "category":"Real Estate",
            "subcategory":"Real Estate Agent",
            "type":"Services"
        }
    ],
    "sg:phone":"+61 8 9652 2077",
    "sg:postcode":"6516",
    "sg:province":"WA",
    "wof:name":"Ray White Jurien Bay",
    "wof:placetype":"venue"
},
  "geometry": {"coordinates":[115.041344,-30.303787],"type":"Point"}
}