{
  "type": "Feature",
  "properties": {
    "iso:country":"AU",
    "sg:address":"Unit 3, 9 Works Pl",
    "sg:city":"Milperra",
    "sg:classifiers":[
        {
            "category":"Professional",
            "subcategory":"Engineering",
            "type":"Services"
        }
    ],
    "sg:phone":"+61 412 670 955",
    "sg:postcode":"2214",
    "sg:province":"NSW",
    "sg:tags":[
        "engineer"
    ],
    "wof:name":"R A S Precision Engineering",
    "wof:placetype":"venue"
},
  "geometry": {"coordinates":[150.993729,-33.934502],"type":"Point"}
}