{
  "type": "Feature",
  "properties": {
    "addr:full":"13 Aldenhoven Rd Lonsdale SA 5160",
    "addr:housenumber":"13",
    "addr:postcode":"5160",
    "addr:street":"Aldenhoven Rd",
    "iso:country":"AU",
    "sg:address":"13 Aldenhoven Rd",
    "sg:city":"Lonsdale",
    "sg:classifiers":[
        {
            "category":"Home & Garden",
            "subcategory":"Kitchen Supply",
            "type":"Retail Goods"
        }
    ],
    "sg:phone":"+61 8 8384 1466",
    "sg:postcode":"5160",
    "sg:province":"SA",
    "sg:tags":[
        "equipment",
        "diving"
    ],
    "wof:name":"Seasuits Australia Pty Ltd",
    "wof:placetype":"venue"
},
  "geometry": {"coordinates":[138.49710082999999,-35.1123428345],"type":"Point"}
}