{
  "type": "Feature",
  "properties": {
    "addr:full":"31 Brisbane St Mackay QLD 4740",
    "addr:housenumber":"31",
    "addr:postcode":"4740",
    "addr:street":"Brisbane St",
    "iso:country":"AU",
    "sg:address":"31 Brisbane St",
    "sg:city":"Mackay",
    "sg:classifiers":[
        {
            "category":"Health Services",
            "subcategory":"Doctor",
            "type":"Services"
        }
    ],
    "sg:phone":"+61 7 4951 9444",
    "sg:postcode":"4740",
    "sg:province":"QLD",
    "sg:tags":[
        "medical",
        "practitioner"
    ],
    "wof:name":"Lloyd Medical Centre",
    "wof:placetype":"venue"
},
  "geometry": {"coordinates":[149.188141,-21.143984],"type":"Point"}
}