{
  "type": "Feature",
  "properties": {
    "iso:country":"AU",
    "sg:address":"Unit 10/ 380 West Botany St",
    "sg:city":"Rockdale",
    "sg:classifiers":[
        {
            "category":"Retail",
            "subcategory":"Auto Repair",
            "type":"Services"
        }
    ],
    "sg:phone":"+61 2 9567 4277",
    "sg:postcode":"2216",
    "sg:province":"NSW",
    "sg:tags":[
        "repairer",
        "motor",
        "engineer"
    ],
    "wof:name":"John & Thomas Chan's Auto Repairs",
    "wof:placetype":"venue"
},
  "geometry": {"coordinates":[151.14721700000001,-33.95723],"type":"Point"}
}