{
  "type": "Feature",
  "properties": {
    "addr:full":"Hawthorne Rd Mylor SA 5153",
    "addr:postcode":"5153",
    "addr:street":"Hawthorne Rd",
    "iso:country":"AU",
    "sg:address":"Hawthorne Rd",
    "sg:city":"Mylor",
    "sg:classifiers":[
        {
            "category":"Building & Trades",
            "subcategory":"Construction",
            "type":"Services"
        }
    ],
    "sg:phone":"+61 8 8388 5131",
    "sg:postcode":"5153",
    "sg:province":"SA",
    "sg:tags":[
        "stonework",
        "stone",
        "mason"
    ],
    "wof:name":"Active Stone Masonry",
    "wof:placetype":"venue"
},
  "geometry": {"coordinates":[138.76789855999999,-35.0289039612],"type":"Point"}
}