{
  "type": "Feature",
  "properties": {
    "iso:country":"AU",
    "sg:address":"568 Somerville Rd",
    "sg:city":"Sunshine",
    "sg:classifiers":[
        {
            "category":"Building & Trades",
            "subcategory":"Construction",
            "type":"Services"
        }
    ],
    "sg:phone":"+61 3 9364 8577",
    "sg:postcode":"3020",
    "sg:province":"VIC",
    "sg:tags":[
        "home",
        "air conditioning"
    ],
    "wof:name":"Cool Breeze Manufacturing Pty Ltd",
    "wof:placetype":"venue"
},
  "geometry": {"coordinates":[144.826218,-37.806252],"type":"Point"}
}