{
  "type": "Feature",
  "properties": {
    "iso:country":"AU",
    "sg:address":"4/ 29 Winnellie Rd",
    "sg:city":"Winnellie",
    "sg:classifiers":[
        {
            "category":"Professional",
            "subcategory":"Printing & Photocopies",
            "type":"Services"
        }
    ],
    "sg:phone":"+61 8 8947 0260",
    "sg:postcode":"0820",
    "sg:province":"NT",
    "sg:tags":[
        "screen",
        "printer"
    ],
    "wof:name":"Moogully Silk Graphics",
    "wof:placetype":"venue"
},
  "geometry": {"coordinates":[130.873336792,-12.4264888763],"type":"Point"}
}