{
  "type": "Feature",
  "properties": {
    "iso:country":"AU",
    "sg:address":"64 Killara Rd",
    "sg:city":"Campbellfield",
    "sg:classifiers":[
        {
            "category":"Professional",
            "subcategory":"Art Services",
            "type":"Services"
        }
    ],
    "sg:phone":"+61 409 888 001",
    "sg:postcode":"3061",
    "sg:province":"VIC",
    "sg:tags":[
        "graphic",
        "designer"
    ],
    "wof:name":"Liquidair Custom Air Brushing",
    "wof:placetype":"venue"
},
  "geometry": {"coordinates":[144.96505737300001,-37.6628875732],"type":"Point"}
}