{
  "type": "Feature",
  "properties": {
    "addr:full":"616 Balcombe Rd Black Rock VIC 3193",
    "addr:housenumber":"616",
    "addr:postcode":"3193",
    "addr:street":"Balcombe Rd",
    "iso:country":"AU",
    "sg:address":"616 Balcombe Rd",
    "sg:city":"Black Rock",
    "sg:classifiers":[
        {
            "category":"Banks & Credit Unions",
            "subcategory":"Investment Brokerage",
            "type":"Services"
        }
    ],
    "sg:phone":"+61 3 9589 6611",
    "sg:postcode":"3193",
    "sg:province":"VIC",
    "wof:name":"Acquest Financial Services",
    "wof:placetype":"venue"
},
  "geometry": {"coordinates":[145.01651000999999,-37.9753837585],"type":"Point"}
}