{
  "type": "Feature",
  "properties": {
    "iso:country":"AU",
    "sg:address":"2 Avern St",
    "sg:city":"Inverell",
    "sg:classifiers":[
        {
            "category":"Real Estate",
            "subcategory":"Architect",
            "type":"Services"
        }
    ],
    "sg:phone":"+61 2 6721 0989",
    "sg:postcode":"2360",
    "sg:province":"NSW",
    "sg:tags":[
        "building",
        "designer"
    ],
    "wof:name":"Eddy Design",
    "wof:placetype":"venue"
},
  "geometry": {"coordinates":[151.10577392600001,-29.7693557739],"type":"Point"}
}