{
  "type": "Feature",
  "properties": {
    "iso:country":"AU",
    "sg:address":"1/ 13 Mitchell St",
    "sg:city":"Norah Head",
    "sg:classifiers":[
        {
            "category":"Health Services",
            "subcategory":"Doctor",
            "type":"Services"
        }
    ],
    "sg:phone":"+61 2 4397 2211",
    "sg:postcode":"2263",
    "sg:province":"NSW",
    "sg:tags":[
        "medical",
        "practitioner"
    ],
    "wof:name":"Tristar Medical Group",
    "wof:placetype":"venue"
},
  "geometry": {"coordinates":[151.56532300000001,-33.279167],"type":"Point"}
}