{
  "type": "Feature",
  "properties": {
    "iso:country":"AU",
    "sg:address":"14 Kell Rd",
    "sg:city":"St Arnaud",
    "sg:classifiers":[
        {
            "category":"Autos & Motor Vehicles",
            "subcategory":"Auto Supplies",
            "type":"Retail Goods"
        }
    ],
    "sg:phone":"+61 3 5495 3222",
    "sg:postcode":"3478",
    "sg:province":"VIC",
    "sg:tags":[
        "equipment",
        "part",
        "truck"
    ],
    "wof:name":"Casey's Truck & Tractor",
    "wof:placetype":"venue"
},
  "geometry": {"coordinates":[143.26693725600001,-36.6283035278],"type":"Point"}
}