{
  "type": "Feature",
  "properties": {
    "addr:full":"The Plaza Kiosk 3 Market Sq Geelong VIC 3220",
    "addr:housenumber":"3",
    "addr:postcode":"3220",
    "addr:street":"Market Sq",
    "iso:country":"AU",
    "sg:address":"The Plaza Kiosk 3 Market Sq",
    "sg:city":"Geelong",
    "sg:classifiers":[
        {
            "category":"Casinos & Gambling",
            "type":"Entertainment"
        }
    ],
    "sg:phone":"+61 3 5229 6529",
    "sg:postcode":"3220",
    "sg:province":"VIC",
    "sg:tags":[
        "lottery",
        "agent"
    ],
    "wof:name":"Market Square Lotto",
    "wof:placetype":"venue"
},
  "geometry": {"coordinates":[144.36016799999999,-38.151413],"type":"Point"}
}