{
  "type": "Feature",
  "properties": {
    "addr:full":"Unit 14 38- 44 Dandenong St Dandenong VIC 3175",
    "addr:housenumber":"38 44",
    "addr:postcode":"3175",
    "addr:street":"Dandenong St",
    "iso:country":"AU",
    "sg:address":"Unit 14 38- 44 Dandenong St",
    "sg:city":"Dandenong",
    "sg:classifiers":[
        {
            "category":"Autos & Motor Vehicles",
            "subcategory":"Fuel & Gas Station",
            "type":"Retail Goods"
        }
    ],
    "sg:phone":"+61 3 9793 1508",
    "sg:postcode":"3175",
    "sg:province":"VIC",
    "wof:name":"N S Mechanical Service",
    "wof:placetype":"venue"
},
  "geometry": {"coordinates":[145.19909668,-37.9951210022],"type":"Point"}
}