{
  "type": "Feature",
  "properties": {
    "addr:full":"PO Box 733 Modbury SA 5092",
    "addr:postcode":"5092",
    "iso:country":"AU",
    "sg:address":"PO Box 733",
    "sg:city":"Modbury",
    "sg:classifiers":[
        {
            "category":"Building & Trades",
            "subcategory":"Cleaning & Sanitation",
            "type":"Services"
        }
    ],
    "sg:phone":"+61 8 8263 0113",
    "sg:postcode":"5092",
    "sg:province":"SA",
    "sg:tags":[
        "window"
    ],
    "wof:name":"Clear View Window Cleaning",
    "wof:placetype":"venue"
},
  "geometry": {"coordinates":[138.69236755399999,-34.8331794739],"type":"Point"}
}