{
  "type": "Feature",
  "properties": {
    "addr:full":"451 Old Geelong Rd Hoppers Crossing VIC 3029",
    "addr:housenumber":"451",
    "addr:postcode":"3029",
    "addr:street":"Old Geelong Rd",
    "iso:country":"AU",
    "sg:address":"451 Old Geelong Rd",
    "sg:city":"Hoppers Crossing",
    "sg:classifiers":[
        {
            "category":"Home & Garden",
            "subcategory":"Building Materials",
            "type":"Retail Goods"
        }
    ],
    "sg:phone":"+61 421 108 078",
    "sg:postcode":"3029",
    "sg:province":"VIC",
    "sg:tags":[
        "gate"
    ],
    "wof:name":"AC Fast Fencing",
    "wof:placetype":"venue"
},
  "geometry": {"coordinates":[144.73251300000001,-37.868183],"type":"Point"}
}