{
  "type": "Feature",
  "properties": {
    "iso:country":"AU",
    "sg:address":"34 Notar Drv",
    "sg:city":"Ormeau",
    "sg:classifiers":[
        {
            "category":"Wholesale",
            "subcategory":"Electrical",
            "type":"Manufacturing & Wholesale Goods"
        }
    ],
    "sg:phone":"+61 7 5540 7877",
    "sg:postcode":"4208",
    "sg:province":"QLD",
    "sg:tags":[
        "wholesaler"
    ],
    "wof:name":"K T Cable Accessories",
    "wof:placetype":"venue"
},
  "geometry": {"coordinates":[153.24969482399999,-27.7599525452],"type":"Point"}
}