{
  "type": "Feature",
  "properties": {
    "iso:country":"AU",
    "sg:address":"Shop 3 Leatherline Centre 131 Old Pacific Hwy",
    "sg:city":"Oxenford",
    "sg:classifiers":[
        {
            "category":"Banks & Credit Unions",
            "subcategory":"Financial Services",
            "type":"Services"
        }
    ],
    "sg:phone":"+61 7 5573 7011",
    "sg:postcode":"4210",
    "sg:province":"QLD",
    "sg:tags":[
        "annuity",
        "rollover",
        "superannuation",
        "consultant"
    ],
    "wof:name":"Professional Superannuation Services",
    "wof:placetype":"venue"
},
  "geometry": {"coordinates":[153.31350707999999,-27.8899879456],"type":"Point"}
}