{
  "type": "Feature",
  "properties": {
    "addr:full":"10 Tenison Ave Cambridge Gardens NSW 2747",
    "addr:housenumber":"10",
    "addr:postcode":"2747",
    "addr:street":"Tenison Ave Cambridge Gardens",
    "iso:country":"AU",
    "sg:address":"10 Tenison Ave",
    "sg:city":"Cambridge Gardens",
    "sg:classifiers":[
        {
            "category":"Military Area",
            "subcategory":"Armory",
            "type":"Public Place"
        }
    ],
    "sg:phone":"+61 404 132 208",
    "sg:postcode":"2747",
    "sg:province":"NSW",
    "sg:tags":[
        "belt",
        "seat"
    ],
    "wof:name":"Beesafe Travel",
    "wof:placetype":"venue"
},
  "geometry": {"coordinates":[150.72259521500001,-33.7405891418],"type":"Point"}
}