{
  "type": "Feature",
  "properties": {
    "addr:full":"Pacific Hwy Urunga NSW 2455",
    "addr:postcode":"2455",
    "addr:street":"Pacific Hwy",
    "iso:country":"AU",
    "sg:address":"Pacific Hwy",
    "sg:city":"Urunga",
    "sg:classifiers":[
        {
            "category":"Place Of Worship",
            "subcategory":"Monastery",
            "type":"Public Place"
        }
    ],
    "sg:phone":"+61 2 6655 6373",
    "sg:postcode":"2455",
    "sg:province":"NSW",
    "sg:tags":[
        "residential",
        "village"
    ],
    "wof:name":"Gundamain Caravan Park",
    "wof:placetype":"venue"
},
  "geometry": {"coordinates":[153.005844,-30.50584],"type":"Point"}
}