{
  "type": "Feature",
  "properties": {
    "iso:country":"AU",
    "sg:address":"81 Olsen Ave",
    "sg:city":"Labrador",
    "sg:classifiers":[
        {
            "category":"Manufacturing",
            "subcategory":"Tobacco Products",
            "type":"Manufacturing & Wholesale Goods"
        }
    ],
    "sg:phone":"+61 7 5529 3717",
    "sg:postcode":"4215",
    "sg:province":"QLD",
    "sg:tags":[
        "car",
        "truck",
        "cleaning",
        "equipment"
    ],
    "wof:name":"Viney R A",
    "wof:placetype":"venue"
},
  "geometry": {"coordinates":[153.387115478,-27.941614151],"type":"Point"}
}