{
  "type": "Feature",
  "properties": {
    "iso:country":"AU",
    "sg:address":"27 Claremont Ave",
    "sg:city":"Greenacre",
    "sg:classifiers":[
        {
            "category":"Banks & Credit Unions",
            "subcategory":"Bureau De Change",
            "type":"Services"
        }
    ],
    "sg:phone":"+61 2 9796 4370",
    "sg:postcode":"2190",
    "sg:province":"NSW",
    "sg:tags":[
        "supply",
        "equipment",
        "beating",
        "panel"
    ],
    "wof:name":"N A Auto Colour",
    "wof:placetype":"venue"
},
  "geometry": {"coordinates":[151.038773,-33.899746],"type":"Point"}
}