{
  "type": "Feature",
  "properties": {
    "addr:full":"11 Oak St Seymour VIC 3660",
    "addr:housenumber":"11",
    "addr:postcode":"3660",
    "addr:street":"Oak St",
    "iso:country":"AU",
    "sg:address":"11 Oak St",
    "sg:city":"Seymour",
    "sg:classifiers":[
        {
            "category":"Retail",
            "subcategory":"Storage",
            "type":"Services"
        }
    ],
    "sg:phone":"+61 3 5799 1599",
    "sg:postcode":"3660",
    "sg:province":"VIC",
    "wof:name":"Seymour Caravan & Self Storage",
    "wof:placetype":"venue"
},
  "geometry": {"coordinates":[145.14454650900001,-37.0266151428],"type":"Point"}
}