{
  "type": "Feature",
  "properties": {
    "iso:country":"AU",
    "sg:address":"Rosella St",
    "sg:city":"Dural",
    "sg:classifiers":[
        {
            "category":"Wholesale",
            "subcategory":"Electrical",
            "type":"Manufacturing & Wholesale Goods"
        }
    ],
    "sg:phone":"+61 2 9651 1022",
    "sg:postcode":"2158",
    "sg:province":"NSW",
    "sg:tags":[
        "equipment",
        "testing",
        "electronic",
        "electric"
    ],
    "wof:name":"Automated Electronic Systems",
    "wof:placetype":"venue"
},
  "geometry": {"coordinates":[151.05427551299999,-33.680305481],"type":"Point"}
}