{
  "type": "Feature",
  "properties": {
    "addr:full":"Contempo Crt Bendigo VIC 3550",
    "addr:postcode":"3550",
    "addr:street":"Contempo",
    "iso:country":"AU",
    "sg:address":"Contempo Crt",
    "sg:city":"Bendigo",
    "sg:classifiers":[
        {
            "category":"Professional",
            "subcategory":"Printing & Photocopies",
            "type":"Services"
        }
    ],
    "sg:phone":"+61 3 5441 6333",
    "sg:postcode":"3550",
    "sg:province":"VIC",
    "sg:tags":[
        "photocopier"
    ],
    "wof:name":"Southern Cross Office Equipment",
    "wof:placetype":"venue"
},
  "geometry": {"coordinates":[144.28216552699999,-36.7626914978],"type":"Point"}
}