{
  "type": "Feature",
  "properties": {
    "addr:full":"Kangaroo Hills Rd Blampied VIC 3364",
    "addr:postcode":"3364",
    "addr:street":"Hills Rd",
    "iso:country":"AU",
    "sg:address":"Kangaroo Hills Rd",
    "sg:city":"Blampied",
    "sg:classifiers":[
        {
            "category":"Farming",
            "subcategory":"Fish & Marine Products",
            "type":"Manufacturing & Wholesale Goods"
        }
    ],
    "sg:phone":"+61 3 5345 7408",
    "sg:postcode":"3364",
    "sg:province":"VIC",
    "sg:tags":[
        "organic"
    ],
    "wof:name":"Captains Creek Organic Wines",
    "wof:placetype":"venue"
},
  "geometry": {"coordinates":[144.01869201700001,-37.3490180969],"type":"Point"}
}