{
  "type": "Feature",
  "properties": {
    "addr:full":"38 Helston St Balwyn North VIC 3104",
    "addr:housenumber":"38",
    "addr:postcode":"3104",
    "addr:street":"Helston St",
    "iso:country":"AU",
    "sg:address":"38 Helston St",
    "sg:city":"Balwyn North",
    "sg:classifiers":[
        {
            "category":"Professional",
            "subcategory":"Art Services",
            "type":"Services"
        }
    ],
    "sg:phone":"+61 418 502 990",
    "sg:postcode":"3104",
    "sg:province":"VIC",
    "sg:tags":[
        "graphic",
        "designer"
    ],
    "wof:name":"Studio Soreal",
    "wof:placetype":"venue"
},
  "geometry": {"coordinates":[145.09526062,-37.7845993042],"type":"Point"}
}