{
  "type": "Feature",
  "properties": {
    "addr:full":"35/ 1 Jubilee Ave Warriewood NSW 2102",
    "addr:housenumber":"35 / 1",
    "addr:postcode":"2102",
    "addr:street":"Jubilee Ave",
    "iso:country":"AU",
    "sg:address":"35/ 1 Jubilee Ave",
    "sg:city":"Warriewood",
    "sg:classifiers":[
        {
            "category":"Shopping",
            "type":"Retail Goods"
        }
    ],
    "sg:phone":"+61 1800 655 129",
    "sg:postcode":"2102",
    "sg:province":"NSW",
    "sg:tags":[
        "equipment",
        "safety",
        "accessory"
    ],
    "wof:name":"Safety Equipment Australia Pty Ltd",
    "wof:placetype":"venue"
},
  "geometry": {"coordinates":[151.28564499999999,-33.679611],"type":"Point"}
}