{
  "type": "Feature",
  "properties": {
    "iso:country":"AU",
    "sg:address":"72b Fitzroy St",
    "sg:city":"Surry Hills",
    "sg:classifiers":[
        {
            "category":"Arts & Performance",
            "subcategory":"Art Gallery",
            "type":"Entertainment"
        }
    ],
    "sg:phone":"+61 2 9331 6637",
    "sg:postcode":"2010",
    "sg:province":"NSW",
    "wof:name":"Somedays",
    "wof:placetype":"venue"
},
  "geometry": {"coordinates":[151.21556091299999,-33.8848953247],"type":"Point"}
}