{
  "type": "Feature",
  "properties": {
    "addr:full":"Shop 2 Exit 67 170 Old Pacific Hwy Oxenford QLD 4210",
    "addr:housenumber":"shop 2;170",
    "addr:postcode":"4210",
    "addr:street":"Exit 67;Old Pacific Hwy",
    "iso:country":"AU",
    "sg:address":"Shop 2 Exit 67 170 Old Pacific Hwy",
    "sg:city":"Oxenford",
    "sg:classifiers":[
        {
            "category":"Fast Food",
            "type":"Food & Drink"
        }
    ],
    "sg:phone":"+61 7 5502 3200",
    "sg:postcode":"4210",
    "sg:province":"QLD",
    "sg:tags":[
        "away",
        "take"
    ],
    "wof:name":"Domino's Pizza",
    "wof:placetype":"venue"
},
  "geometry": {"coordinates":[153.31430053700001,-27.885219574],"type":"Point"}
}