{
  "type": "Feature",
  "properties": {
    "addr:full":"Level 1, 75 George St Parramatta NSW 2150",
    "addr:housenumber":"75",
    "addr:postcode":"2150",
    "addr:street":"George St",
    "iso:country":"AU",
    "sg:address":"Level 1, 75 George St",
    "sg:city":"Parramatta",
    "sg:classifiers":[
        {
            "category":"Professional",
            "subcategory":"Employment Agencies",
            "type":"Services"
        }
    ],
    "sg:phone":"+61 2 9865 6500",
    "sg:postcode":"2150",
    "sg:province":"NSW",
    "wof:name":"Jonathan Wren",
    "wof:placetype":"venue"
},
  "geometry": {"coordinates":[150.97651672399999,-33.8504600525],"type":"Point"}
}