{
  "type": "Feature",
  "properties": {
    "iso:country":"AU",
    "sg:address":"Unit 2/ 229 Centre Rd",
    "sg:city":"Bentleigh",
    "sg:classifiers":[
        {
            "category":"Train Station",
            "subcategory":"Light Rail",
            "type":"Transportation"
        }
    ],
    "sg:phone":"+61 3 9503 4877",
    "sg:postcode":"3204",
    "sg:province":"VIC",
    "sg:tags":[
        "survey",
        "traffic"
    ],
    "wof:name":"C.S. Traffic Surveys",
    "wof:placetype":"venue"
},
  "geometry": {"coordinates":[145.028244,-37.917038],"type":"Point"}
}