{
  "type": "Feature",
  "properties": {
    "iso:country":"AU",
    "sg:address":"39 Murndal Drv",
    "sg:city":"Donvale",
    "sg:classifiers":[
        {
            "category":"Professional",
            "subcategory":"Art Services",
            "type":"Services"
        }
    ],
    "sg:phone":"+61 3 9874 1431",
    "sg:postcode":"3111",
    "sg:province":"VIC",
    "sg:tags":[
        "interior",
        "decorator"
    ],
    "wof:name":"Moonshine Interior Productions",
    "wof:placetype":"venue"
},
  "geometry": {"coordinates":[145.19331359899999,-37.7988624573],"type":"Point"}
}