{
  "type": "Feature",
  "properties": {
    "addr:full":"Unit 3 5 Hudson Ave Castle Hill NSW 2154",
    "addr:housenumber":"5",
    "addr:postcode":"2154",
    "addr:street":"Hudson Ave",
    "iso:country":"AU",
    "sg:address":"Unit 3 5 Hudson Ave",
    "sg:city":"Castle Hill",
    "sg:classifiers":[
        {
            "category":"Shopping",
            "subcategory":"Crafts & Fabrics",
            "type":"Retail Goods"
        }
    ],
    "sg:phone":"+61 2 9659 4100",
    "sg:postcode":"2154",
    "sg:province":"NSW",
    "sg:tags":[
        "supply"
    ],
    "wof:name":"Glamour Beads",
    "wof:placetype":"venue"
},
  "geometry": {"coordinates":[150.98570251500001,-33.7287330627],"type":"Point"}
}