{
  "type": "Feature",
  "properties": {
    "iso:country":"AU",
    "sg:address":"86 Ntaba Rd",
    "sg:city":"Belmont North",
    "sg:classifiers":[
        {
            "category":"Home & Garden",
            "subcategory":"Building Materials",
            "type":"Retail Goods"
        }
    ],
    "sg:phone":"+61 2 4948 8182",
    "sg:postcode":"2280",
    "sg:province":"NSW",
    "sg:tags":[
        "merchant",
        "glass",
        "glazier"
    ],
    "wof:name":"A One Newcastle Glass Service",
    "wof:placetype":"venue"
},
  "geometry": {"coordinates":[151.683059692,-33.0133361816],"type":"Point"}
}