{
  "type": "Feature",
  "properties": {
    "addr:full":"2 Newman St Wangaratta VIC 3677",
    "addr:housenumber":"2",
    "addr:postcode":"3677",
    "addr:street":"Newman St",
    "iso:country":"AU",
    "sg:address":"2 Newman St",
    "sg:city":"Wangaratta",
    "sg:classifiers":[
        {
            "category":"Utilities",
            "type":"Services"
        }
    ],
    "sg:phone":"+61 3 5721 5687",
    "sg:postcode":"3677",
    "sg:province":"VIC",
    "sg:tags":[
        "equipment",
        "towing"
    ],
    "wof:name":"Exhaust & Offroad Services Pty Ltd",
    "wof:placetype":"venue"
},
  "geometry": {"coordinates":[146.31393432600001,-36.3666687012],"type":"Point"}
}