{
  "type": "Feature",
  "properties": {
    "addr:full":"34 Industrial Drv Sunshine VIC 3020",
    "addr:housenumber":"34",
    "addr:postcode":"3020",
    "addr:street":"Industrial Drv",
    "iso:country":"AU",
    "sg:address":"34 Industrial Drv",
    "sg:city":"Sunshine",
    "sg:classifiers":[
        {
            "category":"Professional",
            "subcategory":"Engineering",
            "type":"Services"
        }
    ],
    "sg:phone":"+61 3 9312 0050",
    "sg:postcode":"3020",
    "sg:province":"VIC",
    "sg:tags":[
        "engineer"
    ],
    "wof:name":"D H Engineering",
    "wof:placetype":"venue"
},
  "geometry": {"coordinates":[144.81213399999999,-37.81031],"type":"Point"}
}