{
  "type": "Feature",
  "properties": {
    "addr:full":"Cnr Lucca & Pavitt Sts Wyong North NSW 2259",
    "addr:postcode":"2259",
    "iso:country":"AU",
    "sg:address":"Cnr Lucca & Pavitt Sts",
    "sg:city":"Wyong North",
    "sg:classifiers":[
        {
            "category":"Home & Garden",
            "subcategory":"Building Materials",
            "type":"Retail Goods"
        }
    ],
    "sg:phone":"+61 2 4352 2535",
    "sg:postcode":"2259",
    "sg:province":"NSW",
    "sg:tags":[
        "wall",
        "frame",
        "truss",
        "roof"
    ],
    "wof:name":"Timberfast Building Supplies",
    "wof:placetype":"venue"
},
  "geometry": {"coordinates":[151.41911315900001,-33.3097610474],"type":"Point"}
}