{
  "type": "Feature",
  "properties": {
    "iso:country":"AU",
    "sg:address":"21 Rusden Rd",
    "sg:city":"Blaxland",
    "sg:classifiers":[
        {
            "category":"Banks & Credit Unions",
            "subcategory":"Financial Services",
            "type":"Services"
        }
    ],
    "sg:phone":"+61 2 4739 1123",
    "sg:postcode":"2774",
    "sg:province":"NSW",
    "sg:tags":[
        "planning"
    ],
    "wof:name":"Tony Hunt, BSc, Dip FP- Auth. Rep. of Winchcombe Carson Financial Planning",
    "wof:placetype":"venue"
},
  "geometry": {"coordinates":[150.62306213400001,-33.7434234619],"type":"Point"}
}