{
  "type": "Feature",
  "properties": {
    "addr:full":"6 Cottage La Hackham SA 5163",
    "addr:housenumber":"6",
    "addr:postcode":"5163",
    "addr:street":"Cottage La",
    "iso:country":"AU",
    "sg:address":"6 Cottage La",
    "sg:city":"Hackham",
    "sg:classifiers":[
        {
            "category":"Retail",
            "subcategory":"Auto Repair",
            "type":"Services"
        }
    ],
    "sg:phone":"+61 8 8382 4404",
    "sg:postcode":"5163",
    "sg:province":"SA",
    "sg:tags":[
        "repairer",
        "motor",
        "engineer"
    ],
    "wof:name":"Cottage Lane Automotive Specialists",
    "wof:placetype":"venue"
},
  "geometry": {"coordinates":[138.527053833,-35.1504135132],"type":"Point"}
}