{
  "type": "Feature",
  "properties": {
    "iso:country":"AU",
    "sg:address":"Shop 5 Brockman St",
    "sg:city":"Gingin",
    "sg:classifiers":[
        {
            "category":"Food & Beverages",
            "subcategory":"Liquor & Beverages",
            "type":"Retail Goods"
        }
    ],
    "sg:phone":"+61 8 9575 2573",
    "sg:postcode":"6503",
    "sg:province":"WA",
    "sg:tags":[
        "store"
    ],
    "wof:name":"Cellarbrations",
    "wof:placetype":"venue"
},
  "geometry": {"coordinates":[115.904678,-31.347494],"type":"Point"}
}