{
  "type": "Feature",
  "properties": {
    "addr:full":"Pialba Pl Main St Pialba QLD 4655",
    "addr:postcode":"4655",
    "addr:street":"Pl Main St",
    "iso:country":"AU",
    "sg:address":"Pialba Pl Main St",
    "sg:city":"Pialba",
    "sg:classifiers":[
        {
            "category":"Personal",
            "subcategory":"Beauty Salon",
            "type":"Services"
        }
    ],
    "sg:phone":"+61 7 4128 3166",
    "sg:postcode":"4655",
    "sg:province":"QLD",
    "sg:tags":[
        "hairdresser"
    ],
    "wof:name":"Helga's Hairdressing",
    "wof:placetype":"venue"
},
  "geometry": {"coordinates":[152.83824200000001,-25.287683],"type":"Point"}
}