{
  "type": "Feature",
  "properties": {
    "iso:country":"AU",
    "sg:address":"550 Wilson Rd",
    "sg:city":"Buderim",
    "sg:classifiers":[
        {
            "category":"Home & Garden",
            "subcategory":"Building Materials",
            "type":"Retail Goods"
        }
    ],
    "sg:phone":"+61 7 5456 2497",
    "sg:postcode":"4556",
    "sg:province":"QLD",
    "sg:tags":[
        "retaining",
        "wall"
    ],
    "wof:name":"Coast Constructions",
    "wof:placetype":"venue"
},
  "geometry": {"coordinates":[153.03831481899999,-26.7197761536],"type":"Point"}
}