{
  "type": "Feature",
  "properties": {
    "iso:country":"AU",
    "sg:address":"Lot 10 Old Coach Rd",
    "sg:city":"Aldinga",
    "sg:classifiers":[
        {
            "category":"Health Services",
            "subcategory":"Health Practitioner",
            "type":"Services"
        }
    ],
    "sg:phone":"+61 8 8557 7161",
    "sg:postcode":"5173",
    "sg:province":"SA",
    "sg:tags":[
        "herbalist"
    ],
    "wof:name":"TLC Herbs",
    "wof:placetype":"venue"
},
  "geometry": {"coordinates":[138.48292541500001,-35.2664031982],"type":"Point"}
}