{
  "type": "Feature",
  "properties": {
    "addr:full":"Klugh St Muttaburra QLD 4732",
    "addr:postcode":"4732",
    "addr:street":"Klugh St",
    "iso:country":"AU",
    "sg:address":"Klugh St",
    "sg:city":"Muttaburra",
    "sg:classifiers":[
        {
            "category":"Farming",
            "subcategory":"Farm & Veterinary Services",
            "type":"Manufacturing & Wholesale Goods"
        }
    ],
    "sg:phone":"+61 7 4658 7187",
    "sg:postcode":"4732",
    "sg:province":"QLD",
    "sg:tags":[
        "shearing",
        "contractor"
    ],
    "wof:name":"J & H Shearing",
    "wof:placetype":"venue"
},
  "geometry": {"coordinates":[144.55029300000001,-22.595299],"type":"Point"}
}