{
  "type": "Feature",
  "properties": {
    "iso:country":"AU",
    "sg:address":"50 Henley Beach Rd",
    "sg:city":"Henley Beach South",
    "sg:classifiers":[
        {
            "category":"Personal",
            "subcategory":"Beauty Salon",
            "type":"Services"
        }
    ],
    "sg:phone":"+61 8 8356 6760",
    "sg:postcode":"5022",
    "sg:province":"SA",
    "sg:tags":[
        "hairdresser"
    ],
    "wof:name":"Scissors On Henley",
    "wof:placetype":"venue"
},
  "geometry": {"coordinates":[138.502044678,-34.9252738953],"type":"Point"}
}