{
  "type": "Feature",
  "properties": {
    "addr:full":"Wedmore Rd Emu Heights NSW 2750",
    "addr:postcode":"2750",
    "addr:street":"Wedmore Rd",
    "iso:country":"AU",
    "sg:address":"Wedmore Rd",
    "sg:city":"Emu Heights",
    "sg:classifiers":[
        {
            "category":"Education",
            "subcategory":"School",
            "type":"Public Place"
        }
    ],
    "sg:phone":"+61 2 4735 1290",
    "sg:postcode":"2750",
    "sg:province":"NSW",
    "sg:tags":[
        "state",
        "-",
        "nsw"
    ],
    "wof:name":"Emu Heights Public School",
    "wof:placetype":"venue"
},
  "geometry": {"coordinates":[150.648834228,-33.742980957],"type":"Point"}
}