{
  "type": "Feature",
  "properties": {
    "addr:full":"Suite 1 15-23 Anderson St Chatswood NSW 2067",
    "addr:housenumber":"15-23",
    "addr:postcode":"2067",
    "addr:street":"Anderson St",
    "iso:country":"AU",
    "sg:address":"Suite 1 15-23 Anderson St",
    "sg:city":"Chatswood",
    "sg:classifiers":[
        {
            "category":"Real Estate",
            "subcategory":"Real Estate Agent",
            "type":"Services"
        }
    ],
    "sg:phone":"+61 2 9411 8044",
    "sg:postcode":"2067",
    "sg:province":"NSW",
    "wof:name":"Seiwa Realty Pty Ltd",
    "wof:placetype":"venue"
},
  "geometry": {"coordinates":[151.18287658700001,-33.7952270508],"type":"Point"}
}