{
  "type": "Feature",
  "properties": {
    "addr:full":"2- 3 Reeves Crt Breakwater VIC 3219",
    "addr:housenumber":"3",
    "addr:postcode":"3219",
    "addr:street":"Reeves Crt",
    "iso:country":"AU",
    "sg:address":"2- 3 Reeves Crt",
    "sg:city":"Breakwater",
    "sg:classifiers":[
        {
            "category":"Building & Trades",
            "subcategory":"Construction",
            "type":"Services"
        }
    ],
    "sg:phone":"+61 3 5222 4526",
    "sg:postcode":"3219",
    "sg:province":"VIC",
    "sg:tags":[
        "earth",
        "excavating",
        "moving",
        "contractor"
    ],
    "wof:name":"Vic Pits",
    "wof:placetype":"venue"
},
  "geometry": {"coordinates":[144.37376403799999,-38.1846694946],"type":"Point"}
}