{
  "type": "Feature",
  "properties": {
    "iso:country":"AU",
    "sg:address":"Shop 7 143 Racecourse Rd",
    "sg:city":"Ascot",
    "sg:classifiers":[
        {
            "category":"Health Services",
            "subcategory":"Dentist",
            "type":"Services"
        }
    ],
    "sg:phone":"+61 7 3630 0288",
    "sg:postcode":"4007",
    "sg:province":"QLD",
    "wof:name":"Ang Linda Dental Surgery",
    "wof:placetype":"venue"
},
  "geometry": {"coordinates":[153.065536,-27.432405],"type":"Point"}
}