{
  "type": "Feature",
  "properties": {
    "addr:full":"10 Barron Gorge Rd Lake Placid QLD 4878",
    "addr:housenumber":"10",
    "addr:postcode":"4878",
    "addr:street":"Barron Gorge Rd",
    "iso:country":"AU",
    "sg:address":"10 Barron Gorge Rd",
    "sg:city":"Lake Placid",
    "sg:classifiers":[
        {
            "category":"Organizations",
            "subcategory":"Non-profit Organization",
            "type":"Services"
        }
    ],
    "sg:phone":"+61 7 4039 0018",
    "sg:postcode":"4878",
    "sg:province":"QLD",
    "sg:tags":[
        "support",
        "disability",
        "organisation"
    ],
    "wof:name":"Voluntary Euthanasia Society Of Queensland",
    "wof:placetype":"venue"
},
  "geometry": {"coordinates":[145.67481994600001,-16.8673877716],"type":"Point"}
}