{
  "type": "Feature",
  "properties": {
    "iso:country":"AU",
    "sg:address":"Shp5/ 90 Melbourne Hill Rd",
    "sg:city":"Warrandyte",
    "sg:classifiers":[
        {
            "category":"Social Services",
            "type":"Services"
        }
    ],
    "sg:phone":"+61 3 9844 4852",
    "sg:postcode":"3113",
    "sg:province":"VIC",
    "sg:tags":[
        "kinesiology"
    ],
    "wof:name":"Inner Balance",
    "wof:placetype":"venue"
},
  "geometry": {"coordinates":[145.20611572300001,-37.7473945618],"type":"Point"}
}