{
  "type": "Feature",
  "properties": {
    "addr:full":"20 Lemana St Devonport TAS 7310",
    "addr:housenumber":"20",
    "addr:postcode":"7310",
    "addr:street":"Lemana St",
    "iso:country":"AU",
    "sg:address":"20 Lemana St",
    "sg:city":"Devonport",
    "sg:classifiers":[
        {
            "category":"Personal",
            "subcategory":"Beauty Salon",
            "type":"Services"
        }
    ],
    "sg:phone":"+61 3 6423 3877",
    "sg:postcode":"7310",
    "sg:province":"TAS",
    "sg:tags":[
        "hairdresser"
    ],
    "wof:name":"Lyn's Hair Productions",
    "wof:placetype":"venue"
},
  "geometry": {"coordinates":[146.35610961899999,-41.1981048584],"type":"Point"}
}