{
  "type": "Feature",
  "properties": {
    "addr:full":"Wyoming Village Shopping Centre, Cnr Pacific Hwy & Renwick St Wyoming NSW 2250",
    "addr:postcode":"2250",
    "addr:street":"Cnr Pacific Hwy & Renwick St",
    "iso:country":"AU",
    "sg:address":"Wyoming Village Shopping Centre, Cnr Pacific Hwy & Renwick St",
    "sg:city":"Wyoming",
    "sg:classifiers":[
        {
            "category":"Communications",
            "subcategory":"Film & Video Production",
            "type":"Services"
        }
    ],
    "sg:phone":"+61 2 4329 3766",
    "sg:postcode":"2250",
    "sg:province":"NSW",
    "sg:tags":[
        "dvd",
        "library"
    ],
    "wof:name":"Video Ezy",
    "wof:placetype":"venue"
},
  "geometry": {"coordinates":[151.349243164,-33.4094581604],"type":"Point"}
}