{
  "type": "Feature",
  "properties": {
    "iso:country":"AU",
    "sg:address":"Suite 14, 207 Albany St",
    "sg:city":"North Gosford",
    "sg:classifiers":[
        {
            "category":"Professional",
            "subcategory":"Accounting & Tax Preparation",
            "type":"Services"
        }
    ],
    "sg:phone":"+61 2 4324 5466",
    "sg:postcode":"2250",
    "sg:province":"NSW",
    "sg:tags":[
        "accountant",
        "auditor"
    ],
    "wof:name":"Robson Chartered Accountants",
    "wof:placetype":"venue"
},
  "geometry": {"coordinates":[151.34515380900001,-33.4343147278],"type":"Point"}
}