{
  "type": "Feature",
  "properties": {
    "iso:country":"AU",
    "sg:address":"130 Anzac Hwy",
    "sg:city":"Glandore",
    "sg:classifiers":[
        {
            "category":"Home & Garden",
            "subcategory":"Furniture",
            "type":"Retail Goods"
        }
    ],
    "sg:phone":"+61 8 8351 0666",
    "sg:postcode":"5037",
    "sg:province":"SA",
    "sg:tags":[
        "business"
    ],
    "sg:website":"http://www.backcentre.com.au",
    "wof:name":"Back Centre And Specialty Seating",
    "wof:placetype":"venue"
},
  "geometry": {"coordinates":[138.56907653799999,-34.9550170898],"type":"Point"}
}