{
  "type": "Feature",
  "properties": {
    "addr:full":"47 Dalgarno St Coonabarabran NSW 2357",
    "addr:housenumber":"47",
    "addr:postcode":"2357",
    "addr:street":"Dalgarno St",
    "iso:country":"AU",
    "sg:address":"47 Dalgarno St",
    "sg:city":"Coonabarabran",
    "sg:classifiers":[
        {
            "category":"Travel",
            "subcategory":"Hotels & Motels",
            "type":"Entertainment"
        }
    ],
    "sg:phone":"+61 2 6842 2444",
    "sg:postcode":"2357",
    "sg:province":"NSW",
    "wof:name":"Clock Tower Motor Inn",
    "wof:placetype":"venue"
},
  "geometry": {"coordinates":[149.278930664,-31.2727851868],"type":"Point"}
}