{
  "type": "Feature",
  "properties": {
    "iso:country":"AU",
    "sg:address":"52 Main St",
    "sg:city":"Maldon",
    "sg:classifiers":[
        {
            "category":"Cafe",
            "type":"Food & Drink"
        }
    ],
    "sg:phone":"+61 3 5475 2022",
    "sg:postcode":"3463",
    "sg:province":"VIC",
    "wof:name":"Maldon Cafe",
    "wof:placetype":"venue"
},
  "geometry": {"coordinates":[143.901855469,-36.826675415],"type":"Point"}
}