{
  "type": "Feature",
  "properties": {
    "iso:country":"AU",
    "sg:address":"Ste 2/ 154 Bentinck St",
    "sg:city":"Bathurst",
    "sg:classifiers":[
        {
            "category":"Health Services",
            "subcategory":"Dentist",
            "type":"Services"
        }
    ],
    "sg:phone":"+61 2 6331 7816",
    "sg:postcode":"2795",
    "sg:province":"NSW",
    "wof:name":"Hazenet Hazenet Pty Ltd",
    "wof:placetype":"venue"
},
  "geometry": {"coordinates":[149.577301025,-33.4233665466],"type":"Point"}
}