{
  "type": "Feature",
  "properties": {
    "addr:full":"306-308 Melbourne Rd Newport VIC 3015",
    "addr:housenumber":"306-308",
    "addr:postcode":"3015",
    "addr:street":"Melbourne Rd",
    "iso:country":"AU",
    "sg:address":"306-308 Melbourne Rd",
    "sg:city":"Newport",
    "sg:classifiers":[
        {
            "category":"Fast Food",
            "type":"Food & Drink"
        }
    ],
    "sg:phone":"+61 3 9399 5099",
    "sg:postcode":"3015",
    "sg:province":"VIC",
    "sg:tags":[
        "away",
        "take"
    ],
    "wof:name":"Souvlakihut Newport",
    "wof:placetype":"venue"
},
  "geometry": {"coordinates":[144.885986328,-37.8463554382],"type":"Point"}
}