{
  "type": "Feature",
  "properties": {
    "addr:full":"Eyre Hwy Ceduna SA 5690",
    "addr:postcode":"5690",
    "addr:street":"Eyre Hwy",
    "iso:country":"AU",
    "sg:address":"Eyre Hwy",
    "sg:city":"Ceduna",
    "sg:classifiers":[
        {
            "category":"Autos & Motor Vehicles",
            "subcategory":"Fuel & Gas Station",
            "type":"Retail Goods"
        }
    ],
    "sg:phone":"+61 8 8625 2208",
    "sg:postcode":"5690",
    "sg:province":"SA",
    "wof:name":"BP Highway One Roadhouse",
    "wof:placetype":"venue"
},
  "geometry": {"coordinates":[133.67453002900001,-32.121131897],"type":"Point"}
}