{
  "type": "Feature",
  "properties": {
    "iso:country":"AU",
    "sg:address":"PO Box 236",
    "sg:city":"Albany Creek",
    "sg:classifiers":[
        {
            "category":"Professional",
            "subcategory":"Art Services",
            "type":"Services"
        }
    ],
    "sg:phone":"+61 7 3205 9264",
    "sg:postcode":"4035",
    "sg:province":"QLD",
    "sg:tags":[
        "floral",
        "teacher"
    ],
    "wof:name":"Raylees School of Floral Dzine",
    "wof:placetype":"venue"
},
  "geometry": {"coordinates":[152.96537799999999,-27.34589],"type":"Point"}
}