{
  "type": "Feature",
  "properties": {
    "addr:full":"14 Kingswell Ave Rostrevor SA 5073",
    "addr:housenumber":"14",
    "addr:postcode":"5073",
    "addr:street":"Kingswell Ave",
    "iso:country":"AU",
    "sg:address":"14 Kingswell Ave",
    "sg:city":"Rostrevor",
    "sg:classifiers":[
        {
            "category":"Retail",
            "subcategory":"Repair Shop",
            "type":"Services"
        }
    ],
    "sg:phone":"+61 8 8337 7376",
    "sg:postcode":"5073",
    "sg:province":"SA",
    "sg:tags":[
        "machine",
        "repairs",
        "part",
        "dryer",
        "washing"
    ],
    "wof:name":"Atlas Appliance Services",
    "wof:placetype":"venue"
},
  "geometry": {"coordinates":[138.67576599099999,-34.8945045471],"type":"Point"}
}