{
  "type": "Feature",
  "properties": {
    "addr:full":"236B Dorset Rd Boronia VIC 3155",
    "addr:housenumber":"236b",
    "addr:postcode":"3155",
    "addr:street":"Dorset Rd",
    "iso:country":"AU",
    "sg:address":"236B Dorset Rd",
    "sg:city":"Boronia",
    "sg:classifiers":[
        {
            "category":"Professional",
            "subcategory":"Accounting & Tax Preparation",
            "type":"Services"
        }
    ],
    "sg:phone":"+61 3 9762 5022",
    "sg:postcode":"3155",
    "sg:province":"VIC",
    "sg:tags":[
        "accountant",
        "auditor"
    ],
    "wof:name":"Dudley & Associates",
    "wof:placetype":"venue"
},
  "geometry": {"coordinates":[145.28587341299999,-37.8609619141],"type":"Point"}
}