{
  "type": "Feature",
  "properties": {
    "addr:full":"55 Queen St Woollahra NSW 2025",
    "addr:housenumber":"55",
    "addr:postcode":"2025",
    "addr:street":"Queen St",
    "iso:country":"AU",
    "sg:address":"55 Queen St",
    "sg:city":"Woollahra",
    "sg:classifiers":[
        {
            "category":"Food & Beverages",
            "subcategory":"Supermarket",
            "type":"Retail Goods"
        }
    ],
    "sg:phone":"+61 2 9328 6888",
    "sg:postcode":"2025",
    "sg:province":"NSW",
    "sg:tags":[
        "grocery",
        "store"
    ],
    "wof:name":"Simon Johnsen Purveyor Of Quality Foods",
    "wof:placetype":"venue"
},
  "geometry": {"coordinates":[151.23524475100001,-33.8889122009],"type":"Point"}
}