{
  "type": "Feature",
  "properties": {
    "addr:full":"5 Head Sail Crt Currumbin Waters QLD 4223",
    "addr:housenumber":"5",
    "addr:postcode":"4223",
    "addr:street":"Head Sail Crt",
    "iso:country":"AU",
    "sg:address":"5 Head Sail Crt",
    "sg:city":"Currumbin Waters",
    "sg:classifiers":[
        {
            "category":"Home & Garden",
            "subcategory":"Carpets & Floor Coverings",
            "type":"Retail Goods"
        }
    ],
    "sg:phone":"+61 7 5598 1801",
    "sg:postcode":"4223",
    "sg:province":"QLD",
    "sg:tags":[
        "tile",
        "wall",
        "layer"
    ],
    "wof:name":"Burns Lionel",
    "wof:placetype":"venue"
},
  "geometry": {"coordinates":[153.46730041500001,-28.15391922],"type":"Point"}
}