{
  "type": "Feature",
  "properties": {
    "iso:country":"AU",
    "sg:address":"Unit 9/46- 50 Regent St",
    "sg:city":"Richmond",
    "sg:classifiers":[
        {
            "category":"Organizations",
            "subcategory":"Professional Association",
            "type":"Services"
        }
    ],
    "sg:phone":"+61 3 9415 9877",
    "sg:postcode":"3121",
    "sg:province":"VIC",
    "sg:tags":[
        "web",
        "internet"
    ],
    "wof:name":"d-lin E8 Design Pty Ltd",
    "wof:placetype":"venue"
},
  "geometry": {"coordinates":[144.99186706500001,-37.811958313],"type":"Point"}
}