{
  "type": "Feature",
  "properties": {
    "iso:country":"AU",
    "sg:address":"470 Gardeners Rd",
    "sg:city":"Alexandria",
    "sg:classifiers":[
        {
            "category":"Autos & Motor Vehicles",
            "subcategory":"Automobile Sales",
            "type":"Retail Goods"
        }
    ],
    "sg:phone":"+61 2 9693 9000",
    "sg:postcode":"2015",
    "sg:province":"NSW",
    "sg:tags":[
        "car",
        "used"
    ],
    "wof:name":"Porsche Centre Sydney South",
    "wof:placetype":"venue"
},
  "geometry": {"coordinates":[151.19500732399999,-33.9210853577],"type":"Point"}
}