{
  "type": "Feature",
  "properties": {
    "addr:full":"Cnr Park & Bedford Rds Homebush NSW 2140",
    "addr:postcode":"2140",
    "iso:country":"AU",
    "sg:address":"Cnr Park & Bedford Rds",
    "sg:city":"Homebush",
    "sg:classifiers":[
        {
            "category":"Farming",
            "subcategory":"Dairy Farm",
            "type":"Manufacturing & Wholesale Goods"
        }
    ],
    "sg:phone":"+61 2 9764 2290",
    "sg:postcode":"2140",
    "sg:province":"NSW",
    "sg:tags":[
        "wholesaler",
        "product",
        "mfrs"
    ],
    "wof:name":"Organic Farm Foods Eco Farms",
    "wof:placetype":"venue"
},
  "geometry": {"coordinates":[151.07537841800001,-33.8602333069],"type":"Point"}
}