{
  "type": "Feature",
  "properties": {
    "addr:full":"6 Redwood St Heidelberg West VIC 3081",
    "addr:housenumber":"6",
    "addr:postcode":"3081",
    "addr:street":"Redwood St",
    "iso:country":"AU",
    "sg:address":"6 Redwood St",
    "sg:city":"Heidelberg West",
    "sg:classifiers":[
        {
            "category":"Home & Garden",
            "subcategory":"Home Furnishings",
            "type":"Retail Goods"
        }
    ],
    "sg:phone":"+61 3 9459 3221",
    "sg:postcode":"3081",
    "sg:province":"VIC",
    "sg:tags":[
        "shower",
        "screen"
    ],
    "wof:name":"Heidelberg Shower Screens Pty Ltd",
    "wof:placetype":"venue"
},
  "geometry": {"coordinates":[145.04148864699999,-37.7454071045],"type":"Point"}
}