{
  "type": "Feature",
  "properties": {
    "addr:full":"El Alamein Rd Port Augusta SA 5700",
    "addr:postcode":"5700",
    "addr:street":"El Alamein Rd",
    "iso:country":"AU",
    "sg:address":"El Alamein Rd",
    "sg:city":"Port Augusta",
    "sg:classifiers":[
        {
            "category":"Recreation",
            "type":"Entertainment"
        }
    ],
    "sg:phone":"+61 8 8642 2699",
    "sg:postcode":"5700",
    "sg:province":"SA",
    "sg:tags":[
        "supply",
        "outdoor",
        "adventure",
        "activity"
    ],
    "wof:name":"Port Augusta Aquatic & Outdoor Centre",
    "wof:placetype":"venue"
},
  "geometry": {"coordinates":[137.76040649399999,-32.4912986755],"type":"Point"}
}