{
  "type": "Feature",
  "properties": {
    "addr:full":"Cnr Of Woodcroft Drive & Richmond Rd Woodcroft NSW 2767",
    "addr:postcode":"2767",
    "addr:street":"Rd",
    "iso:country":"AU",
    "sg:address":"Cnr Of Woodcroft Drive & Richmond Rd",
    "sg:city":"Woodcroft",
    "sg:classifiers":[
        {
            "category":"Autos & Motor Vehicles",
            "subcategory":"Fuel & Gas Station",
            "type":"Retail Goods"
        }
    ],
    "sg:phone":"+61 2 9831 8979",
    "sg:postcode":"2767",
    "sg:province":"NSW",
    "wof:name":"BP Australia Pty Ltd",
    "wof:placetype":"venue"
},
  "geometry": {"coordinates":[150.87820434599999,-33.7528038025],"type":"Point"}
}