{
  "type": "Feature",
  "properties": {
    "addr:full":"Factory 3, 1 Tova Drv Carrum Downs VIC 3201",
    "addr:housenumber":"1",
    "addr:postcode":"3201",
    "addr:street":"Tova Drv",
    "iso:country":"AU",
    "sg:address":"Factory 3, 1 Tova Drv",
    "sg:city":"Carrum Downs",
    "sg:classifiers":[
        {
            "category":"Home & Garden",
            "subcategory":"Hardware",
            "type":"Retail Goods"
        }
    ],
    "sg:phone":"+61 3 9770 8400",
    "sg:postcode":"3201",
    "sg:province":"VIC",
    "sg:tags":[
        "nut",
        "bolt"
    ],
    "wof:name":"Bolts Galore",
    "wof:placetype":"venue"
},
  "geometry": {"coordinates":[145.16390999999999,-38.098511],"type":"Point"}
}