{
  "type": "Feature",
  "properties": {
    "addr:full":"Medihelp Medical Centre 122 Olsen Ave Labrador QLD 4215",
    "addr:housenumber":"122",
    "addr:postcode":"4215",
    "addr:street":"Olsen Ave",
    "iso:country":"AU",
    "sg:address":"Medihelp Medical Centre 122 Olsen Ave",
    "sg:city":"Labrador",
    "sg:classifiers":[
        {
            "category":"Health Services",
            "subcategory":"Health Practitioner",
            "type":"Services"
        }
    ],
    "sg:phone":"+61 403 286 614",
    "sg:postcode":"4215",
    "sg:province":"QLD",
    "sg:tags":[
        "psychologist"
    ],
    "wof:name":"Aldrige Samantha",
    "wof:placetype":"venue"
},
  "geometry": {"coordinates":[153.38638305699999,-27.9429321289],"type":"Point"}
}