{
  "type": "Feature",
  "properties": {
    "iso:country":"AU",
    "sg:address":"Shop 3, 178 Keen St",
    "sg:city":"Lismore",
    "sg:classifiers":[
        {
            "category":"Cafe",
            "type":"Food & Drink"
        }
    ],
    "sg:phone":"+61 2 6622 4664",
    "sg:postcode":"2480",
    "sg:province":"NSW",
    "wof:name":"Lismore Cafe Giardino",
    "wof:placetype":"venue"
},
  "geometry": {"coordinates":[153.27789306599999,-28.8101921082],"type":"Point"}
}