{
  "type": "Feature",
  "properties": {
    "addr:full":"Shp 7/ 59 Tansey Drv Tanah Merah QLD 4128",
    "addr:housenumber":"/ 59",
    "addr:postcode":"4128",
    "addr:street":"Tansey Drv",
    "iso:country":"AU",
    "sg:address":"Shp 7/ 59 Tansey Drv",
    "sg:city":"Tanah Merah",
    "sg:classifiers":[
        {
            "category":"Personal",
            "subcategory":"Beauty Salon",
            "type":"Services"
        }
    ],
    "sg:phone":"+61 7 3806 1805",
    "sg:postcode":"4128",
    "sg:province":"QLD",
    "sg:tags":[
        "hairdresser"
    ],
    "wof:name":"Ciao Bella Beaute Salon",
    "wof:placetype":"venue"
},
  "geometry": {"coordinates":[153.17546081500001,-27.6777381897],"type":"Point"}
}