{
  "type": "Feature",
  "properties": {
    "iso:country":"AU",
    "sg:address":"Sandridge Rd",
    "sg:city":"Bunbury",
    "sg:classifiers":[
        {
            "category":"Manufacturing",
            "subcategory":"Food",
            "type":"Manufacturing & Wholesale Goods"
        }
    ],
    "sg:phone":"+61 8 9791 4149",
    "sg:postcode":"6230",
    "sg:province":"WA",
    "sg:tags":[
        "function",
        "catering"
    ],
    "wof:name":"KFC",
    "wof:placetype":"venue"
},
  "geometry": {"coordinates":[115.65014600000001,-33.341118],"type":"Point"}
}