{
  "type": "Feature",
  "properties": {
    "addr:full":"PO Box 135 Wallan VIC 3756",
    "addr:postcode":"3756",
    "iso:country":"AU",
    "sg:address":"PO Box 135",
    "sg:city":"Wallan",
    "sg:classifiers":[
        {
            "category":"Building & Trades",
            "subcategory":"Construction",
            "type":"Services"
        }
    ],
    "sg:phone":"+61 408 360 245",
    "sg:postcode":"3756",
    "sg:province":"VIC",
    "sg:tags":[
        "contractor"
    ],
    "wof:name":"Stabilised Earth Constructions",
    "wof:placetype":"venue"
},
  "geometry": {"coordinates":[145.01965300000001,-37.349861],"type":"Point"}
}