{
  "type": "Feature",
  "properties": {
    "addr:full":"Level 4 406 Collins St Melbourne VIC 3000",
    "addr:housenumber":"406",
    "addr:postcode":"3000",
    "addr:street":"Collins St",
    "iso:country":"AU",
    "sg:address":"Level 4 406 Collins St",
    "sg:city":"Melbourne",
    "sg:classifiers":[
        {
            "category":"Banks & Credit Unions",
            "subcategory":"Investment Brokerage",
            "type":"Services"
        }
    ],
    "sg:phone":"+61 3 9606 0539",
    "sg:postcode":"3000",
    "sg:province":"VIC",
    "wof:name":"Shaw George Financial Services",
    "wof:placetype":"venue"
},
  "geometry": {"coordinates":[144.960845947,-37.8170127869],"type":"Point"}
}