{
  "type": "Feature",
  "properties": {
    "addr:full":"404 Oxford St Bondi Junction NSW 2022",
    "addr:housenumber":"404",
    "addr:postcode":"2022",
    "addr:street":"Oxford St",
    "iso:country":"AU",
    "sg:address":"404 Oxford St",
    "sg:city":"Bondi Junction",
    "sg:classifiers":[
        {
            "category":"Shopping",
            "type":"Retail Goods"
        }
    ],
    "sg:phone":"+61 2 9389 2800",
    "sg:postcode":"2022",
    "sg:province":"NSW",
    "sg:tags":[
        "new age",
        "product"
    ],
    "wof:name":"Rabbit In The Moon",
    "wof:placetype":"venue"
},
  "geometry": {"coordinates":[151.247756958,-33.8917236328],"type":"Point"}
}