{
  "type": "Feature",
  "properties": {
    "addr:full":"60 Mortlake Rd Warrnambool VIC 3280",
    "addr:housenumber":"60",
    "addr:postcode":"3280",
    "addr:street":"Mortlake Rd",
    "iso:country":"AU",
    "sg:address":"60 Mortlake Rd",
    "sg:city":"Warrnambool",
    "sg:classifiers":[
        {
            "category":"Personal",
            "subcategory":"Massage",
            "type":"Services"
        }
    ],
    "sg:phone":"+61 408 555 780",
    "sg:postcode":"3280",
    "sg:province":"VIC",
    "sg:tags":[
        "therapy"
    ],
    "wof:name":"Terry O'Shannessy Remedial Massage Therapist",
    "wof:placetype":"venue"
},
  "geometry": {"coordinates":[142.49327087399999,-38.3693008423],"type":"Point"}
}