{
  "type": "Feature",
  "properties": {
    "iso:country":"AU",
    "sg:address":"Unit 3, 160 Smith St",
    "sg:city":"Darwin",
    "sg:classifiers":[
        {
            "category":"Retail",
            "subcategory":"Car Wash",
            "type":"Services"
        }
    ],
    "sg:phone":"+61 437 167 715",
    "sg:postcode":"0800",
    "sg:province":"NT",
    "sg:tags":[
        "truck",
        "cleaning"
    ],
    "wof:name":"Mobile Wash Away",
    "wof:placetype":"venue"
},
  "geometry": {"coordinates":[130.83348083499999,-12.4548387527],"type":"Point"}
}