{
  "type": "Feature",
  "properties": {
    "iso:country":"AU",
    "sg:address":"8 North St",
    "sg:city":"Nathalia",
    "sg:classifiers":[
        {
            "category":"Health Services",
            "subcategory":"Doctor",
            "type":"Services"
        }
    ],
    "sg:phone":"+61 3 5866 2201",
    "sg:postcode":"3638",
    "sg:province":"VIC",
    "sg:tags":[
        "medical",
        "practitioner"
    ],
    "wof:name":"Poon S K",
    "wof:placetype":"venue"
},
  "geometry": {"coordinates":[145.20191955600001,-36.0543060303],"type":"Point"}
}