{
  "type": "Feature",
  "properties": {
    "addr:full":"24 Robyn St Tamworth NSW 2340",
    "addr:housenumber":"24",
    "addr:postcode":"2340",
    "addr:street":"Robyn St",
    "iso:country":"AU",
    "sg:address":"24 Robyn St",
    "sg:city":"Tamworth",
    "sg:classifiers":[
        {
            "category":"Home & Garden",
            "subcategory":"Building Materials",
            "type":"Retail Goods"
        }
    ],
    "sg:phone":"+61 2 6765 9222",
    "sg:postcode":"2340",
    "sg:province":"NSW",
    "sg:tags":[
        "lawn",
        "cutting",
        "maintenance"
    ],
    "wof:name":"McInnes JE & SR",
    "wof:placetype":"venue"
},
  "geometry": {"coordinates":[150.91595459000001,-31.1071434021],"type":"Point"}
}