{
  "type": "Feature",
  "properties": {
    "addr:full":"41 Miller Drv Happy Valley SA 5159",
    "addr:housenumber":"41",
    "addr:postcode":"5159",
    "addr:street":"Miller Drv",
    "iso:country":"AU",
    "sg:address":"41 Miller Drv",
    "sg:city":"Happy Valley",
    "sg:classifiers":[
        {
            "category":"Utilities",
            "subcategory":"Electric",
            "type":"Services"
        }
    ],
    "sg:phone":"+61 8 8381 3613",
    "sg:postcode":"5159",
    "sg:province":"SA",
    "sg:tags":[
        "electrical",
        "contractor"
    ],
    "wof:name":"Chapman K & C Electrical",
    "wof:placetype":"venue"
},
  "geometry": {"coordinates":[138.57705688499999,-35.0914916992],"type":"Point"}
}