{
  "type": "Feature",
  "properties": {
    "addr:full":"9/ 29-39 Kirkham Rd Keysborough VIC 3173",
    "addr:housenumber":"/ 29-39",
    "addr:postcode":"3173",
    "addr:street":"Kirkham Rd",
    "iso:country":"AU",
    "sg:address":"9/ 29-39 Kirkham Rd",
    "sg:city":"Keysborough",
    "sg:classifiers":[
        {
            "category":"Utilities",
            "subcategory":"Electric",
            "type":"Services"
        }
    ],
    "sg:phone":"+61 3 9798 7070",
    "sg:postcode":"3173",
    "sg:province":"VIC",
    "sg:tags":[
        "electrical",
        "contractor"
    ],
    "wof:name":"John Wade Electrical Services Pty Ltd",
    "wof:placetype":"venue"
},
  "geometry": {"coordinates":[145.186737061,-37.9962806702],"type":"Point"}
}