{
  "type": "Feature",
  "properties": {
    "addr:full":"273 Ingham Rd Garbutt QLD 4814",
    "addr:housenumber":"273",
    "addr:postcode":"4814",
    "addr:street":"Ingham Rd",
    "iso:country":"AU",
    "sg:address":"273 Ingham Rd",
    "sg:city":"Garbutt",
    "sg:classifiers":[
        {
            "category":"Professional",
            "subcategory":"Computer Services",
            "type":"Services"
        }
    ],
    "sg:phone":"+61 7 4789 6500",
    "sg:postcode":"4814",
    "sg:province":"QLD",
    "sg:tags":[
        "tele-communications",
        "consultant"
    ],
    "wof:name":"Silcar Communications",
    "wof:placetype":"venue"
},
  "geometry": {"coordinates":[146.776535,-19.265451],"type":"Point"}
}