{
  "type": "Feature",
  "properties": {
    "addr:full":"2 Thurbro Drv Keysborough VIC 3173",
    "addr:housenumber":"2",
    "addr:postcode":"3173",
    "addr:street":"Thurbro Drv",
    "iso:country":"AU",
    "sg:address":"2 Thurbro Drv",
    "sg:city":"Keysborough",
    "sg:classifiers":[
        {
            "category":"Health Services",
            "subcategory":"Doctor",
            "type":"Services"
        }
    ],
    "sg:phone":"+61 3 9798 6783",
    "sg:postcode":"3173",
    "sg:province":"VIC",
    "sg:tags":[
        "medical",
        "practitioner"
    ],
    "wof:name":"Huq M A & M Drs",
    "wof:placetype":"venue"
},
  "geometry": {"coordinates":[145.18345642099999,-37.9874534607],"type":"Point"}
}