{
  "type": "Feature",
  "properties": {
    "addr:full":"Lvl 9/ 14 Queens Rd Melbourne VIC 3004",
    "addr:housenumber":"/ 14",
    "addr:postcode":"3004",
    "addr:street":"Queens Rd",
    "iso:country":"AU",
    "sg:address":"Lvl 9/ 14 Queens Rd",
    "sg:city":"Melbourne",
    "sg:classifiers":[
        {
            "category":"Banks & Credit Unions",
            "subcategory":"Bank",
            "type":"Services"
        }
    ],
    "sg:phone":"+61 3 9820 6600",
    "sg:postcode":"3004",
    "sg:province":"VIC",
    "sg:tags":[
        "broker",
        "mortgage"
    ],
    "wof:name":"Combined Financial Services Management",
    "wof:placetype":"venue"
},
  "geometry": {"coordinates":[144.97854614299999,-37.8432655334],"type":"Point"}
}