{
  "type": "Feature",
  "properties": {
    "iso:country":"AU",
    "sg:address":"247 Pitt St",
    "sg:city":"Sydney",
    "sg:classifiers":[
        {
            "category":"Travel",
            "subcategory":"Travel Agent",
            "type":"Entertainment"
        }
    ],
    "sg:phone":"+61 2 9261 2800",
    "sg:postcode":"2000",
    "sg:province":"NSW",
    "sg:tags":[
        "consultant"
    ],
    "wof:name":"Northern Territory Travel",
    "wof:placetype":"venue"
},
  "geometry": {"coordinates":[151.20802307100001,-33.8714179993],"type":"Point"}
}