{
  "type": "Feature",
  "properties": {
    "addr:full":"2924 Foresthill Fernvale Rd Lowood QLD 4311",
    "addr:housenumber":"2924",
    "addr:postcode":"4311",
    "addr:street":"Foresthill Fernvale Rd",
    "iso:country":"AU",
    "sg:address":"2924 Foresthill Fernvale Rd",
    "sg:city":"Lowood",
    "sg:classifiers":[
        {
            "category":"Professional",
            "type":"Services"
        }
    ],
    "sg:phone":"+61 7 5426 1146",
    "sg:postcode":"4311",
    "sg:province":"QLD",
    "sg:tags":[
        "transport"
    ],
    "wof:name":"Toohill's Interstate Transport",
    "wof:placetype":"venue"
},
  "geometry": {"coordinates":[152.58624267600001,-27.4683971405],"type":"Point"}
}