{
  "type": "Feature",
  "properties": {
    "iso:country":"AU",
    "sg:address":"16/18 Albert St",
    "sg:city":"Ferntree Gully Upper",
    "sg:classifiers":[
        {
            "category":"Professional",
            "subcategory":"Employment Agencies",
            "type":"Services"
        }
    ],
    "sg:phone":"+61 3 9756 0417",
    "sg:postcode":"3156",
    "sg:province":"VIC",
    "wof:name":"Groundwork Employment Service",
    "wof:placetype":"venue"
},
  "geometry": {"coordinates":[145.31265258799999,-37.8986740112],"type":"Point"}
}