{
  "type": "Feature",
  "properties": {
    "iso:country":"AU",
    "sg:address":"Shop 2023 318 Magill Rd",
    "sg:city":"Indooroopilly",
    "sg:classifiers":[
        {
            "category":"Shopping",
            "subcategory":"Clothing, Apparel, & Fashions",
            "type":"Retail Goods"
        }
    ],
    "sg:phone":"+61 7 3878 5441",
    "sg:postcode":"4068",
    "sg:province":"QLD",
    "sg:tags":[
        "jean"
    ],
    "wof:name":"Westco Jeans (Aust) Pty Ltd",
    "wof:placetype":"venue"
},
  "geometry": {"coordinates":[152.97247314399999,-27.4977474213],"type":"Point"}
}