{
  "type": "Feature",
  "properties": {
    "addr:full":"47 Ash Rd Leopold VIC 3224",
    "addr:housenumber":"47",
    "addr:postcode":"3224",
    "addr:street":"Ash Rd",
    "iso:country":"AU",
    "sg:address":"47 Ash Rd",
    "sg:city":"Leopold",
    "sg:classifiers":[
        {
            "category":"Fast Food",
            "type":"Food & Drink"
        }
    ],
    "sg:phone":"+61 3 5250 3210",
    "sg:postcode":"3224",
    "sg:province":"VIC",
    "sg:tags":[
        "away",
        "take"
    ],
    "wof:name":"Leopold Fish & Chips",
    "wof:placetype":"venue"
},
  "geometry": {"coordinates":[144.468231,-38.19384],"type":"Point"}
}