{
  "type": "Feature",
  "properties": {
    "addr:full":"46 Williamson St Bendigo VIC 3550",
    "addr:housenumber":"46",
    "addr:postcode":"3550",
    "addr:street":"Williamson St",
    "iso:country":"AU",
    "sg:address":"46 Williamson St",
    "sg:city":"Bendigo",
    "sg:classifiers":[
        {
            "category":"Building & Trades",
            "subcategory":"Equipment Rental",
            "type":"Services"
        }
    ],
    "sg:phone":"+61 3 5443 4299",
    "sg:postcode":"3550",
    "sg:province":"VIC",
    "sg:tags":[
        "fitness"
    ],
    "wof:name":"Bicknells Sports Centre",
    "wof:placetype":"venue"
},
  "geometry": {"coordinates":[144.28146362300001,-36.7598876953],"type":"Point"}
}