{
  "type": "Feature",
  "properties": {
    "iso:country":"AU",
    "sg:address":"12a Rae St",
    "sg:city":"Randwick",
    "sg:classifiers":[
        {
            "category":"Communications",
            "subcategory":"News Services",
            "type":"Services"
        }
    ],
    "sg:phone":"+61 2 9314 6666",
    "sg:postcode":"2031",
    "sg:province":"NSW",
    "sg:tags":[
        "information",
        "tourist",
        "attractions"
    ],
    "wof:name":"Country Club Tours",
    "wof:placetype":"venue"
},
  "geometry": {"coordinates":[151.24378967300001,-33.9125289917],"type":"Point"}
}