{
  "type": "Feature",
  "properties": {
    "addr:full":"105 Radium St Welshpool WA 6106",
    "addr:housenumber":"105",
    "addr:postcode":"6106",
    "addr:street":"Radium St",
    "iso:country":"AU",
    "sg:address":"105 Radium St",
    "sg:city":"Welshpool",
    "sg:classifiers":[
        {
            "category":"Home & Garden",
            "subcategory":"Carpets & Floor Coverings",
            "type":"Retail Goods"
        }
    ],
    "sg:phone":"+61 8 9358 3100",
    "sg:postcode":"6106",
    "sg:province":"WA",
    "sg:tags":[
        "mattress"
    ],
    "wof:name":"SlumberCare",
    "wof:placetype":"venue"
},
  "geometry": {"coordinates":[115.93264770499999,-31.9989032745],"type":"Point"}
}