{
  "type": "Feature",
  "properties": {
    "iso:country":"AU",
    "sg:address":"22 South St",
    "sg:city":"Forster",
    "sg:classifiers":[
        {
            "category":"Education",
            "subcategory":"Music School",
            "type":"Public Place"
        }
    ],
    "sg:phone":"+61 2 6555 4062",
    "sg:postcode":"2428",
    "sg:province":"NSW",
    "sg:tags":[
        "therapy",
        "relaxation"
    ],
    "wof:name":"Paul F. King Massage & Associates",
    "wof:placetype":"venue"
},
  "geometry": {"coordinates":[152.514603,-32.189209],"type":"Point"}
}