{
  "type": "Feature",
  "properties": {
    "addr:full":"7 Gary Player Crs Parkwood QLD 4214",
    "addr:housenumber":"7",
    "addr:postcode":"4214",
    "addr:street":"Gary Player Crs",
    "iso:country":"AU",
    "sg:address":"7 Gary Player Crs",
    "sg:city":"Parkwood",
    "sg:classifiers":[
        {
            "category":"Freight",
            "type":"Transportation"
        }
    ],
    "sg:phone":"+61 418 879 213",
    "sg:postcode":"4214",
    "sg:province":"QLD",
    "sg:tags":[
        "transport",
        "refrigerated"
    ],
    "wof:name":"Ice Cold Freight Pty Ltd",
    "wof:placetype":"venue"
},
  "geometry": {"coordinates":[153.36415100100001,-28.021112442],"type":"Point"}
}