{
  "type": "Feature",
  "properties": {
    "iso:country":"AU",
    "sg:address":"64 Collins St",
    "sg:city":"Kiama",
    "sg:classifiers":[
        {
            "category":"Education",
            "subcategory":"Kindergarten",
            "type":"Public Place"
        }
    ],
    "sg:phone":"+61 2 4232 1249",
    "sg:postcode":"2533",
    "sg:province":"NSW",
    "sg:tags":[
        "pre-schools"
    ],
    "wof:name":"Collins Street Kindy Kiama",
    "wof:placetype":"venue"
},
  "geometry": {"coordinates":[150.85235595699999,-34.6697769165],"type":"Point"}
}