{
  "type": "Feature",
  "properties": {
    "addr:full":"49/ 67 Sages Rd Glenroy VIC 3046",
    "addr:housenumber":"49 / 67",
    "addr:postcode":"3046",
    "addr:street":"Sages Rd",
    "iso:country":"AU",
    "sg:address":"49/ 67 Sages Rd",
    "sg:city":"Glenroy",
    "sg:classifiers":[
        {
            "category":"Home & Garden",
            "subcategory":"Hardware",
            "type":"Retail Goods"
        }
    ],
    "sg:phone":"+61 3 9357 1633",
    "sg:postcode":"3046",
    "sg:province":"VIC",
    "sg:tags":[
        "generating",
        "set",
        "generator"
    ],
    "wof:name":"Foster Plastics Inds",
    "wof:placetype":"venue"
},
  "geometry": {"coordinates":[144.95823669399999,-37.6989440918],"type":"Point"}
}