{
  "type": "Feature",
  "properties": {
    "addr:full":"50 Gillespie Rd St Albans VIC 3021",
    "addr:housenumber":"50",
    "addr:postcode":"3021",
    "addr:street":"Gillespie Rd",
    "iso:country":"AU",
    "sg:address":"50 Gillespie Rd",
    "sg:city":"St Albans",
    "sg:classifiers":[
        {
            "category":"Building & Trades",
            "subcategory":"Construction",
            "type":"Services"
        }
    ],
    "sg:phone":"+61 3 9356 0469",
    "sg:postcode":"3021",
    "sg:province":"VIC",
    "sg:tags":[
        "rendering",
        "cement"
    ],
    "wof:name":"RHM Plastering",
    "wof:placetype":"venue"
},
  "geometry": {"coordinates":[144.78329500000001,-37.734257],"type":"Point"}
}