{
  "type": "Feature",
  "properties": {
    "addr:full":"44 Alfred Rd Glen Iris VIC 3146",
    "addr:housenumber":"44",
    "addr:postcode":"3146",
    "addr:street":"Alfred Rd",
    "iso:country":"AU",
    "sg:address":"44 Alfred Rd",
    "sg:city":"Glen Iris",
    "sg:classifiers":[
        {
            "category":"Wholesale",
            "subcategory":"Machinery & Supplies",
            "type":"Manufacturing & Wholesale Goods"
        }
    ],
    "sg:phone":"+61 3 9809 1280",
    "sg:postcode":"3146",
    "sg:province":"VIC",
    "sg:tags":[
        "equipment",
        "welding"
    ],
    "wof:name":"Japan Mechatronics Pty Ltd",
    "wof:placetype":"venue"
},
  "geometry": {"coordinates":[145.08900451700001,-37.8538703918],"type":"Point"}
}