{
  "type": "Feature",
  "properties": {
    "addr:full":"Patton St Broken Hill NSW 2880",
    "addr:postcode":"2880",
    "addr:street":"Patton St",
    "iso:country":"AU",
    "sg:address":"Patton St",
    "sg:city":"Broken Hill",
    "sg:classifiers":[
        {
            "category":"Organizations",
            "subcategory":"Community Association",
            "type":"Services"
        }
    ],
    "sg:phone":"+61 8 8087 2053",
    "sg:postcode":"2880",
    "sg:province":"NSW",
    "sg:tags":[
        "organisation",
        "family",
        "welfare"
    ],
    "wof:name":"Womens Domestic Violence Court Assistance Scheme",
    "wof:placetype":"venue"
},
  "geometry": {"coordinates":[141.47000122099999,-31.9733409882],"type":"Point"}
}