{
  "type": "Feature",
  "properties": {
    "addr:full":"2/ 29 Collinsvale St Rocklea QLD 4106",
    "addr:housenumber":"/ 29",
    "addr:postcode":"4106",
    "addr:street":"Collinsvale St",
    "iso:country":"AU",
    "sg:address":"2/ 29 Collinsvale St",
    "sg:city":"Rocklea",
    "sg:classifiers":[
        {
            "category":"Building & Trades",
            "subcategory":"Construction",
            "type":"Services"
        }
    ],
    "sg:phone":"+61 7 3275 1775",
    "sg:postcode":"4106",
    "sg:province":"QLD",
    "sg:tags":[
        "road",
        "contractor"
    ],
    "wof:name":"STS APPLIED SYSTEMS (QLD) PTY LTD",
    "wof:placetype":"venue"
},
  "geometry": {"coordinates":[152.99424743599999,-27.559305191],"type":"Point"}
}