{
  "type": "Feature",
  "properties": {
    "addr:full":"359 Main Rd Toukley NSW 2263",
    "addr:housenumber":"359",
    "addr:postcode":"2263",
    "addr:street":"Main Rd",
    "iso:country":"AU",
    "sg:address":"359 Main Rd",
    "sg:city":"Toukley",
    "sg:classifiers":[
        {
            "category":"Home & Garden",
            "subcategory":"Hardware",
            "type":"Retail Goods"
        }
    ],
    "sg:phone":"+61 2 4393 3033",
    "sg:postcode":"2263",
    "sg:province":"NSW",
    "sg:tags":[
        "compressor",
        "air"
    ],
    "wof:name":"Charmhaven Hire & Equipment Rental Centre",
    "wof:placetype":"venue"
},
  "geometry": {"coordinates":[151.54951500000001,-33.266659],"type":"Point"}
}