{
  "type": "Feature",
  "properties": {
    "addr:full":"471 Warrandyte Rd Langwarrin South VIC 3911",
    "addr:housenumber":"471",
    "addr:postcode":"3911",
    "addr:street":"Warrandyte Rd",
    "iso:country":"AU",
    "sg:address":"471 Warrandyte Rd",
    "sg:city":"Langwarrin South",
    "sg:classifiers":[
        {
            "category":"Building & Trades",
            "subcategory":"Cleaning & Sanitation",
            "type":"Services"
        }
    ],
    "sg:phone":"+61 3 5971 5952",
    "sg:postcode":"3911",
    "sg:province":"VIC",
    "sg:tags":[
        "window"
    ],
    "wof:name":"Bayview Winclean",
    "wof:placetype":"venue"
},
  "geometry": {"coordinates":[145.182739258,-38.1935997009],"type":"Point"}
}