{
  "type": "Feature",
  "properties": {
    "iso:country":"AU",
    "sg:address":"8 Eastern Pl",
    "sg:city":"Hawthorn East",
    "sg:classifiers":[
        {
            "category":"Professional",
            "subcategory":"Art Services",
            "type":"Services"
        }
    ],
    "sg:phone":"+61 3 9813 3442",
    "sg:postcode":"3123",
    "sg:province":"VIC",
    "sg:tags":[
        "graphic",
        "designer"
    ],
    "wof:name":"Creative Ethos Pty Ltd",
    "wof:placetype":"venue"
},
  "geometry": {"coordinates":[145.04544067399999,-37.8233680725],"type":"Point"}
}