{
  "type": "Feature",
  "properties": {
    "addr:full":"Level 3, 100 Wickham St Fortitude Valley QLD 4006",
    "addr:housenumber":"100",
    "addr:postcode":"4006",
    "addr:street":"Wickham St",
    "iso:country":"AU",
    "sg:address":"Level 3, 100 Wickham St",
    "sg:city":"Fortitude Valley",
    "sg:classifiers":[
        {
            "category":"Professional",
            "subcategory":"Employment Agencies",
            "type":"Services"
        }
    ],
    "sg:phone":"+61 7 3606 7000",
    "sg:postcode":"4006",
    "sg:province":"QLD",
    "sg:tags":[
        "provider",
        "internet"
    ],
    "wof:name":"Connect Internet Solutions",
    "wof:placetype":"venue"
},
  "geometry": {"coordinates":[153.031646728,-27.4597110748],"type":"Point"}
}