{
  "type": "Feature",
  "properties": {
    "iso:country":"AU",
    "sg:address":"64 Grant St",
    "sg:city":"Alexandra",
    "sg:classifiers":[
        {
            "category":"Travel",
            "subcategory":"Hotels & Motels",
            "type":"Entertainment"
        }
    ],
    "sg:phone":"+61 3 5772 1014",
    "sg:postcode":"3714",
    "sg:province":"VIC",
    "sg:tags":[
        "accommodation"
    ],
    "wof:name":"Alexandra Hotel",
    "wof:placetype":"venue"
},
  "geometry": {"coordinates":[145.709472656,-37.1915473938],"type":"Point"}
}