{
  "type": "Feature",
  "properties": {
    "addr:full":"Frederick St Charlestown NSW 2290",
    "addr:postcode":"2290",
    "addr:street":"Frederick St",
    "iso:country":"AU",
    "sg:address":"Frederick St",
    "sg:city":"Charlestown",
    "sg:classifiers":[
        {
            "category":"Education",
            "subcategory":"School",
            "type":"Public Place"
        }
    ],
    "sg:phone":"+61 2 4943 4063",
    "sg:postcode":"2290",
    "sg:province":"NSW",
    "sg:tags":[
        "state",
        "-",
        "nsw"
    ],
    "wof:name":"Charlestown Primary",
    "wof:placetype":"venue"
},
  "geometry": {"coordinates":[151.69383239699999,-32.9652328491],"type":"Point"}
}