{
  "type": "Feature",
  "properties": {
    "iso:country":"AU",
    "sg:address":"663 Beechwood Rd",
    "sg:city":"Beechwood",
    "sg:classifiers":[
        {
            "category":"Food & Beverages",
            "subcategory":"Groceries & Convenience Stores",
            "type":"Retail Goods"
        }
    ],
    "sg:phone":"+61 2 6585 6130",
    "sg:postcode":"2446",
    "sg:province":"NSW",
    "wof:name":"Beechwood General Store & Cafe",
    "wof:placetype":"venue"
},
  "geometry": {"coordinates":[152.668793,-31.435905],"type":"Point"}
}