{
  "type": "Feature",
  "properties": {
    "iso:country":"AU",
    "sg:address":"Pacific Hwy",
    "sg:city":"Cundletown",
    "sg:classifiers":[
        {
            "category":"Retail",
            "subcategory":"Repair Shop",
            "type":"Services"
        }
    ],
    "sg:phone":"+61 2 6553 9209",
    "sg:postcode":"2430",
    "sg:province":"NSW",
    "sg:tags":[
        "upholsterer"
    ],
    "wof:name":"Else Upholstery",
    "wof:placetype":"venue"
},
  "geometry": {"coordinates":[152.519257,-31.907122],"type":"Point"}
}