{
  "type": "Feature",
  "properties": {
    "addr:full":"126 Dandenong Rd Frankston VIC 3199",
    "addr:housenumber":"126",
    "addr:postcode":"3199",
    "addr:street":"Dandenong Rd",
    "iso:country":"AU",
    "sg:address":"126 Dandenong Rd",
    "sg:city":"Frankston",
    "sg:classifiers":[
        {
            "category":"Banks & Credit Unions",
            "subcategory":"Financial Services",
            "type":"Services"
        }
    ],
    "sg:phone":"+61 1800 810 730",
    "sg:postcode":"3199",
    "sg:province":"VIC",
    "sg:tags":[
        "finance",
        "motor",
        "vehicle"
    ],
    "wof:name":"Complete Car Finance",
    "wof:placetype":"venue"
},
  "geometry": {"coordinates":[145.087493897,-37.9840354919],"type":"Point"}
}