{
  "type": "Feature",
  "properties": {
    "addr:full":"15a Awaba St Mosman NSW 2088",
    "addr:housenumber":"15a",
    "addr:postcode":"2088",
    "addr:street":"Awaba St",
    "iso:country":"AU",
    "sg:address":"15a Awaba St",
    "sg:city":"Mosman",
    "sg:classifiers":[
        {
            "category":"Government",
            "subcategory":"Court House",
            "type":"Public Place"
        }
    ],
    "sg:phone":"+61 2 9969 7674",
    "sg:postcode":"2088",
    "sg:province":"NSW",
    "sg:tags":[
        "personal",
        "marriage",
        "family",
        "counselling"
    ],
    "wof:name":"Adolescent Family & Relationship Counselling",
    "wof:placetype":"venue"
},
  "geometry": {"coordinates":[151.24856567399999,-33.8215332031],"type":"Point"}
}