{
  "type": "Feature",
  "properties": {
    "iso:country":"AU",
    "sg:address":"35 Woodland St",
    "sg:city":"Balgowlah Heights",
    "sg:classifiers":[
        {
            "category":"Wholesale",
            "subcategory":"Medical Equipment & Supplies",
            "type":"Manufacturing & Wholesale Goods"
        }
    ],
    "sg:phone":"+61 2 9948 8172",
    "sg:postcode":"2093",
    "sg:province":"NSW",
    "sg:tags":[
        "dental"
    ],
    "wof:name":"ISO Diamond Australia",
    "wof:placetype":"venue"
},
  "geometry": {"coordinates":[151.260055542,-33.8058738708],"type":"Point"}
}