{
  "type": "Feature",
  "properties": {
    "addr:full":"Lvl one 7/448 458 Parramatta Rd Strathfield NSW 2135",
    "addr:housenumber":"/ 448 458",
    "addr:postcode":"2135",
    "addr:street":"Parramatta Rd",
    "iso:country":"AU",
    "sg:address":"Lvl one 7/448 458 Parramatta Rd",
    "sg:city":"Strathfield",
    "sg:classifiers":[
        {
            "category":"Banks & Credit Unions",
            "subcategory":"Financial Services",
            "type":"Services"
        }
    ],
    "sg:phone":"+61 2 9715 3704",
    "sg:postcode":"2135",
    "sg:province":"NSW",
    "sg:tags":[
        "financier"
    ],
    "wof:name":"Home Equity Pty Ltd",
    "wof:placetype":"venue"
},
  "geometry": {"coordinates":[151.097930908,-33.8678817749],"type":"Point"}
}