{
  "type": "Feature",
  "properties": {
    "iso:country":"AU",
    "sg:address":"740 Woodville Rd",
    "sg:city":"Villawood",
    "sg:classifiers":[
        {
            "category":"Shopping",
            "subcategory":"Music",
            "type":"Retail Goods"
        }
    ],
    "sg:phone":"+61 2 9686 2285",
    "sg:postcode":"2163",
    "sg:province":"NSW",
    "sg:tags":[
        "instrument",
        "musical"
    ],
    "wof:name":"Chris Marshalls Piano House",
    "wof:placetype":"venue"
},
  "geometry": {"coordinates":[150.97346496599999,-33.8886833191],"type":"Point"}
}