{
  "type": "Feature",
  "properties": {
    "addr:full":"&#039;Hillside&#039; 190 Princes Hwy Figtree NSW 2525",
    "addr:housenumber":"190",
    "addr:postcode":"2525",
    "addr:street":"Princes Hwy",
    "iso:country":"AU",
    "sg:address":"&#039;Hillside&#039; 190 Princes Hwy",
    "sg:city":"Figtree",
    "sg:classifiers":[
        {
            "category":"Health Services",
            "subcategory":"Doctor",
            "type":"Services"
        }
    ],
    "sg:phone":"+61 2 4272 7384",
    "sg:postcode":"2525",
    "sg:province":"NSW",
    "sg:tags":[
        "occupational",
        "safety"
    ],
    "wof:name":"Smart Occupational Health & Safety",
    "wof:placetype":"venue"
},
  "geometry": {"coordinates":[150.86204528799999,-34.4348716736],"type":"Point"}
}