{
  "type": "Feature",
  "properties": {
    "addr:full":"Woodlands Rd Narrikup WA 6326",
    "addr:postcode":"6326",
    "addr:street":"Woodlands Rd",
    "iso:country":"AU",
    "sg:address":"Woodlands Rd",
    "sg:city":"Narrikup",
    "sg:classifiers":[
        {
            "category":"Farming",
            "subcategory":"Farm",
            "type":"Manufacturing & Wholesale Goods"
        }
    ],
    "sg:phone":"+61 8 9853 2041",
    "sg:postcode":"6326",
    "sg:province":"WA",
    "sg:tags":[
        "farmer"
    ],
    "wof:name":"Matthews H W & E J",
    "wof:placetype":"venue"
},
  "geometry": {"coordinates":[117.833648682,-34.7260131836],"type":"Point"}
}