{
  "type": "Feature",
  "properties": {
    "addr:full":"18 Lyndhurst St Richmond VIC 3121",
    "addr:housenumber":"18",
    "addr:postcode":"3121",
    "addr:street":"Lyndhurst St",
    "iso:country":"AU",
    "sg:address":"18 Lyndhurst St",
    "sg:city":"Richmond",
    "sg:classifiers":[
        {
            "category":"Professional",
            "subcategory":"Art Services",
            "type":"Services"
        }
    ],
    "sg:phone":"+61 3 9427 0554",
    "sg:postcode":"3121",
    "sg:province":"VIC",
    "sg:tags":[
        "artist"
    ],
    "wof:name":"Andrew Gemmill Artist",
    "wof:placetype":"venue"
},
  "geometry": {"coordinates":[145.000442505,-37.8195877075],"type":"Point"}
}