{
  "type": "Feature",
  "properties": {
    "addr:full":"Waterfront City Docklands Dr West Melbourne VIC 3003",
    "addr:postcode":"3003",
    "addr:street":"Dr",
    "iso:country":"AU",
    "sg:address":"Waterfront City Docklands Dr",
    "sg:city":"West Melbourne",
    "sg:classifiers":[
        {
            "category":"Ice Cream",
            "type":"Food & Drink"
        }
    ],
    "sg:phone":"+61 3 9326 9842",
    "sg:postcode":"3003",
    "sg:province":"VIC",
    "sg:tags":[
        "retail"
    ],
    "wof:name":"Dairy Bell Ice Cream (Retail) Pty Ltd",
    "wof:placetype":"venue"
},
  "geometry": {"coordinates":[144.93513488799999,-37.8158111572],"type":"Point"}
}