{
  "type": "Feature",
  "properties": {
    "addr:full":"Adelaide Rd Balaklava SA 5461",
    "addr:postcode":"5461",
    "addr:street":"Adelaide Rd",
    "iso:country":"AU",
    "sg:address":"Adelaide Rd",
    "sg:city":"Balaklava",
    "sg:classifiers":[
        {
            "category":"Building & Trades",
            "subcategory":"Construction",
            "type":"Services"
        }
    ],
    "sg:phone":"+61 8 8862 1666",
    "sg:postcode":"5461",
    "sg:province":"SA",
    "sg:tags":[
        "excavation",
        "foundation"
    ],
    "wof:name":"Balaklava Equipment Hire",
    "wof:placetype":"venue"
},
  "geometry": {"coordinates":[138.41090399999999,-34.1455],"type":"Point"}
}