{
  "type": "Feature",
  "properties": {
    "addr:full":"2/ 22 Beaumont Rd Mt Kuring-gai NSW 2080",
    "addr:housenumber":"/ 22",
    "addr:postcode":"2080",
    "addr:street":"Beaumont Rd",
    "iso:country":"AU",
    "sg:address":"2/ 22 Beaumont Rd",
    "sg:city":"Mt Kuring-gai",
    "sg:classifiers":[
        {
            "category":"Shopping",
            "subcategory":"Stationery & Office Supplies",
            "type":"Retail Goods"
        }
    ],
    "sg:phone":"+61 1800 023 890",
    "sg:postcode":"2080",
    "sg:province":"NSW",
    "sg:tags":[
        "packaging",
        "material"
    ],
    "wof:name":"Australian Warehouse Solutions",
    "wof:placetype":"venue"
},
  "geometry": {"coordinates":[151.13348388700001,-33.6440086365],"type":"Point"}
}