{
  "type": "Feature",
  "properties": {
    "iso:country":"AU",
    "sg:address":"Whiteley St",
    "sg:city":"Dunedoo",
    "sg:classifiers":[
        {
            "category":"Commercial Area",
            "type":"Public Place"
        }
    ],
    "sg:phone":"+61 2 6375 1355",
    "sg:postcode":"2844",
    "sg:province":"NSW",
    "sg:tags":[
        "heavy",
        "carrier"
    ],
    "wof:name":"Watson Transport",
    "wof:placetype":"venue"
},
  "geometry": {"coordinates":[149.388947,-32.014095],"type":"Point"}
}