{
  "type": "Feature",
  "properties": {
    "iso:country":"AU",
    "sg:address":"89 Riding Rd",
    "sg:city":"Hawthorne",
    "sg:classifiers":[
        {
            "category":"Sports & Exercise",
            "subcategory":"Gym",
            "type":"Entertainment"
        }
    ],
    "sg:phone":"+61 418 118 804",
    "sg:postcode":"4171",
    "sg:province":"QLD",
    "sg:tags":[
        "personal",
        "trainer",
        "fitness"
    ],
    "wof:name":"Body Vibe Studios",
    "wof:placetype":"venue"
},
  "geometry": {"coordinates":[153.06434631400001,-27.4650917053],"type":"Point"}
}