{
  "type": "Feature",
  "properties": {
    "addr:full":"20 Prospect St Box Hill VIC 3128",
    "addr:housenumber":"20",
    "addr:postcode":"3128",
    "addr:street":"Prospect St",
    "iso:country":"AU",
    "sg:address":"20 Prospect St",
    "sg:city":"Box Hill",
    "sg:classifiers":[
        {
            "category":"Professional",
            "subcategory":"Computer Services",
            "type":"Services"
        }
    ],
    "sg:phone":"+61 3 9895 2000",
    "sg:postcode":"3128",
    "sg:province":"VIC",
    "sg:tags":[
        "package",
        "software"
    ],
    "wof:name":"ManageSoft Corporation Pty Ltd",
    "wof:placetype":"venue"
},
  "geometry": {"coordinates":[145.11810302699999,-37.8179588318],"type":"Point"}
}