{
  "type": "Feature",
  "properties": {
    "addr:full":"28 St Andrews Way West Lakes SA 5021",
    "addr:housenumber":"28",
    "addr:postcode":"5021",
    "addr:street":"St Andrews Way",
    "iso:country":"AU",
    "sg:address":"28 St Andrews Way",
    "sg:city":"West Lakes",
    "sg:classifiers":[
        {
            "category":"Real Estate",
            "subcategory":"Real Estate Agent",
            "type":"Services"
        }
    ],
    "sg:phone":"+61 8 8356 8194",
    "sg:postcode":"5021",
    "sg:province":"SA",
    "wof:name":"Rositano Property Management",
    "wof:placetype":"venue"
},
  "geometry": {"coordinates":[138.49082946799999,-34.8888664246],"type":"Point"}
}