{
  "type": "Feature",
  "properties": {
    "iso:country":"AU",
    "sg:address":"127 Smith St",
    "sg:city":"Fitzroy",
    "sg:classifiers":[
        {
            "category":"Professional",
            "subcategory":"Accounting & Tax Preparation",
            "type":"Services"
        }
    ],
    "sg:phone":"+61 1800 822 021",
    "sg:postcode":"3065",
    "sg:province":"VIC",
    "sg:tags":[
        "bookkeeping"
    ],
    "wof:name":"Accounting Ontrack",
    "wof:placetype":"venue"
},
  "geometry": {"coordinates":[144.98301696799999,-37.8051948547],"type":"Point"}
}