{
  "type": "Feature",
  "properties": {
    "addr:full":"55 Donald St Nelson Bay NSW 2315",
    "addr:housenumber":"55",
    "addr:postcode":"2315",
    "addr:street":"Donald St",
    "iso:country":"AU",
    "sg:address":"55 Donald St",
    "sg:city":"Nelson Bay",
    "sg:classifiers":[
        {
            "category":"Wholesale",
            "subcategory":"Drugs",
            "type":"Manufacturing & Wholesale Goods"
        }
    ],
    "sg:phone":"+61 2 4984 5088",
    "sg:postcode":"2315",
    "sg:province":"NSW",
    "sg:tags":[
        "wholesaler",
        "pharmaceutical",
        "product",
        "mfrs"
    ],
    "wof:name":"Kingston Chemicals",
    "wof:placetype":"venue"
},
  "geometry": {"coordinates":[152.14324999999999,-32.721947],"type":"Point"}
}