{
  "type": "Feature",
  "properties": {
    "addr:full":"505 Canterbury Rd Vermont VIC 3133",
    "addr:housenumber":"505",
    "addr:postcode":"3133",
    "addr:street":"Canterbury Rd",
    "iso:country":"AU",
    "sg:address":"505 Canterbury Rd",
    "sg:city":"Vermont",
    "sg:classifiers":[
        {
            "category":"Professional",
            "subcategory":"Employment Agencies",
            "type":"Services"
        }
    ],
    "sg:phone":"+61 3 9874 0644",
    "sg:postcode":"3133",
    "sg:province":"VIC",
    "sg:tags":[
        "provider",
        "internet"
    ],
    "wof:name":"E-Guides Australia Pty Ltd",
    "wof:placetype":"venue"
},
  "geometry": {"coordinates":[145.1978302,-37.8353500366],"type":"Point"}
}