{
  "type": "Feature",
  "properties": {
    "addr:full":"24 Dolben St Willowbank QLD 4306",
    "addr:housenumber":"24",
    "addr:postcode":"4306",
    "addr:street":"Dolben St",
    "iso:country":"AU",
    "sg:address":"24 Dolben St",
    "sg:city":"Willowbank",
    "sg:classifiers":[
        {
            "category":"Education",
            "subcategory":"Music School",
            "type":"Public Place"
        }
    ],
    "sg:phone":"+61 7 5467 3218",
    "sg:postcode":"4306",
    "sg:province":"QLD",
    "sg:tags":[
        "teacher"
    ],
    "wof:name":"Katrina May",
    "wof:placetype":"venue"
},
  "geometry": {"coordinates":[152.68824768100001,-27.6577301025],"type":"Point"}
}