{
  "type": "Feature",
  "properties": {
    "iso:country":"AU",
    "sg:address":"2 Hampden Ave",
    "sg:city":"Frankston",
    "sg:classifiers":[
        {
            "category":"Food & Beverages",
            "subcategory":"Groceries & Convenience Stores",
            "type":"Retail Goods"
        }
    ],
    "sg:phone":"+61 3 9776 7722",
    "sg:postcode":"3199",
    "sg:province":"VIC",
    "wof:name":"Michaels Milkbar",
    "wof:placetype":"venue"
},
  "geometry": {"coordinates":[145.157348633,-38.1431465149],"type":"Point"}
}