{
  "type": "Feature",
  "properties": {
    "iso:country":"AU",
    "sg:address":"16 Cherry Blossom La",
    "sg:city":"Mornington",
    "sg:classifiers":[
        {
            "category":"Banks & Credit Unions",
            "subcategory":"Investment Brokerage",
            "type":"Services"
        }
    ],
    "sg:phone":"+61 3 5977 2399",
    "sg:postcode":"3931",
    "sg:province":"VIC",
    "sg:tags":[
        "finance",
        "broker"
    ],
    "wof:name":"B.R.L. Financial Services Pty Ltd",
    "wof:placetype":"venue"
},
  "geometry": {"coordinates":[145.059356689,-38.2145957947],"type":"Point"}
}