{
  "type": "Feature",
  "properties": {
    "addr:full":"17 Long St Cudal NSW 2864",
    "addr:housenumber":"17",
    "addr:postcode":"2864",
    "addr:street":"Long St",
    "iso:country":"AU",
    "sg:address":"17 Long St",
    "sg:city":"Cudal",
    "sg:classifiers":[
        {
            "category":"Food & Beverages",
            "subcategory":"Specialty",
            "type":"Retail Goods"
        }
    ],
    "sg:phone":"+61 2 6364 2397",
    "sg:postcode":"2864",
    "sg:province":"NSW",
    "sg:tags":[
        "ice",
        "supply"
    ],
    "wof:name":"Snooze Ezy Ice",
    "wof:placetype":"venue"
},
  "geometry": {"coordinates":[148.744339,-33.288723],"type":"Point"}
}