{
  "type": "Feature",
  "properties": {
    "addr:full":"77a Were St Brighton VIC 3186",
    "addr:housenumber":"77a",
    "addr:postcode":"3186",
    "addr:street":"Were St",
    "iso:country":"AU",
    "sg:address":"77a Were St",
    "sg:city":"Brighton",
    "sg:classifiers":[
        {
            "category":"Education",
            "subcategory":"Kindergarten",
            "type":"Public Place"
        }
    ],
    "sg:phone":"+61 3 9592 5122",
    "sg:postcode":"3186",
    "sg:province":"VIC",
    "sg:tags":[
        "pre-schools"
    ],
    "wof:name":"St Peters Kindergarten",
    "wof:placetype":"venue"
},
  "geometry": {"coordinates":[144.995803833,-37.9252433777],"type":"Point"}
}