{
  "type": "Feature",
  "properties": {
    "iso:country":"AU",
    "sg:address":"Wangaratta Airport Greta Rd",
    "sg:city":"Wangaratta",
    "sg:classifiers":[
        {
            "category":"Sports & Exercise",
            "subcategory":"Sports Center",
            "type":"Entertainment"
        }
    ],
    "sg:phone":"+61 3 5722 3220",
    "sg:postcode":"3677",
    "sg:province":"VIC",
    "sg:tags":[
        "ground"
    ],
    "wof:name":"National Sport Aviation Centre",
    "wof:placetype":"venue"
},
  "geometry": {"coordinates":[146.28222656200001,-36.3908615112],"type":"Point"}
}