{
  "type": "Feature",
  "properties": {
    "addr:full":".. St Carine WA 6020",
    "addr:housenumber":"..",
    "addr:postcode":"6020",
    "addr:street":"St",
    "iso:country":"AU",
    "sg:address":".. St",
    "sg:city":"Carine",
    "sg:classifiers":[
        {
            "category":"Personal",
            "type":"Services"
        }
    ],
    "sg:phone":"+61 8 9447 0119",
    "sg:postcode":"6020",
    "sg:province":"WA",
    "sg:tags":[
        "reducing",
        "treatment",
        "weight"
    ],
    "wof:name":"Herbalife Carine",
    "wof:placetype":"venue"
},
  "geometry": {"coordinates":[115.776611328,-31.8511104584],"type":"Point"}
}