{
  "type": "Feature",
  "properties": {
    "addr:full":"Level 2/ 89 Raymond St Sale VIC 3850",
    "addr:housenumber":"/ 89",
    "addr:postcode":"3850",
    "addr:street":"Raymond St",
    "iso:country":"AU",
    "sg:address":"Level 2/ 89 Raymond St",
    "sg:city":"Sale",
    "sg:classifiers":[
        {
            "category":"Professional",
            "subcategory":"Employment Agencies",
            "type":"Services"
        }
    ],
    "sg:phone":"+61 3 5144 7488",
    "sg:postcode":"3850",
    "sg:province":"VIC",
    "sg:tags":[
        "hire",
        "labour",
        "contractor"
    ],
    "wof:name":"Work Hire",
    "wof:placetype":"venue"
},
  "geometry": {"coordinates":[147.06562805199999,-38.1112861633],"type":"Point"}
}