{
  "type": "Feature",
  "properties": {
    "iso:country":"AU",
    "sg:address":"41 Hadden Drv",
    "sg:city":"Ballan",
    "sg:classifiers":[
        {
            "category":"Retail",
            "subcategory":"Storage",
            "type":"Services"
        }
    ],
    "sg:phone":"+61 409 689 566",
    "sg:postcode":"3342",
    "sg:province":"VIC",
    "wof:name":"Ballan Storage Sheds",
    "wof:placetype":"venue"
},
  "geometry": {"coordinates":[144.238068,-37.613495],"type":"Point"}
}