{
  "type": "Feature",
  "properties": {
    "addr:full":"2 Lister Crt Ringwood VIC 3134",
    "addr:housenumber":"2",
    "addr:postcode":"3134",
    "addr:street":"Lister Crt",
    "iso:country":"AU",
    "sg:address":"2 Lister Crt",
    "sg:city":"Ringwood",
    "sg:classifiers":[
        {
            "category":"Education",
            "subcategory":"Music School",
            "type":"Public Place"
        }
    ],
    "sg:phone":"+61 3 9879 6210",
    "sg:postcode":"3134",
    "sg:province":"VIC",
    "sg:tags":[
        "teacher"
    ],
    "sg:website":"http://www.msom.com.au",
    "wof:name":"Melbourne School Of Music",
    "wof:placetype":"venue"
},
  "geometry": {"coordinates":[145.23518371599999,-37.8063278198],"type":"Point"}
}