{
  "type": "Feature",
  "properties": {
    "addr:full":"9 Albert St Busselton WA 6280",
    "addr:housenumber":"9",
    "addr:postcode":"6280",
    "addr:street":"Albert St",
    "iso:country":"AU",
    "sg:address":"9 Albert St",
    "sg:city":"Busselton",
    "sg:classifiers":[
        {
            "category":"Fast Food",
            "type":"Food & Drink"
        }
    ],
    "sg:phone":"+61 8 9751 3388",
    "sg:postcode":"6280",
    "sg:province":"WA",
    "sg:tags":[
        "away",
        "take"
    ],
    "wof:name":"Jade Cafe Restaurant",
    "wof:placetype":"venue"
},
  "geometry": {"coordinates":[115.34171295199999,-33.6526527405],"type":"Point"}
}