{
  "type": "Feature",
  "properties": {
    "addr:full":"25 Holland St Goonellabah NSW 2480",
    "addr:housenumber":"25",
    "addr:postcode":"2480",
    "addr:street":"Holland St",
    "iso:country":"AU",
    "sg:address":"25 Holland St",
    "sg:city":"Goonellabah",
    "sg:classifiers":[
        {
            "category":"Building & Trades",
            "subcategory":"Construction",
            "type":"Services"
        }
    ],
    "sg:phone":"+61 2 6625 1154",
    "sg:postcode":"2480",
    "sg:province":"NSW",
    "sg:tags":[
        "window",
        "aluminium"
    ],
    "sg:website":"http://www.versalitewindows.com.au",
    "wof:name":"Versalite Windows",
    "wof:placetype":"venue"
},
  "geometry": {"coordinates":[153.345779419,-28.8200798035],"type":"Point"}
}