{
  "type": "Feature",
  "properties": {
    "addr:full":"128 South Gippsland Hwy Cranbourne VIC 3977",
    "addr:housenumber":"128",
    "addr:postcode":"3977",
    "addr:street":"South Gippsland Hwy",
    "iso:country":"AU",
    "sg:address":"128 South Gippsland Hwy",
    "sg:city":"Cranbourne",
    "sg:classifiers":[
        {
            "category":"Manufacturing",
            "subcategory":"Apparel",
            "type":"Manufacturing & Wholesale Goods"
        }
    ],
    "sg:phone":"+61 3 5995 3680",
    "sg:postcode":"3977",
    "sg:province":"VIC",
    "sg:tags":[
        "wholesaler",
        "mfrs",
        "footwear"
    ],
    "wof:name":"Lawrence Agencies",
    "wof:placetype":"venue"
},
  "geometry": {"coordinates":[145.27557373100001,-38.0809745789],"type":"Point"}
}