{
  "type": "Feature",
  "properties": {
    "addr:full":"186 Grey St Glen Innes NSW 2370",
    "addr:housenumber":"186",
    "addr:postcode":"2370",
    "addr:street":"Grey St",
    "iso:country":"AU",
    "sg:address":"186 Grey St",
    "sg:city":"Glen Innes",
    "sg:classifiers":[
        {
            "category":"Personal",
            "subcategory":"Beauty Salon",
            "type":"Services"
        }
    ],
    "sg:phone":"+61 2 6732 3323",
    "sg:postcode":"2370",
    "sg:province":"NSW",
    "sg:tags":[
        "hairdresser"
    ],
    "wof:name":"Hair Dooz",
    "wof:placetype":"venue"
},
  "geometry": {"coordinates":[151.73550415,-29.7394447327],"type":"Point"}
}