{
  "type": "Feature",
  "properties": {
    "addr:full":"Argyle Ave Chelsea VIC 3196",
    "addr:postcode":"3196",
    "addr:street":"Argyle Ave",
    "iso:country":"AU",
    "sg:address":"Argyle Ave",
    "sg:city":"Chelsea",
    "sg:classifiers":[
        {
            "category":"Education",
            "subcategory":"School",
            "type":"Public Place"
        }
    ],
    "sg:phone":"+61 3 9773 2055",
    "sg:postcode":"3196",
    "sg:province":"VIC",
    "sg:tags":[
        "state",
        "except",
        "nsw"
    ],
    "wof:name":"Chelsea Primary",
    "wof:placetype":"venue"
},
  "geometry": {"coordinates":[145.117675781,-38.0558662415],"type":"Point"}
}