{
  "type": "Feature",
  "properties": {
    "iso:country":"AU",
    "sg:address":"Wesley St",
    "sg:city":"Kangaroo Flat",
    "sg:classifiers":[
        {
            "category":"Travel",
            "subcategory":"Hostel",
            "type":"Entertainment"
        }
    ],
    "sg:phone":"+61 3 5447 0477",
    "sg:postcode":"3555",
    "sg:province":"VIC",
    "sg:tags":[
        "home"
    ],
    "wof:name":"St Laurence Court",
    "wof:placetype":"venue"
},
  "geometry": {"coordinates":[144.242385864,-36.8026657104],"type":"Point"}
}