{
  "type": "Feature",
  "properties": {
    "iso:country":"AU",
    "sg:address":"Unit 9/ 52 Aquarium Ave",
    "sg:city":"Hemmant",
    "sg:classifiers":[
        {
            "category":"Home & Garden",
            "subcategory":"Building Materials",
            "type":"Retail Goods"
        }
    ],
    "sg:phone":"+61 7 3390 6737",
    "sg:postcode":"4174",
    "sg:province":"QLD",
    "sg:tags":[
        "restoration",
        "supply"
    ],
    "wof:name":"Roofshield Restorations",
    "wof:placetype":"venue"
},
  "geometry": {"coordinates":[153.126190186,-27.4427528381],"type":"Point"}
}