{
  "type": "Feature",
  "properties": {
    "iso:country":"AU",
    "sg:address":"150 Greville St",
    "sg:city":"Chatswood",
    "sg:classifiers":[
        {
            "category":"Health Services",
            "subcategory":"Health Practitioner",
            "type":"Services"
        }
    ],
    "sg:phone":"+61 2 9419 6858",
    "sg:postcode":"2067",
    "sg:province":"NSW",
    "sg:tags":[
        "hypnotherapy"
    ],
    "wof:name":"Yourell Asha Dr",
    "wof:placetype":"venue"
},
  "geometry": {"coordinates":[151.16932678200001,-33.7929763794],"type":"Point"}
}