{
  "type": "Feature",
  "properties": {
    "addr:full":"PO Box 3240 Erina NSW 2250",
    "addr:postcode":"2250",
    "iso:country":"AU",
    "sg:address":"PO Box 3240",
    "sg:city":"Erina",
    "sg:classifiers":[
        {
            "category":"Professional",
            "subcategory":"Computer Services",
            "type":"Services"
        }
    ],
    "sg:phone":"+61 2 4367 3922",
    "sg:postcode":"2250",
    "sg:province":"NSW",
    "sg:tags":[
        "consultant",
        "system"
    ],
    "wof:name":"Iveson Consulting Services",
    "wof:placetype":"venue"
},
  "geometry": {"coordinates":[151.395217895,-33.4346389771],"type":"Point"}
}