{
  "type": "Feature",
  "properties": {
    "iso:country":"AU",
    "sg:address":"Serpentine Creek Rd",
    "sg:city":"Redland Bay",
    "sg:classifiers":[
        {
            "category":"Farming",
            "subcategory":"Farm",
            "type":"Manufacturing & Wholesale Goods"
        }
    ],
    "sg:phone":"+61 7 3206 8148",
    "sg:postcode":"4165",
    "sg:province":"QLD",
    "sg:tags":[
        "farmer"
    ],
    "wof:name":"Wilson W E & Son",
    "wof:placetype":"venue"
},
  "geometry": {"coordinates":[153.306182861,-27.638130188],"type":"Point"}
}