{
  "type": "Feature",
  "properties": {
    "addr:full":"22 Eleanor St Footscray West VIC 3012",
    "addr:housenumber":"22",
    "addr:postcode":"3012",
    "addr:street":"Eleanor St",
    "iso:country":"AU",
    "sg:address":"22 Eleanor St",
    "sg:city":"Footscray West",
    "sg:classifiers":[
        {
            "category":"Health Services",
            "subcategory":"Doctor",
            "type":"Services"
        }
    ],
    "sg:phone":"+61 3 9318 1722",
    "sg:postcode":"3012",
    "sg:province":"VIC",
    "sg:tags":[
        "medical",
        "practitioner"
    ],
    "wof:name":"Travers Richard L",
    "wof:placetype":"venue"
},
  "geometry": {"coordinates":[144.88546752900001,-37.7916412354],"type":"Point"}
}