{
  "type": "Feature",
  "properties": {
    "addr:full":"126 High St Kangaroo Flat VIC 3555",
    "addr:housenumber":"126",
    "addr:postcode":"3555",
    "addr:street":"High St",
    "iso:country":"AU",
    "sg:address":"126 High St",
    "sg:city":"Kangaroo Flat",
    "sg:classifiers":[
        {
            "category":"Banks & Credit Unions",
            "subcategory":"Bank",
            "type":"Services"
        }
    ],
    "sg:phone":"+61 3 5433 9795",
    "sg:postcode":"3555",
    "sg:province":"VIC",
    "wof:name":"Bendigo Bank",
    "wof:placetype":"venue"
},
  "geometry": {"coordinates":[144.24418640100001,-36.7957687378],"type":"Point"}
}