{
  "type": "Feature",
  "properties": {
    "iso:country":"AU",
    "sg:address":"Shop 11, 28 Bell St",
    "sg:city":"Toowoomba",
    "sg:classifiers":[
        {
            "category":"Insurance",
            "subcategory":"Hazard Insurance",
            "type":"Services"
        }
    ],
    "sg:phone":"+61 7 4638 9155",
    "sg:postcode":"4350",
    "sg:province":"QLD",
    "sg:tags":[
        "loss",
        "adjuster",
        "assessor"
    ],
    "wof:name":"GAB Robins Australia Pty Ltd",
    "wof:placetype":"venue"
},
  "geometry": {"coordinates":[151.955276,-27.560123],"type":"Point"}
}