{
  "type": "Feature",
  "properties": {
    "addr:full":"74 Acland St St Kilda VIC 3182",
    "addr:housenumber":"74",
    "addr:postcode":"3182",
    "addr:street":"Acland St",
    "iso:country":"AU",
    "sg:address":"74 Acland St",
    "sg:city":"St Kilda",
    "sg:classifiers":[
        {
            "category":"Shopping",
            "subcategory":"Discount & Variety Stores",
            "type":"Retail Goods"
        }
    ],
    "sg:phone":"+61 3 9534 5835",
    "sg:postcode":"3182",
    "sg:province":"VIC",
    "sg:tags":[
        "shop",
        "adult"
    ],
    "wof:name":"Club X",
    "wof:placetype":"venue"
},
  "geometry": {"coordinates":[144.97857665999999,-37.8670845032],"type":"Point"}
}