{
  "type": "Feature",
  "properties": {
    "addr:full":"129 York St Sydney NSW 2000",
    "addr:housenumber":"129",
    "addr:postcode":"2000",
    "addr:street":"York St",
    "iso:country":"AU",
    "sg:address":"129 York St",
    "sg:city":"Sydney",
    "sg:classifiers":[
        {
            "category":"Education",
            "subcategory":"Kindergarten",
            "type":"Public Place"
        }
    ],
    "sg:phone":"+61 2 9264 8366",
    "sg:postcode":"2000",
    "sg:province":"NSW",
    "sg:tags":[
        "pre-schools"
    ],
    "wof:name":"KU Children's Services",
    "wof:placetype":"venue"
},
  "geometry": {"coordinates":[151.20628356899999,-33.8719787598],"type":"Point"}
}