{
  "type": "Feature",
  "properties": {
    "addr:full":"Building 2/ 1 Healey Rd Dandenong South VIC 3175",
    "addr:housenumber":"/ 1",
    "addr:postcode":"3175",
    "addr:street":"Healey Rd",
    "iso:country":"AU",
    "sg:address":"Building 2/ 1 Healey Rd",
    "sg:city":"Dandenong South",
    "sg:classifiers":[
        {
            "category":"Home & Garden",
            "subcategory":"Home Furnishings",
            "type":"Retail Goods"
        }
    ],
    "sg:phone":"+61 3 9706 6330",
    "sg:postcode":"3175",
    "sg:province":"VIC",
    "sg:tags":[
        "candle"
    ],
    "wof:name":"Polyco Candle Company Pty Ltd",
    "wof:placetype":"venue"
},
  "geometry": {"coordinates":[145.21347045900001,-38.028678894],"type":"Point"}
}