{
  "type": "Feature",
  "properties": {
    "addr:full":"Cnr York St & Stirling Tce Albany WA 6330",
    "addr:postcode":"6330",
    "addr:street":"Cnr York St & Stirling Tce",
    "iso:country":"AU",
    "sg:address":"Cnr York St",
    "sg:city":"& Stirling Tce Albany",
    "sg:classifiers":[
        {
            "category":"Insurance",
            "subcategory":"Hazard Insurance",
            "type":"Services"
        }
    ],
    "sg:phone":"+61 8 9841 4344",
    "sg:postcode":"6330",
    "sg:province":"WA",
    "sg:tags":[
        "motor",
        "vehicle"
    ],
    "wof:name":"Western QBE Insurance",
    "wof:placetype":"venue"
},
  "geometry": {"coordinates":[117.884117127,-35.0180053711],"type":"Point"}
}