{
  "type": "Feature",
  "properties": {
    "iso:country":"AU",
    "sg:address":"Ovens Hwy",
    "sg:city":"Eurobin",
    "sg:classifiers":[
        {
            "category":"Manufacturing",
            "subcategory":"Furniture",
            "type":"Manufacturing & Wholesale Goods"
        }
    ],
    "sg:phone":"+61 3 5756 2304",
    "sg:postcode":"3739",
    "sg:province":"VIC",
    "sg:tags":[
        "builder",
        "designer",
        "custom"
    ],
    "wof:name":"Willing G",
    "wof:placetype":"venue"
},
  "geometry": {"coordinates":[146.84979248100001,-36.6359405518],"type":"Point"}
}