{
  "type": "Feature",
  "properties": {
    "iso:country":"AU",
    "sg:address":"223 Colchester Rd",
    "sg:city":"Kilsyth",
    "sg:classifiers":[
        {
            "category":"Autos & Motor Vehicles",
            "subcategory":"Automobile Sales",
            "type":"Retail Goods"
        }
    ],
    "sg:phone":"+61 3 9761 5533",
    "sg:postcode":"3137",
    "sg:province":"VIC",
    "sg:tags":[
        "equipment",
        "trailer"
    ],
    "sg:website":"http://www.trailerfactory.com.au",
    "wof:name":"The Trailer Factory",
    "wof:placetype":"venue"
},
  "geometry": {"coordinates":[145.30506897000001,-37.818107605],"type":"Point"}
}