{
  "type": "Feature",
  "properties": {
    "addr:full":"Shd2/ 3 Douro St North Geelong VIC 3215",
    "addr:housenumber":"3",
    "addr:postcode":"3215",
    "addr:street":"Douro St",
    "iso:country":"AU",
    "sg:address":"Shd2/ 3 Douro St",
    "sg:city":"North Geelong",
    "sg:classifiers":[
        {
            "category":"Home & Garden",
            "subcategory":"Carpets & Floor Coverings",
            "type":"Retail Goods"
        }
    ],
    "sg:phone":"+61 3 5272 1777",
    "sg:postcode":"3215",
    "sg:province":"VIC",
    "sg:tags":[
        "wood"
    ],
    "wof:name":"Weatheredwood Industries",
    "wof:placetype":"venue"
},
  "geometry": {"coordinates":[144.34759521500001,-38.1222076416],"type":"Point"}
}