{
  "type": "Feature",
  "properties": {
    "iso:country":"AU",
    "sg:address":"PO Box 4519",
    "sg:city":"Darwin",
    "sg:classifiers":[
        {
            "category":"Industrial Area",
            "type":"Public Place"
        }
    ],
    "sg:phone":"+61 418 191 678",
    "sg:postcode":"0801",
    "sg:province":"NT",
    "sg:tags":[
        "rural",
        "shed"
    ],
    "wof:name":"Top End Sheds",
    "wof:placetype":"venue"
},
  "geometry": {"coordinates":[130.84190368599999,-12.4613304138],"type":"Point"}
}