{
  "type": "Feature",
  "properties": {
    "iso:country":"AU",
    "sg:address":"35 Rivendell Drv",
    "sg:city":"Tweed Heads",
    "sg:classifiers":[
        {
            "category":"Home & Garden",
            "subcategory":"Building Materials",
            "type":"Retail Goods"
        }
    ],
    "sg:phone":"+61 7 5523 4831",
    "sg:postcode":"2485",
    "sg:province":"NSW",
    "sg:tags":[
        "retaining",
        "wall"
    ],
    "wof:name":"Mills Brick & Paving",
    "wof:placetype":"venue"
},
  "geometry": {"coordinates":[153.543731689,-28.2059555054],"type":"Point"}
}