{
  "type": "Feature",
  "properties": {
    "iso:country":"AU",
    "sg:address":"Unit 36 237 Victoria Rd",
    "sg:city":"Rydalmere",
    "sg:classifiers":[
        {
            "category":"Banks & Credit Unions",
            "subcategory":"Bureau De Change",
            "type":"Services"
        }
    ],
    "sg:phone":"+61 2 9638 3196",
    "sg:postcode":"2116",
    "sg:province":"NSW",
    "sg:tags":[
        "repairs",
        "part",
        "appliance",
        "electrical"
    ],
    "wof:name":"P & R Electrical Wholesalers Pty Ltd",
    "wof:placetype":"venue"
},
  "geometry": {"coordinates":[151.16142273,-33.9104232788],"type":"Point"}
}