{
  "type": "Feature",
  "properties": {
    "iso:country":"AU",
    "sg:address":"49 Annie St",
    "sg:city":"Coopers Plains",
    "sg:classifiers":[
        {
            "category":"Building & Trades",
            "subcategory":"Plumbing",
            "type":"Services"
        }
    ],
    "sg:phone":"+61 7 3875 1977",
    "sg:postcode":"4108",
    "sg:province":"QLD",
    "sg:tags":[
        "equipment",
        "valves"
    ],
    "wof:name":"Norgren Pty Ltd",
    "wof:placetype":"venue"
},
  "geometry": {"coordinates":[153.032302856,-27.5662174225],"type":"Point"}
}