{
  "type": "Feature",
  "properties": {
    "iso:country":"AU",
    "sg:address":"120 Meiers Rd",
    "sg:city":"Indooroopilly",
    "sg:classifiers":[
        {
            "category":"Professional",
            "subcategory":"Research",
            "type":"Services"
        }
    ],
    "sg:phone":"+61 7 3214 2374",
    "sg:postcode":"4068",
    "sg:province":"QLD",
    "sg:tags":[
        "analyst"
    ],
    "wof:name":"CSIRO Divison Of Tropical Agriculture",
    "wof:placetype":"venue"
},
  "geometry": {"coordinates":[152.99517822300001,-27.5112342834],"type":"Point"}
}