{
  "type": "Feature",
  "properties": {
    "iso:country":"AU",
    "sg:address":"1273 Gympie Rd",
    "sg:city":"Aspley",
    "sg:classifiers":[
        {
            "category":"Cafe",
            "type":"Food & Drink"
        }
    ],
    "sg:phone":"+61 7 3263 1932",
    "sg:postcode":"4034",
    "sg:province":"QLD",
    "wof:name":"Sun Chung Cafe",
    "wof:placetype":"venue"
},
  "geometry": {"coordinates":[153.01748699999999,-27.365665],"type":"Point"}
}