{
  "type": "Feature",
  "properties": {
    "addr:full":"16 Darling St Tamworth NSW 2340",
    "addr:housenumber":"16",
    "addr:postcode":"2340",
    "addr:street":"Darling St",
    "iso:country":"AU",
    "sg:address":"16 Darling St",
    "sg:city":"Tamworth",
    "sg:classifiers":[
        {
            "category":"Health Services",
            "subcategory":"Doctor",
            "type":"Services"
        }
    ],
    "sg:phone":"+61 2 6766 6768",
    "sg:postcode":"2340",
    "sg:province":"NSW",
    "sg:tags":[
        "medical",
        "practitioner"
    ],
    "wof:name":"Levendel A",
    "wof:placetype":"venue"
},
  "geometry": {"coordinates":[150.92768859899999,-31.0857524872],"type":"Point"}
}