{
  "type": "Feature",
  "properties": {
    "iso:country":"AU",
    "sg:address":"108- 110 Reservoir Rd",
    "sg:city":"Modbury",
    "sg:classifiers":[
        {
            "category":"Professional",
            "subcategory":"Employment Agencies",
            "type":"Services"
        }
    ],
    "sg:phone":"+61 8 8395 6300",
    "sg:postcode":"5092",
    "sg:province":"SA",
    "wof:name":"Jobs Statewide",
    "wof:placetype":"venue"
},
  "geometry": {"coordinates":[138.68782043499999,-34.8329849243],"type":"Point"}
}