{
  "type": "Feature",
  "properties": {
    "addr:full":"Tocumwal Rd Mulwala NSW 2647",
    "addr:postcode":"2647",
    "addr:street":"Tocumwal Rd",
    "iso:country":"AU",
    "sg:address":"Tocumwal Rd",
    "sg:city":"Mulwala",
    "sg:classifiers":[
        {
            "category":"Farming",
            "subcategory":"Vineyard",
            "type":"Manufacturing & Wholesale Goods"
        }
    ],
    "sg:phone":"+61 3 5745 8345",
    "sg:postcode":"2647",
    "sg:province":"NSW",
    "sg:tags":[
        "winery"
    ],
    "wof:name":"Murray Estate Wines",
    "wof:placetype":"venue"
},
  "geometry": {"coordinates":[145.94569397000001,-35.9083900452],"type":"Point"}
}