{
  "type": "Feature",
  "properties": {
    "iso:country":"AU",
    "sg:address":"High St",
    "sg:city":"Heathcote",
    "sg:classifiers":[
        {
            "category":"Autos & Motor Vehicles",
            "subcategory":"Fuel & Gas Station",
            "type":"Retail Goods"
        }
    ],
    "sg:phone":"+61 3 5433 2644",
    "sg:postcode":"3523",
    "sg:province":"VIC",
    "wof:name":"BP Australia Limited",
    "wof:placetype":"venue"
},
  "geometry": {"coordinates":[144.70036300000001,-36.914326],"type":"Point"}
}