{
  "type": "Feature",
  "properties": {
    "iso:country":"AU",
    "sg:address":"1363 Toorak Rd",
    "sg:city":"Camberwell",
    "sg:classifiers":[
        {
            "category":"Professional",
            "subcategory":"Computer Services",
            "type":"Services"
        }
    ],
    "sg:phone":"+61 3 9889 3000",
    "sg:postcode":"3124",
    "sg:province":"VIC",
    "sg:tags":[
        "repairs",
        "upgrade",
        "equipment"
    ],
    "wof:name":"Total Solutions",
    "wof:placetype":"venue"
},
  "geometry": {"coordinates":[145.09303283700001,-37.8499832153],"type":"Point"}
}