{
  "type": "Feature",
  "properties": {
    "iso:country":"AU",
    "sg:address":"32- 34 Gilmore St",
    "sg:city":"Invermay",
    "sg:classifiers":[
        {
            "category":"Utilities",
            "subcategory":"Recycling",
            "type":"Services"
        }
    ],
    "sg:phone":"+61 3 6326 6760",
    "sg:postcode":"7248",
    "sg:province":"TAS",
    "wof:name":"Collex",
    "wof:placetype":"venue"
},
  "geometry": {"coordinates":[147.125244141,-41.4196281433],"type":"Point"}
}