{
  "type": "Feature",
  "properties": {
    "iso:country":"AU",
    "sg:address":"59 Venetia St",
    "sg:city":"Sylvania",
    "sg:classifiers":[
        {
            "category":"Building & Trades",
            "subcategory":"Landscaping Services",
            "type":"Services"
        }
    ],
    "sg:phone":"+61 2 9544 6879",
    "sg:postcode":"2224",
    "sg:province":"NSW",
    "sg:tags":[
        "stump",
        "tree",
        "felling",
        "removal"
    ],
    "sg:website":"http://www.hart2hart.com.au",
    "wof:name":"Hart To Hart",
    "wof:placetype":"venue"
},
  "geometry": {"coordinates":[151.096435547,-34.0124435425],"type":"Point"}
}