{
  "type": "Feature",
  "properties": {
    "addr:full":"St Andrews VIC 3761",
    "addr:postcode":"3761",
    "iso:country":"AU",
    "sg:address":"St",
    "sg:city":"Andrews",
    "sg:classifiers":[
        {
            "category":"Health Services",
            "subcategory":"Health Practitioner",
            "type":"Services"
        }
    ],
    "sg:phone":"+61 3 9710 1934",
    "sg:postcode":"3761",
    "sg:province":"VIC",
    "sg:tags":[
        "alternative"
    ],
    "wof:name":"Self Healing",
    "wof:placetype":"venue"
},
  "geometry": {"coordinates":[145.28773498499999,-37.5787086487],"type":"Point"}
}