{
  "type": "Feature",
  "properties": {
    "iso:country":"AU",
    "sg:address":"Professional Suite 4, Carlik Place Healthcare Centre 1 Mooney St",
    "sg:city":"Logan",
    "sg:classifiers":[
        {
            "category":"Personal",
            "subcategory":"Day Spa",
            "type":"Services"
        }
    ],
    "sg:phone":"+61 7 3208 1555",
    "sg:postcode":"4114",
    "sg:province":"QLD",
    "wof:name":"Barrachi Day Spa",
    "wof:placetype":"venue"
},
  "geometry": {"coordinates":[153.11485290499999,-27.64153862],"type":"Point"}
}