{
  "type": "Feature",
  "properties": {
    "addr:full":"9 Kellaway Pl Wetherill Park NSW 2164",
    "addr:housenumber":"9",
    "addr:postcode":"2164",
    "addr:street":"Kellaway Pl",
    "iso:country":"AU",
    "sg:address":"9 Kellaway Pl",
    "sg:city":"Wetherill Park",
    "sg:classifiers":[
        {
            "category":"Wholesale",
            "subcategory":"Machinery & Supplies",
            "type":"Manufacturing & Wholesale Goods"
        }
    ],
    "sg:phone":"+61 2 9725 4033",
    "sg:postcode":"2164",
    "sg:province":"NSW",
    "sg:tags":[
        "belting",
        "mfrs"
    ],
    "wof:name":"Engineering Export Services",
    "wof:placetype":"venue"
},
  "geometry": {"coordinates":[150.90507507300001,-33.8400268555],"type":"Point"}
}