{
  "type": "Feature",
  "properties": {
    "addr:full":"22 Ferguson St Williamstown VIC 3016",
    "addr:housenumber":"22",
    "addr:postcode":"3016",
    "addr:street":"Ferguson St",
    "iso:country":"AU",
    "sg:address":"22 Ferguson St",
    "sg:city":"Williamstown",
    "sg:classifiers":[
        {
            "category":"Personal",
            "subcategory":"Hair Removal",
            "type":"Services"
        }
    ],
    "sg:phone":"+61 3 9397 3966",
    "sg:postcode":"3016",
    "sg:province":"VIC",
    "wof:name":"Williamstown Skin Therapy",
    "wof:placetype":"venue"
},
  "geometry": {"coordinates":[144.900756836,-37.8590545654],"type":"Point"}
}