{
  "type": "Feature",
  "properties": {
    "addr:full":"2 Kew Rd Laurieton NSW 2443",
    "addr:housenumber":"2",
    "addr:postcode":"2443",
    "addr:street":"Kew Rd",
    "iso:country":"AU",
    "sg:address":"2 Kew Rd",
    "sg:city":"Laurieton",
    "sg:classifiers":[
        {
            "category":"Autos & Motor Vehicles",
            "subcategory":"Auto Supplies",
            "type":"Retail Goods"
        }
    ],
    "sg:phone":"+61 2 6559 9567",
    "sg:postcode":"2443",
    "sg:province":"NSW",
    "sg:tags":[
        "tyre"
    ],
    "wof:name":"Camden Haven Tyre & Brake Centre",
    "wof:placetype":"venue"
},
  "geometry": {"coordinates":[152.795807,-31.645817],"type":"Point"}
}