{
  "type": "Feature",
  "properties": {
    "addr:full":"17 Harrisons La Glenorie NSW 2157",
    "addr:housenumber":"17",
    "addr:postcode":"2157",
    "addr:street":"Harrisons La",
    "iso:country":"AU",
    "sg:address":"17 Harrisons La",
    "sg:city":"Glenorie",
    "sg:classifiers":[
        {
            "category":"Building & Trades",
            "subcategory":"Plumbing",
            "type":"Services"
        }
    ],
    "sg:phone":"+61 407 944 190",
    "sg:postcode":"2157",
    "sg:province":"NSW",
    "sg:tags":[
        "plumber",
        "gasfitters"
    ],
    "wof:name":"Greg Reid Plumbing Service Pty Ltd",
    "wof:placetype":"venue"
},
  "geometry": {"coordinates":[151.01956176799999,-33.6029052734],"type":"Point"}
}