{
  "type": "Feature",
  "properties": {
    "iso:country":"AU",
    "sg:address":"Roma St",
    "sg:city":"Brisbane",
    "sg:classifiers":[
        {
            "category":"Communications",
            "subcategory":"News Services",
            "type":"Services"
        }
    ],
    "sg:phone":"+61 7 3236 1054",
    "sg:postcode":"4000",
    "sg:province":"QLD",
    "sg:tags":[
        "information",
        "tourist",
        "attractions"
    ],
    "wof:name":"Holiday Services Tours And Cruises",
    "wof:placetype":"venue"
},
  "geometry": {"coordinates":[153.023193359,-27.4683017731],"type":"Point"}
}