{
  "type": "Feature",
  "properties": {
    "iso:country":"AU",
    "sg:address":"4308 Bridport Hwy",
    "sg:city":"Pipers Brook",
    "sg:classifiers":[
        {
            "category":"Commercial Area",
            "type":"Public Place"
        }
    ],
    "sg:phone":"+61 3 6382 7204",
    "sg:postcode":"7254",
    "sg:province":"TAS",
    "sg:tags":[
        "heavy",
        "carrier"
    ],
    "wof:name":"Cannell Cartage",
    "wof:placetype":"venue"
},
  "geometry": {"coordinates":[147.157180786,-41.0769805908],"type":"Point"}
}