{
  "type": "Feature",
  "properties": {
    "addr:full":"227- 233 Dorset Rd Boronia VIC 3155",
    "addr:housenumber":"233",
    "addr:postcode":"3155",
    "addr:street":"Dorset Rd",
    "iso:country":"AU",
    "sg:address":"227- 233 Dorset Rd",
    "sg:city":"Boronia",
    "sg:classifiers":[
        {
            "category":"Professional",
            "subcategory":"Printing & Photocopies",
            "type":"Services"
        }
    ],
    "sg:phone":"+61 3 9739 8707",
    "sg:postcode":"3155",
    "sg:province":"VIC",
    "sg:tags":[
        "rubber",
        "stamp",
        "metal"
    ],
    "wof:name":"Fern Gully Stamps",
    "wof:placetype":"venue"
},
  "geometry": {"coordinates":[145.28541564899999,-37.8628158569],"type":"Point"}
}