{
  "type": "Feature",
  "properties": {
    "addr:full":"200 Bent St South Grafton NSW 2460",
    "addr:housenumber":"200",
    "addr:postcode":"2460",
    "addr:street":"Bent St",
    "iso:country":"AU",
    "sg:address":"200 Bent St",
    "sg:city":"South Grafton",
    "sg:classifiers":[
        {
            "category":"Food & Beverages",
            "subcategory":"Groceries & Convenience Stores",
            "type":"Retail Goods"
        }
    ],
    "sg:phone":"+61 2 6643 1515",
    "sg:postcode":"2460",
    "sg:province":"NSW",
    "wof:name":"Top Shop South Grafton",
    "wof:placetype":"venue"
},
  "geometry": {"coordinates":[152.93458557100001,-29.715927124],"type":"Point"}
}