{
  "type": "Feature",
  "properties": {
    "iso:country":"AU",
    "sg:address":"Shop 8 100B Hill St",
    "sg:city":"Toowoomba",
    "sg:classifiers":[
        {
            "category":"Education",
            "subcategory":"Music School",
            "type":"Public Place"
        }
    ],
    "sg:phone":"+61 7 4632 4477",
    "sg:postcode":"4350",
    "sg:province":"QLD",
    "sg:tags":[
        "therapy",
        "relaxation"
    ],
    "wof:name":"Aromatemple",
    "wof:placetype":"venue"
},
  "geometry": {"coordinates":[151.95077499999999,-27.569567],"type":"Point"}
}