{
  "type": "Feature",
  "properties": {
    "iso:country":"AU",
    "sg:address":"32 Bullara Rd",
    "sg:city":"Craigie",
    "sg:classifiers":[
        {
            "category":"Retail",
            "subcategory":"Repair Shop",
            "type":"Services"
        }
    ],
    "sg:phone":"+61 8 9401 3528",
    "sg:postcode":"6025",
    "sg:province":"WA",
    "sg:tags":[
        "machine",
        "sewing"
    ],
    "wof:name":"Swan Sewing Machine Service",
    "wof:placetype":"venue"
},
  "geometry": {"coordinates":[115.767272949,-31.7816085815],"type":"Point"}
}