{
  "type": "Feature",
  "properties": {
    "addr:full":"49-51 Thomas St West End (Brisbane) QLD 4101",
    "addr:housenumber":"49-51",
    "addr:postcode":"4101",
    "addr:street":"Thomas St",
    "iso:country":"AU",
    "sg:address":"49-51 Thomas St",
    "sg:city":"West End (Brisbane)",
    "sg:classifiers":[
        {
            "category":"Social Services",
            "subcategory":"Adult Care",
            "type":"Services"
        }
    ],
    "sg:phone":"+61 7 3846 1099",
    "sg:postcode":"4101",
    "sg:province":"QLD",
    "sg:tags":[
        "aged"
    ],
    "wof:name":"Diversicare",
    "wof:placetype":"venue"
},
  "geometry": {"coordinates":[153.011108398,-27.4810123444],"type":"Point"}
}