{
  "type": "Feature",
  "properties": {
    "addr:full":"2/ 5 King St Raymond Terrace NSW 2324",
    "addr:housenumber":"/ 5",
    "addr:postcode":"2324",
    "addr:street":"King St",
    "iso:country":"AU",
    "sg:address":"2/ 5 King St",
    "sg:city":"Raymond Terrace",
    "sg:classifiers":[
        {
            "category":"Professional",
            "subcategory":"Accounting & Tax Preparation",
            "type":"Services"
        }
    ],
    "sg:phone":"+61 2 4987 2413",
    "sg:postcode":"2324",
    "sg:province":"NSW",
    "sg:tags":[
        "consultant",
        "taxation"
    ],
    "wof:name":"Low Chris & Co",
    "wof:placetype":"venue"
},
  "geometry": {"coordinates":[151.74345398,-32.7598152161],"type":"Point"}
}