{
  "type": "Feature",
  "properties": {
    "addr:full":"7 Braddock St Robertson QLD 4109",
    "addr:housenumber":"7",
    "addr:postcode":"4109",
    "addr:street":"Braddock St",
    "iso:country":"AU",
    "sg:address":"7 Braddock St",
    "sg:city":"Robertson",
    "sg:classifiers":[
        {
            "category":"Travel",
            "subcategory":"Hostel",
            "type":"Entertainment"
        }
    ],
    "sg:phone":"+61 7 3344 1925",
    "sg:postcode":"4109",
    "sg:province":"QLD",
    "sg:tags":[
        "home"
    ],
    "wof:name":"Aveo Robertson Park",
    "wof:placetype":"venue"
},
  "geometry": {"coordinates":[153.05838012699999,-27.5707950592],"type":"Point"}
}