{
  "type": "Feature",
  "properties": {
    "addr:full":"1/ 52 Fitzmaurice St Wagga Wagga NSW 2650",
    "addr:housenumber":"/ 52",
    "addr:postcode":"2650",
    "addr:street":"Fitzmaurice St",
    "iso:country":"AU",
    "sg:address":"1/ 52 Fitzmaurice St",
    "sg:city":"Wagga Wagga",
    "sg:classifiers":[
        {
            "category":"Personal",
            "subcategory":"Beauty Salon",
            "type":"Services"
        }
    ],
    "sg:phone":"+61 2 6921 3190",
    "sg:postcode":"2650",
    "sg:province":"NSW",
    "wof:name":"Kanz World",
    "wof:placetype":"venue"
},
  "geometry": {"coordinates":[147.36988830600001,-35.1065139771],"type":"Point"}
}