{
  "type": "Feature",
  "properties": {
    "addr:full":"Washington Drv Bonnet Bay NSW 2226",
    "addr:postcode":"2226",
    "addr:street":"Washington Drv",
    "iso:country":"AU",
    "sg:address":"Washington Drv",
    "sg:city":"Bonnet Bay",
    "sg:classifiers":[
        {
            "category":"Building & Trades",
            "subcategory":"Plumbing",
            "type":"Services"
        }
    ],
    "sg:phone":"+61 2 9528 0076",
    "sg:postcode":"2226",
    "sg:province":"NSW",
    "sg:tags":[
        "plumber",
        "gasfitters"
    ],
    "wof:name":"Drip Plumbing",
    "wof:placetype":"venue"
},
  "geometry": {"coordinates":[151.05519104000001,-34.0111999512],"type":"Point"}
}