{
  "type": "Feature",
  "properties": {
    "addr:full":"George St Southport QLD 4215",
    "addr:postcode":"4215",
    "addr:street":"George St",
    "iso:country":"AU",
    "sg:address":"George St",
    "sg:city":"Southport",
    "sg:classifiers":[
        {
            "category":"Retail",
            "subcategory":"Auto Repair",
            "type":"Services"
        }
    ],
    "sg:phone":"+61 402 082 924",
    "sg:postcode":"4215",
    "sg:province":"QLD",
    "sg:tags":[
        "beater",
        "painter",
        "panel"
    ],
    "wof:name":"Shorts Panel Shop",
    "wof:placetype":"venue"
},
  "geometry": {"coordinates":[153.40592956500001,-27.9645404816],"type":"Point"}
}