{
  "type": "Feature",
  "properties": {
    "addr:full":"65 Batchelor St Queenstown TAS 7467",
    "addr:housenumber":"65",
    "addr:postcode":"7467",
    "addr:street":"Batchelor St",
    "iso:country":"AU",
    "sg:address":"65 Batchelor St",
    "sg:city":"Queenstown",
    "sg:classifiers":[
        {
            "category":"Travel",
            "subcategory":"Hotels & Motels",
            "type":"Entertainment"
        }
    ],
    "sg:phone":"+61 3 6471 1005",
    "sg:postcode":"7467",
    "sg:province":"TAS",
    "wof:name":"Comfort Inn Gold Rush",
    "wof:placetype":"venue"
},
  "geometry": {"coordinates":[145.56387329099999,-42.0749168396],"type":"Point"}
}