{
  "type": "Feature",
  "properties": {
    "addr:full":"U30/ 5 Hines Rd O&#039;Connor WA 6163",
    "addr:housenumber":"5",
    "addr:postcode":"6163",
    "addr:street":"/;Hines Rd",
    "iso:country":"AU",
    "sg:address":"U30/ 5 Hines Rd",
    "sg:city":"O&#039;Connor",
    "sg:classifiers":[
        {
            "category":"Professional",
            "subcategory":"Detective & Security Services",
            "type":"Services"
        }
    ],
    "sg:phone":"+61 8 9331 1402",
    "sg:postcode":"6163",
    "sg:province":"WA",
    "sg:tags":[
        "guard",
        "patrol"
    ],
    "wof:name":"Ronin Protective Services",
    "wof:placetype":"venue"
},
  "geometry": {"coordinates":[115.783913,-32.057899],"type":"Point"}
}