{
  "type": "Feature",
  "properties": {
    "addr:full":"171 Riding Rd Hawthorne QLD 4171",
    "addr:housenumber":"171",
    "addr:postcode":"4171",
    "addr:street":"Riding Rd",
    "iso:country":"AU",
    "sg:address":"171 Riding Rd",
    "sg:city":"Hawthorne",
    "sg:classifiers":[
        {
            "category":"Health Services",
            "subcategory":"Health Practitioner",
            "type":"Services"
        }
    ],
    "sg:phone":"+61 7 3899 1111",
    "sg:postcode":"4171",
    "sg:province":"QLD",
    "sg:tags":[
        "physiotherapist"
    ],
    "sg:website":"http://www.physiotherapy.asn.au",
    "wof:name":"Yvonne Morley Physiotherapy",
    "wof:placetype":"venue"
},
  "geometry": {"coordinates":[153.06367492699999,-27.4619884491],"type":"Point"}
}