{
  "type": "Feature",
  "properties": {
    "addr:full":"56 Mountjoy St Petrie Terrace QLD 4000",
    "addr:housenumber":"56",
    "addr:postcode":"4000",
    "addr:street":"Mountjoy St Petrie Terrace",
    "iso:country":"AU",
    "sg:address":"56 Mountjoy St",
    "sg:city":"Petrie Terrace",
    "sg:classifiers":[
        {
            "category":"Building & Trades",
            "subcategory":"Landscaping Services",
            "type":"Services"
        }
    ],
    "sg:phone":"+61 7 3832 9500",
    "sg:postcode":"4000",
    "sg:province":"QLD",
    "sg:tags":[
        "architect",
        "landscape"
    ],
    "wof:name":"Genus The Landscape Company Pty Ltd",
    "wof:placetype":"venue"
},
  "geometry": {"coordinates":[153.01312255900001,-27.4604816437],"type":"Point"}
}