{
  "type": "Feature",
  "properties": {
    "iso:country":"AU",
    "sg:address":"PO Box 7086",
    "sg:city":"Urangan",
    "sg:classifiers":[
        {
            "category":"Cafe",
            "type":"Food & Drink"
        }
    ],
    "sg:phone":"+61 7 4125 6703",
    "sg:postcode":"4655",
    "sg:province":"QLD",
    "wof:name":"Cafe Illusions",
    "wof:placetype":"venue"
},
  "geometry": {"coordinates":[152.896957,-25.28817],"type":"Point"}
}