{
  "type": "Feature",
  "properties": {
    "addr:full":"U3/ 6 Wingate Rd McGraths Hill NSW 2756",
    "addr:housenumber":"6",
    "addr:postcode":"2756",
    "addr:street":"U3 /;Wingate Rd",
    "iso:country":"AU",
    "sg:address":"U3/ 6 Wingate Rd",
    "sg:city":"McGraths Hill",
    "sg:classifiers":[
        {
            "category":"Shopping",
            "subcategory":"Computers & Home Electronics",
            "type":"Retail Goods"
        }
    ],
    "sg:phone":"+61 2 4587 8881",
    "sg:postcode":"2756",
    "sg:province":"NSW",
    "sg:tags":[
        "wholesaler",
        "mfrs",
        "part",
        "electronic"
    ],
    "wof:name":"Remus Technologies",
    "wof:placetype":"venue"
},
  "geometry": {"coordinates":[150.835693359,-33.6219940186],"type":"Point"}
}