{
  "type": "Feature",
  "properties": {
    "addr:full":"Unit 3/60-62 Dampier St Taminda NSW 2340",
    "addr:housenumber":"/ 60-62",
    "addr:postcode":"2340",
    "addr:street":"Dampier St",
    "iso:country":"AU",
    "sg:address":"Unit 3/60-62 Dampier St",
    "sg:city":"Taminda",
    "sg:classifiers":[
        {
            "category":"Building & Trades",
            "subcategory":"Construction",
            "type":"Services"
        }
    ],
    "sg:phone":"+61 2 6762 1919",
    "sg:postcode":"2340",
    "sg:province":"NSW",
    "sg:tags":[
        "polishing",
        "sanding",
        "floor"
    ],
    "wof:name":"Tamworth Timber Floors",
    "wof:placetype":"venue"
},
  "geometry": {"coordinates":[150.89849853499999,-31.0921764374],"type":"Point"}
}