{
  "type": "Feature",
  "properties": {
    "addr:full":"Cnr Sharp & Lambie Sts Cooma NSW 2630",
    "addr:postcode":"2630",
    "addr:street":"Cnr Sharp & Lambie Sts",
    "iso:country":"AU",
    "sg:address":"Cnr Sharp & Lambie Sts",
    "sg:city":"Cooma",
    "sg:classifiers":[
        {
            "category":"Manufacturing",
            "subcategory":"Food",
            "type":"Manufacturing & Wholesale Goods"
        }
    ],
    "sg:phone":"+61 2 6452 1858",
    "sg:postcode":"2630",
    "sg:province":"NSW",
    "sg:tags":[
        "function",
        "catering"
    ],
    "wof:name":"&#034;1858 On Lambie St&#034;",
    "wof:placetype":"venue"
},
  "geometry": {"coordinates":[149.11590576200001,-36.2350158691],"type":"Point"}
}