{
  "type": "Feature",
  "properties": {
    "iso:country":"AU",
    "sg:address":"221 Christine Ave",
    "sg:city":"Varsity Lakes",
    "sg:classifiers":[
        {
            "category":"Banks & Credit Unions",
            "subcategory":"Investment Brokerage",
            "type":"Services"
        }
    ],
    "sg:phone":"+61 7 5593 8494",
    "sg:postcode":"4227",
    "sg:province":"QLD",
    "sg:tags":[
        "management",
        "property"
    ],
    "wof:name":"Retail Investments (Qld) Pty Ltd",
    "wof:placetype":"venue"
},
  "geometry": {"coordinates":[153.40997314399999,-28.0857582092],"type":"Point"}
}