{
  "type": "Feature",
  "properties": {
    "addr:full":"U1/ 136 Wattle Ave Carramar NSW 2163",
    "addr:housenumber":"136",
    "addr:postcode":"2163",
    "addr:street":"U1 /;Wattle Ave",
    "iso:country":"AU",
    "sg:address":"U1/ 136 Wattle Ave",
    "sg:city":"Carramar",
    "sg:classifiers":[
        {
            "category":"Personal",
            "subcategory":"Beauty Salon",
            "type":"Services"
        }
    ],
    "sg:phone":"+61 2 9726 8041",
    "sg:postcode":"2163",
    "sg:province":"NSW",
    "sg:tags":[
        "hairdresser"
    ],
    "wof:name":"Lan Hair Unisex",
    "wof:placetype":"venue"
},
  "geometry": {"coordinates":[150.96510314899999,-33.8839912415],"type":"Point"}
}