{
  "type": "Feature",
  "properties": {
    "iso:country":"AU",
    "sg:address":"222 Leitchs Rd",
    "sg:city":"Brendale",
    "sg:classifiers":[
        {
            "category":"Recreation",
            "subcategory":"Water Park",
            "type":"Entertainment"
        }
    ],
    "sg:phone":"+61 7 3881 1904",
    "sg:postcode":"4500",
    "sg:province":"QLD",
    "sg:tags":[
        "control",
        "seepage"
    ],
    "wof:name":"Jaylon",
    "wof:placetype":"venue"
},
  "geometry": {"coordinates":[152.982345581,-27.32695961],"type":"Point"}
}