{
  "type": "Feature",
  "properties": {
    "iso:country":"AU",
    "sg:address":"76 Atkinson St",
    "sg:city":"Oakleigh",
    "sg:classifiers":[
        {
            "category":"Retail",
            "subcategory":"Auto Repair",
            "type":"Services"
        }
    ],
    "sg:phone":"+61 3 8506 2703",
    "sg:postcode":"3166",
    "sg:province":"VIC",
    "sg:tags":[
        "testing",
        "inspection",
        "motor",
        "vehicle"
    ],
    "wof:name":"Vehicle Maintenance & Testing Pty Ltd",
    "wof:placetype":"venue"
},
  "geometry": {"coordinates":[145.09356689399999,-37.8933525085],"type":"Point"}
}