{
  "type": "Feature",
  "properties": {
    "iso:country":"AU",
    "sg:address":"Centenary Drv",
    "sg:city":"Clarenza",
    "sg:classifiers":[
        {
            "category":"Professional",
            "subcategory":"Business Services",
            "type":"Services"
        }
    ],
    "sg:phone":"+61 2 6643 5820",
    "sg:postcode":"2460",
    "sg:province":"NSW",
    "sg:tags":[
        "drafting"
    ],
    "wof:name":"Coombs Linda",
    "wof:placetype":"venue"
},
  "geometry": {"coordinates":[152.96766662600001,-29.6892585754],"type":"Point"}
}