{
  "type": "Feature",
  "properties": {
    "addr:full":"PO Box 14006 Mt Sheridan QLD 4868",
    "addr:postcode":"4868",
    "iso:country":"AU",
    "sg:address":"PO Box 14006",
    "sg:city":"Mt Sheridan",
    "sg:classifiers":[
        {
            "category":"Home & Garden",
            "subcategory":"Carpets & Floor Coverings",
            "type":"Retail Goods"
        }
    ],
    "sg:phone":"+61 7 4045 0052",
    "sg:postcode":"4868",
    "sg:province":"QLD",
    "sg:tags":[
        "tile",
        "wall",
        "layer"
    ],
    "wof:name":"Frangiosa P & M",
    "wof:placetype":"venue"
},
  "geometry": {"coordinates":[145.74195861800001,-16.9764003754],"type":"Point"}
}