{
  "type": "Feature",
  "properties": {
    "iso:country":"AU",
    "sg:address":"Ste3c/ 14 Barralong Rd",
    "sg:city":"Erina",
    "sg:classifiers":[
        {
            "category":"Banks & Credit Unions",
            "subcategory":"Financial Services",
            "type":"Services"
        }
    ],
    "sg:phone":"+61 2 4320 0400",
    "sg:postcode":"2250",
    "sg:province":"NSW",
    "sg:tags":[
        "loan",
        "finance",
        "mortgage"
    ],
    "wof:name":"Finance Here",
    "wof:placetype":"venue"
},
  "geometry": {"coordinates":[151.38722229000001,-33.4335632324],"type":"Point"}
}