{
  "type": "Feature",
  "properties": {
    "addr:full":"Le Boulevard Shop3- 4 Elkhorn Ave Surfers Paradise QLD 4217",
    "addr:housenumber":"4",
    "addr:postcode":"4217",
    "addr:street":"Shop3;Elkhorn Ave",
    "iso:country":"AU",
    "sg:address":"Le Boulevard Shop3- 4 Elkhorn Ave",
    "sg:city":"Surfers Paradise",
    "sg:classifiers":[
        {
            "category":"Shopping",
            "subcategory":"Jewelry",
            "type":"Retail Goods"
        }
    ],
    "sg:phone":"+61 7 5592 3104",
    "sg:postcode":"4217",
    "sg:province":"QLD",
    "sg:tags":[
        "jeweller"
    ],
    "wof:name":"Hourglass",
    "wof:placetype":"venue"
},
  "geometry": {"coordinates":[153.430541992,-27.9990348816],"type":"Point"}
}