{
  "type": "Feature",
  "properties": {
    "addr:full":"405 High St Penrith NSW 2750",
    "addr:housenumber":"405",
    "addr:postcode":"2750",
    "addr:street":"High St",
    "iso:country":"AU",
    "sg:address":"405 High St",
    "sg:city":"Penrith",
    "sg:classifiers":[
        {
            "category":"Professional",
            "subcategory":"Accounting & Tax Preparation",
            "type":"Services"
        }
    ],
    "sg:phone":"+61 2 4721 0235",
    "sg:postcode":"2750",
    "sg:province":"NSW",
    "sg:tags":[
        "consultant",
        "taxation"
    ],
    "wof:name":"Hurney T.L. & Co.",
    "wof:placetype":"venue"
},
  "geometry": {"coordinates":[150.91557312,-33.8948745728],"type":"Point"}
}