{
  "type": "Feature",
  "properties": {
    "iso:country":"AU",
    "sg:address":"U10/ 1 Irwin Rd",
    "sg:city":"Wangara",
    "sg:classifiers":[
        {
            "category":"Wholesale",
            "subcategory":"Home Furnishings",
            "type":"Manufacturing & Wholesale Goods"
        }
    ],
    "sg:phone":"+61 8 9409 7622",
    "sg:postcode":"6065",
    "sg:province":"WA",
    "sg:tags":[
        "wholesaler",
        "curtain",
        "mfrs"
    ],
    "wof:name":"Mike Stacey Agencies",
    "wof:placetype":"venue"
},
  "geometry": {"coordinates":[115.82245636,-31.7899150848],"type":"Point"}
}