{
  "type": "Feature",
  "properties": {
    "addr:full":"Unit 6/ 14-14 Sir Joseph Banks Dr Botany NSW 2019",
    "addr:housenumber":"/ 14-14",
    "addr:postcode":"2019",
    "addr:street":"Sir Joseph Banks Dr",
    "iso:country":"AU",
    "sg:address":"Unit 6/ 14-14 Sir Joseph Banks Dr",
    "sg:city":"Botany",
    "sg:classifiers":[
        {
            "category":"Real Estate",
            "subcategory":"Architect",
            "type":"Services"
        }
    ],
    "sg:phone":"+61 2 9695 1900",
    "sg:postcode":"2019",
    "sg:province":"NSW",
    "sg:tags":[
        "builder",
        "repairer",
        "ship"
    ],
    "wof:name":"Forgacs Ship Repair",
    "wof:placetype":"venue"
},
  "geometry": {"coordinates":[151.20188903799999,-33.9519691467],"type":"Point"}
}