{
  "type": "Feature",
  "properties": {
    "addr:full":"720 Centre Rd Bentleigh East VIC 3165",
    "addr:housenumber":"720",
    "addr:postcode":"3165",
    "addr:street":"Centre Rd",
    "iso:country":"AU",
    "sg:address":"720 Centre Rd",
    "sg:city":"Bentleigh East",
    "sg:classifiers":[
        {
            "category":"Retail",
            "subcategory":"Laundry & Dry Cleaning",
            "type":"Services"
        }
    ],
    "sg:phone":"+61 3 9579 5811",
    "sg:postcode":"3165",
    "sg:province":"VIC",
    "wof:name":"L'Art Parisien Dry Cleaning & Laundry Service",
    "wof:placetype":"venue"
},
  "geometry": {"coordinates":[145.05801391599999,-37.9211196899],"type":"Point"}
}