{
  "type": "Feature",
  "properties": {
    "iso:country":"AU",
    "sg:address":"2- 6 Spit Rd",
    "sg:city":"Spit Junction",
    "sg:classifiers":[
        {
            "category":"Banks & Credit Unions",
            "subcategory":"Bank",
            "type":"Services"
        }
    ],
    "sg:phone":"+61 2 9969 1655",
    "sg:postcode":"2088",
    "sg:province":"NSW",
    "wof:name":"Colonial",
    "wof:placetype":"venue"
},
  "geometry": {"coordinates":[151.24098205600001,-33.8242797852],"type":"Point"}
}