{
  "type": "Feature",
  "properties": {
    "addr:full":"105 Myola Rd Myola QLD 4872",
    "addr:housenumber":"105",
    "addr:postcode":"4872",
    "addr:street":"Myola Rd",
    "iso:country":"AU",
    "sg:address":"105 Myola Rd",
    "sg:city":"Myola",
    "sg:classifiers":[
        {
            "category":"Building & Trades",
            "subcategory":"Construction",
            "type":"Services"
        }
    ],
    "sg:phone":"+61 418 184 662",
    "sg:postcode":"4872",
    "sg:province":"QLD",
    "sg:tags":[
        "joiner",
        "carpenter"
    ],
    "wof:name":"Vandersar M",
    "wof:placetype":"venue"
},
  "geometry": {"coordinates":[145.61419677699999,-16.8047676086],"type":"Point"}
}