{
  "type": "Feature",
  "properties": {
    "iso:country":"AU",
    "sg:address":"Shop 3, 29 Stockton St",
    "sg:city":"Nelson Bay",
    "sg:classifiers":[
        {
            "category":"Personal",
            "subcategory":"Beauty Salon",
            "type":"Services"
        }
    ],
    "sg:phone":"+61 2 4981 0022",
    "sg:postcode":"2315",
    "sg:province":"NSW",
    "wof:name":"Be Touched By Beauty",
    "wof:placetype":"venue"
},
  "geometry": {"coordinates":[152.143433,-32.722931],"type":"Point"}
}