{
  "type": "Feature",
  "properties": {
    "iso:country":"AU",
    "sg:address":"Glen Innes Hwy",
    "sg:city":"Inverell",
    "sg:classifiers":[
        {
            "category":"Manufacturing",
            "subcategory":"Jewelry",
            "type":"Manufacturing & Wholesale Goods"
        }
    ],
    "sg:phone":"+61 2 6723 2222",
    "sg:postcode":"2360",
    "sg:province":"NSW",
    "sg:tags":[
        "mfrg",
        "jeweller"
    ],
    "wof:name":"Dejon Sapphire Centre Pty Ltd",
    "wof:placetype":"venue"
},
  "geometry": {"coordinates":[151.113555908,-29.776309967],"type":"Point"}
}