{
  "type": "Feature",
  "properties": {
    "iso:country":"AU",
    "sg:address":"Level 3, 72 Mary Street, SURRY HILLS 2010",
    "sg:city":"Surry Hills",
    "sg:classifiers":[
        {
            "category":"Education",
            "subcategory":"Junior College",
            "type":"Public Place"
        }
    ],
    "sg:phone":"+61 2 9212 6322",
    "sg:postcode":"2010",
    "sg:province":"NSW",
    "sg:tags":[
        "business"
    ],
    "wof:name":"AFTA Travel & Tourism College Nsw",
    "wof:placetype":"venue"
},
  "geometry": {"coordinates":[151.20980835,-33.8827476501],"type":"Point"}
}