{
  "type": "Feature",
  "properties": {
    "addr:full":"141 Malop St Geelong VIC 3220",
    "addr:housenumber":"141",
    "addr:postcode":"3220",
    "addr:street":"Malop St",
    "iso:country":"AU",
    "sg:address":"141 Malop St",
    "sg:city":"Geelong",
    "sg:classifiers":[
        {
            "category":"Sports & Exercise",
            "subcategory":"Gym",
            "type":"Entertainment"
        }
    ],
    "sg:phone":"+61 3 5222 7988",
    "sg:postcode":"3220",
    "sg:province":"VIC",
    "sg:tags":[
        "health",
        "fitness"
    ],
    "wof:name":"Body Bronze",
    "wof:placetype":"venue"
},
  "geometry": {"coordinates":[144.36389199999999,-38.147903],"type":"Point"}
}