{
  "type": "Feature",
  "properties": {
    "addr:full":"4 Mathers La Hobart TAS 7000",
    "addr:housenumber":"4",
    "addr:postcode":"7000",
    "addr:street":"Mathers La",
    "iso:country":"AU",
    "sg:address":"4 Mathers La",
    "sg:city":"Hobart",
    "sg:classifiers":[
        {
            "category":"Health Services",
            "subcategory":"Dentist",
            "type":"Services"
        }
    ],
    "sg:phone":"+61 3 6234 4258",
    "sg:postcode":"7000",
    "sg:province":"TAS",
    "sg:tags":[
        "dental",
        "prosthetist"
    ],
    "wof:name":"Metzler R",
    "wof:placetype":"venue"
},
  "geometry": {"coordinates":[147.32562255900001,-42.8816986084],"type":"Point"}
}