{
  "type": "Feature",
  "properties": {
    "iso:country":"AU",
    "sg:address":"85 Rankin St",
    "sg:city":"Forbes",
    "sg:classifiers":[
        {
            "category":"Cafe",
            "type":"Food & Drink"
        }
    ],
    "sg:phone":"+61 2 6852 4310",
    "sg:postcode":"2871",
    "sg:province":"NSW",
    "wof:name":"Wattle Cafe",
    "wof:placetype":"venue"
},
  "geometry": {"coordinates":[148.007156,-33.383755],"type":"Point"}
}