{
  "type": "Feature",
  "properties": {
    "addr:full":"85 Rankin St Forbes NSW 2871",
    "addr:housenumber":"85",
    "addr:postcode":"2871",
    "addr:street":"Rankin St",
    "iso:country":"AU",
    "sg:address":"85 Rankin St",
    "sg:city":"Forbes",
    "sg:classifiers":[
        {
            "category":"Cafe",
            "type":"Food & Drink"
        }
    ],
    "sg:phone":"+61 2 6852 4310",
    "sg:postcode":"2871",
    "sg:province":"NSW",
    "wof:name":"Wattle Cafe",
    "wof:placetype":"venue"
},
  "geometry": {"coordinates":[148.00715600000001,-33.383755],"type":"Point"}
}