{
  "type": "Feature",
  "properties": {
    "addr:full":"Lv 2/ 693 Burke Rd Camberwell VIC 3124",
    "addr:housenumber":"693",
    "addr:postcode":"3124",
    "addr:street":"Burke Rd",
    "iso:country":"AU",
    "sg:address":"Lv 2/ 693 Burke Rd",
    "sg:city":"Camberwell",
    "sg:classifiers":[
        {
            "category":"Professional",
            "subcategory":"Management & Consulting",
            "type":"Services"
        }
    ],
    "sg:phone":"+61 3 9882 0555",
    "sg:postcode":"3124",
    "sg:province":"VIC",
    "sg:tags":[
        "consultant"
    ],
    "wof:name":"Panviva Pty Ltd",
    "wof:placetype":"venue"
},
  "geometry": {"coordinates":[145.05632019000001,-37.8324775696],"type":"Point"}
}