{
  "type": "Feature",
  "properties": {
    "iso:country":"AU",
    "sg:address":"30 Moore St",
    "sg:city":"Port Augusta",
    "sg:classifiers":[
        {
            "category":"Retail",
            "subcategory":"Driving School",
            "type":"Services"
        }
    ],
    "sg:phone":"+61 8 8642 6603",
    "sg:postcode":"5700",
    "sg:province":"SA",
    "wof:name":"Len Kay Driving School",
    "wof:placetype":"venue"
},
  "geometry": {"coordinates":[137.773635864,-32.4825592041],"type":"Point"}
}