{
  "type": "Feature",
  "properties": {
    "addr:full":"235 North Brunswick St Fitzroy VIC 3065",
    "addr:housenumber":"235",
    "addr:postcode":"3065",
    "addr:street":"North Brunswick St",
    "iso:country":"AU",
    "sg:address":"235 North Brunswick St",
    "sg:city":"Fitzroy",
    "sg:classifiers":[
        {
            "category":"Shopping",
            "subcategory":"Clothing, Apparel, & Fashions",
            "type":"Retail Goods"
        }
    ],
    "sg:phone":"+61 3 9419 5999",
    "sg:postcode":"3065",
    "sg:province":"VIC",
    "sg:tags":[
        "lady",
        "wear"
    ],
    "wof:name":"Gorman Industries Pty Ltd",
    "wof:placetype":"venue"
},
  "geometry": {"coordinates":[144.97795105,-37.8002433777],"type":"Point"}
}