{
  "type": "Feature",
  "properties": {
    "addr:full":"178 Brighton Rd Elsternwick VIC 3185",
    "addr:housenumber":"178",
    "addr:postcode":"3185",
    "addr:street":"Brighton Rd",
    "iso:country":"AU",
    "sg:address":"178 Brighton Rd",
    "sg:city":"Elsternwick",
    "sg:classifiers":[
        {
            "category":"Professional",
            "type":"Services"
        }
    ],
    "sg:phone":"+61 1300 881 498",
    "sg:postcode":"3185",
    "sg:province":"VIC",
    "sg:tags":[
        "auctioneer"
    ],
    "wof:name":"Lawsonsonline.com Pty Ltd",
    "wof:placetype":"venue"
},
  "geometry": {"coordinates":[144.99707031200001,-37.8834915161],"type":"Point"}
}