{
  "type": "Feature",
  "properties": {
    "addr:full":"3 Piesse Rd Katanning WA 6317",
    "addr:housenumber":"3",
    "addr:postcode":"6317",
    "addr:street":"Piesse Rd",
    "iso:country":"AU",
    "sg:address":"3 Piesse Rd",
    "sg:city":"Katanning",
    "sg:classifiers":[
        {
            "category":"Health Services",
            "subcategory":"Doctor",
            "type":"Services"
        }
    ],
    "sg:phone":"+61 8 9821 1699",
    "sg:postcode":"6317",
    "sg:province":"WA",
    "sg:tags":[
        "nurse",
        "nursing"
    ],
    "wof:name":"Silver Chain",
    "wof:placetype":"venue"
},
  "geometry": {"coordinates":[117.561401367,-33.6860656738],"type":"Point"}
}