{
  "type": "Feature",
  "properties": {
    "addr:full":"50 Enterprise St Mackay QLD 4740",
    "addr:housenumber":"50",
    "addr:postcode":"4740",
    "addr:street":"Enterprise St",
    "iso:country":"AU",
    "sg:address":"50 Enterprise St",
    "sg:city":"Mackay",
    "sg:classifiers":[
        {
            "category":"Retail",
            "subcategory":"Storage",
            "type":"Services"
        }
    ],
    "sg:phone":"+61 7 4952 4255",
    "sg:postcode":"4740",
    "sg:province":"QLD",
    "wof:name":"Hornicks Removals Pty Ltd",
    "wof:placetype":"venue"
},
  "geometry": {"coordinates":[149.15934799999999,-21.184355],"type":"Point"}
}