{
  "type": "Feature",
  "properties": {
    "addr:full":"683 Chapel St South Yarra VIC 3141",
    "addr:housenumber":"683",
    "addr:postcode":"3141",
    "addr:street":"Chapel St",
    "iso:country":"AU",
    "sg:address":"683 Chapel St",
    "sg:city":"South Yarra",
    "sg:classifiers":[
        {
            "category":"Autos & Motor Vehicles",
            "subcategory":"Automobile Sales",
            "type":"Retail Goods"
        }
    ],
    "sg:phone":"+61 3 9824 2188",
    "sg:postcode":"3141",
    "sg:province":"VIC",
    "sg:tags":[
        "car",
        "new"
    ],
    "wof:name":"South Yarra Automobiles",
    "wof:placetype":"venue"
},
  "geometry": {"coordinates":[144.996368408,-37.8349304199],"type":"Point"}
}