{
  "type": "Feature",
  "properties": {
    "addr:full":"10 Wheeler St Belmont WA 6104",
    "addr:housenumber":"10",
    "addr:postcode":"6104",
    "addr:street":"Wheeler St",
    "iso:country":"AU",
    "sg:address":"10 Wheeler St",
    "sg:city":"Belmont",
    "sg:classifiers":[
        {
            "category":"Landmark",
            "subcategory":"Fountain",
            "type":"Public Place"
        }
    ],
    "sg:phone":"+61 8 9277 7255",
    "sg:postcode":"6104",
    "sg:province":"WA",
    "sg:tags":[
        "wholesaler",
        "spring",
        "mfrs"
    ],
    "wof:name":"Plummer's Spring Works",
    "wof:placetype":"venue"
},
  "geometry": {"coordinates":[115.923240662,-31.9508934021],"type":"Point"}
}