{
  "type": "Feature",
  "properties": {
    "addr:full":"15 Osborne St Flora Hill VIC 3550",
    "addr:housenumber":"15",
    "addr:postcode":"3550",
    "addr:street":"Osborne St Flora Hill",
    "iso:country":"AU",
    "sg:address":"15 Osborne St",
    "sg:city":"Flora Hill",
    "sg:classifiers":[
        {
            "category":"Farming",
            "subcategory":"Farm & Veterinary Services",
            "type":"Manufacturing & Wholesale Goods"
        }
    ],
    "sg:phone":"+61 3 5442 2373",
    "sg:postcode":"3550",
    "sg:province":"VIC",
    "sg:tags":[
        "agricultural",
        "advisory"
    ],
    "wof:name":"Ag Energy",
    "wof:placetype":"venue"
},
  "geometry": {"coordinates":[144.29017639200001,-36.7810935974],"type":"Point"}
}