{
  "type": "Feature",
  "properties": {
    "addr:full":"14 Beatty St North Shore VIC 3214",
    "addr:housenumber":"14",
    "addr:postcode":"3214",
    "addr:street":"Beatty St",
    "iso:country":"AU",
    "sg:address":"14 Beatty St",
    "sg:city":"North Shore",
    "sg:classifiers":[
        {
            "category":"Shopping",
            "subcategory":"Clothing, Apparel, & Fashions",
            "type":"Retail Goods"
        }
    ],
    "sg:phone":"+61 3 5272 2343",
    "sg:postcode":"3214",
    "sg:province":"VIC",
    "sg:tags":[
        "lingerie",
        "hosiery",
        "sleepwear"
    ],
    "wof:name":"McAuliffe Marine Pty Ltd",
    "wof:placetype":"venue"
},
  "geometry": {"coordinates":[144.370849609,-38.094833374],"type":"Point"}
}