{
  "type": "Feature",
  "properties": {
    "iso:country":"AU",
    "sg:address":"47 Commercial St East",
    "sg:city":"Mt Gambier",
    "sg:classifiers":[
        {
            "category":"Shopping",
            "subcategory":"Baby Store",
            "type":"Retail Goods"
        }
    ],
    "sg:phone":"+61 8 8724 9000",
    "sg:postcode":"5290",
    "sg:province":"SA",
    "sg:tags":[
        "children's",
        "wear"
    ],
    "wof:name":"Limestone Coast Kids",
    "wof:placetype":"venue"
},
  "geometry": {"coordinates":[140.782303,-37.828781],"type":"Point"}
}