{
  "type": "Feature",
  "properties": {
    "addr:full":"PO Box 227 Woodcroft Town Centre Woodcroft SA 5162",
    "addr:postcode":"5162",
    "iso:country":"AU",
    "sg:address":"PO Box 227",
    "sg:city":"Woodcroft Town Centre Woodcroft",
    "sg:classifiers":[
        {
            "category":"Food & Beverages",
            "subcategory":"Specialty",
            "type":"Retail Goods"
        }
    ],
    "sg:phone":"+61 1300 797 801",
    "sg:postcode":"5162",
    "sg:province":"SA",
    "sg:tags":[
        "product",
        "health"
    ],
    "wof:name":"H2O &#039;N&#039; Go Australia Pty Ltd",
    "wof:placetype":"venue"
},
  "geometry": {"coordinates":[138.55705261200001,-35.1035385132],"type":"Point"}
}