{
  "type": "Feature",
  "properties": {
    "iso:country":"AU",
    "sg:address":"Suite 4/424- 426 Nepean Hwy",
    "sg:city":"Frankston",
    "sg:classifiers":[
        {
            "category":"Health Services",
            "subcategory":"Health Practitioner",
            "type":"Services"
        }
    ],
    "sg:phone":"+61 412 261 789",
    "sg:postcode":"3199",
    "sg:province":"VIC",
    "sg:tags":[
        "psychologist"
    ],
    "wof:name":"McDonald Joanne",
    "wof:placetype":"venue"
},
  "geometry": {"coordinates":[145.08319091800001,-37.9964599609],"type":"Point"}
}