{
  "type": "Feature",
  "properties": {
    "addr:full":"23- 25 Oxley St Taree NSW 2430",
    "addr:housenumber":"25",
    "addr:postcode":"2430",
    "addr:street":"Oxley St",
    "iso:country":"AU",
    "sg:address":"23- 25 Oxley St",
    "sg:city":"Taree",
    "sg:classifiers":[
        {
            "category":"Travel",
            "subcategory":"Hotels & Motels",
            "type":"Entertainment"
        }
    ],
    "sg:phone":"+61 2 6552 1455",
    "sg:postcode":"2430",
    "sg:province":"NSW",
    "wof:name":"Alabaster Lodge Motor Inn",
    "wof:placetype":"venue"
},
  "geometry": {"coordinates":[152.477417,-31.902582],"type":"Point"}
}