{
  "type": "Feature",
  "properties": {
    "iso:country":"AU",
    "sg:address":"143 Katoomba St",
    "sg:city":"Katoomba",
    "sg:classifiers":[
        {
            "category":"Health Services",
            "subcategory":"Doctor",
            "type":"Services"
        }
    ],
    "sg:phone":"+61 2 4782 2222",
    "sg:postcode":"2780",
    "sg:province":"NSW",
    "sg:tags":[
        "medical",
        "practitioner"
    ],
    "wof:name":"Shah R S",
    "wof:placetype":"venue"
},
  "geometry": {"coordinates":[150.31152343799999,-33.715171814],"type":"Point"}
}