{
  "type": "Feature",
  "properties": {
    "iso:country":"AU",
    "sg:address":"215 Linden Ave",
    "sg:city":"Boambee",
    "sg:classifiers":[
        {
            "category":"Education",
            "subcategory":"Kindergarten",
            "type":"Public Place"
        }
    ],
    "sg:phone":"+61 2 6658 3966",
    "sg:postcode":"2450",
    "sg:province":"NSW",
    "sg:tags":[
        "pre-schools"
    ],
    "wof:name":"Hopscotch Boambee",
    "wof:placetype":"venue"
},
  "geometry": {"coordinates":[153.078659,-30.346313],"type":"Point"}
}