{
  "type": "Feature",
  "properties": {
    "addr:full":"36 Payton Ave Roselands NSW 2196",
    "addr:housenumber":"36",
    "addr:postcode":"2196",
    "addr:street":"Payton Ave Roselands",
    "iso:country":"AU",
    "sg:address":"36 Payton Ave",
    "sg:city":"Roselands",
    "sg:classifiers":[
        {
            "category":"Professional",
            "subcategory":"Art Services",
            "type":"Services"
        }
    ],
    "sg:phone":"+61 2 9740 4359",
    "sg:postcode":"2196",
    "sg:province":"NSW",
    "sg:tags":[
        "decorator",
        "painter"
    ],
    "wof:name":"Anthony's Painting Service",
    "wof:placetype":"venue"
},
  "geometry": {"coordinates":[151.07011399999999,-33.932457],"type":"Point"}
}