{
  "type": "Feature",
  "properties": {
    "iso:country":"AU",
    "sg:address":"5 Maralinga Drv",
    "sg:city":"Chigwell",
    "sg:classifiers":[
        {
            "category":"Professional",
            "subcategory":"Art Services",
            "type":"Services"
        }
    ],
    "sg:phone":"+61 408 128 989",
    "sg:postcode":"7011",
    "sg:province":"TAS",
    "sg:tags":[
        "decorator",
        "painter"
    ],
    "wof:name":"Rogers Garry",
    "wof:placetype":"venue"
},
  "geometry": {"coordinates":[147.25148010300001,-42.7987823486],"type":"Point"}
}