{
  "type": "Feature",
  "properties": {
    "addr:full":"Dry Poles Rd Ellendale TAS 7140",
    "addr:postcode":"7140",
    "addr:street":"Poles Rd",
    "iso:country":"AU",
    "sg:address":"Dry Poles Rd",
    "sg:city":"Ellendale",
    "sg:classifiers":[
        {
            "category":"Farming",
            "subcategory":"Farm",
            "type":"Manufacturing & Wholesale Goods"
        }
    ],
    "sg:phone":"+61 3 6288 1117",
    "sg:postcode":"7140",
    "sg:province":"TAS",
    "sg:tags":[
        "farmer"
    ],
    "wof:name":"Rayner B D",
    "wof:placetype":"venue"
},
  "geometry": {"coordinates":[146.741501,-42.639954],"type":"Point"}
}