{
  "type": "Feature",
  "properties": {
    "iso:country":"AU",
    "sg:address":"144 Beenleigh-Beaudesert Rd",
    "sg:city":"Tamborine",
    "sg:classifiers":[
        {
            "category":"Personal",
            "subcategory":"Beauty Salon",
            "type":"Services"
        }
    ],
    "sg:phone":"+61 423 259 180",
    "sg:postcode":"4270",
    "sg:province":"QLD",
    "sg:tags":[
        "supply",
        "artist",
        "make-up"
    ],
    "wof:name":"Lynne Dixon",
    "wof:placetype":"venue"
},
  "geometry": {"coordinates":[153.13044738799999,-27.8806591034],"type":"Point"}
}