{
  "type": "Feature",
  "properties": {
    "addr:full":"(Cnr Burwood Hwy & Middleborough Rd) Burwood East VIC 3151",
    "addr:postcode":"3151",
    "addr:street":"Burwood Hwy & Middleborough Rd",
    "iso:country":"AU",
    "sg:address":"(Cnr Burwood Hwy",
    "sg:city":"& Middleborough Rd) Burwood East",
    "sg:classifiers":[
        {
            "category":"Health Services",
            "subcategory":"Optometrist",
            "type":"Services"
        }
    ],
    "sg:phone":"+61 3 9808 6050",
    "sg:postcode":"3151",
    "sg:province":"VIC",
    "wof:name":"Gioia Mr Attilio",
    "wof:placetype":"venue"
},
  "geometry": {"coordinates":[145.15034484899999,-37.8537216187],"type":"Point"}
}