{
  "type": "Feature",
  "properties": {
    "iso:country":"AU",
    "sg:address":"100 Wallace St",
    "sg:city":"Colac",
    "sg:classifiers":[
        {
            "category":"Commercial Area",
            "type":"Public Place"
        }
    ],
    "sg:phone":"+61 3 5231 5922",
    "sg:postcode":"3250",
    "sg:province":"VIC",
    "sg:tags":[
        "heavy",
        "carrier"
    ],
    "wof:name":"Amezdroz & Son Pty Ltd",
    "wof:placetype":"venue"
},
  "geometry": {"coordinates":[143.599564,-38.341393],"type":"Point"}
}