{
  "type": "Feature",
  "properties": {
    "iso:country":"AU",
    "sg:address":"236 Melville Rd",
    "sg:city":"Pascoe Vale",
    "sg:classifiers":[
        {
            "category":"Social Services",
            "subcategory":"Child Care",
            "type":"Services"
        }
    ],
    "sg:phone":"+61 3 9350 2026",
    "sg:postcode":"3044",
    "sg:province":"VIC",
    "wof:name":"Coburg & Pascoe Vale South Child Minding Centre",
    "wof:placetype":"venue"
},
  "geometry": {"coordinates":[144.94566345199999,-37.7400512695],"type":"Point"}
}