{
  "type": "Feature",
  "properties": {
    "iso:country":"AU",
    "sg:address":"Cowalellup Rd",
    "sg:city":"Gairdner",
    "sg:classifiers":[
        {
            "category":"Farming",
            "subcategory":"Farm",
            "type":"Manufacturing & Wholesale Goods"
        }
    ],
    "sg:phone":"+61 8 9836 1002",
    "sg:postcode":"6337",
    "sg:province":"WA",
    "sg:tags":[
        "farmer"
    ],
    "wof:name":"Leonhardt J & M & Co",
    "wof:placetype":"venue"
},
  "geometry": {"coordinates":[118.843048096,-34.2198028564],"type":"Point"}
}