{
  "type": "Feature",
  "properties": {
    "iso:country":"AU",
    "sg:address":"256 Leitchs Rd",
    "sg:city":"Brendale",
    "sg:classifiers":[
        {
            "category":"Structure",
            "subcategory":"Bridge",
            "type":"Public Place"
        }
    ],
    "sg:phone":"+61 13 11 97",
    "sg:postcode":"4500",
    "sg:province":"QLD",
    "sg:tags":[
        "chainsaw",
        "brushcutters"
    ],
    "wof:name":"The Mower Supastore",
    "wof:placetype":"venue"
},
  "geometry": {"coordinates":[152.98118591299999,-27.3165111542],"type":"Point"}
}