{
  "type": "Feature",
  "properties": {
    "iso:country":"AU",
    "sg:address":"PO Box 1736",
    "sg:city":"Port Macquarie",
    "sg:classifiers":[
        {
            "category":"Social Services",
            "subcategory":"Retirement Home",
            "type":"Services"
        }
    ],
    "sg:phone":"+61 2 6584 3515",
    "sg:postcode":"2444",
    "sg:province":"NSW",
    "sg:tags":[
        "village"
    ],
    "wof:name":"Catholic Care Of The Aged",
    "wof:placetype":"venue"
},
  "geometry": {"coordinates":[152.908173,-31.4296],"type":"Point"}
}