{
  "type": "Feature",
  "properties": {
    "iso:country":"AU",
    "sg:address":"101 Ilford Ave",
    "sg:city":"Arcadia Vale",
    "sg:classifiers":[
        {
            "category":"Shopping",
            "subcategory":"Crafts & Fabrics",
            "type":"Retail Goods"
        }
    ],
    "sg:phone":"+61 2 4975 5201",
    "sg:postcode":"2283",
    "sg:province":"NSW",
    "sg:tags":[
        "supply"
    ],
    "wof:name":"Josco Lace Supplies",
    "wof:placetype":"venue"
},
  "geometry": {"coordinates":[151.584152222,-33.0588798523],"type":"Point"}
}