{
  "type": "Feature",
  "properties": {
    "addr:full":"8/ 78 Glendenning Rd Glendenning NSW 2761",
    "addr:housenumber":"/ 78",
    "addr:postcode":"2761",
    "addr:street":"Glendenning Rd",
    "iso:country":"AU",
    "sg:address":"8/ 78 Glendenning Rd",
    "sg:city":"Glendenning",
    "sg:classifiers":[
        {
            "category":"Arts & Performance",
            "subcategory":"Dance",
            "type":"Entertainment"
        }
    ],
    "sg:phone":"+61 410 665 901",
    "sg:postcode":"2761",
    "sg:province":"NSW",
    "sg:tags":[
        "theatrical",
        "ballet",
        "tuition"
    ],
    "wof:name":"Dance Junction",
    "wof:placetype":"venue"
},
  "geometry": {"coordinates":[150.85316499999999,-33.749332],"type":"Point"}
}