{
  "type": "Feature",
  "properties": {
    "iso:country":"AU",
    "sg:address":"8/ 78 Glendenning Rd",
    "sg:city":"Glendenning",
    "sg:classifiers":[
        {
            "category":"Arts & Performance",
            "subcategory":"Dance",
            "type":"Entertainment"
        }
    ],
    "sg:phone":"+61 410 665 901",
    "sg:postcode":"2761",
    "sg:province":"NSW",
    "sg:tags":[
        "theatrical",
        "ballet",
        "tuition"
    ],
    "wof:name":"Dance Junction",
    "wof:placetype":"venue"
},
  "geometry": {"coordinates":[150.853165,-33.749332],"type":"Point"}
}