{
  "type": "Feature",
  "properties": {
    "addr:full":"Glen Davidson Drv Snowtown SA 5520",
    "addr:postcode":"5520",
    "addr:street":"Davidson Drv",
    "iso:country":"AU",
    "sg:address":"Glen Davidson Drv",
    "sg:city":"Snowtown",
    "sg:classifiers":[
        {
            "category":"Education",
            "subcategory":"Kindergarten",
            "type":"Public Place"
        }
    ],
    "sg:phone":"+61 8 8865 2195",
    "sg:postcode":"5520",
    "sg:province":"SA",
    "sg:tags":[
        "pre-schools"
    ],
    "wof:name":"Snowtown Kindergarten",
    "wof:placetype":"venue"
},
  "geometry": {"coordinates":[138.21907043499999,-33.7837371826],"type":"Point"}
}