{
  "type": "Feature",
  "properties": {
    "addr:full":"Level 7, 70 Pirie St Adelaide SA 5000",
    "addr:housenumber":"70",
    "addr:postcode":"5000",
    "addr:street":"Pirie St",
    "iso:country":"AU",
    "sg:address":"Level 7, 70 Pirie St",
    "sg:city":"Adelaide",
    "sg:classifiers":[
        {
            "category":"Insurance",
            "subcategory":"Insurance Agent",
            "type":"Services"
        }
    ],
    "sg:phone":"+61 8 8232 1911",
    "sg:postcode":"5000",
    "sg:province":"SA",
    "sg:tags":[
        "broker"
    ],
    "wof:name":"Grand West Pty Ltd",
    "wof:placetype":"venue"
},
  "geometry": {"coordinates":[138.60226440400001,-34.9255142212],"type":"Point"}
}