{
  "type": "Feature",
  "properties": {
    "addr:full":"2745 Gold Coast Hwy Broadbeach QLD 4218",
    "addr:housenumber":"2745",
    "addr:postcode":"4218",
    "addr:street":"Gold Coast Hwy",
    "iso:country":"AU",
    "sg:address":"2745 Gold Coast Hwy",
    "sg:city":"Broadbeach",
    "sg:classifiers":[
        {
            "category":"Autos & Motor Vehicles",
            "subcategory":"Fuel & Gas Station",
            "type":"Retail Goods"
        }
    ],
    "sg:phone":"+61 7 5539 8835",
    "sg:postcode":"4218",
    "sg:province":"QLD",
    "wof:name":"Ampol Broadbeach",
    "wof:placetype":"venue"
},
  "geometry": {"coordinates":[153.42936706500001,-28.025598526],"type":"Point"}
}