{
  "type": "Feature",
  "properties": {
    "iso:country":"AU",
    "sg:address":"1699 Ipswich Rd",
    "sg:city":"Rocklea",
    "sg:classifiers":[
        {
            "category":"Autos & Motor Vehicles",
            "subcategory":"Automobile Sales",
            "type":"Retail Goods"
        }
    ],
    "sg:phone":"+61 7 3275 8745",
    "sg:postcode":"4106",
    "sg:province":"QLD",
    "sg:tags":[
        "bus",
        "truck",
        "new"
    ],
    "wof:name":"DaimerChrysler Commercial Vehicles",
    "wof:placetype":"venue"
},
  "geometry": {"coordinates":[153.00511169399999,-27.557510376],"type":"Point"}
}