{
  "type": "Feature",
  "properties": {
    "addr:full":"43 Santa Monica Ave Coolum Beach QLD 4573",
    "addr:housenumber":"43",
    "addr:postcode":"4573",
    "addr:street":"Santa Monica Ave",
    "iso:country":"AU",
    "sg:address":"43 Santa Monica Ave",
    "sg:city":"Coolum Beach",
    "sg:classifiers":[
        {
            "category":"Health Services",
            "subcategory":"Health Practitioner",
            "type":"Services"
        }
    ],
    "sg:phone":"+61 7 5471 6778",
    "sg:postcode":"4573",
    "sg:province":"QLD",
    "sg:tags":[
        "acupuncture"
    ],
    "wof:name":"Kingston, Lynda Roxanne",
    "wof:placetype":"venue"
},
  "geometry": {"coordinates":[153.08622700000001,-26.531218],"type":"Point"}
}