{
  "type": "Feature",
  "properties": {
    "addr:full":"112 Bundall Rd Bundall QLD 4217",
    "addr:housenumber":"112",
    "addr:postcode":"4217",
    "addr:street":"Bundall Rd",
    "iso:country":"AU",
    "sg:address":"112 Bundall Rd",
    "sg:city":"Bundall",
    "sg:classifiers":[
        {
            "category":"Manufacturing",
            "subcategory":"Electronics",
            "type":"Manufacturing & Wholesale Goods"
        }
    ],
    "sg:phone":"+61 7 5526 2611",
    "sg:postcode":"4217",
    "sg:province":"QLD",
    "sg:tags":[
        "wholesaler",
        "equipment",
        "part",
        "mfrs",
        "refrigeration"
    ],
    "wof:name":"Interfridge Australia",
    "wof:placetype":"venue"
},
  "geometry": {"coordinates":[153.41331481899999,-28.00365448],"type":"Point"}
}