{
  "type": "Feature",
  "properties": {
    "addr:full":"30 Montgomery St Kogarah NSW 2217",
    "addr:housenumber":"30",
    "addr:postcode":"2217",
    "addr:street":"Montgomery St",
    "iso:country":"AU",
    "sg:address":"30 Montgomery St",
    "sg:city":"Kogarah",
    "sg:classifiers":[
        {
            "category":"Social Services",
            "subcategory":"Retirement Home",
            "type":"Services"
        }
    ],
    "sg:phone":"+61 2 9587 6584",
    "sg:postcode":"2217",
    "sg:province":"NSW",
    "sg:tags":[
        "village"
    ],
    "wof:name":"St Vincent De Paul Society Aged Homes",
    "wof:placetype":"venue"
},
  "geometry": {"coordinates":[151.13453699999999,-33.964066],"type":"Point"}
}