{
  "type": "Feature",
  "properties": {
    "addr:full":"92 Laxton Rd Palmview QLD 4553",
    "addr:housenumber":"92",
    "addr:postcode":"4553",
    "addr:street":"Laxton Rd",
    "iso:country":"AU",
    "sg:address":"92 Laxton Rd",
    "sg:city":"Palmview",
    "sg:classifiers":[
        {
            "category":"Building & Trades",
            "subcategory":"Landscaping Services",
            "type":"Services"
        }
    ],
    "sg:phone":"+61 408 193 362",
    "sg:postcode":"4553",
    "sg:province":"QLD",
    "sg:tags":[
        "designer",
        "landscape",
        "contractor"
    ],
    "wof:name":"Can Do Bobcat Hire",
    "wof:placetype":"venue"
},
  "geometry": {"coordinates":[153.05444299999999,-26.763638],"type":"Point"}
}