{
  "type": "Feature",
  "properties": {
    "iso:country":"AU",
    "sg:address":"117 Ramsay St",
    "sg:city":"Haberfield",
    "sg:classifiers":[
        {
            "category":"Food & Beverages",
            "subcategory":"Liquor & Beverages",
            "type":"Retail Goods"
        }
    ],
    "sg:phone":"+61 2 9798 4128",
    "sg:postcode":"2045",
    "sg:province":"NSW",
    "sg:tags":[
        "store"
    ],
    "wof:name":"Haberfield Cellars",
    "wof:placetype":"venue"
},
  "geometry": {"coordinates":[151.13949600000001,-33.881023],"type":"Point"}
}