{
  "type": "Feature",
  "properties": {
    "iso:country":"AU",
    "sg:address":"20 Yamala Drv",
    "sg:city":"Mt Eliza",
    "sg:classifiers":[
        {
            "category":"Building & Trades",
            "subcategory":"Landscaping Services",
            "type":"Services"
        }
    ],
    "sg:phone":"+61 425 712 326",
    "sg:postcode":"3930",
    "sg:province":"VIC",
    "sg:tags":[
        "gardener"
    ],
    "wof:name":"Scotts House & Garden Maintenance",
    "wof:placetype":"venue"
},
  "geometry": {"coordinates":[145.100463867,-38.1630516052],"type":"Point"}
}