{
  "type": "Feature",
  "properties": {
    "iso:country":"AU",
    "sg:address":"Wintergarden Cntr",
    "sg:city":"Brisbane",
    "sg:classifiers":[
        {
            "category":"Shopping",
            "subcategory":"Clothing, Apparel, & Fashions",
            "type":"Retail Goods"
        }
    ],
    "sg:phone":"+61 7 3221 9565",
    "sg:postcode":"4000",
    "sg:province":"QLD",
    "sg:tags":[
        "lady",
        "wear"
    ],
    "wof:name":"Maggie T",
    "wof:placetype":"venue"
},
  "geometry": {"coordinates":[153.02459716800001,-27.4702949524],"type":"Point"}
}