{
  "type": "Feature",
  "properties": {
    "addr:full":"1st Flr, 64 Talbragar St Dubbo NSW 2830",
    "addr:housenumber":"64",
    "addr:postcode":"2830",
    "addr:street":"Talbragar St",
    "iso:country":"AU",
    "sg:address":"1st Flr, 64 Talbragar St",
    "sg:city":"Dubbo",
    "sg:classifiers":[
        {
            "category":"Real Estate",
            "subcategory":"Surveying",
            "type":"Services"
        }
    ],
    "sg:phone":"+61 2 6882 4833",
    "sg:postcode":"2830",
    "sg:province":"NSW",
    "sg:tags":[
        "surveyor",
        "land"
    ],
    "wof:name":"Imrie, Astley & Associate",
    "wof:placetype":"venue"
},
  "geometry": {"coordinates":[148.603607178,-32.2449111938],"type":"Point"}
}