{
  "type": "Feature",
  "properties": {
    "iso:country":"AU",
    "sg:address":"Cnr Maurice & Adelaide Rds",
    "sg:city":"Murray Bridge",
    "sg:classifiers":[
        {
            "category":"Wholesale",
            "subcategory":"Machinery & Supplies",
            "type":"Manufacturing & Wholesale Goods"
        }
    ],
    "sg:phone":"+61 8 8531 2244",
    "sg:postcode":"5253",
    "sg:province":"SA",
    "sg:tags":[
        "agricultural"
    ],
    "wof:name":"John Payne Ag",
    "wof:placetype":"venue"
},
  "geometry": {"coordinates":[139.26742553700001,-35.1384849548],"type":"Point"}
}