{
  "type": "Feature",
  "properties": {
    "iso:country":"AU",
    "sg:address":"34 Ocean St",
    "sg:city":"Bondi",
    "sg:classifiers":[
        {
            "category":"Education",
            "subcategory":"Kindergarten",
            "type":"Public Place"
        }
    ],
    "sg:phone":"+61 2 9386 1948",
    "sg:postcode":"2026",
    "sg:province":"NSW",
    "sg:tags":[
        "pre-schools"
    ],
    "wof:name":"Bondi VIP Long Day Preschool",
    "wof:placetype":"venue"
},
  "geometry": {"coordinates":[151.2628479,-33.8924674988],"type":"Point"}
}