{
  "type": "Feature",
  "properties": {
    "addr:full":"Level 2/ 92 Chandos St St Leonards NSW 2065",
    "addr:housenumber":"/ 92",
    "addr:postcode":"2065",
    "addr:street":"Chandos St",
    "iso:country":"AU",
    "sg:address":"Level 2/ 92 Chandos St",
    "sg:city":"St Leonards",
    "sg:classifiers":[
        {
            "category":"Professional",
            "subcategory":"Research",
            "type":"Services"
        }
    ],
    "sg:phone":"+61 2 8436 8222",
    "sg:postcode":"2065",
    "sg:province":"NSW",
    "sg:tags":[
        "market"
    ],
    "wof:name":"The Digital Connection Group Australia",
    "wof:placetype":"venue"
},
  "geometry": {"coordinates":[151.19985961899999,-33.8219032288],"type":"Point"}
}