{
  "type": "Feature",
  "properties": {
    "addr:full":"6a Lichfield St Victoria Park WA 6100",
    "addr:housenumber":"6a",
    "addr:postcode":"6100",
    "addr:street":"Lichfield St",
    "iso:country":"AU",
    "sg:address":"6a Lichfield St",
    "sg:city":"Victoria Park",
    "sg:classifiers":[
        {
            "category":"Education",
            "subcategory":"Kindergarten",
            "type":"Public Place"
        }
    ],
    "sg:phone":"+61 8 9361 2943",
    "sg:postcode":"6100",
    "sg:province":"WA",
    "sg:tags":[
        "pre-schools"
    ],
    "wof:name":"South Bank Montessori",
    "wof:placetype":"venue"
},
  "geometry": {"coordinates":[115.898727417,-31.9749965668],"type":"Point"}
}