{
  "type": "Feature",
  "properties": {
    "addr:full":"390 Stuart Hwy Winnellie NT 0820",
    "addr:housenumber":"390",
    "addr:postcode":"nt 0820",
    "addr:street":"Stuart Hwy",
    "iso:country":"AU",
    "sg:address":"390 Stuart Hwy",
    "sg:city":"Winnellie",
    "sg:classifiers":[
        {
            "category":"Shopping",
            "subcategory":"Stationery & Office Supplies",
            "type":"Retail Goods"
        }
    ],
    "sg:phone":"+61 8 8922 2444",
    "sg:postcode":"0820",
    "sg:province":"NT",
    "wof:name":"Darwin Office Technology",
    "wof:placetype":"venue"
},
  "geometry": {"coordinates":[130.870803833,-12.4255065918],"type":"Point"}
}