{
  "type": "Feature",
  "properties": {
    "addr:full":"115 Maloney St Mascot NSW 2020",
    "addr:housenumber":"115",
    "addr:postcode":"2020",
    "addr:street":"Maloney St",
    "iso:country":"AU",
    "sg:address":"115 Maloney St",
    "sg:city":"Mascot",
    "sg:classifiers":[
        {
            "category":"Retail",
            "subcategory":"Laundry & Dry Cleaning",
            "type":"Services"
        }
    ],
    "sg:phone":"+61 2 9669 3238",
    "sg:postcode":"2020",
    "sg:province":"NSW",
    "wof:name":"Maloney St Laundrette",
    "wof:placetype":"venue"
},
  "geometry": {"coordinates":[151.20521545400001,-33.930683136],"type":"Point"}
}