{
  "type": "Feature",
  "properties": {
    "addr:full":"3 Purchase Rd Cherrybrook NSW 2126",
    "addr:housenumber":"3",
    "addr:postcode":"2126",
    "addr:street":"Purchase Rd",
    "iso:country":"AU",
    "sg:address":"3 Purchase Rd",
    "sg:city":"Cherrybrook",
    "sg:classifiers":[
        {
            "category":"Professional",
            "subcategory":"Computer Services",
            "type":"Services"
        }
    ],
    "sg:phone":"+61 418 809 980",
    "sg:postcode":"2126",
    "sg:province":"NSW",
    "sg:tags":[
        "consultant",
        "system"
    ],
    "wof:name":"Pro-Connections Pty Ltd",
    "wof:placetype":"venue"
},
  "geometry": {"coordinates":[151.035324097,-33.7216377258],"type":"Point"}
}