{
  "type": "Feature",
  "properties": {
    "addr:full":"L39/ 2 Park St Sydney NSW 2000",
    "addr:housenumber":"l39 / 2",
    "addr:postcode":"2000",
    "addr:street":"Park St",
    "iso:country":"AU",
    "sg:address":"L39/ 2 Park St",
    "sg:city":"Sydney",
    "sg:classifiers":[
        {
            "category":"Professional",
            "subcategory":"Management & Consulting",
            "type":"Services"
        }
    ],
    "sg:phone":"+61 1300 306 579",
    "sg:postcode":"2000",
    "sg:province":"NSW",
    "sg:tags":[
        "consultant",
        "migration"
    ],
    "sg:website":"http://www.voitins.com.au",
    "wof:name":"Voitin Lawyers",
    "wof:placetype":"venue"
},
  "geometry": {"coordinates":[151.20773315400001,-33.8729286194],"type":"Point"}
}