{
  "type": "Feature",
  "properties": {
    "iso:country":"AU",
    "sg:address":"1/ 85a Ocean St",
    "sg:city":"Woollahra",
    "sg:classifiers":[
        {
            "category":"Real Estate",
            "subcategory":"Real Estate Agent",
            "type":"Services"
        }
    ],
    "sg:phone":"+61 2 9328 4845",
    "sg:postcode":"2025",
    "sg:province":"NSW",
    "sg:tags":[
        "export"
    ],
    "wof:name":"Commerce-Link Australia",
    "wof:placetype":"venue"
},
  "geometry": {"coordinates":[151.238739014,-33.8827590942],"type":"Point"}
}