{
  "type": "Feature",
  "properties": {
    "addr:full":"284 High St Lismore NSW 2480",
    "addr:housenumber":"284",
    "addr:postcode":"2480",
    "addr:street":"High St",
    "iso:country":"AU",
    "sg:address":"284 High St",
    "sg:city":"Lismore",
    "sg:classifiers":[
        {
            "category":"Wholesale",
            "subcategory":"Apparel",
            "type":"Manufacturing & Wholesale Goods"
        }
    ],
    "sg:phone":"+61 416 099 430",
    "sg:postcode":"2480",
    "sg:province":"NSW",
    "sg:tags":[
        "wholesaler",
        "mfrs",
        "cap",
        "hat"
    ],
    "wof:name":"Subreco Designs By Sue",
    "wof:placetype":"venue"
},
  "geometry": {"coordinates":[153.304397583,-28.8103199005],"type":"Point"}
}