{
  "type": "Feature",
  "properties": {
    "iso:country":"AU",
    "sg:address":"1b Graham Hill Rd",
    "sg:city":"Narellan",
    "sg:classifiers":[
        {
            "category":"Wholesale",
            "subcategory":"Metals & Minerals",
            "type":"Manufacturing & Wholesale Goods"
        }
    ],
    "sg:phone":"+61 2 4646 1566",
    "sg:postcode":"2567",
    "sg:province":"NSW",
    "sg:tags":[
        "steel",
        "merchant"
    ],
    "wof:name":"Steel Supply Co.",
    "wof:placetype":"venue"
},
  "geometry": {"coordinates":[150.738006592,-34.0428733826],"type":"Point"}
}