{
  "type": "Feature",
  "properties": {
    "addr:full":"suit 601 51 Rawson St Epping NSW 1710",
    "addr:postcode":"51;1710",
    "addr:street":"Rawson St",
    "iso:country":"AU",
    "sg:address":"suit 601 51 Rawson St",
    "sg:city":"Epping",
    "sg:classifiers":[
        {
            "category":"Health Services",
            "subcategory":"Health Practitioner",
            "type":"Services"
        }
    ],
    "sg:phone":"+61 419 803 541",
    "sg:postcode":"1710",
    "sg:province":"NSW",
    "sg:tags":[
        "psychologist"
    ],
    "wof:name":"Work Place Health",
    "wof:placetype":"venue"
},
  "geometry": {"coordinates":[151.08062744099999,-33.772693634],"type":"Point"}
}