{
  "type": "Feature",
  "properties": {
    "addr:full":"479 Underwood Rd Rochedale South QLD 4123",
    "addr:housenumber":"479",
    "addr:postcode":"4123",
    "addr:street":"Underwood Rd",
    "iso:country":"AU",
    "sg:address":"479 Underwood Rd",
    "sg:city":"Rochedale South",
    "sg:classifiers":[
        {
            "category":"Health Services",
            "subcategory":"Health Practitioner",
            "type":"Services"
        }
    ],
    "sg:phone":"+61 7 3341 1538",
    "sg:postcode":"4123",
    "sg:province":"QLD",
    "sg:tags":[
        "naturopath"
    ],
    "wof:name":"Rochedale Acupuncture & Naturopathy",
    "wof:placetype":"venue"
},
  "geometry": {"coordinates":[153.14125060999999,-27.5992202759],"type":"Point"}
}