{
  "type": "Feature",
  "properties": {
    "iso:country":"AU",
    "sg:address":"110 Crown Rd",
    "sg:city":"Queenscliff",
    "sg:classifiers":[
        {
            "category":"Professional",
            "subcategory":"Art Services",
            "type":"Services"
        }
    ],
    "sg:phone":"+61 2 9401 0291",
    "sg:postcode":"2096",
    "sg:province":"NSW",
    "sg:tags":[
        "interior",
        "decorator"
    ],
    "wof:name":"Colour Designs",
    "wof:placetype":"venue"
},
  "geometry": {"coordinates":[151.28314209000001,-33.7809906006],"type":"Point"}
}