{
  "type": "Feature",
  "properties": {
    "iso:country":"AU",
    "sg:address":"115- 117 Unley Rd",
    "sg:city":"Unley",
    "sg:classifiers":[
        {
            "category":"Sports & Exercise",
            "subcategory":"Gym",
            "type":"Entertainment"
        }
    ],
    "sg:phone":"+61 8 8272 3500",
    "sg:postcode":"5061",
    "sg:province":"SA",
    "sg:tags":[
        "personal",
        "trainer",
        "fitness"
    ],
    "wof:name":"Life Personal Trainers",
    "wof:placetype":"venue"
},
  "geometry": {"coordinates":[138.60743713400001,-34.948097229],"type":"Point"}
}