{
  "type": "Feature",
  "properties": {
    "addr:full":"Unit 2/ 61 Ashburn Gr Ashburton VIC 3147",
    "addr:postcode":"3147",
    "addr:street":"Gr",
    "iso:country":"AU",
    "sg:address":"Unit 2/ 61 Ashburn Gr",
    "sg:city":"Ashburton",
    "sg:classifiers":[
        {
            "category":"Health Services",
            "subcategory":"Health Practitioner",
            "type":"Services"
        }
    ],
    "sg:phone":"+61 3 9885 4405",
    "sg:postcode":"3147",
    "sg:province":"VIC",
    "sg:tags":[
        "psychologist"
    ],
    "wof:name":"Elliott Peter Dr",
    "wof:placetype":"venue"
},
  "geometry": {"coordinates":[145.079910278,-37.8690032959],"type":"Point"}
}