{
  "type": "Feature",
  "properties": {
    "addr:full":"170 Main Rd Blackwood SA 5051",
    "addr:housenumber":"170",
    "addr:postcode":"5051",
    "addr:street":"Main Rd",
    "iso:country":"AU",
    "sg:address":"170 Main Rd",
    "sg:city":"Blackwood",
    "sg:classifiers":[
        {
            "category":"Health Services",
            "subcategory":"Chiropractor",
            "type":"Services"
        }
    ],
    "sg:phone":"+61 8 8370 2755",
    "sg:postcode":"5051",
    "sg:province":"SA",
    "wof:name":"Holdback N F",
    "wof:placetype":"venue"
},
  "geometry": {"coordinates":[138.618683,-35.014431],"type":"Point"}
}