{
  "type": "Feature",
  "properties": {
    "iso:country":"AU",
    "sg:address":"Cnr South & Rosberg Rds",
    "sg:city":"Wingfield",
    "sg:classifiers":[
        {
            "category":"Autos & Motor Vehicles",
            "subcategory":"Auto Supplies",
            "type":"Retail Goods"
        }
    ],
    "sg:phone":"+61 8 8344 0800",
    "sg:postcode":"5013",
    "sg:province":"SA",
    "sg:tags":[
        "transmission",
        "equipment",
        "power"
    ],
    "wof:name":"BSC Motion Technology",
    "wof:placetype":"venue"
},
  "geometry": {"coordinates":[138.56515502900001,-34.847076416],"type":"Point"}
}