{
  "type": "Feature",
  "properties": {
    "addr:full":"9 Nurmi Ave Newington NSW 2127",
    "addr:housenumber":"9",
    "addr:postcode":"2127",
    "addr:street":"Nurmi Ave",
    "iso:country":"AU",
    "sg:address":"9 Nurmi Ave",
    "sg:city":"Newington",
    "sg:classifiers":[
        {
            "category":"Building & Trades",
            "subcategory":"Plumbing",
            "type":"Services"
        }
    ],
    "sg:phone":"+61 2 9648 0897",
    "sg:postcode":"2127",
    "sg:province":"NSW",
    "sg:tags":[
        "plumber",
        "gasfitters"
    ],
    "wof:name":"Sure Flow Plumbing",
    "wof:placetype":"venue"
},
  "geometry": {"coordinates":[151.058197022,-33.8383178711],"type":"Point"}
}