{
  "type": "Feature",
  "properties": {
    "iso:country":"AU",
    "sg:address":"353 Moray St",
    "sg:city":"South Melbourne",
    "sg:classifiers":[
        {
            "category":"Personal",
            "type":"Services"
        }
    ],
    "sg:phone":"+61 3 9690 8206",
    "sg:postcode":"3205",
    "sg:province":"VIC",
    "sg:tags":[
        "career",
        "counselling"
    ],
    "wof:name":"C.J. Sinclair & Assoc.Pty Ltd",
    "wof:placetype":"venue"
},
  "geometry": {"coordinates":[144.96560700000001,-37.837421],"type":"Point"}
}