{
  "type": "Feature",
  "properties": {
    "iso:country":"AU",
    "sg:address":"Unit 1, 11 Hanson St",
    "sg:city":"Maddington",
    "sg:classifiers":[
        {
            "category":"Retail",
            "subcategory":"Auto Repair",
            "type":"Services"
        }
    ],
    "sg:phone":"+61 448 878 257",
    "sg:postcode":"6109",
    "sg:province":"WA",
    "sg:tags":[
        "muffler",
        "exhaust",
        "system"
    ],
    "wof:name":"Diesel Exhaust Fabrication & Welding",
    "wof:placetype":"venue"
},
  "geometry": {"coordinates":[115.994171143,-32.0343513489],"type":"Point"}
}