{
  "type": "Feature",
  "properties": {
    "addr:full":"16 Maroondah Rd Ashwood VIC 3147",
    "addr:housenumber":"16",
    "addr:postcode":"3147",
    "addr:street":"Maroondah Rd",
    "iso:country":"AU",
    "sg:address":"16 Maroondah Rd",
    "sg:city":"Ashwood",
    "sg:classifiers":[
        {
            "category":"Professional",
            "subcategory":"Management & Consulting",
            "type":"Services"
        }
    ],
    "sg:phone":"+61 417 372 756",
    "sg:postcode":"3147",
    "sg:province":"VIC",
    "sg:tags":[
        "consultant",
        "energy"
    ],
    "wof:name":"Zwack Pty Ltd",
    "wof:placetype":"venue"
},
  "geometry": {"coordinates":[145.11175537099999,-37.8651351929],"type":"Point"}
}