{
  "type": "Feature",
  "properties": {
    "iso:country":"AU",
    "sg:address":"1 Gilmore St",
    "sg:city":"Kingsley",
    "sg:classifiers":[
        {
            "category":"Professional",
            "subcategory":"Accounting & Tax Preparation",
            "type":"Services"
        }
    ],
    "sg:phone":"+61 8 9409 8024",
    "sg:postcode":"6026",
    "sg:province":"WA",
    "sg:tags":[
        "accountant",
        "auditor"
    ],
    "wof:name":"Drummond Simon",
    "wof:placetype":"venue"
},
  "geometry": {"coordinates":[115.789619446,-31.8169307709],"type":"Point"}
}