{
  "type": "Feature",
  "properties": {
    "addr:full":"190 Emerald-Monbulk Rd Monbulk VIC 3793",
    "addr:housenumber":"190",
    "addr:postcode":"3793",
    "addr:street":"Emerald-Monbulk Rd",
    "iso:country":"AU",
    "sg:address":"190 Emerald-Monbulk Rd",
    "sg:city":"Monbulk",
    "sg:classifiers":[
        {
            "category":"Farming",
            "subcategory":"Nursery",
            "type":"Manufacturing & Wholesale Goods"
        }
    ],
    "sg:phone":"+61 3 9756 6210",
    "sg:postcode":"3793",
    "sg:province":"VIC",
    "wof:name":"Summerhill Nurseries",
    "wof:placetype":"venue"
},
  "geometry": {"coordinates":[145.414154053,-37.8831176758],"type":"Point"}
}