{
  "type": "Feature",
  "properties": {
    "iso:country":"AU",
    "sg:address":"LotG3 Harbour Rd",
    "sg:city":"Carnarvon",
    "sg:classifiers":[
        {
            "category":"Autos & Motor Vehicles",
            "subcategory":"Boat Sales",
            "type":"Retail Goods"
        }
    ],
    "sg:phone":"+61 8 9941 1213",
    "sg:postcode":"6701",
    "sg:province":"WA",
    "sg:tags":[
        "builder",
        "yacht",
        "repairer"
    ],
    "wof:name":"Craig's Marine",
    "wof:placetype":"venue"
},
  "geometry": {"coordinates":[113.65573120099999,-24.8939533234],"type":"Point"}
}