{
  "type": "Feature",
  "properties": {
    "addr:full":"3 Kendall Crt Runcorn QLD 4113",
    "addr:housenumber":"3",
    "addr:postcode":"4113",
    "addr:street":"Kendall Crt",
    "iso:country":"AU",
    "sg:address":"3 Kendall Crt",
    "sg:city":"Runcorn",
    "sg:classifiers":[
        {
            "category":"Banks & Credit Unions",
            "subcategory":"Financial Services",
            "type":"Services"
        }
    ],
    "sg:phone":"+61 7 3273 6070",
    "sg:postcode":"4113",
    "sg:province":"QLD",
    "sg:tags":[
        "planning"
    ],
    "wof:name":"Baroque Financial Services",
    "wof:placetype":"venue"
},
  "geometry": {"coordinates":[153.07066345199999,-27.6074295044],"type":"Point"}
}