{
  "type": "Feature",
  "properties": {
    "iso:country":"AU",
    "sg:address":"770 Military Rd",
    "sg:city":"Mosman",
    "sg:classifiers":[
        {
            "category":"Shopping",
            "subcategory":"Clothing, Apparel, & Fashions",
            "type":"Retail Goods"
        }
    ],
    "sg:phone":"+61 2 9969 9614",
    "sg:postcode":"2088",
    "sg:province":"NSW",
    "sg:tags":[
        "lady",
        "wear"
    ],
    "wof:name":"Perri Cutten",
    "wof:placetype":"venue"
},
  "geometry": {"coordinates":[151.243972778,-33.8266181946],"type":"Point"}
}