{
  "type": "Feature",
  "properties": {
    "addr:full":"U2/ 373 Charles St North Perth WA 6006",
    "addr:housenumber":"373",
    "addr:postcode":"6006",
    "addr:street":"U2 /;Charles St",
    "iso:country":"AU",
    "sg:address":"U2/ 373 Charles St",
    "sg:city":"North Perth",
    "sg:classifiers":[
        {
            "category":"Real Estate",
            "subcategory":"Real Estate Agent",
            "type":"Services"
        }
    ],
    "sg:phone":"+61 8 9202 3600",
    "sg:postcode":"6006",
    "sg:province":"WA",
    "wof:name":"McMahon Real Estate",
    "wof:placetype":"venue"
},
  "geometry": {"coordinates":[115.85191345200001,-31.9260425568],"type":"Point"}
}