{
  "type": "Feature",
  "properties": {
    "iso:country":"AU",
    "sg:address":"4 Ferhill Rd",
    "sg:city":"Caulfield",
    "sg:classifiers":[
        {
            "category":"Professional",
            "type":"Services"
        }
    ],
    "sg:phone":"+61 425 813 524",
    "sg:postcode":"3162",
    "sg:province":"VIC",
    "sg:tags":[
        "transport"
    ],
    "wof:name":"Globus Transport",
    "wof:placetype":"venue"
},
  "geometry": {"coordinates":[145.017303467,-37.8939933777],"type":"Point"}
}