{
  "type": "Feature",
  "properties": {
    "addr:full":"54 Darlinghurst Rd Kings Cross NSW 2011",
    "addr:housenumber":"54",
    "addr:postcode":"2011",
    "addr:street":"Darlinghurst Rd",
    "iso:country":"AU",
    "sg:address":"54 Darlinghurst Rd",
    "sg:city":"Kings Cross",
    "sg:classifiers":[
        {
            "category":"Travel",
            "subcategory":"Hotels & Motels",
            "type":"Entertainment"
        }
    ],
    "sg:phone":"+61 2 9357 3800",
    "sg:postcode":"2011",
    "sg:province":"NSW",
    "sg:tags":[
        "accommodation"
    ],
    "wof:name":"Vegas Hotel The",
    "wof:placetype":"venue"
},
  "geometry": {"coordinates":[151.223144531,-33.8743553162],"type":"Point"}
}