{
  "type": "Feature",
  "properties": {
    "iso:country":"AU",
    "sg:address":"27 Wondabah Pl",
    "sg:city":"Carlingford",
    "sg:classifiers":[
        {
            "category":"Professional",
            "subcategory":"Employment Agencies",
            "type":"Services"
        }
    ],
    "sg:phone":"+61 2 9871 5994",
    "sg:postcode":"2118",
    "sg:province":"NSW",
    "sg:tags":[
        "entertainer",
        "agent"
    ],
    "wof:name":"Popset Pty Ltd",
    "wof:placetype":"venue"
},
  "geometry": {"coordinates":[151.04656982399999,-33.7661514282],"type":"Point"}
}