{
  "type": "Feature",
  "properties": {
    "addr:full":"1631 Botany Rd Botany NSW 2019",
    "addr:housenumber":"1631",
    "addr:postcode":"2019",
    "addr:street":"Botany Rd",
    "iso:country":"AU",
    "sg:address":"1631 Botany Rd",
    "sg:city":"Botany",
    "sg:classifiers":[
        {
            "category":"Professional",
            "subcategory":"Computer Services",
            "type":"Services"
        }
    ],
    "sg:phone":"+61 1300 661 888",
    "sg:postcode":"2019",
    "sg:province":"NSW",
    "sg:tags":[
        "equipment",
        "networking",
        "installation"
    ],
    "wof:name":"115 Solutions Pty Ltd",
    "wof:placetype":"venue"
},
  "geometry": {"coordinates":[151.204315186,-33.9541740417],"type":"Point"}
}