{
  "type": "Feature",
  "properties": {
    "addr:full":"178 Union Rd Ascot Vale VIC 3032",
    "addr:housenumber":"178",
    "addr:postcode":"3032",
    "addr:street":"Union Rd",
    "iso:country":"AU",
    "sg:address":"178 Union Rd",
    "sg:city":"Ascot Vale",
    "sg:classifiers":[
        {
            "category":"Personal",
            "subcategory":"Beauty Salon",
            "type":"Services"
        }
    ],
    "sg:phone":"+61 3 9370 7294",
    "sg:postcode":"3032",
    "sg:province":"VIC",
    "sg:tags":[
        "hairdresser"
    ],
    "wof:name":"C.U.S. Hairdressing",
    "wof:placetype":"venue"
},
  "geometry": {"coordinates":[144.91593900000001,-37.774441],"type":"Point"}
}