{
  "type": "Feature",
  "properties": {
    "addr:full":"44 Muffett St Scone NSW 2337",
    "addr:housenumber":"44",
    "addr:postcode":"2337",
    "addr:street":"Muffett St",
    "iso:country":"AU",
    "sg:address":"44 Muffett St",
    "sg:city":"Scone",
    "sg:classifiers":[
        {
            "category":"Autos & Motor Vehicles",
            "subcategory":"Boat Sales",
            "type":"Retail Goods"
        }
    ],
    "sg:phone":"+61 2 6545 2411",
    "sg:postcode":"2337",
    "sg:province":"NSW",
    "sg:tags":[
        "yacht"
    ],
    "wof:name":"Auscraft Boats",
    "wof:placetype":"venue"
},
  "geometry": {"coordinates":[150.86816406200001,-32.0404281616],"type":"Point"}
}