{
  "type": "Feature",
  "properties": {
    "iso:country":"AU",
    "sg:address":"18 Isabella St",
    "sg:city":"Wingham",
    "sg:classifiers":[
        {
            "category":"Manufacturing",
            "subcategory":"Metals",
            "type":"Manufacturing & Wholesale Goods"
        }
    ],
    "sg:phone":"+61 2 6553 4183",
    "sg:postcode":"2429",
    "sg:province":"NSW",
    "sg:tags":[
        "fabricator",
        "aluminium"
    ],
    "wof:name":"Carlyle's Parts Service Pty. Ltd.",
    "wof:placetype":"venue"
},
  "geometry": {"coordinates":[152.372818,-31.868896],"type":"Point"}
}