{
  "type": "Feature",
  "properties": {
    "addr:full":"100 Alcorn Rd Labertouche VIC 3816",
    "addr:housenumber":"100",
    "addr:postcode":"3816",
    "addr:street":"Alcorn Rd",
    "iso:country":"AU",
    "sg:address":"100 Alcorn Rd",
    "sg:city":"Labertouche",
    "sg:classifiers":[
        {
            "category":"Food & Beverages",
            "subcategory":"Fruits & Vegetables",
            "type":"Retail Goods"
        }
    ],
    "sg:phone":"+61 3 5628 7637",
    "sg:postcode":"3816",
    "sg:province":"VIC",
    "sg:tags":[
        "grower"
    ],
    "wof:name":"Labertouche Organic Farm",
    "wof:placetype":"venue"
},
  "geometry": {"coordinates":[145.800522,-38.029942],"type":"Point"}
}