{
  "type": "Feature",
  "properties": {
    "iso:country":"AU",
    "sg:address":"Lot 561 Molong Rd",
    "sg:city":"Parkes",
    "sg:classifiers":[
        {
            "category":"Real Estate",
            "subcategory":"Real Estate Agent",
            "type":"Services"
        }
    ],
    "sg:phone":"+61 429 624 107",
    "sg:postcode":"2870",
    "sg:province":"NSW",
    "sg:tags":[
        "handyman's",
        "equipment",
        "hire",
        "builders",
        "contractor"
    ],
    "wof:name":"Steve Magill Earthmoving Pty Ltd",
    "wof:placetype":"venue"
},
  "geometry": {"coordinates":[148.157928,-33.139091],"type":"Point"}
}