{
  "type": "Feature",
  "properties": {
    "iso:country":"AU",
    "sg:address":"Suite 5 136 Botanic Rd",
    "sg:city":"Warrnambool",
    "sg:classifiers":[
        {
            "category":"Health Services",
            "subcategory":"Doctor",
            "type":"Services"
        }
    ],
    "sg:phone":"+61 3 5562 2601",
    "sg:postcode":"3280",
    "sg:province":"VIC",
    "sg:tags":[
        "medical",
        "practitioner"
    ],
    "wof:name":"Braniff K M Dr",
    "wof:placetype":"venue"
},
  "geometry": {"coordinates":[142.47955322300001,-38.3721618652],"type":"Point"}
}