{
  "type": "Feature",
  "properties": {
    "iso:country":"AU",
    "sg:address":"29 Kingsford Smith Drv",
    "sg:city":"Berkeley Vale",
    "sg:classifiers":[
        {
            "category":"Building & Trades",
            "subcategory":"Plumbing",
            "type":"Services"
        }
    ],
    "sg:phone":"+61 419 699 474",
    "sg:postcode":"2261",
    "sg:province":"NSW",
    "sg:tags":[
        "plumber",
        "gasfitters"
    ],
    "wof:name":"Central Coast Maintenance Plumbing Services",
    "wof:placetype":"venue"
},
  "geometry": {"coordinates":[151.435715,-33.336628],"type":"Point"}
}