{
  "type": "Feature",
  "properties": {
    "iso:country":"AU",
    "sg:address":"31 Delmar Pde",
    "sg:city":"Gladesville",
    "sg:classifiers":[
        {
            "category":"Banks & Credit Unions",
            "subcategory":"Investment Brokerage",
            "type":"Services"
        }
    ],
    "sg:phone":"+61 2 9879 0188",
    "sg:postcode":"2111",
    "sg:province":"NSW",
    "wof:name":"Zoltran Pty Ltd",
    "wof:placetype":"venue"
},
  "geometry": {"coordinates":[151.12042236299999,-33.8365821838],"type":"Point"}
}