{
  "type": "Feature",
  "properties": {
    "iso:country":"AU",
    "sg:address":"MS 648 Dioth Rd",
    "sg:city":"Upper Yarraman",
    "sg:classifiers":[
        {
            "category":"Retail",
            "subcategory":"Animal Services",
            "type":"Services"
        }
    ],
    "sg:phone":"+61 7 4163 9181",
    "sg:postcode":"4314",
    "sg:province":"QLD",
    "sg:tags":[
        "breeder",
        "sheep",
        "stud",
        "cattle"
    ],
    "wof:name":"Australian Limousin Breeders&#039; Society",
    "wof:placetype":"venue"
},
  "geometry": {"coordinates":[151.89720153799999,-26.906042099],"type":"Point"}
}