{
  "type": "Feature",
  "properties": {
    "addr:full":"2 Samantha Pl Smeaton Grange NSW 2567",
    "addr:housenumber":"2",
    "addr:postcode":"2567",
    "addr:street":"Samantha Pl",
    "iso:country":"AU",
    "sg:address":"2 Samantha Pl",
    "sg:city":"Smeaton Grange",
    "sg:classifiers":[
        {
            "category":"Manufacturing",
            "subcategory":"Retail Goods",
            "type":"Manufacturing & Wholesale Goods"
        }
    ],
    "sg:phone":"+61 2 4648 2311",
    "sg:postcode":"2567",
    "sg:province":"NSW",
    "sg:tags":[
        "merchant",
        "pump",
        "mfrs"
    ],
    "wof:name":"Woma (Australia) Pty. Ltd.",
    "wof:placetype":"venue"
},
  "geometry": {"coordinates":[150.76036071799999,-34.0406036377],"type":"Point"}
}