{
  "type": "Feature",
  "properties": {
    "addr:full":"33 Eddie Rd Minchinbury NSW 2770",
    "addr:housenumber":"33",
    "addr:postcode":"2770",
    "addr:street":"Eddie Rd",
    "iso:country":"AU",
    "sg:address":"33 Eddie Rd",
    "sg:city":"Minchinbury",
    "sg:classifiers":[
        {
            "category":"Building & Trades",
            "subcategory":"Construction",
            "type":"Services"
        }
    ],
    "sg:phone":"+61 2 9832 4266",
    "sg:postcode":"2770",
    "sg:province":"NSW",
    "sg:tags":[
        "joinery"
    ],
    "wof:name":"Fino Commercial Furniture Pty Ltd",
    "wof:placetype":"venue"
},
  "geometry": {"coordinates":[150.81683349599999,-33.7845878601],"type":"Point"}
}