{
  "type": "Feature",
  "properties": {
    "addr:full":"3 Drummond St Carlton VIC 3053",
    "addr:housenumber":"3",
    "addr:postcode":"3053",
    "addr:street":"Drummond St",
    "iso:country":"AU",
    "sg:address":"3 Drummond St",
    "sg:city":"Carlton",
    "sg:classifiers":[
        {
            "category":"Health Services",
            "subcategory":"Health Practitioner",
            "type":"Services"
        }
    ],
    "sg:phone":"+61 3 9809 0366",
    "sg:postcode":"3053",
    "sg:province":"VIC",
    "sg:tags":[
        "psychologist"
    ],
    "wof:name":"Movie Therapy Centre",
    "wof:placetype":"venue"
},
  "geometry": {"coordinates":[144.96717834500001,-37.8069877625],"type":"Point"}
}