{
  "type": "Feature",
  "properties": {
    "addr:full":"12 Mars St Tully QLD 4854",
    "addr:housenumber":"12",
    "addr:postcode":"4854",
    "addr:street":"Mars St",
    "iso:country":"AU",
    "sg:address":"12 Mars St",
    "sg:city":"Tully",
    "sg:classifiers":[
        {
            "category":"Farming",
            "subcategory":"Farm",
            "type":"Manufacturing & Wholesale Goods"
        }
    ],
    "sg:phone":"+61 7 4068 1267",
    "sg:postcode":"4854",
    "sg:province":"QLD",
    "sg:tags":[
        "farmer"
    ],
    "wof:name":"Harney T J",
    "wof:placetype":"venue"
},
  "geometry": {"coordinates":[145.921188355,-17.9369792938],"type":"Point"}
}