{
  "type": "Feature",
  "properties": {
    "addr:full":"29 Geddes St Mulgrave VIC 3170",
    "addr:housenumber":"29",
    "addr:postcode":"3170",
    "addr:street":"Geddes St",
    "iso:country":"AU",
    "sg:address":"29 Geddes St",
    "sg:city":"Mulgrave",
    "sg:classifiers":[
        {
            "category":"Manufacturing",
            "subcategory":"Electronics",
            "type":"Manufacturing & Wholesale Goods"
        }
    ],
    "sg:phone":"+61 3 9561 7200",
    "sg:postcode":"3170",
    "sg:province":"VIC",
    "sg:tags":[
        "wholesaler",
        "equipment",
        "part",
        "mfrs",
        "refrigeration"
    ],
    "wof:name":"Airefrig Australia Pty. Ltd.",
    "wof:placetype":"venue"
},
  "geometry": {"coordinates":[145.15338134800001,-37.9056625366],"type":"Point"}
}