{
  "type": "Feature",
  "properties": {
    "addr:full":"110 Churchill Rd Childers QLD 4660",
    "addr:housenumber":"110",
    "addr:postcode":"4660",
    "addr:street":"Churchill Rd",
    "iso:country":"AU",
    "sg:address":"110 Churchill Rd",
    "sg:city":"Childers",
    "sg:classifiers":[
        {
            "category":"Travel",
            "subcategory":"Hotels & Motels",
            "type":"Entertainment"
        }
    ],
    "sg:phone":"+61 7 4126 1763",
    "sg:postcode":"4660",
    "sg:province":"QLD",
    "sg:tags":[
        "accommodation"
    ],
    "wof:name":"Grand Hotel",
    "wof:placetype":"venue"
},
  "geometry": {"coordinates":[152.277435303,-25.2366275787],"type":"Point"}
}