{
  "type": "Feature",
  "properties": {
    "addr:full":"62 McLachlan St Maclean NSW 2463",
    "addr:housenumber":"62",
    "addr:postcode":"2463",
    "addr:street":"Mclachlan St",
    "iso:country":"AU",
    "sg:address":"62 McLachlan St",
    "sg:city":"Maclean",
    "sg:classifiers":[
        {
            "category":"Building & Trades",
            "subcategory":"Landscaping Services",
            "type":"Services"
        }
    ],
    "sg:phone":"+61 2 6645 2247",
    "sg:postcode":"2463",
    "sg:province":"NSW",
    "sg:tags":[
        "grazier"
    ],
    "wof:name":"McLaren D",
    "wof:placetype":"venue"
},
  "geometry": {"coordinates":[153.20315551799999,-29.4487686157],"type":"Point"}
}