{
  "type": "Feature",
  "properties": {
    "addr:full":"Shop 7, Arndale Shopng Cntr Springwood QLD 4127",
    "addr:housenumber":"shop 7",
    "addr:postcode":"4127",
    "addr:street":"Arndale Shopng Cntr",
    "iso:country":"AU",
    "sg:address":"Shop 7, Arndale Shopng Cntr",
    "sg:city":"Springwood",
    "sg:classifiers":[
        {
            "category":"Health Services",
            "subcategory":"Doctor",
            "type":"Services"
        }
    ],
    "sg:phone":"+61 7 3208 6122",
    "sg:postcode":"4127",
    "sg:province":"QLD",
    "sg:tags":[
        "medical",
        "practitioner"
    ],
    "wof:name":"Moody Wendy",
    "wof:placetype":"venue"
},
  "geometry": {"coordinates":[153.13209533700001,-27.6174602509],"type":"Point"}
}