{
  "type": "Feature",
  "properties": {
    "iso:country":"AU",
    "sg:address":"Home & Leisure Cntr, 14 Carindale St",
    "sg:city":"Carindale",
    "sg:classifiers":[
        {
            "category":"Sports & Exercise",
            "subcategory":"Gym",
            "type":"Entertainment"
        }
    ],
    "sg:phone":"+61 7 3395 3377",
    "sg:postcode":"4152",
    "sg:province":"QLD",
    "sg:tags":[
        "personal",
        "trainer",
        "fitness"
    ],
    "wof:name":"Fernwood",
    "wof:placetype":"venue"
},
  "geometry": {"coordinates":[153.10377502399999,-27.5011806488],"type":"Point"}
}