{
  "type": "Feature",
  "properties": {
    "addr:full":"9 / 48 Smith St Darwin NT 0800",
    "addr:housenumber":"/ 48",
    "addr:postcode":"nt 0800",
    "addr:street":"Smith St",
    "iso:country":"AU",
    "sg:address":"9 / 48 Smith St",
    "sg:city":"Darwin",
    "sg:classifiers":[
        {
            "category":"Personal",
            "subcategory":"Nail Salon",
            "type":"Services"
        }
    ],
    "sg:phone":"+61 8 8941 9199",
    "sg:postcode":"0800",
    "sg:province":"NT",
    "sg:tags":[
        "artificial"
    ],
    "wof:name":"Centrepoint Beauty",
    "wof:placetype":"venue"
},
  "geometry": {"coordinates":[130.84141540499999,-12.462931633],"type":"Point"}
}