{
  "type": "Feature",
  "properties": {
    "addr:full":"Rita Island Rd Jarvisfield QLD 4807",
    "addr:postcode":"4807",
    "addr:street":"Island Rd",
    "iso:country":"AU",
    "sg:address":"Rita Island Rd",
    "sg:city":"Jarvisfield",
    "sg:classifiers":[
        {
            "category":"Education",
            "subcategory":"School",
            "type":"Public Place"
        }
    ],
    "sg:phone":"+61 7 4782 4254",
    "sg:postcode":"4807",
    "sg:province":"QLD",
    "sg:tags":[
        "state",
        "except",
        "nsw"
    ],
    "wof:name":"Jarvisfield Primary",
    "wof:placetype":"venue"
},
  "geometry": {"coordinates":[147.45591735799999,-19.5958404541],"type":"Point"}
}