{
  "type": "Feature",
  "properties": {
    "addr:full":"105 Archer St Shepparton VIC 3630",
    "addr:housenumber":"105",
    "addr:postcode":"3630",
    "addr:street":"Archer St",
    "iso:country":"AU",
    "sg:address":"105 Archer St",
    "sg:city":"Shepparton",
    "sg:classifiers":[
        {
            "category":"Autos & Motor Vehicles",
            "subcategory":"Fuel & Gas Station",
            "type":"Retail Goods"
        }
    ],
    "sg:phone":"+61 3 5821 6712",
    "sg:postcode":"3630",
    "sg:province":"VIC",
    "wof:name":"Mobil Oil Aust Pty Ltd",
    "wof:placetype":"venue"
},
  "geometry": {"coordinates":[145.41242980999999,-36.3858337402],"type":"Point"}
}