{
  "type": "Feature",
  "properties": {
    "addr:full":"Cnr Redlands & Poseidon Rds Corowa NSW 2646",
    "addr:postcode":"2646",
    "addr:street":"Cnr",
    "iso:country":"AU",
    "sg:address":"Cnr Redlands & Poseidon Rds",
    "sg:city":"Corowa",
    "sg:classifiers":[
        {
            "category":"Building & Trades",
            "subcategory":"Construction",
            "type":"Services"
        }
    ],
    "sg:phone":"+61 2 6033 1403",
    "sg:postcode":"2646",
    "sg:province":"NSW",
    "sg:tags":[
        "home",
        "air conditioning"
    ],
    "wof:name":"Bartletts Corowa Gas Supply",
    "wof:placetype":"venue"
},
  "geometry": {"coordinates":[146.38613891599999,-35.9920692444],"type":"Point"}
}