{
  "type": "Feature",
  "properties": {
    "addr:full":"7 Peru Pl Illawong NSW 2234",
    "addr:housenumber":"7",
    "addr:postcode":"2234",
    "addr:street":"Peru Pl",
    "iso:country":"AU",
    "sg:address":"7 Peru Pl",
    "sg:city":"Illawong",
    "sg:classifiers":[
        {
            "category":"Professional",
            "subcategory":"Accounting & Tax Preparation",
            "type":"Services"
        }
    ],
    "sg:phone":"+61 2 9541 4333",
    "sg:postcode":"2234",
    "sg:province":"NSW",
    "sg:tags":[
        "bookkeeping"
    ],
    "wof:name":"Need A Bookkeeper",
    "wof:placetype":"venue"
},
  "geometry": {"coordinates":[151.04473876899999,-33.9966125488],"type":"Point"}
}