{
  "type": "Feature",
  "properties": {
    "addr:full":"118 Lavarack Ave Eagle Farm QLD 4009",
    "addr:housenumber":"118",
    "addr:postcode":"4009",
    "addr:street":"Lavarack Ave",
    "iso:country":"AU",
    "sg:address":"118 Lavarack Ave",
    "sg:city":"Eagle Farm",
    "sg:classifiers":[
        {
            "category":"Retail",
            "subcategory":"Auto Repair",
            "type":"Services"
        }
    ],
    "sg:phone":"+61 7 3630 1099",
    "sg:postcode":"4009",
    "sg:province":"QLD",
    "sg:tags":[
        "beater",
        "painter",
        "panel"
    ],
    "wof:name":"Impact Body Repairs",
    "wof:placetype":"venue"
},
  "geometry": {"coordinates":[153.099411011,-27.4308929443],"type":"Point"}
}