{
  "type": "Feature",
  "properties": {
    "iso:country":"AU",
    "sg:address":"Rear 384 Wardell St",
    "sg:city":"Enoggera",
    "sg:classifiers":[
        {
            "category":"Retail",
            "subcategory":"Auto Repair",
            "type":"Services"
        }
    ],
    "sg:phone":"+61 7 3855 9733",
    "sg:postcode":"4052",
    "sg:province":"QLD",
    "sg:tags":[
        "repairer",
        "motor",
        "engineer"
    ],
    "wof:name":"Midas",
    "wof:placetype":"venue"
},
  "geometry": {"coordinates":[177.54794311500001,-38.2569084167],"type":"Point"}
}