{
  "type": "Feature",
  "properties": {
    "addr:full":"385 Maurice Rd Murray Bridge SA 5253",
    "addr:housenumber":"385",
    "addr:postcode":"5253",
    "addr:street":"Maurice Rd",
    "iso:country":"AU",
    "sg:address":"385 Maurice Rd",
    "sg:city":"Murray Bridge",
    "sg:classifiers":[
        {
            "category":"Utilities",
            "subcategory":"Recycling",
            "type":"Services"
        }
    ],
    "sg:phone":"+61 8 8531 2396",
    "sg:postcode":"5253",
    "sg:province":"SA",
    "wof:name":"Earl Bee Recycling",
    "wof:placetype":"venue"
},
  "geometry": {"coordinates":[139.25770568900001,-35.1268577576],"type":"Point"}
}