{
  "type": "Feature",
  "properties": {
    "addr:full":"1017 Lydiard St North Ballarat VIC 3350",
    "addr:housenumber":"1017",
    "addr:postcode":"3350",
    "addr:street":"Lydiard St North",
    "iso:country":"AU",
    "sg:address":"1017 Lydiard St",
    "sg:city":"North Ballarat",
    "sg:classifiers":[
        {
            "category":"Autos & Motor Vehicles",
            "subcategory":"Fuel & Gas Station",
            "type":"Retail Goods"
        }
    ],
    "sg:phone":"+61 3 5333 4234",
    "sg:postcode":"3350",
    "sg:province":"VIC",
    "wof:name":"Sun-Bar Pty Ltd",
    "wof:placetype":"venue"
},
  "geometry": {"coordinates":[143.861694,-37.539803],"type":"Point"}
}