{
  "type": "Feature",
  "properties": {
    "addr:full":"260 Auburn Rd Hawthorn VIC 3122",
    "addr:housenumber":"260",
    "addr:postcode":"3122",
    "addr:street":"Auburn Rd",
    "iso:country":"AU",
    "sg:address":"260 Auburn Rd",
    "sg:city":"Hawthorn",
    "sg:classifiers":[
        {
            "category":"Professional",
            "subcategory":"Accounting & Tax Preparation",
            "type":"Services"
        }
    ],
    "sg:phone":"+61 3 9818 8800",
    "sg:postcode":"3122",
    "sg:province":"VIC",
    "sg:tags":[
        "accountant",
        "auditor"
    ],
    "wof:name":"Dye & Rennie Chartered Accountants",
    "wof:placetype":"venue"
},
  "geometry": {"coordinates":[145.043655395,-37.8290138245],"type":"Point"}
}