{
  "type": "Feature",
  "properties": {
    "iso:country":"AU",
    "sg:address":"1 Kellett Ave",
    "sg:city":"Lockleys",
    "sg:classifiers":[
        {
            "category":"Food & Beverages",
            "subcategory":"Liquor & Beverages",
            "type":"Retail Goods"
        }
    ],
    "sg:phone":"+61 8 8352 5858",
    "sg:postcode":"5032",
    "sg:province":"SA",
    "sg:tags":[
        "merchant",
        "spirit",
        "wine"
    ],
    "wof:name":"The Hogshead Liquor Company",
    "wof:placetype":"venue"
},
  "geometry": {"coordinates":[138.52870178200001,-34.9246711731],"type":"Point"}
}