{
  "type": "Feature",
  "properties": {
    "addr:full":"1 Adams Crt Sunshine West VIC 3020",
    "addr:housenumber":"1",
    "addr:postcode":"3020",
    "addr:street":"Adams Crt",
    "iso:country":"AU",
    "sg:address":"1 Adams Crt",
    "sg:city":"Sunshine West",
    "sg:classifiers":[
        {
            "category":"Real Estate",
            "subcategory":"Real Estate Operator",
            "type":"Services"
        }
    ],
    "sg:phone":"+61 3 9311 7511",
    "sg:postcode":"3020",
    "sg:province":"VIC",
    "sg:tags":[
        "concrete",
        "pumping"
    ],
    "sg:website":"http://www.improvedconcretepumping.com.au",
    "wof:name":"Improved Concrete Pumping Services (VIC) Pty Ltd",
    "wof:placetype":"venue"
},
  "geometry": {"coordinates":[144.81045499999999,-37.811649],"type":"Point"}
}