{
  "type": "Feature",
  "properties": {
    "iso:country":"AU",
    "sg:address":"PO Box 147",
    "sg:city":"Bencubbin",
    "sg:classifiers":[
        {
            "category":"Farming",
            "subcategory":"Farm",
            "type":"Manufacturing & Wholesale Goods"
        }
    ],
    "sg:phone":"+61 8 9686 2032",
    "sg:postcode":"6477",
    "sg:province":"WA",
    "sg:tags":[
        "farmer"
    ],
    "wof:name":"Gillett A M & GE",
    "wof:placetype":"venue"
},
  "geometry": {"coordinates":[117.86328125,-30.8145694733],"type":"Point"}
}