{
  "type": "Feature",
  "properties": {
    "iso:country":"AU",
    "sg:address":"Derrimut Rd",
    "sg:city":"Hoppers Crossing",
    "sg:classifiers":[
        {
            "category":"Cafe",
            "type":"Food & Drink"
        }
    ],
    "sg:phone":"+61 3 9749 4029",
    "sg:postcode":"3029",
    "sg:province":"VIC",
    "wof:name":"Cherries Cafe",
    "wof:placetype":"venue"
},
  "geometry": {"coordinates":[144.685394,-37.864441],"type":"Point"}
}