{
  "type": "Feature",
  "properties": {
    "addr:full":"100 Griffith St Coolangatta QLD 4225",
    "addr:housenumber":"100",
    "addr:postcode":"4225",
    "addr:street":"Griffith St",
    "iso:country":"AU",
    "sg:address":"100 Griffith St",
    "sg:city":"Coolangatta",
    "sg:classifiers":[
        {
            "category":"Professional",
            "subcategory":"Computer Services",
            "type":"Services"
        }
    ],
    "sg:phone":"+61 7 5599 3305",
    "sg:postcode":"4225",
    "sg:province":"QLD",
    "sg:tags":[
        "repairs",
        "upgrade",
        "equipment"
    ],
    "wof:name":"Dex Computing",
    "wof:placetype":"venue"
},
  "geometry": {"coordinates":[153.53961181599999,-28.1688480377],"type":"Point"}
}