{
  "type": "Feature",
  "properties": {
    "iso:country":"AU",
    "sg:address":"Hanleys Creek Rd",
    "sg:city":"Dungog",
    "sg:classifiers":[
        {
            "category":"Sports & Exercise",
            "subcategory":"Golf",
            "type":"Entertainment"
        }
    ],
    "sg:phone":"+61 2 4992 1394",
    "sg:postcode":"2420",
    "sg:province":"NSW",
    "sg:tags":[
        "club"
    ],
    "wof:name":"Dungog & District Golf Club",
    "wof:placetype":"venue"
},
  "geometry": {"coordinates":[151.732819,-32.42522],"type":"Point"}
}