{
  "type": "Feature",
  "properties": {
    "addr:full":"78 Harbour St Sydney NSW 2000",
    "addr:housenumber":"78",
    "addr:postcode":"2000",
    "addr:street":"Harbour St",
    "iso:country":"AU",
    "sg:address":"78 Harbour St",
    "sg:city":"Sydney",
    "sg:classifiers":[
        {
            "category":"Food & Beverages",
            "subcategory":"Groceries & Convenience Stores",
            "type":"Retail Goods"
        }
    ],
    "sg:phone":"+61 2 9281 4192",
    "sg:postcode":"2000",
    "sg:province":"NSW",
    "wof:name":"Harbour Street Convenience Store",
    "wof:placetype":"venue"
},
  "geometry": {"coordinates":[151.20370483400001,-33.8765449524],"type":"Point"}
}