{
  "type": "Feature",
  "properties": {
    "addr:full":"4 / 36 Campbell Av Cromer NSW 2099",
    "addr:housenumber":"/ 36",
    "addr:postcode":"2099",
    "addr:street":"Campbell Av",
    "iso:country":"AU",
    "sg:address":"4 / 36",
    "sg:city":"Campbell Av Cromer",
    "sg:classifiers":[
        {
            "category":"Home & Garden",
            "subcategory":"Home Furnishings",
            "type":"Retail Goods"
        }
    ],
    "sg:phone":"+61 1300 362 779",
    "sg:postcode":"2099",
    "sg:province":"NSW",
    "sg:tags":[
        "shower",
        "screen"
    ],
    "wof:name":"Clear View Designs",
    "wof:placetype":"venue"
},
  "geometry": {"coordinates":[151.288894653,-33.7402458191],"type":"Point"}
}