{
  "type": "Feature",
  "properties": {
    "iso:country":"AU",
    "sg:address":"30 Brockman St",
    "sg:city":"Denham",
    "sg:classifiers":[
        {
            "category":"Professional",
            "subcategory":"Research",
            "type":"Services"
        }
    ],
    "sg:phone":"+61 8 9948 1185",
    "sg:postcode":"6537",
    "sg:province":"WA",
    "sg:tags":[
        "pearler"
    ],
    "wof:name":"Heritage Pearls",
    "wof:placetype":"venue"
},
  "geometry": {"coordinates":[113.534828186,-25.9262371063],"type":"Point"}
}