{
  "type": "Feature",
  "properties": {
    "iso:country":"AU",
    "sg:address":"370 Kent St",
    "sg:city":"Maryborough",
    "sg:classifiers":[
        {
            "category":"Real Estate",
            "subcategory":"Architect",
            "type":"Services"
        }
    ],
    "sg:phone":"+61 7 4121 5800",
    "sg:postcode":"4650",
    "sg:province":"QLD",
    "wof:name":"Architect Design Company",
    "wof:placetype":"venue"
},
  "geometry": {"coordinates":[152.699265,-25.535538],"type":"Point"}
}