{
  "type": "Feature",
  "properties": {
    "addr:full":"175c King William Rd Hyde Park SA 5061",
    "addr:housenumber":"175c",
    "addr:postcode":"5061",
    "addr:street":"King William Rd",
    "iso:country":"AU",
    "sg:address":"175c King William Rd",
    "sg:city":"Hyde Park",
    "sg:classifiers":[
        {
            "category":"Banks & Credit Unions",
            "subcategory":"Investment Brokerage",
            "type":"Services"
        }
    ],
    "sg:phone":"+61 8 8373 1466",
    "sg:postcode":"5061",
    "sg:province":"SA",
    "sg:tags":[
        "debt",
        "collection"
    ],
    "wof:name":"Philip Scicluna Debt Collection Agent",
    "wof:placetype":"venue"
},
  "geometry": {"coordinates":[138.60020446799999,-34.9542388916],"type":"Point"}
}