{
  "type": "Feature",
  "properties": {
    "addr:full":"Princes Hwy Dandenong VIC 3175",
    "addr:postcode":"3175",
    "addr:street":"Princes Hwy",
    "iso:country":"AU",
    "sg:address":"Princes Hwy",
    "sg:city":"Dandenong",
    "sg:classifiers":[
        {
            "category":"Education",
            "subcategory":"Dance Studio",
            "type":"Public Place"
        }
    ],
    "sg:phone":"+61 3 9791 9289",
    "sg:postcode":"3175",
    "sg:province":"VIC",
    "sg:tags":[
        "instruction",
        "language"
    ],
    "wof:name":"Victorian School of Languages",
    "wof:placetype":"venue"
},
  "geometry": {"coordinates":[145.214157105,-37.9848098755],"type":"Point"}
}