{
  "type": "Feature",
  "properties": {
    "addr:full":"36 Ocean Pde Noraville NSW 2263",
    "addr:housenumber":"36",
    "addr:postcode":"2263",
    "addr:street":"Ocean Pde",
    "iso:country":"AU",
    "sg:address":"36 Ocean Pde",
    "sg:city":"Noraville",
    "sg:classifiers":[
        {
            "category":"Utilities",
            "subcategory":"Electric",
            "type":"Services"
        }
    ],
    "sg:phone":"+61 2 4396 2265",
    "sg:postcode":"2263",
    "sg:province":"NSW",
    "sg:tags":[
        "electrical",
        "contractor"
    ],
    "wof:name":"Captain Kirk Electrical",
    "wof:placetype":"venue"
},
  "geometry": {"coordinates":[151.555038,-33.272263],"type":"Point"}
}