{
  "type": "Feature",
  "properties": {
    "addr:full":"171 Main Rd Speers Point NSW 2284",
    "addr:housenumber":"171",
    "addr:postcode":"2284",
    "addr:street":"Main Rd",
    "iso:country":"AU",
    "sg:address":"171 Main Rd",
    "sg:city":"Speers Point",
    "sg:classifiers":[
        {
            "category":"Shopping",
            "subcategory":"Computers & Home Electronics",
            "type":"Retail Goods"
        }
    ],
    "sg:phone":"+61 2 4358 8799",
    "sg:postcode":"2284",
    "sg:province":"NSW",
    "sg:tags":[
        "detector",
        "electronic"
    ],
    "wof:name":"FAI Home Security Sales",
    "wof:placetype":"venue"
},
  "geometry": {"coordinates":[151.62271118199999,-32.9628067017],"type":"Point"}
}