{
  "type": "Feature",
  "properties": {
    "iso:country":"AU",
    "sg:address":"Shop 3 Todd St",
    "sg:city":"Gawler",
    "sg:classifiers":[
        {
            "category":"Shopping",
            "subcategory":"Clothing, Apparel, & Fashions",
            "type":"Retail Goods"
        }
    ],
    "sg:phone":"+61 8 8523 5970",
    "sg:postcode":"5118",
    "sg:province":"SA",
    "sg:tags":[
        "recycled",
        "clothing"
    ],
    "wof:name":"Lifeline Shop The",
    "wof:placetype":"venue"
},
  "geometry": {"coordinates":[138.749023,-34.59898],"type":"Point"}
}