{
  "type": "Feature",
  "properties": {
    "addr:full":"Osborne Rd North Haven SA 5018",
    "addr:postcode":"5018",
    "addr:street":"Osborne Rd",
    "iso:country":"AU",
    "sg:address":"Osborne Rd",
    "sg:city":"North Haven",
    "sg:classifiers":[
        {
            "category":"Deli",
            "type":"Food & Drink"
        }
    ],
    "sg:phone":"+61 8 8248 3411",
    "sg:postcode":"5018",
    "sg:province":"SA",
    "sg:tags":[
        "delicatessen"
    ],
    "wof:name":"North Haven Delicatessen",
    "wof:placetype":"venue"
},
  "geometry": {"coordinates":[138.492263794,-34.7924880981],"type":"Point"}
}