{
  "type": "Feature",
  "properties": {
    "addr:full":"61 Lodesworth Rd Westminster WA 6061",
    "addr:housenumber":"61",
    "addr:postcode":"6061",
    "addr:street":"Lodesworth Rd",
    "iso:country":"AU",
    "sg:address":"61 Lodesworth Rd",
    "sg:city":"Westminster",
    "sg:classifiers":[
        {
            "category":"Professional",
            "subcategory":"Accounting & Tax Preparation",
            "type":"Services"
        }
    ],
    "sg:phone":"+61 8 9344 7395",
    "sg:postcode":"6061",
    "sg:province":"WA",
    "sg:tags":[
        "accountant",
        "auditor"
    ],
    "wof:name":"Price Baldsing Pty Ltd",
    "wof:placetype":"venue"
},
  "geometry": {"coordinates":[115.828262329,-31.8608474731],"type":"Point"}
}