{
  "type": "Feature",
  "properties": {
    "addr:full":"14 Young St Gosford West NSW 2250",
    "addr:housenumber":"14",
    "addr:postcode":"2250",
    "addr:street":"Young St",
    "iso:country":"AU",
    "sg:address":"14 Young St",
    "sg:city":"Gosford West",
    "sg:classifiers":[
        {
            "category":"Home & Garden",
            "subcategory":"Carpets & Floor Coverings",
            "type":"Retail Goods"
        }
    ],
    "sg:phone":"+61 2 4324 3009",
    "sg:postcode":"2250",
    "sg:province":"NSW",
    "wof:name":"Independent Carpet Centres",
    "wof:placetype":"venue"
},
  "geometry": {"coordinates":[151.32864379899999,-33.4255104065],"type":"Point"}
}