{
  "type": "Feature",
  "properties": {
    "addr:full":"21 Darley St Shellharbour NSW 2529",
    "addr:housenumber":"21",
    "addr:postcode":"2529",
    "addr:street":"Darley St",
    "iso:country":"AU",
    "sg:address":"21 Darley St",
    "sg:city":"Shellharbour",
    "sg:classifiers":[
        {
            "category":"Building & Trades",
            "subcategory":"Plumbing",
            "type":"Services"
        }
    ],
    "sg:phone":"+61 2 4297 3800",
    "sg:postcode":"2529",
    "sg:province":"NSW",
    "sg:tags":[
        "plumber",
        "gasfitters"
    ],
    "wof:name":"Shellharbour Hot Water",
    "wof:placetype":"venue"
},
  "geometry": {"coordinates":[150.869430542,-34.5812225342],"type":"Point"}
}