{
  "type": "Feature",
  "properties": {
    "iso:country":"AU",
    "sg:address":"1 Murdock St",
    "sg:city":"Turramurra",
    "sg:classifiers":[
        {
            "category":"Health Services",
            "subcategory":"Health Practitioner",
            "type":"Services"
        }
    ],
    "sg:phone":"+61 2 9440 8225",
    "sg:postcode":"2074",
    "sg:province":"NSW",
    "sg:tags":[
        "psychologist"
    ],
    "wof:name":"Mehravar Marzbani (S.K.)",
    "wof:placetype":"venue"
},
  "geometry": {"coordinates":[151.14207458499999,-33.7245407104],"type":"Point"}
}