{
  "type": "Feature",
  "properties": {
    "addr:full":"100 West St Glenroy VIC 3046",
    "addr:housenumber":"100",
    "addr:postcode":"3046",
    "addr:street":"West St",
    "iso:country":"AU",
    "sg:address":"100 West St",
    "sg:city":"Glenroy",
    "sg:classifiers":[
        {
            "category":"Personal",
            "subcategory":"Beauty Salon",
            "type":"Services"
        }
    ],
    "sg:phone":"+61 3 9304 2500",
    "sg:postcode":"3046",
    "sg:province":"VIC",
    "sg:tags":[
        "hairdresser"
    ],
    "wof:name":"Nu Do Hair",
    "wof:placetype":"venue"
},
  "geometry": {"coordinates":[144.938232422,-37.7089653015],"type":"Point"}
}