{
  "type": "Feature",
  "properties": {
    "addr:full":"6 Carmen Drv Carlingford NSW 2118",
    "addr:housenumber":"6",
    "addr:postcode":"2118",
    "addr:street":"Carmen Drv",
    "iso:country":"AU",
    "sg:address":"6 Carmen Drv",
    "sg:city":"Carlingford",
    "sg:classifiers":[
        {
            "category":"Food & Beverages",
            "subcategory":"Fruits & Vegetables",
            "type":"Retail Goods"
        }
    ],
    "sg:phone":"+61 2 9871 7233",
    "sg:postcode":"2118",
    "sg:province":"NSW",
    "sg:tags":[
        "greengrocer",
        "fruiterer"
    ],
    "wof:name":"Just Delicious Fruits",
    "wof:placetype":"venue"
},
  "geometry": {"coordinates":[151.041213989,-33.7609367371],"type":"Point"}
}