{
  "type": "Feature",
  "properties": {
    "addr:full":"Tree Tops Square, Suite 3, Level 1, 2 Classic Way Burleigh QLD 4220",
    "addr:housenumber":"2",
    "addr:postcode":"4220",
    "addr:street":"Classic Way",
    "iso:country":"AU",
    "sg:address":"Tree Tops Square, Suite 3, Level 1, 2 Classic Way",
    "sg:city":"Burleigh",
    "sg:classifiers":[
        {
            "category":"Professional",
            "subcategory":"Employment Agencies",
            "type":"Services"
        }
    ],
    "sg:phone":"+61 7 5569 5300",
    "sg:postcode":"4220",
    "sg:province":"QLD",
    "wof:name":"Manpower",
    "wof:placetype":"venue"
},
  "geometry": {"coordinates":[153.423751831,-28.1004199982],"type":"Point"}
}