{
  "type": "Feature",
  "properties": {
    "addr:full":"Suite 2, 1St Floor, 159 Queen St Campbelltown NSW 2560",
    "addr:housenumber":"159",
    "addr:postcode":"2560",
    "addr:street":"Queen St",
    "iso:country":"AU",
    "sg:address":"Suite 2, 1St Floor, 159 Queen St",
    "sg:city":"Campbelltown",
    "sg:classifiers":[
        {
            "category":"Health Services",
            "subcategory":"Health Practitioner",
            "type":"Services"
        }
    ],
    "sg:phone":"+61 416 086 912",
    "sg:postcode":"2560",
    "sg:province":"NSW",
    "sg:tags":[
        "alternative"
    ],
    "wof:name":"Belinda Bailey",
    "wof:placetype":"venue"
},
  "geometry": {"coordinates":[150.814178467,-34.0665512085],"type":"Point"}
}