{
  "type": "Feature",
  "properties": {
    "iso:country":"AU",
    "sg:address":"Aprt1003/ 180 Ocean St",
    "sg:city":"Edgecliff",
    "sg:classifiers":[
        {
            "category":"Banks & Credit Unions",
            "subcategory":"Investment Brokerage",
            "type":"Services"
        }
    ],
    "sg:phone":"+61 2 9362 9665",
    "sg:postcode":"2027",
    "sg:province":"NSW",
    "wof:name":"Investor Promotions Group Pty Ltd",
    "wof:placetype":"venue"
},
  "geometry": {"coordinates":[151.23748779300001,-33.8798713684],"type":"Point"}
}