{
  "type": "Feature",
  "properties": {
    "addr:full":"771 Princes Hwy Brooklyn VIC 3012",
    "addr:housenumber":"771",
    "addr:postcode":"3012",
    "addr:street":"Princes Hwy",
    "iso:country":"AU",
    "sg:address":"771 Princes Hwy",
    "sg:city":"Brooklyn",
    "sg:classifiers":[
        {
            "category":"Retail",
            "subcategory":"Auto Rental",
            "type":"Services"
        }
    ],
    "sg:phone":"+61 3 9314 0077",
    "sg:postcode":"3012",
    "sg:province":"VIC",
    "sg:tags":[
        "camper-trailers",
        "caravan",
        "hire"
    ],
    "wof:name":"Mark Thomas Caravans",
    "wof:placetype":"venue"
},
  "geometry": {"coordinates":[144.84628295900001,-37.8176841736],"type":"Point"}
}