{
  "type": "Feature",
  "properties": {
    "iso:country":"AU",
    "sg:address":"Huntingdale Rd",
    "sg:city":"Oakleigh",
    "sg:classifiers":[
        {
            "category":"Retail",
            "subcategory":"Storage",
            "type":"Services"
        }
    ],
    "sg:phone":"+61 1300 552 521",
    "sg:postcode":"3166",
    "sg:province":"VIC",
    "sg:tags":[
        "removal",
        "furniture"
    ],
    "wof:name":"Atlas Transport & Carrier Agents",
    "wof:placetype":"venue"
},
  "geometry": {"coordinates":[145.105300903,-37.901550293],"type":"Point"}
}