{
  "type": "Feature",
  "properties": {
    "addr:full":"Parramatta Grnd Flr St John's Building 191 Church St Parramatta NSW 2150",
    "addr:housenumber":"191",
    "addr:postcode":"2150",
    "addr:street":"Parramatta Grnd;Church St",
    "iso:country":"AU",
    "sg:address":"Parramatta Grnd Flr St John's Building 191 Church St",
    "sg:city":"Parramatta",
    "sg:classifiers":[
        {
            "category":"Personal",
            "subcategory":"Skin Care",
            "type":"Services"
        }
    ],
    "sg:phone":"+61 2 9730 4372",
    "sg:postcode":"2150",
    "sg:province":"NSW",
    "sg:tags":[
        "treatment"
    ],
    "wof:name":"Psoriasis & Acne Clinic",
    "wof:placetype":"venue"
},
  "geometry": {"coordinates":[151.11875915499999,-33.8752250671],"type":"Point"}
}