{
  "type": "Feature",
  "properties": {
    "addr:full":"13 - 21 Lake Weyba Drv Noosaville QLD 4566",
    "addr:housenumber":"21",
    "addr:postcode":"4566",
    "addr:street":"Lake Weyba Drv",
    "iso:country":"AU",
    "sg:address":"13 - 21 Lake Weyba Drv",
    "sg:city":"Noosaville",
    "sg:classifiers":[
        {
            "category":"Social Services",
            "subcategory":"Retirement Home",
            "type":"Services"
        }
    ],
    "sg:phone":"+61 7 5449 7770",
    "sg:postcode":"4566",
    "sg:province":"QLD",
    "sg:tags":[
        "village"
    ],
    "wof:name":"Laguna Estate Pty Ltd",
    "wof:placetype":"venue"
},
  "geometry": {"coordinates":[153.07188415499999,-26.4046916962],"type":"Point"}
}