{
  "type": "Feature",
  "properties": {
    "addr:full":"501 Great Eastern Hwy Redcliffe WA 6104",
    "addr:housenumber":"501",
    "addr:postcode":"6104",
    "addr:street":"Great Eastern Hwy",
    "iso:country":"AU",
    "sg:address":"501 Great Eastern Hwy",
    "sg:city":"Redcliffe",
    "sg:classifiers":[
        {
            "category":"Retail",
            "subcategory":"Auto Rental",
            "type":"Services"
        }
    ],
    "sg:phone":"+61 8 9478 2755",
    "sg:postcode":"6104",
    "sg:province":"WA",
    "sg:tags":[
        "home",
        "hire",
        "motor",
        "campervans"
    ],
    "sg:website":"http://www.camperworld.com.au",
    "wof:name":"Camperworld",
    "wof:placetype":"venue"
},
  "geometry": {"coordinates":[115.951141357,-31.9264507294],"type":"Point"}
}