{
  "type": "Feature",
  "properties": {
    "iso:country":"AU",
    "sg:address":"37 Sun Crs",
    "sg:city":"Happy Valley",
    "sg:classifiers":[
        {
            "category":"Building & Trades",
            "subcategory":"Landscaping Services",
            "type":"Services"
        }
    ],
    "sg:phone":"+61 8 8381 3666",
    "sg:postcode":"5159",
    "sg:province":"SA",
    "sg:tags":[
        "gardener"
    ],
    "wof:name":"Nandina Complete Gardening Service",
    "wof:placetype":"venue"
},
  "geometry": {"coordinates":[138.57586669899999,-35.0831108093],"type":"Point"}
}