{
  "type": "Feature",
  "properties": {
    "addr:full":"199 Kingaroy St Kingaroy QLD 4610",
    "addr:housenumber":"199",
    "addr:postcode":"4610",
    "addr:street":"Kingaroy St",
    "iso:country":"AU",
    "sg:address":"199 Kingaroy St",
    "sg:city":"Kingaroy",
    "sg:classifiers":[
        {
            "category":"Cafe",
            "type":"Food & Drink"
        }
    ],
    "sg:phone":"+61 7 4162 3833",
    "sg:postcode":"4610",
    "sg:province":"QLD",
    "wof:name":"Utopia Cafe",
    "wof:placetype":"venue"
},
  "geometry": {"coordinates":[151.83926391599999,-26.5400314331],"type":"Point"}
}