{
  "type": "Feature",
  "properties": {
    "addr:full":"Dry Creek Rd Eildon VIC 3713",
    "addr:postcode":"3713",
    "addr:street":"Creek Rd",
    "iso:country":"AU",
    "sg:address":"Dry Creek Rd",
    "sg:city":"Eildon",
    "sg:classifiers":[
        {
            "category":"Sports & Exercise",
            "subcategory":"Golf",
            "type":"Entertainment"
        }
    ],
    "sg:phone":"+61 3 5774 2044",
    "sg:postcode":"3713",
    "sg:province":"VIC",
    "sg:tags":[
        "club"
    ],
    "wof:name":"Eildon Golf Club",
    "wof:placetype":"venue"
},
  "geometry": {"coordinates":[145.90672302199999,-37.3157272339],"type":"Point"}
}