{
  "type": "Feature",
  "properties": {
    "iso:country":"AU",
    "sg:address":"PO Box 15",
    "sg:city":"Drysdale",
    "sg:classifiers":[
        {
            "category":"Utilities",
            "subcategory":"Electric",
            "type":"Services"
        }
    ],
    "sg:phone":"+61 3 5259 3646",
    "sg:postcode":"3222",
    "sg:province":"VIC",
    "sg:tags":[
        "electrical",
        "contractor"
    ],
    "wof:name":"Safeline Electrics",
    "wof:placetype":"venue"
},
  "geometry": {"coordinates":[144.590103,-38.153461],"type":"Point"}
}