{
  "type": "Feature",
  "properties": {
    "iso:country":"AU",
    "sg:address":"Cnr Canning Hwy & Stock Rd",
    "sg:city":"Melville",
    "sg:classifiers":[
        {
            "category":"Health Services",
            "subcategory":"Health Practitioner",
            "type":"Services"
        }
    ],
    "sg:phone":"+61 8 9330 8081",
    "sg:postcode":"6156",
    "sg:province":"WA",
    "sg:tags":[
        "alternative"
    ],
    "wof:name":"Buteyko Perth",
    "wof:placetype":"venue"
},
  "geometry": {"coordinates":[115.804047,-32.03252],"type":"Point"}
}