{
  "type": "Feature",
  "properties": {
    "addr:full":"38 Forge St Blacktown NSW 2148",
    "addr:housenumber":"38",
    "addr:postcode":"2148",
    "addr:street":"Forge St",
    "iso:country":"AU",
    "sg:address":"38 Forge St",
    "sg:city":"Blacktown",
    "sg:classifiers":[
        {
            "category":"Building & Trades",
            "subcategory":"Construction",
            "type":"Services"
        }
    ],
    "sg:phone":"+61 2 9831 3199",
    "sg:postcode":"2148",
    "sg:province":"NSW",
    "sg:tags":[
        "scaffolding"
    ],
    "sg:website":"http://www.activeplatforms.com.au",
    "wof:name":"Active Platforms P/L",
    "wof:placetype":"venue"
},
  "geometry": {"coordinates":[150.91000366200001,-33.7537117004],"type":"Point"}
}