{
  "type": "Feature",
  "properties": {
    "iso:country":"AU",
    "sg:address":"15 Bradpole Rd",
    "sg:city":"Elizabeth West",
    "sg:classifiers":[
        {
            "category":"Retail",
            "subcategory":"Driving School",
            "type":"Services"
        }
    ],
    "sg:phone":"+61 8 8287 0033",
    "sg:postcode":"5113",
    "sg:province":"SA",
    "wof:name":"Allsafe Forklift Training",
    "wof:placetype":"venue"
},
  "geometry": {"coordinates":[138.666183472,-34.7074050903],"type":"Point"}
}