{
  "type": "Feature",
  "properties": {
    "addr:full":"610 South Rd Moorabbin VIC 3189",
    "addr:housenumber":"610",
    "addr:postcode":"3189",
    "addr:street":"South Rd",
    "iso:country":"AU",
    "sg:address":"610 South Rd",
    "sg:city":"Moorabbin",
    "sg:classifiers":[
        {
            "category":"Shopping",
            "subcategory":"Stationery & Office Supplies",
            "type":"Retail Goods"
        }
    ],
    "sg:phone":"+61 3 9553 0033",
    "sg:postcode":"3189",
    "sg:province":"VIC",
    "sg:tags":[
        "equipment",
        "facsimile"
    ],
    "wof:name":"Brother Office National",
    "wof:placetype":"venue"
},
  "geometry": {"coordinates":[145.06466674800001,-37.9370651245],"type":"Point"}
}