{
  "type": "Feature",
  "properties": {
    "addr:full":"30 East St Granville NSW 2142",
    "addr:housenumber":"30",
    "addr:postcode":"2142",
    "addr:street":"East St",
    "iso:country":"AU",
    "sg:address":"30 East St",
    "sg:city":"Granville",
    "sg:classifiers":[
        {
            "category":"Manufacturing",
            "subcategory":"Tobacco Products",
            "type":"Manufacturing & Wholesale Goods"
        }
    ],
    "sg:phone":"+61 2 9682 4144",
    "sg:postcode":"2142",
    "sg:province":"NSW",
    "sg:tags":[
        "car",
        "truck",
        "cleaning",
        "equipment"
    ],
    "sg:website":"http://www.goodsight.com.au",
    "wof:name":"Good Sight Co Ltd",
    "wof:placetype":"venue"
},
  "geometry": {"coordinates":[151.01411438,-33.8332557678],"type":"Point"}
}