{
  "type": "Feature",
  "properties": {
    "iso:country":"AU",
    "sg:address":"303 Victoria Rd",
    "sg:city":"Malaga",
    "sg:classifiers":[
        {
            "category":"Building & Trades",
            "subcategory":"Construction",
            "type":"Services"
        }
    ],
    "sg:phone":"+61 8 9249 1844",
    "sg:postcode":"6090",
    "sg:province":"WA",
    "sg:tags":[
        "fencing",
        "contractor"
    ],
    "wof:name":"Frameless Glass By Hensons",
    "wof:placetype":"venue"
},
  "geometry": {"coordinates":[115.889373779,-31.8616752625],"type":"Point"}
}