{
  "type": "Feature",
  "properties": {
    "addr:full":"PO Box 7057 Aspendale VIC 3195",
    "addr:postcode":"3195",
    "iso:country":"AU",
    "sg:address":"PO Box 7057",
    "sg:city":"Aspendale",
    "sg:classifiers":[
        {
            "category":"Personal",
            "subcategory":"Beauty Salon",
            "type":"Services"
        }
    ],
    "sg:phone":"+61 3 9580 2037",
    "sg:postcode":"3195",
    "sg:province":"VIC",
    "sg:tags":[
        "supply",
        "artist",
        "make-up"
    ],
    "wof:name":"Make Me Over",
    "wof:placetype":"venue"
},
  "geometry": {"coordinates":[145.10214233400001,-38.0269012451],"type":"Point"}
}