{
  "type": "Feature",
  "properties": {
    "iso:country":"AU",
    "sg:address":"122 Boundary Rd",
    "sg:city":"Mordialloc",
    "sg:classifiers":[
        {
            "category":"Retail",
            "subcategory":"Auto Repair",
            "type":"Services"
        }
    ],
    "sg:phone":"+61 3 9580 0427",
    "sg:postcode":"3195",
    "sg:province":"VIC",
    "sg:tags":[
        "repairer",
        "motor",
        "engineer"
    ],
    "wof:name":"Safer Steering",
    "wof:placetype":"venue"
},
  "geometry": {"coordinates":[145.10546875,-38.0012397766],"type":"Point"}
}