{
  "type": "Feature",
  "properties": {
    "iso:country":"AU",
    "sg:address":"118 Arlunya Ave",
    "sg:city":"Cloverdale",
    "sg:classifiers":[
        {
            "category":"Building & Trades",
            "subcategory":"Construction",
            "type":"Services"
        }
    ],
    "sg:phone":"+61 8 9477 6262",
    "sg:postcode":"6105",
    "sg:province":"WA",
    "sg:tags":[
        "concrete",
        "contractor"
    ],
    "wof:name":"Dale Concrete Co",
    "wof:placetype":"venue"
},
  "geometry": {"coordinates":[115.9400177,-31.960308075],"type":"Point"}
}