{
  "type": "Feature",
  "properties": {
    "addr:full":"10 Mellor Crt Midland WA 6056",
    "addr:housenumber":"10",
    "addr:postcode":"6056",
    "addr:street":"Mellor Crt",
    "iso:country":"AU",
    "sg:address":"10 Mellor Crt",
    "sg:city":"Midland",
    "sg:classifiers":[
        {
            "category":"Education",
            "subcategory":"Kindergarten",
            "type":"Public Place"
        }
    ],
    "sg:phone":"+61 8 9250 3319",
    "sg:postcode":"6056",
    "sg:province":"WA",
    "sg:tags":[
        "pre-schools"
    ],
    "wof:name":"Midland School For Early Childhood Development",
    "wof:placetype":"venue"
},
  "geometry": {"coordinates":[116.01374054,-31.8877773285],"type":"Point"}
}