{
  "type": "Feature",
  "properties": {
    "addr:full":"84 Bright St Guildford NSW 2161",
    "addr:housenumber":"84",
    "addr:postcode":"2161",
    "addr:street":"Bright St",
    "iso:country":"AU",
    "sg:address":"84 Bright St",
    "sg:city":"Guildford",
    "sg:classifiers":[
        {
            "category":"Retail",
            "subcategory":"Auto Repair",
            "type":"Services"
        }
    ],
    "sg:phone":"+61 2 9632 9384",
    "sg:postcode":"2161",
    "sg:province":"NSW",
    "sg:tags":[
        "bus",
        "truck"
    ],
    "wof:name":"Baxter Motor Repair Pty Ltd",
    "wof:placetype":"venue"
},
  "geometry": {"coordinates":[150.99661254899999,-33.8550338745],"type":"Point"}
}