{
  "type": "Feature",
  "properties": {
    "addr:full":"934 Beaufort St Inglewood WA 6052",
    "addr:housenumber":"934",
    "addr:postcode":"6052",
    "addr:street":"Beaufort St",
    "iso:country":"AU",
    "sg:address":"934 Beaufort St",
    "sg:city":"Inglewood",
    "sg:classifiers":[
        {
            "category":"Autos & Motor Vehicles",
            "subcategory":"Automobile Sales",
            "type":"Retail Goods"
        }
    ],
    "sg:phone":"+61 8 9272 2888",
    "sg:postcode":"6052",
    "sg:province":"WA",
    "sg:tags":[
        "car",
        "used"
    ],
    "wof:name":"Civic Motors",
    "wof:placetype":"venue"
},
  "geometry": {"coordinates":[115.886642456,-31.9209861755],"type":"Point"}
}