{
  "type": "Feature",
  "properties": {
    "iso:country":"AU",
    "sg:address":"7 Kelly St",
    "sg:city":"Ultimo",
    "sg:classifiers":[
        {
            "category":"Professional",
            "subcategory":"Advertising",
            "type":"Services"
        }
    ],
    "sg:postcode":"2007",
    "sg:tags":[
        "marketing",
        "campaigns",
        "api",
        "email",
        "competitions",
        "reporting",
        "analytics",
        "register"
    ],
    "sg:website":"http://www.jointheclicks.com",
    "wof:name":"Join The Clicks",
    "wof:placetype":"venue"
},
  "geometry": {"coordinates":[151.19551999999999,-33.881451],"type":"Point"}
}