{
  "type": "Feature",
  "properties": {
    "addr:full":"Angus St Clontarf QLD 4019",
    "addr:postcode":"4019",
    "addr:street":"Angus St",
    "iso:country":"AU",
    "sg:address":"Angus St",
    "sg:city":"Clontarf",
    "sg:classifiers":[
        {
            "category":"Wholesale",
            "subcategory":"Medical Equipment & Supplies",
            "type":"Manufacturing & Wholesale Goods"
        }
    ],
    "sg:phone":"+61 7 3284 5302",
    "sg:postcode":"4019",
    "sg:province":"QLD",
    "sg:tags":[
        "aid",
        "care",
        "health",
        "home"
    ],
    "wof:name":"Clontarf Furniture & Bedding Centre",
    "wof:placetype":"venue"
},
  "geometry": {"coordinates":[153.08140564000001,-27.2591285706],"type":"Point"}
}