{
  "type": "Feature",
  "properties": {
    "iso:country":"AU",
    "sg:address":"33 Falcon Rd",
    "sg:city":"Claremont",
    "sg:classifiers":[
        {
            "category":"Health Services",
            "subcategory":"Doctor",
            "type":"Services"
        }
    ],
    "sg:phone":"+61 3 6249 7165",
    "sg:postcode":"7011",
    "sg:province":"TAS",
    "sg:tags":[
        "occupational",
        "safety"
    ],
    "wof:name":"Terts, Pearu",
    "wof:placetype":"venue"
},
  "geometry": {"coordinates":[147.261062622,-42.7993354797],"type":"Point"}
}