{
  "type": "Feature",
  "properties": {
    "addr:full":"2 Stevens Rd Rosewood QLD 4340",
    "addr:housenumber":"2",
    "addr:postcode":"4340",
    "addr:street":"Stevens Rd",
    "iso:country":"AU",
    "sg:address":"2 Stevens Rd",
    "sg:city":"Rosewood",
    "sg:classifiers":[
        {
            "category":"Utilities",
            "subcategory":"Water",
            "type":"Services"
        }
    ],
    "sg:phone":"+61 432 969 684",
    "sg:postcode":"4340",
    "sg:province":"QLD",
    "sg:tags":[
        "cartage"
    ],
    "wof:name":"H2 Go Water Cartage",
    "wof:placetype":"venue"
},
  "geometry": {"coordinates":[152.55390930199999,-27.6442832947],"type":"Point"}
}