{
  "type": "Feature",
  "properties": {
    "addr:full":"Shop 9/ 13 Mount St Cecil Hills NSW 2171",
    "addr:housenumber":"shop 9 / 13",
    "addr:postcode":"2171",
    "addr:street":"Mount St Cecil",
    "iso:country":"AU",
    "sg:address":"Shop 9/ 13 Mount St",
    "sg:city":"Cecil Hills",
    "sg:classifiers":[
        {
            "category":"Banks & Credit Unions",
            "subcategory":"Financial Services",
            "type":"Services"
        }
    ],
    "sg:phone":"+61 2 9832 9811",
    "sg:postcode":"2171",
    "sg:province":"NSW",
    "sg:tags":[
        "loan",
        "finance",
        "mortgage"
    ],
    "wof:name":"Choice Home Loans",
    "wof:placetype":"venue"
},
  "geometry": {"coordinates":[150.86778259299999,-33.8875923157],"type":"Point"}
}