{
  "type": "Feature",
  "properties": {
    "addr:full":"143 Trappers Drv Woodvale WA 6026",
    "addr:housenumber":"143",
    "addr:postcode":"6026",
    "addr:street":"Trappers Drv",
    "iso:country":"AU",
    "sg:address":"143 Trappers Drv",
    "sg:city":"Woodvale",
    "sg:classifiers":[
        {
            "category":"Retail",
            "subcategory":"Event Space",
            "type":"Services"
        }
    ],
    "sg:phone":"+61 8 9309 5288",
    "sg:postcode":"6026",
    "sg:province":"WA",
    "sg:tags":[
        "venue",
        "reception",
        "wedding"
    ],
    "wof:name":"The Moon Woodvale Tavern and Reception Centre",
    "wof:placetype":"venue"
},
  "geometry": {"coordinates":[115.787277222,-31.7836418152],"type":"Point"}
}