{
  "type": "Feature",
  "properties": {
    "addr:full":"Flaxman Valley Rd Angaston SA 5353",
    "addr:postcode":"5353",
    "addr:street":"Valley Rd",
    "iso:country":"AU",
    "sg:address":"Flaxman Valley Rd",
    "sg:city":"Angaston",
    "sg:classifiers":[
        {
            "category":"Farming",
            "subcategory":"Farm",
            "type":"Manufacturing & Wholesale Goods"
        }
    ],
    "sg:phone":"+61 8 8565 3263",
    "sg:postcode":"5353",
    "sg:province":"SA",
    "sg:tags":[
        "farmer"
    ],
    "wof:name":"Grossman R A & M D",
    "wof:placetype":"venue"
},
  "geometry": {"coordinates":[139.05430602999999,-34.5084381104],"type":"Point"}
}