{
  "type": "Feature",
  "properties": {
    "iso:country":"AU",
    "sg:address":"2000 Gold Coast Hwy",
    "sg:city":"Miami",
    "sg:classifiers":[
        {
            "category":"Autos & Motor Vehicles",
            "subcategory":"Fuel & Gas Station",
            "type":"Retail Goods"
        }
    ],
    "sg:phone":"+61 7 5535 2880",
    "sg:postcode":"4220",
    "sg:province":"QLD",
    "wof:name":"Mobil Oil Aust Ltd",
    "wof:placetype":"venue"
},
  "geometry": {"coordinates":[153.443084717,-28.0710067749],"type":"Point"}
}