{
  "type": "Feature",
  "properties": {
    "iso:country":"AU",
    "sg:address":"Shop 1/ 300 Hobart Rd",
    "sg:city":"Youngtown",
    "sg:classifiers":[
        {
            "category":"Manufacturing",
            "subcategory":"Retail Goods",
            "type":"Manufacturing & Wholesale Goods"
        }
    ],
    "sg:phone":"+61 3 6343 6400",
    "sg:postcode":"7249",
    "sg:province":"TAS",
    "sg:tags":[
        "merchant",
        "pump",
        "mfrs"
    ],
    "wof:name":"Pumptech Tasmania",
    "wof:placetype":"venue"
},
  "geometry": {"coordinates":[147.16671752900001,-41.480178833],"type":"Point"}
}