{
  "type": "Feature",
  "properties": {
    "addr:full":"Suite 2/ 10-11 Ferguson Rd Springwood NSW 2777",
    "addr:housenumber":"/ 10-11",
    "addr:postcode":"2777",
    "addr:street":"Ferguson Rd",
    "iso:country":"AU",
    "sg:address":"Suite 2/ 10-11 Ferguson Rd",
    "sg:city":"Springwood",
    "sg:classifiers":[
        {
            "category":"Organizations",
            "subcategory":"Community Association",
            "type":"Services"
        }
    ],
    "sg:phone":"+61 2 4751 3105",
    "sg:postcode":"2777",
    "sg:province":"NSW",
    "sg:tags":[
        "organisation",
        "family",
        "welfare"
    ],
    "wof:name":"Open House Adolescent Foster Care Programme",
    "wof:placetype":"venue"
},
  "geometry": {"coordinates":[150.561004639,-33.7006835938],"type":"Point"}
}