{
  "type": "Feature",
  "properties": {
    "iso:country":"AU",
    "sg:address":"133 Queen St",
    "sg:city":"Concord West",
    "sg:classifiers":[
        {
            "category":"Social Services",
            "subcategory":"Adult Care",
            "type":"Services"
        }
    ],
    "sg:phone":"+61 2 9743 1386",
    "sg:postcode":"2138",
    "sg:province":"NSW",
    "sg:tags":[
        "towing"
    ],
    "wof:name":"Homebush Towing",
    "wof:placetype":"venue"
},
  "geometry": {"coordinates":[151.08615112300001,-33.8492393494],"type":"Point"}
}