{
  "type": "Feature",
  "properties": {
    "addr:full":"U12/ 375 William St Northbridge WA 6003",
    "addr:housenumber":"375",
    "addr:postcode":"6003",
    "addr:street":"/;William St",
    "iso:country":"AU",
    "sg:address":"U12/ 375 William St",
    "sg:city":"Northbridge",
    "sg:classifiers":[
        {
            "category":"Personal",
            "subcategory":"Beauty Salon",
            "type":"Services"
        }
    ],
    "sg:phone":"+61 8 9328 4111",
    "sg:postcode":"6003",
    "sg:province":"WA",
    "sg:tags":[
        "hairdresser"
    ],
    "wof:name":"Top Image Hair Design",
    "wof:placetype":"venue"
},
  "geometry": {"coordinates":[115.861717224,-31.9449768066],"type":"Point"}
}