{
  "type": "Feature",
  "properties": {
    "iso:country":"AU",
    "sg:address":"222 Vincent St",
    "sg:city":"Cessnock",
    "sg:classifiers":[
        {
            "category":"Retail",
            "subcategory":"Auto Repair",
            "type":"Services"
        }
    ],
    "sg:phone":"+61 2 4990 7895",
    "sg:postcode":"2325",
    "sg:province":"NSW",
    "sg:tags":[
        "repairer",
        "motor",
        "engineer"
    ],
    "wof:name":"Carl Walters Automotive",
    "wof:placetype":"venue"
},
  "geometry": {"coordinates":[151.355194092,-32.8414649963],"type":"Point"}
}