{
  "type": "Feature",
  "properties": {
    "addr:full":"South Rd Braybrook VIC 3019",
    "addr:postcode":"3019",
    "addr:street":"South Rd",
    "iso:country":"AU",
    "sg:address":"South Rd",
    "sg:city":"Braybrook",
    "sg:classifiers":[
        {
            "category":"Education",
            "subcategory":"School",
            "type":"Public Place"
        }
    ],
    "sg:phone":"+61 3 9311 1598",
    "sg:postcode":"3019",
    "sg:province":"VIC",
    "sg:tags":[
        "state",
        "except",
        "nsw"
    ],
    "wof:name":"Dinjerra Primary",
    "wof:placetype":"venue"
},
  "geometry": {"coordinates":[144.851730347,-37.7913513184],"type":"Point"}
}