{
  "type": "Feature",
  "properties": {
    "addr:full":"119 Magowar Rd Girraween NSW 2145",
    "addr:housenumber":"119",
    "addr:postcode":"2145",
    "addr:street":"Magowar Rd",
    "iso:country":"AU",
    "sg:address":"119 Magowar Rd",
    "sg:city":"Girraween",
    "sg:classifiers":[
        {
            "category":"Retail",
            "subcategory":"Auto Repair",
            "type":"Services"
        }
    ],
    "sg:phone":"+61 2 9636 1122",
    "sg:postcode":"2145",
    "sg:province":"NSW",
    "sg:tags":[
        "bus",
        "truck"
    ],
    "wof:name":"Willis & Son Automotive Repairs Pty Ltd",
    "wof:placetype":"venue"
},
  "geometry": {"coordinates":[150.94424438499999,-33.8014640808],"type":"Point"}
}