{
  "type": "Feature",
  "properties": {
    "iso:country":"AU",
    "sg:address":"Level 7, 33 Argyle St",
    "sg:city":"Parramatta",
    "sg:classifiers":[
        {
            "category":"Banks & Credit Unions",
            "subcategory":"Financial Services",
            "type":"Services"
        }
    ],
    "sg:phone":"+61 1800 008 999",
    "sg:postcode":"2150",
    "sg:province":"NSW",
    "sg:tags":[
        "loan",
        "finance",
        "mortgage"
    ],
    "wof:name":"Revas Home Loans Pty Limited",
    "wof:placetype":"venue"
},
  "geometry": {"coordinates":[151.077850342,-33.9574432373],"type":"Point"}
}