{
  "type": "Feature",
  "properties": {
    "iso:country":"AU",
    "sg:address":"12 Queens La",
    "sg:city":"Melbourne",
    "sg:classifiers":[
        {
            "category":"Cafe",
            "type":"Food & Drink"
        }
    ],
    "sg:phone":"+61 3 9866 4115",
    "sg:postcode":"3004",
    "sg:province":"VIC",
    "wof:name":"Latte & Lunch",
    "wof:placetype":"venue"
},
  "geometry": {"coordinates":[144.975097656,-37.8388175964],"type":"Point"}
}