{
  "type": "Feature",
  "properties": {
    "addr:full":"Lot 14 Barraba Rd Upper Manilla NSW 2346",
    "addr:postcode":"2346",
    "addr:street":"Barraba Rd",
    "iso:country":"AU",
    "sg:address":"Lot 14 Barraba Rd",
    "sg:city":"Upper Manilla",
    "sg:classifiers":[
        {
            "category":"Building & Trades",
            "subcategory":"Landscaping Services",
            "type":"Services"
        }
    ],
    "sg:phone":"+61 2 6785 6590",
    "sg:postcode":"2346",
    "sg:province":"NSW",
    "sg:tags":[
        "control",
        "weed"
    ],
    "wof:name":"Plains Spraying Pty Ltd",
    "wof:placetype":"venue"
},
  "geometry": {"coordinates":[150.71336364699999,-30.7380371094],"type":"Point"}
}