{
  "type": "Feature",
  "properties": {
    "iso:country":"AU",
    "sg:address":"Suite 2 148 Greenhill Rd",
    "sg:city":"Parkside",
    "sg:classifiers":[
        {
            "category":"Banks & Credit Unions",
            "subcategory":"Investment Brokerage",
            "type":"Services"
        }
    ],
    "sg:phone":"+61 8 8271 1855",
    "sg:postcode":"5063",
    "sg:province":"SA",
    "sg:tags":[
        "management",
        "property"
    ],
    "wof:name":"Leicester Management Services",
    "wof:placetype":"venue"
},
  "geometry": {"coordinates":[138.607177734,-34.9411010742],"type":"Point"}
}