{
  "type": "Feature",
  "properties": {
    "iso:country":"AU",
    "sg:address":"28 Cormack Rd",
    "sg:city":"Wingfield",
    "sg:classifiers":[
        {
            "category":"Wholesale",
            "subcategory":"Auto Parts",
            "type":"Manufacturing & Wholesale Goods"
        }
    ],
    "sg:phone":"+61 8 8243 2000",
    "sg:postcode":"5013",
    "sg:province":"SA",
    "sg:tags":[
        "tyre"
    ],
    "wof:name":"Aichi Industrial Tyres Aust Pty Ltd",
    "wof:placetype":"venue"
},
  "geometry": {"coordinates":[138.56797790499999,-34.8402175903],"type":"Point"}
}