{
  "type": "Feature",
  "properties": {
    "addr:full":"PO Box 448 Nundah QLD 4012",
    "addr:postcode":"4012",
    "iso:country":"AU",
    "sg:address":"PO Box 448",
    "sg:city":"Nundah",
    "sg:classifiers":[
        {
            "category":"Social Services",
            "subcategory":"Adult Care",
            "type":"Services"
        }
    ],
    "sg:phone":"+61 7 3266 3677",
    "sg:postcode":"4012",
    "sg:province":"QLD",
    "sg:tags":[
        "towing"
    ],
    "wof:name":"Tow-N-Ride",
    "wof:placetype":"venue"
},
  "geometry": {"coordinates":[153.05999755900001,-27.4019603729],"type":"Point"}
}