{
  "type": "Feature",
  "properties": {
    "iso:country":"AU",
    "sg:address":"Cnr Hill St & William St",
    "sg:city":"Emu Park",
    "sg:classifiers":[
        {
            "category":"Health Services",
            "subcategory":"Doctor",
            "type":"Services"
        }
    ],
    "sg:phone":"+61 7 4938 7387",
    "sg:postcode":"4702",
    "sg:province":"QLD",
    "sg:tags":[
        "medical",
        "practitioner"
    ],
    "wof:name":"Lang W E",
    "wof:placetype":"venue"
},
  "geometry": {"coordinates":[150.329147339,-23.4824829102],"type":"Point"}
}