{
  "type": "Feature",
  "properties": {
    "iso:country":"AU",
    "sg:address":"48 King St",
    "sg:city":"Hobart",
    "sg:classifiers":[
        {
            "category":"Autos & Motor Vehicles",
            "subcategory":"Automobile Sales",
            "type":"Retail Goods"
        }
    ],
    "sg:phone":"+61 3 6223 7709",
    "sg:postcode":"7000",
    "sg:province":"TAS",
    "sg:tags":[
        "car",
        "new"
    ],
    "wof:name":"Kingsway Motors",
    "wof:placetype":"venue"
},
  "geometry": {"coordinates":[147.32638549800001,-42.8946456909],"type":"Point"}
}