{
  "type": "Feature",
  "properties": {
    "addr:full":"Loxton Rd Pinnaroo SA 5304",
    "addr:postcode":"5304",
    "addr:street":"Loxton Rd",
    "iso:country":"AU",
    "sg:address":"Loxton Rd",
    "sg:city":"Pinnaroo",
    "sg:classifiers":[
        {
            "category":"Farming",
            "subcategory":"Farm",
            "type":"Manufacturing & Wholesale Goods"
        }
    ],
    "sg:phone":"+61 8 8577 8415",
    "sg:postcode":"5304",
    "sg:province":"SA",
    "sg:tags":[
        "farmer"
    ],
    "wof:name":"Thiel M S",
    "wof:placetype":"venue"
},
  "geometry": {"coordinates":[140.872512817,-35.304599762],"type":"Point"}
}