{
  "type": "Feature",
  "properties": {
    "iso:country":"AU",
    "sg:address":"5a Field St",
    "sg:city":"Hampton",
    "sg:classifiers":[
        {
            "category":"Real Estate",
            "subcategory":"Developer",
            "type":"Services"
        }
    ],
    "sg:phone":"+61 3 9598 9401",
    "sg:postcode":"3188",
    "sg:province":"VIC",
    "sg:tags":[
        "development"
    ],
    "wof:name":"Emblem Heights Pty Ltd",
    "wof:placetype":"venue"
},
  "geometry": {"coordinates":[145.01742553700001,-37.9446296692],"type":"Point"}
}