{
  "type": "Feature",
  "properties": {
    "addr:full":"Shp10/ 10 Parks St Mona Vale NSW 2103",
    "addr:postcode":"2103",
    "addr:street":"Parks St",
    "iso:country":"AU",
    "sg:address":"Shp10/ 10 Parks St",
    "sg:city":"Mona Vale",
    "sg:classifiers":[
        {
            "category":"Fast Food",
            "type":"Food & Drink"
        }
    ],
    "sg:phone":"+61 2 9999 4209",
    "sg:postcode":"2103",
    "sg:province":"NSW",
    "sg:tags":[
        "away",
        "take"
    ],
    "wof:name":"Chickens Plus",
    "wof:placetype":"venue"
},
  "geometry": {"coordinates":[151.30526733400001,-33.6764183044],"type":"Point"}
}