{
  "type": "Feature",
  "properties": {
    "iso:country":"AU",
    "sg:address":"2 Elizabeth St",
    "sg:city":"Oakleigh East",
    "sg:classifiers":[
        {
            "category":"Transit Center",
            "subcategory":"Freight",
            "type":"Transportation"
        }
    ],
    "sg:phone":"+61 3 9543 8162",
    "sg:postcode":"3166",
    "sg:province":"VIC",
    "sg:tags":[
        "forklift",
        "truck"
    ],
    "wof:name":"Forkmac",
    "wof:placetype":"venue"
},
  "geometry": {"coordinates":[145.10618591299999,-37.8981437683],"type":"Point"}
}