{
  "type": "Feature",
  "properties": {
    "iso:country":"AU",
    "sg:address":"Shp 2/ 18 Kenthurst Rd",
    "sg:city":"Dural",
    "sg:classifiers":[
        {
            "category":"Personal",
            "type":"Services"
        }
    ],
    "sg:phone":"+61 2 9651 1923",
    "sg:postcode":"2158",
    "sg:province":"NSW",
    "sg:tags":[
        "gift"
    ],
    "wof:name":"Indigo Inspirations",
    "wof:placetype":"venue"
},
  "geometry": {"coordinates":[151.019134522,-33.6912765503],"type":"Point"}
}