{
  "type": "Feature",
  "properties": {
    "addr:full":"Chittaway Cntr Chittaway Bay NSW 2261",
    "addr:postcode":"2261",
    "iso:country":"AU",
    "sg:address":"Chittaway Cntr",
    "sg:city":"Chittaway Bay",
    "sg:classifiers":[
        {
            "category":"Health Services",
            "subcategory":"Optometrist",
            "type":"Services"
        }
    ],
    "sg:phone":"+61 2 4388 9488",
    "sg:postcode":"2261",
    "sg:province":"NSW",
    "wof:name":"Sleeman Optometry",
    "wof:placetype":"venue"
},
  "geometry": {"coordinates":[151.42808500000001,-33.326813],"type":"Point"}
}