{
  "type": "Feature",
  "properties": {
    "iso:country":"AU",
    "sg:address":"1 / 147 Ryrie St",
    "sg:city":"Geelong",
    "sg:classifiers":[
        {
            "category":"Utilities",
            "subcategory":"Natural Gas",
            "type":"Services"
        }
    ],
    "sg:phone":"+61 3 5229 8087",
    "sg:postcode":"3220",
    "sg:province":"VIC",
    "sg:tags":[
        "consultant",
        "resource"
    ],
    "wof:name":"Mark Trengove Ecological Services",
    "wof:placetype":"venue"
},
  "geometry": {"coordinates":[144.359695,-38.149059],"type":"Point"}
}