{
  "type": "Feature",
  "properties": {
    "iso:country":"AU",
    "sg:address":"Factory 38 640 Geelong Rd",
    "sg:city":"Brooklyn",
    "sg:classifiers":[
        {
            "category":"Manufacturing",
            "subcategory":"Metals",
            "type":"Manufacturing & Wholesale Goods"
        }
    ],
    "sg:phone":"+61 3 9314 4121",
    "sg:postcode":"3025",
    "sg:province":"VIC",
    "sg:tags":[
        "polisher"
    ],
    "wof:name":"Stargate Metal Finishing",
    "wof:placetype":"venue"
},
  "geometry": {"coordinates":[144.841431,-37.819237],"type":"Point"}
}