{
  "type": "Feature",
  "properties": {
    "iso:country":"AU",
    "sg:address":"Yeltana Ave",
    "sg:city":"Wattle Park",
    "sg:classifiers":[
        {
            "category":"Education",
            "subcategory":"Kindergarten",
            "type":"Public Place"
        }
    ],
    "sg:phone":"+61 8 8331 3619",
    "sg:postcode":"5066",
    "sg:province":"SA",
    "sg:tags":[
        "pre-schools"
    ],
    "wof:name":"Christopher Rawson Penfold Kindergarten",
    "wof:placetype":"venue"
},
  "geometry": {"coordinates":[138.67547607399999,-34.9250144958],"type":"Point"}
}