{
  "type": "Feature",
  "properties": {
    "iso:country":"AU",
    "sg:address":"31 Pinaroo Crs",
    "sg:city":"Bradbury",
    "sg:classifiers":[
        {
            "category":"Education",
            "subcategory":"University",
            "type":"Public Place"
        }
    ],
    "sg:phone":"+61 2 4620 8068",
    "sg:postcode":"2560",
    "sg:province":"NSW",
    "sg:tags":[
        "educational",
        "organisation",
        "cultural"
    ],
    "wof:name":"Macarthur Communicators",
    "wof:placetype":"venue"
},
  "geometry": {"coordinates":[150.81245422399999,-34.084148407],"type":"Point"}
}