{
  "type": "Feature",
  "properties": {
    "addr:full":"155 Kingston Rd Woodridge QLD 4114",
    "addr:housenumber":"155",
    "addr:postcode":"4114",
    "addr:street":"Kingston Rd",
    "iso:country":"AU",
    "sg:address":"155 Kingston Rd",
    "sg:city":"Woodridge",
    "sg:classifiers":[
        {
            "category":"Autos & Motor Vehicles",
            "subcategory":"Automobile Sales",
            "type":"Retail Goods"
        }
    ],
    "sg:phone":"+61 7 3208 7866",
    "sg:postcode":"4114",
    "sg:province":"QLD",
    "sg:tags":[
        "car",
        "used"
    ],
    "wof:name":"Logan City Motors Pty Ltd",
    "wof:placetype":"venue"
},
  "geometry": {"coordinates":[153.11601257300001,-27.6235733032],"type":"Point"}
}