{
  "type": "Feature",
  "properties": {
    "addr:full":"21 Pitt St Mortdale NSW 2223",
    "addr:housenumber":"21",
    "addr:postcode":"2223",
    "addr:street":"Pitt St",
    "iso:country":"AU",
    "sg:address":"21 Pitt St",
    "sg:city":"Mortdale",
    "sg:classifiers":[
        {
            "category":"Food & Beverages",
            "subcategory":"Supermarket",
            "type":"Retail Goods"
        }
    ],
    "sg:phone":"+61 2 9586 2297",
    "sg:postcode":"2223",
    "sg:province":"NSW",
    "sg:tags":[
        "grocery",
        "store"
    ],
    "wof:name":"Mortdale Trading",
    "wof:placetype":"venue"
},
  "geometry": {"coordinates":[151.07957458499999,-33.9720001221],"type":"Point"}
}