{
  "type": "Feature",
  "properties": {
    "addr:full":"291- 293 Brighton Rd Somerton Park SA 5044",
    "addr:housenumber":"293",
    "addr:postcode":"5044",
    "addr:street":"Brighton Rd",
    "iso:country":"AU",
    "sg:address":"291- 293 Brighton Rd",
    "sg:city":"Somerton Park",
    "sg:classifiers":[
        {
            "category":"Autos & Motor Vehicles",
            "subcategory":"Auto Supplies",
            "type":"Retail Goods"
        }
    ],
    "sg:phone":"+61 8 8298 7177",
    "sg:postcode":"5044",
    "sg:province":"SA",
    "sg:tags":[
        "accessory"
    ],
    "wof:name":"Autopro",
    "wof:placetype":"venue"
},
  "geometry": {"coordinates":[138.52160599999999,-35.001301],"type":"Point"}
}