{
  "type": "Feature",
  "properties": {
    "addr:full":"1/ 21 Broun Ave Bedford WA 6052",
    "addr:housenumber":"/ 21",
    "addr:postcode":"6052",
    "addr:street":"Broun Ave",
    "iso:country":"AU",
    "sg:address":"1/ 21 Broun Ave",
    "sg:city":"Bedford",
    "sg:classifiers":[
        {
            "category":"Personal",
            "subcategory":"Hair Removal",
            "type":"Services"
        }
    ],
    "sg:phone":"+61 8 9272 3223",
    "sg:postcode":"6052",
    "sg:province":"WA",
    "wof:name":"Noras Beauty Studio",
    "wof:placetype":"venue"
},
  "geometry": {"coordinates":[115.89958190900001,-31.9087181091],"type":"Point"}
}