{
  "type": "Feature",
  "properties": {
    "addr:full":"9 Derringer St Cannon Hill QLD 4170",
    "addr:housenumber":"9",
    "addr:postcode":"4170",
    "addr:street":"Derringer St",
    "iso:country":"AU",
    "sg:address":"9 Derringer St",
    "sg:city":"Cannon Hill",
    "sg:classifiers":[
        {
            "category":"Shopping",
            "subcategory":"Computers & Home Electronics",
            "type":"Retail Goods"
        }
    ],
    "sg:phone":"+61 7 3395 6266",
    "sg:postcode":"4170",
    "sg:province":"QLD",
    "sg:tags":[
        "equipment",
        "multimedia"
    ],
    "wof:name":"Media Odyssey Pty Ltd",
    "wof:placetype":"venue"
},
  "geometry": {"coordinates":[153.08265685999999,-27.4668579102],"type":"Point"}
}