{
  "type": "Feature",
  "properties": {
    "addr:full":"No. 7 Hank St Heatherbrae NSW 2324",
    "addr:postcode":"2324",
    "addr:street":"Hank St",
    "iso:country":"AU",
    "sg:address":"No. 7 Hank St",
    "sg:city":"Heatherbrae",
    "sg:classifiers":[
        {
            "category":"Home & Garden",
            "subcategory":"Building Materials",
            "type":"Retail Goods"
        }
    ],
    "sg:phone":"+61 2 4987 2637",
    "sg:postcode":"2324",
    "sg:province":"NSW",
    "sg:tags":[
        "supply"
    ],
    "wof:name":"Terrace Timber Trusses Pty Ltd",
    "wof:placetype":"venue"
},
  "geometry": {"coordinates":[151.72711181599999,-32.7916221619],"type":"Point"}
}