{
  "type": "Feature",
  "properties": {
    "addr:full":"6 Kings Rd New Lambton NSW 2305",
    "addr:housenumber":"6",
    "addr:postcode":"2305",
    "addr:street":"Kings Rd",
    "iso:country":"AU",
    "sg:address":"6 Kings Rd",
    "sg:city":"New Lambton",
    "sg:classifiers":[
        {
            "category":"Wholesale",
            "subcategory":"Metals & Minerals",
            "type":"Manufacturing & Wholesale Goods"
        }
    ],
    "sg:phone":"+61 2 4965 5610",
    "sg:postcode":"2305",
    "sg:province":"NSW",
    "sg:tags":[
        "steel",
        "merchant"
    ],
    "wof:name":"Onesteel Trading",
    "wof:placetype":"venue"
},
  "geometry": {"coordinates":[151.723434,-32.924782],"type":"Point"}
}