{
  "type": "Feature",
  "properties": {
    "addr:full":"5 Fabriano Pl Narre Warren South VIC 3805",
    "addr:postcode":"3805",
    "addr:street":"Pl",
    "iso:country":"AU",
    "sg:address":"5 Fabriano Pl",
    "sg:city":"Narre Warren South",
    "sg:classifiers":[
        {
            "category":"Building & Trades",
            "subcategory":"Cleaning & Sanitation",
            "type":"Services"
        }
    ],
    "sg:phone":"+61 3 9704 0908",
    "sg:postcode":"3805",
    "sg:province":"VIC",
    "sg:tags":[
        "wall",
        "brick"
    ],
    "wof:name":"John Teeuws Brick Cleaning",
    "wof:placetype":"venue"
},
  "geometry": {"coordinates":[145.31968699999999,-38.05711],"type":"Point"}
}