{
  "type": "Feature",
  "properties": {
    "addr:full":"74 William St Beverley SA 5009",
    "addr:housenumber":"74",
    "addr:postcode":"5009",
    "addr:street":"William St",
    "iso:country":"AU",
    "sg:address":"74 William St",
    "sg:city":"Beverley",
    "sg:classifiers":[
        {
            "category":"Manufacturing",
            "subcategory":"Rubber & Plastics",
            "type":"Manufacturing & Wholesale Goods"
        }
    ],
    "sg:phone":"+61 8 8268 9020",
    "sg:postcode":"5009",
    "sg:province":"SA",
    "sg:tags":[
        "wholesaler",
        "product",
        "mfrs"
    ],
    "wof:name":"S.A. Industrial Linings",
    "wof:placetype":"venue"
},
  "geometry": {"coordinates":[138.54728698700001,-34.9000778198],"type":"Point"}
}