{
  "type": "Feature",
  "properties": {
    "addr:full":"15 Foden Ave Somerton VIC 3062",
    "addr:housenumber":"15",
    "addr:postcode":"3062",
    "addr:street":"Foden Ave",
    "iso:country":"AU",
    "sg:address":"15 Foden Ave",
    "sg:city":"Somerton",
    "sg:classifiers":[
        {
            "category":"Autos & Motor Vehicles",
            "subcategory":"Boat Sales",
            "type":"Retail Goods"
        }
    ],
    "sg:phone":"+61 3 9308 0922",
    "sg:postcode":"3062",
    "sg:province":"VIC",
    "sg:tags":[
        "equipment",
        "yacht"
    ],
    "wof:name":"Rolco Marine Engines & Conversions",
    "wof:placetype":"venue"
},
  "geometry": {"coordinates":[144.94338989299999,-37.648349762],"type":"Point"}
}