{
  "type": "Feature",
  "properties": {
    "addr:full":"163 Hyde St Yarraville VIC 3013",
    "addr:housenumber":"163",
    "addr:postcode":"3013",
    "addr:street":"Hyde St",
    "iso:country":"AU",
    "sg:address":"163 Hyde St",
    "sg:city":"Yarraville",
    "sg:classifiers":[
        {
            "category":"Professional",
            "type":"Services"
        }
    ],
    "sg:phone":"+61 3 9687 4488",
    "sg:postcode":"3013",
    "sg:province":"VIC",
    "sg:tags":[
        "auctioneer"
    ],
    "sg:website":"http://www.egans.com.au",
    "wof:name":"Egans Asset Management Pty Ltd",
    "wof:placetype":"venue"
},
  "geometry": {"coordinates":[144.89717102,-37.8153953552],"type":"Point"}
}