{
  "type": "Feature",
  "properties": {
    "iso:country":"AU",
    "sg:address":"254 Kent St",
    "sg:city":"Maryborough",
    "sg:classifiers":[
        {
            "category":"Health Services",
            "subcategory":"Doctor",
            "type":"Services"
        }
    ],
    "sg:phone":"+61 7 4122 1688",
    "sg:postcode":"4650",
    "sg:province":"QLD",
    "sg:tags":[
        "medical",
        "practitioner"
    ],
    "wof:name":"Anderson P E",
    "wof:placetype":"venue"
},
  "geometry": {"coordinates":[152.69856300000001,-25.535048],"type":"Point"}
}