{
  "type": "Feature",
  "properties": {
    "addr:full":"Factory 3, 51 Industrial Ave Hoppers Crossing VIC 3029",
    "addr:housenumber":"51",
    "addr:postcode":"3029",
    "addr:street":"Industrial Ave",
    "iso:country":"AU",
    "sg:address":"Factory 3, 51 Industrial Ave",
    "sg:city":"Hoppers Crossing",
    "sg:classifiers":[
        {
            "category":"Retail",
            "subcategory":"Auto Repair",
            "type":"Services"
        }
    ],
    "sg:phone":"+61 3 9369 5511",
    "sg:postcode":"3029",
    "sg:province":"VIC",
    "sg:tags":[
        "testing",
        "inspection",
        "motor",
        "vehicle"
    ],
    "wof:name":"Defina Automotive Services",
    "wof:placetype":"venue"
},
  "geometry": {"coordinates":[144.731888,-37.867416],"type":"Point"}
}