{
  "type": "Feature",
  "properties": {
    "iso:country":"AU",
    "sg:address":"152 Centaur St",
    "sg:city":"Revesby Heights",
    "sg:classifiers":[
        {
            "category":"Health Services",
            "subcategory":"Doctor",
            "type":"Services"
        }
    ],
    "sg:phone":"+61 2 9773 4878",
    "sg:postcode":"2212",
    "sg:province":"NSW",
    "sg:tags":[
        "medical",
        "practitioner"
    ],
    "wof:name":"Ong Thomas C.M. Dr",
    "wof:placetype":"venue"
},
  "geometry": {"coordinates":[151.018433,-33.965878],"type":"Point"}
}