{
  "type": "Feature",
  "properties": {
    "addr:full":"80 Chandos St St Leonards NSW 2065",
    "addr:housenumber":"80",
    "addr:postcode":"2065",
    "addr:street":"Chandos St",
    "iso:country":"AU",
    "sg:address":"80 Chandos St St",
    "sg:city":"Leonards",
    "sg:classifiers":[
        {
            "category":"Professional",
            "subcategory":"Business Services",
            "type":"Services"
        }
    ],
    "sg:phone":"+61 2 9436 0131",
    "sg:postcode":"2065",
    "sg:province":"NSW",
    "sg:tags":[
        "record",
        "management",
        "storage"
    ],
    "wof:name":"Doctrine Corporation Pty Ltd",
    "wof:placetype":"venue"
},
  "geometry": {"coordinates":[151.19923400900001,-33.8218917847],"type":"Point"}
}