{
  "type": "Feature",
  "properties": {
    "addr:full":"Guernsey St Scone NSW 2337",
    "addr:postcode":"2337",
    "addr:street":"Guernsey St",
    "iso:country":"AU",
    "sg:address":"Guernsey St",
    "sg:city":"Scone",
    "sg:classifiers":[
        {
            "category":"Home & Garden",
            "subcategory":"Building Materials",
            "type":"Retail Goods"
        }
    ],
    "sg:phone":"+61 2 6545 2511",
    "sg:postcode":"2337",
    "sg:province":"NSW",
    "sg:tags":[
        "supply"
    ],
    "wof:name":"Gould Brothers & Co Pty Ltd",
    "wof:placetype":"venue"
},
  "geometry": {"coordinates":[150.865966797,-32.0457611084],"type":"Point"}
}