{
  "type": "Feature",
  "properties": {
    "addr:full":"50 Michael St Bulimba QLD 4171",
    "addr:housenumber":"50",
    "addr:postcode":"4171",
    "addr:street":"Michael St",
    "iso:country":"AU",
    "sg:address":"50 Michael St",
    "sg:city":"Bulimba",
    "sg:classifiers":[
        {
            "category":"Manufacturing",
            "subcategory":"Motor Vehicles & Parts",
            "type":"Manufacturing & Wholesale Goods"
        }
    ],
    "sg:phone":"+61 7 3395 6811",
    "sg:postcode":"4171",
    "sg:province":"QLD",
    "sg:tags":[
        "replacement"
    ],
    "wof:name":"Agra Sales",
    "wof:placetype":"venue"
},
  "geometry": {"coordinates":[153.068649292,-27.4490680695],"type":"Point"}
}