{
  "type": "Feature",
  "properties": {
    "iso:country":"AU",
    "sg:address":"Level 2 Suite 201/22 Belgrave St",
    "sg:city":"Kogarah",
    "sg:classifiers":[
        {
            "category":"Health Services",
            "subcategory":"Health Practitioner",
            "type":"Services"
        }
    ],
    "sg:phone":"+61 2 9588 3211",
    "sg:postcode":"2217",
    "sg:province":"NSW",
    "sg:tags":[
        "dietitian"
    ],
    "wof:name":"Geraldine Georgeou Dietitian",
    "wof:placetype":"venue"
},
  "geometry": {"coordinates":[151.13398699999999,-33.965218],"type":"Point"}
}