{
  "type": "Feature",
  "properties": {
    "iso:country":"AU",
    "sg:address":"3 Zariba Crt",
    "sg:city":"Surrey Downs",
    "sg:classifiers":[
        {
            "category":"Farming",
            "subcategory":"Farm & Veterinary Services",
            "type":"Manufacturing & Wholesale Goods"
        }
    ],
    "sg:phone":"+61 8 8251 1711",
    "sg:postcode":"5126",
    "sg:province":"SA",
    "sg:tags":[
        "irrigation",
        "reticulation",
        "system"
    ],
    "wof:name":"Hawkes International Trading Pty Ltd",
    "wof:placetype":"venue"
},
  "geometry": {"coordinates":[138.7134552,-34.8043632507],"type":"Point"}
}