{
  "type": "Feature",
  "properties": {
    "iso:country":"AU",
    "sg:address":"12 Salecich Pl",
    "sg:city":"Bonnyrigg",
    "sg:classifiers":[
        {
            "category":"Retail",
            "subcategory":"Driving School",
            "type":"Services"
        }
    ],
    "sg:phone":"+61 2 9753 3783",
    "sg:postcode":"2177",
    "sg:province":"NSW",
    "wof:name":"Maria Driving School",
    "wof:placetype":"venue"
},
  "geometry": {"coordinates":[150.90017700199999,-33.8933143616],"type":"Point"}
}