{
  "type": "Feature",
  "properties": {
    "iso:country":"AU",
    "sg:address":"1 Main St",
    "sg:city":"Narre Warren",
    "sg:classifiers":[
        {
            "category":"Home & Garden",
            "subcategory":"Household Appliances",
            "type":"Retail Goods"
        }
    ],
    "sg:phone":"+61 438 277 133",
    "sg:postcode":"3805",
    "sg:province":"VIC",
    "sg:tags":[
        "heating",
        "system"
    ],
    "wof:name":"Hamiltons Hydronic Heating & Air Conditioning",
    "wof:placetype":"venue"
},
  "geometry": {"coordinates":[145.305588,-38.02042],"type":"Point"}
}