{
  "type": "Feature",
  "properties": {
    "addr:full":"1099 Glenhuntly Rd Glen Huntly VIC 3163",
    "addr:housenumber":"1099",
    "addr:postcode":"3163",
    "addr:street":"Glenhuntly Rd",
    "iso:country":"AU",
    "sg:address":"1099 Glenhuntly Rd",
    "sg:city":"Glen Huntly",
    "sg:classifiers":[
        {
            "category":"Personal",
            "subcategory":"Beauty Salon",
            "type":"Services"
        }
    ],
    "sg:phone":"+61 3 9572 3474",
    "sg:postcode":"3163",
    "sg:province":"VIC",
    "sg:tags":[
        "hairdresser"
    ],
    "wof:name":"Caribbean Queen Hair Design",
    "wof:placetype":"venue"
},
  "geometry": {"coordinates":[145.039916992,-37.888999939],"type":"Point"}
}