{
  "type": "Feature",
  "properties": {
    "addr:full":"146 Mort St Toowoomba QLD 4350",
    "addr:housenumber":"146",
    "addr:postcode":"4350",
    "addr:street":"Mort St",
    "iso:country":"AU",
    "sg:address":"146 Mort St",
    "sg:city":"Toowoomba",
    "sg:classifiers":[
        {
            "category":"Professional",
            "subcategory":"Accounting & Tax Preparation",
            "type":"Services"
        }
    ],
    "sg:phone":"+61 7 4638 2866",
    "sg:postcode":"4350",
    "sg:province":"QLD",
    "sg:tags":[
        "accountant",
        "auditor"
    ],
    "wof:name":"Trevarthen J",
    "wof:placetype":"venue"
},
  "geometry": {"coordinates":[151.94941700000001,-27.557791],"type":"Point"}
}