{
  "type": "Feature",
  "properties": {
    "addr:full":"18 Bayldon Drv Raleigh Industrial Est Urunga NSW 2455",
    "addr:housenumber":"18",
    "addr:postcode":"2455",
    "addr:street":"Bayldon Drv;Industrial",
    "iso:country":"AU",
    "sg:address":"18 Bayldon Drv",
    "sg:city":"Raleigh Industrial Est Urunga",
    "sg:classifiers":[
        {
            "category":"Autos & Motor Vehicles",
            "subcategory":"Boat Sales",
            "type":"Retail Goods"
        }
    ],
    "sg:phone":"+61 2 6655 5566",
    "sg:postcode":"2455",
    "sg:province":"NSW",
    "sg:tags":[
        "builder",
        "yacht",
        "repairer"
    ],
    "wof:name":"Dart Metal Works",
    "wof:placetype":"venue"
},
  "geometry": {"coordinates":[153.01637299999999,-30.492731],"type":"Point"}
}