{
  "type": "Feature",
  "properties": {
    "addr:full":"20 Wasley St Kalgoorlie WA 6430",
    "addr:housenumber":"20",
    "addr:postcode":"6430",
    "addr:street":"Wasley St",
    "iso:country":"AU",
    "sg:address":"20 Wasley St",
    "sg:city":"Kalgoorlie",
    "sg:classifiers":[
        {
            "category":"Utilities",
            "subcategory":"Electric",
            "type":"Services"
        }
    ],
    "sg:phone":"+61 417 300 299",
    "sg:postcode":"6430",
    "sg:province":"WA",
    "sg:tags":[
        "electrical",
        "contractor"
    ],
    "wof:name":"Deeble Electrical",
    "wof:placetype":"venue"
},
  "geometry": {"coordinates":[121.452041626,-30.7756118774],"type":"Point"}
}