{
  "type": "Feature",
  "properties": {
    "addr:full":"2b/ 21 Castray Esp Battery Point TAS 7004",
    "addr:housenumber":"2b / 21",
    "addr:postcode":"7004",
    "iso:country":"AU",
    "sg:address":"2b/ 21",
    "sg:city":"Castray Esp Battery Point",
    "sg:classifiers":[
        {
            "category":"Shopping",
            "subcategory":"Beauty & Cosmetics",
            "type":"Retail Goods"
        }
    ],
    "sg:phone":"+61 3 6224 1069",
    "sg:postcode":"7004",
    "sg:province":"TAS",
    "sg:tags":[
        "equipment",
        "salon",
        "supply"
    ],
    "wof:name":"Affinity Creations",
    "wof:placetype":"venue"
},
  "geometry": {"coordinates":[147.336029053,-42.8892097473],"type":"Point"}
}