{
  "type": "Feature",
  "properties": {
    "iso:country":"AU",
    "sg:address":"24 Lillas Pl",
    "sg:city":"Minto",
    "sg:classifiers":[
        {
            "category":"Manufacturing",
            "subcategory":"Tools & Machinery",
            "type":"Manufacturing & Wholesale Goods"
        }
    ],
    "sg:phone":"+61 2 9820 1940",
    "sg:postcode":"2566",
    "sg:province":"NSW",
    "sg:tags":[
        "equipment",
        "scale",
        "weighing"
    ],
    "wof:name":"Add-Weigh Australia",
    "wof:placetype":"venue"
},
  "geometry": {"coordinates":[150.853805542,-34.0237236023],"type":"Point"}
}