{
  "type": "Feature",
  "properties": {
    "iso:country":"AU",
    "sg:address":"1388 Tasman Hwy",
    "sg:city":"Cambridge",
    "sg:classifiers":[
        {
            "category":"Farming",
            "subcategory":"Fish & Marine Products",
            "type":"Manufacturing & Wholesale Goods"
        }
    ],
    "sg:phone":"+61 3 6248 5458",
    "sg:postcode":"7170",
    "sg:province":"TAS",
    "sg:tags":[
        "supplier",
        "oyster",
        "farmer"
    ],
    "wof:name":"Barilla Bay Seafoods",
    "wof:placetype":"venue"
},
  "geometry": {"coordinates":[147.499923706,-42.824054718],"type":"Point"}
}