{
  "type": "Feature",
  "properties": {
    "addr:full":"Warringah Mall Old Pittwater Rd Brookvale NSW 2100",
    "addr:postcode":"2100",
    "addr:street":"Old Pittwater Rd",
    "iso:country":"AU",
    "sg:address":"Warringah Mall Old Pittwater Rd",
    "sg:city":"Brookvale",
    "sg:classifiers":[
        {
            "category":"Food & Beverages",
            "subcategory":"Supermarket",
            "type":"Retail Goods"
        }
    ],
    "sg:phone":"+61 2 9939 6518",
    "sg:postcode":"2100",
    "sg:province":"NSW",
    "sg:tags":[
        "grocery",
        "store"
    ],
    "wof:name":"Franklins Limited",
    "wof:placetype":"venue"
},
  "geometry": {"coordinates":[151.27171325699999,-33.7619056702],"type":"Point"}
}