{
  "type": "Feature",
  "properties": {
    "addr:full":"1/ 1 Lucky La Billinudgel NSW 2483",
    "addr:housenumber":"/ 1",
    "addr:postcode":"2483",
    "addr:street":"Lucky La Billinudgel",
    "iso:country":"AU",
    "sg:address":"1/ 1 Lucky La",
    "sg:city":"Billinudgel",
    "sg:classifiers":[
        {
            "category":"Retail",
            "subcategory":"Auto Repair",
            "type":"Services"
        }
    ],
    "sg:phone":"+61 2 6680 3669",
    "sg:postcode":"2483",
    "sg:province":"NSW",
    "sg:tags":[
        "electrical"
    ],
    "wof:name":"Billinudgel Auto Electrical Service",
    "wof:placetype":"venue"
},
  "geometry": {"coordinates":[153.52857971200001,-28.5045719147],"type":"Point"}
}