{
  "type": "Feature",
  "properties": {
    "addr:full":"Simmons St Revesby NSW 2212",
    "addr:postcode":"2212",
    "addr:street":"Simmons St",
    "iso:country":"AU",
    "sg:address":"Simmons St",
    "sg:city":"Revesby",
    "sg:classifiers":[
        {
            "category":"Professional",
            "subcategory":"Detective & Security Services",
            "type":"Services"
        }
    ],
    "sg:phone":"+61 2 9785 0444",
    "sg:postcode":"2212",
    "sg:province":"NSW",
    "sg:tags":[
        "domestic",
        "alarm",
        "commercial",
        "burglar"
    ],
    "wof:name":"Sydney Home Improvements",
    "wof:placetype":"venue"
},
  "geometry": {"coordinates":[151.01565600000001,-33.951637],"type":"Point"}
}