{
  "type": "Feature",
  "properties": {
    "iso:country":"AU",
    "sg:address":"287 Macquarie St",
    "sg:city":"Hobart",
    "sg:classifiers":[
        {
            "category":"Health Services",
            "subcategory":"Health Practitioner",
            "type":"Services"
        }
    ],
    "sg:phone":"+61 3 6223 7352",
    "sg:postcode":"7000",
    "sg:province":"TAS",
    "sg:tags":[
        "psychotherapist"
    ],
    "wof:name":"Lum Geraldine",
    "wof:placetype":"venue"
},
  "geometry": {"coordinates":[147.32081604000001,-42.8898239136],"type":"Point"}
}