{
  "type": "Feature",
  "properties": {
    "iso:country":"AU",
    "sg:address":"9 Burton St",
    "sg:city":"Concord",
    "sg:classifiers":[
        {
            "category":"Professional",
            "subcategory":"Art Services",
            "type":"Services"
        }
    ],
    "sg:phone":"+61 2 9758 5064",
    "sg:postcode":"2137",
    "sg:province":"NSW",
    "sg:tags":[
        "decorator",
        "painter"
    ],
    "wof:name":"Afterglow Painting & Decorating",
    "wof:placetype":"venue"
},
  "geometry": {"coordinates":[151.107254028,-33.8678779602],"type":"Point"}
}