{
  "type": "Feature",
  "properties": {
    "iso:country":"AU",
    "sg:address":"47 Todman Rd",
    "sg:city":"Gingin",
    "sg:classifiers":[
        {
            "category":"Organizations",
            "subcategory":"Professional Association",
            "type":"Services"
        }
    ],
    "sg:phone":"+61 8 9575 3000",
    "sg:postcode":"6503",
    "sg:province":"WA",
    "sg:tags":[
        "rural",
        "organisation",
        "production",
        "primary"
    ],
    "wof:name":"Gingin Expo (Inc)",
    "wof:placetype":"venue"
},
  "geometry": {"coordinates":[115.860924,-31.341272],"type":"Point"}
}