{
  "type": "Feature",
  "properties": {
    "addr:full":"Shop 49 stockland Shopping Cntr Burleigh Heads QLD 4220",
    "addr:housenumber":"shop 49",
    "addr:postcode":"4220",
    "iso:country":"AU",
    "sg:address":"Shop 49",
    "sg:city":"stockland Shopping Cntr Burleigh Heads",
    "sg:classifiers":[
        {
            "category":"Utilities",
            "subcategory":"Telephone",
            "type":"Services"
        }
    ],
    "sg:phone":"+61 1300 737 195",
    "sg:postcode":"4220",
    "sg:province":"QLD",
    "sg:tags":[
        "equipment",
        "system"
    ],
    "wof:name":"Telstra Business Centre",
    "wof:placetype":"venue"
},
  "geometry": {"coordinates":[153.449752808,-28.0879096985],"type":"Point"}
}