{
  "type": "Feature",
  "properties": {
    "addr:full":"Cnr Hutton & Guthrie Sts Osborne Park WA 6017",
    "addr:postcode":"6017",
    "addr:street":"Cnr",
    "iso:country":"AU",
    "sg:address":"Cnr Hutton & Guthrie Sts",
    "sg:city":"Osborne Park",
    "sg:classifiers":[
        {
            "category":"Home & Garden",
            "subcategory":"Building Materials",
            "type":"Retail Goods"
        }
    ],
    "sg:phone":"+61 8 9446 2609",
    "sg:postcode":"6017",
    "sg:province":"WA",
    "sg:tags":[
        "decorative",
        "coating"
    ],
    "wof:name":"Paint West Centre",
    "wof:placetype":"venue"
},
  "geometry": {"coordinates":[115.817733765,-31.9038505554],"type":"Point"}
}