{
  "type": "Feature",
  "properties": {
    "addr:full":"17 Whistler St Manly NSW 2095",
    "addr:housenumber":"17",
    "addr:postcode":"2095",
    "addr:street":"Whistler St",
    "iso:country":"AU",
    "sg:address":"17 Whistler St",
    "sg:city":"Manly",
    "sg:classifiers":[
        {
            "category":"Health Services",
            "subcategory":"Health Practitioner",
            "type":"Services"
        }
    ],
    "sg:phone":"+61 2 9977 1463",
    "sg:postcode":"2095",
    "sg:province":"NSW",
    "sg:tags":[
        "physiotherapist"
    ],
    "wof:name":"Stanley Margaret",
    "wof:placetype":"venue"
},
  "geometry": {"coordinates":[151.28558349599999,-33.7960739136],"type":"Point"}
}