{
  "type": "Feature",
  "properties": {
    "addr:full":"Mid Western Hwy Cowra NSW 2794",
    "addr:postcode":"2794",
    "addr:street":"Mid Western Hwy",
    "iso:country":"AU",
    "sg:address":"Mid Western Hwy",
    "sg:city":"Cowra",
    "sg:classifiers":[
        {
            "category":"Travel",
            "subcategory":"Hotels & Motels",
            "type":"Entertainment"
        }
    ],
    "sg:phone":"+61 2 6342 3133",
    "sg:postcode":"2794",
    "sg:province":"NSW",
    "wof:name":"Alabaster Motel",
    "wof:placetype":"venue"
},
  "geometry": {"coordinates":[148.69056701700001,-33.8345565796],"type":"Point"}
}