{
  "type": "Feature",
  "properties": {
    "iso:country":"AU",
    "sg:address":"The Gums 76 Bathurst St",
    "sg:city":"Condobolin",
    "sg:classifiers":[
        {
            "category":"Farming",
            "subcategory":"Farm & Veterinary Services",
            "type":"Manufacturing & Wholesale Goods"
        }
    ],
    "sg:phone":"+61 428 952 077",
    "sg:postcode":"2877",
    "sg:province":"NSW",
    "sg:tags":[
        "contracting"
    ],
    "wof:name":"Cary L&#039;Estrange",
    "wof:placetype":"venue"
},
  "geometry": {"coordinates":[147.14674400000001,-33.088219],"type":"Point"}
}