{
  "type": "Feature",
  "properties": {
    "addr:full":"81 Queen St Berry NSW 2535",
    "addr:housenumber":"81",
    "addr:postcode":"2535",
    "addr:street":"Queen St",
    "iso:country":"AU",
    "sg:address":"81 Queen St",
    "sg:city":"Berry",
    "sg:classifiers":[
        {
            "category":"Personal",
            "subcategory":"Skin Care",
            "type":"Services"
        }
    ],
    "sg:phone":"+61 2 4464 1110",
    "sg:postcode":"2535",
    "sg:province":"NSW",
    "sg:tags":[
        "treatment"
    ],
    "wof:name":"Pure Hair & Beauty",
    "wof:placetype":"venue"
},
  "geometry": {"coordinates":[150.696899414,-34.7747612],"type":"Point"}
}