{
  "type": "Feature",
  "properties": {
    "addr:full":"291 Eastwood Rd Wy Yung VIC 3875",
    "addr:housenumber":"291",
    "addr:postcode":"3875",
    "addr:street":"Eastwood Rd",
    "iso:country":"AU",
    "sg:address":"291 Eastwood Rd",
    "sg:city":"Wy Yung",
    "sg:classifiers":[
        {
            "category":"Health Services",
            "subcategory":"Health Practitioner",
            "type":"Services"
        }
    ],
    "sg:phone":"+61 3 5152 3829",
    "sg:postcode":"3875",
    "sg:province":"VIC",
    "sg:tags":[
        "naturopath"
    ],
    "wof:name":"Paterson Judy",
    "wof:placetype":"venue"
},
  "geometry": {"coordinates":[147.63006591800001,-37.7993927002],"type":"Point"}
}