{
  "type": "Feature",
  "properties": {
    "iso:country":"AU",
    "sg:address":"Cnr Williams & Toowoomba Rds",
    "sg:city":"Crows Nest",
    "sg:classifiers":[
        {
            "category":"Food & Beverages",
            "subcategory":"Liquor & Beverages",
            "type":"Retail Goods"
        }
    ],
    "sg:phone":"+61 7 4698 1108",
    "sg:postcode":"4355",
    "sg:province":"QLD",
    "sg:tags":[
        "store"
    ],
    "wof:name":"Liquor Legends",
    "wof:placetype":"venue"
},
  "geometry": {"coordinates":[152.055008,-27.261465],"type":"Point"}
}