{
  "type": "Feature",
  "properties": {
    "iso:country":"AU",
    "sg:address":"4 Jane St",
    "sg:city":"Randwick",
    "sg:classifiers":[
        {
            "category":"Commercial Area",
            "type":"Public Place"
        }
    ],
    "sg:phone":"+61 407 442 837",
    "sg:postcode":"2031",
    "sg:province":"NSW",
    "sg:tags":[
        "clothing",
        "label"
    ],
    "wof:name":"ASAP Name Tapes",
    "wof:placetype":"venue"
},
  "geometry": {"coordinates":[151.236236572,-33.9212226868],"type":"Point"}
}