{
  "type": "Feature",
  "properties": {
    "addr:full":"Melbourne Central Medical Centre, Lower Ground, 30 Melbourne VIC 3000",
    "addr:housenumber":"30",
    "addr:postcode":"3000",
    "iso:country":"AU",
    "sg:address":"Melbourne Central Medical Centre, Lower Ground, 30",
    "sg:city":"Melbourne",
    "sg:classifiers":[
        {
            "category":"Health Services",
            "subcategory":"Doctor",
            "type":"Services"
        }
    ],
    "sg:phone":"+61 3 9654 5544",
    "sg:postcode":"3000",
    "sg:province":"VIC",
    "sg:tags":[
        "medical",
        "practitioner"
    ],
    "wof:name":"David A Phillips",
    "wof:placetype":"venue"
},
  "geometry": {"coordinates":[144.96340942399999,-37.8118057251],"type":"Point"}
}