{
  "type": "Feature",
  "properties": {
    "addr:full":"Shp7/ 49 Berrigan Drv South Lake WA 6164",
    "addr:housenumber":"49",
    "addr:postcode":"6164",
    "addr:street":"Berrigan Drv",
    "iso:country":"AU",
    "sg:address":"Shp7/ 49 Berrigan Drv",
    "sg:city":"South Lake",
    "sg:classifiers":[
        {
            "category":"Shopping",
            "subcategory":"Bicycles & Sporting Goods",
            "type":"Retail Goods"
        }
    ],
    "sg:phone":"+61 8 9414 8330",
    "sg:postcode":"6164",
    "sg:province":"WA",
    "sg:tags":[
        "chemical",
        "equipment",
        "pool",
        "swimming"
    ],
    "wof:name":"South Lake Pool And Spa",
    "wof:placetype":"venue"
},
  "geometry": {"coordinates":[115.842461,-32.110821],"type":"Point"}
}