{
  "type": "Feature",
  "properties": {
    "iso:country":"AU",
    "sg:address":"15 Bedingfeld Rd",
    "sg:city":"Pinjarra",
    "sg:classifiers":[
        {
            "category":"Utilities",
            "subcategory":"Electric",
            "type":"Services"
        }
    ],
    "sg:phone":"+61 8 9531 1094",
    "sg:postcode":"6208",
    "sg:province":"WA",
    "sg:tags":[
        "electrical",
        "contractor"
    ],
    "wof:name":"Sanders B & M Electrical Contractors",
    "wof:placetype":"venue"
},
  "geometry": {"coordinates":[115.874092,-32.637405],"type":"Point"}
}