{
  "type": "Feature",
  "properties": {
    "addr:full":"Patterson St Bayswater VIC 3153",
    "addr:postcode":"3153",
    "addr:street":"Patterson St",
    "iso:country":"AU",
    "sg:address":"Patterson St",
    "sg:city":"Bayswater",
    "sg:classifiers":[
        {
            "category":"Organizations",
            "subcategory":"Professional Association",
            "type":"Services"
        }
    ],
    "sg:phone":"+61 3 9720 1913",
    "sg:postcode":"3153",
    "sg:province":"VIC",
    "sg:tags":[
        "web",
        "internet"
    ],
    "wof:name":"Interweb Solutions",
    "wof:placetype":"venue"
},
  "geometry": {"coordinates":[145.25140380900001,-37.8523330688],"type":"Point"}
}