{
  "type": "Feature",
  "properties": {
    "addr:full":"24- 28 Browns Plains Rd Browns Plains QLD 4118",
    "addr:housenumber":"28",
    "addr:postcode":"4118",
    "addr:street":"Browns Plains Rd",
    "iso:country":"AU",
    "sg:address":"24- 28 Browns Plains Rd",
    "sg:city":"Browns Plains",
    "sg:classifiers":[
        {
            "category":"Banks & Credit Unions",
            "subcategory":"Bank",
            "type":"Services"
        }
    ],
    "sg:phone":"+61 13 20 32",
    "sg:postcode":"4118",
    "sg:province":"QLD",
    "wof:name":"Westpac",
    "wof:placetype":"venue"
},
  "geometry": {"coordinates":[153.047332764,-27.6620559692],"type":"Point"}
}