{
  "type": "Feature",
  "properties": {
    "addr:full":"L6/ 10 Help St Chatswood NSW 2067",
    "addr:housenumber":"l6 / 10",
    "addr:postcode":"2067",
    "addr:street":"Help St",
    "iso:country":"AU",
    "sg:address":"L6/ 10 Help St",
    "sg:city":"Chatswood",
    "sg:classifiers":[
        {
            "category":"Professional",
            "subcategory":"Business Services",
            "type":"Services"
        }
    ],
    "sg:phone":"+61 2 9410 2544",
    "sg:postcode":"2067",
    "sg:province":"NSW",
    "sg:tags":[
        "broker"
    ],
    "wof:name":"Action Negotiators",
    "wof:placetype":"venue"
},
  "geometry": {"coordinates":[151.18182373100001,-33.7952423096],"type":"Point"}
}