{
  "type": "Feature",
  "properties": {
    "addr:full":"19 Samuel Crs North Rockhampton QLD 4701",
    "addr:housenumber":"19",
    "addr:postcode":"4701",
    "addr:street":"Samuel Crs North",
    "iso:country":"AU",
    "sg:address":"19 Samuel Crs",
    "sg:city":"North Rockhampton",
    "sg:classifiers":[
        {
            "category":"Building & Trades",
            "subcategory":"Construction",
            "type":"Services"
        }
    ],
    "sg:phone":"+61 409 362 101",
    "sg:postcode":"4701",
    "sg:province":"QLD",
    "sg:tags":[
        "installation",
        "air conditioning"
    ],
    "wof:name":"Rocky Refrigeration",
    "wof:placetype":"venue"
},
  "geometry": {"coordinates":[150.54896545400001,-23.3510398865],"type":"Point"}
}