{
  "type": "Feature",
  "properties": {
    "addr:full":"14a Sergeant Rd Melville WA 6156",
    "addr:housenumber":"14a",
    "addr:postcode":"6156",
    "addr:street":"Sergeant Rd",
    "iso:country":"AU",
    "sg:address":"14a Sergeant Rd",
    "sg:city":"Melville",
    "sg:classifiers":[
        {
            "category":"Insurance",
            "subcategory":"Life Insurance",
            "type":"Services"
        }
    ],
    "sg:phone":"+61 8 9330 9550",
    "sg:postcode":"6156",
    "sg:province":"WA",
    "wof:name":"Byrne D K Pty Ltd",
    "wof:placetype":"venue"
},
  "geometry": {"coordinates":[115.79743999999999,-32.046776],"type":"Point"}
}