{
  "type": "Feature",
  "properties": {
    "addr:full":"31 Barwon Park Rd St Peters NSW 2044",
    "addr:housenumber":"31",
    "addr:postcode":"2044",
    "addr:street":"Barwon Park Rd",
    "iso:country":"AU",
    "sg:address":"31 Barwon Park Rd St",
    "sg:city":"Peters",
    "sg:classifiers":[
        {
            "category":"Utilities",
            "type":"Services"
        }
    ],
    "sg:phone":"+61 2 9519 6533",
    "sg:postcode":"2044",
    "sg:province":"NSW",
    "sg:tags":[
        "refrigeration",
        "industrial",
        "commercial",
        "retail"
    ],
    "wof:name":"Matsu Chilling Systems",
    "wof:placetype":"venue"
},
  "geometry": {"coordinates":[151.181061,-33.912224],"type":"Point"}
}