{
  "type": "Feature",
  "properties": {
    "iso:country":"AU",
    "sg:address":"104 Redfern St",
    "sg:city":"Redfern",
    "sg:classifiers":[
        {
            "category":"Shopping",
            "subcategory":"Computers & Home Electronics",
            "type":"Retail Goods"
        }
    ],
    "sg:phone":"+61 2 8399 0479",
    "sg:postcode":"2016",
    "sg:province":"NSW",
    "sg:tags":[
        "equipment",
        "multimedia"
    ],
    "wof:name":"Solo Productions Pty Ltd",
    "wof:placetype":"venue"
},
  "geometry": {"coordinates":[151.20437622099999,-33.8926734924],"type":"Point"}
}