{
  "type": "Feature",
  "properties": {
    "addr:full":"201-207 Epping Rd Eastwood NSW 2122",
    "addr:housenumber":"201-207",
    "addr:postcode":"2122",
    "addr:street":"Epping Rd",
    "iso:country":"AU",
    "sg:address":"201-207 Epping Rd",
    "sg:city":"Eastwood",
    "sg:classifiers":[
        {
            "category":"Social Services",
            "subcategory":"Retirement Home",
            "type":"Services"
        }
    ],
    "sg:phone":"+61 2 9869 8432",
    "sg:postcode":"2122",
    "sg:province":"NSW",
    "sg:tags":[
        "village"
    ],
    "wof:name":"Leisure Lea Gardens",
    "wof:placetype":"venue"
},
  "geometry": {"coordinates":[151.10055542000001,-33.7719230652],"type":"Point"}
}