{
  "type": "Feature",
  "properties": {
    "addr:full":"612 Warringah Rd Forestville NSW 2087",
    "addr:housenumber":"612",
    "addr:postcode":"2087",
    "addr:street":"Warringah Rd",
    "iso:country":"AU",
    "sg:address":"612 Warringah Rd",
    "sg:city":"Forestville",
    "sg:classifiers":[
        {
            "category":"Retail",
            "subcategory":"Veterinary Services",
            "type":"Services"
        }
    ],
    "sg:phone":"+61 2 9452 2933",
    "sg:postcode":"2087",
    "sg:province":"NSW",
    "sg:tags":[
        "surgeon"
    ],
    "wof:name":"Emergency Veterinary Service Northside",
    "wof:placetype":"venue"
},
  "geometry": {"coordinates":[151.21678161599999,-33.7606086731],"type":"Point"}
}