{
  "type": "Feature",
  "properties": {
    "iso:country":"AU",
    "sg:address":"11 River Rd",
    "sg:city":"Bayswater",
    "sg:classifiers":[
        {
            "category":"Real Estate",
            "subcategory":"Real Estate Agent",
            "type":"Services"
        }
    ],
    "sg:phone":"+61 8 9279 8822",
    "sg:postcode":"6053",
    "sg:province":"WA",
    "sg:tags":[
        "handyman's",
        "equipment",
        "hire",
        "builders",
        "contractor"
    ],
    "wof:name":"Bayswater DIY hire",
    "wof:placetype":"venue"
},
  "geometry": {"coordinates":[115.92894744900001,-31.9216041565],"type":"Point"}
}