{
  "type": "Feature",
  "properties": {
    "iso:country":"AU",
    "sg:address":"44 Ferry St",
    "sg:city":"Kangaroo Point",
    "sg:classifiers":[
        {
            "category":"Retail",
            "subcategory":"Event Space",
            "type":"Services"
        }
    ],
    "sg:phone":"+61 7 3217 3646",
    "sg:postcode":"4169",
    "sg:province":"QLD",
    "sg:tags":[
        "venue",
        "reception",
        "wedding"
    ],
    "sg:website":"http://www.snugharbour.com.au",
    "wof:name":"Snug Harbour",
    "wof:placetype":"venue"
},
  "geometry": {"coordinates":[153.036987305,-27.471698761],"type":"Point"}
}