{
  "type": "Feature",
  "properties": {
    "iso:country":"AU",
    "sg:address":"216 Spurway St",
    "sg:city":"Dundas",
    "sg:classifiers":[
        {
            "category":"Health Services",
            "subcategory":"Health Practitioner",
            "type":"Services"
        }
    ],
    "sg:phone":"+61 417 676 083",
    "sg:postcode":"2117",
    "sg:province":"NSW",
    "sg:tags":[
        "acupuncture"
    ],
    "wof:name":"Patrick Wong",
    "wof:placetype":"venue"
},
  "geometry": {"coordinates":[151.05235290499999,-33.8004951477],"type":"Point"}
}