{
  "type": "Feature",
  "properties": {
    "addr:full":"5 Bronte Ave Burwood VIC 3125",
    "addr:housenumber":"5",
    "addr:postcode":"3125",
    "addr:street":"Bronte Ave",
    "iso:country":"AU",
    "sg:address":"5 Bronte Ave",
    "sg:city":"Burwood",
    "sg:classifiers":[
        {
            "category":"Personal",
            "type":"Services"
        }
    ],
    "sg:phone":"+61 3 9808 5500",
    "sg:postcode":"3125",
    "sg:province":"VIC",
    "sg:tags":[
        "career",
        "counselling"
    ],
    "wof:name":"Career Action Centre",
    "wof:placetype":"venue"
},
  "geometry": {"coordinates":[145.121170044,-37.8474006653],"type":"Point"}
}