{
  "type": "Feature",
  "properties": {
    "addr:full":"17 Station St Eungai Rail NSW 2441",
    "addr:housenumber":"17",
    "addr:postcode":"2441",
    "addr:street":"Station St Eungai",
    "iso:country":"AU",
    "sg:address":"17 Station St",
    "sg:city":"Eungai Rail",
    "sg:classifiers":[
        {
            "category":"Manufacturing",
            "subcategory":"Glass & Minerals",
            "type":"Manufacturing & Wholesale Goods"
        }
    ],
    "sg:phone":"+61 2 6569 9049",
    "sg:postcode":"2441",
    "sg:province":"NSW",
    "sg:tags":[
        "repair",
        "fibreglass",
        "product"
    ],
    "wof:name":"Thompson C J & N J",
    "wof:placetype":"venue"
},
  "geometry": {"coordinates":[152.901184,-30.848909],"type":"Point"}
}