{
  "type": "Feature",
  "properties": {
    "addr:full":"Village Store 62 Metung Rd Metung VIC 3904",
    "addr:housenumber":"62",
    "addr:postcode":"3904",
    "addr:street":"Metung Rd",
    "iso:country":"AU",
    "sg:address":"Village Store 62 Metung Rd",
    "sg:city":"Metung",
    "sg:classifiers":[
        {
            "category":"Food & Beverages",
            "subcategory":"Liquor & Beverages",
            "type":"Retail Goods"
        }
    ],
    "sg:phone":"+61 3 5156 2201",
    "sg:postcode":"3904",
    "sg:province":"VIC",
    "sg:tags":[
        "store"
    ],
    "wof:name":"Cheeers",
    "wof:placetype":"venue"
},
  "geometry": {"coordinates":[147.853805542,-37.8920822144],"type":"Point"}
}