{
  "type": "Feature",
  "properties": {
    "addr:full":"Unit 3 52 Weld St Nedlands WA 6009",
    "addr:housenumber":"52",
    "addr:postcode":"6009",
    "addr:street":"Weld St",
    "iso:country":"AU",
    "sg:address":"Unit 3 52 Weld St",
    "sg:city":"Nedlands",
    "sg:classifiers":[
        {
            "category":"Professional",
            "subcategory":"Engineering",
            "type":"Services"
        }
    ],
    "sg:phone":"+61 8 9386 3066",
    "sg:postcode":"6009",
    "sg:province":"WA",
    "sg:tags":[
        "consulting",
        "engineer"
    ],
    "wof:name":"Renwick B G (WA) Pty Ltd",
    "wof:placetype":"venue"
},
  "geometry": {"coordinates":[115.79740099999999,-31.980047],"type":"Point"}
}