{
  "type": "Feature",
  "properties": {
    "addr:full":"Shop 15 Boomerang Pl Seven Hills NSW 2147",
    "addr:housenumber":"shop 15",
    "addr:postcode":"2147",
    "addr:street":"Boomerang Pl",
    "iso:country":"AU",
    "sg:address":"Shop 15 Boomerang Pl",
    "sg:city":"Seven Hills",
    "sg:classifiers":[
        {
            "category":"Building & Trades",
            "subcategory":"Equipment Rental",
            "type":"Services"
        }
    ],
    "sg:phone":"+61 2 9622 5155",
    "sg:postcode":"2147",
    "sg:province":"NSW",
    "sg:tags":[
        "party",
        "hire"
    ],
    "wof:name":"Ashta Event Decorators Planners & Hirers",
    "wof:placetype":"venue"
},
  "geometry": {"coordinates":[150.936737061,-33.7753829956],"type":"Point"}
}