{
  "type": "Feature",
  "properties": {
    "addr:full":"PO Box 599 Stepney SA 5069",
    "addr:postcode":"5069",
    "iso:country":"AU",
    "sg:address":"PO Box 599",
    "sg:city":"Stepney",
    "sg:classifiers":[
        {
            "category":"Professional",
            "subcategory":"Research",
            "type":"Services"
        }
    ],
    "sg:phone":"+61 8 8463 1881",
    "sg:postcode":"5069",
    "sg:province":"SA",
    "sg:tags":[
        "market"
    ],
    "wof:name":"Needle In A Haystack",
    "wof:placetype":"venue"
},
  "geometry": {"coordinates":[138.626785278,-34.9107894897],"type":"Point"}
}