{
  "type": "Feature",
  "properties": {
    "addr:full":"23 Anderson St Yarraville VIC 3013",
    "addr:housenumber":"23",
    "addr:postcode":"3013",
    "addr:street":"Anderson St",
    "iso:country":"AU",
    "sg:address":"23 Anderson St",
    "sg:city":"Yarraville",
    "sg:classifiers":[
        {
            "category":"Fast Food",
            "type":"Food & Drink"
        }
    ],
    "sg:phone":"+61 3 9687 7362",
    "sg:postcode":"3013",
    "sg:province":"VIC",
    "sg:tags":[
        "away",
        "take"
    ],
    "wof:name":"Yarraville Pizza & Take Away",
    "wof:placetype":"venue"
},
  "geometry": {"coordinates":[144.89134216299999,-37.8168373108],"type":"Point"}
}