{
  "type": "Feature",
  "properties": {
    "addr:full":"184 Cormack Rd Wingfield SA 5013",
    "addr:housenumber":"184",
    "addr:postcode":"5013",
    "addr:street":"Cormack Rd",
    "iso:country":"AU",
    "sg:address":"184 Cormack Rd",
    "sg:city":"Wingfield",
    "sg:classifiers":[
        {
            "category":"Wholesale",
            "subcategory":"Hardware",
            "type":"Manufacturing & Wholesale Goods"
        }
    ],
    "sg:phone":"+61 8 8243 9100",
    "sg:postcode":"5013",
    "sg:province":"SA",
    "wof:name":"Advansa Pty Ltd",
    "wof:placetype":"venue"
},
  "geometry": {"coordinates":[138.56529235799999,-34.84034729],"type":"Point"}
}