{
  "type": "Feature",
  "properties": {
    "iso:country":"AU",
    "sg:address":"Lvl 14 / 124 Walker St",
    "sg:city":"North Sydney",
    "sg:classifiers":[
        {
            "category":"Building & Trades",
            "subcategory":"Construction",
            "type":"Services"
        }
    ],
    "sg:phone":"+61 1300 765 762",
    "sg:postcode":"2059",
    "sg:province":"NSW",
    "sg:tags":[
        "contractor"
    ],
    "wof:name":"Epic Construction",
    "wof:placetype":"venue"
},
  "geometry": {"coordinates":[151.209015,-33.837303],"type":"Point"}
}