{
  "type": "Feature",
  "properties": {
    "iso:country":"AU",
    "sg:address":"371 Kent St",
    "sg:city":"Maryborough",
    "sg:classifiers":[
        {
            "category":"Real Estate",
            "subcategory":"Real Estate Agent",
            "type":"Services"
        }
    ],
    "sg:phone":"+61 7 4122 3533",
    "sg:postcode":"4650",
    "sg:province":"QLD",
    "wof:name":"L J Hooker",
    "wof:placetype":"venue"
},
  "geometry": {"coordinates":[152.699265,-25.535542],"type":"Point"}
}