{
  "type": "Feature",
  "properties": {
    "iso:country":"AU",
    "sg:address":"12/ 21",
    "sg:city":"Eugene Tce Ringwood",
    "sg:classifiers":[
        {
            "category":"Wholesale",
            "subcategory":"Machinery & Supplies",
            "type":"Manufacturing & Wholesale Goods"
        }
    ],
    "sg:phone":"+61 3 9879 6699",
    "sg:postcode":"3134",
    "sg:province":"VIC",
    "sg:tags":[
        "instrument"
    ],
    "wof:name":"Hydraulic Trade Services",
    "wof:placetype":"venue"
},
  "geometry": {"coordinates":[145.21890258799999,-37.8254547119],"type":"Point"}
}