{
  "type": "Feature",
  "properties": {
    "iso:country":"AU",
    "sg:address":"Suite 53 Sandford Jackson Building 30 Chasley",
    "sg:city":"Auchenflower",
    "sg:classifiers":[
        {
            "category":"Health Services",
            "subcategory":"Doctor",
            "type":"Services"
        }
    ],
    "sg:phone":"+61 7 3371 6033",
    "sg:postcode":"4066",
    "sg:province":"QLD",
    "sg:tags":[
        "medical",
        "practitioner"
    ],
    "wof:name":"The Wesley Centre For Hyperbaric Medicine",
    "wof:placetype":"venue"
},
  "geometry": {"coordinates":[152.99594116200001,-27.4921283722],"type":"Point"}
}