{
  "type": "Feature",
  "properties": {
    "iso:country":"AU",
    "sg:address":"127 Blewers Rd",
    "sg:city":"Morayfield",
    "sg:classifiers":[
        {
            "category":"Home & Garden",
            "subcategory":"Carpets & Floor Coverings",
            "type":"Retail Goods"
        }
    ],
    "sg:phone":"+61 7 5498 7531",
    "sg:postcode":"4506",
    "sg:province":"QLD",
    "sg:tags":[
        "tile",
        "wall",
        "layer"
    ],
    "wof:name":"Kopps Tiling Services",
    "wof:placetype":"venue"
},
  "geometry": {"coordinates":[152.94692993199999,-27.138299942],"type":"Point"}
}