{
  "type": "Feature",
  "properties": {
    "iso:country":"AU",
    "sg:address":"Nowendoc Rd",
    "sg:city":"Walcha",
    "sg:classifiers":[
        {
            "category":"Professional",
            "subcategory":"Engineering",
            "type":"Services"
        }
    ],
    "sg:phone":"+61 2 6778 0588",
    "sg:postcode":"2354",
    "sg:province":"NSW",
    "sg:tags":[
        "engineer"
    ],
    "wof:name":"John Wall Engineering",
    "wof:placetype":"venue"
},
  "geometry": {"coordinates":[151.54124450699999,-31.3869495392],"type":"Point"}
}