{
  "type": "Feature",
  "properties": {
    "iso:country":"AU",
    "sg:address":"95 Woodglen Rd",
    "sg:city":"Woodglen",
    "sg:classifiers":[
        {
            "category":"Food & Beverages",
            "subcategory":"Fruits & Vegetables",
            "type":"Retail Goods"
        }
    ],
    "sg:phone":"+61 3 5157 6348",
    "sg:postcode":"3875",
    "sg:province":"VIC",
    "sg:tags":[
        "grower"
    ],
    "wof:name":"Cox Farms",
    "wof:placetype":"venue"
},
  "geometry": {"coordinates":[147.39645385700001,-37.7773475647],"type":"Point"}
}