{
  "type": "Feature",
  "properties": {
    "addr:full":"16 Tornado Pl Raby NSW 2566",
    "addr:housenumber":"16",
    "addr:postcode":"2566",
    "addr:street":"Tornado Pl Raby",
    "iso:country":"AU",
    "sg:address":"16 Tornado Pl",
    "sg:city":"Raby",
    "sg:classifiers":[
        {
            "category":"Health Services",
            "subcategory":"Health Practitioner",
            "type":"Services"
        }
    ],
    "sg:phone":"+61 2 9820 8890",
    "sg:postcode":"2566",
    "sg:province":"NSW",
    "sg:tags":[
        "pathologist",
        "speech"
    ],
    "wof:name":"Padman Karen",
    "wof:placetype":"venue"
},
  "geometry": {"coordinates":[150.81460571299999,-34.0215415955],"type":"Point"}
}