{
  "type": "Feature",
  "properties": {
    "addr:full":"Old Joe St Gungahlin ACT 2912",
    "addr:postcode":"2912",
    "addr:street":"Old Joe St",
    "iso:country":"AU",
    "sg:address":"Old Joe St",
    "sg:city":"Gungahlin",
    "sg:classifiers":[
        {
            "category":"Food & Beverages",
            "subcategory":"Liquor & Beverages",
            "type":"Retail Goods"
        }
    ],
    "sg:phone":"+61 2 6241 8330",
    "sg:postcode":"2912",
    "sg:province":"ACT",
    "sg:tags":[
        "store"
    ],
    "wof:name":"Macs Liquor",
    "wof:placetype":"venue"
},
  "geometry": {"coordinates":[149.137405395,-35.1838493347],"type":"Point"}
}