{
  "type": "Feature",
  "properties": {
    "addr:full":"Studio 11, 6- 14 Tanner St Richmond VIC 3121",
    "addr:housenumber":"14",
    "addr:postcode":"3121",
    "addr:street":"6;Tanner St",
    "iso:country":"AU",
    "sg:address":"Studio 11, 6- 14 Tanner St",
    "sg:city":"Richmond",
    "sg:classifiers":[
        {
            "category":"Wholesale",
            "subcategory":"Apparel",
            "type":"Manufacturing & Wholesale Goods"
        }
    ],
    "sg:phone":"+61 3 9429 3901",
    "sg:postcode":"3121",
    "sg:province":"VIC",
    "sg:tags":[
        "wholesaler",
        "mfrs",
        "menswear"
    ],
    "wof:name":"Neo Tokyo",
    "wof:placetype":"venue"
},
  "geometry": {"coordinates":[144.990234375,-37.8230438232],"type":"Point"}
}