{
  "type": "Feature",
  "properties": {
    "addr:full":"7 East St Inverell NSW 2360",
    "addr:housenumber":"7",
    "addr:postcode":"2360",
    "addr:street":"East St",
    "iso:country":"AU",
    "sg:address":"7 East St",
    "sg:city":"Inverell",
    "sg:classifiers":[
        {
            "category":"Building & Trades",
            "subcategory":"Cleaning & Sanitation",
            "type":"Services"
        }
    ],
    "sg:phone":"+61 2 6722 4474",
    "sg:postcode":"2360",
    "sg:province":"NSW",
    "sg:tags":[
        "industrial",
        "commercial",
        "contractor"
    ],
    "wof:name":"Inverell Cleaning Service",
    "wof:placetype":"venue"
},
  "geometry": {"coordinates":[151.125442505,-29.7798309326],"type":"Point"}
}