{
  "type": "Feature",
  "properties": {
    "addr:full":"Shop 1/ 3 Abbott St Cairns QLD 4870",
    "addr:housenumber":"shop 1 / 3",
    "addr:postcode":"4870",
    "addr:street":"Abbott St",
    "iso:country":"AU",
    "sg:address":"Shop 1/ 3 Abbott St",
    "sg:city":"Cairns",
    "sg:classifiers":[
        {
            "category":"Real Estate",
            "subcategory":"Real Estate Agent",
            "type":"Services"
        }
    ],
    "sg:phone":"+61 7 4041 4337",
    "sg:postcode":"4870",
    "sg:province":"QLD",
    "wof:name":"Perkins Property Group",
    "wof:placetype":"venue"
},
  "geometry": {"coordinates":[145.77963256800001,-16.9248123169],"type":"Point"}
}