{
  "type": "Feature",
  "properties": {
    "iso:country":"AU",
    "sg:address":"Back Beach Rd",
    "sg:city":"Phillip Island",
    "sg:classifiers":[
        {
            "category":"Sports & Exercise",
            "subcategory":"Race Track",
            "type":"Entertainment"
        }
    ],
    "sg:phone":"+61 3 5952 2710",
    "sg:postcode":"3922",
    "sg:province":"VIC",
    "sg:tags":[
        "club",
        "racing",
        "motor"
    ],
    "wof:name":"Phillip Island Grand Prix Circuit",
    "wof:placetype":"venue"
},
  "geometry": {"coordinates":[145.24630737300001,-38.4965705872],"type":"Point"}
}