{
  "type": "Feature",
  "properties": {
    "addr:full":"258 Pakington St Geelong VIC 3220",
    "addr:housenumber":"258",
    "addr:postcode":"3220",
    "addr:street":"Pakington St",
    "iso:country":"AU",
    "sg:address":"258 Pakington St",
    "sg:city":"Geelong",
    "sg:classifiers":[
        {
            "category":"Retail",
            "subcategory":"Event Space",
            "type":"Services"
        }
    ],
    "sg:phone":"+61 3 5221 5811",
    "sg:postcode":"3220",
    "sg:province":"VIC",
    "sg:tags":[
        "venue",
        "reception",
        "wedding"
    ],
    "sg:website":"http://www.dromolandhouse.com.au",
    "wof:name":"Dromoland House",
    "wof:placetype":"venue"
},
  "geometry": {"coordinates":[144.346451,-38.15131],"type":"Point"}
}