{
  "type": "Feature",
  "properties": {
    "iso:country":"AU",
    "sg:address":"85 Lascelles St",
    "sg:city":"Hopetoun",
    "sg:classifiers":[
        {
            "category":"Professional",
            "subcategory":"Accounting & Tax Preparation",
            "type":"Services"
        }
    ],
    "sg:phone":"+61 3 5083 3117",
    "sg:postcode":"3396",
    "sg:province":"VIC",
    "sg:tags":[
        "accountant",
        "auditor"
    ],
    "wof:name":"Allen, Liston & Hall (Vic) Pty Ltd",
    "wof:placetype":"venue"
},
  "geometry": {"coordinates":[142.36521911599999,-35.7281494141],"type":"Point"}
}