{
  "type": "Feature",
  "properties": {
    "addr:full":"113 High St Maryborough VIC 3465",
    "addr:housenumber":"113",
    "addr:postcode":"3465",
    "addr:street":"High St",
    "iso:country":"AU",
    "sg:address":"113 High St",
    "sg:city":"Maryborough",
    "sg:classifiers":[
        {
            "category":"Government",
            "subcategory":"Court House",
            "type":"Public Place"
        }
    ],
    "sg:phone":"+61 3 5461 4377",
    "sg:postcode":"3465",
    "sg:province":"VIC",
    "sg:tags":[
        "personal",
        "marriage",
        "family",
        "counselling"
    ],
    "wof:name":"Rose La Vie - Creative Facilitator & Mediator",
    "wof:placetype":"venue"
},
  "geometry": {"coordinates":[143.737182617,-37.0470314026],"type":"Point"}
}