{
  "type": "Feature",
  "properties": {
    "addr:full":"&#034;Perlan House&#034; 5/50 Aerodrome Rd Maroochydore QLD 4558",
    "addr:housenumber":"5 / 50",
    "addr:postcode":"4558",
    "addr:street":"Aerodrome Rd",
    "iso:country":"AU",
    "sg:address":"&#034;Perlan House&#034; 5/50 Aerodrome Rd",
    "sg:city":"Maroochydore",
    "sg:classifiers":[
        {
            "category":"Banks & Credit Unions",
            "subcategory":"Investment Brokerage",
            "type":"Services"
        }
    ],
    "sg:phone":"+61 7 5443 3099",
    "sg:postcode":"4558",
    "sg:province":"QLD",
    "sg:tags":[
        "management",
        "property"
    ],
    "wof:name":"Kilpatrick Commercial",
    "wof:placetype":"venue"
},
  "geometry": {"coordinates":[153.100341797,-26.6605834961],"type":"Point"}
}