{
  "type": "Feature",
  "properties": {
    "iso:country":"AU",
    "sg:address":"Unit 1A 37 Expansion St",
    "sg:city":"Ernest",
    "sg:classifiers":[
        {
            "category":"Professional",
            "subcategory":"Computer Services",
            "type":"Services"
        }
    ],
    "sg:phone":"+61 1800 007 648",
    "sg:postcode":"4214",
    "sg:province":"QLD",
    "sg:tags":[
        "tele-communications",
        "consultant"
    ],
    "wof:name":"Next Generation Voice",
    "wof:placetype":"venue"
},
  "geometry": {"coordinates":[153.358886719,-27.9759635925],"type":"Point"}
}