{
  "type": "Feature",
  "properties": {
    "iso:country":"AU",
    "sg:address":"216 Waldron Rd",
    "sg:city":"Chester Hill",
    "sg:classifiers":[
        {
            "category":"Fast Food",
            "type":"Food & Drink"
        }
    ],
    "sg:phone":"+61 2 9645 6285",
    "sg:postcode":"2162",
    "sg:province":"NSW",
    "sg:tags":[
        "away",
        "take"
    ],
    "wof:name":"Chester Hill Pizza",
    "wof:placetype":"venue"
},
  "geometry": {"coordinates":[150.99859619099999,-33.8826332092],"type":"Point"}
}