{
  "type": "Feature",
  "properties": {
    "iso:country":"AU",
    "sg:address":"Tanya Arcade Maitland St",
    "sg:city":"Narrabri",
    "sg:classifiers":[
        {
            "category":"Social Services",
            "subcategory":"Child Care",
            "type":"Services"
        }
    ],
    "sg:phone":"+61 2 6792 4022",
    "sg:postcode":"2390",
    "sg:province":"NSW",
    "wof:name":"Narrabri & District Family Day Care",
    "wof:placetype":"venue"
},
  "geometry": {"coordinates":[149.78642273,-30.3310527802],"type":"Point"}
}