{
  "type": "Feature",
  "properties": {
    "addr:full":"24 Kerferd Rd Glen Iris VIC 3146",
    "addr:housenumber":"24",
    "addr:postcode":"3146",
    "addr:street":"Kerferd Rd",
    "iso:country":"AU",
    "sg:address":"24 Kerferd Rd",
    "sg:city":"Glen Iris",
    "sg:classifiers":[
        {
            "category":"Professional",
            "subcategory":"Management & Consulting",
            "type":"Services"
        }
    ],
    "sg:phone":"+61 411 690 788",
    "sg:postcode":"3146",
    "sg:province":"VIC",
    "sg:tags":[
        "consultant"
    ],
    "wof:name":"POW Consulting",
    "wof:placetype":"venue"
},
  "geometry": {"coordinates":[145.063552856,-37.8581428528],"type":"Point"}
}