{
  "type": "Feature",
  "properties": {
    "addr:full":"Lot 1258 Boundary Rd Carnarvon WA 6701",
    "addr:housenumber":"1258",
    "addr:postcode":"6701",
    "addr:street":"Boundary Rd",
    "iso:country":"AU",
    "sg:address":"Lot 1258 Boundary Rd",
    "sg:city":"Carnarvon",
    "sg:classifiers":[
        {
            "category":"Manufacturing",
            "subcategory":"Metals",
            "type":"Manufacturing & Wholesale Goods"
        }
    ],
    "sg:phone":"+61 8 9941 8313",
    "sg:postcode":"6701",
    "sg:province":"WA",
    "sg:tags":[
        "steel",
        "fabricator",
        "mfrs"
    ],
    "wof:name":"Schipp-Shape",
    "wof:placetype":"venue"
},
  "geometry": {"coordinates":[113.698890686,-24.8713226318],"type":"Point"}
}