{
  "type": "Feature",
  "properties": {
    "iso:country":"AU",
    "sg:address":"6 Admiralty Ave",
    "sg:city":"Tea Gardens",
    "sg:classifiers":[
        {
            "category":"Professional",
            "subcategory":"Accounting & Tax Preparation",
            "type":"Services"
        }
    ],
    "sg:phone":"+61 427 962 075",
    "sg:postcode":"2324",
    "sg:province":"NSW",
    "sg:tags":[
        "accountant",
        "auditor"
    ],
    "wof:name":"Prince & Associates Pty Ltd",
    "wof:placetype":"venue"
},
  "geometry": {"coordinates":[152.154907227,-32.6581192017],"type":"Point"}
}