{
  "type": "Feature",
  "properties": {
    "addr:full":"83 Salisbury Crs West Launceston TAS 7250",
    "addr:housenumber":"83",
    "addr:postcode":"7250",
    "addr:street":"Salisbury Crs West",
    "iso:country":"AU",
    "sg:address":"83 Salisbury Crs",
    "sg:city":"West Launceston",
    "sg:classifiers":[
        {
            "category":"Building & Trades",
            "subcategory":"Construction",
            "type":"Services"
        }
    ],
    "sg:phone":"+61 407 800 513",
    "sg:postcode":"7250",
    "sg:province":"TAS",
    "sg:tags":[
        "brick",
        "paving"
    ],
    "wof:name":"B.J's Paving",
    "wof:placetype":"venue"
},
  "geometry": {"coordinates":[147.133544922,-41.4615211487],"type":"Point"}
}