{
  "type": "Feature",
  "properties": {
    "addr:full":"9- 11 Ausco Pl Dandenong VIC 3175",
    "addr:housenumber":"11",
    "addr:postcode":"3175",
    "addr:street":"9;Pl",
    "iso:country":"AU",
    "sg:address":"9- 11 Ausco Pl",
    "sg:city":"Dandenong",
    "sg:classifiers":[
        {
            "category":"Home & Garden",
            "subcategory":"Building Materials",
            "type":"Retail Goods"
        }
    ],
    "sg:phone":"+61 3 8787 5777",
    "sg:postcode":"3175",
    "sg:province":"VIC",
    "sg:tags":[
        "merchant",
        "glass",
        "glazier"
    ],
    "wof:name":"Superior Glass & Glazing Pty. Ltd.",
    "wof:placetype":"venue"
},
  "geometry": {"coordinates":[145.23629760700001,-38.0338897705],"type":"Point"}
}