{
  "type": "Feature",
  "properties": {
    "addr:full":"91 Railway Ave Werribee VIC 3030",
    "addr:housenumber":"91",
    "addr:postcode":"3030",
    "addr:street":"Railway Ave",
    "iso:country":"AU",
    "sg:address":"91 Railway Ave",
    "sg:city":"Werribee",
    "sg:classifiers":[
        {
            "category":"Wholesale",
            "subcategory":"Apparel",
            "type":"Manufacturing & Wholesale Goods"
        }
    ],
    "sg:phone":"+61 3 9742 4666",
    "sg:postcode":"3030",
    "sg:province":"VIC",
    "sg:tags":[
        "wholesaler",
        "mfrs",
        "cap",
        "hat"
    ],
    "wof:name":"Caps Plus",
    "wof:placetype":"venue"
},
  "geometry": {"coordinates":[144.67297400000001,-37.894253],"type":"Point"}
}