{
  "type": "Feature",
  "properties": {
    "addr:full":"Suite 8, 75 Pacific Hwy Waitara NSW 2077",
    "addr:housenumber":"75",
    "addr:postcode":"2077",
    "addr:street":"Pacific Hwy",
    "iso:country":"AU",
    "sg:address":"Suite 8, 75 Pacific Hwy",
    "sg:city":"Waitara",
    "sg:classifiers":[
        {
            "category":"Freight",
            "type":"Transportation"
        }
    ],
    "sg:phone":"+61 421 084 054",
    "sg:postcode":"2077",
    "sg:province":"NSW",
    "sg:tags":[
        "cargo",
        "container"
    ],
    "wof:name":"Containers 4 Sale",
    "wof:placetype":"venue"
},
  "geometry": {"coordinates":[151.10154724099999,-33.7098693848],"type":"Point"}
}