{
  "type": "Feature",
  "properties": {
    "addr:full":"655 Burke Rd Camberwell VIC 3124",
    "addr:housenumber":"655",
    "addr:postcode":"3124",
    "addr:street":"Burke Rd",
    "iso:country":"AU",
    "sg:address":"655 Burke Rd",
    "sg:city":"Camberwell",
    "sg:classifiers":[
        {
            "category":"Health Services",
            "subcategory":"Health Practitioner",
            "type":"Services"
        }
    ],
    "sg:phone":"+61 3 9882 8840",
    "sg:postcode":"3124",
    "sg:province":"VIC",
    "sg:tags":[
        "alternative"
    ],
    "wof:name":"Colon Irrigation Clinics",
    "wof:placetype":"venue"
},
  "geometry": {"coordinates":[145.055786133,-37.835319519],"type":"Point"}
}