{
  "type": "Feature",
  "properties": {
    "iso:country":"AU",
    "sg:address":"Level 17 15 Blue St",
    "sg:city":"North Sydney",
    "sg:classifiers":[
        {
            "category":"Professional",
            "subcategory":"Accounting & Tax Preparation",
            "type":"Services"
        }
    ],
    "sg:phone":"+61 2 9966 1222",
    "sg:postcode":"2059",
    "sg:province":"NSW",
    "sg:tags":[
        "accountant",
        "auditor"
    ],
    "wof:name":"Keefe J P & Co",
    "wof:placetype":"venue"
},
  "geometry": {"coordinates":[151.207916,-33.841141],"type":"Point"}
}