{
  "type": "Feature",
  "properties": {
    "addr:full":"55 Christensen Rd Stapylton QLD 4207",
    "addr:housenumber":"55",
    "addr:postcode":"4207",
    "addr:street":"Christensen Rd",
    "iso:country":"AU",
    "sg:address":"55 Christensen Rd",
    "sg:city":"Stapylton",
    "sg:classifiers":[
        {
            "category":"Building & Trades",
            "subcategory":"Construction",
            "type":"Services"
        }
    ],
    "sg:phone":"+61 7 3807 1820",
    "sg:postcode":"4207",
    "sg:province":"QLD",
    "sg:tags":[
        "welding"
    ],
    "wof:name":"Alltype Welding",
    "wof:placetype":"venue"
},
  "geometry": {"coordinates":[153.185379028,-27.7124080658],"type":"Point"}
}