{
  "type": "Feature",
  "properties": {
    "addr:full":"5 Fleet St North Parramatta NSW 2151",
    "addr:housenumber":"5",
    "addr:postcode":"2151",
    "addr:street":"Fleet St",
    "iso:country":"AU",
    "sg:address":"5 Fleet St",
    "sg:city":"North Parramatta",
    "sg:classifiers":[
        {
            "category":"Health Services",
            "subcategory":"Health Practitioner",
            "type":"Services"
        }
    ],
    "sg:phone":"+61 407 676 235",
    "sg:postcode":"2151",
    "sg:province":"NSW",
    "sg:tags":[
        "psychologist"
    ],
    "wof:name":"Paneras Helen",
    "wof:placetype":"venue"
},
  "geometry": {"coordinates":[151.00120544399999,-33.8033981323],"type":"Point"}
}