{
  "type": "Feature",
  "properties": {
    "iso:country":"AU",
    "sg:address":"55 Bromby St",
    "sg:city":"South Yarra",
    "sg:classifiers":[
        {
            "category":"Wholesale",
            "subcategory":"Non-durable Goods",
            "type":"Manufacturing & Wholesale Goods"
        }
    ],
    "sg:phone":"+61 3 9821 5271",
    "sg:postcode":"3141",
    "sg:province":"VIC",
    "sg:tags":[
        "wholesaler",
        "mfrs",
        "cosmetic"
    ],
    "wof:name":"Natural Source The",
    "wof:placetype":"venue"
},
  "geometry": {"coordinates":[144.97651672399999,-37.8350334167],"type":"Point"}
}