{
  "type": "Feature",
  "properties": {
    "addr:full":"5 King St Campbelltown NSW 2560",
    "addr:housenumber":"5",
    "addr:postcode":"2560",
    "addr:street":"King St",
    "iso:country":"AU",
    "sg:address":"5 King St",
    "sg:city":"Campbelltown",
    "sg:classifiers":[
        {
            "category":"Health Services",
            "subcategory":"Dentist",
            "type":"Services"
        }
    ],
    "sg:phone":"+61 2 4628 3048",
    "sg:postcode":"2560",
    "sg:province":"NSW",
    "wof:name":"Lalli B & Jarvis R G",
    "wof:placetype":"venue"
},
  "geometry": {"coordinates":[150.81794738799999,-34.0628623962],"type":"Point"}
}