{
  "type": "Feature",
  "properties": {
    "iso:country":"AU",
    "sg:address":"10 Orford Crt",
    "sg:city":"Toowoomba",
    "sg:classifiers":[
        {
            "category":"Wholesale",
            "subcategory":"Fruits & Vegetables",
            "type":"Manufacturing & Wholesale Goods"
        }
    ],
    "sg:phone":"+61 7 4634 6200",
    "sg:postcode":"4350",
    "sg:province":"QLD",
    "sg:tags":[
        "produce",
        "grain"
    ],
    "wof:name":"Takari Seeds",
    "wof:placetype":"venue"
},
  "geometry": {"coordinates":[151.9086,-27.540464],"type":"Point"}
}