{
  "type": "Feature",
  "properties": {
    "addr:full":"95 York St Sydney NSW 2000",
    "addr:housenumber":"95",
    "addr:postcode":"2000",
    "addr:street":"York St",
    "iso:country":"AU",
    "sg:address":"95 York St",
    "sg:city":"Sydney",
    "sg:classifiers":[
        {
            "category":"Banks & Credit Unions",
            "subcategory":"Investment Brokerage",
            "type":"Services"
        }
    ],
    "sg:phone":"+61 2 9299 2038",
    "sg:postcode":"2000",
    "sg:province":"NSW",
    "sg:tags":[
        "finance",
        "broker"
    ],
    "wof:name":"Ausa International Pty Ltd",
    "wof:placetype":"venue"
},
  "geometry": {"coordinates":[151.20603942899999,-33.8699455261],"type":"Point"}
}