{
  "type": "Feature",
  "properties": {
    "iso:country":"AU",
    "sg:address":"Level 2, 11 Morrison St",
    "sg:city":"Hobart",
    "sg:classifiers":[
        {
            "category":"Banks & Credit Unions",
            "subcategory":"Investment Brokerage",
            "type":"Services"
        }
    ],
    "sg:phone":"+61 1300 303 764",
    "sg:postcode":"7000",
    "sg:province":"TAS",
    "sg:tags":[
        "finance",
        "broker"
    ],
    "wof:name":"FROG for Finance",
    "wof:placetype":"venue"
},
  "geometry": {"coordinates":[147.331634522,-42.8841018677],"type":"Point"}
}