{
  "type": "Feature",
  "properties": {
    "addr:full":"Unit 2/ 47 Dellamarta Rd Wangara WA 6065",
    "addr:postcode":"6065",
    "addr:street":"47 Dellamarta Rd",
    "iso:country":"AU",
    "sg:address":"Unit 2/ 47 Dellamarta Rd",
    "sg:city":"Wangara",
    "sg:classifiers":[
        {
            "category":"Building & Trades",
            "subcategory":"Construction",
            "type":"Services"
        }
    ],
    "sg:phone":"+61 8 9409 8288",
    "sg:postcode":"6065",
    "sg:province":"WA",
    "sg:tags":[
        "window",
        "timber"
    ],
    "wof:name":"Taurus Installations",
    "wof:placetype":"venue"
},
  "geometry": {"coordinates":[115.82386779799999,-31.7888202667],"type":"Point"}
}