{
  "type": "Feature",
  "properties": {
    "addr:full":"169 Para Rd Greensborough VIC 3088",
    "addr:housenumber":"169",
    "addr:postcode":"3088",
    "addr:street":"Para Rd",
    "iso:country":"AU",
    "sg:address":"169 Para Rd",
    "sg:city":"Greensborough",
    "sg:classifiers":[
        {
            "category":"Manufacturing",
            "subcategory":"Furniture",
            "type":"Manufacturing & Wholesale Goods"
        }
    ],
    "sg:phone":"+61 3 9432 0988",
    "sg:postcode":"3088",
    "sg:province":"VIC",
    "sg:tags":[
        "builder",
        "designer",
        "custom"
    ],
    "wof:name":"Prestige Timber Furniture",
    "wof:placetype":"venue"
},
  "geometry": {"coordinates":[145.11119079599999,-37.7080535889],"type":"Point"}
}