{
  "type": "Feature",
  "properties": {
    "addr:full":"585 Lyne St Lavington NSW 2641",
    "addr:housenumber":"585",
    "addr:postcode":"2641",
    "addr:street":"Lyne St",
    "iso:country":"AU",
    "sg:address":"585 Lyne St",
    "sg:city":"Lavington",
    "sg:classifiers":[
        {
            "category":"Retail",
            "subcategory":"Car Wash",
            "type":"Services"
        }
    ],
    "sg:phone":"+61 412 819 768",
    "sg:postcode":"2641",
    "sg:province":"NSW",
    "sg:tags":[
        "truck",
        "cleaning"
    ],
    "wof:name":"Kanes Car Care",
    "wof:placetype":"venue"
},
  "geometry": {"coordinates":[146.92526245100001,-36.0370635986],"type":"Point"}
}