{
  "type": "Feature",
  "properties": {
    "iso:country":"AU",
    "sg:address":"132 Bellarine Hwy",
    "sg:city":"Newcomb",
    "sg:classifiers":[
        {
            "category":"Health Services",
            "subcategory":"Doctor",
            "type":"Services"
        }
    ],
    "sg:phone":"+61 3 5248 1299",
    "sg:postcode":"3219",
    "sg:province":"VIC",
    "sg:tags":[
        "medical",
        "practitioner"
    ],
    "wof:name":"Banksia Medical Centre",
    "wof:placetype":"venue"
},
  "geometry": {"coordinates":[144.398529053,-38.1727180481],"type":"Point"}
}