{
  "type": "Feature",
  "properties": {
    "addr:full":"48 Wyadra Ave Harbord NSW 2096",
    "addr:housenumber":"48",
    "addr:postcode":"2096",
    "addr:street":"Wyadra Ave",
    "iso:country":"AU",
    "sg:address":"48 Wyadra Ave",
    "sg:city":"Harbord",
    "sg:classifiers":[
        {
            "category":"Professional",
            "subcategory":"Art Services",
            "type":"Services"
        }
    ],
    "sg:phone":"+61 422 701 749",
    "sg:postcode":"2096",
    "sg:province":"NSW",
    "sg:tags":[
        "decorator",
        "painter"
    ],
    "wof:name":"Adrian Burge Painting & Decorating",
    "wof:placetype":"venue"
},
  "geometry": {"coordinates":[151.28398132300001,-33.7728462219],"type":"Point"}
}