{
  "type": "Feature",
  "properties": {
    "addr:full":"8 Sadlier Crt Stoneville WA 6081",
    "addr:housenumber":"8",
    "addr:postcode":"6081",
    "addr:street":"Sadlier Crt",
    "iso:country":"AU",
    "sg:address":"8 Sadlier Crt",
    "sg:city":"Stoneville",
    "sg:classifiers":[
        {
            "category":"Building & Trades",
            "subcategory":"Locksmith",
            "type":"Services"
        }
    ],
    "sg:phone":"+61 412 473 289",
    "sg:postcode":"6081",
    "sg:province":"WA",
    "sg:tags":[
        "lock"
    ],
    "wof:name":"A Accredited Lock Service",
    "wof:placetype":"venue"
},
  "geometry": {"coordinates":[116.173423767,-31.8798847198],"type":"Point"}
}