{
  "type": "Feature",
  "properties": {
    "iso:country":"AU",
    "sg:address":"168 Ridge St",
    "sg:city":"Muswellbrook",
    "sg:classifiers":[
        {
            "category":"Fast Food",
            "type":"Food & Drink"
        }
    ],
    "sg:phone":"+61 2 6541 3030",
    "sg:postcode":"2333",
    "sg:province":"NSW",
    "sg:tags":[
        "away",
        "take"
    ],
    "wof:name":"Charlee's Chickens",
    "wof:placetype":"venue"
},
  "geometry": {"coordinates":[150.888473511,-32.2640686035],"type":"Point"}
}