{
  "type": "Feature",
  "properties": {
    "addr:full":"119 Elliott Heads Rd Bundaberg QLD 4670",
    "addr:housenumber":"119",
    "addr:postcode":"4670",
    "addr:street":"Elliott Heads Rd",
    "iso:country":"AU",
    "sg:address":"119 Elliott Heads Rd",
    "sg:city":"Bundaberg",
    "sg:classifiers":[
        {
            "category":"Professional",
            "subcategory":"Printing & Photocopies",
            "type":"Services"
        }
    ],
    "sg:phone":"+61 7 4153 1449",
    "sg:postcode":"4670",
    "sg:province":"QLD",
    "sg:tags":[
        "screen",
        "printer"
    ],
    "wof:name":"Bundy Badges",
    "wof:placetype":"venue"
},
  "geometry": {"coordinates":[152.37884521500001,-24.8844413757],"type":"Point"}
}