{
  "type": "Feature",
  "properties": {
    "iso:country":"AU",
    "sg:address":"Clarendon Rd",
    "sg:city":"Lal Lal",
    "sg:classifiers":[
        {
            "category":"Travel",
            "subcategory":"Hotels & Motels",
            "type":"Entertainment"
        }
    ],
    "sg:phone":"+61 3 5341 7574",
    "sg:postcode":"3352",
    "sg:province":"VIC",
    "sg:tags":[
        "accommodation"
    ],
    "wof:name":"Lal Lal Falls Hotel",
    "wof:placetype":"venue"
},
  "geometry": {"coordinates":[143.862793,-37.553772],"type":"Point"}
}