{
  "type": "Feature",
  "properties": {
    "addr:full":"41 Curtin Pl Curtin ACT 2605",
    "addr:housenumber":"41",
    "addr:postcode":"2605",
    "addr:street":"Curtin Pl Curtin",
    "iso:country":"AU",
    "sg:address":"41 Curtin Pl",
    "sg:city":"Curtin",
    "sg:classifiers":[
        {
            "category":"Food & Beverages",
            "subcategory":"Liquor & Beverages",
            "type":"Retail Goods"
        }
    ],
    "sg:phone":"+61 2 6281 0038",
    "sg:postcode":"2605",
    "sg:province":"ACT",
    "sg:tags":[
        "store"
    ],
    "wof:name":"Liquorland",
    "wof:placetype":"venue"
},
  "geometry": {"coordinates":[149.08267211899999,-35.3255157471],"type":"Point"}
}