{
  "type": "Feature",
  "properties": {
    "addr:full":"1a Longley St Alfredton VIC 3350",
    "addr:housenumber":"1a",
    "addr:postcode":"3350",
    "addr:street":"Longley St",
    "iso:country":"AU",
    "sg:address":"1a Longley St",
    "sg:city":"Alfredton",
    "sg:classifiers":[
        {
            "category":"Retail",
            "subcategory":"Self-service Laundry",
            "type":"Services"
        }
    ],
    "sg:phone":"+61 3 5334 1753",
    "sg:postcode":"3350",
    "sg:province":"VIC",
    "wof:name":"Arch Laundrette",
    "wof:placetype":"venue"
},
  "geometry": {"coordinates":[143.81764200000001,-37.555588],"type":"Point"}
}