{
  "type": "Feature",
  "properties": {
    "addr:full":"1096 South Rd Edwardstown SA 5039",
    "addr:housenumber":"1096",
    "addr:postcode":"5039",
    "addr:street":"South Rd",
    "iso:country":"AU",
    "sg:address":"1096 South Rd",
    "sg:city":"Edwardstown",
    "sg:classifiers":[
        {
            "category":"Autos & Motor Vehicles",
            "subcategory":"Auto Supplies",
            "type":"Retail Goods"
        }
    ],
    "sg:phone":"+61 8 8276 5444",
    "sg:postcode":"5039",
    "sg:province":"SA",
    "sg:tags":[
        "camper-trailers",
        "caravan",
        "equipment"
    ],
    "sg:website":"http://www.cameroncaravanssa.com.au",
    "wof:name":"Cameron Caravans",
    "wof:placetype":"venue"
},
  "geometry": {"coordinates":[138.57452392600001,-34.9911460876],"type":"Point"}
}