{
  "type": "Feature",
  "properties": {
    "addr:full":"1881 Dandenong-Hastings Rd Pearcedale VIC 3912",
    "addr:housenumber":"1881",
    "addr:postcode":"3912",
    "addr:street":"Dandenong-Hastings Rd",
    "iso:country":"AU",
    "sg:address":"1881 Dandenong-Hastings Rd",
    "sg:city":"Pearcedale",
    "sg:classifiers":[
        {
            "category":"Retail",
            "subcategory":"Storage",
            "type":"Services"
        }
    ],
    "sg:phone":"+61 3 5978 5900",
    "sg:postcode":"3912",
    "sg:province":"VIC",
    "sg:tags":[
        "removal",
        "furniture"
    ],
    "sg:website":"http://www.cranbourneremovals.com.au",
    "wof:name":"Cranbourne Removals",
    "wof:placetype":"venue"
},
  "geometry": {"coordinates":[145.217163086,-38.1931877136],"type":"Point"}
}