{
  "type": "Feature",
  "properties": {
    "iso:country":"AU",
    "sg:address":"Gold Coast Airport, Bilinga Terminal Dr",
    "sg:city":"Bilinga",
    "sg:classifiers":[
        {
            "category":"Retail",
            "subcategory":"Auto Rental",
            "type":"Services"
        }
    ],
    "sg:phone":"+61 7 5536 8104",
    "sg:postcode":"4225",
    "sg:province":"QLD",
    "sg:tags":[
        "car",
        "hire",
        "minibus"
    ],
    "sg:website":"http://www.economyrentalcars.com.au",
    "wof:name":"Economy Rental Cars",
    "wof:placetype":"venue"
},
  "geometry": {"coordinates":[153.537841797,-28.1684398651],"type":"Point"}
}