{
  "type": "Feature",
  "properties": {
    "iso:country":"AU",
    "sg:address":"13 Muncaster Pl",
    "sg:city":"Cranebrook",
    "sg:classifiers":[
        {
            "category":"Education",
            "subcategory":"Music School",
            "type":"Public Place"
        }
    ],
    "sg:phone":"+61 2 4730 4276",
    "sg:postcode":"2749",
    "sg:province":"NSW",
    "sg:tags":[
        "teacher"
    ],
    "wof:name":"Mal Morgan Drum School",
    "wof:placetype":"venue"
},
  "geometry": {"coordinates":[150.71638488799999,-33.7229270935],"type":"Point"}
}