{
  "type": "Feature",
  "properties": {
    "addr:full":"33 Warren Rd Nannup WA 6275",
    "addr:housenumber":"33",
    "addr:postcode":"6275",
    "addr:street":"Warren Rd",
    "iso:country":"AU",
    "sg:address":"33 Warren Rd",
    "sg:city":"Nannup",
    "sg:classifiers":[
        {
            "category":"Retail",
            "subcategory":"Veterinary Services",
            "type":"Services"
        }
    ],
    "sg:phone":"+61 8 9756 0422",
    "sg:postcode":"6275",
    "sg:province":"WA",
    "sg:tags":[
        "surgeon"
    ],
    "wof:name":"Geovet Veterinary Hospital",
    "wof:placetype":"venue"
},
  "geometry": {"coordinates":[115.76547241199999,-33.9846115112],"type":"Point"}
}