{
  "type": "Feature",
  "properties": {
    "iso:country":"AU",
    "sg:address":"Boland St",
    "sg:city":"Launceston",
    "sg:classifiers":[
        {
            "category":"Wholesale",
            "subcategory":"Farm Supplies",
            "type":"Manufacturing & Wholesale Goods"
        }
    ],
    "sg:phone":"+61 3 6331 2022",
    "sg:postcode":"7250",
    "sg:province":"TAS",
    "sg:tags":[
        "equipment"
    ],
    "wof:name":"Elders",
    "wof:placetype":"venue"
},
  "geometry": {"coordinates":[147.14312744099999,-41.429889679],"type":"Point"}
}