{
  "type": "Feature",
  "properties": {
    "addr:full":"8 Bank St Port Fairy VIC 3284",
    "addr:housenumber":"8",
    "addr:postcode":"3284",
    "addr:street":"Bank St",
    "iso:country":"AU",
    "sg:address":"8 Bank St",
    "sg:city":"Port Fairy",
    "sg:classifiers":[
        {
            "category":"Shopping",
            "subcategory":"Bridal",
            "type":"Retail Goods"
        }
    ],
    "sg:phone":"+61 3 5568 2050",
    "sg:postcode":"3284",
    "sg:province":"VIC",
    "sg:tags":[
        "hire",
        "wear"
    ],
    "wof:name":"County Grey Clothing For Men",
    "wof:placetype":"venue"
},
  "geometry": {"coordinates":[142.237716675,-38.3833580017],"type":"Point"}
}