{
  "type": "Feature",
  "properties": {
    "addr:full":"5 Balgownie Rd Fairy Meadow NSW 2519",
    "addr:housenumber":"5",
    "addr:postcode":"2519",
    "addr:street":"Balgownie Rd",
    "iso:country":"AU",
    "sg:address":"5 Balgownie Rd",
    "sg:city":"Fairy Meadow",
    "sg:classifiers":[
        {
            "category":"Education",
            "subcategory":"Music School",
            "type":"Public Place"
        }
    ],
    "sg:phone":"+61 2 4227 1319",
    "sg:postcode":"2519",
    "sg:province":"NSW",
    "sg:tags":[
        "singing",
        "teacher"
    ],
    "wof:name":"Patricia Worley-Smith",
    "wof:placetype":"venue"
},
  "geometry": {"coordinates":[150.893463,-34.38966],"type":"Point"}
}