{
  "type": "Feature",
  "properties": {
    "addr:full":"Lvl 5/ 46 Holt St Surry Hills NSW 2010",
    "addr:housenumber":"/ 46",
    "addr:postcode":"2010",
    "addr:street":"Holt St",
    "iso:country":"AU",
    "sg:address":"Lvl 5/ 46 Holt St",
    "sg:city":"Surry Hills",
    "sg:classifiers":[
        {
            "category":"Professional",
            "subcategory":"Computer Services",
            "type":"Services"
        }
    ],
    "sg:phone":"+61 2 9699 8122",
    "sg:postcode":"2010",
    "sg:province":"NSW",
    "sg:tags":[
        "equipment",
        "networking",
        "installation"
    ],
    "wof:name":"Cogenesis It Consulting",
    "wof:placetype":"venue"
},
  "geometry": {"coordinates":[151.20942688,-33.886089325],"type":"Point"}
}