{
  "type": "Feature",
  "properties": {
    "iso:country":"AU",
    "sg:address":"52 Kidman Ave",
    "sg:city":"Belmont",
    "sg:classifiers":[
        {
            "category":"Retail",
            "subcategory":"Repair Shop",
            "type":"Services"
        }
    ],
    "sg:phone":"+61 3 5244 3618",
    "sg:postcode":"3216",
    "sg:province":"VIC",
    "sg:tags":[
        "machine",
        "repairs",
        "part",
        "dryer",
        "washing"
    ],
    "wof:name":"Belmont Appliance Repairs",
    "wof:placetype":"venue"
},
  "geometry": {"coordinates":[144.341705322,-38.1852760315],"type":"Point"}
}