{
  "type": "Feature",
  "properties": {
    "addr:full":"76 Poath Rd Hughesdale VIC 3166",
    "addr:housenumber":"76",
    "addr:postcode":"3166",
    "addr:street":"Poath Rd",
    "iso:country":"AU",
    "sg:address":"76 Poath Rd",
    "sg:city":"Hughesdale",
    "sg:classifiers":[
        {
            "category":"Food & Beverages",
            "subcategory":"Liquor & Beverages",
            "type":"Retail Goods"
        }
    ],
    "sg:phone":"+61 3 9568 1831",
    "sg:postcode":"3166",
    "sg:province":"VIC",
    "sg:tags":[
        "store"
    ],
    "wof:name":"Wines On Poath",
    "wof:placetype":"venue"
},
  "geometry": {"coordinates":[145.07708740199999,-37.8936920166],"type":"Point"}
}