{
  "type": "Feature",
  "properties": {
    "addr:full":"76 Lygon St Brunswick VIC 3056",
    "addr:housenumber":"76",
    "addr:postcode":"3056",
    "addr:street":"Lygon St",
    "iso:country":"AU",
    "sg:address":"76 Lygon St",
    "sg:city":"Brunswick",
    "sg:classifiers":[
        {
            "category":"Cafe",
            "type":"Food & Drink"
        }
    ],
    "sg:phone":"+61 3 9387 0497",
    "sg:postcode":"3056",
    "sg:province":"VIC",
    "wof:name":"Cafe L&#039;Amour",
    "wof:placetype":"venue"
},
  "geometry": {"coordinates":[144.97111511200001,-37.7763977051],"type":"Point"}
}