{
  "type": "Feature",
  "properties": {
    "addr:full":"172 Camden St Ulladulla NSW 2539",
    "addr:housenumber":"172",
    "addr:postcode":"2539",
    "addr:street":"Camden St",
    "iso:country":"AU",
    "sg:address":"172 Camden St",
    "sg:city":"Ulladulla",
    "sg:classifiers":[
        {
            "category":"Home & Garden",
            "subcategory":"Building Materials",
            "type":"Retail Goods"
        }
    ],
    "sg:phone":"+61 2 4455 1770",
    "sg:postcode":"2539",
    "sg:province":"NSW",
    "sg:tags":[
        "merchant",
        "glass",
        "glazier"
    ],
    "wof:name":"Ulladulla Glass",
    "wof:placetype":"venue"
},
  "geometry": {"coordinates":[150.468383789,-35.3619651794],"type":"Point"}
}