{
  "type": "Feature",
  "properties": {
    "iso:country":"AU",
    "sg:address":"Lot 25 Anchor Rd",
    "sg:city":"Armidale",
    "sg:classifiers":[
        {
            "category":"Building & Trades",
            "subcategory":"Construction",
            "type":"Services"
        }
    ],
    "sg:phone":"+61 2 6772 5374",
    "sg:postcode":"2350",
    "sg:province":"NSW",
    "sg:tags":[
        "contractor"
    ],
    "wof:name":"Sozou A C",
    "wof:placetype":"venue"
},
  "geometry": {"coordinates":[151.69674682600001,-30.5260543823],"type":"Point"}
}