{
  "type": "Feature",
  "properties": {
    "addr:full":"16 Harvey La Eaglehawk VIC 3556",
    "addr:housenumber":"16",
    "addr:postcode":"3556",
    "addr:street":"Harvey La",
    "iso:country":"AU",
    "sg:address":"16 Harvey La",
    "sg:city":"Eaglehawk",
    "sg:classifiers":[
        {
            "category":"Military Area",
            "subcategory":"Army Base",
            "type":"Public Place"
        }
    ],
    "sg:phone":"+61 3 5446 1738",
    "sg:postcode":"3556",
    "sg:province":"VIC",
    "sg:tags":[
        "concrete",
        "slab",
        "floor"
    ],
    "wof:name":"Stratfords K.G. & V.E.",
    "wof:placetype":"venue"
},
  "geometry": {"coordinates":[144.26603698700001,-36.7210502625],"type":"Point"}
}