{
  "type": "Feature",
  "properties": {
    "addr:full":"153 Davey St Hobart TAS 7000",
    "addr:housenumber":"153",
    "addr:postcode":"7000",
    "addr:street":"Davey St",
    "iso:country":"AU",
    "sg:address":"153 Davey St",
    "sg:city":"Hobart",
    "sg:classifiers":[
        {
            "category":"Real Estate",
            "subcategory":"Architect",
            "type":"Services"
        }
    ],
    "sg:phone":"+61 3 6223 6740",
    "sg:postcode":"7000",
    "sg:province":"TAS",
    "sg:tags":[
        "building",
        "designer"
    ],
    "wof:name":"Design.East",
    "wof:placetype":"venue"
},
  "geometry": {"coordinates":[147.32200622600001,-42.8902664185],"type":"Point"}
}