{
  "type": "Feature",
  "properties": {
    "addr:full":"6-8 Help St Chatswood NSW 2067",
    "addr:housenumber":"6-8",
    "addr:postcode":"2067",
    "addr:street":"Help St",
    "iso:country":"AU",
    "sg:address":"6-8 Help St",
    "sg:city":"Chatswood",
    "sg:classifiers":[
        {
            "category":"Cafe",
            "type":"Food & Drink"
        }
    ],
    "sg:phone":"+61 2 9884 8233",
    "sg:postcode":"2067",
    "sg:province":"NSW",
    "wof:name":"Coffeelink",
    "wof:placetype":"venue"
},
  "geometry": {"coordinates":[151.18174743599999,-33.7952651978],"type":"Point"}
}