{
  "type": "Feature",
  "properties": {
    "addr:full":"&#034;Park View&#034; 3 Cemetery Rd Terang VIC 3264",
    "addr:housenumber":"3",
    "addr:postcode":"3264",
    "addr:street":"Cemetery Rd",
    "iso:country":"AU",
    "sg:address":"&#034;Park View&#034; 3 Cemetery Rd",
    "sg:city":"Terang",
    "sg:classifiers":[
        {
            "category":"Farming",
            "subcategory":"Farm",
            "type":"Manufacturing & Wholesale Goods"
        }
    ],
    "sg:phone":"+61 3 5592 1047",
    "sg:postcode":"3264",
    "sg:province":"VIC",
    "sg:tags":[
        "farmer"
    ],
    "wof:name":"Moloney P & E",
    "wof:placetype":"venue"
},
  "geometry": {"coordinates":[142.918579102,-38.2502365112],"type":"Point"}
}