{
  "type": "Feature",
  "properties": {
    "iso:country":"AU",
    "sg:address":"36 Winslow Crs",
    "sg:city":"Deer Park",
    "sg:classifiers":[
        {
            "category":"Home & Garden",
            "subcategory":"Building Materials",
            "type":"Retail Goods"
        }
    ],
    "sg:phone":"+61 3 9363 8669",
    "sg:postcode":"3023",
    "sg:province":"VIC",
    "sg:tags":[
        "supply"
    ],
    "wof:name":"Sizo Fix Fasteners",
    "wof:placetype":"venue"
},
  "geometry": {"coordinates":[144.774857,-37.76955],"type":"Point"}
}