{
  "type": "Feature",
  "properties": {
    "addr:full":"154 Hudson Rd Spotswood VIC 3015",
    "addr:housenumber":"154",
    "addr:postcode":"3015",
    "addr:street":"Hudson Rd",
    "iso:country":"AU",
    "sg:address":"154 Hudson Rd",
    "sg:city":"Spotswood",
    "sg:classifiers":[
        {
            "category":"Utilities",
            "subcategory":"Natural Gas",
            "type":"Services"
        }
    ],
    "sg:phone":"+61 3 9391 3237",
    "sg:postcode":"3015",
    "sg:province":"VIC",
    "sg:tags":[
        "pressing",
        "metal",
        "stamping"
    ],
    "wof:name":"Presshop Sales & Service",
    "wof:placetype":"venue"
},
  "geometry": {"coordinates":[144.88116455100001,-37.8290557861],"type":"Point"}
}