{
  "type": "Feature",
  "properties": {
    "addr:full":"96 Landsborough Pde Golden Beach QLD 4551",
    "addr:housenumber":"96",
    "addr:postcode":"4551",
    "addr:street":"Landsborough Pde",
    "iso:country":"AU",
    "sg:address":"96 Landsborough Pde",
    "sg:city":"Golden Beach",
    "sg:classifiers":[
        {
            "category":"Professional",
            "subcategory":"Engineering",
            "type":"Services"
        }
    ],
    "sg:phone":"+61 439 647 937",
    "sg:postcode":"4551",
    "sg:province":"QLD",
    "sg:tags":[
        "diesel",
        "engineer"
    ],
    "wof:name":"Onsite Diesel Fitting",
    "wof:placetype":"venue"
},
  "geometry": {"coordinates":[153.11984252900001,-26.8223705292],"type":"Point"}
}