{
  "type": "Feature",
  "properties": {
    "addr:full":"10 Whitehaven Rd Northmead NSW 2152",
    "addr:housenumber":"10",
    "addr:postcode":"2152",
    "addr:street":"Whitehaven Rd",
    "iso:country":"AU",
    "sg:address":"10 Whitehaven Rd",
    "sg:city":"Northmead",
    "sg:classifiers":[
        {
            "category":"Government",
            "subcategory":"Department Of Motor Vehicles",
            "type":"Public Place"
        }
    ],
    "sg:phone":"+61 2 9630 3899",
    "sg:postcode":"2152",
    "sg:province":"NSW",
    "sg:tags":[
        "wholesaler",
        "mfrs",
        "accessory"
    ],
    "wof:name":"Quinn Agencies",
    "wof:placetype":"venue"
},
  "geometry": {"coordinates":[150.99472045900001,-33.7829246521],"type":"Point"}
}