{
  "type": "Feature",
  "properties": {
    "iso:country":"AU",
    "sg:address":"159 Sandy Bay Rd",
    "sg:city":"Sandy Bay",
    "sg:classifiers":[
        {
            "category":"Bars & Pubs",
            "subcategory":"Dive Bar",
            "type":"Food & Drink"
        }
    ],
    "sg:phone":"+61 3 6223 3047",
    "sg:postcode":"7005",
    "sg:province":"TAS",
    "sg:tags":[
        "knitwear",
        "retail"
    ],
    "wof:name":"Yeltuor",
    "wof:placetype":"venue"
},
  "geometry": {"coordinates":[147.32594299300001,-42.8943328857],"type":"Point"}
}