{
  "type": "Feature",
  "properties": {
    "addr:full":"4 Pilot Crt Victor Harbor SA 5211",
    "addr:housenumber":"4",
    "addr:postcode":"5211",
    "addr:street":"Pilot Crt",
    "iso:country":"AU",
    "sg:address":"4 Pilot Crt",
    "sg:city":"Victor Harbor",
    "sg:classifiers":[
        {
            "category":"Mining & Drilling",
            "type":"Manufacturing & Wholesale Goods"
        }
    ],
    "sg:phone":"+61 418 845 858",
    "sg:postcode":"5211",
    "sg:province":"SA",
    "sg:tags":[
        "concrete",
        "breaking",
        "grinding",
        "sawing"
    ],
    "wof:name":"Town & Country Concrete Cutting & Drilling P/L",
    "wof:placetype":"venue"
},
  "geometry": {"coordinates":[138.58824157699999,-35.5835647583],"type":"Point"}
}