{
  "type": "Feature",
  "properties": {
    "addr:full":"244 Pacific Hwy Charlestown NSW 2290",
    "addr:housenumber":"244",
    "addr:postcode":"2290",
    "addr:street":"Pacific Hwy",
    "iso:country":"AU",
    "sg:address":"244 Pacific Hwy",
    "sg:city":"Charlestown",
    "sg:classifiers":[
        {
            "category":"Insurance",
            "subcategory":"Hazard Insurance",
            "type":"Services"
        }
    ],
    "sg:phone":"+61 2 4942 0666",
    "sg:postcode":"2290",
    "sg:province":"NSW",
    "sg:tags":[
        "fire",
        "accident",
        "marine"
    ],
    "wof:name":"AMP General Insurance Ltd",
    "wof:placetype":"venue"
},
  "geometry": {"coordinates":[151.69729614299999,-32.9608726501],"type":"Point"}
}