{
  "type": "Feature",
  "properties": {
    "addr:full":"1 Rose St Essendon VIC 3040",
    "addr:housenumber":"1",
    "addr:postcode":"3040",
    "addr:street":"Rose St",
    "iso:country":"AU",
    "sg:address":"1 Rose St",
    "sg:city":"Essendon",
    "sg:classifiers":[
        {
            "category":"Personal",
            "subcategory":"Beauty Salon",
            "type":"Services"
        }
    ],
    "sg:phone":"+61 3 9331 3800",
    "sg:postcode":"3040",
    "sg:province":"VIC",
    "wof:name":"Beauty On Rose",
    "wof:placetype":"venue"
},
  "geometry": {"coordinates":[144.91575622600001,-37.7567634583],"type":"Point"}
}