{
  "type": "Feature",
  "properties": {
    "iso:country":"AU",
    "sg:address":"5 Larbonya Crs",
    "sg:city":"Capalaba",
    "sg:classifiers":[
        {
            "category":"Health Services",
            "subcategory":"Doctor",
            "type":"Services"
        }
    ],
    "sg:phone":"+61 7 3245 3011",
    "sg:postcode":"4157",
    "sg:province":"QLD",
    "sg:tags":[
        "medical",
        "practitioner"
    ],
    "wof:name":"Wijerathne Monica",
    "wof:placetype":"venue"
},
  "geometry": {"coordinates":[153.21090698200001,-27.5379695892],"type":"Point"}
}