{
  "type": "Feature",
  "properties": {
    "addr:full":"16 Chilvers Rd Thornleigh NSW 2120",
    "addr:housenumber":"16",
    "addr:postcode":"2120",
    "addr:street":"Chilvers Rd",
    "iso:country":"AU",
    "sg:address":"16 Chilvers Rd",
    "sg:city":"Thornleigh",
    "sg:classifiers":[
        {
            "category":"Home & Garden",
            "subcategory":"Building Materials",
            "type":"Retail Goods"
        }
    ],
    "sg:phone":"+61 2 9484 5700",
    "sg:postcode":"2120",
    "sg:province":"NSW",
    "sg:tags":[
        "lawn",
        "cutting",
        "maintenance"
    ],
    "wof:name":"Luhrmann Environment Management",
    "wof:placetype":"venue"
},
  "geometry": {"coordinates":[151.081176758,-33.7221031189],"type":"Point"}
}