{
  "type": "Feature",
  "properties": {
    "addr:full":"GPO Box 1817 Brisbane QLD 4001",
    "addr:postcode":"4001",
    "iso:country":"AU",
    "sg:address":"GPO Box 1817",
    "sg:city":"Brisbane",
    "sg:classifiers":[
        {
            "category":"Real Estate",
            "subcategory":"Surveying",
            "type":"Services"
        }
    ],
    "sg:phone":"+61 7 3343 7706",
    "sg:postcode":"4001",
    "sg:province":"QLD",
    "sg:tags":[
        "map",
        "mapping"
    ],
    "wof:name":"Mapping Sciences Institute, Australia",
    "wof:placetype":"venue"
},
  "geometry": {"coordinates":[152.88900756800001,-27.5977020264],"type":"Point"}
}