{
  "type": "Feature",
  "properties": {
    "iso:country":"AU",
    "sg:address":"220 Military Rd",
    "sg:city":"Henley Beach",
    "sg:classifiers":[
        {
            "category":"Building & Trades",
            "subcategory":"Construction",
            "type":"Services"
        }
    ],
    "sg:phone":"+61 8 8356 9636",
    "sg:postcode":"5022",
    "sg:province":"SA",
    "sg:tags":[
        "brick",
        "paving"
    ],
    "wof:name":"Henley Paving & Painting",
    "wof:placetype":"venue"
},
  "geometry": {"coordinates":[138.49484252900001,-34.9161224365],"type":"Point"}
}