{
  "type": "Feature",
  "properties": {
    "addr:full":"19 Eve St Erskineville NSW 2043",
    "addr:housenumber":"19",
    "addr:postcode":"2043",
    "addr:street":"Eve St",
    "iso:country":"AU",
    "sg:address":"19 Eve St",
    "sg:city":"Erskineville",
    "sg:classifiers":[
        {
            "category":"Organizations",
            "subcategory":"Non-profit Organization",
            "type":"Services"
        }
    ],
    "sg:phone":"+61 2 9011 6884",
    "sg:postcode":"2043",
    "sg:province":"NSW",
    "sg:tags":[
        "environmental",
        "organisation",
        "conservation"
    ],
    "wof:name":"Mineral Policy Institute",
    "wof:placetype":"venue"
},
  "geometry": {"coordinates":[151.185654,-33.904827],"type":"Point"}
}