{
  "type": "Feature",
  "properties": {
    "addr:full":"6 Georges Rd The Patch VIC 3792",
    "addr:housenumber":"6",
    "addr:postcode":"3792",
    "addr:street":"Georges Rd",
    "iso:country":"AU",
    "sg:address":"6 Georges Rd",
    "sg:city":"The Patch",
    "sg:classifiers":[
        {
            "category":"Farming",
            "subcategory":"Nursery",
            "type":"Manufacturing & Wholesale Goods"
        }
    ],
    "sg:phone":"+61 3 9756 6245",
    "sg:postcode":"3792",
    "sg:province":"VIC",
    "wof:name":"Rhodo Glen Nurseries",
    "wof:placetype":"venue"
},
  "geometry": {"coordinates":[145.39561462399999,-37.8927650452],"type":"Point"}
}