{
  "type": "Feature",
  "properties": {
    "addr:full":"164 Memorial Drv Plenty VIC 3090",
    "addr:housenumber":"164",
    "addr:postcode":"3090",
    "addr:street":"Memorial Drv",
    "iso:country":"AU",
    "sg:address":"164 Memorial Drv",
    "sg:city":"Plenty",
    "sg:classifiers":[
        {
            "category":"Building & Trades",
            "subcategory":"Construction",
            "type":"Services"
        }
    ],
    "sg:phone":"+61 3 9434 1975",
    "sg:postcode":"3090",
    "sg:province":"VIC",
    "sg:tags":[
        "contractor"
    ],
    "wof:name":"Lashford T J & L R",
    "wof:placetype":"venue"
},
  "geometry": {"coordinates":[145.10633850100001,-37.6678466797],"type":"Point"}
}