{
  "type": "Feature",
  "properties": {
    "addr:full":"388 The Entrance Rd Long Jetty NSW 2261",
    "addr:housenumber":"388",
    "addr:postcode":"2261",
    "addr:street":"The Entrance Rd",
    "iso:country":"AU",
    "sg:address":"388 The Entrance Rd",
    "sg:city":"Long Jetty",
    "sg:classifiers":[
        {
            "category":"Retail",
            "subcategory":"Auto Repair",
            "type":"Services"
        }
    ],
    "sg:phone":"+61 2 4332 7551",
    "sg:postcode":"2261",
    "sg:province":"NSW",
    "sg:tags":[
        "testing",
        "inspection",
        "motor",
        "vehicle"
    ],
    "wof:name":"Jetty Auto Repairs",
    "wof:placetype":"venue"
},
  "geometry": {"coordinates":[151.47984299999999,-33.363148],"type":"Point"}
}