{
  "type": "Feature",
  "properties": {
    "addr:full":"39 McFarlane St Keilor East VIC 3033",
    "addr:housenumber":"39",
    "addr:postcode":"3033",
    "addr:street":"Mcfarlane St",
    "iso:country":"AU",
    "sg:address":"39 McFarlane St",
    "sg:city":"Keilor East",
    "sg:classifiers":[
        {
            "category":"Home & Garden",
            "subcategory":"Garden Supply",
            "type":"Retail Goods"
        }
    ],
    "sg:phone":"+61 3 9331 1600",
    "sg:postcode":"3033",
    "sg:province":"VIC",
    "sg:tags":[
        "equipment",
        "hydroponics"
    ],
    "wof:name":"Victorian Hydroponics",
    "wof:placetype":"venue"
},
  "geometry": {"coordinates":[144.86651599999999,-37.744106],"type":"Point"}
}