{
  "type": "Feature",
  "properties": {
    "iso:country":"AU",
    "sg:address":"470 Northbourne Ave",
    "sg:city":"Dickson",
    "sg:classifiers":[
        {
            "category":"Professional",
            "subcategory":"Computer Services",
            "type":"Services"
        }
    ],
    "sg:phone":"+61 2 6229 8000",
    "sg:postcode":"2602",
    "sg:province":"ACT",
    "sg:tags":[
        "tele-communications",
        "consultant"
    ],
    "wof:name":"TransACT Communications",
    "wof:placetype":"venue"
},
  "geometry": {"coordinates":[149.133743286,-35.2525024414],"type":"Point"}
}