{
  "type": "Feature",
  "properties": {
    "addr:full":"29 Northcott Drv Kotara NSW 2289",
    "addr:housenumber":"29",
    "addr:postcode":"2289",
    "addr:street":"Northcott Drv",
    "iso:country":"AU",
    "sg:address":"29 Northcott Drv",
    "sg:city":"Kotara",
    "sg:classifiers":[
        {
            "category":"Shopping",
            "subcategory":"Gifts & Souvenirs",
            "type":"Retail Goods"
        }
    ],
    "sg:phone":"+61 2 4952 3777",
    "sg:postcode":"2289",
    "sg:province":"NSW",
    "sg:tags":[
        "print",
        "poster",
        "pictures"
    ],
    "wof:name":"Picture Framing Australia Pty Ltd",
    "wof:placetype":"venue"
},
  "geometry": {"coordinates":[151.71206665,-32.9396438599],"type":"Point"}
}