{
  "type": "Feature",
  "properties": {
    "addr:full":"Suite 6, 12 Tindale St Penrith NSW 2750",
    "addr:housenumber":"12",
    "addr:postcode":"2750",
    "addr:street":"Tindale St",
    "iso:country":"AU",
    "sg:address":"Suite 6, 12 Tindale St",
    "sg:city":"Penrith",
    "sg:classifiers":[
        {
            "category":"Banks & Credit Unions",
            "subcategory":"Investment Brokerage",
            "type":"Services"
        }
    ],
    "sg:phone":"+61 2 4722 2800",
    "sg:postcode":"2750",
    "sg:province":"NSW",
    "sg:tags":[
        "finance",
        "broker"
    ],
    "wof:name":"LendCorp Financial Group Pty Ltd",
    "wof:placetype":"venue"
},
  "geometry": {"coordinates":[150.69810485799999,-33.754650116],"type":"Point"}
}