{
  "type": "Feature",
  "properties": {
    "iso:country":"AU",
    "sg:address":"5 Fairway Crs",
    "sg:city":"Mandurah",
    "sg:classifiers":[
        {
            "category":"Building & Trades",
            "subcategory":"Cleaning & Sanitation",
            "type":"Services"
        }
    ],
    "sg:phone":"+61 8 9581 6635",
    "sg:postcode":"6210",
    "sg:province":"WA",
    "sg:tags":[
        "window"
    ],
    "wof:name":"The Window Cleaning Specialist",
    "wof:placetype":"venue"
},
  "geometry": {"coordinates":[115.784737,-32.509258],"type":"Point"}
}