{
  "type": "Feature",
  "properties": {
    "addr:full":"226a Bridge Rd Pooraka SA 5095",
    "addr:housenumber":"226a",
    "addr:postcode":"5095",
    "addr:street":"Bridge Rd",
    "iso:country":"AU",
    "sg:address":"226a Bridge Rd",
    "sg:city":"Pooraka",
    "sg:classifiers":[
        {
            "category":"Social Services",
            "subcategory":"Adult Care",
            "type":"Services"
        }
    ],
    "sg:phone":"+61 8 8260 2724",
    "sg:postcode":"5095",
    "sg:province":"SA",
    "sg:tags":[
        "towing"
    ],
    "wof:name":"Ingle Farm Towing Services",
    "wof:placetype":"venue"
},
  "geometry": {"coordinates":[138.63853454599999,-34.820766449],"type":"Point"}
}