{
  "type": "Feature",
  "properties": {
    "addr:full":"Ogg Rd Murrumba Downs QLD 4503",
    "addr:postcode":"4503",
    "addr:street":"Ogg Rd",
    "iso:country":"AU",
    "sg:address":"Ogg Rd",
    "sg:city":"Murrumba Downs",
    "sg:classifiers":[
        {
            "category":"Education",
            "subcategory":"School",
            "type":"Public Place"
        }
    ],
    "sg:phone":"+61 7 3480 9139",
    "sg:postcode":"4503",
    "sg:province":"QLD",
    "sg:tags":[
        "state",
        "except",
        "nsw"
    ],
    "wof:name":"Undurba Preschool",
    "wof:placetype":"venue"
},
  "geometry": {"coordinates":[153.00868225100001,-27.2627944946],"type":"Point"}
}