{
  "type": "Feature",
  "properties": {
    "addr:full":"Ocean Drv Mudjimba Beach QLD 4564",
    "addr:postcode":"4564",
    "addr:street":"Ocean Drv Mudjimba",
    "iso:country":"AU",
    "sg:address":"Ocean Drv",
    "sg:city":"Mudjimba Beach",
    "sg:classifiers":[
        {
            "category":"Personal",
            "subcategory":"Beauty Salon",
            "type":"Services"
        }
    ],
    "sg:phone":"+61 7 5450 9565",
    "sg:postcode":"4564",
    "sg:province":"QLD",
    "wof:name":"Lagoon Day Spa",
    "wof:placetype":"venue"
},
  "geometry": {"coordinates":[153.085647583,-26.6150798798],"type":"Point"}
}