{
  "type": "Feature",
  "properties": {
    "addr:full":"52a Phillipson St Wangaratta VIC 3677",
    "addr:housenumber":"52a",
    "addr:postcode":"3677",
    "addr:street":"Phillipson St",
    "iso:country":"AU",
    "sg:address":"52a Phillipson St",
    "sg:city":"Wangaratta",
    "sg:classifiers":[
        {
            "category":"Shopping",
            "subcategory":"Crafts & Fabrics",
            "type":"Retail Goods"
        }
    ],
    "sg:phone":"+61 3 5722 4919",
    "sg:postcode":"3677",
    "sg:province":"VIC",
    "sg:tags":[
        "supply"
    ],
    "wof:name":"Heirloom Creations",
    "wof:placetype":"venue"
},
  "geometry": {"coordinates":[146.30506897000001,-36.3531074524],"type":"Point"}
}