{
  "type": "Feature",
  "properties": {
    "addr:full":"260 Oxley Ave Margate QLD 4019",
    "addr:housenumber":"260",
    "addr:postcode":"4019",
    "addr:street":"Oxley Ave",
    "iso:country":"AU",
    "sg:address":"260 Oxley Ave",
    "sg:city":"Margate",
    "sg:classifiers":[
        {
            "category":"Real Estate",
            "subcategory":"Real Estate Agent",
            "type":"Services"
        }
    ],
    "sg:phone":"+61 7 3883 4877",
    "sg:postcode":"4019",
    "sg:province":"QLD",
    "wof:name":"Ray White Margate",
    "wof:placetype":"venue"
},
  "geometry": {"coordinates":[153.10679626500001,-27.2433185577],"type":"Point"}
}