{
  "type": "Feature",
  "properties": {
    "iso:country":"AU",
    "sg:address":"291 Johnston St",
    "sg:city":"Abbotsford",
    "sg:classifiers":[
        {
            "category":"Health Services",
            "subcategory":"Health Practitioner",
            "type":"Services"
        }
    ],
    "sg:phone":"+61 3 9417 1492",
    "sg:postcode":"3067",
    "sg:province":"VIC",
    "sg:tags":[
        "herbalist"
    ],
    "wof:name":"David Yao Chi Guan Chinese Medical Centre",
    "wof:placetype":"venue"
},
  "geometry": {"coordinates":[144.99621582,-37.8002510071],"type":"Point"}
}