{
  "type": "Feature",
  "properties": {
    "addr:full":"Shop 1/ 271 Newbridge Rd Chipping Norton NSW 2170",
    "addr:housenumber":"shop 1 / 271",
    "addr:postcode":"2170",
    "addr:street":"Newbridge Rd",
    "iso:country":"AU",
    "sg:address":"Shop 1/ 271 Newbridge Rd",
    "sg:city":"Chipping Norton",
    "sg:classifiers":[
        {
            "category":"Deli",
            "type":"Food & Drink"
        }
    ],
    "sg:phone":"+61 2 9734 0769",
    "sg:postcode":"2170",
    "sg:province":"NSW",
    "sg:tags":[
        "delicatessen"
    ],
    "wof:name":"Nonna's Gourmet Sausages & Deli Pty Ltd",
    "wof:placetype":"venue"
},
  "geometry": {"coordinates":[150.948455811,-33.9289588928],"type":"Point"}
}