{
  "type": "Feature",
  "properties": {
    "iso:country":"AU",
    "sg:address":"49 Highett St",
    "sg:city":"Mansfield",
    "sg:classifiers":[
        {
            "category":"Health Services",
            "subcategory":"Doctor",
            "type":"Services"
        }
    ],
    "sg:phone":"+61 3 5775 2166",
    "sg:postcode":"3722",
    "sg:province":"VIC",
    "sg:tags":[
        "medical",
        "practitioner"
    ],
    "wof:name":"Mansfield Medical Clinic",
    "wof:placetype":"venue"
},
  "geometry": {"coordinates":[146.08682250999999,-37.0571975708],"type":"Point"}
}