{
  "type": "Feature",
  "properties": {
    "addr:full":"The Peoples Medical Centre, Cnr Shellharbour & Lak Warilla NSW 2528",
    "addr:postcode":"2528",
    "addr:street":"Cnr Shellharbour",
    "iso:country":"AU",
    "sg:address":"The Peoples Medical Centre, Cnr Shellharbour & Lak",
    "sg:city":"Warilla",
    "sg:classifiers":[
        {
            "category":"Health Services",
            "subcategory":"Doctor",
            "type":"Services"
        }
    ],
    "sg:phone":"+61 2 4296 8888",
    "sg:postcode":"2528",
    "sg:province":"NSW",
    "sg:tags":[
        "medical",
        "practitioner"
    ],
    "wof:name":"Perrott Margaret Dr",
    "wof:placetype":"venue"
},
  "geometry": {"coordinates":[150.86082458499999,-34.5494003296],"type":"Point"}
}