{
  "type": "Feature",
  "properties": {
    "iso:country":"AU",
    "sg:address":"43A Union St",
    "sg:city":"Armadale",
    "sg:classifiers":[
        {
            "category":"Sports & Exercise",
            "subcategory":"Sports Center",
            "type":"Entertainment"
        }
    ],
    "sg:phone":"+61 3 9509 2044",
    "sg:postcode":"3143",
    "sg:province":"VIC",
    "sg:tags":[
        "coach",
        "tennis"
    ],
    "wof:name":"Victorian Tennis Academy",
    "wof:placetype":"venue"
},
  "geometry": {"coordinates":[145.02279663100001,-37.8586616516],"type":"Point"}
}