{
  "type": "Feature",
  "properties": {
    "iso:country":"AU",
    "sg:address":"Corporate Park 49- 53 Dalrymple Rd",
    "sg:city":"Garbutt",
    "sg:classifiers":[
        {
            "category":"Manufacturing",
            "subcategory":"Tools & Machinery",
            "type":"Manufacturing & Wholesale Goods"
        }
    ],
    "sg:phone":"+61 7 4771 8000",
    "sg:postcode":"4814",
    "sg:province":"QLD",
    "sg:tags":[
        "earth",
        "excavating",
        "moving",
        "equipment"
    ],
    "wof:name":"Bobcat Townsville",
    "wof:placetype":"venue"
},
  "geometry": {"coordinates":[146.777084,-19.268442],"type":"Point"}
}