{
  "type": "Feature",
  "properties": {
    "addr:full":"1 United Rd Ashmore QLD 4214",
    "addr:housenumber":"1",
    "addr:postcode":"4214",
    "addr:street":"United Rd",
    "iso:country":"AU",
    "sg:address":"1 United Rd",
    "sg:city":"Ashmore",
    "sg:classifiers":[
        {
            "category":"Home & Garden",
            "subcategory":"Building Materials",
            "type":"Retail Goods"
        }
    ],
    "sg:phone":"+61 7 5539 1522",
    "sg:postcode":"4214",
    "sg:province":"QLD",
    "sg:tags":[
        "supply"
    ],
    "wof:name":"CTS Wardrobes",
    "wof:placetype":"venue"
},
  "geometry": {"coordinates":[153.381958008,-27.9787368774],"type":"Point"}
}