{
  "type": "Feature",
  "properties": {
    "iso:country":"AU",
    "sg:address":"Cnr Primrose & Combined Sts",
    "sg:city":"Wingham",
    "sg:classifiers":[
        {
            "category":"Food & Beverages",
            "subcategory":"Liquor & Beverages",
            "type":"Retail Goods"
        }
    ],
    "sg:phone":"+61 2 6553 4970",
    "sg:postcode":"2429",
    "sg:province":"NSW",
    "sg:tags":[
        "store"
    ],
    "wof:name":"Cellarbrations",
    "wof:placetype":"venue"
},
  "geometry": {"coordinates":[152.371307,-31.871202],"type":"Point"}
}