{
  "type": "Feature",
  "properties": {
    "addr:full":"9 Cardiff Rd New Lambton NSW 2305",
    "addr:housenumber":"9",
    "addr:postcode":"2305",
    "addr:street":"Cardiff Rd",
    "iso:country":"AU",
    "sg:address":"9 Cardiff Rd",
    "sg:city":"New Lambton",
    "sg:classifiers":[
        {
            "category":"Structure",
            "subcategory":"Office Building",
            "type":"Public Place"
        }
    ],
    "sg:phone":"+61 2 4957 2566",
    "sg:postcode":"2305",
    "sg:province":"NSW",
    "sg:tags":[
        "slater",
        "tiler",
        "roof"
    ],
    "wof:name":"Blackbutt Roof Tiling Pty Ltd",
    "wof:placetype":"venue"
},
  "geometry": {"coordinates":[151.68911700000001,-32.93589],"type":"Point"}
}