{
  "type": "Feature",
  "properties": {
    "iso:country":"AU",
    "sg:address":"79 St Albans Rd",
    "sg:city":"Wiseman&#039;s Ferry",
    "sg:classifiers":[
        {
            "category":"Farming",
            "subcategory":"Fish & Marine Products",
            "type":"Manufacturing & Wholesale Goods"
        }
    ],
    "sg:phone":"+61 407 664 756",
    "sg:postcode":"2775",
    "sg:province":"NSW",
    "sg:tags":[
        "fisherman"
    ],
    "wof:name":"Troy Ireland",
    "wof:placetype":"venue"
},
  "geometry": {"coordinates":[151.004959106,-33.3073310852],"type":"Point"}
}