{
  "type": "Feature",
  "properties": {
    "iso:country":"AU",
    "sg:address":"16 Bushlark Pl",
    "sg:city":"Claremont Meadows",
    "sg:classifiers":[
        {
            "category":"Retail",
            "subcategory":"Storage",
            "type":"Services"
        }
    ],
    "sg:phone":"+61 2 9833 7574",
    "sg:postcode":"2747",
    "sg:province":"NSW",
    "sg:tags":[
        "removal",
        "furniture"
    ],
    "wof:name":"All Districts Removals",
    "wof:placetype":"venue"
},
  "geometry": {"coordinates":[150.74996948200001,-33.7761917114],"type":"Point"}
}