{
  "type": "Feature",
  "properties": {
    "addr:full":"54 Barney St Armidale NSW 2350",
    "addr:housenumber":"54",
    "addr:postcode":"2350",
    "addr:street":"Barney St",
    "iso:country":"AU",
    "sg:address":"54 Barney St",
    "sg:city":"Armidale",
    "sg:classifiers":[
        {
            "category":"Education",
            "subcategory":"Dance Studio",
            "type":"Public Place"
        }
    ],
    "sg:phone":"+61 2 6772 6417",
    "sg:postcode":"2350",
    "sg:province":"NSW",
    "sg:tags":[
        "venue",
        "tuition"
    ],
    "wof:name":"Tutu, Tap & Turn Dance Studio",
    "wof:placetype":"venue"
},
  "geometry": {"coordinates":[151.66925048799999,-30.5178546906],"type":"Point"}
}