{
  "type": "Feature",
  "properties": {
    "addr:full":"4 Nelson St Glenroy VIC 3046",
    "addr:housenumber":"4",
    "addr:postcode":"3046",
    "addr:street":"Nelson St",
    "iso:country":"AU",
    "sg:address":"4 Nelson St",
    "sg:city":"Glenroy",
    "sg:classifiers":[
        {
            "category":"Home & Garden",
            "subcategory":"Building Materials",
            "type":"Retail Goods"
        }
    ],
    "sg:phone":"+61 3 9306 9477",
    "sg:postcode":"3046",
    "sg:province":"VIC",
    "sg:tags":[
        "fencing"
    ],
    "wof:name":"Broadmeadows Wire Fence & Gate Co",
    "wof:placetype":"venue"
},
  "geometry": {"coordinates":[144.91792297399999,-37.7042007446],"type":"Point"}
}