{
  "type": "Feature",
  "properties": {
    "addr:full":"Level 1 128 Great North Rd Five Dock NSW 2046",
    "addr:housenumber":"128",
    "addr:postcode":"2046",
    "addr:street":"Great North Rd",
    "iso:country":"AU",
    "sg:address":"Level 1 128 Great North Rd",
    "sg:city":"Five Dock",
    "sg:classifiers":[
        {
            "category":"Professional",
            "subcategory":"Accounting & Tax Preparation",
            "type":"Services"
        }
    ],
    "sg:phone":"+61 2 9713 9213",
    "sg:postcode":"2046",
    "sg:province":"NSW",
    "sg:tags":[
        "accountant",
        "auditor"
    ],
    "wof:name":"Angelopoulos & Michael Accountants",
    "wof:placetype":"venue"
},
  "geometry": {"coordinates":[151.13034099999999,-33.865906],"type":"Point"}
}