{
  "type": "Feature",
  "properties": {
    "addr:full":"Wilpena Rd Hawker SA 5434",
    "addr:postcode":"5434",
    "addr:street":"Wilpena Rd",
    "iso:country":"AU",
    "sg:address":"Wilpena Rd",
    "sg:city":"Hawker",
    "sg:classifiers":[
        {
            "category":"Autos & Motor Vehicles",
            "subcategory":"Fuel & Gas Station",
            "type":"Retail Goods"
        }
    ],
    "sg:phone":"+61 8 8648 4014",
    "sg:postcode":"5434",
    "sg:province":"SA",
    "wof:name":"Hawker Motors",
    "wof:placetype":"venue"
},
  "geometry": {"coordinates":[138.42129516599999,-31.8883209229],"type":"Point"}
}