{
  "type": "Feature",
  "properties": {
    "addr:full":"12B Adams La Berwick VIC 3806",
    "addr:housenumber":"12b",
    "addr:postcode":"3806",
    "addr:street":"Adams La",
    "iso:country":"AU",
    "sg:address":"12B Adams La",
    "sg:city":"Berwick",
    "sg:classifiers":[
        {
            "category":"Ice Cream",
            "type":"Food & Drink"
        }
    ],
    "sg:phone":"+61 3 9769 4495",
    "sg:postcode":"3806",
    "sg:province":"VIC",
    "sg:tags":[
        "retail"
    ],
    "wof:name":"Cold Rock Ice Creamery",
    "wof:placetype":"venue"
},
  "geometry": {"coordinates":[145.34489440900001,-38.0314025879],"type":"Point"}
}