{
  "type": "Feature",
  "properties": {
    "addr:full":"PO Box 1613 Kingscliff NSW 2487",
    "addr:postcode":"2487",
    "iso:country":"AU",
    "sg:address":"PO Box 1613",
    "sg:city":"Kingscliff",
    "sg:classifiers":[
        {
            "category":"Arena",
            "subcategory":"Sports Club",
            "type":"Entertainment"
        }
    ],
    "sg:phone":"+61 2 6674 9888",
    "sg:postcode":"2487",
    "sg:province":"NSW",
    "sg:tags":[
        "organisation",
        "sporting"
    ],
    "wof:name":"Surfing Australia",
    "wof:placetype":"venue"
},
  "geometry": {"coordinates":[153.577957153,-28.2594795227],"type":"Point"}
}