{
  "type": "Feature",
  "properties": {
    "addr:full":"88 Duporth Ave Maroochydore QLD 4558",
    "addr:housenumber":"88",
    "addr:postcode":"4558",
    "addr:street":"Duporth Ave",
    "iso:country":"AU",
    "sg:address":"88 Duporth Ave",
    "sg:city":"Maroochydore",
    "sg:classifiers":[
        {
            "category":"Health Services",
            "subcategory":"Health Practitioner",
            "type":"Services"
        }
    ],
    "sg:phone":"+61 7 5443 7277",
    "sg:postcode":"4558",
    "sg:province":"QLD",
    "sg:tags":[
        "psychologist"
    ],
    "wof:name":"Holland Linda",
    "wof:placetype":"venue"
},
  "geometry": {"coordinates":[153.08900451700001,-26.6493167877],"type":"Point"}
}