{
  "type": "Feature",
  "properties": {
    "addr:full":"5 McDougall Crs Emu Park QLD 4702",
    "addr:housenumber":"5",
    "addr:postcode":"4702",
    "addr:street":"Mcdougall Crs",
    "iso:country":"AU",
    "sg:address":"5 McDougall Crs",
    "sg:city":"Emu Park",
    "sg:classifiers":[
        {
            "category":"Building & Trades",
            "subcategory":"Plumbing",
            "type":"Services"
        }
    ],
    "sg:phone":"+61 7 4938 7590",
    "sg:postcode":"4702",
    "sg:province":"QLD",
    "sg:tags":[
        "plumber",
        "gasfitters"
    ],
    "wof:name":"Turners Plumbing & Roofing",
    "wof:placetype":"venue"
},
  "geometry": {"coordinates":[150.56675720199999,-23.3882160187],"type":"Point"}
}