{
  "type": "Feature",
  "properties": {
    "addr:full":"239 Beaufort St Perth WA 6000",
    "addr:housenumber":"239",
    "addr:postcode":"6000",
    "addr:street":"Beaufort St",
    "iso:country":"AU",
    "sg:address":"239 Beaufort St",
    "sg:city":"Perth",
    "sg:classifiers":[
        {
            "category":"Social Services",
            "subcategory":"Retirement Home",
            "type":"Services"
        }
    ],
    "sg:phone":"+61 8 9227 8099",
    "sg:postcode":"6000",
    "sg:province":"WA",
    "sg:tags":[
        "environmental",
        "consultant",
        "pollution"
    ],
    "wof:name":"Mscience Pty Ltd",
    "wof:placetype":"venue"
},
  "geometry": {"coordinates":[115.864562988,-31.9462280273],"type":"Point"}
}