{
  "type": "Feature",
  "properties": {
    "iso:country":"AU",
    "sg:address":"170 Walker St",
    "sg:city":"Bundaberg",
    "sg:classifiers":[
        {
            "category":"Home & Garden",
            "subcategory":"Carpets & Floor Coverings",
            "type":"Retail Goods"
        }
    ],
    "sg:phone":"+61 7 4152 1317",
    "sg:postcode":"4670",
    "sg:province":"QLD",
    "sg:tags":[
        "tile",
        "wall",
        "layer"
    ],
    "wof:name":"Annan B.J.",
    "wof:placetype":"venue"
},
  "geometry": {"coordinates":[152.38800048799999,-24.8850784302],"type":"Point"}
}