{
  "type": "Feature",
  "properties": {
    "addr:full":"73 Victoria St Taree NSW 2430",
    "addr:housenumber":"73",
    "addr:postcode":"2430",
    "addr:street":"Victoria St",
    "iso:country":"AU",
    "sg:address":"73 Victoria St",
    "sg:city":"Taree",
    "sg:classifiers":[
        {
            "category":"Fast Food",
            "type":"Food & Drink"
        }
    ],
    "sg:phone":"+61 2 6552 2465",
    "sg:postcode":"2430",
    "sg:province":"NSW",
    "sg:tags":[
        "away",
        "take"
    ],
    "wof:name":"East Court Chinese Restaurant",
    "wof:placetype":"venue"
},
  "geometry": {"coordinates":[152.46452300000001,-31.911163],"type":"Point"}
}