{
  "type": "Feature",
  "properties": {
    "iso:country":"AU",
    "sg:address":"Hope Rd Cnr Bibra Drive Bibra Lake",
    "sg:city":"Bibra Lake",
    "sg:classifiers":[
        {
            "category":"Education",
            "subcategory":"School",
            "type":"Public Place"
        }
    ],
    "sg:phone":"+61 8 9417 4060",
    "sg:postcode":"6163",
    "sg:province":"WA",
    "wof:name":"Blue Gum Montessori School",
    "wof:placetype":"venue"
},
  "geometry": {"coordinates":[115.839577,-32.085754],"type":"Point"}
}