{
  "type": "Feature",
  "properties": {
    "addr:full":"1 Hudson Pl Mulgrave NSW 2756",
    "addr:housenumber":"1",
    "addr:postcode":"2756",
    "addr:street":"Hudson Pl",
    "iso:country":"AU",
    "sg:address":"1 Hudson Pl",
    "sg:city":"Mulgrave",
    "sg:classifiers":[
        {
            "category":"Manufacturing",
            "subcategory":"Metals",
            "type":"Manufacturing & Wholesale Goods"
        }
    ],
    "sg:phone":"+61 2 4577 7905",
    "sg:postcode":"2756",
    "sg:province":"NSW",
    "sg:tags":[
        "steel",
        "fabricator",
        "mfrs"
    ],
    "wof:name":"Hawkesbury Steel",
    "wof:placetype":"venue"
},
  "geometry": {"coordinates":[150.83265685999999,-33.6270561218],"type":"Point"}
}