{
  "type": "Feature",
  "properties": {
    "iso:country":"AU",
    "sg:address":"8 Minto Ave",
    "sg:city":"Long Jetty",
    "sg:classifiers":[
        {
            "category":"Shopping",
            "subcategory":"Crafts & Fabrics",
            "type":"Retail Goods"
        }
    ],
    "sg:phone":"+61 2 4332 1370",
    "sg:postcode":"2261",
    "sg:province":"NSW",
    "sg:tags":[
        "synthetic",
        "canvas",
        "product"
    ],
    "wof:name":"Long Jetty Canvas",
    "wof:placetype":"venue"
},
  "geometry": {"coordinates":[151.478134,-33.363724],"type":"Point"}
}