{
  "type": "Feature",
  "properties": {
    "addr:full":"33 Winterton Rd Clayton VIC 3168",
    "addr:housenumber":"33",
    "addr:postcode":"3168",
    "addr:street":"Winterton Rd",
    "iso:country":"AU",
    "sg:address":"33 Winterton Rd",
    "sg:city":"Clayton",
    "sg:classifiers":[
        {
            "category":"Utilities",
            "type":"Services"
        }
    ],
    "sg:phone":"+61 3 9544 1166",
    "sg:postcode":"3168",
    "sg:province":"VIC",
    "sg:tags":[
        "refrigeration",
        "industrial",
        "commercial",
        "retail"
    ],
    "wof:name":"Thermfresh",
    "wof:placetype":"venue"
},
  "geometry": {"coordinates":[145.13479614299999,-37.924118042],"type":"Point"}
}