{
  "type": "Feature",
  "properties": {
    "addr:full":"U2/ 112 Condamine St Balgowlah NSW 2093",
    "addr:housenumber":"112",
    "addr:postcode":"2093",
    "addr:street":"U2 /;Condamine St",
    "iso:country":"AU",
    "sg:address":"U2/ 112 Condamine St",
    "sg:city":"Balgowlah",
    "sg:classifiers":[
        {
            "category":"Health Services",
            "subcategory":"Health Practitioner",
            "type":"Services"
        }
    ],
    "sg:phone":"+61 2 9948 9088",
    "sg:postcode":"2093",
    "sg:province":"NSW",
    "sg:tags":[
        "psychologist"
    ],
    "wof:name":"Noelle Christopher - Psychologist",
    "wof:placetype":"venue"
},
  "geometry": {"coordinates":[151.26504516599999,-33.7942390442],"type":"Point"}
}