{
  "type": "Feature",
  "properties": {
    "iso:country":"AU",
    "sg:address":"147 Elizabeth St",
    "sg:city":"Coochiemudlo Island",
    "sg:classifiers":[
        {
            "category":"Real Estate",
            "subcategory":"Real Estate Agent",
            "type":"Services"
        }
    ],
    "sg:phone":"+61 7 3207 8006",
    "sg:postcode":"4184",
    "sg:province":"QLD",
    "wof:name":"Baywaters Realty",
    "wof:placetype":"venue"
},
  "geometry": {"coordinates":[153.33282470699999,-27.5711116791],"type":"Point"}
}