{
  "type": "Feature",
  "properties": {
    "iso:country":"AU",
    "sg:address":"Prospect St",
    "sg:city":"Eton",
    "sg:classifiers":[
        {
            "category":"Education",
            "subcategory":"School",
            "type":"Public Place"
        }
    ],
    "sg:phone":"+61 7 4954 2111",
    "sg:postcode":"4741",
    "sg:province":"QLD",
    "sg:tags":[
        "state",
        "except",
        "nsw"
    ],
    "wof:name":"Eton Primary School",
    "wof:placetype":"venue"
},
  "geometry": {"coordinates":[148.976257,-21.263613],"type":"Point"}
}