{
  "type": "Feature",
  "properties": {
    "addr:full":"Shop T11, Restaurant Court, Garden City, Riseley St Booragoon WA 6154",
    "addr:postcode":"6154",
    "addr:street":"Court;Riseley St",
    "iso:country":"AU",
    "sg:address":"Shop T11, Restaurant Court, Garden City, Riseley St",
    "sg:city":"Booragoon",
    "sg:classifiers":[
        {
            "category":"Food & Beverages",
            "subcategory":"Bakery",
            "type":"Retail Goods"
        }
    ],
    "sg:phone":"+61 8 9316 2660",
    "sg:postcode":"6154",
    "sg:province":"WA",
    "sg:tags":[
        "baker"
    ],
    "wof:name":"Muffin Break",
    "wof:placetype":"venue"
},
  "geometry": {"coordinates":[115.837959,-32.0364],"type":"Point"}
}