{
  "type": "Feature",
  "properties": {
    "addr:full":"12 Emmett Dr (End of Middle Street) Cleveland QLD 4163",
    "addr:housenumber":"12",
    "addr:postcode":"4163",
    "addr:street":"Emmett Dr End;Street",
    "iso:country":"AU",
    "sg:address":"12 Emmett Dr",
    "sg:city":"(End of Middle Street) Cleveland",
    "sg:classifiers":[
        {
            "category":"Ferry",
            "type":"Transportation"
        }
    ],
    "sg:phone":"+61 7 3488 9777",
    "sg:postcode":"4163",
    "sg:province":"QLD",
    "sg:tags":[
        "barge"
    ],
    "wof:name":"Sea Stradbroke Pty Ltd",
    "wof:placetype":"venue"
},
  "geometry": {"coordinates":[153.283935547,-27.5273799896],"type":"Point"}
}