{
  "type": "Feature",
  "properties": {
    "addr:full":"Grant St Cranbourne VIC 3977",
    "addr:postcode":"3977",
    "addr:street":"Grant St",
    "iso:country":"AU",
    "sg:address":"Grant St",
    "sg:city":"Cranbourne",
    "sg:classifiers":[
        {
            "category":"Sports & Exercise",
            "subcategory":"Playing Field",
            "type":"Entertainment"
        }
    ],
    "sg:phone":"+61 3 5996 3233",
    "sg:postcode":"3977",
    "sg:province":"VIC",
    "sg:tags":[
        "gaming",
        "venue"
    ],
    "wof:name":"Trios Tabaret",
    "wof:placetype":"venue"
},
  "geometry": {"coordinates":[145.27944946299999,-38.113079071],"type":"Point"}
}