{
  "type": "Feature",
  "properties": {
    "addr:full":"Lot 79 Gale Rd Evanston SA 5116",
    "addr:postcode":"5116",
    "addr:street":"Gale Rd",
    "iso:country":"AU",
    "sg:address":"Lot 79 Gale Rd",
    "sg:city":"Evanston",
    "sg:classifiers":[
        {
            "category":"Farming",
            "subcategory":"Farm & Veterinary Services",
            "type":"Manufacturing & Wholesale Goods"
        }
    ],
    "sg:phone":"+61 429 696 267",
    "sg:postcode":"5116",
    "sg:province":"SA",
    "sg:tags":[
        "irrigation",
        "reticulation",
        "system"
    ],
    "wof:name":"JLC Irrigation",
    "wof:placetype":"venue"
},
  "geometry": {"coordinates":[138.72439575199999,-34.6576843262],"type":"Point"}
}