{
  "type": "Feature",
  "properties": {
    "addr:full":"65 High St Berwick VIC 3806",
    "addr:housenumber":"65",
    "addr:postcode":"3806",
    "addr:street":"High St",
    "iso:country":"AU",
    "sg:address":"65 High St",
    "sg:city":"Berwick",
    "sg:classifiers":[
        {
            "category":"Food & Beverages",
            "subcategory":"Liquor & Beverages",
            "type":"Retail Goods"
        }
    ],
    "sg:phone":"+61 3 9769 4777",
    "sg:postcode":"3806",
    "sg:province":"VIC",
    "sg:tags":[
        "store"
    ],
    "wof:name":"Let's Unwine Berwick",
    "wof:placetype":"venue"
},
  "geometry": {"coordinates":[145.34713745100001,-38.0310134888],"type":"Point"}
}