{
  "type": "Feature",
  "properties": {
    "addr:full":"37 Prospect Rd Garden Suburb NSW 2289",
    "addr:housenumber":"37",
    "addr:postcode":"2289",
    "addr:street":"Prospect Rd",
    "iso:country":"AU",
    "sg:address":"37 Prospect Rd",
    "sg:city":"Garden Suburb",
    "sg:classifiers":[
        {
            "category":"Building & Trades",
            "subcategory":"Plumbing",
            "type":"Services"
        }
    ],
    "sg:phone":"+61 2 4943 4316",
    "sg:postcode":"2289",
    "sg:province":"NSW",
    "sg:tags":[
        "plumber",
        "gasfitters"
    ],
    "wof:name":"Johnston G C & M A",
    "wof:placetype":"venue"
},
  "geometry": {"coordinates":[151.68000793499999,-32.9442596436],"type":"Point"}
}