{
  "type": "Feature",
  "properties": {
    "addr:full":"21 William St Orange NSW 2800",
    "addr:housenumber":"21",
    "addr:postcode":"2800",
    "addr:street":"William St",
    "iso:country":"AU",
    "sg:address":"21 William St",
    "sg:city":"Orange",
    "sg:classifiers":[
        {
            "category":"Professional",
            "subcategory":"Engineering",
            "type":"Services"
        }
    ],
    "sg:phone":"+61 2 6362 6689",
    "sg:postcode":"2800",
    "sg:province":"NSW",
    "sg:tags":[
        "diesel",
        "engineer"
    ],
    "wof:name":"Central Diesel Co",
    "wof:placetype":"venue"
},
  "geometry": {"coordinates":[149.10606384299999,-33.2831459045],"type":"Point"}
}