{
  "type": "Feature",
  "properties": {
    "addr:full":"522 Parramatta Rd Petersham NSW 2049",
    "addr:housenumber":"522",
    "addr:postcode":"2049",
    "addr:street":"Parramatta Rd",
    "iso:country":"AU",
    "sg:address":"522 Parramatta Rd",
    "sg:city":"Petersham",
    "sg:classifiers":[
        {
            "category":"Professional",
            "subcategory":"Printing & Photocopies",
            "type":"Services"
        }
    ],
    "sg:phone":"+61 2 9560 3689",
    "sg:postcode":"2049",
    "sg:province":"NSW",
    "sg:tags":[
        "photocopying"
    ],
    "wof:name":"Snap Printing",
    "wof:placetype":"venue"
},
  "geometry": {"coordinates":[151.156723,-33.888584],"type":"Point"}
}