{
  "type": "Feature",
  "properties": {
    "addr:full":"81 Norcal Rd Nunawading VIC 3131",
    "addr:housenumber":"81",
    "addr:postcode":"3131",
    "addr:street":"Norcal Rd",
    "iso:country":"AU",
    "sg:address":"81 Norcal Rd",
    "sg:city":"Nunawading",
    "sg:classifiers":[
        {
            "category":"Banks & Credit Unions",
            "subcategory":"Bank",
            "type":"Services"
        }
    ],
    "sg:phone":"+61 3 8878 3500",
    "sg:postcode":"3131",
    "sg:province":"VIC",
    "sg:tags":[
        "line",
        "marking",
        "road"
    ],
    "wof:name":"Road Signs & Marking Supplies Pty Ltd",
    "wof:placetype":"venue"
},
  "geometry": {"coordinates":[145.181182861,-37.8213806152],"type":"Point"}
}