{
  "type": "Feature",
  "properties": {
    "iso:country":"AU",
    "sg:address":"172 Cowper St",
    "sg:city":"Warrawong",
    "sg:classifiers":[
        {
            "category":"Professional",
            "subcategory":"Accounting & Tax Preparation",
            "type":"Services"
        }
    ],
    "sg:phone":"+61 2 4275 1055",
    "sg:postcode":"2502",
    "sg:province":"NSW",
    "sg:tags":[
        "consultant",
        "taxation"
    ],
    "wof:name":"Pellegrino Perri & Associates",
    "wof:placetype":"venue"
},
  "geometry": {"coordinates":[150.888992,-34.485126],"type":"Point"}
}