{
  "type": "Feature",
  "properties": {
    "iso:country":"AU",
    "sg:address":"208 Buchan St",
    "sg:city":"Cairns",
    "sg:classifiers":[
        {
            "category":"Professional",
            "subcategory":"Testing Lab",
            "type":"Services"
        }
    ],
    "sg:phone":"+61 7 4031 2775",
    "sg:postcode":"4870",
    "sg:province":"QLD",
    "sg:tags":[
        "inspection"
    ],
    "wof:name":"C.M.G. Consulting Engineers Pty Ltd",
    "wof:placetype":"venue"
},
  "geometry": {"coordinates":[145.76148986800001,-16.9297084808],"type":"Point"}
}