{
  "type": "Feature",
  "properties": {
    "addr:full":"PO Box 272 Northcote VIC 3070",
    "addr:postcode":"3070",
    "iso:country":"AU",
    "sg:address":"PO Box 272",
    "sg:city":"Northcote",
    "sg:classifiers":[
        {
            "category":"Education",
            "subcategory":"University",
            "type":"Public Place"
        }
    ],
    "sg:phone":"+61 3 9432 5688",
    "sg:postcode":"3070",
    "sg:province":"VIC",
    "sg:tags":[
        "educational",
        "organisation",
        "cultural"
    ],
    "wof:name":"Dante Alighieri Society",
    "wof:placetype":"venue"
},
  "geometry": {"coordinates":[144.99939000000001,-37.772289],"type":"Point"}
}