{
  "type": "Feature",
  "properties": {
    "iso:country":"AU",
    "sg:address":"1 Bourn Pl",
    "sg:city":"Beverley",
    "sg:classifiers":[
        {
            "category":"Wholesale",
            "subcategory":"Construction Materials",
            "type":"Manufacturing & Wholesale Goods"
        }
    ],
    "sg:phone":"+61 8 8240 1555",
    "sg:postcode":"5009",
    "sg:province":"SA",
    "sg:tags":[
        "protective",
        "coating"
    ],
    "wof:name":"Teflon Coatings",
    "wof:placetype":"venue"
},
  "geometry": {"coordinates":[138.54153442399999,-34.8939666748],"type":"Point"}
}