{
  "type": "Feature",
  "properties": {
    "iso:country":"AU",
    "sg:address":"14 Beresford Ave",
    "sg:city":"Greenacre",
    "sg:classifiers":[
        {
            "category":"Professional",
            "type":"Services"
        }
    ],
    "sg:phone":"+61 2 9790 5589",
    "sg:postcode":"2190",
    "sg:province":"NSW",
    "sg:tags":[
        "spray",
        "painting"
    ],
    "wof:name":"Power Poly Australia Pty Ltd",
    "wof:placetype":"venue"
},
  "geometry": {"coordinates":[151.039764,-33.900349],"type":"Point"}
}