{
  "type": "Feature",
  "properties": {
    "addr:full":"Lvl 6, Ste 33/ 42 Harbourne Rd Kingsford NSW 2032",
    "addr:housenumber":"/ 42",
    "addr:postcode":"2032",
    "addr:street":"Harbourne Rd",
    "iso:country":"AU",
    "sg:address":"Lvl 6, Ste 33/ 42 Harbourne Rd",
    "sg:city":"Kingsford",
    "sg:classifiers":[
        {
            "category":"Personal",
            "subcategory":"Massage",
            "type":"Services"
        }
    ],
    "sg:phone":"+61 2 9663 5228",
    "sg:postcode":"2032",
    "sg:province":"NSW",
    "sg:tags":[
        "therapy"
    ],
    "wof:name":"Yeung Tina",
    "wof:placetype":"venue"
},
  "geometry": {"coordinates":[151.22836303700001,-33.9228668213],"type":"Point"}
}