{
  "type": "Feature",
  "properties": {
    "addr:full":"408 Banna Ave Griffith NSW 2680",
    "addr:housenumber":"408",
    "addr:postcode":"2680",
    "addr:street":"Banna Ave",
    "iso:country":"AU",
    "sg:address":"408 Banna Ave",
    "sg:city":"Griffith",
    "sg:classifiers":[
        {
            "category":"Food & Beverages",
            "subcategory":"Bakery",
            "type":"Retail Goods"
        }
    ],
    "sg:phone":"+61 2 6962 1677",
    "sg:postcode":"2680",
    "sg:province":"NSW",
    "sg:tags":[
        "baker"
    ],
    "wof:name":"Griffith Modern Bakery",
    "wof:placetype":"venue"
},
  "geometry": {"coordinates":[146.04186999999999,-34.287621],"type":"Point"}
}