{
  "type": "Feature",
  "properties": {
    "addr:full":"Suite 1 & 2, 14 Robinson St Carnarvon WA 6701",
    "addr:housenumber":"&;14",
    "addr:postcode":"6701",
    "addr:street":"2;Robinson St",
    "iso:country":"AU",
    "sg:address":"Suite 1 & 2, 14 Robinson St",
    "sg:city":"Carnarvon",
    "sg:classifiers":[
        {
            "category":"Health Services",
            "subcategory":"Dentist",
            "type":"Services"
        }
    ],
    "sg:phone":"+61 8 9941 1882",
    "sg:postcode":"6701",
    "sg:province":"WA",
    "wof:name":"Darcey Kristina",
    "wof:placetype":"venue"
},
  "geometry": {"coordinates":[113.656051636,-24.8852806091],"type":"Point"}
}