{
  "type": "Feature",
  "properties": {
    "addr:full":"293 Shute Harbour Rd Airlie Beach QLD 4802",
    "addr:housenumber":"293",
    "addr:postcode":"4802",
    "addr:street":"Shute Harbour Rd",
    "iso:country":"AU",
    "sg:address":"293 Shute Harbour Rd",
    "sg:city":"Airlie Beach",
    "sg:classifiers":[
        {
            "category":"Food & Beverages",
            "subcategory":"Bakery",
            "type":"Retail Goods"
        }
    ],
    "sg:phone":"+61 7 4946 5577",
    "sg:postcode":"4802",
    "sg:province":"QLD",
    "sg:tags":[
        "baker"
    ],
    "wof:name":"Brumby's Airlie Beach",
    "wof:placetype":"venue"
},
  "geometry": {"coordinates":[148.72001648,-20.2692298889],"type":"Point"}
}