{
  "type": "Feature",
  "properties": {
    "addr:full":"Shop 1006 Ingle Farm Shopping Centre (Near Food Court) SA 5098",
    "addr:housenumber":"1006",
    "addr:postcode":"5098",
    "addr:street":"Ingle;Food Court",
    "iso:country":"AU",
    "sg:address":"Shop 1006",
    "sg:city":"Ingle Farm Shopping Centre (Near Food Court)",
    "sg:classifiers":[
        {
            "category":"Personal",
            "subcategory":"Beauty Salon",
            "type":"Services"
        }
    ],
    "sg:phone":"+61 8 8395 5100",
    "sg:postcode":"5098",
    "sg:province":"SA",
    "wof:name":"Essential Beauty",
    "wof:placetype":"venue"
},
  "geometry": {"coordinates":[138.650756836,-34.8287086487],"type":"Point"}
}