{
  "type": "Feature",
  "properties": {
    "iso:country":"AU",
    "sg:address":"12 Bermuda Ave",
    "sg:city":"West Lakes Shore",
    "sg:classifiers":[
        {
            "category":"Utilities",
            "subcategory":"Electric",
            "type":"Services"
        }
    ],
    "sg:phone":"+61 8 8449 8794",
    "sg:postcode":"5020",
    "sg:province":"SA",
    "sg:tags":[
        "electrical",
        "contractor"
    ],
    "wof:name":"Klopp W.L. & P.A. Electrical Services Pty Ltd",
    "wof:placetype":"venue"
},
  "geometry": {"coordinates":[138.484298706,-34.8583335876],"type":"Point"}
}