{
  "type": "Feature",
  "properties": {
    "addr:full":"56 Pickering St Enoggera QLD 4051",
    "addr:housenumber":"56",
    "addr:postcode":"4051",
    "addr:street":"Pickering St",
    "iso:country":"AU",
    "sg:address":"56 Pickering St",
    "sg:city":"Enoggera",
    "sg:classifiers":[
        {
            "category":"Professional",
            "subcategory":"Art Services",
            "type":"Services"
        }
    ],
    "sg:phone":"+61 1800 643 600",
    "sg:postcode":"4051",
    "sg:province":"QLD",
    "sg:tags":[
        "decorator",
        "painter"
    ],
    "wof:name":"Tilecoat",
    "wof:placetype":"venue"
},
  "geometry": {"coordinates":[152.99574279800001,-27.4198265076],"type":"Point"}
}