{
  "type": "Feature",
  "properties": {
    "addr:full":"U4/ 53 Shire St Coorparoo QLD 4151",
    "addr:housenumber":"53",
    "addr:postcode":"4151",
    "addr:street":"U4 /;Shire St",
    "iso:country":"AU",
    "sg:address":"U4/ 53 Shire St",
    "sg:city":"Coorparoo",
    "sg:classifiers":[
        {
            "category":"Health Services",
            "subcategory":"Doctor",
            "type":"Services"
        }
    ],
    "sg:phone":"+61 7 3397 9203",
    "sg:postcode":"4151",
    "sg:province":"QLD",
    "sg:tags":[
        "medical",
        "practitioner"
    ],
    "wof:name":"Sta Maria Medical Services",
    "wof:placetype":"venue"
},
  "geometry": {"coordinates":[153.06320190400001,-27.4954490662],"type":"Point"}
}