{
  "type": "Feature",
  "properties": {
    "addr:full":"Sturt St Townsville QLD 4810",
    "addr:postcode":"4810",
    "addr:street":"Sturt St",
    "iso:country":"AU",
    "sg:address":"Sturt St",
    "sg:city":"Townsville",
    "sg:classifiers":[
        {
            "category":"Organizations",
            "subcategory":"Community Association",
            "type":"Services"
        }
    ],
    "sg:phone":"+61 7 4721 2888",
    "sg:postcode":"4810",
    "sg:province":"QLD",
    "sg:tags":[
        "organisation",
        "family",
        "welfare"
    ],
    "wof:name":"North Queensland Domestic Violence Resource Centre",
    "wof:placetype":"venue"
},
  "geometry": {"coordinates":[146.80212399999999,-19.271746],"type":"Point"}
}