{
  "type": "Feature",
  "properties": {
    "addr:full":"70 High St Hastings VIC 3915",
    "addr:housenumber":"70",
    "addr:postcode":"3915",
    "addr:street":"High St",
    "iso:country":"AU",
    "sg:address":"70 High St",
    "sg:city":"Hastings",
    "sg:classifiers":[
        {
            "category":"Banks & Credit Unions",
            "subcategory":"Bank",
            "type":"Services"
        }
    ],
    "sg:phone":"+61 13 20 32",
    "sg:postcode":"3915",
    "sg:province":"VIC",
    "wof:name":"Westpac",
    "wof:placetype":"venue"
},
  "geometry": {"coordinates":[145.18939209000001,-38.3075714111],"type":"Point"}
}