{
  "type": "Feature",
  "properties": {
    "addr:full":"Brown St Molloy QLD 4880",
    "addr:postcode":"4880",
    "addr:street":"Brown St",
    "iso:country":"AU",
    "sg:address":"Brown St",
    "sg:city":"Molloy",
    "sg:classifiers":[
        {
            "category":"Retail",
            "subcategory":"Auto Repair",
            "type":"Services"
        }
    ],
    "sg:phone":"+61 7 4094 1260",
    "sg:postcode":"4880",
    "sg:province":"QLD",
    "sg:tags":[
        "repairer",
        "motor",
        "engineer"
    ],
    "wof:name":"Mt Molloy Service Centre",
    "wof:placetype":"venue"
},
  "geometry": {"coordinates":[145.41346740700001,-16.9992694855],"type":"Point"}
}