{
  "type": "Feature",
  "properties": {
    "addr:full":"10 Lower Portrush Rd Marden SA 5070",
    "addr:housenumber":"10",
    "addr:postcode":"5070",
    "addr:street":"Lower Portrush Rd",
    "iso:country":"AU",
    "sg:address":"10 Lower Portrush Rd",
    "sg:city":"Marden",
    "sg:classifiers":[
        {
            "category":"Communications",
            "subcategory":"Film & Video Production",
            "type":"Services"
        }
    ],
    "sg:phone":"+61 8 8363 9088",
    "sg:postcode":"5070",
    "sg:province":"SA",
    "sg:tags":[
        "dvd",
        "library"
    ],
    "wof:name":"Blockbuster",
    "wof:placetype":"venue"
},
  "geometry": {"coordinates":[138.63841247600001,-34.8962554932],"type":"Point"}
}