{
  "type": "Feature",
  "properties": {
    "addr:full":"218 Adelaide St Brisbane QLD 4000",
    "addr:housenumber":"218",
    "addr:postcode":"4000",
    "addr:street":"Adelaide St",
    "iso:country":"AU",
    "sg:address":"218 Adelaide St",
    "sg:city":"Brisbane",
    "sg:classifiers":[
        {
            "category":"Professional",
            "type":"Services"
        }
    ],
    "sg:phone":"+61 7 3221 8460",
    "sg:postcode":"4000",
    "sg:province":"QLD",
    "sg:tags":[
        "auctioneer"
    ],
    "wof:name":"Colonial Auctions Australia Pty Ltd",
    "wof:placetype":"venue"
},
  "geometry": {"coordinates":[153.027511597,-27.4663162231],"type":"Point"}
}