{
  "type": "Feature",
  "properties": {
    "addr:full":"1 Madras La Caroline Springs VIC 3023",
    "addr:housenumber":"1",
    "addr:postcode":"3023",
    "addr:street":"Madras La",
    "iso:country":"AU",
    "sg:address":"1 Madras La",
    "sg:city":"Caroline Springs",
    "sg:classifiers":[
        {
            "category":"Building & Trades",
            "subcategory":"Cleaning & Sanitation",
            "type":"Services"
        }
    ],
    "sg:phone":"+61 416 350 064",
    "sg:postcode":"3023",
    "sg:province":"VIC",
    "sg:tags":[
        "chemical",
        "pressure",
        "steam",
        "contractor"
    ],
    "wof:name":"Chriss Unique Cleaning",
    "wof:placetype":"venue"
},
  "geometry": {"coordinates":[144.74569700000001,-37.755253],"type":"Point"}
}