{
  "type": "Feature",
  "properties": {
    "iso:country":"AU",
    "sg:address":"89 Wattletree Rd",
    "sg:city":"Armadale",
    "sg:classifiers":[
        {
            "category":"Health Services",
            "subcategory":"Health Practitioner",
            "type":"Services"
        }
    ],
    "sg:phone":"+61 403 591 982",
    "sg:postcode":"3143",
    "sg:province":"VIC",
    "sg:tags":[
        "acupuncture"
    ],
    "wof:name":"Yakamoto Oriental Medicine",
    "wof:placetype":"venue"
},
  "geometry": {"coordinates":[145.02650451700001,-37.8619804382],"type":"Point"}
}