{
  "type": "Feature",
  "properties": {
    "addr:full":"117 Sir Donald Bradman Drv Hilton SA 5033",
    "addr:housenumber":"117",
    "addr:postcode":"5033",
    "addr:street":"Sir Donald Bradman Drv",
    "iso:country":"AU",
    "sg:address":"117 Sir Donald Bradman Drv",
    "sg:city":"Hilton",
    "sg:classifiers":[
        {
            "category":"Arena",
            "subcategory":"Sports Club",
            "type":"Entertainment"
        }
    ],
    "sg:phone":"+61 8 8234 1166",
    "sg:postcode":"5033",
    "sg:province":"SA",
    "sg:tags":[
        "organisation",
        "sporting"
    ],
    "wof:name":"Womens Golf South Australia Incorporated",
    "wof:placetype":"venue"
},
  "geometry": {"coordinates":[138.56619262699999,-34.9322547913],"type":"Point"}
}