{
  "type": "Feature",
  "properties": {
    "iso:country":"AU",
    "sg:address":"2, 3040 Ballan Rd",
    "sg:city":"Daylesford",
    "sg:classifiers":[
        {
            "category":"Personal",
            "subcategory":"Day Spa",
            "type":"Services"
        }
    ],
    "sg:phone":"+61 3 5348 1002",
    "sg:postcode":"3460",
    "sg:province":"VIC",
    "wof:name":"Hidden Lotus",
    "wof:placetype":"venue"
},
  "geometry": {"coordinates":[144.143035889,-37.3413505554],"type":"Point"}
}