{
  "type": "Feature",
  "properties": {
    "iso:country":"AU",
    "sg:address":"21 Brett Drv",
    "sg:city":"Carrum Downs",
    "sg:classifiers":[
        {
            "category":"Retail",
            "subcategory":"Auto Repair",
            "type":"Services"
        }
    ],
    "sg:phone":"+61 3 9775 0909",
    "sg:postcode":"3201",
    "sg:province":"VIC",
    "sg:tags":[
        "body",
        "builder",
        "motor"
    ],
    "wof:name":"Damouni Bros. Pty Ltd",
    "wof:placetype":"venue"
},
  "geometry": {"coordinates":[145.163208,-38.095921],"type":"Point"}
}