{
  "type": "Feature",
  "properties": {
    "addr:full":"Redden Drv Cudlee Creek SA 5232",
    "addr:postcode":"5232",
    "addr:street":"Redden Drv",
    "iso:country":"AU",
    "sg:address":"Redden Drv",
    "sg:city":"Cudlee Creek",
    "sg:classifiers":[
        {
            "category":"Park",
            "subcategory":"County",
            "type":"Public Place"
        }
    ],
    "sg:phone":"+61 8 8389 2206",
    "sg:postcode":"5232",
    "sg:province":"SA",
    "sg:tags":[
        "sanctuary",
        "zoos",
        "animal"
    ],
    "wof:name":"Gorge Wildlife Park",
    "wof:placetype":"venue"
},
  "geometry": {"coordinates":[138.81573486299999,-34.8412132263],"type":"Point"}
}