{
  "type": "Feature",
  "properties": {
    "addr:full":"Shop 1/ 254 Hoskins St Temora NSW 2666",
    "addr:housenumber":"shop 1 / 254",
    "addr:postcode":"2666",
    "addr:street":"Hoskins St",
    "iso:country":"AU",
    "sg:address":"Shop 1/ 254 Hoskins St",
    "sg:city":"Temora",
    "sg:classifiers":[
        {
            "category":"Personal",
            "subcategory":"Beauty Salon",
            "type":"Services"
        }
    ],
    "sg:phone":"+61 2 6978 1986",
    "sg:postcode":"2666",
    "sg:province":"NSW",
    "wof:name":"Skin Deep Professional Beauty Therapy",
    "wof:placetype":"venue"
},
  "geometry": {"coordinates":[147.53443908700001,-34.4490509033],"type":"Point"}
}