{
  "type": "Feature",
  "properties": {
    "addr:full":"Aberdeen St Albany WA 6330",
    "addr:postcode":"6330",
    "addr:street":"Aberdeen St",
    "iso:country":"AU",
    "sg:address":"Aberdeen St",
    "sg:city":"Albany",
    "sg:classifiers":[
        {
            "category":"Government",
            "subcategory":"Court House",
            "type":"Public Place"
        }
    ],
    "sg:phone":"+61 414 919 601",
    "sg:postcode":"6330",
    "sg:province":"WA",
    "sg:tags":[
        "personal",
        "marriage",
        "family",
        "counselling"
    ],
    "wof:name":"Alldersea Bruce",
    "wof:placetype":"venue"
},
  "geometry": {"coordinates":[117.884872437,-35.0199127197],"type":"Point"}
}