{
  "type": "Feature",
  "properties": {
    "addr:full":"Unit 2/ 15 Achievement Crs Acacia Ridge QLD 4110",
    "addr:housenumber":"15",
    "addr:postcode":"4110",
    "addr:street":"Achievement Crs",
    "iso:country":"AU",
    "sg:address":"Unit 2/ 15 Achievement Crs",
    "sg:city":"Acacia Ridge",
    "sg:classifiers":[
        {
            "category":"Autos & Motor Vehicles",
            "subcategory":"Auto Supplies",
            "type":"Retail Goods"
        }
    ],
    "sg:phone":"+61 7 3274 1999",
    "sg:postcode":"4110",
    "sg:province":"QLD",
    "sg:tags":[
        "transmission",
        "equipment",
        "power"
    ],
    "wof:name":"Sprockets Australia (Qld) Pty Ltd",
    "wof:placetype":"venue"
},
  "geometry": {"coordinates":[153.02842712399999,-27.590379715],"type":"Point"}
}