{
  "type": "Feature",
  "properties": {
    "addr:full":"8 Boolcunda Ave Salisbury Plain SA 5109",
    "addr:housenumber":"8",
    "addr:postcode":"5109",
    "addr:street":"Boolcunda Ave",
    "iso:country":"AU",
    "sg:address":"8 Boolcunda Ave",
    "sg:city":"Salisbury Plain",
    "sg:classifiers":[
        {
            "category":"Home & Garden",
            "subcategory":"Furniture",
            "type":"Retail Goods"
        }
    ],
    "sg:phone":"+61 8 8250 7977",
    "sg:postcode":"5109",
    "sg:province":"SA",
    "sg:tags":[
        "outdoor"
    ],
    "wof:name":"Caprice Furniture",
    "wof:placetype":"venue"
},
  "geometry": {"coordinates":[138.66517639200001,-34.7657089233],"type":"Point"}
}