{
  "type": "Feature",
  "properties": {
    "iso:country":"AU",
    "sg:address":"389 Boat Harbour Drv",
    "sg:city":"Scarness",
    "sg:classifiers":[
        {
            "category":"Building & Trades",
            "subcategory":"Construction",
            "type":"Services"
        }
    ],
    "sg:phone":"+61 400 701 435",
    "sg:postcode":"4655",
    "sg:province":"QLD",
    "sg:tags":[
        "earth",
        "excavating",
        "moving",
        "contractor"
    ],
    "wof:name":"Greg Kneebone Excavations",
    "wof:placetype":"venue"
},
  "geometry": {"coordinates":[152.85907,-25.290876],"type":"Point"}
}