{
  "type": "Feature",
  "properties": {
    "iso:country":"AU",
    "sg:address":"Unit 4/ 659 Boundary Rd",
    "sg:city":"Richlands",
    "sg:classifiers":[
        {
            "category":"Shopping",
            "subcategory":"Bicycles & Sporting Goods",
            "type":"Retail Goods"
        }
    ],
    "sg:phone":"+61 7 3375 7900",
    "sg:postcode":"4077",
    "sg:province":"QLD",
    "sg:tags":[
        "water",
        "equipment",
        "skiing"
    ],
    "wof:name":"Brisbane Skiboat Centre",
    "wof:placetype":"venue"
},
  "geometry": {"coordinates":[152.95545959500001,-27.5782012939],"type":"Point"}
}