{
  "type": "Feature",
  "properties": {
    "addr:full":"19 Napier St Rooty Hill NSW 2766",
    "addr:housenumber":"19",
    "addr:postcode":"2766",
    "addr:street":"Napier St",
    "iso:country":"AU",
    "sg:address":"19 Napier St",
    "sg:city":"Rooty Hill",
    "sg:classifiers":[
        {
            "category":"Professional",
            "subcategory":"Art Services",
            "type":"Services"
        }
    ],
    "sg:phone":"+61 416 295 739",
    "sg:postcode":"2766",
    "sg:province":"NSW",
    "sg:tags":[
        "decorator",
        "painter"
    ],
    "wof:name":"Jai Pratt Painting",
    "wof:placetype":"venue"
},
  "geometry": {"coordinates":[150.84286499000001,-33.7615089417],"type":"Point"}
}