{
  "type": "Feature",
  "properties": {
    "addr:full":"7/ 2 Prossers Forest Rd Ravenswood TAS 7250",
    "addr:housenumber":"/ 2",
    "addr:postcode":"7250",
    "addr:street":"Prossers Forest Rd",
    "iso:country":"AU",
    "sg:address":"7/ 2 Prossers Forest Rd",
    "sg:city":"Ravenswood",
    "sg:classifiers":[
        {
            "category":"Government",
            "subcategory":"Post Office",
            "type":"Public Place"
        }
    ],
    "sg:phone":"+61 3 6339 1405",
    "sg:postcode":"7250",
    "sg:province":"TAS",
    "sg:tags":[
        "postal"
    ],
    "wof:name":"Australia Post",
    "wof:placetype":"venue"
},
  "geometry": {"coordinates":[147.12257385300001,-41.4334487915],"type":"Point"}
}