{
  "type": "Feature",
  "properties": {
    "iso:country":"AU",
    "sg:address":"17 Hubert St",
    "sg:city":"Townsville",
    "sg:classifiers":[
        {
            "category":"Health Services",
            "subcategory":"Chiropractor",
            "type":"Services"
        }
    ],
    "sg:phone":"+61 7 4772 2895",
    "sg:postcode":"4810",
    "sg:province":"QLD",
    "wof:name":"Barnes Kenneth W.",
    "wof:placetype":"venue"
},
  "geometry": {"coordinates":[146.83050499999999,-19.266106],"type":"Point"}
}