{
  "type": "Feature",
  "properties": {
    "addr:full":"Airstrip Rd Biggenden QLD 4621",
    "addr:postcode":"4621",
    "addr:street":"Airstrip Rd",
    "iso:country":"AU",
    "sg:address":"Airstrip Rd",
    "sg:city":"Biggenden",
    "sg:classifiers":[
        {
            "category":"Building & Trades",
            "subcategory":"Construction",
            "type":"Services"
        }
    ],
    "sg:phone":"+61 7 4127 1128",
    "sg:postcode":"4621",
    "sg:province":"QLD",
    "sg:tags":[
        "welding"
    ],
    "wof:name":"Biggenden Engineering Works",
    "wof:placetype":"venue"
},
  "geometry": {"coordinates":[152.04753099999999,-25.512774],"type":"Point"}
}