{
  "type": "Feature",
  "properties": {
    "addr:full":"15 Cook Ave Caboolture QLD 4510",
    "addr:housenumber":"15",
    "addr:postcode":"4510",
    "addr:street":"Cook Ave",
    "iso:country":"AU",
    "sg:address":"15 Cook Ave",
    "sg:city":"Caboolture",
    "sg:classifiers":[
        {
            "category":"Manufacturing",
            "subcategory":"Chemicals & Compounds",
            "type":"Manufacturing & Wholesale Goods"
        }
    ],
    "sg:phone":"+61 408 283 533",
    "sg:postcode":"4510",
    "sg:province":"QLD",
    "sg:tags":[
        "electroplating"
    ],
    "wof:name":"Julia Bronze Baby Shoes",
    "wof:placetype":"venue"
},
  "geometry": {"coordinates":[152.937881,-27.091269],"type":"Point"}
}