{
  "type": "Feature",
  "properties": {
    "addr:full":"Gibson Rd Noosaville QLD 4566",
    "addr:postcode":"4566",
    "addr:street":"Gibson Rd",
    "iso:country":"AU",
    "sg:address":"Gibson Rd",
    "sg:city":"Noosaville",
    "sg:classifiers":[
        {
            "category":"Sports & Exercise",
            "subcategory":"Gym",
            "type":"Entertainment"
        }
    ],
    "sg:phone":"+61 7 5455 5222",
    "sg:postcode":"4566",
    "sg:province":"QLD",
    "sg:tags":[
        "health",
        "fitness"
    ],
    "wof:name":"Karate Budokan International",
    "wof:placetype":"venue"
},
  "geometry": {"coordinates":[153.05279540999999,-26.4004974365],"type":"Point"}
}