{
  "type": "Feature",
  "properties": {
    "addr:full":"127 Auburn St Goulburn NSW 2580",
    "addr:housenumber":"127",
    "addr:postcode":"2580",
    "addr:street":"Auburn St",
    "iso:country":"AU",
    "sg:address":"127 Auburn St",
    "sg:city":"Goulburn",
    "sg:classifiers":[
        {
            "category":"Professional",
            "subcategory":"Employment Agencies",
            "type":"Services"
        }
    ],
    "sg:phone":"+61 500 522 400",
    "sg:postcode":"2580",
    "sg:province":"NSW",
    "sg:tags":[
        "provider",
        "internet"
    ],
    "wof:name":"Goulburn Internet",
    "wof:placetype":"venue"
},
  "geometry": {"coordinates":[149.71669006400001,-34.7568702698],"type":"Point"}
}