{
  "type": "Feature",
  "properties": {
    "addr:full":"652 Newcastle St Leederville WA 6007",
    "addr:housenumber":"652",
    "addr:postcode":"6007",
    "addr:street":"Newcastle St",
    "iso:country":"AU",
    "sg:address":"652 Newcastle St",
    "sg:city":"Leederville",
    "sg:classifiers":[
        {
            "category":"Retail",
            "subcategory":"Auto Repair",
            "type":"Services"
        }
    ],
    "sg:phone":"+61 8 9328 1916",
    "sg:postcode":"6007",
    "sg:province":"WA",
    "sg:tags":[
        "repairer",
        "motor",
        "engineer"
    ],
    "wof:name":"Rino's Automotive Repair",
    "wof:placetype":"venue"
},
  "geometry": {"coordinates":[115.843139648,-31.9378814697],"type":"Point"}
}