{
  "type": "Feature",
  "properties": {
    "addr:full":"Shop 4, 20 Main St Narangba QLD 4504",
    "addr:housenumber":"shop;20",
    "addr:postcode":"4504",
    "addr:street":"Main St",
    "iso:country":"AU",
    "sg:address":"Shop 4, 20 Main St",
    "sg:city":"Narangba",
    "sg:classifiers":[
        {
            "category":"Health Services",
            "subcategory":"Health Practitioner",
            "type":"Services"
        }
    ],
    "sg:phone":"+61 418 783 411",
    "sg:postcode":"4504",
    "sg:province":"QLD",
    "sg:tags":[
        "acupuncture"
    ],
    "wof:name":"Verdel Robyn",
    "wof:placetype":"venue"
},
  "geometry": {"coordinates":[152.96107482900001,-27.2039146423],"type":"Point"}
}