{
  "type": "Feature",
  "properties": {
    "iso:country":"AU",
    "sg:address":"Factory 2 49 Sinclair Rd",
    "sg:city":"Dandenong",
    "sg:classifiers":[
        {
            "category":"Manufacturing",
            "subcategory":"Rubber & Plastics",
            "type":"Manufacturing & Wholesale Goods"
        }
    ],
    "sg:phone":"+61 3 9792 5290",
    "sg:postcode":"3175",
    "sg:province":"VIC",
    "sg:tags":[
        "moulders"
    ],
    "wof:name":"Atac Plastics Pty Ltd",
    "wof:placetype":"venue"
},
  "geometry": {"coordinates":[145.197143555,-37.9881401062],"type":"Point"}
}