{
  "type": "Feature",
  "properties": {
    "addr:full":"559 Pittwater Rd Brookvale NSW 2100",
    "addr:housenumber":"559",
    "addr:postcode":"2100",
    "addr:street":"Pittwater Rd",
    "iso:country":"AU",
    "sg:address":"559 Pittwater Rd",
    "sg:city":"Brookvale",
    "sg:classifiers":[
        {
            "category":"Retail",
            "subcategory":"Car Wash",
            "type":"Services"
        }
    ],
    "sg:phone":"+61 2 9907 2666",
    "sg:postcode":"2100",
    "sg:province":"NSW",
    "sg:tags":[
        "truck",
        "cleaning"
    ],
    "sg:website":"http://www.crystalcarwashbrookvale.com.au",
    "wof:name":"Crystal Car Wash Pty Ltd",
    "wof:placetype":"venue"
},
  "geometry": {"coordinates":[151.27682495100001,-33.7609062195],"type":"Point"}
}