{
  "type": "Feature",
  "properties": {
    "addr:full":"PO Box 75 Jimboomba QLD 4280",
    "addr:postcode":"4280",
    "iso:country":"AU",
    "sg:address":"PO Box 75",
    "sg:city":"Jimboomba",
    "sg:classifiers":[
        {
            "category":"Professional",
            "type":"Services"
        }
    ],
    "sg:phone":"+61 413 738 141",
    "sg:postcode":"4280",
    "sg:province":"QLD",
    "sg:tags":[
        "shop",
        "fitting"
    ],
    "wof:name":"A B C E L Building Services",
    "wof:placetype":"venue"
},
  "geometry": {"coordinates":[153.02887000000001,-27.813459],"type":"Point"}
}