{
  "type": "Feature",
  "properties": {
    "addr:full":"PO Box 965 Hornsby NSW 2077",
    "addr:postcode":"2077",
    "iso:country":"AU",
    "sg:address":"PO Box 965",
    "sg:city":"Hornsby",
    "sg:classifiers":[
        {
            "category":"Wholesale",
            "subcategory":"Toys & Hobbies",
            "type":"Manufacturing & Wholesale Goods"
        }
    ],
    "sg:phone":"+61 2 9477 2558",
    "sg:postcode":"2077",
    "sg:province":"NSW",
    "sg:website":"http://www.tyaustralia.com.au",
    "wof:name":"Ty Australia",
    "wof:placetype":"venue"
},
  "geometry": {"coordinates":[151.11174011200001,-33.69713974],"type":"Point"}
}