{
  "type": "Feature",
  "properties": {
    "iso:country":"AU",
    "sg:address":"Unit 4/ 15-17 Blackburn St",
    "sg:city":"Maddington",
    "sg:classifiers":[
        {
            "category":"Arts & Performance",
            "subcategory":"Dance",
            "type":"Entertainment"
        }
    ],
    "sg:phone":"+61 412 083 482",
    "sg:postcode":"6109",
    "sg:province":"WA",
    "sg:tags":[
        "theatrical",
        "ballet",
        "tuition"
    ],
    "wof:name":"Dance Focus",
    "wof:placetype":"venue"
},
  "geometry": {"coordinates":[115.979820252,-32.0518608093],"type":"Point"}
}