{
  "type": "Feature",
  "properties": {
    "addr:full":"21 Riverview Ave Dangar Island NSW 2083",
    "addr:housenumber":"21",
    "addr:postcode":"2083",
    "addr:street":"Riverview Ave",
    "iso:country":"AU",
    "sg:address":"21 Riverview Ave",
    "sg:city":"Dangar Island",
    "sg:classifiers":[
        {
            "category":"Sports & Exercise",
            "subcategory":"Gym",
            "type":"Entertainment"
        }
    ],
    "sg:phone":"+61 2 9985 8551",
    "sg:postcode":"2083",
    "sg:province":"NSW",
    "sg:tags":[
        "personal",
        "trainer",
        "fitness"
    ],
    "wof:name":"Get Vibrant !",
    "wof:placetype":"venue"
},
  "geometry": {"coordinates":[151.24176025400001,-33.5393600464],"type":"Point"}
}