{
  "type": "Feature",
  "properties": {
    "iso:country":"AU",
    "sg:address":"B5/ 2a Westall Rd",
    "sg:city":"Clayton",
    "sg:classifiers":[
        {
            "category":"Home & Garden",
            "subcategory":"Carpets & Floor Coverings",
            "type":"Retail Goods"
        }
    ],
    "sg:phone":"+61 1800 626 001",
    "sg:postcode":"3168",
    "sg:province":"VIC",
    "sg:tags":[
        "machine"
    ],
    "wof:name":"Ezi Floor Products",
    "wof:placetype":"venue"
},
  "geometry": {"coordinates":[145.14338684099999,-37.9245376587],"type":"Point"}
}