{
  "type": "Feature",
  "properties": {
    "iso:country":"AU",
    "sg:address":"21 Endurance Ave",
    "sg:city":"Queanbeyan",
    "sg:phone":"+61 2 6297 1446",
    "sg:postcode":"2620",
    "sg:province":"ACT",
    "wof:name":"Discount Fencing & Water Tanks Pty Ltd",
    "wof:placetype":"venue"
},
  "geometry": {"coordinates":[149.24586486800001,-35.3405456543],"type":"Point"}
}