{
  "type": "Feature",
  "properties": {
    "iso:country":"AU",
    "sg:address":"691a Port Rd",
    "sg:city":"Woodville",
    "sg:classifiers":[
        {
            "category":"Autos & Motor Vehicles",
            "subcategory":"Automobile Sales",
            "type":"Retail Goods"
        }
    ],
    "sg:phone":"+61 8 8268 1022",
    "sg:postcode":"5011",
    "sg:province":"SA",
    "sg:tags":[
        "car",
        "used"
    ],
    "wof:name":"Statewide Auto Wholesale Co",
    "wof:placetype":"venue"
},
  "geometry": {"coordinates":[138.543869019,-34.8860664368],"type":"Point"}
}