{
  "type": "Feature",
  "properties": {
    "iso:country":"AU",
    "sg:address":"102 St John St",
    "sg:city":"Launceston",
    "sg:classifiers":[
        {
            "category":"Shopping",
            "subcategory":"Luggage & Leather Goods",
            "type":"Retail Goods"
        }
    ],
    "sg:phone":"+61 3 6331 3391",
    "sg:postcode":"7250",
    "sg:province":"TAS",
    "wof:name":"Cleo Bagland",
    "wof:placetype":"venue"
},
  "geometry": {"coordinates":[147.13955688499999,-41.4379653931],"type":"Point"}
}