{
  "type": "Feature",
  "properties": {
    "addr:full":"265 Robinson Rd East Geebung QLD 4034",
    "addr:housenumber":"265",
    "addr:postcode":"4034",
    "addr:street":"Robinson Rd East",
    "iso:country":"AU",
    "sg:address":"265 Robinson Rd",
    "sg:city":"East Geebung",
    "sg:classifiers":[
        {
            "category":"Building & Trades",
            "subcategory":"Equipment Rental",
            "type":"Services"
        }
    ],
    "sg:phone":"+61 1300 731 277",
    "sg:postcode":"4034",
    "sg:province":"QLD",
    "sg:tags":[
        "supply",
        "catering"
    ],
    "wof:name":"AAA Commercial Catering Equipment",
    "wof:placetype":"venue"
},
  "geometry": {"coordinates":[153.04737900000001,-27.368275],"type":"Point"}
}