{
  "type": "Feature",
  "properties": {
    "iso:country":"AU",
    "sg:address":"Racecourse Rd",
    "sg:city":"Port Augusta",
    "sg:classifiers":[
        {
            "category":"Arena",
            "subcategory":"Sports Club",
            "type":"Entertainment"
        }
    ],
    "sg:phone":"+61 8 8642 5666",
    "sg:postcode":"5700",
    "sg:province":"SA",
    "sg:tags":[
        "hunt",
        "racing"
    ],
    "wof:name":"Port Augusta Owners & Trainers Association Incorporated",
    "wof:placetype":"venue"
},
  "geometry": {"coordinates":[137.80242919899999,-32.50050354],"type":"Point"}
}