{
  "type": "Feature",
  "properties": {
    "addr:full":"9 Coralgum Pl Blacktown NSW 2148",
    "addr:housenumber":"9",
    "addr:postcode":"2148",
    "addr:street":"Coralgum Pl",
    "iso:country":"AU",
    "sg:address":"9 Coralgum Pl",
    "sg:city":"Blacktown",
    "sg:classifiers":[
        {
            "category":"Building & Trades",
            "subcategory":"Landscaping Services",
            "type":"Services"
        }
    ],
    "sg:phone":"+61 2 9621 4455",
    "sg:postcode":"2148",
    "sg:province":"NSW",
    "sg:tags":[
        "designer",
        "landscape",
        "contractor"
    ],
    "wof:name":"Mosaica Gardening Design",
    "wof:placetype":"venue"
},
  "geometry": {"coordinates":[150.91784668,-33.7788772583],"type":"Point"}
}