{
  "type": "Feature",
  "properties": {
    "addr:full":"17 Garrison Rd Bossley Park NSW 2176",
    "addr:housenumber":"17",
    "addr:postcode":"2176",
    "addr:street":"Garrison Rd",
    "iso:country":"AU",
    "sg:address":"17 Garrison Rd",
    "sg:city":"Bossley Park",
    "sg:classifiers":[
        {
            "category":"Utilities",
            "subcategory":"Electric",
            "type":"Services"
        }
    ],
    "sg:phone":"+61 414 924 216",
    "sg:postcode":"2176",
    "sg:province":"NSW",
    "sg:tags":[
        "electrical",
        "contractor"
    ],
    "wof:name":"Electrical Trade Developments",
    "wof:placetype":"venue"
},
  "geometry": {"coordinates":[150.88258361800001,-33.8608436584],"type":"Point"}
}