{
  "type": "Feature",
  "properties": {
    "addr:full":"1/ 28 Anchorage Drv Mindarie WA 6030",
    "addr:housenumber":"/ 28",
    "addr:postcode":"6030",
    "addr:street":"Anchorage Drv",
    "iso:country":"AU",
    "sg:address":"1/ 28 Anchorage Drv",
    "sg:city":"Mindarie",
    "sg:classifiers":[
        {
            "category":"Real Estate",
            "subcategory":"Real Estate Agent",
            "type":"Services"
        }
    ],
    "sg:phone":"+61 8 9407 1888",
    "sg:postcode":"6030",
    "sg:province":"WA",
    "wof:name":"RE/MAX Coastal",
    "wof:placetype":"venue"
},
  "geometry": {"coordinates":[115.71327209499999,-31.6937274933],"type":"Point"}
}