{
  "type": "Feature",
  "properties": {
    "addr:full":"615 Windsor Rd Vineyard NSW 2765",
    "addr:housenumber":"615",
    "addr:postcode":"2765",
    "addr:street":"Windsor Rd",
    "iso:country":"AU",
    "sg:address":"615 Windsor Rd",
    "sg:city":"Vineyard",
    "sg:classifiers":[
        {
            "category":"Manufacturing",
            "subcategory":"Tools & Machinery",
            "type":"Manufacturing & Wholesale Goods"
        }
    ],
    "sg:phone":"+61 2 9627 3209",
    "sg:postcode":"2765",
    "sg:province":"NSW",
    "sg:tags":[
        "earth",
        "excavating",
        "moving",
        "equipment"
    ],
    "wof:name":"Morison Tractor Parts",
    "wof:placetype":"venue"
},
  "geometry": {"coordinates":[150.86398315400001,-33.6500091553],"type":"Point"}
}