{
  "type": "Feature",
  "properties": {
    "addr:full":"94a Bourke St Bulla VIC 3428",
    "addr:housenumber":"94a",
    "addr:postcode":"3428",
    "addr:street":"Bourke St",
    "iso:country":"AU",
    "sg:address":"94a Bourke St",
    "sg:city":"Bulla",
    "sg:classifiers":[
        {
            "category":"Wholesale",
            "subcategory":"Farm Supplies",
            "type":"Manufacturing & Wholesale Goods"
        }
    ],
    "sg:phone":"+61 3 9307 1441",
    "sg:postcode":"3428",
    "sg:province":"VIC",
    "sg:tags":[
        "feed",
        "supplement",
        "stock"
    ],
    "wof:name":"Bulla Produce",
    "wof:placetype":"venue"
},
  "geometry": {"coordinates":[144.80509948700001,-37.6359672546],"type":"Point"}
}