{
  "type": "Feature",
  "properties": {
    "iso:country":"AU",
    "sg:address":"44 - 46 Francis Rd",
    "sg:city":"Wingfield",
    "sg:classifiers":[
        {
            "category":"Building & Trades",
            "subcategory":"Construction",
            "type":"Services"
        }
    ],
    "sg:phone":"+61 8 8268 9212",
    "sg:postcode":"5013",
    "sg:province":"SA",
    "sg:tags":[
        "earth",
        "excavating",
        "moving",
        "contractor"
    ],
    "wof:name":"Superlifters",
    "wof:placetype":"venue"
},
  "geometry": {"coordinates":[138.547317505,-34.8458175659],"type":"Point"}
}