{
  "type": "Feature",
  "properties": {
    "addr:full":"Shop 22 Harbour Town Shopping Centre 22 Wellington St West Perth WA 6005",
    "addr:housenumber":"shop 22;22",
    "addr:postcode":"6005",
    "addr:street":"Harbour Town Shopping;Wellington St",
    "iso:country":"AU",
    "sg:address":"Shop 22 Harbour Town Shopping Centre 22 Wellington St",
    "sg:city":"West Perth",
    "sg:classifiers":[
        {
            "category":"Ice Cream",
            "type":"Food & Drink"
        }
    ],
    "sg:phone":"+61 8 9481 2133",
    "sg:postcode":"6005",
    "sg:province":"WA",
    "sg:tags":[
        "retail"
    ],
    "wof:name":"Gelare",
    "wof:placetype":"venue"
},
  "geometry": {"coordinates":[115.8465271,-31.9449996948],"type":"Point"}
}