{
  "type": "Feature",
  "properties": {
    "addr:full":"40 Boyd St Webberton WA 6530",
    "addr:housenumber":"40",
    "addr:postcode":"6530",
    "addr:street":"Boyd St",
    "iso:country":"AU",
    "sg:address":"40 Boyd St",
    "sg:city":"Webberton",
    "sg:classifiers":[
        {
            "category":"Building & Trades",
            "subcategory":"Construction",
            "type":"Services"
        }
    ],
    "sg:phone":"+61 8 9921 1961",
    "sg:postcode":"6530",
    "sg:province":"WA",
    "sg:tags":[
        "pool",
        "swimming"
    ],
    "wof:name":"Central Pool Maintenance & Spa Showroom",
    "wof:placetype":"venue"
},
  "geometry": {"coordinates":[114.63491821300001,-28.7518253326],"type":"Point"}
}