{
  "type": "Feature",
  "properties": {
    "addr:full":"276 Carlisle St Balaclava VIC 3183",
    "addr:housenumber":"276",
    "addr:postcode":"3183",
    "addr:street":"Carlisle St",
    "iso:country":"AU",
    "sg:address":"276 Carlisle St",
    "sg:city":"Balaclava",
    "sg:classifiers":[
        {
            "category":"Fast Food",
            "type":"Food & Drink"
        }
    ],
    "sg:phone":"+61 3 9534 0988",
    "sg:postcode":"3183",
    "sg:province":"VIC",
    "sg:tags":[
        "away",
        "take"
    ],
    "wof:name":"Monkee Juice",
    "wof:placetype":"venue"
},
  "geometry": {"coordinates":[144.99310302699999,-37.8685569763],"type":"Point"}
}