{
  "type": "Feature",
  "properties": {
    "iso:country":"AU",
    "sg:address":"565 Bestmann Rd",
    "sg:city":"Ningi",
    "sg:classifiers":[
        {
            "category":"Home & Garden",
            "subcategory":"Garden Supply",
            "type":"Retail Goods"
        }
    ],
    "sg:phone":"+61 7 5497 5955",
    "sg:postcode":"4511",
    "sg:province":"QLD",
    "sg:tags":[
        "landscape"
    ],
    "wof:name":"Southern Pacific Sands",
    "wof:placetype":"venue"
},
  "geometry": {"coordinates":[153.096115,-27.07366],"type":"Point"}
}