{
  "type": "Feature",
  "properties": {
    "iso:country":"AU",
    "sg:address":"PO Box 16",
    "sg:city":"Rydalmere",
    "sg:classifiers":[
        {
            "category":"Banks & Credit Unions",
            "subcategory":"Bank",
            "type":"Services"
        }
    ],
    "sg:phone":"+61 2 9631 6081",
    "sg:postcode":"1701",
    "sg:province":"NSW",
    "sg:tags":[
        "broker",
        "mortgage"
    ],
    "wof:name":"Ask Homeloan Specialist Pty Ltd",
    "wof:placetype":"venue"
},
  "geometry": {"coordinates":[151.04173278799999,-33.8123283386],"type":"Point"}
}