{
  "type": "Feature",
  "properties": {
    "addr:full":"Suite 8/ 45 Delawney St Balcatta WA 6021",
    "addr:postcode":"6021",
    "addr:street":"45 Delawney St",
    "iso:country":"AU",
    "sg:address":"Suite 8/ 45 Delawney St",
    "sg:city":"Balcatta",
    "sg:classifiers":[
        {
            "category":"Professional",
            "subcategory":"Accounting & Tax Preparation",
            "type":"Services"
        }
    ],
    "sg:phone":"+61 8 9240 6581",
    "sg:postcode":"6021",
    "sg:province":"WA",
    "sg:tags":[
        "accountant",
        "auditor"
    ],
    "wof:name":"Accounting Focus",
    "wof:placetype":"venue"
},
  "geometry": {"coordinates":[115.813468933,-31.8664054871],"type":"Point"}
}