{
  "type": "Feature",
  "properties": {
    "addr:full":"7/60 Fitzroy St St Kilda VIC 3182",
    "addr:housenumber":"/ 60",
    "addr:postcode":"3182",
    "addr:street":"Fitzroy St",
    "iso:country":"AU",
    "sg:address":"7/60 Fitzroy St",
    "sg:city":"St Kilda",
    "sg:classifiers":[
        {
            "category":"Professional",
            "subcategory":"Employment Agencies",
            "type":"Services"
        }
    ],
    "sg:phone":"+61 416 060 021",
    "sg:postcode":"3182",
    "sg:province":"VIC",
    "sg:tags":[
        "entertainer",
        "agent"
    ],
    "wof:name":"RPJ Promotions",
    "wof:placetype":"venue"
},
  "geometry": {"coordinates":[144.97744750999999,-37.8595581055],"type":"Point"}
}