{
  "type": "Feature",
  "properties": {
    "addr:full":"2 Pitt St Cowra NSW 2794",
    "addr:housenumber":"2",
    "addr:postcode":"2794",
    "addr:street":"Pitt St",
    "iso:country":"AU",
    "sg:address":"2 Pitt St",
    "sg:city":"Cowra",
    "sg:classifiers":[
        {
            "category":"Food & Beverages",
            "subcategory":"Groceries & Convenience Stores",
            "type":"Retail Goods"
        }
    ],
    "sg:phone":"+61 2 6342 2580",
    "sg:postcode":"2794",
    "sg:province":"NSW",
    "wof:name":"Pitt Street Store",
    "wof:placetype":"venue"
},
  "geometry": {"coordinates":[148.68931579599999,-33.824054718],"type":"Point"}
}