{
  "type": "Feature",
  "properties": {
    "addr:full":"74 Wigram St Harris Park NSW 2150",
    "addr:housenumber":"74",
    "addr:postcode":"2150",
    "addr:street":"Wigram St",
    "iso:country":"AU",
    "sg:address":"74 Wigram St",
    "sg:city":"Harris Park",
    "sg:classifiers":[
        {
            "category":"Banks & Credit Unions",
            "subcategory":"Financial Services",
            "type":"Services"
        }
    ],
    "sg:phone":"+61 2 9893 7911",
    "sg:postcode":"2150",
    "sg:province":"NSW",
    "sg:tags":[
        "loan",
        "finance",
        "mortgage"
    ],
    "wof:name":"Mortgage Advisory Services Pty Ltd",
    "wof:placetype":"venue"
},
  "geometry": {"coordinates":[151.00898742699999,-33.8211975098],"type":"Point"}
}