{
  "type": "Feature",
  "properties": {
    "addr:full":"1 Elizabeth St. 10/F, Suite 3 Melbourne VIC 3000",
    "addr:housenumber":"1;10 /",
    "addr:postcode":"3000",
    "addr:street":"Elizabeth St.",
    "iso:country":"AU",
    "sg:address":"1 Elizabeth St. 10/F, Suite 3",
    "sg:city":"Melbourne",
    "sg:classifiers":[
        {
            "category":"Health Services",
            "subcategory":"Dentist",
            "type":"Services"
        }
    ],
    "sg:phone":"+61 3 9629 7664",
    "sg:postcode":"3000",
    "sg:province":"VIC",
    "wof:name":"Castro Z. Dr.",
    "wof:placetype":"venue"
},
  "geometry": {"coordinates":[144.96505737300001,-37.8179359436],"type":"Point"}
}