{
  "type": "Feature",
  "properties": {
    "iso:country":"AU",
    "sg:address":"2a Weerona Pl",
    "sg:city":"Caringbah",
    "sg:classifiers":[
        {
            "category":"Building & Trades",
            "subcategory":"Landscaping Services",
            "type":"Services"
        }
    ],
    "sg:phone":"+61 2 9525 2985",
    "sg:postcode":"2229",
    "sg:province":"NSW",
    "sg:tags":[
        "architect",
        "landscape"
    ],
    "wof:name":"Amour Pam",
    "wof:placetype":"venue"
},
  "geometry": {"coordinates":[151.10960388199999,-34.0586547852],"type":"Point"}
}