{
  "type": "Feature",
  "properties": {
    "iso:country":"AU",
    "sg:address":"55 Bronzewing Drv",
    "sg:city":"Erina",
    "sg:classifiers":[
        {
            "category":"Retail",
            "subcategory":"Driving School",
            "type":"Services"
        }
    ],
    "sg:phone":"+61 2 4365 2990",
    "sg:postcode":"2250",
    "sg:province":"NSW",
    "wof:name":"A Plus Driver Education",
    "wof:placetype":"venue"
},
  "geometry": {"coordinates":[151.391159058,-33.4447097778],"type":"Point"}
}