{
  "type": "Feature",
  "properties": {
    "addr:full":"79 Commercial Rd Port Augusta SA 5700",
    "addr:housenumber":"79",
    "addr:postcode":"5700",
    "addr:street":"Commercial Rd",
    "iso:country":"AU",
    "sg:address":"79 Commercial Rd",
    "sg:city":"Port Augusta",
    "sg:classifiers":[
        {
            "category":"Professional",
            "subcategory":"Management & Consulting",
            "type":"Services"
        }
    ],
    "sg:phone":"+61 8 8642 6656",
    "sg:postcode":"5700",
    "sg:province":"SA",
    "sg:tags":[
        "consultant",
        "energy"
    ],
    "wof:name":"Habitat Solutions",
    "wof:placetype":"venue"
},
  "geometry": {"coordinates":[137.763183594,-32.4930915833],"type":"Point"}
}