{
  "type": "Feature",
  "properties": {
    "addr:full":"23 Parry St Fremantle WA 6160",
    "addr:housenumber":"23",
    "addr:postcode":"6160",
    "addr:street":"Parry St",
    "iso:country":"AU",
    "sg:address":"23 Parry St",
    "sg:city":"Fremantle",
    "sg:classifiers":[
        {
            "category":"Mining & Drilling",
            "type":"Manufacturing & Wholesale Goods"
        }
    ],
    "sg:phone":"+61 8 9433 2222",
    "sg:postcode":"6160",
    "sg:province":"WA",
    "sg:tags":[
        "geologist"
    ],
    "wof:name":"Groundwater Resource Management Pty Ltd",
    "wof:placetype":"venue"
},
  "geometry": {"coordinates":[115.751457,-32.053257],"type":"Point"}
}