{
  "type": "Feature",
  "properties": {
    "addr:full":"1290 Abernethy Rd Hazelmere WA 6055",
    "addr:housenumber":"1290",
    "addr:postcode":"6055",
    "addr:street":"Abernethy Rd",
    "iso:country":"AU",
    "sg:address":"1290 Abernethy Rd",
    "sg:city":"Hazelmere",
    "sg:classifiers":[
        {
            "category":"Farming",
            "subcategory":"Crops",
            "type":"Manufacturing & Wholesale Goods"
        }
    ],
    "sg:phone":"+61 1300 722 534",
    "sg:postcode":"6055",
    "sg:province":"WA",
    "sg:tags":[
        "warehousing"
    ],
    "wof:name":"Northline Pty Limited",
    "wof:placetype":"venue"
},
  "geometry": {"coordinates":[115.999779,-31.920448],"type":"Point"}
}