{
  "type": "Feature",
  "properties": {
    "iso:country":"AU",
    "sg:address":"204 Goodwood Rd",
    "sg:city":"Childers",
    "sg:classifiers":[
        {
            "category":"Sports & Exercise",
            "subcategory":"Golf",
            "type":"Entertainment"
        }
    ],
    "sg:phone":"+61 7 4126 1430",
    "sg:postcode":"4660",
    "sg:province":"QLD",
    "sg:tags":[
        "club"
    ],
    "wof:name":"Isis Golf Club",
    "wof:placetype":"venue"
},
  "geometry": {"coordinates":[152.30410766599999,-25.227186203],"type":"Point"}
}