{
  "type": "Feature",
  "properties": {
    "addr:full":"Mashman Ave Kingsgrove NSW 2208",
    "addr:postcode":"2208",
    "addr:street":"Mashman Ave",
    "iso:country":"AU",
    "sg:address":"Mashman Ave",
    "sg:city":"Kingsgrove",
    "sg:classifiers":[
        {
            "category":"Home & Garden",
            "subcategory":"Carpets & Floor Coverings",
            "type":"Retail Goods"
        }
    ],
    "sg:phone":"+61 2 9502 2344",
    "sg:postcode":"2208",
    "sg:province":"NSW",
    "sg:tags":[
        "tile",
        "wall"
    ],
    "wof:name":"Mashman Fred A Pty Ltd",
    "wof:placetype":"venue"
},
  "geometry": {"coordinates":[151.09922800000001,-33.941689],"type":"Point"}
}