{
  "type": "Feature",
  "properties": {
    "addr:full":"610 Geelong Rd Brooklyn VIC 3025",
    "addr:housenumber":"610",
    "addr:postcode":"3025",
    "addr:street":"Geelong Rd",
    "iso:country":"AU",
    "sg:address":"610 Geelong Rd",
    "sg:city":"Brooklyn",
    "sg:classifiers":[
        {
            "category":"Retail",
            "subcategory":"Repair Shop",
            "type":"Services"
        }
    ],
    "sg:phone":"+61 13 16 16",
    "sg:postcode":"3025",
    "sg:province":"VIC",
    "sg:tags":[
        "windscreen"
    ],
    "wof:name":"O&#039;Brien",
    "wof:placetype":"venue"
},
  "geometry": {"coordinates":[144.844269,-37.818443],"type":"Point"}
}