{
  "type": "Feature",
  "properties": {
    "addr:full":"83b Kembla St Wollongong NSW 2500",
    "addr:housenumber":"83b",
    "addr:postcode":"2500",
    "addr:street":"Kembla St",
    "iso:country":"AU",
    "sg:address":"83b Kembla St",
    "sg:city":"Wollongong",
    "sg:classifiers":[
        {
            "category":"Real Estate",
            "subcategory":"Architect",
            "type":"Services"
        }
    ],
    "sg:phone":"+61 2 4227 1199",
    "sg:postcode":"2500",
    "sg:province":"NSW",
    "sg:tags":[
        "building",
        "designer"
    ],
    "wof:name":"Thunder Design Studio",
    "wof:placetype":"venue"
},
  "geometry": {"coordinates":[150.897156,-34.427521],"type":"Point"}
}