{
  "type": "Feature",
  "properties": {
    "iso:country":"AU",
    "sg:address":"931 Nepean Hwy",
    "sg:city":"Bentleigh",
    "sg:classifiers":[
        {
            "category":"Retail",
            "subcategory":"Auto Repair",
            "type":"Services"
        }
    ],
    "sg:phone":"+61 3 9563 9977",
    "sg:postcode":"3204",
    "sg:province":"VIC",
    "sg:tags":[
        "repairer",
        "motor",
        "engineer"
    ],
    "sg:website":"http://www.brightonnissan.com.au",
    "wof:name":"Brighton Nissan",
    "wof:placetype":"venue"
},
  "geometry": {"coordinates":[145.033386,-37.93129],"type":"Point"}
}