{
  "type": "Feature",
  "properties": {
    "iso:country":"AU",
    "sg:address":"10 Glenferrie Rd",
    "sg:city":"Malvern",
    "sg:classifiers":[
        {
            "category":"Professional",
            "subcategory":"Art Services",
            "type":"Services"
        }
    ],
    "sg:phone":"+61 3 9509 5855",
    "sg:postcode":"3144",
    "sg:province":"VIC",
    "sg:tags":[
        "picture",
        "frame",
        "framing"
    ],
    "wof:name":"Picture Framing Centre",
    "wof:placetype":"venue"
},
  "geometry": {"coordinates":[145.02798461899999,-37.8653335571],"type":"Point"}
}