{
  "type": "Feature",
  "properties": {
    "iso:country":"AU",
    "sg:address":"58 Cowper St",
    "sg:city":"Glebe",
    "sg:classifiers":[
        {
            "category":"Travel",
            "subcategory":"Hotels & Motels",
            "type":"Entertainment"
        }
    ],
    "sg:phone":"+61 2 9660 2326",
    "sg:postcode":"2037",
    "sg:province":"NSW",
    "sg:tags":[
        "accommodation"
    ],
    "wof:name":"Friend In Hand Hotel",
    "wof:placetype":"venue"
},
  "geometry": {"coordinates":[151.19256591800001,-33.8815193176],"type":"Point"}
}