{
  "type": "Feature",
  "properties": {
    "addr:full":"119 Ormond Rd Elwood VIC 3184",
    "addr:housenumber":"119",
    "addr:postcode":"3184",
    "addr:street":"Ormond Rd",
    "iso:country":"AU",
    "sg:address":"119 Ormond Rd",
    "sg:city":"Elwood",
    "sg:classifiers":[
        {
            "category":"Real Estate",
            "subcategory":"Real Estate Agent",
            "type":"Services"
        }
    ],
    "sg:phone":"+61 3 9525 7770",
    "sg:postcode":"3184",
    "sg:province":"VIC",
    "wof:name":"One Stop Real Estate Shop The",
    "wof:placetype":"venue"
},
  "geometry": {"coordinates":[144.98806762699999,-37.8854904175],"type":"Point"}
}