{
  "type": "Feature",
  "properties": {
    "addr:full":"421 Hampton St Hampton VIC 3188",
    "addr:housenumber":"421",
    "addr:postcode":"3188",
    "addr:street":"Hampton St",
    "iso:country":"AU",
    "sg:address":"421 Hampton St",
    "sg:city":"Hampton",
    "sg:classifiers":[
        {
            "category":"Home & Garden",
            "subcategory":"Furniture",
            "type":"Retail Goods"
        }
    ],
    "sg:phone":"+61 3 9598 7643",
    "sg:postcode":"3188",
    "sg:province":"VIC",
    "sg:tags":[
        "outdoor"
    ],
    "wof:name":"Precedence Pty Ltd",
    "wof:placetype":"venue"
},
  "geometry": {"coordinates":[145.002807617,-37.9350585938],"type":"Point"}
}