{
  "type": "Feature",
  "properties": {
    "addr:full":"36 Burringbar St Mullumbimby NSW 2482",
    "addr:housenumber":"36",
    "addr:postcode":"2482",
    "addr:street":"Burringbar St",
    "iso:country":"AU",
    "sg:address":"36 Burringbar St",
    "sg:city":"Mullumbimby",
    "sg:classifiers":[
        {
            "category":"Food & Beverages",
            "subcategory":"Supermarket",
            "type":"Retail Goods"
        }
    ],
    "sg:phone":"+61 2 6684 2255",
    "sg:postcode":"2482",
    "sg:province":"NSW",
    "sg:tags":[
        "grocery",
        "store"
    ],
    "wof:name":"Mallam's Supermarket",
    "wof:placetype":"venue"
},
  "geometry": {"coordinates":[153.500488281,-28.5531272888],"type":"Point"}
}