{
  "type": "Feature",
  "properties": {
    "iso:country":"AU",
    "sg:address":"Dandenong Medical Centre 176 Lonsdale St",
    "sg:city":"Dandenong",
    "sg:classifiers":[
        {
            "category":"Health Services",
            "subcategory":"Doctor",
            "type":"Services"
        }
    ],
    "sg:phone":"+61 3 9794 7866",
    "sg:postcode":"3175",
    "sg:province":"VIC",
    "sg:tags":[
        "medical",
        "practitioner"
    ],
    "wof:name":"Fernando S Dr",
    "wof:placetype":"venue"
},
  "geometry": {"coordinates":[145.21502685600001,-37.9896774292],"type":"Point"}
}