{
  "type": "Feature",
  "properties": {
    "addr:full":"8 Court Rd Nambour QLD 4560",
    "addr:housenumber":"8",
    "addr:postcode":"4560",
    "addr:street":"Court Rd",
    "iso:country":"AU",
    "sg:address":"8 Court Rd",
    "sg:city":"Nambour",
    "sg:classifiers":[
        {
            "category":"Home & Garden",
            "subcategory":"Hardware",
            "type":"Retail Goods"
        }
    ],
    "sg:phone":"+61 7 5441 4900",
    "sg:postcode":"4560",
    "sg:province":"QLD",
    "sg:tags":[
        "repair",
        "tool",
        "power"
    ],
    "wof:name":"The Tool Repair Guy",
    "wof:placetype":"venue"
},
  "geometry": {"coordinates":[152.9634552,-26.6308345795],"type":"Point"}
}