{
  "type": "Feature",
  "properties": {
    "iso:country":"AU",
    "sg:address":"Suite 4, Colonial Arcade, 75",
    "sg:city":"Main Street Alstonville",
    "sg:classifiers":[
        {
            "category":"Government",
            "subcategory":"Court House",
            "type":"Public Place"
        }
    ],
    "sg:phone":"+61 2 6628 6488",
    "sg:postcode":"2477",
    "sg:province":"NSW",
    "sg:tags":[
        "personal",
        "marriage",
        "family",
        "counselling"
    ],
    "wof:name":"Christina Wannan",
    "wof:placetype":"venue"
},
  "geometry": {"coordinates":[153.435943603,-28.8380241394],"type":"Point"}
}