{
  "type": "Feature",
  "properties": {
    "addr:full":"8 Riverglen Crt Bellmere QLD 4510",
    "addr:housenumber":"8",
    "addr:postcode":"4510",
    "addr:street":"Riverglen Crt",
    "iso:country":"AU",
    "sg:address":"8 Riverglen Crt",
    "sg:city":"Bellmere",
    "sg:classifiers":[
        {
            "category":"Professional",
            "subcategory":"Business Services",
            "type":"Services"
        }
    ],
    "sg:phone":"+61 7 5498 9356",
    "sg:postcode":"4510",
    "sg:province":"QLD",
    "sg:tags":[
        "drafting"
    ],
    "wof:name":"Clifton Jeff",
    "wof:placetype":"venue"
},
  "geometry": {"coordinates":[152.921494,-27.095076],"type":"Point"}
}