{
  "type": "Feature",
  "properties": {
    "iso:country":"AU",
    "sg:address":"Randall Ave",
    "sg:city":"Edithvale",
    "sg:classifiers":[
        {
            "category":"Health Services",
            "subcategory":"Doctor",
            "type":"Services"
        }
    ],
    "sg:phone":"+61 3 9774 3776",
    "sg:postcode":"3196",
    "sg:province":"VIC",
    "sg:tags":[
        "reflexology"
    ],
    "wof:name":"Emma Gierschick",
    "wof:placetype":"venue"
},
  "geometry": {"coordinates":[145.12022399899999,-38.0385971069],"type":"Point"}
}