{
  "type": "Feature",
  "properties": {
    "addr:full":"106 Queen St Woollahra NSW 2025",
    "addr:housenumber":"106",
    "addr:postcode":"2025",
    "addr:street":"Queen St",
    "iso:country":"AU",
    "sg:address":"106 Queen St",
    "sg:city":"Woollahra",
    "sg:classifiers":[
        {
            "category":"Shopping",
            "subcategory":"Antiques",
            "type":"Retail Goods"
        }
    ],
    "sg:phone":"+61 2 9363 2423",
    "sg:postcode":"2025",
    "sg:province":"NSW",
    "wof:name":"Gaslight Antiques",
    "wof:placetype":"venue"
},
  "geometry": {"coordinates":[151.23646545400001,-33.8884277344],"type":"Point"}
}