{
  "type": "Feature",
  "properties": {
    "iso:country":"AU",
    "sg:address":"Unit 4/ 273 Williamstown Rd",
    "sg:city":"Port Melbourne",
    "sg:classifiers":[
        {
            "category":"Manufacturing",
            "subcategory":"Printing",
            "type":"Manufacturing & Wholesale Goods"
        }
    ],
    "sg:phone":"+61 3 9645 1166",
    "sg:postcode":"3207",
    "sg:province":"VIC",
    "sg:tags":[
        "wholesaler",
        "mfrs",
        "greeting",
        "card"
    ],
    "wof:name":"Gallery Collection",
    "wof:placetype":"venue"
},
  "geometry": {"coordinates":[144.921524,-37.835514],"type":"Point"}
}