{
  "type": "Feature",
  "properties": {
    "addr:full":"1/ 224 Princes Hwy Dandenong VIC 3175",
    "addr:housenumber":"/ 224",
    "addr:postcode":"3175",
    "addr:street":"Princes Hwy",
    "iso:country":"AU",
    "sg:address":"1/ 224 Princes Hwy",
    "sg:city":"Dandenong",
    "sg:classifiers":[
        {
            "category":"Professional",
            "type":"Services"
        }
    ],
    "sg:phone":"+61 3 9793 4755",
    "sg:postcode":"3175",
    "sg:province":"VIC",
    "sg:tags":[
        "shop",
        "fitting"
    ],
    "wof:name":"Ecco Shopfitting",
    "wof:placetype":"venue"
},
  "geometry": {"coordinates":[145.19937133799999,-37.9707527161],"type":"Point"}
}