{
  "type": "Feature",
  "properties": {
    "iso:country":"AU",
    "sg:address":"Gooch Rd",
    "sg:city":"Clackline",
    "sg:classifiers":[
        {
            "category":"Recreation",
            "type":"Entertainment"
        }
    ],
    "sg:phone":"+61 8 9574 1480",
    "sg:postcode":"6564",
    "sg:province":"WA",
    "sg:tags":[
        "supply",
        "outdoor",
        "adventure",
        "activity"
    ],
    "wof:name":"Blue Gum Camel Farm",
    "wof:placetype":"venue"
},
  "geometry": {"coordinates":[116.549217,-31.738775],"type":"Point"}
}