{
  "type": "Feature",
  "properties": {
    "addr:full":"26 Cavan Rd Dry Creek SA 5094",
    "addr:housenumber":"26",
    "addr:postcode":"5094",
    "addr:street":"Cavan Rd Dry",
    "iso:country":"AU",
    "sg:address":"26 Cavan Rd",
    "sg:city":"Dry Creek",
    "sg:classifiers":[
        {
            "category":"Utilities",
            "type":"Services"
        }
    ],
    "sg:phone":"+61 8 8368 2300",
    "sg:postcode":"5094",
    "sg:province":"SA",
    "sg:tags":[
        "refrigeration",
        "industrial",
        "commercial",
        "retail"
    ],
    "sg:website":"http://www.hill.com.au",
    "wof:name":"Hill Equipment & Refrigeration",
    "wof:placetype":"venue"
},
  "geometry": {"coordinates":[138.58401489299999,-34.8470535278],"type":"Point"}
}