{
  "type": "Feature",
  "properties": {
    "addr:full":"147 Paterson St Launceston TAS 7250",
    "addr:housenumber":"147",
    "addr:postcode":"7250",
    "addr:street":"Paterson St",
    "iso:country":"AU",
    "sg:address":"147 Paterson St",
    "sg:city":"Launceston",
    "sg:classifiers":[
        {
            "category":"Travel",
            "subcategory":"Hotels & Motels",
            "type":"Entertainment"
        }
    ],
    "sg:phone":"+61 3 6331 6699",
    "sg:postcode":"7250",
    "sg:province":"TAS",
    "sg:tags":[
        "accommodation"
    ],
    "wof:name":"Penny Royal",
    "wof:placetype":"venue"
},
  "geometry": {"coordinates":[147.13064575199999,-41.4405632019],"type":"Point"}
}