{
  "type": "Feature",
  "properties": {
    "iso:country":"AU",
    "sg:address":"451 Belmont Ave",
    "sg:city":"Kewdale",
    "sg:classifiers":[
        {
            "category":"Manufacturing",
            "subcategory":"Rubber & Plastics",
            "type":"Manufacturing & Wholesale Goods"
        }
    ],
    "sg:phone":"+61 8 9353 3477",
    "sg:postcode":"6105",
    "sg:province":"WA",
    "sg:tags":[
        "moulders"
    ],
    "sg:website":"http://www.superline.com.au",
    "wof:name":"Superline",
    "wof:placetype":"venue"
},
  "geometry": {"coordinates":[115.947532654,-31.9774475098],"type":"Point"}
}