{
  "type": "Feature",
  "properties": {
    "addr:full":"Old Mornington-Flinders Rd Dromana VIC 3936",
    "addr:postcode":"3936",
    "addr:street":"Mornington-Flinders Rd",
    "iso:country":"AU",
    "sg:address":"Old Mornington-Flinders Rd",
    "sg:city":"Dromana",
    "sg:classifiers":[
        {
            "category":"Sports & Exercise",
            "subcategory":"Sports Center",
            "type":"Entertainment"
        }
    ],
    "sg:phone":"+61 3 5981 0347",
    "sg:postcode":"3936",
    "sg:province":"VIC",
    "sg:tags":[
        "ground"
    ],
    "wof:name":"Dromana Basketball Stadium",
    "wof:placetype":"venue"
},
  "geometry": {"coordinates":[144.99493408199999,-38.3662719727],"type":"Point"}
}