{
  "type": "Feature",
  "properties": {
    "addr:full":"61 Trade Pl Coburg VIC 3058",
    "addr:housenumber":"61",
    "addr:postcode":"3058",
    "addr:street":"Trade Pl",
    "iso:country":"AU",
    "sg:address":"61 Trade Pl",
    "sg:city":"Coburg",
    "sg:classifiers":[
        {
            "category":"Professional",
            "subcategory":"Employment Agencies",
            "type":"Services"
        }
    ],
    "sg:phone":"+61 3 9350 3333",
    "sg:postcode":"3058",
    "sg:province":"VIC",
    "sg:tags":[
        "vic",
        "escort"
    ],
    "wof:name":"Crystal Lodge",
    "wof:placetype":"venue"
},
  "geometry": {"coordinates":[144.96958923299999,-37.7242698669],"type":"Point"}
}