{
  "type": "Feature",
  "properties": {
    "addr:full":"1/ 59 Kalang Rd Elanora Heights NSW 2101",
    "addr:housenumber":"/ 59",
    "addr:postcode":"2101",
    "addr:street":"Kalang Rd",
    "iso:country":"AU",
    "sg:address":"1/ 59 Kalang Rd",
    "sg:city":"Elanora Heights",
    "sg:classifiers":[
        {
            "category":"Health Services",
            "subcategory":"Health Practitioner",
            "type":"Services"
        }
    ],
    "sg:phone":"+61 417 794 279",
    "sg:postcode":"2101",
    "sg:province":"NSW",
    "sg:tags":[
        "acupuncture"
    ],
    "wof:name":"Mingmen Gateway To Vitality",
    "wof:placetype":"venue"
},
  "geometry": {"coordinates":[151.28010599999999,-33.695885],"type":"Point"}
}