{
  "type": "Feature",
  "properties": {
    "iso:country":"AU",
    "sg:address":"16 Dundas St",
    "sg:city":"Lancefield",
    "sg:classifiers":[
        {
            "category":"Social Services",
            "subcategory":"Adult Care",
            "type":"Services"
        }
    ],
    "sg:phone":"+61 427 516 071",
    "sg:postcode":"3435",
    "sg:province":"VIC",
    "sg:tags":[
        "towing"
    ],
    "wof:name":"Jackson Towing Service",
    "wof:placetype":"venue"
},
  "geometry": {"coordinates":[144.73484802199999,-37.2755661011],"type":"Point"}
}