{
  "type": "Feature",
  "properties": {
    "addr:full":"55 Quayle Rd Wandin Yallock VIC 3139",
    "addr:housenumber":"55",
    "addr:postcode":"3139",
    "addr:street":"Quayle Rd",
    "iso:country":"AU",
    "sg:address":"55 Quayle Rd",
    "sg:city":"Wandin Yallock",
    "sg:classifiers":[
        {
            "category":"Food & Beverages",
            "subcategory":"Fruits & Vegetables",
            "type":"Retail Goods"
        }
    ],
    "sg:phone":"+61 3 5964 4584",
    "sg:postcode":"3139",
    "sg:province":"VIC",
    "sg:tags":[
        "wholesale"
    ],
    "wof:name":"Harvey G R & E R Pty Ltd",
    "wof:placetype":"venue"
},
  "geometry": {"coordinates":[145.445220947,-37.7830238342],"type":"Point"}
}