{
  "type": "Feature",
  "properties": {
    "addr:full":"PO Box 1839 Wangara DC WA 6947",
    "addr:postcode":"6947",
    "iso:country":"AU",
    "sg:address":"PO Box 1839",
    "sg:city":"Wangara DC",
    "sg:classifiers":[
        {
            "category":"Building & Trades",
            "subcategory":"Construction",
            "type":"Services"
        }
    ],
    "sg:phone":"+61 412 088 220",
    "sg:postcode":"6947",
    "sg:province":"WA",
    "sg:tags":[
        "repairing",
        "window"
    ],
    "wof:name":"Access Windows & Doors",
    "wof:placetype":"venue"
},
  "geometry": {"coordinates":[115.83036041299999,-31.7966709137],"type":"Point"}
}