{
  "type": "Feature",
  "properties": {
    "iso:country":"AU",
    "sg:address":"87 Fitzroy St",
    "sg:city":"Geelong",
    "sg:classifiers":[
        {
            "category":"Personal",
            "type":"Services"
        }
    ],
    "sg:phone":"+61 3 5221 7706",
    "sg:postcode":"3220",
    "sg:province":"VIC",
    "sg:tags":[
        "dressmaker"
    ],
    "wof:name":"Bernice Fashions",
    "wof:placetype":"venue"
},
  "geometry": {"coordinates":[144.36720299999999,-38.158211],"type":"Point"}
}