{
  "type": "Feature",
  "properties": {
    "addr:full":"4/ 137 Brebner Drv West Lakes SA 5021",
    "addr:housenumber":"/ 137",
    "addr:postcode":"5021",
    "addr:street":"Brebner Drv",
    "iso:country":"AU",
    "sg:address":"4/ 137 Brebner Drv",
    "sg:city":"West Lakes",
    "sg:classifiers":[
        {
            "category":"Real Estate",
            "subcategory":"Real Estate Agent",
            "type":"Services"
        }
    ],
    "sg:phone":"+61 8 8235 9177",
    "sg:postcode":"5021",
    "sg:province":"SA",
    "wof:name":"Mackenzie Real Estate Pty Ltd",
    "wof:placetype":"venue"
},
  "geometry": {"coordinates":[138.489135742,-34.8807411194],"type":"Point"}
}