{
  "type": "Feature",
  "properties": {
    "addr:full":"5 Evans St Braybrook VIC 3019",
    "addr:housenumber":"5",
    "addr:postcode":"3019",
    "addr:street":"Evans St",
    "iso:country":"AU",
    "sg:address":"5 Evans St",
    "sg:city":"Braybrook",
    "sg:classifiers":[
        {
            "category":"Shopping",
            "subcategory":"Baby Store",
            "type":"Retail Goods"
        }
    ],
    "sg:phone":"+61 3 9317 7231",
    "sg:postcode":"3019",
    "sg:province":"VIC",
    "sg:tags":[
        "children's",
        "wear"
    ],
    "wof:name":"I.C.M. Clothing",
    "wof:placetype":"venue"
},
  "geometry": {"coordinates":[144.862792969,-37.7797431946],"type":"Point"}
}