{
  "type": "Feature",
  "properties": {
    "addr:full":"Level 1/ 195 Lyons St Cairns QLD 4870",
    "addr:housenumber":"/ 195",
    "addr:postcode":"4870",
    "addr:street":"Lyons St",
    "iso:country":"AU",
    "sg:address":"Level 1/ 195 Lyons St",
    "sg:city":"Cairns",
    "sg:classifiers":[
        {
            "category":"Professional",
            "subcategory":"Business Services",
            "type":"Services"
        }
    ],
    "sg:phone":"+61 7 4041 2245",
    "sg:postcode":"4870",
    "sg:province":"QLD",
    "sg:tags":[
        "drafting"
    ],
    "wof:name":"Dunworth John Design & Drafting",
    "wof:placetype":"venue"
},
  "geometry": {"coordinates":[145.75769043,-16.9413394928],"type":"Point"}
}