{
  "type": "Feature",
  "properties": {
    "addr:full":"Shp 2/ 48 Agnes St Kingston SE SA 5275",
    "addr:housenumber":"/ 48",
    "addr:postcode":"5275",
    "addr:street":"Agnes St",
    "iso:country":"AU",
    "sg:address":"Shp 2/ 48 Agnes St",
    "sg:city":"Kingston SE",
    "sg:classifiers":[
        {
            "category":"Personal",
            "subcategory":"Beauty Salon",
            "type":"Services"
        }
    ],
    "sg:phone":"+61 8 8767 2879",
    "sg:postcode":"5275",
    "sg:province":"SA",
    "sg:tags":[
        "hairdresser"
    ],
    "wof:name":"Club Cuts",
    "wof:placetype":"venue"
},
  "geometry": {"coordinates":[139.853836,-36.830814],"type":"Point"}
}