{
  "type": "Feature",
  "properties": {
    "addr:full":"78 Barney St Armidale NSW 2350",
    "addr:housenumber":"78",
    "addr:postcode":"2350",
    "addr:street":"Barney St",
    "iso:country":"AU",
    "sg:address":"78 Barney St",
    "sg:city":"Armidale",
    "sg:classifiers":[
        {
            "category":"Health Services",
            "subcategory":"Doctor",
            "type":"Services"
        }
    ],
    "sg:phone":"+61 2 6772 2233",
    "sg:postcode":"2350",
    "sg:province":"NSW",
    "sg:tags":[
        "medical",
        "practitioner"
    ],
    "wof:name":"Glover Brian Dr",
    "wof:placetype":"venue"
},
  "geometry": {"coordinates":[151.66726684599999,-30.5173416138],"type":"Point"}
}