{
  "type": "Feature",
  "properties": {
    "iso:country":"AU",
    "sg:address":"Lot 15 Wilcox & Bluff Rd",
    "sg:city":"Kenilworth",
    "sg:classifiers":[
        {
            "category":"Farming",
            "subcategory":"Vineyard",
            "type":"Manufacturing & Wholesale Goods"
        }
    ],
    "sg:phone":"+61 7 5472 3168",
    "sg:postcode":"4574",
    "sg:province":"QLD",
    "sg:tags":[
        "winery"
    ],
    "wof:name":"Blind Man's Bluff Vineyards",
    "wof:placetype":"venue"
},
  "geometry": {"coordinates":[152.729431,-26.554628],"type":"Point"}
}