{
  "type": "Feature",
  "properties": {
    "addr:full":"154 Guineas Creek Rd Currumbin Waters QLD 4223",
    "addr:housenumber":"154",
    "addr:postcode":"4223",
    "addr:street":"Guineas Creek Rd",
    "iso:country":"AU",
    "sg:address":"154 Guineas Creek Rd",
    "sg:city":"Currumbin Waters",
    "sg:classifiers":[
        {
            "category":"Building & Trades",
            "subcategory":"Construction",
            "type":"Services"
        }
    ],
    "sg:phone":"+61 7 5598 6005",
    "sg:postcode":"4223",
    "sg:province":"QLD",
    "sg:tags":[
        "contractor"
    ],
    "wof:name":"Hammersley Peter",
    "wof:placetype":"venue"
},
  "geometry": {"coordinates":[153.458862305,-28.1385059357],"type":"Point"}
}