{
  "type": "Feature",
  "properties": {
    "iso:country":"AU",
    "sg:address":"109 Waverley Rd",
    "sg:city":"Malvern East",
    "sg:classifiers":[
        {
            "category":"Fast Food",
            "type":"Food & Drink"
        }
    ],
    "sg:phone":"+61 3 9571 9324",
    "sg:postcode":"3145",
    "sg:province":"VIC",
    "sg:tags":[
        "away",
        "take"
    ],
    "wof:name":"Zeng Fish & Chips",
    "wof:placetype":"venue"
},
  "geometry": {"coordinates":[145.048339844,-37.8758392334],"type":"Point"}
}