{
  "type": "Feature",
  "properties": {
    "iso:country":"AU",
    "sg:address":"2 Hubert St",
    "sg:city":"Belmont",
    "sg:classifiers":[
        {
            "category":"Building & Trades",
            "subcategory":"Construction",
            "type":"Services"
        }
    ],
    "sg:phone":"+61 8 9282 1888",
    "sg:postcode":"6104",
    "sg:province":"WA",
    "sg:tags":[
        "escalator",
        "maintenance"
    ],
    "wof:name":"Schindler Lifts Australia Pty Ltd",
    "wof:placetype":"venue"
},
  "geometry": {"coordinates":[115.92857360799999,-31.9501094818],"type":"Point"}
}