{
  "type": "Feature",
  "properties": {
    "iso:country":"AU",
    "sg:address":"170 Melrose Drv",
    "sg:city":"Phillip",
    "sg:classifiers":[
        {
            "category":"Food & Beverages",
            "subcategory":"Liquor & Beverages",
            "type":"Retail Goods"
        }
    ],
    "sg:phone":"+61 2 6122 8901",
    "sg:postcode":"2606",
    "sg:province":"ACT",
    "sg:tags":[
        "store"
    ],
    "wof:name":"1st Choice Liquor Superstore",
    "wof:placetype":"venue"
},
  "geometry": {"coordinates":[149.084915161,-35.3500099182],"type":"Point"}
}