{
  "type": "Feature",
  "properties": {
    "addr:full":"Unit 6, 54 Prindiville Drv Wangara WA 6065",
    "addr:housenumber":"54",
    "addr:postcode":"6065",
    "addr:street":"Prindiville Drv",
    "iso:country":"AU",
    "sg:address":"Unit 6, 54 Prindiville Drv",
    "sg:city":"Wangara",
    "sg:classifiers":[
        {
            "category":"Arena",
            "subcategory":"Sports Club",
            "type":"Entertainment"
        }
    ],
    "sg:phone":"+61 419 197 083",
    "sg:postcode":"6065",
    "sg:province":"WA",
    "sg:tags":[
        "defence",
        "supply",
        "self",
        "instruction",
        "martial art"
    ],
    "sg:website":"http://www.subfactory.com.au",
    "wof:name":"Submission Factory",
    "wof:placetype":"venue"
},
  "geometry": {"coordinates":[115.825408935,-31.7913589478],"type":"Point"}
}