{
  "type": "Feature",
  "properties": {
    "iso:country":"AU",
    "sg:address":"378 - 390 St Georges Rd",
    "sg:city":"Fitzroy North",
    "sg:classifiers":[
        {
            "category":"Home & Garden",
            "subcategory":"Hardware",
            "type":"Retail Goods"
        }
    ],
    "sg:phone":"+61 3 9481 3666",
    "sg:postcode":"3068",
    "sg:province":"VIC",
    "sg:tags":[
        "plumber",
        "supply"
    ],
    "wof:name":"Tradelink Plumbing Centres",
    "wof:placetype":"venue"
},
  "geometry": {"coordinates":[144.988204956,-37.7784957886],"type":"Point"}
}