{
  "type": "Feature",
  "properties": {
    "iso:country":"AU",
    "sg:address":"182 Grafton St",
    "sg:city":"Cairns",
    "sg:classifiers":[
        {
            "category":"Government",
            "subcategory":"Court House",
            "type":"Public Place"
        }
    ],
    "sg:phone":"+61 7 4031 3590",
    "sg:postcode":"4870",
    "sg:province":"QLD",
    "sg:tags":[
        "personal",
        "marriage",
        "family",
        "counselling"
    ],
    "wof:name":"Sexual Assault Service (FPQ Cairns)",
    "wof:placetype":"venue"
},
  "geometry": {"coordinates":[145.77023315400001,-16.9217834473],"type":"Point"}
}