{
  "type": "Feature",
  "properties": {
    "addr:full":"Oval Ave Warooka SA 5577",
    "addr:postcode":"5577",
    "addr:street":"Ave",
    "iso:country":"AU",
    "sg:address":"Oval Ave",
    "sg:city":"Warooka",
    "sg:classifiers":[
        {
            "category":"Arena",
            "subcategory":"Sports Club",
            "type":"Entertainment"
        }
    ],
    "sg:phone":"+61 8 8854 5198",
    "sg:postcode":"5577",
    "sg:province":"SA",
    "sg:tags":[
        "australian",
        "football",
        "rule"
    ],
    "wof:name":"Western United Football Club Incorporated",
    "wof:placetype":"venue"
},
  "geometry": {"coordinates":[137.398269653,-34.9914588928],"type":"Point"}
}