{
  "type": "Feature",
  "properties": {
    "iso:country":"AU",
    "sg:address":"Westridge Shopng Cntr 300 West St",
    "sg:city":"Toowoomba",
    "sg:classifiers":[
        {
            "category":"Food & Beverages",
            "subcategory":"Bakery",
            "type":"Retail Goods"
        }
    ],
    "sg:phone":"+61 7 4635 6913",
    "sg:postcode":"4350",
    "sg:province":"QLD",
    "sg:tags":[
        "baker"
    ],
    "wof:name":"Brumby's Bakeries",
    "wof:placetype":"venue"
},
  "geometry": {"coordinates":[151.937164,-27.596003],"type":"Point"}
}