{
  "type": "Feature",
  "properties": {
    "addr:full":"Shop 3/ 6 Kenny St Wollongong NSW 2500",
    "addr:housenumber":"shop 3 / 6",
    "addr:postcode":"2500",
    "addr:street":"Kenny St",
    "iso:country":"AU",
    "sg:address":"Shop 3/ 6 Kenny St",
    "sg:city":"Wollongong",
    "sg:classifiers":[
        {
            "category":"Education",
            "subcategory":"Dance Studio",
            "type":"Public Place"
        }
    ],
    "sg:phone":"+61 2 4226 1861",
    "sg:postcode":"2500",
    "sg:province":"NSW",
    "sg:tags":[
        "venue",
        "tuition"
    ],
    "wof:name":"Cinnamon Twist School of Belly Dance",
    "wof:placetype":"venue"
},
  "geometry": {"coordinates":[150.89179999999999,-34.426422],"type":"Point"}
}