{
  "type": "Feature",
  "properties": {
    "addr:full":"316 Stephensons Rd Mt Waverley VIC 3149",
    "addr:housenumber":"316",
    "addr:postcode":"3149",
    "addr:street":"Stephensons Rd",
    "iso:country":"AU",
    "sg:address":"316 Stephensons Rd",
    "sg:city":"Mt Waverley",
    "sg:classifiers":[
        {
            "category":"Autos & Motor Vehicles",
            "subcategory":"Auto Supplies",
            "type":"Retail Goods"
        }
    ],
    "sg:phone":"+61 3 9807 1334",
    "sg:postcode":"3149",
    "sg:province":"VIC",
    "sg:tags":[
        "accessory"
    ],
    "wof:name":"Renagate Sequential Shifters",
    "wof:placetype":"venue"
},
  "geometry": {"coordinates":[145.128616333,-37.8789215088],"type":"Point"}
}