{
  "type": "Feature",
  "properties": {
    "addr:full":"Shed 2, 31 Premier Cct Warana QLD 4575",
    "addr:housenumber":"31",
    "addr:postcode":"4575",
    "addr:street":"Premier Cct",
    "iso:country":"AU",
    "sg:address":"Shed 2, 31 Premier Cct",
    "sg:city":"Warana",
    "sg:classifiers":[
        {
            "category":"Real Estate",
            "subcategory":"Real Estate Agent",
            "type":"Services"
        }
    ],
    "sg:phone":"+61 7 5437 8111",
    "sg:postcode":"4575",
    "sg:province":"QLD",
    "sg:tags":[
        "handyman's",
        "equipment",
        "hire",
        "builders",
        "contractor"
    ],
    "sg:website":"http://www.jchire.com.au",
    "wof:name":"J C Hire Service",
    "wof:placetype":"venue"
},
  "geometry": {"coordinates":[153.13076799999999,-26.719839],"type":"Point"}
}