{
  "type": "Feature",
  "properties": {
    "addr:full":"5 Wallaringa Ave Neutral Bay NSW 2089",
    "addr:housenumber":"5",
    "addr:postcode":"2089",
    "addr:street":"Wallaringa Ave",
    "iso:country":"AU",
    "sg:address":"5 Wallaringa Ave",
    "sg:city":"Neutral Bay",
    "sg:classifiers":[
        {
            "category":"Museum",
            "type":"Entertainment"
        }
    ],
    "sg:phone":"+61 2 9953 4453",
    "sg:postcode":"2089",
    "sg:province":"NSW",
    "wof:name":"May Gibbs' Nutcote Trust",
    "wof:placetype":"venue"
},
  "geometry": {"coordinates":[151.220901489,-33.8411712646],"type":"Point"}
}