{
  "type": "Feature",
  "properties": {
    "addr:full":"15- 16 Carl Crt Hallam VIC 3803",
    "addr:housenumber":"16",
    "addr:postcode":"3803",
    "addr:street":"Carl Crt",
    "iso:country":"AU",
    "sg:address":"15- 16 Carl Crt",
    "sg:city":"Hallam",
    "sg:classifiers":[
        {
            "category":"Building & Trades",
            "subcategory":"Construction",
            "type":"Services"
        }
    ],
    "sg:phone":"+61 3 9796 3742",
    "sg:postcode":"3803",
    "sg:province":"VIC",
    "sg:tags":[
        "welding"
    ],
    "wof:name":"McKean Sheet Metal Fabrications",
    "wof:placetype":"venue"
},
  "geometry": {"coordinates":[145.26817321799999,-38.0084877014],"type":"Point"}
}