{
  "type": "Feature",
  "properties": {
    "addr:full":"PO Box 7 West Perth WA 6005",
    "addr:postcode":"6005",
    "iso:country":"AU",
    "sg:address":"PO Box 7",
    "sg:city":"West Perth",
    "sg:classifiers":[
        {
            "category":"Government",
            "subcategory":"Customs House",
            "type":"Public Place"
        }
    ],
    "sg:phone":"+61 8 9481 5122",
    "sg:postcode":"6005",
    "sg:province":"WA",
    "sg:tags":[
        "title",
        "management",
        "stratum"
    ],
    "wof:name":"Strata Titles Institute Of WA (Inc)",
    "wof:placetype":"venue"
},
  "geometry": {"coordinates":[115.8465271,-31.9449996948],"type":"Point"}
}