{
  "type": "Feature",
  "properties": {
    "iso:country":"AU",
    "sg:address":"Factory 1 46 Aerodrome Rd",
    "sg:city":"Caboolture",
    "sg:classifiers":[
        {
            "category":"Home & Garden",
            "subcategory":"Building Materials",
            "type":"Retail Goods"
        }
    ],
    "sg:phone":"+61 7 5499 0332",
    "sg:postcode":"4510",
    "sg:province":"QLD",
    "sg:tags":[
        "skylight"
    ],
    "wof:name":"Suncity Roofing & Supplies Pty Ltd",
    "wof:placetype":"venue"
},
  "geometry": {"coordinates":[152.981079,-27.08149],"type":"Point"}
}