{
  "type": "Feature",
  "properties": {
    "addr:full":"33 Bank St Box Hill VIC 3128",
    "addr:housenumber":"33",
    "addr:postcode":"3128",
    "addr:street":"Bank St",
    "iso:country":"AU",
    "sg:address":"33 Bank St",
    "sg:city":"Box Hill",
    "sg:classifiers":[
        {
            "category":"Education",
            "subcategory":"Kindergarten",
            "type":"Public Place"
        }
    ],
    "sg:phone":"+61 3 9890 8457",
    "sg:postcode":"3128",
    "sg:province":"VIC",
    "sg:tags":[
        "pre-schools"
    ],
    "wof:name":"St Peters Anglican Kindergarten",
    "wof:placetype":"venue"
},
  "geometry": {"coordinates":[145.127243042,-37.8196258545],"type":"Point"}
}