{
  "type": "Feature",
  "properties": {
    "addr:full":"37 Wells Rd Mordialloc VIC 3195",
    "addr:housenumber":"37",
    "addr:postcode":"3195",
    "addr:street":"Wells Rd",
    "iso:country":"AU",
    "sg:address":"37 Wells Rd",
    "sg:city":"Mordialloc",
    "sg:classifiers":[
        {
            "category":"Manufacturing",
            "subcategory":"Glass & Minerals",
            "type":"Manufacturing & Wholesale Goods"
        }
    ],
    "sg:phone":"+61 3 8586 5500",
    "sg:postcode":"3195",
    "sg:province":"VIC",
    "sg:tags":[
        "fabricator",
        "fibreglass"
    ],
    "wof:name":"Bolwell Corporation Pty Ltd",
    "wof:placetype":"venue"
},
  "geometry": {"coordinates":[145.10208129899999,-38.0110282898],"type":"Point"}
}