{
  "type": "Feature",
  "properties": {
    "addr:full":"117- 123 Pacific Hwy Tweed Heads South NSW 2486",
    "addr:housenumber":"123",
    "addr:postcode":"2486",
    "addr:street":"Pacific Hwy",
    "iso:country":"AU",
    "sg:address":"117- 123 Pacific Hwy",
    "sg:city":"Tweed Heads South",
    "sg:classifiers":[
        {
            "category":"Autos & Motor Vehicles",
            "subcategory":"Automobile Sales",
            "type":"Retail Goods"
        }
    ],
    "sg:phone":"+61 7 5569 1377",
    "sg:postcode":"2486",
    "sg:province":"NSW",
    "sg:tags":[
        "car",
        "new"
    ],
    "wof:name":"Tweed Chrysler Jeep",
    "wof:placetype":"venue"
},
  "geometry": {"coordinates":[153.491744995,-28.213344574],"type":"Point"}
}