{
  "type": "Feature",
  "properties": {
    "addr:full":"750 Mountain Hwy Bayswater VIC 3153",
    "addr:housenumber":"750",
    "addr:postcode":"3153",
    "addr:street":"Mountain Hwy",
    "iso:country":"AU",
    "sg:address":"750 Mountain Hwy",
    "sg:city":"Bayswater",
    "sg:classifiers":[
        {
            "category":"Retail",
            "subcategory":"Auto Repair",
            "type":"Services"
        }
    ],
    "sg:phone":"+61 3 9720 2058",
    "sg:postcode":"3153",
    "sg:province":"VIC",
    "sg:tags":[
        "electrical"
    ],
    "wof:name":"Station Auto Electrics",
    "wof:placetype":"venue"
},
  "geometry": {"coordinates":[145.266555786,-37.8407516479],"type":"Point"}
}