{
  "type": "Feature",
  "properties": {
    "addr:full":"134 Merrylands Rd Merrylands NSW 2160",
    "addr:housenumber":"134",
    "addr:postcode":"2160",
    "addr:street":"Merrylands Rd",
    "iso:country":"AU",
    "sg:address":"134 Merrylands Rd",
    "sg:city":"Merrylands",
    "sg:classifiers":[
        {
            "category":"Personal",
            "subcategory":"Beauty Salon",
            "type":"Services"
        }
    ],
    "sg:phone":"+61 2 9637 4847",
    "sg:postcode":"2160",
    "sg:province":"NSW",
    "sg:tags":[
        "hairdresser"
    ],
    "wof:name":"Paul's Barber",
    "wof:placetype":"venue"
},
  "geometry": {"coordinates":[150.990997314,-33.8368377686],"type":"Point"}
}