{
  "type": "Feature",
  "properties": {
    "addr:full":"115 Bellambi La Bellambi NSW 2518",
    "addr:housenumber":"115",
    "addr:postcode":"2518",
    "addr:street":"Bellambi La Bellambi",
    "iso:country":"AU",
    "sg:address":"115 Bellambi La",
    "sg:city":"Bellambi",
    "sg:classifiers":[
        {
            "category":"Autos & Motor Vehicles",
            "subcategory":"Fuel & Gas Station",
            "type":"Retail Goods"
        }
    ],
    "sg:phone":"+61 2 4285 9183",
    "sg:postcode":"2518",
    "sg:province":"NSW",
    "wof:name":"Russell Vale Self Serve",
    "wof:placetype":"venue"
},
  "geometry": {"coordinates":[150.89944499999999,-34.361073],"type":"Point"}
}