{
  "type": "Feature",
  "properties": {
    "iso:country":"AU",
    "sg:address":"GPO Box 413",
    "sg:city":"NN Melbourne",
    "sg:classifiers":[
        {
            "category":"Organizations",
            "subcategory":"Professional Association",
            "type":"Services"
        }
    ],
    "sg:phone":"+61 3 9607 6908",
    "sg:postcode":"3001",
    "sg:province":"VIC",
    "sg:tags":[
        "organisation",
        "business"
    ],
    "wof:name":"Institute Of Arbitrators & Mediators Australia",
    "wof:placetype":"venue"
},
  "geometry": {"coordinates":[144.88279724099999,-37.8407249451],"type":"Point"}
}