{
  "type": "Feature",
  "properties": {
    "iso:country":"AU",
    "sg:address":"25 Keelendi Rd",
    "sg:city":"Cessnock",
    "sg:classifiers":[
        {
            "category":"Retail",
            "subcategory":"Storage",
            "type":"Services"
        }
    ],
    "sg:phone":"+61 2 4991 2445",
    "sg:postcode":"2325",
    "sg:province":"NSW",
    "sg:tags":[
        "removal",
        "furniture"
    ],
    "wof:name":"Matilda Bay Removals",
    "wof:placetype":"venue"
},
  "geometry": {"coordinates":[151.335327148,-32.8449554443],"type":"Point"}
}