{
  "type": "Feature",
  "properties": {
    "addr:full":"66 Wellington St Cleveland QLD 4163",
    "addr:housenumber":"66",
    "addr:postcode":"4163",
    "addr:street":"Wellington St",
    "iso:country":"AU",
    "sg:address":"66 Wellington St",
    "sg:city":"Cleveland",
    "sg:classifiers":[
        {
            "category":"Building & Trades",
            "subcategory":"Landscaping Services",
            "type":"Services"
        }
    ],
    "sg:phone":"+61 412 759 308",
    "sg:postcode":"4163",
    "sg:province":"QLD",
    "sg:tags":[
        "stump",
        "tree",
        "felling",
        "removal"
    ],
    "wof:name":"Livingstone R & L",
    "wof:placetype":"venue"
},
  "geometry": {"coordinates":[153.255462647,-27.5307178497],"type":"Point"}
}