{
  "type": "Feature",
  "properties": {
    "addr:full":"207 Beaudesert Rd Moorooka QLD 4105",
    "addr:housenumber":"207",
    "addr:postcode":"4105",
    "addr:street":"Beaudesert Rd",
    "iso:country":"AU",
    "sg:address":"207 Beaudesert Rd",
    "sg:city":"Moorooka",
    "sg:classifiers":[
        {
            "category":"Manufacturing",
            "subcategory":"Motor Vehicles & Parts",
            "type":"Manufacturing & Wholesale Goods"
        }
    ],
    "sg:phone":"+61 7 3892 2565",
    "sg:postcode":"4105",
    "sg:province":"QLD",
    "sg:tags":[
        "replacement"
    ],
    "wof:name":"Super Cheap Auto",
    "wof:placetype":"venue"
},
  "geometry": {"coordinates":[153.02488708499999,-27.5332832336],"type":"Point"}
}