{
  "type": "Feature",
  "properties": {
    "iso:country":"AU",
    "sg:address":"Carlton Pde",
    "sg:city":"Port Augusta",
    "sg:classifiers":[
        {
            "category":"Building & Trades",
            "subcategory":"Plumbing",
            "type":"Services"
        }
    ],
    "sg:phone":"+61 8 8641 0066",
    "sg:postcode":"5700",
    "sg:province":"SA",
    "sg:tags":[
        "plumber",
        "gasfitters"
    ],
    "wof:name":"Footner's Plumbing Contractors Pty Ltd",
    "wof:placetype":"venue"
},
  "geometry": {"coordinates":[137.76934814399999,-32.4964675903],"type":"Point"}
}