{
  "type": "Feature",
  "properties": {
    "addr:full":"Shop 31 , Campus Shopping Village Smithfield QLD 4878",
    "addr:housenumber":"shop 31",
    "addr:postcode":"4878",
    "addr:street":"Campus",
    "iso:country":"AU",
    "sg:address":"Shop 31",
    "sg:city":", Campus Shopping Village Smithfield",
    "sg:classifiers":[
        {
            "category":"Shopping",
            "subcategory":"Baby Store",
            "type":"Retail Goods"
        }
    ],
    "sg:phone":"+61 7 4057 9911",
    "sg:postcode":"4878",
    "sg:province":"QLD",
    "sg:tags":[
        "wear"
    ],
    "wof:name":"Tropical Beach Babies",
    "wof:placetype":"venue"
},
  "geometry": {"coordinates":[145.68907165499999,-16.83852005],"type":"Point"}
}