{
  "type": "Feature",
  "properties": {
    "addr:full":"Unit 2, 9 Charlton Crt Stuart Park NT 0820",
    "addr:housenumber":"9",
    "addr:postcode":"0820",
    "addr:street":"Charlton Crt",
    "iso:country":"AU",
    "sg:address":"Unit 2, 9 Charlton Crt",
    "sg:city":"Stuart Park",
    "sg:classifiers":[
        {
            "category":"Real Estate",
            "subcategory":"Architect",
            "type":"Services"
        }
    ],
    "sg:phone":"+61 8 8941 8262",
    "sg:postcode":"0820",
    "sg:province":"NT",
    "wof:name":"Architects Studio Pty Ltd",
    "wof:placetype":"venue"
},
  "geometry": {"coordinates":[130.85932922399999,-12.4321022034],"type":"Point"}
}