{
  "type": "Feature",
  "properties": {
    "iso:country":"AU",
    "sg:address":"164 Belmore Rd",
    "sg:city":"Randwick",
    "sg:classifiers":[
        {
            "category":"Health Services",
            "subcategory":"Doctor",
            "type":"Services"
        }
    ],
    "sg:phone":"+61 2 9398 9555",
    "sg:postcode":"2031",
    "sg:province":"NSW",
    "sg:tags":[
        "medical",
        "practitioner"
    ],
    "wof:name":"IHC Randwick",
    "wof:placetype":"venue"
},
  "geometry": {"coordinates":[151.24215698200001,-33.9178581238],"type":"Point"}
}