{
  "type": "Feature",
  "properties": {
    "addr:full":"Level 9, 162-166 Goulburn St Surry Hills, NSW 2010",
    "addr:housenumber":"162-166",
    "addr:postcode":"2010",
    "addr:street":"Goulburn St",
    "iso:country":"AU",
    "sg:address":"Level 9, 162-166 Goulburn St",
    "sg:city":"Surry Hills, NSW",
    "sg:classifiers":[
        {
            "category":"Professional",
            "subcategory":"Computer Services",
            "type":"Services"
        }
    ],
    "sg:postcode":"2010",
    "sg:tags":[
        "ecommerce",
        "shopping-cart",
        "email-marketing",
        "saas",
        "content-management"
    ],
    "sg:website":"http://www.Interspire.com",
    "wof:name":"Interspire",
    "wof:placetype":"venue"
},
  "geometry": {"coordinates":[151.21231,-33.878684],"type":"Point"}
}