{
  "type": "Feature",
  "properties": {
    "addr:full":"Shop 318 Kawana Waters Shopping Centre Kawana Waters QLD 4575",
    "addr:housenumber":"318",
    "addr:postcode":"4575",
    "addr:street":"Kawana Waters",
    "iso:country":"AU",
    "sg:address":"Shop 318",
    "sg:city":"Kawana Waters Shopping Centre Kawana Waters",
    "sg:classifiers":[
        {
            "category":"Shopping",
            "subcategory":"Mobile Phones",
            "type":"Retail Goods"
        }
    ],
    "sg:phone":"+61 7 5444 7166",
    "sg:postcode":"4575",
    "sg:province":"QLD",
    "sg:tags":[
        "telephone",
        "accessory"
    ],
    "wof:name":"Vodafone",
    "wof:placetype":"venue"
},
  "geometry": {"coordinates":[153.12910500000001,-26.73616],"type":"Point"}
}