{
  "type": "Feature",
  "properties": {
    "iso:country":"AU",
    "sg:address":"Cnr Michael St & Princes Hwy",
    "sg:city":"Pakenham",
    "sg:classifiers":[
        {
            "category":"Autos & Motor Vehicles",
            "subcategory":"Auto Supplies",
            "type":"Retail Goods"
        }
    ],
    "sg:phone":"+61 3 5940 1669",
    "sg:postcode":"3810",
    "sg:province":"VIC",
    "sg:tags":[
        "tyre"
    ],
    "wof:name":"Pakenham Tyre & Mechanical Service",
    "wof:placetype":"venue"
},
  "geometry": {"coordinates":[145.457718,-38.06255],"type":"Point"}
}