{
  "type": "Feature",
  "properties": {
    "addr:full":"213 Ingham Rd West End QLD 4810",
    "addr:housenumber":"213",
    "addr:postcode":"4810",
    "addr:street":"Ingham Rd",
    "iso:country":"AU",
    "sg:address":"213 Ingham Rd",
    "sg:city":"West End",
    "sg:classifiers":[
        {
            "category":"Donuts",
            "subcategory":"None",
            "type":"Food & Drink"
        }
    ],
    "sg:phone":"+61 7 4725 6544",
    "sg:postcode":"4810",
    "sg:province":"QLD",
    "sg:tags":[
        "die",
        "engraver",
        "sinker"
    ],
    "wof:name":"Townsville Signs Engravers of Townsville",
    "wof:placetype":"venue"
},
  "geometry": {"coordinates":[146.784378,-19.266323],"type":"Point"}
}