{
  "type": "Feature",
  "properties": {
    "addr:full":"Shop 8 Queens Pde Brighton QLD 4017",
    "addr:housenumber":"shop 8",
    "addr:postcode":"4017",
    "addr:street":"Queens Pde",
    "iso:country":"AU",
    "sg:address":"Shop 8 Queens Pde",
    "sg:city":"Brighton",
    "sg:classifiers":[
        {
            "category":"Personal",
            "subcategory":"Massage",
            "type":"Services"
        }
    ],
    "sg:phone":"+61 7 3869 2622",
    "sg:postcode":"4017",
    "sg:province":"QLD",
    "sg:tags":[
        "therapy"
    ],
    "wof:name":"Elks Jean",
    "wof:placetype":"venue"
},
  "geometry": {"coordinates":[153.06150817899999,-27.3037509918],"type":"Point"}
}