{
  "type": "Feature",
  "properties": {
    "addr:full":"27 Salisbury Rd Hornsby NSW 2077",
    "addr:housenumber":"27",
    "addr:postcode":"2077",
    "addr:street":"Salisbury Rd",
    "iso:country":"AU",
    "sg:address":"27 Salisbury Rd",
    "sg:city":"Hornsby",
    "sg:classifiers":[
        {
            "category":"Wholesale",
            "subcategory":"Medical Equipment & Supplies",
            "type":"Manufacturing & Wholesale Goods"
        }
    ],
    "sg:phone":"+61 2 9987 4891",
    "sg:postcode":"2077",
    "sg:province":"NSW",
    "sg:tags":[
        "dental"
    ],
    "wof:name":"Caredent",
    "wof:placetype":"venue"
},
  "geometry": {"coordinates":[151.11129760700001,-33.6956787109],"type":"Point"}
}