{
  "type": "Feature",
  "properties": {
    "iso:country":"AU",
    "sg:address":"41 Peter St",
    "sg:city":"Blacktown",
    "sg:classifiers":[
        {
            "category":"Education",
            "subcategory":"Music School",
            "type":"Public Place"
        }
    ],
    "sg:phone":"+61 2 9676 5018",
    "sg:postcode":"2148",
    "sg:province":"NSW",
    "sg:tags":[
        "teacher"
    ],
    "wof:name":"Stuart Adams",
    "wof:placetype":"venue"
},
  "geometry": {"coordinates":[150.91444397000001,-33.7648773193],"type":"Point"}
}