{
  "type": "Feature",
  "properties": {
    "addr:full":"20 Bronhill Rd Ringwood East VIC 3135",
    "addr:housenumber":"20",
    "addr:postcode":"3135",
    "addr:street":"Bronhill Rd",
    "iso:country":"AU",
    "sg:address":"20 Bronhill Rd",
    "sg:city":"Ringwood East",
    "sg:classifiers":[
        {
            "category":"Wholesale",
            "subcategory":"Construction Materials",
            "type":"Manufacturing & Wholesale Goods"
        }
    ],
    "sg:phone":"+61 408 374 058",
    "sg:postcode":"3135",
    "sg:province":"VIC",
    "sg:tags":[
        "wholesaler",
        "lighting",
        "mfrs",
        "accessory"
    ],
    "wof:name":"Lighting Services",
    "wof:placetype":"venue"
},
  "geometry": {"coordinates":[145.25743102999999,-37.7987327576],"type":"Point"}
}