{
  "type": "Feature",
  "properties": {
    "addr:full":"239 Park St South Melbourne VIC 3205",
    "addr:housenumber":"239",
    "addr:postcode":"3205",
    "addr:street":"Park St",
    "iso:country":"AU",
    "sg:address":"239 Park St",
    "sg:city":"South Melbourne",
    "sg:classifiers":[
        {
            "category":"Banks & Credit Unions",
            "subcategory":"Financial Services",
            "type":"Services"
        }
    ],
    "sg:phone":"+61 3 9696 9744",
    "sg:postcode":"3205",
    "sg:province":"VIC",
    "sg:tags":[
        "finance",
        "motor",
        "vehicle"
    ],
    "wof:name":"Melbourne Car Loans",
    "wof:placetype":"venue"
},
  "geometry": {"coordinates":[144.96006800000001,-37.835785],"type":"Point"}
}