{
  "type": "Feature",
  "properties": {
    "addr:full":"15/ 262 Miller Rd Villawood NSW 2163",
    "addr:housenumber":"15 / 262",
    "addr:postcode":"2163",
    "addr:street":"Miller Rd",
    "iso:country":"AU",
    "sg:address":"15/ 262 Miller Rd",
    "sg:city":"Villawood",
    "sg:classifiers":[
        {
            "category":"Retail",
            "subcategory":"Auto Repair",
            "type":"Services"
        }
    ],
    "sg:phone":"+61 2 9724 3030",
    "sg:postcode":"2163",
    "sg:province":"NSW",
    "sg:tags":[
        "repairer",
        "motor",
        "engineer"
    ],
    "wof:name":"Unique Automotive",
    "wof:placetype":"venue"
},
  "geometry": {"coordinates":[150.99249267600001,-33.8864250183],"type":"Point"}
}