{
  "type": "Feature",
  "properties": {
    "addr:full":"Cnr Queen St & Edgecliff Rd Woollahra NSW 2025",
    "addr:postcode":"2025",
    "addr:street":"Cnr Queen St & Edgecliff Rd",
    "iso:country":"AU",
    "sg:address":"Cnr Queen St & Edgecliff Rd",
    "sg:city":"Woollahra",
    "sg:classifiers":[
        {
            "category":"Organizations",
            "subcategory":"Community Association",
            "type":"Services"
        }
    ],
    "sg:phone":"+61 2 9363 5957",
    "sg:postcode":"2025",
    "sg:province":"NSW",
    "sg:tags":[
        "club",
        "senior",
        "citizen"
    ],
    "wof:name":"Woollahra Senior Citizens Welfare Association",
    "wof:placetype":"venue"
},
  "geometry": {"coordinates":[151.243286133,-33.8872909546],"type":"Point"}
}