{
  "type": "Feature",
  "properties": {
    "addr:full":"101 Bridge St Benalla VIC 3672",
    "addr:housenumber":"101",
    "addr:postcode":"3672",
    "addr:street":"Bridge St",
    "iso:country":"AU",
    "sg:address":"101 Bridge St",
    "sg:city":"Benalla",
    "sg:classifiers":[
        {
            "category":"Professional",
            "subcategory":"Art Services",
            "type":"Services"
        }
    ],
    "sg:phone":"+61 3 5762 1817",
    "sg:postcode":"3672",
    "sg:province":"VIC",
    "sg:tags":[
        "picture",
        "frame",
        "framing"
    ],
    "wof:name":"She's Arty",
    "wof:placetype":"venue"
},
  "geometry": {"coordinates":[145.98666399999999,-36.550865],"type":"Point"}
}