{
  "type": "Feature",
  "properties": {
    "iso:country":"AU",
    "sg:address":"101 Bridge St",
    "sg:city":"Benalla",
    "sg:classifiers":[
        {
            "category":"Professional",
            "subcategory":"Art Services",
            "type":"Services"
        }
    ],
    "sg:phone":"+61 3 5762 1817",
    "sg:postcode":"3672",
    "sg:province":"VIC",
    "sg:tags":[
        "picture",
        "frame",
        "framing"
    ],
    "wof:name":"She's Arty",
    "wof:placetype":"venue"
},
  "geometry": {"coordinates":[145.986664,-36.550865],"type":"Point"}
}