{
  "type": "Feature",
  "properties": {
    "iso:country":"AU",
    "sg:address":"Mason Rd",
    "sg:city":"Kuranda",
    "sg:classifiers":[
        {
            "category":"Health Services",
            "subcategory":"Health Practitioner",
            "type":"Services"
        }
    ],
    "sg:phone":"+61 7 4093 9143",
    "sg:postcode":"4872",
    "sg:province":"QLD",
    "sg:tags":[
        "reiki"
    ],
    "wof:name":"Hammond Sandra",
    "wof:placetype":"venue"
},
  "geometry": {"coordinates":[145.630401611,-16.8337078094],"type":"Point"}
}