{
  "type": "Feature",
  "properties": {
    "addr:full":"38 Redwood Drv Hoppers Crossing VIC 3029",
    "addr:housenumber":"38",
    "addr:postcode":"3029",
    "addr:street":"Redwood Drv",
    "iso:country":"AU",
    "sg:address":"38 Redwood Drv",
    "sg:city":"Hoppers Crossing",
    "sg:classifiers":[
        {
            "category":"Manufacturing",
            "subcategory":"Metals",
            "type":"Manufacturing & Wholesale Goods"
        }
    ],
    "sg:phone":"+61 3 9748 0340",
    "sg:postcode":"3029",
    "sg:province":"VIC",
    "sg:tags":[
        "steel",
        "fabricator",
        "mfrs"
    ],
    "wof:name":"Wyndham Steel Fabricators",
    "wof:placetype":"venue"
},
  "geometry": {"coordinates":[144.693466,-37.855984],"type":"Point"}
}