{
  "type": "Feature",
  "properties": {
    "addr:full":"Suite 5 899 Whitehorse Rd Box Hill VIC 3128",
    "addr:housenumber":"899",
    "addr:postcode":"3128",
    "addr:street":"Whitehorse Rd",
    "iso:country":"AU",
    "sg:address":"Suite 5 899 Whitehorse Rd",
    "sg:city":"Box Hill",
    "sg:classifiers":[
        {
            "category":"Shopping",
            "subcategory":"Computers & Home Electronics",
            "type":"Retail Goods"
        }
    ],
    "sg:phone":"+61 3 9896 8833",
    "sg:postcode":"3128",
    "sg:province":"VIC",
    "sg:tags":[
        "hardware",
        "equipment"
    ],
    "wof:name":"ACA Image Centre",
    "wof:placetype":"venue"
},
  "geometry": {"coordinates":[145.120803833,-37.8173980713],"type":"Point"}
}