{
  "type": "Feature",
  "properties": {
    "addr:full":"90 Neill St Beaufort VIC 3373",
    "addr:housenumber":"90",
    "addr:postcode":"3373",
    "addr:street":"Neill St",
    "iso:country":"AU",
    "sg:address":"90 Neill St",
    "sg:city":"Beaufort",
    "sg:classifiers":[
        {
            "category":"Restaurant",
            "type":"Food & Drink"
        }
    ],
    "sg:phone":"+61 3 5349 2877",
    "sg:postcode":"3373",
    "sg:province":"VIC",
    "wof:name":"Columbine Cottage",
    "wof:placetype":"venue"
},
  "geometry": {"coordinates":[143.375854492,-37.4287986755],"type":"Point"}
}