{
  "type": "Feature",
  "properties": {
    "iso:country":"AU",
    "sg:address":"8a George St",
    "sg:city":"Moonta",
    "sg:classifiers":[
        {
            "category":"Health Services",
            "subcategory":"Chiropractor",
            "type":"Services"
        }
    ],
    "sg:phone":"+61 8 8825 2822",
    "sg:postcode":"5558",
    "sg:province":"SA",
    "wof:name":"Plank Chiropractic Centres",
    "wof:placetype":"venue"
},
  "geometry": {"coordinates":[137.59121704099999,-34.068271637],"type":"Point"}
}