{
  "type": "Feature",
  "properties": {
    "addr:full":"86 Clayton Rd Narrogin WA 6312",
    "addr:housenumber":"86",
    "addr:postcode":"6312",
    "addr:street":"Clayton Rd",
    "iso:country":"AU",
    "sg:address":"86 Clayton Rd",
    "sg:city":"Narrogin",
    "sg:classifiers":[
        {
            "category":"Home & Garden",
            "subcategory":"Building Materials",
            "type":"Retail Goods"
        }
    ],
    "sg:phone":"+61 8 9881 1077",
    "sg:postcode":"6312",
    "sg:province":"WA",
    "sg:tags":[
        "lawn",
        "cutting",
        "maintenance"
    ],
    "wof:name":"Creative Design & Garden Care",
    "wof:placetype":"venue"
},
  "geometry": {"coordinates":[117.167572022,-32.9306640625],"type":"Point"}
}