{
  "type": "Feature",
  "properties": {
    "addr:full":"Unit 3 / 10 Clifton St Prahran VIC 3181",
    "addr:housenumber":"10",
    "addr:postcode":"3181",
    "addr:street":"Clifton St",
    "iso:country":"AU",
    "sg:address":"Unit 3 / 10 Clifton St",
    "sg:city":"Prahran",
    "sg:classifiers":[
        {
            "category":"Professional",
            "subcategory":"Art Services",
            "type":"Services"
        }
    ],
    "sg:phone":"+61 3 9533 6293",
    "sg:postcode":"3181",
    "sg:province":"VIC",
    "sg:tags":[
        "graphic",
        "designer"
    ],
    "wof:name":"The Refinery Design",
    "wof:placetype":"venue"
},
  "geometry": {"coordinates":[144.995361328,-37.8512573242],"type":"Point"}
}