{
  "type": "Feature",
  "properties": {
    "addr:full":"Pascoe Vale Rd Strathmore VIC 3041",
    "addr:postcode":"3041",
    "addr:street":"Pascoe Vale Rd",
    "iso:country":"AU",
    "sg:address":"Pascoe Vale Rd",
    "sg:city":"Strathmore",
    "sg:classifiers":[
        {
            "category":"Education",
            "subcategory":"School",
            "type":"Public Place"
        }
    ],
    "sg:phone":"+61 3 9379 7999",
    "sg:postcode":"3041",
    "sg:province":"VIC",
    "sg:tags":[
        "state",
        "except",
        "nsw"
    ],
    "wof:name":"Strathmore Secondary College",
    "wof:placetype":"venue"
},
  "geometry": {"coordinates":[144.924316406,-37.7339057922],"type":"Point"}
}