{
  "type": "Feature",
  "properties": {
    "addr:full":"227 Ballarat Rd Braybrook VIC 3019",
    "addr:housenumber":"227",
    "addr:postcode":"3019",
    "addr:street":"Ballarat Rd",
    "iso:country":"AU",
    "sg:address":"227 Ballarat Rd",
    "sg:city":"Braybrook",
    "sg:classifiers":[
        {
            "category":"Food & Beverages",
            "subcategory":"Supermarket",
            "type":"Retail Goods"
        }
    ],
    "sg:phone":"+61 3 9317 5644",
    "sg:postcode":"3019",
    "sg:province":"VIC",
    "sg:tags":[
        "grocery",
        "store"
    ],
    "wof:name":"Safeway",
    "wof:placetype":"venue"
},
  "geometry": {"coordinates":[144.86485290499999,-37.7813491821],"type":"Point"}
}