{
  "type": "Feature",
  "properties": {
    "addr:full":"3/57 Canton Beach Rd Toukley NSW 2263",
    "addr:housenumber":"/ 57",
    "addr:postcode":"2263",
    "addr:street":"Beach Rd",
    "iso:country":"AU",
    "sg:address":"3/57 Canton Beach Rd",
    "sg:city":"Toukley",
    "sg:classifiers":[
        {
            "category":"Cafe",
            "type":"Food & Drink"
        }
    ],
    "sg:phone":"+61 2 4396 3113",
    "sg:postcode":"2263",
    "sg:province":"NSW",
    "wof:name":"Blu -Js Cafe",
    "wof:placetype":"venue"
},
  "geometry": {"coordinates":[151.54072600000001,-33.264477],"type":"Point"}
}