{
  "type": "Feature",
  "properties": {
    "iso:country":"AU",
    "sg:address":"Shp 2/ 22 Cadell St",
    "sg:city":"Goolwa",
    "sg:classifiers":[
        {
            "category":"Fast Food",
            "type":"Food & Drink"
        }
    ],
    "sg:phone":"+61 8 8555 5419",
    "sg:postcode":"5214",
    "sg:province":"SA",
    "sg:tags":[
        "away",
        "take"
    ],
    "wof:name":"Cadell Street Fish & Chips",
    "wof:placetype":"venue"
},
  "geometry": {"coordinates":[138.78182983400001,-35.5008430481],"type":"Point"}
}