{
  "type": "Feature",
  "properties": {
    "iso:country":"AU",
    "sg:address":"1- Lt Princes St",
    "sg:city":"Flemington",
    "sg:classifiers":[
        {
            "category":"Travel",
            "subcategory":"Hostel",
            "type":"Entertainment"
        }
    ],
    "sg:phone":"+61 3 9376 1599",
    "sg:postcode":"3031",
    "sg:province":"VIC",
    "sg:tags":[
        "home"
    ],
    "wof:name":"Wintringham Hostels",
    "wof:placetype":"venue"
},
  "geometry": {"coordinates":[144.932861,-37.787502],"type":"Point"}
}