{
  "type": "Feature",
  "properties": {
    "addr:full":"36 Mt Ida Ave Hawthorn East VIC 3123",
    "addr:housenumber":"36",
    "addr:postcode":"3123",
    "addr:street":"Mt Ida Ave",
    "iso:country":"AU",
    "sg:address":"36 Mt Ida Ave",
    "sg:city":"Hawthorn East",
    "sg:classifiers":[
        {
            "category":"Shopping",
            "subcategory":"Discount & Variety Stores",
            "type":"Retail Goods"
        }
    ],
    "sg:phone":"+61 3 9813 1297",
    "sg:postcode":"3123",
    "sg:province":"VIC",
    "sg:tags":[
        "information",
        "cooking",
        "class"
    ],
    "wof:name":"Penny Harris",
    "wof:placetype":"venue"
},
  "geometry": {"coordinates":[145.05026245100001,-37.838306427],"type":"Point"}
}