{
  "type": "Feature",
  "properties": {
    "iso:country":"AU",
    "sg:address":"Casey Lifestyle Centre, 430- 440 Princess Hwy",
    "sg:city":"Narre Warren",
    "sg:classifiers":[
        {
            "category":"Autos & Motor Vehicles",
            "subcategory":"Auto Supplies",
            "type":"Retail Goods"
        }
    ],
    "sg:phone":"+61 3 8786 5444",
    "sg:postcode":"3805",
    "sg:province":"VIC",
    "sg:tags":[
        "automotive",
        "stereo",
        "radio"
    ],
    "wof:name":"JB HI-FI",
    "wof:placetype":"venue"
},
  "geometry": {"coordinates":[145.307388,-38.026234],"type":"Point"}
}