{
  "type": "Feature",
  "properties": {
    "addr:full":"2 Second Ave Loftus NSW 2232",
    "addr:housenumber":"2",
    "addr:postcode":"2232",
    "addr:street":"Second Ave",
    "iso:country":"AU",
    "sg:address":"2 Second Ave",
    "sg:city":"Loftus",
    "sg:classifiers":[
        {
            "category":"Building & Trades",
            "subcategory":"Construction",
            "type":"Services"
        }
    ],
    "sg:phone":"+61 2 9545 2016",
    "sg:postcode":"2232",
    "sg:province":"NSW",
    "sg:tags":[
        "concrete",
        "contractor"
    ],
    "wof:name":"Capri Concreting",
    "wof:placetype":"venue"
},
  "geometry": {"coordinates":[151.05189514200001,-34.0380592346],"type":"Point"}
}