{
  "type": "Feature",
  "properties": {
    "iso:country":"AU",
    "sg:address":"Level 15, 179 Elizabeth St",
    "sg:city":"Sydney",
    "sg:classifiers":[
        {
            "category":"Banks & Credit Unions",
            "subcategory":"Financial Services",
            "type":"Services"
        }
    ],
    "sg:phone":"+61 13 18 33",
    "sg:postcode":"2000",
    "sg:province":"NSW",
    "sg:tags":[
        "planning"
    ],
    "wof:name":"Financial Partners Pty Ltd",
    "wof:placetype":"venue"
},
  "geometry": {"coordinates":[151.209884644,-33.8724250793],"type":"Point"}
}