{
  "type": "Feature",
  "properties": {
    "addr:full":"11 Simpson Crt Golden Grove SA 5125",
    "addr:housenumber":"11",
    "addr:postcode":"5125",
    "addr:street":"Simpson Crt",
    "iso:country":"AU",
    "sg:address":"11 Simpson Crt",
    "sg:city":"Golden Grove",
    "sg:classifiers":[
        {
            "category":"Shopping",
            "subcategory":"Mobile Phones",
            "type":"Retail Goods"
        }
    ],
    "sg:phone":"+61 8 8289 3644",
    "sg:postcode":"5125",
    "sg:province":"SA",
    "sg:tags":[
        "wholesaler",
        "mfrs",
        "electrical",
        "switchboard"
    ],
    "wof:name":"Tolcher Motor & Process Controls",
    "wof:placetype":"venue"
},
  "geometry": {"coordinates":[138.69964599599999,-34.7809715271],"type":"Point"}
}