{
  "type": "Feature",
  "properties": {
    "addr:full":"143 Fitzmaurice St Wagga Wagga NSW 2650",
    "addr:housenumber":"143",
    "addr:postcode":"2650",
    "addr:street":"Fitzmaurice St",
    "iso:country":"AU",
    "sg:address":"143 Fitzmaurice St",
    "sg:city":"Wagga Wagga",
    "sg:classifiers":[
        {
            "category":"Travel",
            "subcategory":"Hotels & Motels",
            "type":"Entertainment"
        }
    ],
    "sg:phone":"+61 2 6921 1922",
    "sg:postcode":"2650",
    "sg:province":"NSW",
    "sg:website":"http://www.princeofwalesmotel.com.au/",
    "wof:name":"Comfort Inn Prince of Wales",
    "wof:placetype":"venue"
},
  "geometry": {"coordinates":[147.36880493199999,-35.1035728455],"type":"Point"}
}