{
  "type": "Feature",
  "properties": {
    "addr:full":"5/ 15 Mitchell St Nambour QLD 4560",
    "addr:housenumber":"/ 15",
    "addr:postcode":"4560",
    "addr:street":"Mitchell St",
    "iso:country":"AU",
    "sg:address":"5/ 15 Mitchell St",
    "sg:city":"Nambour",
    "sg:classifiers":[
        {
            "category":"Education",
            "subcategory":"Dance Studio",
            "type":"Public Place"
        }
    ],
    "sg:phone":"+61 7 5445 3107",
    "sg:postcode":"4560",
    "sg:province":"QLD",
    "sg:tags":[
        "venue",
        "tuition"
    ],
    "wof:name":"Sunshine Dance Centre",
    "wof:placetype":"venue"
},
  "geometry": {"coordinates":[152.95753479000001,-26.6289024353],"type":"Point"}
}