{
  "type": "Feature",
  "properties": {
    "iso:country":"AU",
    "sg:address":"268 Ellesmere Rd",
    "sg:city":"Gymea Bay",
    "sg:classifiers":[
        {
            "category":"Real Estate",
            "subcategory":"Architect",
            "type":"Services"
        }
    ],
    "sg:phone":"+61 2 9526 1504",
    "sg:postcode":"2227",
    "sg:province":"NSW",
    "wof:name":"Welsh P R",
    "wof:placetype":"venue"
},
  "geometry": {"coordinates":[151.08697509800001,-34.0528259277],"type":"Point"}
}