{
  "type": "Feature",
  "properties": {
    "addr:full":"56 Helen St South Golden Beach NSW 2483",
    "addr:housenumber":"56",
    "addr:postcode":"2483",
    "addr:street":"Helen St South",
    "iso:country":"AU",
    "sg:address":"56 Helen St",
    "sg:city":"South Golden Beach",
    "sg:classifiers":[
        {
            "category":"Government",
            "subcategory":"Court House",
            "type":"Public Place"
        }
    ],
    "sg:phone":"+61 2 6680 2805",
    "sg:postcode":"2483",
    "sg:province":"NSW",
    "sg:tags":[
        "personal",
        "marriage",
        "family",
        "counselling"
    ],
    "wof:name":"Susan Allen",
    "wof:placetype":"venue"
},
  "geometry": {"coordinates":[153.54560852,-28.4974784851],"type":"Point"}
}