{
  "type": "Feature",
  "properties": {
    "iso:country":"AU",
    "sg:address":"225 Commercial Rd",
    "sg:city":"South Yarra",
    "sg:classifiers":[
        {
            "category":"Fast Food",
            "type":"Food & Drink"
        }
    ],
    "sg:phone":"+61 3 9827 4608",
    "sg:postcode":"3141",
    "sg:province":"VIC",
    "sg:tags":[
        "away",
        "take"
    ],
    "wof:name":"Cyclo Express",
    "wof:placetype":"venue"
},
  "geometry": {"coordinates":[144.993743897,-37.8466720581],"type":"Point"}
}