{
  "type": "Feature",
  "properties": {
    "iso:country":"AU",
    "sg:address":"29 Eltham St",
    "sg:city":"Dulwich Hill",
    "sg:classifiers":[
        {
            "category":"Utilities",
            "subcategory":"Electric",
            "type":"Services"
        }
    ],
    "sg:phone":"+61 418 233 601",
    "sg:postcode":"2203",
    "sg:province":"NSW",
    "sg:tags":[
        "electrical",
        "contractor"
    ],
    "wof:name":"Ken Burns Electrical Services",
    "wof:placetype":"venue"
},
  "geometry": {"coordinates":[151.142487,-33.896919],"type":"Point"}
}