{
  "type": "Feature",
  "properties": {
    "iso:country":"AU",
    "sg:address":"Paratea Ave",
    "sg:city":"Frankston South",
    "sg:classifiers":[
        {
            "category":"Education",
            "subcategory":"Kindergarten",
            "type":"Public Place"
        }
    ],
    "sg:phone":"+61 3 9787 3842",
    "sg:postcode":"3199",
    "sg:province":"VIC",
    "sg:tags":[
        "pre-schools"
    ],
    "wof:name":"Paratea Pre School Inc",
    "wof:placetype":"venue"
},
  "geometry": {"coordinates":[145.12692260700001,-38.1887321472],"type":"Point"}
}