{
  "type": "Feature",
  "properties": {
    "addr:full":"306 Dowling St Wendouree VIC 3355",
    "addr:housenumber":"306",
    "addr:postcode":"3355",
    "addr:street":"Dowling St",
    "iso:country":"AU",
    "sg:address":"306 Dowling St",
    "sg:city":"Wendouree",
    "sg:classifiers":[
        {
            "category":"Retail",
            "subcategory":"Auto Repair",
            "type":"Services"
        }
    ],
    "sg:phone":"+61 3 5338 1788",
    "sg:postcode":"3355",
    "sg:province":"VIC",
    "sg:tags":[
        "clutch",
        "brake"
    ],
    "wof:name":"Wakeling Automotive Centre",
    "wof:placetype":"venue"
},
  "geometry": {"coordinates":[143.841385,-37.532967],"type":"Point"}
}