{
  "type": "Feature",
  "properties": {
    "iso:country":"AU",
    "sg:address":"75 Murray St",
    "sg:city":"Gawler",
    "sg:classifiers":[
        {
            "category":"Banks & Credit Unions",
            "subcategory":"Bank",
            "type":"Services"
        }
    ],
    "sg:phone":"+61 13 20 32",
    "sg:postcode":"5118",
    "sg:province":"SA",
    "wof:name":"Westpac",
    "wof:placetype":"venue"
},
  "geometry": {"coordinates":[138.74923699999999,-34.596687],"type":"Point"}
}