{
  "type": "Feature",
  "properties": {
    "iso:country":"AU",
    "sg:address":"Unit 3 / 11 Palmer Pl",
    "sg:city":"Murarrie",
    "sg:classifiers":[
        {
            "category":"Shopping",
            "subcategory":"Stationery & Office Supplies",
            "type":"Retail Goods"
        }
    ],
    "sg:phone":"+61 7 3390 6255",
    "sg:postcode":"4172",
    "sg:province":"QLD",
    "sg:tags":[
        "equipment",
        "display",
        "exhibition"
    ],
    "wof:name":"Digital Ink",
    "wof:placetype":"venue"
},
  "geometry": {"coordinates":[153.09967040999999,-27.4603252411],"type":"Point"}
}