{
  "type": "Feature",
  "properties": {
    "iso:country":"AU",
    "sg:address":"3 Unicorn St",
    "sg:city":"Sanctuary Point",
    "sg:classifiers":[
        {
            "category":"Professional",
            "subcategory":"Computer Services",
            "type":"Services"
        }
    ],
    "sg:phone":"+61 421 214 689",
    "sg:postcode":"2540",
    "sg:province":"NSW",
    "sg:tags":[
        "repairs",
        "upgrade",
        "equipment"
    ],
    "wof:name":"Karl's Computer Services",
    "wof:placetype":"venue"
},
  "geometry": {"coordinates":[150.626663208,-35.1069869995],"type":"Point"}
}