{
  "type": "Feature",
  "properties": {
    "addr:full":"12 Curtis Rd Mulgrave NSW 2756",
    "addr:housenumber":"12",
    "addr:postcode":"2756",
    "addr:street":"Curtis Rd",
    "iso:country":"AU",
    "sg:address":"12 Curtis Rd",
    "sg:city":"Mulgrave",
    "sg:classifiers":[
        {
            "category":"Manufacturing",
            "subcategory":"Rubber & Plastics",
            "type":"Manufacturing & Wholesale Goods"
        }
    ],
    "sg:phone":"+61 2 4577 9955",
    "sg:postcode":"2756",
    "sg:province":"NSW",
    "sg:tags":[
        "moulders"
    ],
    "wof:name":"Ambi Sales",
    "wof:placetype":"venue"
},
  "geometry": {"coordinates":[150.834472656,-33.6228942871],"type":"Point"}
}