{
  "type": "Feature",
  "properties": {
    "iso:country":"AU",
    "sg:address":"59 Morris Rd",
    "sg:city":"Hoppers Crossing",
    "sg:classifiers":[
        {
            "category":"Professional",
            "subcategory":"Computer Services",
            "type":"Services"
        }
    ],
    "sg:phone":"+61 1300 653 943",
    "sg:postcode":"3029",
    "sg:province":"VIC",
    "sg:tags":[
        "repairs",
        "upgrade",
        "equipment"
    ],
    "wof:name":"Generation 3 Computers",
    "wof:placetype":"venue"
},
  "geometry": {"coordinates":[144.70065299999999,-37.880554],"type":"Point"}
}