{
  "type": "Feature",
  "properties": {
    "addr:full":"20 Ranelagh Drv Mt Eliza VIC 3930",
    "addr:housenumber":"20",
    "addr:postcode":"3930",
    "addr:street":"Ranelagh Drv",
    "iso:country":"AU",
    "sg:address":"20 Ranelagh Drv",
    "sg:city":"Mt Eliza",
    "sg:classifiers":[
        {
            "category":"Professional",
            "subcategory":"Computer Services",
            "type":"Services"
        }
    ],
    "sg:phone":"+61 3 9787 0031",
    "sg:postcode":"3930",
    "sg:province":"VIC",
    "sg:tags":[
        "repairs",
        "upgrade",
        "equipment"
    ],
    "wof:name":"Info Integrity",
    "wof:placetype":"venue"
},
  "geometry": {"coordinates":[145.087982178,-38.1843795776],"type":"Point"}
}