{
  "type": "Feature",
  "properties": {
    "addr:full":"Lvl 1/ 488 Botany Rd Alexandria NSW 2015",
    "addr:housenumber":"/ 488",
    "addr:postcode":"2015",
    "addr:street":"Botany Rd",
    "iso:country":"AU",
    "sg:address":"Lvl 1/ 488 Botany Rd",
    "sg:city":"Alexandria",
    "sg:classifiers":[
        {
            "category":"Building & Trades",
            "subcategory":"Construction",
            "type":"Services"
        }
    ],
    "sg:phone":"+61 2 8332 6128",
    "sg:postcode":"2015",
    "sg:province":"NSW",
    "sg:tags":[
        "industrial",
        "commercial",
        "air conditioning"
    ],
    "wof:name":"Metropolitan Air",
    "wof:placetype":"venue"
},
  "geometry": {"coordinates":[151.20132446299999,-33.912815094],"type":"Point"}
}