{
  "type": "Feature",
  "properties": {
    "iso:country":"AU",
    "sg:address":"9 Rosslyn St",
    "sg:city":"Bellevue Hill",
    "sg:classifiers":[
        {
            "category":"Real Estate",
            "subcategory":"Architect",
            "type":"Services"
        }
    ],
    "sg:phone":"+61 2 9327 6585",
    "sg:postcode":"2023",
    "sg:province":"NSW",
    "wof:name":"Susan Fuller Architects",
    "wof:placetype":"venue"
},
  "geometry": {"coordinates":[151.255126953,-33.8839378357],"type":"Point"}
}