{
  "type": "Feature",
  "properties": {
    "addr:full":"117 High St Terang VIC 3264",
    "addr:housenumber":"117",
    "addr:postcode":"3264",
    "addr:street":"High St",
    "iso:country":"AU",
    "sg:address":"117 High St",
    "sg:city":"Terang",
    "sg:classifiers":[
        {
            "category":"Personal",
            "subcategory":"Beauty Salon",
            "type":"Services"
        }
    ],
    "sg:phone":"+61 3 5592 1664",
    "sg:postcode":"3264",
    "sg:province":"VIC",
    "sg:tags":[
        "hairdresser"
    ],
    "wof:name":"TJs Dyeing To Curl Hair & Beauty",
    "wof:placetype":"venue"
},
  "geometry": {"coordinates":[142.91648864699999,-38.2414398193],"type":"Point"}
}