{
  "type": "Feature",
  "properties": {
    "addr:full":"187 Nicholson St Brunswick East VIC 3057",
    "addr:housenumber":"187",
    "addr:postcode":"3057",
    "addr:street":"Nicholson St",
    "iso:country":"AU",
    "sg:address":"187 Nicholson St",
    "sg:city":"Brunswick East",
    "sg:classifiers":[
        {
            "category":"Professional",
            "subcategory":"Accounting & Tax Preparation",
            "type":"Services"
        }
    ],
    "sg:phone":"+61 3 9380 5399",
    "sg:postcode":"3057",
    "sg:province":"VIC",
    "sg:tags":[
        "accountant",
        "auditor"
    ],
    "wof:name":"El-Fahkri A",
    "wof:placetype":"venue"
},
  "geometry": {"coordinates":[144.97967529300001,-37.7693824768],"type":"Point"}
}