{
  "type": "Feature",
  "properties": {
    "addr:full":"203 Annangrove Rd Annangrove NSW 2156",
    "addr:housenumber":"203",
    "addr:postcode":"2156",
    "addr:street":"Annangrove Rd",
    "iso:country":"AU",
    "sg:address":"203 Annangrove Rd",
    "sg:city":"Annangrove",
    "sg:classifiers":[
        {
            "category":"Retail",
            "subcategory":"Car Wash",
            "type":"Services"
        }
    ],
    "sg:phone":"+61 418 240 215",
    "sg:postcode":"2156",
    "sg:province":"NSW",
    "sg:tags":[
        "truck",
        "cleaning"
    ],
    "wof:name":"Premium Detailing Services",
    "wof:placetype":"venue"
},
  "geometry": {"coordinates":[150.948654175,-33.6633720398],"type":"Point"}
}