{
  "type": "Feature",
  "properties": {
    "iso:country":"AU",
    "sg:address":"Unit 11 / 2 Jeffcoat St",
    "sg:city":"Paget",
    "sg:classifiers":[
        {
            "category":"Professional",
            "subcategory":"Testing Lab",
            "type":"Services"
        }
    ],
    "sg:phone":"+61 408 701 952",
    "sg:postcode":"4740",
    "sg:province":"QLD",
    "sg:tags":[
        "inspection"
    ],
    "wof:name":"INDT",
    "wof:placetype":"venue"
},
  "geometry": {"coordinates":[149.17231799999999,-21.171618],"type":"Point"}
}