{
  "type": "Feature",
  "properties": {
    "iso:country":"AU",
    "sg:address":"98 Miller St",
    "sg:city":"Chermside",
    "sg:classifiers":[
        {
            "category":"Shopping",
            "subcategory":"Bridal",
            "type":"Retail Goods"
        }
    ],
    "sg:phone":"+61 419 460 667",
    "sg:postcode":"4032",
    "sg:province":"QLD",
    "sg:tags":[
        "hire",
        "wear"
    ],
    "wof:name":"World Design",
    "wof:placetype":"venue"
},
  "geometry": {"coordinates":[153.03602599999999,-27.388313],"type":"Point"}
}