{
  "type": "Feature",
  "properties": {
    "iso:country":"AU",
    "sg:address":"Queen Victoria Building, Shop G26, 455",
    "sg:city":"George St, Sydney",
    "sg:classifiers":[
        {
            "category":"Shopping",
            "subcategory":"Clothing, Apparel, & Fashions",
            "type":"Retail Goods"
        }
    ],
    "sg:phone":"+61 2 9264 5131",
    "sg:postcode":"2000",
    "sg:province":"NSW",
    "sg:tags":[
        "lady",
        "wear"
    ],
    "wof:name":"Anthea Crawford (Australia) Pty Ltd",
    "wof:placetype":"venue"
},
  "geometry": {"coordinates":[151.206863403,-33.8719215393],"type":"Point"}
}