{
  "type": "Feature",
  "properties": {
    "addr:full":"40 Prior St Tarragindi QLD 4121",
    "addr:housenumber":"40",
    "addr:postcode":"4121",
    "addr:street":"Prior St",
    "iso:country":"AU",
    "sg:address":"40 Prior St",
    "sg:city":"Tarragindi",
    "sg:classifiers":[
        {
            "category":"Professional",
            "subcategory":"Accounting & Tax Preparation",
            "type":"Services"
        }
    ],
    "sg:phone":"+61 7 3848 2885",
    "sg:postcode":"4121",
    "sg:province":"QLD",
    "sg:tags":[
        "accountant",
        "auditor"
    ],
    "wof:name":"Crawford W G M",
    "wof:placetype":"venue"
},
  "geometry": {"coordinates":[153.042892456,-27.5313892365],"type":"Point"}
}