{
  "type": "Feature",
  "properties": {
    "iso:country":"AU",
    "sg:address":"6 Howard St",
    "sg:city":"Warners Bay",
    "sg:classifiers":[
        {
            "category":"Banks & Credit Unions",
            "subcategory":"Financial Services",
            "type":"Services"
        }
    ],
    "sg:phone":"+61 2 4947 2233",
    "sg:postcode":"2282",
    "sg:province":"NSW",
    "sg:tags":[
        "annuity",
        "rollover",
        "superannuation",
        "consultant"
    ],
    "wof:name":"Progressive Financial Planners Pty Ltd",
    "wof:placetype":"venue"
},
  "geometry": {"coordinates":[151.646209717,-32.9758071899],"type":"Point"}
}