{
  "type": "Feature",
  "properties": {
    "addr:full":"152 Wickham St Fortitude Valley QLD 4006",
    "addr:housenumber":"152",
    "addr:postcode":"4006",
    "addr:street":"Wickham St",
    "iso:country":"AU",
    "sg:address":"152 Wickham St",
    "sg:city":"Fortitude Valley",
    "sg:classifiers":[
        {
            "category":"Home & Garden",
            "subcategory":"Building Materials",
            "type":"Retail Goods"
        }
    ],
    "sg:phone":"+61 7 3220 0198",
    "sg:postcode":"4006",
    "sg:province":"QLD",
    "sg:tags":[
        "insulation"
    ],
    "wof:name":"Digi-Time",
    "wof:placetype":"venue"
},
  "geometry": {"coordinates":[153.032073975,-27.4588508606],"type":"Point"}
}