{
  "type": "Feature",
  "properties": {
    "iso:country":"AU",
    "sg:address":"Shop 5/ 7 Woodpecker Ave",
    "sg:city":"Willetton",
    "sg:classifiers":[
        {
            "category":"Shopping",
            "subcategory":"Crafts & Fabrics",
            "type":"Retail Goods"
        }
    ],
    "sg:phone":"+61 8 9259 0150",
    "sg:postcode":"6155",
    "sg:province":"WA",
    "sg:tags":[
        "supply"
    ],
    "wof:name":"Folk Art Factory Of WA (The)",
    "wof:placetype":"venue"
},
  "geometry": {"coordinates":[115.8815,-32.049019],"type":"Point"}
}