{
  "type": "Feature",
  "properties": {
    "addr:full":"21 Waiora Rd Caulfield North VIC 3161",
    "addr:housenumber":"21",
    "addr:postcode":"3161",
    "addr:street":"Waiora Rd",
    "iso:country":"AU",
    "sg:address":"21 Waiora Rd",
    "sg:city":"Caulfield North",
    "sg:classifiers":[
        {
            "category":"Real Estate",
            "subcategory":"Developer",
            "type":"Services"
        }
    ],
    "sg:phone":"+61 3 9509 3371",
    "sg:postcode":"3161",
    "sg:province":"VIC",
    "sg:tags":[
        "development"
    ],
    "wof:name":"Waiora Nominees Pty Ltd",
    "wof:placetype":"venue"
},
  "geometry": {"coordinates":[145.01551818900001,-37.8614578247],"type":"Point"}
}