{
  "type": "Feature",
  "properties": {
    "addr:full":"5 Earls Pl Balga WA 6061",
    "addr:housenumber":"5",
    "addr:postcode":"6061",
    "addr:street":"Earls Pl",
    "iso:country":"AU",
    "sg:address":"5 Earls Pl",
    "sg:city":"Balga",
    "sg:classifiers":[
        {
            "category":"Education",
            "subcategory":"Vocational School",
            "type":"Public Place"
        }
    ],
    "sg:phone":"+61 8 9343 2650",
    "sg:postcode":"6061",
    "sg:province":"WA",
    "sg:tags":[
        "cake",
        "decorating",
        "decorator"
    ],
    "wof:name":"A Cake A Day",
    "wof:placetype":"venue"
},
  "geometry": {"coordinates":[115.854499817,-31.8493728638],"type":"Point"}
}