{
  "type": "Feature",
  "properties": {
    "addr:full":"282 Burwood Rd Burwood NSW 2134",
    "addr:housenumber":"282",
    "addr:postcode":"2134",
    "addr:street":"Burwood Rd",
    "iso:country":"AU",
    "sg:address":"282 Burwood Rd",
    "sg:city":"Burwood",
    "sg:classifiers":[
        {
            "category":"Health Services",
            "subcategory":"Doctor",
            "type":"Services"
        }
    ],
    "sg:phone":"+61 2 9745 3399",
    "sg:postcode":"2134",
    "sg:province":"NSW",
    "sg:tags":[
        "medical",
        "practitioner"
    ],
    "wof:name":"Burwood Endoscopy Centre",
    "wof:placetype":"venue"
},
  "geometry": {"coordinates":[151.10299682600001,-33.8815917969],"type":"Point"}
}