{
  "type": "Feature",
  "properties": {
    "addr:full":"33 Symons St Healesville VIC 3777",
    "addr:housenumber":"33",
    "addr:postcode":"3777",
    "addr:street":"Symons St",
    "iso:country":"AU",
    "sg:address":"33 Symons St",
    "sg:city":"Healesville",
    "sg:classifiers":[
        {
            "category":"Social Services",
            "subcategory":"Child Care",
            "type":"Services"
        }
    ],
    "sg:phone":"+61 3 5962 4163",
    "sg:postcode":"3777",
    "sg:province":"VIC",
    "sg:tags":[
        "support",
        "health"
    ],
    "wof:name":"Maternal & Child Health Centres",
    "wof:placetype":"venue"
},
  "geometry": {"coordinates":[145.518066,-37.654739],"type":"Point"}
}