{
  "type": "Feature",
  "properties": {
    "iso:country":"AU",
    "sg:address":"PO Box 510",
    "sg:city":"Bribie Island",
    "sg:classifiers":[
        {
            "category":"Professional",
            "subcategory":"Art Services",
            "type":"Services"
        }
    ],
    "sg:phone":"+61 7 3408 7483",
    "sg:postcode":"4507",
    "sg:province":"QLD",
    "sg:tags":[
        "decorator",
        "painter"
    ],
    "wof:name":"Bribie Painting Service",
    "wof:placetype":"venue"
},
  "geometry": {"coordinates":[153.14137268100001,-26.9570903778],"type":"Point"}
}