{
  "type": "Feature",
  "properties": {
    "iso:country":"AU",
    "sg:address":"1374 Gympie Rd",
    "sg:city":"Aspley",
    "sg:classifiers":[
        {
            "category":"Communications",
            "subcategory":"Film & Video Production",
            "type":"Services"
        }
    ],
    "sg:phone":"+61 7 3263 7555",
    "sg:postcode":"4034",
    "sg:province":"QLD",
    "sg:tags":[
        "dvd",
        "library"
    ],
    "wof:name":"Video 2000",
    "wof:placetype":"venue"
},
  "geometry": {"coordinates":[153.016907,-27.36215],"type":"Point"}
}