{
  "type": "Feature",
  "properties": {
    "addr:full":"10/ 41 Tintern Ave Toorak VIC 3142",
    "addr:housenumber":"10 / 41",
    "addr:postcode":"3142",
    "addr:street":"Tintern Ave",
    "iso:country":"AU",
    "sg:address":"10/ 41 Tintern Ave",
    "sg:city":"Toorak",
    "sg:classifiers":[
        {
            "category":"Manufacturing",
            "subcategory":"Food",
            "type":"Manufacturing & Wholesale Goods"
        }
    ],
    "sg:phone":"+61 417 780 701",
    "sg:postcode":"3142",
    "sg:province":"VIC",
    "sg:tags":[
        "function",
        "catering"
    ],
    "wof:name":"AIX Provencial Catering",
    "wof:placetype":"venue"
},
  "geometry": {"coordinates":[145.005737305,-37.8409500122],"type":"Point"}
}