{
  "type": "Feature",
  "properties": {
    "iso:country":"AU",
    "sg:address":"88 Bolinda Rd",
    "sg:city":"Campbellfield",
    "sg:classifiers":[
        {
            "category":"Retail",
            "subcategory":"Repair Shop",
            "type":"Services"
        }
    ],
    "sg:phone":"+61 3 9359 6022",
    "sg:postcode":"3061",
    "sg:province":"VIC",
    "sg:tags":[
        "upholsterer"
    ],
    "wof:name":"M G Upholstery",
    "wof:placetype":"venue"
},
  "geometry": {"coordinates":[144.962814331,-37.6838417053],"type":"Point"}
}