{
  "type": "Feature",
  "properties": {
    "addr:full":"2 Ashford Ave Milperra NSW 2214",
    "addr:housenumber":"2",
    "addr:postcode":"2214",
    "addr:street":"Ashford Ave",
    "iso:country":"AU",
    "sg:address":"2 Ashford Ave",
    "sg:city":"Milperra",
    "sg:classifiers":[
        {
            "category":"Manufacturing",
            "subcategory":"Aerospace",
            "type":"Manufacturing & Wholesale Goods"
        }
    ],
    "sg:phone":"+61 2 8723 6400",
    "sg:postcode":"2214",
    "sg:province":"NSW",
    "sg:tags":[
        "equipment",
        "aircraft",
        "maintenance"
    ],
    "wof:name":"Byron GSE",
    "wof:placetype":"venue"
},
  "geometry": {"coordinates":[150.99058500000001,-33.930122],"type":"Point"}
}