{
  "type": "Feature",
  "properties": {
    "iso:country":"AU",
    "sg:address":"Tomahawk Creek Rd",
    "sg:city":"Simpson",
    "sg:classifiers":[
        {
            "category":"Wholesale",
            "subcategory":"Fruits & Vegetables",
            "type":"Manufacturing & Wholesale Goods"
        }
    ],
    "sg:phone":"+61 3 5594 3403",
    "sg:postcode":"3266",
    "sg:province":"VIC",
    "sg:tags":[
        "produce",
        "grain"
    ],
    "wof:name":"Heytesbury Stockfeeds Pty Ltd",
    "wof:placetype":"venue"
},
  "geometry": {"coordinates":[143.20854187,-38.4941368103],"type":"Point"}
}