{
  "type": "Feature",
  "properties": {
    "iso:country":"AU",
    "sg:address":"11 King William St",
    "sg:city":"Kent Town",
    "sg:classifiers":[
        {
            "category":"Real Estate",
            "subcategory":"Surveying",
            "type":"Services"
        }
    ],
    "sg:phone":"+61 8 8130 1666",
    "sg:postcode":"5067",
    "sg:province":"SA",
    "sg:tags":[
        "map",
        "mapping"
    ],
    "wof:name":"Alexander Symonds",
    "wof:placetype":"venue"
},
  "geometry": {"coordinates":[138.61549377399999,-34.9205093384],"type":"Point"}
}