{
  "type": "Feature",
  "properties": {
    "addr:full":"Riverton Forum Shopping Centre High Rd Riverton WA 6148",
    "addr:postcode":"6148",
    "addr:street":"High Rd",
    "iso:country":"AU",
    "sg:address":"Riverton Forum Shopping Centre High Rd",
    "sg:city":"Riverton",
    "sg:classifiers":[
        {
            "category":"Shopping",
            "subcategory":"Shoes",
            "type":"Retail Goods"
        }
    ],
    "sg:phone":"+61 8 9457 9225",
    "sg:postcode":"6148",
    "sg:province":"WA",
    "sg:tags":[
        "footwear"
    ],
    "wof:name":"Betts",
    "wof:placetype":"venue"
},
  "geometry": {"coordinates":[115.894211,-32.038651],"type":"Point"}
}