{
  "type": "Feature",
  "properties": {
    "addr:full":"412 Rockingham Rd Spearwood WA 6163",
    "addr:housenumber":"412",
    "addr:postcode":"6163",
    "addr:street":"Rockingham Rd",
    "iso:country":"AU",
    "sg:address":"412 Rockingham Rd",
    "sg:city":"Spearwood",
    "sg:classifiers":[
        {
            "category":"Education",
            "subcategory":"Music School",
            "type":"Public Place"
        }
    ],
    "sg:phone":"+61 422 480 040",
    "sg:postcode":"6163",
    "sg:province":"WA",
    "sg:tags":[
        "teacher"
    ],
    "wof:name":"Mr Faz School Of Music",
    "wof:placetype":"venue"
},
  "geometry": {"coordinates":[115.782921,-32.113297],"type":"Point"}
}