{
  "type": "Feature",
  "properties": {
    "addr:full":"55 Waterfield St Coburg VIC 3058",
    "addr:housenumber":"55",
    "addr:postcode":"3058",
    "addr:street":"Waterfield St",
    "iso:country":"AU",
    "sg:address":"55 Waterfield St",
    "sg:city":"Coburg",
    "sg:classifiers":[
        {
            "category":"Fast Food",
            "type":"Food & Drink"
        }
    ],
    "sg:phone":"+61 3 9354 4066",
    "sg:postcode":"3058",
    "sg:province":"VIC",
    "sg:tags":[
        "away",
        "take"
    ],
    "wof:name":"Habibs Pizza & Takeaway",
    "wof:placetype":"venue"
},
  "geometry": {"coordinates":[144.96499633799999,-37.7421188354],"type":"Point"}
}