{
  "type": "Feature",
  "properties": {
    "addr:full":"17 Montrose Ave Bethania QLD 4205",
    "addr:housenumber":"17",
    "addr:postcode":"4205",
    "addr:street":"Montrose Ave",
    "iso:country":"AU",
    "sg:address":"17 Montrose Ave",
    "sg:city":"Bethania",
    "sg:classifiers":[
        {
            "category":"Building & Trades",
            "subcategory":"Construction",
            "type":"Services"
        }
    ],
    "sg:phone":"+61 7 3229 7870",
    "sg:postcode":"4205",
    "sg:province":"QLD",
    "sg:tags":[
        "contractor"
    ],
    "wof:name":"Arthur J Byrnes",
    "wof:placetype":"venue"
},
  "geometry": {"coordinates":[153.154495239,-27.6932601929],"type":"Point"}
}