{
  "type": "Feature",
  "properties": {
    "addr:full":"64 Louisa Rd Birchgrove NSW 2041",
    "addr:housenumber":"64",
    "addr:postcode":"2041",
    "addr:street":"Louisa Rd",
    "iso:country":"AU",
    "sg:address":"64 Louisa Rd",
    "sg:city":"Birchgrove",
    "sg:classifiers":[
        {
            "category":"Professional",
            "subcategory":"Art Services",
            "type":"Services"
        }
    ],
    "sg:phone":"+61 2 9555 8963",
    "sg:postcode":"2041",
    "sg:province":"NSW",
    "wof:name":"Pamela Adams",
    "wof:placetype":"venue"
},
  "geometry": {"coordinates":[151.18081699999999,-33.848301],"type":"Point"}
}