{
  "type": "Feature",
  "properties": {
    "iso:country":"AU",
    "sg:address":"U2/ 142-144 Sydney St",
    "sg:city":"Muswellbrook",
    "sg:classifiers":[
        {
            "category":"Retail",
            "subcategory":"Auto Repair",
            "type":"Services"
        }
    ],
    "sg:phone":"+61 2 6543 4234",
    "sg:postcode":"2333",
    "sg:province":"NSW",
    "sg:tags":[
        "bus",
        "truck"
    ],
    "wof:name":"F M Mechanical",
    "wof:placetype":"venue"
},
  "geometry": {"coordinates":[150.886260986,-32.2682342529],"type":"Point"}
}