{
  "type": "Feature",
  "properties": {
    "addr:full":"Suite 306, 118 Christie St St Leonards NSW 2065",
    "addr:housenumber":"118",
    "addr:postcode":"2065",
    "addr:street":"Christie St",
    "iso:country":"AU",
    "sg:address":"Suite 306, 118 Christie St St",
    "sg:city":"Leonards",
    "sg:classifiers":[
        {
            "category":"Banks & Credit Unions",
            "subcategory":"Bureau De Change",
            "type":"Services"
        }
    ],
    "sg:phone":"+61 2 9113 5400",
    "sg:postcode":"2065",
    "sg:province":"NSW",
    "sg:tags":[
        "preparation",
        "processing",
        "data"
    ],
    "wof:name":"Database Dept. The",
    "wof:placetype":"venue"
},
  "geometry": {"coordinates":[151.19552612300001,-33.8232307434],"type":"Point"}
}