{
  "type": "Feature",
  "properties": {
    "iso:country":"AU",
    "sg:address":"PO Box 3228",
    "sg:city":"Burleigh Heads",
    "sg:classifiers":[
        {
            "category":"Building & Trades",
            "subcategory":"Equipment Rental",
            "type":"Services"
        }
    ],
    "sg:phone":"+61 7 5535 7666",
    "sg:postcode":"4220",
    "sg:province":"QLD",
    "sg:tags":[
        "platform",
        "hire",
        "work",
        "elevating"
    ],
    "wof:name":"Alloy Platforms",
    "wof:placetype":"venue"
},
  "geometry": {"coordinates":[153.449752808,-28.0879096985],"type":"Point"}
}