{
  "type": "Feature",
  "properties": {
    "addr:full":"35 Lyons St Rye VIC 3941",
    "addr:housenumber":"35",
    "addr:postcode":"3941",
    "addr:street":"Lyons St",
    "iso:country":"AU",
    "sg:address":"35 Lyons St",
    "sg:city":"Rye",
    "sg:classifiers":[
        {
            "category":"Organizations",
            "subcategory":"Community Association",
            "type":"Services"
        }
    ],
    "sg:phone":"+61 3 5985 1399",
    "sg:postcode":"3941",
    "sg:province":"VIC",
    "sg:tags":[
        "organisation",
        "family",
        "welfare"
    ],
    "wof:name":"The Anglican Parish Centre",
    "wof:placetype":"venue"
},
  "geometry": {"coordinates":[144.82417297399999,-38.3741569519],"type":"Point"}
}