{
  "type": "Feature",
  "properties": {
    "addr:full":"28 Grovedale Rd Surrey Hills VIC 3127",
    "addr:housenumber":"28",
    "addr:postcode":"3127",
    "addr:street":"Grovedale Rd",
    "iso:country":"AU",
    "sg:address":"28 Grovedale Rd",
    "sg:city":"Surrey Hills",
    "sg:classifiers":[
        {
            "category":"Recreation",
            "type":"Entertainment"
        }
    ],
    "sg:phone":"+61 416 146 713",
    "sg:postcode":"3127",
    "sg:province":"VIC",
    "sg:tags":[
        "supply",
        "outdoor",
        "adventure",
        "activity"
    ],
    "wof:name":"Jeremiah Clothing",
    "wof:placetype":"venue"
},
  "geometry": {"coordinates":[145.09425354000001,-37.8168869019],"type":"Point"}
}