{
  "type": "Feature",
  "properties": {
    "iso:country":"AU",
    "sg:address":"13 Druid Ave",
    "sg:city":"Stirling",
    "sg:classifiers":[
        {
            "category":"Personal",
            "subcategory":"Massage",
            "type":"Services"
        }
    ],
    "sg:phone":"+61 8 8370 8557",
    "sg:postcode":"5152",
    "sg:province":"SA",
    "sg:tags":[
        "therapy"
    ],
    "wof:name":"Meaney Sue & Bob-Vital Harmony",
    "wof:placetype":"venue"
},
  "geometry": {"coordinates":[138.71554565400001,-35.0063095093],"type":"Point"}
}