{
  "type": "Feature",
  "properties": {
    "addr:full":"Unit 5- 51 Mandoon Rd Girraween NSW 2145",
    "addr:housenumber":"51",
    "addr:postcode":"2145",
    "addr:street":"Mandoon Rd",
    "iso:country":"AU",
    "sg:address":"Unit 5- 51 Mandoon Rd",
    "sg:city":"Girraween",
    "sg:classifiers":[
        {
            "category":"Wholesale",
            "subcategory":"Furniture",
            "type":"Manufacturing & Wholesale Goods"
        }
    ],
    "sg:phone":"+61 2 9688 2121",
    "sg:postcode":"2145",
    "sg:province":"NSW",
    "sg:tags":[
        "wholesaler",
        "mfrs"
    ],
    "wof:name":"Willoughbridge Imports NSW",
    "wof:placetype":"venue"
},
  "geometry": {"coordinates":[150.94244384800001,-33.8041915894],"type":"Point"}
}