{
  "type": "Feature",
  "properties": {
    "addr:full":"63 Williams Rd Nedlands WA 6009",
    "addr:housenumber":"63",
    "addr:postcode":"6009",
    "addr:street":"Williams Rd",
    "iso:country":"AU",
    "sg:address":"63 Williams Rd",
    "sg:city":"Nedlands",
    "sg:classifiers":[
        {
            "category":"Real Estate",
            "subcategory":"Architect",
            "type":"Services"
        }
    ],
    "sg:phone":"+61 8 9389 8319",
    "sg:postcode":"6009",
    "sg:province":"WA",
    "sg:tags":[
        "raw",
        "material",
        "plastic"
    ],
    "wof:name":"Korea Pacific Export (Australia) Company Pty Ltd",
    "wof:placetype":"venue"
},
  "geometry": {"coordinates":[115.809113,-31.975933],"type":"Point"}
}