{
  "type": "Feature",
  "properties": {
    "iso:country":"AU",
    "sg:address":"PO Box 404",
    "sg:city":"Inala",
    "sg:classifiers":[
        {
            "category":"Real Estate",
            "subcategory":"Real Estate Agent",
            "type":"Services"
        }
    ],
    "sg:phone":"+61 417 705 335",
    "sg:postcode":"4077",
    "sg:province":"QLD",
    "wof:name":"Impact Property Enterprises",
    "wof:placetype":"venue"
},
  "geometry": {"coordinates":[152.971603394,-27.5873908997],"type":"Point"}
}