{
  "type": "Feature",
  "properties": {
    "iso:country":"AU",
    "sg:address":"159a Darby St",
    "sg:city":"Cooks Hill",
    "sg:classifiers":[
        {
            "category":"Fast Food",
            "type":"Food & Drink"
        }
    ],
    "sg:phone":"+61 2 4929 1022",
    "sg:postcode":"2300",
    "sg:province":"NSW",
    "sg:tags":[
        "away",
        "take"
    ],
    "wof:name":"Le Dynasty Vietnamese Restaurant",
    "wof:placetype":"venue"
},
  "geometry": {"coordinates":[151.77119400000001,-32.932198],"type":"Point"}
}