{
  "type": "Feature",
  "properties": {
    "addr:full":"Ste15-16/ 513 High St Penrith NSW 2750",
    "addr:housenumber":"513",
    "addr:postcode":"2750",
    "addr:street":"High St",
    "iso:country":"AU",
    "sg:address":"Ste15-16/ 513 High St",
    "sg:city":"Penrith",
    "sg:classifiers":[
        {
            "category":"Professional",
            "subcategory":"Accounting & Tax Preparation",
            "type":"Services"
        }
    ],
    "sg:phone":"+61 2 4721 8366",
    "sg:postcode":"2750",
    "sg:province":"NSW",
    "sg:tags":[
        "consultant",
        "taxation"
    ],
    "wof:name":"Tax Today Penrith",
    "wof:placetype":"venue"
},
  "geometry": {"coordinates":[150.91554260300001,-33.8950157166],"type":"Point"}
}