{
  "type": "Feature",
  "properties": {
    "addr:full":"40 Brewster St Essendon VIC 3040",
    "addr:housenumber":"40",
    "addr:postcode":"3040",
    "addr:street":"Brewster St",
    "iso:country":"AU",
    "sg:address":"40 Brewster St",
    "sg:city":"Essendon",
    "sg:classifiers":[
        {
            "category":"Retail",
            "subcategory":"Car Wash",
            "type":"Services"
        }
    ],
    "sg:phone":"+61 419 305 463",
    "sg:postcode":"3040",
    "sg:province":"VIC",
    "sg:tags":[
        "truck",
        "cleaning"
    ],
    "wof:name":"Auto Ultimate Valet",
    "wof:placetype":"venue"
},
  "geometry": {"coordinates":[144.91986084000001,-37.7506828308],"type":"Point"}
}