{
  "type": "Feature",
  "properties": {
    "addr:full":"Shop 1, Centrepoint 159 Shoreham Rd Red Hill South VIC 3937",
    "addr:housenumber":"shop 1;159",
    "addr:postcode":"3937",
    "addr:street":"Centrepoint;Shoreham Rd",
    "iso:country":"AU",
    "sg:address":"Shop 1, Centrepoint 159 Shoreham Rd",
    "sg:city":"Red Hill South",
    "sg:classifiers":[
        {
            "category":"Health Services",
            "subcategory":"Health Practitioner",
            "type":"Services"
        }
    ],
    "sg:phone":"+61 409 330 447",
    "sg:postcode":"3937",
    "sg:province":"VIC",
    "sg:tags":[
        "naturopath"
    ],
    "wof:name":"Christine Brumby N.D.",
    "wof:placetype":"venue"
},
  "geometry": {"coordinates":[145.02586364699999,-38.3800621033],"type":"Point"}
}