{
  "type": "Feature",
  "properties": {
    "addr:full":"48 Belmont St Merrylands NSW 2160",
    "addr:housenumber":"48",
    "addr:postcode":"2160",
    "addr:street":"Belmont St",
    "iso:country":"AU",
    "sg:address":"48 Belmont St",
    "sg:city":"Merrylands",
    "sg:classifiers":[
        {
            "category":"Professional",
            "subcategory":"Business Services",
            "type":"Services"
        }
    ],
    "sg:phone":"+61 417 213 694",
    "sg:postcode":"2160",
    "sg:province":"NSW",
    "sg:tags":[
        "drafting"
    ],
    "wof:name":"D.C. Drafting",
    "wof:placetype":"venue"
},
  "geometry": {"coordinates":[150.98518371599999,-33.8447265625],"type":"Point"}
}