{
  "type": "Feature",
  "properties": {
    "addr:full":"Bangowannah Rd Jindera NSW 2642",
    "addr:postcode":"2642",
    "addr:street":"Bangowannah Rd",
    "iso:country":"AU",
    "sg:address":"Bangowannah Rd",
    "sg:city":"Jindera",
    "sg:classifiers":[
        {
            "category":"Train Station",
            "subcategory":"Rail",
            "type":"Transportation"
        }
    ],
    "sg:phone":"+61 2 6026 3835",
    "sg:postcode":"2642",
    "sg:province":"NSW",
    "sg:tags":[
        "goat",
        "farmer"
    ],
    "wof:name":"Petlyn Park Boer Goats",
    "wof:placetype":"venue"
},
  "geometry": {"coordinates":[146.88897705100001,-35.9545898438],"type":"Point"}
}