{
  "type": "Feature",
  "properties": {
    "addr:full":"7 Deloraine Rd Edwardstown SA 5039",
    "addr:housenumber":"7",
    "addr:postcode":"5039",
    "addr:street":"Deloraine Rd",
    "iso:country":"AU",
    "sg:address":"7 Deloraine Rd",
    "sg:city":"Edwardstown",
    "sg:classifiers":[
        {
            "category":"Autos & Motor Vehicles",
            "subcategory":"Automobile Sales",
            "type":"Retail Goods"
        }
    ],
    "sg:phone":"+61 8 8277 0488",
    "sg:postcode":"5039",
    "sg:province":"SA",
    "sg:tags":[
        "equipment",
        "trailer"
    ],
    "wof:name":"Maco International Sales",
    "wof:placetype":"venue"
},
  "geometry": {"coordinates":[138.57420349099999,-34.9875144958],"type":"Point"}
}