{
  "type": "Feature",
  "properties": {
    "addr:full":"10 Bevan Rd Galston NSW 2159",
    "addr:housenumber":"10",
    "addr:postcode":"2159",
    "addr:street":"Bevan Rd",
    "iso:country":"AU",
    "sg:address":"10 Bevan Rd",
    "sg:city":"Galston",
    "sg:classifiers":[
        {
            "category":"Retail",
            "subcategory":"Repair Shop",
            "type":"Services"
        }
    ],
    "sg:phone":"+61 418 999 964",
    "sg:postcode":"2159",
    "sg:province":"NSW",
    "sg:tags":[
        "upholsterer"
    ],
    "wof:name":"Cascade Upholstery Services",
    "wof:placetype":"venue"
},
  "geometry": {"coordinates":[151.06028747600001,-33.6491165161],"type":"Point"}
}