{
  "type": "Feature",
  "properties": {
    "addr:full":"\"Riverside\" Colac Rd Cressy VIC 3322",
    "addr:postcode":"3322",
    "addr:street":"Colac Rd",
    "iso:country":"AU",
    "sg:address":"\"Riverside\" Colac Rd",
    "sg:city":"Cressy",
    "sg:classifiers":[
        {
            "category":"Building & Trades",
            "subcategory":"Landscaping Services",
            "type":"Services"
        }
    ],
    "sg:phone":"+61 3 5238 8321",
    "sg:postcode":"3322",
    "sg:province":"VIC",
    "sg:tags":[
        "grazier"
    ],
    "wof:name":"Williams H",
    "wof:placetype":"venue"
},
  "geometry": {"coordinates":[143.64030500000001,-38.02504],"type":"Point"}
}