{
  "type": "Feature",
  "properties": {
    "addr:full":"10 Rawlings Pl Fadden ACT 2904",
    "addr:housenumber":"10",
    "addr:postcode":"2904",
    "addr:street":"Rawlings Pl",
    "iso:country":"AU",
    "sg:address":"10 Rawlings Pl",
    "sg:city":"Fadden",
    "sg:classifiers":[
        {
            "category":"Organizations",
            "subcategory":"Professional Association",
            "type":"Services"
        }
    ],
    "sg:phone":"+61 413 642 004",
    "sg:postcode":"2904",
    "sg:province":"ACT",
    "sg:tags":[
        "web",
        "internet"
    ],
    "wof:name":"AEW Studios",
    "wof:placetype":"venue"
},
  "geometry": {"coordinates":[149.12257385300001,-35.4076423645],"type":"Point"}
}