{
  "type": "Feature",
  "properties": {
    "addr:full":"259 Bulleen Rd Bulleen VIC 3105",
    "addr:housenumber":"259",
    "addr:postcode":"3105",
    "addr:street":"Bulleen Rd",
    "iso:country":"AU",
    "sg:address":"259 Bulleen Rd",
    "sg:city":"Bulleen",
    "sg:classifiers":[
        {
            "category":"Professional",
            "type":"Services"
        }
    ],
    "sg:phone":"+61 3 9850 2381",
    "sg:postcode":"3105",
    "sg:province":"VIC",
    "sg:tags":[
        "shop",
        "fitting"
    ],
    "wof:name":"Dario Shop Fitters & Joinery",
    "wof:placetype":"venue"
},
  "geometry": {"coordinates":[145.083496094,-37.7610778809],"type":"Point"}
}