{
  "type": "Feature",
  "properties": {
    "addr:full":"82 Boundary Rd Urangan QLD 4655",
    "addr:housenumber":"82",
    "addr:postcode":"4655",
    "addr:street":"Boundary Rd",
    "iso:country":"AU",
    "sg:address":"82 Boundary Rd",
    "sg:city":"Urangan",
    "sg:classifiers":[
        {
            "category":"Manufacturing",
            "subcategory":"Food",
            "type":"Manufacturing & Wholesale Goods"
        }
    ],
    "sg:phone":"+61 7 4125 3058",
    "sg:postcode":"4655",
    "sg:province":"QLD",
    "sg:tags":[
        "function",
        "catering"
    ],
    "wof:name":"Pep&#039;es Kaf",
    "wof:placetype":"venue"
},
  "geometry": {"coordinates":[152.87822,-25.303402],"type":"Point"}
}