{
  "type": "Feature",
  "properties": {
    "addr:full":"2 Lawrence St Wodonga VIC 3690",
    "addr:housenumber":"2",
    "addr:postcode":"3690",
    "addr:street":"Lawrence St",
    "iso:country":"AU",
    "sg:address":"2 Lawrence St",
    "sg:city":"Wodonga",
    "sg:classifiers":[
        {
            "category":"Building & Trades",
            "subcategory":"Construction",
            "type":"Services"
        }
    ],
    "sg:phone":"+61 2 6056 6440",
    "sg:postcode":"3690",
    "sg:province":"VIC",
    "sg:tags":[
        "installation",
        "air conditioning"
    ],
    "wof:name":"Aafco Hygiene Pty. Ltd.",
    "wof:placetype":"venue"
},
  "geometry": {"coordinates":[146.904098511,-36.1264533997],"type":"Point"}
}