{
  "type": "Feature",
  "properties": {
    "addr:full":"700 High St Kew East VIC 3102",
    "addr:housenumber":"700",
    "addr:postcode":"3102",
    "addr:street":"High St",
    "iso:country":"AU",
    "sg:address":"700 High St",
    "sg:city":"Kew East",
    "sg:classifiers":[
        {
            "category":"Shopping",
            "subcategory":"Stationery & Office Supplies",
            "type":"Retail Goods"
        }
    ],
    "sg:phone":"+61 3 9859 8744",
    "sg:postcode":"3102",
    "sg:province":"VIC",
    "sg:tags":[
        "packaging",
        "material"
    ],
    "wof:name":"Treofan Australia P/L",
    "wof:placetype":"venue"
},
  "geometry": {"coordinates":[145.055343628,-37.797252655],"type":"Point"}
}