{
  "type": "Feature",
  "properties": {
    "addr:full":"68 Moncur St Woollahra NSW 2025",
    "addr:housenumber":"68",
    "addr:postcode":"2025",
    "addr:street":"Moncur St",
    "iso:country":"AU",
    "sg:address":"68 Moncur St",
    "sg:city":"Woollahra",
    "sg:classifiers":[
        {
            "category":"Deli",
            "type":"Food & Drink"
        }
    ],
    "sg:phone":"+61 2 9362 1222",
    "sg:postcode":"2025",
    "sg:province":"NSW",
    "sg:tags":[
        "delicatessen"
    ],
    "wof:name":"Jones The Grocer",
    "wof:placetype":"venue"
},
  "geometry": {"coordinates":[151.23687744099999,-33.8877639771],"type":"Point"}
}