{
  "type": "Feature",
  "properties": {
    "iso:country":"AU",
    "sg:address":"Finniss Point Rd",
    "sg:city":"Riverton",
    "sg:classifiers":[
        {
            "category":"Professional",
            "subcategory":"Art Services",
            "type":"Services"
        }
    ],
    "sg:phone":"+61 8 8847 2497",
    "sg:postcode":"5412",
    "sg:province":"SA",
    "sg:tags":[
        "decorator",
        "painter"
    ],
    "wof:name":"Callery G J",
    "wof:placetype":"venue"
},
  "geometry": {"coordinates":[138.747680664,-34.1579017639],"type":"Point"}
}