{
  "type": "Feature",
  "properties": {
    "addr:full":"24a Atherton Rd Oakleigh VIC 3166",
    "addr:housenumber":"24a",
    "addr:postcode":"3166",
    "addr:street":"Atherton Rd",
    "iso:country":"AU",
    "sg:address":"24a Atherton Rd",
    "sg:city":"Oakleigh",
    "sg:classifiers":[
        {
            "category":"Shopping",
            "subcategory":"Music",
            "type":"Retail Goods"
        }
    ],
    "sg:phone":"+61 3 9568 2808",
    "sg:postcode":"3166",
    "sg:province":"VIC",
    "sg:tags":[
        "store"
    ],
    "wof:name":"Verginis Music Centre",
    "wof:placetype":"venue"
},
  "geometry": {"coordinates":[145.08990478499999,-37.8988265991],"type":"Point"}
}