{
  "type": "Feature",
  "properties": {
    "addr:full":"Canoe Point Rd Tannum Sands QLD 4680",
    "addr:postcode":"4680",
    "addr:street":"Canoe;Rd",
    "iso:country":"AU",
    "sg:address":"Canoe Point Rd",
    "sg:city":"Tannum Sands",
    "sg:classifiers":[
        {
            "category":"Organizations",
            "subcategory":"Community Association",
            "type":"Services"
        }
    ],
    "sg:phone":"+61 7 4973 9994",
    "sg:postcode":"4680",
    "sg:province":"QLD",
    "sg:tags":[
        "organisation",
        "family",
        "welfare"
    ],
    "wof:name":"Boyne-Tannum Meals On Wheels",
    "wof:placetype":"venue"
},
  "geometry": {"coordinates":[151.36729431099999,-23.9404411316],"type":"Point"}
}