{
  "type": "Feature",
  "properties": {
    "addr:full":"328 River St Ballina NSW 2478",
    "addr:housenumber":"328",
    "addr:postcode":"2478",
    "addr:street":"River St",
    "iso:country":"AU",
    "sg:address":"328 River St",
    "sg:city":"Ballina",
    "sg:classifiers":[
        {
            "category":"Professional",
            "subcategory":"Computer Services",
            "type":"Services"
        }
    ],
    "sg:phone":"+61 2 6681 5889",
    "sg:postcode":"2478",
    "sg:province":"NSW",
    "sg:tags":[
        "consultant",
        "system"
    ],
    "wof:name":"Horticom Services Pty Ltd",
    "wof:placetype":"venue"
},
  "geometry": {"coordinates":[153.54980468799999,-28.866235733],"type":"Point"}
}