{
  "type": "Feature",
  "properties": {
    "addr:full":"Howard Rd Launceston TAS 7250",
    "addr:postcode":"7250",
    "addr:street":"Howard Rd",
    "iso:country":"AU",
    "sg:address":"Howard Rd",
    "sg:city":"Launceston",
    "sg:classifiers":[
        {
            "category":"Professional",
            "subcategory":"Accounting & Tax Preparation",
            "type":"Services"
        }
    ],
    "sg:phone":"+61 3 6272 5677",
    "sg:postcode":"7250",
    "sg:province":"TAS",
    "sg:tags":[
        "insulation",
        "wholesaler",
        "material",
        "mfrs"
    ],
    "wof:name":"Bradford Insulation",
    "wof:placetype":"venue"
},
  "geometry": {"coordinates":[147.12858581500001,-41.4237213135],"type":"Point"}
}