{
  "type": "Feature",
  "properties": {
    "addr:full":"68 Robinson Ave Belmont WA 6104",
    "addr:housenumber":"68",
    "addr:postcode":"6104",
    "addr:street":"Robinson Ave",
    "iso:country":"AU",
    "sg:address":"68 Robinson Ave",
    "sg:city":"Belmont",
    "sg:classifiers":[
        {
            "category":"Building & Trades",
            "subcategory":"Equipment Rental",
            "type":"Services"
        }
    ],
    "sg:phone":"+61 8 9479 4916",
    "sg:postcode":"6104",
    "sg:province":"WA",
    "sg:tags":[
        "party",
        "hire"
    ],
    "wof:name":"Morgan's Catering & Party Hire",
    "wof:placetype":"venue"
},
  "geometry": {"coordinates":[115.92880249,-31.9590606689],"type":"Point"}
}