{
  "type": "Feature",
  "properties": {
    "iso:country":"AU",
    "sg:address":"Unit 2/ 10A Durkin Pl",
    "sg:city":"Peakhurst",
    "sg:classifiers":[
        {
            "category":"Sports & Exercise",
            "subcategory":"Playing Field",
            "type":"Entertainment"
        }
    ],
    "sg:phone":"+61 2 9153 0500",
    "sg:postcode":"2210",
    "sg:province":"NSW",
    "sg:tags":[
        "gaming",
        "venue"
    ],
    "wof:name":"Compurep",
    "wof:placetype":"venue"
},
  "geometry": {"coordinates":[151.064697,-33.960171],"type":"Point"}
}