{
  "type": "Feature",
  "properties": {
    "iso:country":"AU",
    "sg:address":"133 Darby St",
    "sg:city":"Cooks Hill",
    "sg:classifiers":[
        {
            "category":"Restaurant",
            "type":"Food & Drink"
        }
    ],
    "sg:phone":"+61 2 4929 3610",
    "sg:postcode":"2300",
    "sg:province":"NSW",
    "wof:name":"Al-Oi Thai Restaurants",
    "wof:placetype":"venue"
},
  "geometry": {"coordinates":[151.771729,-32.931629],"type":"Point"}
}