{
  "type": "Feature",
  "properties": {
    "iso:country":"AU",
    "sg:address":"Hugh Quinn Crs",
    "sg:city":"Charters Towers",
    "sg:classifiers":[
        {
            "category":"Home & Garden",
            "subcategory":"Building Materials",
            "type":"Retail Goods"
        }
    ],
    "sg:phone":"+61 7 4761 5000",
    "sg:postcode":"4820",
    "sg:province":"QLD",
    "sg:tags":[
        "fencing"
    ],
    "sg:website":"http://www.metalcorpsteel.com.au",
    "wof:name":"Metalcorp Steel",
    "wof:placetype":"venue"
},
  "geometry": {"coordinates":[146.263153,-20.0774],"type":"Point"}
}