{
  "type": "Feature",
  "properties": {
    "addr:full":"38 Redden St Portsmith QLD 4870",
    "addr:housenumber":"38",
    "addr:postcode":"4870",
    "addr:street":"Redden St Portsmith",
    "iso:country":"AU",
    "sg:address":"38 Redden St",
    "sg:city":"Portsmith",
    "sg:classifiers":[
        {
            "category":"Food & Beverages",
            "subcategory":"Groceries & Convenience Stores",
            "type":"Retail Goods"
        }
    ],
    "sg:phone":"+61 7 4035 3456",
    "sg:postcode":"4870",
    "sg:province":"QLD",
    "sg:tags":[
        "merchant",
        "egg"
    ],
    "wof:name":"Bidvest Garozzo",
    "wof:placetype":"venue"
},
  "geometry": {"coordinates":[145.76968383799999,-16.9431419373],"type":"Point"}
}