{
  "type": "Feature",
  "properties": {
    "addr:full":"21 Redgum Pl Suffolk Park NSW 2481",
    "addr:housenumber":"21",
    "addr:postcode":"2481",
    "addr:street":"Redgum Pl Suffolk Park",
    "iso:country":"AU",
    "sg:address":"21 Redgum Pl",
    "sg:city":"Suffolk Park",
    "sg:classifiers":[
        {
            "category":"Utilities",
            "subcategory":"Electric",
            "type":"Services"
        }
    ],
    "sg:phone":"+61 2 6685 3243",
    "sg:postcode":"2481",
    "sg:province":"NSW",
    "sg:tags":[
        "electrical",
        "contractor"
    ],
    "wof:name":"Keenan's Electrical Service",
    "wof:placetype":"venue"
},
  "geometry": {"coordinates":[153.607818603,-28.6779613495],"type":"Point"}
}