{
  "type": "Feature",
  "properties": {
    "iso:country":"AU",
    "sg:address":"71 Victoria St",
    "sg:city":"Warragul",
    "sg:classifiers":[
        {
            "category":"Professional",
            "subcategory":"Printing & Photocopies",
            "type":"Services"
        }
    ],
    "sg:phone":"+61 3 5623 5173",
    "sg:postcode":"3820",
    "sg:province":"VIC",
    "sg:tags":[
        "photocopier"
    ],
    "wof:name":"Action Copiers",
    "wof:placetype":"venue"
},
  "geometry": {"coordinates":[145.929626,-38.15955],"type":"Point"}
}