{
  "type": "Feature",
  "properties": {
    "iso:country":"AU",
    "sg:address":"140 Church St",
    "sg:city":"Manifold Heights",
    "sg:classifiers":[
        {
            "category":"Sports & Exercise",
            "subcategory":"Gym",
            "type":"Entertainment"
        }
    ],
    "sg:phone":"+61 414 295 357",
    "sg:postcode":"3218",
    "sg:province":"VIC",
    "sg:tags":[
        "personal",
        "trainer",
        "fitness"
    ],
    "wof:name":"Vital Fitness",
    "wof:placetype":"venue"
},
  "geometry": {"coordinates":[144.338134766,-38.1304893494],"type":"Point"}
}