{
  "type": "Feature",
  "properties": {
    "addr:full":"120 Clifford St Stafford Heights QLD 4053",
    "addr:housenumber":"120",
    "addr:postcode":"4053",
    "addr:street":"Clifford St",
    "iso:country":"AU",
    "sg:address":"120 Clifford St",
    "sg:city":"Stafford Heights",
    "sg:classifiers":[
        {
            "category":"Food & Beverages",
            "subcategory":"Fruits & Vegetables",
            "type":"Retail Goods"
        }
    ],
    "sg:phone":"+61 7 3256 4411",
    "sg:postcode":"4053",
    "sg:province":"QLD",
    "sg:tags":[
        "consultant",
        "catering"
    ],
    "wof:name":"Essentially Gourmet",
    "wof:placetype":"venue"
},
  "geometry": {"coordinates":[153.02149963400001,-27.4043312073],"type":"Point"}
}