{
  "type": "Feature",
  "properties": {
    "iso:country":"AU",
    "sg:address":"131 Alexanders St",
    "sg:city":"Crows Nest",
    "sg:classifiers":[
        {
            "category":"Shopping",
            "subcategory":"Computers & Home Electronics",
            "type":"Retail Goods"
        }
    ],
    "sg:phone":"+61 2 9439 8955",
    "sg:postcode":"2065",
    "sg:province":"NSW",
    "sg:tags":[
        "equipment",
        "supply"
    ],
    "wof:name":"MEMFLEX",
    "wof:placetype":"venue"
},
  "geometry": {"coordinates":[151.20281982399999,-33.8244781494],"type":"Point"}
}