{
  "type": "Feature",
  "properties": {
    "addr:full":"1/ 1108 Waugh Rd North Albury NSW 2640",
    "addr:housenumber":"/ 1108",
    "addr:postcode":"2640",
    "addr:street":"Waugh Rd",
    "iso:country":"AU",
    "sg:address":"1/ 1108 Waugh Rd",
    "sg:city":"North Albury",
    "sg:classifiers":[
        {
            "category":"Shopping",
            "subcategory":"Stationery & Office Supplies",
            "type":"Retail Goods"
        }
    ],
    "sg:phone":"+61 2 6040 5292",
    "sg:postcode":"2640",
    "sg:province":"NSW",
    "sg:tags":[
        "equipment",
        "facsimile"
    ],
    "wof:name":"The Printer Wizards",
    "wof:placetype":"venue"
},
  "geometry": {"coordinates":[146.93284606899999,-36.0526695251],"type":"Point"}
}