{
  "type": "Feature",
  "properties": {
    "addr:full":"211 Westbury Rd Prospect TAS 7250",
    "addr:housenumber":"211",
    "addr:postcode":"7250",
    "addr:street":"Westbury Rd",
    "iso:country":"AU",
    "sg:address":"211 Westbury Rd",
    "sg:city":"Prospect",
    "sg:classifiers":[
        {
            "category":"Food & Beverages",
            "subcategory":"Supermarket",
            "type":"Retail Goods"
        }
    ],
    "sg:phone":"+61 3 6343 1611",
    "sg:postcode":"7250",
    "sg:province":"TAS",
    "sg:tags":[
        "grocery",
        "store"
    ],
    "wof:name":"Prospect Foodfare Supermarket",
    "wof:placetype":"venue"
},
  "geometry": {"coordinates":[147.137207031,-41.4699783325],"type":"Point"}
}