{
  "type": "Feature",
  "properties": {
    "iso:country":"AU",
    "sg:address":"Factory 4 85 High St",
    "sg:city":"Melton",
    "sg:classifiers":[
        {
            "category":"Retail",
            "subcategory":"Auto Repair",
            "type":"Services"
        }
    ],
    "sg:phone":"+61 3 9743 6926",
    "sg:postcode":"3337",
    "sg:province":"VIC",
    "sg:tags":[
        "automotive",
        "air conditioning"
    ],
    "wof:name":"Western Auto Air",
    "wof:placetype":"venue"
},
  "geometry": {"coordinates":[144.604034,-37.691086],"type":"Point"}
}