{
  "type": "Feature",
  "properties": {
    "addr:full":"Factory 4 85 High St Melton VIC 3337",
    "addr:housenumber":"85",
    "addr:postcode":"3337",
    "addr:street":"High St",
    "iso:country":"AU",
    "sg:address":"Factory 4 85 High St",
    "sg:city":"Melton",
    "sg:classifiers":[
        {
            "category":"Retail",
            "subcategory":"Auto Repair",
            "type":"Services"
        }
    ],
    "sg:phone":"+61 3 9743 6926",
    "sg:postcode":"3337",
    "sg:province":"VIC",
    "sg:tags":[
        "automotive",
        "air conditioning"
    ],
    "wof:name":"Western Auto Air",
    "wof:placetype":"venue"
},
  "geometry": {"coordinates":[144.60403400000001,-37.691086],"type":"Point"}
}