{
  "type": "Feature",
  "properties": {
    "addr:full":"8 MacKay Pl Wagga Wagga NSW 2650",
    "addr:housenumber":"8",
    "addr:postcode":"2650",
    "addr:street":"Mackay Pl",
    "iso:country":"AU",
    "sg:address":"8 MacKay Pl",
    "sg:city":"Wagga Wagga",
    "sg:classifiers":[
        {
            "category":"Social Services",
            "subcategory":"Child Care",
            "type":"Services"
        }
    ],
    "sg:phone":"+61 2 6971 2175",
    "sg:postcode":"2650",
    "sg:province":"NSW",
    "sg:tags":[
        "shearer"
    ],
    "wof:name":"R M Jacobson",
    "wof:placetype":"venue"
},
  "geometry": {"coordinates":[147.33949279800001,-35.119430542],"type":"Point"}
}