{
  "type": "Feature",
  "properties": {
    "iso:country":"AU",
    "sg:address":"60 Boyanda St",
    "sg:city":"Wishart",
    "sg:classifiers":[
        {
            "category":"Professional",
            "subcategory":"Art Services",
            "type":"Services"
        }
    ],
    "sg:phone":"+61 7 3420 6582",
    "sg:postcode":"4122",
    "sg:province":"QLD",
    "sg:tags":[
        "graphic",
        "designer"
    ],
    "wof:name":"Russell Kelly",
    "wof:placetype":"venue"
},
  "geometry": {"coordinates":[153.106201172,-27.5555820465],"type":"Point"}
}