{
  "type": "Feature",
  "properties": {
    "addr:full":"157 Liverpool St Sydney NSW 2000",
    "addr:housenumber":"157",
    "addr:postcode":"2000",
    "addr:street":"Liverpool St",
    "iso:country":"AU",
    "sg:address":"157 Liverpool St",
    "sg:city":"Sydney",
    "sg:classifiers":[
        {
            "category":"Real Estate",
            "subcategory":"Developer",
            "type":"Services"
        }
    ],
    "sg:phone":"+61 1800 251 813",
    "sg:postcode":"2000",
    "sg:province":"NSW",
    "sg:tags":[
        "development"
    ],
    "wof:name":"Stockland",
    "wof:placetype":"venue"
},
  "geometry": {"coordinates":[151.21014404300001,-33.8770103455],"type":"Point"}
}