{
  "type": "Feature",
  "properties": {
    "iso:country":"AU",
    "sg:address":"10 Spireton Pl",
    "sg:city":"Pendle Hill",
    "sg:classifiers":[
        {
            "category":"Professional",
            "subcategory":"Detective & Security Services",
            "type":"Services"
        }
    ],
    "sg:phone":"+61 2 9838 8979",
    "sg:postcode":"2145",
    "sg:province":"NSW",
    "sg:tags":[
        "consultant",
        "system"
    ],
    "wof:name":"Boss Safes & Security Pty Ltd",
    "wof:placetype":"venue"
},
  "geometry": {"coordinates":[150.95745849599999,-33.7968330383],"type":"Point"}
}