{
  "type": "Feature",
  "properties": {
    "addr:full":"1st Floor Corner Gladstone rd & Willford rd Enmore Enmore NSW 2042",
    "addr:postcode":"2042",
    "addr:street":"Gladstone Rd & Willford Rd",
    "iso:country":"AU",
    "sg:address":"1st Floor Corner Gladstone rd & Willford rd Enmore",
    "sg:city":"Enmore",
    "sg:classifiers":[
        {
            "category":"Government",
            "subcategory":"Post Office",
            "type":"Public Place"
        }
    ],
    "sg:phone":"+61 2 9519 3002",
    "sg:postcode":"2042",
    "sg:province":"NSW",
    "sg:tags":[
        "yoga"
    ],
    "wof:name":"Black Lotus Studios",
    "wof:placetype":"venue"
},
  "geometry": {"coordinates":[151.174667,-33.897732],"type":"Point"}
}