{
  "type": "Feature",
  "properties": {
    "iso:country":"AU",
    "sg:address":"382 Kent St",
    "sg:city":"Maryborough",
    "sg:classifiers":[
        {
            "category":"Shopping",
            "subcategory":"Jewelry",
            "type":"Retail Goods"
        }
    ],
    "sg:phone":"+61 7 4122 1122",
    "sg:postcode":"4650",
    "sg:province":"QLD",
    "sg:tags":[
        "jeweller"
    ],
    "wof:name":"Prestige Jewellery & Gifts",
    "wof:placetype":"venue"
},
  "geometry": {"coordinates":[152.699341,-25.535587],"type":"Point"}
}