{
  "type": "Feature",
  "properties": {
    "iso:country":"AU",
    "sg:address":"167 Main North Rd",
    "sg:city":"Clare",
    "sg:classifiers":[
        {
            "category":"Real Estate",
            "subcategory":"Real Estate Agent",
            "type":"Services"
        }
    ],
    "sg:phone":"+61 8 8842 3888",
    "sg:postcode":"5453",
    "sg:province":"SA",
    "wof:name":"L.J. Hooker",
    "wof:placetype":"venue"
},
  "geometry": {"coordinates":[138.611465,-33.832836],"type":"Point"}
}