{
  "type": "Feature",
  "properties": {
    "addr:full":"60 Main St Stawell VIC 3380",
    "addr:housenumber":"60",
    "addr:postcode":"3380",
    "addr:street":"Main St",
    "iso:country":"AU",
    "sg:address":"60 Main St",
    "sg:city":"Stawell",
    "sg:classifiers":[
        {
            "category":"Professional",
            "subcategory":"Computer Services",
            "type":"Services"
        }
    ],
    "sg:phone":"+61 3 5358 2432",
    "sg:postcode":"3380",
    "sg:province":"VIC",
    "sg:tags":[
        "repairs",
        "upgrade",
        "equipment"
    ],
    "wof:name":"Vicwest I.T.",
    "wof:placetype":"venue"
},
  "geometry": {"coordinates":[142.78558349599999,-37.0525588989],"type":"Point"}
}