{
  "type": "Feature",
  "properties": {
    "addr:full":"3 Putland Pl Oakville NSW 2765",
    "addr:housenumber":"3",
    "addr:postcode":"2765",
    "addr:street":"Putland Pl",
    "iso:country":"AU",
    "sg:address":"3 Putland Pl",
    "sg:city":"Oakville",
    "sg:classifiers":[
        {
            "category":"Parking",
            "subcategory":"Lot",
            "type":"Transportation"
        }
    ],
    "sg:phone":"+61 2 9627 3788",
    "sg:postcode":"2765",
    "sg:province":"NSW",
    "sg:tags":[
        "vegetable",
        "packing",
        "fruit",
        "pack"
    ],
    "wof:name":"Vegfarm Pty Ltd",
    "wof:placetype":"venue"
},
  "geometry": {"coordinates":[150.868240356,-33.6437301636],"type":"Point"}
}