{
  "type": "Feature",
  "properties": {
    "addr:full":"44 Leake St Bayswater WA 6053",
    "addr:housenumber":"44",
    "addr:postcode":"6053",
    "addr:street":"Leake St",
    "iso:country":"AU",
    "sg:address":"44 Leake St",
    "sg:city":"Bayswater",
    "sg:classifiers":[
        {
            "category":"Personal",
            "subcategory":"Massage",
            "type":"Services"
        }
    ],
    "sg:phone":"+61 8 9271 9809",
    "sg:postcode":"6053",
    "sg:province":"WA",
    "sg:tags":[
        "therapy"
    ],
    "wof:name":"Marian Hofstee",
    "wof:placetype":"venue"
},
  "geometry": {"coordinates":[115.912582398,-31.9225387573],"type":"Point"}
}