{
  "type": "Feature",
  "properties": {
    "addr:full":"128 Ellen St Port Pirie SA 5540",
    "addr:housenumber":"128",
    "addr:postcode":"5540",
    "addr:street":"Ellen St",
    "iso:country":"AU",
    "sg:address":"128 Ellen St",
    "sg:city":"Port Pirie",
    "sg:classifiers":[
        {
            "category":"Shopping",
            "subcategory":"Jewelry",
            "type":"Retail Goods"
        }
    ],
    "sg:phone":"+61 8 8633 0575",
    "sg:postcode":"5540",
    "sg:province":"SA",
    "sg:tags":[
        "jeweller"
    ],
    "wof:name":"LJ Edwards",
    "wof:placetype":"venue"
},
  "geometry": {"coordinates":[138.01014709500001,-33.1773529053],"type":"Point"}
}