{
  "type": "Feature",
  "properties": {
    "addr:full":"8 Grandview Pl Blakeview SA 5114",
    "addr:housenumber":"8",
    "addr:postcode":"5114",
    "addr:street":"Grandview Pl",
    "iso:country":"AU",
    "sg:address":"8 Grandview Pl",
    "sg:city":"Blakeview",
    "sg:classifiers":[
        {
            "category":"Home & Garden",
            "subcategory":"Building Materials",
            "type":"Retail Goods"
        }
    ],
    "sg:phone":"+61 417 809 059",
    "sg:postcode":"5114",
    "sg:province":"SA",
    "sg:tags":[
        "retaining",
        "wall"
    ],
    "wof:name":"Aussie Retaining Walls",
    "wof:placetype":"venue"
},
  "geometry": {"coordinates":[138.720245361,-34.6878700256],"type":"Point"}
}