{
  "type": "Feature",
  "properties": {
    "addr:full":"43 Grice St Clontarf QLD 4019",
    "addr:housenumber":"43",
    "addr:postcode":"4019",
    "addr:street":"Grice St",
    "iso:country":"AU",
    "sg:address":"43 Grice St",
    "sg:city":"Clontarf",
    "sg:classifiers":[
        {
            "category":"Wholesale",
            "subcategory":"Construction Materials",
            "type":"Manufacturing & Wholesale Goods"
        }
    ],
    "sg:phone":"+61 7 3883 1888",
    "sg:postcode":"4019",
    "sg:province":"QLD",
    "sg:tags":[
        "protective",
        "coating"
    ],
    "wof:name":"Adcrete Industries Pty Ltd",
    "wof:placetype":"venue"
},
  "geometry": {"coordinates":[153.0809021,-27.2353096008],"type":"Point"}
}