{
  "type": "Feature",
  "properties": {
    "iso:country":"AU",
    "sg:address":"51 Channel Hwy",
    "sg:city":"Margate",
    "sg:classifiers":[
        {
            "category":"Food & Beverages",
            "subcategory":"Supermarket",
            "type":"Retail Goods"
        }
    ],
    "sg:phone":"+61 3 6267 2188",
    "sg:postcode":"7054",
    "sg:province":"TAS",
    "sg:tags":[
        "grocery",
        "store"
    ],
    "wof:name":"Margate Village Supermarket",
    "wof:placetype":"venue"
},
  "geometry": {"coordinates":[147.261017,-43.026169],"type":"Point"}
}