{
  "type": "Feature",
  "properties": {
    "addr:full":"135 Cadogan St Carindale QLD 4152",
    "addr:housenumber":"135",
    "addr:postcode":"4152",
    "addr:street":"Cadogan St",
    "iso:country":"AU",
    "sg:address":"135 Cadogan St",
    "sg:city":"Carindale",
    "sg:classifiers":[
        {
            "category":"Education",
            "subcategory":"Music School",
            "type":"Public Place"
        }
    ],
    "sg:phone":"+61 7 3843 2647",
    "sg:postcode":"4152",
    "sg:province":"QLD",
    "sg:tags":[
        "teacher"
    ],
    "wof:name":"Berthelsen Margaret",
    "wof:placetype":"venue"
},
  "geometry": {"coordinates":[153.11843872099999,-27.4947052002],"type":"Point"}
}