{
  "type": "Feature",
  "properties": {
    "addr:full":"17 Duke St Mt Isa QLD 4825",
    "addr:housenumber":"17",
    "addr:postcode":"4825",
    "addr:street":"Duke St",
    "iso:country":"AU",
    "sg:address":"17 Duke St",
    "sg:city":"Mt Isa",
    "sg:classifiers":[
        {
            "category":"Professional",
            "subcategory":"Testing Lab",
            "type":"Services"
        }
    ],
    "sg:phone":"+61 7 4743 0544",
    "sg:postcode":"4825",
    "sg:province":"QLD",
    "sg:tags":[
        "inspection"
    ],
    "wof:name":"Inspections X-Ray & Testing Pty Ltd",
    "wof:placetype":"venue"
},
  "geometry": {"coordinates":[139.49617000000001,-20.741737],"type":"Point"}
}