{
  "type": "Feature",
  "properties": {
    "addr:full":"247a Beach St Frankston VIC 3199",
    "addr:housenumber":"247a",
    "addr:postcode":"3199",
    "addr:street":"Beach St",
    "iso:country":"AU",
    "sg:address":"247a Beach St",
    "sg:city":"Frankston",
    "sg:classifiers":[
        {
            "category":"Banks & Credit Unions",
            "subcategory":"Investment Brokerage",
            "type":"Services"
        }
    ],
    "sg:phone":"+61 414 866 369",
    "sg:postcode":"3199",
    "sg:province":"VIC",
    "sg:tags":[
        "finance",
        "broker"
    ],
    "wof:name":"Money Man",
    "wof:placetype":"venue"
},
  "geometry": {"coordinates":[145.14463806099999,-38.163433075],"type":"Point"}
}