{
  "type": "Feature",
  "properties": {
    "addr:full":"3 Sherwin Crt Fulham SA 5024",
    "addr:housenumber":"3",
    "addr:postcode":"5024",
    "addr:street":"Sherwin Crt",
    "iso:country":"AU",
    "sg:address":"3 Sherwin Crt",
    "sg:city":"Fulham",
    "sg:classifiers":[
        {
            "category":"Organizations",
            "subcategory":"Membership Organization",
            "type":"Services"
        }
    ],
    "sg:phone":"+61 8 8356 9508",
    "sg:postcode":"5024",
    "sg:province":"SA",
    "sg:tags":[
        "club",
        "car"
    ],
    "wof:name":"Singer Car Club Of South Australia Inc",
    "wof:placetype":"venue"
},
  "geometry": {"coordinates":[138.513595581,-34.9269790649],"type":"Point"}
}