{
  "type": "Feature",
  "properties": {
    "iso:country":"AU",
    "sg:address":"Unit 3, 707 Forest Rd",
    "sg:city":"Bexley",
    "sg:classifiers":[
        {
            "category":"Building & Trades",
            "subcategory":"Construction",
            "type":"Services"
        }
    ],
    "sg:phone":"+61 2 9588 6000",
    "sg:postcode":"2207",
    "sg:province":"NSW",
    "sg:tags":[
        "contractor"
    ],
    "wof:name":"Trudecon Pty Ltd",
    "wof:placetype":"venue"
},
  "geometry": {"coordinates":[151.116257,-33.960613],"type":"Point"}
}