{
  "type": "Feature",
  "properties": {
    "addr:full":"27 Manning Rd Como WA 6152",
    "addr:housenumber":"27",
    "addr:postcode":"6152",
    "addr:street":"Manning Rd",
    "iso:country":"AU",
    "sg:address":"27 Manning Rd",
    "sg:city":"Como",
    "sg:classifiers":[
        {
            "category":"Travel",
            "subcategory":"Hotels & Motels",
            "type":"Entertainment"
        }
    ],
    "sg:phone":"+61 8 9450 7709",
    "sg:postcode":"6152",
    "sg:province":"WA",
    "sg:tags":[
        "accommodation"
    ],
    "wof:name":"Mount Henry Tavern",
    "wof:placetype":"venue"
},
  "geometry": {"coordinates":[115.865173,-32.011616],"type":"Point"}
}