{
  "type": "Feature",
  "properties": {
    "iso:country":"AU",
    "sg:address":"3/ 703 Murray St",
    "sg:city":"West Perth",
    "sg:classifiers":[
        {
            "category":"Health Services",
            "subcategory":"Health Practitioner",
            "type":"Services"
        }
    ],
    "sg:phone":"+61 8 9486 1830",
    "sg:postcode":"6005",
    "sg:province":"WA",
    "sg:tags":[
        "psychotherapist"
    ],
    "wof:name":"Agape Psychotherapy & Counselling",
    "wof:placetype":"venue"
},
  "geometry": {"coordinates":[115.839820862,-31.9465751648],"type":"Point"}
}