{
  "type": "Feature",
  "properties": {
    "addr:full":"26 Bickford Rd Grovedale VIC 3216",
    "addr:housenumber":"26",
    "addr:postcode":"3216",
    "addr:street":"Bickford Rd",
    "iso:country":"AU",
    "sg:address":"26 Bickford Rd",
    "sg:city":"Grovedale",
    "sg:classifiers":[
        {
            "category":"Building & Trades",
            "subcategory":"Construction",
            "type":"Services"
        }
    ],
    "sg:phone":"+61 425 762 437",
    "sg:postcode":"3216",
    "sg:province":"VIC",
    "sg:tags":[
        "contractor"
    ],
    "wof:name":"All Areas Building Services Pty Ltd",
    "wof:placetype":"venue"
},
  "geometry": {"coordinates":[144.33189392099999,-38.2123374939],"type":"Point"}
}