{
  "type": "Feature",
  "properties": {
    "addr:full":"265 Arden St Coogee NSW 2034",
    "addr:housenumber":"265",
    "addr:postcode":"2034",
    "addr:street":"Arden St",
    "iso:country":"AU",
    "sg:address":"265 Arden St",
    "sg:city":"Coogee",
    "sg:classifiers":[
        {
            "category":"Shopping",
            "subcategory":"Clothing, Apparel, & Fashions",
            "type":"Retail Goods"
        }
    ],
    "sg:phone":"+61 2 9665 5330",
    "sg:postcode":"2034",
    "sg:province":"NSW",
    "sg:tags":[
        "recycled",
        "clothing"
    ],
    "wof:name":"Bobby Dazzler",
    "wof:placetype":"venue"
},
  "geometry": {"coordinates":[151.256393433,-33.9236068726],"type":"Point"}
}