{
  "type": "Feature",
  "properties": {
    "addr:full":"75 Beaumont St Hamilton NSW 2303",
    "addr:housenumber":"75",
    "addr:postcode":"2303",
    "addr:street":"Beaumont St",
    "iso:country":"AU",
    "sg:address":"75 Beaumont St",
    "sg:city":"Hamilton",
    "sg:classifiers":[
        {
            "category":"Health Services",
            "subcategory":"Doctor",
            "type":"Services"
        }
    ],
    "sg:phone":"+61 2 4962 2662",
    "sg:postcode":"2303",
    "sg:province":"NSW",
    "sg:tags":[
        "medical",
        "practitioner"
    ],
    "wof:name":"Eastham C Dr",
    "wof:placetype":"venue"
},
  "geometry": {"coordinates":[151.74737500000001,-32.922344],"type":"Point"}
}