{
  "type": "Feature",
  "properties": {
    "addr:full":"7 Lindsay Crt Traralgon VIC 3844",
    "addr:housenumber":"7",
    "addr:postcode":"3844",
    "addr:street":"Lindsay Crt",
    "iso:country":"AU",
    "sg:address":"7 Lindsay Crt",
    "sg:city":"Traralgon",
    "sg:classifiers":[
        {
            "category":"Personal",
            "subcategory":"Massage",
            "type":"Services"
        }
    ],
    "sg:phone":"+61 3 5174 1579",
    "sg:postcode":"3844",
    "sg:province":"VIC",
    "sg:tags":[
        "therapy"
    ],
    "wof:name":"Airey Ron G",
    "wof:placetype":"venue"
},
  "geometry": {"coordinates":[146.532073975,-38.1900901794],"type":"Point"}
}