{
  "type": "Feature",
  "properties": {
    "addr:full":"Great Western Super Centre, Cnr Old Settlement & S Keperra QLD 4054",
    "addr:postcode":"4054",
    "addr:street":"Cnr Old",
    "iso:country":"AU",
    "sg:address":"Great Western Super Centre, Cnr Old Settlement & S",
    "sg:city":"Keperra",
    "sg:classifiers":[
        {
            "category":"Fast Food",
            "type":"Food & Drink"
        }
    ],
    "sg:phone":"+61 7 3892 1111",
    "sg:postcode":"4054",
    "sg:province":"QLD",
    "sg:tags":[
        "away",
        "take"
    ],
    "wof:name":"Pizza Hut",
    "wof:placetype":"venue"
},
  "geometry": {"coordinates":[152.96205139200001,-27.4123306274],"type":"Point"}
}