{
  "type": "Feature",
  "properties": {
    "addr:full":"55 Blaxland Rd Campbelltown NSW 2560",
    "addr:housenumber":"55",
    "addr:postcode":"2560",
    "addr:street":"Blaxland Rd",
    "iso:country":"AU",
    "sg:address":"55 Blaxland Rd",
    "sg:city":"Campbelltown",
    "sg:classifiers":[
        {
            "category":"Home & Garden",
            "subcategory":"Garden Supply",
            "type":"Retail Goods"
        }
    ],
    "sg:phone":"+61 2 4628 1330",
    "sg:postcode":"2560",
    "sg:province":"NSW",
    "sg:tags":[
        "fertilizer"
    ],
    "wof:name":"Campbelltown Produce",
    "wof:placetype":"venue"
},
  "geometry": {"coordinates":[150.81195068400001,-34.0605583191],"type":"Point"}
}