{
  "type": "Feature",
  "properties": {
    "iso:country":"AU",
    "sg:address":"\"Belleville\" Mitta Rd",
    "sg:city":"Mitta Mitta",
    "sg:classifiers":[
        {
            "category":"Farming",
            "subcategory":"Farm",
            "type":"Manufacturing & Wholesale Goods"
        }
    ],
    "sg:phone":"+61 2 6072 3542",
    "sg:postcode":"3701",
    "sg:province":"VIC",
    "sg:tags":[
        "farmer"
    ],
    "wof:name":"Cardwell John R",
    "wof:placetype":"venue"
},
  "geometry": {"coordinates":[147.26625060999999,-36.4568061829],"type":"Point"}
}