{
  "type": "Feature",
  "properties": {
    "addr:full":"17 Wadhurst Drv Boronia VIC 3155",
    "addr:housenumber":"17",
    "addr:postcode":"3155",
    "addr:street":"Wadhurst Drv",
    "iso:country":"AU",
    "sg:address":"17 Wadhurst Drv",
    "sg:city":"Boronia",
    "sg:classifiers":[
        {
            "category":"Manufacturing",
            "subcategory":"Building Materials",
            "type":"Manufacturing & Wholesale Goods"
        }
    ],
    "sg:phone":"+61 3 9801 3166",
    "sg:postcode":"3155",
    "sg:province":"VIC",
    "sg:tags":[
        "concrete",
        "product"
    ],
    "wof:name":"Cope Industries Pty Ltd",
    "wof:placetype":"venue"
},
  "geometry": {"coordinates":[145.25494384800001,-37.8662757874],"type":"Point"}
}