{
  "type": "Feature",
  "properties": {
    "addr:full":"173 Davey St Hobart TAS 7000",
    "addr:housenumber":"173",
    "addr:postcode":"7000",
    "addr:street":"Davey St",
    "iso:country":"AU",
    "sg:address":"173 Davey St",
    "sg:city":"Hobart",
    "sg:classifiers":[
        {
            "category":"Health Services",
            "subcategory":"Doctor",
            "type":"Services"
        }
    ],
    "sg:phone":"+61 3 6223 8981",
    "sg:postcode":"7000",
    "sg:province":"TAS",
    "sg:tags":[
        "medical",
        "practitioner"
    ],
    "wof:name":"Ram Asha",
    "wof:placetype":"venue"
},
  "geometry": {"coordinates":[147.32098388700001,-42.891002655],"type":"Point"}
}