{
  "type": "Feature",
  "properties": {
    "addr:full":"257 North east Rd Hampstead Gardens SA 5086",
    "addr:housenumber":"257",
    "addr:postcode":"5086",
    "addr:street":"North East Rd",
    "iso:country":"AU",
    "sg:address":"257 North east Rd",
    "sg:city":"Hampstead Gardens",
    "sg:classifiers":[
        {
            "category":"Health Services",
            "subcategory":"Health Practitioner",
            "type":"Services"
        }
    ],
    "sg:phone":"+61 8 8269 3800",
    "sg:postcode":"5086",
    "sg:province":"SA",
    "sg:tags":[
        "physiotherapist"
    ],
    "wof:name":"Ashley Smith PhysioNow",
    "wof:placetype":"venue"
},
  "geometry": {"coordinates":[138.63150024399999,-34.8753051758],"type":"Point"}
}