{
  "type": "Feature",
  "properties": {
    "iso:country":"AU",
    "sg:address":"19 Randall St",
    "sg:city":"Slacks Creek",
    "sg:classifiers":[
        {
            "category":"Transit Center",
            "subcategory":"Passenger",
            "type":"Transportation"
        }
    ],
    "sg:phone":"+61 7 3808 9388",
    "sg:postcode":"4127",
    "sg:province":"QLD",
    "sg:tags":[
        "packing",
        "gasket"
    ],
    "wof:name":"Spareco Pty Ltd",
    "wof:placetype":"venue"
},
  "geometry": {"coordinates":[153.11917114299999,-27.6258926392],"type":"Point"}
}