{
  "type": "Feature",
  "properties": {
    "addr:full":"140 Gerler Rd Hendra QLD 4011",
    "addr:housenumber":"140",
    "addr:postcode":"4011",
    "addr:street":"Gerler Rd",
    "iso:country":"AU",
    "sg:address":"140 Gerler Rd",
    "sg:city":"Hendra",
    "sg:classifiers":[
        {
            "category":"Utilities",
            "subcategory":"Refuse",
            "type":"Services"
        }
    ],
    "sg:phone":"+61 1300 663 205",
    "sg:postcode":"4011",
    "sg:province":"QLD",
    "sg:tags":[
        "disposal",
        "reduction",
        "waste"
    ],
    "wof:name":"Andys Skips",
    "wof:placetype":"venue"
},
  "geometry": {"coordinates":[153.07247899999999,-27.418926],"type":"Point"}
}