{
  "type": "Feature",
  "properties": {
    "iso:country":"AU",
    "sg:address":"5 Hayward Crt",
    "sg:city":"Bairnsdale",
    "sg:classifiers":[
        {
            "category":"Manufacturing",
            "subcategory":"Metals",
            "type":"Manufacturing & Wholesale Goods"
        }
    ],
    "sg:phone":"+61 3 5153 2611",
    "sg:postcode":"3875",
    "sg:province":"VIC",
    "sg:tags":[
        "steel",
        "fabricator",
        "mfrs"
    ],
    "wof:name":"A.C.C. Engineering Pty Ltd",
    "wof:placetype":"venue"
},
  "geometry": {"coordinates":[147.61555480999999,-37.8372917175],"type":"Point"}
}