{
  "type": "Feature",
  "properties": {
    "addr:full":"1188 Toorak Rd Camberwell VIC 3124",
    "addr:housenumber":"1188",
    "addr:postcode":"3124",
    "addr:street":"Toorak Rd",
    "iso:country":"AU",
    "sg:address":"1188 Toorak Rd",
    "sg:city":"Camberwell",
    "sg:classifiers":[
        {
            "category":"Building & Trades",
            "subcategory":"Construction",
            "type":"Services"
        }
    ],
    "sg:phone":"+61 3 8832 9000",
    "sg:postcode":"3124",
    "sg:province":"VIC",
    "sg:tags":[
        "window",
        "aluminium"
    ],
    "wof:name":"Valley Windows Pty Ltd",
    "wof:placetype":"venue"
},
  "geometry": {"coordinates":[145.07963562,-37.8486480713],"type":"Point"}
}