{
  "type": "Feature",
  "properties": {
    "addr:full":"612 Crown St Surry Hills NSW 2010",
    "addr:housenumber":"612",
    "addr:postcode":"2010",
    "addr:street":"Crown St",
    "iso:country":"AU",
    "sg:address":"612 Crown St",
    "sg:city":"Surry Hills",
    "sg:classifiers":[
        {
            "category":"Cafe",
            "type":"Food & Drink"
        }
    ],
    "sg:phone":"+61 2 9690 2949",
    "sg:postcode":"2010",
    "sg:province":"NSW",
    "wof:name":"Fine Food Deli Cafe",
    "wof:placetype":"venue"
},
  "geometry": {"coordinates":[151.21322631800001,-33.8902359009],"type":"Point"}
}