{
  "type": "Feature",
  "properties": {
    "iso:country":"AU",
    "sg:address":"5 Hall St",
    "sg:city":"Moonee Ponds",
    "sg:classifiers":[
        {
            "category":"Personal",
            "subcategory":"Beauty Salon",
            "type":"Services"
        }
    ],
    "sg:phone":"+61 3 9370 0922",
    "sg:postcode":"3039",
    "sg:province":"VIC",
    "sg:tags":[
        "hairdresser"
    ],
    "wof:name":"Johan Hairdressing",
    "wof:placetype":"venue"
},
  "geometry": {"coordinates":[144.92385899999999,-37.766357],"type":"Point"}
}