{
  "type": "Feature",
  "properties": {
    "addr:full":"60 Magnesium Drv Crestmead QLD 4132",
    "addr:housenumber":"60",
    "addr:postcode":"4132",
    "addr:street":"Magnesium Drv",
    "iso:country":"AU",
    "sg:address":"60 Magnesium Drv",
    "sg:city":"Crestmead",
    "sg:classifiers":[
        {
            "category":"Manufacturing",
            "subcategory":"Glass & Minerals",
            "type":"Manufacturing & Wholesale Goods"
        }
    ],
    "sg:phone":"+61 7 3803 7100",
    "sg:postcode":"4132",
    "sg:province":"QLD",
    "sg:tags":[
        "fabricator",
        "foam",
        "processor"
    ],
    "wof:name":"Hi-Tek Foamworks Pty Ltd",
    "wof:placetype":"venue"
},
  "geometry": {"coordinates":[153.07562255900001,-27.677444458],"type":"Point"}
}