{
  "type": "Feature",
  "properties": {
    "addr:full":"Lot 26 Wrightville St Cobar NSW 2835",
    "addr:postcode":"2835",
    "addr:street":"St",
    "iso:country":"AU",
    "sg:address":"Lot 26 Wrightville St",
    "sg:city":"Cobar",
    "sg:classifiers":[
        {
            "category":"Manufacturing",
            "subcategory":"Metals",
            "type":"Manufacturing & Wholesale Goods"
        }
    ],
    "sg:phone":"+61 2 6836 1377",
    "sg:postcode":"2835",
    "sg:province":"NSW",
    "sg:tags":[
        "steel",
        "fabricator",
        "mfrs"
    ],
    "wof:name":"Raboc Enterprises",
    "wof:placetype":"venue"
},
  "geometry": {"coordinates":[145.85348500000001,-31.498552],"type":"Point"}
}