{
  "type": "Feature",
  "properties": {
    "addr:full":"Cnr Sydney & Brunswick Rds Brunswick VIC 3056",
    "addr:postcode":"3056",
    "iso:country":"AU",
    "sg:address":"Cnr Sydney & Brunswick Rds",
    "sg:city":"Brunswick",
    "sg:classifiers":[
        {
            "category":"Food & Beverages",
            "subcategory":"Groceries & Convenience Stores",
            "type":"Retail Goods"
        }
    ],
    "sg:phone":"+61 3 9380 4273",
    "sg:postcode":"3056",
    "sg:province":"VIC",
    "wof:name":"7-Eleven Stores Pty Ltd",
    "wof:placetype":"venue"
},
  "geometry": {"coordinates":[144.96217346200001,-37.7665748596],"type":"Point"}
}