{
  "type": "Feature",
  "properties": {
    "addr:full":"Unit 2/ 3 Contaplas St Arndell Park NSW 2148",
    "addr:housenumber":"3",
    "addr:postcode":"2148",
    "addr:street":"Contaplas St",
    "iso:country":"AU",
    "sg:address":"Unit 2/ 3 Contaplas St",
    "sg:city":"Arndell Park",
    "sg:classifiers":[
        {
            "category":"Military Area",
            "subcategory":"Army Base",
            "type":"Public Place"
        }
    ],
    "sg:phone":"+61 2 9831 7771",
    "sg:postcode":"2148",
    "sg:province":"NSW",
    "sg:tags":[
        "wholesaler",
        "clutch",
        "brake",
        "mfrs",
        "equipment"
    ],
    "wof:name":"Exedy Australia Pty Ltd",
    "wof:placetype":"venue"
},
  "geometry": {"coordinates":[150.87661743199999,-33.7878189087],"type":"Point"}
}