{
  "type": "Feature",
  "properties": {
    "iso:country":"AU",
    "sg:address":"Elizabeth St",
    "sg:city":"York",
    "sg:classifiers":[
        {
            "category":"Retail",
            "subcategory":"Auto Repair",
            "type":"Services"
        }
    ],
    "sg:phone":"+61 8 9641 1929",
    "sg:postcode":"6302",
    "sg:province":"WA",
    "sg:tags":[
        "electrical"
    ],
    "wof:name":"York Auto Electrics",
    "wof:placetype":"venue"
},
  "geometry": {"coordinates":[116.76799774200001,-31.8952960968],"type":"Point"}
}