{
  "type": "Feature",
  "properties": {
    "iso:country":"AU",
    "sg:address":"Ground Floor, 8 Manning Rd",
    "sg:city":"Double Bay",
    "sg:classifiers":[
        {
            "category":"Health Services",
            "subcategory":"Doctor",
            "type":"Services"
        }
    ],
    "sg:phone":"+61 2 9327 8265",
    "sg:postcode":"2028",
    "sg:province":"NSW",
    "sg:tags":[
        "medical",
        "practitioner"
    ],
    "wof:name":"SDS Pathology",
    "wof:placetype":"venue"
},
  "geometry": {"coordinates":[151.242645264,-33.87890625],"type":"Point"}
}