{
  "type": "Feature",
  "properties": {
    "addr:full":"12a Oraston Ave Brighton SA 5048",
    "addr:housenumber":"12a",
    "addr:postcode":"5048",
    "addr:street":"Oraston Ave",
    "iso:country":"AU",
    "sg:address":"12a Oraston Ave",
    "sg:city":"Brighton",
    "sg:classifiers":[
        {
            "category":"Real Estate",
            "subcategory":"Architect",
            "type":"Services"
        }
    ],
    "sg:phone":"+61 8 8377 5661",
    "sg:postcode":"5048",
    "sg:province":"SA",
    "wof:name":"Bartlett John Architect",
    "wof:placetype":"venue"
},
  "geometry": {"coordinates":[138.52593999999999,-35.020477],"type":"Point"}
}