{
  "type": "Feature",
  "properties": {
    "iso:country":"AU",
    "sg:address":"PO Box 118",
    "sg:city":"Rosewood",
    "sg:classifiers":[
        {
            "category":"Building & Trades",
            "subcategory":"Landscaping Services",
            "type":"Services"
        }
    ],
    "sg:phone":"+61 7 5464 0566",
    "sg:postcode":"4340",
    "sg:province":"QLD",
    "sg:tags":[
        "designer",
        "landscape",
        "contractor"
    ],
    "wof:name":"A J & M Excavations",
    "wof:placetype":"venue"
},
  "geometry": {"coordinates":[152.58900451700001,-27.6344203949],"type":"Point"}
}