{
  "type": "Feature",
  "properties": {
    "addr:full":"Shop 2/ 3 Ballantine St Gladstone QLD 4680",
    "addr:housenumber":"shop 2 / 3",
    "addr:postcode":"4680",
    "addr:street":"Ballantine St",
    "iso:country":"AU",
    "sg:address":"Shop 2/ 3 Ballantine St",
    "sg:city":"Gladstone",
    "sg:classifiers":[
        {
            "category":"Fast Food",
            "type":"Food & Drink"
        }
    ],
    "sg:phone":"+61 7 4978 0161",
    "sg:postcode":"4680",
    "sg:province":"QLD",
    "sg:tags":[
        "away",
        "take"
    ],
    "wof:name":"Georgias Fish Cafe",
    "wof:placetype":"venue"
},
  "geometry": {"coordinates":[151.22486877399999,-23.874956131],"type":"Point"}
}