{
  "type": "Feature",
  "properties": {
    "addr:full":"16 Warra St Jandowae QLD 4410",
    "addr:housenumber":"16",
    "addr:postcode":"4410",
    "addr:street":"Warra St",
    "iso:country":"AU",
    "sg:address":"16 Warra St",
    "sg:city":"Jandowae",
    "sg:classifiers":[
        {
            "category":"Food & Beverages",
            "subcategory":"Fruits & Vegetables",
            "type":"Retail Goods"
        }
    ],
    "sg:phone":"+61 7 4668 5181",
    "sg:postcode":"4410",
    "sg:province":"QLD",
    "sg:tags":[
        "wholesale"
    ],
    "wof:name":"Jandowae Enterprises",
    "wof:placetype":"venue"
},
  "geometry": {"coordinates":[151.107025147,-26.7820835114],"type":"Point"}
}