{
  "type": "Feature",
  "properties": {
    "addr:full":"Shop 6 / 35 Fawcett St Ballina NSW 2478",
    "addr:housenumber":"shop 6 / 35",
    "addr:postcode":"2478",
    "addr:street":"Fawcett St",
    "iso:country":"AU",
    "sg:address":"Shop 6 / 35 Fawcett St",
    "sg:city":"Ballina",
    "sg:classifiers":[
        {
            "category":"Personal",
            "subcategory":"Hair Removal",
            "type":"Services"
        }
    ],
    "sg:phone":"+61 1300 665 338",
    "sg:postcode":"2478",
    "sg:province":"NSW",
    "wof:name":"Hair Free Centre",
    "wof:placetype":"venue"
},
  "geometry": {"coordinates":[153.55917358400001,-28.8705101013],"type":"Point"}
}