{
  "type": "Feature",
  "properties": {
    "addr:full":"Suite 7 / 409 King Georges Rd Beverly Hills NSW 2209",
    "addr:housenumber":"/ 409",
    "addr:postcode":"2209",
    "addr:street":"King Georges Rd",
    "iso:country":"AU",
    "sg:address":"Suite 7 / 409 King Georges Rd",
    "sg:city":"Beverly Hills",
    "sg:classifiers":[
        {
            "category":"Professional",
            "subcategory":"Accounting & Tax Preparation",
            "type":"Services"
        }
    ],
    "sg:phone":"+61 2 9570 3427",
    "sg:postcode":"2209",
    "sg:province":"NSW",
    "sg:tags":[
        "accountant",
        "auditor"
    ],
    "wof:name":"GPL Partners",
    "wof:placetype":"venue"
},
  "geometry": {"coordinates":[151.08059700000001,-33.94949],"type":"Point"}
}