{
  "type": "Feature",
  "properties": {
    "addr:full":"121 Herald St Cheltenham VIC 3192",
    "addr:housenumber":"121",
    "addr:postcode":"3192",
    "addr:street":"Herald St",
    "iso:country":"AU",
    "sg:address":"121 Herald St",
    "sg:city":"Cheltenham",
    "sg:classifiers":[
        {
            "category":"Farming",
            "subcategory":"Farm & Veterinary Services",
            "type":"Manufacturing & Wholesale Goods"
        }
    ],
    "sg:phone":"+61 3 9553 3777",
    "sg:postcode":"3192",
    "sg:province":"VIC",
    "sg:tags":[
        "irrigation",
        "reticulation",
        "system"
    ],
    "wof:name":"Sage Horticultural",
    "wof:placetype":"venue"
},
  "geometry": {"coordinates":[145.073028564,-37.9540710449],"type":"Point"}
}