{
  "type": "Feature",
  "properties": {
    "addr:full":"32 Shorts Rd Coburg North VIC 3058",
    "addr:housenumber":"32",
    "addr:postcode":"3058",
    "addr:street":"Shorts Rd",
    "iso:country":"AU",
    "sg:address":"32 Shorts Rd",
    "sg:city":"Coburg North",
    "sg:classifiers":[
        {
            "category":"Personal",
            "subcategory":"Massage",
            "type":"Services"
        }
    ],
    "sg:phone":"+61 3 9354 9141",
    "sg:postcode":"3058",
    "sg:province":"VIC",
    "sg:tags":[
        "therapy"
    ],
    "wof:name":"Christidis, Venetia",
    "wof:placetype":"venue"
},
  "geometry": {"coordinates":[144.95857238799999,-37.7233848572],"type":"Point"}
}