{
  "type": "Feature",
  "properties": {
    "addr:full":"CWA Hall Kamerunga Rd Caravonica QLD 4878",
    "addr:postcode":"4878",
    "addr:street":"Kamerunga Rd",
    "iso:country":"AU",
    "sg:address":"CWA Hall Kamerunga Rd",
    "sg:city":"Caravonica",
    "sg:classifiers":[
        {
            "category":"Sports & Exercise",
            "subcategory":"Gym",
            "type":"Entertainment"
        }
    ],
    "sg:phone":"+61 403 828 785",
    "sg:postcode":"4878",
    "sg:province":"QLD",
    "sg:tags":[
        "health",
        "fitness"
    ],
    "wof:name":"Dance Junction",
    "wof:placetype":"venue"
},
  "geometry": {"coordinates":[145.71015930199999,-16.8811378479],"type":"Point"}
}