{
  "type": "Feature",
  "properties": {
    "addr:full":"11 Cowper Rd Umina Beach NSW 2257",
    "addr:housenumber":"11",
    "addr:postcode":"2257",
    "addr:street":"Cowper Rd",
    "iso:country":"AU",
    "sg:address":"11 Cowper Rd",
    "sg:city":"Umina Beach",
    "sg:classifiers":[
        {
            "category":"Building & Trades",
            "subcategory":"Cleaning & Sanitation",
            "type":"Services"
        }
    ],
    "sg:phone":"+61 2 4341 0159",
    "sg:postcode":"2257",
    "sg:province":"NSW",
    "sg:tags":[
        "grease",
        "trap"
    ],
    "wof:name":"Bright's Grease Trap Service",
    "wof:placetype":"venue"
},
  "geometry": {"coordinates":[151.30418395999999,-33.5316619873],"type":"Point"}
}