{
  "type": "Feature",
  "properties": {
    "addr:full":"Shed 8 Deefa St Caloundra QLD 4551",
    "addr:housenumber":"8",
    "addr:postcode":"4551",
    "addr:street":"Deefa St",
    "iso:country":"AU",
    "sg:address":"Shed 8 Deefa St",
    "sg:city":"Caloundra",
    "sg:classifiers":[
        {
            "category":"Building & Trades",
            "subcategory":"Plumbing",
            "type":"Services"
        }
    ],
    "sg:phone":"+61 7 5492 8477",
    "sg:postcode":"4551",
    "sg:province":"QLD",
    "sg:tags":[
        "plumber",
        "gasfitters"
    ],
    "wof:name":"I W & D J McArthur Pty Ltd",
    "wof:placetype":"venue"
},
  "geometry": {"coordinates":[153.10992431599999,-26.7945766449],"type":"Point"}
}