{
  "type": "Feature",
  "properties": {
    "iso:country":"AU",
    "sg:address":"61 Church St",
    "sg:city":"Wollongong",
    "sg:classifiers":[
        {
            "category":"Retail",
            "subcategory":"Event Space",
            "type":"Services"
        }
    ],
    "sg:phone":"+61 2 4229 6466",
    "sg:postcode":"2500",
    "sg:province":"NSW",
    "sg:tags":[
        "venue",
        "reception",
        "wedding"
    ],
    "wof:name":"Illawarra Master Builders Club",
    "wof:placetype":"venue"
},
  "geometry": {"coordinates":[150.896545,-34.420921],"type":"Point"}
}