{
  "type": "Feature",
  "properties": {
    "addr:full":"Unit A1 / 255 Rawson St Auburn NSW 2144",
    "addr:housenumber":"255",
    "addr:postcode":"2144",
    "addr:street":"Rawson St",
    "iso:country":"AU",
    "sg:address":"Unit A1 / 255 Rawson St",
    "sg:city":"Auburn",
    "sg:classifiers":[
        {
            "category":"Professional",
            "subcategory":"Art Services",
            "type":"Services"
        }
    ],
    "sg:phone":"+61 2 9748 7088",
    "sg:postcode":"2144",
    "sg:province":"NSW",
    "sg:tags":[
        "decorator",
        "painter"
    ],
    "wof:name":"Programmed Maintenance Services",
    "wof:placetype":"venue"
},
  "geometry": {"coordinates":[151.026733398,-33.8401756287],"type":"Point"}
}