{
  "type": "Feature",
  "properties": {
    "addr:full":"Unit 7, 36 Port Kembla Drv Bibra Lake WA 6163",
    "addr:housenumber":"36",
    "addr:postcode":"6163",
    "addr:street":"Port Kembla Drv",
    "iso:country":"AU",
    "sg:address":"Unit 7, 36 Port Kembla Drv",
    "sg:city":"Bibra Lake",
    "sg:classifiers":[
        {
            "category":"Home & Garden",
            "subcategory":"Garden Supply",
            "type":"Retail Goods"
        }
    ],
    "sg:phone":"+61 8 9434 5118",
    "sg:postcode":"6163",
    "sg:province":"WA",
    "sg:tags":[
        "equipment",
        "hydroponics"
    ],
    "wof:name":"Tru Bloomin Hydroponics",
    "wof:placetype":"venue"
},
  "geometry": {"coordinates":[115.801361,-32.10038],"type":"Point"}
}