{
  "type": "Feature",
  "properties": {
    "addr:full":"2/ 6 Roeszler La Melbourne VIC 3000",
    "addr:housenumber":"/ 6",
    "addr:postcode":"3000",
    "addr:street":"Roeszler La",
    "iso:country":"AU",
    "sg:address":"2/ 6 Roeszler La",
    "sg:city":"Melbourne",
    "sg:classifiers":[
        {
            "category":"Organizations",
            "subcategory":"Professional Association",
            "type":"Services"
        }
    ],
    "sg:phone":"+61 3 9600 0091",
    "sg:postcode":"3000",
    "sg:province":"VIC",
    "sg:tags":[
        "web",
        "internet"
    ],
    "wof:name":"Flip Digital",
    "wof:placetype":"venue"
},
  "geometry": {"coordinates":[144.960403442,-37.8162498474],"type":"Point"}
}