{
  "type": "Feature",
  "properties": {
    "addr:full":"High St Alford SA 5555",
    "addr:postcode":"5555",
    "addr:street":"High St",
    "iso:country":"AU",
    "sg:address":"High St",
    "sg:city":"Alford",
    "sg:classifiers":[
        {
            "category":"Education",
            "subcategory":"School",
            "type":"Public Place"
        }
    ],
    "sg:phone":"+61 8 8824 2239",
    "sg:postcode":"5555",
    "sg:province":"SA",
    "sg:tags":[
        "state",
        "except",
        "nsw"
    ],
    "wof:name":"Alford Primary School",
    "wof:placetype":"venue"
},
  "geometry": {"coordinates":[137.82167053200001,-33.8163566589],"type":"Point"}
}