{
  "type": "Feature",
  "properties": {
    "addr:full":"Bass Hwy Inverloch VIC 3996",
    "addr:postcode":"3996",
    "addr:street":"Bass Hwy",
    "iso:country":"AU",
    "sg:address":"Bass Hwy",
    "sg:city":"Inverloch",
    "sg:classifiers":[
        {
            "category":"Professional",
            "subcategory":"Engineering",
            "type":"Services"
        }
    ],
    "sg:phone":"+61 417 533 823",
    "sg:postcode":"3996",
    "sg:province":"VIC",
    "sg:tags":[
        "engineer"
    ],
    "wof:name":"South Gippsland Machinery Industries",
    "wof:placetype":"venue"
},
  "geometry": {"coordinates":[145.719864,-38.627316],"type":"Point"}
}