{
  "type": "Feature",
  "properties": {
    "addr:full":"17 Beonaddy Rd Wanneroo WA 6065",
    "addr:housenumber":"17",
    "addr:postcode":"6065",
    "addr:street":"Beonaddy Rd",
    "iso:country":"AU",
    "sg:address":"17 Beonaddy Rd",
    "sg:city":"Wanneroo",
    "sg:classifiers":[
        {
            "category":"Home & Garden",
            "subcategory":"Building Materials",
            "type":"Retail Goods"
        }
    ],
    "sg:phone":"+61 8 9407 5321",
    "sg:postcode":"6065",
    "sg:province":"WA",
    "sg:tags":[
        "gate"
    ],
    "wof:name":"Coastal Gates",
    "wof:placetype":"venue"
},
  "geometry": {"coordinates":[115.803771973,-31.7504901886],"type":"Point"}
}