{
  "type": "Feature",
  "properties": {
    "addr:full":"2 Weecoon St Eden NSW 2551",
    "addr:housenumber":"2",
    "addr:postcode":"2551",
    "addr:street":"Weecoon St",
    "iso:country":"AU",
    "sg:address":"2 Weecoon St",
    "sg:city":"Eden",
    "sg:classifiers":[
        {
            "category":"Wholesale",
            "subcategory":"Seafood",
            "type":"Manufacturing & Wholesale Goods"
        }
    ],
    "sg:phone":"+61 2 6496 3636",
    "sg:postcode":"2551",
    "sg:province":"NSW",
    "sg:tags":[
        "fish"
    ],
    "wof:name":"Mantons Fresh Fish Supply",
    "wof:placetype":"venue"
},
  "geometry": {"coordinates":[149.91342163100001,-37.0716247559],"type":"Point"}
}