{
  "type": "Feature",
  "properties": {
    "iso:country":"AU",
    "sg:address":"L1, 355 Sussex St",
    "sg:city":"Sydney",
    "sg:classifiers":[
        {
            "category":"Arena",
            "subcategory":"Sports Club",
            "type":"Entertainment"
        }
    ],
    "sg:phone":"+61 2 9264 1999",
    "sg:postcode":"2000",
    "sg:province":"NSW",
    "sg:tags":[
        "defence",
        "supply",
        "self",
        "instruction",
        "martial art"
    ],
    "wof:name":"International Wing Chun (Kung Fu) Academy",
    "wof:placetype":"venue"
},
  "geometry": {"coordinates":[151.20440673799999,-33.8763656616],"type":"Point"}
}