{
  "type": "Feature",
  "properties": {
    "addr:full":"61 McBride Ave Wonthaggi VIC 3995",
    "addr:housenumber":"61",
    "addr:postcode":"3995",
    "addr:street":"Mcbride Ave",
    "iso:country":"AU",
    "sg:address":"61 McBride Ave",
    "sg:city":"Wonthaggi",
    "sg:classifiers":[
        {
            "category":"Building & Trades",
            "subcategory":"Locksmith",
            "type":"Services"
        }
    ],
    "sg:phone":"+61 3 5672 4774",
    "sg:postcode":"3995",
    "sg:province":"VIC",
    "sg:tags":[
        "strongroom",
        "safe",
        "door"
    ],
    "wof:name":"Raneye Systems",
    "wof:placetype":"venue"
},
  "geometry": {"coordinates":[145.59144599999999,-38.606831],"type":"Point"}
}