{
  "type": "Feature",
  "properties": {
    "addr:full":"117 Cardigan St Carlton VIC 3053",
    "addr:housenumber":"117",
    "addr:postcode":"3053",
    "addr:street":"Cardigan St",
    "iso:country":"AU",
    "sg:address":"117 Cardigan St",
    "sg:city":"Carlton",
    "sg:classifiers":[
        {
            "category":"Wholesale",
            "subcategory":"Photographic Equipment",
            "type":"Manufacturing & Wholesale Goods"
        }
    ],
    "sg:phone":"+61 1300 130 370",
    "sg:postcode":"3053",
    "sg:province":"VIC",
    "sg:tags":[
        "wholesaler",
        "mfrs",
        "supply"
    ],
    "wof:name":"Dragon Image",
    "wof:placetype":"venue"
},
  "geometry": {"coordinates":[144.96470642099999,-37.8039016724],"type":"Point"}
}