{
  "type": "Feature",
  "properties": {
    "addr:full":"339 Blaxland Rd Ryde NSW 2112",
    "addr:housenumber":"339",
    "addr:postcode":"2112",
    "addr:street":"Blaxland Rd",
    "iso:country":"AU",
    "sg:address":"339 Blaxland Rd",
    "sg:city":"Ryde",
    "sg:classifiers":[
        {
            "category":"Professional",
            "subcategory":"Computer Services",
            "type":"Services"
        }
    ],
    "sg:phone":"+61 2 9808 6328",
    "sg:postcode":"2112",
    "sg:province":"NSW",
    "sg:tags":[
        "consultant",
        "system"
    ],
    "wof:name":"Aussec",
    "wof:placetype":"venue"
},
  "geometry": {"coordinates":[151.10151672399999,-33.8026771545],"type":"Point"}
}