{
  "type": "Feature",
  "properties": {
    "addr:full":"9 Church St Gordonvale QLD 4865",
    "addr:housenumber":"9",
    "addr:postcode":"4865",
    "addr:street":"Church St",
    "iso:country":"AU",
    "sg:address":"9 Church St",
    "sg:city":"Gordonvale",
    "sg:classifiers":[
        {
            "category":"Wholesale",
            "subcategory":"Farm Supplies",
            "type":"Manufacturing & Wholesale Goods"
        }
    ],
    "sg:phone":"+61 7 4056 1179",
    "sg:postcode":"4865",
    "sg:province":"QLD",
    "sg:tags":[
        "equipment"
    ],
    "wof:name":"F.N.Q.Tractors Pty Ltd",
    "wof:placetype":"venue"
},
  "geometry": {"coordinates":[145.786834717,-17.0944252014],"type":"Point"}
}