{
  "type": "Feature",
  "properties": {
    "addr:full":"Stewart St Berrigan NSW 2712",
    "addr:postcode":"2712",
    "addr:street":"Stewart St",
    "iso:country":"AU",
    "sg:address":"Stewart St",
    "sg:city":"Berrigan",
    "sg:classifiers":[
        {
            "category":"Travel",
            "subcategory":"Hotels & Motels",
            "type":"Entertainment"
        }
    ],
    "sg:phone":"+61 3 5885 2229",
    "sg:postcode":"2712",
    "sg:province":"NSW",
    "wof:name":"Berrigan Golf & Bowling Club Ltd",
    "wof:placetype":"venue"
},
  "geometry": {"coordinates":[145.80897522000001,-35.6594619751],"type":"Point"}
}