{
  "type": "Feature",
  "properties": {
    "addr:full":"127 Anderson St Webberton WA 6530",
    "addr:housenumber":"127",
    "addr:postcode":"6530",
    "addr:street":"Anderson St",
    "iso:country":"AU",
    "sg:address":"127 Anderson St",
    "sg:city":"Webberton",
    "sg:classifiers":[
        {
            "category":"Sports & Exercise",
            "subcategory":"Playing Field",
            "type":"Entertainment"
        }
    ],
    "sg:phone":"+61 8 9964 1088",
    "sg:postcode":"6530",
    "sg:province":"WA",
    "sg:tags":[
        "net",
        "fishing"
    ],
    "wof:name":"Petersen Craypots",
    "wof:placetype":"venue"
},
  "geometry": {"coordinates":[114.633171081,-28.7472019196],"type":"Point"}
}