{
  "type": "Feature",
  "properties": {
    "addr:full":"Mckinney House 18 Duggan St Toowoomba QLD 4350",
    "addr:housenumber":"18",
    "addr:postcode":"4350",
    "addr:street":"Duggan St",
    "iso:country":"AU",
    "sg:address":"Mckinney House 18 Duggan St",
    "sg:city":"Toowoomba",
    "sg:classifiers":[
        {
            "category":"Shopping",
            "subcategory":"Beauty & Cosmetics",
            "type":"Retail Goods"
        }
    ],
    "sg:phone":"+61 7 4638 0477",
    "sg:postcode":"4350",
    "sg:province":"QLD",
    "sg:tags":[
        "equipment",
        "salon",
        "supply"
    ],
    "wof:name":"Cj's Wholesalers",
    "wof:placetype":"venue"
},
  "geometry": {"coordinates":[151.95202599999999,-27.562897],"type":"Point"}
}