{
  "type": "Feature",
  "properties": {
    "addr:full":"16 Goonan St Tamworth NSW 2340",
    "addr:housenumber":"16",
    "addr:postcode":"2340",
    "addr:street":"Goonan St",
    "iso:country":"AU",
    "sg:address":"16 Goonan St",
    "sg:city":"Tamworth",
    "sg:classifiers":[
        {
            "category":"Retail",
            "subcategory":"Auto Repair",
            "type":"Services"
        }
    ],
    "sg:phone":"+61 2 6765 9346",
    "sg:postcode":"2340",
    "sg:province":"NSW",
    "sg:tags":[
        "beater",
        "painter",
        "panel"
    ],
    "wof:name":"Barnes Smash Repairs",
    "wof:placetype":"venue"
},
  "geometry": {"coordinates":[150.89500427199999,-31.0927696228],"type":"Point"}
}