{
  "type": "Feature",
  "properties": {
    "iso:country":"AU",
    "sg:address":"Bowling Green La",
    "sg:city":"Avalon",
    "sg:classifiers":[
        {
            "category":"Education",
            "subcategory":"University",
            "type":"Public Place"
        }
    ],
    "sg:phone":"+61 2 9973 2431",
    "sg:postcode":"2107",
    "sg:province":"NSW",
    "sg:tags":[
        "educational",
        "organisation",
        "cultural"
    ],
    "wof:name":"Guides New South Wales",
    "wof:placetype":"venue"
},
  "geometry": {"coordinates":[151.32835388199999,-33.6349487305],"type":"Point"}
}