{
  "type": "Feature",
  "properties": {
    "addr:full":"21 Enterprise Ave Berwick VIC 3806",
    "addr:housenumber":"21",
    "addr:postcode":"3806",
    "addr:street":"Enterprise Ave",
    "iso:country":"AU",
    "sg:address":"21 Enterprise Ave",
    "sg:city":"Berwick",
    "sg:classifiers":[
        {
            "category":"Fast Food",
            "type":"Food & Drink"
        }
    ],
    "sg:phone":"+61 3 9796 2447",
    "sg:postcode":"3806",
    "sg:province":"VIC",
    "sg:tags":[
        "away",
        "take"
    ],
    "wof:name":"Chubbys",
    "wof:placetype":"venue"
},
  "geometry": {"coordinates":[145.34036254899999,-38.0371322632],"type":"Point"}
}