{
  "type": "Feature",
  "properties": {
    "iso:country":"AU",
    "sg:address":"PO Box 1017",
    "sg:city":"Richmond North",
    "sg:classifiers":[
        {
            "category":"Communications",
            "type":"Services"
        }
    ],
    "sg:phone":"+61 3 9428 9156",
    "sg:postcode":"3121",
    "sg:province":"VIC",
    "sg:tags":[
        "translation"
    ],
    "wof:name":"Asia Technical Translation Pty Ltd",
    "wof:placetype":"venue"
},
  "geometry": {"coordinates":[145.00819397000001,-37.8212509155],"type":"Point"}
}