{
  "type": "Feature",
  "properties": {
    "addr:full":"409 Victoria St Wetherill Park NSW 2164",
    "addr:housenumber":"409",
    "addr:postcode":"2164",
    "addr:street":"Victoria St",
    "iso:country":"AU",
    "sg:address":"409 Victoria St",
    "sg:city":"Wetherill Park",
    "sg:classifiers":[
        {
            "category":"Home & Garden",
            "subcategory":"Building Materials",
            "type":"Retail Goods"
        }
    ],
    "sg:phone":"+61 2 8787 5490",
    "sg:postcode":"2164",
    "sg:province":"NSW",
    "sg:tags":[
        "supply"
    ],
    "wof:name":"Hudson Home Improvements",
    "wof:placetype":"venue"
},
  "geometry": {"coordinates":[150.900299072,-33.8456993103],"type":"Point"}
}