{
  "type": "Feature",
  "properties": {
    "addr:full":"110 Slater Pde Keilor East VIC 3033",
    "addr:housenumber":"110",
    "addr:postcode":"3033",
    "addr:street":"Slater Pde",
    "iso:country":"AU",
    "sg:address":"110 Slater Pde",
    "sg:city":"Keilor East",
    "sg:classifiers":[
        {
            "category":"Utilities",
            "subcategory":"Fuel Oil & Lpg",
            "type":"Services"
        }
    ],
    "sg:phone":"+61 404 689 107",
    "sg:postcode":"3033",
    "sg:province":"VIC",
    "sg:tags":[
        "merchant"
    ],
    "wof:name":"Fire Brix",
    "wof:placetype":"venue"
},
  "geometry": {"coordinates":[144.86058,-37.730946],"type":"Point"}
}