{
  "type": "Feature",
  "properties": {
    "addr:full":"43 Swan Rd Edensor Park NSW 2176",
    "addr:housenumber":"43",
    "addr:postcode":"2176",
    "addr:street":"Swan Rd",
    "iso:country":"AU",
    "sg:address":"43 Swan Rd",
    "sg:city":"Edensor Park",
    "sg:classifiers":[
        {
            "category":"Home & Garden",
            "subcategory":"Building Materials",
            "type":"Retail Goods"
        }
    ],
    "sg:phone":"+61 411 727 561",
    "sg:postcode":"2176",
    "sg:province":"NSW",
    "sg:tags":[
        "restoration",
        "supply"
    ],
    "wof:name":"Federation Tuck-Pointing",
    "wof:placetype":"venue"
},
  "geometry": {"coordinates":[150.877044678,-33.8802375793],"type":"Point"}
}