{
  "type": "Feature",
  "properties": {
    "addr:full":"Flinders St Jabiru NT 0886",
    "addr:postcode":"nt 0886",
    "addr:street":"Flinders St",
    "iso:country":"AU",
    "sg:address":"Flinders St",
    "sg:city":"Jabiru",
    "sg:classifiers":[
        {
            "category":"Retail",
            "subcategory":"Event Space",
            "type":"Services"
        }
    ],
    "sg:phone":"+61 8 8979 9000",
    "sg:postcode":"0886",
    "sg:province":"NT",
    "sg:tags":[
        "function",
        "organiser"
    ],
    "wof:name":"Gagudju Crocodile Holiday Inn",
    "wof:placetype":"venue"
},
  "geometry": {"coordinates":[132.83161899999999,-12.671146],"type":"Point"}
}