{
  "type": "Feature",
  "properties": {
    "iso:country":"AU",
    "sg:address":"5/ 16 Hertford St",
    "sg:city":"Upper Mt Gravatt",
    "sg:classifiers":[
        {
            "category":"Utilities",
            "subcategory":"Refuse",
            "type":"Services"
        }
    ],
    "sg:phone":"+61 7 3216 8827",
    "sg:postcode":"4122",
    "sg:province":"QLD",
    "sg:tags":[
        "disposal",
        "reduction",
        "waste"
    ],
    "wof:name":"Heslin Resources Pty Ltd",
    "wof:placetype":"venue"
},
  "geometry": {"coordinates":[153.07992553700001,-27.5509586334],"type":"Point"}
}