{
  "type": "Feature",
  "properties": {
    "iso:country":"AU",
    "sg:address":"Shop 26",
    "sg:city":", Mountain Gate Shopng Cntr Ferntree Gully",
    "sg:classifiers":[
        {
            "category":"Health Services",
            "subcategory":"Doctor",
            "type":"Services"
        }
    ],
    "sg:phone":"+61 3 9758 4166",
    "sg:postcode":"3156",
    "sg:province":"VIC",
    "sg:tags":[
        "medical",
        "practitioner"
    ],
    "wof:name":"Mayne Medical Centres",
    "wof:placetype":"venue"
},
  "geometry": {"coordinates":[145.276245117,-37.88722229],"type":"Point"}
}