{
  "type": "Feature",
  "properties": {
    "addr:full":"45 Fitzroy St St Kilda VIC 3182",
    "addr:housenumber":"45",
    "addr:postcode":"3182",
    "addr:street":"Fitzroy St",
    "iso:country":"AU",
    "sg:address":"45 Fitzroy St",
    "sg:city":"St Kilda",
    "sg:classifiers":[
        {
            "category":"Food & Beverages",
            "subcategory":"Liquor & Beverages",
            "type":"Retail Goods"
        }
    ],
    "sg:phone":"+61 3 9534 5926",
    "sg:postcode":"3182",
    "sg:province":"VIC",
    "sg:tags":[
        "store"
    ],
    "wof:name":"St Kilda Cellars",
    "wof:placetype":"venue"
},
  "geometry": {"coordinates":[144.974365234,-37.86170578],"type":"Point"}
}