{
  "type": "Feature",
  "properties": {
    "addr:full":"PO Box 419 Bundoora VIC 3083",
    "addr:postcode":"3083",
    "iso:country":"AU",
    "sg:address":"PO Box 419",
    "sg:city":"Bundoora",
    "sg:classifiers":[
        {
            "category":"Professional",
            "subcategory":"Detective & Security Services",
            "type":"Services"
        }
    ],
    "sg:phone":"+61 3 9467 4300",
    "sg:postcode":"3083",
    "sg:province":"VIC",
    "sg:tags":[
        "guard",
        "patrol"
    ],
    "wof:name":"R & R Security Australia Pty Ltd",
    "wof:placetype":"venue"
},
  "geometry": {"coordinates":[145.06968689000001,-37.7010803223],"type":"Point"}
}