{
  "type": "Feature",
  "properties": {
    "addr:full":"2a Morgan Rd Belrose NSW 2085",
    "addr:housenumber":"2a",
    "addr:postcode":"2085",
    "addr:street":"Morgan Rd",
    "iso:country":"AU",
    "sg:address":"2a Morgan Rd",
    "sg:city":"Belrose",
    "sg:classifiers":[
        {
            "category":"Education",
            "subcategory":"Kindergarten",
            "type":"Public Place"
        }
    ],
    "sg:phone":"+61 2 9452 2510",
    "sg:postcode":"2085",
    "sg:province":"NSW",
    "sg:tags":[
        "pre-schools"
    ],
    "wof:name":"The Forest Pre-School Kindergarten",
    "wof:placetype":"venue"
},
  "geometry": {"coordinates":[151.217727661,-33.7221641541],"type":"Point"}
}