{
  "type": "Feature",
  "properties": {
    "iso:country":"AU",
    "sg:address":"PO Box 1369",
    "sg:city":"Osborne Park",
    "sg:classifiers":[
        {
            "category":"Building & Trades",
            "subcategory":"Construction",
            "type":"Services"
        }
    ],
    "sg:phone":"+61 1300 307 911",
    "sg:postcode":"6017",
    "sg:province":"WA",
    "sg:tags":[
        "home",
        "air conditioning"
    ],
    "wof:name":"Apollo Air Conditioning",
    "wof:placetype":"venue"
},
  "geometry": {"coordinates":[115.817710877,-31.9038391113],"type":"Point"}
}