{
  "type": "Feature",
  "properties": {
    "iso:country":"AU",
    "sg:address":"Shop 2/ 463 Church St",
    "sg:city":"North Parramatta",
    "sg:classifiers":[
        {
            "category":"Fast Food",
            "type":"Food & Drink"
        }
    ],
    "sg:phone":"+61 2 9890 5898",
    "sg:postcode":"2151",
    "sg:province":"NSW",
    "sg:tags":[
        "away",
        "take"
    ],
    "wof:name":"Shiraz Restaurant",
    "wof:placetype":"venue"
},
  "geometry": {"coordinates":[151.005615234,-33.803691864],"type":"Point"}
}