{
  "type": "Feature",
  "properties": {
    "iso:country":"AU",
    "sg:address":"Canty St",
    "sg:city":"Narooma",
    "sg:classifiers":[
        {
            "category":"Organizations",
            "subcategory":"Community Association",
            "type":"Services"
        }
    ],
    "sg:phone":"+61 2 4476 4228",
    "sg:postcode":"2546",
    "sg:province":"NSW",
    "sg:tags":[
        "organisation",
        "family",
        "welfare"
    ],
    "wof:name":"St Vincent De Paul Society",
    "wof:placetype":"venue"
},
  "geometry": {"coordinates":[150.13186645499999,-36.2192955017],"type":"Point"}
}