{
  "type": "Feature",
  "properties": {
    "addr:full":"613 Stanley St Woolloongabba QLD 4102",
    "addr:housenumber":"613",
    "addr:postcode":"4102",
    "addr:street":"Stanley St",
    "iso:country":"AU",
    "sg:address":"613 Stanley St",
    "sg:city":"Woolloongabba",
    "sg:classifiers":[
        {
            "category":"Shopping",
            "subcategory":"Computers & Home Electronics",
            "type":"Retail Goods"
        }
    ],
    "sg:phone":"+61 7 3891 1511",
    "sg:postcode":"4102",
    "sg:province":"QLD",
    "sg:tags":[
        "equipment",
        "multimedia"
    ],
    "wof:name":"Harrys Collar",
    "wof:placetype":"venue"
},
  "geometry": {"coordinates":[153.029464722,-27.485742569],"type":"Point"}
}