{
  "type": "Feature",
  "properties": {
    "iso:country":"AU",
    "sg:address":"Unit 2, 17 Fleming St",
    "sg:city":"Aitkenvale",
    "sg:classifiers":[
        {
            "category":"Professional",
            "type":"Services"
        }
    ],
    "sg:phone":"+61 7 4775 3838",
    "sg:postcode":"4814",
    "sg:province":"QLD",
    "sg:tags":[
        "shop",
        "fitting"
    ],
    "wof:name":"Craftwood Carpentry",
    "wof:placetype":"venue"
},
  "geometry": {"coordinates":[146.768677,-19.293449],"type":"Point"}
}