{
  "type": "Feature",
  "properties": {
    "addr:full":"Suite 34, 207 Currumburra Rd Ashmore QLD 4214",
    "addr:housenumber":"207",
    "addr:postcode":"4214",
    "addr:street":"Currumburra Rd",
    "iso:country":"AU",
    "sg:address":"Suite 34, 207 Currumburra Rd",
    "sg:city":"Ashmore",
    "sg:classifiers":[
        {
            "category":"Professional",
            "subcategory":"Business Services",
            "type":"Services"
        }
    ],
    "sg:phone":"+61 7 5539 5388",
    "sg:postcode":"4214",
    "sg:province":"QLD",
    "sg:tags":[
        "management",
        "event"
    ],
    "wof:name":"Sports Corp Elite",
    "wof:placetype":"venue"
},
  "geometry": {"coordinates":[153.381225586,-27.9784183502],"type":"Point"}
}