{
  "type": "Feature",
  "properties": {
    "iso:country":"AU",
    "sg:address":"Lot10/ 26 Lake St",
    "sg:city":"Varsity Lakes",
    "sg:classifiers":[
        {
            "category":"Professional",
            "subcategory":"Business Services",
            "type":"Services"
        }
    ],
    "sg:phone":"+61 7 5578 8736",
    "sg:postcode":"4226",
    "sg:province":"QLD",
    "sg:tags":[
        "drafting"
    ],
    "wof:name":"Network Drafting Services Pty Ltd",
    "wof:placetype":"venue"
},
  "geometry": {"coordinates":[153.415283203,-28.0775642395],"type":"Point"}
}