{
  "type": "Feature",
  "properties": {
    "addr:full":"285 Geelong Rd Footscray VIC 3011",
    "addr:housenumber":"285",
    "addr:postcode":"3011",
    "addr:street":"Geelong Rd",
    "iso:country":"AU",
    "sg:address":"285 Geelong Rd",
    "sg:city":"Footscray",
    "sg:classifiers":[
        {
            "category":"Fast Food",
            "type":"Food & Drink"
        }
    ],
    "sg:phone":"+61 3 9687 8522",
    "sg:postcode":"3011",
    "sg:province":"VIC",
    "sg:tags":[
        "away",
        "take"
    ],
    "wof:name":"Pizza Haven",
    "wof:placetype":"venue"
},
  "geometry": {"coordinates":[144.87974548299999,-37.806022644],"type":"Point"}
}