{
  "type": "Feature",
  "properties": {
    "addr:full":"366 Sydney Rd Brunswick VIC 3056",
    "addr:housenumber":"366",
    "addr:postcode":"3056",
    "addr:street":"Sydney Rd",
    "iso:country":"AU",
    "sg:address":"366 Sydney Rd",
    "sg:city":"Brunswick",
    "sg:classifiers":[
        {
            "category":"Professional",
            "subcategory":"Art Services",
            "type":"Services"
        }
    ],
    "sg:phone":"+61 3 9387 2866",
    "sg:postcode":"3056",
    "sg:province":"VIC",
    "sg:tags":[
        "interior",
        "decorator"
    ],
    "wof:name":"Sortino",
    "wof:placetype":"venue"
},
  "geometry": {"coordinates":[144.96188354500001,-37.7693977356],"type":"Point"}
}