{
  "type": "Feature",
  "properties": {
    "addr:full":"Shop 9 Southside Village 157 Swanport Rd Murray Bridge SA 5253",
    "addr:housenumber":"shop 9;157",
    "addr:postcode":"5253",
    "addr:street":"Southside Village;Swanport Rd",
    "iso:country":"AU",
    "sg:address":"Shop 9 Southside Village 157 Swanport Rd",
    "sg:city":"Murray Bridge",
    "sg:classifiers":[
        {
            "category":"Personal",
            "subcategory":"Beauty Salon",
            "type":"Services"
        }
    ],
    "sg:phone":"+61 8 8532 1355",
    "sg:postcode":"5253",
    "sg:province":"SA",
    "sg:tags":[
        "hairdresser"
    ],
    "wof:name":"E-Clipz Hair & Beauty",
    "wof:placetype":"venue"
},
  "geometry": {"coordinates":[139.282073975,-35.1344680786],"type":"Point"}
}