{
  "type": "Feature",
  "properties": {
    "iso:country":"AU",
    "sg:address":"95 Middletons Rd North",
    "sg:city":"Labertouche",
    "sg:classifiers":[
        {
            "category":"Farming",
            "subcategory":"Farm",
            "type":"Manufacturing & Wholesale Goods"
        }
    ],
    "sg:phone":"+61 3 5628 7553",
    "sg:postcode":"3816",
    "sg:province":"VIC",
    "sg:tags":[
        "farmer"
    ],
    "wof:name":"Sgarbossa P L",
    "wof:placetype":"venue"
},
  "geometry": {"coordinates":[145.766953,-38.036228],"type":"Point"}
}