{
  "type": "Feature",
  "properties": {
    "iso:country":"AU",
    "sg:address":"GPO Box 2220",
    "sg:city":"Canberra City",
    "sg:classifiers":[
        {
            "category":"Personal",
            "type":"Services"
        }
    ],
    "sg:phone":"+61 2 6103 0959",
    "sg:postcode":"2601",
    "sg:province":"ACT",
    "sg:tags":[
        "career",
        "counselling"
    ],
    "wof:name":"Capital Coaching Pty Ltd",
    "wof:placetype":"venue"
},
  "geometry": {"coordinates":[149.13090515100001,-35.2801513672],"type":"Point"}
}