{
  "type": "Feature",
  "properties": {
    "addr:full":"52-58 Main St Kapunda SA 5373",
    "addr:housenumber":"52-58",
    "addr:postcode":"5373",
    "addr:street":"Main St",
    "iso:country":"AU",
    "sg:address":"52-58 Main St",
    "sg:city":"Kapunda",
    "sg:classifiers":[
        {
            "category":"Food & Beverages",
            "subcategory":"Supermarket",
            "type":"Retail Goods"
        }
    ],
    "sg:phone":"+61 8 8566 2003",
    "sg:postcode":"5373",
    "sg:province":"SA",
    "sg:tags":[
        "grocery",
        "store"
    ],
    "wof:name":"IGA Everyday",
    "wof:placetype":"venue"
},
  "geometry": {"coordinates":[138.916625977,-34.3393936157],"type":"Point"}
}