{
  "type": "Feature",
  "properties": {
    "addr:full":"62 Piper St Kyneton VIC 3444",
    "addr:housenumber":"62",
    "addr:postcode":"3444",
    "addr:street":"Piper St",
    "iso:country":"AU",
    "sg:address":"62 Piper St",
    "sg:city":"Kyneton",
    "sg:classifiers":[
        {
            "category":"Fast Food",
            "type":"Food & Drink"
        }
    ],
    "sg:phone":"+61 3 5422 7400",
    "sg:postcode":"3444",
    "sg:province":"VIC",
    "sg:tags":[
        "away",
        "take"
    ],
    "wof:name":"Pizza Verde",
    "wof:placetype":"venue"
},
  "geometry": {"coordinates":[144.449417114,-37.2440109253],"type":"Point"}
}