{
  "type": "Feature",
  "properties": {
    "addr:full":"5 Duke St West Launceston TAS 7250",
    "addr:housenumber":"5",
    "addr:postcode":"7250",
    "addr:street":"Duke St West",
    "iso:country":"AU",
    "sg:address":"5 Duke St",
    "sg:city":"West Launceston",
    "sg:classifiers":[
        {
            "category":"Retail",
            "subcategory":"Storage",
            "type":"Services"
        }
    ],
    "sg:phone":"+61 411 433 765",
    "sg:postcode":"7250",
    "sg:province":"TAS",
    "sg:tags":[
        "removal",
        "furniture"
    ],
    "wof:name":"Goodger Carriers",
    "wof:placetype":"venue"
},
  "geometry": {"coordinates":[147.13583374000001,-41.4522209167],"type":"Point"}
}