{
  "type": "Feature",
  "properties": {
    "iso:country":"AU",
    "sg:address":"13 Finsbury Rd",
    "sg:city":"Devon Meadows",
    "sg:classifiers":[
        {
            "category":"Building & Trades",
            "subcategory":"Plumbing",
            "type":"Services"
        }
    ],
    "sg:phone":"+61 418 322 017",
    "sg:postcode":"3977",
    "sg:province":"VIC",
    "sg:tags":[
        "plumber",
        "gasfitters"
    ],
    "wof:name":"Gippsland Plumbing Pty Ltd",
    "wof:placetype":"venue"
},
  "geometry": {"coordinates":[145.314208984,-38.1594238281],"type":"Point"}
}