{
  "type": "Feature",
  "properties": {
    "addr:full":"Shop 3, 60 Archibald St Willagee WA 6156",
    "addr:housenumber":"shop;60",
    "addr:postcode":"6156",
    "addr:street":"Archibald St",
    "iso:country":"AU",
    "sg:address":"Shop 3, 60 Archibald St",
    "sg:city":"Willagee",
    "sg:classifiers":[
        {
            "category":"Health Services",
            "subcategory":"Dentist",
            "type":"Services"
        }
    ],
    "sg:phone":"+61 8 9337 5502",
    "sg:postcode":"6156",
    "sg:province":"WA",
    "wof:name":"Willagee Dental Care",
    "wof:placetype":"venue"
},
  "geometry": {"coordinates":[115.807587,-32.05312],"type":"Point"}
}