{
  "type": "Feature",
  "properties": {
    "addr:full":"37 Bourke St Dubbo NSW 2830",
    "addr:housenumber":"37",
    "addr:postcode":"2830",
    "addr:street":"Bourke St",
    "iso:country":"AU",
    "sg:address":"37 Bourke St",
    "sg:city":"Dubbo",
    "sg:classifiers":[
        {
            "category":"Professional",
            "subcategory":"Employment Agencies",
            "type":"Services"
        }
    ],
    "sg:phone":"+61 13 98 49",
    "sg:postcode":"2830",
    "sg:province":"NSW",
    "sg:tags":[
        "provider",
        "internet"
    ],
    "wof:name":"Elders Telecommunications",
    "wof:placetype":"venue"
},
  "geometry": {"coordinates":[148.61175537099999,-32.2321395874],"type":"Point"}
}