{
  "type": "Feature",
  "properties": {
    "iso:country":"AU",
    "sg:address":"Griffith Base Hospital Noorebar Ave",
    "sg:city":"Griffith",
    "sg:classifiers":[
        {
            "category":"Health Services",
            "subcategory":"Doctor",
            "type":"Services"
        }
    ],
    "sg:phone":"+61 2 6969 5728",
    "sg:postcode":"2680",
    "sg:province":"NSW",
    "sg:tags":[
        "medical",
        "practitioner"
    ],
    "wof:name":"Griffith Pathology Laboratory SWPS",
    "wof:placetype":"venue"
},
  "geometry": {"coordinates":[146.045029,-34.283146],"type":"Point"}
}