{
  "type": "Feature",
  "properties": {
    "iso:country":"AU",
    "sg:address":"18 Patterson St",
    "sg:city":"Wongan Hills",
    "sg:classifiers":[
        {
            "category":"Professional",
            "subcategory":"Management & Consulting",
            "type":"Services"
        }
    ],
    "sg:phone":"+61 8 9671 1560",
    "sg:postcode":"6603",
    "sg:province":"WA",
    "sg:tags":[
        "consultant",
        "business"
    ],
    "wof:name":"Agrow Consulting",
    "wof:placetype":"venue"
},
  "geometry": {"coordinates":[116.718788147,-30.888212204],"type":"Point"}
}