{
  "type": "Feature",
  "properties": {
    "iso:country":"AU",
    "sg:address":"9 Fourth Ave",
    "sg:city":"Glenelg East",
    "sg:classifiers":[
        {
            "category":"Building & Trades",
            "subcategory":"Cleaning & Sanitation",
            "type":"Services"
        }
    ],
    "sg:phone":"+61 415 977 240",
    "sg:postcode":"5045",
    "sg:province":"SA",
    "sg:tags":[
        "commercial",
        "maintenance"
    ],
    "wof:name":"Custom Built Steel Industries Pty Ltd",
    "wof:placetype":"venue"
},
  "geometry": {"coordinates":[138.52539100000001,-34.978413],"type":"Point"}
}