{
  "type": "Feature",
  "properties": {
    "addr:full":"Shp 9/ 53 The Crescent Midland WA 6056",
    "addr:housenumber":"/ 53",
    "addr:postcode":"6056",
    "addr:street":"The Crescent",
    "iso:country":"AU",
    "sg:address":"Shp 9/ 53 The Crescent",
    "sg:city":"Midland",
    "sg:classifiers":[
        {
            "category":"Personal",
            "subcategory":"Beauty Salon",
            "type":"Services"
        }
    ],
    "sg:phone":"+61 8 9274 7385",
    "sg:postcode":"6056",
    "sg:province":"WA",
    "sg:tags":[
        "hairdresser"
    ],
    "wof:name":"Bevington's Hairdressing",
    "wof:placetype":"venue"
},
  "geometry": {"coordinates":[116.006813049,-31.8887901306],"type":"Point"}
}