{
  "type": "Feature",
  "properties": {
    "iso:country":"AU",
    "sg:address":"2 Thompson St",
    "sg:city":"Frankston",
    "sg:classifiers":[
        {
            "category":"Personal",
            "subcategory":"Beauty Salon",
            "type":"Services"
        }
    ],
    "sg:phone":"+61 3 9783 8433",
    "sg:postcode":"3199",
    "sg:province":"VIC",
    "sg:tags":[
        "hairdresser"
    ],
    "wof:name":"Hair Razor",
    "wof:placetype":"venue"
},
  "geometry": {"coordinates":[145.11329650900001,-37.9187507629],"type":"Point"}
}