{
  "type": "Feature",
  "properties": {
    "addr:full":"Suite 7, 334 Highbury Rd Mt Waverley VIC 3149",
    "addr:housenumber":"334",
    "addr:postcode":"3149",
    "addr:street":"Highbury Rd",
    "iso:country":"AU",
    "sg:address":"Suite 7, 334 Highbury Rd",
    "sg:city":"Mt Waverley",
    "sg:classifiers":[
        {
            "category":"Professional",
            "subcategory":"Accounting & Tax Preparation",
            "type":"Services"
        }
    ],
    "sg:phone":"+61 3 9802 5800",
    "sg:postcode":"3149",
    "sg:province":"VIC",
    "sg:tags":[
        "consultant",
        "taxation"
    ],
    "wof:name":"Harmer Business Development",
    "wof:placetype":"venue"
},
  "geometry": {"coordinates":[145.13203430199999,-37.8577346802],"type":"Point"}
}