{
  "type": "Feature",
  "properties": {
    "addr:full":"PO Box 1808 Fremantle WA 6959",
    "addr:postcode":"6959",
    "iso:country":"AU",
    "sg:address":"PO Box 1808",
    "sg:city":"Fremantle",
    "sg:classifiers":[
        {
            "category":"Shopping",
            "subcategory":"Party Supplies",
            "type":"Retail Goods"
        }
    ],
    "sg:phone":"+61 8 9339 1852",
    "sg:postcode":"6959",
    "sg:province":"WA",
    "wof:name":"PartyZone",
    "wof:placetype":"venue"
},
  "geometry": {"coordinates":[115.974151611,-32.0679168701],"type":"Point"}
}