{
  "type": "Feature",
  "properties": {
    "addr:full":"Brigooda Rd Proston QLD 4613",
    "addr:postcode":"4613",
    "addr:street":"Brigooda Rd",
    "iso:country":"AU",
    "sg:address":"Brigooda Rd",
    "sg:city":"Proston",
    "sg:classifiers":[
        {
            "category":"Health Services",
            "subcategory":"Doctor",
            "type":"Services"
        }
    ],
    "sg:phone":"+61 7 4168 9288",
    "sg:postcode":"4613",
    "sg:province":"QLD",
    "sg:tags":[
        "medical",
        "practitioner"
    ],
    "wof:name":"Proston Clinic",
    "wof:placetype":"venue"
},
  "geometry": {"coordinates":[151.60093689000001,-26.1606407166],"type":"Point"}
}