{
  "type": "Feature",
  "properties": {
    "addr:full":"18 Edith St Edithburgh SA 5583",
    "addr:housenumber":"18",
    "addr:postcode":"5583",
    "addr:street":"Edith St",
    "iso:country":"AU",
    "sg:address":"18 Edith St",
    "sg:city":"Edithburgh",
    "sg:classifiers":[
        {
            "category":"Government",
            "subcategory":"Post Office",
            "type":"Public Place"
        }
    ],
    "sg:phone":"+61 8 8852 6295",
    "sg:postcode":"5583",
    "sg:province":"SA",
    "sg:tags":[
        "postal"
    ],
    "wof:name":"Australia Post",
    "wof:placetype":"venue"
},
  "geometry": {"coordinates":[137.74551391599999,-35.0846672058],"type":"Point"}
}