{
  "type": "Feature",
  "properties": {
    "addr:full":"147 Faulkner St Armidale NSW 2350",
    "addr:housenumber":"147",
    "addr:postcode":"2350",
    "addr:street":"Faulkner St",
    "iso:country":"AU",
    "sg:address":"147 Faulkner St",
    "sg:city":"Armidale",
    "sg:classifiers":[
        {
            "category":"Education",
            "subcategory":"School",
            "type":"Public Place"
        }
    ],
    "sg:phone":"+61 2 6776 0200",
    "sg:postcode":"2350",
    "sg:province":"NSW",
    "sg:tags":[
        "teaching",
        "aid"
    ],
    "wof:name":"New Horizons Educational Computing Services",
    "wof:placetype":"venue"
},
  "geometry": {"coordinates":[151.66604614299999,-30.5171470642],"type":"Point"}
}