{
  "type": "Feature",
  "properties": {
    "iso:country":"AU",
    "sg:address":"220 Melbourne St",
    "sg:city":"South Brisbane",
    "sg:classifiers":[
        {
            "category":"Real Estate",
            "subcategory":"Developer",
            "type":"Services"
        }
    ],
    "sg:phone":"+61 7 3846 2891",
    "sg:postcode":"4101",
    "sg:province":"QLD",
    "sg:tags":[
        "development"
    ],
    "wof:name":"Newco Holdings Pty Ltd",
    "wof:placetype":"venue"
},
  "geometry": {"coordinates":[153.013473511,-27.4768238068],"type":"Point"}
}