{
  "type": "Feature",
  "properties": {
    "addr:full":"38 Demaine Ave Bexley North NSW 2207",
    "addr:housenumber":"38",
    "addr:postcode":"2207",
    "addr:street":"Demaine Ave",
    "iso:country":"AU",
    "sg:address":"38 Demaine Ave",
    "sg:city":"Bexley North",
    "sg:classifiers":[
        {
            "category":"Retail",
            "subcategory":"Auto Repair",
            "type":"Services"
        }
    ],
    "sg:phone":"+61 405 434 814",
    "sg:postcode":"2207",
    "sg:province":"NSW",
    "sg:tags":[
        "beater",
        "painter",
        "panel"
    ],
    "wof:name":"Amazing Mobile Paint & Panels",
    "wof:placetype":"venue"
},
  "geometry": {"coordinates":[151.11123699999999,-33.939362],"type":"Point"}
}