{
  "type": "Feature",
  "properties": {
    "addr:full":"Shop 3/ Roma Arcade Agnes St Rosebery TAS 7470",
    "addr:housenumber":"shop 3 / roma",
    "addr:postcode":"7470",
    "addr:street":"Agnes St",
    "iso:country":"AU",
    "sg:address":"Shop 3/ Roma Arcade Agnes St",
    "sg:city":"Rosebery",
    "sg:classifiers":[
        {
            "category":"Professional",
            "subcategory":"Detective & Security Services",
            "type":"Services"
        }
    ],
    "sg:phone":"+61 3 6473 1500",
    "sg:postcode":"7470",
    "sg:province":"TAS",
    "sg:tags":[
        "guard",
        "patrol"
    ],
    "wof:name":"West Coast Security Services Pty Ltd",
    "wof:placetype":"venue"
},
  "geometry": {"coordinates":[145.53953552199999,-41.7795791626],"type":"Point"}
}