{
  "type": "Feature",
  "properties": {
    "addr:full":"43 Old Barrenjoey Rd Avalon NSW 2107",
    "addr:housenumber":"43",
    "addr:postcode":"2107",
    "addr:street":"Old Barrenjoey Rd",
    "iso:country":"AU",
    "sg:address":"43 Old Barrenjoey Rd",
    "sg:city":"Avalon",
    "sg:classifiers":[
        {
            "category":"Banks & Credit Unions",
            "subcategory":"Bank",
            "type":"Services"
        }
    ],
    "sg:phone":"+61 13 33 30",
    "sg:postcode":"2107",
    "sg:province":"NSW",
    "wof:name":"St.George Bank Limited",
    "wof:placetype":"venue"
},
  "geometry": {"coordinates":[151.32893371599999,-33.6366996765],"type":"Point"}
}