{
  "type": "Feature",
  "properties": {
    "addr:full":"40 Boulder St Malaga WA 6090",
    "addr:housenumber":"40",
    "addr:postcode":"6090",
    "addr:street":"Boulder St",
    "iso:country":"AU",
    "sg:address":"40 Boulder St",
    "sg:city":"Malaga",
    "sg:classifiers":[
        {
            "category":"Manufacturing",
            "subcategory":"Tobacco Products",
            "type":"Manufacturing & Wholesale Goods"
        }
    ],
    "sg:phone":"+61 8 9209 2933",
    "sg:postcode":"6090",
    "sg:province":"WA",
    "sg:tags":[
        "feather",
        "supply"
    ],
    "wof:name":"Challenge Manufacturing Pty Ltd",
    "wof:placetype":"venue"
},
  "geometry": {"coordinates":[115.905258179,-31.8649177551],"type":"Point"}
}