{
  "type": "Feature",
  "properties": {
    "addr:full":"969 Gold Coast Hwy Palm Beach QLD 4221",
    "addr:housenumber":"969",
    "addr:postcode":"4221",
    "addr:street":"Gold Coast Hwy",
    "iso:country":"AU",
    "sg:address":"969 Gold Coast Hwy",
    "sg:city":"Palm Beach",
    "sg:classifiers":[
        {
            "category":"Wholesale",
            "subcategory":"Office Equipment",
            "type":"Manufacturing & Wholesale Goods"
        }
    ],
    "sg:phone":"+61 7 5521 0058",
    "sg:postcode":"4221",
    "sg:province":"QLD",
    "sg:tags":[
        "packaging",
        "consultant"
    ],
    "wof:name":"Pack Creations",
    "wof:placetype":"venue"
},
  "geometry": {"coordinates":[153.47561645499999,-28.125415802],"type":"Point"}
}