{
  "type": "Feature",
  "properties": {
    "addr:full":"250 Missing Link Rd Cygnet TAS 7112",
    "addr:housenumber":"250",
    "addr:postcode":"7112",
    "addr:street":"Missing Link Rd",
    "iso:country":"AU",
    "sg:address":"250 Missing Link Rd",
    "sg:city":"Cygnet",
    "sg:classifiers":[
        {
            "category":"Utilities",
            "subcategory":"Electric",
            "type":"Services"
        }
    ],
    "sg:phone":"+61 418 512 973",
    "sg:postcode":"7112",
    "sg:province":"TAS",
    "sg:tags":[
        "electrical",
        "contractor"
    ],
    "wof:name":"G & D Woolnough Electrical",
    "wof:placetype":"venue"
},
  "geometry": {"coordinates":[147.03562927199999,-43.1678237915],"type":"Point"}
}