{
  "type": "Feature",
  "properties": {
    "iso:country":"AU",
    "sg:address":"470 Cedar Creek Rd",
    "sg:city":"Belli Park",
    "sg:classifiers":[
        {
            "category":"Farming",
            "subcategory":"Nursery",
            "type":"Manufacturing & Wholesale Goods"
        }
    ],
    "sg:phone":"+61 7 5447 0101",
    "sg:postcode":"4562",
    "sg:province":"QLD",
    "wof:name":"Cedar Creek Nursery",
    "wof:placetype":"venue"
},
  "geometry": {"coordinates":[152.83439636200001,-26.5474414825],"type":"Point"}
}