{
  "type": "Feature",
  "properties": {
    "addr:full":"87-93 Lisbon St Fairfield East NSW 2165",
    "addr:housenumber":"87-93",
    "addr:postcode":"2165",
    "addr:street":"Lisbon St",
    "iso:country":"AU",
    "sg:address":"87-93 Lisbon St",
    "sg:city":"Fairfield East",
    "sg:classifiers":[
        {
            "category":"Utilities",
            "subcategory":"Refuse",
            "type":"Services"
        }
    ],
    "sg:phone":"+61 2 9726 5900",
    "sg:postcode":"2165",
    "sg:province":"NSW",
    "sg:tags":[
        "disposal",
        "reduction",
        "waste"
    ],
    "wof:name":"Recyclex Pty Ltd",
    "wof:placetype":"venue"
},
  "geometry": {"coordinates":[150.97457885700001,-33.8705940247],"type":"Point"}
}