{
  "type": "Feature",
  "properties": {
    "iso:country":"AU",
    "sg:address":"133 Main Rd",
    "sg:city":"McLaren Vale",
    "sg:classifiers":[
        {
            "category":"Health Services",
            "subcategory":"Health Practitioner",
            "type":"Services"
        }
    ],
    "sg:phone":"+61 8 8323 8089",
    "sg:postcode":"5171",
    "sg:province":"SA",
    "sg:tags":[
        "hypnotherapy"
    ],
    "wof:name":"Windhilly Counselling Service",
    "wof:placetype":"venue"
},
  "geometry": {"coordinates":[138.53721618599999,-35.2150154114],"type":"Point"}
}