{
  "type": "Feature",
  "properties": {
    "addr:full":"28 Philip Hwy Elizabeth SA 5112",
    "addr:housenumber":"28",
    "addr:postcode":"5112",
    "addr:street":"Philip Hwy",
    "iso:country":"AU",
    "sg:address":"28 Philip Hwy",
    "sg:city":"Elizabeth",
    "sg:classifiers":[
        {
            "category":"Social Services",
            "subcategory":"Child Care",
            "type":"Services"
        }
    ],
    "sg:phone":"+61 8 8252 3711",
    "sg:postcode":"5112",
    "sg:province":"SA",
    "sg:tags":[
        "childbirth"
    ],
    "wof:name":"Community Midwifery Programme",
    "wof:placetype":"venue"
},
  "geometry": {"coordinates":[138.66644287099999,-34.7258224487],"type":"Point"}
}