{
  "type": "Feature",
  "properties": {
    "addr:full":"Barlow Crt Lockridge WA 6054",
    "addr:postcode":"6054",
    "addr:street":"Barlow Crt",
    "iso:country":"AU",
    "sg:address":"Barlow Crt",
    "sg:city":"Lockridge",
    "sg:classifiers":[
        {
            "category":"Education",
            "subcategory":"School",
            "type":"Public Place"
        }
    ],
    "sg:phone":"+61 8 9279 1782",
    "sg:postcode":"6054",
    "sg:province":"WA",
    "sg:tags":[
        "state",
        "except",
        "nsw"
    ],
    "wof:name":"Lockridge Primary School kindergarten",
    "wof:placetype":"venue"
},
  "geometry": {"coordinates":[115.95012664799999,-31.884349823],"type":"Point"}
}