{
  "type": "Feature",
  "properties": {
    "iso:country":"AU",
    "sg:address":"Shp 1/ 16 Bonegilla Rd",
    "sg:city":"Griffith",
    "sg:classifiers":[
        {
            "category":"Retail",
            "subcategory":"Auto Repair",
            "type":"Services"
        }
    ],
    "sg:phone":"+61 2 6962 4015",
    "sg:postcode":"2680",
    "sg:province":"NSW",
    "sg:tags":[
        "engine",
        "reconditioning"
    ],
    "wof:name":"Hirst Heads",
    "wof:placetype":"venue"
},
  "geometry": {"coordinates":[146.05328399999999,-34.290356],"type":"Point"}
}