{
  "type": "Feature",
  "properties": {
    "addr:full":"Shop 4, 92- 96 Boronia Rd Boronia VIC 3155",
    "addr:housenumber":"shop;92 96",
    "addr:postcode":"3155",
    "addr:street":"Boronia Rd",
    "iso:country":"AU",
    "sg:address":"Shop 4, 92- 96 Boronia Rd",
    "sg:city":"Boronia",
    "sg:classifiers":[
        {
            "category":"Personal",
            "subcategory":"Beauty Salon",
            "type":"Services"
        }
    ],
    "sg:phone":"+61 3 9762 8499",
    "sg:postcode":"3155",
    "sg:province":"VIC",
    "sg:tags":[
        "hairdresser"
    ],
    "wof:name":"Tempo Hair Design",
    "wof:placetype":"venue"
},
  "geometry": {"coordinates":[145.287185669,-37.8628540039],"type":"Point"}
}