{
  "type": "Feature",
  "properties": {
    "addr:full":"7 New St Windsor NSW 2756",
    "addr:housenumber":"7",
    "addr:postcode":"2756",
    "addr:street":"New St",
    "iso:country":"AU",
    "sg:address":"7 New St",
    "sg:city":"Windsor",
    "sg:classifiers":[
        {
            "category":"Arts & Performance",
            "subcategory":"Dance",
            "type":"Entertainment"
        }
    ],
    "sg:phone":"+61 2 4577 5389",
    "sg:postcode":"2756",
    "sg:province":"NSW",
    "sg:tags":[
        "theatrical",
        "ballet",
        "tuition"
    ],
    "wof:name":"A. Hawkesbury Ballroom Dance Centre",
    "wof:placetype":"venue"
},
  "geometry": {"coordinates":[150.818084717,-33.6076812744],"type":"Point"}
}