{
  "type": "Feature",
  "properties": {
    "iso:country":"AU",
    "sg:address":"PO Box 51",
    "sg:city":"Toorak",
    "sg:classifiers":[
        {
            "category":"Professional",
            "subcategory":"Management & Consulting",
            "type":"Services"
        }
    ],
    "sg:phone":"+61 3 9827 7997",
    "sg:postcode":"3142",
    "sg:province":"VIC",
    "sg:tags":[
        "consultant"
    ],
    "wof:name":"Roberts Management Concepts Pty Ltd",
    "wof:placetype":"venue"
},
  "geometry": {"coordinates":[145.01136779800001,-37.8367843628],"type":"Point"}
}