{
  "type": "Feature",
  "properties": {
    "iso:country":"AU",
    "sg:address":"93 Hill St",
    "sg:city":"West Hobart",
    "sg:classifiers":[
        {
            "category":"Health Services",
            "subcategory":"Health Practitioner",
            "type":"Services"
        }
    ],
    "sg:phone":"+61 3 6234 5143",
    "sg:postcode":"7000",
    "sg:province":"TAS",
    "sg:tags":[
        "psychologist"
    ],
    "wof:name":"Hill Street Psychology",
    "wof:placetype":"venue"
},
  "geometry": {"coordinates":[147.312103272,-42.8802185059],"type":"Point"}
}