{
  "type": "Feature",
  "properties": {
    "addr:full":"2/ 56 Burrows St Bowen Hills QLD 4006",
    "addr:housenumber":"/ 56",
    "addr:postcode":"4006",
    "addr:street":"Burrows St",
    "iso:country":"AU",
    "sg:address":"2/ 56 Burrows St",
    "sg:city":"Bowen Hills",
    "sg:classifiers":[
        {
            "category":"Building & Trades",
            "subcategory":"Construction",
            "type":"Services"
        }
    ],
    "sg:phone":"+61 13 84 68",
    "sg:postcode":"4006",
    "sg:province":"QLD",
    "sg:tags":[
        "window",
        "tinting"
    ],
    "wof:name":"Tint.A.Car",
    "wof:placetype":"venue"
},
  "geometry": {"coordinates":[153.04083251899999,-27.4346389771],"type":"Point"}
}