{
  "type": "Feature",
  "properties": {
    "addr:full":"79 Hillsdon Rd Taringa QLD 4068",
    "addr:housenumber":"79",
    "addr:postcode":"4068",
    "addr:street":"Hillsdon Rd",
    "iso:country":"AU",
    "sg:address":"79 Hillsdon Rd",
    "sg:city":"Taringa",
    "sg:classifiers":[
        {
            "category":"Education",
            "subcategory":"Kindergarten",
            "type":"Public Place"
        }
    ],
    "sg:phone":"+61 7 3870 7861",
    "sg:postcode":"4068",
    "sg:province":"QLD",
    "sg:tags":[
        "pre-schools"
    ],
    "wof:name":"C&K Hillsdon Kindergarten",
    "wof:placetype":"venue"
},
  "geometry": {"coordinates":[152.97366332999999,-27.4896526337],"type":"Point"}
}