{
  "type": "Feature",
  "properties": {
    "iso:country":"AU",
    "sg:address":"39b Daly St",
    "sg:city":"South Fremantle",
    "sg:classifiers":[
        {
            "category":"Professional",
            "subcategory":"Engineering",
            "type":"Services"
        }
    ],
    "sg:phone":"+61 8 9335 7545",
    "sg:postcode":"6162",
    "sg:province":"WA",
    "sg:tags":[
        "installation",
        "maintenance",
        "engineer"
    ],
    "wof:name":"Expeditors Pty Ltd The",
    "wof:placetype":"venue"
},
  "geometry": {"coordinates":[115.757110596,-32.0722961426],"type":"Point"}
}