{
  "type": "Feature",
  "properties": {
    "addr:full":"44 Newham Drv Cambridge Gardens NSW 2747",
    "addr:housenumber":"44",
    "addr:postcode":"2747",
    "addr:street":"Newham Drv",
    "iso:country":"AU",
    "sg:address":"44 Newham Drv",
    "sg:city":"Cambridge Gardens",
    "sg:classifiers":[
        {
            "category":"Farming",
            "subcategory":"Farm & Veterinary Services",
            "type":"Manufacturing & Wholesale Goods"
        }
    ],
    "sg:phone":"+61 2 4730 1514",
    "sg:postcode":"2747",
    "sg:province":"NSW",
    "sg:tags":[
        "blacksmith",
        "farrier"
    ],
    "wof:name":"Levy J M",
    "wof:placetype":"venue"
},
  "geometry": {"coordinates":[150.721893311,-33.7335281372],"type":"Point"}
}