{
  "type": "Feature",
  "properties": {
    "addr:full":"Crn Eumundi Rd & Ely St Noosaville Noosaville QLD 4566",
    "addr:postcode":"4566",
    "addr:street":"Crn Eumundi Rd & Ely St",
    "iso:country":"AU",
    "sg:address":"Crn Eumundi Rd & Ely St Noosaville",
    "sg:city":"Noosaville",
    "sg:classifiers":[
        {
            "category":"Health Services",
            "subcategory":"Dentist",
            "type":"Services"
        }
    ],
    "sg:phone":"+61 429 003 808",
    "sg:postcode":"4566",
    "sg:province":"QLD",
    "wof:name":"Pandanas Dental",
    "wof:placetype":"venue"
},
  "geometry": {"coordinates":[153.051055908,-26.4020080566],"type":"Point"}
}