{
  "type": "Feature",
  "properties": {
    "addr:full":"Cnr Duke & Prince Sts Myrtleford VIC 3737",
    "addr:postcode":"3737",
    "iso:country":"AU",
    "sg:address":"Cnr Duke & Prince Sts",
    "sg:city":"Myrtleford",
    "sg:classifiers":[
        {
            "category":"Social Services",
            "subcategory":"Child Care",
            "type":"Services"
        }
    ],
    "sg:phone":"+61 3 5752 2111",
    "sg:postcode":"3737",
    "sg:province":"VIC",
    "wof:name":"Mountain View Children's Centre",
    "wof:placetype":"venue"
},
  "geometry": {"coordinates":[146.720870972,-36.5589904785],"type":"Point"}
}