{
  "type": "Feature",
  "properties": {
    "addr:full":"151 High St Thomastown VIC 3074",
    "addr:housenumber":"151",
    "addr:postcode":"3074",
    "addr:street":"High St",
    "iso:country":"AU",
    "sg:address":"151 High St",
    "sg:city":"Thomastown",
    "sg:classifiers":[
        {
            "category":"Retail",
            "subcategory":"Repair Shop",
            "type":"Services"
        }
    ],
    "sg:phone":"+61 3 9464 0801",
    "sg:postcode":"3074",
    "sg:province":"VIC",
    "sg:tags":[
        "machine",
        "repairs",
        "part",
        "dryer",
        "washing"
    ],
    "wof:name":"Sammy's Refrigeration Service",
    "wof:placetype":"venue"
},
  "geometry": {"coordinates":[145.013305664,-37.6823158264],"type":"Point"}
}