{
  "type": "Feature",
  "properties": {
    "addr:full":"Level 2, 729 Pacific Hwy Gordon NSW 2072",
    "addr:housenumber":"729",
    "addr:postcode":"2072",
    "addr:street":"Pacific Hwy",
    "iso:country":"AU",
    "sg:address":"Level 2, 729 Pacific Hwy",
    "sg:city":"Gordon",
    "sg:classifiers":[
        {
            "category":"Professional",
            "subcategory":"Art Services",
            "type":"Services"
        }
    ],
    "sg:phone":"+61 2 9418 4133",
    "sg:postcode":"2072",
    "sg:province":"NSW",
    "sg:tags":[
        "conservation",
        "restoration"
    ],
    "wof:name":"Art North Gallery",
    "wof:placetype":"venue"
},
  "geometry": {"coordinates":[151.15322875999999,-33.7565841675],"type":"Point"}
}