{
  "type": "Feature",
  "properties": {
    "addr:full":"131 Honors Rd Bundaberg QLD 4670",
    "addr:housenumber":"131",
    "addr:postcode":"4670",
    "addr:street":"Honors Rd",
    "iso:country":"AU",
    "sg:address":"131 Honors Rd",
    "sg:city":"Bundaberg",
    "sg:classifiers":[
        {
            "category":"Building & Trades",
            "subcategory":"Cleaning & Sanitation",
            "type":"Services"
        }
    ],
    "sg:phone":"+61 428 796 437",
    "sg:postcode":"4670",
    "sg:province":"QLD",
    "sg:tags":[
        "abrasive",
        "blasting"
    ],
    "wof:name":"Honor Sandblasting Services",
    "wof:placetype":"venue"
},
  "geometry": {"coordinates":[152.34573364299999,-24.9178543091],"type":"Point"}
}