{
  "type": "Feature",
  "properties": {
    "iso:country":"AU",
    "sg:address":"69 Farrel Rd",
    "sg:city":"Bulli",
    "sg:classifiers":[
        {
            "category":"Building & Trades",
            "subcategory":"Construction",
            "type":"Services"
        }
    ],
    "sg:phone":"+61 403 197 787",
    "sg:postcode":"2516",
    "sg:province":"NSW",
    "sg:tags":[
        "contractor"
    ],
    "wof:name":"Victor's Quality Building",
    "wof:placetype":"venue"
},
  "geometry": {"coordinates":[150.914474,-34.338913],"type":"Point"}
}