{
  "type": "Feature",
  "properties": {
    "iso:country":"AU",
    "sg:address":"PO Box 3684",
    "sg:city":"Hermit Park",
    "sg:classifiers":[
        {
            "category":"Manufacturing",
            "subcategory":"Chemicals & Compounds",
            "type":"Manufacturing & Wholesale Goods"
        }
    ],
    "sg:phone":"+61 7 4728 5807",
    "sg:postcode":"4812",
    "sg:province":"QLD",
    "sg:tags":[
        "product",
        "geosynthetic"
    ],
    "wof:name":"Ten Cate Australia Pty Ltd",
    "wof:placetype":"venue"
},
  "geometry": {"coordinates":[146.805527,-19.282761],"type":"Point"}
}