{
  "type": "Feature",
  "properties": {
    "addr:full":"Shop 4/ 36 Milligan St Perth TAS 6805",
    "addr:housenumber":"shop 4 / 36",
    "addr:postcode":"6805",
    "addr:street":"Milligan St",
    "iso:country":"AU",
    "sg:address":"Shop 4/ 36 Milligan St",
    "sg:city":"Perth",
    "sg:classifiers":[
        {
            "category":"Utilities",
            "subcategory":"Electric",
            "type":"Services"
        }
    ],
    "sg:phone":"+61 418 953 918",
    "sg:postcode":"6805",
    "sg:province":"TAS",
    "sg:tags":[
        "electrical",
        "contractor"
    ],
    "wof:name":"Williams Ray Electrical & Mechanical Services",
    "wof:placetype":"venue"
},
  "geometry": {"coordinates":[115.851753,-31.951715],"type":"Point"}
}