{
  "type": "Feature",
  "properties": {
    "addr:full":"Unit F1, Lidcombe Business Park, 3-29 Birnie Avenue Lidcombe NSW 2141",
    "addr:housenumber":"unit f1;3-29",
    "addr:postcode":"2141",
    "addr:street":"Business;Birnie Avenue",
    "iso:country":"AU",
    "sg:address":"Unit F1, Lidcombe Business Park, 3-29 Birnie Avenue",
    "sg:city":"Lidcombe",
    "sg:classifiers":[
        {
            "category":"Wholesale",
            "subcategory":"Photographic Equipment",
            "type":"Manufacturing & Wholesale Goods"
        }
    ],
    "sg:phone":"+61 1300 366 499",
    "sg:postcode":"2141",
    "sg:province":"NSW",
    "sg:tags":[
        "wholesaler",
        "mfrs",
        "supply"
    ],
    "wof:name":"Maxwell Optical",
    "wof:placetype":"venue"
},
  "geometry": {"coordinates":[151.056762695,-33.8595581055],"type":"Point"}
}