{
  "type": "Feature",
  "properties": {
    "addr:full":"Shop 3 408 King William St Adelaide SA 5000",
    "addr:housenumber":"shop 3 408",
    "addr:postcode":"5000",
    "addr:street":"King William St",
    "iso:country":"AU",
    "sg:address":"Shop 3 408 King William St",
    "sg:city":"Adelaide",
    "sg:classifiers":[
        {
            "category":"Home & Garden",
            "subcategory":"Building Materials",
            "type":"Retail Goods"
        }
    ],
    "sg:phone":"+61 8 8378 3555",
    "sg:postcode":"5000",
    "sg:province":"SA",
    "sg:tags":[
        "lawn",
        "cutting",
        "maintenance"
    ],
    "wof:name":"Alpine Lawn & Gardening",
    "wof:placetype":"venue"
},
  "geometry": {"coordinates":[138.59971618599999,-34.9243736267],"type":"Point"}
}