{
  "type": "Feature",
  "properties": {
    "addr:full":"34-36 McLachlan Ave Rushcutters Bay NSW 2011",
    "addr:housenumber":"34-36",
    "addr:postcode":"2011",
    "addr:street":"Mclachlan Ave",
    "iso:country":"AU",
    "sg:address":"34-36 McLachlan Ave",
    "sg:city":"Rushcutters Bay",
    "sg:classifiers":[
        {
            "category":"Shopping",
            "subcategory":"Antiques",
            "type":"Retail Goods"
        }
    ],
    "sg:phone":"+61 2 9332 4455",
    "sg:postcode":"2011",
    "sg:province":"NSW",
    "sg:tags":[
        "restoration",
        "reproduction"
    ],
    "wof:name":"Mother Of Pearl & Sons Trading Pty Ltd",
    "wof:placetype":"venue"
},
  "geometry": {"coordinates":[151.228607178,-33.8764648438],"type":"Point"}
}