{
  "type": "Feature",
  "properties": {
    "addr:full":"shop 3 ,75 Lynbrook Blv Lynbrook VIC 3975",
    "addr:housenumber":"shop;75",
    "addr:postcode":"3975",
    "addr:street":"Lynbrook Blv",
    "iso:country":"AU",
    "sg:address":"shop 3",
    "sg:city":",75 Lynbrook Blv Lynbrook",
    "sg:classifiers":[
        {
            "category":"Real Estate",
            "subcategory":"Real Estate Agent",
            "type":"Services"
        }
    ],
    "sg:phone":"+61 3 8768 6300",
    "sg:postcode":"3975",
    "sg:province":"VIC",
    "wof:name":"MPRE Harcourts",
    "wof:placetype":"venue"
},
  "geometry": {"coordinates":[145.25309753400001,-38.0529289246],"type":"Point"}
}