{
  "type": "Feature",
  "properties": {
    "iso:country":"AU",
    "sg:address":"116 Magill Rd",
    "sg:city":"Norwood",
    "sg:classifiers":[
        {
            "category":"Manufacturing",
            "subcategory":"Furniture",
            "type":"Manufacturing & Wholesale Goods"
        }
    ],
    "sg:phone":"+61 8 8362 2344",
    "sg:postcode":"5067",
    "sg:province":"SA",
    "sg:tags":[
        "equipment",
        "hire"
    ],
    "wof:name":"Pabs Furniture Rentals Pty Ltd",
    "wof:placetype":"venue"
},
  "geometry": {"coordinates":[138.633209228,-34.9152832031],"type":"Point"}
}