{
  "type": "Feature",
  "properties": {
    "iso:country":"AU",
    "sg:address":"480 Peel St",
    "sg:city":"Tamworth",
    "sg:classifiers":[
        {
            "category":"Shopping",
            "subcategory":"Stationery & Office Supplies",
            "type":"Retail Goods"
        }
    ],
    "sg:phone":"+61 2 6766 4944",
    "sg:postcode":"2340",
    "sg:province":"NSW",
    "wof:name":"Cartridge World",
    "wof:placetype":"venue"
},
  "geometry": {"coordinates":[150.934204102,-31.0951652527],"type":"Point"}
}