{
  "type": "Feature",
  "properties": {
    "iso:country":"AU",
    "sg:address":"23",
    "sg:city":"/ 23 Baynton Cres Roxburgh Park",
    "sg:classifiers":[
        {
            "category":"Retail",
            "subcategory":"Auto Repair",
            "type":"Services"
        }
    ],
    "sg:phone":"+61 438 377 176",
    "sg:postcode":"3064",
    "sg:province":"VIC",
    "sg:tags":[
        "repairer",
        "motor",
        "engineer"
    ],
    "wof:name":"Steves Mobile Mechanics",
    "wof:placetype":"venue"
},
  "geometry": {"coordinates":[144.92044067399999,-37.6277084351],"type":"Point"}
}