{
  "type": "Feature",
  "properties": {
    "addr:full":"92 Fulton Rd Mt Eliza VIC 3930",
    "addr:housenumber":"92",
    "addr:postcode":"3930",
    "addr:street":"Fulton Rd",
    "iso:country":"AU",
    "sg:address":"92 Fulton Rd",
    "sg:city":"Mt Eliza",
    "sg:classifiers":[
        {
            "category":"Building & Trades",
            "subcategory":"Landscaping Services",
            "type":"Services"
        }
    ],
    "sg:phone":"+61 3 9775 2966",
    "sg:postcode":"3930",
    "sg:province":"VIC",
    "sg:tags":[
        "stump",
        "tree",
        "felling",
        "removal"
    ],
    "wof:name":"Browns Complete Tree Removal",
    "wof:placetype":"venue"
},
  "geometry": {"coordinates":[145.113082886,-38.1826820374],"type":"Point"}
}