{
  "type": "Feature",
  "properties": {
    "addr:full":"60 Nunns Rd Mornington VIC 3931",
    "addr:housenumber":"60",
    "addr:postcode":"3931",
    "addr:street":"Nunns Rd",
    "iso:country":"AU",
    "sg:address":"60 Nunns Rd",
    "sg:city":"Mornington",
    "sg:classifiers":[
        {
            "category":"Wholesale",
            "subcategory":"Painting Supplies",
            "type":"Manufacturing & Wholesale Goods"
        }
    ],
    "sg:phone":"+61 3 5975 2818",
    "sg:postcode":"3931",
    "sg:province":"VIC",
    "sg:tags":[
        "product",
        "cleaning"
    ],
    "wof:name":"Young A K & P E",
    "wof:placetype":"venue"
},
  "geometry": {"coordinates":[145.02935790999999,-38.2295875549],"type":"Point"}
}