{
  "type": "Feature",
  "properties": {
    "addr:full":"Bussell Hwy Cowaramup WA 6284",
    "addr:postcode":"6284",
    "addr:street":"Bussell Hwy",
    "iso:country":"AU",
    "sg:address":"Bussell Hwy",
    "sg:city":"Cowaramup",
    "sg:classifiers":[
        {
            "category":"Building & Trades",
            "subcategory":"Construction",
            "type":"Services"
        }
    ],
    "sg:phone":"+61 8 9755 5479",
    "sg:postcode":"6284",
    "sg:province":"WA",
    "sg:tags":[
        "earth",
        "excavating",
        "moving",
        "contractor"
    ],
    "wof:name":"Cowara Contractors Pty Ltd",
    "wof:placetype":"venue"
},
  "geometry": {"coordinates":[115.102851868,-33.8509368896],"type":"Point"}
}