{
  "type": "Feature",
  "properties": {
    "addr:full":"116 Peter St Wagga Wagga NSW 2650",
    "addr:housenumber":"116",
    "addr:postcode":"2650",
    "addr:street":"Peter St",
    "iso:country":"AU",
    "sg:address":"116 Peter St",
    "sg:city":"Wagga Wagga",
    "sg:classifiers":[
        {
            "category":"Health Services",
            "subcategory":"Health Practitioner",
            "type":"Services"
        }
    ],
    "sg:phone":"+61 2 6921 7866",
    "sg:postcode":"2650",
    "sg:province":"NSW",
    "sg:tags":[
        "physiotherapist"
    ],
    "wof:name":"Riverina Manipulative & Sports Physiotherapy Centre",
    "wof:placetype":"venue"
},
  "geometry": {"coordinates":[147.36849975600001,-35.1115913391],"type":"Point"}
}