{
  "type": "Feature",
  "properties": {
    "addr:full":"Shop TO2 Pemulwuy Market Place Greystane & Old Prospect Rds Greystanes NSW 2145",
    "addr:postcode":"2145",
    "addr:street":"Market Place Greystane & Old Prospect Rds",
    "iso:country":"AU",
    "sg:address":"Shop TO2 Pemulwuy Market Place Greystane & Old Prospect Rds",
    "sg:city":"Greystanes",
    "sg:classifiers":[
        {
            "category":"Communications",
            "subcategory":"Film & Video Production",
            "type":"Services"
        }
    ],
    "sg:phone":"+61 2 9688 2877",
    "sg:postcode":"2145",
    "sg:province":"NSW",
    "sg:tags":[
        "dvd",
        "library"
    ],
    "wof:name":"Blockbuster",
    "wof:placetype":"venue"
},
  "geometry": {"coordinates":[150.94769287099999,-33.8190078735],"type":"Point"}
}