{
  "type": "Feature",
  "properties": {
    "addr:full":"32 Graylands Rd Claremont WA 6010",
    "addr:housenumber":"32",
    "addr:postcode":"6010",
    "addr:street":"Graylands Rd",
    "iso:country":"AU",
    "sg:address":"32 Graylands Rd",
    "sg:city":"Claremont",
    "sg:classifiers":[
        {
            "category":"Professional",
            "subcategory":"Detective & Security Services",
            "type":"Services"
        }
    ],
    "sg:phone":"+61 8 9385 0400",
    "sg:postcode":"6010",
    "sg:province":"WA",
    "sg:tags":[
        "guard",
        "patrol"
    ],
    "wof:name":"Securecor",
    "wof:placetype":"venue"
},
  "geometry": {"coordinates":[115.782981873,-31.9748497009],"type":"Point"}
}