{
  "type": "Feature",
  "properties": {
    "iso:country":"AU",
    "sg:address":"96 Warren Rd",
    "sg:city":"Mordialloc",
    "sg:classifiers":[
        {
            "category":"Real Estate",
            "subcategory":"Surveying",
            "type":"Services"
        }
    ],
    "sg:phone":"+61 3 9588 1701",
    "sg:postcode":"3195",
    "sg:province":"VIC",
    "sg:tags":[
        "building",
        "surveyor"
    ],
    "wof:name":"KZB Building Surveying",
    "wof:placetype":"venue"
},
  "geometry": {"coordinates":[145.092987061,-37.9923477173],"type":"Point"}
}