{
  "type": "Feature",
  "properties": {
    "iso:country":"AU",
    "sg:address":"3B Coombes Drv",
    "sg:city":"Penrith",
    "sg:classifiers":[
        {
            "category":"Building & Trades",
            "subcategory":"Equipment Rental",
            "type":"Services"
        }
    ],
    "sg:phone":"+61 2 4731 1313",
    "sg:postcode":"2750",
    "sg:province":"NSW",
    "sg:tags":[
        "hire",
        "catering"
    ],
    "wof:name":"Penrith Party Hire",
    "wof:placetype":"venue"
},
  "geometry": {"coordinates":[150.69595336899999,-33.7434883118],"type":"Point"}
}