{
  "type": "Feature",
  "properties": {
    "addr:full":"103 Empire Ave Manly West QLD 4179",
    "addr:housenumber":"103",
    "addr:postcode":"4179",
    "addr:street":"Empire Ave",
    "iso:country":"AU",
    "sg:address":"103 Empire Ave",
    "sg:city":"Manly West",
    "sg:classifiers":[
        {
            "category":"Professional",
            "subcategory":"Accounting & Tax Preparation",
            "type":"Services"
        }
    ],
    "sg:phone":"+61 7 3333 1897",
    "sg:postcode":"4179",
    "sg:province":"QLD",
    "sg:tags":[
        "bookkeeping"
    ],
    "wof:name":"In Balance Bookkeeping",
    "wof:placetype":"venue"
},
  "geometry": {"coordinates":[153.177902222,-27.4683990479],"type":"Point"}
}