{
  "type": "Feature",
  "properties": {
    "addr:full":"24 Jacobs St Whyalla Norrie SA 5608",
    "addr:housenumber":"24",
    "addr:postcode":"5608",
    "addr:street":"Jacobs St",
    "iso:country":"AU",
    "sg:address":"24 Jacobs St",
    "sg:city":"Whyalla Norrie",
    "sg:classifiers":[
        {
            "category":"Manufacturing",
            "subcategory":"Motor Vehicles & Parts",
            "type":"Manufacturing & Wholesale Goods"
        }
    ],
    "sg:phone":"+61 8 8645 4111",
    "sg:postcode":"5608",
    "sg:province":"SA",
    "sg:tags":[
        "engine",
        "equipment",
        "diesel"
    ],
    "wof:name":"Diesel Fuel Injection Service (Whyalla)",
    "wof:placetype":"venue"
},
  "geometry": {"coordinates":[137.54373200000001,-33.040707],"type":"Point"}
}