{
  "type": "Feature",
  "properties": {
    "addr:full":"U9/ 2 Donald St Guildford NSW 2161",
    "addr:housenumber":"2",
    "addr:postcode":"2161",
    "addr:street":"U9 /;Donald St",
    "iso:country":"AU",
    "sg:address":"U9/ 2 Donald St",
    "sg:city":"Guildford",
    "sg:classifiers":[
        {
            "category":"Autos & Motor Vehicles",
            "subcategory":"Auto Supplies",
            "type":"Retail Goods"
        }
    ],
    "sg:phone":"+61 2 9681 3940",
    "sg:postcode":"2161",
    "sg:province":"NSW",
    "sg:tags":[
        "tyre"
    ],
    "wof:name":"AAA Tyre Factory",
    "wof:placetype":"venue"
},
  "geometry": {"coordinates":[150.98042297399999,-33.8695335388],"type":"Point"}
}