{
  "type": "Feature",
  "properties": {
    "addr:full":"434 Wright Rd Modbury SA 5092",
    "addr:housenumber":"434",
    "addr:postcode":"5092",
    "addr:street":"Wright Rd",
    "iso:country":"AU",
    "sg:address":"434 Wright Rd",
    "sg:city":"Modbury",
    "sg:classifiers":[
        {
            "category":"Food & Beverages",
            "subcategory":"Specialty",
            "type":"Retail Goods"
        }
    ],
    "sg:phone":"+61 8 8264 2297",
    "sg:postcode":"5092",
    "sg:province":"SA",
    "sg:tags":[
        "product",
        "health"
    ],
    "wof:name":"USANA Independent Associate",
    "wof:placetype":"venue"
},
  "geometry": {"coordinates":[138.673538208,-34.8340644836],"type":"Point"}
}