{
  "type": "Feature",
  "properties": {
    "addr:full":"105 Wollumbin St Murwillumbah NSW 2484",
    "addr:housenumber":"105",
    "addr:postcode":"2484",
    "addr:street":"Wollumbin St",
    "iso:country":"AU",
    "sg:address":"105 Wollumbin St",
    "sg:city":"Murwillumbah",
    "sg:classifiers":[
        {
            "category":"Retail",
            "subcategory":"Auto Repair",
            "type":"Services"
        }
    ],
    "sg:phone":"+61 2 6672 9019",
    "sg:postcode":"2484",
    "sg:province":"NSW",
    "sg:tags":[
        "repairer",
        "motor",
        "engineer"
    ],
    "wof:name":"Sunrise Motors",
    "wof:placetype":"venue"
},
  "geometry": {"coordinates":[153.393844605,-28.327167511],"type":"Point"}
}