{
  "type": "Feature",
  "properties": {
    "iso:country":"AU",
    "sg:address":"174 Cavendish Rd",
    "sg:city":"(Cnr Old Cleveland Rd) Coorparoo",
    "sg:classifiers":[
        {
            "category":"Health Services",
            "subcategory":"Optometrist",
            "type":"Services"
        }
    ],
    "sg:phone":"+61 7 3394 1166",
    "sg:postcode":"4151",
    "sg:province":"QLD",
    "wof:name":"ST.EYE.LE - Eyeswider Optometrists",
    "wof:placetype":"venue"
},
  "geometry": {"coordinates":[153.05900573700001,-27.4939041138],"type":"Point"}
}