{
  "type": "Feature",
  "properties": {
    "addr:full":"77B High St Kangaroo Flat VIC 3555",
    "addr:housenumber":"77b",
    "addr:postcode":"3555",
    "addr:street":"High St",
    "iso:country":"AU",
    "sg:address":"77B High St",
    "sg:city":"Kangaroo Flat",
    "sg:classifiers":[
        {
            "category":"Industrial Area",
            "type":"Public Place"
        }
    ],
    "sg:phone":"+61 3 5447 4301",
    "sg:postcode":"3555",
    "sg:province":"VIC",
    "sg:tags":[
        "protective",
        "clothing"
    ],
    "wof:name":"Hip Pocket Workwear & Safety",
    "wof:placetype":"venue"
},
  "geometry": {"coordinates":[144.24418640100001,-36.7957687378],"type":"Point"}
}