{
  "type": "Feature",
  "properties": {
    "iso:country":"AU",
    "sg:address":"48 Agnew St",
    "sg:city":"Norman Park",
    "sg:classifiers":[
        {
            "category":"Health Services",
            "subcategory":"Dentist",
            "type":"Services"
        }
    ],
    "sg:phone":"+61 404 883 451",
    "sg:postcode":"4170",
    "sg:province":"QLD",
    "sg:tags":[
        "technician",
        "dental"
    ],
    "wof:name":"Q Dental Services",
    "wof:placetype":"venue"
},
  "geometry": {"coordinates":[153.060424805,-27.4732456207],"type":"Point"}
}