{
  "type": "Feature",
  "properties": {
    "iso:country":"AU",
    "sg:address":"Lot 3/ Wentworth St",
    "sg:city":"Glen Innes",
    "sg:classifiers":[
        {
            "category":"Professional",
            "subcategory":"Art Services",
            "type":"Services"
        }
    ],
    "sg:phone":"+61 2 6732 7024",
    "sg:postcode":"2370",
    "sg:province":"NSW",
    "sg:tags":[
        "graphic",
        "designer"
    ],
    "wof:name":"Tricked Graphics",
    "wof:placetype":"venue"
},
  "geometry": {"coordinates":[151.73541259800001,-29.7408866882],"type":"Point"}
}