{
  "type": "Feature",
  "properties": {
    "addr:full":"68 - 72 York St South Melbourne VIC 3205",
    "addr:housenumber":"72",
    "addr:postcode":"3205",
    "addr:street":"York St",
    "iso:country":"AU",
    "sg:address":"68 - 72 York St",
    "sg:city":"South Melbourne",
    "sg:classifiers":[
        {
            "category":"Professional",
            "subcategory":"Art Services",
            "type":"Services"
        }
    ],
    "sg:phone":"+61 3 9323 0567",
    "sg:postcode":"3205",
    "sg:province":"VIC",
    "sg:tags":[
        "graphic",
        "designer"
    ],
    "wof:name":"Coopers Lloyd",
    "wof:placetype":"venue"
},
  "geometry": {"coordinates":[144.95988500000001,-37.830547],"type":"Point"}
}