{
  "type": "Feature",
  "properties": {
    "addr:full":"36/ 28 Barry Rd Chipping Norton NSW 2170",
    "addr:housenumber":"36 / 28",
    "addr:postcode":"2170",
    "addr:street":"Barry Rd",
    "iso:country":"AU",
    "sg:address":"36/ 28 Barry Rd",
    "sg:city":"Chipping Norton",
    "sg:classifiers":[
        {
            "category":"Autos & Motor Vehicles",
            "subcategory":"Auto Supplies",
            "type":"Retail Goods"
        }
    ],
    "sg:phone":"+61 2 9872 3881",
    "sg:postcode":"2170",
    "sg:province":"NSW",
    "sg:tags":[
        "transmission",
        "equipment",
        "power"
    ],
    "wof:name":"Hercus Powertrans",
    "wof:placetype":"venue"
},
  "geometry": {"coordinates":[150.96188354500001,-33.9153060913],"type":"Point"}
}