{
  "type": "Feature",
  "properties": {
    "iso:country":"AU",
    "sg:address":"60 Esher St",
    "sg:city":"Tarragindi",
    "sg:classifiers":[
        {
            "category":"Professional",
            "subcategory":"Computer Services",
            "type":"Services"
        }
    ],
    "sg:phone":"+61 7 3847 9769",
    "sg:postcode":"4121",
    "sg:province":"QLD",
    "sg:tags":[
        "package",
        "software"
    ],
    "wof:name":"Chips Software",
    "wof:placetype":"venue"
},
  "geometry": {"coordinates":[153.05088806099999,-27.5195331573],"type":"Point"}
}