{
  "type": "Feature",
  "properties": {
    "iso:country":"AU",
    "sg:address":"Hospital Rd",
    "sg:city":"Emerald",
    "sg:classifiers":[
        {
            "category":"Travel",
            "subcategory":"Hostel",
            "type":"Entertainment"
        }
    ],
    "sg:phone":"+61 7 4982 4188",
    "sg:postcode":"4720",
    "sg:province":"QLD",
    "sg:tags":[
        "home"
    ],
    "wof:name":"Emerald Hostel",
    "wof:placetype":"venue"
},
  "geometry": {"coordinates":[148.158096,-23.52412],"type":"Point"}
}