{
  "type": "Feature",
  "properties": {
    "addr:full":"3/ 75 Boronia Rd Vermont VIC 3133",
    "addr:housenumber":"/ 75",
    "addr:postcode":"3133",
    "addr:street":"Boronia Rd",
    "iso:country":"AU",
    "sg:address":"3/ 75 Boronia Rd",
    "sg:city":"Vermont",
    "sg:classifiers":[
        {
            "category":"Retail",
            "subcategory":"Driving School",
            "type":"Services"
        }
    ],
    "sg:phone":"+61 3 9874 3840",
    "sg:postcode":"3133",
    "sg:province":"VIC",
    "sg:tags":[
        "operator",
        "plant",
        "training"
    ],
    "wof:name":"Update Driver Training",
    "wof:placetype":"venue"
},
  "geometry": {"coordinates":[145.20506286599999,-37.8418960571],"type":"Point"}
}