{
  "type": "Feature",
  "properties": {
    "addr:full":"5 Urunga Pde Wollongong NSW 2500",
    "addr:housenumber":"5",
    "addr:postcode":"2500",
    "addr:street":"Urunga Pde",
    "iso:country":"AU",
    "sg:address":"5 Urunga Pde",
    "sg:city":"Wollongong",
    "sg:classifiers":[
        {
            "category":"Health Services",
            "subcategory":"Doctor",
            "type":"Services"
        }
    ],
    "sg:phone":"+61 2 4228 1175",
    "sg:postcode":"2500",
    "sg:province":"NSW",
    "sg:tags":[
        "medical",
        "practitioner"
    ],
    "wof:name":"B.V. Krishna Dr.",
    "wof:placetype":"venue"
},
  "geometry": {"coordinates":[150.88171399999999,-34.425335],"type":"Point"}
}