{
  "type": "Feature",
  "properties": {
    "iso:country":"AU",
    "sg:address":"97 High St",
    "sg:city":"Doncaster",
    "sg:classifiers":[
        {
            "category":"Social Services",
            "subcategory":"Child Care",
            "type":"Services"
        }
    ],
    "sg:phone":"+61 3 9857 8204",
    "sg:postcode":"3108",
    "sg:province":"VIC",
    "wof:name":"Dinky's Early Learning Centre",
    "wof:placetype":"venue"
},
  "geometry": {"coordinates":[145.11070251500001,-37.7814254761],"type":"Point"}
}