{
  "type": "Feature",
  "properties": {
    "iso:country":"AU",
    "sg:address":"110 Wattle Ave",
    "sg:city":"Werribee",
    "sg:classifiers":[
        {
            "category":"Education",
            "subcategory":"School",
            "type":"Public Place"
        }
    ],
    "sg:phone":"+61 3 9974 1088",
    "sg:postcode":"3030",
    "sg:province":"VIC",
    "sg:tags":[
        "teaching",
        "aid"
    ],
    "wof:name":"MS Vision Pty Ltd",
    "wof:placetype":"venue"
},
  "geometry": {"coordinates":[144.679489,-37.902927],"type":"Point"}
}