{
  "type": "Feature",
  "properties": {
    "iso:country":"AU",
    "sg:address":"Shop 1/ 491 Brighton Rd",
    "sg:city":"Brighton",
    "sg:classifiers":[
        {
            "category":"Personal",
            "subcategory":"Tanning Parlor",
            "type":"Services"
        }
    ],
    "sg:phone":"+61 8 8296 6662",
    "sg:postcode":"5048",
    "sg:province":"SA",
    "sg:tags":[
        "solarium"
    ],
    "wof:name":"Enhance-Brighton",
    "wof:placetype":"venue"
},
  "geometry": {"coordinates":[138.522964,-35.01886],"type":"Point"}
}