{
  "type": "Feature",
  "properties": {
    "addr:full":"Unit 9 Annois Rd (Cnr Parkway Rd) South Lake WA 6164",
    "addr:postcode":"6164",
    "addr:street":"Annois Rd Cnr Parkway Rd",
    "iso:country":"AU",
    "sg:address":"Unit 9 Annois Rd",
    "sg:city":"(Cnr Parkway Rd) South Lake",
    "sg:classifiers":[
        {
            "category":"Health Services",
            "subcategory":"Doctor",
            "type":"Services"
        }
    ],
    "sg:phone":"+61 8 9417 7664",
    "sg:postcode":"6164",
    "sg:province":"WA",
    "sg:tags":[
        "medical",
        "practitioner"
    ],
    "wof:name":"Bibra Lake Medical Centre",
    "wof:placetype":"venue"
},
  "geometry": {"coordinates":[115.840462,-32.095531],"type":"Point"}
}