{
  "type": "Feature",
  "properties": {
    "addr:full":"2 Patrona St Dandenong VIC 3175",
    "addr:housenumber":"2",
    "addr:postcode":"3175",
    "addr:street":"Patrona St",
    "iso:country":"AU",
    "sg:address":"2 Patrona St",
    "sg:city":"Dandenong",
    "sg:classifiers":[
        {
            "category":"Manufacturing",
            "subcategory":"Chemicals & Compounds",
            "type":"Manufacturing & Wholesale Goods"
        }
    ],
    "sg:phone":"+61 3 9701 3171",
    "sg:postcode":"3175",
    "sg:province":"VIC",
    "sg:tags":[
        "electroplating"
    ],
    "wof:name":"Black Oxide Metal Finishers",
    "wof:placetype":"venue"
},
  "geometry": {"coordinates":[145.22508239699999,-37.9990158081],"type":"Point"}
}