{
  "type": "Feature",
  "properties": {
    "addr:full":"Seville Drv Armadale WA 6112",
    "addr:postcode":"6112",
    "addr:street":"Seville Drv",
    "iso:country":"AU",
    "sg:address":"Seville Drv",
    "sg:city":"Armadale",
    "sg:classifiers":[
        {
            "category":"Education",
            "subcategory":"School",
            "type":"Public Place"
        }
    ],
    "sg:phone":"+61 8 9497 0200",
    "sg:postcode":"6112",
    "sg:province":"WA",
    "sg:tags":[
        "state",
        "except",
        "nsw"
    ],
    "wof:name":"Schools Government (Public)",
    "wof:placetype":"venue"
},
  "geometry": {"coordinates":[116.02057647700001,-32.1510009766],"type":"Point"}
}