{
  "type": "Feature",
  "properties": {
    "iso:country":"AU",
    "sg:address":"59 Freemantle Rd",
    "sg:city":"Port Noarlunga",
    "sg:classifiers":[
        {
            "category":"Utilities",
            "subcategory":"Telephone",
            "type":"Services"
        }
    ],
    "sg:phone":"+61 8 8386 2247",
    "sg:postcode":"5167",
    "sg:province":"SA",
    "sg:tags":[
        "installation",
        "system",
        "maintenance"
    ],
    "wof:name":"Telecommunications Resources Pty Ltd",
    "wof:placetype":"venue"
},
  "geometry": {"coordinates":[138.474975586,-35.1694831848],"type":"Point"}
}