{
  "type": "Feature",
  "properties": {
    "addr:full":"96 Union St Pyrmont NSW 2009",
    "addr:housenumber":"96",
    "addr:postcode":"2009",
    "addr:street":"Union St",
    "iso:country":"AU",
    "sg:address":"96 Union St",
    "sg:city":"Pyrmont",
    "sg:classifiers":[
        {
            "category":"Travel",
            "subcategory":"Hotels & Motels",
            "type":"Entertainment"
        }
    ],
    "sg:phone":"+61 2 9660 6996",
    "sg:postcode":"2009",
    "sg:province":"NSW",
    "sg:tags":[
        "pub"
    ],
    "wof:name":"Pyrmont Bridge Hotel",
    "wof:placetype":"venue"
},
  "geometry": {"coordinates":[151.19778442399999,-33.8698387146],"type":"Point"}
}