{
  "type": "Feature",
  "properties": {
    "iso:country":"AU",
    "sg:address":"4/ 186 Henley Beach Rd",
    "sg:city":"Torrensville",
    "sg:classifiers":[
        {
            "category":"Shopping",
            "subcategory":"Baby Store",
            "type":"Retail Goods"
        }
    ],
    "sg:phone":"+61 8 8352 7129",
    "sg:postcode":"5031",
    "sg:province":"SA",
    "sg:tags":[
        "wear"
    ],
    "wof:name":"Ela Anixi",
    "wof:placetype":"venue"
},
  "geometry": {"coordinates":[138.560424805,-34.9239883423],"type":"Point"}
}