{
  "type": "Feature",
  "properties": {
    "addr:full":"5 Parkhurst St Mornington VIC 3931",
    "addr:housenumber":"5",
    "addr:postcode":"3931",
    "addr:street":"Parkhurst St",
    "iso:country":"AU",
    "sg:address":"5 Parkhurst St",
    "sg:city":"Mornington",
    "sg:classifiers":[
        {
            "category":"Autos & Motor Vehicles",
            "subcategory":"Auto Supplies",
            "type":"Retail Goods"
        }
    ],
    "sg:phone":"+61 419 446 566",
    "sg:postcode":"3931",
    "sg:province":"VIC",
    "sg:tags":[
        "car",
        "alarm"
    ],
    "wof:name":"All Car Security",
    "wof:placetype":"venue"
},
  "geometry": {"coordinates":[145.03924560600001,-38.2389984131],"type":"Point"}
}