{
  "type": "Feature",
  "properties": {
    "iso:country":"AU",
    "sg:address":"6a Mathers La",
    "sg:city":"Hobart",
    "sg:classifiers":[
        {
            "category":"Education",
            "subcategory":"Music School",
            "type":"Public Place"
        }
    ],
    "sg:phone":"+61 409 418 219",
    "sg:postcode":"7000",
    "sg:province":"TAS",
    "sg:tags":[
        "teacher"
    ],
    "wof:name":"John Lockwood",
    "wof:placetype":"venue"
},
  "geometry": {"coordinates":[147.32632446299999,-42.8818435669],"type":"Point"}
}