{
  "type": "Feature",
  "properties": {
    "iso:country":"AU",
    "sg:address":"132 Station St",
    "sg:city":"Aspendale",
    "sg:classifiers":[
        {
            "category":"Real Estate",
            "subcategory":"Real Estate Agent",
            "type":"Services"
        }
    ],
    "sg:phone":"+61 3 9580 3888",
    "sg:postcode":"3195",
    "sg:province":"VIC",
    "wof:name":"Century Twenty One Wilson Pride",
    "wof:placetype":"venue"
},
  "geometry": {"coordinates":[145.10220336899999,-38.0267066956],"type":"Point"}
}