{
  "type": "Feature",
  "properties": {
    "addr:full":"PO Box 637 North Narrabeen NSW 2101",
    "addr:postcode":"2101",
    "iso:country":"AU",
    "sg:address":"PO Box 637",
    "sg:city":"North Narrabeen",
    "sg:classifiers":[
        {
            "category":"Building & Trades",
            "subcategory":"Construction",
            "type":"Services"
        }
    ],
    "sg:phone":"+61 2 9970 6729",
    "sg:postcode":"2101",
    "sg:province":"NSW",
    "sg:tags":[
        "contractor"
    ],
    "wof:name":"Steven Bain Constructions Pty Ltd",
    "wof:placetype":"venue"
},
  "geometry": {"coordinates":[151.296707,-33.716614],"type":"Point"}
}