{
  "type": "Feature",
  "properties": {
    "addr:full":"45 Walker St Bundaberg QLD 4670",
    "addr:housenumber":"45",
    "addr:postcode":"4670",
    "addr:street":"Walker St",
    "iso:country":"AU",
    "sg:address":"45 Walker St",
    "sg:city":"Bundaberg",
    "sg:classifiers":[
        {
            "category":"Autos & Motor Vehicles",
            "subcategory":"Automobile Sales",
            "type":"Retail Goods"
        }
    ],
    "sg:phone":"+61 7 4152 7355",
    "sg:postcode":"4670",
    "sg:province":"QLD",
    "sg:tags":[
        "car",
        "new"
    ],
    "wof:name":"West Car Sales",
    "wof:placetype":"venue"
},
  "geometry": {"coordinates":[152.35546875,-24.8782444],"type":"Point"}
}