{
  "type": "Feature",
  "properties": {
    "addr:full":"Studio 812, 118 Franklin St Melbourne VIC 3000",
    "addr:housenumber":"118",
    "addr:postcode":"3000",
    "addr:street":"Franklin St",
    "iso:country":"AU",
    "sg:address":"Studio 812, 118 Franklin St",
    "sg:city":"Melbourne",
    "sg:classifiers":[
        {
            "category":"Education",
            "subcategory":"Dance Studio",
            "type":"Public Place"
        }
    ],
    "sg:phone":"+61 3 9417 6663",
    "sg:postcode":"3000",
    "sg:province":"VIC",
    "sg:tags":[
        "venue",
        "tuition"
    ],
    "wof:name":"Kirsten Leahs School of Belly Dance",
    "wof:placetype":"venue"
},
  "geometry": {"coordinates":[144.959075928,-37.8084182739],"type":"Point"}
}