{
  "type": "Feature",
  "properties": {
    "addr:full":"13a Queen St Goodna QLD 4300",
    "addr:housenumber":"13a",
    "addr:postcode":"4300",
    "addr:street":"Queen St",
    "iso:country":"AU",
    "sg:address":"13a Queen St",
    "sg:city":"Goodna",
    "sg:classifiers":[
        {
            "category":"Professional",
            "type":"Services"
        }
    ],
    "sg:phone":"+61 7 3288 1653",
    "sg:postcode":"4300",
    "sg:province":"QLD",
    "sg:tags":[
        "industrial",
        "commercial",
        "catering"
    ],
    "wof:name":"Yummys",
    "wof:placetype":"venue"
},
  "geometry": {"coordinates":[152.89837646500001,-27.6106204987],"type":"Point"}
}