{
  "type": "Feature",
  "properties": {
    "addr:full":"26 Orlando St Coffs Harbour NSW 2450",
    "addr:housenumber":"26",
    "addr:postcode":"2450",
    "addr:street":"Orlando St",
    "iso:country":"AU",
    "sg:address":"26 Orlando St",
    "sg:city":"Coffs Harbour",
    "sg:classifiers":[
        {
            "category":"Structure",
            "subcategory":"Building",
            "type":"Public Place"
        }
    ],
    "sg:phone":"+61 2 6651 1286",
    "sg:postcode":"2450",
    "sg:province":"NSW",
    "sg:tags":[
        "sail",
        "shade"
    ],
    "wof:name":"Offshore Sails",
    "wof:placetype":"venue"
},
  "geometry": {"coordinates":[153.13665800000001,-30.297199],"type":"Point"}
}