{
  "type": "Feature",
  "properties": {
    "addr:full":"25 Tuncurry St Tuncurry NSW 2428",
    "addr:housenumber":"25",
    "addr:postcode":"2428",
    "addr:street":"Tuncurry St",
    "iso:country":"AU",
    "sg:address":"25 Tuncurry St",
    "sg:city":"Tuncurry",
    "sg:classifiers":[
        {
            "category":"Farming",
            "subcategory":"Fish & Marine Products",
            "type":"Manufacturing & Wholesale Goods"
        }
    ],
    "sg:phone":"+61 2 6554 6462",
    "sg:postcode":"2428",
    "sg:province":"NSW",
    "sg:tags":[
        "supplier",
        "oyster",
        "farmer"
    ],
    "wof:name":"Cain N A",
    "wof:placetype":"venue"
},
  "geometry": {"coordinates":[152.495926,-32.171928],"type":"Point"}
}