{
  "type": "Feature",
  "properties": {
    "addr:full":"4 Tangari St Ngunnawal ACT 2913",
    "addr:housenumber":"4",
    "addr:postcode":"2913",
    "addr:street":"Tangari St",
    "iso:country":"AU",
    "sg:address":"4 Tangari St",
    "sg:city":"Ngunnawal",
    "sg:classifiers":[
        {
            "category":"Health Services",
            "subcategory":"Doctor",
            "type":"Services"
        }
    ],
    "sg:phone":"+61 2 6242 0556",
    "sg:postcode":"2913",
    "sg:province":"ACT",
    "sg:tags":[
        "reflexology"
    ],
    "wof:name":"Gungahlin Health Matters Naturally",
    "wof:placetype":"venue"
},
  "geometry": {"coordinates":[149.119506836,-35.1775588989],"type":"Point"}
}