{
  "type": "Feature",
  "properties": {
    "addr:full":"89 Princes Hwy Fairy Meadow NSW 2519",
    "addr:housenumber":"89",
    "addr:postcode":"2519",
    "addr:street":"Princes Hwy",
    "iso:country":"AU",
    "sg:address":"89 Princes Hwy",
    "sg:city":"Fairy Meadow",
    "sg:classifiers":[
        {
            "category":"Building & Trades",
            "subcategory":"Construction",
            "type":"Services"
        }
    ],
    "sg:phone":"+61 2 4225 8500",
    "sg:postcode":"2519",
    "sg:province":"NSW",
    "sg:tags":[
        "pool",
        "swimming"
    ],
    "wof:name":"Clark Pools & Spas",
    "wof:placetype":"venue"
},
  "geometry": {"coordinates":[150.89210499999999,-34.397865],"type":"Point"}
}