{
  "type": "Feature",
  "properties": {
    "addr:full":"455 North East Rd Hillcrest SA 5086",
    "addr:housenumber":"455",
    "addr:postcode":"5086",
    "addr:street":"North East Rd",
    "iso:country":"AU",
    "sg:address":"455 North East Rd",
    "sg:city":"Hillcrest",
    "sg:classifiers":[
        {
            "category":"Home & Garden",
            "subcategory":"Building Materials",
            "type":"Retail Goods"
        }
    ],
    "sg:phone":"+61 8 8261 3473",
    "sg:postcode":"5086",
    "sg:province":"SA",
    "sg:tags":[
        "merchant",
        "glass",
        "glazier"
    ],
    "wof:name":"Apex Glass Service Pty Ltd",
    "wof:placetype":"venue"
},
  "geometry": {"coordinates":[138.647140503,-34.863243103],"type":"Point"}
}