{
  "type": "Feature",
  "properties": {
    "addr:full":"FctyA/ 59 Waratah St Kirrawee NSW 2232",
    "addr:housenumber":"59",
    "addr:postcode":"2232",
    "addr:street":"Waratah St",
    "iso:country":"AU",
    "sg:address":"FctyA/ 59 Waratah St",
    "sg:city":"Kirrawee",
    "sg:classifiers":[
        {
            "category":"Retail",
            "subcategory":"Auto Repair",
            "type":"Services"
        }
    ],
    "sg:phone":"+61 2 9545 2087",
    "sg:postcode":"2232",
    "sg:province":"NSW",
    "sg:tags":[
        "beater",
        "painter",
        "panel"
    ],
    "wof:name":"Garnett D Panel Beating",
    "wof:placetype":"venue"
},
  "geometry": {"coordinates":[151.07427978499999,-34.0284385681],"type":"Point"}
}