{
  "type": "Feature",
  "properties": {
    "iso:country":"AU",
    "sg:address":"Palmerston St",
    "sg:city":"Sale",
    "sg:classifiers":[
        {
            "category":"Social Services",
            "subcategory":"Child Care",
            "type":"Services"
        }
    ],
    "sg:phone":"+61 3 5149 6800",
    "sg:postcode":"3850",
    "sg:province":"VIC",
    "sg:tags":[
        "support",
        "health"
    ],
    "wof:name":"Maternal & Child Health Centres",
    "wof:placetype":"venue"
},
  "geometry": {"coordinates":[147.07997131400001,-38.1100349426],"type":"Point"}
}