{
  "type": "Feature",
  "properties": {
    "addr:full":"85 Maguire Ave Beechboro WA 6063",
    "addr:housenumber":"85",
    "addr:postcode":"6063",
    "addr:street":"Maguire Ave",
    "iso:country":"AU",
    "sg:address":"85 Maguire Ave",
    "sg:city":"Beechboro",
    "sg:classifiers":[
        {
            "category":"Professional",
            "subcategory":"Art Services",
            "type":"Services"
        }
    ],
    "sg:phone":"+61 412 303 155",
    "sg:postcode":"6063",
    "sg:province":"WA",
    "sg:tags":[
        "decorator",
        "painter"
    ],
    "wof:name":"Findlay SD & VH",
    "wof:placetype":"venue"
},
  "geometry": {"coordinates":[115.949180603,-31.8649406433],"type":"Point"}
}