{
  "type": "Feature",
  "properties": {
    "addr:full":"10 Church La Kelso NSW 2795",
    "addr:housenumber":"10",
    "addr:postcode":"2795",
    "addr:street":"Church La",
    "iso:country":"AU",
    "sg:address":"10 Church La",
    "sg:city":"Kelso",
    "sg:classifiers":[
        {
            "category":"Food & Beverages",
            "subcategory":"Specialty",
            "type":"Retail Goods"
        }
    ],
    "sg:phone":"+61 2 6331 4202",
    "sg:postcode":"2795",
    "sg:province":"NSW",
    "sg:tags":[
        "product",
        "health"
    ],
    "wof:name":"The Cork Centre",
    "wof:placetype":"venue"
},
  "geometry": {"coordinates":[149.608322144,-33.4189414978],"type":"Point"}
}