{
  "type": "Feature",
  "properties": {
    "addr:full":"152 Liebig St Warrnambool VIC 3280",
    "addr:housenumber":"152",
    "addr:postcode":"3280",
    "addr:street":"Liebig St",
    "iso:country":"AU",
    "sg:address":"152 Liebig St",
    "sg:city":"Warrnambool",
    "sg:classifiers":[
        {
            "category":"Health Services",
            "subcategory":"Optometrist",
            "type":"Services"
        }
    ],
    "sg:phone":"+61 3 5562 2244",
    "sg:postcode":"3280",
    "sg:province":"VIC",
    "wof:name":"Eyecare Plus Optometrists",
    "wof:placetype":"venue"
},
  "geometry": {"coordinates":[142.48489379899999,-38.3822135925],"type":"Point"}
}