{
  "type": "Feature",
  "properties": {
    "addr:full":"Unit 3/ 69 Seca St Mansfield QLD 4122",
    "addr:housenumber":"69",
    "addr:postcode":"4122",
    "addr:street":"Seca St",
    "iso:country":"AU",
    "sg:address":"Unit 3/ 69 Seca St",
    "sg:city":"Mansfield",
    "sg:classifiers":[
        {
            "category":"Shopping",
            "subcategory":"Computers & Home Electronics",
            "type":"Retail Goods"
        }
    ],
    "sg:phone":"+61 7 3849 2299",
    "sg:postcode":"4122",
    "sg:province":"QLD",
    "sg:tags":[
        "equipment",
        "supply"
    ],
    "wof:name":"Sato Technology (QLD)",
    "wof:placetype":"venue"
},
  "geometry": {"coordinates":[153.09898376500001,-27.5287208557],"type":"Point"}
}