{
  "type": "Feature",
  "properties": {
    "iso:country":"AU",
    "sg:address":"20 Stonehouse Crs",
    "sg:city":"Bentley",
    "sg:classifiers":[
        {
            "category":"Professional",
            "subcategory":"Accounting & Tax Preparation",
            "type":"Services"
        }
    ],
    "sg:phone":"+61 8 9451 3171",
    "sg:postcode":"6102",
    "sg:province":"WA",
    "sg:tags":[
        "consultant",
        "taxation"
    ],
    "wof:name":"Tax Help",
    "wof:placetype":"venue"
},
  "geometry": {"coordinates":[115.917778015,-32.0027809143],"type":"Point"}
}