{
  "type": "Feature",
  "properties": {
    "addr:full":"54 - 56 Lindsay St Perth WA 6000",
    "addr:housenumber":"56",
    "addr:postcode":"6000",
    "addr:street":"Lindsay St",
    "iso:country":"AU",
    "sg:address":"54 - 56 Lindsay St",
    "sg:city":"Perth",
    "sg:classifiers":[
        {
            "category":"Professional",
            "subcategory":"Business Services",
            "type":"Services"
        }
    ],
    "sg:phone":"+61 8 9449 3913",
    "sg:postcode":"6000",
    "sg:province":"WA",
    "sg:tags":[
        "management",
        "event"
    ],
    "wof:name":"Shearmans",
    "wof:placetype":"venue"
},
  "geometry": {"coordinates":[115.864402771,-31.9452571869],"type":"Point"}
}