{
  "type": "Feature",
  "properties": {
    "addr:full":"21 Gladstone St Perth WA 6000",
    "addr:housenumber":"21",
    "addr:postcode":"6000",
    "addr:street":"Gladstone St",
    "iso:country":"AU",
    "sg:address":"21 Gladstone St",
    "sg:city":"Perth",
    "sg:classifiers":[
        {
            "category":"Retail",
            "subcategory":"Auto Repair",
            "type":"Services"
        }
    ],
    "sg:phone":"+61 8 9227 8079",
    "sg:postcode":"6000",
    "sg:province":"WA",
    "sg:tags":[
        "repairer",
        "motor",
        "engineer"
    ],
    "wof:name":"Europa Automotives",
    "wof:placetype":"venue"
},
  "geometry": {"coordinates":[115.871528626,-31.9477329254],"type":"Point"}
}