{
  "type": "Feature",
  "properties": {
    "addr:full":"173 Hampton St Bridgetown WA 6255",
    "addr:housenumber":"173",
    "addr:postcode":"6255",
    "addr:street":"Hampton St",
    "iso:country":"AU",
    "sg:address":"173 Hampton St",
    "sg:city":"Bridgetown",
    "sg:classifiers":[
        {
            "category":"Professional",
            "subcategory":"Employment Agencies",
            "type":"Services"
        }
    ],
    "sg:phone":"+61 8 9761 2921",
    "sg:postcode":"6255",
    "sg:province":"WA",
    "sg:tags":[
        "entertainer",
        "agent"
    ],
    "wof:name":"Blues At Bridgetown",
    "wof:placetype":"venue"
},
  "geometry": {"coordinates":[116.137161255,-33.9564590454],"type":"Point"}
}