{
  "type": "Feature",
  "properties": {
    "iso:country":"AU",
    "sg:address":"Unit 2, Manly Marine World 1029 Manly Rd Manly Rd",
    "sg:city":"Tingalpa",
    "sg:classifiers":[
        {
            "category":"Recreation",
            "type":"Entertainment"
        }
    ],
    "sg:phone":"+61 7 3390 4533",
    "sg:postcode":"4173",
    "sg:province":"QLD",
    "sg:tags":[
        "recreational",
        "diver"
    ],
    "wof:name":"Aqua X-treme",
    "wof:placetype":"venue"
},
  "geometry": {"coordinates":[153.13275146500001,-27.4755058289],"type":"Point"}
}