{
  "type": "Feature",
  "properties": {
    "addr:full":"Walkers Complex, Harbour Rd Mackay QLD 4740",
    "addr:postcode":"4740",
    "addr:street":"Harbour Rd",
    "iso:country":"AU",
    "sg:address":"Walkers Complex, Harbour Rd",
    "sg:city":"Mackay",
    "sg:classifiers":[
        {
            "category":"Real Estate",
            "subcategory":"Real Estate Agent",
            "type":"Services"
        }
    ],
    "sg:phone":"+61 7 4957 2433",
    "sg:postcode":"4740",
    "sg:province":"QLD",
    "sg:tags":[
        "handyman's",
        "equipment",
        "hire",
        "builders",
        "contractor"
    ],
    "wof:name":"Australian Temporary Fencing North Queensland",
    "wof:placetype":"venue"
},
  "geometry": {"coordinates":[149.190369,-21.128302],"type":"Point"}
}