{
  "type": "Feature",
  "properties": {
    "addr:full":"PO Box 75 Lalor Park NSW 2147",
    "addr:postcode":"2147",
    "iso:country":"AU",
    "sg:address":"PO Box 75",
    "sg:city":"Lalor Park",
    "sg:classifiers":[
        {
            "category":"Real Estate",
            "subcategory":"Real Estate Operator",
            "type":"Services"
        }
    ],
    "sg:phone":"+61 418 630 429",
    "sg:postcode":"2147",
    "sg:province":"NSW",
    "sg:tags":[
        "concrete",
        "pumping"
    ],
    "wof:name":"Queanbeyan Concrete Pumping",
    "wof:placetype":"venue"
},
  "geometry": {"coordinates":[150.93145751899999,-33.7619895935],"type":"Point"}
}