{
  "type": "Feature",
  "properties": {
    "addr:full":"Anzac Pde Yeppoon QLD 4703",
    "addr:postcode":"4703",
    "addr:street":"Anzac Pde",
    "iso:country":"AU",
    "sg:address":"Anzac Pde",
    "sg:city":"Yeppoon",
    "sg:classifiers":[
        {
            "category":"Arena",
            "subcategory":"Sports Club",
            "type":"Entertainment"
        }
    ],
    "sg:phone":"+61 7 4939 1425",
    "sg:postcode":"4703",
    "sg:province":"QLD",
    "sg:tags":[
        "life",
        "surfing",
        "saving"
    ],
    "wof:name":"Yeppoon Surf Life Saving Club Incorporated",
    "wof:placetype":"venue"
},
  "geometry": {"coordinates":[150.74922180199999,-23.1300296783],"type":"Point"}
}