{
  "type": "Feature",
  "properties": {
    "addr:full":"326 Alexander Rd Belmont WA 6104",
    "addr:housenumber":"326",
    "addr:postcode":"6104",
    "addr:street":"Alexander Rd",
    "iso:country":"AU",
    "sg:address":"326 Alexander Rd",
    "sg:city":"Belmont",
    "sg:classifiers":[
        {
            "category":"Professional",
            "subcategory":"Employment Agencies",
            "type":"Services"
        }
    ],
    "sg:phone":"+61 8 9277 9501",
    "sg:postcode":"6104",
    "sg:province":"WA",
    "sg:tags":[
        "provider",
        "internet"
    ],
    "wof:name":"On The .Fli Pty Ltd",
    "wof:placetype":"venue"
},
  "geometry": {"coordinates":[115.936378479,-31.9543437958],"type":"Point"}
}