{
  "type": "Feature",
  "properties": {
    "iso:country":"AU",
    "sg:address":"Shop 3 Atlantis Shopping Centre, Cnr Sovereign Drive & Enterprise Ave",
    "sg:city":"Two Rocks",
    "sg:classifiers":[
        {
            "category":"Fast Food",
            "type":"Food & Drink"
        }
    ],
    "sg:phone":"+61 8 9561 6070",
    "sg:postcode":"6037",
    "sg:province":"WA",
    "sg:tags":[
        "away",
        "take"
    ],
    "wof:name":"Eagle Boys Pizza - Two Rocks",
    "wof:placetype":"venue"
},
  "geometry": {"coordinates":[115.587966919,-31.4941368103],"type":"Point"}
}