{
  "type": "Feature",
  "properties": {
    "addr:full":"16 Ocean Reef Drv Patterson Lakes VIC 3197",
    "addr:housenumber":"16",
    "addr:postcode":"3197",
    "addr:street":"Ocean Reef Drv",
    "iso:country":"AU",
    "sg:address":"16 Ocean Reef Drv",
    "sg:city":"Patterson Lakes",
    "sg:classifiers":[
        {
            "category":"Personal",
            "subcategory":"Beauty Salon",
            "type":"Services"
        }
    ],
    "sg:phone":"+61 410 725 923",
    "sg:postcode":"3197",
    "sg:province":"VIC",
    "sg:tags":[
        "supply",
        "artist",
        "make-up"
    ],
    "wof:name":"Lauren Pitt",
    "wof:placetype":"venue"
},
  "geometry": {"coordinates":[145.14495849599999,-38.0795288086],"type":"Point"}
}