{
  "type": "Feature",
  "properties": {
    "iso:country":"AU",
    "sg:address":"Cranbourne Rd",
    "sg:city":"Langwarrin",
    "sg:classifiers":[
        {
            "category":"Health Services",
            "subcategory":"Health Practitioner",
            "type":"Services"
        }
    ],
    "sg:phone":"+61 419 309 030",
    "sg:postcode":"3910",
    "sg:province":"VIC",
    "sg:tags":[
        "psychologist"
    ],
    "wof:name":"Papasava Dr. Micheal",
    "wof:placetype":"venue"
},
  "geometry": {"coordinates":[145.20419311500001,-38.1448974609],"type":"Point"}
}