{
  "type": "Feature",
  "properties": {
    "addr:full":"136 Cobden St South Melbourne VIC 3205",
    "addr:housenumber":"136",
    "addr:postcode":"3205",
    "addr:street":"Cobden St",
    "iso:country":"AU",
    "sg:address":"136 Cobden St",
    "sg:city":"South Melbourne",
    "sg:classifiers":[
        {
            "category":"Professional",
            "subcategory":"Management & Consulting",
            "type":"Services"
        }
    ],
    "sg:phone":"+61 3 9682 6300",
    "sg:postcode":"3205",
    "sg:province":"VIC",
    "sg:tags":[
        "consultant"
    ],
    "wof:name":"Comprii Pty Ltd",
    "wof:placetype":"venue"
},
  "geometry": {"coordinates":[144.963211,-37.836502],"type":"Point"}
}