{
  "type": "Feature",
  "properties": {
    "addr:full":"PO Box 906 Ingleburn NSW 2565",
    "addr:postcode":"2565",
    "iso:country":"AU",
    "sg:address":"PO Box 906",
    "sg:city":"Ingleburn",
    "sg:classifiers":[
        {
            "category":"Professional",
            "subcategory":"Accounting & Tax Preparation",
            "type":"Services"
        }
    ],
    "sg:phone":"+61 405 134 790",
    "sg:postcode":"2565",
    "sg:province":"NSW",
    "sg:tags":[
        "bookkeeping"
    ],
    "wof:name":"Parkdale Services Pty Ltd",
    "wof:placetype":"venue"
},
  "geometry": {"coordinates":[150.865997314,-33.9984893799],"type":"Point"}
}