{
  "type": "Feature",
  "properties": {
    "addr:full":"1 Matthews Crt Launching Place VIC 3139",
    "addr:housenumber":"1",
    "addr:postcode":"3139",
    "addr:street":"Matthews Crt",
    "iso:country":"AU",
    "sg:address":"1 Matthews Crt",
    "sg:city":"Launching Place",
    "sg:classifiers":[
        {
            "category":"Building & Trades",
            "subcategory":"Equipment Rental",
            "type":"Services"
        }
    ],
    "sg:phone":"+61 3 5961 5294",
    "sg:postcode":"3139",
    "sg:province":"VIC",
    "sg:tags":[
        "party",
        "hire"
    ],
    "wof:name":"The Kings Inflatables",
    "wof:placetype":"venue"
},
  "geometry": {"coordinates":[145.5675354,-37.7847900391],"type":"Point"}
}