{
  "type": "Feature",
  "properties": {
    "addr:full":"967 Whitehorse Rd Box Hill VIC 3128",
    "addr:housenumber":"967",
    "addr:postcode":"3128",
    "addr:street":"Whitehorse Rd",
    "iso:country":"AU",
    "sg:address":"967 Whitehorse Rd",
    "sg:city":"Box Hill",
    "sg:classifiers":[
        {
            "category":"Professional",
            "subcategory":"Accounting & Tax Preparation",
            "type":"Services"
        }
    ],
    "sg:phone":"+61 3 9898 3800",
    "sg:postcode":"3128",
    "sg:province":"VIC",
    "sg:tags":[
        "accountant",
        "auditor"
    ],
    "wof:name":"Karla Eldridge & Associates",
    "wof:placetype":"venue"
},
  "geometry": {"coordinates":[145.124313355,-37.8178367615],"type":"Point"}
}