{
  "type": "Feature",
  "properties": {
    "iso:country":"AU",
    "sg:address":"4 Harwood St",
    "sg:city":"Brighton",
    "sg:classifiers":[
        {
            "category":"Insurance",
            "subcategory":"Title Insurance",
            "type":"Services"
        }
    ],
    "sg:phone":"+61 3 9596 5180",
    "sg:postcode":"3186",
    "sg:province":"VIC",
    "sg:tags":[
        "searcher"
    ],
    "wof:name":"Barker M C",
    "wof:placetype":"venue"
},
  "geometry": {"coordinates":[144.991134644,-37.8928833008],"type":"Point"}
}