{
  "type": "Feature",
  "properties": {
    "iso:country":"AU",
    "sg:address":"2400 Plenty Rd",
    "sg:city":"Whittlesea",
    "sg:classifiers":[
        {
            "category":"Home & Garden",
            "subcategory":"Hardware",
            "type":"Retail Goods"
        }
    ],
    "sg:phone":"+61 3 9716 3499",
    "sg:postcode":"3757",
    "sg:province":"VIC",
    "sg:tags":[
        "plumber",
        "supply"
    ],
    "wof:name":"Reece Pty Ltd",
    "wof:placetype":"venue"
},
  "geometry": {"coordinates":[145.11398299999999,-37.518536],"type":"Point"}
}