{
  "type": "Feature",
  "properties": {
    "addr:full":"43a Dickson St Lambton NSW 2299",
    "addr:housenumber":"43a",
    "addr:postcode":"2299",
    "addr:street":"Dickson St",
    "iso:country":"AU",
    "sg:address":"43a Dickson St",
    "sg:city":"Lambton",
    "sg:classifiers":[
        {
            "category":"Shopping",
            "subcategory":"Pets & Pet Supplies",
            "type":"Retail Goods"
        }
    ],
    "sg:phone":"+61 2 4952 2489",
    "sg:postcode":"2299",
    "sg:province":"NSW",
    "sg:tags":[
        "equipment",
        "ceramic"
    ],
    "wof:name":"Lambton Ceramics Studio",
    "wof:placetype":"venue"
},
  "geometry": {"coordinates":[151.70884704599999,-32.9103279114],"type":"Point"}
}