{
  "type": "Feature",
  "properties": {
    "iso:country":"AU",
    "sg:address":"7a Tubber St",
    "sg:city":"Beaudesert",
    "sg:classifiers":[
        {
            "category":"Home & Garden",
            "subcategory":"Hardware",
            "type":"Retail Goods"
        }
    ],
    "sg:phone":"+61 416 269 181",
    "sg:postcode":"4285",
    "sg:province":"QLD",
    "sg:tags":[
        "compressor",
        "air"
    ],
    "wof:name":"Beaudesert Industrial Tool & Trade Supplies",
    "wof:placetype":"venue"
},
  "geometry": {"coordinates":[152.99624600000001,-27.983002],"type":"Point"}
}