{
  "type": "Feature",
  "properties": {
    "addr:full":"635 Magill Rd Magill SA 5072",
    "addr:housenumber":"635",
    "addr:postcode":"5072",
    "addr:street":"Magill Rd",
    "iso:country":"AU",
    "sg:address":"635 Magill Rd",
    "sg:city":"Magill",
    "sg:classifiers":[
        {
            "category":"Sports & Exercise",
            "subcategory":"Gym",
            "type":"Entertainment"
        }
    ],
    "sg:phone":"+61 8 8361 2111",
    "sg:postcode":"5072",
    "sg:province":"SA",
    "sg:tags":[
        "health",
        "fitness"
    ],
    "wof:name":"Enjoy Fitness",
    "wof:placetype":"venue"
},
  "geometry": {"coordinates":[138.677658081,-34.9127960205],"type":"Point"}
}