{
  "type": "Feature",
  "properties": {
    "addr:full":"9 Mango St Kununurra WA 6743",
    "addr:housenumber":"9",
    "addr:postcode":"6743",
    "addr:street":"Mango St",
    "iso:country":"AU",
    "sg:address":"9 Mango St",
    "sg:city":"Kununurra",
    "sg:classifiers":[
        {
            "category":"Home & Garden",
            "subcategory":"Building Materials",
            "type":"Retail Goods"
        }
    ],
    "sg:phone":"+61 8 9169 1411",
    "sg:postcode":"6743",
    "sg:province":"WA",
    "sg:tags":[
        "pre-mixed",
        "concrete"
    ],
    "wof:name":"Guerinoni & Son",
    "wof:placetype":"venue"
},
  "geometry": {"coordinates":[128.73936462399999,-15.7726697922],"type":"Point"}
}