{
  "type": "Feature",
  "properties": {
    "addr:full":"135 George St The Rocks Sydney NSW 2000",
    "addr:housenumber":"135",
    "addr:postcode":"2000",
    "addr:street":"George St",
    "iso:country":"AU",
    "sg:address":"135 George St",
    "sg:city":"The Rocks Sydney",
    "sg:classifiers":[
        {
            "category":"Restaurant",
            "type":"Food & Drink"
        }
    ],
    "sg:phone":"+61 2 9247 1920",
    "sg:postcode":"2000",
    "sg:province":"NSW",
    "wof:name":"Amo Roma Ristorante",
    "wof:placetype":"venue"
},
  "geometry": {"coordinates":[151.20843505900001,-33.8603897095],"type":"Point"}
}