{
  "type": "Feature",
  "properties": {
    "addr:full":"103 Thomas St Broken Hill NSW 2880",
    "addr:housenumber":"103",
    "addr:postcode":"2880",
    "addr:street":"Thomas St",
    "iso:country":"AU",
    "sg:address":"103 Thomas St",
    "sg:city":"Broken Hill",
    "sg:classifiers":[
        {
            "category":"Manufacturing",
            "subcategory":"Food",
            "type":"Manufacturing & Wholesale Goods"
        }
    ],
    "sg:phone":"+61 8 8087 2544",
    "sg:postcode":"2880",
    "sg:province":"NSW",
    "sg:tags":[
        "function",
        "catering"
    ],
    "wof:name":"Denley Butchers Pty Ltd",
    "wof:placetype":"venue"
},
  "geometry": {"coordinates":[141.44715881400001,-31.9533634186],"type":"Point"}
}