{
  "type": "Feature",
  "properties": {
    "addr:full":"245 Eastbourne Rd Rosebud VIC 3939",
    "addr:housenumber":"245",
    "addr:postcode":"3939",
    "addr:street":"Eastbourne Rd",
    "iso:country":"AU",
    "sg:address":"245 Eastbourne Rd",
    "sg:city":"Rosebud",
    "sg:classifiers":[
        {
            "category":"Education",
            "subcategory":"School",
            "type":"Public Place"
        }
    ],
    "sg:phone":"+61 3 5986 8595",
    "sg:postcode":"3939",
    "sg:province":"VIC",
    "sg:tags":[
        "state",
        "except",
        "nsw"
    ],
    "wof:name":"Rosebud Secondary College",
    "wof:placetype":"venue"
},
  "geometry": {"coordinates":[144.88751220699999,-38.3674888611],"type":"Point"}
}