{
  "type": "Feature",
  "properties": {
    "addr:full":"71 Main St West Wyalong NSW 2671",
    "addr:housenumber":"71",
    "addr:postcode":"2671",
    "addr:street":"Main St West",
    "iso:country":"AU",
    "sg:address":"71 Main St",
    "sg:city":"West Wyalong",
    "sg:classifiers":[
        {
            "category":"Autos & Motor Vehicles",
            "subcategory":"Auto Supplies",
            "type":"Retail Goods"
        }
    ],
    "sg:phone":"+61 2 6972 2595",
    "sg:postcode":"2671",
    "sg:province":"NSW",
    "sg:tags":[
        "accessory"
    ],
    "wof:name":"Autopro",
    "wof:placetype":"venue"
},
  "geometry": {"coordinates":[147.201416016,-33.9222717285],"type":"Point"}
}