{
  "type": "Feature",
  "properties": {
    "addr:full":"310 Oxley Hwy Port Macquarie NSW 2444",
    "addr:housenumber":"310",
    "addr:postcode":"2444",
    "addr:street":"Oxley Hwy",
    "iso:country":"AU",
    "sg:address":"310 Oxley Hwy",
    "sg:city":"Port Macquarie",
    "sg:classifiers":[
        {
            "category":"Building & Trades",
            "subcategory":"Pest Control",
            "type":"Services"
        }
    ],
    "sg:phone":"+61 412 653 786",
    "sg:postcode":"2444",
    "sg:province":"NSW",
    "wof:name":"The Port Pest Control Pty Ltd",
    "wof:placetype":"venue"
},
  "geometry": {"coordinates":[152.881561,-31.441662],"type":"Point"}
}