{
  "type": "Feature",
  "properties": {
    "iso:country":"AU",
    "sg:address":"78 Gardenvale Rd",
    "sg:city":"Elsternwick",
    "sg:classifiers":[
        {
            "category":"Retail",
            "subcategory":"Event Space",
            "type":"Services"
        }
    ],
    "sg:phone":"+61 3 9596 2529",
    "sg:postcode":"3185",
    "sg:province":"VIC",
    "sg:tags":[
        "venue",
        "reception",
        "wedding"
    ],
    "wof:name":"Lloloma Receptions",
    "wof:placetype":"venue"
},
  "geometry": {"coordinates":[145.010375977,-37.8980178833],"type":"Point"}
}