{
  "type": "Feature",
  "properties": {
    "addr:full":"313 St Georges Rd Thornbury VIC 3071",
    "addr:housenumber":"313",
    "addr:postcode":"3071",
    "addr:street":"St Georges Rd",
    "iso:country":"AU",
    "sg:address":"313 St Georges Rd",
    "sg:city":"Thornbury",
    "sg:classifiers":[
        {
            "category":"Social Services",
            "subcategory":"Child Care",
            "type":"Services"
        }
    ],
    "sg:phone":"+61 3 9416 9227",
    "sg:postcode":"3071",
    "sg:province":"VIC",
    "wof:name":"Merri Community Child Care Centre & Kindergarten",
    "wof:placetype":"venue"
},
  "geometry": {"coordinates":[144.99244689899999,-37.7611312866],"type":"Point"}
}