{
  "type": "Feature",
  "properties": {
    "addr:full":"462 Swan St Richmond VIC 3121",
    "addr:housenumber":"462",
    "addr:postcode":"3121",
    "addr:street":"Swan St",
    "iso:country":"AU",
    "sg:address":"462 Swan St",
    "sg:city":"Richmond",
    "sg:classifiers":[
        {
            "category":"Health Services",
            "subcategory":"Medical Lab",
            "type":"Services"
        }
    ],
    "sg:phone":"+61 3 9429 2692",
    "sg:postcode":"3121",
    "sg:province":"VIC",
    "sg:tags":[
        "laboratory",
        "dental"
    ],
    "wof:name":"N.G. Dental Laboratories",
    "wof:placetype":"venue"
},
  "geometry": {"coordinates":[145.00721740700001,-37.8267745972],"type":"Point"}
}