{
  "type": "Feature",
  "properties": {
    "iso:country":"AU",
    "sg:address":"PO Box 293",
    "sg:city":"Willunga",
    "sg:classifiers":[
        {
            "category":"Building & Trades",
            "subcategory":"Locksmith",
            "type":"Services"
        }
    ],
    "sg:phone":"+61 1800 644 774",
    "sg:postcode":"5172",
    "sg:province":"SA",
    "sg:tags":[
        "lock"
    ],
    "wof:name":"Keyhole Services",
    "wof:placetype":"venue"
},
  "geometry": {"coordinates":[138.57168579099999,-35.2866897583],"type":"Point"}
}