{
  "type": "Feature",
  "properties": {
    "addr:full":"PO Box 6 Wudinna SA 5652",
    "addr:postcode":"5652",
    "iso:country":"AU",
    "sg:address":"PO Box 6",
    "sg:city":"Wudinna",
    "sg:classifiers":[
        {
            "category":"Farming",
            "subcategory":"Farm & Veterinary Services",
            "type":"Manufacturing & Wholesale Goods"
        }
    ],
    "sg:phone":"+61 8 8680 2901",
    "sg:postcode":"5652",
    "sg:province":"SA",
    "sg:tags":[
        "agricultural",
        "advisory"
    ],
    "wof:name":"Elliston Le Hunte Animal & Plant",
    "wof:placetype":"venue"
},
  "geometry": {"coordinates":[135.460281372,-33.0488586426],"type":"Point"}
}