{
  "type": "Feature",
  "properties": {
    "addr:full":"Shp 1/ 91 Wallace St Braidwood NSW 2622",
    "addr:housenumber":"/ 91",
    "addr:postcode":"2622",
    "addr:street":"Wallace St",
    "iso:country":"AU",
    "sg:address":"Shp 1/ 91 Wallace St",
    "sg:city":"Braidwood",
    "sg:classifiers":[
        {
            "category":"Deli",
            "type":"Food & Drink"
        }
    ],
    "sg:phone":"+61 2 4842 1201",
    "sg:postcode":"2622",
    "sg:province":"NSW",
    "sg:tags":[
        "delicatessen"
    ],
    "wof:name":"Braidwood Deli The",
    "wof:placetype":"venue"
},
  "geometry": {"coordinates":[149.80113220199999,-35.4372062683],"type":"Point"}
}