{
  "type": "Feature",
  "properties": {
    "addr:full":"Level 2, 33 Colin St West Perth WA 6005",
    "addr:housenumber":"33",
    "addr:postcode":"6005",
    "addr:street":"Colin St",
    "iso:country":"AU",
    "sg:address":"Level 2, 33 Colin St",
    "sg:city":"West Perth",
    "sg:classifiers":[
        {
            "category":"Utilities",
            "subcategory":"Sewage",
            "type":"Services"
        }
    ],
    "sg:phone":"+61 8 9420 0300",
    "sg:postcode":"6005",
    "sg:province":"WA",
    "sg:tags":[
        "electricity",
        "retailer"
    ],
    "wof:name":"Perth Energy Pty Ltd",
    "wof:placetype":"venue"
},
  "geometry": {"coordinates":[115.841201782,-31.9504909515],"type":"Point"}
}