{
  "type": "Feature",
  "properties": {
    "iso:country":"AU",
    "sg:address":"91 Dixon Rd",
    "sg:city":"Rockingham",
    "sg:classifiers":[
        {
            "category":"Autos & Motor Vehicles",
            "subcategory":"Auto Supplies",
            "type":"Retail Goods"
        }
    ],
    "sg:phone":"+61 8 9592 1113",
    "sg:postcode":"6168",
    "sg:province":"WA",
    "sg:tags":[
        "part",
        "cycles",
        "accessory"
    ],
    "wof:name":"Kim Britton Kawasaki",
    "wof:placetype":"venue"
},
  "geometry": {"coordinates":[115.766037,-32.276848],"type":"Point"}
}