{
  "type": "Feature",
  "properties": {
    "addr:full":"3 Weld Rd Palmyra WA 6157",
    "addr:housenumber":"3",
    "addr:postcode":"6157",
    "addr:street":"Weld Rd",
    "iso:country":"AU",
    "sg:address":"3 Weld Rd",
    "sg:city":"Palmyra",
    "sg:classifiers":[
        {
            "category":"Professional",
            "subcategory":"Computer Services",
            "type":"Services"
        }
    ],
    "sg:phone":"+61 8 9339 3111",
    "sg:postcode":"6157",
    "sg:province":"WA",
    "sg:tags":[
        "training"
    ],
    "wof:name":"Computer TeleVision",
    "wof:placetype":"venue"
},
  "geometry": {"coordinates":[115.788483,-32.038643],"type":"Point"}
}