{
  "type": "Feature",
  "properties": {
    "iso:country":"AU",
    "sg:address":"520 Camberwell Rd",
    "sg:city":"Camberwell",
    "sg:classifiers":[
        {
            "category":"Home & Garden",
            "subcategory":"Carpets & Floor Coverings",
            "type":"Retail Goods"
        }
    ],
    "sg:phone":"+61 3 9809 0711",
    "sg:postcode":"3124",
    "sg:province":"VIC",
    "sg:tags":[
        "flooring",
        "parquet"
    ],
    "wof:name":"The Floor Studio",
    "wof:placetype":"venue"
},
  "geometry": {"coordinates":[145.069091797,-37.8423728943],"type":"Point"}
}