{
  "type": "Feature",
  "properties": {
    "addr:full":"Shop 4/ 25 Morayfield Rd Caboolture QLD 4510",
    "addr:housenumber":"shop 4 / 25",
    "addr:postcode":"4510",
    "addr:street":"Morayfield Rd",
    "iso:country":"AU",
    "sg:address":"Shop 4/ 25 Morayfield Rd",
    "sg:city":"Caboolture",
    "sg:classifiers":[
        {
            "category":"Personal",
            "subcategory":"Beauty Salon",
            "type":"Services"
        }
    ],
    "sg:phone":"+61 7 5495 5909",
    "sg:postcode":"4510",
    "sg:province":"QLD",
    "sg:tags":[
        "hairdresser"
    ],
    "wof:name":"Shear Technique Hairdressers",
    "wof:placetype":"venue"
},
  "geometry": {"coordinates":[152.95013399999999,-27.092611],"type":"Point"}
}