{
  "type": "Feature",
  "properties": {
    "addr:full":"Gibbney Reserve Queen St Maylands WA 6051",
    "addr:postcode":"6051",
    "addr:street":"Queen St",
    "iso:country":"AU",
    "sg:address":"Gibbney Reserve Queen St",
    "sg:city":"Maylands",
    "sg:classifiers":[
        {
            "category":"Arena",
            "subcategory":"Sports Club",
            "type":"Entertainment"
        }
    ],
    "sg:phone":"+61 8 9271 7677",
    "sg:postcode":"6051",
    "sg:province":"WA",
    "sg:tags":[
        "organisation",
        "sporting"
    ],
    "wof:name":"Junior Soccer Association Of WA (Inc)",
    "wof:placetype":"venue"
},
  "geometry": {"coordinates":[115.90593,-31.933565],"type":"Point"}
}