{
  "type": "Feature",
  "properties": {
    "iso:country":"AU",
    "sg:address":"126 Market St",
    "sg:city":"Mudgee",
    "sg:classifiers":[
        {
            "category":"Museum",
            "type":"Entertainment"
        }
    ],
    "sg:phone":"+61 2 6372 7395",
    "sg:postcode":"2850",
    "sg:province":"NSW",
    "wof:name":"Mudgee Museum",
    "wof:placetype":"venue"
},
  "geometry": {"coordinates":[149.578033,-32.589558],"type":"Point"}
}