{
  "type": "Feature",
  "properties": {
    "iso:country":"AU",
    "sg:address":"Cnr Celebration Drv & Windsor Rd",
    "sg:city":"Bella Vista",
    "sg:classifiers":[
        {
            "category":"Wholesale",
            "subcategory":"Painting Supplies",
            "type":"Manufacturing & Wholesale Goods"
        }
    ],
    "sg:phone":"+61 2 8814 6500",
    "sg:postcode":"2153",
    "sg:province":"NSW",
    "sg:tags":[
        "painter"
    ],
    "wof:name":"Wattyl",
    "wof:placetype":"venue"
},
  "geometry": {"coordinates":[150.97261047399999,-33.7338066101],"type":"Point"}
}