{
  "type": "Feature",
  "properties": {
    "iso:country":"AU",
    "sg:address":"42 Nobility St",
    "sg:city":"Moolap",
    "sg:classifiers":[
        {
            "category":"Building & Trades",
            "subcategory":"Construction",
            "type":"Services"
        }
    ],
    "sg:phone":"+61 3 5248 6777",
    "sg:postcode":"3221",
    "sg:province":"VIC",
    "sg:tags":[
        "plasterboard",
        "plasterer",
        "fixer"
    ],
    "wof:name":"M & B Grace",
    "wof:placetype":"venue"
},
  "geometry": {"coordinates":[144.41099500000001,-38.166718],"type":"Point"}
}