{
  "type": "Feature",
  "properties": {
    "iso:country":"AU",
    "sg:address":"631- 635 George St",
    "sg:city":"Sydney",
    "sg:classifiers":[
        {
            "category":"Travel",
            "subcategory":"Hotels & Motels",
            "type":"Entertainment"
        }
    ],
    "sg:phone":"+61 2 9265 8888",
    "sg:postcode":"2000",
    "sg:province":"NSW",
    "sg:tags":[
        "accommodation"
    ],
    "sg:website":"http://www.eighthotels.com",
    "wof:name":"The Pensione Hotel",
    "wof:placetype":"venue"
},
  "geometry": {"coordinates":[151.205474853,-33.8784217834],"type":"Point"}
}