{
  "type": "Feature",
  "properties": {
    "addr:full":"Mildura Airport Mildura VIC 3500",
    "addr:postcode":"3500",
    "iso:country":"AU",
    "sg:address":"Mildura Airport",
    "sg:city":"Mildura",
    "sg:classifiers":[
        {
            "category":"Airline",
            "type":"Transportation"
        }
    ],
    "sg:phone":"+61 3 5021 2225",
    "sg:postcode":"3500",
    "sg:province":"VIC",
    "sg:tags":[
        "aircraft",
        "rental",
        "charter"
    ],
    "wof:name":"Cobden Air",
    "wof:placetype":"venue"
},
  "geometry": {"coordinates":[142.14866638199999,-34.1853637695],"type":"Point"}
}