{
  "type": "Feature",
  "properties": {
    "addr:full":"5 Bath La Bendigo VIC 3550",
    "addr:housenumber":"5",
    "addr:postcode":"3550",
    "addr:street":"Bath La",
    "iso:country":"AU",
    "sg:address":"5 Bath La",
    "sg:city":"Bendigo",
    "sg:classifiers":[
        {
            "category":"Shopping",
            "subcategory":"Bridal",
            "type":"Retail Goods"
        }
    ],
    "sg:phone":"+61 3 5444 5095",
    "sg:postcode":"3550",
    "sg:province":"VIC",
    "sg:tags":[
        "hire",
        "wear"
    ],
    "wof:name":"Buds Flowers, Pots & Things",
    "wof:placetype":"venue"
},
  "geometry": {"coordinates":[144.27897644000001,-36.7603683472],"type":"Point"}
}