{
  "type": "Feature",
  "properties": {
    "addr:full":"488 Main Rd Montrose TAS 7010",
    "addr:housenumber":"488",
    "addr:postcode":"7010",
    "addr:street":"Main Rd",
    "iso:country":"AU",
    "sg:address":"488 Main Rd",
    "sg:city":"Montrose",
    "sg:classifiers":[
        {
            "category":"Retail",
            "subcategory":"Veterinary Services",
            "type":"Services"
        }
    ],
    "sg:phone":"+61 3 6272 3599",
    "sg:postcode":"7010",
    "sg:province":"TAS",
    "sg:tags":[
        "surgeon"
    ],
    "wof:name":"Burch Fiona",
    "wof:placetype":"venue"
},
  "geometry": {"coordinates":[147.26632690400001,-42.8262672424],"type":"Point"}
}