{
  "type": "Feature",
  "properties": {
    "addr:full":"272 Foreshore Drv Geraldton WA 6530",
    "addr:housenumber":"272",
    "addr:postcode":"6530",
    "addr:street":"Foreshore Drv",
    "iso:country":"AU",
    "sg:address":"272 Foreshore Drv",
    "sg:city":"Geraldton",
    "sg:classifiers":[
        {
            "category":"Professional",
            "subcategory":"Business Services",
            "type":"Services"
        }
    ],
    "sg:phone":"+61 8 9964 1882",
    "sg:postcode":"6530",
    "sg:province":"WA",
    "sg:tags":[
        "drafting"
    ],
    "wof:name":"Peter Teakle & Co",
    "wof:placetype":"venue"
},
  "geometry": {"coordinates":[114.613059998,-28.7681484222],"type":"Point"}
}