{
  "type": "Feature",
  "properties": {
    "iso:country":"AU",
    "sg:address":"Lloyd St",
    "sg:city":"Strathmore",
    "sg:classifiers":[
        {
            "category":"Education",
            "subcategory":"School",
            "type":"Public Place"
        }
    ],
    "sg:phone":"+61 3 9379 3991",
    "sg:postcode":"3041",
    "sg:province":"VIC",
    "sg:tags":[
        "state",
        "except",
        "nsw"
    ],
    "wof:name":"Strathmore Primary",
    "wof:placetype":"venue"
},
  "geometry": {"coordinates":[144.91679382300001,-37.7355194092],"type":"Point"}
}