{
  "type": "Feature",
  "properties": {
    "iso:country":"AU",
    "sg:address":"8/52 MacDonald St",
    "sg:city":"Lakemba",
    "sg:classifiers":[
        {
            "category":"Manufacturing",
            "subcategory":"Metals",
            "type":"Manufacturing & Wholesale Goods"
        }
    ],
    "sg:phone":"+61 2 9750 7579",
    "sg:postcode":"2195",
    "sg:province":"NSW",
    "sg:tags":[
        "merchant"
    ],
    "wof:name":"Deen Corparation Private Ltd",
    "wof:placetype":"venue"
},
  "geometry": {"coordinates":[151.07148699999999,-33.915668],"type":"Point"}
}