{
  "type": "Feature",
  "properties": {
    "iso:country":"AU",
    "sg:address":"19 Darcy La",
    "sg:city":"West Kalgoorlie",
    "sg:classifiers":[
        {
            "category":"Wholesale",
            "subcategory":"Machinery & Supplies",
            "type":"Manufacturing & Wholesale Goods"
        }
    ],
    "sg:phone":"+61 8 9091 4277",
    "sg:postcode":"6430",
    "sg:province":"WA",
    "sg:tags":[
        "bearing",
        "bushing"
    ],
    "wof:name":"SKF Bearing Supplies Pty Ltd",
    "wof:placetype":"venue"
},
  "geometry": {"coordinates":[121.434959412,-30.7795658112],"type":"Point"}
}