{
  "type": "Feature",
  "properties": {
    "addr:full":"8/ 144 Brisbane Rd Mooloolaba QLD 4557",
    "addr:housenumber":"/ 144",
    "addr:postcode":"4557",
    "addr:street":"Brisbane Rd",
    "iso:country":"AU",
    "sg:address":"8/ 144 Brisbane Rd",
    "sg:city":"Mooloolaba",
    "sg:classifiers":[
        {
            "category":"Building & Trades",
            "subcategory":"Construction",
            "type":"Services"
        }
    ],
    "sg:phone":"+61 7 5477 7188",
    "sg:postcode":"4557",
    "sg:province":"QLD",
    "sg:tags":[
        "pool",
        "swimming"
    ],
    "wof:name":"Aquablue Pool Services",
    "wof:placetype":"venue"
},
  "geometry": {"coordinates":[153.11491394000001,-26.6900978088],"type":"Point"}
}