{
  "type": "Feature",
  "properties": {
    "addr:full":"9 Woodpine Crt Ballajura WA 6066",
    "addr:housenumber":"9",
    "addr:postcode":"6066",
    "addr:street":"Woodpine Crt",
    "iso:country":"AU",
    "sg:address":"9 Woodpine Crt",
    "sg:city":"Ballajura",
    "sg:classifiers":[
        {
            "category":"Utilities",
            "subcategory":"Refuse",
            "type":"Services"
        }
    ],
    "sg:phone":"+61 8 9249 1093",
    "sg:postcode":"6066",
    "sg:province":"WA",
    "sg:tags":[
        "remover",
        "rubbish"
    ],
    "wof:name":"Sunshine Garden Bags",
    "wof:placetype":"venue"
},
  "geometry": {"coordinates":[115.889129639,-31.8288249969],"type":"Point"}
}