{
  "type": "Feature",
  "properties": {
    "iso:country":"AU",
    "sg:address":"7 Cavallaro Ave",
    "sg:city":"Earlville",
    "sg:classifiers":[
        {
            "category":"Building & Trades",
            "subcategory":"Plumbing",
            "type":"Services"
        }
    ],
    "sg:phone":"+61 412 710 710",
    "sg:postcode":"4870",
    "sg:province":"QLD",
    "sg:tags":[
        "plumber",
        "gasfitters"
    ],
    "wof:name":"Leightonmac Plumbers",
    "wof:placetype":"venue"
},
  "geometry": {"coordinates":[145.741943359,-16.945482254],"type":"Point"}
}