{
  "type": "Feature",
  "properties": {
    "addr:full":"59 Ash Drv Kingston TAS 7050",
    "addr:housenumber":"59",
    "addr:postcode":"7050",
    "addr:street":"Ash Drv",
    "iso:country":"AU",
    "sg:address":"59 Ash Drv",
    "sg:city":"Kingston",
    "sg:classifiers":[
        {
            "category":"Professional",
            "subcategory":"Art Services",
            "type":"Services"
        }
    ],
    "sg:phone":"+61 3 6229 3821",
    "sg:postcode":"7050",
    "sg:province":"TAS",
    "sg:tags":[
        "graphic",
        "designer"
    ],
    "wof:name":"Visual Directions Tasmania",
    "wof:placetype":"venue"
},
  "geometry": {"coordinates":[147.309586,-42.991955],"type":"Point"}
}