{
  "type": "Feature",
  "properties": {
    "addr:full":"3 Wattle Crt Traralgon VIC 3844",
    "addr:housenumber":"3",
    "addr:postcode":"3844",
    "addr:street":"Wattle Crt",
    "iso:country":"AU",
    "sg:address":"3 Wattle Crt",
    "sg:city":"Traralgon",
    "sg:classifiers":[
        {
            "category":"Building & Trades",
            "subcategory":"Construction",
            "type":"Services"
        }
    ],
    "sg:phone":"+61 3 5176 6634",
    "sg:postcode":"3844",
    "sg:province":"VIC",
    "sg:tags":[
        "contractor"
    ],
    "wof:name":"RJ Jennings Constructions",
    "wof:placetype":"venue"
},
  "geometry": {"coordinates":[146.51832580600001,-38.2056045532],"type":"Point"}
}