{
  "type": "Feature",
  "properties": {
    "iso:country":"AU",
    "sg:address":"64 Sunnyside Crs",
    "sg:city":"Wattle Glen",
    "sg:phone":"+61 3 9438 4300",
    "sg:postcode":"3096",
    "sg:province":"VIC",
    "wof:name":"D.E. Glass",
    "wof:placetype":"venue"
},
  "geometry": {"coordinates":[145.18870544399999,-37.669921875],"type":"Point"}
}