{
  "type": "Feature",
  "properties": {
    "iso:country":"AU",
    "sg:address":"1962 Toodyay Rd",
    "sg:city":"Gidgegannup",
    "sg:classifiers":[
        {
            "category":"Retail",
            "subcategory":"Veterinary Services",
            "type":"Services"
        }
    ],
    "sg:phone":"+61 8 9574 6262",
    "sg:postcode":"6083",
    "sg:province":"WA",
    "sg:tags":[
        "surgeon"
    ],
    "wof:name":"Gidgegannup Veterinary Clinic",
    "wof:placetype":"venue"
},
  "geometry": {"coordinates":[116.196907044,-31.792766571],"type":"Point"}
}