{
  "type": "Feature",
  "properties": {
    "addr:full":"Unit 4/ 3 Ramly Drv Burleigh Heads QLD 4220",
    "addr:housenumber":"3",
    "addr:postcode":"4220",
    "addr:street":"Ramly Drv",
    "iso:country":"AU",
    "sg:address":"Unit 4/ 3 Ramly Drv",
    "sg:city":"Burleigh Heads",
    "sg:classifiers":[
        {
            "category":"Retail",
            "subcategory":"Repair Shop",
            "type":"Services"
        }
    ],
    "sg:phone":"+61 403 295 030",
    "sg:postcode":"4220",
    "sg:province":"QLD",
    "sg:tags":[
        "upholsterer"
    ],
    "wof:name":"JCF Designs",
    "wof:placetype":"venue"
},
  "geometry": {"coordinates":[153.43400573700001,-28.1029205322],"type":"Point"}
}