{
  "type": "Feature",
  "properties": {
    "iso:country":"AU",
    "sg:address":"Unit 2 & 3 Hawker Pl",
    "sg:city":"Hawker",
    "sg:classifiers":[
        {
            "category":"Health Services",
            "subcategory":"Doctor",
            "type":"Services"
        }
    ],
    "sg:phone":"+61 2 6255 2400",
    "sg:postcode":"2614",
    "sg:province":"ACT",
    "sg:tags":[
        "medical",
        "practitioner"
    ],
    "wof:name":"Mya Joanna",
    "wof:placetype":"venue"
},
  "geometry": {"coordinates":[149.045166016,-35.2431373596],"type":"Point"}
}