{
  "type": "Feature",
  "properties": {
    "addr:full":"29 Chaffers St Boulder WA 6432",
    "addr:housenumber":"29",
    "addr:postcode":"6432",
    "addr:street":"Chaffers St",
    "iso:country":"AU",
    "sg:address":"29 Chaffers St",
    "sg:city":"Boulder",
    "sg:classifiers":[
        {
            "category":"Professional",
            "subcategory":"Art Services",
            "type":"Services"
        }
    ],
    "sg:phone":"+61 8 9093 3372",
    "sg:postcode":"6432",
    "sg:province":"WA",
    "sg:tags":[
        "decorator",
        "painter"
    ],
    "wof:name":"Programmed Maintenance Services",
    "wof:placetype":"venue"
},
  "geometry": {"coordinates":[121.496322632,-30.7930145264],"type":"Point"}
}