{
  "type": "Feature",
  "properties": {
    "addr:full":"77 Edwardes St Reservoir VIC 3073",
    "addr:housenumber":"77",
    "addr:postcode":"3073",
    "addr:street":"Edwardes St",
    "iso:country":"AU",
    "sg:address":"77 Edwardes St",
    "sg:city":"Reservoir",
    "sg:classifiers":[
        {
            "category":"Health Services",
            "subcategory":"Dentist",
            "type":"Services"
        }
    ],
    "sg:phone":"+61 3 9462 3000",
    "sg:postcode":"3073",
    "sg:province":"VIC",
    "sg:tags":[
        "dental",
        "prosthetist"
    ],
    "wof:name":"(Paul Werner) Denture Clinic",
    "wof:placetype":"venue"
},
  "geometry": {"coordinates":[145.0025177,-37.7159767151],"type":"Point"}
}