{
  "type": "Feature",
  "properties": {
    "addr:full":"57 Portman St Oakleigh VIC 3166",
    "addr:housenumber":"57",
    "addr:postcode":"3166",
    "addr:street":"Portman St",
    "iso:country":"AU",
    "sg:address":"57 Portman St",
    "sg:city":"Oakleigh",
    "sg:classifiers":[
        {
            "category":"Shopping",
            "subcategory":"Bridal",
            "type":"Retail Goods"
        }
    ],
    "sg:phone":"+61 3 9568 0511",
    "sg:postcode":"3166",
    "sg:province":"VIC",
    "sg:tags":[
        "hire",
        "wear"
    ],
    "wof:name":"Nifi Bridal",
    "wof:placetype":"venue"
},
  "geometry": {"coordinates":[145.09175109899999,-37.9001617432],"type":"Point"}
}