{
  "type": "Feature",
  "properties": {
    "addr:full":"Suite 103/ 515 Kent St Sydney NSW 2000",
    "addr:housenumber":"/ 515",
    "addr:postcode":"2000",
    "addr:street":"Kent St",
    "iso:country":"AU",
    "sg:address":"Suite 103/ 515 Kent St",
    "sg:city":"Sydney",
    "sg:classifiers":[
        {
            "category":"Professional",
            "subcategory":"Employment Agencies",
            "type":"Services"
        }
    ],
    "sg:phone":"+61 2 9264 6920",
    "sg:postcode":"2000",
    "sg:province":"NSW",
    "wof:name":"Media NetWork & Personnel",
    "wof:placetype":"venue"
},
  "geometry": {"coordinates":[151.205169678,-33.8747024536],"type":"Point"}
}