{
  "type": "Feature",
  "properties": {
    "addr:full":"18 Turner Drv Warrnambool VIC 3280",
    "addr:housenumber":"18",
    "addr:postcode":"3280",
    "addr:street":"Turner Drv",
    "iso:country":"AU",
    "sg:address":"18 Turner Drv",
    "sg:city":"Warrnambool",
    "sg:classifiers":[
        {
            "category":"Building & Trades",
            "subcategory":"Construction",
            "type":"Services"
        }
    ],
    "sg:phone":"+61 419 506 816",
    "sg:postcode":"3280",
    "sg:province":"VIC",
    "sg:tags":[
        "scaffolding"
    ],
    "wof:name":"Sky High Scaffolding",
    "wof:placetype":"venue"
},
  "geometry": {"coordinates":[142.495925903,-38.3609962463],"type":"Point"}
}