{
  "type": "Feature",
  "properties": {
    "addr:full":"336 Great Eastern Hwy Midland WA 6056",
    "addr:housenumber":"336",
    "addr:postcode":"6056",
    "addr:street":"Great Eastern Hwy",
    "iso:country":"AU",
    "sg:address":"336 Great Eastern Hwy",
    "sg:city":"Midland",
    "sg:classifiers":[
        {
            "category":"Shopping",
            "subcategory":"Mobile Phones",
            "type":"Retail Goods"
        }
    ],
    "sg:phone":"+61 8 9250 2402",
    "sg:postcode":"6056",
    "sg:province":"WA",
    "sg:tags":[
        "telephone",
        "accessory"
    ],
    "wof:name":"Strathfield",
    "wof:placetype":"venue"
},
  "geometry": {"coordinates":[116.012512207,-31.8918266296],"type":"Point"}
}