{
  "type": "Feature",
  "properties": {
    "addr:full":"33 Archer St Carlisle WA 6101",
    "addr:housenumber":"33",
    "addr:postcode":"6101",
    "addr:street":"Archer St",
    "iso:country":"AU",
    "sg:address":"33 Archer St",
    "sg:city":"Carlisle",
    "sg:classifiers":[
        {
            "category":"Building & Trades",
            "subcategory":"Construction",
            "type":"Services"
        }
    ],
    "sg:phone":"+61 8 9472 1766",
    "sg:postcode":"6101",
    "sg:province":"WA",
    "sg:tags":[
        "contractor"
    ],
    "wof:name":"Dalcon Construction Pty Ltd",
    "wof:placetype":"venue"
},
  "geometry": {"coordinates":[115.911720276,-31.9776172638],"type":"Point"}
}