{
  "type": "Feature",
  "properties": {
    "addr:full":"199 Ferntree Gully Rd Mt Waverley VIC 3149",
    "addr:housenumber":"199",
    "addr:postcode":"3149",
    "addr:street":"Ferntree Gully Rd",
    "iso:country":"AU",
    "sg:address":"199 Ferntree Gully Rd",
    "sg:city":"Mt Waverley",
    "sg:classifiers":[
        {
            "category":"Professional",
            "subcategory":"Computer Services",
            "type":"Services"
        }
    ],
    "sg:phone":"+61 3 9562 6992",
    "sg:postcode":"3149",
    "sg:province":"VIC",
    "sg:tags":[
        "repairs",
        "upgrade",
        "equipment"
    ],
    "wof:name":"Allied Computer Solutions",
    "wof:placetype":"venue"
},
  "geometry": {"coordinates":[145.12037658700001,-37.8982620239],"type":"Point"}
}