{
  "type": "Feature",
  "properties": {
    "iso:country":"AU",
    "sg:address":"PO Box 152",
    "sg:city":"Mortlake",
    "sg:classifiers":[
        {
            "category":"Education",
            "subcategory":"Special Training",
            "type":"Public Place"
        }
    ],
    "sg:phone":"+61 3 5567 1108",
    "sg:postcode":"3272",
    "sg:province":"VIC",
    "sg:tags":[
        "development"
    ],
    "wof:name":"Higgins Plant Operator Training & Assessment",
    "wof:placetype":"venue"
},
  "geometry": {"coordinates":[142.80844116200001,-38.0809707642],"type":"Point"}
}