{
  "type": "Feature",
  "properties": {
    "iso:country":"AU",
    "sg:address":"U1a/ 27 Truganina Rd",
    "sg:city":"Malaga",
    "sg:classifiers":[
        {
            "category":"Home & Garden",
            "subcategory":"Hardware",
            "type":"Retail Goods"
        }
    ],
    "sg:phone":"+61 8 9249 8934",
    "sg:postcode":"6090",
    "sg:province":"WA",
    "sg:tags":[
        "supply",
        "maker",
        "cabinet"
    ],
    "wof:name":"Midtown Intl Trading Pty Ltd",
    "wof:placetype":"venue"
},
  "geometry": {"coordinates":[115.885536194,-31.8639278412],"type":"Point"}
}