{
  "type": "Feature",
  "properties": {
    "iso:country":"AU",
    "sg:address":"21 Strathmore Rd",
    "sg:city":"Caves Beach",
    "sg:classifiers":[
        {
            "category":"Wholesale",
            "subcategory":"Machinery & Supplies",
            "type":"Manufacturing & Wholesale Goods"
        }
    ],
    "sg:phone":"+61 2 4971 2561",
    "sg:postcode":"2281",
    "sg:province":"NSW",
    "sg:tags":[
        "chemist"
    ],
    "wof:name":"Just-Ess Fundraising",
    "wof:placetype":"venue"
},
  "geometry": {"coordinates":[151.6378479,-33.0987052917],"type":"Point"}
}