{
  "type": "Feature",
  "properties": {
    "addr:full":"24 Palmerston Rd (West) Ringwood VIC 3134",
    "addr:housenumber":"24",
    "addr:postcode":"3134",
    "addr:street":"Palmerston Rd West",
    "iso:country":"AU",
    "sg:address":"24 Palmerston Rd",
    "sg:city":"(West) Ringwood",
    "sg:classifiers":[
        {
            "category":"Utilities",
            "subcategory":"Electric",
            "type":"Services"
        }
    ],
    "sg:phone":"+61 3 9845 8300",
    "sg:postcode":"3134",
    "sg:province":"VIC",
    "sg:tags":[
        "element"
    ],
    "wof:name":"Stokes Synertec Ltd",
    "wof:placetype":"venue"
},
  "geometry": {"coordinates":[145.21505737300001,-37.8253250122],"type":"Point"}
}