{
  "type": "Feature",
  "properties": {
    "addr:full":"Unit 1/ 21 Expansion St Molendinar QLD 4214",
    "addr:housenumber":"21",
    "addr:postcode":"4214",
    "addr:street":"Expansion St",
    "iso:country":"AU",
    "sg:address":"Unit 1/ 21 Expansion St",
    "sg:city":"Molendinar",
    "sg:classifiers":[
        {
            "category":"Professional",
            "type":"Services"
        }
    ],
    "sg:phone":"+61 7 5564 5455",
    "sg:postcode":"4214",
    "sg:province":"QLD",
    "sg:tags":[
        "spray",
        "painting"
    ],
    "wof:name":"Lacquer Factory",
    "wof:placetype":"venue"
},
  "geometry": {"coordinates":[153.356369019,-27.9769554138],"type":"Point"}
}