{
  "type": "Feature",
  "properties": {
    "addr:full":"57 Wayo St Goulburn NSW 2580",
    "addr:housenumber":"57",
    "addr:postcode":"2580",
    "addr:street":"Wayo St",
    "iso:country":"AU",
    "sg:address":"57 Wayo St",
    "sg:city":"Goulburn",
    "sg:classifiers":[
        {
            "category":"Utilities",
            "subcategory":"Recycling",
            "type":"Services"
        }
    ],
    "sg:phone":"+61 2 4828 5800",
    "sg:postcode":"2580",
    "sg:province":"NSW",
    "wof:name":"Smorgon Steel Recycling",
    "wof:placetype":"venue"
},
  "geometry": {"coordinates":[149.73733520499999,-34.7399139404],"type":"Point"}
}