{
  "type": "Feature",
  "properties": {
    "addr:full":"Unit-3, 17 Premier Cct Warana QLD 4575",
    "addr:housenumber":"17",
    "addr:postcode":"4575",
    "addr:street":"Premier Cct",
    "iso:country":"AU",
    "sg:address":"Unit-3, 17",
    "sg:city":"Premier Cct Warana",
    "sg:classifiers":[
        {
            "category":"Manufacturing",
            "subcategory":"Building Materials",
            "type":"Manufacturing & Wholesale Goods"
        }
    ],
    "sg:phone":"+61 7 5493 8380",
    "sg:postcode":"4575",
    "sg:province":"QLD",
    "sg:tags":[
        "adhesive",
        "tape"
    ],
    "wof:name":"Printatape Pty Ltd",
    "wof:placetype":"venue"
},
  "geometry": {"coordinates":[153.13076799999999,-26.719839],"type":"Point"}
}