{
  "type": "Feature",
  "properties": {
    "addr:full":"22 Diane St Mornington VIC 3931",
    "addr:housenumber":"22",
    "addr:postcode":"3931",
    "addr:street":"Diane St",
    "iso:country":"AU",
    "sg:address":"22 Diane St",
    "sg:city":"Mornington",
    "sg:classifiers":[
        {
            "category":"Shopping",
            "subcategory":"Discount & Variety Stores",
            "type":"Retail Goods"
        }
    ],
    "sg:phone":"+61 1300 851 661",
    "sg:postcode":"3931",
    "sg:province":"VIC",
    "sg:tags":[
        "shop",
        "adult"
    ],
    "wof:name":"Adult Indulgence",
    "wof:placetype":"venue"
},
  "geometry": {"coordinates":[145.049118042,-38.2330627441],"type":"Point"}
}