{
  "type": "Feature",
  "properties": {
    "addr:full":"Bay Rd (Cnr Yells Rd) Moorak Mt Gambier SA 5290",
    "addr:postcode":"5290",
    "addr:street":"Bay Rd Cnr Yells Rd",
    "iso:country":"AU",
    "sg:address":"Bay Rd",
    "sg:city":"(Cnr Yells Rd) Moorak Mt Gambier",
    "sg:classifiers":[
        {
            "category":"Retail",
            "subcategory":"Storage",
            "type":"Services"
        }
    ],
    "sg:phone":"+61 8 8726 8055",
    "sg:postcode":"5290",
    "sg:province":"SA",
    "sg:tags":[
        "removal",
        "furniture"
    ],
    "wof:name":"Jacobs Removals",
    "wof:placetype":"venue"
},
  "geometry": {"coordinates":[140.780563,-37.828697],"type":"Point"}
}