{
  "type": "Feature",
  "properties": {
    "addr:full":"U1/ 61 Mcdonald St Osborne Park WA 6017",
    "addr:housenumber":"61",
    "addr:postcode":"6017",
    "addr:street":"U1 /;Mcdonald St",
    "iso:country":"AU",
    "sg:address":"U1/ 61 Mcdonald St",
    "sg:city":"Osborne Park",
    "sg:classifiers":[
        {
            "category":"Building & Trades",
            "subcategory":"Construction",
            "type":"Services"
        }
    ],
    "sg:phone":"+61 8 9444 2888",
    "sg:postcode":"6017",
    "sg:province":"WA",
    "sg:tags":[
        "stonework",
        "stone",
        "mason"
    ],
    "wof:name":"Andes Stonework Pty Ltd",
    "wof:placetype":"venue"
},
  "geometry": {"coordinates":[115.824783325,-31.905834198],"type":"Point"}
}