{
  "type": "Feature",
  "properties": {
    "addr:full":"Suite 3, Cnsultng Rooms Geelong Private Hospital, Argyle St Geelong VIC 3220",
    "addr:postcode":"3220",
    "addr:street":"Argyle St",
    "iso:country":"AU",
    "sg:address":"Suite 3, Cnsultng Rooms Geelong Private Hospital, Argyle St",
    "sg:city":"Geelong",
    "sg:classifiers":[
        {
            "category":"Health Services",
            "subcategory":"Doctor",
            "type":"Services"
        }
    ],
    "sg:phone":"+61 3 5226 1866",
    "sg:postcode":"3220",
    "sg:province":"VIC",
    "sg:tags":[
        "medical",
        "practitioner"
    ],
    "wof:name":"Mander Alastair Dr",
    "wof:placetype":"venue"
},
  "geometry": {"coordinates":[144.36341899999999,-38.15097],"type":"Point"}
}