{
  "type": "Feature",
  "properties": {
    "iso:country":"AU",
    "sg:address":"36 Bent St",
    "sg:city":"South Grafton",
    "sg:classifiers":[
        {
            "category":"Home & Garden",
            "subcategory":"Furniture",
            "type":"Retail Goods"
        }
    ],
    "sg:phone":"+61 2 6643 1179",
    "sg:postcode":"2460",
    "sg:province":"NSW",
    "sg:tags":[
        "repair",
        "restoration"
    ],
    "wof:name":"Roy's The Boy",
    "wof:placetype":"venue"
},
  "geometry": {"coordinates":[152.94108581500001,-29.702911377],"type":"Point"}
}