{
  "type": "Feature",
  "properties": {
    "addr:full":"22 Gawler Pl Coomera QLD 4209",
    "addr:housenumber":"22",
    "addr:postcode":"4209",
    "addr:street":"Gawler Pl",
    "iso:country":"AU",
    "sg:address":"22 Gawler Pl",
    "sg:city":"Coomera",
    "sg:classifiers":[
        {
            "category":"Education",
            "subcategory":"Music School",
            "type":"Public Place"
        }
    ],
    "sg:phone":"+61 413 949 905",
    "sg:postcode":"4209",
    "sg:province":"QLD",
    "sg:tags":[
        "teacher"
    ],
    "wof:name":"Coomera Music School",
    "wof:placetype":"venue"
},
  "geometry": {"coordinates":[153.28607177699999,-27.899728775],"type":"Point"}
}