{
  "type": "Feature",
  "properties": {
    "iso:country":"AU",
    "sg:address":"56 Frankel St",
    "sg:city":"Carey Park",
    "sg:classifiers":[
        {
            "category":"Food & Beverages",
            "subcategory":"Liquor & Beverages",
            "type":"Retail Goods"
        }
    ],
    "sg:phone":"+61 8 9721 3383",
    "sg:postcode":"6230",
    "sg:province":"WA",
    "sg:tags":[
        "store"
    ],
    "wof:name":"Knox",
    "wof:placetype":"venue"
},
  "geometry": {"coordinates":[115.648178,-33.349167],"type":"Point"}
}