{
  "type": "Feature",
  "properties": {
    "addr:full":"Treetops Plaza Cnr Bermuda St & Reedy Ck Rd Burleigh Waters QLD 4220",
    "addr:postcode":"4220",
    "addr:street":"Cnr Bermuda St &;Ck Rd",
    "iso:country":"AU",
    "sg:address":"Treetops Plaza Cnr Bermuda St & Reedy Ck Rd",
    "sg:city":"Burleigh Waters",
    "sg:classifiers":[
        {
            "category":"Food & Beverages",
            "subcategory":"Bakery",
            "type":"Retail Goods"
        }
    ],
    "sg:phone":"+61 7 5593 4305",
    "sg:postcode":"4220",
    "sg:province":"QLD",
    "sg:tags":[
        "cake",
        "shop",
        "pastry"
    ],
    "wof:name":"Duvalls",
    "wof:placetype":"venue"
},
  "geometry": {"coordinates":[153.423553467,-28.0794391632],"type":"Point"}
}