{
  "type": "Feature",
  "properties": {
    "addr:full":"Arthur Kaines Drv Merimbula NSW 2548",
    "addr:postcode":"2548",
    "addr:street":"Arthur Kaines Drv",
    "iso:country":"AU",
    "sg:address":"Arthur Kaines Drv",
    "sg:city":"Merimbula",
    "sg:classifiers":[
        {
            "category":"Travel",
            "subcategory":"Hotels & Motels",
            "type":"Entertainment"
        }
    ],
    "sg:phone":"+61 2 6495 1500",
    "sg:postcode":"2548",
    "sg:province":"NSW",
    "wof:name":"Black Dolphin Motel",
    "wof:placetype":"venue"
},
  "geometry": {"coordinates":[149.91119384800001,-36.8958091736],"type":"Point"}
}