{
  "type": "Feature",
  "properties": {
    "iso:country":"AU",
    "sg:address":"9 Turner Rd",
    "sg:city":"Berowra Heights",
    "sg:classifiers":[
        {
            "category":"Retail",
            "subcategory":"Veterinary Services",
            "type":"Services"
        }
    ],
    "sg:phone":"+61 2 9456 2492",
    "sg:postcode":"2082",
    "sg:province":"NSW",
    "sg:tags":[
        "surgeon"
    ],
    "wof:name":"A.J. Morgan Veterinary Practice",
    "wof:placetype":"venue"
},
  "geometry": {"coordinates":[151.138275147,-33.612285614],"type":"Point"}
}