{
  "type": "Feature",
  "properties": {
    "iso:country":"AU",
    "sg:address":"U4/ 68 Industry Rd",
    "sg:city":"Mulgrave",
    "sg:classifiers":[
        {
            "category":"Building & Trades",
            "subcategory":"Construction",
            "type":"Services"
        }
    ],
    "sg:phone":"+61 1300 874 654",
    "sg:postcode":"2756",
    "sg:province":"NSW",
    "sg:tags":[
        "fencing",
        "contractor"
    ],
    "sg:website":"http://www.trimlite.com.au",
    "wof:name":"Trimlite",
    "wof:placetype":"venue"
},
  "geometry": {"coordinates":[150.839111328,-33.6146812439],"type":"Point"}
}