{
  "type": "Feature",
  "properties": {
    "iso:country":"AU",
    "sg:address":"20 Hillside Pde",
    "sg:city":"Glen Iris",
    "sg:classifiers":[
        {
            "category":"Building & Trades",
            "subcategory":"Construction",
            "type":"Services"
        }
    ],
    "sg:phone":"+61 3 9889 3315",
    "sg:postcode":"3146",
    "sg:province":"VIC",
    "sg:tags":[
        "fencing",
        "contractor"
    ],
    "wof:name":"C.J Fencing",
    "wof:placetype":"venue"
},
  "geometry": {"coordinates":[145.063995361,-37.8485183716],"type":"Point"}
}