{
  "type": "Feature",
  "properties": {
    "iso:country":"AU",
    "sg:address":"10 Smith Crs",
    "sg:city":"Footscray",
    "sg:classifiers":[
        {
            "category":"Building & Trades",
            "subcategory":"Landscaping Services",
            "type":"Services"
        }
    ],
    "sg:phone":"+61 3 9687 3736",
    "sg:postcode":"3011",
    "sg:province":"VIC",
    "sg:tags":[
        "consultant"
    ],
    "wof:name":"Manallack W N",
    "wof:placetype":"venue"
},
  "geometry": {"coordinates":[144.89125060999999,-37.7917098999],"type":"Point"}
}