{
  "type": "Feature",
  "properties": {
    "addr:full":"LV5/ 113 Wicks Rd North Ryde NSW 2113",
    "addr:housenumber":"113",
    "addr:postcode":"2113",
    "addr:street":"Wicks Rd",
    "iso:country":"AU",
    "sg:address":"LV5/ 113 Wicks Rd",
    "sg:city":"North Ryde",
    "sg:classifiers":[
        {
            "category":"Banks & Credit Unions",
            "subcategory":"Atm",
            "type":"Services"
        }
    ],
    "sg:phone":"+61 1800 809 606",
    "sg:postcode":"2113",
    "sg:province":"NSW",
    "sg:tags":[
        "detector",
        "gas"
    ],
    "wof:name":"Industrial Scientific Australia Pty Ltd",
    "wof:placetype":"venue"
},
  "geometry": {"coordinates":[151.13136291500001,-33.7905693054],"type":"Point"}
}