{
  "type": "Feature",
  "properties": {
    "addr:full":"17 King St Port Lincoln SA 5606",
    "addr:housenumber":"17",
    "addr:postcode":"5606",
    "addr:street":"King St",
    "iso:country":"AU",
    "sg:address":"17 King St",
    "sg:city":"Port Lincoln",
    "sg:classifiers":[
        {
            "category":"Retail",
            "subcategory":"Funeral Services",
            "type":"Services"
        }
    ],
    "sg:phone":"+61 8 8683 4000",
    "sg:postcode":"5606",
    "sg:province":"SA",
    "sg:tags":[
        "director"
    ],
    "wof:name":"Williams Funeral Services",
    "wof:placetype":"venue"
},
  "geometry": {"coordinates":[135.864609,-34.72271],"type":"Point"}
}