{
  "type": "Feature",
  "properties": {
    "addr:full":"Unit 1/ 15 Galoola Drv Nelson Bay NSW 2315",
    "addr:postcode":"2315",
    "addr:street":"15 Galoola Drv",
    "iso:country":"AU",
    "sg:address":"Unit 1/ 15 Galoola Drv",
    "sg:city":"Nelson Bay",
    "sg:classifiers":[
        {
            "category":"Building & Trades",
            "subcategory":"Construction",
            "type":"Services"
        }
    ],
    "sg:phone":"+61 422 231 494",
    "sg:postcode":"2315",
    "sg:province":"NSW",
    "sg:tags":[
        "joiner",
        "carpenter"
    ],
    "wof:name":"Waring M",
    "wof:placetype":"venue"
},
  "geometry": {"coordinates":[152.13554400000001,-32.726353],"type":"Point"}
}