{
  "type": "Feature",
  "properties": {
    "iso:country":"AU",
    "sg:address":"Cowper St",
    "sg:city":"Glebe",
    "sg:classifiers":[
        {
            "category":"Shopping",
            "subcategory":"Music",
            "type":"Retail Goods"
        }
    ],
    "sg:phone":"+61 2 9552 3753",
    "sg:postcode":"2037",
    "sg:province":"NSW",
    "sg:tags":[
        "store"
    ],
    "wof:name":"Metal Rocks Australia",
    "wof:placetype":"venue"
},
  "geometry": {"coordinates":[151.19293212900001,-33.8800926208],"type":"Point"}
}