{
  "type": "Feature",
  "properties": {
    "iso:country":"AU",
    "sg:address":"140 Bryces Rd",
    "sg:city":"Berry",
    "sg:classifiers":[
        {
            "category":"Building & Trades",
            "subcategory":"Pest Control",
            "type":"Services"
        }
    ],
    "sg:phone":"+61 2 4464 3441",
    "sg:postcode":"2535",
    "sg:province":"NSW",
    "sg:tags":[
        "equipment",
        "construction",
        "green",
        "bowling"
    ],
    "wof:name":"Rink Promotions",
    "wof:placetype":"venue"
},
  "geometry": {"coordinates":[150.716262817,-34.8248748779],"type":"Point"}
}