{
  "type": "Feature",
  "properties": {
    "iso:country":"AU",
    "sg:address":"Suite 2/ 125 Melville Pde",
    "sg:city":"Como",
    "sg:classifiers":[
        {
            "category":"Shopping",
            "subcategory":"Computers & Home Electronics",
            "type":"Retail Goods"
        }
    ],
    "sg:phone":"+61 8 9367 9066",
    "sg:postcode":"6152",
    "sg:province":"WA",
    "sg:tags":[
        "hardware",
        "equipment"
    ],
    "wof:name":"Hitachi Data Systems Australia Pty Ltd",
    "wof:placetype":"venue"
},
  "geometry": {"coordinates":[115.855797,-31.992916],"type":"Point"}
}