{
  "type": "Feature",
  "properties": {
    "addr:full":"Industrial Estate 13 Blacksmith Crt Childers QLD 4660",
    "addr:housenumber":"13",
    "addr:postcode":"4660",
    "addr:street":"Blacksmith Crt",
    "iso:country":"AU",
    "sg:address":"Industrial Estate 13 Blacksmith Crt",
    "sg:city":"Childers",
    "sg:classifiers":[
        {
            "category":"Professional",
            "type":"Services"
        }
    ],
    "sg:phone":"+61 7 4126 3485",
    "sg:postcode":"4660",
    "sg:province":"QLD",
    "sg:tags":[
        "transport"
    ],
    "wof:name":"Isis Petroleum Pty Ltd",
    "wof:placetype":"venue"
},
  "geometry": {"coordinates":[152.29606628400001,-25.2377586365],"type":"Point"}
}