{
  "type": "Feature",
  "properties": {
    "iso:country":"AU",
    "sg:address":"Pearson St",
    "sg:city":"Guyra",
    "sg:classifiers":[
        {
            "category":"Building & Trades",
            "subcategory":"Construction",
            "type":"Services"
        }
    ],
    "sg:phone":"+61 428 791 641",
    "sg:postcode":"2365",
    "sg:province":"NSW",
    "sg:tags":[
        "earth",
        "excavating",
        "moving",
        "contractor"
    ],
    "wof:name":"Williamson Earthmoving",
    "wof:placetype":"venue"
},
  "geometry": {"coordinates":[151.678497314,-30.2257575989],"type":"Point"}
}