{
  "type": "Feature",
  "properties": {
    "addr:full":"3 Linden Pl Doveton VIC 3177",
    "addr:housenumber":"3",
    "addr:postcode":"3177",
    "addr:street":"Linden Pl",
    "iso:country":"AU",
    "sg:address":"3 Linden Pl",
    "sg:city":"Doveton",
    "sg:classifiers":[
        {
            "category":"Food & Beverages",
            "subcategory":"Supermarket",
            "type":"Retail Goods"
        }
    ],
    "sg:phone":"+61 3 9792 9762",
    "sg:postcode":"3177",
    "sg:province":"VIC",
    "sg:tags":[
        "grocery",
        "store"
    ],
    "wof:name":"Foodtown",
    "wof:placetype":"venue"
},
  "geometry": {"coordinates":[145.23905944800001,-37.985244751],"type":"Point"}
}