{
  "type": "Feature",
  "properties": {
    "iso:country":"AU",
    "sg:address":"314 Cedar Party Rd",
    "sg:city":"Taree",
    "sg:classifiers":[
        {
            "category":"Mining & Drilling",
            "type":"Manufacturing & Wholesale Goods"
        }
    ],
    "sg:phone":"+61 2 6551 0744",
    "sg:postcode":"2430",
    "sg:province":"NSW",
    "sg:tags":[
        "boring",
        "contractor"
    ],
    "wof:name":"Country To Coast Drilling",
    "wof:placetype":"venue"
},
  "geometry": {"coordinates":[152.424255,-31.851349],"type":"Point"}
}