{
  "type": "Feature",
  "properties": {
    "addr:full":"314 Cedar Party Rd Taree NSW 2430",
    "addr:housenumber":"314",
    "addr:postcode":"2430",
    "addr:street":"Cedar Party Rd",
    "iso:country":"AU",
    "sg:address":"314 Cedar Party Rd",
    "sg:city":"Taree",
    "sg:classifiers":[
        {
            "category":"Mining & Drilling",
            "type":"Manufacturing & Wholesale Goods"
        }
    ],
    "sg:phone":"+61 2 6551 0744",
    "sg:postcode":"2430",
    "sg:province":"NSW",
    "sg:tags":[
        "boring",
        "contractor"
    ],
    "wof:name":"Country To Coast Drilling",
    "wof:placetype":"venue"
},
  "geometry": {"coordinates":[152.42425499999999,-31.851349],"type":"Point"}
}