{
  "type": "Feature",
  "properties": {
    "addr:full":"210 Henley Beach Rd Torrensville SA 5031",
    "addr:housenumber":"210",
    "addr:postcode":"5031",
    "addr:street":"Henley Beach Rd",
    "iso:country":"AU",
    "sg:address":"210 Henley Beach Rd",
    "sg:city":"Torrensville",
    "sg:classifiers":[
        {
            "category":"Arts & Performance",
            "subcategory":"Dance",
            "type":"Entertainment"
        }
    ],
    "sg:phone":"+61 8 8234 1334",
    "sg:postcode":"5031",
    "sg:province":"SA",
    "sg:tags":[
        "theatrical",
        "ballet",
        "tuition"
    ],
    "wof:name":"Dance Gallery",
    "wof:placetype":"venue"
},
  "geometry": {"coordinates":[138.557861328,-34.9240951538],"type":"Point"}
}