{
  "type": "Feature",
  "properties": {
    "iso:country":"AU",
    "sg:address":"Shed 2/ 21 Pendlebury Rd",
    "sg:city":"Cardiff",
    "sg:classifiers":[
        {
            "category":"Autos & Motor Vehicles",
            "subcategory":"Automobile Sales",
            "type":"Retail Goods"
        }
    ],
    "sg:phone":"+61 2 4956 8808",
    "sg:postcode":"2285",
    "sg:province":"NSW",
    "sg:tags":[
        "equipment",
        "trailer"
    ],
    "wof:name":"TRG Automotive",
    "wof:placetype":"venue"
},
  "geometry": {"coordinates":[151.65388488799999,-32.9481163025],"type":"Point"}
}