{
  "type": "Feature",
  "properties": {
    "addr:full":"Mildura Cntr Plz, Cnr Deakin Ave & 15th St Mildura VIC 3502",
    "addr:postcode":"3502",
    "addr:street":"Cntr Plz Cnr Deakin Ave & 15Th St",
    "iso:country":"AU",
    "sg:address":"Mildura Cntr Plz, Cnr Deakin Ave & 15th St",
    "sg:city":"Mildura",
    "sg:classifiers":[
        {
            "category":"Banks & Credit Unions",
            "subcategory":"Bank",
            "type":"Services"
        }
    ],
    "sg:phone":"+61 13 13 14",
    "sg:postcode":"3502",
    "sg:province":"VIC",
    "wof:name":"ANZ",
    "wof:placetype":"venue"
},
  "geometry": {"coordinates":[142.16400146500001,-34.1843338013],"type":"Point"}
}