{
  "type": "Feature",
  "properties": {
    "addr:full":"Cnr Linton & Walsh Sts Roma QLD 4455",
    "addr:postcode":"4455",
    "addr:street":"Cnr;Qld",
    "iso:country":"AU",
    "sg:address":"Cnr Linton & Walsh Sts",
    "sg:city":"Roma",
    "sg:classifiers":[
        {
            "category":"Commercial Area",
            "type":"Public Place"
        }
    ],
    "sg:phone":"+61 7 4622 6188",
    "sg:postcode":"4455",
    "sg:province":"QLD",
    "sg:tags":[
        "heavy",
        "carrier"
    ],
    "wof:name":"Pyes Transport",
    "wof:placetype":"venue"
},
  "geometry": {"coordinates":[148.77755737300001,-26.5834617615],"type":"Point"}
}