{
  "type": "Feature",
  "properties": {
    "addr:full":"Sanderson Rd Lesmurdie WA 6076",
    "addr:postcode":"6076",
    "addr:street":"Sanderson Rd",
    "iso:country":"AU",
    "sg:address":"Sanderson Rd",
    "sg:city":"Lesmurdie",
    "sg:classifiers":[
        {
            "category":"Education",
            "subcategory":"Kindergarten",
            "type":"Public Place"
        }
    ],
    "sg:phone":"+61 8 9291 6178",
    "sg:postcode":"6076",
    "sg:province":"WA",
    "sg:tags":[
        "pre-schools"
    ],
    "wof:name":"Lesmurdie 4 Year Old Pre-Primary",
    "wof:placetype":"venue"
},
  "geometry": {"coordinates":[116.046150208,-32.0097351074],"type":"Point"}
}