{
  "type": "Feature",
  "properties": {
    "addr:full":"218 Herries St Toowoomba QLD 4350",
    "addr:housenumber":"218",
    "addr:postcode":"4350",
    "addr:street":"Herries St",
    "iso:country":"AU",
    "sg:address":"218 Herries St",
    "sg:city":"Toowoomba",
    "sg:classifiers":[
        {
            "category":"Professional",
            "subcategory":"Computer Services",
            "type":"Services"
        }
    ],
    "sg:phone":"+61 7 4613 1300",
    "sg:postcode":"4350",
    "sg:province":"QLD",
    "sg:tags":[
        "technical",
        "support"
    ],
    "wof:name":"Pracnet Pty Ltd",
    "wof:placetype":"venue"
},
  "geometry": {"coordinates":[151.93507399999999,-27.561899],"type":"Point"}
}