{
  "type": "Feature",
  "properties": {
    "addr:full":"120 John St Singleton NSW 2330",
    "addr:housenumber":"120",
    "addr:postcode":"2330",
    "addr:street":"John St",
    "iso:country":"AU",
    "sg:address":"120 John St",
    "sg:city":"Singleton",
    "sg:classifiers":[
        {
            "category":"Fast Food",
            "type":"Food & Drink"
        }
    ],
    "sg:phone":"+61 2 6572 1643",
    "sg:postcode":"2330",
    "sg:province":"NSW",
    "sg:tags":[
        "away",
        "take"
    ],
    "wof:name":"Singleton Chicken Spot",
    "wof:placetype":"venue"
},
  "geometry": {"coordinates":[151.167023,-32.565193],"type":"Point"}
}