{
  "type": "Feature",
  "properties": {
    "iso:country":"AU",
    "sg:address":"421 King Georges Rd",
    "sg:city":"Beverly Hills",
    "sg:classifiers":[
        {
            "category":"Sports & Exercise",
            "subcategory":"Gym",
            "type":"Entertainment"
        }
    ],
    "sg:phone":"+61 2 9580 5104",
    "sg:postcode":"2209",
    "sg:province":"NSW",
    "sg:tags":[
        "health",
        "fitness"
    ],
    "wof:name":"Leisure Dome Fitness Centre",
    "wof:placetype":"venue"
},
  "geometry": {"coordinates":[151.080765,-33.94968],"type":"Point"}
}