{
  "type": "Feature",
  "properties": {
    "iso:country":"AU",
    "sg:address":"4 Hilton Rd",
    "sg:city":"Springwood",
    "sg:classifiers":[
        {
            "category":"Utilities",
            "subcategory":"Electric",
            "type":"Services"
        }
    ],
    "sg:phone":"+61 425 259 206",
    "sg:postcode":"2777",
    "sg:province":"NSW",
    "sg:tags":[
        "electrical",
        "contractor"
    ],
    "wof:name":"Belle Electrical Service",
    "wof:placetype":"venue"
},
  "geometry": {"coordinates":[150.57426452600001,-33.705291748],"type":"Point"}
}