{
  "type": "Feature",
  "properties": {
    "iso:country":"AU",
    "sg:address":"1 Taurus Crt",
    "sg:city":"Lilydale",
    "sg:classifiers":[
        {
            "category":"Social Services",
            "type":"Services"
        }
    ],
    "sg:phone":"+61 3 9739 7989",
    "sg:postcode":"3140",
    "sg:province":"VIC",
    "sg:tags":[
        "kinesiology"
    ],
    "wof:name":"Anne Cowan Kinesiologist",
    "wof:placetype":"venue"
},
  "geometry": {"coordinates":[145.37011718799999,-37.7592315674],"type":"Point"}
}