{
  "type": "Feature",
  "properties": {
    "addr:full":"Level 2/ 11 Cambridge St The Rocks NSW 2000",
    "addr:housenumber":"/ 11",
    "addr:postcode":"2000",
    "addr:street":"Cambridge St",
    "iso:country":"AU",
    "sg:address":"Level 2/ 11 Cambridge St",
    "sg:city":"The Rocks",
    "sg:classifiers":[
        {
            "category":"Professional",
            "subcategory":"Research",
            "type":"Services"
        }
    ],
    "sg:phone":"+61 2 9423 5233",
    "sg:postcode":"2000",
    "sg:province":"NSW",
    "sg:tags":[
        "market"
    ],
    "wof:name":"Open House Research Services",
    "wof:placetype":"venue"
},
  "geometry": {"coordinates":[151.20738220199999,-33.8597984314],"type":"Point"}
}