{
  "type": "Feature",
  "properties": {
    "addr:full":"15 Bokhara St Brewarrina NSW 2839",
    "addr:housenumber":"15",
    "addr:postcode":"2839",
    "addr:street":"Bokhara St",
    "iso:country":"AU",
    "sg:address":"15 Bokhara St",
    "sg:city":"Brewarrina",
    "sg:classifiers":[
        {
            "category":"Food & Beverages",
            "subcategory":"Supermarket",
            "type":"Retail Goods"
        }
    ],
    "sg:phone":"+61 2 6839 2023",
    "sg:postcode":"2839",
    "sg:province":"NSW",
    "sg:tags":[
        "grocery",
        "store"
    ],
    "wof:name":"Brewill Pty Ltd",
    "wof:placetype":"venue"
},
  "geometry": {"coordinates":[146.864273,-29.966969],"type":"Point"}
}