{
  "type": "Feature",
  "properties": {
    "iso:country":"AU",
    "sg:address":"Cnr Neil & King Sts",
    "sg:city":"Toowoomba",
    "sg:classifiers":[
        {
            "category":"Autos & Motor Vehicles",
            "subcategory":"Automobile Sales",
            "type":"Retail Goods"
        }
    ],
    "sg:phone":"+61 7 4632 2150",
    "sg:postcode":"4350",
    "sg:province":"QLD",
    "sg:tags":[
        "car",
        "used"
    ],
    "wof:name":"Grady Frank",
    "wof:placetype":"venue"
},
  "geometry": {"coordinates":[151.875641,-27.55761],"type":"Point"}
}