{
  "type": "Feature",
  "properties": {
    "iso:country":"AU",
    "sg:address":"44 Holman St",
    "sg:city":"Curtin",
    "sg:classifiers":[
        {
            "category":"Parking",
            "subcategory":"Bicycle",
            "type":"Transportation"
        }
    ],
    "sg:phone":"+61 2 6282 2164",
    "sg:postcode":"2605",
    "sg:province":"ACT",
    "sg:tags":[
        "pebble",
        "paving"
    ],
    "wof:name":"Canberra Pebble Topping",
    "wof:placetype":"venue"
},
  "geometry": {"coordinates":[149.082885742,-35.3336524963],"type":"Point"}
}