{
  "type": "Feature",
  "properties": {
    "iso:country":"AU",
    "sg:address":"5/ 1240 North East Rd",
    "sg:city":"St Agnes",
    "sg:classifiers":[
        {
            "category":"Health Services",
            "subcategory":"Health Practitioner",
            "type":"Services"
        }
    ],
    "sg:phone":"+61 8 8396 1500",
    "sg:postcode":"5097",
    "sg:province":"SA",
    "sg:tags":[
        "naturopath"
    ],
    "wof:name":"Health Logistics",
    "wof:placetype":"venue"
},
  "geometry": {"coordinates":[138.714935303,-34.8213920593],"type":"Point"}
}