{
  "type": "Feature",
  "properties": {
    "addr:full":"136 Brigalow St Lyneham ACT 2602",
    "addr:housenumber":"136",
    "addr:postcode":"2602",
    "addr:street":"Brigalow St",
    "iso:country":"AU",
    "sg:address":"136 Brigalow St",
    "sg:city":"Lyneham",
    "sg:classifiers":[
        {
            "category":"Education",
            "subcategory":"School",
            "type":"Public Place"
        }
    ],
    "sg:phone":"+61 2 6247 4644",
    "sg:postcode":"2602",
    "sg:province":"ACT",
    "wof:name":"Brindabella Christian College",
    "wof:placetype":"venue"
},
  "geometry": {"coordinates":[149.127197266,-35.2498664856],"type":"Point"}
}