{
  "type": "Feature",
  "properties": {
    "addr:full":"10th Floor Century House 316 Adelaide St Brisbane QLD 4000",
    "addr:housenumber":"316",
    "addr:postcode":"4000",
    "addr:street":"Adelaide St",
    "iso:country":"AU",
    "sg:address":"10th Floor Century House 316 Adelaide St",
    "sg:city":"Brisbane",
    "sg:classifiers":[
        {
            "category":"Personal",
            "type":"Services"
        }
    ],
    "sg:phone":"+61 13 19 97",
    "sg:postcode":"4000",
    "sg:province":"QLD",
    "sg:tags":[
        "reducing",
        "treatment",
        "weight"
    ],
    "wof:name":"Weight Watchers",
    "wof:placetype":"venue"
},
  "geometry": {"coordinates":[153.029205322,-27.4650058746],"type":"Point"}
}