{
  "type": "Feature",
  "properties": {
    "addr:full":"61 Livingstone St Ivanhoe VIC 3079",
    "addr:housenumber":"61",
    "addr:postcode":"3079",
    "addr:street":"Livingstone St",
    "iso:country":"AU",
    "sg:address":"61 Livingstone St",
    "sg:city":"Ivanhoe",
    "sg:classifiers":[
        {
            "category":"Health Services",
            "subcategory":"Doctor",
            "type":"Services"
        }
    ],
    "sg:phone":"+61 3 9499 7599",
    "sg:postcode":"3079",
    "sg:province":"VIC",
    "sg:tags":[
        "medical",
        "practitioner"
    ],
    "wof:name":"Merory Dr",
    "wof:placetype":"venue"
},
  "geometry": {"coordinates":[145.036254883,-37.7670135498],"type":"Point"}
}