{
  "type": "Feature",
  "properties": {
    "addr:full":"11 Newfield Rd Para Hills West SA 5096",
    "addr:housenumber":"11",
    "addr:postcode":"5096",
    "addr:street":"Newfield Rd Para Hills West",
    "iso:country":"AU",
    "sg:address":"11 Newfield Rd",
    "sg:city":"Para Hills West",
    "sg:classifiers":[
        {
            "category":"Utilities",
            "subcategory":"Refuse",
            "type":"Services"
        }
    ],
    "sg:phone":"+61 8 8260 3270",
    "sg:postcode":"5096",
    "sg:province":"SA",
    "sg:tags":[
        "disposal",
        "reduction",
        "waste"
    ],
    "wof:name":"TA Kings Waste Services",
    "wof:placetype":"venue"
},
  "geometry": {"coordinates":[138.636444092,-34.8071784973],"type":"Point"}
}