{
  "type": "Feature",
  "properties": {
    "addr:full":"9 Maple Ave Moree NSW 2400",
    "addr:housenumber":"9",
    "addr:postcode":"2400",
    "addr:street":"Maple Ave",
    "iso:country":"AU",
    "sg:address":"9 Maple Ave",
    "sg:city":"Moree",
    "sg:classifiers":[
        {
            "category":"Retail",
            "subcategory":"Storage",
            "type":"Services"
        }
    ],
    "sg:phone":"+61 2 6752 7300",
    "sg:postcode":"2400",
    "sg:province":"NSW",
    "sg:tags":[
        "removal",
        "furniture"
    ],
    "wof:name":"Northern N.S.W. Removals",
    "wof:placetype":"venue"
},
  "geometry": {"coordinates":[149.841598511,-29.4661998749],"type":"Point"}
}