{
  "type": "Feature",
  "properties": {
    "addr:full":"11 Elizabeth St Noosaville QLD 4566",
    "addr:housenumber":"11",
    "addr:postcode":"4566",
    "addr:street":"Elizabeth St",
    "iso:country":"AU",
    "sg:address":"11 Elizabeth St",
    "sg:city":"Noosaville",
    "sg:classifiers":[
        {
            "category":"Utilities",
            "subcategory":"Electric",
            "type":"Services"
        }
    ],
    "sg:phone":"+61 412 500 035",
    "sg:postcode":"4566",
    "sg:province":"QLD",
    "sg:tags":[
        "electrical",
        "contractor"
    ],
    "wof:name":"Duckworths Electrical Services",
    "wof:placetype":"venue"
},
  "geometry": {"coordinates":[153.06423950199999,-26.3980693817],"type":"Point"}
}