{
  "type": "Feature",
  "properties": {
    "addr:full":"42 Albert St Warragul VIC 3820",
    "addr:housenumber":"42",
    "addr:postcode":"3820",
    "addr:street":"Albert St",
    "iso:country":"AU",
    "sg:address":"42 Albert St",
    "sg:city":"Warragul",
    "sg:classifiers":[
        {
            "category":"Organizations",
            "subcategory":"Non-profit Organization",
            "type":"Services"
        }
    ],
    "sg:phone":"+61 3 5622 1651",
    "sg:postcode":"3820",
    "sg:province":"VIC",
    "sg:tags":[
        "support",
        "disability",
        "organisation"
    ],
    "wof:name":"Gippsland Accommodation & Rehabilitation Support Service (G.A.R.S.S.)",
    "wof:placetype":"venue"
},
  "geometry": {"coordinates":[145.932907,-38.15976],"type":"Point"}
}