{
  "type": "Feature",
  "properties": {
    "iso:country":"AU",
    "sg:address":"23 New Canterbury Rd",
    "sg:city":"Petersham",
    "sg:classifiers":[
        {
            "category":"Government",
            "subcategory":"City Hall",
            "type":"Public Place"
        }
    ],
    "sg:phone":"+61 2 9569 5699",
    "sg:postcode":"2049",
    "sg:province":"NSW",
    "wof:name":"Masonic Halls & Centres",
    "wof:placetype":"venue"
},
  "geometry": {"coordinates":[151.152466,-33.896748],"type":"Point"}
}