{
  "type": "Feature",
  "properties": {
    "addr:full":"80 Main St Zeehan TAS 7469",
    "addr:housenumber":"80",
    "addr:postcode":"7469",
    "addr:street":"Main St",
    "iso:country":"AU",
    "sg:address":"80 Main St",
    "sg:city":"Zeehan",
    "sg:classifiers":[
        {
            "category":"Building & Trades",
            "subcategory":"Construction",
            "type":"Services"
        }
    ],
    "sg:phone":"+61 3 6264 1155",
    "sg:postcode":"7469",
    "sg:province":"TAS",
    "sg:tags":[
        "earth",
        "excavating",
        "moving",
        "contractor"
    ],
    "wof:name":"Pettit Hire",
    "wof:placetype":"venue"
},
  "geometry": {"coordinates":[145.33807373100001,-41.8862762451],"type":"Point"}
}