{
  "type": "Feature",
  "properties": {
    "iso:country":"AU",
    "sg:address":"75 Molong Rd",
    "sg:city":"Parkes",
    "sg:classifiers":[
        {
            "category":"Home & Garden",
            "subcategory":"Hardware",
            "type":"Retail Goods"
        }
    ],
    "sg:phone":"+61 2 6862 6261",
    "sg:postcode":"2870",
    "sg:province":"NSW",
    "sg:tags":[
        "repair",
        "tool",
        "power"
    ],
    "wof:name":"Wilson's Service Centre",
    "wof:placetype":"venue"
},
  "geometry": {"coordinates":[148.193451,-33.142181],"type":"Point"}
}