{
  "type": "Feature",
  "properties": {
    "iso:country":"AU",
    "sg:address":"Lot 31 Kingfisher Drv",
    "sg:city":"Clare",
    "sg:classifiers":[
        {
            "category":"Insurance",
            "subcategory":"Life Insurance",
            "type":"Services"
        }
    ],
    "sg:phone":"+61 8 8842 1714",
    "sg:postcode":"5453",
    "sg:province":"SA",
    "wof:name":"David Forrest Financial Services Pty Ltd",
    "wof:placetype":"venue"
},
  "geometry": {"coordinates":[138.627335,-33.855896],"type":"Point"}
}