{
  "type": "Feature",
  "properties": {
    "addr:full":"86 Wigram St Harris Park NSW 2150",
    "addr:housenumber":"86",
    "addr:postcode":"2150",
    "addr:street":"Wigram St",
    "iso:country":"AU",
    "sg:address":"86 Wigram St",
    "sg:city":"Harris Park",
    "sg:classifiers":[
        {
            "category":"Retail",
            "subcategory":"Laundry & Dry Cleaning",
            "type":"Services"
        }
    ],
    "sg:phone":"+61 2 9635 6747",
    "sg:postcode":"2150",
    "sg:province":"NSW",
    "wof:name":"Harris Park Laundrette",
    "wof:placetype":"venue"
},
  "geometry": {"coordinates":[151.009155273,-33.8201713562],"type":"Point"}
}