{
  "type": "Feature",
  "properties": {
    "addr:full":"Shp 2/ 151 Victoria Rd Drummoyne NSW 2047",
    "addr:housenumber":"/ 151",
    "addr:postcode":"2047",
    "addr:street":"Victoria Rd",
    "iso:country":"AU",
    "sg:address":"Shp 2/ 151 Victoria Rd",
    "sg:city":"Drummoyne",
    "sg:classifiers":[
        {
            "category":"Personal",
            "subcategory":"Beauty Salon",
            "type":"Services"
        }
    ],
    "sg:phone":"+61 2 9719 3100",
    "sg:postcode":"2047",
    "sg:province":"NSW",
    "sg:tags":[
        "supply",
        "artist",
        "make-up"
    ],
    "wof:name":"mju",
    "wof:placetype":"venue"
},
  "geometry": {"coordinates":[151.15580700000001,-33.852531],"type":"Point"}
}