{
  "type": "Feature",
  "properties": {
    "addr:full":"Middleton Medi-Clinic, 5 Goolwa Rd Middleton SA 5213",
    "addr:housenumber":"5",
    "addr:postcode":"5213",
    "addr:street":"Goolwa Rd",
    "iso:country":"AU",
    "sg:address":"Middleton Medi-Clinic, 5 Goolwa Rd",
    "sg:city":"Middleton",
    "sg:classifiers":[
        {
            "category":"Health Services",
            "subcategory":"Health Practitioner",
            "type":"Services"
        }
    ],
    "sg:phone":"+61 8 8272 0046",
    "sg:postcode":"5213",
    "sg:province":"SA",
    "sg:tags":[
        "psychologist"
    ],
    "wof:name":"Taylor Liana",
    "wof:placetype":"venue"
},
  "geometry": {"coordinates":[138.70599365199999,-35.4847602844],"type":"Point"}
}