{
  "type": "Feature",
  "properties": {
    "iso:country":"AU",
    "sg:address":"25 Woodward Pl",
    "sg:city":"Tuncurry",
    "sg:classifiers":[
        {
            "category":"Professional",
            "subcategory":"Art Services",
            "type":"Services"
        }
    ],
    "sg:phone":"+61 2 6555 2511",
    "sg:postcode":"2428",
    "sg:province":"NSW",
    "sg:tags":[
        "decorator",
        "painter"
    ],
    "wof:name":"D & V Painting Contractors",
    "wof:placetype":"venue"
},
  "geometry": {"coordinates":[152.48722799999999,-32.170395],"type":"Point"}
}