{
  "type": "Feature",
  "properties": {
    "addr:full":"2/27 Malua St Dolls Point NSW 2219",
    "addr:housenumber":"/ 27",
    "addr:postcode":"2219",
    "addr:street":"Malua St",
    "iso:country":"AU",
    "sg:address":"2/27 Malua St",
    "sg:city":"Dolls Point",
    "sg:classifiers":[
        {
            "category":"Building & Trades",
            "subcategory":"Construction",
            "type":"Services"
        }
    ],
    "sg:phone":"+61 2 9529 5976",
    "sg:postcode":"2219",
    "sg:province":"NSW",
    "sg:tags":[
        "contractor"
    ],
    "wof:name":"K.N.H. Constructions Pty Ltd",
    "wof:placetype":"venue"
},
  "geometry": {"coordinates":[151.13679500000001,-34.002743],"type":"Point"}
}