{
  "type": "Feature",
  "properties": {
    "addr:full":"171 Commercial Rd Port Adelaide SA 5015",
    "addr:housenumber":"171",
    "addr:postcode":"5015",
    "addr:street":"Commercial Rd",
    "iso:country":"AU",
    "sg:address":"171 Commercial Rd",
    "sg:city":"Port Adelaide",
    "sg:classifiers":[
        {
            "category":"Transit Center",
            "subcategory":"Freight",
            "type":"Transportation"
        }
    ],
    "sg:phone":"+61 8 8240 1201",
    "sg:postcode":"5015",
    "sg:province":"SA",
    "sg:tags":[
        "ship",
        "provedores"
    ],
    "wof:name":"Legend Nautilus",
    "wof:placetype":"venue"
},
  "geometry": {"coordinates":[138.50749206500001,-34.8471641541],"type":"Point"}
}