{
  "type": "Feature",
  "properties": {
    "addr:full":"289 High St Maitland NSW 2320",
    "addr:housenumber":"289",
    "addr:postcode":"2320",
    "addr:street":"High St",
    "iso:country":"AU",
    "sg:address":"289 High St",
    "sg:city":"Maitland",
    "sg:classifiers":[
        {
            "category":"Travel",
            "subcategory":"Hotels & Motels",
            "type":"Entertainment"
        }
    ],
    "sg:phone":"+61 2 4933 5255",
    "sg:postcode":"2320",
    "sg:province":"NSW",
    "sg:tags":[
        "accommodation"
    ],
    "wof:name":"Metropolitan Hotel",
    "wof:placetype":"venue"
},
  "geometry": {"coordinates":[151.55752563499999,-32.7336845398],"type":"Point"}
}