{
  "type": "Feature",
  "properties": {
    "addr:full":"3/ 74 Moss St Slacks Creek QLD 4127",
    "addr:housenumber":"/ 74",
    "addr:postcode":"4127",
    "addr:street":"Moss St",
    "iso:country":"AU",
    "sg:address":"3/ 74 Moss St",
    "sg:city":"Slacks Creek",
    "sg:classifiers":[
        {
            "category":"Retail",
            "subcategory":"Auto Repair",
            "type":"Services"
        }
    ],
    "sg:phone":"+61 7 3299 4344",
    "sg:postcode":"4127",
    "sg:province":"QLD",
    "sg:tags":[
        "sport",
        "motor"
    ],
    "wof:name":"Hardcore Racing Components Australia Pty Ltd",
    "wof:placetype":"venue"
},
  "geometry": {"coordinates":[153.12445068400001,-27.6210842133],"type":"Point"}
}