{
  "type": "Feature",
  "properties": {
    "addr:full":"3/ 60 The Boulevarde Toronto NSW 2283",
    "addr:housenumber":"/ 60",
    "addr:postcode":"2283",
    "addr:street":"The Boulevarde",
    "iso:country":"AU",
    "sg:address":"3/ 60 The Boulevarde",
    "sg:city":"Toronto",
    "sg:classifiers":[
        {
            "category":"Professional",
            "subcategory":"Printing & Photocopies",
            "type":"Services"
        }
    ],
    "sg:phone":"+61 2 4959 8905",
    "sg:postcode":"2283",
    "sg:province":"NSW",
    "sg:tags":[
        "rubber",
        "stamp",
        "metal"
    ],
    "wof:name":"The Copy Shop",
    "wof:placetype":"venue"
},
  "geometry": {"coordinates":[151.585083008,-33.0113792419],"type":"Point"}
}