{
  "type": "Feature",
  "properties": {
    "addr:full":"23 Stephen St Balmain NSW 2041",
    "addr:housenumber":"23",
    "addr:postcode":"2041",
    "addr:street":"Stephen St",
    "iso:country":"AU",
    "sg:address":"23 Stephen St",
    "sg:city":"Balmain",
    "sg:classifiers":[
        {
            "category":"Utilities",
            "subcategory":"Electric",
            "type":"Services"
        }
    ],
    "sg:phone":"+61 2 9818 7261",
    "sg:postcode":"2041",
    "sg:province":"NSW",
    "sg:tags":[
        "electrical",
        "contractor"
    ],
    "wof:name":"Baltel",
    "wof:placetype":"venue"
},
  "geometry": {"coordinates":[151.18609599999999,-33.859283],"type":"Point"}
}