{
  "type": "Feature",
  "properties": {
    "iso:country":"AU",
    "sg:address":"Maple Drv (cnr Peatey St)",
    "sg:city":"Andergrove",
    "sg:classifiers":[
        {
            "category":"Food & Beverages",
            "subcategory":"Groceries & Convenience Stores",
            "type":"Retail Goods"
        }
    ],
    "sg:phone":"+61 7 4955 4878",
    "sg:postcode":"4740",
    "sg:province":"QLD",
    "wof:name":"Maple Drive Mini Mart",
    "wof:placetype":"venue"
},
  "geometry": {"coordinates":[149.18718,-21.096144],"type":"Point"}
}