{
  "type": "Feature",
  "properties": {
    "addr:full":"6 Congressional Drv Liverpool NSW 2170",
    "addr:housenumber":"6",
    "addr:postcode":"2170",
    "addr:street":"Congressional Drv",
    "iso:country":"AU",
    "sg:address":"6 Congressional Drv",
    "sg:city":"Liverpool",
    "sg:classifiers":[
        {
            "category":"Building & Trades",
            "subcategory":"Landscaping Services",
            "type":"Services"
        }
    ],
    "sg:phone":"+61 410 462 542",
    "sg:postcode":"2170",
    "sg:province":"NSW",
    "sg:tags":[
        "inspection"
    ],
    "wof:name":"Asbestos Detectives P/L",
    "wof:placetype":"venue"
},
  "geometry": {"coordinates":[150.91696167000001,-33.9354438782],"type":"Point"}
}