{
  "type": "Feature",
  "properties": {
    "addr:full":"31 Inghams Pl Hemmant QLD 4174",
    "addr:housenumber":"31",
    "addr:postcode":"4174",
    "addr:street":"Inghams Pl",
    "iso:country":"AU",
    "sg:address":"31 Inghams Pl",
    "sg:city":"Hemmant",
    "sg:classifiers":[
        {
            "category":"Professional",
            "type":"Services"
        }
    ],
    "sg:phone":"+61 7 3348 3755",
    "sg:postcode":"4174",
    "sg:province":"QLD",
    "sg:tags":[
        "transport"
    ],
    "wof:name":"Kagan Logistics Pty Ltd",
    "wof:placetype":"venue"
},
  "geometry": {"coordinates":[153.138275147,-27.441034317],"type":"Point"}
}