{
  "type": "Feature",
  "properties": {
    "addr:full":"21 Willow Green Rd Falls Creek NSW 2540",
    "addr:housenumber":"21",
    "addr:postcode":"2540",
    "addr:street":"Willow Green Rd",
    "iso:country":"AU",
    "sg:address":"21 Willow Green Rd",
    "sg:city":"Falls Creek",
    "sg:classifiers":[
        {
            "category":"Professional",
            "subcategory":"Computer Services",
            "type":"Services"
        }
    ],
    "sg:phone":"+61 2 4447 8405",
    "sg:postcode":"2540",
    "sg:province":"NSW",
    "sg:tags":[
        "training"
    ],
    "wof:name":"Micro Maze Pty Ltd",
    "wof:placetype":"venue"
},
  "geometry": {"coordinates":[150.585647583,-34.9874954224],"type":"Point"}
}