{
  "type": "Feature",
  "properties": {
    "addr:full":"Bracken Ave Horsham VIC 3402",
    "addr:postcode":"3402",
    "addr:street":"Bracken Ave",
    "iso:country":"AU",
    "sg:address":"Bracken Ave",
    "sg:city":"Horsham",
    "sg:classifiers":[
        {
            "category":"Retail",
            "subcategory":"Car Wash",
            "type":"Services"
        }
    ],
    "sg:phone":"+61 3 5382 4406",
    "sg:postcode":"3402",
    "sg:province":"VIC",
    "sg:tags":[
        "bitumen",
        "spraying"
    ],
    "wof:name":"Inroads Pty Ltd",
    "wof:placetype":"venue"
},
  "geometry": {"coordinates":[142.20179748499999,-36.7392997742],"type":"Point"}
}