{
  "type": "Feature",
  "properties": {
    "addr:full":"Pacific Hwy Sydney NSW 2000",
    "addr:postcode":"2000",
    "addr:street":"Pacific Hwy",
    "iso:country":"AU",
    "sg:address":"Pacific Hwy",
    "sg:city":"Sydney",
    "sg:classifiers":[
        {
            "category":"Wholesale",
            "subcategory":"Medical Equipment & Supplies",
            "type":"Manufacturing & Wholesale Goods"
        }
    ],
    "sg:phone":"+61 1800 682 262",
    "sg:postcode":"2000",
    "sg:province":"NSW",
    "sg:tags":[
        "aids",
        "hearing"
    ],
    "wof:name":"Digital Hearing Solutions",
    "wof:placetype":"venue"
},
  "geometry": {"coordinates":[151.21002197300001,-33.8420448303],"type":"Point"}
}