{
  "type": "Feature",
  "properties": {
    "addr:full":"366 Stenner St Toowoomba QLD 4350",
    "addr:housenumber":"366",
    "addr:postcode":"4350",
    "addr:street":"Stenner St",
    "iso:country":"AU",
    "sg:address":"366 Stenner St",
    "sg:city":"Toowoomba",
    "sg:classifiers":[
        {
            "category":"Retail",
            "subcategory":"Veterinary Services",
            "type":"Services"
        }
    ],
    "sg:phone":"+61 7 4635 3616",
    "sg:postcode":"4350",
    "sg:province":"QLD",
    "sg:tags":[
        "surgeon"
    ],
    "wof:name":"South Toowoomba Veterinary Surgery",
    "wof:placetype":"venue"
},
  "geometry": {"coordinates":[151.94665499999999,-27.592997],"type":"Point"}
}