{
  "type": "Feature",
  "properties": {
    "iso:country":"AU",
    "sg:address":"366 Stenner St",
    "sg:city":"Toowoomba",
    "sg:classifiers":[
        {
            "category":"Retail",
            "subcategory":"Veterinary Services",
            "type":"Services"
        }
    ],
    "sg:phone":"+61 7 4635 3616",
    "sg:postcode":"4350",
    "sg:province":"QLD",
    "sg:tags":[
        "surgeon"
    ],
    "wof:name":"South Toowoomba Veterinary Surgery",
    "wof:placetype":"venue"
},
  "geometry": {"coordinates":[151.946655,-27.592997],"type":"Point"}
}