{
  "type": "Feature",
  "properties": {
    "addr:full":"Dockside Apartment Hotel, 1 / 44 Ferry St Kangaroo Point QLD 4169",
    "addr:housenumber":"1 / 44",
    "addr:postcode":"4169",
    "addr:street":"Ferry St",
    "iso:country":"AU",
    "sg:address":"Dockside Apartment Hotel, 1 / 44 Ferry St",
    "sg:city":"Kangaroo Point",
    "sg:classifiers":[
        {
            "category":"Professional",
            "subcategory":"Detective & Security Services",
            "type":"Services"
        }
    ],
    "sg:phone":"+61 7 3891 5260",
    "sg:postcode":"4169",
    "sg:province":"QLD",
    "sg:tags":[
        "guard",
        "patrol"
    ],
    "wof:name":"Quest Security Services Pty Ltd",
    "wof:placetype":"venue"
},
  "geometry": {"coordinates":[153.036987305,-27.471698761],"type":"Point"}
}