{
  "type": "Feature",
  "properties": {
    "iso:country":"AU",
    "sg:address":"515 Mt Alexander Rd",
    "sg:city":"Moonee Ponds",
    "sg:classifiers":[
        {
            "category":"Home & Garden",
            "subcategory":"Carpets & Floor Coverings",
            "type":"Retail Goods"
        }
    ],
    "sg:phone":"+61 3 9370 8409",
    "sg:postcode":"3039",
    "sg:province":"VIC",
    "sg:tags":[
        "tile",
        "wall"
    ],
    "wof:name":"Schots Restoration Emporium",
    "wof:placetype":"venue"
},
  "geometry": {"coordinates":[144.926117,-37.770962],"type":"Point"}
}