{
  "type": "Feature",
  "properties": {
    "addr:full":"Old Bathurst Road Emu Plains NSW 2750",
    "addr:postcode":"2750",
    "addr:street":"Bathurst Road",
    "iso:country":"AU",
    "sg:address":"Old Bathurst Road",
    "sg:city":"Emu Plains",
    "sg:classifiers":[
        {
            "category":"Home & Garden",
            "subcategory":"Building Materials",
            "type":"Retail Goods"
        }
    ],
    "sg:phone":"+61 13 10 04",
    "sg:postcode":"2750",
    "sg:province":"NSW",
    "sg:tags":[
        "supply"
    ],
    "wof:name":"Rocla",
    "wof:placetype":"venue"
},
  "geometry": {"coordinates":[150.65948486299999,-33.7425689697],"type":"Point"}
}