{
  "type": "Feature",
  "properties": {
    "addr:full":"806 Ingham Rd Bohle QLD 4818",
    "addr:housenumber":"806",
    "addr:postcode":"4818",
    "addr:street":"Ingham Rd",
    "iso:country":"AU",
    "sg:address":"806 Ingham Rd",
    "sg:city":"Bohle",
    "sg:classifiers":[
        {
            "category":"Shopping",
            "subcategory":"Stationery & Office Supplies",
            "type":"Retail Goods"
        }
    ],
    "sg:phone":"+61 7 4774 9444",
    "sg:postcode":"4818",
    "sg:province":"QLD",
    "sg:tags":[
        "packaging",
        "material"
    ],
    "wof:name":"Amcor Fibre Packaging",
    "wof:placetype":"venue"
},
  "geometry": {"coordinates":[146.723602,-19.260853],"type":"Point"}
}