{
  "type": "Feature",
  "properties": {
    "addr:full":"616 Ballina Rd Goonellabah NSW 2480",
    "addr:housenumber":"616",
    "addr:postcode":"2480",
    "addr:street":"Ballina Rd",
    "iso:country":"AU",
    "sg:address":"616 Ballina Rd",
    "sg:city":"Goonellabah",
    "sg:classifiers":[
        {
            "category":"Health Services",
            "subcategory":"Doctor",
            "type":"Services"
        }
    ],
    "sg:phone":"+61 2 6625 0000",
    "sg:postcode":"2480",
    "sg:province":"NSW",
    "sg:tags":[
        "medical",
        "practitioner"
    ],
    "wof:name":"Guest David",
    "wof:placetype":"venue"
},
  "geometry": {"coordinates":[153.31675720199999,-28.8150997162],"type":"Point"}
}