{
  "type": "Feature",
  "properties": {
    "addr:full":"6 Bundaberg Crt Glenorchy TAS 7010",
    "addr:housenumber":"6",
    "addr:postcode":"7010",
    "addr:street":"Bundaberg Crt",
    "iso:country":"AU",
    "sg:address":"6 Bundaberg Crt",
    "sg:city":"Glenorchy",
    "sg:classifiers":[
        {
            "category":"Building & Trades",
            "subcategory":"Electrical",
            "type":"Services"
        }
    ],
    "sg:phone":"+61 3 6273 9298",
    "sg:postcode":"7010",
    "sg:province":"TAS",
    "sg:tags":[
        "testing",
        "tagging"
    ],
    "wof:name":"MG Test And Tag",
    "wof:placetype":"venue"
},
  "geometry": {"coordinates":[147.25767517099999,-42.8324623108],"type":"Point"}
}