{
  "type": "Feature",
  "properties": {
    "iso:country":"AU",
    "sg:address":"Pine St",
    "sg:city":"Killarney",
    "sg:classifiers":[
        {
            "category":"Travel",
            "subcategory":"Hotels & Motels",
            "type":"Entertainment"
        }
    ],
    "sg:phone":"+61 7 4664 1318",
    "sg:postcode":"4373",
    "sg:province":"QLD",
    "wof:name":"Killarney Sundown Motel",
    "wof:placetype":"venue"
},
  "geometry": {"coordinates":[152.29612731899999,-28.3422813416],"type":"Point"}
}