{
  "type": "Feature",
  "properties": {
    "iso:country":"AU",
    "sg:address":"108 Flinders St",
    "sg:city":"South Melbourne",
    "sg:classifiers":[
        {
            "category":"Building & Trades",
            "subcategory":"Construction",
            "type":"Services"
        }
    ],
    "sg:phone":"+61 3 9650 8388",
    "sg:postcode":"3205",
    "sg:province":"VIC",
    "sg:tags":[
        "contractor"
    ],
    "wof:name":"Stanhouse Group (Aust) Pty Ltd",
    "wof:placetype":"venue"
},
  "geometry": {"coordinates":[144.971313,-37.816181],"type":"Point"}
}