{
  "type": "Feature",
  "properties": {
    "iso:country":"AU",
    "sg:address":"4 Mulga Rd",
    "sg:city":"Hawthorndene",
    "sg:classifiers":[
        {
            "category":"Home & Garden",
            "subcategory":"Carpets & Floor Coverings",
            "type":"Retail Goods"
        }
    ],
    "sg:phone":"+61 417 810 250",
    "sg:postcode":"5051",
    "sg:province":"SA",
    "sg:tags":[
        "tile",
        "wall",
        "layer"
    ],
    "wof:name":"Tessitore Renato",
    "wof:placetype":"venue"
},
  "geometry": {"coordinates":[138.626709,-35.01725],"type":"Point"}
}