{
  "type": "Feature",
  "properties": {
    "iso:country":"AU",
    "sg:address":"Balfour St",
    "sg:city":"Holbrook",
    "sg:classifiers":[
        {
            "category":"Organizations",
            "subcategory":"Non-profit Organization",
            "type":"Services"
        }
    ],
    "sg:phone":"+61 2 6029 7482",
    "sg:postcode":"2644",
    "sg:province":"NSW",
    "sg:tags":[
        "support",
        "disability",
        "organisation"
    ],
    "wof:name":"Department of Ageing, Disability & Homecare",
    "wof:placetype":"venue"
},
  "geometry": {"coordinates":[147.31758117699999,-35.7186012268],"type":"Point"}
}