{
  "type": "Feature",
  "properties": {
    "addr:full":"25 Parap Rd Parap NT 0820",
    "addr:housenumber":"25",
    "addr:postcode":"nt 0820",
    "addr:street":"Parap Rd",
    "iso:country":"AU",
    "sg:address":"25 Parap Rd",
    "sg:city":"Parap",
    "sg:classifiers":[
        {
            "category":"Retail",
            "subcategory":"Auto Repair",
            "type":"Services"
        }
    ],
    "sg:phone":"+61 8 8941 4339",
    "sg:postcode":"0820",
    "sg:province":"NT",
    "sg:tags":[
        "testing",
        "inspection",
        "motor",
        "vehicle"
    ],
    "wof:name":"Action Automotive",
    "wof:placetype":"venue"
},
  "geometry": {"coordinates":[130.84317016599999,-12.4324941635],"type":"Point"}
}