{
  "type": "Feature",
  "properties": {
    "addr:full":"6 Bellona Ave Regents Park NSW 2143",
    "addr:housenumber":"6",
    "addr:postcode":"2143",
    "addr:street":"Bellona Ave Regents",
    "iso:country":"AU",
    "sg:address":"6 Bellona Ave",
    "sg:city":"Regents Park",
    "sg:classifiers":[
        {
            "category":"Shopping",
            "subcategory":"Stationery & Office Supplies",
            "type":"Retail Goods"
        }
    ],
    "sg:phone":"+61 2 9738 9622",
    "sg:postcode":"2143",
    "sg:province":"NSW",
    "sg:tags":[
        "packaging",
        "material"
    ],
    "wof:name":"M & N Hawks Pty Ltd",
    "wof:placetype":"venue"
},
  "geometry": {"coordinates":[151.019897461,-33.882194519],"type":"Point"}
}