{
  "type": "Feature",
  "properties": {
    "addr:full":"55 Storey Rd Logan Village QLD 4207",
    "addr:housenumber":"55",
    "addr:postcode":"4207",
    "addr:street":"Storey Rd",
    "iso:country":"AU",
    "sg:address":"55 Storey Rd",
    "sg:city":"Logan Village",
    "sg:classifiers":[
        {
            "category":"Professional",
            "subcategory":"Accounting & Tax Preparation",
            "type":"Services"
        }
    ],
    "sg:phone":"+61 1800 999 924",
    "sg:postcode":"4207",
    "sg:province":"QLD",
    "sg:tags":[
        "jukebox"
    ],
    "wof:name":"A&A Stewart Jukebox Hire",
    "wof:placetype":"venue"
},
  "geometry": {"coordinates":[153.10482788100001,-27.7645339966],"type":"Point"}
}