{
  "type": "Feature",
  "properties": {
    "addr:full":"1/ 21 Howleys Rd Notting Hill VIC 3168",
    "addr:housenumber":"/ 21",
    "addr:postcode":"3168",
    "addr:street":"Howleys Rd",
    "iso:country":"AU",
    "sg:address":"1/ 21 Howleys Rd",
    "sg:city":"Notting Hill",
    "sg:classifiers":[
        {
            "category":"Social Services",
            "subcategory":"Retirement Home",
            "type":"Services"
        }
    ],
    "sg:phone":"+61 3 9562 7111",
    "sg:postcode":"3168",
    "sg:province":"VIC",
    "sg:tags":[
        "environmental",
        "consultant",
        "pollution"
    ],
    "wof:name":"B F P Consultants Pty Ltd",
    "wof:placetype":"venue"
},
  "geometry": {"coordinates":[145.137817383,-37.9025154114],"type":"Point"}
}