{
  "type": "Feature",
  "properties": {
    "addr:full":"Shop 18 218 - 22 Dorset Rd Boronia VIC 3155",
    "addr:housenumber":"shop 18",
    "addr:postcode":"218 22;3155",
    "addr:street":"Dorset Rd",
    "iso:country":"AU",
    "sg:address":"Shop 18 218 - 22 Dorset Rd",
    "sg:city":"Boronia",
    "sg:classifiers":[
        {
            "category":"Fast Food",
            "type":"Food & Drink"
        }
    ],
    "sg:phone":"+61 3 9762 1826",
    "sg:postcode":"3155",
    "sg:province":"VIC",
    "sg:tags":[
        "away",
        "take"
    ],
    "wof:name":"Noodle Canteen",
    "wof:placetype":"venue"
},
  "geometry": {"coordinates":[145.28579711899999,-37.861869812],"type":"Point"}
}