{
  "type": "Feature",
  "properties": {
    "iso:country":"AU",
    "sg:address":"38 Barrabool Rd",
    "sg:city":"Highton",
    "sg:classifiers":[
        {
            "category":"Health Services",
            "subcategory":"Health Practitioner",
            "type":"Services"
        }
    ],
    "sg:phone":"+61 3 5243 3819",
    "sg:postcode":"3216",
    "sg:province":"VIC",
    "sg:tags":[
        "osteopath"
    ],
    "wof:name":"Procare Sports & Spinal",
    "wof:placetype":"venue"
},
  "geometry": {"coordinates":[144.32516479500001,-38.1708526611],"type":"Point"}
}