{
  "type": "Feature",
  "properties": {
    "addr:full":"Frenchville Rd North Rockhampton QLD 4701",
    "addr:postcode":"4701",
    "addr:street":"Frenchville Rd North",
    "iso:country":"AU",
    "sg:address":"Frenchville Rd",
    "sg:city":"North Rockhampton",
    "sg:classifiers":[
        {
            "category":"Education",
            "subcategory":"School",
            "type":"Public Place"
        }
    ],
    "sg:phone":"+61 7 4931 5337",
    "sg:postcode":"4701",
    "sg:province":"QLD",
    "sg:tags":[
        "state",
        "except",
        "nsw"
    ],
    "wof:name":"Frenchville Preschool",
    "wof:placetype":"venue"
},
  "geometry": {"coordinates":[150.54887390100001,-23.3438663483],"type":"Point"}
}