{
  "type": "Feature",
  "properties": {
    "addr:full":"192 Chapel Rd Bankstown NSW 2200",
    "addr:housenumber":"192",
    "addr:postcode":"2200",
    "addr:street":"Chapel Rd",
    "iso:country":"AU",
    "sg:address":"192 Chapel Rd",
    "sg:city":"Bankstown",
    "sg:classifiers":[
        {
            "category":"Health Services",
            "subcategory":"Dentist",
            "type":"Services"
        }
    ],
    "sg:phone":"+61 2 9708 1130",
    "sg:postcode":"2200",
    "sg:province":"NSW",
    "wof:name":"Mahony Tim",
    "wof:placetype":"venue"
},
  "geometry": {"coordinates":[151.031677,-33.920013],"type":"Point"}
}