{
  "type": "Feature",
  "properties": {
    "iso:country":"AU",
    "sg:address":"7 Purdie Ave",
    "sg:city":"Ardross",
    "sg:classifiers":[
        {
            "category":"Professional",
            "subcategory":"Business Services",
            "type":"Services"
        }
    ],
    "sg:phone":"+61 412 005 222",
    "sg:postcode":"6153",
    "sg:province":"WA",
    "sg:tags":[
        "drafting"
    ],
    "wof:name":"Ferrante Design Co.",
    "wof:placetype":"venue"
},
  "geometry": {"coordinates":[115.842506,-32.022919],"type":"Point"}
}