{
  "type": "Feature",
  "properties": {
    "addr:full":"Crn Appin & Orkney Sts Wangaratta VIC 3677",
    "addr:postcode":"3677",
    "addr:street":"Crn",
    "iso:country":"AU",
    "sg:address":"Crn Appin & Orkney Sts",
    "sg:city":"Wangaratta",
    "sg:classifiers":[
        {
            "category":"Education",
            "subcategory":"Kindergarten",
            "type":"Public Place"
        }
    ],
    "sg:phone":"+61 3 5721 6015",
    "sg:postcode":"3677",
    "sg:province":"VIC",
    "sg:tags":[
        "pre-schools"
    ],
    "wof:name":"Appin Park Kindergarten",
    "wof:placetype":"venue"
},
  "geometry": {"coordinates":[146.298065186,-36.358341217],"type":"Point"}
}