{
  "type": "Feature",
  "properties": {
    "iso:country":"AU",
    "sg:address":"25 Wheeler St",
    "sg:city":"Belmont",
    "sg:classifiers":[
        {
            "category":"Retail",
            "subcategory":"Auto Repair",
            "type":"Services"
        }
    ],
    "sg:phone":"+61 8 9277 1378",
    "sg:postcode":"6104",
    "sg:province":"WA",
    "sg:tags":[
        "repairer",
        "motor",
        "engineer"
    ],
    "wof:name":"Repco Authorised Service",
    "wof:placetype":"venue"
},
  "geometry": {"coordinates":[115.926513672,-31.9477405548],"type":"Point"}
}