{
  "type": "Feature",
  "properties": {
    "addr:full":"Wisemans Ferry Rd Cattai NSW 2756",
    "addr:postcode":"2756",
    "addr:street":"Wisemans Ferry Rd",
    "iso:country":"AU",
    "sg:address":"Wisemans Ferry Rd",
    "sg:city":"Cattai",
    "sg:classifiers":[
        {
            "category":"Building & Trades",
            "subcategory":"Plumbing",
            "type":"Services"
        }
    ],
    "sg:phone":"+61 2 4572 8805",
    "sg:postcode":"2756",
    "sg:province":"NSW",
    "sg:tags":[
        "plumber",
        "gasfitters"
    ],
    "wof:name":"Boring G",
    "wof:placetype":"venue"
},
  "geometry": {"coordinates":[150.91041564899999,-33.5544967651],"type":"Point"}
}