{
  "type": "Feature",
  "properties": {
    "addr:full":"Unit 13, 38- 46 South St Rydalmere NSW 2116",
    "addr:housenumber":"38 46",
    "addr:postcode":"2116",
    "addr:street":"South St",
    "iso:country":"AU",
    "sg:address":"Unit 13, 38- 46 South St",
    "sg:city":"Rydalmere",
    "sg:classifiers":[
        {
            "category":"Professional",
            "subcategory":"Testing Lab",
            "type":"Services"
        }
    ],
    "sg:phone":"+61 1300 767 071",
    "sg:postcode":"2116",
    "sg:province":"NSW",
    "sg:tags":[
        "inspection"
    ],
    "wof:name":"TechRentals",
    "wof:placetype":"venue"
},
  "geometry": {"coordinates":[151.01080322300001,-33.8342208862],"type":"Point"}
}