{
  "type": "Feature",
  "properties": {
    "iso:country":"AU",
    "sg:address":"Wimmers La",
    "sg:city":"Cooroy",
    "sg:classifiers":[
        {
            "category":"Home & Garden",
            "subcategory":"Building Materials",
            "type":"Retail Goods"
        }
    ],
    "sg:phone":"+61 7 5447 7457",
    "sg:postcode":"4563",
    "sg:province":"QLD",
    "sg:tags":[
        "merchant",
        "glass",
        "glazier"
    ],
    "wof:name":"Sunrise Glass Co",
    "wof:placetype":"venue"
},
  "geometry": {"coordinates":[152.909103394,-26.4178180695],"type":"Point"}
}