{
  "type": "Feature",
  "properties": {
    "addr:full":"708 Mowbray Rd Lane Cove NSW 2066",
    "addr:housenumber":"708",
    "addr:postcode":"2066",
    "addr:street":"Mowbray Rd",
    "iso:country":"AU",
    "sg:address":"708 Mowbray Rd",
    "sg:city":"Lane Cove",
    "sg:classifiers":[
        {
            "category":"Professional",
            "subcategory":"Computer Services",
            "type":"Services"
        }
    ],
    "sg:phone":"+61 2 9420 6700",
    "sg:postcode":"2066",
    "sg:province":"NSW",
    "sg:tags":[
        "equipment",
        "networking",
        "installation"
    ],
    "wof:name":"Dataflow Computer Services Pty Ltd",
    "wof:placetype":"venue"
},
  "geometry": {"coordinates":[151.14855957,-33.8036460876],"type":"Point"}
}