{
  "type": "Feature",
  "properties": {
    "addr:full":"2359 Wynnum Rd Wynnum QLD 4178",
    "addr:housenumber":"2359",
    "addr:postcode":"4178",
    "addr:street":"Wynnum Rd",
    "iso:country":"AU",
    "sg:address":"2359 Wynnum Rd",
    "sg:city":"Wynnum",
    "sg:classifiers":[
        {
            "category":"Home & Garden",
            "subcategory":"Carpets & Floor Coverings",
            "type":"Retail Goods"
        }
    ],
    "sg:phone":"+61 7 3396 1257",
    "sg:postcode":"4178",
    "sg:province":"QLD",
    "sg:tags":[
        "mat",
        "matting"
    ],
    "wof:name":"J B Lewis Distributors",
    "wof:placetype":"venue"
},
  "geometry": {"coordinates":[153.163986206,-27.4383525848],"type":"Point"}
}