{
  "type": "Feature",
  "properties": {
    "addr:full":"96 Moore St Liverpool NSW 2170",
    "addr:housenumber":"96",
    "addr:postcode":"2170",
    "addr:street":"Moore St",
    "iso:country":"AU",
    "sg:address":"96 Moore St",
    "sg:city":"Liverpool",
    "sg:classifiers":[
        {
            "category":"Communications",
            "subcategory":"Film & Video Production",
            "type":"Services"
        }
    ],
    "sg:phone":"+61 2 9600 6772",
    "sg:postcode":"2170",
    "sg:province":"NSW",
    "sg:tags":[
        "dvd",
        "library"
    ],
    "wof:name":"Dhadkan",
    "wof:placetype":"venue"
},
  "geometry": {"coordinates":[150.92332458499999,-33.9225654602],"type":"Point"}
}