{
  "type": "Feature",
  "properties": {
    "addr:full":"376 Main North Rd Blair Athol SA 5084",
    "addr:housenumber":"376",
    "addr:postcode":"5084",
    "addr:street":"Main North Rd",
    "iso:country":"AU",
    "sg:address":"376 Main North Rd",
    "sg:city":"Blair Athol",
    "sg:classifiers":[
        {
            "category":"Autos & Motor Vehicles",
            "subcategory":"Automobile Sales",
            "type":"Retail Goods"
        }
    ],
    "sg:phone":"+61 8 8359 5999",
    "sg:postcode":"5084",
    "sg:province":"SA",
    "sg:tags":[
        "car",
        "used"
    ],
    "wof:name":"Road & Track Motors",
    "wof:placetype":"venue"
},
  "geometry": {"coordinates":[138.601074219,-34.8642921448],"type":"Point"}
}