{
  "type": "Feature",
  "properties": {
    "addr:full":"44 Thomas Drv Chevron Island QLD 4217",
    "addr:housenumber":"44",
    "addr:postcode":"4217",
    "addr:street":"Thomas Drv Chevron",
    "iso:country":"AU",
    "sg:address":"44 Thomas Drv",
    "sg:city":"Chevron Island",
    "sg:classifiers":[
        {
            "category":"Travel",
            "subcategory":"Travel Agent",
            "type":"Entertainment"
        }
    ],
    "sg:phone":"+61 13 18 66",
    "sg:postcode":"4217",
    "sg:province":"QLD",
    "sg:tags":[
        "consultant"
    ],
    "wof:name":"Flight Centre",
    "wof:placetype":"venue"
},
  "geometry": {"coordinates":[153.419723511,-27.9981803894],"type":"Point"}
}