{
  "type": "Feature",
  "properties": {
    "addr:full":"Level 10, 15 Adelaide St Brisbane QLD 4000",
    "addr:housenumber":"15",
    "addr:postcode":"4000",
    "addr:street":"Adelaide St",
    "iso:country":"AU",
    "sg:address":"Level 10, 15 Adelaide St",
    "sg:city":"Brisbane",
    "sg:classifiers":[
        {
            "category":"Professional",
            "subcategory":"Business Services",
            "type":"Services"
        }
    ],
    "sg:phone":"+61 7 3210 1833",
    "sg:postcode":"4000",
    "sg:province":"QLD",
    "sg:tags":[
        "small",
        "advisory"
    ],
    "wof:name":"Maunsell Pennington Solicitors",
    "wof:placetype":"venue"
},
  "geometry": {"coordinates":[153.02308654800001,-27.4701156616],"type":"Point"}
}