{
  "type": "Feature",
  "properties": {
    "iso:country":"AU",
    "sg:address":"8 Racecourse Rd",
    "sg:city":"Brighton",
    "sg:classifiers":[
        {
            "category":"Professional",
            "subcategory":"Detective & Security Services",
            "type":"Services"
        }
    ],
    "sg:phone":"+61 3 6268 0668",
    "sg:postcode":"7030",
    "sg:province":"TAS",
    "sg:tags":[
        "equipment",
        "window",
        "doors"
    ],
    "wof:name":"Top Gun Glass & Aluminium Pty Ltd",
    "wof:placetype":"venue"
},
  "geometry": {"coordinates":[147.25038147000001,-42.6988677979],"type":"Point"}
}