{
  "type": "Feature",
  "properties": {
    "addr:full":"258-260 Johnston St Abbotsford VIC 3067",
    "addr:housenumber":"258-260",
    "addr:postcode":"3067",
    "addr:street":"Johnston St",
    "iso:country":"AU",
    "sg:address":"258-260 Johnston St",
    "sg:city":"Abbotsford",
    "sg:classifiers":[
        {
            "category":"Manufacturing",
            "subcategory":"Tools & Machinery",
            "type":"Manufacturing & Wholesale Goods"
        }
    ],
    "sg:phone":"+61 3 9419 5898",
    "sg:postcode":"3067",
    "sg:province":"VIC",
    "wof:name":"Abbotsford Tools",
    "wof:placetype":"venue"
},
  "geometry": {"coordinates":[144.993972778,-37.7997817993],"type":"Point"}
}