{
  "type": "Feature",
  "properties": {
    "addr:full":"72 Mersey Main Rd Spreyton TAS 7310",
    "addr:housenumber":"72",
    "addr:postcode":"7310",
    "addr:street":"Mersey Main Rd",
    "iso:country":"AU",
    "sg:address":"72 Mersey Main Rd",
    "sg:city":"Spreyton",
    "sg:classifiers":[
        {
            "category":"Food & Beverages",
            "subcategory":"Supermarket",
            "type":"Retail Goods"
        }
    ],
    "sg:phone":"+61 3 6427 2092",
    "sg:postcode":"7310",
    "sg:province":"TAS",
    "sg:tags":[
        "grocery",
        "store"
    ],
    "wof:name":"Value Plus IGA Stores",
    "wof:placetype":"venue"
},
  "geometry": {"coordinates":[146.344802856,-41.2172737122],"type":"Point"}
}