{
  "type": "Feature",
  "properties": {
    "addr:full":"60 Wittenberg Drv Canning Vale WA 6155",
    "addr:housenumber":"60",
    "addr:postcode":"6155",
    "addr:street":"Wittenberg Drv",
    "iso:country":"AU",
    "sg:address":"60 Wittenberg Drv",
    "sg:city":"Canning Vale",
    "sg:classifiers":[
        {
            "category":"Manufacturing",
            "subcategory":"Building Materials",
            "type":"Manufacturing & Wholesale Goods"
        }
    ],
    "sg:phone":"+61 8 9455 3622",
    "sg:postcode":"6155",
    "sg:province":"WA",
    "sg:tags":[
        "concrete",
        "product"
    ],
    "wof:name":"Reid Construction Systems",
    "wof:placetype":"venue"
},
  "geometry": {"coordinates":[115.923233,-32.068455],"type":"Point"}
}