{
  "type": "Feature",
  "properties": {
    "addr:full":"28 - 38 Albert St Preston VIC 3072",
    "addr:housenumber":"38",
    "addr:postcode":"3072",
    "addr:street":"Albert St",
    "iso:country":"AU",
    "sg:address":"28 - 38 Albert St",
    "sg:city":"Preston",
    "sg:classifiers":[
        {
            "category":"Bus Stop",
            "subcategory":"None",
            "type":"Transportation"
        }
    ],
    "sg:phone":"+61 3 9480 2866",
    "sg:postcode":"3072",
    "sg:province":"VIC",
    "sg:tags":[
        "galvanising",
        "tinning"
    ],
    "wof:name":"Industrial Galvanizers (Melbourne)",
    "wof:placetype":"venue"
},
  "geometry": {"coordinates":[145.02163696299999,-37.7491874695],"type":"Point"}
}