{
  "type": "Feature",
  "properties": {
    "addr:full":"1a Lynell St Hamilton QLD 4007",
    "addr:housenumber":"1a",
    "addr:postcode":"4007",
    "addr:street":"Lynell St",
    "iso:country":"AU",
    "sg:address":"1a Lynell St",
    "sg:city":"Hamilton",
    "sg:classifiers":[
        {
            "category":"Professional",
            "subcategory":"Employment Agencies",
            "type":"Services"
        }
    ],
    "sg:phone":"+61 7 3862 2027",
    "sg:postcode":"4007",
    "sg:province":"QLD",
    "sg:tags":[
        "provider",
        "internet"
    ],
    "wof:name":"Web Blue Hosting",
    "wof:placetype":"venue"
},
  "geometry": {"coordinates":[153.05186499999999,-27.435492],"type":"Point"}
}