{
  "type": "Feature",
  "properties": {
    "iso:country":"AU",
    "sg:address":"591 Bridge Rd",
    "sg:city":"Richmond",
    "sg:classifiers":[
        {
            "category":"Real Estate",
            "subcategory":"Architect",
            "type":"Services"
        }
    ],
    "sg:phone":"+61 3 9429 4255",
    "sg:postcode":"3121",
    "sg:province":"VIC",
    "wof:name":"B.H.A Pty Ltd",
    "wof:placetype":"venue"
},
  "geometry": {"coordinates":[145.010421753,-37.8195877075],"type":"Point"}
}