{
  "type": "Feature",
  "properties": {
    "addr:full":"288 Old South Head Rd Watsons Bay NSW 2030",
    "addr:housenumber":"288",
    "addr:postcode":"2030",
    "addr:street":"Old South Head Rd",
    "iso:country":"AU",
    "sg:address":"288 Old South Head Rd",
    "sg:city":"Watsons Bay",
    "sg:classifiers":[
        {
            "category":"Professional",
            "subcategory":"Management & Consulting",
            "type":"Services"
        }
    ],
    "sg:phone":"+61 2 9337 1421",
    "sg:postcode":"2030",
    "sg:province":"NSW",
    "sg:tags":[
        "consultant"
    ],
    "wof:name":"Cameron Consulting Group",
    "wof:placetype":"venue"
},
  "geometry": {"coordinates":[151.28367614699999,-33.8465538025],"type":"Point"}
}