{
  "type": "Feature",
  "properties": {
    "addr:full":"421 South Rd Moorabbin VIC 3189",
    "addr:housenumber":"421",
    "addr:postcode":"3189",
    "addr:street":"South Rd",
    "iso:country":"AU",
    "sg:address":"421 South Rd",
    "sg:city":"Moorabbin",
    "sg:classifiers":[
        {
            "category":"Personal",
            "type":"Services"
        }
    ],
    "sg:phone":"+61 3 9532 0811",
    "sg:postcode":"3189",
    "sg:province":"VIC",
    "sg:tags":[
        "counselling",
        "alcohol",
        "drug"
    ],
    "wof:name":"TaskForce Community Agency",
    "wof:placetype":"venue"
},
  "geometry": {"coordinates":[145.03585815400001,-37.932964325],"type":"Point"}
}