{
  "type": "Feature",
  "properties": {
    "addr:full":"Whittaker St Quirindi NSW 2343",
    "addr:postcode":"2343",
    "addr:street":"Whittaker St",
    "iso:country":"AU",
    "sg:address":"Whittaker St",
    "sg:city":"Quirindi",
    "sg:classifiers":[
        {
            "category":"Farming",
            "subcategory":"Farm & Veterinary Services",
            "type":"Manufacturing & Wholesale Goods"
        }
    ],
    "sg:phone":"+61 2 6746 1911",
    "sg:postcode":"2343",
    "sg:province":"NSW",
    "sg:tags":[
        "seedsman"
    ],
    "wof:name":"Websters Stock Feeds Pty Ltd",
    "wof:placetype":"venue"
},
  "geometry": {"coordinates":[150.67706298799999,-31.5127906799],"type":"Point"}
}