{
  "type": "Feature",
  "properties": {
    "iso:country":"AU",
    "sg:address":"36 Finnie Rd",
    "sg:city":"Deagon",
    "sg:classifiers":[
        {
            "category":"Personal",
            "subcategory":"Massage",
            "type":"Services"
        }
    ],
    "sg:phone":"+61 7 3602 5254",
    "sg:postcode":"4017",
    "sg:province":"QLD",
    "sg:tags":[
        "therapy"
    ],
    "wof:name":"Bluebell Therapies",
    "wof:placetype":"venue"
},
  "geometry": {"coordinates":[153.06336975100001,-27.3317699432],"type":"Point"}
}