{
  "type": "Feature",
  "properties": {
    "iso:country":"AU",
    "sg:address":"2 Nora St",
    "sg:city":"Maylands",
    "sg:classifiers":[
        {
            "category":"Building & Trades",
            "subcategory":"Landscaping Services",
            "type":"Services"
        }
    ],
    "sg:phone":"+61 411 199 886",
    "sg:postcode":"5069",
    "sg:province":"SA",
    "sg:tags":[
        "gardener"
    ],
    "wof:name":"Green Hornet",
    "wof:placetype":"venue"
},
  "geometry": {"coordinates":[138.637252808,-34.9086151123],"type":"Point"}
}