{
  "type": "Feature",
  "properties": {
    "iso:country":"AU",
    "sg:address":"49- 59 Owens St",
    "sg:city":"Wangaratta",
    "sg:classifiers":[
        {
            "category":"Food & Beverages",
            "subcategory":"Supermarket",
            "type":"Retail Goods"
        }
    ],
    "sg:phone":"+61 3 5721 6844",
    "sg:postcode":"3677",
    "sg:province":"VIC",
    "sg:tags":[
        "grocery",
        "store"
    ],
    "wof:name":"Safeway",
    "wof:placetype":"venue"
},
  "geometry": {"coordinates":[146.323974609,-36.3542022705],"type":"Point"}
}