{
  "type": "Feature",
  "properties": {
    "addr:full":"Shop 9024 Eastland Shopping Centre, 171 Maroondah Ringwood VIC 3134",
    "addr:housenumber":"9024;171",
    "addr:postcode":"3134",
    "addr:street":"Maroondah",
    "iso:country":"AU",
    "sg:address":"Shop 9024 Eastland Shopping Centre, 171 Maroondah",
    "sg:city":"Ringwood",
    "sg:classifiers":[
        {
            "category":"Shopping",
            "subcategory":"Shoes",
            "type":"Retail Goods"
        }
    ],
    "sg:phone":"+61 3 9870 0522",
    "sg:postcode":"3134",
    "sg:province":"VIC",
    "sg:tags":[
        "footwear"
    ],
    "wof:name":"Diana Ferrari",
    "wof:placetype":"venue"
},
  "geometry": {"coordinates":[145.229537964,-37.8148956299],"type":"Point"}
}