{
  "type": "Feature",
  "properties": {
    "addr:full":"114 Central Springs Rd Daylesford VIC 3460",
    "addr:housenumber":"114",
    "addr:postcode":"3460",
    "addr:street":"Central Springs Rd",
    "iso:country":"AU",
    "sg:address":"114 Central Springs Rd",
    "sg:city":"Daylesford",
    "sg:classifiers":[
        {
            "category":"Health Services",
            "subcategory":"Doctor",
            "type":"Services"
        }
    ],
    "sg:phone":"+61 3 5348 1166",
    "sg:postcode":"3460",
    "sg:province":"VIC",
    "sg:tags":[
        "medical",
        "practitioner"
    ],
    "wof:name":"D&#039;Ahremberg C A",
    "wof:placetype":"venue"
},
  "geometry": {"coordinates":[144.14309692399999,-37.3436584473],"type":"Point"}
}