{
  "type": "Feature",
  "properties": {
    "addr:full":"10 Northbow Crt Tallebudgera QLD 4228",
    "addr:housenumber":"10",
    "addr:postcode":"4228",
    "addr:street":"Northbow Crt",
    "iso:country":"AU",
    "sg:address":"10 Northbow Crt",
    "sg:city":"Tallebudgera",
    "sg:classifiers":[
        {
            "category":"Utilities",
            "subcategory":"Electric",
            "type":"Services"
        }
    ],
    "sg:phone":"+61 7 5522 6142",
    "sg:postcode":"4228",
    "sg:province":"QLD",
    "sg:tags":[
        "electrical",
        "contractor"
    ],
    "wof:name":"Don Chant Electrics",
    "wof:placetype":"venue"
},
  "geometry": {"coordinates":[153.437423706,-28.1461544037],"type":"Point"}
}