{
  "type": "Feature",
  "properties": {
    "addr:full":"124 Grand Pde Bonnells Bay NSW 2264",
    "addr:housenumber":"124",
    "addr:postcode":"2264",
    "addr:street":"Grand Pde",
    "iso:country":"AU",
    "sg:address":"124 Grand Pde",
    "sg:city":"Bonnells Bay",
    "sg:classifiers":[
        {
            "category":"Health Services",
            "subcategory":"Health Practitioner",
            "type":"Services"
        }
    ],
    "sg:phone":"+61 2 4973 4255",
    "sg:postcode":"2264",
    "sg:province":"NSW",
    "sg:tags":[
        "hypnotherapy"
    ],
    "wof:name":"Gambrill Peter",
    "wof:placetype":"venue"
},
  "geometry": {"coordinates":[151.526703,-33.10759],"type":"Point"}
}