{
  "type": "Feature",
  "properties": {
    "addr:full":"3/ 182 Jull St Armadale WA 6112",
    "addr:housenumber":"/ 182",
    "addr:postcode":"6112",
    "addr:street":"Jull St",
    "iso:country":"AU",
    "sg:address":"3/ 182 Jull St",
    "sg:city":"Armadale",
    "sg:classifiers":[
        {
            "category":"Real Estate",
            "subcategory":"Real Estate Agent",
            "type":"Services"
        }
    ],
    "sg:phone":"+61 8 9399 3666",
    "sg:postcode":"6112",
    "sg:province":"WA",
    "wof:name":"Westate Realty",
    "wof:placetype":"venue"
},
  "geometry": {"coordinates":[116.020599365,-32.1502418518],"type":"Point"}
}