{
  "type": "Feature",
  "properties": {
    "addr:full":"18-20 Bridge St (West) Benalla VIC 3672",
    "addr:housenumber":"18-20",
    "addr:postcode":"3672",
    "addr:street":"Bridge St West",
    "iso:country":"AU",
    "sg:address":"18-20 Bridge St",
    "sg:city":"(West) Benalla",
    "sg:classifiers":[
        {
            "category":"Retail",
            "subcategory":"Auto Repair",
            "type":"Services"
        }
    ],
    "sg:phone":"+61 3 5762 3388",
    "sg:postcode":"3672",
    "sg:province":"VIC",
    "sg:tags":[
        "clutch",
        "brake"
    ],
    "wof:name":"Goodyear Autocare",
    "wof:placetype":"venue"
},
  "geometry": {"coordinates":[145.98306299999999,-36.551987],"type":"Point"}
}