{
  "type": "Feature",
  "properties": {
    "addr:full":"Suite- C7 21 Lake St Cairns QLD 4870",
    "addr:housenumber":"21",
    "addr:postcode":"4870",
    "addr:street":"Lake St",
    "iso:country":"AU",
    "sg:address":"Suite- C7 21 Lake St",
    "sg:city":"Cairns",
    "sg:classifiers":[
        {
            "category":"Professional",
            "subcategory":"Management & Consulting",
            "type":"Services"
        }
    ],
    "sg:phone":"+61 411 369 620",
    "sg:postcode":"4870",
    "sg:province":"QLD",
    "sg:tags":[
        "project"
    ],
    "wof:name":"Civil Infrastructure Services",
    "wof:placetype":"venue"
},
  "geometry": {"coordinates":[145.687255859,-16.8890190125],"type":"Point"}
}