{
  "type": "Feature",
  "properties": {
    "addr:full":"PO Box 3271 Joondalup WA 6027",
    "addr:postcode":"6027",
    "iso:country":"AU",
    "sg:address":"PO Box 3271",
    "sg:city":"Joondalup",
    "sg:phone":"+61 8 9305 7570",
    "sg:postcode":"6027",
    "sg:province":"WA",
    "wof:name":"Windscreens West",
    "wof:placetype":"venue"
},
  "geometry": {"coordinates":[115.759986877,-31.7324905396],"type":"Point"}
}