{
  "type": "Feature",
  "properties": {
    "addr:full":"38 Fortune St Narrogin WA 6312",
    "addr:housenumber":"38",
    "addr:postcode":"6312",
    "addr:street":"Fortune St",
    "iso:country":"AU",
    "sg:address":"38 Fortune St",
    "sg:city":"Narrogin",
    "sg:classifiers":[
        {
            "category":"Banks & Credit Unions",
            "subcategory":"Bank",
            "type":"Services"
        }
    ],
    "sg:phone":"+61 13 20 32",
    "sg:postcode":"6312",
    "sg:province":"WA",
    "wof:name":"Westpac",
    "wof:placetype":"venue"
},
  "geometry": {"coordinates":[117.177513123,-32.9348258972],"type":"Point"}
}