{
  "type": "Feature",
  "properties": {
    "iso:country":"AU",
    "sg:address":"Suite 502, 152 Bunnerong Rd",
    "sg:city":"Eastgardens",
    "sg:classifiers":[
        {
            "category":"Health Services",
            "subcategory":"Health Practitioner",
            "type":"Services"
        }
    ],
    "sg:phone":"+61 417 223 109",
    "sg:postcode":"2036",
    "sg:province":"NSW",
    "sg:tags":[
        "pathologist",
        "speech"
    ],
    "wof:name":"O'Meally-Spence Martha",
    "wof:placetype":"venue"
},
  "geometry": {"coordinates":[151.226486206,-33.9449501038],"type":"Point"}
}