{
  "type": "Feature",
  "properties": {
    "iso:country":"AU",
    "sg:address":"171 Merrylands Rd",
    "sg:city":"Merrylands",
    "sg:classifiers":[
        {
            "category":"Real Estate",
            "subcategory":"Real Estate Agent",
            "type":"Services"
        }
    ],
    "sg:phone":"+61 2 9682 7777",
    "sg:postcode":"2160",
    "sg:province":"NSW",
    "wof:name":"Andrew Robert R-Merrylands",
    "wof:placetype":"venue"
},
  "geometry": {"coordinates":[150.99000549300001,-33.836391449],"type":"Point"}
}