{
  "type": "Feature",
  "properties": {
    "addr:full":"Suite 17, 149 Queen St Concord West NSW 2138",
    "addr:housenumber":"149",
    "addr:postcode":"2138",
    "addr:street":"Queen St",
    "iso:country":"AU",
    "sg:address":"Suite 17, 149 Queen St",
    "sg:city":"Concord West",
    "sg:classifiers":[
        {
            "category":"Building & Trades",
            "subcategory":"Cleaning & Sanitation",
            "type":"Services"
        }
    ],
    "sg:phone":"+61 2 9898 0476",
    "sg:postcode":"2138",
    "sg:province":"NSW",
    "sg:tags":[
        "industrial",
        "commercial",
        "contractor"
    ],
    "wof:name":"Always Complete Cleaning Pty Ltd",
    "wof:placetype":"venue"
},
  "geometry": {"coordinates":[151.08612060600001,-33.8490638733],"type":"Point"}
}