{
  "type": "Feature",
  "properties": {
    "addr:full":"13 Ferguson St Abbotsford VIC 3067",
    "addr:housenumber":"13",
    "addr:postcode":"3067",
    "addr:street":"Ferguson St",
    "iso:country":"AU",
    "sg:address":"13 Ferguson St",
    "sg:city":"Abbotsford",
    "sg:classifiers":[
        {
            "category":"Professional",
            "subcategory":"Art Services",
            "type":"Services"
        }
    ],
    "sg:phone":"+61 3 9417 0170",
    "sg:postcode":"3067",
    "sg:province":"VIC",
    "sg:tags":[
        "graphic",
        "designer"
    ],
    "wof:name":"Pulp Free Design",
    "wof:placetype":"venue"
},
  "geometry": {"coordinates":[144.99232482900001,-37.8088989258],"type":"Point"}
}