{
  "type": "Feature",
  "properties": {
    "iso:country":"AU",
    "sg:address":"314 Sneaths Rd",
    "sg:city":"Alstonvalle",
    "sg:classifiers":[
        {
            "category":"Building & Trades",
            "subcategory":"Construction",
            "type":"Services"
        }
    ],
    "sg:phone":"+61 2 6628 1511",
    "sg:postcode":"2477",
    "sg:province":"NSW",
    "sg:tags":[
        "contractor"
    ],
    "wof:name":"Young Ian Builder",
    "wof:placetype":"venue"
},
  "geometry": {"coordinates":[153.42767334000001,-28.806224823],"type":"Point"}
}