{
  "type": "Feature",
  "properties": {
    "iso:country":"AU",
    "sg:address":"22 Coongan Ave",
    "sg:city":"Greenmount",
    "sg:classifiers":[
        {
            "category":"Health Services",
            "subcategory":"Nursing And Care Facility",
            "type":"Services"
        }
    ],
    "sg:phone":"+61 8 9294 1944",
    "sg:postcode":"6056",
    "sg:province":"WA",
    "sg:tags":[
        "home"
    ],
    "wof:name":"Undercliffe Nursing Home",
    "wof:placetype":"venue"
},
  "geometry": {"coordinates":[116.043159485,-31.9012641907],"type":"Point"}
}