{
  "type": "Feature",
  "properties": {
    "addr:full":"PO Box 103 Scarborough WA 6922",
    "addr:postcode":"6922",
    "iso:country":"AU",
    "sg:address":"PO Box 103",
    "sg:city":"Scarborough",
    "sg:classifiers":[
        {
            "category":"Manufacturing",
            "subcategory":"Jewelry",
            "type":"Manufacturing & Wholesale Goods"
        }
    ],
    "sg:phone":"+61 424 472 440",
    "sg:postcode":"6922",
    "sg:province":"WA",
    "sg:tags":[
        "designer",
        "jewellery"
    ],
    "wof:name":"Giselle Design",
    "wof:placetype":"venue"
},
  "geometry": {"coordinates":[115.760162353,-31.8943595886],"type":"Point"}
}