{
  "type": "Feature",
  "properties": {
    "addr:full":"350 Taylors Rd Delahey VIC 3037",
    "addr:housenumber":"350",
    "addr:postcode":"3037",
    "addr:street":"Taylors Rd",
    "iso:country":"AU",
    "sg:address":"350 Taylors Rd",
    "sg:city":"Delahey",
    "sg:classifiers":[
        {
            "category":"Food & Beverages",
            "subcategory":"Bakery",
            "type":"Retail Goods"
        }
    ],
    "sg:phone":"+61 3 9356 9906",
    "sg:postcode":"3037",
    "sg:province":"VIC",
    "sg:tags":[
        "baker"
    ],
    "wof:name":"T R Hot Bread",
    "wof:placetype":"venue"
},
  "geometry": {"coordinates":[144.77032500000001,-37.726089],"type":"Point"}
}