{
  "type": "Feature",
  "properties": {
    "iso:country":"AU",
    "sg:address":"16 Edward St",
    "sg:city":"Strathalbyn",
    "sg:classifiers":[
        {
            "category":"Building & Trades",
            "subcategory":"Plumbing",
            "type":"Services"
        }
    ],
    "sg:phone":"+61 422 316 530",
    "sg:postcode":"5255",
    "sg:province":"SA",
    "sg:tags":[
        "plumber",
        "gasfitters"
    ],
    "wof:name":"Alan Young",
    "wof:placetype":"venue"
},
  "geometry": {"coordinates":[138.88897705100001,-35.2633171082],"type":"Point"}
}