{
  "type": "Feature",
  "properties": {
    "addr:full":"Emerald Airport Emerald QLD 4720",
    "addr:postcode":"4720",
    "iso:country":"AU",
    "sg:address":"Emerald Airport",
    "sg:city":"Emerald",
    "sg:classifiers":[
        {
            "category":"Retail",
            "subcategory":"Auto Rental",
            "type":"Services"
        }
    ],
    "sg:phone":"+61 7 4982 0693",
    "sg:postcode":"4720",
    "sg:province":"QLD",
    "sg:tags":[
        "car",
        "hire",
        "minibus"
    ],
    "wof:name":"Hertz.",
    "wof:placetype":"venue"
},
  "geometry": {"coordinates":[148.155518,-23.510698],"type":"Point"}
}