{
  "type": "Feature",
  "properties": {
    "addr:full":"Bellevue St St Peters NSW 2044",
    "addr:postcode":"2044",
    "addr:street":"Bellevue St",
    "iso:country":"AU",
    "sg:address":"Bellevue St",
    "sg:city":"St Peters",
    "sg:classifiers":[
        {
            "category":"Professional",
            "type":"Services"
        }
    ],
    "sg:phone":"+61 2 9516 4239",
    "sg:postcode":"2044",
    "sg:province":"NSW",
    "sg:tags":[
        "transport"
    ],
    "wof:name":"Osgood Holdings Ltd",
    "wof:placetype":"venue"
},
  "geometry": {"coordinates":[151.169861,-33.92012],"type":"Point"}
}