{
  "type": "Feature",
  "properties": {
    "iso:country":"AU",
    "sg:address":"459 New Canterbury Rd",
    "sg:city":"Dulwich Hill",
    "sg:classifiers":[
        {
            "category":"Personal",
            "subcategory":"Beauty Salon",
            "type":"Services"
        }
    ],
    "sg:phone":"+61 2 9564 5143",
    "sg:postcode":"2203",
    "sg:province":"NSW",
    "sg:tags":[
        "hairdresser"
    ],
    "wof:name":"Bare and Dare Hair & Beauty Studio",
    "wof:placetype":"venue"
},
  "geometry": {"coordinates":[151.136353,-33.905766],"type":"Point"}
}