{
  "type": "Feature",
  "properties": {
    "addr:full":"459 New Canterbury Rd Dulwich Hill NSW 2203",
    "addr:housenumber":"459",
    "addr:postcode":"2203",
    "addr:street":"New Canterbury Rd",
    "iso:country":"AU",
    "sg:address":"459 New Canterbury Rd",
    "sg:city":"Dulwich Hill",
    "sg:classifiers":[
        {
            "category":"Personal",
            "subcategory":"Beauty Salon",
            "type":"Services"
        }
    ],
    "sg:phone":"+61 2 9564 5143",
    "sg:postcode":"2203",
    "sg:province":"NSW",
    "sg:tags":[
        "hairdresser"
    ],
    "wof:name":"Bare and Dare Hair & Beauty Studio",
    "wof:placetype":"venue"
},
  "geometry": {"coordinates":[151.13635300000001,-33.905766],"type":"Point"}
}