{
  "type": "Feature",
  "properties": {
    "iso:country":"AU",
    "sg:address":"173 Carlisle St",
    "sg:city":"Balaclava",
    "sg:classifiers":[
        {
            "category":"Shopping",
            "subcategory":"Jewelry",
            "type":"Retail Goods"
        }
    ],
    "sg:phone":"+61 3 9531 2834",
    "sg:postcode":"3183",
    "sg:province":"VIC",
    "sg:tags":[
        "jeweller"
    ],
    "wof:name":"Taylor H T",
    "wof:placetype":"venue"
},
  "geometry": {"coordinates":[144.99266052199999,-37.8687705994],"type":"Point"}
}