{
  "type": "Feature",
  "properties": {
    "addr:full":"1 Yanco Ave Leeton NSW 2705",
    "addr:housenumber":"1",
    "addr:postcode":"2705",
    "addr:street":"Yanco Ave",
    "iso:country":"AU",
    "sg:address":"1 Yanco Ave",
    "sg:city":"Leeton",
    "sg:classifiers":[
        {
            "category":"Travel",
            "subcategory":"Hotels & Motels",
            "type":"Entertainment"
        }
    ],
    "sg:phone":"+61 2 6953 2955",
    "sg:postcode":"2705",
    "sg:province":"NSW",
    "wof:name":"Riverina Motel",
    "wof:placetype":"venue"
},
  "geometry": {"coordinates":[146.41049194300001,-34.5560646057],"type":"Point"}
}