{
  "type": "Feature",
  "properties": {
    "addr:full":"90 Turrella St Turrella NSW 2205",
    "addr:housenumber":"90",
    "addr:postcode":"2205",
    "addr:street":"Turrella St",
    "iso:country":"AU",
    "sg:address":"90 Turrella St",
    "sg:city":"Turrella",
    "sg:classifiers":[
        {
            "category":"Building & Trades",
            "subcategory":"Construction",
            "type":"Services"
        }
    ],
    "sg:phone":"+61 2 9597 4346",
    "sg:postcode":"2205",
    "sg:province":"NSW",
    "sg:tags":[
        "builder",
        "designer",
        "room",
        "cool"
    ],
    "wof:name":"Insulated Building Materials Design & Construction Pty Ltd",
    "wof:placetype":"venue"
},
  "geometry": {"coordinates":[151.144363,-33.930168],"type":"Point"}
}