{
  "type": "Feature",
  "properties": {
    "iso:country":"AU",
    "sg:address":"1790 South Gippsland Hwy",
    "sg:city":"Cranbourne",
    "sg:classifiers":[
        {
            "category":"Wholesale",
            "subcategory":"Auto Parts",
            "type":"Manufacturing & Wholesale Goods"
        }
    ],
    "sg:phone":"+61 3 5996 1110",
    "sg:postcode":"3977",
    "sg:province":"VIC",
    "sg:tags":[
        "recyclers"
    ],
    "wof:name":"Abacus Auto Parts",
    "wof:placetype":"venue"
},
  "geometry": {"coordinates":[145.30751037600001,-38.1417274475],"type":"Point"}
}