{
  "type": "Feature",
  "properties": {
    "iso:country":"AU",
    "sg:address":"PO Box 116",
    "sg:city":"Mt Kuring-gai",
    "sg:classifiers":[
        {
            "category":"Manufacturing",
            "subcategory":"Jewelry",
            "type":"Manufacturing & Wholesale Goods"
        }
    ],
    "sg:phone":"+61 2 9477 7620",
    "sg:postcode":"2080",
    "sg:province":"NSW",
    "sg:tags":[
        "mfrg",
        "jeweller"
    ],
    "wof:name":"Savoy Jewellery Aust Pty Ltd",
    "wof:placetype":"venue"
},
  "geometry": {"coordinates":[151.13221740700001,-33.6463508606],"type":"Point"}
}