{
  "type": "Feature",
  "properties": {
    "iso:country":"AU",
    "sg:address":"Suite 1/ 90 Pacific Hwy",
    "sg:city":"Roseville",
    "sg:classifiers":[
        {
            "category":"Real Estate",
            "subcategory":"Architect",
            "type":"Services"
        }
    ],
    "sg:phone":"+61 2 9413 3099",
    "sg:postcode":"2069",
    "sg:province":"NSW",
    "wof:name":"Mitchell Group Architects",
    "wof:placetype":"venue"
},
  "geometry": {"coordinates":[151.17723083499999,-33.784942627],"type":"Point"}
}