{
  "type": "Feature",
  "properties": {
    "addr:full":"32 A Kennard St Kensington WA 6151",
    "addr:housenumber":"32 a",
    "addr:postcode":"6151",
    "addr:street":"Kennard St",
    "iso:country":"AU",
    "sg:address":"32 A Kennard St",
    "sg:city":"Kensington",
    "sg:classifiers":[
        {
            "category":"Personal",
            "subcategory":"Beauty Salon",
            "type":"Services"
        }
    ],
    "sg:phone":"+61 8 9367 2009",
    "sg:postcode":"6151",
    "sg:province":"WA",
    "sg:tags":[
        "hairdresser"
    ],
    "wof:name":"Hair On Kennard",
    "wof:placetype":"venue"
},
  "geometry": {"coordinates":[115.889427,-31.984135],"type":"Point"}
}