{
  "type": "Feature",
  "properties": {
    "addr:full":"Lvl 2 / 67 Astor Tce Spring Hill QLD 4000",
    "addr:housenumber":"/ 67",
    "addr:postcode":"4000",
    "addr:street":"Astor Tce",
    "iso:country":"AU",
    "sg:address":"Lvl 2 / 67",
    "sg:city":"Astor Tce Spring Hill",
    "sg:classifiers":[
        {
            "category":"Professional",
            "subcategory":"Testing Lab",
            "type":"Services"
        }
    ],
    "sg:phone":"+61 7 3832 6265",
    "sg:postcode":"4000",
    "sg:province":"QLD",
    "sg:tags":[
        "inspection"
    ],
    "wof:name":"Concrete Slab Technology Pty Ltd",
    "wof:placetype":"venue"
},
  "geometry": {"coordinates":[153.02638244600001,-27.4634857178],"type":"Point"}
}