{
  "type": "Feature",
  "properties": {
    "addr:full":"Unit 3/51-53 Kewdale Road, Welshpool WA 6106",
    "addr:housenumber":"/ 51-53",
    "addr:postcode":"6106",
    "addr:street":"Kewdale Road",
    "iso:country":"AU",
    "sg:address":"Unit 3/51-53 Kewdale Road,",
    "sg:city":"Welshpool",
    "sg:classifiers":[
        {
            "category":"Taxi",
            "type":"Transportation"
        }
    ],
    "sg:phone":"+61 8 9352 5800",
    "sg:postcode":"6106",
    "sg:province":"WA",
    "sg:tags":[
        "truck"
    ],
    "wof:name":"Capital Transport",
    "wof:placetype":"venue"
},
  "geometry": {"coordinates":[115.954376221,-31.9845142365],"type":"Point"}
}