{
  "type": "Feature",
  "properties": {
    "iso:country":"AU",
    "sg:address":"163 Sailors Bay Rd",
    "sg:city":"Northbridge",
    "sg:classifiers":[
        {
            "category":"Building & Trades",
            "subcategory":"Landscaping Services",
            "type":"Services"
        }
    ],
    "sg:phone":"+61 2 9388 1570",
    "sg:postcode":"2063",
    "sg:province":"NSW",
    "sg:tags":[
        "consultant"
    ],
    "wof:name":"Award Project Management & Building Consultant Pty Ltd",
    "wof:placetype":"venue"
},
  "geometry": {"coordinates":[151.21182250999999,-33.8108482361],"type":"Point"}
}