{
  "type": "Feature",
  "properties": {
    "iso:country":"AU",
    "sg:address":"76 Wideview Rd",
    "sg:city":"Berowra Heights",
    "sg:classifiers":[
        {
            "category":"Professional",
            "subcategory":"Business Services",
            "type":"Services"
        }
    ],
    "sg:phone":"+61 2 9456 5156",
    "sg:postcode":"2082",
    "sg:province":"NSW",
    "sg:tags":[
        "broker"
    ],
    "wof:name":"Objective Solutions Pty Ltd",
    "wof:placetype":"venue"
},
  "geometry": {"coordinates":[151.14576721200001,-33.6056213379],"type":"Point"}
}