{
  "type": "Feature",
  "properties": {
    "addr:full":"84 High St Berwick VIC 3806",
    "addr:housenumber":"84",
    "addr:postcode":"3806",
    "addr:street":"High St",
    "iso:country":"AU",
    "sg:address":"84 High St",
    "sg:city":"Berwick",
    "sg:classifiers":[
        {
            "category":"Food & Beverages",
            "subcategory":"Bakery",
            "type":"Retail Goods"
        }
    ],
    "sg:phone":"+61 3 9707 3771",
    "sg:postcode":"3806",
    "sg:province":"VIC",
    "sg:tags":[
        "cake",
        "shop",
        "pastry"
    ],
    "wof:name":"Berwick Village Bakery",
    "wof:placetype":"venue"
},
  "geometry": {"coordinates":[145.34544372600001,-38.0314559937],"type":"Point"}
}