{
  "type": "Feature",
  "properties": {
    "addr:full":"25- 27 Ceafield Rd Para Hills SA 5096",
    "addr:housenumber":"27",
    "addr:postcode":"5096",
    "addr:street":"Ceafield Rd Para",
    "iso:country":"AU",
    "sg:address":"25- 27 Ceafield Rd",
    "sg:city":"Para Hills",
    "sg:classifiers":[
        {
            "category":"Building & Trades",
            "subcategory":"Landscaping Services",
            "type":"Services"
        }
    ],
    "sg:phone":"+61 8 8258 3700",
    "sg:postcode":"5096",
    "sg:province":"SA",
    "sg:tags":[
        "stump",
        "tree",
        "felling",
        "removal"
    ],
    "wof:name":"Austral",
    "wof:placetype":"venue"
},
  "geometry": {"coordinates":[138.644622803,-34.8000297546],"type":"Point"}
}