{
  "type": "Feature",
  "properties": {
    "addr:full":"80 Jane Ave Lake Heights NSW 2502",
    "addr:housenumber":"80",
    "addr:postcode":"2502",
    "addr:street":"Jane Ave",
    "iso:country":"AU",
    "sg:address":"80 Jane Ave",
    "sg:city":"Lake Heights",
    "sg:classifiers":[
        {
            "category":"Social Services",
            "subcategory":"Child Care",
            "type":"Services"
        }
    ],
    "sg:phone":"+61 2 4274 0401",
    "sg:postcode":"2502",
    "sg:province":"NSW",
    "wof:name":"Wilbur Duckling Childcare Centre",
    "wof:placetype":"venue"
},
  "geometry": {"coordinates":[150.874741,-34.487637],"type":"Point"}
}