{
  "type": "Feature",
  "properties": {
    "iso:country":"AU",
    "sg:address":"371- 375 Warrigal Rd",
    "sg:city":"Cheltenham",
    "sg:classifiers":[
        {
            "category":"Retail",
            "subcategory":"Storage",
            "type":"Services"
        }
    ],
    "sg:phone":"+61 3 9553 2211",
    "sg:postcode":"3192",
    "sg:province":"VIC",
    "wof:name":"EZY Self Storage Group Pty Ltd",
    "wof:placetype":"venue"
},
  "geometry": {"coordinates":[145.07635498100001,-37.9540901184],"type":"Point"}
}