{
  "type": "Feature",
  "properties": {
    "addr:full":"Factory 1/ 224 Princes Hwy Dandenong VIC 3175",
    "addr:housenumber":"/ 224",
    "addr:postcode":"3175",
    "addr:street":"Princes Hwy",
    "iso:country":"AU",
    "sg:address":"Factory 1/ 224 Princes Hwy",
    "sg:city":"Dandenong",
    "sg:classifiers":[
        {
            "category":"Retail",
            "subcategory":"Storage",
            "type":"Services"
        }
    ],
    "sg:phone":"+61 3 9792 2691",
    "sg:postcode":"3175",
    "sg:province":"VIC",
    "wof:name":"Transcare Pty Ltd",
    "wof:placetype":"venue"
},
  "geometry": {"coordinates":[145.19937133799999,-37.9707527161],"type":"Point"}
}