{
  "type": "Feature",
  "properties": {
    "iso:country":"AU",
    "sg:address":"104 Robey St",
    "sg:city":"Mascot",
    "sg:classifiers":[
        {
            "category":"Manufacturing",
            "subcategory":"Tools & Machinery",
            "type":"Manufacturing & Wholesale Goods"
        }
    ],
    "sg:phone":"+61 2 9667 1650",
    "sg:postcode":"2020",
    "sg:province":"NSW",
    "sg:tags":[
        "toolmaker"
    ],
    "wof:name":"Aviation Tooling Pty Ltd",
    "wof:placetype":"venue"
},
  "geometry": {"coordinates":[151.187957764,-33.9307556152],"type":"Point"}
}