{
  "type": "Feature",
  "properties": {
    "addr:full":"Rear 152-154, Hume Hwy (Entry from Hollywood Dr) Lansvale NSW 2166",
    "addr:housenumber":"152-154;from",
    "addr:postcode":"2166",
    "addr:street":"Hume Hwy Entry;Dr",
    "iso:country":"AU",
    "sg:address":"Rear 152-154, Hume Hwy",
    "sg:city":"(Entry from Hollywood Dr) Lansvale",
    "sg:classifiers":[
        {
            "category":"Building & Trades",
            "subcategory":"Construction",
            "type":"Services"
        }
    ],
    "sg:phone":"+61 404 339 984",
    "sg:postcode":"2166",
    "sg:province":"NSW",
    "sg:tags":[
        "fencing",
        "contractor"
    ],
    "wof:name":"Platinum Steel Designs",
    "wof:placetype":"venue"
},
  "geometry": {"coordinates":[150.957305908,-33.8948059082],"type":"Point"}
}