{
  "type": "Feature",
  "properties": {
    "iso:country":"AU",
    "sg:address":"PO Box 52",
    "sg:city":"Lane Cove",
    "sg:classifiers":[
        {
            "category":"Education",
            "subcategory":"Special Training",
            "type":"Public Place"
        }
    ],
    "sg:phone":"+61 2 9972 7606",
    "sg:postcode":"2066",
    "sg:province":"NSW",
    "sg:tags":[
        "development"
    ],
    "wof:name":"Plus Plus Pty Ltd",
    "wof:placetype":"venue"
},
  "geometry": {"coordinates":[151.16998290999999,-33.8138999939],"type":"Point"}
}