{
  "type": "Feature",
  "properties": {
    "addr:full":"133 Church St Brighton VIC 3186",
    "addr:housenumber":"133",
    "addr:postcode":"3186",
    "addr:street":"Church St",
    "iso:country":"AU",
    "sg:address":"133 Church St",
    "sg:city":"Brighton",
    "sg:classifiers":[
        {
            "category":"Restaurant",
            "type":"Food & Drink"
        }
    ],
    "sg:phone":"+61 3 9592 1671",
    "sg:postcode":"3186",
    "sg:province":"VIC",
    "wof:name":"Akiya Japanese Restaurant",
    "wof:placetype":"venue"
},
  "geometry": {"coordinates":[144.99647522000001,-37.9155693054],"type":"Point"}
}