{
  "type": "Feature",
  "properties": {
    "addr:full":"30 Decco Drv Campbellfield VIC 3061",
    "addr:housenumber":"30",
    "addr:postcode":"3061",
    "addr:street":"Decco Drv",
    "iso:country":"AU",
    "sg:address":"30 Decco Drv",
    "sg:city":"Campbellfield",
    "sg:classifiers":[
        {
            "category":"Food & Beverages",
            "subcategory":"Bakery",
            "type":"Retail Goods"
        }
    ],
    "sg:phone":"+61 3 9355 0999",
    "sg:postcode":"3061",
    "sg:province":"VIC",
    "sg:tags":[
        "baker"
    ],
    "wof:name":"Middle East Bakeries Pty Ltd",
    "wof:placetype":"venue"
},
  "geometry": {"coordinates":[144.95309448200001,-37.6790504456],"type":"Point"}
}