{
  "type": "Feature",
  "properties": {
    "iso:country":"AU",
    "sg:address":"Unit 2, 6-8 Cavendish St",
    "sg:city":"Mittagong",
    "sg:classifiers":[
        {
            "category":"Shopping",
            "subcategory":"Crafts & Fabrics",
            "type":"Retail Goods"
        }
    ],
    "sg:phone":"+61 2 4871 1388",
    "sg:postcode":"2575",
    "sg:province":"NSW",
    "sg:tags":[
        "quilting"
    ],
    "wof:name":"Jap?nache",
    "wof:placetype":"venue"
},
  "geometry": {"coordinates":[150.433792114,-34.4481010437],"type":"Point"}
}