{
  "type": "Feature",
  "properties": {
    "addr:full":"Shop t14 The Shops at Ellenbrook, Cnr Pinnaster & Promenade Rds Ellenbrook WA 6069",
    "addr:postcode":"6069",
    "addr:street":"Cnr Pinnaster & Promenade Rds",
    "iso:country":"AU",
    "sg:address":"Shop t14 The Shops at Ellenbrook, Cnr Pinnaster & Promenade Rds",
    "sg:city":"Ellenbrook",
    "sg:classifiers":[
        {
            "category":"Retail",
            "subcategory":"Repair Shop",
            "type":"Services"
        }
    ],
    "sg:phone":"+61 8 9297 2057",
    "sg:postcode":"6069",
    "sg:province":"WA",
    "sg:tags":[
        "cleaner",
        "part",
        "vacuum"
    ],
    "wof:name":"Godfreys",
    "wof:placetype":"venue"
},
  "geometry": {"coordinates":[116.024726868,-31.7282371521],"type":"Point"}
}