{
  "type": "Feature",
  "properties": {
    "iso:country":"AU",
    "sg:address":"Cnr Alexandria & Oborn Rds",
    "sg:city":"Mt Barker",
    "sg:classifiers":[
        {
            "category":"Home & Garden",
            "subcategory":"Household Appliances",
            "type":"Retail Goods"
        }
    ],
    "sg:phone":"+61 8 8391 1068",
    "sg:postcode":"5251",
    "sg:province":"SA",
    "sg:tags":[
        "heating",
        "system"
    ],
    "wof:name":"Adelaide Hills Wood Heating Centre",
    "wof:placetype":"venue"
},
  "geometry": {"coordinates":[138.87495422399999,-35.0776367188],"type":"Point"}
}