{
  "type": "Feature",
  "properties": {
    "iso:country":"AU",
    "sg:address":"41 Court Rd",
    "sg:city":"Fairfield",
    "sg:classifiers":[
        {
            "category":"Health Services",
            "subcategory":"Doctor",
            "type":"Services"
        }
    ],
    "sg:phone":"+61 2 9724 0038",
    "sg:postcode":"2165",
    "sg:province":"NSW",
    "sg:tags":[
        "podiatrist"
    ],
    "wof:name":"I C B Gait & Posture Clinic",
    "wof:placetype":"venue"
},
  "geometry": {"coordinates":[150.957855225,-33.8698234558],"type":"Point"}
}