{
  "type": "Feature",
  "properties": {
    "iso:country":"AU",
    "sg:address":"137 Bellevue Rd",
    "sg:city":"Bellevue Hill",
    "sg:classifiers":[
        {
            "category":"Building & Trades",
            "subcategory":"Construction",
            "type":"Services"
        }
    ],
    "sg:phone":"+61 412 624 624",
    "sg:postcode":"2023",
    "sg:province":"NSW",
    "sg:tags":[
        "management"
    ],
    "wof:name":"The Hopetoun Group Pty Ltd",
    "wof:placetype":"venue"
},
  "geometry": {"coordinates":[151.24876403799999,-33.8801498413],"type":"Point"}
}