{
  "type": "Feature",
  "properties": {
    "addr:full":"20 Wilma St Toowoomba QLD 4350",
    "addr:housenumber":"20",
    "addr:postcode":"4350",
    "addr:street":"Wilma St",
    "iso:country":"AU",
    "sg:address":"20 Wilma St",
    "sg:city":"Toowoomba",
    "sg:classifiers":[
        {
            "category":"Building & Trades",
            "subcategory":"Construction",
            "type":"Services"
        }
    ],
    "sg:phone":"+61 7 4635 3382",
    "sg:postcode":"4350",
    "sg:province":"QLD",
    "sg:tags":[
        "decking",
        "contractor"
    ],
    "wof:name":"John Moes",
    "wof:placetype":"venue"
},
  "geometry": {"coordinates":[151.95962499999999,-27.585381],"type":"Point"}
}