{
  "type": "Feature",
  "properties": {
    "addr:full":"PO Box 74 Brighton TAS 7030",
    "addr:postcode":"7030",
    "iso:country":"AU",
    "sg:address":"PO Box 74",
    "sg:city":"Brighton",
    "sg:classifiers":[
        {
            "category":"Building & Trades",
            "subcategory":"Construction",
            "type":"Services"
        }
    ],
    "sg:phone":"+61 3 6268 1755",
    "sg:postcode":"7030",
    "sg:province":"TAS",
    "sg:tags":[
        "concrete",
        "contractor"
    ],
    "wof:name":"Andrew Bullock",
    "wof:placetype":"venue"
},
  "geometry": {"coordinates":[147.25169372600001,-42.6992988586],"type":"Point"}
}