{
  "type": "Feature",
  "properties": {
    "iso:country":"AU",
    "sg:address":"The Niche, Suite A, 11 Aberdare Rd",
    "sg:city":"Nedlands",
    "sg:classifiers":[
        {
            "category":"Wholesale",
            "subcategory":"Medical Equipment & Supplies",
            "type":"Manufacturing & Wholesale Goods"
        }
    ],
    "sg:phone":"+61 1300 885 886",
    "sg:postcode":"6009",
    "sg:province":"WA",
    "sg:tags":[
        "aid",
        "care",
        "health",
        "home"
    ],
    "wof:name":"Independent Living Centre Of WA (Inc)",
    "wof:placetype":"venue"
},
  "geometry": {"coordinates":[115.816978,-31.96452],"type":"Point"}
}