{
  "type": "Feature",
  "properties": {
    "iso:country":"AU",
    "sg:address":"Glasson St Industrial Est",
    "sg:city":"Emerald",
    "sg:classifiers":[
        {
            "category":"Home & Garden",
            "subcategory":"Building Materials",
            "type":"Retail Goods"
        }
    ],
    "sg:phone":"+61 7 4987 4088",
    "sg:postcode":"4720",
    "sg:province":"QLD",
    "sg:tags":[
        "fitting",
        "door"
    ],
    "wof:name":"Emerald Home Hardware",
    "wof:placetype":"venue"
},
  "geometry": {"coordinates":[148.146698,-23.522635],"type":"Point"}
}