{
  "type": "Feature",
  "properties": {
    "iso:country":"AU",
    "sg:address":"Level 1/ 12 Rodborough Rd",
    "sg:city":"Frenchs Forest",
    "sg:classifiers":[
        {
            "category":"Professional",
            "subcategory":"Computer Services",
            "type":"Services"
        }
    ],
    "sg:phone":"+61 2 9975 7144",
    "sg:postcode":"2086",
    "sg:province":"NSW",
    "sg:tags":[
        "package",
        "software"
    ],
    "wof:name":"Grand Canyon Technologies",
    "wof:placetype":"venue"
},
  "geometry": {"coordinates":[151.24415588400001,-33.7535324097],"type":"Point"}
}