{
  "type": "Feature",
  "properties": {
    "addr:full":"25 Galashiels St North Mackay QLD 4740",
    "addr:housenumber":"25",
    "addr:postcode":"4740",
    "addr:street":"Galashiels St",
    "iso:country":"AU",
    "sg:address":"25 Galashiels St",
    "sg:city":"North Mackay",
    "sg:classifiers":[
        {
            "category":"Manufacturing",
            "subcategory":"Tools & Machinery",
            "type":"Manufacturing & Wholesale Goods"
        }
    ],
    "sg:phone":"+61 418 989 725",
    "sg:postcode":"4740",
    "sg:province":"QLD",
    "sg:tags":[
        "earth",
        "excavating",
        "moving",
        "equipment"
    ],
    "wof:name":"Masters Mobile Maintenance",
    "wof:placetype":"venue"
},
  "geometry": {"coordinates":[149.17147800000001,-21.089441],"type":"Point"}
}