{
  "type": "Feature",
  "properties": {
    "addr:full":"Laycock Rd Carey Bay NSW 2283",
    "addr:postcode":"2283",
    "addr:street":"Laycock Rd",
    "iso:country":"AU",
    "sg:address":"Laycock Rd",
    "sg:city":"Carey Bay",
    "sg:classifiers":[
        {
            "category":"Building & Trades",
            "subcategory":"Equipment Rental",
            "type":"Services"
        }
    ],
    "sg:phone":"+61 2 9477 4177",
    "sg:postcode":"2283",
    "sg:province":"NSW",
    "sg:tags":[
        "fitness"
    ],
    "wof:name":"Energy Fitness Centre",
    "wof:placetype":"venue"
},
  "geometry": {"coordinates":[151.60621643100001,-33.0268516541],"type":"Point"}
}