{
  "type": "Feature",
  "properties": {
    "addr:full":"PO Box 415 Katherine NT 0851",
    "addr:postcode":"nt 0851",
    "iso:country":"AU",
    "sg:address":"PO Box 415",
    "sg:city":"Katherine",
    "sg:classifiers":[
        {
            "category":"Organizations",
            "subcategory":"Non-profit Organization",
            "type":"Services"
        }
    ],
    "sg:phone":"+61 8 8972 1571",
    "sg:postcode":"0851",
    "sg:province":"NT",
    "sg:tags":[
        "support",
        "disability",
        "organisation"
    ],
    "wof:name":"Anglicare NT-Employability",
    "wof:placetype":"venue"
},
  "geometry": {"coordinates":[132.26362599999999,-14.46575],"type":"Point"}
}