{
  "type": "Feature",
  "properties": {
    "addr:full":"14-16 Elliott Rd Dandenong VIC 3175",
    "addr:housenumber":"14-16",
    "addr:postcode":"3175",
    "addr:street":"Elliott Rd",
    "iso:country":"AU",
    "sg:address":"14-16 Elliott Rd",
    "sg:city":"Dandenong",
    "sg:classifiers":[
        {
            "category":"Building & Trades",
            "subcategory":"Construction",
            "type":"Services"
        }
    ],
    "sg:phone":"+61 3 9794 0565",
    "sg:postcode":"3175",
    "sg:province":"VIC",
    "sg:tags":[
        "road",
        "contractor"
    ],
    "wof:name":"Boax Constructions Pty Ltd",
    "wof:placetype":"venue"
},
  "geometry": {"coordinates":[145.21072387699999,-38.0233917236],"type":"Point"}
}