{
  "type": "Feature",
  "properties": {
    "addr:full":"23 Nellbern St Moorabbin VIC 3189",
    "addr:housenumber":"23",
    "addr:postcode":"3189",
    "addr:street":"Nellbern St",
    "iso:country":"AU",
    "sg:address":"23 Nellbern St",
    "sg:city":"Moorabbin",
    "sg:classifiers":[
        {
            "category":"Building & Trades",
            "subcategory":"Cleaning & Sanitation",
            "type":"Services"
        }
    ],
    "sg:phone":"+61 3 9589 4454",
    "sg:postcode":"3189",
    "sg:province":"VIC",
    "sg:tags":[
        "industrial",
        "commercial",
        "contractor"
    ],
    "wof:name":"Nationwide Maintenance Services (Southern Division) Pty Ltd",
    "wof:placetype":"venue"
},
  "geometry": {"coordinates":[145.066314697,-37.9392662048],"type":"Point"}
}