{
  "type": "Feature",
  "properties": {
    "addr:full":"22 Ellison Rd Geebung QLD 4034",
    "addr:housenumber":"22",
    "addr:postcode":"4034",
    "addr:street":"Ellison Rd",
    "iso:country":"AU",
    "sg:address":"22 Ellison Rd",
    "sg:city":"Geebung",
    "sg:classifiers":[
        {
            "category":"Building & Trades",
            "subcategory":"Construction",
            "type":"Services"
        }
    ],
    "sg:phone":"+61 13 15 57",
    "sg:postcode":"4034",
    "sg:province":"QLD",
    "sg:tags":[
        "fencing",
        "contractor"
    ],
    "wof:name":"ARC Fences",
    "wof:placetype":"venue"
},
  "geometry": {"coordinates":[153.053696,-27.377064],"type":"Point"}
}