{
  "type": "Feature",
  "properties": {
    "iso:country":"AU",
    "sg:address":"Samaria Rd",
    "sg:city":"Benalla",
    "sg:classifiers":[
        {
            "category":"Retail",
            "subcategory":"Veterinary Services",
            "type":"Services"
        }
    ],
    "sg:phone":"+61 3 5762 6888",
    "sg:postcode":"3672",
    "sg:province":"VIC",
    "sg:tags":[
        "surgeon"
    ],
    "wof:name":"Bartram Peter",
    "wof:placetype":"venue"
},
  "geometry": {"coordinates":[145.99295,-36.568256],"type":"Point"}
}