{
  "type": "Feature",
  "properties": {
    "iso:country":"AU",
    "sg:address":"Unit 11/ 137 Kings Rd",
    "sg:city":"Five Dock",
    "sg:classifiers":[
        {
            "category":"Retail",
            "subcategory":"Auto Repair",
            "type":"Services"
        }
    ],
    "sg:phone":"+61 2 9744 5849",
    "sg:postcode":"2046",
    "sg:province":"NSW",
    "sg:tags":[
        "beater",
        "painter",
        "panel"
    ],
    "wof:name":"G I A Motors",
    "wof:placetype":"venue"
},
  "geometry": {"coordinates":[151.121124,-33.868652],"type":"Point"}
}