{
  "type": "Feature",
  "properties": {
    "addr:full":"PO Box 3 Panania NSW 2213",
    "addr:postcode":"2213",
    "iso:country":"AU",
    "sg:address":"PO Box 3",
    "sg:city":"Panania",
    "sg:classifiers":[
        {
            "category":"Shopping",
            "subcategory":"Jewelry",
            "type":"Retail Goods"
        }
    ],
    "sg:phone":"+61 413 701 333",
    "sg:postcode":"2213",
    "sg:province":"NSW",
    "sg:tags":[
        "jeweller"
    ],
    "wof:name":"www.opaltraders.com",
    "wof:placetype":"venue"
},
  "geometry": {"coordinates":[150.998367,-33.9548],"type":"Point"}
}