{
  "type": "Feature",
  "properties": {
    "addr:full":"Level 1 / 236 George St Windsor NSW 2756",
    "addr:housenumber":"/ 236",
    "addr:postcode":"2756",
    "addr:street":"George St",
    "iso:country":"AU",
    "sg:address":"Level 1 / 236 George St",
    "sg:city":"Windsor",
    "sg:classifiers":[
        {
            "category":"Professional",
            "subcategory":"Accounting & Tax Preparation",
            "type":"Services"
        }
    ],
    "sg:phone":"+61 2 4577 6688",
    "sg:postcode":"2756",
    "sg:province":"NSW",
    "sg:tags":[
        "consultant",
        "taxation"
    ],
    "wof:name":"Pinnacle Taxation Services",
    "wof:placetype":"venue"
},
  "geometry": {"coordinates":[150.81719970699999,-33.6091651917],"type":"Point"}
}