{
  "type": "Feature",
  "properties": {
    "addr:full":"1 Walker Ave West Perth WA 6005",
    "addr:housenumber":"1",
    "addr:postcode":"6005",
    "addr:street":"Walker Ave",
    "iso:country":"AU",
    "sg:address":"1 Walker Ave",
    "sg:city":"West Perth",
    "sg:classifiers":[
        {
            "category":"Health Services",
            "subcategory":"Dentist",
            "type":"Services"
        }
    ],
    "sg:phone":"+61 8 9322 7363",
    "sg:postcode":"6005",
    "sg:province":"WA",
    "wof:name":"Kakulas Evan G",
    "wof:placetype":"venue"
},
  "geometry": {"coordinates":[115.836196899,-31.9506721497],"type":"Point"}
}