{
  "type": "Feature",
  "properties": {
    "iso:country":"AU",
    "sg:address":"27 Mayne Avenue",
    "sg:city":"Hastings",
    "sg:classifiers":[
        {
            "category":"Retail",
            "subcategory":"Storage",
            "type":"Services"
        }
    ],
    "sg:phone":"+61 3 5979 1058",
    "sg:postcode":"3915",
    "sg:province":"VIC",
    "wof:name":"Winstons Self Storage",
    "wof:placetype":"venue"
},
  "geometry": {"coordinates":[145.192062378,-38.2925605774],"type":"Point"}
}