{
  "type": "Feature",
  "properties": {
    "addr:full":"25 Browtop Rd Narre Warren VIC 3805",
    "addr:housenumber":"25",
    "addr:postcode":"3805",
    "addr:street":"Browtop Rd",
    "iso:country":"AU",
    "sg:address":"25 Browtop Rd",
    "sg:city":"Narre Warren",
    "sg:classifiers":[
        {
            "category":"Building & Trades",
            "subcategory":"Cleaning & Sanitation",
            "type":"Services"
        }
    ],
    "sg:phone":"+61 417 304 559",
    "sg:postcode":"3805",
    "sg:province":"VIC",
    "sg:tags":[
        "industrial",
        "commercial",
        "contractor"
    ],
    "wof:name":"Vision Cleaning Service",
    "wof:placetype":"venue"
},
  "geometry": {"coordinates":[145.32020600000001,-38.00386],"type":"Point"}
}