{
  "type": "Feature",
  "properties": {
    "iso:country":"AU",
    "sg:address":"25 Browtop Rd",
    "sg:city":"Narre Warren",
    "sg:classifiers":[
        {
            "category":"Building & Trades",
            "subcategory":"Cleaning & Sanitation",
            "type":"Services"
        }
    ],
    "sg:phone":"+61 417 304 559",
    "sg:postcode":"3805",
    "sg:province":"VIC",
    "sg:tags":[
        "industrial",
        "commercial",
        "contractor"
    ],
    "wof:name":"Vision Cleaning Service",
    "wof:placetype":"venue"
},
  "geometry": {"coordinates":[145.320206,-38.00386],"type":"Point"}
}