{
  "type": "Feature",
  "properties": {
    "iso:country":"AU",
    "sg:address":"6 Fernhill Drv",
    "sg:city":"Highton",
    "sg:classifiers":[
        {
            "category":"Home & Garden",
            "subcategory":"Carpets & Floor Coverings",
            "type":"Retail Goods"
        }
    ],
    "sg:phone":"+61 3 5241 7454",
    "sg:postcode":"3216",
    "sg:province":"VIC",
    "sg:tags":[
        "layer",
        "planner"
    ],
    "wof:name":"Bill Rogers Carpet Services",
    "wof:placetype":"venue"
},
  "geometry": {"coordinates":[144.32476806599999,-38.1678123474],"type":"Point"}
}