{
  "type": "Feature",
  "properties": {
    "addr:full":"cnr Percy St & Otway Crt Portland VIC 3305",
    "addr:postcode":"3305",
    "addr:street":"Percy St & Otway Crt",
    "iso:country":"AU",
    "sg:address":"cnr Percy St & Otway Crt",
    "sg:city":"Portland",
    "sg:classifiers":[
        {
            "category":"Retail",
            "subcategory":"Auto Rental",
            "type":"Services"
        }
    ],
    "sg:phone":"+61 3 5521 7211",
    "sg:postcode":"3305",
    "sg:province":"VIC",
    "sg:tags":[
        "car",
        "hire",
        "minibus"
    ],
    "wof:name":"Hertz.",
    "wof:placetype":"venue"
},
  "geometry": {"coordinates":[141.60345459000001,-38.3519134521],"type":"Point"}
}