{
  "type": "Feature",
  "properties": {
    "addr:full":"235 Main St Bairnsdale VIC 3875",
    "addr:housenumber":"235",
    "addr:postcode":"3875",
    "addr:street":"Main St",
    "iso:country":"AU",
    "sg:address":"235 Main St",
    "sg:city":"Bairnsdale",
    "sg:classifiers":[
        {
            "category":"Fast Food",
            "type":"Food & Drink"
        }
    ],
    "sg:phone":"+61 3 5152 2477",
    "sg:postcode":"3875",
    "sg:province":"VIC",
    "sg:tags":[
        "away",
        "take"
    ],
    "wof:name":"Isley's Fish & Chips",
    "wof:placetype":"venue"
},
  "geometry": {"coordinates":[147.827224731,-37.7086296082],"type":"Point"}
}