{
  "type": "Feature",
  "properties": {
    "addr:full":"942 Geographe Bay Rd Busselton WA 6280",
    "addr:housenumber":"942",
    "addr:postcode":"6280",
    "addr:street":"Geographe Bay Rd",
    "iso:country":"AU",
    "sg:address":"942 Geographe Bay Rd",
    "sg:city":"Busselton",
    "sg:classifiers":[
        {
            "category":"Professional",
            "subcategory":"Art Services",
            "type":"Services"
        }
    ],
    "sg:phone":"+61 409 115 818",
    "sg:postcode":"6280",
    "sg:province":"WA",
    "sg:tags":[
        "decorator",
        "painter"
    ],
    "wof:name":"Mark Evans Painting Pty Ltd",
    "wof:placetype":"venue"
},
  "geometry": {"coordinates":[115.330848694,-33.6503334045],"type":"Point"}
}