{
  "type": "Feature",
  "properties": {
    "iso:country":"AU",
    "sg:address":"3 Mawson St",
    "sg:city":"Bluewater Park",
    "sg:classifiers":[
        {
            "category":"Building & Trades",
            "subcategory":"Construction",
            "type":"Services"
        }
    ],
    "sg:phone":"+61 7 4751 3157",
    "sg:postcode":"4818",
    "sg:province":"QLD",
    "sg:tags":[
        "concrete",
        "contractor"
    ],
    "wof:name":"Eastcrete",
    "wof:placetype":"venue"
},
  "geometry": {"coordinates":[146.509323,-19.208862],"type":"Point"}
}