{
  "type": "Feature",
  "properties": {
    "addr:full":"1/15-19 Atchison St St Marys NSW 2760",
    "addr:housenumber":"/ 15-19",
    "addr:postcode":"2760",
    "addr:street":"Atchison St",
    "iso:country":"AU",
    "sg:address":"1/15-19 Atchison St",
    "sg:city":"St Marys",
    "sg:classifiers":[
        {
            "category":"Professional",
            "subcategory":"Detective & Security Services",
            "type":"Services"
        }
    ],
    "sg:phone":"+61 1300 764 337",
    "sg:postcode":"2760",
    "sg:province":"NSW",
    "sg:tags":[
        "guard",
        "patrol"
    ],
    "sg:website":"http://www.clubsecurityservices.com.au",
    "wof:name":"Club Security Services",
    "wof:placetype":"venue"
},
  "geometry": {"coordinates":[150.769241333,-33.7799034119],"type":"Point"}
}