{
  "type": "Feature",
  "properties": {
    "addr:full":"18a/ 9 Lyn Pde Prestons NSW 2170",
    "addr:housenumber":"18a / 9",
    "addr:postcode":"2170",
    "addr:street":"Lyn Pde",
    "iso:country":"AU",
    "sg:address":"18a/ 9 Lyn Pde",
    "sg:city":"Prestons",
    "sg:classifiers":[
        {
            "category":"Wholesale",
            "subcategory":"Seafood",
            "type":"Manufacturing & Wholesale Goods"
        }
    ],
    "sg:phone":"+61 2 9607 4767",
    "sg:postcode":"2170",
    "sg:province":"NSW",
    "sg:tags":[
        "fish"
    ],
    "wof:name":"New Drive Food Pty Ltd",
    "wof:placetype":"venue"
},
  "geometry": {"coordinates":[150.88824462900001,-33.9282722473],"type":"Point"}
}