{
  "type": "Feature",
  "properties": {
    "iso:country":"AU",
    "sg:address":"23 Plumer Rd",
    "sg:city":"Rose Bay",
    "sg:classifiers":[
        {
            "category":"Cafe",
            "type":"Food & Drink"
        }
    ],
    "sg:phone":"+61 2 9327 5717",
    "sg:postcode":"2029",
    "sg:province":"NSW",
    "wof:name":"Bernasconi's",
    "wof:placetype":"venue"
},
  "geometry": {"coordinates":[151.25938415499999,-33.8753890991],"type":"Point"}
}