{
  "type": "Feature",
  "properties": {
    "addr:full":"16 Yiannis Crt Springvale VIC 3171",
    "addr:housenumber":"16",
    "addr:postcode":"3171",
    "addr:street":"Yiannis Crt",
    "iso:country":"AU",
    "sg:address":"16 Yiannis Crt",
    "sg:city":"Springvale",
    "sg:classifiers":[
        {
            "category":"Retail",
            "subcategory":"Auto Repair",
            "type":"Services"
        }
    ],
    "sg:phone":"+61 3 9548 3414",
    "sg:postcode":"3171",
    "sg:province":"VIC",
    "sg:tags":[
        "repairer",
        "motor",
        "engineer"
    ],
    "sg:website":"http://www.recustoms.com.au",
    "wof:name":"RE Customs",
    "wof:placetype":"venue"
},
  "geometry": {"coordinates":[145.14361572300001,-37.9334754944],"type":"Point"}
}