{
  "type": "Feature",
  "properties": {
    "addr:full":"PO Box 193 Miranda NSW 2228",
    "addr:postcode":"2228",
    "iso:country":"AU",
    "sg:address":"PO Box 193",
    "sg:city":"Miranda",
    "sg:classifiers":[
        {
            "category":"Banks & Credit Unions",
            "subcategory":"Financial Services",
            "type":"Services"
        }
    ],
    "sg:phone":"+61 2 9542 4444",
    "sg:postcode":"2228",
    "sg:province":"NSW",
    "sg:tags":[
        "loan",
        "finance",
        "mortgage"
    ],
    "wof:name":"Mortgage Wisdom Woronora",
    "wof:placetype":"venue"
},
  "geometry": {"coordinates":[151.102493286,-34.033908844],"type":"Point"}
}