{
  "type": "Feature",
  "properties": {
    "iso:country":"AU",
    "sg:address":"33 Smith St",
    "sg:city":"Parramatta",
    "sg:classifiers":[
        {
            "category":"Building & Trades",
            "subcategory":"Plumbing",
            "type":"Services"
        }
    ],
    "sg:phone":"+61 2 9635 5600",
    "sg:postcode":"2150",
    "sg:province":"NSW",
    "sg:tags":[
        "plumber",
        "gasfitters"
    ],
    "wof:name":"A Active Tradesmen Plumbing Gasfitting & Draining Services",
    "wof:placetype":"venue"
},
  "geometry": {"coordinates":[151.00672912600001,-33.8310127258],"type":"Point"}
}