{
  "type": "Feature",
  "properties": {
    "addr:full":"9 Leichhardt St Glebe NSW 2037",
    "addr:housenumber":"9",
    "addr:postcode":"2037",
    "addr:street":"Leichhardt St",
    "iso:country":"AU",
    "sg:address":"9 Leichhardt St",
    "sg:city":"Glebe",
    "sg:classifiers":[
        {
            "category":"Shopping",
            "subcategory":"Computers & Home Electronics",
            "type":"Retail Goods"
        }
    ],
    "sg:phone":"+61 2 9660 7540",
    "sg:postcode":"2037",
    "sg:province":"NSW",
    "sg:tags":[
        "equipment",
        "multimedia"
    ],
    "wof:name":"Jaws Entertainment",
    "wof:placetype":"venue"
},
  "geometry": {"coordinates":[151.183517456,-33.8735122681],"type":"Point"}
}