{
  "type": "Feature",
  "properties": {
    "iso:country":"AU",
    "sg:address":"906 South Rd",
    "sg:city":"Edwardstown",
    "sg:classifiers":[
        {
            "category":"Personal",
            "subcategory":"Barber",
            "type":"Services"
        }
    ],
    "sg:phone":"+61 8 8293 6848",
    "sg:postcode":"5039",
    "sg:province":"SA",
    "wof:name":"Menage Hair For Men",
    "wof:placetype":"venue"
},
  "geometry": {"coordinates":[138.57330322300001,-34.9746437073],"type":"Point"}
}