{
  "type": "Feature",
  "properties": {
    "addr:full":"35 Railway Pde Hazelbrook NSW 2779",
    "addr:housenumber":"35",
    "addr:postcode":"2779",
    "addr:street":"Railway Pde",
    "iso:country":"AU",
    "sg:address":"35 Railway Pde",
    "sg:city":"Hazelbrook",
    "sg:classifiers":[
        {
            "category":"Retail",
            "subcategory":"Repair Shop",
            "type":"Services"
        }
    ],
    "sg:phone":"+61 2 4758 6399",
    "sg:postcode":"2779",
    "sg:province":"NSW",
    "sg:tags":[
        "machine",
        "repairs",
        "part",
        "dryer",
        "washing"
    ],
    "wof:name":"Pogson R E",
    "wof:placetype":"venue"
},
  "geometry": {"coordinates":[150.45338439899999,-33.7234039307],"type":"Point"}
}