{
  "type": "Feature",
  "properties": {
    "addr:full":"Unit 5/ 90 Aumuller St Cairns QLD 4870",
    "addr:postcode":"4870",
    "addr:street":"90 Aumuller St",
    "iso:country":"AU",
    "sg:address":"Unit 5/ 90 Aumuller St",
    "sg:city":"Cairns",
    "sg:classifiers":[
        {
            "category":"Building & Trades",
            "subcategory":"Landscaping Services",
            "type":"Services"
        }
    ],
    "sg:phone":"+61 7 4035 3855",
    "sg:postcode":"4870",
    "sg:province":"QLD",
    "sg:tags":[
        "consultant"
    ],
    "wof:name":"G.J. Apps & Associates",
    "wof:placetype":"venue"
},
  "geometry": {"coordinates":[145.76614379899999,-16.9400596619],"type":"Point"}
}