{
  "type": "Feature",
  "properties": {
    "addr:full":"7A Young St St Kilda East VIC 3183",
    "addr:housenumber":"7a",
    "addr:postcode":"3183",
    "addr:street":"Young St",
    "iso:country":"AU",
    "sg:address":"7A Young St",
    "sg:city":"St Kilda East",
    "sg:classifiers":[
        {
            "category":"Professional",
            "subcategory":"Art Services",
            "type":"Services"
        }
    ],
    "sg:phone":"+61 3 9527 1393",
    "sg:postcode":"3183",
    "sg:province":"VIC",
    "sg:tags":[
        "graphic",
        "designer"
    ],
    "wof:name":"Fallon Image Design",
    "wof:placetype":"venue"
},
  "geometry": {"coordinates":[144.99458313,-37.8642501831],"type":"Point"}
}