{
  "type": "Feature",
  "properties": {
    "addr:full":"Suite 8, Cabrini Medical Centre, Isabella St Malvern VIC 3144",
    "addr:postcode":"3144",
    "addr:street":"Isabella St",
    "iso:country":"AU",
    "sg:address":"Suite 8, Cabrini Medical Centre, Isabella St",
    "sg:city":"Malvern",
    "sg:classifiers":[
        {
            "category":"Health Services",
            "subcategory":"Doctor",
            "type":"Services"
        }
    ],
    "sg:phone":"+61 3 9509 5977",
    "sg:postcode":"3144",
    "sg:province":"VIC",
    "sg:tags":[
        "medical",
        "practitioner"
    ],
    "wof:name":"Markov G Dr",
    "wof:placetype":"venue"
},
  "geometry": {"coordinates":[145.03277587900001,-37.8609466553],"type":"Point"}
}