{
  "type": "Feature",
  "properties": {
    "addr:full":"U2/ 51 Dempster St Esperance WA 6450",
    "addr:housenumber":"51",
    "addr:postcode":"6450",
    "addr:street":"U2 /;Dempster St",
    "iso:country":"AU",
    "sg:address":"U2/ 51 Dempster St",
    "sg:city":"Esperance",
    "sg:classifiers":[
        {
            "category":"Shopping",
            "subcategory":"Bridal",
            "type":"Retail Goods"
        }
    ],
    "sg:phone":"+61 8 9071 2771",
    "sg:postcode":"6450",
    "sg:province":"WA",
    "sg:tags":[
        "hire",
        "wear"
    ],
    "wof:name":"Alethea Rose Bridal",
    "wof:placetype":"venue"
},
  "geometry": {"coordinates":[121.89362335200001,-33.8586502075],"type":"Point"}
}