{
  "type": "Feature",
  "properties": {
    "addr:full":"Level 1, Greensborough Plz Greensborough VIC 3088",
    "addr:postcode":"3088",
    "addr:street":"Plz",
    "iso:country":"AU",
    "sg:address":"Level 1, Greensborough Plz",
    "sg:city":"Greensborough",
    "sg:classifiers":[
        {
            "category":"Personal",
            "subcategory":"Beauty Salon",
            "type":"Services"
        }
    ],
    "sg:phone":"+61 3 9432 4952",
    "sg:postcode":"3088",
    "sg:province":"VIC",
    "wof:name":"Rainbow Nails",
    "wof:placetype":"venue"
},
  "geometry": {"coordinates":[145.09190368599999,-37.7033882141],"type":"Point"}
}