{
  "type": "Feature",
  "properties": {
    "iso:country":"AU",
    "sg:address":"Lot 2 Gisborne Rd",
    "sg:city":"Bacchus Marsh",
    "sg:classifiers":[
        {
            "category":"Home & Garden",
            "subcategory":"Garden Supply",
            "type":"Retail Goods"
        }
    ],
    "sg:phone":"+61 3 5367 1666",
    "sg:postcode":"3340",
    "sg:province":"VIC",
    "sg:tags":[
        "equipment"
    ],
    "wof:name":"Bacchus Marsh Redgum & Garden Centre Pty Ltd",
    "wof:placetype":"venue"
},
  "geometry": {"coordinates":[144.43565368599999,-37.6748542786],"type":"Point"}
}