{
  "type": "Feature",
  "properties": {
    "addr:full":"260 Maroondah Hwy Healesville VIC 3777",
    "addr:housenumber":"260",
    "addr:postcode":"3777",
    "addr:street":"Maroondah Hwy",
    "iso:country":"AU",
    "sg:address":"260 Maroondah Hwy",
    "sg:city":"Healesville",
    "sg:classifiers":[
        {
            "category":"Fast Food",
            "type":"Food & Drink"
        }
    ],
    "sg:phone":"+61 3 5962 1777",
    "sg:postcode":"3777",
    "sg:province":"VIC",
    "sg:tags":[
        "away",
        "take"
    ],
    "wof:name":"Healesville Cook The",
    "wof:placetype":"venue"
},
  "geometry": {"coordinates":[145.51632699999999,-37.654217],"type":"Point"}
}