{
  "type": "Feature",
  "properties": {
    "iso:country":"AU",
    "sg:address":"188 Stephen St",
    "sg:city":"Toowoomba",
    "sg:classifiers":[
        {
            "category":"Building & Trades",
            "subcategory":"Construction",
            "type":"Services"
        }
    ],
    "sg:phone":"+61 7 4633 2906",
    "sg:postcode":"4350",
    "sg:province":"QLD",
    "sg:tags":[
        "builder",
        "designer",
        "room",
        "cool"
    ],
    "wof:name":"Custom Refrigeration",
    "wof:placetype":"venue"
},
  "geometry": {"coordinates":[151.924057,-27.569906],"type":"Point"}
}