{
  "type": "Feature",
  "properties": {
    "addr:full":"78 Adler Pde Greystanes NSW 2145",
    "addr:housenumber":"78",
    "addr:postcode":"2145",
    "addr:street":"Adler Pde",
    "iso:country":"AU",
    "sg:address":"78 Adler Pde",
    "sg:city":"Greystanes",
    "sg:classifiers":[
        {
            "category":"Building & Trades",
            "subcategory":"Construction",
            "type":"Services"
        }
    ],
    "sg:phone":"+61 2 9688 1091",
    "sg:postcode":"2145",
    "sg:province":"NSW",
    "sg:tags":[
        "polishing",
        "sanding",
        "floor"
    ],
    "wof:name":"True Blue Floor Sanding",
    "wof:placetype":"venue"
},
  "geometry": {"coordinates":[150.95919799800001,-33.828578949],"type":"Point"}
}