{
  "type": "Feature",
  "properties": {
    "iso:country":"AU",
    "sg:address":"7 Cedarwood Crt",
    "sg:city":"Arana Hills",
    "sg:classifiers":[
        {
            "category":"Communications",
            "type":"Services"
        }
    ],
    "sg:phone":"+61 7 3351 1313",
    "sg:postcode":"4054",
    "sg:province":"QLD",
    "sg:tags":[
        "public",
        "system",
        "address"
    ],
    "wof:name":"Audiovision",
    "wof:placetype":"venue"
},
  "geometry": {"coordinates":[152.94955444300001,-27.3860416412],"type":"Point"}
}