{
  "type": "Feature",
  "properties": {
    "addr:full":"22/ 198 Young St Waterloo NSW 2017",
    "addr:housenumber":"22 / 198",
    "addr:postcode":"2017",
    "addr:street":"Young St",
    "iso:country":"AU",
    "sg:address":"22/ 198 Young St",
    "sg:city":"Waterloo",
    "sg:classifiers":[
        {
            "category":"Wholesale",
            "subcategory":"Medical Equipment & Supplies",
            "type":"Manufacturing & Wholesale Goods"
        }
    ],
    "sg:phone":"+61 2 8306 3000",
    "sg:postcode":"2017",
    "sg:province":"NSW",
    "sg:tags":[
        "dental"
    ],
    "wof:name":"NSK Oceania Pty Ltd",
    "wof:placetype":"venue"
},
  "geometry": {"coordinates":[151.209075928,-33.898273468],"type":"Point"}
}