{
  "type": "Feature",
  "properties": {
    "iso:country":"AU",
    "sg:address":"19 Minmi Rd",
    "sg:city":"Wallsend",
    "sg:classifiers":[
        {
            "category":"Fast Food",
            "type":"Food & Drink"
        }
    ],
    "sg:phone":"+61 2 4955 8458",
    "sg:postcode":"2287",
    "sg:province":"NSW",
    "sg:tags":[
        "away",
        "take"
    ],
    "wof:name":"M & M's Take Away",
    "wof:placetype":"venue"
},
  "geometry": {"coordinates":[151.62196350100001,-32.9233016968],"type":"Point"}
}