{
  "type": "Feature",
  "properties": {
    "addr:full":"75 Point Cook Rd Point Cook VIC 3030",
    "addr:housenumber":"75",
    "addr:postcode":"3030",
    "addr:street":"Point Cook Rd",
    "iso:country":"AU",
    "sg:address":"75 Point Cook Rd",
    "sg:city":"Point Cook",
    "sg:classifiers":[
        {
            "category":"Real Estate",
            "subcategory":"Real Estate Agent",
            "type":"Services"
        }
    ],
    "sg:phone":"+61 3 9360 9399",
    "sg:postcode":"3030",
    "sg:province":"VIC",
    "wof:name":"Sweeney Estate Agents",
    "wof:placetype":"venue"
},
  "geometry": {"coordinates":[144.75799599999999,-37.877174],"type":"Point"}
}