{
  "type": "Feature",
  "properties": {
    "iso:country":"AU",
    "sg:address":"75 Point Cook Rd",
    "sg:city":"Point Cook",
    "sg:classifiers":[
        {
            "category":"Real Estate",
            "subcategory":"Real Estate Agent",
            "type":"Services"
        }
    ],
    "sg:phone":"+61 3 9360 9399",
    "sg:postcode":"3030",
    "sg:province":"VIC",
    "wof:name":"Sweeney Estate Agents",
    "wof:placetype":"venue"
},
  "geometry": {"coordinates":[144.757996,-37.877174],"type":"Point"}
}