{
  "type": "Feature",
  "properties": {
    "iso:country":"AU",
    "sg:address":"24 Zoe St",
    "sg:city":"Bunbury",
    "sg:classifiers":[
        {
            "category":"Education",
            "subcategory":"Music School",
            "type":"Public Place"
        }
    ],
    "sg:phone":"+61 8 9721 2777",
    "sg:postcode":"6230",
    "sg:province":"WA",
    "sg:tags":[
        "choir",
        "bands",
        "orchestra"
    ],
    "wof:name":"Caddam Wood Bush Band",
    "wof:placetype":"venue"
},
  "geometry": {"coordinates":[115.640999,-33.33062],"type":"Point"}
}