{
  "type": "Feature",
  "properties": {
    "iso:country":"AU",
    "sg:address":"59 Angelica St",
    "sg:city":"Elanora",
    "sg:classifiers":[
        {
            "category":"Home & Garden",
            "subcategory":"Carpets & Floor Coverings",
            "type":"Retail Goods"
        }
    ],
    "sg:phone":"+61 414 941 503",
    "sg:postcode":"4221",
    "sg:province":"QLD",
    "sg:tags":[
        "tile",
        "wall",
        "layer"
    ],
    "wof:name":"VMP Tiling",
    "wof:placetype":"venue"
},
  "geometry": {"coordinates":[153.45655822800001,-28.1222877502],"type":"Point"}
}