{
  "type": "Feature",
  "properties": {
    "iso:country":"AU",
    "sg:address":"314A High St",
    "sg:city":"Penrith",
    "sg:classifiers":[
        {
            "category":"Real Estate",
            "subcategory":"Real Estate Agent",
            "type":"Services"
        }
    ],
    "sg:phone":"+61 2 4721 7799",
    "sg:postcode":"2750",
    "sg:province":"NSW",
    "wof:name":"Choice One Real Estate",
    "wof:placetype":"venue"
},
  "geometry": {"coordinates":[150.91558837900001,-33.8947563171],"type":"Point"}
}