{
  "type": "Feature",
  "properties": {
    "addr:full":"93 Cabarita Rd Avalon NSW 2107",
    "addr:housenumber":"93",
    "addr:postcode":"2107",
    "addr:street":"Cabarita Rd",
    "iso:country":"AU",
    "sg:address":"93 Cabarita Rd",
    "sg:city":"Avalon",
    "sg:classifiers":[
        {
            "category":"Building & Trades",
            "subcategory":"Construction",
            "type":"Services"
        }
    ],
    "sg:phone":"+61 2 9973 2865",
    "sg:postcode":"2107",
    "sg:province":"NSW",
    "sg:tags":[
        "contractor"
    ],
    "wof:name":"insight",
    "wof:placetype":"venue"
},
  "geometry": {"coordinates":[151.31956481899999,-33.6217918396],"type":"Point"}
}