{
  "type": "Feature",
  "properties": {
    "iso:country":"AU",
    "sg:address":"Shop 7-8 Karri St",
    "sg:city":"Munno Para",
    "sg:classifiers":[
        {
            "category":"Shopping",
            "subcategory":"Baby Store",
            "type":"Retail Goods"
        }
    ],
    "sg:phone":"+61 8 8254 8300",
    "sg:postcode":"5115",
    "sg:province":"SA",
    "sg:tags":[
        "wear"
    ],
    "wof:name":"Bow Peep's",
    "wof:placetype":"venue"
},
  "geometry": {"coordinates":[138.70112609899999,-34.6676826477],"type":"Point"}
}