{
  "type": "Feature",
  "properties": {
    "addr:full":"Penola Rd Mt Gambier SA 5290",
    "addr:postcode":"5290",
    "addr:street":"Penola Rd",
    "iso:country":"AU",
    "sg:address":"Penola Rd",
    "sg:city":"Mt Gambier",
    "sg:classifiers":[
        {
            "category":"Building & Trades",
            "subcategory":"Landscaping Services",
            "type":"Services"
        }
    ],
    "sg:phone":"+61 8 8721 2222",
    "sg:postcode":"5290",
    "sg:province":"SA",
    "sg:tags":[
        "forestry",
        "consultant"
    ],
    "wof:name":"Auspine Ltd",
    "wof:placetype":"venue"
},
  "geometry": {"coordinates":[140.782104,-37.825691],"type":"Point"}
}