{
  "type": "Feature",
  "properties": {
    "addr:full":"Shop2/ 135 East St Rockhampton QLD 4700",
    "addr:housenumber":"135",
    "addr:postcode":"4700",
    "addr:street":"East St",
    "iso:country":"AU",
    "sg:address":"Shop2/ 135 East St",
    "sg:city":"Rockhampton",
    "sg:classifiers":[
        {
            "category":"Shopping",
            "subcategory":"Clothing, Apparel, & Fashions",
            "type":"Retail Goods"
        }
    ],
    "sg:phone":"+61 7 4921 0026",
    "sg:postcode":"4700",
    "sg:province":"QLD",
    "sg:tags":[
        "lady",
        "wear"
    ],
    "wof:name":"Tantrum",
    "wof:placetype":"venue"
},
  "geometry": {"coordinates":[150.52137756400001,-23.3892440796],"type":"Point"}
}