{
  "type": "Feature",
  "properties": {
    "addr:full":"4 Iron Rd Malaga WA 6090",
    "addr:housenumber":"4",
    "addr:postcode":"6090",
    "addr:street":"Iron Rd",
    "iso:country":"AU",
    "sg:address":"4 Iron Rd",
    "sg:city":"Malaga",
    "sg:classifiers":[
        {
            "category":"Shopping",
            "type":"Retail Goods"
        }
    ],
    "sg:phone":"+61 8 9247 8900",
    "sg:postcode":"6090",
    "sg:province":"WA",
    "sg:tags":[
        "equipment",
        "safety",
        "accessory"
    ],
    "wof:name":"MSA (Aust.) Pty. Limited",
    "wof:placetype":"venue"
},
  "geometry": {"coordinates":[115.90688324,-31.8592224121],"type":"Point"}
}