{
  "type": "Feature",
  "properties": {
    "addr:full":"292 Boundary Rd Dingley VIC 3172",
    "addr:housenumber":"292",
    "addr:postcode":"3172",
    "addr:street":"Boundary Rd",
    "iso:country":"AU",
    "sg:address":"292 Boundary Rd",
    "sg:city":"Dingley",
    "sg:classifiers":[
        {
            "category":"Professional",
            "subcategory":"Printing & Photocopies",
            "type":"Services"
        }
    ],
    "sg:phone":"+61 3 9551 5211",
    "sg:postcode":"3172",
    "sg:province":"VIC",
    "sg:tags":[
        "photocopying"
    ],
    "wof:name":"Nu-Print Office Choice",
    "wof:placetype":"venue"
},
  "geometry": {"coordinates":[145.109863281,-37.9862327576],"type":"Point"}
}