{
  "type": "Feature",
  "properties": {
    "iso:country":"AU",
    "sg:address":"10 - 12 Allworth St",
    "sg:city":"Northgate",
    "sg:classifiers":[
        {
            "category":"Transit Center",
            "subcategory":"Freight",
            "type":"Transportation"
        }
    ],
    "sg:phone":"+61 7 3260 5622",
    "sg:postcode":"4013",
    "sg:province":"QLD",
    "sg:tags":[
        "agent",
        "shipping"
    ],
    "wof:name":"Pacific Network Global Logistics",
    "wof:placetype":"venue"
},
  "geometry": {"coordinates":[153.07115173299999,-27.3940258026],"type":"Point"}
}