{
  "type": "Feature",
  "properties": {
    "iso:country":"AU",
    "sg:address":"221 Berkeley Rd",
    "sg:city":"Unanderra",
    "sg:classifiers":[
        {
            "category":"Food & Beverages",
            "subcategory":"Bakery",
            "type":"Retail Goods"
        }
    ],
    "sg:phone":"+61 2 4271 1869",
    "sg:postcode":"2526",
    "sg:province":"NSW",
    "sg:tags":[
        "baker"
    ],
    "wof:name":"Betta Maid Fundraising",
    "wof:placetype":"venue"
},
  "geometry": {"coordinates":[150.84815979000001,-34.4562530518],"type":"Point"}
}