{
  "type": "Feature",
  "properties": {
    "iso:country":"AU",
    "sg:address":"Old Hume Hwy",
    "sg:city":"Mittagong",
    "sg:classifiers":[
        {
            "category":"Travel",
            "subcategory":"Hotels & Motels",
            "type":"Entertainment"
        }
    ],
    "sg:phone":"+61 2 4871 3133",
    "sg:postcode":"2575",
    "sg:province":"NSW",
    "wof:name":"Mittagong RSL Motel",
    "wof:placetype":"venue"
},
  "geometry": {"coordinates":[150.44309997600001,-34.4511947632],"type":"Point"}
}