{
  "type": "Feature",
  "properties": {
    "addr:full":"Rockhampton Shopping Fair Yaamba Rd North Rockhampton QLD 4701",
    "addr:postcode":"4701",
    "addr:street":"Yaamba Rd North",
    "iso:country":"AU",
    "sg:address":"Rockhampton Shopping Fair Yaamba Rd",
    "sg:city":"North Rockhampton",
    "sg:classifiers":[
        {
            "category":"Food & Beverages",
            "subcategory":"Supermarket",
            "type":"Retail Goods"
        }
    ],
    "sg:phone":"+61 7 4928 0400",
    "sg:postcode":"4701",
    "sg:province":"QLD",
    "sg:tags":[
        "grocery",
        "store"
    ],
    "wof:name":"Woolworths Limited",
    "wof:placetype":"venue"
},
  "geometry": {"coordinates":[150.52438354500001,-23.3512802124],"type":"Point"}
}