{
  "type": "Feature",
  "properties": {
    "addr:full":"Shop 7/ 72 Main Hurstbridge Rd Diamond Creek VIC 3089",
    "addr:housenumber":"shop 7 / 72",
    "addr:postcode":"3089",
    "addr:street":"Main Hurstbridge Rd",
    "iso:country":"AU",
    "sg:address":"Shop 7/ 72 Main Hurstbridge Rd",
    "sg:city":"Diamond Creek",
    "sg:classifiers":[
        {
            "category":"Personal",
            "subcategory":"Beauty Salon",
            "type":"Services"
        }
    ],
    "sg:phone":"+61 3 9438 1111",
    "sg:postcode":"3089",
    "sg:province":"VIC",
    "sg:tags":[
        "hairdresser"
    ],
    "wof:name":"D-Zine Hair Studio",
    "wof:placetype":"venue"
},
  "geometry": {"coordinates":[145.15986599999999,-37.674721],"type":"Point"}
}