{
  "type": "Feature",
  "properties": {
    "iso:country":"AU",
    "sg:address":"7 Fourth St",
    "sg:city":"Keith",
    "sg:classifiers":[
        {
            "category":"Military Area",
            "subcategory":"Air Force Base",
            "type":"Public Place"
        }
    ],
    "sg:phone":"+61 8 8755 1088",
    "sg:postcode":"5267",
    "sg:province":"SA",
    "sg:tags":[
        "windmill"
    ],
    "wof:name":"Yates L & S",
    "wof:placetype":"venue"
},
  "geometry": {"coordinates":[140.359802,-36.105167],"type":"Point"}
}