{
  "type": "Feature",
  "properties": {
    "iso:country":"AU",
    "sg:address":"150-152 Elizabeth St",
    "sg:city":"Sydney",
    "sg:classifiers":[
        {
            "category":"Health Services",
            "subcategory":"Health Practitioner",
            "type":"Services"
        }
    ],
    "sg:phone":"+61 425 795 706",
    "sg:postcode":"2000",
    "sg:province":"NSW",
    "sg:tags":[
        "psychologist"
    ],
    "wof:name":"Watson- Munro Tim",
    "wof:placetype":"venue"
},
  "geometry": {"coordinates":[151.21026611299999,-33.8719596863],"type":"Point"}
}