{
  "type": "Feature",
  "properties": {
    "addr:full":"152 Scarborough Beach Rd Mt Hawthorn WA 6016",
    "addr:housenumber":"152",
    "addr:postcode":"6016",
    "addr:street":"Scarborough Beach Rd",
    "iso:country":"AU",
    "sg:address":"152 Scarborough Beach Rd",
    "sg:city":"Mt Hawthorn",
    "sg:classifiers":[
        {
            "category":"Arts & Performance",
            "subcategory":"Art Gallery",
            "type":"Entertainment"
        }
    ],
    "sg:phone":"+61 8 9201 2266",
    "sg:postcode":"6016",
    "sg:province":"WA",
    "wof:name":"Studio Red Dust",
    "wof:placetype":"venue"
},
  "geometry": {"coordinates":[115.839073181,-31.921377182],"type":"Point"}
}