{
  "type": "Feature",
  "properties": {
    "addr:full":"39 Hamilton Rd Horsham VIC 3400",
    "addr:housenumber":"39",
    "addr:postcode":"3400",
    "addr:street":"Hamilton Rd",
    "iso:country":"AU",
    "sg:address":"39 Hamilton Rd",
    "sg:city":"Horsham",
    "sg:classifiers":[
        {
            "category":"Building & Trades",
            "subcategory":"Equipment Rental",
            "type":"Services"
        }
    ],
    "sg:phone":"+61 3 5382 7000",
    "sg:postcode":"3400",
    "sg:province":"VIC",
    "sg:tags":[
        "party",
        "hire"
    ],
    "wof:name":"Schucat Party Hire",
    "wof:placetype":"venue"
},
  "geometry": {"coordinates":[142.202590942,-36.717956543],"type":"Point"}
}