{
  "type": "Feature",
  "properties": {
    "addr:full":"Suite 3, 15 Woodlark St Lismore Lismore NSW 2480",
    "addr:housenumber":"15",
    "addr:postcode":"2480",
    "addr:street":"Woodlark St",
    "iso:country":"AU",
    "sg:address":"Suite 3, 15 Woodlark St",
    "sg:city":"Lismore Lismore",
    "sg:classifiers":[
        {
            "category":"Personal",
            "subcategory":"Beauty Salon",
            "type":"Services"
        }
    ],
    "sg:phone":"+61 2 6621 5150",
    "sg:postcode":"2480",
    "sg:province":"NSW",
    "wof:name":"Intense Skin Care",
    "wof:placetype":"venue"
},
  "geometry": {"coordinates":[153.27767944300001,-28.8070373535],"type":"Point"}
}