{
  "type": "Feature",
  "properties": {
    "iso:country":"AU",
    "sg:address":"Suite 12, 622 Ferntree Gully Rd",
    "sg:city":"Wheelers Hill",
    "sg:classifiers":[
        {
            "category":"Professional",
            "subcategory":"Computer Services",
            "type":"Services"
        }
    ],
    "sg:phone":"+61 3 9560 0977",
    "sg:postcode":"3150",
    "sg:province":"VIC",
    "sg:tags":[
        "equipment",
        "networking",
        "installation"
    ],
    "wof:name":"Krone",
    "wof:placetype":"venue"
},
  "geometry": {"coordinates":[145.16346740700001,-37.9036026001],"type":"Point"}
}