{
  "type": "Feature",
  "properties": {
    "addr:full":"PO Box 778 Raymond Terrace NSW 2324",
    "addr:postcode":"2324",
    "iso:country":"AU",
    "sg:address":"PO Box 778",
    "sg:city":"Raymond Terrace",
    "sg:classifiers":[
        {
            "category":"Insurance",
            "subcategory":"Insurance Agent",
            "type":"Services"
        }
    ],
    "sg:phone":"+61 2 4987 7622",
    "sg:postcode":"2324",
    "sg:province":"NSW",
    "wof:name":"Breese Insurance Advisors Pty Ltd",
    "wof:placetype":"venue"
},
  "geometry": {"coordinates":[151.76373290999999,-32.7550582886],"type":"Point"}
}