{
  "type": "Feature",
  "properties": {
    "iso:country":"AU",
    "sg:address":"Cnr Yorktown Rd & Turner Drv",
    "sg:city":"Craigmore",
    "sg:classifiers":[
        {
            "category":"Fast Food",
            "type":"Food & Drink"
        }
    ],
    "sg:phone":"+61 8 8252 0795",
    "sg:postcode":"5114",
    "sg:province":"SA",
    "sg:tags":[
        "away",
        "take"
    ],
    "wof:name":"Chef Lam's Restaurant",
    "wof:placetype":"venue"
},
  "geometry": {"coordinates":[138.70249939000001,-34.7079162598],"type":"Point"}
}