{
  "type": "Feature",
  "properties": {
    "iso:country":"AU",
    "sg:address":"24 Sankey St",
    "sg:city":"Highgate Hill",
    "sg:classifiers":[
        {
            "category":"Building & Trades",
            "subcategory":"Landscaping Services",
            "type":"Services"
        }
    ],
    "sg:phone":"+61 7 3255 1284",
    "sg:postcode":"4101",
    "sg:province":"QLD",
    "sg:tags":[
        "consultant"
    ],
    "wof:name":"McGilvery & Associates Pty Ltd",
    "wof:placetype":"venue"
},
  "geometry": {"coordinates":[153.01329040499999,-27.4888877869],"type":"Point"}
}