{
  "type": "Feature",
  "properties": {
    "iso:country":"AU",
    "sg:address":"10 Park St",
    "sg:city":"Peakhurst",
    "sg:classifiers":[
        {
            "category":"Shopping",
            "subcategory":"Bicycles & Sporting Goods",
            "type":"Retail Goods"
        }
    ],
    "sg:phone":"+61 2 9533 3223",
    "sg:postcode":"2210",
    "sg:province":"NSW",
    "sg:tags":[
        "chemical",
        "equipment",
        "pool",
        "swimming"
    ],
    "wof:name":"Peakhurst Pool Centre",
    "wof:placetype":"venue"
},
  "geometry": {"coordinates":[151.057053,-33.963833],"type":"Point"}
}