{
  "type": "Feature",
  "properties": {
    "addr:full":"25 Barrie Rd Tullamarine VIC 3043",
    "addr:housenumber":"25",
    "addr:postcode":"3043",
    "addr:street":"Barrie Rd",
    "iso:country":"AU",
    "sg:address":"25 Barrie Rd",
    "sg:city":"Tullamarine",
    "sg:classifiers":[
        {
            "category":"Retail",
            "subcategory":"Car Wash",
            "type":"Services"
        }
    ],
    "sg:phone":"+61 3 9334 2663",
    "sg:postcode":"3043",
    "sg:province":"VIC",
    "sg:tags":[
        "truck",
        "cleaning"
    ],
    "wof:name":"Kryptonite Car Detailing",
    "wof:placetype":"venue"
},
  "geometry": {"coordinates":[144.87672424300001,-37.7131919861],"type":"Point"}
}