{
  "type": "Feature",
  "properties": {
    "addr:full":"103 Curtis Rd Mulgrave NSW 2756",
    "addr:housenumber":"103",
    "addr:postcode":"2756",
    "addr:street":"Curtis Rd",
    "iso:country":"AU",
    "sg:address":"103 Curtis Rd",
    "sg:city":"Mulgrave",
    "sg:classifiers":[
        {
            "category":"Real Estate",
            "subcategory":"Real Estate Agent",
            "type":"Services"
        }
    ],
    "sg:phone":"+61 2 4587 7011",
    "sg:postcode":"2756",
    "sg:province":"NSW",
    "sg:tags":[
        "steel",
        "foundry",
        "iron"
    ],
    "sg:website":"http://www.durham.com.au",
    "wof:name":"B.R. Durham & Son",
    "wof:placetype":"venue"
},
  "geometry": {"coordinates":[150.83709716800001,-33.6228713989],"type":"Point"}
}