{
  "type": "Feature",
  "properties": {
    "iso:country":"AU",
    "sg:address":"44 Barwell Ave",
    "sg:city":"Barmera",
    "sg:classifiers":[
        {
            "category":"Autos & Motor Vehicles",
            "subcategory":"Fuel & Gas Station",
            "type":"Retail Goods"
        }
    ],
    "sg:phone":"+61 8 8578 1084",
    "sg:postcode":"5345",
    "sg:province":"SA",
    "wof:name":"BP Oil",
    "wof:placetype":"venue"
},
  "geometry": {"coordinates":[140.46472168,-34.2516593933],"type":"Point"}
}