{
  "type": "Feature",
  "properties": {
    "addr:full":"405 Cressy St Deniliquin NSW 2710",
    "addr:housenumber":"405",
    "addr:postcode":"2710",
    "addr:street":"Cressy St",
    "iso:country":"AU",
    "sg:address":"405 Cressy St",
    "sg:city":"Deniliquin",
    "sg:classifiers":[
        {
            "category":"Health Services",
            "subcategory":"Dentist",
            "type":"Services"
        }
    ],
    "sg:phone":"+61 3 5881 5456",
    "sg:postcode":"2710",
    "sg:province":"NSW",
    "sg:tags":[
        "dental",
        "prosthetist"
    ],
    "wof:name":"Glenn Burrage",
    "wof:placetype":"venue"
},
  "geometry": {"coordinates":[144.95997619600001,-35.5254478455],"type":"Point"}
}