{
  "type": "Feature",
  "properties": {
    "addr:full":"Suite 16, 1st Flr Stanton Pl, Cnr Stanton Rd & Cap Smithfield QLD 4878",
    "addr:postcode":"4878",
    "addr:street":"Pl Cnr Stanton Rd &",
    "iso:country":"AU",
    "sg:address":"Suite 16, 1st Flr Stanton Pl, Cnr Stanton Rd & Cap",
    "sg:city":"Smithfield",
    "sg:classifiers":[
        {
            "category":"Professional",
            "subcategory":"Accounting & Tax Preparation",
            "type":"Services"
        }
    ],
    "sg:phone":"+61 7 4038 8888",
    "sg:postcode":"4878",
    "sg:province":"QLD",
    "sg:tags":[
        "consultant",
        "taxation"
    ],
    "wof:name":"Goodman Chartered Accountants",
    "wof:placetype":"venue"
},
  "geometry": {"coordinates":[145.68737793,-16.8317813873],"type":"Point"}
}