{
  "type": "Feature",
  "properties": {
    "iso:country":"AU",
    "sg:address":"Lot 673 Franklin St",
    "sg:city":"Manjimup",
    "sg:classifiers":[
        {
            "category":"Retail",
            "subcategory":"Auto Repair",
            "type":"Services"
        }
    ],
    "sg:phone":"+61 418 908 246",
    "sg:postcode":"6258",
    "sg:province":"WA",
    "sg:tags":[
        "electrical"
    ],
    "wof:name":"Warren Auto Electrics",
    "wof:placetype":"venue"
},
  "geometry": {"coordinates":[116.14785766599999,-34.2545928955],"type":"Point"}
}