{
  "type": "Feature",
  "properties": {
    "addr:full":"Studio 2, 118 Warners Ave Bondi Beach NSW 2026",
    "addr:housenumber":"118",
    "addr:postcode":"2026",
    "addr:street":"Warners Ave",
    "iso:country":"AU",
    "sg:address":"Studio 2, 118 Warners Ave",
    "sg:city":"Bondi Beach",
    "sg:classifiers":[
        {
            "category":"Professional",
            "subcategory":"Art Services",
            "type":"Services"
        }
    ],
    "sg:phone":"+61 2 9300 6448",
    "sg:postcode":"2026",
    "sg:province":"NSW",
    "sg:tags":[
        "caricaturist",
        "cartoonist"
    ],
    "wof:name":"A Cartoonist Danny Cohen",
    "wof:placetype":"venue"
},
  "geometry": {"coordinates":[151.27719116200001,-33.8879508972],"type":"Point"}
}