{
  "type": "Feature",
  "properties": {
    "iso:country":"AU",
    "sg:address":"Unit 1, 5 Sussex St",
    "sg:city":"Glenorchy",
    "sg:classifiers":[
        {
            "category":"Manufacturing",
            "subcategory":"Furniture",
            "type":"Manufacturing & Wholesale Goods"
        }
    ],
    "sg:phone":"+61 407 745 835",
    "sg:postcode":"7010",
    "sg:province":"TAS",
    "sg:tags":[
        "builder",
        "designer",
        "custom"
    ],
    "wof:name":"AJB Furniture & Joinery",
    "wof:placetype":"venue"
},
  "geometry": {"coordinates":[147.262542725,-42.8332481384],"type":"Point"}
}