{
  "type": "Feature",
  "properties": {
    "addr:full":"86 (Fact. 1 Keys Rd, Cheltenham VIC 3192",
    "addr:housenumber":"86;1",
    "addr:postcode":"3192",
    "addr:street":"Fact.;Keys Rd",
    "iso:country":"AU",
    "sg:address":"86 (Fact. 1",
    "sg:city":"Keys Rd, Cheltenham",
    "sg:classifiers":[
        {
            "category":"Shopping",
            "type":"Retail Goods"
        }
    ],
    "sg:phone":"+61 3 9553 2655",
    "sg:postcode":"3192",
    "sg:province":"VIC",
    "sg:tags":[
        "equipment",
        "safety",
        "accessory"
    ],
    "wof:name":"All- About Safety",
    "wof:placetype":"venue"
},
  "geometry": {"coordinates":[145.068435669,-37.9488601685],"type":"Point"}
}