{
  "type": "Feature",
  "properties": {
    "addr:full":"Carrington Ave Dubbo NSW 2830",
    "addr:postcode":"2830",
    "addr:street":"Carrington Ave",
    "iso:country":"AU",
    "sg:address":"Carrington Ave",
    "sg:city":"Dubbo",
    "sg:classifiers":[
        {
            "category":"Organizations",
            "subcategory":"Community Association",
            "type":"Services"
        }
    ],
    "sg:phone":"+61 2 6882 6025",
    "sg:postcode":"2830",
    "sg:province":"NSW",
    "sg:tags":[
        "club",
        "senior",
        "citizen"
    ],
    "wof:name":"Dubbo Senior Citizen Centre",
    "wof:placetype":"venue"
},
  "geometry": {"coordinates":[148.60487365700001,-32.2484588623],"type":"Point"}
}