{
  "type": "Feature",
  "properties": {
    "iso:country":"AU",
    "sg:address":"3 Nelson St",
    "sg:city":"Fullarton",
    "sg:classifiers":[
        {
            "category":"Sports & Exercise",
            "subcategory":"Gym",
            "type":"Entertainment"
        }
    ],
    "sg:phone":"+61 8 8379 9511",
    "sg:postcode":"5063",
    "sg:province":"SA",
    "sg:tags":[
        "meditation"
    ],
    "wof:name":"Buddha House",
    "wof:placetype":"venue"
},
  "geometry": {"coordinates":[138.63172912600001,-34.9509391785],"type":"Point"}
}