{
  "type": "Feature",
  "properties": {
    "iso:country":"AU",
    "sg:address":"311 Marrickville Rd",
    "sg:city":"Marrickville",
    "sg:classifiers":[
        {
            "category":"Health Services",
            "subcategory":"Doctor",
            "type":"Services"
        }
    ],
    "sg:phone":"+61 2 9569 6100",
    "sg:postcode":"2204",
    "sg:province":"NSW",
    "sg:tags":[
        "medical",
        "practitioner"
    ],
    "wof:name":"Pham Tri H",
    "wof:placetype":"venue"
},
  "geometry": {"coordinates":[151.154785,-33.909924],"type":"Point"}
}