{
  "type": "Feature",
  "properties": {
    "addr:full":"160 Simpson St East Melbourne VIC 3002",
    "addr:housenumber":"160",
    "addr:postcode":"3002",
    "addr:street":"Simpson St",
    "iso:country":"AU",
    "sg:address":"160 Simpson St",
    "sg:city":"East Melbourne",
    "sg:classifiers":[
        {
            "category":"Travel",
            "subcategory":"Hotels & Motels",
            "type":"Entertainment"
        }
    ],
    "sg:phone":"+61 3 9417 2344",
    "sg:postcode":"3002",
    "sg:province":"VIC",
    "sg:tags":[
        "accommodation"
    ],
    "wof:name":"Birches",
    "wof:placetype":"venue"
},
  "geometry": {"coordinates":[144.988967895,-37.8108177185],"type":"Point"}
}