{
  "type": "Feature",
  "properties": {
    "addr:full":"1/ 3 Antoine Rd Rydalmere NSW 2116",
    "addr:housenumber":"/ 3",
    "addr:postcode":"2116",
    "addr:street":"Antoine Rd",
    "iso:country":"AU",
    "sg:address":"1/ 3 Antoine Rd",
    "sg:city":"Rydalmere",
    "sg:classifiers":[
        {
            "category":"Retail",
            "subcategory":"Auto Repair",
            "type":"Services"
        }
    ],
    "sg:phone":"+61 2 9638 5744",
    "sg:postcode":"2116",
    "sg:province":"NSW",
    "sg:tags":[
        "body",
        "motor",
        "trimmer"
    ],
    "wof:name":"Blackman & Sons Custom Leather Craftsmen",
    "wof:placetype":"venue"
},
  "geometry": {"coordinates":[151.04127502399999,-33.8161506653],"type":"Point"}
}