{
  "type": "Feature",
  "properties": {
    "iso:country":"AU",
    "sg:address":"Unit 2, 55 John St",
    "sg:city":"Bentley",
    "sg:classifiers":[
        {
            "category":"Autos & Motor Vehicles",
            "subcategory":"Auto Supplies",
            "type":"Retail Goods"
        }
    ],
    "sg:phone":"+61 8 9358 2444",
    "sg:postcode":"6102",
    "sg:province":"WA",
    "sg:tags":[
        "transmission",
        "equipment",
        "power"
    ],
    "wof:name":"SES Linear Bearings Pty Ltd",
    "wof:placetype":"venue"
},
  "geometry": {"coordinates":[115.923599243,-31.9972934723],"type":"Point"}
}