{
  "type": "Feature",
  "properties": {
    "addr:full":"10 Court St Box Hill VIC 3128",
    "addr:housenumber":"10",
    "addr:postcode":"3128",
    "addr:street":"Court St",
    "iso:country":"AU",
    "sg:address":"10 Court St",
    "sg:city":"Box Hill",
    "sg:classifiers":[
        {
            "category":"Professional",
            "subcategory":"Art Services",
            "type":"Services"
        }
    ],
    "sg:phone":"+61 3 9898 7274",
    "sg:postcode":"3128",
    "sg:province":"VIC",
    "sg:tags":[
        "arranger",
        "music",
        "composer"
    ],
    "wof:name":"Greenball Productions",
    "wof:placetype":"venue"
},
  "geometry": {"coordinates":[145.12684631400001,-37.8168945312],"type":"Point"}
}