{
  "type": "Feature",
  "properties": {
    "addr:full":"19 Mitchell Drv Greenhills NSW 2323",
    "addr:housenumber":"19",
    "addr:postcode":"2323",
    "addr:street":"Mitchell Drv",
    "iso:country":"AU",
    "sg:address":"19 Mitchell Drv",
    "sg:city":"Greenhills",
    "sg:classifiers":[
        {
            "category":"Personal",
            "subcategory":"Massage",
            "type":"Services"
        }
    ],
    "sg:phone":"+61 2 4934 2349",
    "sg:postcode":"2323",
    "sg:province":"NSW",
    "sg:tags":[
        "therapy"
    ],
    "wof:name":"Renae Polson Remedial Massage",
    "wof:placetype":"venue"
},
  "geometry": {"coordinates":[151.58958435100001,-32.7617988586],"type":"Point"}
}