{
  "type": "Feature",
  "properties": {
    "addr:full":"18 Adderston Ave North Sydney NSW 2060",
    "addr:housenumber":"18",
    "addr:postcode":"2060",
    "addr:street":"Adderston Ave",
    "iso:country":"AU",
    "sg:address":"18 Adderston Ave",
    "sg:city":"North Sydney",
    "sg:classifiers":[
        {
            "category":"Professional",
            "subcategory":"Art Services",
            "type":"Services"
        }
    ],
    "sg:phone":"+61 2 9959 5025",
    "sg:postcode":"2060",
    "sg:province":"NSW",
    "sg:tags":[
        "interior",
        "decorator"
    ],
    "wof:name":"Inside Ideas",
    "wof:placetype":"venue"
},
  "geometry": {"coordinates":[151.215774536,-33.8419265747],"type":"Point"}
}