{
  "type": "Feature",
  "properties": {
    "addr:full":"205 Stewart St Bathurst NSW 2795",
    "addr:housenumber":"205",
    "addr:postcode":"2795",
    "addr:street":"Stewart St",
    "iso:country":"AU",
    "sg:address":"205 Stewart St",
    "sg:city":"Bathurst",
    "sg:classifiers":[
        {
            "category":"Building & Trades",
            "subcategory":"Construction",
            "type":"Services"
        }
    ],
    "sg:phone":"+61 2 6331 1784",
    "sg:postcode":"2795",
    "sg:province":"NSW",
    "sg:tags":[
        "contractor"
    ],
    "wof:name":"Adam Hart Constructions Pty Ltd",
    "wof:placetype":"venue"
},
  "geometry": {"coordinates":[149.508575439,-33.4366264343],"type":"Point"}
}