{
  "type": "Feature",
  "properties": {
    "iso:country":"AU",
    "sg:address":"85 Cambridge Rd",
    "sg:city":"Bellerive",
    "sg:classifiers":[
        {
            "category":"Farming",
            "subcategory":"Nursery",
            "type":"Manufacturing & Wholesale Goods"
        }
    ],
    "sg:phone":"+61 3 6244 2737",
    "sg:postcode":"7018",
    "sg:province":"TAS",
    "wof:name":"Succulent Sensations",
    "wof:placetype":"venue"
},
  "geometry": {"coordinates":[147.37095642099999,-42.8702392578],"type":"Point"}
}