{
  "type": "Feature",
  "properties": {
    "addr:full":"16 Harding St Coburg VIC 3058",
    "addr:housenumber":"16",
    "addr:postcode":"3058",
    "addr:street":"Harding St",
    "iso:country":"AU",
    "sg:address":"16 Harding St",
    "sg:city":"Coburg",
    "sg:classifiers":[
        {
            "category":"Health Services",
            "subcategory":"Doctor",
            "type":"Services"
        }
    ],
    "sg:phone":"+61 3 9384 1321",
    "sg:postcode":"3058",
    "sg:province":"VIC",
    "sg:tags":[
        "medical",
        "practitioner"
    ],
    "wof:name":"Macgill Susan",
    "wof:placetype":"venue"
},
  "geometry": {"coordinates":[144.967697144,-37.7452697754],"type":"Point"}
}