{
  "type": "Feature",
  "properties": {
    "iso:country":"AU",
    "sg:address":"24 Chapman St",
    "sg:city":"Queanbeyan",
    "sg:classifiers":[
        {
            "category":"Home & Garden",
            "subcategory":"Furniture",
            "type":"Retail Goods"
        }
    ],
    "sg:phone":"+61 2 6299 6777",
    "sg:postcode":"2620",
    "sg:province":"NSW",
    "sg:tags":[
        "business"
    ],
    "wof:name":"VSL Joinery",
    "wof:placetype":"venue"
},
  "geometry": {"coordinates":[149.24357605,-35.336769104],"type":"Point"}
}