{
  "type": "Feature",
  "properties": {
    "iso:country":"AU",
    "sg:address":"Unit 2 15 Ivan St",
    "sg:city":"Labrador",
    "sg:classifiers":[
        {
            "category":"Retail",
            "subcategory":"Auto Repair",
            "type":"Services"
        }
    ],
    "sg:phone":"+61 7 5529 3871",
    "sg:postcode":"4215",
    "sg:province":"QLD",
    "sg:tags":[
        "repairer",
        "motor",
        "engineer"
    ],
    "wof:name":"Dyson Rotary",
    "wof:placetype":"venue"
},
  "geometry": {"coordinates":[153.38458251899999,-27.9375228882],"type":"Point"}
}