{
  "type": "Feature",
  "properties": {
    "iso:country":"AU",
    "sg:address":"92 Robinson Ave",
    "sg:city":"Belmont",
    "sg:classifiers":[
        {
            "category":"Farming",
            "subcategory":"Vineyard",
            "type":"Manufacturing & Wholesale Goods"
        }
    ],
    "sg:phone":"+61 8 9479 2633",
    "sg:postcode":"6104",
    "sg:province":"WA",
    "sg:tags":[
        "winery"
    ],
    "wof:name":"WA Wine Worldwide",
    "wof:placetype":"venue"
},
  "geometry": {"coordinates":[115.929260254,-31.9594554901],"type":"Point"}
}