{
  "type": "Feature",
  "properties": {
    "addr:full":"Lot 30 Warman St Neerabup WA 6031",
    "addr:postcode":"6031",
    "addr:street":"Warman St",
    "iso:country":"AU",
    "sg:address":"Lot 30 Warman St",
    "sg:city":"Neerabup",
    "sg:classifiers":[
        {
            "category":"Manufacturing",
            "subcategory":"Building Materials",
            "type":"Manufacturing & Wholesale Goods"
        }
    ],
    "sg:phone":"+61 8 9306 4407",
    "sg:postcode":"6031",
    "sg:province":"WA",
    "sg:tags":[
        "stone",
        "product",
        "supply"
    ],
    "wof:name":"Abcast Limestone",
    "wof:placetype":"venue"
},
  "geometry": {"coordinates":[115.786872864,-31.6853504181],"type":"Point"}
}