{
  "type": "Feature",
  "properties": {
    "addr:full":"Level 1/ 194 Devonshire St Surry Hills NSW 2010",
    "addr:housenumber":"/ 194",
    "addr:postcode":"2010",
    "addr:street":"Devonshire St",
    "iso:country":"AU",
    "sg:address":"Level 1/ 194 Devonshire St",
    "sg:city":"Surry Hills",
    "sg:classifiers":[
        {
            "category":"Professional",
            "subcategory":"Art Services",
            "type":"Services"
        }
    ],
    "sg:phone":"+61 2 8399 3233",
    "sg:postcode":"2010",
    "sg:province":"NSW",
    "sg:tags":[
        "graphic",
        "designer"
    ],
    "wof:name":"Ascender Design",
    "wof:placetype":"venue"
},
  "geometry": {"coordinates":[151.211013794,-33.8875045776],"type":"Point"}
}