{
  "type": "Feature",
  "properties": {
    "iso:country":"AU",
    "sg:address":"20 McGuire Mews",
    "sg:city":"Rockingham",
    "sg:classifiers":[
        {
            "category":"Autos & Motor Vehicles",
            "subcategory":"Boat Sales",
            "type":"Retail Goods"
        }
    ],
    "sg:phone":"+61 405 163 777",
    "sg:postcode":"6168",
    "sg:province":"WA",
    "sg:tags":[
        "builder",
        "yacht",
        "repairer"
    ],
    "wof:name":"Cobra Alloys",
    "wof:placetype":"venue"
},
  "geometry": {"coordinates":[115.72577699999999,-32.291924],"type":"Point"}
}