{
  "type": "Feature",
  "properties": {
    "addr:full":"1651 Burwood Hwy Belgrave VIC 3160",
    "addr:housenumber":"1651",
    "addr:postcode":"3160",
    "addr:street":"Burwood Hwy",
    "iso:country":"AU",
    "sg:address":"1651 Burwood Hwy",
    "sg:city":"Belgrave",
    "sg:classifiers":[
        {
            "category":"Health Services",
            "subcategory":"Doctor",
            "type":"Services"
        }
    ],
    "sg:phone":"+61 3 9752 5211",
    "sg:postcode":"3160",
    "sg:province":"VIC",
    "sg:tags":[
        "medical",
        "practitioner"
    ],
    "wof:name":"Belgrave Health Care",
    "wof:placetype":"venue"
},
  "geometry": {"coordinates":[145.35353088400001,-37.9096565247],"type":"Point"}
}