{
  "type": "Feature",
  "properties": {
    "addr:full":"Level 1, 10 Market St Brisbane QLD 4000",
    "addr:housenumber":"10",
    "addr:postcode":"4000",
    "addr:street":"Market St",
    "iso:country":"AU",
    "sg:address":"Level 1, 10 Market St",
    "sg:city":"Brisbane",
    "sg:classifiers":[
        {
            "category":"Professional",
            "type":"Services"
        }
    ],
    "sg:phone":"+61 7 3221 2300",
    "sg:postcode":"4000",
    "sg:province":"QLD",
    "sg:tags":[
        "auctioneer"
    ],
    "wof:name":"Mason Gray Strange Auctioneers & Valuers Pty Ltd",
    "wof:placetype":"venue"
},
  "geometry": {"coordinates":[153.029785156,-27.4697532654],"type":"Point"}
}