{
  "type": "Feature",
  "properties": {
    "addr:full":"6 Wenden Pl Willetton WA 6155",
    "addr:housenumber":"6",
    "addr:postcode":"6155",
    "addr:street":"Pl",
    "iso:country":"AU",
    "sg:address":"6 Wenden Pl",
    "sg:city":"Willetton",
    "sg:classifiers":[
        {
            "category":"Professional",
            "subcategory":"Business Services",
            "type":"Services"
        }
    ],
    "sg:phone":"+61 8 9354 7404",
    "sg:postcode":"6155",
    "sg:province":"WA",
    "sg:tags":[
        "drafting"
    ],
    "wof:name":"Needle Drafting Service",
    "wof:placetype":"venue"
},
  "geometry": {"coordinates":[115.90186300000001,-32.042034],"type":"Point"}
}