{
  "type": "Feature",
  "properties": {
    "iso:country":"AU",
    "sg:address":"U2/ 20 Sundercombe St",
    "sg:city":"Osborne Park",
    "sg:classifiers":[
        {
            "category":"Shopping",
            "subcategory":"Computers & Home Electronics",
            "type":"Retail Goods"
        }
    ],
    "sg:phone":"+61 8 9446 4088",
    "sg:postcode":"6017",
    "sg:province":"WA",
    "sg:tags":[
        "hardware",
        "equipment"
    ],
    "wof:name":"A E Tech",
    "wof:placetype":"venue"
},
  "geometry": {"coordinates":[115.81288146999999,-31.9036808014],"type":"Point"}
}