{
  "type": "Feature",
  "properties": {
    "addr:full":"49 Irrigation Rd Merrylands West NSW 2160",
    "addr:housenumber":"49",
    "addr:postcode":"2160",
    "addr:street":"Irrigation Rd",
    "iso:country":"AU",
    "sg:address":"49 Irrigation Rd",
    "sg:city":"Merrylands West",
    "sg:classifiers":[
        {
            "category":"Education",
            "subcategory":"University",
            "type":"Public Place"
        }
    ],
    "sg:phone":"+61 2 9896 1683",
    "sg:postcode":"2160",
    "sg:province":"NSW",
    "sg:tags":[
        "educational",
        "organisation",
        "cultural"
    ],
    "wof:name":"Guides New South Wales",
    "wof:placetype":"venue"
},
  "geometry": {"coordinates":[150.96429443400001,-33.8284683228],"type":"Point"}
}