{
  "type": "Feature",
  "properties": {
    "iso:country":"AU",
    "sg:address":"95 Burwood Rd",
    "sg:city":"Burwood",
    "sg:classifiers":[
        {
            "category":"Professional",
            "subcategory":"Accounting & Tax Preparation",
            "type":"Services"
        }
    ],
    "sg:phone":"+61 2 9744 2443",
    "sg:postcode":"2134",
    "sg:province":"NSW",
    "sg:tags":[
        "accountant",
        "auditor"
    ],
    "wof:name":"Tusa Leonard C",
    "wof:placetype":"venue"
},
  "geometry": {"coordinates":[151.10382080100001,-33.8759460449],"type":"Point"}
}