{
  "type": "Feature",
  "properties": {
    "iso:country":"AU",
    "sg:address":"PO Box 155",
    "sg:city":"Silverdale",
    "sg:classifiers":[
        {
            "category":"Utilities",
            "type":"Services"
        }
    ],
    "sg:phone":"+61 2 9608 4303",
    "sg:postcode":"2752",
    "sg:province":"NSW",
    "sg:tags":[
        "refrigeration",
        "industrial",
        "commercial",
        "retail"
    ],
    "wof:name":"Orbit Refrigeration",
    "wof:placetype":"venue"
},
  "geometry": {"coordinates":[150.60534668,-33.9075317383],"type":"Point"}
}