{
  "type": "Feature",
  "properties": {
    "addr:full":"26 Grove St Waratah NSW 2298",
    "addr:housenumber":"26",
    "addr:postcode":"2298",
    "addr:street":"Grove St",
    "iso:country":"AU",
    "sg:address":"26 Grove St",
    "sg:city":"Waratah",
    "sg:classifiers":[
        {
            "category":"Utilities",
            "subcategory":"Electric",
            "type":"Services"
        }
    ],
    "sg:phone":"+61 2 4967 4941",
    "sg:postcode":"2298",
    "sg:province":"NSW",
    "sg:tags":[
        "electrical",
        "contractor"
    ],
    "wof:name":"Cross Mick Electrician",
    "wof:placetype":"venue"
},
  "geometry": {"coordinates":[151.72564697300001,-32.9001731873],"type":"Point"}
}