{
  "type": "Feature",
  "properties": {
    "iso:country":"AU",
    "sg:address":"20 Church St",
    "sg:city":"Moruya",
    "sg:classifiers":[
        {
            "category":"Restaurant",
            "type":"Food & Drink"
        }
    ],
    "sg:phone":"+61 2 4474 2979",
    "sg:postcode":"2537",
    "sg:province":"NSW",
    "wof:name":"Anna & Sam Pizzeria Restaurant",
    "wof:placetype":"venue"
},
  "geometry": {"coordinates":[150.08319091800001,-35.9095077515],"type":"Point"}
}