{
  "type": "Feature",
  "properties": {
    "addr:full":"12- 14 King St Airport West VIC 3042",
    "addr:housenumber":"14",
    "addr:postcode":"3042",
    "addr:street":"King St",
    "iso:country":"AU",
    "sg:address":"12- 14 King St",
    "sg:city":"Airport West",
    "sg:classifiers":[
        {
            "category":"Sports & Exercise",
            "subcategory":"Race Track",
            "type":"Entertainment"
        }
    ],
    "sg:phone":"+61 3 9335 5355",
    "sg:postcode":"3042",
    "sg:province":"VIC",
    "sg:tags":[
        "access",
        "cover",
        "grating"
    ],
    "wof:name":"Access Covers Australia Pty Ltd",
    "wof:placetype":"venue"
},
  "geometry": {"coordinates":[144.88981628400001,-37.7233428955],"type":"Point"}
}