{
  "type": "Feature",
  "properties": {
    "iso:country":"AU",
    "sg:address":"42 Franklin St",
    "sg:city":"Swansea",
    "sg:classifiers":[
        {
            "category":"Personal",
            "subcategory":"Beauty Salon",
            "type":"Services"
        }
    ],
    "sg:phone":"+61 3 6257 8244",
    "sg:postcode":"7190",
    "sg:province":"TAS",
    "sg:tags":[
        "hairdresser"
    ],
    "wof:name":"Swansea Hair Design",
    "wof:placetype":"venue"
},
  "geometry": {"coordinates":[148.071213,-42.121288],"type":"Point"}
}