{
  "type": "Feature",
  "properties": {
    "addr:full":"Community Health Centre Back Beach Rd San Remo VIC 3925",
    "addr:postcode":"3925",
    "addr:street":"Back Beach Rd",
    "iso:country":"AU",
    "sg:address":"Community Health Centre Back Beach Rd",
    "sg:city":"San Remo",
    "sg:classifiers":[
        {
            "category":"Social Services",
            "subcategory":"Child Care",
            "type":"Services"
        }
    ],
    "sg:phone":"+61 3 5678 5388",
    "sg:postcode":"3925",
    "sg:province":"VIC",
    "sg:tags":[
        "support",
        "health"
    ],
    "wof:name":"Maternal & Child Health Centres",
    "wof:placetype":"venue"
},
  "geometry": {"coordinates":[145.371185303,-38.5292167664],"type":"Point"}
}