{
  "type": "Feature",
  "properties": {
    "addr:full":"Suite 21, Abergeldie House 548 Port Rush Rd Glen Osmond SA 5064",
    "addr:housenumber":"548",
    "addr:postcode":"5064",
    "addr:street":"Port Rush Rd",
    "iso:country":"AU",
    "sg:address":"Suite 21, Abergeldie House 548 Port Rush Rd",
    "sg:city":"Glen Osmond",
    "sg:classifiers":[
        {
            "category":"Health Services",
            "subcategory":"Health Practitioner",
            "type":"Services"
        }
    ],
    "sg:phone":"+61 406 257 598",
    "sg:postcode":"5064",
    "sg:province":"SA",
    "sg:tags":[
        "physiotherapist"
    ],
    "wof:name":"James McLoughlin Neurophysiotherapy",
    "wof:placetype":"venue"
},
  "geometry": {"coordinates":[138.64390564000001,-34.9565162659],"type":"Point"}
}