{
  "type": "Feature",
  "properties": {
    "iso:country":"AU",
    "sg:address":"38 Graves St",
    "sg:city":"Kadina",
    "sg:classifiers":[
        {
            "category":"Retail",
            "subcategory":"Repair Shop",
            "type":"Services"
        }
    ],
    "sg:phone":"+61 8 8821 1322",
    "sg:postcode":"5554",
    "sg:province":"SA",
    "sg:tags":[
        "machine",
        "repairs",
        "part",
        "dryer",
        "washing"
    ],
    "wof:name":"Kadina Electrical",
    "wof:placetype":"venue"
},
  "geometry": {"coordinates":[137.71426391599999,-33.9636116028],"type":"Point"}
}