{
  "type": "Feature",
  "properties": {
    "addr:full":"143 Murray St Gawler SA 5118",
    "addr:housenumber":"143",
    "addr:postcode":"5118",
    "addr:street":"Murray St",
    "iso:country":"AU",
    "sg:address":"143 Murray St",
    "sg:city":"Gawler",
    "sg:classifiers":[
        {
            "category":"Health Services",
            "subcategory":"Doctor",
            "type":"Services"
        }
    ],
    "sg:phone":"+61 8 8522 1544",
    "sg:postcode":"5118",
    "sg:province":"SA",
    "sg:tags":[
        "medical",
        "practitioner"
    ],
    "wof:name":"Murray St Clinic",
    "wof:placetype":"venue"
},
  "geometry": {"coordinates":[138.74923699999999,-34.596626],"type":"Point"}
}