{
  "type": "Feature",
  "properties": {
    "iso:country":"AU",
    "sg:address":"21 Beach St",
    "sg:city":"Fremantle",
    "sg:classifiers":[
        {
            "category":"Arts & Performance",
            "subcategory":"Art Gallery",
            "type":"Entertainment"
        }
    ],
    "sg:phone":"+61 8 9430 2414",
    "sg:postcode":"6160",
    "sg:province":"WA",
    "wof:name":"Freight Gallery",
    "wof:placetype":"venue"
},
  "geometry": {"coordinates":[115.749046326,-32.0490951538],"type":"Point"}
}