{
  "type": "Feature",
  "properties": {
    "iso:country":"AU",
    "sg:address":"175 Como Pde East",
    "sg:city":"Parkdale",
    "sg:classifiers":[
        {
            "category":"Fast Food",
            "type":"Food & Drink"
        }
    ],
    "sg:phone":"+61 13 11 66",
    "sg:postcode":"3194",
    "sg:province":"VIC",
    "sg:tags":[
        "away",
        "take"
    ],
    "wof:name":"Pizza Hut Delivery",
    "wof:placetype":"venue"
},
  "geometry": {"coordinates":[145.077026367,-37.993183136],"type":"Point"}
}