{
  "type": "Feature",
  "properties": {
    "addr:full":"167 Plenty Rd Preston VIC 3072",
    "addr:housenumber":"167",
    "addr:postcode":"3072",
    "addr:street":"Plenty Rd",
    "iso:country":"AU",
    "sg:address":"167 Plenty Rd",
    "sg:city":"Preston",
    "sg:classifiers":[
        {
            "category":"Social Services",
            "subcategory":"Adult Care",
            "type":"Services"
        }
    ],
    "sg:phone":"+61 3 9480 1311",
    "sg:postcode":"3072",
    "sg:province":"VIC",
    "sg:tags":[
        "towing"
    ],
    "wof:name":"Allnyte Towing Service Pty Ltd",
    "wof:placetype":"venue"
},
  "geometry": {"coordinates":[145.065917969,-37.6884536743],"type":"Point"}
}