{
  "type": "Feature",
  "properties": {
    "iso:country":"AU",
    "sg:address":"Albany Hwy",
    "sg:city":"Maddington",
    "sg:classifiers":[
        {
            "category":"Education",
            "subcategory":"School",
            "type":"Public Place"
        }
    ],
    "sg:phone":"+61 8 9459 1239",
    "sg:postcode":"6109",
    "sg:province":"WA",
    "sg:tags":[
        "state",
        "except",
        "nsw"
    ],
    "wof:name":"Maddington Primary",
    "wof:placetype":"venue"
},
  "geometry": {"coordinates":[115.98346710200001,-32.050819397],"type":"Point"}
}