{
  "type": "Feature",
  "properties": {
    "addr:full":"Unit 4/ 64 McCoy St Myaree WA 6154",
    "addr:housenumber":"64",
    "addr:postcode":"6154",
    "addr:street":"Mccoy St",
    "iso:country":"AU",
    "sg:address":"Unit 4/ 64 McCoy St",
    "sg:city":"Myaree",
    "sg:classifiers":[
        {
            "category":"Building & Trades",
            "subcategory":"Cleaning & Sanitation",
            "type":"Services"
        }
    ],
    "sg:phone":"+61 8 9330 6807",
    "sg:postcode":"6154",
    "sg:province":"WA",
    "sg:tags":[
        "commercial",
        "maintenance"
    ],
    "wof:name":"Midolo Building Services",
    "wof:placetype":"venue"
},
  "geometry": {"coordinates":[115.81710099999999,-32.043381],"type":"Point"}
}