{
  "type": "Feature",
  "properties": {
    "iso:country":"AU",
    "sg:address":"Suite 8, 279 Canning Hwy",
    "sg:city":"Palmyra",
    "sg:classifiers":[
        {
            "category":"Health Services",
            "subcategory":"Doctor",
            "type":"Services"
        }
    ],
    "sg:phone":"+61 8 9339 0288",
    "sg:postcode":"6157",
    "sg:province":"WA",
    "sg:tags":[
        "medical",
        "practitioner"
    ],
    "wof:name":"Rhodes Helen",
    "wof:placetype":"venue"
},
  "geometry": {"coordinates":[115.77787,-32.037991],"type":"Point"}
}