{
  "type": "Feature",
  "properties": {
    "addr:full":"145 Chesterfield Rd Park Ridge South QLD 4125",
    "addr:housenumber":"145",
    "addr:postcode":"4125",
    "addr:street":"Chesterfield Rd",
    "iso:country":"AU",
    "sg:address":"145 Chesterfield Rd",
    "sg:city":"Park Ridge South",
    "sg:classifiers":[
        {
            "category":"Commercial Area",
            "type":"Public Place"
        }
    ],
    "sg:phone":"+61 418 788 632",
    "sg:postcode":"4125",
    "sg:province":"QLD",
    "sg:tags":[
        "heavy",
        "carrier"
    ],
    "wof:name":"BSF Heavy Haulage",
    "wof:placetype":"venue"
},
  "geometry": {"coordinates":[153.04258727999999,-27.7234840393],"type":"Point"}
}