{
  "type": "Feature",
  "properties": {
    "addr:full":"66 Roberts Rd Osborne Park WA 6017",
    "addr:housenumber":"66",
    "addr:postcode":"6017",
    "addr:street":"Roberts Rd",
    "iso:country":"AU",
    "sg:address":"66 Roberts Rd",
    "sg:city":"Osborne Park",
    "sg:classifiers":[
        {
            "category":"Professional",
            "subcategory":"Art Services",
            "type":"Services"
        }
    ],
    "sg:phone":"+61 8 9444 4304",
    "sg:postcode":"6017",
    "sg:province":"WA",
    "sg:tags":[
        "picture",
        "frame",
        "framing"
    ],
    "wof:name":"ArtWorld",
    "wof:placetype":"venue"
},
  "geometry": {"coordinates":[115.823928833,-31.9079647064],"type":"Point"}
}