{
  "type": "Feature",
  "properties": {
    "addr:full":"21 Marshall Ave Highett VIC 3190",
    "addr:housenumber":"21",
    "addr:postcode":"3190",
    "addr:street":"Marshall Ave",
    "iso:country":"AU",
    "sg:address":"21 Marshall Ave",
    "sg:city":"Highett",
    "sg:classifiers":[
        {
            "category":"Government",
            "subcategory":"Court House",
            "type":"Public Place"
        }
    ],
    "sg:phone":"+61 3 9598 5373",
    "sg:postcode":"3190",
    "sg:province":"VIC",
    "sg:tags":[
        "personal",
        "marriage",
        "family",
        "counselling"
    ],
    "wof:name":"Staley Holistic Counselling",
    "wof:placetype":"venue"
},
  "geometry": {"coordinates":[145.02757263199999,-37.9519424438],"type":"Point"}
}