{
  "type": "Feature",
  "properties": {
    "addr:full":"PO Box 93 Lindfield NSW 2070",
    "addr:postcode":"2070",
    "iso:country":"AU",
    "sg:address":"PO Box 93",
    "sg:city":"Lindfield",
    "sg:classifiers":[
        {
            "category":"Home & Garden",
            "subcategory":"Garden Supply",
            "type":"Retail Goods"
        }
    ],
    "sg:phone":"+61 2 4567 7468",
    "sg:postcode":"2070",
    "sg:province":"NSW",
    "sg:tags":[
        "landscape"
    ],
    "wof:name":"Stoned Decorative Pebble Supplies",
    "wof:placetype":"venue"
},
  "geometry": {"coordinates":[151.16867065400001,-33.775188446],"type":"Point"}
}