{
  "type": "Feature",
  "properties": {
    "iso:country":"AU",
    "sg:address":"Shop 5/ 78 Daisy St",
    "sg:city":"Fairy Meadow",
    "sg:classifiers":[
        {
            "category":"Personal",
            "subcategory":"Nail Salon",
            "type":"Services"
        }
    ],
    "sg:phone":"+61 2 4283 2727",
    "sg:postcode":"2519",
    "sg:province":"NSW",
    "sg:tags":[
        "artificial"
    ],
    "wof:name":"Allure Beauty & Nails",
    "wof:placetype":"venue"
},
  "geometry": {"coordinates":[150.895264,-34.394405],"type":"Point"}
}