{
  "type": "Feature",
  "properties": {
    "iso:country":"AU",
    "sg:address":"2/ 92 Garden St",
    "sg:city":"North Narrabeen",
    "sg:classifiers":[
        {
            "category":"Retail",
            "subcategory":"Auto Repair",
            "type":"Services"
        }
    ],
    "sg:phone":"+61 2 9970 6963",
    "sg:postcode":"2101",
    "sg:province":"NSW",
    "sg:tags":[
        "transmission",
        "automotive",
        "car"
    ],
    "wof:name":"Powershift Automatics",
    "wof:placetype":"venue"
},
  "geometry": {"coordinates":[151.294769,-33.700359],"type":"Point"}
}