{
  "type": "Feature",
  "properties": {
    "iso:country":"AU",
    "sg:address":"Suite 3G John Flynn Hospital",
    "sg:city":"Tugun",
    "sg:classifiers":[
        {
            "category":"Health Services",
            "subcategory":"Doctor",
            "type":"Services"
        }
    ],
    "sg:phone":"+61 7 5598 9188",
    "sg:postcode":"4224",
    "sg:province":"QLD",
    "sg:tags":[
        "medical",
        "practitioner"
    ],
    "wof:name":"Cherry Richard E",
    "wof:placetype":"venue"
},
  "geometry": {"coordinates":[153.49212646500001,-28.1418399811],"type":"Point"}
}