{
  "type": "Feature",
  "properties": {
    "addr:full":"U6/ 312 High St Chatswood NSW 2067",
    "addr:housenumber":"312",
    "addr:postcode":"2067",
    "addr:street":"U6 /;High St",
    "iso:country":"AU",
    "sg:address":"U6/ 312 High St",
    "sg:city":"Chatswood",
    "sg:classifiers":[
        {
            "category":"Autos & Motor Vehicles",
            "subcategory":"Automobile Sales",
            "type":"Retail Goods"
        }
    ],
    "sg:phone":"+61 2 9882 3339",
    "sg:postcode":"2067",
    "sg:province":"NSW",
    "sg:tags":[
        "car",
        "used"
    ],
    "wof:name":"Online Autos Chatswood",
    "wof:placetype":"venue"
},
  "geometry": {"coordinates":[151.19642639200001,-33.7869873047],"type":"Point"}
}