{
  "type": "Feature",
  "properties": {
    "addr:full":"1/ 1111 High St Armadale VIC 3143",
    "addr:housenumber":"/ 1111",
    "addr:postcode":"3143",
    "addr:street":"High St",
    "iso:country":"AU",
    "sg:address":"1/ 1111 High St",
    "sg:city":"Armadale",
    "sg:classifiers":[
        {
            "category":"Wholesale",
            "subcategory":"Apparel",
            "type":"Manufacturing & Wholesale Goods"
        }
    ],
    "sg:phone":"+61 3 9823 1965",
    "sg:postcode":"3143",
    "sg:province":"VIC",
    "sg:tags":[
        "wholesaler",
        "mfrs",
        "uniform"
    ],
    "wof:name":"Rockmans Corporate Promotions",
    "wof:placetype":"venue"
},
  "geometry": {"coordinates":[145.024536133,-37.8558616638],"type":"Point"}
}