{
  "type": "Feature",
  "properties": {
    "addr:full":"988 Nepean Hwy Mornington VIC 3931",
    "addr:housenumber":"988",
    "addr:postcode":"3931",
    "addr:street":"Nepean Hwy",
    "iso:country":"AU",
    "sg:address":"988 Nepean Hwy",
    "sg:city":"Mornington",
    "sg:classifiers":[
        {
            "category":"Home & Garden",
            "subcategory":"Garden Supply",
            "type":"Retail Goods"
        }
    ],
    "sg:phone":"+61 3 5975 4195",
    "sg:postcode":"3931",
    "sg:province":"VIC",
    "sg:tags":[
        "equipment"
    ],
    "wof:name":"Shanted Organic Manures",
    "wof:placetype":"venue"
},
  "geometry": {"coordinates":[145.04620361299999,-38.2287025452],"type":"Point"}
}