{
  "type": "Feature",
  "properties": {
    "iso:country":"AU",
    "sg:address":"PO Box 6",
    "sg:city":"Sandown Village",
    "sg:classifiers":[
        {
            "category":"Wholesale",
            "subcategory":"Painting Supplies",
            "type":"Manufacturing & Wholesale Goods"
        }
    ],
    "sg:phone":"+61 3 9796 1177",
    "sg:postcode":"3171",
    "sg:province":"VIC",
    "sg:tags":[
        "equipment",
        "drawing",
        "drafting"
    ],
    "wof:name":"W & G Australia",
    "wof:placetype":"venue"
},
  "geometry": {"coordinates":[145.170379639,-37.9420127869],"type":"Point"}
}