{
  "type": "Feature",
  "properties": {
    "addr:full":"3 Vespa Crt Bundall QLD 4217",
    "addr:housenumber":"3",
    "addr:postcode":"4217",
    "addr:street":"Vespa Crt",
    "iso:country":"AU",
    "sg:address":"3 Vespa Crt",
    "sg:city":"Bundall",
    "sg:classifiers":[
        {
            "category":"Professional",
            "subcategory":"Employment Agencies",
            "type":"Services"
        }
    ],
    "sg:phone":"+61 7 5592 8880",
    "sg:postcode":"4217",
    "sg:province":"QLD",
    "wof:name":"EVP (Gold Coast) Pty Ltd",
    "wof:placetype":"venue"
},
  "geometry": {"coordinates":[153.41325378400001,-28.0075416565],"type":"Point"}
}