{
  "type": "Feature",
  "properties": {
    "addr:full":"4/ 4 Duke St Nambucca Heads NSW 2448",
    "addr:housenumber":"/ 4",
    "addr:postcode":"2448",
    "addr:street":"Duke St",
    "iso:country":"AU",
    "sg:address":"4/ 4 Duke St",
    "sg:city":"Nambucca Heads",
    "sg:classifiers":[
        {
            "category":"Retail",
            "subcategory":"Auto Repair",
            "type":"Services"
        }
    ],
    "sg:phone":"+61 2 6568 5366",
    "sg:postcode":"2448",
    "sg:province":"NSW",
    "sg:tags":[
        "repairer",
        "motor",
        "engineer"
    ],
    "wof:name":"Nambucca Auto Clinic & Tyre Shop",
    "wof:placetype":"venue"
},
  "geometry": {"coordinates":[152.97903400000001,-30.635668],"type":"Point"}
}