{
  "type": "Feature",
  "properties": {
    "addr:full":"Sportsman Hotel Bottleshop 130 Leichhardt St Spring Hill QLD 4000",
    "addr:housenumber":"130",
    "addr:postcode":"4000",
    "addr:street":"Leichhardt St",
    "iso:country":"AU",
    "sg:address":"Sportsman Hotel Bottleshop 130 Leichhardt St",
    "sg:city":"Spring Hill",
    "sg:classifiers":[
        {
            "category":"Food & Beverages",
            "subcategory":"Liquor & Beverages",
            "type":"Retail Goods"
        }
    ],
    "sg:phone":"+61 7 3831 3833",
    "sg:postcode":"4000",
    "sg:province":"QLD",
    "sg:tags":[
        "store"
    ],
    "wof:name":"Liquorwise",
    "wof:placetype":"venue"
},
  "geometry": {"coordinates":[153.02500915499999,-27.4625282288],"type":"Point"}
}