{
  "type": "Feature",
  "properties": {
    "iso:country":"AU",
    "sg:address":"34 Clevedon Rd",
    "sg:city":"Hurstville",
    "sg:classifiers":[
        {
            "category":"Professional",
            "subcategory":"Business Services",
            "type":"Services"
        }
    ],
    "sg:phone":"+61 2 9594 4890",
    "sg:postcode":"2220",
    "sg:province":"NSW",
    "sg:tags":[
        "broker"
    ],
    "wof:name":"Frontline Solutions",
    "wof:placetype":"venue"
},
  "geometry": {"coordinates":[151.10177612300001,-33.9580955505],"type":"Point"}
}