{
  "type": "Feature",
  "properties": {
    "iso:country":"AU",
    "sg:address":"560 Mulgrave Rd",
    "sg:city":"Woree",
    "sg:classifiers":[
        {
            "category":"Mining & Drilling",
            "type":"Manufacturing & Wholesale Goods"
        }
    ],
    "sg:phone":"+61 7 4033 1805",
    "sg:postcode":"4868",
    "sg:province":"QLD",
    "sg:tags":[
        "geologist"
    ],
    "wof:name":"Reveleigh Graham & Associates",
    "wof:placetype":"venue"
},
  "geometry": {"coordinates":[145.74111938499999,-16.9492778778],"type":"Point"}
}