{
  "type": "Feature",
  "properties": {
    "addr:full":"5a Tointon St Toowoomba QLD 4350",
    "addr:housenumber":"5a",
    "addr:postcode":"4350",
    "addr:street":"Tointon St",
    "iso:country":"AU",
    "sg:address":"5a Tointon St",
    "sg:city":"Toowoomba",
    "sg:classifiers":[
        {
            "category":"Retail",
            "subcategory":"Auto Repair",
            "type":"Services"
        }
    ],
    "sg:phone":"+61 7 4638 2346",
    "sg:postcode":"4350",
    "sg:province":"QLD",
    "sg:tags":[
        "repairer",
        "motor",
        "engineer"
    ],
    "wof:name":"Briffas Auto Repairs",
    "wof:placetype":"venue"
},
  "geometry": {"coordinates":[151.94564800000001,-27.56498],"type":"Point"}
}