{
  "type": "Feature",
  "properties": {
    "iso:country":"AU",
    "sg:address":"Cnr Coral & Elizabeth St",
    "sg:city":"Urangan",
    "sg:classifiers":[
        {
            "category":"Retail",
            "subcategory":"Laundry & Dry Cleaning",
            "type":"Services"
        }
    ],
    "sg:phone":"+61 7 4124 1563",
    "sg:postcode":"4655",
    "sg:province":"QLD",
    "wof:name":"Hervey Bay Laundromat",
    "wof:placetype":"venue"
},
  "geometry": {"coordinates":[152.89894100000001,-25.285597],"type":"Point"}
}