{
  "type": "Feature",
  "properties": {
    "addr:full":"24 Cohn St Carlisle WA 6101",
    "addr:housenumber":"24",
    "addr:postcode":"6101",
    "addr:street":"Cohn St",
    "iso:country":"AU",
    "sg:address":"24 Cohn St",
    "sg:city":"Carlisle",
    "sg:classifiers":[
        {
            "category":"Wholesale",
            "subcategory":"Drugs",
            "type":"Manufacturing & Wholesale Goods"
        }
    ],
    "sg:phone":"+61 8 9472 3888",
    "sg:postcode":"6101",
    "sg:province":"WA",
    "sg:tags":[
        "wholesaler",
        "lawn",
        "mfrs",
        "mower"
    ],
    "wof:name":"Western Mower Spares",
    "wof:placetype":"venue"
},
  "geometry": {"coordinates":[115.92224883999999,-31.9851207733],"type":"Point"}
}