{
  "type": "Feature",
  "properties": {
    "iso:country":"AU",
    "sg:address":"U1/ 11 Maurita Crt",
    "sg:city":"Canungra",
    "sg:classifiers":[
        {
            "category":"Ferry Terminal",
            "type":"Transportation"
        }
    ],
    "sg:phone":"+61 7 5543 4612",
    "sg:postcode":"4275",
    "sg:province":"QLD",
    "sg:tags":[
        "inverter",
        "rectifier"
    ],
    "wof:name":"Electronic Solutions Technology",
    "wof:placetype":"venue"
},
  "geometry": {"coordinates":[153.15982055699999,-28.0260715485],"type":"Point"}
}