{
  "type": "Feature",
  "properties": {
    "addr:full":"PO Box 4348 Dandenong South VIC 3164",
    "addr:postcode":"3164",
    "iso:country":"AU",
    "sg:address":"PO Box 4348",
    "sg:city":"Dandenong South",
    "sg:classifiers":[
        {
            "category":"Shopping",
            "type":"Retail Goods"
        }
    ],
    "sg:phone":"+61 3 9701 7133",
    "sg:postcode":"3164",
    "sg:province":"VIC",
    "sg:tags":[
        "equipment",
        "safety",
        "accessory"
    ],
    "wof:name":"Access Safety Services",
    "wof:placetype":"venue"
},
  "geometry": {"coordinates":[145.201705933,-38.0340309143],"type":"Point"}
}