{
  "type": "Feature",
  "properties": {
    "addr:full":"PO Box 674 Bulimba QLD 4171",
    "addr:postcode":"4171",
    "iso:country":"AU",
    "sg:address":"PO Box 674",
    "sg:city":"Bulimba",
    "sg:classifiers":[
        {
            "category":"Banks & Credit Unions",
            "subcategory":"Bureau De Change",
            "type":"Services"
        }
    ],
    "sg:phone":"+61 7 3217 9544",
    "sg:postcode":"4171",
    "sg:province":"QLD",
    "sg:tags":[
        "escort",
        "transport",
        "pilot"
    ],
    "wof:name":"Torres Pilots Pty Ltd",
    "wof:placetype":"venue"
},
  "geometry": {"coordinates":[153.05929565400001,-27.4513607025],"type":"Point"}
}