{
  "type": "Feature",
  "properties": {
    "addr:full":"27 Northgate Drv Thomastown VIC 3074",
    "addr:housenumber":"27",
    "addr:postcode":"3074",
    "addr:street":"Northgate Drv",
    "iso:country":"AU",
    "sg:address":"27 Northgate Drv",
    "sg:city":"Thomastown",
    "sg:classifiers":[
        {
            "category":"Shopping",
            "subcategory":"Computers & Home Electronics",
            "type":"Retail Goods"
        }
    ],
    "sg:phone":"+61 3 9465 7631",
    "sg:postcode":"3074",
    "sg:province":"VIC",
    "sg:tags":[
        "plate",
        "name"
    ],
    "wof:name":"Inscribe Australia Signage & Badges",
    "wof:placetype":"venue"
},
  "geometry": {"coordinates":[145.04225158700001,-37.6893882751],"type":"Point"}
}