{
  "type": "Feature",
  "properties": {
    "addr:full":"Shop 1, Mater Private 538 Stanley St South Brisbane QLD 4101",
    "addr:housenumber":"shop 1;538",
    "addr:postcode":"4101",
    "addr:street":"Mater Private;Stanley St",
    "iso:country":"AU",
    "sg:address":"Shop 1, Mater Private 538 Stanley St",
    "sg:city":"South Brisbane",
    "sg:classifiers":[
        {
            "category":"Cafe",
            "type":"Food & Drink"
        }
    ],
    "sg:phone":"+61 7 3255 3913",
    "sg:postcode":"4101",
    "sg:province":"QLD",
    "wof:name":"Coffee Club The",
    "wof:placetype":"venue"
},
  "geometry": {"coordinates":[153.02835082999999,-27.4846801758],"type":"Point"}
}