{
  "type": "Feature",
  "properties": {
    "iso:country":"AU",
    "sg:address":"1 Blencowe St",
    "sg:city":"West Leederville",
    "sg:classifiers":[
        {
            "category":"Recreation",
            "subcategory":"Boat Charter",
            "type":"Entertainment"
        }
    ],
    "sg:phone":"+61 8 9381 2704",
    "sg:postcode":"6007",
    "sg:province":"WA",
    "wof:name":"Jazz II Charters",
    "wof:placetype":"venue"
},
  "geometry": {"coordinates":[115.831047058,-31.9424228668],"type":"Point"}
}