{
  "type": "Feature",
  "properties": {
    "addr:full":"12 Penshurst St Penshurst NSW 2222",
    "addr:housenumber":"12",
    "addr:postcode":"2222",
    "addr:street":"Penshurst St",
    "iso:country":"AU",
    "sg:address":"12 Penshurst St",
    "sg:city":"Penshurst",
    "sg:classifiers":[
        {
            "category":"Real Estate",
            "subcategory":"Real Estate Agent",
            "type":"Services"
        }
    ],
    "sg:phone":"+61 2 9585 1888",
    "sg:postcode":"2222",
    "sg:province":"NSW",
    "wof:name":"Professionals The",
    "wof:placetype":"venue"
},
  "geometry": {"coordinates":[151.088821411,-33.9654884338],"type":"Point"}
}