{
  "type": "Feature",
  "properties": {
    "iso:country":"AU",
    "sg:address":"2 Elderslie Rd",
    "sg:city":"Brighton",
    "sg:classifiers":[
        {
            "category":"Personal",
            "subcategory":"Massage",
            "type":"Services"
        }
    ],
    "sg:phone":"+61 3 6268 0019",
    "sg:postcode":"7030",
    "sg:province":"TAS",
    "sg:tags":[
        "therapy"
    ],
    "wof:name":"Amity Massage",
    "wof:placetype":"venue"
},
  "geometry": {"coordinates":[147.248123169,-42.7024726868],"type":"Point"}
}