{
  "type": "Feature",
  "properties": {
    "addr:full":"66 Commissioner St Cooma NSW 2630",
    "addr:housenumber":"66",
    "addr:postcode":"2630",
    "addr:street":"Commissioner St",
    "iso:country":"AU",
    "sg:address":"66 Commissioner St",
    "sg:city":"Cooma",
    "sg:classifiers":[
        {
            "category":"Education",
            "subcategory":"Vocational School",
            "type":"Public Place"
        }
    ],
    "sg:phone":"+61 2 6452 0799",
    "sg:postcode":"2630",
    "sg:province":"NSW",
    "sg:tags":[
        "technical",
        "college",
        "trade"
    ],
    "wof:name":"Cooma College of TAFE",
    "wof:placetype":"venue"
},
  "geometry": {"coordinates":[149.12809753400001,-36.2351837158],"type":"Point"}
}