{
  "type": "Feature",
  "properties": {
    "iso:country":"AU",
    "sg:address":"29-30 Grattan St",
    "sg:city":"Prahran",
    "sg:classifiers":[
        {
            "category":"Farming",
            "subcategory":"Fish & Marine Products",
            "type":"Manufacturing & Wholesale Goods"
        }
    ],
    "sg:phone":"+61 3 9522 6300",
    "sg:postcode":"3181",
    "sg:province":"VIC",
    "sg:tags":[
        "chemical",
        "supplier"
    ],
    "wof:name":"Hilditch Pty Ltd",
    "wof:placetype":"venue"
},
  "geometry": {"coordinates":[144.99130249000001,-37.846660614],"type":"Point"}
}