{
  "type": "Feature",
  "properties": {
    "addr:full":"56 Wharf St Forster NSW 2428",
    "addr:housenumber":"56",
    "addr:postcode":"2428",
    "addr:street":"Wharf St",
    "iso:country":"AU",
    "sg:address":"56 Wharf St",
    "sg:city":"Forster",
    "sg:classifiers":[
        {
            "category":"Shopping",
            "subcategory":"Clothing, Apparel, & Fashions",
            "type":"Retail Goods"
        }
    ],
    "sg:phone":"+61 2 6555 6788",
    "sg:postcode":"2428",
    "sg:province":"NSW",
    "sg:tags":[
        "menswear"
    ],
    "wof:name":"Mensland",
    "wof:placetype":"venue"
},
  "geometry": {"coordinates":[152.51101700000001,-32.180473],"type":"Point"}
}