{
  "type": "Feature",
  "properties": {
    "iso:country":"AU",
    "sg:address":"&#034;Lynian&#034; Ellerslie North Rd",
    "sg:city":"Palinyewah",
    "sg:classifiers":[
        {
            "category":"Farming",
            "subcategory":"Berry Farm",
            "type":"Manufacturing & Wholesale Goods"
        }
    ],
    "sg:phone":"+61 3 5027 9252",
    "sg:postcode":"2648",
    "sg:province":"NSW",
    "sg:tags":[
        "fruit",
        "grower"
    ],
    "wof:name":"Robertson I & E M",
    "wof:placetype":"venue"
},
  "geometry": {"coordinates":[142.155563,-33.824749],"type":"Point"}
}