{
  "type": "Feature",
  "properties": {
    "iso:country":"AU",
    "sg:address":"32 Armstrong St",
    "sg:city":"Middle Park",
    "sg:classifiers":[
        {
            "category":"Cafe",
            "type":"Food & Drink"
        }
    ],
    "sg:phone":"+61 3 9696 1951",
    "sg:postcode":"3206",
    "sg:province":"VIC",
    "wof:name":"Cafe Loco",
    "wof:placetype":"venue"
},
  "geometry": {"coordinates":[144.964127,-37.850418],"type":"Point"}
}