{
  "type": "Feature",
  "properties": {
    "iso:country":"AU",
    "sg:address":"24 Benwerrin Ave",
    "sg:city":"Carss Park",
    "sg:classifiers":[
        {
            "category":"Building & Trades",
            "subcategory":"Construction",
            "type":"Services"
        }
    ],
    "sg:phone":"+61 412 865 322",
    "sg:postcode":"2221",
    "sg:province":"NSW",
    "sg:tags":[
        "renovation",
        "alterations",
        "extension",
        "contractor"
    ],
    "wof:name":"Buildex Building Services",
    "wof:placetype":"venue"
},
  "geometry": {"coordinates":[151.117355347,-33.9851303101],"type":"Point"}
}