{
  "type": "Feature",
  "properties": {
    "addr:full":"PO Box 11 Raymond Terrace NSW 2324",
    "addr:postcode":"2324",
    "iso:country":"AU",
    "sg:address":"PO Box 11",
    "sg:city":"Raymond Terrace",
    "sg:classifiers":[
        {
            "category":"Utilities",
            "subcategory":"Sewage",
            "type":"Services"
        }
    ],
    "sg:phone":"+61 2 4988 6825",
    "sg:postcode":"2324",
    "sg:province":"NSW",
    "sg:tags":[
        "water",
        "waste",
        "treatment"
    ],
    "wof:name":"Trilogy Solutions",
    "wof:placetype":"venue"
},
  "geometry": {"coordinates":[151.76373290999999,-32.7550582886],"type":"Point"}
}