{
  "type": "Feature",
  "properties": {
    "addr:full":"269 Tapper Rd Atwell WA 6164",
    "addr:housenumber":"269",
    "addr:postcode":"6164",
    "addr:street":"Tapper Rd",
    "iso:country":"AU",
    "sg:address":"269 Tapper Rd",
    "sg:city":"Atwell",
    "sg:classifiers":[
        {
            "category":"Health Services",
            "subcategory":"Health Practitioner",
            "type":"Services"
        }
    ],
    "sg:phone":"+61 8 9414 5363",
    "sg:postcode":"6164",
    "sg:province":"WA",
    "sg:tags":[
        "naturopath"
    ],
    "wof:name":"Dunlop Kareen",
    "wof:placetype":"venue"
},
  "geometry": {"coordinates":[115.869698,-32.151714],"type":"Point"}
}