{
  "type": "Feature",
  "properties": {
    "addr:full":"3/ 11 Industry Drv Tweed Heads South NSW 2486",
    "addr:housenumber":"/ 11",
    "addr:postcode":"2486",
    "addr:street":"Industry Drv",
    "iso:country":"AU",
    "sg:address":"3/ 11 Industry Drv",
    "sg:city":"Tweed Heads South",
    "sg:classifiers":[
        {
            "category":"Home & Garden",
            "subcategory":"Carpets & Floor Coverings",
            "type":"Retail Goods"
        }
    ],
    "sg:phone":"+61 7 5524 7524",
    "sg:postcode":"2486",
    "sg:province":"NSW",
    "sg:tags":[
        "tile",
        "wall"
    ],
    "wof:name":"Banora Tile & Stone Centre",
    "wof:placetype":"venue"
},
  "geometry": {"coordinates":[153.491744995,-28.213344574],"type":"Point"}
}