{
  "type": "Feature",
  "properties": {
    "addr:full":"6 Axminster Crs Craigmore SA 5114",
    "addr:housenumber":"6",
    "addr:postcode":"5114",
    "addr:street":"Axminster Crs",
    "iso:country":"AU",
    "sg:address":"6 Axminster Crs",
    "sg:city":"Craigmore",
    "sg:classifiers":[
        {
            "category":"Military Area",
            "subcategory":"Armory",
            "type":"Public Place"
        }
    ],
    "sg:phone":"+61 8 8254 3051",
    "sg:postcode":"5114",
    "sg:province":"SA",
    "sg:tags":[
        "belt",
        "seat"
    ],
    "wof:name":"In Car Saftey",
    "wof:placetype":"venue"
},
  "geometry": {"coordinates":[138.706176758,-34.6972618103],"type":"Point"}
}