{
  "type": "Feature",
  "properties": {
    "addr:full":"30 Maitland St Bingara NSW 2404",
    "addr:housenumber":"30",
    "addr:postcode":"2404",
    "addr:street":"Maitland St",
    "iso:country":"AU",
    "sg:address":"30 Maitland St",
    "sg:city":"Bingara",
    "sg:classifiers":[
        {
            "category":"Retail",
            "subcategory":"Funeral Services",
            "type":"Services"
        }
    ],
    "sg:phone":"+61 2 6724 7171",
    "sg:postcode":"2404",
    "sg:province":"NSW",
    "sg:tags":[
        "director"
    ],
    "wof:name":"Southern Cross Funerals",
    "wof:placetype":"venue"
},
  "geometry": {"coordinates":[150.57110595699999,-29.8671379089],"type":"Point"}
}