{
  "type": "Feature",
  "properties": {
    "addr:full":"10 Crowther St Bayswater WA 6053",
    "addr:housenumber":"10",
    "addr:postcode":"6053",
    "addr:street":"Crowther St",
    "iso:country":"AU",
    "sg:address":"10 Crowther St",
    "sg:city":"Bayswater",
    "sg:classifiers":[
        {
            "category":"Professional",
            "subcategory":"Detective & Security Services",
            "type":"Services"
        }
    ],
    "sg:phone":"+61 8 9371 5895",
    "sg:postcode":"6053",
    "sg:province":"WA",
    "sg:tags":[
        "consultant",
        "system"
    ],
    "wof:name":"D.S.C. Consolidated Services",
    "wof:placetype":"venue"
},
  "geometry": {"coordinates":[115.908126831,-31.9230804443],"type":"Point"}
}