{
  "type": "Feature",
  "properties": {
    "iso:country":"AU",
    "sg:address":"Suite 17, Northlands Centre 386 Waneroo Rd",
    "sg:city":"Westminster",
    "sg:classifiers":[
        {
            "category":"Professional",
            "subcategory":"Detective & Security Services",
            "type":"Services"
        }
    ],
    "sg:phone":"+61 8 9296 1742",
    "sg:postcode":"6061",
    "sg:province":"WA",
    "sg:tags":[
        "consultant",
        "system"
    ],
    "wof:name":"Minesite Security",
    "wof:placetype":"venue"
},
  "geometry": {"coordinates":[115.83187866199999,-31.8732395172],"type":"Point"}
}