{
  "type": "Feature",
  "properties": {
    "addr:full":"299 Elizabeth St Melbourne VIC 3000",
    "addr:housenumber":"299",
    "addr:postcode":"3000",
    "addr:street":"Elizabeth St",
    "iso:country":"AU",
    "sg:address":"299 Elizabeth St",
    "sg:city":"Melbourne",
    "sg:classifiers":[
        {
            "category":"Autos & Motor Vehicles",
            "subcategory":"Auto Supplies",
            "type":"Retail Goods"
        }
    ],
    "sg:phone":"+61 3 9602 1229",
    "sg:postcode":"3000",
    "sg:province":"VIC",
    "sg:tags":[
        "part",
        "cycles",
        "accessory"
    ],
    "wof:name":"Modak Motorcycles",
    "wof:placetype":"venue"
},
  "geometry": {"coordinates":[144.96182250999999,-37.8116531372],"type":"Point"}
}