{
  "type": "Feature",
  "properties": {
    "addr:full":"Suit 90 / City West Centre 102 Railway St West Perth WA 6005",
    "addr:housenumber":"90;102",
    "addr:postcode":"6005",
    "addr:street":"Railway St",
    "iso:country":"AU",
    "sg:address":"Suit 90 / City West Centre 102 Railway St",
    "sg:city":"West Perth",
    "sg:classifiers":[
        {
            "category":"Communications",
            "subcategory":"Film & Video Production",
            "type":"Services"
        }
    ],
    "sg:phone":"+61 8 9278 8888",
    "sg:postcode":"6005",
    "sg:province":"WA",
    "sg:tags":[
        "information",
        "recorded",
        "telephone"
    ],
    "wof:name":"On Hold Magic",
    "wof:placetype":"venue"
},
  "geometry": {"coordinates":[115.84548950200001,-31.9444484711],"type":"Point"}
}