{
  "type": "Feature",
  "properties": {
    "addr:full":"PO Box 133 Wandin North VIC 3139",
    "addr:postcode":"3139",
    "iso:country":"AU",
    "sg:address":"PO Box 133",
    "sg:city":"Wandin North",
    "sg:classifiers":[
        {
            "category":"Building & Trades",
            "subcategory":"Construction",
            "type":"Services"
        }
    ],
    "sg:phone":"+61 3 5964 3599",
    "sg:postcode":"3139",
    "sg:province":"VIC",
    "sg:tags":[
        "renovation",
        "alterations",
        "extension",
        "contractor"
    ],
    "wof:name":"AJ & J Hanssen",
    "wof:placetype":"venue"
},
  "geometry": {"coordinates":[145.46908569300001,-37.7675209045],"type":"Point"}
}