{
  "type": "Feature",
  "properties": {
    "addr:full":"1727 Botany Rd Banksmeadow NSW 2019",
    "addr:housenumber":"1727",
    "addr:postcode":"2019",
    "addr:street":"Botany Rd",
    "iso:country":"AU",
    "sg:address":"1727 Botany Rd",
    "sg:city":"Banksmeadow",
    "sg:classifiers":[
        {
            "category":"Professional",
            "type":"Services"
        }
    ],
    "sg:phone":"+61 2 8335 8458",
    "sg:postcode":"2019",
    "sg:province":"NSW",
    "sg:tags":[
        "courier"
    ],
    "wof:name":"Greyhound Freight",
    "wof:placetype":"venue"
},
  "geometry": {"coordinates":[151.20903015100001,-33.9590644836],"type":"Point"}
}