{
  "type": "Feature",
  "properties": {
    "addr:full":"Lot 48, Cutler Rd Jandakot WA 6164",
    "addr:postcode":"6164",
    "addr:street":"Cutler Rd",
    "iso:country":"AU",
    "sg:address":"Lot 48, Cutler Rd",
    "sg:city":"Jandakot",
    "sg:classifiers":[
        {
            "category":"Autos & Motor Vehicles",
            "subcategory":"Auto Supplies",
            "type":"Retail Goods"
        }
    ],
    "sg:phone":"+61 8 9414 7800",
    "sg:postcode":"6164",
    "sg:province":"WA",
    "sg:tags":[
        "transmission",
        "equipment",
        "power"
    ],
    "wof:name":"Falk Australia Pty Ltd",
    "wof:placetype":"venue"
},
  "geometry": {"coordinates":[115.867958,-32.120567],"type":"Point"}
}