{
  "type": "Feature",
  "properties": {
    "iso:country":"AU",
    "sg:address":"555 Glenferrie Rd",
    "sg:city":"Hawthorn",
    "sg:classifiers":[
        {
            "category":"Retail",
            "subcategory":"Event Space",
            "type":"Services"
        }
    ],
    "sg:phone":"+61 3 9818 1355",
    "sg:postcode":"3122",
    "sg:province":"VIC",
    "sg:tags":[
        "venue",
        "reception",
        "wedding"
    ],
    "wof:name":"Hawthorn Receptions",
    "wof:placetype":"venue"
},
  "geometry": {"coordinates":[145.03421020499999,-37.8278198242],"type":"Point"}
}