{
  "type": "Feature",
  "properties": {
    "addr:full":"22 Sovereign Ave Willetton WA 6155",
    "addr:housenumber":"22",
    "addr:postcode":"6155",
    "addr:street":"Sovereign Ave",
    "iso:country":"AU",
    "sg:address":"22 Sovereign Ave",
    "sg:city":"Willetton",
    "sg:classifiers":[
        {
            "category":"Building & Trades",
            "subcategory":"Cleaning & Sanitation",
            "type":"Services"
        }
    ],
    "sg:phone":"+61 409 903 087",
    "sg:postcode":"6155",
    "sg:province":"WA",
    "sg:tags":[
        "sweeping",
        "machine"
    ],
    "wof:name":"Bob's Sweeping",
    "wof:placetype":"venue"
},
  "geometry": {"coordinates":[115.87571,-32.06144],"type":"Point"}
}