{
  "type": "Feature",
  "properties": {
    "addr:full":"Shed 3, 109 Hertford St Sebastopol VIC 3356",
    "addr:housenumber":"3 109",
    "addr:postcode":"3356",
    "addr:street":"Hertford St",
    "iso:country":"AU",
    "sg:address":"Shed 3, 109 Hertford St",
    "sg:city":"Sebastopol",
    "sg:classifiers":[
        {
            "category":"Building & Trades",
            "subcategory":"Locksmith",
            "type":"Services"
        }
    ],
    "sg:phone":"+61 3 5336 0575",
    "sg:postcode":"3356",
    "sg:province":"VIC",
    "sg:tags":[
        "lock"
    ],
    "wof:name":"Lock U Up Mobile Locksmiths",
    "wof:placetype":"venue"
},
  "geometry": {"coordinates":[143.82681299999999,-37.587357],"type":"Point"}
}