{
  "type": "Feature",
  "properties": {
    "iso:country":"AU",
    "sg:address":"14 Peter Mills Drv",
    "sg:city":"Gilston",
    "sg:classifiers":[
        {
            "category":"Banks & Credit Unions",
            "subcategory":"Financial Services",
            "type":"Services"
        }
    ],
    "sg:phone":"+61 13 94 62",
    "sg:postcode":"4211",
    "sg:province":"QLD",
    "sg:tags":[
        "loan",
        "finance",
        "mortgage"
    ],
    "wof:name":"Mark Blake",
    "wof:placetype":"venue"
},
  "geometry": {"coordinates":[153.31419372600001,-28.0185661316],"type":"Point"}
}