{
  "type": "Feature",
  "properties": {
    "addr:full":"Suite 1/Cronulla Plaza 30 Cronulla St Cronulla NSW 2230",
    "addr:housenumber":"30",
    "addr:postcode":"2230",
    "addr:street":"Cronulla St",
    "iso:country":"AU",
    "sg:address":"Suite 1/Cronulla Plaza 30 Cronulla St",
    "sg:city":"Cronulla",
    "sg:classifiers":[
        {
            "category":"Personal",
            "subcategory":"Massage",
            "type":"Services"
        }
    ],
    "sg:phone":"+61 2 9544 0810",
    "sg:postcode":"2230",
    "sg:province":"NSW",
    "sg:tags":[
        "therapy"
    ],
    "wof:name":"Forever Young",
    "wof:placetype":"venue"
},
  "geometry": {"coordinates":[151.15293884299999,-34.0525245667],"type":"Point"}
}