{
  "type": "Feature",
  "properties": {
    "addr:full":"61 Flockton St Stafford Heights QLD 4053",
    "addr:housenumber":"61",
    "addr:postcode":"4053",
    "addr:street":"Flockton St",
    "iso:country":"AU",
    "sg:address":"61 Flockton St",
    "sg:city":"Stafford Heights",
    "sg:classifiers":[
        {
            "category":"Professional",
            "subcategory":"Secretarial Services",
            "type":"Services"
        }
    ],
    "sg:phone":"+61 7 3353 4033",
    "sg:postcode":"4053",
    "sg:province":"QLD",
    "sg:tags":[
        "typing"
    ],
    "wof:name":"Office Overload Services",
    "wof:placetype":"venue"
},
  "geometry": {"coordinates":[153.002044678,-27.3960151672],"type":"Point"}
}