{
  "type": "Feature",
  "properties": {
    "iso:country":"AU",
    "sg:address":"465 Bellarine Hwy",
    "sg:city":"Moolap",
    "sg:classifiers":[
        {
            "category":"Food & Beverages",
            "subcategory":"Groceries & Convenience Stores",
            "type":"Retail Goods"
        }
    ],
    "sg:phone":"+61 3 5250 1470",
    "sg:postcode":"3221",
    "sg:province":"VIC",
    "sg:tags":[
        "merchant",
        "egg"
    ],
    "wof:name":"Good Egg Farm",
    "wof:placetype":"venue"
},
  "geometry": {"coordinates":[144.43417400000001,-38.181644],"type":"Point"}
}