{
  "type": "Feature",
  "properties": {
    "iso:country":"AU",
    "sg:address":"21 Byre Ave",
    "sg:city":"Somerton Park",
    "sg:classifiers":[
        {
            "category":"Building & Trades",
            "subcategory":"Construction",
            "type":"Services"
        }
    ],
    "sg:phone":"+61 8 8294 5819",
    "sg:postcode":"5044",
    "sg:province":"SA",
    "sg:tags":[
        "welding"
    ],
    "wof:name":"Del-Five Industries",
    "wof:placetype":"venue"
},
  "geometry": {"coordinates":[138.524506,-34.99815],"type":"Point"}
}