{
  "type": "Feature",
  "properties": {
    "addr:full":"Logan Rd Upper Mt Gravatt QLD 4122",
    "addr:postcode":"4122",
    "addr:street":"Logan Rd Upper",
    "iso:country":"AU",
    "sg:address":"Logan Rd",
    "sg:city":"Upper Mt Gravatt",
    "sg:classifiers":[
        {
            "category":"Government",
            "subcategory":"Post Office",
            "type":"Public Place"
        }
    ],
    "sg:phone":"+61 13 13 18",
    "sg:postcode":"4122",
    "sg:province":"QLD",
    "sg:tags":[
        "postal"
    ],
    "wof:name":"Upper Mount Gravatt Post Office",
    "wof:placetype":"venue"
},
  "geometry": {"coordinates":[153.07232665999999,-27.5301265717],"type":"Point"}
}