{
  "type": "Feature",
  "properties": {
    "addr:full":"160 Pitt St Sydney NSW 2000",
    "addr:housenumber":"160",
    "addr:postcode":"2000",
    "addr:street":"Pitt St",
    "iso:country":"AU",
    "sg:address":"160 Pitt St",
    "sg:city":"Sydney",
    "sg:classifiers":[
        {
            "category":"Retail",
            "subcategory":"Laundry & Dry Cleaning",
            "type":"Services"
        }
    ],
    "sg:phone":"+61 2 9231 4396",
    "sg:postcode":"2000",
    "sg:province":"NSW",
    "sg:tags":[
        "manicurist"
    ],
    "wof:name":"Margherita Nail Artist",
    "wof:placetype":"venue"
},
  "geometry": {"coordinates":[151.2084198,-33.8693771362],"type":"Point"}
}