{
  "type": "Feature",
  "properties": {
    "addr:full":"41 Canberra St Ayr QLD 4807",
    "addr:housenumber":"41",
    "addr:postcode":"4807",
    "addr:street":"Canberra St",
    "iso:country":"AU",
    "sg:address":"41 Canberra St",
    "sg:city":"Ayr",
    "sg:classifiers":[
        {
            "category":"Sports & Exercise",
            "subcategory":"Gym",
            "type":"Entertainment"
        }
    ],
    "sg:phone":"+61 7 4783 5444",
    "sg:postcode":"4807",
    "sg:province":"QLD",
    "sg:tags":[
        "health",
        "fitness"
    ],
    "wof:name":"Adrenalin Health & Fitness Centre",
    "wof:placetype":"venue"
},
  "geometry": {"coordinates":[147.41175842300001,-19.5733642578],"type":"Point"}
}