{
  "type": "Feature",
  "properties": {
    "addr:full":"41 Doonside Rd Doonside NSW 2767",
    "addr:housenumber":"41",
    "addr:postcode":"2767",
    "addr:street":"Doonside Rd",
    "iso:country":"AU",
    "sg:address":"41 Doonside Rd",
    "sg:city":"Doonside",
    "sg:classifiers":[
        {
            "category":"Education",
            "subcategory":"School",
            "type":"Public Place"
        }
    ],
    "sg:phone":"+61 2 9622 2424",
    "sg:postcode":"2767",
    "sg:province":"NSW",
    "wof:name":"Mountain View Adventist Primary & Junior High School",
    "wof:placetype":"venue"
},
  "geometry": {"coordinates":[150.871017456,-33.7679214478],"type":"Point"}
}