{
  "type": "Feature",
  "properties": {
    "iso:country":"AU",
    "sg:address":"Fcty 163/ 248 Osborne Ave",
    "sg:city":"Clayton South",
    "sg:classifiers":[
        {
            "category":"Building & Trades",
            "subcategory":"Construction",
            "type":"Services"
        }
    ],
    "sg:phone":"+61 3 9551 3133",
    "sg:postcode":"3169",
    "sg:province":"VIC",
    "sg:tags":[
        "welding"
    ],
    "wof:name":"Ip Fabrications And Welding",
    "wof:placetype":"venue"
},
  "geometry": {"coordinates":[145.13946533199999,-37.9458389282],"type":"Point"}
}