{
  "type": "Feature",
  "properties": {
    "iso:country":"AU",
    "sg:address":"Maryvale Rd",
    "sg:city":"Morwell",
    "sg:classifiers":[
        {
            "category":"Education",
            "subcategory":"Vocational School",
            "type":"Public Place"
        }
    ],
    "sg:phone":"+61 3 5134 3466",
    "sg:postcode":"3840",
    "sg:province":"VIC",
    "sg:tags":[
        "technical",
        "college",
        "trade"
    ],
    "wof:name":"Morwell Technical",
    "wof:placetype":"venue"
},
  "geometry": {"coordinates":[146.40957641599999,-38.2302513123],"type":"Point"}
}