{
  "type": "Feature",
  "properties": {
    "iso:country":"AU",
    "sg:address":"193 Pascoe Vale Rd",
    "sg:city":"Essendon",
    "sg:classifiers":[
        {
            "category":"Health Services",
            "subcategory":"Health Practitioner",
            "type":"Services"
        }
    ],
    "sg:phone":"+61 3 9370 6652",
    "sg:postcode":"3040",
    "sg:province":"VIC",
    "sg:tags":[
        "acupuncture"
    ],
    "wof:name":"Mrs Ah Choo Teo",
    "wof:placetype":"venue"
},
  "geometry": {"coordinates":[144.92625427199999,-37.7557487488],"type":"Point"}
}