{
  "type": "Feature",
  "properties": {
    "iso:country":"AU",
    "sg:address":"371 Woolcock St",
    "sg:city":"Garbutt",
    "sg:classifiers":[
        {
            "category":"Home & Garden",
            "subcategory":"Garden Supply",
            "type":"Retail Goods"
        }
    ],
    "sg:phone":"+61 7 4775 5977",
    "sg:postcode":"4814",
    "sg:province":"QLD",
    "sg:tags":[
        "landscape"
    ],
    "wof:name":"Maccaferri Pty Ltd",
    "wof:placetype":"venue"
},
  "geometry": {"coordinates":[146.76473999999999,-19.268486],"type":"Point"}
}