{
  "type": "Feature",
  "properties": {
    "iso:country":"AU",
    "sg:address":"23 Hale St",
    "sg:city":"Botany",
    "sg:classifiers":[
        {
            "category":"Professional",
            "subcategory":"Employment Agencies",
            "type":"Services"
        }
    ],
    "sg:phone":"+61 2 9666 5100",
    "sg:postcode":"2019",
    "sg:province":"NSW",
    "sg:tags":[
        "provider",
        "internet"
    ],
    "wof:name":"Hotup City Pty Ltd",
    "wof:placetype":"venue"
},
  "geometry": {"coordinates":[151.191970825,-33.9460983276],"type":"Point"}
}