{
  "type": "Feature",
  "properties": {
    "addr:full":"80 Northgate Drv Thomastown VIC 3074",
    "addr:housenumber":"80",
    "addr:postcode":"3074",
    "addr:street":"Northgate Drv",
    "iso:country":"AU",
    "sg:address":"80 Northgate Drv",
    "sg:city":"Thomastown",
    "sg:classifiers":[
        {
            "category":"Communications",
            "subcategory":"Film & Video Production",
            "type":"Services"
        }
    ],
    "sg:phone":"+61 3 9464 5077",
    "sg:postcode":"3074",
    "sg:province":"VIC",
    "sg:tags":[
        "equipment",
        "window",
        "operating"
    ],
    "wof:name":"J P Hardware Supplies",
    "wof:placetype":"venue"
},
  "geometry": {"coordinates":[145.03468322800001,-37.688457489],"type":"Point"}
}