{
  "type": "Feature",
  "properties": {
    "addr:full":"39 Peregrine St Mourilyan QLD 4858",
    "addr:housenumber":"39",
    "addr:postcode":"4858",
    "addr:street":"Peregrine St",
    "iso:country":"AU",
    "sg:address":"39 Peregrine St",
    "sg:city":"Mourilyan",
    "sg:classifiers":[
        {
            "category":"Farming",
            "subcategory":"Farm",
            "type":"Manufacturing & Wholesale Goods"
        }
    ],
    "sg:phone":"+61 7 4063 2144",
    "sg:postcode":"4858",
    "sg:province":"QLD",
    "sg:tags":[
        "farmer"
    ],
    "wof:name":"Ferlora N & E",
    "wof:placetype":"venue"
},
  "geometry": {"coordinates":[146.045379639,-17.5830001831],"type":"Point"}
}