{
  "type": "Feature",
  "properties": {
    "addr:full":"15 Kenny Drv Duncraig WA 6023",
    "addr:housenumber":"15",
    "addr:postcode":"6023",
    "addr:street":"Kenny Drv",
    "iso:country":"AU",
    "sg:address":"15 Kenny Drv",
    "sg:city":"Duncraig",
    "sg:classifiers":[
        {
            "category":"Shopping",
            "subcategory":"Computers & Home Electronics",
            "type":"Retail Goods"
        }
    ],
    "sg:phone":"+61 8 9243 1396",
    "sg:postcode":"6023",
    "sg:province":"WA",
    "sg:tags":[
        "hardware",
        "equipment"
    ],
    "wof:name":"Ozcom Computer Services",
    "wof:placetype":"venue"
},
  "geometry": {"coordinates":[115.763221741,-31.8252983093],"type":"Point"}
}