{
  "type": "Feature",
  "properties": {
    "iso:country":"AU",
    "sg:address":"72 Ettalong Rd",
    "sg:city":"Pendle Hill",
    "sg:classifiers":[
        {
            "category":"Deli",
            "type":"Food & Drink"
        }
    ],
    "sg:phone":"+61 2 9631 2005",
    "sg:postcode":"2145",
    "sg:province":"NSW",
    "sg:tags":[
        "delicatessen"
    ],
    "wof:name":"Camilleri's Deli",
    "wof:placetype":"venue"
},
  "geometry": {"coordinates":[150.95201110799999,-33.8172531128],"type":"Point"}
}