{
  "type": "Feature",
  "properties": {
    "addr:full":"Unit 2, 501 Scarborough Beach Rd Osborne Park WA 6017",
    "addr:housenumber":"501",
    "addr:postcode":"6017",
    "addr:street":"Scarborough Beach Rd",
    "iso:country":"AU",
    "sg:address":"Unit 2, 501 Scarborough Beach Rd",
    "sg:city":"Osborne Park",
    "sg:classifiers":[
        {
            "category":"Autos & Motor Vehicles",
            "subcategory":"Auto Supplies",
            "type":"Retail Goods"
        }
    ],
    "sg:phone":"+61 8 9244 5300",
    "sg:postcode":"6017",
    "sg:province":"WA",
    "sg:tags":[
        "automotive",
        "stereo",
        "radio"
    ],
    "wof:name":"JB HI-FI",
    "wof:placetype":"venue"
},
  "geometry": {"coordinates":[115.80477142300001,-31.9045314789],"type":"Point"}
}