{
  "type": "Feature",
  "properties": {
    "addr:full":"Eastgardens 152 Bunnerong Rd Pagewood NSW 2035",
    "addr:housenumber":"152",
    "addr:postcode":"2035",
    "addr:street":"Eastgardens;Bunnerong Rd",
    "iso:country":"AU",
    "sg:address":"Eastgardens 152 Bunnerong Rd",
    "sg:city":"Pagewood",
    "sg:classifiers":[
        {
            "category":"Shopping",
            "subcategory":"Mobile Phones",
            "type":"Retail Goods"
        }
    ],
    "sg:phone":"+61 2 9344 9999",
    "sg:postcode":"2035",
    "sg:province":"NSW",
    "sg:tags":[
        "telephone",
        "accessory"
    ],
    "wof:name":"Telstra Shop",
    "wof:placetype":"venue"
},
  "geometry": {"coordinates":[151.226486206,-33.9449501038],"type":"Point"}
}