{
  "type": "Feature",
  "properties": {
    "iso:country":"AU",
    "sg:address":"Factory 1B, 1 Reeves Crt",
    "sg:city":"Breakwater",
    "sg:classifiers":[
        {
            "category":"Retail",
            "subcategory":"Auto Repair",
            "type":"Services"
        }
    ],
    "sg:phone":"+61 3 5229 2279",
    "sg:postcode":"3219",
    "sg:province":"VIC",
    "sg:tags":[
        "beater",
        "painter",
        "panel"
    ],
    "wof:name":"Gee Wiz Scratch & Dent Repairs",
    "wof:placetype":"venue"
},
  "geometry": {"coordinates":[144.37371826200001,-38.1855964661],"type":"Point"}
}