{
  "type": "Feature",
  "properties": {
    "iso:country":"AU",
    "sg:address":"165 King St",
    "sg:city":"Caboolture",
    "sg:classifiers":[
        {
            "category":"Organizations",
            "subcategory":"Community Association",
            "type":"Services"
        }
    ],
    "sg:phone":"+61 7 5495 8718",
    "sg:postcode":"4510",
    "sg:province":"QLD",
    "sg:tags":[
        "organisation",
        "family",
        "welfare"
    ],
    "wof:name":"TRACC Strengthening Families Program",
    "wof:placetype":"venue"
},
  "geometry": {"coordinates":[152.93890400000001,-27.083866],"type":"Point"}
}