{
  "type": "Feature",
  "properties": {
    "iso:country":"AU",
    "sg:address":"34 Rutland St",
    "sg:city":"Newtown",
    "sg:classifiers":[
        {
            "category":"Professional",
            "type":"Services"
        }
    ],
    "sg:phone":"+61 3 5224 1722",
    "sg:postcode":"3220",
    "sg:province":"VIC",
    "sg:tags":[
        "shop",
        "fitting"
    ],
    "wof:name":"G & L Joinery Pty Ltd",
    "wof:placetype":"venue"
},
  "geometry": {"coordinates":[144.341263,-38.160587],"type":"Point"}
}