{
  "type": "Feature",
  "properties": {
    "addr:full":"Upstairs, Cnr Knuckey & Cavenagh Sts Darwin NT 0800",
    "addr:postcode":"nt 0800",
    "iso:country":"AU",
    "sg:address":"Upstairs, Cnr Knuckey & Cavenagh Sts",
    "sg:city":"Darwin",
    "sg:classifiers":[
        {
            "category":"Shopping",
            "subcategory":"Crafts & Fabrics",
            "type":"Retail Goods"
        }
    ],
    "sg:phone":"+61 8 8942 2858",
    "sg:postcode":"0800",
    "sg:province":"NT",
    "sg:tags":[
        "supply"
    ],
    "wof:name":"Bella Life Bead & Lifestyle",
    "wof:placetype":"venue"
},
  "geometry": {"coordinates":[130.84257507300001,-12.4620265961],"type":"Point"}
}