{
  "type": "Feature",
  "properties": {
    "iso:country":"AU",
    "sg:address":"Shop 3, 13-15 Francis St",
    "sg:city":"Dee Why",
    "sg:classifiers":[
        {
            "category":"Personal",
            "subcategory":"Beauty Salon",
            "type":"Services"
        }
    ],
    "sg:phone":"+61 2 9971 8191",
    "sg:postcode":"2099",
    "sg:province":"NSW",
    "sg:tags":[
        "hairdresser"
    ],
    "wof:name":"Boomerang Hairdressing Dee Why",
    "wof:placetype":"venue"
},
  "geometry": {"coordinates":[151.283737183,-33.7533149719],"type":"Point"}
}