{
  "type": "Feature",
  "properties": {
    "addr:full":"PO Box 116 Chirnside Park VIC 3116",
    "addr:postcode":"3116",
    "iso:country":"AU",
    "sg:address":"PO Box 116",
    "sg:city":"Chirnside Park",
    "sg:classifiers":[
        {
            "category":"Banks & Credit Unions",
            "subcategory":"Bank",
            "type":"Services"
        }
    ],
    "sg:phone":"+61 418 327 842",
    "sg:postcode":"3116",
    "sg:province":"VIC",
    "sg:tags":[
        "line",
        "marking",
        "road"
    ],
    "wof:name":"Precision Roadmarking",
    "wof:placetype":"venue"
},
  "geometry": {"coordinates":[145.31483459500001,-37.7397918701],"type":"Point"}
}