{
  "type": "Feature",
  "properties": {
    "iso:country":"AU",
    "sg:address":"67 Stevedore St",
    "sg:city":"Williamstown",
    "sg:classifiers":[
        {
            "category":"Travel",
            "subcategory":"Travel Agent",
            "type":"Entertainment"
        }
    ],
    "sg:phone":"+61 3 9397 2842",
    "sg:postcode":"3016",
    "sg:province":"VIC",
    "sg:tags":[
        "consultant"
    ],
    "wof:name":"Riviera International Travel",
    "wof:placetype":"venue"
},
  "geometry": {"coordinates":[144.897506714,-37.8569793701],"type":"Point"}
}