{
  "type": "Feature",
  "properties": {
    "addr:full":"217 Margaret St Toowoomba QLD 4350",
    "addr:housenumber":"217",
    "addr:postcode":"4350",
    "addr:street":"Margaret St",
    "iso:country":"AU",
    "sg:address":"217 Margaret St",
    "sg:city":"Toowoomba",
    "sg:classifiers":[
        {
            "category":"Banks & Credit Unions",
            "subcategory":"Financial Services",
            "type":"Services"
        }
    ],
    "sg:phone":"+61 7 4632 4199",
    "sg:postcode":"4350",
    "sg:province":"QLD",
    "sg:tags":[
        "annuity",
        "rollover",
        "superannuation",
        "consultant"
    ],
    "wof:name":"Zurich Australian Insurance Ltd",
    "wof:placetype":"venue"
},
  "geometry": {"coordinates":[151.953979,-27.560957],"type":"Point"}
}