{
  "type": "Feature",
  "properties": {
    "iso:country":"AU",
    "sg:address":"Shop 144, 183 Ackland St",
    "sg:city":"St Kilda",
    "sg:classifiers":[
        {
            "category":"Shopping",
            "subcategory":"Clothing, Apparel, & Fashions",
            "type":"Retail Goods"
        }
    ],
    "sg:phone":"+61 3 9593 8129",
    "sg:postcode":"3182",
    "sg:province":"VIC",
    "sg:tags":[
        "jean"
    ],
    "wof:name":"Westco Jeans (Aust) Pty Ltd",
    "wof:placetype":"venue"
},
  "geometry": {"coordinates":[144.980392456,-37.869392395],"type":"Point"}
}