{
  "type": "Feature",
  "properties": {
    "addr:full":"Great Eastern Hwy Kalgoorlie WA 6430",
    "addr:postcode":"6430",
    "addr:street":"Eastern Hwy",
    "iso:country":"AU",
    "sg:address":"Great Eastern Hwy",
    "sg:city":"Kalgoorlie",
    "sg:classifiers":[
        {
            "category":"School Buses",
            "type":"Transportation"
        }
    ],
    "sg:phone":"+61 8 9021 4961",
    "sg:postcode":"6430",
    "sg:province":"WA",
    "sg:tags":[
        "brick"
    ],
    "wof:name":"Midland Brick",
    "wof:placetype":"venue"
},
  "geometry": {"coordinates":[121.45101928699999,-30.7655296326],"type":"Point"}
}