{
  "type": "Feature",
  "properties": {
    "iso:country":"AU",
    "sg:address":"562 Chapel St",
    "sg:city":"South Yarra",
    "sg:classifiers":[
        {
            "category":"Shopping",
            "subcategory":"Jewelry",
            "type":"Retail Goods"
        }
    ],
    "sg:phone":"+61 3 9827 2600",
    "sg:postcode":"3141",
    "sg:province":"VIC",
    "sg:tags":[
        "jeweller"
    ],
    "wof:name":"Dinosaur Designs",
    "wof:placetype":"venue"
},
  "geometry": {"coordinates":[144.995529175,-37.8407287598],"type":"Point"}
}