{
  "type": "Feature",
  "properties": {
    "addr:full":"Suite 5, 14 Druids Ave Stirling SA 5152",
    "addr:housenumber":"14",
    "addr:postcode":"5152",
    "addr:street":"Druids Ave",
    "iso:country":"AU",
    "sg:address":"Suite 5, 14 Druids Ave",
    "sg:city":"Stirling",
    "sg:classifiers":[
        {
            "category":"Health Services",
            "subcategory":"Doctor",
            "type":"Services"
        }
    ],
    "sg:phone":"+61 8 8339 3344",
    "sg:postcode":"5152",
    "sg:province":"SA",
    "sg:tags":[
        "podiatrist"
    ],
    "wof:name":"Stirling Podiatry Clinic",
    "wof:placetype":"venue"
},
  "geometry": {"coordinates":[138.71571350100001,-35.0054321289],"type":"Point"}
}