{
  "type": "Feature",
  "properties": {
    "addr:full":"14 Moloney Rd Wodonga VIC 3690",
    "addr:housenumber":"14",
    "addr:postcode":"3690",
    "addr:street":"Moloney Rd",
    "iso:country":"AU",
    "sg:address":"14 Moloney Rd",
    "sg:city":"Wodonga",
    "sg:classifiers":[
        {
            "category":"Professional",
            "subcategory":"Engineering",
            "type":"Services"
        }
    ],
    "sg:phone":"+61 2 6056 1944",
    "sg:postcode":"3690",
    "sg:province":"VIC",
    "sg:tags":[
        "engineer"
    ],
    "wof:name":"Steel Skill",
    "wof:placetype":"venue"
},
  "geometry": {"coordinates":[146.86509704599999,-36.1041603088],"type":"Point"}
}