{
  "type": "Feature",
  "properties": {
    "addr:full":"313 Vincent St Leederville WA 6007",
    "addr:housenumber":"313",
    "addr:postcode":"6007",
    "addr:street":"Vincent St",
    "iso:country":"AU",
    "sg:address":"313 Vincent St",
    "sg:city":"Leederville",
    "sg:classifiers":[
        {
            "category":"Food & Beverages",
            "subcategory":"Supermarket",
            "type":"Retail Goods"
        }
    ],
    "sg:phone":"+61 8 9444 8431",
    "sg:postcode":"6007",
    "sg:province":"WA",
    "sg:tags":[
        "grocery",
        "store"
    ],
    "wof:name":"IGA Supermarkets",
    "wof:placetype":"venue"
},
  "geometry": {"coordinates":[115.840530395,-31.9365177155],"type":"Point"}
}