{
  "type": "Feature",
  "properties": {
    "addr:full":"Shop 2, 39 Victor St Chatswood NSW 2067",
    "addr:housenumber":"shop;39",
    "addr:postcode":"2067",
    "addr:street":"Victor St",
    "iso:country":"AU",
    "sg:address":"Shop 2, 39 Victor St",
    "sg:city":"Chatswood",
    "sg:classifiers":[
        {
            "category":"Shopping",
            "subcategory":"Mobile Phones",
            "type":"Retail Goods"
        }
    ],
    "sg:phone":"+61 2 9410 3344",
    "sg:postcode":"2067",
    "sg:province":"NSW",
    "sg:tags":[
        "telephone",
        "accessory"
    ],
    "wof:name":"Target Digitals",
    "wof:placetype":"venue"
},
  "geometry": {"coordinates":[151.18261718799999,-33.7978286743],"type":"Point"}
}