{
  "type": "Feature",
  "properties": {
    "iso:country":"AU",
    "sg:address":"124 Adelaide St",
    "sg:city":"Brisbane",
    "sg:classifiers":[
        {
            "category":"Personal",
            "subcategory":"Beauty Salon",
            "type":"Services"
        }
    ],
    "sg:phone":"+61 7 3221 7650",
    "sg:postcode":"4000",
    "sg:province":"QLD",
    "sg:tags":[
        "hairdresser"
    ],
    "wof:name":"Danny Royali Hair Design",
    "wof:placetype":"venue"
},
  "geometry": {"coordinates":[153.02513122600001,-27.4681816101],"type":"Point"}
}