{
  "type": "Feature",
  "properties": {
    "addr:full":"556 Somerville Rd Sunshine VIC 3020",
    "addr:housenumber":"556",
    "addr:postcode":"3020",
    "addr:street":"Somerville Rd",
    "iso:country":"AU",
    "sg:address":"556 Somerville Rd",
    "sg:city":"Sunshine",
    "sg:classifiers":[
        {
            "category":"Wholesale",
            "subcategory":"Machinery & Supplies",
            "type":"Manufacturing & Wholesale Goods"
        }
    ],
    "sg:phone":"+61 3 9312 4999",
    "sg:postcode":"3020",
    "sg:province":"VIC",
    "sg:tags":[
        "equipment",
        "welding"
    ],
    "sg:website":"http://www.migomag.com.au",
    "wof:name":"Migomag",
    "wof:placetype":"venue"
},
  "geometry": {"coordinates":[144.827988,-37.806522],"type":"Point"}
}