{
  "type": "Feature",
  "properties": {
    "addr:full":"Camp Cable Rd Jimboomba QLD 4280",
    "addr:postcode":"4280",
    "addr:street":"Cable Rd",
    "iso:country":"AU",
    "sg:address":"Camp Cable Rd",
    "sg:city":"Jimboomba",
    "sg:classifiers":[
        {
            "category":"Retail",
            "subcategory":"Driving School",
            "type":"Services"
        }
    ],
    "sg:phone":"+61 7 5546 9775",
    "sg:postcode":"4280",
    "sg:province":"QLD",
    "wof:name":"Jimboomba Driving School",
    "wof:placetype":"venue"
},
  "geometry": {"coordinates":[153.02903699999999,-27.813055],"type":"Point"}
}