{
  "type": "Feature",
  "properties": {
    "addr:full":"Shop 14k/ 1 Bay St Ultimo NSW 2007",
    "addr:housenumber":"14k / 1",
    "addr:postcode":"2007",
    "addr:street":"Shop;Bay St",
    "iso:country":"AU",
    "sg:address":"Shop 14k/ 1 Bay St",
    "sg:city":"Ultimo",
    "sg:classifiers":[
        {
            "category":"Shopping",
            "subcategory":"Clothing, Apparel, & Fashions",
            "type":"Retail Goods"
        }
    ],
    "sg:phone":"+61 2 9280 4499",
    "sg:postcode":"2007",
    "sg:province":"NSW",
    "sg:tags":[
        "menswear"
    ],
    "wof:name":"Modus Vivendi",
    "wof:placetype":"venue"
},
  "geometry": {"coordinates":[151.194778442,-33.883228302],"type":"Point"}
}