{
  "type": "Feature",
  "properties": {
    "iso:country":"AU",
    "sg:address":"61 Arnold St",
    "sg:city":"Holland Park",
    "sg:classifiers":[
        {
            "category":"Building & Trades",
            "subcategory":"Construction",
            "type":"Services"
        }
    ],
    "sg:phone":"+61 7 3847 9000",
    "sg:postcode":"4121",
    "sg:province":"QLD",
    "sg:tags":[
        "roof"
    ],
    "wof:name":"Multi-Run Roofing",
    "wof:placetype":"venue"
},
  "geometry": {"coordinates":[153.06541442899999,-27.5168972015],"type":"Point"}
}