{
  "type": "Feature",
  "properties": {
    "addr:full":"206 Oldaker St Devonport TAS 7310",
    "addr:housenumber":"206",
    "addr:postcode":"7310",
    "addr:street":"Oldaker St",
    "iso:country":"AU",
    "sg:address":"206 Oldaker St",
    "sg:city":"Devonport",
    "sg:classifiers":[
        {
            "category":"Home & Garden",
            "subcategory":"Garden Supply",
            "type":"Retail Goods"
        }
    ],
    "sg:phone":"+61 407 436 302",
    "sg:postcode":"7310",
    "sg:province":"TAS",
    "sg:tags":[
        "turf",
        "lawn"
    ],
    "wof:name":"Graham Green",
    "wof:placetype":"venue"
},
  "geometry": {"coordinates":[146.33273315400001,-41.1730613708],"type":"Point"}
}