{
  "type": "Feature",
  "properties": {
    "addr:full":"PO Box 456 Aireys Inlet VIC 3231",
    "addr:postcode":"3231",
    "iso:country":"AU",
    "sg:address":"PO Box 456",
    "sg:city":"Aireys Inlet",
    "sg:classifiers":[
        {
            "category":"Professional",
            "subcategory":"Art Services",
            "type":"Services"
        }
    ],
    "sg:phone":"+61 3 5289 7072",
    "sg:postcode":"3231",
    "sg:province":"VIC",
    "sg:tags":[
        "graphic",
        "designer"
    ],
    "wof:name":"Munch Design",
    "wof:placetype":"venue"
},
  "geometry": {"coordinates":[144.10638427699999,-38.4604187012],"type":"Point"}
}