{
  "type": "Feature",
  "properties": {
    "iso:country":"AU",
    "sg:address":"PO Box 1117",
    "sg:city":"Lalor",
    "sg:classifiers":[
        {
            "category":"Personal",
            "subcategory":"Adult",
            "type":"Services"
        }
    ],
    "sg:phone":"+61 3 9886 4597",
    "sg:postcode":"3075",
    "sg:province":"VIC",
    "sg:tags":[
        "entertainment"
    ],
    "wof:name":"ACE Strippers",
    "wof:placetype":"venue"
},
  "geometry": {"coordinates":[145.00875854500001,-37.6659889221],"type":"Point"}
}