{
  "type": "Feature",
  "properties": {
    "addr:full":"136 Spence St Cairns QLD 4870",
    "addr:housenumber":"136",
    "addr:postcode":"4870",
    "addr:street":"Spence St",
    "iso:country":"AU",
    "sg:address":"136 Spence St",
    "sg:city":"Cairns",
    "sg:classifiers":[
        {
            "category":"Autos & Motor Vehicles",
            "subcategory":"Auto Supplies",
            "type":"Retail Goods"
        }
    ],
    "sg:phone":"+61 7 4051 0033",
    "sg:postcode":"4870",
    "sg:province":"QLD",
    "sg:tags":[
        "tyre"
    ],
    "wof:name":"Cairns Pit Stop",
    "wof:placetype":"venue"
},
  "geometry": {"coordinates":[145.75424194300001,-16.9414749146],"type":"Point"}
}