{
  "type": "Feature",
  "properties": {
    "addr:full":"137 Lansdowne St Goulburn NSW 2580",
    "addr:housenumber":"137",
    "addr:postcode":"2580",
    "addr:street":"Lansdowne St",
    "iso:country":"AU",
    "sg:address":"137 Lansdowne St",
    "sg:city":"Goulburn",
    "sg:classifiers":[
        {
            "category":"Manufacturing",
            "subcategory":"Metals",
            "type":"Manufacturing & Wholesale Goods"
        }
    ],
    "sg:phone":"+61 411 284 596",
    "sg:postcode":"2580",
    "sg:province":"NSW",
    "sg:tags":[
        "steel",
        "fabricator",
        "mfrs"
    ],
    "wof:name":"Allmac Welding",
    "wof:placetype":"venue"
},
  "geometry": {"coordinates":[149.69645690900001,-34.7655448914],"type":"Point"}
}