{
  "type": "Feature",
  "properties": {
    "addr:full":"Cnr Smithfield & Racecourse Rds Kensington VIC 3031",
    "addr:postcode":"3031",
    "iso:country":"AU",
    "sg:address":"Cnr Smithfield & Racecourse Rds",
    "sg:city":"Kensington",
    "sg:classifiers":[
        {
            "category":"Food & Beverages",
            "subcategory":"Fruits & Vegetables",
            "type":"Retail Goods"
        }
    ],
    "sg:phone":"+61 3 9372 1773",
    "sg:postcode":"3031",
    "sg:province":"VIC",
    "sg:tags":[
        "consultant",
        "catering"
    ],
    "wof:name":"Maori Club Entertainers Takumana",
    "wof:placetype":"venue"
},
  "geometry": {"coordinates":[144.92163099999999,-37.79002],"type":"Point"}
}