{
  "type": "Feature",
  "properties": {
    "addr:full":"1st Floor, 262 Latrobe Tce Geelong VIC 3220",
    "addr:housenumber":"262",
    "addr:postcode":"3220",
    "addr:street":"Latrobe Tce",
    "iso:country":"AU",
    "sg:address":"1st Floor, 262",
    "sg:city":"Latrobe Tce Geelong",
    "sg:classifiers":[
        {
            "category":"Building & Trades",
            "subcategory":"Construction",
            "type":"Services"
        }
    ],
    "sg:phone":"+61 3 5221 3097",
    "sg:postcode":"3220",
    "sg:province":"VIC",
    "sg:tags":[
        "contractor"
    ],
    "wof:name":"Building Images Pty Ltd",
    "wof:placetype":"venue"
},
  "geometry": {"coordinates":[144.35226399999999,-38.148403],"type":"Point"}
}