{
  "type": "Feature",
  "properties": {
    "addr:full":"1 Normanby St Yeppoon QLD 4703",
    "addr:housenumber":"1",
    "addr:postcode":"4703",
    "addr:street":"Normanby St",
    "iso:country":"AU",
    "sg:address":"1 Normanby St",
    "sg:city":"Yeppoon",
    "sg:classifiers":[
        {
            "category":"Shopping",
            "subcategory":"Shoes",
            "type":"Retail Goods"
        }
    ],
    "sg:phone":"+61 7 4939 1380",
    "sg:postcode":"4703",
    "sg:province":"QLD",
    "sg:tags":[
        "footwear"
    ],
    "wof:name":"Capricorn Coast Casuals",
    "wof:placetype":"venue"
},
  "geometry": {"coordinates":[150.74862670900001,-23.128944397],"type":"Point"}
}