{
  "type": "Feature",
  "properties": {
    "iso:country":"AU",
    "sg:address":"PO Box 397",
    "sg:city":"Terrigal",
    "sg:classifiers":[
        {
            "category":"Building & Trades",
            "subcategory":"Construction",
            "type":"Services"
        }
    ],
    "sg:phone":"+61 428 436 250",
    "sg:postcode":"2260",
    "sg:province":"NSW",
    "sg:tags":[
        "excavation",
        "foundation"
    ],
    "wof:name":"Credere Excavation",
    "wof:placetype":"venue"
},
  "geometry": {"coordinates":[151.44570899999999,-33.4478],"type":"Point"}
}