{
  "type": "Feature",
  "properties": {
    "addr:full":"6 The Pinnacle Worongary QLD 4213",
    "addr:housenumber":"6",
    "addr:postcode":"4213",
    "addr:street":"The",
    "iso:country":"AU",
    "sg:address":"6 The Pinnacle",
    "sg:city":"Worongary",
    "sg:classifiers":[
        {
            "category":"Manufacturing",
            "subcategory":"Apparel",
            "type":"Manufacturing & Wholesale Goods"
        }
    ],
    "sg:phone":"+61 7 5530 7899",
    "sg:postcode":"4213",
    "sg:province":"QLD",
    "sg:tags":[
        "wholesaler",
        "mfrs",
        "lady",
        "suit"
    ],
    "wof:name":"Jolie Femme Fashions Aust Pty Ltd",
    "wof:placetype":"venue"
},
  "geometry": {"coordinates":[153.336868286,-28.0467834473],"type":"Point"}
}