{
  "type": "Feature",
  "properties": {
    "addr:full":"97. Harrison Rd Dudley Park SA 5008",
    "addr:housenumber":"97",
    "addr:postcode":"5008",
    "addr:street":"Harrison Rd",
    "iso:country":"AU",
    "sg:address":"97. Harrison Rd",
    "sg:city":"Dudley Park",
    "sg:classifiers":[
        {
            "category":"Wholesale",
            "subcategory":"Construction Materials",
            "type":"Manufacturing & Wholesale Goods"
        }
    ],
    "sg:phone":"+61 8 8346 0066",
    "sg:postcode":"5008",
    "sg:province":"SA",
    "sg:tags":[
        "wholesaler",
        "equipment",
        "bathroom",
        "mfrs",
        "accessory"
    ],
    "wof:name":"Access Bathroom Ware Pty Ltd",
    "wof:placetype":"venue"
},
  "geometry": {"coordinates":[138.576019,-34.882332],"type":"Point"}
}