{
  "type": "Feature",
  "properties": {
    "addr:full":"73 Llewellyn St Merewether NSW 2291",
    "addr:housenumber":"73",
    "addr:postcode":"2291",
    "addr:street":"Llewellyn St",
    "iso:country":"AU",
    "sg:address":"73 Llewellyn St",
    "sg:city":"Merewether",
    "sg:classifiers":[
        {
            "category":"Health Services",
            "subcategory":"Health Practitioner",
            "type":"Services"
        }
    ],
    "sg:phone":"+61 412 162 003",
    "sg:postcode":"2291",
    "sg:province":"NSW",
    "sg:tags":[
        "pathologist",
        "speech"
    ],
    "wof:name":"Macquarie Speech Pathology",
    "wof:placetype":"venue"
},
  "geometry": {"coordinates":[151.749801636,-32.9398269653],"type":"Point"}
}