{
  "type": "Feature",
  "properties": {
    "iso:country":"AU",
    "sg:address":"6 Rosedale Ave",
    "sg:city":"Greenacre",
    "sg:classifiers":[
        {
            "category":"Manufacturing",
            "subcategory":"Motor Vehicles & Parts",
            "type":"Manufacturing & Wholesale Goods"
        }
    ],
    "sg:phone":"+61 2 9709 2122",
    "sg:postcode":"2190",
    "sg:province":"NSW",
    "sg:tags":[
        "replacement"
    ],
    "wof:name":"A Aabargain Auto Spares",
    "wof:placetype":"venue"
},
  "geometry": {"coordinates":[151.041336,-33.899776],"type":"Point"}
}