{
  "type": "Feature",
  "properties": {
    "addr:full":"40 B Burlington St Naval Base WA 6165",
    "addr:housenumber":"40 b",
    "addr:postcode":"6165",
    "addr:street":"Burlington St",
    "iso:country":"AU",
    "sg:address":"40 B Burlington St",
    "sg:city":"Naval Base",
    "sg:classifiers":[
        {
            "category":"Home & Garden",
            "subcategory":"Garden Supply",
            "type":"Retail Goods"
        }
    ],
    "sg:phone":"+61 8 9437 2992",
    "sg:postcode":"6165",
    "sg:province":"WA",
    "sg:tags":[
        "landscape"
    ],
    "wof:name":"AAA Garden Supplies",
    "wof:placetype":"venue"
},
  "geometry": {"coordinates":[115.781448,-32.200272],"type":"Point"}
}