{
  "type": "Feature",
  "properties": {
    "addr:full":"Mullewa Rd Kojarena WA 6532",
    "addr:postcode":"6532",
    "addr:street":"Mullewa Rd",
    "iso:country":"AU",
    "sg:address":"Mullewa Rd",
    "sg:city":"Kojarena",
    "sg:classifiers":[
        {
            "category":"Food & Beverages",
            "subcategory":"Meat & Fish",
            "type":"Retail Goods"
        }
    ],
    "sg:phone":"+61 8 9924 3234",
    "sg:postcode":"6532",
    "sg:province":"WA",
    "sg:tags":[
        "aquaculture"
    ],
    "wof:name":"Bringo Springs Marron Farm",
    "wof:placetype":"venue"
},
  "geometry": {"coordinates":[114.86366271999999,-28.723690033],"type":"Point"}
}