{
  "type": "Feature",
  "properties": {
    "addr:full":"PO Box 75 Warringah Mall NSW 2100",
    "addr:postcode":"2100",
    "iso:country":"AU",
    "sg:address":"PO Box 75",
    "sg:city":"Warringah Mall",
    "sg:classifiers":[
        {
            "category":"Shopping",
            "subcategory":"Antiques",
            "type":"Retail Goods"
        }
    ],
    "sg:phone":"+61 2 9982 6500",
    "sg:postcode":"2100",
    "sg:province":"NSW",
    "wof:name":"AA AAABAM Antiques",
    "wof:placetype":"venue"
},
  "geometry": {"coordinates":[151.266067505,-33.7677383423],"type":"Point"}
}