{
  "type": "Feature",
  "properties": {
    "iso:country":"AU",
    "sg:address":"13-19 Herbert St",
    "sg:city":"Bowen",
    "sg:classifiers":[
        {
            "category":"Autos & Motor Vehicles",
            "subcategory":"Automobile Sales",
            "type":"Retail Goods"
        }
    ],
    "sg:phone":"+61 7 4786 7600",
    "sg:postcode":"4805",
    "sg:province":"QLD",
    "sg:tags":[
        "car",
        "used"
    ],
    "wof:name":"Carmichael Ford",
    "wof:placetype":"venue"
},
  "geometry": {"coordinates":[148.24101257300001,-20.0035114288],"type":"Point"}
}