{
  "type": "Feature",
  "properties": {
    "addr:full":"28 Bangor St Archerfield QLD 4108",
    "addr:housenumber":"28",
    "addr:postcode":"4108",
    "addr:street":"Bangor St",
    "iso:country":"AU",
    "sg:address":"28 Bangor St",
    "sg:city":"Archerfield",
    "sg:phone":"+61 7 3277 8919",
    "sg:postcode":"4108",
    "sg:province":"QLD",
    "wof:name":"F.S.A. Filters",
    "wof:placetype":"venue"
},
  "geometry": {"coordinates":[153.017333984,-27.5630931854],"type":"Point"}
}