{
  "type": "Feature",
  "properties": {
    "iso:country":"AU",
    "sg:address":"Bridgman Rd",
    "sg:city":"Singleton",
    "sg:classifiers":[
        {
            "category":"Utilities",
            "subcategory":"Fuel Oil & Lpg",
            "type":"Services"
        }
    ],
    "sg:phone":"+61 2 6570 2111",
    "sg:postcode":"2330",
    "sg:province":"NSW",
    "sg:tags":[
        "merchant"
    ],
    "wof:name":"Camberwell Coal Pty Ltd",
    "wof:placetype":"venue"
},
  "geometry": {"coordinates":[151.166946,-32.558826],"type":"Point"}
}