{
  "type": "Feature",
  "properties": {
    "iso:country":"AU",
    "sg:address":"398 Sydney Rd",
    "sg:city":"Brunswick",
    "sg:classifiers":[
        {
            "category":"Casinos & Gambling",
            "type":"Entertainment"
        }
    ],
    "sg:phone":"+61 3 9380 6689",
    "sg:postcode":"3056",
    "sg:province":"VIC",
    "sg:tags":[
        "lottery",
        "agent"
    ],
    "wof:name":"Sydney Road Lucky Lotto",
    "wof:placetype":"venue"
},
  "geometry": {"coordinates":[144.96202087399999,-37.7686424255],"type":"Point"}
}