{
  "type": "Feature",
  "properties": {
    "addr:full":"39 Beaumaris Pde Highett VIC 3190",
    "addr:housenumber":"39",
    "addr:postcode":"3190",
    "addr:street":"Beaumaris Pde",
    "iso:country":"AU",
    "sg:address":"39 Beaumaris Pde",
    "sg:city":"Highett",
    "sg:classifiers":[
        {
            "category":"Personal",
            "subcategory":"Massage",
            "type":"Services"
        }
    ],
    "sg:phone":"+61 3 9555 3725",
    "sg:postcode":"3190",
    "sg:province":"VIC",
    "sg:tags":[
        "therapy"
    ],
    "wof:name":"Matthew Recchia",
    "wof:placetype":"venue"
},
  "geometry": {"coordinates":[145.035430908,-37.9512290955],"type":"Point"}
}