{
  "type": "Feature",
  "properties": {
    "addr:full":"9 Sefton Rd Thornleigh NSW 2120",
    "addr:housenumber":"9",
    "addr:postcode":"2120",
    "addr:street":"Sefton Rd",
    "iso:country":"AU",
    "sg:address":"9 Sefton Rd",
    "sg:city":"Thornleigh",
    "sg:classifiers":[
        {
            "category":"Building & Trades",
            "subcategory":"Construction",
            "type":"Services"
        }
    ],
    "sg:phone":"+61 2 9875 3088",
    "sg:postcode":"2120",
    "sg:province":"NSW",
    "sg:tags":[
        "installation",
        "air conditioning"
    ],
    "sg:website":"http://www.baratech.com.au",
    "wof:name":"Baratech Pty Ltd",
    "wof:placetype":"venue"
},
  "geometry": {"coordinates":[151.08499145499999,-33.7217407227],"type":"Point"}
}