{
  "type": "Feature",
  "properties": {
    "addr:full":"Lot 4 Farringdon Rd Kalorama VIC 3766",
    "addr:postcode":"3766",
    "addr:street":"Farringdon Rd",
    "iso:country":"AU",
    "sg:address":"Lot 4 Farringdon Rd",
    "sg:city":"Kalorama",
    "sg:classifiers":[
        {
            "category":"Retail",
            "subcategory":"Repair Shop",
            "type":"Services"
        }
    ],
    "sg:phone":"+61 3 9761 9439",
    "sg:postcode":"3766",
    "sg:province":"VIC",
    "sg:tags":[
        "leadlights"
    ],
    "wof:name":"Rajak Leadlight",
    "wof:placetype":"venue"
},
  "geometry": {"coordinates":[145.374267578,-37.8171958923],"type":"Point"}
}