{
  "type": "Feature",
  "properties": {
    "iso:country":"AU",
    "sg:address":"5 Brunsdon La",
    "sg:city":"Macksville",
    "sg:classifiers":[
        {
            "category":"Building & Trades",
            "subcategory":"Landscaping Services",
            "type":"Services"
        }
    ],
    "sg:phone":"+61 2 6568 2245",
    "sg:postcode":"2447",
    "sg:province":"NSW",
    "sg:tags":[
        "stump",
        "tree",
        "felling",
        "removal"
    ],
    "wof:name":"Nambucca/Kempsey Tree Recycling",
    "wof:placetype":"venue"
},
  "geometry": {"coordinates":[152.914246,-30.71137],"type":"Point"}
}