{
  "type": "Feature",
  "properties": {
    "iso:country":"AU",
    "sg:address":"75 High St",
    "sg:city":"Fremantle",
    "sg:classifiers":[
        {
            "category":"Shopping",
            "subcategory":"Stationery & Office Supplies",
            "type":"Retail Goods"
        }
    ],
    "sg:phone":"+61 8 9430 4565",
    "sg:postcode":"6160",
    "sg:province":"WA",
    "wof:name":"Port Stationery",
    "wof:placetype":"venue"
},
  "geometry": {"coordinates":[115.745583,-32.054893],"type":"Point"}
}