{
  "type": "Feature",
  "properties": {
    "addr:full":"Main North Rd Laura SA 5480",
    "addr:postcode":"5480",
    "addr:street":"Main North Rd",
    "iso:country":"AU",
    "sg:address":"Main North Rd",
    "sg:city":"Laura",
    "sg:classifiers":[
        {
            "category":"Professional",
            "subcategory":"Engineering",
            "type":"Services"
        }
    ],
    "sg:phone":"+61 427 201 428",
    "sg:postcode":"5480",
    "sg:province":"SA",
    "sg:tags":[
        "engineer"
    ],
    "wof:name":"Cooper Glass & Metal Works",
    "wof:placetype":"venue"
},
  "geometry": {"coordinates":[138.301544189,-33.1895523071],"type":"Point"}
}