{
  "type": "Feature",
  "properties": {
    "addr:full":"47 Minns St (East) Seaton SA 5023",
    "addr:housenumber":"47",
    "addr:postcode":"5023",
    "addr:street":"Minns St East",
    "iso:country":"AU",
    "sg:address":"47 Minns St",
    "sg:city":"(East) Seaton",
    "sg:classifiers":[
        {
            "category":"Professional",
            "subcategory":"Detective & Security Services",
            "type":"Services"
        }
    ],
    "sg:phone":"+61 8 8347 4885",
    "sg:postcode":"5023",
    "sg:province":"SA",
    "sg:tags":[
        "domestic",
        "alarm",
        "commercial",
        "burglar"
    ],
    "wof:name":"Switch Electrics",
    "wof:placetype":"venue"
},
  "geometry": {"coordinates":[138.52084350600001,-34.8877983093],"type":"Point"}
}