{
  "type": "Feature",
  "properties": {
    "addr:full":"480 Railway Pde Allawah NSW 2218",
    "addr:housenumber":"480",
    "addr:postcode":"2218",
    "addr:street":"Railway Pde",
    "iso:country":"AU",
    "sg:address":"480 Railway Pde",
    "sg:city":"Allawah",
    "sg:classifiers":[
        {
            "category":"Professional",
            "subcategory":"Accounting & Tax Preparation",
            "type":"Services"
        }
    ],
    "sg:phone":"+61 2 9553 8411",
    "sg:postcode":"2218",
    "sg:province":"NSW",
    "sg:tags":[
        "accountant",
        "auditor"
    ],
    "wof:name":"Leslie R Nelson & Co",
    "wof:placetype":"venue"
},
  "geometry": {"coordinates":[151.11300700000001,-33.96973],"type":"Point"}
}