{
  "type": "Feature",
  "properties": {
    "addr:full":"Shop F4 Sportsgirl Centre 230 Collins St Melbourne VIC 3000",
    "addr:housenumber":"230",
    "addr:postcode":"3000",
    "addr:street":"Collins St",
    "iso:country":"AU",
    "sg:address":"Shop F4 Sportsgirl Centre 230 Collins St",
    "sg:city":"Melbourne",
    "sg:classifiers":[
        {
            "category":"Shopping",
            "subcategory":"Clothing, Apparel, & Fashions",
            "type":"Retail Goods"
        }
    ],
    "sg:phone":"+61 3 9650 1211",
    "sg:postcode":"3000",
    "sg:province":"VIC",
    "sg:tags":[
        "lady",
        "wear"
    ],
    "wof:name":"Esprit (Retail) Pty Ltd",
    "wof:placetype":"venue"
},
  "geometry": {"coordinates":[144.9662323,-37.815448761],"type":"Point"}
}