{
  "type": "Feature",
  "properties": {
    "addr:full":"Brown St Chatswood NSW 2067",
    "addr:postcode":"2067",
    "addr:street":"Brown St",
    "iso:country":"AU",
    "sg:address":"Brown St",
    "sg:city":"Chatswood",
    "sg:classifiers":[
        {
            "category":"Parking",
            "type":"Transportation"
        }
    ],
    "sg:phone":"+61 2 9412 3997",
    "sg:postcode":"2067",
    "sg:province":"NSW",
    "wof:name":"Prudential Centre Carpark",
    "wof:placetype":"venue"
},
  "geometry": {"coordinates":[151.17918395999999,-33.7966690063],"type":"Point"}
}