{
  "type": "Feature",
  "properties": {
    "addr:full":"328 Koornang Rd Carnegie VIC 3163",
    "addr:housenumber":"328",
    "addr:postcode":"3163",
    "addr:street":"Koornang Rd",
    "iso:country":"AU",
    "sg:address":"328 Koornang Rd",
    "sg:city":"Carnegie",
    "sg:classifiers":[
        {
            "category":"Banks & Credit Unions",
            "subcategory":"Bank",
            "type":"Services"
        }
    ],
    "sg:phone":"+61 3 9578 3225",
    "sg:postcode":"3163",
    "sg:province":"VIC",
    "sg:tags":[
        "broker",
        "mortgage"
    ],
    "wof:name":"Mortgage Wisdom",
    "wof:placetype":"venue"
},
  "geometry": {"coordinates":[145.05511474599999,-37.9003219604],"type":"Point"}
}