{
  "type": "Feature",
  "properties": {
    "addr:full":"3 Shields La Pennant Hills NSW 2120",
    "addr:housenumber":"3",
    "addr:postcode":"2120",
    "addr:street":"Shields La",
    "iso:country":"AU",
    "sg:address":"3 Shields La",
    "sg:city":"Pennant Hills",
    "sg:classifiers":[
        {
            "category":"Education",
            "subcategory":"Kindergarten",
            "type":"Public Place"
        }
    ],
    "sg:phone":"+61 2 9484 1133",
    "sg:postcode":"2120",
    "sg:province":"NSW",
    "sg:tags":[
        "pre-schools"
    ],
    "wof:name":"Pennant Hills War Memorial Children's Centre",
    "wof:placetype":"venue"
},
  "geometry": {"coordinates":[151.072174072,-33.7359886169],"type":"Point"}
}