{
  "type": "Feature",
  "properties": {
    "addr:full":"81 Flinder St Adelaide SA 5000",
    "addr:housenumber":"81",
    "addr:postcode":"5000",
    "addr:street":"Flinder St",
    "iso:country":"AU",
    "sg:address":"81 Flinder St",
    "sg:city":"Adelaide",
    "sg:classifiers":[
        {
            "category":"Professional",
            "subcategory":"Accounting & Tax Preparation",
            "type":"Services"
        }
    ],
    "sg:phone":"+61 8 8205 6200",
    "sg:postcode":"5000",
    "sg:province":"SA",
    "sg:tags":[
        "accountant",
        "auditor"
    ],
    "wof:name":"Gregg Peter C",
    "wof:placetype":"venue"
},
  "geometry": {"coordinates":[138.60336303700001,-34.9268493652],"type":"Point"}
}