{
  "type": "Feature",
  "properties": {
    "iso:country":"AU",
    "sg:address":"425 Hall Rd",
    "sg:city":"Skye",
    "sg:classifiers":[
        {
            "category":"Building & Trades",
            "subcategory":"Construction",
            "type":"Services"
        }
    ],
    "sg:phone":"+61 3 9782 2707",
    "sg:postcode":"3977",
    "sg:province":"VIC",
    "sg:tags":[
        "plasterboard",
        "plasterer",
        "fixer"
    ],
    "wof:name":"C & J Rendell Linings Pty Ltd",
    "wof:placetype":"venue"
},
  "geometry": {"coordinates":[145.22056579599999,-38.105381012],"type":"Point"}
}