{
  "type": "Feature",
  "properties": {
    "addr:full":"142 Blair St Bunbury WA 6230",
    "addr:housenumber":"142",
    "addr:postcode":"6230",
    "addr:street":"Blair St",
    "iso:country":"AU",
    "sg:address":"142 Blair St",
    "sg:city":"Bunbury",
    "sg:classifiers":[
        {
            "category":"Train Station",
            "subcategory":"Light Rail",
            "type":"Transportation"
        }
    ],
    "sg:phone":"+61 8 9791 3600",
    "sg:postcode":"6230",
    "sg:province":"WA",
    "sg:tags":[
        "equipment",
        "energy",
        "solar"
    ],
    "wof:name":"Bathroom Decor And Tiles",
    "wof:placetype":"venue"
},
  "geometry": {"coordinates":[115.645309,-33.335495],"type":"Point"}
}