{
  "type": "Feature",
  "properties": {
    "addr:full":"1 Collins St Corrimal NSW 2518",
    "addr:housenumber":"1",
    "addr:postcode":"2518",
    "addr:street":"Collins St",
    "iso:country":"AU",
    "sg:address":"1 Collins St",
    "sg:city":"Corrimal",
    "sg:classifiers":[
        {
            "category":"Utilities",
            "subcategory":"Recycling",
            "type":"Services"
        }
    ],
    "sg:phone":"+61 2 4283 8366",
    "sg:postcode":"2518",
    "sg:province":"NSW",
    "wof:name":"Coasties Big Shed",
    "wof:placetype":"venue"
},
  "geometry": {"coordinates":[150.906387,-34.370876],"type":"Point"}
}