{
  "type": "Feature",
  "properties": {
    "addr:full":"47 Churchill St Childers QLD 4660",
    "addr:housenumber":"47",
    "addr:postcode":"4660",
    "addr:street":"Churchill St",
    "iso:country":"AU",
    "sg:address":"47 Churchill St",
    "sg:city":"Childers",
    "sg:classifiers":[
        {
            "category":"Utilities",
            "subcategory":"Water",
            "type":"Services"
        }
    ],
    "sg:phone":"+61 7 4126 2722",
    "sg:postcode":"4660",
    "sg:province":"QLD",
    "sg:tags":[
        "cartage"
    ],
    "wof:name":"AAA Water Cartage",
    "wof:placetype":"venue"
},
  "geometry": {"coordinates":[152.28077697800001,-25.2357826233],"type":"Point"}
}