{
  "type": "Feature",
  "properties": {
    "addr:full":"32 Percy St Mordialloc VIC 3195",
    "addr:housenumber":"32",
    "addr:postcode":"3195",
    "addr:street":"Percy St",
    "iso:country":"AU",
    "sg:address":"32 Percy St",
    "sg:city":"Mordialloc",
    "sg:classifiers":[
        {
            "category":"Building & Trades",
            "subcategory":"Cleaning & Sanitation",
            "type":"Services"
        }
    ],
    "sg:phone":"+61 3 9580 9499",
    "sg:postcode":"3195",
    "sg:province":"VIC",
    "sg:tags":[
        "asbestos",
        "treatment",
        "removal"
    ],
    "wof:name":"M G R Industries",
    "wof:placetype":"venue"
},
  "geometry": {"coordinates":[145.09548950199999,-38.0069160461],"type":"Point"}
}