{
  "type": "Feature",
  "properties": {
    "iso:country":"AU",
    "sg:address":"150a Beatty Rd",
    "sg:city":"Archerfield",
    "sg:classifiers":[
        {
            "category":"Wholesale",
            "subcategory":"Machinery & Supplies",
            "type":"Manufacturing & Wholesale Goods"
        }
    ],
    "sg:phone":"+61 7 3216 6963",
    "sg:postcode":"4108",
    "sg:province":"QLD",
    "sg:tags":[
        "equipment",
        "pneumatic"
    ],
    "sg:website":"http://www.pneumaticsolutions.com.au",
    "wof:name":"Pneumactic Solutions Australia",
    "wof:placetype":"venue"
},
  "geometry": {"coordinates":[153.016159058,-27.5626792908],"type":"Point"}
}