{
  "type": "Feature",
  "properties": {
    "addr:full":"1 Partridge St Glenelg SA 5045",
    "addr:housenumber":"1",
    "addr:postcode":"5045",
    "addr:street":"Partridge St",
    "iso:country":"AU",
    "sg:address":"1 Partridge St",
    "sg:city":"Glenelg",
    "sg:classifiers":[
        {
            "category":"Personal",
            "subcategory":"Beauty Salon",
            "type":"Services"
        }
    ],
    "sg:phone":"+61 8 8295 6426",
    "sg:postcode":"5045",
    "sg:province":"SA",
    "sg:tags":[
        "hairdresser"
    ],
    "wof:name":"Sublime Edge",
    "wof:placetype":"venue"
},
  "geometry": {"coordinates":[138.51759300000001,-34.980339],"type":"Point"}
}