{
  "type": "Feature",
  "properties": {
    "addr:full":"69 Mosman St Charters Towers QLD 4820",
    "addr:housenumber":"69",
    "addr:postcode":"4820",
    "addr:street":"Mosman St",
    "iso:country":"AU",
    "sg:address":"69 Mosman St",
    "sg:city":"Charters Towers",
    "sg:classifiers":[
        {
            "category":"Travel",
            "subcategory":"Hotels & Motels",
            "type":"Entertainment"
        }
    ],
    "sg:phone":"+61 7 4787 1605",
    "sg:postcode":"4820",
    "sg:province":"QLD",
    "wof:name":"Rix Hotel Motel",
    "wof:placetype":"venue"
},
  "geometry": {"coordinates":[146.25762900000001,-20.074745],"type":"Point"}
}