{
  "type": "Feature",
  "properties": {
    "iso:country":"AU",
    "sg:address":"39 Grant St",
    "sg:city":"Cottesloe",
    "sg:classifiers":[
        {
            "category":"Farming",
            "subcategory":"Farm",
            "type":"Manufacturing & Wholesale Goods"
        }
    ],
    "sg:phone":"+61 8 9284 2443",
    "sg:postcode":"6011",
    "sg:province":"WA",
    "sg:tags":[
        "farmer"
    ],
    "wof:name":"Kuehlmann K & V",
    "wof:placetype":"venue"
},
  "geometry": {"coordinates":[115.75823211700001,-31.9866142273],"type":"Point"}
}