{
  "type": "Feature",
  "properties": {
    "addr:full":"Main St Tolga QLD 4882",
    "addr:postcode":"4882",
    "addr:street":"Main St",
    "iso:country":"AU",
    "sg:address":"Main St",
    "sg:city":"Tolga",
    "sg:classifiers":[
        {
            "category":"Retail",
            "subcategory":"Car Wash",
            "type":"Services"
        }
    ],
    "sg:phone":"+61 7 4095 4338",
    "sg:postcode":"4882",
    "sg:province":"QLD",
    "sg:tags":[
        "merchant",
        "oil",
        "refiner"
    ],
    "wof:name":"Ampol Petroleum (Qld) Pty Ltd",
    "wof:placetype":"venue"
},
  "geometry": {"coordinates":[145.47398376500001,-17.2227649689],"type":"Point"}
}