{
  "type": "Feature",
  "properties": {
    "addr:full":"5 Leigh Crt Lilydale VIC 3140",
    "addr:housenumber":"5",
    "addr:postcode":"3140",
    "addr:street":"Leigh Crt",
    "iso:country":"AU",
    "sg:address":"5 Leigh Crt",
    "sg:city":"Lilydale",
    "sg:classifiers":[
        {
            "category":"Retail",
            "subcategory":"Repair Shop",
            "type":"Services"
        }
    ],
    "sg:phone":"+61 413 145 862",
    "sg:postcode":"3140",
    "sg:province":"VIC",
    "sg:tags":[
        "upholsterer"
    ],
    "wof:name":"Exclusive Upholstery Design",
    "wof:placetype":"venue"
},
  "geometry": {"coordinates":[145.14768981899999,-37.6878318787],"type":"Point"}
}