{
  "type": "Feature",
  "properties": {
    "addr:full":"Royal Brisbane Hospital, Herston Rd Herston QLD 4006",
    "addr:postcode":"4006",
    "addr:street":"Herston Rd",
    "iso:country":"AU",
    "sg:address":"Royal Brisbane Hospital, Herston Rd",
    "sg:city":"Herston",
    "sg:classifiers":[
        {
            "category":"Health Services",
            "subcategory":"Doctor",
            "type":"Services"
        }
    ],
    "sg:phone":"+61 7 3636 8346",
    "sg:postcode":"4006",
    "sg:province":"QLD",
    "sg:tags":[
        "medical",
        "practitioner"
    ],
    "wof:name":"Royal Brisbane Hospital & Royal Women's Hospital & Health Service Districts",
    "wof:placetype":"venue"
},
  "geometry": {"coordinates":[153.02609252900001,-27.4496421814],"type":"Point"}
}