{
  "type": "Feature",
  "properties": {
    "iso:country":"AU",
    "sg:address":"18 Paterson St",
    "sg:city":"Carlingford",
    "sg:classifiers":[
        {
            "category":"Travel",
            "subcategory":"Travel Agent",
            "type":"Entertainment"
        }
    ],
    "sg:phone":"+61 2 9872 1688",
    "sg:postcode":"2118",
    "sg:province":"NSW",
    "sg:tags":[
        "consultant"
    ],
    "wof:name":"Selective Tours Pty Ltd",
    "wof:placetype":"venue"
},
  "geometry": {"coordinates":[151.055984497,-33.7720222473],"type":"Point"}
}