{
  "type": "Feature",
  "properties": {
    "addr:full":"Lot 5 Marina Crs Urunga NSW 2455",
    "addr:housenumber":"5",
    "addr:postcode":"2455",
    "addr:street":"Marina Crs",
    "iso:country":"AU",
    "sg:address":"Lot 5 Marina Crs",
    "sg:city":"Urunga",
    "sg:classifiers":[
        {
            "category":"Retail",
            "subcategory":"Auto Repair",
            "type":"Services"
        }
    ],
    "sg:phone":"+61 2 6655 6259",
    "sg:postcode":"2455",
    "sg:province":"NSW",
    "sg:tags":[
        "repairer",
        "motor",
        "engineer"
    ],
    "wof:name":"Navin Auto Repairs",
    "wof:placetype":"venue"
},
  "geometry": {"coordinates":[153.01473999999999,-30.497259],"type":"Point"}
}