{
  "type": "Feature",
  "properties": {
    "iso:country":"AU",
    "sg:address":"2229 Castlereagh Rd",
    "sg:city":"Penrith",
    "sg:classifiers":[
        {
            "category":"Education",
            "subcategory":"Special Training",
            "type":"Public Place"
        }
    ],
    "sg:phone":"+61 2 4721 0099",
    "sg:postcode":"2750",
    "sg:province":"NSW",
    "sg:tags":[
        "development"
    ],
    "wof:name":"Skillswest Training Company Pty Ltd",
    "wof:placetype":"venue"
},
  "geometry": {"coordinates":[150.68885803200001,-33.7486877441],"type":"Point"}
}