{
  "type": "Feature",
  "properties": {
    "iso:country":"AU",
    "sg:address":"614 Elgar Rd",
    "sg:city":"Box Hill",
    "sg:classifiers":[
        {
            "category":"Social Services",
            "subcategory":"Retirement Home",
            "type":"Services"
        }
    ],
    "sg:phone":"+61 3 9898 8566",
    "sg:postcode":"3128",
    "sg:province":"VIC",
    "sg:tags":[
        "accommodation",
        "special"
    ],
    "wof:name":"Tinagill Aged Care Home",
    "wof:placetype":"venue"
},
  "geometry": {"coordinates":[145.11502075199999,-37.8168716431],"type":"Point"}
}