{
  "type": "Feature",
  "properties": {
    "addr:full":"41 Alberton Rd Alberton QLD 4207",
    "addr:housenumber":"41",
    "addr:postcode":"4207",
    "addr:street":"Alberton Rd",
    "iso:country":"AU",
    "sg:address":"41 Alberton Rd",
    "sg:city":"Alberton",
    "sg:classifiers":[
        {
            "category":"Professional",
            "type":"Services"
        }
    ],
    "sg:phone":"+61 7 3807 7611",
    "sg:postcode":"4207",
    "sg:province":"QLD",
    "sg:tags":[
        "coating",
        "powder"
    ],
    "wof:name":"Willwin Powder Coating",
    "wof:placetype":"venue"
},
  "geometry": {"coordinates":[153.257369995,-27.7144374847],"type":"Point"}
}