{
  "type": "Feature",
  "properties": {
    "iso:country":"AU",
    "sg:address":"Lot 16 Nowra Rd",
    "sg:city":"Fitzroy Falls",
    "sg:classifiers":[
        {
            "category":"Arts & Performance",
            "subcategory":"Art Gallery",
            "type":"Entertainment"
        }
    ],
    "sg:phone":"+61 2 4887 7015",
    "sg:postcode":"2577",
    "sg:province":"NSW",
    "wof:name":"Wildwood Gallery",
    "wof:placetype":"venue"
},
  "geometry": {"coordinates":[150.47999572800001,-34.6450538635],"type":"Point"}
}