{
  "type": "Feature",
  "properties": {
    "addr:full":"112 Manilla St Manilla NSW 2346",
    "addr:housenumber":"112",
    "addr:postcode":"2346",
    "addr:street":"Manilla St",
    "iso:country":"AU",
    "sg:address":"112 Manilla St",
    "sg:city":"Manilla",
    "sg:classifiers":[
        {
            "category":"Shopping",
            "type":"Retail Goods"
        }
    ],
    "sg:phone":"+61 2 6785 1406",
    "sg:postcode":"2346",
    "sg:province":"NSW",
    "sg:tags":[
        "agent",
        "stock"
    ],
    "wof:name":"Garry Kirk Pty Ltd",
    "wof:placetype":"venue"
},
  "geometry": {"coordinates":[150.72038269000001,-30.7482814789],"type":"Point"}
}