{
  "type": "Feature",
  "properties": {
    "iso:country":"AU",
    "sg:address":"Hillman St",
    "sg:city":"Darkan",
    "sg:classifiers":[
        {
            "category":"Farming",
            "subcategory":"Farm & Veterinary Services",
            "type":"Manufacturing & Wholesale Goods"
        }
    ],
    "sg:phone":"+61 8 9736 1077",
    "sg:postcode":"6392",
    "sg:province":"WA",
    "sg:tags":[
        "shearing",
        "contractor"
    ],
    "wof:name":"Spiers D R & C A",
    "wof:placetype":"venue"
},
  "geometry": {"coordinates":[116.740669251,-33.3377113342],"type":"Point"}
}