{
  "type": "Feature",
  "properties": {
    "addr:full":"7 West St Paddington NSW 2021",
    "addr:housenumber":"7",
    "addr:postcode":"2021",
    "addr:street":"West St",
    "iso:country":"AU",
    "sg:address":"7 West St",
    "sg:city":"Paddington",
    "sg:classifiers":[
        {
            "category":"Health Services",
            "subcategory":"Health Practitioner",
            "type":"Services"
        }
    ],
    "sg:phone":"+61 2 9331 4859",
    "sg:postcode":"2021",
    "sg:province":"NSW",
    "sg:tags":[
        "homoeopath"
    ],
    "wof:name":"Lander Annie",
    "wof:placetype":"venue"
},
  "geometry": {"coordinates":[151.220626831,-33.8819351196],"type":"Point"}
}