{
  "type": "Feature",
  "properties": {
    "addr:full":"SGIO Building 45 Cathedral Ave Geraldton WA 6530",
    "addr:housenumber":"45",
    "addr:postcode":"6530",
    "addr:street":"Cathedral Ave",
    "iso:country":"AU",
    "sg:address":"SGIO Building 45 Cathedral Ave",
    "sg:city":"Geraldton",
    "sg:classifiers":[
        {
            "category":"Professional",
            "subcategory":"Business Services",
            "type":"Services"
        }
    ],
    "sg:phone":"+61 8 9921 0702",
    "sg:postcode":"6530",
    "sg:province":"WA",
    "sg:tags":[
        "broker"
    ],
    "wof:name":"Mid West Industry Development Unit",
    "wof:placetype":"venue"
},
  "geometry": {"coordinates":[114.610092163,-28.7750778198],"type":"Point"}
}