{
  "type": "Feature",
  "properties": {
    "iso:country":"AU",
    "sg:address":"11 Manning St",
    "sg:city":"Kingswood",
    "sg:classifiers":[
        {
            "category":"Cafe",
            "type":"Food & Drink"
        }
    ],
    "sg:phone":"+61 2 4736 2031",
    "sg:postcode":"2747",
    "sg:province":"NSW",
    "wof:name":"Allrich Food Bar",
    "wof:placetype":"venue"
},
  "geometry": {"coordinates":[150.725631714,-33.764251709],"type":"Point"}
}