{
  "type": "Feature",
  "properties": {
    "addr:full":"Suite 6 Level 12 20 Collins St Melbourne VIC 3000",
    "addr:housenumber":"20",
    "addr:postcode":"3000",
    "addr:street":"Collins St",
    "iso:country":"AU",
    "sg:address":"Suite 6 Level 12 20 Collins St",
    "sg:city":"Melbourne",
    "sg:classifiers":[
        {
            "category":"Travel",
            "subcategory":"Travel Agent",
            "type":"Entertainment"
        }
    ],
    "sg:phone":"+61 3 9663 4022",
    "sg:postcode":"3000",
    "sg:province":"VIC",
    "sg:tags":[
        "consultant"
    ],
    "wof:name":"Mekina & Associates",
    "wof:placetype":"venue"
},
  "geometry": {"coordinates":[144.973190308,-37.8134040833],"type":"Point"}
}