{
  "type": "Feature",
  "properties": {
    "iso:country":"AU",
    "sg:address":"2 Alhambra Ave",
    "sg:city":"Cardiff",
    "sg:classifiers":[
        {
            "category":"Building & Trades",
            "subcategory":"Construction",
            "type":"Services"
        }
    ],
    "sg:phone":"+61 1800 656 442",
    "sg:postcode":"2285",
    "sg:province":"NSW",
    "sg:tags":[
        "contractor"
    ],
    "wof:name":"Contour Building + Construction",
    "wof:placetype":"venue"
},
  "geometry": {"coordinates":[151.65350341800001,-32.9482955933],"type":"Point"}
}