{
  "type": "Feature",
  "properties": {
    "iso:country":"AU",
    "sg:address":"Cnr Lake Ave & Five Island Rd",
    "sg:city":"Cringila",
    "sg:classifiers":[
        {
            "category":"Fast Food",
            "type":"Food & Drink"
        }
    ],
    "sg:phone":"+61 2 4275 1670",
    "sg:postcode":"2502",
    "sg:province":"NSW",
    "sg:tags":[
        "away",
        "take"
    ],
    "wof:name":"Cringila Kebabs",
    "wof:placetype":"venue"
},
  "geometry": {"coordinates":[150.872543,-34.466866],"type":"Point"}
}