{
  "type": "Feature",
  "properties": {
    "addr:full":"Mahoneys Rd Forest Hill VIC 3131",
    "addr:postcode":"3131",
    "addr:street":"Mahoneys Rd",
    "iso:country":"AU",
    "sg:address":"Mahoneys Rd",
    "sg:city":"Forest Hill",
    "sg:classifiers":[
        {
            "category":"Retail",
            "subcategory":"Event Space",
            "type":"Services"
        }
    ],
    "sg:phone":"+61 3 9941 3184",
    "sg:postcode":"3131",
    "sg:province":"VIC",
    "sg:tags":[
        "function",
        "organiser"
    ],
    "wof:name":"Nunawading Social Club",
    "wof:placetype":"venue"
},
  "geometry": {"coordinates":[145.165084839,-37.8423347473],"type":"Point"}
}