{
  "type": "Feature",
  "properties": {
    "addr:full":"328 Alice St Maryborough QLD 4650",
    "addr:housenumber":"328",
    "addr:postcode":"4650",
    "addr:street":"Alice St",
    "iso:country":"AU",
    "sg:address":"328 Alice St",
    "sg:city":"Maryborough",
    "sg:classifiers":[
        {
            "category":"Professional",
            "subcategory":"Engineering",
            "type":"Services"
        }
    ],
    "sg:phone":"+61 7 4121 4344",
    "sg:postcode":"4650",
    "sg:province":"QLD",
    "sg:tags":[
        "consulting",
        "engineer"
    ],
    "wof:name":"Holmes McLeod Consulting Engineers Pty Ltd",
    "wof:placetype":"venue"
},
  "geometry": {"coordinates":[152.69607500000001,-25.538282],"type":"Point"}
}