{
  "type": "Feature",
  "properties": {
    "addr:full":"Level 21, Allendale Square 77 St Georges Tce Perth WA 6000",
    "addr:housenumber":"77",
    "addr:postcode":"6000",
    "addr:street":"Allendale;St Georges Tce",
    "iso:country":"AU",
    "sg:address":"Level 21, Allendale Square 77 St",
    "sg:city":"Georges Tce Perth",
    "sg:classifiers":[
        {
            "category":"Professional",
            "subcategory":"Computer Services",
            "type":"Services"
        }
    ],
    "sg:phone":"+61 8 9325 1900",
    "sg:postcode":"6000",
    "sg:province":"WA",
    "sg:tags":[
        "information"
    ],
    "wof:name":"Watermark Patent & Trade Mark Attorneys",
    "wof:placetype":"venue"
},
  "geometry": {"coordinates":[115.85836792000001,-31.9554367065],"type":"Point"}
}