{
  "type": "Feature",
  "properties": {
    "addr:full":"10 Haverbrack Crs Churchill VIC 3842",
    "addr:housenumber":"10",
    "addr:postcode":"3842",
    "addr:street":"Haverbrack Crs",
    "iso:country":"AU",
    "sg:address":"10 Haverbrack Crs",
    "sg:city":"Churchill",
    "sg:classifiers":[
        {
            "category":"Building & Trades",
            "subcategory":"Construction",
            "type":"Services"
        }
    ],
    "sg:phone":"+61 3 5122 2245",
    "sg:postcode":"3842",
    "sg:province":"VIC",
    "sg:tags":[
        "contractor"
    ],
    "wof:name":"Veldman's Building Service",
    "wof:placetype":"venue"
},
  "geometry": {"coordinates":[146.42181396500001,-38.3153915405],"type":"Point"}
}