{
  "type": "Feature",
  "properties": {
    "addr:full":"13 Kendall St Gloucester NSW 2422",
    "addr:housenumber":"13",
    "addr:postcode":"2422",
    "addr:street":"Kendall St",
    "iso:country":"AU",
    "sg:address":"13 Kendall St",
    "sg:city":"Gloucester",
    "sg:classifiers":[
        {
            "category":"Retail",
            "subcategory":"Auto Repair",
            "type":"Services"
        }
    ],
    "sg:phone":"+61 2 6558 2157",
    "sg:postcode":"2422",
    "sg:province":"NSW",
    "sg:tags":[
        "beater",
        "painter",
        "panel"
    ],
    "wof:name":"Stubs Panel & Paint",
    "wof:placetype":"venue"
},
  "geometry": {"coordinates":[151.955704,-32.027775],"type":"Point"}
}