{
  "type": "Feature",
  "properties": {
    "iso:country":"AU",
    "sg:address":"51 Clarendon St",
    "sg:city":"Maryborough",
    "sg:classifiers":[
        {
            "category":"Retail",
            "subcategory":"Auto Repair",
            "type":"Services"
        }
    ],
    "sg:phone":"+61 419 116 014",
    "sg:postcode":"3465",
    "sg:province":"VIC",
    "sg:tags":[
        "electrical"
    ],
    "wof:name":"Smartlec Automotive Pty Ltd",
    "wof:placetype":"venue"
},
  "geometry": {"coordinates":[143.735107422,-37.0475845337],"type":"Point"}
}