{
  "type": "Feature",
  "properties": {
    "addr:full":"22 Delmont St Werribee VIC 3030",
    "addr:housenumber":"22",
    "addr:postcode":"3030",
    "addr:street":"Delmont St",
    "iso:country":"AU",
    "sg:address":"22 Delmont St",
    "sg:city":"Werribee",
    "sg:classifiers":[
        {
            "category":"Professional",
            "subcategory":"Computer Services",
            "type":"Services"
        }
    ],
    "sg:phone":"+61 1300 763 384",
    "sg:postcode":"3030",
    "sg:province":"VIC",
    "sg:tags":[
        "consultant",
        "system"
    ],
    "wof:name":"Alink Network Services Pty Ltd",
    "wof:placetype":"venue"
},
  "geometry": {"coordinates":[144.63949600000001,-37.912399],"type":"Point"}
}