{
  "type": "Feature",
  "properties": {
    "iso:country":"AU",
    "sg:address":"6 Grayling St",
    "sg:city":"Belmont",
    "sg:classifiers":[
        {
            "category":"Retail",
            "subcategory":"Auto Repair",
            "type":"Services"
        }
    ],
    "sg:phone":"+61 3 5241 3177",
    "sg:postcode":"3216",
    "sg:province":"VIC",
    "sg:tags":[
        "repairer",
        "motor",
        "engineer"
    ],
    "wof:name":"Lister Automotive",
    "wof:placetype":"venue"
},
  "geometry": {"coordinates":[144.35348510700001,-38.1835212708],"type":"Point"}
}