{
  "type": "Feature",
  "properties": {
    "iso:country":"AU",
    "sg:address":"467 Morphett St",
    "sg:city":"Adelaide",
    "sg:classifiers":[
        {
            "category":"Building & Trades",
            "subcategory":"Locksmith",
            "type":"Services"
        }
    ],
    "sg:phone":"+61 8 8231 7825",
    "sg:postcode":"5000",
    "sg:province":"SA",
    "sg:tags":[
        "lock"
    ],
    "wof:name":"Mobile Locksmiths",
    "wof:placetype":"venue"
},
  "geometry": {"coordinates":[138.59422302199999,-34.9354667664],"type":"Point"}
}