{
  "type": "Feature",
  "properties": {
    "addr:full":"724 Pittwater Rd Brookvale NSW 2100",
    "addr:housenumber":"724",
    "addr:postcode":"2100",
    "addr:street":"Pittwater Rd",
    "iso:country":"AU",
    "sg:address":"724 Pittwater Rd",
    "sg:city":"Brookvale",
    "sg:classifiers":[
        {
            "category":"Home & Garden",
            "subcategory":"Furniture",
            "type":"Retail Goods"
        }
    ],
    "sg:phone":"+61 2 9905 9055",
    "sg:postcode":"2100",
    "sg:province":"NSW",
    "sg:tags":[
        "outdoor"
    ],
    "wof:name":"The Teak Warehouse",
    "wof:placetype":"venue"
},
  "geometry": {"coordinates":[151.273147583,-33.7612571716],"type":"Point"}
}