{
  "type": "Feature",
  "properties": {
    "addr:full":"17 Manning St South Brisbane QLD 4101",
    "addr:housenumber":"17",
    "addr:postcode":"4101",
    "addr:street":"Manning St",
    "iso:country":"AU",
    "sg:address":"17 Manning St",
    "sg:city":"South Brisbane",
    "sg:classifiers":[
        {
            "category":"Professional",
            "subcategory":"Computer Services",
            "type":"Services"
        }
    ],
    "sg:phone":"+61 7 3844 0879",
    "sg:postcode":"4101",
    "sg:province":"QLD",
    "sg:tags":[
        "consultant",
        "system"
    ],
    "sg:website":"http://www.rcity.com.au",
    "wof:name":"Rivercity Solutions",
    "wof:placetype":"venue"
},
  "geometry": {"coordinates":[153.01449585,-27.4761867523],"type":"Point"}
}