{
  "type": "Feature",
  "properties": {
    "addr:full":"56 George St Parramatta NSW 2150",
    "addr:housenumber":"56",
    "addr:postcode":"2150",
    "addr:street":"George St",
    "iso:country":"AU",
    "sg:address":"56 George St",
    "sg:city":"Parramatta",
    "sg:classifiers":[
        {
            "category":"Shopping",
            "subcategory":"Discount & Variety Stores",
            "type":"Retail Goods"
        }
    ],
    "sg:phone":"+61 2 9633 5568",
    "sg:postcode":"2150",
    "sg:province":"NSW",
    "sg:tags":[
        "shop",
        "adult"
    ],
    "wof:name":"Venus Adult Shop",
    "wof:placetype":"venue"
},
  "geometry": {"coordinates":[151.01942443900001,-33.8317146301],"type":"Point"}
}