{
  "type": "Feature",
  "properties": {
    "addr:full":"720- 722 Woodville Rd Guildford NSW 2161",
    "addr:housenumber":"720 722",
    "addr:postcode":"2161",
    "addr:street":"Woodville Rd",
    "iso:country":"AU",
    "sg:address":"720- 722 Woodville Rd",
    "sg:city":"Guildford",
    "sg:classifiers":[
        {
            "category":"Home & Garden",
            "subcategory":"Carpets & Floor Coverings",
            "type":"Retail Goods"
        }
    ],
    "sg:phone":"+61 2 9723 6000",
    "sg:postcode":"2161",
    "sg:province":"NSW",
    "sg:tags":[
        "tile",
        "wall"
    ],
    "wof:name":"Saba Industries",
    "wof:placetype":"venue"
},
  "geometry": {"coordinates":[150.99046325699999,-33.8639678955],"type":"Point"}
}