{
  "type": "Feature",
  "properties": {
    "addr:full":"419 High St Prahran VIC 3181",
    "addr:housenumber":"419",
    "addr:postcode":"3181",
    "addr:street":"High St",
    "iso:country":"AU",
    "sg:address":"419 High St",
    "sg:city":"Prahran",
    "sg:classifiers":[
        {
            "category":"Banks & Credit Unions",
            "subcategory":"Bureau De Change",
            "type":"Services"
        }
    ],
    "sg:phone":"+61 3 9522 7000",
    "sg:postcode":"3181",
    "sg:province":"VIC",
    "sg:tags":[
        "motorised",
        "scooter"
    ],
    "wof:name":"Scooter Centre John Blair Honda",
    "wof:placetype":"venue"
},
  "geometry": {"coordinates":[145.002563477,-37.8529586792],"type":"Point"}
}