{
  "type": "Feature",
  "properties": {
    "addr:full":"39 Southacre Dr Canning Vale WA 6155",
    "addr:housenumber":"39",
    "addr:postcode":"6155",
    "addr:street":"Southacre Dr",
    "iso:country":"AU",
    "sg:address":"39 Southacre Dr",
    "sg:city":"Canning Vale",
    "sg:classifiers":[
        {
            "category":"Retail",
            "subcategory":"Storage",
            "type":"Services"
        }
    ],
    "sg:phone":"+61 412 425 380",
    "sg:postcode":"6155",
    "sg:province":"WA",
    "sg:tags":[
        "removal",
        "furniture"
    ],
    "wof:name":"Tonys Removals",
    "wof:placetype":"venue"
},
  "geometry": {"coordinates":[115.90634900000001,-32.086185],"type":"Point"}
}