{
  "type": "Feature",
  "properties": {
    "iso:country":"AU",
    "sg:address":"19 Vista Rd",
    "sg:city":"South Maclean",
    "sg:classifiers":[
        {
            "category":"Home & Garden",
            "subcategory":"Garden Supply",
            "type":"Retail Goods"
        }
    ],
    "sg:phone":"+61 7 5546 0276",
    "sg:postcode":"4280",
    "sg:province":"QLD",
    "sg:tags":[
        "nursery"
    ],
    "wof:name":"Henson Enterprises Pty Ltd",
    "wof:placetype":"venue"
},
  "geometry": {"coordinates":[153.005173,-27.786289],"type":"Point"}
}