{
  "type": "Feature",
  "properties": {
    "iso:country":"AU",
    "sg:address":"39- 41 Langford St",
    "sg:city":"Pooraka",
    "sg:classifiers":[
        {
            "category":"Building & Trades",
            "subcategory":"Construction",
            "type":"Services"
        }
    ],
    "sg:phone":"+61 8 8260 2666",
    "sg:postcode":"5095",
    "sg:province":"SA",
    "sg:tags":[
        "scaffolding"
    ],
    "wof:name":"John Wark & Son Pty Ltd",
    "wof:placetype":"venue"
},
  "geometry": {"coordinates":[138.63107299800001,-34.8172950745],"type":"Point"}
}