{
  "type": "Feature",
  "properties": {
    "addr:full":"197 Manifold St Camperdown VIC 3260",
    "addr:housenumber":"197",
    "addr:postcode":"3260",
    "addr:street":"Manifold St",
    "iso:country":"AU",
    "sg:address":"197 Manifold St",
    "sg:city":"Camperdown",
    "sg:classifiers":[
        {
            "category":"Cafe",
            "type":"Food & Drink"
        }
    ],
    "sg:phone":"+61 3 5593 1288",
    "sg:postcode":"3260",
    "sg:province":"VIC",
    "wof:name":"Take A Peek Cafe & Winebar",
    "wof:placetype":"venue"
},
  "geometry": {"coordinates":[143.14605712900001,-38.2322769165],"type":"Point"}
}