{
  "type": "Feature",
  "properties": {
    "addr:full":"Fcty69/ 266 Osborne Ave Clayton South VIC 3169",
    "addr:housenumber":"266",
    "addr:postcode":"3169",
    "addr:street":"Osborne Ave",
    "iso:country":"AU",
    "sg:address":"Fcty69/ 266 Osborne Ave",
    "sg:city":"Clayton South",
    "sg:phone":"+61 414 531 538",
    "sg:postcode":"3169",
    "sg:province":"VIC",
    "wof:name":"All Weather Tanks",
    "wof:placetype":"venue"
},
  "geometry": {"coordinates":[145.118606567,-37.9432868958],"type":"Point"}
}