{
  "type": "Feature",
  "properties": {
    "addr:full":"21 Carlisle St St Kilda VIC 3182",
    "addr:housenumber":"21",
    "addr:postcode":"3182",
    "addr:street":"Carlisle St",
    "iso:country":"AU",
    "sg:address":"21 Carlisle St",
    "sg:city":"St Kilda",
    "sg:classifiers":[
        {
            "category":"Shopping",
            "subcategory":"Clothing, Apparel, & Fashions",
            "type":"Retail Goods"
        }
    ],
    "sg:phone":"+61 3 9593 8888",
    "sg:postcode":"3182",
    "sg:province":"VIC",
    "sg:tags":[
        "lady",
        "wear"
    ],
    "wof:name":"Lawton Knows Ruby",
    "wof:placetype":"venue"
},
  "geometry": {"coordinates":[144.980743408,-37.8671951294],"type":"Point"}
}