{
  "type": "Feature",
  "properties": {
    "addr:full":"Boothenba Rd Troy Junction NSW 2830",
    "addr:postcode":"2830",
    "addr:street":"Boothenba Rd",
    "iso:country":"AU",
    "sg:address":"Boothenba Rd",
    "sg:city":"Troy Junction",
    "sg:classifiers":[
        {
            "category":"Farming",
            "subcategory":"Vineyard",
            "type":"Manufacturing & Wholesale Goods"
        }
    ],
    "sg:phone":"+61 2 6882 2155",
    "sg:postcode":"2830",
    "sg:province":"NSW",
    "sg:tags":[
        "saleyards"
    ],
    "wof:name":"Dubbo Regional Livestock Markets",
    "wof:placetype":"venue"
},
  "geometry": {"coordinates":[148.618865967,-32.2080764771],"type":"Point"}
}