{
  "type": "Feature",
  "properties": {
    "addr:full":"PO Box 213 Bentley WA 6982",
    "addr:postcode":"6982",
    "iso:country":"AU",
    "sg:address":"PO Box 213",
    "sg:city":"Bentley",
    "sg:classifiers":[
        {
            "category":"Utilities",
            "subcategory":"Refuse",
            "type":"Services"
        }
    ],
    "sg:phone":"+61 8 9356 5737",
    "sg:postcode":"6982",
    "sg:province":"WA",
    "sg:tags":[
        "disposal",
        "reduction",
        "waste"
    ],
    "wof:name":"Medi-Collect",
    "wof:placetype":"venue"
},
  "geometry": {"coordinates":[115.918983,-32.001781],"type":"Point"}
}