{
  "type": "Feature",
  "properties": {
    "iso:country":"AU",
    "sg:address":"143 Lumley St",
    "sg:city":"Upper Mt Gravatt",
    "sg:classifiers":[
        {
            "category":"Professional",
            "subcategory":"Printing & Photocopies",
            "type":"Services"
        }
    ],
    "sg:phone":"+61 7 3349 5458",
    "sg:postcode":"4122",
    "sg:province":"QLD",
    "sg:tags":[
        "trophy"
    ],
    "wof:name":"Win Trophies",
    "wof:placetype":"venue"
},
  "geometry": {"coordinates":[153.087234497,-27.5532741547],"type":"Point"}
}