{
  "type": "Feature",
  "properties": {
    "iso:country":"AU",
    "sg:address":"Shop 1/ 72-74 Grafton St",
    "sg:city":"Cairns",
    "sg:classifiers":[
        {
            "category":"Shopping",
            "subcategory":"Clothing, Apparel, & Fashions",
            "type":"Retail Goods"
        }
    ],
    "sg:phone":"+61 7 4031 7333",
    "sg:postcode":"4870",
    "sg:province":"QLD",
    "sg:tags":[
        "menswear"
    ],
    "wof:name":"Delinquent",
    "wof:placetype":"venue"
},
  "geometry": {"coordinates":[145.77699279800001,-16.9236736298],"type":"Point"}
}