{
  "type": "Feature",
  "properties": {
    "addr:full":"31 Challis Ave Potts Point NSW 2011",
    "addr:housenumber":"31",
    "addr:postcode":"2011",
    "addr:street":"Challis Ave",
    "iso:country":"AU",
    "sg:address":"31 Challis Ave",
    "sg:city":"Potts Point",
    "sg:classifiers":[
        {
            "category":"Travel",
            "subcategory":"Hotels & Motels",
            "type":"Entertainment"
        }
    ],
    "sg:phone":"+61 2 9357 3878",
    "sg:postcode":"2011",
    "sg:province":"NSW",
    "sg:tags":[
        "accommodation"
    ],
    "wof:name":"The Maison Ette",
    "wof:placetype":"venue"
},
  "geometry": {"coordinates":[151.224121094,-33.8689041138],"type":"Point"}
}