{
  "type": "Feature",
  "properties": {
    "addr:full":"32 Thomas Mitchell Drv Wodonga VIC 3690",
    "addr:housenumber":"32",
    "addr:postcode":"3690",
    "addr:street":"Thomas Mitchell Drv",
    "iso:country":"AU",
    "sg:address":"32 Thomas Mitchell Drv",
    "sg:city":"Wodonga",
    "sg:classifiers":[
        {
            "category":"Building & Trades",
            "subcategory":"Equipment Rental",
            "type":"Services"
        }
    ],
    "sg:phone":"+61 2 6024 2507",
    "sg:postcode":"3690",
    "sg:province":"VIC",
    "sg:tags":[
        "party",
        "hire"
    ],
    "wof:name":"R.B.R. Party Hire & Wholesale Pty Ltd",
    "wof:placetype":"venue"
},
  "geometry": {"coordinates":[146.89190673799999,-36.1265640259],"type":"Point"}
}