{
  "type": "Feature",
  "properties": {
    "addr:full":"49 Lagoon St Goondiwindi QLD 4390",
    "addr:housenumber":"49",
    "addr:postcode":"4390",
    "addr:street":"Lagoon St",
    "iso:country":"AU",
    "sg:address":"49 Lagoon St",
    "sg:city":"Goondiwindi",
    "sg:classifiers":[
        {
            "category":"Building & Trades",
            "subcategory":"Construction",
            "type":"Services"
        }
    ],
    "sg:phone":"+61 7 4671 0360",
    "sg:postcode":"4390",
    "sg:province":"QLD",
    "sg:tags":[
        "earth",
        "excavating",
        "moving",
        "contractor"
    ],
    "wof:name":"AR & DA Edwards",
    "wof:placetype":"venue"
},
  "geometry": {"coordinates":[150.292572022,-28.534992218],"type":"Point"}
}