{
  "type": "Feature",
  "properties": {
    "addr:full":"267 Lower Heidelberg Rd Ivanhoe East VIC 3079",
    "addr:housenumber":"267",
    "addr:postcode":"3079",
    "addr:street":"Lower Heidelberg Rd",
    "iso:country":"AU",
    "sg:address":"267 Lower Heidelberg Rd",
    "sg:city":"Ivanhoe East",
    "sg:classifiers":[
        {
            "category":"Personal",
            "subcategory":"Beauty Salon",
            "type":"Services"
        }
    ],
    "sg:phone":"+61 3 9499 6230",
    "sg:postcode":"3079",
    "sg:province":"VIC",
    "wof:name":"Iniquity Beauty",
    "wof:placetype":"venue"
},
  "geometry": {"coordinates":[145.059890747,-37.7727470398],"type":"Point"}
}