{
  "type": "Feature",
  "properties": {
    "iso:country":"AU",
    "sg:address":"132 Fitzmaurice St",
    "sg:city":"Wagga Wagga",
    "sg:classifiers":[
        {
            "category":"Wholesale",
            "subcategory":"Non-durable Goods",
            "type":"Manufacturing & Wholesale Goods"
        }
    ],
    "sg:phone":"+61 2 6921 4072",
    "sg:postcode":"2650",
    "sg:province":"NSW",
    "sg:tags":[
        "wholesaler",
        "mfrs",
        "cosmetic"
    ],
    "wof:name":"Riverina Salon Supplies",
    "wof:placetype":"venue"
},
  "geometry": {"coordinates":[147.368774414,-35.1041374207],"type":"Point"}
}