{
  "type": "Feature",
  "properties": {
    "addr:full":"19 Wollongong St Fyshwick ACT 2609",
    "addr:housenumber":"19",
    "addr:postcode":"2609",
    "addr:street":"Wollongong St",
    "iso:country":"AU",
    "sg:address":"19 Wollongong St",
    "sg:city":"Fyshwick",
    "sg:classifiers":[
        {
            "category":"Home & Garden",
            "subcategory":"Carpets & Floor Coverings",
            "type":"Retail Goods"
        }
    ],
    "sg:phone":"+61 2 6280 6046",
    "sg:postcode":"2609",
    "sg:province":"ACT",
    "sg:tags":[
        "tile",
        "wall"
    ],
    "wof:name":"Discount Ceramic Tiles",
    "wof:placetype":"venue"
},
  "geometry": {"coordinates":[149.17820739699999,-35.3266487122],"type":"Point"}
}