{
  "type": "Feature",
  "properties": {
    "addr:full":"33 Hill St Bentleigh East VIC 3165",
    "addr:housenumber":"33",
    "addr:postcode":"3165",
    "addr:street":"Hill St",
    "iso:country":"AU",
    "sg:address":"33 Hill St",
    "sg:city":"Bentleigh East",
    "sg:classifiers":[
        {
            "category":"Building & Trades",
            "subcategory":"Construction",
            "type":"Services"
        }
    ],
    "sg:phone":"+61 3 9570 5302",
    "sg:postcode":"3165",
    "sg:province":"VIC",
    "sg:tags":[
        "joiner",
        "carpenter"
    ],
    "wof:name":"Henshaw Don",
    "wof:placetype":"venue"
},
  "geometry": {"coordinates":[145.06040954599999,-37.9236183167],"type":"Point"}
}