{
  "type": "Feature",
  "properties": {
    "iso:country":"AU",
    "sg:address":"PO Box 35",
    "sg:city":"Banyo",
    "sg:classifiers":[
        {
            "category":"Retail",
            "subcategory":"Laundry & Dry Cleaning",
            "type":"Services"
        }
    ],
    "sg:phone":"+61 7 3267 0215",
    "sg:postcode":"4014",
    "sg:province":"QLD",
    "sg:tags":[
        "cloth",
        "supply"
    ],
    "wof:name":"Rippa Rags",
    "wof:placetype":"venue"
},
  "geometry": {"coordinates":[153.077835083,-27.3749103546],"type":"Point"}
}