{
  "type": "Feature",
  "properties": {
    "addr:full":"112 Castle Hill Rd West Pennant Hills NSW 2125",
    "addr:housenumber":"112",
    "addr:postcode":"2125",
    "addr:street":"Castle Hill Rd",
    "iso:country":"AU",
    "sg:address":"112 Castle Hill Rd",
    "sg:city":"West Pennant Hills",
    "sg:classifiers":[
        {
            "category":"Professional",
            "subcategory":"Business Services",
            "type":"Services"
        }
    ],
    "sg:phone":"+61 2 9481 8967",
    "sg:postcode":"2125",
    "sg:province":"NSW",
    "sg:tags":[
        "drafting"
    ],
    "wof:name":"Knight & Associates Pty Ltd",
    "wof:placetype":"venue"
},
  "geometry": {"coordinates":[151.04078674300001,-33.7404632568],"type":"Point"}
}