{
  "type": "Feature",
  "properties": {
    "addr:full":"12 Bearing Ave Warana QLD 4575",
    "addr:housenumber":"12",
    "addr:postcode":"4575",
    "addr:street":"Bearing Ave",
    "iso:country":"AU",
    "sg:address":"12 Bearing Ave",
    "sg:city":"Warana",
    "sg:classifiers":[
        {
            "category":"Retail",
            "subcategory":"Auto Repair",
            "type":"Services"
        }
    ],
    "sg:phone":"+61 7 5493 5600",
    "sg:postcode":"4575",
    "sg:province":"QLD",
    "sg:tags":[
        "beater",
        "painter",
        "panel"
    ],
    "wof:name":"Kawana Automotive Refinishers",
    "wof:placetype":"venue"
},
  "geometry": {"coordinates":[153.12690699999999,-26.728222],"type":"Point"}
}