{
  "type": "Feature",
  "properties": {
    "addr:full":"398 Tingira St Pinkenba QLD 4008",
    "addr:housenumber":"398",
    "addr:postcode":"4008",
    "addr:street":"Tingira St",
    "iso:country":"AU",
    "sg:address":"398 Tingira St",
    "sg:city":"Pinkenba",
    "sg:classifiers":[
        {
            "category":"Farming",
            "subcategory":"Fish & Marine Products",
            "type":"Manufacturing & Wholesale Goods"
        }
    ],
    "sg:phone":"+61 7 3260 2361",
    "sg:postcode":"4008",
    "sg:province":"QLD",
    "sg:tags":[
        "chemical",
        "supplier"
    ],
    "wof:name":"Devco Australia Holdings Pty Ltd",
    "wof:placetype":"venue"
},
  "geometry": {"coordinates":[153.13539123499999,-27.4166507721],"type":"Point"}
}