{
  "type": "Feature",
  "properties": {
    "addr:full":"Level 2, 141 St Georges Tce Perth WA 6000",
    "addr:housenumber":"141",
    "addr:postcode":"6000",
    "addr:street":"St Georges Tce",
    "iso:country":"AU",
    "sg:address":"Level 2, 141 St",
    "sg:city":"Georges Tce Perth",
    "sg:classifiers":[
        {
            "category":"Banks & Credit Unions",
            "subcategory":"Financial Services",
            "type":"Services"
        }
    ],
    "sg:phone":"+61 8 9480 2800",
    "sg:postcode":"6000",
    "sg:province":"WA",
    "sg:tags":[
        "annuity",
        "rollover",
        "superannuation",
        "consultant"
    ],
    "wof:name":"Challenger Financial Services Group",
    "wof:placetype":"venue"
},
  "geometry": {"coordinates":[115.855300903,-31.9544258118],"type":"Point"}
}