{
  "type": "Feature",
  "properties": {
    "addr:full":"44 Riverstone Rd Gordonvale QLD 4865",
    "addr:housenumber":"44",
    "addr:postcode":"4865",
    "addr:street":"Riverstone Rd",
    "iso:country":"AU",
    "sg:address":"44 Riverstone Rd",
    "sg:city":"Gordonvale",
    "sg:classifiers":[
        {
            "category":"Building & Trades",
            "subcategory":"Construction",
            "type":"Services"
        }
    ],
    "sg:phone":"+61 7 4056 1304",
    "sg:postcode":"4865",
    "sg:province":"QLD",
    "sg:tags":[
        "welding"
    ],
    "wof:name":"ASJM Contractors",
    "wof:placetype":"venue"
},
  "geometry": {"coordinates":[145.781616211,-17.0973262787],"type":"Point"}
}