{
  "type": "Feature",
  "properties": {
    "iso:country":"AU",
    "sg:address":"Unit 5 405 Bayswater Rd",
    "sg:city":"Garbutt",
    "sg:classifiers":[
        {
            "category":"Donuts",
            "subcategory":"None",
            "type":"Food & Drink"
        }
    ],
    "sg:phone":"+61 7 4725 2477",
    "sg:postcode":"4814",
    "sg:province":"QLD",
    "sg:tags":[
        "die",
        "engraver",
        "sinker"
    ],
    "wof:name":"Northpoint Neon Pty Ltd",
    "wof:placetype":"venue"
},
  "geometry": {"coordinates":[146.755783,-19.27244],"type":"Point"}
}