{
  "type": "Feature",
  "properties": {
    "addr:full":"Suite 1 16 Mahony Crt Weston ACT 2611",
    "addr:housenumber":"16",
    "addr:postcode":"2611",
    "addr:street":"Mahony Crt",
    "iso:country":"AU",
    "sg:address":"Suite 1 16 Mahony Crt",
    "sg:city":"Weston",
    "sg:classifiers":[
        {
            "category":"Health Services",
            "subcategory":"Doctor",
            "type":"Services"
        }
    ],
    "sg:phone":"+61 2 6288 6008",
    "sg:postcode":"2611",
    "sg:province":"ACT",
    "sg:tags":[
        "medical",
        "practitioner"
    ],
    "wof:name":"Paterson F",
    "wof:placetype":"venue"
},
  "geometry": {"coordinates":[149.099075317,-35.3355712891],"type":"Point"}
}