{
  "type": "Feature",
  "properties": {
    "iso:country":"AU",
    "sg:address":"20 Angove Park Drv",
    "sg:city":"Tea Tree Gully",
    "sg:classifiers":[
        {
            "category":"Professional",
            "subcategory":"Art Services",
            "type":"Services"
        }
    ],
    "sg:phone":"+61 8 8264 1988",
    "sg:postcode":"5091",
    "sg:province":"SA",
    "sg:tags":[
        "decorator",
        "painter"
    ],
    "wof:name":"Richard Morgan",
    "wof:placetype":"venue"
},
  "geometry": {"coordinates":[138.72366332999999,-34.8223228455],"type":"Point"}
}