{
  "type": "Feature",
  "properties": {
    "addr:full":"163 Audley St Narrandera NSW 2700",
    "addr:housenumber":"163",
    "addr:postcode":"2700",
    "addr:street":"Audley St",
    "iso:country":"AU",
    "sg:address":"163 Audley St",
    "sg:city":"Narrandera",
    "sg:classifiers":[
        {
            "category":"Building & Trades",
            "subcategory":"Construction",
            "type":"Services"
        }
    ],
    "sg:phone":"+61 2 6959 4500",
    "sg:postcode":"2700",
    "sg:province":"NSW",
    "sg:tags":[
        "joinery"
    ],
    "wof:name":"Narrandera Joinery",
    "wof:placetype":"venue"
},
  "geometry": {"coordinates":[146.543823242,-34.7469177246],"type":"Point"}
}