{
  "type": "Feature",
  "properties": {
    "iso:country":"AU",
    "sg:address":"297 Mann St",
    "sg:city":"Gosford",
    "sg:classifiers":[
        {
            "category":"Banks & Credit Unions",
            "subcategory":"Financial Services",
            "type":"Services"
        }
    ],
    "sg:phone":"+61 2 4362 7174",
    "sg:postcode":"2250",
    "sg:province":"NSW",
    "sg:tags":[
        "loan",
        "finance",
        "mortgage"
    ],
    "wof:name":"Cyba Financial Services",
    "wof:placetype":"venue"
},
  "geometry": {"coordinates":[151.34324645999999,-33.4208831787],"type":"Point"}
}