{
  "type": "Feature",
  "properties": {
    "iso:country":"AU",
    "sg:address":"2-12 Cain Ave",
    "sg:city":"Keilor East",
    "sg:classifiers":[
        {
            "category":"Wholesale",
            "subcategory":"Auto Parts",
            "type":"Manufacturing & Wholesale Goods"
        }
    ],
    "sg:phone":"+61 3 9274 4443",
    "sg:postcode":"3033",
    "sg:province":"VIC",
    "sg:tags":[
        "recyclers"
    ],
    "wof:name":"East Keilor Wreckers (Importing) Pty Ltd",
    "wof:placetype":"venue"
},
  "geometry": {"coordinates":[144.856476,-37.733704],"type":"Point"}
}