{
  "type": "Feature",
  "properties": {
    "iso:country":"AU",
    "sg:address":"30 Victoria St",
    "sg:city":"Potts Point",
    "sg:classifiers":[
        {
            "category":"Professional",
            "subcategory":"Art Services",
            "type":"Services"
        }
    ],
    "sg:phone":"+61 2 9357 3755",
    "sg:postcode":"2011",
    "sg:province":"NSW",
    "wof:name":"Thirty Victoria Street",
    "wof:placetype":"venue"
},
  "geometry": {"coordinates":[151.22390747099999,-33.8677864075],"type":"Point"}
}