{
  "type": "Feature",
  "properties": {
    "addr:full":"11 Separation St Fairfield VIC 3078",
    "addr:housenumber":"11",
    "addr:postcode":"3078",
    "addr:street":"Separation St",
    "iso:country":"AU",
    "sg:address":"11 Separation St",
    "sg:city":"Fairfield",
    "sg:classifiers":[
        {
            "category":"Building & Trades",
            "subcategory":"Plumbing",
            "type":"Services"
        }
    ],
    "sg:phone":"+61 418 341 563",
    "sg:postcode":"3078",
    "sg:province":"VIC",
    "sg:tags":[
        "plumber",
        "gasfitters"
    ],
    "wof:name":"Prendergast Plumbing",
    "wof:placetype":"venue"
},
  "geometry": {"coordinates":[145.02488708499999,-37.7723770142],"type":"Point"}
}