{
  "type": "Feature",
  "properties": {
    "iso:country":"AU",
    "sg:address":"8 Chelsey St",
    "sg:city":"Ardeer",
    "sg:classifiers":[
        {
            "category":"Arts & Performance",
            "subcategory":"Music",
            "type":"Entertainment"
        }
    ],
    "sg:phone":"+61 3 9363 4763",
    "sg:postcode":"3022",
    "sg:province":"VIC",
    "sg:tags":[
        "mobile",
        "jockey",
        "disc"
    ],
    "wof:name":"Unique Entertainment",
    "wof:placetype":"venue"
},
  "geometry": {"coordinates":[144.79791299999999,-37.776592],"type":"Point"}
}