{
  "type": "Feature",
  "properties": {
    "iso:country":"AU",
    "sg:address":"53 Forbes St",
    "sg:city":"Grenfell",
    "sg:classifiers":[
        {
            "category":"Retail",
            "subcategory":"Veterinary Services",
            "type":"Services"
        }
    ],
    "sg:phone":"+61 2 6343 1581",
    "sg:postcode":"2810",
    "sg:province":"NSW",
    "sg:tags":[
        "surgeon"
    ],
    "wof:name":"Fletcher Chris",
    "wof:placetype":"venue"
},
  "geometry": {"coordinates":[148.16026306099999,-33.9041557312],"type":"Point"}
}