{
  "type": "Feature",
  "properties": {
    "addr:full":"216 Karingal Drv Frankston VIC 3199",
    "addr:housenumber":"216",
    "addr:postcode":"3199",
    "addr:street":"Karingal Drv",
    "iso:country":"AU",
    "sg:address":"216 Karingal Drv",
    "sg:city":"Frankston",
    "sg:classifiers":[
        {
            "category":"Health Services",
            "subcategory":"Dentist",
            "type":"Services"
        }
    ],
    "sg:phone":"+61 3 9775 5088",
    "sg:postcode":"3199",
    "sg:province":"VIC",
    "sg:tags":[
        "technician",
        "dental"
    ],
    "wof:name":"Karingal Denture Clinic",
    "wof:placetype":"venue"
},
  "geometry": {"coordinates":[145.163131714,-38.1526412964],"type":"Point"}
}