{
  "type": "Feature",
  "properties": {
    "addr:full":"Unit 4/ 13 Strathwyn St Brendale QLD 4500",
    "addr:postcode":"4500",
    "addr:street":"13 Strathwyn St",
    "iso:country":"AU",
    "sg:address":"Unit 4/ 13 Strathwyn St",
    "sg:city":"Brendale",
    "sg:classifiers":[
        {
            "category":"Wholesale",
            "subcategory":"Construction Materials",
            "type":"Manufacturing & Wholesale Goods"
        }
    ],
    "sg:phone":"+61 7 3205 1665",
    "sg:postcode":"4500",
    "sg:province":"QLD",
    "sg:tags":[
        "wholesaler",
        "felt",
        "mfrs"
    ],
    "wof:name":"C A Stephan Pty Ltd",
    "wof:placetype":"venue"
},
  "geometry": {"coordinates":[152.978805542,-27.3205680847],"type":"Point"}
}