{
  "type": "Feature",
  "properties": {
    "addr:full":"33 Montpelier Rd Bowen Hills QLD 4006",
    "addr:housenumber":"33",
    "addr:postcode":"4006",
    "addr:street":"Montpelier Rd",
    "iso:country":"AU",
    "sg:address":"33 Montpelier Rd",
    "sg:city":"Bowen Hills",
    "sg:classifiers":[
        {
            "category":"Professional",
            "subcategory":"Art Services",
            "type":"Services"
        }
    ],
    "sg:phone":"+61 1300 551 942",
    "sg:postcode":"4006",
    "sg:province":"QLD",
    "sg:tags":[
        "decorator",
        "painter"
    ],
    "wof:name":"Commercial Maintenance & Painting Solutions",
    "wof:placetype":"venue"
},
  "geometry": {"coordinates":[153.04000854500001,-27.4490280151],"type":"Point"}
}