{
  "type": "Feature",
  "properties": {
    "addr:full":"42 Marcia St Coffs Harbour NSW 2450",
    "addr:housenumber":"42",
    "addr:postcode":"2450",
    "addr:street":"Marcia St",
    "iso:country":"AU",
    "sg:address":"42 Marcia St",
    "sg:city":"Coffs Harbour",
    "sg:classifiers":[
        {
            "category":"Wholesale",
            "subcategory":"Metals & Minerals",
            "type":"Manufacturing & Wholesale Goods"
        }
    ],
    "sg:phone":"+61 2 6652 1476",
    "sg:postcode":"2450",
    "sg:province":"NSW",
    "sg:tags":[
        "steel",
        "stainless",
        "product",
        "equipment"
    ],
    "wof:name":"Marcia Street Fabricators Pty. Ltd.",
    "wof:placetype":"venue"
},
  "geometry": {"coordinates":[153.119247,-30.289768],"type":"Point"}
}