{
  "type": "Feature",
  "properties": {
    "addr:full":"3260 Sth Gippsland Hwy Tooradin VIC 3980",
    "addr:housenumber":"3260",
    "addr:postcode":"3980",
    "addr:street":"Sth Gippsland Hwy",
    "iso:country":"AU",
    "sg:address":"3260 Sth Gippsland Hwy",
    "sg:city":"Tooradin",
    "sg:classifiers":[
        {
            "category":"Education",
            "subcategory":"Special Training",
            "type":"Public Place"
        }
    ],
    "sg:phone":"+61 3 9558 3711",
    "sg:postcode":"3980",
    "sg:province":"VIC",
    "sg:tags":[
        "instruction",
        "display",
        "parachuting"
    ],
    "wof:name":"Skydive Melbourne",
    "wof:placetype":"venue"
},
  "geometry": {"coordinates":[145.38255310100001,-38.2140312195],"type":"Point"}
}