{
  "type": "Feature",
  "properties": {
    "addr:full":"98 Fitzroy St Dubbo NSW 2830",
    "addr:housenumber":"98",
    "addr:postcode":"2830",
    "addr:street":"Fitzroy St",
    "iso:country":"AU",
    "sg:address":"98 Fitzroy St",
    "sg:city":"Dubbo",
    "sg:classifiers":[
        {
            "category":"Social Services",
            "subcategory":"Adult Care",
            "type":"Services"
        }
    ],
    "sg:phone":"+61 2 6884 1456",
    "sg:postcode":"2830",
    "sg:province":"NSW",
    "sg:tags":[
        "towing"
    ],
    "wof:name":"Graham Barkers Towing",
    "wof:placetype":"venue"
},
  "geometry": {"coordinates":[148.61346435600001,-32.2499351501],"type":"Point"}
}