{
  "type": "Feature",
  "properties": {
    "addr:full":"301 Ingham Rd Garbutt QLD 4814",
    "addr:housenumber":"301",
    "addr:postcode":"4814",
    "addr:street":"Ingham Rd",
    "iso:country":"AU",
    "sg:address":"301 Ingham Rd",
    "sg:city":"Garbutt",
    "sg:classifiers":[
        {
            "category":"Utilities",
            "subcategory":"Electric",
            "type":"Services"
        }
    ],
    "sg:phone":"+61 7 4725 8500",
    "sg:postcode":"4814",
    "sg:province":"QLD",
    "sg:tags":[
        "electrical",
        "contractor"
    ],
    "wof:name":"O&#039;Donnell Griffin",
    "wof:placetype":"venue"
},
  "geometry": {"coordinates":[146.77354399999999,-19.265152],"type":"Point"}
}