{
  "type": "Feature",
  "properties": {
    "addr:full":"11/ 49 Royal Crs null VIC 3037",
    "addr:housenumber":"11 / 49",
    "addr:postcode":"3037",
    "addr:street":"Royal Crs",
    "iso:country":"AU",
    "sg:address":"11/ 49 Royal Crs",
    "sg:city":"null",
    "sg:classifiers":[
        {
            "category":"Health Services",
            "subcategory":"Health Practitioner",
            "type":"Services"
        }
    ],
    "sg:phone":"+61 3 8390 8322",
    "sg:postcode":"3037",
    "sg:province":"VIC",
    "sg:tags":[
        "physiotherapist"
    ],
    "wof:name":"Pierre Caroline",
    "wof:placetype":"venue"
},
  "geometry": {"coordinates":[144.75900300000001,-37.695461],"type":"Point"}
}