{
  "type": "Feature",
  "properties": {
    "iso:country":"AU",
    "sg:address":"Unit 3/ 276 New Line Rd",
    "sg:city":"Dural",
    "sg:classifiers":[
        {
            "category":"Home & Garden",
            "subcategory":"Household Appliances",
            "type":"Retail Goods"
        }
    ],
    "sg:phone":"+61 2 9651 6222",
    "sg:postcode":"2158",
    "sg:province":"NSW",
    "sg:tags":[
        "heating",
        "system"
    ],
    "wof:name":"Icoolm Air Conditioning",
    "wof:placetype":"venue"
},
  "geometry": {"coordinates":[151.03053283700001,-33.6961631775],"type":"Point"}
}