{
  "type": "Feature",
  "properties": {
    "iso:country":"AU",
    "sg:address":"Three Bridge Rd",
    "sg:city":"Lower Norton",
    "sg:classifiers":[
        {
            "category":"Building & Trades",
            "subcategory":"Construction",
            "type":"Services"
        }
    ],
    "sg:phone":"+61 418 387 335",
    "sg:postcode":"3401",
    "sg:province":"VIC",
    "sg:tags":[
        "brick",
        "paving"
    ],
    "wof:name":"Colin Share Landscapes & Paving",
    "wof:placetype":"venue"
},
  "geometry": {"coordinates":[142.11363220199999,-36.7602043152],"type":"Point"}
}