{
  "type": "Feature",
  "properties": {
    "addr:full":"398 Raymond St Sale VIC 3850",
    "addr:housenumber":"398",
    "addr:postcode":"3850",
    "addr:street":"Raymond St",
    "iso:country":"AU",
    "sg:address":"398 Raymond St",
    "sg:city":"Sale",
    "sg:classifiers":[
        {
            "category":"Home & Garden",
            "subcategory":"Carpets & Floor Coverings",
            "type":"Retail Goods"
        }
    ],
    "sg:phone":"+61 3 5143 0266",
    "sg:postcode":"3850",
    "sg:province":"VIC",
    "sg:tags":[
        "tile",
        "wall"
    ],
    "wof:name":"Beaumont Tiles",
    "wof:placetype":"venue"
},
  "geometry": {"coordinates":[147.06562805199999,-38.1043586731],"type":"Point"}
}