{
  "type": "Feature",
  "properties": {
    "iso:country":"AU",
    "sg:address":"20 Serpentine Rd",
    "sg:city":"Hendra",
    "sg:classifiers":[
        {
            "category":"Industrial Area",
            "type":"Public Place"
        }
    ],
    "sg:phone":"+61 7 3252 5786",
    "sg:postcode":"4011",
    "sg:province":"QLD",
    "sg:tags":[
        "rural",
        "shed"
    ],
    "wof:name":"Clearspan Building Systems",
    "wof:placetype":"venue"
},
  "geometry": {"coordinates":[153.075317,-27.411388],"type":"Point"}
}