{
  "type": "Feature",
  "properties": {
    "iso:country":"AU",
    "sg:address":"29a Logan Rd",
    "sg:city":"Woolloongabba",
    "sg:classifiers":[
        {
            "category":"Professional",
            "subcategory":"Computer Services",
            "type":"Services"
        }
    ],
    "sg:phone":"+61 7 3891 5216",
    "sg:postcode":"4102",
    "sg:province":"QLD",
    "sg:tags":[
        "training"
    ],
    "wof:name":"Cosmos Holdings Pty Ltd",
    "wof:placetype":"venue"
},
  "geometry": {"coordinates":[153.037841797,-27.4887275696],"type":"Point"}
}