{
  "type": "Feature",
  "properties": {
    "iso:country":"AU",
    "sg:address":"1376 Silkwood Rd",
    "sg:city":"Japoonvale",
    "sg:classifiers":[
        {
            "category":"Home & Garden",
            "subcategory":"Garden Supply",
            "type":"Retail Goods"
        }
    ],
    "sg:phone":"+61 7 4065 5123",
    "sg:postcode":"4856",
    "sg:province":"QLD",
    "sg:tags":[
        "fertilizer"
    ],
    "wof:name":"Japoonvale Fertilizers & Transport",
    "wof:placetype":"venue"
},
  "geometry": {"coordinates":[145.93931579599999,-17.7162399292],"type":"Point"}
}