{
  "type": "Feature",
  "properties": {
    "iso:country":"AU",
    "sg:address":"55 Barnes St",
    "sg:city":"Tamworth",
    "sg:classifiers":[
        {
            "category":"Retail",
            "subcategory":"Auto Repair",
            "type":"Services"
        }
    ],
    "sg:phone":"+61 2 6762 0442",
    "sg:postcode":"2340",
    "sg:province":"NSW",
    "sg:tags":[
        "beater",
        "painter",
        "panel"
    ],
    "wof:name":"Taminda Smash Repairs",
    "wof:placetype":"venue"
},
  "geometry": {"coordinates":[150.91177368199999,-31.0915489197],"type":"Point"}
}