{
  "type": "Feature",
  "properties": {
    "addr:full":"27 Camira St Maroubra NSW 2035",
    "addr:housenumber":"27",
    "addr:postcode":"2035",
    "addr:street":"Camira St",
    "iso:country":"AU",
    "sg:address":"27 Camira St",
    "sg:city":"Maroubra",
    "sg:classifiers":[
        {
            "category":"Building & Trades",
            "subcategory":"Construction",
            "type":"Services"
        }
    ],
    "sg:phone":"+61 418 477 072",
    "sg:postcode":"2035",
    "sg:province":"NSW",
    "sg:tags":[
        "renovation",
        "alterations",
        "extension",
        "contractor"
    ],
    "wof:name":"T & R Siltala",
    "wof:placetype":"venue"
},
  "geometry": {"coordinates":[151.25062560999999,-33.947353363],"type":"Point"}
}