{
  "type": "Feature",
  "properties": {
    "addr:full":"2 Glenroy Crt Hovea WA 6071",
    "addr:housenumber":"2",
    "addr:postcode":"6071",
    "addr:street":"Glenroy Crt",
    "iso:country":"AU",
    "sg:address":"2 Glenroy Crt",
    "sg:city":"Hovea",
    "sg:classifiers":[
        {
            "category":"Professional",
            "subcategory":"Business Services",
            "type":"Services"
        }
    ],
    "sg:phone":"+61 8 9298 8155",
    "sg:postcode":"6071",
    "sg:province":"WA",
    "sg:tags":[
        "drafting"
    ],
    "wof:name":"Cleaver C.R.",
    "wof:placetype":"venue"
},
  "geometry": {"coordinates":[116.104278565,-31.8867664337],"type":"Point"}
}