{
  "type": "Feature",
  "properties": {
    "addr:full":"1 Main St Cobram VIC 3644",
    "addr:housenumber":"1",
    "addr:postcode":"3644",
    "addr:street":"Main St",
    "iso:country":"AU",
    "sg:address":"1 Main St",
    "sg:city":"Cobram",
    "sg:classifiers":[
        {
            "category":"Travel",
            "subcategory":"Hotels & Motels",
            "type":"Entertainment"
        }
    ],
    "sg:phone":"+61 3 5872 2488",
    "sg:postcode":"3644",
    "sg:province":"VIC",
    "wof:name":"Golden Chain Regency Court Motel",
    "wof:placetype":"venue"
},
  "geometry": {"coordinates":[145.64625549300001,-35.9210624695],"type":"Point"}
}