{
  "type": "Feature",
  "properties": {
    "iso:country":"AU",
    "sg:address":"4 Reading Ave",
    "sg:city":"Killara",
    "sg:classifiers":[
        {
            "category":"Insurance",
            "subcategory":"Insurance Agent",
            "type":"Services"
        }
    ],
    "sg:phone":"+61 2 9418 1800",
    "sg:postcode":"2071",
    "sg:province":"NSW",
    "wof:name":"Gowling Nigel T & Associates Pty Ltd",
    "wof:placetype":"venue"
},
  "geometry": {"coordinates":[151.17530822800001,-33.7536125183],"type":"Point"}
}