{
  "type": "Feature",
  "properties": {
    "addr:full":"PO Box 245 Moorebank NSW 2170",
    "addr:postcode":"2170",
    "iso:country":"AU",
    "sg:address":"PO Box 245",
    "sg:city":"Moorebank",
    "sg:classifiers":[
        {
            "category":"Real Estate",
            "subcategory":"Real Estate Operator",
            "type":"Services"
        }
    ],
    "sg:phone":"+61 419 653 550",
    "sg:postcode":"2170",
    "sg:province":"NSW",
    "sg:tags":[
        "concrete",
        "pumping"
    ],
    "wof:name":"On Call Allcrete",
    "wof:placetype":"venue"
},
  "geometry": {"coordinates":[150.922927856,-33.9513893127],"type":"Point"}
}