{
  "type": "Feature",
  "properties": {
    "iso:country":"AU",
    "sg:address":"PO Box 297",
    "sg:city":"Sanctuary Cove",
    "sg:classifiers":[
        {
            "category":"Real Estate",
            "subcategory":"Real Estate Agent",
            "type":"Services"
        }
    ],
    "sg:phone":"+61 414 306 630",
    "sg:postcode":"4212",
    "sg:province":"QLD",
    "wof:name":"Brett Hughes Marketing Quality Property",
    "wof:placetype":"venue"
},
  "geometry": {"coordinates":[153.35943603499999,-27.8538703918],"type":"Point"}
}