{
  "type": "Feature",
  "properties": {
    "addr:full":"11 Dunbar Ave Sunshine VIC 3020",
    "addr:housenumber":"11",
    "addr:postcode":"3020",
    "addr:street":"Dunbar Ave",
    "iso:country":"AU",
    "sg:address":"11 Dunbar Ave",
    "sg:city":"Sunshine",
    "sg:classifiers":[
        {
            "category":"Building & Trades",
            "subcategory":"Construction",
            "type":"Services"
        }
    ],
    "sg:phone":"+61 414 591 944",
    "sg:postcode":"3020",
    "sg:province":"VIC",
    "sg:tags":[
        "concrete",
        "paving"
    ],
    "wof:name":"Rullo Paving Pty Ltd",
    "wof:placetype":"venue"
},
  "geometry": {"coordinates":[144.82664500000001,-37.796684],"type":"Point"}
}