{
  "type": "Feature",
  "properties": {
    "iso:country":"AU",
    "sg:address":"Unit 7 485 Waterloo Corner Rd",
    "sg:city":"Burton",
    "sg:classifiers":[
        {
            "category":"Autos & Motor Vehicles",
            "subcategory":"Auto Supplies",
            "type":"Retail Goods"
        }
    ],
    "sg:phone":"+61 8 8280 9677",
    "sg:postcode":"5110",
    "sg:province":"SA",
    "sg:tags":[
        "accessory"
    ],
    "wof:name":"Austech Spoilers & Window Tinting",
    "wof:placetype":"venue"
},
  "geometry": {"coordinates":[138.607055664,-34.7413520813],"type":"Point"}
}