{
  "type": "Feature",
  "properties": {
    "addr:full":"7/ 1 Herveys Range Rd Kirwan QLD 4817",
    "addr:housenumber":"/ 1",
    "addr:postcode":"4817",
    "addr:street":"Herveys Range Rd",
    "iso:country":"AU",
    "sg:address":"7/ 1 Herveys Range Rd",
    "sg:city":"Kirwan",
    "sg:classifiers":[
        {
            "category":"Shopping",
            "subcategory":"Bicycles & Sporting Goods",
            "type":"Retail Goods"
        }
    ],
    "sg:phone":"+61 7 4773 4755",
    "sg:postcode":"4817",
    "sg:province":"QLD",
    "sg:tags":[
        "chemical",
        "equipment",
        "pool",
        "swimming"
    ],
    "wof:name":"Swimart Townsville",
    "wof:placetype":"venue"
},
  "geometry": {"coordinates":[146.72125199999999,-19.319578],"type":"Point"}
}