{
  "type": "Feature",
  "properties": {
    "addr:full":"192 Miller St Armidale NSW 2350",
    "addr:housenumber":"192",
    "addr:postcode":"2350",
    "addr:street":"Miller St",
    "iso:country":"AU",
    "sg:address":"192 Miller St",
    "sg:city":"Armidale",
    "sg:classifiers":[
        {
            "category":"Travel",
            "subcategory":"Hotels & Motels",
            "type":"Entertainment"
        }
    ],
    "sg:phone":"+61 2 6772 7733",
    "sg:postcode":"2350",
    "sg:province":"NSW",
    "wof:name":"Acacia Motor Inn",
    "wof:placetype":"venue"
},
  "geometry": {"coordinates":[151.646606445,-30.5189342499],"type":"Point"}
}