{
  "type": "Feature",
  "properties": {
    "addr:full":"38 Barellan Ave Dapto NSW 2530",
    "addr:housenumber":"38",
    "addr:postcode":"2530",
    "addr:street":"Barellan Ave",
    "iso:country":"AU",
    "sg:address":"38 Barellan Ave",
    "sg:city":"Dapto",
    "sg:classifiers":[
        {
            "category":"Building & Trades",
            "subcategory":"Plumbing",
            "type":"Services"
        }
    ],
    "sg:phone":"+61 2 4261 7907",
    "sg:postcode":"2530",
    "sg:province":"NSW",
    "sg:tags":[
        "plumber",
        "gasfitters"
    ],
    "wof:name":"Thew P J",
    "wof:placetype":"venue"
},
  "geometry": {"coordinates":[150.800872803,-34.4908676147],"type":"Point"}
}