{
  "type": "Feature",
  "properties": {
    "addr:full":"Shop 1, 60 Fairfield Rd Elizabeth Grove SA 5112",
    "addr:housenumber":"shop;60",
    "addr:postcode":"5112",
    "addr:street":"Fairfield Rd",
    "iso:country":"AU",
    "sg:address":"Shop 1, 60 Fairfield Rd",
    "sg:city":"Elizabeth Grove",
    "sg:classifiers":[
        {
            "category":"Building & Trades",
            "subcategory":"Locksmith",
            "type":"Services"
        }
    ],
    "sg:phone":"+61 8 8287 0508",
    "sg:postcode":"5112",
    "sg:province":"SA",
    "sg:tags":[
        "strongroom",
        "safe",
        "door"
    ],
    "wof:name":"Elizabeth Locksmiths",
    "wof:placetype":"venue"
},
  "geometry": {"coordinates":[138.663009644,-34.7317581177],"type":"Point"}
}