{
  "type": "Feature",
  "properties": {
    "iso:country":"AU",
    "sg:address":"The Basement St Ives Shopping Plaza 351 Mona Vale",
    "sg:city":"Ives",
    "sg:classifiers":[
        {
            "category":"Utilities",
            "subcategory":"Mobile Phone",
            "type":"Services"
        }
    ],
    "sg:phone":"+61 2 9440 9111",
    "sg:postcode":"2075",
    "sg:province":"NSW",
    "sg:tags":[
        "repair",
        "telephone"
    ],
    "wof:name":"Leading Edge Telecoms Gordon",
    "wof:placetype":"venue"
},
  "geometry": {"coordinates":[151.173339844,-33.7172546387],"type":"Point"}
}