{
  "type": "Feature",
  "properties": {
    "addr:full":"162 Macquarie St Hobart TAS 7000",
    "addr:housenumber":"162",
    "addr:postcode":"7000",
    "addr:street":"Macquarie St",
    "iso:country":"AU",
    "sg:address":"162 Macquarie St",
    "sg:city":"Hobart",
    "sg:classifiers":[
        {
            "category":"Professional",
            "subcategory":"Employment Agencies",
            "type":"Services"
        }
    ],
    "sg:phone":"+61 3 6224 9341",
    "sg:postcode":"7000",
    "sg:province":"TAS",
    "wof:name":"Julia Ross",
    "wof:placetype":"venue"
},
  "geometry": {"coordinates":[147.32685852,-42.8854866028],"type":"Point"}
}