{
  "type": "Feature",
  "properties": {
    "addr:full":"1 Della Torra Rd Moe VIC 3825",
    "addr:housenumber":"1",
    "addr:postcode":"3825",
    "addr:street":"Della Torra Rd",
    "iso:country":"AU",
    "sg:address":"1 Della Torra Rd",
    "sg:city":"Moe",
    "sg:classifiers":[
        {
            "category":"Utilities",
            "subcategory":"Recycling",
            "type":"Services"
        }
    ],
    "sg:phone":"+61 421 347 395",
    "sg:postcode":"3825",
    "sg:province":"VIC",
    "wof:name":"Ricks Metal",
    "wof:placetype":"venue"
},
  "geometry": {"coordinates":[146.26156599999999,-38.168022],"type":"Point"}
}