{
  "type": "Feature",
  "properties": {
    "addr:full":"19 Clarkson Ave Wanneroo WA 6065",
    "addr:housenumber":"19",
    "addr:postcode":"6065",
    "addr:street":"Clarkson Ave",
    "iso:country":"AU",
    "sg:address":"19 Clarkson Ave",
    "sg:city":"Wanneroo",
    "sg:classifiers":[
        {
            "category":"Professional",
            "subcategory":"Business Services",
            "type":"Services"
        }
    ],
    "sg:phone":"+61 8 9306 3466",
    "sg:postcode":"6065",
    "sg:province":"WA",
    "sg:tags":[
        "exporter"
    ],
    "wof:name":"Freshlink Export Pty Ltd",
    "wof:placetype":"venue"
},
  "geometry": {"coordinates":[115.786781311,-31.7190494537],"type":"Point"}
}