{
  "type": "Feature",
  "properties": {
    "addr:full":"37 Kenjulie Drv Bentleigh East VIC 3165",
    "addr:housenumber":"37",
    "addr:postcode":"3165",
    "addr:street":"Kenjulie Drv",
    "iso:country":"AU",
    "sg:address":"37 Kenjulie Drv",
    "sg:city":"Bentleigh East",
    "sg:classifiers":[
        {
            "category":"Personal",
            "subcategory":"Beauty Salon",
            "type":"Services"
        }
    ],
    "sg:phone":"+61 3 9563 7282",
    "sg:postcode":"3165",
    "sg:province":"VIC",
    "sg:tags":[
        "hairdresser"
    ],
    "wof:name":"Thomai Hair Creations",
    "wof:placetype":"venue"
},
  "geometry": {"coordinates":[145.065643311,-37.9301605225],"type":"Point"}
}