{
  "type": "Feature",
  "properties": {
    "addr:full":"U 41/ 75 Spofforth St Mosman NSW 2088",
    "addr:housenumber":"41 / 75",
    "addr:postcode":"2088",
    "addr:street":"Spofforth St",
    "iso:country":"AU",
    "sg:address":"U 41/ 75 Spofforth St",
    "sg:city":"Mosman",
    "sg:classifiers":[
        {
            "category":"Professional",
            "subcategory":"Art Services",
            "type":"Services"
        }
    ],
    "sg:phone":"+61 412 468 216",
    "sg:postcode":"2088",
    "sg:province":"NSW",
    "sg:tags":[
        "graphic",
        "designer"
    ],
    "wof:name":"Charlie Horse Design",
    "wof:placetype":"venue"
},
  "geometry": {"coordinates":[151.23036193900001,-33.8288803101],"type":"Point"}
}