{
  "type": "Feature",
  "properties": {
    "addr:full":"Unit 10 47 William St Armadale WA 6112",
    "addr:housenumber":"47",
    "addr:postcode":"6112",
    "addr:street":"William St",
    "iso:country":"AU",
    "sg:address":"Unit 10 47 William St",
    "sg:city":"Armadale",
    "sg:classifiers":[
        {
            "category":"Professional",
            "subcategory":"Employment Agencies",
            "type":"Services"
        }
    ],
    "sg:phone":"+61 1300 360 562",
    "sg:postcode":"6112",
    "sg:province":"WA",
    "wof:name":"Jobfind Centre",
    "wof:placetype":"venue"
},
  "geometry": {"coordinates":[116.013679504,-32.1553573608],"type":"Point"}
}