{
  "type": "Feature",
  "properties": {
    "addr:full":"PO Box 708 Gisborne VIC 3437",
    "addr:postcode":"3437",
    "iso:country":"AU",
    "sg:address":"PO Box 708",
    "sg:city":"Gisborne",
    "sg:classifiers":[
        {
            "category":"Structure",
            "subcategory":"Building",
            "type":"Public Place"
        }
    ],
    "sg:phone":"+61 3 5428 9180",
    "sg:postcode":"3437",
    "sg:province":"VIC",
    "sg:tags":[
        "sail",
        "shade"
    ],
    "wof:name":"Dashco Pty Ltd",
    "wof:placetype":"venue"
},
  "geometry": {"coordinates":[144.59135437,-37.4869995117],"type":"Point"}
}