{
  "type": "Feature",
  "properties": {
    "addr:full":"Shop 131 Redbank Plaza 1 Collingwood Drv Redbank QLD 4301",
    "addr:housenumber":"131;1",
    "addr:postcode":"4301",
    "addr:street":"Redbank Plaza;Collingwood Drv",
    "iso:country":"AU",
    "sg:address":"Shop 131 Redbank Plaza 1 Collingwood Drv",
    "sg:city":"Redbank",
    "sg:classifiers":[
        {
            "category":"Deli",
            "type":"Food & Drink"
        }
    ],
    "sg:phone":"+61 7 3818 0148",
    "sg:postcode":"4301",
    "sg:province":"QLD",
    "sg:tags":[
        "delicatessen"
    ],
    "wof:name":"Cut Price Deli",
    "wof:placetype":"venue"
},
  "geometry": {"coordinates":[152.86949157699999,-27.6062335968],"type":"Point"}
}