{
  "type": "Feature",
  "properties": {
    "addr:full":"5a 35 Belgrave St Kempsey NSW 2440",
    "addr:housenumber":"35",
    "addr:postcode":"2440",
    "addr:street":"Belgrave St",
    "iso:country":"AU",
    "sg:address":"5a 35 Belgrave St",
    "sg:city":"Kempsey",
    "sg:classifiers":[
        {
            "category":"Health Services",
            "subcategory":"Doctor",
            "type":"Services"
        }
    ],
    "sg:phone":"+61 2 6566 2950",
    "sg:postcode":"2440",
    "sg:province":"NSW",
    "sg:tags":[
        "medical",
        "practitioner"
    ],
    "wof:name":"Macleay Skin Cancer Clinic",
    "wof:placetype":"venue"
},
  "geometry": {"coordinates":[152.839493,-31.080172],"type":"Point"}
}