{
  "type": "Feature",
  "properties": {
    "iso:country":"AU",
    "sg:address":"69 Bellambi La",
    "sg:city":"Bellambi",
    "sg:classifiers":[
        {
            "category":"Utilities",
            "subcategory":"Electric",
            "type":"Services"
        }
    ],
    "sg:phone":"+61 2 4221 1444",
    "sg:postcode":"2518",
    "sg:province":"NSW",
    "sg:tags":[
        "electrical",
        "contractor"
    ],
    "wof:name":"JDC Electrical",
    "wof:placetype":"venue"
},
  "geometry": {"coordinates":[150.90292400000001,-34.361504],"type":"Point"}
}