{
  "type": "Feature",
  "properties": {
    "addr:full":"20 Gregory St Sandy Bay TAS 7005",
    "addr:housenumber":"20",
    "addr:postcode":"7005",
    "addr:street":"Gregory St",
    "iso:country":"AU",
    "sg:address":"20 Gregory St",
    "sg:city":"Sandy Bay",
    "sg:classifiers":[
        {
            "category":"Health Services",
            "subcategory":"Health Practitioner",
            "type":"Services"
        }
    ],
    "sg:phone":"+61 3 6224 1313",
    "sg:postcode":"7005",
    "sg:province":"TAS",
    "sg:tags":[
        "naturopath"
    ],
    "wof:name":"Harmony Chinese Medical Centre",
    "wof:placetype":"venue"
},
  "geometry": {"coordinates":[147.325927734,-42.8957901001],"type":"Point"}
}