{
  "type": "Feature",
  "properties": {
    "addr:full":"232 Boundary St Spring Hill QLD 4000",
    "addr:housenumber":"232",
    "addr:postcode":"4000",
    "addr:street":"Boundary St",
    "iso:country":"AU",
    "sg:address":"232 Boundary St",
    "sg:city":"Spring Hill",
    "sg:classifiers":[
        {
            "category":"Professional",
            "subcategory":"Employment Agencies",
            "type":"Services"
        }
    ],
    "sg:phone":"+61 7 3832 4088",
    "sg:postcode":"4000",
    "sg:province":"QLD",
    "wof:name":"Glenda Stenner Recruitment Proprietary Limited",
    "wof:placetype":"venue"
},
  "geometry": {"coordinates":[153.028762817,-27.4615898132],"type":"Point"}
}