{
  "type": "Feature",
  "properties": {
    "iso:country":"AU",
    "sg:address":"52 Clarke St South",
    "sg:city":"Peakhurst",
    "sg:classifiers":[
        {
            "category":"Building & Trades",
            "subcategory":"Pest Control",
            "type":"Services"
        }
    ],
    "sg:phone":"+61 2 9534 3669",
    "sg:postcode":"2210",
    "sg:province":"NSW",
    "wof:name":"Rowland's Pest Control",
    "wof:placetype":"venue"
},
  "geometry": {"coordinates":[151.04527300000001,-33.96315],"type":"Point"}
}