{
  "type": "Feature",
  "properties": {
    "addr:full":"9 Russell Crt Dandenong VIC 3175",
    "addr:housenumber":"9",
    "addr:postcode":"3175",
    "addr:street":"Russell Crt",
    "iso:country":"AU",
    "sg:address":"9 Russell Crt",
    "sg:city":"Dandenong",
    "sg:classifiers":[
        {
            "category":"Building & Trades",
            "subcategory":"Construction",
            "type":"Services"
        }
    ],
    "sg:phone":"+61 3 9794 7477",
    "sg:postcode":"3175",
    "sg:province":"VIC",
    "sg:tags":[
        "welding"
    ],
    "wof:name":"Shane O&#039;Neill Design & Associates",
    "wof:placetype":"venue"
},
  "geometry": {"coordinates":[145.21983337399999,-38.0005874634],"type":"Point"}
}