{
  "type": "Feature",
  "properties": {
    "addr:full":"63 Valfern Crt Dundowran QLD 4655",
    "addr:housenumber":"63",
    "addr:postcode":"4655",
    "addr:street":"Valfern Crt",
    "iso:country":"AU",
    "sg:address":"63 Valfern Crt",
    "sg:city":"Dundowran",
    "sg:classifiers":[
        {
            "category":"Building & Trades",
            "subcategory":"Construction",
            "type":"Services"
        }
    ],
    "sg:phone":"+61 7 4124 4004",
    "sg:postcode":"4655",
    "sg:province":"QLD",
    "sg:tags":[
        "earth",
        "excavating",
        "moving",
        "contractor"
    ],
    "wof:name":"Erroll Pearson Backhoe & Bobcat Excavators Hire",
    "wof:placetype":"venue"
},
  "geometry": {"coordinates":[152.78619399999999,-25.293257],"type":"Point"}
}