{
  "type": "Feature",
  "properties": {
    "addr:full":"139 Long St Smithfield NSW 2164",
    "addr:housenumber":"139",
    "addr:postcode":"2164",
    "addr:street":"Long St",
    "iso:country":"AU",
    "sg:address":"139 Long St",
    "sg:city":"Smithfield",
    "sg:classifiers":[
        {
            "category":"Manufacturing",
            "subcategory":"Tools & Machinery",
            "type":"Manufacturing & Wholesale Goods"
        }
    ],
    "sg:phone":"+61 2 9604 2851",
    "sg:postcode":"2164",
    "sg:province":"NSW",
    "sg:tags":[
        "crankshaft",
        "cylinder",
        "grinding"
    ],
    "wof:name":"Cavalier Engine Reconditioning",
    "wof:placetype":"venue"
},
  "geometry": {"coordinates":[150.93272399899999,-33.8410568237],"type":"Point"}
}