{
  "type": "Feature",
  "properties": {
    "iso:country":"AU",
    "sg:address":"48 Hill St",
    "sg:city":"Gawler South",
    "sg:classifiers":[
        {
            "category":"Shopping",
            "subcategory":"Music",
            "type":"Retail Goods"
        }
    ],
    "sg:phone":"+61 405 565 032",
    "sg:postcode":"5118",
    "sg:province":"SA",
    "sg:tags":[
        "instrument",
        "musical"
    ],
    "wof:name":"Four Dot Guitars",
    "wof:placetype":"venue"
},
  "geometry": {"coordinates":[138.748795,-34.609612],"type":"Point"}
}