{
  "type": "Feature",
  "properties": {
    "addr:full":"58 Paxton St Denman NSW 2328",
    "addr:housenumber":"58",
    "addr:postcode":"2328",
    "addr:street":"Paxton St",
    "iso:country":"AU",
    "sg:address":"58 Paxton St",
    "sg:city":"Denman",
    "sg:classifiers":[
        {
            "category":"Education",
            "subcategory":"School",
            "type":"Public Place"
        }
    ],
    "sg:phone":"+61 2 6547 2491",
    "sg:postcode":"2328",
    "sg:province":"NSW",
    "sg:tags":[
        "state",
        "-",
        "nsw"
    ],
    "wof:name":"Denman Public School",
    "wof:placetype":"venue"
},
  "geometry": {"coordinates":[150.68719482399999,-32.385093689],"type":"Point"}
}