{
  "type": "Feature",
  "properties": {
    "addr:full":"Suite 3/ 39 Lytton Rd East Brisbane QLD 4169",
    "addr:housenumber":"39",
    "addr:postcode":"4169",
    "addr:street":"Lytton Rd",
    "iso:country":"AU",
    "sg:address":"Suite 3/ 39 Lytton Rd",
    "sg:city":"East Brisbane",
    "sg:classifiers":[
        {
            "category":"Professional",
            "subcategory":"Detective & Security Services",
            "type":"Services"
        }
    ],
    "sg:phone":"+61 7 3391 7400",
    "sg:postcode":"4169",
    "sg:province":"QLD",
    "sg:tags":[
        "consultant",
        "system"
    ],
    "wof:name":"Universal Access",
    "wof:placetype":"venue"
},
  "geometry": {"coordinates":[153.041625977,-27.4787082672],"type":"Point"}
}