{
  "type": "Feature",
  "properties": {
    "addr:full":"2 Clay Crt Thomastown VIC 3074",
    "addr:housenumber":"2",
    "addr:postcode":"3074",
    "addr:street":"Clay Crt",
    "iso:country":"AU",
    "sg:address":"2 Clay Crt",
    "sg:city":"Thomastown",
    "sg:classifiers":[
        {
            "category":"Manufacturing",
            "subcategory":"Apparel",
            "type":"Manufacturing & Wholesale Goods"
        }
    ],
    "sg:phone":"+61 3 9469 5799",
    "sg:postcode":"3074",
    "sg:province":"VIC",
    "sg:tags":[
        "makers-up",
        "clothing"
    ],
    "wof:name":"Gold Star Clothing",
    "wof:placetype":"venue"
},
  "geometry": {"coordinates":[144.99168395999999,-37.6922302246],"type":"Point"}
}