{
  "type": "Feature",
  "properties": {
    "addr:full":"9 Pearl St Altona North VIC 3025",
    "addr:housenumber":"9",
    "addr:postcode":"3025",
    "addr:street":"Pearl St",
    "iso:country":"AU",
    "sg:address":"9 Pearl St",
    "sg:city":"Altona North",
    "sg:classifiers":[
        {
            "category":"Manufacturing",
            "subcategory":"Metals",
            "type":"Manufacturing & Wholesale Goods"
        }
    ],
    "sg:phone":"+61 3 9314 0545",
    "sg:postcode":"3025",
    "sg:province":"VIC",
    "sg:tags":[
        "sheet",
        "worker"
    ],
    "wof:name":"Star Sheetmetal Pty Ltd",
    "wof:placetype":"venue"
},
  "geometry": {"coordinates":[144.83215300000001,-37.823509],"type":"Point"}
}