{
  "type": "Feature",
  "properties": {
    "addr:full":"90 Sippy Downs Drv Sippy Downs QLD 4556",
    "addr:housenumber":"90",
    "addr:postcode":"4556",
    "addr:street":"Sippy Downs Drv",
    "iso:country":"AU",
    "sg:address":"90 Sippy Downs Drv",
    "sg:city":"Sippy Downs",
    "sg:classifiers":[
        {
            "category":"Professional",
            "subcategory":"Art Services",
            "type":"Services"
        }
    ],
    "sg:phone":"+61 7 5456 5024",
    "sg:postcode":"4556",
    "sg:province":"QLD",
    "sg:tags":[
        "graphic",
        "designer"
    ],
    "wof:name":"Six Degrees",
    "wof:placetype":"venue"
},
  "geometry": {"coordinates":[153.059158325,-26.7149963379],"type":"Point"}
}