{
  "type": "Feature",
  "properties": {
    "addr:full":"63 Helen St Bellevue WA 6056",
    "addr:housenumber":"63",
    "addr:postcode":"6056",
    "addr:street":"Helen St",
    "iso:country":"AU",
    "sg:address":"63 Helen St",
    "sg:city":"Bellevue",
    "sg:classifiers":[
        {
            "category":"Wholesale",
            "subcategory":"Scrap",
            "type":"Manufacturing & Wholesale Goods"
        }
    ],
    "sg:phone":"+61 8 9274 6344",
    "sg:postcode":"6056",
    "sg:province":"WA",
    "sg:tags":[
        "merchant",
        "metal"
    ],
    "wof:name":"Jolly Metal Recyclers",
    "wof:placetype":"venue"
},
  "geometry": {"coordinates":[116.021888733,-31.8983840942],"type":"Point"}
}