{
  "type": "Feature",
  "properties": {
    "addr:full":"312 Sydney Rd Balgowlah NSW 2093",
    "addr:housenumber":"312",
    "addr:postcode":"2093",
    "addr:street":"Sydney Rd",
    "iso:country":"AU",
    "sg:address":"312 Sydney Rd",
    "sg:city":"Balgowlah",
    "sg:classifiers":[
        {
            "category":"Fast Food",
            "type":"Food & Drink"
        }
    ],
    "sg:phone":"+61 2 9481 1111",
    "sg:postcode":"2093",
    "sg:province":"NSW",
    "sg:tags":[
        "away",
        "take"
    ],
    "wof:name":"Pizza Hut",
    "wof:placetype":"venue"
},
  "geometry": {"coordinates":[151.264526367,-33.7941513062],"type":"Point"}
}