{
  "type": "Feature",
  "properties": {
    "iso:country":"AU",
    "sg:address":"Cheltenham Shop 3071 Westfield Southland",
    "sg:city":"Cheltenham",
    "sg:classifiers":[
        {
            "category":"Recreation",
            "type":"Entertainment"
        }
    ],
    "sg:phone":"+61 3 9583 3627",
    "sg:postcode":"3192",
    "sg:province":"VIC",
    "sg:tags":[
        "supply",
        "outdoor",
        "adventure",
        "activity"
    ],
    "wof:name":"Aussie Disposals Pty Ltd",
    "wof:placetype":"venue"
},
  "geometry": {"coordinates":[145.033493042,-37.9687194824],"type":"Point"}
}