{
  "type": "Feature",
  "properties": {
    "iso:country":"AU",
    "sg:address":"175 Norton St",
    "sg:city":"Leichhardt",
    "sg:classifiers":[
        {
            "category":"Communications",
            "subcategory":"Film & Video Production",
            "type":"Services"
        }
    ],
    "sg:phone":"+61 2 9564 2820",
    "sg:postcode":"2040",
    "sg:province":"NSW",
    "sg:tags":[
        "dvd",
        "library"
    ],
    "wof:name":"Civic Video Pty Ltd",
    "wof:placetype":"venue"
},
  "geometry": {"coordinates":[151.15686,-33.880764],"type":"Point"}
}