{
  "type": "Feature",
  "properties": {
    "addr:full":"Shp 16 , Brassall Shopng Cntr Brassall QLD 4305",
    "addr:housenumber":"16",
    "addr:postcode":"4305",
    "addr:street":"Brassall Shopng Cntr",
    "iso:country":"AU",
    "sg:address":"Shp 16",
    "sg:city":", Brassall Shopng Cntr Brassall",
    "sg:classifiers":[
        {
            "category":"Banks & Credit Unions",
            "subcategory":"Bank",
            "type":"Services"
        }
    ],
    "sg:phone":"+61 13 20 32",
    "sg:postcode":"4305",
    "sg:province":"QLD",
    "wof:name":"Westpac",
    "wof:placetype":"venue"
},
  "geometry": {"coordinates":[152.74256897000001,-27.5875396729],"type":"Point"}
}