{
  "type": "Feature",
  "properties": {
    "addr:full":"25 Albert St Daylesford VIC 3460",
    "addr:housenumber":"25",
    "addr:postcode":"3460",
    "addr:street":"Albert St",
    "iso:country":"AU",
    "sg:address":"25 Albert St",
    "sg:city":"Daylesford",
    "sg:classifiers":[
        {
            "category":"Personal",
            "subcategory":"Day Spa",
            "type":"Services"
        }
    ],
    "sg:phone":"+61 3 5348 2331",
    "sg:postcode":"3460",
    "sg:province":"VIC",
    "wof:name":"Daylesford Day Spa",
    "wof:placetype":"venue"
},
  "geometry": {"coordinates":[144.142303467,-37.3413276672],"type":"Point"}
}