{
  "type": "Feature",
  "properties": {
    "addr:full":"32 Trentbridge Crt Mt Nathan QLD 4211",
    "addr:housenumber":"32",
    "addr:postcode":"4211",
    "addr:street":"Trentbridge Crt;Nathan",
    "iso:country":"AU",
    "sg:address":"32 Trentbridge Crt",
    "sg:city":"Mt Nathan",
    "sg:classifiers":[
        {
            "category":"Building & Trades",
            "subcategory":"Construction",
            "type":"Services"
        }
    ],
    "sg:phone":"+61 417 712 174",
    "sg:postcode":"4211",
    "sg:province":"QLD",
    "sg:tags":[
        "home",
        "air conditioning"
    ],
    "wof:name":"Coolzone Air Conditioning",
    "wof:placetype":"venue"
},
  "geometry": {"coordinates":[153.275756836,-27.9791545868],"type":"Point"}
}