{
  "type": "Feature",
  "properties": {
    "addr:full":"105 Orange Ave Mildura VIC 3500",
    "addr:housenumber":"105",
    "addr:postcode":"3500",
    "addr:street":"Orange Ave",
    "iso:country":"AU",
    "sg:address":"105 Orange Ave",
    "sg:city":"Mildura",
    "sg:classifiers":[
        {
            "category":"Professional",
            "subcategory":"Employment Agencies",
            "type":"Services"
        }
    ],
    "sg:phone":"+61 3 5023 8840",
    "sg:postcode":"3500",
    "sg:province":"VIC",
    "wof:name":"Altus Business Consulting",
    "wof:placetype":"venue"
},
  "geometry": {"coordinates":[142.161941528,-34.1890106201],"type":"Point"}
}