{
  "type": "Feature",
  "properties": {
    "iso:country":"AU",
    "sg:address":"33 Hinton St",
    "sg:city":"Underdale",
    "sg:classifiers":[
        {
            "category":"Building & Trades",
            "subcategory":"Plumbing",
            "type":"Services"
        }
    ],
    "sg:phone":"+61 8 8443 4241",
    "sg:postcode":"5032",
    "sg:province":"SA",
    "sg:tags":[
        "plumber",
        "gasfitters"
    ],
    "wof:name":"Barry Robertson",
    "wof:placetype":"venue"
},
  "geometry": {"coordinates":[138.54461669899999,-34.9212417603],"type":"Point"}
}