{
  "type": "Feature",
  "properties": {
    "addr:full":"Prince of Wales Private Hsptl Barker St Randwick NSW 2031",
    "addr:postcode":"2031",
    "addr:street":"Barker St",
    "iso:country":"AU",
    "sg:address":"Prince of Wales Private Hsptl Barker St",
    "sg:city":"Randwick",
    "sg:classifiers":[
        {
            "category":"Health Services",
            "subcategory":"Doctor",
            "type":"Services"
        }
    ],
    "sg:phone":"+61 2 9650 4976",
    "sg:postcode":"2031",
    "sg:province":"NSW",
    "sg:tags":[
        "medical",
        "practitioner"
    ],
    "wof:name":"Murray I P C",
    "wof:placetype":"venue"
},
  "geometry": {"coordinates":[151.24273681599999,-33.921787262],"type":"Point"}
}