{
  "type": "Feature",
  "properties": {
    "addr:full":"149 Camden Rd Douglas Park NSW 2569",
    "addr:housenumber":"149",
    "addr:postcode":"2569",
    "addr:street":"Camden Rd",
    "iso:country":"AU",
    "sg:address":"149 Camden Rd",
    "sg:city":"Douglas Park",
    "sg:classifiers":[
        {
            "category":"Manufacturing",
            "subcategory":"Building Materials",
            "type":"Manufacturing & Wholesale Goods"
        }
    ],
    "sg:phone":"+61 2 4632 7096",
    "sg:postcode":"2569",
    "sg:province":"NSW",
    "sg:tags":[
        "concrete",
        "product"
    ],
    "wof:name":"The Pot Works",
    "wof:placetype":"venue"
},
  "geometry": {"coordinates":[150.7109375,-34.1828041077],"type":"Point"}
}