{
  "type": "Feature",
  "properties": {
    "iso:country":"AU",
    "sg:address":"486 Burwood Hwy",
    "sg:city":"Vermont",
    "sg:classifiers":[
        {
            "category":"Health Services",
            "subcategory":"Doctor",
            "type":"Services"
        }
    ],
    "sg:phone":"+61 3 9887 8188",
    "sg:postcode":"3133",
    "sg:province":"VIC",
    "sg:tags":[
        "medical",
        "practitioner"
    ],
    "wof:name":"Vasectomy Centres Of Melbourne",
    "wof:placetype":"venue"
},
  "geometry": {"coordinates":[145.183227539,-37.8567848206],"type":"Point"}
}