{
  "type": "Feature",
  "properties": {
    "addr:full":"47 Wason St Milton NSW 2538",
    "addr:housenumber":"47",
    "addr:postcode":"2538",
    "addr:street":"Wason St",
    "iso:country":"AU",
    "sg:address":"47 Wason St",
    "sg:city":"Milton",
    "sg:classifiers":[
        {
            "category":"Professional",
            "subcategory":"Accounting & Tax Preparation",
            "type":"Services"
        }
    ],
    "sg:phone":"+61 2 4455 1338",
    "sg:postcode":"2538",
    "sg:province":"NSW",
    "sg:tags":[
        "accountant",
        "auditor"
    ],
    "wof:name":"Thomson J N A",
    "wof:placetype":"venue"
},
  "geometry": {"coordinates":[150.435623169,-35.3170433044],"type":"Point"}
}