{
  "type": "Feature",
  "properties": {
    "addr:full":"4 Gordon St Newstead QLD 4006",
    "addr:housenumber":"4",
    "addr:postcode":"4006",
    "addr:street":"Gordon St",
    "iso:country":"AU",
    "sg:address":"4 Gordon St",
    "sg:city":"Newstead",
    "sg:classifiers":[
        {
            "category":"Communications",
            "type":"Services"
        }
    ],
    "sg:phone":"+61 7 3252 4433",
    "sg:postcode":"4006",
    "sg:province":"QLD",
    "sg:tags":[
        "public",
        "system",
        "address"
    ],
    "wof:name":"Richardson & Devine Pty Ltd",
    "wof:placetype":"venue"
},
  "geometry": {"coordinates":[153.04457092300001,-27.4478683472],"type":"Point"}
}