{
  "type": "Feature",
  "properties": {
    "addr:full":"67 Eton Rd Cambridge Park NSW 2747",
    "addr:housenumber":"67",
    "addr:postcode":"2747",
    "addr:street":"Eton Rd",
    "iso:country":"AU",
    "sg:address":"67 Eton Rd",
    "sg:city":"Cambridge Park",
    "sg:classifiers":[
        {
            "category":"Utilities",
            "subcategory":"Water",
            "type":"Services"
        }
    ],
    "sg:phone":"+61 418 298 395",
    "sg:postcode":"2747",
    "sg:province":"NSW",
    "sg:tags":[
        "hot",
        "system"
    ],
    "wof:name":"Trent Beckwith Plumbing",
    "wof:placetype":"venue"
},
  "geometry": {"coordinates":[150.717697144,-33.7437171936],"type":"Point"}
}