{
  "type": "Feature",
  "properties": {
    "iso:country":"AU",
    "sg:address":"UNIT 4/ 8 diamond Pl",
    "sg:city":"Runcorn",
    "sg:classifiers":[
        {
            "category":"Travel",
            "subcategory":"Hostel",
            "type":"Entertainment"
        }
    ],
    "sg:phone":"+61 7 3456 7799",
    "sg:postcode":"4113",
    "sg:province":"QLD",
    "sg:tags":[
        "home"
    ],
    "wof:name":"sunny bank approach",
    "wof:placetype":"venue"
},
  "geometry": {"coordinates":[153.07623290999999,-27.5871238708],"type":"Point"}
}