{
  "type": "Feature",
  "properties": {
    "iso:country":"AU",
    "sg:address":"27 Buckley Rd",
    "sg:city":"Burpengary",
    "sg:classifiers":[
        {
            "category":"Travel",
            "subcategory":"Hostel",
            "type":"Entertainment"
        }
    ],
    "sg:phone":"+61 7 3888 2857",
    "sg:postcode":"4505",
    "sg:province":"QLD",
    "sg:tags":[
        "home"
    ],
    "wof:name":"United Disabled Servicemans Assoc UDSA Memorial Home",
    "wof:placetype":"venue"
},
  "geometry": {"coordinates":[152.97915649399999,-27.1462745667],"type":"Point"}
}