{
  "type": "Feature",
  "properties": {
    "addr:full":"353 Settlement Rd Thomastown VIC 3074",
    "addr:housenumber":"353",
    "addr:postcode":"3074",
    "addr:street":"Settlement Rd",
    "iso:country":"AU",
    "sg:address":"353 Settlement Rd",
    "sg:city":"Thomastown",
    "sg:classifiers":[
        {
            "category":"Retail",
            "subcategory":"Auto Repair",
            "type":"Services"
        }
    ],
    "sg:phone":"+61 3 9466 4499",
    "sg:postcode":"3074",
    "sg:province":"VIC",
    "sg:tags":[
        "transmission",
        "automotive",
        "car"
    ],
    "wof:name":"Second-Hand Transmission Parts Company",
    "wof:placetype":"venue"
},
  "geometry": {"coordinates":[145.02008056599999,-37.6887893677],"type":"Point"}
}