{
  "type": "Feature",
  "properties": {
    "addr:full":"Tasman Hwy Buckland TAS 7190",
    "addr:postcode":"7190",
    "addr:street":"Tasman Hwy",
    "iso:country":"AU",
    "sg:address":"Tasman Hwy",
    "sg:city":"Buckland",
    "sg:classifiers":[
        {
            "category":"Professional",
            "subcategory":"Art Services",
            "type":"Services"
        }
    ],
    "sg:phone":"+61 400 753 998",
    "sg:postcode":"7190",
    "sg:province":"TAS",
    "sg:tags":[
        "sculptor"
    ],
    "wof:name":"Ron Krulow",
    "wof:placetype":"venue"
},
  "geometry": {"coordinates":[147.71871899999999,-42.608105],"type":"Point"}
}