{
  "type": "Feature",
  "properties": {
    "addr:full":"101 Albany Hwy Kojonup WA 6395",
    "addr:housenumber":"101",
    "addr:postcode":"6395",
    "addr:street":"Albany Hwy",
    "iso:country":"AU",
    "sg:address":"101 Albany Hwy",
    "sg:city":"Kojonup",
    "sg:classifiers":[
        {
            "category":"Personal",
            "subcategory":"Beauty Salon",
            "type":"Services"
        }
    ],
    "sg:phone":"+61 8 9831 1261",
    "sg:postcode":"6395",
    "sg:province":"WA",
    "sg:tags":[
        "hairdresser"
    ],
    "wof:name":"Curly Wig Salon",
    "wof:placetype":"venue"
},
  "geometry": {"coordinates":[117.15924835200001,-33.8354721069],"type":"Point"}
}