{
  "type": "Feature",
  "properties": {
    "iso:country":"AU",
    "sg:address":"Shop 56, 75 Joondalup Drv",
    "sg:city":"Edgewater",
    "sg:classifiers":[
        {
            "category":"Shopping",
            "subcategory":"Gifts & Souvenirs",
            "type":"Retail Goods"
        }
    ],
    "sg:phone":"+61 8 9300 3710",
    "sg:postcode":"6027",
    "sg:province":"WA",
    "sg:tags":[
        "shop",
        "supply"
    ],
    "wof:name":"Mikasa Factory Outlet",
    "wof:placetype":"venue"
},
  "geometry": {"coordinates":[115.781967163,-31.771987915],"type":"Point"}
}