{
  "type": "Feature",
  "properties": {
    "addr:full":"409 Milton Rd Auchenflower QLD 4066",
    "addr:housenumber":"409",
    "addr:postcode":"4066",
    "addr:street":"Milton Rd",
    "iso:country":"AU",
    "sg:address":"409 Milton Rd",
    "sg:city":"Auchenflower",
    "sg:classifiers":[
        {
            "category":"Personal",
            "subcategory":"Beauty Salon",
            "type":"Services"
        }
    ],
    "sg:phone":"+61 7 3871 2151",
    "sg:postcode":"4066",
    "sg:province":"QLD",
    "sg:tags":[
        "hairdresser"
    ],
    "wof:name":"Ferrini Hair Studio",
    "wof:placetype":"venue"
},
  "geometry": {"coordinates":[152.99531555199999,-27.4738616943],"type":"Point"}
}