{
  "type": "Feature",
  "properties": {
    "iso:country":"AU",
    "sg:address":"39 Moreton Ave",
    "sg:city":"Kingsgrove",
    "sg:classifiers":[
        {
            "category":"Professional",
            "subcategory":"Management & Consulting",
            "type":"Services"
        }
    ],
    "sg:phone":"+61 2 9502 1109",
    "sg:postcode":"2208",
    "sg:province":"NSW",
    "sg:tags":[
        "consultant",
        "migration"
    ],
    "wof:name":"Advent Migration Services",
    "wof:placetype":"venue"
},
  "geometry": {"coordinates":[151.098648,-33.94511],"type":"Point"}
}