{
  "type": "Feature",
  "properties": {
    "addr:full":"51 Sherwood Rd Toowong QLD 4066",
    "addr:housenumber":"51",
    "addr:postcode":"4066",
    "addr:street":"Sherwood Rd",
    "iso:country":"AU",
    "sg:address":"51 Sherwood Rd",
    "sg:city":"Toowong",
    "sg:classifiers":[
        {
            "category":"Personal",
            "subcategory":"Beauty Salon",
            "type":"Services"
        }
    ],
    "sg:phone":"+61 7 3870 8366",
    "sg:postcode":"4066",
    "sg:province":"QLD",
    "sg:tags":[
        "hairdresser"
    ],
    "wof:name":"Village Hairdressers",
    "wof:placetype":"venue"
},
  "geometry": {"coordinates":[152.99075317399999,-27.4851856232],"type":"Point"}
}