{
  "type": "Feature",
  "properties": {
    "addr:full":"1018 Murrindindi Rd Murrindindi VIC 3717",
    "addr:postcode":"1018;3717",
    "addr:street":"Murrindindi Rd",
    "iso:country":"AU",
    "sg:address":"1018 Murrindindi Rd",
    "sg:city":"Murrindindi",
    "sg:classifiers":[
        {
            "category":"Farming",
            "subcategory":"Vineyard",
            "type":"Manufacturing & Wholesale Goods"
        }
    ],
    "sg:phone":"+61 3 5797 8330",
    "sg:postcode":"3717",
    "sg:province":"VIC",
    "sg:tags":[
        "winery"
    ],
    "wof:name":"Yea Valley Vineyard Pty Ltd",
    "wof:placetype":"venue"
},
  "geometry": {"coordinates":[145.50953674300001,-37.3499679565],"type":"Point"}
}