{
  "type": "Feature",
  "properties": {
    "iso:country":"AU",
    "sg:address":"1117 Main Rd",
    "sg:city":"Eltham",
    "sg:classifiers":[
        {
            "category":"Government",
            "subcategory":"Court House",
            "type":"Public Place"
        }
    ],
    "sg:phone":"+61 3 9431 3933",
    "sg:postcode":"3095",
    "sg:province":"VIC",
    "sg:tags":[
        "personal",
        "marriage",
        "family",
        "counselling"
    ],
    "wof:name":"Trathen Salli",
    "wof:placetype":"venue"
},
  "geometry": {"coordinates":[145.14956665,-37.7078399658],"type":"Point"}
}