{
  "type": "Feature",
  "properties": {
    "iso:country":"AU",
    "sg:address":"378 Goodwood Rd",
    "sg:city":"Goodwood",
    "sg:classifiers":[
        {
            "category":"Health Services",
            "subcategory":"Chiropractor",
            "type":"Services"
        }
    ],
    "sg:phone":"+61 8 8373 3896",
    "sg:postcode":"5034",
    "sg:province":"SA",
    "wof:name":"ChiroPartners SA",
    "wof:placetype":"venue"
},
  "geometry": {"coordinates":[138.58970642099999,-34.952091217],"type":"Point"}
}