{
  "type": "Feature",
  "properties": {
    "addr:full":"PO Box 145 Denman NSW 2328",
    "addr:postcode":"2328",
    "iso:country":"AU",
    "sg:address":"PO Box 145",
    "sg:city":"Denman",
    "sg:classifiers":[
        {
            "category":"Parking",
            "type":"Transportation"
        }
    ],
    "sg:phone":"+61 2 6547 4470",
    "sg:postcode":"2328",
    "sg:province":"NSW",
    "sg:tags":[
        "branding",
        "animal"
    ],
    "wof:name":"D-C Freeze Branding Services",
    "wof:placetype":"venue"
},
  "geometry": {"coordinates":[150.68443298299999,-32.3875198364],"type":"Point"}
}