{
  "type": "Feature",
  "properties": {
    "addr:full":"494 Rocky Point Rd Sans Souci NSW 2219",
    "addr:housenumber":"494",
    "addr:postcode":"2219",
    "addr:street":"Rocky Point Rd",
    "iso:country":"AU",
    "sg:address":"494 Rocky Point Rd",
    "sg:city":"Sans Souci",
    "sg:classifiers":[
        {
            "category":"Fast Food",
            "type":"Food & Drink"
        }
    ],
    "sg:phone":"+61 2 9529 4422",
    "sg:postcode":"2219",
    "sg:province":"NSW",
    "sg:tags":[
        "away",
        "take"
    ],
    "wof:name":"McDonald's Family Restaurants",
    "wof:placetype":"venue"
},
  "geometry": {"coordinates":[151.132858,-33.991425],"type":"Point"}
}