{
  "type": "Feature",
  "properties": {
    "addr:full":"102 George St Redfern NSW 2016",
    "addr:housenumber":"102",
    "addr:postcode":"2016",
    "addr:street":"George St",
    "iso:country":"AU",
    "sg:address":"102 George St",
    "sg:city":"Redfern",
    "sg:classifiers":[
        {
            "category":"Shopping",
            "subcategory":"Shoes",
            "type":"Retail Goods"
        }
    ],
    "sg:phone":"+61 2 9319 5579",
    "sg:postcode":"2016",
    "sg:province":"NSW",
    "sg:tags":[
        "footwear"
    ],
    "wof:name":"102 Shoes",
    "wof:placetype":"venue"
},
  "geometry": {"coordinates":[151.20205688499999,-33.8924102783],"type":"Point"}
}