{
  "type": "Feature",
  "properties": {
    "addr:full":"Shop 11 1- 3 Eastwood St Ballarat VIC 3350",
    "addr:housenumber":"shop 11;3",
    "addr:postcode":"3350",
    "addr:street":"1;St",
    "iso:country":"AU",
    "sg:address":"Shop 11 1- 3 Eastwood St",
    "sg:city":"Ballarat",
    "sg:classifiers":[
        {
            "category":"Shopping",
            "subcategory":"Discount & Variety Stores",
            "type":"Retail Goods"
        }
    ],
    "sg:phone":"+61 3 5333 2277",
    "sg:postcode":"3350",
    "sg:province":"VIC",
    "sg:tags":[
        "register",
        "cash"
    ],
    "wof:name":"Webb Office Services",
    "wof:placetype":"venue"
},
  "geometry": {"coordinates":[143.861176,-37.564484],"type":"Point"}
}