{
  "type": "Feature",
  "properties": {
    "addr:full":"43 James St Burleigh Heads QLD 4220",
    "addr:housenumber":"43",
    "addr:postcode":"4220",
    "addr:street":"James St",
    "iso:country":"AU",
    "sg:address":"43 James St",
    "sg:city":"Burleigh Heads",
    "sg:classifiers":[
        {
            "category":"Real Estate",
            "subcategory":"Surveying",
            "type":"Services"
        }
    ],
    "sg:phone":"+61 7 5535 6233",
    "sg:postcode":"4220",
    "sg:province":"QLD",
    "sg:tags":[
        "map",
        "mapping"
    ],
    "wof:name":"MERIDIAN MAPS",
    "wof:placetype":"venue"
},
  "geometry": {"coordinates":[153.450317383,-28.089094162],"type":"Point"}
}