{
  "type": "Feature",
  "properties": {
    "addr:full":"Suite 1 102 Main Rd Diamond Creek VIC 3089",
    "addr:housenumber":"102",
    "addr:postcode":"3089",
    "addr:street":"Main Rd",
    "iso:country":"AU",
    "sg:address":"Suite 1 102 Main Rd",
    "sg:city":"Diamond Creek",
    "sg:classifiers":[
        {
            "category":"Health Services",
            "subcategory":"Health Practitioner",
            "type":"Services"
        }
    ],
    "sg:phone":"+61 3 9438 5366",
    "sg:postcode":"3089",
    "sg:province":"VIC",
    "sg:tags":[
        "naturopath"
    ],
    "wof:name":"Hayward I J",
    "wof:placetype":"venue"
},
  "geometry": {"coordinates":[145.18150299999999,-37.665768],"type":"Point"}
}