{
  "type": "Feature",
  "properties": {
    "addr:full":"Ross Ave Flinders Park SA 5025",
    "addr:postcode":"5025",
    "addr:street":"Ross Ave Flinders",
    "iso:country":"AU",
    "sg:address":"Ross Ave",
    "sg:city":"Flinders Park",
    "sg:classifiers":[
        {
            "category":"Education",
            "subcategory":"Kindergarten",
            "type":"Public Place"
        }
    ],
    "sg:phone":"+61 8 8346 1668",
    "sg:postcode":"5025",
    "sg:province":"SA",
    "sg:tags":[
        "pre-schools"
    ],
    "wof:name":"Jean Horan Kindergarten",
    "wof:placetype":"venue"
},
  "geometry": {"coordinates":[138.548904419,-34.9074211121],"type":"Point"}
}