{
  "type": "Feature",
  "properties": {
    "addr:full":"21 Sutherland Ave Paddington NSW 2021",
    "addr:housenumber":"21",
    "addr:postcode":"2021",
    "addr:street":"Sutherland Ave",
    "iso:country":"AU",
    "sg:address":"21 Sutherland Ave",
    "sg:city":"Paddington",
    "sg:classifiers":[
        {
            "category":"Professional",
            "subcategory":"Management & Consulting",
            "type":"Services"
        }
    ],
    "sg:phone":"+61 2 9363 4067",
    "sg:postcode":"2021",
    "sg:province":"NSW",
    "sg:tags":[
        "consultant"
    ],
    "wof:name":"Calkin Jenny & Associates",
    "wof:placetype":"venue"
},
  "geometry": {"coordinates":[151.23582458499999,-33.884185791],"type":"Point"}
}