{
  "type": "Feature",
  "properties": {
    "addr:full":"Cnr Racecourse Rd & Kent St Ascot QLD 4007",
    "addr:postcode":"4007",
    "addr:street":"Racecourse Rd & Kent St",
    "iso:country":"AU",
    "sg:address":"Cnr Racecourse Rd & Kent St",
    "sg:city":"Ascot",
    "sg:classifiers":[
        {
            "category":"Food & Beverages",
            "subcategory":"Supermarket",
            "type":"Retail Goods"
        }
    ],
    "sg:phone":"+61 7 3268 6970",
    "sg:postcode":"4007",
    "sg:province":"QLD",
    "sg:tags":[
        "grocery",
        "store"
    ],
    "wof:name":"Woolworths Metro",
    "wof:placetype":"venue"
},
  "geometry": {"coordinates":[153.065414,-27.432249],"type":"Point"}
}