{
  "type": "Feature",
  "properties": {
    "addr:full":"PO Box 78 Warrandyte VIC 3113",
    "addr:postcode":"3113",
    "iso:country":"AU",
    "sg:address":"PO Box 78",
    "sg:city":"Warrandyte",
    "sg:classifiers":[
        {
            "category":"Farming",
            "subcategory":"Farm & Veterinary Services",
            "type":"Manufacturing & Wholesale Goods"
        }
    ],
    "sg:phone":"+61 3 9844 1100",
    "sg:postcode":"3113",
    "sg:province":"VIC",
    "sg:tags":[
        "contracting"
    ],
    "wof:name":"Spenell Pastoral Pty Ltd",
    "wof:placetype":"venue"
},
  "geometry": {"coordinates":[145.23545837399999,-37.747379303],"type":"Point"}
}