{
  "type": "Feature",
  "properties": {
    "addr:full":"2/Lot 5 Depot Rd Mudgee NSW 2850",
    "addr:housenumber":"/;5",
    "addr:postcode":"2850",
    "addr:street":"Lot;Depot Rd",
    "iso:country":"AU",
    "sg:address":"2/Lot 5 Depot Rd",
    "sg:city":"Mudgee",
    "sg:classifiers":[
        {
            "category":"Freight",
            "type":"Transportation"
        }
    ],
    "sg:phone":"+61 2 6372 2804",
    "sg:postcode":"2850",
    "sg:province":"NSW",
    "sg:tags":[
        "light",
        "carrier"
    ],
    "wof:name":"Security Express Wards Skyrdad",
    "wof:placetype":"venue"
},
  "geometry": {"coordinates":[149.600525,-32.609512],"type":"Point"}
}