{
  "type": "Feature",
  "properties": {
    "addr:full":"Suite 5 / 30a Hardy St Lilydale VIC 3140",
    "addr:housenumber":"/ 30a",
    "addr:postcode":"3140",
    "addr:street":"Hardy St",
    "iso:country":"AU",
    "sg:address":"Suite 5 / 30a Hardy St",
    "sg:city":"Lilydale",
    "sg:classifiers":[
        {
            "category":"Health Services",
            "subcategory":"Dentist",
            "type":"Services"
        }
    ],
    "sg:phone":"+61 3 9735 5533",
    "sg:postcode":"3140",
    "sg:province":"VIC",
    "wof:name":"Prokop Dr Mariola",
    "wof:placetype":"venue"
},
  "geometry": {"coordinates":[145.35188293499999,-37.7588233948],"type":"Point"}
}