{
  "type": "Feature",
  "properties": {
    "addr:full":"6 Zambesi Drv Mandurah WA 6210",
    "addr:housenumber":"6",
    "addr:postcode":"6210",
    "addr:street":"Zambesi Drv",
    "iso:country":"AU",
    "sg:address":"6 Zambesi Drv",
    "sg:city":"Mandurah",
    "sg:classifiers":[
        {
            "category":"Home & Garden",
            "subcategory":"Building Materials",
            "type":"Retail Goods"
        }
    ],
    "sg:phone":"+61 8 9535 8831",
    "sg:postcode":"6210",
    "sg:province":"WA",
    "sg:tags":[
        "lawn",
        "cutting",
        "maintenance"
    ],
    "wof:name":"Sarah & Terry's Garden & Lawncare",
    "wof:placetype":"venue"
},
  "geometry": {"coordinates":[115.75042000000001,-32.535973],"type":"Point"}
}