{
  "type": "Feature",
  "properties": {
    "addr:full":"7a Tina St Beaudesert QLD 4285",
    "addr:housenumber":"7a",
    "addr:postcode":"4285",
    "addr:street":"Tina St",
    "iso:country":"AU",
    "sg:address":"7a Tina St",
    "sg:city":"Beaudesert",
    "sg:classifiers":[
        {
            "category":"Retail",
            "subcategory":"Repair Shop",
            "type":"Services"
        }
    ],
    "sg:phone":"+61 1800 253 536",
    "sg:postcode":"4285",
    "sg:province":"QLD",
    "sg:tags":[
        "repairing",
        "piano",
        "tuning"
    ],
    "wof:name":"Braitlings Since 1888",
    "wof:placetype":"venue"
},
  "geometry": {"coordinates":[153.00202899999999,-27.990454],"type":"Point"}
}