{
  "type": "Feature",
  "properties": {
    "addr:full":"30 Byass St Shepparton VIC 3630",
    "addr:housenumber":"30",
    "addr:postcode":"3630",
    "addr:street":"Byass St",
    "iso:country":"AU",
    "sg:address":"30 Byass St",
    "sg:city":"Shepparton",
    "sg:classifiers":[
        {
            "category":"Home & Garden",
            "subcategory":"Building Materials",
            "type":"Retail Goods"
        }
    ],
    "sg:phone":"+61 3 5821 7277",
    "sg:postcode":"3630",
    "sg:province":"VIC",
    "sg:tags":[
        "supply"
    ],
    "wof:name":"Shepparton Building Supplies",
    "wof:placetype":"venue"
},
  "geometry": {"coordinates":[145.41403198200001,-36.3798561096],"type":"Point"}
}