{
  "type": "Feature",
  "properties": {
    "iso:country":"AU",
    "sg:address":"1st Floor 352 Main Rd West",
    "sg:city":"St Albans",
    "sg:classifiers":[
        {
            "category":"Health Services",
            "subcategory":"Dentist",
            "type":"Services"
        }
    ],
    "sg:phone":"+61 3 9366 0684",
    "sg:postcode":"3021",
    "sg:province":"VIC",
    "wof:name":"Kang In Lee",
    "wof:placetype":"venue"
},
  "geometry": {"coordinates":[144.770538,-37.74107],"type":"Point"}
}