{
  "type": "Feature",
  "properties": {
    "addr:full":"4 Caladenia Rd Walliston WA 6076",
    "addr:housenumber":"4",
    "addr:postcode":"6076",
    "addr:street":"Caladenia Rd",
    "iso:country":"AU",
    "sg:address":"4 Caladenia Rd",
    "sg:city":"Walliston",
    "sg:classifiers":[
        {
            "category":"Building & Trades",
            "subcategory":"Cleaning & Sanitation",
            "type":"Services"
        }
    ],
    "sg:phone":"+61 418 904 415",
    "sg:postcode":"6076",
    "sg:province":"WA",
    "sg:tags":[
        "cleaner",
        "repairer",
        "roof"
    ],
    "wof:name":"Blue Sky Contractors",
    "wof:placetype":"venue"
},
  "geometry": {"coordinates":[116.07379913299999,-31.9965648651],"type":"Point"}
}