{
  "type": "Feature",
  "properties": {
    "addr:full":"20 Zanker Ave Stirling North SA 5710",
    "addr:housenumber":"20",
    "addr:postcode":"5710",
    "addr:street":"Zanker Ave",
    "iso:country":"AU",
    "sg:address":"20 Zanker Ave",
    "sg:city":"Stirling North",
    "sg:classifiers":[
        {
            "category":"Home & Garden",
            "subcategory":"Carpets & Floor Coverings",
            "type":"Retail Goods"
        }
    ],
    "sg:phone":"+61 8 8643 6097",
    "sg:postcode":"5710",
    "sg:province":"SA",
    "sg:tags":[
        "tile",
        "wall",
        "layer"
    ],
    "wof:name":"Gerlach Home Improvements",
    "wof:placetype":"venue"
},
  "geometry": {"coordinates":[137.84472656200001,-32.5202407837],"type":"Point"}
}