{
  "type": "Feature",
  "properties": {
    "addr:full":"Shop 16, Gungahlin Market Place Gungahlin ACT 2912",
    "addr:housenumber":"shop 16",
    "addr:postcode":"2912",
    "addr:street":"Market Place",
    "iso:country":"AU",
    "sg:address":"Shop 16, Gungahlin Market Place",
    "sg:city":"Gungahlin",
    "sg:classifiers":[
        {
            "category":"Personal",
            "subcategory":"Beauty Salon",
            "type":"Services"
        }
    ],
    "sg:phone":"+61 2 6241 9855",
    "sg:postcode":"2912",
    "sg:province":"ACT",
    "sg:tags":[
        "hairdresser"
    ],
    "wof:name":"Time Hair Design",
    "wof:placetype":"venue"
},
  "geometry": {"coordinates":[149.135665894,-35.183506012],"type":"Point"}
}