{
  "type": "Feature",
  "properties": {
    "addr:full":"14 Edmondstone St Newmarket QLD 4051",
    "addr:housenumber":"14",
    "addr:postcode":"4051",
    "addr:street":"Edmondstone St",
    "iso:country":"AU",
    "sg:address":"14 Edmondstone St",
    "sg:city":"Newmarket",
    "sg:classifiers":[
        {
            "category":"Education",
            "subcategory":"Kindergarten",
            "type":"Public Place"
        }
    ],
    "sg:phone":"+61 7 3552 5333",
    "sg:postcode":"4051",
    "sg:province":"QLD",
    "sg:tags":[
        "pre-schools"
    ],
    "wof:name":"Creche & Kindergarten Association of Queensland",
    "wof:placetype":"venue"
},
  "geometry": {"coordinates":[153.00828552199999,-27.4378585815],"type":"Point"}
}