{
  "type": "Feature",
  "properties": {
    "addr:full":"368 Sussex St Sydney NSW 2000",
    "addr:housenumber":"368",
    "addr:postcode":"2000",
    "addr:street":"Sussex St",
    "iso:country":"AU",
    "sg:address":"368 Sussex St",
    "sg:city":"Sydney",
    "sg:classifiers":[
        {
            "category":"Travel",
            "subcategory":"Travel Agent",
            "type":"Entertainment"
        }
    ],
    "sg:phone":"+61 2 9283 3358",
    "sg:postcode":"2000",
    "sg:province":"NSW",
    "sg:tags":[
        "consultant"
    ],
    "wof:name":"Aviation Travel Services",
    "wof:placetype":"venue"
},
  "geometry": {"coordinates":[151.20469665499999,-33.8762512207],"type":"Point"}
}