{
  "type": "Feature",
  "properties": {
    "iso:country":"AU",
    "sg:address":"94 Essington Lewis Ave",
    "sg:city":"Whyalla",
    "sg:classifiers":[
        {
            "category":"Manufacturing",
            "subcategory":"Motor Vehicles & Parts",
            "type":"Manufacturing & Wholesale Goods"
        }
    ],
    "sg:phone":"+61 8 8645 7311",
    "sg:postcode":"5600",
    "sg:province":"SA",
    "sg:tags":[
        "replacement"
    ],
    "wof:name":"Sprint Auto Parts Pty Ltd",
    "wof:placetype":"venue"
},
  "geometry": {"coordinates":[137.573013,-33.037548],"type":"Point"}
}