{
  "type": "Feature",
  "properties": {
    "addr:full":"Shp 10/ 211 Latrobe St Melbourne VIC 3000",
    "addr:housenumber":"10 / 211",
    "addr:postcode":"3000",
    "addr:street":"Latrobe St",
    "iso:country":"AU",
    "sg:address":"Shp 10/ 211 Latrobe St",
    "sg:city":"Melbourne",
    "sg:classifiers":[
        {
            "category":"Personal",
            "subcategory":"Beauty Salon",
            "type":"Services"
        }
    ],
    "sg:phone":"+61 3 9663 7274",
    "sg:postcode":"3000",
    "sg:province":"VIC",
    "sg:tags":[
        "hairdresser"
    ],
    "wof:name":"Barber On Central",
    "wof:placetype":"venue"
},
  "geometry": {"coordinates":[144.963424683,-37.8098258972],"type":"Point"}
}