{
  "type": "Feature",
  "properties": {
    "iso:country":"AU",
    "sg:address":"41 Chifley Ave",
    "sg:city":"Sefton",
    "sg:classifiers":[
        {
            "category":"Utilities",
            "type":"Services"
        }
    ],
    "sg:phone":"+61 429 900 510",
    "sg:postcode":"2162",
    "sg:province":"NSW",
    "sg:tags":[
        "refrigeration",
        "industrial",
        "commercial",
        "retail"
    ],
    "wof:name":"Continental Commercial Refrigeration",
    "wof:placetype":"venue"
},
  "geometry": {"coordinates":[151.00862121599999,-33.8807029724],"type":"Point"}
}