{
  "type": "Feature",
  "properties": {
    "addr:full":"Factory 2/ 3 Rosella St Frankston VIC 3199",
    "addr:housenumber":"/ 3",
    "addr:postcode":"3199",
    "addr:street":"Rosella St",
    "iso:country":"AU",
    "sg:address":"Factory 2/ 3 Rosella St",
    "sg:city":"Frankston",
    "sg:classifiers":[
        {
            "category":"Retail",
            "subcategory":"Auto Repair",
            "type":"Services"
        }
    ],
    "sg:phone":"+61 3 9781 3260",
    "sg:postcode":"3199",
    "sg:province":"VIC",
    "sg:tags":[
        "repairer",
        "motor",
        "engineer"
    ],
    "wof:name":"Gotech",
    "wof:placetype":"venue"
},
  "geometry": {"coordinates":[145.126663208,-38.1307067871],"type":"Point"}
}