{
  "type": "Feature",
  "properties": {
    "addr:full":"Shp2/ 1 Transvaal Ave Double Bay NSW 2028",
    "addr:postcode":"2028",
    "addr:street":"Transvaal Ave",
    "iso:country":"AU",
    "sg:address":"Shp2/ 1 Transvaal Ave",
    "sg:city":"Double Bay",
    "sg:classifiers":[
        {
            "category":"Shopping",
            "subcategory":"Clothing, Apparel, & Fashions",
            "type":"Retail Goods"
        }
    ],
    "sg:phone":"+61 2 9327 3901",
    "sg:postcode":"2028",
    "sg:province":"NSW",
    "sg:tags":[
        "lady",
        "wear"
    ],
    "wof:name":"Little Joe Pty Ltd",
    "wof:placetype":"venue"
},
  "geometry": {"coordinates":[151.243972778,-33.8765411377],"type":"Point"}
}