{
  "type": "Feature",
  "properties": {
    "iso:country":"AU",
    "sg:address":"17 Camp Mountain Rd",
    "sg:city":"Samford",
    "sg:classifiers":[
        {
            "category":"Education",
            "subcategory":"Kindergarten",
            "type":"Public Place"
        }
    ],
    "sg:phone":"+61 7 3289 1759",
    "sg:postcode":"4520",
    "sg:province":"QLD",
    "sg:tags":[
        "pre-schools"
    ],
    "wof:name":"C&K Samford Community Kindergarten",
    "wof:placetype":"venue"
},
  "geometry": {"coordinates":[152.88879399999999,-27.37644],"type":"Point"}
}