{
  "type": "Feature",
  "properties": {
    "iso:country":"AU",
    "sg:address":"Bayswater Clinic, 1 Gertrude Pl",
    "sg:city":"Gosford",
    "sg:classifiers":[
        {
            "category":"Health Services",
            "subcategory":"Doctor",
            "type":"Services"
        }
    ],
    "sg:phone":"+61 2 4323 2565",
    "sg:postcode":"2250",
    "sg:province":"NSW",
    "sg:tags":[
        "medical",
        "practitioner"
    ],
    "wof:name":"Armstrong Susan",
    "wof:placetype":"venue"
},
  "geometry": {"coordinates":[151.34283447300001,-33.4329147339],"type":"Point"}
}