{
  "type": "Feature",
  "properties": {
    "addr:full":"1 Huntingdale Crt Cooloongup WA 6168",
    "addr:housenumber":"1",
    "addr:postcode":"6168",
    "addr:street":"Huntingdale Crt",
    "iso:country":"AU",
    "sg:address":"1 Huntingdale Crt",
    "sg:city":"Cooloongup",
    "sg:classifiers":[
        {
            "category":"Building & Trades",
            "subcategory":"Construction",
            "type":"Services"
        }
    ],
    "sg:phone":"+61 400 952 832",
    "sg:postcode":"6168",
    "sg:province":"WA",
    "sg:tags":[
        "fencing",
        "contractor"
    ],
    "wof:name":"Jet Fencing",
    "wof:placetype":"venue"
},
  "geometry": {"coordinates":[115.76467100000001,-32.295479],"type":"Point"}
}