{
  "type": "Feature",
  "properties": {
    "addr:full":"140 Edgecliffe Rd Woollahra NSW 2025",
    "addr:housenumber":"140",
    "addr:postcode":"2025",
    "addr:street":"Edgecliffe Rd",
    "iso:country":"AU",
    "sg:address":"140 Edgecliffe Rd",
    "sg:city":"Woollahra",
    "sg:classifiers":[
        {
            "category":"Personal",
            "subcategory":"Beauty Salon",
            "type":"Services"
        }
    ],
    "sg:phone":"+61 2 9389 1444",
    "sg:postcode":"2025",
    "sg:province":"NSW",
    "sg:tags":[
        "hairdresser"
    ],
    "wof:name":"Hair On 140",
    "wof:placetype":"venue"
},
  "geometry": {"coordinates":[151.242019653,-33.8848342896],"type":"Point"}
}