{
  "type": "Feature",
  "properties": {
    "addr:full":"41 Lambeck Drv Tullamarine VIC 3043",
    "addr:housenumber":"41",
    "addr:postcode":"3043",
    "addr:street":"Lambeck Drv",
    "iso:country":"AU",
    "sg:address":"41 Lambeck Drv",
    "sg:city":"Tullamarine",
    "sg:classifiers":[
        {
            "category":"Wholesale",
            "subcategory":"Electrical",
            "type":"Manufacturing & Wholesale Goods"
        }
    ],
    "sg:phone":"+61 3 9338 1600",
    "sg:postcode":"3043",
    "sg:province":"VIC",
    "sg:tags":[
        "wholesaler",
        "mfrs",
        "accessory"
    ],
    "wof:name":"Australmold Pty Ltd",
    "wof:placetype":"venue"
},
  "geometry": {"coordinates":[144.85133361800001,-37.7056427002],"type":"Point"}
}