{
  "type": "Feature",
  "properties": {
    "addr:full":"106 Pitt St Nowra North NSW 2541",
    "addr:housenumber":"106",
    "addr:postcode":"2541",
    "addr:street":"Pitt St",
    "iso:country":"AU",
    "sg:address":"106 Pitt St",
    "sg:city":"Nowra North",
    "sg:classifiers":[
        {
            "category":"Professional",
            "subcategory":"Detective & Security Services",
            "type":"Services"
        }
    ],
    "sg:phone":"+61 2 4421 6448",
    "sg:postcode":"2541",
    "sg:province":"NSW",
    "sg:tags":[
        "protective",
        "rustproofing"
    ],
    "wof:name":"North Nowra Smash Repairs",
    "wof:placetype":"venue"
},
  "geometry": {"coordinates":[150.57681274399999,-34.8505821228],"type":"Point"}
}