{
  "type": "Feature",
  "properties": {
    "addr:full":"7/ 50B Riverside Rd Chipping Norton NSW 2170",
    "addr:housenumber":"/ 50b",
    "addr:postcode":"2170",
    "addr:street":"Riverside Rd",
    "iso:country":"AU",
    "sg:address":"7/ 50B Riverside Rd",
    "sg:city":"Chipping Norton",
    "sg:classifiers":[
        {
            "category":"Retail",
            "subcategory":"Auto Repair",
            "type":"Services"
        }
    ],
    "sg:phone":"+61 2 9728 1977",
    "sg:postcode":"2170",
    "sg:province":"NSW",
    "sg:tags":[
        "gas",
        "conversion",
        "natural",
        "lp",
        "vehicle"
    ],
    "wof:name":"Jimac Autos",
    "wof:placetype":"venue"
},
  "geometry": {"coordinates":[150.96852111800001,-33.9214820862],"type":"Point"}
}