{
  "type": "Feature",
  "properties": {
    "iso:country":"AU",
    "sg:address":"48 Barker Rd",
    "sg:city":"Albany",
    "sg:classifiers":[
        {
            "category":"Retail",
            "subcategory":"Auto Repair",
            "type":"Services"
        }
    ],
    "sg:phone":"+61 8 9842 5080",
    "sg:postcode":"6330",
    "sg:province":"WA",
    "sg:tags":[
        "beater",
        "painter",
        "panel"
    ],
    "wof:name":"Turpin Wayne Panel Beaters",
    "wof:placetype":"venue"
},
  "geometry": {"coordinates":[117.877868652,-35.010974884],"type":"Point"}
}