{
  "type": "Feature",
  "properties": {
    "iso:country":"AU",
    "sg:address":"8 Pikki St",
    "sg:city":"Maroochydore",
    "sg:classifiers":[
        {
            "category":"Social Services",
            "subcategory":"Retirement Home",
            "type":"Services"
        }
    ],
    "sg:phone":"+61 7 5451 9901",
    "sg:postcode":"4558",
    "sg:province":"QLD",
    "sg:tags":[
        "environmental",
        "consultant",
        "pollution"
    ],
    "wof:name":"Douglas Partners",
    "wof:placetype":"venue"
},
  "geometry": {"coordinates":[153.086425781,-26.6535758972],"type":"Point"}
}