{
  "type": "Feature",
  "properties": {
    "addr:full":"Unit 2/ 2 - 12 Gallipoli St St Marys NSW 2760",
    "addr:housenumber":"12",
    "addr:postcode":"2760",
    "addr:street":"Gallipoli St",
    "iso:country":"AU",
    "sg:address":"Unit 2/ 2 - 12 Gallipoli St",
    "sg:city":"St Marys",
    "sg:classifiers":[
        {
            "category":"Retail",
            "subcategory":"Auto Repair",
            "type":"Services"
        }
    ],
    "sg:phone":"+61 2 9623 4385",
    "sg:postcode":"2760",
    "sg:province":"NSW",
    "sg:tags":[
        "repairer",
        "motor",
        "engineer"
    ],
    "wof:name":"Ultra Tune",
    "wof:placetype":"venue"
},
  "geometry": {"coordinates":[150.769989014,-33.78125],"type":"Point"}
}