{
  "type": "Feature",
  "properties": {
    "iso:country":"AU",
    "sg:address":"251 Fallon St",
    "sg:city":"Albury North",
    "sg:classifiers":[
        {
            "category":"Manufacturing",
            "subcategory":"Glass & Minerals",
            "type":"Manufacturing & Wholesale Goods"
        }
    ],
    "sg:phone":"+61 2 6040 2001",
    "sg:postcode":"2640",
    "sg:province":"NSW",
    "sg:tags":[
        "fabricator",
        "foam",
        "processor"
    ],
    "wof:name":"Aussie Jigsaw Mats",
    "wof:placetype":"venue"
},
  "geometry": {"coordinates":[146.92715454099999,-36.0622558594],"type":"Point"}
}