{
  "type": "Feature",
  "properties": {
    "addr:full":"Federal St Narrogin WA 6312",
    "addr:postcode":"6312",
    "addr:street":"Federal St",
    "iso:country":"AU",
    "sg:address":"Federal St",
    "sg:city":"Narrogin",
    "sg:classifiers":[
        {
            "category":"Wholesale",
            "subcategory":"Farm Supplies",
            "type":"Manufacturing & Wholesale Goods"
        }
    ],
    "sg:phone":"+61 8 9881 1411",
    "sg:postcode":"6312",
    "sg:province":"WA",
    "sg:tags":[
        "equipment"
    ],
    "wof:name":"Landmark",
    "wof:placetype":"venue"
},
  "geometry": {"coordinates":[117.178352356,-32.931388855],"type":"Point"}
}