{
  "type": "Feature",
  "properties": {
    "addr:full":"PO Box 161 Galston NSW 2159",
    "addr:postcode":"2159",
    "iso:country":"AU",
    "sg:address":"PO Box 161",
    "sg:city":"Galston",
    "sg:classifiers":[
        {
            "category":"Home & Garden",
            "subcategory":"Garden Supply",
            "type":"Retail Goods"
        }
    ],
    "sg:phone":"+61 2 9656 1200",
    "sg:postcode":"2159",
    "sg:province":"NSW",
    "sg:tags":[
        "landscape"
    ],
    "wof:name":"A.R.G. Tipping Contractors Pty Ltd",
    "wof:placetype":"venue"
},
  "geometry": {"coordinates":[151.045013428,-33.6529197693],"type":"Point"}
}