{
  "type": "Feature",
  "properties": {
    "iso:country":"AU",
    "sg:address":"276 Charters Towers Rd",
    "sg:city":"Hermit Park",
    "sg:classifiers":[
        {
            "category":"Shopping",
            "subcategory":"Clothing, Apparel, & Fashions",
            "type":"Retail Goods"
        }
    ],
    "sg:phone":"+61 7 4771 2438",
    "sg:postcode":"4812",
    "sg:province":"QLD",
    "sg:tags":[
        "lady",
        "wear"
    ],
    "wof:name":"Uniform Shop The",
    "wof:placetype":"venue"
},
  "geometry": {"coordinates":[146.796402,-19.29027],"type":"Point"}
}