{
  "type": "Feature",
  "properties": {
    "iso:country":"AU",
    "sg:address":"8 Elgee Rd",
    "sg:city":"Bellevue",
    "sg:classifiers":[
        {
            "category":"Utilities",
            "subcategory":"Water",
            "type":"Services"
        }
    ],
    "sg:phone":"+61 8 9250 2375",
    "sg:postcode":"6056",
    "sg:province":"WA",
    "sg:tags":[
        "equipment",
        "treatment"
    ],
    "wof:name":"Waterex Pty Ltd",
    "wof:placetype":"venue"
},
  "geometry": {"coordinates":[116.024360657,-31.8958873749],"type":"Point"}
}