{
  "type": "Feature",
  "properties": {
    "addr:full":"Caravan St Wendouree VIC 3355",
    "addr:postcode":"3355",
    "addr:street":"Caravan St",
    "iso:country":"AU",
    "sg:address":"Caravan St",
    "sg:city":"Wendouree",
    "sg:classifiers":[
        {
            "category":"Government",
            "subcategory":"Fire Station",
            "type":"Public Place"
        }
    ],
    "sg:phone":"+61 3 5339 3030",
    "sg:postcode":"3355",
    "sg:province":"VIC",
    "sg:tags":[
        "spring",
        "shock",
        "absorbers",
        "suspension"
    ],
    "wof:name":"West Exhaust Enterprise",
    "wof:placetype":"venue"
},
  "geometry": {"coordinates":[143.81478899999999,-37.530979],"type":"Point"}
}