{
  "type": "Feature",
  "properties": {
    "addr:full":"25 William St Paddington NSW 2021",
    "addr:housenumber":"25",
    "addr:postcode":"2021",
    "addr:street":"William St",
    "iso:country":"AU",
    "sg:address":"25 William St",
    "sg:city":"Paddington",
    "sg:classifiers":[
        {
            "category":"Personal",
            "subcategory":"Beauty Salon",
            "type":"Services"
        }
    ],
    "sg:phone":"+61 2 9360 1088",
    "sg:postcode":"2021",
    "sg:province":"NSW",
    "sg:tags":[
        "hairdresser"
    ],
    "wof:name":"Axis Hair Face Body",
    "wof:placetype":"venue"
},
  "geometry": {"coordinates":[151.229644775,-33.8856086731],"type":"Point"}
}