{
  "type": "Feature",
  "properties": {
    "iso:country":"AU",
    "sg:address":"Suite 1 83a Charles St",
    "sg:city":"Putney",
    "sg:classifiers":[
        {
            "category":"Personal",
            "subcategory":"Nail Salon",
            "type":"Services"
        }
    ],
    "sg:phone":"+61 2 9807 3419",
    "sg:postcode":"2112",
    "sg:province":"NSW",
    "sg:tags":[
        "artificial"
    ],
    "wof:name":"Vouge Nails",
    "wof:placetype":"venue"
},
  "geometry": {"coordinates":[151.10853576700001,-33.8232192993],"type":"Point"}
}