{
  "type": "Feature",
  "properties": {
    "addr:full":"52 Ocean Beach Rd Sorrento VIC 3943",
    "addr:housenumber":"52",
    "addr:postcode":"3943",
    "addr:street":"Ocean Beach Rd",
    "iso:country":"AU",
    "sg:address":"52 Ocean Beach Rd",
    "sg:city":"Sorrento",
    "sg:classifiers":[
        {
            "category":"Shopping",
            "subcategory":"Clothing, Apparel, & Fashions",
            "type":"Retail Goods"
        }
    ],
    "sg:phone":"+61 3 5984 4554",
    "sg:postcode":"3943",
    "sg:province":"VIC",
    "sg:tags":[
        "lingerie",
        "hosiery",
        "sleepwear"
    ],
    "wof:name":"Rosies Lingerie",
    "wof:placetype":"venue"
},
  "geometry": {"coordinates":[144.73968505900001,-38.3390617371],"type":"Point"}
}