{
  "type": "Feature",
  "properties": {
    "iso:country":"AU",
    "sg:address":"1/ 31 Norfolk Crt",
    "sg:city":"Coburg North",
    "sg:classifiers":[
        {
            "category":"Home & Garden",
            "subcategory":"Hardware",
            "type":"Retail Goods"
        }
    ],
    "sg:phone":"+61 3 9350 7233",
    "sg:postcode":"3058",
    "sg:province":"VIC",
    "sg:tags":[
        "compressor",
        "air"
    ],
    "wof:name":"W & T Pty Ltd",
    "wof:placetype":"venue"
},
  "geometry": {"coordinates":[144.980392456,-37.7221031189],"type":"Point"}
}