{
  "type": "Feature",
  "properties": {
    "iso:country":"AU",
    "sg:address":"392 High St",
    "sg:city":"Maitland",
    "sg:classifiers":[
        {
            "category":"Fast Food",
            "type":"Food & Drink"
        }
    ],
    "sg:phone":"+61 2 4934 5255",
    "sg:postcode":"2320",
    "sg:province":"NSW",
    "sg:tags":[
        "away",
        "take"
    ],
    "wof:name":"Subway",
    "wof:placetype":"venue"
},
  "geometry": {"coordinates":[151.55345153799999,-32.7311134338],"type":"Point"}
}