{
  "type": "Feature",
  "properties": {
    "addr:full":"7 Luxford Rd Mt Druitt NSW 2770",
    "addr:housenumber":"7",
    "addr:postcode":"2770",
    "addr:street":"Luxford Rd",
    "iso:country":"AU",
    "sg:address":"7 Luxford Rd",
    "sg:city":"Mt Druitt",
    "sg:classifiers":[
        {
            "category":"Health Services",
            "subcategory":"Doctor",
            "type":"Services"
        }
    ],
    "sg:phone":"+61 2 9832 3955",
    "sg:postcode":"2770",
    "sg:province":"NSW",
    "sg:tags":[
        "medical",
        "practitioner"
    ],
    "wof:name":"Ultrascan Radiology",
    "wof:placetype":"venue"
},
  "geometry": {"coordinates":[150.820480347,-33.7644805908],"type":"Point"}
}