{
  "type": "Feature",
  "properties": {
    "addr:full":"1126 Stud Rd Rowville VIC 3178",
    "addr:housenumber":"1126",
    "addr:postcode":"3178",
    "addr:street":"Stud Rd",
    "iso:country":"AU",
    "sg:address":"1126 Stud Rd",
    "sg:city":"Rowville",
    "sg:classifiers":[
        {
            "category":"Building & Trades",
            "subcategory":"Plumbing",
            "type":"Services"
        }
    ],
    "sg:phone":"+61 3 9764 4442",
    "sg:postcode":"3178",
    "sg:province":"VIC",
    "sg:tags":[
        "plumber",
        "gasfitters"
    ],
    "wof:name":"Cannon Plumbing Service Pty Ltd",
    "wof:placetype":"venue"
},
  "geometry": {"coordinates":[145.233886719,-37.9214401245],"type":"Point"}
}