{
  "type": "Feature",
  "properties": {
    "addr:full":"Suite 1/ 45 Moore St Liverpool NSW 2170",
    "addr:housenumber":"45",
    "addr:postcode":"2170",
    "addr:street":"Moore St",
    "iso:country":"AU",
    "sg:address":"Suite 1/ 45 Moore St",
    "sg:city":"Liverpool",
    "sg:classifiers":[
        {
            "category":"Personal",
            "subcategory":"Beauty Salon",
            "type":"Services"
        }
    ],
    "sg:phone":"+61 2 9601 1577",
    "sg:postcode":"2170",
    "sg:province":"NSW",
    "wof:name":"Electrolysis Beauty And Hair Training School & Services",
    "wof:placetype":"venue"
},
  "geometry": {"coordinates":[150.91252136200001,-33.9210205078],"type":"Point"}
}