{
  "type": "Feature",
  "properties": {
    "iso:country":"AU",
    "sg:address":"861 Albany Hwy",
    "sg:city":"East Victoria Park",
    "sg:classifiers":[
        {
            "category":"Personal",
            "subcategory":"Beauty Salon",
            "type":"Services"
        }
    ],
    "sg:phone":"+61 8 9361 5691",
    "sg:postcode":"6101",
    "sg:province":"WA",
    "sg:tags":[
        "hairdresser"
    ],
    "wof:name":"Headmasters In The Park",
    "wof:placetype":"venue"
},
  "geometry": {"coordinates":[115.903312683,-31.9851703644],"type":"Point"}
}