{
  "type": "Feature",
  "properties": {
    "iso:country":"AU",
    "sg:address":"Ksk2/ 59 Gillies St",
    "sg:city":"Wendouree",
    "sg:classifiers":[
        {
            "category":"Cafe",
            "type":"Food & Drink"
        }
    ],
    "sg:phone":"+61 3 5339 9200",
    "sg:postcode":"3355",
    "sg:province":"VIC",
    "wof:name":"Donut King Wendouree",
    "wof:placetype":"venue"
},
  "geometry": {"coordinates":[143.823578,-37.532459],"type":"Point"}
}