{
  "type": "Feature",
  "properties": {
    "addr:full":"40 Oxford St Collingwood VIC 3066",
    "addr:housenumber":"40",
    "addr:postcode":"3066",
    "addr:street":"Oxford St",
    "iso:country":"AU",
    "sg:address":"40 Oxford St",
    "sg:city":"Collingwood",
    "sg:classifiers":[
        {
            "category":"Banks & Credit Unions",
            "subcategory":"Atm",
            "type":"Services"
        }
    ],
    "sg:phone":"+61 3 9417 5402",
    "sg:postcode":"3066",
    "sg:province":"VIC",
    "sg:tags":[
        "wholesaler",
        "mfrs",
        "shirt",
        "pyjama"
    ],
    "wof:name":"Van Heusen Co (Aust) Pty Ltd",
    "wof:placetype":"venue"
},
  "geometry": {"coordinates":[144.98449707,-37.8063850403],"type":"Point"}
}