{
  "type": "Feature",
  "properties": {
    "iso:country":"AU",
    "sg:address":"Cross St",
    "sg:city":"South Gundagai",
    "sg:classifiers":[
        {
            "category":"Home & Garden",
            "subcategory":"Garden Supply",
            "type":"Retail Goods"
        }
    ],
    "sg:phone":"+61 2 6944 3150",
    "sg:postcode":"2722",
    "sg:province":"NSW",
    "sg:tags":[
        "landscape"
    ],
    "wof:name":"Vision Concrete",
    "wof:placetype":"venue"
},
  "geometry": {"coordinates":[148.094666,-35.084373],"type":"Point"}
}