{
  "type": "Feature",
  "properties": {
    "addr:full":"96 Melbourne Rd Rye VIC 3941",
    "addr:housenumber":"96",
    "addr:postcode":"3941",
    "addr:street":"Melbourne Rd",
    "iso:country":"AU",
    "sg:address":"96 Melbourne Rd",
    "sg:city":"Rye",
    "sg:classifiers":[
        {
            "category":"Home & Garden",
            "subcategory":"Garden Supply",
            "type":"Retail Goods"
        }
    ],
    "sg:phone":"+61 3 5985 2231",
    "sg:postcode":"3941",
    "sg:province":"VIC",
    "sg:tags":[
        "equipment"
    ],
    "wof:name":"Clarrie Jennings & Sons Pty Ltd",
    "wof:placetype":"venue"
},
  "geometry": {"coordinates":[144.807662964,-38.3765449524],"type":"Point"}
}