{
  "type": "Feature",
  "properties": {
    "addr:full":"51 Hill View Drv West End Yarravel NSW 2440",
    "addr:housenumber":"51",
    "addr:postcode":"2440",
    "addr:street":"Hill View Drv",
    "iso:country":"AU",
    "sg:address":"51 Hill View Drv",
    "sg:city":"West End Yarravel",
    "sg:classifiers":[
        {
            "category":"Home & Garden",
            "subcategory":"Hardware",
            "type":"Retail Goods"
        }
    ],
    "sg:phone":"+61 427 662 672",
    "sg:postcode":"2440",
    "sg:province":"NSW",
    "sg:tags":[
        "tarpaulin"
    ],
    "wof:name":"Fishers Kempsey Canvas",
    "wof:placetype":"venue"
},
  "geometry": {"coordinates":[152.82064800000001,-31.098564],"type":"Point"}
}