{
  "type": "Feature",
  "properties": {
    "addr:full":"103 Victoria St Cardwell QLD 4849",
    "addr:housenumber":"103",
    "addr:postcode":"4849",
    "addr:street":"Victoria St",
    "iso:country":"AU",
    "sg:address":"103 Victoria St",
    "sg:city":"Cardwell",
    "sg:classifiers":[
        {
            "category":"Personal",
            "subcategory":"Beauty Salon",
            "type":"Services"
        }
    ],
    "sg:phone":"+61 7 4066 8666",
    "sg:postcode":"4849",
    "sg:province":"QLD",
    "sg:tags":[
        "hairdresser"
    ],
    "wof:name":"Bravo Hair Design",
    "wof:placetype":"venue"
},
  "geometry": {"coordinates":[146.027176,-18.265278],"type":"Point"}
}