{
  "type": "Feature",
  "properties": {
    "addr:full":"7 Cozens St Brunswick VIC 3056",
    "addr:housenumber":"7",
    "addr:postcode":"3056",
    "addr:street":"Cozens St",
    "iso:country":"AU",
    "sg:address":"7 Cozens St",
    "sg:city":"Brunswick",
    "sg:classifiers":[
        {
            "category":"Wholesale",
            "subcategory":"Apparel",
            "type":"Manufacturing & Wholesale Goods"
        }
    ],
    "sg:phone":"+61 3 9384 2333",
    "sg:postcode":"3056",
    "sg:province":"VIC",
    "sg:tags":[
        "wholesaler",
        "mfrs",
        "menswear"
    ],
    "wof:name":"Back Bay Clothing",
    "wof:placetype":"venue"
},
  "geometry": {"coordinates":[144.9637146,-37.7563362122],"type":"Point"}
}