{
  "type": "Feature",
  "properties": {
    "iso:country":"AU",
    "sg:address":"35 Blackwattle Pl",
    "sg:city":"Cherrybrook",
    "sg:classifiers":[
        {
            "category":"Health Services",
            "subcategory":"Health Practitioner",
            "type":"Services"
        }
    ],
    "sg:phone":"+61 2 9484 7684",
    "sg:postcode":"2126",
    "sg:province":"NSW",
    "sg:tags":[
        "alternative"
    ],
    "wof:name":"Bowen Technique In Cherrybrook",
    "wof:placetype":"venue"
},
  "geometry": {"coordinates":[151.050323486,-33.7190628052],"type":"Point"}
}