{
  "type": "Feature",
  "properties": {
    "addr:full":"88 Belmont Ave Belmont WA 6104",
    "addr:housenumber":"88",
    "addr:postcode":"6104",
    "addr:street":"Belmont Ave",
    "iso:country":"AU",
    "sg:address":"88 Belmont Ave",
    "sg:city":"Belmont",
    "sg:classifiers":[
        {
            "category":"Building & Trades",
            "subcategory":"Construction",
            "type":"Services"
        }
    ],
    "sg:phone":"+61 8 9270 1432",
    "sg:postcode":"6104",
    "sg:province":"WA",
    "sg:tags":[
        "industrial",
        "commercial",
        "air conditioning"
    ],
    "wof:name":"York Airconditioning & Heating",
    "wof:placetype":"venue"
},
  "geometry": {"coordinates":[115.92440033,-31.9581985474],"type":"Point"}
}