{
  "type": "Feature",
  "properties": {
    "addr:full":"4/ 16 Tarnard Drv Braeside VIC 3195",
    "addr:housenumber":"/ 16",
    "addr:postcode":"3195",
    "addr:street":"Tarnard Drv",
    "iso:country":"AU",
    "sg:address":"4/ 16 Tarnard Drv",
    "sg:city":"Braeside",
    "sg:classifiers":[
        {
            "category":"Retail",
            "subcategory":"Storage",
            "type":"Services"
        }
    ],
    "sg:phone":"+61 3 9587 3473",
    "sg:postcode":"3195",
    "sg:province":"VIC",
    "sg:tags":[
        "shelving",
        "system"
    ],
    "wof:name":"Head For The Hills Pty Ltd",
    "wof:placetype":"venue"
},
  "geometry": {"coordinates":[145.110473633,-37.9891738892],"type":"Point"}
}