{
  "type": "Feature",
  "properties": {
    "addr:full":"17 Boxhill Rd Claremont TAS 7011",
    "addr:housenumber":"17",
    "addr:postcode":"7011",
    "addr:street":"Boxhill Rd",
    "iso:country":"AU",
    "sg:address":"17 Boxhill Rd",
    "sg:city":"Claremont",
    "sg:classifiers":[
        {
            "category":"Building & Trades",
            "subcategory":"Construction",
            "type":"Services"
        }
    ],
    "sg:phone":"+61 427 846 137",
    "sg:postcode":"7011",
    "sg:province":"TAS",
    "sg:tags":[
        "rigging",
        "erection",
        "contractor"
    ],
    "wof:name":"Comrig National Pty Ltd",
    "wof:placetype":"venue"
},
  "geometry": {"coordinates":[147.25413513199999,-42.7912330627],"type":"Point"}
}