{
  "type": "Feature",
  "properties": {
    "iso:country":"AU",
    "sg:address":"Bains Centre, Fawcett St",
    "sg:city":"Woolgoolga",
    "sg:classifiers":[
        {
            "category":"Sports & Exercise",
            "subcategory":"Gym",
            "type":"Entertainment"
        }
    ],
    "sg:phone":"+61 2 6654 0800",
    "sg:postcode":"2456",
    "sg:province":"NSW",
    "sg:tags":[
        "health",
        "fitness"
    ],
    "wof:name":"Woolgoolga Massage Clinic & Health Club",
    "wof:placetype":"venue"
},
  "geometry": {"coordinates":[153.19838,-30.11278],"type":"Point"}
}