{
  "type": "Feature",
  "properties": {
    "addr:full":"PO Box 193 Doncaster VIC 3108",
    "addr:postcode":"3108",
    "iso:country":"AU",
    "sg:address":"PO Box 193",
    "sg:city":"Doncaster",
    "sg:classifiers":[
        {
            "category":"Utilities",
            "subcategory":"Natural Gas",
            "type":"Services"
        }
    ],
    "sg:phone":"+61 3 9848 3355",
    "sg:postcode":"3108",
    "sg:province":"VIC",
    "sg:tags":[
        "solid",
        "plasterer"
    ],
    "wof:name":"Ace Rendering & Textures Pty Ltd",
    "wof:placetype":"venue"
},
  "geometry": {"coordinates":[145.122512817,-37.7830314636],"type":"Point"}
}