{
  "type": "Feature",
  "properties": {
    "iso:country":"AU",
    "sg:address":"PO Box 401",
    "sg:city":"Kempsey",
    "sg:classifiers":[
        {
            "category":"Building & Trades",
            "subcategory":"Landscaping Services",
            "type":"Services"
        }
    ],
    "sg:phone":"+61 2 6567 8202",
    "sg:postcode":"2440",
    "sg:province":"NSW",
    "sg:tags":[
        "grazier"
    ],
    "wof:name":"Landers J W",
    "wof:placetype":"venue"
},
  "geometry": {"coordinates":[152.84234599999999,-31.07839],"type":"Point"}
}