{
  "type": "Feature",
  "properties": {
    "iso:country":"AU",
    "sg:address":"6 Wilpena St St",
    "sg:city":"Albans",
    "sg:classifiers":[
        {
            "category":"Professional",
            "subcategory":"Detective & Security Services",
            "type":"Services"
        }
    ],
    "sg:phone":"+61 3 9310 8256",
    "sg:postcode":"3021",
    "sg:province":"VIC",
    "sg:tags":[
        "equipment",
        "window",
        "doors"
    ],
    "wof:name":"Dynamic Security Doors & Screens",
    "wof:placetype":"venue"
},
  "geometry": {"coordinates":[144.827179,-37.749268],"type":"Point"}
}