{
  "type": "Feature",
  "properties": {
    "addr:full":"Fac 1/ 17 Diane St Mornington VIC 3931",
    "addr:housenumber":"17",
    "addr:postcode":"3931",
    "addr:street":"Diane St",
    "iso:country":"AU",
    "sg:address":"Fac 1/ 17 Diane St",
    "sg:city":"Mornington",
    "sg:classifiers":[
        {
            "category":"Professional",
            "subcategory":"Accounting & Tax Preparation",
            "type":"Services"
        }
    ],
    "sg:phone":"+61 3 5975 3908",
    "sg:postcode":"3931",
    "sg:province":"VIC",
    "sg:tags":[
        "consultant",
        "taxation"
    ],
    "wof:name":"Economic Management Service",
    "wof:placetype":"venue"
},
  "geometry": {"coordinates":[145.060836792,-38.2248573303],"type":"Point"}
}