{
  "type": "Feature",
  "properties": {
    "addr:full":"113 Sheridan St Cairns QLD 4870",
    "addr:housenumber":"113",
    "addr:postcode":"4870",
    "addr:street":"Sheridan St",
    "iso:country":"AU",
    "sg:address":"113 Sheridan St",
    "sg:city":"Cairns",
    "sg:classifiers":[
        {
            "category":"Retail",
            "subcategory":"Self-service Laundry",
            "type":"Services"
        }
    ],
    "sg:phone":"+61 7 4031 3331",
    "sg:postcode":"4870",
    "sg:province":"QLD",
    "wof:name":"Civic Laundromat",
    "wof:placetype":"venue"
},
  "geometry": {"coordinates":[145.77235412600001,-16.9217224121],"type":"Point"}
}