{
  "type": "Feature",
  "properties": {
    "addr:full":"118 Comur St Yass NSW 2582",
    "addr:housenumber":"118",
    "addr:postcode":"2582",
    "addr:street":"Comur St",
    "iso:country":"AU",
    "sg:address":"118 Comur St",
    "sg:city":"Yass",
    "sg:classifiers":[
        {
            "category":"Shopping",
            "subcategory":"Shoes",
            "type":"Retail Goods"
        }
    ],
    "sg:phone":"+61 2 6226 2005",
    "sg:postcode":"2582",
    "sg:province":"NSW",
    "sg:tags":[
        "footwear"
    ],
    "wof:name":"Abbey Footwear",
    "wof:placetype":"venue"
},
  "geometry": {"coordinates":[148.91232299800001,-34.8431129456],"type":"Point"}
}