{
  "type": "Feature",
  "properties": {
    "addr:full":"2330 Main Rd Neerim South VIC 3831",
    "addr:housenumber":"2330",
    "addr:postcode":"3831",
    "addr:street":"Main Rd",
    "iso:country":"AU",
    "sg:address":"2330 Main Rd",
    "sg:city":"Neerim South",
    "sg:classifiers":[
        {
            "category":"Farming",
            "subcategory":"Vineyard",
            "type":"Manufacturing & Wholesale Goods"
        }
    ],
    "sg:phone":"+61 3 5628 1661",
    "sg:postcode":"3831",
    "sg:province":"VIC",
    "sg:tags":[
        "winery"
    ],
    "wof:name":"Ada River Vineyard",
    "wof:placetype":"venue"
},
  "geometry": {"coordinates":[145.95416299999999,-38.01688],"type":"Point"}
}