{
  "type": "Feature",
  "properties": {
    "addr:full":"Browns Rd Pemberton WA 6260",
    "addr:postcode":"6260",
    "addr:street":"Browns Rd",
    "iso:country":"AU",
    "sg:address":"Browns Rd",
    "sg:city":"Pemberton",
    "sg:classifiers":[
        {
            "category":"Building & Trades",
            "subcategory":"Construction",
            "type":"Services"
        }
    ],
    "sg:phone":"+61 8 9776 1168",
    "sg:postcode":"6260",
    "sg:province":"WA",
    "sg:tags":[
        "contractor"
    ],
    "wof:name":"Ryan JG & MC",
    "wof:placetype":"venue"
},
  "geometry": {"coordinates":[116.05420684800001,-34.4362792969],"type":"Point"}
}