{
  "type": "Feature",
  "properties": {
    "addr:full":"24 Barrier St Fyshwick ACT 2609",
    "addr:housenumber":"24",
    "addr:postcode":"2609",
    "addr:street":"Barrier St",
    "iso:country":"AU",
    "sg:address":"24 Barrier St",
    "sg:city":"Fyshwick",
    "sg:classifiers":[
        {
            "category":"Train Station",
            "subcategory":"Light Rail",
            "type":"Transportation"
        }
    ],
    "sg:phone":"+61 2 6280 4954",
    "sg:postcode":"2609",
    "sg:province":"ACT",
    "sg:tags":[
        "equipment",
        "energy",
        "solar"
    ],
    "wof:name":"Canberra Pools Pty Ltd",
    "wof:placetype":"venue"
},
  "geometry": {"coordinates":[149.17590332,-35.3304405212],"type":"Point"}
}