{
  "type": "Feature",
  "properties": {
    "iso:country":"AU",
    "sg:address":"22 Mahony Rd",
    "sg:city":"Riverstone",
    "sg:classifiers":[
        {
            "category":"Autos & Motor Vehicles",
            "subcategory":"Automobile Sales",
            "type":"Retail Goods"
        }
    ],
    "sg:phone":"+61 1300 550 564",
    "sg:postcode":"2765",
    "sg:province":"NSW",
    "sg:tags":[
        "equipment",
        "trailer"
    ],
    "wof:name":"Web Trailers",
    "wof:placetype":"venue"
},
  "geometry": {"coordinates":[150.86555480999999,-33.671913147],"type":"Point"}
}