{
  "type": "Feature",
  "properties": {
    "addr:full":"2 Staff Rd Cordeaux Heights NSW 2526",
    "addr:housenumber":"2",
    "addr:postcode":"2526",
    "addr:street":"Staff Rd",
    "iso:country":"AU",
    "sg:address":"2 Staff Rd",
    "sg:city":"Cordeaux Heights",
    "sg:classifiers":[
        {
            "category":"Professional",
            "subcategory":"Computer Services",
            "type":"Services"
        }
    ],
    "sg:phone":"+61 2 4272 5955",
    "sg:postcode":"2526",
    "sg:province":"NSW",
    "sg:tags":[
        "package",
        "software"
    ],
    "wof:name":"Peace of Mind Computing Pty Ltd",
    "wof:placetype":"venue"
},
  "geometry": {"coordinates":[150.839920044,-34.4466590881],"type":"Point"}
}