{
  "type": "Feature",
  "properties": {
    "addr:full":"21 Clivejay St Glen Waverley VIC 3150",
    "addr:housenumber":"21",
    "addr:postcode":"3150",
    "addr:street":"Clivejay St",
    "iso:country":"AU",
    "sg:address":"21 Clivejay St",
    "sg:city":"Glen Waverley",
    "sg:classifiers":[
        {
            "category":"Health Services",
            "subcategory":"Doctor",
            "type":"Services"
        }
    ],
    "sg:phone":"+61 3 9886 7488",
    "sg:postcode":"3150",
    "sg:province":"VIC",
    "sg:tags":[
        "occupational",
        "safety"
    ],
    "wof:name":"Applied Occupational Health & Safety Pty Ltd",
    "wof:placetype":"venue"
},
  "geometry": {"coordinates":[145.155685425,-37.8625946045],"type":"Point"}
}