{
  "type": "Feature",
  "properties": {
    "iso:country":"AU",
    "sg:address":"37 Aruma St",
    "sg:city":"Mornington",
    "sg:classifiers":[
        {
            "category":"Home & Garden",
            "subcategory":"Household Appliances",
            "type":"Retail Goods"
        }
    ],
    "sg:phone":"+61 419 976 891",
    "sg:postcode":"7018",
    "sg:province":"TAS",
    "sg:tags":[
        "heating",
        "system"
    ],
    "wof:name":"Ashlin Air & Gas Pty Ltd",
    "wof:placetype":"venue"
},
  "geometry": {"coordinates":[147.38746643100001,-42.8635520935],"type":"Point"}
}