{
  "type": "Feature",
  "properties": {
    "addr:full":"32 Kayleigh Drv Maroochydore QLD 4558",
    "addr:housenumber":"32",
    "addr:postcode":"4558",
    "addr:street":"Kayleigh Drv",
    "iso:country":"AU",
    "sg:address":"32 Kayleigh Drv",
    "sg:city":"Maroochydore",
    "sg:classifiers":[
        {
            "category":"Retail",
            "subcategory":"Storage",
            "type":"Services"
        }
    ],
    "sg:phone":"+61 13 25 54",
    "sg:postcode":"4558",
    "sg:province":"QLD",
    "sg:tags":[
        "removal",
        "furniture"
    ],
    "wof:name":"Allied Pickfords",
    "wof:placetype":"venue"
},
  "geometry": {"coordinates":[153.088912964,-26.6698036194],"type":"Point"}
}