{
  "type": "Feature",
  "properties": {
    "iso:country":"AU",
    "sg:address":"1 Pimmy's Crt",
    "sg:city":"Frankston North",
    "sg:classifiers":[
        {
            "category":"Shopping",
            "subcategory":"Bicycles & Sporting Goods",
            "type":"Retail Goods"
        }
    ],
    "sg:phone":"+61 3 9782 5335",
    "sg:postcode":"3200",
    "sg:province":"VIC",
    "sg:tags":[
        "chemical",
        "equipment",
        "pool",
        "swimming"
    ],
    "wof:name":"Smiths Solar Heating",
    "wof:placetype":"venue"
},
  "geometry": {"coordinates":[145.159378,-38.118],"type":"Point"}
}