{
  "type": "Feature",
  "properties": {
    "addr:full":"14 Cecil Ave Cannington WA 6107",
    "addr:housenumber":"14",
    "addr:postcode":"6107",
    "addr:street":"Cecil Ave",
    "iso:country":"AU",
    "sg:address":"14 Cecil Ave",
    "sg:city":"Cannington",
    "sg:classifiers":[
        {
            "category":"Health Services",
            "subcategory":"Chiropractor",
            "type":"Services"
        }
    ],
    "sg:phone":"+61 8 9350 5371",
    "sg:postcode":"6107",
    "sg:province":"WA",
    "sg:website":"http://www.backandneck.com.au",
    "wof:name":"Cannington Chiro",
    "wof:placetype":"venue"
},
  "geometry": {"coordinates":[115.936408997,-32.0169525146],"type":"Point"}
}