{
  "type": "Feature",
  "properties": {
    "addr:full":"Shop 30, Benowa Gardens Shopping Centre Cnr Ashmore & Benowa Rds Benowa QLD 4217",
    "addr:housenumber":"shop 30",
    "addr:postcode":"4217",
    "addr:street":"Benowa Gardens;Cnr",
    "iso:country":"AU",
    "sg:address":"Shop 30, Benowa Gardens Shopping Centre Cnr Ashmore & Benowa Rds",
    "sg:city":"Benowa",
    "sg:classifiers":[
        {
            "category":"Travel",
            "subcategory":"Travel Agent",
            "type":"Entertainment"
        }
    ],
    "sg:phone":"+61 7 5557 9888",
    "sg:postcode":"4217",
    "sg:province":"QLD",
    "sg:tags":[
        "consultant"
    ],
    "wof:name":"American Express Travel Services",
    "wof:placetype":"venue"
},
  "geometry": {"coordinates":[153.39222717300001,-28.0099372864],"type":"Point"}
}