{
  "type": "Feature",
  "properties": {
    "addr:full":"4/ 1147 Sth Pine Rd Arana Hills QLD 4054",
    "addr:housenumber":"/ 1147",
    "addr:postcode":"4054",
    "addr:street":"Sth Pine Rd",
    "iso:country":"AU",
    "sg:address":"4/ 1147 Sth Pine Rd",
    "sg:city":"Arana Hills",
    "sg:classifiers":[
        {
            "category":"Building & Trades",
            "subcategory":"Landscaping Services",
            "type":"Services"
        }
    ],
    "sg:phone":"+61 7 3851 0104",
    "sg:postcode":"4054",
    "sg:province":"QLD",
    "sg:tags":[
        "stump",
        "tree",
        "felling",
        "removal"
    ],
    "sg:website":"http://www.aarontreeservice.com.au",
    "wof:name":"Aaron Tree Service",
    "wof:placetype":"venue"
},
  "geometry": {"coordinates":[152.96157836899999,-27.3890953064],"type":"Point"}
}