{
  "type": "Feature",
  "properties": {
    "addr:full":"Manly Harbour Village 222 Stratton Tce Manly QLD 4179",
    "addr:housenumber":"222",
    "addr:postcode":"4179",
    "addr:street":"Stratton Tce",
    "iso:country":"AU",
    "sg:address":"Manly Harbour Village 222",
    "sg:city":"Stratton Tce Manly",
    "sg:classifiers":[
        {
            "category":"Food & Beverages",
            "subcategory":"Specialty",
            "type":"Retail Goods"
        }
    ],
    "sg:phone":"+61 7 3348 2077",
    "sg:postcode":"4179",
    "sg:province":"QLD",
    "sg:tags":[
        "product",
        "health"
    ],
    "wof:name":"Health Foods 2000 & Naturopathic Clinic",
    "wof:placetype":"venue"
},
  "geometry": {"coordinates":[153.185546875,-27.4545135498],"type":"Point"}
}