{
  "type": "Feature",
  "properties": {
    "addr:full":"14 Fitzgerald St Bundaberg QLD 4670",
    "addr:housenumber":"14",
    "addr:postcode":"4670",
    "addr:street":"Fitzgerald St",
    "iso:country":"AU",
    "sg:address":"14 Fitzgerald St",
    "sg:city":"Bundaberg",
    "sg:classifiers":[
        {
            "category":"Banks & Credit Unions",
            "subcategory":"Investment Brokerage",
            "type":"Services"
        }
    ],
    "sg:phone":"+61 7 4152 9233",
    "sg:postcode":"4670",
    "sg:province":"QLD",
    "sg:tags":[
        "care",
        "day",
        "family",
        "child"
    ],
    "wof:name":"Family Day Care Schemes Bundaberg",
    "wof:placetype":"venue"
},
  "geometry": {"coordinates":[152.34376525900001,-24.8953266144],"type":"Point"}
}