{
  "type": "Feature",
  "properties": {
    "addr:full":"12 Pax Rd Traralgon VIC 3844",
    "addr:housenumber":"12",
    "addr:postcode":"3844",
    "addr:street":"Pax Rd",
    "iso:country":"AU",
    "sg:address":"12 Pax Rd",
    "sg:city":"Traralgon",
    "sg:classifiers":[
        {
            "category":"Organizations",
            "subcategory":"Professional Association",
            "type":"Services"
        }
    ],
    "sg:phone":"+61 3 5174 9358",
    "sg:postcode":"3844",
    "sg:province":"VIC",
    "sg:tags":[
        "web",
        "internet"
    ],
    "wof:name":"Scribex Business Solutions",
    "wof:placetype":"venue"
},
  "geometry": {"coordinates":[146.53094482399999,-38.1902160645],"type":"Point"}
}