{
  "type": "Feature",
  "properties": {
    "iso:country":"AU",
    "sg:address":"959 Ann St (Cnr Chester St)",
    "sg:city":"Fortitude Valley",
    "sg:classifiers":[
        {
            "category":"Professional",
            "type":"Services"
        }
    ],
    "sg:phone":"+61 7 3620 8555",
    "sg:postcode":"4006",
    "sg:province":"QLD",
    "sg:tags":[
        "shop",
        "fitting"
    ],
    "sg:website":"http://www.urbanfitout.com.au",
    "wof:name":"Urban Fitout",
    "wof:placetype":"venue"
},
  "geometry": {"coordinates":[153.04026794399999,-27.4533004761],"type":"Point"}
}