{
  "type": "Feature",
  "properties": {
    "addr:full":"4/ 4 Broadview Ave Gosford NSW 2250",
    "addr:housenumber":"/ 4",
    "addr:postcode":"2250",
    "addr:street":"Broadview Ave",
    "iso:country":"AU",
    "sg:address":"4/ 4 Broadview Ave",
    "sg:city":"Gosford",
    "sg:classifiers":[
        {
            "category":"Real Estate",
            "subcategory":"Architect",
            "type":"Services"
        }
    ],
    "sg:phone":"+61 2 4325 3855",
    "sg:postcode":"2250",
    "sg:province":"NSW",
    "wof:name":"DWG Architecture",
    "wof:placetype":"venue"
},
  "geometry": {"coordinates":[151.34193420400001,-33.4316902161],"type":"Point"}
}