{
  "type": "Feature",
  "properties": {
    "iso:country":"AU",
    "sg:address":"2/ 45 Grafton St",
    "sg:city":"Coffs Harbour",
    "sg:classifiers":[
        {
            "category":"Banks & Credit Unions",
            "subcategory":"Investment Brokerage",
            "type":"Services"
        }
    ],
    "sg:phone":"+61 2 6651 7500",
    "sg:postcode":"2450",
    "sg:province":"NSW",
    "sg:tags":[
        "cashing",
        "cheque"
    ],
    "wof:name":"AMX Money",
    "wof:placetype":"venue"
},
  "geometry": {"coordinates":[153.112808,-30.29777],"type":"Point"}
}