{
  "type": "Feature",
  "properties": {
    "addr:full":"1 Parry Rd Eltham North VIC 3095",
    "addr:housenumber":"1",
    "addr:postcode":"3095",
    "addr:street":"Parry Rd",
    "iso:country":"AU",
    "sg:address":"1 Parry Rd",
    "sg:city":"Eltham North",
    "sg:classifiers":[
        {
            "category":"Personal",
            "subcategory":"Massage",
            "type":"Services"
        }
    ],
    "sg:phone":"+61 3 9431 2755",
    "sg:postcode":"3095",
    "sg:province":"VIC",
    "sg:tags":[
        "therapy"
    ],
    "wof:name":"Eltham Remedial & Sports Massage",
    "wof:placetype":"venue"
},
  "geometry": {"coordinates":[145.14292907699999,-37.6881713867],"type":"Point"}
}