{
  "type": "Feature",
  "properties": {
    "addr:full":"14 Keryn Pl Keperra QLD 4054",
    "addr:housenumber":"14",
    "addr:postcode":"4054",
    "addr:street":"Keryn Pl",
    "iso:country":"AU",
    "sg:address":"14 Keryn Pl",
    "sg:city":"Keperra",
    "sg:classifiers":[
        {
            "category":"Sports & Exercise",
            "subcategory":"Gym",
            "type":"Entertainment"
        }
    ],
    "sg:phone":"+61 404 679 081",
    "sg:postcode":"4054",
    "sg:province":"QLD",
    "sg:tags":[
        "personal",
        "trainer",
        "fitness"
    ],
    "wof:name":"Sports Gurus",
    "wof:placetype":"venue"
},
  "geometry": {"coordinates":[152.944747925,-27.4206428528],"type":"Point"}
}