{
  "type": "Feature",
  "properties": {
    "addr:full":"311 Hay St Perth WA 6000",
    "addr:housenumber":"311",
    "addr:postcode":"6000",
    "addr:street":"Hay St",
    "iso:country":"AU",
    "sg:address":"311 Hay St",
    "sg:city":"Perth",
    "sg:classifiers":[
        {
            "category":"Retail",
            "subcategory":"Auto Rental",
            "type":"Services"
        }
    ],
    "sg:phone":"+61 8 9221 1333",
    "sg:postcode":"6000",
    "sg:province":"WA",
    "sg:tags":[
        "car",
        "hire",
        "minibus"
    ],
    "wof:name":"A Aaarons Rent-A-Car",
    "wof:placetype":"venue"
},
  "geometry": {"coordinates":[115.856086731,-31.953371048],"type":"Point"}
}