{
  "type": "Feature",
  "properties": {
    "addr:full":"8 River St Mackay QLD 4740",
    "addr:housenumber":"8",
    "addr:postcode":"4740",
    "addr:street":"River St",
    "iso:country":"AU",
    "sg:address":"8 River St",
    "sg:city":"Mackay",
    "sg:classifiers":[
        {
            "category":"Retail",
            "subcategory":"Event Space",
            "type":"Services"
        }
    ],
    "sg:phone":"+61 7 4957 8131",
    "sg:postcode":"4740",
    "sg:province":"QLD",
    "sg:tags":[
        "venue",
        "reception",
        "wedding"
    ],
    "wof:name":"Pacinos The Waterfront",
    "wof:placetype":"venue"
},
  "geometry": {"coordinates":[149.18400600000001,-21.138649],"type":"Point"}
}