{
  "type": "Feature",
  "properties": {
    "iso:country":"AU",
    "sg:address":"339 North Rocks Rd",
    "sg:city":"North Rocks",
    "sg:classifiers":[
        {
            "category":"Retail",
            "subcategory":"Repair Shop",
            "type":"Services"
        }
    ],
    "sg:phone":"+61 2 9873 1356",
    "sg:postcode":"2151",
    "sg:province":"NSW",
    "sg:tags":[
        "mending",
        "clothing",
        "alteration"
    ],
    "wof:name":"Sue's Alterations",
    "wof:placetype":"venue"
},
  "geometry": {"coordinates":[151.02549743599999,-33.7710151672],"type":"Point"}
}