{
  "type": "Feature",
  "properties": {
    "addr:full":"31 Edward St Horsham VIC 3400",
    "addr:housenumber":"31",
    "addr:postcode":"3400",
    "addr:street":"Edward St",
    "iso:country":"AU",
    "sg:address":"31 Edward St",
    "sg:city":"Horsham",
    "sg:classifiers":[
        {
            "category":"Farming",
            "subcategory":"Farm & Veterinary Services",
            "type":"Manufacturing & Wholesale Goods"
        }
    ],
    "sg:phone":"+61 3 5382 0297",
    "sg:postcode":"3400",
    "sg:province":"VIC",
    "sg:tags":[
        "drying",
        "seed",
        "cleaning",
        "grading"
    ],
    "wof:name":"Dunn-Eazy Seed Cleaning",
    "wof:placetype":"venue"
},
  "geometry": {"coordinates":[142.189285278,-36.7047920227],"type":"Point"}
}