{
  "type": "Feature",
  "properties": {
    "addr:full":"Shp2/ 471 Marrickville Rd Dulwich Hill NSW 2203",
    "addr:housenumber":"471",
    "addr:postcode":"2203",
    "addr:street":"Marrickville Rd",
    "iso:country":"AU",
    "sg:address":"Shp2/ 471 Marrickville Rd",
    "sg:city":"Dulwich Hill",
    "sg:classifiers":[
        {
            "category":"Personal",
            "subcategory":"Beauty Salon",
            "type":"Services"
        }
    ],
    "sg:phone":"+61 2 9518 3551",
    "sg:postcode":"2203",
    "sg:province":"NSW",
    "wof:name":"Royal Nails & Waxing",
    "wof:placetype":"venue"
},
  "geometry": {"coordinates":[151.14355499999999,-33.904228],"type":"Point"}
}