{
  "type": "Feature",
  "properties": {
    "addr:full":"4 Motto La Heatherbrae NSW 2324",
    "addr:housenumber":"4",
    "addr:postcode":"2324",
    "addr:street":"Motto",
    "iso:country":"AU",
    "sg:address":"4 Motto La",
    "sg:city":"Heatherbrae",
    "sg:classifiers":[
        {
            "category":"Home & Garden",
            "subcategory":"Hardware",
            "type":"Retail Goods"
        }
    ],
    "sg:phone":"+61 2 4983 1539",
    "sg:postcode":"2324",
    "sg:province":"NSW",
    "sg:tags":[
        "tarpaulin"
    ],
    "wof:name":"All Tarps",
    "wof:placetype":"venue"
},
  "geometry": {"coordinates":[151.73304748499999,-32.7861938477],"type":"Point"}
}