{
  "type": "Feature",
  "properties": {
    "addr:full":"10 Coraki Pl Bonnyrigg NSW 2177",
    "addr:housenumber":"10",
    "addr:postcode":"2177",
    "addr:street":"Coraki Pl",
    "iso:country":"AU",
    "sg:address":"10 Coraki Pl",
    "sg:city":"Bonnyrigg",
    "sg:classifiers":[
        {
            "category":"Home & Garden",
            "subcategory":"Carpets & Floor Coverings",
            "type":"Retail Goods"
        }
    ],
    "sg:phone":"+61 2 9610 5299",
    "sg:postcode":"2177",
    "sg:province":"NSW",
    "sg:tags":[
        "tile",
        "wall"
    ],
    "wof:name":"Radovic Dragoljub",
    "wof:placetype":"venue"
},
  "geometry": {"coordinates":[150.88702392600001,-33.8959083557],"type":"Point"}
}