{
  "type": "Feature",
  "properties": {
    "iso:country":"AU",
    "sg:address":"41 Stanmore Rd",
    "sg:city":"Stanmore",
    "sg:classifiers":[
        {
            "category":"Health Services",
            "subcategory":"Health Practitioner",
            "type":"Services"
        }
    ],
    "sg:phone":"+61 2 9557 0166",
    "sg:postcode":"2048",
    "sg:province":"NSW",
    "sg:tags":[
        "acupuncture"
    ],
    "wof:name":"Jim Mann Acupuncture",
    "wof:placetype":"venue"
},
  "geometry": {"coordinates":[151.16892999999999,-33.898846],"type":"Point"}
}