{
  "type": "Feature",
  "properties": {
    "addr:full":"109 Queen St Woollahra NSW 2025",
    "addr:housenumber":"109",
    "addr:postcode":"2025",
    "addr:street":"Queen St",
    "iso:country":"AU",
    "sg:address":"109 Queen St",
    "sg:city":"Woollahra",
    "sg:classifiers":[
        {
            "category":"Real Estate",
            "subcategory":"Developer",
            "type":"Services"
        }
    ],
    "sg:phone":"+61 2 9328 2777",
    "sg:postcode":"2025",
    "sg:province":"NSW",
    "sg:tags":[
        "development"
    ],
    "wof:name":"Pongrass Development Group Pty Ltd",
    "wof:placetype":"venue"
},
  "geometry": {"coordinates":[151.23753356899999,-33.8884887695],"type":"Point"}
}