{
  "type": "Feature",
  "properties": {
    "iso:country":"AU",
    "sg:address":"Ardessie St",
    "sg:city":"Ardross",
    "sg:classifiers":[
        {
            "category":"Shopping",
            "subcategory":"Music",
            "type":"Retail Goods"
        }
    ],
    "sg:phone":"+61 8 9316 9996",
    "sg:postcode":"6153",
    "sg:province":"WA",
    "sg:tags":[
        "instrument",
        "musical"
    ],
    "wof:name":"Yamaha Music School",
    "wof:placetype":"venue"
},
  "geometry": {"coordinates":[115.83593,-32.025898],"type":"Point"}
}