{
  "type": "Feature",
  "properties": {
    "addr:full":"21 Tripoli Ave Carlingford NSW 2118",
    "addr:housenumber":"21",
    "addr:postcode":"2118",
    "addr:street":"Tripoli Ave",
    "iso:country":"AU",
    "sg:address":"21 Tripoli Ave",
    "sg:city":"Carlingford",
    "sg:classifiers":[
        {
            "category":"Professional",
            "subcategory":"Computer Services",
            "type":"Services"
        }
    ],
    "sg:phone":"+61 416 080 503",
    "sg:postcode":"2118",
    "sg:province":"NSW",
    "sg:tags":[
        "consultant",
        "system"
    ],
    "wof:name":"Astra Software Pty Ltd",
    "wof:placetype":"venue"
},
  "geometry": {"coordinates":[151.04963684099999,-33.7678909302],"type":"Point"}
}