{
  "type": "Feature",
  "properties": {
    "addr:full":"30 Welshpool Rd Welshpool WA 6106",
    "addr:housenumber":"30",
    "addr:postcode":"6106",
    "addr:street":"Welshpool Rd",
    "iso:country":"AU",
    "sg:address":"30 Welshpool Rd",
    "sg:city":"Welshpool",
    "sg:classifiers":[
        {
            "category":"Autos & Motor Vehicles",
            "subcategory":"Automobile Sales",
            "type":"Retail Goods"
        }
    ],
    "sg:phone":"+61 8 9362 6336",
    "sg:postcode":"6106",
    "sg:province":"WA",
    "sg:tags":[
        "car",
        "used"
    ],
    "wof:name":"Geta-way Motor Vehicles",
    "wof:placetype":"venue"
},
  "geometry": {"coordinates":[115.919517517,-31.9938144684],"type":"Point"}
}