{
  "type": "Feature",
  "properties": {
    "addr:full":"69 Brooke St Woomelang VIC 3485",
    "addr:housenumber":"69",
    "addr:postcode":"3485",
    "addr:street":"Brooke St",
    "iso:country":"AU",
    "sg:address":"69 Brooke St",
    "sg:city":"Woomelang",
    "sg:classifiers":[
        {
            "category":"Food & Beverages",
            "subcategory":"Groceries & Convenience Stores",
            "type":"Retail Goods"
        }
    ],
    "sg:phone":"+61 3 5081 2126",
    "sg:postcode":"3485",
    "sg:province":"VIC",
    "wof:name":"Woomelang Food Store",
    "wof:placetype":"venue"
},
  "geometry": {"coordinates":[142.66392517099999,-35.6807479858],"type":"Point"}
}