{
  "type": "Feature",
  "properties": {
    "iso:country":"AU",
    "sg:address":"232 Fraser Rd",
    "sg:city":"Currie",
    "sg:classifiers":[
        {
            "category":"Building & Trades",
            "subcategory":"Construction",
            "type":"Services"
        }
    ],
    "sg:phone":"+61 3 6462 1127",
    "sg:postcode":"7256",
    "sg:province":"TAS",
    "sg:tags":[
        "contractor"
    ],
    "wof:name":"Gobel J W F",
    "wof:placetype":"venue"
},
  "geometry": {"coordinates":[143.89065551799999,-39.9188766479],"type":"Point"}
}