{
  "type": "Feature",
  "properties": {
    "iso:country":"AU",
    "sg:address":"Cnr Central & Mitchell Rds",
    "sg:city":"Kialla",
    "sg:classifiers":[
        {
            "category":"Utilities",
            "subcategory":"Refuse",
            "type":"Services"
        }
    ],
    "sg:phone":"+61 3 5827 1401",
    "sg:postcode":"3631",
    "sg:province":"VIC",
    "sg:tags":[
        "remover",
        "rubbish"
    ],
    "wof:name":"Anderson Ross",
    "wof:placetype":"venue"
},
  "geometry": {"coordinates":[145.39300537099999,-36.4570007324],"type":"Point"}
}