{
  "type": "Feature",
  "properties": {
    "addr:full":"16 MacQuarie Rd Mannering Park NSW 2259",
    "addr:housenumber":"16",
    "addr:postcode":"2259",
    "addr:street":"Macquarie Rd",
    "iso:country":"AU",
    "sg:address":"16 MacQuarie Rd",
    "sg:city":"Mannering Park",
    "sg:classifiers":[
        {
            "category":"Personal",
            "subcategory":"Massage",
            "type":"Services"
        }
    ],
    "sg:phone":"+61 2 4359 2552",
    "sg:postcode":"2259",
    "sg:province":"NSW",
    "sg:tags":[
        "therapy"
    ],
    "wof:name":"Del Soul Massage and Weightloss",
    "wof:placetype":"venue"
},
  "geometry": {"coordinates":[151.536056519,-33.1522827148],"type":"Point"}
}