{
  "type": "Feature",
  "properties": {
    "addr:full":"1 Beatty Pde Mornington VIC 3931",
    "addr:housenumber":"1",
    "addr:postcode":"3931",
    "addr:street":"Beatty Pde",
    "iso:country":"AU",
    "sg:address":"1 Beatty Pde",
    "sg:city":"Mornington",
    "sg:classifiers":[
        {
            "category":"Shopping",
            "subcategory":"Stationery & Office Supplies",
            "type":"Retail Goods"
        }
    ],
    "sg:phone":"+61 3 5976 1322",
    "sg:postcode":"3931",
    "sg:province":"VIC",
    "sg:tags":[
        "equipment",
        "display",
        "exhibition"
    ],
    "wof:name":"Interactive Animators",
    "wof:placetype":"venue"
},
  "geometry": {"coordinates":[145.04411315900001,-38.2218055725],"type":"Point"}
}