{
  "type": "Feature",
  "properties": {
    "addr:full":"Shop 2, 186 Scarborough Beach Rd Mt Hawthorn WA 6016",
    "addr:housenumber":"shop 2 186",
    "addr:postcode":"6016",
    "addr:street":"Scarborough Beach Rd",
    "iso:country":"AU",
    "sg:address":"Shop 2, 186 Scarborough Beach Rd",
    "sg:city":"Mt Hawthorn",
    "sg:classifiers":[
        {
            "category":"Travel",
            "subcategory":"Travel Agent",
            "type":"Entertainment"
        }
    ],
    "sg:phone":"+61 13 18 66",
    "sg:postcode":"6016",
    "sg:province":"WA",
    "sg:tags":[
        "consultant"
    ],
    "wof:name":"Flight Centre",
    "wof:placetype":"venue"
},
  "geometry": {"coordinates":[115.83682251,-31.9202575684],"type":"Point"}
}