{
  "type": "Feature",
  "properties": {
    "addr:full":"Suite 1A, 242 Sheridan St Cairns QLD 4870",
    "addr:housenumber":"242",
    "addr:postcode":"4870",
    "addr:street":"Sheridan St",
    "iso:country":"AU",
    "sg:address":"Suite 1A, 242 Sheridan St",
    "sg:city":"Cairns",
    "sg:classifiers":[
        {
            "category":"Personal",
            "subcategory":"Beauty Salon",
            "type":"Services"
        }
    ],
    "sg:phone":"+61 7 4041 5105",
    "sg:postcode":"4870",
    "sg:province":"QLD",
    "sg:tags":[
        "hair",
        "wedding"
    ],
    "wof:name":"Rhonda's Beauty Spot",
    "wof:placetype":"venue"
},
  "geometry": {"coordinates":[145.76296997099999,-16.9107627869],"type":"Point"}
}