{
  "type": "Feature",
  "properties": {
    "iso:country":"AU",
    "sg:address":"11 Lancaster Crt",
    "sg:city":"Greenvale",
    "sg:classifiers":[
        {
            "category":"Social Services",
            "subcategory":"Child Care",
            "type":"Services"
        }
    ],
    "sg:phone":"+61 412 489 064",
    "sg:postcode":"3059",
    "sg:province":"VIC",
    "sg:tags":[
        "childbirth"
    ],
    "wof:name":"Penelope Longo",
    "wof:placetype":"venue"
},
  "geometry": {"coordinates":[144.889129639,-37.6409416199],"type":"Point"}
}