{
  "type": "Feature",
  "properties": {
    "addr:full":"35 Jackson St Glenorchy TAS 7010",
    "addr:housenumber":"35",
    "addr:postcode":"7010",
    "addr:street":"Jackson St",
    "iso:country":"AU",
    "sg:address":"35 Jackson St",
    "sg:city":"Glenorchy",
    "sg:classifiers":[
        {
            "category":"Autos & Motor Vehicles",
            "subcategory":"Motorcycle Sales",
            "type":"Retail Goods"
        }
    ],
    "sg:phone":"+61 3 6273 0368",
    "sg:postcode":"7010",
    "sg:province":"TAS",
    "sg:tags":[
        "part",
        "recyclers",
        "cycle"
    ],
    "wof:name":"Hotwire",
    "wof:placetype":"venue"
},
  "geometry": {"coordinates":[147.25723266599999,-42.8410110474],"type":"Point"}
}