{
  "type": "Feature",
  "properties": {
    "iso:country":"AU",
    "sg:address":"Shop 2/ 611 Dean St",
    "sg:city":"Albury",
    "sg:classifiers":[
        {
            "category":"Banks & Credit Unions",
            "subcategory":"Financial Services",
            "type":"Services"
        }
    ],
    "sg:phone":"+61 2 6021 7706",
    "sg:postcode":"2640",
    "sg:province":"NSW",
    "sg:tags":[
        "loan",
        "finance",
        "mortgage"
    ],
    "wof:name":"The Banksia Financial Group",
    "wof:placetype":"venue"
},
  "geometry": {"coordinates":[146.91249084500001,-36.0804138184],"type":"Point"}
}