{
  "type": "Feature",
  "properties": {
    "iso:country":"AU",
    "sg:address":"80 Hillcrest Ave",
    "sg:city":"Hurstville",
    "sg:classifiers":[
        {
            "category":"Building & Trades",
            "subcategory":"Construction",
            "type":"Services"
        }
    ],
    "sg:phone":"+61 2 9579 2271",
    "sg:postcode":"2220",
    "sg:province":"NSW",
    "sg:tags":[
        "concrete",
        "contractor"
    ],
    "wof:name":"Drysdale Bert",
    "wof:placetype":"venue"
},
  "geometry": {"coordinates":[151.094573975,-33.9726142883],"type":"Point"}
}