{
  "type": "Feature",
  "properties": {
    "iso:country":"AU",
    "sg:address":"PO Box 688",
    "sg:city":"Turramurra",
    "sg:classifiers":[
        {
            "category":"Shopping",
            "subcategory":"Musical Instruments",
            "type":"Retail Goods"
        }
    ],
    "sg:phone":"+61 412 964 225",
    "sg:postcode":"2074",
    "sg:province":"NSW",
    "sg:tags":[
        "musician",
        "agent"
    ],
    "wof:name":"Ross Hamilton",
    "wof:placetype":"venue"
},
  "geometry": {"coordinates":[151.129196167,-33.7326011658],"type":"Point"}
}