{
  "type": "Feature",
  "properties": {
    "iso:country":"AU",
    "sg:address":"55 Croyden Rd",
    "sg:city":"Roleystone",
    "sg:classifiers":[
        {
            "category":"Sports & Exercise",
            "subcategory":"Sports Center",
            "type":"Entertainment"
        }
    ],
    "sg:phone":"+61 8 9496 0325",
    "sg:postcode":"6111",
    "sg:province":"WA",
    "sg:tags":[
        "coach",
        "tennis"
    ],
    "wof:name":"Roberts, John",
    "wof:placetype":"venue"
},
  "geometry": {"coordinates":[116.07308197,-32.1238708496],"type":"Point"}
}