{
  "type": "Feature",
  "properties": {
    "iso:country":"AU",
    "sg:address":"Shop 1/ 225 Tower St",
    "sg:city":"Panania",
    "sg:classifiers":[
        {
            "category":"Food & Beverages",
            "subcategory":"Bakery",
            "type":"Retail Goods"
        }
    ],
    "sg:phone":"+61 2 9773 7628",
    "sg:postcode":"2213",
    "sg:province":"NSW",
    "sg:tags":[
        "baker"
    ],
    "wof:name":"Panania Bakery",
    "wof:placetype":"venue"
},
  "geometry": {"coordinates":[150.998199,-33.956264],"type":"Point"}
}