{
  "type": "Feature",
  "properties": {
    "addr:full":"Gough Drv Castle Hill NSW 2154",
    "addr:postcode":"2154",
    "addr:street":"Gough Drv",
    "iso:country":"AU",
    "sg:address":"Gough Drv",
    "sg:city":"Castle Hill",
    "sg:classifiers":[
        {
            "category":"Travel",
            "subcategory":"Hostel",
            "type":"Entertainment"
        }
    ],
    "sg:phone":"+61 2 9634 0595",
    "sg:postcode":"2154",
    "sg:province":"NSW",
    "sg:tags":[
        "home"
    ],
    "wof:name":"Anglican Retirement Villages",
    "wof:placetype":"venue"
},
  "geometry": {"coordinates":[151.02064514200001,-33.7313270569],"type":"Point"}
}