{
  "type": "Feature",
  "properties": {
    "addr:full":"Suite 33 7 Narabang Way Belrose NSW 2085",
    "addr:housenumber":"7",
    "addr:postcode":"2085",
    "addr:street":"Narabang Way",
    "iso:country":"AU",
    "sg:address":"Suite 33 7 Narabang Way",
    "sg:city":"Belrose",
    "sg:classifiers":[
        {
            "category":"Wholesale",
            "subcategory":"Machinery & Supplies",
            "type":"Manufacturing & Wholesale Goods"
        }
    ],
    "sg:phone":"+61 2 9986 1222",
    "sg:postcode":"2085",
    "sg:province":"NSW",
    "sg:tags":[
        "instrument",
        "scientific"
    ],
    "wof:name":"Scandinavian Electronics Pty Ltd",
    "wof:placetype":"venue"
},
  "geometry": {"coordinates":[151.212356567,-33.70520401],"type":"Point"}
}