{
  "type": "Feature",
  "properties": {
    "addr:full":"7 Bensley Pl Riverhills QLD 4074",
    "addr:housenumber":"7",
    "addr:postcode":"4074",
    "addr:street":"Bensley Pl",
    "iso:country":"AU",
    "sg:address":"7 Bensley Pl",
    "sg:city":"Riverhills",
    "sg:classifiers":[
        {
            "category":"Home & Garden",
            "subcategory":"Household Appliances",
            "type":"Retail Goods"
        }
    ],
    "sg:phone":"+61 7 3279 7999",
    "sg:postcode":"4074",
    "sg:province":"QLD",
    "sg:tags":[
        "equipment",
        "gas"
    ],
    "wof:name":"A Steven Watts Gasfitting Services",
    "wof:placetype":"venue"
},
  "geometry": {"coordinates":[152.90162658700001,-27.5619945526],"type":"Point"}
}