{
  "type": "Feature",
  "properties": {
    "addr:full":"122 Parramatta Rd Croydon NSW 2132",
    "addr:housenumber":"122",
    "addr:postcode":"2132",
    "addr:street":"Parramatta Rd",
    "iso:country":"AU",
    "sg:address":"122 Parramatta Rd",
    "sg:city":"Croydon",
    "sg:classifiers":[
        {
            "category":"Retail",
            "subcategory":"Auto Repair",
            "type":"Services"
        }
    ],
    "sg:phone":"+61 2 9744 2822",
    "sg:postcode":"2132",
    "sg:province":"NSW",
    "sg:tags":[
        "repairer",
        "motor",
        "engineer"
    ],
    "wof:name":"Sincere Motor Repairs Pty Ltd",
    "wof:placetype":"venue"
},
  "geometry": {"coordinates":[151.11436462399999,-33.8703079224],"type":"Point"}
}