{
  "type": "Feature",
  "properties": {
    "addr:full":"16 Dalkeith Rd Wantirna VIC 3152",
    "addr:housenumber":"16",
    "addr:postcode":"3152",
    "addr:street":"Dalkeith Rd",
    "iso:country":"AU",
    "sg:address":"16 Dalkeith Rd",
    "sg:city":"Wantirna",
    "sg:classifiers":[
        {
            "category":"Building & Trades",
            "subcategory":"Plumbing",
            "type":"Services"
        }
    ],
    "sg:phone":"+61 3 9729 7327",
    "sg:postcode":"3152",
    "sg:province":"VIC",
    "sg:tags":[
        "plumber",
        "gasfitters"
    ],
    "wof:name":"P J Plumbing Services Pty Ltd",
    "wof:placetype":"venue"
},
  "geometry": {"coordinates":[145.244384766,-37.8481369019],"type":"Point"}
}