{
  "type": "Feature",
  "properties": {
    "addr:full":"20 Ann St Williamstown VIC 3016",
    "addr:housenumber":"20",
    "addr:postcode":"3016",
    "addr:street":"Ann St",
    "iso:country":"AU",
    "sg:address":"20 Ann St",
    "sg:city":"Williamstown",
    "sg:classifiers":[
        {
            "category":"Ice Cream",
            "type":"Food & Drink"
        }
    ],
    "sg:phone":"+61 3 9397 2871",
    "sg:postcode":"3016",
    "sg:province":"VIC",
    "sg:tags":[
        "retail"
    ],
    "wof:name":"The Williamstown IceCream Factory",
    "wof:placetype":"venue"
},
  "geometry": {"coordinates":[144.90711975100001,-37.8652572632],"type":"Point"}
}