{
  "type": "Feature",
  "properties": {
    "addr:full":"61 Monaco Drv Zilzie QLD 4710",
    "addr:housenumber":"61",
    "addr:postcode":"4710",
    "addr:street":"Monaco Drv",
    "iso:country":"AU",
    "sg:address":"61 Monaco Drv",
    "sg:city":"Zilzie",
    "sg:classifiers":[
        {
            "category":"Restaurant",
            "type":"Food & Drink"
        }
    ],
    "sg:phone":"+61 7 4938 7577",
    "sg:postcode":"4710",
    "sg:province":"QLD",
    "wof:name":"Bay Bar & Restaurant The",
    "wof:placetype":"venue"
},
  "geometry": {"coordinates":[150.798981,-23.290686],"type":"Point"}
}