{
  "type": "Feature",
  "properties": {
    "iso:country":"AU",
    "sg:address":"13 Greenlands Ave",
    "sg:city":"Peakhurst",
    "sg:classifiers":[
        {
            "category":"Utilities",
            "subcategory":"Electric",
            "type":"Services"
        }
    ],
    "sg:phone":"+61 418 271 647",
    "sg:postcode":"2210",
    "sg:province":"NSW",
    "sg:tags":[
        "electrical",
        "contractor"
    ],
    "wof:name":"Electrical Maintenance Connections",
    "wof:placetype":"venue"
},
  "geometry": {"coordinates":[151.064804,-33.955078],"type":"Point"}
}