{
  "type": "Feature",
  "properties": {
    "iso:country":"AU",
    "sg:address":"Shop 1",
    "sg:city":"A Cnr Clare Mace Cres & Bon Mace Cl Berkeley",
    "sg:classifiers":[
        {
            "category":"Shopping",
            "subcategory":"Music",
            "type":"Retail Goods"
        }
    ],
    "sg:phone":"+61 2 4389 2550",
    "sg:postcode":"2261",
    "sg:province":"NSW",
    "sg:tags":[
        "instrument",
        "musical"
    ],
    "wof:name":"Prime Music",
    "wof:placetype":"venue"
},
  "geometry": {"coordinates":[151.4431,-33.359783],"type":"Point"}
}