{
  "type": "Feature",
  "properties": {
    "addr:full":"348 Auburn St Goulburn NSW 2580",
    "addr:housenumber":"348",
    "addr:postcode":"2580",
    "addr:street":"Auburn St",
    "iso:country":"AU",
    "sg:address":"348 Auburn St",
    "sg:city":"Goulburn",
    "sg:classifiers":[
        {
            "category":"Fast Food",
            "type":"Food & Drink"
        }
    ],
    "sg:phone":"+61 2 4821 9577",
    "sg:postcode":"2580",
    "sg:province":"NSW",
    "sg:tags":[
        "away",
        "take"
    ],
    "wof:name":"Goulburn Take Away Fresh Food Spot",
    "wof:placetype":"venue"
},
  "geometry": {"coordinates":[149.72091674800001,-34.7514381409],"type":"Point"}
}