{
  "type": "Feature",
  "properties": {
    "iso:country":"AU",
    "sg:address":"57 Campbell St",
    "sg:city":"Millmerran",
    "sg:classifiers":[
        {
            "category":"Cafe",
            "type":"Food & Drink"
        }
    ],
    "sg:phone":"+61 7 4695 1659",
    "sg:postcode":"4357",
    "sg:province":"QLD",
    "wof:name":"The Coffee Shoppe",
    "wof:placetype":"venue"
},
  "geometry": {"coordinates":[151.269363,-27.877977],"type":"Point"}
}