{
  "type": "Feature",
  "properties": {
    "addr:full":"404 Oxford St Mt Hawthorn WA 6016",
    "addr:housenumber":"404",
    "addr:postcode":"6016",
    "addr:street":"Oxford St Mt",
    "iso:country":"AU",
    "sg:address":"404 Oxford St",
    "sg:city":"Mt Hawthorn",
    "sg:classifiers":[
        {
            "category":"Fast Food",
            "type":"Food & Drink"
        }
    ],
    "sg:phone":"+61 8 9242 5051",
    "sg:postcode":"6016",
    "sg:province":"WA",
    "sg:tags":[
        "away",
        "take"
    ],
    "wof:name":"Oxford Streatz Lunch Bar",
    "wof:placetype":"venue"
},
  "geometry": {"coordinates":[115.841392517,-31.9231281281],"type":"Point"}
}