{
  "type": "Feature",
  "properties": {
    "iso:country":"AU",
    "sg:address":"16 Holland St",
    "sg:city":"Northgate",
    "sg:classifiers":[
        {
            "category":"Utilities",
            "subcategory":"Electric",
            "type":"Services"
        }
    ],
    "sg:phone":"+61 411 743 921",
    "sg:postcode":"4013",
    "sg:province":"QLD",
    "sg:tags":[
        "electrical",
        "contractor"
    ],
    "wof:name":"City View Electrical",
    "wof:placetype":"venue"
},
  "geometry": {"coordinates":[153.07139587399999,-27.3923740387],"type":"Point"}
}