{
  "type": "Feature",
  "properties": {
    "addr:full":"Suite 8, 43 Cordelia St South Brisbane QLD 4101",
    "addr:housenumber":"43",
    "addr:postcode":"4101",
    "addr:street":"Cordelia St",
    "iso:country":"AU",
    "sg:address":"Suite 8, 43 Cordelia St",
    "sg:city":"South Brisbane",
    "sg:classifiers":[
        {
            "category":"Manufacturing",
            "subcategory":"Food",
            "type":"Manufacturing & Wholesale Goods"
        }
    ],
    "sg:phone":"+61 7 3844 3340",
    "sg:postcode":"4101",
    "sg:province":"QLD",
    "sg:tags":[
        "function",
        "catering"
    ],
    "wof:name":"CMR Catering Services Pty Ltd",
    "wof:placetype":"venue"
},
  "geometry": {"coordinates":[153.016082764,-27.4765853882],"type":"Point"}
}