{
  "type": "Feature",
  "properties": {
    "addr:full":"3 Simper Crs Mt Barker SA 5251",
    "addr:housenumber":"3",
    "addr:postcode":"5251",
    "addr:street":"Simper Crs Mt",
    "iso:country":"AU",
    "sg:address":"3 Simper Crs",
    "sg:city":"Mt Barker",
    "sg:classifiers":[
        {
            "category":"Professional",
            "type":"Services"
        }
    ],
    "sg:phone":"+61 8 8398 4688",
    "sg:postcode":"5251",
    "sg:province":"SA",
    "sg:tags":[
        "packaging",
        "filling",
        "assembling"
    ],
    "wof:name":"Media Promotions",
    "wof:placetype":"venue"
},
  "geometry": {"coordinates":[138.85289001500001,-35.0617103577],"type":"Point"}
}