{
  "type": "Feature",
  "properties": {
    "addr:full":"141 Nicholson St Brunswick East VIC 3057",
    "addr:housenumber":"141",
    "addr:postcode":"3057",
    "addr:street":"Nicholson St",
    "iso:country":"AU",
    "sg:address":"141 Nicholson St",
    "sg:city":"Brunswick East",
    "sg:classifiers":[
        {
            "category":"Wholesale",
            "subcategory":"Office Equipment",
            "type":"Manufacturing & Wholesale Goods"
        }
    ],
    "sg:phone":"+61 1800 338 105",
    "sg:postcode":"3057",
    "sg:province":"VIC",
    "sg:tags":[
        "nail",
        "nailing"
    ],
    "wof:name":"Senco",
    "wof:placetype":"venue"
},
  "geometry": {"coordinates":[144.97926330600001,-37.7717666626],"type":"Point"}
}