{
  "type": "Feature",
  "properties": {
    "addr:full":"Fact 5, 505 Maroondah Hwy Ringwood VIC 3134",
    "addr:housenumber":"5",
    "addr:postcode":"505;3134",
    "addr:street":"Fact;Maroondah Hwy",
    "iso:country":"AU",
    "sg:address":"Fact 5, 505 Maroondah Hwy",
    "sg:city":"Ringwood",
    "sg:classifiers":[
        {
            "category":"Retail",
            "subcategory":"Repair Shop",
            "type":"Services"
        }
    ],
    "sg:phone":"+61 3 9704 8268",
    "sg:postcode":"3134",
    "sg:province":"VIC",
    "sg:tags":[
        "windscreen"
    ],
    "wof:name":"Elite Windscreens",
    "wof:placetype":"venue"
},
  "geometry": {"coordinates":[145.25247192399999,-37.7987327576],"type":"Point"}
}