{
  "type": "Feature",
  "properties": {
    "iso:country":"AU",
    "sg:address":"40 Panorama Rd",
    "sg:city":"Tamworth",
    "sg:classifiers":[
        {
            "category":"Retail",
            "subcategory":"Auto Rental",
            "type":"Services"
        }
    ],
    "sg:phone":"+61 429 612 817",
    "sg:postcode":"2340",
    "sg:province":"NSW",
    "sg:tags":[
        "car",
        "wedding"
    ],
    "wof:name":"Higher Cars",
    "wof:placetype":"venue"
},
  "geometry": {"coordinates":[150.947631836,-31.1343898773],"type":"Point"}
}