{
  "type": "Feature",
  "properties": {
    "iso:country":"AU",
    "sg:address":"1 Strachan Rd",
    "sg:city":"Bullsbrook",
    "sg:classifiers":[
        {
            "category":"Building & Trades",
            "subcategory":"Construction",
            "type":"Services"
        }
    ],
    "sg:phone":"+61 8 9571 1203",
    "sg:postcode":"6084",
    "sg:province":"WA",
    "sg:tags":[
        "earth",
        "excavating",
        "moving",
        "contractor"
    ],
    "wof:name":"G & S Ritchie",
    "wof:placetype":"venue"
},
  "geometry": {"coordinates":[115.99796295199999,-31.6668281555],"type":"Point"}
}