{
  "type": "Feature",
  "properties": {
    "addr:full":"Shp 7/ 10 Memorial Ave Tewantin QLD 4565",
    "addr:housenumber":"/ 10",
    "addr:postcode":"4565",
    "addr:street":"Memorial Ave",
    "iso:country":"AU",
    "sg:address":"Shp 7/ 10 Memorial Ave",
    "sg:city":"Tewantin",
    "sg:classifiers":[
        {
            "category":"Shopping",
            "subcategory":"Discount & Variety Stores",
            "type":"Retail Goods"
        }
    ],
    "sg:phone":"+61 7 5474 4788",
    "sg:postcode":"4565",
    "sg:province":"QLD",
    "sg:tags":[
        "shop",
        "adult"
    ],
    "wof:name":"Sensual Interludes",
    "wof:placetype":"venue"
},
  "geometry": {"coordinates":[153.039520264,-26.3935909271],"type":"Point"}
}