{
  "type": "Feature",
  "properties": {
    "addr:full":"106 Hertford St Sebastopol VIC 3356",
    "addr:housenumber":"106",
    "addr:postcode":"3356",
    "addr:street":"Hertford St",
    "iso:country":"AU",
    "sg:address":"106 Hertford St",
    "sg:city":"Sebastopol",
    "sg:classifiers":[
        {
            "category":"Retail",
            "subcategory":"Auto Repair",
            "type":"Services"
        }
    ],
    "sg:phone":"+61 3 5336 0666",
    "sg:postcode":"3356",
    "sg:province":"VIC",
    "sg:tags":[
        "testing",
        "inspection",
        "motor",
        "vehicle"
    ],
    "wof:name":"Hertford Street Mechanical Repairs",
    "wof:placetype":"venue"
},
  "geometry": {"coordinates":[143.82792699999999,-37.586903],"type":"Point"}
}