{
  "type": "Feature",
  "properties": {
    "addr:full":"18 Roebuck Ave Eagleby QLD 4207",
    "addr:housenumber":"18",
    "addr:postcode":"4207",
    "addr:street":"Roebuck Ave",
    "iso:country":"AU",
    "sg:address":"18 Roebuck Ave",
    "sg:city":"Eagleby",
    "sg:classifiers":[
        {
            "category":"Home & Garden",
            "subcategory":"Building Materials",
            "type":"Retail Goods"
        }
    ],
    "sg:phone":"+61 412 592 644",
    "sg:postcode":"4207",
    "sg:province":"QLD",
    "sg:tags":[
        "lawn",
        "cutting",
        "maintenance"
    ],
    "wof:name":"Mt Warren Mowing Service",
    "wof:placetype":"venue"
},
  "geometry": {"coordinates":[153.207519531,-27.7067012787],"type":"Point"}
}