{
  "type": "Feature",
  "properties": {
    "addr:full":"Unit 1, 33 Buchanan Rd Banyo QLD 4014",
    "addr:housenumber":"33",
    "addr:postcode":"4014",
    "addr:street":"Buchanan Rd",
    "iso:country":"AU",
    "sg:address":"Unit 1, 33 Buchanan Rd",
    "sg:city":"Banyo",
    "sg:classifiers":[
        {
            "category":"Professional",
            "subcategory":"Engineering",
            "type":"Services"
        }
    ],
    "sg:phone":"+61 7 3267 1170",
    "sg:postcode":"4014",
    "sg:province":"QLD",
    "sg:tags":[
        "electronic",
        "engineer"
    ],
    "sg:website":"http://www.onlineautomation.com.au",
    "wof:name":"Online Automation Pty Ltd",
    "wof:placetype":"venue"
},
  "geometry": {"coordinates":[153.093017578,-27.3855266571],"type":"Point"}
}