{
  "type": "Feature",
  "properties": {
    "addr:full":"Admiralty Drv Paradise Waters QLD 4217",
    "addr:postcode":"4217",
    "addr:street":"Admiralty Drv",
    "iso:country":"AU",
    "sg:address":"Admiralty Drv",
    "sg:city":"Paradise Waters",
    "sg:classifiers":[
        {
            "category":"Education",
            "subcategory":"Special Training",
            "type":"Public Place"
        }
    ],
    "sg:phone":"+61 419 706 325",
    "sg:postcode":"4217",
    "sg:province":"QLD",
    "sg:tags":[
        "development"
    ],
    "wof:name":"Superb Coaching",
    "wof:placetype":"venue"
},
  "geometry": {"coordinates":[153.42652893100001,-27.98736763],"type":"Point"}
}