{
  "type": "Feature",
  "properties": {
    "addr:full":"489 Crystal St Broken Hill NSW 2880",
    "addr:housenumber":"489",
    "addr:postcode":"2880",
    "addr:street":"Crystal St",
    "iso:country":"AU",
    "sg:address":"489 Crystal St",
    "sg:city":"Broken Hill",
    "sg:classifiers":[
        {
            "category":"Retail",
            "subcategory":"Storage",
            "type":"Services"
        }
    ],
    "sg:phone":"+61 8 8087 1100",
    "sg:postcode":"2880",
    "sg:province":"NSW",
    "sg:tags":[
        "removal",
        "furniture"
    ],
    "wof:name":"Broken Hill U-STORE-IT Units",
    "wof:placetype":"venue"
},
  "geometry": {"coordinates":[141.47396850600001,-31.954864502],"type":"Point"}
}