{
  "type": "Feature",
  "properties": {
    "iso:country":"AU",
    "sg:address":"PO Box 8002",
    "sg:city":"Newtown",
    "sg:classifiers":[
        {
            "category":"Education",
            "subcategory":"Dance Studio",
            "type":"Public Place"
        }
    ],
    "sg:phone":"+61 401 746 704",
    "sg:postcode":"3220",
    "sg:province":"VIC",
    "sg:tags":[
        "instruction",
        "language"
    ],
    "wof:name":"Alliance Francaise De Geelong",
    "wof:placetype":"venue"
},
  "geometry": {"coordinates":[144.344955,-38.15387],"type":"Point"}
}