{
  "type": "Feature",
  "properties": {
    "iso:country":"AU",
    "sg:address":"135 Marconi Rd",
    "sg:city":"Morisset",
    "sg:classifiers":[
        {
            "category":"Building & Trades",
            "subcategory":"Landscaping Services",
            "type":"Services"
        }
    ],
    "sg:phone":"+61 2 4973 2608",
    "sg:postcode":"2264",
    "sg:province":"NSW",
    "sg:tags":[
        "designer",
        "landscape",
        "contractor"
    ],
    "wof:name":"Arboreden",
    "wof:placetype":"venue"
},
  "geometry": {"coordinates":[151.506531,-33.10434],"type":"Point"}
}