{
  "type": "Feature",
  "properties": {
    "iso:country":"AU",
    "sg:address":"817a Ballarat Rd",
    "sg:city":"Deer Park",
    "sg:classifiers":[
        {
            "category":"Travel",
            "subcategory":"Travel Agent",
            "type":"Entertainment"
        }
    ],
    "sg:phone":"+61 3 9363 7941",
    "sg:postcode":"3023",
    "sg:province":"VIC",
    "sg:tags":[
        "consultant"
    ],
    "wof:name":"White Travel",
    "wof:placetype":"venue"
},
  "geometry": {"coordinates":[144.77314799999999,-37.770317],"type":"Point"}
}