{
  "type": "Feature",
  "properties": {
    "iso:country":"AU",
    "sg:address":"PO Box 767",
    "sg:city":"Kings Meadows",
    "sg:classifiers":[
        {
            "category":"Building & Trades",
            "subcategory":"Cleaning & Sanitation",
            "type":"Services"
        }
    ],
    "sg:phone":"+61 3 6344 4980",
    "sg:postcode":"7249",
    "sg:province":"TAS",
    "sg:tags":[
        "industrial",
        "commercial",
        "contractor"
    ],
    "wof:name":"Complete Cleaning Service",
    "wof:placetype":"venue"
},
  "geometry": {"coordinates":[147.16050720199999,-41.4677696228],"type":"Point"}
}