{
  "type": "Feature",
  "properties": {
    "iso:country":"AU",
    "sg:address":"8 Honeysuckle Drv",
    "sg:city":"Suffolk Park",
    "sg:classifiers":[
        {
            "category":"Professional",
            "subcategory":"Art Services",
            "type":"Services"
        }
    ],
    "sg:phone":"+61 2 6685 3241",
    "sg:postcode":"2481",
    "sg:province":"NSW",
    "sg:tags":[
        "picture",
        "frame",
        "framing"
    ],
    "wof:name":"Byron Bay Picture Framing",
    "wof:placetype":"venue"
},
  "geometry": {"coordinates":[153.610794067,-28.6892623901],"type":"Point"}
}