{
  "type": "Feature",
  "properties": {
    "iso:country":"AU",
    "sg:address":"8- 10 Parkhurst Drv",
    "sg:city":"Knoxfield",
    "sg:classifiers":[
        {
            "category":"Home & Garden",
            "subcategory":"Hardware",
            "type":"Retail Goods"
        }
    ],
    "sg:phone":"+61 3 9801 0088",
    "sg:postcode":"3180",
    "sg:province":"VIC",
    "sg:tags":[
        "compressor",
        "air"
    ],
    "wof:name":"Toolkwip Air Pipe Systems",
    "wof:placetype":"venue"
},
  "geometry": {"coordinates":[145.25250244099999,-37.8737487793],"type":"Point"}
}