{
  "type": "Feature",
  "properties": {
    "iso:country":"AU",
    "sg:address":"70 Princes Hwy",
    "sg:city":"Sylvania",
    "sg:classifiers":[
        {
            "category":"Building & Trades",
            "subcategory":"Landscaping Services",
            "type":"Services"
        }
    ],
    "sg:phone":"+61 2 9522 7215",
    "sg:postcode":"2224",
    "sg:province":"NSW",
    "sg:tags":[
        "designer",
        "landscape",
        "contractor"
    ],
    "wof:name":"Southern Belle Landscaping",
    "wof:placetype":"venue"
},
  "geometry": {"coordinates":[151.10890197800001,-34.0090026855],"type":"Point"}
}