{
  "type": "Feature",
  "properties": {
    "iso:country":"AU",
    "sg:address":"PO Box 811",
    "sg:city":"Kununurra",
    "sg:classifiers":[
        {
            "category":"Building & Trades",
            "subcategory":"Construction",
            "type":"Services"
        }
    ],
    "sg:phone":"+61 8 9168 2107",
    "sg:postcode":"6743",
    "sg:province":"WA",
    "sg:tags":[
        "fencing",
        "contractor"
    ],
    "wof:name":"Kununurra Mobile Welding Service",
    "wof:placetype":"venue"
},
  "geometry": {"coordinates":[128.73936462399999,-15.7726697922],"type":"Point"}
}