{
  "type": "Feature",
  "properties": {
    "iso:country":"AU",
    "sg:address":"3/ 17 Rowood Rd",
    "sg:city":"Prospect",
    "sg:classifiers":[
        {
            "category":"Building & Trades",
            "subcategory":"Cleaning & Sanitation",
            "type":"Services"
        }
    ],
    "sg:phone":"+61 2 9769 1822",
    "sg:postcode":"2148",
    "sg:province":"NSW",
    "sg:tags":[
        "commercial",
        "maintenance"
    ],
    "wof:name":"Albacore Constructions",
    "wof:placetype":"venue"
},
  "geometry": {"coordinates":[150.92318725600001,-33.8019752502],"type":"Point"}
}