{
  "type": "Feature",
  "properties": {
    "iso:country":"AU",
    "sg:address":"Building 4, 415 West Botany St",
    "sg:city":"Rockdale",
    "sg:classifiers":[
        {
            "category":"Wholesale",
            "subcategory":"Furniture",
            "type":"Manufacturing & Wholesale Goods"
        }
    ],
    "sg:phone":"+61 2 9748 6565",
    "sg:postcode":"2216",
    "sg:province":"NSW",
    "sg:tags":[
        "wholesaler",
        "mfrs"
    ],
    "wof:name":"Formway Furniture Ltd",
    "wof:placetype":"venue"
},
  "geometry": {"coordinates":[151.145218,-33.959888],"type":"Point"}
}