{
  "type": "Feature",
  "properties": {
    "addr:full":"3 Alan Rd Berowra Heights NSW 2082",
    "addr:housenumber":"3",
    "addr:postcode":"2082",
    "addr:street":"Alan Rd",
    "iso:country":"AU",
    "sg:address":"3 Alan Rd",
    "sg:city":"Berowra Heights",
    "sg:classifiers":[
        {
            "category":"Banks & Credit Unions",
            "subcategory":"Financial Services",
            "type":"Services"
        }
    ],
    "sg:phone":"+61 2 9456 4726",
    "sg:postcode":"2082",
    "sg:province":"NSW",
    "sg:tags":[
        "surge",
        "protection",
        "lightning"
    ],
    "wof:name":"Lightning Protection International NSW",
    "wof:placetype":"venue"
},
  "geometry": {"coordinates":[151.14010620100001,-33.6129989624],"type":"Point"}
}