{
  "type": "Feature",
  "properties": {
    "addr:full":"Shop 3, Ground Floor 151 Clarence St Sydney NSW 2000",
    "addr:housenumber":"shop 3;151",
    "addr:postcode":"2000",
    "addr:street":"Clarence St",
    "iso:country":"AU",
    "sg:address":"Shop 3, Ground Floor 151 Clarence St",
    "sg:city":"Sydney",
    "sg:classifiers":[
        {
            "category":"Professional",
            "subcategory":"Management & Consulting",
            "type":"Services"
        }
    ],
    "sg:phone":"+61 2 9248 0103",
    "sg:postcode":"2000",
    "sg:province":"NSW",
    "sg:tags":[
        "consultant",
        "migration"
    ],
    "wof:name":"TK Legal",
    "wof:placetype":"venue"
},
  "geometry": {"coordinates":[151.20504760700001,-33.867855072],"type":"Point"}
}