{
  "type": "Feature",
  "properties": {
    "iso:country":"AU",
    "sg:address":"Shop 12, 64-66 Bannister Rd",
    "sg:city":"Canning Vale",
    "sg:classifiers":[
        {
            "category":"Shopping",
            "subcategory":"Baby Store",
            "type":"Retail Goods"
        }
    ],
    "sg:phone":"+61 8 9456 1777",
    "sg:postcode":"6155",
    "sg:province":"WA",
    "sg:tags":[
        "wear"
    ],
    "wof:name":"Catholics Corner",
    "wof:placetype":"venue"
},
  "geometry": {"coordinates":[115.92614,-32.063076],"type":"Point"}
}