{
  "type": "Feature",
  "properties": {
    "iso:country":"AU",
    "sg:address":"59 Post Office Rd",
    "sg:city":"Smythes Creek",
    "sg:classifiers":[
        {
            "category":"Building & Trades",
            "subcategory":"Equipment Rental",
            "type":"Services"
        }
    ],
    "sg:phone":"+61 418 176 475",
    "sg:postcode":"3351",
    "sg:province":"VIC",
    "sg:tags":[
        "demolition",
        "contractor"
    ],
    "wof:name":"Calora Pty Ltd",
    "wof:placetype":"venue"
},
  "geometry": {"coordinates":[143.755753,-37.611],"type":"Point"}
}