{
  "type": "Feature",
  "properties": {
    "addr:full":"75 Dixon Rd Rockingham WA 6168",
    "addr:housenumber":"75",
    "addr:postcode":"6168",
    "addr:street":"Dixon Rd",
    "iso:country":"AU",
    "sg:address":"75 Dixon Rd",
    "sg:city":"Rockingham",
    "sg:classifiers":[
        {
            "category":"Retail",
            "subcategory":"Auto Repair",
            "type":"Services"
        }
    ],
    "sg:phone":"+61 8 9527 5755",
    "sg:postcode":"6168",
    "sg:province":"WA",
    "sg:tags":[
        "repairer",
        "motor",
        "engineer"
    ],
    "sg:website":"http://www.toyotaways.com.au",
    "wof:name":"Toyotaways",
    "wof:placetype":"venue"
},
  "geometry": {"coordinates":[115.76149700000001,-32.276848],"type":"Point"}
}