{
  "type": "Feature",
  "properties": {
    "addr:full":"109 Napier St St Arnaud VIC 3478",
    "addr:housenumber":"109",
    "addr:postcode":"3478",
    "addr:street":"Napier St",
    "iso:country":"AU",
    "sg:address":"109 Napier St St",
    "sg:city":"Arnaud",
    "sg:classifiers":[
        {
            "category":"Shopping",
            "subcategory":"Shoes",
            "type":"Retail Goods"
        }
    ],
    "sg:phone":"+61 3 5495 1206",
    "sg:postcode":"3478",
    "sg:province":"VIC",
    "sg:tags":[
        "footwear"
    ],
    "wof:name":"Boots &#034;N&#034; All",
    "wof:placetype":"venue"
},
  "geometry": {"coordinates":[142.98953247099999,-36.3740768433],"type":"Point"}
}