{
  "type": "Feature",
  "properties": {
    "addr:full":"31 Wombat St Berkeley Vale NSW 2261",
    "addr:housenumber":"31",
    "addr:postcode":"2261",
    "addr:street":"Wombat St",
    "iso:country":"AU",
    "sg:address":"31 Wombat St",
    "sg:city":"Berkeley Vale",
    "sg:classifiers":[
        {
            "category":"Banks & Credit Unions",
            "subcategory":"Bureau De Change",
            "type":"Services"
        }
    ],
    "sg:phone":"+61 2 4388 2169",
    "sg:postcode":"2261",
    "sg:province":"NSW",
    "sg:tags":[
        "archaeology"
    ],
    "wof:name":"Robert V J P Varman Ph D",
    "wof:placetype":"venue"
},
  "geometry": {"coordinates":[151.43585200000001,-33.332836],"type":"Point"}
}