{
  "type": "Feature",
  "properties": {
    "iso:country":"AU",
    "sg:address":"2 Centre Kirkham Rd",
    "sg:city":"Dandenong",
    "sg:classifiers":[
        {
            "category":"Personal",
            "subcategory":"Adult",
            "type":"Services"
        }
    ],
    "sg:phone":"+61 3 9792 4411",
    "sg:postcode":"3175",
    "sg:province":"VIC",
    "sg:tags":[
        "entertainment"
    ],
    "sg:website":"http://www.goe.com.au",
    "wof:name":"Garden Of Eden Relaxation Centre",
    "wof:placetype":"venue"
},
  "geometry": {"coordinates":[145.19566345199999,-37.9972839355],"type":"Point"}
}