{
  "type": "Feature",
  "properties": {
    "addr:full":"12 Ralston Rd Mt Gambier SA 5290",
    "addr:housenumber":"12",
    "addr:postcode":"5290",
    "addr:street":"Ralston Rd",
    "iso:country":"AU",
    "sg:address":"12 Ralston Rd",
    "sg:city":"Mt Gambier",
    "sg:classifiers":[
        {
            "category":"Farming",
            "subcategory":"Farm & Veterinary Services",
            "type":"Manufacturing & Wholesale Goods"
        }
    ],
    "sg:phone":"+61 8 8725 7321",
    "sg:postcode":"5290",
    "sg:province":"SA",
    "sg:tags":[
        "irrigation",
        "reticulation",
        "system"
    ],
    "wof:name":"Sims J C & F M",
    "wof:placetype":"venue"
},
  "geometry": {"coordinates":[140.80470275900001,-37.8344841003],"type":"Point"}
}