{
  "type": "Feature",
  "properties": {
    "iso:country":"AU",
    "sg:address":"Unit 3 14 Nello Pl",
    "sg:city":"Wetherill Park",
    "sg:classifiers":[
        {
            "category":"Wholesale",
            "subcategory":"Painting Supplies",
            "type":"Manufacturing & Wholesale Goods"
        }
    ],
    "sg:phone":"+61 2 9756 0730",
    "sg:postcode":"2164",
    "sg:province":"NSW",
    "sg:tags":[
        "product",
        "polyurethane"
    ],
    "wof:name":"Magic Poly Pty Ltd",
    "wof:placetype":"venue"
},
  "geometry": {"coordinates":[150.89378356899999,-33.8504104614],"type":"Point"}
}