{
  "type": "Feature",
  "properties": {
    "iso:country":"AU",
    "sg:address":"11 Merryburn Drv",
    "sg:city":"Tully",
    "sg:classifiers":[
        {
            "category":"Professional",
            "type":"Services"
        }
    ],
    "sg:phone":"+61 419 443 090",
    "sg:postcode":"4854",
    "sg:province":"QLD",
    "sg:tags":[
        "transport"
    ],
    "wof:name":"Jarra Creek Marketing Pty Ltd",
    "wof:placetype":"venue"
},
  "geometry": {"coordinates":[145.97651672399999,-17.9160194397],"type":"Point"}
}