{
  "type": "Feature",
  "properties": {
    "iso:country":"AU",
    "sg:address":"66 Wilson St",
    "sg:city":"Burnie",
    "sg:classifiers":[
        {
            "category":"Fast Food",
            "type":"Food & Drink"
        }
    ],
    "sg:phone":"+61 3 6431 9035",
    "sg:postcode":"7320",
    "sg:province":"TAS",
    "sg:tags":[
        "away",
        "take"
    ],
    "wof:name":"Fortuna Garden Chinese Restaurant",
    "wof:placetype":"venue"
},
  "geometry": {"coordinates":[145.906204,-41.052551],"type":"Point"}
}