{
  "type": "Feature",
  "properties": {
    "addr:full":"5/ 1a Hale St Botany NSW 2019",
    "addr:housenumber":"/ 1a",
    "addr:postcode":"2019",
    "addr:street":"Hale St",
    "iso:country":"AU",
    "sg:address":"5/ 1a Hale St",
    "sg:city":"Botany",
    "sg:classifiers":[
        {
            "category":"Professional",
            "subcategory":"Employment Agencies",
            "type":"Services"
        }
    ],
    "sg:phone":"+61 2 8304 4400",
    "sg:postcode":"2019",
    "sg:province":"NSW",
    "sg:tags":[
        "broker",
        "custom"
    ],
    "wof:name":"UTi",
    "wof:placetype":"venue"
},
  "geometry": {"coordinates":[151.196899414,-33.9470748901],"type":"Point"}
}