{
  "type": "Feature",
  "properties": {
    "addr:full":"Shop 1/ 38 Bell St Torquay VIC 3228",
    "addr:housenumber":"shop 1 / 38",
    "addr:postcode":"3228",
    "addr:street":"Bell St",
    "iso:country":"AU",
    "sg:address":"Shop 1/ 38 Bell St",
    "sg:city":"Torquay",
    "sg:classifiers":[
        {
            "category":"Fast Food",
            "type":"Food & Drink"
        }
    ],
    "sg:phone":"+61 3 5261 7114",
    "sg:postcode":"3228",
    "sg:province":"VIC",
    "sg:tags":[
        "away",
        "take"
    ],
    "wof:name":"Great Ocean Roast",
    "wof:placetype":"venue"
},
  "geometry": {"coordinates":[144.31883199999999,-38.33746],"type":"Point"}
}