{
  "type": "Feature",
  "properties": {
    "addr:full":"78 Monbulk Rd Kallista VIC 3791",
    "addr:housenumber":"78",
    "addr:postcode":"3791",
    "addr:street":"Monbulk Rd",
    "iso:country":"AU",
    "sg:address":"78 Monbulk Rd",
    "sg:city":"Kallista",
    "sg:classifiers":[
        {
            "category":"Cafe",
            "type":"Food & Drink"
        }
    ],
    "sg:phone":"+61 3 9755 2887",
    "sg:postcode":"3791",
    "sg:province":"VIC",
    "wof:name":"Kallista Deli",
    "wof:placetype":"venue"
},
  "geometry": {"coordinates":[145.36984252900001,-37.8843727112],"type":"Point"}
}