{
  "type": "Feature",
  "properties": {
    "iso:country":"AU",
    "sg:address":"42b Elbow St",
    "sg:city":"West Kempsey",
    "sg:classifiers":[
        {
            "category":"Professional",
            "subcategory":"Printing & Photocopies",
            "type":"Services"
        }
    ],
    "sg:phone":"+61 1300 733 626",
    "sg:postcode":"2440",
    "sg:province":"NSW",
    "sg:tags":[
        "photocopier"
    ],
    "wof:name":"Redman Business Equipment Pty Ltd",
    "wof:placetype":"venue"
},
  "geometry": {"coordinates":[152.830048,-31.080084],"type":"Point"}
}