{
  "type": "Feature",
  "properties": {
    "addr:full":"23 Edols St North Geelong VIC 3215",
    "addr:housenumber":"23",
    "addr:postcode":"3215",
    "addr:street":"Edols St",
    "iso:country":"AU",
    "sg:address":"23 Edols St",
    "sg:city":"North Geelong",
    "sg:classifiers":[
        {
            "category":"Manufacturing",
            "subcategory":"Tools & Machinery",
            "type":"Manufacturing & Wholesale Goods"
        }
    ],
    "sg:phone":"+61 3 5278 5753",
    "sg:postcode":"3215",
    "sg:province":"VIC",
    "sg:tags":[
        "crankshaft",
        "cylinder",
        "grinding"
    ],
    "wof:name":"Johnny Dyno Engines",
    "wof:placetype":"venue"
},
  "geometry": {"coordinates":[144.350708008,-38.1091384888],"type":"Point"}
}