{
  "type": "Feature",
  "properties": {
    "iso:country":"AU",
    "sg:address":"Suite 6/ 69-71 Rosstown Rd",
    "sg:city":"Carnegie",
    "sg:classifiers":[
        {
            "category":"Insurance",
            "subcategory":"Insurance Agent",
            "type":"Services"
        }
    ],
    "sg:phone":"+61 3 9572 5422",
    "sg:postcode":"3163",
    "sg:province":"VIC",
    "sg:tags":[
        "broker"
    ],
    "wof:name":"Shopping Centre Business Services",
    "wof:placetype":"venue"
},
  "geometry": {"coordinates":[145.05738830600001,-37.8861961365],"type":"Point"}
}