{
  "type": "Feature",
  "properties": {
    "iso:country":"AU",
    "sg:address":"31 Joadja Crs",
    "sg:city":"Glendenning",
    "sg:classifiers":[
        {
            "category":"Home & Garden",
            "subcategory":"Hardware",
            "type":"Retail Goods"
        }
    ],
    "sg:phone":"+61 2 9675 5122",
    "sg:postcode":"2761",
    "sg:province":"NSW",
    "sg:tags":[
        "trolley",
        "truck",
        "hand"
    ],
    "wof:name":"Retail Services Australia Pty Ltd",
    "wof:placetype":"venue"
},
  "geometry": {"coordinates":[150.854614,-33.741699],"type":"Point"}
}