{
  "type": "Feature",
  "properties": {
    "addr:full":"143 Old South Rd Reynella SA 5161",
    "addr:housenumber":"143",
    "addr:postcode":"5161",
    "addr:street":"Old South Rd",
    "iso:country":"AU",
    "sg:address":"143 Old South Rd",
    "sg:city":"Reynella",
    "sg:classifiers":[
        {
            "category":"Retail",
            "subcategory":"Storage",
            "type":"Services"
        }
    ],
    "sg:phone":"+61 8 8322 7122",
    "sg:postcode":"5161",
    "sg:province":"SA",
    "wof:name":"National Storage",
    "wof:placetype":"venue"
},
  "geometry": {"coordinates":[138.537277222,-35.0956687927],"type":"Point"}
}