{
  "type": "Feature",
  "properties": {
    "addr:full":"6 Walpole Crs Wetherill Park NSW 2164",
    "addr:housenumber":"6",
    "addr:postcode":"2164",
    "addr:street":"Walpole Crs",
    "iso:country":"AU",
    "sg:address":"6 Walpole Crs",
    "sg:city":"Wetherill Park",
    "sg:classifiers":[
        {
            "category":"Building & Trades",
            "subcategory":"Construction",
            "type":"Services"
        }
    ],
    "sg:phone":"+61 404 040 528",
    "sg:postcode":"2164",
    "sg:province":"NSW",
    "sg:tags":[
        "concrete",
        "contractor"
    ],
    "wof:name":"Suburban Concreting",
    "wof:placetype":"venue"
},
  "geometry": {"coordinates":[150.90489196799999,-33.8546104431],"type":"Point"}
}