{
  "type": "Feature",
  "properties": {
    "iso:country":"AU",
    "sg:address":"(Opp. Novotel Hotel) 274-276 Springvale Rd",
    "sg:city":"Glen Waverley",
    "sg:classifiers":[
        {
            "category":"Health Services",
            "subcategory":"Medical Lab",
            "type":"Services"
        }
    ],
    "sg:phone":"+61 3 9574 9053",
    "sg:postcode":"3150",
    "sg:province":"VIC",
    "sg:tags":[
        "laboratory",
        "dental"
    ],
    "wof:name":"Andrews Chris Dental Laboratory",
    "wof:placetype":"venue"
},
  "geometry": {"coordinates":[145.16560363799999,-37.8821258545],"type":"Point"}
}