{
  "type": "Feature",
  "properties": {
    "addr:full":"Shd3/ 38 Grandview Pde Moolap VIC 3221",
    "addr:housenumber":"38",
    "addr:postcode":"3221",
    "addr:street":"Grandview Pde",
    "iso:country":"AU",
    "sg:address":"Shd3/ 38 Grandview Pde",
    "sg:city":"Moolap",
    "sg:classifiers":[
        {
            "category":"Wholesale",
            "subcategory":"Metals & Minerals",
            "type":"Manufacturing & Wholesale Goods"
        }
    ],
    "sg:phone":"+61 3 5248 3303",
    "sg:postcode":"3221",
    "sg:province":"VIC",
    "sg:tags":[
        "steel",
        "stainless",
        "product",
        "equipment"
    ],
    "wof:name":"Instyle & Stainless",
    "wof:placetype":"venue"
},
  "geometry": {"coordinates":[144.41888399999999,-38.168404],"type":"Point"}
}