{
  "type": "Feature",
  "properties": {
    "addr:full":"5B Howes St Airport West VIC 3042",
    "addr:housenumber":"5b",
    "addr:postcode":"3042",
    "addr:street":"Howes St",
    "iso:country":"AU",
    "sg:address":"5B Howes St",
    "sg:city":"Airport West",
    "sg:classifiers":[
        {
            "category":"Autos & Motor Vehicles",
            "subcategory":"Auto Supplies",
            "type":"Retail Goods"
        }
    ],
    "sg:phone":"+61 3 9338 5518",
    "sg:postcode":"3042",
    "sg:province":"VIC",
    "sg:tags":[
        "part",
        "cycles",
        "accessory"
    ],
    "wof:name":"Airport West Motorcycles",
    "wof:placetype":"venue"
},
  "geometry": {"coordinates":[144.88958740199999,-37.71534729],"type":"Point"}
}