{
  "type": "Feature",
  "properties": {
    "iso:country":"AU",
    "sg:address":"80 Hayden Brook Rd",
    "sg:city":"Woodrising",
    "sg:classifiers":[
        {
            "category":"Shopping",
            "subcategory":"Party Supplies",
            "type":"Retail Goods"
        }
    ],
    "sg:phone":"+61 2 4959 5531",
    "sg:postcode":"2284",
    "sg:province":"NSW",
    "sg:tags":[
        "children's"
    ],
    "wof:name":"Seeds Circus",
    "wof:placetype":"venue"
},
  "geometry": {"coordinates":[151.60585022000001,-32.9816513062],"type":"Point"}
}