{
  "type": "Feature",
  "properties": {
    "addr:full":"7 Rawlinson St O'Connor WA 6163",
    "addr:housenumber":"7",
    "addr:postcode":"6163",
    "addr:street":"Rawlinson St",
    "iso:country":"AU",
    "sg:address":"7 Rawlinson St",
    "sg:city":"O'Connor",
    "sg:classifiers":[
        {
            "category":"Professional",
            "subcategory":"Engineering",
            "type":"Services"
        }
    ],
    "sg:phone":"+61 8 9337 4566",
    "sg:postcode":"6163",
    "sg:province":"WA",
    "sg:tags":[
        "engineer"
    ],
    "wof:name":"Baguley Engineering",
    "wof:placetype":"venue"
},
  "geometry": {"coordinates":[115.802589,-32.058704],"type":"Point"}
}