{
  "type": "Feature",
  "properties": {
    "addr:full":"Level 5 64 Northbourne Ave Canberra City ACT 2601",
    "addr:housenumber":"64",
    "addr:postcode":"2601",
    "addr:street":"Northbourne Ave",
    "iso:country":"AU",
    "sg:address":"Level 5 64 Northbourne Ave",
    "sg:city":"Canberra City",
    "sg:classifiers":[
        {
            "category":"Professional",
            "subcategory":"Management & Consulting",
            "type":"Services"
        }
    ],
    "sg:phone":"+61 2 6245 5800",
    "sg:postcode":"2601",
    "sg:province":"ACT",
    "sg:tags":[
        "consultant",
        "business"
    ],
    "wof:name":"United Group Services Pty Limited",
    "wof:placetype":"venue"
},
  "geometry": {"coordinates":[149.129837036,-35.2774124146],"type":"Point"}
}