{
  "type": "Feature",
  "properties": {
    "addr:full":"23/ 193 Southpine Rd Brendale QLD 4500",
    "addr:housenumber":"23 / 193",
    "addr:postcode":"4500",
    "addr:street":"Southpine Rd",
    "iso:country":"AU",
    "sg:address":"23/ 193 Southpine Rd",
    "sg:city":"Brendale",
    "sg:classifiers":[
        {
            "category":"Banks & Credit Unions",
            "subcategory":"Investment Brokerage",
            "type":"Services"
        }
    ],
    "sg:phone":"+61 7 3205 6196",
    "sg:postcode":"4500",
    "sg:province":"QLD",
    "sg:tags":[
        "shutter",
        "louvre"
    ],
    "wof:name":"Coastal Louvres & Blinds",
    "wof:placetype":"venue"
},
  "geometry": {"coordinates":[153.004394531,-27.3167686462],"type":"Point"}
}