{
  "type": "Feature",
  "properties": {
    "addr:full":"109 Carpenter St Bendigo VIC 3539",
    "addr:housenumber":"109",
    "addr:postcode":"3539",
    "addr:street":"Carpenter St",
    "iso:country":"AU",
    "sg:address":"109 Carpenter St",
    "sg:city":"Bendigo",
    "sg:classifiers":[
        {
            "category":"Personal",
            "subcategory":"Massage",
            "type":"Services"
        }
    ],
    "sg:phone":"+61 3 5441 3396",
    "sg:postcode":"3539",
    "sg:province":"VIC",
    "sg:tags":[
        "therapy"
    ],
    "wof:name":"Allure",
    "wof:placetype":"venue"
},
  "geometry": {"coordinates":[144.28486599999999,-36.779167],"type":"Point"}
}