{
  "type": "Feature",
  "properties": {
    "iso:country":"AU",
    "sg:address":"109 Carpenter St",
    "sg:city":"Bendigo",
    "sg:classifiers":[
        {
            "category":"Personal",
            "subcategory":"Massage",
            "type":"Services"
        }
    ],
    "sg:phone":"+61 3 5441 3396",
    "sg:postcode":"3539",
    "sg:province":"VIC",
    "sg:tags":[
        "therapy"
    ],
    "wof:name":"Allure",
    "wof:placetype":"venue"
},
  "geometry": {"coordinates":[144.284866,-36.779167],"type":"Point"}
}