{
  "type": "Feature",
  "properties": {
    "addr:full":"107 Darby St Newcastle NSW 2300",
    "addr:housenumber":"107",
    "addr:postcode":"2300",
    "addr:street":"Darby St",
    "iso:country":"AU",
    "sg:address":"107 Darby St",
    "sg:city":"Newcastle",
    "sg:classifiers":[
        {
            "category":"Professional",
            "subcategory":"Accounting & Tax Preparation",
            "type":"Services"
        }
    ],
    "sg:phone":"+61 2 4929 1899",
    "sg:postcode":"2300",
    "sg:province":"NSW",
    "sg:tags":[
        "consultant",
        "taxation"
    ],
    "wof:name":"Davidson Accountants",
    "wof:placetype":"venue"
},
  "geometry": {"coordinates":[151.772324,-32.930973],"type":"Point"}
}