{
  "type": "Feature",
  "properties": {
    "iso:country":"AU",
    "sg:address":"PO Box 4208",
    "sg:city":"Maroubra South",
    "sg:classifiers":[
        {
            "category":"Personal",
            "subcategory":"Skin Care",
            "type":"Services"
        }
    ],
    "sg:phone":"+61 413 707 858",
    "sg:postcode":"2035",
    "sg:province":"NSW",
    "sg:tags":[
        "hair",
        "product"
    ],
    "wof:name":"Glide Hair Tools",
    "wof:placetype":"venue"
},
  "geometry": {"coordinates":[151.24659729000001,-33.9488601685],"type":"Point"}
}