{
  "type": "Feature",
  "properties": {
    "iso:country":"AU",
    "sg:address":"43 Fishery Point Rd",
    "sg:city":"Mirrabooka",
    "sg:classifiers":[
        {
            "category":"Home & Garden",
            "subcategory":"Building Materials",
            "type":"Retail Goods"
        }
    ],
    "sg:phone":"+61 2 4973 2431",
    "sg:postcode":"2264",
    "sg:province":"NSW",
    "sg:tags":[
        "ventilating",
        "equipment",
        "system"
    ],
    "wof:name":"Airtech Ventilation & Skylights",
    "wof:placetype":"venue"
},
  "geometry": {"coordinates":[151.54939300000001,-33.106342],"type":"Point"}
}