{
  "type": "Feature",
  "properties": {
    "iso:country":"AU",
    "sg:address":"Elanora Rd",
    "sg:city":"Elanora Heights",
    "sg:classifiers":[
        {
            "category":"Education",
            "subcategory":"University",
            "type":"Public Place"
        }
    ],
    "sg:phone":"+61 2 9913 7124",
    "sg:postcode":"2101",
    "sg:province":"NSW",
    "sg:tags":[
        "educational",
        "organisation",
        "cultural"
    ],
    "wof:name":"Girl Guides Asscn (NSW)",
    "wof:placetype":"venue"
},
  "geometry": {"coordinates":[151.27969400000001,-33.701027],"type":"Point"}
}