{
  "type": "Feature",
  "properties": {
    "addr:full":"758 Pacific Hwy Gordon NSW 2072",
    "addr:housenumber":"758",
    "addr:postcode":"2072",
    "addr:street":"Pacific Hwy",
    "iso:country":"AU",
    "sg:address":"758 Pacific Hwy",
    "sg:city":"Gordon",
    "sg:classifiers":[
        {
            "category":"Health Services",
            "subcategory":"Dentist",
            "type":"Services"
        }
    ],
    "sg:phone":"+61 2 9499 2878",
    "sg:postcode":"2072",
    "sg:province":"NSW",
    "sg:tags":[
        "dental",
        "emergency"
    ],
    "wof:name":"Pak Stephen",
    "wof:placetype":"venue"
},
  "geometry": {"coordinates":[151.152908325,-33.7565917969],"type":"Point"}
}