{
  "type": "Feature",
  "properties": {
    "iso:country":"AU",
    "sg:address":"Suite 3/Lvl 2 505 Old Northern Rd",
    "sg:city":"Castle Hill",
    "sg:classifiers":[
        {
            "category":"Professional",
            "subcategory":"Computer Services",
            "type":"Services"
        }
    ],
    "sg:phone":"+61 2 9899 8702",
    "sg:postcode":"2154",
    "sg:province":"NSW",
    "sg:tags":[
        "package",
        "software"
    ],
    "wof:name":"Business Thinking Systems",
    "wof:placetype":"venue"
},
  "geometry": {"coordinates":[151.01864624000001,-33.7261314392],"type":"Point"}
}