{
  "type": "Feature",
  "properties": {
    "addr:full":"Brisbane Markets, 385 Sherwood Rd Rocklea QLD 4106",
    "addr:housenumber":"385",
    "addr:postcode":"4106",
    "addr:street":"Sherwood Rd",
    "iso:country":"AU",
    "sg:address":"Brisbane Markets, 385 Sherwood Rd",
    "sg:city":"Rocklea",
    "sg:classifiers":[
        {
            "category":"Wholesale",
            "subcategory":"Photographic Equipment",
            "type":"Manufacturing & Wholesale Goods"
        }
    ],
    "sg:phone":"+61 7 3716 0366",
    "sg:postcode":"4106",
    "sg:province":"QLD",
    "sg:tags":[
        "hire",
        "nursery"
    ],
    "wof:name":"All About Bubs Pty Ltd",
    "wof:placetype":"venue"
},
  "geometry": {"coordinates":[153.000244141,-27.5356426239],"type":"Point"}
}