{
  "type": "Feature",
  "properties": {
    "addr:full":"5 Strehlow St Alice Springs NT 0870",
    "addr:housenumber":"5",
    "addr:postcode":"nt 0870",
    "addr:street":"Strehlow St",
    "iso:country":"AU",
    "sg:address":"5 Strehlow St",
    "sg:city":"Alice Springs",
    "sg:classifiers":[
        {
            "category":"Travel",
            "subcategory":"Hotels & Motels",
            "type":"Entertainment"
        }
    ],
    "sg:phone":"+61 8 8953 8033",
    "sg:postcode":"0870",
    "sg:province":"NT",
    "sg:tags":[
        "accommodation"
    ],
    "wof:name":"Alice On Todd",
    "wof:placetype":"venue"
},
  "geometry": {"coordinates":[133.875244141,-23.7147121429],"type":"Point"}
}