{
  "type": "Feature",
  "properties": {
    "iso:country":"AU",
    "sg:address":"312 Victoria Ave",
    "sg:city":"Chatswood",
    "sg:classifiers":[
        {
            "category":"Personal",
            "subcategory":"Beauty Salon",
            "type":"Services"
        }
    ],
    "sg:phone":"+61 2 9411 5154",
    "sg:postcode":"2067",
    "sg:province":"NSW",
    "sg:tags":[
        "hairdresser"
    ],
    "wof:name":"Epique Hair & Body",
    "wof:placetype":"venue"
},
  "geometry": {"coordinates":[151.185623169,-33.7956542969],"type":"Point"}
}