{
  "type": "Feature",
  "properties": {
    "iso:country":"AU",
    "sg:address":"Unit 16, 56 Norcal Rd",
    "sg:city":"Nunawading",
    "sg:classifiers":[
        {
            "category":"Professional",
            "subcategory":"Detective & Security Services",
            "type":"Services"
        }
    ],
    "sg:phone":"+61 1300 551 662",
    "sg:postcode":"3131",
    "sg:province":"VIC",
    "sg:tags":[
        "consultant",
        "system"
    ],
    "wof:name":"Vitag Retail Loss Prevention",
    "wof:placetype":"venue"
},
  "geometry": {"coordinates":[145.16784668,-37.820400238],"type":"Point"}
}