{
  "type": "Feature",
  "properties": {
    "iso:country":"AU",
    "sg:address":"Shp133/ 85 Reynolds St",
    "sg:city":"Balmain",
    "sg:classifiers":[
        {
            "category":"Real Estate",
            "subcategory":"Architect",
            "type":"Services"
        }
    ],
    "sg:phone":"+61 2 9810 4426",
    "sg:postcode":"2041",
    "sg:province":"NSW",
    "wof:name":"Adinc Australia Pty ltd",
    "wof:placetype":"venue"
},
  "geometry": {"coordinates":[151.177933,-33.861027],"type":"Point"}
}