{
  "type": "Feature",
  "properties": {
    "addr:full":"429 Wondall Rd Wynnum QLD 4178",
    "addr:housenumber":"429",
    "addr:postcode":"4178",
    "addr:street":"Wondall Rd",
    "iso:country":"AU",
    "sg:address":"429 Wondall Rd",
    "sg:city":"Wynnum",
    "sg:classifiers":[
        {
            "category":"Building & Trades",
            "subcategory":"Plumbing",
            "type":"Services"
        }
    ],
    "sg:phone":"+61 7 3396 4993",
    "sg:postcode":"4178",
    "sg:province":"QLD",
    "sg:tags":[
        "pump",
        "repairer"
    ],
    "wof:name":"Bayside Pool & Spa Centre",
    "wof:placetype":"venue"
},
  "geometry": {"coordinates":[153.16688537600001,-27.4547786713],"type":"Point"}
}