{
  "type": "Feature",
  "properties": {
    "addr:full":"309 Townsend St Albury NSW 2640",
    "addr:housenumber":"309",
    "addr:postcode":"2640",
    "addr:street":"Townsend St",
    "iso:country":"AU",
    "sg:address":"309 Townsend St",
    "sg:city":"Albury",
    "sg:classifiers":[
        {
            "category":"Retail",
            "subcategory":"Auto Repair",
            "type":"Services"
        }
    ],
    "sg:phone":"+61 2 6041 3893",
    "sg:postcode":"2640",
    "sg:province":"NSW",
    "sg:tags":[
        "repairer",
        "motor",
        "engineer"
    ],
    "wof:name":"Albury Ice Radiators",
    "wof:placetype":"venue"
},
  "geometry": {"coordinates":[146.912765503,-36.081199646],"type":"Point"}
}