{
  "type": "Feature",
  "properties": {
    "addr:full":"17 Manufacturer Drv Ernest QLD 4214",
    "addr:housenumber":"17",
    "addr:postcode":"4214",
    "addr:street":"Manufacturer Drv Ernest",
    "iso:country":"AU",
    "sg:address":"17 Manufacturer Drv",
    "sg:city":"Ernest",
    "sg:classifiers":[
        {
            "category":"Wholesale",
            "subcategory":"Auto Parts",
            "type":"Manufacturing & Wholesale Goods"
        }
    ],
    "sg:phone":"+61 7 5594 0918",
    "sg:postcode":"4214",
    "sg:province":"QLD",
    "sg:tags":[
        "recyclers"
    ],
    "wof:name":"The Ford Shed",
    "wof:placetype":"venue"
},
  "geometry": {"coordinates":[153.363449097,-27.9651622772],"type":"Point"}
}