{
  "type": "Feature",
  "properties": {
    "iso:country":"AU",
    "sg:address":"12 Foster Rd",
    "sg:city":"Eltham",
    "sg:classifiers":[
        {
            "category":"Building & Trades",
            "subcategory":"Construction",
            "type":"Services"
        }
    ],
    "sg:phone":"+61 3 9439 1542",
    "sg:postcode":"3095",
    "sg:province":"VIC",
    "sg:tags":[
        "home",
        "air conditioning"
    ],
    "wof:name":"Airosmith",
    "wof:placetype":"venue"
},
  "geometry": {"coordinates":[145.16619873100001,-37.7061347961],"type":"Point"}
}