{
  "type": "Feature",
  "properties": {
    "iso:country":"AU",
    "sg:address":"58 Oratava Ave",
    "sg:city":"West Pennant Hills",
    "sg:classifiers":[
        {
            "category":"Professional",
            "subcategory":"Engineering",
            "type":"Services"
        }
    ],
    "sg:phone":"+61 414 420 943",
    "sg:postcode":"2125",
    "sg:province":"NSW",
    "sg:tags":[
        "engineer"
    ],
    "wof:name":"C H E Engineering Pty Ltd",
    "wof:placetype":"venue"
},
  "geometry": {"coordinates":[151.042724609,-33.749584198],"type":"Point"}
}