{
  "type": "Feature",
  "properties": {
    "addr:full":"193 Springvale Rd Nunawading VIC 3131",
    "addr:housenumber":"193",
    "addr:postcode":"3131",
    "addr:street":"Springvale Rd",
    "iso:country":"AU",
    "sg:address":"193 Springvale Rd",
    "sg:city":"Nunawading",
    "sg:classifiers":[
        {
            "category":"Autos & Motor Vehicles",
            "subcategory":"Fuel & Gas Station",
            "type":"Retail Goods"
        }
    ],
    "sg:phone":"+61 3 9877 6055",
    "sg:postcode":"3131",
    "sg:province":"VIC",
    "wof:name":"Caltex Nunawading",
    "wof:placetype":"venue"
},
  "geometry": {"coordinates":[145.175704956,-37.8215560913],"type":"Point"}
}