{
  "type": "Feature",
  "properties": {
    "addr:full":"4/ 212 Glen Osmond Rd Fullarton SA 5063",
    "addr:housenumber":"/ 212",
    "addr:postcode":"5063",
    "addr:street":"Glen Osmond Rd",
    "iso:country":"AU",
    "sg:address":"4/ 212 Glen Osmond Rd",
    "sg:city":"Fullarton",
    "sg:classifiers":[
        {
            "category":"Banks & Credit Unions",
            "subcategory":"Financial Services",
            "type":"Services"
        }
    ],
    "sg:phone":"+61 8 8379 0888",
    "sg:postcode":"5063",
    "sg:province":"SA",
    "sg:tags":[
        "planning"
    ],
    "wof:name":"Andrew Varga & Associates",
    "wof:placetype":"venue"
},
  "geometry": {"coordinates":[138.629837036,-34.9491882324],"type":"Point"}
}