{
  "type": "Feature",
  "properties": {
    "iso:country":"AU",
    "sg:address":"32 Cupania Crs",
    "sg:city":"Garden Suburb",
    "sg:classifiers":[
        {
            "category":"Building & Trades",
            "subcategory":"Construction",
            "type":"Services"
        }
    ],
    "sg:phone":"+61 2 4954 3311",
    "sg:postcode":"2289",
    "sg:province":"NSW",
    "sg:tags":[
        "contractor"
    ],
    "wof:name":"Pollicino F",
    "wof:placetype":"venue"
},
  "geometry": {"coordinates":[151.679962158,-32.9444084167],"type":"Point"}
}