{
  "type": "Feature",
  "properties": {
    "addr:full":"160 Grassdale Rd Gumdale QLD 4154",
    "addr:housenumber":"160",
    "addr:postcode":"4154",
    "addr:street":"Grassdale Rd",
    "iso:country":"AU",
    "sg:address":"160 Grassdale Rd",
    "sg:city":"Gumdale",
    "sg:classifiers":[
        {
            "category":"Conference Center",
            "type":"Public Place"
        }
    ],
    "sg:phone":"+61 7 3390 5075",
    "sg:postcode":"4154",
    "sg:province":"QLD",
    "sg:tags":[
        "venue",
        "convention"
    ],
    "wof:name":"The Grassdale Country Club Ltd",
    "wof:placetype":"venue"
},
  "geometry": {"coordinates":[153.15802001899999,-27.4989738464],"type":"Point"}
}