{
  "type": "Feature",
  "properties": {
    "addr:full":"16 Coolibah Drv Greenwood WA 6024",
    "addr:housenumber":"16",
    "addr:postcode":"6024",
    "addr:street":"Coolibah Drv",
    "iso:country":"AU",
    "sg:address":"16 Coolibah Drv",
    "sg:city":"Greenwood",
    "sg:classifiers":[
        {
            "category":"Health Services",
            "subcategory":"Health Practitioner",
            "type":"Services"
        }
    ],
    "sg:phone":"+61 8 9447 9833",
    "sg:postcode":"6024",
    "sg:province":"WA",
    "sg:tags":[
        "physiotherapist"
    ],
    "wof:name":"LifeCare Physiotherapy Centres",
    "wof:placetype":"venue"
},
  "geometry": {"coordinates":[115.80178832999999,-31.8326358795],"type":"Point"}
}