{
  "type": "Feature",
  "properties": {
    "addr:full":"155 McDougall St Toowoomba QLD 4350",
    "addr:housenumber":"155",
    "addr:postcode":"4350",
    "addr:street":"Mcdougall St",
    "iso:country":"AU",
    "sg:address":"155 McDougall St",
    "sg:city":"Toowoomba",
    "sg:classifiers":[
        {
            "category":"Autos & Motor Vehicles",
            "subcategory":"Auto Supplies",
            "type":"Retail Goods"
        }
    ],
    "sg:phone":"+61 7 4634 5559",
    "sg:postcode":"4350",
    "sg:province":"QLD",
    "sg:tags":[
        "equipment",
        "part",
        "truck"
    ],
    "wof:name":"Toowoomba Exhaust Centre",
    "wof:placetype":"venue"
},
  "geometry": {"coordinates":[151.90756200000001,-27.559626],"type":"Point"}
}