{
  "type": "Feature",
  "properties": {
    "iso:country":"AU",
    "sg:address":"155 McDougall St",
    "sg:city":"Toowoomba",
    "sg:classifiers":[
        {
            "category":"Autos & Motor Vehicles",
            "subcategory":"Auto Supplies",
            "type":"Retail Goods"
        }
    ],
    "sg:phone":"+61 7 4634 5559",
    "sg:postcode":"4350",
    "sg:province":"QLD",
    "sg:tags":[
        "equipment",
        "part",
        "truck"
    ],
    "wof:name":"Toowoomba Exhaust Centre",
    "wof:placetype":"venue"
},
  "geometry": {"coordinates":[151.907562,-27.559626],"type":"Point"}
}