{
  "type": "Feature",
  "properties": {
    "addr:full":"Cnr Devon & Liverpool Rds Ingleburn NSW 2565",
    "addr:postcode":"2565",
    "addr:street":"Cnr",
    "iso:country":"AU",
    "sg:address":"Cnr Devon & Liverpool Rds",
    "sg:city":"Ingleburn",
    "sg:classifiers":[
        {
            "category":"Autos & Motor Vehicles",
            "subcategory":"Auto Supplies",
            "type":"Retail Goods"
        }
    ],
    "sg:phone":"+61 2 9829 7555",
    "sg:postcode":"2565",
    "sg:province":"NSW",
    "sg:tags":[
        "oil",
        "spirit"
    ],
    "wof:name":"Atlantic Lubricants",
    "wof:placetype":"venue"
},
  "geometry": {"coordinates":[150.85906982399999,-34.0012550354],"type":"Point"}
}