{
  "type": "Feature",
  "properties": {
    "iso:country":"AU",
    "sg:address":"PO Box 69",
    "sg:city":"Mt Barker",
    "sg:classifiers":[
        {
            "category":"Shopping",
            "subcategory":"Antiques",
            "type":"Retail Goods"
        }
    ],
    "sg:phone":"+61 8 8398 4938",
    "sg:postcode":"5251",
    "sg:province":"SA",
    "sg:tags":[
        "restoration",
        "reproduction"
    ],
    "wof:name":"Adelaide Hills Upholstery",
    "wof:placetype":"venue"
},
  "geometry": {"coordinates":[138.86329650900001,-35.0572738647],"type":"Point"}
}