{
  "type": "Feature",
  "properties": {
    "addr:full":"15 Randle Rd Pinkenba QLD 4008",
    "addr:housenumber":"15",
    "addr:postcode":"4008",
    "addr:street":"Randle Rd",
    "iso:country":"AU",
    "sg:address":"15 Randle Rd",
    "sg:city":"Pinkenba",
    "sg:classifiers":[
        {
            "category":"Farming",
            "subcategory":"Fish & Marine Products",
            "type":"Manufacturing & Wholesale Goods"
        }
    ],
    "sg:phone":"+61 7 3260 2622",
    "sg:postcode":"4008",
    "sg:province":"QLD",
    "sg:tags":[
        "bitumen"
    ],
    "wof:name":"SAMI Bitumen Technologies",
    "wof:placetype":"venue"
},
  "geometry": {"coordinates":[153.10894775400001,-27.429649353],"type":"Point"}
}