{
  "type": "Feature",
  "properties": {
    "addr:full":"11 Charleroi Rd Belrose NSW 2085",
    "addr:postcode":"2085",
    "addr:street":"Charleroi Rd",
    "iso:country":"AU",
    "sg:address":"11 Charleroi Rd",
    "sg:city":"Belrose",
    "sg:classifiers":[
        {
            "category":"Professional",
            "subcategory":"Accounting & Tax Preparation",
            "type":"Services"
        }
    ],
    "sg:phone":"+61 2 9451 0076",
    "sg:postcode":"2085",
    "sg:province":"NSW",
    "sg:tags":[
        "accountant",
        "auditor"
    ],
    "wof:name":"R Lorking & Co",
    "wof:placetype":"venue"
},
  "geometry": {"coordinates":[151.21658325199999,-33.7236862183],"type":"Point"}
}