{
  "type": "Feature",
  "properties": {
    "addr:full":"PO Box 554 Plympton SA 5038",
    "addr:postcode":"5038",
    "iso:country":"AU",
    "sg:address":"PO Box 554",
    "sg:city":"Plympton",
    "sg:classifiers":[
        {
            "category":"Education",
            "subcategory":"Special Training",
            "type":"Public Place"
        }
    ],
    "sg:phone":"+61 8 8293 5595",
    "sg:postcode":"5038",
    "sg:province":"SA",
    "sg:tags":[
        "development"
    ],
    "wof:name":"A.A.T. (Achievement Awareness Training)",
    "wof:placetype":"venue"
},
  "geometry": {"coordinates":[138.55458068900001,-34.9622688293],"type":"Point"}
}