{
  "type": "Feature",
  "properties": {
    "iso:country":"AU",
    "sg:address":"49 Waymouth St",
    "sg:city":"Adelaide",
    "sg:classifiers":[
        {
            "category":"Health Services",
            "subcategory":"Doctor",
            "type":"Services"
        }
    ],
    "sg:phone":"+61 8 8221 5300",
    "sg:postcode":"5000",
    "sg:province":"SA",
    "sg:tags":[
        "nurse",
        "nursing"
    ],
    "wof:name":"Care Path Australia",
    "wof:placetype":"venue"
},
  "geometry": {"coordinates":[138.59902954099999,-34.9259376526],"type":"Point"}
}