{
  "type": "Feature",
  "properties": {
    "iso:country":"AU",
    "sg:address":"Factory 18/ 155 Beresford Rd",
    "sg:city":"Lilydale",
    "sg:classifiers":[
        {
            "category":"Social Services",
            "subcategory":"Adult Care",
            "type":"Services"
        }
    ],
    "sg:phone":"+61 407 829 219",
    "sg:postcode":"3140",
    "sg:province":"VIC",
    "sg:tags":[
        "towing"
    ],
    "wof:name":"J & L Towing",
    "wof:placetype":"venue"
},
  "geometry": {"coordinates":[145.35130310100001,-37.7512359619],"type":"Point"}
}