{
  "type": "Feature",
  "properties": {
    "addr:full":"16 Hartung St Mundaring WA 6073",
    "addr:housenumber":"16",
    "addr:postcode":"6073",
    "addr:street":"Hartung St",
    "iso:country":"AU",
    "sg:address":"16 Hartung St",
    "sg:city":"Mundaring",
    "sg:classifiers":[
        {
            "category":"Social Services",
            "subcategory":"Child Care",
            "type":"Services"
        }
    ],
    "sg:phone":"+61 8 9295 6550",
    "sg:postcode":"6073",
    "sg:province":"WA",
    "wof:name":"Hills Child Care Centre",
    "wof:placetype":"venue"
},
  "geometry": {"coordinates":[116.164138794,-31.9000797272],"type":"Point"}
}