{
  "type": "Feature",
  "properties": {
    "addr:full":"1634 Ferntree Gully Rd Knoxfield VIC 3180",
    "addr:housenumber":"1634",
    "addr:postcode":"3180",
    "addr:street":"Ferntree Gully Rd",
    "iso:country":"AU",
    "sg:address":"1634 Ferntree Gully Rd",
    "sg:city":"Knoxfield",
    "sg:classifiers":[
        {
            "category":"Food & Beverages",
            "subcategory":"Liquor & Beverages",
            "type":"Retail Goods"
        }
    ],
    "sg:phone":"+61 1300 553 536",
    "sg:postcode":"3180",
    "sg:province":"VIC",
    "sg:tags":[
        "merchant",
        "spirit",
        "wine"
    ],
    "wof:name":"12 Celcius Corp",
    "wof:placetype":"venue"
},
  "geometry": {"coordinates":[145.25462341299999,-37.8935585022],"type":"Point"}
}