{
  "type": "Feature",
  "properties": {
    "iso:country":"AU",
    "sg:address":"Barley Rd",
    "sg:city":"Port Lincoln",
    "sg:classifiers":[
        {
            "category":"Food & Beverages",
            "subcategory":"Fruits & Vegetables",
            "type":"Retail Goods"
        }
    ],
    "sg:phone":"+61 8 8683 3137",
    "sg:postcode":"5606",
    "sg:province":"SA",
    "sg:tags":[
        "wholesale"
    ],
    "wof:name":"Piantedosi M P",
    "wof:placetype":"venue"
},
  "geometry": {"coordinates":[135.84823600000001,-34.741428],"type":"Point"}
}