{
  "type": "Feature",
  "properties": {
    "addr:full":"49 Puckle St Moonee Ponds VIC 3039",
    "addr:housenumber":"49",
    "addr:postcode":"3039",
    "addr:street":"Puckle St",
    "iso:country":"AU",
    "sg:address":"49 Puckle St",
    "sg:city":"Moonee Ponds",
    "sg:classifiers":[
        {
            "category":"Banks & Credit Unions",
            "subcategory":"Investment Brokerage",
            "type":"Services"
        }
    ],
    "sg:phone":"+61 1800 653 061",
    "sg:postcode":"3039",
    "sg:province":"VIC",
    "wof:name":"Commonwealth Financial Planning",
    "wof:placetype":"venue"
},
  "geometry": {"coordinates":[144.922867,-37.76701],"type":"Point"}
}