{
  "type": "Feature",
  "properties": {
    "addr:full":"23 Stockton Drv Horsham VIC 3400",
    "addr:housenumber":"23",
    "addr:postcode":"3400",
    "addr:street":"Stockton Drv",
    "iso:country":"AU",
    "sg:address":"23 Stockton Drv",
    "sg:city":"Horsham",
    "sg:classifiers":[
        {
            "category":"Building & Trades",
            "subcategory":"Plumbing",
            "type":"Services"
        }
    ],
    "sg:phone":"+61 3 5382 6709",
    "sg:postcode":"3400",
    "sg:province":"VIC",
    "sg:tags":[
        "plumber",
        "gasfitters"
    ],
    "wof:name":"Aly's Plumbing",
    "wof:placetype":"venue"
},
  "geometry": {"coordinates":[142.21702575699999,-36.723865509],"type":"Point"}
}