{
  "type": "Feature",
  "properties": {
    "addr:full":"\"Killeneen\" Tom Roberts Rd Corowa NSW 2646",
    "addr:postcode":"2646",
    "addr:street":"Tom Roberts Rd",
    "iso:country":"AU",
    "sg:address":"\"Killeneen\" Tom Roberts Rd",
    "sg:city":"Corowa",
    "sg:classifiers":[
        {
            "category":"Military Area",
            "subcategory":"Air Force Base",
            "type":"Public Place"
        }
    ],
    "sg:phone":"+61 2 6035 3824",
    "sg:postcode":"2646",
    "sg:province":"NSW",
    "sg:tags":[
        "windmill"
    ],
    "wof:name":"Riverina Bore Pumps",
    "wof:placetype":"venue"
},
  "geometry": {"coordinates":[146.32171630900001,-35.9564247131],"type":"Point"}
}