{
  "type": "Feature",
  "properties": {
    "addr:full":"3 Hamilton Pl Mt Waverley VIC 3149",
    "addr:housenumber":"3",
    "addr:postcode":"3149",
    "addr:street":"Hamilton Pl Mt",
    "iso:country":"AU",
    "sg:address":"3 Hamilton Pl",
    "sg:city":"Mt Waverley",
    "sg:classifiers":[
        {
            "category":"Personal",
            "subcategory":"Beauty Salon",
            "type":"Services"
        }
    ],
    "sg:phone":"+61 3 9807 4524",
    "sg:postcode":"3149",
    "sg:province":"VIC",
    "sg:tags":[
        "hairdresser"
    ],
    "wof:name":"Hanna Hair & Beauty",
    "wof:placetype":"venue"
},
  "geometry": {"coordinates":[145.12759399399999,-37.8758392334],"type":"Point"}
}