{
  "type": "Feature",
  "properties": {
    "addr:full":"95 Argo St South Yarra VIC 3141",
    "addr:housenumber":"95",
    "addr:postcode":"3141",
    "addr:street":"Argo St",
    "iso:country":"AU",
    "sg:address":"95 Argo St",
    "sg:city":"South Yarra",
    "sg:classifiers":[
        {
            "category":"Personal",
            "subcategory":"Beauty Salon",
            "type":"Services"
        }
    ],
    "sg:phone":"+61 3 9866 2646",
    "sg:postcode":"3141",
    "sg:province":"VIC",
    "wof:name":"Beauty Gallery The",
    "wof:placetype":"venue"
},
  "geometry": {"coordinates":[144.99034118599999,-37.8441848755],"type":"Point"}
}