{
  "type": "Feature",
  "properties": {
    "addr:full":"7 Kanni Crt Ashmore QLD 4214",
    "addr:housenumber":"7",
    "addr:postcode":"4214",
    "addr:street":"Kanni Crt",
    "iso:country":"AU",
    "sg:address":"7 Kanni Crt",
    "sg:city":"Ashmore",
    "sg:classifiers":[
        {
            "category":"Banks & Credit Unions",
            "subcategory":"Bank",
            "type":"Services"
        }
    ],
    "sg:phone":"+61 7 5539 1541",
    "sg:postcode":"4214",
    "sg:province":"QLD",
    "sg:tags":[
        "concrete",
        "reinforcement"
    ],
    "wof:name":"Ashmore Formwork Pty Ltd",
    "wof:placetype":"venue"
},
  "geometry": {"coordinates":[153.37965393100001,-27.9911441803],"type":"Point"}
}