{
  "type": "Feature",
  "properties": {
    "addr:full":"Bridge St Tumbarumba NSW 2653",
    "addr:postcode":"2653",
    "addr:street":"Bridge St",
    "iso:country":"AU",
    "sg:address":"Bridge St",
    "sg:city":"Tumbarumba",
    "sg:classifiers":[
        {
            "category":"Organizations",
            "subcategory":"Community Association",
            "type":"Services"
        }
    ],
    "sg:phone":"+61 2 6948 3088",
    "sg:postcode":"2653",
    "sg:province":"NSW",
    "sg:tags":[
        "organisation",
        "family",
        "welfare"
    ],
    "wof:name":"Home & Community Care Centre (HACC)",
    "wof:placetype":"venue"
},
  "geometry": {"coordinates":[148.012481689,-35.777381897],"type":"Point"}
}