{
  "type": "Feature",
  "properties": {
    "addr:full":"Shop 4, 255- 271 Anzac Pde Kingsford NSW 2032",
    "addr:housenumber":"shop 4;271",
    "addr:postcode":"255;2032",
    "addr:street":"Anzac Pde",
    "iso:country":"AU",
    "sg:address":"Shop 4, 255- 271 Anzac Pde",
    "sg:city":"Kingsford",
    "sg:classifiers":[
        {
            "category":"Shopping",
            "subcategory":"Computers & Home Electronics",
            "type":"Retail Goods"
        }
    ],
    "sg:phone":"+61 2 9663 0349",
    "sg:postcode":"2032",
    "sg:province":"NSW",
    "sg:tags":[
        "hardware",
        "equipment"
    ],
    "wof:name":"Apus Computer & Communication",
    "wof:placetype":"venue"
},
  "geometry": {"coordinates":[151.226470947,-33.9205970764],"type":"Point"}
}