{
  "type": "Feature",
  "properties": {
    "addr:full":"479 Fairfield Rd Yeronga QLD 4104",
    "addr:housenumber":"479",
    "addr:postcode":"4104",
    "addr:street":"Fairfield Rd",
    "iso:country":"AU",
    "sg:address":"479 Fairfield Rd",
    "sg:city":"Yeronga",
    "sg:classifiers":[
        {
            "category":"Food & Beverages",
            "subcategory":"Liquor & Beverages",
            "type":"Retail Goods"
        }
    ],
    "sg:phone":"+61 7 3848 5100",
    "sg:postcode":"4104",
    "sg:province":"QLD",
    "sg:tags":[
        "store"
    ],
    "wof:name":"Kings Bottleshops",
    "wof:placetype":"venue"
},
  "geometry": {"coordinates":[153.01701355,-27.5168533325],"type":"Point"}
}