{
  "type": "Feature",
  "properties": {
    "addr:full":"449 Lennard St Dianella WA 6059",
    "addr:housenumber":"449",
    "addr:postcode":"6059",
    "addr:street":"Lennard St",
    "iso:country":"AU",
    "sg:address":"449 Lennard St",
    "sg:city":"Dianella",
    "sg:classifiers":[
        {
            "category":"Professional",
            "subcategory":"Art Services",
            "type":"Services"
        }
    ],
    "sg:phone":"+61 8 9276 8275",
    "sg:postcode":"6059",
    "sg:province":"WA",
    "sg:tags":[
        "graphic",
        "designer"
    ],
    "wof:name":"Ricardo Design",
    "wof:placetype":"venue"
},
  "geometry": {"coordinates":[116.008346558,-31.8355636597],"type":"Point"}
}