{
  "type": "Feature",
  "properties": {
    "iso:country":"AU",
    "sg:address":"1/ 21 Stennett Rd",
    "sg:city":"Ingleburn",
    "sg:classifiers":[
        {
            "category":"Manufacturing",
            "subcategory":"Building Materials",
            "type":"Manufacturing & Wholesale Goods"
        }
    ],
    "sg:phone":"+61 2 9829 1034",
    "sg:postcode":"2565",
    "sg:province":"NSW",
    "sg:tags":[
        "adhesive",
        "tape"
    ],
    "sg:website":"http://www.premiumpackaging.com.au",
    "wof:name":"Premium Packaging",
    "wof:placetype":"venue"
},
  "geometry": {"coordinates":[150.85252380399999,-34.0036354065],"type":"Point"}
}