{
  "type": "Feature",
  "properties": {
    "addr:full":"22 Wilson Ave Brunswick VIC 3056",
    "addr:housenumber":"22",
    "addr:postcode":"3056",
    "addr:street":"Wilson Ave",
    "iso:country":"AU",
    "sg:address":"22 Wilson Ave",
    "sg:city":"Brunswick",
    "sg:classifiers":[
        {
            "category":"Manufacturing",
            "subcategory":"Apparel",
            "type":"Manufacturing & Wholesale Goods"
        }
    ],
    "sg:phone":"+61 3 9387 8842",
    "sg:postcode":"3056",
    "sg:province":"VIC",
    "sg:tags":[
        "makers-up",
        "clothing"
    ],
    "wof:name":"Judy Garments Pty Ltd",
    "wof:placetype":"venue"
},
  "geometry": {"coordinates":[144.95932006800001,-37.7749938965],"type":"Point"}
}