{
  "type": "Feature",
  "properties": {
    "iso:country":"AU",
    "sg:address":"\"The Quarry\" Barney St",
    "sg:city":"Kiama",
    "sg:classifiers":[
        {
            "category":"Transit Center",
            "subcategory":"Freight",
            "type":"Transportation"
        }
    ],
    "sg:phone":"+61 2 4232 3223",
    "sg:postcode":"2533",
    "sg:province":"NSW",
    "sg:tags":[
        "forklift",
        "truck"
    ],
    "wof:name":"Kiama Landscape And Building Supplies Pty Ltd",
    "wof:placetype":"venue"
},
  "geometry": {"coordinates":[150.845703125,-34.6728019714],"type":"Point"}
}