{
  "type": "Feature",
  "properties": {
    "iso:country":"AU",
    "sg:address":"123B Forest Rd",
    "sg:city":"Tamworth",
    "sg:classifiers":[
        {
            "category":"Utilities",
            "subcategory":"Refuse",
            "type":"Services"
        }
    ],
    "sg:phone":"+61 2 6766 9179",
    "sg:postcode":"2340",
    "sg:province":"NSW",
    "sg:tags":[
        "disposal",
        "reduction",
        "waste"
    ],
    "wof:name":"Challenge Recycling",
    "wof:placetype":"venue"
},
  "geometry": {"coordinates":[150.93031310999999,-31.076089859],"type":"Point"}
}