{
  "type": "Feature",
  "properties": {
    "addr:full":"Shop 1, 144-148 Goulburn St Sydney NSW 2000",
    "addr:housenumber":"shop 1",
    "addr:postcode":"144-148;2000",
    "addr:street":"Goulburn St",
    "iso:country":"AU",
    "sg:address":"Shop 1, 144-148 Goulburn St",
    "sg:city":"Sydney",
    "sg:classifiers":[
        {
            "category":"Professional",
            "subcategory":"Art Services",
            "type":"Services"
        }
    ],
    "sg:phone":"+61 2 9261 2371",
    "sg:postcode":"2000",
    "sg:province":"NSW",
    "sg:tags":[
        "picture",
        "frame",
        "framing"
    ],
    "wof:name":"Business And Corporate Framing Pty Ltd",
    "wof:placetype":"venue"
},
  "geometry": {"coordinates":[151.21173095699999,-33.878578186],"type":"Point"}
}