{
  "type": "Feature",
  "properties": {
    "iso:country":"AU",
    "sg:address":"Hopkins St",
    "sg:city":"Lancelin",
    "sg:classifiers":[
        {
            "category":"Arena",
            "subcategory":"Indoor Arena",
            "type":"Entertainment"
        }
    ],
    "sg:phone":"+61 8 9655 2162",
    "sg:postcode":"6044",
    "sg:province":"WA",
    "sg:tags":[
        "club",
        "angling"
    ],
    "wof:name":"Lancelin Angling & Aquatic Club (Inc)",
    "wof:placetype":"venue"
},
  "geometry": {"coordinates":[115.331687927,-31.0248203278],"type":"Point"}
}