{
  "type": "Feature",
  "properties": {
    "iso:country":"AU",
    "sg:address":"Unit 2/ 63 George St",
    "sg:city":"Beenleigh",
    "sg:classifiers":[
        {
            "category":"Professional",
            "subcategory":"Detective & Security Services",
            "type":"Services"
        }
    ],
    "sg:phone":"+61 7 3807 7655",
    "sg:postcode":"4207",
    "sg:province":"QLD",
    "sg:tags":[
        "consultant",
        "system"
    ],
    "wof:name":"Kings Security Services (Int) Pty Ltd",
    "wof:placetype":"venue"
},
  "geometry": {"coordinates":[153.198822022,-27.7155265808],"type":"Point"}
}