{
  "type": "Feature",
  "properties": {
    "iso:country":"AU",
    "sg:address":"762 Anzac Hwy",
    "sg:city":"Glenelg",
    "sg:classifiers":[
        {
            "category":"Professional",
            "subcategory":"Accounting & Tax Preparation",
            "type":"Services"
        }
    ],
    "sg:phone":"+61 8 8295 7983",
    "sg:postcode":"5045",
    "sg:province":"SA",
    "sg:tags":[
        "consultant",
        "taxation"
    ],
    "wof:name":"H&R Block",
    "wof:placetype":"venue"
},
  "geometry": {"coordinates":[138.513336,-34.97683],"type":"Point"}
}