{
  "type": "Feature",
  "properties": {
    "iso:country":"AU",
    "sg:address":"U7/ 1a Carmen St",
    "sg:city":"Bankstown",
    "sg:classifiers":[
        {
            "category":"Professional",
            "type":"Services"
        }
    ],
    "sg:phone":"+61 2 9793 2563",
    "sg:postcode":"2200",
    "sg:province":"NSW",
    "sg:tags":[
        "transport"
    ],
    "wof:name":"Instant Transport Services Pty Ltd",
    "wof:placetype":"venue"
},
  "geometry": {"coordinates":[151.02934300000001,-33.911633],"type":"Point"}
}