{
  "type": "Feature",
  "properties": {
    "addr:full":"45 Joseph St Cabramatta NSW 2166",
    "addr:housenumber":"45",
    "addr:postcode":"2166",
    "addr:street":"Joseph St",
    "iso:country":"AU",
    "sg:address":"45 Joseph St",
    "sg:city":"Cabramatta",
    "sg:classifiers":[
        {
            "category":"Wholesale",
            "subcategory":"Non-durable Goods",
            "type":"Manufacturing & Wholesale Goods"
        }
    ],
    "sg:phone":"+61 2 9755 7288",
    "sg:postcode":"2166",
    "sg:province":"NSW",
    "sg:tags":[
        "wholesaler",
        "mfrs",
        "cosmetic"
    ],
    "wof:name":"Belle Cosmetics",
    "wof:placetype":"venue"
},
  "geometry": {"coordinates":[150.92228698700001,-33.8926315308],"type":"Point"}
}