{
  "type": "Feature",
  "properties": {
    "addr:full":"432 Victoria Rd Gladesville NSW 2111",
    "addr:housenumber":"432",
    "addr:postcode":"2111",
    "addr:street":"Victoria Rd",
    "iso:country":"AU",
    "sg:address":"432 Victoria Rd",
    "sg:city":"Gladesville",
    "sg:classifiers":[
        {
            "category":"Utilities",
            "subcategory":"Electric",
            "type":"Services"
        }
    ],
    "sg:phone":"+61 2 9817 3307",
    "sg:postcode":"2111",
    "sg:province":"NSW",
    "sg:tags":[
        "electrical",
        "contractor"
    ],
    "wof:name":"Robert Scott Electrical P/L",
    "wof:placetype":"venue"
},
  "geometry": {"coordinates":[151.12376403799999,-33.8238792419],"type":"Point"}
}