{
  "type": "Feature",
  "properties": {
    "addr:full":"127 Waggs La Mortlake VIC 3272",
    "addr:housenumber":"127",
    "addr:postcode":"3272",
    "addr:street":"Waggs La",
    "iso:country":"AU",
    "sg:address":"127 Waggs La",
    "sg:city":"Mortlake",
    "sg:classifiers":[
        {
            "category":"Professional",
            "subcategory":"Business Services",
            "type":"Services"
        }
    ],
    "sg:phone":"+61 3 5599 2025",
    "sg:postcode":"3272",
    "sg:province":"VIC",
    "sg:tags":[
        "broker"
    ],
    "wof:name":"Murphy Michael J & Co Pty Ltd",
    "wof:placetype":"venue"
},
  "geometry": {"coordinates":[142.80838012699999,-38.0714035034],"type":"Point"}
}