{
  "type": "Feature",
  "properties": {
    "addr:full":"Gowing Ave Bega NSW 2550",
    "addr:postcode":"2550",
    "addr:street":"Gowing Ave",
    "iso:country":"AU",
    "sg:address":"Gowing Ave",
    "sg:city":"Bega",
    "sg:classifiers":[
        {
            "category":"Food & Beverages",
            "subcategory":"Bakery",
            "type":"Retail Goods"
        }
    ],
    "sg:phone":"+61 2 6492 2785",
    "sg:postcode":"2550",
    "sg:province":"NSW",
    "sg:tags":[
        "baker"
    ],
    "wof:name":"Buttercup Bakeries Pty Ltd",
    "wof:placetype":"venue"
},
  "geometry": {"coordinates":[149.836013794,-36.6818695068],"type":"Point"}
}