{
  "type": "Feature",
  "properties": {
    "addr:full":"129 North West Coastal Hwy Geraldton WA 6530",
    "addr:housenumber":"129",
    "addr:postcode":"6530",
    "addr:street":"North West Coastal Hwy",
    "iso:country":"AU",
    "sg:address":"129 North West Coastal Hwy",
    "sg:city":"Geraldton",
    "sg:classifiers":[
        {
            "category":"Retail",
            "subcategory":"Auto Rental",
            "type":"Services"
        }
    ],
    "sg:phone":"+61 8 9964 3464",
    "sg:postcode":"6530",
    "sg:province":"WA",
    "sg:tags":[
        "bus",
        "truck"
    ],
    "wof:name":"Avis Geraldton",
    "wof:placetype":"venue"
},
  "geometry": {"coordinates":[114.62449646,-28.7673797607],"type":"Point"}
}