{
  "type": "Feature",
  "properties": {
    "addr:full":"82 Commercial St Mt Gambier SA 5290",
    "addr:housenumber":"82",
    "addr:postcode":"5290",
    "addr:street":"Commercial St",
    "iso:country":"AU",
    "sg:address":"82 Commercial St",
    "sg:city":"Mt Gambier",
    "sg:classifiers":[
        {
            "category":"Cafe",
            "type":"Food & Drink"
        }
    ],
    "sg:phone":"+61 8 8723 5321",
    "sg:postcode":"5290",
    "sg:province":"SA",
    "wof:name":"Vanilla Bean",
    "wof:placetype":"venue"
},
  "geometry": {"coordinates":[140.776443,-37.826885],"type":"Point"}
}