{
  "type": "Feature",
  "properties": {
    "addr:full":"85 Mcdowall St Roma QLD 4455",
    "addr:housenumber":"85",
    "addr:postcode":"4455",
    "addr:street":"Mcdowall St",
    "iso:country":"AU",
    "sg:address":"85 Mcdowall St",
    "sg:city":"Roma",
    "sg:classifiers":[
        {
            "category":"Personal",
            "subcategory":"Beauty Salon",
            "type":"Services"
        }
    ],
    "sg:phone":"+61 7 4622 1683",
    "sg:postcode":"4455",
    "sg:province":"QLD",
    "sg:tags":[
        "hairdresser"
    ],
    "wof:name":"Hair & Body Zone",
    "wof:placetype":"venue"
},
  "geometry": {"coordinates":[148.788604736,-26.5713710785],"type":"Point"}
}