{
  "type": "Feature",
  "properties": {
    "addr:full":"Shp7/ 2 Bechert Rd Chiswick NSW 2046",
    "addr:postcode":"2046",
    "addr:street":"Bechert Rd",
    "iso:country":"AU",
    "sg:address":"Shp7/ 2 Bechert Rd",
    "sg:city":"Chiswick",
    "sg:classifiers":[
        {
            "category":"Food & Beverages",
            "subcategory":"Supermarket",
            "type":"Retail Goods"
        }
    ],
    "sg:phone":"+61 2 9712 4499",
    "sg:postcode":"2046",
    "sg:province":"NSW",
    "sg:tags":[
        "grocery",
        "store"
    ],
    "wof:name":"Nautica Convenience Store",
    "wof:placetype":"venue"
},
  "geometry": {"coordinates":[151.13403299999999,-33.851704],"type":"Point"}
}