{
  "type": "Feature",
  "properties": {
    "iso:country":"AU",
    "sg:address":"171 Barkly St",
    "sg:city":"St Kilda",
    "sg:classifiers":[
        {
            "category":"Shopping",
            "subcategory":"Discount & Variety Stores",
            "type":"Retail Goods"
        }
    ],
    "sg:phone":"+61 3 9525 3586",
    "sg:postcode":"3182",
    "sg:province":"VIC",
    "sg:tags":[
        "shop",
        "adult"
    ],
    "wof:name":"Love 2 Adult Bookshop",
    "wof:placetype":"venue"
},
  "geometry": {"coordinates":[144.98106384299999,-37.8672409058],"type":"Point"}
}