{
  "type": "Feature",
  "properties": {
    "addr:full":"161 Jackson Rd Sunnybank Hills QLD 4109",
    "addr:housenumber":"161",
    "addr:postcode":"4109",
    "addr:street":"Jackson Rd",
    "iso:country":"AU",
    "sg:address":"161 Jackson Rd",
    "sg:city":"Sunnybank Hills",
    "sg:classifiers":[
        {
            "category":"Wholesale",
            "subcategory":"Chemicals & Plastics",
            "type":"Manufacturing & Wholesale Goods"
        }
    ],
    "sg:phone":"+61 7 3323 9300",
    "sg:postcode":"4109",
    "sg:province":"QLD",
    "sg:tags":[
        "extruders"
    ],
    "wof:name":"Q.P.A. Quality Plasterboard Accessories",
    "wof:placetype":"venue"
},
  "geometry": {"coordinates":[153.045822144,-27.5876235962],"type":"Point"}
}