{
  "type": "Feature",
  "properties": {
    "addr:full":"153 Eley Rd Blackburn South VIC 3130",
    "addr:housenumber":"153",
    "addr:postcode":"3130",
    "addr:street":"Eley Rd",
    "iso:country":"AU",
    "sg:address":"153 Eley Rd",
    "sg:city":"Blackburn South",
    "sg:classifiers":[
        {
            "category":"Professional",
            "subcategory":"Computer Services",
            "type":"Services"
        }
    ],
    "sg:phone":"+61 3 9803 0672",
    "sg:postcode":"3130",
    "sg:province":"VIC",
    "sg:tags":[
        "repairs",
        "upgrade",
        "equipment"
    ],
    "wof:name":"Fix - I.T. Mobile Computer Service Pty. Ltd.",
    "wof:placetype":"venue"
},
  "geometry": {"coordinates":[145.15081787099999,-37.8477210999],"type":"Point"}
}