{
  "type": "Feature",
  "properties": {
    "iso:country":"AU",
    "sg:address":"194 Flinders St",
    "sg:city":"Townsville City",
    "sg:classifiers":[
        {
            "category":"Retail",
            "subcategory":"Event Space",
            "type":"Services"
        }
    ],
    "sg:phone":"+61 7 4772 0900",
    "sg:postcode":"4810",
    "sg:province":"QLD",
    "sg:tags":[
        "function",
        "organiser"
    ],
    "wof:name":"Monsoons Bar & Grill",
    "wof:placetype":"venue"
},
  "geometry": {"coordinates":[146.81007399999999,-19.266464],"type":"Point"}
}