{
  "type": "Feature",
  "properties": {
    "addr:full":"55 High St Bowraville NSW 2449",
    "addr:housenumber":"55",
    "addr:postcode":"2449",
    "addr:street":"High St",
    "iso:country":"AU",
    "sg:address":"55 High St",
    "sg:city":"Bowraville",
    "sg:classifiers":[
        {
            "category":"Government",
            "subcategory":"Fire Station",
            "type":"Public Place"
        }
    ],
    "sg:phone":"+61 2 6564 7116",
    "sg:postcode":"2449",
    "sg:province":"NSW",
    "sg:tags":[
        "brigade"
    ],
    "wof:name":"Fire Brigades-NSW",
    "wof:placetype":"venue"
},
  "geometry": {"coordinates":[152.852417,-30.648001],"type":"Point"}
}