{
  "type": "Feature",
  "properties": {
    "iso:country":"AU",
    "sg:address":"Shp2/ 8 Copernicus Way",
    "sg:city":"Keilor Downs",
    "sg:classifiers":[
        {
            "category":"Parking",
            "subcategory":"Garage",
            "type":"Transportation"
        }
    ],
    "sg:phone":"+61 3 9364 0540",
    "sg:postcode":"3038",
    "sg:province":"VIC",
    "sg:tags":[
        "radiographer"
    ],
    "wof:name":"Treadwell Radiology",
    "wof:placetype":"venue"
},
  "geometry": {"coordinates":[144.806229,-37.723812],"type":"Point"}
}