{
  "type": "Feature",
  "properties": {
    "addr:full":"34a Bates St Merredin WA 6415",
    "addr:housenumber":"34a",
    "addr:postcode":"6415",
    "addr:street":"Bates St",
    "iso:country":"AU",
    "sg:address":"34a Bates St",
    "sg:city":"Merredin",
    "sg:classifiers":[
        {
            "category":"Health Services",
            "subcategory":"Chiropractor",
            "type":"Services"
        }
    ],
    "sg:phone":"+61 8 9041 1275",
    "sg:postcode":"6415",
    "sg:province":"WA",
    "wof:name":"Merredin Chiropractic and Accupunture",
    "wof:placetype":"venue"
},
  "geometry": {"coordinates":[118.27848815900001,-31.4806556702],"type":"Point"}
}