{
  "type": "Feature",
  "properties": {
    "addr:full":"Shop 20 482 Salisbury Hwy Parafield Gardens SA 5107",
    "addr:housenumber":"shop 20 482",
    "addr:postcode":"5107",
    "addr:street":"Salisbury Hwy",
    "iso:country":"AU",
    "sg:address":"Shop 20 482 Salisbury Hwy",
    "sg:city":"Parafield Gardens",
    "sg:classifiers":[
        {
            "category":"Food & Beverages",
            "subcategory":"Bakery",
            "type":"Retail Goods"
        }
    ],
    "sg:phone":"+61 8 8281 8065",
    "sg:postcode":"5107",
    "sg:province":"SA",
    "sg:tags":[
        "baker"
    ],
    "wof:name":"Nina Bakery",
    "wof:placetype":"venue"
},
  "geometry": {"coordinates":[138.62051391599999,-34.7853775024],"type":"Point"}
}