{
  "type": "Feature",
  "properties": {
    "addr:full":"Shop 5 Dickensons Arc 109 Main Rd Moonah TAS 7009",
    "addr:housenumber":"shop 5;109",
    "addr:postcode":"7009",
    "addr:street":"Dickensons Arc;Main Rd",
    "iso:country":"AU",
    "sg:address":"Shop 5 Dickensons Arc 109 Main Rd",
    "sg:city":"Moonah",
    "sg:classifiers":[
        {
            "category":"Banks & Credit Unions",
            "subcategory":"Financial Services",
            "type":"Services"
        }
    ],
    "sg:phone":"+61 3 6278 1199",
    "sg:postcode":"7009",
    "sg:province":"TAS",
    "sg:tags":[
        "planning"
    ],
    "wof:name":"David Allen",
    "wof:placetype":"venue"
},
  "geometry": {"coordinates":[147.294845581,-42.8463478088],"type":"Point"}
}