{
  "type": "Feature",
  "properties": {
    "iso:country":"AU",
    "sg:address":"282 Nicholson St",
    "sg:city":"Fitzroy",
    "sg:classifiers":[
        {
            "category":"Sports & Exercise",
            "subcategory":"Gym",
            "type":"Entertainment"
        }
    ],
    "sg:phone":"+61 3 9625 1998",
    "sg:postcode":"3065",
    "sg:province":"VIC",
    "sg:tags":[
        "meditation"
    ],
    "wof:name":"Bacash Meditation Therapy",
    "wof:placetype":"venue"
},
  "geometry": {"coordinates":[144.97532653799999,-37.79662323],"type":"Point"}
}