{
  "type": "Feature",
  "properties": {
    "addr:full":"1/ 219 Mona Vale Rd North St Ives NSW 2075",
    "addr:housenumber":"/ 219",
    "addr:postcode":"2075",
    "addr:street":"Mona Vale Rd North St",
    "iso:country":"AU",
    "sg:address":"1/ 219 Mona Vale Rd North",
    "sg:city":"St Ives",
    "sg:classifiers":[
        {
            "category":"Real Estate",
            "subcategory":"Architect",
            "type":"Services"
        }
    ],
    "sg:phone":"+61 2 9440 4539",
    "sg:postcode":"2075",
    "sg:province":"NSW",
    "wof:name":"Laurie Richard N",
    "wof:placetype":"venue"
},
  "geometry": {"coordinates":[151.160552978,-33.730556488],"type":"Point"}
}