{
  "type": "Feature",
  "properties": {
    "iso:country":"AU",
    "sg:address":"154- 162 Petrie Tce",
    "sg:city":"Spring Hill",
    "sg:classifiers":[
        {
            "category":"Banks & Credit Unions",
            "subcategory":"Financial Services",
            "type":"Services"
        }
    ],
    "sg:phone":"+61 7 3368 2711",
    "sg:postcode":"4000",
    "sg:province":"QLD",
    "sg:tags":[
        "planning"
    ],
    "wof:name":"Genesys Wealth Advisers",
    "wof:placetype":"venue"
},
  "geometry": {"coordinates":[153.01429748499999,-27.4628925323],"type":"Point"}
}