{
  "type": "Feature",
  "properties": {
    "addr:full":"Suite 11, Williams Court, William St Gosford NSW 2250",
    "addr:postcode":"2250",
    "addr:street":"Williams;William St",
    "iso:country":"AU",
    "sg:address":"Suite 11, Williams Court, William St",
    "sg:city":"Gosford",
    "sg:classifiers":[
        {
            "category":"Manufacturing",
            "subcategory":"Jewelry",
            "type":"Manufacturing & Wholesale Goods"
        }
    ],
    "sg:phone":"+61 2 4324 2462",
    "sg:postcode":"2250",
    "sg:province":"NSW",
    "sg:tags":[
        "designer",
        "jewellery"
    ],
    "wof:name":"Grono Tom",
    "wof:placetype":"venue"
},
  "geometry": {"coordinates":[151.342407227,-33.4260978699],"type":"Point"}
}