{
  "type": "Feature",
  "properties": {
    "iso:country":"AU",
    "sg:address":"43 Charles St",
    "sg:city":"Coburg North",
    "sg:classifiers":[
        {
            "category":"Retail",
            "subcategory":"Auto Repair",
            "type":"Services"
        }
    ],
    "sg:phone":"+61 3 9354 1275",
    "sg:postcode":"3058",
    "sg:province":"VIC",
    "sg:tags":[
        "body",
        "motor",
        "trimmer"
    ],
    "wof:name":"Super Trim Vinyl Hardtops Pty. Ltd.",
    "wof:placetype":"venue"
},
  "geometry": {"coordinates":[144.956008911,-37.7306098938],"type":"Point"}
}