{
  "type": "Feature",
  "properties": {
    "iso:country":"AU",
    "sg:address":"2 Clear Mountain Rd",
    "sg:city":"Cashmere",
    "sg:classifiers":[
        {
            "category":"Building & Trades",
            "subcategory":"Construction",
            "type":"Services"
        }
    ],
    "sg:phone":"+61 418 783 125",
    "sg:postcode":"4500",
    "sg:province":"QLD",
    "sg:tags":[
        "contractor"
    ],
    "wof:name":"Toomac Constructions",
    "wof:placetype":"venue"
},
  "geometry": {"coordinates":[152.91131591800001,-27.3232192993],"type":"Point"}
}