{
  "type": "Feature",
  "properties": {
    "addr:full":"Office 21 Haymarket NSW 2000",
    "addr:postcode":"2000",
    "iso:country":"AU",
    "sg:address":"Office 21",
    "sg:city":"Haymarket",
    "sg:classifiers":[
        {
            "category":"Professional",
            "subcategory":"Management & Consulting",
            "type":"Services"
        }
    ],
    "sg:phone":"+61 2 9281 2122",
    "sg:postcode":"2000",
    "sg:province":"NSW",
    "sg:tags":[
        "consultant",
        "migration"
    ],
    "wof:name":"Migration Law Consultants Pty Ltd",
    "wof:placetype":"venue"
},
  "geometry": {"coordinates":[151.205200195,-33.8800506592],"type":"Point"}
}