{
  "type": "Feature",
  "properties": {
    "iso:country":"AU",
    "sg:address":"50 Lidbetter Rd",
    "sg:city":"Berry",
    "sg:classifiers":[
        {
            "category":"Building & Trades",
            "subcategory":"Construction",
            "type":"Services"
        }
    ],
    "sg:phone":"+61 402 406 192",
    "sg:postcode":"2535",
    "sg:province":"NSW",
    "sg:tags":[
        "stonework",
        "stone",
        "mason"
    ],
    "wof:name":"Stonehedge",
    "wof:placetype":"venue"
},
  "geometry": {"coordinates":[150.68170165999999,-34.832359314],"type":"Point"}
}