{
  "type": "Feature",
  "properties": {
    "iso:country":"AU",
    "sg:address":"PO Box 4263",
    "sg:city":"Dubbo",
    "sg:classifiers":[
        {
            "category":"Building & Trades",
            "subcategory":"Construction",
            "type":"Services"
        }
    ],
    "sg:phone":"+61 2 6882 0325",
    "sg:postcode":"2830",
    "sg:province":"NSW",
    "sg:tags":[
        "contractor"
    ],
    "wof:name":"Neil MacInnes",
    "wof:placetype":"venue"
},
  "geometry": {"coordinates":[148.60118102999999,-32.2478713989],"type":"Point"}
}