{
  "type": "Feature",
  "properties": {
    "addr:full":"70 High St Maryborough VIC 3465",
    "addr:housenumber":"70",
    "addr:postcode":"3465",
    "addr:street":"High St",
    "iso:country":"AU",
    "sg:address":"70 High St",
    "sg:city":"Maryborough",
    "sg:classifiers":[
        {
            "category":"Social Services",
            "subcategory":"Adult Care",
            "type":"Services"
        }
    ],
    "sg:phone":"+61 3 5461 1303",
    "sg:postcode":"3465",
    "sg:province":"VIC",
    "sg:tags":[
        "towing"
    ],
    "wof:name":"Maffescioni P & C Pty Ltd",
    "wof:placetype":"venue"
},
  "geometry": {"coordinates":[143.73561096200001,-37.0484275818],"type":"Point"}
}