{
  "type": "Feature",
  "properties": {
    "iso:country":"AU",
    "sg:address":"Level 1, 49- 51 Colbee Crt",
    "sg:city":"Phillip",
    "sg:classifiers":[
        {
            "category":"Education",
            "subcategory":"Special Training",
            "type":"Public Place"
        }
    ],
    "sg:phone":"+61 2 6282 5660",
    "sg:postcode":"2606",
    "sg:province":"ACT",
    "sg:tags":[
        "development"
    ],
    "wof:name":"Bayley & Associates Pty Ltd",
    "wof:placetype":"venue"
},
  "geometry": {"coordinates":[149.088745117,-35.3525390625],"type":"Point"}
}