{
  "type": "Feature",
  "properties": {
    "addr:full":"Shop 1, 196 Jacobs Drv Sussex Inlet NSW 2540",
    "addr:housenumber":"shop 1 196",
    "addr:postcode":"2540",
    "addr:street":"Jacobs Drv",
    "iso:country":"AU",
    "sg:address":"Shop 1, 196 Jacobs Drv",
    "sg:city":"Sussex Inlet",
    "sg:classifiers":[
        {
            "category":"Health Services",
            "subcategory":"Optometrist",
            "type":"Services"
        }
    ],
    "sg:phone":"+61 2 4441 2417",
    "sg:postcode":"2540",
    "sg:province":"NSW",
    "wof:name":"Pain Stephen",
    "wof:placetype":"venue"
},
  "geometry": {"coordinates":[150.60287475600001,-35.1568374634],"type":"Point"}
}