{
  "type": "Feature",
  "properties": {
    "addr:full":"Cnr Somerville Rd & Whitehall St Yarraville VIC 3013",
    "addr:postcode":"3013",
    "addr:street":"Cnr Somerville Rd & Whitehall St",
    "iso:country":"AU",
    "sg:address":"Cnr Somerville Rd & Whitehall St",
    "sg:city":"Yarraville",
    "sg:classifiers":[
        {
            "category":"Transit Center",
            "subcategory":"Freight",
            "type":"Transportation"
        }
    ],
    "sg:phone":"+61 1300 138 553",
    "sg:postcode":"3013",
    "sg:province":"VIC",
    "sg:tags":[
        "forklift",
        "truck"
    ],
    "wof:name":"Hyster",
    "wof:placetype":"venue"
},
  "geometry": {"coordinates":[144.88316345199999,-37.8127555847],"type":"Point"}
}