{
  "type": "Feature",
  "properties": {
    "addr:full":"35a Bluff Rd Black Rock VIC 3193",
    "addr:housenumber":"35a",
    "addr:postcode":"3193",
    "addr:street":"Bluff Rd",
    "iso:country":"AU",
    "sg:address":"35a Bluff Rd",
    "sg:city":"Black Rock",
    "sg:classifiers":[
        {
            "category":"Health Services",
            "subcategory":"Health Practitioner",
            "type":"Services"
        }
    ],
    "sg:phone":"+61 3 9589 6209",
    "sg:postcode":"3193",
    "sg:province":"VIC",
    "sg:tags":[
        "naturopath"
    ],
    "wof:name":"Optimal Health Solutions",
    "wof:placetype":"venue"
},
  "geometry": {"coordinates":[145.01620483400001,-37.9743652344],"type":"Point"}
}