{
  "type": "Feature",
  "properties": {
    "addr:full":"Level 5, 20 Smith St Parramatta NSW 2150",
    "addr:housenumber":"20",
    "addr:postcode":"2150",
    "addr:street":"Smith St",
    "iso:country":"AU",
    "sg:address":"Level 5, 20 Smith St",
    "sg:city":"Parramatta",
    "sg:classifiers":[
        {
            "category":"Professional",
            "subcategory":"Employment Agencies",
            "type":"Services"
        }
    ],
    "sg:phone":"+61 2 9893 0222",
    "sg:postcode":"2150",
    "sg:province":"NSW",
    "wof:name":"Essential Appointments Pty Ltd",
    "wof:placetype":"venue"
},
  "geometry": {"coordinates":[151.006469727,-33.8308105469],"type":"Point"}
}