{
  "type": "Feature",
  "properties": {
    "addr:full":"194 Mooloolah Connection Rd Glenview QLD 4553",
    "addr:housenumber":"194",
    "addr:postcode":"4553",
    "addr:street":"Mooloolah Connection Rd",
    "iso:country":"AU",
    "sg:address":"194 Mooloolah Connection Rd",
    "sg:city":"Glenview",
    "sg:classifiers":[
        {
            "category":"Home & Garden",
            "subcategory":"Garden Supply",
            "type":"Retail Goods"
        }
    ],
    "sg:phone":"+61 7 5494 7582",
    "sg:postcode":"4553",
    "sg:province":"QLD",
    "sg:tags":[
        "turf",
        "lawn"
    ],
    "wof:name":"Bendles Mooloolah Valley Turf",
    "wof:placetype":"venue"
},
  "geometry": {"coordinates":[153.00302099999999,-26.773819],"type":"Point"}
}