{
  "type": "Feature",
  "properties": {
    "iso:country":"AU",
    "sg:address":"21b Belmore St",
    "sg:city":"Arncliffe",
    "sg:classifiers":[
        {
            "category":"Personal",
            "subcategory":"Beauty Salon",
            "type":"Services"
        }
    ],
    "sg:phone":"+61 2 9567 1012",
    "sg:postcode":"2205",
    "sg:province":"NSW",
    "sg:tags":[
        "hairdresser"
    ],
    "wof:name":"Helens Hair Care",
    "wof:placetype":"venue"
},
  "geometry": {"coordinates":[151.146103,-33.935616],"type":"Point"}
}