{
  "type": "Feature",
  "properties": {
    "addr:full":"526 Marion Rd Plympton Park SA 5038",
    "addr:housenumber":"526",
    "addr:postcode":"5038",
    "addr:street":"Marion Rd",
    "iso:country":"AU",
    "sg:address":"526 Marion Rd",
    "sg:city":"Plympton Park",
    "sg:classifiers":[
        {
            "category":"Health Services",
            "subcategory":"Health Practitioner",
            "type":"Services"
        }
    ],
    "sg:phone":"+61 8 8351 0388",
    "sg:postcode":"5038",
    "sg:province":"SA",
    "sg:tags":[
        "acupuncture"
    ],
    "wof:name":"Kang & Zhang",
    "wof:placetype":"venue"
},
  "geometry": {"coordinates":[138.55552673299999,-34.9760627747],"type":"Point"}
}