{
  "type": "Feature",
  "properties": {
    "addr:full":"U20/South Terrace Piazza 18-54 South Tce Fremantle WA 6160",
    "addr:housenumber":"18-54",
    "addr:postcode":"6160",
    "addr:street":"/;Terrace Piazza;South Tce",
    "iso:country":"AU",
    "sg:address":"U20/South Terrace Piazza 18-54 South Tce",
    "sg:city":"Fremantle",
    "sg:classifiers":[
        {
            "category":"Personal",
            "subcategory":"Beauty Salon",
            "type":"Services"
        }
    ],
    "sg:phone":"+61 8 9430 5195",
    "sg:postcode":"6160",
    "sg:province":"WA",
    "sg:tags":[
        "hairdresser"
    ],
    "wof:name":"James Hair Studio",
    "wof:placetype":"venue"
},
  "geometry": {"coordinates":[115.747612,-32.055546],"type":"Point"}
}