{
  "type": "Feature",
  "properties": {
    "addr:full":"75b Boundary Rd Liverpool NSW 1871",
    "addr:housenumber":"75b",
    "addr:postcode":"1871",
    "addr:street":"Boundary Rd",
    "iso:country":"AU",
    "sg:address":"75b Boundary Rd",
    "sg:city":"Liverpool",
    "sg:classifiers":[
        {
            "category":"Autos & Motor Vehicles",
            "subcategory":"Auto Supplies",
            "type":"Retail Goods"
        }
    ],
    "sg:phone":"+61 2 9727 5564",
    "sg:postcode":"1871",
    "sg:province":"NSW",
    "sg:tags":[
        "part",
        "cycles",
        "accessory"
    ],
    "wof:name":"Gforce Bikes",
    "wof:placetype":"venue"
},
  "geometry": {"coordinates":[150.90606689399999,-33.9351043701],"type":"Point"}
}