{
  "type": "Feature",
  "properties": {
    "addr:full":"90 Braeside St Wahroonga NSW 2076",
    "addr:housenumber":"90",
    "addr:postcode":"2076",
    "addr:street":"Braeside St",
    "iso:country":"AU",
    "sg:address":"90 Braeside St",
    "sg:city":"Wahroonga",
    "sg:classifiers":[
        {
            "category":"Banks & Credit Unions",
            "subcategory":"Investment Brokerage",
            "type":"Services"
        }
    ],
    "sg:phone":"+61 2 9489 7889",
    "sg:postcode":"2076",
    "sg:province":"NSW",
    "sg:tags":[
        "management",
        "property"
    ],
    "wof:name":"Elkava Pty Ltd",
    "wof:placetype":"venue"
},
  "geometry": {"coordinates":[151.13096618599999,-33.713104248],"type":"Point"}
}