{
  "type": "Feature",
  "properties": {
    "addr:full":"U18/ 77 Dempster St Esperance WA 6450",
    "addr:housenumber":"77",
    "addr:postcode":"6450",
    "addr:street":"/;Dempster St",
    "iso:country":"AU",
    "sg:address":"U18/ 77 Dempster St",
    "sg:city":"Esperance",
    "sg:classifiers":[
        {
            "category":"Professional",
            "subcategory":"Art Services",
            "type":"Services"
        }
    ],
    "sg:phone":"+61 8 9071 3111",
    "sg:postcode":"6450",
    "sg:province":"WA",
    "sg:tags":[
        "picture",
        "frame",
        "framing"
    ],
    "wof:name":"Old Courthouse Framers",
    "wof:placetype":"venue"
},
  "geometry": {"coordinates":[121.893608093,-33.8588752747],"type":"Point"}
}