{
  "type": "Feature",
  "properties": {
    "iso:country":"AU",
    "sg:address":"5 Greenhills Ave",
    "sg:city":"Moorebank",
    "sg:classifiers":[
        {
            "category":"Building & Trades",
            "subcategory":"Equipment Rental",
            "type":"Services"
        }
    ],
    "sg:phone":"+61 2 9602 2222",
    "sg:postcode":"2170",
    "sg:province":"NSW",
    "sg:tags":[
        "crane",
        "hire"
    ],
    "wof:name":"B G Crane & Compaction Pty Ltd",
    "wof:placetype":"venue"
},
  "geometry": {"coordinates":[150.932174683,-33.9368972778],"type":"Point"}
}