{
  "type": "Feature",
  "properties": {
    "iso:country":"AU",
    "sg:address":"28 Arthur St",
    "sg:city":"Forestville",
    "sg:classifiers":[
        {
            "category":"Building & Trades",
            "subcategory":"Construction",
            "type":"Services"
        }
    ],
    "sg:phone":"+61 2 9402 2621",
    "sg:postcode":"2087",
    "sg:province":"NSW",
    "sg:tags":[
        "contractor"
    ],
    "wof:name":"Caromac Pty Ltd",
    "wof:placetype":"venue"
},
  "geometry": {"coordinates":[151.20599365199999,-33.7598152161],"type":"Point"}
}