{
  "type": "Feature",
  "properties": {
    "iso:country":"AU",
    "sg:address":"1a Cook St",
    "sg:city":"Hawthorn",
    "sg:classifiers":[
        {
            "category":"Cafe",
            "type":"Food & Drink"
        }
    ],
    "sg:phone":"+61 3 9819 9254",
    "sg:postcode":"3122",
    "sg:province":"VIC",
    "wof:name":"Cravings Cafe Hawthorn",
    "wof:placetype":"venue"
},
  "geometry": {"coordinates":[145.03361511200001,-37.8226699829],"type":"Point"}
}