{
  "type": "Feature",
  "properties": {
    "addr:full":"Ground St Moore Park NSW 2021",
    "addr:postcode":"2021",
    "iso:country":"AU",
    "sg:address":"Ground St",
    "sg:city":"Moore Park",
    "sg:classifiers":[
        {
            "category":"Sports & Exercise",
            "subcategory":"Sports Center",
            "type":"Entertainment"
        }
    ],
    "sg:phone":"+61 2 9360 6601",
    "sg:postcode":"2021",
    "sg:province":"NSW",
    "sg:tags":[
        "ground"
    ],
    "wof:name":"Sydney Cricket & Sports Ground Trust",
    "wof:placetype":"venue"
},
  "geometry": {"coordinates":[151.22596740700001,-33.8964805603],"type":"Point"}
}