{
  "type": "Feature",
  "properties": {
    "addr:full":"54 Frenchs Rd Willoughby NSW 2068",
    "addr:housenumber":"54",
    "addr:postcode":"2068",
    "addr:street":"Frenchs Rd",
    "iso:country":"AU",
    "sg:address":"54 Frenchs Rd",
    "sg:city":"Willoughby",
    "sg:classifiers":[
        {
            "category":"Social Services",
            "subcategory":"Retirement Home",
            "type":"Services"
        }
    ],
    "sg:phone":"+61 2 9958 2266",
    "sg:postcode":"2068",
    "sg:province":"NSW",
    "sg:tags":[
        "environmental",
        "consultant",
        "pollution"
    ],
    "wof:name":"Johnson David & Johnstone Ted",
    "wof:placetype":"venue"
},
  "geometry": {"coordinates":[151.20030212399999,-33.8073387146],"type":"Point"}
}