{
  "type": "Feature",
  "properties": {
    "iso:country":"AU",
    "sg:address":"68 Clifton St",
    "sg:city":"North Rockhampton",
    "sg:classifiers":[
        {
            "category":"Manufacturing",
            "subcategory":"Paper Products",
            "type":"Manufacturing & Wholesale Goods"
        }
    ],
    "sg:phone":"+61 7 4926 1844",
    "sg:postcode":"4701",
    "sg:province":"QLD",
    "sg:tags":[
        "container",
        "plastic"
    ],
    "wof:name":"J.B. Distributors",
    "wof:placetype":"venue"
},
  "geometry": {"coordinates":[150.52537536599999,-23.3570137024],"type":"Point"}
}