{
  "type": "Feature",
  "properties": {
    "addr:full":"69 Hampstead Rd Manningham SA 5086",
    "addr:housenumber":"69",
    "addr:postcode":"5086",
    "addr:street":"Hampstead Rd",
    "iso:country":"AU",
    "sg:address":"69 Hampstead Rd",
    "sg:city":"Manningham",
    "sg:classifiers":[
        {
            "category":"Health Services",
            "subcategory":"Dentist",
            "type":"Services"
        }
    ],
    "sg:phone":"+61 8 8261 7987",
    "sg:postcode":"5086",
    "sg:province":"SA",
    "wof:name":"Phung Hoa",
    "wof:placetype":"venue"
},
  "geometry": {"coordinates":[138.61965942399999,-34.8767127991],"type":"Point"}
}