{
  "type": "Feature",
  "properties": {
    "iso:country":"AU",
    "sg:address":"116 Murray St",
    "sg:city":"Gawler",
    "sg:classifiers":[
        {
            "category":"Shopping",
            "subcategory":"Music",
            "type":"Retail Goods"
        }
    ],
    "sg:phone":"+61 8 8522 1518",
    "sg:postcode":"5118",
    "sg:province":"SA",
    "sg:tags":[
        "store"
    ],
    "wof:name":"Gawler Records",
    "wof:placetype":"venue"
},
  "geometry": {"coordinates":[138.748886,-34.596409],"type":"Point"}
}