{
  "type": "Feature",
  "properties": {
    "addr:full":"PO Box 558 Carlton North VIC 3054",
    "addr:postcode":"3054",
    "iso:country":"AU",
    "sg:address":"PO Box 558",
    "sg:city":"Carlton North",
    "sg:classifiers":[
        {
            "category":"Travel",
            "subcategory":"Travel Agent",
            "type":"Entertainment"
        }
    ],
    "sg:phone":"+61 3 9415 6524",
    "sg:postcode":"3054",
    "sg:province":"VIC",
    "sg:tags":[
        "consultant"
    ],
    "wof:name":"Southern Italian Tours",
    "wof:placetype":"venue"
},
  "geometry": {"coordinates":[144.97186279300001,-37.7892417908],"type":"Point"}
}