{
  "type": "Feature",
  "properties": {
    "addr:full":"17 Challenger Ave Manning WA 6152",
    "addr:housenumber":"17",
    "addr:postcode":"6152",
    "addr:street":"Challenger Ave",
    "iso:country":"AU",
    "sg:address":"17 Challenger Ave",
    "sg:city":"Manning",
    "sg:classifiers":[
        {
            "category":"Building & Trades",
            "subcategory":"Plumbing",
            "type":"Services"
        }
    ],
    "sg:phone":"+61 8 9313 1083",
    "sg:postcode":"6152",
    "sg:province":"WA",
    "sg:tags":[
        "plumber",
        "gasfitters"
    ],
    "wof:name":"D.H. Steineck & Co",
    "wof:placetype":"venue"
},
  "geometry": {"coordinates":[115.87381000000001,-32.01421],"type":"Point"}
}