{
  "type": "Feature",
  "properties": {
    "addr:full":"Unit 4/ 2 Baltic Crt Maddington WA 6109",
    "addr:housenumber":"2",
    "addr:postcode":"6109",
    "addr:street":"Baltic Crt",
    "iso:country":"AU",
    "sg:address":"Unit 4/ 2 Baltic Crt",
    "sg:city":"Maddington",
    "sg:classifiers":[
        {
            "category":"Retail",
            "subcategory":"Laundry & Dry Cleaning",
            "type":"Services"
        }
    ],
    "sg:phone":"+61 8 9493 3163",
    "sg:postcode":"6109",
    "sg:province":"WA",
    "sg:tags":[
        "machine",
        "commercial",
        "industrial",
        "washing"
    ],
    "wof:name":"Laundry Systems Pty Ltd",
    "wof:placetype":"venue"
},
  "geometry": {"coordinates":[115.99356079099999,-32.0347747803],"type":"Point"}
}