{
  "type": "Feature",
  "properties": {
    "addr:full":"115b Ferrars St South Melbourne VIC 3205",
    "addr:housenumber":"115b",
    "addr:postcode":"3205",
    "addr:street":"Ferrars St",
    "iso:country":"AU",
    "sg:address":"115b Ferrars St",
    "sg:city":"South Melbourne",
    "sg:classifiers":[
        {
            "category":"Travel",
            "subcategory":"Travel Agent",
            "type":"Entertainment"
        }
    ],
    "sg:phone":"+61 3 9682 6166",
    "sg:postcode":"3205",
    "sg:province":"VIC",
    "sg:tags":[
        "consultant"
    ],
    "wof:name":"Stage & Screen Travel & Freight Service",
    "wof:placetype":"venue"
},
  "geometry": {"coordinates":[144.95745849599999,-37.8367614746],"type":"Point"}
}