{
  "type": "Feature",
  "properties": {
    "addr:full":"26 Argyle St Albion QLD 4010",
    "addr:housenumber":"26",
    "addr:postcode":"4010",
    "addr:street":"Argyle St",
    "iso:country":"AU",
    "sg:address":"26 Argyle St",
    "sg:city":"Albion",
    "sg:classifiers":[
        {
            "category":"Shopping",
            "subcategory":"Computers & Home Electronics",
            "type":"Retail Goods"
        }
    ],
    "sg:phone":"+61 7 3262 1655",
    "sg:postcode":"4010",
    "sg:province":"QLD",
    "sg:tags":[
        "equipment",
        "multimedia"
    ],
    "wof:name":"Complete Presence",
    "wof:placetype":"venue"
},
  "geometry": {"coordinates":[153.042480469,-27.4410324097],"type":"Point"}
}