{
  "type": "Feature",
  "properties": {
    "addr:full":"33 Frazer St Lilyfield NSW 2040",
    "addr:housenumber":"33",
    "addr:postcode":"2040",
    "addr:street":"Frazer St",
    "iso:country":"AU",
    "sg:address":"33 Frazer St",
    "sg:city":"Lilyfield",
    "sg:classifiers":[
        {
            "category":"Travel",
            "subcategory":"Bed & Breakfast",
            "type":"Entertainment"
        }
    ],
    "sg:phone":"+61 2 9973 2906",
    "sg:postcode":"2040",
    "sg:province":"NSW",
    "sg:tags":[
        "control",
        "system",
        "wetting"
    ],
    "wof:name":"OneOnOne",
    "wof:placetype":"venue"
},
  "geometry": {"coordinates":[151.153244,-33.870945],"type":"Point"}
}