{
  "type": "Feature",
  "properties": {
    "iso:country":"AU",
    "sg:address":"19 Bibby St",
    "sg:city":"Chiswick",
    "sg:classifiers":[
        {
            "category":"Government",
            "subcategory":"Post Office",
            "type":"Public Place"
        }
    ],
    "sg:phone":"+61 1300 133 767",
    "sg:postcode":"2046",
    "sg:province":"NSW",
    "sg:tags":[
        "equipment",
        "hole",
        "contractor"
    ],
    "wof:name":"Red Roo Sales & Service",
    "wof:placetype":"venue"
},
  "geometry": {"coordinates":[151.137527,-33.8507],"type":"Point"}
}