{
  "type": "Feature",
  "properties": {
    "addr:full":"PO Box 238 Sandy Bay TAS 7005",
    "addr:postcode":"7005",
    "iso:country":"AU",
    "sg:address":"PO Box 238",
    "sg:city":"Sandy Bay",
    "sg:classifiers":[
        {
            "category":"Professional",
            "subcategory":"Employment Agencies",
            "type":"Services"
        }
    ],
    "sg:phone":"+61 3 6223 6160",
    "sg:postcode":"7005",
    "sg:province":"TAS",
    "wof:name":"TasmanianJobs.Com",
    "wof:placetype":"venue"
},
  "geometry": {"coordinates":[147.33280944800001,-42.9012489319],"type":"Point"}
}