{
  "type": "Feature",
  "properties": {
    "addr:full":"13 Krauss Ave South Lismore NSW 2480",
    "addr:housenumber":"13",
    "addr:postcode":"2480",
    "addr:street":"Krauss Ave South",
    "iso:country":"AU",
    "sg:address":"13 Krauss Ave",
    "sg:city":"South Lismore",
    "sg:classifiers":[
        {
            "category":"Home & Garden",
            "subcategory":"Carpets & Floor Coverings",
            "type":"Retail Goods"
        }
    ],
    "sg:phone":"+61 2 6621 2804",
    "sg:postcode":"2480",
    "sg:province":"NSW",
    "sg:tags":[
        "tile",
        "wall"
    ],
    "wof:name":"H.R. Christie Pty Limited T/As Willetts Tiles",
    "wof:placetype":"venue"
},
  "geometry": {"coordinates":[153.26466369600001,-28.8234825134],"type":"Point"}
}