{
  "type": "Feature",
  "properties": {
    "addr:full":"40B Capital Link Drv Campbellfield VIC 3061",
    "addr:housenumber":"40b",
    "addr:postcode":"3061",
    "addr:street":"Capital Link Drv",
    "iso:country":"AU",
    "sg:address":"40B Capital Link Drv",
    "sg:city":"Campbellfield",
    "sg:classifiers":[
        {
            "category":"Professional",
            "subcategory":"Engineering",
            "type":"Services"
        }
    ],
    "sg:phone":"+61 3 9357 8393",
    "sg:postcode":"3061",
    "sg:province":"VIC",
    "sg:tags":[
        "engineer"
    ],
    "wof:name":"Heat Treatment Australia",
    "wof:placetype":"venue"
},
  "geometry": {"coordinates":[144.963546753,-37.6540412903],"type":"Point"}
}