{
  "type": "Feature",
  "properties": {
    "addr:full":"18 Masons Rd Legana TAS 7277",
    "addr:housenumber":"18",
    "addr:postcode":"7277",
    "addr:street":"Masons Rd",
    "iso:country":"AU",
    "sg:address":"18 Masons Rd",
    "sg:city":"Legana",
    "sg:classifiers":[
        {
            "category":"Farming",
            "subcategory":"Livestock Farm",
            "type":"Manufacturing & Wholesale Goods"
        }
    ],
    "sg:phone":"+61 3 6394 4470",
    "sg:postcode":"7277",
    "sg:province":"TAS",
    "sg:tags":[
        "breeder",
        "horse",
        "stud"
    ],
    "wof:name":"Silver Star Miniature Horse Stud",
    "wof:placetype":"venue"
},
  "geometry": {"coordinates":[146.98728942899999,-41.3314056396],"type":"Point"}
}