{
  "type": "Feature",
  "properties": {
    "addr:full":"13/ 255 Adelaide St Brisbane QLD 4000",
    "addr:housenumber":"13 / 255",
    "addr:postcode":"4000",
    "addr:street":"Adelaide St",
    "iso:country":"AU",
    "sg:address":"13/ 255 Adelaide St",
    "sg:city":"Brisbane",
    "sg:classifiers":[
        {
            "category":"Professional",
            "subcategory":"Employment Agencies",
            "type":"Services"
        }
    ],
    "sg:phone":"+61 7 3220 3633",
    "sg:postcode":"4000",
    "sg:province":"QLD",
    "wof:name":"LINK Recruitment",
    "wof:placetype":"venue"
},
  "geometry": {"coordinates":[153.029006958,-27.4655094147],"type":"Point"}
}