{
  "type": "Feature",
  "properties": {
    "iso:country":"AU",
    "sg:address":"33 Lydaird St",
    "sg:city":"South Ballarat",
    "sg:classifiers":[
        {
            "category":"Cafe",
            "type":"Food & Drink"
        }
    ],
    "sg:phone":"+61 3 5331 1162",
    "sg:postcode":"3350",
    "sg:province":"VIC",
    "wof:name":"Wattle Food Bar",
    "wof:placetype":"venue"
},
  "geometry": {"coordinates":[143.861328,-37.542706],"type":"Point"}
}