{
  "type": "Feature",
  "properties": {
    "addr:full":"Unit 1, 69 Springwood Rd Springwood QLD 4127",
    "addr:housenumber":"69",
    "addr:postcode":"4127",
    "addr:street":"Springwood Rd",
    "iso:country":"AU",
    "sg:address":"Unit 1, 69 Springwood Rd",
    "sg:city":"Springwood",
    "sg:classifiers":[
        {
            "category":"Professional",
            "subcategory":"Accounting & Tax Preparation",
            "type":"Services"
        }
    ],
    "sg:phone":"+61 7 3219 8077",
    "sg:postcode":"4127",
    "sg:province":"QLD",
    "sg:tags":[
        "deduction",
        "payroll"
    ],
    "wof:name":"Paywell Australia Pty Ltd",
    "wof:placetype":"venue"
},
  "geometry": {"coordinates":[153.125274658,-27.6098041534],"type":"Point"}
}