{
  "type": "Feature",
  "properties": {
    "addr:full":"Unit 2/ 269 Olive St Albury NSW 2640",
    "addr:housenumber":"/ 269",
    "addr:postcode":"2640",
    "addr:street":"Olive St",
    "iso:country":"AU",
    "sg:address":"Unit 2/ 269 Olive St",
    "sg:city":"Albury",
    "sg:classifiers":[
        {
            "category":"Banks & Credit Unions",
            "subcategory":"Investment Brokerage",
            "type":"Services"
        }
    ],
    "sg:phone":"+61 2 6041 5777",
    "sg:postcode":"2640",
    "sg:province":"NSW",
    "sg:tags":[
        "paint",
        "supply",
        "removal"
    ],
    "wof:name":"Albury Paint Strippers",
    "wof:placetype":"venue"
},
  "geometry": {"coordinates":[146.91746520999999,-36.085647583],"type":"Point"}
}