{
  "type": "Feature",
  "properties": {
    "iso:country":"AU",
    "sg:address":"3 Buckle Rd",
    "sg:city":"Melton",
    "sg:classifiers":[
        {
            "category":"Shopping",
            "subcategory":"Musical Instruments",
            "type":"Retail Goods"
        }
    ],
    "sg:phone":"+61 3 9743 7603",
    "sg:postcode":"3337",
    "sg:province":"VIC",
    "sg:tags":[
        "musician",
        "agent"
    ],
    "wof:name":"McKenzie Gordon L",
    "wof:placetype":"venue"
},
  "geometry": {"coordinates":[144.601395,-37.669495],"type":"Point"}
}