{
  "type": "Feature",
  "properties": {
    "addr:full":"204 Queen St St Marys NSW 2760",
    "addr:housenumber":"204",
    "addr:postcode":"2760",
    "addr:street":"Queen St",
    "iso:country":"AU",
    "sg:address":"204 Queen St St",
    "sg:city":"Marys",
    "sg:classifiers":[
        {
            "category":"Health Services",
            "subcategory":"Doctor",
            "type":"Services"
        }
    ],
    "sg:phone":"+61 2 9623 4533",
    "sg:postcode":"2760",
    "sg:province":"NSW",
    "sg:tags":[
        "medical",
        "practitioner"
    ],
    "wof:name":"Wong W K Lam K S Ngan M Reeves M W Simmons K",
    "wof:placetype":"venue"
},
  "geometry": {"coordinates":[150.77384948700001,-33.7685623169],"type":"Point"}
}