{
  "type": "Feature",
  "properties": {
    "iso:country":"AU",
    "sg:address":"200 Oxford St",
    "sg:city":"Bulimba",
    "sg:classifiers":[
        {
            "category":"Shopping",
            "subcategory":"Clothing, Apparel, & Fashions",
            "type":"Retail Goods"
        }
    ],
    "sg:phone":"+61 7 3899 9941",
    "sg:postcode":"4171",
    "sg:province":"QLD",
    "sg:tags":[
        "lady",
        "wear"
    ],
    "wof:name":"Timbuctoo",
    "wof:placetype":"venue"
},
  "geometry": {"coordinates":[153.061279297,-27.4514713287],"type":"Point"}
}