{
  "type": "Feature",
  "properties": {
    "addr:full":"60 Wellington St Mackay QLD 4740",
    "addr:housenumber":"60",
    "addr:postcode":"4740",
    "addr:street":"Wellington St",
    "iso:country":"AU",
    "sg:address":"60 Wellington St",
    "sg:city":"Mackay",
    "sg:classifiers":[
        {
            "category":"Organizations",
            "subcategory":"Non-profit Organization",
            "type":"Services"
        }
    ],
    "sg:phone":"+61 7 4957 8571",
    "sg:postcode":"4740",
    "sg:province":"QLD",
    "sg:tags":[
        "support",
        "disability",
        "organisation"
    ],
    "wof:name":"Mackay Family Care & Community Support Association",
    "wof:placetype":"venue"
},
  "geometry": {"coordinates":[149.17948899999999,-21.148731],"type":"Point"}
}