{
  "type": "Feature",
  "properties": {
    "iso:country":"AU",
    "sg:address":"PO Box 7192",
    "sg:city":"Garbutt",
    "sg:classifiers":[
        {
            "category":"Building & Trades",
            "subcategory":"Construction",
            "type":"Services"
        }
    ],
    "sg:phone":"+61 7 4721 4055",
    "sg:postcode":"4814",
    "sg:province":"QLD",
    "sg:tags":[
        "earth",
        "excavating",
        "moving",
        "contractor"
    ],
    "wof:name":"Northwest Construction Co",
    "wof:placetype":"venue"
},
  "geometry": {"coordinates":[146.783768,-19.26436],"type":"Point"}
}