{
  "type": "Feature",
  "properties": {
    "addr:full":"1068 South Rd Edwardstown SA 5039",
    "addr:housenumber":"1068",
    "addr:postcode":"5039",
    "addr:street":"South Rd",
    "iso:country":"AU",
    "sg:address":"1068 South Rd",
    "sg:city":"Edwardstown",
    "sg:classifiers":[
        {
            "category":"Retail",
            "subcategory":"Auto Repair",
            "type":"Services"
        }
    ],
    "sg:phone":"+61 8 8277 0099",
    "sg:postcode":"5039",
    "sg:province":"SA",
    "sg:tags":[
        "beater",
        "painter",
        "panel"
    ],
    "wof:name":"South Road Crash Repairs",
    "wof:placetype":"venue"
},
  "geometry": {"coordinates":[138.57452392600001,-34.9911842346],"type":"Point"}
}