{
  "type": "Feature",
  "properties": {
    "addr:full":"Unit 20 8 Penkivil St Bondi NSW 2026",
    "addr:housenumber":"8",
    "addr:postcode":"2026",
    "addr:street":"Penkivil St",
    "iso:country":"AU",
    "sg:address":"Unit 20 8 Penkivil St",
    "sg:city":"Bondi",
    "sg:classifiers":[
        {
            "category":"Professional",
            "subcategory":"Business Services",
            "type":"Services"
        }
    ],
    "sg:phone":"+61 2 9365 7277",
    "sg:postcode":"2026",
    "sg:province":"NSW",
    "sg:tags":[
        "management",
        "event"
    ],
    "wof:name":"Clinch Total Event Management",
    "wof:placetype":"venue"
},
  "geometry": {"coordinates":[151.26213073700001,-33.8887939453],"type":"Point"}
}