{
  "type": "Feature",
  "properties": {
    "iso:country":"AU",
    "sg:address":"106 Main Hurstbridge Rd",
    "sg:city":"Diamond Creek",
    "sg:classifiers":[
        {
            "category":"Health Services",
            "subcategory":"Health Practitioner",
            "type":"Services"
        }
    ],
    "sg:phone":"+61 3 9438 2666",
    "sg:postcode":"3089",
    "sg:province":"VIC",
    "sg:tags":[
        "physiotherapist"
    ],
    "wof:name":"Diamond Creek Physiotherapy Clinic",
    "wof:placetype":"venue"
},
  "geometry": {"coordinates":[145.162766,-37.674797],"type":"Point"}
}