{
  "type": "Feature",
  "properties": {
    "addr:full":"21 Amour St Revesby NSW 2212",
    "addr:housenumber":"21",
    "addr:postcode":"2212",
    "addr:street":"Amour St",
    "iso:country":"AU",
    "sg:address":"21 Amour St",
    "sg:city":"Revesby",
    "sg:classifiers":[
        {
            "category":"Wholesale",
            "subcategory":"Metals & Minerals",
            "type":"Manufacturing & Wholesale Goods"
        }
    ],
    "sg:phone":"+61 2 9772 5600",
    "sg:postcode":"2212",
    "sg:province":"NSW",
    "sg:tags":[
        "wholesaler",
        "carbon",
        "product",
        "mfrs"
    ],
    "wof:name":"Morganite Australia Pty Ltd",
    "wof:placetype":"venue"
},
  "geometry": {"coordinates":[150.99876399999999,-33.935417],"type":"Point"}
}