{
  "type": "Feature",
  "properties": {
    "addr:full":"Stirling Arcade 39 Mt Barker Rd Stirling SA 5152",
    "addr:housenumber":"39",
    "addr:postcode":"5152",
    "addr:street":"Mt Barker Rd",
    "iso:country":"AU",
    "sg:address":"Stirling Arcade 39 Mt Barker Rd",
    "sg:city":"Stirling",
    "sg:classifiers":[
        {
            "category":"Health Services",
            "subcategory":"Health Practitioner",
            "type":"Services"
        }
    ],
    "sg:phone":"+61 8 8339 3188",
    "sg:postcode":"5152",
    "sg:province":"SA",
    "sg:tags":[
        "physiotherapist"
    ],
    "wof:name":"Deere Jane",
    "wof:placetype":"venue"
},
  "geometry": {"coordinates":[138.72184753400001,-35.0078926086],"type":"Point"}
}