{
  "type": "Feature",
  "properties": {
    "addr:full":"Unit 1/ 27 Millenium Pl Tingalpa QLD 4173",
    "addr:housenumber":"27",
    "addr:postcode":"4173",
    "addr:street":"Millenium Pl",
    "iso:country":"AU",
    "sg:address":"Unit 1/ 27 Millenium Pl",
    "sg:city":"Tingalpa",
    "sg:classifiers":[
        {
            "category":"Shopping",
            "subcategory":"Bicycles & Sporting Goods",
            "type":"Retail Goods"
        }
    ],
    "sg:phone":"+61 7 3393 3233",
    "sg:postcode":"4173",
    "sg:province":"QLD",
    "sg:tags":[
        "chemical",
        "equipment",
        "pool",
        "swimming"
    ],
    "wof:name":"Hurlcon Pty Ltd",
    "wof:placetype":"venue"
},
  "geometry": {"coordinates":[153.15093994099999,-27.4667816162],"type":"Point"}
}