{
  "type": "Feature",
  "properties": {
    "addr:full":"7 Stokes Ave Alexandria NSW 2015",
    "addr:housenumber":"7",
    "addr:postcode":"2015",
    "addr:street":"Stokes Ave",
    "iso:country":"AU",
    "sg:address":"7 Stokes Ave",
    "sg:city":"Alexandria",
    "sg:classifiers":[
        {
            "category":"Shopping",
            "subcategory":"Stationery & Office Supplies",
            "type":"Retail Goods"
        }
    ],
    "sg:phone":"+61 2 8394 8299",
    "sg:postcode":"2015",
    "sg:province":"NSW",
    "sg:tags":[
        "equipment",
        "display",
        "exhibition"
    ],
    "wof:name":"Go-n-Show Displays & Graphics",
    "wof:placetype":"venue"
},
  "geometry": {"coordinates":[151.19781494099999,-33.9029273987],"type":"Point"}
}