{
  "type": "Feature",
  "properties": {
    "addr:full":"U2/ 67 William St Moffat Beach QLD 4551",
    "addr:housenumber":"67",
    "addr:postcode":"4551",
    "addr:street":"U2 /;William St",
    "iso:country":"AU",
    "sg:address":"U2/ 67 William St",
    "sg:city":"Moffat Beach",
    "sg:classifiers":[
        {
            "category":"Shopping",
            "subcategory":"Computers & Home Electronics",
            "type":"Retail Goods"
        }
    ],
    "sg:phone":"+61 7 5491 9998",
    "sg:postcode":"4551",
    "sg:province":"QLD",
    "sg:tags":[
        "small",
        "equipment",
        "business"
    ],
    "wof:name":"In Time Computer Services",
    "wof:placetype":"venue"
},
  "geometry": {"coordinates":[153.11122131400001,-26.7917766571],"type":"Point"}
}