{
  "type": "Feature",
  "properties": {
    "addr:full":"Bawa 6- 8 Old Town Plz Bankstown NSW 2200",
    "addr:housenumber":"6 8",
    "addr:postcode":"2200",
    "addr:street":"Bawa;Old Town Plz",
    "iso:country":"AU",
    "sg:address":"Bawa 6- 8 Old Town Plz",
    "sg:city":"Bankstown",
    "sg:classifiers":[
        {
            "category":"Organizations",
            "subcategory":"Community Association",
            "type":"Services"
        }
    ],
    "sg:phone":"+61 2 9793 7129",
    "sg:postcode":"2200",
    "sg:province":"NSW",
    "sg:tags":[
        "organisation",
        "family",
        "welfare"
    ],
    "wof:name":"Vietnamese-Australian Welfare Association",
    "wof:placetype":"venue"
},
  "geometry": {"coordinates":[151.03407300000001,-33.918468],"type":"Point"}
}