{
  "type": "Feature",
  "properties": {
    "iso:country":"AU",
    "sg:address":"PO Box 521",
    "sg:city":"Swan Hill",
    "sg:classifiers":[
        {
            "category":"Professional",
            "type":"Services"
        }
    ],
    "sg:phone":"+61 408 344 135",
    "sg:postcode":"3585",
    "sg:province":"VIC",
    "sg:tags":[
        "transport"
    ],
    "wof:name":"Shiralee Transport",
    "wof:placetype":"venue"
},
  "geometry": {"coordinates":[143.561554,-35.340969],"type":"Point"}
}