{
  "type": "Feature",
  "properties": {
    "iso:country":"AU",
    "sg:address":"40 Athol St",
    "sg:city":"Athol Park",
    "sg:classifiers":[
        {
            "category":"Industrial Area",
            "type":"Public Place"
        }
    ],
    "sg:phone":"+61 8 8341 2980",
    "sg:postcode":"5012",
    "sg:province":"SA",
    "sg:tags":[
        "rural",
        "shed"
    ],
    "wof:name":"Better Built Industries",
    "wof:placetype":"venue"
},
  "geometry": {"coordinates":[138.542480469,-34.8527641296],"type":"Point"}
}