{
  "type": "Feature",
  "properties": {
    "addr:full":"Lot 600 36 Stebbing Rd Maddington WA 6109",
    "addr:housenumber":"36",
    "addr:postcode":"6109",
    "addr:street":"Stebbing Rd",
    "iso:country":"AU",
    "sg:address":"Lot 600 36 Stebbing Rd",
    "sg:city":"Maddington",
    "sg:classifiers":[
        {
            "category":"Commercial Area",
            "type":"Public Place"
        }
    ],
    "sg:phone":"+61 8 9459 9380",
    "sg:postcode":"6109",
    "sg:province":"WA",
    "sg:tags":[
        "heavy",
        "carrier"
    ],
    "wof:name":"Young & Land Transport",
    "wof:placetype":"venue"
},
  "geometry": {"coordinates":[115.991699219,-32.0420608521],"type":"Point"}
}