{
  "type": "Feature",
  "properties": {
    "addr:full":"Crn Edward & Ann St Brisbane QLD 4000",
    "addr:postcode":"4000",
    "addr:street":"Crn;St",
    "iso:country":"AU",
    "sg:address":"Crn Edward & Ann St",
    "sg:city":"Brisbane",
    "sg:classifiers":[
        {
            "category":"Professional",
            "subcategory":"Employment Agencies",
            "type":"Services"
        }
    ],
    "sg:phone":"+61 7 3832 5544",
    "sg:postcode":"4000",
    "sg:province":"QLD",
    "wof:name":"Peoplebank Australia Ltd",
    "wof:placetype":"venue"
},
  "geometry": {"coordinates":[153.02961730999999,-27.4712600708],"type":"Point"}
}