{
  "type": "Feature",
  "properties": {
    "addr:full":"14 Dirkala Ave Heathmont VIC 3135",
    "addr:housenumber":"14",
    "addr:postcode":"3135",
    "addr:street":"Dirkala Ave",
    "iso:country":"AU",
    "sg:address":"14 Dirkala Ave",
    "sg:city":"Heathmont",
    "sg:classifiers":[
        {
            "category":"Real Estate",
            "subcategory":"Surveying",
            "type":"Services"
        }
    ],
    "sg:phone":"+61 3 9729 7107",
    "sg:postcode":"3135",
    "sg:province":"VIC",
    "sg:tags":[
        "surveyor",
        "land"
    ],
    "wof:name":"J Paul Land Surveyor Pty Ltd",
    "wof:placetype":"venue"
},
  "geometry": {"coordinates":[145.24029540999999,-37.837802887],"type":"Point"}
}