{
  "type": "Feature",
  "properties": {
    "addr:full":"88 Currie St Adelaide SA 5000",
    "addr:housenumber":"88",
    "addr:postcode":"5000",
    "addr:street":"Currie St",
    "iso:country":"AU",
    "sg:address":"88 Currie St",
    "sg:city":"Adelaide",
    "sg:classifiers":[
        {
            "category":"Personal",
            "subcategory":"Massage",
            "type":"Services"
        }
    ],
    "sg:phone":"+61 8 8410 1977",
    "sg:postcode":"5000",
    "sg:province":"SA",
    "sg:tags":[
        "therapy"
    ],
    "wof:name":"S.A. Health Education Centre",
    "wof:placetype":"venue"
},
  "geometry": {"coordinates":[138.59634399399999,-34.9243087769],"type":"Point"}
}