{
  "type": "Feature",
  "properties": {
    "addr:full":"Lot 22, Colliery St Moranbah QLD 4744",
    "addr:postcode":"4744",
    "addr:street":"Colliery St",
    "iso:country":"AU",
    "sg:address":"Lot 22, Colliery St",
    "sg:city":"Moranbah",
    "sg:classifiers":[
        {
            "category":"Banks & Credit Unions",
            "subcategory":"Bureau De Change",
            "type":"Services"
        }
    ],
    "sg:phone":"+61 7 4941 8141",
    "sg:postcode":"4744",
    "sg:province":"QLD",
    "sg:tags":[
        "repairs",
        "part",
        "appliance",
        "electrical"
    ],
    "wof:name":"C'Breeze Airconditioning",
    "wof:placetype":"venue"
},
  "geometry": {"coordinates":[148.09439086899999,-22.1004600525],"type":"Point"}
}