{
  "type": "Feature",
  "properties": {
    "addr:full":"31 Tannadice St Winnellie NT 0820",
    "addr:housenumber":"31",
    "addr:postcode":"nt 0820",
    "addr:street":"Tannadice St",
    "iso:country":"AU",
    "sg:address":"31 Tannadice St",
    "sg:city":"Winnellie",
    "sg:classifiers":[
        {
            "category":"Retail",
            "subcategory":"Auto Repair",
            "type":"Services"
        }
    ],
    "sg:phone":"+61 8 8947 5151",
    "sg:postcode":"0820",
    "sg:province":"NT",
    "sg:tags":[
        "repairer",
        "motor",
        "engineer"
    ],
    "wof:name":"Redline Automotive",
    "wof:placetype":"venue"
},
  "geometry": {"coordinates":[130.876296997,-12.4284152985],"type":"Point"}
}