{
  "type": "Feature",
  "properties": {
    "iso:country":"AU",
    "sg:address":"South St",
    "sg:city":"Tuncurry",
    "sg:classifiers":[
        {
            "category":"Health Services",
            "subcategory":"Doctor",
            "type":"Services"
        }
    ],
    "sg:phone":"+61 2 6555 3910",
    "sg:postcode":"2428",
    "sg:province":"NSW",
    "sg:tags":[
        "nurse",
        "nursing"
    ],
    "wof:name":"Mayo Home Nursing Service",
    "wof:placetype":"venue"
},
  "geometry": {"coordinates":[152.498734,-32.174671],"type":"Point"}
}