{
  "type": "Feature",
  "properties": {
    "addr:full":"11 McCarrs Creek Rd Church Point NSW 2105",
    "addr:housenumber":"11",
    "addr:postcode":"2105",
    "addr:street":"Mccarrs Creek Rd",
    "iso:country":"AU",
    "sg:address":"11 McCarrs Creek Rd",
    "sg:city":"Church Point",
    "sg:classifiers":[
        {
            "category":"Real Estate",
            "subcategory":"Architect",
            "type":"Services"
        }
    ],
    "sg:phone":"+61 2 9999 3080",
    "sg:postcode":"2105",
    "sg:province":"NSW",
    "wof:name":"David Naylor Architects",
    "wof:placetype":"venue"
},
  "geometry": {"coordinates":[151.282715,-33.64555],"type":"Point"}
}