{
  "type": "Feature",
  "properties": {
    "addr:full":"15 Fifth St Railway Estate QLD 4810",
    "addr:housenumber":"15",
    "addr:postcode":"4810",
    "addr:street":"Fifth St",
    "iso:country":"AU",
    "sg:address":"15 Fifth St",
    "sg:city":"Railway Estate",
    "sg:classifiers":[
        {
            "category":"Building & Trades",
            "subcategory":"Construction",
            "type":"Services"
        }
    ],
    "sg:phone":"+61 408 060 719",
    "sg:postcode":"4810",
    "sg:province":"QLD",
    "sg:tags":[
        "ceiling"
    ],
    "wof:name":"Fred's Plastering Service",
    "wof:placetype":"venue"
},
  "geometry": {"coordinates":[146.815155,-19.280516],"type":"Point"}
}