{
  "type": "Feature",
  "properties": {
    "addr:full":"5 Kumbari St Rochedale South QLD 4123",
    "addr:housenumber":"5",
    "addr:postcode":"4123",
    "addr:street":"Kumbari St",
    "iso:country":"AU",
    "sg:address":"5 Kumbari St",
    "sg:city":"Rochedale South",
    "sg:classifiers":[
        {
            "category":"Building & Trades",
            "subcategory":"Cleaning & Sanitation",
            "type":"Services"
        }
    ],
    "sg:phone":"+61 7 3841 6737",
    "sg:postcode":"4123",
    "sg:province":"QLD",
    "sg:tags":[
        "industrial",
        "commercial",
        "contractor"
    ],
    "wof:name":"AW & JM Gaylor",
    "wof:placetype":"venue"
},
  "geometry": {"coordinates":[153.12086486800001,-27.6069889069],"type":"Point"}
}