{
  "type": "Feature",
  "properties": {
    "iso:country":"AU",
    "sg:address":"3/ 70",
    "sg:city":"Walkerville Tce Walkerville",
    "sg:classifiers":[
        {
            "category":"Health Services",
            "subcategory":"Doctor",
            "type":"Services"
        }
    ],
    "sg:phone":"+61 8 8269 2622",
    "sg:postcode":"5081",
    "sg:province":"SA",
    "sg:tags":[
        "medical",
        "practitioner"
    ],
    "wof:name":"Monaghan Chris",
    "wof:placetype":"venue"
},
  "geometry": {"coordinates":[138.61492919899999,-34.8972396851],"type":"Point"}
}