{
  "type": "Feature",
  "properties": {
    "iso:country":"AU",
    "sg:address":"Shop 2/ 1132 Gold Coast Hwy",
    "sg:city":"Palm Beach",
    "sg:classifiers":[
        {
            "category":"Fast Food",
            "type":"Food & Drink"
        }
    ],
    "sg:phone":"+61 7 5598 4310",
    "sg:postcode":"4221",
    "sg:province":"QLD",
    "sg:tags":[
        "away",
        "take"
    ],
    "wof:name":"Ada's Kebabs",
    "wof:placetype":"venue"
},
  "geometry": {"coordinates":[153.47251892099999,-28.1211338043],"type":"Point"}
}