{
  "type": "Feature",
  "properties": {
    "addr:full":"75 Killara Rd Campbellfield VIC 3061",
    "addr:housenumber":"75",
    "addr:postcode":"3061",
    "addr:street":"Killara Rd",
    "iso:country":"AU",
    "sg:address":"75 Killara Rd",
    "sg:city":"Campbellfield",
    "sg:classifiers":[
        {
            "category":"Manufacturing",
            "subcategory":"Apparel",
            "type":"Manufacturing & Wholesale Goods"
        }
    ],
    "sg:phone":"+61 3 9357 9954",
    "sg:postcode":"3061",
    "sg:province":"VIC",
    "sg:tags":[
        "wholesaler",
        "mfrs",
        "footwear"
    ],
    "wof:name":"Fazzari Tony Shoes",
    "wof:placetype":"venue"
},
  "geometry": {"coordinates":[144.96490478499999,-37.6616592407],"type":"Point"}
}