{
  "type": "Feature",
  "properties": {
    "iso:country":"AU",
    "sg:address":"1/ 6 Success St",
    "sg:city":"Acacia Ridge",
    "sg:classifiers":[
        {
            "category":"Wholesale",
            "subcategory":"Machinery & Supplies",
            "type":"Manufacturing & Wholesale Goods"
        }
    ],
    "sg:phone":"+61 7 3255 5422",
    "sg:postcode":"4110",
    "sg:province":"QLD",
    "sg:tags":[
        "equipment",
        "hydraulic"
    ],
    "wof:name":"Andiline Distributors Pty Ltd",
    "wof:placetype":"venue"
},
  "geometry": {"coordinates":[153.008056641,-27.5810070038],"type":"Point"}
}