{
  "type": "Feature",
  "properties": {
    "addr:full":"Shop 510 Chirnside Park Shopping Centre, 239-241 Maroondah Hwy Chirnside Park VIC 3116",
    "addr:housenumber":"510;239-241",
    "addr:postcode":"3116",
    "addr:street":"Chirnside;Maroondah Hwy",
    "iso:country":"AU",
    "sg:address":"Shop 510 Chirnside Park Shopping Centre, 239-241 Maroondah Hwy",
    "sg:city":"Chirnside Park",
    "sg:classifiers":[
        {
            "category":"Shopping",
            "subcategory":"Clothing, Apparel, & Fashions",
            "type":"Retail Goods"
        }
    ],
    "sg:phone":"+61 3 9727 1279",
    "sg:postcode":"3116",
    "sg:province":"VIC",
    "sg:tags":[
        "lady",
        "wear"
    ],
    "wof:name":"Giordano (Australia) Pty Ltd",
    "wof:placetype":"venue"
},
  "geometry": {"coordinates":[145.321655273,-37.7562484741],"type":"Point"}
}