{
  "type": "Feature",
  "properties": {
    "addr:full":"Unit 2/ 82 Johnson Rd Browns Plains QLD 4118",
    "addr:housenumber":"82",
    "addr:postcode":"4118",
    "addr:street":"Johnson Rd",
    "iso:country":"AU",
    "sg:address":"Unit 2/ 82 Johnson Rd",
    "sg:city":"Browns Plains",
    "sg:classifiers":[
        {
            "category":"Building & Trades",
            "subcategory":"Construction",
            "type":"Services"
        }
    ],
    "sg:phone":"+61 7 3800 6557",
    "sg:postcode":"4118",
    "sg:province":"QLD",
    "sg:tags":[
        "fencing",
        "contractor"
    ],
    "wof:name":"A1 Factory Direct",
    "wof:placetype":"venue"
},
  "geometry": {"coordinates":[153.03250122099999,-27.6595363617],"type":"Point"}
}