{
  "type": "Feature",
  "properties": {
    "iso:country":"AU",
    "sg:address":"Sailors Bay Rd",
    "sg:city":"Northbridge",
    "sg:classifiers":[
        {
            "category":"Utilities",
            "subcategory":"Water",
            "type":"Services"
        }
    ],
    "sg:phone":"+61 2 9958 7644",
    "sg:postcode":"2063",
    "sg:province":"NSW",
    "sg:tags":[
        "hot",
        "system"
    ],
    "wof:name":"Aqua-Max Pty Ltd",
    "wof:placetype":"venue"
},
  "geometry": {"coordinates":[151.218505859,-33.8120040894],"type":"Point"}
}