{
  "type": "Feature",
  "properties": {
    "iso:country":"AU",
    "sg:address":"86 Victoria Rd",
    "sg:city":"Parramatta",
    "sg:classifiers":[
        {
            "category":"Retail",
            "subcategory":"Auto Rental",
            "type":"Services"
        }
    ],
    "sg:phone":"+61 2 9630 5877",
    "sg:postcode":"2150",
    "sg:province":"NSW",
    "sg:tags":[
        "bus",
        "truck"
    ],
    "wof:name":"Avis",
    "wof:placetype":"venue"
},
  "geometry": {"coordinates":[151.053009033,-33.7389068604],"type":"Point"}
}