{
  "type": "Feature",
  "properties": {
    "iso:country":"AU",
    "sg:address":"Bank Rd",
    "sg:city":"Sedan",
    "sg:classifiers":[
        {
            "category":"Commercial Area",
            "type":"Public Place"
        }
    ],
    "sg:phone":"+61 8 8565 2113",
    "sg:postcode":"5353",
    "sg:province":"SA",
    "sg:tags":[
        "heavy",
        "carrier"
    ],
    "wof:name":"Seidel L D & C",
    "wof:placetype":"venue"
},
  "geometry": {"coordinates":[139.2940979,-34.5729103088],"type":"Point"}
}