{
  "type": "Feature",
  "properties": {
    "addr:full":"19 Chataway St Murgon QLD 4605",
    "addr:housenumber":"19",
    "addr:postcode":"4605",
    "addr:street":"Chataway St",
    "iso:country":"AU",
    "sg:address":"19 Chataway St",
    "sg:city":"Murgon",
    "sg:classifiers":[
        {
            "category":"Manufacturing",
            "subcategory":"Tools & Machinery",
            "type":"Manufacturing & Wholesale Goods"
        }
    ],
    "sg:phone":"+61 409 277 665",
    "sg:postcode":"4605",
    "sg:province":"QLD",
    "sg:tags":[
        "earth",
        "excavating",
        "moving",
        "equipment"
    ],
    "wof:name":"BJ's Earthmoving",
    "wof:placetype":"venue"
},
  "geometry": {"coordinates":[151.945786,-26.240498],"type":"Point"}
}