{
  "type": "Feature",
  "properties": {
    "addr:full":"5 Sanford Rd Albany WA 6330",
    "addr:housenumber":"5",
    "addr:postcode":"6330",
    "addr:street":"Sanford Rd",
    "iso:country":"AU",
    "sg:address":"5 Sanford Rd",
    "sg:city":"Albany",
    "sg:classifiers":[
        {
            "category":"Autos & Motor Vehicles",
            "subcategory":"Auto Supplies",
            "type":"Retail Goods"
        }
    ],
    "sg:phone":"+61 8 9841 4444",
    "sg:postcode":"6330",
    "sg:province":"WA",
    "sg:tags":[
        "tyre"
    ],
    "wof:name":"Diffen Ian Tyre & Muffler Centre",
    "wof:placetype":"venue"
},
  "geometry": {"coordinates":[117.879493713,-35.0173797607],"type":"Point"}
}