{
  "type": "Feature",
  "properties": {
    "addr:full":"37 Mckeon St Maroubra NSW 2035",
    "addr:housenumber":"37",
    "addr:postcode":"2035",
    "addr:street":"Mckeon St",
    "iso:country":"AU",
    "sg:address":"37 Mckeon St",
    "sg:city":"Maroubra",
    "sg:classifiers":[
        {
            "category":"Fast Food",
            "type":"Food & Drink"
        }
    ],
    "sg:phone":"+61 2 9349 2581",
    "sg:postcode":"2035",
    "sg:province":"NSW",
    "sg:tags":[
        "away",
        "take"
    ],
    "wof:name":"Maroubra Seafood",
    "wof:placetype":"venue"
},
  "geometry": {"coordinates":[151.255935669,-33.9460716248],"type":"Point"}
}