{
  "type": "Feature",
  "properties": {
    "addr:full":"Chadwick Drv North Maclean QLD 4280",
    "addr:postcode":"4280",
    "addr:street":"Chadwick Drv North",
    "iso:country":"AU",
    "sg:address":"Chadwick Drv",
    "sg:city":"North Maclean",
    "sg:classifiers":[
        {
            "category":"Utilities",
            "subcategory":"Electric",
            "type":"Services"
        }
    ],
    "sg:phone":"+61 411 867 774",
    "sg:postcode":"4280",
    "sg:province":"QLD",
    "sg:tags":[
        "electrical",
        "contractor"
    ],
    "wof:name":"Lazarus Electrical",
    "wof:placetype":"venue"
},
  "geometry": {"coordinates":[153.000214,-27.799526],"type":"Point"}
}