{
  "type": "Feature",
  "properties": {
    "iso:country":"AU",
    "sg:address":"18 Sirius St",
    "sg:city":"Coorparoo",
    "sg:classifiers":[
        {
            "category":"Professional",
            "subcategory":"Management & Consulting",
            "type":"Services"
        }
    ],
    "sg:phone":"+61 7 3394 1136",
    "sg:postcode":"4151",
    "sg:province":"QLD",
    "sg:tags":[
        "consultant"
    ],
    "wof:name":"Industry Consulting Group",
    "wof:placetype":"venue"
},
  "geometry": {"coordinates":[153.07066345199999,-27.5038604736],"type":"Point"}
}