{
  "type": "Feature",
  "properties": {
    "addr:full":"61-63 Leeds St Footscray VIC 3011",
    "addr:housenumber":"61-63",
    "addr:postcode":"3011",
    "addr:street":"Leeds St",
    "iso:country":"AU",
    "sg:address":"61-63 Leeds St",
    "sg:city":"Footscray",
    "sg:classifiers":[
        {
            "category":"Fast Food",
            "type":"Food & Drink"
        }
    ],
    "sg:phone":"+61 3 9687 7803",
    "sg:postcode":"3011",
    "sg:province":"VIC",
    "sg:tags":[
        "away",
        "take"
    ],
    "wof:name":"Express Corner Take Away",
    "wof:placetype":"venue"
},
  "geometry": {"coordinates":[144.90109252900001,-37.8002815247],"type":"Point"}
}