{
  "type": "Feature",
  "properties": {
    "addr:full":"Unit 2, 5 Gamban Esp Currimundi QLD 4551",
    "addr:housenumber":"5",
    "addr:postcode":"4551",
    "addr:street":"Gamban Esp",
    "iso:country":"AU",
    "sg:address":"Unit 2, 5 Gamban Esp",
    "sg:city":"Currimundi",
    "sg:classifiers":[
        {
            "category":"Health Services",
            "subcategory":"Doctor",
            "type":"Services"
        }
    ],
    "sg:phone":"+61 402 804 729",
    "sg:postcode":"4551",
    "sg:province":"QLD",
    "sg:tags":[
        "medical",
        "practitioner"
    ],
    "wof:name":"Lee Albert C H",
    "wof:placetype":"venue"
},
  "geometry": {"coordinates":[153.12620544399999,-26.7661762238],"type":"Point"}
}