{
  "type": "Feature",
  "properties": {
    "addr:full":"44 Aldershot Rd Lonsdale SA 5160",
    "addr:housenumber":"44",
    "addr:postcode":"5160",
    "addr:street":"Aldershot Rd",
    "iso:country":"AU",
    "sg:address":"44 Aldershot Rd",
    "sg:city":"Lonsdale",
    "sg:classifiers":[
        {
            "category":"Building & Trades",
            "subcategory":"Equipment Rental",
            "type":"Services"
        }
    ],
    "sg:phone":"+61 8 8384 3400",
    "sg:postcode":"5160",
    "sg:province":"SA",
    "sg:tags":[
        "crane",
        "hire"
    ],
    "sg:website":"http://www.tigercrane.com.au",
    "wof:name":"Tiger Crane Hire Pty Ltd",
    "wof:placetype":"venue"
},
  "geometry": {"coordinates":[138.50738525400001,-35.1091194153],"type":"Point"}
}