{
  "type": "Feature",
  "properties": {
    "addr:full":"45- 47 Hotham St Collingwood VIC 3066",
    "addr:housenumber":"47",
    "addr:postcode":"3066",
    "addr:street":"Hotham St",
    "iso:country":"AU",
    "sg:address":"45- 47 Hotham St",
    "sg:city":"Collingwood",
    "sg:classifiers":[
        {
            "category":"Real Estate",
            "subcategory":"Architect",
            "type":"Services"
        }
    ],
    "sg:phone":"+61 3 9416 3355",
    "sg:postcode":"3066",
    "sg:province":"VIC",
    "wof:name":"West Simpson Hatzellis Pty Ltd",
    "wof:placetype":"venue"
},
  "geometry": {"coordinates":[144.987518311,-37.7965965271],"type":"Point"}
}