{
  "type": "Feature",
  "properties": {
    "addr:full":"18 Langton St Glenroy VIC 3046",
    "addr:housenumber":"18",
    "addr:postcode":"3046",
    "addr:street":"Langton St",
    "iso:country":"AU",
    "sg:address":"18 Langton St",
    "sg:city":"Glenroy",
    "sg:classifiers":[
        {
            "category":"Industrial Area",
            "type":"Public Place"
        }
    ],
    "sg:phone":"+61 3 9306 8765",
    "sg:postcode":"3046",
    "sg:province":"VIC",
    "sg:tags":[
        "protective",
        "clothing"
    ],
    "wof:name":"A-C Direct Links",
    "wof:placetype":"venue"
},
  "geometry": {"coordinates":[144.91404724099999,-37.7008743286],"type":"Point"}
}