{
  "type": "Feature",
  "properties": {
    "addr:full":"Nicklin Way & Wyanda Drv Bokarina QLD 4575",
    "addr:postcode":"4575",
    "addr:street":"Nicklin Way & Wyanda Drv",
    "iso:country":"AU",
    "sg:address":"Nicklin Way & Wyanda Drv",
    "sg:city":"Bokarina",
    "sg:classifiers":[
        {
            "category":"Autos & Motor Vehicles",
            "subcategory":"Fuel & Gas Station",
            "type":"Retail Goods"
        }
    ],
    "sg:phone":"+61 7 5493 4282",
    "sg:postcode":"4575",
    "sg:province":"QLD",
    "wof:name":"BP Australia Limited",
    "wof:placetype":"venue"
},
  "geometry": {"coordinates":[153.12912,-26.738562],"type":"Point"}
}