{
  "type": "Feature",
  "properties": {
    "addr:full":"34 Belgrave-Hallam Rd Hallam VIC 3803",
    "addr:housenumber":"34",
    "addr:postcode":"3803",
    "addr:street":"Belgrave-Hallam Rd",
    "iso:country":"AU",
    "sg:address":"34 Belgrave-Hallam Rd",
    "sg:city":"Hallam",
    "sg:classifiers":[
        {
            "category":"Home & Garden",
            "subcategory":"Building Materials",
            "type":"Retail Goods"
        }
    ],
    "sg:phone":"+61 3 9796 3655",
    "sg:postcode":"3803",
    "sg:province":"VIC",
    "sg:tags":[
        "merchant",
        "glass",
        "glazier"
    ],
    "wof:name":"A. Aaabalone Glass",
    "wof:placetype":"venue"
},
  "geometry": {"coordinates":[145.27488708499999,-38.0002288818],"type":"Point"}
}