{
  "type": "Feature",
  "properties": {
    "addr:full":"17a Buckland St Toowoomba City QLD 4350",
    "addr:housenumber":"17a",
    "addr:postcode":"4350",
    "addr:street":"Buckland St",
    "iso:country":"AU",
    "sg:address":"17a Buckland St",
    "sg:city":"Toowoomba City",
    "sg:classifiers":[
        {
            "category":"Shopping",
            "subcategory":"Computers & Home Electronics",
            "type":"Retail Goods"
        }
    ],
    "sg:phone":"+61 7 4635 3386",
    "sg:postcode":"4350",
    "sg:province":"QLD",
    "sg:tags":[
        "small",
        "equipment",
        "business"
    ],
    "wof:name":"Garden City Computers",
    "wof:placetype":"venue"
},
  "geometry": {"coordinates":[151.93287699999999,-27.577984],"type":"Point"}
}