{
  "type": "Feature",
  "properties": {
    "addr:full":"Level 1, AAP Centre, Cnr George & Jamison Sts Sydney NSW 2000",
    "addr:postcode":"2000",
    "addr:street":"Cnr George &;Sts",
    "iso:country":"AU",
    "sg:address":"Level 1, AAP Centre, Cnr George & Jamison Sts",
    "sg:city":"Sydney",
    "sg:classifiers":[
        {
            "category":"Health Services",
            "subcategory":"Doctor",
            "type":"Services"
        }
    ],
    "sg:phone":"+61 2 9247 1162",
    "sg:postcode":"2000",
    "sg:province":"NSW",
    "sg:tags":[
        "medical",
        "practitioner"
    ],
    "wof:name":"Turner Mary",
    "wof:placetype":"venue"
},
  "geometry": {"coordinates":[151.20669555699999,-33.8643264771],"type":"Point"}
}