{
  "type": "Feature",
  "properties": {
    "iso:country":"AU",
    "sg:address":"496 North East Rd",
    "sg:city":"Windsor Gardens",
    "sg:classifiers":[
        {
            "category":"Wholesale",
            "subcategory":"Electrical",
            "type":"Manufacturing & Wholesale Goods"
        }
    ],
    "sg:phone":"+61 8 8369 0255",
    "sg:postcode":"5087",
    "sg:province":"SA",
    "sg:tags":[
        "wholesaler"
    ],
    "wof:name":"Rexel Australia Electrical Supplies",
    "wof:placetype":"venue"
},
  "geometry": {"coordinates":[138.651779175,-34.8602905273],"type":"Point"}
}