{
  "type": "Feature",
  "properties": {
    "iso:country":"AU",
    "sg:address":"125 Kavanagh St",
    "sg:city":"South Melbourne",
    "sg:classifiers":[
        {
            "category":"Home & Garden",
            "subcategory":"Furniture",
            "type":"Retail Goods"
        }
    ],
    "sg:phone":"+61 3 9696 2811",
    "sg:postcode":"3205",
    "sg:province":"VIC",
    "sg:tags":[
        "business"
    ],
    "wof:name":"Data Decor Interiors Pty Ltd",
    "wof:placetype":"venue"
},
  "geometry": {"coordinates":[144.96173099999999,-37.826534],"type":"Point"}
}