{
  "type": "Feature",
  "properties": {
    "iso:country":"AU",
    "sg:address":"26 Somerset Ave",
    "sg:city":"Narellan",
    "sg:classifiers":[
        {
            "category":"Professional",
            "subcategory":"Accounting & Tax Preparation",
            "type":"Services"
        }
    ],
    "sg:phone":"+61 2 4647 2533",
    "sg:postcode":"2567",
    "sg:province":"NSW",
    "sg:tags":[
        "consultant",
        "taxation"
    ],
    "wof:name":"JT Ryan & Co Accountants",
    "wof:placetype":"venue"
},
  "geometry": {"coordinates":[150.739624023,-34.0417556763],"type":"Point"}
}