{
  "type": "Feature",
  "properties": {
    "addr:full":"New England Hwy Glen Innes NSW 2370",
    "addr:postcode":"2370",
    "addr:street":"England Hwy",
    "iso:country":"AU",
    "sg:address":"New England Hwy",
    "sg:city":"Glen Innes",
    "sg:classifiers":[
        {
            "category":"Autos & Motor Vehicles",
            "subcategory":"Boat Sales",
            "type":"Retail Goods"
        }
    ],
    "sg:phone":"+61 2 6732 1755",
    "sg:postcode":"2370",
    "sg:province":"NSW",
    "sg:tags":[
        "yacht"
    ],
    "wof:name":"Fakes Engineering & Marine",
    "wof:placetype":"venue"
},
  "geometry": {"coordinates":[151.73831176799999,-29.7364063263],"type":"Point"}
}