{
  "type": "Feature",
  "properties": {
    "addr:full":"U17/ 151 Horton Pde Maroochydore QLD 4558",
    "addr:postcode":"4558",
    "addr:street":"/;Horton Pde",
    "iso:country":"AU",
    "sg:address":"U17/ 151 Horton Pde",
    "sg:city":"Maroochydore",
    "sg:classifiers":[
        {
            "category":"Shopping",
            "subcategory":"Pawn Shop",
            "type":"Retail Goods"
        }
    ],
    "sg:phone":"+61 7 5443 5378",
    "sg:postcode":"4558",
    "sg:province":"QLD",
    "sg:tags":[
        "pawnbroker"
    ],
    "wof:name":"Oz Fast Payday Loans Pty Ltd",
    "wof:placetype":"venue"
},
  "geometry": {"coordinates":[153.09127807600001,-26.654712677],"type":"Point"}
}