{
  "type": "Feature",
  "properties": {
    "iso:country":"AU",
    "sg:address":"145 Argyle St",
    "sg:city":"Traralgon",
    "sg:classifiers":[
        {
            "category":"Retail",
            "subcategory":"Repair Shop",
            "type":"Services"
        }
    ],
    "sg:phone":"+61 13 18 38",
    "sg:postcode":"3844",
    "sg:province":"VIC",
    "sg:tags":[
        "windscreen"
    ],
    "wof:name":"Protector Autoglass",
    "wof:placetype":"venue"
},
  "geometry": {"coordinates":[146.555450439,-38.1920852661],"type":"Point"}
}