{
  "type": "Feature",
  "properties": {
    "iso:country":"AU",
    "sg:address":"81 Wade St",
    "sg:city":"Crookwell",
    "sg:classifiers":[
        {
            "category":"Home & Garden",
            "subcategory":"Building Materials",
            "type":"Retail Goods"
        }
    ],
    "sg:phone":"+61 417 831 532",
    "sg:postcode":"2583",
    "sg:province":"NSW",
    "sg:tags":[
        "retaining",
        "wall"
    ],
    "wof:name":"Craig O&#039;Brien Stone Mason & Bricklaying",
    "wof:placetype":"venue"
},
  "geometry": {"coordinates":[149.472000122,-34.4649658203],"type":"Point"}
}