{
  "type": "Feature",
  "properties": {
    "iso:country":"AU",
    "sg:address":"113 Wharf St",
    "sg:city":"Cannington",
    "sg:classifiers":[
        {
            "category":"Professional",
            "subcategory":"Accounting & Tax Preparation",
            "type":"Services"
        }
    ],
    "sg:phone":"+61 8 9358 3831",
    "sg:postcode":"6107",
    "sg:province":"WA",
    "sg:tags":[
        "consultant",
        "taxation"
    ],
    "wof:name":"Del Carlo Reid & Subra Pty Ltd",
    "wof:placetype":"venue"
},
  "geometry": {"coordinates":[115.933731079,-32.015586853],"type":"Point"}
}