{
  "type": "Feature",
  "properties": {
    "addr:full":"12th St Mildura VIC 3500",
    "addr:postcode":"3500",
    "addr:street":"12Th St",
    "iso:country":"AU",
    "sg:address":"12th St",
    "sg:city":"Mildura",
    "sg:classifiers":[
        {
            "category":"Retail",
            "subcategory":"Event Space",
            "type":"Services"
        }
    ],
    "sg:phone":"+61 3 5023 0751",
    "sg:postcode":"3500",
    "sg:province":"VIC",
    "sg:tags":[
        "venue",
        "reception",
        "wedding"
    ],
    "wof:name":"Mildura Function Centre",
    "wof:placetype":"venue"
},
  "geometry": {"coordinates":[142.12792968799999,-34.2341804504],"type":"Point"}
}