{
  "type": "Feature",
  "properties": {
    "iso:country":"AU",
    "sg:address":"611 Wisemans Ferry Rd",
    "sg:city":"Somersby",
    "sg:classifiers":[
        {
            "category":"Retail",
            "subcategory":"Event Space",
            "type":"Services"
        }
    ],
    "sg:phone":"+61 2 4372 1444",
    "sg:postcode":"2250",
    "sg:province":"NSW",
    "sg:tags":[
        "venue",
        "reception",
        "wedding"
    ],
    "wof:name":"Linton Gardens Reception & Function Centre",
    "wof:placetype":"venue"
},
  "geometry": {"coordinates":[151.29071044899999,-33.3735847473],"type":"Point"}
}