{
  "type": "Feature",
  "properties": {
    "addr:full":"191 Main Rd McLaren Vale SA 5171",
    "addr:housenumber":"191",
    "addr:postcode":"5171",
    "addr:street":"Main Rd",
    "iso:country":"AU",
    "sg:address":"191 Main Rd",
    "sg:city":"McLaren Vale",
    "sg:classifiers":[
        {
            "category":"Health Services",
            "subcategory":"Doctor",
            "type":"Services"
        }
    ],
    "sg:phone":"+61 8 8323 8944",
    "sg:postcode":"5171",
    "sg:province":"SA",
    "sg:tags":[
        "podiatrist"
    ],
    "wof:name":"Bennetts Rosemary L",
    "wof:placetype":"venue"
},
  "geometry": {"coordinates":[138.53788757300001,-35.215461731],"type":"Point"}
}