{
  "type": "Feature",
  "properties": {
    "addr:full":"147 Main St Peterborough SA 5422",
    "addr:housenumber":"147",
    "addr:postcode":"5422",
    "addr:street":"Main St",
    "iso:country":"AU",
    "sg:address":"147 Main St",
    "sg:city":"Peterborough",
    "sg:classifiers":[
        {
            "category":"Personal",
            "subcategory":"Beauty Salon",
            "type":"Services"
        }
    ],
    "sg:phone":"+61 8 8651 2675",
    "sg:postcode":"5422",
    "sg:province":"SA",
    "sg:tags":[
        "hairdresser"
    ],
    "wof:name":"Brendans Hairdressing",
    "wof:placetype":"venue"
},
  "geometry": {"coordinates":[138.83827209500001,-32.9731254578],"type":"Point"}
}