{
  "type": "Feature",
  "properties": {
    "iso:country":"AU",
    "sg:address":"PO Box 287",
    "sg:city":"Fairy Meadow",
    "sg:classifiers":[
        {
            "category":"Commercial Area",
            "type":"Public Place"
        }
    ],
    "sg:phone":"+61 418 423 342",
    "sg:postcode":"2519",
    "sg:province":"NSW",
    "sg:tags":[
        "heavy",
        "carrier"
    ],
    "wof:name":"Linpet Logistics",
    "wof:placetype":"venue"
},
  "geometry": {"coordinates":[150.893326,-34.39167],"type":"Point"}
}