{
  "type": "Feature",
  "properties": {
    "addr:full":"Wynwyn Rd Natimuk VIC 3409",
    "addr:postcode":"3409",
    "addr:street":"Wynwyn Rd",
    "iso:country":"AU",
    "sg:address":"Wynwyn Rd",
    "sg:city":"Natimuk",
    "sg:classifiers":[
        {
            "category":"Farming",
            "subcategory":"Farm",
            "type":"Manufacturing & Wholesale Goods"
        }
    ],
    "sg:phone":"+61 3 5387 1250",
    "sg:postcode":"3409",
    "sg:province":"VIC",
    "sg:tags":[
        "farmer"
    ],
    "wof:name":"Smith P W & M A",
    "wof:placetype":"venue"
},
  "geometry": {"coordinates":[141.92149352999999,-36.7343292236],"type":"Point"}
}