{
  "type": "Feature",
  "properties": {
    "addr:full":"Jackeys Marsh Rd Meander TAS 7304",
    "addr:postcode":"7304",
    "addr:street":"Jackeys Marsh Rd",
    "iso:country":"AU",
    "sg:address":"Jackeys Marsh Rd",
    "sg:city":"Meander",
    "sg:classifiers":[
        {
            "category":"Wholesale",
            "subcategory":"Machinery & Supplies",
            "type":"Manufacturing & Wholesale Goods"
        }
    ],
    "sg:phone":"+61 3 6369 5205",
    "sg:postcode":"7304",
    "sg:province":"TAS",
    "wof:name":"Super-Axe",
    "wof:placetype":"venue"
},
  "geometry": {"coordinates":[146.62678500000001,-41.649254],"type":"Point"}
}