{
  "type": "Feature",
  "properties": {
    "iso:country":"AU",
    "sg:address":"PO Box 194",
    "sg:city":"Waverley",
    "sg:classifiers":[
        {
            "category":"Real Estate",
            "subcategory":"Developer",
            "type":"Services"
        }
    ],
    "sg:phone":"+61 2 9665 0997",
    "sg:postcode":"2024",
    "sg:province":"NSW",
    "sg:tags":[
        "development"
    ],
    "wof:name":"Maverick Developments Pty Ltd",
    "wof:placetype":"venue"
},
  "geometry": {"coordinates":[151.253814697,-33.8993492126],"type":"Point"}
}