{
  "type": "Feature",
  "properties": {
    "addr:full":"131- 133 Hawthorn Rd Caulfield VIC 3162",
    "addr:housenumber":"133",
    "addr:postcode":"3162",
    "addr:street":"Hawthorn Rd",
    "iso:country":"AU",
    "sg:address":"131- 133 Hawthorn Rd",
    "sg:city":"Caulfield",
    "sg:classifiers":[
        {
            "category":"Organizations",
            "subcategory":"Community Association",
            "type":"Services"
        }
    ],
    "sg:phone":"+61 3 9523 0535",
    "sg:postcode":"3162",
    "sg:province":"VIC",
    "sg:tags":[
        "organisation",
        "family",
        "welfare"
    ],
    "wof:name":"National Council Of Jewish Women",
    "wof:placetype":"venue"
},
  "geometry": {"coordinates":[145.02317810100001,-37.880645752],"type":"Point"}
}