{
  "type": "Feature",
  "properties": {
    "addr:full":"PO Box 3217 Murrumbateman ACT 2582",
    "addr:postcode":"2582",
    "iso:country":"AU",
    "sg:address":"PO Box 3217",
    "sg:city":"Murrumbateman",
    "sg:classifiers":[
        {
            "category":"Communications",
            "subcategory":"Film & Video Production",
            "type":"Services"
        }
    ],
    "sg:phone":"+61 1300 791 415",
    "sg:postcode":"2582",
    "sg:province":"ACT",
    "sg:tags":[
        "television",
        "system",
        "circuit",
        "closed"
    ],
    "wof:name":"Complete Security Solutions",
    "wof:placetype":"venue"
},
  "geometry": {"coordinates":[149.029693603,-34.9732208252],"type":"Point"}
}