{
  "type": "Feature",
  "properties": {
    "addr:full":"RMB 139 Blakers Rd Maroota NSW 2756",
    "addr:postcode":"2756",
    "addr:street":"Blakers Rd",
    "iso:country":"AU",
    "sg:address":"RMB 139 Blakers Rd",
    "sg:city":"Maroota",
    "sg:classifiers":[
        {
            "category":"Freight",
            "type":"Transportation"
        }
    ],
    "sg:phone":"+61 2 4575 0208",
    "sg:postcode":"2756",
    "sg:province":"NSW",
    "sg:tags":[
        "light",
        "carrier"
    ],
    "wof:name":"Roberts K B",
    "wof:placetype":"venue"
},
  "geometry": {"coordinates":[150.96437072800001,-33.4686775208],"type":"Point"}
}