{
  "type": "Feature",
  "properties": {
    "iso:country":"AU",
    "sg:address":"52 Osborne St",
    "sg:city":"Nowra",
    "sg:classifiers":[
        {
            "category":"Professional",
            "subcategory":"Accounting & Tax Preparation",
            "type":"Services"
        }
    ],
    "sg:phone":"+61 2 4421 4344",
    "sg:postcode":"2541",
    "sg:province":"NSW",
    "sg:tags":[
        "accountant",
        "auditor"
    ],
    "wof:name":"Murphy David",
    "wof:placetype":"venue"
},
  "geometry": {"coordinates":[150.598419189,-34.8738479614],"type":"Point"}
}