{
  "type": "Feature",
  "properties": {
    "iso:country":"AU",
    "sg:address":"2 Gladstone Rd",
    "sg:city":"Dandenong",
    "sg:classifiers":[
        {
            "category":"Autos & Motor Vehicles",
            "subcategory":"Auto Supplies",
            "type":"Retail Goods"
        }
    ],
    "sg:phone":"+61 3 9794 6155",
    "sg:postcode":"3175",
    "sg:province":"VIC",
    "sg:tags":[
        "paint",
        "automotive"
    ],
    "wof:name":"C D Auto Paints Supplies Pty Ltd",
    "wof:placetype":"venue"
},
  "geometry": {"coordinates":[145.20375060999999,-37.9746589661],"type":"Point"}
}