{
  "type": "Feature",
  "properties": {
    "addr:full":"13 Venn Pde Thornlands QLD 4164",
    "addr:housenumber":"13",
    "addr:postcode":"4164",
    "addr:street":"Venn Pde",
    "iso:country":"AU",
    "sg:address":"13 Venn Pde",
    "sg:city":"Thornlands",
    "sg:classifiers":[
        {
            "category":"Shopping",
            "subcategory":"Mobile Phones",
            "type":"Retail Goods"
        }
    ],
    "sg:phone":"+61 7 3206 3535",
    "sg:postcode":"4164",
    "sg:province":"QLD",
    "sg:tags":[
        "wholesaler",
        "mfrs",
        "electrical",
        "switchboard"
    ],
    "wof:name":"Custom Control Systems",
    "wof:placetype":"venue"
},
  "geometry": {"coordinates":[153.26481628400001,-27.5760040283],"type":"Point"}
}