{
  "type": "Feature",
  "properties": {
    "addr:full":"238 Sloane St Goulburn NSW 2580",
    "addr:housenumber":"238",
    "addr:postcode":"2580",
    "addr:street":"Sloane St",
    "iso:country":"AU",
    "sg:address":"238 Sloane St",
    "sg:city":"Goulburn",
    "sg:classifiers":[
        {
            "category":"Home & Garden",
            "subcategory":"Furniture",
            "type":"Retail Goods"
        }
    ],
    "sg:phone":"+61 2 4821 5992",
    "sg:postcode":"2580",
    "sg:province":"NSW",
    "sg:tags":[
        "outdoor"
    ],
    "wof:name":"The Complete Garden",
    "wof:placetype":"venue"
},
  "geometry": {"coordinates":[149.71853637699999,-34.7542533875],"type":"Point"}
}