{
  "type": "Feature",
  "properties": {
    "addr:full":"U3/ 93 Matthews Ave Airport West VIC 3042",
    "addr:housenumber":"93",
    "addr:postcode":"3042",
    "addr:street":"U3 /;Matthews Ave",
    "iso:country":"AU",
    "sg:address":"U3/ 93 Matthews Ave",
    "sg:city":"Airport West",
    "sg:classifiers":[
        {
            "category":"Professional",
            "type":"Services"
        }
    ],
    "sg:phone":"+61 3 9317 2500",
    "sg:postcode":"3042",
    "sg:province":"VIC",
    "sg:tags":[
        "shop",
        "fitting"
    ],
    "wof:name":"Shopco Fitouts Pty Ltd",
    "wof:placetype":"venue"
},
  "geometry": {"coordinates":[144.89097595199999,-37.71484375],"type":"Point"}
}