{
  "type": "Feature",
  "properties": {
    "addr:full":"F.E. Walker St Bundaberg QLD 4670",
    "addr:postcode":"4670",
    "addr:street":"F.E. Walker St",
    "iso:country":"AU",
    "sg:address":"F.E. Walker St",
    "sg:city":"Bundaberg",
    "sg:classifiers":[
        {
            "category":"Wholesale",
            "subcategory":"Farm Supplies",
            "type":"Manufacturing & Wholesale Goods"
        }
    ],
    "sg:phone":"+61 7 4159 3140",
    "sg:postcode":"4670",
    "sg:province":"QLD",
    "sg:tags":[
        "equipment"
    ],
    "wof:name":"K A Tractor Repairs & Spares",
    "wof:placetype":"venue"
},
  "geometry": {"coordinates":[152.36387634299999,-24.8759822845],"type":"Point"}
}