{
  "type": "Feature",
  "properties": {
    "addr:full":"5 Gallipoli St Bossley Park NSW 2176",
    "addr:housenumber":"5",
    "addr:postcode":"2176",
    "addr:street":"Gallipoli St",
    "iso:country":"AU",
    "sg:address":"5 Gallipoli St",
    "sg:city":"Bossley Park",
    "sg:classifiers":[
        {
            "category":"Communications",
            "type":"Services"
        }
    ],
    "sg:phone":"+61 2 8205 7807",
    "sg:postcode":"2176",
    "sg:province":"NSW",
    "sg:tags":[
        "data"
    ],
    "wof:name":"Hightel Communications",
    "wof:placetype":"venue"
},
  "geometry": {"coordinates":[150.88417053200001,-33.8559646606],"type":"Point"}
}