{
  "type": "Feature",
  "properties": {
    "iso:country":"AU",
    "sg:address":"Shp 10/ 218 Dorset Rd",
    "sg:city":"Boronia",
    "sg:classifiers":[
        {
            "category":"Food & Beverages",
            "subcategory":"Liquor & Beverages",
            "type":"Retail Goods"
        }
    ],
    "sg:phone":"+61 3 9762 2005",
    "sg:postcode":"3155",
    "sg:province":"VIC",
    "sg:tags":[
        "merchant",
        "spirit",
        "wine"
    ],
    "wof:name":"Jack Riley King Valley Wines",
    "wof:placetype":"venue"
},
  "geometry": {"coordinates":[145.28579711899999,-37.861869812],"type":"Point"}
}