{
  "type": "Feature",
  "properties": {
    "addr:full":"160 Canterbury Rd Bayswater VIC 3153",
    "addr:housenumber":"160",
    "addr:postcode":"3153",
    "addr:street":"Canterbury Rd",
    "iso:country":"AU",
    "sg:address":"160 Canterbury Rd",
    "sg:city":"Bayswater",
    "sg:classifiers":[
        {
            "category":"Manufacturing",
            "subcategory":"Rubber & Plastics",
            "type":"Manufacturing & Wholesale Goods"
        }
    ],
    "sg:phone":"+61 3 9720 3279",
    "sg:postcode":"3153",
    "sg:province":"VIC",
    "sg:tags":[
        "product",
        "retail"
    ],
    "wof:name":"RSP Rubber& Hose Products",
    "wof:placetype":"venue"
},
  "geometry": {"coordinates":[145.282836914,-37.8273925781],"type":"Point"}
}