{
  "type": "Feature",
  "properties": {
    "iso:country":"AU",
    "sg:address":"953 Nepean Hwy",
    "sg:city":"Moorabbin",
    "sg:classifiers":[
        {
            "category":"Professional",
            "subcategory":"Accounting & Tax Preparation",
            "type":"Services"
        }
    ],
    "sg:phone":"+61 3 9557 5842",
    "sg:postcode":"3189",
    "sg:province":"VIC",
    "sg:tags":[
        "accountant",
        "auditor"
    ],
    "wof:name":"Harold Sztainbok & Co Pty Ltd",
    "wof:placetype":"venue"
},
  "geometry": {"coordinates":[145.03729248100001,-37.9373588562],"type":"Point"}
}