{
  "type": "Feature",
  "properties": {
    "addr:full":"8 Horizon Crt Highton VIC 3216",
    "addr:housenumber":"8",
    "addr:postcode":"3216",
    "addr:street":"Horizon Crt",
    "iso:country":"AU",
    "sg:address":"8 Horizon Crt",
    "sg:city":"Highton",
    "sg:classifiers":[
        {
            "category":"Professional",
            "subcategory":"Employment Agencies",
            "type":"Services"
        }
    ],
    "sg:phone":"+61 3 5221 8206",
    "sg:postcode":"3216",
    "sg:province":"VIC",
    "sg:tags":[
        "occupational",
        "therapist"
    ],
    "wof:name":"OTcare (Tina Stenos)",
    "wof:placetype":"venue"
},
  "geometry": {"coordinates":[144.31198120100001,-38.1539039612],"type":"Point"}
}