{
  "type": "Feature",
  "properties": {
    "addr:full":"12 Commercial St Korumburra VIC 3950",
    "addr:housenumber":"12",
    "addr:postcode":"3950",
    "addr:street":"Commercial St",
    "iso:country":"AU",
    "sg:address":"12 Commercial St",
    "sg:city":"Korumburra",
    "sg:classifiers":[
        {
            "category":"Shopping",
            "type":"Retail Goods"
        }
    ],
    "sg:phone":"+61 3 5655 1171",
    "sg:postcode":"3950",
    "sg:province":"VIC",
    "sg:tags":[
        "produce",
        "grain"
    ],
    "wof:name":"Korumburra Produce,Plants & Pets",
    "wof:placetype":"venue"
},
  "geometry": {"coordinates":[145.82281494099999,-38.4323501587],"type":"Point"}
}