{
  "type": "Feature",
  "properties": {
    "addr:full":"Shop 5 Paul Crt Dandenong VIC 3175",
    "addr:housenumber":"shop 5",
    "addr:postcode":"3175",
    "addr:street":"Paul Crt",
    "iso:country":"AU",
    "sg:address":"Shop 5 Paul Crt",
    "sg:city":"Dandenong",
    "sg:classifiers":[
        {
            "category":"Home & Garden",
            "subcategory":"Kitchen Supply",
            "type":"Retail Goods"
        }
    ],
    "sg:phone":"+61 3 9792 2605",
    "sg:postcode":"3175",
    "sg:province":"VIC",
    "sg:tags":[
        "equipment",
        "diving"
    ],
    "wof:name":"Skin & Scuba Sports",
    "wof:placetype":"venue"
},
  "geometry": {"coordinates":[145.20242309599999,-37.9869613647],"type":"Point"}
}