{
  "type": "Feature",
  "properties": {
    "addr:full":"Sd1/ 211 Princes Hwy Port Fairy VIC 3284",
    "addr:housenumber":"sd1 / 211",
    "addr:postcode":"3284",
    "addr:street":"Princes Hwy",
    "iso:country":"AU",
    "sg:address":"Sd1/ 211 Princes Hwy",
    "sg:city":"Port Fairy",
    "sg:classifiers":[
        {
            "category":"Retail",
            "subcategory":"Repair Shop",
            "type":"Services"
        }
    ],
    "sg:phone":"+61 409 148 468",
    "sg:postcode":"3284",
    "sg:province":"VIC",
    "sg:tags":[
        "windscreen"
    ],
    "wof:name":"Conlan Richard Panel Beating & Oven Baked Spray Painting",
    "wof:placetype":"venue"
},
  "geometry": {"coordinates":[142.236572266,-38.3644447327],"type":"Point"}
}