{
  "type": "Feature",
  "properties": {
    "addr:full":"Cnr Boundary & Potassium St Narangba QLD 4504",
    "addr:postcode":"4504",
    "addr:street":"Cnr;St",
    "iso:country":"AU",
    "sg:address":"Cnr Boundary & Potassium St",
    "sg:city":"Narangba",
    "sg:classifiers":[
        {
            "category":"Retail",
            "subcategory":"Car Wash",
            "type":"Services"
        }
    ],
    "sg:phone":"+61 7 3204 1844",
    "sg:postcode":"4504",
    "sg:province":"QLD",
    "sg:tags":[
        "merchant",
        "oil",
        "refiner"
    ],
    "wof:name":"Marque Lubricants",
    "wof:placetype":"venue"
},
  "geometry": {"coordinates":[153.005096436,-27.2022819519],"type":"Point"}
}