{
  "type": "Feature",
  "properties": {
    "addr:full":"69 Grey St East Melbourne VIC 3002",
    "addr:housenumber":"69",
    "addr:postcode":"3002",
    "addr:street":"Grey St",
    "iso:country":"AU",
    "sg:address":"69 Grey St",
    "sg:city":"East Melbourne",
    "sg:classifiers":[
        {
            "category":"Real Estate",
            "subcategory":"Architect",
            "type":"Services"
        }
    ],
    "sg:phone":"+61 3 9416 0514",
    "sg:postcode":"3002",
    "sg:province":"VIC",
    "wof:name":"Dowling Hobba Pty Ltd",
    "wof:placetype":"venue"
},
  "geometry": {"coordinates":[144.98724365199999,-37.8121185303],"type":"Point"}
}