{
  "type": "Feature",
  "properties": {
    "addr:full":"Boyters La South West Rocks NSW 2431",
    "addr:postcode":"2431",
    "addr:street":"La South West Rocks",
    "iso:country":"AU",
    "sg:address":"Boyters La",
    "sg:city":"South West Rocks",
    "sg:classifiers":[
        {
            "category":"Farming",
            "subcategory":"Fish & Marine Products",
            "type":"Manufacturing & Wholesale Goods"
        }
    ],
    "sg:phone":"+61 2 6566 6248",
    "sg:postcode":"2431",
    "sg:province":"NSW",
    "sg:tags":[
        "supplier",
        "oyster",
        "farmer"
    ],
    "wof:name":"Mr Oyster Pty Ltd",
    "wof:placetype":"venue"
},
  "geometry": {"coordinates":[153.03413399999999,-30.915678],"type":"Point"}
}