{
  "type": "Feature",
  "properties": {
    "addr:full":"11 Killingholme Drv Mornington VIC 3931",
    "addr:housenumber":"11",
    "addr:postcode":"3931",
    "addr:street":"Killingholme Drv",
    "iso:country":"AU",
    "sg:address":"11 Killingholme Drv",
    "sg:city":"Mornington",
    "sg:classifiers":[
        {
            "category":"Professional",
            "subcategory":"Art Services",
            "type":"Services"
        }
    ],
    "sg:phone":"+61 403 722 211",
    "sg:postcode":"3931",
    "sg:province":"VIC",
    "sg:tags":[
        "graphic",
        "designer"
    ],
    "wof:name":"James Hart Design",
    "wof:placetype":"venue"
},
  "geometry": {"coordinates":[145.05569457999999,-38.2419776917],"type":"Point"}
}