{
  "type": "Feature",
  "properties": {
    "addr:full":"30 Browning St South Brisbane QLD 4101",
    "addr:housenumber":"30",
    "addr:postcode":"4101",
    "addr:street":"Browning St",
    "iso:country":"AU",
    "sg:address":"30 Browning St",
    "sg:city":"South Brisbane",
    "sg:classifiers":[
        {
            "category":"Education",
            "subcategory":"Kindergarten",
            "type":"Public Place"
        }
    ],
    "sg:phone":"+61 7 3844 6187",
    "sg:postcode":"4101",
    "sg:province":"QLD",
    "sg:tags":[
        "pre-schools"
    ],
    "wof:name":"Greek Orthodox Community Child Care Centre",
    "wof:placetype":"venue"
},
  "geometry": {"coordinates":[153.014434814,-27.479429245],"type":"Point"}
}