{
  "type": "Feature",
  "properties": {
    "addr:full":"3/57 Regent St Paddington NSW 2021",
    "addr:housenumber":"/ 57",
    "addr:postcode":"2021",
    "addr:street":"Regent St",
    "iso:country":"AU",
    "sg:address":"3/57 Regent St",
    "sg:city":"Paddington",
    "sg:classifiers":[
        {
            "category":"Real Estate",
            "subcategory":"Architect",
            "type":"Services"
        }
    ],
    "sg:phone":"+61 2 9361 6790",
    "sg:postcode":"2021",
    "sg:province":"NSW",
    "wof:name":"Graham Humphrys Pty Ltd",
    "wof:placetype":"venue"
},
  "geometry": {"coordinates":[151.22773742699999,-33.8880233765],"type":"Point"}
}