{
  "type": "Feature",
  "properties": {
    "addr:full":"Murray St Jurien WA 6516",
    "addr:postcode":"6516",
    "addr:street":"Murray St",
    "iso:country":"AU",
    "sg:address":"Murray St",
    "sg:city":"Jurien",
    "sg:classifiers":[
        {
            "category":"Personal",
            "subcategory":"Beauty Salon",
            "type":"Services"
        }
    ],
    "sg:phone":"+61 8 9652 1391",
    "sg:postcode":"6516",
    "sg:province":"WA",
    "sg:tags":[
        "hairdresser"
    ],
    "wof:name":"Jurien Hairstylists",
    "wof:placetype":"venue"
},
  "geometry": {"coordinates":[115.042252,-30.303211],"type":"Point"}
}