{
  "type": "Feature",
  "properties": {
    "addr:full":"Dolmison Ave Wyong NSW 2259",
    "addr:postcode":"2259",
    "addr:street":"Dolmison Ave",
    "iso:country":"AU",
    "sg:address":"Dolmison Ave",
    "sg:city":"Wyong",
    "sg:classifiers":[
        {
            "category":"Building & Trades",
            "subcategory":"Construction",
            "type":"Services"
        }
    ],
    "sg:phone":"+61 2 4353 2497",
    "sg:postcode":"2259",
    "sg:province":"NSW",
    "sg:tags":[
        "fitting",
        "line",
        "electric",
        "power"
    ],
    "wof:name":"Dulmison / Utilux",
    "wof:placetype":"venue"
},
  "geometry": {"coordinates":[151.44085693400001,-33.2684211731],"type":"Point"}
}