{
  "type": "Feature",
  "properties": {
    "addr:full":"14 Joseph St Lidcombe NSW 2141",
    "addr:housenumber":"14",
    "addr:postcode":"2141",
    "addr:street":"Joseph St",
    "iso:country":"AU",
    "sg:address":"14 Joseph St",
    "sg:city":"Lidcombe",
    "sg:classifiers":[
        {
            "category":"Retail",
            "subcategory":"Driving School",
            "type":"Services"
        }
    ],
    "sg:phone":"+61 2 9649 7447",
    "sg:postcode":"2141",
    "sg:province":"NSW",
    "wof:name":"Least Cost Taxi Centre Pty Ltd",
    "wof:placetype":"venue"
},
  "geometry": {"coordinates":[151.04354858400001,-33.8642501831],"type":"Point"}
}