{
  "type": "Feature",
  "properties": {
    "iso:country":"AU",
    "sg:address":"83 The Grand Pde",
    "sg:city":"Brighton-le-Sands",
    "sg:classifiers":[
        {
            "category":"Cafe",
            "type":"Food & Drink"
        }
    ],
    "sg:phone":"+61 2 9556 1727",
    "sg:postcode":"2216",
    "sg:province":"NSW",
    "wof:name":"Bay Vista Gateau",
    "wof:placetype":"venue"
},
  "geometry": {"coordinates":[151.155945,-33.961243],"type":"Point"}
}