{
  "type": "Feature",
  "properties": {
    "iso:country":"AU",
    "sg:address":"29 Saville St",
    "sg:city":"Broome",
    "sg:classifiers":[
        {
            "category":"Food & Beverages",
            "subcategory":"Supermarket",
            "type":"Retail Goods"
        }
    ],
    "sg:phone":"+61 8 9192 1027",
    "sg:postcode":"6725",
    "sg:province":"WA",
    "sg:tags":[
        "grocery",
        "store"
    ],
    "wof:name":"Fong's Store",
    "wof:placetype":"venue"
},
  "geometry": {"coordinates":[122.230911255,-17.966501236],"type":"Point"}
}