{
  "type": "Feature",
  "properties": {
    "addr:full":"Senior Campus - Etty St Castlemaine VIC 3450",
    "addr:postcode":"3450",
    "addr:street":"Etty St",
    "iso:country":"AU",
    "sg:address":"Senior Campus - Etty St",
    "sg:city":"Castlemaine",
    "sg:classifiers":[
        {
            "category":"Education",
            "subcategory":"School",
            "type":"Public Place"
        }
    ],
    "sg:phone":"+61 3 5479 4230",
    "sg:postcode":"3450",
    "sg:province":"VIC",
    "sg:tags":[
        "state",
        "except",
        "nsw"
    ],
    "wof:name":"Castlemaine Secondary College",
    "wof:placetype":"venue"
},
  "geometry": {"coordinates":[144.214752197,-37.0776405334],"type":"Point"}
}