{
  "type": "Feature",
  "properties": {
    "iso:country":"AU",
    "sg:address":"Shop 47, Stud Park Shopping Centre",
    "sg:city":"Rowville",
    "sg:classifiers":[
        {
            "category":"Personal",
            "subcategory":"Beauty Salon",
            "type":"Services"
        }
    ],
    "sg:phone":"+61 3 9753 3966",
    "sg:postcode":"3178",
    "sg:province":"VIC",
    "wof:name":"The Painted Lady",
    "wof:placetype":"venue"
},
  "geometry": {"coordinates":[145.221466064,-37.980430603],"type":"Point"}
}