{
  "type": "Feature",
  "properties": {
    "iso:country":"AU",
    "sg:address":"Ste105/ 33 Lexington Drv",
    "sg:city":"Bella Vista",
    "sg:classifiers":[
        {
            "category":"Professional",
            "subcategory":"Employment Agencies",
            "type":"Services"
        }
    ],
    "sg:phone":"+61 2 8883 4689",
    "sg:postcode":"2153",
    "sg:province":"NSW",
    "wof:name":"Leadership Source",
    "wof:placetype":"venue"
},
  "geometry": {"coordinates":[150.94619750999999,-33.733707428],"type":"Point"}
}