{
  "type": "Feature",
  "properties": {
    "iso:country":"AU",
    "sg:address":"94 Queen St",
    "sg:city":"Busselton",
    "sg:classifiers":[
        {
            "category":"Personal",
            "subcategory":"Beauty Salon",
            "type":"Services"
        }
    ],
    "sg:phone":"+61 8 9752 2277",
    "sg:postcode":"6280",
    "sg:province":"WA",
    "sg:tags":[
        "hairdresser"
    ],
    "wof:name":"Studio Capricorn",
    "wof:placetype":"venue"
},
  "geometry": {"coordinates":[115.344848633,-33.6515388489],"type":"Point"}
}