{
  "type": "Feature",
  "properties": {
    "addr:full":"3 Tabuteau Rd Moe VIC 3825",
    "addr:housenumber":"3",
    "addr:postcode":"3825",
    "addr:street":"Tabuteau Rd",
    "iso:country":"AU",
    "sg:address":"3 Tabuteau Rd",
    "sg:city":"Moe",
    "sg:classifiers":[
        {
            "category":"Autos & Motor Vehicles",
            "subcategory":"Auto Supplies",
            "type":"Retail Goods"
        }
    ],
    "sg:phone":"+61 3 5127 5164",
    "sg:postcode":"3825",
    "sg:province":"VIC",
    "sg:tags":[
        "car",
        "alarm"
    ],
    "wof:name":"P & V Grealy Automotive Electrician",
    "wof:placetype":"venue"
},
  "geometry": {"coordinates":[146.25943000000001,-38.169552],"type":"Point"}
}