{
  "type": "Feature",
  "properties": {
    "addr:full":"42 Dean Pde Rankin Park NSW 2287",
    "addr:housenumber":"42",
    "addr:postcode":"2287",
    "addr:street":"Dean Pde Rankin",
    "iso:country":"AU",
    "sg:address":"42 Dean Pde",
    "sg:city":"Rankin Park",
    "sg:classifiers":[
        {
            "category":"Shopping",
            "subcategory":"Bridal",
            "type":"Retail Goods"
        }
    ],
    "sg:phone":"+61 2 4965 5234",
    "sg:postcode":"2287",
    "sg:province":"NSW",
    "sg:tags":[
        "hire",
        "wear"
    ],
    "wof:name":"Kylie-Ann Couture",
    "wof:placetype":"venue"
},
  "geometry": {"coordinates":[151.68295288100001,-32.9218559265],"type":"Point"}
}