{
  "type": "Feature",
  "properties": {
    "addr:full":"Suite 1, Level 1/ 41A Burwood Rd Burwood NSW 2134",
    "addr:housenumber":"/ 41a",
    "addr:postcode":"2134",
    "addr:street":"Burwood Rd",
    "iso:country":"AU",
    "sg:address":"Suite 1, Level 1/ 41A Burwood Rd",
    "sg:city":"Burwood",
    "sg:classifiers":[
        {
            "category":"Banks & Credit Unions",
            "subcategory":"Bank",
            "type":"Services"
        }
    ],
    "sg:phone":"+61 2 9745 3166",
    "sg:postcode":"2134",
    "sg:province":"NSW",
    "sg:tags":[
        "broker",
        "mortgage"
    ],
    "wof:name":"Paradiso Investments Pty Ltd",
    "wof:placetype":"venue"
},
  "geometry": {"coordinates":[151.10409545900001,-33.8745117188],"type":"Point"}
}