{
  "type": "Feature",
  "properties": {
    "addr:full":"103 Bay Shore Ave Clifton Springs VIC 3222",
    "addr:housenumber":"103",
    "addr:postcode":"3222",
    "addr:street":"Bay Shore Ave",
    "iso:country":"AU",
    "sg:address":"103 Bay Shore Ave",
    "sg:city":"Clifton Springs",
    "sg:classifiers":[
        {
            "category":"Professional",
            "subcategory":"Art Services",
            "type":"Services"
        }
    ],
    "sg:phone":"+61 3 5253 1937",
    "sg:postcode":"3222",
    "sg:province":"VIC",
    "sg:tags":[
        "decorator",
        "painter"
    ],
    "wof:name":"J.B & S.K Sorensen",
    "wof:placetype":"venue"
},
  "geometry": {"coordinates":[144.56205700000001,-38.157421],"type":"Point"}
}