{
  "type": "Feature",
  "properties": {
    "addr:full":"32 Lyric St Aberfoyle Park SA 5159",
    "addr:housenumber":"32",
    "addr:postcode":"5159",
    "addr:street":"Lyric St",
    "iso:country":"AU",
    "sg:address":"32 Lyric St",
    "sg:city":"Aberfoyle Park",
    "sg:classifiers":[
        {
            "category":"Professional",
            "subcategory":"Art Services",
            "type":"Services"
        }
    ],
    "sg:phone":"+61 8 8270 7760",
    "sg:postcode":"5159",
    "sg:province":"SA",
    "sg:tags":[
        "graphic",
        "designer"
    ],
    "wof:name":"Pure Gold Design",
    "wof:placetype":"venue"
},
  "geometry": {"coordinates":[138.59971618599999,-35.0672645569],"type":"Point"}
}