{
  "type": "Feature",
  "properties": {
    "addr:full":"1/ 62 Annie St Rocklea QLD 4106",
    "addr:housenumber":"/ 62",
    "addr:postcode":"4106",
    "addr:street":"Annie St",
    "iso:country":"AU",
    "sg:address":"1/ 62 Annie St",
    "sg:city":"Rocklea",
    "sg:classifiers":[
        {
            "category":"Retail",
            "subcategory":"Auto Repair",
            "type":"Services"
        }
    ],
    "sg:phone":"+61 7 3373 8854",
    "sg:postcode":"4106",
    "sg:province":"QLD",
    "sg:tags":[
        "repairer",
        "motor",
        "engineer"
    ],
    "wof:name":"Comprehensive Automotive Repair & Services",
    "wof:placetype":"venue"
},
  "geometry": {"coordinates":[153.01559448200001,-27.5463352203],"type":"Point"}
}