{
  "type": "Feature",
  "properties": {
    "addr:full":"388 Burnley St Richmond VIC 3121",
    "addr:housenumber":"388",
    "addr:postcode":"3121",
    "addr:street":"Burnley St",
    "iso:country":"AU",
    "sg:address":"388 Burnley St",
    "sg:city":"Richmond",
    "sg:classifiers":[
        {
            "category":"Home & Garden",
            "subcategory":"Furniture",
            "type":"Retail Goods"
        }
    ],
    "sg:phone":"+61 3 9428 2914",
    "sg:postcode":"3121",
    "sg:province":"VIC",
    "sg:tags":[
        "repair",
        "restoration"
    ],
    "wof:name":"Daly Kieran Fine Furniture & Restoration",
    "wof:placetype":"venue"
},
  "geometry": {"coordinates":[145.00700378400001,-37.8257865906],"type":"Point"}
}