{
  "type": "Feature",
  "properties": {
    "addr:full":"Shop 5, 255 Forest Lake Blv Forest Lake QLD 4078",
    "addr:housenumber":"shop 5 255",
    "addr:postcode":"4078",
    "addr:street":"Forest Lake Blv",
    "iso:country":"AU",
    "sg:address":"Shop 5, 255",
    "sg:city":"Forest Lake Blv Forest Lake",
    "sg:classifiers":[
        {
            "category":"Health Services",
            "subcategory":"Dentist",
            "type":"Services"
        }
    ],
    "sg:phone":"+61 7 3879 7072",
    "sg:postcode":"4078",
    "sg:province":"QLD",
    "wof:name":"Forest Lake Dental",
    "wof:placetype":"venue"
},
  "geometry": {"coordinates":[152.96972656200001,-27.6259250641],"type":"Point"}
}