{
  "type": "Feature",
  "properties": {
    "iso:country":"AU",
    "sg:address":"1a 85 Commercial Rd",
    "sg:city":"Teneriffe",
    "sg:classifiers":[
        {
            "category":"Communications",
            "subcategory":"Film & Video Production",
            "type":"Services"
        }
    ],
    "sg:phone":"+61 7 3852 2242",
    "sg:postcode":"4005",
    "sg:province":"QLD",
    "sg:tags":[
        "fan",
        "blower"
    ],
    "wof:name":"IPMI",
    "wof:placetype":"venue"
},
  "geometry": {"coordinates":[153.04664611800001,-27.4542121887],"type":"Point"}
}