{
  "type": "Feature",
  "properties": {
    "addr:full":"27 Rushwood Drv Craigieburn VIC 3064",
    "addr:housenumber":"27",
    "addr:postcode":"3064",
    "addr:street":"Rushwood Drv",
    "iso:country":"AU",
    "sg:address":"27 Rushwood Drv",
    "sg:city":"Craigieburn",
    "sg:classifiers":[
        {
            "category":"Professional",
            "type":"Services"
        }
    ],
    "sg:phone":"+61 418 179 559",
    "sg:postcode":"3064",
    "sg:province":"VIC",
    "sg:tags":[
        "transport"
    ],
    "wof:name":"D Caelli Crane Trucks",
    "wof:placetype":"venue"
},
  "geometry": {"coordinates":[144.950805664,-37.6123313904],"type":"Point"}
}