{
  "type": "Feature",
  "properties": {
    "addr:full":"PO Box 64 Willetton WA 6955",
    "addr:postcode":"6955",
    "iso:country":"AU",
    "sg:address":"PO Box 64",
    "sg:city":"Willetton",
    "sg:classifiers":[
        {
            "category":"Shopping",
            "subcategory":"Beauty & Cosmetics",
            "type":"Retail Goods"
        }
    ],
    "sg:phone":"+61 8 9332 5905",
    "sg:postcode":"6955",
    "sg:province":"WA",
    "sg:tags":[
        "equipment",
        "salon",
        "supply"
    ],
    "wof:name":"Pronail Essentials",
    "wof:placetype":"venue"
},
  "geometry": {"coordinates":[115.881530762,-32.053150177],"type":"Point"}
}