{
  "type": "Feature",
  "properties": {
    "iso:country":"AU",
    "sg:address":"30 Beatty St",
    "sg:city":"Balgowlah Heights",
    "sg:classifiers":[
        {
            "category":"Real Estate",
            "subcategory":"Real Estate Agent",
            "type":"Services"
        }
    ],
    "sg:phone":"+61 2 9948 1234",
    "sg:postcode":"2093",
    "sg:province":"NSW",
    "wof:name":"Andersen-Wright Real Estate",
    "wof:placetype":"venue"
},
  "geometry": {"coordinates":[151.26922607399999,-33.8034362793],"type":"Point"}
}