{
  "type": "Feature",
  "properties": {
    "addr:full":"2 Apia Pl Lethbridge Park NSW 2770",
    "addr:housenumber":"2",
    "addr:postcode":"2770",
    "addr:street":"Apia Pl Lethbridge Park",
    "iso:country":"AU",
    "sg:address":"2 Apia Pl",
    "sg:city":"Lethbridge Park",
    "sg:classifiers":[
        {
            "category":"Food & Beverages",
            "subcategory":"Supermarket",
            "type":"Retail Goods"
        }
    ],
    "sg:phone":"+61 2 9628 6185",
    "sg:postcode":"2770",
    "sg:province":"NSW",
    "sg:tags":[
        "grocery",
        "store"
    ],
    "wof:name":"M.F.C. Food Stores",
    "wof:placetype":"venue"
},
  "geometry": {"coordinates":[150.79826355,-33.7373046875],"type":"Point"}
}