{
  "type": "Feature",
  "properties": {
    "iso:country":"AU",
    "sg:address":"1428 High St",
    "sg:city":"Malvern",
    "sg:classifiers":[
        {
            "category":"Shopping",
            "subcategory":"Clothing, Apparel, & Fashions",
            "type":"Retail Goods"
        }
    ],
    "sg:phone":"+61 3 9509 6263",
    "sg:postcode":"3144",
    "sg:province":"VIC",
    "sg:tags":[
        "recycled",
        "clothing"
    ],
    "wof:name":"Arthritis Foundation Of Victoria Inc",
    "wof:placetype":"venue"
},
  "geometry": {"coordinates":[145.04087829599999,-37.8582344055],"type":"Point"}
}