{
  "type": "Feature",
  "properties": {
    "iso:country":"AU",
    "sg:address":"22 Buranda Rd",
    "sg:city":"Clear Mountain",
    "sg:classifiers":[
        {
            "category":"Building & Trades",
            "subcategory":"Construction",
            "type":"Services"
        }
    ],
    "sg:phone":"+61 7 3325 1595",
    "sg:postcode":"4500",
    "sg:province":"QLD",
    "sg:tags":[
        "contractor"
    ],
    "wof:name":"N J Properties Pty Ltd",
    "wof:placetype":"venue"
},
  "geometry": {"coordinates":[152.899932861,-27.326210022],"type":"Point"}
}