{
  "type": "Feature",
  "properties": {
    "addr:full":"PO Box 19 South Strathfield NSW 2136",
    "addr:postcode":"2136",
    "addr:street":"South",
    "iso:country":"AU",
    "sg:address":"PO Box 19",
    "sg:city":"South Strathfield",
    "sg:classifiers":[
        {
            "category":"Professional",
            "subcategory":"Art Services",
            "type":"Services"
        }
    ],
    "sg:phone":"+61 417 210 333",
    "sg:postcode":"2136",
    "sg:province":"NSW",
    "sg:tags":[
        "decorator",
        "painter"
    ],
    "wof:name":"Haus Services",
    "wof:placetype":"venue"
},
  "geometry": {"coordinates":[151.08720398,-33.8964614868],"type":"Point"}
}