{
  "type": "Feature",
  "properties": {
    "addr:full":"2 Sheppards La Chirnside Park VIC 3116",
    "addr:housenumber":"2",
    "addr:postcode":"3116",
    "addr:street":"Sheppards La",
    "iso:country":"AU",
    "sg:address":"2 Sheppards La",
    "sg:city":"Chirnside Park",
    "sg:classifiers":[
        {
            "category":"Education",
            "subcategory":"Music School",
            "type":"Public Place"
        }
    ],
    "sg:phone":"+61 3 9727 1707",
    "sg:postcode":"3116",
    "sg:province":"VIC",
    "sg:tags":[
        "teacher"
    ],
    "wof:name":"Realm Music",
    "wof:placetype":"venue"
},
  "geometry": {"coordinates":[145.32095336899999,-37.758556366],"type":"Point"}
}