{
  "type": "Feature",
  "properties": {
    "iso:country":"AU",
    "sg:address":"28 Hillview Rd",
    "sg:city":"Eastwood",
    "sg:classifiers":[
        {
            "category":"Education",
            "subcategory":"School",
            "type":"Public Place"
        }
    ],
    "sg:phone":"+61 2 9874 3315",
    "sg:postcode":"2122",
    "sg:province":"NSW",
    "wof:name":"St Kevin's Primary School",
    "wof:placetype":"venue"
},
  "geometry": {"coordinates":[151.07835388199999,-33.78956604],"type":"Point"}
}