{
  "type": "Feature",
  "properties": {
    "addr:full":"Unit 2, 5- 7 Hinkler St Tamworth NSW 2340",
    "addr:housenumber":"5 7",
    "addr:postcode":"2340",
    "addr:street":"Hinkler St",
    "iso:country":"AU",
    "sg:address":"Unit 2, 5- 7 Hinkler St",
    "sg:city":"Tamworth",
    "sg:classifiers":[
        {
            "category":"Professional",
            "subcategory":"Employment Agencies",
            "type":"Services"
        }
    ],
    "sg:phone":"+61 2 6762 2452",
    "sg:postcode":"2340",
    "sg:province":"NSW",
    "sg:tags":[
        "entertainer",
        "agent"
    ],
    "wof:name":"Muscapro Music Production Hire & Sales",
    "wof:placetype":"venue"
},
  "geometry": {"coordinates":[150.903686523,-31.0964756012],"type":"Point"}
}