{
  "type": "Feature",
  "properties": {
    "addr:full":"9 Bevan St Albert Park VIC 3206",
    "addr:housenumber":"9",
    "addr:postcode":"3206",
    "addr:street":"Bevan St",
    "iso:country":"AU",
    "sg:address":"9 Bevan St",
    "sg:city":"Albert Park",
    "sg:classifiers":[
        {
            "category":"Building & Trades",
            "subcategory":"Construction",
            "type":"Services"
        }
    ],
    "sg:phone":"+61 3 9696 3881",
    "sg:postcode":"3206",
    "sg:province":"VIC",
    "sg:tags":[
        "window",
        "tinting"
    ],
    "wof:name":"Solarx Pty Ltd",
    "wof:placetype":"venue"
},
  "geometry": {"coordinates":[144.95739699999999,-37.839661],"type":"Point"}
}