{
  "type": "Feature",
  "properties": {
    "addr:full":"17 William St Granville NSW 2142",
    "addr:housenumber":"17",
    "addr:postcode":"2142",
    "addr:street":"William St",
    "iso:country":"AU",
    "sg:address":"17 William St",
    "sg:city":"Granville",
    "sg:classifiers":[
        {
            "category":"Personal",
            "subcategory":"Massage",
            "type":"Services"
        }
    ],
    "sg:phone":"+61 2 9682 1342",
    "sg:postcode":"2142",
    "sg:province":"NSW",
    "sg:tags":[
        "therapy"
    ],
    "wof:name":"Olson Therese",
    "wof:placetype":"venue"
},
  "geometry": {"coordinates":[151.015090942,-33.8364562988],"type":"Point"}
}