{
  "type": "Feature",
  "properties": {
    "iso:country":"AU",
    "sg:address":"PO Box 332",
    "sg:city":"Ascot Vale",
    "sg:classifiers":[
        {
            "category":"Building & Trades",
            "subcategory":"Construction",
            "type":"Services"
        }
    ],
    "sg:phone":"+61 402 479 570",
    "sg:postcode":"3032",
    "sg:province":"VIC",
    "sg:tags":[
        "roof"
    ],
    "wof:name":"Metal Roofing Professionals",
    "wof:placetype":"venue"
},
  "geometry": {"coordinates":[144.91554300000001,-37.7756],"type":"Point"}
}