{
  "type": "Feature",
  "properties": {
    "addr:full":"117 Rakow St Broken Hill NSW 2880",
    "addr:housenumber":"117",
    "addr:postcode":"2880",
    "addr:street":"Rakow St",
    "iso:country":"AU",
    "sg:address":"117 Rakow St",
    "sg:city":"Broken Hill",
    "sg:classifiers":[
        {
            "category":"Commercial Area",
            "type":"Public Place"
        }
    ],
    "sg:phone":"+61 8 8088 2666",
    "sg:postcode":"2880",
    "sg:province":"NSW",
    "sg:tags":[
        "heavy",
        "carrier"
    ],
    "wof:name":"Attard's Transport Service Pty Ltd",
    "wof:placetype":"venue"
},
  "geometry": {"coordinates":[141.442260742,-31.9588432312],"type":"Point"}
}