{
  "type": "Feature",
  "properties": {
    "addr:full":"41 Malcomson St Mackay QLD 4740",
    "addr:housenumber":"41",
    "addr:postcode":"4740",
    "addr:street":"Malcomson St",
    "iso:country":"AU",
    "sg:address":"41 Malcomson St",
    "sg:city":"Mackay",
    "sg:phone":"+61 7 4940 0733",
    "sg:postcode":"4740",
    "sg:province":"QLD",
    "wof:name":"Mackay Garden Sheds",
    "wof:placetype":"venue"
},
  "geometry": {"coordinates":[149.17065400000001,-21.122244],"type":"Point"}
}