{
  "type": "Feature",
  "properties": {
    "addr:full":"96 Main St Bairnsdale VIC 3875",
    "addr:housenumber":"96",
    "addr:postcode":"3875",
    "addr:street":"Main St",
    "iso:country":"AU",
    "sg:address":"96 Main St",
    "sg:city":"Bairnsdale",
    "sg:classifiers":[
        {
            "category":"Food & Beverages",
            "subcategory":"Liquor & Beverages",
            "type":"Retail Goods"
        }
    ],
    "sg:phone":"+61 3 5152 2021",
    "sg:postcode":"3875",
    "sg:province":"VIC",
    "sg:tags":[
        "store"
    ],
    "wof:name":"Liquorland Pty Ltd",
    "wof:placetype":"venue"
},
  "geometry": {"coordinates":[147.827224731,-37.7086296082],"type":"Point"}
}