{
  "type": "Feature",
  "properties": {
    "iso:country":"AU",
    "sg:address":"Suite 3,172- 176 Rowe St",
    "sg:city":"Eastwood",
    "sg:classifiers":[
        {
            "category":"Personal",
            "subcategory":"Hair Removal",
            "type":"Services"
        }
    ],
    "sg:phone":"+61 2 9874 0171",
    "sg:postcode":"2122",
    "sg:province":"NSW",
    "sg:tags":[
        "ornament"
    ],
    "wof:name":"Pritti Design Company",
    "wof:placetype":"venue"
},
  "geometry": {"coordinates":[151.08105468799999,-33.7917366028],"type":"Point"}
}