{
  "type": "Feature",
  "properties": {
    "addr:full":"15 Tarlington Pl Smithfield NSW 2164",
    "addr:housenumber":"15",
    "addr:postcode":"2164",
    "addr:street":"Tarlington Pl",
    "iso:country":"AU",
    "sg:address":"15 Tarlington Pl",
    "sg:city":"Smithfield",
    "sg:classifiers":[
        {
            "category":"Building & Trades",
            "subcategory":"Cleaning & Sanitation",
            "type":"Services"
        }
    ],
    "sg:phone":"+61 2 9725 4433",
    "sg:postcode":"2164",
    "sg:province":"NSW",
    "sg:tags":[
        "duct"
    ],
    "wof:name":"Commercial Duct Cleaning Services",
    "wof:placetype":"venue"
},
  "geometry": {"coordinates":[150.925949097,-33.834980011],"type":"Point"}
}