{
  "type": "Feature",
  "properties": {
    "addr:full":"Cnr Freeman&#039;s Reach Rd & Errick&#039;s Lane, Freemans Reach NSW 2756",
    "addr:postcode":"2756",
    "addr:street":"Cnr;S Reach Rd &;S Lane",
    "iso:country":"AU",
    "sg:address":"Cnr Freeman&#039;s Reach Rd",
    "sg:city":"& Errick&#039;s Lane, Freemans Reach",
    "sg:classifiers":[
        {
            "category":"Home & Garden",
            "subcategory":"Garden Supply",
            "type":"Retail Goods"
        }
    ],
    "sg:phone":"+61 1800 796 173",
    "sg:postcode":"2756",
    "sg:province":"NSW",
    "sg:tags":[
        "turf",
        "lawn"
    ],
    "wof:name":"Bills Turf Supplies",
    "wof:placetype":"venue"
},
  "geometry": {"coordinates":[150.793792725,-33.5723762512],"type":"Point"}
}