{
  "type": "Feature",
  "properties": {
    "iso:country":"AU",
    "sg:address":"26 Walker St",
    "sg:city":"Dalyston",
    "sg:classifiers":[
        {
            "category":"Building & Trades",
            "subcategory":"Plumbing",
            "type":"Services"
        }
    ],
    "sg:phone":"+61 419 361 765",
    "sg:postcode":"3992",
    "sg:province":"VIC",
    "sg:tags":[
        "plumber",
        "gasfitters"
    ],
    "wof:name":"Williams Mathew",
    "wof:placetype":"venue"
},
  "geometry": {"coordinates":[145.546799,-38.565609],"type":"Point"}
}