{
  "type": "Feature",
  "properties": {
    "addr:full":"PO Box 129 Warilla NSW 2528",
    "addr:postcode":"2528",
    "iso:country":"AU",
    "sg:address":"PO Box 129",
    "sg:city":"Warilla",
    "sg:classifiers":[
        {
            "category":"Professional",
            "subcategory":"Engineering",
            "type":"Services"
        }
    ],
    "sg:phone":"+61 411 372 173",
    "sg:postcode":"2528",
    "sg:province":"NSW",
    "sg:tags":[
        "electrical",
        "engineer"
    ],
    "wof:name":"Electrical Engineering & Drafting Pty Ltd",
    "wof:placetype":"venue"
},
  "geometry": {"coordinates":[150.86082458499999,-34.5493812561],"type":"Point"}
}