{
  "type": "Feature",
  "properties": {
    "addr:full":"1, 32 Robinson Ave Belmont WA 6104",
    "addr:housenumber":"32",
    "addr:postcode":"6104",
    "addr:street":"1;Robinson Ave",
    "iso:country":"AU",
    "sg:address":"1, 32 Robinson Ave",
    "sg:city":"Belmont",
    "sg:classifiers":[
        {
            "category":"Military Area",
            "subcategory":"Air Force Base",
            "type":"Public Place"
        }
    ],
    "sg:phone":"+61 8 6253 2200",
    "sg:postcode":"6104",
    "sg:province":"WA",
    "sg:tags":[
        "fibre",
        "optic"
    ],
    "wof:name":"AFC Group Pty Ltd",
    "wof:placetype":"venue"
},
  "geometry": {"coordinates":[115.922607422,-31.9538116455],"type":"Point"}
}