{
  "type": "Feature",
  "properties": {
    "iso:country":"AU",
    "sg:address":"Lot 174a Paschendale Ave",
    "sg:city":"Yelta",
    "sg:classifiers":[
        {
            "category":"Retail",
            "subcategory":"Auto Repair",
            "type":"Services"
        }
    ],
    "sg:phone":"+61 3 5025 3003",
    "sg:postcode":"3505",
    "sg:province":"VIC",
    "sg:tags":[
        "car",
        "restoration",
        "supply"
    ],
    "wof:name":"Quick's Mechanical Repairs",
    "wof:placetype":"venue"
},
  "geometry": {"coordinates":[142.01760864299999,-34.1283226013],"type":"Point"}
}