{
  "type": "Feature",
  "properties": {
    "addr:full":"10 Aldershot Rd Langwarrin VIC 3910",
    "addr:housenumber":"10",
    "addr:postcode":"3910",
    "addr:street":"Aldershot Rd",
    "iso:country":"AU",
    "sg:address":"10 Aldershot Rd",
    "sg:city":"Langwarrin",
    "sg:classifiers":[
        {
            "category":"Government",
            "subcategory":"City Hall",
            "type":"Public Place"
        }
    ],
    "sg:phone":"+61 3 9789 1954",
    "sg:postcode":"3910",
    "sg:province":"VIC",
    "wof:name":"Club 27 Incorporated",
    "wof:placetype":"venue"
},
  "geometry": {"coordinates":[145.182296753,-38.1655426025],"type":"Point"}
}