{
  "type": "Feature",
  "properties": {
    "addr:full":"358 Quinzeh Creek Rd Logan Village QLD 4207",
    "addr:housenumber":"358",
    "addr:postcode":"4207",
    "addr:street":"Quinzeh Creek Rd",
    "iso:country":"AU",
    "sg:address":"358 Quinzeh Creek Rd",
    "sg:city":"Logan Village",
    "sg:classifiers":[
        {
            "category":"Manufacturing",
            "subcategory":"Motor Vehicles & Parts",
            "type":"Manufacturing & Wholesale Goods"
        }
    ],
    "sg:phone":"+61 7 5547 0204",
    "sg:postcode":"4207",
    "sg:province":"QLD",
    "sg:tags":[
        "replacement"
    ],
    "wof:name":"Top Gun",
    "wof:placetype":"venue"
},
  "geometry": {"coordinates":[153.13044738799999,-27.7812232971],"type":"Point"}
}