{
  "type": "Feature",
  "properties": {
    "iso:country":"AU",
    "sg:address":"42/ 48 Plunkett St",
    "sg:city":"Drummoyne",
    "sg:classifiers":[
        {
            "category":"Professional",
            "subcategory":"Printing & Photocopies",
            "type":"Services"
        }
    ],
    "sg:phone":"+61 411 399 444",
    "sg:postcode":"2047",
    "sg:province":"NSW",
    "sg:tags":[
        "publishing",
        "desktop"
    ],
    "wof:name":"Anthi Prieston Creative",
    "wof:placetype":"venue"
},
  "geometry": {"coordinates":[151.149689,-33.857422],"type":"Point"}
}