{
  "type": "Feature",
  "properties": {
    "addr:full":"1205 Princes Hwy Mt Moriac VIC 3240",
    "addr:housenumber":"1205",
    "addr:postcode":"3240",
    "addr:street":"Princes Hwy Mt Moriac",
    "iso:country":"AU",
    "sg:address":"1205 Princes Hwy",
    "sg:city":"Mt Moriac",
    "sg:classifiers":[
        {
            "category":"Building & Trades",
            "subcategory":"Construction",
            "type":"Services"
        }
    ],
    "sg:phone":"+61 3 5266 1239",
    "sg:postcode":"3240",
    "sg:province":"VIC",
    "sg:tags":[
        "polishing",
        "sanding",
        "floor"
    ],
    "wof:name":"Eastern Floor Service",
    "wof:placetype":"venue"
},
  "geometry": {"coordinates":[144.15858459500001,-38.2135314941],"type":"Point"}
}