{
  "type": "Feature",
  "properties": {
    "iso:country":"AU",
    "sg:address":"50a Marlborough St",
    "sg:city":"Smithfield",
    "sg:classifiers":[
        {
            "category":"Social Services",
            "subcategory":"Child Care",
            "type":"Services"
        }
    ],
    "sg:phone":"+61 2 9726 2173",
    "sg:postcode":"2164",
    "sg:province":"NSW",
    "wof:name":"Fairfield City Council",
    "wof:placetype":"venue"
},
  "geometry": {"coordinates":[150.94578552199999,-33.8603630066],"type":"Point"}
}