{
  "type": "Feature",
  "properties": {
    "iso:country":"AU",
    "sg:address":"10 Sydenham Rd",
    "sg:city":"Brookvale",
    "sg:classifiers":[
        {
            "category":"Professional",
            "type":"Services"
        }
    ],
    "sg:phone":"+61 2 9938 5166",
    "sg:postcode":"2100",
    "sg:province":"NSW",
    "sg:tags":[
        "packaging",
        "filling",
        "assembling"
    ],
    "sg:website":"http://www.totalpackage.com.au",
    "wof:name":"Total Package",
    "wof:placetype":"venue"
},
  "geometry": {"coordinates":[151.272705078,-33.764377594],"type":"Point"}
}