{
  "type": "Feature",
  "properties": {
    "addr:full":"149 Ashbrook Ave Trinity Gardens SA 5068",
    "addr:housenumber":"149",
    "addr:postcode":"5068",
    "addr:street":"Ashbrook Ave Trinity Gardens",
    "iso:country":"AU",
    "sg:address":"149 Ashbrook Ave",
    "sg:city":"Trinity Gardens",
    "sg:classifiers":[
        {
            "category":"Professional",
            "subcategory":"Detective & Security Services",
            "type":"Services"
        }
    ],
    "sg:phone":"+61 8 8332 9227",
    "sg:postcode":"5068",
    "sg:province":"SA",
    "sg:tags":[
        "consultant",
        "system"
    ],
    "wof:name":"M & M Electrical",
    "wof:placetype":"venue"
},
  "geometry": {"coordinates":[138.646118164,-34.913646698],"type":"Point"}
}