{
  "type": "Feature",
  "properties": {
    "addr:full":"85 Sungold Rd Chambers Flat QLD 4133",
    "addr:housenumber":"85",
    "addr:postcode":"4133",
    "addr:street":"Sungold Rd",
    "iso:country":"AU",
    "sg:address":"85 Sungold Rd",
    "sg:city":"Chambers Flat",
    "sg:classifiers":[
        {
            "category":"Professional",
            "subcategory":"Computer Services",
            "type":"Services"
        }
    ],
    "sg:phone":"+61 7 3802 1342",
    "sg:postcode":"4133",
    "sg:province":"QLD",
    "sg:tags":[
        "consultant",
        "system"
    ],
    "wof:name":"Sungold Consulting Pty Ltd",
    "wof:placetype":"venue"
},
  "geometry": {"coordinates":[153.07844543499999,-27.7325134277],"type":"Point"}
}