{
  "type": "Feature",
  "properties": {
    "addr:full":"Throselle St Collie WA 6225",
    "addr:postcode":"6225",
    "addr:street":"St",
    "iso:country":"AU",
    "sg:address":"Throselle St",
    "sg:city":"Collie",
    "sg:classifiers":[
        {
            "category":"Retail",
            "subcategory":"Auto Rental",
            "type":"Services"
        }
    ],
    "sg:phone":"+61 8 9721 7988",
    "sg:postcode":"6225",
    "sg:province":"WA",
    "sg:tags":[
        "car",
        "hire",
        "minibus"
    ],
    "wof:name":"Avis",
    "wof:placetype":"venue"
},
  "geometry": {"coordinates":[116.15522,-33.360744],"type":"Point"}
}