{
  "type": "Feature",
  "properties": {
    "addr:full":"242 Tooronga Rd Tooronga VIC 3146",
    "addr:housenumber":"242",
    "addr:postcode":"3146",
    "addr:street":"Tooronga Rd",
    "iso:country":"AU",
    "sg:address":"242 Tooronga Rd",
    "sg:city":"Tooronga",
    "sg:classifiers":[
        {
            "category":"Professional",
            "subcategory":"Art Services",
            "type":"Services"
        }
    ],
    "sg:phone":"+61 3 9822 3137",
    "sg:postcode":"3146",
    "sg:province":"VIC",
    "sg:tags":[
        "artist"
    ],
    "wof:name":"Verstraeten, Marylyn",
    "wof:placetype":"venue"
},
  "geometry": {"coordinates":[145.04171752900001,-37.8562736511],"type":"Point"}
}