{
  "type": "Feature",
  "properties": {
    "addr:full":"6/ 33 Fairlight Crs Fairlight NSW 2094",
    "addr:housenumber":"/ 33",
    "addr:postcode":"2094",
    "addr:street":"Fairlight Crs",
    "iso:country":"AU",
    "sg:address":"6/ 33 Fairlight Crs",
    "sg:city":"Fairlight",
    "sg:classifiers":[
        {
            "category":"Arena",
            "subcategory":"Indoor Arena",
            "type":"Entertainment"
        }
    ],
    "sg:phone":"+61 417 994 803",
    "sg:postcode":"2094",
    "sg:province":"NSW",
    "sg:tags":[
        "modelmakers"
    ],
    "wof:name":"Jonathan Westley",
    "wof:placetype":"venue"
},
  "geometry": {"coordinates":[151.27468872099999,-33.7970542908],"type":"Point"}
}