{
  "type": "Feature",
  "properties": {
    "addr:full":"11 Latona Ave Knoxfield VIC 3180",
    "addr:housenumber":"11",
    "addr:postcode":"3180",
    "addr:street":"Latona Ave",
    "iso:country":"AU",
    "sg:address":"11 Latona Ave",
    "sg:city":"Knoxfield",
    "sg:classifiers":[
        {
            "category":"Professional",
            "subcategory":"Art Services",
            "type":"Services"
        }
    ],
    "sg:phone":"+61 3 9763 3116",
    "sg:postcode":"3180",
    "sg:province":"VIC",
    "sg:tags":[
        "interior",
        "decorator"
    ],
    "wof:name":"Ian Wood Managed Interiors",
    "wof:placetype":"venue"
},
  "geometry": {"coordinates":[145.24230957,-37.8921813965],"type":"Point"}
}