{
  "type": "Feature",
  "properties": {
    "iso:country":"AU",
    "sg:address":"Cnr Victoria & Carey St",
    "sg:city":"Bunbury",
    "sg:classifiers":[
        {
            "category":"Building & Trades",
            "subcategory":"Landscaping Services",
            "type":"Services"
        }
    ],
    "sg:phone":"+61 8 9791 4591",
    "sg:postcode":"6230",
    "sg:province":"WA",
    "sg:tags":[
        "market"
    ],
    "wof:name":"Harbour City Markets",
    "wof:placetype":"venue"
},
  "geometry": {"coordinates":[115.637032,-33.326599],"type":"Point"}
}