{
  "type": "Feature",
  "properties": {
    "iso:country":"AU",
    "sg:address":"Lindsay Rd",
    "sg:city":"Buderim",
    "sg:classifiers":[
        {
            "category":"Professional",
            "subcategory":"Accounting & Tax Preparation",
            "type":"Services"
        }
    ],
    "sg:phone":"+61 7 5456 1650",
    "sg:postcode":"4556",
    "sg:province":"QLD",
    "sg:tags":[
        "accountant",
        "auditor"
    ],
    "wof:name":"James McKean & Associates",
    "wof:placetype":"venue"
},
  "geometry": {"coordinates":[153.050506592,-26.6847934723],"type":"Point"}
}