{
  "type": "Feature",
  "properties": {
    "addr:full":"Cnr Commercial & Driffield Rds Morwell VIC 3840",
    "addr:postcode":"3840",
    "iso:country":"AU",
    "sg:address":"Cnr Commercial & Driffield Rds",
    "sg:city":"Morwell",
    "sg:classifiers":[
        {
            "category":"Home & Garden",
            "subcategory":"Building Materials",
            "type":"Retail Goods"
        }
    ],
    "sg:phone":"+61 3 5134 1555",
    "sg:postcode":"3840",
    "sg:province":"VIC",
    "sg:tags":[
        "lawn",
        "cutting",
        "maintenance"
    ],
    "wof:name":"Gippsland Grounds Maintenance",
    "wof:placetype":"venue"
},
  "geometry": {"coordinates":[146.38438415499999,-38.2365112305],"type":"Point"}
}