{
  "type": "Feature",
  "properties": {
    "iso:country":"AU",
    "sg:address":"121 Bell St",
    "sg:city":"Preston",
    "sg:classifiers":[
        {
            "category":"Home & Garden",
            "subcategory":"Carpets & Floor Coverings",
            "type":"Retail Goods"
        }
    ],
    "sg:phone":"+61 3 9269 3307",
    "sg:postcode":"3072",
    "sg:province":"VIC",
    "sg:tags":[
        "wood"
    ],
    "wof:name":"Harvey Norman Flooring",
    "wof:placetype":"venue"
},
  "geometry": {"coordinates":[145.01808166500001,-37.7470397949],"type":"Point"}
}