{
  "type": "Feature",
  "properties": {
    "addr:full":"Block U Shed 1 Brisbane Markets Rocklea QLD 4106",
    "addr:housenumber":"1",
    "addr:postcode":"4106",
    "iso:country":"AU",
    "sg:address":"Block U Shed 1 Brisbane Markets",
    "sg:city":"Rocklea",
    "sg:classifiers":[
        {
            "category":"Food & Beverages",
            "subcategory":"Fruits & Vegetables",
            "type":"Retail Goods"
        }
    ],
    "sg:phone":"+61 7 3278 2240",
    "sg:postcode":"4106",
    "sg:province":"QLD",
    "sg:tags":[
        "wholesale"
    ],
    "wof:name":"G.M.N/Vegie Prepi",
    "wof:placetype":"venue"
},
  "geometry": {"coordinates":[153.029663086,-27.5011062622],"type":"Point"}
}