{
  "type": "Feature",
  "properties": {
    "iso:country":"AU",
    "sg:address":"Crowne Plaza Hotel 1 Binara St",
    "sg:city":"Canberra",
    "sg:classifiers":[
        {
            "category":"Sports & Exercise",
            "subcategory":"Gym",
            "type":"Entertainment"
        }
    ],
    "sg:phone":"+61 2 6274 5595",
    "sg:postcode":"2600",
    "sg:province":"ACT",
    "sg:tags":[
        "health",
        "fitness"
    ],
    "wof:name":"Glebe Park Health Club",
    "wof:placetype":"venue"
},
  "geometry": {"coordinates":[149.13491821299999,-35.2821617126],"type":"Point"}
}