{
  "type": "Feature",
  "properties": {
    "addr:full":"Suite 3.1 9 Bowman St South Perth WA 6151",
    "addr:housenumber":"3.1 9",
    "addr:postcode":"6151",
    "addr:street":"Bowman St South",
    "iso:country":"AU",
    "sg:address":"Suite 3.1 9 Bowman St",
    "sg:city":"South Perth",
    "sg:classifiers":[
        {
            "category":"Food & Beverages",
            "subcategory":"Meat & Fish",
            "type":"Retail Goods"
        }
    ],
    "sg:phone":"+61 8 9368 5633",
    "sg:postcode":"6151",
    "sg:province":"WA",
    "sg:tags":[
        "aquaculture"
    ],
    "wof:name":"Cape SeaFarms Pty Ltd",
    "wof:placetype":"venue"
},
  "geometry": {"coordinates":[115.849113,-31.973969],"type":"Point"}
}