{
  "type": "Feature",
  "properties": {
    "addr:full":"9 Talus St Naremburn NSW 2065",
    "addr:housenumber":"9",
    "addr:postcode":"2065",
    "addr:street":"Talus St",
    "iso:country":"AU",
    "sg:address":"9 Talus St",
    "sg:city":"Naremburn",
    "sg:classifiers":[
        {
            "category":"Social Services",
            "subcategory":"Child Care",
            "type":"Services"
        }
    ],
    "sg:phone":"+61 2 9436 3747",
    "sg:postcode":"2065",
    "sg:province":"NSW",
    "wof:name":"Berry Cottage Childcare",
    "wof:placetype":"venue"
},
  "geometry": {"coordinates":[151.195236206,-33.8182449341],"type":"Point"}
}