{
  "type": "Feature",
  "properties": {
    "addr:full":"8 Westbrook St Woody Point QLD 4019",
    "addr:housenumber":"8",
    "addr:postcode":"4019",
    "addr:street":"Westbrook St",
    "iso:country":"AU",
    "sg:address":"8 Westbrook St",
    "sg:city":"Woody Point",
    "sg:classifiers":[
        {
            "category":"Landmark",
            "subcategory":"Square",
            "type":"Public Place"
        }
    ],
    "sg:phone":"+61 7 3284 4057",
    "sg:postcode":"4019",
    "sg:province":"QLD",
    "sg:tags":[
        "lampshade"
    ],
    "wof:name":"Lampshades by Design",
    "wof:placetype":"venue"
},
  "geometry": {"coordinates":[153.104370117,-27.2531986237],"type":"Point"}
}