{
  "type": "Feature",
  "properties": {
    "addr:full":"2 Surf St Kingscliff NSW 2487",
    "addr:housenumber":"2",
    "addr:postcode":"2487",
    "addr:street":"Surf St",
    "iso:country":"AU",
    "sg:address":"2 Surf St",
    "sg:city":"Kingscliff",
    "sg:classifiers":[
        {
            "category":"Building & Trades",
            "subcategory":"Construction",
            "type":"Services"
        }
    ],
    "sg:phone":"+61 2 6674 3999",
    "sg:postcode":"2487",
    "sg:province":"NSW",
    "sg:tags":[
        "earth",
        "excavating",
        "moving",
        "contractor"
    ],
    "wof:name":"Bourkes Bobcat Hire",
    "wof:placetype":"venue"
},
  "geometry": {"coordinates":[153.56692504899999,-28.243183136],"type":"Point"}
}