{
  "type": "Feature",
  "properties": {
    "iso:country":"AU",
    "sg:address":"Wilson St",
    "sg:city":"South Lismore",
    "sg:classifiers":[
        {
            "category":"Education",
            "subcategory":"School",
            "type":"Public Place"
        }
    ],
    "sg:phone":"+61 2 6621 3433",
    "sg:postcode":"2480",
    "sg:province":"NSW",
    "sg:tags":[
        "state",
        "-",
        "nsw"
    ],
    "wof:name":"Lismore South Public School",
    "wof:placetype":"venue"
},
  "geometry": {"coordinates":[153.260894775,-28.8120002747],"type":"Point"}
}