{
  "type": "Feature",
  "properties": {
    "addr:full":"214 Aqueduct Rd St Helena VIC 3088",
    "addr:housenumber":"214",
    "addr:postcode":"3088",
    "addr:street":"Aqueduct Rd",
    "iso:country":"AU",
    "sg:address":"214 Aqueduct Rd",
    "sg:city":"St Helena",
    "sg:classifiers":[
        {
            "category":"Deli",
            "type":"Food & Drink"
        }
    ],
    "sg:phone":"+61 3 9438 6899",
    "sg:postcode":"3088",
    "sg:province":"VIC",
    "sg:tags":[
        "delicatessen"
    ],
    "wof:name":"Delicut Deli",
    "wof:placetype":"venue"
},
  "geometry": {"coordinates":[145.13676452600001,-37.6853713989],"type":"Point"}
}