{
  "type": "Feature",
  "properties": {
    "iso:country":"AU",
    "sg:address":"1/241- 271 Pt Nepean Rd",
    "sg:city":"Dromana",
    "sg:classifiers":[
        {
            "category":"Health Services",
            "subcategory":"Doctor",
            "type":"Services"
        }
    ],
    "sg:phone":"+61 3 5981 4300",
    "sg:postcode":"3936",
    "sg:province":"VIC",
    "sg:tags":[
        "medical",
        "practitioner"
    ],
    "wof:name":"Deravin G. Dr",
    "wof:placetype":"venue"
},
  "geometry": {"coordinates":[144.96388244600001,-38.3333129883],"type":"Point"}
}