{
  "type": "Feature",
  "properties": {
    "addr:full":"Level 4 33 Argyle St Parramatta NSW 2150",
    "addr:housenumber":"33",
    "addr:postcode":"2150",
    "addr:street":"Argyle St",
    "iso:country":"AU",
    "sg:address":"Level 4 33 Argyle St",
    "sg:city":"Parramatta",
    "sg:classifiers":[
        {
            "category":"Insurance",
            "subcategory":"Insurance Agent",
            "type":"Services"
        }
    ],
    "sg:phone":"+61 412 442 606",
    "sg:postcode":"2150",
    "sg:province":"NSW",
    "wof:name":"Stephen G Allan Pty Ltd",
    "wof:placetype":"venue"
},
  "geometry": {"coordinates":[151.077850342,-33.9574432373],"type":"Point"}
}