{
  "type": "Feature",
  "properties": {
    "iso:country":"AU",
    "sg:address":"20 Roberts Ave",
    "sg:city":"Balaklava",
    "sg:classifiers":[
        {
            "category":"Shopping",
            "type":"Retail Goods"
        }
    ],
    "sg:phone":"+61 8 8862 1572",
    "sg:postcode":"5461",
    "sg:province":"SA",
    "sg:tags":[
        "agent",
        "stock"
    ],
    "wof:name":"Butterfield Agencies",
    "wof:placetype":"venue"
},
  "geometry": {"coordinates":[138.421799,-34.153484],"type":"Point"}
}