{
  "type": "Feature",
  "properties": {
    "iso:country":"AU",
    "sg:address":"3/ 25 Snook St",
    "sg:city":"Clontarf",
    "sg:classifiers":[
        {
            "category":"Retail",
            "subcategory":"Auto Repair",
            "type":"Services"
        }
    ],
    "sg:phone":"+61 7 3283 4300",
    "sg:postcode":"4019",
    "sg:province":"QLD",
    "sg:tags":[
        "car",
        "restoration",
        "supply"
    ],
    "wof:name":"Custom Roadsters",
    "wof:placetype":"venue"
},
  "geometry": {"coordinates":[153.08265685999999,-27.2458763123],"type":"Point"}
}