{
  "type": "Feature",
  "properties": {
    "addr:full":"23 Moss St Slacks Creek QLD 4127",
    "addr:housenumber":"23",
    "addr:postcode":"4127",
    "addr:street":"Moss St",
    "iso:country":"AU",
    "sg:address":"23 Moss St",
    "sg:city":"Slacks Creek",
    "sg:classifiers":[
        {
            "category":"Fast Food",
            "type":"Food & Drink"
        }
    ],
    "sg:phone":"+61 7 3208 1466",
    "sg:postcode":"4127",
    "sg:province":"QLD",
    "sg:tags":[
        "away",
        "take"
    ],
    "wof:name":"Moss Street Snack Bar",
    "wof:placetype":"venue"
},
  "geometry": {"coordinates":[153.11949157699999,-27.6242637634],"type":"Point"}
}