{
  "type": "Feature",
  "properties": {
    "addr:full":"42 Alfrieda St St Albans VIC 3021",
    "addr:housenumber":"42",
    "addr:postcode":"3021",
    "addr:street":"Alfrieda St",
    "iso:country":"AU",
    "sg:address":"42 Alfrieda St",
    "sg:city":"St Albans",
    "sg:classifiers":[
        {
            "category":"Personal",
            "subcategory":"Beauty Salon",
            "type":"Services"
        }
    ],
    "sg:phone":"+61 3 9366 4688",
    "sg:postcode":"3021",
    "sg:province":"VIC",
    "sg:tags":[
        "hairdresser"
    ],
    "wof:name":"Ngoc Dzung Hair Salon",
    "wof:placetype":"venue"
},
  "geometry": {"coordinates":[144.800949,-37.742886],"type":"Point"}
}