{
  "type": "Feature",
  "properties": {
    "iso:country":"AU",
    "sg:address":"55 Garfield Rd",
    "sg:city":"Riverstone",
    "sg:classifiers":[
        {
            "category":"Autos & Motor Vehicles",
            "subcategory":"Fuel & Gas Station",
            "type":"Retail Goods"
        }
    ],
    "sg:phone":"+61 2 9627 5811",
    "sg:postcode":"2765",
    "sg:province":"NSW",
    "wof:name":"Burmah Riverstone",
    "wof:placetype":"venue"
},
  "geometry": {"coordinates":[150.863677978,-33.67811203],"type":"Point"}
}