{
  "type": "Feature",
  "properties": {
    "addr:full":"Suite 3/ 218 Upper Heidelberg Rd Ivanhoe VIC 3079",
    "addr:housenumber":"/ 218",
    "addr:postcode":"3079",
    "addr:street":"Upper Heidelberg Rd",
    "iso:country":"AU",
    "sg:address":"Suite 3/ 218 Upper Heidelberg Rd",
    "sg:city":"Ivanhoe",
    "sg:classifiers":[
        {
            "category":"Health Services",
            "subcategory":"Health Practitioner",
            "type":"Services"
        }
    ],
    "sg:phone":"+61 3 9497 1966",
    "sg:postcode":"3079",
    "sg:province":"VIC",
    "sg:tags":[
        "psychologist"
    ],
    "wof:name":"Newell Glenda",
    "wof:placetype":"venue"
},
  "geometry": {"coordinates":[145.044525147,-37.7672691345],"type":"Point"}
}