{
  "type": "Feature",
  "properties": {
    "addr:full":"97 Ernest St Lakemba NSW 2195",
    "addr:housenumber":"97",
    "addr:postcode":"2195",
    "addr:street":"Ernest St",
    "iso:country":"AU",
    "sg:address":"97 Ernest St",
    "sg:city":"Lakemba",
    "sg:classifiers":[
        {
            "category":"Professional",
            "subcategory":"Detective & Security Services",
            "type":"Services"
        }
    ],
    "sg:phone":"+61 2 9750 8970",
    "sg:postcode":"2195",
    "sg:province":"NSW",
    "sg:tags":[
        "consultant",
        "system"
    ],
    "wof:name":"Visonic Australia",
    "wof:placetype":"venue"
},
  "geometry": {"coordinates":[151.075287,-33.926628],"type":"Point"}
}