{
  "type": "Feature",
  "properties": {
    "addr:full":"56 O&#039;Connell Pde Wellington Point QLD 4160",
    "addr:housenumber":"56",
    "addr:postcode":"4160",
    "addr:street":"O &;Connell Pde",
    "iso:country":"AU",
    "sg:address":"56 O&#039;Connell Pde",
    "sg:city":"Wellington Point",
    "sg:classifiers":[
        {
            "category":"Building & Trades",
            "subcategory":"Plumbing",
            "type":"Services"
        }
    ],
    "sg:phone":"+61 7 3207 5595",
    "sg:postcode":"4160",
    "sg:province":"QLD",
    "sg:tags":[
        "plumber",
        "gasfitters"
    ],
    "wof:name":"David Hutton",
    "wof:placetype":"venue"
},
  "geometry": {"coordinates":[153.241897583,-27.4866943359],"type":"Point"}
}