{
  "type": "Feature",
  "properties": {
    "iso:country":"AU",
    "sg:address":"Edols Pl",
    "sg:city":"Geelong North",
    "sg:classifiers":[
        {
            "category":"Fast Food",
            "type":"Food & Drink"
        }
    ],
    "sg:phone":"+61 3 5278 7264",
    "sg:postcode":"3215",
    "sg:province":"VIC",
    "sg:tags":[
        "away",
        "take"
    ],
    "wof:name":"Edol Food Shop",
    "wof:placetype":"venue"
},
  "geometry": {"coordinates":[144.35072326700001,-38.1071128845],"type":"Point"}
}