{
  "type": "Feature",
  "properties": {
    "addr:full":"32 - 34 Market St Manilla NSW 2346",
    "addr:housenumber":"34",
    "addr:postcode":"2346",
    "addr:street":"Market St",
    "iso:country":"AU",
    "sg:address":"32 - 34 Market St",
    "sg:city":"Manilla",
    "sg:classifiers":[
        {
            "category":"Professional",
            "subcategory":"Engineering",
            "type":"Services"
        }
    ],
    "sg:phone":"+61 2 6785 1850",
    "sg:postcode":"2346",
    "sg:province":"NSW",
    "sg:tags":[
        "engineer"
    ],
    "wof:name":"AMW Feeders & Engineering",
    "wof:placetype":"venue"
},
  "geometry": {"coordinates":[150.72065734899999,-30.7452735901],"type":"Point"}
}