{
  "type": "Feature",
  "properties": {
    "iso:country":"AU",
    "sg:address":"12 Edward St",
    "sg:city":"Camden",
    "sg:classifiers":[
        {
            "category":"Health Services",
            "subcategory":"Doctor",
            "type":"Services"
        }
    ],
    "sg:phone":"+61 2 4655 3225",
    "sg:postcode":"2570",
    "sg:province":"NSW",
    "sg:tags":[
        "occupational",
        "safety"
    ],
    "wof:name":"Occupational Safety Pty Ltd",
    "wof:placetype":"venue"
},
  "geometry": {"coordinates":[150.69767761200001,-34.0500907898],"type":"Point"}
}