{
  "type": "Feature",
  "properties": {
    "iso:country":"AU",
    "sg:address":"Unit 4 Churchill Court 335 Hay St",
    "sg:city":"Subiaco",
    "sg:classifiers":[
        {
            "category":"Real Estate",
            "subcategory":"Developer",
            "type":"Services"
        }
    ],
    "sg:phone":"+61 8 9388 0536",
    "sg:postcode":"6008",
    "sg:province":"WA",
    "sg:tags":[
        "chartering",
        "ship",
        "broker"
    ],
    "wof:name":"Sea Wise Australia PTY LTD",
    "wof:placetype":"venue"
},
  "geometry": {"coordinates":[115.827796936,-31.9471702576],"type":"Point"}
}