{
  "type": "Feature",
  "properties": {
    "iso:country":"AU",
    "sg:address":"Shop 1 18",
    "sg:city":"Garden City Kotara",
    "sg:classifiers":[
        {
            "category":"Farming",
            "subcategory":"Poultry Farm",
            "type":"Manufacturing & Wholesale Goods"
        }
    ],
    "sg:phone":"+61 2 4952 6177",
    "sg:postcode":"2289",
    "sg:province":"NSW",
    "sg:tags":[
        "breeder",
        "bird"
    ],
    "wof:name":"Allans Garden City Pet Shoppe",
    "wof:placetype":"venue"
},
  "geometry": {"coordinates":[151.699386597,-32.9403076172],"type":"Point"}
}