{
  "type": "Feature",
  "properties": {
    "addr:full":"7 Murphy St Bendigo VIC 3550",
    "addr:housenumber":"7",
    "addr:postcode":"3550",
    "addr:street":"Murphy St",
    "iso:country":"AU",
    "sg:address":"7 Murphy St",
    "sg:city":"Bendigo",
    "sg:classifiers":[
        {
            "category":"Travel",
            "subcategory":"Hostel",
            "type":"Entertainment"
        }
    ],
    "sg:phone":"+61 3 5441 6041",
    "sg:postcode":"3550",
    "sg:province":"VIC",
    "sg:tags":[
        "home"
    ],
    "wof:name":"Bignold Park",
    "wof:placetype":"venue"
},
  "geometry": {"coordinates":[144.29649352999999,-36.7616767883],"type":"Point"}
}