{
  "type": "Feature",
  "properties": {
    "addr:full":"Shop 144 Darling Harbour Aprtmnts Cnr Allen & Harris Sts Pyrmont NSW 2009",
    "addr:housenumber":"144",
    "addr:postcode":"2009",
    "addr:street":"Cnr Allen & Harris Sts",
    "iso:country":"AU",
    "sg:address":"Shop 144 Darling Harbour Aprtmnts Cnr Allen & Harris Sts",
    "sg:city":"Pyrmont",
    "sg:classifiers":[
        {
            "category":"Health Services",
            "subcategory":"Dentist",
            "type":"Services"
        }
    ],
    "sg:phone":"+61 2 9660 3322",
    "sg:postcode":"2009",
    "sg:province":"NSW",
    "wof:name":"After Hours Dental Care",
    "wof:placetype":"venue"
},
  "geometry": {"coordinates":[151.19790649399999,-33.8700561523],"type":"Point"}
}