{
  "type": "Feature",
  "properties": {
    "addr:full":"Cnr Greenfield & Mimosa Rds Greenfield Park NSW 2176",
    "addr:postcode":"2176",
    "addr:street":"Cnr",
    "iso:country":"AU",
    "sg:address":"Cnr Greenfield & Mimosa Rds",
    "sg:city":"Greenfield Park",
    "sg:classifiers":[
        {
            "category":"Food & Beverages",
            "subcategory":"Liquor & Beverages",
            "type":"Retail Goods"
        }
    ],
    "sg:phone":"+61 2 9610 5000",
    "sg:postcode":"2176",
    "sg:province":"NSW",
    "sg:tags":[
        "store"
    ],
    "wof:name":"Pubmart",
    "wof:placetype":"venue"
},
  "geometry": {"coordinates":[150.89126586899999,-33.872253418],"type":"Point"}
}