{
  "type": "Feature",
  "properties": {
    "iso:country":"AU",
    "sg:address":"4 Avendale Pl",
    "sg:city":"Tallai",
    "sg:classifiers":[
        {
            "category":"Home & Garden",
            "subcategory":"Building Materials",
            "type":"Retail Goods"
        }
    ],
    "sg:phone":"+61 438 779 116",
    "sg:postcode":"4213",
    "sg:province":"QLD",
    "sg:tags":[
        "lawn",
        "cutting",
        "maintenance"
    ],
    "wof:name":"Staycut",
    "wof:placetype":"venue"
},
  "geometry": {"coordinates":[153.33523559599999,-28.0782375336],"type":"Point"}
}