{
  "type": "Feature",
  "properties": {
    "addr:full":"2 Sapphire St Wellington NSW 2820",
    "addr:housenumber":"2",
    "addr:postcode":"2820",
    "addr:street":"Sapphire St",
    "iso:country":"AU",
    "sg:address":"2 Sapphire St",
    "sg:city":"Wellington",
    "sg:classifiers":[
        {
            "category":"Commercial Area",
            "type":"Public Place"
        }
    ],
    "sg:phone":"+61 418 648 313",
    "sg:postcode":"2820",
    "sg:province":"NSW",
    "sg:tags":[
        "heavy",
        "carrier"
    ],
    "wof:name":"Hosking G R & R T",
    "wof:placetype":"venue"
},
  "geometry": {"coordinates":[148.942962647,-32.5556411743],"type":"Point"}
}