{
  "type": "Feature",
  "properties": {
    "iso:country":"AU",
    "sg:address":"4 Bent St",
    "sg:city":"Northcote",
    "sg:classifiers":[
        {
            "category":"Shopping",
            "subcategory":"Computers & Home Electronics",
            "type":"Retail Goods"
        }
    ],
    "sg:phone":"+61 3 9489 1863",
    "sg:postcode":"3070",
    "sg:province":"VIC",
    "sg:tags":[
        "cleaning"
    ],
    "wof:name":"On-Site Computer Clean",
    "wof:placetype":"venue"
},
  "geometry": {"coordinates":[144.99899300000001,-37.767349],"type":"Point"}
}