{
  "type": "Feature",
  "properties": {
    "addr:full":"Elizabeth St Moss Vale NSW 2577",
    "addr:postcode":"2577",
    "addr:street":"Elizabeth St",
    "iso:country":"AU",
    "sg:address":"Elizabeth St",
    "sg:city":"Moss Vale",
    "sg:classifiers":[
        {
            "category":"Food & Beverages",
            "subcategory":"Supermarket",
            "type":"Retail Goods"
        }
    ],
    "sg:phone":"+61 2 4868 2640",
    "sg:postcode":"2577",
    "sg:province":"NSW",
    "sg:tags":[
        "grocery",
        "store"
    ],
    "wof:name":"Tuckerbag",
    "wof:placetype":"venue"
},
  "geometry": {"coordinates":[150.372924805,-34.5501976013],"type":"Point"}
}