{
  "type": "Feature",
  "properties": {
    "iso:country":"AU",
    "sg:address":"422 Bay St",
    "sg:city":"Port Melbourne",
    "sg:classifiers":[
        {
            "category":"Retail",
            "subcategory":"Auto Repair",
            "type":"Services"
        }
    ],
    "sg:phone":"+61 3 9646 5482",
    "sg:postcode":"3207",
    "sg:province":"VIC",
    "sg:tags":[
        "repairer",
        "motor",
        "engineer"
    ],
    "wof:name":"Bay Street Auto Performance",
    "wof:placetype":"venue"
},
  "geometry": {"coordinates":[144.93821700000001,-37.843082],"type":"Point"}
}