{
  "type": "Feature",
  "properties": {
    "addr:full":"491 Flinders St Townsville QLD 4810",
    "addr:housenumber":"491",
    "addr:postcode":"4810",
    "addr:street":"Flinders St",
    "iso:country":"AU",
    "sg:address":"491 Flinders St",
    "sg:city":"Townsville",
    "sg:classifiers":[
        {
            "category":"Shopping",
            "subcategory":"Shoes",
            "type":"Retail Goods"
        }
    ],
    "sg:phone":"+61 7 4772 3088",
    "sg:postcode":"4810",
    "sg:province":"QLD",
    "sg:tags":[
        "footwear"
    ],
    "wof:name":"Askern Bros Disposals Pty Ltd",
    "wof:placetype":"venue"
},
  "geometry": {"coordinates":[146.80938699999999,-19.266891],"type":"Point"}
}