{
  "type": "Feature",
  "properties": {
    "addr:full":"1 Currockbilly St Welby NSW 2575",
    "addr:housenumber":"1",
    "addr:postcode":"2575",
    "addr:street":"Currockbilly St",
    "iso:country":"AU",
    "sg:address":"1 Currockbilly St",
    "sg:city":"Welby",
    "sg:classifiers":[
        {
            "category":"Retail",
            "subcategory":"Repair Shop",
            "type":"Services"
        }
    ],
    "sg:phone":"+61 2 4871 3446",
    "sg:postcode":"2575",
    "sg:province":"NSW",
    "sg:tags":[
        "upholsterer"
    ],
    "wof:name":"Provincial Upholstery",
    "wof:placetype":"venue"
},
  "geometry": {"coordinates":[150.42301940900001,-34.4426002502],"type":"Point"}
}