{
  "type": "Feature",
  "properties": {
    "addr:full":"69 McQuoid St Queanbeyan NSW 2620",
    "addr:housenumber":"69",
    "addr:postcode":"2620",
    "addr:street":"Mcquoid St",
    "iso:country":"AU",
    "sg:address":"69 McQuoid St",
    "sg:city":"Queanbeyan",
    "sg:classifiers":[
        {
            "category":"Building & Trades",
            "subcategory":"Construction",
            "type":"Services"
        }
    ],
    "sg:phone":"+61 2 6299 5561",
    "sg:postcode":"2620",
    "sg:province":"NSW",
    "sg:tags":[
        "contractor"
    ],
    "wof:name":"Lee J A",
    "wof:placetype":"venue"
},
  "geometry": {"coordinates":[149.24349975600001,-35.3499183655],"type":"Point"}
}