{
  "type": "Feature",
  "properties": {
    "iso:country":"AU",
    "sg:address":"Suite 8, 65 St Pauls St",
    "sg:city":"Randwick",
    "sg:classifiers":[
        {
            "category":"Food & Beverages",
            "subcategory":"Liquor & Beverages",
            "type":"Retail Goods"
        }
    ],
    "sg:phone":"+61 1800 802 388",
    "sg:postcode":"2031",
    "sg:province":"NSW",
    "sg:tags":[
        "merchant",
        "spirit",
        "wine"
    ],
    "wof:name":"A. Swords & Co Wines",
    "wof:placetype":"venue"
},
  "geometry": {"coordinates":[151.24468994099999,-33.9206314087],"type":"Point"}
}