{
  "type": "Feature",
  "properties": {
    "iso:country":"AU",
    "sg:address":"79 The River Rd",
    "sg:city":"Revesby",
    "sg:classifiers":[
        {
            "category":"Personal",
            "subcategory":"Beauty Salon",
            "type":"Services"
        }
    ],
    "sg:phone":"+61 2 9792 6821",
    "sg:postcode":"2212",
    "sg:province":"NSW",
    "sg:tags":[
        "hairdresser"
    ],
    "wof:name":"Hair Appeal & Beauty Connection",
    "wof:placetype":"venue"
},
  "geometry": {"coordinates":[151.016647,-33.960175],"type":"Point"}
}