{
  "type": "Feature",
  "properties": {
    "addr:full":"17 Officer St Meadow Heights VIC 3048",
    "addr:housenumber":"17",
    "addr:postcode":"3048",
    "addr:street":"Officer St",
    "iso:country":"AU",
    "sg:address":"17 Officer St",
    "sg:city":"Meadow Heights",
    "sg:classifiers":[
        {
            "category":"Building & Trades",
            "subcategory":"Cleaning & Sanitation",
            "type":"Services"
        }
    ],
    "sg:phone":"+61 402 753 098",
    "sg:postcode":"3048",
    "sg:province":"VIC",
    "sg:tags":[
        "industrial",
        "commercial",
        "contractor"
    ],
    "wof:name":"Jims Cleaning Coburg",
    "wof:placetype":"venue"
},
  "geometry": {"coordinates":[144.928146,-37.651871],"type":"Point"}
}