{
  "type": "Feature",
  "properties": {
    "addr:full":"150 Thirteenth St Mildura VIC 3500",
    "addr:housenumber":"150",
    "addr:postcode":"3500",
    "addr:street":"Thirteenth St",
    "iso:country":"AU",
    "sg:address":"150 Thirteenth St",
    "sg:city":"Mildura",
    "sg:classifiers":[
        {
            "category":"Health Services",
            "subcategory":"Health Practitioner",
            "type":"Services"
        }
    ],
    "sg:phone":"+61 3 5021 1965",
    "sg:postcode":"3500",
    "sg:province":"VIC",
    "sg:tags":[
        "naturopath"
    ],
    "wof:name":"Dichiera Michelina",
    "wof:placetype":"venue"
},
  "geometry": {"coordinates":[142.151580811,-34.1903686523],"type":"Point"}
}