{
  "type": "Feature",
  "properties": {
    "iso:country":"AU",
    "sg:address":"3 Commercial Rd",
    "sg:city":"Mallacoota",
    "sg:classifiers":[
        {
            "category":"Autos & Motor Vehicles",
            "subcategory":"Motorcycle Sales",
            "type":"Retail Goods"
        }
    ],
    "sg:phone":"+61 3 5158 0459",
    "sg:postcode":"3892",
    "sg:province":"VIC",
    "sg:tags":[
        "outboard"
    ],
    "wof:name":"Mallacoota Outboards",
    "wof:placetype":"venue"
},
  "geometry": {"coordinates":[149.74388122600001,-37.5559158325],"type":"Point"}
}