{
  "type": "Feature",
  "properties": {
    "iso:country":"AU",
    "sg:address":"Unit 1 45 Northbourne Ave",
    "sg:city":"Canberra City",
    "sg:classifiers":[
        {
            "category":"Education",
            "subcategory":"Special Training",
            "type":"Public Place"
        }
    ],
    "sg:phone":"+61 2 6247 5674",
    "sg:postcode":"2601",
    "sg:province":"ACT",
    "sg:tags":[
        "development"
    ],
    "wof:name":"Kenja Communication",
    "wof:placetype":"venue"
},
  "geometry": {"coordinates":[149.12878418,-35.278968811],"type":"Point"}
}