{
  "type": "Feature",
  "properties": {
    "addr:full":"Lot 9 Hooper Rd Kersbrook SA 5231",
    "addr:postcode":"5231",
    "addr:street":"Hooper Rd",
    "iso:country":"AU",
    "sg:address":"Lot 9 Hooper Rd",
    "sg:city":"Kersbrook",
    "sg:classifiers":[
        {
            "category":"Shopping",
            "subcategory":"Musical Instruments",
            "type":"Retail Goods"
        }
    ],
    "sg:phone":"+61 8 8389 3035",
    "sg:postcode":"5231",
    "sg:province":"SA",
    "sg:tags":[
        "piano",
        "organ"
    ],
    "wof:name":"GumHaven - Ebony & Ivory",
    "wof:placetype":"venue"
},
  "geometry": {"coordinates":[138.88641357399999,-34.7846183777],"type":"Point"}
}