{
  "type": "Feature",
  "properties": {
    "iso:country":"AU",
    "sg:address":"2 Edwards St",
    "sg:city":"Katoomba",
    "sg:classifiers":[
        {
            "category":"Social Services",
            "subcategory":"Child Care",
            "type":"Services"
        }
    ],
    "sg:phone":"+61 2 4782 4220",
    "sg:postcode":"2780",
    "sg:province":"NSW",
    "wof:name":"Mikayla Children's Centre Inc",
    "wof:placetype":"venue"
},
  "geometry": {"coordinates":[150.31036376899999,-33.7184257507],"type":"Point"}
}