{
  "type": "Feature",
  "properties": {
    "addr:full":"Un 16/ 10 Benson St Toowong QLD 4066",
    "addr:housenumber":"/ 10",
    "addr:postcode":"4066",
    "addr:street":"Benson St",
    "iso:country":"AU",
    "sg:address":"Un 16/ 10 Benson St",
    "sg:city":"Toowong",
    "sg:classifiers":[
        {
            "category":"Education",
            "subcategory":"Special Training",
            "type":"Public Place"
        }
    ],
    "sg:phone":"+61 7 3871 2539",
    "sg:postcode":"4066",
    "sg:province":"QLD",
    "sg:tags":[
        "development"
    ],
    "sg:website":"http://www.assenttecs.com.au",
    "wof:name":"AssentTECS",
    "wof:placetype":"venue"
},
  "geometry": {"coordinates":[152.99359130900001,-27.4855175018],"type":"Point"}
}