{
  "type": "Feature",
  "properties": {
    "addr:full":"View Ave Cnr View & Gold Coast Hwy Surfers Paradise QLD 4217",
    "addr:postcode":"4217",
    "addr:street":"View Ave Cnr View;Coast Hwy",
    "iso:country":"AU",
    "sg:address":"View Ave Cnr View & Gold Coast Hwy",
    "sg:city":"Surfers Paradise",
    "sg:classifiers":[
        {
            "category":"Parking",
            "type":"Transportation"
        }
    ],
    "sg:phone":"+61 7 5592 1960",
    "sg:postcode":"4217",
    "sg:province":"QLD",
    "wof:name":"Secure Parking",
    "wof:placetype":"venue"
},
  "geometry": {"coordinates":[153.42953491200001,-28.0110912323],"type":"Point"}
}