{
  "type": "Feature",
  "properties": {
    "addr:full":"26 Dunbar Rd Edgeworth NSW 2285",
    "addr:housenumber":"26",
    "addr:postcode":"2285",
    "addr:street":"Dunbar Rd",
    "iso:country":"AU",
    "sg:address":"26 Dunbar Rd",
    "sg:city":"Edgeworth",
    "sg:classifiers":[
        {
            "category":"Building & Trades",
            "subcategory":"Pest Control",
            "type":"Services"
        }
    ],
    "sg:phone":"+61 2 4955 1611",
    "sg:postcode":"2285",
    "sg:province":"NSW",
    "wof:name":"Coastal-Valley Pest & Weed Control Services",
    "wof:placetype":"venue"
},
  "geometry": {"coordinates":[151.60699462900001,-32.9194908142],"type":"Point"}
}