{
  "type": "Feature",
  "properties": {
    "addr:full":"107- 123 Muriel Ave Moorooka QLD 4105",
    "addr:housenumber":"123",
    "addr:postcode":"4105",
    "addr:street":"Muriel Ave",
    "iso:country":"AU",
    "sg:address":"107- 123 Muriel Ave",
    "sg:city":"Moorooka",
    "sg:classifiers":[
        {
            "category":"Retail",
            "subcategory":"Auto Rental",
            "type":"Services"
        }
    ],
    "sg:phone":"+61 7 3892 3676",
    "sg:postcode":"4105",
    "sg:province":"QLD",
    "sg:tags":[
        "car",
        "armoured"
    ],
    "wof:name":"Chubb Security Services",
    "wof:placetype":"venue"
},
  "geometry": {"coordinates":[153.01461792000001,-27.5411777496],"type":"Point"}
}