{
  "type": "Feature",
  "properties": {
    "addr:full":"U3/ 17 Rawlins Cct Kunda Park QLD 4556",
    "addr:housenumber":"17",
    "addr:postcode":"4556",
    "addr:street":"U3 /;Cct",
    "iso:country":"AU",
    "sg:address":"U3/ 17",
    "sg:city":"Rawlins Cct Kunda Park",
    "sg:classifiers":[
        {
            "category":"Wholesale",
            "subcategory":"Metals & Minerals",
            "type":"Manufacturing & Wholesale Goods"
        }
    ],
    "sg:phone":"+61 7 5453 7561",
    "sg:postcode":"4556",
    "sg:province":"QLD",
    "sg:tags":[
        "steel",
        "stainless",
        "product",
        "equipment"
    ],
    "wof:name":"First Choice Fabrications",
    "wof:placetype":"venue"
},
  "geometry": {"coordinates":[153.03143310600001,-26.6670532227],"type":"Point"}
}