{
  "type": "Feature",
  "properties": {
    "addr:full":"Level 1, Glen Eira Rd Ripponlea VIC 3185",
    "addr:postcode":"3185",
    "addr:street":"Glen Eira Rd",
    "iso:country":"AU",
    "sg:address":"Level 1, Glen Eira Rd",
    "sg:city":"Ripponlea",
    "sg:classifiers":[
        {
            "category":"Retail",
            "subcategory":"Auto Rental",
            "type":"Services"
        }
    ],
    "sg:phone":"+61 3 9645 6929",
    "sg:postcode":"3185",
    "sg:province":"VIC",
    "sg:tags":[
        "chauffeur",
        "car",
        "hire",
        "driven",
        "limousine"
    ],
    "wof:name":"Capital Chauffeured Cars",
    "wof:placetype":"venue"
},
  "geometry": {"coordinates":[144.99281310999999,-37.8761482239],"type":"Point"}
}