{
  "type": "Feature",
  "properties": {
    "iso:country":"AU",
    "sg:address":"41 Joan St",
    "sg:city":"Forresters Beach",
    "sg:classifiers":[
        {
            "category":"Personal",
            "subcategory":"Massage",
            "type":"Services"
        }
    ],
    "sg:phone":"+61 2 4384 4055",
    "sg:postcode":"2260",
    "sg:province":"NSW",
    "sg:tags":[
        "therapy"
    ],
    "wof:name":"Beltran Lesley",
    "wof:placetype":"venue"
},
  "geometry": {"coordinates":[151.47067300000001,-33.400982],"type":"Point"}
}