{
  "type": "Feature",
  "properties": {
    "iso:country":"AU",
    "sg:address":"30 Ingoldby Rd",
    "sg:city":"McLaren Flat",
    "sg:classifiers":[
        {
            "category":"Farming",
            "subcategory":"Vineyard",
            "type":"Manufacturing & Wholesale Goods"
        }
    ],
    "sg:phone":"+61 8 8324 5000",
    "sg:postcode":"5171",
    "sg:province":"SA",
    "sg:tags":[
        "winery"
    ],
    "wof:name":"Rosemount Estate",
    "wof:placetype":"venue"
},
  "geometry": {"coordinates":[138.593841553,-35.205116272],"type":"Point"}
}