{
  "type": "Feature",
  "properties": {
    "iso:country":"AU",
    "sg:address":"Shop 84 Tweed City Shopng Cntr",
    "sg:city":"Tweed Heads",
    "sg:classifiers":[
        {
            "category":"Shopping",
            "subcategory":"Pets & Pet Supplies",
            "type":"Retail Goods"
        }
    ],
    "sg:phone":"+61 7 5523 1395",
    "sg:postcode":"2485",
    "sg:province":"NSW",
    "sg:tags":[
        "shop",
        "supplier"
    ],
    "wof:name":"Pets Paradise",
    "wof:placetype":"venue"
},
  "geometry": {"coordinates":[153.54066467300001,-28.179693222],"type":"Point"}
}