{
  "type": "Feature",
  "properties": {
    "addr:full":"Shop 30, Station Arcade, 24 Main St Blacktown NSW 2148",
    "addr:housenumber":"shop 30;24",
    "addr:postcode":"2148",
    "addr:street":"Station Arcade;Main St",
    "iso:country":"AU",
    "sg:address":"Shop 30, Station Arcade, 24 Main St",
    "sg:city":"Blacktown",
    "sg:classifiers":[
        {
            "category":"Health Services",
            "subcategory":"Dentist",
            "type":"Services"
        }
    ],
    "sg:phone":"+61 2 9150 9211",
    "sg:postcode":"2148",
    "sg:province":"NSW",
    "wof:name":"Dr Umesh Gaikaiwari",
    "wof:placetype":"venue"
},
  "geometry": {"coordinates":[150.907913208,-33.7691078186],"type":"Point"}
}