{
  "type": "Feature",
  "properties": {
    "addr:full":"1 York St Airport West VIC 3042",
    "addr:housenumber":"1",
    "addr:postcode":"3042",
    "addr:street":"York St",
    "iso:country":"AU",
    "sg:address":"1 York St",
    "sg:city":"Airport West",
    "sg:classifiers":[
        {
            "category":"Education",
            "subcategory":"Special Training",
            "type":"Public Place"
        }
    ],
    "sg:phone":"+61 3 9310 5310",
    "sg:postcode":"3042",
    "sg:province":"VIC",
    "sg:tags":[
        "school",
        "flying"
    ],
    "wof:name":"Alteon Training Australia Pty Ltd",
    "wof:placetype":"venue"
},
  "geometry": {"coordinates":[144.890335083,-37.7266273499],"type":"Point"}
}