{
  "type": "Feature",
  "properties": {
    "addr:full":"21 Alder Pl Dubbo NSW 2830",
    "addr:housenumber":"21",
    "addr:postcode":"2830",
    "addr:street":"Alder Pl",
    "iso:country":"AU",
    "sg:address":"21 Alder Pl",
    "sg:city":"Dubbo",
    "sg:classifiers":[
        {
            "category":"Professional",
            "subcategory":"Printing & Photocopies",
            "type":"Services"
        }
    ],
    "sg:phone":"+61 429 826 076",
    "sg:postcode":"2830",
    "sg:province":"NSW",
    "sg:tags":[
        "laminating"
    ],
    "wof:name":"Central West Print",
    "wof:placetype":"venue"
},
  "geometry": {"coordinates":[148.62637329099999,-32.2538566589],"type":"Point"}
}