{
  "type": "Feature",
  "properties": {
    "iso:country":"AU",
    "sg:address":"20 Pelican St",
    "sg:city":"Darlinghurst",
    "sg:classifiers":[
        {
            "category":"Parking",
            "type":"Transportation"
        }
    ],
    "sg:phone":"+61 2 9264 3208",
    "sg:postcode":"2010",
    "sg:province":"NSW",
    "wof:name":"Kings Parking",
    "wof:placetype":"venue"
},
  "geometry": {"coordinates":[151.21315002399999,-33.8790550232],"type":"Point"}
}