{
  "type": "Feature",
  "properties": {
    "addr:full":"30 Main St Maldon VIC 3463",
    "addr:housenumber":"30",
    "addr:postcode":"3463",
    "addr:street":"Main St",
    "iso:country":"AU",
    "sg:address":"30 Main St",
    "sg:city":"Maldon",
    "sg:classifiers":[
        {
            "category":"Cafe",
            "type":"Food & Drink"
        }
    ],
    "sg:phone":"+61 3 5475 2904",
    "sg:postcode":"3463",
    "sg:province":"VIC",
    "wof:name":"Berryman's Cafe & Tearooms",
    "wof:placetype":"venue"
},
  "geometry": {"coordinates":[143.90333557100001,-36.8270111084],"type":"Point"}
}