{
  "type": "Feature",
  "properties": {
    "addr:full":"41 Short St Port Macquarie NSW 2444",
    "addr:housenumber":"41",
    "addr:postcode":"2444",
    "addr:street":"Short St",
    "iso:country":"AU",
    "sg:address":"41 Short St",
    "sg:city":"Port Macquarie",
    "sg:classifiers":[
        {
            "category":"Professional",
            "subcategory":"Printing & Photocopies",
            "type":"Services"
        }
    ],
    "sg:phone":"+61 2 6584 0800",
    "sg:postcode":"2444",
    "sg:province":"NSW",
    "sg:tags":[
        "photocopying"
    ],
    "wof:name":"The Xerox Business Centre Mid North Coast",
    "wof:placetype":"venue"
},
  "geometry": {"coordinates":[152.90669299999999,-31.430395],"type":"Point"}
}