{
  "type": "Feature",
  "properties": {
    "addr:full":"PO Box 51 Jesmond NSW 2299",
    "addr:postcode":"2299",
    "iso:country":"AU",
    "sg:address":"PO Box 51",
    "sg:city":"Jesmond",
    "sg:classifiers":[
        {
            "category":"Retail",
            "subcategory":"Auto Rental",
            "type":"Services"
        }
    ],
    "sg:phone":"+61 421 373 454",
    "sg:postcode":"2299",
    "sg:province":"NSW",
    "sg:tags":[
        "car",
        "wedding"
    ],
    "wof:name":"Silver Classic Limousines",
    "wof:placetype":"venue"
},
  "geometry": {"coordinates":[151.690841675,-32.9033889771],"type":"Point"}
}