{
  "type": "Feature",
  "properties": {
    "addr:full":"Dyer St Landsborough QLD 4550",
    "addr:postcode":"4550",
    "addr:street":"Dyer St",
    "iso:country":"AU",
    "sg:address":"Dyer St",
    "sg:city":"Landsborough",
    "sg:classifiers":[
        {
            "category":"Retail",
            "subcategory":"Auto Repair",
            "type":"Services"
        }
    ],
    "sg:phone":"+61 7 5494 1092",
    "sg:postcode":"4550",
    "sg:province":"QLD",
    "sg:tags":[
        "repairer",
        "motor",
        "engineer"
    ],
    "wof:name":"Landsborough Mechanical",
    "wof:placetype":"venue"
},
  "geometry": {"coordinates":[152.967819214,-26.8090076447],"type":"Point"}
}