{
  "type": "Feature",
  "properties": {
    "addr:full":"131 Cummins Rd Bundaberg QLD 4670",
    "addr:housenumber":"131",
    "addr:postcode":"4670",
    "addr:street":"Cummins Rd",
    "iso:country":"AU",
    "sg:address":"131 Cummins Rd",
    "sg:city":"Bundaberg",
    "sg:classifiers":[
        {
            "category":"Professional",
            "subcategory":"Art Services",
            "type":"Services"
        }
    ],
    "sg:phone":"+61 7 4155 0537",
    "sg:postcode":"4670",
    "sg:province":"QLD",
    "sg:tags":[
        "decorator",
        "painter"
    ],
    "wof:name":"Bragg - More Painting Pty Ltd",
    "wof:placetype":"venue"
},
  "geometry": {"coordinates":[152.28395080600001,-24.9006404877],"type":"Point"}
}