{
  "type": "Feature",
  "properties": {
    "addr:full":"Suite 2/ 8 Sixth Ave Palm Beach QLD 4221",
    "addr:housenumber":"8",
    "addr:postcode":"4221",
    "addr:street":"Sixth Ave",
    "iso:country":"AU",
    "sg:address":"Suite 2/ 8 Sixth Ave",
    "sg:city":"Palm Beach",
    "sg:classifiers":[
        {
            "category":"Professional",
            "subcategory":"Engineering",
            "type":"Services"
        }
    ],
    "sg:phone":"+61 7 5525 7377",
    "sg:postcode":"4221",
    "sg:province":"QLD",
    "sg:tags":[
        "consulting",
        "engineer"
    ],
    "wof:name":"Roadnet Pty Ltd",
    "wof:placetype":"venue"
},
  "geometry": {"coordinates":[153.47279357900001,-28.1213493347],"type":"Point"}
}