{
  "type": "Feature",
  "properties": {
    "addr:full":"336 Belmore Rd Balwyn VIC 3103",
    "addr:housenumber":"336",
    "addr:postcode":"3103",
    "addr:street":"Belmore Rd",
    "iso:country":"AU",
    "sg:address":"336 Belmore Rd",
    "sg:city":"Balwyn",
    "sg:classifiers":[
        {
            "category":"Travel",
            "subcategory":"Travel Agent",
            "type":"Entertainment"
        }
    ],
    "sg:phone":"+61 3 9857 5877",
    "sg:postcode":"3103",
    "sg:province":"VIC",
    "sg:tags":[
        "consultant"
    ],
    "wof:name":"Jetset",
    "wof:placetype":"venue"
},
  "geometry": {"coordinates":[145.102127075,-37.8039131165],"type":"Point"}
}