{
  "type": "Feature",
  "properties": {
    "addr:full":"18 Scarr St Cloncurry QLD 4824",
    "addr:housenumber":"18",
    "addr:postcode":"4824",
    "addr:street":"Scarr St",
    "iso:country":"AU",
    "sg:address":"18 Scarr St",
    "sg:city":"Cloncurry",
    "sg:classifiers":[
        {
            "category":"Arts & Performance",
            "subcategory":"Theater",
            "type":"Entertainment"
        }
    ],
    "sg:phone":"+61 7 4742 1770",
    "sg:postcode":"4824",
    "sg:province":"QLD",
    "sg:tags":[
        "theatre"
    ],
    "wof:name":"Bio Cafe & Cinema",
    "wof:placetype":"venue"
},
  "geometry": {"coordinates":[140.50903299999999,-20.705812],"type":"Point"}
}