{
  "type": "Feature",
  "properties": {
    "iso:country":"AU",
    "sg:address":"5 Dunsmore St",
    "sg:city":"Kelvin Grove",
    "sg:classifiers":[
        {
            "category":"Manufacturing",
            "subcategory":"Wood Products",
            "type":"Manufacturing & Wholesale Goods"
        }
    ],
    "sg:phone":"+61 7 3856 4548",
    "sg:postcode":"4059",
    "sg:province":"QLD",
    "sg:tags":[
        "polisher",
        "french"
    ],
    "wof:name":"Knobel R & C",
    "wof:placetype":"venue"
},
  "geometry": {"coordinates":[153.01559448200001,-27.4440288544],"type":"Point"}
}