{
  "type": "Feature",
  "properties": {
    "iso:country":"AU",
    "sg:address":"59 Corfield St",
    "sg:city":"Gosnells",
    "sg:classifiers":[
        {
            "category":"Social Services",
            "subcategory":"Child Care",
            "type":"Services"
        }
    ],
    "sg:phone":"+61 8 9398 7788",
    "sg:postcode":"6110",
    "sg:province":"WA",
    "wof:name":"Wirrabirra Child Care",
    "wof:placetype":"venue"
},
  "geometry": {"coordinates":[115.999382019,-32.0901222229],"type":"Point"}
}