{
  "type": "Feature",
  "properties": {
    "addr:full":"Sh: 5 Gregory St Parap NT 0820",
    "addr:postcode":"nt 0820",
    "addr:street":"Sh 5 Gregory St",
    "iso:country":"AU",
    "sg:address":"Sh: 5 Gregory St",
    "sg:city":"Parap",
    "sg:classifiers":[
        {
            "category":"Personal",
            "subcategory":"Beauty Salon",
            "type":"Services"
        }
    ],
    "sg:phone":"+61 8 8981 0890",
    "sg:postcode":"0820",
    "sg:province":"NT",
    "sg:tags":[
        "hairdresser"
    ],
    "wof:name":"Idiom Hair Studio",
    "wof:placetype":"venue"
},
  "geometry": {"coordinates":[130.839279175,-12.4323358536],"type":"Point"}
}