{
  "type": "Feature",
  "properties": {
    "addr:full":"Jenner St Merbein VIC 3505",
    "addr:postcode":"3505",
    "addr:street":"Jenner St",
    "iso:country":"AU",
    "sg:address":"Jenner St",
    "sg:city":"Merbein",
    "sg:classifiers":[
        {
            "category":"Education",
            "subcategory":"School",
            "type":"Public Place"
        }
    ],
    "sg:phone":"+61 3 5025 2295",
    "sg:postcode":"3505",
    "sg:province":"VIC",
    "sg:tags":[
        "state",
        "except",
        "nsw"
    ],
    "wof:name":"Merbein Primary School",
    "wof:placetype":"venue"
},
  "geometry": {"coordinates":[142.052200317,-34.1699790955],"type":"Point"}
}