{
  "type": "Feature",
  "properties": {
    "addr:full":"Shp Go 16 , Roselands NSW 2196",
    "addr:housenumber":"16",
    "addr:postcode":"2196",
    "addr:street":"Roselands",
    "iso:country":"AU",
    "sg:address":"Shp Go 16",
    "sg:city":", Roselands",
    "sg:classifiers":[
        {
            "category":"Shopping",
            "subcategory":"Clothing, Apparel, & Fashions",
            "type":"Retail Goods"
        }
    ],
    "sg:phone":"+61 2 9759 6272",
    "sg:postcode":"2196",
    "sg:province":"NSW",
    "sg:tags":[
        "menswear"
    ],
    "wof:name":"Melt Roselands",
    "wof:placetype":"venue"
},
  "geometry": {"coordinates":[151.074387,-33.936729],"type":"Point"}
}