{
  "type": "Feature",
  "properties": {
    "iso:country":"AU",
    "sg:address":"16 Ferguson St",
    "sg:city":"Mitcham",
    "sg:classifiers":[
        {
            "category":"Banks & Credit Unions",
            "subcategory":"Investment Brokerage",
            "type":"Services"
        }
    ],
    "sg:phone":"+61 3 9874 1449",
    "sg:postcode":"3132",
    "sg:province":"VIC",
    "wof:name":"MKT Enterprises",
    "wof:placetype":"venue"
},
  "geometry": {"coordinates":[145.21060180699999,-37.8207435608],"type":"Point"}
}