{
  "type": "Feature",
  "properties": {
    "addr:full":"GPO Box 186C Melbourne VIC 3001",
    "addr:postcode":"3001",
    "iso:country":"AU",
    "sg:address":"GPO Box 186C",
    "sg:city":"Melbourne",
    "sg:classifiers":[
        {
            "category":"Utilities",
            "subcategory":"Natural Gas",
            "type":"Services"
        }
    ],
    "sg:phone":"+61 13 24 61",
    "sg:postcode":"3001",
    "sg:province":"VIC",
    "sg:tags":[
        "supplier"
    ],
    "wof:name":"Origin Energy",
    "wof:placetype":"venue"
},
  "geometry": {"coordinates":[144.89015197800001,-37.8525733948],"type":"Point"}
}