{
  "type": "Feature",
  "properties": {
    "iso:country":"AU",
    "sg:address":"150 Jetty Rd",
    "sg:city":"Glenelg",
    "sg:classifiers":[
        {
            "category":"Health Services",
            "subcategory":"Optometrist",
            "type":"Services"
        }
    ],
    "sg:phone":"+61 8 8294 2566",
    "sg:postcode":"5045",
    "sg:province":"SA",
    "wof:name":"OPSM",
    "wof:placetype":"venue"
},
  "geometry": {"coordinates":[138.518539,-34.980247],"type":"Point"}
}