{
  "type": "Feature",
  "properties": {
    "addr:full":"2a Broughton Rd Artarmon NSW 2064",
    "addr:housenumber":"2a",
    "addr:postcode":"2064",
    "addr:street":"Broughton Rd",
    "iso:country":"AU",
    "sg:address":"2a Broughton Rd",
    "sg:city":"Artarmon",
    "sg:classifiers":[
        {
            "category":"Professional",
            "subcategory":"Engineering",
            "type":"Services"
        }
    ],
    "sg:phone":"+61 2 8448 2800",
    "sg:postcode":"2064",
    "sg:province":"NSW",
    "sg:tags":[
        "civil",
        "engineer"
    ],
    "wof:name":"Woolacotts",
    "wof:placetype":"venue"
},
  "geometry": {"coordinates":[151.18359375,-33.8093986511],"type":"Point"}
}