{
  "type": "Feature",
  "properties": {
    "iso:country":"AU",
    "sg:address":"18 Brisbane St",
    "sg:city":"Launceston",
    "sg:classifiers":[
        {
            "category":"Health Services",
            "subcategory":"Health Practitioner",
            "type":"Services"
        }
    ],
    "sg:phone":"+61 3 6334 8266",
    "sg:postcode":"7250",
    "sg:province":"TAS",
    "sg:tags":[
        "osteopath"
    ],
    "wof:name":"Vaughan Lisa",
    "wof:placetype":"venue"
},
  "geometry": {"coordinates":[147.142120361,-41.434715271],"type":"Point"}
}