{
  "type": "Feature",
  "properties": {
    "addr:full":"419 Nepean Hwy Chelsea VIC 3196",
    "addr:housenumber":"419",
    "addr:postcode":"3196",
    "addr:street":"Nepean Hwy",
    "iso:country":"AU",
    "sg:address":"419 Nepean Hwy",
    "sg:city":"Chelsea",
    "sg:classifiers":[
        {
            "category":"Cafe",
            "type":"Food & Drink"
        }
    ],
    "sg:phone":"+61 3 9772 9558",
    "sg:postcode":"3196",
    "sg:province":"VIC",
    "wof:name":"Bru's@chelsea Cafe",
    "wof:placetype":"venue"
},
  "geometry": {"coordinates":[145.116577148,-38.0539512634],"type":"Point"}
}