{
  "type": "Feature",
  "properties": {
    "iso:country":"AU",
    "sg:address":"67 Torquay Rd",
    "sg:city":"Pialba",
    "sg:classifiers":[
        {
            "category":"Health Services",
            "subcategory":"Dentist",
            "type":"Services"
        }
    ],
    "sg:phone":"+61 7 4191 4549",
    "sg:postcode":"4655",
    "sg:province":"QLD",
    "sg:tags":[
        "qld",
        "orthodontist"
    ],
    "wof:name":"Saxby P J",
    "wof:placetype":"venue"
},
  "geometry": {"coordinates":[152.846237,-25.284986],"type":"Point"}
}