{
  "type": "Feature",
  "properties": {
    "addr:full":"GPO Box 38 Brisbane QLD 4001",
    "addr:postcode":"4001",
    "iso:country":"AU",
    "sg:address":"GPO Box 38",
    "sg:city":"Brisbane",
    "sg:classifiers":[
        {
            "category":"Utilities",
            "subcategory":"Sewage",
            "type":"Services"
        }
    ],
    "sg:phone":"+61 1300 728 325",
    "sg:postcode":"4001",
    "sg:province":"QLD",
    "sg:tags":[
        "electricity",
        "retailer"
    ],
    "wof:name":"Queensland Electricity",
    "wof:placetype":"venue"
},
  "geometry": {"coordinates":[153.052734375,-27.4471607208],"type":"Point"}
}