{
  "type": "Feature",
  "properties": {
    "addr:full":"59 Worrigee St Nowra NSW 2541",
    "addr:housenumber":"59",
    "addr:postcode":"2541",
    "addr:street":"Worrigee St",
    "iso:country":"AU",
    "sg:address":"59 Worrigee St",
    "sg:city":"Nowra",
    "sg:classifiers":[
        {
            "category":"Health Services",
            "subcategory":"Doctor",
            "type":"Services"
        }
    ],
    "sg:phone":"+61 2 4421 4422",
    "sg:postcode":"2541",
    "sg:province":"NSW",
    "sg:tags":[
        "medical",
        "practitioner"
    ],
    "wof:name":"Worrigee Street Medical Centre",
    "wof:placetype":"venue"
},
  "geometry": {"coordinates":[150.59950256400001,-34.8760375977],"type":"Point"}
}