{
  "type": "Feature",
  "properties": {
    "addr:full":"455 Flinders St West Townsville QLD 4810",
    "addr:housenumber":"455",
    "addr:postcode":"4810",
    "addr:street":"Flinders St West",
    "iso:country":"AU",
    "sg:address":"455 Flinders St West",
    "sg:city":"Townsville",
    "sg:classifiers":[
        {
            "category":"Fast Food",
            "type":"Food & Drink"
        }
    ],
    "sg:phone":"+61 7 4721 6701",
    "sg:postcode":"4810",
    "sg:province":"QLD",
    "sg:tags":[
        "away",
        "take"
    ],
    "wof:name":"Reef Thai Char-Grilled Seafood Restaurant The",
    "wof:placetype":"venue"
},
  "geometry": {"coordinates":[146.80947900000001,-19.26683],"type":"Point"}
}