{
  "type": "Feature",
  "properties": {
    "addr:full":"186A Macquarie St Dubbo NSW 2830",
    "addr:housenumber":"186a",
    "addr:postcode":"2830",
    "addr:street":"Macquarie St",
    "iso:country":"AU",
    "sg:address":"186A Macquarie St",
    "sg:city":"Dubbo",
    "sg:classifiers":[
        {
            "category":"Insurance",
            "subcategory":"Hazard Insurance",
            "type":"Services"
        }
    ],
    "sg:phone":"+61 13 10 10",
    "sg:postcode":"2830",
    "sg:province":"NSW",
    "sg:tags":[
        "fire",
        "accident",
        "marine"
    ],
    "wof:name":"GIO General Ltd",
    "wof:placetype":"venue"
},
  "geometry": {"coordinates":[148.60118102999999,-32.2487487793],"type":"Point"}
}