{
  "type": "Feature",
  "properties": {
    "addr:full":"190 Queen St St Marys NSW 2760",
    "addr:housenumber":"190",
    "addr:postcode":"2760",
    "addr:street":"Queen St",
    "iso:country":"AU",
    "sg:address":"190 Queen St",
    "sg:city":"St Marys",
    "sg:classifiers":[
        {
            "category":"Shopping",
            "subcategory":"Crafts & Fabrics",
            "type":"Retail Goods"
        }
    ],
    "sg:phone":"+61 2 9673 4181",
    "sg:postcode":"2760",
    "sg:province":"NSW",
    "sg:tags":[
        "material",
        "dress"
    ],
    "wof:name":"Lee Nova Pty Ltd",
    "wof:placetype":"venue"
},
  "geometry": {"coordinates":[150.773925781,-33.7681541443],"type":"Point"}
}