{
  "type": "Feature",
  "properties": {
    "addr:full":"58 Avenue Rd Paradise SA 5075",
    "addr:housenumber":"58",
    "addr:postcode":"5075",
    "addr:street":"Avenue Rd",
    "iso:country":"AU",
    "sg:address":"58 Avenue Rd",
    "sg:city":"Paradise",
    "sg:classifiers":[
        {
            "category":"Travel",
            "subcategory":"Hostel",
            "type":"Entertainment"
        }
    ],
    "sg:phone":"+61 8 8365 3004",
    "sg:postcode":"5075",
    "sg:province":"SA",
    "sg:tags":[
        "home"
    ],
    "wof:name":"Baltic Communities Home",
    "wof:placetype":"venue"
},
  "geometry": {"coordinates":[138.67956543,-34.8710632324],"type":"Point"}
}