{
  "type": "Feature",
  "properties": {
    "iso:country":"AU",
    "sg:address":"16 Cross St",
    "sg:city":"Augusta",
    "sg:classifiers":[
        {
            "category":"Utilities",
            "subcategory":"Electric",
            "type":"Services"
        }
    ],
    "sg:phone":"+61 8 9758 1660",
    "sg:postcode":"6290",
    "sg:province":"WA",
    "sg:tags":[
        "electrical",
        "contractor"
    ],
    "wof:name":"Augusta Electrics",
    "wof:placetype":"venue"
},
  "geometry": {"coordinates":[115.155906677,-34.3069610596],"type":"Point"}
}