{
  "type": "Feature",
  "properties": {
    "addr:full":"37 Mt Druitt Rd Mt Druitt NSW 2770",
    "addr:housenumber":"37",
    "addr:postcode":"2770",
    "addr:street":"Mt Druitt Rd",
    "iso:country":"AU",
    "sg:address":"37 Mt Druitt Rd",
    "sg:city":"Mt Druitt",
    "sg:classifiers":[
        {
            "category":"Arena",
            "subcategory":"Sports Club",
            "type":"Entertainment"
        }
    ],
    "sg:phone":"+61 2 9625 2022",
    "sg:postcode":"2770",
    "sg:province":"NSW",
    "sg:tags":[
        "defence",
        "supply",
        "self",
        "instruction",
        "martial art"
    ],
    "wof:name":"Scorpion Taekwondo Academy",
    "wof:placetype":"venue"
},
  "geometry": {"coordinates":[150.81231689399999,-33.7700996399],"type":"Point"}
}