{
  "type": "Feature",
  "properties": {
    "iso:country":"AU",
    "sg:address":"264 Old Cleveland Rd",
    "sg:city":"Coorparoo",
    "sg:classifiers":[
        {
            "category":"Real Estate",
            "subcategory":"Real Estate Agent",
            "type":"Services"
        }
    ],
    "sg:phone":"+61 7 3394 2511",
    "sg:postcode":"4151",
    "sg:province":"QLD",
    "wof:name":"L.J. Hooker Coorparoo",
    "wof:placetype":"venue"
},
  "geometry": {"coordinates":[153.057693481,-27.4951782227],"type":"Point"}
}