{
  "type": "Feature",
  "properties": {
    "addr:full":"Howard St Nambour QLD 4560",
    "addr:postcode":"4560",
    "addr:street":"Howard St",
    "iso:country":"AU",
    "sg:address":"Howard St",
    "sg:city":"Nambour",
    "sg:classifiers":[
        {
            "category":"Personal",
            "subcategory":"Beauty Salon",
            "type":"Services"
        }
    ],
    "sg:phone":"+61 7 5441 7911",
    "sg:postcode":"4560",
    "sg:province":"QLD",
    "sg:tags":[
        "hairdresser"
    ],
    "wof:name":"Lea's Men's Hairstylist",
    "wof:placetype":"venue"
},
  "geometry": {"coordinates":[152.96955871599999,-26.6259117126],"type":"Point"}
}