{
  "type": "Feature",
  "properties": {
    "addr:full":"43 Slater Pde Keilor VIC 3036",
    "addr:housenumber":"43",
    "addr:postcode":"3036",
    "addr:street":"Slater Pde",
    "iso:country":"AU",
    "sg:address":"43 Slater Pde",
    "sg:city":"Keilor",
    "sg:classifiers":[
        {
            "category":"Manufacturing",
            "subcategory":"Tools & Machinery",
            "type":"Manufacturing & Wholesale Goods"
        }
    ],
    "sg:phone":"+61 3 9331 5955",
    "sg:postcode":"3036",
    "sg:province":"VIC",
    "sg:tags":[
        "earth",
        "excavating",
        "moving",
        "equipment"
    ],
    "wof:name":"William Adams Pty Ltd",
    "wof:placetype":"venue"
},
  "geometry": {"coordinates":[144.854095,-37.734959],"type":"Point"}
}