{
  "type": "Feature",
  "properties": {
    "addr:full":"Cnr Barber & Tempest Sts Gunnedah NSW 2380",
    "addr:postcode":"2380",
    "addr:street":"Sts",
    "iso:country":"AU",
    "sg:address":"Cnr Barber & Tempest Sts",
    "sg:city":"Gunnedah",
    "sg:classifiers":[
        {
            "category":"Manufacturing",
            "subcategory":"Motor Vehicles & Parts",
            "type":"Manufacturing & Wholesale Goods"
        }
    ],
    "sg:phone":"+61 2 6742 5178",
    "sg:postcode":"2380",
    "sg:province":"NSW",
    "sg:tags":[
        "replacement"
    ],
    "wof:name":"Gunnedah Auto Exhaust Specialists",
    "wof:placetype":"venue"
},
  "geometry": {"coordinates":[150.247848511,-30.9774456024],"type":"Point"}
}