{
  "type": "Feature",
  "properties": {
    "addr:full":"13 Martin St Port Pirie SA 5540",
    "addr:housenumber":"13",
    "addr:postcode":"5540",
    "addr:street":"Martin St",
    "iso:country":"AU",
    "sg:address":"13 Martin St",
    "sg:city":"Port Pirie",
    "sg:classifiers":[
        {
            "category":"Professional",
            "type":"Services"
        }
    ],
    "sg:phone":"+61 8 8632 1206",
    "sg:postcode":"5540",
    "sg:province":"SA",
    "sg:tags":[
        "courier"
    ],
    "wof:name":"Pirie Transport Co",
    "wof:placetype":"venue"
},
  "geometry": {"coordinates":[138.001785278,-33.2027397156],"type":"Point"}
}