{
  "type": "Feature",
  "properties": {
    "iso:country":"AU",
    "sg:address":"Goodearth Hotel, Lobby Level, 195",
    "sg:city":"Adelaide Tce Perth",
    "sg:classifiers":[
        {
            "category":"Personal",
            "subcategory":"Beauty Salon",
            "type":"Services"
        }
    ],
    "sg:phone":"+61 8 9221 1540",
    "sg:postcode":"6000",
    "sg:province":"WA",
    "wof:name":"Salon Antics Hair, Beauty, Spa",
    "wof:placetype":"venue"
},
  "geometry": {"coordinates":[115.869300842,-31.9590892792],"type":"Point"}
}