{
  "type": "Feature",
  "properties": {
    "addr:full":"21 Falcon St Narrogin WA 6312",
    "addr:housenumber":"21",
    "addr:postcode":"6312",
    "addr:street":"Falcon St",
    "iso:country":"AU",
    "sg:address":"21 Falcon St",
    "sg:city":"Narrogin",
    "sg:classifiers":[
        {
            "category":"Professional",
            "subcategory":"Secretarial Services",
            "type":"Services"
        }
    ],
    "sg:phone":"+61 8 9881 2824",
    "sg:postcode":"6312",
    "sg:province":"WA",
    "sg:tags":[
        "typing"
    ],
    "wof:name":"Dryandra Marketing & Secretarial Services",
    "wof:placetype":"venue"
},
  "geometry": {"coordinates":[117.175338745,-32.9369316101],"type":"Point"}
}