{
  "type": "Feature",
  "properties": {
    "addr:full":"236 Rokeby Rd Subiaco WA 6008",
    "addr:housenumber":"236",
    "addr:postcode":"6008",
    "addr:street":"Rokeby Rd",
    "iso:country":"AU",
    "sg:address":"236 Rokeby Rd",
    "sg:city":"Subiaco",
    "sg:classifiers":[
        {
            "category":"Real Estate",
            "subcategory":"Real Estate Services",
            "type":"Services"
        }
    ],
    "sg:phone":"+61 8 9381 2055",
    "sg:postcode":"6008",
    "sg:province":"WA",
    "sg:tags":[
        "auctioneer"
    ],
    "wof:name":"Michael & Wearne Real Estate",
    "wof:placetype":"venue"
},
  "geometry": {"coordinates":[115.82409668,-31.9519042969],"type":"Point"}
}