{
  "type": "Feature",
  "properties": {
    "addr:full":"508 High St Melton VIC 3337",
    "addr:housenumber":"508",
    "addr:postcode":"3337",
    "addr:street":"High St",
    "iso:country":"AU",
    "sg:address":"508 High St",
    "sg:city":"Melton",
    "sg:classifiers":[
        {
            "category":"Personal",
            "subcategory":"Beauty Salon",
            "type":"Services"
        }
    ],
    "sg:phone":"+61 3 9747 6888",
    "sg:postcode":"3337",
    "sg:province":"VIC",
    "wof:name":"Unique Day Spa",
    "wof:placetype":"venue"
},
  "geometry": {"coordinates":[144.56913800000001,-37.684113],"type":"Point"}
}