{
  "type": "Feature",
  "properties": {
    "addr:full":"1 Stewart St Windsor VIC 3181",
    "addr:housenumber":"1",
    "addr:postcode":"3181",
    "addr:street":"Stewart St",
    "iso:country":"AU",
    "sg:address":"1 Stewart St",
    "sg:city":"Windsor",
    "sg:classifiers":[
        {
            "category":"Retail",
            "subcategory":"Auto Rental",
            "type":"Services"
        }
    ],
    "sg:phone":"+61 3 9529 2222",
    "sg:postcode":"3181",
    "sg:province":"VIC",
    "sg:tags":[
        "home",
        "hire",
        "motor",
        "campervans"
    ],
    "wof:name":"Out-There Global Campers",
    "wof:placetype":"venue"
},
  "geometry": {"coordinates":[144.98875427199999,-37.8540306091],"type":"Point"}
}