{
  "type": "Feature",
  "properties": {
    "addr:full":"Shop 15 , Kiora Mall Miranda NSW 2228",
    "addr:housenumber":"shop 15",
    "addr:postcode":"2228",
    "addr:street":"Kiora Mall Miranda",
    "iso:country":"AU",
    "sg:address":"Shop 15",
    "sg:city":", Kiora Mall Miranda",
    "sg:classifiers":[
        {
            "category":"Health Services",
            "subcategory":"Dentist",
            "type":"Services"
        }
    ],
    "sg:phone":"+61 2 9531 1584",
    "sg:postcode":"2228",
    "sg:province":"NSW",
    "sg:tags":[
        "dental",
        "prosthetist"
    ],
    "wof:name":"Peter Kammerloher Denture Clinic",
    "wof:placetype":"venue"
},
  "geometry": {"coordinates":[151.10426330600001,-34.0312538147],"type":"Point"}
}