{
  "type": "Feature",
  "properties": {
    "iso:country":"AU",
    "sg:address":"PO Box 87",
    "sg:city":"Fairfield",
    "sg:classifiers":[
        {
            "category":"Professional",
            "subcategory":"Detective & Security Services",
            "type":"Services"
        }
    ],
    "sg:phone":"+61 417 725 700",
    "sg:postcode":"2165",
    "sg:province":"NSW",
    "sg:tags":[
        "consultant",
        "system"
    ],
    "wof:name":"V.P. Security Pty Ltd",
    "wof:placetype":"venue"
},
  "geometry": {"coordinates":[150.95323181099999,-33.8718490601],"type":"Point"}
}