{
  "type": "Feature",
  "properties": {
    "addr:full":"Shop 9 2 Star Rd Bright VIC 3741",
    "addr:housenumber":"shop;2",
    "addr:postcode":"3741",
    "addr:street":"Star Rd",
    "iso:country":"AU",
    "sg:address":"Shop 9 2 Star Rd",
    "sg:city":"Bright",
    "sg:classifiers":[
        {
            "category":"Social Services",
            "type":"Services"
        }
    ],
    "sg:phone":"+61 3 5750 1099",
    "sg:postcode":"3741",
    "sg:province":"VIC",
    "sg:tags":[
        "kinesiology"
    ],
    "wof:name":"Self Reflections",
    "wof:placetype":"venue"
},
  "geometry": {"coordinates":[146.96250900000001,-36.726734],"type":"Point"}
}