{
  "type": "Feature",
  "properties": {
    "iso:country":"AU",
    "sg:address":"Shop 10, Shepherd Court Shopping Centre, 365 Shepherds Hill Rd",
    "sg:city":"Blackwood",
    "sg:classifiers":[
        {
            "category":"Health Services",
            "subcategory":"Doctor",
            "type":"Services"
        }
    ],
    "sg:phone":"+61 8 8278 4100",
    "sg:postcode":"5051",
    "sg:province":"SA",
    "sg:tags":[
        "podiatrist"
    ],
    "wof:name":"Robert Perry",
    "wof:placetype":"venue"
},
  "geometry": {"coordinates":[138.614502,-35.021164],"type":"Point"}
}