{
  "type": "Feature",
  "properties": {
    "addr:full":"Cnr Kyogle & Union Sts South Lismore NSW 2480",
    "addr:postcode":"2480",
    "addr:street":"Cnr Kyogle &;Sts South",
    "iso:country":"AU",
    "sg:address":"Cnr Kyogle & Union Sts",
    "sg:city":"South Lismore",
    "sg:classifiers":[
        {
            "category":"Home & Garden",
            "subcategory":"Hardware",
            "type":"Retail Goods"
        }
    ],
    "sg:phone":"+61 2 6622 3000",
    "sg:postcode":"2480",
    "sg:province":"NSW",
    "sg:tags":[
        "battery",
        "dry",
        "rechargeable",
        "cell"
    ],
    "wof:name":"Northern Rivers Discount Batteries",
    "wof:placetype":"venue"
},
  "geometry": {"coordinates":[153.26724243199999,-28.8106803894],"type":"Point"}
}