{
  "type": "Feature",
  "properties": {
    "addr:full":"1167 Eumundi-Noosa Rd Eumundi QLD 4562",
    "addr:housenumber":"1167",
    "addr:postcode":"4562",
    "addr:street":"Eumundi-Noosa Rd",
    "iso:country":"AU",
    "sg:address":"1167 Eumundi-Noosa Rd",
    "sg:city":"Eumundi",
    "sg:classifiers":[
        {
            "category":"Professional",
            "subcategory":"Printing & Photocopies",
            "type":"Services"
        }
    ],
    "sg:phone":"+61 7 5449 1010",
    "sg:postcode":"4562",
    "sg:province":"QLD",
    "sg:tags":[
        "plaque"
    ],
    "wof:name":"J.J. Pilling",
    "wof:placetype":"venue"
},
  "geometry": {"coordinates":[152.95248413100001,-26.4728317261],"type":"Point"}
}