{
  "type": "Feature",
  "properties": {
    "addr:full":"Unit H, 134- 140 Old Pittwater Rd Brookvale NSW 2100",
    "addr:housenumber":"134 140",
    "addr:postcode":"2100",
    "addr:street":"H;Old Pittwater Rd",
    "iso:country":"AU",
    "sg:address":"Unit H, 134- 140 Old Pittwater Rd",
    "sg:city":"Brookvale",
    "sg:classifiers":[
        {
            "category":"Manufacturing",
            "subcategory":"Wood Products",
            "type":"Manufacturing & Wholesale Goods"
        }
    ],
    "sg:phone":"+61 2 9905 1544",
    "sg:postcode":"2100",
    "sg:province":"NSW",
    "sg:tags":[
        "pallet",
        "platform"
    ],
    "wof:name":"Eco Pak",
    "wof:placetype":"venue"
},
  "geometry": {"coordinates":[151.262405395,-33.7678451538],"type":"Point"}
}