{
  "type": "Feature",
  "properties": {
    "iso:country":"AU",
    "sg:address":"31 Woods Rd",
    "sg:city":"Yarrawonga",
    "sg:classifiers":[
        {
            "category":"Personal",
            "type":"Services"
        }
    ],
    "sg:phone":"+61 3 5743 2540",
    "sg:postcode":"3730",
    "sg:province":"VIC",
    "sg:tags":[
        "gift"
    ],
    "wof:name":"Poetry Factory, The",
    "wof:placetype":"venue"
},
  "geometry": {"coordinates":[146.0131073,-36.0114097595],"type":"Point"}
}