{
  "type": "Feature",
  "properties": {
    "addr:full":"Ste3/ 74 Old Barrenjoey Rd Avalon NSW 2107",
    "addr:housenumber":"74",
    "addr:postcode":"2107",
    "addr:street":"Old Barrenjoey Rd",
    "iso:country":"AU",
    "sg:address":"Ste3/ 74 Old Barrenjoey Rd",
    "sg:city":"Avalon",
    "sg:classifiers":[
        {
            "category":"Health Services",
            "subcategory":"Health Practitioner",
            "type":"Services"
        }
    ],
    "sg:phone":"+61 2 9918 2188",
    "sg:postcode":"2107",
    "sg:province":"NSW",
    "sg:tags":[
        "psychologist"
    ],
    "wof:name":"Peter Rossouw Dr",
    "wof:placetype":"venue"
},
  "geometry": {"coordinates":[151.32972717300001,-33.635974884],"type":"Point"}
}