{
  "type": "Feature",
  "properties": {
    "addr:full":"20 Sheridan St Bundaberg QLD 4670",
    "addr:housenumber":"20",
    "addr:postcode":"4670",
    "addr:street":"Sheridan St",
    "iso:country":"AU",
    "sg:address":"20 Sheridan St",
    "sg:city":"Bundaberg",
    "sg:classifiers":[
        {
            "category":"Commercial Area",
            "type":"Public Place"
        }
    ],
    "sg:phone":"+61 7 4152 2822",
    "sg:postcode":"4670",
    "sg:province":"QLD",
    "sg:tags":[
        "heavy",
        "carrier"
    ],
    "wof:name":"North Queensland Express",
    "wof:placetype":"venue"
},
  "geometry": {"coordinates":[152.37948608400001,-24.8630161285],"type":"Point"}
}