{
  "type": "Feature",
  "properties": {
    "addr:full":"U 1/ 572 Frankston-Dandenong Rd Carrum Downs VIC 3201",
    "addr:housenumber":"/ 572",
    "addr:postcode":"3201",
    "addr:street":"Frankston-Dandenong Rd",
    "iso:country":"AU",
    "sg:address":"U 1/ 572 Frankston-Dandenong Rd",
    "sg:city":"Carrum Downs",
    "sg:classifiers":[
        {
            "category":"Ferry Terminal",
            "type":"Transportation"
        }
    ],
    "sg:phone":"+61 3 9775 0992",
    "sg:postcode":"3201",
    "sg:province":"VIC",
    "sg:tags":[
        "mixing",
        "concrete",
        "vibrator",
        "equipment"
    ],
    "wof:name":"Brickies Shop The",
    "wof:placetype":"venue"
},
  "geometry": {"coordinates":[145.17198200000001,-38.099644],"type":"Point"}
}