{
  "type": "Feature",
  "properties": {
    "addr:full":"Jessop St Hamilton VIC 3300",
    "addr:postcode":"3300",
    "addr:street":"Jessop St",
    "iso:country":"AU",
    "sg:address":"Jessop St",
    "sg:city":"Hamilton",
    "sg:classifiers":[
        {
            "category":"Building & Trades",
            "subcategory":"Plumbing",
            "type":"Services"
        }
    ],
    "sg:phone":"+61 3 5572 5722",
    "sg:postcode":"3300",
    "sg:province":"VIC",
    "sg:tags":[
        "tool",
        "air",
        "accessory",
        "supply"
    ],
    "wof:name":"Antech Tool Repairs",
    "wof:placetype":"venue"
},
  "geometry": {"coordinates":[142.03408813499999,-37.7415771484],"type":"Point"}
}