{
  "type": "Feature",
  "properties": {
    "addr:full":"PO Box 299 South Grafton NSW 2460",
    "addr:postcode":"2460",
    "iso:country":"AU",
    "sg:address":"PO Box 299",
    "sg:city":"South Grafton",
    "sg:classifiers":[
        {
            "category":"Manufacturing",
            "subcategory":"Musical Instruments",
            "type":"Manufacturing & Wholesale Goods"
        }
    ],
    "sg:phone":"+61 2 6642 8600",
    "sg:postcode":"2460",
    "sg:province":"NSW",
    "sg:tags":[
        "logging",
        "timber"
    ],
    "wof:name":"Tableland Timbers",
    "wof:placetype":"venue"
},
  "geometry": {"coordinates":[152.942016602,-29.7072200775],"type":"Point"}
}