{
  "type": "Feature",
  "properties": {
    "addr:full":"Cnr Bridge & Erin Sts Wilsonton QLD 4350",
    "addr:postcode":"4350",
    "addr:street":"Cnr Bridge & Erin Sts",
    "iso:country":"AU",
    "sg:address":"Cnr Bridge & Erin Sts",
    "sg:city":"Wilsonton",
    "sg:classifiers":[
        {
            "category":"Fast Food",
            "type":"Food & Drink"
        }
    ],
    "sg:phone":"+61 7 4634 4640",
    "sg:postcode":"4350",
    "sg:province":"QLD",
    "sg:tags":[
        "away",
        "take"
    ],
    "wof:name":"KFC",
    "wof:placetype":"venue"
},
  "geometry": {"coordinates":[151.913376,-27.539141],"type":"Point"}
}