{
  "type": "Feature",
  "properties": {
    "iso:country":"AU",
    "sg:address":"82 Summer St",
    "sg:city":"Orange",
    "sg:classifiers":[
        {
            "category":"Real Estate",
            "subcategory":"Real Estate Agent",
            "type":"Services"
        }
    ],
    "sg:phone":"+61 2 6361 1134",
    "sg:postcode":"2800",
    "sg:province":"NSW",
    "wof:name":"Central West Properties and Invesments",
    "wof:placetype":"venue"
},
  "geometry": {"coordinates":[149.09483337399999,-33.2829742432],"type":"Point"}
}