{
  "type": "Feature",
  "properties": {
    "addr:full":"202 South St Ballarat VIC 3350",
    "addr:housenumber":"202",
    "addr:postcode":"3350",
    "addr:street":"South St",
    "iso:country":"AU",
    "sg:address":"202 South St",
    "sg:city":"Ballarat",
    "sg:classifiers":[
        {
            "category":"Shopping",
            "subcategory":"Clothing, Apparel, & Fashions",
            "type":"Retail Goods"
        }
    ],
    "sg:phone":"+61 3 5332 8300",
    "sg:postcode":"3350",
    "sg:province":"VIC",
    "sg:tags":[
        "recycled",
        "clothing"
    ],
    "wof:name":"De's Recycled Fashions",
    "wof:placetype":"venue"
},
  "geometry": {"coordinates":[143.85159300000001,-37.56995],"type":"Point"}
}