{
  "type": "Feature",
  "properties": {
    "addr:full":"Cnr Queenswharf Rd & King St Melbourne VIC 3000",
    "addr:postcode":"3000",
    "addr:street":"Cnr Queenswharf Rd & King St",
    "iso:country":"AU",
    "sg:address":"Cnr Queenswharf Rd & King St",
    "sg:city":"Melbourne",
    "sg:classifiers":[
        {
            "category":"Communications",
            "subcategory":"News Services",
            "type":"Services"
        }
    ],
    "sg:phone":"+61 3 9620 0999",
    "sg:postcode":"3000",
    "sg:province":"VIC",
    "sg:tags":[
        "information",
        "tourist",
        "attractions"
    ],
    "wof:name":"Melbourne Aquarium",
    "wof:placetype":"venue"
},
  "geometry": {"coordinates":[144.97027587900001,-37.8145599365],"type":"Point"}
}