{
  "type": "Feature",
  "properties": {
    "iso:country":"AU",
    "sg:address":"45 Andrew Rd St",
    "sg:city":"Albans",
    "sg:classifiers":[
        {
            "category":"Building & Trades",
            "subcategory":"Cleaning & Sanitation",
            "type":"Services"
        }
    ],
    "sg:phone":"+61 1300 139 650",
    "sg:postcode":"3021",
    "sg:province":"VIC",
    "sg:tags":[
        "asbestos",
        "treatment",
        "removal"
    ],
    "wof:name":"Australian Waterproof & Insulation Service",
    "wof:placetype":"venue"
},
  "geometry": {"coordinates":[144.783295,-37.735329],"type":"Point"}
}