{
  "type": "Feature",
  "properties": {
    "addr:full":"16 Birch Ave Dandenong North VIC 3175",
    "addr:housenumber":"16",
    "addr:postcode":"3175",
    "addr:street":"Birch Ave",
    "iso:country":"AU",
    "sg:address":"16 Birch Ave",
    "sg:city":"Dandenong North",
    "sg:classifiers":[
        {
            "category":"Organizations",
            "subcategory":"Professional Association",
            "type":"Services"
        }
    ],
    "sg:phone":"+61 3 9795 4205",
    "sg:postcode":"3175",
    "sg:province":"VIC",
    "sg:tags":[
        "web",
        "internet"
    ],
    "wof:name":"Blue Drop Computer Services",
    "wof:placetype":"venue"
},
  "geometry": {"coordinates":[145.20445251500001,-37.9637145996],"type":"Point"}
}