{
  "type": "Feature",
  "properties": {
    "iso:country":"AU",
    "sg:address":"Penn St",
    "sg:city":"South Mackay",
    "sg:classifiers":[
        {
            "category":"Education",
            "subcategory":"University",
            "type":"Public Place"
        }
    ],
    "sg:phone":"+61 7 4957 6048",
    "sg:postcode":"4740",
    "sg:province":"QLD",
    "sg:tags":[
        "college",
        "tertiary"
    ],
    "wof:name":"James Cook University (Mackay Campus)",
    "wof:placetype":"venue"
},
  "geometry": {"coordinates":[149.174866,-21.15414],"type":"Point"}
}