{
  "type": "Feature",
  "properties": {
    "iso:country":"AU",
    "sg:address":"7 Villiers Drv",
    "sg:city":"Currumbin",
    "sg:classifiers":[
        {
            "category":"Retail",
            "subcategory":"Storage",
            "type":"Services"
        }
    ],
    "sg:phone":"+61 1300 736 682",
    "sg:postcode":"4223",
    "sg:province":"QLD",
    "sg:tags":[
        "removal",
        "furniture"
    ],
    "wof:name":"1300 Removals",
    "wof:placetype":"venue"
},
  "geometry": {"coordinates":[153.47122192399999,-28.1506919861],"type":"Point"}
}