{
  "type": "Feature",
  "properties": {
    "addr:full":"99 - 109 Charles St Launceston TAS 7250",
    "addr:housenumber":"109",
    "addr:postcode":"7250",
    "addr:street":"99;Charles St",
    "iso:country":"AU",
    "sg:address":"99 - 109 Charles St",
    "sg:city":"Launceston",
    "sg:classifiers":[
        {
            "category":"Professional",
            "subcategory":"Printing & Photocopies",
            "type":"Services"
        }
    ],
    "sg:phone":"+61 3 6332 1400",
    "sg:postcode":"7250",
    "sg:province":"TAS",
    "sg:tags":[
        "publishing",
        "desktop"
    ],
    "wof:name":"Foot & Playsted Pty Ltd",
    "wof:placetype":"venue"
},
  "geometry": {"coordinates":[147.13659668,-41.4370384216],"type":"Point"}
}