{
  "type": "Feature",
  "properties": {
    "addr:full":"27a Mologa Rd Heidelberg West VIC 3081",
    "addr:housenumber":"27a",
    "addr:postcode":"3081",
    "addr:street":"Mologa Rd",
    "iso:country":"AU",
    "sg:address":"27a Mologa Rd",
    "sg:city":"Heidelberg West",
    "sg:classifiers":[
        {
            "category":"Wholesale",
            "subcategory":"Auto Parts",
            "type":"Manufacturing & Wholesale Goods"
        }
    ],
    "sg:phone":"+61 3 9458 5458",
    "sg:postcode":"3081",
    "sg:province":"VIC",
    "sg:tags":[
        "tyre"
    ],
    "wof:name":"Kerneys Tyres Pty Ltd",
    "wof:placetype":"venue"
},
  "geometry": {"coordinates":[145.048095703,-37.7325592041],"type":"Point"}
}