{
  "type": "Feature",
  "properties": {
    "addr:full":"Lot 23 Werribee Rd Wooroloo WA 6558",
    "addr:postcode":"6558",
    "addr:street":"Werribee Rd",
    "iso:country":"AU",
    "sg:address":"Lot 23 Werribee Rd",
    "sg:city":"Wooroloo",
    "sg:classifiers":[
        {
            "category":"Health Services",
            "subcategory":"Doctor",
            "type":"Services"
        }
    ],
    "sg:phone":"+61 8 9298 9774",
    "sg:postcode":"6558",
    "sg:province":"WA",
    "sg:tags":[
        "holiday",
        "retreat"
    ],
    "wof:name":"Hilltop Farm Retreat",
    "wof:placetype":"venue"
},
  "geometry": {"coordinates":[116.346420288,-31.7873573303],"type":"Point"}
}