{
  "type": "Feature",
  "properties": {
    "iso:country":"AU",
    "sg:address":"4/ 6 Oxford St",
    "sg:city":"Mittagong",
    "sg:classifiers":[
        {
            "category":"Education",
            "subcategory":"Special Training",
            "type":"Public Place"
        }
    ],
    "sg:phone":"+61 2 4872 3338",
    "sg:postcode":"2575",
    "sg:province":"NSW",
    "sg:tags":[
        "drama",
        "speech",
        "speaking",
        "tuition"
    ],
    "wof:name":"Joan Cowan School Of Drama",
    "wof:placetype":"venue"
},
  "geometry": {"coordinates":[150.44854736299999,-34.4566001892],"type":"Point"}
}