{
  "type": "Feature",
  "properties": {
    "iso:country":"AU",
    "sg:address":"King St",
    "sg:city":"Caboolture",
    "sg:classifiers":[
        {
            "category":"Personal",
            "subcategory":"Shoe Repair & Shine",
            "type":"Services"
        }
    ],
    "sg:phone":"+61 7 5498 3937",
    "sg:postcode":"4510",
    "sg:province":"QLD",
    "sg:tags":[
        "footwear"
    ],
    "wof:name":"Mister Minit Australia Pty Ltd",
    "wof:placetype":"venue"
},
  "geometry": {"coordinates":[152.952866,-27.084667],"type":"Point"}
}