{
  "type": "Feature",
  "properties": {
    "addr:full":"49 Anne St George Town TAS 7253",
    "addr:housenumber":"49;st",
    "addr:postcode":"7253",
    "addr:street":"Anne",
    "iso:country":"AU",
    "sg:address":"49 Anne St",
    "sg:city":"George Town",
    "sg:classifiers":[
        {
            "category":"Health Services",
            "subcategory":"Doctor",
            "type":"Services"
        }
    ],
    "sg:phone":"+61 3 6382 4333",
    "sg:postcode":"7253",
    "sg:province":"TAS",
    "sg:tags":[
        "medical",
        "practitioner"
    ],
    "wof:name":"Bowring B",
    "wof:placetype":"venue"
},
  "geometry": {"coordinates":[146.82168579099999,-41.1037368774],"type":"Point"}
}