{
  "type": "Feature",
  "properties": {
    "addr:full":"Unit 1A/ 16 Dellamarta Rd Wangara WA 6065",
    "addr:housenumber":"unit 1a / 16",
    "addr:postcode":"6065",
    "addr:street":"Dellamarta Rd",
    "iso:country":"AU",
    "sg:address":"Unit 1A/ 16 Dellamarta Rd",
    "sg:city":"Wangara",
    "sg:classifiers":[
        {
            "category":"Retail",
            "subcategory":"Driving School",
            "type":"Services"
        }
    ],
    "sg:phone":"+61 8 9309 9531",
    "sg:postcode":"6065",
    "sg:province":"WA",
    "wof:name":"Plant Operator Training (Aust) Pty Ltd",
    "wof:placetype":"venue"
},
  "geometry": {"coordinates":[115.81678771999999,-31.7890415192],"type":"Point"}
}