{
  "type": "Feature",
  "properties": {
    "addr:full":"19 Blaxland Rd Campbelltown NSW 2560",
    "addr:housenumber":"19",
    "addr:postcode":"2560",
    "addr:street":"Blaxland Rd",
    "iso:country":"AU",
    "sg:address":"19 Blaxland Rd",
    "sg:city":"Campbelltown",
    "sg:classifiers":[
        {
            "category":"Professional",
            "subcategory":"Printing & Photocopies",
            "type":"Services"
        }
    ],
    "sg:phone":"+61 2 4625 4389",
    "sg:postcode":"2560",
    "sg:province":"NSW",
    "sg:tags":[
        "trophy"
    ],
    "wof:name":"Campbelltown Trophies",
    "wof:placetype":"venue"
},
  "geometry": {"coordinates":[150.81640625,-34.0575714111],"type":"Point"}
}