{
  "type": "Feature",
  "properties": {
    "iso:country":"AU",
    "sg:address":"24 Talinga Pl",
    "sg:city":"Cherrybrook",
    "sg:classifiers":[
        {
            "category":"Farming",
            "subcategory":"Farm & Veterinary Services",
            "type":"Manufacturing & Wholesale Goods"
        }
    ],
    "sg:phone":"+61 2 9894 9505",
    "sg:postcode":"2126",
    "sg:province":"NSW",
    "sg:tags":[
        "blacksmith",
        "farrier"
    ],
    "wof:name":"Eddie Overs",
    "wof:placetype":"venue"
},
  "geometry": {"coordinates":[151.03070068400001,-33.726436615],"type":"Point"}
}