{
  "type": "Feature",
  "properties": {
    "addr:full":"627 Sydney Rd Brunswick VIC 3056",
    "addr:housenumber":"627",
    "addr:postcode":"3056",
    "addr:street":"Sydney Rd",
    "iso:country":"AU",
    "sg:address":"627 Sydney Rd",
    "sg:city":"Brunswick",
    "sg:classifiers":[
        {
            "category":"Manufacturing",
            "subcategory":"Food",
            "type":"Manufacturing & Wholesale Goods"
        }
    ],
    "sg:phone":"+61 3 9386 4147",
    "sg:postcode":"3056",
    "sg:province":"VIC",
    "sg:tags":[
        "function",
        "catering"
    ],
    "wof:name":"City Circle Catering",
    "wof:placetype":"venue"
},
  "geometry": {"coordinates":[144.962966919,-37.762878418],"type":"Point"}
}