{
  "type": "Feature",
  "properties": {
    "addr:full":"6 Woolmer Crt Croydon Hills VIC 3136",
    "addr:housenumber":"6",
    "addr:postcode":"3136",
    "addr:street":"Woolmer Crt",
    "iso:country":"AU",
    "sg:address":"6 Woolmer Crt",
    "sg:city":"Croydon Hills",
    "sg:classifiers":[
        {
            "category":"Insurance",
            "subcategory":"Title Insurance",
            "type":"Services"
        }
    ],
    "sg:phone":"+61 3 9876 6778",
    "sg:postcode":"3136",
    "sg:province":"VIC",
    "sg:tags":[
        "searcher"
    ],
    "wof:name":"N.U.A Searching",
    "wof:placetype":"venue"
},
  "geometry": {"coordinates":[145.259643555,-37.7787780762],"type":"Point"}
}