{
  "type": "Feature",
  "properties": {
    "iso:country":"AU",
    "sg:address":"6 Kew Crt",
    "sg:city":"Sheidow Park",
    "sg:classifiers":[
        {
            "category":"Personal",
            "subcategory":"Beauty Salon",
            "type":"Services"
        }
    ],
    "sg:phone":"+61 411 668 122",
    "sg:postcode":"5158",
    "sg:province":"SA",
    "sg:tags":[
        "supply",
        "artist",
        "make-up"
    ],
    "wof:name":"AJM Creative Faces",
    "wof:placetype":"venue"
},
  "geometry": {"coordinates":[138.53474426299999,-35.0779075623],"type":"Point"}
}