{
  "type": "Feature",
  "properties": {
    "addr:full":"Hassall St Parramatta NSW 2150",
    "addr:postcode":"2150",
    "addr:street":"Hassall St",
    "iso:country":"AU",
    "sg:address":"Hassall St",
    "sg:city":"Parramatta",
    "sg:classifiers":[
        {
            "category":"Education",
            "subcategory":"School",
            "type":"Public Place"
        }
    ],
    "sg:phone":"+61 2 9635 6363",
    "sg:postcode":"2150",
    "sg:province":"NSW",
    "sg:tags":[
        "state",
        "-",
        "nsw"
    ],
    "wof:name":"Rowland Hassall Public School For Specific Purposes",
    "wof:placetype":"venue"
},
  "geometry": {"coordinates":[151.00668335,-33.81483078],"type":"Point"}
}