{
  "type": "Feature",
  "properties": {
    "iso:country":"AU",
    "sg:address":"Level 3, 754 - 758 Pacific Hwy",
    "sg:city":"Chatswood",
    "sg:classifiers":[
        {
            "category":"Professional",
            "subcategory":"Lawyer & Legal Services",
            "type":"Services"
        }
    ],
    "sg:phone":"+61 1300 799 888",
    "sg:postcode":"2057",
    "sg:province":"NSW",
    "sg:tags":[
        "wills",
        "probate",
        "estate"
    ],
    "wof:name":"LAC Lawyers Pty Ltd",
    "wof:placetype":"venue"
},
  "geometry": {"coordinates":[151.178482,-33.794773],"type":"Point"}
}