{
  "type": "Feature",
  "properties": {
    "iso:country":"AU",
    "sg:address":"571 - 575 Boundary St",
    "sg:city":"Toowoomba",
    "sg:classifiers":[
        {
            "category":"Autos & Motor Vehicles",
            "subcategory":"Auto Supplies",
            "type":"Retail Goods"
        }
    ],
    "sg:phone":"+61 7 4634 0042",
    "sg:postcode":"4350",
    "sg:province":"QLD",
    "sg:tags":[
        "equipment",
        "part",
        "truck"
    ],
    "sg:website":"http://www.truckwreckers.com/toowoombatruck/",
    "wof:name":"Toowoomba Truck Wreckers",
    "wof:placetype":"venue"
},
  "geometry": {"coordinates":[151.901505,-27.555523],"type":"Point"}
}