{
  "type": "Feature",
  "properties": {
    "iso:country":"AU",
    "sg:address":"42 Sydney Rd",
    "sg:city":"Manly",
    "sg:classifiers":[
        {
            "category":"Health Services",
            "subcategory":"Optometrist",
            "type":"Services"
        }
    ],
    "sg:phone":"+61 2 9977 4923",
    "sg:postcode":"2095",
    "sg:province":"NSW",
    "wof:name":"Ryman Leslie A W, Woodhouse Melanie",
    "wof:placetype":"venue"
},
  "geometry": {"coordinates":[151.28623962399999,-33.7969398499],"type":"Point"}
}