{
  "type": "Feature",
  "properties": {
    "addr:full":"251 Bird Rd Guanaba QLD 4210",
    "addr:housenumber":"251",
    "addr:postcode":"4210",
    "addr:street":"Bird Rd",
    "iso:country":"AU",
    "sg:address":"251 Bird Rd",
    "sg:city":"Guanaba",
    "sg:classifiers":[
        {
            "category":"Home & Garden",
            "subcategory":"Carpets & Floor Coverings",
            "type":"Retail Goods"
        }
    ],
    "sg:phone":"+61 7 5533 2759",
    "sg:postcode":"4210",
    "sg:province":"QLD",
    "sg:tags":[
        "tile",
        "wall",
        "layer"
    ],
    "wof:name":"Campbell Tiling",
    "wof:placetype":"venue"
},
  "geometry": {"coordinates":[153.260620117,-27.9272766113],"type":"Point"}
}