{
  "type": "Feature",
  "properties": {
    "iso:country":"AU",
    "sg:address":"Dick Ward Drv",
    "sg:city":"Coconut Grove",
    "sg:classifiers":[
        {
            "category":"Manufacturing",
            "subcategory":"Glass & Minerals",
            "type":"Manufacturing & Wholesale Goods"
        }
    ],
    "sg:phone":"+61 8 8948 1448",
    "sg:postcode":"0810",
    "sg:province":"NT",
    "sg:tags":[
        "stained"
    ],
    "wof:name":"CraftMarriott",
    "wof:placetype":"venue"
},
  "geometry": {"coordinates":[130.852294922,-12.3901700974],"type":"Point"}
}