{
  "type": "Feature",
  "properties": {
    "addr:full":"121 Cox Ave Kingswood NSW 2747",
    "addr:housenumber":"121",
    "addr:postcode":"2747",
    "addr:street":"Cox Ave",
    "iso:country":"AU",
    "sg:address":"121 Cox Ave",
    "sg:city":"Kingswood",
    "sg:classifiers":[
        {
            "category":"Autos & Motor Vehicles",
            "subcategory":"Automobile Sales",
            "type":"Retail Goods"
        }
    ],
    "sg:phone":"+61 2 4731 6632",
    "sg:postcode":"2747",
    "sg:province":"NSW",
    "sg:tags":[
        "car",
        "used"
    ],
    "wof:name":"Grand Prix Motors",
    "wof:placetype":"venue"
},
  "geometry": {"coordinates":[150.71284484899999,-33.7555999756],"type":"Point"}
}