{
  "type": "Feature",
  "properties": {
    "addr:full":"232 Boorowa St Young NSW 2594",
    "addr:housenumber":"232",
    "addr:postcode":"2594",
    "addr:street":"Boorowa St",
    "iso:country":"AU",
    "sg:address":"232 Boorowa St",
    "sg:city":"Young",
    "sg:classifiers":[
        {
            "category":"Shopping",
            "type":"Retail Goods"
        }
    ],
    "sg:phone":"+61 2 6382 1800",
    "sg:postcode":"2594",
    "sg:province":"NSW",
    "sg:tags":[
        "agent",
        "stock"
    ],
    "wof:name":"Elders Limited Merchandising",
    "wof:placetype":"venue"
},
  "geometry": {"coordinates":[148.293167114,-34.3125267029],"type":"Point"}
}