{
  "type": "Feature",
  "properties": {
    "iso:country":"AU",
    "sg:address":"Shop 2/ 12 Tingira Crs",
    "sg:city":"Kiama",
    "sg:classifiers":[
        {
            "category":"Personal",
            "subcategory":"Beauty Salon",
            "type":"Services"
        }
    ],
    "sg:phone":"+61 2 4232 1771",
    "sg:postcode":"2533",
    "sg:province":"NSW",
    "sg:tags":[
        "hairdresser"
    ],
    "wof:name":"Destiny Hair & Beauty",
    "wof:placetype":"venue"
},
  "geometry": {"coordinates":[150.85409545900001,-34.6723861694],"type":"Point"}
}