{
  "type": "Feature",
  "properties": {
    "addr:full":"Suite 5, Hillcrest Rd Pennant Hills NSW 2120",
    "addr:postcode":"2120",
    "addr:street":"Hillcrest Rd",
    "iso:country":"AU",
    "sg:address":"Suite 5, Hillcrest Rd",
    "sg:city":"Pennant Hills",
    "sg:classifiers":[
        {
            "category":"Health Services",
            "subcategory":"Dentist",
            "type":"Services"
        }
    ],
    "sg:phone":"+61 2 9980 1999",
    "sg:postcode":"2120",
    "sg:province":"NSW",
    "wof:name":"Topgum",
    "wof:placetype":"venue"
},
  "geometry": {"coordinates":[151.070602417,-33.7382469177],"type":"Point"}
}