{
  "type": "Feature",
  "properties": {
    "addr:full":"Roadside Mail Box 2077+ Cowes VIC 3922",
    "addr:postcode":"3922",
    "iso:country":"AU",
    "sg:address":"Roadside Mail Box 2077+",
    "sg:city":"Cowes",
    "sg:classifiers":[
        {
            "category":"Professional",
            "subcategory":"Art Services",
            "type":"Services"
        }
    ],
    "sg:phone":"+61 3 5956 8594",
    "sg:postcode":"3922",
    "sg:province":"VIC",
    "sg:tags":[
        "artist"
    ],
    "wof:name":"Island Influence",
    "wof:placetype":"venue"
},
  "geometry": {"coordinates":[145.23898315400001,-38.4565200806],"type":"Point"}
}