{
  "type": "Feature",
  "properties": {
    "addr:full":"1 Mt Pleasant Ave Mona Vale NSW 2103",
    "addr:housenumber":"1",
    "addr:postcode":"2103",
    "addr:street":"Mt Pleasant Ave",
    "iso:country":"AU",
    "sg:address":"1 Mt Pleasant Ave",
    "sg:city":"Mona Vale",
    "sg:classifiers":[
        {
            "category":"Building & Trades",
            "subcategory":"Construction",
            "type":"Services"
        }
    ],
    "sg:phone":"+61 2 9940 0672",
    "sg:postcode":"2103",
    "sg:province":"NSW",
    "sg:tags":[
        "renovation",
        "alterations",
        "extension",
        "contractor"
    ],
    "wof:name":"Sure Wood Work",
    "wof:placetype":"venue"
},
  "geometry": {"coordinates":[151.311843872,-33.6729698181],"type":"Point"}
}