{
  "type": "Feature",
  "properties": {
    "iso:country":"AU",
    "sg:address":"33 Kewdale Rd",
    "sg:city":"Kewdale",
    "sg:classifiers":[
        {
            "category":"Professional",
            "subcategory":"Engineering",
            "type":"Services"
        }
    ],
    "sg:phone":"+61 8 9351 3300",
    "sg:postcode":"6105",
    "sg:province":"WA",
    "sg:tags":[
        "engineer",
        "mechanical"
    ],
    "wof:name":"Stork ICM",
    "wof:placetype":"venue"
},
  "geometry": {"coordinates":[115.954650879,-31.9842777252],"type":"Point"}
}