{
  "type": "Feature",
  "properties": {
    "addr:full":"66 Wigmore Drv Bathurst NSW 2795",
    "addr:housenumber":"66",
    "addr:postcode":"2795",
    "addr:street":"Wigmore Drv",
    "iso:country":"AU",
    "sg:address":"66 Wigmore Drv",
    "sg:city":"Bathurst",
    "sg:classifiers":[
        {
            "category":"Wholesale",
            "subcategory":"Painting Supplies",
            "type":"Manufacturing & Wholesale Goods"
        }
    ],
    "sg:phone":"+61 419 248 452",
    "sg:postcode":"2795",
    "sg:province":"NSW",
    "sg:tags":[
        "painter"
    ],
    "wof:name":"David Catt Spray Repair",
    "wof:placetype":"venue"
},
  "geometry": {"coordinates":[149.53927612300001,-33.4213905334],"type":"Point"}
}