{
  "type": "Feature",
  "properties": {
    "addr:full":"1 surfside Ave Clovelly NSW 2031",
    "addr:housenumber":"1",
    "addr:postcode":"2031",
    "addr:street":"Surfside Ave",
    "iso:country":"AU",
    "sg:address":"1 surfside Ave",
    "sg:city":"Clovelly",
    "sg:classifiers":[
        {
            "category":"Building & Trades",
            "subcategory":"Equipment Rental",
            "type":"Services"
        }
    ],
    "sg:phone":"+61 413 167 541",
    "sg:postcode":"2031",
    "sg:province":"NSW",
    "sg:tags":[
        "demolition",
        "contractor"
    ],
    "wof:name":"AL HAJJ EXCAVATIONS",
    "wof:placetype":"venue"
},
  "geometry": {"coordinates":[151.26380920400001,-33.911819458],"type":"Point"}
}