{
  "type": "Feature",
  "properties": {
    "addr:full":"54 Bungil St Roma QLD 4455",
    "addr:housenumber":"54",
    "addr:postcode":"4455",
    "addr:street":"Bungil St",
    "iso:country":"AU",
    "sg:address":"54 Bungil St",
    "sg:city":"Roma",
    "sg:classifiers":[
        {
            "category":"Wholesale",
            "subcategory":"Machinery & Supplies",
            "type":"Manufacturing & Wholesale Goods"
        }
    ],
    "sg:phone":"+61 7 4622 3122",
    "sg:postcode":"4455",
    "sg:province":"QLD",
    "sg:tags":[
        "engine",
        "petrol"
    ],
    "wof:name":"Roma Mower Centre",
    "wof:placetype":"venue"
},
  "geometry": {"coordinates":[148.788406372,-26.5694675446],"type":"Point"}
}