{
  "type": "Feature",
  "properties": {
    "addr:full":"13 Lombard Pl Prospect NSW 2148",
    "addr:housenumber":"13",
    "addr:postcode":"2148",
    "addr:street":"Pl",
    "iso:country":"AU",
    "sg:address":"13 Lombard Pl",
    "sg:city":"Prospect",
    "sg:classifiers":[
        {
            "category":"Professional",
            "subcategory":"Computer Services",
            "type":"Services"
        }
    ],
    "sg:phone":"+61 2 9671 6016",
    "sg:postcode":"2148",
    "sg:province":"NSW",
    "sg:tags":[
        "consultant",
        "system"
    ],
    "wof:name":"Podger Consultants Pty Ltd",
    "wof:placetype":"venue"
},
  "geometry": {"coordinates":[150.922897339,-33.7974243164],"type":"Point"}
}