{
  "type": "Feature",
  "properties": {
    "iso:country":"AU",
    "sg:address":"175 Through Rd",
    "sg:city":"Burwood",
    "sg:classifiers":[
        {
            "category":"Manufacturing",
            "subcategory":"Food",
            "type":"Manufacturing & Wholesale Goods"
        }
    ],
    "sg:phone":"+61 3 9836 6385",
    "sg:postcode":"3125",
    "sg:province":"VIC",
    "sg:tags":[
        "function",
        "catering"
    ],
    "wof:name":"Through Road Pantry",
    "wof:placetype":"venue"
},
  "geometry": {"coordinates":[145.09342956500001,-37.8363037109],"type":"Point"}
}