{
  "type": "Feature",
  "properties": {
    "addr:full":"153 Lake St Cairns QLD 4870",
    "addr:housenumber":"153",
    "addr:postcode":"4870",
    "addr:street":"Lake St",
    "iso:country":"AU",
    "sg:address":"153 Lake St",
    "sg:city":"Cairns",
    "sg:classifiers":[
        {
            "category":"Retail",
            "subcategory":"Auto Rental",
            "type":"Services"
        }
    ],
    "sg:phone":"+61 7 4051 9222",
    "sg:postcode":"4870",
    "sg:province":"QLD",
    "sg:tags":[
        "car",
        "hire",
        "minibus"
    ],
    "wof:name":"Budget Car & Truck Rental",
    "wof:placetype":"venue"
},
  "geometry": {"coordinates":[145.773147583,-16.9192218781],"type":"Point"}
}