{
  "type": "Feature",
  "properties": {
    "addr:full":"Shop 3/ Albion Park Village Albion Park NSW 2527",
    "addr:housenumber":"shop 3 / albion",
    "addr:postcode":"2527",
    "iso:country":"AU",
    "sg:address":"Shop 3/ Albion Park Village",
    "sg:city":"Albion Park",
    "sg:classifiers":[
        {
            "category":"Shopping",
            "subcategory":"Clothing, Apparel, & Fashions",
            "type":"Retail Goods"
        }
    ],
    "sg:phone":"+61 2 4257 3814",
    "sg:postcode":"2527",
    "sg:province":"NSW",
    "sg:tags":[
        "lady",
        "wear"
    ],
    "wof:name":"Miller's Fashion Club",
    "wof:placetype":"venue"
},
  "geometry": {"coordinates":[150.777511597,-34.5793991089],"type":"Point"}
}