{
  "type": "Feature",
  "properties": {
    "addr:full":"11 Point Pde Congo NSW 2537",
    "addr:housenumber":"11",
    "addr:postcode":"2537",
    "addr:street":"Point Pde",
    "iso:country":"AU",
    "sg:address":"11 Point Pde",
    "sg:city":"Congo",
    "sg:classifiers":[
        {
            "category":"Professional",
            "type":"Services"
        }
    ],
    "sg:phone":"+61 2 4474 2886",
    "sg:postcode":"2537",
    "sg:province":"NSW",
    "sg:tags":[
        "quality",
        "assurance"
    ],
    "wof:name":"Green & Douglass Consultants",
    "wof:placetype":"venue"
},
  "geometry": {"coordinates":[150.15335082999999,-35.9581336975],"type":"Point"}
}