{
  "type": "Feature",
  "properties": {
    "addr:full":"120 Koornang Rd Carnegie VIC 3163",
    "addr:housenumber":"120",
    "addr:postcode":"3163",
    "addr:street":"Koornang Rd",
    "iso:country":"AU",
    "sg:address":"120 Koornang Rd",
    "sg:city":"Carnegie",
    "sg:classifiers":[
        {
            "category":"Shopping",
            "subcategory":"Shoes",
            "type":"Retail Goods"
        }
    ],
    "sg:phone":"+61 3 9568 5346",
    "sg:postcode":"3163",
    "sg:province":"VIC",
    "sg:tags":[
        "footwear"
    ],
    "wof:name":"Colliers Shoes",
    "wof:placetype":"venue"
},
  "geometry": {"coordinates":[145.057403564,-37.8882904053],"type":"Point"}
}