{
  "type": "Feature",
  "properties": {
    "addr:full":"63 Hoskins Ave Bankstown NSW 2200",
    "addr:housenumber":"63",
    "addr:postcode":"2200",
    "addr:street":"Hoskins Ave",
    "iso:country":"AU",
    "sg:address":"63 Hoskins Ave",
    "sg:city":"Bankstown",
    "sg:classifiers":[
        {
            "category":"Building & Trades",
            "subcategory":"Plumbing",
            "type":"Services"
        }
    ],
    "sg:phone":"+61 2 9708 2044",
    "sg:postcode":"2200",
    "sg:province":"NSW",
    "sg:tags":[
        "equipment",
        "valves"
    ],
    "wof:name":"Afcos Pty Ltd",
    "wof:placetype":"venue"
},
  "geometry": {"coordinates":[151.034775,-33.931568],"type":"Point"}
}