{
  "type": "Feature",
  "properties": {
    "iso:country":"AU",
    "sg:address":"225 Bourke St",
    "sg:city":"Melbourne",
    "sg:classifiers":[
        {
            "category":"Cafe",
            "type":"Food & Drink"
        }
    ],
    "sg:phone":"+61 3 9663 3944",
    "sg:postcode":"3000",
    "sg:province":"VIC",
    "wof:name":"Sweet Mama's Cafe",
    "wof:placetype":"venue"
},
  "geometry": {"coordinates":[144.96705627399999,-37.8132362366],"type":"Point"}
}