{
  "type": "Feature",
  "properties": {
    "addr:full":"446 Gaffney St Pascoe Vale VIC 3044",
    "addr:housenumber":"446",
    "addr:postcode":"3044",
    "addr:street":"Gaffney St",
    "iso:country":"AU",
    "sg:address":"446 Gaffney St",
    "sg:city":"Pascoe Vale",
    "sg:classifiers":[
        {
            "category":"Health Services",
            "subcategory":"Health Practitioner",
            "type":"Services"
        }
    ],
    "sg:phone":"+61 404 242 509",
    "sg:postcode":"3044",
    "sg:province":"VIC",
    "sg:tags":[
        "naturopath"
    ],
    "wof:name":"Natalja Pavnovic",
    "wof:placetype":"venue"
},
  "geometry": {"coordinates":[144.927856445,-37.7302284241],"type":"Point"}
}