{
  "type": "Feature",
  "properties": {
    "addr:full":"33 Main South Rd Reynella SA 5161",
    "addr:housenumber":"33",
    "addr:postcode":"5161",
    "addr:street":"Main South Rd",
    "iso:country":"AU",
    "sg:address":"33 Main South Rd",
    "sg:city":"Reynella",
    "sg:classifiers":[
        {
            "category":"Government",
            "subcategory":"Customs House",
            "type":"Public Place"
        }
    ],
    "sg:phone":"+61 8 8381 1111",
    "sg:postcode":"5161",
    "sg:province":"SA",
    "sg:tags":[
        "title",
        "management",
        "stratum"
    ],
    "wof:name":"Century 21 M.F. Paterson",
    "wof:placetype":"venue"
},
  "geometry": {"coordinates":[138.53135681099999,-35.1005249023],"type":"Point"}
}