{
  "type": "Feature",
  "properties": {
    "addr:full":"Corner Fowler & Hassall St Hamilton NSW 2303",
    "addr:postcode":"2303",
    "addr:street":"St",
    "iso:country":"AU",
    "sg:address":"Corner Fowler & Hassall St",
    "sg:city":"Hamilton",
    "sg:classifiers":[
        {
            "category":"Food & Beverages",
            "subcategory":"Liquor & Beverages",
            "type":"Retail Goods"
        }
    ],
    "sg:phone":"+61 2 4961 1822",
    "sg:postcode":"2303",
    "sg:province":"NSW",
    "sg:tags":[
        "store"
    ],
    "wof:name":"Diggers Bottleshop",
    "wof:placetype":"venue"
},
  "geometry": {"coordinates":[151.73791499999999,-32.933208],"type":"Point"}
}