{
  "type": "Feature",
  "properties": {
    "addr:full":"6-12 Atchinson St St Leonards NSW 2065",
    "addr:housenumber":"6-12",
    "addr:postcode":"2065",
    "addr:street":"Atchinson St",
    "iso:country":"AU",
    "sg:address":"6-12 Atchinson St",
    "sg:city":"St Leonards",
    "sg:classifiers":[
        {
            "category":"Organizations",
            "subcategory":"Professional Association",
            "type":"Services"
        }
    ],
    "sg:phone":"+61 2 9935 7900",
    "sg:postcode":"2065",
    "sg:province":"NSW",
    "sg:tags":[
        "organisation",
        "business"
    ],
    "wof:name":"Australasian Performing Right Association Ltd",
    "wof:placetype":"venue"
},
  "geometry": {"coordinates":[151.196243286,-33.8227577209],"type":"Point"}
}