{
  "type": "Feature",
  "properties": {
    "addr:full":"59a Central Ave Oak Flats NSW 2529",
    "addr:housenumber":"59a",
    "addr:postcode":"2529",
    "addr:street":"Central Ave Oak Flats",
    "iso:country":"AU",
    "sg:address":"59a Central Ave",
    "sg:city":"Oak Flats",
    "sg:classifiers":[
        {
            "category":"Retail",
            "subcategory":"Repair Shop",
            "type":"Services"
        }
    ],
    "sg:phone":"+61 2 4256 4266",
    "sg:postcode":"2529",
    "sg:province":"NSW",
    "sg:tags":[
        "machine",
        "repairs",
        "part",
        "dryer",
        "washing"
    ],
    "wof:name":"Affordable Appliance Alternatives",
    "wof:placetype":"venue"
},
  "geometry": {"coordinates":[150.819122314,-34.5643501282],"type":"Point"}
}