{
  "type": "Feature",
  "properties": {
    "iso:country":"AU",
    "sg:address":"168 Main St",
    "sg:city":"Lilydale",
    "sg:classifiers":[
        {
            "category":"Shopping",
            "subcategory":"Clothing, Apparel, & Fashions",
            "type":"Retail Goods"
        }
    ],
    "sg:phone":"+61 3 9735 1136",
    "sg:postcode":"3140",
    "sg:province":"VIC",
    "sg:tags":[
        "hire",
        "men's",
        "wear",
        "formal"
    ],
    "wof:name":"Trevor Dudleys Mens & Boys Wear",
    "wof:placetype":"venue"
},
  "geometry": {"coordinates":[145.347366333,-37.7572517395],"type":"Point"}
}