{
  "type": "Feature",
  "properties": {
    "addr:full":"9 Dungogie Drv Tallebudgera QLD 4228",
    "addr:housenumber":"9",
    "addr:postcode":"4228",
    "addr:street":"Dungogie Drv",
    "iso:country":"AU",
    "sg:address":"9 Dungogie Drv",
    "sg:city":"Tallebudgera",
    "sg:classifiers":[
        {
            "category":"Building & Trades",
            "subcategory":"Construction",
            "type":"Services"
        }
    ],
    "sg:phone":"+61 7 5533 9569",
    "sg:postcode":"4228",
    "sg:province":"QLD",
    "sg:tags":[
        "contractor"
    ],
    "wof:name":"Ces Stevens",
    "wof:placetype":"venue"
},
  "geometry": {"coordinates":[153.42611694300001,-28.1499004364],"type":"Point"}
}