{
  "type": "Feature",
  "properties": {
    "addr:full":"3 Felspar St Welshpool WA 6106",
    "addr:housenumber":"3",
    "addr:postcode":"6106",
    "addr:street":"Felspar St",
    "iso:country":"AU",
    "sg:address":"3 Felspar St",
    "sg:city":"Welshpool",
    "sg:classifiers":[
        {
            "category":"Utilities",
            "subcategory":"Refuse",
            "type":"Services"
        }
    ],
    "sg:phone":"+61 8 9358 1111",
    "sg:postcode":"6106",
    "sg:province":"WA",
    "sg:tags":[
        "remover",
        "rubbish"
    ],
    "wof:name":"Stericorp Limited",
    "wof:placetype":"venue"
},
  "geometry": {"coordinates":[115.970077515,-32.0015487671],"type":"Point"}
}