{
  "type": "Feature",
  "properties": {
    "iso:country":"AU",
    "sg:address":"37 Railway Rd",
    "sg:city":"New Lambton",
    "sg:classifiers":[
        {
            "category":"Education",
            "subcategory":"Music School",
            "type":"Public Place"
        }
    ],
    "sg:phone":"+61 2 4952 2950",
    "sg:postcode":"2305",
    "sg:province":"NSW",
    "sg:tags":[
        "teacher"
    ],
    "wof:name":"Abbandono",
    "wof:placetype":"venue"
},
  "geometry": {"coordinates":[151.707596,-32.919426],"type":"Point"}
}