{
  "type": "Feature",
  "properties": {
    "addr:full":"16 Hill St Emu Park QLD 4702",
    "addr:housenumber":"16",
    "addr:postcode":"4702",
    "addr:street":"Hill St",
    "iso:country":"AU",
    "sg:address":"16 Hill St",
    "sg:city":"Emu Park",
    "sg:classifiers":[
        {
            "category":"Food & Beverages",
            "subcategory":"Fruits & Vegetables",
            "type":"Retail Goods"
        }
    ],
    "sg:phone":"+61 7 4939 6280",
    "sg:postcode":"4702",
    "sg:province":"QLD",
    "sg:tags":[
        "greengrocer",
        "fruiterer"
    ],
    "wof:name":"Charlie's Corner",
    "wof:placetype":"venue"
},
  "geometry": {"coordinates":[150.329147339,-23.4824829102],"type":"Point"}
}