{
  "type": "Feature",
  "properties": {
    "addr:full":"PO Box 1310 Camberwell VIC 3124",
    "addr:postcode":"3124",
    "iso:country":"AU",
    "sg:address":"PO Box 1310",
    "sg:city":"Camberwell",
    "sg:classifiers":[
        {
            "category":"Building & Trades",
            "subcategory":"Cleaning & Sanitation",
            "type":"Services"
        }
    ],
    "sg:phone":"+61 419 345 274",
    "sg:postcode":"3124",
    "sg:province":"VIC",
    "sg:tags":[
        "window"
    ],
    "wof:name":"Kevs Window Cleaning",
    "wof:placetype":"venue"
},
  "geometry": {"coordinates":[145.07565307600001,-37.8356399536],"type":"Point"}
}