{
  "type": "Feature",
  "properties": {
    "addr:full":"37 Archer St Rockhampton QLD 4700",
    "addr:housenumber":"37",
    "addr:postcode":"4700",
    "addr:street":"Archer St",
    "iso:country":"AU",
    "sg:address":"37 Archer St",
    "sg:city":"Rockhampton",
    "sg:classifiers":[
        {
            "category":"Building & Trades",
            "subcategory":"Construction",
            "type":"Services"
        }
    ],
    "sg:phone":"+61 7 4922 4450",
    "sg:postcode":"4700",
    "sg:province":"QLD",
    "sg:tags":[
        "window",
        "tinting"
    ],
    "wof:name":"Select-A-Tint",
    "wof:placetype":"venue"
},
  "geometry": {"coordinates":[150.495361328,-23.3846263885],"type":"Point"}
}