{
  "type": "Feature",
  "properties": {
    "addr:full":"54 Flinders St Darlinghurst NSW 2010",
    "addr:housenumber":"54",
    "addr:postcode":"2010",
    "addr:street":"Flinders St",
    "iso:country":"AU",
    "sg:address":"54 Flinders St",
    "sg:city":"Darlinghurst",
    "sg:classifiers":[
        {
            "category":"Real Estate",
            "subcategory":"Architect",
            "type":"Services"
        }
    ],
    "sg:phone":"+61 2 9360 6066",
    "sg:postcode":"2010",
    "sg:province":"NSW",
    "wof:name":"John Barker & Partners",
    "wof:placetype":"venue"
},
  "geometry": {"coordinates":[151.21751403799999,-33.8823204041],"type":"Point"}
}