{
  "type": "Feature",
  "properties": {
    "iso:country":"AU",
    "sg:address":"4 Allen St",
    "sg:city":"Moffat Beach",
    "sg:classifiers":[
        {
            "category":"Manufacturing",
            "subcategory":"Watercraft",
            "type":"Manufacturing & Wholesale Goods"
        }
    ],
    "sg:phone":"+61 7 5492 8220",
    "sg:postcode":"4551",
    "sg:province":"QLD",
    "sg:tags":[
        "sail",
        "marine",
        "maker"
    ],
    "wof:name":"Ullman Sails",
    "wof:placetype":"venue"
},
  "geometry": {"coordinates":[153.13519287099999,-26.7924156189],"type":"Point"}
}