{
  "type": "Feature",
  "properties": {
    "iso:country":"AU",
    "sg:address":"35 Hutchinsons Rd",
    "sg:city":"Bonnie Doon",
    "sg:classifiers":[
        {
            "category":"Building & Trades",
            "subcategory":"Plumbing",
            "type":"Services"
        }
    ],
    "sg:phone":"+61 3 5778 7262",
    "sg:postcode":"3720",
    "sg:province":"VIC",
    "sg:tags":[
        "plumber",
        "gasfitters"
    ],
    "wof:name":"Purcell Plumbing",
    "wof:placetype":"venue"
},
  "geometry": {"coordinates":[145.88084411599999,-37.0273513794],"type":"Point"}
}