{
  "type": "Feature",
  "properties": {
    "iso:country":"AU",
    "sg:address":"146 Deniliquin St",
    "sg:city":"Tocumwal",
    "sg:classifiers":[
        {
            "category":"Ice Cream",
            "type":"Food & Drink"
        }
    ],
    "sg:phone":"+61 3 5874 3166",
    "sg:postcode":"2714",
    "sg:province":"NSW",
    "sg:tags":[
        "retail"
    ],
    "wof:name":"Lime Spider",
    "wof:placetype":"venue"
},
  "geometry": {"coordinates":[145.57737731899999,-35.8112564087],"type":"Point"}
}