{
  "type": "Feature",
  "properties": {
    "addr:full":"Unit 2/ 18 Main St Osborne Park WA 6017",
    "addr:housenumber":"18",
    "addr:postcode":"6017",
    "addr:street":"Main St",
    "iso:country":"AU",
    "sg:address":"Unit 2/ 18 Main St",
    "sg:city":"Osborne Park",
    "sg:classifiers":[
        {
            "category":"Personal",
            "type":"Services"
        }
    ],
    "sg:phone":"+61 8 9443 2500",
    "sg:postcode":"6017",
    "sg:province":"WA",
    "sg:tags":[
        "gift"
    ],
    "wof:name":"Dial-A-Basket",
    "wof:placetype":"venue"
},
  "geometry": {"coordinates":[115.828330994,-31.9126186371],"type":"Point"}
}