{
  "type": "Feature",
  "properties": {
    "iso:country":"AU",
    "sg:address":"17 Gentle Rd",
    "sg:city":"Medina",
    "sg:classifiers":[
        {
            "category":"Manufacturing",
            "subcategory":"Metals",
            "type":"Manufacturing & Wholesale Goods"
        }
    ],
    "sg:phone":"+61 8 9419 1011",
    "sg:postcode":"6167",
    "sg:province":"WA",
    "sg:tags":[
        "sheet",
        "worker"
    ],
    "wof:name":"Kwinana Insulation & Sheet Metal Co",
    "wof:placetype":"venue"
},
  "geometry": {"coordinates":[115.799339,-32.240692],"type":"Point"}
}