{
  "type": "Feature",
  "properties": {
    "iso:country":"AU",
    "sg:address":"177 Beaconsfield Pde",
    "sg:city":"Middle Park",
    "sg:classifiers":[
        {
            "category":"Retail",
            "subcategory":"Event Space",
            "type":"Services"
        }
    ],
    "sg:phone":"+61 3 9645 9215",
    "sg:postcode":"3206",
    "sg:province":"VIC",
    "sg:tags":[
        "venue",
        "reception",
        "wedding"
    ],
    "wof:name":"Danish Club The",
    "wof:placetype":"venue"
},
  "geometry": {"coordinates":[144.95515399999999,-37.850727],"type":"Point"}
}