{
  "type": "Feature",
  "properties": {
    "iso:country":"AU",
    "sg:address":"27 Waterford Pde",
    "sg:city":"Lennox Head",
    "sg:classifiers":[
        {
            "category":"Personal",
            "subcategory":"Massage",
            "type":"Services"
        }
    ],
    "sg:phone":"+61 2 6687 6952",
    "sg:postcode":"2478",
    "sg:province":"NSW",
    "sg:tags":[
        "therapy"
    ],
    "wof:name":"Graham Lees",
    "wof:placetype":"venue"
},
  "geometry": {"coordinates":[153.602294922,-28.8296203613],"type":"Point"}
}