{
  "type": "Feature",
  "properties": {
    "addr:full":"21 Hill Leichhardt NSW 2040",
    "addr:housenumber":"21",
    "addr:postcode":"2040",
    "addr:street":"Hill",
    "iso:country":"AU",
    "sg:address":"21 Hill",
    "sg:city":"Leichhardt",
    "sg:classifiers":[
        {
            "category":"Organizations",
            "subcategory":"Professional Association",
            "type":"Services"
        }
    ],
    "sg:phone":"+61 2 9569 2665",
    "sg:postcode":"2040",
    "sg:province":"NSW",
    "sg:tags":[
        "hire",
        "overall"
    ],
    "wof:name":"Ace Overall Service Pty Ltd",
    "wof:placetype":"venue"
},
  "geometry": {"coordinates":[151.16369599999999,-33.880733],"type":"Point"}
}