{
  "type": "Feature",
  "properties": {
    "addr:full":"Cooper St Chinchilla QLD 4413",
    "addr:postcode":"4413",
    "addr:street":"Cooper St",
    "iso:country":"AU",
    "sg:address":"Cooper St",
    "sg:city":"Chinchilla",
    "sg:classifiers":[
        {
            "category":"Home & Garden",
            "subcategory":"Garden Supply",
            "type":"Retail Goods"
        }
    ],
    "sg:phone":"+61 7 4668 9399",
    "sg:postcode":"4413",
    "sg:province":"QLD",
    "sg:tags":[
        "landscape"
    ],
    "wof:name":"Golden West Gardenlovers Nursery & Landscape Supplies",
    "wof:placetype":"venue"
},
  "geometry": {"coordinates":[150.642379761,-26.7485256195],"type":"Point"}
}