{
  "type": "Feature",
  "properties": {
    "addr:full":"4 Eady St Browns Plains QLD 4118",
    "addr:housenumber":"4",
    "addr:postcode":"4118",
    "addr:street":"Eady St",
    "iso:country":"AU",
    "sg:address":"4 Eady St",
    "sg:city":"Browns Plains",
    "sg:classifiers":[
        {
            "category":"Building & Trades",
            "subcategory":"Landscaping Services",
            "type":"Services"
        }
    ],
    "sg:phone":"+61 7 3802 1251",
    "sg:postcode":"4118",
    "sg:province":"QLD",
    "sg:tags":[
        "stump",
        "tree",
        "felling",
        "removal"
    ],
    "wof:name":"Axme Treelopping",
    "wof:placetype":"venue"
},
  "geometry": {"coordinates":[153.05728149399999,-27.6598186493],"type":"Point"}
}