{
  "type": "Feature",
  "properties": {
    "iso:country":"AU",
    "sg:address":"502 Howitt St",
    "sg:city":"Ballarat",
    "sg:classifiers":[
        {
            "category":"Sports & Exercise",
            "subcategory":"Gym",
            "type":"Entertainment"
        }
    ],
    "sg:phone":"+61 3 5333 4333",
    "sg:postcode":"3350",
    "sg:province":"VIC",
    "sg:tags":[
        "health",
        "fitness"
    ],
    "wof:name":"Spartans Gym Pty Ltd",
    "wof:placetype":"venue"
},
  "geometry": {"coordinates":[143.857986,-37.543224],"type":"Point"}
}