{
  "type": "Feature",
  "properties": {
    "addr:full":"Ste 607/6th Flr, 20 Bungan St Mona Vale NSW 2103",
    "addr:housenumber":"/;20",
    "addr:postcode":"2103",
    "addr:street":"Bungan St",
    "iso:country":"AU",
    "sg:address":"Ste 607/6th Flr, 20 Bungan St",
    "sg:city":"Mona Vale",
    "sg:classifiers":[
        {
            "category":"Banks & Credit Unions",
            "subcategory":"Financial Services",
            "type":"Services"
        }
    ],
    "sg:phone":"+61 2 9979 7811",
    "sg:postcode":"2103",
    "sg:province":"NSW",
    "sg:tags":[
        "planning"
    ],
    "wof:name":"Count Wealth Accountants",
    "wof:placetype":"venue"
},
  "geometry": {"coordinates":[151.30172729500001,-33.6778488159],"type":"Point"}
}