{
  "type": "Feature",
  "properties": {
    "iso:country":"AU",
    "sg:address":"7- 9 Lambton Rd",
    "sg:city":"Broadmeadow",
    "sg:classifiers":[
        {
            "category":"Health Services",
            "subcategory":"Doctor",
            "type":"Services"
        }
    ],
    "sg:phone":"+61 2 4961 2088",
    "sg:postcode":"2292",
    "sg:province":"NSW",
    "sg:tags":[
        "medical",
        "practitioner"
    ],
    "wof:name":"Barrie Peter Dr",
    "wof:placetype":"venue"
},
  "geometry": {"coordinates":[151.736206055,-32.9248428345],"type":"Point"}
}