{
  "type": "Feature",
  "properties": {
    "addr:full":"249- 251 Parramatta Rd Haberfield NSW 2045",
    "addr:housenumber":"251",
    "addr:postcode":"2045",
    "addr:street":"Parramatta Rd",
    "iso:country":"AU",
    "sg:address":"249- 251 Parramatta Rd",
    "sg:city":"Haberfield",
    "sg:classifiers":[
        {
            "category":"Food & Beverages",
            "subcategory":"Liquor & Beverages",
            "type":"Retail Goods"
        }
    ],
    "sg:phone":"+61 2 8753 2100",
    "sg:postcode":"2045",
    "sg:province":"NSW",
    "sg:tags":[
        "store"
    ],
    "wof:name":"1st Choice Liquor Superstore",
    "wof:placetype":"venue"
},
  "geometry": {"coordinates":[151.129593,-33.8764],"type":"Point"}
}