{
  "type": "Feature",
  "properties": {
    "addr:full":"Suite 3, 40 Old Barrenjoey Rd Avalon NSW 2107",
    "addr:housenumber":"40",
    "addr:postcode":"2107",
    "addr:street":"Old Barrenjoey Rd",
    "iso:country":"AU",
    "sg:address":"Suite 3, 40 Old Barrenjoey Rd",
    "sg:city":"Avalon",
    "sg:classifiers":[
        {
            "category":"Banks & Credit Unions",
            "subcategory":"Financial Services",
            "type":"Services"
        }
    ],
    "sg:phone":"+61 2 9918 5136",
    "sg:postcode":"2107",
    "sg:province":"NSW",
    "sg:tags":[
        "planning"
    ],
    "wof:name":"Paul & Julia Blenkhorn",
    "wof:placetype":"venue"
},
  "geometry": {"coordinates":[151.32846069300001,-33.6381645203],"type":"Point"}
}