{
  "type": "Feature",
  "properties": {
    "addr:full":"9 - 11 Minjungbal Drv Tweed Heads South NSW 2486",
    "addr:housenumber":"11",
    "addr:postcode":"2486",
    "addr:street":"9;Minjungbal Drv",
    "iso:country":"AU",
    "sg:address":"9 - 11 Minjungbal Drv",
    "sg:city":"Tweed Heads South",
    "sg:classifiers":[
        {
            "category":"Travel",
            "subcategory":"Hotels & Motels",
            "type":"Entertainment"
        }
    ],
    "sg:phone":"+61 7 5524 3111",
    "sg:postcode":"2486",
    "sg:province":"NSW",
    "wof:name":"South Tweed Motor Inn",
    "wof:placetype":"venue"
},
  "geometry": {"coordinates":[153.543624878,-28.1961174011],"type":"Point"}
}