{
  "type": "Feature",
  "properties": {
    "addr:full":"9 Bartley St Chippendale NSW 2008",
    "addr:housenumber":"9",
    "addr:postcode":"2008",
    "addr:street":"Bartley St",
    "iso:country":"AU",
    "sg:address":"9 Bartley St",
    "sg:city":"Chippendale",
    "sg:classifiers":[
        {
            "category":"Professional",
            "subcategory":"Computer Services",
            "type":"Services"
        }
    ],
    "sg:phone":"+61 1300 657 835",
    "sg:postcode":"2008",
    "sg:province":"NSW",
    "sg:tags":[
        "equipment",
        "networking",
        "installation"
    ],
    "wof:name":"Kwiklink Networks",
    "wof:placetype":"venue"
},
  "geometry": {"coordinates":[151.199615478,-33.8881340027],"type":"Point"}
}