{
  "type": "Feature",
  "properties": {
    "addr:full":"516 Mair St Ballarat VIC 3350",
    "addr:housenumber":"516",
    "addr:postcode":"3350",
    "addr:street":"Mair St",
    "iso:country":"AU",
    "sg:address":"516 Mair St",
    "sg:city":"Ballarat",
    "sg:classifiers":[
        {
            "category":"Insurance",
            "subcategory":"Insurance Agent",
            "type":"Services"
        }
    ],
    "sg:phone":"+61 3 5331 1300",
    "sg:postcode":"3350",
    "sg:province":"VIC",
    "sg:tags":[
        "broker"
    ],
    "wof:name":"David Marks Insurance Brokers",
    "wof:placetype":"venue"
},
  "geometry": {"coordinates":[143.853195,-37.55904],"type":"Point"}
}