{
  "type": "Feature",
  "properties": {
    "iso:country":"AU",
    "sg:address":"16 Tapley St",
    "sg:city":"Coffin Bay",
    "sg:classifiers":[
        {
            "category":"Building & Trades",
            "subcategory":"Cleaning & Sanitation",
            "type":"Services"
        }
    ],
    "sg:phone":"+61 8 8685 4120",
    "sg:postcode":"5607",
    "sg:province":"SA",
    "sg:tags":[
        "chemical",
        "pressure",
        "steam",
        "contractor"
    ],
    "wof:name":"E P Waterblasters",
    "wof:placetype":"venue"
},
  "geometry": {"coordinates":[135.468674,-34.624126],"type":"Point"}
}