{
  "type": "Feature",
  "properties": {
    "iso:country":"AU",
    "sg:address":"289 Enmore Rd",
    "sg:city":"Enmore",
    "sg:classifiers":[
        {
            "category":"Fast Food",
            "type":"Food & Drink"
        }
    ],
    "sg:phone":"+61 2 9516 1781",
    "sg:postcode":"2042",
    "sg:province":"NSW",
    "sg:tags":[
        "away",
        "take"
    ],
    "wof:name":"Melinzana Wood Fired Pizza",
    "wof:placetype":"venue"
},
  "geometry": {"coordinates":[151.16949500000001,-33.901783],"type":"Point"}
}