{
  "type": "Feature",
  "properties": {
    "addr:full":"17 Clapham Rd Regents Park NSW 2143",
    "addr:housenumber":"17",
    "addr:postcode":"2143",
    "addr:street":"Clapham Rd",
    "iso:country":"AU",
    "sg:address":"17 Clapham Rd",
    "sg:city":"Regents Park",
    "sg:classifiers":[
        {
            "category":"Wholesale",
            "subcategory":"Machinery & Supplies",
            "type":"Manufacturing & Wholesale Goods"
        }
    ],
    "sg:phone":"+61 2 9645 4444",
    "sg:postcode":"2143",
    "sg:province":"NSW",
    "sg:tags":[
        "engineer"
    ],
    "wof:name":"McPhersons Engineering Supplies Pty Ltd",
    "wof:placetype":"venue"
},
  "geometry": {"coordinates":[151.01942443900001,-33.8848686218],"type":"Point"}
}