{
  "type": "Feature",
  "properties": {
    "iso:country":"AU",
    "sg:address":"251 Rundle St",
    "sg:city":"Adelaide",
    "sg:classifiers":[
        {
            "category":"Cinema",
            "subcategory":"Movie Theater",
            "type":"Entertainment"
        }
    ],
    "sg:phone":"+61 8 8232 3434",
    "sg:postcode":"5000",
    "sg:province":"SA",
    "wof:name":"Palace Nova East End Cinemas",
    "wof:placetype":"venue"
},
  "geometry": {"coordinates":[138.60870361299999,-34.9226531982],"type":"Point"}
}