{
  "type": "Feature",
  "properties": {
    "addr:full":"2 Beach Ave Mordialloc VIC 3195",
    "addr:housenumber":"2",
    "addr:postcode":"3195",
    "addr:street":"Beach Ave",
    "iso:country":"AU",
    "sg:address":"2 Beach Ave",
    "sg:city":"Mordialloc",
    "sg:classifiers":[
        {
            "category":"Building & Trades",
            "subcategory":"Construction",
            "type":"Services"
        }
    ],
    "sg:phone":"+61 3 9580 8813",
    "sg:postcode":"3195",
    "sg:province":"VIC",
    "sg:tags":[
        "contractor"
    ],
    "wof:name":"G.J. Lawson Woodturning",
    "wof:placetype":"venue"
},
  "geometry": {"coordinates":[145.10060119600001,-38.0105667114],"type":"Point"}
}