{
  "type": "Feature",
  "properties": {
    "addr:full":"6 Mary St Cygnet TAS 7112",
    "addr:housenumber":"6",
    "addr:postcode":"7112",
    "addr:street":"Mary St",
    "iso:country":"AU",
    "sg:address":"6 Mary St",
    "sg:city":"Cygnet",
    "sg:classifiers":[
        {
            "category":"Food & Beverages",
            "subcategory":"Supermarket",
            "type":"Retail Goods"
        }
    ],
    "sg:phone":"+61 3 6295 1524",
    "sg:postcode":"7112",
    "sg:province":"TAS",
    "sg:tags":[
        "grocery",
        "store"
    ],
    "wof:name":"Friendly Grocer IGA Stores",
    "wof:placetype":"venue"
},
  "geometry": {"coordinates":[147.07423400900001,-43.1567115784],"type":"Point"}
}