{
  "type": "Feature",
  "properties": {
    "addr:full":"2 Geneva St Kyogle NSW 2474",
    "addr:housenumber":"2",
    "addr:postcode":"2474",
    "addr:street":"Geneva St",
    "iso:country":"AU",
    "sg:address":"2 Geneva St",
    "sg:city":"Kyogle",
    "sg:classifiers":[
        {
            "category":"Health Services",
            "subcategory":"Health Practitioner",
            "type":"Services"
        }
    ],
    "sg:phone":"+61 2 6632 2544",
    "sg:postcode":"2474",
    "sg:province":"NSW",
    "sg:tags":[
        "physiotherapist"
    ],
    "wof:name":"Kyogle Physiotherapy",
    "wof:placetype":"venue"
},
  "geometry": {"coordinates":[153.002029419,-28.6198806763],"type":"Point"}
}