{
  "type": "Feature",
  "properties": {
    "addr:full":"Shop 37 & 38 Muswellbrook Mrkt Pl 22 Sowerby Ave Muswellbrook NSW 2333",
    "addr:housenumber":"shop 37 & 38;22",
    "addr:postcode":"2333",
    "addr:street":"Pl;Sowerby Ave",
    "iso:country":"AU",
    "sg:address":"Shop 37 & 38 Muswellbrook Mrkt Pl 22 Sowerby Ave",
    "sg:city":"Muswellbrook",
    "sg:classifiers":[
        {
            "category":"Shopping",
            "subcategory":"Computers & Home Electronics",
            "type":"Retail Goods"
        }
    ],
    "sg:phone":"+61 2 6541 5833",
    "sg:postcode":"2333",
    "sg:province":"NSW",
    "sg:tags":[
        "equipment",
        "part",
        "electronic"
    ],
    "wof:name":"Dick Smith Electronics",
    "wof:placetype":"venue"
},
  "geometry": {"coordinates":[150.89120483400001,-32.263004303],"type":"Point"}
}