{
  "type": "Feature",
  "properties": {
    "iso:country":"AU",
    "sg:address":"1st Floor City Galleria Bunda St",
    "sg:city":"Canberra City",
    "sg:classifiers":[
        {
            "category":"Shopping",
            "subcategory":"Clothing, Apparel, & Fashions",
            "type":"Retail Goods"
        }
    ],
    "sg:phone":"+61 2 6257 2734",
    "sg:postcode":"2601",
    "sg:province":"ACT",
    "sg:tags":[
        "lady",
        "wear"
    ],
    "wof:name":"Country Road Clothing Pty Ltd",
    "wof:placetype":"venue"
},
  "geometry": {"coordinates":[149.13360595699999,-35.2794952393],"type":"Point"}
}