{
  "type": "Feature",
  "properties": {
    "iso:country":"AU",
    "sg:address":"47- 51 Boundary Rd",
    "sg:city":"North Melbourne",
    "sg:classifiers":[
        {
            "category":"Autos & Motor Vehicles",
            "subcategory":"Auto Supplies",
            "type":"Retail Goods"
        }
    ],
    "sg:phone":"+61 3 9329 6066",
    "sg:postcode":"3051",
    "sg:province":"VIC",
    "sg:tags":[
        "part",
        "cycles",
        "accessory"
    ],
    "wof:name":"Sumoto Trading Pty Ltd",
    "wof:placetype":"venue"
},
  "geometry": {"coordinates":[144.938995361,-37.7939834595],"type":"Point"}
}