{
  "type": "Feature",
  "properties": {
    "iso:country":"AU",
    "sg:address":"7 Gill St",
    "sg:city":"Mt Hutton",
    "sg:classifiers":[
        {
            "category":"Building & Trades",
            "subcategory":"Cleaning & Sanitation",
            "type":"Services"
        }
    ],
    "sg:phone":"+61 2 4948 9696",
    "sg:postcode":"2290",
    "sg:province":"NSW",
    "sg:tags":[
        "cleaner",
        "repairer",
        "roof"
    ],
    "wof:name":"Hudson Roofing (Newcastle) Pty Ltd",
    "wof:placetype":"venue"
},
  "geometry": {"coordinates":[151.67384338400001,-32.9971733093],"type":"Point"}
}