{
  "type": "Feature",
  "properties": {
    "addr:full":"1/ 30 Sterling Rd Minchinbury NSW 2770",
    "addr:housenumber":"/ 30",
    "addr:postcode":"2770",
    "addr:street":"Sterling Rd",
    "iso:country":"AU",
    "sg:address":"1/ 30 Sterling Rd",
    "sg:city":"Minchinbury",
    "sg:classifiers":[
        {
            "category":"Professional",
            "type":"Services"
        }
    ],
    "sg:phone":"+61 2 9677 2811",
    "sg:postcode":"2770",
    "sg:province":"NSW",
    "sg:tags":[
        "shop",
        "fitting"
    ],
    "wof:name":"Atherton Shopfitting Pty Ltd",
    "wof:placetype":"venue"
},
  "geometry": {"coordinates":[150.82037353499999,-33.7827033997],"type":"Point"}
}