{
  "type": "Feature",
  "properties": {
    "iso:country":"AU",
    "sg:address":"18 Warrandyte Rd",
    "sg:city":"Ringwood",
    "sg:classifiers":[
        {
            "category":"Health Services",
            "subcategory":"Doctor",
            "type":"Services"
        }
    ],
    "sg:phone":"+61 3 9870 8022",
    "sg:postcode":"3134",
    "sg:province":"VIC",
    "sg:tags":[
        "medical",
        "practitioner"
    ],
    "wof:name":"Vaughan Geoffrey N Dr",
    "wof:placetype":"venue"
},
  "geometry": {"coordinates":[145.230926514,-37.8131713867],"type":"Point"}
}