{
  "type": "Feature",
  "properties": {
    "iso:country":"AU",
    "sg:address":"7 Mary St",
    "sg:city":"West End (Townsville)",
    "sg:classifiers":[
        {
            "category":"Manufacturing",
            "subcategory":"Glass & Minerals",
            "type":"Manufacturing & Wholesale Goods"
        }
    ],
    "sg:phone":"+61 7 4721 2003",
    "sg:postcode":"4810",
    "sg:province":"QLD",
    "sg:tags":[
        "exploration"
    ],
    "wof:name":"Klondike Exploration Services",
    "wof:placetype":"venue"
},
  "geometry": {"coordinates":[146.798706,-19.266846],"type":"Point"}
}