{
  "type": "Feature",
  "properties": {
    "addr:full":"Shp 2/ 38 Reef St Gympie QLD 4570",
    "addr:housenumber":"/ 38",
    "addr:postcode":"4570",
    "addr:street":"Reef St",
    "iso:country":"AU",
    "sg:address":"Shp 2/ 38 Reef St",
    "sg:city":"Gympie",
    "sg:classifiers":[
        {
            "category":"Personal",
            "subcategory":"Massage",
            "type":"Services"
        }
    ],
    "sg:phone":"+61 7 5483 7699",
    "sg:postcode":"4570",
    "sg:province":"QLD",
    "sg:tags":[
        "therapy"
    ],
    "wof:name":"Cooloola Bodycare",
    "wof:placetype":"venue"
},
  "geometry": {"coordinates":[152.65763855,-26.1884937286],"type":"Point"}
}