{
  "type": "Feature",
  "properties": {
    "addr:full":"15 Miall Way Albion Park Rail NSW 2527",
    "addr:housenumber":"15",
    "addr:postcode":"2527",
    "addr:street":"Miall Way",
    "iso:country":"AU",
    "sg:address":"15 Miall Way",
    "sg:city":"Albion Park Rail",
    "sg:classifiers":[
        {
            "category":"Professional",
            "type":"Services"
        }
    ],
    "sg:phone":"+61 2 4257 5755",
    "sg:postcode":"2527",
    "sg:province":"NSW",
    "sg:tags":[
        "shop",
        "fitting"
    ],
    "wof:name":"Todays Prestige Interiors Pty Ltd",
    "wof:placetype":"venue"
},
  "geometry": {"coordinates":[150.799224853,-34.5644721985],"type":"Point"}
}