{
  "type": "Feature",
  "properties": {
    "iso:country":"AU",
    "sg:address":"Shop 304",
    "sg:city":"westcourt Plaza Edge Hill",
    "sg:classifiers":[
        {
            "category":"Organizations",
            "subcategory":"Professional Association",
            "type":"Services"
        }
    ],
    "sg:phone":"+61 7 4031 7888",
    "sg:postcode":"4870",
    "sg:province":"QLD",
    "sg:tags":[
        "web",
        "internet"
    ],
    "wof:name":"KISS",
    "wof:placetype":"venue"
},
  "geometry": {"coordinates":[145.740066528,-16.9015407562],"type":"Point"}
}