{
  "type": "Feature",
  "properties": {
    "iso:country":"AU",
    "sg:address":"Shop 6a Whitsunday Shopping Centre",
    "sg:city":"Cannonvale",
    "sg:classifiers":[
        {
            "category":"Fast Food",
            "type":"Food & Drink"
        }
    ],
    "sg:phone":"+61 7 4946 6711",
    "sg:postcode":"4802",
    "sg:province":"QLD",
    "sg:tags":[
        "away",
        "take"
    ],
    "wof:name":"F J Dial A Pizza",
    "wof:placetype":"venue"
},
  "geometry": {"coordinates":[148.78736877399999,-20.2876834869],"type":"Point"}
}