{
  "type": "Feature",
  "properties": {
    "addr:full":"Heritage Plaza 400 Ruthven St Toowoomba QLD 4350",
    "addr:housenumber":"400",
    "addr:postcode":"4350",
    "addr:street":"Ruthven St",
    "iso:country":"AU",
    "sg:address":"Heritage Plaza 400 Ruthven St",
    "sg:city":"Toowoomba",
    "sg:classifiers":[
        {
            "category":"Food & Beverages",
            "subcategory":"Bakery",
            "type":"Retail Goods"
        }
    ],
    "sg:phone":"+61 7 4638 1251",
    "sg:postcode":"4350",
    "sg:province":"QLD",
    "sg:tags":[
        "baker"
    ],
    "wof:name":"The Bakafe",
    "wof:placetype":"venue"
},
  "geometry": {"coordinates":[151.95228599999999,-27.568256],"type":"Point"}
}