{
  "type": "Feature",
  "properties": {
    "addr:full":"PO Box 41 Austral NSW 2179",
    "addr:postcode":"2179",
    "iso:country":"AU",
    "sg:address":"PO Box 41",
    "sg:city":"Austral",
    "sg:classifiers":[
        {
            "category":"Building & Trades",
            "subcategory":"Construction",
            "type":"Services"
        }
    ],
    "sg:phone":"+61 2 9606 0023",
    "sg:postcode":"2179",
    "sg:province":"NSW",
    "sg:tags":[
        "contractor"
    ],
    "wof:name":"Superb Building Company",
    "wof:placetype":"venue"
},
  "geometry": {"coordinates":[150.811737061,-33.9345283508],"type":"Point"}
}