{
  "type": "Feature",
  "properties": {
    "iso:country":"AU",
    "sg:address":"32 Langtree Ave",
    "sg:city":"Mildura",
    "sg:classifiers":[
        {
            "category":"Restaurant",
            "type":"Food & Drink"
        }
    ],
    "sg:phone":"+61 3 5023 2336",
    "sg:postcode":"3500",
    "sg:province":"VIC",
    "wof:name":"Antigonis Greek Tavern",
    "wof:placetype":"venue"
},
  "geometry": {"coordinates":[142.16226196299999,-34.1837310791],"type":"Point"}
}