{
  "type": "Feature",
  "properties": {
    "addr:full":"281 Guildford Rd (Cnr Ferguson St) Maylands WA 6051",
    "addr:housenumber":"281",
    "addr:postcode":"6051",
    "addr:street":"Guildford Rd Cnr Ferguson St",
    "iso:country":"AU",
    "sg:address":"281 Guildford Rd (Cnr Ferguson St)",
    "sg:city":"Maylands",
    "sg:classifiers":[
        {
            "category":"Professional",
            "subcategory":"Art Services",
            "type":"Services"
        }
    ],
    "sg:phone":"+61 8 9271 0922",
    "sg:postcode":"6051",
    "sg:province":"WA",
    "sg:tags":[
        "picture",
        "frame",
        "framing"
    ],
    "wof:name":"Leonardo's Art Of Picture Framing",
    "wof:placetype":"venue"
},
  "geometry": {"coordinates":[115.90016900000001,-31.928371],"type":"Point"}
}