{
  "type": "Feature",
  "properties": {
    "addr:full":"Shop 4030 Westfield Shopping Cntr Parramatta NSW 2124",
    "addr:housenumber":"4030",
    "addr:postcode":"2124",
    "addr:street":"Westfield Shopping Cntr",
    "iso:country":"AU",
    "sg:address":"Shop 4030",
    "sg:city":"Westfield Shopping Cntr Parramatta",
    "sg:classifiers":[
        {
            "category":"Shopping",
            "subcategory":"Clothing, Apparel, & Fashions",
            "type":"Retail Goods"
        }
    ],
    "sg:phone":"+61 2 9891 9230",
    "sg:postcode":"2124",
    "sg:province":"NSW",
    "sg:tags":[
        "menswear"
    ],
    "wof:name":"Oxford.",
    "wof:placetype":"venue"
},
  "geometry": {"coordinates":[151.003448486,-33.8169593811],"type":"Point"}
}