{
  "type": "Feature",
  "properties": {
    "addr:full":"Unit 7 7 Floriston Rd Boronia VIC 3155",
    "addr:housenumber":"7",
    "addr:postcode":"3155",
    "addr:street":"Floriston Rd",
    "iso:country":"AU",
    "sg:address":"Unit 7 7 Floriston Rd",
    "sg:city":"Boronia",
    "sg:classifiers":[
        {
            "category":"Health Services",
            "subcategory":"Health Practitioner",
            "type":"Services"
        }
    ],
    "sg:phone":"+61 3 9739 8828",
    "sg:postcode":"3155",
    "sg:province":"VIC",
    "sg:tags":[
        "hypnotherapy"
    ],
    "wof:name":"Melbourne Natural Healthcare Centre",
    "wof:placetype":"venue"
},
  "geometry": {"coordinates":[145.28817749000001,-37.8610534668],"type":"Point"}
}