{
  "type": "Feature",
  "properties": {
    "iso:country":"AU",
    "sg:address":"Level 2 167 Collins St",
    "sg:city":"Melbourne",
    "sg:classifiers":[
        {
            "category":"Travel",
            "subcategory":"Travel Agent",
            "type":"Entertainment"
        }
    ],
    "sg:phone":"+61 3 9654 5366",
    "sg:postcode":"3000",
    "sg:province":"VIC",
    "sg:tags":[
        "consultant"
    ],
    "wof:name":"Wonderworld Travel Pty Ltd",
    "wof:placetype":"venue"
},
  "geometry": {"coordinates":[144.96824645999999,-37.8151054382],"type":"Point"}
}