{
  "type": "Feature",
  "properties": {
    "iso:country":"AU",
    "sg:address":"23 Meridian Pde",
    "sg:city":"Wantirna South",
    "sg:classifiers":[
        {
            "category":"Building & Trades",
            "subcategory":"Construction",
            "type":"Services"
        }
    ],
    "sg:phone":"+61 3 9887 0422",
    "sg:postcode":"3152",
    "sg:province":"VIC",
    "sg:tags":[
        "contractor"
    ],
    "wof:name":"All Round Building Services",
    "wof:placetype":"venue"
},
  "geometry": {"coordinates":[145.22517395,-37.8763923645],"type":"Point"}
}