{
  "type": "Feature",
  "properties": {
    "iso:country":"AU",
    "sg:address":"243 South Rd",
    "sg:city":"Ridleyton",
    "sg:classifiers":[
        {
            "category":"Retail",
            "subcategory":"Auto Repair",
            "type":"Services"
        }
    ],
    "sg:phone":"+61 8 8340 2303",
    "sg:postcode":"5008",
    "sg:province":"SA",
    "sg:tags":[
        "beater",
        "painter",
        "panel"
    ],
    "wof:name":"IBS Crash Repairs",
    "wof:placetype":"venue"
},
  "geometry": {"coordinates":[138.570007,-34.88929],"type":"Point"}
}