{
  "type": "Feature",
  "properties": {
    "addr:full":"2/ 12 Copeland St Kingswood NSW 2747",
    "addr:housenumber":"/ 12",
    "addr:postcode":"2747",
    "addr:street":"Copeland St",
    "iso:country":"AU",
    "sg:address":"2/ 12 Copeland St",
    "sg:city":"Kingswood",
    "sg:classifiers":[
        {
            "category":"Retail",
            "subcategory":"Auto Repair",
            "type":"Services"
        }
    ],
    "sg:phone":"+61 2 4731 3435",
    "sg:postcode":"2747",
    "sg:province":"NSW",
    "sg:tags":[
        "beater",
        "painter",
        "panel"
    ],
    "wof:name":"Motor Vehicle Perfection Spraypainting",
    "wof:placetype":"venue"
},
  "geometry": {"coordinates":[150.719238281,-33.7553482056],"type":"Point"}
}