{
  "type": "Feature",
  "properties": {
    "addr:full":"147 Pirie St Adelaide SA 5000",
    "addr:housenumber":"147",
    "addr:postcode":"5000",
    "addr:street":"Pirie St",
    "iso:country":"AU",
    "sg:address":"147 Pirie St",
    "sg:city":"Adelaide",
    "sg:classifiers":[
        {
            "category":"Banks & Credit Unions",
            "subcategory":"Bank",
            "type":"Services"
        }
    ],
    "sg:phone":"+61 8 8224 1000",
    "sg:postcode":"5000",
    "sg:province":"SA",
    "sg:tags":[
        "society"
    ],
    "wof:name":"PowerState Credit Union",
    "wof:placetype":"venue"
},
  "geometry": {"coordinates":[138.604934692,-34.9256362915],"type":"Point"}
}