{
  "type": "Feature",
  "properties": {
    "addr:full":"35 Norman St Peakhurst NSW 2210",
    "addr:housenumber":"35",
    "addr:postcode":"2210",
    "addr:street":"Norman St",
    "iso:country":"AU",
    "sg:address":"35 Norman St",
    "sg:city":"Peakhurst",
    "sg:classifiers":[
        {
            "category":"Home & Garden",
            "subcategory":"Building Materials",
            "type":"Retail Goods"
        }
    ],
    "sg:phone":"+61 2 9584 1965",
    "sg:postcode":"2210",
    "sg:province":"NSW",
    "sg:tags":[
        "merchant",
        "glass",
        "glazier"
    ],
    "wof:name":"Illawong Glass",
    "wof:placetype":"venue"
},
  "geometry": {"coordinates":[151.06434631400001,-33.9641952515],"type":"Point"}
}