{
  "type": "Feature",
  "properties": {
    "addr:full":"481 King St Newtown NSW 2042",
    "addr:housenumber":"481",
    "addr:postcode":"2042",
    "addr:street":"King St",
    "iso:country":"AU",
    "sg:address":"481 King St",
    "sg:city":"Newtown",
    "sg:classifiers":[
        {
            "category":"Education",
            "subcategory":"University",
            "type":"Public Place"
        }
    ],
    "sg:phone":"+61 417 238 993",
    "sg:postcode":"2042",
    "sg:province":"NSW",
    "sg:tags":[
        "college",
        "tertiary"
    ],
    "wof:name":"An International Student Home",
    "wof:placetype":"venue"
},
  "geometry": {"coordinates":[151.17894000000001,-33.902222],"type":"Point"}
}