{
  "type": "Feature",
  "properties": {
    "addr:full":"26 Rowan St Wangaratta VIC 3677",
    "addr:housenumber":"26",
    "addr:postcode":"3677",
    "addr:street":"Rowan St",
    "iso:country":"AU",
    "sg:address":"26 Rowan St",
    "sg:city":"Wangaratta",
    "sg:classifiers":[
        {
            "category":"Home & Garden",
            "subcategory":"Hardware",
            "type":"Retail Goods"
        }
    ],
    "sg:phone":"+61 3 5721 2752",
    "sg:postcode":"3677",
    "sg:province":"VIC",
    "sg:tags":[
        "generating",
        "set",
        "generator"
    ],
    "wof:name":"Ray Wason Motor Cycles Pty Ltd",
    "wof:placetype":"venue"
},
  "geometry": {"coordinates":[146.32273864699999,-36.3526191711],"type":"Point"}
}