{
  "type": "Feature",
  "properties": {
    "iso:country":"AU",
    "sg:address":"104 Peel Rd",
    "sg:city":"Inverleigh",
    "sg:classifiers":[
        {
            "category":"Manufacturing",
            "subcategory":"Soap",
            "type":"Manufacturing & Wholesale Goods"
        }
    ],
    "sg:phone":"+61 3 5265 1526",
    "sg:postcode":"3321",
    "sg:province":"VIC",
    "sg:tags":[
        "detergent"
    ],
    "wof:name":"White G & Y",
    "wof:placetype":"venue"
},
  "geometry": {"coordinates":[144.077927,-38.100906],"type":"Point"}
}