{
  "type": "Feature",
  "properties": {
    "addr:full":"50 Bonwick St Fawkner VIC 3060",
    "addr:housenumber":"50",
    "addr:postcode":"3060",
    "addr:street":"Bonwick St",
    "iso:country":"AU",
    "sg:address":"50 Bonwick St",
    "sg:city":"Fawkner",
    "sg:classifiers":[
        {
            "category":"Personal",
            "subcategory":"Beauty Salon",
            "type":"Services"
        }
    ],
    "sg:phone":"+61 3 9357 1911",
    "sg:postcode":"3060",
    "sg:province":"VIC",
    "wof:name":"Beauty Room",
    "wof:placetype":"venue"
},
  "geometry": {"coordinates":[144.965667725,-37.7023887634],"type":"Point"}
}