{
  "type": "Feature",
  "properties": {
    "addr:full":"30 Byrnes St Botany NSW 2019",
    "addr:housenumber":"30",
    "addr:postcode":"2019",
    "addr:street":"Byrnes St",
    "iso:country":"AU",
    "sg:address":"30 Byrnes St",
    "sg:city":"Botany",
    "sg:classifiers":[
        {
            "category":"Professional",
            "type":"Services"
        }
    ],
    "sg:phone":"+61 2 9316 6188",
    "sg:postcode":"2019",
    "sg:province":"NSW",
    "sg:tags":[
        "courier"
    ],
    "wof:name":"Deltec International Courier Pty Ltd",
    "wof:placetype":"venue"
},
  "geometry": {"coordinates":[151.19473266599999,-33.946231842],"type":"Point"}
}