{
  "type": "Feature",
  "properties": {
    "iso:country":"AU",
    "sg:address":"Level 2, 373 Pitt St",
    "sg:city":"Sydney",
    "sg:classifiers":[
        {
            "category":"Education",
            "subcategory":"Music School",
            "type":"Public Place"
        }
    ],
    "sg:phone":"+61 2 9267 3655",
    "sg:postcode":"2000",
    "sg:province":"NSW",
    "sg:tags":[
        "teacher"
    ],
    "wof:name":"DJ Central HQ",
    "wof:placetype":"venue"
},
  "geometry": {"coordinates":[151.20770263700001,-33.8762054443],"type":"Point"}
}