{
  "type": "Feature",
  "properties": {
    "iso:country":"AU",
    "sg:address":"19 Mair St",
    "sg:city":"Ballarat",
    "sg:classifiers":[
        {
            "category":"Retail",
            "subcategory":"Auto Repair",
            "type":"Services"
        }
    ],
    "sg:phone":"+61 3 5331 8322",
    "sg:postcode":"3350",
    "sg:province":"VIC",
    "sg:tags":[
        "clutch",
        "brake"
    ],
    "wof:name":"City Central Mechanics & Suspension",
    "wof:placetype":"venue"
},
  "geometry": {"coordinates":[143.861847,-37.560059],"type":"Point"}
}