{
  "type": "Feature",
  "properties": {
    "iso:country":"AU",
    "sg:address":"31 Lindsays Rd",
    "sg:city":"Mitchell Park",
    "sg:classifiers":[
        {
            "category":"Shopping",
            "subcategory":"Mobile Phones",
            "type":"Retail Goods"
        }
    ],
    "sg:phone":"+61 407 406 070",
    "sg:postcode":"3352",
    "sg:province":"VIC",
    "sg:tags":[
        "wholesaler",
        "mfrs",
        "electrical",
        "switchboard"
    ],
    "wof:name":"S.S. Electrics",
    "wof:placetype":"venue"
},
  "geometry": {"coordinates":[143.801331,-37.503262],"type":"Point"}
}