{
  "type": "Feature",
  "properties": {
    "iso:country":"AU",
    "sg:address":"55 Cranhaven Rd",
    "sg:city":"Langwarrin",
    "sg:classifiers":[
        {
            "category":"Farming",
            "subcategory":"Poultry Farm",
            "type":"Manufacturing & Wholesale Goods"
        }
    ],
    "sg:phone":"+61 3 9789 1582",
    "sg:postcode":"3910",
    "sg:province":"VIC",
    "sg:tags":[
        "farmer"
    ],
    "wof:name":"Cranhaven Poultry Farm",
    "wof:placetype":"venue"
},
  "geometry": {"coordinates":[145.18374633799999,-38.1580963135],"type":"Point"}
}