{
  "type": "Feature",
  "properties": {
    "iso:country":"AU",
    "sg:address":"149A Main St",
    "sg:city":"Bacchus Marsh",
    "sg:classifiers":[
        {
            "category":"Shopping",
            "subcategory":"Computers & Home Electronics",
            "type":"Retail Goods"
        }
    ],
    "sg:phone":"+61 3 5367 3778",
    "sg:postcode":"3340",
    "sg:province":"VIC",
    "sg:tags":[
        "small",
        "equipment",
        "business"
    ],
    "wof:name":"Computer Shoppe The Bacchus Marsh",
    "wof:placetype":"venue"
},
  "geometry": {"coordinates":[144.43808,-37.676022],"type":"Point"}
}