{
  "type": "Feature",
  "properties": {
    "addr:full":"PO Box 10427 Adelaide St Brisbane QLD 4000",
    "addr:postcode":"4000",
    "addr:street":"Adelaide St",
    "iso:country":"AU",
    "sg:address":"PO Box 10427 Adelaide St",
    "sg:city":"Brisbane",
    "sg:classifiers":[
        {
            "category":"Communications",
            "type":"Services"
        }
    ],
    "sg:phone":"+61 7 3870 3396",
    "sg:postcode":"4000",
    "sg:province":"QLD",
    "sg:tags":[
        "translation"
    ],
    "wof:name":"Ausit",
    "wof:placetype":"venue"
},
  "geometry": {"coordinates":[153.02536010700001,-27.4681777954],"type":"Point"}
}