{
  "type": "Feature",
  "properties": {
    "addr:full":"229 Gilbert Rd Preston VIC 3072",
    "addr:housenumber":"229",
    "addr:postcode":"3072",
    "addr:street":"Gilbert Rd",
    "iso:country":"AU",
    "sg:address":"229 Gilbert Rd",
    "sg:city":"Preston",
    "sg:classifiers":[
        {
            "category":"Retail",
            "subcategory":"Event Space",
            "type":"Services"
        }
    ],
    "sg:phone":"+61 3 9484 6220",
    "sg:postcode":"3072",
    "sg:province":"VIC",
    "sg:tags":[
        "venue",
        "reception",
        "wedding"
    ],
    "wof:name":"Whitehall Receptions",
    "wof:placetype":"venue"
},
  "geometry": {"coordinates":[144.98916625999999,-37.7427787781],"type":"Point"}
}