{
  "type": "Feature",
  "properties": {
    "iso:country":"AU",
    "sg:address":"57 Whitbread St",
    "sg:city":"Taree",
    "sg:classifiers":[
        {
            "category":"Manufacturing",
            "subcategory":"Motor Vehicles & Parts",
            "type":"Manufacturing & Wholesale Goods"
        }
    ],
    "sg:phone":"+61 2 6551 0888",
    "sg:postcode":"2430",
    "sg:province":"NSW",
    "sg:tags":[
        "replacement"
    ],
    "wof:name":"Taree Radiators",
    "wof:placetype":"venue"
},
  "geometry": {"coordinates":[152.45842,-31.898762],"type":"Point"}
}