{
  "type": "Feature",
  "properties": {
    "iso:country":"AU",
    "sg:address":"PO Box 40",
    "sg:city":"Clarinda",
    "sg:classifiers":[
        {
            "category":"Building & Trades",
            "subcategory":"Construction",
            "type":"Services"
        }
    ],
    "sg:phone":"+61 3 9562 9568",
    "sg:postcode":"3169",
    "sg:province":"VIC",
    "sg:tags":[
        "contractor"
    ],
    "wof:name":"New Generation Homes Vic Pty Ltd",
    "wof:placetype":"venue"
},
  "geometry": {"coordinates":[145.10856628400001,-37.935043335],"type":"Point"}
}