{
  "type": "Feature",
  "properties": {
    "addr:full":"93 Logan Rd Woolloongabba QLD 4102",
    "addr:housenumber":"93",
    "addr:postcode":"4102",
    "addr:street":"Logan Rd",
    "iso:country":"AU",
    "sg:address":"93 Logan Rd",
    "sg:city":"Woolloongabba",
    "sg:classifiers":[
        {
            "category":"Travel",
            "subcategory":"Hotels & Motels",
            "type":"Entertainment"
        }
    ],
    "sg:phone":"+61 7 3217 3469",
    "sg:postcode":"4102",
    "sg:province":"QLD",
    "sg:tags":[
        "pub"
    ],
    "wof:name":"Hotel Broadway The",
    "wof:placetype":"venue"
},
  "geometry": {"coordinates":[153.038970947,-27.4900512695],"type":"Point"}
}