{
  "type": "Feature",
  "properties": {
    "addr:full":"PO Box 1077 Noosa Heads QLD 4567",
    "addr:postcode":"4567",
    "iso:country":"AU",
    "sg:address":"PO Box 1077",
    "sg:city":"Noosa Heads",
    "sg:classifiers":[
        {
            "category":"Education",
            "subcategory":"Dance Studio",
            "type":"Public Place"
        }
    ],
    "sg:phone":"+61 7 5455 6955",
    "sg:postcode":"4567",
    "sg:province":"QLD",
    "sg:tags":[
        "training",
        "video",
        "film"
    ],
    "wof:name":"Corporate Expression Pty Ltd",
    "wof:placetype":"venue"
},
  "geometry": {"coordinates":[153.086105347,-26.3990192413],"type":"Point"}
}