{
  "type": "Feature",
  "properties": {
    "addr:full":"Shop 8, 365 Turbot St, Spring Hill Marketplace Spring Hill QLD 4004",
    "addr:housenumber":"shop 8",
    "addr:postcode":"365;4004",
    "addr:street":"Turbot St",
    "iso:country":"AU",
    "sg:address":"Shop 8, 365 Turbot St, Spring Hill Marketplace",
    "sg:city":"Spring Hill",
    "sg:classifiers":[
        {
            "category":"Food & Beverages",
            "subcategory":"Bakery",
            "type":"Retail Goods"
        }
    ],
    "sg:phone":"+61 7 3832 3616",
    "sg:postcode":"4004",
    "sg:province":"QLD",
    "sg:tags":[
        "baker"
    ],
    "wof:name":"Bakers Delight Ltd",
    "wof:placetype":"venue"
},
  "geometry": {"coordinates":[153.02650451700001,-27.4651298523],"type":"Point"}
}