{
  "type": "Feature",
  "properties": {
    "addr:full":"100 Main St Kapunda SA 5373",
    "addr:housenumber":"100",
    "addr:postcode":"5373",
    "addr:street":"Main St",
    "iso:country":"AU",
    "sg:address":"100 Main St",
    "sg:city":"Kapunda",
    "sg:classifiers":[
        {
            "category":"Home & Garden",
            "subcategory":"Building Materials",
            "type":"Retail Goods"
        }
    ],
    "sg:phone":"+61 8 8566 3066",
    "sg:postcode":"5373",
    "sg:province":"SA",
    "sg:tags":[
        "concrete",
        "panel",
        "pre-cast"
    ],
    "wof:name":"Concept Walling Pty Ltd",
    "wof:placetype":"venue"
},
  "geometry": {"coordinates":[138.91656494099999,-34.3394813538],"type":"Point"}
}