{
  "type": "Feature",
  "properties": {
    "iso:country":"AU",
    "sg:address":"107 Charters Towers Rd",
    "sg:city":"Hermit Park",
    "sg:classifiers":[
        {
            "category":"Banks & Credit Unions",
            "subcategory":"Financial Services",
            "type":"Services"
        }
    ],
    "sg:phone":"+61 7 4722 3525",
    "sg:postcode":"4812",
    "sg:province":"QLD",
    "sg:tags":[
        "loan",
        "finance",
        "mortgage"
    ],
    "wof:name":"C B F C Ltd",
    "wof:placetype":"venue"
},
  "geometry": {"coordinates":[146.800568,-19.276054],"type":"Point"}
}