{
  "type": "Feature",
  "properties": {
    "iso:country":"AU",
    "sg:address":"14b Webb St",
    "sg:city":"Gosnells",
    "sg:classifiers":[
        {
            "category":"Building & Trades",
            "subcategory":"Equipment Rental",
            "type":"Services"
        }
    ],
    "sg:phone":"+61 8 9398 1625",
    "sg:postcode":"6110",
    "sg:province":"WA",
    "sg:tags":[
        "repairing",
        "changing",
        "retreading",
        "tyre"
    ],
    "wof:name":"Stu's Tyre Repair & Tool Supplies",
    "wof:placetype":"venue"
},
  "geometry": {"coordinates":[115.991188049,-32.0728416443],"type":"Point"}
}