{
  "type": "Feature",
  "properties": {
    "addr:full":"13 Oxford Drv Wangaratta VIC 3677",
    "addr:housenumber":"13",
    "addr:postcode":"3677",
    "addr:street":"Oxford Drv",
    "iso:country":"AU",
    "sg:address":"13 Oxford Drv",
    "sg:city":"Wangaratta",
    "sg:classifiers":[
        {
            "category":"Building & Trades",
            "subcategory":"Construction",
            "type":"Services"
        }
    ],
    "sg:phone":"+61 419 573 891",
    "sg:postcode":"3677",
    "sg:province":"VIC",
    "sg:tags":[
        "brick",
        "paving"
    ],
    "wof:name":"Harris Garry & M",
    "wof:placetype":"venue"
},
  "geometry": {"coordinates":[146.30632019000001,-36.3345375061],"type":"Point"}
}