{
  "type": "Feature",
  "properties": {
    "iso:country":"AU",
    "sg:address":"450 Nepean Hwy",
    "sg:city":"Mt Martha",
    "sg:classifiers":[
        {
            "category":"Retail",
            "subcategory":"Event Space",
            "type":"Services"
        }
    ],
    "sg:phone":"+61 3 5974 1104",
    "sg:postcode":"3934",
    "sg:province":"VIC",
    "sg:tags":[
        "venue",
        "reception",
        "wedding"
    ],
    "wof:name":"Josephines Restaurant At The Briars",
    "wof:placetype":"venue"
},
  "geometry": {"coordinates":[145.033111572,-38.2741012573],"type":"Point"}
}