{
  "type": "Feature",
  "properties": {
    "iso:country":"AU",
    "sg:address":"11/ 15 Churchill Rd North",
    "sg:city":"Dry Creek",
    "sg:classifiers":[
        {
            "category":"Professional",
            "type":"Services"
        }
    ],
    "sg:phone":"+61 8 8349 4799",
    "sg:postcode":"5094",
    "sg:province":"SA",
    "sg:tags":[
        "forwarding",
        "agent",
        "transport"
    ],
    "wof:name":"Cobby Rick Pty Ltd",
    "wof:placetype":"venue"
},
  "geometry": {"coordinates":[138.588256836,-34.8364295959],"type":"Point"}
}