{
  "type": "Feature",
  "properties": {
    "addr:full":"Shop 3 / 2558 Gold Coast Hwy Mermaid Beach QLD 4218",
    "addr:housenumber":"shop 3 / 2558",
    "addr:postcode":"4218",
    "addr:street":"Gold Coast Hwy",
    "iso:country":"AU",
    "sg:address":"Shop 3 / 2558 Gold Coast Hwy",
    "sg:city":"Mermaid Beach",
    "sg:classifiers":[
        {
            "category":"Utilities",
            "subcategory":"Mobile Phone",
            "type":"Services"
        }
    ],
    "sg:phone":"+61 433 150 150",
    "sg:postcode":"4218",
    "sg:province":"QLD",
    "sg:tags":[
        "repair",
        "telephone"
    ],
    "wof:name":"Funky Fones Accessory Warehouse",
    "wof:placetype":"venue"
},
  "geometry": {"coordinates":[153.43341064399999,-28.0396461487],"type":"Point"}
}