{
  "type": "Feature",
  "properties": {
    "iso:country":"AU",
    "sg:address":"11/ 1 Manning St",
    "sg:city":"Tuncurry",
    "sg:classifiers":[
        {
            "category":"Health Services",
            "subcategory":"Dentist",
            "type":"Services"
        }
    ],
    "sg:phone":"+61 2 6554 7273",
    "sg:postcode":"2428",
    "sg:province":"NSW",
    "wof:name":"Isles Stewart",
    "wof:placetype":"venue"
},
  "geometry": {"coordinates":[152.50062600000001,-32.178593],"type":"Point"}
}