{
  "type": "Feature",
  "properties": {
    "addr:full":"14 Paxton St Frenchs Forest NSW 2086",
    "addr:housenumber":"14",
    "addr:postcode":"2086",
    "addr:street":"Paxton St",
    "iso:country":"AU",
    "sg:address":"14 Paxton St",
    "sg:city":"Frenchs Forest",
    "sg:classifiers":[
        {
            "category":"Real Estate",
            "subcategory":"Surveying",
            "type":"Services"
        }
    ],
    "sg:phone":"+61 2 9402 1206",
    "sg:postcode":"2086",
    "sg:province":"NSW",
    "sg:tags":[
        "surveyor",
        "land"
    ],
    "wof:name":"Palmer M J & Associates Pty Ltd",
    "wof:placetype":"venue"
},
  "geometry": {"coordinates":[151.24266052199999,-33.7471733093],"type":"Point"}
}