{
  "type": "Feature",
  "properties": {
    "addr:full":"Cnr Laurie & Woods Sts Newport West VIC 3015",
    "addr:postcode":"3015",
    "addr:street":"Cnr;West",
    "iso:country":"AU",
    "sg:address":"Cnr Laurie & Woods Sts",
    "sg:city":"Newport West",
    "sg:classifiers":[
        {
            "category":"Social Services",
            "subcategory":"Child Care",
            "type":"Services"
        }
    ],
    "sg:phone":"+61 3 9932 2040",
    "sg:postcode":"3015",
    "sg:province":"VIC",
    "sg:tags":[
        "support",
        "health"
    ],
    "wof:name":"Maternal & Child Health Centres",
    "wof:placetype":"venue"
},
  "geometry": {"coordinates":[144.87057495100001,-37.8431243896],"type":"Point"}
}