{
  "type": "Feature",
  "properties": {
    "iso:country":"AU",
    "sg:address":"Shop 11 Millstream Arcade, Mends St",
    "sg:city":"South Perth",
    "sg:classifiers":[
        {
            "category":"Personal",
            "subcategory":"Beauty Salon",
            "type":"Services"
        }
    ],
    "sg:phone":"+61 8 9474 1991",
    "sg:postcode":"6151",
    "sg:province":"WA",
    "wof:name":"Beauty On Mends",
    "wof:placetype":"venue"
},
  "geometry": {"coordinates":[115.85262299999999,-31.972372],"type":"Point"}
}