{
  "type": "Feature",
  "properties": {
    "addr:full":"Lancewood St Caloundra QLD 4551",
    "addr:postcode":"4551",
    "addr:street":"Lancewood St",
    "iso:country":"AU",
    "sg:address":"Lancewood St",
    "sg:city":"Caloundra",
    "sg:classifiers":[
        {
            "category":"Home & Garden",
            "subcategory":"Building Materials",
            "type":"Retail Goods"
        }
    ],
    "sg:phone":"+61 428 783 115",
    "sg:postcode":"4551",
    "sg:province":"QLD",
    "sg:tags":[
        "merchant",
        "glass",
        "glazier"
    ],
    "wof:name":"G.B.s Aluminium & Glass",
    "wof:placetype":"venue"
},
  "geometry": {"coordinates":[153.108612061,-26.7886943817],"type":"Point"}
}