{
  "type": "Feature",
  "properties": {
    "iso:country":"AU",
    "sg:address":"2/21 Ganges Crt",
    "sg:city":"Werribee",
    "sg:classifiers":[
        {
            "category":"Building & Trades",
            "subcategory":"Construction",
            "type":"Services"
        }
    ],
    "sg:phone":"+61 431 123 625",
    "sg:postcode":"3030",
    "sg:province":"VIC",
    "sg:tags":[
        "joiner",
        "carpenter"
    ],
    "wof:name":"X-Clusiv Carpentry",
    "wof:placetype":"venue"
},
  "geometry": {"coordinates":[144.660904,-37.876362],"type":"Point"}
}