{
  "type": "Feature",
  "properties": {
    "iso:country":"AU",
    "sg:address":"57 Gawler St",
    "sg:city":"Mt Barker",
    "sg:classifiers":[
        {
            "category":"Shopping",
            "subcategory":"Clothing, Apparel, & Fashions",
            "type":"Retail Goods"
        }
    ],
    "sg:phone":"+61 8 8391 4470",
    "sg:postcode":"5251",
    "sg:province":"SA",
    "sg:tags":[
        "menswear"
    ],
    "wof:name":"Outback Outpost",
    "wof:placetype":"venue"
},
  "geometry": {"coordinates":[138.85934448200001,-35.067073822],"type":"Point"}
}