{
  "type": "Feature",
  "properties": {
    "addr:full":"26 Elliott St Woolloongabba QLD 4102",
    "addr:housenumber":"26",
    "addr:postcode":"4102",
    "addr:street":"Elliott St",
    "iso:country":"AU",
    "sg:address":"26 Elliott St",
    "sg:city":"Woolloongabba",
    "sg:classifiers":[
        {
            "category":"Retail",
            "subcategory":"Auto Repair",
            "type":"Services"
        }
    ],
    "sg:phone":"+61 7 3391 4324",
    "sg:postcode":"4102",
    "sg:province":"QLD",
    "sg:tags":[
        "repairer",
        "motor",
        "engineer"
    ],
    "wof:name":"Shafston Service Centre",
    "wof:placetype":"venue"
},
  "geometry": {"coordinates":[153.03157043499999,-27.493686676],"type":"Point"}
}