{
  "type": "Feature",
  "properties": {
    "iso:country":"AU",
    "sg:address":"800 Chermside Rd",
    "sg:city":"Chermside",
    "sg:classifiers":[
        {
            "category":"Health Services",
            "subcategory":"Dentist",
            "type":"Services"
        }
    ],
    "sg:phone":"+61 7 3350 4344",
    "sg:postcode":"4032",
    "sg:province":"QLD",
    "wof:name":"Garraway Rachel",
    "wof:placetype":"venue"
},
  "geometry": {"coordinates":[153.03393600000001,-27.38636],"type":"Point"}
}