{
  "type": "Feature",
  "properties": {
    "addr:full":"Shop 12 Midland Gate Shopping Centre+The Crescent Mid WA 6056",
    "addr:housenumber":"shop 12",
    "addr:postcode":"6056",
    "addr:street":"Midland Gate Shopping Centre+The Crescent",
    "iso:country":"AU",
    "sg:address":"Shop 12",
    "sg:city":"Midland Gate Shopping Centre+The Crescent Mid",
    "sg:classifiers":[
        {
            "category":"Personal",
            "subcategory":"Beauty Salon",
            "type":"Services"
        }
    ],
    "sg:phone":"+61 8 9274 6811",
    "sg:postcode":"6056",
    "sg:province":"WA",
    "sg:tags":[
        "hairdresser"
    ],
    "wof:name":"Mussan for Hair",
    "wof:placetype":"venue"
},
  "geometry": {"coordinates":[116.009140015,-31.8885135651],"type":"Point"}
}