{
  "type": "Feature",
  "properties": {
    "addr:full":"94 Chloride St Broken Hill NSW 2880",
    "addr:housenumber":"94",
    "addr:postcode":"2880",
    "addr:street":"Chloride St",
    "iso:country":"AU",
    "sg:address":"94 Chloride St",
    "sg:city":"Broken Hill",
    "sg:classifiers":[
        {
            "category":"Retail",
            "subcategory":"Repair Shop",
            "type":"Services"
        }
    ],
    "sg:phone":"+61 8 8087 6487",
    "sg:postcode":"2880",
    "sg:province":"NSW",
    "sg:tags":[
        "upholsterer"
    ],
    "wof:name":"Silver City Trimmers",
    "wof:placetype":"venue"
},
  "geometry": {"coordinates":[141.464935303,-31.9569664001],"type":"Point"}
}