{
  "type": "Feature",
  "properties": {
    "iso:country":"AU",
    "sg:address":"Cnr Muldoon St & Grey Gum Rd",
    "sg:city":"Taree",
    "sg:classifiers":[
        {
            "category":"Utilities",
            "subcategory":"Fuel Oil & Lpg",
            "type":"Services"
        }
    ],
    "sg:phone":"+61 2 6551 0851",
    "sg:postcode":"2430",
    "sg:province":"NSW",
    "sg:tags":[
        "merchant"
    ],
    "wof:name":"Performance Fuels",
    "wof:placetype":"venue"
},
  "geometry": {"coordinates":[152.464523,-31.899712],"type":"Point"}
}