{
  "type": "Feature",
  "properties": {
    "addr:full":"Unit 5, 2092 Logan Rd Upper Mt Gravatt QLD 4122",
    "addr:housenumber":"2092",
    "addr:postcode":"4122",
    "addr:street":"Logan Rd Upper",
    "iso:country":"AU",
    "sg:address":"Unit 5, 2092 Logan Rd",
    "sg:city":"Upper Mt Gravatt",
    "sg:classifiers":[
        {
            "category":"Shopping",
            "subcategory":"Computers & Home Electronics",
            "type":"Retail Goods"
        }
    ],
    "sg:phone":"+61 7 3849 7866",
    "sg:postcode":"4122",
    "sg:province":"QLD",
    "sg:tags":[
        "hardware",
        "equipment"
    ],
    "wof:name":"Karel Cad",
    "wof:placetype":"venue"
},
  "geometry": {"coordinates":[153.08280944800001,-27.5609855652],"type":"Point"}
}