{
  "type": "Feature",
  "properties": {
    "addr:full":"Cnr Hidden Valley & Beaton Rds Berrimah NT 0828",
    "addr:housenumber":"cnr",
    "addr:postcode":"nt 0828",
    "iso:country":"AU",
    "sg:address":"Cnr Hidden Valley & Beaton Rds",
    "sg:city":"Berrimah",
    "sg:classifiers":[
        {
            "category":"Military Area",
            "subcategory":"Air Force Base",
            "type":"Public Place"
        }
    ],
    "sg:phone":"+61 8 8947 0870",
    "sg:postcode":"0828",
    "sg:province":"NT",
    "sg:tags":[
        "pole",
        "lighting",
        "power"
    ],
    "wof:name":"INGAL EPS",
    "wof:placetype":"venue"
},
  "geometry": {"coordinates":[130.916503906,-12.4344244003],"type":"Point"}
}