{
  "type": "Feature",
  "properties": {
    "iso:country":"AU",
    "sg:address":"489 Bilsen Rd",
    "sg:city":"Geebung",
    "sg:classifiers":[
        {
            "category":"Real Estate",
            "subcategory":"Real Estate Agent",
            "type":"Services"
        }
    ],
    "sg:phone":"+61 7 3865 4545",
    "sg:postcode":"4034",
    "sg:province":"QLD",
    "sg:tags":[
        "handyman's",
        "equipment",
        "hire",
        "builders",
        "contractor"
    ],
    "wof:name":"Skyreach Pty Ltd",
    "wof:placetype":"venue"
},
  "geometry": {"coordinates":[153.05694600000001,-27.366812],"type":"Point"}
}