{
  "type": "Feature",
  "properties": {
    "addr:full":"62 Marshall St Dapto NSW 2530",
    "addr:housenumber":"62",
    "addr:postcode":"2530",
    "addr:street":"Marshall St",
    "iso:country":"AU",
    "sg:address":"62 Marshall St",
    "sg:city":"Dapto",
    "sg:classifiers":[
        {
            "category":"Retail",
            "subcategory":"Auto Repair",
            "type":"Services"
        }
    ],
    "sg:phone":"+61 2 4262 2646",
    "sg:postcode":"2530",
    "sg:province":"NSW",
    "sg:tags":[
        "testing",
        "inspection",
        "motor",
        "vehicle"
    ],
    "wof:name":"Bruce Buddens Automotive",
    "wof:placetype":"venue"
},
  "geometry": {"coordinates":[150.78918457,-34.499546051],"type":"Point"}
}