{
  "type": "Feature",
  "properties": {
    "addr:full":"AMEC Vere St Collingwood VIC 3066",
    "addr:postcode":"3066",
    "addr:street":"Vere St",
    "iso:country":"AU",
    "sg:address":"AMEC Vere St",
    "sg:city":"Collingwood",
    "sg:classifiers":[
        {
            "category":"Education",
            "subcategory":"University",
            "type":"Public Place"
        }
    ],
    "sg:phone":"+61 3 9417 4183",
    "sg:postcode":"3066",
    "sg:province":"VIC",
    "sg:tags":[
        "educational",
        "organisation",
        "cultural"
    ],
    "wof:name":"AMES Volunteer Tutor Program",
    "wof:placetype":"venue"
},
  "geometry": {"coordinates":[144.988189697,-37.8020553589],"type":"Point"}
}