{
  "type": "Feature",
  "properties": {
    "addr:full":"25- 31 Main St Woodside SA 5244",
    "addr:housenumber":"31",
    "addr:postcode":"5244",
    "addr:street":"Main St",
    "iso:country":"AU",
    "sg:address":"25- 31 Main St",
    "sg:city":"Woodside",
    "sg:classifiers":[
        {
            "category":"Manufacturing",
            "subcategory":"Motor Vehicles & Parts",
            "type":"Manufacturing & Wholesale Goods"
        }
    ],
    "sg:phone":"+61 8 8389 9283",
    "sg:postcode":"5244",
    "sg:province":"SA",
    "sg:tags":[
        "engine",
        "equipment",
        "diesel"
    ],
    "wof:name":"Kelley Diesel Services",
    "wof:placetype":"venue"
},
  "geometry": {"coordinates":[138.87393188499999,-34.9071083069],"type":"Point"}
}