{
  "type": "Feature",
  "properties": {
    "iso:country":"AU",
    "sg:address":"437 Fullarton Rd",
    "sg:city":"Highgate",
    "sg:classifiers":[
        {
            "category":"Personal",
            "subcategory":"Beauty Salon",
            "type":"Services"
        }
    ],
    "sg:phone":"+61 8 8271 8948",
    "sg:postcode":"5063",
    "sg:province":"SA",
    "sg:tags":[
        "hairdresser"
    ],
    "wof:name":"Highgate Hair",
    "wof:placetype":"venue"
},
  "geometry": {"coordinates":[138.62594604500001,-34.9596672058],"type":"Point"}
}