{
  "type": "Feature",
  "properties": {
    "addr:full":"PO Box 2 Morpeth NSW 2321",
    "addr:postcode":"2321",
    "iso:country":"AU",
    "sg:address":"PO Box 2",
    "sg:city":"Morpeth",
    "sg:classifiers":[
        {
            "category":"Utilities",
            "subcategory":"Water",
            "type":"Services"
        }
    ],
    "sg:phone":"+61 2 4934 3091",
    "sg:postcode":"2321",
    "sg:province":"NSW",
    "sg:tags":[
        "hot",
        "system"
    ],
    "wof:name":"Brad Lantry Plumbing Services Pty Ltd",
    "wof:placetype":"venue"
},
  "geometry": {"coordinates":[151.627044678,-32.7248497009],"type":"Point"}
}