{
  "type": "Feature",
  "properties": {
    "iso:country":"AU",
    "sg:address":"5 Berrallan St",
    "sg:city":"Greenwell Point",
    "sg:classifiers":[
        {
            "category":"Autos & Motor Vehicles",
            "subcategory":"Motorcycle Sales",
            "type":"Retail Goods"
        }
    ],
    "sg:phone":"+61 2 4447 0404",
    "sg:postcode":"2540",
    "sg:province":"NSW",
    "sg:tags":[
        "outboard"
    ],
    "wof:name":"Murray's Mobile Maintenance",
    "wof:placetype":"venue"
},
  "geometry": {"coordinates":[150.72837829599999,-34.9057312012],"type":"Point"}
}