{
  "type": "Feature",
  "properties": {
    "addr:full":"Unit 1/ 69 Mayne St Murrurundi NSW 2338",
    "addr:housenumber":"69",
    "addr:postcode":"2338",
    "addr:street":"Mayne St",
    "iso:country":"AU",
    "sg:address":"Unit 1/ 69 Mayne St",
    "sg:city":"Murrurundi",
    "sg:classifiers":[
        {
            "category":"Farming",
            "subcategory":"Fish & Marine Products",
            "type":"Manufacturing & Wholesale Goods"
        }
    ],
    "sg:phone":"+61 2 6546 6007",
    "sg:postcode":"2338",
    "sg:province":"NSW",
    "sg:tags":[
        "organic"
    ],
    "wof:name":"Dynamic Wholefoods",
    "wof:placetype":"venue"
},
  "geometry": {"coordinates":[150.83815002399999,-31.7649326324],"type":"Point"}
}