{
  "type": "Feature",
  "properties": {
    "iso:country":"AU",
    "sg:address":"69 Hebe St",
    "sg:city":"Bardon",
    "sg:classifiers":[
        {
            "category":"Professional",
            "subcategory":"Art Services",
            "type":"Services"
        }
    ],
    "sg:phone":"+61 7 3369 1106",
    "sg:postcode":"4065",
    "sg:province":"QLD",
    "sg:tags":[
        "decorator",
        "painter"
    ],
    "wof:name":"Ascot Painters",
    "wof:placetype":"venue"
},
  "geometry": {"coordinates":[152.98507690400001,-27.4648303986],"type":"Point"}
}