{
  "type": "Feature",
  "properties": {
    "addr:full":"32 Richard St Bourke NSW 2840",
    "addr:housenumber":"32",
    "addr:postcode":"2840",
    "addr:street":"Richard St",
    "iso:country":"AU",
    "sg:address":"32 Richard St",
    "sg:city":"Bourke",
    "sg:classifiers":[
        {
            "category":"Freight",
            "type":"Transportation"
        }
    ],
    "sg:phone":"+61 2 6872 2092",
    "sg:postcode":"2840",
    "sg:province":"NSW",
    "sg:tags":[
        "light",
        "carrier"
    ],
    "wof:name":"Bourke Courier Service",
    "wof:placetype":"venue"
},
  "geometry": {"coordinates":[145.937759,-30.087912],"type":"Point"}
}