{
  "type": "Feature",
  "properties": {
    "iso:country":"AU",
    "sg:address":"5 Victoria Ave",
    "sg:city":"Castle Hill",
    "sg:classifiers":[
        {
            "category":"Building & Trades",
            "subcategory":"Construction",
            "type":"Services"
        }
    ],
    "sg:phone":"+61 1300 880 590",
    "sg:postcode":"2154",
    "sg:province":"NSW",
    "sg:tags":[
        "pool",
        "swimming"
    ],
    "wof:name":"Inpools Australia Pty Ltd",
    "wof:placetype":"venue"
},
  "geometry": {"coordinates":[150.981079102,-33.7336502075],"type":"Point"}
}