{
  "type": "Feature",
  "properties": {
    "addr:full":"Neals Rd Farleigh QLD 4741",
    "addr:postcode":"4741",
    "addr:street":"Neals Rd",
    "iso:country":"AU",
    "sg:address":"Neals Rd",
    "sg:city":"Farleigh",
    "sg:classifiers":[
        {
            "category":"Farming",
            "subcategory":"Nursery",
            "type":"Manufacturing & Wholesale Goods"
        }
    ],
    "sg:phone":"+61 7 4959 8942",
    "sg:postcode":"4741",
    "sg:province":"QLD",
    "wof:name":"North Queensland Foliage Supplies Pty Ltd",
    "wof:placetype":"venue"
},
  "geometry": {"coordinates":[149.092026,-21.10285],"type":"Point"}
}