{
  "type": "Feature",
  "properties": {
    "iso:country":"AU",
    "sg:address":"401 Moreland Rd",
    "sg:city":"Coburg",
    "sg:classifiers":[
        {
            "category":"Fast Food",
            "type":"Food & Drink"
        }
    ],
    "sg:phone":"+61 3 9386 6252",
    "sg:postcode":"3058",
    "sg:province":"VIC",
    "sg:tags":[
        "away",
        "take"
    ],
    "wof:name":"Red Rooster",
    "wof:placetype":"venue"
},
  "geometry": {"coordinates":[144.94619750999999,-37.7531814575],"type":"Point"}
}