{
  "type": "Feature",
  "properties": {
    "iso:country":"AU",
    "sg:address":"30 Aurora Pl",
    "sg:city":"Bateau Bay",
    "sg:classifiers":[
        {
            "category":"Home & Garden",
            "subcategory":"Carpets & Floor Coverings",
            "type":"Retail Goods"
        }
    ],
    "sg:phone":"+61 400 996 001",
    "sg:postcode":"2261",
    "sg:province":"NSW",
    "sg:tags":[
        "tile",
        "wall",
        "layer"
    ],
    "wof:name":"Darren Gilbert",
    "wof:placetype":"venue"
},
  "geometry": {"coordinates":[151.468063,-33.392799],"type":"Point"}
}