{
  "type": "Feature",
  "properties": {
    "addr:full":"PO Box 361 Proserpine QLD 4800",
    "addr:postcode":"4800",
    "iso:country":"AU",
    "sg:address":"PO Box 361",
    "sg:city":"Proserpine",
    "sg:classifiers":[
        {
            "category":"Farming",
            "subcategory":"Farm",
            "type":"Manufacturing & Wholesale Goods"
        }
    ],
    "sg:phone":"+61 7 4947 5124",
    "sg:postcode":"4800",
    "sg:province":"QLD",
    "sg:tags":[
        "farmer"
    ],
    "wof:name":"Winton W F & L B",
    "wof:placetype":"venue"
},
  "geometry": {"coordinates":[148.59341430699999,-20.4060001373],"type":"Point"}
}