{
  "type": "Feature",
  "properties": {
    "addr:full":"14 Smalls Rd Camden NSW 2570",
    "addr:housenumber":"14",
    "addr:postcode":"2570",
    "addr:street":"Smalls Rd",
    "iso:country":"AU",
    "sg:address":"14 Smalls Rd",
    "sg:city":"Camden",
    "sg:classifiers":[
        {
            "category":"Building & Trades",
            "subcategory":"Construction",
            "type":"Services"
        }
    ],
    "sg:phone":"+61 2 4655 1411",
    "sg:postcode":"2570",
    "sg:province":"NSW",
    "sg:tags":[
        "concrete",
        "contractor"
    ],
    "wof:name":"Legovic M & M",
    "wof:placetype":"venue"
},
  "geometry": {"coordinates":[150.66885375999999,-34.0539703369],"type":"Point"}
}