{
  "type": "Feature",
  "properties": {
    "addr:full":"80 Mann St Armidale NSW 2350",
    "addr:housenumber":"80",
    "addr:postcode":"2350",
    "addr:street":"Mann St",
    "iso:country":"AU",
    "sg:address":"80 Mann St",
    "sg:city":"Armidale",
    "sg:classifiers":[
        {
            "category":"Farming",
            "subcategory":"Farm & Veterinary Services",
            "type":"Manufacturing & Wholesale Goods"
        }
    ],
    "sg:phone":"+61 2 6771 1620",
    "sg:postcode":"2350",
    "sg:province":"NSW",
    "sg:tags":[
        "agricultural",
        "advisory"
    ],
    "wof:name":"Armidale Tree Group Inc.",
    "wof:placetype":"venue"
},
  "geometry": {"coordinates":[151.67007446299999,-30.5222835541],"type":"Point"}
}