{
  "type": "Feature",
  "properties": {
    "addr:full":"Novotel, Princess St Brighton-le-Sands NSW 2216",
    "addr:postcode":"2216",
    "addr:street":"Princess St",
    "iso:country":"AU",
    "sg:address":"Novotel, Princess St",
    "sg:city":"Brighton-le-Sands",
    "sg:classifiers":[
        {
            "category":"Sports & Exercise",
            "subcategory":"Gym",
            "type":"Entertainment"
        }
    ],
    "sg:phone":"+61 2 9567 6133",
    "sg:postcode":"2216",
    "sg:province":"NSW",
    "sg:tags":[
        "health",
        "fitness"
    ],
    "wof:name":"Revive Day Spa & Fitness Centre",
    "wof:placetype":"venue"
},
  "geometry": {"coordinates":[151.15643299999999,-33.959923],"type":"Point"}
}