{
  "type": "Feature",
  "properties": {
    "addr:full":"318 Church St Parramatta NSW 2140",
    "addr:housenumber":"318",
    "addr:postcode":"2140",
    "addr:street":"Church St",
    "iso:country":"AU",
    "sg:address":"318 Church St",
    "sg:city":"Parramatta",
    "sg:classifiers":[
        {
            "category":"Food & Beverages",
            "subcategory":"Bakery",
            "type":"Retail Goods"
        }
    ],
    "sg:phone":"+61 2 9687 7766",
    "sg:postcode":"2140",
    "sg:province":"NSW",
    "sg:tags":[
        "cake",
        "shop",
        "pastry"
    ],
    "wof:name":"Lellos",
    "wof:placetype":"venue"
},
  "geometry": {"coordinates":[151.074295044,-33.8632202148],"type":"Point"}
}