{
  "type": "Feature",
  "properties": {
    "iso:country":"AU",
    "sg:address":"7934 Goulburn Valley Hwy",
    "sg:city":"Kialla",
    "sg:classifiers":[
        {
            "category":"Autos & Motor Vehicles",
            "subcategory":"Auto Supplies",
            "type":"Retail Goods"
        }
    ],
    "sg:phone":"+61 3 5823 1638",
    "sg:postcode":"3631",
    "sg:province":"VIC",
    "sg:tags":[
        "camper-trailers",
        "caravan",
        "equipment"
    ],
    "wof:name":"Kialla Caravans Pty Ltd",
    "wof:placetype":"venue"
},
  "geometry": {"coordinates":[145.389572144,-36.4276161194],"type":"Point"}
}