{
  "type": "Feature",
  "properties": {
    "addr:full":"22 Cambridge Drv Wangaratta VIC 3677",
    "addr:housenumber":"22",
    "addr:postcode":"3677",
    "addr:street":"Cambridge Drv",
    "iso:country":"AU",
    "sg:address":"22 Cambridge Drv",
    "sg:city":"Wangaratta",
    "sg:classifiers":[
        {
            "category":"Building & Trades",
            "subcategory":"Plumbing",
            "type":"Services"
        }
    ],
    "sg:phone":"+61 3 5721 7899",
    "sg:postcode":"3677",
    "sg:province":"VIC",
    "sg:tags":[
        "plumber",
        "gasfitters"
    ],
    "wof:name":"Dean Plumbing Pty Ltd",
    "wof:placetype":"venue"
},
  "geometry": {"coordinates":[146.318527222,-36.3704109192],"type":"Point"}
}