{
  "type": "Feature",
  "properties": {
    "iso:country":"AU",
    "sg:address":"107- 113 Crown St",
    "sg:city":"East Sydney",
    "sg:classifiers":[
        {
            "category":"Sports & Exercise",
            "subcategory":"Gym",
            "type":"Entertainment"
        }
    ],
    "sg:phone":"+61 2 9360 6247",
    "sg:postcode":"2010",
    "sg:province":"NSW",
    "sg:tags":[
        "health",
        "fitness"
    ],
    "wof:name":"City Gym",
    "wof:placetype":"venue"
},
  "geometry": {"coordinates":[151.21592712399999,-33.8753395081],"type":"Point"}
}