{
  "type": "Feature",
  "properties": {
    "addr:full":"24 Braidwood Rd Goulburn NSW 2580",
    "addr:housenumber":"24",
    "addr:postcode":"2580",
    "addr:street":"Braidwood Rd",
    "iso:country":"AU",
    "sg:address":"24 Braidwood Rd",
    "sg:city":"Goulburn",
    "sg:classifiers":[
        {
            "category":"Commercial Area",
            "type":"Public Place"
        }
    ],
    "sg:phone":"+61 2 4821 4498",
    "sg:postcode":"2580",
    "sg:province":"NSW",
    "sg:tags":[
        "heavy",
        "carrier"
    ],
    "wof:name":"McIntyre's Transport",
    "wof:placetype":"venue"
},
  "geometry": {"coordinates":[149.71180725100001,-34.772983551],"type":"Point"}
}