{
  "type": "Feature",
  "properties": {
    "iso:country":"AU",
    "sg:address":"314 Mulgrave Rd",
    "sg:city":"Cairns",
    "sg:classifiers":[
        {
            "category":"Travel",
            "subcategory":"Hotels & Motels",
            "type":"Entertainment"
        }
    ],
    "sg:phone":"+61 7 4031 1777",
    "sg:postcode":"4870",
    "sg:province":"QLD",
    "sg:website":"http://www.tropicalgardenscairns.com.au",
    "wof:name":"Cairns Tropical Gardens Motel",
    "wof:placetype":"venue"
},
  "geometry": {"coordinates":[145.74720764200001,-16.9377384186],"type":"Point"}
}