{
  "type": "Feature",
  "properties": {
    "addr:full":"25 Carrington Rd Waverley NSW 2024",
    "addr:housenumber":"25",
    "addr:postcode":"2024",
    "addr:street":"Carrington Rd",
    "iso:country":"AU",
    "sg:address":"25 Carrington Rd",
    "sg:city":"Waverley",
    "sg:classifiers":[
        {
            "category":"Education",
            "subcategory":"School",
            "type":"Public Place"
        }
    ],
    "sg:phone":"+61 2 9389 1929",
    "sg:postcode":"2024",
    "sg:province":"NSW",
    "sg:tags":[
        "girl"
    ],
    "wof:name":"St Clare's College",
    "wof:placetype":"venue"
},
  "geometry": {"coordinates":[151.25396728499999,-33.8979721069],"type":"Point"}
}