{
  "type": "Feature",
  "properties": {
    "addr:full":"55 City Rd South Melbourne VIC 3205",
    "addr:housenumber":"55",
    "addr:postcode":"3205",
    "addr:street":"City Rd",
    "iso:country":"AU",
    "sg:address":"55 City Rd",
    "sg:city":"South Melbourne",
    "sg:classifiers":[
        {
            "category":"Shopping",
            "subcategory":"Computers & Home Electronics",
            "type":"Retail Goods"
        }
    ],
    "sg:phone":"+61 3 9686 1166",
    "sg:postcode":"3205",
    "sg:province":"VIC",
    "sg:tags":[
        "hardware",
        "equipment"
    ],
    "wof:name":"Printer Power Pty Ltd",
    "wof:placetype":"venue"
},
  "geometry": {"coordinates":[144.96603400000001,-37.821884],"type":"Point"}
}