{
  "type": "Feature",
  "properties": {
    "addr:full":"14 Heather St Heatherbrae NSW 2324",
    "addr:housenumber":"14",
    "addr:postcode":"2324",
    "addr:street":"Heather St",
    "iso:country":"AU",
    "sg:address":"14 Heather St",
    "sg:city":"Heatherbrae",
    "sg:classifiers":[
        {
            "category":"Professional",
            "subcategory":"Detective & Security Services",
            "type":"Services"
        }
    ],
    "sg:phone":"+61 2 4987 3303",
    "sg:postcode":"2324",
    "sg:province":"NSW",
    "sg:tags":[
        "protective",
        "rustproofing"
    ],
    "wof:name":"Stuart Jones Precision Body Repairs",
    "wof:placetype":"venue"
},
  "geometry": {"coordinates":[151.73501586899999,-32.7855873108],"type":"Point"}
}