{
  "type": "Feature",
  "properties": {
    "iso:country":"AU",
    "sg:address":"Trowbridge House 9 Luhrs Rd",
    "sg:city":"Payneham South",
    "sg:classifiers":[
        {
            "category":"Health Services",
            "subcategory":"Nursing And Care Facility",
            "type":"Services"
        }
    ],
    "sg:phone":"+61 8 8332 3155",
    "sg:postcode":"5070",
    "sg:province":"SA",
    "sg:tags":[
        "home"
    ],
    "wof:name":"Eldercare Incorporated",
    "wof:placetype":"venue"
},
  "geometry": {"coordinates":[138.641387939,-34.9047241211],"type":"Point"}
}