{
  "type": "Feature",
  "properties": {
    "addr:full":"226 South Pine Rd Enoggera QLD 4051",
    "addr:housenumber":"226",
    "addr:postcode":"4051",
    "addr:street":"South Pine Rd",
    "iso:country":"AU",
    "sg:address":"226 South Pine Rd",
    "sg:city":"Enoggera",
    "sg:classifiers":[
        {
            "category":"Retail",
            "subcategory":"Repair Shop",
            "type":"Services"
        }
    ],
    "sg:phone":"+61 7 3355 0600",
    "sg:postcode":"4051",
    "sg:province":"QLD",
    "sg:tags":[
        "machine",
        "repairs",
        "part",
        "dryer",
        "washing"
    ],
    "wof:name":"Shannons Electrical Service",
    "wof:placetype":"venue"
},
  "geometry": {"coordinates":[152.995559692,-27.4177474976],"type":"Point"}
}