{
  "type": "Feature",
  "properties": {
    "addr:full":"5 Fay St Balwyn North VIC 3104",
    "addr:housenumber":"5",
    "addr:postcode":"3104",
    "addr:street":"Fay St",
    "iso:country":"AU",
    "sg:address":"5 Fay St",
    "sg:city":"Balwyn North",
    "sg:classifiers":[
        {
            "category":"Building & Trades",
            "subcategory":"Equipment Rental",
            "type":"Services"
        }
    ],
    "sg:phone":"+61 3 9857 9744",
    "sg:postcode":"3104",
    "sg:province":"VIC",
    "sg:tags":[
        "supply",
        "catering"
    ],
    "wof:name":"Radford Mark",
    "wof:placetype":"venue"
},
  "geometry": {"coordinates":[145.09132385300001,-37.7876396179],"type":"Point"}
}