{
  "type": "Feature",
  "properties": {
    "addr:full":"58 Banyula Pl Mt Colah NSW 2079",
    "addr:housenumber":"58",
    "addr:postcode":"2079",
    "addr:street":"Banyula Pl Mt Colah",
    "iso:country":"AU",
    "sg:address":"58 Banyula Pl",
    "sg:city":"Mt Colah",
    "sg:classifiers":[
        {
            "category":"Retail",
            "subcategory":"Event Space",
            "type":"Services"
        }
    ],
    "sg:phone":"+61 2 9457 6931",
    "sg:postcode":"2079",
    "sg:province":"NSW",
    "sg:tags":[
        "venue",
        "reception",
        "wedding"
    ],
    "wof:name":"A Brides Best Friend Wedding Planning & Consultancy Services",
    "wof:placetype":"venue"
},
  "geometry": {"coordinates":[151.123504639,-33.6549530029],"type":"Point"}
}