{
  "type": "Feature",
  "properties": {
    "iso:country":"AU",
    "sg:address":"7a Gregory St",
    "sg:city":"Sandy Bay",
    "sg:classifiers":[
        {
            "category":"Personal",
            "subcategory":"Beauty Salon",
            "type":"Services"
        }
    ],
    "sg:phone":"+61 3 6224 0139",
    "sg:postcode":"7005",
    "sg:province":"TAS",
    "wof:name":"Ella Bache Sandy Bay",
    "wof:placetype":"venue"
},
  "geometry": {"coordinates":[147.32713317899999,-42.8956794739],"type":"Point"}
}