{
  "type": "Feature",
  "properties": {
    "iso:country":"AU",
    "sg:address":"Suite 22/ 10 Bridge St",
    "sg:city":"Granville",
    "sg:classifiers":[
        {
            "category":"Banks & Credit Unions",
            "subcategory":"Financial Services",
            "type":"Services"
        }
    ],
    "sg:phone":"+61 2 9637 8955",
    "sg:postcode":"1830",
    "sg:province":"NSW",
    "sg:tags":[
        "planning"
    ],
    "wof:name":"Retire Secure Pty Ltd",
    "wof:placetype":"venue"
},
  "geometry": {"coordinates":[151.04307556099999,-33.8640785217],"type":"Point"}
}