{
  "type": "Feature",
  "properties": {
    "addr:full":"34 Mt Vernon Drv Kambah ACT 2902",
    "addr:housenumber":"34",
    "addr:postcode":"2902",
    "addr:street":"Mt Vernon Drv",
    "iso:country":"AU",
    "sg:address":"34 Mt Vernon Drv",
    "sg:city":"Kambah",
    "sg:classifiers":[
        {
            "category":"Wholesale",
            "subcategory":"Drugs",
            "type":"Manufacturing & Wholesale Goods"
        }
    ],
    "sg:phone":"+61 2 6296 4101",
    "sg:postcode":"2902",
    "sg:province":"ACT",
    "sg:tags":[
        "wholesaler",
        "pharmaceutical",
        "product",
        "mfrs"
    ],
    "wof:name":"Woolias Consultancy Services Pty Ltd",
    "wof:placetype":"venue"
},
  "geometry": {"coordinates":[149.03607177699999,-35.3882102966],"type":"Point"}
}