{
  "type": "Feature",
  "properties": {
    "iso:country":"AU",
    "sg:address":"256 Whitehorse Rd",
    "sg:city":"Balwyn",
    "sg:classifiers":[
        {
            "category":"Shopping",
            "subcategory":"Clothing, Apparel, & Fashions",
            "type":"Retail Goods"
        }
    ],
    "sg:phone":"+61 3 9836 6944",
    "sg:postcode":"3103",
    "sg:province":"VIC",
    "sg:tags":[
        "lady",
        "wear"
    ],
    "wof:name":"Blue Illusion Pty Ltd",
    "wof:placetype":"venue"
},
  "geometry": {"coordinates":[145.08201599099999,-37.8130187988],"type":"Point"}
}