{
  "type": "Feature",
  "properties": {
    "addr:full":"236 Commercial St West Mt Gambier SA 5290",
    "addr:housenumber":"236",
    "addr:postcode":"5290",
    "addr:street":"Commercial St West",
    "iso:country":"AU",
    "sg:address":"236 Commercial St West",
    "sg:city":"Mt Gambier",
    "sg:classifiers":[
        {
            "category":"Food & Beverages",
            "subcategory":"Groceries & Convenience Stores",
            "type":"Retail Goods"
        }
    ],
    "sg:phone":"+61 8 8725 2705",
    "sg:postcode":"5290",
    "sg:province":"SA",
    "wof:name":"Rosaville General Store",
    "wof:placetype":"venue"
},
  "geometry": {"coordinates":[140.764633,-37.823132],"type":"Point"}
}