{
  "type": "Feature",
  "properties": {
    "addr:full":"145 Foster St Dandenong VIC 3175",
    "addr:housenumber":"145",
    "addr:postcode":"3175",
    "addr:street":"Foster St",
    "iso:country":"AU",
    "sg:address":"145 Foster St",
    "sg:city":"Dandenong",
    "sg:classifiers":[
        {
            "category":"Cafe",
            "type":"Food & Drink"
        }
    ],
    "sg:phone":"+61 3 9793 5125",
    "sg:postcode":"3175",
    "sg:province":"VIC",
    "wof:name":"Tamo Daleko",
    "wof:placetype":"venue"
},
  "geometry": {"coordinates":[145.21565246599999,-37.9898414612],"type":"Point"}
}