{
  "type": "Feature",
  "properties": {
    "addr:full":"128 Waratah Rd Wentworth Falls NSW 2782",
    "addr:housenumber":"128",
    "addr:postcode":"2782",
    "addr:street":"Waratah Rd",
    "iso:country":"AU",
    "sg:address":"128 Waratah Rd",
    "sg:city":"Wentworth Falls",
    "sg:classifiers":[
        {
            "category":"Health Services",
            "subcategory":"Health Practitioner",
            "type":"Services"
        }
    ],
    "sg:phone":"+61 2 4757 3066",
    "sg:postcode":"2782",
    "sg:province":"NSW",
    "sg:tags":[
        "psychotherapist"
    ],
    "wof:name":"MacFarlane, Susan",
    "wof:placetype":"venue"
},
  "geometry": {"coordinates":[150.35905456500001,-33.6990127563],"type":"Point"}
}