{
  "type": "Feature",
  "properties": {
    "addr:full":"Unit 4,71- 73 Lords Rd Leichhardt NSW 2040",
    "addr:housenumber":"4,71 73",
    "addr:postcode":"2040",
    "addr:street":"Lords Rd",
    "iso:country":"AU",
    "sg:address":"Unit 4,71- 73 Lords Rd",
    "sg:city":"Leichhardt",
    "sg:classifiers":[
        {
            "category":"Health Services",
            "subcategory":"Doctor",
            "type":"Services"
        }
    ],
    "sg:phone":"+61 2 9569 2122",
    "sg:postcode":"2040",
    "sg:province":"NSW",
    "sg:tags":[
        "occupational",
        "safety"
    ],
    "wof:name":"Store-Safe",
    "wof:placetype":"venue"
},
  "geometry": {"coordinates":[151.14584400000001,-33.886093],"type":"Point"}
}