{
  "type": "Feature",
  "properties": {
    "addr:full":"24 Hawkin Drv St Lucia QLD 4067",
    "addr:housenumber":"24",
    "addr:postcode":"4067",
    "addr:street":"Hawkin Drv",
    "iso:country":"AU",
    "sg:address":"24 Hawkin Drv",
    "sg:city":"St Lucia",
    "sg:classifiers":[
        {
            "category":"Personal",
            "type":"Services"
        }
    ],
    "sg:phone":"+61 7 3371 4704",
    "sg:postcode":"4067",
    "sg:province":"QLD",
    "sg:tags":[
        "gift"
    ],
    "wof:name":"St Lucia House Of Flowers",
    "wof:placetype":"venue"
},
  "geometry": {"coordinates":[152.99656677199999,-27.5015544891],"type":"Point"}
}