{
  "type": "Feature",
  "properties": {
    "iso:country":"AU",
    "sg:address":"10 Milan St",
    "sg:city":"Wantirna",
    "sg:classifiers":[
        {
            "category":"Home & Garden",
            "subcategory":"Carpets & Floor Coverings",
            "type":"Retail Goods"
        }
    ],
    "sg:phone":"+61 3 9720 1306",
    "sg:postcode":"3152",
    "sg:province":"VIC",
    "sg:tags":[
        "layer",
        "planner"
    ],
    "wof:name":"D & J Carpet Laying Service",
    "wof:placetype":"venue"
},
  "geometry": {"coordinates":[145.23280334500001,-37.8456878662],"type":"Point"}
}