{
  "type": "Feature",
  "properties": {
    "iso:country":"AU",
    "sg:address":"PO Box 357",
    "sg:city":"Main Beach",
    "sg:classifiers":[
        {
            "category":"Shopping",
            "subcategory":"Computers & Home Electronics",
            "type":"Retail Goods"
        }
    ],
    "sg:phone":"+61 7 5532 4393",
    "sg:postcode":"4217",
    "sg:province":"QLD",
    "sg:tags":[
        "equipment",
        "multimedia"
    ],
    "wof:name":"Evolution Web Systems",
    "wof:placetype":"venue"
},
  "geometry": {"coordinates":[153.429153442,-27.982339859],"type":"Point"}
}