{
  "type": "Feature",
  "properties": {
    "addr:full":"9 Day St East Maitland NSW 2323",
    "addr:housenumber":"9",
    "addr:postcode":"2323",
    "addr:street":"Day St",
    "iso:country":"AU",
    "sg:address":"9 Day St",
    "sg:city":"East Maitland",
    "sg:classifiers":[
        {
            "category":"Cafe",
            "type":"Food & Drink"
        }
    ],
    "sg:phone":"+61 2 4936 6867",
    "sg:postcode":"2323",
    "sg:province":"NSW",
    "wof:name":"Anoushka&#039;a Cafe",
    "wof:placetype":"venue"
},
  "geometry": {"coordinates":[151.58731079099999,-32.7458114624],"type":"Point"}
}