{
  "type": "Feature",
  "properties": {
    "addr:full":"Factory 1/ 21 Lindaway Pl Tullamarine VIC 3043",
    "addr:housenumber":"/ 21",
    "addr:postcode":"3043",
    "addr:street":"Lindaway Pl",
    "iso:country":"AU",
    "sg:address":"Factory 1/ 21 Lindaway Pl",
    "sg:city":"Tullamarine",
    "sg:classifiers":[
        {
            "category":"Manufacturing",
            "subcategory":"Tools & Machinery",
            "type":"Manufacturing & Wholesale Goods"
        }
    ],
    "sg:phone":"+61 3 9335 1132",
    "sg:postcode":"3043",
    "sg:province":"VIC",
    "sg:tags":[
        "wholesaler",
        "lingerie",
        "mfrs",
        "sleepwear"
    ],
    "wof:name":"Rogi Lingerie",
    "wof:placetype":"venue"
},
  "geometry": {"coordinates":[144.887207031,-37.7029075623],"type":"Point"}
}