{
  "type": "Feature",
  "properties": {
    "iso:country":"AU",
    "sg:address":"Level 14, 380 St Kilda Rd",
    "sg:city":"Melbourne",
    "sg:classifiers":[
        {
            "category":"Professional",
            "subcategory":"Employment Agencies",
            "type":"Services"
        }
    ],
    "sg:phone":"+61 3 9696 2300",
    "sg:postcode":"3000",
    "sg:province":"VIC",
    "sg:tags":[
        "hire",
        "labour",
        "contractor"
    ],
    "wof:name":"The Interchange Bench",
    "wof:placetype":"venue"
},
  "geometry": {"coordinates":[144.97140502900001,-37.8321914673],"type":"Point"}
}