{
  "type": "Feature",
  "properties": {
    "addr:full":"142 Pine Ave Mildura VIC 3500",
    "addr:housenumber":"142",
    "addr:postcode":"3500",
    "addr:street":"Pine Ave",
    "iso:country":"AU",
    "sg:address":"142 Pine Ave",
    "sg:city":"Mildura",
    "sg:classifiers":[
        {
            "category":"Building & Trades",
            "subcategory":"Cleaning & Sanitation",
            "type":"Services"
        }
    ],
    "sg:phone":"+61 3 5022 1579",
    "sg:postcode":"3500",
    "sg:province":"VIC",
    "sg:tags":[
        "industrial",
        "commercial",
        "contractor"
    ],
    "wof:name":"Sunny Services",
    "wof:placetype":"venue"
},
  "geometry": {"coordinates":[142.15538024899999,-34.1861076355],"type":"Point"}
}