{
  "type": "Feature",
  "properties": {
    "iso:country":"AU",
    "sg:address":"251 Thompson Rd",
    "sg:city":"Geelong",
    "sg:classifiers":[
        {
            "category":"Home & Garden",
            "subcategory":"Building Materials",
            "type":"Retail Goods"
        }
    ],
    "sg:phone":"+61 3 5272 2177",
    "sg:postcode":"3220",
    "sg:province":"VIC",
    "sg:tags":[
        "fitting",
        "door"
    ],
    "wof:name":"Doors Plus",
    "wof:placetype":"venue"
},
  "geometry": {"coordinates":[144.343918,-38.107285],"type":"Point"}
}