{
  "type": "Feature",
  "properties": {
    "addr:full":"3/ 1 Shoebury St Rocklea QLD 4106",
    "addr:housenumber":"/ 1",
    "addr:postcode":"4106",
    "addr:street":"Shoebury St",
    "iso:country":"AU",
    "sg:address":"3/ 1 Shoebury St",
    "sg:city":"Rocklea",
    "sg:classifiers":[
        {
            "category":"Government",
            "subcategory":"Fire Station",
            "type":"Public Place"
        }
    ],
    "sg:phone":"+61 7 3892 4289",
    "sg:postcode":"4106",
    "sg:province":"QLD",
    "sg:tags":[
        "spring",
        "shock",
        "absorbers",
        "suspension"
    ],
    "wof:name":"Straight Wheels Truck Alignment",
    "wof:placetype":"venue"
},
  "geometry": {"coordinates":[153.00706481899999,-27.542011261],"type":"Point"}
}