{
  "type": "Feature",
  "properties": {
    "addr:full":"7 Berwick Rd Campbellfield VIC 3061",
    "addr:housenumber":"7",
    "addr:postcode":"3061",
    "addr:street":"Berwick Rd",
    "iso:country":"AU",
    "sg:address":"7 Berwick Rd",
    "sg:city":"Campbellfield",
    "sg:classifiers":[
        {
            "category":"Retail",
            "subcategory":"Auto Repair",
            "type":"Services"
        }
    ],
    "sg:phone":"+61 3 9357 2111",
    "sg:postcode":"3061",
    "sg:province":"VIC",
    "sg:tags":[
        "beater",
        "painter",
        "panel"
    ],
    "wof:name":"Alrin Panels Pty Ltd",
    "wof:placetype":"venue"
},
  "geometry": {"coordinates":[144.95867919899999,-37.6717834473],"type":"Point"}
}