{
  "type": "Feature",
  "properties": {
    "addr:full":"Balaclava Rd Marsfield NSW 2122",
    "addr:postcode":"2122",
    "addr:street":"Balaclava Rd",
    "iso:country":"AU",
    "sg:address":"Balaclava Rd",
    "sg:city":"Marsfield",
    "sg:classifiers":[
        {
            "category":"Retail",
            "subcategory":"Auto Repair",
            "type":"Services"
        }
    ],
    "sg:phone":"+61 2 9874 4855",
    "sg:postcode":"2122",
    "sg:province":"NSW",
    "sg:tags":[
        "repairer",
        "motor",
        "engineer"
    ],
    "wof:name":"Autodoc The",
    "wof:placetype":"venue"
},
  "geometry": {"coordinates":[151.10234069800001,-33.7803497314],"type":"Point"}
}