{
  "type": "Feature",
  "properties": {
    "addr:full":"55 Gardiner Rd Orange NSW 2800",
    "addr:housenumber":"55",
    "addr:postcode":"2800",
    "addr:street":"Gardiner Rd",
    "iso:country":"AU",
    "sg:address":"55 Gardiner Rd",
    "sg:city":"Orange",
    "sg:classifiers":[
        {
            "category":"Professional",
            "subcategory":"Computer Services",
            "type":"Services"
        }
    ],
    "sg:phone":"+61 2 6362 9000",
    "sg:postcode":"2800",
    "sg:province":"NSW",
    "sg:tags":[
        "equipment",
        "networking",
        "installation"
    ],
    "wof:name":"Pronet Computer Solutions",
    "wof:placetype":"venue"
},
  "geometry": {"coordinates":[149.092330933,-33.2936248779],"type":"Point"}
}