{
  "type": "Feature",
  "properties": {
    "addr:full":"87 Milton St Ashfield NSW 2131",
    "addr:housenumber":"87",
    "addr:postcode":"2131",
    "addr:street":"Milton St",
    "iso:country":"AU",
    "sg:address":"87 Milton St",
    "sg:city":"Ashfield",
    "sg:classifiers":[
        {
            "category":"Health Services",
            "subcategory":"Doctor",
            "type":"Services"
        }
    ],
    "sg:phone":"+61 2 9799 5211",
    "sg:postcode":"2131",
    "sg:province":"NSW",
    "sg:tags":[
        "medical",
        "practitioner"
    ],
    "wof:name":"Tran Dong",
    "wof:placetype":"venue"
},
  "geometry": {"coordinates":[151.11692810100001,-33.8921661377],"type":"Point"}
}