{
  "type": "Feature",
  "properties": {
    "iso:country":"AU",
    "sg:address":"32 Jellicoe St",
    "sg:city":"Nowra South",
    "sg:classifiers":[
        {
            "category":"Manufacturing",
            "subcategory":"Rubber & Plastics",
            "type":"Manufacturing & Wholesale Goods"
        }
    ],
    "sg:phone":"+61 2 4422 6880",
    "sg:postcode":"2541",
    "sg:province":"NSW",
    "sg:tags":[
        "wholesaler",
        "product",
        "mfrs"
    ],
    "wof:name":"Lynell Plastics",
    "wof:placetype":"venue"
},
  "geometry": {"coordinates":[150.60043335,-34.9091644287],"type":"Point"}
}