{
  "type": "Feature",
  "properties": {
    "iso:country":"AU",
    "sg:address":"56 Green Point Drv",
    "sg:city":"Green Point (Forster)",
    "sg:classifiers":[
        {
            "category":"Building & Trades",
            "subcategory":"Construction",
            "type":"Services"
        }
    ],
    "sg:phone":"+61 2 6554 9820",
    "sg:postcode":"2428",
    "sg:province":"NSW",
    "sg:tags":[
        "contractor"
    ],
    "wof:name":"Holm Greg",
    "wof:placetype":"venue"
},
  "geometry": {"coordinates":[152.521912,-32.25153],"type":"Point"}
}