{
  "type": "Feature",
  "properties": {
    "addr:full":"Simms Rd Tolga QLD 4882",
    "addr:postcode":"4882",
    "addr:street":"Simms Rd",
    "iso:country":"AU",
    "sg:address":"Simms Rd",
    "sg:city":"Tolga",
    "sg:classifiers":[
        {
            "category":"Farming",
            "subcategory":"Farm",
            "type":"Manufacturing & Wholesale Goods"
        }
    ],
    "sg:phone":"+61 7 4095 4391",
    "sg:postcode":"4882",
    "sg:province":"QLD",
    "sg:tags":[
        "farmer"
    ],
    "wof:name":"Floreancig John",
    "wof:placetype":"venue"
},
  "geometry": {"coordinates":[145.45783996599999,-17.2321853638],"type":"Point"}
}