{
  "type": "Feature",
  "properties": {
    "addr:full":"21B Green St Mt Hawthorn WA 6016",
    "addr:housenumber":"21b",
    "addr:postcode":"6016",
    "addr:street":"Green St Mt",
    "iso:country":"AU",
    "sg:address":"21B Green St",
    "sg:city":"Mt Hawthorn",
    "sg:classifiers":[
        {
            "category":"Shopping",
            "subcategory":"Party Supplies",
            "type":"Retail Goods"
        }
    ],
    "sg:phone":"+61 8 9443 6166",
    "sg:postcode":"6016",
    "sg:province":"WA",
    "sg:tags":[
        "hire",
        "costume"
    ],
    "wof:name":"The Dressup Box",
    "wof:placetype":"venue"
},
  "geometry": {"coordinates":[115.83026123,-31.914226532],"type":"Point"}
}