{
  "type": "Feature",
  "properties": {
    "iso:country":"AU",
    "sg:address":"32 Wattletree Crs",
    "sg:city":"Morwell",
    "sg:classifiers":[
        {
            "category":"Shopping",
            "subcategory":"Computers & Home Electronics",
            "type":"Retail Goods"
        }
    ],
    "sg:phone":"+61 3 5133 9424",
    "sg:postcode":"3840",
    "sg:province":"VIC",
    "sg:tags":[
        "small",
        "equipment",
        "business"
    ],
    "wof:name":"Neptune Computer Services",
    "wof:placetype":"venue"
},
  "geometry": {"coordinates":[146.39114379899999,-38.2888298035],"type":"Point"}
}