{
  "type": "Feature",
  "properties": {
    "addr:full":"Cnr High & Cooper Sts Epping VIC 3076",
    "addr:postcode":"3076",
    "iso:country":"AU",
    "sg:address":"Cnr High & Cooper Sts",
    "sg:city":"Epping",
    "sg:classifiers":[
        {
            "category":"Autos & Motor Vehicles",
            "subcategory":"Auto Supplies",
            "type":"Retail Goods"
        }
    ],
    "sg:phone":"+61 3 9408 5444",
    "sg:postcode":"3076",
    "sg:province":"VIC",
    "sg:tags":[
        "tyre"
    ],
    "wof:name":"JAXQuickfit Tyres",
    "wof:placetype":"venue"
},
  "geometry": {"coordinates":[145.05174255399999,-37.79895401],"type":"Point"}
}