{
  "type": "Feature",
  "properties": {
    "iso:country":"AU",
    "sg:address":"Level 52, 525 Collins St",
    "sg:city":"Melbourne",
    "sg:classifiers":[
        {
            "category":"Professional",
            "subcategory":"Business Services",
            "type":"Services"
        }
    ],
    "sg:phone":"+61 3 9627 2800",
    "sg:postcode":"3000",
    "sg:province":"VIC",
    "sg:tags":[
        "consultant",
        "leasing"
    ],
    "wof:name":"Babcock & Brown Pty Ltd",
    "wof:placetype":"venue"
},
  "geometry": {"coordinates":[144.95716857900001,-37.8183326721],"type":"Point"}
}