{
  "type": "Feature",
  "properties": {
    "addr:full":"52 Hepburn St Mt Magnet WA 6638",
    "addr:housenumber":"52",
    "addr:postcode":"6638",
    "addr:street":"Hepburn St Mt Magnet",
    "iso:country":"AU",
    "sg:address":"52 Hepburn St",
    "sg:city":"Mt Magnet",
    "sg:classifiers":[
        {
            "category":"Retail",
            "subcategory":"Repair Shop",
            "type":"Services"
        }
    ],
    "sg:phone":"+61 8 9963 4544",
    "sg:postcode":"6638",
    "sg:province":"WA",
    "sg:tags":[
        "windscreen"
    ],
    "wof:name":"Novus Autoglass Repair & Replacement",
    "wof:placetype":"venue"
},
  "geometry": {"coordinates":[117.848556519,-28.0649642944],"type":"Point"}
}