{
  "type": "Feature",
  "properties": {
    "addr:full":"The Shrine 502- 514 Ruthven St Toowoomba QLD 4350",
    "addr:housenumber":"502 514",
    "addr:postcode":"4350",
    "addr:street":"Ruthven St",
    "iso:country":"AU",
    "sg:address":"The Shrine 502- 514 Ruthven St",
    "sg:city":"Toowoomba",
    "sg:classifiers":[
        {
            "category":"Organizations",
            "subcategory":"Professional Association",
            "type":"Services"
        }
    ],
    "sg:phone":"+61 7 4632 7589",
    "sg:postcode":"4350",
    "sg:province":"QLD",
    "sg:tags":[
        "organisation",
        "business"
    ],
    "wof:name":"Diocesan Development Fund Catholic Diocese",
    "wof:placetype":"venue"
},
  "geometry": {"coordinates":[151.952316,-27.568136],"type":"Point"}
}