{
  "type": "Feature",
  "properties": {
    "addr:full":"Unit 10, Aerolink Business Centre, Cnr Keilor Park Tullamarine VIC 3043",
    "addr:postcode":"3043",
    "addr:street":"Cnr",
    "iso:country":"AU",
    "sg:address":"Unit 10, Aerolink Business Centre, Cnr Keilor Park",
    "sg:city":"Tullamarine",
    "sg:classifiers":[
        {
            "category":"Autos & Motor Vehicles",
            "subcategory":"Auto Supplies",
            "type":"Retail Goods"
        }
    ],
    "sg:phone":"+61 1300 769 282",
    "sg:postcode":"3043",
    "sg:province":"VIC",
    "sg:tags":[
        "battery",
        "automotive"
    ],
    "wof:name":"R & J Batteries",
    "wof:placetype":"venue"
},
  "geometry": {"coordinates":[144.859664917,-37.7115211487],"type":"Point"}
}