{
  "type": "Feature",
  "properties": {
    "addr:full":"C/O 43 Denham St Rockhampton QLD 4700",
    "addr:housenumber":"43",
    "addr:postcode":"4700",
    "addr:street":"C / O;Denham St",
    "iso:country":"AU",
    "sg:address":"C/O 43 Denham St",
    "sg:city":"Rockhampton",
    "sg:classifiers":[
        {
            "category":"Banks & Credit Unions",
            "subcategory":"Financial Services",
            "type":"Services"
        }
    ],
    "sg:phone":"+61 7 4921 3460",
    "sg:postcode":"4700",
    "sg:province":"QLD",
    "sg:tags":[
        "loan",
        "finance",
        "mortgage"
    ],
    "wof:name":"Professional Investment Services Pty Ltd",
    "wof:placetype":"venue"
},
  "geometry": {"coordinates":[150.49876403799999,-23.3875370026],"type":"Point"}
}