{
  "type": "Feature",
  "properties": {
    "addr:full":"10 Norton Rd Croydon VIC 3136",
    "addr:housenumber":"10",
    "addr:postcode":"3136",
    "addr:street":"Norton Rd",
    "iso:country":"AU",
    "sg:address":"10 Norton Rd",
    "sg:city":"Croydon",
    "sg:classifiers":[
        {
            "category":"Retail",
            "subcategory":"Auto Repair",
            "type":"Services"
        }
    ],
    "sg:phone":"+61 3 9725 6210",
    "sg:postcode":"3136",
    "sg:province":"VIC",
    "sg:tags":[
        "beater",
        "painter",
        "panel"
    ],
    "wof:name":"Stylerod Panels",
    "wof:placetype":"venue"
},
  "geometry": {"coordinates":[145.285400391,-37.7997627258],"type":"Point"}
}