{
  "type": "Feature",
  "properties": {
    "iso:country":"AU",
    "sg:address":"62 Merrigal St",
    "sg:city":"Griffith",
    "sg:classifiers":[
        {
            "category":"Building & Trades",
            "subcategory":"Construction",
            "type":"Services"
        }
    ],
    "sg:phone":"+61 2 6962 4190",
    "sg:postcode":"2680",
    "sg:province":"NSW",
    "sg:tags":[
        "contractor"
    ],
    "wof:name":"G & A Colpo",
    "wof:placetype":"venue"
},
  "geometry": {"coordinates":[146.03106700000001,-34.29295],"type":"Point"}
}