{
  "type": "Feature",
  "properties": {
    "addr:full":"6/6 Farnham Crt Flemington VIC 3031",
    "addr:housenumber":"/ 6",
    "addr:postcode":"3031",
    "addr:street":"Farnham Crt",
    "iso:country":"AU",
    "sg:address":"6/6 Farnham Crt",
    "sg:city":"Flemington",
    "sg:classifiers":[
        {
            "category":"Professional",
            "subcategory":"Art Services",
            "type":"Services"
        }
    ],
    "sg:phone":"+61 402 437 055",
    "sg:postcode":"3031",
    "sg:province":"VIC",
    "sg:tags":[
        "graphic",
        "designer"
    ],
    "wof:name":"Quintanilla Designs",
    "wof:placetype":"venue"
},
  "geometry": {"coordinates":[144.930115,-37.782173],"type":"Point"}
}