{
  "type": "Feature",
  "properties": {
    "addr:full":"Walker St Bundaberg QLD 4670",
    "addr:postcode":"4670",
    "addr:street":"Walker St",
    "iso:country":"AU",
    "sg:address":"Walker St",
    "sg:city":"Bundaberg",
    "sg:classifiers":[
        {
            "category":"Industrial Area",
            "type":"Public Place"
        }
    ],
    "sg:phone":"+61 7 4152 8374",
    "sg:postcode":"4670",
    "sg:province":"QLD",
    "sg:tags":[
        "rural",
        "shed"
    ],
    "wof:name":"Easyshade Products",
    "wof:placetype":"venue"
},
  "geometry": {"coordinates":[152.35113525400001,-24.8770332336],"type":"Point"}
}