{
  "type": "Feature",
  "properties": {
    "addr:full":"257 Nepean Hwy Seaford VIC 3198",
    "addr:housenumber":"257",
    "addr:postcode":"3198",
    "addr:street":"Nepean Hwy",
    "iso:country":"AU",
    "sg:address":"257 Nepean Hwy",
    "sg:city":"Seaford",
    "sg:classifiers":[
        {
            "category":"Travel",
            "subcategory":"Hotels & Motels",
            "type":"Entertainment"
        }
    ],
    "sg:phone":"+61 3 9786 1277",
    "sg:postcode":"3198",
    "sg:province":"VIC",
    "wof:name":"Seaford Beach Cabin Park",
    "wof:placetype":"venue"
},
  "geometry": {"coordinates":[145.125823975,-38.1118812561],"type":"Point"}
}