{
  "type": "Feature",
  "properties": {
    "addr:full":"21 Vidler Ave Woy Woy NSW 2256",
    "addr:housenumber":"21",
    "addr:postcode":"2256",
    "addr:street":"Vidler Ave",
    "iso:country":"AU",
    "sg:address":"21 Vidler Ave",
    "sg:city":"Woy Woy",
    "sg:classifiers":[
        {
            "category":"Health Services",
            "subcategory":"Doctor",
            "type":"Services"
        }
    ],
    "sg:phone":"+61 2 4342 2061",
    "sg:postcode":"2256",
    "sg:province":"NSW",
    "sg:tags":[
        "medical",
        "practitioner"
    ],
    "wof:name":"Brisbane Water Nuclear Medicine",
    "wof:placetype":"venue"
},
  "geometry": {"coordinates":[151.32211303700001,-33.4952545166],"type":"Point"}
}