{
  "type": "Feature",
  "properties": {
    "iso:country":"AU",
    "sg:address":"38 Samdon St",
    "sg:city":"Hamilton",
    "sg:classifiers":[
        {
            "category":"Banks & Credit Unions",
            "subcategory":"Financial Services",
            "type":"Services"
        }
    ],
    "sg:phone":"+61 2 4940 8999",
    "sg:postcode":"2303",
    "sg:province":"NSW",
    "sg:tags":[
        "annuity",
        "rollover",
        "superannuation",
        "consultant"
    ],
    "wof:name":"Australian Loan Services",
    "wof:placetype":"venue"
},
  "geometry": {"coordinates":[151.741776,-32.923431],"type":"Point"}
}