{
  "type": "Feature",
  "properties": {
    "addr:full":"467 Pacific Hwy Wyoming NSW 2250",
    "addr:housenumber":"467",
    "addr:postcode":"2250",
    "addr:street":"Pacific Hwy",
    "iso:country":"AU",
    "sg:address":"467 Pacific Hwy",
    "sg:city":"Wyoming",
    "sg:classifiers":[
        {
            "category":"Fast Food",
            "type":"Food & Drink"
        }
    ],
    "sg:phone":"+61 2 4322 0176",
    "sg:postcode":"2250",
    "sg:province":"NSW",
    "sg:tags":[
        "away",
        "take"
    ],
    "wof:name":"McDonald's Family Restaurants",
    "wof:placetype":"venue"
},
  "geometry": {"coordinates":[151.35057067899999,-33.4087333679],"type":"Point"}
}