{
  "type": "Feature",
  "properties": {
    "addr:full":"79 Adelaide St Brisbane QLD 4000",
    "addr:housenumber":"79",
    "addr:postcode":"4000",
    "addr:street":"Adelaide St",
    "iso:country":"AU",
    "sg:address":"79 Adelaide St",
    "sg:city":"Brisbane",
    "sg:classifiers":[
        {
            "category":"Health Services",
            "subcategory":"Medical Lab",
            "type":"Services"
        }
    ],
    "sg:phone":"+61 7 3223 5000",
    "sg:postcode":"4000",
    "sg:province":"QLD",
    "sg:tags":[
        "laboratory",
        "dental"
    ],
    "wof:name":"Studio 12 Dental Design",
    "wof:placetype":"venue"
},
  "geometry": {"coordinates":[153.02479553200001,-27.4687843323],"type":"Point"}
}