{
  "type": "Feature",
  "properties": {
    "addr:full":"6/ 133 Station Rd Seven Hills NSW 2147",
    "addr:housenumber":"/ 133",
    "addr:postcode":"2147",
    "addr:street":"Station Rd",
    "iso:country":"AU",
    "sg:address":"6/ 133 Station Rd",
    "sg:city":"Seven Hills",
    "sg:classifiers":[
        {
            "category":"Retail",
            "subcategory":"Auto Repair",
            "type":"Services"
        }
    ],
    "sg:phone":"+61 2 9838 9999",
    "sg:postcode":"2147",
    "sg:province":"NSW",
    "sg:tags":[
        "clutch",
        "brake"
    ],
    "wof:name":"Blacktown Mufflers & Brakes",
    "wof:placetype":"venue"
},
  "geometry": {"coordinates":[150.933883667,-33.775970459],"type":"Point"}
}