{
  "type": "Feature",
  "properties": {
    "addr:full":"PO Box 235 Derby WA 6728",
    "addr:postcode":"6728",
    "iso:country":"AU",
    "sg:address":"PO Box 235",
    "sg:city":"Derby",
    "sg:classifiers":[
        {
            "category":"Communications",
            "type":"Services"
        }
    ],
    "sg:phone":"+61 8 9191 1399",
    "sg:postcode":"6728",
    "sg:province":"WA",
    "sg:tags":[
        "equipment",
        "satellite"
    ],
    "wof:name":"Kimberley Solutions Pty Ltd",
    "wof:placetype":"venue"
},
  "geometry": {"coordinates":[123.665222168,-17.3448696136],"type":"Point"}
}