{
  "type": "Feature",
  "properties": {
    "addr:full":"Fcty7/ 22 Westwood Drv Ravenhall VIC 3023",
    "addr:housenumber":"22",
    "addr:postcode":"3023",
    "addr:street":"Westwood Drv",
    "iso:country":"AU",
    "sg:address":"Fcty7/ 22 Westwood Drv",
    "sg:city":"Ravenhall",
    "sg:classifiers":[
        {
            "category":"Retail",
            "subcategory":"Auto Repair",
            "type":"Services"
        }
    ],
    "sg:phone":"+61 3 8390 1600",
    "sg:postcode":"3023",
    "sg:province":"VIC",
    "sg:tags":[
        "gas",
        "conversion",
        "natural",
        "lp",
        "vehicle"
    ],
    "wof:name":"HKTG Motors & LPG Conversions",
    "wof:placetype":"venue"
},
  "geometry": {"coordinates":[144.752747,-37.766739],"type":"Point"}
}