{
  "type": "Feature",
  "properties": {
    "iso:country":"AU",
    "sg:address":"PO Box 31 St",
    "sg:city":"Andrews",
    "sg:classifiers":[
        {
            "category":"Retail",
            "subcategory":"Car Wash",
            "type":"Services"
        }
    ],
    "sg:phone":"+61 418 516 598",
    "sg:postcode":"3761",
    "sg:province":"VIC",
    "sg:tags":[
        "bitumen",
        "spraying"
    ],
    "wof:name":"Roadseal Bitumen Service",
    "wof:placetype":"venue"
},
  "geometry": {"coordinates":[145.28773498499999,-37.5787086487],"type":"Point"}
}