{
  "type": "Feature",
  "properties": {
    "addr:full":"179a Bell St Preston VIC 3072",
    "addr:housenumber":"179a",
    "addr:postcode":"3072",
    "addr:street":"Bell St",
    "iso:country":"AU",
    "sg:address":"179a Bell St",
    "sg:city":"Preston",
    "sg:classifiers":[
        {
            "category":"Retail",
            "subcategory":"Funeral Services",
            "type":"Services"
        }
    ],
    "sg:phone":"+61 1800 802 345",
    "sg:postcode":"3072",
    "sg:province":"VIC",
    "sg:tags":[
        "director"
    ],
    "wof:name":"Burial Funeral Services",
    "wof:placetype":"venue"
},
  "geometry": {"coordinates":[145.01300048799999,-37.7464294434],"type":"Point"}
}