{
  "type": "Feature",
  "properties": {
    "addr:full":"Factory 3- 417 Hammond Rd Dandenong VIC 3175",
    "addr:housenumber":"417",
    "addr:postcode":"3175",
    "addr:street":"Hammond Rd",
    "iso:country":"AU",
    "sg:address":"Factory 3- 417 Hammond Rd",
    "sg:city":"Dandenong",
    "sg:classifiers":[
        {
            "category":"Building & Trades",
            "subcategory":"Construction",
            "type":"Services"
        }
    ],
    "sg:phone":"+61 3 9706 8199",
    "sg:postcode":"3175",
    "sg:province":"VIC",
    "sg:tags":[
        "window",
        "timber"
    ],
    "wof:name":"Action Windows & Doors Pty Ltd",
    "wof:placetype":"venue"
},
  "geometry": {"coordinates":[145.210250855,-37.9920272827],"type":"Point"}
}