{
  "type": "Feature",
  "properties": {
    "addr:full":"26 Abbott St Sandringham VIC 3191",
    "addr:housenumber":"26",
    "addr:postcode":"3191",
    "addr:street":"Abbott St",
    "iso:country":"AU",
    "sg:address":"26 Abbott St",
    "sg:city":"Sandringham",
    "sg:classifiers":[
        {
            "category":"Retail",
            "subcategory":"Veterinary Services",
            "type":"Services"
        }
    ],
    "sg:phone":"+61 3 9598 7848",
    "sg:postcode":"3191",
    "sg:province":"VIC",
    "sg:tags":[
        "surgeon"
    ],
    "wof:name":"Baker Nicole",
    "wof:placetype":"venue"
},
  "geometry": {"coordinates":[145.00544738799999,-37.9490623474],"type":"Point"}
}