{
  "type": "Feature",
  "properties": {
    "iso:country":"AU",
    "sg:address":"U10/ 495 Princes Hwy",
    "sg:city":"Rockdale",
    "sg:classifiers":[
        {
            "category":"Personal",
            "subcategory":"Beauty Salon",
            "type":"Services"
        }
    ],
    "sg:phone":"+61 2 9599 8382",
    "sg:postcode":"2216",
    "sg:province":"NSW",
    "wof:name":"Innermost Body Care Pty Ltd",
    "wof:placetype":"venue"
},
  "geometry": {"coordinates":[151.13772599999999,-33.95216],"type":"Point"}
}