{
  "type": "Feature",
  "properties": {
    "addr:full":"Shop A, 55 Morts Rd Mortdale NSW 2223",
    "addr:housenumber":"55",
    "addr:postcode":"2223",
    "addr:street":"A;Morts Rd",
    "iso:country":"AU",
    "sg:address":"Shop A, 55 Morts Rd",
    "sg:city":"Mortdale",
    "sg:classifiers":[
        {
            "category":"Personal",
            "subcategory":"Beauty Salon",
            "type":"Services"
        }
    ],
    "sg:phone":"+61 2 9579 1325",
    "sg:postcode":"2223",
    "sg:province":"NSW",
    "sg:tags":[
        "hairdresser"
    ],
    "wof:name":"Headoffice Hair Studio",
    "wof:placetype":"venue"
},
  "geometry": {"coordinates":[151.07809448200001,-33.9684371948],"type":"Point"}
}