{
  "type": "Feature",
  "properties": {
    "addr:full":"1590 Mulgoa Rd Wallacia NSW 2745",
    "addr:housenumber":"1590",
    "addr:postcode":"2745",
    "addr:street":"Mulgoa Rd",
    "iso:country":"AU",
    "sg:address":"1590 Mulgoa Rd",
    "sg:city":"Wallacia",
    "sg:classifiers":[
        {
            "category":"Retail",
            "subcategory":"Event Space",
            "type":"Services"
        }
    ],
    "sg:phone":"+61 2 4773 8888",
    "sg:postcode":"2745",
    "sg:province":"NSW",
    "sg:tags":[
        "venue",
        "reception",
        "wedding"
    ],
    "wof:name":"Wallacia Hotel",
    "wof:placetype":"venue"
},
  "geometry": {"coordinates":[150.64097595199999,-33.8646888733],"type":"Point"}
}