{
  "type": "Feature",
  "properties": {
    "addr:full":"128 Clarinda St Parkes NSW 2870",
    "addr:housenumber":"128",
    "addr:postcode":"2870",
    "addr:street":"Clarinda St",
    "iso:country":"AU",
    "sg:address":"128 Clarinda St",
    "sg:city":"Parkes",
    "sg:classifiers":[
        {
            "category":"Manufacturing",
            "subcategory":"Chemicals & Compounds",
            "type":"Manufacturing & Wholesale Goods"
        }
    ],
    "sg:phone":"+61 2 6862 2844",
    "sg:postcode":"2870",
    "sg:province":"NSW",
    "sg:tags":[
        "agricultural"
    ],
    "wof:name":"Lees R",
    "wof:placetype":"venue"
},
  "geometry": {"coordinates":[148.17576600000001,-33.140053],"type":"Point"}
}