{
  "type": "Feature",
  "properties": {
    "addr:full":"Coolbellup Shopping Centre, Crn Coolbellup & Corde Coolbellup WA 6163",
    "addr:postcode":"6163",
    "addr:street":"Crn",
    "iso:country":"AU",
    "sg:address":"Coolbellup Shopping Centre, Crn Coolbellup & Corde",
    "sg:city":"Coolbellup",
    "sg:classifiers":[
        {
            "category":"Health Services",
            "subcategory":"Doctor",
            "type":"Services"
        }
    ],
    "sg:phone":"+61 8 9337 3731",
    "sg:postcode":"6163",
    "sg:province":"WA",
    "sg:tags":[
        "podiatrist"
    ],
    "wof:name":"Fully Feet Podiatry",
    "wof:placetype":"venue"
},
  "geometry": {"coordinates":[115.80677799999999,-32.082279],"type":"Point"}
}