{
  "type": "Feature",
  "properties": {
    "iso:country":"AU",
    "sg:address":"33 Spring St",
    "sg:city":"Prahran East",
    "sg:classifiers":[
        {
            "category":"Government",
            "subcategory":"Court House",
            "type":"Public Place"
        }
    ],
    "sg:phone":"+61 3 9510 8011",
    "sg:postcode":"3181",
    "sg:province":"VIC",
    "sg:tags":[
        "personal",
        "marriage",
        "family",
        "counselling"
    ],
    "wof:name":"Dayspring Counselling Service",
    "wof:placetype":"venue"
},
  "geometry": {"coordinates":[145.004730225,-37.8503990173],"type":"Point"}
}