{
  "type": "Feature",
  "properties": {
    "addr:full":"324 Livingstone Rd Marrickville NSW 2204",
    "addr:housenumber":"324",
    "addr:postcode":"2204",
    "addr:street":"Livingstone Rd",
    "iso:country":"AU",
    "sg:address":"324 Livingstone Rd",
    "sg:city":"Marrickville",
    "sg:classifiers":[
        {
            "category":"Professional",
            "subcategory":"Art Services",
            "type":"Services"
        }
    ],
    "sg:phone":"+61 2 9558 7262",
    "sg:postcode":"2204",
    "sg:province":"NSW",
    "sg:tags":[
        "graphic",
        "designer"
    ],
    "wof:name":"My Design Doctor",
    "wof:placetype":"venue"
},
  "geometry": {"coordinates":[151.14518699999999,-33.915951],"type":"Point"}
}