{
  "type": "Feature",
  "properties": {
    "addr:full":"33 McIntosh St Airport West VIC 3042",
    "addr:housenumber":"33",
    "addr:postcode":"3042",
    "addr:street":"Mcintosh St",
    "iso:country":"AU",
    "sg:address":"33 McIntosh St",
    "sg:city":"Airport West",
    "sg:classifiers":[
        {
            "category":"Retail",
            "subcategory":"Auto Repair",
            "type":"Services"
        }
    ],
    "sg:phone":"+61 3 9338 1733",
    "sg:postcode":"3042",
    "sg:province":"VIC",
    "sg:tags":[
        "repairer",
        "motor",
        "engineer"
    ],
    "wof:name":"Weltune Motors",
    "wof:placetype":"venue"
},
  "geometry": {"coordinates":[144.88803100600001,-37.721282959],"type":"Point"}
}