{
  "type": "Feature",
  "properties": {
    "addr:full":"25 Nelson St Stepney SA 5069",
    "addr:housenumber":"25",
    "addr:postcode":"5069",
    "addr:street":"Nelson St",
    "iso:country":"AU",
    "sg:address":"25 Nelson St",
    "sg:city":"Stepney",
    "sg:classifiers":[
        {
            "category":"Shopping",
            "subcategory":"Stationery & Office Supplies",
            "type":"Retail Goods"
        }
    ],
    "sg:phone":"+61 8 8362 0110",
    "sg:postcode":"5069",
    "sg:province":"SA",
    "sg:tags":[
        "equipment",
        "display",
        "exhibition"
    ],
    "wof:name":"Group Colour Pty Ltd",
    "wof:placetype":"venue"
},
  "geometry": {"coordinates":[138.63099670400001,-34.9137420654],"type":"Point"}
}