{
  "type": "Feature",
  "properties": {
    "addr:full":"4a Mount Joy Pde Lorne VIC 3232",
    "addr:housenumber":"4a",
    "addr:postcode":"3232",
    "addr:street":"Mount;Pde",
    "iso:country":"AU",
    "sg:address":"4a Mount Joy Pde",
    "sg:city":"Lorne",
    "sg:classifiers":[
        {
            "category":"Shopping",
            "subcategory":"Antiques",
            "type":"Retail Goods"
        }
    ],
    "sg:phone":"+61 3 5289 1208",
    "sg:postcode":"3232",
    "sg:province":"VIC",
    "wof:name":"Lorne Antiques & Books",
    "wof:placetype":"venue"
},
  "geometry": {"coordinates":[143.97357199999999,-38.536469],"type":"Point"}
}