{
  "type": "Feature",
  "properties": {
    "iso:country":"AU",
    "sg:address":"Chitna Rd",
    "sg:city":"Gingin West",
    "sg:classifiers":[
        {
            "category":"Shopping",
            "subcategory":"Pets & Pet Supplies",
            "type":"Retail Goods"
        }
    ],
    "sg:phone":"+61 8 9575 7532",
    "sg:postcode":"6503",
    "sg:province":"WA",
    "sg:tags":[
        "boring",
        "drilling",
        "equipment"
    ],
    "wof:name":"Gingin Drilling",
    "wof:placetype":"venue"
},
  "geometry": {"coordinates":[115.691208,-31.340044],"type":"Point"}
}