{
  "type": "Feature",
  "properties": {
    "addr:full":"43 Melaleuca Drv Thomastown VIC 3074",
    "addr:housenumber":"43",
    "addr:postcode":"3074",
    "addr:street":"Melaleuca Drv",
    "iso:country":"AU",
    "sg:address":"43 Melaleuca Drv",
    "sg:city":"Thomastown",
    "sg:classifiers":[
        {
            "category":"Mining & Drilling",
            "type":"Manufacturing & Wholesale Goods"
        }
    ],
    "sg:phone":"+61 3 9465 9756",
    "sg:postcode":"3074",
    "sg:province":"VIC",
    "sg:tags":[
        "concrete",
        "breaking",
        "grinding",
        "sawing"
    ],
    "wof:name":"All Concrete Services (Aust) Pty Ltd",
    "wof:placetype":"venue"
},
  "geometry": {"coordinates":[145.005462647,-37.6756210327],"type":"Point"}
}