{
  "type": "Feature",
  "properties": {
    "addr:full":"1 Jim Moule St Gargett QLD 4741",
    "addr:housenumber":"1",
    "addr:postcode":"4741",
    "addr:street":"Jim Moule St",
    "iso:country":"AU",
    "sg:address":"1 Jim Moule St",
    "sg:city":"Gargett",
    "sg:classifiers":[
        {
            "category":"Travel",
            "subcategory":"Hotels & Motels",
            "type":"Entertainment"
        }
    ],
    "sg:phone":"+61 7 4958 5106",
    "sg:postcode":"4741",
    "sg:province":"QLD",
    "sg:tags":[
        "pub"
    ],
    "wof:name":"Pioneer Valley Hotel Motel",
    "wof:placetype":"venue"
},
  "geometry": {"coordinates":[148.74598700000001,-21.157333],"type":"Point"}
}