{
  "type": "Feature",
  "properties": {
    "iso:country":"AU",
    "sg:address":"22 Northholm Crs",
    "sg:city":"Boondall",
    "sg:classifiers":[
        {
            "category":"Wholesale",
            "subcategory":"Electrical",
            "type":"Manufacturing & Wholesale Goods"
        }
    ],
    "sg:phone":"+61 7 3865 4233",
    "sg:postcode":"4034",
    "sg:province":"QLD",
    "sg:tags":[
        "wholesaler"
    ],
    "wof:name":"Aussie Test Tags",
    "wof:placetype":"venue"
},
  "geometry": {"coordinates":[153.06127900000001,-27.352949],"type":"Point"}
}