{
  "type": "Feature",
  "properties": {
    "iso:country":"AU",
    "sg:address":"Mons St",
    "sg:city":"Merriwagga",
    "sg:classifiers":[
        {
            "category":"Travel",
            "subcategory":"Hotels & Motels",
            "type":"Entertainment"
        }
    ],
    "sg:phone":"+61 2 6965 4457",
    "sg:postcode":"2652",
    "sg:province":"NSW",
    "sg:tags":[
        "accommodation"
    ],
    "wof:name":"Black Stump Hotel",
    "wof:placetype":"venue"
},
  "geometry": {"coordinates":[145.62385559099999,-33.816734314],"type":"Point"}
}