{
  "type": "Feature",
  "properties": {
    "addr:full":"198 High St Ashburton VIC 3147",
    "addr:housenumber":"198",
    "addr:postcode":"3147",
    "addr:street":"High St",
    "iso:country":"AU",
    "sg:address":"198 High St",
    "sg:city":"Ashburton",
    "sg:classifiers":[
        {
            "category":"Shopping",
            "subcategory":"Clothing, Apparel, & Fashions",
            "type":"Retail Goods"
        }
    ],
    "sg:phone":"+61 3 9886 9339",
    "sg:postcode":"3147",
    "sg:province":"VIC",
    "sg:tags":[
        "lingerie",
        "hosiery",
        "sleepwear"
    ],
    "wof:name":"Bedtime Bugs",
    "wof:placetype":"venue"
},
  "geometry": {"coordinates":[145.10581970199999,-37.8670768738],"type":"Point"}
}