{
  "type": "Feature",
  "properties": {
    "addr:full":"Factory 4 Silverton Pk Walsh Rd Warrnambool VIC 3280",
    "addr:housenumber":"4",
    "addr:postcode":"3280",
    "addr:street":"Silverton Pk Walsh Rd",
    "iso:country":"AU",
    "sg:address":"Factory 4 Silverton Pk Walsh Rd",
    "sg:city":"Warrnambool",
    "sg:classifiers":[
        {
            "category":"Manufacturing",
            "subcategory":"Signs",
            "type":"Manufacturing & Wholesale Goods"
        }
    ],
    "sg:phone":"+61 3 5561 2959",
    "sg:postcode":"3280",
    "sg:province":"VIC",
    "sg:tags":[
        "traffic",
        "safety"
    ],
    "wof:name":"Fagan Signco",
    "wof:placetype":"venue"
},
  "geometry": {"coordinates":[142.45884704599999,-38.3691329956],"type":"Point"}
}