{
  "type": "Feature",
  "properties": {
    "iso:country":"AU",
    "sg:address":"287 Darling St",
    "sg:city":"Balmain",
    "sg:classifiers":[
        {
            "category":"Shopping",
            "subcategory":"Mobile Phones",
            "type":"Retail Goods"
        }
    ],
    "sg:phone":"+61 2 9818 5000",
    "sg:postcode":"2041",
    "sg:province":"NSW",
    "sg:tags":[
        "telephone",
        "accessory"
    ],
    "wof:name":"Access Mobile Solutions",
    "wof:placetype":"venue"
},
  "geometry": {"coordinates":[151.180984,-33.857391],"type":"Point"}
}