{
  "type": "Feature",
  "properties": {
    "iso:country":"AU",
    "sg:address":"PO Box 54",
    "sg:city":"North Perth",
    "sg:classifiers":[
        {
            "category":"Manufacturing",
            "subcategory":"Jewelry",
            "type":"Manufacturing & Wholesale Goods"
        }
    ],
    "sg:phone":"+61 8 9444 6925",
    "sg:postcode":"6006",
    "sg:province":"WA",
    "sg:tags":[
        "mfrg",
        "jeweller"
    ],
    "wof:name":"925 Silver Australia Pty Ltd",
    "wof:placetype":"venue"
},
  "geometry": {"coordinates":[115.854103088,-31.9246997833],"type":"Point"}
}