{
  "type": "Feature",
  "properties": {
    "iso:country":"AU",
    "sg:address":"9a View Street 9 View St",
    "sg:city":"Geraldton",
    "sg:classifiers":[
        {
            "category":"Utilities",
            "subcategory":"Water",
            "type":"Services"
        }
    ],
    "sg:phone":"+61 8 9921 7225",
    "sg:postcode":"6530",
    "sg:province":"WA",
    "sg:tags":[
        "hot",
        "system"
    ],
    "wof:name":"T & T Plumbing Air-Conditioning & Gas",
    "wof:placetype":"venue"
},
  "geometry": {"coordinates":[114.61717224100001,-28.7662944794],"type":"Point"}
}