{
  "type": "Feature",
  "properties": {
    "addr:full":"PO Box 2209 Strathpine Centre QLD 4500",
    "addr:postcode":"4500",
    "iso:country":"AU",
    "sg:address":"PO Box 2209",
    "sg:city":"Strathpine Centre",
    "sg:classifiers":[
        {
            "category":"Building & Trades",
            "subcategory":"Construction",
            "type":"Services"
        }
    ],
    "sg:phone":"+61 7 5498 7433",
    "sg:postcode":"4500",
    "sg:province":"QLD",
    "sg:tags":[
        "earth",
        "excavating",
        "moving",
        "contractor"
    ],
    "wof:name":"Citycat Contracting Pty Ltd",
    "wof:placetype":"venue"
},
  "geometry": {"coordinates":[152.939254761,-27.2981395721],"type":"Point"}
}