{
  "type": "Feature",
  "properties": {
    "iso:country":"AU",
    "sg:address":"PO Box 137",
    "sg:city":"Port Vincent",
    "sg:classifiers":[
        {
            "category":"Landmark",
            "subcategory":"City Walls",
            "type":"Public Place"
        }
    ],
    "sg:phone":"+61 8 8853 7098",
    "sg:postcode":"5581",
    "sg:province":"SA",
    "sg:tags":[
        "facing",
        "hard"
    ],
    "wof:name":"Tungsten Agri Coatings Australia YP",
    "wof:placetype":"venue"
},
  "geometry": {"coordinates":[137.83456420900001,-34.7845497131],"type":"Point"}
}