{
  "type": "Feature",
  "properties": {
    "addr:full":"23 Dent St Toowoomba QLD 4350",
    "addr:housenumber":"23",
    "addr:postcode":"4350",
    "addr:street":"Dent St",
    "iso:country":"AU",
    "sg:address":"23 Dent St",
    "sg:city":"Toowoomba",
    "sg:classifiers":[
        {
            "category":"Manufacturing",
            "subcategory":"Motor Vehicles & Parts",
            "type":"Manufacturing & Wholesale Goods"
        }
    ],
    "sg:phone":"+61 7 4639 1355",
    "sg:postcode":"4350",
    "sg:province":"QLD",
    "sg:tags":[
        "replacement"
    ],
    "wof:name":"Petrena Windscreens",
    "wof:placetype":"venue"
},
  "geometry": {"coordinates":[151.94920300000001,-27.563076],"type":"Point"}
}