{
  "type": "Feature",
  "properties": {
    "addr:full":"19- 21 Mills Ave Moranbah QLD 4744",
    "addr:housenumber":"21",
    "addr:postcode":"4744",
    "addr:street":"Mills Ave",
    "iso:country":"AU",
    "sg:address":"19- 21 Mills Ave",
    "sg:city":"Moranbah",
    "sg:classifiers":[
        {
            "category":"Travel",
            "subcategory":"Hotels & Motels",
            "type":"Entertainment"
        }
    ],
    "sg:phone":"+61 7 4941 9711",
    "sg:postcode":"4744",
    "sg:province":"QLD",
    "wof:name":"Moranbah Motor Inn",
    "wof:placetype":"venue"
},
  "geometry": {"coordinates":[148.04006957999999,-22.0061702728],"type":"Point"}
}