{
  "type": "Feature",
  "properties": {
    "addr:full":"PO Box 295 Mont Albert VIC 3127",
    "addr:postcode":"3127",
    "iso:country":"AU",
    "sg:address":"PO Box 295",
    "sg:city":"Mont Albert",
    "sg:classifiers":[
        {
            "category":"Real Estate",
            "subcategory":"Surveying",
            "type":"Services"
        }
    ],
    "sg:phone":"+61 3 9899 9628",
    "sg:postcode":"3127",
    "sg:province":"VIC",
    "sg:tags":[
        "geophysicist"
    ],
    "wof:name":"Robert J Smith",
    "wof:placetype":"venue"
},
  "geometry": {"coordinates":[145.109207153,-37.8161888123],"type":"Point"}
}