{
  "type": "Feature",
  "properties": {
    "addr:full":"12/ 6 Hindmarsh Ave North Wollongong NSW 2500",
    "addr:housenumber":"12 / 6",
    "addr:postcode":"2500",
    "addr:street":"Hindmarsh Ave North",
    "iso:country":"AU",
    "sg:address":"12/ 6 Hindmarsh Ave",
    "sg:city":"North Wollongong",
    "sg:classifiers":[
        {
            "category":"Personal",
            "subcategory":"Massage",
            "type":"Services"
        }
    ],
    "sg:phone":"+61 2 4229 9526",
    "sg:postcode":"2500",
    "sg:province":"NSW",
    "sg:tags":[
        "therapy"
    ],
    "wof:name":"Reiher R S",
    "wof:placetype":"venue"
},
  "geometry": {"coordinates":[150.89132699999999,-34.410324],"type":"Point"}
}