{
  "type": "Feature",
  "properties": {
    "addr:full":"Unit 1, 9 Hampden Rd Nedlands WA 6009",
    "addr:housenumber":"9",
    "addr:postcode":"6009",
    "addr:street":"Hampden Rd",
    "iso:country":"AU",
    "sg:address":"Unit 1, 9 Hampden Rd",
    "sg:city":"Nedlands",
    "sg:classifiers":[
        {
            "category":"Personal",
            "subcategory":"Beauty Salon",
            "type":"Services"
        }
    ],
    "sg:phone":"+61 8 9389 1398",
    "sg:postcode":"6009",
    "sg:province":"WA",
    "wof:name":"Tessas Beauty Clinic",
    "wof:placetype":"venue"
},
  "geometry": {"coordinates":[115.813301,-31.971676],"type":"Point"}
}