{
  "type": "Feature",
  "properties": {
    "iso:country":"AU",
    "sg:address":"8, 288 High Rd",
    "sg:city":"Riverton",
    "sg:classifiers":[
        {
            "category":"Banks & Credit Unions",
            "subcategory":"Financial Services",
            "type":"Services"
        }
    ],
    "sg:phone":"+61 8 9457 7266",
    "sg:postcode":"6148",
    "sg:province":"WA",
    "sg:tags":[
        "settlement",
        "nt",
        "agent",
        "wa"
    ],
    "wof:name":"Prompt Settlements",
    "wof:placetype":"venue"
},
  "geometry": {"coordinates":[115.868149,-32.03862],"type":"Point"}
}