{
  "type": "Feature",
  "properties": {
    "iso:country":"AU",
    "sg:address":"Shop 3/ 79 Central St",
    "sg:city":"Labrador",
    "sg:classifiers":[
        {
            "category":"Personal",
            "subcategory":"Beauty Salon",
            "type":"Services"
        }
    ],
    "sg:phone":"+61 7 5528 2523",
    "sg:postcode":"4215",
    "sg:province":"QLD",
    "sg:tags":[
        "hairdresser"
    ],
    "wof:name":"Frenz Hair & Beauty",
    "wof:placetype":"venue"
},
  "geometry": {"coordinates":[153.40281677199999,-27.9486598969],"type":"Point"}
}