{
  "type": "Feature",
  "properties": {
    "addr:full":"232 Halse Rd Marble Bar WA 6760",
    "addr:housenumber":"232",
    "addr:postcode":"6760",
    "addr:street":"Halse Rd",
    "iso:country":"AU",
    "sg:address":"232 Halse Rd",
    "sg:city":"Marble Bar",
    "sg:classifiers":[
        {
            "category":"Autos & Motor Vehicles",
            "subcategory":"Fuel & Gas Station",
            "type":"Retail Goods"
        }
    ],
    "sg:phone":"+61 8 9176 1166",
    "sg:postcode":"6760",
    "sg:province":"WA",
    "wof:name":"Caltex",
    "wof:placetype":"venue"
},
  "geometry": {"coordinates":[119.748093,-21.173124],"type":"Point"}
}