{
  "type": "Feature",
  "properties": {
    "addr:full":"Suite 1 Level 1 205 Anson St Orange NSW 2800",
    "addr:housenumber":"205",
    "addr:postcode":"2800",
    "addr:street":"Anson St",
    "iso:country":"AU",
    "sg:address":"Suite 1 Level 1 205 Anson St",
    "sg:city":"Orange",
    "sg:classifiers":[
        {
            "category":"Banks & Credit Unions",
            "subcategory":"Bank",
            "type":"Services"
        }
    ],
    "sg:phone":"+61 2 6360 3110",
    "sg:postcode":"2800",
    "sg:province":"NSW",
    "wof:name":"BankWest",
    "wof:placetype":"venue"
},
  "geometry": {"coordinates":[149.099212647,-33.2818756104],"type":"Point"}
}