{
  "type": "Feature",
  "properties": {
    "addr:full":"Kiosk 8 Brandon Park Shopng Cntr Cnr Springvale & Ferntree Gully Rds Wheelers Hill VIC 3150",
    "addr:postcode":"3150",
    "addr:street":"Brandon",
    "iso:country":"AU",
    "sg:address":"Kiosk 8 Brandon Park Shopng Cntr Cnr Springvale & Ferntree Gully Rds",
    "sg:city":"Wheelers Hill",
    "sg:classifiers":[
        {
            "category":"Cafe",
            "type":"Food & Drink"
        }
    ],
    "sg:phone":"+61 3 8561 0848",
    "sg:postcode":"3150",
    "sg:province":"VIC",
    "wof:name":"Gloria Jean's Coffees",
    "wof:placetype":"venue"
},
  "geometry": {"coordinates":[145.16229248100001,-37.9005088806],"type":"Point"}
}