{
  "type": "Feature",
  "properties": {
    "iso:country":"AU",
    "sg:address":"76 William St",
    "sg:city":"Howard",
    "sg:classifiers":[
        {
            "category":"Real Estate",
            "subcategory":"Real Estate Agent",
            "type":"Services"
        }
    ],
    "sg:phone":"+61 7 4129 0222",
    "sg:postcode":"4659",
    "sg:province":"QLD",
    "wof:name":"Advantage One Pty Ltd",
    "wof:placetype":"venue"
},
  "geometry": {"coordinates":[152.56163000000001,-25.318327],"type":"Point"}
}