{
  "type": "Feature",
  "properties": {
    "addr:full":"Unit 4/ 10 Powdrill Rd Prestons NSW 2170",
    "addr:postcode":"2170",
    "addr:street":"10 Powdrill Rd",
    "iso:country":"AU",
    "sg:address":"Unit 4/ 10 Powdrill Rd",
    "sg:city":"Prestons",
    "sg:classifiers":[
        {
            "category":"Home & Garden",
            "subcategory":"Building Materials",
            "type":"Retail Goods"
        }
    ],
    "sg:phone":"+61 2 9826 6083",
    "sg:postcode":"2170",
    "sg:province":"NSW",
    "sg:tags":[
        "fencing"
    ],
    "wof:name":"MGD Fencing Pty Ltd",
    "wof:placetype":"venue"
},
  "geometry": {"coordinates":[150.88938903799999,-33.9336624146],"type":"Point"}
}