{
  "type": "Feature",
  "properties": {
    "iso:country":"AU",
    "sg:address":"69b The Terrace St",
    "sg:city":"Ocean Grove",
    "sg:classifiers":[
        {
            "category":"Casinos & Gambling",
            "type":"Entertainment"
        }
    ],
    "sg:phone":"+61 3 5255 2948",
    "sg:postcode":"3226",
    "sg:province":"VIC",
    "sg:tags":[
        "lottery",
        "agent"
    ],
    "wof:name":"Ocean Grove Tattslotto & Cards",
    "wof:placetype":"venue"
},
  "geometry": {"coordinates":[144.522537,-38.267723],"type":"Point"}
}