{
  "type": "Feature",
  "properties": {
    "addr:full":"Shop 11 Glendalough Shopng Cntr Glendalough WA 6016",
    "addr:housenumber":"shop 11",
    "addr:postcode":"6016",
    "addr:street":"Glendalough Shopng Cntr",
    "iso:country":"AU",
    "sg:address":"Shop 11",
    "sg:city":"Glendalough Shopng Cntr Glendalough",
    "sg:classifiers":[
        {
            "category":"Fast Food",
            "type":"Food & Drink"
        }
    ],
    "sg:phone":"+61 8 9444 8196",
    "sg:postcode":"6016",
    "sg:province":"WA",
    "sg:tags":[
        "away",
        "take"
    ],
    "wof:name":"Glendalough Gourmet",
    "wof:placetype":"venue"
},
  "geometry": {"coordinates":[115.820617676,-31.9192295074],"type":"Point"}
}