{
  "type": "Feature",
  "properties": {
    "addr:full":"5 Dewrang St Blakehurst NSW 2221",
    "addr:housenumber":"5",
    "addr:postcode":"2221",
    "addr:street":"Dewrang St",
    "iso:country":"AU",
    "sg:address":"5 Dewrang St",
    "sg:city":"Blakehurst",
    "sg:classifiers":[
        {
            "category":"Building & Trades",
            "subcategory":"Construction",
            "type":"Services"
        }
    ],
    "sg:phone":"+61 2 9546 5166",
    "sg:postcode":"2221",
    "sg:province":"NSW",
    "sg:tags":[
        "waterproofing",
        "contractor"
    ],
    "wof:name":"L & P Waterproofing",
    "wof:placetype":"venue"
},
  "geometry": {"coordinates":[151.11581420900001,-33.9842071533],"type":"Point"}
}