{
  "type": "Feature",
  "properties": {
    "addr:full":"276 Devonshire Rd Surry Hills NSW 2010",
    "addr:housenumber":"276",
    "addr:postcode":"2010",
    "addr:street":"Devonshire Rd",
    "iso:country":"AU",
    "sg:address":"276 Devonshire Rd",
    "sg:city":"Surry Hills",
    "sg:classifiers":[
        {
            "category":"Home & Garden",
            "subcategory":"Building Materials",
            "type":"Retail Goods"
        }
    ],
    "sg:phone":"+61 2 8394 9696",
    "sg:postcode":"2010",
    "sg:province":"NSW",
    "sg:tags":[
        "laminate",
        "laminated",
        "panel"
    ],
    "wof:name":"Formica",
    "wof:placetype":"venue"
},
  "geometry": {"coordinates":[151.21420288100001,-33.8891067505],"type":"Point"}
}