{
  "type": "Feature",
  "properties": {
    "addr:full":"37 Lobb St Ipswich QLD 4305",
    "addr:housenumber":"37",
    "addr:postcode":"4305",
    "addr:street":"Lobb St",
    "iso:country":"AU",
    "sg:address":"37 Lobb St",
    "sg:city":"Ipswich",
    "sg:classifiers":[
        {
            "category":"Industrial Area",
            "type":"Public Place"
        }
    ],
    "sg:phone":"+61 7 3282 8880",
    "sg:postcode":"4305",
    "sg:province":"QLD",
    "sg:tags":[
        "rural",
        "shed"
    ],
    "wof:name":"Competitive Garages & Patios",
    "wof:placetype":"venue"
},
  "geometry": {"coordinates":[152.747802734,-27.6282138824],"type":"Point"}
}