{
  "type": "Feature",
  "properties": {
    "iso:country":"AU",
    "sg:address":"PO Box 132",
    "sg:city":"Para Hills",
    "sg:classifiers":[
        {
            "category":"Building & Trades",
            "subcategory":"Landscaping Services",
            "type":"Services"
        }
    ],
    "sg:phone":"+61 417 806 904",
    "sg:postcode":"5096",
    "sg:province":"SA",
    "sg:tags":[
        "designer",
        "landscape",
        "contractor"
    ],
    "wof:name":"Mr B's Garden Care",
    "wof:placetype":"venue"
},
  "geometry": {"coordinates":[138.65762329099999,-34.8117485046],"type":"Point"}
}