{
  "type": "Feature",
  "properties": {
    "iso:country":"AU",
    "sg:address":"Unit 6, 51 York Rd",
    "sg:city":"Penrith",
    "sg:classifiers":[
        {
            "category":"Retail",
            "subcategory":"Auto Repair",
            "type":"Services"
        }
    ],
    "sg:phone":"+61 411 870 006",
    "sg:postcode":"2750",
    "sg:province":"NSW",
    "sg:tags":[
        "electrical"
    ],
    "wof:name":"J.K. Car Air Pty Ltd",
    "wof:placetype":"venue"
},
  "geometry": {"coordinates":[150.68817138700001,-33.7662734985],"type":"Point"}
}