{
  "type": "Feature",
  "properties": {
    "addr:full":"723 Cavendish Rd Holland Park QLD 4121",
    "addr:housenumber":"723",
    "addr:postcode":"4121",
    "addr:street":"Cavendish Rd",
    "iso:country":"AU",
    "sg:address":"723 Cavendish Rd",
    "sg:city":"Holland Park",
    "sg:classifiers":[
        {
            "category":"Arts & Performance",
            "subcategory":"Dance",
            "type":"Entertainment"
        }
    ],
    "sg:phone":"+61 7 3849 2316",
    "sg:postcode":"4121",
    "sg:province":"QLD",
    "sg:tags":[
        "theatrical",
        "ballet",
        "tuition"
    ],
    "wof:name":"Crocker School of Irish Dance",
    "wof:placetype":"venue"
},
  "geometry": {"coordinates":[153.07696533199999,-27.5186214447],"type":"Point"}
}