{
  "type": "Feature",
  "properties": {
    "addr:full":"Logan River Rd Bethania QLD 4205",
    "addr:postcode":"4205",
    "addr:street":"River Rd",
    "iso:country":"AU",
    "sg:address":"Logan River Rd",
    "sg:city":"Bethania",
    "sg:classifiers":[
        {
            "category":"Fast Food",
            "type":"Food & Drink"
        }
    ],
    "sg:phone":"+61 7 3200 9898",
    "sg:postcode":"4205",
    "sg:province":"QLD",
    "sg:tags":[
        "away",
        "take"
    ],
    "wof:name":"H & K Chinese Takeaway",
    "wof:placetype":"venue"
},
  "geometry": {"coordinates":[153.153686523,-27.6952819824],"type":"Point"}
}