{
  "type": "Feature",
  "properties": {
    "iso:country":"AU",
    "sg:address":"Suite 3 Level 1, 4-10 Hillcrest Rd",
    "sg:city":"Pennant Hills",
    "sg:classifiers":[
        {
            "category":"Shopping",
            "subcategory":"Jewelry",
            "type":"Retail Goods"
        }
    ],
    "sg:phone":"+61 2 9875 4600",
    "sg:postcode":"2120",
    "sg:province":"NSW",
    "sg:tags":[
        "jeweller"
    ],
    "wof:name":"Drakes Handmade Jewellery",
    "wof:placetype":"venue"
},
  "geometry": {"coordinates":[151.06997680699999,-33.737827301],"type":"Point"}
}