{
  "type": "Feature",
  "properties": {
    "iso:country":"AU",
    "sg:address":"6 Lawrence St",
    "sg:city":"Fairfield",
    "sg:classifiers":[
        {
            "category":"Building & Trades",
            "subcategory":"Construction",
            "type":"Services"
        }
    ],
    "sg:phone":"+61 2 9728 3166",
    "sg:postcode":"2165",
    "sg:province":"NSW",
    "sg:tags":[
        "rendering",
        "cement"
    ],
    "wof:name":"Samaha Rendering",
    "wof:placetype":"venue"
},
  "geometry": {"coordinates":[150.95494079599999,-33.8604698181],"type":"Point"}
}