{
  "type": "Feature",
  "properties": {
    "addr:full":"PO Box 315 Laidley QLD 4341",
    "addr:postcode":"4341",
    "iso:country":"AU",
    "sg:address":"PO Box 315",
    "sg:city":"Laidley",
    "sg:classifiers":[
        {
            "category":"Banks & Credit Unions",
            "subcategory":"Bank",
            "type":"Services"
        }
    ],
    "sg:phone":"+61 409 019 470",
    "sg:postcode":"4341",
    "sg:province":"QLD",
    "sg:tags":[
        "broker",
        "mortgage"
    ],
    "wof:name":"Lockyer Mortgage & Finance",
    "wof:placetype":"venue"
},
  "geometry": {"coordinates":[152.38941955600001,-27.6451702118],"type":"Point"}
}