{
  "type": "Feature",
  "properties": {
    "addr:full":"99 Melbourne St North Adelaide SA 5006",
    "addr:housenumber":"99",
    "addr:postcode":"5006",
    "addr:street":"Melbourne St",
    "iso:country":"AU",
    "sg:address":"99 Melbourne St",
    "sg:city":"North Adelaide",
    "sg:classifiers":[
        {
            "category":"Cafe",
            "type":"Food & Drink"
        }
    ],
    "sg:phone":"+61 8 8267 2141",
    "sg:postcode":"5006",
    "sg:province":"SA",
    "wof:name":"The Vines Cafe",
    "wof:placetype":"venue"
},
  "geometry": {"coordinates":[138.60786438,-34.9069213867],"type":"Point"}
}