{
  "type": "Feature",
  "properties": {
    "addr:full":"492 High St Lalor VIC 3075",
    "addr:housenumber":"492",
    "addr:postcode":"3075",
    "addr:street":"High St",
    "iso:country":"AU",
    "sg:address":"492 High St",
    "sg:city":"Lalor",
    "sg:classifiers":[
        {
            "category":"Manufacturing",
            "subcategory":"Glass & Minerals",
            "type":"Manufacturing & Wholesale Goods"
        }
    ],
    "sg:phone":"+61 3 9401 4255",
    "sg:postcode":"3075",
    "sg:province":"VIC",
    "sg:tags":[
        "merchant",
        "granite",
        "marble"
    ],
    "wof:name":"Supergress Tiles",
    "wof:placetype":"venue"
},
  "geometry": {"coordinates":[145.01919555699999,-37.6600456238],"type":"Point"}
}