{
  "type": "Feature",
  "properties": {
    "addr:full":"26 Old Pacific Hwy Newrybar NSW 2479",
    "addr:housenumber":"26",
    "addr:postcode":"2479",
    "addr:street":"Old Pacific Hwy",
    "iso:country":"AU",
    "sg:address":"26 Old Pacific Hwy",
    "sg:city":"Newrybar",
    "sg:classifiers":[
        {
            "category":"Building & Trades",
            "subcategory":"Construction",
            "type":"Services"
        }
    ],
    "sg:phone":"+61 2 6687 2334",
    "sg:postcode":"2479",
    "sg:province":"NSW",
    "sg:tags":[
        "concrete",
        "contractor"
    ],
    "wof:name":"Boss Networking",
    "wof:placetype":"venue"
},
  "geometry": {"coordinates":[153.53112793,-28.7194042206],"type":"Point"}
}