{
  "type": "Feature",
  "properties": {
    "iso:country":"AU",
    "sg:address":"201 Torrens Rd",
    "sg:city":"Croydon",
    "sg:classifiers":[
        {
            "category":"Shopping",
            "subcategory":"Computers & Home Electronics",
            "type":"Retail Goods"
        }
    ],
    "sg:phone":"+61 8 8346 9234",
    "sg:postcode":"5008",
    "sg:province":"SA",
    "sg:tags":[
        "equipment",
        "part",
        "electronic"
    ],
    "sg:website":"http://www.electricbug.com.au",
    "wof:name":"Electric Bug Pty Ltd",
    "wof:placetype":"venue"
},
  "geometry": {"coordinates":[138.570267,-34.888504],"type":"Point"}
}