{
  "type": "Feature",
  "properties": {
    "iso:country":"AU",
    "sg:address":"60 Duxford St",
    "sg:city":"Paddington",
    "sg:classifiers":[
        {
            "category":"Professional",
            "subcategory":"Employment Agencies",
            "type":"Services"
        }
    ],
    "sg:phone":"+61 2 9331 1311",
    "sg:postcode":"2021",
    "sg:province":"NSW",
    "sg:tags":[
        "provider",
        "internet"
    ],
    "wof:name":"eCyan",
    "wof:placetype":"venue"
},
  "geometry": {"coordinates":[151.228424072,-33.8836212158],"type":"Point"}
}