{
  "type": "Feature",
  "properties": {
    "iso:country":"AU",
    "sg:address":"Lemon Rd",
    "sg:city":"Sheidow Park",
    "sg:classifiers":[
        {
            "category":"Food & Beverages",
            "subcategory":"Supermarket",
            "type":"Retail Goods"
        }
    ],
    "sg:phone":"+61 8 8322 4577",
    "sg:postcode":"5158",
    "sg:province":"SA",
    "sg:tags":[
        "grocery",
        "store"
    ],
    "wof:name":"Woodend Mini Mart",
    "wof:placetype":"venue"
},
  "geometry": {"coordinates":[138.536819458,-35.0816764832],"type":"Point"}
}