{
  "type": "Feature",
  "properties": {
    "addr:full":"32 Albert Rd Moonah TAS 7009",
    "addr:housenumber":"32",
    "addr:postcode":"7009",
    "addr:street":"Albert Rd",
    "iso:country":"AU",
    "sg:address":"32 Albert Rd",
    "sg:city":"Moonah",
    "sg:classifiers":[
        {
            "category":"Personal",
            "subcategory":"Beauty Salon",
            "type":"Services"
        }
    ],
    "sg:phone":"+61 3 6228 4390",
    "sg:postcode":"7009",
    "sg:province":"TAS",
    "sg:tags":[
        "hairdresser"
    ],
    "wof:name":"Unique Barber",
    "wof:placetype":"venue"
},
  "geometry": {"coordinates":[147.296020508,-42.8475952148],"type":"Point"}
}