{
  "type": "Feature",
  "properties": {
    "iso:country":"AU",
    "sg:address":"18 Lewington St Bomen Via",
    "sg:city":"Wagga Wagga",
    "sg:classifiers":[
        {
            "category":"Autos & Motor Vehicles",
            "subcategory":"Auto Supplies",
            "type":"Retail Goods"
        }
    ],
    "sg:phone":"+61 2 6921 4710",
    "sg:postcode":"2650",
    "sg:province":"NSW",
    "sg:tags":[
        "oil",
        "spirit"
    ],
    "wof:name":"Riverina Fuel Supplies",
    "wof:placetype":"venue"
},
  "geometry": {"coordinates":[147.41003418,-35.0713310242],"type":"Point"}
}