{
  "type": "Feature",
  "properties": {
    "addr:full":"35 Blanche St Edithburgh SA 5583",
    "addr:housenumber":"35",
    "addr:postcode":"5583",
    "addr:street":"Blanche St",
    "iso:country":"AU",
    "sg:address":"35 Blanche St",
    "sg:city":"Edithburgh",
    "sg:classifiers":[
        {
            "category":"Farming",
            "subcategory":"Farm & Veterinary Services",
            "type":"Manufacturing & Wholesale Goods"
        }
    ],
    "sg:phone":"+61 407 151 141",
    "sg:postcode":"5583",
    "sg:province":"SA",
    "sg:tags":[
        "irrigation",
        "reticulation",
        "system"
    ],
    "wof:name":"Cowpasture Horticultural",
    "wof:placetype":"venue"
},
  "geometry": {"coordinates":[137.74595642099999,-35.0853843689],"type":"Point"}
}