{
  "type": "Feature",
  "properties": {
    "addr:full":"74 Brisbane Rd, Labrador QLD 4215",
    "addr:housenumber":"74",
    "addr:postcode":"4215",
    "addr:street":"Brisbane Rd",
    "iso:country":"AU",
    "sg:address":"74 Brisbane Rd,",
    "sg:city":"Labrador",
    "sg:classifiers":[
        {
            "category":"Health Services",
            "subcategory":"Dentist",
            "type":"Services"
        }
    ],
    "sg:phone":"+61 7 5529 1411",
    "sg:postcode":"4215",
    "sg:province":"QLD",
    "sg:tags":[
        "dental",
        "prosthetist"
    ],
    "wof:name":"Labrador Denture Clinic",
    "wof:placetype":"venue"
},
  "geometry": {"coordinates":[153.40086364699999,-27.9354133606],"type":"Point"}
}