{
  "type": "Feature",
  "properties": {
    "addr:full":"67 King William Rd Unley SA 5061",
    "addr:housenumber":"67",
    "addr:postcode":"5061",
    "addr:street":"King William Rd",
    "iso:country":"AU",
    "sg:address":"67 King William Rd",
    "sg:city":"Unley",
    "sg:classifiers":[
        {
            "category":"Building & Trades",
            "subcategory":"Construction",
            "type":"Services"
        }
    ],
    "sg:phone":"+61 8 8357 2367",
    "sg:postcode":"5061",
    "sg:province":"SA",
    "sg:tags":[
        "contractor"
    ],
    "wof:name":"Leah Miller Interiors & Construction",
    "wof:placetype":"venue"
},
  "geometry": {"coordinates":[138.599685669,-34.9470405579],"type":"Point"}
}