{
  "type": "Feature",
  "properties": {
    "iso:country":"AU",
    "sg:address":"Shop 8/ 113 Brisbane St",
    "sg:city":"Beaudesert",
    "sg:classifiers":[
        {
            "category":"Home & Garden",
            "subcategory":"Carpets & Floor Coverings",
            "type":"Retail Goods"
        }
    ],
    "sg:phone":"+61 7 5541 4755",
    "sg:postcode":"4285",
    "sg:province":"QLD",
    "sg:tags":[
        "tile",
        "wall"
    ],
    "wof:name":"Beaudesert Tiles",
    "wof:placetype":"venue"
},
  "geometry": {"coordinates":[152.99588,-27.986717],"type":"Point"}
}