{
  "type": "Feature",
  "properties": {
    "addr:full":"PO Box 3366 B.M.D.C. Belconnen ACT 2617",
    "addr:postcode":"2617",
    "iso:country":"AU",
    "sg:address":"PO Box 3366",
    "sg:city":"B.M.D.C. Belconnen",
    "sg:classifiers":[
        {
            "category":"Utilities",
            "subcategory":"Refuse",
            "type":"Services"
        }
    ],
    "sg:phone":"+61 2 6241 5255",
    "sg:postcode":"2617",
    "sg:province":"ACT",
    "sg:tags":[
        "disposal",
        "reduction",
        "waste"
    ],
    "wof:name":"Economy Tidy Bags",
    "wof:placetype":"venue"
},
  "geometry": {"coordinates":[149.06353759800001,-35.239730835],"type":"Point"}
}