{
  "type": "Feature",
  "properties": {
    "iso:country":"AU",
    "sg:address":"2906 Albany Hwy",
    "sg:city":"Kelmscott",
    "sg:classifiers":[
        {
            "category":"Health Services",
            "subcategory":"Dentist",
            "type":"Services"
        }
    ],
    "sg:phone":"+61 8 9390 5927",
    "sg:postcode":"6111",
    "sg:province":"WA",
    "wof:name":"Caroline Mak",
    "wof:placetype":"venue"
},
  "geometry": {"coordinates":[116.018226623,-32.1242828369],"type":"Point"}
}