{
  "type": "Feature",
  "properties": {
    "addr:full":"Suite 1, Level 1, 6- 8 Regent St Wollongong NSW 2500",
    "addr:housenumber":"6 8",
    "addr:postcode":"2500",
    "addr:street":"Regent St",
    "iso:country":"AU",
    "sg:address":"Suite 1, Level 1, 6- 8 Regent St",
    "sg:city":"Wollongong",
    "sg:classifiers":[
        {
            "category":"Professional",
            "subcategory":"Employment Agencies",
            "type":"Services"
        }
    ],
    "sg:phone":"+61 13 14 48",
    "sg:postcode":"2500",
    "sg:province":"NSW",
    "sg:tags":[
        "hire",
        "labour",
        "contractor"
    ],
    "wof:name":"Drake",
    "wof:placetype":"venue"
},
  "geometry": {"coordinates":[150.89123499999999,-34.423744],"type":"Point"}
}