{
  "type": "Feature",
  "properties": {
    "addr:full":"102a Chapman Ave Beecroft NSW 2119",
    "addr:housenumber":"102a",
    "addr:postcode":"2119",
    "addr:street":"Chapman Ave",
    "iso:country":"AU",
    "sg:address":"102a Chapman Ave",
    "sg:city":"Beecroft",
    "sg:classifiers":[
        {
            "category":"Professional",
            "subcategory":"Management & Consulting",
            "type":"Services"
        }
    ],
    "sg:phone":"+61 2 9980 8416",
    "sg:postcode":"2119",
    "sg:province":"NSW",
    "sg:tags":[
        "consultant",
        "educational"
    ],
    "wof:name":"Grant William Dr & Associates",
    "wof:placetype":"venue"
},
  "geometry": {"coordinates":[151.05516052199999,-33.7490348816],"type":"Point"}
}