{
  "type": "Feature",
  "properties": {
    "addr:full":"37 Daintree Pl Riverhills QLD 4074",
    "addr:housenumber":"37",
    "addr:postcode":"4074",
    "addr:street":"Daintree Pl",
    "iso:country":"AU",
    "sg:address":"37 Daintree Pl",
    "sg:city":"Riverhills",
    "sg:classifiers":[
        {
            "category":"Autos & Motor Vehicles",
            "subcategory":"Automobile Sales",
            "type":"Retail Goods"
        }
    ],
    "sg:phone":"+61 416 045 149",
    "sg:postcode":"4074",
    "sg:province":"QLD",
    "sg:tags":[
        "car",
        "new"
    ],
    "wof:name":"Noel Gruppetta",
    "wof:placetype":"venue"
},
  "geometry": {"coordinates":[152.90463256800001,-27.5596809387],"type":"Point"}
}