{
  "type": "Feature",
  "properties": {
    "addr:full":"481 Victoria St Richmond VIC 3121",
    "addr:housenumber":"481",
    "addr:postcode":"3121",
    "addr:street":"Victoria St",
    "iso:country":"AU",
    "sg:address":"481 Victoria St",
    "sg:city":"Richmond",
    "sg:classifiers":[
        {
            "category":"Real Estate",
            "subcategory":"Real Estate Agent",
            "type":"Services"
        }
    ],
    "sg:phone":"+61 3 9427 9300",
    "sg:postcode":"3121",
    "sg:province":"VIC",
    "sg:tags":[
        "handyman's",
        "equipment",
        "hire",
        "builders",
        "contractor"
    ],
    "wof:name":"Busy Beaver Bobcat & Loader Hire",
    "wof:placetype":"venue"
},
  "geometry": {"coordinates":[145.00199890100001,-37.810546875],"type":"Point"}
}