{
  "type": "Feature",
  "properties": {
    "iso:country":"AU",
    "sg:address":"Tristram Rd",
    "sg:city":"Beacon Hill",
    "sg:classifiers":[
        {
            "category":"Social Services",
            "subcategory":"Child Care",
            "type":"Services"
        }
    ],
    "sg:phone":"+61 2 9975 2859",
    "sg:postcode":"2100",
    "sg:province":"NSW",
    "wof:name":"Beacon Hill Public School Before & After School Care Centre",
    "wof:placetype":"venue"
},
  "geometry": {"coordinates":[151.25920105,-33.7520751953],"type":"Point"}
}