{
  "type": "Feature",
  "properties": {
    "addr:full":"13 Brighton Rd Bowen QLD 4805",
    "addr:housenumber":"13",
    "addr:postcode":"4805",
    "addr:street":"Brighton Rd",
    "iso:country":"AU",
    "sg:address":"13 Brighton Rd",
    "sg:city":"Bowen",
    "sg:classifiers":[
        {
            "category":"Personal",
            "type":"Services"
        }
    ],
    "sg:phone":"+61 414 942 811",
    "sg:postcode":"4805",
    "sg:province":"QLD",
    "sg:tags":[
        "reducing",
        "treatment",
        "weight"
    ],
    "wof:name":"Gaining Slimness",
    "wof:placetype":"venue"
},
  "geometry": {"coordinates":[148.23553466800001,-19.9910240173],"type":"Point"}
}