{
  "type": "Feature",
  "properties": {
    "iso:country":"AU",
    "sg:address":"197 Geelong Rd",
    "sg:city":"Kingsville",
    "sg:classifiers":[
        {
            "category":"Retail",
            "subcategory":"Auto Repair",
            "type":"Services"
        }
    ],
    "sg:phone":"+61 3 9687 7727",
    "sg:postcode":"3012",
    "sg:province":"VIC",
    "sg:tags":[
        "repairer",
        "motor",
        "engineer"
    ],
    "wof:name":"New Rising Sun Mechanical Repairs",
    "wof:placetype":"venue"
},
  "geometry": {"coordinates":[144.88490295400001,-37.8032836914],"type":"Point"}
}