{
  "type": "Feature",
  "properties": {
    "addr:full":"47 Duneba Drv Westleigh NSW 2120",
    "addr:housenumber":"47",
    "addr:postcode":"2120",
    "addr:street":"Duneba Drv",
    "iso:country":"AU",
    "sg:address":"47 Duneba Drv",
    "sg:city":"Westleigh",
    "sg:classifiers":[
        {
            "category":"Education",
            "subcategory":"Music School",
            "type":"Public Place"
        }
    ],
    "sg:phone":"+61 403 896 890",
    "sg:postcode":"2120",
    "sg:province":"NSW",
    "sg:tags":[
        "teacher"
    ],
    "wof:name":"Academy of Concert Band Education",
    "wof:placetype":"venue"
},
  "geometry": {"coordinates":[151.06794738799999,-33.7217788696],"type":"Point"}
}