{
  "type": "Feature",
  "properties": {
    "iso:country":"AU",
    "sg:address":"9 Curnow St",
    "sg:city":"Crows Nest",
    "sg:classifiers":[
        {
            "category":"Food & Beverages",
            "subcategory":"Supermarket",
            "type":"Retail Goods"
        }
    ],
    "sg:phone":"+61 7 4698 1429",
    "sg:postcode":"4355",
    "sg:province":"QLD",
    "sg:tags":[
        "grocery",
        "store"
    ],
    "wof:name":"IGA Crows Nest",
    "wof:placetype":"venue"
},
  "geometry": {"coordinates":[152.055206,-27.262226],"type":"Point"}
}