{
  "type": "Feature",
  "properties": {
    "iso:country":"AU",
    "sg:address":"Ste 9/ 60 Albany St",
    "sg:city":"Coffs Harbour",
    "sg:classifiers":[
        {
            "category":"Health Services",
            "subcategory":"Doctor",
            "type":"Services"
        }
    ],
    "sg:phone":"+61 2 6652 4599",
    "sg:postcode":"2450",
    "sg:province":"NSW",
    "sg:tags":[
        "medical",
        "practitioner"
    ],
    "wof:name":"Yelf C Dr",
    "wof:placetype":"venue"
},
  "geometry": {"coordinates":[153.114883,-30.300173],"type":"Point"}
}