{
  "type": "Feature",
  "properties": {
    "addr:full":"366 Clayton Rd Clayton VIC 3168",
    "addr:housenumber":"366",
    "addr:postcode":"3168",
    "addr:street":"Clayton Rd",
    "iso:country":"AU",
    "sg:address":"366 Clayton Rd",
    "sg:city":"Clayton",
    "sg:classifiers":[
        {
            "category":"Health Services",
            "subcategory":"Optometrist",
            "type":"Services"
        }
    ],
    "sg:phone":"+61 3 9544 3371",
    "sg:postcode":"3168",
    "sg:province":"VIC",
    "wof:name":"Optical World",
    "wof:placetype":"venue"
},
  "geometry": {"coordinates":[145.119216919,-37.9284477234],"type":"Point"}
}