{
  "type": "Feature",
  "properties": {
    "addr:full":"Shop 3109, Highpoint Shopping Centre, Rosamond Rd Maribyrnong VIC 3032",
    "addr:housenumber":"3109",
    "addr:postcode":"3032",
    "addr:street":"Highpoint Shopping;Rosamond Rd",
    "iso:country":"AU",
    "sg:address":"Shop 3109, Highpoint Shopping Centre, Rosamond Rd",
    "sg:city":"Maribyrnong",
    "sg:classifiers":[
        {
            "category":"Shopping",
            "subcategory":"Shoes",
            "type":"Retail Goods"
        }
    ],
    "sg:phone":"+61 3 9317 0750",
    "sg:postcode":"3032",
    "sg:province":"VIC",
    "sg:tags":[
        "footwear"
    ],
    "wof:name":"Diana Ferrari",
    "wof:placetype":"venue"
},
  "geometry": {"coordinates":[144.88632200000001,-37.771435],"type":"Point"}
}