{
  "type": "Feature",
  "properties": {
    "iso:country":"AU",
    "sg:address":"Sp 24, Cnr Montacute & Stradbroke Rds",
    "sg:city":"Newton",
    "sg:classifiers":[
        {
            "category":"Communications",
            "subcategory":"Film & Video Production",
            "type":"Services"
        }
    ],
    "sg:phone":"+61 8 8165 0111",
    "sg:postcode":"5074",
    "sg:province":"SA",
    "sg:tags":[
        "dvd",
        "library"
    ],
    "wof:name":"Blockbuster",
    "wof:placetype":"venue"
},
  "geometry": {"coordinates":[138.691772461,-34.8864974976],"type":"Point"}
}