{
  "type": "Feature",
  "properties": {
    "iso:country":"AU",
    "sg:address":"848 Boundary Rd",
    "sg:city":"Richlands",
    "sg:classifiers":[
        {
            "category":"Professional",
            "subcategory":"Testing Lab",
            "type":"Services"
        }
    ],
    "sg:phone":"+61 1300 731 523",
    "sg:postcode":"4077",
    "sg:province":"QLD",
    "sg:tags":[
        "soil",
        "investigation"
    ],
    "wof:name":"STA Alliance",
    "wof:placetype":"venue"
},
  "geometry": {"coordinates":[152.946166992,-27.5802612305],"type":"Point"}
}