{
  "type": "Feature",
  "properties": {
    "addr:full":"Shp15/ 95 John St Cabramatta NSW 2166",
    "addr:housenumber":"95",
    "addr:postcode":"2166",
    "addr:street":"John St",
    "iso:country":"AU",
    "sg:address":"Shp15/ 95 John St",
    "sg:city":"Cabramatta",
    "sg:classifiers":[
        {
            "category":"Shopping",
            "subcategory":"Clothing, Apparel, & Fashions",
            "type":"Retail Goods"
        }
    ],
    "sg:phone":"+61 2 9727 9001",
    "sg:postcode":"2166",
    "sg:province":"NSW",
    "sg:tags":[
        "boutique"
    ],
    "wof:name":"Fangy Formal",
    "wof:placetype":"venue"
},
  "geometry": {"coordinates":[150.93519592300001,-33.8948173523],"type":"Point"}
}