{
  "type": "Feature",
  "properties": {
    "addr:full":"30 Millway St Kedron QLD 4031",
    "addr:housenumber":"30",
    "addr:postcode":"4031",
    "addr:street":"Millway St",
    "iso:country":"AU",
    "sg:address":"30 Millway St",
    "sg:city":"Kedron",
    "sg:classifiers":[
        {
            "category":"Shopping",
            "subcategory":"Stationery & Office Supplies",
            "type":"Retail Goods"
        }
    ],
    "sg:phone":"+61 7 3350 1144",
    "sg:postcode":"4031",
    "sg:province":"QLD",
    "sg:tags":[
        "equipment",
        "display",
        "exhibition"
    ],
    "sg:website":"http://www.stagingdimensions.com.au",
    "wof:name":"Staging Dimensions",
    "wof:placetype":"venue"
},
  "geometry": {"coordinates":[153.02171300000001,-27.395981],"type":"Point"}
}