{
  "type": "Feature",
  "properties": {
    "iso:country":"AU",
    "sg:address":"68 Levanswell Rd",
    "sg:city":"Moorabbin",
    "sg:classifiers":[
        {
            "category":"Banks & Credit Unions",
            "subcategory":"Atm",
            "type":"Services"
        }
    ],
    "sg:phone":"+61 3 9555 0872",
    "sg:postcode":"3189",
    "sg:province":"VIC",
    "sg:tags":[
        "detector",
        "gas"
    ],
    "wof:name":"Tech Air Pty Ltd",
    "wof:placetype":"venue"
},
  "geometry": {"coordinates":[145.07032775900001,-37.9456214905],"type":"Point"}
}