{
  "type": "Feature",
  "properties": {
    "addr:full":"190 Kerry Rd Archerfield QLD 4108",
    "addr:housenumber":"190",
    "addr:postcode":"4108",
    "addr:street":"Kerry Rd",
    "iso:country":"AU",
    "sg:address":"190 Kerry Rd",
    "sg:city":"Archerfield",
    "sg:classifiers":[
        {
            "category":"Autos & Motor Vehicles",
            "subcategory":"Auto Supplies",
            "type":"Retail Goods"
        }
    ],
    "sg:phone":"+61 7 3255 5577",
    "sg:postcode":"4108",
    "sg:province":"QLD",
    "sg:tags":[
        "camper-trailers",
        "caravan",
        "equipment"
    ],
    "wof:name":"Lifestyle Camper Trailers",
    "wof:placetype":"venue"
},
  "geometry": {"coordinates":[153.01484680199999,-27.5715637207],"type":"Point"}
}