{
  "type": "Feature",
  "properties": {
    "addr:full":"6 Hellenic Crt Carrum Downs VIC 3201",
    "addr:housenumber":"6",
    "addr:postcode":"3201",
    "addr:street":"Hellenic Crt",
    "iso:country":"AU",
    "sg:address":"6 Hellenic Crt",
    "sg:city":"Carrum Downs",
    "sg:classifiers":[
        {
            "category":"Professional",
            "type":"Services"
        }
    ],
    "sg:phone":"+61 412 214 786",
    "sg:postcode":"3201",
    "sg:province":"VIC",
    "sg:tags":[
        "courier"
    ],
    "wof:name":"Confidence Couriers",
    "wof:placetype":"venue"
},
  "geometry": {"coordinates":[145.19137599999999,-38.114571],"type":"Point"}
}