{
  "type": "Feature",
  "properties": {
    "addr:full":"37 Mimnagh St Norville QLD 4670",
    "addr:housenumber":"37",
    "addr:postcode":"4670",
    "addr:street":"Mimnagh St",
    "iso:country":"AU",
    "sg:address":"37 Mimnagh St",
    "sg:city":"Norville",
    "sg:classifiers":[
        {
            "category":"Food & Beverages",
            "subcategory":"Groceries & Convenience Stores",
            "type":"Retail Goods"
        }
    ],
    "sg:phone":"+61 7 4152 0485",
    "sg:postcode":"4670",
    "sg:province":"QLD",
    "wof:name":"Norville Food Store",
    "wof:placetype":"venue"
},
  "geometry": {"coordinates":[152.34739685100001,-24.8842658997],"type":"Point"}
}