{
  "type": "Feature",
  "properties": {
    "iso:country":"AU",
    "sg:address":"8 Moriarty Rd",
    "sg:city":"Welshpool",
    "sg:classifiers":[
        {
            "category":"Health Services",
            "subcategory":"Health Practitioner",
            "type":"Services"
        }
    ],
    "sg:phone":"+61 8 9350 6579",
    "sg:postcode":"6106",
    "sg:province":"WA",
    "sg:tags":[
        "physiotherapist"
    ],
    "wof:name":"Carepoint Physiotherapy Services Pty Ltd",
    "wof:placetype":"venue"
},
  "geometry": {"coordinates":[115.933792114,-31.9934616089],"type":"Point"}
}