{
  "type": "Feature",
  "properties": {
    "addr:full":"unit 2, Level 1 46 - 48 Jedda Rd Prestons NSW 2170",
    "addr:housenumber":"46 48",
    "addr:postcode":"2170",
    "addr:street":"Jedda Rd",
    "iso:country":"AU",
    "sg:address":"unit 2, Level 1 46 - 48 Jedda Rd",
    "sg:city":"Prestons",
    "sg:classifiers":[
        {
            "category":"Professional",
            "subcategory":"Business Services",
            "type":"Services"
        }
    ],
    "sg:phone":"+61 2 9825 0018",
    "sg:postcode":"2170",
    "sg:province":"NSW",
    "sg:tags":[
        "drafting"
    ],
    "wof:name":"Ross Oliveri Drafting & Design",
    "wof:placetype":"venue"
},
  "geometry": {"coordinates":[150.88743591299999,-33.9347953796],"type":"Point"}
}