{
  "type": "Feature",
  "properties": {
    "addr:full":"Unit 1/ 277 Nerang-Southport Rd Southport QLD 4215",
    "addr:housenumber":"/ 277",
    "addr:postcode":"4215",
    "addr:street":"Nerang-Southport Rd",
    "iso:country":"AU",
    "sg:address":"Unit 1/ 277 Nerang-Southport Rd",
    "sg:city":"Southport",
    "sg:classifiers":[
        {
            "category":"Retail",
            "subcategory":"Auto Repair",
            "type":"Services"
        }
    ],
    "sg:phone":"+61 7 5531 1399",
    "sg:postcode":"4215",
    "sg:province":"QLD",
    "sg:tags":[
        "testing",
        "inspection",
        "motor",
        "vehicle"
    ],
    "wof:name":"Performance Autogas",
    "wof:placetype":"venue"
},
  "geometry": {"coordinates":[153.415939331,-27.9664154053],"type":"Point"}
}