{
  "type": "Feature",
  "properties": {
    "addr:full":"Unit 2, Cnr Bushells Pl & Newton Rd Wetherill Park NSW 2164",
    "addr:housenumber":"cnr",
    "addr:postcode":"2164",
    "addr:street":"Bushells Pl & Newton Rd",
    "iso:country":"AU",
    "sg:address":"Unit 2, Cnr Bushells Pl & Newton Rd",
    "sg:city":"Wetherill Park",
    "sg:classifiers":[
        {
            "category":"Retail",
            "subcategory":"Auto Repair",
            "type":"Services"
        }
    ],
    "sg:phone":"+61 2 9756 0877",
    "sg:postcode":"2164",
    "sg:province":"NSW",
    "sg:tags":[
        "aluminium"
    ],
    "wof:name":"Capral Aluminium Centres",
    "wof:placetype":"venue"
},
  "geometry": {"coordinates":[150.89219665499999,-33.8426551819],"type":"Point"}
}