{
  "type": "Feature",
  "properties": {
    "addr:full":"49 Capella Crs Moorabbin VIC 3189",
    "addr:housenumber":"49",
    "addr:postcode":"3189",
    "addr:street":"Capella Crs",
    "iso:country":"AU",
    "sg:address":"49 Capella Crs",
    "sg:city":"Moorabbin",
    "sg:classifiers":[
        {
            "category":"Building & Trades",
            "subcategory":"Pest Control",
            "type":"Services"
        }
    ],
    "sg:phone":"+61 1800 083 300",
    "sg:postcode":"3189",
    "sg:province":"VIC",
    "sg:tags":[
        "wholesaler",
        "mfrs",
        "walking",
        "umbrella",
        "stick"
    ],
    "sg:website":"http://www.instantshadeumbrellas.com.au",
    "wof:name":"Instant Shade Umbrellas",
    "wof:placetype":"venue"
},
  "geometry": {"coordinates":[145.07533264200001,-37.9423942566],"type":"Point"}
}