{
  "type": "Feature",
  "properties": {
    "addr:full":"6/ 154 Fullarton Rd Rose Park SA 5067",
    "addr:housenumber":"/ 154",
    "addr:postcode":"5067",
    "addr:street":"Fullarton Rd Rose",
    "iso:country":"AU",
    "sg:address":"6/ 154 Fullarton Rd",
    "sg:city":"Rose Park",
    "sg:classifiers":[
        {
            "category":"Shopping",
            "subcategory":"Mobile Phones",
            "type":"Retail Goods"
        }
    ],
    "sg:phone":"+61 1300 765 056",
    "sg:postcode":"5067",
    "sg:province":"SA",
    "sg:tags":[
        "telephone",
        "accessory"
    ],
    "wof:name":"DVM Telecommunications P/L",
    "wof:placetype":"venue"
},
  "geometry": {"coordinates":[138.624145508,-34.9314575195],"type":"Point"}
}