{
  "type": "Feature",
  "properties": {
    "addr:full":"100 Bar Beach Ave Merewether NSW 2291",
    "addr:postcode":"2291",
    "addr:street":"Beach Ave",
    "iso:country":"AU",
    "sg:address":"100 Bar Beach Ave",
    "sg:city":"Merewether",
    "sg:classifiers":[
        {
            "category":"Health Services",
            "subcategory":"Dentist",
            "type":"Services"
        }
    ],
    "sg:phone":"+61 2 4929 2790",
    "sg:postcode":"2291",
    "sg:province":"NSW",
    "sg:tags":[
        "dental",
        "prosthetist"
    ],
    "wof:name":"Hutchinson Brent",
    "wof:placetype":"venue"
},
  "geometry": {"coordinates":[151.76121520999999,-32.9394111633],"type":"Point"}
}