{
  "type": "Feature",
  "properties": {
    "iso:country":"AU",
    "sg:address":"Wyreema St",
    "sg:city":"Murray Bridge",
    "sg:classifiers":[
        {
            "category":"Retail",
            "subcategory":"Auto Repair",
            "type":"Services"
        }
    ],
    "sg:phone":"+61 8 8532 4583",
    "sg:postcode":"5253",
    "sg:province":"SA",
    "sg:tags":[
        "beater",
        "painter",
        "panel"
    ],
    "wof:name":"Alan Wise Crash Repairs",
    "wof:placetype":"venue"
},
  "geometry": {"coordinates":[139.258712769,-35.1216125488],"type":"Point"}
}