{
  "type": "Feature",
  "properties": {
    "iso:country":"AU",
    "sg:address":"230 Sheridan St",
    "sg:city":"Cairns",
    "sg:classifiers":[
        {
            "category":"Retail",
            "subcategory":"Auto Repair",
            "type":"Services"
        }
    ],
    "sg:phone":"+61 7 4041 6645",
    "sg:postcode":"4870",
    "sg:province":"QLD",
    "sg:tags":[
        "repairer",
        "motor",
        "engineer"
    ],
    "wof:name":"Far Northern Mechanical",
    "wof:placetype":"venue"
},
  "geometry": {"coordinates":[145.76335144000001,-16.9112491608],"type":"Point"}
}