{
  "type": "Feature",
  "properties": {
    "iso:country":"AU",
    "sg:address":"6 Bunyan Rd",
    "sg:city":"Leonay",
    "sg:classifiers":[
        {
            "category":"Building & Trades",
            "subcategory":"Landscaping Services",
            "type":"Services"
        }
    ],
    "sg:phone":"+61 2 4735 7501",
    "sg:postcode":"2750",
    "sg:province":"NSW",
    "sg:tags":[
        "inspection"
    ],
    "wof:name":"S.D.S. Pest Services",
    "wof:placetype":"venue"
},
  "geometry": {"coordinates":[150.65507507300001,-33.7623405457],"type":"Point"}
}