{
  "type": "Feature",
  "properties": {
    "iso:country":"AU",
    "sg:address":"64 Wogolin Rd",
    "sg:city":"Wickepin",
    "sg:classifiers":[
        {
            "category":"Autos & Motor Vehicles",
            "subcategory":"Fuel & Gas Station",
            "type":"Retail Goods"
        }
    ],
    "sg:phone":"+61 8 9888 1122",
    "sg:postcode":"6370",
    "sg:province":"WA",
    "wof:name":"Ampol",
    "wof:placetype":"venue"
},
  "geometry": {"coordinates":[117.503197,-32.781673],"type":"Point"}
}