{
  "type": "Feature",
  "properties": {
    "addr:full":"Shop 6, 282 Princes Hwy Sylvania Heights NSW 2224",
    "addr:housenumber":"shop 6 282",
    "addr:postcode":"2224",
    "addr:street":"Princes Hwy",
    "iso:country":"AU",
    "sg:address":"Shop 6, 282 Princes Hwy",
    "sg:city":"Sylvania Heights",
    "sg:classifiers":[
        {
            "category":"Personal",
            "subcategory":"Beauty Salon",
            "type":"Services"
        }
    ],
    "sg:phone":"+61 2 9544 9440",
    "sg:postcode":"2224",
    "sg:province":"NSW",
    "sg:tags":[
        "hairdresser"
    ],
    "wof:name":"Hair Xclusive",
    "wof:placetype":"venue"
},
  "geometry": {"coordinates":[151.09446716299999,-34.0141868591],"type":"Point"}
}