{
  "type": "Feature",
  "properties": {
    "addr:full":"41 Gow St Padstow NSW 2211",
    "addr:housenumber":"41",
    "addr:postcode":"2211",
    "addr:street":"Gow St",
    "iso:country":"AU",
    "sg:address":"41 Gow St",
    "sg:city":"Padstow",
    "sg:classifiers":[
        {
            "category":"Retail",
            "subcategory":"Auto Repair",
            "type":"Services"
        }
    ],
    "sg:phone":"+61 2 9790 4888",
    "sg:postcode":"2211",
    "sg:province":"NSW",
    "sg:tags":[
        "clutch",
        "brake"
    ],
    "wof:name":"Quick-Fit The Automotive Service Specialists",
    "wof:placetype":"venue"
},
  "geometry": {"coordinates":[151.03582800000001,-33.937683],"type":"Point"}
}