{
  "type": "Feature",
  "properties": {
    "addr:full":"Shop 7, Anglo Rd Campsie NSW 2194",
    "addr:housenumber":"shop 7",
    "addr:postcode":"2194",
    "addr:street":"Anglo Rd",
    "iso:country":"AU",
    "sg:address":"Shop 7, Anglo Rd",
    "sg:city":"Campsie",
    "sg:classifiers":[
        {
            "category":"Personal",
            "subcategory":"Beauty Salon",
            "type":"Services"
        }
    ],
    "sg:phone":"+61 2 9789 2790",
    "sg:postcode":"2194",
    "sg:province":"NSW",
    "sg:tags":[
        "hairdresser"
    ],
    "wof:name":"Salon Edward",
    "wof:placetype":"venue"
},
  "geometry": {"coordinates":[151.10325599999999,-33.911007],"type":"Point"}
}