{
  "type": "Feature",
  "properties": {
    "iso:country":"AU",
    "sg:address":"4 Loader St",
    "sg:city":"Berri",
    "sg:classifiers":[
        {
            "category":"Education",
            "subcategory":"School",
            "type":"Public Place"
        }
    ],
    "sg:phone":"+61 8 8582 1170",
    "sg:postcode":"5343",
    "sg:province":"SA",
    "sg:tags":[
        "state",
        "except",
        "nsw"
    ],
    "wof:name":"Vocational Education & Training Centre",
    "wof:placetype":"venue"
},
  "geometry": {"coordinates":[140.60528564399999,-34.2818984985],"type":"Point"}
}