{
  "type": "Feature",
  "properties": {
    "addr:full":"Sarsfield Site Sandy Creek Rd Ravenswood QLD 4816",
    "addr:postcode":"4816",
    "addr:street":"Sandy Creek Rd",
    "iso:country":"AU",
    "sg:address":"Sarsfield Site Sandy Creek Rd",
    "sg:city":"Ravenswood",
    "sg:classifiers":[
        {
            "category":"Building & Trades",
            "subcategory":"Construction",
            "type":"Services"
        }
    ],
    "sg:phone":"+61 7 4770 2273",
    "sg:postcode":"4816",
    "sg:province":"QLD",
    "sg:tags":[
        "earth",
        "excavating",
        "moving",
        "contractor"
    ],
    "wof:name":"Emeco International Pty Limited",
    "wof:placetype":"venue"
},
  "geometry": {"coordinates":[146.89991800000001,-20.10808],"type":"Point"}
}