{
  "type": "Feature",
  "properties": {
    "iso:country":"AU",
    "sg:address":"15 Auburn Ave",
    "sg:city":"Northcote",
    "sg:classifiers":[
        {
            "category":"Building & Trades",
            "subcategory":"Construction",
            "type":"Services"
        }
    ],
    "sg:phone":"+61 408 556 722",
    "sg:postcode":"3070",
    "sg:province":"VIC",
    "sg:tags":[
        "stonework",
        "stone",
        "mason"
    ],
    "wof:name":"David Williams Pty Ltd",
    "wof:placetype":"venue"
},
  "geometry": {"coordinates":[144.989258,-37.769142],"type":"Point"}
}