{
  "type": "Feature",
  "properties": {
    "iso:country":"AU",
    "sg:address":"44 Sydney St",
    "sg:city":"Oxley Park",
    "sg:classifiers":[
        {
            "category":"Food & Beverages",
            "subcategory":"Supermarket",
            "type":"Retail Goods"
        }
    ],
    "sg:phone":"+61 2 9623 4901",
    "sg:postcode":"2760",
    "sg:province":"NSW",
    "sg:tags":[
        "grocery",
        "store"
    ],
    "wof:name":"Oxley Park Supermarket",
    "wof:placetype":"venue"
},
  "geometry": {"coordinates":[150.78854370100001,-33.7680587769],"type":"Point"}
}