{
  "type": "Feature",
  "properties": {
    "addr:full":"55 George St Rockhampton QLD 4700",
    "addr:housenumber":"55",
    "addr:postcode":"4700",
    "addr:street":"George St",
    "iso:country":"AU",
    "sg:address":"55 George St",
    "sg:city":"Rockhampton",
    "sg:classifiers":[
        {
            "category":"Travel",
            "subcategory":"Hotels & Motels",
            "type":"Entertainment"
        }
    ],
    "sg:phone":"+61 7 4922 6577",
    "sg:postcode":"4700",
    "sg:province":"QLD",
    "wof:name":"Rockhampton Palms Motor Inn",
    "wof:placetype":"venue"
},
  "geometry": {"coordinates":[150.51019287099999,-23.3872127533],"type":"Point"}
}