{
  "type": "Feature",
  "properties": {
    "addr:full":"24 Trevor St Ulverstone TAS 7315",
    "addr:housenumber":"24",
    "addr:postcode":"7315",
    "addr:street":"Trevor St",
    "iso:country":"AU",
    "sg:address":"24 Trevor St",
    "sg:city":"Ulverstone",
    "sg:classifiers":[
        {
            "category":"Utilities",
            "subcategory":"Fuel Oil & Lpg",
            "type":"Services"
        }
    ],
    "sg:phone":"+61 1300 367 999",
    "sg:postcode":"7315",
    "sg:province":"TAS",
    "sg:tags":[
        "heating"
    ],
    "wof:name":"Norvac Pty Ltd",
    "wof:placetype":"venue"
},
  "geometry": {"coordinates":[146.16209411599999,-41.1641235352],"type":"Point"}
}