{
  "type": "Feature",
  "properties": {
    "addr:full":"Shp 5, 338 Camden Valley Way Narellan NSW 2567",
    "addr:housenumber":"338",
    "addr:postcode":"2567",
    "addr:street":"Camden Valley Way",
    "iso:country":"AU",
    "sg:address":"Shp 5, 338",
    "sg:city":"Camden Valley Way Narellan",
    "sg:classifiers":[
        {
            "category":"Banks & Credit Unions",
            "subcategory":"Financial Services",
            "type":"Services"
        }
    ],
    "sg:phone":"+61 2 4647 2155",
    "sg:postcode":"2567",
    "sg:province":"NSW",
    "sg:tags":[
        "loan",
        "finance",
        "mortgage"
    ],
    "wof:name":"Wizard",
    "wof:placetype":"venue"
},
  "geometry": {"coordinates":[150.73765564000001,-34.0401344299],"type":"Point"}
}