{
  "type": "Feature",
  "properties": {
    "iso:country":"AU",
    "sg:address":"158 Lennox St",
    "sg:city":"Richmond",
    "sg:classifiers":[
        {
            "category":"Health Services",
            "subcategory":"Doctor",
            "type":"Services"
        }
    ],
    "sg:phone":"+61 3 9429 5955",
    "sg:postcode":"3121",
    "sg:province":"VIC",
    "sg:tags":[
        "medical",
        "practitioner"
    ],
    "wof:name":"Devine T J",
    "wof:placetype":"venue"
},
  "geometry": {"coordinates":[144.99458313,-37.8173065186],"type":"Point"}
}