{
  "type": "Feature",
  "properties": {
    "addr:full":"11 Hulme Court, Myaree WA 6154",
    "addr:housenumber":"11",
    "addr:postcode":"6154",
    "addr:street":"Hulme Court",
    "iso:country":"AU",
    "sg:address":"11 Hulme Court,",
    "sg:city":"Myaree",
    "sg:classifiers":[
        {
            "category":"Professional",
            "subcategory":"Employment Agencies",
            "type":"Services"
        }
    ],
    "sg:phone":"+61 8 9329 9011",
    "sg:postcode":"6154",
    "sg:province":"WA",
    "sg:tags":[
        "occupational",
        "therapist"
    ],
    "wof:name":"Maximum Independence",
    "wof:placetype":"venue"
},
  "geometry": {"coordinates":[115.812462,-32.044807],"type":"Point"}
}