{
  "type": "Feature",
  "properties": {
    "iso:country":"AU",
    "sg:address":"240 Centre Dandenong Rd",
    "sg:city":"Cheltenham",
    "sg:classifiers":[
        {
            "category":"Building & Trades",
            "subcategory":"Construction",
            "type":"Services"
        }
    ],
    "sg:phone":"+61 3 9583 5969",
    "sg:postcode":"3192",
    "sg:province":"VIC",
    "sg:tags":[
        "scaffolding"
    ],
    "wof:name":"Baycity Scaffold & Equipment Rentals",
    "wof:placetype":"venue"
},
  "geometry": {"coordinates":[145.085403442,-37.9692726135],"type":"Point"}
}