{
  "type": "Feature",
  "properties": {
    "iso:country":"AU",
    "sg:address":"30 Levy St",
    "sg:city":"Glenbrook",
    "sg:classifiers":[
        {
            "category":"Utilities",
            "subcategory":"Refuse",
            "type":"Services"
        }
    ],
    "sg:phone":"+61 2 4739 4009",
    "sg:postcode":"2773",
    "sg:province":"NSW",
    "sg:tags":[
        "remover",
        "rubbish"
    ],
    "wof:name":"Egan B P",
    "wof:placetype":"venue"
},
  "geometry": {"coordinates":[150.62193298299999,-33.7611885071],"type":"Point"}
}