{
  "type": "Feature",
  "properties": {
    "addr:full":"53 High St Beechworth VIC 3747",
    "addr:housenumber":"53",
    "addr:postcode":"3747",
    "addr:street":"High St",
    "iso:country":"AU",
    "sg:address":"53 High St",
    "sg:city":"Beechworth",
    "sg:classifiers":[
        {
            "category":"Retail",
            "subcategory":"Funeral Services",
            "type":"Services"
        }
    ],
    "sg:phone":"+61 3 5728 1052",
    "sg:postcode":"3747",
    "sg:province":"VIC",
    "sg:tags":[
        "director"
    ],
    "wof:name":"Brindley Ross",
    "wof:placetype":"venue"
},
  "geometry": {"coordinates":[146.687714,-36.360386],"type":"Point"}
}