{
  "type": "Feature",
  "properties": {
    "iso:country":"AU",
    "sg:address":"49 Primary School Rd",
    "sg:city":"Maroochydore",
    "sg:classifiers":[
        {
            "category":"Health Services",
            "subcategory":"Doctor",
            "type":"Services"
        }
    ],
    "sg:phone":"+61 7 5479 1211",
    "sg:postcode":"4558",
    "sg:province":"QLD",
    "sg:tags":[
        "podiatrist"
    ],
    "wof:name":"Alana Underwood",
    "wof:placetype":"venue"
},
  "geometry": {"coordinates":[153.084747314,-26.6528930664],"type":"Point"}
}