{
  "type": "Feature",
  "properties": {
    "addr:full":"PO Box 508 Lilydale VIC 3140",
    "addr:postcode":"3140",
    "iso:country":"AU",
    "sg:address":"PO Box 508",
    "sg:city":"Lilydale",
    "sg:classifiers":[
        {
            "category":"Wholesale",
            "subcategory":"Machinery & Supplies",
            "type":"Manufacturing & Wholesale Goods"
        }
    ],
    "sg:phone":"+61 1300 883 690",
    "sg:postcode":"3140",
    "sg:province":"VIC",
    "sg:tags":[
        "process",
        "instrument",
        "control"
    ],
    "wof:name":"Fox All Services Pty Ltd",
    "wof:placetype":"venue"
},
  "geometry": {"coordinates":[145.37161254899999,-37.7617797852],"type":"Point"}
}