{
  "type": "Feature",
  "properties": {
    "addr:full":"13 Narrabri Crt Nerang QLD 4211",
    "addr:housenumber":"13",
    "addr:postcode":"4211",
    "addr:street":"Narrabri Crt",
    "iso:country":"AU",
    "sg:address":"13 Narrabri Crt",
    "sg:city":"Nerang",
    "sg:classifiers":[
        {
            "category":"Professional",
            "subcategory":"Detective & Security Services",
            "type":"Services"
        }
    ],
    "sg:phone":"+61 7 5535 0682",
    "sg:postcode":"4211",
    "sg:province":"QLD",
    "sg:tags":[
        "equipment",
        "window",
        "doors"
    ],
    "wof:name":"Hinterland Screens",
    "wof:placetype":"venue"
},
  "geometry": {"coordinates":[153.3359375,-27.9646511078],"type":"Point"}
}