{
  "type": "Feature",
  "properties": {
    "addr:full":"Cnr Hassall & Priddle Sts Westmead NSW 2145",
    "addr:postcode":"2145",
    "addr:street":"Cnr",
    "iso:country":"AU",
    "sg:address":"Cnr Hassall & Priddle Sts",
    "sg:city":"Westmead",
    "sg:classifiers":[
        {
            "category":"Government",
            "subcategory":"City Hall",
            "type":"Public Place"
        }
    ],
    "sg:phone":"+61 2 9840 9840",
    "sg:postcode":"2145",
    "sg:province":"NSW",
    "wof:name":"Westmead Progress Hall",
    "wof:placetype":"venue"
},
  "geometry": {"coordinates":[150.988723755,-33.8095245361],"type":"Point"}
}