{
  "type": "Feature",
  "properties": {
    "addr:full":"31 Lincoln St Lindisfarne TAS 7015",
    "addr:housenumber":"31",
    "addr:postcode":"7015",
    "addr:street":"Lincoln St",
    "iso:country":"AU",
    "sg:address":"31 Lincoln St",
    "sg:city":"Lindisfarne",
    "sg:classifiers":[
        {
            "category":"Health Services",
            "subcategory":"Doctor",
            "type":"Services"
        }
    ],
    "sg:phone":"+61 3 6243 8788",
    "sg:postcode":"7015",
    "sg:province":"TAS",
    "sg:tags":[
        "medical",
        "practitioner"
    ],
    "wof:name":"Whyte George G",
    "wof:placetype":"venue"
},
  "geometry": {"coordinates":[147.35354614299999,-42.8476638794],"type":"Point"}
}