{
  "type": "Feature",
  "properties": {
    "iso:country":"AU",
    "sg:address":"107 Great Western Hwy",
    "sg:city":"Kingswood",
    "sg:classifiers":[
        {
            "category":"Autos & Motor Vehicles",
            "subcategory":"Automobile Sales",
            "type":"Retail Goods"
        }
    ],
    "sg:phone":"+61 2 4736 4555",
    "sg:postcode":"2747",
    "sg:province":"NSW",
    "sg:tags":[
        "car",
        "new"
    ],
    "wof:name":"Penrith SSangyong",
    "wof:placetype":"venue"
},
  "geometry": {"coordinates":[150.723419189,-33.7591743469],"type":"Point"}
}