{
  "type": "Feature",
  "properties": {
    "addr:full":"18f Purinuan Rd Reservoir VIC 3073",
    "addr:housenumber":"18f",
    "addr:postcode":"3073",
    "addr:street":"Purinuan Rd",
    "iso:country":"AU",
    "sg:address":"18f Purinuan Rd",
    "sg:city":"Reservoir",
    "sg:classifiers":[
        {
            "category":"Communications",
            "subcategory":"Television Station",
            "type":"Services"
        }
    ],
    "sg:phone":"+61 3 9402 1960",
    "sg:postcode":"3073",
    "sg:province":"VIC",
    "sg:tags":[
        "equipment",
        "laser"
    ],
    "wof:name":"BTH Spares",
    "wof:placetype":"venue"
},
  "geometry": {"coordinates":[145.03286743199999,-37.7094230652],"type":"Point"}
}