{
  "type": "Feature",
  "properties": {
    "addr:full":"8 Henry St Chittaway NSW 2261",
    "addr:housenumber":"8",
    "addr:postcode":"2261",
    "addr:street":"Henry St",
    "iso:country":"AU",
    "sg:address":"8 Henry St",
    "sg:city":"Chittaway",
    "sg:classifiers":[
        {
            "category":"Professional",
            "subcategory":"Art Services",
            "type":"Services"
        }
    ],
    "sg:phone":"+61 410 480 680",
    "sg:postcode":"2261",
    "sg:province":"NSW",
    "sg:tags":[
        "decorator",
        "painter"
    ],
    "wof:name":"Mike Gavin Painter & Decorator",
    "wof:placetype":"venue"
},
  "geometry": {"coordinates":[151.44914199999999,-33.322178],"type":"Point"}
}