{
  "type": "Feature",
  "properties": {
    "addr:full":"97- 109 Railway Ave Townsville QLD 4810",
    "addr:housenumber":"109",
    "addr:postcode":"4810",
    "addr:street":"97;Railway Ave",
    "iso:country":"AU",
    "sg:address":"97- 109 Railway Ave",
    "sg:city":"Townsville",
    "sg:classifiers":[
        {
            "category":"Train Station",
            "subcategory":"Light Rail",
            "type":"Transportation"
        }
    ],
    "sg:phone":"+61 7 4772 2595",
    "sg:postcode":"4810",
    "sg:province":"QLD",
    "sg:tags":[
        "equipment",
        "energy",
        "solar"
    ],
    "wof:name":"Harry Newitts Specialist Insulations",
    "wof:placetype":"venue"
},
  "geometry": {"coordinates":[146.815674,-19.281528],"type":"Point"}
}