{
  "type": "Feature",
  "properties": {
    "iso:country":"AU",
    "sg:address":"43 Station St",
    "sg:city":"Cobram",
    "sg:classifiers":[
        {
            "category":"Personal",
            "subcategory":"Beauty Salon",
            "type":"Services"
        }
    ],
    "sg:phone":"+61 3 5872 2750",
    "sg:postcode":"3644",
    "sg:province":"VIC",
    "sg:tags":[
        "hairdresser"
    ],
    "wof:name":"Shear Kaos",
    "wof:placetype":"venue"
},
  "geometry": {"coordinates":[145.64662170400001,-35.9219970703],"type":"Point"}
}