{
  "type": "Feature",
  "properties": {
    "addr:full":"172 Welsford St Shepparton VIC 3630",
    "addr:housenumber":"172",
    "addr:postcode":"3630",
    "addr:street":"Welsford St",
    "iso:country":"AU",
    "sg:address":"172 Welsford St",
    "sg:city":"Shepparton",
    "sg:classifiers":[
        {
            "category":"Health Services",
            "subcategory":"Doctor",
            "type":"Services"
        }
    ],
    "sg:phone":"+61 3 5821 9655",
    "sg:postcode":"3630",
    "sg:province":"VIC",
    "sg:tags":[
        "medical",
        "practitioner"
    ],
    "wof:name":"Ron Tomkins",
    "wof:placetype":"venue"
},
  "geometry": {"coordinates":[145.39749145499999,-36.3817939758],"type":"Point"}
}