{
  "type": "Feature",
  "properties": {
    "addr:full":"39 Latje Rd Robinvale VIC 3549",
    "addr:housenumber":"39",
    "addr:postcode":"3549",
    "addr:street":"Latje Rd",
    "iso:country":"AU",
    "sg:address":"39 Latje Rd",
    "sg:city":"Robinvale",
    "sg:classifiers":[
        {
            "category":"Health Services",
            "subcategory":"Doctor",
            "type":"Services"
        }
    ],
    "sg:phone":"+61 3 5026 1744",
    "sg:postcode":"3549",
    "sg:province":"VIC",
    "sg:tags":[
        "medical",
        "practitioner"
    ],
    "wof:name":"Robinvale District Medical Centre",
    "wof:placetype":"venue"
},
  "geometry": {"coordinates":[142.77484130900001,-34.5825653076],"type":"Point"}
}