{
  "type": "Feature",
  "properties": {
    "addr:full":"262 Charman Rd Cheltenham VIC 3192",
    "addr:housenumber":"262",
    "addr:postcode":"3192",
    "addr:street":"Charman Rd",
    "iso:country":"AU",
    "sg:address":"262 Charman Rd",
    "sg:city":"Cheltenham",
    "sg:classifiers":[
        {
            "category":"Real Estate",
            "subcategory":"Real Estate Agent",
            "type":"Services"
        }
    ],
    "sg:phone":"+61 3 9583 0996",
    "sg:postcode":"3192",
    "sg:province":"VIC",
    "wof:name":"Aitken Real Estate Pty Ltd",
    "wof:placetype":"venue"
},
  "geometry": {"coordinates":[145.05532836899999,-37.9683036804],"type":"Point"}
}