{
  "type": "Feature",
  "properties": {
    "addr:full":"Wurrup St Normanton QLD 4890",
    "addr:postcode":"4890",
    "addr:street":"St",
    "iso:country":"AU",
    "sg:address":"Wurrup St",
    "sg:city":"Normanton",
    "sg:classifiers":[
        {
            "category":"Building & Trades",
            "subcategory":"Plumbing",
            "type":"Services"
        }
    ],
    "sg:phone":"+61 7 4745 1364",
    "sg:postcode":"4890",
    "sg:province":"QLD",
    "sg:tags":[
        "plumber",
        "gasfitters"
    ],
    "wof:name":"Foote's Plumbing",
    "wof:placetype":"venue"
},
  "geometry": {"coordinates":[141.07513427699999,-17.6805973053],"type":"Point"}
}