{
  "type": "Feature",
  "properties": {
    "addr:full":"47 Godwin St Forster NSW 2428",
    "addr:housenumber":"47",
    "addr:postcode":"2428",
    "addr:street":"Godwin St",
    "iso:country":"AU",
    "sg:address":"47 Godwin St",
    "sg:city":"Forster",
    "sg:classifiers":[
        {
            "category":"Social Services",
            "subcategory":"Child Care",
            "type":"Services"
        }
    ],
    "sg:phone":"+61 2 6555 5133",
    "sg:postcode":"2428",
    "sg:province":"NSW",
    "wof:name":"Pokey Possum Preschool",
    "wof:placetype":"venue"
},
  "geometry": {"coordinates":[152.515457,-32.193874],"type":"Point"}
}