{
  "type": "Feature",
  "properties": {
    "addr:full":"16 Crown Rd Alexandra Hills QLD 4161",
    "addr:housenumber":"16",
    "addr:postcode":"4161",
    "addr:street":"Crown Rd",
    "iso:country":"AU",
    "sg:address":"16 Crown Rd",
    "sg:city":"Alexandra Hills",
    "sg:classifiers":[
        {
            "category":"Food & Beverages",
            "subcategory":"Specialty",
            "type":"Retail Goods"
        }
    ],
    "sg:phone":"+61 7 3824 1416",
    "sg:postcode":"4161",
    "sg:province":"QLD",
    "sg:tags":[
        "product",
        "health"
    ],
    "wof:name":"Herbalife Alexandra Hills",
    "wof:placetype":"venue"
},
  "geometry": {"coordinates":[153.224411011,-27.5202598572],"type":"Point"}
}