{
  "type": "Feature",
  "properties": {
    "addr:full":"36 Pradella St Darra QLD 4076",
    "addr:housenumber":"36",
    "addr:postcode":"4076",
    "addr:street":"Pradella St",
    "iso:country":"AU",
    "sg:address":"36 Pradella St",
    "sg:city":"Darra",
    "sg:classifiers":[
        {
            "category":"Manufacturing",
            "subcategory":"Electronics",
            "type":"Manufacturing & Wholesale Goods"
        }
    ],
    "sg:phone":"+61 7 3713 7800",
    "sg:postcode":"4076",
    "sg:province":"QLD",
    "sg:tags":[
        "wholesaler",
        "equipment",
        "part",
        "mfrs",
        "refrigeration"
    ],
    "wof:name":"Abton Compressors",
    "wof:placetype":"venue"
},
  "geometry": {"coordinates":[152.95179748499999,-27.5773429871],"type":"Point"}
}