{
  "type": "Feature",
  "properties": {
    "addr:full":"Fcty1/ 493 Hammond Rd Dandenong South VIC 3175",
    "addr:housenumber":"493",
    "addr:postcode":"3175",
    "addr:street":"Hammond Rd",
    "iso:country":"AU",
    "sg:address":"Fcty1/ 493 Hammond Rd",
    "sg:city":"Dandenong South",
    "sg:classifiers":[
        {
            "category":"Home & Garden",
            "subcategory":"Home Furnishings",
            "type":"Retail Goods"
        }
    ],
    "sg:phone":"+61 3 9768 2584",
    "sg:postcode":"3175",
    "sg:province":"VIC",
    "sg:tags":[
        "shower",
        "screen"
    ],
    "wof:name":"Platinum Shower Screens",
    "wof:placetype":"venue"
},
  "geometry": {"coordinates":[145.20216369600001,-38.0324516296],"type":"Point"}
}