{
  "type": "Feature",
  "properties": {
    "addr:full":"1351 Malvern Rd Malvern VIC 3144",
    "addr:housenumber":"1351",
    "addr:postcode":"3144",
    "addr:street":"Malvern Rd",
    "iso:country":"AU",
    "sg:address":"1351 Malvern Rd",
    "sg:city":"Malvern",
    "sg:classifiers":[
        {
            "category":"Building & Trades",
            "subcategory":"Construction",
            "type":"Services"
        }
    ],
    "sg:phone":"+61 3 9821 0244",
    "sg:postcode":"3144",
    "sg:province":"VIC",
    "sg:tags":[
        "contractor"
    ],
    "wof:name":"Ravida Homes Pty Ltd",
    "wof:placetype":"venue"
},
  "geometry": {"coordinates":[145.03912353499999,-37.8526916504],"type":"Point"}
}