{
  "type": "Feature",
  "properties": {
    "addr:full":"9 Kayleigh Drv Maroochydore QLD 4558",
    "addr:housenumber":"9",
    "addr:postcode":"4558",
    "addr:street":"Kayleigh Drv",
    "iso:country":"AU",
    "sg:address":"9 Kayleigh Drv",
    "sg:city":"Maroochydore",
    "sg:classifiers":[
        {
            "category":"Building & Trades",
            "subcategory":"Plumbing",
            "type":"Services"
        }
    ],
    "sg:phone":"+61 7 5479 1900",
    "sg:postcode":"4558",
    "sg:province":"QLD",
    "sg:tags":[
        "drainers"
    ],
    "wof:name":"Tacoma Plumbing & Drainage Pty Ltd",
    "wof:placetype":"venue"
},
  "geometry": {"coordinates":[153.09025573700001,-26.6703586578],"type":"Point"}
}