{
  "type": "Feature",
  "properties": {
    "iso:country":"AU",
    "sg:address":"1a Kentish Pl",
    "sg:city":"Millicent",
    "sg:classifiers":[
        {
            "category":"Cafe",
            "type":"Food & Drink"
        }
    ],
    "sg:phone":"+61 8 8733 2645",
    "sg:postcode":"5280",
    "sg:province":"SA",
    "wof:name":"Pick &#039;N&#039; Chews Deli",
    "wof:placetype":"venue"
},
  "geometry": {"coordinates":[140.35205099999999,-37.595436],"type":"Point"}
}