{
  "type": "Feature",
  "properties": {
    "iso:country":"AU",
    "sg:address":"24 Hibiscus Ave",
    "sg:city":"Cheltenham",
    "sg:classifiers":[
        {
            "category":"Utilities",
            "subcategory":"Electric",
            "type":"Services"
        }
    ],
    "sg:phone":"+61 3 9584 2848",
    "sg:postcode":"3192",
    "sg:province":"VIC",
    "sg:tags":[
        "electrical",
        "contractor"
    ],
    "wof:name":"Nuttall Electrical Pty Ltd",
    "wof:placetype":"venue"
},
  "geometry": {"coordinates":[145.08203125,-37.9708251953],"type":"Point"}
}