{
  "type": "Feature",
  "properties": {
    "addr:full":"18 Post Office Pl Glenroy VIC 3046",
    "addr:housenumber":"18",
    "addr:postcode":"3046",
    "addr:street":"Post Office Pl",
    "iso:country":"AU",
    "sg:address":"18 Post Office Pl",
    "sg:city":"Glenroy",
    "sg:classifiers":[
        {
            "category":"Shopping",
            "subcategory":"Clothing, Apparel, & Fashions",
            "type":"Retail Goods"
        }
    ],
    "sg:phone":"+61 3 9304 3000",
    "sg:postcode":"3046",
    "sg:province":"VIC",
    "sg:tags":[
        "lady",
        "wear"
    ],
    "wof:name":"Ash Garments & Fabrics",
    "wof:placetype":"venue"
},
  "geometry": {"coordinates":[144.91604614299999,-37.7043838501],"type":"Point"}
}