{
  "type": "Feature",
  "properties": {
    "iso:country":"AU",
    "sg:address":"Spencer St",
    "sg:city":"Iluka",
    "sg:classifiers":[
        {
            "category":"Autos & Motor Vehicles",
            "subcategory":"Fuel & Gas Station",
            "type":"Retail Goods"
        }
    ],
    "sg:phone":"+61 2 6645 7121",
    "sg:postcode":"2466",
    "sg:province":"NSW",
    "wof:name":"BP Australia Limited",
    "wof:placetype":"venue"
},
  "geometry": {"coordinates":[153.351074219,-29.4058113098],"type":"Point"}
}