{
  "type": "Feature",
  "properties": {
    "iso:country":"AU",
    "sg:address":"Aerodrome Rd",
    "sg:city":"Maroochydore",
    "sg:classifiers":[
        {
            "category":"Shopping",
            "subcategory":"Computers & Home Electronics",
            "type":"Retail Goods"
        }
    ],
    "sg:phone":"+61 7 5443 4500",
    "sg:postcode":"4558",
    "sg:province":"QLD",
    "sg:tags":[
        "equipment",
        "multimedia"
    ],
    "wof:name":"Visual Magic Productions",
    "wof:placetype":"venue"
},
  "geometry": {"coordinates":[153.092987061,-26.6567630768],"type":"Point"}
}