{
  "type": "Feature",
  "properties": {
    "addr:full":"32 Carlinga Drv Vermont VIC 3133",
    "addr:housenumber":"32",
    "addr:postcode":"3133",
    "addr:street":"Carlinga Drv",
    "iso:country":"AU",
    "sg:address":"32 Carlinga Drv",
    "sg:city":"Vermont",
    "sg:classifiers":[
        {
            "category":"Utilities",
            "subcategory":"Fuel Oil & Lpg",
            "type":"Services"
        }
    ],
    "sg:phone":"+61 417 470 032",
    "sg:postcode":"3133",
    "sg:province":"VIC",
    "sg:tags":[
        "combustion",
        "engineer"
    ],
    "wof:name":"Steathron Pty Ltd",
    "wof:placetype":"venue"
},
  "geometry": {"coordinates":[145.203857422,-37.8426094055],"type":"Point"}
}