{
  "type": "Feature",
  "properties": {
    "iso:country":"AU",
    "sg:address":"45 Jetty Rd",
    "sg:city":"Rosebud",
    "sg:classifiers":[
        {
            "category":"Health Services",
            "subcategory":"Doctor",
            "type":"Services"
        }
    ],
    "sg:phone":"+61 3 5982 1092",
    "sg:postcode":"3939",
    "sg:province":"VIC",
    "sg:tags":[
        "medical",
        "practitioner"
    ],
    "wof:name":"DR VINITHRA KUMAR",
    "wof:placetype":"venue"
},
  "geometry": {"coordinates":[144.90928649899999,-38.3589706421],"type":"Point"}
}