{
  "type": "Feature",
  "properties": {
    "addr:full":"39a Semaphore Rd Semaphore SA 5019",
    "addr:housenumber":"39a",
    "addr:postcode":"5019",
    "addr:street":"Semaphore Rd",
    "iso:country":"AU",
    "sg:address":"39a Semaphore Rd",
    "sg:city":"Semaphore",
    "sg:classifiers":[
        {
            "category":"Cafe",
            "type":"Food & Drink"
        }
    ],
    "sg:phone":"+61 8 8449 1949",
    "sg:postcode":"5019",
    "sg:province":"SA",
    "wof:name":"Erika's Cafe",
    "wof:placetype":"venue"
},
  "geometry": {"coordinates":[138.483032227,-34.8384437561],"type":"Point"}
}