{
  "type": "Feature",
  "properties": {
    "addr:full":"156 Vincent St North Perth WA 6006",
    "addr:housenumber":"156",
    "addr:postcode":"6006",
    "addr:street":"Vincent St",
    "iso:country":"AU",
    "sg:address":"156 Vincent St",
    "sg:city":"North Perth",
    "sg:classifiers":[
        {
            "category":"Building & Trades",
            "subcategory":"Construction",
            "type":"Services"
        }
    ],
    "sg:phone":"+61 8 9328 7371",
    "sg:postcode":"6006",
    "sg:province":"WA",
    "sg:tags":[
        "contractor"
    ],
    "wof:name":"Metrocon Pty Ltd",
    "wof:placetype":"venue"
},
  "geometry": {"coordinates":[115.85846710200001,-31.9363250732],"type":"Point"}
}