{
  "type": "Feature",
  "properties": {
    "addr:full":"51 Station St Wentworthville NSW 2145",
    "addr:housenumber":"51",
    "addr:postcode":"2145",
    "addr:street":"Station St",
    "iso:country":"AU",
    "sg:address":"51 Station St",
    "sg:city":"Wentworthville",
    "sg:classifiers":[
        {
            "category":"Health Services",
            "subcategory":"Doctor",
            "type":"Services"
        }
    ],
    "sg:phone":"+61 2 9896 1133",
    "sg:postcode":"2145",
    "sg:province":"NSW",
    "sg:tags":[
        "podiatrist"
    ],
    "wof:name":"Begg Lindy",
    "wof:placetype":"venue"
},
  "geometry": {"coordinates":[150.971893311,-33.8081932068],"type":"Point"}
}