{
  "type": "Feature",
  "properties": {
    "addr:full":"325 Wagga Rd Lavington NSW 2641",
    "addr:housenumber":"325",
    "addr:postcode":"2641",
    "addr:street":"Wagga Rd",
    "iso:country":"AU",
    "sg:address":"325 Wagga Rd",
    "sg:city":"Lavington",
    "sg:classifiers":[
        {
            "category":"Shopping",
            "subcategory":"Pets & Pet Supplies",
            "type":"Retail Goods"
        }
    ],
    "sg:phone":"+61 2 6025 0021",
    "sg:postcode":"2641",
    "sg:province":"NSW",
    "sg:tags":[
        "food"
    ],
    "wof:name":"Renos Pet Food Deli",
    "wof:placetype":"venue"
},
  "geometry": {"coordinates":[146.963012695,-36.0376701355],"type":"Point"}
}