{
  "type": "Feature",
  "properties": {
    "addr:full":"level 1, Suite 6-7, 899 Whitehorse Rd Box Hill VIC 3128",
    "addr:housenumber":"899",
    "addr:postcode":"3128",
    "addr:street":"Whitehorse Rd",
    "iso:country":"AU",
    "sg:address":"level 1, Suite 6-7, 899 Whitehorse Rd",
    "sg:city":"Box Hill",
    "sg:classifiers":[
        {
            "category":"Banks & Credit Unions",
            "subcategory":"Financial Services",
            "type":"Services"
        }
    ],
    "sg:phone":"+61 3 9896 2222",
    "sg:postcode":"3128",
    "sg:province":"VIC",
    "sg:tags":[
        "loan",
        "finance",
        "mortgage"
    ],
    "wof:name":"Mortgage House Of Australia",
    "wof:placetype":"venue"
},
  "geometry": {"coordinates":[145.120803833,-37.8173980713],"type":"Point"}
}