{
  "type": "Feature",
  "properties": {
    "addr:full":"305 Sailors Bay Rd Northbridge NSW 2063",
    "addr:housenumber":"305",
    "addr:postcode":"2063",
    "addr:street":"Sailors Bay Rd",
    "iso:country":"AU",
    "sg:address":"305 Sailors Bay Rd",
    "sg:city":"Northbridge",
    "sg:classifiers":[
        {
            "category":"Shopping",
            "subcategory":"Stationery & Office Supplies",
            "type":"Retail Goods"
        }
    ],
    "sg:phone":"+61 2 9958 0688",
    "sg:postcode":"2063",
    "sg:province":"NSW",
    "sg:tags":[
        "equipment",
        "facsimile"
    ],
    "wof:name":"Facsimile Specialists",
    "wof:placetype":"venue"
},
  "geometry": {"coordinates":[151.218017578,-33.812046051],"type":"Point"}
}