{
  "type": "Feature",
  "properties": {
    "addr:full":"46 Hunter St Newcastle NSW 2300",
    "addr:housenumber":"46",
    "addr:postcode":"2300",
    "addr:street":"Hunter St",
    "iso:country":"AU",
    "sg:address":"46 Hunter St",
    "sg:city":"Newcastle",
    "sg:classifiers":[
        {
            "category":"Shopping",
            "subcategory":"Beauty & Cosmetics",
            "type":"Retail Goods"
        }
    ],
    "sg:phone":"+61 2 4927 1957",
    "sg:postcode":"2300",
    "sg:province":"NSW",
    "sg:tags":[
        "equipment",
        "salon",
        "supply"
    ],
    "wof:name":"Annod Face & Body Care",
    "wof:placetype":"venue"
},
  "geometry": {"coordinates":[151.78509500000001,-32.927868],"type":"Point"}
}