{
  "type": "Feature",
  "properties": {
    "addr:full":"111 Kew St Welshpool WA 6106",
    "addr:housenumber":"111",
    "addr:postcode":"6106",
    "addr:street":"Kew St",
    "iso:country":"AU",
    "sg:address":"111 Kew St",
    "sg:city":"Welshpool",
    "sg:classifiers":[
        {
            "category":"Manufacturing",
            "subcategory":"Aerospace",
            "type":"Manufacturing & Wholesale Goods"
        }
    ],
    "sg:phone":"+61 8 9361 8316",
    "sg:postcode":"6106",
    "sg:province":"WA",
    "sg:tags":[
        "equipment",
        "aircraft",
        "maintenance"
    ],
    "wof:name":"Universal Plastics",
    "wof:placetype":"venue"
},
  "geometry": {"coordinates":[115.93206024200001,-31.9846038818],"type":"Point"}
}