{
  "type": "Feature",
  "properties": {
    "addr:full":"Shop 25, Sowerby St Muswellbrook Market Place Muswellbrook NSW 2333",
    "addr:housenumber":"shop 25",
    "addr:postcode":"2333",
    "addr:street":"Sowerby St;Market Place",
    "iso:country":"AU",
    "sg:address":"Shop 25, Sowerby St",
    "sg:city":"Muswellbrook Market Place Muswellbrook",
    "sg:classifiers":[
        {
            "category":"Health Services",
            "subcategory":"Optometrist",
            "type":"Services"
        }
    ],
    "sg:phone":"+61 2 6541 3998",
    "sg:postcode":"2333",
    "sg:province":"NSW",
    "wof:name":"Hunter Optical Specialists",
    "wof:placetype":"venue"
},
  "geometry": {"coordinates":[150.89161682100001,-32.2624778748],"type":"Point"}
}