{
  "type": "Feature",
  "properties": {
    "addr:full":"Level 1, 265 Coronation Drv Milton QLD 4064",
    "addr:housenumber":"265",
    "addr:postcode":"4064",
    "addr:street":"Coronation Drv",
    "iso:country":"AU",
    "sg:address":"Level 1, 265 Coronation Drv",
    "sg:city":"Milton",
    "sg:classifiers":[
        {
            "category":"Professional",
            "subcategory":"Computer Services",
            "type":"Services"
        }
    ],
    "sg:phone":"+61 7 3369 4499",
    "sg:postcode":"4064",
    "sg:province":"QLD",
    "sg:tags":[
        "consultant",
        "system"
    ],
    "wof:name":"Ceanet",
    "wof:placetype":"venue"
},
  "geometry": {"coordinates":[153.00457763700001,-27.4734287262],"type":"Point"}
}