{
  "type": "Feature",
  "properties": {
    "iso:country":"AU",
    "sg:address":"1835 Ballarto Rd",
    "sg:city":"Clyde",
    "sg:classifiers":[
        {
            "category":"Industrial Area",
            "type":"Public Place"
        }
    ],
    "sg:phone":"+61 3 5998 9033",
    "sg:postcode":"3978",
    "sg:province":"VIC",
    "sg:tags":[
        "rural",
        "shed"
    ],
    "wof:name":"Equine Enterprises Pty Ltd",
    "wof:placetype":"venue"
},
  "geometry": {"coordinates":[145.36174011200001,-38.1380615234],"type":"Point"}
}