{
  "type": "Feature",
  "properties": {
    "addr:full":"44 Boyd St Geraldton WA 6530",
    "addr:housenumber":"44",
    "addr:postcode":"6530",
    "addr:street":"Boyd St",
    "iso:country":"AU",
    "sg:address":"44 Boyd St",
    "sg:city":"Geraldton",
    "sg:classifiers":[
        {
            "category":"Professional",
            "type":"Services"
        }
    ],
    "sg:phone":"+61 8 9964 8096",
    "sg:postcode":"6530",
    "sg:province":"WA",
    "sg:tags":[
        "transport"
    ],
    "wof:name":"D.E.A.L. Freight",
    "wof:placetype":"venue"
},
  "geometry": {"coordinates":[114.637390137,-28.7518253326],"type":"Point"}
}