{
  "type": "Feature",
  "properties": {
    "addr:full":"251 Marius St Tamworth NSW 2340",
    "addr:housenumber":"251",
    "addr:postcode":"2340",
    "addr:street":"Marius St",
    "iso:country":"AU",
    "sg:address":"251 Marius St",
    "sg:city":"Tamworth",
    "sg:classifiers":[
        {
            "category":"Train Station",
            "subcategory":"Light Rail",
            "type":"Transportation"
        }
    ],
    "sg:phone":"+61 2 6762 4513",
    "sg:postcode":"2340",
    "sg:province":"NSW",
    "sg:tags":[
        "equipment",
        "energy",
        "solar"
    ],
    "wof:name":"Battery World Tamworth",
    "wof:placetype":"venue"
},
  "geometry": {"coordinates":[150.93492126500001,-31.0930423737],"type":"Point"}
}