{
  "type": "Feature",
  "properties": {
    "iso:country":"AU",
    "sg:address":"92 Hotham St",
    "sg:city":"Traralgon",
    "sg:classifiers":[
        {
            "category":"Health Services",
            "subcategory":"Optometrist",
            "type":"Services"
        }
    ],
    "sg:phone":"+61 3 5174 1451",
    "sg:postcode":"3844",
    "sg:province":"VIC",
    "wof:name":"Margaret Squires Optometrist",
    "wof:placetype":"venue"
},
  "geometry": {"coordinates":[146.535552978,-38.1972961426],"type":"Point"}
}