{
  "type": "Feature",
  "properties": {
    "addr:full":"2 Keira St Kelmscott WA 6111",
    "addr:housenumber":"2",
    "addr:postcode":"6111",
    "addr:street":"Keira St",
    "iso:country":"AU",
    "sg:address":"2 Keira St",
    "sg:city":"Kelmscott",
    "sg:classifiers":[
        {
            "category":"Retail",
            "subcategory":"Auto Repair",
            "type":"Services"
        }
    ],
    "sg:phone":"+61 8 9497 1818",
    "sg:postcode":"6111",
    "sg:province":"WA",
    "sg:tags":[
        "beater",
        "painter",
        "panel"
    ],
    "wof:name":"AJ's Accident Repair Centre",
    "wof:placetype":"venue"
},
  "geometry": {"coordinates":[116.003631592,-32.1315498352],"type":"Point"}
}