{
  "type": "Feature",
  "properties": {
    "addr:full":"1423 Malvern Rd Malvern VIC 3144",
    "addr:housenumber":"1423",
    "addr:postcode":"3144",
    "addr:street":"Malvern Rd",
    "iso:country":"AU",
    "sg:address":"1423 Malvern Rd",
    "sg:city":"Malvern",
    "sg:classifiers":[
        {
            "category":"Personal",
            "subcategory":"Beauty Salon",
            "type":"Services"
        }
    ],
    "sg:phone":"+61 3 9822 8127",
    "sg:postcode":"3144",
    "sg:province":"VIC",
    "sg:tags":[
        "hairdresser"
    ],
    "wof:name":"Stevens Of London Hairdressing",
    "wof:placetype":"venue"
},
  "geometry": {"coordinates":[145.041549683,-37.8529853821],"type":"Point"}
}