{
  "type": "Feature",
  "properties": {
    "addr:full":"6/ 126 Wellington Pde East Melbourne VIC 3002",
    "addr:housenumber":"/ 126",
    "addr:postcode":"3002",
    "addr:street":"Wellington Pde",
    "iso:country":"AU",
    "sg:address":"6/ 126 Wellington Pde",
    "sg:city":"East Melbourne",
    "sg:classifiers":[
        {
            "category":"Travel",
            "subcategory":"Travel Agent",
            "type":"Entertainment"
        }
    ],
    "sg:phone":"+61 3 9281 1100",
    "sg:postcode":"3002",
    "sg:province":"VIC",
    "sg:tags":[
        "consultant"
    ],
    "wof:name":"Wings Abroad Australia Pty Ltd",
    "wof:placetype":"venue"
},
  "geometry": {"coordinates":[144.98558044399999,-37.8162307739],"type":"Point"}
}