{
  "type": "Feature",
  "properties": {
    "iso:country":"AU",
    "sg:address":"12 Marni St",
    "sg:city":"Dandenong South",
    "sg:classifiers":[
        {
            "category":"Wholesale",
            "subcategory":"Construction Materials",
            "type":"Manufacturing & Wholesale Goods"
        }
    ],
    "sg:phone":"+61 3 9706 4780",
    "sg:postcode":"3175",
    "sg:province":"VIC",
    "sg:tags":[
        "wholesaler",
        "equipment",
        "bathroom",
        "mfrs",
        "accessory"
    ],
    "wof:name":"Trim Seal",
    "wof:placetype":"venue"
},
  "geometry": {"coordinates":[145.20298767099999,-38.0287132263],"type":"Point"}
}