{
  "type": "Feature",
  "properties": {
    "addr:full":"11 Sturt Rd Brighton SA 5048",
    "addr:housenumber":"11",
    "addr:postcode":"5048",
    "addr:street":"Sturt Rd",
    "iso:country":"AU",
    "sg:address":"11 Sturt Rd",
    "sg:city":"Brighton",
    "sg:classifiers":[
        {
            "category":"Real Estate",
            "subcategory":"Real Estate Agent",
            "type":"Services"
        }
    ],
    "sg:phone":"+61 8 8296 2055",
    "sg:postcode":"5048",
    "sg:province":"SA",
    "wof:name":"Raine & Horne",
    "wof:placetype":"venue"
},
  "geometry": {"coordinates":[138.52479600000001,-35.019253],"type":"Point"}
}