{
  "type": "Feature",
  "properties": {
    "addr:full":"1 John St Hunters Hill NSW 2110",
    "addr:housenumber":"1",
    "addr:postcode":"2110",
    "addr:street":"John St",
    "iso:country":"AU",
    "sg:address":"1 John St",
    "sg:city":"Hunters Hill",
    "sg:classifiers":[
        {
            "category":"Building & Trades",
            "subcategory":"Construction",
            "type":"Services"
        }
    ],
    "sg:phone":"+61 2 9816 1692",
    "sg:postcode":"2110",
    "sg:province":"NSW",
    "sg:tags":[
        "contractor"
    ],
    "wof:name":"Oxley Constructions Pty Ltd",
    "wof:placetype":"venue"
},
  "geometry": {"coordinates":[151.13735961899999,-33.8312072754],"type":"Point"}
}