{
  "type": "Feature",
  "properties": {
    "addr:full":"7 Barolin St Bundaberg QLD 4670",
    "addr:housenumber":"7",
    "addr:postcode":"4670",
    "addr:street":"Barolin St",
    "iso:country":"AU",
    "sg:address":"7 Barolin St",
    "sg:city":"Bundaberg",
    "sg:classifiers":[
        {
            "category":"Health Services",
            "subcategory":"Optometrist",
            "type":"Services"
        }
    ],
    "sg:phone":"+61 7 4151 2767",
    "sg:postcode":"4670",
    "sg:province":"QLD",
    "wof:name":"Blackwell Geoff",
    "wof:placetype":"venue"
},
  "geometry": {"coordinates":[152.348876953,-24.8668022156],"type":"Point"}
}