{
  "type": "Feature",
  "properties": {
    "iso:country":"AU",
    "sg:address":"61 Maitland Rd",
    "sg:city":"Maitland",
    "sg:classifiers":[
        {
            "category":"Autos & Motor Vehicles",
            "subcategory":"Auto Supplies",
            "type":"Retail Goods"
        }
    ],
    "sg:phone":"+61 2 4968 3650",
    "sg:postcode":"2320",
    "sg:province":"NSW",
    "sg:tags":[
        "tyre"
    ],
    "wof:name":"Yokohama High Performance Tyres",
    "wof:placetype":"venue"
},
  "geometry": {"coordinates":[151.569015503,-32.7129592896],"type":"Point"}
}