{
  "type": "Feature",
  "properties": {
    "iso:country":"AU",
    "sg:address":"62 West St",
    "sg:city":"Balgowlah",
    "sg:classifiers":[
        {
            "category":"Health Services",
            "subcategory":"Doctor",
            "type":"Services"
        }
    ],
    "sg:phone":"+61 2 9948 3784",
    "sg:postcode":"2093",
    "sg:province":"NSW",
    "sg:tags":[
        "medical",
        "practitioner"
    ],
    "wof:name":"White W G",
    "wof:placetype":"venue"
},
  "geometry": {"coordinates":[151.26072692899999,-33.7936134338],"type":"Point"}
}