{
  "type": "Feature",
  "properties": {
    "addr:full":"Cnr Kenthurst Rd & Maple St Dural NSW 2158",
    "addr:postcode":"2158",
    "addr:street":"Cnr Kenthurst Rd & Maple St",
    "iso:country":"AU",
    "sg:address":"Cnr Kenthurst Rd & Maple St",
    "sg:city":"Dural",
    "sg:classifiers":[
        {
            "category":"Health Services",
            "subcategory":"Dentist",
            "type":"Services"
        }
    ],
    "sg:phone":"+61 2 9651 4488",
    "sg:postcode":"2158",
    "sg:province":"NSW",
    "wof:name":"Integrity Dental - Kobler Laurie Dr",
    "wof:placetype":"venue"
},
  "geometry": {"coordinates":[151.018875122,-33.6912879944],"type":"Point"}
}