{
  "type": "Feature",
  "properties": {
    "addr:full":"Shop 41 -51 Kooringal Mall Kooringal NSW 2650",
    "addr:housenumber":"shop 41 -51",
    "addr:postcode":"2650",
    "addr:street":"Mall",
    "iso:country":"AU",
    "sg:address":"Shop 41",
    "sg:city":"-51 Kooringal Mall Kooringal",
    "sg:classifiers":[
        {
            "category":"Food & Beverages",
            "subcategory":"Supermarket",
            "type":"Retail Goods"
        }
    ],
    "sg:phone":"+61 2 6922 6601",
    "sg:postcode":"2650",
    "sg:province":"NSW",
    "sg:tags":[
        "grocery",
        "store"
    ],
    "wof:name":"Woolworths Ltd",
    "wof:placetype":"venue"
},
  "geometry": {"coordinates":[147.387619019,-35.1425437927],"type":"Point"}
}