{
  "type": "Feature",
  "properties": {
    "addr:full":"13 Barrinia St Slacks Creek QLD 4127",
    "addr:housenumber":"13",
    "addr:postcode":"4127",
    "addr:street":"Barrinia St",
    "iso:country":"AU",
    "sg:address":"13 Barrinia St",
    "sg:city":"Slacks Creek",
    "sg:classifiers":[
        {
            "category":"Manufacturing",
            "subcategory":"Rubber & Plastics",
            "type":"Manufacturing & Wholesale Goods"
        }
    ],
    "sg:phone":"+61 7 3290 3511",
    "sg:postcode":"4127",
    "sg:province":"QLD",
    "sg:tags":[
        "fabricator"
    ],
    "wof:name":"Sterling Products",
    "wof:placetype":"venue"
},
  "geometry": {"coordinates":[153.12600707999999,-27.6238002777],"type":"Point"}
}