{
  "type": "Feature",
  "properties": {
    "iso:country":"AU",
    "sg:address":"547 Great Eastern Hwy",
    "sg:city":"Redcliffe",
    "sg:classifiers":[
        {
            "category":"Wholesale",
            "subcategory":"Machinery & Supplies",
            "type":"Manufacturing & Wholesale Goods"
        }
    ],
    "sg:phone":"+61 8 9475 1600",
    "sg:postcode":"6104",
    "sg:province":"WA",
    "sg:tags":[
        "agricultural"
    ],
    "wof:name":"McIntosh & Son",
    "wof:placetype":"venue"
},
  "geometry": {"coordinates":[115.95198822,-31.9257850647],"type":"Point"}
}