{
  "type": "Feature",
  "properties": {
    "addr:full":"First Floor Unit 6/ 6- 8 Byfield St North Ryde NSW 2113",
    "addr:housenumber":"6 / 6 8",
    "addr:postcode":"2113",
    "addr:street":"First;Byfield St",
    "iso:country":"AU",
    "sg:address":"First Floor Unit 6/ 6- 8 Byfield St",
    "sg:city":"North Ryde",
    "sg:classifiers":[
        {
            "category":"Wholesale",
            "subcategory":"Medical Equipment & Supplies",
            "type":"Manufacturing & Wholesale Goods"
        }
    ],
    "sg:phone":"+61 1800 802 457",
    "sg:postcode":"2113",
    "sg:province":"NSW",
    "sg:tags":[
        "dental"
    ],
    "wof:name":"Biomet 3I Australia Pty Ltd",
    "wof:placetype":"venue"
},
  "geometry": {"coordinates":[151.12051391599999,-33.7807006836],"type":"Point"}
}