{
  "type": "Feature",
  "properties": {
    "iso:country":"AU",
    "sg:address":"31 Stanley St",
    "sg:city":"Wodonga",
    "sg:classifiers":[
        {
            "category":"Health Services",
            "subcategory":"Doctor",
            "type":"Services"
        }
    ],
    "sg:phone":"+61 2 6024 2155",
    "sg:postcode":"3690",
    "sg:province":"VIC",
    "sg:tags":[
        "medical",
        "practitioner"
    ],
    "wof:name":"Johanson Michael",
    "wof:placetype":"venue"
},
  "geometry": {"coordinates":[146.88412475600001,-36.1220588684],"type":"Point"}
}