{
  "type": "Feature",
  "properties": {
    "iso:country":"AU",
    "sg:address":"1146 Dandenong Rd",
    "sg:city":"Carnegie",
    "sg:classifiers":[
        {
            "category":"Health Services",
            "subcategory":"Health Practitioner",
            "type":"Services"
        }
    ],
    "sg:phone":"+61 3 9568 3122",
    "sg:postcode":"3163",
    "sg:province":"VIC",
    "sg:tags":[
        "psychologist"
    ],
    "wof:name":"Buscombe Laraine",
    "wof:placetype":"venue"
},
  "geometry": {"coordinates":[145.06367492699999,-37.8850212097],"type":"Point"}
}