{
  "type": "Feature",
  "properties": {
    "addr:full":"508a George St Windsor South NSW 2756",
    "addr:housenumber":"508a",
    "addr:postcode":"2756",
    "addr:street":"George St",
    "iso:country":"AU",
    "sg:address":"508a George St",
    "sg:city":"Windsor South",
    "sg:classifiers":[
        {
            "category":"Health Services",
            "subcategory":"Doctor",
            "type":"Services"
        }
    ],
    "sg:phone":"+61 2 4587 7133",
    "sg:postcode":"2756",
    "sg:province":"NSW",
    "sg:tags":[
        "medical",
        "practitioner"
    ],
    "wof:name":"Morris Nagwa Dr",
    "wof:placetype":"venue"
},
  "geometry": {"coordinates":[150.8072052,-33.6179351807],"type":"Point"}
}