{
  "type": "Feature",
  "properties": {
    "addr:full":"Kiosk 59, Epping Plaza, Cnr High & Cooper St Epping VIC 3076",
    "addr:postcode":"3076",
    "addr:street":"Epping;Cnr High;St",
    "iso:country":"AU",
    "sg:address":"Kiosk 59, Epping Plaza, Cnr High & Cooper St",
    "sg:city":"Epping",
    "sg:classifiers":[
        {
            "category":"Shopping",
            "subcategory":"Mobile Phones",
            "type":"Retail Goods"
        }
    ],
    "sg:phone":"+61 13 19 30",
    "sg:postcode":"3076",
    "sg:province":"VIC",
    "sg:tags":[
        "telephone",
        "accessory"
    ],
    "wof:name":"TeleChoice",
    "wof:placetype":"venue"
},
  "geometry": {"coordinates":[145.009490967,-37.6383590698],"type":"Point"}
}