{
  "type": "Feature",
  "properties": {
    "addr:full":"20- 22 Strong St Warrnambool VIC 3280",
    "addr:housenumber":"22",
    "addr:postcode":"3280",
    "addr:street":"Strong St",
    "iso:country":"AU",
    "sg:address":"20- 22 Strong St",
    "sg:city":"Warrnambool",
    "sg:classifiers":[
        {
            "category":"Farming",
            "subcategory":"Fish & Marine Products",
            "type":"Manufacturing & Wholesale Goods"
        }
    ],
    "sg:phone":"+61 3 5561 1766",
    "sg:postcode":"3280",
    "sg:province":"VIC",
    "sg:tags":[
        "asphalt",
        "supply"
    ],
    "wof:name":"Netherway Asphalting Pty Ltd",
    "wof:placetype":"venue"
},
  "geometry": {"coordinates":[142.45913696299999,-38.3760757446],"type":"Point"}
}