{
  "type": "Feature",
  "properties": {
    "addr:full":"114 Grey St East Melbourne VIC 3002",
    "addr:housenumber":"114",
    "addr:postcode":"3002",
    "addr:street":"Grey St",
    "iso:country":"AU",
    "sg:address":"114 Grey St",
    "sg:city":"East Melbourne",
    "sg:classifiers":[
        {
            "category":"Professional",
            "subcategory":"Business Services",
            "type":"Services"
        }
    ],
    "sg:phone":"+61 3 9415 9811",
    "sg:postcode":"3002",
    "sg:province":"VIC",
    "sg:tags":[
        "consultant",
        "system"
    ],
    "wof:name":"Keep It Simple Systems",
    "wof:placetype":"venue"
},
  "geometry": {"coordinates":[144.984619141,-37.811580658],"type":"Point"}
}