{
  "type": "Feature",
  "properties": {
    "addr:full":"PO Box 320 Belmore NSW 2192",
    "addr:postcode":"2192",
    "iso:country":"AU",
    "sg:address":"PO Box 320",
    "sg:city":"Belmore",
    "sg:classifiers":[
        {
            "category":"Utilities",
            "subcategory":"Natural Gas",
            "type":"Services"
        }
    ],
    "sg:phone":"+61 412 280 235",
    "sg:postcode":"2192",
    "sg:province":"NSW",
    "sg:tags":[
        "supplier"
    ],
    "wof:name":"Alpha Gas Delivery & Heating",
    "wof:placetype":"venue"
},
  "geometry": {"coordinates":[151.08824200000001,-33.91946],"type":"Point"}
}