{
  "type": "Feature",
  "properties": {
    "addr:full":"762 Duncan Rd Dunoon NSW 2480",
    "addr:housenumber":"762",
    "addr:postcode":"2480",
    "addr:street":"Duncan Rd",
    "iso:country":"AU",
    "sg:address":"762 Duncan Rd",
    "sg:city":"Dunoon",
    "sg:classifiers":[
        {
            "category":"Building & Trades",
            "subcategory":"Construction",
            "type":"Services"
        }
    ],
    "sg:phone":"+61 2 6689 5180",
    "sg:postcode":"2480",
    "sg:province":"NSW",
    "sg:tags":[
        "contractor"
    ],
    "wof:name":"Henderson J S Pty Ltd",
    "wof:placetype":"venue"
},
  "geometry": {"coordinates":[153.31309509299999,-28.6914997101],"type":"Point"}
}