{
  "type": "Feature",
  "properties": {
    "iso:country":"AU",
    "sg:address":"Edison St",
    "sg:city":"Belmore",
    "sg:classifiers":[
        {
            "category":"Utilities",
            "subcategory":"Refuse",
            "type":"Services"
        }
    ],
    "sg:phone":"+61 2 9718 1002",
    "sg:postcode":"2192",
    "sg:province":"NSW",
    "sg:tags":[
        "remover",
        "rubbish"
    ],
    "wof:name":"Genuine Rubbish Removal",
    "wof:placetype":"venue"
},
  "geometry": {"coordinates":[151.094086,-33.918289],"type":"Point"}
}