{
  "type": "Feature",
  "properties": {
    "addr:full":"184 adderley St Auburn NSW 2144",
    "addr:housenumber":"184",
    "addr:postcode":"2144",
    "addr:street":"Adderley St",
    "iso:country":"AU",
    "sg:address":"184 adderley St",
    "sg:city":"Auburn",
    "sg:classifiers":[
        {
            "category":"Military Area",
            "subcategory":"Air Force Base",
            "type":"Public Place"
        }
    ],
    "sg:phone":"+61 2 8799 2400",
    "sg:postcode":"2144",
    "sg:province":"NSW",
    "sg:tags":[
        "equipment",
        "climbing",
        "venue",
        "rock"
    ],
    "wof:name":"Paddy Pallin",
    "wof:placetype":"venue"
},
  "geometry": {"coordinates":[151.03103637699999,-33.8368263245],"type":"Point"}
}