{
  "type": "Feature",
  "properties": {
    "iso:country":"AU",
    "sg:address":"Shop 23 Bullcreek Shopping Centre",
    "sg:city":"Bullcreek",
    "sg:classifiers":[
        {
            "category":"Shopping",
            "subcategory":"Clothing, Apparel, & Fashions",
            "type":"Retail Goods"
        }
    ],
    "sg:phone":"+61 8 9332 8832",
    "sg:postcode":"6149",
    "sg:province":"WA",
    "sg:tags":[
        "lady",
        "wear"
    ],
    "wof:name":"Suzanne Grae",
    "wof:placetype":"venue"
},
  "geometry": {"coordinates":[115.87059,-32.066471],"type":"Point"}
}