{
  "type": "Feature",
  "properties": {
    "iso:country":"AU",
    "sg:address":"28 Heather St",
    "sg:city":"Heatherbrae",
    "sg:classifiers":[
        {
            "category":"Professional",
            "subcategory":"Business Services",
            "type":"Services"
        }
    ],
    "sg:phone":"+61 2 4983 1400",
    "sg:postcode":"2324",
    "sg:province":"NSW",
    "sg:tags":[
        "record",
        "management",
        "storage"
    ],
    "wof:name":"Pack-Safe",
    "wof:placetype":"venue"
},
  "geometry": {"coordinates":[151.73358154300001,-32.7859764099],"type":"Point"}
}