{
  "type": "Feature",
  "properties": {
    "iso:country":"AU",
    "sg:address":"Shop 59 Village Lane, Lake St",
    "sg:city":"Cairns",
    "sg:classifiers":[
        {
            "category":"Personal",
            "subcategory":"Beauty Salon",
            "type":"Services"
        }
    ],
    "sg:phone":"+61 7 4051 1743",
    "sg:postcode":"4870",
    "sg:province":"QLD",
    "sg:tags":[
        "hairdresser"
    ],
    "wof:name":"Zhivagos Hair & Beauty",
    "wof:placetype":"venue"
},
  "geometry": {"coordinates":[145.779205322,-16.9260311127],"type":"Point"}
}