{
  "type": "Feature",
  "properties": {
    "iso:country":"AU",
    "sg:address":"Shop 4 & 5, Niecon Tower 19 Victoria Ave",
    "sg:city":"Broadbeach",
    "sg:classifiers":[
        {
            "category":"Personal",
            "subcategory":"Massage",
            "type":"Services"
        }
    ],
    "sg:phone":"+61 7 5526 7272",
    "sg:postcode":"4218",
    "sg:province":"QLD",
    "sg:tags":[
        "therapy"
    ],
    "wof:name":"Body Sanctuary",
    "wof:placetype":"venue"
},
  "geometry": {"coordinates":[153.43316650400001,-28.0287647247],"type":"Point"}
}