{
  "type": "Feature",
  "properties": {
    "iso:country":"AU",
    "sg:address":"5 Lode Crt",
    "sg:city":"Aberfoyle Park",
    "sg:classifiers":[
        {
            "category":"Building & Trades",
            "subcategory":"Construction",
            "type":"Services"
        }
    ],
    "sg:phone":"+61 8 8381 5494",
    "sg:postcode":"5159",
    "sg:province":"SA",
    "sg:tags":[
        "contractor"
    ],
    "wof:name":"A.W. Mountford-Jones Builders",
    "wof:placetype":"venue"
},
  "geometry": {"coordinates":[138.60585022000001,-35.0626144409],"type":"Point"}
}