{
  "type": "Feature",
  "properties": {
    "addr:full":"60 Thurlow St Riverwood NSW 2210",
    "addr:housenumber":"60",
    "addr:postcode":"2210",
    "addr:street":"Thurlow St",
    "iso:country":"AU",
    "sg:address":"60 Thurlow St",
    "sg:city":"Riverwood",
    "sg:classifiers":[
        {
            "category":"Personal",
            "subcategory":"Shoe Repair & Shine",
            "type":"Services"
        }
    ],
    "sg:phone":"+61 2 9533 3179",
    "sg:postcode":"2210",
    "sg:province":"NSW",
    "sg:tags":[
        "footwear"
    ],
    "wof:name":"Riverwood Shoes, Bags & Shoe Repairs",
    "wof:placetype":"venue"
},
  "geometry": {"coordinates":[151.05427599999999,-33.951351],"type":"Point"}
}