{
  "type": "Feature",
  "properties": {
    "iso:country":"AU",
    "sg:address":"60 Thurlow St",
    "sg:city":"Riverwood",
    "sg:classifiers":[
        {
            "category":"Personal",
            "subcategory":"Shoe Repair & Shine",
            "type":"Services"
        }
    ],
    "sg:phone":"+61 2 9533 3179",
    "sg:postcode":"2210",
    "sg:province":"NSW",
    "sg:tags":[
        "footwear"
    ],
    "wof:name":"Riverwood Shoes, Bags & Shoe Repairs",
    "wof:placetype":"venue"
},
  "geometry": {"coordinates":[151.054276,-33.951351],"type":"Point"}
}