{
  "type": "Feature",
  "properties": {
    "iso:country":"AU",
    "sg:address":"Guineas Creek Rd",
    "sg:city":"Tallebudgera",
    "sg:classifiers":[
        {
            "category":"Home & Garden",
            "subcategory":"Carpets & Floor Coverings",
            "type":"Retail Goods"
        }
    ],
    "sg:phone":"+61 7 5533 9173",
    "sg:postcode":"4228",
    "sg:province":"QLD",
    "sg:tags":[
        "layer",
        "planner"
    ],
    "wof:name":"Davis M",
    "wof:placetype":"venue"
},
  "geometry": {"coordinates":[153.43301391599999,-28.1368923187],"type":"Point"}
}