{
  "type": "Feature",
  "properties": {
    "iso:country":"AU",
    "sg:address":"Shop 20 Padbury Shopping Centre 75 Warburton Avenue",
    "sg:city":"Padbury",
    "sg:classifiers":[
        {
            "category":"Restaurant",
            "type":"Food & Drink"
        }
    ],
    "sg:phone":"+61 8 9401 7644",
    "sg:postcode":"6025",
    "sg:province":"WA",
    "sg:tags":[
        "pizza"
    ],
    "wof:name":"Domino's Pizza",
    "wof:placetype":"venue"
},
  "geometry": {"coordinates":[115.76673889200001,-31.8114490509],"type":"Point"}
}