{
  "type": "Feature",
  "properties": {
    "addr:full":"307 Pacific Hwy Heatherbrae NSW 2324",
    "addr:housenumber":"307",
    "addr:postcode":"2324",
    "addr:street":"Pacific Hwy",
    "iso:country":"AU",
    "sg:address":"307 Pacific Hwy",
    "sg:city":"Heatherbrae",
    "sg:classifiers":[
        {
            "category":"Retail",
            "subcategory":"Auto Repair",
            "type":"Services"
        }
    ],
    "sg:phone":"+61 2 4987 6999",
    "sg:postcode":"2324",
    "sg:province":"NSW",
    "sg:tags":[
        "camper-trailers",
        "caravan",
        "servicing"
    ],
    "wof:name":"Ricks Caravan Centre",
    "wof:placetype":"venue"
},
  "geometry": {"coordinates":[151.73231506400001,-32.785736084],"type":"Point"}
}