{
  "type": "Feature",
  "properties": {
    "addr:full":"13 Regent St Melrose Park SA 5039",
    "addr:housenumber":"13",
    "addr:postcode":"5039",
    "addr:street":"Regent St",
    "iso:country":"AU",
    "sg:address":"13 Regent St",
    "sg:city":"Melrose Park",
    "sg:classifiers":[
        {
            "category":"Professional",
            "subcategory":"Engineering",
            "type":"Services"
        }
    ],
    "sg:phone":"+61 8 8374 2033",
    "sg:postcode":"5039",
    "sg:province":"SA",
    "sg:tags":[
        "engineer"
    ],
    "wof:name":"Short S J & Co",
    "wof:placetype":"venue"
},
  "geometry": {"coordinates":[138.57530212399999,-34.9819908142],"type":"Point"}
}