{
  "type": "Feature",
  "properties": {
    "addr:full":"566 The Entrance Rd Bateau Bay NSW 2261",
    "addr:housenumber":"566",
    "addr:postcode":"2261",
    "addr:street":"The Entrance Rd",
    "iso:country":"AU",
    "sg:address":"566 The Entrance Rd",
    "sg:city":"Bateau Bay",
    "sg:classifiers":[
        {
            "category":"Food & Beverages",
            "subcategory":"Liquor & Beverages",
            "type":"Retail Goods"
        }
    ],
    "sg:phone":"+61 2 4332 8033",
    "sg:postcode":"2261",
    "sg:province":"NSW",
    "sg:tags":[
        "store"
    ],
    "wof:name":"Bateau Bay Cellars",
    "wof:placetype":"venue"
},
  "geometry": {"coordinates":[151.47331199999999,-33.389023],"type":"Point"}
}