{
  "type": "Feature",
  "properties": {
    "addr:full":"57 Rainbow Crs Dunwich QLD 4183",
    "addr:housenumber":"57",
    "addr:postcode":"4183",
    "addr:street":"Rainbow Crs",
    "iso:country":"AU",
    "sg:address":"57 Rainbow Crs",
    "sg:city":"Dunwich",
    "sg:classifiers":[
        {
            "category":"Taxi",
            "type":"Transportation"
        }
    ],
    "sg:phone":"+61 408 193 685",
    "sg:postcode":"4183",
    "sg:province":"QLD",
    "sg:tags":[
        "cab"
    ],
    "wof:name":"Stradbroke Cab Service",
    "wof:placetype":"venue"
},
  "geometry": {"coordinates":[153.40899658199999,-27.4981594086],"type":"Point"}
}