{
  "type": "Feature",
  "properties": {
    "iso:country":"AU",
    "sg:address":"36 Tulloch St",
    "sg:city":"Blacktown",
    "sg:classifiers":[
        {
            "category":"Social Services",
            "subcategory":"Child Care",
            "type":"Services"
        }
    ],
    "sg:phone":"+61 2 8814 9437",
    "sg:postcode":"2148",
    "sg:province":"NSW",
    "wof:name":"Rainbow Paradise Pre-School",
    "wof:placetype":"venue"
},
  "geometry": {"coordinates":[150.88783264200001,-33.7558670044],"type":"Point"}
}