{
  "type": "Feature",
  "properties": {
    "addr:full":"Cotswold Pl Wishart QLD 4122",
    "addr:postcode":"4122",
    "addr:street":"Pl",
    "iso:country":"AU",
    "sg:address":"Cotswold Pl",
    "sg:city":"Wishart",
    "sg:classifiers":[
        {
            "category":"Building & Trades",
            "subcategory":"Construction",
            "type":"Services"
        }
    ],
    "sg:phone":"+61 7 3216 8143",
    "sg:postcode":"4122",
    "sg:province":"QLD",
    "sg:tags":[
        "contractor"
    ],
    "wof:name":"Ownit Homes Pty Ltd",
    "wof:placetype":"venue"
},
  "geometry": {"coordinates":[153.10104370100001,-27.5491046906],"type":"Point"}
}