{
  "type": "Feature",
  "properties": {
    "iso:country":"AU",
    "sg:address":"Unit 4 130 Oats St",
    "sg:city":"Carlisle",
    "sg:classifiers":[
        {
            "category":"Retail",
            "subcategory":"Auto Repair",
            "type":"Services"
        }
    ],
    "sg:phone":"+61 8 9355 4044",
    "sg:postcode":"6101",
    "sg:province":"WA",
    "sg:tags":[
        "repairer",
        "motor",
        "engineer"
    ],
    "wof:name":"Singh Auto Sales & Repairs",
    "wof:placetype":"venue"
},
  "geometry": {"coordinates":[115.92424774200001,-31.9808712006],"type":"Point"}
}