{
  "type": "Feature",
  "properties": {
    "addr:full":"4 Charles St Forestville SA 5035",
    "addr:housenumber":"4",
    "addr:postcode":"5035",
    "addr:street":"Charles St",
    "iso:country":"AU",
    "sg:address":"4 Charles St",
    "sg:city":"Forestville",
    "sg:classifiers":[
        {
            "category":"Professional",
            "subcategory":"Art Services",
            "type":"Services"
        }
    ],
    "sg:phone":"+61 412 836 323",
    "sg:postcode":"5035",
    "sg:province":"SA",
    "sg:tags":[
        "decorator",
        "painter"
    ],
    "wof:name":"C.J. Capurso Home-Property Maintenance",
    "wof:placetype":"venue"
},
  "geometry": {"coordinates":[138.58190918,-34.9493255615],"type":"Point"}
}