{
  "type": "Feature",
  "properties": {
    "addr:full":"51 Walker St North Sydney NSW 2060",
    "addr:housenumber":"51",
    "addr:postcode":"2060",
    "addr:street":"Walker St",
    "iso:country":"AU",
    "sg:address":"51 Walker St",
    "sg:city":"North Sydney",
    "sg:classifiers":[
        {
            "category":"Professional",
            "subcategory":"Accounting & Tax Preparation",
            "type":"Services"
        }
    ],
    "sg:phone":"+61 2 9955 4949",
    "sg:postcode":"2060",
    "sg:province":"NSW",
    "sg:tags":[
        "consultant",
        "taxation"
    ],
    "wof:name":"H&R Block",
    "wof:placetype":"venue"
},
  "geometry": {"coordinates":[151.207717895,-33.8398590088],"type":"Point"}
}