{
  "type": "Feature",
  "properties": {
    "addr:full":"Bldg 2, 243 Bradman St Acacia Ridge QLD 4110",
    "addr:housenumber":"243",
    "addr:postcode":"4110",
    "addr:street":"Bradman St",
    "iso:country":"AU",
    "sg:address":"Bldg 2, 243 Bradman St",
    "sg:city":"Acacia Ridge",
    "sg:classifiers":[
        {
            "category":"Farming",
            "subcategory":"Crops",
            "type":"Manufacturing & Wholesale Goods"
        }
    ],
    "sg:phone":"+61 7 3273 7433",
    "sg:postcode":"4110",
    "sg:province":"QLD",
    "sg:tags":[
        "warehousing"
    ],
    "wof:name":"RMSDAS Distribution Services Pty Ltd",
    "wof:placetype":"venue"
},
  "geometry": {"coordinates":[153.03749084500001,-27.5880050659],"type":"Point"}
}