{
  "type": "Feature",
  "properties": {
    "iso:country":"AU",
    "sg:address":"67 Edward St",
    "sg:city":"Norwood",
    "sg:classifiers":[
        {
            "category":"Health Services",
            "subcategory":"Doctor",
            "type":"Services"
        }
    ],
    "sg:phone":"+61 8 8332 0055",
    "sg:postcode":"5067",
    "sg:province":"SA",
    "sg:tags":[
        "medical",
        "practitioner"
    ],
    "wof:name":"Mencel, Julie",
    "wof:placetype":"venue"
},
  "geometry": {"coordinates":[138.63435363799999,-34.9221458435],"type":"Point"}
}