{
  "type": "Feature",
  "properties": {
    "addr:full":"26 Albion St Waverley NSW 2024",
    "addr:housenumber":"26",
    "addr:postcode":"2024",
    "addr:street":"Albion St",
    "iso:country":"AU",
    "sg:address":"26 Albion St",
    "sg:city":"Waverley",
    "sg:classifiers":[
        {
            "category":"Education",
            "subcategory":"School",
            "type":"Public Place"
        }
    ],
    "sg:phone":"+61 2 8305 6200",
    "sg:postcode":"2024",
    "sg:province":"NSW",
    "sg:tags":[
        "girl"
    ],
    "wof:name":"St Catherine's School Waverley",
    "wof:placetype":"venue"
},
  "geometry": {"coordinates":[151.25468444800001,-33.9041175842],"type":"Point"}
}