{
  "type": "Feature",
  "properties": {
    "addr:full":"169 Burwood Rd Hawthorn VIC 3122",
    "addr:housenumber":"169",
    "addr:postcode":"3122",
    "addr:street":"Burwood Rd",
    "iso:country":"AU",
    "sg:address":"169 Burwood Rd",
    "sg:city":"Hawthorn",
    "sg:classifiers":[
        {
            "category":"Building & Trades",
            "subcategory":"Cleaning & Sanitation",
            "type":"Services"
        }
    ],
    "sg:phone":"+61 3 9819 0284",
    "sg:postcode":"3122",
    "sg:province":"VIC",
    "sg:tags":[
        "asbestos",
        "treatment",
        "removal"
    ],
    "wof:name":"Enterra Pty Limited",
    "wof:placetype":"venue"
},
  "geometry": {"coordinates":[145.02865600600001,-37.8216781616],"type":"Point"}
}