{
  "type": "Feature",
  "properties": {
    "iso:country":"AU",
    "sg:address":"7 Hensley Rd",
    "sg:city":"Lalor",
    "sg:classifiers":[
        {
            "category":"Shopping",
            "subcategory":"Gifts & Souvenirs",
            "type":"Retail Goods"
        }
    ],
    "sg:phone":"+61 3 9465 0305",
    "sg:postcode":"3075",
    "sg:province":"VIC",
    "sg:tags":[
        "shop",
        "supply"
    ],
    "wof:name":"Mary T. Designs Pty Ltd",
    "wof:placetype":"venue"
},
  "geometry": {"coordinates":[145.00997924800001,-37.6638641357],"type":"Point"}
}