{
  "type": "Feature",
  "properties": {
    "addr:full":"Suite A, Lvl 2, 68- 70 Dorcas St South Melbourne VIC 3205",
    "addr:housenumber":"68 70",
    "addr:postcode":"3205",
    "addr:street":"Dorcas St",
    "iso:country":"AU",
    "sg:address":"Suite A, Lvl 2, 68- 70 Dorcas St",
    "sg:city":"South Melbourne",
    "sg:classifiers":[
        {
            "category":"Professional",
            "subcategory":"Accounting & Tax Preparation",
            "type":"Services"
        }
    ],
    "sg:phone":"+61 3 9686 6911",
    "sg:postcode":"3205",
    "sg:province":"VIC",
    "sg:tags":[
        "accountant",
        "auditor"
    ],
    "wof:name":"Thorburn Partners Pty Ltd",
    "wof:placetype":"venue"
},
  "geometry": {"coordinates":[144.96752900000001,-37.830868],"type":"Point"}
}