{
  "type": "Feature",
  "properties": {
    "iso:country":"AU",
    "sg:address":"PO Box 10",
    "sg:city":"Eden Valley",
    "sg:classifiers":[
        {
            "category":"Building & Trades",
            "subcategory":"Cleaning & Sanitation",
            "type":"Services"
        }
    ],
    "sg:phone":"+61 8 8564 1103",
    "sg:postcode":"5235",
    "sg:province":"SA",
    "sg:tags":[
        "window"
    ],
    "wof:name":"Valley Cleaning Services",
    "wof:placetype":"venue"
},
  "geometry": {"coordinates":[139.08616638199999,-34.6310195923],"type":"Point"}
}