{
  "type": "Feature",
  "properties": {
    "iso:country":"AU",
    "sg:address":"Level 2, 1 Hutt St",
    "sg:city":"Adelaide",
    "sg:classifiers":[
        {
            "category":"Banks & Credit Unions",
            "subcategory":"Investment Brokerage",
            "type":"Services"
        }
    ],
    "sg:phone":"+61 8 8232 8388",
    "sg:postcode":"5000",
    "sg:province":"SA",
    "wof:name":"Anderson Planners Pty Ltd",
    "wof:placetype":"venue"
},
  "geometry": {"coordinates":[138.61155700699999,-34.9257278442],"type":"Point"}
}