{
  "type": "Feature",
  "properties": {
    "iso:country":"AU",
    "sg:address":"Lvl 1/42- 44 Church St",
    "sg:city":"Dubbo",
    "sg:classifiers":[
        {
            "category":"Real Estate",
            "subcategory":"Real Estate Services",
            "type":"Services"
        }
    ],
    "sg:phone":"+61 2 6884 8944",
    "sg:postcode":"2830",
    "sg:province":"NSW",
    "sg:tags":[
        "valuer"
    ],
    "wof:name":"Aspect Property Consultants",
    "wof:placetype":"venue"
},
  "geometry": {"coordinates":[148.60316467300001,-32.2470054626],"type":"Point"}
}