{
  "type": "Feature",
  "properties": {
    "addr:full":"16 Chatswood Ave Chatswood NSW 2067",
    "addr:housenumber":"16",
    "addr:postcode":"2067",
    "addr:street":"Chatswood Ave",
    "iso:country":"AU",
    "sg:address":"16 Chatswood Ave",
    "sg:city":"Chatswood",
    "sg:classifiers":[
        {
            "category":"Professional",
            "subcategory":"Engineering",
            "type":"Services"
        }
    ],
    "sg:phone":"+61 2 9411 5350",
    "sg:postcode":"2067",
    "sg:province":"NSW",
    "sg:tags":[
        "consulting",
        "engineer"
    ],
    "wof:name":"Automation Consultants Australia Pty Ltd",
    "wof:placetype":"venue"
},
  "geometry": {"coordinates":[151.19041442899999,-33.7934417725],"type":"Point"}
}