{
  "type": "Feature",
  "properties": {
    "addr:full":"15 Bunya St Maleny QLD 4552",
    "addr:housenumber":"15",
    "addr:postcode":"4552",
    "addr:street":"Bunya St",
    "iso:country":"AU",
    "sg:address":"15 Bunya St",
    "sg:city":"Maleny",
    "sg:classifiers":[
        {
            "category":"Professional",
            "subcategory":"Art Services",
            "type":"Services"
        }
    ],
    "sg:phone":"+61 7 5499 9288",
    "sg:postcode":"4552",
    "sg:province":"QLD",
    "sg:tags":[
        "artist"
    ],
    "wof:name":"Frangi Leonie",
    "wof:placetype":"venue"
},
  "geometry": {"coordinates":[152.85479736299999,-26.7603874207],"type":"Point"}
}