{
  "type": "Feature",
  "properties": {
    "addr:full":"RSM 232 Boallia WA 6282",
    "addr:housenumber":"232",
    "addr:postcode":"6282",
    "addr:street":"Rsm",
    "iso:country":"AU",
    "sg:address":"RSM 232",
    "sg:city":"Boallia",
    "sg:classifiers":[
        {
            "category":"Farming",
            "subcategory":"Farm",
            "type":"Manufacturing & Wholesale Goods"
        }
    ],
    "sg:phone":"+61 8 9753 1104",
    "sg:postcode":"6282",
    "sg:province":"WA",
    "sg:tags":[
        "farmer"
    ],
    "wof:name":"Sissoev A C & A",
    "wof:placetype":"venue"
},
  "geometry": {"coordinates":[114.99407959,-33.7478599548],"type":"Point"}
}