{
  "type": "Feature",
  "properties": {
    "addr:full":"209 St Georges Rd Fitzroy North VIC 3068",
    "addr:housenumber":"209",
    "addr:postcode":"3068",
    "addr:street":"St Georges Rd",
    "iso:country":"AU",
    "sg:address":"209 St Georges Rd",
    "sg:city":"Fitzroy North",
    "sg:classifiers":[
        {
            "category":"Bars & Pubs",
            "subcategory":"Wine Bar",
            "type":"Food & Drink"
        }
    ],
    "sg:phone":"+61 3 9486 6745",
    "sg:postcode":"3068",
    "sg:province":"VIC",
    "wof:name":"Deco Wine Bar",
    "wof:placetype":"venue"
},
  "geometry": {"coordinates":[144.98286438,-37.7842063904],"type":"Point"}
}