{
  "type": "Feature",
  "properties": {
    "addr:full":"82 - 84 Echuca Rd Rochester VIC 3561",
    "addr:housenumber":"84",
    "addr:postcode":"3561",
    "addr:street":"Echuca Rd",
    "iso:country":"AU",
    "sg:address":"82 - 84 Echuca Rd",
    "sg:city":"Rochester",
    "sg:classifiers":[
        {
            "category":"Home & Garden",
            "subcategory":"Carpets & Floor Coverings",
            "type":"Retail Goods"
        }
    ],
    "sg:phone":"+61 3 5484 3227",
    "sg:postcode":"3561",
    "sg:province":"VIC",
    "wof:name":"A & H Lambert Floor Coverings",
    "wof:placetype":"venue"
},
  "geometry": {"coordinates":[144.69656372099999,-36.3527145386],"type":"Point"}
}