{
  "type": "Feature",
  "properties": {
    "addr:full":"suite 9 424 Nepean Hwy Frankston VIC 3199",
    "addr:housenumber":"424",
    "addr:postcode":"3199",
    "addr:street":"Nepean Hwy",
    "iso:country":"AU",
    "sg:address":"suite 9 424 Nepean Hwy",
    "sg:city":"Frankston",
    "sg:classifiers":[
        {
            "category":"Health Services",
            "subcategory":"Dentist",
            "type":"Services"
        }
    ],
    "sg:phone":"+61 3 9783 5098",
    "sg:postcode":"3199",
    "sg:province":"VIC",
    "wof:name":"Lindner C",
    "wof:placetype":"venue"
},
  "geometry": {"coordinates":[145.08317565900001,-37.9963188171],"type":"Point"}
}