{
  "type": "Feature",
  "properties": {
    "addr:full":"26 Glebe Ave Cheltenham VIC 3192",
    "addr:housenumber":"26",
    "addr:postcode":"3192",
    "addr:street":"Glebe Ave",
    "iso:country":"AU",
    "sg:address":"26 Glebe Ave",
    "sg:city":"Cheltenham",
    "sg:classifiers":[
        {
            "category":"Professional",
            "subcategory":"Detective & Security Services",
            "type":"Services"
        }
    ],
    "sg:phone":"+61 3 9585 6798",
    "sg:postcode":"3192",
    "sg:province":"VIC",
    "sg:tags":[
        "equipment",
        "window",
        "doors"
    ],
    "wof:name":"All About Security Doors",
    "wof:placetype":"venue"
},
  "geometry": {"coordinates":[145.053665161,-37.9695587158],"type":"Point"}
}