{
  "type": "Feature",
  "properties": {
    "iso:country":"AU",
    "sg:address":"269 Troughton Rd",
    "sg:city":"Robertson",
    "sg:classifiers":[
        {
            "category":"Professional",
            "subcategory":"Art Services",
            "type":"Services"
        }
    ],
    "sg:phone":"+61 411 175 115",
    "sg:postcode":"4109",
    "sg:province":"QLD",
    "sg:tags":[
        "decorator",
        "painter"
    ],
    "wof:name":"Hudson Ian",
    "wof:placetype":"venue"
},
  "geometry": {"coordinates":[153.049850464,-27.5639820099],"type":"Point"}
}