{
  "type": "Feature",
  "properties": {
    "addr:full":"2/ 15 Wrights Pl Labrador QLD 4215",
    "addr:housenumber":"/ 15",
    "addr:postcode":"4215",
    "addr:street":"Wrights Pl",
    "iso:country":"AU",
    "sg:address":"2/ 15 Wrights Pl",
    "sg:city":"Labrador",
    "sg:classifiers":[
        {
            "category":"Building & Trades",
            "subcategory":"Construction",
            "type":"Services"
        }
    ],
    "sg:phone":"+61 7 5537 7773",
    "sg:postcode":"4215",
    "sg:province":"QLD",
    "sg:tags":[
        "welding"
    ],
    "wof:name":"Abbott Welding",
    "wof:placetype":"venue"
},
  "geometry": {"coordinates":[153.38160705600001,-27.9352264404],"type":"Point"}
}