{
  "type": "Feature",
  "properties": {
    "iso:country":"AU",
    "sg:address":"Shop 17 Burnside Shopping Centre",
    "sg:city":"Burnside",
    "sg:classifiers":[
        {
            "category":"Health Services",
            "subcategory":"Optometrist",
            "type":"Services"
        }
    ],
    "sg:phone":"+61 3 9360 4444",
    "sg:postcode":"3023",
    "sg:province":"VIC",
    "wof:name":"Visioncrest Optometrists",
    "wof:placetype":"venue"
},
  "geometry": {"coordinates":[144.772324,-37.771763],"type":"Point"}
}