{
  "type": "Feature",
  "properties": {
    "addr:full":"5 Westbury St Red Hill QLD 4059",
    "addr:housenumber":"5",
    "addr:postcode":"4059",
    "addr:street":"Westbury St",
    "iso:country":"AU",
    "sg:address":"5 Westbury St",
    "sg:city":"Red Hill",
    "sg:classifiers":[
        {
            "category":"Social Services",
            "subcategory":"Retirement Home",
            "type":"Services"
        }
    ],
    "sg:phone":"+61 7 3831 2773",
    "sg:postcode":"4059",
    "sg:province":"QLD",
    "sg:tags":[
        "environmental",
        "consultant",
        "pollution"
    ],
    "wof:name":"Environ Best",
    "wof:placetype":"venue"
},
  "geometry": {"coordinates":[153.01193237300001,-27.4551887512],"type":"Point"}
}