{
  "type": "Feature",
  "properties": {
    "iso:country":"AU",
    "sg:address":"Suite 29 17 Prowse St",
    "sg:city":"West Perth",
    "sg:classifiers":[
        {
            "category":"Banks & Credit Unions",
            "subcategory":"Financial Services",
            "type":"Services"
        }
    ],
    "sg:phone":"+61 8 9322 2284",
    "sg:postcode":"6005",
    "sg:province":"WA",
    "sg:tags":[
        "settlement",
        "nt",
        "agent",
        "wa"
    ],
    "wof:name":"Brearley Don",
    "wof:placetype":"venue"
},
  "geometry": {"coordinates":[115.841560364,-31.9449291229],"type":"Point"}
}