{
  "type": "Feature",
  "properties": {
    "addr:full":"Kingston View Drv Kingston TAS 7050",
    "addr:postcode":"7050",
    "addr:street":"View Drv",
    "iso:country":"AU",
    "sg:address":"Kingston View Drv",
    "sg:city":"Kingston",
    "sg:classifiers":[
        {
            "category":"Sports & Exercise",
            "subcategory":"Sports Center",
            "type":"Entertainment"
        }
    ],
    "sg:phone":"+61 3 6229 0900",
    "sg:postcode":"7050",
    "sg:province":"TAS",
    "sg:tags":[
        "ground"
    ],
    "wof:name":"Kingborough Sports Centre Gymnastics",
    "wof:placetype":"venue"
},
  "geometry": {"coordinates":[147.28935200000001,-42.969334],"type":"Point"}
}