{
  "type": "Feature",
  "properties": {
    "iso:country":"AU",
    "sg:address":"Old Port Wakefield Rd",
    "sg:city":"Two Wells",
    "sg:classifiers":[
        {
            "category":"Arena",
            "subcategory":"Bull Ring",
            "type":"Entertainment"
        }
    ],
    "sg:phone":"+61 8 8520 2959",
    "sg:postcode":"5501",
    "sg:province":"SA",
    "sg:tags":[
        "breeder",
        "pig"
    ],
    "wof:name":"Gene Nucleus",
    "wof:placetype":"venue"
},
  "geometry": {"coordinates":[138.514755,-34.593967],"type":"Point"}
}