{
  "type": "Feature",
  "properties": {
    "iso:country":"AU",
    "sg:address":"\"Roads End\" 585 High St",
    "sg:city":"Maitland",
    "sg:classifiers":[
        {
            "category":"Government",
            "subcategory":"Post Office",
            "type":"Public Place"
        }
    ],
    "sg:phone":"+61 2 4932 3277",
    "sg:postcode":"2320",
    "sg:province":"NSW",
    "sg:tags":[
        "house",
        "doll"
    ],
    "wof:name":"Carousel Keepsake Dollhouses",
    "wof:placetype":"venue"
},
  "geometry": {"coordinates":[151.54576110799999,-32.7277183533],"type":"Point"}
}