{
  "type": "Feature",
  "properties": {
    "addr:full":"18- 20 Buckland St Chippendale NSW 2008",
    "addr:housenumber":"20",
    "addr:postcode":"2008",
    "addr:street":"Buckland St",
    "iso:country":"AU",
    "sg:address":"18- 20 Buckland St",
    "sg:city":"Chippendale",
    "sg:classifiers":[
        {
            "category":"Food & Beverages",
            "subcategory":"Groceries & Convenience Stores",
            "type":"Retail Goods"
        }
    ],
    "sg:phone":"+61 2 9690 1566",
    "sg:postcode":"2008",
    "sg:province":"NSW",
    "wof:name":"Captain Cook Convenience Store",
    "wof:placetype":"venue"
},
  "geometry": {"coordinates":[151.197555542,-33.8859977722],"type":"Point"}
}