{
  "type": "Feature",
  "properties": {
    "iso:country":"AU",
    "sg:address":"Shop 6/ 53 Wharf St",
    "sg:city":"Woolgoolga",
    "sg:classifiers":[
        {
            "category":"Food & Beverages",
            "subcategory":"Meat & Fish",
            "type":"Retail Goods"
        }
    ],
    "sg:phone":"+61 2 6654 2611",
    "sg:postcode":"2456",
    "sg:province":"NSW",
    "sg:tags":[
        "seafood"
    ],
    "wof:name":"Surfside Seafood & Curry",
    "wof:placetype":"venue"
},
  "geometry": {"coordinates":[153.200638,-30.110104],"type":"Point"}
}