{
  "type": "Feature",
  "properties": {
    "addr:full":"17 Scott Crs Mildura VIC 3502",
    "addr:housenumber":"17",
    "addr:postcode":"3502",
    "addr:street":"Scott Crs",
    "iso:country":"AU",
    "sg:address":"17 Scott Crs",
    "sg:city":"Mildura",
    "sg:classifiers":[
        {
            "category":"Arena",
            "subcategory":"Sports Club",
            "type":"Entertainment"
        }
    ],
    "sg:phone":"+61 418 500 537",
    "sg:postcode":"3502",
    "sg:province":"VIC",
    "sg:tags":[
        "defence",
        "supply",
        "self",
        "instruction",
        "martial art"
    ],
    "wof:name":"Ataru International Tae Kwon Do I.T.F.",
    "wof:placetype":"venue"
},
  "geometry": {"coordinates":[142.165557861,-34.184551239],"type":"Point"}
}