{
  "type": "Feature",
  "properties": {
    "iso:country":"AU",
    "sg:address":"6 Talbot St",
    "sg:city":"Peakhurst",
    "sg:classifiers":[
        {
            "category":"Utilities",
            "subcategory":"Water",
            "type":"Services"
        }
    ],
    "sg:phone":"+61 2 9584 8044",
    "sg:postcode":"2210",
    "sg:province":"NSW",
    "sg:tags":[
        "equipment",
        "ultraviolet"
    ],
    "wof:name":"Alpha UV Systems",
    "wof:placetype":"venue"
},
  "geometry": {"coordinates":[151.058334,-33.953648],"type":"Point"}
}