{
  "type": "Feature",
  "properties": {
    "addr:full":"Unit 2 16 Hearn St Mortdale NSW 2223",
    "addr:housenumber":"16",
    "addr:postcode":"2223",
    "addr:street":"Hearn St",
    "iso:country":"AU",
    "sg:address":"Unit 2 16 Hearn St",
    "sg:city":"Mortdale",
    "sg:classifiers":[
        {
            "category":"Professional",
            "subcategory":"Engineering",
            "type":"Services"
        }
    ],
    "sg:phone":"+61 2 9584 1083",
    "sg:postcode":"2223",
    "sg:province":"NSW",
    "sg:tags":[
        "engineer"
    ],
    "wof:name":"Engineering Developments & Investments Pty Ltd",
    "wof:placetype":"venue"
},
  "geometry": {"coordinates":[151.066894531,-33.9654579163],"type":"Point"}
}