{
  "type": "Feature",
  "properties": {
    "addr:full":"Farnborough Rd Yeppoon QLD 4703",
    "addr:postcode":"4703",
    "addr:street":"Farnborough Rd",
    "iso:country":"AU",
    "sg:address":"Farnborough Rd",
    "sg:city":"Yeppoon",
    "sg:classifiers":[
        {
            "category":"Travel",
            "subcategory":"Hotels & Motels",
            "type":"Entertainment"
        }
    ],
    "sg:phone":"+61 1800 075 902",
    "sg:postcode":"4703",
    "sg:province":"QLD",
    "sg:tags":[
        "accommodation"
    ],
    "wof:name":"Rydges Capricorn Resort",
    "wof:placetype":"venue"
},
  "geometry": {"coordinates":[150.749557495,-23.1280002594],"type":"Point"}
}