{
  "type": "Feature",
  "properties": {
    "addr:full":"PO Box 84 Swan Hill VIC 3585",
    "addr:postcode":"3585",
    "iso:country":"AU",
    "sg:address":"PO Box 84",
    "sg:city":"Swan Hill",
    "sg:classifiers":[
        {
            "category":"Building & Trades",
            "subcategory":"Landscaping Services",
            "type":"Services"
        }
    ],
    "sg:phone":"+61 3 5030 2450",
    "sg:postcode":"3585",
    "sg:province":"VIC",
    "sg:tags":[
        "stump",
        "tree",
        "felling",
        "removal"
    ],
    "wof:name":"Northern Tree Maintenance",
    "wof:placetype":"venue"
},
  "geometry": {"coordinates":[143.561554,-35.340969],"type":"Point"}
}