{
  "type": "Feature",
  "properties": {
    "addr:full":"94 Patrea St Banyo QLD 4014",
    "addr:housenumber":"94",
    "addr:postcode":"4014",
    "addr:street":"Patrea St",
    "iso:country":"AU",
    "sg:address":"94 Patrea St",
    "sg:city":"Banyo",
    "sg:classifiers":[
        {
            "category":"Professional",
            "subcategory":"Secretarial Services",
            "type":"Services"
        }
    ],
    "sg:phone":"+61 7 3267 6811",
    "sg:postcode":"4014",
    "sg:province":"QLD",
    "sg:tags":[
        "typing"
    ],
    "wof:name":"A1 Typing",
    "wof:placetype":"venue"
},
  "geometry": {"coordinates":[153.08578491200001,-27.3842277527],"type":"Point"}
}