{
  "type": "Feature",
  "properties": {
    "iso:country":"AU",
    "sg:address":"Grey St",
    "sg:city":"Glen Innes",
    "sg:classifiers":[
        {
            "category":"Cafe",
            "type":"Food & Drink"
        }
    ],
    "sg:phone":"+61 2 6732 3353",
    "sg:postcode":"2370",
    "sg:province":"NSW",
    "wof:name":"Tea & Coffee Shop The",
    "wof:placetype":"venue"
},
  "geometry": {"coordinates":[151.73631286599999,-29.7342185974],"type":"Point"}
}