{
  "type": "Feature",
  "properties": {
    "addr:full":"47- 49 Red Gum Drv Dandenong South VIC 3175",
    "addr:housenumber":"49",
    "addr:postcode":"3175",
    "addr:street":"Red Gum Drv",
    "iso:country":"AU",
    "sg:address":"47- 49 Red Gum Drv",
    "sg:city":"Dandenong South",
    "sg:classifiers":[
        {
            "category":"Farming",
            "subcategory":"Fish & Marine Products",
            "type":"Manufacturing & Wholesale Goods"
        }
    ],
    "sg:phone":"+61 3 9768 2220",
    "sg:postcode":"3175",
    "sg:province":"VIC",
    "sg:tags":[
        "chemical",
        "supplier"
    ],
    "wof:name":"Chiron Chemicals Pty Ltd",
    "wof:placetype":"venue"
},
  "geometry": {"coordinates":[145.19712829599999,-38.0260238647],"type":"Point"}
}