{
  "type": "Feature",
  "properties": {
    "addr:full":"11/ 277 Mulgrave Rd Cairns QLD 4870",
    "addr:housenumber":"11 / 277",
    "addr:postcode":"4870",
    "addr:street":"Mulgrave Rd",
    "iso:country":"AU",
    "sg:address":"11/ 277 Mulgrave Rd",
    "sg:city":"Cairns",
    "sg:classifiers":[
        {
            "category":"Personal",
            "subcategory":"Massage",
            "type":"Services"
        }
    ],
    "sg:phone":"+61 7 4051 0441",
    "sg:postcode":"4870",
    "sg:province":"QLD",
    "sg:tags":[
        "therapy"
    ],
    "wof:name":"The Touch Therapy Centre",
    "wof:placetype":"venue"
},
  "geometry": {"coordinates":[145.74334716800001,-16.9400348663],"type":"Point"}
}