{
  "type": "Feature",
  "properties": {
    "addr:full":"313 Warrigal Rd Cheltenham VIC 3192",
    "addr:housenumber":"313",
    "addr:postcode":"3192",
    "addr:street":"Warrigal Rd",
    "iso:country":"AU",
    "sg:address":"313 Warrigal Rd",
    "sg:city":"Cheltenham",
    "sg:classifiers":[
        {
            "category":"Social Services",
            "type":"Services"
        }
    ],
    "sg:phone":"+61 1300 133 120",
    "sg:postcode":"3192",
    "sg:province":"VIC",
    "sg:tags":[
        "disabled",
        "person",
        "equipment"
    ],
    "wof:name":"Lifestyle & Rehab",
    "wof:placetype":"venue"
},
  "geometry": {"coordinates":[145.07539367699999,-37.9595870972],"type":"Point"}
}