{
  "type": "Feature",
  "properties": {
    "addr:full":"159 Derby St Penrith NSW 2750",
    "addr:housenumber":"159",
    "addr:postcode":"2750",
    "addr:street":"Derby St",
    "iso:country":"AU",
    "sg:address":"159 Derby St",
    "sg:city":"Penrith",
    "sg:classifiers":[
        {
            "category":"Health Services",
            "subcategory":"Health Practitioner",
            "type":"Services"
        }
    ],
    "sg:phone":"+61 2 4721 1488",
    "sg:postcode":"2750",
    "sg:province":"NSW",
    "sg:tags":[
        "hypnotherapy"
    ],
    "wof:name":"Penrith Therapy Centre",
    "wof:placetype":"venue"
},
  "geometry": {"coordinates":[150.70204162600001,-33.7584838867],"type":"Point"}
}