{
  "type": "Feature",
  "properties": {
    "addr:full":"Lot 1 412-440 Hanson Rd Dry Creek VIC 3720",
    "addr:housenumber":"412-440",
    "addr:postcode":"3720",
    "addr:street":"Hanson Rd Dry Creek",
    "iso:country":"AU",
    "sg:address":"Lot 1 412-440 Hanson Rd",
    "sg:city":"Dry Creek",
    "sg:classifiers":[
        {
            "category":"Utilities",
            "subcategory":"Recycling",
            "type":"Services"
        }
    ],
    "sg:phone":"+61 1800 819 000",
    "sg:postcode":"3720",
    "sg:province":"VIC",
    "wof:name":"Amcor Recycling",
    "wof:placetype":"venue"
},
  "geometry": {"coordinates":[145.88276672399999,-37.0129508972],"type":"Point"}
}