{
  "type": "Feature",
  "properties": {
    "addr:full":"30/ 7 Narabang Way Belrose NSW 2085",
    "addr:housenumber":"30 / 7",
    "addr:postcode":"2085",
    "addr:street":"Narabang Way",
    "iso:country":"AU",
    "sg:address":"30/ 7",
    "sg:city":"Narabang Way Belrose",
    "sg:classifiers":[
        {
            "category":"Professional",
            "subcategory":"Management & Consulting",
            "type":"Services"
        }
    ],
    "sg:phone":"+61 2 9450 2660",
    "sg:postcode":"2085",
    "sg:province":"NSW",
    "sg:tags":[
        "consultant"
    ],
    "wof:name":"Teal Management Services Pty Ltd",
    "wof:placetype":"venue"
},
  "geometry": {"coordinates":[151.212356567,-33.70520401],"type":"Point"}
}