{
  "type": "Feature",
  "properties": {
    "addr:full":"6/ 4 Hillside Pde Glen Iris VIC 3146",
    "addr:housenumber":"/ 4",
    "addr:postcode":"3146",
    "addr:street":"Hillside Pde",
    "iso:country":"AU",
    "sg:address":"6/ 4 Hillside Pde",
    "sg:city":"Glen Iris",
    "sg:classifiers":[
        {
            "category":"Home & Garden",
            "subcategory":"Building Materials",
            "type":"Retail Goods"
        }
    ],
    "sg:phone":"+61 3 9411 5387",
    "sg:postcode":"3146",
    "sg:province":"VIC",
    "sg:tags":[
        "lawn",
        "cutting",
        "maintenance"
    ],
    "wof:name":"Andrew & Angela Seager Gardening Services",
    "wof:placetype":"venue"
},
  "geometry": {"coordinates":[145.06422424300001,-37.8471641541],"type":"Point"}
}