{
  "type": "Feature",
  "properties": {
    "iso:country":"AU",
    "sg:address":"89 Paisley St",
    "sg:city":"Footscray",
    "sg:classifiers":[
        {
            "category":"Health Services",
            "subcategory":"Optometrist",
            "type":"Services"
        }
    ],
    "sg:phone":"+61 3 9689 9233",
    "sg:postcode":"3011",
    "sg:province":"VIC",
    "wof:name":"Eye Clinic Footscray",
    "wof:placetype":"venue"
},
  "geometry": {"coordinates":[144.89544677699999,-37.800491333],"type":"Point"}
}