{
  "type": "Feature",
  "properties": {
    "iso:country":"AU",
    "sg:address":"12 Jones St",
    "sg:city":"Wagga Wagga",
    "sg:classifiers":[
        {
            "category":"Retail",
            "subcategory":"Auto Repair",
            "type":"Services"
        }
    ],
    "sg:phone":"+61 2 6921 2598",
    "sg:postcode":"2650",
    "sg:province":"NSW",
    "sg:tags":[
        "wheel",
        "balancing",
        "alignment"
    ],
    "wof:name":"Pats Tyre Service",
    "wof:placetype":"venue"
},
  "geometry": {"coordinates":[147.384277344,-35.1229171753],"type":"Point"}
}