{
  "type": "Feature",
  "properties": {
    "addr:full":"60 Leonard Rd Lilydale VIC 3140",
    "addr:housenumber":"60",
    "addr:postcode":"3140",
    "addr:street":"Leonard Rd",
    "iso:country":"AU",
    "sg:address":"60 Leonard Rd",
    "sg:city":"Lilydale",
    "sg:classifiers":[
        {
            "category":"Home & Garden",
            "subcategory":"Carpets & Floor Coverings",
            "type":"Retail Goods"
        }
    ],
    "sg:phone":"+61 412 123 387",
    "sg:postcode":"3140",
    "sg:province":"VIC",
    "sg:tags":[
        "tile",
        "wall",
        "layer"
    ],
    "wof:name":"Yarra Ceramic Services",
    "wof:placetype":"venue"
},
  "geometry": {"coordinates":[145.39202880900001,-37.7518844604],"type":"Point"}
}