{
  "type": "Feature",
  "properties": {
    "addr:full":"PO Box 12509 Melbourne VIC 3000",
    "addr:postcode":"3000",
    "iso:country":"AU",
    "sg:address":"PO Box 12509",
    "sg:city":"Melbourne",
    "sg:classifiers":[
        {
            "category":"Organizations",
            "subcategory":"Professional Association",
            "type":"Services"
        }
    ],
    "sg:phone":"+61 3 9841 0986",
    "sg:postcode":"3000",
    "sg:province":"VIC",
    "sg:tags":[
        "web",
        "internet"
    ],
    "wof:name":"SABE Computer Solutions",
    "wof:placetype":"venue"
},
  "geometry": {"coordinates":[144.97027587900001,-37.8145599365],"type":"Point"}
}