{
  "type": "Feature",
  "properties": {
    "addr:full":"195 Norton St Leichhardt NSW 2040",
    "addr:housenumber":"195",
    "addr:postcode":"2040",
    "addr:street":"Norton St",
    "iso:country":"AU",
    "sg:address":"195 Norton St",
    "sg:city":"Leichhardt",
    "sg:classifiers":[
        {
            "category":"Health Services",
            "subcategory":"Health Practitioner",
            "type":"Services"
        }
    ],
    "sg:phone":"+61 2 9569 8076",
    "sg:postcode":"2040",
    "sg:province":"NSW",
    "sg:tags":[
        "psychologist"
    ],
    "wof:name":"Conlon Erika",
    "wof:placetype":"venue"
},
  "geometry": {"coordinates":[151.15679900000001,-33.88031],"type":"Point"}
}