{
  "type": "Feature",
  "properties": {
    "iso:country":"AU",
    "sg:address":"110 Sladen St",
    "sg:city":"Cranbourne",
    "sg:classifiers":[
        {
            "category":"Restaurant",
            "type":"Food & Drink"
        }
    ],
    "sg:phone":"+61 3 5996 8555",
    "sg:postcode":"3977",
    "sg:province":"VIC",
    "wof:name":"Bear House Restaurant",
    "wof:placetype":"venue"
},
  "geometry": {"coordinates":[145.275924683,-38.1123771667],"type":"Point"}
}