{
  "type": "Feature",
  "properties": {
    "iso:country":"AU",
    "sg:address":"10 Brisbane St",
    "sg:city":"Ipswich",
    "sg:classifiers":[
        {
            "category":"Health Services",
            "subcategory":"Doctor",
            "type":"Services"
        }
    ],
    "sg:phone":"+61 7 3281 4622",
    "sg:postcode":"4305",
    "sg:province":"QLD",
    "sg:tags":[
        "medical",
        "practitioner"
    ],
    "wof:name":"Limestone Medical Centre",
    "wof:placetype":"venue"
},
  "geometry": {"coordinates":[152.76478576700001,-27.6155548096],"type":"Point"}
}