{
  "type": "Feature",
  "properties": {
    "addr:full":"8 Vince Hinde Drv Mudgeeraba QLD 4213",
    "addr:housenumber":"8",
    "addr:postcode":"4213",
    "addr:street":"Vince Hinde Drv",
    "iso:country":"AU",
    "sg:address":"8 Vince Hinde Drv",
    "sg:city":"Mudgeeraba",
    "sg:classifiers":[
        {
            "category":"Professional",
            "subcategory":"Accounting & Tax Preparation",
            "type":"Services"
        }
    ],
    "sg:phone":"+61 7 5530 4759",
    "sg:postcode":"4213",
    "sg:province":"QLD",
    "sg:tags":[
        "accountant",
        "auditor"
    ],
    "wof:name":"N&T Accountancy",
    "wof:placetype":"venue"
},
  "geometry": {"coordinates":[153.33645629899999,-28.0587024689],"type":"Point"}
}