{
  "type": "Feature",
  "properties": {
    "iso:country":"AU",
    "sg:address":"Shop 57, 200 Mirrabooka Ave",
    "sg:city":"Mirrabooka",
    "sg:classifiers":[
        {
            "category":"Fast Food",
            "type":"Food & Drink"
        }
    ],
    "sg:phone":"+61 8 9343 4800",
    "sg:postcode":"6061",
    "sg:province":"WA",
    "sg:tags":[
        "away",
        "take"
    ],
    "wof:name":"Dominos Pizza",
    "wof:placetype":"venue"
},
  "geometry": {"coordinates":[115.85494995099999,-31.8521404266],"type":"Point"}
}