{
  "type": "Feature",
  "properties": {
    "iso:country":"AU",
    "sg:address":"115 Harrington St",
    "sg:city":"Hobart",
    "sg:classifiers":[
        {
            "category":"Building & Trades",
            "subcategory":"Locksmith",
            "type":"Services"
        }
    ],
    "sg:phone":"+61 3 6234 3727",
    "sg:postcode":"7000",
    "sg:province":"TAS",
    "sg:tags":[
        "strongroom",
        "safe",
        "door"
    ],
    "wof:name":"Tasmanian Locksmiths Pty Ltd",
    "wof:placetype":"venue"
},
  "geometry": {"coordinates":[147.32351684599999,-42.8832931519],"type":"Point"}
}