{
  "type": "Feature",
  "properties": {
    "addr:full":"31 Henry St Cardiff NSW 2285",
    "addr:housenumber":"31",
    "addr:postcode":"2285",
    "addr:street":"Henry St",
    "iso:country":"AU",
    "sg:address":"31 Henry St",
    "sg:city":"Cardiff",
    "sg:classifiers":[
        {
            "category":"Sports & Exercise",
            "subcategory":"Gym",
            "type":"Entertainment"
        }
    ],
    "sg:phone":"+61 2 4956 6185",
    "sg:postcode":"2285",
    "sg:province":"NSW",
    "sg:tags":[
        "health",
        "fitness"
    ],
    "wof:name":"Iacconi Excavations",
    "wof:placetype":"venue"
},
  "geometry": {"coordinates":[151.66409301799999,-32.9464111328],"type":"Point"}
}