{
  "type": "Feature",
  "properties": {
    "addr:full":"Shp2/ 217 Mickleham Rd Westmeadows VIC 3049",
    "addr:housenumber":"217",
    "addr:postcode":"3049",
    "addr:street":"Mickleham Rd",
    "iso:country":"AU",
    "sg:address":"Shp2/ 217 Mickleham Rd",
    "sg:city":"Westmeadows",
    "sg:classifiers":[
        {
            "category":"Professional",
            "subcategory":"Computer Services",
            "type":"Services"
        }
    ],
    "sg:phone":"+61 3 9338 9909",
    "sg:postcode":"3049",
    "sg:province":"VIC",
    "sg:tags":[
        "training"
    ],
    "wof:name":"UCT",
    "wof:placetype":"venue"
},
  "geometry": {"coordinates":[144.882385,-37.685413],"type":"Point"}
}