{
  "type": "Feature",
  "properties": {
    "addr:full":"Woolsthorpe Rd Hexham VIC 3273",
    "addr:postcode":"3273",
    "addr:street":"Woolsthorpe Rd",
    "iso:country":"AU",
    "sg:address":"Woolsthorpe Rd",
    "sg:city":"Hexham",
    "sg:classifiers":[
        {
            "category":"Farming",
            "subcategory":"Farm",
            "type":"Manufacturing & Wholesale Goods"
        }
    ],
    "sg:phone":"+61 3 5599 7285",
    "sg:postcode":"3273",
    "sg:province":"VIC",
    "sg:tags":[
        "farmer"
    ],
    "wof:name":"Coomete Pty Ltd",
    "wof:placetype":"venue"
},
  "geometry": {"coordinates":[142.67161560100001,-38.0229415894],"type":"Point"}
}