{
  "type": "Feature",
  "properties": {
    "iso:country":"AU",
    "sg:address":"4/ 27 Casey St",
    "sg:city":"Aitkenvale",
    "sg:classifiers":[
        {
            "category":"Retail",
            "subcategory":"Auto Repair",
            "type":"Services"
        }
    ],
    "sg:phone":"+61 408 777 155",
    "sg:postcode":"4814",
    "sg:province":"QLD",
    "sg:tags":[
        "repairer",
        "motor",
        "engineer"
    ],
    "wof:name":"Terry's Dial-A-Mechanic",
    "wof:placetype":"venue"
},
  "geometry": {"coordinates":[146.76980599999999,-19.294333],"type":"Point"}
}