{
  "type": "Feature",
  "properties": {
    "addr:full":"Direct Factory Outlets Shop 60, 250 Centre Dandeno Cheltenham VIC 3192",
    "addr:housenumber":"60 250",
    "addr:postcode":"3192",
    "addr:street":"Centre Dandeno",
    "iso:country":"AU",
    "sg:address":"Direct Factory Outlets Shop 60, 250 Centre Dandeno",
    "sg:city":"Cheltenham",
    "sg:classifiers":[
        {
            "category":"Shopping",
            "type":"Retail Goods"
        }
    ],
    "sg:phone":"+61 3 9585 5945",
    "sg:postcode":"3192",
    "sg:province":"VIC",
    "sg:tags":[
        "clearance",
        "factory",
        "outlet"
    ],
    "wof:name":"My Cargo Hold",
    "wof:placetype":"venue"
},
  "geometry": {"coordinates":[145.086700439,-37.9693908691],"type":"Point"}
}