{
  "type": "Feature",
  "properties": {
    "addr:full":"13 Broadway St Broadway NSW 2007",
    "addr:housenumber":"13",
    "addr:postcode":"2007",
    "addr:street":"Broadway St",
    "iso:country":"AU",
    "sg:address":"13 Broadway St",
    "sg:city":"Broadway",
    "sg:classifiers":[
        {
            "category":"Shopping",
            "subcategory":"Optical Goods",
            "type":"Retail Goods"
        }
    ],
    "sg:phone":"+61 2 9211 5770",
    "sg:postcode":"2007",
    "sg:province":"NSW",
    "sg:tags":[
        "dispenser",
        "prescription"
    ],
    "wof:name":"Modern Specs",
    "wof:placetype":"venue"
},
  "geometry": {"coordinates":[151.20018005399999,-33.8841514587],"type":"Point"}
}