{
  "type": "Feature",
  "properties": {
    "addr:full":"22 Halls Rd Coffs Harbour NSW 2450",
    "addr:housenumber":"22",
    "addr:postcode":"2450",
    "addr:street":"Halls Rd",
    "iso:country":"AU",
    "sg:address":"22 Halls Rd",
    "sg:city":"Coffs Harbour",
    "sg:classifiers":[
        {
            "category":"Professional",
            "type":"Services"
        }
    ],
    "sg:phone":"+61 407 029 225",
    "sg:postcode":"2450",
    "sg:province":"NSW",
    "sg:tags":[
        "spray",
        "painting"
    ],
    "wof:name":"Kwik Fix",
    "wof:placetype":"venue"
},
  "geometry": {"coordinates":[153.09759521500001,-30.3054275513],"type":"Point"}
}