{
  "type": "Feature",
  "properties": {
    "iso:country":"AU",
    "sg:address":"30 Cottam Ave",
    "sg:city":"Bankstown",
    "sg:classifiers":[
        {
            "category":"Wholesale",
            "subcategory":"Auto Parts",
            "type":"Manufacturing & Wholesale Goods"
        }
    ],
    "sg:phone":"+61 2 9708 4077",
    "sg:postcode":"2200",
    "sg:province":"NSW",
    "sg:tags":[
        "recyclers"
    ],
    "wof:name":"Aivi Auto Wreckers",
    "wof:placetype":"venue"
},
  "geometry": {"coordinates":[151.03405799999999,-33.932083],"type":"Point"}
}