{
  "type": "Feature",
  "properties": {
    "addr:full":"171 Albury St Murrumburrah NSW 2587",
    "addr:housenumber":"171",
    "addr:postcode":"2587",
    "addr:street":"Albury St",
    "iso:country":"AU",
    "sg:address":"171 Albury St",
    "sg:city":"Murrumburrah",
    "sg:classifiers":[
        {
            "category":"Social Services",
            "subcategory":"Child Care",
            "type":"Services"
        }
    ],
    "sg:phone":"+61 2 6386 3291",
    "sg:postcode":"2587",
    "sg:province":"NSW",
    "wof:name":"Minbalup Childcare Centre Pty Ltd",
    "wof:placetype":"venue"
},
  "geometry": {"coordinates":[148.350997925,-34.5496292114],"type":"Point"}
}