{
  "type": "Feature",
  "properties": {
    "addr:full":"9 Elizabeth St Coburg North VIC 3058",
    "addr:housenumber":"9",
    "addr:postcode":"3058",
    "addr:street":"Elizabeth St",
    "iso:country":"AU",
    "sg:address":"9 Elizabeth St",
    "sg:city":"Coburg North",
    "sg:classifiers":[
        {
            "category":"Retail",
            "subcategory":"Car Wash",
            "type":"Services"
        }
    ],
    "sg:phone":"+61 3 9304 6500",
    "sg:postcode":"3058",
    "sg:province":"VIC",
    "sg:tags":[
        "truck",
        "cleaning"
    ],
    "wof:name":"Prime Car Wash",
    "wof:placetype":"venue"
},
  "geometry": {"coordinates":[144.980026245,-37.7419090271],"type":"Point"}
}