{
  "type": "Feature",
  "properties": {
    "iso:country":"AU",
    "sg:address":"218 Kensington Rd",
    "sg:city":"Kensington",
    "sg:classifiers":[
        {
            "category":"Autos & Motor Vehicles",
            "subcategory":"Automobile Sales",
            "type":"Retail Goods"
        }
    ],
    "sg:phone":"+61 1300 137 733",
    "sg:postcode":"5068",
    "sg:province":"SA",
    "sg:tags":[
        "car",
        "used"
    ],
    "wof:name":"Jarvis Ford",
    "wof:placetype":"venue"
},
  "geometry": {"coordinates":[138.64907836899999,-34.9266777039],"type":"Point"}
}