{
  "type": "Feature",
  "properties": {
    "addr:full":"Unit 3/ 6 Resources Crt Molendinar QLD 4214",
    "addr:postcode":"4214",
    "addr:street":"Resources Crt",
    "iso:country":"AU",
    "sg:address":"Unit 3/ 6 Resources Crt",
    "sg:city":"Molendinar",
    "sg:classifiers":[
        {
            "category":"Building & Trades",
            "subcategory":"Construction",
            "type":"Services"
        }
    ],
    "sg:phone":"+61 413 734 305",
    "sg:postcode":"4214",
    "sg:province":"QLD",
    "sg:tags":[
        "pool",
        "swimming"
    ],
    "wof:name":"Coastal Pool Tiling & Pebble Contractors",
    "wof:placetype":"venue"
},
  "geometry": {"coordinates":[153.35780334500001,-27.9789295197],"type":"Point"}
}