{
  "type": "Feature",
  "properties": {
    "addr:full":"240 Whitehorse Rd Balwyn VIC 3103",
    "addr:housenumber":"240",
    "addr:postcode":"3103",
    "addr:street":"Whitehorse Rd",
    "iso:country":"AU",
    "sg:address":"240 Whitehorse Rd",
    "sg:city":"Balwyn",
    "sg:classifiers":[
        {
            "category":"Shopping",
            "subcategory":"Optical Goods",
            "type":"Retail Goods"
        }
    ],
    "sg:phone":"+61 3 9888 6530",
    "sg:postcode":"3103",
    "sg:province":"VIC",
    "sg:tags":[
        "supply"
    ],
    "wof:name":"Smith Robin",
    "wof:placetype":"venue"
},
  "geometry": {"coordinates":[145.081497192,-37.8129386902],"type":"Point"}
}