{
  "type": "Feature",
  "properties": {
    "addr:full":"8 Nelson Rd Box Hill NSW 2765",
    "addr:housenumber":"8",
    "addr:postcode":"2765",
    "addr:street":"Nelson Rd",
    "iso:country":"AU",
    "sg:address":"8 Nelson Rd",
    "sg:city":"Box Hill",
    "sg:classifiers":[
        {
            "category":"Building & Trades",
            "subcategory":"Construction",
            "type":"Services"
        }
    ],
    "sg:phone":"+61 2 9679 0930",
    "sg:postcode":"2765",
    "sg:province":"NSW",
    "sg:tags":[
        "roof"
    ],
    "wof:name":"Doyle Steel Frames & Trusses",
    "wof:placetype":"venue"
},
  "geometry": {"coordinates":[150.90379333499999,-33.6645050049],"type":"Point"}
}