{
  "type": "Feature",
  "properties": {
    "iso:country":"AU",
    "sg:address":"14 Brisbane St",
    "sg:city":"Ipswich",
    "sg:classifiers":[
        {
            "category":"Utilities",
            "subcategory":"Telephone",
            "type":"Services"
        }
    ],
    "sg:phone":"+61 7 3812 5001",
    "sg:postcode":"4305",
    "sg:province":"QLD",
    "sg:tags":[
        "equipment",
        "system"
    ],
    "sg:website":"http://www.mansol.net.au",
    "wof:name":"Managed Solutions Pty Ltd",
    "wof:placetype":"venue"
},
  "geometry": {"coordinates":[152.76446533199999,-27.6154747009],"type":"Point"}
}