{
  "type": "Feature",
  "properties": {
    "addr:full":"Bayview Ave Earlwood NSW 2206",
    "addr:postcode":"2206",
    "addr:street":"Bayview Ave",
    "iso:country":"AU",
    "sg:address":"Bayview Ave",
    "sg:city":"Earlwood",
    "sg:classifiers":[
        {
            "category":"Education",
            "subcategory":"School",
            "type":"Public Place"
        }
    ],
    "sg:phone":"+61 2 9558 3432",
    "sg:postcode":"2206",
    "sg:province":"NSW",
    "sg:tags":[
        "state",
        "-",
        "nsw"
    ],
    "wof:name":"Undercliffe Public School",
    "wof:placetype":"venue"
},
  "geometry": {"coordinates":[151.13592499999999,-33.92387],"type":"Point"}
}