{
  "type": "Feature",
  "properties": {
    "iso:country":"AU",
    "sg:address":"118 Racecourse Rd",
    "sg:city":"Ascot",
    "sg:classifiers":[
        {
            "category":"Health Services",
            "subcategory":"Doctor",
            "type":"Services"
        }
    ],
    "sg:phone":"+61 7 3268 2318",
    "sg:postcode":"4007",
    "sg:province":"QLD",
    "sg:tags":[
        "medical",
        "practitioner"
    ],
    "wof:name":"Toalster Rosemary",
    "wof:placetype":"venue"
},
  "geometry": {"coordinates":[153.065048,-27.43371],"type":"Point"}
}