{
  "type": "Feature",
  "properties": {
    "iso:country":"AU",
    "sg:address":"Shop 52-53, Port Central Shopping Centre, 40 - 42 Horton Street",
    "sg:city":"Port Macquarie",
    "sg:classifiers":[
        {
            "category":"Travel",
            "subcategory":"Travel Agent",
            "type":"Entertainment"
        }
    ],
    "sg:phone":"+61 2 6584 0690",
    "sg:postcode":"2444",
    "sg:province":"NSW",
    "sg:tags":[
        "consultant"
    ],
    "wof:name":"Flight Centre",
    "wof:placetype":"venue"
},
  "geometry": {"coordinates":[152.908356,-31.429701],"type":"Point"}
}