{
  "type": "Feature",
  "properties": {
    "addr:full":"16 Paula Ave Windsor Gardens SA 5087",
    "addr:housenumber":"16",
    "addr:postcode":"5087",
    "addr:street":"Paula Ave",
    "iso:country":"AU",
    "sg:address":"16 Paula Ave",
    "sg:city":"Windsor Gardens",
    "sg:classifiers":[
        {
            "category":"Retail",
            "subcategory":"Auto Repair",
            "type":"Services"
        }
    ],
    "sg:phone":"+61 8 8266 4488",
    "sg:postcode":"5087",
    "sg:province":"SA",
    "sg:tags":[
        "repairer",
        "motor",
        "engineer"
    ],
    "wof:name":"Paks Auto Services",
    "wof:placetype":"venue"
},
  "geometry": {"coordinates":[138.65040588400001,-34.8630638123],"type":"Point"}
}