{
  "type": "Feature",
  "properties": {
    "addr:full":"120 Prospect Rd Prospect SA 5082",
    "addr:housenumber":"120",
    "addr:postcode":"5082",
    "addr:street":"Prospect Rd",
    "iso:country":"AU",
    "sg:address":"120 Prospect Rd",
    "sg:city":"Prospect",
    "sg:classifiers":[
        {
            "category":"Train Station",
            "subcategory":"Light Rail",
            "type":"Transportation"
        }
    ],
    "sg:phone":"+61 8 8344 7298",
    "sg:postcode":"5082",
    "sg:province":"SA",
    "sg:tags":[
        "equipment",
        "energy",
        "solar"
    ],
    "wof:name":"Natural Technology Systems",
    "wof:placetype":"venue"
},
  "geometry": {"coordinates":[138.593826294,-34.8866920471],"type":"Point"}
}