{
  "type": "Feature",
  "properties": {
    "addr:full":"114 Leahy Rd Caboolture QLD 4510",
    "addr:housenumber":"114",
    "addr:postcode":"4510",
    "addr:street":"Leahy Rd",
    "iso:country":"AU",
    "sg:address":"114 Leahy Rd",
    "sg:city":"Caboolture",
    "sg:classifiers":[
        {
            "category":"Farming",
            "subcategory":"Nursery",
            "type":"Manufacturing & Wholesale Goods"
        }
    ],
    "sg:phone":"+61 7 5499 0460",
    "sg:postcode":"4510",
    "sg:province":"QLD",
    "wof:name":"Topiary Madness",
    "wof:placetype":"venue"
},
  "geometry": {"coordinates":[152.98774700000001,-27.062712],"type":"Point"}
}