{
  "type": "Feature",
  "properties": {
    "addr:full":"16 Depot Rd Peakhurst NSW 2210",
    "addr:housenumber":"16",
    "addr:postcode":"2210",
    "addr:street":"Depot Rd",
    "iso:country":"AU",
    "sg:address":"16 Depot Rd",
    "sg:city":"Peakhurst",
    "sg:classifiers":[
        {
            "category":"Shopping",
            "subcategory":"Antiques",
            "type":"Retail Goods"
        }
    ],
    "sg:phone":"+61 2 9533 9666",
    "sg:postcode":"2210",
    "sg:province":"NSW",
    "sg:tags":[
        "restoration",
        "reproduction"
    ],
    "wof:name":"Hallmark Furniture (Aust) Pty Ltd",
    "wof:placetype":"venue"
},
  "geometry": {"coordinates":[151.06343100000001,-33.96759],"type":"Point"}
}