{
  "type": "Feature",
  "properties": {
    "addr:full":"3 Electra St Williamstown VIC 3016",
    "addr:housenumber":"3",
    "addr:postcode":"3016",
    "addr:street":"Electra St",
    "iso:country":"AU",
    "sg:address":"3 Electra St",
    "sg:city":"Williamstown",
    "sg:classifiers":[
        {
            "category":"Travel",
            "subcategory":"Hotels & Motels",
            "type":"Entertainment"
        }
    ],
    "sg:phone":"+61 3 9397 6082",
    "sg:postcode":"3016",
    "sg:province":"VIC",
    "sg:tags":[
        "accommodation"
    ],
    "wof:name":"Morning Star Hotel",
    "wof:placetype":"venue"
},
  "geometry": {"coordinates":[144.89906310999999,-37.8640518188],"type":"Point"}
}