{
  "type": "Feature",
  "properties": {
    "addr:full":"Unit 10/ 78 Reserve Rd Artarmon NSW 2064",
    "addr:housenumber":"/ 78",
    "addr:postcode":"2064",
    "addr:street":"Reserve Rd",
    "iso:country":"AU",
    "sg:address":"Unit 10/ 78 Reserve Rd",
    "sg:city":"Artarmon",
    "sg:classifiers":[
        {
            "category":"Shopping",
            "subcategory":"Computers & Home Electronics",
            "type":"Retail Goods"
        }
    ],
    "sg:phone":"+61 2 9906 8228",
    "sg:postcode":"2064",
    "sg:province":"NSW",
    "sg:tags":[
        "hardware",
        "equipment"
    ],
    "wof:name":"Apek Computers",
    "wof:placetype":"venue"
},
  "geometry": {"coordinates":[151.18850707999999,-33.8183631897],"type":"Point"}
}