{
  "type": "Feature",
  "properties": {
    "addr:full":"20 Quarry Rd Dural NSW 2158",
    "addr:housenumber":"20",
    "addr:postcode":"2158",
    "addr:street":"Quarry Rd",
    "iso:country":"AU",
    "sg:address":"20 Quarry Rd",
    "sg:city":"Dural",
    "sg:classifiers":[
        {
            "category":"Autos & Motor Vehicles",
            "subcategory":"Auto Supplies",
            "type":"Retail Goods"
        }
    ],
    "sg:phone":"+61 2 9651 5677",
    "sg:postcode":"2158",
    "sg:province":"NSW",
    "sg:tags":[
        "car",
        "alarm"
    ],
    "wof:name":"T & K Security Pty Ltd",
    "wof:placetype":"venue"
},
  "geometry": {"coordinates":[151.03947448700001,-33.697227478],"type":"Point"}
}