{
  "type": "Feature",
  "properties": {
    "iso:country":"AU",
    "sg:address":"142 Deanmore Rd",
    "sg:city":"Scarborough",
    "sg:classifiers":[
        {
            "category":"Shopping",
            "subcategory":"Party Supplies",
            "type":"Retail Goods"
        }
    ],
    "sg:phone":"+61 8 9341 4219",
    "sg:postcode":"6019",
    "sg:province":"WA",
    "sg:tags":[
        "hire",
        "costume"
    ],
    "wof:name":"Fun Room The",
    "wof:placetype":"venue"
},
  "geometry": {"coordinates":[115.76789092999999,-31.8955936432],"type":"Point"}
}