{
  "type": "Feature",
  "properties": {
    "addr:full":"5a Napoleon St Sans Souci NSW 2219",
    "addr:housenumber":"5a",
    "addr:postcode":"2219",
    "addr:street":"Napoleon St",
    "iso:country":"AU",
    "sg:address":"5a Napoleon St",
    "sg:city":"Sans Souci",
    "sg:classifiers":[
        {
            "category":"Building & Trades",
            "subcategory":"Construction",
            "type":"Services"
        }
    ],
    "sg:phone":"+61 2 9529 0644",
    "sg:postcode":"2219",
    "sg:province":"NSW",
    "sg:tags":[
        "contractor"
    ],
    "wof:name":"Precise-Lee Building",
    "wof:placetype":"venue"
},
  "geometry": {"coordinates":[151.135895,-33.9981],"type":"Point"}
}