{
  "type": "Feature",
  "properties": {
    "addr:full":"275- 277 Burwood Hwy Burwood East VIC 3151",
    "addr:housenumber":"277",
    "addr:postcode":"3151",
    "addr:street":"Burwood Hwy",
    "iso:country":"AU",
    "sg:address":"275- 277 Burwood Hwy",
    "sg:city":"Burwood East",
    "sg:classifiers":[
        {
            "category":"Health Services",
            "subcategory":"Doctor",
            "type":"Services"
        }
    ],
    "sg:phone":"+61 3 9886 8077",
    "sg:postcode":"3151",
    "sg:province":"VIC",
    "sg:tags":[
        "medical",
        "practitioner"
    ],
    "wof:name":"Hii D O",
    "wof:placetype":"venue"
},
  "geometry": {"coordinates":[145.15818786599999,-37.8532562256],"type":"Point"}
}