{
  "type": "Feature",
  "properties": {
    "iso:country":"AU",
    "sg:address":"Commercial St West",
    "sg:city":"Mt Gambier",
    "sg:classifiers":[
        {
            "category":"Sports & Exercise",
            "subcategory":"Sports Center",
            "type":"Entertainment"
        }
    ],
    "sg:phone":"+61 8 8723 2050",
    "sg:postcode":"5290",
    "sg:province":"SA",
    "sg:tags":[
        "ground"
    ],
    "wof:name":"Mt Gambier Basketball Stadium",
    "wof:placetype":"venue"
},
  "geometry": {"coordinates":[140.78009,-37.828213],"type":"Point"}
}