{
  "type": "Feature",
  "properties": {
    "addr:full":"Unit 3/ 78-80 Bellingara Rd Miranda NSW 2228",
    "addr:housenumber":"/ 78-80",
    "addr:postcode":"2228",
    "addr:street":"Bellingara Rd",
    "iso:country":"AU",
    "sg:address":"Unit 3/ 78-80 Bellingara Rd",
    "sg:city":"Miranda",
    "sg:classifiers":[
        {
            "category":"Home & Garden",
            "subcategory":"Hardware",
            "type":"Retail Goods"
        }
    ],
    "sg:phone":"+61 2 9544 8854",
    "sg:postcode":"2228",
    "sg:province":"NSW",
    "sg:tags":[
        "part",
        "air conditioning"
    ],
    "wof:name":"Blend Air Pty Ltd",
    "wof:placetype":"venue"
},
  "geometry": {"coordinates":[151.10223388700001,-34.0235214233],"type":"Point"}
}