{
  "type": "Feature",
  "properties": {
    "addr:full":"Shp 5/ 144 Polding St Fairfield Heights NSW 2165",
    "addr:housenumber":"/ 144",
    "addr:postcode":"2165",
    "addr:street":"Polding St",
    "iso:country":"AU",
    "sg:address":"Shp 5/ 144 Polding St",
    "sg:city":"Fairfield Heights",
    "sg:classifiers":[
        {
            "category":"Professional",
            "subcategory":"Accounting & Tax Preparation",
            "type":"Services"
        }
    ],
    "sg:phone":"+61 2 9725 1422",
    "sg:postcode":"2165",
    "sg:province":"NSW",
    "sg:tags":[
        "consultant",
        "taxation"
    ],
    "wof:name":"AM Finanz",
    "wof:placetype":"venue"
},
  "geometry": {"coordinates":[150.93951415999999,-33.8618888855],"type":"Point"}
}