{
  "type": "Feature",
  "properties": {
    "iso:country":"AU",
    "sg:address":"93 Gellibrand St",
    "sg:city":"Colac",
    "sg:classifiers":[
        {
            "category":"Health Services",
            "subcategory":"Doctor",
            "type":"Services"
        }
    ],
    "sg:phone":"+61 1300 654 456",
    "sg:postcode":"3250",
    "sg:province":"VIC",
    "sg:tags":[
        "medical",
        "practitioner"
    ],
    "wof:name":"Dance Geoffrey Mr",
    "wof:placetype":"venue"
},
  "geometry": {"coordinates":[143.586884,-38.338684],"type":"Point"}
}