{
  "type": "Feature",
  "properties": {
    "addr:full":"10 Campaspe Mews Bendigo VIC 3550",
    "addr:housenumber":"10",
    "addr:postcode":"3550",
    "addr:street":"Campaspe Mews",
    "iso:country":"AU",
    "sg:address":"10 Campaspe Mews",
    "sg:city":"Bendigo",
    "sg:classifiers":[
        {
            "category":"Home & Garden",
            "subcategory":"Carpets & Floor Coverings",
            "type":"Retail Goods"
        }
    ],
    "sg:phone":"+61 418 417 577",
    "sg:postcode":"3550",
    "sg:province":"VIC",
    "sg:tags":[
        "mat",
        "matting"
    ],
    "wof:name":"Slippery Solutions",
    "wof:placetype":"venue"
},
  "geometry": {"coordinates":[144.31214904800001,-36.7777290344],"type":"Point"}
}