{
  "type": "Feature",
  "properties": {
    "addr:full":"2nd Floor, 20- 26 President Ave Caringbah NSW 2229",
    "addr:housenumber":"20 26",
    "addr:postcode":"2229",
    "addr:street":"President Ave",
    "iso:country":"AU",
    "sg:address":"2nd Floor, 20- 26 President Ave",
    "sg:city":"Caringbah",
    "sg:classifiers":[
        {
            "category":"Arena",
            "subcategory":"Sports Club",
            "type":"Entertainment"
        }
    ],
    "sg:phone":"+61 2 9525 5799",
    "sg:postcode":"2229",
    "sg:province":"NSW",
    "sg:tags":[
        "defence",
        "supply",
        "self",
        "instruction",
        "martial art"
    ],
    "wof:name":"Taekwondo",
    "wof:placetype":"venue"
},
  "geometry": {"coordinates":[151.12188720699999,-34.0430908203],"type":"Point"}
}