{
  "type": "Feature",
  "properties": {
    "iso:country":"AU",
    "sg:address":"29a Beachton St",
    "sg:city":"North Beach",
    "sg:classifiers":[
        {
            "category":"Building & Trades",
            "subcategory":"Landscaping Services",
            "type":"Services"
        }
    ],
    "sg:phone":"+61 8 9447 6919",
    "sg:postcode":"6020",
    "sg:province":"WA",
    "sg:tags":[
        "designer",
        "landscape",
        "contractor"
    ],
    "wof:name":"Allusion Landscapes",
    "wof:placetype":"venue"
},
  "geometry": {"coordinates":[115.754966736,-31.8620281219],"type":"Point"}
}