{
  "type": "Feature",
  "properties": {
    "addr:full":"2/ 30 Onslow Ave Campbellfield VIC 3061",
    "addr:housenumber":"/ 30",
    "addr:postcode":"3061",
    "addr:street":"Onslow Ave",
    "iso:country":"AU",
    "sg:address":"2/ 30 Onslow Ave",
    "sg:city":"Campbellfield",
    "sg:classifiers":[
        {
            "category":"Wholesale",
            "subcategory":"Photographic Equipment",
            "type":"Manufacturing & Wholesale Goods"
        }
    ],
    "sg:phone":"+61 3 9359 9973",
    "sg:postcode":"3061",
    "sg:province":"VIC",
    "sg:tags":[
        "wholesaler",
        "mfrs",
        "supply"
    ],
    "wof:name":"Poly Pockets Pty Ltd",
    "wof:placetype":"venue"
},
  "geometry": {"coordinates":[144.964935303,-37.6877593994],"type":"Point"}
}