{
  "type": "Feature",
  "properties": {
    "iso:country":"AU",
    "sg:address":"31 College St",
    "sg:city":"Hamilton",
    "sg:classifiers":[
        {
            "category":"Professional",
            "subcategory":"Accounting & Tax Preparation",
            "type":"Services"
        }
    ],
    "sg:phone":"+61 7 3868 4911",
    "sg:postcode":"4007",
    "sg:province":"QLD",
    "sg:tags":[
        "accountant",
        "auditor"
    ],
    "wof:name":"vxpartner",
    "wof:placetype":"venue"
},
  "geometry": {"coordinates":[153.075592,-27.434031],"type":"Point"}
}