{
  "type": "Feature",
  "properties": {
    "addr:full":"Colarado Drv Blue Haven NSW 2262",
    "addr:postcode":"2262",
    "addr:street":"Colarado Drv",
    "iso:country":"AU",
    "sg:address":"Colarado Drv",
    "sg:city":"Blue Haven",
    "sg:classifiers":[
        {
            "category":"Building & Trades",
            "subcategory":"Construction",
            "type":"Services"
        }
    ],
    "sg:phone":"+61 2 4390 8444",
    "sg:postcode":"2262",
    "sg:province":"NSW",
    "sg:tags":[
        "contractor"
    ],
    "wof:name":"Sydney Housing Company",
    "wof:placetype":"venue"
},
  "geometry": {"coordinates":[151.51147499999999,-33.212067],"type":"Point"}
}