{
  "type": "Feature",
  "properties": {
    "addr:full":"19 Mallee St Murrumba Downs QLD 4503",
    "addr:housenumber":"19",
    "addr:postcode":"4503",
    "addr:street":"Mallee St",
    "iso:country":"AU",
    "sg:address":"19 Mallee St",
    "sg:city":"Murrumba Downs",
    "sg:classifiers":[
        {
            "category":"Building & Trades",
            "subcategory":"Construction",
            "type":"Services"
        }
    ],
    "sg:phone":"+61 7 3886 4363",
    "sg:postcode":"4503",
    "sg:province":"QLD",
    "sg:tags":[
        "contractor"
    ],
    "wof:name":"Barry Dutton",
    "wof:placetype":"venue"
},
  "geometry": {"coordinates":[153.00103759800001,-27.258764267],"type":"Point"}
}