{
  "type": "Feature",
  "properties": {
    "iso:country":"AU",
    "sg:address":"19 Mallee St",
    "sg:city":"Murrumba Downs",
    "sg:classifiers":[
        {
            "category":"Building & Trades",
            "subcategory":"Construction",
            "type":"Services"
        }
    ],
    "sg:phone":"+61 7 3886 4363",
    "sg:postcode":"4503",
    "sg:province":"QLD",
    "sg:tags":[
        "contractor"
    ],
    "wof:name":"Barry Dutton",
    "wof:placetype":"venue"
},
  "geometry": {"coordinates":[153.00103759800001,-27.258764267],"type":"Point"}
}