{
  "type": "Feature",
  "properties": {
    "addr:full":"Cnr Darling & Church Sts Dubbo NSW 2830",
    "addr:postcode":"2830",
    "iso:country":"AU",
    "sg:address":"Cnr Darling & Church Sts",
    "sg:city":"Dubbo",
    "sg:classifiers":[
        {
            "category":"Professional",
            "subcategory":"Accounting & Tax Preparation",
            "type":"Services"
        }
    ],
    "sg:phone":"+61 2 6882 3933",
    "sg:postcode":"2830",
    "sg:province":"NSW",
    "sg:tags":[
        "accountant",
        "auditor"
    ],
    "wof:name":"Peacocke G F B & Co",
    "wof:placetype":"venue"
},
  "geometry": {"coordinates":[148.60604858400001,-32.2486076355],"type":"Point"}
}