{
  "type": "Feature",
  "properties": {
    "addr:full":"8 Bream St Coogee NSW 2034",
    "addr:housenumber":"8",
    "addr:postcode":"2034",
    "addr:street":"Bream St",
    "iso:country":"AU",
    "sg:address":"8 Bream St",
    "sg:city":"Coogee",
    "sg:classifiers":[
        {
            "category":"Health Services",
            "subcategory":"Doctor",
            "type":"Services"
        }
    ],
    "sg:phone":"+61 2 9665 0330",
    "sg:postcode":"2034",
    "sg:province":"NSW",
    "sg:tags":[
        "medical",
        "practitioner"
    ],
    "wof:name":"Bream Street Medical Practise",
    "wof:placetype":"venue"
},
  "geometry": {"coordinates":[151.249237061,-33.9170074463],"type":"Point"}
}