{
  "type": "Feature",
  "properties": {
    "iso:country":"AU",
    "sg:address":"16 Luland St",
    "sg:city":"Botany",
    "sg:classifiers":[
        {
            "category":"Professional",
            "type":"Services"
        }
    ],
    "sg:phone":"+61 2 9700 1919",
    "sg:postcode":"2019",
    "sg:province":"NSW",
    "sg:tags":[
        "forwarding",
        "agent",
        "transport"
    ],
    "wof:name":"P & L Freight Services Pty Ltd",
    "wof:placetype":"venue"
},
  "geometry": {"coordinates":[151.191696167,-33.9461593628],"type":"Point"}
}