{
  "type": "Feature",
  "properties": {
    "addr:full":"704 Merrylands Rd Greystanes NSW 2145",
    "addr:housenumber":"704",
    "addr:postcode":"2145",
    "addr:street":"Merrylands Rd",
    "iso:country":"AU",
    "sg:address":"704 Merrylands Rd",
    "sg:city":"Greystanes",
    "sg:classifiers":[
        {
            "category":"Health Services",
            "subcategory":"Doctor",
            "type":"Services"
        }
    ],
    "sg:phone":"+61 2 9631 9168",
    "sg:postcode":"2145",
    "sg:province":"NSW",
    "sg:tags":[
        "medical",
        "practitioner"
    ],
    "wof:name":"Greysmead Pty Ltd",
    "wof:placetype":"venue"
},
  "geometry": {"coordinates":[150.944213867,-33.8291397095],"type":"Point"}
}