{
  "type": "Feature",
  "properties": {
    "addr:full":"30 Flora St Kirrawee NSW 2232",
    "addr:housenumber":"30",
    "addr:postcode":"2232",
    "addr:street":"Flora St",
    "iso:country":"AU",
    "sg:address":"30 Flora St",
    "sg:city":"Kirrawee",
    "sg:classifiers":[
        {
            "category":"Real Estate",
            "subcategory":"Real Estate Agent",
            "type":"Services"
        }
    ],
    "sg:phone":"+61 2 9521 1382",
    "sg:postcode":"2232",
    "sg:province":"NSW",
    "sg:tags":[
        "steel",
        "foundry",
        "iron"
    ],
    "wof:name":"Kirrawee Castings Pty Ltd",
    "wof:placetype":"venue"
},
  "geometry": {"coordinates":[151.07281494099999,-34.0340461731],"type":"Point"}
}