{
  "type": "Feature",
  "properties": {
    "addr:full":"5/ 135 Great Eastern Hwy Belmont WA 6104",
    "addr:housenumber":"/ 135",
    "addr:postcode":"6104",
    "addr:street":"Great Eastern Hwy",
    "iso:country":"AU",
    "sg:address":"5/ 135 Great Eastern Hwy",
    "sg:city":"Belmont",
    "sg:classifiers":[
        {
            "category":"Wholesale",
            "subcategory":"Metals & Minerals",
            "type":"Manufacturing & Wholesale Goods"
        }
    ],
    "sg:phone":"+61 8 9479 1596",
    "sg:postcode":"6104",
    "sg:province":"WA",
    "sg:tags":[
        "steel",
        "stainless",
        "product",
        "equipment"
    ],
    "wof:name":"Mardale P.C.I Australia Pty Ltd",
    "wof:placetype":"venue"
},
  "geometry": {"coordinates":[115.922706604,-31.9522972107],"type":"Point"}
}