{
  "type": "Feature",
  "properties": {
    "addr:full":"71 Delaneys Creek School Rd Delaneys Creek QLD 4514",
    "addr:housenumber":"71",
    "addr:postcode":"4514",
    "addr:street":"Delaneys Creek School Rd",
    "iso:country":"AU",
    "sg:address":"71 Delaneys Creek School Rd",
    "sg:city":"Delaneys Creek",
    "sg:classifiers":[
        {
            "category":"Building & Trades",
            "subcategory":"Construction",
            "type":"Services"
        }
    ],
    "sg:phone":"+61 419 736 215",
    "sg:postcode":"4514",
    "sg:province":"QLD",
    "sg:tags":[
        "contractor"
    ],
    "wof:name":"Glen Wilkie",
    "wof:placetype":"venue"
},
  "geometry": {"coordinates":[152.79939300000001,-26.996962],"type":"Point"}
}