{
  "type": "Feature",
  "properties": {
    "addr:full":"28 Ormond St Pascoe Vale VIC 3044",
    "addr:housenumber":"28",
    "addr:postcode":"3044",
    "addr:street":"Ormond St",
    "iso:country":"AU",
    "sg:address":"28 Ormond St",
    "sg:city":"Pascoe Vale",
    "sg:classifiers":[
        {
            "category":"Shopping",
            "subcategory":"Gifts & Souvenirs",
            "type":"Retail Goods"
        }
    ],
    "sg:phone":"+61 3 9354 0531",
    "sg:postcode":"3044",
    "sg:province":"VIC",
    "sg:tags":[
        "print",
        "poster",
        "pictures"
    ],
    "wof:name":"Encoe Australia",
    "wof:placetype":"venue"
},
  "geometry": {"coordinates":[144.94235229500001,-37.7242660522],"type":"Point"}
}