{
  "type": "Feature",
  "properties": {
    "addr:full":"Factory 4, 55 Dingley Ave Dandenong VIC 3175",
    "addr:housenumber":"55",
    "addr:postcode":"3175",
    "addr:street":"Dingley Ave",
    "iso:country":"AU",
    "sg:address":"Factory 4, 55 Dingley Ave",
    "sg:city":"Dandenong",
    "sg:classifiers":[
        {
            "category":"Wholesale",
            "subcategory":"Construction Materials",
            "type":"Manufacturing & Wholesale Goods"
        }
    ],
    "sg:phone":"+61 3 9792 0722",
    "sg:postcode":"3175",
    "sg:province":"VIC",
    "sg:tags":[
        "protective",
        "coating"
    ],
    "wof:name":"Australian Hi-Tech Fabric Protection Pty Ltd",
    "wof:placetype":"venue"
},
  "geometry": {"coordinates":[145.1953125,-37.9969520569],"type":"Point"}
}