{
  "type": "Feature",
  "properties": {
    "iso:country":"AU",
    "sg:address":"415 Goodwood Rd",
    "sg:city":"Westbourne Park",
    "sg:classifiers":[
        {
            "category":"Health Services",
            "subcategory":"Optometrist",
            "type":"Services"
        }
    ],
    "sg:phone":"+61 8 8373 2200",
    "sg:postcode":"5041",
    "sg:province":"SA",
    "wof:name":"Orthokeratology Centre",
    "wof:placetype":"venue"
},
  "geometry": {"coordinates":[138.591476,-34.97316],"type":"Point"}
}