{
  "type": "Feature",
  "properties": {
    "iso:country":"AU",
    "sg:address":"Shop 1/ 2705 Gold Coast Hwy",
    "sg:city":"Broadbeach",
    "sg:classifiers":[
        {
            "category":"Fast Food",
            "type":"Food & Drink"
        }
    ],
    "sg:phone":"+61 7 5592 3738",
    "sg:postcode":"4218",
    "sg:province":"QLD",
    "sg:tags":[
        "away",
        "take"
    ],
    "wof:name":"Rossini Italian Restaurant",
    "wof:placetype":"venue"
},
  "geometry": {"coordinates":[153.43028259299999,-28.0291938782],"type":"Point"}
}