{
  "type": "Feature",
  "properties": {
    "addr:full":"7 Victoria St Wandin North VIC 3139",
    "addr:housenumber":"7",
    "addr:postcode":"3139",
    "addr:street":"Victoria St",
    "iso:country":"AU",
    "sg:address":"7 Victoria St",
    "sg:city":"Wandin North",
    "sg:classifiers":[
        {
            "category":"Building & Trades",
            "subcategory":"Construction",
            "type":"Services"
        }
    ],
    "sg:phone":"+61 3 5964 3304",
    "sg:postcode":"3139",
    "sg:province":"VIC",
    "sg:tags":[
        "earth",
        "excavating",
        "moving",
        "contractor"
    ],
    "wof:name":"Meyland Constructions Pty Ltd",
    "wof:placetype":"venue"
},
  "geometry": {"coordinates":[145.410552978,-37.7724456787],"type":"Point"}
}