{
  "type": "Feature",
  "properties": {
    "addr:full":"Level 1/44- 52 Townshend St Phillip ACT 2606",
    "addr:housenumber":"/;52",
    "addr:postcode":"2606",
    "addr:street":"44;Townshend St",
    "iso:country":"AU",
    "sg:address":"Level 1/44- 52 Townshend St",
    "sg:city":"Phillip",
    "sg:classifiers":[
        {
            "category":"Banks & Credit Unions",
            "subcategory":"Investment Brokerage",
            "type":"Services"
        }
    ],
    "sg:phone":"+61 2 6162 0055",
    "sg:postcode":"2606",
    "sg:province":"ACT",
    "sg:tags":[
        "management",
        "property"
    ],
    "wof:name":"RE/MAX Advantage",
    "wof:placetype":"venue"
},
  "geometry": {"coordinates":[149.08839416500001,-35.3536529541],"type":"Point"}
}