{
  "type": "Feature",
  "properties": {
    "addr:full":"Shop 73 Stockland Shopng Cntr 537 Mulgrave Rd Earlville QLD 4870",
    "addr:housenumber":"shop 73;537",
    "addr:postcode":"4870",
    "addr:street":"Mulgrave Rd",
    "iso:country":"AU",
    "sg:address":"Shop 73 Stockland Shopng Cntr 537 Mulgrave Rd",
    "sg:city":"Earlville",
    "sg:classifiers":[
        {
            "category":"Travel",
            "subcategory":"Travel Agent",
            "type":"Entertainment"
        }
    ],
    "sg:phone":"+61 13 18 66",
    "sg:postcode":"4870",
    "sg:province":"QLD",
    "sg:tags":[
        "consultant"
    ],
    "wof:name":"Flight Centre",
    "wof:placetype":"venue"
},
  "geometry": {"coordinates":[145.73860168499999,-16.945941925],"type":"Point"}
}