{
  "type": "Feature",
  "properties": {
    "addr:full":"160a Magill Rd Norwood SA 5067",
    "addr:housenumber":"160a",
    "addr:postcode":"5067",
    "addr:street":"Magill Rd",
    "iso:country":"AU",
    "sg:address":"160a Magill Rd",
    "sg:city":"Norwood",
    "sg:classifiers":[
        {
            "category":"Health Services",
            "subcategory":"Health Practitioner",
            "type":"Services"
        }
    ],
    "sg:phone":"+61 412 091 730",
    "sg:postcode":"5067",
    "sg:province":"SA",
    "sg:tags":[
        "bowen",
        "therapy"
    ],
    "wof:name":"Carolyn Wild",
    "wof:placetype":"venue"
},
  "geometry": {"coordinates":[138.635131836,-34.9151878357],"type":"Point"}
}