{
  "type": "Feature",
  "properties": {
    "addr:full":"PO Box 533 Brunswick VIC 3056",
    "addr:postcode":"3056",
    "iso:country":"AU",
    "sg:address":"PO Box 533",
    "sg:city":"Brunswick",
    "sg:classifiers":[
        {
            "category":"Building & Trades",
            "subcategory":"Landscaping Services",
            "type":"Services"
        }
    ],
    "sg:phone":"+61 414 260 163",
    "sg:postcode":"3056",
    "sg:province":"VIC",
    "sg:tags":[
        "designer",
        "landscape",
        "contractor"
    ],
    "wof:name":"Small Spaces",
    "wof:placetype":"venue"
},
  "geometry": {"coordinates":[144.96284484899999,-37.7666893005],"type":"Point"}
}