{
  "type": "Feature",
  "properties": {
    "addr:full":"PO Box 2975 Taren Point NSW 2229",
    "addr:postcode":"2229",
    "iso:country":"AU",
    "sg:address":"PO Box 2975",
    "sg:city":"Taren Point",
    "sg:classifiers":[
        {
            "category":"Professional",
            "subcategory":"Printing & Photocopies",
            "type":"Services"
        }
    ],
    "sg:phone":"+61 2 9531 8444",
    "sg:postcode":"2229",
    "sg:province":"NSW",
    "sg:tags":[
        "embroidery"
    ],
    "wof:name":"Be Promoted Embroidery Business Apparel",
    "wof:placetype":"venue"
},
  "geometry": {"coordinates":[151.123336792,-34.0180511475],"type":"Point"}
}