{
  "type": "Feature",
  "properties": {
    "iso:country":"AU",
    "sg:address":"10/ 50 Banksia Rd",
    "sg:city":"Welshpool",
    "sg:classifiers":[
        {
            "category":"Building & Trades",
            "subcategory":"Construction",
            "type":"Services"
        }
    ],
    "sg:phone":"+61 8 9356 3114",
    "sg:postcode":"6106",
    "sg:province":"WA",
    "sg:tags":[
        "monumental",
        "mason"
    ],
    "wof:name":"Stewart Masonry",
    "wof:placetype":"venue"
},
  "geometry": {"coordinates":[115.962341309,-31.9958114624],"type":"Point"}
}