{
  "type": "Feature",
  "properties": {
    "iso:country":"AU",
    "sg:address":"Commins St",
    "sg:city":"Junee",
    "sg:classifiers":[
        {
            "category":"Sports & Exercise",
            "subcategory":"Sports Center",
            "type":"Entertainment"
        }
    ],
    "sg:phone":"+61 2 6924 1500",
    "sg:postcode":"2663",
    "sg:province":"NSW",
    "sg:tags":[
        "ground"
    ],
    "wof:name":"Junee Sports Centre",
    "wof:placetype":"venue"
},
  "geometry": {"coordinates":[147.58729553200001,-34.8690261841],"type":"Point"}
}