{
  "type": "Feature",
  "properties": {
    "iso:country":"AU",
    "sg:address":"Bloomfield Rd",
    "sg:city":"Bloomfield",
    "sg:classifiers":[
        {
            "category":"Fast Food",
            "type":"Food & Drink"
        }
    ],
    "sg:phone":"+61 7 4060 8174",
    "sg:postcode":"4871",
    "sg:province":"QLD",
    "sg:tags":[
        "away",
        "take"
    ],
    "wof:name":"Bloomfield River Inn",
    "wof:placetype":"venue"
},
  "geometry": {"coordinates":[145.24177551299999,-15.7415838242],"type":"Point"}
}