{
  "type": "Feature",
  "properties": {
    "addr:full":"Windsor Rd (cnr Blaxland Rd) Burnside QLD 4560",
    "addr:postcode":"4560",
    "addr:street":"Windsor Rd Cnr Blaxland Rd",
    "iso:country":"AU",
    "sg:address":"Windsor Rd",
    "sg:city":"(cnr Blaxland Rd) Burnside",
    "sg:classifiers":[
        {
            "category":"Education",
            "subcategory":"School",
            "type":"Public Place"
        }
    ],
    "sg:phone":"+61 7 5441 3668",
    "sg:postcode":"4560",
    "sg:province":"QLD",
    "sg:tags":[
        "state",
        "except",
        "nsw"
    ],
    "wof:name":"Burnside Preschool",
    "wof:placetype":"venue"
},
  "geometry": {"coordinates":[152.93333435100001,-26.621055603],"type":"Point"}
}