{
  "type": "Feature",
  "properties": {
    "iso:country":"AU",
    "sg:address":"96 Auburn St",
    "sg:city":"Wollongong",
    "sg:classifiers":[
        {
            "category":"Autos & Motor Vehicles",
            "subcategory":"Auto Supplies",
            "type":"Retail Goods"
        }
    ],
    "sg:phone":"+61 410 373 021",
    "sg:postcode":"2500",
    "sg:province":"NSW",
    "sg:tags":[
        "part",
        "cycles",
        "accessory"
    ],
    "wof:name":"Factory Element",
    "wof:placetype":"venue"
},
  "geometry": {"coordinates":[150.88781700000001,-34.434055],"type":"Point"}
}