{
  "type": "Feature",
  "properties": {
    "addr:full":"15 Sovereign Rd Amity Point QLD 4183",
    "addr:housenumber":"15",
    "addr:postcode":"4183",
    "addr:street":"Sovereign Rd",
    "iso:country":"AU",
    "sg:address":"15 Sovereign Rd",
    "sg:city":"Amity Point",
    "sg:classifiers":[
        {
            "category":"Real Estate",
            "subcategory":"Real Estate Agent",
            "type":"Services"
        }
    ],
    "sg:phone":"+61 7 3409 7126",
    "sg:postcode":"4183",
    "sg:province":"QLD",
    "wof:name":"Stradbroke Realty Rentals",
    "wof:placetype":"venue"
},
  "geometry": {"coordinates":[153.44340515100001,-27.3950252533],"type":"Point"}
}