{
  "type": "Feature",
  "properties": {
    "iso:country":"AU",
    "sg:address":"498 Nudgee Rd",
    "sg:city":"Hendra",
    "sg:classifiers":[
        {
            "category":"Professional",
            "subcategory":"Accounting & Tax Preparation",
            "type":"Services"
        }
    ],
    "sg:phone":"+61 1800 445 444",
    "sg:postcode":"4011",
    "sg:province":"QLD",
    "sg:tags":[
        "broom",
        "brush"
    ],
    "wof:name":"Josco Industrial Agencies (Vic) Pty Ltd",
    "wof:placetype":"venue"
},
  "geometry": {"coordinates":[153.074677,-27.408855],"type":"Point"}
}