{
  "type": "Feature",
  "properties": {
    "addr:full":"215 Melbourne St North Adelaide SA 5006",
    "addr:housenumber":"215",
    "addr:postcode":"5006",
    "addr:street":"Melbourne St",
    "iso:country":"AU",
    "sg:address":"215 Melbourne St",
    "sg:city":"North Adelaide",
    "sg:classifiers":[
        {
            "category":"Health Services",
            "subcategory":"Doctor",
            "type":"Services"
        }
    ],
    "sg:phone":"+61 8 8239 0027",
    "sg:postcode":"5006",
    "sg:province":"SA",
    "sg:tags":[
        "medical",
        "practitioner"
    ],
    "wof:name":"Accident & Injury Assessment Clinics",
    "wof:placetype":"venue"
},
  "geometry": {"coordinates":[138.60403442399999,-34.9087104797],"type":"Point"}
}