{
  "type": "Feature",
  "properties": {
    "iso:country":"AU",
    "sg:address":"Paradise Point Shopping Village Grice Ave",
    "sg:city":"Paradise Point",
    "sg:classifiers":[
        {
            "category":"Personal",
            "subcategory":"Beauty Salon",
            "type":"Services"
        }
    ],
    "sg:phone":"+61 7 5577 2564",
    "sg:postcode":"4216",
    "sg:province":"QLD",
    "sg:tags":[
        "hairdresser"
    ],
    "wof:name":"Beauty Spot Hair Stylists",
    "wof:placetype":"venue"
},
  "geometry": {"coordinates":[153.394454956,-27.8858509064],"type":"Point"}
}