{
  "type": "Feature",
  "properties": {
    "addr:full":"169 School Of Arts Rd Redland Bay QLD 4165",
    "addr:housenumber":"169",
    "addr:postcode":"4165",
    "addr:street":"Rd",
    "iso:country":"AU",
    "sg:address":"169 School Of Arts Rd",
    "sg:city":"Redland Bay",
    "sg:classifiers":[
        {
            "category":"Home & Garden",
            "subcategory":"Building Materials",
            "type":"Retail Goods"
        }
    ],
    "sg:phone":"+61 7 3206 8683",
    "sg:postcode":"4165",
    "sg:province":"QLD",
    "sg:tags":[
        "lawn",
        "cutting",
        "maintenance"
    ],
    "wof:name":"A1 Mowing & Gardening Service",
    "wof:placetype":"venue"
},
  "geometry": {"coordinates":[153.304855347,-27.6294517517],"type":"Point"}
}