{
  "type": "Feature",
  "properties": {
    "addr:full":"28 Woodburn St Evans Head NSW 2473",
    "addr:housenumber":"28",
    "addr:postcode":"2473",
    "addr:street":"Woodburn St Evans",
    "iso:country":"AU",
    "sg:address":"28 Woodburn St",
    "sg:city":"Evans Head",
    "sg:classifiers":[
        {
            "category":"Recreation",
            "subcategory":"Fishing",
            "type":"Entertainment"
        }
    ],
    "sg:phone":"+61 2 6682 4536",
    "sg:postcode":"2473",
    "sg:province":"NSW",
    "sg:tags":[
        "tackle"
    ],
    "wof:name":"Evans Head Sports & Marine",
    "wof:placetype":"venue"
},
  "geometry": {"coordinates":[153.43084716800001,-29.1178073883],"type":"Point"}
}