{
  "type": "Feature",
  "properties": {
    "addr:full":"1a Bridge St Lidcombe NSW 2141",
    "addr:housenumber":"1a",
    "addr:postcode":"2141",
    "addr:street":"Bridge St",
    "iso:country":"AU",
    "sg:address":"1a Bridge St",
    "sg:city":"Lidcombe",
    "sg:classifiers":[
        {
            "category":"Real Estate",
            "subcategory":"Real Estate Agent",
            "type":"Services"
        }
    ],
    "sg:phone":"+61 2 9649 1288",
    "sg:postcode":"2141",
    "sg:province":"NSW",
    "wof:name":"Elders Real Estate",
    "wof:placetype":"venue"
},
  "geometry": {"coordinates":[151.043457031,-33.8641166687],"type":"Point"}
}