{
  "type": "Feature",
  "properties": {
    "iso:country":"AU",
    "sg:address":"36 Hinkler Rd",
    "sg:city":"Mordialloc",
    "sg:classifiers":[
        {
            "category":"Utilities",
            "subcategory":"Mobile Phone",
            "type":"Services"
        }
    ],
    "sg:phone":"+61 3 9587 0556",
    "sg:postcode":"3195",
    "sg:province":"VIC",
    "sg:tags":[
        "wire",
        "straightener",
        "cutter"
    ],
    "wof:name":"10/08 Wire & Mesh",
    "wof:placetype":"venue"
},
  "geometry": {"coordinates":[145.098876953,-37.9903335571],"type":"Point"}
}