{
  "type": "Feature",
  "properties": {
    "iso:country":"AU",
    "sg:address":"82 White St",
    "sg:city":"Wavell Heights",
    "sg:classifiers":[
        {
            "category":"Personal",
            "subcategory":"Beauty Salon",
            "type":"Services"
        }
    ],
    "sg:phone":"+61 439 997 974",
    "sg:postcode":"4012",
    "sg:province":"QLD",
    "sg:tags":[
        "supply",
        "artist",
        "make-up"
    ],
    "wof:name":"Maree Andersen",
    "wof:placetype":"venue"
},
  "geometry": {"coordinates":[153.03872680699999,-27.3976783752],"type":"Point"}
}