{
  "type": "Feature",
  "properties": {
    "addr:full":"147 Burwood Rd Burwood NSW 2134",
    "addr:housenumber":"147",
    "addr:postcode":"2134",
    "addr:street":"Burwood Rd",
    "iso:country":"AU",
    "sg:address":"147 Burwood Rd",
    "sg:city":"Burwood",
    "sg:classifiers":[
        {
            "category":"Shopping",
            "subcategory":"Jewelry",
            "type":"Retail Goods"
        }
    ],
    "sg:phone":"+61 2 9744 2665",
    "sg:postcode":"2134",
    "sg:province":"NSW",
    "sg:tags":[
        "jeweller"
    ],
    "wof:name":"Watch Palace",
    "wof:placetype":"venue"
},
  "geometry": {"coordinates":[151.10369873100001,-33.8765716553],"type":"Point"}
}