{
  "type": "Feature",
  "properties": {
    "addr:full":"Dubbo Rd Coonamble NSW 2829",
    "addr:postcode":"2829",
    "addr:street":"Dubbo Rd",
    "iso:country":"AU",
    "sg:address":"Dubbo Rd",
    "sg:city":"Coonamble",
    "sg:classifiers":[
        {
            "category":"Arena",
            "subcategory":"Sports Club",
            "type":"Entertainment"
        }
    ],
    "sg:phone":"+61 2 6822 1078",
    "sg:postcode":"2829",
    "sg:province":"NSW",
    "sg:tags":[
        "hunt",
        "racing"
    ],
    "wof:name":"Coonamble Greyhound Racing Club",
    "wof:placetype":"venue"
},
  "geometry": {"coordinates":[148.39398193400001,-30.9539432526],"type":"Point"}
}