{
  "type": "Feature",
  "properties": {
    "iso:country":"AU",
    "sg:address":"15 Gilmour Crt",
    "sg:city":"Toowoomba",
    "sg:classifiers":[
        {
            "category":"Professional",
            "subcategory":"Accounting & Tax Preparation",
            "type":"Services"
        }
    ],
    "sg:phone":"+61 7 4639 1383",
    "sg:postcode":"4350",
    "sg:province":"QLD",
    "sg:tags":[
        "accountant",
        "auditor"
    ],
    "wof:name":"Wyton R J",
    "wof:placetype":"venue"
},
  "geometry": {"coordinates":[151.959457,-27.525476],"type":"Point"}
}