{
  "type": "Feature",
  "properties": {
    "iso:country":"AU",
    "sg:address":"14 Campbell St",
    "sg:city":"Newstead",
    "sg:classifiers":[
        {
            "category":"Building & Trades",
            "subcategory":"Landscaping Services",
            "type":"Services"
        }
    ],
    "sg:phone":"+61 3 6334 7694",
    "sg:postcode":"7250",
    "sg:province":"TAS",
    "sg:tags":[
        "consultant"
    ],
    "wof:name":"Protek Consulting Pty Ltd",
    "wof:placetype":"venue"
},
  "geometry": {"coordinates":[147.16021728499999,-41.4445495605],"type":"Point"}
}