{
  "type": "Feature",
  "properties": {
    "addr:full":"Elizabeth St Acacia Ridge QLD 4110",
    "addr:postcode":"4110",
    "addr:street":"Elizabeth St",
    "iso:country":"AU",
    "sg:address":"Elizabeth St",
    "sg:city":"Acacia Ridge",
    "sg:classifiers":[
        {
            "category":"Government",
            "subcategory":"Post Office",
            "type":"Public Place"
        }
    ],
    "sg:phone":"+61 7 3277 1609",
    "sg:postcode":"4110",
    "sg:province":"QLD",
    "sg:tags":[
        "postal"
    ],
    "wof:name":"Acacia Ridge LPO",
    "wof:placetype":"venue"
},
  "geometry": {"coordinates":[153.02720642099999,-27.5894527435],"type":"Point"}
}