{
  "type": "Feature",
  "properties": {
    "addr:full":"Norrie Ave Whyalla SA 5600",
    "addr:postcode":"5600",
    "addr:street":"Norrie Ave",
    "iso:country":"AU",
    "sg:address":"Norrie Ave",
    "sg:city":"Whyalla",
    "sg:classifiers":[
        {
            "category":"Autos & Motor Vehicles",
            "subcategory":"Auto Supplies",
            "type":"Retail Goods"
        }
    ],
    "sg:phone":"+61 13 32 27",
    "sg:postcode":"5600",
    "sg:province":"SA",
    "sg:tags":[
        "accessory"
    ],
    "wof:name":"Repco",
    "wof:placetype":"venue"
},
  "geometry": {"coordinates":[137.551086,-33.023174],"type":"Point"}
}