{
  "type": "Feature",
  "properties": {
    "addr:full":"Unit 14-15, Miak, International Drive Tullamarine VIC 3043",
    "addr:postcode":"3043",
    "addr:street":"International Drive",
    "iso:country":"AU",
    "sg:address":"Unit 14-15, Miak, International Drive",
    "sg:city":"Tullamarine",
    "sg:classifiers":[
        {
            "category":"Professional",
            "subcategory":"Employment Agencies",
            "type":"Services"
        }
    ],
    "sg:phone":"+61 3 9330 2033",
    "sg:postcode":"3043",
    "sg:province":"VIC",
    "sg:tags":[
        "broker",
        "custom"
    ],
    "wof:name":"Hunter I H Pty Ltd",
    "wof:placetype":"venue"
},
  "geometry": {"coordinates":[144.88145446799999,-37.6879196167],"type":"Point"}
}