{
  "type": "Feature",
  "properties": {
    "addr:full":"27 Lumsdaine St Picton NSW 2571",
    "addr:housenumber":"27",
    "addr:postcode":"2571",
    "addr:street":"Lumsdaine St",
    "iso:country":"AU",
    "sg:address":"27 Lumsdaine St",
    "sg:city":"Picton",
    "sg:classifiers":[
        {
            "category":"Education",
            "subcategory":"School",
            "type":"Public Place"
        }
    ],
    "sg:phone":"+61 2 4677 1497",
    "sg:postcode":"2571",
    "sg:province":"NSW",
    "sg:tags":[
        "state",
        "-",
        "nsw"
    ],
    "wof:name":"Picton Primary School",
    "wof:placetype":"venue"
},
  "geometry": {"coordinates":[150.610275269,-34.1773452759],"type":"Point"}
}