{
  "type": "Feature",
  "properties": {
    "iso:country":"AU",
    "sg:address":"228 Guildford Rd",
    "sg:city":"Maylands",
    "sg:classifiers":[
        {
            "category":"Fast Food",
            "type":"Food & Drink"
        }
    ],
    "sg:phone":"+61 8 9371 2288",
    "sg:postcode":"6051",
    "sg:province":"WA",
    "sg:tags":[
        "away",
        "take"
    ],
    "wof:name":"Yawara Japanese Takeaway",
    "wof:placetype":"venue"
},
  "geometry": {"coordinates":[115.895042,-31.930031],"type":"Point"}
}