{
  "type": "Feature",
  "properties": {
    "addr:full":"79 Montpelier Rd Bowen Hills QLD 4006",
    "addr:housenumber":"79",
    "addr:postcode":"4006",
    "addr:street":"Montpelier Rd",
    "iso:country":"AU",
    "sg:address":"79 Montpelier Rd",
    "sg:city":"Bowen Hills",
    "sg:classifiers":[
        {
            "category":"Fast Food",
            "type":"Food & Drink"
        }
    ],
    "sg:phone":"+61 7 3852 1168",
    "sg:postcode":"4006",
    "sg:province":"QLD",
    "sg:tags":[
        "away",
        "take"
    ],
    "wof:name":"Junction Express",
    "wof:placetype":"venue"
},
  "geometry": {"coordinates":[153.03887939399999,-27.4482765198],"type":"Point"}
}