{
  "type": "Feature",
  "properties": {
    "addr:full":"Lvl 5 991 Whitehorse Rd Surrey Hills VIC 3127",
    "addr:housenumber":"991",
    "addr:postcode":"3127",
    "addr:street":"Whitehorse Rd",
    "iso:country":"AU",
    "sg:address":"Lvl 5 991 Whitehorse Rd",
    "sg:city":"Surrey Hills",
    "sg:classifiers":[
        {
            "category":"Autos & Motor Vehicles",
            "subcategory":"Fuel & Gas Station",
            "type":"Retail Goods"
        }
    ],
    "sg:phone":"+61 3 9888 6880",
    "sg:postcode":"3127",
    "sg:province":"VIC",
    "wof:name":"Care Retail Services Pty Ltd",
    "wof:placetype":"venue"
},
  "geometry": {"coordinates":[145.11480712900001,-37.8169174194],"type":"Point"}
}