{
  "type": "Feature",
  "properties": {
    "addr:full":"491 Mountain Hwy Bayswater VIC 3153",
    "addr:housenumber":"491",
    "addr:postcode":"3153",
    "addr:street":"Mountain Hwy",
    "iso:country":"AU",
    "sg:address":"491 Mountain Hwy",
    "sg:city":"Bayswater",
    "sg:classifiers":[
        {
            "category":"Home & Garden",
            "subcategory":"Building Materials",
            "type":"Retail Goods"
        }
    ],
    "sg:phone":"+61 3 9722 5555",
    "sg:postcode":"3153",
    "sg:province":"VIC",
    "sg:tags":[
        "supply"
    ],
    "wof:name":"Stramit Industries",
    "wof:placetype":"venue"
},
  "geometry": {"coordinates":[145.24598693900001,-37.8435630798],"type":"Point"}
}