{
  "type": "Feature",
  "properties": {
    "addr:full":"160/ 168 East St Rockhampton QLD 4700",
    "addr:housenumber":"160 / 168",
    "addr:postcode":"4700",
    "addr:street":"East St",
    "iso:country":"AU",
    "sg:address":"160/ 168 East St",
    "sg:city":"Rockhampton",
    "sg:classifiers":[
        {
            "category":"Professional",
            "subcategory":"Business Services",
            "type":"Services"
        }
    ],
    "sg:phone":"+61 7 4927 5388",
    "sg:postcode":"4700",
    "sg:province":"QLD",
    "sg:tags":[
        "record",
        "management",
        "storage"
    ],
    "wof:name":"Storage King",
    "wof:placetype":"venue"
},
  "geometry": {"coordinates":[150.52145385700001,-23.3893699646],"type":"Point"}
}