{
  "type": "Feature",
  "properties": {
    "addr:full":"125 Belgrave-Gembrook Rd Selby VIC 3159",
    "addr:housenumber":"125",
    "addr:postcode":"3159",
    "addr:street":"Belgrave-Gembrook Rd",
    "iso:country":"AU",
    "sg:address":"125 Belgrave-Gembrook Rd",
    "sg:city":"Selby",
    "sg:classifiers":[
        {
            "category":"Farming",
            "subcategory":"Fish & Marine Products",
            "type":"Manufacturing & Wholesale Goods"
        }
    ],
    "sg:phone":"+61 1300 135 589",
    "sg:postcode":"3159",
    "sg:province":"VIC",
    "sg:tags":[
        "organic"
    ],
    "wof:name":"Blessed Earth",
    "wof:placetype":"venue"
},
  "geometry": {"coordinates":[145.37347412099999,-37.9148254395],"type":"Point"}
}