{
  "type": "Feature",
  "properties": {
    "iso:country":"AU",
    "sg:address":"72 Head St",
    "sg:city":"Traralgon",
    "sg:classifiers":[
        {
            "category":"Manufacturing",
            "subcategory":"Signs",
            "type":"Manufacturing & Wholesale Goods"
        }
    ],
    "sg:phone":"+61 3 5174 4616",
    "sg:postcode":"3844",
    "sg:province":"VIC",
    "sg:tags":[
        "traffic",
        "safety"
    ],
    "wof:name":"Mortimer Rob & Jenny",
    "wof:placetype":"venue"
},
  "geometry": {"coordinates":[146.55755615199999,-38.1925582886],"type":"Point"}
}