{
  "type": "Feature",
  "properties": {
    "addr:full":"Shop 118a Level E The Myer Centre 91 Queens St Brisbane QLD 4000",
    "addr:housenumber":"118a;91",
    "addr:postcode":"4000",
    "addr:street":"Queens St",
    "iso:country":"AU",
    "sg:address":"Shop 118a Level E The Myer Centre 91 Queens St",
    "sg:city":"Brisbane",
    "sg:classifiers":[
        {
            "category":"Personal",
            "subcategory":"Shoe Repair & Shine",
            "type":"Services"
        }
    ],
    "sg:phone":"+61 7 3012 8957",
    "sg:postcode":"4000",
    "sg:province":"QLD",
    "sg:tags":[
        "footwear"
    ],
    "wof:name":"Engraving Plus",
    "wof:placetype":"venue"
},
  "geometry": {"coordinates":[153.02461242699999,-27.4702720642],"type":"Point"}
}