{
  "type": "Feature",
  "properties": {
    "addr:full":"300 Railway Pde Carlton NSW 2218",
    "addr:housenumber":"300",
    "addr:postcode":"2218",
    "addr:street":"Railway Pde",
    "iso:country":"AU",
    "sg:address":"300 Railway Pde",
    "sg:city":"Carlton",
    "sg:classifiers":[
        {
            "category":"Shopping",
            "subcategory":"Antiques",
            "type":"Retail Goods"
        }
    ],
    "sg:phone":"+61 2 9587 5207",
    "sg:postcode":"2218",
    "sg:province":"NSW",
    "wof:name":"Abacus Antiques (You Can Count On Us)",
    "wof:placetype":"venue"
},
  "geometry": {"coordinates":[151.12312299999999,-33.968906],"type":"Point"}
}