{
  "type": "Feature",
  "properties": {
    "iso:country":"AU",
    "sg:address":"300 Railway Pde",
    "sg:city":"Carlton",
    "sg:classifiers":[
        {
            "category":"Shopping",
            "subcategory":"Antiques",
            "type":"Retail Goods"
        }
    ],
    "sg:phone":"+61 2 9587 5207",
    "sg:postcode":"2218",
    "sg:province":"NSW",
    "wof:name":"Abacus Antiques (You Can Count On Us)",
    "wof:placetype":"venue"
},
  "geometry": {"coordinates":[151.123123,-33.968906],"type":"Point"}
}