{
  "type": "Feature",
  "properties": {
    "addr:full":"9 Kulsi Crt Croydon Hills VIC 3136",
    "addr:housenumber":"9",
    "addr:postcode":"3136",
    "addr:street":"Kulsi Crt",
    "iso:country":"AU",
    "sg:address":"9 Kulsi Crt",
    "sg:city":"Croydon Hills",
    "sg:classifiers":[
        {
            "category":"Building & Trades",
            "subcategory":"Construction",
            "type":"Services"
        }
    ],
    "sg:phone":"+61 413 042 816",
    "sg:postcode":"3136",
    "sg:province":"VIC",
    "sg:tags":[
        "joiner",
        "carpenter"
    ],
    "wof:name":"Woodman David",
    "wof:placetype":"venue"
},
  "geometry": {"coordinates":[145.268310547,-37.7735099792],"type":"Point"}
}