{
  "type": "Feature",
  "properties": {
    "iso:country":"AU",
    "sg:address":"12 Seldon St",
    "sg:city":"Quakers Hill",
    "sg:classifiers":[
        {
            "category":"Professional",
            "subcategory":"Art Services",
            "type":"Services"
        }
    ],
    "sg:phone":"+61 417 223 288",
    "sg:postcode":"2763",
    "sg:province":"NSW",
    "sg:tags":[
        "decorator",
        "painter"
    ],
    "wof:name":"M & J Painting & Decorating Pty Ltd",
    "wof:placetype":"venue"
},
  "geometry": {"coordinates":[150.88116455100001,-33.7125358582],"type":"Point"}
}