{
  "type": "Feature",
  "properties": {
    "iso:country":"AU",
    "sg:address":"33 Carrington St",
    "sg:city":"Nedlands",
    "sg:classifiers":[
        {
            "category":"Home & Garden",
            "subcategory":"Hardware",
            "type":"Retail Goods"
        }
    ],
    "sg:phone":"+61 8 9389 6100",
    "sg:postcode":"6009",
    "sg:province":"WA",
    "sg:tags":[
        "plumber",
        "supply"
    ],
    "wof:name":"Galvins Plumbing Plus",
    "wof:placetype":"venue"
},
  "geometry": {"coordinates":[115.79631000000001,-31.975542],"type":"Point"}
}