{
  "type": "Feature",
  "properties": {
    "iso:country":"AU",
    "sg:address":"PO Box 1046",
    "sg:city":"Port Douglas",
    "sg:classifiers":[
        {
            "category":"Home & Garden",
            "subcategory":"Building Materials",
            "type":"Retail Goods"
        }
    ],
    "sg:phone":"+61 422 988 767",
    "sg:postcode":"4877",
    "sg:province":"QLD",
    "sg:tags":[
        "lawn",
        "cutting",
        "maintenance"
    ],
    "wof:name":"Yellow Yak Garden & Property Maintenance",
    "wof:placetype":"venue"
},
  "geometry": {"coordinates":[145.46543884299999,-16.4844493866],"type":"Point"}
}