{
  "type": "Feature",
  "properties": {
    "iso:country":"AU",
    "sg:address":"PO Box 302",
    "sg:city":"Toowoomba Business Centre",
    "sg:classifiers":[
        {
            "category":"Professional",
            "subcategory":"Management & Consulting",
            "type":"Services"
        }
    ],
    "sg:phone":"+61 7 4638 2889",
    "sg:postcode":"4350",
    "sg:province":"QLD",
    "sg:tags":[
        "project"
    ],
    "wof:name":"Maxime",
    "wof:placetype":"venue"
},
  "geometry": {"coordinates":[151.875641,-27.55761],"type":"Point"}
}