{
  "type": "Feature",
  "properties": {
    "iso:country":"AU",
    "sg:address":"20 Jamberoo Crt",
    "sg:city":"Tallebudgera",
    "sg:classifiers":[
        {
            "category":"Social Services",
            "subcategory":"Retirement Home",
            "type":"Services"
        }
    ],
    "sg:phone":"+61 7 5534 8440",
    "sg:postcode":"4228",
    "sg:province":"QLD",
    "sg:tags":[
        "environmental",
        "consultant",
        "pollution"
    ],
    "wof:name":"Richard Birt & Associates Pty Ltd",
    "wof:placetype":"venue"
},
  "geometry": {"coordinates":[153.43475341800001,-28.1488342285],"type":"Point"}
}