{
  "type": "Feature",
  "properties": {
    "iso:country":"AU",
    "sg:address":"339 Princes Hwy",
    "sg:city":"Woonona",
    "sg:classifiers":[
        {
            "category":"Personal",
            "subcategory":"Beauty Salon",
            "type":"Services"
        }
    ],
    "sg:phone":"+61 2 4285 0988",
    "sg:postcode":"2517",
    "sg:province":"NSW",
    "sg:tags":[
        "hairdresser"
    ],
    "wof:name":"Hair with Brooke & Tori",
    "wof:placetype":"venue"
},
  "geometry": {"coordinates":[150.908081,-34.339729],"type":"Point"}
}