{
  "type": "Feature",
  "properties": {
    "addr:full":"339 Princes Hwy Woonona NSW 2517",
    "addr:housenumber":"339",
    "addr:postcode":"2517",
    "addr:street":"Princes Hwy",
    "iso:country":"AU",
    "sg:address":"339 Princes Hwy",
    "sg:city":"Woonona",
    "sg:classifiers":[
        {
            "category":"Personal",
            "subcategory":"Beauty Salon",
            "type":"Services"
        }
    ],
    "sg:phone":"+61 2 4285 0988",
    "sg:postcode":"2517",
    "sg:province":"NSW",
    "sg:tags":[
        "hairdresser"
    ],
    "wof:name":"Hair with Brooke & Tori",
    "wof:placetype":"venue"
},
  "geometry": {"coordinates":[150.90808100000001,-34.339729],"type":"Point"}
}