{
  "type": "Feature",
  "properties": {
    "iso:country":"AU",
    "sg:address":"Unit 2/ 348 Stanmore Rd",
    "sg:city":"Petersham",
    "sg:classifiers":[
        {
            "category":"Arts & Performance",
            "subcategory":"Art Gallery",
            "type":"Entertainment"
        }
    ],
    "sg:phone":"+61 2 9564 6515",
    "sg:postcode":"2049",
    "sg:province":"NSW",
    "wof:name":"Wood Paper Silk",
    "wof:placetype":"venue"
},
  "geometry": {"coordinates":[151.156891,-33.895802],"type":"Point"}
}