{
  "type": "Feature",
  "properties": {
    "iso:country":"AU",
    "sg:address":"266 Evans Rd",
    "sg:city":"Salisbury",
    "sg:classifiers":[
        {
            "category":"Manufacturing",
            "subcategory":"Tools & Machinery",
            "type":"Manufacturing & Wholesale Goods"
        }
    ],
    "sg:phone":"+61 7 3216 6447",
    "sg:postcode":"4107",
    "sg:province":"QLD",
    "sg:tags":[
        "earth",
        "excavating",
        "moving",
        "equipment"
    ],
    "wof:name":"Avant Loaders & Equipment",
    "wof:placetype":"venue"
},
  "geometry": {"coordinates":[153.03726196299999,-27.5458145142],"type":"Point"}
}