{
  "type": "Feature",
  "properties": {
    "iso:country":"AU",
    "sg:address":"13 Thiele St",
    "sg:city":"Doncaster",
    "sg:classifiers":[
        {
            "category":"Utilities",
            "subcategory":"Electric",
            "type":"Services"
        }
    ],
    "sg:phone":"+61 408 788 130",
    "sg:postcode":"3108",
    "sg:province":"VIC",
    "sg:tags":[
        "electrical",
        "contractor"
    ],
    "wof:name":"C.T. Electrics",
    "wof:placetype":"venue"
},
  "geometry": {"coordinates":[145.13545227,-37.78465271],"type":"Point"}
}