{
  "type": "Feature",
  "properties": {
    "addr:full":"209 Pacific Hwy Coffs Harbour NSW 2450",
    "addr:housenumber":"209",
    "addr:postcode":"2450",
    "addr:street":"Pacific Hwy",
    "iso:country":"AU",
    "sg:address":"209 Pacific Hwy",
    "sg:city":"Coffs Harbour",
    "sg:classifiers":[
        {
            "category":"Travel",
            "subcategory":"Hotels & Motels",
            "type":"Entertainment"
        }
    ],
    "sg:phone":"+61 2 6652 1444",
    "sg:postcode":"2450",
    "sg:province":"NSW",
    "wof:name":"Midway Motor Inn",
    "wof:placetype":"venue"
},
  "geometry": {"coordinates":[153.091003,-30.317823],"type":"Point"}
}