{
  "type": "Feature",
  "properties": {
    "addr:full":"335A Gardeners Rd Rosebery NSW 2018",
    "addr:housenumber":"335a",
    "addr:postcode":"2018",
    "addr:street":"Gardeners Rd",
    "iso:country":"AU",
    "sg:address":"335A Gardeners Rd",
    "sg:city":"Rosebery",
    "sg:classifiers":[
        {
            "category":"Banks & Credit Unions",
            "subcategory":"Financial Services",
            "type":"Services"
        }
    ],
    "sg:phone":"+61 2 9700 9040",
    "sg:postcode":"2018",
    "sg:province":"NSW",
    "sg:tags":[
        "loan",
        "finance",
        "mortgage"
    ],
    "wof:name":"Mortgage House Of Australia",
    "wof:placetype":"venue"
},
  "geometry": {"coordinates":[151.20518493599999,-33.9227790833],"type":"Point"}
}