{
  "type": "Feature",
  "properties": {
    "addr:full":"14 Dunluce Ave Brighton SA 5048",
    "addr:housenumber":"14",
    "addr:postcode":"5048",
    "addr:street":"Dunluce Ave",
    "iso:country":"AU",
    "sg:address":"14 Dunluce Ave",
    "sg:city":"Brighton",
    "sg:classifiers":[
        {
            "category":"Building & Trades",
            "subcategory":"Construction",
            "type":"Services"
        }
    ],
    "sg:phone":"+61 408 829 433",
    "sg:postcode":"5048",
    "sg:province":"SA",
    "sg:tags":[
        "contractor"
    ],
    "wof:name":"Unicon Pty Ltd",
    "wof:placetype":"venue"
},
  "geometry": {"coordinates":[138.516998,-35.015804],"type":"Point"}
}