{
  "type": "Feature",
  "properties": {
    "addr:full":"Cottenham Rd Banksia Park SA 5091",
    "addr:postcode":"5091",
    "addr:street":"Cottenham Rd",
    "iso:country":"AU",
    "sg:address":"Cottenham Rd",
    "sg:city":"Banksia Park",
    "sg:classifiers":[
        {
            "category":"Education",
            "subcategory":"School",
            "type":"Public Place"
        }
    ],
    "sg:phone":"+61 8 8264 2114",
    "sg:postcode":"5091",
    "sg:province":"SA",
    "sg:tags":[
        "state",
        "except",
        "nsw"
    ],
    "wof:name":"Banksia Park School R - 7",
    "wof:placetype":"venue"
},
  "geometry": {"coordinates":[138.72483825699999,-34.8082695007],"type":"Point"}
}