{
  "type": "Feature",
  "properties": {
    "iso:country":"AU",
    "sg:address":"208 Sturt St",
    "sg:city":"Ballarat",
    "sg:classifiers":[
        {
            "category":"Banks & Credit Unions",
            "subcategory":"Financial Services",
            "type":"Services"
        }
    ],
    "sg:phone":"+61 3 5333 3476",
    "sg:postcode":"3350",
    "sg:province":"VIC",
    "sg:tags":[
        "coin"
    ],
    "wof:name":"I.S. Wright Militaria",
    "wof:placetype":"venue"
},
  "geometry": {"coordinates":[143.856979,-37.561554],"type":"Point"}
}