{
  "type": "Feature",
  "properties": {
    "iso:country":"AU",
    "sg:address":"101 Mercer St",
    "sg:city":"Geelong",
    "sg:classifiers":[
        {
            "category":"Autos & Motor Vehicles",
            "subcategory":"Automobile Sales",
            "type":"Retail Goods"
        }
    ],
    "sg:phone":"+61 3 5222 1811",
    "sg:postcode":"3220",
    "sg:province":"VIC",
    "sg:tags":[
        "car",
        "new"
    ],
    "wof:name":"Winter & Taylor Saab",
    "wof:placetype":"venue"
},
  "geometry": {"coordinates":[144.356766,-38.143578],"type":"Point"}
}