{
  "type": "Feature",
  "properties": {
    "addr:full":"77 Albert Rd Draper QLD 4520",
    "addr:housenumber":"77",
    "addr:postcode":"4520",
    "addr:street":"Albert Rd",
    "iso:country":"AU",
    "sg:address":"77 Albert Rd",
    "sg:city":"Draper",
    "sg:classifiers":[
        {
            "category":"Professional",
            "subcategory":"Management & Consulting",
            "type":"Services"
        }
    ],
    "sg:phone":"+61 7 3289 5338",
    "sg:postcode":"4520",
    "sg:province":"QLD",
    "sg:tags":[
        "consultant",
        "business"
    ],
    "wof:name":"Ripple Effect Aust Pty Ltd",
    "wof:placetype":"venue"
},
  "geometry": {"coordinates":[152.90351899999999,-27.343843],"type":"Point"}
}