{
  "type": "Feature",
  "properties": {
    "addr:full":"Unit 5/ 8a Prosperity Pde Warriewood NSW 2102",
    "addr:housenumber":"/ 8a",
    "addr:postcode":"2102",
    "addr:street":"Prosperity Pde",
    "iso:country":"AU",
    "sg:address":"Unit 5/ 8a Prosperity Pde",
    "sg:city":"Warriewood",
    "sg:classifiers":[
        {
            "category":"Manufacturing",
            "subcategory":"Printing",
            "type":"Manufacturing & Wholesale Goods"
        }
    ],
    "sg:phone":"+61 2 9999 4288",
    "sg:postcode":"2102",
    "sg:province":"NSW",
    "sg:tags":[
        "encoding",
        "cheque"
    ],
    "wof:name":"MICRvision Pty Ltd",
    "wof:placetype":"venue"
},
  "geometry": {"coordinates":[151.289658,-33.681007],"type":"Point"}
}