{
  "type": "Feature",
  "properties": {
    "addr:full":"Units 3&4 30-32 Whyalla Pl Prestons NSW 2170",
    "addr:housenumber":"units 3 & 4",
    "addr:postcode":"30-32;2170",
    "iso:country":"AU",
    "sg:address":"Units 3&4 30-32 Whyalla Pl",
    "sg:city":"Prestons",
    "sg:classifiers":[
        {
            "category":"Home & Garden",
            "subcategory":"Building Materials",
            "type":"Retail Goods"
        }
    ],
    "sg:phone":"+61 2 9608 8711",
    "sg:postcode":"2170",
    "sg:province":"NSW",
    "sg:tags":[
        "laminate",
        "laminated",
        "panel"
    ],
    "wof:name":"Multiform Australasia Pty Ltd",
    "wof:placetype":"venue"
},
  "geometry": {"coordinates":[150.879180908,-33.9301528931],"type":"Point"}
}