{
  "type": "Feature",
  "properties": {
    "iso:country":"AU",
    "sg:address":"Fcty3/ 5 Simcock St",
    "sg:city":"Somerville",
    "sg:classifiers":[
        {
            "category":"Autos & Motor Vehicles",
            "subcategory":"Automobile Sales",
            "type":"Retail Goods"
        }
    ],
    "sg:phone":"+61 3 5977 9551",
    "sg:postcode":"3912",
    "sg:province":"VIC",
    "sg:tags":[
        "car",
        "used"
    ],
    "wof:name":"Somerville Car & Four Wheel Drive Sales",
    "wof:placetype":"venue"
},
  "geometry": {"coordinates":[145.177536011,-38.2214508057],"type":"Point"}
}