{
  "type": "Feature",
  "properties": {
    "iso:country":"AU",
    "sg:address":"Port Wakefield Hwy",
    "sg:city":"Virginia",
    "sg:classifiers":[
        {
            "category":"Farming",
            "subcategory":"Farm",
            "type":"Manufacturing & Wholesale Goods"
        }
    ],
    "sg:phone":"+61 8 8380 9316",
    "sg:postcode":"5120",
    "sg:province":"SA",
    "sg:tags":[
        "farmer"
    ],
    "wof:name":"Sheedy KJ & KM",
    "wof:placetype":"venue"
},
  "geometry": {"coordinates":[138.54849243199999,-34.671459198],"type":"Point"}
}