{
  "type": "Feature",
  "properties": {
    "addr:full":"7/ 31 Brabyn St Windsor NSW 2756",
    "addr:housenumber":"/ 31",
    "addr:postcode":"2756",
    "addr:street":"Brabyn St",
    "iso:country":"AU",
    "sg:address":"7/ 31 Brabyn St",
    "sg:city":"Windsor",
    "sg:classifiers":[
        {
            "category":"Autos & Motor Vehicles",
            "subcategory":"Auto Supplies",
            "type":"Retail Goods"
        }
    ],
    "sg:phone":"+61 2 4587 8430",
    "sg:postcode":"2756",
    "sg:province":"NSW",
    "sg:tags":[
        "part",
        "cycles",
        "accessory"
    ],
    "wof:name":"Planet Motorcycles Pty Ltd",
    "wof:placetype":"venue"
},
  "geometry": {"coordinates":[150.81260681099999,-33.6137771606],"type":"Point"}
}