{
  "type": "Feature",
  "properties": {
    "iso:country":"AU",
    "sg:address":"42 Grubb Rd",
    "sg:city":"Ocean Grove",
    "sg:classifiers":[
        {
            "category":"Retail",
            "subcategory":"Veterinary Services",
            "type":"Services"
        }
    ],
    "sg:phone":"+61 3 5256 2400",
    "sg:postcode":"3226",
    "sg:province":"VIC",
    "sg:tags":[
        "surgeon"
    ],
    "wof:name":"Bellarine Veterinary Practice",
    "wof:placetype":"venue"
},
  "geometry": {"coordinates":[144.53634600000001,-38.254517],"type":"Point"}
}