{
  "type": "Feature",
  "properties": {
    "addr:full":"65 Market St Fremantle WA 6160",
    "addr:housenumber":"65",
    "addr:postcode":"6160",
    "addr:street":"Market St",
    "iso:country":"AU",
    "sg:address":"65 Market St",
    "sg:city":"Fremantle",
    "sg:classifiers":[
        {
            "category":"Utilities",
            "subcategory":"Refuse",
            "type":"Services"
        }
    ],
    "sg:phone":"+61 8 9430 4140",
    "sg:postcode":"6160",
    "sg:province":"WA",
    "sg:tags":[
        "leather",
        "retail",
        "clothing"
    ],
    "wof:name":"Terrace Men",
    "wof:placetype":"venue"
},
  "geometry": {"coordinates":[115.74645200000001,-32.054855],"type":"Point"}
}