{
  "type": "Feature",
  "properties": {
    "iso:country":"AU",
    "sg:address":"7 Young St",
    "sg:city":"Blackwood",
    "sg:classifiers":[
        {
            "category":"Education",
            "subcategory":"Dance Studio",
            "type":"Public Place"
        }
    ],
    "sg:phone":"+61 8 8270 4214",
    "sg:postcode":"5051",
    "sg:province":"SA",
    "sg:tags":[
        "venue",
        "tuition"
    ],
    "wof:name":"Panache Dance Studio",
    "wof:placetype":"venue"
},
  "geometry": {"coordinates":[138.615067,-35.01997],"type":"Point"}
}