{
  "type": "Feature",
  "properties": {
    "iso:country":"AU",
    "sg:address":"52 Gymea Bay Rd",
    "sg:city":"Gymea",
    "sg:classifiers":[
        {
            "category":"Bars & Pubs",
            "subcategory":"Nightclub",
            "type":"Food & Drink"
        }
    ],
    "sg:phone":"+61 2 9526 5199",
    "sg:postcode":"2227",
    "sg:province":"NSW",
    "sg:tags":[
        "discotheque"
    ],
    "wof:name":"The Vinyl Room",
    "wof:placetype":"venue"
},
  "geometry": {"coordinates":[151.08529663100001,-34.0344619751],"type":"Point"}
}