{
  "type": "Feature",
  "properties": {
    "addr:full":"Cnr North & Pratten Sts Dalby QLD 4405",
    "addr:postcode":"4405",
    "addr:street":"Cnr",
    "iso:country":"AU",
    "sg:address":"Cnr North & Pratten Sts",
    "sg:city":"Dalby",
    "sg:classifiers":[
        {
            "category":"Social Services",
            "type":"Services"
        }
    ],
    "sg:phone":"+61 7 4662 3702",
    "sg:postcode":"4405",
    "sg:province":"QLD",
    "sg:tags":[
        "kinesiology"
    ],
    "wof:name":"Dalby Natural Therapies & Massage Clinic",
    "wof:placetype":"venue"
},
  "geometry": {"coordinates":[151.257415772,-27.1783504486],"type":"Point"}
}