{
  "type": "Feature",
  "properties": {
    "addr:full":"190 Numurkah Rd Shepparton VIC 3630",
    "addr:housenumber":"190",
    "addr:postcode":"3630",
    "addr:street":"Numurkah Rd",
    "iso:country":"AU",
    "sg:address":"190 Numurkah Rd",
    "sg:city":"Shepparton",
    "sg:classifiers":[
        {
            "category":"Retail",
            "subcategory":"Event Space",
            "type":"Services"
        }
    ],
    "sg:phone":"+61 3 5821 1699",
    "sg:postcode":"3630",
    "sg:province":"VIC",
    "sg:tags":[
        "function",
        "organiser"
    ],
    "wof:name":"Jungle Jive",
    "wof:placetype":"venue"
},
  "geometry": {"coordinates":[145.401855469,-36.3523864746],"type":"Point"}
}