{
  "type": "Feature",
  "properties": {
    "addr:full":"10 Daniel Drv Carrum Downs VIC 3201",
    "addr:housenumber":"10",
    "addr:postcode":"3201",
    "addr:street":"Daniel Drv",
    "iso:country":"AU",
    "sg:address":"10 Daniel Drv",
    "sg:city":"Carrum Downs",
    "sg:classifiers":[
        {
            "category":"Building & Trades",
            "subcategory":"Construction",
            "type":"Services"
        }
    ],
    "sg:phone":"+61 3 9773 6033",
    "sg:postcode":"3201",
    "sg:province":"VIC",
    "sg:tags":[
        "brick",
        "paving"
    ],
    "wof:name":"Classicstone Pavers & Products",
    "wof:placetype":"venue"
},
  "geometry": {"coordinates":[145.161743,-38.105492],"type":"Point"}
}