{
  "type": "Feature",
  "properties": {
    "addr:full":"Blomfield St Maitland NSW 2320",
    "addr:postcode":"2320",
    "addr:street":"Blomfield St",
    "iso:country":"AU",
    "sg:address":"Blomfield St",
    "sg:city":"Maitland",
    "sg:classifiers":[
        {
            "category":"Organizations",
            "subcategory":"Professional Association",
            "type":"Services"
        }
    ],
    "sg:phone":"+61 2 4933 5052",
    "sg:postcode":"2320",
    "sg:province":"NSW",
    "sg:tags":[
        "rural",
        "organisation",
        "production",
        "primary"
    ],
    "wof:name":"Hunter River Agricultural & Horticultural Society",
    "wof:placetype":"venue"
},
  "geometry": {"coordinates":[151.55665588400001,-32.7418441772],"type":"Point"}
}