{
  "type": "Feature",
  "properties": {
    "addr:full":"West Kalgoorlie Rd Kalgoorlie WA 6430",
    "addr:postcode":"6430",
    "addr:street":"West Kalgoorlie Rd",
    "iso:country":"AU",
    "sg:address":"West Kalgoorlie Rd",
    "sg:city":"Kalgoorlie",
    "sg:classifiers":[
        {
            "category":"Utilities",
            "subcategory":"Fuel Oil & Lpg",
            "type":"Services"
        }
    ],
    "sg:phone":"+61 8 9021 8666",
    "sg:postcode":"6430",
    "sg:province":"WA",
    "sg:tags":[
        "merchant"
    ],
    "wof:name":"Sovereign Petroleum",
    "wof:placetype":"venue"
},
  "geometry": {"coordinates":[121.427871704,-30.7762527466],"type":"Point"}
}