{
  "type": "Feature",
  "properties": {
    "addr:full":"263 Brighton Rd Somerton Park SA 5044",
    "addr:housenumber":"263",
    "addr:postcode":"5044",
    "addr:street":"Brighton Rd",
    "iso:country":"AU",
    "sg:address":"263 Brighton Rd",
    "sg:city":"Somerton Park",
    "sg:classifiers":[
        {
            "category":"Retail",
            "subcategory":"Funeral Services",
            "type":"Services"
        }
    ],
    "sg:phone":"+61 8 8295 5600",
    "sg:postcode":"5044",
    "sg:province":"SA",
    "sg:tags":[
        "director"
    ],
    "wof:name":"Glenelg Funerals",
    "wof:placetype":"venue"
},
  "geometry": {"coordinates":[138.52145400000001,-34.998901],"type":"Point"}
}