{
  "type": "Feature",
  "properties": {
    "addr:full":"112 Rickard Rd Empire Bay NSW 2257",
    "addr:housenumber":"112",
    "addr:postcode":"2257",
    "addr:street":"Rickard Rd",
    "iso:country":"AU",
    "sg:address":"112 Rickard Rd",
    "sg:city":"Empire Bay",
    "sg:classifiers":[
        {
            "category":"Utilities",
            "type":"Services"
        }
    ],
    "sg:phone":"+61 2 4369 0777",
    "sg:postcode":"2257",
    "sg:province":"NSW",
    "sg:tags":[
        "refrigeration",
        "industrial",
        "commercial",
        "retail"
    ],
    "wof:name":"Rex Refrigeration",
    "wof:placetype":"venue"
},
  "geometry": {"coordinates":[151.362838745,-33.4942398071],"type":"Point"}
}