{
  "type": "Feature",
  "properties": {
    "iso:country":"AU",
    "sg:address":"300 The Entrance Rd",
    "sg:city":"The Entrance",
    "sg:classifiers":[
        {
            "category":"Shopping",
            "subcategory":"Beauty & Cosmetics",
            "type":"Retail Goods"
        }
    ],
    "sg:phone":"+61 405 419 446",
    "sg:postcode":"2261",
    "sg:province":"NSW",
    "sg:tags":[
        "equipment",
        "salon",
        "supply"
    ],
    "wof:name":"Central Coast Beauty Supplies",
    "wof:placetype":"venue"
},
  "geometry": {"coordinates":[151.492462,-33.349312],"type":"Point"}
}