{
  "type": "Feature",
  "properties": {
    "addr:full":"16 Cashmere Pl Morayfield QLD 4506",
    "addr:housenumber":"16",
    "addr:postcode":"4506",
    "addr:street":"Cashmere Pl",
    "iso:country":"AU",
    "sg:address":"16 Cashmere Pl",
    "sg:city":"Morayfield",
    "sg:classifiers":[
        {
            "category":"Building & Trades",
            "subcategory":"Construction",
            "type":"Services"
        }
    ],
    "sg:phone":"+61 7 5498 6108",
    "sg:postcode":"4506",
    "sg:province":"QLD",
    "sg:tags":[
        "plasterboard",
        "plasterer",
        "fixer"
    ],
    "wof:name":"Barry M D & G R",
    "wof:placetype":"venue"
},
  "geometry": {"coordinates":[152.93672180199999,-27.1340732574],"type":"Point"}
}