{
  "type": "Feature",
  "properties": {
    "addr:full":"Level 1, 3 West St North Sydney NSW 2060",
    "addr:housenumber":"3",
    "addr:postcode":"2060",
    "addr:street":"West St",
    "iso:country":"AU",
    "sg:address":"Level 1, 3 West St",
    "sg:city":"North Sydney",
    "sg:classifiers":[
        {
            "category":"Professional",
            "subcategory":"Printing & Photocopies",
            "type":"Services"
        }
    ],
    "sg:phone":"+61 2 9959 4821",
    "sg:postcode":"2060",
    "sg:province":"NSW",
    "sg:tags":[
        "publishing",
        "desktop"
    ],
    "wof:name":"Morton Branding Consultants",
    "wof:placetype":"venue"
},
  "geometry": {"coordinates":[151.205352783,-33.8335914612],"type":"Point"}
}