{
  "type": "Feature",
  "properties": {
    "addr:full":"2065 Frankston-Flinders Rd Hastings VIC 3915",
    "addr:housenumber":"2065",
    "addr:postcode":"3915",
    "addr:street":"Frankston-Flinders Rd",
    "iso:country":"AU",
    "sg:address":"2065 Frankston-Flinders Rd",
    "sg:city":"Hastings",
    "sg:classifiers":[
        {
            "category":"Retail",
            "subcategory":"Auto Repair",
            "type":"Services"
        }
    ],
    "sg:phone":"+61 3 5979 1870",
    "sg:postcode":"3915",
    "sg:province":"VIC",
    "sg:tags":[
        "electrical"
    ],
    "wof:name":"Hastings Auto Electrical",
    "wof:placetype":"venue"
},
  "geometry": {"coordinates":[145.18380737300001,-38.3049545288],"type":"Point"}
}