{
  "type": "Feature",
  "properties": {
    "addr:full":"Level 57, MLC Centre, Cnr King & Castlereagh Sts Sydney NSW 2000",
    "addr:postcode":"2000",
    "addr:street":"Cnr",
    "iso:country":"AU",
    "sg:address":"Level 57, MLC Centre, Cnr King & Castlereagh Sts",
    "sg:city":"Sydney",
    "sg:classifiers":[
        {
            "category":"Professional",
            "subcategory":"Management & Consulting",
            "type":"Services"
        }
    ],
    "sg:phone":"+61 2 9238 6869",
    "sg:postcode":"2000",
    "sg:province":"NSW",
    "sg:tags":[
        "consultant"
    ],
    "wof:name":"Axon Solutions Pty Ltd",
    "wof:placetype":"venue"
},
  "geometry": {"coordinates":[151.20957946799999,-33.8699073792],"type":"Point"}
}