{
  "type": "Feature",
  "properties": {
    "addr:full":"90- 96 Loftus St Temora NSW 2666",
    "addr:housenumber":"96",
    "addr:postcode":"2666",
    "addr:street":"Loftus St",
    "iso:country":"AU",
    "sg:address":"90- 96 Loftus St",
    "sg:city":"Temora",
    "sg:classifiers":[
        {
            "category":"Professional",
            "subcategory":"Accounting & Tax Preparation",
            "type":"Services"
        }
    ],
    "sg:phone":"+61 2 6977 4333",
    "sg:postcode":"2666",
    "sg:province":"NSW",
    "sg:tags":[
        "accountant",
        "auditor"
    ],
    "wof:name":"Catalyst Accountants & Financial Solutions",
    "wof:placetype":"venue"
},
  "geometry": {"coordinates":[147.54034423799999,-34.4450492859],"type":"Point"}
}