{
  "type": "Feature",
  "properties": {
    "addr:full":"33 Joynt St Hamilton QLD 4007",
    "addr:housenumber":"33",
    "addr:postcode":"4007",
    "addr:street":"Joynt St",
    "iso:country":"AU",
    "sg:address":"33 Joynt St",
    "sg:city":"Hamilton",
    "sg:classifiers":[
        {
            "category":"Building & Trades",
            "subcategory":"Cleaning & Sanitation",
            "type":"Services"
        }
    ],
    "sg:phone":"+61 7 3262 5084",
    "sg:postcode":"4007",
    "sg:province":"QLD",
    "sg:tags":[
        "industrial",
        "commercial",
        "contractor"
    ],
    "wof:name":"JKI Property Maintenance",
    "wof:placetype":"venue"
},
  "geometry": {"coordinates":[153.05076600000001,-27.435242],"type":"Point"}
}