{
  "type": "Feature",
  "properties": {
    "iso:country":"AU",
    "sg:address":"18 Clyde Ave",
    "sg:city":"Moorebank",
    "sg:classifiers":[
        {
            "category":"Personal",
            "subcategory":"Beauty Salon",
            "type":"Services"
        }
    ],
    "sg:phone":"+61 2 9601 1495",
    "sg:postcode":"2170",
    "sg:province":"NSW",
    "sg:tags":[
        "supply",
        "artist",
        "make-up"
    ],
    "wof:name":"Make-up Artistry",
    "wof:placetype":"venue"
},
  "geometry": {"coordinates":[150.953216553,-33.9443359375],"type":"Point"}
}