{
  "type": "Feature",
  "properties": {
    "iso:country":"AU",
    "sg:address":"260 Scrub Rd",
    "sg:city":"Carindale",
    "sg:classifiers":[
        {
            "category":"Real Estate",
            "subcategory":"Real Estate Agent",
            "type":"Services"
        }
    ],
    "sg:phone":"+61 7 3849 5355",
    "sg:postcode":"4152",
    "sg:province":"QLD",
    "wof:name":"Harcourts Carindale",
    "wof:placetype":"venue"
},
  "geometry": {"coordinates":[153.11248779300001,-27.520608902],"type":"Point"}
}