{
  "type": "Feature",
  "properties": {
    "addr:full":"4 Berkley Crt Devonport TAS 7310",
    "addr:housenumber":"4",
    "addr:postcode":"7310",
    "addr:street":"Berkley Crt",
    "iso:country":"AU",
    "sg:address":"4 Berkley Crt",
    "sg:city":"Devonport",
    "sg:classifiers":[
        {
            "category":"Professional",
            "subcategory":"Art Services",
            "type":"Services"
        }
    ],
    "sg:phone":"+61 3 6424 5028",
    "sg:postcode":"7310",
    "sg:province":"TAS",
    "sg:tags":[
        "decorator",
        "painter"
    ],
    "wof:name":"Wessing T M",
    "wof:placetype":"venue"
},
  "geometry": {"coordinates":[146.344512939,-41.1931838989],"type":"Point"}
}