{
  "type": "Feature",
  "properties": {
    "addr:full":"2 Thomas Crt Shepparton VIC 3630",
    "addr:housenumber":"2",
    "addr:postcode":"3630",
    "addr:street":"Thomas Crt",
    "iso:country":"AU",
    "sg:address":"2 Thomas Crt",
    "sg:city":"Shepparton",
    "sg:classifiers":[
        {
            "category":"Building & Trades",
            "subcategory":"Landscaping Services",
            "type":"Services"
        }
    ],
    "sg:phone":"+61 3 5831 6100",
    "sg:postcode":"3630",
    "sg:province":"VIC",
    "sg:tags":[
        "horticultural",
        "consultant"
    ],
    "wof:name":"Advanced Horticulture Consultants Pty Ltd",
    "wof:placetype":"venue"
},
  "geometry": {"coordinates":[145.40525817899999,-36.3602371216],"type":"Point"}
}