{
  "type": "Feature",
  "properties": {
    "addr:full":"1 Silks Rd Kurmond NSW 2757",
    "addr:housenumber":"1",
    "addr:postcode":"2757",
    "addr:street":"Silks Rd",
    "iso:country":"AU",
    "sg:address":"1 Silks Rd",
    "sg:city":"Kurmond",
    "sg:classifiers":[
        {
            "category":"Professional",
            "subcategory":"Accounting & Tax Preparation",
            "type":"Services"
        }
    ],
    "sg:phone":"+61 2 4573 1345",
    "sg:postcode":"2757",
    "sg:province":"NSW",
    "sg:tags":[
        "accountant",
        "auditor"
    ],
    "wof:name":"Millenium Accounting Solutions",
    "wof:placetype":"venue"
},
  "geometry": {"coordinates":[150.705352783,-33.5494689941],"type":"Point"}
}