{
  "type": "Feature",
  "properties": {
    "iso:country":"AU",
    "sg:address":"Rear 28 Dreadnought St",
    "sg:city":"Roselands",
    "sg:classifiers":[
        {
            "category":"Government",
            "subcategory":"Department Of Motor Vehicles",
            "type":"Public Place"
        }
    ],
    "sg:phone":"+61 2 9703 3070",
    "sg:postcode":"2196",
    "sg:province":"NSW",
    "sg:tags":[
        "body",
        "supply",
        "trimmer"
    ],
    "wof:name":"Backing Board Supplies",
    "wof:placetype":"venue"
},
  "geometry": {"coordinates":[151.080109,-33.929852],"type":"Point"}
}