{
  "type": "Feature",
  "properties": {
    "iso:country":"AU",
    "sg:address":"1/ 150 Merrylands Rd",
    "sg:city":"Merrylands",
    "sg:classifiers":[
        {
            "category":"Real Estate",
            "subcategory":"Real Estate Agent",
            "type":"Services"
        }
    ],
    "sg:phone":"+61 2 9897 5877",
    "sg:postcode":"2160",
    "sg:province":"NSW",
    "wof:name":"Starr Partners",
    "wof:placetype":"venue"
},
  "geometry": {"coordinates":[150.99026489299999,-33.8366966248],"type":"Point"}
}