{
  "type": "Feature",
  "properties": {
    "iso:country":"AU",
    "sg:address":"118 Rawson Rd",
    "sg:city":"Greenacre",
    "sg:classifiers":[
        {
            "category":"Food & Beverages",
            "subcategory":"Liquor & Beverages",
            "type":"Retail Goods"
        }
    ],
    "sg:phone":"+61 2 9790 4887",
    "sg:postcode":"2190",
    "sg:province":"NSW",
    "sg:tags":[
        "store"
    ],
    "wof:name":"Greenacre Liquor Stax",
    "wof:placetype":"venue"
},
  "geometry": {"coordinates":[151.05270400000001,-33.901901],"type":"Point"}
}