{
  "type": "Feature",
  "properties": {
    "addr:full":"1 Davenport St Rankin Park NSW 2287",
    "addr:housenumber":"1",
    "addr:postcode":"2287",
    "addr:street":"Davenport St Rankin",
    "iso:country":"AU",
    "sg:address":"1 Davenport St",
    "sg:city":"Rankin Park",
    "sg:classifiers":[
        {
            "category":"Banks & Credit Unions",
            "subcategory":"Financial Services",
            "type":"Services"
        }
    ],
    "sg:phone":"+61 2 4952 8780",
    "sg:postcode":"2287",
    "sg:province":"NSW",
    "sg:tags":[
        "financier"
    ],
    "wof:name":"Finance & Investments Pty Ltd",
    "wof:placetype":"venue"
},
  "geometry": {"coordinates":[151.67274475100001,-32.9255638123],"type":"Point"}
}