{
  "type": "Feature",
  "properties": {
    "iso:country":"AU",
    "sg:address":"3 Michael Pl",
    "sg:city":"Leongatha",
    "sg:classifiers":[
        {
            "category":"Utilities",
            "type":"Services"
        }
    ],
    "sg:phone":"+61 3 5662 2329",
    "sg:postcode":"3953",
    "sg:province":"VIC",
    "sg:tags":[
        "equipment",
        "towing"
    ],
    "wof:name":"Autobarn McNivens Pty Ltd",
    "wof:placetype":"venue"
},
  "geometry": {"coordinates":[145.945800781,-38.4754676819],"type":"Point"}
}