{
  "type": "Feature",
  "properties": {
    "iso:country":"AU",
    "sg:address":"47 Carrington Rd",
    "sg:city":"Toowoomba",
    "sg:classifiers":[
        {
            "category":"Utilities",
            "subcategory":"Fuel Oil & Lpg",
            "type":"Services"
        }
    ],
    "sg:phone":"+61 7 4634 4844",
    "sg:postcode":"4350",
    "sg:province":"QLD",
    "sg:tags":[
        "merchant"
    ],
    "wof:name":"South State Fuel",
    "wof:placetype":"venue"
},
  "geometry": {"coordinates":[151.876617,-27.542086],"type":"Point"}
}