{
  "type": "Feature",
  "properties": {
    "addr:full":"Shop 4- 5 Pacific Broadbeach QLD 4218",
    "addr:housenumber":"shop;5",
    "addr:postcode":"4218",
    "addr:street":"Pacific",
    "iso:country":"AU",
    "sg:address":"Shop 4- 5 Pacific",
    "sg:city":"Broadbeach",
    "sg:classifiers":[
        {
            "category":"Personal",
            "subcategory":"Beauty Salon",
            "type":"Services"
        }
    ],
    "sg:phone":"+61 7 5575 5545",
    "sg:postcode":"4218",
    "sg:province":"QLD",
    "sg:tags":[
        "hairdresser"
    ],
    "wof:name":"Colourado Hair Gold Pacific Fair",
    "wof:placetype":"venue"
},
  "geometry": {"coordinates":[153.43174743599999,-28.0374698639],"type":"Point"}
}