{
  "type": "Feature",
  "properties": {
    "addr:full":"54 MacRossan St Port Douglas QLD 4877",
    "addr:housenumber":"54",
    "addr:postcode":"4877",
    "addr:street":"Macrossan St",
    "iso:country":"AU",
    "sg:address":"54 MacRossan St",
    "sg:city":"Port Douglas",
    "sg:classifiers":[
        {
            "category":"Travel",
            "subcategory":"Hotels & Motels",
            "type":"Entertainment"
        }
    ],
    "sg:phone":"+61 7 4099 5730",
    "sg:postcode":"4877",
    "sg:province":"QLD",
    "sg:tags":[
        "accommodation"
    ],
    "wof:name":"Barrier Reef Tavern",
    "wof:placetype":"venue"
},
  "geometry": {"coordinates":[145.46568298299999,-16.4839782715],"type":"Point"}
}