{
  "type": "Feature",
  "properties": {
    "addr:full":"82 Raeburn Rd Roleystone WA 6111",
    "addr:housenumber":"82",
    "addr:postcode":"6111",
    "addr:street":"Raeburn Rd",
    "iso:country":"AU",
    "sg:address":"82 Raeburn Rd",
    "sg:city":"Roleystone",
    "sg:classifiers":[
        {
            "category":"Retail",
            "subcategory":"Auto Repair",
            "type":"Services"
        }
    ],
    "sg:phone":"+61 407 558 951",
    "sg:postcode":"6111",
    "sg:province":"WA",
    "sg:tags":[
        "body",
        "motor",
        "trimmer"
    ],
    "wof:name":"Prestige Car Upholstery",
    "wof:placetype":"venue"
},
  "geometry": {"coordinates":[116.083808899,-32.1046638489],"type":"Point"}
}