{
  "type": "Feature",
  "properties": {
    "iso:country":"AU",
    "sg:address":"Wireless Rd",
    "sg:city":"East Mt Gambier",
    "sg:classifiers":[
        {
            "category":"Professional",
            "subcategory":"Engineering",
            "type":"Services"
        }
    ],
    "sg:phone":"+61 8 8725 7216",
    "sg:postcode":"5290",
    "sg:province":"SA",
    "sg:tags":[
        "engineer"
    ],
    "wof:name":"McKee Engineering",
    "wof:placetype":"venue"
},
  "geometry": {"coordinates":[140.788986,-37.81411],"type":"Point"}
}