{
  "type": "Feature",
  "properties": {
    "addr:full":"Unit 11/ 23 Childs Rd Chipping Norton NSW 2170",
    "addr:housenumber":"/ 23",
    "addr:postcode":"2170",
    "addr:street":"Childs Rd",
    "iso:country":"AU",
    "sg:address":"Unit 11/ 23 Childs Rd",
    "sg:city":"Chipping Norton",
    "sg:classifiers":[
        {
            "category":"Shopping",
            "type":"Retail Goods"
        }
    ],
    "sg:phone":"+61 2 9755 4975",
    "sg:postcode":"2170",
    "sg:province":"NSW",
    "sg:tags":[
        "repair",
        "travel"
    ],
    "wof:name":"Kaili International",
    "wof:placetype":"venue"
},
  "geometry": {"coordinates":[150.96307373100001,-33.9187965393],"type":"Point"}
}