{
  "type": "Feature",
  "properties": {
    "iso:country":"AU",
    "sg:address":"Rode Rd",
    "sg:city":"Stafford Heights",
    "sg:classifiers":[
        {
            "category":"Food & Beverages",
            "subcategory":"Bakery",
            "type":"Retail Goods"
        }
    ],
    "sg:phone":"+61 7 3350 2020",
    "sg:postcode":"4053",
    "sg:province":"QLD",
    "sg:tags":[
        "baker"
    ],
    "wof:name":"Brumby's Bakery",
    "wof:placetype":"venue"
},
  "geometry": {"coordinates":[153.01271057100001,-27.3915519714],"type":"Point"}
}