{
  "type": "Feature",
  "properties": {
    "iso:country":"AU",
    "sg:address":"Warringal Medical Centre, Level 2",
    "sg:city":", Heidelberg",
    "sg:classifiers":[
        {
            "category":"Health Services",
            "subcategory":"Doctor",
            "type":"Services"
        }
    ],
    "sg:phone":"+61 3 9459 8633",
    "sg:postcode":"3084",
    "sg:province":"VIC",
    "sg:tags":[
        "medical",
        "practitioner"
    ],
    "wof:name":"MIA Victoria",
    "wof:placetype":"venue"
},
  "geometry": {"coordinates":[145.05604553200001,-37.7576293945],"type":"Point"}
}