{
  "type": "Feature",
  "properties": {
    "addr:full":"10 Casuarina Drv Cherrybrook NSW 2126",
    "addr:housenumber":"10",
    "addr:postcode":"2126",
    "addr:street":"Casuarina Drv",
    "iso:country":"AU",
    "sg:address":"10 Casuarina Drv",
    "sg:city":"Cherrybrook",
    "sg:classifiers":[
        {
            "category":"Social Services",
            "subcategory":"Retirement Home",
            "type":"Services"
        }
    ],
    "sg:phone":"+61 2 9481 0578",
    "sg:postcode":"2126",
    "sg:province":"NSW",
    "sg:tags":[
        "village"
    ],
    "wof:name":"Cherrybrook Gardens Retirement Village",
    "wof:placetype":"venue"
},
  "geometry": {"coordinates":[151.045578003,-33.7324905396],"type":"Point"}
}