{
  "type": "Feature",
  "properties": {
    "addr:full":"43 Vinter Ave Croydon VIC 3136",
    "addr:housenumber":"43",
    "addr:postcode":"3136",
    "addr:street":"Vinter Ave",
    "iso:country":"AU",
    "sg:address":"43 Vinter Ave",
    "sg:city":"Croydon",
    "sg:classifiers":[
        {
            "category":"Building & Trades",
            "subcategory":"Construction",
            "type":"Services"
        }
    ],
    "sg:phone":"+61 3 9725 0533",
    "sg:postcode":"3136",
    "sg:province":"VIC",
    "sg:tags":[
        "home",
        "air conditioning"
    ],
    "wof:name":"Cozy Air-Heating & Cooling",
    "wof:placetype":"venue"
},
  "geometry": {"coordinates":[145.27821350100001,-37.8058280945],"type":"Point"}
}