{
  "type": "Feature",
  "properties": {
    "addr:full":"28/ 30 Keon Pde Thomastown VIC 3074",
    "addr:housenumber":"28 / 30",
    "addr:postcode":"3074",
    "addr:street":"Keon Pde",
    "iso:country":"AU",
    "sg:address":"28/ 30 Keon Pde",
    "sg:city":"Thomastown",
    "sg:classifiers":[
        {
            "category":"Building & Trades",
            "subcategory":"Construction",
            "type":"Services"
        }
    ],
    "sg:phone":"+61 13 15 57",
    "sg:postcode":"3074",
    "sg:province":"VIC",
    "sg:tags":[
        "fencing",
        "contractor"
    ],
    "wof:name":"Cyclone Fences",
    "wof:placetype":"venue"
},
  "geometry": {"coordinates":[145.01580810600001,-37.6949882507],"type":"Point"}
}