{
  "type": "Feature",
  "properties": {
    "addr:full":"Hanger 2 Vickers Rd Mascot NSW 2020",
    "addr:housenumber":"2",
    "addr:postcode":"2020",
    "addr:street":"Hanger;Vickers Rd",
    "iso:country":"AU",
    "sg:address":"Hanger 2 Vickers Rd",
    "sg:city":"Mascot",
    "sg:classifiers":[
        {
            "category":"Communications",
            "type":"Services"
        }
    ],
    "sg:phone":"+61 2 9317 4049",
    "sg:postcode":"2020",
    "sg:province":"NSW",
    "sg:tags":[
        "equipment",
        "radio"
    ],
    "wof:name":"Silverwater Communications Pty Ltd",
    "wof:placetype":"venue"
},
  "geometry": {"coordinates":[151.18377685600001,-33.9356918335],"type":"Point"}
}