{
  "type": "Feature",
  "properties": {
    "addr:full":"33 Errol St North Melbourne VIC 3051",
    "addr:housenumber":"33",
    "addr:postcode":"3051",
    "addr:street":"Errol St",
    "iso:country":"AU",
    "sg:address":"33 Errol St",
    "sg:city":"North Melbourne",
    "sg:classifiers":[
        {
            "category":"Travel",
            "subcategory":"Hotels & Motels",
            "type":"Entertainment"
        }
    ],
    "sg:phone":"+61 3 9328 1983",
    "sg:postcode":"3051",
    "sg:province":"VIC",
    "sg:tags":[
        "accommodation"
    ],
    "wof:name":"Town Hall Hotel The",
    "wof:placetype":"venue"
},
  "geometry": {"coordinates":[144.94926452600001,-37.8041419983],"type":"Point"}
}