{
  "type": "Feature",
  "properties": {
    "addr:full":"7 Groome Crt Altona Meadows VIC 3028",
    "addr:housenumber":"7",
    "addr:postcode":"3028",
    "addr:street":"Groome Crt",
    "iso:country":"AU",
    "sg:address":"7 Groome Crt",
    "sg:city":"Altona Meadows",
    "sg:classifiers":[
        {
            "category":"Building & Trades",
            "subcategory":"Plumbing",
            "type":"Services"
        }
    ],
    "sg:phone":"+61 3 9315 6500",
    "sg:postcode":"3028",
    "sg:province":"VIC",
    "sg:tags":[
        "plumber",
        "gasfitters"
    ],
    "wof:name":"Dean Stephen",
    "wof:placetype":"venue"
},
  "geometry": {"coordinates":[144.78320299999999,-37.893711],"type":"Point"}
}