{
  "type": "Feature",
  "properties": {
    "iso:country":"AU",
    "sg:address":"7 Avondale Pl",
    "sg:city":"Tallai",
    "sg:classifiers":[
        {
            "category":"Professional",
            "subcategory":"Art Services",
            "type":"Services"
        }
    ],
    "sg:phone":"+61 421 857 742",
    "sg:postcode":"4213",
    "sg:province":"QLD",
    "sg:tags":[
        "graphic",
        "designer"
    ],
    "wof:name":"Paul Mann",
    "wof:placetype":"venue"
},
  "geometry": {"coordinates":[153.334259033,-28.0779514313],"type":"Point"}
}