{
  "type": "Feature",
  "properties": {
    "addr:full":"41 Balcombe Rd Mentone VIC 3194",
    "addr:housenumber":"41",
    "addr:postcode":"3194",
    "addr:street":"Balcombe Rd",
    "iso:country":"AU",
    "sg:address":"41 Balcombe Rd",
    "sg:city":"Mentone",
    "sg:classifiers":[
        {
            "category":"Health Services",
            "subcategory":"Doctor",
            "type":"Services"
        }
    ],
    "sg:phone":"+61 3 9583 6949",
    "sg:postcode":"3194",
    "sg:province":"VIC",
    "sg:tags":[
        "medical",
        "practitioner"
    ],
    "wof:name":"MIA Victoria",
    "wof:placetype":"venue"
},
  "geometry": {"coordinates":[145.067596436,-37.9816932678],"type":"Point"}
}