{
  "type": "Feature",
  "properties": {
    "addr:full":"12 Heather Crt Woodford QLD 4514",
    "addr:housenumber":"12",
    "addr:postcode":"4514",
    "addr:street":"Heather Crt",
    "iso:country":"AU",
    "sg:address":"12 Heather Crt",
    "sg:city":"Woodford",
    "sg:classifiers":[
        {
            "category":"Building & Trades",
            "subcategory":"Construction",
            "type":"Services"
        }
    ],
    "sg:phone":"+61 7 5422 9993",
    "sg:postcode":"4514",
    "sg:province":"QLD",
    "sg:tags":[
        "earth",
        "excavating",
        "moving",
        "contractor"
    ],
    "wof:name":"GT Plant Hire Pty Ltd",
    "wof:placetype":"venue"
},
  "geometry": {"coordinates":[152.77032500000001,-26.967035],"type":"Point"}
}