{
  "type": "Feature",
  "properties": {
    "addr:full":"Kiosk 70 Magid Drv Fountain Gate VIC 3805",
    "addr:postcode":"3805",
    "addr:street":"Magid Drv Fountain",
    "iso:country":"AU",
    "sg:address":"Kiosk 70 Magid Drv",
    "sg:city":"Fountain Gate",
    "sg:classifiers":[
        {
            "category":"Food & Beverages",
            "subcategory":"Bakery",
            "type":"Retail Goods"
        }
    ],
    "sg:phone":"+61 3 9705 2622",
    "sg:postcode":"3805",
    "sg:province":"VIC",
    "sg:tags":[
        "baker"
    ],
    "wof:name":"Muffin Break",
    "wof:placetype":"venue"
},
  "geometry": {"coordinates":[145.30024700000001,-38.016224],"type":"Point"}
}