{
  "type": "Feature",
  "properties": {
    "addr:full":"368 Elizabeth St Melbourne VIC 3000",
    "addr:housenumber":"368",
    "addr:postcode":"3000",
    "addr:street":"Elizabeth St",
    "iso:country":"AU",
    "sg:address":"368 Elizabeth St",
    "sg:city":"Melbourne",
    "sg:classifiers":[
        {
            "category":"Health Services",
            "subcategory":"Health Practitioner",
            "type":"Services"
        }
    ],
    "sg:phone":"+61 3 9662 9911",
    "sg:postcode":"3000",
    "sg:province":"VIC",
    "sg:tags":[
        "naturopath"
    ],
    "wof:name":"Melbourne College of Natural Medicine",
    "wof:placetype":"venue"
},
  "geometry": {"coordinates":[144.96131897000001,-37.8098258972],"type":"Point"}
}