{
  "type": "Feature",
  "properties": {
    "iso:country":"AU",
    "sg:address":"24 William St",
    "sg:city":"Brookvale",
    "sg:classifiers":[
        {
            "category":"Manufacturing",
            "subcategory":"Rubber & Plastics",
            "type":"Manufacturing & Wholesale Goods"
        }
    ],
    "sg:phone":"+61 2 9905 1411",
    "sg:postcode":"2100",
    "sg:province":"NSW",
    "sg:tags":[
        "wholesaler",
        "product",
        "mfrs"
    ],
    "wof:name":"Rubberworld",
    "wof:placetype":"venue"
},
  "geometry": {"coordinates":[151.2706604,-33.768321991],"type":"Point"}
}