{
  "type": "Feature",
  "properties": {
    "addr:full":"128 Grandview Rd Pullenvale QLD 4069",
    "addr:housenumber":"128",
    "addr:postcode":"4069",
    "addr:street":"Grandview Rd",
    "iso:country":"AU",
    "sg:address":"128 Grandview Rd",
    "sg:city":"Pullenvale",
    "sg:classifiers":[
        {
            "category":"Building & Trades",
            "subcategory":"Construction",
            "type":"Services"
        }
    ],
    "sg:phone":"+61 418 795 241",
    "sg:postcode":"4069",
    "sg:province":"QLD",
    "sg:tags":[
        "earth",
        "excavating",
        "moving",
        "contractor"
    ],
    "wof:name":"Godson Groundworks",
    "wof:placetype":"venue"
},
  "geometry": {"coordinates":[152.894287109,-27.5316638947],"type":"Point"}
}