{
  "type": "Feature",
  "properties": {
    "addr:full":"21 Ebsworth Rd Rose Bay NSW 2029",
    "addr:housenumber":"21",
    "addr:postcode":"2029",
    "addr:street":"Ebsworth Rd",
    "iso:country":"AU",
    "sg:address":"21 Ebsworth Rd",
    "sg:city":"Rose Bay",
    "sg:classifiers":[
        {
            "category":"Manufacturing",
            "subcategory":"Textiles",
            "type":"Manufacturing & Wholesale Goods"
        }
    ],
    "sg:phone":"+61 2 9371 4353",
    "sg:postcode":"2029",
    "sg:province":"NSW",
    "sg:tags":[
        "agent"
    ],
    "wof:name":"Sonnentex Pty Ltd",
    "wof:placetype":"venue"
},
  "geometry": {"coordinates":[151.27636718799999,-33.8677787781],"type":"Point"}
}