{
  "type": "Feature",
  "properties": {
    "addr:full":"15 Bermill St Rockdale NSW 2216",
    "addr:housenumber":"15",
    "addr:postcode":"2216",
    "addr:street":"Bermill St",
    "iso:country":"AU",
    "sg:address":"15 Bermill St",
    "sg:city":"Rockdale",
    "sg:classifiers":[
        {
            "category":"Home & Garden",
            "subcategory":"Household Appliances",
            "type":"Retail Goods"
        }
    ],
    "sg:phone":"+61 2 9599 9874",
    "sg:postcode":"2216",
    "sg:province":"NSW",
    "sg:tags":[
        "equipment",
        "gas"
    ],
    "wof:name":"Gas & Electric Appliances Warehouse",
    "wof:placetype":"venue"
},
  "geometry": {"coordinates":[151.14672899999999,-33.960304],"type":"Point"}
}