{
  "type": "Feature",
  "properties": {
    "addr:full":"1 Hibernia Crs Brinkin NT 0810",
    "addr:housenumber":"1",
    "addr:postcode":"nt 0810",
    "addr:street":"Hibernia Crs",
    "iso:country":"AU",
    "sg:address":"1 Hibernia Crs",
    "sg:city":"Brinkin",
    "sg:classifiers":[
        {
            "category":"Building & Trades",
            "subcategory":"Construction",
            "type":"Services"
        }
    ],
    "sg:phone":"+61 8 8927 0115",
    "sg:postcode":"0810",
    "sg:province":"NT",
    "sg:tags":[
        "contractor"
    ],
    "wof:name":"Zaroufis M",
    "wof:placetype":"venue"
},
  "geometry": {"coordinates":[130.87338256800001,-12.3654003143],"type":"Point"}
}