{
  "type": "Feature",
  "properties": {
    "addr:full":"PO Box 537 Busselton WA 6280",
    "addr:postcode":"6280",
    "iso:country":"AU",
    "sg:address":"PO Box 537",
    "sg:city":"Busselton",
    "sg:classifiers":[
        {
            "category":"Train Station",
            "subcategory":"Rail",
            "type":"Transportation"
        }
    ],
    "sg:phone":"+61 8 9753 1160",
    "sg:postcode":"6280",
    "sg:province":"WA",
    "sg:tags":[
        "goat",
        "farmer"
    ],
    "wof:name":"Boer Bok Goat Stud",
    "wof:placetype":"venue"
},
  "geometry": {"coordinates":[115.344818115,-33.652141571],"type":"Point"}
}