{
  "type": "Feature",
  "properties": {
    "addr:full":"300 Little Lonsdale St Melbourne VIC 3000",
    "addr:housenumber":"300",
    "addr:postcode":"3000",
    "addr:street":"Little Lonsdale St",
    "iso:country":"AU",
    "sg:address":"300 Little Lonsdale St",
    "sg:city":"Melbourne",
    "sg:classifiers":[
        {
            "category":"Real Estate",
            "subcategory":"Developer",
            "type":"Services"
        }
    ],
    "sg:phone":"+61 3 9670 7788",
    "sg:postcode":"3000",
    "sg:province":"VIC",
    "sg:tags":[
        "development"
    ],
    "wof:name":"Merlin Properties Pty Ltd",
    "wof:placetype":"venue"
},
  "geometry": {"coordinates":[144.96055602999999,-37.8115272522],"type":"Point"}
}