{
  "type": "Feature",
  "properties": {
    "addr:full":"389 Maroondah Hwy Ringwood VIC 3134",
    "addr:housenumber":"389",
    "addr:postcode":"3134",
    "addr:street":"Maroondah Hwy",
    "iso:country":"AU",
    "sg:address":"389 Maroondah Hwy",
    "sg:city":"Ringwood",
    "sg:classifiers":[
        {
            "category":"Home & Garden",
            "subcategory":"Building Materials",
            "type":"Retail Goods"
        }
    ],
    "sg:phone":"+61 3 9879 5399",
    "sg:postcode":"3134",
    "sg:province":"VIC",
    "sg:tags":[
        "plaster",
        "plasterboard",
        "supply"
    ],
    "wof:name":"Boral Plasterboard",
    "wof:placetype":"venue"
},
  "geometry": {"coordinates":[145.24583435100001,-37.8039283752],"type":"Point"}
}