{
  "type": "Feature",
  "properties": {
    "iso:country":"AU",
    "sg:address":"U1/ 129 Canning Hwy",
    "sg:city":"South Perth",
    "sg:classifiers":[
        {
            "category":"Retail",
            "subcategory":"Self-service Laundry",
            "type":"Services"
        }
    ],
    "sg:phone":"+61 8 9474 3388",
    "sg:postcode":"6151",
    "sg:province":"WA",
    "wof:name":"Marion Dawn's Laundrette",
    "wof:placetype":"venue"
},
  "geometry": {"coordinates":[115.876183,-31.981897],"type":"Point"}
}