{
  "type": "Feature",
  "properties": {
    "iso:country":"AU",
    "sg:address":"Suite 6/7- 12 Alma Rd",
    "sg:city":"New Lambton",
    "sg:classifiers":[
        {
            "category":"Insurance",
            "subcategory":"Insurance Agent",
            "type":"Services"
        }
    ],
    "sg:phone":"+61 2 4950 9989",
    "sg:postcode":"2305",
    "sg:province":"NSW",
    "wof:name":"Sonter Grahame",
    "wof:placetype":"venue"
},
  "geometry": {"coordinates":[151.719604,-32.919868],"type":"Point"}
}