{
  "type": "Feature",
  "properties": {
    "addr:full":"Kororoit Creek Rd Altona VIC 3018",
    "addr:postcode":"3018",
    "addr:street":"Creek Rd",
    "iso:country":"AU",
    "sg:address":"Kororoit Creek Rd",
    "sg:city":"Altona",
    "sg:classifiers":[
        {
            "category":"Shopping",
            "type":"Retail Goods"
        }
    ],
    "sg:phone":"+61 3 9226 3500",
    "sg:postcode":"3018",
    "sg:province":"VIC",
    "sg:tags":[
        "product",
        "plastic"
    ],
    "wof:name":"Dow Chemical (Aust) Ltd",
    "wof:placetype":"venue"
},
  "geometry": {"coordinates":[144.827438355,-37.8492012024],"type":"Point"}
}