{
  "type": "Feature",
  "properties": {
    "iso:country":"AU",
    "sg:address":"Gove Rd",
    "sg:city":"Roper River",
    "sg:classifiers":[
        {
            "category":"Food & Beverages",
            "subcategory":"Groceries & Convenience Stores",
            "type":"Retail Goods"
        }
    ],
    "sg:phone":"+61 8 8975 4390",
    "sg:postcode":"0852",
    "sg:province":"NT",
    "wof:name":"Mainoru Outstation Store",
    "wof:placetype":"venue"
},
  "geometry": {"coordinates":[135.33316,-14.73585],"type":"Point"}
}