{
  "type": "Feature",
  "properties": {
    "iso:country":"AU",
    "sg:address":"12 Wey St",
    "sg:city":"Blackwater",
    "sg:classifiers":[
        {
            "category":"Utilities",
            "subcategory":"Electric",
            "type":"Services"
        }
    ],
    "sg:phone":"+61 7 4982 5549",
    "sg:postcode":"4717",
    "sg:province":"QLD",
    "sg:tags":[
        "electrical",
        "contractor"
    ],
    "wof:name":"Chris Ralphs",
    "wof:placetype":"venue"
},
  "geometry": {"coordinates":[148.87858600000001,-23.583191],"type":"Point"}
}