{
  "type": "Feature",
  "properties": {
    "addr:full":"Lot 6 Brush Rd Ourimbah NSW 2258",
    "addr:postcode":"2258",
    "addr:street":"Brush Rd",
    "iso:country":"AU",
    "sg:address":"Lot 6 Brush Rd",
    "sg:city":"Ourimbah",
    "sg:classifiers":[
        {
            "category":"Professional",
            "subcategory":"Art Services",
            "type":"Services"
        }
    ],
    "sg:phone":"+61 2 4388 2741",
    "sg:postcode":"2258",
    "sg:province":"NSW",
    "sg:tags":[
        "artist"
    ],
    "wof:name":"Greg Somers",
    "wof:placetype":"venue"
},
  "geometry": {"coordinates":[151.39662170400001,-33.3645133972],"type":"Point"}
}