{
  "type": "Feature",
  "properties": {
    "addr:full":"1 Mungerie Rd Rouse Hill NSW 2155",
    "addr:housenumber":"1",
    "addr:postcode":"2155",
    "addr:street":"Mungerie Rd",
    "iso:country":"AU",
    "sg:address":"1 Mungerie Rd",
    "sg:city":"Rouse Hill",
    "sg:classifiers":[
        {
            "category":"Education",
            "subcategory":"School",
            "type":"Public Place"
        }
    ],
    "sg:phone":"+61 2 9629 3942",
    "sg:postcode":"2155",
    "sg:province":"NSW",
    "wof:name":"Armenian-St Gregorys Armenian School",
    "wof:placetype":"venue"
},
  "geometry": {"coordinates":[150.939544678,-33.6925582886],"type":"Point"}
}