{
  "type": "Feature",
  "properties": {
    "addr:full":"1275 North East Rd Ridgehaven SA 5097",
    "addr:housenumber":"1275",
    "addr:postcode":"5097",
    "addr:street":"North East Rd",
    "iso:country":"AU",
    "sg:address":"1275 North East Rd",
    "sg:city":"Ridgehaven",
    "sg:classifiers":[
        {
            "category":"Personal",
            "subcategory":"Massage",
            "type":"Services"
        }
    ],
    "sg:phone":"+61 8 8264 1397",
    "sg:postcode":"5097",
    "sg:province":"SA",
    "sg:tags":[
        "therapy"
    ],
    "wof:name":"Julie Zanelli",
    "wof:placetype":"venue"
},
  "geometry": {"coordinates":[138.71803283700001,-34.8208084106],"type":"Point"}
}