{
  "type": "Feature",
  "properties": {
    "addr:full":"Logan Specialist Centre, Shop 10, 3-5 Dennis Rd Springwood QLD 4127",
    "addr:housenumber":"shop 10 3-5",
    "addr:postcode":"4127",
    "addr:street":"Dennis Rd",
    "iso:country":"AU",
    "sg:address":"Logan Specialist Centre, Shop 10, 3-5 Dennis Rd",
    "sg:city":"Springwood",
    "sg:classifiers":[
        {
            "category":"Health Services",
            "subcategory":"Doctor",
            "type":"Services"
        }
    ],
    "sg:phone":"+61 7 3208 5552",
    "sg:postcode":"4127",
    "sg:province":"QLD",
    "sg:tags":[
        "medical",
        "practitioner"
    ],
    "wof:name":"Taylor Kerry Dr",
    "wof:placetype":"venue"
},
  "geometry": {"coordinates":[153.12806701700001,-27.6213874817],"type":"Point"}
}