{
  "type": "Feature",
  "properties": {
    "addr:full":"7 Curtawilla St Banora Point NSW 2486",
    "addr:housenumber":"7",
    "addr:postcode":"2486",
    "addr:street":"Curtawilla St",
    "iso:country":"AU",
    "sg:address":"7 Curtawilla St",
    "sg:city":"Banora Point",
    "sg:classifiers":[
        {
            "category":"Building & Trades",
            "subcategory":"Landscaping Services",
            "type":"Services"
        }
    ],
    "sg:phone":"+61 7 5524 1656",
    "sg:postcode":"2486",
    "sg:province":"NSW",
    "sg:tags":[
        "stump",
        "tree",
        "felling",
        "removal"
    ],
    "wof:name":"Harlock Tree Surgery",
    "wof:placetype":"venue"
},
  "geometry": {"coordinates":[153.54124450699999,-28.2293949127],"type":"Point"}
}