{
  "type": "Feature",
  "properties": {
    "addr:full":"Frederick St Gosford East NSW 2250",
    "addr:postcode":"2250",
    "addr:street":"Frederick St",
    "iso:country":"AU",
    "sg:address":"Frederick St",
    "sg:city":"Gosford East",
    "sg:classifiers":[
        {
            "category":"Education",
            "subcategory":"School",
            "type":"Public Place"
        }
    ],
    "sg:phone":"+61 2 4324 5300",
    "sg:postcode":"2250",
    "sg:province":"NSW",
    "wof:name":"St Edward's Christian Brothers",
    "wof:placetype":"venue"
},
  "geometry": {"coordinates":[151.34667968799999,-33.4346427917],"type":"Point"}
}