{
  "type": "Feature",
  "properties": {
    "iso:country":"AU",
    "sg:address":"48 Mount Perry Rd",
    "sg:city":"Bundaberg",
    "sg:classifiers":[
        {
            "category":"Building & Trades",
            "subcategory":"Construction",
            "type":"Services"
        }
    ],
    "sg:phone":"+61 7 4152 9529",
    "sg:postcode":"4670",
    "sg:province":"QLD",
    "sg:tags":[
        "road",
        "contractor"
    ],
    "wof:name":"Stephen Bergovicz",
    "wof:placetype":"venue"
},
  "geometry": {"coordinates":[152.335037231,-24.8503437042],"type":"Point"}
}