{
  "type": "Feature",
  "properties": {
    "addr:full":"Benwell Rd Townsville Port Townsville QLD 4810",
    "addr:postcode":"4810",
    "addr:street":"Benwell Rd",
    "iso:country":"AU",
    "sg:address":"Benwell Rd",
    "sg:city":"Townsville Port Townsville",
    "sg:classifiers":[
        {
            "category":"Military Area",
            "subcategory":"Army Base",
            "type":"Public Place"
        }
    ],
    "sg:phone":"+61 1800 671 062",
    "sg:postcode":"4810",
    "sg:province":"QLD",
    "sg:tags":[
        "wholesaler",
        "mfrs",
        "cement",
        "supply"
    ],
    "wof:name":"Cement Australia",
    "wof:placetype":"venue"
},
  "geometry": {"coordinates":[146.834259,-19.253157],"type":"Point"}
}