{
  "type": "Feature",
  "properties": {
    "addr:full":"123 Maroondah Hwy Healesville VIC 3777",
    "addr:housenumber":"123",
    "addr:postcode":"3777",
    "addr:street":"Maroondah Hwy",
    "iso:country":"AU",
    "sg:address":"123 Maroondah Hwy",
    "sg:city":"Healesville",
    "sg:classifiers":[
        {
            "category":"Autos & Motor Vehicles",
            "subcategory":"Fuel & Gas Station",
            "type":"Retail Goods"
        }
    ],
    "sg:phone":"+61 3 5962 4286",
    "sg:postcode":"3777",
    "sg:province":"VIC",
    "wof:name":"Sanctuary Service Station",
    "wof:placetype":"venue"
},
  "geometry": {"coordinates":[145.51565600000001,-37.654041],"type":"Point"}
}