{
  "type": "Feature",
  "properties": {
    "iso:country":"AU",
    "sg:address":"121 Steele St",
    "sg:city":"Devonport",
    "sg:classifiers":[
        {
            "category":"Retail",
            "subcategory":"Repair Shop",
            "type":"Services"
        }
    ],
    "sg:phone":"+61 3 6424 4453",
    "sg:postcode":"7310",
    "sg:province":"TAS",
    "sg:tags":[
        "machine",
        "repairs",
        "part",
        "dryer",
        "washing"
    ],
    "wof:name":"Northwest Appliance Service",
    "wof:placetype":"venue"
},
  "geometry": {"coordinates":[146.34996032699999,-41.180103302],"type":"Point"}
}