{
  "type": "Feature",
  "properties": {
    "iso:country":"AU",
    "sg:address":"Cnr Connors Rd & Farrelys La",
    "sg:city":"Paget",
    "sg:classifiers":[
        {
            "category":"Building & Trades",
            "subcategory":"Cleaning & Sanitation",
            "type":"Services"
        }
    ],
    "sg:phone":"+61 7 4944 5400",
    "sg:postcode":"4740",
    "sg:province":"QLD",
    "sg:tags":[
        "abrasive",
        "blasting"
    ],
    "wof:name":"Emeco",
    "wof:placetype":"venue"
},
  "geometry": {"coordinates":[149.161179,-21.169504],"type":"Point"}
}