{
  "type": "Feature",
  "properties": {
    "addr:full":"115 Wattletree Rd Malvern VIC 3144",
    "addr:housenumber":"115",
    "addr:postcode":"3144",
    "addr:street":"Wattletree Rd",
    "iso:country":"AU",
    "sg:address":"115 Wattletree Rd",
    "sg:city":"Malvern",
    "sg:classifiers":[
        {
            "category":"Personal",
            "subcategory":"Barber",
            "type":"Services"
        }
    ],
    "sg:phone":"+61 3 9500 0896",
    "sg:postcode":"3144",
    "sg:province":"VIC",
    "wof:name":"The Malvern Barber Shop",
    "wof:placetype":"venue"
},
  "geometry": {"coordinates":[145.02850341800001,-37.8622283936],"type":"Point"}
}