{
  "type": "Feature",
  "properties": {
    "addr:full":"676 Wynnum Rd Morningside QLD 4170",
    "addr:housenumber":"676",
    "addr:postcode":"4170",
    "addr:street":"Wynnum Rd",
    "iso:country":"AU",
    "sg:address":"676 Wynnum Rd",
    "sg:city":"Morningside",
    "sg:classifiers":[
        {
            "category":"Real Estate",
            "subcategory":"Real Estate Agent",
            "type":"Services"
        }
    ],
    "sg:phone":"+61 7 3899 1433",
    "sg:postcode":"4170",
    "sg:province":"QLD",
    "wof:name":"The Professionals Harry MacKenzie",
    "wof:placetype":"venue"
},
  "geometry": {"coordinates":[153.07142639200001,-27.4685077667],"type":"Point"}
}