{
  "type": "Feature",
  "properties": {
    "addr:full":"283 West Tamar Rd Riverside TAS 7250",
    "addr:housenumber":"283",
    "addr:postcode":"7250",
    "addr:street":"West Tamar Rd",
    "iso:country":"AU",
    "sg:address":"283 West Tamar Rd",
    "sg:city":"Riverside",
    "sg:classifiers":[
        {
            "category":"Building & Trades",
            "subcategory":"Plumbing",
            "type":"Services"
        }
    ],
    "sg:phone":"+61 419 539 063",
    "sg:postcode":"7250",
    "sg:province":"TAS",
    "sg:tags":[
        "plumber",
        "gasfitters"
    ],
    "wof:name":"McCoach Plumbing",
    "wof:placetype":"venue"
},
  "geometry": {"coordinates":[147.10255432100001,-41.4155845642],"type":"Point"}
}