{
  "type": "Feature",
  "properties": {
    "addr:full":"Nerang-Broadbeach Rd Nerang QLD 4211",
    "addr:postcode":"4211",
    "addr:street":"Nerang-Broadbeach Rd",
    "iso:country":"AU",
    "sg:address":"Nerang-Broadbeach Rd",
    "sg:city":"Nerang",
    "sg:classifiers":[
        {
            "category":"Retail",
            "subcategory":"Funeral Services",
            "type":"Services"
        }
    ],
    "sg:phone":"+61 7 5596 4908",
    "sg:postcode":"4211",
    "sg:province":"QLD",
    "sg:tags":[
        "director"
    ],
    "wof:name":"Earl E Blooms Florist",
    "wof:placetype":"venue"
},
  "geometry": {"coordinates":[153.34016418499999,-27.9934844971],"type":"Point"}
}