{
  "type": "Feature",
  "properties": {
    "addr:full":"Unit 3/1 Stout Rd (cnr Kurrajong Ave) Mt Druitt NSW 2770",
    "addr:housenumber":"1",
    "addr:postcode":"2770",
    "addr:street":"Stout Rd Cnr Kurrajong Ave Mt",
    "iso:country":"AU",
    "sg:address":"Unit 3/1 Stout Rd (cnr Kurrajong Ave)",
    "sg:city":"Mt Druitt",
    "sg:classifiers":[
        {
            "category":"Banks & Credit Unions",
            "subcategory":"Investment Brokerage",
            "type":"Services"
        }
    ],
    "sg:phone":"+61 2 9625 4994",
    "sg:postcode":"2770",
    "sg:province":"NSW",
    "sg:tags":[
        "radiator",
        "motor"
    ],
    "wof:name":"E.T. Auto Radiator Repairs",
    "wof:placetype":"venue"
},
  "geometry": {"coordinates":[150.811004639,-33.7670783997],"type":"Point"}
}