{
  "type": "Feature",
  "properties": {
    "iso:country":"AU",
    "sg:address":"97 Albion Rd",
    "sg:city":"Albion",
    "sg:classifiers":[
        {
            "category":"Retail",
            "subcategory":"Veterinary Services",
            "type":"Services"
        }
    ],
    "sg:phone":"+61 7 3357 7849",
    "sg:postcode":"4010",
    "sg:province":"QLD",
    "sg:tags":[
        "surgeon"
    ],
    "wof:name":"Albion Vet",
    "wof:placetype":"venue"
},
  "geometry": {"coordinates":[153.03717040999999,-27.4292125702],"type":"Point"}
}