{
  "type": "Feature",
  "properties": {
    "addr:full":"45 South St Crows Nest QLD 4355",
    "addr:housenumber":"45",
    "addr:postcode":"4355",
    "addr:street":"South St",
    "iso:country":"AU",
    "sg:address":"45 South St",
    "sg:city":"Crows Nest",
    "sg:classifiers":[
        {
            "category":"Building & Trades",
            "subcategory":"Landscaping Services",
            "type":"Services"
        }
    ],
    "sg:phone":"+61 407 981 737",
    "sg:postcode":"4355",
    "sg:province":"QLD",
    "sg:tags":[
        "gardener"
    ],
    "wof:name":"N & B Gardens & Horticulture Services",
    "wof:placetype":"venue"
},
  "geometry": {"coordinates":[152.059967,-27.266958],"type":"Point"}
}