{
  "type": "Feature",
  "properties": {
    "addr:full":"PO Box 462 Tully QLD 4854",
    "addr:postcode":"4854",
    "iso:country":"AU",
    "sg:address":"PO Box 462",
    "sg:city":"Tully",
    "sg:classifiers":[
        {
            "category":"Personal",
            "subcategory":"Beauty Salon",
            "type":"Services"
        }
    ],
    "sg:phone":"+61 7 4068 1976",
    "sg:postcode":"4854",
    "sg:province":"QLD",
    "wof:name":"Perfection Plus Skin Care Clinic",
    "wof:placetype":"venue"
},
  "geometry": {"coordinates":[145.93263244600001,-17.933889389],"type":"Point"}
}