{
  "type": "Feature",
  "properties": {
    "iso:country":"AU",
    "sg:address":"33 Provident Ave",
    "sg:city":"Glynde",
    "sg:classifiers":[
        {
            "category":"Retail",
            "subcategory":"Repair Shop",
            "type":"Services"
        }
    ],
    "sg:phone":"+61 8 8365 7044",
    "sg:postcode":"5070",
    "sg:province":"SA",
    "sg:tags":[
        "upholsterer"
    ],
    "wof:name":"Bruno Damin",
    "wof:placetype":"venue"
},
  "geometry": {"coordinates":[138.65574645999999,-34.8943862915],"type":"Point"}
}