{
  "type": "Feature",
  "properties": {
    "iso:country":"AU",
    "sg:address":"3/ 32 Main St",
    "sg:city":"Samford",
    "sg:classifiers":[
        {
            "category":"Health Services",
            "subcategory":"Dentist",
            "type":"Services"
        }
    ],
    "sg:phone":"+61 7 3289 6699",
    "sg:postcode":"4520",
    "sg:province":"QLD",
    "wof:name":"Tucker Ed Dr",
    "wof:placetype":"venue"
},
  "geometry": {"coordinates":[152.88699299999999,-27.370071],"type":"Point"}
}