{
  "type": "Feature",
  "properties": {
    "addr:full":"12 Fairview St Dubbo NSW 2830",
    "addr:housenumber":"12",
    "addr:postcode":"2830",
    "addr:street":"Fairview St",
    "iso:country":"AU",
    "sg:address":"12 Fairview St",
    "sg:city":"Dubbo",
    "sg:classifiers":[
        {
            "category":"Home & Garden",
            "subcategory":"Carpets & Floor Coverings",
            "type":"Retail Goods"
        }
    ],
    "sg:phone":"+61 2 6882 4623",
    "sg:postcode":"2830",
    "sg:province":"NSW",
    "sg:tags":[
        "tile",
        "wall",
        "layer"
    ],
    "wof:name":"Triplett K J & C A",
    "wof:placetype":"venue"
},
  "geometry": {"coordinates":[148.61183166500001,-32.2732887268],"type":"Point"}
}