{
  "type": "Feature",
  "properties": {
    "addr:full":"224 Henley Beach Rd Torrensville SA 5031",
    "addr:housenumber":"224",
    "addr:postcode":"5031",
    "addr:street":"Henley Beach Rd",
    "iso:country":"AU",
    "sg:address":"224 Henley Beach Rd",
    "sg:city":"Torrensville",
    "sg:classifiers":[
        {
            "category":"Shopping",
            "subcategory":"Clothing, Apparel, & Fashions",
            "type":"Retail Goods"
        }
    ],
    "sg:phone":"+61 8 8234 1466",
    "sg:postcode":"5031",
    "sg:province":"SA",
    "sg:tags":[
        "uniform"
    ],
    "wof:name":"Adelaide Career Apparel",
    "wof:placetype":"venue"
},
  "geometry": {"coordinates":[138.55566406200001,-34.9241867065],"type":"Point"}
}