{
  "type": "Feature",
  "properties": {
    "addr:full":"Shop 11 Cooper St Cessnock NSW 2325",
    "addr:housenumber":"shop 11",
    "addr:postcode":"2325",
    "addr:street":"Cooper St",
    "iso:country":"AU",
    "sg:address":"Shop 11 Cooper St",
    "sg:city":"Cessnock",
    "sg:classifiers":[
        {
            "category":"Utilities",
            "subcategory":"Mobile Phone",
            "type":"Services"
        }
    ],
    "sg:phone":"+61 2 4991 2800",
    "sg:postcode":"2325",
    "sg:province":"NSW",
    "sg:tags":[
        "repair",
        "telephone"
    ],
    "wof:name":"Network Communications",
    "wof:placetype":"venue"
},
  "geometry": {"coordinates":[151.358612061,-32.8359146118],"type":"Point"}
}