{
  "type": "Feature",
  "properties": {
    "iso:country":"AU",
    "sg:address":"6/14 Paisley Drv",
    "sg:city":"Lawnton",
    "sg:classifiers":[
        {
            "category":"Social Services",
            "subcategory":"Adult Care",
            "type":"Services"
        }
    ],
    "sg:phone":"+61 7 3888 6013",
    "sg:postcode":"4501",
    "sg:province":"QLD",
    "sg:tags":[
        "towing"
    ],
    "wof:name":"Pine City Towing",
    "wof:placetype":"venue"
},
  "geometry": {"coordinates":[152.98823547399999,-27.2832183838],"type":"Point"}
}