{
  "type": "Feature",
  "properties": {
    "iso:country":"AU",
    "sg:address":"391 Canterbury Rd",
    "sg:city":"Surrey Hills",
    "sg:classifiers":[
        {
            "category":"Arena",
            "subcategory":"Sports Club",
            "type":"Entertainment"
        }
    ],
    "sg:phone":"+61 3 9830 4588",
    "sg:postcode":"3127",
    "sg:province":"VIC",
    "sg:tags":[
        "organisation",
        "sporting"
    ],
    "wof:name":"Australian Gymnastic Federation",
    "wof:placetype":"venue"
},
  "geometry": {"coordinates":[145.10086059599999,-37.8262405396],"type":"Point"}
}