{
  "type": "Feature",
  "properties": {
    "iso:country":"AU",
    "sg:address":"6 Park St",
    "sg:city":"Peakhurst",
    "sg:classifiers":[
        {
            "category":"Health Services",
            "subcategory":"Health Practitioner",
            "type":"Services"
        }
    ],
    "sg:phone":"+61 2 9534 6638",
    "sg:postcode":"2210",
    "sg:province":"NSW",
    "sg:tags":[
        "physiotherapist"
    ],
    "sg:website":"http://www.physiotherapy.asn.au",
    "wof:name":"Peakhurst Physiotherapy & Sports Injury Centre",
    "wof:placetype":"venue"
},
  "geometry": {"coordinates":[151.057434,-33.963898],"type":"Point"}
}