{
  "type": "Feature",
  "properties": {
    "addr:full":"38 Stephen Rd Dandenong VIC 3175",
    "addr:housenumber":"38",
    "addr:postcode":"3175",
    "addr:street":"Stephen Rd",
    "iso:country":"AU",
    "sg:address":"38 Stephen Rd",
    "sg:city":"Dandenong",
    "sg:classifiers":[
        {
            "category":"Manufacturing",
            "subcategory":"Building Materials",
            "type":"Manufacturing & Wholesale Goods"
        }
    ],
    "sg:phone":"+61 3 9794 6533",
    "sg:postcode":"3175",
    "sg:province":"VIC",
    "sg:tags":[
        "equipment",
        "handling"
    ],
    "wof:name":"Andritz Pty Ltd",
    "wof:placetype":"venue"
},
  "geometry": {"coordinates":[145.21287536599999,-38.0076332092],"type":"Point"}
}