{
  "type": "Feature",
  "properties": {
    "addr:full":"96 Herbert St Gulgong NSW 2852",
    "addr:housenumber":"96",
    "addr:postcode":"2852",
    "addr:street":"Herbert St",
    "iso:country":"AU",
    "sg:address":"96 Herbert St",
    "sg:city":"Gulgong",
    "sg:classifiers":[
        {
            "category":"Building & Trades",
            "subcategory":"Construction",
            "type":"Services"
        }
    ],
    "sg:phone":"+61 2 6374 2148",
    "sg:postcode":"2852",
    "sg:province":"NSW",
    "sg:tags":[
        "home",
        "air conditioning"
    ],
    "wof:name":"McConnell Air & Electrical Services Pty Ltd",
    "wof:placetype":"venue"
},
  "geometry": {"coordinates":[149.53320299999999,-32.363243],"type":"Point"}
}