{
  "type": "Feature",
  "properties": {
    "iso:country":"AU",
    "sg:address":"101 Adelaide St",
    "sg:city":"West Ryde",
    "sg:classifiers":[
        {
            "category":"Shopping",
            "subcategory":"Stationery & Office Supplies",
            "type":"Retail Goods"
        }
    ],
    "sg:phone":"+61 2 9874 5920",
    "sg:postcode":"2114",
    "sg:province":"NSW",
    "sg:tags":[
        "equipment",
        "display",
        "exhibition"
    ],
    "sg:website":"http://www.brochureholdercity.com.au",
    "wof:name":"Brochure Holders & Displays",
    "wof:placetype":"venue"
},
  "geometry": {"coordinates":[151.081787109,-33.8157501221],"type":"Point"}
}