{
  "type": "Feature",
  "properties": {
    "iso:country":"AU",
    "sg:address":"10 Indy Crt",
    "sg:city":"Nerang",
    "sg:classifiers":[
        {
            "category":"Building & Trades",
            "subcategory":"Construction",
            "type":"Services"
        }
    ],
    "sg:phone":"+61 7 5596 3344",
    "sg:postcode":"4211",
    "sg:province":"QLD",
    "sg:tags":[
        "welding"
    ],
    "wof:name":"Superior Steel Supplies Pty Ltd",
    "wof:placetype":"venue"
},
  "geometry": {"coordinates":[153.34739685100001,-28.010061264],"type":"Point"}
}