{
  "type": "Feature",
  "properties": {
    "iso:country":"AU",
    "sg:address":"133B McDowall St",
    "sg:city":"Roma",
    "sg:classifiers":[
        {
            "category":"Health Services",
            "subcategory":"Doctor",
            "type":"Services"
        }
    ],
    "sg:phone":"+61 7 4622 1471",
    "sg:postcode":"4455",
    "sg:province":"QLD",
    "sg:tags":[
        "nurse",
        "nursing"
    ],
    "wof:name":"Spiritus Care Services",
    "wof:placetype":"venue"
},
  "geometry": {"coordinates":[148.78660583499999,-26.5710926056],"type":"Point"}
}