{
  "type": "Feature",
  "properties": {
    "addr:full":"Lower Ground Floor, Shop 11, 255 Queen St Brisbane QLD 4000",
    "addr:housenumber":"shop 11 255",
    "addr:postcode":"4000",
    "addr:street":"Queen St",
    "iso:country":"AU",
    "sg:address":"Lower Ground Floor, Shop 11, 255 Queen St",
    "sg:city":"Brisbane",
    "sg:classifiers":[
        {
            "category":"Health Services",
            "subcategory":"Doctor",
            "type":"Services"
        }
    ],
    "sg:phone":"+61 7 3221 6666",
    "sg:postcode":"4000",
    "sg:province":"QLD",
    "sg:tags":[
        "medical",
        "practitioner"
    ],
    "wof:name":"Citycare Doctors",
    "wof:placetype":"venue"
},
  "geometry": {"coordinates":[153.027786255,-27.4678173065],"type":"Point"}
}