{
  "type": "Feature",
  "properties": {
    "addr:full":"1 Enterprise St Maroochydore QLD 4558",
    "addr:housenumber":"1",
    "addr:postcode":"4558",
    "addr:street":"Enterprise St",
    "iso:country":"AU",
    "sg:address":"1 Enterprise St",
    "sg:city":"Maroochydore",
    "sg:classifiers":[
        {
            "category":"Wholesale",
            "subcategory":"Metals & Minerals",
            "type":"Manufacturing & Wholesale Goods"
        }
    ],
    "sg:phone":"+61 7 5445 2794",
    "sg:postcode":"4558",
    "sg:province":"QLD",
    "sg:tags":[
        "steel",
        "stainless",
        "product",
        "equipment"
    ],
    "wof:name":"A 2 Z Stainless Supplies",
    "wof:placetype":"venue"
},
  "geometry": {"coordinates":[153.06553649899999,-26.6553192139],"type":"Point"}
}