{
  "type": "Feature",
  "properties": {
    "addr:full":"South Wharf Rd Southbank VIC 3006",
    "addr:postcode":"3006",
    "addr:street":"South Wharf Rd",
    "iso:country":"AU",
    "sg:address":"South Wharf Rd",
    "sg:city":"Southbank",
    "sg:classifiers":[
        {
            "category":"Communications",
            "subcategory":"News Services",
            "type":"Services"
        }
    ],
    "sg:phone":"+61 3 9699 9760",
    "sg:postcode":"3006",
    "sg:province":"VIC",
    "sg:tags":[
        "information",
        "tourist",
        "attractions"
    ],
    "wof:name":"Melbourne Maritime Museum Polly Woodside",
    "wof:placetype":"venue"
},
  "geometry": {"coordinates":[144.94737243599999,-37.8223609924],"type":"Point"}
}