{
  "type": "Feature",
  "properties": {
    "addr:full":"Veterans Pde Collaroy Plateau NSW 2097",
    "addr:postcode":"2097",
    "addr:street":"Veterans Pde",
    "iso:country":"AU",
    "sg:address":"Veterans Pde",
    "sg:city":"Collaroy Plateau",
    "sg:classifiers":[
        {
            "category":"Education",
            "subcategory":"School",
            "type":"Public Place"
        }
    ],
    "sg:phone":"+61 2 9971 8352",
    "sg:postcode":"2097",
    "sg:province":"NSW",
    "sg:tags":[
        "state",
        "-",
        "nsw"
    ],
    "wof:name":"Wheeler Heights Public School",
    "wof:placetype":"venue"
},
  "geometry": {"coordinates":[151.28594970699999,-33.7305793762],"type":"Point"}
}