{
  "type": "Feature",
  "properties": {
    "addr:full":"6 Woodcrest Way Springfield QLD 4300",
    "addr:housenumber":"6",
    "addr:postcode":"4300",
    "addr:street":"Woodcrest Way",
    "iso:country":"AU",
    "sg:address":"6 Woodcrest Way",
    "sg:city":"Springfield",
    "sg:classifiers":[
        {
            "category":"Sports & Exercise",
            "subcategory":"Gym",
            "type":"Entertainment"
        }
    ],
    "sg:phone":"+61 7 3288 5333",
    "sg:postcode":"4300",
    "sg:province":"QLD",
    "sg:tags":[
        "health",
        "fitness"
    ],
    "wof:name":"Maximum Effort Fitness Centre",
    "wof:placetype":"venue"
},
  "geometry": {"coordinates":[152.91717529300001,-27.6543159485],"type":"Point"}
}