{
  "type": "Feature",
  "properties": {
    "iso:country":"AU",
    "sg:address":"\"Glen Isla\" Terang Rd",
    "sg:city":"Camperdown",
    "sg:classifiers":[
        {
            "category":"Personal",
            "type":"Services"
        }
    ],
    "sg:phone":"+61 3 5593 2218",
    "sg:postcode":"3260",
    "sg:province":"VIC",
    "sg:tags":[
        "wallpapering",
        "wallcovering"
    ],
    "wof:name":"Bradshaw Kevin & Julie",
    "wof:placetype":"venue"
},
  "geometry": {"coordinates":[143.14210510300001,-38.2296600342],"type":"Point"}
}