{
  "type": "Feature",
  "properties": {
    "addr:full":"810- 814 Epping Rd Woodstock VIC 3751",
    "addr:housenumber":"810 814",
    "addr:postcode":"3751",
    "addr:street":"Epping Rd",
    "iso:country":"AU",
    "sg:address":"810- 814 Epping Rd",
    "sg:city":"Woodstock",
    "sg:classifiers":[
        {
            "category":"Social Services",
            "subcategory":"Retirement Home",
            "type":"Services"
        }
    ],
    "sg:phone":"+61 3 9408 1559",
    "sg:postcode":"3751",
    "sg:province":"VIC",
    "sg:tags":[
        "environmental",
        "consultant",
        "pollution"
    ],
    "wof:name":"Prompt Environmental Services Pty Ltd",
    "wof:placetype":"venue"
},
  "geometry": {"coordinates":[145.032669,-37.564892],"type":"Point"}
}