{
  "type": "Feature",
  "properties": {
    "addr:full":"Unit 1, 34 Jade St Maddington WA 6109",
    "addr:housenumber":"34",
    "addr:postcode":"6109",
    "addr:street":"Jade St",
    "iso:country":"AU",
    "sg:address":"Unit 1, 34 Jade St",
    "sg:city":"Maddington",
    "sg:classifiers":[
        {
            "category":"Wholesale",
            "subcategory":"Non-durable Goods",
            "type":"Manufacturing & Wholesale Goods"
        }
    ],
    "sg:phone":"+61 8 9493 7211",
    "sg:postcode":"6109",
    "sg:province":"WA",
    "sg:tags":[
        "wholesaler",
        "craft",
        "mfrs"
    ],
    "wof:name":"Yirra-Kurl Pty Ltd",
    "wof:placetype":"venue"
},
  "geometry": {"coordinates":[116.00116729699999,-32.0397033691],"type":"Point"}
}