{
  "type": "Feature",
  "properties": {
    "addr:full":"235 Sunshine Rd Tottenham VIC 3012",
    "addr:housenumber":"235",
    "addr:postcode":"3012",
    "addr:street":"Sunshine Rd",
    "iso:country":"AU",
    "sg:address":"235 Sunshine Rd",
    "sg:city":"Tottenham",
    "sg:classifiers":[
        {
            "category":"Communications",
            "type":"Services"
        }
    ],
    "sg:phone":"+61 3 9314 6966",
    "sg:postcode":"3012",
    "sg:province":"VIC",
    "sg:tags":[
        "public",
        "system",
        "address"
    ],
    "wof:name":"Entertainment Warehouse Hires",
    "wof:placetype":"venue"
},
  "geometry": {"coordinates":[144.848312378,-37.7982444763],"type":"Point"}
}