{
  "type": "Feature",
  "properties": {
    "addr:full":"Bruce Hwy Gympie QLD 4570",
    "addr:postcode":"4570",
    "addr:street":"Bruce Hwy",
    "iso:country":"AU",
    "sg:address":"Bruce Hwy",
    "sg:city":"Gympie",
    "sg:classifiers":[
        {
            "category":"Industrial Area",
            "type":"Public Place"
        }
    ],
    "sg:phone":"+61 7 5481 1888",
    "sg:postcode":"4570",
    "sg:province":"QLD",
    "sg:tags":[
        "rural",
        "shed"
    ],
    "wof:name":"DB Sheds Durabuilt",
    "wof:placetype":"venue"
},
  "geometry": {"coordinates":[152.65594482399999,-26.190279007],"type":"Point"}
}