{
  "type": "Feature",
  "properties": {
    "addr:full":"58 Garden St Narrabeen NSW 2101",
    "addr:housenumber":"58",
    "addr:postcode":"2101",
    "addr:street":"Garden St",
    "iso:country":"AU",
    "sg:address":"58 Garden St",
    "sg:city":"Narrabeen",
    "sg:classifiers":[
        {
            "category":"Autos & Motor Vehicles",
            "subcategory":"Motorcycle Sales",
            "type":"Retail Goods"
        }
    ],
    "sg:phone":"+61 2 9913 3522",
    "sg:postcode":"2101",
    "sg:province":"NSW",
    "sg:tags":[
        "outboard"
    ],
    "wof:name":"Bullen Ken Outboard Service",
    "wof:placetype":"venue"
},
  "geometry": {"coordinates":[151.295547,-33.702244],"type":"Point"}
}