{
  "type": "Feature",
  "properties": {
    "iso:country":"AU",
    "sg:address":"26b Chuter Ave",
    "sg:city":"Monterey",
    "sg:classifiers":[
        {
            "category":"Building & Trades",
            "subcategory":"Landscaping Services",
            "type":"Services"
        }
    ],
    "sg:phone":"+61 2 9553 7667",
    "sg:postcode":"2217",
    "sg:province":"NSW",
    "sg:tags":[
        "stump",
        "tree",
        "felling",
        "removal"
    ],
    "wof:name":"AS Tree Lopping",
    "wof:placetype":"venue"
},
  "geometry": {"coordinates":[151.14608799999999,-33.973721],"type":"Point"}
}