{
  "type": "Feature",
  "properties": {
    "addr:full":"Suite 3/ 107 Dandenong Rd Mt Ommaney QLD 4074",
    "addr:housenumber":"/ 107",
    "addr:postcode":"4074",
    "addr:street":"Dandenong Rd;Ommaney",
    "iso:country":"AU",
    "sg:address":"Suite 3/ 107 Dandenong Rd",
    "sg:city":"Mt Ommaney",
    "sg:classifiers":[
        {
            "category":"Professional",
            "subcategory":"Accounting & Tax Preparation",
            "type":"Services"
        }
    ],
    "sg:phone":"+61 7 3279 0094",
    "sg:postcode":"4074",
    "sg:province":"QLD",
    "sg:tags":[
        "consultant",
        "taxation"
    ],
    "wof:name":"Adam M & Co",
    "wof:placetype":"venue"
},
  "geometry": {"coordinates":[152.93597412099999,-27.5507774353],"type":"Point"}
}