{
  "type": "Feature",
  "properties": {
    "iso:country":"AU",
    "sg:address":"5 Inglisby Rd",
    "sg:city":"Mont Albert",
    "sg:classifiers":[
        {
            "category":"Building & Trades",
            "subcategory":"Cleaning & Sanitation",
            "type":"Services"
        }
    ],
    "sg:phone":"+61 1300 889 798",
    "sg:postcode":"3127",
    "sg:province":"VIC",
    "sg:tags":[
        "duct"
    ],
    "wof:name":"7 Net Cleaning Service",
    "wof:placetype":"venue"
},
  "geometry": {"coordinates":[145.10333251899999,-37.8144416809],"type":"Point"}
}