{
  "type": "Feature",
  "properties": {
    "iso:country":"AU",
    "sg:address":"87 Best St",
    "sg:city":"Devonport",
    "sg:classifiers":[
        {
            "category":"Insurance",
            "subcategory":"Insurance Agent",
            "type":"Services"
        }
    ],
    "sg:phone":"+61 3 6423 0050",
    "sg:postcode":"7310",
    "sg:province":"TAS",
    "wof:name":"Insurance Options Pty Ltd",
    "wof:placetype":"venue"
},
  "geometry": {"coordinates":[146.35151672399999,-41.1772155762],"type":"Point"}
}