{
  "type": "Feature",
  "properties": {
    "addr:full":"57 Goldfields Rd Esperance WA 6450",
    "addr:housenumber":"57",
    "addr:postcode":"6450",
    "addr:street":"Goldfields Rd",
    "iso:country":"AU",
    "sg:address":"57 Goldfields Rd",
    "sg:city":"Esperance",
    "sg:classifiers":[
        {
            "category":"Autos & Motor Vehicles",
            "subcategory":"Fuel & Gas Station",
            "type":"Retail Goods"
        }
    ],
    "sg:phone":"+61 8 9071 1473",
    "sg:postcode":"6450",
    "sg:province":"WA",
    "wof:name":"B.P. Castletown Service Station",
    "wof:placetype":"venue"
},
  "geometry": {"coordinates":[121.90782165500001,-33.8384666443],"type":"Point"}
}