{
  "type": "Feature",
  "properties": {
    "iso:country":"AU",
    "sg:address":"218 St George St",
    "sg:city":"Mungindi",
    "sg:classifiers":[
        {
            "category":"Travel",
            "subcategory":"Hotels & Motels",
            "type":"Entertainment"
        }
    ],
    "sg:phone":"+61 2 6753 2022",
    "sg:postcode":"2406",
    "sg:province":"NSW",
    "sg:tags":[
        "accommodation"
    ],
    "wof:name":"Jolly Swagman Hotel Motel",
    "wof:placetype":"venue"
},
  "geometry": {"coordinates":[148.98606872600001,-28.9764595032],"type":"Point"}
}