{
  "type": "Feature",
  "properties": {
    "iso:country":"AU",
    "sg:address":"3 Griffin St",
    "sg:city":"Booragoon",
    "sg:classifiers":[
        {
            "category":"Real Estate",
            "subcategory":"Real Estate Agent",
            "type":"Services"
        }
    ],
    "sg:phone":"+61 8 9364 6475",
    "sg:postcode":"6154",
    "sg:province":"WA",
    "wof:name":"Astral Estate",
    "wof:placetype":"venue"
},
  "geometry": {"coordinates":[115.837509,-32.037922],"type":"Point"}
}