{
  "type": "Feature",
  "properties": {
    "iso:country":"AU",
    "sg:address":"30- 32 Albert Ave",
    "sg:city":"Chatswood",
    "sg:classifiers":[
        {
            "category":"Education",
            "subcategory":"Kindergarten",
            "type":"Public Place"
        }
    ],
    "sg:phone":"+61 2 9419 3499",
    "sg:postcode":"2067",
    "sg:province":"NSW",
    "sg:tags":[
        "pre-schools"
    ],
    "wof:name":"Chatswood International Kindergarten",
    "wof:placetype":"venue"
},
  "geometry": {"coordinates":[151.18466186500001,-33.7976608276],"type":"Point"}
}