{
  "type": "Feature",
  "properties": {
    "addr:full":"31 Heversham Drv Seaford VIC 3198",
    "addr:housenumber":"31",
    "addr:postcode":"3198",
    "addr:street":"Heversham Drv",
    "iso:country":"AU",
    "sg:address":"31 Heversham Drv",
    "sg:city":"Seaford",
    "sg:classifiers":[
        {
            "category":"Utilities",
            "subcategory":"Water",
            "type":"Services"
        }
    ],
    "sg:phone":"+61 1800 643 168",
    "sg:postcode":"3198",
    "sg:province":"VIC",
    "sg:tags":[
        "hot",
        "system"
    ],
    "wof:name":"Eliza Plumbing And Heating",
    "wof:placetype":"venue"
},
  "geometry": {"coordinates":[145.14077758799999,-38.1123542786],"type":"Point"}
}