{
  "type": "Feature",
  "properties": {
    "iso:country":"AU",
    "sg:address":"PO Box 7045",
    "sg:city":"Eaton",
    "sg:classifiers":[
        {
            "category":"Building & Trades",
            "subcategory":"Equipment Rental",
            "type":"Services"
        }
    ],
    "sg:phone":"+61 408 252 256",
    "sg:postcode":"6232",
    "sg:province":"WA",
    "sg:tags":[
        "crane",
        "hire"
    ],
    "wof:name":"Bunbury Crane Hire",
    "wof:placetype":"venue"
},
  "geometry": {"coordinates":[115.715233,-33.323139],"type":"Point"}
}