{
  "type": "Feature",
  "properties": {
    "iso:country":"AU",
    "sg:address":"Unit 5 21 Foundry Rd",
    "sg:city":"Seven Hills",
    "sg:classifiers":[
        {
            "category":"Manufacturing",
            "subcategory":"Motor Vehicles & Parts",
            "type":"Manufacturing & Wholesale Goods"
        }
    ],
    "sg:phone":"+61 2 9838 0033",
    "sg:postcode":"2147",
    "sg:province":"NSW",
    "sg:tags":[
        "replacement"
    ],
    "wof:name":"Rennies Auto Parts Pty Ltd",
    "wof:placetype":"venue"
},
  "geometry": {"coordinates":[150.956665039,-33.7692375183],"type":"Point"}
}