{
  "type": "Feature",
  "properties": {
    "addr:full":"179 Watton St Werribee VIC 3030",
    "addr:housenumber":"179",
    "addr:postcode":"3030",
    "addr:street":"Watton St",
    "iso:country":"AU",
    "sg:address":"179 Watton St",
    "sg:city":"Werribee",
    "sg:classifiers":[
        {
            "category":"Professional",
            "subcategory":"Art Services",
            "type":"Services"
        }
    ],
    "sg:phone":"+61 3 9741 3384",
    "sg:postcode":"3030",
    "sg:province":"VIC",
    "sg:tags":[
        "picture",
        "frame",
        "framing"
    ],
    "wof:name":"Pierre's Image Centre",
    "wof:placetype":"venue"
},
  "geometry": {"coordinates":[144.657455,-37.90358],"type":"Point"}
}