{
  "type": "Feature",
  "properties": {
    "addr:full":"31 Rushall St Pymble NSW 2073",
    "addr:housenumber":"31",
    "addr:postcode":"2073",
    "addr:street":"Rushall St",
    "iso:country":"AU",
    "sg:address":"31 Rushall St",
    "sg:city":"Pymble",
    "sg:classifiers":[
        {
            "category":"Professional",
            "subcategory":"Engineering",
            "type":"Services"
        }
    ],
    "sg:phone":"+61 2 9449 5076",
    "sg:postcode":"2073",
    "sg:province":"NSW",
    "sg:tags":[
        "consulting",
        "engineer"
    ],
    "wof:name":"Electropower Consulting Engineers",
    "wof:placetype":"venue"
},
  "geometry": {"coordinates":[151.14122009299999,-33.7328224182],"type":"Point"}
}