{
  "type": "Feature",
  "properties": {
    "addr:full":"78 Newlands Rd Coburg VIC 3058",
    "addr:housenumber":"78",
    "addr:postcode":"3058",
    "addr:street":"Newlands Rd",
    "iso:country":"AU",
    "sg:address":"78 Newlands Rd",
    "sg:city":"Coburg",
    "sg:classifiers":[
        {
            "category":"Utilities",
            "subcategory":"Electric",
            "type":"Services"
        }
    ],
    "sg:phone":"+61 3 9350 2855",
    "sg:postcode":"3058",
    "sg:province":"VIC",
    "sg:tags":[
        "electrical",
        "contractor"
    ],
    "wof:name":"Modec Security",
    "wof:placetype":"venue"
},
  "geometry": {"coordinates":[144.971832275,-37.7301750183],"type":"Point"}
}