{
  "type": "Feature",
  "properties": {
    "addr:full":"U 5/ 11 Stanley St Peakhurst NSW 2210",
    "addr:housenumber":"11",
    "addr:postcode":"2210",
    "addr:street":"Stanley St",
    "iso:country":"AU",
    "sg:address":"U 5/ 11 Stanley St",
    "sg:city":"Peakhurst",
    "sg:classifiers":[
        {
            "category":"Retail",
            "subcategory":"Auto Repair",
            "type":"Services"
        }
    ],
    "sg:phone":"+61 2 9534 8844",
    "sg:postcode":"2210",
    "sg:province":"NSW",
    "sg:tags":[
        "bus",
        "truck"
    ],
    "wof:name":"ASD Bus & Truck Repairs",
    "wof:placetype":"venue"
},
  "geometry": {"coordinates":[151.064987,-33.961769],"type":"Point"}
}