{
  "type": "Feature",
  "properties": {
    "addr:full":"8 Russell Ave Mooroolbark VIC 3138",
    "addr:housenumber":"8",
    "addr:postcode":"3138",
    "addr:street":"Russell Ave",
    "iso:country":"AU",
    "sg:address":"8 Russell Ave",
    "sg:city":"Mooroolbark",
    "sg:classifiers":[
        {
            "category":"Building & Trades",
            "subcategory":"Construction",
            "type":"Services"
        }
    ],
    "sg:phone":"+61 402 228 262",
    "sg:postcode":"3138",
    "sg:province":"VIC",
    "sg:tags":[
        "plasterboard",
        "plasterer",
        "fixer"
    ],
    "wof:name":"Victrowel Plastering Pty Ltd",
    "wof:placetype":"venue"
},
  "geometry": {"coordinates":[145.32757568400001,-37.782169342],"type":"Point"}
}