{
  "type": "Feature",
  "properties": {
    "iso:country":"AU",
    "sg:address":"16 Westlink Pl",
    "sg:city":"Richlands",
    "sg:classifiers":[
        {
            "category":"Professional",
            "subcategory":"Detective & Security Services",
            "type":"Services"
        }
    ],
    "sg:phone":"+61 7 3375 6022",
    "sg:postcode":"4077",
    "sg:province":"QLD",
    "sg:tags":[
        "consultant",
        "laser"
    ],
    "wof:name":"Laser Central",
    "wof:placetype":"venue"
},
  "geometry": {"coordinates":[152.95428466800001,-27.5964202881],"type":"Point"}
}