{
  "type": "Feature",
  "properties": {
    "iso:country":"AU",
    "sg:address":"608 Old Northern Rd",
    "sg:city":"Dural",
    "sg:classifiers":[
        {
            "category":"Building & Trades",
            "subcategory":"Construction",
            "type":"Services"
        }
    ],
    "sg:phone":"+61 2 9651 2915",
    "sg:postcode":"2158",
    "sg:province":"NSW",
    "sg:tags":[
        "contractor"
    ],
    "wof:name":"Billyard Homes Pty Ltd",
    "wof:placetype":"venue"
},
  "geometry": {"coordinates":[151.03225707999999,-33.692276001],"type":"Point"}
}