{
  "type": "Feature",
  "properties": {
    "iso:country":"AU",
    "sg:address":"Suite 6a Bourne House, Barracks La",
    "sg:city":"Port Macquarie",
    "sg:classifiers":[
        {
            "category":"Sports & Exercise",
            "subcategory":"Gym",
            "type":"Entertainment"
        }
    ],
    "sg:phone":"+61 2 6584 4218",
    "sg:postcode":"2444",
    "sg:province":"NSW",
    "sg:tags":[
        "health",
        "fitness"
    ],
    "wof:name":"Studio 1 Personal Training",
    "wof:placetype":"venue"
},
  "geometry": {"coordinates":[152.926239,-31.47834],"type":"Point"}
}