{
  "type": "Feature",
  "properties": {
    "addr:full":"Level 2, 166 Gipps St East Melbourne VIC 3002",
    "addr:housenumber":"166",
    "addr:postcode":"3002",
    "addr:street":"Gipps St",
    "iso:country":"AU",
    "sg:address":"Level 2, 166 Gipps St",
    "sg:city":"East Melbourne",
    "sg:classifiers":[
        {
            "category":"Health Services",
            "subcategory":"Doctor",
            "type":"Services"
        }
    ],
    "sg:phone":"+61 3 9419 6766",
    "sg:postcode":"3002",
    "sg:province":"VIC",
    "sg:tags":[
        "medical",
        "practitioner"
    ],
    "sg:website":"http://www.breastunit.com",
    "wof:name":"Breast Imaging Victoria",
    "wof:placetype":"venue"
},
  "geometry": {"coordinates":[144.98396301299999,-37.8126525879],"type":"Point"}
}