{
  "type": "Feature",
  "properties": {
    "iso:country":"AU",
    "sg:address":"11 / 420 Mowbray Rd",
    "sg:city":"Lane Cove",
    "sg:classifiers":[
        {
            "category":"Professional",
            "subcategory":"Computer Services",
            "type":"Services"
        }
    ],
    "sg:phone":"+61 2 9420 8629",
    "sg:postcode":"2066",
    "sg:province":"NSW",
    "sg:tags":[
        "consultant",
        "system"
    ],
    "wof:name":"Creative Spark Solutions",
    "wof:placetype":"venue"
},
  "geometry": {"coordinates":[151.17312622099999,-33.807434082],"type":"Point"}
}