{
  "type": "Feature",
  "properties": {
    "iso:country":"AU",
    "sg:address":"604 Pine Ridge Rd",
    "sg:city":"Labrador",
    "sg:classifiers":[
        {
            "category":"Airport",
            "subcategory":"General Aviation",
            "type":"Transportation"
        }
    ],
    "sg:phone":"+61 1300 327 927",
    "sg:postcode":"4215",
    "sg:province":"QLD",
    "sg:tags":[
        "helicopter"
    ],
    "wof:name":"ABC Heli",
    "wof:placetype":"venue"
},
  "geometry": {"coordinates":[153.40838623100001,-27.945930481],"type":"Point"}
}