{
  "type": "Feature",
  "properties": {
    "addr:full":"Cnr Creek Rd & Zahel St Carina QLD 4152",
    "addr:postcode":"4152",
    "addr:street":"Cnr Creek Rd & Zahel St",
    "iso:country":"AU",
    "sg:address":"Cnr Creek Rd & Zahel St",
    "sg:city":"Carina",
    "sg:classifiers":[
        {
            "category":"Personal",
            "subcategory":"Beauty Salon",
            "type":"Services"
        }
    ],
    "sg:phone":"+61 7 3843 2933",
    "sg:postcode":"4152",
    "sg:province":"QLD",
    "wof:name":"Glowing Goddess",
    "wof:placetype":"venue"
},
  "geometry": {"coordinates":[153.10144043,-27.4932804108],"type":"Point"}
}