{
  "type": "Feature",
  "properties": {
    "iso:country":"AU",
    "sg:address":"23 First Ave",
    "sg:city":"Sawtell",
    "sg:classifiers":[
        {
            "category":"Restaurant",
            "type":"Food & Drink"
        }
    ],
    "sg:phone":"+61 2 6658 8255",
    "sg:postcode":"2452",
    "sg:province":"NSW",
    "wof:name":"Barrels Bistro",
    "wof:placetype":"venue"
},
  "geometry": {"coordinates":[153.099884,-30.36928],"type":"Point"}
}