{
  "type": "Feature",
  "properties": {
    "addr:full":"1 Bill River Ave William Creek SA 5710",
    "addr:housenumber":"1",
    "addr:postcode":"5710",
    "addr:street":"Bill River Ave",
    "iso:country":"AU",
    "sg:address":"1 Bill River Ave",
    "sg:city":"William Creek",
    "sg:classifiers":[
        {
            "category":"Airline",
            "type":"Transportation"
        }
    ],
    "sg:phone":"+61 8 8670 7962",
    "sg:postcode":"5710",
    "sg:province":"SA",
    "sg:tags":[
        "aircraft",
        "rental",
        "charter"
    ],
    "wof:name":"Wrightsair Aircraft Charter & Scenic Flights",
    "wof:placetype":"venue"
},
  "geometry": {"coordinates":[136.325515747,-28.923500061],"type":"Point"}
}