{
  "type": "Feature",
  "properties": {
    "addr:full":"58 McMinn St Darwin NT 0800",
    "addr:housenumber":"58",
    "addr:postcode":"nt 0800",
    "addr:street":"Mcminn St",
    "iso:country":"AU",
    "sg:address":"58 McMinn St",
    "sg:city":"Darwin",
    "sg:classifiers":[
        {
            "category":"Professional",
            "subcategory":"Detective & Security Services",
            "type":"Services"
        }
    ],
    "sg:phone":"+61 1300 662 668",
    "sg:postcode":"0800",
    "sg:province":"NT",
    "sg:tags":[
        "investigator"
    ],
    "wof:name":"Chubb Corporate Risk Services",
    "wof:placetype":"venue"
},
  "geometry": {"coordinates":[130.841873169,-12.4565219879],"type":"Point"}
}