{
  "type": "Feature",
  "properties": {
    "iso:country":"AU",
    "sg:address":"10 Gallop St",
    "sg:city":"Colac",
    "sg:classifiers":[
        {
            "category":"Retail",
            "subcategory":"Auto Repair",
            "type":"Services"
        }
    ],
    "sg:phone":"+61 3 5232 1626",
    "sg:postcode":"3250",
    "sg:province":"VIC",
    "sg:tags":[
        "beater",
        "painter",
        "panel"
    ],
    "wof:name":"Argento Panels",
    "wof:placetype":"venue"
},
  "geometry": {"coordinates":[143.609711,-38.334831],"type":"Point"}
}