{
  "type": "Feature",
  "properties": {
    "iso:country":"AU",
    "sg:address":"Shp6/ 131 Scott St",
    "sg:city":"Cairns City",
    "sg:classifiers":[
        {
            "category":"Real Estate",
            "subcategory":"Real Estate Agent",
            "type":"Services"
        }
    ],
    "sg:phone":"+61 7 4031 1552",
    "sg:postcode":"4870",
    "sg:province":"QLD",
    "wof:name":"Koala Blue Real Estate",
    "wof:placetype":"venue"
},
  "geometry": {"coordinates":[145.75796508799999,-16.9358654022],"type":"Point"}
}