{
  "type": "Feature",
  "properties": {
    "iso:country":"AU",
    "sg:address":"35 Mellor St",
    "sg:city":"Gympie",
    "sg:classifiers":[
        {
            "category":"Retail",
            "subcategory":"Auto Repair",
            "type":"Services"
        }
    ],
    "sg:phone":"+61 7 5480 5500",
    "sg:postcode":"4570",
    "sg:province":"QLD",
    "sg:tags":[
        "repairer",
        "motor",
        "engineer"
    ],
    "wof:name":"Holden",
    "wof:placetype":"venue"
},
  "geometry": {"coordinates":[152.666946411,-26.1888217926],"type":"Point"}
}