{
  "type": "Feature",
  "properties": {
    "addr:full":"122 Ayr St Doncaster VIC 3108",
    "addr:housenumber":"122",
    "addr:postcode":"3108",
    "addr:street":"Ayr St",
    "iso:country":"AU",
    "sg:address":"122 Ayr St",
    "sg:city":"Doncaster",
    "sg:classifiers":[
        {
            "category":"Food & Beverages",
            "subcategory":"Groceries & Convenience Stores",
            "type":"Retail Goods"
        }
    ],
    "sg:phone":"+61 3 9852 0447",
    "sg:postcode":"3108",
    "sg:province":"VIC",
    "wof:name":"Yan Xiao Heng",
    "wof:placetype":"venue"
},
  "geometry": {"coordinates":[145.103881836,-37.7768173218],"type":"Point"}
}