{
  "type": "Feature",
  "properties": {
    "iso:country":"AU",
    "sg:address":"90 Kings Rd",
    "sg:city":"Parafield Gardens",
    "sg:classifiers":[
        {
            "category":"Arena",
            "subcategory":"Sports Club",
            "type":"Entertainment"
        }
    ],
    "sg:phone":"+61 8 8289 6765",
    "sg:postcode":"5107",
    "sg:province":"SA",
    "sg:tags":[
        "defence",
        "supply",
        "self",
        "instruction",
        "martial art"
    ],
    "wof:name":"Adelaide Kyokushin Karate Centre",
    "wof:placetype":"venue"
},
  "geometry": {"coordinates":[138.61380004899999,-34.7713012695],"type":"Point"}
}