{
  "type": "Feature",
  "properties": {
    "addr:full":"65 George St Moonta SA 5558",
    "addr:housenumber":"65",
    "addr:postcode":"5558",
    "addr:street":"George St",
    "iso:country":"AU",
    "sg:address":"65 George St",
    "sg:city":"Moonta",
    "sg:classifiers":[
        {
            "category":"Wholesale",
            "subcategory":"Apparel",
            "type":"Manufacturing & Wholesale Goods"
        }
    ],
    "sg:phone":"+61 8 8825 2824",
    "sg:postcode":"5558",
    "sg:province":"SA",
    "sg:tags":[
        "wholesaler",
        "men's",
        "mfrs",
        "sportswear"
    ],
    "wof:name":"Copper City Signs",
    "wof:placetype":"venue"
},
  "geometry": {"coordinates":[137.59161376899999,-34.068611145],"type":"Point"}
}