{
  "type": "Feature",
  "properties": {
    "addr:full":"25 Daphne Cl Cherrybrook NSW 2126",
    "addr:housenumber":"25",
    "addr:postcode":"2126",
    "addr:street":"Daphne Cl",
    "iso:country":"AU",
    "sg:address":"25 Daphne Cl",
    "sg:city":"Cherrybrook",
    "sg:classifiers":[
        {
            "category":"Wholesale",
            "subcategory":"Photographic Equipment",
            "type":"Manufacturing & Wholesale Goods"
        }
    ],
    "sg:phone":"+61 2 9481 9288",
    "sg:postcode":"2126",
    "sg:province":"NSW",
    "sg:tags":[
        "machinery",
        "plastic"
    ],
    "wof:name":"Modern Plastics Equipment Sales Pty Ltd",
    "wof:placetype":"venue"
},
  "geometry": {"coordinates":[151.05575561500001,-33.7128982544],"type":"Point"}
}