{
  "type": "Feature",
  "properties": {
    "addr:full":"Nielsens Rd Carrara QLD 4211",
    "addr:postcode":"4211",
    "addr:street":"Nielsens Rd",
    "iso:country":"AU",
    "sg:address":"Nielsens Rd",
    "sg:city":"Carrara",
    "sg:classifiers":[
        {
            "category":"Food & Beverages",
            "subcategory":"Groceries & Convenience Stores",
            "type":"Retail Goods"
        }
    ],
    "sg:phone":"+61 7 5594 1099",
    "sg:postcode":"4211",
    "sg:province":"QLD",
    "wof:name":"Boonooroo Park Supermarket",
    "wof:placetype":"venue"
},
  "geometry": {"coordinates":[153.35969543499999,-28.019903183],"type":"Point"}
}