{
  "type": "Feature",
  "properties": {
    "iso:country":"AU",
    "sg:address":"63 Garden St",
    "sg:city":"East Geelong",
    "sg:classifiers":[
        {
            "category":"Sports & Exercise",
            "subcategory":"Sports Center",
            "type":"Entertainment"
        }
    ],
    "sg:phone":"+61 3 5229 8007",
    "sg:postcode":"3219",
    "sg:province":"VIC",
    "sg:tags":[
        "card",
        "memorabilia"
    ],
    "wof:name":"Sportznut",
    "wof:placetype":"venue"
},
  "geometry": {"coordinates":[144.372192383,-38.1536026001],"type":"Point"}
}