{
  "type": "Feature",
  "properties": {
    "iso:country":"AU",
    "sg:address":"26 Moss St",
    "sg:city":"Slacks Creek",
    "sg:classifiers":[
        {
            "category":"Wholesale",
            "subcategory":"Metals & Minerals",
            "type":"Manufacturing & Wholesale Goods"
        }
    ],
    "sg:phone":"+61 7 3808 5903",
    "sg:postcode":"4127",
    "sg:province":"QLD",
    "sg:tags":[
        "steel",
        "merchant"
    ],
    "wof:name":"Brisbane Steel Supplies",
    "wof:placetype":"venue"
},
  "geometry": {"coordinates":[153.11993408199999,-27.6238498688],"type":"Point"}
}