{
  "type": "Feature",
  "properties": {
    "addr:full":"1/ 44 Olive St Asquith NSW 2077",
    "addr:housenumber":"/ 44",
    "addr:postcode":"2077",
    "addr:street":"Olive St",
    "iso:country":"AU",
    "sg:address":"1/ 44 Olive St",
    "sg:city":"Asquith",
    "sg:classifiers":[
        {
            "category":"Education",
            "subcategory":"Special Training",
            "type":"Public Place"
        }
    ],
    "sg:phone":"+61 2 9482 7665",
    "sg:postcode":"2077",
    "sg:province":"NSW",
    "sg:tags":[
        "development"
    ],
    "wof:name":"Vision Ventures Pty Ltd",
    "wof:placetype":"venue"
},
  "geometry": {"coordinates":[151.10794067399999,-33.6905212402],"type":"Point"}
}