{
  "type": "Feature",
  "properties": {
    "addr:full":"Shop 4 48 Park Rd Cabramatta NSW 2166",
    "addr:housenumber":"shop;48",
    "addr:postcode":"2166",
    "addr:street":"Park Rd",
    "iso:country":"AU",
    "sg:address":"Shop 4 48 Park Rd",
    "sg:city":"Cabramatta",
    "sg:classifiers":[
        {
            "category":"Health Services",
            "subcategory":"Doctor",
            "type":"Services"
        }
    ],
    "sg:phone":"+61 2 9726 2666",
    "sg:postcode":"2166",
    "sg:province":"NSW",
    "sg:tags":[
        "medical",
        "practitioner"
    ],
    "wof:name":"Virulhapan Suwat Dr",
    "wof:placetype":"venue"
},
  "geometry": {"coordinates":[150.93719482399999,-33.8939743042],"type":"Point"}
}