{
  "type": "Feature",
  "properties": {
    "iso:country":"AU",
    "sg:address":"50 Chard Rd",
    "sg:city":"Brookvale",
    "sg:classifiers":[
        {
            "category":"Banks & Credit Unions",
            "subcategory":"Investment Brokerage",
            "type":"Services"
        }
    ],
    "sg:phone":"+61 2 9938 1800",
    "sg:postcode":"2100",
    "sg:province":"NSW",
    "sg:tags":[
        "paint",
        "supply",
        "removal"
    ],
    "sg:website":"http://www.sosafegraffitiremover.com.au",
    "wof:name":"So-Safe Specialty Products",
    "wof:placetype":"venue"
},
  "geometry": {"coordinates":[151.275192261,-33.7633132935],"type":"Point"}
}