{
  "type": "Feature",
  "properties": {
    "addr:full":"11 Valetta St Sale VIC 3850",
    "addr:housenumber":"11",
    "addr:postcode":"3850",
    "addr:street":"Valetta St",
    "iso:country":"AU",
    "sg:address":"11 Valetta St",
    "sg:city":"Sale",
    "sg:classifiers":[
        {
            "category":"Utilities",
            "subcategory":"Electric",
            "type":"Services"
        }
    ],
    "sg:phone":"+61 3 5144 5848",
    "sg:postcode":"3850",
    "sg:province":"VIC",
    "sg:tags":[
        "electrical",
        "contractor"
    ],
    "wof:name":"I.G. Electrical Contractors",
    "wof:placetype":"venue"
},
  "geometry": {"coordinates":[147.081344605,-38.1169052124],"type":"Point"}
}