{
  "type": "Feature",
  "properties": {
    "addr:full":"493 Cross Keys Rd Cavan SA 5094",
    "addr:housenumber":"493",
    "addr:postcode":"5094",
    "addr:street":"Cross Keys Rd",
    "iso:country":"AU",
    "sg:address":"493 Cross Keys Rd",
    "sg:city":"Cavan",
    "sg:classifiers":[
        {
            "category":"Wholesale",
            "subcategory":"Electrical",
            "type":"Manufacturing & Wholesale Goods"
        }
    ],
    "sg:phone":"+61 8 8262 8711",
    "sg:postcode":"5094",
    "sg:province":"SA",
    "sg:tags":[
        "wholesaler",
        "mfrs",
        "accessory"
    ],
    "wof:name":"Aussie Duct",
    "wof:placetype":"venue"
},
  "geometry": {"coordinates":[138.60040283199999,-34.8260345459],"type":"Point"}
}