{
  "type": "Feature",
  "properties": {
    "addr:full":"3/ 588 Goodwood Rd Daw Park SA 5041",
    "addr:housenumber":"/ 588",
    "addr:postcode":"5041",
    "addr:street":"Goodwood Rd",
    "iso:country":"AU",
    "sg:address":"3/ 588 Goodwood Rd",
    "sg:city":"Daw Park",
    "sg:classifiers":[
        {
            "category":"Education",
            "subcategory":"Junior College",
            "type":"Public Place"
        }
    ],
    "sg:phone":"+61 8 8276 8449",
    "sg:postcode":"5041",
    "sg:province":"SA",
    "sg:tags":[
        "wholesaler",
        "school",
        "mfrs",
        "uniform"
    ],
    "wof:name":"DZ Australia",
    "wof:placetype":"venue"
},
  "geometry": {"coordinates":[138.59179700000001,-34.981812],"type":"Point"}
}