{
  "type": "Feature",
  "properties": {
    "iso:country":"AU",
    "sg:address":"316 Kingsgrove Rd",
    "sg:city":"Kingsgrove",
    "sg:classifiers":[
        {
            "category":"Real Estate",
            "subcategory":"Real Estate Agent",
            "type":"Services"
        }
    ],
    "sg:phone":"+61 2 9150 0318",
    "sg:postcode":"2208",
    "sg:province":"NSW",
    "wof:name":"Bramley First National",
    "wof:placetype":"venue"
},
  "geometry": {"coordinates":[151.101852,-33.943592],"type":"Point"}
}