{
  "type": "Feature",
  "properties": {
    "addr:full":"37 Willoughby Rd Crows Nest NSW 2065",
    "addr:housenumber":"37",
    "addr:postcode":"2065",
    "addr:street":"Willoughby Rd",
    "iso:country":"AU",
    "sg:address":"37 Willoughby Rd",
    "sg:city":"Crows Nest",
    "sg:classifiers":[
        {
            "category":"Food & Beverages",
            "subcategory":"Liquor & Beverages",
            "type":"Retail Goods"
        }
    ],
    "sg:phone":"+61 2 9438 1352",
    "sg:postcode":"2065",
    "sg:province":"NSW",
    "sg:tags":[
        "store"
    ],
    "wof:name":"Georges Wine Nest",
    "wof:placetype":"venue"
},
  "geometry": {"coordinates":[151.20103454599999,-33.8264274597],"type":"Point"}
}