{
  "type": "Feature",
  "properties": {
    "iso:country":"AU",
    "sg:address":"U7/ 39 Main St",
    "sg:city":"Samford Village",
    "sg:classifiers":[
        {
            "category":"Retail",
            "subcategory":"Laundry & Dry Cleaning",
            "type":"Services"
        }
    ],
    "sg:phone":"+61 7 3289 6905",
    "sg:postcode":"4520",
    "sg:province":"QLD",
    "wof:name":"Sapphire Laundry Service",
    "wof:placetype":"venue"
},
  "geometry": {"coordinates":[152.88694799999999,-27.370371],"type":"Point"}
}