{
  "type": "Feature",
  "properties": {
    "addr:full":"19 Fordson Rd Campbellfield VIC 3061",
    "addr:housenumber":"19",
    "addr:postcode":"3061",
    "addr:street":"Fordson Rd",
    "iso:country":"AU",
    "sg:address":"19 Fordson Rd",
    "sg:city":"Campbellfield",
    "sg:classifiers":[
        {
            "category":"Wholesale",
            "subcategory":"Furniture",
            "type":"Manufacturing & Wholesale Goods"
        }
    ],
    "sg:phone":"+61 3 9357 2343",
    "sg:postcode":"3061",
    "sg:province":"VIC",
    "sg:tags":[
        "wholesaler",
        "mfrs"
    ],
    "wof:name":"Iwood Australia",
    "wof:placetype":"venue"
},
  "geometry": {"coordinates":[144.958908081,-37.6743240356],"type":"Point"}
}