{
  "type": "Feature",
  "properties": {
    "addr:full":"Unit 6/ 27 Collingwood St Osborne Park WA 6017",
    "addr:housenumber":"27",
    "addr:postcode":"6017",
    "addr:street":"Collingwood St",
    "iso:country":"AU",
    "sg:address":"Unit 6/ 27 Collingwood St",
    "sg:city":"Osborne Park",
    "sg:classifiers":[
        {
            "category":"Shopping",
            "subcategory":"Pets & Pet Supplies",
            "type":"Retail Goods"
        }
    ],
    "sg:phone":"+61 8 9244 7955",
    "sg:postcode":"6017",
    "sg:province":"WA",
    "sg:tags":[
        "food"
    ],
    "wof:name":"Glacier Pet Care Pty Ltd",
    "wof:placetype":"venue"
},
  "geometry": {"coordinates":[115.815872192,-31.9035167694],"type":"Point"}
}