{
  "type": "Feature",
  "properties": {
    "addr:full":"89 Westbury St St Kilda East VIC 3183",
    "addr:housenumber":"89",
    "addr:postcode":"3183",
    "addr:street":"Westbury St",
    "iso:country":"AU",
    "sg:address":"89 Westbury St St",
    "sg:city":"Kilda East",
    "sg:classifiers":[
        {
            "category":"Social Services",
            "subcategory":"Child Care",
            "type":"Services"
        }
    ],
    "sg:phone":"+61 3 9527 5963",
    "sg:postcode":"3183",
    "sg:province":"VIC",
    "wof:name":"Summerleas Nursery and Kindergarten",
    "wof:placetype":"venue"
},
  "geometry": {"coordinates":[144.99595642099999,-37.8655891418],"type":"Point"}
}