{
  "type": "Feature",
  "properties": {
    "iso:country":"AU",
    "sg:address":"Cnr Victoria & Woods Sts",
    "sg:city":"Mackay",
    "sg:classifiers":[
        {
            "category":"Organizations",
            "subcategory":"Community Association",
            "type":"Services"
        }
    ],
    "sg:phone":"+61 7 4944 0340",
    "sg:postcode":"4740",
    "sg:province":"QLD",
    "sg:tags":[
        "organisation",
        "family",
        "welfare"
    ],
    "wof:name":"Mackay Area Home Assist Home Secure",
    "wof:placetype":"venue"
},
  "geometry": {"coordinates":[149.176743,-21.140074],"type":"Point"}
}