{
  "type": "Feature",
  "properties": {
    "addr:full":"282 Prospect Rd Prospect SA 5082",
    "addr:housenumber":"282",
    "addr:postcode":"5082",
    "addr:street":"Prospect Rd",
    "iso:country":"AU",
    "sg:address":"282 Prospect Rd",
    "sg:city":"Prospect",
    "sg:classifiers":[
        {
            "category":"Manufacturing",
            "subcategory":"Glass & Minerals",
            "type":"Manufacturing & Wholesale Goods"
        }
    ],
    "sg:phone":"+61 8 8344 9640",
    "sg:postcode":"5082",
    "sg:province":"SA",
    "sg:tags":[
        "stained"
    ],
    "wof:name":"Prospect Leadlight",
    "wof:placetype":"venue"
},
  "geometry": {"coordinates":[138.59295654300001,-34.8738746643],"type":"Point"}
}