{
  "type": "Feature",
  "properties": {
    "iso:country":"AU",
    "sg:address":"2/ 36 Peachtree Rd",
    "sg:city":"Penrith",
    "sg:classifiers":[
        {
            "category":"Building & Trades",
            "subcategory":"Plumbing",
            "type":"Services"
        }
    ],
    "sg:phone":"+61 2 4732 3911",
    "sg:postcode":"2750",
    "sg:province":"NSW",
    "sg:tags":[
        "pump",
        "repairer"
    ],
    "wof:name":"Peachtree Electric Motor Rewinds",
    "wof:placetype":"venue"
},
  "geometry": {"coordinates":[150.97479248100001,-33.7890472412],"type":"Point"}
}