{
  "type": "Feature",
  "properties": {
    "addr:full":"Sherwood St Glenroy VIC 3046",
    "addr:postcode":"3046",
    "addr:street":"Sherwood St",
    "iso:country":"AU",
    "sg:address":"Sherwood St",
    "sg:city":"Glenroy",
    "sg:classifiers":[
        {
            "category":"Shopping",
            "subcategory":"Party Supplies",
            "type":"Retail Goods"
        }
    ],
    "sg:phone":"+61 433 458 457",
    "sg:postcode":"3046",
    "sg:province":"VIC",
    "sg:tags":[
        "selling",
        "plan"
    ],
    "wof:name":"Nice Butt Naughty Independant Consultant",
    "wof:placetype":"venue"
},
  "geometry": {"coordinates":[144.951004028,-37.7124404907],"type":"Point"}
}