{
  "type": "Feature",
  "properties": {
    "addr:full":"Unit 1/ 3 Westpool Drv Hallam VIC 3803",
    "addr:housenumber":"3",
    "addr:postcode":"3803",
    "addr:street":"Westpool Drv",
    "iso:country":"AU",
    "sg:address":"Unit 1/ 3 Westpool Drv",
    "sg:city":"Hallam",
    "sg:classifiers":[
        {
            "category":"Real Estate",
            "subcategory":"Real Estate Agent",
            "type":"Services"
        }
    ],
    "sg:phone":"+61 3 9703 1115",
    "sg:postcode":"3803",
    "sg:province":"VIC",
    "wof:name":"Power Property Real Estate",
    "wof:placetype":"venue"
},
  "geometry": {"coordinates":[145.26243591299999,-38.0153961182],"type":"Point"}
}