{
  "type": "Feature",
  "properties": {
    "addr:full":"16 Artists Ave Oxenford QLD 4210",
    "addr:housenumber":"16",
    "addr:postcode":"4210",
    "addr:street":"Artists Ave",
    "iso:country":"AU",
    "sg:address":"16 Artists Ave",
    "sg:city":"Oxenford",
    "sg:classifiers":[
        {
            "category":"Professional",
            "subcategory":"Engineering",
            "type":"Services"
        }
    ],
    "sg:phone":"+61 420 853 266",
    "sg:postcode":"4210",
    "sg:province":"QLD",
    "sg:tags":[
        "engineer",
        "mechanical"
    ],
    "wof:name":"Chris Turner Mechanical",
    "wof:placetype":"venue"
},
  "geometry": {"coordinates":[153.31695556599999,-27.9234447479],"type":"Point"}
}