{
  "type": "Feature",
  "properties": {
    "addr:full":"154 Marshalltown Rd Grovedale VIC 3216",
    "addr:housenumber":"154",
    "addr:postcode":"3216",
    "addr:street":"Marshalltown Rd",
    "iso:country":"AU",
    "sg:address":"154 Marshalltown Rd",
    "sg:city":"Grovedale",
    "sg:classifiers":[
        {
            "category":"Travel",
            "subcategory":"Travel Agent",
            "type":"Entertainment"
        }
    ],
    "sg:phone":"+61 1800 033 026",
    "sg:postcode":"3216",
    "sg:province":"VIC",
    "sg:tags":[
        "consultant"
    ],
    "wof:name":"Navini Island Resort (Fiji)",
    "wof:placetype":"venue"
},
  "geometry": {"coordinates":[144.34677124000001,-38.196269989],"type":"Point"}
}