{
  "type": "Feature",
  "properties": {
    "addr:full":"13 Bellarine Crt Keysborough VIC 3173",
    "addr:housenumber":"13",
    "addr:postcode":"3173",
    "addr:street":"Bellarine Crt",
    "iso:country":"AU",
    "sg:address":"13 Bellarine Crt",
    "sg:city":"Keysborough",
    "sg:classifiers":[
        {
            "category":"Professional",
            "subcategory":"Accounting & Tax Preparation",
            "type":"Services"
        }
    ],
    "sg:phone":"+61 3 9798 3483",
    "sg:postcode":"3173",
    "sg:province":"VIC",
    "sg:tags":[
        "accountant",
        "auditor"
    ],
    "wof:name":"Walsh Kevin Accountant",
    "wof:placetype":"venue"
},
  "geometry": {"coordinates":[145.168167114,-37.9909934998],"type":"Point"}
}