{
  "type": "Feature",
  "properties": {
    "iso:country":"AU",
    "sg:address":"7 Aralia Pl",
    "sg:city":"Dianella",
    "sg:classifiers":[
        {
            "category":"Manufacturing",
            "subcategory":"Wood Products",
            "type":"Manufacturing & Wholesale Goods"
        }
    ],
    "sg:phone":"+61 422 016 943",
    "sg:postcode":"6059",
    "sg:province":"WA",
    "sg:tags":[
        "polisher",
        "french"
    ],
    "wof:name":"Colonial Heritage French Polishing",
    "wof:placetype":"venue"
},
  "geometry": {"coordinates":[115.871261597,-31.8774662018],"type":"Point"}
}