{
  "type": "Feature",
  "properties": {
    "addr:full":"56 Samson Rd Point Samson WA 6720",
    "addr:housenumber":"56",
    "addr:postcode":"6720",
    "addr:street":"Samson Rd",
    "iso:country":"AU",
    "sg:address":"56 Samson Rd",
    "sg:city":"Point Samson",
    "sg:classifiers":[
        {
            "category":"Travel",
            "subcategory":"Hotels & Motels",
            "type":"Entertainment"
        }
    ],
    "sg:phone":"+61 8 9187 1052",
    "sg:postcode":"6720",
    "sg:province":"WA",
    "wof:name":"Point Samson Resort.",
    "wof:placetype":"venue"
},
  "geometry": {"coordinates":[117.194122315,-20.6288700104],"type":"Point"}
}