{
  "type": "Feature",
  "properties": {
    "addr:full":"4a Lawley St Dicky Beach QLD 4551",
    "addr:housenumber":"4a",
    "addr:postcode":"4551",
    "addr:street":"Lawley St",
    "iso:country":"AU",
    "sg:address":"4a Lawley St",
    "sg:city":"Dicky Beach",
    "sg:classifiers":[
        {
            "category":"Building & Trades",
            "subcategory":"Construction",
            "type":"Services"
        }
    ],
    "sg:phone":"+61 7 5491 5269",
    "sg:postcode":"4551",
    "sg:province":"QLD",
    "sg:tags":[
        "contractor"
    ],
    "wof:name":"Walker R G",
    "wof:placetype":"venue"
},
  "geometry": {"coordinates":[153.134002686,-26.7877464294],"type":"Point"}
}