{
  "type": "Feature",
  "properties": {
    "iso:country":"AU",
    "sg:address":"66 Diamond Valley Rd",
    "sg:city":"Mooloolah",
    "sg:classifiers":[
        {
            "category":"Utilities",
            "subcategory":"Water",
            "type":"Services"
        }
    ],
    "sg:phone":"+61 7 5492 9502",
    "sg:postcode":"4553",
    "sg:province":"QLD",
    "sg:tags":[
        "hot",
        "system"
    ],
    "wof:name":"Mooloolah Electrical",
    "wof:placetype":"venue"
},
  "geometry": {"coordinates":[152.953171,-26.760813],"type":"Point"}
}