{
  "type": "Feature",
  "properties": {
    "addr:full":"985 Nepean Hwy Moorabbin VIC 3189",
    "addr:housenumber":"985",
    "addr:postcode":"3189",
    "addr:street":"Nepean Hwy",
    "iso:country":"AU",
    "sg:address":"985 Nepean Hwy",
    "sg:city":"Moorabbin",
    "sg:classifiers":[
        {
            "category":"Retail",
            "subcategory":"Event Space",
            "type":"Services"
        }
    ],
    "sg:phone":"+61 3 9556 4313",
    "sg:postcode":"3189",
    "sg:province":"VIC",
    "sg:tags":[
        "function",
        "organiser"
    ],
    "wof:name":"Chelsea Hall",
    "wof:placetype":"venue"
},
  "geometry": {"coordinates":[145.035598755,-37.9336357117],"type":"Point"}
}