{
  "type": "Feature",
  "properties": {
    "addr:full":"Cnr Brisbane Rd & Hamilton St Booval QLD 4304",
    "addr:postcode":"4304",
    "addr:street":"Cnr Brisbane Rd & Hamilton St",
    "iso:country":"AU",
    "sg:address":"Cnr Brisbane Rd & Hamilton St",
    "sg:city":"Booval",
    "sg:classifiers":[
        {
            "category":"Real Estate",
            "subcategory":"Real Estate Agent",
            "type":"Services"
        }
    ],
    "sg:phone":"+61 7 3810 2000",
    "sg:postcode":"4304",
    "sg:province":"QLD",
    "wof:name":"RE/MAX Lifestyle",
    "wof:placetype":"venue"
},
  "geometry": {"coordinates":[152.78590393100001,-27.6139144897],"type":"Point"}
}