{
  "type": "Feature",
  "properties": {
    "iso:country":"AU",
    "sg:address":"Cnr Byrnes & Eccles Sts",
    "sg:city":"Mareeba",
    "sg:classifiers":[
        {
            "category":"Health Services",
            "subcategory":"Health Practitioner",
            "type":"Services"
        }
    ],
    "sg:phone":"+61 7 4092 7781",
    "sg:postcode":"4880",
    "sg:province":"QLD",
    "sg:tags":[
        "herbalist"
    ],
    "wof:name":"Global Herbal Supplies",
    "wof:placetype":"venue"
},
  "geometry": {"coordinates":[145.42005920400001,-16.9866485596],"type":"Point"}
}