{
  "type": "Feature",
  "properties": {
    "addr:full":"10 St Peter Crt Tarneit VIC 3029",
    "addr:housenumber":"10",
    "addr:postcode":"3029",
    "addr:street":"St Peter Crt",
    "iso:country":"AU",
    "sg:address":"10 St Peter Crt",
    "sg:city":"Tarneit",
    "sg:classifiers":[
        {
            "category":"Retail",
            "subcategory":"Repair Shop",
            "type":"Services"
        }
    ],
    "sg:phone":"+61 3 9749 1699",
    "sg:postcode":"3029",
    "sg:province":"VIC",
    "sg:tags":[
        "leadlights"
    ],
    "wof:name":"Glass Lighthouse The",
    "wof:placetype":"venue"
},
  "geometry": {"coordinates":[144.70747399999999,-37.849545],"type":"Point"}
}