{
  "type": "Feature",
  "properties": {
    "iso:country":"AU",
    "sg:address":"91 Main Rd",
    "sg:city":"Monbulk",
    "sg:classifiers":[
        {
            "category":"Retail",
            "subcategory":"Auto Repair",
            "type":"Services"
        }
    ],
    "sg:phone":"+61 3 9756 7329",
    "sg:postcode":"3793",
    "sg:province":"VIC",
    "sg:tags":[
        "repairer",
        "motor",
        "engineer"
    ],
    "wof:name":"Rogers B J",
    "wof:placetype":"venue"
},
  "geometry": {"coordinates":[145.40708923299999,-37.8746871948],"type":"Point"}
}