{
  "type": "Feature",
  "properties": {
    "iso:country":"AU",
    "sg:address":"Woolnough Rd",
    "sg:city":"Largs Bay",
    "sg:classifiers":[
        {
            "category":"Arena",
            "subcategory":"Sports Club",
            "type":"Entertainment"
        }
    ],
    "sg:phone":"+61 8 8449 8330",
    "sg:postcode":"5016",
    "sg:province":"SA",
    "sg:tags":[
        "australian",
        "football",
        "rule"
    ],
    "wof:name":"Port District Football Club",
    "wof:placetype":"venue"
},
  "geometry": {"coordinates":[138.48727417000001,-34.8311538696],"type":"Point"}
}