{
  "type": "Feature",
  "properties": {
    "iso:country":"AU",
    "sg:address":"17 Kingview Crt",
    "sg:city":"Kingston",
    "sg:classifiers":[
        {
            "category":"Building & Trades",
            "subcategory":"Construction",
            "type":"Services"
        }
    ],
    "sg:phone":"+61 409 976 434",
    "sg:postcode":"7050",
    "sg:province":"TAS",
    "sg:tags":[
        "contractor"
    ],
    "wof:name":"Pottinger Steve",
    "wof:placetype":"venue"
},
  "geometry": {"coordinates":[147.25737,-42.964439],"type":"Point"}
}