{
  "type": "Feature",
  "properties": {
    "addr:full":"135 Birralee Rd Westbury TAS 7303",
    "addr:housenumber":"135",
    "addr:postcode":"7303",
    "addr:street":"Birralee Rd",
    "iso:country":"AU",
    "sg:address":"135 Birralee Rd",
    "sg:city":"Westbury",
    "sg:classifiers":[
        {
            "category":"Utilities",
            "subcategory":"Fuel Oil & Lpg",
            "type":"Services"
        }
    ],
    "sg:phone":"+61 419 311 228",
    "sg:postcode":"7303",
    "sg:province":"TAS",
    "sg:tags":[
        "merchant"
    ],
    "wof:name":"Mitchelson Petroleum",
    "wof:placetype":"venue"
},
  "geometry": {"coordinates":[146.82986500000001,-41.514587],"type":"Point"}
}