{
  "type": "Feature",
  "properties": {
    "addr:full":"52 William St Gosford NSW 2250",
    "addr:housenumber":"52",
    "addr:postcode":"2250",
    "addr:street":"William St",
    "iso:country":"AU",
    "sg:address":"52 William St",
    "sg:city":"Gosford",
    "sg:classifiers":[
        {
            "category":"Professional",
            "subcategory":"Printing & Photocopies",
            "type":"Services"
        }
    ],
    "sg:phone":"+61 2 4324 1133",
    "sg:postcode":"2250",
    "sg:province":"NSW",
    "sg:tags":[
        "photocopying"
    ],
    "wof:name":"Snap Printing",
    "wof:placetype":"venue"
},
  "geometry": {"coordinates":[151.344650269,-33.4261817932],"type":"Point"}
}