{
  "type": "Feature",
  "properties": {
    "addr:full":"177 Ryrie St Geelong VIC 3220",
    "addr:housenumber":"177",
    "addr:postcode":"3220",
    "addr:street":"Ryrie St",
    "iso:country":"AU",
    "sg:address":"177 Ryrie St",
    "sg:city":"Geelong",
    "sg:classifiers":[
        {
            "category":"Travel",
            "subcategory":"Hotels & Motels",
            "type":"Entertainment"
        }
    ],
    "sg:phone":"+61 3 5223 2366",
    "sg:postcode":"3220",
    "sg:province":"VIC",
    "sg:tags":[
        "accommodation"
    ],
    "wof:name":"Preston Hotel",
    "wof:placetype":"venue"
},
  "geometry": {"coordinates":[144.361099,-38.149494],"type":"Point"}
}