{
  "type": "Feature",
  "properties": {
    "iso:country":"AU",
    "sg:address":"PO Box 3134",
    "sg:city":"Freemans Reach",
    "sg:classifiers":[
        {
            "category":"Professional",
            "subcategory":"Testing Lab",
            "type":"Services"
        }
    ],
    "sg:phone":"+61 2 4579 7526",
    "sg:postcode":"2756",
    "sg:province":"NSW",
    "sg:tags":[
        "equipment"
    ],
    "wof:name":"Ben O&#039;Brian",
    "wof:placetype":"venue"
},
  "geometry": {"coordinates":[150.79960632300001,-33.5579185486],"type":"Point"}
}