{
  "type": "Feature",
  "properties": {
    "iso:country":"AU",
    "sg:address":"Lot 7 R W Henry Drv",
    "sg:city":"Ettamogah",
    "sg:classifiers":[
        {
            "category":"Manufacturing",
            "subcategory":"Metals",
            "type":"Manufacturing & Wholesale Goods"
        }
    ],
    "sg:phone":"+61 2 6025 6777",
    "sg:postcode":"2640",
    "sg:province":"NSW",
    "sg:tags":[
        "forging"
    ],
    "wof:name":"Overall Forge Pty Ltd",
    "wof:placetype":"venue"
},
  "geometry": {"coordinates":[146.98403930699999,-36.005153656],"type":"Point"}
}