{
  "type": "Feature",
  "properties": {
    "addr:full":"62 Waterworks Rd Red Hill QLD 4059",
    "addr:housenumber":"62",
    "addr:postcode":"4059",
    "addr:street":"Waterworks Rd",
    "iso:country":"AU",
    "sg:address":"62 Waterworks Rd",
    "sg:city":"Red Hill",
    "sg:classifiers":[
        {
            "category":"Professional",
            "subcategory":"Art Services",
            "type":"Services"
        }
    ],
    "sg:phone":"+61 7 3217 5800",
    "sg:postcode":"4059",
    "sg:province":"QLD",
    "sg:tags":[
        "graphic",
        "designer"
    ],
    "wof:name":"Carolyn Morgan Design",
    "wof:placetype":"venue"
},
  "geometry": {"coordinates":[153.000732422,-27.4507675171],"type":"Point"}
}