{
  "type": "Feature",
  "properties": {
    "addr:full":"97 Maybe St Bombala NSW 2632",
    "addr:housenumber":"97",
    "addr:postcode":"2632",
    "addr:street":"Maybe St",
    "iso:country":"AU",
    "sg:address":"97 Maybe St",
    "sg:city":"Bombala",
    "sg:classifiers":[
        {
            "category":"Banks & Credit Unions",
            "subcategory":"Bureau De Change",
            "type":"Services"
        }
    ],
    "sg:phone":"+61 2 6458 3154",
    "sg:postcode":"2632",
    "sg:province":"NSW",
    "sg:tags":[
        "repairs",
        "part",
        "appliance",
        "electrical"
    ],
    "wof:name":"Bombala Hardware & Electrical",
    "wof:placetype":"venue"
},
  "geometry": {"coordinates":[149.23825073200001,-36.912071228],"type":"Point"}
}