{
  "type": "Feature",
  "properties": {
    "addr:full":"160a Percy Davis Drv Moruya NSW 2537",
    "addr:housenumber":"160a",
    "addr:postcode":"2537",
    "addr:street":"Percy Davis Drv",
    "iso:country":"AU",
    "sg:address":"160a Percy Davis Drv",
    "sg:city":"Moruya",
    "sg:classifiers":[
        {
            "category":"Utilities",
            "subcategory":"Electric",
            "type":"Services"
        }
    ],
    "sg:phone":"+61 2 4474 5287",
    "sg:postcode":"2537",
    "sg:province":"NSW",
    "sg:tags":[
        "electrical",
        "contractor"
    ],
    "wof:name":"Wombat Hollow",
    "wof:placetype":"venue"
},
  "geometry": {"coordinates":[150.12171935999999,-35.8757247925],"type":"Point"}
}