{
  "type": "Feature",
  "properties": {
    "iso:country":"AU",
    "sg:address":"PO Box 234",
    "sg:city":"Brooklyn Park",
    "sg:classifiers":[
        {
            "category":"Building & Trades",
            "subcategory":"Plumbing",
            "type":"Services"
        }
    ],
    "sg:phone":"+61 419 219 878",
    "sg:postcode":"5032",
    "sg:province":"SA",
    "sg:tags":[
        "plumber",
        "gasfitters"
    ],
    "wof:name":"Keen Plumbing Pty Ltd",
    "wof:placetype":"venue"
},
  "geometry": {"coordinates":[138.550537109,-34.928478241],"type":"Point"}
}