{
  "type": "Feature",
  "properties": {
    "addr:full":"PO Box 55 Esperance WA 6450",
    "addr:postcode":"6450",
    "iso:country":"AU",
    "sg:address":"PO Box 55",
    "sg:city":"Esperance",
    "sg:classifiers":[
        {
            "category":"Farming",
            "subcategory":"Farm",
            "type":"Manufacturing & Wholesale Goods"
        }
    ],
    "sg:phone":"+61 8 9076 1203",
    "sg:postcode":"6450",
    "sg:province":"WA",
    "sg:tags":[
        "farmer"
    ],
    "wof:name":"Sanderson C E",
    "wof:placetype":"venue"
},
  "geometry": {"coordinates":[121.895149231,-33.8598403931],"type":"Point"}
}