{
  "type": "Feature",
  "properties": {
    "addr:full":"5 Bayview St Russell Island QLD 4184",
    "addr:housenumber":"5",
    "addr:postcode":"4184",
    "addr:street":"Bayview St",
    "iso:country":"AU",
    "sg:address":"5 Bayview St",
    "sg:city":"Russell Island",
    "sg:classifiers":[
        {
            "category":"Real Estate",
            "subcategory":"Real Estate Agent",
            "type":"Services"
        }
    ],
    "sg:phone":"+61 7 3409 2255",
    "sg:postcode":"4184",
    "sg:province":"QLD",
    "wof:name":"LJ Hooker Bay Islands",
    "wof:placetype":"venue"
},
  "geometry": {"coordinates":[153.38119506800001,-27.646780014],"type":"Point"}
}