{
  "type": "Feature",
  "properties": {
    "addr:full":"Cnr South & Marys Sts Granville NSW 2142",
    "addr:postcode":"2142",
    "addr:street":"Cnr South & Marys Sts",
    "iso:country":"AU",
    "sg:address":"Cnr South & Marys Sts",
    "sg:city":"Granville",
    "sg:classifiers":[
        {
            "category":"Retail",
            "subcategory":"Laundry & Dry Cleaning",
            "type":"Services"
        }
    ],
    "sg:phone":"+61 2 9637 8425",
    "sg:postcode":"2142",
    "sg:province":"NSW",
    "sg:tags":[
        "manicurist"
    ],
    "wof:name":"Nail Tech",
    "wof:placetype":"venue"
},
  "geometry": {"coordinates":[151.00163269000001,-33.8295936584],"type":"Point"}
}