{
  "type": "Feature",
  "properties": {
    "addr:full":"181 Kruger Pde Redbank Plains QLD 4301",
    "addr:housenumber":"181",
    "addr:postcode":"4301",
    "addr:street":"Kruger Pde",
    "iso:country":"AU",
    "sg:address":"181 Kruger Pde",
    "sg:city":"Redbank Plains",
    "sg:classifiers":[
        {
            "category":"Retail",
            "subcategory":"Auto Repair",
            "type":"Services"
        }
    ],
    "sg:phone":"+61 7 3814 4040",
    "sg:postcode":"4301",
    "sg:province":"QLD",
    "sg:tags":[
        "repairer",
        "motor",
        "engineer"
    ],
    "wof:name":"Kruger Street Motors",
    "wof:placetype":"venue"
},
  "geometry": {"coordinates":[152.87448120100001,-27.6292495728],"type":"Point"}
}