{
  "type": "Feature",
  "properties": {
    "iso:country":"AU",
    "sg:address":"Flt 2 492 Dandenong Rd",
    "sg:city":"Caulfield North",
    "sg:classifiers":[
        {
            "category":"Professional",
            "subcategory":"Art Services",
            "type":"Services"
        }
    ],
    "sg:phone":"+61 3 9576 2227",
    "sg:postcode":"3161",
    "sg:province":"VIC",
    "sg:tags":[
        "commercial",
        "artist"
    ],
    "wof:name":"Robert Elliott Illustration",
    "wof:placetype":"venue"
},
  "geometry": {"coordinates":[145.02340698200001,-37.8647079468],"type":"Point"}
}