{
  "type": "Feature",
  "properties": {
    "addr:full":"31 Wentworth St Wallsend NSW 2287",
    "addr:housenumber":"31",
    "addr:postcode":"2287",
    "addr:street":"Wentworth St",
    "iso:country":"AU",
    "sg:address":"31 Wentworth St",
    "sg:city":"Wallsend",
    "sg:classifiers":[
        {
            "category":"Professional",
            "subcategory":"Art Services",
            "type":"Services"
        }
    ],
    "sg:phone":"+61 2 4951 5554",
    "sg:postcode":"2287",
    "sg:province":"NSW",
    "sg:tags":[
        "decorator",
        "painter"
    ],
    "wof:name":"Steel City Painting Service",
    "wof:placetype":"venue"
},
  "geometry": {"coordinates":[151.664672852,-32.8968887329],"type":"Point"}
}