{
  "type": "Feature",
  "properties": {
    "iso:country":"AU",
    "sg:address":"Unit 3, 1924 Beach Rd",
    "sg:city":"Malaga",
    "sg:classifiers":[
        {
            "category":"Home & Garden",
            "subcategory":"Furniture",
            "type":"Retail Goods"
        }
    ],
    "sg:phone":"+61 8 9248 9909",
    "sg:postcode":"6090",
    "sg:province":"WA",
    "sg:tags":[
        "business"
    ],
    "wof:name":"Hopkins J.& K.",
    "wof:placetype":"venue"
},
  "geometry": {"coordinates":[115.88722991900001,-31.8555812836],"type":"Point"}
}