{
  "type": "Feature",
  "properties": {
    "iso:country":"AU",
    "sg:address":"229 Nambour Connection Rd",
    "sg:city":"Woombye",
    "sg:classifiers":[
        {
            "category":"Home & Garden",
            "subcategory":"Garden Supply",
            "type":"Retail Goods"
        }
    ],
    "sg:phone":"+61 7 5442 3337",
    "sg:postcode":"4559",
    "sg:province":"QLD",
    "sg:tags":[
        "landscape"
    ],
    "wof:name":"Woombye Sand, Gravel & Landscaping Supplies",
    "wof:placetype":"venue"
},
  "geometry": {"coordinates":[152.97329711899999,-26.6664009094],"type":"Point"}
}