{
  "type": "Feature",
  "properties": {
    "iso:country":"AU",
    "sg:address":"295 Cleveland St",
    "sg:city":"Surry Hills",
    "sg:classifiers":[
        {
            "category":"Education",
            "subcategory":"University",
            "type":"Public Place"
        }
    ],
    "sg:phone":"+61 2 9699 3552",
    "sg:postcode":"2010",
    "sg:province":"NSW",
    "sg:tags":[
        "educational",
        "organisation",
        "cultural"
    ],
    "wof:name":"D.A.M.E.C.",
    "wof:placetype":"venue"
},
  "geometry": {"coordinates":[151.208740234,-33.8903770447],"type":"Point"}
}