{
  "type": "Feature",
  "properties": {
    "addr:full":"Shop 13 , Toronto Town Square Toronto NSW 2283",
    "addr:housenumber":"shop 13",
    "addr:postcode":"2283",
    "addr:street":"Square",
    "iso:country":"AU",
    "sg:address":"Shop 13",
    "sg:city":", Toronto Town Square Toronto",
    "sg:classifiers":[
        {
            "category":"Communications",
            "subcategory":"Film & Video Production",
            "type":"Services"
        }
    ],
    "sg:phone":"+61 2 4950 4727",
    "sg:postcode":"2283",
    "sg:province":"NSW",
    "sg:tags":[
        "dvd",
        "library"
    ],
    "wof:name":"Blockbuster",
    "wof:placetype":"venue"
},
  "geometry": {"coordinates":[151.559692383,-33.0059890747],"type":"Point"}
}