{
  "type": "Feature",
  "properties": {
    "addr:full":"79 Parker St Goodna QLD 4300",
    "addr:housenumber":"79",
    "addr:postcode":"4300",
    "addr:street":"Parker St",
    "iso:country":"AU",
    "sg:address":"79 Parker St",
    "sg:city":"Goodna",
    "sg:classifiers":[
        {
            "category":"Retail",
            "subcategory":"Auto Rental",
            "type":"Services"
        }
    ],
    "sg:phone":"+61 7 3855 3355",
    "sg:postcode":"4300",
    "sg:province":"QLD",
    "sg:tags":[
        "chauffeur",
        "car",
        "hire",
        "driven",
        "limousine"
    ],
    "wof:name":"Goldstar Limousine",
    "wof:placetype":"venue"
},
  "geometry": {"coordinates":[152.90351867699999,-27.6197624207],"type":"Point"}
}