{
  "type": "Feature",
  "properties": {
    "iso:country":"AU",
    "sg:address":"Densleys Rd",
    "sg:city":"Dalyston",
    "sg:classifiers":[
        {
            "category":"Farming",
            "subcategory":"Farm",
            "type":"Manufacturing & Wholesale Goods"
        }
    ],
    "sg:phone":"+61 3 5678 7371",
    "sg:postcode":"3992",
    "sg:province":"VIC",
    "sg:tags":[
        "farmer"
    ],
    "wof:name":"Hodgson D & W",
    "wof:placetype":"venue"
},
  "geometry": {"coordinates":[145.516785,-38.556442],"type":"Point"}
}