{
  "type": "Feature",
  "properties": {
    "addr:full":"Shop 3, Ramada Apartments 35 Fawcett St Ballina NSW 2478",
    "addr:housenumber":"shop 3;35",
    "addr:postcode":"2478",
    "addr:street":"Fawcett St",
    "iso:country":"AU",
    "sg:address":"Shop 3, Ramada Apartments 35 Fawcett St",
    "sg:city":"Ballina",
    "sg:classifiers":[
        {
            "category":"Banks & Credit Unions",
            "subcategory":"Financial Services",
            "type":"Services"
        }
    ],
    "sg:phone":"+61 2 6681 3477",
    "sg:postcode":"2478",
    "sg:province":"NSW",
    "sg:tags":[
        "annuity",
        "rollover",
        "superannuation",
        "consultant"
    ],
    "wof:name":"Wilson HTM",
    "wof:placetype":"venue"
},
  "geometry": {"coordinates":[153.55917358400001,-28.8705101013],"type":"Point"}
}