{
  "type": "Feature",
  "properties": {
    "iso:country":"AU",
    "sg:address":"21 Bultje St",
    "sg:city":"Dubbo",
    "sg:classifiers":[
        {
            "category":"Autos & Motor Vehicles",
            "subcategory":"Auto Supplies",
            "type":"Retail Goods"
        }
    ],
    "sg:phone":"+61 2 6882 1922",
    "sg:postcode":"2830",
    "sg:province":"NSW",
    "sg:tags":[
        "battery",
        "automotive"
    ],
    "wof:name":"Beaurepaires",
    "wof:placetype":"venue"
},
  "geometry": {"coordinates":[148.60113525400001,-32.2512321472],"type":"Point"}
}