{
  "type": "Feature",
  "properties": {
    "iso:country":"AU",
    "sg:address":"3 Parkmore Rd",
    "sg:city":"Forest Hill",
    "sg:classifiers":[
        {
            "category":"Professional",
            "subcategory":"Computer Services",
            "type":"Services"
        }
    ],
    "sg:phone":"+61 3 9893 5016",
    "sg:postcode":"3131",
    "sg:province":"VIC",
    "sg:tags":[
        "consultant",
        "system"
    ],
    "wof:name":"Acceber",
    "wof:placetype":"venue"
},
  "geometry": {"coordinates":[145.17219543499999,-37.8410377502],"type":"Point"}
}