{
  "type": "Feature",
  "properties": {
    "addr:full":"6 Goff St Coburg East VIC 3058",
    "addr:housenumber":"6",
    "addr:postcode":"3058",
    "addr:street":"Goff St",
    "iso:country":"AU",
    "sg:address":"6 Goff St",
    "sg:city":"Coburg East",
    "sg:classifiers":[
        {
            "category":"Health Services",
            "subcategory":"Dentist",
            "type":"Services"
        }
    ],
    "sg:phone":"+61 3 9355 8913",
    "sg:postcode":"3058",
    "sg:province":"VIC",
    "sg:tags":[
        "technician",
        "dental"
    ],
    "wof:name":"Roche Gregory J",
    "wof:placetype":"venue"
},
  "geometry": {"coordinates":[144.980194092,-37.7389640808],"type":"Point"}
}