{
  "type": "Feature",
  "properties": {
    "addr:full":"1 - 5 Eagle Heights Rd North Tamborine QLD 4272",
    "addr:housenumber":"5",
    "addr:postcode":"4272",
    "addr:street":"Eagle Heights Rd",
    "iso:country":"AU",
    "sg:address":"1 - 5 Eagle Heights Rd",
    "sg:city":"North Tamborine",
    "sg:classifiers":[
        {
            "category":"Retail",
            "subcategory":"Event Space",
            "type":"Services"
        }
    ],
    "sg:phone":"+61 7 5545 1099",
    "sg:postcode":"4272",
    "sg:province":"QLD",
    "sg:tags":[
        "function",
        "organiser"
    ],
    "wof:name":"The Governors Inn",
    "wof:placetype":"venue"
},
  "geometry": {"coordinates":[153.19261169399999,-27.9267234802],"type":"Point"}
}