{
  "type": "Feature",
  "properties": {
    "addr:full":"Shp50/ 427-441 Victoria Ave Chatswood NSW 2067",
    "addr:housenumber":"427-441",
    "addr:postcode":"2067",
    "addr:street":"Victoria Ave",
    "iso:country":"AU",
    "sg:address":"Shp50/ 427-441 Victoria Ave",
    "sg:city":"Chatswood",
    "sg:classifiers":[
        {
            "category":"Personal",
            "subcategory":"Beauty Salon",
            "type":"Services"
        }
    ],
    "sg:phone":"+61 2 9884 9818",
    "sg:postcode":"2067",
    "sg:province":"NSW",
    "wof:name":"Venus Beauty Centre",
    "wof:placetype":"venue"
},
  "geometry": {"coordinates":[151.18263244600001,-33.7962188721],"type":"Point"}
}