{
  "type": "Feature",
  "properties": {
    "addr:full":"11 Davey Crt Springvale VIC 3171",
    "addr:housenumber":"11",
    "addr:postcode":"3171",
    "addr:street":"Davey Crt",
    "iso:country":"AU",
    "sg:address":"11 Davey Crt",
    "sg:city":"Springvale",
    "sg:classifiers":[
        {
            "category":"Professional",
            "type":"Services"
        }
    ],
    "sg:phone":"+61 409 422 613",
    "sg:postcode":"3171",
    "sg:province":"VIC",
    "sg:tags":[
        "control",
        "equipment",
        "traffic"
    ],
    "wof:name":"RTM Traffic Control",
    "wof:placetype":"venue"
},
  "geometry": {"coordinates":[145.163040161,-37.9431610107],"type":"Point"}
}