{
  "type": "Feature",
  "properties": {
    "addr:full":"Level 10 / Exchange Plaza, 2 The Esp Perth WA 6000",
    "addr:housenumber":"/;2",
    "addr:postcode":"6000",
    "addr:street":"Plaza;The Esp",
    "iso:country":"AU",
    "sg:address":"Level 10 / Exchange Plaza, 2",
    "sg:city":"The Esp Perth",
    "sg:classifiers":[
        {
            "category":"Professional",
            "subcategory":"Detective & Security Services",
            "type":"Services"
        }
    ],
    "sg:phone":"+61 8 9225 2417",
    "sg:postcode":"6000",
    "sg:province":"WA",
    "sg:tags":[
        "guard",
        "patrol"
    ],
    "wof:name":"Choice Security",
    "wof:placetype":"venue"
},
  "geometry": {"coordinates":[115.858642578,-31.9566688538],"type":"Point"}
}