{
  "type": "Feature",
  "properties": {
    "iso:country":"AU",
    "sg:address":"Unit 35/ 123 Post Office St",
    "sg:city":"Carlingford",
    "sg:classifiers":[
        {
            "category":"Building & Trades",
            "subcategory":"Construction",
            "type":"Services"
        }
    ],
    "sg:phone":"+61 2 9871 1171",
    "sg:postcode":"2118",
    "sg:province":"NSW",
    "sg:tags":[
        "plasterboard",
        "plasterer",
        "fixer"
    ],
    "wof:name":"RBI Plastering",
    "wof:placetype":"venue"
},
  "geometry": {"coordinates":[151.04786682100001,-33.7791748047],"type":"Point"}
}