{
  "type": "Feature",
  "properties": {
    "addr:full":"247 Lords Pl Orange NSW 2800",
    "addr:housenumber":"247",
    "addr:postcode":"2800",
    "addr:street":"Lords Pl",
    "iso:country":"AU",
    "sg:address":"247 Lords Pl",
    "sg:city":"Orange",
    "sg:classifiers":[
        {
            "category":"Professional",
            "subcategory":"Detective & Security Services",
            "type":"Services"
        }
    ],
    "sg:phone":"+61 419 995 438",
    "sg:postcode":"2800",
    "sg:province":"NSW",
    "sg:tags":[
        "guard",
        "patrol"
    ],
    "wof:name":"Orange Protection Service",
    "wof:placetype":"venue"
},
  "geometry": {"coordinates":[149.101104736,-33.2834014893],"type":"Point"}
}