{
  "type": "Feature",
  "properties": {
    "addr:full":"420 Liverpool Rd Strathfield NSW 2135",
    "addr:housenumber":"420",
    "addr:postcode":"2135",
    "addr:street":"Liverpool Rd",
    "iso:country":"AU",
    "sg:address":"420 Liverpool Rd",
    "sg:city":"Strathfield",
    "sg:classifiers":[
        {
            "category":"Education",
            "subcategory":"School",
            "type":"Public Place"
        }
    ],
    "sg:phone":"+61 2 9642 0104",
    "sg:postcode":"2135",
    "sg:province":"NSW",
    "wof:name":"Noor Al Houda Islamic College",
    "wof:placetype":"venue"
},
  "geometry": {"coordinates":[151.0884552,-33.892036438],"type":"Point"}
}