{
  "type": "Feature",
  "properties": {
    "addr:full":"581 Terranora Rd Terranora QLD 2486",
    "addr:housenumber":"581",
    "addr:postcode":"2486",
    "addr:street":"Terranora Rd",
    "iso:country":"AU",
    "sg:address":"581 Terranora Rd",
    "sg:city":"Terranora",
    "sg:classifiers":[
        {
            "category":"Building & Trades",
            "subcategory":"Plumbing",
            "type":"Services"
        }
    ],
    "sg:phone":"+61 7 5590 4486",
    "sg:postcode":"2486",
    "sg:province":"QLD",
    "sg:tags":[
        "plumber",
        "gasfitters"
    ],
    "wof:name":"Jarrod Mohr Plumbing & Excavations",
    "wof:placetype":"venue"
},
  "geometry": {"coordinates":[153.50465393100001,-28.2405471802],"type":"Point"}
}