{
  "type": "Feature",
  "properties": {
    "addr:full":"97 Seventh St Mildura VIC 3500",
    "addr:housenumber":"97",
    "addr:postcode":"3500",
    "addr:street":"Seventh St",
    "iso:country":"AU",
    "sg:address":"97 Seventh St",
    "sg:city":"Mildura",
    "sg:classifiers":[
        {
            "category":"Shopping",
            "subcategory":"Computers & Home Electronics",
            "type":"Retail Goods"
        }
    ],
    "sg:phone":"+61 3 5023 4141",
    "sg:postcode":"3500",
    "sg:province":"VIC",
    "sg:tags":[
        "hardware",
        "equipment"
    ],
    "wof:name":"Stealthtech",
    "wof:placetype":"venue"
},
  "geometry": {"coordinates":[142.153244019,-34.1758880615],"type":"Point"}
}