{
  "type": "Feature",
  "properties": {
    "addr:full":"Cnr High & Chapel Sts Prahran VIC 3181",
    "addr:postcode":"3181",
    "iso:country":"AU",
    "sg:address":"Cnr High & Chapel Sts",
    "sg:city":"Prahran",
    "sg:classifiers":[
        {
            "category":"Health Services",
            "subcategory":"Health Practitioner",
            "type":"Services"
        }
    ],
    "sg:phone":"+61 409 002 242",
    "sg:postcode":"3181",
    "sg:province":"VIC",
    "sg:tags":[
        "naturopath"
    ],
    "wof:name":"John Catsicas Naturopath Clinic",
    "wof:placetype":"venue"
},
  "geometry": {"coordinates":[144.99342346200001,-37.8513412476],"type":"Point"}
}