{
  "type": "Feature",
  "properties": {
    "iso:country":"AU",
    "sg:address":"5a Beresford Ave",
    "sg:city":"Beresfield",
    "sg:classifiers":[
        {
            "category":"Shopping",
            "subcategory":"Party Supplies",
            "type":"Retail Goods"
        }
    ],
    "sg:phone":"+61 2 4966 0655",
    "sg:postcode":"2322",
    "sg:province":"NSW",
    "wof:name":"Balloon Party",
    "wof:placetype":"venue"
},
  "geometry": {"coordinates":[151.65748596200001,-32.8009567261],"type":"Point"}
}