{
  "type": "Feature",
  "properties": {
    "addr:full":"2 Irrawang St Raymond Terrace NSW 2324",
    "addr:housenumber":"2",
    "addr:postcode":"2324",
    "addr:street":"Irrawang St",
    "iso:country":"AU",
    "sg:address":"2 Irrawang St",
    "sg:city":"Raymond Terrace",
    "sg:classifiers":[
        {
            "category":"Retail",
            "subcategory":"Repair Shop",
            "type":"Services"
        }
    ],
    "sg:phone":"+61 2 4987 2985",
    "sg:postcode":"2324",
    "sg:province":"NSW",
    "sg:tags":[
        "upholsterer"
    ],
    "wof:name":"Raymond Terrace Upholstery",
    "wof:placetype":"venue"
},
  "geometry": {"coordinates":[151.752044678,-32.7612190247],"type":"Point"}
}