{
  "type": "Feature",
  "properties": {
    "iso:country":"AU",
    "sg:address":"2/9 Anderson St",
    "sg:city":"Neutral Bay",
    "sg:classifiers":[
        {
            "category":"Real Estate",
            "subcategory":"Surveying",
            "type":"Services"
        }
    ],
    "sg:phone":"+61 2 9990 9595",
    "sg:postcode":"2089",
    "sg:province":"NSW",
    "sg:tags":[
        "mathematical",
        "statistical"
    ],
    "wof:name":"Mathematical/Numerical Consulting",
    "wof:placetype":"venue"
},
  "geometry": {"coordinates":[151.220703125,-33.8366546631],"type":"Point"}
}