{
  "type": "Feature",
  "properties": {
    "iso:country":"AU",
    "sg:address":"1 Balmoral Rd",
    "sg:city":"Dernancourt",
    "sg:classifiers":[
        {
            "category":"Shopping",
            "subcategory":"Mobile Phones",
            "type":"Retail Goods"
        }
    ],
    "sg:phone":"+61 418 834 000",
    "sg:postcode":"5075",
    "sg:province":"SA",
    "sg:tags":[
        "telephone",
        "accessory"
    ],
    "wof:name":"Cell-Com Mobile Communications",
    "wof:placetype":"venue"
},
  "geometry": {"coordinates":[138.680130005,-34.8640213013],"type":"Point"}
}