{
  "type": "Feature",
  "properties": {
    "addr:full":"726 Pittwater Rd Brookvale NSW 2100",
    "addr:housenumber":"726",
    "addr:postcode":"2100",
    "addr:street":"Pittwater Rd",
    "iso:country":"AU",
    "sg:address":"726 Pittwater Rd",
    "sg:city":"Brookvale",
    "sg:classifiers":[
        {
            "category":"Wholesale",
            "subcategory":"Construction Materials",
            "type":"Manufacturing & Wholesale Goods"
        }
    ],
    "sg:phone":"+61 2 9939 1122",
    "sg:postcode":"2100",
    "sg:province":"NSW",
    "sg:tags":[
        "wholesaler",
        "lighting",
        "mfrs",
        "accessory"
    ],
    "wof:name":"Tovo (Australasia) Pty. Ltd.",
    "wof:placetype":"venue"
},
  "geometry": {"coordinates":[151.27325439399999,-33.7612457275],"type":"Point"}
}