{
  "type": "Feature",
  "properties": {
    "iso:country":"AU",
    "sg:address":"Suite 5, 61 Smith St",
    "sg:city":"Warragul",
    "sg:classifiers":[
        {
            "category":"Real Estate",
            "subcategory":"Surveying",
            "type":"Services"
        }
    ],
    "sg:phone":"+61 3 5623 2257",
    "sg:postcode":"3820",
    "sg:province":"VIC",
    "sg:tags":[
        "surveyor",
        "land"
    ],
    "wof:name":"Ross & Worth Pty Ltd",
    "wof:placetype":"venue"
},
  "geometry": {"coordinates":[145.932251,-38.159866],"type":"Point"}
}