{
  "type": "Feature",
  "properties": {
    "iso:country":"AU",
    "sg:address":"PO Box 200",
    "sg:city":"Karoonda",
    "sg:classifiers":[
        {
            "category":"Professional",
            "type":"Services"
        }
    ],
    "sg:phone":"+61 8 8578 1181",
    "sg:postcode":"5307",
    "sg:province":"SA",
    "sg:tags":[
        "transport"
    ],
    "wof:name":"Karoonda Freight Service",
    "wof:placetype":"venue"
},
  "geometry": {"coordinates":[139.893707275,-35.0954093933],"type":"Point"}
}