{
  "type": "Feature",
  "properties": {
    "addr:full":"Unit 2 29 McIntyre Way Kenwick WA 6107",
    "addr:housenumber":"29",
    "addr:postcode":"6107",
    "addr:street":"Mcintyre Way",
    "iso:country":"AU",
    "sg:address":"Unit 2 29 McIntyre Way",
    "sg:city":"Kenwick",
    "sg:classifiers":[
        {
            "category":"Home & Garden",
            "subcategory":"Home Furnishings",
            "type":"Retail Goods"
        }
    ],
    "sg:phone":"+61 8 9493 4750",
    "sg:postcode":"6107",
    "sg:province":"WA",
    "sg:tags":[
        "shower",
        "screen"
    ],
    "wof:name":"Update Glass & Aluminium",
    "wof:placetype":"venue"
},
  "geometry": {"coordinates":[115.97575378400001,-32.0446510315],"type":"Point"}
}