{
  "type": "Feature",
  "properties": {
    "iso:country":"AU",
    "sg:address":"Schmeider&#039;s Cooperage 3- 7 Alexandra St",
    "sg:city":"Bundaberg",
    "sg:classifiers":[
        {
            "category":"Shopping",
            "subcategory":"Crafts & Fabrics",
            "type":"Retail Goods"
        }
    ],
    "sg:phone":"+61 7 4151 8167",
    "sg:postcode":"4670",
    "sg:province":"QLD",
    "sg:tags":[
        "supply"
    ],
    "wof:name":"The Craft Centre & Gallery",
    "wof:placetype":"venue"
},
  "geometry": {"coordinates":[152.36935424800001,-24.8576622009],"type":"Point"}
}