{
  "type": "Feature",
  "properties": {
    "addr:full":"2 5 Canara St Doncaster East VIC 3109",
    "addr:housenumber":"5",
    "addr:postcode":"3109",
    "addr:street":"Canara St",
    "iso:country":"AU",
    "sg:address":"2 5 Canara St",
    "sg:city":"Doncaster East",
    "sg:classifiers":[
        {
            "category":"Professional",
            "subcategory":"Art Services",
            "type":"Services"
        }
    ],
    "sg:phone":"+61 418 196 236",
    "sg:postcode":"3109",
    "sg:province":"VIC",
    "sg:tags":[
        "decorator",
        "painter"
    ],
    "wof:name":"Ajax Painting Services",
    "wof:placetype":"venue"
},
  "geometry": {"coordinates":[145.154907227,-37.7948570251],"type":"Point"}
}