{
  "type": "Feature",
  "properties": {
    "iso:country":"AU",
    "sg:address":"21 Pine Hill Drv",
    "sg:city":"Pakenham",
    "sg:classifiers":[
        {
            "category":"Building & Trades",
            "subcategory":"Construction",
            "type":"Services"
        }
    ],
    "sg:phone":"+61 417 385 814",
    "sg:postcode":"3810",
    "sg:province":"VIC",
    "sg:tags":[
        "earth",
        "excavating",
        "moving",
        "contractor"
    ],
    "wof:name":"McRae Excavations",
    "wof:placetype":"venue"
},
  "geometry": {"coordinates":[145.509094,-38.082741],"type":"Point"}
}