{
  "type": "Feature",
  "properties": {
    "addr:full":"40- 42 Coronation Pde Strathfield NSW 2135",
    "addr:housenumber":"42",
    "addr:postcode":"2135",
    "addr:street":"Coronation Pde",
    "iso:country":"AU",
    "sg:address":"40- 42 Coronation Pde",
    "sg:city":"Strathfield",
    "sg:classifiers":[
        {
            "category":"Government",
            "subcategory":"Customs House",
            "type":"Public Place"
        }
    ],
    "sg:phone":"+61 2 9744 1622",
    "sg:postcode":"2135",
    "sg:province":"NSW",
    "sg:tags":[
        "title",
        "management",
        "stratum"
    ],
    "wof:name":"SMS Community & Strata Specialists",
    "wof:placetype":"venue"
},
  "geometry": {"coordinates":[151.09141540499999,-33.8895454407],"type":"Point"}
}