{
  "type": "Feature",
  "properties": {
    "addr:full":"Cnr Alan St & Blackburn Rd Blackburn VIC 3130",
    "addr:postcode":"3130",
    "addr:street":"Alan St & Blackburn Rd",
    "iso:country":"AU",
    "sg:address":"Cnr Alan St & Blackburn Rd",
    "sg:city":"Blackburn",
    "sg:classifiers":[
        {
            "category":"Health Services",
            "subcategory":"Health Practitioner",
            "type":"Services"
        }
    ],
    "sg:phone":"+61 3 9878 8088",
    "sg:postcode":"3130",
    "sg:province":"VIC",
    "sg:tags":[
        "myotherapy"
    ],
    "wof:name":"Sally Aspinall",
    "wof:placetype":"venue"
},
  "geometry": {"coordinates":[145.15507507300001,-37.8343925476],"type":"Point"}
}