{
  "type": "Feature",
  "properties": {
    "iso:country":"AU",
    "sg:address":"Flr 1/ 308- 310 Centre Rd",
    "sg:city":"Bentleigh",
    "sg:classifiers":[
        {
            "category":"Real Estate",
            "subcategory":"Real Estate Services",
            "type":"Services"
        }
    ],
    "sg:phone":"+61 3 9557 9155",
    "sg:postcode":"3204",
    "sg:province":"VIC",
    "sg:tags":[
        "consultant",
        "property"
    ],
    "wof:name":"Beveridge Property Consultants",
    "wof:placetype":"venue"
},
  "geometry": {"coordinates":[145.032883,-37.917858],"type":"Point"}
}