{
  "type": "Feature",
  "properties": {
    "iso:country":"AU",
    "sg:address":"185 New Town Rd",
    "sg:city":"New Town",
    "sg:classifiers":[
        {
            "category":"Personal",
            "subcategory":"Barber",
            "type":"Services"
        }
    ],
    "sg:phone":"+61 3 6278 3876",
    "sg:postcode":"7008",
    "sg:province":"TAS",
    "wof:name":"New Town Barber Shop",
    "wof:placetype":"venue"
},
  "geometry": {"coordinates":[147.30381774899999,-42.856136322],"type":"Point"}
}