{
  "type": "Feature",
  "properties": {
    "addr:full":"4/ 2 Ewing Rd Woodridge QLD 4114",
    "addr:housenumber":"/ 2",
    "addr:postcode":"4114",
    "addr:street":"Ewing Rd",
    "iso:country":"AU",
    "sg:address":"4/ 2 Ewing Rd",
    "sg:city":"Woodridge",
    "sg:classifiers":[
        {
            "category":"Health Services",
            "subcategory":"Dentist",
            "type":"Services"
        }
    ],
    "sg:phone":"+61 7 3808 9567",
    "sg:postcode":"4114",
    "sg:province":"QLD",
    "wof:name":"Karydas A",
    "wof:placetype":"venue"
},
  "geometry": {"coordinates":[153.107345581,-27.6403198242],"type":"Point"}
}