{
  "type": "Feature",
  "properties": {
    "iso:country":"AU",
    "sg:address":"60 Raphael Rd",
    "sg:city":"Winnellie",
    "sg:classifiers":[
        {
            "category":"Transit Center",
            "subcategory":"Freight",
            "type":"Transportation"
        }
    ],
    "sg:phone":"+61 13 16 07",
    "sg:postcode":"0820",
    "sg:province":"NT",
    "sg:tags":[
        "forklift",
        "truck"
    ],
    "wof:name":"NT Fork Lifts",
    "wof:placetype":"venue"
},
  "geometry": {"coordinates":[130.867431641,-12.431886673],"type":"Point"}
}