{
  "type": "Feature",
  "properties": {
    "iso:country":"AU",
    "sg:address":"66 Glenferrie Rd",
    "sg:city":"Malvern",
    "sg:classifiers":[
        {
            "category":"Shopping",
            "subcategory":"Crafts & Fabrics",
            "type":"Retail Goods"
        }
    ],
    "sg:phone":"+61 3 9576 2011",
    "sg:postcode":"3144",
    "sg:province":"VIC",
    "sg:tags":[
        "material",
        "dress"
    ],
    "wof:name":"Spotlight Stores",
    "wof:placetype":"venue"
},
  "geometry": {"coordinates":[145.028396606,-37.8630523682],"type":"Point"}
}