{
  "type": "Feature",
  "properties": {
    "addr:full":"301 Morayfield Rd Morayfield QLD 4506",
    "addr:housenumber":"301",
    "addr:postcode":"4506",
    "addr:street":"Morayfield Rd",
    "iso:country":"AU",
    "sg:address":"301 Morayfield Rd",
    "sg:city":"Morayfield",
    "sg:classifiers":[
        {
            "category":"Retail",
            "subcategory":"Repair Shop",
            "type":"Services"
        }
    ],
    "sg:phone":"+61 7 5497 8333",
    "sg:postcode":"4506",
    "sg:province":"QLD",
    "sg:tags":[
        "windscreen"
    ],
    "wof:name":"Morayfield Discount Autoglass",
    "wof:placetype":"venue"
},
  "geometry": {"coordinates":[152.952560425,-27.1147727966],"type":"Point"}
}