{
  "type": "Feature",
  "properties": {
    "iso:country":"AU",
    "sg:address":"Nicholson St",
    "sg:city":"Healesville",
    "sg:classifiers":[
        {
            "category":"Cinema",
            "subcategory":"Movie Theater",
            "type":"Entertainment"
        }
    ],
    "sg:phone":"+61 3 5962 4480",
    "sg:postcode":"3777",
    "sg:province":"VIC",
    "wof:name":"Healesville Cinema",
    "wof:placetype":"venue"
},
  "geometry": {"coordinates":[145.521454,-37.651909],"type":"Point"}
}