{
  "type": "Feature",
  "properties": {
    "addr:full":"32 Gehrke Rd Plainland QLD 4341",
    "addr:housenumber":"32",
    "addr:postcode":"4341",
    "addr:street":"Gehrke Rd",
    "iso:country":"AU",
    "sg:address":"32 Gehrke Rd",
    "sg:city":"Plainland",
    "sg:classifiers":[
        {
            "category":"Building & Trades",
            "subcategory":"Construction",
            "type":"Services"
        }
    ],
    "sg:phone":"+61 7 5465 7059",
    "sg:postcode":"4341",
    "sg:province":"QLD",
    "sg:tags":[
        "earth",
        "excavating",
        "moving",
        "contractor"
    ],
    "wof:name":"Bruce Andrews Earthmoving",
    "wof:placetype":"venue"
},
  "geometry": {"coordinates":[152.42440795900001,-27.5559673309],"type":"Point"}
}