{
  "type": "Feature",
  "properties": {
    "addr:full":"South West Hwy Donnybrook WA 6239",
    "addr:postcode":"6239",
    "addr:street":"South West Hwy",
    "iso:country":"AU",
    "sg:address":"South West Hwy",
    "sg:city":"Donnybrook",
    "sg:classifiers":[
        {
            "category":"Sports & Exercise",
            "subcategory":"Golf",
            "type":"Entertainment"
        }
    ],
    "sg:phone":"+61 8 9731 1268",
    "sg:postcode":"6239",
    "sg:province":"WA",
    "sg:tags":[
        "club"
    ],
    "wof:name":"Donnybrook Country Club Inc",
    "wof:placetype":"venue"
},
  "geometry": {"coordinates":[115.823013,-33.570419],"type":"Point"}
}