{
  "type": "Feature",
  "properties": {
    "addr:full":"238 Old Geelong Rd Hoppers Crossing VIC 3029",
    "addr:housenumber":"238",
    "addr:postcode":"3029",
    "addr:street":"Old Geelong Rd",
    "iso:country":"AU",
    "sg:address":"238 Old Geelong Rd",
    "sg:city":"Hoppers Crossing",
    "sg:classifiers":[
        {
            "category":"Retail",
            "subcategory":"Auto Repair",
            "type":"Services"
        }
    ],
    "sg:phone":"+61 3 9749 5539",
    "sg:postcode":"3029",
    "sg:province":"VIC",
    "sg:tags":[
        "beater",
        "painter",
        "panel"
    ],
    "wof:name":"Precision Body Works",
    "wof:placetype":"venue"
},
  "geometry": {"coordinates":[144.71961999999999,-37.874832],"type":"Point"}
}