{
  "type": "Feature",
  "properties": {
    "iso:country":"AU",
    "sg:address":"427 City Rd",
    "sg:city":"Melbourne",
    "sg:classifiers":[
        {
            "category":"Professional",
            "subcategory":"Computer Services",
            "type":"Services"
        }
    ],
    "sg:phone":"+61 3 9686 4088",
    "sg:postcode":"3000",
    "sg:province":"VIC",
    "sg:tags":[
        "training"
    ],
    "wof:name":"Brilliant Training & Consulting",
    "wof:placetype":"venue"
},
  "geometry": {"coordinates":[144.95309448200001,-37.832069397],"type":"Point"}
}