{
  "type": "Feature",
  "properties": {
    "iso:country":"AU",
    "sg:address":"188 Cambridge St",
    "sg:city":"Wembley",
    "sg:classifiers":[
        {
            "category":"Health Services",
            "subcategory":"Doctor",
            "type":"Services"
        }
    ],
    "sg:phone":"+61 8 9274 5166",
    "sg:postcode":"6014",
    "sg:province":"WA",
    "sg:tags":[
        "medical",
        "practitioner"
    ],
    "wof:name":"Langlands D R",
    "wof:placetype":"venue"
},
  "geometry": {"coordinates":[115.820678711,-31.9405956268],"type":"Point"}
}