{
  "type": "Feature",
  "properties": {
    "iso:country":"AU",
    "sg:address":"Parkwood Rd",
    "sg:city":"MacGregor",
    "sg:classifiers":[
        {
            "category":"Home & Garden",
            "subcategory":"Garden Supply",
            "type":"Retail Goods"
        }
    ],
    "sg:phone":"+61 2 6254 8284",
    "sg:postcode":"2615",
    "sg:province":"ACT",
    "sg:tags":[
        "landscape"
    ],
    "wof:name":"Belconnen Landscape Supplies",
    "wof:placetype":"venue"
},
  "geometry": {"coordinates":[149.00328064000001,-35.2178344727],"type":"Point"}
}