{
  "type": "Feature",
  "properties": {
    "iso:country":"AU",
    "sg:address":"987 Croydon Rd",
    "sg:city":"Karratha",
    "sg:classifiers":[
        {
            "category":"Wholesale",
            "subcategory":"Machinery & Supplies",
            "type":"Manufacturing & Wholesale Goods"
        }
    ],
    "sg:phone":"+61 8 9185 2933",
    "sg:postcode":"6714",
    "sg:province":"WA",
    "sg:tags":[
        "equipment",
        "welding"
    ],
    "wof:name":"BOC Gas & Gear",
    "wof:placetype":"venue"
},
  "geometry": {"coordinates":[116.86184692400001,-20.7725811005],"type":"Point"}
}