{
  "type": "Feature",
  "properties": {
    "addr:full":"34 Ingham Ave Five Dock NSW 2046",
    "addr:housenumber":"34",
    "addr:postcode":"2046",
    "addr:street":"Ingham Ave",
    "iso:country":"AU",
    "sg:address":"34 Ingham Ave",
    "sg:city":"Five Dock",
    "sg:classifiers":[
        {
            "category":"Professional",
            "subcategory":"Accounting & Tax Preparation",
            "type":"Services"
        }
    ],
    "sg:phone":"+61 2 9713 4404",
    "sg:postcode":"2046",
    "sg:province":"NSW",
    "sg:tags":[
        "accountant",
        "auditor"
    ],
    "wof:name":"Hughes Gerard Michael",
    "wof:placetype":"venue"
},
  "geometry": {"coordinates":[151.13568100000001,-33.870396],"type":"Point"}
}