{
  "type": "Feature",
  "properties": {
    "addr:full":"34 David Brand Drv Carnarvon WA 6701",
    "addr:housenumber":"34",
    "addr:postcode":"6701",
    "addr:street":"David Brand Drv",
    "iso:country":"AU",
    "sg:address":"34 David Brand Drv",
    "sg:city":"Carnarvon",
    "sg:classifiers":[
        {
            "category":"Travel",
            "subcategory":"Hotels & Motels",
            "type":"Entertainment"
        }
    ],
    "sg:phone":"+61 8 9941 0600",
    "sg:postcode":"6701",
    "sg:province":"WA",
    "wof:name":"Carnarvon Fascine Lodge",
    "wof:placetype":"venue"
},
  "geometry": {"coordinates":[113.653038025,-24.8812122345],"type":"Point"}
}