{
  "type": "Feature",
  "properties": {
    "addr:full":"1A Johnson St Chatswood NSW 2067",
    "addr:housenumber":"1a",
    "addr:postcode":"2067",
    "addr:street":"Johnson St",
    "iso:country":"AU",
    "sg:address":"1A Johnson St",
    "sg:city":"Chatswood",
    "sg:classifiers":[
        {
            "category":"Professional",
            "subcategory":"Computer Services",
            "type":"Services"
        }
    ],
    "sg:phone":"+61 2 9410 1112",
    "sg:postcode":"2067",
    "sg:province":"NSW",
    "sg:tags":[
        "repairs",
        "upgrade",
        "equipment"
    ],
    "wof:name":"Computer Repair Pty Ltd",
    "wof:placetype":"venue"
},
  "geometry": {"coordinates":[151.190795898,-33.798248291],"type":"Point"}
}