{
  "type": "Feature",
  "properties": {
    "addr:full":"42a Ware St Fairfield NSW 2165",
    "addr:housenumber":"42a",
    "addr:postcode":"2165",
    "addr:street":"Ware St",
    "iso:country":"AU",
    "sg:address":"42a Ware St",
    "sg:city":"Fairfield",
    "sg:classifiers":[
        {
            "category":"Personal",
            "subcategory":"Beauty Salon",
            "type":"Services"
        }
    ],
    "sg:phone":"+61 2 9727 6442",
    "sg:postcode":"2165",
    "sg:province":"NSW",
    "wof:name":"Beauty Infusion",
    "wof:placetype":"venue"
},
  "geometry": {"coordinates":[150.95510864299999,-33.8711509705],"type":"Point"}
}