{
  "type": "Feature",
  "properties": {
    "addr:full":"1/ 336 Keira St Wollongong NSW 2500",
    "addr:housenumber":"/ 336",
    "addr:postcode":"2500",
    "addr:street":"Keira St",
    "iso:country":"AU",
    "sg:address":"1/ 336 Keira St",
    "sg:city":"Wollongong",
    "sg:classifiers":[
        {
            "category":"Education",
            "subcategory":"Special Training",
            "type":"Public Place"
        }
    ],
    "sg:phone":"+61 2 4223 3100",
    "sg:postcode":"2500",
    "sg:province":"NSW",
    "sg:tags":[
        "development"
    ],
    "wof:name":"Illawarra ITeC Ltd",
    "wof:placetype":"venue"
},
  "geometry": {"coordinates":[150.89215100000001,-34.433254],"type":"Point"}
}