{
  "type": "Feature",
  "properties": {
    "addr:full":"Unit 4/ 198 Spit Rd Mosman NSW 2088",
    "addr:housenumber":"/ 198",
    "addr:postcode":"2088",
    "addr:street":"Spit Rd",
    "iso:country":"AU",
    "sg:address":"Unit 4/ 198 Spit Rd",
    "sg:city":"Mosman",
    "sg:classifiers":[
        {
            "category":"Building & Trades",
            "subcategory":"Construction",
            "type":"Services"
        }
    ],
    "sg:phone":"+61 2 9430 6699",
    "sg:postcode":"2088",
    "sg:province":"NSW",
    "sg:tags":[
        "contractor"
    ],
    "wof:name":"All In One Construction Pty Ltd",
    "wof:placetype":"venue"
},
  "geometry": {"coordinates":[151.24339294399999,-33.8146858215],"type":"Point"}
}