{
  "type": "Feature",
  "properties": {
    "iso:country":"AU",
    "sg:address":"11 Wandoo St",
    "sg:city":"Fortitude Valley",
    "sg:classifiers":[
        {
            "category":"Shopping",
            "subcategory":"Mobile Phones",
            "type":"Retail Goods"
        }
    ],
    "sg:phone":"+61 7 3252 3055",
    "sg:postcode":"4006",
    "sg:province":"QLD",
    "sg:tags":[
        "wholesaler",
        "mfrs",
        "electrical",
        "switchboard"
    ],
    "wof:name":"Heinemann Electric Pty Ltd",
    "wof:placetype":"venue"
},
  "geometry": {"coordinates":[153.03941345199999,-27.4551296234],"type":"Point"}
}