{
  "type": "Feature",
  "properties": {
    "addr:full":"1 Barter St Gympie QLD 4570",
    "addr:housenumber":"1",
    "addr:postcode":"4570",
    "addr:street":"Barter St",
    "iso:country":"AU",
    "sg:address":"1 Barter St",
    "sg:city":"Gympie",
    "sg:classifiers":[
        {
            "category":"Retail",
            "subcategory":"Auto Repair",
            "type":"Services"
        }
    ],
    "sg:phone":"+61 7 5481 1699",
    "sg:postcode":"4570",
    "sg:province":"QLD",
    "sg:tags":[
        "electrical"
    ],
    "wof:name":"Savanna Auto Electrical",
    "wof:placetype":"venue"
},
  "geometry": {"coordinates":[152.658813477,-26.1908988953],"type":"Point"}
}