{
  "type": "Feature",
  "properties": {
    "iso:country":"AU",
    "sg:address":"89 Abel St",
    "sg:city":"Boyup Brook",
    "sg:classifiers":[
        {
            "category":"Banks & Credit Unions",
            "subcategory":"Bank",
            "type":"Services"
        }
    ],
    "sg:phone":"+61 13 20 32",
    "sg:postcode":"6244",
    "sg:province":"WA",
    "wof:name":"Westpac",
    "wof:placetype":"venue"
},
  "geometry": {"coordinates":[116.387451172,-33.8326148987],"type":"Point"}
}