{
  "type": "Feature",
  "properties": {
    "iso:country":"AU",
    "sg:address":"PO Box 251",
    "sg:city":"Sandringham",
    "sg:classifiers":[
        {
            "category":"Building & Trades",
            "subcategory":"Construction",
            "type":"Services"
        }
    ],
    "sg:phone":"+61 13 15 46",
    "sg:postcode":"3191",
    "sg:province":"VIC",
    "sg:tags":[
        "brick",
        "paving"
    ],
    "wof:name":"Jims Paving",
    "wof:placetype":"venue"
},
  "geometry": {"coordinates":[145.01231384299999,-37.9524917603],"type":"Point"}
}