{
  "type": "Feature",
  "properties": {
    "addr:full":"169 A Main St Bacchus Marsh VIC 3340",
    "addr:housenumber":"169",
    "addr:postcode":"3340",
    "addr:street":"A Main St",
    "iso:country":"AU",
    "sg:address":"169 A Main St",
    "sg:city":"Bacchus Marsh",
    "sg:classifiers":[
        {
            "category":"Personal",
            "subcategory":"Beauty Salon",
            "type":"Services"
        }
    ],
    "sg:phone":"+61 3 5367 0644",
    "sg:postcode":"3340",
    "sg:province":"VIC",
    "sg:tags":[
        "hairdresser"
    ],
    "wof:name":"Peter's Hair Salon",
    "wof:placetype":"venue"
},
  "geometry": {"coordinates":[144.43464700000001,-37.675426],"type":"Point"}
}