{
  "type": "Feature",
  "properties": {
    "addr:full":"175 Concord Rd Strathfield NSW 2135",
    "addr:housenumber":"175",
    "addr:postcode":"2135",
    "addr:street":"Concord Rd",
    "iso:country":"AU",
    "sg:address":"175 Concord Rd",
    "sg:city":"Strathfield",
    "sg:classifiers":[
        {
            "category":"Fast Food",
            "type":"Food & Drink"
        }
    ],
    "sg:phone":"+61 2 9481 1111",
    "sg:postcode":"2135",
    "sg:province":"NSW",
    "sg:tags":[
        "away",
        "take"
    ],
    "wof:name":"Pizza Hut",
    "wof:placetype":"venue"
},
  "geometry": {"coordinates":[151.09223938,-33.8578109741],"type":"Point"}
}