{
  "type": "Feature",
  "properties": {
    "addr:full":"59 Bourbong St Bundaberg QLD 4670",
    "addr:housenumber":"59",
    "addr:postcode":"4670",
    "addr:street":"Bourbong St",
    "iso:country":"AU",
    "sg:address":"59 Bourbong St",
    "sg:city":"Bundaberg",
    "sg:classifiers":[
        {
            "category":"Shopping",
            "subcategory":"Computers & Home Electronics",
            "type":"Retail Goods"
        }
    ],
    "sg:phone":"+61 7 4152 1785",
    "sg:postcode":"4670",
    "sg:province":"QLD",
    "sg:tags":[
        "equipment",
        "part",
        "electronic"
    ],
    "wof:name":"Dick Smith Electronics Pty Ltd",
    "wof:placetype":"venue"
},
  "geometry": {"coordinates":[152.350143433,-24.8655319214],"type":"Point"}
}