{
  "type": "Feature",
  "properties": {
    "addr:full":"Shop 25 Crown Central Shopping Centre Wollongong NSW 2500",
    "addr:housenumber":"shop 25",
    "addr:postcode":"2500",
    "addr:street":"Crown Central",
    "iso:country":"AU",
    "sg:address":"Shop 25 Crown Central Shopping Centre",
    "sg:city":"Wollongong",
    "sg:classifiers":[
        {
            "category":"Shopping",
            "subcategory":"Clothing, Apparel, & Fashions",
            "type":"Retail Goods"
        }
    ],
    "sg:phone":"+61 2 4225 8809",
    "sg:postcode":"2500",
    "sg:province":"NSW",
    "sg:tags":[
        "jean"
    ],
    "wof:name":"JeansWest",
    "wof:placetype":"venue"
},
  "geometry": {"coordinates":[150.870285,-34.409199],"type":"Point"}
}