{
  "type": "Feature",
  "properties": {
    "iso:country":"AU",
    "sg:address":"First Floor 42 Raff St",
    "sg:city":"Toowoomba",
    "sg:classifiers":[
        {
            "category":"Personal",
            "type":"Services"
        }
    ],
    "sg:phone":"+61 7 4639 3066",
    "sg:postcode":"4350",
    "sg:province":"QLD",
    "sg:tags":[
        "reducing",
        "treatment",
        "weight"
    ],
    "wof:name":"TrueHealth Wellness",
    "wof:placetype":"venue"
},
  "geometry": {"coordinates":[151.956635,-27.554296],"type":"Point"}
}