{
  "type": "Feature",
  "properties": {
    "iso:country":"AU",
    "sg:address":"5a Wirra Cl",
    "sg:city":"St Ives",
    "sg:classifiers":[
        {
            "category":"Building & Trades",
            "subcategory":"Landscaping Services",
            "type":"Services"
        }
    ],
    "sg:phone":"+61 2 9449 9333",
    "sg:postcode":"2075",
    "sg:province":"NSW",
    "sg:tags":[
        "inspection"
    ],
    "wof:name":"M A Partridge & Sons",
    "wof:placetype":"venue"
},
  "geometry": {"coordinates":[151.16558837900001,-33.7382392883],"type":"Point"}
}