{
  "type": "Feature",
  "properties": {
    "addr:full":"1 Brickworks Crt Mackay QLD 4740",
    "addr:housenumber":"1",
    "addr:postcode":"4740",
    "addr:street":"Brickworks Crt",
    "iso:country":"AU",
    "sg:address":"1 Brickworks Crt",
    "sg:city":"Mackay",
    "sg:classifiers":[
        {
            "category":"Building & Trades",
            "subcategory":"Construction",
            "type":"Services"
        }
    ],
    "sg:phone":"+61 7 4942 2544",
    "sg:postcode":"4740",
    "sg:province":"QLD",
    "sg:tags":[
        "management"
    ],
    "sg:website":"http://www.mondoliving.com.au",
    "wof:name":"Fergus Builders",
    "wof:placetype":"venue"
},
  "geometry": {"coordinates":[149.14935299999999,-21.131355],"type":"Point"}
}