{
  "type": "Feature",
  "properties": {
    "addr:full":"599 Argyle St Moss Vale NSW 2577",
    "addr:housenumber":"599",
    "addr:postcode":"2577",
    "addr:street":"Argyle St",
    "iso:country":"AU",
    "sg:address":"599 Argyle St",
    "sg:city":"Moss Vale",
    "sg:classifiers":[
        {
            "category":"Building & Trades",
            "subcategory":"Landscaping Services",
            "type":"Services"
        }
    ],
    "sg:phone":"+61 2 4869 5999",
    "sg:postcode":"2577",
    "sg:province":"NSW",
    "sg:tags":[
        "consultant"
    ],
    "wof:name":"Advanced Building Certifiers",
    "wof:placetype":"venue"
},
  "geometry": {"coordinates":[150.371185303,-34.5501174927],"type":"Point"}
}