{
  "type": "Feature",
  "properties": {
    "addr:full":"Shop 5/266- 276 Burwood Rd Burwood NSW 2134",
    "addr:housenumber":"shop 5 / 266 276",
    "addr:postcode":"2134",
    "addr:street":"Burwood Rd",
    "iso:country":"AU",
    "sg:address":"Shop 5/266- 276 Burwood Rd",
    "sg:city":"Burwood",
    "sg:classifiers":[
        {
            "category":"Health Services",
            "subcategory":"Medical Lab",
            "type":"Services"
        }
    ],
    "sg:phone":"+61 2 9744 5762",
    "sg:postcode":"2134",
    "sg:province":"NSW",
    "sg:tags":[
        "laboratory",
        "dental"
    ],
    "wof:name":"Aesthetic Restoration Technique",
    "wof:placetype":"venue"
},
  "geometry": {"coordinates":[151.103027344,-33.8814544678],"type":"Point"}
}