{
  "type": "Feature",
  "properties": {
    "iso:country":"AU",
    "sg:address":"19 Chinchilla St",
    "sg:city":"Chinchilla",
    "sg:classifiers":[
        {
            "category":"Personal",
            "subcategory":"Beauty Salon",
            "type":"Services"
        }
    ],
    "sg:phone":"+61 7 4668 9555",
    "sg:postcode":"4413",
    "sg:province":"QLD",
    "sg:tags":[
        "hairdresser"
    ],
    "wof:name":"Azha's Hair Studio",
    "wof:placetype":"venue"
},
  "geometry": {"coordinates":[150.62858581500001,-26.738609314],"type":"Point"}
}