{
  "type": "Feature",
  "properties": {
    "iso:country":"AU",
    "sg:address":"90 Newcombe St",
    "sg:city":"Portarlington",
    "sg:classifiers":[
        {
            "category":"Wholesale",
            "subcategory":"Medical Equipment & Supplies",
            "type":"Manufacturing & Wholesale Goods"
        }
    ],
    "sg:phone":"+61 3 5259 2363",
    "sg:postcode":"3223",
    "sg:province":"VIC",
    "sg:tags":[
        "aid",
        "care",
        "health",
        "home"
    ],
    "wof:name":"Portarlington Pharmacy",
    "wof:placetype":"venue"
},
  "geometry": {"coordinates":[144.653717,-38.115204],"type":"Point"}
}