{
  "type": "Feature",
  "properties": {
    "addr:full":"2-5 North St Ascot Vale VIC 3032",
    "addr:housenumber":"2-5",
    "addr:postcode":"3032",
    "addr:street":"North St",
    "iso:country":"AU",
    "sg:address":"2-5 North St",
    "sg:city":"Ascot Vale",
    "sg:classifiers":[
        {
            "category":"Sports & Exercise",
            "subcategory":"Gym",
            "type":"Entertainment"
        }
    ],
    "sg:phone":"+61 3 9375 2399",
    "sg:postcode":"3032",
    "sg:province":"VIC",
    "sg:tags":[
        "personal",
        "trainer",
        "fitness"
    ],
    "wof:name":"Fernwood Women's Health Clubs",
    "wof:placetype":"venue"
},
  "geometry": {"coordinates":[144.92829900000001,-37.776505],"type":"Point"}
}