{
  "type": "Feature",
  "properties": {
    "addr:full":"165 Bannister Rd Canning Vale WA 6155",
    "addr:housenumber":"165",
    "addr:postcode":"6155",
    "addr:street":"Bannister Rd",
    "iso:country":"AU",
    "sg:address":"165 Bannister Rd",
    "sg:city":"Canning Vale",
    "sg:classifiers":[
        {
            "category":"Health Services",
            "subcategory":"Doctor",
            "type":"Services"
        }
    ],
    "sg:phone":"+61 8 9455 2403",
    "sg:postcode":"6155",
    "sg:province":"WA",
    "sg:tags":[
        "medical",
        "practitioner"
    ],
    "wof:name":"Khan Jamil Dr",
    "wof:placetype":"venue"
},
  "geometry": {"coordinates":[115.904892,-32.061665],"type":"Point"}
}