{
  "type": "Feature",
  "properties": {
    "iso:country":"AU",
    "sg:address":"223 Lower Heidelberg Rd",
    "sg:city":"Ivanhoe East",
    "sg:classifiers":[
        {
            "category":"Personal",
            "type":"Services"
        }
    ],
    "sg:phone":"+61 3 9499 9633",
    "sg:postcode":"3079",
    "sg:province":"VIC",
    "sg:tags":[
        "dressmaker"
    ],
    "wof:name":"Catherine R Couture",
    "wof:placetype":"venue"
},
  "geometry": {"coordinates":[145.05818176299999,-37.7725067139],"type":"Point"}
}