{
  "type": "Feature",
  "properties": {
    "iso:country":"AU",
    "sg:address":"464 Oxford St",
    "sg:city":"Paddington",
    "sg:classifiers":[
        {
            "category":"Shopping",
            "subcategory":"Clothing, Apparel, & Fashions",
            "type":"Retail Goods"
        }
    ],
    "sg:phone":"+61 2 9380 9511",
    "sg:postcode":"2021",
    "sg:province":"NSW",
    "sg:tags":[
        "textile",
        "designer"
    ],
    "wof:name":"Fleur Wood Fabrics & Designs Pty Ltd",
    "wof:placetype":"venue"
},
  "geometry": {"coordinates":[151.231811523,-33.8881072998],"type":"Point"}
}