{
  "type": "Feature",
  "properties": {
    "addr:full":"12 Mitchell St Merewether NSW 2291",
    "addr:housenumber":"12",
    "addr:postcode":"2291",
    "addr:street":"Mitchell St",
    "iso:country":"AU",
    "sg:address":"12 Mitchell St",
    "sg:city":"Merewether",
    "sg:classifiers":[
        {
            "category":"Retail",
            "subcategory":"Auto Repair",
            "type":"Services"
        }
    ],
    "sg:phone":"+61 2 4963 2530",
    "sg:postcode":"2291",
    "sg:province":"NSW",
    "sg:tags":[
        "automotive",
        "air conditioning"
    ],
    "wof:name":"Merewether Auto Electrics & Air Conditioning",
    "wof:placetype":"venue"
},
  "geometry": {"coordinates":[151.75700378400001,-32.9416389465],"type":"Point"}
}