{
  "type": "Feature",
  "properties": {
    "addr:full":"97 Belmont Ave Belmont WA 6104",
    "addr:housenumber":"97",
    "addr:postcode":"6104",
    "addr:street":"Belmont Ave",
    "iso:country":"AU",
    "sg:address":"97 Belmont Ave",
    "sg:city":"Belmont",
    "sg:classifiers":[
        {
            "category":"Transit Center",
            "subcategory":"Freight",
            "type":"Transportation"
        }
    ],
    "sg:phone":"+61 8 9479 2000",
    "sg:postcode":"6104",
    "sg:province":"WA",
    "sg:tags":[
        "agent",
        "shipping"
    ],
    "wof:name":"Kent",
    "wof:placetype":"venue"
},
  "geometry": {"coordinates":[115.92549896200001,-31.9587306976],"type":"Point"}
}