{
  "type": "Feature",
  "properties": {
    "addr:full":"261 Green Valley Rd Green Valley NSW 2168",
    "addr:housenumber":"261",
    "addr:postcode":"2168",
    "addr:street":"Green Valley Rd",
    "iso:country":"AU",
    "sg:address":"261 Green Valley Rd",
    "sg:city":"Green Valley",
    "sg:classifiers":[
        {
            "category":"Health Services",
            "subcategory":"Dentist",
            "type":"Services"
        }
    ],
    "sg:phone":"+61 2 9825 0092",
    "sg:postcode":"2168",
    "sg:province":"NSW",
    "wof:name":"Green Valley Dental",
    "wof:placetype":"venue"
},
  "geometry": {"coordinates":[150.860397339,-33.9007644653],"type":"Point"}
}