{
  "type": "Feature",
  "properties": {
    "addr:full":"20 Knutsford Ave Rivervale WA 6103",
    "addr:housenumber":"20",
    "addr:postcode":"6103",
    "addr:street":"Knutsford Ave",
    "iso:country":"AU",
    "sg:address":"20 Knutsford Ave",
    "sg:city":"Rivervale",
    "sg:classifiers":[
        {
            "category":"Building & Trades",
            "subcategory":"Equipment Rental",
            "type":"Services"
        }
    ],
    "sg:phone":"+61 8 9478 1680",
    "sg:postcode":"6103",
    "sg:province":"WA",
    "sg:tags":[
        "crane",
        "hire"
    ],
    "wof:name":"Skip Hiab & Transport Services",
    "wof:placetype":"venue"
},
  "geometry": {"coordinates":[115.918426514,-31.9558982849],"type":"Point"}
}