{
  "type": "Feature",
  "properties": {
    "addr:full":"29 Hunter Rd Healesville VIC 3777",
    "addr:housenumber":"29",
    "addr:postcode":"3777",
    "addr:street":"Hunter Rd",
    "iso:country":"AU",
    "sg:address":"29 Hunter Rd",
    "sg:city":"Healesville",
    "sg:classifiers":[
        {
            "category":"Retail",
            "subcategory":"Auto Repair",
            "type":"Services"
        }
    ],
    "sg:phone":"+61 3 5962 4319",
    "sg:postcode":"3777",
    "sg:province":"VIC",
    "sg:tags":[
        "beater",
        "painter",
        "panel"
    ],
    "wof:name":"Chippys Motor & Panel Repairs",
    "wof:placetype":"venue"
},
  "geometry": {"coordinates":[145.50535600000001,-37.655605],"type":"Point"}
}