{
  "type": "Feature",
  "properties": {
    "iso:country":"AU",
    "sg:address":"23 Rigby St St",
    "sg:city":"Leonards",
    "sg:classifiers":[
        {
            "category":"Building & Trades",
            "subcategory":"Construction",
            "type":"Services"
        }
    ],
    "sg:phone":"+61 3 5257 1878",
    "sg:postcode":"3223",
    "sg:province":"VIC",
    "sg:tags":[
        "polishing",
        "sanding",
        "floor"
    ],
    "wof:name":"Rods Handyman Service",
    "wof:placetype":"venue"
},
  "geometry": {"coordinates":[144.710785,-38.172993],"type":"Point"}
}