{
  "type": "Feature",
  "properties": {
    "iso:country":"AU",
    "sg:address":"Shp 1a/ 23 Mary St",
    "sg:city":"Surry Hills",
    "sg:classifiers":[
        {
            "category":"Cafe",
            "type":"Food & Drink"
        }
    ],
    "sg:phone":"+61 2 9280 1161",
    "sg:postcode":"2010",
    "sg:province":"NSW",
    "wof:name":"Strawberry X Cafe & Catering",
    "wof:placetype":"venue"
},
  "geometry": {"coordinates":[151.20996093799999,-33.8817100525],"type":"Point"}
}