{
  "type": "Feature",
  "properties": {
    "iso:country":"AU",
    "sg:address":"PO Box 1175",
    "sg:city":"Newcastle",
    "sg:classifiers":[
        {
            "category":"Real Estate",
            "subcategory":"Architect",
            "type":"Services"
        }
    ],
    "sg:phone":"+61 2 4926 3511",
    "sg:postcode":"2300",
    "sg:province":"NSW",
    "wof:name":"Crone Partners Architecture Studios",
    "wof:placetype":"venue"
},
  "geometry": {"coordinates":[151.770538,-32.925648],"type":"Point"}
}