{
  "type": "Feature",
  "properties": {
    "addr:full":"4 Buckley Drv Drewvale QLD 4116",
    "addr:housenumber":"4",
    "addr:postcode":"4116",
    "addr:street":"Buckley Drv",
    "iso:country":"AU",
    "sg:address":"4 Buckley Drv",
    "sg:city":"Drewvale",
    "sg:classifiers":[
        {
            "category":"Social Services",
            "subcategory":"Child Care",
            "type":"Services"
        }
    ],
    "sg:phone":"+61 7 3800 6566",
    "sg:postcode":"4116",
    "sg:province":"QLD",
    "wof:name":"Bright Start Child Care Centre",
    "wof:placetype":"venue"
},
  "geometry": {"coordinates":[153.05668640100001,-27.6536884308],"type":"Point"}
}