{
  "type": "Feature",
  "properties": {
    "iso:country":"AU",
    "sg:address":"2 Scott St",
    "sg:city":"Toowoomba",
    "sg:classifiers":[
        {
            "category":"Travel",
            "subcategory":"Hotels & Motels",
            "type":"Entertainment"
        }
    ],
    "sg:phone":"+61 7 4638 1822",
    "sg:postcode":"4350",
    "sg:province":"QLD",
    "sg:website":"http://www.tudorlodgemotel.com.au",
    "wof:name":"A Tudor Lodge Motel",
    "wof:placetype":"venue"
},
  "geometry": {"coordinates":[151.97499099999999,-27.565907],"type":"Point"}
}