{
  "type": "Feature",
  "properties": {
    "iso:country":"AU",
    "sg:address":"Enable, 39 Bungil St",
    "sg:city":"Roma",
    "sg:classifiers":[
        {
            "category":"Health Services",
            "subcategory":"Doctor",
            "type":"Services"
        }
    ],
    "sg:phone":"+61 7 4622 6224",
    "sg:postcode":"4455",
    "sg:province":"QLD",
    "sg:tags":[
        "nurse",
        "nursing"
    ],
    "wof:name":"Spiritus Care Services",
    "wof:placetype":"venue"
},
  "geometry": {"coordinates":[148.79151916500001,-26.5696125031],"type":"Point"}
}