{
  "type": "Feature",
  "properties": {
    "addr:full":"Suite 4 23a Auburn Rd Auburn NSW 2144",
    "addr:housenumber":"23a",
    "addr:postcode":"2144",
    "addr:street":"Auburn Rd",
    "iso:country":"AU",
    "sg:address":"Suite 4 23a Auburn Rd",
    "sg:city":"Auburn",
    "sg:classifiers":[
        {
            "category":"Health Services",
            "subcategory":"Doctor",
            "type":"Services"
        }
    ],
    "sg:phone":"+61 2 9643 2389",
    "sg:postcode":"2144",
    "sg:province":"NSW",
    "sg:tags":[
        "medical",
        "practitioner"
    ],
    "wof:name":"Nguyen Nguyen Hoai",
    "wof:placetype":"venue"
},
  "geometry": {"coordinates":[151.032836914,-33.8509902954],"type":"Point"}
}