{
  "type": "Feature",
  "properties": {
    "iso:country":"AU",
    "sg:address":"4b Silicon Pl",
    "sg:city":"Tullamarine",
    "sg:classifiers":[
        {
            "category":"Communications",
            "subcategory":"Film & Video Production",
            "type":"Services"
        }
    ],
    "sg:phone":"+61 3 8336 1220",
    "sg:postcode":"3043",
    "sg:province":"VIC",
    "sg:tags":[
        "equipment",
        "window",
        "operating"
    ],
    "wof:name":"Innovative Glass Solutions",
    "wof:placetype":"venue"
},
  "geometry": {"coordinates":[144.873535156,-37.7136878967],"type":"Point"}
}