{
  "type": "Feature",
  "properties": {
    "addr:full":"263 Neeld St West Wyalong NSW 2671",
    "addr:housenumber":"263",
    "addr:postcode":"2671",
    "addr:street":"Neeld St West",
    "iso:country":"AU",
    "sg:address":"263 Neeld St",
    "sg:city":"West Wyalong",
    "sg:classifiers":[
        {
            "category":"Travel",
            "subcategory":"Hotels & Motels",
            "type":"Entertainment"
        }
    ],
    "sg:phone":"+61 2 6972 2255",
    "sg:postcode":"2671",
    "sg:province":"NSW",
    "wof:name":"Cameo Inn Motel",
    "wof:placetype":"venue"
},
  "geometry": {"coordinates":[147.201416016,-33.9222717285],"type":"Point"}
}