{
  "type": "Feature",
  "properties": {
    "iso:country":"AU",
    "sg:address":"104 Main St",
    "sg:city":"Greensborough",
    "sg:classifiers":[
        {
            "category":"Education",
            "subcategory":"University",
            "type":"Public Place"
        }
    ],
    "sg:phone":"+61 3 9434 3677",
    "sg:postcode":"3088",
    "sg:province":"VIC",
    "sg:tags":[
        "sewing",
        "dressmaking",
        "tuition"
    ],
    "wof:name":"Design Draft & Make",
    "wof:placetype":"venue"
},
  "geometry": {"coordinates":[145.10562133799999,-37.7028541565],"type":"Point"}
}