{
  "type": "Feature",
  "properties": {
    "addr:full":"68 York St Launceston TAS 7250",
    "addr:housenumber":"68",
    "addr:postcode":"7250",
    "addr:street":"York St",
    "iso:country":"AU",
    "sg:address":"68 York St",
    "sg:city":"Launceston",
    "sg:classifiers":[
        {
            "category":"Health Services",
            "subcategory":"Doctor",
            "type":"Services"
        }
    ],
    "sg:phone":"+61 3 6336 3536",
    "sg:postcode":"7250",
    "sg:province":"TAS",
    "sg:tags":[
        "occupational",
        "safety"
    ],
    "wof:name":"TCCI College Of Management",
    "wof:placetype":"venue"
},
  "geometry": {"coordinates":[147.14251709000001,-41.4365501404],"type":"Point"}
}