{
  "type": "Feature",
  "properties": {
    "addr:full":"28 Debbie St The Gap QLD 4061",
    "addr:housenumber":"28",
    "addr:postcode":"4061",
    "addr:street":"Debbie St",
    "iso:country":"AU",
    "sg:address":"28 Debbie St",
    "sg:city":"The Gap",
    "sg:classifiers":[
        {
            "category":"Building & Trades",
            "subcategory":"Construction",
            "type":"Services"
        }
    ],
    "sg:phone":"+61 7 3300 3154",
    "sg:postcode":"4061",
    "sg:province":"QLD",
    "sg:tags":[
        "plasterboard",
        "plasterer",
        "fixer"
    ],
    "wof:name":"Hevey Jim Plasterers",
    "wof:placetype":"venue"
},
  "geometry": {"coordinates":[152.93812560999999,-27.4410552979],"type":"Point"}
}