{
  "type": "Feature",
  "properties": {
    "addr:full":"Cnr The Boulevarde & Polding St Fairfield Heights NSW 2165",
    "addr:postcode":"2165",
    "addr:street":"Cnr The Boulevarde & Polding St",
    "iso:country":"AU",
    "sg:address":"Cnr The Boulevarde & Polding St",
    "sg:city":"Fairfield Heights",
    "sg:classifiers":[
        {
            "category":"Social Services",
            "subcategory":"Child Care",
            "type":"Services"
        }
    ],
    "sg:phone":"+61 2 9604 5629",
    "sg:postcode":"2165",
    "sg:province":"NSW",
    "sg:tags":[
        "support",
        "health"
    ],
    "wof:name":"Early Childhood Health Centres",
    "wof:placetype":"venue"
},
  "geometry": {"coordinates":[150.938323975,-33.8652572632],"type":"Point"}
}