{
  "type": "Feature",
  "properties": {
    "iso:country":"AU",
    "sg:address":"86 Bayswater Rd",
    "sg:city":"Pimlico",
    "sg:classifiers":[
        {
            "category":"Fast Food",
            "type":"Food & Drink"
        }
    ],
    "sg:phone":"+61 7 4772 7227",
    "sg:postcode":"4812",
    "sg:province":"QLD",
    "sg:tags":[
        "away",
        "take"
    ],
    "wof:name":"Mediterranean Seafoods & Snack Bar",
    "wof:placetype":"venue"
},
  "geometry": {"coordinates":[146.791687,-19.276644],"type":"Point"}
}