{
  "type": "Feature",
  "properties": {
    "iso:country":"AU",
    "sg:address":"11 Angel Rd",
    "sg:city":"Stapylton",
    "sg:classifiers":[
        {
            "category":"Professional",
            "type":"Services"
        }
    ],
    "sg:phone":"+61 7 3807 8466",
    "sg:postcode":"4207",
    "sg:province":"QLD",
    "sg:tags":[
        "control",
        "equipment",
        "traffic"
    ],
    "wof:name":"BTC Booths Hire",
    "wof:placetype":"venue"
},
  "geometry": {"coordinates":[153.23945617699999,-27.7304134369],"type":"Point"}
}