{
  "type": "Feature",
  "properties": {
    "addr:full":"129a Canterbury Rd Blackburn South VIC 3130",
    "addr:housenumber":"129a",
    "addr:postcode":"3130",
    "addr:street":"Canterbury Rd",
    "iso:country":"AU",
    "sg:address":"129a Canterbury Rd",
    "sg:city":"Blackburn South",
    "sg:classifiers":[
        {
            "category":"Banks & Credit Unions",
            "subcategory":"Financial Services",
            "type":"Services"
        }
    ],
    "sg:phone":"+61 3 9875 4300",
    "sg:postcode":"3130",
    "sg:province":"VIC",
    "sg:tags":[
        "advisory",
        "planning",
        "retirement"
    ],
    "wof:name":"Money Guidance Pty Ltd",
    "wof:placetype":"venue"
},
  "geometry": {"coordinates":[145.148635864,-37.8317298889],"type":"Point"}
}