{
  "type": "Feature",
  "properties": {
    "iso:country":"AU",
    "sg:address":"282 Neerim Rd",
    "sg:city":"Carnegie",
    "sg:classifiers":[
        {
            "category":"Building & Trades",
            "subcategory":"Construction",
            "type":"Services"
        }
    ],
    "sg:phone":"+61 3 9571 4700",
    "sg:postcode":"3163",
    "sg:province":"VIC",
    "sg:tags":[
        "contractor"
    ],
    "wof:name":"Prm Constructions",
    "wof:placetype":"venue"
},
  "geometry": {"coordinates":[145.05650329599999,-37.8888626099],"type":"Point"}
}