{
  "type": "Feature",
  "properties": {
    "iso:country":"AU",
    "sg:address":"59- 61 Stewart St",
    "sg:city":"Devonport",
    "sg:classifiers":[
        {
            "category":"Social Services",
            "subcategory":"Child Care",
            "type":"Services"
        }
    ],
    "sg:phone":"+61 3 6424 1744",
    "sg:postcode":"7310",
    "sg:province":"TAS",
    "wof:name":"Pixie Child Centres",
    "wof:placetype":"venue"
},
  "geometry": {"coordinates":[146.35670471200001,-41.1795387268],"type":"Point"}
}