{
  "type": "Feature",
  "properties": {
    "addr:full":"5 Gale Crt Shepparton VIC 3630",
    "addr:housenumber":"5",
    "addr:postcode":"3630",
    "addr:street":"Gale Crt",
    "iso:country":"AU",
    "sg:address":"5 Gale Crt",
    "sg:city":"Shepparton",
    "sg:classifiers":[
        {
            "category":"Building & Trades",
            "subcategory":"Construction",
            "type":"Services"
        }
    ],
    "sg:phone":"+61 428 570 276",
    "sg:postcode":"3630",
    "sg:province":"VIC",
    "sg:tags":[
        "renovation",
        "alterations",
        "extension",
        "contractor"
    ],
    "wof:name":"M & L Nardella Home Builders Pty Ltd",
    "wof:placetype":"venue"
},
  "geometry": {"coordinates":[145.40777587900001,-36.3974609375],"type":"Point"}
}