{
  "type": "Feature",
  "properties": {
    "addr:full":"PO Box 4558 Maroochydore Bus Cntr QLD 4558",
    "addr:postcode":"4558",
    "iso:country":"AU",
    "sg:address":"PO Box 4558",
    "sg:city":"Maroochydore Bus Cntr",
    "sg:classifiers":[
        {
            "category":"Utilities",
            "subcategory":"Electric",
            "type":"Services"
        }
    ],
    "sg:phone":"+61 413 734 351",
    "sg:postcode":"4558",
    "sg:province":"QLD",
    "sg:tags":[
        "electrical",
        "contractor"
    ],
    "wof:name":"Coolum Beach Electrical Service",
    "wof:placetype":"venue"
},
  "geometry": {"coordinates":[153.07473754899999,-26.6551475525],"type":"Point"}
}