{
  "type": "Feature",
  "properties": {
    "iso:country":"AU",
    "sg:address":"143 Reeves St",
    "sg:city":"Narara",
    "sg:classifiers":[
        {
            "category":"Wholesale",
            "subcategory":"Construction Materials",
            "type":"Manufacturing & Wholesale Goods"
        }
    ],
    "sg:phone":"+61 2 4324 4702",
    "sg:postcode":"2250",
    "sg:province":"NSW",
    "sg:tags":[
        "lift"
    ],
    "wof:name":"Elevate Pty Ltd",
    "wof:placetype":"venue"
},
  "geometry": {"coordinates":[151.32760620100001,-33.4019813538],"type":"Point"}
}