{
  "type": "Feature",
  "properties": {
    "addr:full":"20 Montgomery St West End (Brisbane) QLD 4810",
    "addr:housenumber":"20",
    "addr:postcode":"4810",
    "addr:street":"Montgomery St",
    "iso:country":"AU",
    "sg:address":"20 Montgomery St",
    "sg:city":"West End (Brisbane)",
    "sg:classifiers":[
        {
            "category":"Home & Garden",
            "subcategory":"Building Materials",
            "type":"Retail Goods"
        }
    ],
    "sg:phone":"+61 7 4775 4577",
    "sg:postcode":"4810",
    "sg:province":"QLD",
    "sg:tags":[
        "fitting",
        "door"
    ],
    "wof:name":"CSI Doors Townsville",
    "wof:placetype":"venue"
},
  "geometry": {"coordinates":[146.786575,-19.2654],"type":"Point"}
}