{
  "type": "Feature",
  "properties": {
    "addr:full":"PO Box 1 Walwa VIC 3709",
    "addr:postcode":"3709",
    "iso:country":"AU",
    "sg:address":"PO Box 1",
    "sg:city":"Walwa",
    "sg:classifiers":[
        {
            "category":"Building & Trades",
            "subcategory":"Construction",
            "type":"Services"
        }
    ],
    "sg:phone":"+61 427 553 661",
    "sg:postcode":"3709",
    "sg:province":"VIC",
    "sg:tags":[
        "earth",
        "excavating",
        "moving",
        "contractor"
    ],
    "wof:name":"Marwood Earthmoving",
    "wof:placetype":"venue"
},
  "geometry": {"coordinates":[147.73606872600001,-35.9638900757],"type":"Point"}
}