{
  "type": "Feature",
  "properties": {
    "iso:country":"AU",
    "sg:address":"2 Railway St",
    "sg:city":"Deloraine",
    "sg:classifiers":[
        {
            "category":"Cafe",
            "type":"Food & Drink"
        }
    ],
    "sg:phone":"+61 3 6362 2978",
    "sg:postcode":"7304",
    "sg:province":"TAS",
    "wof:name":"Lost in the 50s diner",
    "wof:placetype":"venue"
},
  "geometry": {"coordinates":[146.662125,-41.523727],"type":"Point"}
}