{
  "type": "Feature",
  "properties": {
    "iso:country":"AU",
    "sg:address":"147 Bulleen Rd",
    "sg:city":"Balwyn North",
    "sg:classifiers":[
        {
            "category":"Professional",
            "subcategory":"Computer Services",
            "type":"Services"
        }
    ],
    "sg:phone":"+61 1800 600 661",
    "sg:postcode":"3104",
    "sg:province":"VIC",
    "sg:tags":[
        "repairs",
        "upgrade",
        "equipment"
    ],
    "wof:name":"Business Computer Maintenance Pty Ltd",
    "wof:placetype":"venue"
},
  "geometry": {"coordinates":[145.078033447,-37.7831535339],"type":"Point"}
}