{
  "type": "Feature",
  "properties": {
    "addr:full":"431 Elizabeth St Melbourne VIC 3000",
    "addr:housenumber":"431",
    "addr:postcode":"3000",
    "addr:street":"Elizabeth St",
    "iso:country":"AU",
    "sg:address":"431 Elizabeth St",
    "sg:city":"Melbourne",
    "sg:classifiers":[
        {
            "category":"Personal",
            "subcategory":"Beauty Salon",
            "type":"Services"
        }
    ],
    "sg:phone":"+61 3 9329 6440",
    "sg:postcode":"3000",
    "sg:province":"VIC",
    "sg:tags":[
        "hairdresser"
    ],
    "wof:name":"Jet Hairstylist",
    "wof:placetype":"venue"
},
  "geometry": {"coordinates":[144.96055602999999,-37.8088722229],"type":"Point"}
}