{
  "type": "Feature",
  "properties": {
    "addr:full":"Calvary Hospital 20 Joynton St Lenah Valley TAS 7008",
    "addr:housenumber":"20",
    "addr:postcode":"7008",
    "addr:street":"Joynton St",
    "iso:country":"AU",
    "sg:address":"Calvary Hospital 20 Joynton St",
    "sg:city":"Lenah Valley",
    "sg:classifiers":[
        {
            "category":"Health Services",
            "subcategory":"Doctor",
            "type":"Services"
        }
    ],
    "sg:phone":"+61 3 6278 9221",
    "sg:postcode":"7008",
    "sg:province":"TAS",
    "sg:tags":[
        "medical",
        "practitioner"
    ],
    "wof:name":"Flukes W K",
    "wof:placetype":"venue"
},
  "geometry": {"coordinates":[147.30377197300001,-42.8653793335],"type":"Point"}
}