{
  "type": "Feature",
  "properties": {
    "addr:full":"65 St Vincent St Port Adelaide SA 5015",
    "addr:housenumber":"65",
    "addr:postcode":"5015",
    "addr:street":"St Vincent St",
    "iso:country":"AU",
    "sg:address":"65 St Vincent St",
    "sg:city":"Port Adelaide",
    "sg:classifiers":[
        {
            "category":"Organizations",
            "subcategory":"Labor Organization",
            "type":"Services"
        }
    ],
    "sg:phone":"+61 8 8447 1779",
    "sg:postcode":"5015",
    "sg:province":"SA",
    "sg:tags":[
        "union"
    ],
    "wof:name":"Maritime Union Of Australia The",
    "wof:placetype":"venue"
},
  "geometry": {"coordinates":[138.500656128,-34.8450241089],"type":"Point"}
}