{
  "type": "Feature",
  "properties": {
    "iso:country":"AU",
    "sg:address":"328 Oxley Ave",
    "sg:city":"Margate",
    "sg:classifiers":[
        {
            "category":"Health Services",
            "subcategory":"Health Practitioner",
            "type":"Services"
        }
    ],
    "sg:phone":"+61 7 3284 6383",
    "sg:postcode":"4019",
    "sg:province":"QLD",
    "sg:tags":[
        "physiotherapist"
    ],
    "wof:name":"Ruthenberg Justin",
    "wof:placetype":"venue"
},
  "geometry": {"coordinates":[153.107910156,-27.2374687195],"type":"Point"}
}