{
  "type": "Feature",
  "properties": {
    "addr:full":"53 Collie St Fyshwick ACT 2609",
    "addr:housenumber":"53",
    "addr:postcode":"2609",
    "addr:street":"Collie St",
    "iso:country":"AU",
    "sg:address":"53 Collie St",
    "sg:city":"Fyshwick",
    "sg:classifiers":[
        {
            "category":"Home & Garden",
            "subcategory":"Building Materials",
            "type":"Retail Goods"
        }
    ],
    "sg:phone":"+61 2 6239 2422",
    "sg:postcode":"2609",
    "sg:province":"ACT",
    "sg:tags":[
        "fencing"
    ],
    "wof:name":"Metal Mart",
    "wof:placetype":"venue"
},
  "geometry": {"coordinates":[149.18035888700001,-35.3291168213],"type":"Point"}
}