{
  "type": "Feature",
  "properties": {
    "addr:full":"Unit 2/ 305 Dandenong Rd Prahran VIC 3181",
    "addr:housenumber":"/ 305",
    "addr:postcode":"3181",
    "addr:street":"Dandenong Rd",
    "iso:country":"AU",
    "sg:address":"Unit 2/ 305 Dandenong Rd",
    "sg:city":"Prahran",
    "sg:classifiers":[
        {
            "category":"Arts & Performance",
            "subcategory":"Dance",
            "type":"Entertainment"
        }
    ],
    "sg:phone":"+61 410 402 392",
    "sg:postcode":"3181",
    "sg:province":"VIC",
    "sg:tags":[
        "theatrical",
        "ballet",
        "tuition"
    ],
    "wof:name":"Moving Pictures Dance Theatre",
    "wof:placetype":"venue"
},
  "geometry": {"coordinates":[145.00633239699999,-37.8594436646],"type":"Point"}
}