{
  "type": "Feature",
  "properties": {
    "addr:full":"Roseneath La Armidale NSW 2350",
    "addr:postcode":"2350",
    "addr:street":"La",
    "iso:country":"AU",
    "sg:address":"Roseneath La",
    "sg:city":"Armidale",
    "sg:classifiers":[
        {
            "category":"Retail",
            "subcategory":"Animal Services",
            "type":"Services"
        }
    ],
    "sg:phone":"+61 2 6772 1856",
    "sg:postcode":"2350",
    "sg:province":"NSW",
    "sg:tags":[
        "breeder",
        "sheep",
        "stud",
        "cattle"
    ],
    "wof:name":"Roberts-Thomson B",
    "wof:placetype":"venue"
},
  "geometry": {"coordinates":[151.685455322,-30.5452842712],"type":"Point"}
}