{
  "type": "Feature",
  "properties": {
    "addr:full":"U2/ 8 Yangan Drv Beresfield NSW 2322",
    "addr:postcode":"2322",
    "addr:street":"U2 / 8 Yangan Drv",
    "iso:country":"AU",
    "sg:address":"U2/ 8 Yangan Drv",
    "sg:city":"Beresfield",
    "sg:classifiers":[
        {
            "category":"Home & Garden",
            "subcategory":"Hardware",
            "type":"Retail Goods"
        }
    ],
    "sg:phone":"+61 2 4966 3002",
    "sg:postcode":"2322",
    "sg:province":"NSW",
    "sg:tags":[
        "nut",
        "bolt"
    ],
    "wof:name":"Coventry Fasteners",
    "wof:placetype":"venue"
},
  "geometry": {"coordinates":[151.632354736,-32.8096084595],"type":"Point"}
}