{
  "type": "Feature",
  "properties": {
    "addr:full":"232 Musgrave Rd Coopers Plains QLD 4108",
    "addr:housenumber":"232",
    "addr:postcode":"4108",
    "addr:street":"Musgrave Rd",
    "iso:country":"AU",
    "sg:address":"232 Musgrave Rd",
    "sg:city":"Coopers Plains",
    "sg:classifiers":[
        {
            "category":"Professional",
            "type":"Services"
        }
    ],
    "sg:phone":"+61 7 3276 8481",
    "sg:postcode":"4108",
    "sg:province":"QLD",
    "sg:tags":[
        "shop",
        "fitting"
    ],
    "wof:name":"P.R. Shopfitters",
    "wof:placetype":"venue"
},
  "geometry": {"coordinates":[153.03338623100001,-27.5621738434],"type":"Point"}
}