{
  "type": "Feature",
  "properties": {
    "iso:country":"AU",
    "sg:address":"67-71 Jersey St",
    "sg:city":"Hornsby",
    "sg:classifiers":[
        {
            "category":"Government",
            "subcategory":"Court House",
            "type":"Public Place"
        }
    ],
    "sg:phone":"+61 405 753 607",
    "sg:postcode":"2077",
    "sg:province":"NSW",
    "sg:tags":[
        "personal",
        "marriage",
        "family",
        "counselling"
    ],
    "wof:name":"Deborah Wardle Counselling Services",
    "wof:placetype":"venue"
},
  "geometry": {"coordinates":[151.09910583499999,-33.6974029541],"type":"Point"}
}