{
  "type": "Feature",
  "properties": {
    "addr:full":"Shp 1/ 148 Campbell St Woonona NSW 2517",
    "addr:housenumber":"/ 148",
    "addr:postcode":"2517",
    "addr:street":"Campbell St",
    "iso:country":"AU",
    "sg:address":"Shp 1/ 148 Campbell St",
    "sg:city":"Woonona",
    "sg:classifiers":[
        {
            "category":"Personal",
            "subcategory":"Beauty Salon",
            "type":"Services"
        }
    ],
    "sg:phone":"+61 2 4285 4610",
    "sg:postcode":"2517",
    "sg:province":"NSW",
    "wof:name":"Harmonie Beauty Therapy",
    "wof:placetype":"venue"
},
  "geometry": {"coordinates":[150.905731,-34.342312],"type":"Point"}
}