{
  "type": "Feature",
  "properties": {
    "addr:full":"46 Kent St Rockhampton QLD 4700",
    "addr:housenumber":"46",
    "addr:postcode":"4700",
    "addr:street":"Kent St",
    "iso:country":"AU",
    "sg:address":"46 Kent St",
    "sg:city":"Rockhampton",
    "sg:classifiers":[
        {
            "category":"Building & Trades",
            "subcategory":"Construction",
            "type":"Services"
        }
    ],
    "sg:phone":"+61 429 627 661",
    "sg:postcode":"4700",
    "sg:province":"QLD",
    "sg:tags":[
        "earth",
        "excavating",
        "moving",
        "contractor"
    ],
    "wof:name":"Rolfs Mini Diggers & Gardening Service",
    "wof:placetype":"venue"
},
  "geometry": {"coordinates":[150.51927185100001,-23.3951778412],"type":"Point"}
}