{
  "type": "Feature",
  "properties": {
    "addr:full":"31 Nutwood La Windsor Downs NSW 2756",
    "addr:housenumber":"31",
    "addr:postcode":"2756",
    "addr:street":"Nutwood La",
    "iso:country":"AU",
    "sg:address":"31 Nutwood La",
    "sg:city":"Windsor Downs",
    "sg:classifiers":[
        {
            "category":"Professional",
            "subcategory":"Art Services",
            "type":"Services"
        }
    ],
    "sg:phone":"+61 417 271 208",
    "sg:postcode":"2756",
    "sg:province":"NSW",
    "sg:tags":[
        "decorator",
        "painter"
    ],
    "wof:name":"Nelbo Painting Pty Ltd",
    "wof:placetype":"venue"
},
  "geometry": {"coordinates":[150.81509399399999,-33.6537666321],"type":"Point"}
}