{
  "type": "Feature",
  "properties": {
    "addr:full":"16 Mcmahons Rd Nowra North NSW 2541",
    "addr:housenumber":"16",
    "addr:postcode":"2541",
    "addr:street":"Mcmahons Rd",
    "iso:country":"AU",
    "sg:address":"16 Mcmahons Rd",
    "sg:city":"Nowra North",
    "sg:classifiers":[
        {
            "category":"Social Services",
            "subcategory":"Child Care",
            "type":"Services"
        }
    ],
    "sg:phone":"+61 2 4422 3780",
    "sg:postcode":"2541",
    "sg:province":"NSW",
    "sg:tags":[
        "breeding",
        "artificial"
    ],
    "wof:name":"Stenway Livestock & Breeding Services",
    "wof:placetype":"venue"
},
  "geometry": {"coordinates":[150.582489014,-34.8589401245],"type":"Point"}
}