{
  "type": "Feature",
  "properties": {
    "iso:country":"AU",
    "sg:address":"918 Glenferrie Rd",
    "sg:city":"Kew",
    "sg:classifiers":[
        {
            "category":"Personal",
            "subcategory":"Beauty Salon",
            "type":"Services"
        }
    ],
    "sg:phone":"+61 3 9819 9951",
    "sg:postcode":"3101",
    "sg:province":"VIC",
    "wof:name":"Q Beauty",
    "wof:placetype":"venue"
},
  "geometry": {"coordinates":[145.03808593799999,-37.8087043762],"type":"Point"}
}