{
  "type": "Feature",
  "properties": {
    "iso:country":"AU",
    "sg:address":"187 Katoomba St",
    "sg:city":"Katoomba",
    "sg:classifiers":[
        {
            "category":"Shopping",
            "subcategory":"Clothing, Apparel, & Fashions",
            "type":"Retail Goods"
        }
    ],
    "sg:phone":"+61 2 4782 1487",
    "sg:postcode":"2780",
    "sg:province":"NSW",
    "sg:tags":[
        "menswear"
    ],
    "wof:name":"Ellis Davidsons Menswear",
    "wof:placetype":"venue"
},
  "geometry": {"coordinates":[150.311477661,-33.7154083252],"type":"Point"}
}