{
  "type": "Feature",
  "properties": {
    "addr:full":"133 Katoomba St Katoomba NSW 2780",
    "addr:housenumber":"133",
    "addr:postcode":"2780",
    "addr:street":"Katoomba St",
    "iso:country":"AU",
    "sg:address":"133 Katoomba St",
    "sg:city":"Katoomba",
    "sg:classifiers":[
        {
            "category":"Personal",
            "subcategory":"Beauty Salon",
            "type":"Services"
        }
    ],
    "sg:phone":"+61 2 4782 1207",
    "sg:postcode":"2780",
    "sg:province":"NSW",
    "sg:tags":[
        "hairdresser"
    ],
    "wof:name":"Ginas Salon",
    "wof:placetype":"venue"
},
  "geometry": {"coordinates":[150.311157227,-33.7154769897],"type":"Point"}
}