{
  "type": "Feature",
  "properties": {
    "iso:country":"AU",
    "sg:address":"399 Tooronga Rd",
    "sg:city":"Hawthorn",
    "sg:classifiers":[
        {
            "category":"Retail",
            "subcategory":"Auto Repair",
            "type":"Services"
        }
    ],
    "sg:phone":"+61 1300 139 894",
    "sg:postcode":"3122",
    "sg:province":"VIC",
    "sg:tags":[
        "beater",
        "painter",
        "panel"
    ],
    "wof:name":"Accident Repair Centre Hawthorn",
    "wof:placetype":"venue"
},
  "geometry": {"coordinates":[145.045043945,-37.8442459106],"type":"Point"}
}