{
  "type": "Feature",
  "properties": {
    "addr:full":"25 Hoskin St Shepparton VIC 3630",
    "addr:housenumber":"25",
    "addr:postcode":"3630",
    "addr:street":"Hoskin St",
    "iso:country":"AU",
    "sg:address":"25 Hoskin St",
    "sg:city":"Shepparton",
    "sg:classifiers":[
        {
            "category":"Professional",
            "type":"Services"
        }
    ],
    "sg:phone":"+61 3 5831 5350",
    "sg:postcode":"3630",
    "sg:province":"VIC",
    "sg:tags":[
        "transport"
    ],
    "wof:name":"Shepparton Light Freight Centre",
    "wof:placetype":"venue"
},
  "geometry": {"coordinates":[145.404174805,-36.3844108582],"type":"Point"}
}