{
  "type": "Feature",
  "properties": {
    "addr:full":"Cnr Velution & Propense St Innisfail QLD 4860",
    "addr:postcode":"4860",
    "addr:street":"Cnr Velution & Propense St",
    "iso:country":"AU",
    "sg:address":"Cnr Velution & Propense St",
    "sg:city":"Innisfail",
    "sg:classifiers":[
        {
            "category":"Juice Bar",
            "subcategory":"None",
            "type":"Food & Drink"
        }
    ],
    "sg:phone":"+61 7 4061 1800",
    "sg:postcode":"4860",
    "sg:province":"QLD",
    "sg:tags":[
        "merchant",
        "fruit",
        "processor"
    ],
    "wof:name":"Collins Cordials",
    "wof:placetype":"venue"
},
  "geometry": {"coordinates":[146.01629638700001,-17.5227832794],"type":"Point"}
}