{
  "type": "Feature",
  "properties": {
    "addr:full":"Bondi Westfield 500 Oxford St Bondi Junction NSW 2022",
    "addr:housenumber":"500",
    "addr:postcode":"2022",
    "addr:street":"Oxford St",
    "iso:country":"AU",
    "sg:address":"Bondi Westfield 500 Oxford St",
    "sg:city":"Bondi Junction",
    "sg:classifiers":[
        {
            "category":"Transit Center",
            "subcategory":"Passenger",
            "type":"Transportation"
        }
    ],
    "sg:phone":"+61 2 9369 2066",
    "sg:postcode":"2022",
    "sg:province":"NSW",
    "sg:tags":[
        "retail",
        "toiletry",
        "perfume"
    ],
    "wof:name":"The Perfume Connection",
    "wof:placetype":"venue"
},
  "geometry": {"coordinates":[151.24789428700001,-33.8918838501],"type":"Point"}
}