{
  "type": "Feature",
  "properties": {
    "addr:full":"Factory 4, 30 Cochranes Rd Moorabbin VIC 3189",
    "addr:housenumber":"30",
    "addr:postcode":"3189",
    "addr:street":"Cochranes Rd",
    "iso:country":"AU",
    "sg:address":"Factory 4, 30 Cochranes Rd",
    "sg:city":"Moorabbin",
    "sg:classifiers":[
        {
            "category":"Manufacturing",
            "subcategory":"Signs",
            "type":"Manufacturing & Wholesale Goods"
        }
    ],
    "sg:phone":"+61 1300 188 811",
    "sg:postcode":"3189",
    "sg:province":"VIC",
    "sg:tags":[
        "traffic",
        "safety"
    ],
    "wof:name":"Roadworx Traffic Solutions",
    "wof:placetype":"venue"
},
  "geometry": {"coordinates":[145.06333923299999,-37.9423599243],"type":"Point"}
}