{
  "type": "Feature",
  "properties": {
    "addr:full":"1 Gheringhap St Geelong VIC 3220",
    "addr:housenumber":"1",
    "addr:postcode":"3220",
    "addr:street":"Gheringhap St",
    "iso:country":"AU",
    "sg:address":"1 Gheringhap St",
    "sg:city":"Geelong",
    "sg:classifiers":[
        {
            "category":"Education",
            "subcategory":"University",
            "type":"Public Place"
        }
    ],
    "sg:phone":"+61 3 5227 8100",
    "sg:postcode":"3220",
    "sg:province":"VIC",
    "sg:tags":[
        "college",
        "tertiary"
    ],
    "wof:name":"Deakin University",
    "wof:placetype":"venue"
},
  "geometry": {"coordinates":[144.35966500000001,-38.143627],"type":"Point"}
}