{
  "type": "Feature",
  "properties": {
    "addr:full":"1276 Boundary Rd Wacol QLD 4076",
    "addr:housenumber":"1276",
    "addr:postcode":"4076",
    "addr:street":"Boundary Rd",
    "iso:country":"AU",
    "sg:address":"1276 Boundary Rd",
    "sg:city":"Wacol",
    "sg:classifiers":[
        {
            "category":"Autos & Motor Vehicles",
            "subcategory":"Auto Supplies",
            "type":"Retail Goods"
        }
    ],
    "sg:phone":"+61 7 3271 3357",
    "sg:postcode":"4076",
    "sg:province":"QLD",
    "sg:tags":[
        "tyre"
    ],
    "sg:website":"http://www.envirocool.com.au",
    "wof:name":"Envirocool Pty Ltd",
    "wof:placetype":"venue"
},
  "geometry": {"coordinates":[152.93354797399999,-27.597820282],"type":"Point"}
}