{
  "type": "Feature",
  "properties": {
    "addr:full":"1/ 17 Wyreema Tce Caloundra QLD 4551",
    "addr:housenumber":"/ 17",
    "addr:postcode":"4551",
    "addr:street":"Wyreema Tce",
    "iso:country":"AU",
    "sg:address":"1/ 17",
    "sg:city":"Wyreema Tce Caloundra",
    "sg:classifiers":[
        {
            "category":"Health Services",
            "subcategory":"Doctor",
            "type":"Services"
        }
    ],
    "sg:phone":"+61 7 5499 7015",
    "sg:postcode":"4551",
    "sg:province":"QLD",
    "sg:tags":[
        "medical",
        "practitioner"
    ],
    "wof:name":"Molescan Pty Ltd",
    "wof:placetype":"venue"
},
  "geometry": {"coordinates":[153.13475036599999,-26.8037891388],"type":"Point"}
}