{
  "type": "Feature",
  "properties": {
    "iso:country":"AU",
    "sg:address":"480 Hargreaves St",
    "sg:city":"Bendigo",
    "sg:classifiers":[
        {
            "category":"Health Services",
            "subcategory":"Health Practitioner",
            "type":"Services"
        }
    ],
    "sg:phone":"+61 3 5442 5017",
    "sg:postcode":"3539",
    "sg:province":"VIC",
    "sg:tags":[
        "physiotherapist"
    ],
    "wof:name":"Hand In Hand Physiotherapy",
    "wof:placetype":"venue"
},
  "geometry": {"coordinates":[144.27372700000001,-36.76461],"type":"Point"}
}