{
  "type": "Feature",
  "properties": {
    "iso:country":"AU",
    "sg:address":"89 Lowood Rd",
    "sg:city":"Mt Barker",
    "sg:classifiers":[
        {
            "category":"Utilities",
            "subcategory":"Electric",
            "type":"Services"
        }
    ],
    "sg:phone":"+61 8 9851 1436",
    "sg:postcode":"6324",
    "sg:province":"WA",
    "sg:tags":[
        "electrical",
        "contractor"
    ],
    "wof:name":"Mt Barker Electrics",
    "wof:placetype":"venue"
},
  "geometry": {"coordinates":[117.662208557,-34.6282157898],"type":"Point"}
}