{
  "type": "Feature",
  "properties": {
    "addr:full":"1/ 9 D&#039;arcy St Doncaster VIC 3108",
    "addr:housenumber":"/ 9 d",
    "addr:postcode":"3108",
    "addr:street":"Arcy St",
    "iso:country":"AU",
    "sg:address":"1/ 9 D&#039;arcy St",
    "sg:city":"Doncaster",
    "sg:classifiers":[
        {
            "category":"Building & Trades",
            "subcategory":"Locksmith",
            "type":"Services"
        }
    ],
    "sg:phone":"+61 3 9848 1409",
    "sg:postcode":"3108",
    "sg:province":"VIC",
    "sg:tags":[
        "lock"
    ],
    "wof:name":"Frontline Locksmiths",
    "wof:placetype":"venue"
},
  "geometry": {"coordinates":[145.14149475100001,-37.7877655029],"type":"Point"}
}