{
  "type": "Feature",
  "properties": {
    "iso:country":"AU",
    "sg:address":"207 Coogee Bay Rd",
    "sg:city":"Coogee",
    "sg:classifiers":[
        {
            "category":"Cafe",
            "type":"Food & Drink"
        }
    ],
    "sg:phone":"+61 2 9665 5619",
    "sg:postcode":"2034",
    "sg:province":"NSW",
    "wof:name":"Tropicana Cafe",
    "wof:placetype":"venue"
},
  "geometry": {"coordinates":[151.25474548299999,-33.9206085205],"type":"Point"}
}