{
  "type": "Feature",
  "properties": {
    "addr:full":"New England Hwy Toowoomba QLD 4350",
    "addr:postcode":"4350",
    "addr:street":"England Hwy",
    "iso:country":"AU",
    "sg:address":"New England Hwy",
    "sg:city":"Toowoomba",
    "sg:classifiers":[
        {
            "category":"Restaurant",
            "type":"Food & Drink"
        }
    ],
    "sg:phone":"+61 7 4632 3258",
    "sg:postcode":"4350",
    "sg:province":"QLD",
    "wof:name":"Christophers",
    "wof:placetype":"venue"
},
  "geometry": {"coordinates":[151.957458,-27.529217],"type":"Point"}
}