{
  "type": "Feature",
  "properties": {
    "addr:full":"U 7/ 377 Scarborugh Beach Rd Innaloo WA 6018",
    "addr:housenumber":"/ 377",
    "addr:postcode":"6018",
    "addr:street":"Scarborugh Beach Rd",
    "iso:country":"AU",
    "sg:address":"U 7/ 377 Scarborugh Beach Rd",
    "sg:city":"Innaloo",
    "sg:classifiers":[
        {
            "category":"Sports & Exercise",
            "subcategory":"Gym",
            "type":"Entertainment"
        }
    ],
    "sg:phone":"+61 8 9445 8055",
    "sg:postcode":"6018",
    "sg:province":"WA",
    "sg:tags":[
        "health",
        "fitness"
    ],
    "wof:name":"Curves",
    "wof:placetype":"venue"
},
  "geometry": {"coordinates":[115.796897888,-31.9024868011],"type":"Point"}
}