{
  "type": "Feature",
  "properties": {
    "iso:country":"AU",
    "sg:address":"1 - 5 Richelieu St",
    "sg:city":"Footscray West",
    "sg:classifiers":[
        {
            "category":"Professional",
            "type":"Services"
        }
    ],
    "sg:phone":"+61 3 9689 9733",
    "sg:postcode":"3012",
    "sg:province":"VIC",
    "sg:tags":[
        "shop",
        "fitting"
    ],
    "wof:name":"A.P.S. Modular Shopfitters",
    "wof:placetype":"venue"
},
  "geometry": {"coordinates":[144.87057495100001,-37.7922821045],"type":"Point"}
}