{
  "type": "Feature",
  "properties": {
    "addr:full":"67 Wilfred Rd Ivanhoe East VIC 3079",
    "addr:housenumber":"67",
    "addr:postcode":"3079",
    "addr:street":"Wilfred Rd",
    "iso:country":"AU",
    "sg:address":"67 Wilfred Rd",
    "sg:city":"Ivanhoe East",
    "sg:classifiers":[
        {
            "category":"Health Services",
            "subcategory":"Dentist",
            "type":"Services"
        }
    ],
    "sg:phone":"+61 3 9497 3303",
    "sg:postcode":"3079",
    "sg:province":"VIC",
    "wof:name":"Panagiotopoulos, George Dr",
    "wof:placetype":"venue"
},
  "geometry": {"coordinates":[145.05862426799999,-37.7730102539],"type":"Point"}
}