{
  "type": "Feature",
  "properties": {
    "addr:full":"Cnr Sidwell Ave & Hopman Crt Shalvey NSW 2770",
    "addr:postcode":"2770",
    "addr:street":"Sidwell Ave & Hopman Crt",
    "iso:country":"AU",
    "sg:address":"Cnr Sidwell Ave & Hopman Crt",
    "sg:city":"Shalvey",
    "sg:classifiers":[
        {
            "category":"Education",
            "subcategory":"Kindergarten",
            "type":"Public Place"
        }
    ],
    "sg:phone":"+61 2 9628 5583",
    "sg:postcode":"2770",
    "sg:province":"NSW",
    "sg:tags":[
        "pre-schools"
    ],
    "wof:name":"KU Children's Services",
    "wof:placetype":"venue"
},
  "geometry": {"coordinates":[150.80563354500001,-33.7292175293],"type":"Point"}
}