{
  "type": "Feature",
  "properties": {
    "iso:country":"AU",
    "sg:address":"Suite 6, 71 Regent St",
    "sg:city":"New Lambton",
    "sg:classifiers":[
        {
            "category":"Health Services",
            "subcategory":"Dentist",
            "type":"Services"
        }
    ],
    "sg:phone":"+61 2 4957 4830",
    "sg:postcode":"2305",
    "sg:province":"NSW",
    "wof:name":"Johnson Andrew P. Dr",
    "wof:placetype":"venue"
},
  "geometry": {"coordinates":[151.71331799999999,-32.924191],"type":"Point"}
}