{
  "type": "Feature",
  "properties": {
    "iso:country":"AU",
    "sg:address":"1/ 200 Kerry St",
    "sg:city":"Sanctuary Point",
    "sg:classifiers":[
        {
            "category":"Banks & Credit Unions",
            "subcategory":"Bank",
            "type":"Services"
        }
    ],
    "sg:phone":"+61 2 4443 9825",
    "sg:postcode":"2540",
    "sg:province":"NSW",
    "wof:name":"Bendigo Community Bank",
    "wof:placetype":"venue"
},
  "geometry": {"coordinates":[150.62399292000001,-35.1051559448],"type":"Point"}
}