{
  "type": "Feature",
  "properties": {
    "addr:full":"Cnr of Park Ave & Ernest St Cammeray NSW 2062",
    "addr:postcode":"2062",
    "addr:street":"St",
    "iso:country":"AU",
    "sg:address":"Cnr of Park Ave & Ernest St",
    "sg:city":"Cammeray",
    "sg:classifiers":[
        {
            "category":"Sports & Exercise",
            "subcategory":"Sports Center",
            "type":"Entertainment"
        }
    ],
    "sg:phone":"+61 2 9953 3878",
    "sg:postcode":"2062",
    "sg:province":"NSW",
    "sg:tags":[
        "coach",
        "tennis"
    ],
    "sg:website":"http://www.michaelritchietennis.com.au",
    "wof:name":"Michael Ritchie Tennis At Cammeray",
    "wof:placetype":"venue"
},
  "geometry": {"coordinates":[151.21841430699999,-33.823474884],"type":"Point"}
}