{
  "type": "Feature",
  "properties": {
    "iso:country":"AU",
    "sg:address":"39 Maitland St",
    "sg:city":"Bingara",
    "sg:classifiers":[
        {
            "category":"Banks & Credit Unions",
            "subcategory":"Bank",
            "type":"Services"
        }
    ],
    "sg:phone":"+61 2 6724 0111",
    "sg:postcode":"2404",
    "sg:province":"NSW",
    "sg:tags":[
        "society"
    ],
    "wof:name":"Peel Valley Credit Union Ltd",
    "wof:placetype":"venue"
},
  "geometry": {"coordinates":[150.57122802699999,-29.8674850464],"type":"Point"}
}