{
  "type": "Feature",
  "properties": {
    "addr:full":"Morrisset St Bathurst NSW 2795",
    "addr:postcode":"2795",
    "addr:street":"Morrisset St",
    "iso:country":"AU",
    "sg:address":"Morrisset St",
    "sg:city":"Bathurst",
    "sg:classifiers":[
        {
            "category":"Personal",
            "subcategory":"Massage",
            "type":"Services"
        }
    ],
    "sg:phone":"+61 2 6332 6119",
    "sg:postcode":"2795",
    "sg:province":"NSW",
    "sg:tags":[
        "therapy"
    ],
    "wof:name":"In Harmony",
    "wof:placetype":"venue"
},
  "geometry": {"coordinates":[149.58303832999999,-33.4122238159],"type":"Point"}
}