{
  "type": "Feature",
  "properties": {
    "addr:full":"Depot 58 - 62 Feltham St North Hobart TAS 7000",
    "addr:housenumber":"62",
    "addr:postcode":"7000",
    "addr:street":"Feltham St",
    "iso:country":"AU",
    "sg:address":"Depot 58 - 62 Feltham St",
    "sg:city":"North Hobart",
    "sg:classifiers":[
        {
            "category":"Building & Trades",
            "subcategory":"Construction",
            "type":"Services"
        }
    ],
    "sg:phone":"+61 3 6234 7030",
    "sg:postcode":"7000",
    "sg:province":"TAS",
    "sg:tags":[
        "earth",
        "excavating",
        "moving",
        "contractor"
    ],
    "wof:name":"Stokely F & P Pty Ltd",
    "wof:placetype":"venue"
},
  "geometry": {"coordinates":[147.317703247,-42.8710250854],"type":"Point"}
}