{
  "type": "Feature",
  "properties": {
    "addr:full":"Lot 74 Ocago St Vineyard NSW 2765",
    "addr:postcode":"2765",
    "addr:street":"St",
    "iso:country":"AU",
    "sg:address":"Lot 74 Ocago St",
    "sg:city":"Vineyard",
    "sg:classifiers":[
        {
            "category":"Building & Trades",
            "subcategory":"Construction",
            "type":"Services"
        }
    ],
    "sg:phone":"+61 407 438 409",
    "sg:postcode":"2765",
    "sg:province":"NSW",
    "sg:tags":[
        "concrete",
        "contractor"
    ],
    "wof:name":"Lanzon Concreting",
    "wof:placetype":"venue"
},
  "geometry": {"coordinates":[150.92857360799999,-33.7030677795],"type":"Point"}
}