{
  "type": "Feature",
  "properties": {
    "iso:country":"AU",
    "sg:address":"111 Elizabeth St",
    "sg:city":"Sydney",
    "sg:classifiers":[
        {
            "category":"Shopping",
            "subcategory":"Clothing, Apparel, & Fashions",
            "type":"Retail Goods"
        }
    ],
    "sg:phone":"+61 2 9231 6341",
    "sg:postcode":"2000",
    "sg:province":"NSW",
    "sg:tags":[
        "menswear"
    ],
    "wof:name":"Val Parks Fine Clothing For Men",
    "wof:placetype":"venue"
},
  "geometry": {"coordinates":[151.21014404300001,-33.8698692322],"type":"Point"}
}