{
  "type": "Feature",
  "properties": {
    "iso:country":"AU",
    "sg:address":"163 Windsor St",
    "sg:city":"Richmond",
    "sg:classifiers":[
        {
            "category":"Travel",
            "subcategory":"Hotels & Motels",
            "type":"Entertainment"
        }
    ],
    "sg:phone":"+61 2 4578 1011",
    "sg:postcode":"2753",
    "sg:province":"NSW",
    "sg:tags":[
        "accommodation"
    ],
    "wof:name":"Royal Family Hotel",
    "wof:placetype":"venue"
},
  "geometry": {"coordinates":[150.753143311,-33.5976638794],"type":"Point"}
}