{
  "type": "Feature",
  "properties": {
    "addr:full":"S2, Waterway Wonderland, Sunshine Blvd Mermaid Waters QLD 4218",
    "addr:postcode":"4218",
    "addr:street":"Sunshine Blvd",
    "iso:country":"AU",
    "sg:address":"S2, Waterway Wonderland, Sunshine Blvd",
    "sg:city":"Mermaid Waters",
    "sg:classifiers":[
        {
            "category":"Personal",
            "subcategory":"Beauty Salon",
            "type":"Services"
        }
    ],
    "sg:phone":"+61 7 5526 1644",
    "sg:postcode":"4218",
    "sg:province":"QLD",
    "wof:name":"Charms Beauty & Skin Solutions",
    "wof:placetype":"venue"
},
  "geometry": {"coordinates":[153.42874145499999,-28.0586299896],"type":"Point"}
}