{
  "type": "Feature",
  "properties": {
    "addr:full":"Rear 1227 Victoria Rd West Ryde NSW 2114",
    "addr:housenumber":"1227",
    "addr:postcode":"2114",
    "addr:street":"Victoria Rd",
    "iso:country":"AU",
    "sg:address":"Rear 1227 Victoria Rd",
    "sg:city":"West Ryde",
    "sg:classifiers":[
        {
            "category":"Professional",
            "subcategory":"Computer Services",
            "type":"Services"
        }
    ],
    "sg:phone":"+61 2 9874 9910",
    "sg:postcode":"2114",
    "sg:province":"NSW",
    "sg:tags":[
        "repairs",
        "upgrade",
        "equipment"
    ],
    "wof:name":"Technocat Technical Services",
    "wof:placetype":"venue"
},
  "geometry": {"coordinates":[151.07128906200001,-33.8067436218],"type":"Point"}
}