{
  "type": "Feature",
  "properties": {
    "iso:country":"AU",
    "sg:address":"Unit 1 / 27 Forge St",
    "sg:city":"Blacktown",
    "sg:classifiers":[
        {
            "category":"Landmark",
            "subcategory":"Scenic View",
            "type":"Public Place"
        }
    ],
    "sg:phone":"+61 411 733 869",
    "sg:postcode":"2148",
    "sg:province":"NSW",
    "sg:tags":[
        "staircase",
        "handrail"
    ],
    "wof:name":"Star Welding & Fabrication",
    "wof:placetype":"venue"
},
  "geometry": {"coordinates":[150.91011047399999,-33.7547340393],"type":"Point"}
}