{
  "type": "Feature",
  "properties": {
    "addr:full":"337 Wellington St Launceston TAS 7250",
    "addr:housenumber":"337",
    "addr:postcode":"7250",
    "addr:street":"Wellington St",
    "iso:country":"AU",
    "sg:address":"337 Wellington St",
    "sg:city":"Launceston",
    "sg:classifiers":[
        {
            "category":"Health Services",
            "subcategory":"Health Practitioner",
            "type":"Services"
        }
    ],
    "sg:phone":"+61 3 6343 7610",
    "sg:postcode":"7250",
    "sg:province":"TAS",
    "sg:tags":[
        "hypnotherapy"
    ],
    "wof:name":"Launceston Hypnotherapy Clinic",
    "wof:placetype":"venue"
},
  "geometry": {"coordinates":[147.14486694300001,-41.454120636],"type":"Point"}
}