{
  "type": "Feature",
  "properties": {
    "addr:full":"10 Langford St Pooraka SA 5095",
    "addr:housenumber":"10",
    "addr:postcode":"5095",
    "addr:street":"Langford St",
    "iso:country":"AU",
    "sg:address":"10 Langford St",
    "sg:city":"Pooraka",
    "sg:classifiers":[
        {
            "category":"Manufacturing",
            "subcategory":"Motor Vehicles & Parts",
            "type":"Manufacturing & Wholesale Goods"
        }
    ],
    "sg:phone":"+61 8 8349 8311",
    "sg:postcode":"5095",
    "sg:province":"SA",
    "sg:tags":[
        "replacement"
    ],
    "wof:name":"Auto Tranz Diff Parts Pty Ltd",
    "wof:placetype":"venue"
},
  "geometry": {"coordinates":[138.62895202600001,-34.8164901733],"type":"Point"}
}