{
  "type": "Feature",
  "properties": {
    "iso:country":"AU",
    "sg:address":"175 Main St",
    "sg:city":"Osborne Park",
    "sg:classifiers":[
        {
            "category":"Professional",
            "subcategory":"Business Services",
            "type":"Services"
        }
    ],
    "sg:phone":"+61 8 9344 5622",
    "sg:postcode":"6017",
    "sg:province":"WA",
    "sg:tags":[
        "drafting"
    ],
    "wof:name":"Marchesani Lou & Associates",
    "wof:placetype":"venue"
},
  "geometry": {"coordinates":[115.828102112,-31.8997077942],"type":"Point"}
}