{
  "type": "Feature",
  "properties": {
    "addr:full":"120 Abercrombie St Chippendale NSW 2008",
    "addr:housenumber":"120",
    "addr:postcode":"2008",
    "addr:street":"Abercrombie St",
    "iso:country":"AU",
    "sg:address":"120 Abercrombie St",
    "sg:city":"Chippendale",
    "sg:classifiers":[
        {
            "category":"Real Estate",
            "subcategory":"Architect",
            "type":"Services"
        }
    ],
    "sg:phone":"+61 2 9310 2228",
    "sg:postcode":"2008",
    "sg:province":"NSW",
    "sg:tags":[
        "building",
        "designer"
    ],
    "wof:name":"JAF Design Pty. Ltd.",
    "wof:placetype":"venue"
},
  "geometry": {"coordinates":[151.19900512699999,-33.8884162903],"type":"Point"}
}