{
  "type": "Feature",
  "properties": {
    "iso:country":"AU",
    "sg:address":"48 Van Der Haar Ave",
    "sg:city":"Berwick",
    "sg:classifiers":[
        {
            "category":"Health Services",
            "subcategory":"Doctor",
            "type":"Services"
        }
    ],
    "sg:phone":"+61 3 9796 2111",
    "sg:postcode":"3806",
    "sg:province":"VIC",
    "sg:tags":[
        "medical",
        "practitioner"
    ],
    "wof:name":"McDonald Sally",
    "wof:placetype":"venue"
},
  "geometry": {"coordinates":[145.34333801299999,-38.0308113098],"type":"Point"}
}