{
  "type": "Feature",
  "properties": {
    "iso:country":"AU",
    "sg:address":"378 Goodwood Rd",
    "sg:city":"Cumberland Park",
    "sg:classifiers":[
        {
            "category":"Health Services",
            "subcategory":"Chiropractor",
            "type":"Services"
        }
    ],
    "sg:phone":"+61 8 8373 3896",
    "sg:postcode":"5041",
    "sg:province":"SA",
    "wof:name":"Westbourne Park Family Chiropractic Centre",
    "wof:placetype":"venue"
},
  "geometry": {"coordinates":[138.590836,-34.968838],"type":"Point"}
}