{
  "type": "Feature",
  "properties": {
    "addr:full":"1083 Frankston-Flinders Rd Somerville VIC 3912",
    "addr:housenumber":"1083",
    "addr:postcode":"3912",
    "addr:street":"Frankston-Flinders Rd",
    "iso:country":"AU",
    "sg:address":"1083 Frankston-Flinders Rd",
    "sg:city":"Somerville",
    "sg:classifiers":[
        {
            "category":"Personal",
            "subcategory":"Tanning Parlor",
            "type":"Services"
        }
    ],
    "sg:phone":"+61 3 5977 6555",
    "sg:postcode":"3912",
    "sg:province":"VIC",
    "sg:tags":[
        "solarium"
    ],
    "wof:name":"Tan Smart Solarium",
    "wof:placetype":"venue"
},
  "geometry": {"coordinates":[145.176879883,-38.224822998],"type":"Point"}
}