{
  "type": "Feature",
  "properties": {
    "addr:full":"101 Percival Rd Smithfield NSW 2164",
    "addr:housenumber":"101",
    "addr:postcode":"2164",
    "addr:street":"Percival Rd",
    "iso:country":"AU",
    "sg:address":"101 Percival Rd",
    "sg:city":"Smithfield",
    "sg:classifiers":[
        {
            "category":"Wholesale",
            "subcategory":"Machinery & Supplies",
            "type":"Manufacturing & Wholesale Goods"
        }
    ],
    "sg:phone":"+61 2 9725 4088",
    "sg:postcode":"2164",
    "sg:province":"NSW",
    "sg:tags":[
        "equipment",
        "hydraulic"
    ],
    "wof:name":"Excel Hydraulics Pty Ltd",
    "wof:placetype":"venue"
},
  "geometry": {"coordinates":[150.95095825199999,-33.8381500244],"type":"Point"}
}