{
  "type": "Feature",
  "properties": {
    "addr:full":"310 Kelvin Park Drv Bringelly NSW 2171",
    "addr:housenumber":"310",
    "addr:postcode":"2171",
    "addr:street":"Kelvin Park Drv",
    "iso:country":"AU",
    "sg:address":"310 Kelvin Park Drv",
    "sg:city":"Bringelly",
    "sg:classifiers":[
        {
            "category":"Building & Trades",
            "subcategory":"Construction",
            "type":"Services"
        }
    ],
    "sg:phone":"+61 418 233 458",
    "sg:postcode":"2171",
    "sg:province":"NSW",
    "sg:tags":[
        "concrete",
        "contractor"
    ],
    "wof:name":"T & B Concreting Pty Ltd",
    "wof:placetype":"venue"
},
  "geometry": {"coordinates":[150.846237183,-33.9284286499],"type":"Point"}
}