{
  "type": "Feature",
  "properties": {
    "iso:country":"AU",
    "sg:address":"312 George St",
    "sg:city":"Sydney",
    "sg:classifiers":[
        {
            "category":"Banks & Credit Unions",
            "subcategory":"Financial Services",
            "type":"Services"
        }
    ],
    "sg:phone":"+61 2 9231 0466",
    "sg:postcode":"2000",
    "sg:province":"NSW",
    "sg:tags":[
        "building",
        "society"
    ],
    "wof:name":"IMB",
    "wof:placetype":"venue"
},
  "geometry": {"coordinates":[151.20738220199999,-33.8661003113],"type":"Point"}
}