{
  "type": "Feature",
  "properties": {
    "addr:full":"74 Dunrod St Holland Park West QLD 4121",
    "addr:housenumber":"74",
    "addr:postcode":"4121",
    "addr:street":"Dunrod St",
    "iso:country":"AU",
    "sg:address":"74 Dunrod St",
    "sg:city":"Holland Park West",
    "sg:classifiers":[
        {
            "category":"Sports & Exercise",
            "subcategory":"Sports Center",
            "type":"Entertainment"
        }
    ],
    "sg:phone":"+61 7 3849 7822",
    "sg:postcode":"4121",
    "sg:province":"QLD",
    "sg:tags":[
        "card",
        "memorabilia"
    ],
    "wof:name":"Brian Craig",
    "wof:placetype":"venue"
},
  "geometry": {"coordinates":[153.06304931599999,-27.5294589996],"type":"Point"}
}