{
  "type": "Feature",
  "properties": {
    "addr:full":"22 Macallan St Carrara QLD 4211",
    "addr:housenumber":"22",
    "addr:postcode":"4211",
    "addr:street":"Macallan St",
    "iso:country":"AU",
    "sg:address":"22 Macallan St",
    "sg:city":"Carrara",
    "sg:classifiers":[
        {
            "category":"Professional",
            "subcategory":"Management & Consulting",
            "type":"Services"
        }
    ],
    "sg:phone":"+61 7 5559 0166",
    "sg:postcode":"4211",
    "sg:province":"QLD",
    "sg:tags":[
        "consultant",
        "business"
    ],
    "wof:name":"Jigsaw Sales Marketing & Training",
    "wof:placetype":"venue"
},
  "geometry": {"coordinates":[153.35896301299999,-28.0454711914],"type":"Point"}
}