{
  "type": "Feature",
  "properties": {
    "addr:full":"3 Bryant Drv Tuggerah NSW 2259",
    "addr:housenumber":"3",
    "addr:postcode":"2259",
    "addr:street":"Bryant Drv",
    "iso:country":"AU",
    "sg:address":"3 Bryant Drv",
    "sg:city":"Tuggerah",
    "sg:classifiers":[
        {
            "category":"Real Estate",
            "subcategory":"Developer",
            "type":"Services"
        }
    ],
    "sg:phone":"+61 2 4351 8404",
    "sg:postcode":"2259",
    "sg:province":"NSW",
    "sg:tags":[
        "development"
    ],
    "wof:name":"Transnational Investment",
    "wof:placetype":"venue"
},
  "geometry": {"coordinates":[151.42239379899999,-33.3122406006],"type":"Point"}
}