{
  "type": "Feature",
  "properties": {
    "iso:country":"AU",
    "sg:address":"122 Strelly St",
    "sg:city":"Busselton",
    "sg:classifiers":[
        {
            "category":"Autos & Motor Vehicles",
            "subcategory":"Automobile Sales",
            "type":"Retail Goods"
        }
    ],
    "sg:phone":"+61 8 9754 8844",
    "sg:postcode":"6280",
    "sg:province":"WA",
    "sg:tags":[
        "equipment",
        "trailer"
    ],
    "wof:name":"Trade Hire",
    "wof:placetype":"venue"
},
  "geometry": {"coordinates":[115.349082947,-33.6623039246],"type":"Point"}
}