{
  "type": "Feature",
  "properties": {
    "iso:country":"AU",
    "sg:address":"Lot 14 East Feluga Rd",
    "sg:city":"Tully",
    "sg:classifiers":[
        {
            "category":"Building & Trades",
            "subcategory":"Pest Control",
            "type":"Services"
        }
    ],
    "sg:phone":"+61 7 4068 9069",
    "sg:postcode":"4854",
    "sg:province":"QLD",
    "wof:name":"Amalgamated Pest Control",
    "wof:placetype":"venue"
},
  "geometry": {"coordinates":[145.98892211899999,-17.882610321],"type":"Point"}
}