{
  "type": "Feature",
  "properties": {
    "addr:full":"Unit 5/ 2 College Rd Berrimah NT 0828",
    "addr:postcode":"nt 0828",
    "addr:street":"College Rd",
    "iso:country":"AU",
    "sg:address":"Unit 5/ 2 College Rd",
    "sg:city":"Berrimah",
    "sg:classifiers":[
        {
            "category":"Farming",
            "subcategory":"Fish & Marine Products",
            "type":"Manufacturing & Wholesale Goods"
        }
    ],
    "sg:phone":"+61 8 8947 3866",
    "sg:postcode":"0828",
    "sg:province":"NT",
    "sg:tags":[
        "wire"
    ],
    "wof:name":"Locker Group Pty Ltd",
    "wof:placetype":"venue"
},
  "geometry": {"coordinates":[130.92283630399999,-12.4385032654],"type":"Point"}
}