{
  "type": "Feature",
  "properties": {
    "addr:full":"Suite 16, Level 2, 25 Solent Circuit Baulkham Hills NSW 2153",
    "addr:housenumber":"25",
    "addr:postcode":"2153",
    "addr:street":"Solent Circuit",
    "iso:country":"AU",
    "sg:address":"Suite 16, Level 2, 25 Solent Circuit",
    "sg:city":"Baulkham Hills",
    "sg:classifiers":[
        {
            "category":"Building & Trades",
            "subcategory":"Cleaning & Sanitation",
            "type":"Services"
        }
    ],
    "sg:phone":"+61 1300 662 428",
    "sg:postcode":"2153",
    "sg:province":"NSW",
    "sg:tags":[
        "industrial",
        "commercial",
        "contractor"
    ],
    "sg:website":"http://www.australianstarsgroup.com.au",
    "wof:name":"Australian Stars Group",
    "wof:placetype":"venue"
},
  "geometry": {"coordinates":[150.96582031200001,-33.7307853699],"type":"Point"}
}