{
  "type": "Feature",
  "properties": {
    "addr:full":"30 Langston Pl Epping NSW 2121",
    "addr:housenumber":"30",
    "addr:postcode":"2121",
    "addr:street":"Langston Pl",
    "iso:country":"AU",
    "sg:address":"30 Langston Pl",
    "sg:city":"Epping",
    "sg:classifiers":[
        {
            "category":"Travel",
            "subcategory":"Travel Agent",
            "type":"Entertainment"
        }
    ],
    "sg:phone":"+61 2 9868 3555",
    "sg:postcode":"2121",
    "sg:province":"NSW",
    "sg:tags":[
        "consultant"
    ],
    "wof:name":"Travelworld",
    "wof:placetype":"venue"
},
  "geometry": {"coordinates":[151.082855225,-33.7732772827],"type":"Point"}
}