{
  "type": "Feature",
  "properties": {
    "iso:country":"AU",
    "sg:address":"Shp 12/ 227 Brisbane St",
    "sg:city":"Ipswich",
    "sg:classifiers":[
        {
            "category":"Arts & Performance",
            "subcategory":"Art Gallery",
            "type":"Entertainment"
        }
    ],
    "sg:phone":"+61 7 3812 3152",
    "sg:postcode":"4305",
    "sg:province":"QLD",
    "wof:name":"Old Flower Mill Art Gallery",
    "wof:placetype":"venue"
},
  "geometry": {"coordinates":[152.75564575199999,-27.6142978668],"type":"Point"}
}