{
  "type": "Feature",
  "properties": {
    "iso:country":"AU",
    "sg:address":"8/5 Ocean St",
    "sg:city":"Bondi",
    "sg:classifiers":[
        {
            "category":"Health Services",
            "subcategory":"Health Practitioner",
            "type":"Services"
        }
    ],
    "sg:phone":"+61 415 867 094",
    "sg:postcode":"2026",
    "sg:province":"NSW",
    "sg:tags":[
        "pathologist",
        "speech"
    ],
    "wof:name":"Niasoff Devorah",
    "wof:placetype":"venue"
},
  "geometry": {"coordinates":[151.26298523,-33.8904304504],"type":"Point"}
}