{
  "type": "Feature",
  "properties": {
    "addr:full":"32 Stainsby Ave Kings Langley NSW 2147",
    "addr:housenumber":"32",
    "addr:postcode":"2147",
    "addr:street":"Stainsby Ave",
    "iso:country":"AU",
    "sg:address":"32 Stainsby Ave",
    "sg:city":"Kings Langley",
    "sg:classifiers":[
        {
            "category":"Building & Trades",
            "subcategory":"Construction",
            "type":"Services"
        }
    ],
    "sg:phone":"+61 2 9624 5086",
    "sg:postcode":"2147",
    "sg:province":"NSW",
    "sg:tags":[
        "contractor"
    ],
    "wof:name":"J.E. Christie & Sons Pty Ltd",
    "wof:placetype":"venue"
},
  "geometry": {"coordinates":[150.945556641,-33.7551078796],"type":"Point"}
}