{
  "type": "Feature",
  "properties": {
    "addr:full":"88 Tasman St Kurnell NSW 2231",
    "addr:housenumber":"88",
    "addr:postcode":"2231",
    "addr:street":"Tasman St",
    "iso:country":"AU",
    "sg:address":"88 Tasman St",
    "sg:city":"Kurnell",
    "sg:classifiers":[
        {
            "category":"Transit Center",
            "subcategory":"Freight",
            "type":"Transportation"
        }
    ],
    "sg:phone":"+61 2 9668 9475",
    "sg:postcode":"2231",
    "sg:province":"NSW",
    "sg:tags":[
        "forklift",
        "truck"
    ],
    "wof:name":"Loadarm Australia Pty Ltd",
    "wof:placetype":"venue"
},
  "geometry": {"coordinates":[151.20054626500001,-34.0128250122],"type":"Point"}
}