{
  "type": "Feature",
  "properties": {
    "addr:full":"480 Parramatta Rd Petersham NSW 2049",
    "addr:housenumber":"480",
    "addr:postcode":"2049",
    "addr:street":"Parramatta Rd",
    "iso:country":"AU",
    "sg:address":"480 Parramatta Rd",
    "sg:city":"Petersham",
    "sg:classifiers":[
        {
            "category":"Banks & Credit Unions",
            "subcategory":"Financial Services",
            "type":"Services"
        }
    ],
    "sg:phone":"+61 2 9568 2044",
    "sg:postcode":"2049",
    "sg:province":"NSW",
    "sg:tags":[
        "financier"
    ],
    "wof:name":"Cash Stop",
    "wof:placetype":"venue"
},
  "geometry": {"coordinates":[151.158005,-33.888325],"type":"Point"}
}