{
  "type": "Feature",
  "properties": {
    "addr:full":"Zouch St Young NSW 2594",
    "addr:postcode":"2594",
    "addr:street":"Zouch St",
    "iso:country":"AU",
    "sg:address":"Zouch St",
    "sg:city":"Young",
    "sg:classifiers":[
        {
            "category":"Autos & Motor Vehicles",
            "subcategory":"Fuel & Gas Station",
            "type":"Retail Goods"
        }
    ],
    "sg:phone":"+61 2 6382 1802",
    "sg:postcode":"2594",
    "sg:province":"NSW",
    "wof:name":"Caltex Oil (Aust) Pty Ltd",
    "wof:placetype":"venue"
},
  "geometry": {"coordinates":[148.29986572300001,-34.3155860901],"type":"Point"}
}