{
  "type": "Feature",
  "properties": {
    "iso:country":"AU",
    "sg:address":"8 Neville St",
    "sg:city":"Meringandan West",
    "sg:classifiers":[
        {
            "category":"Personal",
            "type":"Services"
        }
    ],
    "sg:phone":"+61 7 4696 9034",
    "sg:postcode":"4352",
    "sg:province":"QLD",
    "sg:tags":[
        "dressmaker"
    ],
    "wof:name":"Annette Hutchison Designs",
    "wof:placetype":"venue"
},
  "geometry": {"coordinates":[151.89506499999999,-27.418167],"type":"Point"}
}