{
  "type": "Feature",
  "properties": {
    "addr:full":"Wheelers Hill Shopping Centre, 26/200 Jells Rd Wheelers Hill VIC 3150",
    "addr:housenumber":"26 / 200",
    "addr:postcode":"3150",
    "addr:street":"Jells Rd",
    "iso:country":"AU",
    "sg:address":"Wheelers Hill Shopping Centre, 26/200 Jells Rd",
    "sg:city":"Wheelers Hill",
    "sg:classifiers":[
        {
            "category":"Health Services",
            "subcategory":"Optometrist",
            "type":"Services"
        }
    ],
    "sg:phone":"+61 3 9561 2045",
    "sg:postcode":"3150",
    "sg:province":"VIC",
    "wof:name":"Focus Eyecare",
    "wof:placetype":"venue"
},
  "geometry": {"coordinates":[145.18856811500001,-37.9102706909],"type":"Point"}
}