{
  "type": "Feature",
  "properties": {
    "addr:full":"45a Edgeworth David Ave Hornsby NSW 2077",
    "addr:housenumber":"45a",
    "addr:postcode":"2077",
    "addr:street":"Edgeworth David Ave",
    "iso:country":"AU",
    "sg:address":"45a Edgeworth David Ave",
    "sg:city":"Hornsby",
    "sg:classifiers":[
        {
            "category":"Health Services",
            "subcategory":"Health Practitioner",
            "type":"Services"
        }
    ],
    "sg:phone":"+61 2 9482 8113",
    "sg:postcode":"2077",
    "sg:province":"NSW",
    "sg:tags":[
        "bowen",
        "therapy"
    ],
    "wof:name":"Jane Murphy",
    "wof:placetype":"venue"
},
  "geometry": {"coordinates":[151.10430908199999,-33.7062225342],"type":"Point"}
}