{
  "type": "Feature",
  "properties": {
    "addr:full":"Upper Level, 34 Bridge St Muswellbrook NSW 2333",
    "addr:housenumber":"34",
    "addr:postcode":"2333",
    "addr:street":"Bridge St",
    "iso:country":"AU",
    "sg:address":"Upper Level, 34 Bridge St",
    "sg:city":"Muswellbrook",
    "sg:classifiers":[
        {
            "category":"Professional",
            "subcategory":"Employment Agencies",
            "type":"Services"
        }
    ],
    "sg:phone":"+61 1300 364 357",
    "sg:postcode":"2333",
    "sg:province":"NSW",
    "sg:tags":[
        "provider",
        "internet"
    ],
    "wof:name":"Hunterlink Pty Ltd",
    "wof:placetype":"venue"
},
  "geometry": {"coordinates":[150.88832092300001,-32.2649879456],"type":"Point"}
}