{
  "type": "Feature",
  "properties": {
    "iso:country":"AU",
    "sg:address":"570 Boston Rd",
    "sg:city":"Chandler",
    "sg:classifiers":[
        {
            "category":"Professional",
            "subcategory":"Accounting & Tax Preparation",
            "type":"Services"
        }
    ],
    "sg:phone":"+61 7 3390 1603",
    "sg:postcode":"4155",
    "sg:province":"QLD",
    "sg:tags":[
        "accountant",
        "auditor"
    ],
    "wof:name":"Starkey G L",
    "wof:placetype":"venue"
},
  "geometry": {"coordinates":[153.15672302199999,-27.5064659119],"type":"Point"}
}