{
  "type": "Feature",
  "properties": {
    "addr:full":"PO Box 399 Croydon VIC 3136",
    "addr:postcode":"3136",
    "iso:country":"AU",
    "sg:address":"PO Box 399",
    "sg:city":"Croydon",
    "sg:classifiers":[
        {
            "category":"Shopping",
            "subcategory":"Party Supplies",
            "type":"Retail Goods"
        }
    ],
    "sg:phone":"+61 411 326 257",
    "sg:postcode":"3136",
    "sg:province":"VIC",
    "sg:tags":[
        "children's"
    ],
    "wof:name":"Tip Top Tom the clown",
    "wof:placetype":"venue"
},
  "geometry": {"coordinates":[145.279754639,-37.7989196777],"type":"Point"}
}