{
  "type": "Feature",
  "properties": {
    "addr:full":"Albrecht Rd Tolga QLD 4882",
    "addr:postcode":"4882",
    "addr:street":"Albrecht Rd",
    "iso:country":"AU",
    "sg:address":"Albrecht Rd",
    "sg:city":"Tolga",
    "sg:classifiers":[
        {
            "category":"Building & Trades",
            "subcategory":"Equipment Rental",
            "type":"Services"
        }
    ],
    "sg:phone":"+61 7 4095 4600",
    "sg:postcode":"4882",
    "sg:province":"QLD",
    "sg:tags":[
        "crane",
        "hire"
    ],
    "wof:name":"Atherton Crane Hire",
    "wof:placetype":"venue"
},
  "geometry": {"coordinates":[145.48161315900001,-17.2330513],"type":"Point"}
}