{
  "type": "Feature",
  "properties": {
    "addr:full":"9 Bonner Drv Malaga WA 6090",
    "addr:housenumber":"9",
    "addr:postcode":"6090",
    "addr:street":"Bonner Drv",
    "iso:country":"AU",
    "sg:address":"9 Bonner Drv",
    "sg:city":"Malaga",
    "sg:classifiers":[
        {
            "category":"Real Estate",
            "subcategory":"Real Estate Agent",
            "type":"Services"
        }
    ],
    "sg:phone":"+61 8 9209 1818",
    "sg:postcode":"6090",
    "sg:province":"WA",
    "wof:name":"Home Buyers Realty",
    "wof:placetype":"venue"
},
  "geometry": {"coordinates":[115.879638672,-31.8504180908],"type":"Point"}
}