{
  "type": "Feature",
  "properties": {
    "iso:country":"AU",
    "sg:address":"158 Cheltenham Rd",
    "sg:city":"Dandenong",
    "sg:classifiers":[
        {
            "category":"Shopping",
            "subcategory":"Baby Store",
            "type":"Retail Goods"
        }
    ],
    "sg:phone":"+61 3 9769 2016",
    "sg:postcode":"3175",
    "sg:province":"VIC",
    "sg:tags":[
        "wear"
    ],
    "wof:name":"Hush-A-Bye Baby Nursery Furniture",
    "wof:placetype":"venue"
},
  "geometry": {"coordinates":[145.196044922,-37.9911804199],"type":"Point"}
}