{
  "type": "Feature",
  "properties": {
    "addr:full":"18 Prowse St West Perth WA 6005",
    "addr:housenumber":"18",
    "addr:postcode":"6005",
    "addr:street":"Prowse St",
    "iso:country":"AU",
    "sg:address":"18 Prowse St",
    "sg:city":"West Perth",
    "sg:classifiers":[
        {
            "category":"Real Estate",
            "subcategory":"Real Estate Services",
            "type":"Services"
        }
    ],
    "sg:phone":"+61 8 9322 4955",
    "sg:postcode":"6005",
    "sg:province":"WA",
    "sg:tags":[
        "listing"
    ],
    "wof:name":"Landstore.Com.Au",
    "wof:placetype":"venue"
},
  "geometry": {"coordinates":[115.84171295199999,-31.9447078705],"type":"Point"}
}