{
  "type": "Feature",
  "properties": {
    "addr:full":"14 Hill St Carlton NSW 2218",
    "addr:housenumber":"14",
    "addr:postcode":"2218",
    "addr:street":"Hill St",
    "iso:country":"AU",
    "sg:address":"14 Hill St",
    "sg:city":"Carlton",
    "sg:classifiers":[
        {
            "category":"Professional",
            "subcategory":"Art Services",
            "type":"Services"
        }
    ],
    "sg:phone":"+61 2 9588 5253",
    "sg:postcode":"2218",
    "sg:province":"NSW",
    "sg:tags":[
        "decorator",
        "painter"
    ],
    "wof:name":"Bexley Painting",
    "wof:placetype":"venue"
},
  "geometry": {"coordinates":[151.12649500000001,-33.964584],"type":"Point"}
}