{
  "type": "Feature",
  "properties": {
    "iso:country":"AU",
    "sg:address":"13 Yarrowee St",
    "sg:city":"Currajong",
    "sg:classifiers":[
        {
            "category":"Building & Trades",
            "subcategory":"Cleaning & Sanitation",
            "type":"Services"
        }
    ],
    "sg:phone":"+61 7 4725 2466",
    "sg:postcode":"4812",
    "sg:province":"QLD",
    "sg:tags":[
        "cleaner",
        "repairer",
        "roof"
    ],
    "wof:name":"Graham Pope Plumbing",
    "wof:placetype":"venue"
},
  "geometry": {"coordinates":[146.77410900000001,-19.273079],"type":"Point"}
}