{
  "type": "Feature",
  "properties": {
    "addr:full":"119 Lakemba St Lakemba NSW 2195",
    "addr:housenumber":"119",
    "addr:postcode":"2195",
    "addr:street":"Lakemba St",
    "iso:country":"AU",
    "sg:address":"119 Lakemba St",
    "sg:city":"Lakemba",
    "sg:classifiers":[
        {
            "category":"Health Services",
            "subcategory":"Doctor",
            "type":"Services"
        }
    ],
    "sg:phone":"+61 2 9750 2087",
    "sg:postcode":"2195",
    "sg:province":"NSW",
    "sg:tags":[
        "medical",
        "practitioner"
    ],
    "wof:name":"Ferkh M",
    "wof:placetype":"venue"
},
  "geometry": {"coordinates":[151.08071899999999,-33.915886],"type":"Point"}
}