{
  "type": "Feature",
  "properties": {
    "iso:country":"AU",
    "sg:address":"28 Hastings Drv",
    "sg:city":"Raymond Terrace",
    "sg:classifiers":[
        {
            "category":"Building & Trades",
            "subcategory":"Construction",
            "type":"Services"
        }
    ],
    "sg:phone":"+61 2 4987 1944",
    "sg:postcode":"2324",
    "sg:province":"NSW",
    "sg:tags":[
        "renovation",
        "alterations",
        "extension",
        "contractor"
    ],
    "wof:name":"Nemich Constructions",
    "wof:placetype":"venue"
},
  "geometry": {"coordinates":[151.77565002399999,-32.7585372925],"type":"Point"}
}