{
  "type": "Feature",
  "properties": {
    "addr:full":"Woolwich Rd Hunters Hill NSW 2110",
    "addr:postcode":"2110",
    "addr:street":"Woolwich Rd",
    "iso:country":"AU",
    "sg:address":"Woolwich Rd",
    "sg:city":"Hunters Hill",
    "sg:classifiers":[
        {
            "category":"Professional",
            "subcategory":"Computer Services",
            "type":"Services"
        }
    ],
    "sg:phone":"+61 2 9817 0750",
    "sg:postcode":"2110",
    "sg:province":"NSW",
    "sg:tags":[
        "consultant",
        "system"
    ],
    "wof:name":"Ratio Consulting Pty Ltd",
    "wof:placetype":"venue"
},
  "geometry": {"coordinates":[151.156082153,-33.8375282288],"type":"Point"}
}