{
  "type": "Feature",
  "properties": {
    "addr:full":"35 Victory Rd Airport West VIC 3042",
    "addr:housenumber":"35",
    "addr:postcode":"3042",
    "addr:street":"Victory Rd",
    "iso:country":"AU",
    "sg:address":"35 Victory Rd",
    "sg:city":"Airport West",
    "sg:classifiers":[
        {
            "category":"Professional",
            "subcategory":"Printing & Photocopies",
            "type":"Services"
        }
    ],
    "sg:phone":"+61 3 9338 4566",
    "sg:postcode":"3042",
    "sg:province":"VIC",
    "sg:tags":[
        "trophy"
    ],
    "wof:name":"The Trophy Maker",
    "wof:placetype":"venue"
},
  "geometry": {"coordinates":[144.88873290999999,-37.7185325623],"type":"Point"}
}