{
  "type": "Feature",
  "properties": {
    "addr:full":"275 Hyde St Yarraville VIC 3013",
    "addr:housenumber":"275",
    "addr:postcode":"3013",
    "addr:street":"Hyde St",
    "iso:country":"AU",
    "sg:address":"275 Hyde St",
    "sg:city":"Yarraville",
    "sg:classifiers":[
        {
            "category":"Sports & Exercise",
            "subcategory":"Gym",
            "type":"Entertainment"
        }
    ],
    "sg:phone":"+61 3 9687 5888",
    "sg:postcode":"3013",
    "sg:province":"VIC",
    "sg:tags":[
        "personal",
        "trainer",
        "fitness"
    ],
    "wof:name":"Fusion Martial Arts & Fitness",
    "wof:placetype":"venue"
},
  "geometry": {"coordinates":[144.89610290499999,-37.8213691711],"type":"Point"}
}