{
  "type": "Feature",
  "properties": {
    "addr:full":"177 Binowee Drv Googong ACT 2620",
    "addr:housenumber":"177",
    "addr:postcode":"2620",
    "addr:street":"Binowee Drv",
    "iso:country":"AU",
    "sg:address":"177 Binowee Drv",
    "sg:city":"Googong",
    "sg:classifiers":[
        {
            "category":"Building & Trades",
            "subcategory":"Plumbing",
            "type":"Services"
        }
    ],
    "sg:phone":"+61 417 719 940",
    "sg:postcode":"2620",
    "sg:province":"ACT",
    "sg:tags":[
        "plumber",
        "gasfitters"
    ],
    "wof:name":"Capital Gas Works Pty Ltd",
    "wof:placetype":"venue"
},
  "geometry": {"coordinates":[149.23298645,-35.4141387939],"type":"Point"}
}