{
  "type": "Feature",
  "properties": {
    "iso:country":"AU",
    "sg:address":"205 Main Rd",
    "sg:city":"Lower Plenty",
    "sg:classifiers":[
        {
            "category":"Personal",
            "type":"Services"
        }
    ],
    "sg:phone":"+61 3 9439 0828",
    "sg:postcode":"3093",
    "sg:province":"VIC",
    "sg:tags":[
        "reducing",
        "treatment",
        "weight"
    ],
    "wof:name":"Lower Plenty Health Centre",
    "wof:placetype":"venue"
},
  "geometry": {"coordinates":[145.122314453,-37.7251319885],"type":"Point"}
}