{
  "type": "Feature",
  "properties": {
    "addr:full":"147 Jones St Stirling WA 6021",
    "addr:housenumber":"147",
    "addr:postcode":"6021",
    "addr:street":"Jones St",
    "iso:country":"AU",
    "sg:address":"147 Jones St",
    "sg:city":"Stirling",
    "sg:classifiers":[
        {
            "category":"Professional",
            "subcategory":"Art Services",
            "type":"Services"
        }
    ],
    "sg:phone":"+61 8 9344 7804",
    "sg:postcode":"6021",
    "sg:province":"WA",
    "sg:tags":[
        "decorator",
        "painter"
    ],
    "wof:name":"Colour Works Painting Service",
    "wof:placetype":"venue"
},
  "geometry": {"coordinates":[115.82003021200001,-31.8779354095],"type":"Point"}
}