{
  "type": "Feature",
  "properties": {
    "iso:country":"AU",
    "sg:address":"4 Trent St",
    "sg:city":"Moorabbin",
    "sg:classifiers":[
        {
            "category":"Building & Trades",
            "subcategory":"Cleaning & Sanitation",
            "type":"Services"
        }
    ],
    "sg:phone":"+61 3 9555 7519",
    "sg:postcode":"3189",
    "sg:province":"VIC",
    "sg:tags":[
        "commercial",
        "maintenance"
    ],
    "wof:name":"Pyramid Hill Consultants Pty Ltd",
    "wof:placetype":"venue"
},
  "geometry": {"coordinates":[145.073730469,-37.9427909851],"type":"Point"}
}