{
  "type": "Feature",
  "properties": {
    "addr:full":"86 King St Charleville QLD 4470",
    "addr:housenumber":"86",
    "addr:postcode":"4470",
    "addr:street":"King St",
    "iso:country":"AU",
    "sg:address":"86 King St",
    "sg:city":"Charleville",
    "sg:classifiers":[
        {
            "category":"Autos & Motor Vehicles",
            "subcategory":"Auto Supplies",
            "type":"Retail Goods"
        }
    ],
    "sg:phone":"+61 7 4654 1606",
    "sg:postcode":"4470",
    "sg:province":"QLD",
    "sg:tags":[
        "oil",
        "spirit"
    ],
    "wof:name":"Caltex Oil (Australia) Pty Ltd",
    "wof:placetype":"venue"
},
  "geometry": {"coordinates":[146.25140380900001,-26.4011898041],"type":"Point"}
}