{
  "type": "Feature",
  "properties": {
    "iso:country":"AU",
    "sg:address":"1202 High St",
    "sg:city":"Malvern",
    "sg:classifiers":[
        {
            "category":"Professional",
            "subcategory":"Art Services",
            "type":"Services"
        }
    ],
    "sg:phone":"+61 418 306 896",
    "sg:postcode":"3144",
    "sg:province":"VIC",
    "sg:tags":[
        "decorator",
        "painter"
    ],
    "wof:name":"Just Right Fence Painting",
    "wof:placetype":"venue"
},
  "geometry": {"coordinates":[145.027252197,-37.856464386],"type":"Point"}
}