{
  "type": "Feature",
  "properties": {
    "addr:full":"15- 18 Alfred Rd Chipping Norton NSW 2170",
    "addr:housenumber":"18",
    "addr:postcode":"2170",
    "addr:street":"Alfred Rd",
    "iso:country":"AU",
    "sg:address":"15- 18 Alfred Rd",
    "sg:city":"Chipping Norton",
    "sg:classifiers":[
        {
            "category":"Military Area",
            "subcategory":"Air Force Base",
            "type":"Public Place"
        }
    ],
    "sg:phone":"+61 2 9755 1455",
    "sg:postcode":"2170",
    "sg:province":"NSW",
    "sg:tags":[
        "wholesaler",
        "bag",
        "mfrs",
        "sack"
    ],
    "wof:name":"Mailbag Manufacturing Co.",
    "wof:placetype":"venue"
},
  "geometry": {"coordinates":[150.96629333499999,-33.9231948853],"type":"Point"}
}