{
  "type": "Feature",
  "properties": {
    "iso:country":"AU",
    "sg:address":"184 Mt Dandenong Rd",
    "sg:city":"Ringwood East",
    "sg:classifiers":[
        {
            "category":"Professional",
            "subcategory":"Accounting & Tax Preparation",
            "type":"Services"
        }
    ],
    "sg:phone":"+61 3 9879 1504",
    "sg:postcode":"3135",
    "sg:province":"VIC",
    "sg:tags":[
        "accountant",
        "auditor"
    ],
    "wof:name":"Pile Partners",
    "wof:placetype":"venue"
},
  "geometry": {"coordinates":[145.25944519000001,-37.8016281128],"type":"Point"}
}