{
  "type": "Feature",
  "properties": {
    "addr:full":"174 River Rd Ravenshoe QLD 4872",
    "addr:housenumber":"174",
    "addr:postcode":"4872",
    "addr:street":"River Rd",
    "iso:country":"AU",
    "sg:address":"174 River Rd",
    "sg:city":"Ravenshoe",
    "sg:classifiers":[
        {
            "category":"Building & Trades",
            "subcategory":"Construction",
            "type":"Services"
        }
    ],
    "sg:phone":"+61 7 4097 7704",
    "sg:postcode":"4872",
    "sg:province":"QLD",
    "sg:tags":[
        "contractor"
    ],
    "wof:name":"Barr Greg",
    "wof:placetype":"venue"
},
  "geometry": {"coordinates":[145.41854858400001,-17.6827983856],"type":"Point"}
}