{
  "type": "Feature",
  "properties": {
    "addr:full":"5 Longdown St Newtown NSW 2042",
    "addr:housenumber":"5",
    "addr:postcode":"2042",
    "addr:street":"Longdown St",
    "iso:country":"AU",
    "sg:address":"5 Longdown St",
    "sg:city":"Newtown",
    "sg:classifiers":[
        {
            "category":"Professional",
            "subcategory":"Art Services",
            "type":"Services"
        }
    ],
    "sg:phone":"+61 415 979 022",
    "sg:postcode":"2042",
    "sg:province":"NSW",
    "sg:tags":[
        "graphic",
        "designer"
    ],
    "wof:name":"Liquid Logic",
    "wof:placetype":"venue"
},
  "geometry": {"coordinates":[151.183044,-33.893154],"type":"Point"}
}