{
  "type": "Feature",
  "properties": {
    "addr:full":"195 Melbourne Rd Wodonga VIC 3690",
    "addr:housenumber":"195",
    "addr:postcode":"3690",
    "addr:street":"Melbourne Rd",
    "iso:country":"AU",
    "sg:address":"195 Melbourne Rd",
    "sg:city":"Wodonga",
    "sg:classifiers":[
        {
            "category":"Health Services",
            "subcategory":"Doctor",
            "type":"Services"
        }
    ],
    "sg:phone":"+61 2 6056 2447",
    "sg:postcode":"3690",
    "sg:province":"VIC",
    "sg:tags":[
        "medical",
        "practitioner"
    ],
    "wof:name":"The Travel Doctor TMVC",
    "wof:placetype":"venue"
},
  "geometry": {"coordinates":[146.866500855,-36.1138725281],"type":"Point"}
}