{
  "type": "Feature",
  "properties": {
    "iso:country":"AU",
    "sg:address":"103 Marian St",
    "sg:city":"Mt Isa",
    "sg:classifiers":[
        {
            "category":"Restaurant",
            "type":"Food & Drink"
        }
    ],
    "sg:phone":"+61 7 4743 9399",
    "sg:postcode":"4825",
    "sg:province":"QLD",
    "wof:name":"Abyssinia Cafe Restaurant",
    "wof:placetype":"venue"
},
  "geometry": {"coordinates":[139.49588,-20.72624],"type":"Point"}
}