{
  "type": "Feature",
  "properties": {
    "addr:full":"U8/ 16 Vale St Malaga WA 6090",
    "addr:housenumber":"16",
    "addr:postcode":"6090",
    "addr:street":"U8 /;Vale St",
    "iso:country":"AU",
    "sg:address":"U8/ 16 Vale St",
    "sg:city":"Malaga",
    "sg:classifiers":[
        {
            "category":"Retail",
            "subcategory":"Auto Repair",
            "type":"Services"
        }
    ],
    "sg:phone":"+61 8 9248 4645",
    "sg:postcode":"6090",
    "sg:province":"WA",
    "sg:tags":[
        "beater",
        "painter",
        "panel"
    ],
    "wof:name":"Metal Obsession Smash Repairs",
    "wof:placetype":"venue"
},
  "geometry": {"coordinates":[115.890960693,-31.848405838],"type":"Point"}
}