{
  "type": "Feature",
  "properties": {
    "addr:full":"31 Janet St Five Dock NSW 2046",
    "addr:housenumber":"31",
    "addr:postcode":"2046",
    "addr:street":"Janet St",
    "iso:country":"AU",
    "sg:address":"31 Janet St",
    "sg:city":"Five Dock",
    "sg:classifiers":[
        {
            "category":"Professional",
            "subcategory":"Engineering",
            "type":"Services"
        }
    ],
    "sg:phone":"+61 2 9962 5356",
    "sg:postcode":"2046",
    "sg:province":"NSW",
    "sg:tags":[
        "engineer",
        "structural"
    ],
    "wof:name":"Romano P & Associates Pty Ltd",
    "wof:placetype":"venue"
},
  "geometry": {"coordinates":[151.147018,-33.859249],"type":"Point"}
}