{
  "type": "Feature",
  "properties": {
    "addr:full":"Geelong Market Sq, 56-58 Yarra St Geelong VIC 3220",
    "addr:housenumber":"56-58",
    "addr:postcode":"3220",
    "addr:street":"Yarra St",
    "iso:country":"AU",
    "sg:address":"Geelong Market Sq, 56-58 Yarra St",
    "sg:city":"Geelong",
    "sg:classifiers":[
        {
            "category":"Food & Beverages",
            "subcategory":"Supermarket",
            "type":"Retail Goods"
        }
    ],
    "sg:phone":"+61 3 5222 1933",
    "sg:postcode":"3220",
    "sg:province":"VIC",
    "sg:tags":[
        "grocery",
        "store"
    ],
    "wof:name":"Safeway",
    "wof:placetype":"venue"
},
  "geometry": {"coordinates":[144.36279300000001,-38.148613],"type":"Point"}
}