{
  "type": "Feature",
  "properties": {
    "addr:full":"PO Box 8163 Warnbro WA 6169",
    "addr:postcode":"6169",
    "iso:country":"AU",
    "sg:address":"PO Box 8163",
    "sg:city":"Warnbro",
    "sg:classifiers":[
        {
            "category":"Shopping",
            "subcategory":"Party Supplies",
            "type":"Retail Goods"
        }
    ],
    "sg:phone":"+61 8 9594 2001",
    "sg:postcode":"6169",
    "sg:province":"WA",
    "sg:tags":[
        "children's"
    ],
    "wof:name":"Mad Cow Entertainment Co",
    "wof:placetype":"venue"
},
  "geometry": {"coordinates":[115.759407,-32.347149],"type":"Point"}
}