{
  "type": "Feature",
  "properties": {
    "addr:full":"4 Roder Crt St Agnes SA 5097",
    "addr:housenumber":"4",
    "addr:postcode":"5097",
    "addr:street":"Roder Crt",
    "iso:country":"AU",
    "sg:address":"4 Roder Crt St",
    "sg:city":"Agnes",
    "sg:classifiers":[
        {
            "category":"Wholesale",
            "subcategory":"Non-durable Goods",
            "type":"Manufacturing & Wholesale Goods"
        }
    ],
    "sg:phone":"+61 8 8395 3195",
    "sg:postcode":"5097",
    "sg:province":"SA",
    "sg:tags":[
        "wholesaler",
        "craft",
        "mfrs"
    ],
    "wof:name":"Beadz &#039;n&#039; Jewelz",
    "wof:placetype":"venue"
},
  "geometry": {"coordinates":[138.70605468799999,-34.8335723877],"type":"Point"}
}