{
  "type": "Feature",
  "properties": {
    "iso:country":"AU",
    "sg:address":"19 Pitt St",
    "sg:city":"Taree",
    "sg:classifiers":[
        {
            "category":"Organizations",
            "subcategory":"Membership Organization",
            "type":"Services"
        }
    ],
    "sg:phone":"+61 2 6551 0091",
    "sg:postcode":"2430",
    "sg:province":"NSW",
    "sg:tags":[
        "club",
        "bridge"
    ],
    "wof:name":"Taree Bridge Club Incorporated",
    "wof:placetype":"venue"
},
  "geometry": {"coordinates":[152.479218,-31.905016],"type":"Point"}
}