{
  "type": "Feature",
  "properties": {
    "addr:full":"Cnr Anzac Ave & James St Toowoomba QLD 4350",
    "addr:postcode":"4350",
    "addr:street":"Anzac Ave & James St",
    "iso:country":"AU",
    "sg:address":"Cnr Anzac Ave & James St",
    "sg:city":"Toowoomba",
    "sg:classifiers":[
        {
            "category":"Food & Beverages",
            "subcategory":"Supermarket",
            "type":"Retail Goods"
        }
    ],
    "sg:phone":"+61 7 4634 8211",
    "sg:postcode":"4350",
    "sg:province":"QLD",
    "sg:tags":[
        "grocery",
        "store"
    ],
    "wof:name":"Action Supermarkets",
    "wof:placetype":"venue"
},
  "geometry": {"coordinates":[151.92172199999999,-27.577253],"type":"Point"}
}