{
  "type": "Feature",
  "properties": {
    "iso:country":"AU",
    "sg:address":"Crestwood Drv",
    "sg:city":"Baulkham Hills",
    "sg:classifiers":[
        {
            "category":"Utilities",
            "subcategory":"Water",
            "type":"Services"
        }
    ],
    "sg:phone":"+61 2 9674 6668",
    "sg:postcode":"2153",
    "sg:province":"NSW",
    "sg:tags":[
        "hot",
        "system"
    ],
    "wof:name":"Cooke SJ & JL",
    "wof:placetype":"venue"
},
  "geometry": {"coordinates":[150.97642517099999,-33.7541503906],"type":"Point"}
}