{
  "type": "Feature",
  "properties": {
    "iso:country":"AU",
    "sg:address":"Shop 2, 343 Anzac Pde",
    "sg:city":"Kingsford",
    "sg:classifiers":[
        {
            "category":"Shopping",
            "subcategory":"Computers & Home Electronics",
            "type":"Retail Goods"
        }
    ],
    "sg:phone":"+61 2 9697 0822",
    "sg:postcode":"2032",
    "sg:province":"NSW",
    "sg:tags":[
        "hardware",
        "equipment"
    ],
    "wof:name":"Giant Technology Pty Ltd",
    "wof:placetype":"venue"
},
  "geometry": {"coordinates":[151.22726440400001,-33.923324585],"type":"Point"}
}