{
  "type": "Feature",
  "properties": {
    "addr:full":"Queen St Mall Brisbane QLD 4000",
    "addr:postcode":"4000",
    "addr:street":"Queen St Mall",
    "iso:country":"AU",
    "sg:address":"Queen St Mall",
    "sg:city":"Brisbane",
    "sg:classifiers":[
        {
            "category":"Communications",
            "subcategory":"News Services",
            "type":"Services"
        }
    ],
    "sg:phone":"+61 7 3006 6290",
    "sg:postcode":"4000",
    "sg:province":"QLD",
    "sg:tags":[
        "information",
        "tourist",
        "attractions"
    ],
    "wof:name":"Brisbane Visitor Info Centre",
    "wof:placetype":"venue"
},
  "geometry": {"coordinates":[153.02577209500001,-27.4692306519],"type":"Point"}
}