{
  "type": "Feature",
  "properties": {
    "iso:country":"AU",
    "sg:address":"62 Alma St",
    "sg:city":"Malvern East",
    "sg:classifiers":[
        {
            "category":"Professional",
            "subcategory":"Accounting & Tax Preparation",
            "type":"Services"
        }
    ],
    "sg:phone":"+61 3 9504 4752",
    "sg:postcode":"3145",
    "sg:province":"VIC",
    "sg:tags":[
        "bookkeeping"
    ],
    "wof:name":"Busy Bookkeeping - Camberwell",
    "wof:placetype":"venue"
},
  "geometry": {"coordinates":[145.07708740199999,-37.8810462952],"type":"Point"}
}