{
  "type": "Feature",
  "properties": {
    "addr:full":"11 Hall St Newport VIC 3015",
    "addr:housenumber":"11",
    "addr:postcode":"3015",
    "addr:street":"Hall St",
    "iso:country":"AU",
    "sg:address":"11 Hall St",
    "sg:city":"Newport",
    "sg:classifiers":[
        {
            "category":"Manufacturing",
            "subcategory":"Food",
            "type":"Manufacturing & Wholesale Goods"
        }
    ],
    "sg:phone":"+61 3 9399 5522",
    "sg:postcode":"3015",
    "sg:province":"VIC",
    "sg:tags":[
        "function",
        "catering"
    ],
    "wof:name":"Grazyna's Gourmet Catering",
    "wof:placetype":"venue"
},
  "geometry": {"coordinates":[144.88420105,-37.8436813354],"type":"Point"}
}