{
  "type": "Feature",
  "properties": {
    "addr:full":"Shop 5, 102- 108 Toorak Rd South Yarra VIC 3141",
    "addr:housenumber":"shop 5;108",
    "addr:postcode":"102;3141",
    "addr:street":"Toorak Rd",
    "iso:country":"AU",
    "sg:address":"Shop 5, 102- 108 Toorak Rd",
    "sg:city":"South Yarra",
    "sg:classifiers":[
        {
            "category":"Health Services",
            "subcategory":"Doctor",
            "type":"Services"
        }
    ],
    "sg:phone":"+61 3 9820 1144",
    "sg:postcode":"3141",
    "sg:province":"VIC",
    "sg:tags":[
        "medical",
        "practitioner"
    ],
    "wof:name":"Holden, Luke Dr",
    "wof:placetype":"venue"
},
  "geometry": {"coordinates":[144.989624023,-37.838848114],"type":"Point"}
}