{
  "type": "Feature",
  "properties": {
    "addr:full":"14 Sussex Rd Frankston VIC 3199",
    "addr:housenumber":"14",
    "addr:postcode":"3199",
    "addr:street":"Sussex Rd",
    "iso:country":"AU",
    "sg:address":"14 Sussex Rd",
    "sg:city":"Frankston",
    "sg:classifiers":[
        {
            "category":"Sports & Exercise",
            "subcategory":"Sports Center",
            "type":"Entertainment"
        }
    ],
    "sg:phone":"+61 3 9775 2858",
    "sg:postcode":"3199",
    "sg:province":"VIC",
    "sg:tags":[
        "coach",
        "tennis"
    ],
    "wof:name":"Thrupp Tennis Services",
    "wof:placetype":"venue"
},
  "geometry": {"coordinates":[145.11807250999999,-38.1668815613],"type":"Point"}
}