{
  "type": "Feature",
  "properties": {
    "addr:full":"B3 Harbour Rocks Hotel, Nurses Walk The Rocks NSW 2000",
    "addr:housenumber":"b3",
    "addr:postcode":"2000",
    "addr:street":"Harbour",
    "iso:country":"AU",
    "sg:address":"B3 Harbour Rocks Hotel, Nurses Walk",
    "sg:city":"The Rocks",
    "sg:classifiers":[
        {
            "category":"Arts & Performance",
            "subcategory":"Art Gallery",
            "type":"Entertainment"
        }
    ],
    "sg:phone":"+61 2 9251 7600",
    "sg:postcode":"2000",
    "sg:province":"NSW",
    "wof:name":"Seductive Art - Gallery by Avi Ohana",
    "wof:placetype":"venue"
},
  "geometry": {"coordinates":[151.20811462399999,-33.8596229553],"type":"Point"}
}