{
  "type": "Feature",
  "properties": {
    "iso:country":"AU",
    "sg:address":"12 Sir John Overall Drv",
    "sg:city":"Helensvale",
    "sg:classifiers":[
        {
            "category":"Building & Trades",
            "subcategory":"Construction",
            "type":"Services"
        }
    ],
    "sg:phone":"+61 7 5529 9933",
    "sg:postcode":"4212",
    "sg:province":"QLD",
    "sg:tags":[
        "pool",
        "swimming"
    ],
    "wof:name":"Luxury Gold Coast Pools",
    "wof:placetype":"venue"
},
  "geometry": {"coordinates":[153.334640503,-27.9223613739],"type":"Point"}
}