{
  "type": "Feature",
  "properties": {
    "iso:country":"AU",
    "sg:address":"53 Wharf St",
    "sg:city":"Woolgoolga",
    "sg:classifiers":[
        {
            "category":"Retail",
            "subcategory":"Laundry & Dry Cleaning",
            "type":"Services"
        }
    ],
    "sg:phone":"+61 411 565 202",
    "sg:postcode":"2456",
    "sg:province":"NSW",
    "wof:name":"Blue Water Laundry",
    "wof:placetype":"venue"
},
  "geometry": {"coordinates":[153.200638,-30.110104],"type":"Point"}
}