{
  "type": "Feature",
  "properties": {
    "iso:country":"AU",
    "sg:address":"58-62 Molong St",
    "sg:city":"Condobolin",
    "sg:classifiers":[
        {
            "category":"Government",
            "subcategory":"Fire Station",
            "type":"Public Place"
        }
    ],
    "sg:phone":"+61 2 6895 4444",
    "sg:postcode":"2877",
    "sg:province":"NSW",
    "sg:tags":[
        "brigade"
    ],
    "wof:name":"NSW Rural Fire Service",
    "wof:placetype":"venue"
},
  "geometry": {"coordinates":[147.1427,-33.083786],"type":"Point"}
}