{
  "type": "Feature",
  "properties": {
    "addr:full":"27 Greenwood St Abbotsford VIC 3067",
    "addr:housenumber":"27",
    "addr:postcode":"3067",
    "addr:street":"Greenwood St",
    "iso:country":"AU",
    "sg:address":"27 Greenwood St",
    "sg:city":"Abbotsford",
    "sg:classifiers":[
        {
            "category":"Personal",
            "subcategory":"Massage",
            "type":"Services"
        }
    ],
    "sg:phone":"+61 3 9427 0769",
    "sg:postcode":"3067",
    "sg:province":"VIC",
    "sg:tags":[
        "therapy"
    ],
    "wof:name":"Bray G & C",
    "wof:placetype":"venue"
},
  "geometry": {"coordinates":[144.99339294399999,-37.8084449768],"type":"Point"}
}