{
  "type": "Feature",
  "properties": {
    "iso:country":"AU",
    "sg:address":"141 Durham Rd",
    "sg:city":"Sunshine",
    "sg:classifiers":[
        {
            "category":"Health Services",
            "subcategory":"Doctor",
            "type":"Services"
        }
    ],
    "sg:phone":"+61 3 9311 6411",
    "sg:postcode":"3020",
    "sg:province":"VIC",
    "sg:tags":[
        "medical",
        "practitioner"
    ],
    "wof:name":"Durham Road Clinic",
    "wof:placetype":"venue"
},
  "geometry": {"coordinates":[144.828033,-37.788204],"type":"Point"}
}