{
  "type": "Feature",
  "properties": {
    "iso:country":"AU",
    "sg:address":"11 Phillimore St",
    "sg:city":"Fremantle",
    "sg:classifiers":[
        {
            "category":"Health Services",
            "subcategory":"Health Practitioner",
            "type":"Services"
        }
    ],
    "sg:phone":"+61 8 9437 6330",
    "sg:postcode":"6160",
    "sg:province":"WA",
    "sg:tags":[
        "psychologist"
    ],
    "wof:name":"Martinovich Psychological Services",
    "wof:placetype":"venue"
},
  "geometry": {"coordinates":[115.742409,-32.055096],"type":"Point"}
}