{
  "type": "Feature",
  "properties": {
    "addr:full":"26 Gouger St Adelaide SA 5000",
    "addr:housenumber":"26",
    "addr:postcode":"5000",
    "addr:street":"Gouger St",
    "iso:country":"AU",
    "sg:address":"26 Gouger St",
    "sg:city":"Adelaide",
    "sg:classifiers":[
        {
            "category":"Restaurant",
            "type":"Food & Drink"
        }
    ],
    "sg:phone":"+61 8 8211 7036",
    "sg:postcode":"5000",
    "sg:province":"SA",
    "wof:name":"Ding Hao Restaurant",
    "wof:placetype":"venue"
},
  "geometry": {"coordinates":[138.598556519,-34.930065155],"type":"Point"}
}