{
  "type": "Feature",
  "properties": {
    "iso:country":"AU",
    "sg:address":"PO Box 634",
    "sg:city":"Rye",
    "sg:classifiers":[
        {
            "category":"Real Estate",
            "subcategory":"Architect",
            "type":"Services"
        }
    ],
    "sg:phone":"+61 407 397 969",
    "sg:postcode":"3941",
    "sg:province":"VIC",
    "wof:name":"Rod Thorley Architect",
    "wof:placetype":"venue"
},
  "geometry": {"coordinates":[144.820755005,-38.3701400757],"type":"Point"}
}