{
  "type": "Feature",
  "properties": {
    "addr:full":"3/ 33 Phillips St Kogarah NSW 2217",
    "addr:housenumber":"/ 33",
    "addr:postcode":"2217",
    "addr:street":"Phillips St",
    "iso:country":"AU",
    "sg:address":"3/ 33 Phillips St",
    "sg:city":"Kogarah",
    "sg:classifiers":[
        {
            "category":"Manufacturing",
            "subcategory":"Chemicals & Compounds",
            "type":"Manufacturing & Wholesale Goods"
        }
    ],
    "sg:phone":"+61 2 9588 3500",
    "sg:postcode":"2217",
    "sg:province":"NSW",
    "sg:tags":[
        "industrial"
    ],
    "wof:name":"ATZ Speciality Chemicals Pty Ltd",
    "wof:placetype":"venue"
},
  "geometry": {"coordinates":[151.13943499999999,-33.976864],"type":"Point"}
}