{
  "type": "Feature",
  "properties": {
    "addr:full":"16 Wynne St Colac VIC 3250",
    "addr:housenumber":"16",
    "addr:postcode":"3250",
    "addr:street":"Wynne St",
    "iso:country":"AU",
    "sg:address":"16 Wynne St",
    "sg:city":"Colac",
    "sg:classifiers":[
        {
            "category":"Home & Garden",
            "subcategory":"Garden Supply",
            "type":"Retail Goods"
        }
    ],
    "sg:phone":"+61 3 5231 3283",
    "sg:postcode":"3250",
    "sg:province":"VIC",
    "sg:tags":[
        "fertilizer"
    ],
    "wof:name":"Robb G A",
    "wof:placetype":"venue"
},
  "geometry": {"coordinates":[143.57345599999999,-38.334827],"type":"Point"}
}