{
  "type": "Feature",
  "properties": {
    "addr:full":"59 Albion Rd Albion QLD 4010",
    "addr:housenumber":"59",
    "addr:postcode":"4010",
    "addr:street":"Albion Rd",
    "iso:country":"AU",
    "sg:address":"59 Albion Rd",
    "sg:city":"Albion",
    "sg:classifiers":[
        {
            "category":"Retail",
            "subcategory":"Auto Repair",
            "type":"Services"
        }
    ],
    "sg:phone":"+61 407 160 907",
    "sg:postcode":"4010",
    "sg:province":"QLD",
    "sg:tags":[
        "electrical"
    ],
    "wof:name":"Tecco Car Electrics",
    "wof:placetype":"venue"
},
  "geometry": {"coordinates":[153.038772583,-27.4293937683],"type":"Point"}
}