{
  "type": "Feature",
  "properties": {
    "iso:country":"AU",
    "sg:address":"15 Churchill St",
    "sg:city":"Leura",
    "sg:classifiers":[
        {
            "category":"Building & Trades",
            "subcategory":"Construction",
            "type":"Services"
        }
    ],
    "sg:phone":"+61 2 4784 1996",
    "sg:postcode":"2780",
    "sg:province":"NSW",
    "sg:tags":[
        "contractor"
    ],
    "wof:name":"Le Breton J T",
    "wof:placetype":"venue"
},
  "geometry": {"coordinates":[150.33387756400001,-33.7091026306],"type":"Point"}
}