{
  "type": "Feature",
  "properties": {
    "addr:full":"124 Manchester Rd Mooroolbark VIC 3138",
    "addr:housenumber":"124",
    "addr:postcode":"3138",
    "addr:street":"Manchester Rd",
    "iso:country":"AU",
    "sg:address":"124 Manchester Rd",
    "sg:city":"Mooroolbark",
    "sg:classifiers":[
        {
            "category":"Health Services",
            "subcategory":"Health Practitioner",
            "type":"Services"
        }
    ],
    "sg:phone":"+61 3 9727 2144",
    "sg:postcode":"3138",
    "sg:province":"VIC",
    "sg:tags":[
        "physiotherapist"
    ],
    "wof:name":"In Touch Physiotherapy",
    "wof:placetype":"venue"
},
  "geometry": {"coordinates":[145.312042236,-37.7810707092],"type":"Point"}
}