{
  "type": "Feature",
  "properties": {
    "addr:full":"Shp 4/ 417 High St Preston VIC 3072",
    "addr:housenumber":"/ 417",
    "addr:postcode":"3072",
    "addr:street":"High St",
    "iso:country":"AU",
    "sg:address":"Shp 4/ 417 High St",
    "sg:city":"Preston",
    "sg:classifiers":[
        {
            "category":"Personal",
            "subcategory":"Beauty Salon",
            "type":"Services"
        }
    ],
    "sg:phone":"+61 3 9470 5473",
    "sg:postcode":"3072",
    "sg:province":"VIC",
    "sg:tags":[
        "hairdresser"
    ],
    "wof:name":"Dida Hairdressing",
    "wof:placetype":"venue"
},
  "geometry": {"coordinates":[145.00357055699999,-37.7397041321],"type":"Point"}
}