{
  "type": "Feature",
  "properties": {
    "addr:full":"215 West St Umina Beach NSW 2257",
    "addr:housenumber":"215",
    "addr:postcode":"2257",
    "addr:street":"West St",
    "iso:country":"AU",
    "sg:address":"215 West St",
    "sg:city":"Umina Beach",
    "sg:classifiers":[
        {
            "category":"Wholesale",
            "subcategory":"Medical Equipment & Supplies",
            "type":"Manufacturing & Wholesale Goods"
        }
    ],
    "sg:phone":"+61 2 4342 5308",
    "sg:postcode":"2257",
    "sg:province":"NSW",
    "sg:tags":[
        "scooter",
        "mobility"
    ],
    "wof:name":"Mobility Hire & Sales",
    "wof:placetype":"venue"
},
  "geometry": {"coordinates":[151.32273864699999,-33.5217514038],"type":"Point"}
}