{
  "type": "Feature",
  "properties": {
    "addr:full":"Shop 10 Parra Mall 55 George St Parramatta NSW 2150",
    "addr:housenumber":"shop 10;55",
    "addr:postcode":"2150",
    "addr:street":"Parra Mall;George St",
    "iso:country":"AU",
    "sg:address":"Shop 10 Parra Mall 55 George St",
    "sg:city":"Parramatta",
    "sg:classifiers":[
        {
            "category":"Retail",
            "subcategory":"Repair Shop",
            "type":"Services"
        }
    ],
    "sg:phone":"+61 2 9635 5877",
    "sg:postcode":"2150",
    "sg:province":"NSW",
    "sg:tags":[
        "handbag"
    ],
    "wof:name":"Harmony Handbags",
    "wof:placetype":"venue"
},
  "geometry": {"coordinates":[151.01885986299999,-33.8317871094],"type":"Point"}
}