{
  "type": "Feature",
  "properties": {
    "iso:country":"AU",
    "sg:address":"121 Bedford St",
    "sg:city":"Gillman",
    "sg:classifiers":[
        {
            "category":"Commercial Area",
            "type":"Public Place"
        }
    ],
    "sg:phone":"+61 8 8240 2033",
    "sg:postcode":"5013",
    "sg:province":"SA",
    "sg:tags":[
        "heavy",
        "carrier"
    ],
    "wof:name":"Kennedy P T & T K Transport Pty Ltd",
    "wof:placetype":"venue"
},
  "geometry": {"coordinates":[138.527954102,-34.8391838074],"type":"Point"}
}