{
  "type": "Feature",
  "properties": {
    "addr:full":"Shop 79-80 Brookside Shopping Centre Osborne Rd Brookside Centre QLD 4053",
    "addr:housenumber":"79-80",
    "addr:postcode":"4053",
    "addr:street":"Brookside Shopping;Osborne Rd",
    "iso:country":"AU",
    "sg:address":"Shop 79-80 Brookside Shopping Centre Osborne Rd",
    "sg:city":"Brookside Centre",
    "sg:classifiers":[
        {
            "category":"Cafe",
            "type":"Food & Drink"
        }
    ],
    "sg:phone":"+61 7 3855 1632",
    "sg:postcode":"4053",
    "sg:province":"QLD",
    "wof:name":"Coffee Club The",
    "wof:placetype":"venue"
},
  "geometry": {"coordinates":[152.977752686,-27.4088954926],"type":"Point"}
}