{
  "type": "Feature",
  "properties": {
    "addr:full":"29 Francis Ave Karrinyup WA 6018",
    "addr:housenumber":"29",
    "addr:postcode":"6018",
    "addr:street":"Francis Ave",
    "iso:country":"AU",
    "sg:address":"29 Francis Ave",
    "sg:city":"Karrinyup",
    "sg:classifiers":[
        {
            "category":"Professional",
            "subcategory":"Art Services",
            "type":"Services"
        }
    ],
    "sg:phone":"+61 8 9445 9153",
    "sg:postcode":"6018",
    "sg:province":"WA",
    "sg:tags":[
        "graphic",
        "designer"
    ],
    "wof:name":"Corporate Design Centre",
    "wof:placetype":"venue"
},
  "geometry": {"coordinates":[115.78279113799999,-31.8730163574],"type":"Point"}
}