{
  "type": "Feature",
  "properties": {
    "addr:full":"Lvl 3 , Indooroopilly Shopping Ctr Indooroopilly QLD 4068",
    "addr:postcode":"4068",
    "addr:street":"Shopping Ctr",
    "iso:country":"AU",
    "sg:address":"Lvl 3",
    "sg:city":", Indooroopilly Shopping Ctr Indooroopilly",
    "sg:classifiers":[
        {
            "category":"Professional",
            "subcategory":"Printing & Photocopies",
            "type":"Services"
        }
    ],
    "sg:phone":"+61 7 3878 2199",
    "sg:postcode":"4068",
    "sg:province":"QLD",
    "sg:tags":[
        "photocopying"
    ],
    "wof:name":"Image Plus Digital Imaging Indooroopilly",
    "wof:placetype":"venue"
},
  "geometry": {"coordinates":[152.98948669399999,-27.4924507141],"type":"Point"}
}