{
  "type": "Feature",
  "properties": {
    "addr:full":"33/ 28 - 32 Crown Rd Queenscliff NSW 2096",
    "addr:housenumber":"33 / 28 32",
    "addr:postcode":"2096",
    "addr:street":"Crown Rd",
    "iso:country":"AU",
    "sg:address":"33/ 28 - 32 Crown Rd",
    "sg:city":"Queenscliff",
    "sg:classifiers":[
        {
            "category":"Building & Trades",
            "subcategory":"Landscaping Services",
            "type":"Services"
        }
    ],
    "sg:phone":"+61 2 9939 2793",
    "sg:postcode":"2096",
    "sg:province":"NSW",
    "sg:tags":[
        "architect",
        "landscape"
    ],
    "wof:name":"Wallman Partners Pty Ltd",
    "wof:placetype":"venue"
},
  "geometry": {"coordinates":[151.285232544,-33.7816848755],"type":"Point"}
}