{
  "type": "Feature",
  "properties": {
    "addr:full":"53 Cranwell St Braybrook VIC 3019",
    "addr:housenumber":"53",
    "addr:postcode":"3019",
    "addr:street":"Cranwell St",
    "iso:country":"AU",
    "sg:address":"53 Cranwell St",
    "sg:city":"Braybrook",
    "sg:classifiers":[
        {
            "category":"Wholesale",
            "subcategory":"Apparel",
            "type":"Manufacturing & Wholesale Goods"
        }
    ],
    "sg:phone":"+61 3 9364 9988",
    "sg:postcode":"3019",
    "sg:province":"VIC",
    "sg:tags":[
        "wholesaler",
        "mfrs",
        "dress"
    ],
    "wof:name":"Sam Boy Clothing Pty Ltd",
    "wof:placetype":"venue"
},
  "geometry": {"coordinates":[144.860275269,-37.7786369324],"type":"Point"}
}