{
  "type": "Feature",
  "properties": {
    "iso:country":"AU",
    "sg:address":"40 Pilbara St",
    "sg:city":"Welshpool",
    "sg:classifiers":[
        {
            "category":"Wholesale",
            "subcategory":"Metals & Minerals",
            "type":"Manufacturing & Wholesale Goods"
        }
    ],
    "sg:phone":"+61 8 9258 6710",
    "sg:postcode":"6106",
    "sg:province":"WA",
    "sg:tags":[
        "steel",
        "merchant"
    ],
    "wof:name":"Bright Steel Australia",
    "wof:placetype":"venue"
},
  "geometry": {"coordinates":[115.939987183,-31.9925918579],"type":"Point"}
}