{
  "type": "Feature",
  "properties": {
    "iso:country":"AU",
    "sg:address":"1-2 Little Bega St",
    "sg:city":"Bega",
    "sg:classifiers":[
        {
            "category":"Home & Garden",
            "subcategory":"Carpets & Floor Coverings",
            "type":"Retail Goods"
        }
    ],
    "sg:phone":"+61 2 6492 1364",
    "sg:postcode":"2550",
    "sg:province":"NSW",
    "sg:tags":[
        "tile",
        "wall",
        "layer"
    ],
    "wof:name":"Morris (Perc) Brunton",
    "wof:placetype":"venue"
},
  "geometry": {"coordinates":[149.84852600100001,-36.6736831665],"type":"Point"}
}