{
  "type": "Feature",
  "properties": {
    "addr:full":"5 Indra Rd Blackburn South VIC 3130",
    "addr:housenumber":"5",
    "addr:postcode":"3130",
    "addr:street":"Indra Rd",
    "iso:country":"AU",
    "sg:address":"5 Indra Rd",
    "sg:city":"Blackburn South",
    "sg:classifiers":[
        {
            "category":"Building & Trades",
            "subcategory":"Cleaning & Sanitation",
            "type":"Services"
        }
    ],
    "sg:phone":"+61 411 585 175",
    "sg:postcode":"3130",
    "sg:province":"VIC",
    "sg:tags":[
        "industrial",
        "commercial",
        "contractor"
    ],
    "wof:name":"Canterbury Custom Cleaning",
    "wof:placetype":"venue"
},
  "geometry": {"coordinates":[145.140335083,-37.8376083374],"type":"Point"}
}