{
  "type": "Feature",
  "properties": {
    "addr:full":"209 Ipswich St Esk QLD 4312",
    "addr:housenumber":"209",
    "addr:postcode":"4312",
    "addr:street":"Ipswich St",
    "iso:country":"AU",
    "sg:address":"209 Ipswich St",
    "sg:city":"Esk",
    "sg:classifiers":[
        {
            "category":"Shopping",
            "subcategory":"Clothing, Apparel, & Fashions",
            "type":"Retail Goods"
        }
    ],
    "sg:phone":"+61 7 5424 2077",
    "sg:postcode":"4312",
    "sg:province":"QLD",
    "sg:tags":[
        "recycled",
        "clothing"
    ],
    "wof:name":"Blue Nursing Thrift Shop",
    "wof:placetype":"venue"
},
  "geometry": {"coordinates":[152.423736572,-27.2419662476],"type":"Point"}
}