{
  "type": "Feature",
  "properties": {
    "addr:full":"16 Bain Pl Dundas Valley NSW 2117",
    "addr:housenumber":"16",
    "addr:postcode":"2117",
    "addr:street":"Bain Pl",
    "iso:country":"AU",
    "sg:address":"16 Bain Pl",
    "sg:city":"Dundas Valley",
    "sg:classifiers":[
        {
            "category":"Manufacturing",
            "subcategory":"Furniture",
            "type":"Manufacturing & Wholesale Goods"
        }
    ],
    "sg:phone":"+61 2 9086 9004",
    "sg:postcode":"2117",
    "sg:province":"NSW",
    "sg:tags":[
        "mfrs",
        "supply"
    ],
    "wof:name":"Flat Panel Products",
    "wof:placetype":"venue"
},
  "geometry": {"coordinates":[151.061767578,-33.7929382324],"type":"Point"}
}