{
  "type": "Feature",
  "properties": {
    "iso:country":"AU",
    "sg:address":"227 Grange Rd",
    "sg:city":"Findon",
    "sg:classifiers":[
        {
            "category":"Food & Beverages",
            "subcategory":"Specialty",
            "type":"Retail Goods"
        }
    ],
    "sg:phone":"+61 8 8268 5438",
    "sg:postcode":"5023",
    "sg:province":"SA",
    "sg:tags":[
        "delicacy"
    ],
    "wof:name":"Pink Olive Food Styling",
    "wof:placetype":"venue"
},
  "geometry": {"coordinates":[138.54156494099999,-34.9048919678],"type":"Point"}
}