{
  "type": "Feature",
  "properties": {
    "addr:full":"Unit C 57 Addison Rd Manly NSW 2095",
    "addr:housenumber":"57",
    "addr:postcode":"2095",
    "addr:street":"C;Addison Rd",
    "iso:country":"AU",
    "sg:address":"Unit C 57 Addison Rd",
    "sg:city":"Manly",
    "sg:classifiers":[
        {
            "category":"Professional",
            "subcategory":"Employment Agencies",
            "type":"Services"
        }
    ],
    "sg:phone":"+61 2 9956 6990",
    "sg:postcode":"2095",
    "sg:province":"NSW",
    "sg:tags":[
        "provider",
        "internet"
    ],
    "wof:name":"The Radio Room Digital Designs",
    "wof:placetype":"venue"
},
  "geometry": {"coordinates":[151.28712463400001,-33.8039093018],"type":"Point"}
}