{
  "type": "Feature",
  "properties": {
    "addr:full":"1665 Burwood Hwy Belgrave VIC 3160",
    "addr:housenumber":"1665",
    "addr:postcode":"3160",
    "addr:street":"Burwood Hwy",
    "iso:country":"AU",
    "sg:address":"1665 Burwood Hwy",
    "sg:city":"Belgrave",
    "sg:classifiers":[
        {
            "category":"Shopping",
            "subcategory":"Clothing, Apparel, & Fashions",
            "type":"Retail Goods"
        }
    ],
    "sg:phone":"+61 3 9752 5621",
    "sg:postcode":"3160",
    "sg:province":"VIC",
    "sg:tags":[
        "recycled",
        "clothing"
    ],
    "wof:name":"Belgrave Re-Cycling Shop",
    "wof:placetype":"venue"
},
  "geometry": {"coordinates":[145.354049683,-37.9093742371],"type":"Point"}
}