{
  "type": "Feature",
  "properties": {
    "iso:country":"AU",
    "sg:address":"7 Gangell Pl",
    "sg:city":"Bridgewater",
    "sg:classifiers":[
        {
            "category":"Health Services",
            "subcategory":"Doctor",
            "type":"Services"
        }
    ],
    "sg:phone":"+61 3 6263 6403",
    "sg:postcode":"7030",
    "sg:province":"TAS",
    "sg:tags":[
        "medical",
        "practitioner"
    ],
    "wof:name":"Chambers A",
    "wof:placetype":"venue"
},
  "geometry": {"coordinates":[147.26113891599999,-42.7485618591],"type":"Point"}
}