{
  "type": "Feature",
  "properties": {
    "addr:full":"252 charters towers Rd Hermit Park QLD 4812",
    "addr:housenumber":"252",
    "addr:postcode":"4812",
    "addr:street":"Charters Towers Rd",
    "iso:country":"AU",
    "sg:address":"252 charters towers Rd",
    "sg:city":"Hermit Park",
    "sg:classifiers":[
        {
            "category":"Real Estate",
            "subcategory":"Real Estate Agent",
            "type":"Services"
        }
    ],
    "sg:phone":"+61 7 4759 3967",
    "sg:postcode":"4812",
    "sg:province":"QLD",
    "wof:name":"Dawn Entriken",
    "wof:placetype":"venue"
},
  "geometry": {"coordinates":[146.797043,-19.28793],"type":"Point"}
}