{
  "type": "Feature",
  "properties": {
    "iso:country":"AU",
    "sg:address":"Willows Shoppingtown Thuringowa Drv",
    "sg:city":"Kirwan",
    "sg:classifiers":[
        {
            "category":"Health Services",
            "subcategory":"Health Practitioner",
            "type":"Services"
        }
    ],
    "sg:phone":"+61 1800 356 517",
    "sg:postcode":"4817",
    "sg:province":"QLD",
    "sg:tags":[
        "naturopath"
    ],
    "wof:name":"Payless Chemists",
    "wof:placetype":"venue"
},
  "geometry": {"coordinates":[146.726776,-19.31628],"type":"Point"}
}