{
  "type": "Feature",
  "properties": {
    "iso:country":"AU",
    "sg:address":"3/ 410 Stuart Hwy",
    "sg:city":"Winnellie",
    "sg:classifiers":[
        {
            "category":"Building & Trades",
            "subcategory":"Equipment Rental",
            "type":"Services"
        }
    ],
    "sg:phone":"+61 8 8984 4775",
    "sg:postcode":"0820",
    "sg:province":"NT",
    "sg:tags":[
        "fitness"
    ],
    "wof:name":"The Foam And Rubber Shop",
    "wof:placetype":"venue"
},
  "geometry": {"coordinates":[130.875686645,-12.4254217148],"type":"Point"}
}