{
  "type": "Feature",
  "properties": {
    "addr:full":"179 Furnissdale Rd Furnissdale WA 6210",
    "addr:housenumber":"179",
    "addr:postcode":"6210",
    "addr:street":"Furnissdale Rd",
    "iso:country":"AU",
    "sg:address":"179 Furnissdale Rd",
    "sg:city":"Furnissdale",
    "sg:classifiers":[
        {
            "category":"Manufacturing",
            "subcategory":"Buildings",
            "type":"Manufacturing & Wholesale Goods"
        }
    ],
    "sg:phone":"+61 8 9581 5156",
    "sg:postcode":"6210",
    "sg:province":"WA",
    "sg:tags":[
        "house",
        "gazebo",
        "shade"
    ],
    "wof:name":"Eric Van Den Bergh",
    "wof:placetype":"venue"
},
  "geometry": {"coordinates":[115.778122,-32.553596],"type":"Point"}
}