{
  "type": "Feature",
  "properties": {
    "addr:full":"Suite 3, Ashmore Professional Centre, 115 Currumburra Rd Ashmore QLD 4214",
    "addr:housenumber":"115",
    "addr:postcode":"4214",
    "addr:street":"Currumburra Rd",
    "iso:country":"AU",
    "sg:address":"Suite 3, Ashmore Professional Centre, 115 Currumburra Rd",
    "sg:city":"Ashmore",
    "sg:classifiers":[
        {
            "category":"Health Services",
            "subcategory":"Health Practitioner",
            "type":"Services"
        }
    ],
    "sg:phone":"+61 7 5597 4155",
    "sg:postcode":"4214",
    "sg:province":"QLD",
    "sg:tags":[
        "naturopath"
    ],
    "wof:name":"Gold Coast Complementary Medicine Clinic",
    "wof:placetype":"venue"
},
  "geometry": {"coordinates":[153.38218689000001,-27.9868030548],"type":"Point"}
}