{
  "type": "Feature",
  "properties": {
    "addr:full":"88 King St Manly Vale NSW 2093",
    "addr:housenumber":"88",
    "addr:postcode":"2093",
    "addr:street":"King St",
    "iso:country":"AU",
    "sg:address":"88 King St",
    "sg:city":"Manly Vale",
    "sg:classifiers":[
        {
            "category":"Professional",
            "subcategory":"Art Services",
            "type":"Services"
        }
    ],
    "sg:phone":"+61 2 9949 4108",
    "sg:postcode":"2093",
    "sg:province":"NSW",
    "sg:tags":[
        "decorator",
        "painter"
    ],
    "wof:name":"Paes P C",
    "wof:placetype":"venue"
},
  "geometry": {"coordinates":[151.26072692899999,-33.7812385559],"type":"Point"}
}