{
  "type": "Feature",
  "properties": {
    "addr:full":"172 Main South Rd Morphett Vale SA 5162",
    "addr:housenumber":"172",
    "addr:postcode":"5162",
    "addr:street":"Main South Rd",
    "iso:country":"AU",
    "sg:address":"172 Main South Rd",
    "sg:city":"Morphett Vale",
    "sg:classifiers":[
        {
            "category":"Home & Garden",
            "subcategory":"Household Appliances",
            "type":"Retail Goods"
        }
    ],
    "sg:phone":"+61 8 8326 3555",
    "sg:postcode":"5162",
    "sg:province":"SA",
    "sg:tags":[
        "equipment",
        "gas"
    ],
    "wof:name":"Mannix Airconditioning",
    "wof:placetype":"venue"
},
  "geometry": {"coordinates":[138.52375793499999,-35.1246147156],"type":"Point"}
}