{
  "type": "Feature",
  "properties": {
    "iso:country":"AU",
    "sg:address":"2 Pearl St",
    "sg:city":"Glenroy",
    "sg:classifiers":[
        {
            "category":"Social Services",
            "subcategory":"Child Care",
            "type":"Services"
        }
    ],
    "sg:phone":"+61 3 9306 8366",
    "sg:postcode":"3046",
    "sg:province":"VIC",
    "wof:name":"Pearl Street Child Care Centre",
    "wof:placetype":"venue"
},
  "geometry": {"coordinates":[144.926879883,-37.7098197937],"type":"Point"}
}