{
  "type": "Feature",
  "properties": {
    "addr:full":"13 Greenshank St Peregian Beach QLD 4573",
    "addr:housenumber":"13",
    "addr:postcode":"4573",
    "addr:street":"Greenshank St",
    "iso:country":"AU",
    "sg:address":"13 Greenshank St",
    "sg:city":"Peregian Beach",
    "sg:classifiers":[
        {
            "category":"Building & Trades",
            "subcategory":"Plumbing",
            "type":"Services"
        }
    ],
    "sg:phone":"+61 7 5448 2608",
    "sg:postcode":"4573",
    "sg:province":"QLD",
    "sg:tags":[
        "plumber",
        "gasfitters"
    ],
    "wof:name":"M & C Smith Plumbing",
    "wof:placetype":"venue"
},
  "geometry": {"coordinates":[153.09406999999999,-26.492678],"type":"Point"}
}