{
  "type": "Feature",
  "properties": {
    "addr:full":"41 King St Boort VIC 3537",
    "addr:housenumber":"41",
    "addr:postcode":"3537",
    "addr:street":"King St",
    "iso:country":"AU",
    "sg:address":"41 King St",
    "sg:city":"Boort",
    "sg:classifiers":[
        {
            "category":"Cafe",
            "type":"Food & Drink"
        }
    ],
    "sg:phone":"+61 3 5455 2139",
    "sg:postcode":"3537",
    "sg:province":"VIC",
    "wof:name":"Lakeside Cafe",
    "wof:placetype":"venue"
},
  "geometry": {"coordinates":[143.72706600000001,-36.116161],"type":"Point"}
}