{
  "type": "Feature",
  "properties": {
    "addr:full":"87 McLennan St Mooroopna VIC 3629",
    "addr:housenumber":"87",
    "addr:postcode":"3629",
    "addr:street":"Mclennan St",
    "iso:country":"AU",
    "sg:address":"87 McLennan St",
    "sg:city":"Mooroopna",
    "sg:classifiers":[
        {
            "category":"Health Services",
            "subcategory":"Doctor",
            "type":"Services"
        }
    ],
    "sg:phone":"+61 3 5825 2755",
    "sg:postcode":"3629",
    "sg:province":"VIC",
    "sg:tags":[
        "medical",
        "practitioner"
    ],
    "wof:name":"Ball David",
    "wof:placetype":"venue"
},
  "geometry": {"coordinates":[145.358886719,-36.395072937],"type":"Point"}
}