{
  "type": "Feature",
  "properties": {
    "addr:full":"2/1- 3 Whyalla Pl Prestons NSW 2170",
    "addr:housenumber":"/ 1 3",
    "addr:postcode":"2170",
    "iso:country":"AU",
    "sg:address":"2/1- 3 Whyalla Pl",
    "sg:city":"Prestons",
    "sg:classifiers":[
        {
            "category":"Wholesale",
            "subcategory":"Electrical",
            "type":"Manufacturing & Wholesale Goods"
        }
    ],
    "sg:phone":"+61 1300 852 411",
    "sg:postcode":"2170",
    "sg:province":"NSW",
    "sg:tags":[
        "equipment",
        "testing",
        "electronic",
        "electric"
    ],
    "wof:name":"Nesco Electrical Products",
    "wof:placetype":"venue"
},
  "geometry": {"coordinates":[150.87889099099999,-33.933139801],"type":"Point"}
}