{
  "type": "Feature",
  "properties": {
    "iso:country":"AU",
    "sg:address":"11 Kuring-Gai Ave",
    "sg:city":"Tarragindi",
    "sg:classifiers":[
        {
            "category":"Fast Food",
            "type":"Food & Drink"
        }
    ],
    "sg:phone":"+61 7 3397 9888",
    "sg:postcode":"4121",
    "sg:province":"QLD",
    "sg:tags":[
        "away",
        "take"
    ],
    "wof:name":"Ming Garden Chinese Takeaway",
    "wof:placetype":"venue"
},
  "geometry": {"coordinates":[153.05531310999999,-27.5267467499],"type":"Point"}
}