{
  "type": "Feature",
  "properties": {
    "addr:full":"37 Spring Rd Highett VIC 3190",
    "addr:housenumber":"37",
    "addr:postcode":"3190",
    "addr:street":"Spring Rd",
    "iso:country":"AU",
    "sg:address":"37 Spring Rd",
    "sg:city":"Highett",
    "sg:classifiers":[
        {
            "category":"Shopping",
            "type":"Retail Goods"
        }
    ],
    "sg:phone":"+61 3 9553 4848",
    "sg:postcode":"3190",
    "sg:province":"VIC",
    "sg:tags":[
        "equipment",
        "safety",
        "accessory"
    ],
    "wof:name":"Mine & Safety Lighting Co",
    "wof:placetype":"venue"
},
  "geometry": {"coordinates":[145.03225707999999,-37.9455032349],"type":"Point"}
}