{
  "type": "Feature",
  "properties": {
    "addr:full":"136 Waldron Rd Chester Hill NSW 2162",
    "addr:housenumber":"136",
    "addr:postcode":"2162",
    "addr:street":"Waldron Rd",
    "iso:country":"AU",
    "sg:address":"136 Waldron Rd",
    "sg:city":"Chester Hill",
    "sg:classifiers":[
        {
            "category":"Communications",
            "subcategory":"Film & Video Production",
            "type":"Services"
        }
    ],
    "sg:phone":"+61 2 9645 5279",
    "sg:postcode":"2162",
    "sg:province":"NSW",
    "sg:tags":[
        "dvd",
        "library"
    ],
    "wof:name":"Family Land",
    "wof:placetype":"venue"
},
  "geometry": {"coordinates":[151.00148010300001,-33.8830375671],"type":"Point"}
}