{
  "type": "Feature",
  "properties": {
    "addr:full":"10 Furlong Crt Endeavour Hills VIC 3802",
    "addr:housenumber":"10",
    "addr:postcode":"3802",
    "addr:street":"Furlong Crt",
    "iso:country":"AU",
    "sg:address":"10 Furlong Crt",
    "sg:city":"Endeavour Hills",
    "sg:classifiers":[
        {
            "category":"Home & Garden",
            "subcategory":"Building Materials",
            "type":"Retail Goods"
        }
    ],
    "sg:phone":"+61 411 484 846",
    "sg:postcode":"3802",
    "sg:province":"VIC",
    "sg:tags":[
        "lawn",
        "cutting",
        "maintenance"
    ],
    "wof:name":"Brighter Gardens",
    "wof:placetype":"venue"
},
  "geometry": {"coordinates":[145.27331543,-37.9685134888],"type":"Point"}
}