{
  "type": "Feature",
  "properties": {
    "iso:country":"AU",
    "sg:address":"5 Harvey St",
    "sg:city":"Port Broughton",
    "sg:classifiers":[
        {
            "category":"Real Estate",
            "subcategory":"Real Estate Agent",
            "type":"Services"
        }
    ],
    "sg:phone":"+61 8 8635 3038",
    "sg:postcode":"5522",
    "sg:province":"SA",
    "wof:name":"Professionals Port Broughton",
    "wof:placetype":"venue"
},
  "geometry": {"coordinates":[137.93205261200001,-33.5969276428],"type":"Point"}
}