{
  "type": "Feature",
  "properties": {
    "addr:full":"3 Well St Brighton VIC 3186",
    "addr:housenumber":"3",
    "addr:postcode":"3186",
    "addr:street":"Well St",
    "iso:country":"AU",
    "sg:address":"3 Well St",
    "sg:city":"Brighton",
    "sg:classifiers":[
        {
            "category":"Fast Food",
            "type":"Food & Drink"
        }
    ],
    "sg:phone":"+61 3 9592 6000",
    "sg:postcode":"3186",
    "sg:province":"VIC",
    "sg:tags":[
        "away",
        "take"
    ],
    "wof:name":"La Porchetta",
    "wof:placetype":"venue"
},
  "geometry": {"coordinates":[144.9921875,-37.9134521484],"type":"Point"}
}