{
  "type": "Feature",
  "properties": {
    "addr:full":"Cnr Woodrow & Queensbury Sts Bunbury WA 6230",
    "addr:postcode":"6230",
    "addr:street":"Cnr Woodrow & Queensbury Sts",
    "iso:country":"AU",
    "sg:address":"Cnr Woodrow & Queensbury Sts",
    "sg:city":"Bunbury",
    "sg:classifiers":[
        {
            "category":"Recreation",
            "type":"Entertainment"
        }
    ],
    "sg:phone":"+61 8 9791 2500",
    "sg:postcode":"6230",
    "sg:province":"WA",
    "sg:tags":[
        "children's",
        "play",
        "programme"
    ],
    "wof:name":"Munchkin Manor Child Care Centre",
    "wof:placetype":"venue"
},
  "geometry": {"coordinates":[115.650627,-33.349922],"type":"Point"}
}