{
  "type": "Feature",
  "properties": {
    "addr:full":"23 Spica St Coorparoo QLD 4151",
    "addr:housenumber":"23",
    "addr:postcode":"4151",
    "addr:street":"Spica St",
    "iso:country":"AU",
    "sg:address":"23 Spica St",
    "sg:city":"Coorparoo",
    "sg:classifiers":[
        {
            "category":"Banks & Credit Unions",
            "subcategory":"Investment Brokerage",
            "type":"Services"
        }
    ],
    "sg:phone":"+61 7 3394 1829",
    "sg:postcode":"4151",
    "sg:province":"QLD",
    "sg:tags":[
        "share",
        "broker",
        "stock"
    ],
    "wof:name":"Evans Peter D",
    "wof:placetype":"venue"
},
  "geometry": {"coordinates":[153.07119750999999,-27.5030117035],"type":"Point"}
}