{
  "type": "Feature",
  "properties": {
    "addr:full":"64 Wills St Bendigo VIC 3550",
    "addr:housenumber":"64",
    "addr:postcode":"3550",
    "addr:street":"Wills St",
    "iso:country":"AU",
    "sg:address":"64 Wills St",
    "sg:city":"Bendigo",
    "sg:classifiers":[
        {
            "category":"Professional",
            "subcategory":"Accounting & Tax Preparation",
            "type":"Services"
        }
    ],
    "sg:phone":"+61 3 5442 5650",
    "sg:postcode":"3550",
    "sg:province":"VIC",
    "sg:tags":[
        "consultant",
        "taxation"
    ],
    "wof:name":"McConnachie Paul",
    "wof:placetype":"venue"
},
  "geometry": {"coordinates":[144.27859497099999,-36.7647209167],"type":"Point"}
}