{
  "type": "Feature",
  "properties": {
    "addr:full":"37 Beverage Drv Tullamarine VIC 3043",
    "addr:postcode":"3043",
    "addr:street":"Beverage Drv",
    "iso:country":"AU",
    "sg:address":"37 Beverage Drv",
    "sg:city":"Tullamarine",
    "sg:classifiers":[
        {
            "category":"Fast Food",
            "type":"Food & Drink"
        }
    ],
    "sg:phone":"+61 3 9338 0816",
    "sg:postcode":"3043",
    "sg:province":"VIC",
    "sg:tags":[
        "away",
        "take"
    ],
    "wof:name":"Cafe on Beverage",
    "wof:placetype":"venue"
},
  "geometry": {"coordinates":[144.86468505900001,-37.7191925049],"type":"Point"}
}