{
  "type": "Feature",
  "properties": {
    "addr:full":"272 Nutt Rd Londonderry NSW 2753",
    "addr:housenumber":"272",
    "addr:postcode":"2753",
    "addr:street":"Nutt Rd",
    "iso:country":"AU",
    "sg:address":"272 Nutt Rd",
    "sg:city":"Londonderry",
    "sg:classifiers":[
        {
            "category":"Building & Trades",
            "subcategory":"Construction",
            "type":"Services"
        }
    ],
    "sg:phone":"+61 2 4777 5244",
    "sg:postcode":"2753",
    "sg:province":"NSW",
    "sg:tags":[
        "earth",
        "excavating",
        "moving",
        "contractor"
    ],
    "wof:name":"Gemhawk Pty Ltd",
    "wof:placetype":"venue"
},
  "geometry": {"coordinates":[150.72088623100001,-33.6615867615],"type":"Point"}
}