{
  "type": "Feature",
  "properties": {
    "addr:full":"62 Plateau Rd Reservoir VIC 3073",
    "addr:housenumber":"62",
    "addr:postcode":"3073",
    "addr:street":"Plateau Rd",
    "iso:country":"AU",
    "sg:address":"62 Plateau Rd",
    "sg:city":"Reservoir",
    "sg:classifiers":[
        {
            "category":"Building & Trades",
            "subcategory":"Construction",
            "type":"Services"
        }
    ],
    "sg:phone":"+61 3 9462 3535",
    "sg:postcode":"3073",
    "sg:province":"VIC",
    "sg:tags":[
        "window",
        "timber"
    ],
    "wof:name":"Five Seasons Windows",
    "wof:placetype":"venue"
},
  "geometry": {"coordinates":[144.98663330100001,-37.7088851929],"type":"Point"}
}