{
  "type": "Feature",
  "properties": {
    "iso:country":"AU",
    "sg:address":"Holy Spirit, Northside, 627",
    "sg:city":"Rode Rd, Chermside",
    "sg:classifiers":[
        {
            "category":"Health Services",
            "subcategory":"Doctor",
            "type":"Services"
        }
    ],
    "sg:phone":"+61 7 3883 3772",
    "sg:postcode":"4032",
    "sg:province":"QLD",
    "sg:tags":[
        "medical",
        "practitioner"
    ],
    "wof:name":"Yaxley John",
    "wof:placetype":"venue"
},
  "geometry": {"coordinates":[153.020187,-27.392399],"type":"Point"}
}