{
  "type": "Feature",
  "properties": {
    "addr:full":"98 Maude St Shepparton VIC 3630",
    "addr:housenumber":"98",
    "addr:postcode":"3630",
    "addr:street":"Maude St",
    "iso:country":"AU",
    "sg:address":"98 Maude St",
    "sg:city":"Shepparton",
    "sg:classifiers":[
        {
            "category":"Health Services",
            "subcategory":"Optometrist",
            "type":"Services"
        }
    ],
    "sg:phone":"+61 3 5821 2811",
    "sg:postcode":"3630",
    "sg:province":"VIC",
    "wof:name":"Nguyen Thao",
    "wof:placetype":"venue"
},
  "geometry": {"coordinates":[145.40170288100001,-36.3758888245],"type":"Point"}
}