{
  "type": "Feature",
  "properties": {
    "iso:country":"AU",
    "sg:address":"238 Brunswick St",
    "sg:city":"Fitzroy",
    "sg:classifiers":[
        {
            "category":"Personal",
            "subcategory":"Beauty Salon",
            "type":"Services"
        }
    ],
    "sg:phone":"+61 3 9415 6665",
    "sg:postcode":"3065",
    "sg:province":"VIC",
    "sg:tags":[
        "hairdresser"
    ],
    "wof:name":"BDH",
    "wof:placetype":"venue"
},
  "geometry": {"coordinates":[144.97828674300001,-37.8002433777],"type":"Point"}
}