{
  "type": "Feature",
  "properties": {
    "addr:full":"54- 62 Anomaly St Moolap VIC 3221",
    "addr:housenumber":"62",
    "addr:postcode":"3221",
    "addr:street":"Anomaly St",
    "iso:country":"AU",
    "sg:address":"54- 62 Anomaly St",
    "sg:city":"Moolap",
    "sg:classifiers":[
        {
            "category":"Farming",
            "subcategory":"Fish & Marine Products",
            "type":"Manufacturing & Wholesale Goods"
        }
    ],
    "sg:phone":"+61 407 345 970",
    "sg:postcode":"3221",
    "sg:province":"VIC",
    "sg:tags":[
        "equipment",
        "salvage"
    ],
    "wof:name":"Grant Rochow Marine Services Charter & Brokerage",
    "wof:placetype":"venue"
},
  "geometry": {"coordinates":[144.411835,-38.16824],"type":"Point"}
}