{
  "type": "Feature",
  "properties": {
    "iso:country":"AU",
    "sg:address":"58832 Bruce Hwy",
    "sg:city":"Silky Oak",
    "sg:classifiers":[
        {
            "category":"Building & Trades",
            "subcategory":"Construction",
            "type":"Services"
        }
    ],
    "sg:phone":"+61 7 4066 9248",
    "sg:postcode":"4854",
    "sg:province":"QLD",
    "sg:tags":[
        "earth",
        "excavating",
        "moving",
        "contractor"
    ],
    "wof:name":"Evans J W & J F",
    "wof:placetype":"venue"
},
  "geometry": {"coordinates":[145.94483947800001,-17.9720954895],"type":"Point"}
}