{
  "type": "Feature",
  "properties": {
    "addr:full":"Women&#039;s and Children&#039;s Hospital 72 King North Adelaide SA 5006",
    "addr:housenumber":"72",
    "addr:postcode":"5006",
    "addr:street":"S;S;King",
    "iso:country":"AU",
    "sg:address":"Women&#039;s and Children&#039;s Hospital 72 King",
    "sg:city":"North Adelaide",
    "sg:classifiers":[
        {
            "category":"Health Services",
            "subcategory":"Doctor",
            "type":"Services"
        }
    ],
    "sg:phone":"+61 8 8161 7261",
    "sg:postcode":"5006",
    "sg:province":"SA",
    "sg:tags":[
        "medical",
        "practitioner"
    ],
    "wof:name":"Knight Brodie",
    "wof:placetype":"venue"
},
  "geometry": {"coordinates":[138.598876953,-34.9107933044],"type":"Point"}
}