{
  "type": "Feature",
  "properties": {
    "iso:country":"AU",
    "sg:address":"Shp 2/ 66 Brice Ave",
    "sg:city":"Mooroolbark",
    "sg:classifiers":[
        {
            "category":"Personal",
            "subcategory":"Beauty Salon",
            "type":"Services"
        }
    ],
    "sg:phone":"+61 3 9726 8891",
    "sg:postcode":"3138",
    "sg:province":"VIC",
    "sg:tags":[
        "hairdresser"
    ],
    "wof:name":"Rage Hair & Supplies",
    "wof:placetype":"venue"
},
  "geometry": {"coordinates":[145.31199645999999,-37.7852783203],"type":"Point"}
}