{
  "type": "Feature",
  "properties": {
    "addr:full":"Greensborough Plaza Food Court 25 Main St Greensborough VIC 3088",
    "addr:housenumber":"25",
    "addr:postcode":"3088",
    "addr:street":"Main St",
    "iso:country":"AU",
    "sg:address":"Greensborough Plaza Food Court 25 Main St",
    "sg:city":"Greensborough",
    "sg:classifiers":[
        {
            "category":"Fast Food",
            "type":"Food & Drink"
        }
    ],
    "sg:phone":"+61 3 9432 8017",
    "sg:postcode":"3088",
    "sg:province":"VIC",
    "sg:tags":[
        "away",
        "take"
    ],
    "wof:name":"Red Rooster",
    "wof:placetype":"venue"
},
  "geometry": {"coordinates":[145.103393555,-37.7037506104],"type":"Point"}
}