{
  "type": "Feature",
  "properties": {
    "addr:full":"80 Binburra Ave Avalon NSW 2107",
    "addr:housenumber":"80",
    "addr:postcode":"2107",
    "addr:street":"Binburra Ave",
    "iso:country":"AU",
    "sg:address":"80 Binburra Ave",
    "sg:city":"Avalon",
    "sg:classifiers":[
        {
            "category":"Building & Trades",
            "subcategory":"Construction",
            "type":"Services"
        }
    ],
    "sg:phone":"+61 2 9918 0267",
    "sg:postcode":"2107",
    "sg:province":"NSW",
    "sg:tags":[
        "fencing",
        "contractor"
    ],
    "wof:name":"Boler Paul Fencing",
    "wof:placetype":"venue"
},
  "geometry": {"coordinates":[151.339019775,-33.6240501404],"type":"Point"}
}