{
  "type": "Feature",
  "properties": {
    "iso:country":"AU",
    "sg:address":"36- 38 Chickerell St",
    "sg:city":"Morwell",
    "sg:classifiers":[
        {
            "category":"Industrial Area",
            "type":"Public Place"
        }
    ],
    "sg:phone":"+61 3 5134 4100",
    "sg:postcode":"3840",
    "sg:province":"VIC",
    "sg:tags":[
        "rural",
        "shed"
    ],
    "wof:name":"EJ Steel Pty. Ltd.",
    "wof:placetype":"venue"
},
  "geometry": {"coordinates":[146.43655395499999,-38.2318840027],"type":"Point"}
}