{
  "type": "Feature",
  "properties": {
    "iso:country":"AU",
    "sg:address":"21 Meadow Park Drv",
    "sg:city":"Traralgon",
    "sg:classifiers":[
        {
            "category":"Building & Trades",
            "subcategory":"Cleaning & Sanitation",
            "type":"Services"
        }
    ],
    "sg:phone":"+61 3 5176 2295",
    "sg:postcode":"3844",
    "sg:province":"VIC",
    "sg:tags":[
        "industrial",
        "commercial",
        "contractor"
    ],
    "wof:name":"Revive Cleaning And Maintenance",
    "wof:placetype":"venue"
},
  "geometry": {"coordinates":[146.514328003,-38.1872367859],"type":"Point"}
}