{
  "type": "Feature",
  "properties": {
    "iso:country":"AU",
    "sg:address":"9 Observatory Rd",
    "sg:city":"Mt Dandenong",
    "sg:classifiers":[
        {
            "category":"Building & Trades",
            "subcategory":"Pest Control",
            "type":"Services"
        }
    ],
    "sg:phone":"+61 3 9751 1555",
    "sg:postcode":"3767",
    "sg:province":"VIC",
    "sg:tags":[
        "equipment",
        "abattoir",
        "machinery"
    ],
    "wof:name":"Kentmaster Equipment (Aust) Pty Ltd",
    "wof:placetype":"venue"
},
  "geometry": {"coordinates":[145.35252380399999,-37.8303642273],"type":"Point"}
}