{
  "type": "Feature",
  "properties": {
    "iso:country":"AU",
    "sg:address":"2 Spring St",
    "sg:city":"Burnie",
    "sg:classifiers":[
        {
            "category":"Professional",
            "subcategory":"Business Services",
            "type":"Services"
        }
    ],
    "sg:phone":"+61 3 6431 6118",
    "sg:postcode":"7320",
    "sg:province":"TAS",
    "sg:tags":[
        "small",
        "advisory"
    ],
    "wof:name":"Portside Small Business Incubator",
    "wof:placetype":"venue"
},
  "geometry": {"coordinates":[145.906754,-41.055954],"type":"Point"}
}