{
  "type": "Feature",
  "properties": {
    "addr:full":"Unit 1 Block Q Regents Park Estate Princes Rd Regents Park NSW 2143",
    "addr:postcode":"2143",
    "addr:street":"Princes Rd",
    "iso:country":"AU",
    "sg:address":"Unit 1 Block Q Regents Park Estate Princes Rd",
    "sg:city":"Regents Park",
    "sg:classifiers":[
        {
            "category":"Wholesale",
            "subcategory":"Vending Machines",
            "type":"Manufacturing & Wholesale Goods"
        }
    ],
    "sg:phone":"+61 1800 422 402",
    "sg:postcode":"2143",
    "sg:province":"NSW",
    "sg:tags":[
        "equipment",
        "mailing"
    ],
    "wof:name":"Fordigraph",
    "wof:placetype":"venue"
},
  "geometry": {"coordinates":[151.02441406200001,-33.8764381409],"type":"Point"}
}