{
  "type": "Feature",
  "properties": {
    "addr:full":"7 Pamela Pl Ringwood North VIC 3134",
    "addr:housenumber":"7",
    "addr:postcode":"3134",
    "addr:street":"Pamela Pl",
    "iso:country":"AU",
    "sg:address":"7 Pamela Pl",
    "sg:city":"Ringwood North",
    "sg:classifiers":[
        {
            "category":"Building & Trades",
            "subcategory":"Construction",
            "type":"Services"
        }
    ],
    "sg:phone":"+61 3 9720 0143",
    "sg:postcode":"3134",
    "sg:province":"VIC",
    "sg:tags":[
        "plasterboard",
        "plasterer",
        "fixer"
    ],
    "wof:name":"Glenndale Plaster",
    "wof:placetype":"venue"
},
  "geometry": {"coordinates":[145.22259521500001,-37.7973709106],"type":"Point"}
}