{
  "type": "Feature",
  "properties": {
    "iso:country":"AU",
    "sg:address":"9 Colin St",
    "sg:city":"West Perth",
    "sg:classifiers":[
        {
            "category":"Health Services",
            "subcategory":"Chiropractor",
            "type":"Services"
        }
    ],
    "sg:phone":"+61 8 9321 1964",
    "sg:postcode":"6005",
    "sg:province":"WA",
    "wof:name":"Brodie Neil C",
    "wof:placetype":"venue"
},
  "geometry": {"coordinates":[115.84058380099999,-31.9518661499],"type":"Point"}
}