{
  "type": "Feature",
  "properties": {
    "iso:country":"AU",
    "sg:address":"5 Leanne Crt",
    "sg:city":"Highfields",
    "sg:classifiers":[
        {
            "category":"Building & Trades",
            "subcategory":"Cleaning & Sanitation",
            "type":"Services"
        }
    ],
    "sg:phone":"+61 7 4630 8746",
    "sg:postcode":"4352",
    "sg:province":"QLD",
    "sg:tags":[
        "window"
    ],
    "wof:name":"Clean &#039;N&#039; Gleam",
    "wof:placetype":"venue"
},
  "geometry": {"coordinates":[151.95387299999999,-27.446985],"type":"Point"}
}