{
  "type": "Feature",
  "properties": {
    "addr:full":"10 Sadean Pl Grovedale VIC 3216",
    "addr:housenumber":"10",
    "addr:postcode":"3216",
    "addr:street":"Sadean Pl",
    "iso:country":"AU",
    "sg:address":"10 Sadean Pl",
    "sg:city":"Grovedale",
    "sg:classifiers":[
        {
            "category":"Building & Trades",
            "subcategory":"Plumbing",
            "type":"Services"
        }
    ],
    "sg:phone":"+61 438 433 482",
    "sg:postcode":"3216",
    "sg:province":"VIC",
    "sg:tags":[
        "plumber",
        "gasfitters"
    ],
    "wof:name":"On Tap Plumbing",
    "wof:placetype":"venue"
},
  "geometry": {"coordinates":[144.35542297399999,-38.1969223022],"type":"Point"}
}