{
  "type": "Feature",
  "properties": {
    "iso:country":"AU",
    "sg:address":"7 Neerim Crs",
    "sg:city":"Wendouree",
    "sg:classifiers":[
        {
            "category":"Manufacturing",
            "subcategory":"Metals",
            "type":"Manufacturing & Wholesale Goods"
        }
    ],
    "sg:phone":"+61 3 5339 6333",
    "sg:postcode":"3355",
    "sg:province":"VIC",
    "sg:tags":[
        "cutting"
    ],
    "wof:name":"Balray Manufacturing Pty Ltd",
    "wof:placetype":"venue"
},
  "geometry": {"coordinates":[143.823654,-37.531689],"type":"Point"}
}