{
  "type": "Feature",
  "properties": {
    "addr:full":"Shop 23, Grand Plaza Browns Plains Rd Browns Plains QLD 4118",
    "addr:housenumber":"shop 23",
    "addr:postcode":"4118",
    "addr:street":"Grand Plaza Browns Plains Rd",
    "iso:country":"AU",
    "sg:address":"Shop 23, Grand Plaza Browns Plains Rd",
    "sg:city":"Browns Plains",
    "sg:classifiers":[
        {
            "category":"Shopping",
            "subcategory":"Shoes",
            "type":"Retail Goods"
        }
    ],
    "sg:phone":"+61 7 3800 7477",
    "sg:postcode":"4118",
    "sg:province":"QLD",
    "sg:tags":[
        "footwear"
    ],
    "wof:name":"Colorado",
    "wof:placetype":"venue"
},
  "geometry": {"coordinates":[153.055145264,-27.6627578735],"type":"Point"}
}