{
  "type": "Feature",
  "properties": {
    "iso:country":"AU",
    "sg:address":"7 Crawford Rd",
    "sg:city":"Brighton-le-Sands",
    "sg:classifiers":[
        {
            "category":"Social Services",
            "subcategory":"Child Care",
            "type":"Services"
        }
    ],
    "sg:phone":"+61 2 9599 0999",
    "sg:postcode":"2216",
    "sg:province":"NSW",
    "wof:name":"Babyccino Long Day Centre",
    "wof:placetype":"venue"
},
  "geometry": {"coordinates":[151.151978,-33.959698],"type":"Point"}
}