{
  "type": "Feature",
  "properties": {
    "iso:country":"AU",
    "sg:address":"Cnr Market & Kembla Sts",
    "sg:city":"Wollongong",
    "sg:classifiers":[
        {
            "category":"Parking",
            "type":"Transportation"
        }
    ],
    "sg:phone":"+61 2 4229 4044",
    "sg:postcode":"2521",
    "sg:province":"NSW",
    "wof:name":"Kings Parking",
    "wof:placetype":"venue"
},
  "geometry": {"coordinates":[150.87223815900001,-34.4146308899],"type":"Point"}
}