{
  "type": "Feature",
  "properties": {
    "iso:country":"AU",
    "sg:address":"1/282- 290 Forest Rd",
    "sg:city":"Hurstville",
    "sg:classifiers":[
        {
            "category":"Health Services",
            "subcategory":"Optometrist",
            "type":"Services"
        }
    ],
    "sg:phone":"+61 2 9580 5765",
    "sg:postcode":"2220",
    "sg:province":"NSW",
    "sg:website":"http://www.oaansw.com.au",
    "wof:name":"Kimber Optical",
    "wof:placetype":"venue"
},
  "geometry": {"coordinates":[151.10287475600001,-33.9667434692],"type":"Point"}
}