{
  "type": "Feature",
  "properties": {
    "addr:full":"222 Anakie Rd Bell Park VIC 3215",
    "addr:housenumber":"222",
    "addr:postcode":"3215",
    "addr:street":"Anakie Rd",
    "iso:country":"AU",
    "sg:address":"222 Anakie Rd",
    "sg:city":"Bell Park",
    "sg:classifiers":[
        {
            "category":"Food & Beverages",
            "subcategory":"Groceries & Convenience Stores",
            "type":"Retail Goods"
        }
    ],
    "sg:phone":"+61 3 5277 0007",
    "sg:postcode":"3215",
    "sg:province":"VIC",
    "wof:name":"Najda's Foodstore",
    "wof:placetype":"venue"
},
  "geometry": {"coordinates":[144.33433532699999,-38.0971832275],"type":"Point"}
}