{
  "type": "Feature",
  "properties": {
    "addr:full":"32 Bridge Rd Pooraka SA 5095",
    "addr:housenumber":"32",
    "addr:postcode":"5095",
    "addr:street":"Bridge Rd",
    "iso:country":"AU",
    "sg:address":"32 Bridge Rd",
    "sg:city":"Pooraka",
    "sg:classifiers":[
        {
            "category":"Home & Garden",
            "subcategory":"Carpets & Floor Coverings",
            "type":"Retail Goods"
        }
    ],
    "sg:phone":"+61 418 818 770",
    "sg:postcode":"5095",
    "sg:province":"SA",
    "sg:tags":[
        "tile",
        "wall",
        "layer"
    ],
    "wof:name":"A R & A G Tiling",
    "wof:placetype":"venue"
},
  "geometry": {"coordinates":[138.625854492,-34.8351554871],"type":"Point"}
}