{
  "type": "Feature",
  "properties": {
    "iso:country":"AU",
    "sg:address":"1875 The Northern Rd",
    "sg:city":"Luddenham",
    "sg:classifiers":[
        {
            "category":"Wholesale",
            "subcategory":"Farm Supplies",
            "type":"Manufacturing & Wholesale Goods"
        }
    ],
    "sg:phone":"+61 2 4773 3131",
    "sg:postcode":"2745",
    "sg:province":"NSW",
    "sg:tags":[
        "feed",
        "supplement",
        "stock"
    ],
    "wof:name":"TDP Produce",
    "wof:placetype":"venue"
},
  "geometry": {"coordinates":[150.689331055,-33.8778076172],"type":"Point"}
}