{
  "type": "Feature",
  "properties": {
    "addr:full":"6 Birch Crt Tewantin QLD 4565",
    "addr:housenumber":"6",
    "addr:postcode":"4565",
    "addr:street":"Birch Crt",
    "iso:country":"AU",
    "sg:address":"6 Birch Crt",
    "sg:city":"Tewantin",
    "sg:classifiers":[
        {
            "category":"Mining & Drilling",
            "type":"Manufacturing & Wholesale Goods"
        }
    ],
    "sg:phone":"+61 7 5455 6977",
    "sg:postcode":"4565",
    "sg:province":"QLD",
    "sg:tags":[
        "geologist"
    ],
    "wof:name":"Coal Search Consultants",
    "wof:placetype":"venue"
},
  "geometry": {"coordinates":[153.02461242699999,-26.3993625641],"type":"Point"}
}