{
  "type": "Feature",
  "properties": {
    "iso:country":"AU",
    "sg:address":"407 Mt Alexander Rd",
    "sg:city":"Ascot Vale",
    "sg:classifiers":[
        {
            "category":"Shopping",
            "subcategory":"Bridal",
            "type":"Retail Goods"
        }
    ],
    "sg:phone":"+61 3 9372 7888",
    "sg:postcode":"3032",
    "sg:province":"VIC",
    "sg:tags":[
        "hire",
        "wear"
    ],
    "wof:name":"Suzanne Harward",
    "wof:placetype":"venue"
},
  "geometry": {"coordinates":[144.927521,-37.774269],"type":"Point"}
}