{
  "type": "Feature",
  "properties": {
    "iso:country":"AU",
    "sg:address":"26 Armstrong St",
    "sg:city":"West Wollongong",
    "sg:classifiers":[
        {
            "category":"Building & Trades",
            "subcategory":"Construction",
            "type":"Services"
        }
    ],
    "sg:phone":"+61 2 4228 7310",
    "sg:postcode":"2500",
    "sg:province":"NSW",
    "sg:tags":[
        "contractor"
    ],
    "wof:name":"Faulkner T & S",
    "wof:placetype":"venue"
},
  "geometry": {"coordinates":[150.865692,-34.420509],"type":"Point"}
}