{
  "type": "Feature",
  "properties": {
    "addr:full":"145 Commercial St West Mt Gambier SA 5290",
    "addr:housenumber":"145",
    "addr:postcode":"5290",
    "addr:street":"Commercial St West",
    "iso:country":"AU",
    "sg:address":"145 Commercial St West",
    "sg:city":"Mt Gambier",
    "sg:classifiers":[
        {
            "category":"Professional",
            "subcategory":"Detective & Security Services",
            "type":"Services"
        }
    ],
    "sg:phone":"+61 8 8723 9272",
    "sg:postcode":"5290",
    "sg:province":"SA",
    "sg:tags":[
        "consultant",
        "system"
    ],
    "wof:name":"Hills C.Q.Rity P/L",
    "wof:placetype":"venue"
},
  "geometry": {"coordinates":[140.774002,-37.826363],"type":"Point"}
}