{
  "type": "Feature",
  "properties": {
    "iso:country":"AU",
    "sg:address":"17 Arcadia Rd",
    "sg:city":"Galston",
    "sg:classifiers":[
        {
            "category":"Organizations",
            "subcategory":"Community Association",
            "type":"Services"
        }
    ],
    "sg:phone":"+61 2 9653 2313",
    "sg:postcode":"2159",
    "sg:province":"NSW",
    "sg:tags":[
        "organisation",
        "family",
        "welfare"
    ],
    "wof:name":"Neighbour Aid Galston & District",
    "wof:placetype":"venue"
},
  "geometry": {"coordinates":[151.04652404800001,-33.6510658264],"type":"Point"}
}