{
  "type": "Feature",
  "properties": {
    "addr:full":"23 Farview St Glenroy VIC 3046",
    "addr:housenumber":"23",
    "addr:postcode":"3046",
    "addr:street":"Farview St",
    "iso:country":"AU",
    "sg:address":"23 Farview St",
    "sg:city":"Glenroy",
    "sg:classifiers":[
        {
            "category":"Professional",
            "subcategory":"Accounting & Tax Preparation",
            "type":"Services"
        }
    ],
    "sg:phone":"+61 3 9306 8822",
    "sg:postcode":"3046",
    "sg:province":"VIC",
    "sg:tags":[
        "accountant",
        "auditor"
    ],
    "wof:name":"Rosegold Taxation & Accounting Services",
    "wof:placetype":"venue"
},
  "geometry": {"coordinates":[144.934524536,-37.7126846313],"type":"Point"}
}