{
  "type": "Feature",
  "properties": {
    "iso:country":"AU",
    "sg:address":"87 Levanswell Rd",
    "sg:city":"Moorabbin",
    "sg:classifiers":[
        {
            "category":"Autos & Motor Vehicles",
            "subcategory":"Automobile Sales",
            "type":"Retail Goods"
        }
    ],
    "sg:phone":"+61 3 9555 0657",
    "sg:postcode":"3189",
    "sg:province":"VIC",
    "sg:tags":[
        "equipment",
        "trailer"
    ],
    "wof:name":"Noble Trailers Pty Ltd",
    "wof:placetype":"venue"
},
  "geometry": {"coordinates":[145.07321167000001,-37.9456863403],"type":"Point"}
}