{
  "type": "Feature",
  "properties": {
    "addr:full":"320 Carlisle St Balaclava VIC 3183",
    "addr:housenumber":"320",
    "addr:postcode":"3183",
    "addr:street":"Carlisle St",
    "iso:country":"AU",
    "sg:address":"320 Carlisle St",
    "sg:city":"Balaclava",
    "sg:classifiers":[
        {
            "category":"Arena",
            "subcategory":"Sports Club",
            "type":"Entertainment"
        }
    ],
    "sg:phone":"+61 3 9824 5064",
    "sg:postcode":"3183",
    "sg:province":"VIC",
    "sg:tags":[
        "defence",
        "supply",
        "self",
        "instruction",
        "martial art"
    ],
    "wof:name":"Progressive Combat Science",
    "wof:placetype":"venue"
},
  "geometry": {"coordinates":[144.99528503400001,-37.8688278198],"type":"Point"}
}