{
  "type": "Feature",
  "properties": {
    "addr:full":"57 Pascoe Rd Ormeau QLD 4208",
    "addr:housenumber":"57",
    "addr:postcode":"4208",
    "addr:street":"Pascoe Rd",
    "iso:country":"AU",
    "sg:address":"57 Pascoe Rd",
    "sg:city":"Ormeau",
    "sg:classifiers":[
        {
            "category":"Building & Trades",
            "subcategory":"Construction",
            "type":"Services"
        }
    ],
    "sg:phone":"+61 7 5546 6788",
    "sg:postcode":"4208",
    "sg:province":"QLD",
    "sg:tags":[
        "contractor"
    ],
    "wof:name":"Heaton Industrial Holdings Pty Ltd",
    "wof:placetype":"venue"
},
  "geometry": {"coordinates":[153.23179626500001,-27.770160675],"type":"Point"}
}