{
  "type": "Feature",
  "properties": {
    "addr:full":"Risdon Rd Lutana TAS 7009",
    "addr:postcode":"7009",
    "addr:street":"Risdon Rd",
    "iso:country":"AU",
    "sg:address":"Risdon Rd",
    "sg:city":"Lutana",
    "sg:classifiers":[
        {
            "category":"Home & Garden",
            "subcategory":"Kitchen Supply",
            "type":"Retail Goods"
        }
    ],
    "sg:phone":"+61 3 6278 4444",
    "sg:postcode":"7009",
    "sg:province":"TAS",
    "sg:tags":[
        "product",
        "zinc"
    ],
    "wof:name":"Zinifex Hobart Smelter",
    "wof:placetype":"venue"
},
  "geometry": {"coordinates":[147.314254761,-42.8453445435],"type":"Point"}
}