{
  "type": "Feature",
  "properties": {
    "iso:country":"AU",
    "sg:address":"1/ 60 McIvor Rd",
    "sg:city":"Bendigo",
    "sg:classifiers":[
        {
            "category":"Building & Trades",
            "subcategory":"Landscaping Services",
            "type":"Services"
        }
    ],
    "sg:phone":"+61 3 5441 4149",
    "sg:postcode":"3550",
    "sg:province":"VIC",
    "sg:tags":[
        "consultant"
    ],
    "wof:name":"Building Issues",
    "wof:placetype":"venue"
},
  "geometry": {"coordinates":[144.29377746599999,-36.7577667236],"type":"Point"}
}