{
  "type": "Feature",
  "properties": {
    "addr:full":"PO Box 257 Cannington WA 6107",
    "addr:postcode":"6107",
    "iso:country":"AU",
    "sg:address":"PO Box 257",
    "sg:city":"Cannington",
    "sg:classifiers":[
        {
            "category":"Utilities",
            "subcategory":"Electric",
            "type":"Services"
        }
    ],
    "sg:phone":"+61 418 941 849",
    "sg:postcode":"6107",
    "sg:province":"WA",
    "sg:tags":[
        "electrical",
        "contractor"
    ],
    "wof:name":"SJR Electrical Services",
    "wof:placetype":"venue"
},
  "geometry": {"coordinates":[115.933868408,-32.0152893066],"type":"Point"}
}