{
  "type": "Feature",
  "properties": {
    "iso:country":"AU",
    "sg:address":"50 Fullarton Rd",
    "sg:city":"Norwood",
    "sg:classifiers":[
        {
            "category":"Insurance",
            "subcategory":"Insurance Agent",
            "type":"Services"
        }
    ],
    "sg:phone":"+61 8 8362 6411",
    "sg:postcode":"5067",
    "sg:province":"SA",
    "wof:name":"Murdock Andrew Financial Services Pty Ltd",
    "wof:placetype":"venue"
},
  "geometry": {"coordinates":[138.62327575699999,-34.9201889038],"type":"Point"}
}