{
  "type": "Feature",
  "properties": {
    "addr:full":"Catalonia St Cervantes WA 6511",
    "addr:postcode":"6511",
    "addr:street":"Catalonia St",
    "iso:country":"AU",
    "sg:address":"Catalonia St",
    "sg:city":"Cervantes",
    "sg:classifiers":[
        {
            "category":"Manufacturing",
            "subcategory":"Tools & Machinery",
            "type":"Manufacturing & Wholesale Goods"
        }
    ],
    "sg:phone":"+61 8 9652 7018",
    "sg:postcode":"6511",
    "sg:province":"WA",
    "sg:tags":[
        "earth",
        "excavating",
        "moving",
        "equipment"
    ],
    "wof:name":"Cervantes Earthworks",
    "wof:placetype":"venue"
},
  "geometry": {"coordinates":[115.073662,-30.502689],"type":"Point"}
}