{
  "type": "Feature",
  "properties": {
    "iso:country":"AU",
    "sg:address":"337 Hampton St",
    "sg:city":"Hampton",
    "sg:classifiers":[
        {
            "category":"Shopping",
            "subcategory":"Clothing, Apparel, & Fashions",
            "type":"Retail Goods"
        }
    ],
    "sg:phone":"+61 3 9598 2089",
    "sg:postcode":"3188",
    "sg:province":"VIC",
    "sg:tags":[
        "menswear"
    ],
    "wof:name":"Coachman Menswear",
    "wof:placetype":"venue"
},
  "geometry": {"coordinates":[145.00230407699999,-37.9376373291],"type":"Point"}
}