{
  "type": "Feature",
  "properties": {
    "addr:full":"Shop 2, 22 Charles St Adelaide SA 5000",
    "addr:housenumber":"shop;22",
    "addr:postcode":"5000",
    "addr:street":"Charles St",
    "iso:country":"AU",
    "sg:address":"Shop 2, 22 Charles St",
    "sg:city":"Adelaide",
    "sg:classifiers":[
        {
            "category":"Ice Cream",
            "type":"Food & Drink"
        }
    ],
    "sg:phone":"+61 8 8232 0336",
    "sg:postcode":"5000",
    "sg:province":"SA",
    "sg:tags":[
        "specialised",
        "fitting",
        "lady",
        "wear"
    ],
    "wof:name":"Dressing Station",
    "wof:placetype":"venue"
},
  "geometry": {"coordinates":[138.60354614299999,-34.9225502014],"type":"Point"}
}