{
  "type": "Feature",
  "properties": {
    "iso:country":"AU",
    "sg:address":"Cnr Bruce Hwy & Heaths Rd",
    "sg:city":"Mt Pleasant",
    "sg:classifiers":[
        {
            "category":"Wholesale",
            "subcategory":"Music Publishers",
            "type":"Manufacturing & Wholesale Goods"
        }
    ],
    "sg:phone":"+61 13 28 38",
    "sg:postcode":"4740",
    "sg:province":"QLD",
    "sg:tags":[
        "wholesaler",
        "dvd",
        "mfrs",
        "cd"
    ],
    "wof:name":"Wow Sight & Sound",
    "wof:placetype":"venue"
},
  "geometry": {"coordinates":[149.154694,-21.120399],"type":"Point"}
}