{
  "type": "Feature",
  "properties": {
    "addr:full":"3/ 5 Burgess Rd Bayswater VIC 3153",
    "addr:housenumber":"/ 5",
    "addr:postcode":"3153",
    "addr:street":"Burgess Rd",
    "iso:country":"AU",
    "sg:address":"3/ 5 Burgess Rd",
    "sg:city":"Bayswater",
    "sg:classifiers":[
        {
            "category":"Health Services",
            "subcategory":"Nursing And Care Facility",
            "type":"Services"
        }
    ],
    "sg:phone":"+61 3 9761 4498",
    "sg:postcode":"3153",
    "sg:province":"VIC",
    "sg:tags":[
        "treatment",
        "preservation",
        "timber"
    ],
    "wof:name":"Timber Coatings Australia",
    "wof:placetype":"venue"
},
  "geometry": {"coordinates":[145.28825378400001,-37.8222885132],"type":"Point"}
}