{
  "type": "Feature",
  "properties": {
    "addr:full":"136 Victoria Rd Marrickville NSW 2204",
    "addr:housenumber":"136",
    "addr:postcode":"2204",
    "addr:street":"Victoria Rd",
    "iso:country":"AU",
    "sg:address":"136 Victoria Rd",
    "sg:city":"Marrickville",
    "sg:classifiers":[
        {
            "category":"Building & Trades",
            "subcategory":"Construction",
            "type":"Services"
        }
    ],
    "sg:phone":"+61 2 9310 2161",
    "sg:postcode":"2204",
    "sg:province":"NSW",
    "sg:tags":[
        "contractor"
    ],
    "wof:name":"Redwood Projects",
    "wof:placetype":"venue"
},
  "geometry": {"coordinates":[151.16482500000001,-33.906685],"type":"Point"}
}