{
  "type": "Feature",
  "properties": {
    "addr:full":"U 16/ 7 Delage St Joondalup WA 6027",
    "addr:housenumber":"16 / 7",
    "addr:postcode":"6027",
    "addr:street":"Delage St",
    "iso:country":"AU",
    "sg:address":"U 16/ 7 Delage St",
    "sg:city":"Joondalup",
    "sg:classifiers":[
        {
            "category":"Personal",
            "subcategory":"Adult",
            "type":"Services"
        }
    ],
    "sg:phone":"+61 8 9301 2356",
    "sg:postcode":"6027",
    "sg:province":"WA",
    "sg:tags":[
        "vic",
        "except",
        "state",
        "escort",
        "social",
        "qld"
    ],
    "wof:name":"Miss Ella Bella",
    "wof:placetype":"venue"
},
  "geometry": {"coordinates":[115.762702942,-31.7448863983],"type":"Point"}
}