{
  "type": "Feature",
  "properties": {
    "iso:country":"AU",
    "sg:address":"209 Doveton St",
    "sg:city":"Sth Ballarat",
    "sg:classifiers":[
        {
            "category":"Professional",
            "type":"Services"
        }
    ],
    "sg:phone":"+61 419 887 145",
    "sg:postcode":"3350",
    "sg:province":"VIC",
    "sg:tags":[
        "industrial",
        "commercial",
        "catering"
    ],
    "wof:name":"Graham Commercial Catering",
    "wof:placetype":"venue"
},
  "geometry": {"coordinates":[143.855713,-37.555794],"type":"Point"}
}