{
  "type": "Feature",
  "properties": {
    "addr:full":"209 Doveton St Sth Ballarat VIC 3350",
    "addr:housenumber":"209",
    "addr:postcode":"3350",
    "addr:street":"Doveton St Sth",
    "iso:country":"AU",
    "sg:address":"209 Doveton St",
    "sg:city":"Sth Ballarat",
    "sg:classifiers":[
        {
            "category":"Professional",
            "type":"Services"
        }
    ],
    "sg:phone":"+61 419 887 145",
    "sg:postcode":"3350",
    "sg:province":"VIC",
    "sg:tags":[
        "industrial",
        "commercial",
        "catering"
    ],
    "wof:name":"Graham Commercial Catering",
    "wof:placetype":"venue"
},
  "geometry": {"coordinates":[143.85571300000001,-37.555794],"type":"Point"}
}