{
  "type": "Feature",
  "properties": {
    "addr:full":"Cnr Antill And Cowper Street Dickson ACT 2602",
    "addr:postcode":"2602",
    "addr:street":"Cnr Antill;Cowper Street",
    "iso:country":"AU",
    "sg:address":"Cnr Antill And Cowper Street",
    "sg:city":"Dickson",
    "sg:classifiers":[
        {
            "category":"Health Services",
            "subcategory":"Health Practitioner",
            "type":"Services"
        }
    ],
    "sg:phone":"+61 2 6248 9841",
    "sg:postcode":"2602",
    "sg:province":"ACT",
    "sg:tags":[
        "physiotherapist"
    ],
    "wof:name":"Sportscare & Physiotherapy Dickson",
    "wof:placetype":"venue"
},
  "geometry": {"coordinates":[149.142974853,-35.2488517761],"type":"Point"}
}