{
  "type": "Feature",
  "properties": {
    "addr:full":"142 Main North Rd Prospect SA 5082",
    "addr:housenumber":"142",
    "addr:postcode":"5082",
    "addr:street":"Main North Rd",
    "iso:country":"AU",
    "sg:address":"142 Main North Rd",
    "sg:city":"Prospect",
    "sg:classifiers":[
        {
            "category":"Autos & Motor Vehicles",
            "subcategory":"Automobile Sales",
            "type":"Retail Goods"
        }
    ],
    "sg:phone":"+61 8 8343 1900",
    "sg:postcode":"5082",
    "sg:province":"SA",
    "sg:tags":[
        "car",
        "new"
    ],
    "wof:name":"Chrysler Aust",
    "wof:placetype":"venue"
},
  "geometry": {"coordinates":[138.60270690900001,-34.886592865],"type":"Point"}
}