{
  "type": "Feature",
  "properties": {
    "iso:country":"AU",
    "sg:address":"87 Lear Jet Drv",
    "sg:city":"Caboolture",
    "sg:classifiers":[
        {
            "category":"Manufacturing",
            "subcategory":"Buildings",
            "type":"Manufacturing & Wholesale Goods"
        }
    ],
    "sg:phone":"+61 7 5499 2160",
    "sg:postcode":"4510",
    "sg:province":"QLD",
    "sg:tags":[
        "transportable",
        "domestic",
        "relocatable"
    ],
    "sg:website":"http://www.wrightbros.com.au",
    "wof:name":"All About Homes",
    "wof:placetype":"venue"
},
  "geometry": {"coordinates":[152.979477,-27.079996],"type":"Point"}
}