{
  "type": "Feature",
  "properties": {
    "addr:full":"29 Grevillea Ave Warriewood NSW 2102",
    "addr:housenumber":"29",
    "addr:postcode":"2102",
    "addr:street":"Grevillea Ave",
    "iso:country":"AU",
    "sg:address":"29 Grevillea Ave",
    "sg:city":"Warriewood",
    "sg:classifiers":[
        {
            "category":"Building & Trades",
            "subcategory":"Cleaning & Sanitation",
            "type":"Services"
        }
    ],
    "sg:phone":"+61 2 9453 9143",
    "sg:postcode":"2102",
    "sg:province":"NSW",
    "sg:tags":[
        "commercial",
        "maintenance"
    ],
    "wof:name":"Grey Skills",
    "wof:placetype":"venue"
},
  "geometry": {"coordinates":[151.28787199999999,-33.690723],"type":"Point"}
}