{
  "type": "Feature",
  "properties": {
    "addr:full":"33 Redpath St Wishart QLD 4122",
    "addr:housenumber":"33",
    "addr:postcode":"4122",
    "addr:street":"Redpath St",
    "iso:country":"AU",
    "sg:address":"33 Redpath St",
    "sg:city":"Wishart",
    "sg:classifiers":[
        {
            "category":"Professional",
            "subcategory":"Art Services",
            "type":"Services"
        }
    ],
    "sg:phone":"+61 402 473 425",
    "sg:postcode":"4122",
    "sg:province":"QLD",
    "sg:tags":[
        "decorator",
        "painter"
    ],
    "wof:name":"Poulsen Painting",
    "wof:placetype":"venue"
},
  "geometry": {"coordinates":[153.110305786,-27.5512905121],"type":"Point"}
}