{
  "type": "Feature",
  "properties": {
    "addr:full":"Shp1/ 17 Lytton Rd East Brisbane QLD 4169",
    "addr:housenumber":"17",
    "addr:postcode":"4169",
    "addr:street":"Lytton Rd",
    "iso:country":"AU",
    "sg:address":"Shp1/ 17 Lytton Rd",
    "sg:city":"East Brisbane",
    "sg:classifiers":[
        {
            "category":"Personal",
            "subcategory":"Beauty Salon",
            "type":"Services"
        }
    ],
    "sg:phone":"+61 7 3891 2027",
    "sg:postcode":"4169",
    "sg:province":"QLD",
    "sg:tags":[
        "hairdresser"
    ],
    "wof:name":"Studio X-Pose",
    "wof:placetype":"venue"
},
  "geometry": {"coordinates":[153.04394531200001,-27.4793052673],"type":"Point"}
}