{
  "type": "Feature",
  "properties": {
    "addr:full":"35 Kent St Deakin ACT 2600",
    "addr:housenumber":"35",
    "addr:postcode":"2600",
    "addr:street":"Kent St Deakin",
    "iso:country":"AU",
    "sg:address":"35 Kent St",
    "sg:city":"Deakin",
    "sg:classifiers":[
        {
            "category":"Education",
            "subcategory":"Special Training",
            "type":"Public Place"
        }
    ],
    "sg:phone":"+61 2 6282 9977",
    "sg:postcode":"2600",
    "sg:province":"ACT",
    "sg:tags":[
        "instruction",
        "display",
        "parachuting"
    ],
    "wof:name":"Jump! Australia",
    "wof:placetype":"venue"
},
  "geometry": {"coordinates":[149.09843444800001,-35.3164825439],"type":"Point"}
}