{
  "type": "Feature",
  "properties": {
    "iso:country":"AU",
    "sg:address":"10 Yeates Rd",
    "sg:city":"Beerwah",
    "sg:classifiers":[
        {
            "category":"Building & Trades",
            "subcategory":"Construction",
            "type":"Services"
        }
    ],
    "sg:phone":"+61 7 5494 6794",
    "sg:postcode":"4519",
    "sg:province":"QLD",
    "sg:tags":[
        "contractor"
    ],
    "wof:name":"Hall & Sons",
    "wof:placetype":"venue"
},
  "geometry": {"coordinates":[152.923065,-26.867855],"type":"Point"}
}