{
  "type": "Feature",
  "properties": {
    "addr:full":"27 Watt St Newcastle NSW 2300",
    "addr:housenumber":"27",
    "addr:postcode":"2300",
    "addr:street":"Watt St",
    "iso:country":"AU",
    "sg:address":"27 Watt St",
    "sg:city":"Newcastle",
    "sg:classifiers":[
        {
            "category":"Structure",
            "subcategory":"Office Building",
            "type":"Public Place"
        }
    ],
    "sg:phone":"+61 2 4926 2281",
    "sg:postcode":"2300",
    "sg:province":"NSW",
    "sg:tags":[
        "serviced"
    ],
    "wof:name":"Mundana Office Properties Pty Ltd",
    "wof:placetype":"venue"
},
  "geometry": {"coordinates":[151.78436300000001,-32.928207],"type":"Point"}
}