{
  "type": "Feature",
  "properties": {
    "addr:full":"36 Merton St Albert Park VIC 3206",
    "addr:housenumber":"36",
    "addr:postcode":"3206",
    "addr:street":"Merton St",
    "iso:country":"AU",
    "sg:address":"36 Merton St",
    "sg:city":"Albert Park",
    "sg:classifiers":[
        {
            "category":"Building & Trades",
            "subcategory":"Construction",
            "type":"Services"
        }
    ],
    "sg:phone":"+61 417 377 426",
    "sg:postcode":"3206",
    "sg:province":"VIC",
    "sg:tags":[
        "repair",
        "maintenance",
        "contractor"
    ],
    "wof:name":"Cummings David & Associates",
    "wof:placetype":"venue"
},
  "geometry": {"coordinates":[144.95394899999999,-37.84227],"type":"Point"}
}