{
  "type": "Feature",
  "properties": {
    "iso:country":"AU",
    "sg:address":"151 Corio St",
    "sg:city":"Geelong",
    "sg:classifiers":[
        {
            "category":"Education",
            "subcategory":"Music School",
            "type":"Public Place"
        }
    ],
    "sg:phone":"+61 431 145 849",
    "sg:postcode":"3220",
    "sg:province":"VIC",
    "sg:tags":[
        "teacher"
    ],
    "wof:name":"Del Reis",
    "wof:placetype":"venue"
},
  "geometry": {"coordinates":[144.367645,-38.147888],"type":"Point"}
}