{
  "type": "Feature",
  "properties": {
    "addr:full":"302 Glenferrie Rd Malvern VIC 3144",
    "addr:housenumber":"302",
    "addr:postcode":"3144",
    "addr:street":"Glenferrie Rd",
    "iso:country":"AU",
    "sg:address":"302 Glenferrie Rd",
    "sg:city":"Malvern",
    "sg:classifiers":[
        {
            "category":"Health Services",
            "subcategory":"Doctor",
            "type":"Services"
        }
    ],
    "sg:phone":"+61 3 9822 9822",
    "sg:postcode":"3144",
    "sg:province":"VIC",
    "sg:tags":[
        "medical",
        "practitioner"
    ],
    "wof:name":"Carew-Reid Elizabeth",
    "wof:placetype":"venue"
},
  "geometry": {"coordinates":[145.02980041500001,-37.8543701172],"type":"Point"}
}