{
  "type": "Feature",
  "properties": {
    "addr:full":"141 Howard St Nambour QLD 4560",
    "addr:housenumber":"141",
    "addr:postcode":"4560",
    "addr:street":"Howard St",
    "iso:country":"AU",
    "sg:address":"141 Howard St",
    "sg:city":"Nambour",
    "sg:classifiers":[
        {
            "category":"Professional",
            "subcategory":"Engineering",
            "type":"Services"
        }
    ],
    "sg:phone":"+61 7 5441 7518",
    "sg:postcode":"4560",
    "sg:province":"QLD",
    "sg:tags":[
        "engineer",
        "mechanical"
    ],
    "wof:name":"Doolan Mike Auto Repairs",
    "wof:placetype":"venue"
},
  "geometry": {"coordinates":[152.966873169,-26.6261844635],"type":"Point"}
}