{
  "type": "Feature",
  "properties": {
    "iso:country":"AU",
    "sg:address":"121 Grenfell St",
    "sg:city":"Adelaide",
    "sg:classifiers":[
        {
            "category":"Sports & Exercise",
            "subcategory":"Ski Slope",
            "type":"Entertainment"
        }
    ],
    "sg:phone":"+61 8 8223 5505",
    "sg:postcode":"5000",
    "sg:province":"SA",
    "sg:tags":[
        "equipment",
        "hire",
        "retail",
        "snow"
    ],
    "wof:name":"JR's Surf & Ski",
    "wof:placetype":"venue"
},
  "geometry": {"coordinates":[138.60409545900001,-34.9243621826],"type":"Point"}
}