{
  "type": "Feature",
  "properties": {
    "iso:country":"AU",
    "sg:address":"45 Military Rd",
    "sg:city":"Avondale Heights",
    "sg:classifiers":[
        {
            "category":"Health Services",
            "subcategory":"Doctor",
            "type":"Services"
        }
    ],
    "sg:phone":"+61 3 9318 5320",
    "sg:postcode":"3034",
    "sg:province":"VIC",
    "sg:tags":[
        "podiatrist"
    ],
    "sg:website":"http://www.podiatryvic.com.au",
    "wof:name":"Alexandra Pugliesi Podiatry",
    "wof:placetype":"venue"
},
  "geometry": {"coordinates":[144.864594,-37.768593],"type":"Point"}
}