{
  "type": "Feature",
  "properties": {
    "iso:country":"AU",
    "sg:address":"61 Cobar St",
    "sg:city":"Nyngan",
    "sg:classifiers":[
        {
            "category":"Government",
            "subcategory":"Post Office",
            "type":"Public Place"
        }
    ],
    "sg:phone":"+61 2 6832 1260",
    "sg:postcode":"2825",
    "sg:province":"NSW",
    "sg:tags":[
        "postal"
    ],
    "wof:name":"Australia Post",
    "wof:placetype":"venue"
},
  "geometry": {"coordinates":[147.19252014200001,-31.562664032],"type":"Point"}
}