{
  "type": "Feature",
  "properties": {
    "addr:full":"Shop 21 Morayfield Shopping Centre Morayfield QLD 4506",
    "addr:housenumber":"shop 21",
    "addr:postcode":"4506",
    "addr:street":"Morayfield Shopping",
    "iso:country":"AU",
    "sg:address":"Shop 21 Morayfield Shopping Centre",
    "sg:city":"Morayfield",
    "sg:classifiers":[
        {
            "category":"Shopping",
            "subcategory":"Clothing, Apparel, & Fashions",
            "type":"Retail Goods"
        }
    ],
    "sg:phone":"+61 7 5499 3099",
    "sg:postcode":"4506",
    "sg:province":"QLD",
    "sg:tags":[
        "lady",
        "wear"
    ],
    "wof:name":"Suzanne Grae",
    "wof:placetype":"venue"
},
  "geometry": {"coordinates":[152.94937133799999,-27.1093521118],"type":"Point"}
}