{
  "type": "Feature",
  "properties": {
    "addr:full":"2 Madrid Crt Wishart QLD 4122",
    "addr:housenumber":"2",
    "addr:postcode":"4122",
    "addr:street":"Madrid Crt",
    "iso:country":"AU",
    "sg:address":"2 Madrid Crt",
    "sg:city":"Wishart",
    "sg:classifiers":[
        {
            "category":"Health Services",
            "subcategory":"Health Practitioner",
            "type":"Services"
        }
    ],
    "sg:phone":"+61 7 3420 4430",
    "sg:postcode":"4122",
    "sg:province":"QLD",
    "sg:tags":[
        "pathologist",
        "speech"
    ],
    "wof:name":"Talking Results",
    "wof:placetype":"venue"
},
  "geometry": {"coordinates":[153.096237183,-27.5588245392],"type":"Point"}
}