{
  "type": "Feature",
  "properties": {
    "addr:full":"Cnr Boundary Rd & Tile St Wacol QLD 4076",
    "addr:postcode":"4076",
    "addr:street":"Cnr Boundary Rd & Tile St",
    "iso:country":"AU",
    "sg:address":"Cnr Boundary Rd & Tile St",
    "sg:city":"Wacol",
    "sg:classifiers":[
        {
            "category":"Shopping",
            "subcategory":"Bicycles & Sporting Goods",
            "type":"Retail Goods"
        }
    ],
    "sg:phone":"+61 7 3271 1935",
    "sg:postcode":"4076",
    "sg:province":"QLD",
    "sg:tags":[
        "dance",
        "accessory",
        "wear",
        "supply"
    ],
    "sg:website":"http://www.dancepacific.com",
    "wof:name":"Dance Pacific",
    "wof:placetype":"venue"
},
  "geometry": {"coordinates":[152.93244934099999,-27.6037902832],"type":"Point"}
}