{
  "type": "Feature",
  "properties": {
    "addr:full":"1777 Princes Hwy Johnsonville VIC 3902",
    "addr:housenumber":"1777",
    "addr:postcode":"3902",
    "addr:street":"Princes Hwy",
    "iso:country":"AU",
    "sg:address":"1777 Princes Hwy",
    "sg:city":"Johnsonville",
    "sg:classifiers":[
        {
            "category":"Manufacturing",
            "subcategory":"Motor Vehicles & Parts",
            "type":"Manufacturing & Wholesale Goods"
        }
    ],
    "sg:phone":"+61 3 5156 4281",
    "sg:postcode":"3902",
    "sg:province":"VIC",
    "sg:tags":[
        "engine",
        "equipment",
        "diesel"
    ],
    "wof:name":"Bream Marine & Industrial",
    "wof:placetype":"venue"
},
  "geometry": {"coordinates":[147.83294677699999,-37.8202552795],"type":"Point"}
}