{
  "type": "Feature",
  "properties": {
    "iso:country":"AU",
    "sg:address":"114 Flagstaff Gully Rd",
    "sg:city":"Lindisfarne",
    "sg:classifiers":[
        {
            "category":"Communications",
            "subcategory":"News Services",
            "type":"Services"
        }
    ],
    "sg:phone":"+61 408 550 803",
    "sg:postcode":"7015",
    "sg:province":"TAS",
    "sg:tags":[
        "information",
        "tourist",
        "attractions"
    ],
    "wof:name":"Devilmania Tours & Charters",
    "wof:placetype":"venue"
},
  "geometry": {"coordinates":[147.37889099099999,-42.8540382385],"type":"Point"}
}