{
  "type": "Feature",
  "properties": {
    "addr:full":"26 Popes Rd Keysborough VIC 3173",
    "addr:housenumber":"26",
    "addr:postcode":"3173",
    "addr:street":"Popes Rd",
    "iso:country":"AU",
    "sg:address":"26 Popes Rd",
    "sg:city":"Keysborough",
    "sg:classifiers":[
        {
            "category":"Building & Trades",
            "subcategory":"Landscaping Services",
            "type":"Services"
        }
    ],
    "sg:phone":"+61 417 371 511",
    "sg:postcode":"3173",
    "sg:province":"VIC",
    "sg:tags":[
        "gardener"
    ],
    "wof:name":"Tony Di Iorio",
    "wof:placetype":"venue"
},
  "geometry": {"coordinates":[145.18754577600001,-37.9826011658],"type":"Point"}
}