{
  "type": "Feature",
  "properties": {
    "addr:full":"7 Vera St Murrumbeena VIC 3163",
    "addr:housenumber":"7",
    "addr:postcode":"3163",
    "addr:street":"Vera St",
    "iso:country":"AU",
    "sg:address":"7 Vera St",
    "sg:city":"Murrumbeena",
    "sg:classifiers":[
        {
            "category":"Home & Garden",
            "subcategory":"Building Materials",
            "type":"Retail Goods"
        }
    ],
    "sg:phone":"+61 3 9579 5134",
    "sg:postcode":"3163",
    "sg:province":"VIC",
    "sg:tags":[
        "lawn",
        "cutting",
        "maintenance"
    ],
    "wof:name":"Crosscut House and Garden",
    "wof:placetype":"venue"
},
  "geometry": {"coordinates":[145.07341003400001,-37.9043312073],"type":"Point"}
}