{
  "type": "Feature",
  "properties": {
    "iso:country":"AU",
    "sg:address":"241 Margaret St",
    "sg:city":"Toowoomba",
    "sg:classifiers":[
        {
            "category":"Professional",
            "subcategory":"Computer Services",
            "type":"Services"
        }
    ],
    "sg:phone":"+61 7 4659 9566",
    "sg:postcode":"4350",
    "sg:province":"QLD",
    "sg:tags":[
        "repairs",
        "upgrade",
        "equipment"
    ],
    "wof:name":"Meadow & Larson Computer Works",
    "wof:placetype":"venue"
},
  "geometry": {"coordinates":[151.95280500000001,-27.560787],"type":"Point"}
}