{
  "type": "Feature",
  "properties": {
    "addr:full":"Shop T15, Harbourtown Tapleys Hill Rd West Beach SA 5024",
    "addr:postcode":"5024",
    "addr:street":"Tapleys Hill Rd",
    "iso:country":"AU",
    "sg:address":"Shop T15, Harbourtown Tapleys Hill Rd",
    "sg:city":"West Beach",
    "sg:classifiers":[
        {
            "category":"Shopping",
            "subcategory":"Shoes",
            "type":"Retail Goods"
        }
    ],
    "sg:phone":"+61 8 8235 1944",
    "sg:postcode":"5024",
    "sg:province":"SA",
    "sg:tags":[
        "footwear"
    ],
    "wof:name":"Colorado",
    "wof:placetype":"venue"
},
  "geometry": {"coordinates":[138.51646423299999,-34.9348640442],"type":"Point"}
}