{
  "type": "Feature",
  "properties": {
    "addr:full":"22 Payneham Rd Stepney SA 5069",
    "addr:housenumber":"22",
    "addr:postcode":"5069",
    "addr:street":"Payneham Rd",
    "iso:country":"AU",
    "sg:address":"22 Payneham Rd",
    "sg:city":"Stepney",
    "sg:classifiers":[
        {
            "category":"Utilities",
            "subcategory":"Mobile Phone",
            "type":"Services"
        }
    ],
    "sg:phone":"+61 8 8363 3777",
    "sg:postcode":"5069",
    "sg:province":"SA",
    "sg:tags":[
        "repair",
        "telephone"
    ],
    "wof:name":"Alltech Industries Australia",
    "wof:placetype":"venue"
},
  "geometry": {"coordinates":[138.62402343799999,-34.9143562317],"type":"Point"}
}