{
  "type": "Feature",
  "properties": {
    "addr:full":"71 Buring Crs Minchinbury NSW 2770",
    "addr:housenumber":"71",
    "addr:postcode":"2770",
    "addr:street":"Buring Crs",
    "iso:country":"AU",
    "sg:address":"71 Buring Crs",
    "sg:city":"Minchinbury",
    "sg:classifiers":[
        {
            "category":"Personal",
            "subcategory":"Beauty Salon",
            "type":"Services"
        }
    ],
    "sg:phone":"+61 2 9832 7850",
    "sg:postcode":"2770",
    "sg:province":"NSW",
    "wof:name":"Biba's Beauty Therapy (Pty) Ltd",
    "wof:placetype":"venue"
},
  "geometry": {"coordinates":[150.825714111,-33.7820510864],"type":"Point"}
}