{
  "type": "Feature",
  "properties": {
    "iso:country":"AU",
    "sg:address":"167 Reynard St",
    "sg:city":"Coburg West",
    "sg:classifiers":[
        {
            "category":"Retail",
            "subcategory":"Auto Repair",
            "type":"Services"
        }
    ],
    "sg:phone":"+61 3 9386 1506",
    "sg:postcode":"3058",
    "sg:province":"VIC",
    "sg:tags":[
        "repairer",
        "motor",
        "engineer"
    ],
    "wof:name":"D & B Supertune",
    "wof:placetype":"venue"
},
  "geometry": {"coordinates":[144.94985961899999,-37.7471923828],"type":"Point"}
}