{
  "type": "Feature",
  "properties": {
    "iso:country":"AU",
    "sg:address":"Level 4/ 75 Flinders La",
    "sg:city":"Melbourne",
    "sg:classifiers":[
        {
            "category":"Arts & Performance",
            "subcategory":"Art Gallery",
            "type":"Entertainment"
        }
    ],
    "sg:phone":"+61 3 9654 5658",
    "sg:postcode":"3000",
    "sg:province":"VIC",
    "wof:name":"Agathon Gallery",
    "wof:placetype":"venue"
},
  "geometry": {"coordinates":[144.97213745100001,-37.8150939941],"type":"Point"}
}