{
  "type": "Feature",
  "properties": {
    "addr:full":"13 Panama St Canning Vale WA 6155",
    "addr:housenumber":"13",
    "addr:postcode":"6155",
    "addr:street":"Panama St",
    "iso:country":"AU",
    "sg:address":"13 Panama St",
    "sg:city":"Canning Vale",
    "sg:classifiers":[
        {
            "category":"Professional",
            "subcategory":"Engineering",
            "type":"Services"
        }
    ],
    "sg:phone":"+61 8 9456 5355",
    "sg:postcode":"6155",
    "sg:province":"WA",
    "sg:tags":[
        "engineer"
    ],
    "wof:name":"Tuart Engineering Pty Ltd",
    "wof:placetype":"venue"
},
  "geometry": {"coordinates":[115.932518,-32.064407],"type":"Point"}
}