{
  "type": "Feature",
  "properties": {
    "iso:country":"AU",
    "sg:address":"145 Oxford St",
    "sg:city":"Bulimba",
    "sg:classifiers":[
        {
            "category":"Real Estate",
            "subcategory":"Real Estate Agent",
            "type":"Services"
        }
    ],
    "sg:phone":"+61 13 39 11",
    "sg:postcode":"4171",
    "sg:province":"QLD",
    "wof:name":"Place Estate Agents",
    "wof:placetype":"venue"
},
  "geometry": {"coordinates":[153.059036255,-27.4511699677],"type":"Point"}
}