{
  "type": "Feature",
  "properties": {
    "addr:full":"4/ 35 Chapple St Gladstone QLD 4680",
    "addr:housenumber":"/ 35",
    "addr:postcode":"4680",
    "addr:street":"Chapple St",
    "iso:country":"AU",
    "sg:address":"4/ 35 Chapple St",
    "sg:city":"Gladstone",
    "sg:classifiers":[
        {
            "category":"Government",
            "subcategory":"Fire Station",
            "type":"Public Place"
        }
    ],
    "sg:phone":"+61 7 4973 4500",
    "sg:postcode":"4680",
    "sg:province":"QLD",
    "sg:tags":[
        "equipment",
        "protection",
        "consultant"
    ],
    "wof:name":"Chubb Fire Safety",
    "wof:placetype":"venue"
},
  "geometry": {"coordinates":[151.24057006800001,-23.8425731659],"type":"Point"}
}