{
  "type": "Feature",
  "properties": {
    "addr:full":"18 Arthur St Fortitude Valley QLD 4006",
    "addr:housenumber":"18",
    "addr:postcode":"4006",
    "addr:street":"Arthur St",
    "iso:country":"AU",
    "sg:address":"18 Arthur St",
    "sg:city":"Fortitude Valley",
    "sg:classifiers":[
        {
            "category":"Arts & Performance",
            "subcategory":"Art Gallery",
            "type":"Entertainment"
        }
    ],
    "sg:phone":"+61 7 3254 2277",
    "sg:postcode":"4006",
    "sg:province":"QLD",
    "wof:name":"A Day on Earth",
    "wof:placetype":"venue"
},
  "geometry": {"coordinates":[153.03814697300001,-27.4604969025],"type":"Point"}
}