{
  "type": "Feature",
  "properties": {
    "addr:full":"20 Norman St Clifton QLD 4361",
    "addr:housenumber":"20",
    "addr:postcode":"4361",
    "addr:street":"Norman St",
    "iso:country":"AU",
    "sg:address":"20 Norman St",
    "sg:city":"Clifton",
    "sg:classifiers":[
        {
            "category":"Health Services",
            "subcategory":"Doctor",
            "type":"Services"
        }
    ],
    "sg:phone":"+61 7 4697 3097",
    "sg:postcode":"4361",
    "sg:province":"QLD",
    "sg:tags":[
        "medical",
        "practitioner"
    ],
    "wof:name":"Clifton Medical Practice",
    "wof:placetype":"venue"
},
  "geometry": {"coordinates":[151.91113281200001,-27.9281978607],"type":"Point"}
}