{
  "type": "Feature",
  "properties": {
    "addr:full":"33 Shawlands Ave Blackburn South VIC 3130",
    "addr:housenumber":"33",
    "addr:postcode":"3130",
    "addr:street":"Shawlands Ave",
    "iso:country":"AU",
    "sg:address":"33 Shawlands Ave",
    "sg:city":"Blackburn South",
    "sg:classifiers":[
        {
            "category":"Building & Trades",
            "subcategory":"Landscaping Services",
            "type":"Services"
        }
    ],
    "sg:phone":"+61 425 709 010",
    "sg:postcode":"3130",
    "sg:province":"VIC",
    "sg:tags":[
        "gardener"
    ],
    "wof:name":"Garden Impressions",
    "wof:placetype":"venue"
},
  "geometry": {"coordinates":[145.15081787099999,-37.8354301453],"type":"Point"}
}