{
  "type": "Feature",
  "properties": {
    "iso:country":"AU",
    "sg:address":"7 Elizabeth Drv",
    "sg:city":"Alexandra Hills",
    "sg:classifiers":[
        {
            "category":"Home & Garden",
            "subcategory":"Carpets & Floor Coverings",
            "type":"Retail Goods"
        }
    ],
    "sg:phone":"+61 7 3824 3874",
    "sg:postcode":"4161",
    "sg:province":"QLD",
    "sg:tags":[
        "tile",
        "wall",
        "layer"
    ],
    "wof:name":"Markwell, Neil",
    "wof:placetype":"venue"
},
  "geometry": {"coordinates":[153.22102355999999,-27.5207614899],"type":"Point"}
}