{
  "type": "Feature",
  "properties": {
    "addr:full":"Shp 3/ 42 Old North Rd Clare SA 5453",
    "addr:housenumber":"/ 42",
    "addr:postcode":"5453",
    "addr:street":"Old North Rd",
    "iso:country":"AU",
    "sg:address":"Shp 3/ 42 Old North Rd",
    "sg:city":"Clare",
    "sg:classifiers":[
        {
            "category":"Shopping",
            "subcategory":"Clothing, Apparel, & Fashions",
            "type":"Retail Goods"
        }
    ],
    "sg:phone":"+61 8 8842 3535",
    "sg:postcode":"5453",
    "sg:province":"SA",
    "sg:tags":[
        "lady",
        "wear"
    ],
    "wof:name":"Clare Fashions & Fabrics",
    "wof:placetype":"venue"
},
  "geometry": {"coordinates":[138.61132799999999,-33.83271],"type":"Point"}
}