{
  "type": "Feature",
  "properties": {
    "iso:country":"AU",
    "sg:address":"173 George St",
    "sg:city":"Doncaster East",
    "sg:classifiers":[
        {
            "category":"Building & Trades",
            "subcategory":"Construction",
            "type":"Services"
        }
    ],
    "sg:phone":"+61 3 9840 1400",
    "sg:postcode":"3109",
    "sg:province":"VIC",
    "sg:tags":[
        "renovation",
        "alterations",
        "extension",
        "contractor"
    ],
    "wof:name":"Victoriana Homes",
    "wof:placetype":"venue"
},
  "geometry": {"coordinates":[145.14149475100001,-37.7795219421],"type":"Point"}
}