{
  "type": "Feature",
  "properties": {
    "iso:country":"AU",
    "sg:address":"148 Station St",
    "sg:city":"Fairfield",
    "sg:classifiers":[
        {
            "category":"Shopping",
            "subcategory":"Baby Store",
            "type":"Retail Goods"
        }
    ],
    "sg:phone":"+61 3 9482 6686",
    "sg:postcode":"3078",
    "sg:province":"VIC",
    "sg:tags":[
        "children's",
        "wear"
    ],
    "wof:name":"Get Shorty",
    "wof:placetype":"venue"
},
  "geometry": {"coordinates":[145.01846313499999,-37.7758750916],"type":"Point"}
}