{
  "type": "Feature",
  "properties": {
    "addr:full":"337 High St Northcote VIC 3070",
    "addr:housenumber":"337",
    "addr:postcode":"3070",
    "addr:street":"High St",
    "iso:country":"AU",
    "sg:address":"337 High St",
    "sg:city":"Northcote",
    "sg:classifiers":[
        {
            "category":"Food & Beverages",
            "subcategory":"Bakery",
            "type":"Retail Goods"
        }
    ],
    "sg:phone":"+61 3 9489 2993",
    "sg:postcode":"3070",
    "sg:province":"VIC",
    "sg:tags":[
        "baker"
    ],
    "wof:name":"Babis Pty Ltd",
    "wof:placetype":"venue"
},
  "geometry": {"coordinates":[144.998627,-37.770515],"type":"Point"}
}