{
  "type": "Feature",
  "properties": {
    "addr:full":"66 Rutters Ridge Rd Oberon NSW 2787",
    "addr:housenumber":"66",
    "addr:postcode":"2787",
    "addr:street":"Rutters Ridge Rd",
    "iso:country":"AU",
    "sg:address":"66 Rutters Ridge Rd",
    "sg:city":"Oberon",
    "sg:classifiers":[
        {
            "category":"Home & Garden",
            "subcategory":"Hardware",
            "type":"Retail Goods"
        }
    ],
    "sg:phone":"+61 1300 881 028",
    "sg:postcode":"2787",
    "sg:province":"NSW",
    "sg:tags":[
        "product",
        "treatment",
        "floor"
    ],
    "wof:name":"Central West Anti-Slip",
    "wof:placetype":"venue"
},
  "geometry": {"coordinates":[149.86592102,-33.6774940491],"type":"Point"}
}