{
  "type": "Feature",
  "properties": {
    "addr:full":"5 Robert Cambell Drv Raymond Terrace NSW 2324",
    "addr:housenumber":"5",
    "addr:postcode":"2324",
    "addr:street":"Robert Cambell Drv",
    "iso:country":"AU",
    "sg:address":"5 Robert Cambell Drv",
    "sg:city":"Raymond Terrace",
    "sg:classifiers":[
        {
            "category":"Utilities",
            "subcategory":"Water",
            "type":"Services"
        }
    ],
    "sg:phone":"+61 415 684 770",
    "sg:postcode":"2324",
    "sg:province":"NSW",
    "sg:tags":[
        "cartage"
    ],
    "wof:name":"Allan Dunn's Watertanker Hire",
    "wof:placetype":"venue"
},
  "geometry": {"coordinates":[151.76388549800001,-32.7591133118],"type":"Point"}
}