{
  "type": "Feature",
  "properties": {
    "addr:full":"140 Brisbane St Beaudesert QLD 4285",
    "addr:housenumber":"140",
    "addr:postcode":"4285",
    "addr:street":"Brisbane St",
    "iso:country":"AU",
    "sg:address":"140 Brisbane St",
    "sg:city":"Beaudesert",
    "sg:classifiers":[
        {
            "category":"Professional",
            "subcategory":"Detective & Security Services",
            "type":"Services"
        }
    ],
    "sg:phone":"+61 7 5546 3499",
    "sg:postcode":"4285",
    "sg:province":"QLD",
    "sg:tags":[
        "equipment",
        "window",
        "doors"
    ],
    "wof:name":"Nash Glass & Aluminium Pty Ltd",
    "wof:placetype":"venue"
},
  "geometry": {"coordinates":[152.99392700000001,-27.979362],"type":"Point"}
}