{
  "type": "Feature",
  "properties": {
    "addr:full":"5 Alderford Drv Wantirna South VIC 3152",
    "addr:housenumber":"5",
    "addr:postcode":"3152",
    "addr:street":"Alderford Drv",
    "iso:country":"AU",
    "sg:address":"5 Alderford Drv",
    "sg:city":"Wantirna South",
    "sg:classifiers":[
        {
            "category":"Professional",
            "subcategory":"Business Services",
            "type":"Services"
        }
    ],
    "sg:phone":"+61 3 9899 1952",
    "sg:postcode":"3152",
    "sg:province":"VIC",
    "sg:tags":[
        "drafting"
    ],
    "wof:name":"A1 House Plans",
    "wof:placetype":"venue"
},
  "geometry": {"coordinates":[145.23814392099999,-37.8610954285],"type":"Point"}
}