{
  "type": "Feature",
  "properties": {
    "addr:full":"PO Box 1706 Broadbeach QLD 4218",
    "addr:postcode":"4218",
    "iso:country":"AU",
    "sg:address":"PO Box 1706",
    "sg:city":"Broadbeach",
    "sg:classifiers":[
        {
            "category":"Manufacturing",
            "subcategory":"Food",
            "type":"Manufacturing & Wholesale Goods"
        }
    ],
    "sg:phone":"+61 7 5525 1277",
    "sg:postcode":"4218",
    "sg:province":"QLD",
    "sg:tags":[
        "function",
        "catering"
    ],
    "wof:name":"Chef Talk Catering Co.",
    "wof:placetype":"venue"
},
  "geometry": {"coordinates":[153.429397583,-28.0263690948],"type":"Point"}
}