{
  "type": "Feature",
  "properties": {
    "iso:country":"AU",
    "sg:address":"188 B Barkly St",
    "sg:city":"St Kilda",
    "sg:classifiers":[
        {
            "category":"Personal",
            "subcategory":"Beauty Salon",
            "type":"Services"
        }
    ],
    "sg:phone":"+61 3 9593 6083",
    "sg:postcode":"3182",
    "sg:province":"VIC",
    "sg:tags":[
        "hairdresser"
    ],
    "wof:name":"Resin Hair",
    "wof:placetype":"venue"
},
  "geometry": {"coordinates":[144.982666016,-37.8592605591],"type":"Point"}
}