{
  "type": "Feature",
  "properties": {
    "addr:full":"230 Mt Ommaney Drv Mt Ommaney QLD 4074",
    "addr:housenumber":"230",
    "addr:postcode":"4074",
    "addr:street":"Mt Ommaney Drv Mt Ommaney",
    "iso:country":"AU",
    "sg:address":"230 Mt Ommaney Drv",
    "sg:city":"Mt Ommaney",
    "sg:classifiers":[
        {
            "category":"Communications",
            "type":"Services"
        }
    ],
    "sg:phone":"+61 418 198 539",
    "sg:postcode":"4074",
    "sg:province":"QLD",
    "sg:tags":[
        "translation"
    ],
    "wof:name":"Vietnamese Kay See Services",
    "wof:placetype":"venue"
},
  "geometry": {"coordinates":[152.93075561500001,-27.5437030792],"type":"Point"}
}