{
  "type": "Feature",
  "properties": {
    "iso:country":"AU",
    "sg:address":"Shop 74, Epping Plaza, Cnr Cooper & High Sts",
    "sg:city":"Epping",
    "sg:classifiers":[
        {
            "category":"Food & Beverages",
            "subcategory":"Bakery",
            "type":"Retail Goods"
        }
    ],
    "sg:phone":"+61 3 9408 8577",
    "sg:postcode":"3076",
    "sg:province":"VIC",
    "sg:tags":[
        "cake",
        "shop",
        "pastry"
    ],
    "wof:name":"Ferguson Plarre Bakehouses Pty Ltd",
    "wof:placetype":"venue"
},
  "geometry": {"coordinates":[145.02752685600001,-37.6315765381],"type":"Point"}
}