{
  "type": "Feature",
  "properties": {
    "iso:country":"AU",
    "sg:address":"Lot 1 Sixty Eight Rd",
    "sg:city":"Baldivis",
    "sg:classifiers":[
        {
            "category":"Retail",
            "subcategory":"Veterinary Services",
            "type":"Services"
        }
    ],
    "sg:phone":"+61 8 9524 1105",
    "sg:postcode":"6171",
    "sg:province":"WA",
    "sg:tags":[
        "surgeon"
    ],
    "wof:name":"Sixty Eight Rd Mobile Veterinary Service",
    "wof:placetype":"venue"
},
  "geometry": {"coordinates":[115.783691,-32.362507],"type":"Point"}
}