{
  "type": "Feature",
  "properties": {
    "addr:full":"Lvl2/ 430 Little Collins St Melbourne VIC 3000",
    "addr:housenumber":"430",
    "addr:postcode":"3000",
    "addr:street":"Little Collins St",
    "iso:country":"AU",
    "sg:address":"Lvl2/ 430 Little Collins St",
    "sg:city":"Melbourne",
    "sg:classifiers":[
        {
            "category":"Professional",
            "subcategory":"Computer Services",
            "type":"Services"
        }
    ],
    "sg:phone":"+61 3 9663 4500",
    "sg:postcode":"3000",
    "sg:province":"VIC",
    "sg:tags":[
        "package",
        "software"
    ],
    "wof:name":"Progenesis Pty Ltd",
    "wof:placetype":"venue"
},
  "geometry": {"coordinates":[144.97265625,-37.8135528564],"type":"Point"}
}