{
  "type": "Feature",
  "properties": {
    "addr:full":"38b Somerset St Kingswood NSW 2747",
    "addr:housenumber":"38b",
    "addr:postcode":"2747",
    "addr:street":"Somerset St",
    "iso:country":"AU",
    "sg:address":"38b Somerset St",
    "sg:city":"Kingswood",
    "sg:classifiers":[
        {
            "category":"Health Services",
            "subcategory":"Doctor",
            "type":"Services"
        }
    ],
    "sg:phone":"+61 2 4736 8377",
    "sg:postcode":"2747",
    "sg:province":"NSW",
    "sg:tags":[
        "medical",
        "practitioner"
    ],
    "wof:name":"Cheung Deborah Dr",
    "wof:placetype":"venue"
},
  "geometry": {"coordinates":[150.715454102,-33.7614479065],"type":"Point"}
}