{
  "type": "Feature",
  "properties": {
    "addr:full":"Point Rd Mooney Mooney NSW 2083",
    "addr:postcode":"2083",
    "addr:street":"Point Rd",
    "iso:country":"AU",
    "sg:address":"Point Rd",
    "sg:city":"Mooney Mooney",
    "sg:classifiers":[
        {
            "category":"Farming",
            "subcategory":"Fish & Marine Products",
            "type":"Manufacturing & Wholesale Goods"
        }
    ],
    "sg:phone":"+61 2 9985 9106",
    "sg:postcode":"2083",
    "sg:province":"NSW",
    "sg:tags":[
        "supplier",
        "oyster",
        "farmer"
    ],
    "wof:name":"Barclay G",
    "wof:placetype":"venue"
},
  "geometry": {"coordinates":[151.20161438,-33.5241851807],"type":"Point"}
}