{
  "type": "Feature",
  "properties": {
    "addr:full":"249 James St Northbridge WA 6003",
    "addr:housenumber":"249",
    "addr:postcode":"6003",
    "addr:street":"James St",
    "iso:country":"AU",
    "sg:address":"249 James St",
    "sg:city":"Northbridge",
    "sg:classifiers":[
        {
            "category":"Fast Food",
            "type":"Food & Drink"
        }
    ],
    "sg:phone":"+61 8 9328 7647",
    "sg:postcode":"6003",
    "sg:province":"WA",
    "sg:tags":[
        "away",
        "take"
    ],
    "wof:name":"Dusit Thai Restaurant",
    "wof:placetype":"venue"
},
  "geometry": {"coordinates":[115.85272979699999,-31.9461288452],"type":"Point"}
}