{
  "type": "Feature",
  "properties": {
    "addr:full":"Lot 59 23 Campbell Rd Greenbank QLD 4124",
    "addr:housenumber":"23",
    "addr:postcode":"4124",
    "addr:street":"Campbell Rd",
    "iso:country":"AU",
    "sg:address":"Lot 59 23 Campbell Rd",
    "sg:city":"Greenbank",
    "sg:classifiers":[
        {
            "category":"Farming",
            "subcategory":"Farm",
            "type":"Manufacturing & Wholesale Goods"
        }
    ],
    "sg:phone":"+61 7 3200 0566",
    "sg:postcode":"4124",
    "sg:province":"QLD",
    "sg:tags":[
        "farmer"
    ],
    "wof:name":"A Siesta Palms",
    "wof:placetype":"venue"
},
  "geometry": {"coordinates":[152.99124145499999,-27.7265949249],"type":"Point"}
}