{
  "type": "Feature",
  "properties": {
    "addr:full":"363 Glenfern Rd Upwey VIC 3158",
    "addr:housenumber":"363",
    "addr:postcode":"3158",
    "addr:street":"Glenfern Rd",
    "iso:country":"AU",
    "sg:address":"363 Glenfern Rd",
    "sg:city":"Upwey",
    "sg:classifiers":[
        {
            "category":"Shopping",
            "subcategory":"Musical Instruments",
            "type":"Retail Goods"
        }
    ],
    "sg:phone":"+61 3 9754 4187",
    "sg:postcode":"3158",
    "sg:province":"VIC",
    "sg:tags":[
        "musician",
        "agent"
    ],
    "wof:name":"Ellis J W",
    "wof:placetype":"venue"
},
  "geometry": {"coordinates":[145.336181641,-37.9156532288],"type":"Point"}
}