{
  "type": "Feature",
  "properties": {
    "addr:full":"29 Hygeia Pde Ringwood VIC 3134",
    "addr:housenumber":"29",
    "addr:postcode":"3134",
    "addr:street":"Hygeia Pde",
    "iso:country":"AU",
    "sg:address":"29 Hygeia Pde",
    "sg:city":"Ringwood",
    "sg:classifiers":[
        {
            "category":"Education",
            "subcategory":"Kindergarten",
            "type":"Public Place"
        }
    ],
    "sg:phone":"+61 3 9870 3582",
    "sg:postcode":"3134",
    "sg:province":"VIC",
    "sg:tags":[
        "pre-schools"
    ],
    "wof:name":"Pinemont Pre-School",
    "wof:placetype":"venue"
},
  "geometry": {"coordinates":[145.217453003,-37.806312561],"type":"Point"}
}