{
  "type": "Feature",
  "properties": {
    "iso:country":"AU",
    "sg:address":"528 Hay St",
    "sg:city":"Perth",
    "sg:classifiers":[
        {
            "category":"Cafe",
            "type":"Food & Drink"
        }
    ],
    "sg:phone":"+61 8 9325 8150",
    "sg:postcode":"6000",
    "sg:province":"WA",
    "wof:name":"Bernadis of Hay Street",
    "wof:placetype":"venue"
},
  "geometry": {"coordinates":[115.855537415,-31.9532051086],"type":"Point"}
}