{
  "type": "Feature",
  "properties": {
    "iso:country":"AU",
    "sg:address":"41 Downs St",
    "sg:city":"Roma",
    "sg:classifiers":[
        {
            "category":"Retail",
            "subcategory":"Storage",
            "type":"Services"
        }
    ],
    "sg:phone":"+61 7 4622 5453",
    "sg:postcode":"4455",
    "sg:province":"QLD",
    "sg:tags":[
        "removal",
        "furniture"
    ],
    "wof:name":"Roma Removals",
    "wof:placetype":"venue"
},
  "geometry": {"coordinates":[148.774047852,-26.5769004822],"type":"Point"}
}