{
  "type": "Feature",
  "properties": {
    "iso:country":"AU",
    "sg:address":"14 Buckley St",
    "sg:city":"Marrickville",
    "sg:classifiers":[
        {
            "category":"Home & Garden",
            "subcategory":"Carpets & Floor Coverings",
            "type":"Retail Goods"
        }
    ],
    "sg:phone":"+61 2 9565 4070",
    "sg:postcode":"2204",
    "sg:province":"NSW",
    "sg:tags":[
        "double",
        "window",
        "glazed"
    ],
    "wof:name":"Magnetite (Inside Insulating Window Systems)",
    "wof:placetype":"venue"
},
  "geometry": {"coordinates":[151.16539,-33.913143],"type":"Point"}
}