{
  "type": "Feature",
  "properties": {
    "addr:full":"27 Richardson Rd Port Denison WA 6525",
    "addr:housenumber":"27",
    "addr:postcode":"6525",
    "addr:street":"Richardson Rd",
    "iso:country":"AU",
    "sg:address":"27 Richardson Rd",
    "sg:city":"Port Denison",
    "sg:classifiers":[
        {
            "category":"Building & Trades",
            "subcategory":"Construction",
            "type":"Services"
        }
    ],
    "sg:phone":"+61 8 9927 1054",
    "sg:postcode":"6525",
    "sg:province":"WA",
    "sg:tags":[
        "fencing",
        "contractor"
    ],
    "wof:name":"Residential & Rural Services",
    "wof:placetype":"venue"
},
  "geometry": {"coordinates":[114.92514038100001,-29.2624988556],"type":"Point"}
}