{
  "type": "Feature",
  "properties": {
    "iso:country":"AU",
    "sg:address":"1 Alkina St",
    "sg:city":"Sapphire",
    "sg:classifiers":[
        {
            "category":"Shopping",
            "subcategory":"Party Supplies",
            "type":"Retail Goods"
        }
    ],
    "sg:phone":"+61 2 6653 6183",
    "sg:postcode":"2360",
    "sg:province":"NSW",
    "sg:tags":[
        "selling",
        "plan"
    ],
    "wof:name":"Crafty Kids",
    "wof:placetype":"venue"
},
  "geometry": {"coordinates":[151.28468322800001,-29.6887893677],"type":"Point"}
}