{
  "type": "Feature",
  "properties": {
    "iso:country":"AU",
    "sg:address":"435- 441 Victoria St",
    "sg:city":"Brunswick West",
    "sg:classifiers":[
        {
            "category":"Banks & Credit Unions",
            "subcategory":"Investment Brokerage",
            "type":"Services"
        }
    ],
    "sg:phone":"+61 3 9380 1411",
    "sg:postcode":"3055",
    "sg:province":"VIC",
    "sg:tags":[
        "radiator",
        "motor"
    ],
    "wof:name":"Pansino F & Co Pty Ltd",
    "wof:placetype":"venue"
},
  "geometry": {"coordinates":[144.94854736299999,-37.7651557922],"type":"Point"}
}