{
  "type": "Feature",
  "properties": {
    "iso:country":"AU",
    "sg:address":"88 Mallett St",
    "sg:city":"Camperdown",
    "sg:classifiers":[
        {
            "category":"Education",
            "subcategory":"Dance Studio",
            "type":"Public Place"
        }
    ],
    "sg:phone":"+61 2 9351 0706",
    "sg:postcode":"2050",
    "sg:province":"NSW",
    "sg:tags":[
        "instruction",
        "language"
    ],
    "wof:name":"The Centre For English Teaching",
    "wof:placetype":"venue"
},
  "geometry": {"coordinates":[151.177567,-33.888809],"type":"Point"}
}