{
  "type": "Feature",
  "properties": {
    "addr:full":"U49/ 80 Mcintyre St Hendra QLD 4011",
    "addr:postcode":"4011",
    "addr:street":"/ 80 Mcintyre St",
    "iso:country":"AU",
    "sg:address":"U49/ 80 Mcintyre St",
    "sg:city":"Hendra",
    "sg:classifiers":[
        {
            "category":"Banks & Credit Unions",
            "subcategory":"Investment Brokerage",
            "type":"Services"
        }
    ],
    "sg:phone":"+61 7 3268 3843",
    "sg:postcode":"4011",
    "sg:province":"QLD",
    "sg:tags":[
        "management",
        "property"
    ],
    "wof:name":"Millbrook Property Management",
    "wof:placetype":"venue"
},
  "geometry": {"coordinates":[153.06929,-27.414848],"type":"Point"}
}