{
  "type": "Feature",
  "properties": {
    "addr:full":"33 John St Pakenham VIC 3810",
    "addr:housenumber":"33",
    "addr:postcode":"3810",
    "addr:street":"John St",
    "iso:country":"AU",
    "sg:address":"33 John St",
    "sg:city":"Pakenham",
    "sg:classifiers":[
        {
            "category":"Travel",
            "subcategory":"Travel Agent",
            "type":"Entertainment"
        }
    ],
    "sg:phone":"+61 13 18 66",
    "sg:postcode":"3810",
    "sg:province":"VIC",
    "sg:tags":[
        "consultant"
    ],
    "wof:name":"Flight Centre",
    "wof:placetype":"venue"
},
  "geometry": {"coordinates":[145.48161300000001,-38.077644],"type":"Point"}
}