{
  "type": "Feature",
  "properties": {
    "addr:full":"29th Floor 201 Kent St Sydney NSW 2000",
    "addr:housenumber":"201",
    "addr:postcode":"2000",
    "addr:street":"Kent St",
    "iso:country":"AU",
    "sg:address":"29th Floor 201 Kent St",
    "sg:city":"Sydney",
    "sg:classifiers":[
        {
            "category":"Utilities",
            "subcategory":"Natural Gas",
            "type":"Services"
        }
    ],
    "sg:phone":"+61 2 9259 0100",
    "sg:postcode":"2000",
    "sg:province":"NSW",
    "sg:tags":[
        "consultant",
        "resource"
    ],
    "wof:name":"National Power Australia LLC",
    "wof:placetype":"venue"
},
  "geometry": {"coordinates":[151.20382690400001,-33.8636398315],"type":"Point"}
}