{
  "type": "Feature",
  "properties": {
    "iso:country":"AU",
    "sg:address":"26 Alma Rd St",
    "sg:city":"Kilda",
    "sg:classifiers":[
        {
            "category":"Museum",
            "type":"Entertainment"
        }
    ],
    "sg:phone":"+61 3 9534 0083",
    "sg:postcode":"3182",
    "sg:province":"VIC",
    "wof:name":"Jewish Museum Of Australia The Gandel Centre of Judaica",
    "wof:placetype":"venue"
},
  "geometry": {"coordinates":[144.98501586899999,-37.8604354858],"type":"Point"}
}