{
  "type": "Feature",
  "properties": {
    "iso:country":"AU",
    "sg:address":"901 Lydiard St",
    "sg:city":"(North) Ballarat",
    "sg:classifiers":[
        {
            "category":"Personal",
            "subcategory":"Beauty Salon",
            "type":"Services"
        }
    ],
    "sg:phone":"+61 3 5331 3041",
    "sg:postcode":"3350",
    "sg:province":"VIC",
    "wof:name":"Salon Euphoria",
    "wof:placetype":"venue"
},
  "geometry": {"coordinates":[143.861008,-37.543507],"type":"Point"}
}