{
  "type": "Feature",
  "properties": {
    "iso:country":"AU",
    "sg:address":"Unit 3 119 Harbord Rd",
    "sg:city":"Harbord",
    "sg:classifiers":[
        {
            "category":"Food & Beverages",
            "subcategory":"Fruits & Vegetables",
            "type":"Retail Goods"
        }
    ],
    "sg:phone":"+61 2 9905 1099",
    "sg:postcode":"2096",
    "sg:province":"NSW",
    "sg:tags":[
        "greengrocer",
        "fruiterer"
    ],
    "wof:name":"Harbord Fruit Shop",
    "wof:placetype":"venue"
},
  "geometry": {"coordinates":[151.279388428,-33.7724113464],"type":"Point"}
}