{
  "type": "Feature",
  "properties": {
    "addr:full":"29 Somerset St Sunshine VIC 3020",
    "addr:housenumber":"29",
    "addr:postcode":"3020",
    "addr:street":"Somerset St",
    "iso:country":"AU",
    "sg:address":"29 Somerset St",
    "sg:city":"Sunshine",
    "sg:classifiers":[
        {
            "category":"Building & Trades",
            "subcategory":"Construction",
            "type":"Services"
        }
    ],
    "sg:phone":"+61 404 454 833",
    "sg:postcode":"3020",
    "sg:province":"VIC",
    "sg:tags":[
        "plasterboard",
        "plasterer",
        "fixer"
    ],
    "wof:name":"Majer Plastering",
    "wof:placetype":"venue"
},
  "geometry": {"coordinates":[144.827271,-37.757313],"type":"Point"}
}