{
  "type": "Feature",
  "properties": {
    "iso:country":"AU",
    "sg:address":"276 Batchlers Rd",
    "sg:city":"Bundaberg",
    "sg:classifiers":[
        {
            "category":"Home & Garden",
            "subcategory":"Garden Supply",
            "type":"Retail Goods"
        }
    ],
    "sg:phone":"+61 418 778 865",
    "sg:postcode":"4670",
    "sg:province":"QLD",
    "sg:tags":[
        "turf",
        "lawn"
    ],
    "wof:name":"Burnett Turf",
    "wof:placetype":"venue"
},
  "geometry": {"coordinates":[152.315719605,-24.8458061218],"type":"Point"}
}