{
  "type": "Feature",
  "properties": {
    "addr:full":"Shop 4, 7-9 Grand Plaza Drv Browns Plains QLD 4118",
    "addr:housenumber":"shop;7-9",
    "addr:postcode":"4118",
    "addr:street":"Grand Plaza Drv",
    "iso:country":"AU",
    "sg:address":"Shop 4, 7-9 Grand Plaza Drv",
    "sg:city":"Browns Plains",
    "sg:classifiers":[
        {
            "category":"Banks & Credit Unions",
            "subcategory":"Financial Services",
            "type":"Services"
        }
    ],
    "sg:phone":"+61 7 3802 8188",
    "sg:postcode":"4118",
    "sg:province":"QLD",
    "sg:tags":[
        "loan",
        "finance",
        "mortgage"
    ],
    "wof:name":"RAMS Home Loans",
    "wof:placetype":"venue"
},
  "geometry": {"coordinates":[153.03741455100001,-27.664352417],"type":"Point"}
}