{
  "type": "Feature",
  "properties": {
    "addr:full":"158 Wilson Drv Hill Top NSW 2575",
    "addr:housenumber":"158",
    "addr:postcode":"2575",
    "addr:street":"Wilson Drv",
    "iso:country":"AU",
    "sg:address":"158 Wilson Drv",
    "sg:city":"Hill Top",
    "sg:classifiers":[
        {
            "category":"Building & Trades",
            "subcategory":"Construction",
            "type":"Services"
        }
    ],
    "sg:phone":"+61 414 592 996",
    "sg:postcode":"2575",
    "sg:province":"NSW",
    "sg:tags":[
        "concrete",
        "contractor"
    ],
    "wof:name":"Gordon's Concreting",
    "wof:placetype":"venue"
},
  "geometry": {"coordinates":[150.49346923799999,-34.347038269],"type":"Point"}
}