{
  "type": "Feature",
  "properties": {
    "iso:country":"AU",
    "sg:address":"Cnr Main St & Edgar Rd",
    "sg:city":"Thomastown",
    "sg:classifiers":[
        {
            "category":"Food & Beverages",
            "subcategory":"Supermarket",
            "type":"Retail Goods"
        }
    ],
    "sg:phone":"+61 3 9465 9244",
    "sg:postcode":"3074",
    "sg:province":"VIC",
    "sg:tags":[
        "grocery",
        "store"
    ],
    "wof:name":"Thomastown Supa IGA",
    "wof:placetype":"venue"
},
  "geometry": {"coordinates":[145.01194763199999,-37.6799583435],"type":"Point"}
}