{
  "type": "Feature",
  "properties": {
    "addr:full":"19 Awatea Rd St Ives Chase NSW 2075",
    "addr:housenumber":"19",
    "addr:postcode":"2075",
    "addr:street":"Awatea Rd",
    "iso:country":"AU",
    "sg:address":"19 Awatea Rd",
    "sg:city":"St Ives Chase",
    "sg:classifiers":[
        {
            "category":"Real Estate",
            "subcategory":"Real Estate Services",
            "type":"Services"
        }
    ],
    "sg:phone":"+61 412 277 823",
    "sg:postcode":"2075",
    "sg:province":"NSW",
    "sg:tags":[
        "consultant",
        "property"
    ],
    "wof:name":"Jarrah Bay Pty Ltd",
    "wof:placetype":"venue"
},
  "geometry": {"coordinates":[151.16093444800001,-33.7057037354],"type":"Point"}
}