{
  "type": "Feature",
  "properties": {
    "addr:full":"Shop 28 Wentworthville Mall Dunmore St Wentworthville NSW 2145",
    "addr:housenumber":"shop 28",
    "addr:postcode":"2145",
    "addr:street":"Wentworthville Mall Dunmore St",
    "iso:country":"AU",
    "sg:address":"Shop 28 Wentworthville Mall Dunmore St",
    "sg:city":"Wentworthville",
    "sg:classifiers":[
        {
            "category":"Shopping",
            "subcategory":"Clothing, Apparel, & Fashions",
            "type":"Retail Goods"
        }
    ],
    "sg:phone":"+61 2 9631 8363",
    "sg:postcode":"2145",
    "sg:province":"NSW",
    "sg:tags":[
        "lady",
        "wear"
    ],
    "wof:name":"Suzanne Grae",
    "wof:placetype":"venue"
},
  "geometry": {"coordinates":[150.97108459500001,-33.8076248169],"type":"Point"}
}