{
  "type": "Feature",
  "properties": {
    "iso:country":"AU",
    "sg:address":"49 Pringle Rd",
    "sg:city":"Fairy Meadow",
    "sg:classifiers":[
        {
            "category":"Mining & Drilling",
            "type":"Manufacturing & Wholesale Goods"
        }
    ],
    "sg:phone":"+61 2 4285 4655",
    "sg:postcode":"2519",
    "sg:province":"NSW",
    "sg:tags":[
        "equipment",
        "quarrying",
        "supply"
    ],
    "wof:name":"Mark M Industrial Pty Ltd",
    "wof:placetype":"venue"
},
  "geometry": {"coordinates":[150.891403,-34.386955],"type":"Point"}
}