{
  "type": "Feature",
  "properties": {
    "addr:full":"950 Centre Rd Oakleigh South VIC 3167",
    "addr:housenumber":"950",
    "addr:postcode":"3167",
    "addr:street":"Centre Rd",
    "iso:country":"AU",
    "sg:address":"950 Centre Rd",
    "sg:city":"Oakleigh South",
    "sg:classifiers":[
        {
            "category":"Travel",
            "subcategory":"Travel Agent",
            "type":"Entertainment"
        }
    ],
    "sg:phone":"+61 3 9563 8399",
    "sg:postcode":"3167",
    "sg:province":"VIC",
    "sg:tags":[
        "consultant"
    ],
    "wof:name":"African Dreams Travel",
    "wof:placetype":"venue"
},
  "geometry": {"coordinates":[145.082962036,-37.9241218567],"type":"Point"}
}