{
  "type": "Feature",
  "properties": {
    "iso:country":"AU",
    "sg:address":"32 Kularoo Drv",
    "sg:city":"Forster",
    "sg:classifiers":[
        {
            "category":"Autos & Motor Vehicles",
            "subcategory":"Auto Supplies",
            "type":"Retail Goods"
        }
    ],
    "sg:phone":"+61 2 6555 6844",
    "sg:postcode":"2428",
    "sg:province":"NSW",
    "sg:tags":[
        "car",
        "alarm"
    ],
    "wof:name":"Great Lakes Auto Electrical & E.F.I. Specialists",
    "wof:placetype":"venue"
},
  "geometry": {"coordinates":[152.51754800000001,-32.196323],"type":"Point"}
}