{
  "type": "Feature",
  "properties": {
    "addr:full":"40 French St Eagle Farm QLD 4009",
    "addr:housenumber":"40",
    "addr:postcode":"4009",
    "addr:street":"French St",
    "iso:country":"AU",
    "sg:address":"40 French St",
    "sg:city":"Eagle Farm",
    "sg:classifiers":[
        {
            "category":"Professional",
            "subcategory":"Employment Agencies",
            "type":"Services"
        }
    ],
    "sg:phone":"+61 7 3268 7255",
    "sg:postcode":"4009",
    "sg:province":"QLD",
    "sg:tags":[
        "broker",
        "custom"
    ],
    "wof:name":"Hinton McNeil Customs Pty Ltd",
    "wof:placetype":"venue"
},
  "geometry": {"coordinates":[153.09576415999999,-27.4318065643],"type":"Point"}
}