{
  "type": "Feature",
  "properties": {
    "addr:full":"Level 1, 65 London Cct Canberra City ACT 2601",
    "addr:housenumber":"65",
    "addr:postcode":"2601",
    "addr:street":"London Cct",
    "iso:country":"AU",
    "sg:address":"Level 1, 65",
    "sg:city":"London Cct Canberra City",
    "sg:classifiers":[
        {
            "category":"Banks & Credit Unions",
            "subcategory":"Financial Services",
            "type":"Services"
        }
    ],
    "sg:phone":"+61 2 6249 1988",
    "sg:postcode":"2601",
    "sg:province":"ACT",
    "sg:tags":[
        "planning"
    ],
    "wof:name":"Malcolm Phillips",
    "wof:placetype":"venue"
},
  "geometry": {"coordinates":[149.12818908700001,-35.2793464661],"type":"Point"}
}