{
  "type": "Feature",
  "properties": {
    "iso:country":"AU",
    "sg:address":"Hudson Rd",
    "sg:city":"Bunbury",
    "sg:classifiers":[
        {
            "category":"Food & Beverages",
            "subcategory":"Liquor & Beverages",
            "type":"Retail Goods"
        }
    ],
    "sg:phone":"+61 8 9795 8958",
    "sg:postcode":"6230",
    "sg:province":"WA",
    "sg:tags":[
        "store"
    ],
    "wof:name":"Condello's Liquor Stores",
    "wof:placetype":"venue"
},
  "geometry": {"coordinates":[115.636391,-33.365311],"type":"Point"}
}