{
  "type": "Feature",
  "properties": {
    "addr:full":"PO Box 88 Berrima NSW 2577",
    "addr:postcode":"2577",
    "iso:country":"AU",
    "sg:address":"PO Box 88",
    "sg:city":"Berrima",
    "sg:classifiers":[
        {
            "category":"Utilities",
            "subcategory":"Electric",
            "type":"Services"
        }
    ],
    "sg:phone":"+61 2 4877 1166",
    "sg:postcode":"2577",
    "sg:province":"NSW",
    "sg:tags":[
        "electrical",
        "contractor"
    ],
    "wof:name":"Marcus O'Connell Electrical Pty Ltd",
    "wof:placetype":"venue"
},
  "geometry": {"coordinates":[150.33674621599999,-34.4880485535],"type":"Point"}
}