{
  "type": "Feature",
  "properties": {
    "addr:full":"1 Browns Rd Montrose VIC 3765",
    "addr:housenumber":"1",
    "addr:postcode":"3765",
    "addr:street":"Browns Rd",
    "iso:country":"AU",
    "sg:address":"1 Browns Rd",
    "sg:city":"Montrose",
    "sg:classifiers":[
        {
            "category":"Professional",
            "subcategory":"Business Services",
            "type":"Services"
        }
    ],
    "sg:phone":"+61 3 9728 5141",
    "sg:postcode":"3765",
    "sg:province":"VIC",
    "sg:tags":[
        "drafting"
    ],
    "wof:name":"R L Design Engineering",
    "wof:placetype":"venue"
},
  "geometry": {"coordinates":[145.353805542,-37.8163833618],"type":"Point"}
}