{
  "type": "Feature",
  "properties": {
    "iso:country":"AU",
    "sg:address":"138 Cathedral St",
    "sg:city":"Woolloomooloo",
    "sg:classifiers":[
        {
            "category":"Professional",
            "subcategory":"Art Services",
            "type":"Services"
        }
    ],
    "sg:phone":"+61 2 9368 1234",
    "sg:postcode":"2011",
    "sg:province":"NSW",
    "sg:tags":[
        "interior",
        "designer"
    ],
    "wof:name":"Hare & Klein Pty Ltd",
    "wof:placetype":"venue"
},
  "geometry": {"coordinates":[151.218185425,-33.872467041],"type":"Point"}
}