{
  "type": "Feature",
  "properties": {
    "iso:country":"AU",
    "sg:address":"181 Bigge St",
    "sg:city":"Liverpool",
    "sg:classifiers":[
        {
            "category":"Health Services",
            "subcategory":"Doctor",
            "type":"Services"
        }
    ],
    "sg:phone":"+61 2 9822 4288",
    "sg:postcode":"2170",
    "sg:province":"NSW",
    "sg:tags":[
        "medical",
        "practitioner"
    ],
    "wof:name":"Rail David",
    "wof:placetype":"venue"
},
  "geometry": {"coordinates":[150.92684936500001,-33.9221496582],"type":"Point"}
}