{
  "type": "Feature",
  "properties": {
    "iso:country":"AU",
    "sg:address":"17566 Bass Hwy",
    "sg:city":"Boat Harbour",
    "sg:classifiers":[
        {
            "category":"Commercial Area",
            "type":"Public Place"
        }
    ],
    "sg:phone":"+61 417 147 903",
    "sg:postcode":"7321",
    "sg:province":"TAS",
    "sg:tags":[
        "heavy",
        "carrier"
    ],
    "wof:name":"Cooper D A",
    "wof:placetype":"venue"
},
  "geometry": {"coordinates":[145.62043800000001,-40.952965],"type":"Point"}
}