{
  "type": "Feature",
  "properties": {
    "addr:full":"364 Bong Bong St Bowral NSW 2576",
    "addr:housenumber":"364",
    "addr:postcode":"2576",
    "addr:street":"Bong Bong St",
    "iso:country":"AU",
    "sg:address":"364 Bong Bong St",
    "sg:city":"Bowral",
    "sg:classifiers":[
        {
            "category":"Food & Beverages",
            "subcategory":"Bakery",
            "type":"Retail Goods"
        }
    ],
    "sg:phone":"+61 2 4862 4001",
    "sg:postcode":"2576",
    "sg:province":"NSW",
    "sg:tags":[
        "baker"
    ],
    "wof:name":"Big L's Bakery Cafe",
    "wof:placetype":"venue"
},
  "geometry": {"coordinates":[150.417694092,-34.480381012],"type":"Point"}
}