{
  "type": "Feature",
  "properties": {
    "addr:full":"Lot 4 Campbells Lane Goulburn NSW 2580",
    "addr:postcode":"2580",
    "addr:street":"Campbells Lane",
    "iso:country":"AU",
    "sg:address":"Lot 4",
    "sg:city":"Campbells Lane Goulburn",
    "sg:classifiers":[
        {
            "category":"Farming",
            "subcategory":"Farm & Veterinary Services",
            "type":"Manufacturing & Wholesale Goods"
        }
    ],
    "sg:phone":"+61 2 4821 3362",
    "sg:postcode":"2580",
    "sg:province":"NSW",
    "sg:tags":[
        "contracting"
    ],
    "wof:name":"Grahame Chambers Agricultural Contractor",
    "wof:placetype":"venue"
},
  "geometry": {"coordinates":[149.74900817899999,-34.6914138794],"type":"Point"}
}