{
  "type": "Feature",
  "properties": {
    "addr:full":"62a Harrow Rd Stanmore NSW 2048",
    "addr:housenumber":"62a",
    "addr:postcode":"2048",
    "addr:street":"Harrow Rd",
    "iso:country":"AU",
    "sg:address":"62a Harrow Rd",
    "sg:city":"Stanmore",
    "sg:classifiers":[
        {
            "category":"Professional",
            "subcategory":"Art Services",
            "type":"Services"
        }
    ],
    "sg:phone":"+61 2 9519 2449",
    "sg:postcode":"2048",
    "sg:province":"NSW",
    "sg:tags":[
        "decorator",
        "painter"
    ],
    "wof:name":"Ammit F C & Son",
    "wof:placetype":"venue"
},
  "geometry": {"coordinates":[151.16716,-33.89476],"type":"Point"}
}