{
  "type": "Feature",
  "properties": {
    "addr:full":"87 Hipwood St Norman Park QLD 4170",
    "addr:housenumber":"87",
    "addr:postcode":"4170",
    "addr:street":"Hipwood St",
    "iso:country":"AU",
    "sg:address":"87 Hipwood St",
    "sg:city":"Norman Park",
    "sg:classifiers":[
        {
            "category":"Building & Trades",
            "subcategory":"Construction",
            "type":"Services"
        }
    ],
    "sg:phone":"+61 7 3899 5297",
    "sg:postcode":"4170",
    "sg:province":"QLD",
    "sg:tags":[
        "underpinning"
    ],
    "wof:name":"Augerpile Drilling & Underpinning Pty Ltd",
    "wof:placetype":"venue"
},
  "geometry": {"coordinates":[153.06480407699999,-27.4747772217],"type":"Point"}
}