{
  "type": "Feature",
  "properties": {
    "addr:full":"78 East St Narrandera NSW 2700",
    "addr:housenumber":"78",
    "addr:postcode":"2700",
    "addr:street":"East St",
    "iso:country":"AU",
    "sg:address":"78 East St",
    "sg:city":"Narrandera",
    "sg:classifiers":[
        {
            "category":"Communications",
            "subcategory":"Film & Video Production",
            "type":"Services"
        }
    ],
    "sg:phone":"+61 2 6959 2622",
    "sg:postcode":"2700",
    "sg:province":"NSW",
    "sg:tags":[
        "dvd",
        "library"
    ],
    "wof:name":"Narrandera Video World",
    "wof:placetype":"venue"
},
  "geometry": {"coordinates":[146.553344727,-34.7446098328],"type":"Point"}
}