{
  "type": "Feature",
  "properties": {
    "addr:full":"90 Elvian Rd Woori Yallock VIC 3139",
    "addr:housenumber":"90",
    "addr:postcode":"3139",
    "addr:street":"Elvian Rd",
    "iso:country":"AU",
    "sg:address":"90 Elvian Rd",
    "sg:city":"Woori Yallock",
    "sg:classifiers":[
        {
            "category":"Farming",
            "subcategory":"Livestock Farm",
            "type":"Manufacturing & Wholesale Goods"
        }
    ],
    "sg:phone":"+61 3 5961 5698",
    "sg:postcode":"3139",
    "sg:province":"VIC",
    "sg:tags":[
        "agistment"
    ],
    "wof:name":"D & J R Long",
    "wof:placetype":"venue"
},
  "geometry": {"coordinates":[145.523361206,-37.7827911377],"type":"Point"}
}