{
  "type": "Feature",
  "properties": {
    "iso:country":"AU",
    "sg:address":"73 Ducat St",
    "sg:city":"Tweed Heads",
    "sg:classifiers":[
        {
            "category":"Professional",
            "type":"Services"
        }
    ],
    "sg:phone":"+61 409 363 355",
    "sg:postcode":"2485",
    "sg:province":"NSW",
    "sg:tags":[
        "auctioneer"
    ],
    "wof:name":"John Guinery-Smith",
    "wof:placetype":"venue"
},
  "geometry": {"coordinates":[153.526245117,-28.1825675964],"type":"Point"}
}