{
  "type": "Feature",
  "properties": {
    "addr:full":"20 Morgan St Hindmarsh West SA 5007",
    "addr:housenumber":"20",
    "addr:postcode":"5007",
    "addr:street":"Morgan St",
    "iso:country":"AU",
    "sg:address":"20 Morgan St",
    "sg:city":"Hindmarsh West",
    "sg:classifiers":[
        {
            "category":"Sports & Exercise",
            "subcategory":"Gym",
            "type":"Entertainment"
        }
    ],
    "sg:phone":"+61 8 8346 3465",
    "sg:postcode":"5007",
    "sg:province":"SA",
    "sg:tags":[
        "health",
        "fitness"
    ],
    "wof:name":"Roscoe's Massage Clinic",
    "wof:placetype":"venue"
},
  "geometry": {"coordinates":[138.56117248499999,-34.9004364014],"type":"Point"}
}