{
  "type": "Feature",
  "properties": {
    "addr:full":"F4 / 50 Hinderson Rd Rowville VIC 3178",
    "addr:postcode":"3178",
    "addr:street":"/ 50 Hinderson Rd",
    "iso:country":"AU",
    "sg:address":"F4 / 50 Hinderson Rd",
    "sg:city":"Rowville",
    "sg:classifiers":[
        {
            "category":"Retail",
            "subcategory":"Repair Shop",
            "type":"Services"
        }
    ],
    "sg:phone":"+61 1300 304 704",
    "sg:postcode":"3178",
    "sg:province":"VIC",
    "sg:tags":[
        "restorer",
        "repairer",
        "carpet"
    ],
    "wof:name":"High Craft Carpet Cleaning",
    "wof:placetype":"venue"
},
  "geometry": {"coordinates":[145.245697022,-37.9051399231],"type":"Point"}
}