{
  "type": "Feature",
  "properties": {
    "addr:full":"2 - 32 Gledsdale Rd Hallett Cove SA 5158",
    "addr:housenumber":"32",
    "addr:postcode":"5158",
    "addr:street":"2;Gledsdale Rd",
    "iso:country":"AU",
    "sg:address":"2 - 32 Gledsdale Rd",
    "sg:city":"Hallett Cove",
    "sg:classifiers":[
        {
            "category":"Education",
            "subcategory":"School",
            "type":"Public Place"
        }
    ],
    "sg:phone":"+61 8 8392 1020",
    "sg:postcode":"5158",
    "sg:province":"SA",
    "sg:tags":[
        "state",
        "except",
        "nsw"
    ],
    "wof:name":"Hallett Cove R-12 School",
    "wof:placetype":"venue"
},
  "geometry": {"coordinates":[138.50999450699999,-35.0777397156],"type":"Point"}
}