{
  "type": "Feature",
  "properties": {
    "addr:full":"23 Queen St Harrisville QLD 4307",
    "addr:housenumber":"23",
    "addr:postcode":"4307",
    "addr:street":"Queen St",
    "iso:country":"AU",
    "sg:address":"23 Queen St",
    "sg:city":"Harrisville",
    "sg:classifiers":[
        {
            "category":"Building & Trades",
            "subcategory":"Plumbing",
            "type":"Services"
        }
    ],
    "sg:phone":"+61 7 5467 1228",
    "sg:postcode":"4307",
    "sg:province":"QLD",
    "sg:tags":[
        "plumber",
        "gasfitters"
    ],
    "wof:name":"Carson K D",
    "wof:placetype":"venue"
},
  "geometry": {"coordinates":[152.66784668,-27.811258316],"type":"Point"}
}