{
  "type": "Feature",
  "properties": {
    "addr:full":"16 Fullview Crs Buderim QLD 4556",
    "addr:housenumber":"16",
    "addr:postcode":"4556",
    "addr:street":"Fullview Crs",
    "iso:country":"AU",
    "sg:address":"16 Fullview Crs",
    "sg:city":"Buderim",
    "sg:classifiers":[
        {
            "category":"Arts & Performance",
            "subcategory":"Art Gallery",
            "type":"Entertainment"
        }
    ],
    "sg:phone":"+61 7 5445 5859",
    "sg:postcode":"4556",
    "sg:province":"QLD",
    "wof:name":"Jack Russell Art Galleries",
    "wof:placetype":"venue"
},
  "geometry": {"coordinates":[153.09310913100001,-26.6773891449],"type":"Point"}
}