{
  "type": "Feature",
  "properties": {
    "addr:full":"11 North St Mt Colah NSW 2079",
    "addr:housenumber":"11",
    "addr:postcode":"2079",
    "addr:street":"North St Mt Colah",
    "iso:country":"AU",
    "sg:address":"11 North St",
    "sg:city":"Mt Colah",
    "sg:classifiers":[
        {
            "category":"Utilities",
            "subcategory":"Electric",
            "type":"Services"
        }
    ],
    "sg:phone":"+61 2 9940 5599",
    "sg:postcode":"2079",
    "sg:province":"NSW",
    "sg:tags":[
        "electrical",
        "contractor"
    ],
    "wof:name":"Sydney Poles & Power Lines Pty Ltd",
    "wof:placetype":"venue"
},
  "geometry": {"coordinates":[151.11256408700001,-33.6653671265],"type":"Point"}
}