{
  "type": "Feature",
  "properties": {
    "addr:full":"252a Commercial St West Mt Gambier SA 5290",
    "addr:housenumber":"252a",
    "addr:postcode":"5290",
    "addr:street":"Commercial St West",
    "iso:country":"AU",
    "sg:address":"252a Commercial St West",
    "sg:city":"Mt Gambier",
    "sg:classifiers":[
        {
            "category":"Government",
            "subcategory":"Post Office",
            "type":"Public Place"
        }
    ],
    "sg:phone":"+61 8 8725 2922",
    "sg:postcode":"5290",
    "sg:province":"SA",
    "sg:tags":[
        "postal"
    ],
    "wof:name":"Australia Post",
    "wof:placetype":"venue"
},
  "geometry": {"coordinates":[140.76329000000001,-37.822723],"type":"Point"}
}