{
  "type": "Feature",
  "properties": {
    "addr:full":"1/ 1 Elysium Rd Carrara QLD 4211",
    "addr:housenumber":"/ 1",
    "addr:postcode":"4211",
    "addr:street":"Elysium Rd",
    "iso:country":"AU",
    "sg:address":"1/ 1 Elysium Rd",
    "sg:city":"Carrara",
    "sg:classifiers":[
        {
            "category":"Home & Garden",
            "subcategory":"Building Materials",
            "type":"Retail Goods"
        }
    ],
    "sg:phone":"+61 7 5525 1153",
    "sg:postcode":"4211",
    "sg:province":"QLD",
    "sg:tags":[
        "wall",
        "frame",
        "truss",
        "roof"
    ],
    "wof:name":"Gold Coast Steel House Frames",
    "wof:placetype":"venue"
},
  "geometry": {"coordinates":[153.35304260300001,-28.0332393646],"type":"Point"}
}