{
  "type": "Feature",
  "properties": {
    "addr:full":"35 Playne St Frankston VIC 3199",
    "addr:housenumber":"35",
    "addr:postcode":"3199",
    "addr:street":"Playne St",
    "iso:country":"AU",
    "sg:address":"35 Playne St",
    "sg:city":"Frankston",
    "sg:classifiers":[
        {
            "category":"Home & Garden",
            "subcategory":"Building Materials",
            "type":"Retail Goods"
        }
    ],
    "sg:phone":"+61 3 9783 2882",
    "sg:postcode":"3199",
    "sg:province":"VIC",
    "sg:tags":[
        "fitting",
        "door"
    ],
    "wof:name":"Frankston Door & Window Installations",
    "wof:placetype":"venue"
},
  "geometry": {"coordinates":[145.12257385300001,-38.1448707581],"type":"Point"}
}