{
  "type": "Feature",
  "properties": {
    "iso:country":"AU",
    "sg:address":"249 Bungower Rd",
    "sg:city":"Somerville",
    "sg:classifiers":[
        {
            "category":"Sports & Exercise",
            "subcategory":"Gym",
            "type":"Entertainment"
        }
    ],
    "sg:phone":"+61 3 5977 6040",
    "sg:postcode":"3912",
    "sg:province":"VIC",
    "sg:tags":[
        "pilate",
        "method"
    ],
    "wof:name":"Pilates On Bungower",
    "wof:placetype":"venue"
},
  "geometry": {"coordinates":[145.15550231899999,-38.2360534668],"type":"Point"}
}