{
  "type": "Feature",
  "properties": {
    "iso:country":"AU",
    "sg:address":"406 Kiewa St",
    "sg:city":"Albury",
    "sg:classifiers":[
        {
            "category":"Shopping",
            "subcategory":"Stationery & Office Supplies",
            "type":"Retail Goods"
        }
    ],
    "sg:phone":"+61 2 6021 3266",
    "sg:postcode":"2640",
    "sg:province":"NSW",
    "sg:tags":[
        "equipment",
        "facsimile"
    ],
    "wof:name":"North Eastern Business Machines",
    "wof:placetype":"venue"
},
  "geometry": {"coordinates":[146.916015625,-36.0796127319],"type":"Point"}
}