{
  "type": "Feature",
  "properties": {
    "addr:full":"PO Box 525 Curtin ACT 2605",
    "addr:postcode":"2605",
    "iso:country":"AU",
    "sg:address":"PO Box 525",
    "sg:city":"Curtin",
    "sg:classifiers":[
        {
            "category":"Professional",
            "subcategory":"Art Services",
            "type":"Services"
        }
    ],
    "sg:phone":"+61 2 6232 4350",
    "sg:postcode":"2605",
    "sg:province":"ACT",
    "sg:tags":[
        "graphic",
        "designer"
    ],
    "wof:name":"Lets Create",
    "wof:placetype":"venue"
},
  "geometry": {"coordinates":[149.081298828,-35.3241615295],"type":"Point"}
}