{
  "type": "Feature",
  "properties": {
    "addr:full":"91 Station St Burwood VIC 3125",
    "addr:housenumber":"91",
    "addr:postcode":"3125",
    "addr:street":"Station St",
    "iso:country":"AU",
    "sg:address":"91 Station St",
    "sg:city":"Burwood",
    "sg:classifiers":[
        {
            "category":"Professional",
            "subcategory":"Art Services",
            "type":"Services"
        }
    ],
    "sg:phone":"+61 3 9830 6417",
    "sg:postcode":"3125",
    "sg:province":"VIC",
    "sg:tags":[
        "picture",
        "frame",
        "framing"
    ],
    "wof:name":"Spectrum 4 Pty Ltd",
    "wof:placetype":"venue"
},
  "geometry": {"coordinates":[145.12013244600001,-37.8485145569],"type":"Point"}
}