{
  "type": "Feature",
  "properties": {
    "iso:country":"AU",
    "sg:address":"94 Elizabeth St",
    "sg:city":"Melbourne",
    "sg:classifiers":[
        {
            "category":"Shopping",
            "subcategory":"Jewelry",
            "type":"Retail Goods"
        }
    ],
    "sg:phone":"+61 3 9654 8357",
    "sg:postcode":"3000",
    "sg:province":"VIC",
    "sg:tags":[
        "jeweller"
    ],
    "wof:name":"Michaels Handmade Jewellery",
    "wof:placetype":"venue"
},
  "geometry": {"coordinates":[144.964019775,-37.8157310486],"type":"Point"}
}