{
  "type": "Feature",
  "properties": {
    "iso:country":"AU",
    "sg:address":"Lot 15 Pioneer Drv",
    "sg:city":"Bindoon",
    "sg:classifiers":[
        {
            "category":"Utilities",
            "subcategory":"Electric",
            "type":"Services"
        }
    ],
    "sg:phone":"+61 428 945 385",
    "sg:postcode":"6502",
    "sg:province":"WA",
    "sg:tags":[
        "electrical",
        "contractor"
    ],
    "wof:name":"RDS Electrics",
    "wof:placetype":"venue"
},
  "geometry": {"coordinates":[116.088448,-31.386576],"type":"Point"}
}