{
  "type": "Feature",
  "properties": {
    "addr:full":"2 Bolton St Horsham VIC 3400",
    "addr:housenumber":"2",
    "addr:postcode":"3400",
    "addr:street":"Bolton St",
    "iso:country":"AU",
    "sg:address":"2 Bolton St",
    "sg:city":"Horsham",
    "sg:classifiers":[
        {
            "category":"Utilities",
            "subcategory":"Water",
            "type":"Services"
        }
    ],
    "sg:phone":"+61 3 5382 5075",
    "sg:postcode":"3400",
    "sg:province":"VIC",
    "sg:tags":[
        "hot",
        "system"
    ],
    "wof:name":"Dawson's Plumbing & Gasfitting Pty Ltd",
    "wof:placetype":"venue"
},
  "geometry": {"coordinates":[142.20428466800001,-36.7206993103],"type":"Point"}
}