{
  "type": "Feature",
  "properties": {
    "iso:country":"AU",
    "sg:address":"760 Ingham Rd",
    "sg:city":"Bohle",
    "sg:classifiers":[
        {
            "category":"Transit Center",
            "subcategory":"Freight",
            "type":"Transportation"
        }
    ],
    "sg:phone":"+61 7 4774 4332",
    "sg:postcode":"4818",
    "sg:province":"QLD",
    "sg:tags":[
        "forklift",
        "truck"
    ],
    "wof:name":"Independent Forklift Services (NQ) Pty Ltd",
    "wof:placetype":"venue"
},
  "geometry": {"coordinates":[146.729645,-19.260839],"type":"Point"}
}