{
  "type": "Feature",
  "properties": {
    "addr:full":"5 / 57 Marina Blv Cullen Bay NT 0820",
    "addr:housenumber":"/ 57",
    "addr:postcode":"nt 0820",
    "addr:street":"Marina Blv Cullen",
    "iso:country":"AU",
    "sg:address":"5 / 57",
    "sg:city":"Marina Blv Cullen Bay",
    "sg:classifiers":[
        {
            "category":"Banks & Credit Unions",
            "subcategory":"Investment Brokerage",
            "type":"Services"
        }
    ],
    "sg:phone":"+61 8 8982 2888",
    "sg:postcode":"0820",
    "sg:province":"NT",
    "sg:tags":[
        "share",
        "broker",
        "stock"
    ],
    "wof:name":"Baker Young Stockbrokers",
    "wof:placetype":"venue"
},
  "geometry": {"coordinates":[130.822067261,-12.4509429932],"type":"Point"}
}