{
  "type": "Feature",
  "properties": {
    "addr:full":"313 Pacific Hwy Swansea South NSW 2281",
    "addr:housenumber":"313",
    "addr:postcode":"2281",
    "addr:street":"Pacific Hwy",
    "iso:country":"AU",
    "sg:address":"313 Pacific Hwy",
    "sg:city":"Swansea South",
    "sg:classifiers":[
        {
            "category":"Retail",
            "subcategory":"Repair Shop",
            "type":"Services"
        }
    ],
    "sg:phone":"+61 2 4972 1550",
    "sg:postcode":"2281",
    "sg:province":"NSW",
    "sg:tags":[
        "upholsterer"
    ],
    "wof:name":"Whitbread Upholstery",
    "wof:placetype":"venue"
},
  "geometry": {"coordinates":[151.626953125,-33.1139984131],"type":"Point"}
}