{
  "type": "Feature",
  "properties": {
    "iso:country":"AU",
    "sg:address":"Blight Rd",
    "sg:city":"Penola",
    "sg:classifiers":[
        {
            "category":"Building & Trades",
            "subcategory":"Landscaping Services",
            "type":"Services"
        }
    ],
    "sg:phone":"+61 8 8737 3042",
    "sg:postcode":"5277",
    "sg:province":"SA",
    "sg:tags":[
        "grazier"
    ],
    "wof:name":"Pembroke Pastoral Co",
    "wof:placetype":"venue"
},
  "geometry": {"coordinates":[140.891342,-37.35268],"type":"Point"}
}