{
  "type": "Feature",
  "properties": {
    "iso:country":"AU",
    "sg:address":"671- 685 Elizabeth Drv",
    "sg:city":"Edensor Park",
    "sg:classifiers":[
        {
            "category":"Building & Trades",
            "subcategory":"Construction",
            "type":"Services"
        }
    ],
    "sg:phone":"+61 2 9610 4120",
    "sg:postcode":"2176",
    "sg:province":"NSW",
    "sg:tags":[
        "contractor"
    ],
    "wof:name":"Bernard G & M Builders",
    "wof:placetype":"venue"
},
  "geometry": {"coordinates":[150.899093628,-33.8510971069],"type":"Point"}
}