{
  "type": "Feature",
  "properties": {
    "addr:full":"10 Masthead Drv Cleveland QLD 4163",
    "addr:housenumber":"10",
    "addr:postcode":"4163",
    "addr:street":"Masthead Drv",
    "iso:country":"AU",
    "sg:address":"10 Masthead Drv",
    "sg:city":"Cleveland",
    "sg:classifiers":[
        {
            "category":"Professional",
            "subcategory":"Computer Services",
            "type":"Services"
        }
    ],
    "sg:phone":"+61 7 3286 1422",
    "sg:postcode":"4163",
    "sg:province":"QLD",
    "sg:tags":[
        "package",
        "software"
    ],
    "wof:name":"Dynamic Retail Systems Pty Ltd",
    "wof:placetype":"venue"
},
  "geometry": {"coordinates":[153.269332886,-27.5231990814],"type":"Point"}
}