{
  "type": "Feature",
  "properties": {
    "addr:full":"Green Point Rd Oyster Bay NSW 2225",
    "addr:postcode":"2225",
    "addr:street":"Green;Rd",
    "iso:country":"AU",
    "sg:address":"Green Point Rd",
    "sg:city":"Oyster Bay",
    "sg:classifiers":[
        {
            "category":"Social Services",
            "subcategory":"Child Care",
            "type":"Services"
        }
    ],
    "sg:phone":"+61 2 9528 5003",
    "sg:postcode":"2225",
    "sg:province":"NSW",
    "wof:name":"Point Pre-School Corporation",
    "wof:placetype":"venue"
},
  "geometry": {"coordinates":[151.07420349099999,-34.0071182251],"type":"Point"}
}