{
  "type": "Feature",
  "properties": {
    "addr:full":"Suite 4/ 318 Old Cleveland Rd Coorparoo QLD 4151",
    "addr:housenumber":"/ 318",
    "addr:postcode":"4151",
    "addr:street":"Old Cleveland Rd",
    "iso:country":"AU",
    "sg:address":"Suite 4/ 318 Old Cleveland Rd",
    "sg:city":"Coorparoo",
    "sg:classifiers":[
        {
            "category":"Professional",
            "subcategory":"Management & Consulting",
            "type":"Services"
        }
    ],
    "sg:phone":"+61 1800 236 687",
    "sg:postcode":"4151",
    "sg:province":"QLD",
    "sg:tags":[
        "consultant"
    ],
    "wof:name":"Certiorari Management Consultants",
    "wof:placetype":"venue"
},
  "geometry": {"coordinates":[153.05982971200001,-27.4939537048],"type":"Point"}
}