{
  "type": "Feature",
  "properties": {
    "addr:full":"92 Spencer Rd Killara NSW 2071",
    "addr:housenumber":"92",
    "addr:postcode":"2071",
    "addr:street":"Spencer Rd",
    "iso:country":"AU",
    "sg:address":"92 Spencer Rd",
    "sg:city":"Killara",
    "sg:classifiers":[
        {
            "category":"Professional",
            "subcategory":"Management & Consulting",
            "type":"Services"
        }
    ],
    "sg:phone":"+61 2 9418 2405",
    "sg:postcode":"2071",
    "sg:province":"NSW",
    "sg:tags":[
        "consultant",
        "energy"
    ],
    "wof:name":"Wilkenfeld George & Associates",
    "wof:placetype":"venue"
},
  "geometry": {"coordinates":[151.146316528,-33.7669639587],"type":"Point"}
}