{
  "type": "Feature",
  "properties": {
    "iso:country":"AU",
    "sg:address":"815 Doncaster Rd",
    "sg:city":"Doncaster",
    "sg:classifiers":[
        {
            "category":"Health Services",
            "subcategory":"Dentist",
            "type":"Services"
        }
    ],
    "sg:phone":"+61 3 9848 9422",
    "sg:postcode":"3108",
    "sg:province":"VIC",
    "wof:name":"Lee Jenny P S Dr",
    "wof:placetype":"venue"
},
  "geometry": {"coordinates":[145.139572144,-37.7863388062],"type":"Point"}
}