{
  "type": "Feature",
  "properties": {
    "iso:country":"AU",
    "sg:address":"97 William St",
    "sg:city":"Devonport",
    "sg:classifiers":[
        {
            "category":"Health Services",
            "subcategory":"Health Practitioner",
            "type":"Services"
        }
    ],
    "sg:phone":"+61 3 6423 6835",
    "sg:postcode":"7310",
    "sg:province":"TAS",
    "sg:tags":[
        "naturopath"
    ],
    "wof:name":"F G Chinese Medicine Clinic",
    "wof:placetype":"venue"
},
  "geometry": {"coordinates":[146.349884033,-41.1810722351],"type":"Point"}
}