{
  "type": "Feature",
  "properties": {
    "iso:country":"AU",
    "sg:address":"323 Keilor Rd",
    "sg:city":"Essendon",
    "sg:classifiers":[
        {
            "category":"Social Services",
            "type":"Services"
        }
    ],
    "sg:phone":"+61 3 9374 3967",
    "sg:postcode":"3040",
    "sg:province":"VIC",
    "sg:tags":[
        "disabled",
        "person",
        "equipment"
    ],
    "wof:name":"Custom Scooters",
    "wof:placetype":"venue"
},
  "geometry": {"coordinates":[144.89517211899999,-37.7385215759],"type":"Point"}
}