{
  "type": "Feature",
  "properties": {
    "iso:country":"AU",
    "sg:address":"Shop 50/ 52 Currie St",
    "sg:city":"Nambour",
    "sg:classifiers":[
        {
            "category":"Health Services",
            "subcategory":"Doctor",
            "type":"Services"
        }
    ],
    "sg:phone":"+61 7 5441 6666",
    "sg:postcode":"4560",
    "sg:province":"QLD",
    "sg:tags":[
        "medical",
        "practitioner"
    ],
    "wof:name":"Bull Larry Dr",
    "wof:placetype":"venue"
},
  "geometry": {"coordinates":[152.959075928,-26.625585556],"type":"Point"}
}