{
  "type": "Feature",
  "properties": {
    "iso:country":"AU",
    "sg:address":"192 Beamish St",
    "sg:city":"Campsie",
    "sg:classifiers":[
        {
            "category":"Food & Beverages",
            "subcategory":"Meat & Fish",
            "type":"Retail Goods"
        }
    ],
    "sg:phone":"+61 2 9789 2361",
    "sg:postcode":"2194",
    "sg:province":"NSW",
    "sg:tags":[
        "seafood"
    ],
    "wof:name":"A J's Seafood",
    "wof:placetype":"venue"
},
  "geometry": {"coordinates":[151.103561,-33.910786],"type":"Point"}
}