{
  "type": "Feature",
  "properties": {
    "addr:full":"Unit 1 121 Albert St Osborne Park WA 6017",
    "addr:housenumber":"121",
    "addr:postcode":"6017",
    "addr:street":"Albert St",
    "iso:country":"AU",
    "sg:address":"Unit 1 121 Albert St",
    "sg:city":"Osborne Park",
    "sg:classifiers":[
        {
            "category":"Personal",
            "subcategory":"Beauty Salon",
            "type":"Services"
        }
    ],
    "sg:phone":"+61 405 129 095",
    "sg:postcode":"6017",
    "sg:province":"WA",
    "sg:tags":[
        "hairdresser"
    ],
    "wof:name":"Scissor Sister",
    "wof:placetype":"venue"
},
  "geometry": {"coordinates":[115.825439453,-31.9024143219],"type":"Point"}
}