{
  "type": "Feature",
  "properties": {
    "iso:country":"AU",
    "sg:address":"8 Augustus Rd",
    "sg:city":"Cairns North",
    "sg:classifiers":[
        {
            "category":"Utilities",
            "subcategory":"Electric",
            "type":"Services"
        }
    ],
    "sg:phone":"+61 420 300 656",
    "sg:postcode":"4870",
    "sg:province":"QLD",
    "sg:tags":[
        "electrical",
        "contractor"
    ],
    "wof:name":"ADK Civil Pty Ltd",
    "wof:placetype":"venue"
},
  "geometry": {"coordinates":[145.72848510700001,-16.9387073517],"type":"Point"}
}