{
  "type": "Feature",
  "properties": {
    "addr:full":"2 Juniper Rd Wantirna VIC 3152",
    "addr:housenumber":"2",
    "addr:postcode":"3152",
    "addr:street":"Juniper Rd",
    "iso:country":"AU",
    "sg:address":"2 Juniper Rd",
    "sg:city":"Wantirna",
    "sg:classifiers":[
        {
            "category":"Banks & Credit Unions",
            "subcategory":"Investment Brokerage",
            "type":"Services"
        }
    ],
    "sg:phone":"+61 3 9660 5904",
    "sg:postcode":"3152",
    "sg:province":"VIC",
    "wof:name":"Bleakleys Ltd",
    "wof:placetype":"venue"
},
  "geometry": {"coordinates":[145.222579956,-37.8419685364],"type":"Point"}
}