{
  "type": "Feature",
  "properties": {
    "iso:country":"AU",
    "sg:address":"14A David Muir Drv",
    "sg:city":"Slade Point",
    "sg:classifiers":[
        {
            "category":"Home & Garden",
            "subcategory":"Building Materials",
            "type":"Retail Goods"
        }
    ],
    "sg:phone":"+61 7 4955 6392",
    "sg:postcode":"4740",
    "sg:province":"QLD",
    "sg:tags":[
        "tile",
        "roofing"
    ],
    "wof:name":"Boral Roofing",
    "wof:placetype":"venue"
},
  "geometry": {"coordinates":[149.21264600000001,-21.090891],"type":"Point"}
}