{
  "type": "Feature",
  "properties": {
    "addr:full":"64-68 Collie St Fyshwick ACT 2609",
    "addr:housenumber":"64-68",
    "addr:postcode":"2609",
    "addr:street":"Collie St",
    "iso:country":"AU",
    "sg:address":"64-68 Collie St",
    "sg:city":"Fyshwick",
    "sg:classifiers":[
        {
            "category":"Retail",
            "subcategory":"Storage",
            "type":"Services"
        }
    ],
    "sg:phone":"+61 2 6162 0040",
    "sg:postcode":"2609",
    "sg:province":"ACT",
    "sg:website":"http://www.fyshwickselfstorage.com.au",
    "wof:name":"Fyshwick Self Storage",
    "wof:placetype":"venue"
},
  "geometry": {"coordinates":[149.180709839,-35.3295898438],"type":"Point"}
}