{
  "type": "Feature",
  "properties": {
    "addr:full":"1272 North East Rd Tea Tree Gully SA 5091",
    "addr:housenumber":"1272",
    "addr:postcode":"5091",
    "addr:street":"North East Rd Tea Tree",
    "iso:country":"AU",
    "sg:address":"1272 North East Rd",
    "sg:city":"Tea Tree Gully",
    "sg:classifiers":[
        {
            "category":"Retail",
            "subcategory":"Auto Repair",
            "type":"Services"
        }
    ],
    "sg:phone":"+61 8 8396 1511",
    "sg:postcode":"5091",
    "sg:province":"SA",
    "sg:tags":[
        "repairer",
        "motor",
        "engineer"
    ],
    "wof:name":"BP St Agnes",
    "wof:placetype":"venue"
},
  "geometry": {"coordinates":[138.72703552199999,-34.8209075928],"type":"Point"}
}