{
  "type": "Feature",
  "properties": {
    "addr:full":"Shop 3 Centro Toombul QLD 4012",
    "addr:housenumber":"shop 3",
    "addr:postcode":"4012",
    "iso:country":"AU",
    "sg:address":"Shop 3 Centro",
    "sg:city":"Toombul",
    "sg:classifiers":[
        {
            "category":"Food & Beverages",
            "subcategory":"Specialty",
            "type":"Retail Goods"
        }
    ],
    "sg:phone":"+61 7 3266 3077",
    "sg:postcode":"4012",
    "sg:province":"QLD",
    "sg:tags":[
        "product",
        "health"
    ],
    "wof:name":"Healthy Life",
    "wof:placetype":"venue"
},
  "geometry": {"coordinates":[153.05982971200001,-27.4076595306],"type":"Point"}
}