{
  "type": "Feature",
  "properties": {
    "iso:country":"AU",
    "sg:address":"Oliver Rd",
    "sg:city":"Chatswood",
    "sg:classifiers":[
        {
            "category":"Education",
            "subcategory":"University",
            "type":"Public Place"
        }
    ],
    "sg:phone":"+61 2 9413 4562",
    "sg:postcode":"2067",
    "sg:province":"NSW",
    "sg:tags":[
        "college",
        "tertiary"
    ],
    "wof:name":"Macquarie Community College",
    "wof:placetype":"venue"
},
  "geometry": {"coordinates":[151.17820739699999,-33.7994270325],"type":"Point"}
}