{
  "type": "Feature",
  "properties": {
    "addr:full":"50 Pirie St Adelaide SA 5000",
    "addr:housenumber":"50",
    "addr:postcode":"5000",
    "addr:street":"Pirie St",
    "iso:country":"AU",
    "sg:address":"50 Pirie St",
    "sg:city":"Adelaide",
    "sg:classifiers":[
        {
            "category":"Cafe",
            "type":"Food & Drink"
        }
    ],
    "sg:phone":"+61 8 8212 9190",
    "sg:postcode":"5000",
    "sg:province":"SA",
    "wof:name":"Taste On Pirie",
    "wof:placetype":"venue"
},
  "geometry": {"coordinates":[138.6015625,-34.9255447388],"type":"Point"}
}