{
  "type": "Feature",
  "properties": {
    "addr:full":"66 Burn St Downer ACT 2602",
    "addr:housenumber":"66",
    "addr:postcode":"2602",
    "addr:street":"Burn St",
    "iso:country":"AU",
    "sg:address":"66 Burn St",
    "sg:city":"Downer",
    "sg:classifiers":[
        {
            "category":"Shopping",
            "subcategory":"Party Supplies",
            "type":"Retail Goods"
        }
    ],
    "sg:phone":"+61 2 6285 2508",
    "sg:postcode":"2602",
    "sg:province":"ACT",
    "sg:tags":[
        "children's"
    ],
    "wof:name":"Luv &#039;N&#039; It Produktionz",
    "wof:placetype":"venue"
},
  "geometry": {"coordinates":[149.15266418499999,-35.2463607788],"type":"Point"}
}