{
  "type": "Feature",
  "properties": {
    "addr:full":"389 Hargreaves St Bendigo VIC 3550",
    "addr:housenumber":"389",
    "addr:postcode":"3550",
    "addr:street":"Hargreaves St",
    "iso:country":"AU",
    "sg:address":"389 Hargreaves St",
    "sg:city":"Bendigo",
    "sg:classifiers":[
        {
            "category":"Organizations",
            "subcategory":"Non-profit Organization",
            "type":"Services"
        }
    ],
    "sg:phone":"+61 3 5441 7455",
    "sg:postcode":"3550",
    "sg:province":"VIC",
    "sg:tags":[
        "support",
        "disability",
        "organisation"
    ],
    "wof:name":"Victorian Deaf Society",
    "wof:placetype":"venue"
},
  "geometry": {"coordinates":[144.27804565400001,-36.7617950439],"type":"Point"}
}