{
  "type": "Feature",
  "properties": {
    "addr:full":"22 St Andrews Tce Port Lincoln SA 5606",
    "addr:housenumber":"22",
    "addr:postcode":"5606",
    "addr:street":"St Andrews Tce",
    "iso:country":"AU",
    "sg:address":"22 St",
    "sg:city":"Andrews Tce Port Lincoln",
    "sg:classifiers":[
        {
            "category":"Home & Garden",
            "subcategory":"Building Materials",
            "type":"Retail Goods"
        }
    ],
    "sg:phone":"+61 8 8683 1700",
    "sg:postcode":"5606",
    "sg:province":"SA",
    "sg:tags":[
        "supply"
    ],
    "wof:name":"Home Building Products & Selection Centre",
    "wof:placetype":"venue"
},
  "geometry": {"coordinates":[135.87356600000001,-34.738956],"type":"Point"}
}