{
  "type": "Feature",
  "properties": {
    "iso:country":"AU",
    "sg:address":"9 Labrina Ave",
    "sg:city":"Prospect",
    "sg:classifiers":[
        {
            "category":"Building & Trades",
            "subcategory":"Construction",
            "type":"Services"
        }
    ],
    "sg:phone":"+61 417 805 322",
    "sg:postcode":"5082",
    "sg:province":"SA",
    "sg:tags":[
        "earth",
        "excavating",
        "moving",
        "contractor"
    ],
    "wof:name":"All Excavations Prospect",
    "wof:placetype":"venue"
},
  "geometry": {"coordinates":[138.59500122099999,-34.8883476257],"type":"Point"}
}