{
  "type": "Feature",
  "properties": {
    "addr:full":"5 Leura Rd Double Bay NSW 2028",
    "addr:housenumber":"5",
    "addr:postcode":"2028",
    "addr:street":"Leura Rd",
    "iso:country":"AU",
    "sg:address":"5 Leura Rd",
    "sg:city":"Double Bay",
    "sg:classifiers":[
        {
            "category":"Health Services",
            "subcategory":"Health Practitioner",
            "type":"Services"
        }
    ],
    "sg:phone":"+61 2 9328 0501",
    "sg:postcode":"2028",
    "sg:province":"NSW",
    "sg:tags":[
        "acupuncture"
    ],
    "wof:name":"Phillips Mark",
    "wof:placetype":"venue"
},
  "geometry": {"coordinates":[151.24542236299999,-33.8782806396],"type":"Point"}
}