{
  "type": "Feature",
  "properties": {
    "addr:full":"72 King William Rd North Adelaide SA 5006",
    "addr:housenumber":"72",
    "addr:postcode":"5006",
    "addr:street":"King William Rd",
    "iso:country":"AU",
    "sg:address":"72 King William Rd",
    "sg:city":"North Adelaide",
    "sg:classifiers":[
        {
            "category":"Wholesale",
            "subcategory":"Medical Equipment & Supplies",
            "type":"Manufacturing & Wholesale Goods"
        }
    ],
    "sg:phone":"+61 8 8336 9857",
    "sg:postcode":"5006",
    "sg:province":"SA",
    "sg:tags":[
        "aids",
        "hearing"
    ],
    "wof:name":"North Adelaide Hearing Services",
    "wof:placetype":"venue"
},
  "geometry": {"coordinates":[138.598876953,-34.9107933044],"type":"Point"}
}