{
  "type": "Feature",
  "properties": {
    "iso:country":"AU",
    "sg:address":"PO Box 132",
    "sg:city":"Kenilworth",
    "sg:classifiers":[
        {
            "category":"Utilities",
            "subcategory":"Natural Gas",
            "type":"Services"
        }
    ],
    "sg:phone":"+61 7 5446 0507",
    "sg:postcode":"4574",
    "sg:province":"QLD",
    "sg:tags":[
        "supplier"
    ],
    "wof:name":"M.V. Gas",
    "wof:placetype":"venue"
},
  "geometry": {"coordinates":[152.727478,-26.59549],"type":"Point"}
}