{
  "type": "Feature",
  "properties": {
    "iso:country":"AU",
    "sg:address":"12 Russell St",
    "sg:city":"Essendon",
    "sg:classifiers":[
        {
            "category":"Professional",
            "subcategory":"Computer Services",
            "type":"Services"
        }
    ],
    "sg:phone":"+61 3 9326 2776",
    "sg:postcode":"3040",
    "sg:province":"VIC",
    "sg:tags":[
        "repairs",
        "upgrade",
        "equipment"
    ],
    "wof:name":"Mooness Computers",
    "wof:placetype":"venue"
},
  "geometry": {"coordinates":[144.916503906,-37.7558097839],"type":"Point"}
}