{
  "type": "Feature",
  "properties": {
    "iso:country":"AU",
    "sg:address":"10 Riverstone Pde",
    "sg:city":"Riverstone",
    "sg:classifiers":[
        {
            "category":"Fast Food",
            "type":"Food & Drink"
        }
    ],
    "sg:phone":"+61 2 9627 4585",
    "sg:postcode":"2765",
    "sg:province":"NSW",
    "sg:tags":[
        "away",
        "take"
    ],
    "wof:name":"Chargrill Cafe",
    "wof:placetype":"venue"
},
  "geometry": {"coordinates":[150.861038208,-33.6793441772],"type":"Point"}
}