{
  "type": "Feature",
  "properties": {
    "iso:country":"AU",
    "sg:address":"2/ 85 Foster St",
    "sg:city":"Dandenong",
    "sg:classifiers":[
        {
            "category":"Professional",
            "subcategory":"Accounting & Tax Preparation",
            "type":"Services"
        }
    ],
    "sg:phone":"+61 3 9708 5644",
    "sg:postcode":"3175",
    "sg:province":"VIC",
    "sg:tags":[
        "consultant",
        "taxation"
    ],
    "wof:name":"P & J Accounting Service Pty Ltd",
    "wof:placetype":"venue"
},
  "geometry": {"coordinates":[145.21220398,-37.9897766113],"type":"Point"}
}