{
  "type": "Feature",
  "properties": {
    "iso:country":"AU",
    "sg:address":"3 Quail Crt",
    "sg:city":"Cameron Park",
    "sg:classifiers":[
        {
            "category":"Manufacturing",
            "subcategory":"Glass & Minerals",
            "type":"Manufacturing & Wholesale Goods"
        }
    ],
    "sg:phone":"+61 2 4950 6445",
    "sg:postcode":"2285",
    "sg:province":"NSW",
    "sg:tags":[
        "case",
        "counter",
        "show"
    ],
    "wof:name":"Shane Kelly-Glass & Aluminium",
    "wof:placetype":"venue"
},
  "geometry": {"coordinates":[151.61834716800001,-32.9141998291],"type":"Point"}
}