{
  "type": "Feature",
  "properties": {
    "addr:full":"39a Ardagh Ave Kalgoorlie WA 6430",
    "addr:housenumber":"39a",
    "addr:postcode":"6430",
    "addr:street":"Ardagh Ave",
    "iso:country":"AU",
    "sg:address":"39a Ardagh Ave",
    "sg:city":"Kalgoorlie",
    "sg:classifiers":[
        {
            "category":"Professional",
            "subcategory":"Art Services",
            "type":"Services"
        }
    ],
    "sg:phone":"+61 8 9022 3039",
    "sg:postcode":"6430",
    "sg:province":"WA",
    "sg:tags":[
        "graphic",
        "designer"
    ],
    "wof:name":"JK Designs",
    "wof:placetype":"venue"
},
  "geometry": {"coordinates":[121.470733643,-30.7560806274],"type":"Point"}
}