{
  "type": "Feature",
  "properties": {
    "addr:full":"Mosman Park Shop 4 Mosman Park Shopng Cntr Monument St Mosman Park WA 6012",
    "addr:housenumber":"4",
    "addr:postcode":"6012",
    "addr:street":"Mosman Park Shopng;St",
    "iso:country":"AU",
    "sg:address":"Mosman Park Shop 4 Mosman Park Shopng Cntr Monument St",
    "sg:city":"Mosman Park",
    "sg:classifiers":[
        {
            "category":"Personal",
            "subcategory":"Beauty Salon",
            "type":"Services"
        }
    ],
    "sg:phone":"+61 8 9383 1559",
    "sg:postcode":"6012",
    "sg:province":"WA",
    "sg:tags":[
        "hairdresser"
    ],
    "wof:name":"Fabiani Group Hair Design",
    "wof:placetype":"venue"
},
  "geometry": {"coordinates":[115.760948181,-32.0141296387],"type":"Point"}
}