{
  "type": "Feature",
  "properties": {
    "addr:full":"Suite 2, 2 Kochia La Lindfield NSW 2070",
    "addr:housenumber":"2",
    "addr:postcode":"2070",
    "addr:street":"Kochia La Lindfield",
    "iso:country":"AU",
    "sg:address":"Suite 2, 2 Kochia La",
    "sg:city":"Lindfield",
    "sg:classifiers":[
        {
            "category":"Health Services",
            "subcategory":"Doctor",
            "type":"Services"
        }
    ],
    "sg:phone":"+61 2 9416 3871",
    "sg:postcode":"2070",
    "sg:province":"NSW",
    "sg:tags":[
        "medical",
        "practitioner"
    ],
    "wof:name":"Way Stephanie",
    "wof:placetype":"venue"
},
  "geometry": {"coordinates":[151.169555664,-33.7746543884],"type":"Point"}
}