{
  "type": "Feature",
  "properties": {
    "addr:full":"1/ 12 Export Drv Molendinar QLD 4214",
    "addr:housenumber":"/ 12",
    "addr:postcode":"4214",
    "addr:street":"Export Drv",
    "iso:country":"AU",
    "sg:address":"1/ 12 Export Drv",
    "sg:city":"Molendinar",
    "sg:classifiers":[
        {
            "category":"Building & Trades",
            "subcategory":"Construction",
            "type":"Services"
        }
    ],
    "sg:phone":"+61 7 5571 5661",
    "sg:postcode":"4214",
    "sg:province":"QLD",
    "sg:tags":[
        "fencing",
        "contractor"
    ],
    "wof:name":"A-Grade Aluminium",
    "wof:placetype":"venue"
},
  "geometry": {"coordinates":[153.36148071299999,-27.9689388275],"type":"Point"}
}