{
  "type": "Feature",
  "properties": {
    "iso:country":"AU",
    "sg:address":"11 Waratah St",
    "sg:city":"Mona Vale",
    "sg:classifiers":[
        {
            "category":"Health Services",
            "subcategory":"Doctor",
            "type":"Services"
        }
    ],
    "sg:phone":"+61 2 9999 4256",
    "sg:postcode":"2103",
    "sg:province":"NSW",
    "sg:tags":[
        "medical",
        "practitioner"
    ],
    "wof:name":"King A C",
    "wof:placetype":"venue"
},
  "geometry": {"coordinates":[151.30258178700001,-33.6775474548],"type":"Point"}
}