{
  "type": "Feature",
  "properties": {
    "iso:country":"AU",
    "sg:address":"125 Lytton Rd",
    "sg:city":"East Brisbane",
    "sg:classifiers":[
        {
            "category":"Real Estate",
            "subcategory":"Real Estate Agent",
            "type":"Services"
        }
    ],
    "sg:phone":"+61 7 3391 0571",
    "sg:postcode":"4169",
    "sg:province":"QLD",
    "wof:name":"davidkdifference# Real Estate",
    "wof:placetype":"venue"
},
  "geometry": {"coordinates":[153.04786682100001,-27.4785022736],"type":"Point"}
}