{
  "type": "Feature",
  "properties": {
    "addr:full":"50 Florence St Mentone VIC 3194",
    "addr:housenumber":"50",
    "addr:postcode":"3194",
    "addr:street":"Florence St",
    "iso:country":"AU",
    "sg:address":"50 Florence St",
    "sg:city":"Mentone",
    "sg:classifiers":[
        {
            "category":"Personal",
            "type":"Services"
        }
    ],
    "sg:phone":"+61 3 9583 8261",
    "sg:postcode":"3194",
    "sg:province":"VIC",
    "sg:tags":[
        "gift"
    ],
    "wof:name":"Chocolate Corporate Gift Service",
    "wof:placetype":"venue"
},
  "geometry": {"coordinates":[145.064285278,-37.9828834534],"type":"Point"}
}