{
  "type": "Feature",
  "properties": {
    "addr:full":"225 Brunswick St Fitzroy VIC 3065",
    "addr:housenumber":"225",
    "addr:postcode":"3065",
    "addr:street":"Brunswick St",
    "iso:country":"AU",
    "sg:address":"225 Brunswick St",
    "sg:city":"Fitzroy",
    "sg:classifiers":[
        {
            "category":"Personal",
            "subcategory":"Beauty Salon",
            "type":"Services"
        }
    ],
    "sg:phone":"+61 3 9419 1448",
    "sg:postcode":"3065",
    "sg:province":"VIC",
    "sg:tags":[
        "hairdresser"
    ],
    "wof:name":"Headingout",
    "wof:placetype":"venue"
},
  "geometry": {"coordinates":[144.97787475600001,-37.8006973267],"type":"Point"}
}