{
  "type": "Feature",
  "properties": {
    "addr:full":"177 Badimara St Fisher ACT 2611",
    "addr:housenumber":"177",
    "addr:postcode":"2611",
    "addr:street":"Badimara St",
    "iso:country":"AU",
    "sg:address":"177 Badimara St",
    "sg:city":"Fisher",
    "sg:classifiers":[
        {
            "category":"Social Services",
            "subcategory":"Retirement Home",
            "type":"Services"
        }
    ],
    "sg:phone":"+61 2 6288 9555",
    "sg:postcode":"2611",
    "sg:province":"ACT",
    "sg:tags":[
        "village"
    ],
    "wof:name":"Araluen- The Weston Creek Village",
    "wof:placetype":"venue"
},
  "geometry": {"coordinates":[149.05714416500001,-35.358165741],"type":"Point"}
}