{
  "type": "Feature",
  "properties": {
    "addr:full":"U 1/ 6 Aldershot Rd Lonsdale SA 5160",
    "addr:housenumber":"6",
    "addr:postcode":"5160",
    "addr:street":"Aldershot Rd",
    "iso:country":"AU",
    "sg:address":"U 1/ 6 Aldershot Rd",
    "sg:city":"Lonsdale",
    "sg:classifiers":[
        {
            "category":"Government",
            "subcategory":"Fire Station",
            "type":"Public Place"
        }
    ],
    "sg:phone":"+61 8 8326 9022",
    "sg:postcode":"5160",
    "sg:province":"SA",
    "sg:tags":[
        "equipment",
        "protection",
        "consultant"
    ],
    "wof:name":"Andrew McLeod Fire Protection Pty Ltd",
    "wof:placetype":"venue"
},
  "geometry": {"coordinates":[138.50782775900001,-35.1154289246],"type":"Point"}
}