{
  "type": "Feature",
  "properties": {
    "addr:full":"PO Box 133 Cairns QLD 4870",
    "addr:postcode":"4870",
    "iso:country":"AU",
    "sg:address":"PO Box 133",
    "sg:city":"Cairns",
    "sg:classifiers":[
        {
            "category":"Building & Trades",
            "subcategory":"Landscaping Services",
            "type":"Services"
        }
    ],
    "sg:phone":"+61 417 702 514",
    "sg:postcode":"4870",
    "sg:province":"QLD",
    "sg:tags":[
        "designer",
        "landscape",
        "contractor"
    ],
    "wof:name":"Peter Fisher Landscapes",
    "wof:placetype":"venue"
},
  "geometry": {"coordinates":[145.66958618199999,-17.0185699463],"type":"Point"}
}