{
  "type": "Feature",
  "properties": {
    "addr:full":"50 Broadmeadow Rd Broadmeadow NSW 2292",
    "addr:housenumber":"50",
    "addr:postcode":"2292",
    "addr:street":"Broadmeadow Rd",
    "iso:country":"AU",
    "sg:address":"50 Broadmeadow Rd",
    "sg:city":"Broadmeadow",
    "sg:classifiers":[
        {
            "category":"Retail",
            "subcategory":"Auto Repair",
            "type":"Services"
        }
    ],
    "sg:phone":"+61 2 4940 8849",
    "sg:postcode":"2292",
    "sg:province":"NSW",
    "sg:tags":[
        "repairer",
        "motor",
        "engineer"
    ],
    "wof:name":"Dasha's Auto Care",
    "wof:placetype":"venue"
},
  "geometry": {"coordinates":[151.73208618199999,-32.9161338806],"type":"Point"}
}