{
  "type": "Feature",
  "properties": {
    "addr:full":"U1b/ 8 Bonanza Drv Billinudgel NSW 2483",
    "addr:housenumber":"8",
    "addr:postcode":"2483",
    "addr:street":"Bonanza Drv",
    "iso:country":"AU",
    "sg:address":"U1b/ 8 Bonanza Drv",
    "sg:city":"Billinudgel",
    "sg:classifiers":[
        {
            "category":"Shopping",
            "subcategory":"Jewelry",
            "type":"Retail Goods"
        }
    ],
    "sg:phone":"+61 2 6680 5191",
    "sg:postcode":"2483",
    "sg:province":"NSW",
    "sg:tags":[
        "jeweller"
    ],
    "wof:name":"Crystal Gardens The",
    "wof:placetype":"venue"
},
  "geometry": {"coordinates":[153.52835082999999,-28.5051765442],"type":"Point"}
}