{
  "type": "Feature",
  "properties": {
    "addr:full":"23 Arinya St Kingsgrove NSW 2208",
    "addr:housenumber":"23",
    "addr:postcode":"2208",
    "addr:street":"Arinya St",
    "iso:country":"AU",
    "sg:address":"23 Arinya St",
    "sg:city":"Kingsgrove",
    "sg:classifiers":[
        {
            "category":"Retail",
            "subcategory":"Repair Shop",
            "type":"Services"
        }
    ],
    "sg:phone":"+61 2 9150 5211",
    "sg:postcode":"2208",
    "sg:province":"NSW",
    "sg:tags":[
        "repairing",
        "piano",
        "tuning"
    ],
    "wof:name":"W.A. Ridley",
    "wof:placetype":"venue"
},
  "geometry": {"coordinates":[151.10218800000001,-33.935295],"type":"Point"}
}