{
  "type": "Feature",
  "properties": {
    "addr:full":"First Floor, 384- 390 Haughton Rd Clayton VIC 3168",
    "addr:housenumber":"384",
    "addr:postcode":"390;3168",
    "addr:street":"First Floor;Haughton Rd",
    "iso:country":"AU",
    "sg:address":"First Floor, 384- 390 Haughton Rd",
    "sg:city":"Clayton",
    "sg:classifiers":[
        {
            "category":"Professional",
            "subcategory":"Employment Agencies",
            "type":"Services"
        }
    ],
    "sg:phone":"+61 3 9535 9000",
    "sg:postcode":"3168",
    "sg:province":"VIC",
    "wof:name":"Salvation Army Employment Plus The",
    "wof:placetype":"venue"
},
  "geometry": {"coordinates":[145.119537353,-37.9243011475],"type":"Point"}
}