{
  "type": "Feature",
  "properties": {
    "addr:full":"Cnr The Strand & Sir Leslie Thiess Drv Townsville QLD 4810",
    "addr:postcode":"4810",
    "addr:street":"Cnr;Thiess Drv",
    "iso:country":"AU",
    "sg:address":"Cnr The Strand & Sir Leslie Thiess Drv",
    "sg:city":"Townsville",
    "sg:classifiers":[
        {
            "category":"Professional",
            "subcategory":"Business Services",
            "type":"Services"
        }
    ],
    "sg:phone":"+61 13 26 50",
    "sg:postcode":"4810",
    "sg:province":"QLD",
    "sg:tags":[
        "small",
        "advisory"
    ],
    "wof:name":"Department of State Development, Trade and Innovation",
    "wof:placetype":"venue"
},
  "geometry": {"coordinates":[146.806915,-19.24127],"type":"Point"}
}