{
  "type": "Feature",
  "properties": {
    "iso:country":"AU",
    "sg:address":"8 Rodney Ave",
    "sg:city":"Tranmere",
    "sg:classifiers":[
        {
            "category":"Education",
            "subcategory":"Special Training",
            "type":"Public Place"
        }
    ],
    "sg:phone":"+61 8 8337 4239",
    "sg:postcode":"5073",
    "sg:province":"SA",
    "sg:tags":[
        "school",
        "art"
    ],
    "wof:name":"Lyn Robins",
    "wof:placetype":"venue"
},
  "geometry": {"coordinates":[138.661056519,-34.9008636475],"type":"Point"}
}