{
  "type": "Feature",
  "properties": {
    "iso:country":"AU",
    "sg:address":"37 Bank St",
    "sg:city":"Pyrmont",
    "sg:classifiers":[
        {
            "category":"Retail",
            "subcategory":"Event Space",
            "type":"Services"
        }
    ],
    "sg:phone":"+61 2 9660 0388",
    "sg:postcode":"2009",
    "sg:province":"NSW",
    "sg:tags":[
        "venue",
        "reception",
        "wedding"
    ],
    "wof:name":"Vagabond Cruises.",
    "wof:placetype":"venue"
},
  "geometry": {"coordinates":[151.19346618599999,-33.872013092],"type":"Point"}
}