{
  "type": "Feature",
  "properties": {
    "addr:full":"Unit 2 46 Kennedy Hwy Tolga QLD 4882",
    "addr:housenumber":"46",
    "addr:postcode":"4882",
    "addr:street":"Kennedy Hwy",
    "iso:country":"AU",
    "sg:address":"Unit 2 46 Kennedy Hwy",
    "sg:city":"Tolga",
    "sg:classifiers":[
        {
            "category":"Professional",
            "subcategory":"Testing Lab",
            "type":"Services"
        }
    ],
    "sg:phone":"+61 1800 663 009",
    "sg:postcode":"4882",
    "sg:province":"QLD",
    "sg:tags":[
        "soil",
        "investigation"
    ],
    "wof:name":"Wastewater Consultants",
    "wof:placetype":"venue"
},
  "geometry": {"coordinates":[145.47877502399999,-17.2249546051],"type":"Point"}
}