{
  "type": "Feature",
  "properties": {
    "addr:full":"80 Railway Rd Blackburn VIC 3130",
    "addr:housenumber":"80",
    "addr:postcode":"3130",
    "addr:street":"Railway Rd",
    "iso:country":"AU",
    "sg:address":"80 Railway Rd",
    "sg:city":"Blackburn",
    "sg:classifiers":[
        {
            "category":"Retail",
            "subcategory":"Auto Repair",
            "type":"Services"
        }
    ],
    "sg:phone":"+61 3 9894 1612",
    "sg:postcode":"3130",
    "sg:province":"VIC",
    "sg:tags":[
        "automotive",
        "air conditioning"
    ],
    "wof:name":"On Site Auto Air",
    "wof:placetype":"venue"
},
  "geometry": {"coordinates":[145.15583801299999,-37.8188400269],"type":"Point"}
}