{
  "type": "Feature",
  "properties": {
    "iso:country":"AU",
    "sg:address":"35 Kewdale Rd",
    "sg:city":"Welshpool",
    "sg:classifiers":[
        {
            "category":"Wholesale",
            "subcategory":"Machinery & Supplies",
            "type":"Manufacturing & Wholesale Goods"
        }
    ],
    "sg:phone":"+61 8 9350 5553",
    "sg:postcode":"6106",
    "sg:province":"WA",
    "sg:tags":[
        "engineer"
    ],
    "wof:name":"Blackwood J & Son Ltd",
    "wof:placetype":"venue"
},
  "geometry": {"coordinates":[115.954627991,-31.9843025208],"type":"Point"}
}