{
  "type": "Feature",
  "properties": {
    "addr:full":"16 Frankston-Dandenong Rd Dandenong VIC 3175",
    "addr:housenumber":"16",
    "addr:postcode":"3175",
    "addr:street":"Frankston-Dandenong Rd",
    "iso:country":"AU",
    "sg:address":"16 Frankston-Dandenong Rd",
    "sg:city":"Dandenong",
    "sg:classifiers":[
        {
            "category":"Manufacturing",
            "subcategory":"Tools & Machinery",
            "type":"Manufacturing & Wholesale Goods"
        }
    ],
    "sg:phone":"+61 3 9793 4949",
    "sg:postcode":"3175",
    "sg:province":"VIC",
    "sg:tags":[
        "earth",
        "excavating",
        "moving",
        "equipment"
    ],
    "wof:name":"A.C.M. Engineering & Earthmoving Repairs",
    "wof:placetype":"venue"
},
  "geometry": {"coordinates":[145.218017578,-37.9992675781],"type":"Point"}
}