{
  "type": "Feature",
  "properties": {
    "addr:full":"Lot 1518 Matison St Gosnells WA 6110",
    "addr:housenumber":"1518",
    "addr:postcode":"6110",
    "addr:street":"Matison St",
    "iso:country":"AU",
    "sg:address":"Lot 1518 Matison St",
    "sg:city":"Gosnells",
    "sg:classifiers":[
        {
            "category":"Building & Trades",
            "subcategory":"Construction",
            "type":"Services"
        }
    ],
    "sg:phone":"+61 8 9398 1865",
    "sg:postcode":"6110",
    "sg:province":"WA",
    "sg:tags":[
        "bitumen",
        "paving",
        "asphalt"
    ],
    "wof:name":"Brown C E & Son Pty Ltd",
    "wof:placetype":"venue"
},
  "geometry": {"coordinates":[115.976837158,-32.097442627],"type":"Point"}
}