{
  "type": "Feature",
  "properties": {
    "iso:country":"AU",
    "sg:address":"24 Oakridge Rd",
    "sg:city":"Aberfoyle Park",
    "sg:classifiers":[
        {
            "category":"Building & Trades",
            "subcategory":"Landscaping Services",
            "type":"Services"
        }
    ],
    "sg:phone":"+61 409 877 375",
    "sg:postcode":"5159",
    "sg:province":"SA",
    "sg:tags":[
        "consultant"
    ],
    "wof:name":"BDI Property Inspections",
    "wof:placetype":"venue"
},
  "geometry": {"coordinates":[138.609741211,-35.0650596619],"type":"Point"}
}