{
  "type": "Feature",
  "properties": {
    "iso:country":"AU",
    "sg:address":"26 Jardine St",
    "sg:city":"Fairy Meadow",
    "sg:classifiers":[
        {
            "category":"Building & Trades",
            "subcategory":"Construction",
            "type":"Services"
        }
    ],
    "sg:phone":"+61 2 4285 3449",
    "sg:postcode":"2519",
    "sg:province":"NSW",
    "sg:tags":[
        "window",
        "tinting"
    ],
    "wof:name":"South Coast Window Tinting",
    "wof:placetype":"venue"
},
  "geometry": {"coordinates":[150.89657600000001,-34.388054],"type":"Point"}
}