{
  "type": "Feature",
  "properties": {
    "addr:full":"300 Oxford St Paddington NSW 2021",
    "addr:housenumber":"300",
    "addr:postcode":"2021",
    "addr:street":"Oxford St",
    "iso:country":"AU",
    "sg:address":"300 Oxford St",
    "sg:city":"Paddington",
    "sg:classifiers":[
        {
            "category":"Shopping",
            "subcategory":"Clothing, Apparel, & Fashions",
            "type":"Retail Goods"
        }
    ],
    "sg:phone":"+61 2 9380 5101",
    "sg:postcode":"2021",
    "sg:province":"NSW",
    "sg:tags":[
        "menswear"
    ],
    "wof:name":"Tarocash",
    "wof:placetype":"venue"
},
  "geometry": {"coordinates":[151.22833251899999,-33.8854408264],"type":"Point"}
}