{
  "type": "Feature",
  "properties": {
    "iso:country":"AU",
    "sg:address":"234 Torquay Rd",
    "sg:city":"Grovedale",
    "sg:classifiers":[
        {
            "category":"Travel",
            "subcategory":"Hotels & Motels",
            "type":"Entertainment"
        }
    ],
    "sg:phone":"+61 3 5243 1077",
    "sg:postcode":"3216",
    "sg:province":"VIC",
    "wof:name":"Golden Chain Golden Palms Motel",
    "wof:placetype":"venue"
},
  "geometry": {"coordinates":[144.34048461899999,-38.20677948],"type":"Point"}
}