{
  "type": "Feature",
  "properties": {
    "addr:full":"(opposite Dog Swamp Shopping Centre) 11 Wanneroo Rd Tuart Hill WA 6060",
    "addr:housenumber":"11",
    "addr:postcode":"6060",
    "addr:street":"Wanneroo Rd",
    "iso:country":"AU",
    "sg:address":"(opposite Dog Swamp Shopping Centre) 11 Wanneroo Rd",
    "sg:city":"Tuart Hill",
    "sg:classifiers":[
        {
            "category":"Retail",
            "subcategory":"Veterinary Services",
            "type":"Services"
        }
    ],
    "sg:phone":"+61 8 9444 6800",
    "sg:postcode":"6060",
    "sg:province":"WA",
    "sg:tags":[
        "surgeon"
    ],
    "wof:name":"Dog Swamp Veterinary Hospital",
    "wof:placetype":"venue"
},
  "geometry": {"coordinates":[115.84472656200001,-31.9089984894],"type":"Point"}
}