{
  "type": "Feature",
  "properties": {
    "addr:full":"117- 125 Canterbury Rd Blackburn South VIC 3130",
    "addr:housenumber":"125",
    "addr:postcode":"3130",
    "addr:street":"Canterbury Rd",
    "iso:country":"AU",
    "sg:address":"117- 125 Canterbury Rd",
    "sg:city":"Blackburn South",
    "sg:classifiers":[
        {
            "category":"Food & Beverages",
            "subcategory":"Supermarket",
            "type":"Retail Goods"
        }
    ],
    "sg:phone":"+61 3 9877 1666",
    "sg:postcode":"3130",
    "sg:province":"VIC",
    "sg:tags":[
        "grocery",
        "store"
    ],
    "wof:name":"Safeway",
    "wof:placetype":"venue"
},
  "geometry": {"coordinates":[145.147613525,-37.8315734863],"type":"Point"}
}