{
  "type": "Feature",
  "properties": {
    "addr:full":"PO Box 1100 Burwood North NSW 2134",
    "addr:postcode":"2134",
    "iso:country":"AU",
    "sg:address":"PO Box 1100",
    "sg:city":"Burwood North",
    "sg:classifiers":[
        {
            "category":"Insurance",
            "subcategory":"Health Insurance",
            "type":"Services"
        }
    ],
    "sg:phone":"+61 1300 886 123",
    "sg:postcode":"2134",
    "sg:province":"NSW",
    "wof:name":"Railway & Transport Health Fund",
    "wof:placetype":"venue"
},
  "geometry": {"coordinates":[151.10392761200001,-33.8761482239],"type":"Point"}
}