{
  "type": "Feature",
  "properties": {
    "iso:country":"AU",
    "sg:address":"62 Balgowlah Rd",
    "sg:city":"Balgowlah",
    "sg:classifiers":[
        {
            "category":"Deli",
            "type":"Food & Drink"
        }
    ],
    "sg:phone":"+61 2 9949 1981",
    "sg:postcode":"2093",
    "sg:province":"NSW",
    "sg:tags":[
        "delicatessen"
    ],
    "wof:name":"Balrose Deli",
    "wof:placetype":"venue"
},
  "geometry": {"coordinates":[151.266921997,-33.7902603149],"type":"Point"}
}