{
  "type": "Feature",
  "properties": {
    "addr:full":"5 Kaleski Moorebank NSW 2170",
    "addr:housenumber":"5",
    "addr:postcode":"2170",
    "addr:street":"Kaleski",
    "iso:country":"AU",
    "sg:address":"5 Kaleski",
    "sg:city":"Moorebank",
    "sg:classifiers":[
        {
            "category":"Professional",
            "subcategory":"Engineering",
            "type":"Services"
        }
    ],
    "sg:phone":"+61 2 9821 2123",
    "sg:postcode":"2170",
    "sg:province":"NSW",
    "sg:tags":[
        "engineer",
        "toolmaker",
        "plastic"
    ],
    "wof:name":"Accumould Plastics",
    "wof:placetype":"venue"
},
  "geometry": {"coordinates":[150.93107605,-33.9362449646],"type":"Point"}
}