{
  "type": "Feature",
  "properties": {
    "addr:full":"36 Buckhurst St South Melbourne VIC 3205",
    "addr:housenumber":"36",
    "addr:postcode":"3205",
    "addr:street":"Buckhurst St",
    "iso:country":"AU",
    "sg:address":"36 Buckhurst St",
    "sg:city":"South Melbourne",
    "sg:classifiers":[
        {
            "category":"Autos & Motor Vehicles",
            "subcategory":"Automobile Sales",
            "type":"Retail Goods"
        }
    ],
    "sg:phone":"+61 3 9682 8818",
    "sg:postcode":"3205",
    "sg:province":"VIC",
    "sg:tags":[
        "car",
        "used"
    ],
    "wof:name":"Glen Eira Cars",
    "wof:placetype":"venue"
},
  "geometry": {"coordinates":[144.95210299999999,-37.829758],"type":"Point"}
}