{
  "type": "Feature",
  "properties": {
    "addr:full":"53 Mitchell St Mt Pleasant WA 6153",
    "addr:housenumber":"53",
    "addr:postcode":"6153",
    "addr:street":"Mitchell St",
    "iso:country":"AU",
    "sg:address":"53 Mitchell St",
    "sg:city":"Mt Pleasant",
    "sg:classifiers":[
        {
            "category":"Health Services",
            "subcategory":"Doctor",
            "type":"Services"
        }
    ],
    "sg:phone":"+61 8 9364 2068",
    "sg:postcode":"6153",
    "sg:province":"WA",
    "sg:tags":[
        "occupational",
        "safety"
    ],
    "wof:name":"Armarego & Associates",
    "wof:placetype":"venue"
},
  "geometry": {"coordinates":[115.843079,-32.019543],"type":"Point"}
}