{
  "type": "Feature",
  "properties": {
    "addr:full":"147 Princes Hwy Unanderra NSW 2526",
    "addr:housenumber":"147",
    "addr:postcode":"2526",
    "addr:street":"Princes Hwy",
    "iso:country":"AU",
    "sg:address":"147 Princes Hwy",
    "sg:city":"Unanderra",
    "sg:classifiers":[
        {
            "category":"Building & Trades",
            "subcategory":"Construction",
            "type":"Services"
        }
    ],
    "sg:phone":"+61 2 4271 4411",
    "sg:postcode":"2526",
    "sg:province":"NSW",
    "sg:tags":[
        "contractor"
    ],
    "wof:name":"AVJennings Ltd",
    "wof:placetype":"venue"
},
  "geometry": {"coordinates":[150.84429931599999,-34.4557037354],"type":"Point"}
}