{
  "type": "Feature",
  "properties": {
    "iso:country":"AU",
    "sg:address":"PO Box 1080",
    "sg:city":"Miranda",
    "sg:classifiers":[
        {
            "category":"Insurance",
            "subcategory":"Hazard Insurance",
            "type":"Services"
        }
    ],
    "sg:phone":"+61 2 9531 7474",
    "sg:postcode":"1490",
    "sg:province":"NSW",
    "sg:tags":[
        "loss",
        "adjuster",
        "assessor"
    ],
    "wof:name":"Ibels F C & Co Pty Ltd",
    "wof:placetype":"venue"
},
  "geometry": {"coordinates":[144.600509644,-34.9115104675],"type":"Point"}
}