{
  "type": "Feature",
  "properties": {
    "iso:country":"AU",
    "sg:address":"40 Shelley St",
    "sg:city":"Richmond",
    "sg:classifiers":[
        {
            "category":"Home & Garden",
            "subcategory":"Carpets & Floor Coverings",
            "type":"Retail Goods"
        }
    ],
    "sg:phone":"+61 3 9429 8104",
    "sg:postcode":"3121",
    "sg:province":"VIC",
    "sg:tags":[
        "tile",
        "wall"
    ],
    "wof:name":"G.T. Tiles",
    "wof:placetype":"venue"
},
  "geometry": {"coordinates":[144.99331665,-37.8122673035],"type":"Point"}
}