{
  "type": "Feature",
  "properties": {
    "addr:full":"13 Sunderland St Moonah TAS 7009",
    "addr:housenumber":"13",
    "addr:postcode":"7009",
    "addr:street":"Sunderland St",
    "iso:country":"AU",
    "sg:address":"13 Sunderland St",
    "sg:city":"Moonah",
    "sg:classifiers":[
        {
            "category":"Autos & Motor Vehicles",
            "subcategory":"Auto Supplies",
            "type":"Retail Goods"
        }
    ],
    "sg:phone":"+61 3 6272 6400",
    "sg:postcode":"7009",
    "sg:province":"TAS",
    "sg:tags":[
        "transmission",
        "equipment",
        "power"
    ],
    "wof:name":"Tas Bearing & Chain (Hobart)",
    "wof:placetype":"venue"
},
  "geometry": {"coordinates":[147.295196533,-42.8422889709],"type":"Point"}
}