{
  "type": "Feature",
  "properties": {
    "iso:country":"AU",
    "sg:address":"138 Allister Ave",
    "sg:city":"Knoxfield",
    "sg:classifiers":[
        {
            "category":"Shopping",
            "subcategory":"Mobile Phones",
            "type":"Retail Goods"
        }
    ],
    "sg:phone":"+61 1300 368 683",
    "sg:postcode":"3180",
    "sg:province":"VIC",
    "sg:tags":[
        "telephone",
        "accessory"
    ],
    "wof:name":"Hotcakes Accessories",
    "wof:placetype":"venue"
},
  "geometry": {"coordinates":[145.24296569800001,-37.882610321],"type":"Point"}
}