{
  "type": "Feature",
  "properties": {
    "addr:full":"35 Rushall St Fairfield VIC 3078",
    "addr:housenumber":"35",
    "addr:postcode":"3078",
    "addr:street":"Rushall St",
    "iso:country":"AU",
    "sg:address":"35 Rushall St",
    "sg:city":"Fairfield",
    "sg:classifiers":[
        {
            "category":"Utilities",
            "subcategory":"Electric",
            "type":"Services"
        }
    ],
    "sg:phone":"+61 418 385 377",
    "sg:postcode":"3078",
    "sg:province":"VIC",
    "sg:tags":[
        "electrical",
        "contractor"
    ],
    "wof:name":"Bettiol A J Property Services",
    "wof:placetype":"venue"
},
  "geometry": {"coordinates":[145.02047729500001,-37.776348114],"type":"Point"}
}