{
  "type": "Feature",
  "properties": {
    "addr:full":"126 Weller Rd Tarragindi QLD 4121",
    "addr:housenumber":"126",
    "addr:postcode":"4121",
    "addr:street":"Weller Rd",
    "iso:country":"AU",
    "sg:address":"126 Weller Rd",
    "sg:city":"Tarragindi",
    "sg:classifiers":[
        {
            "category":"Organizations",
            "subcategory":"Non-profit Organization",
            "type":"Services"
        }
    ],
    "sg:phone":"+61 7 3848 1262",
    "sg:postcode":"4121",
    "sg:province":"QLD",
    "sg:tags":[
        "support",
        "disability",
        "organisation"
    ],
    "wof:name":"Prader-Willi Syndrome Assoc.",
    "wof:placetype":"venue"
},
  "geometry": {"coordinates":[153.048583984,-27.5243358612],"type":"Point"}
}