{
  "type": "Feature",
  "properties": {
    "iso:country":"AU",
    "sg:address":"PO Box 355",
    "sg:city":"Goodwood",
    "sg:classifiers":[
        {
            "category":"Education",
            "subcategory":"Music School",
            "type":"Public Place"
        }
    ],
    "sg:phone":"+61 417 896 473",
    "sg:postcode":"5034",
    "sg:province":"SA",
    "sg:tags":[
        "choir",
        "bands",
        "orchestra"
    ],
    "wof:name":"Adelaide Boys Choir",
    "wof:placetype":"venue"
},
  "geometry": {"coordinates":[138.589645386,-34.9516410828],"type":"Point"}
}