{
  "type": "Feature",
  "properties": {
    "addr:full":"321 Springvale Rd Glen Waverley VIC 3150",
    "addr:housenumber":"321",
    "addr:postcode":"3150",
    "addr:street":"Springvale Rd",
    "iso:country":"AU",
    "sg:address":"321 Springvale Rd",
    "sg:city":"Glen Waverley",
    "sg:classifiers":[
        {
            "category":"Professional",
            "subcategory":"Art Services",
            "type":"Services"
        }
    ],
    "sg:phone":"+61 419 008 537",
    "sg:postcode":"3150",
    "sg:province":"VIC",
    "sg:tags":[
        "decorator",
        "painter"
    ],
    "wof:name":"DIT Decorators Pty Ltd",
    "wof:placetype":"venue"
},
  "geometry": {"coordinates":[145.16494750999999,-37.8831138611],"type":"Point"}
}