{
  "type": "Feature",
  "properties": {
    "iso:country":"AU",
    "sg:address":"Unit6/ 165 Melbourne St",
    "sg:city":"South Brisbane",
    "sg:classifiers":[
        {
            "category":"Professional",
            "subcategory":"Engineering",
            "type":"Services"
        }
    ],
    "sg:phone":"+61 7 3844 4972",
    "sg:postcode":"4101",
    "sg:province":"QLD",
    "sg:tags":[
        "consulting",
        "engineer"
    ],
    "wof:name":"Upstream Petroleum Pty Ltd",
    "wof:placetype":"venue"
},
  "geometry": {"coordinates":[153.01434326200001,-27.4760112762],"type":"Point"}
}