{
  "type": "Feature",
  "properties": {
    "iso:country":"AU",
    "sg:address":"1 Wallis St",
    "sg:city":"Forster",
    "sg:classifiers":[
        {
            "category":"Food & Beverages",
            "subcategory":"Meat & Fish",
            "type":"Retail Goods"
        }
    ],
    "sg:phone":"+61 2 6557 5300",
    "sg:postcode":"2428",
    "sg:province":"NSW",
    "sg:tags":[
        "seafood"
    ],
    "wof:name":"Beach Street Seafoods",
    "wof:placetype":"venue"
},
  "geometry": {"coordinates":[152.51182600000001,-32.180733],"type":"Point"}
}