{
  "type": "Feature",
  "properties": {
    "addr:full":"80 Angelo St South Perth WA 6151",
    "addr:housenumber":"80",
    "addr:postcode":"6151",
    "addr:street":"Angelo St South",
    "iso:country":"AU",
    "sg:address":"80 Angelo St",
    "sg:city":"South Perth",
    "sg:classifiers":[
        {
            "category":"Food & Beverages",
            "subcategory":"Supermarket",
            "type":"Retail Goods"
        }
    ],
    "sg:phone":"+61 8 9367 1541",
    "sg:postcode":"6151",
    "sg:province":"WA",
    "sg:tags":[
        "grocery",
        "store"
    ],
    "wof:name":"Eziway Food Stores",
    "wof:placetype":"venue"
},
  "geometry": {"coordinates":[115.863541,-31.980747],"type":"Point"}
}