{
  "type": "Feature",
  "properties": {
    "iso:country":"AU",
    "sg:address":"PO Box 163",
    "sg:city":"Yamba",
    "sg:classifiers":[
        {
            "category":"Food & Beverages",
            "subcategory":"Fruits & Vegetables",
            "type":"Retail Goods"
        }
    ],
    "sg:phone":"+61 448 463 135",
    "sg:postcode":"2464",
    "sg:province":"NSW",
    "sg:tags":[
        "wholesale"
    ],
    "wof:name":"Clarence Valley Fruit & Veg Wholesaler and Transport",
    "wof:placetype":"venue"
},
  "geometry": {"coordinates":[153.32157898,-29.428609848],"type":"Point"}
}