{
  "type": "Feature",
  "properties": {
    "addr:full":"Unit 1 1 Bushells Pl Wetherill Park NSW 2164",
    "addr:housenumber":"1",
    "addr:postcode":"2164",
    "addr:street":"Bushells Pl",
    "iso:country":"AU",
    "sg:address":"Unit 1 1 Bushells Pl",
    "sg:city":"Wetherill Park",
    "sg:classifiers":[
        {
            "category":"Government",
            "subcategory":"Department Of Motor Vehicles",
            "type":"Public Place"
        }
    ],
    "sg:phone":"+61 1300 369 787",
    "sg:postcode":"2164",
    "sg:province":"NSW",
    "sg:tags":[
        "mfrs",
        "clutch",
        "brake",
        "lining",
        "wholesaler",
        "pad"
    ],
    "wof:name":"Clutch Industries Pty Ltd",
    "wof:placetype":"venue"
},
  "geometry": {"coordinates":[150.891067505,-33.8423614502],"type":"Point"}
}