{
  "type": "Feature",
  "properties": {
    "addr:full":"PO Box 2 Sanctuary Point NSW 2540",
    "addr:postcode":"2540",
    "iso:country":"AU",
    "sg:address":"PO Box 2",
    "sg:city":"Sanctuary Point",
    "sg:classifiers":[
        {
            "category":"Banks & Credit Unions",
            "subcategory":"Investment Brokerage",
            "type":"Services"
        }
    ],
    "sg:phone":"+61 2 4443 3310",
    "sg:postcode":"2540",
    "sg:province":"NSW",
    "sg:tags":[
        "testing",
        "licence",
        "boat"
    ],
    "wof:name":"NSW Boating College",
    "wof:placetype":"venue"
},
  "geometry": {"coordinates":[150.62261962900001,-35.1057090759],"type":"Point"}
}