{
  "type": "Feature",
  "properties": {
    "addr:full":"Lot 434 Darby Cl Dubbo NSW 2830",
    "addr:postcode":"2830",
    "addr:street":"Darby Cl",
    "iso:country":"AU",
    "sg:address":"Lot 434 Darby Cl",
    "sg:city":"Dubbo",
    "sg:classifiers":[
        {
            "category":"Social Services",
            "subcategory":"Retirement Home",
            "type":"Services"
        }
    ],
    "sg:phone":"+61 2 6882 7022",
    "sg:postcode":"2830",
    "sg:province":"NSW",
    "sg:tags":[
        "village"
    ],
    "wof:name":"Masonic Retirement Village Dubbo",
    "wof:placetype":"venue"
},
  "geometry": {"coordinates":[148.60247802699999,-32.2471809387],"type":"Point"}
}