{
  "type": "Feature",
  "properties": {
    "addr:full":"166a Argyle St Traralgon VIC 3844",
    "addr:housenumber":"166a",
    "addr:postcode":"3844",
    "addr:street":"Argyle St",
    "iso:country":"AU",
    "sg:address":"166a Argyle St",
    "sg:city":"Traralgon",
    "sg:classifiers":[
        {
            "category":"Fast Food",
            "type":"Food & Drink"
        }
    ],
    "sg:phone":"+61 3 5174 7531",
    "sg:postcode":"3844",
    "sg:province":"VIC",
    "sg:tags":[
        "away",
        "take"
    ],
    "wof:name":"Argyle Eatery",
    "wof:placetype":"venue"
},
  "geometry": {"coordinates":[146.55690002399999,-38.1911239624],"type":"Point"}
}