{
  "type": "Feature",
  "properties": {
    "iso:country":"AU",
    "sg:address":"Redbanks Rd",
    "sg:city":"Mallala",
    "sg:classifiers":[
        {
            "category":"Food & Beverages",
            "subcategory":"Fruits & Vegetables",
            "type":"Retail Goods"
        }
    ],
    "sg:phone":"+61 8 8527 2268",
    "sg:postcode":"5502",
    "sg:province":"SA",
    "sg:tags":[
        "wholesale"
    ],
    "wof:name":"A 1 Mushrooms",
    "wof:placetype":"venue"
},
  "geometry": {"coordinates":[138.509964,-34.437969],"type":"Point"}
}