{
  "type": "Feature",
  "properties": {
    "addr:full":"45 George St Norwood SA 5067",
    "addr:housenumber":"45",
    "addr:postcode":"5067",
    "addr:street":"George St",
    "iso:country":"AU",
    "sg:address":"45 George St",
    "sg:city":"Norwood",
    "sg:classifiers":[
        {
            "category":"Banks & Credit Unions",
            "subcategory":"Financial Services",
            "type":"Services"
        }
    ],
    "sg:phone":"+61 8 8364 6555",
    "sg:postcode":"5067",
    "sg:province":"SA",
    "sg:tags":[
        "planning"
    ],
    "wof:name":"Longbottom Robin",
    "wof:placetype":"venue"
},
  "geometry": {"coordinates":[138.63638305699999,-34.9200820923],"type":"Point"}
}