{
  "type": "Feature",
  "properties": {
    "iso:country":"AU",
    "sg:address":"Pearsalls Rd",
    "sg:city":"Inverloch",
    "sg:classifiers":[
        {
            "category":"Farming",
            "subcategory":"Nursery",
            "type":"Manufacturing & Wholesale Goods"
        }
    ],
    "sg:phone":"+61 3 5674 1014",
    "sg:postcode":"3996",
    "sg:province":"VIC",
    "wof:name":"Teesdale B A & Hambly L.J.",
    "wof:placetype":"venue"
},
  "geometry": {"coordinates":[145.698044,-38.617313],"type":"Point"}
}