{
  "type": "Feature",
  "properties": {
    "addr:full":"739 Main Rd Eltham VIC 3095",
    "addr:housenumber":"739",
    "addr:postcode":"3095",
    "addr:street":"Main Rd",
    "iso:country":"AU",
    "sg:address":"739 Main Rd",
    "sg:city":"Eltham",
    "sg:classifiers":[
        {
            "category":"Education",
            "subcategory":"Special Training",
            "type":"Public Place"
        }
    ],
    "sg:phone":"+61 3 9430 1313",
    "sg:postcode":"3095",
    "sg:province":"VIC",
    "sg:tags":[
        "development"
    ],
    "wof:name":"Living & Learning Nillumbik",
    "wof:placetype":"venue"
},
  "geometry": {"coordinates":[145.14561462399999,-37.7212295532],"type":"Point"}
}