{
  "type": "Feature",
  "properties": {
    "iso:country":"AU",
    "sg:address":"Shop 4/ 876 Old Cleveland Rd",
    "sg:city":"Carina",
    "sg:classifiers":[
        {
            "category":"Health Services",
            "subcategory":"Health Practitioner",
            "type":"Services"
        }
    ],
    "sg:phone":"+61 7 3398 8862",
    "sg:postcode":"4152",
    "sg:province":"QLD",
    "sg:tags":[
        "consultant",
        "conservation",
        "hearing"
    ],
    "sg:website":"http://www.johnpearcyaudiology.com.au",
    "wof:name":"John Pearcy Audiology",
    "wof:placetype":"venue"
},
  "geometry": {"coordinates":[153.09478759800001,-27.4955863953],"type":"Point"}
}