{
  "type": "Feature",
  "properties": {
    "iso:country":"AU",
    "sg:address":"105 Lonsdale St",
    "sg:city":"Ballarat",
    "sg:classifiers":[
        {
            "category":"Education",
            "subcategory":"Kindergarten",
            "type":"Public Place"
        }
    ],
    "sg:phone":"+61 3 5335 7590",
    "sg:postcode":"3350",
    "sg:province":"VIC",
    "sg:tags":[
        "pre-schools"
    ],
    "wof:name":"Iris Ramsay Kindergarten Inc",
    "wof:placetype":"venue"
},
  "geometry": {"coordinates":[143.835114,-37.575405],"type":"Point"}
}