{
  "type": "Feature",
  "properties": {
    "iso:country":"AU",
    "sg:address":"Shop 10 Blenheim Rd",
    "sg:city":"North Ryde",
    "sg:classifiers":[
        {
            "category":"Health Services",
            "subcategory":"Health Practitioner",
            "type":"Services"
        }
    ],
    "sg:phone":"+61 2 9805 0333",
    "sg:postcode":"2113",
    "sg:province":"NSW",
    "sg:tags":[
        "physiotherapist"
    ],
    "wof:name":"Ryan Michael",
    "wof:placetype":"venue"
},
  "geometry": {"coordinates":[151.12010192899999,-33.7936134338],"type":"Point"}
}