{
  "type": "Feature",
  "properties": {
    "addr:full":"30 Main St Narangba QLD 4504",
    "addr:housenumber":"30",
    "addr:postcode":"4504",
    "addr:street":"Main St",
    "iso:country":"AU",
    "sg:address":"30 Main St",
    "sg:city":"Narangba",
    "sg:classifiers":[
        {
            "category":"Health Services",
            "subcategory":"Doctor",
            "type":"Services"
        }
    ],
    "sg:phone":"+61 7 3886 6888",
    "sg:postcode":"4504",
    "sg:province":"QLD",
    "sg:tags":[
        "medical",
        "practitioner"
    ],
    "wof:name":"Stephenson Peter C Family Doctor",
    "wof:placetype":"venue"
},
  "geometry": {"coordinates":[152.96014404300001,-27.2031764984],"type":"Point"}
}