{
  "type": "Feature",
  "properties": {
    "addr:full":"31 Yangara Rd O&#039;Sullivan Beach SA 5166",
    "addr:housenumber":"31",
    "addr:postcode":"5166",
    "addr:street":"Yangara Rd;Sullivan",
    "iso:country":"AU",
    "sg:address":"31 Yangara Rd",
    "sg:city":"O&#039;Sullivan Beach",
    "sg:classifiers":[
        {
            "category":"Professional",
            "subcategory":"Art Services",
            "type":"Services"
        }
    ],
    "sg:phone":"+61 8 8326 3202",
    "sg:postcode":"5166",
    "sg:province":"SA",
    "sg:tags":[
        "arranger",
        "music",
        "composer"
    ],
    "wof:name":"Brucewaynemusic.com",
    "wof:placetype":"venue"
},
  "geometry": {"coordinates":[138.47787475600001,-35.1194076538],"type":"Point"}
}