{
  "type": "Feature",
  "properties": {
    "iso:country":"AU",
    "sg:address":"6 Cheshire St",
    "sg:city":"Wagga Wagga",
    "sg:classifiers":[
        {
            "category":"Mining & Drilling",
            "type":"Manufacturing & Wholesale Goods"
        }
    ],
    "sg:phone":"+61 2 6925 4660",
    "sg:postcode":"2650",
    "sg:province":"NSW",
    "sg:tags":[
        "boring",
        "contractor"
    ],
    "wof:name":"Wagga Directional Drilling",
    "wof:placetype":"venue"
},
  "geometry": {"coordinates":[147.344482422,-35.1238708496],"type":"Point"}
}