{
  "type": "Feature",
  "properties": {
    "iso:country":"AU",
    "sg:address":"1/ 19 Adelaide St",
    "sg:city":"St Albans",
    "sg:classifiers":[
        {
            "category":"Building & Trades",
            "subcategory":"Construction",
            "type":"Services"
        }
    ],
    "sg:phone":"+61 3 9364 4625",
    "sg:postcode":"3021",
    "sg:province":"VIC",
    "sg:tags":[
        "contractor"
    ],
    "sg:website":"http://www.mbav.com.au",
    "wof:name":"V.C. Construction",
    "wof:placetype":"venue"
},
  "geometry": {"coordinates":[144.792892,-37.741272],"type":"Point"}
}