{
  "type": "Feature",
  "properties": {
    "iso:country":"AU",
    "sg:address":"Unit 4 1 Park St",
    "sg:city":"McLaren Vale",
    "sg:classifiers":[
        {
            "category":"Manufacturing",
            "subcategory":"Furniture",
            "type":"Manufacturing & Wholesale Goods"
        }
    ],
    "sg:phone":"+61 8 8323 7520",
    "sg:postcode":"5171",
    "sg:province":"SA",
    "sg:tags":[
        "builder",
        "designer",
        "custom"
    ],
    "wof:name":"The Craft Factory Of McLaren Vale",
    "wof:placetype":"venue"
},
  "geometry": {"coordinates":[138.53659057600001,-35.215007782],"type":"Point"}
}