{
  "type": "Feature",
  "properties": {
    "addr:full":"1 Cockatoo St Singleton NSW 2330",
    "addr:housenumber":"1",
    "addr:postcode":"2330",
    "addr:street":"Cockatoo St",
    "iso:country":"AU",
    "sg:address":"1 Cockatoo St",
    "sg:city":"Singleton",
    "sg:classifiers":[
        {
            "category":"Utilities",
            "subcategory":"Electric",
            "type":"Services"
        }
    ],
    "sg:phone":"+61 2 6578 8000",
    "sg:postcode":"2330",
    "sg:province":"NSW",
    "sg:tags":[
        "electrical",
        "contractor"
    ],
    "wof:name":"Power Serve Pty Ltd",
    "wof:placetype":"venue"
},
  "geometry": {"coordinates":[151.14077800000001,-32.549713],"type":"Point"}
}