{
  "type": "Feature",
  "properties": {
    "iso:country":"AU",
    "sg:address":"PO Box 304",
    "sg:city":"Ingle Farm",
    "sg:classifiers":[
        {
            "category":"Wholesale",
            "subcategory":"Painting Supplies",
            "type":"Manufacturing & Wholesale Goods"
        }
    ],
    "sg:phone":"+61 413 259 990",
    "sg:postcode":"5098",
    "sg:province":"SA",
    "sg:tags":[
        "product",
        "cleaning"
    ],
    "wof:name":"Cleaning Supplies Direct Pty Ltd",
    "wof:placetype":"venue"
},
  "geometry": {"coordinates":[138.650756836,-34.8287086487],"type":"Point"}
}