{
  "type": "Feature",
  "properties": {
    "addr:full":"121 Marsh St Armidale NSW 2350",
    "addr:housenumber":"121",
    "addr:postcode":"2350",
    "addr:street":"Marsh St",
    "iso:country":"AU",
    "sg:address":"121 Marsh St",
    "sg:city":"Armidale",
    "sg:classifiers":[
        {
            "category":"Manufacturing",
            "subcategory":"Motor Vehicles & Parts",
            "type":"Manufacturing & Wholesale Goods"
        }
    ],
    "sg:phone":"+61 2 6772 3580",
    "sg:postcode":"2350",
    "sg:province":"NSW",
    "sg:tags":[
        "replacement"
    ],
    "wof:name":"KG Motors Pty Ltd",
    "wof:placetype":"venue"
},
  "geometry": {"coordinates":[151.66636657699999,-30.5217037201],"type":"Point"}
}