{
  "type": "Feature",
  "properties": {
    "iso:country":"AU",
    "sg:address":"Shop 4, 90 Edwin St North",
    "sg:city":"Croydon",
    "sg:classifiers":[
        {
            "category":"Building & Trades",
            "subcategory":"Construction",
            "type":"Services"
        }
    ],
    "sg:phone":"+61 2 9799 9990",
    "sg:postcode":"2132",
    "sg:province":"NSW",
    "sg:tags":[
        "earth",
        "excavating",
        "moving",
        "contractor"
    ],
    "wof:name":"Rocktown Pty Ltd",
    "wof:placetype":"venue"
},
  "geometry": {"coordinates":[151.11688232399999,-33.8828849792],"type":"Point"}
}