{
  "type": "Feature",
  "properties": {
    "addr:full":"5/ 1 Billson St Wonthaggi VIC 3995",
    "addr:housenumber":"/ 1",
    "addr:postcode":"3995",
    "addr:street":"Billson St",
    "iso:country":"AU",
    "sg:address":"5/ 1 Billson St",
    "sg:city":"Wonthaggi",
    "sg:classifiers":[
        {
            "category":"Health Services",
            "subcategory":"Health Practitioner",
            "type":"Services"
        }
    ],
    "sg:phone":"+61 3 5956 6071",
    "sg:postcode":"3995",
    "sg:province":"VIC",
    "sg:tags":[
        "psychologist"
    ],
    "wof:name":"Jason Crestani",
    "wof:placetype":"venue"
},
  "geometry": {"coordinates":[145.588593,-38.6054],"type":"Point"}
}