{
  "type": "Feature",
  "properties": {
    "addr:full":"1 Blamey St Caloundra QLD 4551",
    "addr:housenumber":"1",
    "addr:postcode":"4551",
    "addr:street":"Blamey St",
    "iso:country":"AU",
    "sg:address":"1 Blamey St",
    "sg:city":"Caloundra",
    "sg:classifiers":[
        {
            "category":"Education",
            "subcategory":"Special Training",
            "type":"Public Place"
        }
    ],
    "sg:phone":"+61 7 5491 1432",
    "sg:postcode":"4551",
    "sg:province":"QLD",
    "sg:tags":[
        "tuition-educational"
    ],
    "wof:name":"Albert Rick",
    "wof:placetype":"venue"
},
  "geometry": {"coordinates":[153.12890625,-26.7799396515],"type":"Point"}
}