{
  "type": "Feature",
  "properties": {
    "addr:full":"21 Service Rd Moe VIC 3825",
    "addr:housenumber":"21",
    "addr:postcode":"3825",
    "addr:street":"Service Rd",
    "iso:country":"AU",
    "sg:address":"21 Service Rd",
    "sg:city":"Moe",
    "sg:classifiers":[
        {
            "category":"Home & Garden",
            "subcategory":"Hardware",
            "type":"Retail Goods"
        }
    ],
    "sg:phone":"+61 3 5126 1489",
    "sg:postcode":"3825",
    "sg:province":"VIC",
    "sg:tags":[
        "tarpaulin"
    ],
    "wof:name":"Valley Canvas Repairs",
    "wof:placetype":"venue"
},
  "geometry": {"coordinates":[146.25915499999999,-38.18602],"type":"Point"}
}