{
  "type": "Feature",
  "properties": {
    "addr:full":"77 Sandgate Rd Wallsend NSW 2287",
    "addr:housenumber":"77",
    "addr:postcode":"2287",
    "addr:street":"Sandgate Rd",
    "iso:country":"AU",
    "sg:address":"77 Sandgate Rd",
    "sg:city":"Wallsend",
    "sg:classifiers":[
        {
            "category":"Retail",
            "subcategory":"Auto Repair",
            "type":"Services"
        }
    ],
    "sg:phone":"+61 2 4950 0128",
    "sg:postcode":"2287",
    "sg:province":"NSW",
    "sg:tags":[
        "repairer",
        "motor",
        "engineer"
    ],
    "wof:name":"Buxtons Automotive Services",
    "wof:placetype":"venue"
},
  "geometry": {"coordinates":[151.68157959000001,-32.8956947327],"type":"Point"}
}