{
  "type": "Feature",
  "properties": {
    "iso:country":"AU",
    "sg:address":"Suite 1000, Homemaker Cntr, Overland Drv",
    "sg:city":"Narre Warren",
    "sg:classifiers":[
        {
            "category":"Professional",
            "subcategory":"Employment Agencies",
            "type":"Services"
        }
    ],
    "sg:phone":"+61 3 9705 4600",
    "sg:postcode":"3805",
    "sg:province":"VIC",
    "wof:name":"Salvation Army Employment Plus The",
    "wof:placetype":"venue"
},
  "geometry": {"coordinates":[145.30560299999999,-38.020424],"type":"Point"}
}