{
  "type": "Feature",
  "properties": {
    "iso:country":"AU",
    "sg:address":"Unit 7/ 37 Machinery Drv",
    "sg:city":"Tweed Heads South",
    "sg:classifiers":[
        {
            "category":"Recreation",
            "subcategory":"Fishing",
            "type":"Entertainment"
        }
    ],
    "sg:phone":"+61 7 5524 6422",
    "sg:postcode":"2486",
    "sg:province":"NSW",
    "sg:tags":[
        "tackle"
    ],
    "wof:name":"Border Batteries & Radiators",
    "wof:placetype":"venue"
},
  "geometry": {"coordinates":[153.541915894,-28.2024898529],"type":"Point"}
}