{
  "type": "Feature",
  "properties": {
    "addr:full":"Lot 347 Flett Rd Roseworthy SA 5371",
    "addr:postcode":"5371",
    "addr:street":"Flett Rd",
    "iso:country":"AU",
    "sg:address":"Lot 347 Flett Rd",
    "sg:city":"Roseworthy",
    "sg:classifiers":[
        {
            "category":"Utilities",
            "subcategory":"Telephone",
            "type":"Services"
        }
    ],
    "sg:phone":"+61 8 8524 8399",
    "sg:postcode":"5371",
    "sg:province":"SA",
    "sg:tags":[
        "installation",
        "system",
        "maintenance"
    ],
    "wof:name":"Country Phone and Data",
    "wof:placetype":"venue"
},
  "geometry": {"coordinates":[138.752243042,-34.5361671448],"type":"Point"}
}