{
  "type": "Feature",
  "properties": {
    "addr:full":"177 Yarra View Rd Yarra Glen VIC 3775",
    "addr:housenumber":"177",
    "addr:postcode":"3775",
    "addr:street":"Yarra View Rd",
    "iso:country":"AU",
    "sg:address":"177 Yarra View Rd",
    "sg:city":"Yarra Glen",
    "sg:classifiers":[
        {
            "category":"Travel",
            "subcategory":"Travel Agent",
            "type":"Entertainment"
        }
    ],
    "sg:phone":"+61 3 9730 1581",
    "sg:postcode":"3775",
    "sg:province":"VIC",
    "sg:tags":[
        "consultant"
    ],
    "wof:name":"Innhouse Travel",
    "wof:placetype":"venue"
},
  "geometry": {"coordinates":[145.36283900000001,-37.663414],"type":"Point"}
}