{
  "type": "Feature",
  "properties": {
    "iso:country":"AU",
    "sg:address":"4/ 12 Susan St",
    "sg:city":"Auburn",
    "sg:classifiers":[
        {
            "category":"Home & Garden",
            "subcategory":"Building Materials",
            "type":"Retail Goods"
        }
    ],
    "sg:phone":"+61 417 022 900",
    "sg:postcode":"2144",
    "sg:province":"NSW",
    "sg:tags":[
        "shutter",
        "roller",
        "grille"
    ],
    "wof:name":"CeeVee Roller Shutters Pty Ltd",
    "wof:placetype":"venue"
},
  "geometry": {"coordinates":[151.03314209000001,-33.8470726013],"type":"Point"}
}