{
  "type": "Feature",
  "properties": {
    "addr:full":"PO Box 30 Caringbah NSW 1495",
    "addr:postcode":"1495",
    "iso:country":"AU",
    "sg:address":"PO Box 30",
    "sg:city":"Caringbah",
    "sg:classifiers":[
        {
            "category":"Building & Trades",
            "subcategory":"Construction",
            "type":"Services"
        }
    ],
    "sg:phone":"+61 2 9585 1777",
    "sg:postcode":"1495",
    "sg:province":"NSW",
    "sg:tags":[
        "window",
        "tinting"
    ],
    "wof:name":"A1 Window Tinting",
    "wof:placetype":"venue"
},
  "geometry": {"coordinates":[151.121475,-34.046501],"type":"Point"}
}