{
  "type": "Feature",
  "properties": {
    "addr:full":"Shop 1/4 1283 Pt Nepean Rd Rosebud VIC 3939",
    "addr:housenumber":"shop 1 / 4",
    "addr:postcode":"1283;3939",
    "addr:street":"Pt Nepean Rd",
    "iso:country":"AU",
    "sg:address":"Shop 1/4 1283 Pt Nepean Rd",
    "sg:city":"Rosebud",
    "sg:classifiers":[
        {
            "category":"Building & Trades",
            "subcategory":"Landscaping Services",
            "type":"Services"
        }
    ],
    "sg:phone":"+61 3 5986 2466",
    "sg:postcode":"3939",
    "sg:province":"VIC",
    "sg:tags":[
        "consultant"
    ],
    "wof:name":"Nepean Building Permits & Consultants",
    "wof:placetype":"venue"
},
  "geometry": {"coordinates":[144.89468383799999,-38.358669281],"type":"Point"}
}