{
  "type": "Feature",
  "properties": {
    "addr:full":"16c Hayes Ave Yokine WA 6060",
    "addr:housenumber":"16c",
    "addr:postcode":"6060",
    "addr:street":"Hayes Ave",
    "iso:country":"AU",
    "sg:address":"16c Hayes Ave",
    "sg:city":"Yokine",
    "sg:classifiers":[
        {
            "category":"Shopping",
            "subcategory":"Beauty & Cosmetics",
            "type":"Retail Goods"
        }
    ],
    "sg:phone":"+61 8 9440 5797",
    "sg:postcode":"6060",
    "sg:province":"WA",
    "wof:name":"Timlu Distributors",
    "wof:placetype":"venue"
},
  "geometry": {"coordinates":[115.852180481,-31.8998985291],"type":"Point"}
}