{
  "type": "Feature",
  "properties": {
    "addr:full":"53 Rupert St Bairnsdale VIC 3875",
    "addr:housenumber":"53",
    "addr:postcode":"3875",
    "addr:street":"Rupert St",
    "iso:country":"AU",
    "sg:address":"53 Rupert St",
    "sg:city":"Bairnsdale",
    "sg:classifiers":[
        {
            "category":"Personal",
            "subcategory":"Hair Removal",
            "type":"Services"
        }
    ],
    "sg:phone":"+61 3 5153 1699",
    "sg:postcode":"3875",
    "sg:province":"VIC",
    "wof:name":"Leonie Eynstone",
    "wof:placetype":"venue"
},
  "geometry": {"coordinates":[147.62654113799999,-37.8309440613],"type":"Point"}
}