{
  "type": "Feature",
  "properties": {
    "addr:full":"9 Opal La Emerald QLD 4720",
    "addr:housenumber":"9",
    "addr:postcode":"4720",
    "addr:street":"Opal La",
    "iso:country":"AU",
    "sg:address":"9 Opal La",
    "sg:city":"Emerald",
    "sg:classifiers":[
        {
            "category":"Building & Trades",
            "subcategory":"Pest Control",
            "type":"Services"
        }
    ],
    "sg:phone":"+61 1300 858 510",
    "sg:postcode":"4720",
    "sg:province":"QLD",
    "wof:name":"JWK Services Pty Ltd",
    "wof:placetype":"venue"
},
  "geometry": {"coordinates":[148.166977,-23.520231],"type":"Point"}
}