{
  "type": "Feature",
  "properties": {
    "iso:country":"AU",
    "sg:address":"345 Windsor Rd",
    "sg:city":"Baulkham Hills",
    "sg:classifiers":[
        {
            "category":"Real Estate",
            "subcategory":"Real Estate Agent",
            "type":"Services"
        }
    ],
    "sg:phone":"+61 2 9639 8200",
    "sg:postcode":"2153",
    "sg:province":"NSW",
    "sg:website":"http://www.raywhite.com",
    "wof:name":"Ray White Baulkham Hills",
    "wof:placetype":"venue"
},
  "geometry": {"coordinates":[150.990432739,-33.7592506409],"type":"Point"}
}