{
  "type": "Feature",
  "properties": {
    "addr:full":"130 Princes Hwy Arncliffe NSW 2205",
    "addr:housenumber":"130",
    "addr:postcode":"2205",
    "addr:street":"Princes Hwy",
    "iso:country":"AU",
    "sg:address":"130 Princes Hwy",
    "sg:city":"Arncliffe",
    "sg:classifiers":[
        {
            "category":"Autos & Motor Vehicles",
            "subcategory":"Automobile Sales",
            "type":"Retail Goods"
        }
    ],
    "sg:phone":"+61 2 9556 2113",
    "sg:postcode":"2205",
    "sg:province":"NSW",
    "sg:tags":[
        "car",
        "used"
    ],
    "wof:name":"Travellers Mate",
    "wof:placetype":"venue"
},
  "geometry": {"coordinates":[151.14854399999999,-33.938435],"type":"Point"}
}