{
  "type": "Feature",
  "properties": {
    "iso:country":"AU",
    "sg:address":"20 Pearl St",
    "sg:city":"Newtown",
    "sg:classifiers":[
        {
            "category":"Manufacturing",
            "subcategory":"Food",
            "type":"Manufacturing & Wholesale Goods"
        }
    ],
    "sg:phone":"+61 2 9516 5038",
    "sg:postcode":"2042",
    "sg:province":"NSW",
    "sg:tags":[
        "function",
        "catering"
    ],
    "wof:name":"Pan Ultimate Catering",
    "wof:placetype":"venue"
},
  "geometry": {"coordinates":[151.177322,-33.904808],"type":"Point"}
}