{
  "type": "Feature",
  "properties": {
    "iso:country":"AU",
    "sg:address":"76 Newman St",
    "sg:city":"Thornbury",
    "sg:classifiers":[
        {
            "category":"Manufacturing",
            "subcategory":"Wood Products",
            "type":"Manufacturing & Wholesale Goods"
        }
    ],
    "sg:phone":"+61 3 9386 1188",
    "sg:postcode":"3071",
    "sg:province":"VIC",
    "sg:tags":[
        "polisher",
        "french"
    ],
    "wof:name":"Antique Restorations By Wakim Pty Ltd",
    "wof:placetype":"venue"
},
  "geometry": {"coordinates":[144.98246765100001,-37.7556343079],"type":"Point"}
}