{
  "type": "Feature",
  "properties": {
    "addr:full":"Shop 3B, 156-168 City Arcade Queen St Campbelltown NSW 2560",
    "addr:housenumber":"shop 3b",
    "addr:postcode":"156-168;2560",
    "addr:street":"Queen St",
    "iso:country":"AU",
    "sg:address":"Shop 3B, 156-168 City Arcade Queen St",
    "sg:city":"Campbelltown",
    "sg:classifiers":[
        {
            "category":"Shopping",
            "subcategory":"Party Supplies",
            "type":"Retail Goods"
        }
    ],
    "sg:phone":"+61 2 4627 6599",
    "sg:postcode":"2560",
    "sg:province":"NSW",
    "wof:name":"Ace One Stop Party Shop",
    "wof:placetype":"venue"
},
  "geometry": {"coordinates":[150.814697266,-34.0664024353],"type":"Point"}
}