{
  "type": "Feature",
  "properties": {
    "iso:country":"AU",
    "sg:address":"3/ 90 Faunce St",
    "sg:city":"Gosford",
    "sg:classifiers":[
        {
            "category":"Health Services",
            "subcategory":"Health Practitioner",
            "type":"Services"
        }
    ],
    "sg:phone":"+61 413 641 339",
    "sg:postcode":"2250",
    "sg:province":"NSW",
    "sg:tags":[
        "herbalist"
    ],
    "wof:name":"Wu Y",
    "wof:placetype":"venue"
},
  "geometry": {"coordinates":[151.33827209500001,-33.4221763611],"type":"Point"}
}