{
  "type": "Feature",
  "properties": {
    "addr:full":"Lot 3 Cnr Cambridge & Teranca Rds Greenfields WA 6210",
    "addr:housenumber":"cnr",
    "addr:postcode":"6210",
    "addr:street":"Cambridge & Teranca Rds",
    "iso:country":"AU",
    "sg:address":"Lot 3 Cnr Cambridge & Teranca Rds",
    "sg:city":"Greenfields",
    "sg:classifiers":[
        {
            "category":"Social Services",
            "subcategory":"Child Care",
            "type":"Services"
        }
    ],
    "sg:phone":"+61 8 9534 9577",
    "sg:postcode":"6210",
    "sg:province":"WA",
    "wof:name":"ABC Learning Centres",
    "wof:placetype":"venue"
},
  "geometry": {"coordinates":[115.76223,-32.537018],"type":"Point"}
}