{
  "type": "Feature",
  "properties": {
    "addr:full":"Rear 42 Anderson Rd Mortdale NSW 2223",
    "addr:housenumber":"42",
    "addr:postcode":"2223",
    "addr:street":"Anderson Rd",
    "iso:country":"AU",
    "sg:address":"Rear 42 Anderson Rd",
    "sg:city":"Mortdale",
    "sg:classifiers":[
        {
            "category":"Professional",
            "subcategory":"Engineering",
            "type":"Services"
        }
    ],
    "sg:phone":"+61 2 9580 7869",
    "sg:postcode":"2223",
    "sg:province":"NSW",
    "sg:tags":[
        "engineer"
    ],
    "wof:name":"Anjor Engineering",
    "wof:placetype":"venue"
},
  "geometry": {"coordinates":[151.067092895,-33.9675827026],"type":"Point"}
}