{
  "type": "Feature",
  "properties": {
    "addr:full":"326 Eddystone Ave Heathridge WA 6027",
    "addr:housenumber":"326",
    "addr:postcode":"6027",
    "addr:street":"Eddystone Ave",
    "iso:country":"AU",
    "sg:address":"326 Eddystone Ave",
    "sg:city":"Heathridge",
    "sg:classifiers":[
        {
            "category":"Building & Trades",
            "subcategory":"Plumbing",
            "type":"Services"
        }
    ],
    "sg:phone":"+61 402 120 626",
    "sg:postcode":"6027",
    "sg:province":"WA",
    "sg:tags":[
        "plumber",
        "gasfitters"
    ],
    "wof:name":"Andys Waterworks",
    "wof:placetype":"venue"
},
  "geometry": {"coordinates":[115.77050781200001,-31.7636241913],"type":"Point"}
}