{
  "type": "Feature",
  "properties": {
    "addr:full":"65 Monaro St Queanbeyan NSW 2620",
    "addr:housenumber":"65",
    "addr:postcode":"2620",
    "addr:street":"Monaro St",
    "iso:country":"AU",
    "sg:address":"65 Monaro St",
    "sg:city":"Queanbeyan",
    "sg:classifiers":[
        {
            "category":"Shopping",
            "subcategory":"Jewelry",
            "type":"Retail Goods"
        }
    ],
    "sg:phone":"+61 2 6297 6904",
    "sg:postcode":"2620",
    "sg:province":"NSW",
    "sg:tags":[
        "jeweller"
    ],
    "wof:name":"Today's Jewellers",
    "wof:placetype":"venue"
},
  "geometry": {"coordinates":[149.23358154300001,-35.3535194397],"type":"Point"}
}