{
  "type": "Feature",
  "properties": {
    "addr:full":"43 Maitland St Narrabri NSW 2390",
    "addr:housenumber":"43",
    "addr:postcode":"2390",
    "addr:street":"Maitland St",
    "iso:country":"AU",
    "sg:address":"43 Maitland St",
    "sg:city":"Narrabri",
    "sg:classifiers":[
        {
            "category":"Real Estate",
            "subcategory":"Real Estate Agent",
            "type":"Services"
        }
    ],
    "sg:phone":"+61 2 6792 4522",
    "sg:postcode":"2390",
    "sg:province":"NSW",
    "sg:tags":[
        "handyman's",
        "equipment",
        "hire",
        "builders",
        "contractor"
    ],
    "wof:name":"Campbells Hire",
    "wof:placetype":"venue"
},
  "geometry": {"coordinates":[149.78538513199999,-30.3295269012],"type":"Point"}
}