{
  "type": "Feature",
  "properties": {
    "addr:full":"Shop T294 West Lakes Mall 111 West Lakes Blv West Lakes SA 5021",
    "addr:housenumber":"t294;111",
    "addr:postcode":"5021",
    "addr:street":"West Lakes Blv",
    "iso:country":"AU",
    "sg:address":"Shop T294 West Lakes Mall 111 West Lakes Blv",
    "sg:city":"West Lakes",
    "sg:classifiers":[
        {
            "category":"Cafe",
            "type":"Food & Drink"
        }
    ],
    "sg:phone":"+61 8 8353 0070",
    "sg:postcode":"5021",
    "sg:province":"SA",
    "wof:name":"Gloria Jean's Coffees",
    "wof:placetype":"venue"
},
  "geometry": {"coordinates":[138.488006592,-34.8724136353],"type":"Point"}
}