{
  "type": "Feature",
  "properties": {
    "iso:country":"AU",
    "sg:address":"2/ 112 Dunheved Cct",
    "sg:city":"Dunheved",
    "sg:classifiers":[
        {
            "category":"Manufacturing",
            "subcategory":"Motor Vehicles & Parts",
            "type":"Manufacturing & Wholesale Goods"
        }
    ],
    "sg:phone":"+61 2 9833 0216",
    "sg:postcode":"2760",
    "sg:province":"NSW",
    "sg:tags":[
        "replacement"
    ],
    "wof:name":"Suzuki Wreckers",
    "wof:placetype":"venue"
},
  "geometry": {"coordinates":[150.774459839,-33.7462272644],"type":"Point"}
}