{
  "type": "Feature",
  "properties": {
    "addr:full":"61 Volitans Rd Mt Eliza VIC 3930",
    "addr:housenumber":"61",
    "addr:postcode":"3930",
    "addr:street":"Volitans Rd",
    "iso:country":"AU",
    "sg:address":"61 Volitans Rd",
    "sg:city":"Mt Eliza",
    "sg:classifiers":[
        {
            "category":"Utilities",
            "subcategory":"Electric",
            "type":"Services"
        }
    ],
    "sg:phone":"+61 417 566 361",
    "sg:postcode":"3930",
    "sg:province":"VIC",
    "sg:tags":[
        "electrical",
        "contractor"
    ],
    "wof:name":"Richard Evans Electricians",
    "wof:placetype":"venue"
},
  "geometry": {"coordinates":[145.07911682100001,-38.2005004883],"type":"Point"}
}