{
  "type": "Feature",
  "properties": {
    "iso:country":"AU",
    "sg:address":"658 Burke Rd",
    "sg:city":"Camberwell",
    "sg:classifiers":[
        {
            "category":"Shopping",
            "subcategory":"Clothing, Apparel, & Fashions",
            "type":"Retail Goods"
        }
    ],
    "sg:phone":"+61 3 9882 5866",
    "sg:postcode":"3124",
    "sg:province":"VIC",
    "sg:tags":[
        "lingerie",
        "hosiery",
        "sleepwear"
    ],
    "wof:name":"La Figure Lingerie",
    "wof:placetype":"venue"
},
  "geometry": {"coordinates":[145.057373047,-37.8286018372],"type":"Point"}
}