{
  "type": "Feature",
  "properties": {
    "addr:full":"Level 1, 38- 40 Garden St South Yarra VIC 3141",
    "addr:housenumber":"38 40",
    "addr:postcode":"3141",
    "addr:street":"Garden St",
    "iso:country":"AU",
    "sg:address":"Level 1, 38- 40 Garden St",
    "sg:city":"South Yarra",
    "sg:classifiers":[
        {
            "category":"Travel",
            "subcategory":"Travel Agent",
            "type":"Entertainment"
        }
    ],
    "sg:phone":"+61 3 9823 8333",
    "sg:postcode":"3141",
    "sg:province":"VIC",
    "sg:tags":[
        "wholesaler"
    ],
    "wof:name":"Fiji- Executive Destinations",
    "wof:placetype":"venue"
},
  "geometry": {"coordinates":[144.996994019,-37.8433761597],"type":"Point"}
}