{
  "type": "Feature",
  "properties": {
    "addr:full":"Factory 75 Triholm Ave Laverton VIC 3028",
    "addr:housenumber":"75",
    "addr:postcode":"3028",
    "addr:street":"Triholm Ave",
    "iso:country":"AU",
    "sg:address":"Factory 75 Triholm Ave",
    "sg:city":"Laverton",
    "sg:classifiers":[
        {
            "category":"Education",
            "subcategory":"Dance Studio",
            "type":"Public Place"
        }
    ],
    "sg:phone":"+61 414 830 723",
    "sg:postcode":"3028",
    "sg:province":"VIC",
    "sg:tags":[
        "venue",
        "tuition"
    ],
    "wof:name":"Dance Lane",
    "wof:placetype":"venue"
},
  "geometry": {"coordinates":[144.756271,-37.868439],"type":"Point"}
}