{
  "type": "Feature",
  "properties": {
    "iso:country":"AU",
    "sg:address":"281 Darebin Rd",
    "sg:city":"Thornbury",
    "sg:classifiers":[
        {
            "category":"Manufacturing",
            "subcategory":"Food",
            "type":"Manufacturing & Wholesale Goods"
        }
    ],
    "sg:phone":"+61 3 9480 1331",
    "sg:postcode":"3071",
    "sg:province":"VIC",
    "sg:tags":[
        "function",
        "catering"
    ],
    "sg:website":"http://www.darebincitybowls.com.au",
    "wof:name":"Darebin City Bowls Club Inc",
    "wof:placetype":"venue"
},
  "geometry": {"coordinates":[145.02403259299999,-37.765712738],"type":"Point"}
}