{
  "type": "Feature",
  "properties": {
    "addr:full":"Level 1, 240 Pakington St Geelong West VIC 3218",
    "addr:housenumber":"240",
    "addr:postcode":"3218",
    "addr:street":"Pakington St",
    "iso:country":"AU",
    "sg:address":"Level 1, 240 Pakington St",
    "sg:city":"Geelong West",
    "sg:classifiers":[
        {
            "category":"Banks & Credit Unions",
            "subcategory":"Financial Services",
            "type":"Services"
        }
    ],
    "sg:phone":"+61 3 5221 7700",
    "sg:postcode":"3218",
    "sg:province":"VIC",
    "sg:tags":[
        "planning"
    ],
    "wof:name":"PB Financial Solutions",
    "wof:placetype":"venue"
},
  "geometry": {"coordinates":[144.34791564899999,-38.1436195374],"type":"Point"}
}