{
  "type": "Feature",
  "properties": {
    "iso:country":"AU",
    "sg:address":"63 High St",
    "sg:city":"Boonah",
    "sg:classifiers":[
        {
            "category":"Cafe",
            "type":"Food & Drink"
        }
    ],
    "sg:phone":"+61 7 5463 2075",
    "sg:postcode":"4310",
    "sg:province":"QLD",
    "wof:name":"Art & Soul Cafe",
    "wof:placetype":"venue"
},
  "geometry": {"coordinates":[152.6824646,-27.9950752258],"type":"Point"}
}