{
  "type": "Feature",
  "properties": {
    "addr:full":"Unit 2/ 35 Birch St Condell Park NSW 2200",
    "addr:housenumber":"35",
    "addr:postcode":"2200",
    "addr:street":"Birch St",
    "iso:country":"AU",
    "sg:address":"Unit 2/ 35 Birch St",
    "sg:city":"Condell Park",
    "sg:classifiers":[
        {
            "category":"Building & Trades",
            "subcategory":"Plumbing",
            "type":"Services"
        }
    ],
    "sg:phone":"+61 2 9791 0993",
    "sg:postcode":"2200",
    "sg:province":"NSW",
    "sg:tags":[
        "pump",
        "repairer"
    ],
    "sg:website":"http://www.propump.com.au",
    "wof:name":"Propump Services",
    "wof:placetype":"venue"
},
  "geometry": {"coordinates":[150.99847399999999,-33.915977],"type":"Point"}
}