{
  "type": "Feature",
  "properties": {
    "iso:country":"AU",
    "sg:address":"310 Summer St",
    "sg:city":"Orange",
    "sg:classifiers":[
        {
            "category":"Fast Food",
            "type":"Food & Drink"
        }
    ],
    "sg:phone":"+61 2 6362 5628",
    "sg:postcode":"2800",
    "sg:province":"NSW",
    "sg:tags":[
        "away",
        "take"
    ],
    "wof:name":"Chopsticks Take Away",
    "wof:placetype":"venue"
},
  "geometry": {"coordinates":[149.10296630900001,-33.2841453552],"type":"Point"}
}