{
  "type": "Feature",
  "properties": {
    "addr:full":"Davidson Rd Euramo QLD 4854",
    "addr:postcode":"4854",
    "addr:street":"Davidson Rd",
    "iso:country":"AU",
    "sg:address":"Davidson Rd",
    "sg:city":"Euramo",
    "sg:classifiers":[
        {
            "category":"Farming",
            "subcategory":"Farm",
            "type":"Manufacturing & Wholesale Goods"
        }
    ],
    "sg:phone":"+61 7 4066 7706",
    "sg:postcode":"4854",
    "sg:province":"QLD",
    "sg:tags":[
        "farmer"
    ],
    "wof:name":"Jenkins W J & C A",
    "wof:placetype":"venue"
},
  "geometry": {"coordinates":[145.92738342300001,-18.004732132],"type":"Point"}
}