{
  "type": "Feature",
  "properties": {
    "iso:country":"AU",
    "sg:address":"700 Logan Rd",
    "sg:city":"Greenslopes",
    "sg:classifiers":[
        {
            "category":"Shopping",
            "subcategory":"Jewelry",
            "type":"Retail Goods"
        }
    ],
    "sg:phone":"+61 7 3397 2659",
    "sg:postcode":"4120",
    "sg:province":"QLD",
    "sg:tags":[
        "jeweller"
    ],
    "wof:name":"Simply Charmed Jewellery & Gifts",
    "wof:placetype":"venue"
},
  "geometry": {"coordinates":[153.05331420900001,-27.5121440887],"type":"Point"}
}