{
  "type": "Feature",
  "properties": {
    "addr:full":"268 Raymond St Sale VIC 3850",
    "addr:housenumber":"268",
    "addr:postcode":"3850",
    "addr:street":"Raymond St",
    "iso:country":"AU",
    "sg:address":"268 Raymond St",
    "sg:city":"Sale",
    "sg:classifiers":[
        {
            "category":"Travel",
            "subcategory":"Travel Agent",
            "type":"Entertainment"
        }
    ],
    "sg:phone":"+61 13 27 57",
    "sg:postcode":"3850",
    "sg:province":"VIC",
    "sg:tags":[
        "consultant"
    ],
    "wof:name":"Harvey World Travel Sale",
    "wof:placetype":"venue"
},
  "geometry": {"coordinates":[147.06578064000001,-38.107711792],"type":"Point"}
}