{
  "type": "Feature",
  "properties": {
    "iso:country":"AU",
    "sg:address":"Shop 38",
    "sg:city":", Lakes Village Shopping Centre Mt Gambier",
    "sg:classifiers":[
        {
            "category":"Shopping",
            "subcategory":"Jewelry",
            "type":"Retail Goods"
        }
    ],
    "sg:phone":"+61 8 8725 2700",
    "sg:postcode":"5290",
    "sg:province":"SA",
    "sg:tags":[
        "jeweller"
    ],
    "wof:name":"Zamels",
    "wof:placetype":"venue"
},
  "geometry": {"coordinates":[140.78329500000001,-37.826321],"type":"Point"}
}