{
  "type": "Feature",
  "properties": {
    "iso:country":"AU",
    "sg:address":"Suite 332, 80 The Pines",
    "sg:city":"Elanora",
    "sg:classifiers":[
        {
            "category":"Education",
            "subcategory":"Special Training",
            "type":"Public Place"
        }
    ],
    "sg:phone":"+61 424 716 190",
    "sg:postcode":"4221",
    "sg:province":"QLD",
    "sg:tags":[
        "development"
    ],
    "wof:name":"Square Orange Corporate Training",
    "wof:placetype":"venue"
},
  "geometry": {"coordinates":[153.46052551299999,-28.1234397888],"type":"Point"}
}