{
  "type": "Feature",
  "properties": {
    "addr:full":"Suite 3, Macquarie Court, 180 Main Rd Speers Point NSW 2284",
    "addr:housenumber":"180",
    "addr:postcode":"2284",
    "addr:street":"Macquarie;Main Rd",
    "iso:country":"AU",
    "sg:address":"Suite 3, Macquarie Court, 180 Main Rd",
    "sg:city":"Speers Point",
    "sg:classifiers":[
        {
            "category":"Social Services",
            "subcategory":"Retirement Home",
            "type":"Services"
        }
    ],
    "sg:phone":"+61 2 4946 3300",
    "sg:postcode":"2284",
    "sg:province":"NSW",
    "sg:tags":[
        "environmental",
        "consultant",
        "pollution"
    ],
    "wof:name":"Heggies Australia",
    "wof:placetype":"venue"
},
  "geometry": {"coordinates":[151.62286376899999,-32.9639968872],"type":"Point"}
}