{
  "type": "Feature",
  "properties": {
    "addr:full":"Unit 16, 1-13 Atkinson Rd Taren Point NSW 2229",
    "addr:housenumber":"1-13",
    "addr:postcode":"2229",
    "addr:street":"Atkinson Rd",
    "iso:country":"AU",
    "sg:address":"Unit 16, 1-13 Atkinson Rd",
    "sg:city":"Taren Point",
    "sg:classifiers":[
        {
            "category":"Wholesale",
            "subcategory":"Painting Supplies",
            "type":"Manufacturing & Wholesale Goods"
        }
    ],
    "sg:phone":"+61 2 9525 5102",
    "sg:postcode":"2229",
    "sg:province":"NSW",
    "sg:tags":[
        "product",
        "cleaning"
    ],
    "wof:name":"Esime & Company Australia Pty Ltd",
    "wof:placetype":"venue"
},
  "geometry": {"coordinates":[151.12957763700001,-34.0224571228],"type":"Point"}
}