{
  "type": "Feature",
  "properties": {
    "addr:full":"9 Hocking Pl Erskine Park NSW 2759",
    "addr:housenumber":"9",
    "addr:postcode":"2759",
    "addr:street":"Hocking Pl",
    "iso:country":"AU",
    "sg:address":"9 Hocking Pl",
    "sg:city":"Erskine Park",
    "sg:classifiers":[
        {
            "category":"Utilities",
            "subcategory":"Refuse",
            "type":"Services"
        }
    ],
    "sg:phone":"+61 2 9670 1173",
    "sg:postcode":"2759",
    "sg:province":"NSW",
    "sg:tags":[
        "remover",
        "rubbish"
    ],
    "wof:name":"Peakeys Mini Skips",
    "wof:placetype":"venue"
},
  "geometry": {"coordinates":[150.80743408199999,-33.8061561584],"type":"Point"}
}