{
  "type": "Feature",
  "properties": {
    "addr:full":"Cnr Cheddar Rd & Orrong Ave Reservoir VIC 3073",
    "addr:postcode":"3073",
    "addr:street":"Cnr Cheddar Rd & Orrong Ave",
    "iso:country":"AU",
    "sg:address":"Cnr Cheddar Rd & Orrong Ave",
    "sg:city":"Reservoir",
    "sg:classifiers":[
        {
            "category":"Personal",
            "subcategory":"Massage",
            "type":"Services"
        }
    ],
    "sg:phone":"+61 3 9469 3157",
    "sg:postcode":"3073",
    "sg:province":"VIC",
    "sg:tags":[
        "therapy"
    ],
    "wof:name":"A.N.T.A.R. Massage",
    "wof:placetype":"venue"
},
  "geometry": {"coordinates":[145.009765625,-37.7137832642],"type":"Point"}
}