{
  "type": "Feature",
  "properties": {
    "addr:full":"Unit 5/ 29 Macquarie Drv Thomastown VIC 3074",
    "addr:housenumber":"29",
    "addr:postcode":"3074",
    "addr:street":"Macquarie Drv",
    "iso:country":"AU",
    "sg:address":"Unit 5/ 29 Macquarie Drv",
    "sg:city":"Thomastown",
    "sg:classifiers":[
        {
            "category":"Professional",
            "subcategory":"Detective & Security Services",
            "type":"Services"
        }
    ],
    "sg:phone":"+61 3 9466 1645",
    "sg:postcode":"3074",
    "sg:province":"VIC",
    "sg:tags":[
        "consultant",
        "system"
    ],
    "wof:name":"Safeway Safe Removals",
    "wof:placetype":"venue"
},
  "geometry": {"coordinates":[145.03102111800001,-37.6902580261],"type":"Point"}
}