{
  "type": "Feature",
  "properties": {
    "iso:country":"AU",
    "sg:address":"3 Melita Rd",
    "sg:city":"Cambridge Park",
    "sg:classifiers":[
        {
            "category":"Retail",
            "subcategory":"Auto Repair",
            "type":"Services"
        }
    ],
    "sg:phone":"+61 2 4721 2025",
    "sg:postcode":"2747",
    "sg:province":"NSW",
    "sg:tags":[
        "electrical"
    ],
    "wof:name":"Penrith Auto Electric Mobile Service",
    "wof:placetype":"venue"
},
  "geometry": {"coordinates":[150.72277832,-33.7506828308],"type":"Point"}
}