{
  "type": "Feature",
  "properties": {
    "iso:country":"AU",
    "sg:address":"Karrinyup Rd",
    "sg:city":"Karrinyup",
    "sg:classifiers":[
        {
            "category":"Shopping",
            "subcategory":"Department Store",
            "type":"Retail Goods"
        }
    ],
    "sg:phone":"+61 8 9347 9200",
    "sg:postcode":"6018",
    "sg:province":"WA",
    "wof:name":"Myer Pty Ltd",
    "wof:placetype":"venue"
},
  "geometry": {"coordinates":[115.77133178699999,-31.8735256195],"type":"Point"}
}