{
  "type": "Feature",
  "properties": {
    "iso:country":"AU",
    "sg:address":"9 Queens Ave",
    "sg:city":"Hawthorn",
    "sg:classifiers":[
        {
            "category":"Building & Trades",
            "subcategory":"Construction",
            "type":"Services"
        }
    ],
    "sg:phone":"+61 3 9815 3566",
    "sg:postcode":"3122",
    "sg:province":"VIC",
    "sg:tags":[
        "contractor"
    ],
    "wof:name":"BuildingMakers Pty Ltd",
    "wof:placetype":"venue"
},
  "geometry": {"coordinates":[145.04301452600001,-37.8226928711],"type":"Point"}
}