{
  "type": "Feature",
  "properties": {
    "addr:full":"29 Knightsbridge Crs Mullaloo WA 6027",
    "addr:housenumber":"29",
    "addr:postcode":"6027",
    "addr:street":"Knightsbridge Crs",
    "iso:country":"AU",
    "sg:address":"29 Knightsbridge Crs",
    "sg:city":"Mullaloo",
    "sg:classifiers":[
        {
            "category":"Building & Trades",
            "subcategory":"Landscaping Services",
            "type":"Services"
        }
    ],
    "sg:phone":"+61 8 9401 7209",
    "sg:postcode":"6027",
    "sg:province":"WA",
    "sg:tags":[
        "consultant"
    ],
    "wof:name":"BCS Building Consultancy Services",
    "wof:placetype":"venue"
},
  "geometry": {"coordinates":[115.74329376199999,-31.7780704498],"type":"Point"}
}