{
  "type": "Feature",
  "properties": {
    "addr:full":"U2/ 200 Wallace St Braidwood NSW 2622",
    "addr:housenumber":"200",
    "addr:postcode":"2622",
    "addr:street":"U2 /;Wallace St",
    "iso:country":"AU",
    "sg:address":"U2/ 200 Wallace St",
    "sg:city":"Braidwood",
    "sg:classifiers":[
        {
            "category":"Personal",
            "subcategory":"Beauty Salon",
            "type":"Services"
        }
    ],
    "sg:phone":"+61 2 4842 1588",
    "sg:postcode":"2622",
    "sg:province":"NSW",
    "sg:tags":[
        "hairdresser"
    ],
    "wof:name":"Braidwood Hair Studio",
    "wof:placetype":"venue"
},
  "geometry": {"coordinates":[149.801223755,-35.4366874695],"type":"Point"}
}