{
  "type": "Feature",
  "properties": {
    "iso:country":"AU",
    "sg:address":"47 Palm St",
    "sg:city":"St Ives",
    "sg:classifiers":[
        {
            "category":"Insurance",
            "subcategory":"Insurance Agent",
            "type":"Services"
        }
    ],
    "sg:phone":"+61 2 9449 9854",
    "sg:postcode":"2075",
    "sg:province":"NSW",
    "wof:name":"Warren-Smith Tony",
    "wof:placetype":"venue"
},
  "geometry": {"coordinates":[151.16891479500001,-33.713924408],"type":"Point"}
}