{
  "type": "Feature",
  "properties": {
    "addr:full":"Nelson St Wauchope NSW 2446",
    "addr:postcode":"2446",
    "addr:street":"Nelson St",
    "iso:country":"AU",
    "sg:address":"Nelson St",
    "sg:city":"Wauchope",
    "sg:classifiers":[
        {
            "category":"Education",
            "subcategory":"School",
            "type":"Public Place"
        }
    ],
    "sg:phone":"+61 2 6585 1400",
    "sg:postcode":"2446",
    "sg:province":"NSW",
    "sg:tags":[
        "state",
        "-",
        "nsw"
    ],
    "wof:name":"Wauchope High School",
    "wof:placetype":"venue"
},
  "geometry": {"coordinates":[152.73173499999999,-31.452028],"type":"Point"}
}