{
  "type": "Feature",
  "properties": {
    "addr:full":"211 Bondi Rd Bondi NSW 2026",
    "addr:housenumber":"211",
    "addr:postcode":"2026",
    "addr:street":"Bondi Rd",
    "iso:country":"AU",
    "sg:address":"211 Bondi Rd",
    "sg:city":"Bondi",
    "sg:classifiers":[
        {
            "category":"Restaurant",
            "type":"Food & Drink"
        }
    ],
    "sg:phone":"+61 2 9130 7166",
    "sg:postcode":"2026",
    "sg:province":"NSW",
    "wof:name":"Big John's Kitchen",
    "wof:placetype":"venue"
},
  "geometry": {"coordinates":[151.26568603499999,-33.8943519592],"type":"Point"}
}