{
  "type": "Feature",
  "properties": {
    "iso:country":"AU",
    "sg:address":"704 Beaudesert Rd",
    "sg:city":"Salisbury",
    "sg:classifiers":[
        {
            "category":"Retail",
            "subcategory":"Auto Repair",
            "type":"Services"
        }
    ],
    "sg:phone":"+61 7 3343 9440",
    "sg:postcode":"4107",
    "sg:province":"QLD",
    "sg:tags":[
        "beater",
        "painter",
        "panel"
    ],
    "wof:name":"Mitch's Smash Repairs",
    "wof:placetype":"venue"
},
  "geometry": {"coordinates":[153.020874023,-27.5566368103],"type":"Point"}
}