{
  "type": "Feature",
  "properties": {
    "addr:full":"Shop 4 Cocos Food Fair Cnr Goodings & Nerang Broadbeach Rds Carrara QLD 4211",
    "addr:housenumber":"shop 4",
    "addr:postcode":"4211",
    "addr:street":"Cnr Goodings & Nerang;Rds",
    "iso:country":"AU",
    "sg:address":"Shop 4 Cocos Food Fair Cnr Goodings & Nerang Broadbeach Rds",
    "sg:city":"Carrara",
    "sg:classifiers":[
        {
            "category":"Food & Beverages",
            "subcategory":"Bakery",
            "type":"Retail Goods"
        }
    ],
    "sg:phone":"+61 7 5579 9550",
    "sg:postcode":"4211",
    "sg:province":"QLD",
    "sg:tags":[
        "baker"
    ],
    "wof:name":"Brumby's Bakeries",
    "wof:placetype":"venue"
},
  "geometry": {"coordinates":[153.366653442,-28.0085773468],"type":"Point"}
}