{
  "type": "Feature",
  "properties": {
    "addr:full":"Level 1/ 225 Chapel St Prahran VIC 3181",
    "addr:housenumber":"/ 225",
    "addr:postcode":"3181",
    "addr:street":"Chapel St",
    "iso:country":"AU",
    "sg:address":"Level 1/ 225 Chapel St",
    "sg:city":"Prahran",
    "sg:classifiers":[
        {
            "category":"Shopping",
            "subcategory":"Computers & Home Electronics",
            "type":"Retail Goods"
        }
    ],
    "sg:phone":"+61 3 9533 6225",
    "sg:postcode":"3181",
    "sg:province":"VIC",
    "sg:tags":[
        "equipment",
        "multimedia"
    ],
    "wof:name":"Blank Motion Studios",
    "wof:placetype":"venue"
},
  "geometry": {"coordinates":[144.99339294399999,-37.8506164551],"type":"Point"}
}