{
  "type": "Feature",
  "properties": {
    "iso:country":"AU",
    "sg:address":"12 Kundabung Rd",
    "sg:city":"Kundabung",
    "sg:classifiers":[
        {
            "category":"Building & Trades",
            "subcategory":"Construction",
            "type":"Services"
        }
    ],
    "sg:phone":"+61 2 6561 5029",
    "sg:postcode":"2441",
    "sg:province":"NSW",
    "sg:tags":[
        "contractor"
    ],
    "wof:name":"Scaysbrook A B",
    "wof:placetype":"venue"
},
  "geometry": {"coordinates":[152.837418,-31.15987],"type":"Point"}
}