{
  "type": "Feature",
  "properties": {
    "addr:full":"421 Keilor Rd Niddrie VIC 3042",
    "addr:housenumber":"421",
    "addr:postcode":"3042",
    "addr:street":"Keilor Rd",
    "iso:country":"AU",
    "sg:address":"421 Keilor Rd",
    "sg:city":"Niddrie",
    "sg:classifiers":[
        {
            "category":"Banks & Credit Unions",
            "subcategory":"Bank",
            "type":"Services"
        }
    ],
    "sg:phone":"+61 3 9374 1911",
    "sg:postcode":"3042",
    "sg:province":"VIC",
    "wof:name":"National Australia Bank Ltd",
    "wof:placetype":"venue"
},
  "geometry": {"coordinates":[144.891082764,-37.7369346619],"type":"Point"}
}