{
  "type": "Feature",
  "properties": {
    "iso:country":"AU",
    "sg:address":"Shop 2, 86 Curragundi Rd",
    "sg:city":"Jindalee",
    "sg:classifiers":[
        {
            "category":"Food & Beverages",
            "subcategory":"Bakery",
            "type":"Retail Goods"
        }
    ],
    "sg:phone":"+61 7 3376 1487",
    "sg:postcode":"4074",
    "sg:province":"QLD",
    "sg:tags":[
        "baker"
    ],
    "wof:name":"Brumby's Bakeries",
    "wof:placetype":"venue"
},
  "geometry": {"coordinates":[152.93577575699999,-27.534822464],"type":"Point"}
}