{
  "type": "Feature",
  "properties": {
    "iso:country":"AU",
    "sg:address":"7 Henry St",
    "sg:city":"Gympie",
    "sg:classifiers":[
        {
            "category":"Health Services",
            "subcategory":"Doctor",
            "type":"Services"
        }
    ],
    "sg:phone":"+61 7 5482 5577",
    "sg:postcode":"4570",
    "sg:province":"QLD",
    "sg:tags":[
        "medical",
        "practitioner"
    ],
    "wof:name":"Henry St. Medical Clinic",
    "wof:placetype":"venue"
},
  "geometry": {"coordinates":[152.659713745,-26.1852378845],"type":"Point"}
}