{
  "type": "Feature",
  "properties": {
    "addr:full":"48 Winbourne Rd Brookvale NSW 2100",
    "addr:housenumber":"48",
    "addr:postcode":"2100",
    "addr:street":"Winbourne Rd",
    "iso:country":"AU",
    "sg:address":"48 Winbourne Rd",
    "sg:city":"Brookvale",
    "sg:classifiers":[
        {
            "category":"Wholesale",
            "subcategory":"Auto Parts",
            "type":"Manufacturing & Wholesale Goods"
        }
    ],
    "sg:phone":"+61 2 9905 8288",
    "sg:postcode":"2100",
    "sg:province":"NSW",
    "sg:tags":[
        "recyclers"
    ],
    "wof:name":"Suburban Installations Pty Ltd",
    "wof:placetype":"venue"
},
  "geometry": {"coordinates":[151.27662658700001,-33.762386322],"type":"Point"}
}