{
  "type": "Feature",
  "properties": {
    "iso:country":"AU",
    "sg:address":"Shop 3 26 Kingussie St",
    "sg:city":"Kenmore",
    "sg:classifiers":[
        {
            "category":"Personal",
            "subcategory":"Beauty Salon",
            "type":"Services"
        }
    ],
    "sg:phone":"+61 7 3378 6701",
    "sg:postcode":"4069",
    "sg:province":"QLD",
    "wof:name":"Erika's Beauty On The Park",
    "wof:placetype":"venue"
},
  "geometry": {"coordinates":[152.93055725100001,-27.5133533478],"type":"Point"}
}