{
  "type": "Feature",
  "properties": {
    "addr:full":"Shp T30,Erina Fair,Terrigal Drv Erina NSW 2250",
    "addr:postcode":"2250",
    "addr:street":"Terrigal Drv",
    "iso:country":"AU",
    "sg:address":"Shp T30,Erina Fair,Terrigal Drv",
    "sg:city":"Erina",
    "sg:classifiers":[
        {
            "category":"Shopping",
            "subcategory":"Clothing, Apparel, & Fashions",
            "type":"Retail Goods"
        }
    ],
    "sg:phone":"+61 2 4367 0855",
    "sg:postcode":"2250",
    "sg:province":"NSW",
    "sg:tags":[
        "accessory"
    ],
    "wof:name":"Js Room",
    "wof:placetype":"venue"
},
  "geometry": {"coordinates":[151.39523315400001,-33.4345855713],"type":"Point"}
}