{
  "type": "Feature",
  "properties": {
    "iso:country":"AU",
    "sg:address":"40 Payne St",
    "sg:city":"Caboolture",
    "sg:classifiers":[
        {
            "category":"Social Services",
            "type":"Services"
        }
    ],
    "sg:phone":"+61 7 5428 0633",
    "sg:postcode":"4510",
    "sg:province":"QLD",
    "sg:tags":[
        "disabled",
        "person",
        "equipment"
    ],
    "wof:name":"Adjust-A-Fit Medical Group",
    "wof:placetype":"venue"
},
  "geometry": {"coordinates":[152.979477,-27.079996],"type":"Point"}
}