{
  "type": "Feature",
  "properties": {
    "iso:country":"AU",
    "sg:address":"194 Jubilee Hwy",
    "sg:city":"East Mt Gambier",
    "sg:classifiers":[
        {
            "category":"Farming",
            "subcategory":"Nursery",
            "type":"Manufacturing & Wholesale Goods"
        }
    ],
    "sg:phone":"+61 8 8724 5555",
    "sg:postcode":"5290",
    "sg:province":"SA",
    "wof:name":"Van Schaiks Bio-Gro Pty Ltd",
    "wof:placetype":"venue"
},
  "geometry": {"coordinates":[140.759445,-37.816086],"type":"Point"}
}