{
  "type": "Feature",
  "properties": {
    "addr:full":"15 Knights Drv Glen Waverley VIC 3150",
    "addr:housenumber":"15",
    "addr:postcode":"3150",
    "addr:street":"Knights Drv",
    "iso:country":"AU",
    "sg:address":"15 Knights Drv",
    "sg:city":"Glen Waverley",
    "sg:classifiers":[
        {
            "category":"Professional",
            "subcategory":"Computer Services",
            "type":"Services"
        }
    ],
    "sg:phone":"+61 3 9886 3386",
    "sg:postcode":"3150",
    "sg:province":"VIC",
    "sg:tags":[
        "consultant",
        "system"
    ],
    "wof:name":"Customized Computer Systems",
    "wof:placetype":"venue"
},
  "geometry": {"coordinates":[145.187576294,-37.8719482422],"type":"Point"}
}