{
  "type": "Feature",
  "properties": {
    "iso:country":"AU",
    "sg:address":"19 Norfolk St",
    "sg:city":"Paddington",
    "sg:classifiers":[
        {
            "category":"Organizations",
            "subcategory":"Professional Association",
            "type":"Services"
        }
    ],
    "sg:phone":"+61 2 9331 2932",
    "sg:postcode":"2021",
    "sg:province":"NSW",
    "sg:tags":[
        "web",
        "internet"
    ],
    "wof:name":"Designmodule",
    "wof:placetype":"venue"
},
  "geometry": {"coordinates":[151.231079102,-33.8827209473],"type":"Point"}
}