{
  "type": "Feature",
  "properties": {
    "addr:full":"Shop 3/ 176 Fox Valley Rd Wahroonga NSW 2076",
    "addr:housenumber":"shop 3 / 176",
    "addr:postcode":"2076",
    "addr:street":"Fox Valley Rd",
    "iso:country":"AU",
    "sg:address":"Shop 3/ 176 Fox Valley Rd",
    "sg:city":"Wahroonga",
    "sg:classifiers":[
        {
            "category":"Food & Beverages",
            "subcategory":"Fruits & Vegetables",
            "type":"Retail Goods"
        }
    ],
    "sg:phone":"+61 2 9489 6968",
    "sg:postcode":"2076",
    "sg:province":"NSW",
    "sg:tags":[
        "greengrocer",
        "fruiterer"
    ],
    "wof:name":"Fox Valley Greengrocer & Flower Shop",
    "wof:placetype":"venue"
},
  "geometry": {"coordinates":[151.1015625,-33.73229599],"type":"Point"}
}