{
  "type": "Feature",
  "properties": {
    "addr:full":"158 Lesmurdie Rd Lesmurdie WA 6076",
    "addr:housenumber":"158",
    "addr:postcode":"6076",
    "addr:street":"Lesmurdie Rd",
    "iso:country":"AU",
    "sg:address":"158 Lesmurdie Rd",
    "sg:city":"Lesmurdie",
    "sg:classifiers":[
        {
            "category":"Manufacturing",
            "subcategory":"Musical Instruments",
            "type":"Manufacturing & Wholesale Goods"
        }
    ],
    "sg:phone":"+61 8 9291 0191",
    "sg:postcode":"6076",
    "sg:province":"WA",
    "sg:tags":[
        "repair",
        "maker"
    ],
    "wof:name":"Ivan's In Tune Musical Services",
    "wof:placetype":"venue"
},
  "geometry": {"coordinates":[116.05284881599999,-31.9977798462],"type":"Point"}
}