{
  "type": "Feature",
  "properties": {
    "addr:full":"Sturt Hwy Monash SA 5342",
    "addr:postcode":"5342",
    "addr:street":"Sturt Hwy",
    "iso:country":"AU",
    "sg:address":"Sturt Hwy",
    "sg:city":"Monash",
    "sg:classifiers":[
        {
            "category":"Retail",
            "subcategory":"Repair Shop",
            "type":"Services"
        }
    ],
    "sg:phone":"+61 8 8583 5483",
    "sg:postcode":"5342",
    "sg:province":"SA",
    "sg:tags":[
        "windscreen"
    ],
    "wof:name":"Luke's Body Works",
    "wof:placetype":"venue"
},
  "geometry": {"coordinates":[140.56727600100001,-34.2385482788],"type":"Point"}
}