{
  "type": "Feature",
  "properties": {
    "addr:full":"13 Russell St Toowoomba QLD 4350",
    "addr:housenumber":"13",
    "addr:postcode":"4350",
    "addr:street":"Russell St",
    "iso:country":"AU",
    "sg:address":"13 Russell St",
    "sg:city":"Toowoomba",
    "sg:classifiers":[
        {
            "category":"Personal",
            "type":"Services"
        }
    ],
    "sg:phone":"+61 7 4638 5960",
    "sg:postcode":"4350",
    "sg:province":"QLD",
    "sg:tags":[
        "dressmaker"
    ],
    "wof:name":"Gwen Smith Dressmaking",
    "wof:placetype":"venue"
},
  "geometry": {"coordinates":[151.95494099999999,-27.559111],"type":"Point"}
}