{
  "type": "Feature",
  "properties": {
    "iso:country":"AU",
    "sg:address":"43 Elliott Ave",
    "sg:city":"Holden Hill",
    "sg:classifiers":[
        {
            "category":"Social Services",
            "subcategory":"Adult Care",
            "type":"Services"
        }
    ],
    "sg:phone":"+61 407 971 222",
    "sg:postcode":"5088",
    "sg:province":"SA",
    "sg:tags":[
        "towing"
    ],
    "wof:name":"A Too B Towing",
    "wof:placetype":"venue"
},
  "geometry": {"coordinates":[138.67723083499999,-34.8500099182],"type":"Point"}
}