{
  "type": "Feature",
  "properties": {
    "iso:country":"AU",
    "sg:address":"PO Box 7004",
    "sg:city":"Hutt Street",
    "sg:classifiers":[
        {
            "category":"Banks & Credit Unions",
            "subcategory":"Investment Brokerage",
            "type":"Services"
        }
    ],
    "sg:phone":"+61 8 8346 0885",
    "sg:postcode":"5000",
    "sg:province":"SA",
    "sg:tags":[
        "debt",
        "collection"
    ],
    "wof:name":"Mercantile Collection Services Pty Ltd",
    "wof:placetype":"venue"
},
  "geometry": {"coordinates":[138.61167907699999,-34.9254798889],"type":"Point"}
}