{
  "type": "Feature",
  "properties": {
    "addr:full":"47 Caldwell Ave Lismore NSW 2480",
    "addr:housenumber":"47",
    "addr:postcode":"2480",
    "addr:street":"Caldwell Ave",
    "iso:country":"AU",
    "sg:address":"47 Caldwell Ave",
    "sg:city":"Lismore",
    "sg:classifiers":[
        {
            "category":"Manufacturing",
            "subcategory":"Soap",
            "type":"Manufacturing & Wholesale Goods"
        }
    ],
    "sg:phone":"+61 2 6622 6026",
    "sg:postcode":"2480",
    "sg:province":"NSW",
    "sg:tags":[
        "detergent"
    ],
    "wof:name":"Soapbiz",
    "wof:placetype":"venue"
},
  "geometry": {"coordinates":[153.294067383,-28.8259773254],"type":"Point"}
}