{
  "type": "Feature",
  "properties": {
    "iso:country":"AU",
    "sg:address":"7 Iron St",
    "sg:city":"North Parramatta",
    "sg:classifiers":[
        {
            "category":"Personal",
            "subcategory":"Beauty Salon",
            "type":"Services"
        }
    ],
    "sg:phone":"+61 2 9683 3577",
    "sg:postcode":"2151",
    "sg:province":"NSW",
    "sg:tags":[
        "hairdresser"
    ],
    "wof:name":"Silver Streaks Hair Design",
    "wof:placetype":"venue"
},
  "geometry": {"coordinates":[151.00506591800001,-33.7983131409],"type":"Point"}
}