{
  "type": "Feature",
  "properties": {
    "addr:full":"28 Benwerrin Rd Wamberal NSW 2260",
    "addr:housenumber":"28",
    "addr:postcode":"2260",
    "addr:street":"Benwerrin Rd",
    "iso:country":"AU",
    "sg:address":"28 Benwerrin Rd",
    "sg:city":"Wamberal",
    "sg:classifiers":[
        {
            "category":"Building & Trades",
            "subcategory":"Construction",
            "type":"Services"
        }
    ],
    "sg:phone":"+61 2 4385 3388",
    "sg:postcode":"2260",
    "sg:province":"NSW",
    "sg:tags":[
        "contractor"
    ],
    "wof:name":"S J Reid Building Services",
    "wof:placetype":"venue"
},
  "geometry": {"coordinates":[151.446426,-33.414715],"type":"Point"}
}