{
  "type": "Feature",
  "properties": {
    "addr:full":"12 Boileau St Keysborough VIC 3173",
    "addr:housenumber":"12",
    "addr:postcode":"3173",
    "addr:street":"Boileau St",
    "iso:country":"AU",
    "sg:address":"12 Boileau St",
    "sg:city":"Keysborough",
    "sg:classifiers":[
        {
            "category":"Professional",
            "subcategory":"Engineering",
            "type":"Services"
        }
    ],
    "sg:phone":"+61 3 9798 8281",
    "sg:postcode":"3173",
    "sg:province":"VIC",
    "sg:tags":[
        "patternmaker"
    ],
    "wof:name":"D & A Patterns & Engineering",
    "wof:placetype":"venue"
},
  "geometry": {"coordinates":[145.18658447300001,-37.9971008301],"type":"Point"}
}