{
  "type": "Feature",
  "properties": {
    "iso:country":"AU",
    "sg:address":"Unit 3/ 66 Bryant St",
    "sg:city":"Padstow",
    "sg:classifiers":[
        {
            "category":"Transit Center",
            "subcategory":"Passenger",
            "type":"Transportation"
        }
    ],
    "sg:phone":"+61 2 9792 1699",
    "sg:postcode":"2211",
    "sg:province":"NSW",
    "sg:tags":[
        "packing",
        "gasket"
    ],
    "wof:name":"Flexitallic (Aust)",
    "wof:placetype":"venue"
},
  "geometry": {"coordinates":[151.032913,-33.940899],"type":"Point"}
}