{
  "type": "Feature",
  "properties": {
    "addr:full":"28 Millwood Ave Chatswood NSW 2067",
    "addr:housenumber":"28",
    "addr:postcode":"2067",
    "addr:street":"Millwood Ave",
    "iso:country":"AU",
    "sg:address":"28 Millwood Ave",
    "sg:city":"Chatswood",
    "sg:classifiers":[
        {
            "category":"Banks & Credit Unions",
            "subcategory":"Bank",
            "type":"Services"
        }
    ],
    "sg:phone":"+61 2 9415 1501",
    "sg:postcode":"2067",
    "sg:province":"NSW",
    "sg:tags":[
        "broker",
        "mortgage"
    ],
    "wof:name":"Max Money Pty Ltd",
    "wof:placetype":"venue"
},
  "geometry": {"coordinates":[151.16636657699999,-33.7945365906],"type":"Point"}
}