{
  "type": "Feature",
  "properties": {
    "iso:country":"AU",
    "sg:address":"90 Grant Ave",
    "sg:city":"Toorak Gardens",
    "sg:classifiers":[
        {
            "category":"Travel",
            "subcategory":"Hotels & Motels",
            "type":"Entertainment"
        }
    ],
    "sg:phone":"+61 1800 330 441",
    "sg:postcode":"5065",
    "sg:province":"SA",
    "wof:name":"Adelaide's Toorak Gardens Luxury Serviced Apartments",
    "wof:placetype":"venue"
},
  "geometry": {"coordinates":[138.63377380399999,-34.9319877625],"type":"Point"}
}