{
  "type": "Feature",
  "properties": {
    "iso:country":"AU",
    "sg:address":"29 Breakaway Drv",
    "sg:city":"Breakaway",
    "sg:classifiers":[
        {
            "category":"Building & Trades",
            "subcategory":"Construction",
            "type":"Services"
        }
    ],
    "sg:phone":"+61 7 4749 1722",
    "sg:postcode":"4825",
    "sg:province":"QLD",
    "sg:tags":[
        "contractor"
    ],
    "wof:name":"Pinbuilt Constructions Pty Ltd",
    "wof:placetype":"venue"
},
  "geometry": {"coordinates":[139.533905,-20.725601],"type":"Point"}
}