{
  "type": "Feature",
  "properties": {
    "addr:full":"333a Canterbury Rd Forest Hill VIC 3131",
    "addr:housenumber":"333a",
    "addr:postcode":"3131",
    "addr:street":"Canterbury Rd",
    "iso:country":"AU",
    "sg:address":"333a Canterbury Rd",
    "sg:city":"Forest Hill",
    "sg:classifiers":[
        {
            "category":"Education",
            "subcategory":"Kindergarten",
            "type":"Public Place"
        }
    ],
    "sg:phone":"+61 3 9878 1725",
    "sg:postcode":"3131",
    "sg:province":"VIC",
    "sg:tags":[
        "pre-schools"
    ],
    "wof:name":"Mount Pleasant Kindergarten",
    "wof:placetype":"venue"
},
  "geometry": {"coordinates":[145.17799377399999,-37.8351554871],"type":"Point"}
}