{
  "type": "Feature",
  "properties": {
    "iso:country":"AU",
    "sg:address":"46 Kent St",
    "sg:city":"Richmond",
    "sg:classifiers":[
        {
            "category":"Professional",
            "subcategory":"Computer Services",
            "type":"Services"
        }
    ],
    "sg:phone":"+61 3 9428 5392",
    "sg:postcode":"3121",
    "sg:province":"VIC",
    "sg:tags":[
        "repairs",
        "upgrade",
        "equipment"
    ],
    "wof:name":"David Furst Computer Services",
    "wof:placetype":"venue"
},
  "geometry": {"coordinates":[145.00242614699999,-37.8148880005],"type":"Point"}
}