{
  "type": "Feature",
  "properties": {
    "addr:full":"Lot 12 Anomally St Moolap VIC 3221",
    "addr:postcode":"3221",
    "addr:street":"St",
    "iso:country":"AU",
    "sg:address":"Lot 12 Anomally St",
    "sg:city":"Moolap",
    "sg:classifiers":[
        {
            "category":"Building & Trades",
            "subcategory":"Construction",
            "type":"Services"
        }
    ],
    "sg:phone":"+61 3 5248 2525",
    "sg:postcode":"3221",
    "sg:province":"VIC",
    "sg:tags":[
        "joinery"
    ],
    "wof:name":"Windsor Kitchens",
    "wof:placetype":"venue"
},
  "geometry": {"coordinates":[144.41250600000001,-38.164845],"type":"Point"}
}