{
  "type": "Feature",
  "properties": {
    "addr:full":"14 Hazel Ave Dandenong VIC 3175",
    "addr:housenumber":"14",
    "addr:postcode":"3175",
    "addr:street":"Hazel Ave",
    "iso:country":"AU",
    "sg:address":"14 Hazel Ave",
    "sg:city":"Dandenong",
    "sg:classifiers":[
        {
            "category":"Retail",
            "subcategory":"Auto Repair",
            "type":"Services"
        }
    ],
    "sg:phone":"+61 3 9791 8139",
    "sg:postcode":"3175",
    "sg:province":"VIC",
    "sg:tags":[
        "beater",
        "painter",
        "panel"
    ],
    "wof:name":"Garage National",
    "wof:placetype":"venue"
},
  "geometry": {"coordinates":[145.19732665999999,-37.9923171997],"type":"Point"}
}