{
  "type": "Feature",
  "properties": {
    "addr:full":"97 South Head Rd Moruya NSW 2537",
    "addr:housenumber":"97",
    "addr:postcode":"2537",
    "addr:street":"South Head Rd",
    "iso:country":"AU",
    "sg:address":"97 South Head Rd",
    "sg:city":"Moruya",
    "sg:classifiers":[
        {
            "category":"Wholesale",
            "subcategory":"Furniture",
            "type":"Manufacturing & Wholesale Goods"
        }
    ],
    "sg:phone":"+61 2 4474 4182",
    "sg:postcode":"2537",
    "sg:province":"NSW",
    "sg:tags":[
        "wholesaler",
        "mfrs"
    ],
    "wof:name":"Cenedeb Pty Ltd",
    "wof:placetype":"venue"
},
  "geometry": {"coordinates":[150.10279846200001,-35.9174919128],"type":"Point"}
}