{
  "type": "Feature",
  "properties": {
    "iso:country":"AU",
    "sg:address":"Murdoch University Veterinary Hospital Murdoch Drv",
    "sg:city":"Murdoch",
    "sg:classifiers":[
        {
            "category":"Retail",
            "subcategory":"Veterinary Services",
            "type":"Services"
        }
    ],
    "sg:phone":"+61 8 9360 2356",
    "sg:postcode":"6150",
    "sg:province":"WA",
    "sg:tags":[
        "surgeon"
    ],
    "wof:name":"Exclusively Dermatology",
    "wof:placetype":"venue"
},
  "geometry": {"coordinates":[115.836212,-32.063122],"type":"Point"}
}