{
  "type": "Feature",
  "properties": {
    "iso:country":"AU",
    "sg:address":"74 Robertson St",
    "sg:city":"Mudgee",
    "sg:classifiers":[
        {
            "category":"Building & Trades",
            "subcategory":"Construction",
            "type":"Services"
        }
    ],
    "sg:phone":"+61 2 6372 1268",
    "sg:postcode":"2850",
    "sg:province":"NSW",
    "sg:tags":[
        "earth",
        "excavating",
        "moving",
        "contractor"
    ],
    "wof:name":"Box C & M",
    "wof:placetype":"venue"
},
  "geometry": {"coordinates":[149.592377,-32.603493],"type":"Point"}
}