{
  "type": "Feature",
  "properties": {
    "iso:country":"AU",
    "sg:address":"3 Booth St",
    "sg:city":"Dubbo",
    "sg:classifiers":[
        {
            "category":"Utilities",
            "subcategory":"Electric",
            "type":"Services"
        }
    ],
    "sg:phone":"+61 419 974 504",
    "sg:postcode":"2830",
    "sg:province":"NSW",
    "sg:tags":[
        "electrical",
        "contractor"
    ],
    "wof:name":"Ensor J & M Electrical",
    "wof:placetype":"venue"
},
  "geometry": {"coordinates":[148.60678100600001,-32.2692985535],"type":"Point"}
}