{
  "type": "Feature",
  "properties": {
    "iso:country":"AU",
    "sg:address":"23 Prince St",
    "sg:city":"Alberton",
    "sg:classifiers":[
        {
            "category":"Retail",
            "subcategory":"Repair Shop",
            "type":"Services"
        }
    ],
    "sg:phone":"+61 403 866 219",
    "sg:postcode":"5014",
    "sg:province":"SA",
    "sg:tags":[
        "maintenance",
        "pool",
        "swimming"
    ],
    "wof:name":"Pool Medic The",
    "wof:placetype":"venue"
},
  "geometry": {"coordinates":[138.52093505900001,-34.8617324829],"type":"Point"}
}