{
  "type": "Feature",
  "properties": {
    "addr:full":"17 Cavell Ave Rhodes NSW 2138",
    "addr:housenumber":"17",
    "addr:postcode":"2138",
    "addr:street":"Cavell Ave",
    "iso:country":"AU",
    "sg:address":"17 Cavell Ave",
    "sg:city":"Rhodes",
    "sg:classifiers":[
        {
            "category":"Shopping",
            "subcategory":"Crafts & Fabrics",
            "type":"Retail Goods"
        }
    ],
    "sg:phone":"+61 2 9736 1501",
    "sg:postcode":"2138",
    "sg:province":"NSW",
    "sg:tags":[
        "supply"
    ],
    "wof:name":"Petlin's Spinning & Weaving Supplies",
    "wof:placetype":"venue"
},
  "geometry": {"coordinates":[151.089767456,-33.8268356323],"type":"Point"}
}