{
  "type": "Feature",
  "properties": {
    "addr:full":"Witham Rd Lake Biddy WA 6355",
    "addr:postcode":"6355",
    "addr:street":"Witham Rd",
    "iso:country":"AU",
    "sg:address":"Witham Rd",
    "sg:city":"Lake Biddy",
    "sg:classifiers":[
        {
            "category":"Shopping",
            "subcategory":"Computers & Home Electronics",
            "type":"Retail Goods"
        }
    ],
    "sg:phone":"+61 8 9871 2014",
    "sg:postcode":"6355",
    "sg:province":"WA",
    "sg:tags":[
        "small",
        "equipment",
        "business"
    ],
    "wof:name":"Newdegate Computers",
    "wof:placetype":"venue"
},
  "geometry": {"coordinates":[118.942078,-32.99966],"type":"Point"}
}