{
  "type": "Feature",
  "properties": {
    "addr:full":"Shop 4C Pelican Plaza, 1007 North East Rd Ridgehaven SA 5097",
    "addr:housenumber":"4c;1007",
    "addr:postcode":"5097",
    "addr:street":"Shop;Plaza;North East Rd",
    "iso:country":"AU",
    "sg:address":"Shop 4C Pelican Plaza, 1007 North East Rd",
    "sg:city":"Ridgehaven",
    "sg:classifiers":[
        {
            "category":"Personal",
            "subcategory":"Tanning Parlor",
            "type":"Services"
        }
    ],
    "sg:phone":"+61 8 8395 5102",
    "sg:postcode":"5097",
    "sg:province":"SA",
    "sg:tags":[
        "solarium"
    ],
    "wof:name":"Ambersun",
    "wof:placetype":"venue"
},
  "geometry": {"coordinates":[138.70997619600001,-34.8241233826],"type":"Point"}
}