{
  "type": "Feature",
  "properties": {
    "addr:full":"279 Napier St Strathmore VIC 3041",
    "addr:housenumber":"279",
    "addr:postcode":"3041",
    "addr:street":"Napier St",
    "iso:country":"AU",
    "sg:address":"279 Napier St",
    "sg:city":"Strathmore",
    "sg:classifiers":[
        {
            "category":"Building & Trades",
            "subcategory":"Locksmith",
            "type":"Services"
        }
    ],
    "sg:phone":"+61 3 9379 5522",
    "sg:postcode":"3041",
    "sg:province":"VIC",
    "sg:tags":[
        "lock"
    ],
    "wof:name":"Aussielock Locksmiths",
    "wof:placetype":"venue"
},
  "geometry": {"coordinates":[144.91934204099999,-37.7369155884],"type":"Point"}
}