{
  "type": "Feature",
  "properties": {
    "iso:country":"AU",
    "sg:address":"Cnr Terranora Road",
    "sg:city":"& Henry Lawson Drive Terranora",
    "sg:classifiers":[
        {
            "category":"Health Services",
            "subcategory":"Doctor",
            "type":"Services"
        }
    ],
    "sg:phone":"+61 7 5590 5875",
    "sg:postcode":"2486",
    "sg:province":"NSW",
    "sg:tags":[
        "medical",
        "practitioner"
    ],
    "wof:name":"Terranora Village Medical Centre",
    "wof:placetype":"venue"
},
  "geometry": {"coordinates":[153.504364014,-28.2403507233],"type":"Point"}
}