{
  "type": "Feature",
  "properties": {
    "addr:full":"94 Kembla St Wollongong NSW 2500",
    "addr:housenumber":"94",
    "addr:postcode":"2500",
    "addr:street":"Kembla St",
    "iso:country":"AU",
    "sg:address":"94 Kembla St",
    "sg:city":"Wollongong",
    "sg:classifiers":[
        {
            "category":"Real Estate",
            "subcategory":"Architect",
            "type":"Services"
        }
    ],
    "sg:phone":"+61 2 4228 6400",
    "sg:postcode":"2500",
    "sg:province":"NSW",
    "wof:name":"ADM Architects",
    "wof:placetype":"venue"
},
  "geometry": {"coordinates":[150.896759,-34.427864],"type":"Point"}
}