{
  "type": "Feature",
  "properties": {
    "iso:country":"AU",
    "sg:address":"91 Kelvin Road (Cnr Madrid Place)",
    "sg:city":"Maddington",
    "sg:classifiers":[
        {
            "category":"Communications",
            "type":"Services"
        }
    ],
    "sg:phone":"+61 8 9452 2793",
    "sg:postcode":"6109",
    "sg:province":"WA",
    "sg:tags":[
        "equipment",
        "radio"
    ],
    "wof:name":"Mobile Masters",
    "wof:placetype":"venue"
},
  "geometry": {"coordinates":[115.982681274,-32.0467643738],"type":"Point"}
}