{
  "type": "Feature",
  "properties": {
    "iso:country":"AU",
    "sg:address":"PO Box 131",
    "sg:city":"Ringwood East",
    "sg:classifiers":[
        {
            "category":"Professional",
            "subcategory":"Detective & Security Services",
            "type":"Services"
        }
    ],
    "sg:phone":"+61 3 9726 5700",
    "sg:postcode":"3135",
    "sg:province":"VIC",
    "sg:tags":[
        "guard",
        "patrol"
    ],
    "wof:name":"Taylors Property Services Pty Ltd",
    "wof:placetype":"venue"
},
  "geometry": {"coordinates":[145.24940490700001,-37.8085784912],"type":"Point"}
}