{
  "type": "Feature",
  "properties": {
    "addr:full":"28 River Rd Wollstonecraft NSW 2065",
    "addr:housenumber":"28",
    "addr:postcode":"2065",
    "addr:street":"River Rd",
    "iso:country":"AU",
    "sg:address":"28 River Rd",
    "sg:city":"Wollstonecraft",
    "sg:classifiers":[
        {
            "category":"Professional",
            "subcategory":"Engineering",
            "type":"Services"
        }
    ],
    "sg:phone":"+61 2 9437 6867",
    "sg:postcode":"2065",
    "sg:province":"NSW",
    "sg:tags":[
        "consulting",
        "engineer"
    ],
    "wof:name":"Gerald Renton & Partners Pty Ltd",
    "wof:placetype":"venue"
},
  "geometry": {"coordinates":[151.19247436500001,-33.8276977539],"type":"Point"}
}