{
  "type": "Feature",
  "properties": {
    "addr:full":"PO Box 8210 Mackay QLD 4740",
    "addr:postcode":"4740",
    "iso:country":"AU",
    "sg:address":"PO Box 8210",
    "sg:city":"Mackay",
    "sg:classifiers":[
        {
            "category":"Building & Trades",
            "subcategory":"Construction",
            "type":"Services"
        }
    ],
    "sg:phone":"+61 7 4955 0557",
    "sg:postcode":"4740",
    "sg:province":"QLD",
    "sg:tags":[
        "concrete",
        "contractor"
    ],
    "wof:name":"Mackay Look-a-Like Spray on Tiles",
    "wof:placetype":"venue"
},
  "geometry": {"coordinates":[149.11184692399999,-21.1551895142],"type":"Point"}
}