{
  "type": "Feature",
  "properties": {
    "addr:full":"Wingham Rd Nowendoc NSW 2354",
    "addr:postcode":"2354",
    "addr:street":"Wingham Rd",
    "iso:country":"AU",
    "sg:address":"Wingham Rd",
    "sg:city":"Nowendoc",
    "sg:classifiers":[
        {
            "category":"Travel",
            "subcategory":"Hotels & Motels",
            "type":"Entertainment"
        }
    ],
    "sg:phone":"+61 2 6777 0952",
    "sg:postcode":"2354",
    "sg:province":"NSW",
    "wof:name":"Nowendoc Village Inn",
    "wof:placetype":"venue"
},
  "geometry": {"coordinates":[151.611938477,-31.439239502],"type":"Point"}
}