{
  "type": "Feature",
  "properties": {
    "addr:full":"5 Sturt St Dunwich QLD 4183",
    "addr:housenumber":"5",
    "addr:postcode":"4183",
    "addr:street":"Sturt St",
    "iso:country":"AU",
    "sg:address":"5 Sturt St",
    "sg:city":"Dunwich",
    "sg:classifiers":[
        {
            "category":"Manufacturing",
            "subcategory":"Glass & Minerals",
            "type":"Manufacturing & Wholesale Goods"
        }
    ],
    "sg:phone":"+61 7 3415 2127",
    "sg:postcode":"4183",
    "sg:province":"QLD",
    "sg:tags":[
        "repair",
        "fibreglass",
        "product"
    ],
    "wof:name":"Mermaid Composites",
    "wof:placetype":"venue"
},
  "geometry": {"coordinates":[153.40960693400001,-27.4978275299],"type":"Point"}
}