{
  "type": "Feature",
  "properties": {
    "addr:full":"108 Scarborough St Southport QLD 4215",
    "addr:housenumber":"108",
    "addr:postcode":"4215",
    "addr:street":"Scarborough St",
    "iso:country":"AU",
    "sg:address":"108 Scarborough St",
    "sg:city":"Southport",
    "sg:classifiers":[
        {
            "category":"Shopping",
            "subcategory":"Clothing, Apparel, & Fashions",
            "type":"Retail Goods"
        }
    ],
    "sg:phone":"+61 7 5532 2178",
    "sg:postcode":"4215",
    "sg:province":"QLD",
    "sg:tags":[
        "recycled",
        "clothing"
    ],
    "wof:name":"St Vincent de Paul",
    "wof:placetype":"venue"
},
  "geometry": {"coordinates":[153.41314697300001,-27.9662322998],"type":"Point"}
}