{
  "type": "Feature",
  "properties": {
    "iso:country":"AU",
    "sg:address":"Lvl 1, 107 Alexander St",
    "sg:city":"Crows Nest",
    "sg:classifiers":[
        {
            "category":"Professional",
            "subcategory":"Art Services",
            "type":"Services"
        }
    ],
    "sg:phone":"+61 2 8436 4555",
    "sg:postcode":"2065",
    "sg:province":"NSW",
    "sg:tags":[
        "graphic",
        "designer"
    ],
    "wof:name":"Orson & Burk",
    "wof:placetype":"venue"
},
  "geometry": {"coordinates":[151.20262145999999,-33.8253593445],"type":"Point"}
}