{
  "type": "Feature",
  "properties": {
    "addr:full":"180 Mary St Gympie QLD 4570",
    "addr:housenumber":"180",
    "addr:postcode":"4570",
    "addr:street":"Mary St",
    "iso:country":"AU",
    "sg:address":"180 Mary St",
    "sg:city":"Gympie",
    "sg:classifiers":[
        {
            "category":"Shopping",
            "subcategory":"Crafts & Fabrics",
            "type":"Retail Goods"
        }
    ],
    "sg:phone":"+61 7 5482 1296",
    "sg:postcode":"4570",
    "sg:province":"QLD",
    "sg:tags":[
        "supply"
    ],
    "wof:name":"Woodrow Handicrafts",
    "wof:placetype":"venue"
},
  "geometry": {"coordinates":[152.660522461,-26.1895523071],"type":"Point"}
}