{
  "type": "Feature",
  "properties": {
    "addr:full":"Lot 43 Chester Rd Altona West VIC 3024",
    "addr:postcode":"3024",
    "addr:street":"Chester Rd",
    "iso:country":"AU",
    "sg:address":"Lot 43 Chester Rd",
    "sg:city":"Altona West",
    "sg:classifiers":[
        {
            "category":"Professional",
            "subcategory":"Engineering",
            "type":"Services"
        }
    ],
    "sg:phone":"+61 3 9398 3873",
    "sg:postcode":"3024",
    "sg:province":"VIC",
    "sg:tags":[
        "engineer"
    ],
    "wof:name":"KA-BE Engineering & Design Pty Ltd",
    "wof:placetype":"venue"
},
  "geometry": {"coordinates":[144.63017300000001,-37.895351],"type":"Point"}
}