{
  "type": "Feature",
  "properties": {
    "addr:full":"19 Curdie St Cobden VIC 3266",
    "addr:housenumber":"19",
    "addr:postcode":"3266",
    "addr:street":"Curdie St",
    "iso:country":"AU",
    "sg:address":"19 Curdie St",
    "sg:city":"Cobden",
    "sg:classifiers":[
        {
            "category":"Building & Trades",
            "subcategory":"Landscaping Services",
            "type":"Services"
        }
    ],
    "sg:phone":"+61 3 5595 2298",
    "sg:postcode":"3266",
    "sg:province":"VIC",
    "sg:tags":[
        "designer",
        "landscape",
        "contractor"
    ],
    "wof:name":"Dawson S",
    "wof:placetype":"venue"
},
  "geometry": {"coordinates":[143.07835388199999,-38.3287658691],"type":"Point"}
}