{
  "type": "Feature",
  "properties": {
    "addr:full":"504 Cessnock Rd Gillieston Heights NSW 2321",
    "addr:housenumber":"504",
    "addr:postcode":"2321",
    "addr:street":"Cessnock Rd",
    "iso:country":"AU",
    "sg:address":"504 Cessnock Rd",
    "sg:city":"Gillieston Heights",
    "sg:classifiers":[
        {
            "category":"Building & Trades",
            "subcategory":"Construction",
            "type":"Services"
        }
    ],
    "sg:phone":"+61 2 4932 4294",
    "sg:postcode":"2321",
    "sg:province":"NSW",
    "sg:tags":[
        "earth",
        "excavating",
        "moving",
        "contractor"
    ],
    "wof:name":"Buxton G & V",
    "wof:placetype":"venue"
},
  "geometry": {"coordinates":[151.525466919,-32.776473999],"type":"Point"}
}