{
  "type": "Feature",
  "properties": {
    "iso:country":"AU",
    "sg:address":"21- 25 Kialba Rd",
    "sg:city":"Campbelltown",
    "sg:classifiers":[
        {
            "category":"Home & Garden",
            "subcategory":"Building Materials",
            "type":"Retail Goods"
        }
    ],
    "sg:phone":"+61 2 4628 2122",
    "sg:postcode":"2560",
    "sg:province":"NSW",
    "sg:tags":[
        "ventilating",
        "equipment",
        "system"
    ],
    "wof:name":"Industrial Ventilation Equipment",
    "wof:placetype":"venue"
},
  "geometry": {"coordinates":[150.822631836,-34.0565605164],"type":"Point"}
}