{
  "type": "Feature",
  "properties": {
    "addr:full":"8- 10 Brooks Way Kalgoorlie West WA 6430",
    "addr:housenumber":"10",
    "addr:postcode":"6430",
    "addr:street":"8;Brooks Way;West",
    "iso:country":"AU",
    "sg:address":"8- 10",
    "sg:city":"Brooks Way Kalgoorlie West",
    "sg:classifiers":[
        {
            "category":"Building & Trades",
            "subcategory":"Equipment Rental",
            "type":"Services"
        }
    ],
    "sg:phone":"+61 1300 668 700",
    "sg:postcode":"6430",
    "sg:province":"WA",
    "sg:tags":[
        "crane",
        "hire"
    ],
    "wof:name":"Goldfields Crane Hire",
    "wof:placetype":"venue"
},
  "geometry": {"coordinates":[121.43717956499999,-30.7817249298],"type":"Point"}
}