{
  "type": "Feature",
  "properties": {
    "addr:full":"39 Rawlings Rd Modbury North SA 5092",
    "addr:housenumber":"39",
    "addr:postcode":"5092",
    "addr:street":"Rawlings Rd",
    "iso:country":"AU",
    "sg:address":"39 Rawlings Rd",
    "sg:city":"Modbury North",
    "sg:classifiers":[
        {
            "category":"Building & Trades",
            "subcategory":"Plumbing",
            "type":"Services"
        }
    ],
    "sg:phone":"+61 8 8264 2289",
    "sg:postcode":"5092",
    "sg:province":"SA",
    "sg:tags":[
        "plumber",
        "gasfitters"
    ],
    "wof:name":"Lindsay Rogers Plumbing Service",
    "wof:placetype":"venue"
},
  "geometry": {"coordinates":[138.69119262699999,-34.8238525391],"type":"Point"}
}