{
  "type": "Feature",
  "properties": {
    "addr:full":"U 1/ 57 Garden Drv Tullamarine VIC 3043",
    "addr:housenumber":"57",
    "addr:postcode":"3043",
    "addr:street":"Garden Drv",
    "iso:country":"AU",
    "sg:address":"U 1/ 57 Garden Drv",
    "sg:city":"Tullamarine",
    "sg:classifiers":[
        {
            "category":"Fast Food",
            "type":"Food & Drink"
        }
    ],
    "sg:phone":"+61 3 9330 3311",
    "sg:postcode":"3043",
    "sg:province":"VIC",
    "sg:tags":[
        "away",
        "take"
    ],
    "wof:name":"Workers Cafe",
    "wof:placetype":"venue"
},
  "geometry": {"coordinates":[144.876663208,-37.6899452209],"type":"Point"}
}