{
  "type": "Feature",
  "properties": {
    "addr:full":"2 De Jounge Crt Boreen Point QLD 4565",
    "addr:housenumber":"2",
    "addr:postcode":"4565",
    "addr:street":"De Jounge Crt",
    "iso:country":"AU",
    "sg:address":"2 De Jounge Crt",
    "sg:city":"Boreen Point",
    "sg:classifiers":[
        {
            "category":"Professional",
            "subcategory":"Employment Agencies",
            "type":"Services"
        }
    ],
    "sg:phone":"+61 7 5485 3621",
    "sg:postcode":"4565",
    "sg:province":"QLD",
    "sg:tags":[
        "entertainer",
        "agent"
    ],
    "wof:name":"Col Noble",
    "wof:placetype":"venue"
},
  "geometry": {"coordinates":[152.99234008799999,-26.283996582],"type":"Point"}
}