{
  "type": "Feature",
  "properties": {
    "addr:full":"43 McKeon St Maroubra NSW 2035",
    "addr:housenumber":"43",
    "addr:postcode":"2035",
    "addr:street":"Mckeon St",
    "iso:country":"AU",
    "sg:address":"43 McKeon St",
    "sg:city":"Maroubra",
    "sg:classifiers":[
        {
            "category":"Food & Beverages",
            "subcategory":"Bakery",
            "type":"Retail Goods"
        }
    ],
    "sg:phone":"+61 2 9349 2744",
    "sg:postcode":"2035",
    "sg:province":"NSW",
    "sg:tags":[
        "cake",
        "shop",
        "pastry"
    ],
    "wof:name":"Maroubra Bay Cakes & Pies",
    "wof:placetype":"venue"
},
  "geometry": {"coordinates":[151.25619506800001,-33.9462432861],"type":"Point"}
}