{
  "type": "Feature",
  "properties": {
    "iso:country":"AU",
    "sg:address":"22 Urquhart St",
    "sg:city":"Horsham",
    "sg:classifiers":[
        {
            "category":"Health Services",
            "subcategory":"Doctor",
            "type":"Services"
        }
    ],
    "sg:phone":"+61 3 5381 0599",
    "sg:postcode":"3400",
    "sg:province":"VIC",
    "sg:tags":[
        "podiatrist"
    ],
    "wof:name":"Horsham Foot Care Clinic",
    "wof:placetype":"venue"
},
  "geometry": {"coordinates":[142.20216369600001,-36.7123222351],"type":"Point"}
}