{
  "type": "Feature",
  "properties": {
    "iso:country":"AU",
    "sg:address":"Unit 5/ 43 Bay Rd",
    "sg:city":"Taren Point",
    "sg:classifiers":[
        {
            "category":"Shopping",
            "subcategory":"Clothing, Apparel, & Fashions",
            "type":"Retail Goods"
        }
    ],
    "sg:phone":"+61 2 9531 2944",
    "sg:postcode":"2229",
    "sg:province":"NSW",
    "sg:tags":[
        "maternity",
        "wear"
    ],
    "wof:name":"Cosmic Maternity Wear",
    "wof:placetype":"venue"
},
  "geometry": {"coordinates":[151.123947144,-34.0231056213],"type":"Point"}
}