{
  "type": "Feature",
  "properties": {
    "iso:country":"AU",
    "sg:address":"19 Streiff Rd",
    "sg:city":"Wingfield",
    "sg:classifiers":[
        {
            "category":"Building & Trades",
            "subcategory":"Construction",
            "type":"Services"
        }
    ],
    "sg:phone":"+61 8 8349 4711",
    "sg:postcode":"5013",
    "sg:province":"SA",
    "sg:tags":[
        "equipment",
        "balancing"
    ],
    "wof:name":"Hancock & Just Wheel Alignment Specialists",
    "wof:placetype":"venue"
},
  "geometry": {"coordinates":[138.568634033,-34.8486747742],"type":"Point"}
}