{
  "type": "Feature",
  "properties": {
    "addr:full":"Shop 1014 Westfield Shopping Centre Cobbs Rd Tuggerah NSW 2259",
    "addr:housenumber":"1014",
    "addr:postcode":"2259",
    "addr:street":"Westfield Shopping;Cobbs Rd",
    "iso:country":"AU",
    "sg:address":"Shop 1014 Westfield Shopping Centre Cobbs Rd",
    "sg:city":"Tuggerah",
    "sg:classifiers":[
        {
            "category":"Insurance",
            "subcategory":"Health Insurance",
            "type":"Services"
        }
    ],
    "sg:phone":"+61 2 4353 5235",
    "sg:postcode":"2259",
    "sg:province":"NSW",
    "wof:name":"The Hospitals Contribution Fund Of Australia Limited",
    "wof:placetype":"venue"
},
  "geometry": {"coordinates":[151.417205811,-33.307674408],"type":"Point"}
}