{
  "type": "Feature",
  "properties": {
    "iso:country":"AU",
    "sg:address":"25 Bailey St",
    "sg:city":"Bairnsdale",
    "sg:classifiers":[
        {
            "category":"Professional",
            "subcategory":"Printing & Photocopies",
            "type":"Services"
        }
    ],
    "sg:phone":"+61 3 5153 0876",
    "sg:postcode":"3875",
    "sg:province":"VIC",
    "sg:tags":[
        "trophy"
    ],
    "wof:name":"Bairnsdale Trophy Centre",
    "wof:placetype":"venue"
},
  "geometry": {"coordinates":[147.63206481899999,-37.8254432678],"type":"Point"}
}