{
  "type": "Feature",
  "properties": {
    "addr:full":"Langslow St Castlemaine VIC 3450",
    "addr:postcode":"3450",
    "addr:street":"Langslow St",
    "iso:country":"AU",
    "sg:address":"Langslow St",
    "sg:city":"Castlemaine",
    "sg:classifiers":[
        {
            "category":"Home & Garden",
            "subcategory":"Furniture",
            "type":"Retail Goods"
        }
    ],
    "sg:phone":"+61 3 5472 4947",
    "sg:postcode":"3450",
    "sg:province":"VIC",
    "sg:tags":[
        "business"
    ],
    "wof:name":"Goldline Executive Furniture",
    "wof:placetype":"venue"
},
  "geometry": {"coordinates":[144.20179748499999,-37.0711479187],"type":"Point"}
}