{
  "type": "Feature",
  "properties": {
    "addr:full":"Factory 18/ 25 Bald Hill Rd Pakenham VIC 3810",
    "addr:housenumber":"18 / 25",
    "addr:postcode":"3810",
    "addr:street":"Bald Hill Rd",
    "iso:country":"AU",
    "sg:address":"Factory 18/ 25 Bald Hill Rd",
    "sg:city":"Pakenham",
    "sg:classifiers":[
        {
            "category":"Retail",
            "subcategory":"Auto Repair",
            "type":"Services"
        }
    ],
    "sg:phone":"+61 401 263 759",
    "sg:postcode":"3810",
    "sg:province":"VIC",
    "sg:tags":[
        "body",
        "motor",
        "trimmer"
    ],
    "wof:name":"Attoni Seating",
    "wof:placetype":"venue"
},
  "geometry": {"coordinates":[145.48637400000001,-38.081345],"type":"Point"}
}