{
  "type": "Feature",
  "properties": {
    "iso:country":"AU",
    "sg:address":"Level 1, 12 Commercial Rd",
    "sg:city":"Newstead",
    "sg:classifiers":[
        {
            "category":"Building & Trades",
            "subcategory":"Construction",
            "type":"Services"
        }
    ],
    "sg:phone":"+61 7 3251 6300",
    "sg:postcode":"4006",
    "sg:province":"QLD",
    "sg:tags":[
        "contractor"
    ],
    "wof:name":"Watpac",
    "wof:placetype":"venue"
},
  "geometry": {"coordinates":[153.04060363799999,-27.4521751404],"type":"Point"}
}