{
  "type": "Feature",
  "properties": {
    "addr:full":"25 Heytesbury Rd Subiaco WA 6008",
    "addr:housenumber":"25",
    "addr:postcode":"6008",
    "addr:street":"Heytesbury Rd",
    "iso:country":"AU",
    "sg:address":"25 Heytesbury Rd",
    "sg:city":"Subiaco",
    "sg:classifiers":[
        {
            "category":"Manufacturing",
            "subcategory":"Printing",
            "type":"Manufacturing & Wholesale Goods"
        }
    ],
    "sg:phone":"+61 8 9382 4752",
    "sg:postcode":"6008",
    "sg:province":"WA",
    "sg:tags":[
        "wholesaler",
        "mfrs",
        "greeting",
        "card"
    ],
    "wof:name":"Fatara Products",
    "wof:placetype":"venue"
},
  "geometry": {"coordinates":[115.826400757,-31.9545783997],"type":"Point"}
}