{
  "type": "Feature",
  "properties": {
    "addr:full":"14 Glen Stuart Rd Magill SA 5072",
    "addr:housenumber":"14",
    "addr:postcode":"5072",
    "addr:street":"Glen Stuart Rd",
    "iso:country":"AU",
    "sg:address":"14 Glen Stuart Rd",
    "sg:city":"Magill",
    "sg:classifiers":[
        {
            "category":"Shopping",
            "subcategory":"Gifts & Souvenirs",
            "type":"Retail Goods"
        }
    ],
    "sg:phone":"+61 8 8332 1286",
    "sg:postcode":"5072",
    "sg:province":"SA",
    "sg:tags":[
        "shop",
        "supply"
    ],
    "wof:name":"Magill Agencies / Magill Ceramics",
    "wof:placetype":"venue"
},
  "geometry": {"coordinates":[138.68458557100001,-34.9081497192],"type":"Point"}
}