{
  "type": "Feature",
  "properties": {
    "addr:full":"14 Railway St Woy Woy NSW 2256",
    "addr:housenumber":"14",
    "addr:postcode":"2256",
    "addr:street":"Railway St",
    "iso:country":"AU",
    "sg:address":"14 Railway St",
    "sg:city":"Woy Woy",
    "sg:classifiers":[
        {
            "category":"Health Services",
            "subcategory":"Dentist",
            "type":"Services"
        }
    ],
    "sg:phone":"+61 2 4342 1080",
    "sg:postcode":"2256",
    "sg:province":"NSW",
    "wof:name":"Woy Woy Dental Centre",
    "wof:placetype":"venue"
},
  "geometry": {"coordinates":[151.30328369099999,-33.4979248047],"type":"Point"}
}