{
  "type": "Feature",
  "properties": {
    "addr:full":"284 Smith St Collingwood VIC 3066",
    "addr:housenumber":"284",
    "addr:postcode":"3066",
    "addr:street":"Smith St",
    "iso:country":"AU",
    "sg:address":"284 Smith St",
    "sg:city":"Collingwood",
    "sg:classifiers":[
        {
            "category":"Retail",
            "subcategory":"Event Space",
            "type":"Services"
        }
    ],
    "sg:phone":"+61 3 9417 1860",
    "sg:postcode":"3066",
    "sg:province":"VIC",
    "sg:tags":[
        "function",
        "organiser"
    ],
    "wof:name":"Suede",
    "wof:placetype":"venue"
},
  "geometry": {"coordinates":[144.984100342,-37.8008346558],"type":"Point"}
}