{
  "type": "Feature",
  "properties": {
    "addr:full":"17 Fourth St Port Pirie SA 5540",
    "addr:housenumber":"17",
    "addr:postcode":"5540",
    "addr:street":"Fourth St",
    "iso:country":"AU",
    "sg:address":"17 Fourth St",
    "sg:city":"Port Pirie",
    "sg:classifiers":[
        {
            "category":"Utilities",
            "subcategory":"Water",
            "type":"Services"
        }
    ],
    "sg:phone":"+61 8 8632 6025",
    "sg:postcode":"5540",
    "sg:province":"SA",
    "sg:tags":[
        "hot",
        "system"
    ],
    "wof:name":"Ellis S J",
    "wof:placetype":"venue"
},
  "geometry": {"coordinates":[138.00163269000001,-33.1814994812],"type":"Point"}
}