{
  "type": "Feature",
  "properties": {
    "addr:full":"91 Brice Ave Mooroolbark VIC 3138",
    "addr:housenumber":"91",
    "addr:postcode":"3138",
    "addr:street":"Brice Ave",
    "iso:country":"AU",
    "sg:address":"91 Brice Ave",
    "sg:city":"Mooroolbark",
    "sg:classifiers":[
        {
            "category":"Professional",
            "subcategory":"Art Services",
            "type":"Services"
        }
    ],
    "sg:phone":"+61 3 9727 3312",
    "sg:postcode":"3138",
    "sg:province":"VIC",
    "sg:tags":[
        "picture",
        "frame",
        "framing"
    ],
    "wof:name":"Mooroolbark Picture Framing",
    "wof:placetype":"venue"
},
  "geometry": {"coordinates":[145.31683349599999,-37.7860794067],"type":"Point"}
}