{
  "type": "Feature",
  "properties": {
    "addr:full":"255 Victoria Rd Rydalmere NSW 2116",
    "addr:housenumber":"255",
    "addr:postcode":"2116",
    "addr:street":"Victoria Rd",
    "iso:country":"AU",
    "sg:address":"255 Victoria Rd",
    "sg:city":"Rydalmere",
    "sg:classifiers":[
        {
            "category":"Retail",
            "subcategory":"Auto Repair",
            "type":"Services"
        }
    ],
    "sg:phone":"+61 2 9638 0563",
    "sg:postcode":"2116",
    "sg:province":"NSW",
    "sg:tags":[
        "gas",
        "conversion",
        "natural",
        "lp",
        "vehicle"
    ],
    "wof:name":"Dr Gas",
    "wof:placetype":"venue"
},
  "geometry": {"coordinates":[151.161087036,-33.9108505249],"type":"Point"}
}