{
  "type": "Feature",
  "properties": {
    "addr:full":"10 Adelaide St Cairns QLD 4870",
    "addr:housenumber":"10",
    "addr:postcode":"4870",
    "addr:street":"Adelaide St",
    "iso:country":"AU",
    "sg:address":"10 Adelaide St",
    "sg:city":"Cairns",
    "sg:classifiers":[
        {
            "category":"Retail",
            "subcategory":"Auto Repair",
            "type":"Services"
        }
    ],
    "sg:phone":"+61 7 4051 2330",
    "sg:postcode":"4870",
    "sg:province":"QLD",
    "sg:tags":[
        "automotive",
        "air conditioning"
    ],
    "wof:name":"Williams Auto Electrician",
    "wof:placetype":"venue"
},
  "geometry": {"coordinates":[145.750442505,-16.9156532288],"type":"Point"}
}