{
  "type": "Feature",
  "properties": {
    "addr:full":"PO Box 4175 Pitt Town NSW 2756",
    "addr:postcode":"2756",
    "iso:country":"AU",
    "sg:address":"PO Box 4175",
    "sg:city":"Pitt Town",
    "sg:classifiers":[
        {
            "category":"Real Estate",
            "subcategory":"Real Estate Operator",
            "type":"Services"
        }
    ],
    "sg:phone":"+61 408 630 201",
    "sg:postcode":"2756",
    "sg:province":"NSW",
    "sg:tags":[
        "concrete",
        "pumping"
    ],
    "wof:name":"Son-Line Concrete Pumping Pty. Ltd.",
    "wof:placetype":"venue"
},
  "geometry": {"coordinates":[150.861938477,-33.5864486694],"type":"Point"}
}