{
  "type": "Feature",
  "properties": {
    "addr:full":"Vincent St Brunswick Junction WA 6224",
    "addr:postcode":"6224",
    "addr:street":"Vincent St",
    "iso:country":"AU",
    "sg:address":"Vincent St",
    "sg:city":"Brunswick Junction",
    "sg:classifiers":[
        {
            "category":"Education",
            "subcategory":"School",
            "type":"Public Place"
        }
    ],
    "sg:phone":"+61 8 9726 1142",
    "sg:postcode":"6224",
    "sg:province":"WA",
    "sg:tags":[
        "state",
        "except",
        "nsw"
    ],
    "wof:name":"Brunswick Primary School",
    "wof:placetype":"venue"
},
  "geometry": {"coordinates":[115.834198,-33.252716],"type":"Point"}
}