{
  "type": "Feature",
  "properties": {
    "addr:full":"1 McGowan St Putney NSW 2112",
    "addr:housenumber":"1",
    "addr:postcode":"2112",
    "addr:street":"Mcgowan St",
    "iso:country":"AU",
    "sg:address":"1 McGowan St",
    "sg:city":"Putney",
    "sg:classifiers":[
        {
            "category":"Banks & Credit Unions",
            "subcategory":"Financial Services",
            "type":"Services"
        }
    ],
    "sg:phone":"+61 2 9807 7700",
    "sg:postcode":"2112",
    "sg:province":"NSW",
    "sg:tags":[
        "planning"
    ],
    "wof:name":"Don Bailey",
    "wof:placetype":"venue"
},
  "geometry": {"coordinates":[151.11015319800001,-33.8322372437],"type":"Point"}
}