{
  "type": "Feature",
  "properties": {
    "addr:full":"58 Yamboyna St Manly QLD 4179",
    "addr:housenumber":"58",
    "addr:postcode":"4179",
    "addr:street":"Yamboyna St",
    "iso:country":"AU",
    "sg:address":"58 Yamboyna St",
    "sg:city":"Manly",
    "sg:classifiers":[
        {
            "category":"Professional",
            "subcategory":"Employment Agencies",
            "type":"Services"
        }
    ],
    "sg:phone":"+61 7 3396 3965",
    "sg:postcode":"4179",
    "sg:province":"QLD",
    "wof:name":"Wynnum Manly Employment & Training",
    "wof:placetype":"venue"
},
  "geometry": {"coordinates":[153.181274414,-27.4571762085],"type":"Point"}
}