{
  "type": "Feature",
  "properties": {
    "iso:country":"AU",
    "sg:address":"2 Missenden Rd",
    "sg:city":"Camperdown",
    "sg:classifiers":[
        {
            "category":"Social Services",
            "subcategory":"Child Care",
            "type":"Services"
        }
    ],
    "sg:phone":"+61 2 9516 1552",
    "sg:postcode":"2050",
    "sg:province":"NSW",
    "wof:name":"Camperdown Child Care Centre",
    "wof:placetype":"venue"
},
  "geometry": {"coordinates":[151.179733,-33.886745],"type":"Point"}
}