{
  "type": "Feature",
  "properties": {
    "iso:country":"AU",
    "sg:address":"94 Adams St",
    "sg:city":"Narrandera",
    "sg:classifiers":[
        {
            "category":"Food & Beverages",
            "subcategory":"Groceries & Convenience Stores",
            "type":"Retail Goods"
        }
    ],
    "sg:phone":"+61 2 6959 1699",
    "sg:postcode":"2700",
    "sg:province":"NSW",
    "wof:name":"Col & Betsy's Corner Store",
    "wof:placetype":"venue"
},
  "geometry": {"coordinates":[146.547729492,-34.7474212646],"type":"Point"}
}