{
  "type": "Feature",
  "properties": {
    "addr:full":"45 Queens Rd Everton Hills QLD 4053",
    "addr:housenumber":"45",
    "addr:postcode":"4053",
    "addr:street":"Queens Rd",
    "iso:country":"AU",
    "sg:address":"45 Queens Rd",
    "sg:city":"Everton Hills",
    "sg:classifiers":[
        {
            "category":"Shopping",
            "subcategory":"Music",
            "type":"Retail Goods"
        }
    ],
    "sg:phone":"+61 7 3353 0333",
    "sg:postcode":"4053",
    "sg:province":"QLD",
    "sg:tags":[
        "store"
    ],
    "wof:name":"Ever Technology",
    "wof:placetype":"venue"
},
  "geometry": {"coordinates":[152.978759766,-27.3887290955],"type":"Point"}
}