{
  "type": "Feature",
  "properties": {
    "addr:full":"77 Beach Rd Christies Beach SA 5165",
    "addr:housenumber":"77",
    "addr:postcode":"5165",
    "addr:street":"Beach Rd",
    "iso:country":"AU",
    "sg:address":"77 Beach Rd",
    "sg:city":"Christies Beach",
    "sg:classifiers":[
        {
            "category":"Health Services",
            "subcategory":"Doctor",
            "type":"Services"
        }
    ],
    "sg:phone":"+61 8 8382 5088",
    "sg:postcode":"5165",
    "sg:province":"SA",
    "sg:tags":[
        "medical",
        "practitioner"
    ],
    "wof:name":"Pahuja P D",
    "wof:placetype":"venue"
},
  "geometry": {"coordinates":[138.47920227,-35.1388893127],"type":"Point"}
}