{
  "type": "Feature",
  "properties": {
    "iso:country":"AU",
    "sg:address":"Grant Crt",
    "sg:city":"Shepparton",
    "sg:classifiers":[
        {
            "category":"Utilities",
            "subcategory":"Refuse",
            "type":"Services"
        }
    ],
    "sg:phone":"+61 3 5831 6639",
    "sg:postcode":"3630",
    "sg:province":"VIC",
    "sg:tags":[
        "disposal",
        "reduction",
        "waste"
    ],
    "wof:name":"Barry Bros Specialised Service Pty Ltd",
    "wof:placetype":"venue"
},
  "geometry": {"coordinates":[145.4034729,-36.3500518799],"type":"Point"}
}