{
  "type": "Feature",
  "properties": {
    "addr:full":"Unit 2 271 Selby St Churchlands WA 6018",
    "addr:housenumber":"271",
    "addr:postcode":"6018",
    "addr:street":"Selby St",
    "iso:country":"AU",
    "sg:address":"Unit 2 271 Selby St",
    "sg:city":"Churchlands",
    "sg:classifiers":[
        {
            "category":"Professional",
            "subcategory":"Accounting & Tax Preparation",
            "type":"Services"
        }
    ],
    "sg:phone":"+61 8 9387 8987",
    "sg:postcode":"6018",
    "sg:province":"WA",
    "sg:tags":[
        "consultant",
        "taxation"
    ],
    "wof:name":"Bhardwaj A",
    "wof:placetype":"venue"
},
  "geometry": {"coordinates":[115.80397796600001,-31.9318447113],"type":"Point"}
}