{
  "type": "Feature",
  "properties": {
    "addr:full":"439 Harbourside Festival Mar St Darling Harbour NSW 2000",
    "addr:housenumber":"439",
    "addr:postcode":"2000",
    "addr:street":"Harbourside Festival Mar St",
    "iso:country":"AU",
    "sg:address":"439 Harbourside Festival Mar St",
    "sg:city":"Darling Harbour",
    "sg:classifiers":[
        {
            "category":"Fast Food",
            "type":"Food & Drink"
        }
    ],
    "sg:phone":"+61 2 9281 3813",
    "sg:postcode":"2000",
    "sg:province":"NSW",
    "sg:tags":[
        "away",
        "take"
    ],
    "wof:name":"Jo Jo Ivorys",
    "wof:placetype":"venue"
},
  "geometry": {"coordinates":[151.19822692899999,-33.8725891113],"type":"Point"}
}