{
  "type": "Feature",
  "properties": {
    "iso:country":"AU",
    "sg:address":"Unit 2/ 13 Elliot Crt",
    "sg:city":"Hillcrest",
    "sg:classifiers":[
        {
            "category":"Autos & Motor Vehicles",
            "subcategory":"Auto Supplies",
            "type":"Retail Goods"
        }
    ],
    "sg:phone":"+61 7 3806 9711",
    "sg:postcode":"4118",
    "sg:province":"QLD",
    "sg:tags":[
        "part",
        "cycles",
        "accessory"
    ],
    "wof:name":"One Stop Motorcycles",
    "wof:placetype":"venue"
},
  "geometry": {"coordinates":[153.032745361,-27.6597709656],"type":"Point"}
}