{
  "type": "Feature",
  "properties": {
    "addr:full":"9 Burgay Crt Osborne Park WA 6017",
    "addr:housenumber":"9",
    "addr:postcode":"6017",
    "addr:street":"Burgay Crt",
    "iso:country":"AU",
    "sg:address":"9 Burgay Crt",
    "sg:city":"Osborne Park",
    "sg:classifiers":[
        {
            "category":"Social Services",
            "subcategory":"Retirement Home",
            "type":"Services"
        }
    ],
    "sg:phone":"+61 8 9244 3188",
    "sg:postcode":"6017",
    "sg:province":"WA",
    "sg:tags":[
        "t-shirt",
        "supplier"
    ],
    "wof:name":"R & R T Shirt Distributors WA",
    "wof:placetype":"venue"
},
  "geometry": {"coordinates":[115.803398132,-31.9065132141],"type":"Point"}
}