{
  "type": "Feature",
  "properties": {
    "addr:full":"12 Cobb & Co Drv Beerwah QLD 4519",
    "addr:housenumber":"12",
    "addr:postcode":"4519",
    "addr:street":"&;Drv",
    "iso:country":"AU",
    "sg:address":"12 Cobb & Co Drv",
    "sg:city":"Beerwah",
    "sg:classifiers":[
        {
            "category":"Health Services",
            "subcategory":"Health Practitioner",
            "type":"Services"
        }
    ],
    "sg:phone":"+61 7 5496 0252",
    "sg:postcode":"4519",
    "sg:province":"QLD",
    "sg:tags":[
        "acupuncture"
    ],
    "wof:name":"Whight, Narelle Frances",
    "wof:placetype":"venue"
},
  "geometry": {"coordinates":[152.96725499999999,-26.811001],"type":"Point"}
}