{
  "type": "Feature",
  "properties": {
    "iso:country":"AU",
    "sg:address":"12 Cobb & Co Drv",
    "sg:city":"Beerwah",
    "sg:classifiers":[
        {
            "category":"Health Services",
            "subcategory":"Health Practitioner",
            "type":"Services"
        }
    ],
    "sg:phone":"+61 7 5496 0252",
    "sg:postcode":"4519",
    "sg:province":"QLD",
    "sg:tags":[
        "acupuncture"
    ],
    "wof:name":"Whight, Narelle Frances",
    "wof:placetype":"venue"
},
  "geometry": {"coordinates":[152.967255,-26.811001],"type":"Point"}
}