{
  "type": "Feature",
  "properties": {
    "addr:full":"Goondoon St Gladstone QLD 4680",
    "addr:postcode":"4680",
    "addr:street":"Goondoon St",
    "iso:country":"AU",
    "sg:address":"Goondoon St",
    "sg:city":"Gladstone",
    "sg:classifiers":[
        {
            "category":"Food & Beverages",
            "subcategory":"Supermarket",
            "type":"Retail Goods"
        }
    ],
    "sg:phone":"+61 7 4124 5422",
    "sg:postcode":"4680",
    "sg:province":"QLD",
    "sg:tags":[
        "grocery",
        "store"
    ],
    "wof:name":"Centro Gladstone",
    "wof:placetype":"venue"
},
  "geometry": {"coordinates":[151.255584717,-23.8428573608],"type":"Point"}
}