{
  "type": "Feature",
  "properties": {
    "iso:country":"AU",
    "sg:address":"50a Main Rd",
    "sg:city":"Moonah",
    "sg:classifiers":[
        {
            "category":"Shopping",
            "subcategory":"Computers & Home Electronics",
            "type":"Retail Goods"
        }
    ],
    "sg:phone":"+61 3 6228 0922",
    "sg:postcode":"7009",
    "sg:province":"TAS",
    "sg:tags":[
        "equipment",
        "supply"
    ],
    "wof:name":"Cartridge World",
    "wof:placetype":"venue"
},
  "geometry": {"coordinates":[147.29609680199999,-42.848449707],"type":"Point"}
}