{
  "type": "Feature",
  "properties": {
    "addr:full":"8 Charles Rd Lilydale VIC 3140",
    "addr:housenumber":"8",
    "addr:postcode":"3140",
    "addr:street":"Charles Rd",
    "iso:country":"AU",
    "sg:address":"8 Charles Rd",
    "sg:city":"Lilydale",
    "sg:classifiers":[
        {
            "category":"Retail",
            "subcategory":"Auto Repair",
            "type":"Services"
        }
    ],
    "sg:phone":"+61 3 9739 5288",
    "sg:postcode":"3140",
    "sg:province":"VIC",
    "sg:tags":[
        "beater",
        "painter",
        "panel"
    ],
    "wof:name":"Smith Ian Panels & Automotive Repairs",
    "wof:placetype":"venue"
},
  "geometry": {"coordinates":[145.35867309599999,-37.779045105],"type":"Point"}
}