{
  "type": "Feature",
  "properties": {
    "iso:country":"AU",
    "sg:address":"Fcty 4/ 1",
    "sg:city":"Armstrong Gr Yarra Glen",
    "sg:classifiers":[
        {
            "category":"Retail",
            "subcategory":"Auto Repair",
            "type":"Services"
        }
    ],
    "sg:phone":"+61 3 9730 1844",
    "sg:postcode":"3775",
    "sg:province":"VIC",
    "sg:tags":[
        "repairer",
        "motor",
        "engineer"
    ],
    "wof:name":"Yarra Glen Brake & Front End Centre",
    "wof:placetype":"venue"
},
  "geometry": {"coordinates":[145.379486,-37.65799],"type":"Point"}
}