{
  "type": "Feature",
  "properties": {
    "iso:country":"AU",
    "sg:address":"12 Schooner St",
    "sg:city":"Jamboree Heights",
    "sg:classifiers":[
        {
            "category":"Building & Trades",
            "subcategory":"Landscaping Services",
            "type":"Services"
        }
    ],
    "sg:phone":"+61 7 3376 4277",
    "sg:postcode":"4074",
    "sg:province":"QLD",
    "sg:tags":[
        "designer",
        "landscape",
        "contractor"
    ],
    "wof:name":"Bloomin Bliss",
    "wof:placetype":"venue"
},
  "geometry": {"coordinates":[152.937942505,-27.5510406494],"type":"Point"}
}