{
  "type": "Feature",
  "properties": {
    "iso:country":"AU",
    "sg:address":"24 Landy St",
    "sg:city":"Horsham",
    "sg:classifiers":[
        {
            "category":"Building & Trades",
            "subcategory":"Construction",
            "type":"Services"
        }
    ],
    "sg:phone":"+61 3 5382 2838",
    "sg:postcode":"3400",
    "sg:province":"VIC",
    "sg:tags":[
        "contractor"
    ],
    "wof:name":"Taig G & L Pty Ltd",
    "wof:placetype":"venue"
},
  "geometry": {"coordinates":[142.191314697,-36.723285675],"type":"Point"}
}