{
  "type": "Feature",
  "properties": {
    "iso:country":"AU",
    "sg:address":"74 Moore St",
    "sg:city":"Campbelltown",
    "sg:classifiers":[
        {
            "category":"Building & Trades",
            "subcategory":"Landscaping Services",
            "type":"Services"
        }
    ],
    "sg:phone":"+61 2 4625 1201",
    "sg:postcode":"2560",
    "sg:province":"NSW",
    "sg:tags":[
        "consultant"
    ],
    "wof:name":"Jensen M.M. & S.J.",
    "wof:placetype":"venue"
},
  "geometry": {"coordinates":[150.81741332999999,-34.0681304932],"type":"Point"}
}