{
  "type": "Feature",
  "properties": {
    "iso:country":"AU",
    "sg:address":"6 Bricker St",
    "sg:city":"Cheltenham",
    "sg:classifiers":[
        {
            "category":"Home & Garden",
            "subcategory":"Building Materials",
            "type":"Retail Goods"
        }
    ],
    "sg:phone":"+61 3 9555 4717",
    "sg:postcode":"3192",
    "sg:province":"VIC",
    "sg:tags":[
        "supply"
    ],
    "wof:name":"Foilboard",
    "wof:placetype":"venue"
},
  "geometry": {"coordinates":[145.072265625,-37.9523048401],"type":"Point"}
}