{
  "type": "Feature",
  "properties": {
    "addr:full":"159 Burswood Rd Burswood WA 6100",
    "addr:housenumber":"159",
    "addr:postcode":"6100",
    "addr:street":"Burswood Rd",
    "iso:country":"AU",
    "sg:address":"159 Burswood Rd",
    "sg:city":"Burswood",
    "sg:classifiers":[
        {
            "category":"Retail",
            "subcategory":"Auto Repair",
            "type":"Services"
        }
    ],
    "sg:phone":"+61 8 9470 3337",
    "sg:postcode":"6100",
    "sg:province":"WA",
    "sg:tags":[
        "repairer",
        "motor",
        "engineer"
    ],
    "wof:name":"Stuttgart Autos",
    "wof:placetype":"venue"
},
  "geometry": {"coordinates":[115.89781189,-31.9648761749],"type":"Point"}
}