{
  "type": "Feature",
  "properties": {
    "iso:country":"AU",
    "sg:address":"The Sister Garvoc Rd",
    "sg:city":"The Sisters",
    "sg:classifiers":[
        {
            "category":"Farming",
            "subcategory":"Farm",
            "type":"Manufacturing & Wholesale Goods"
        }
    ],
    "sg:phone":"+61 3 5592 6297",
    "sg:postcode":"3265",
    "sg:province":"VIC",
    "sg:tags":[
        "farmer"
    ],
    "wof:name":"Kenna J M & E I",
    "wof:placetype":"venue"
},
  "geometry": {"coordinates":[142.76918029800001,-38.1981697083],"type":"Point"}
}