{
  "type": "Feature",
  "properties": {
    "addr:full":"206 Gympie Rd Maryborough QLD 4650",
    "addr:housenumber":"206",
    "addr:postcode":"4650",
    "addr:street":"Gympie Rd",
    "iso:country":"AU",
    "sg:address":"206 Gympie Rd",
    "sg:city":"Maryborough",
    "sg:classifiers":[
        {
            "category":"Shopping",
            "subcategory":"Crafts & Fabrics",
            "type":"Retail Goods"
        }
    ],
    "sg:phone":"+61 7 4121 2591",
    "sg:postcode":"4650",
    "sg:province":"QLD",
    "sg:tags":[
        "synthetic",
        "canvas",
        "product"
    ],
    "wof:name":"Stanfast Pty Ltd",
    "wof:placetype":"venue"
},
  "geometry": {"coordinates":[152.68176299999999,-25.546167],"type":"Point"}
}