{
  "type": "Feature",
  "properties": {
    "addr:full":"81 Sheridan St Cairns QLD 4870",
    "addr:housenumber":"81",
    "addr:postcode":"4870",
    "addr:street":"Sheridan St",
    "iso:country":"AU",
    "sg:address":"81 Sheridan St",
    "sg:city":"Cairns",
    "sg:classifiers":[
        {
            "category":"Professional",
            "subcategory":"Printing & Photocopies",
            "type":"Services"
        }
    ],
    "sg:phone":"+61 7 4031 5211",
    "sg:postcode":"4870",
    "sg:province":"QLD",
    "sg:tags":[
        "photocopying"
    ],
    "wof:name":"Cairns Instant Printing",
    "wof:placetype":"venue"
},
  "geometry": {"coordinates":[145.771881103,-16.9218196869],"type":"Point"}
}