{
  "type": "Feature",
  "properties": {
    "iso:country":"AU",
    "sg:address":"128 Marion Rd",
    "sg:city":"Richmond West",
    "sg:classifiers":[
        {
            "category":"Autos & Motor Vehicles",
            "subcategory":"Fuel & Gas Station",
            "type":"Retail Goods"
        }
    ],
    "sg:phone":"+61 8 8234 1074",
    "sg:postcode":"5033",
    "sg:province":"SA",
    "wof:name":"United Convenience Store",
    "wof:placetype":"venue"
},
  "geometry": {"coordinates":[138.552658081,-34.9365119934],"type":"Point"}
}