{
  "type": "Feature",
  "properties": {
    "iso:country":"AU",
    "sg:address":"18 Irene Crt",
    "sg:city":"Cheltenham",
    "sg:classifiers":[
        {
            "category":"Professional",
            "subcategory":"Accounting & Tax Preparation",
            "type":"Services"
        }
    ],
    "sg:phone":"+61 438 846 984",
    "sg:postcode":"3192",
    "sg:province":"VIC",
    "sg:tags":[
        "bookkeeping"
    ],
    "wof:name":"T-GO Business Services",
    "wof:placetype":"venue"
},
  "geometry": {"coordinates":[145.07423400900001,-37.9655151367],"type":"Point"}
}