{
  "type": "Feature",
  "properties": {
    "iso:country":"AU",
    "sg:address":"2/ 13 Strathwyn St",
    "sg:city":"Brendale",
    "sg:classifiers":[
        {
            "category":"Home & Garden",
            "subcategory":"Hardware",
            "type":"Retail Goods"
        }
    ],
    "sg:phone":"+61 7 3881 3450",
    "sg:postcode":"4500",
    "sg:province":"QLD",
    "sg:tags":[
        "generating",
        "set",
        "generator"
    ],
    "wof:name":"Powerlite Generators",
    "wof:placetype":"venue"
},
  "geometry": {"coordinates":[152.978805542,-27.3205680847],"type":"Point"}
}