{
  "type": "Feature",
  "properties": {
    "iso:country":"AU",
    "sg:address":"PO Box 3022",
    "sg:city":"Victoria Gardens",
    "sg:classifiers":[
        {
            "category":"Government",
            "subcategory":"Court House",
            "type":"Public Place"
        }
    ],
    "sg:phone":"+61 3 9428 2899",
    "sg:postcode":"3121",
    "sg:province":"VIC",
    "sg:tags":[
        "personal",
        "marriage",
        "family",
        "counselling"
    ],
    "wof:name":"Mens Referral Service",
    "wof:placetype":"venue"
},
  "geometry": {"coordinates":[145.00813293499999,-37.8220596313],"type":"Point"}
}