{
  "type": "Feature",
  "properties": {
    "addr:full":"14 Chester St Fortitude Valley QLD 4006",
    "addr:housenumber":"14",
    "addr:postcode":"4006",
    "addr:street":"Chester St",
    "iso:country":"AU",
    "sg:address":"14 Chester St",
    "sg:city":"Fortitude Valley",
    "sg:classifiers":[
        {
            "category":"Wholesale",
            "subcategory":"Electrical",
            "type":"Manufacturing & Wholesale Goods"
        }
    ],
    "sg:phone":"+61 7 3370 0333",
    "sg:postcode":"4006",
    "sg:province":"QLD",
    "sg:tags":[
        "wholesaler"
    ],
    "wof:name":"Haymans Electrical",
    "wof:placetype":"venue"
},
  "geometry": {"coordinates":[153.04060363799999,-27.4538402557],"type":"Point"}
}