{
  "type": "Feature",
  "properties": {
    "addr:full":"483 Brighton Rd Brighton SA 5048",
    "addr:housenumber":"483",
    "addr:postcode":"5048",
    "addr:street":"Brighton Rd",
    "iso:country":"AU",
    "sg:address":"483 Brighton Rd",
    "sg:city":"Brighton",
    "sg:classifiers":[
        {
            "category":"Personal",
            "subcategory":"Beauty Salon",
            "type":"Services"
        }
    ],
    "sg:phone":"+61 8 8298 6306",
    "sg:postcode":"5048",
    "sg:province":"SA",
    "sg:tags":[
        "hairdresser"
    ],
    "wof:name":"Nicholls John",
    "wof:placetype":"venue"
},
  "geometry": {"coordinates":[138.522919,-35.018257],"type":"Point"}
}