{
  "type": "Feature",
  "properties": {
    "iso:country":"AU",
    "sg:address":"St Stephen&#039;s Hall Annand St",
    "sg:city":"Toowoomba",
    "sg:classifiers":[
        {
            "category":"Education",
            "subcategory":"Dance Studio",
            "type":"Public Place"
        }
    ],
    "sg:phone":"+61 7 4632 5435",
    "sg:postcode":"4350",
    "sg:province":"QLD",
    "sg:tags":[
        "venue",
        "tuition"
    ],
    "wof:name":"Dale Coles A.R.A.D",
    "wof:placetype":"venue"
},
  "geometry": {"coordinates":[151.953781,-27.564741],"type":"Point"}
}