{
  "type": "Feature",
  "properties": {
    "iso:country":"AU",
    "sg:address":"Factory 3/ 115 Elm Park Drv",
    "sg:city":"Hoppers Crossing",
    "sg:classifiers":[
        {
            "category":"Manufacturing",
            "subcategory":"Motor Vehicles & Parts",
            "type":"Manufacturing & Wholesale Goods"
        }
    ],
    "sg:phone":"+61 3 9748 8691",
    "sg:postcode":"3029",
    "sg:province":"VIC",
    "sg:tags":[
        "replacement"
    ],
    "wof:name":"Hoppers Crossing Radiator Services",
    "wof:placetype":"venue"
},
  "geometry": {"coordinates":[144.720703,-37.871986],"type":"Point"}
}