{
  "type": "Feature",
  "properties": {
    "addr:full":"Factory 3/ 115 Elm Park Drv Hoppers Crossing VIC 3029",
    "addr:housenumber":"/ 115",
    "addr:postcode":"3029",
    "addr:street":"Elm Park Drv",
    "iso:country":"AU",
    "sg:address":"Factory 3/ 115 Elm Park Drv",
    "sg:city":"Hoppers Crossing",
    "sg:classifiers":[
        {
            "category":"Manufacturing",
            "subcategory":"Motor Vehicles & Parts",
            "type":"Manufacturing & Wholesale Goods"
        }
    ],
    "sg:phone":"+61 3 9748 8691",
    "sg:postcode":"3029",
    "sg:province":"VIC",
    "sg:tags":[
        "replacement"
    ],
    "wof:name":"Hoppers Crossing Radiator Services",
    "wof:placetype":"venue"
},
  "geometry": {"coordinates":[144.72070299999999,-37.871986],"type":"Point"}
}