{
  "type": "Feature",
  "properties": {
    "addr:full":"16 Mildura St Fyshwick ACT 2609",
    "addr:housenumber":"16",
    "addr:postcode":"2609",
    "addr:street":"Mildura St",
    "iso:country":"AU",
    "sg:address":"16 Mildura St",
    "sg:city":"Fyshwick",
    "sg:classifiers":[
        {
            "category":"Professional",
            "subcategory":"Testing Lab",
            "type":"Services"
        }
    ],
    "sg:phone":"+61 2 6260 7288",
    "sg:postcode":"2609",
    "sg:province":"ACT",
    "sg:tags":[
        "soil",
        "investigation"
    ],
    "wof:name":"Coffey Geotechnics Pty Ltd",
    "wof:placetype":"venue"
},
  "geometry": {"coordinates":[149.152633667,-35.3215866089],"type":"Point"}
}