{
  "type": "Feature",
  "properties": {
    "iso:country":"AU",
    "sg:address":"Shute Harbour Rd",
    "sg:city":"Airlie Beach",
    "sg:classifiers":[
        {
            "category":"Restaurant",
            "type":"Food & Drink"
        }
    ],
    "sg:phone":"+61 7 4946 5033",
    "sg:postcode":"4802",
    "sg:province":"QLD",
    "wof:name":"Cappas Cake & Ale",
    "wof:placetype":"venue"
},
  "geometry": {"coordinates":[148.71969604500001,-20.2692375183],"type":"Point"}
}