{
  "type": "Feature",
  "properties": {
    "addr:full":"138 Vincent St Cessnock NSW 2325",
    "addr:housenumber":"138",
    "addr:postcode":"2325",
    "addr:street":"Vincent St",
    "iso:country":"AU",
    "sg:address":"138 Vincent St",
    "sg:city":"Cessnock",
    "sg:classifiers":[
        {
            "category":"Shopping",
            "subcategory":"Music",
            "type":"Retail Goods"
        }
    ],
    "sg:phone":"+61 2 4990 8068",
    "sg:postcode":"2325",
    "sg:province":"NSW",
    "sg:tags":[
        "instrument",
        "musical"
    ],
    "wof:name":"Musitopia",
    "wof:placetype":"venue"
},
  "geometry": {"coordinates":[151.356033325,-32.8371734619],"type":"Point"}
}