{
  "type": "Feature",
  "properties": {
    "iso:country":"AU",
    "sg:address":"Lvl 11/ 124 Walker St",
    "sg:city":"North Sydney",
    "sg:classifiers":[
        {
            "category":"Professional",
            "subcategory":"Computer Services",
            "type":"Services"
        }
    ],
    "sg:phone":"+61 411 595 443",
    "sg:postcode":"2060",
    "sg:province":"NSW",
    "sg:tags":[
        "package",
        "software"
    ],
    "wof:name":"R.S.A.",
    "wof:placetype":"venue"
},
  "geometry": {"coordinates":[151.20901489299999,-33.8373031616],"type":"Point"}
}