{
  "type": "Feature",
  "properties": {
    "iso:country":"AU",
    "sg:address":"2/ 272- 274",
    "sg:city":"Princes Way Drouin",
    "sg:classifiers":[
        {
            "category":"Autos & Motor Vehicles",
            "subcategory":"Automobile Sales",
            "type":"Retail Goods"
        }
    ],
    "sg:phone":"+61 3 5625 4911",
    "sg:postcode":"3818",
    "sg:province":"VIC",
    "sg:tags":[
        "car",
        "used"
    ],
    "wof:name":"Drouin Car Sales",
    "wof:placetype":"venue"
},
  "geometry": {"coordinates":[145.845444,-38.123344],"type":"Point"}
}