{
  "type": "Feature",
  "properties": {
    "addr:full":"221 Stud Rd Wantirna South VIC 3152",
    "addr:housenumber":"221",
    "addr:postcode":"3152",
    "addr:street":"Stud Rd",
    "iso:country":"AU",
    "sg:address":"221 Stud Rd",
    "sg:city":"Wantirna South",
    "sg:classifiers":[
        {
            "category":"Food & Beverages",
            "subcategory":"Bakery",
            "type":"Retail Goods"
        }
    ],
    "sg:phone":"+61 3 9801 6263",
    "sg:postcode":"3152",
    "sg:province":"VIC",
    "sg:tags":[
        "baker"
    ],
    "wof:name":"Fran's Studfield Bakeries",
    "wof:placetype":"venue"
},
  "geometry": {"coordinates":[145.24029540999999,-37.8601303101],"type":"Point"}
}