{
  "type": "Feature",
  "properties": {
    "addr:full":"9 Harley Crt Finley NSW 2713",
    "addr:housenumber":"9",
    "addr:postcode":"2713",
    "addr:street":"Harley Crt",
    "iso:country":"AU",
    "sg:address":"9 Harley Crt",
    "sg:city":"Finley",
    "sg:classifiers":[
        {
            "category":"Building & Trades",
            "subcategory":"Construction",
            "type":"Services"
        }
    ],
    "sg:phone":"+61 3 5883 1428",
    "sg:postcode":"2713",
    "sg:province":"NSW",
    "sg:tags":[
        "earth",
        "excavating",
        "moving",
        "contractor"
    ],
    "wof:name":"Robinson John M",
    "wof:placetype":"venue"
},
  "geometry": {"coordinates":[145.58009338400001,-35.630443573],"type":"Point"}
}