{
  "type": "Feature",
  "properties": {
    "iso:country":"AU",
    "sg:address":"25 Huntingdale Rd",
    "sg:city":"Burwood",
    "sg:classifiers":[
        {
            "category":"Professional",
            "type":"Services"
        }
    ],
    "sg:phone":"+61 3 9808 6000",
    "sg:postcode":"3125",
    "sg:province":"VIC",
    "sg:tags":[
        "courier"
    ],
    "wof:name":"Blue Circle Warehousing",
    "wof:placetype":"venue"
},
  "geometry": {"coordinates":[145.113479614,-37.8575439453],"type":"Point"}
}