{
  "type": "Feature",
  "properties": {
    "addr:full":"1001 Nepean Hwy Moorabbin VIC 3189",
    "addr:housenumber":"1001",
    "addr:postcode":"3189",
    "addr:street":"Nepean Hwy",
    "iso:country":"AU",
    "sg:address":"1001 Nepean Hwy",
    "sg:city":"Moorabbin",
    "sg:classifiers":[
        {
            "category":"Shopping",
            "subcategory":"Computers & Home Electronics",
            "type":"Retail Goods"
        }
    ],
    "sg:phone":"+61 3 9553 3573",
    "sg:postcode":"3189",
    "sg:province":"VIC",
    "sg:tags":[
        "equipment",
        "part",
        "electronic"
    ],
    "wof:name":"Tandy Electronics",
    "wof:placetype":"venue"
},
  "geometry": {"coordinates":[145.03709411599999,-37.9359207153],"type":"Point"}
}