{
  "type": "Feature",
  "properties": {
    "addr:full":"75 Webb St Stafford QLD 4053",
    "addr:housenumber":"75",
    "addr:postcode":"4053",
    "addr:street":"Webb St",
    "iso:country":"AU",
    "sg:address":"75 Webb St",
    "sg:city":"Stafford",
    "sg:classifiers":[
        {
            "category":"Social Services",
            "subcategory":"Retirement Home",
            "type":"Services"
        }
    ],
    "sg:phone":"+61 7 3356 1550",
    "sg:postcode":"4053",
    "sg:province":"QLD",
    "sg:tags":[
        "environmental",
        "consultant",
        "pollution"
    ],
    "wof:name":"NETech Network Environment Technologies",
    "wof:placetype":"venue"
},
  "geometry": {"coordinates":[153.000366211,-27.4098434448],"type":"Point"}
}