{
  "type": "Feature",
  "properties": {
    "addr:full":"2/ 321 Balwyn Rd Balwyn North VIC 3104",
    "addr:housenumber":"/ 321",
    "addr:postcode":"3104",
    "addr:street":"Balwyn Rd",
    "iso:country":"AU",
    "sg:address":"2/ 321 Balwyn Rd",
    "sg:city":"Balwyn North",
    "sg:classifiers":[
        {
            "category":"Professional",
            "subcategory":"Engineering",
            "type":"Services"
        }
    ],
    "sg:phone":"+61 3 9857 4900",
    "sg:postcode":"3104",
    "sg:province":"VIC",
    "sg:tags":[
        "electronic",
        "engineer"
    ],
    "wof:name":"Omnitron Technologies",
    "wof:placetype":"venue"
},
  "geometry": {"coordinates":[145.086105347,-37.7873916626],"type":"Point"}
}