{
  "type": "Feature",
  "properties": {
    "addr:full":"5 Noonameena Drv Orange NSW 2800",
    "addr:housenumber":"5",
    "addr:postcode":"2800",
    "addr:street":"Noonameena Drv",
    "iso:country":"AU",
    "sg:address":"5 Noonameena Drv",
    "sg:city":"Orange",
    "sg:classifiers":[
        {
            "category":"Professional",
            "subcategory":"Art Services",
            "type":"Services"
        }
    ],
    "sg:phone":"+61 2 6362 3808",
    "sg:postcode":"2800",
    "sg:province":"NSW",
    "sg:tags":[
        "picture",
        "frame",
        "framing"
    ],
    "wof:name":"Action Photos & Framing",
    "wof:placetype":"venue"
},
  "geometry": {"coordinates":[149.07191467300001,-33.284324646],"type":"Point"}
}