{
  "type": "Feature",
  "properties": {
    "iso:country":"AU",
    "sg:address":"PO Box 17",
    "sg:city":"Capella",
    "sg:classifiers":[
        {
            "category":"Food & Beverages",
            "subcategory":"Specialty",
            "type":"Retail Goods"
        }
    ],
    "sg:phone":"+61 427 849 151",
    "sg:postcode":"4723",
    "sg:province":"QLD",
    "sg:tags":[
        "product",
        "health"
    ],
    "wof:name":"Timeless Remedies",
    "wof:placetype":"venue"
},
  "geometry": {"coordinates":[148.02314799999999,-23.08637],"type":"Point"}
}