{
  "type": "Feature",
  "properties": {
    "addr:full":"U4/ 10 Hudson Ave Castle Hill NSW 2154",
    "addr:housenumber":"10",
    "addr:postcode":"2154",
    "addr:street":"U4 /;Hudson Ave",
    "iso:country":"AU",
    "sg:address":"U4/ 10 Hudson Ave",
    "sg:city":"Castle Hill",
    "sg:classifiers":[
        {
            "category":"Building & Trades",
            "subcategory":"Plumbing",
            "type":"Services"
        }
    ],
    "sg:phone":"+61 2 9894 8188",
    "sg:postcode":"2154",
    "sg:province":"NSW",
    "sg:tags":[
        "plumber",
        "gasfitters"
    ],
    "wof:name":"Cleary Plumbing Services Pty Ltd",
    "wof:placetype":"venue"
},
  "geometry": {"coordinates":[150.97450256400001,-33.7294998169],"type":"Point"}
}