{
  "type": "Feature",
  "properties": {
    "addr:full":"163 Anakie Rd Bell Post Hill VIC 3215",
    "addr:housenumber":"163",
    "addr:postcode":"3215",
    "addr:street":"Anakie Rd;Post Hill",
    "iso:country":"AU",
    "sg:address":"163 Anakie Rd",
    "sg:city":"Bell Post Hill",
    "sg:classifiers":[
        {
            "category":"Shopping",
            "subcategory":"Computers & Home Electronics",
            "type":"Retail Goods"
        }
    ],
    "sg:phone":"+61 3 5278 3890",
    "sg:postcode":"3215",
    "sg:province":"VIC",
    "sg:tags":[
        "equipment",
        "multimedia"
    ],
    "wof:name":"Beechfront Media",
    "wof:placetype":"venue"
},
  "geometry": {"coordinates":[144.33314514200001,-38.1015663147],"type":"Point"}
}