{
  "type": "Feature",
  "properties": {
    "addr:full":"83 Miller St Epping VIC 3076",
    "addr:housenumber":"83",
    "addr:postcode":"3076",
    "addr:street":"Miller St",
    "iso:country":"AU",
    "sg:address":"83 Miller St",
    "sg:city":"Epping",
    "sg:classifiers":[
        {
            "category":"Home & Garden",
            "subcategory":"Building Materials",
            "type":"Retail Goods"
        }
    ],
    "sg:phone":"+61 3 9408 7711",
    "sg:postcode":"3076",
    "sg:province":"VIC",
    "sg:tags":[
        "fencing"
    ],
    "wof:name":"Surdex Steel Pty Ltd",
    "wof:placetype":"venue"
},
  "geometry": {"coordinates":[144.990402222,-37.751335144],"type":"Point"}
}