{
  "type": "Feature",
  "properties": {
    "iso:country":"AU",
    "sg:address":"Level 1/ 41 Weston St",
    "sg:city":"Brunswick",
    "sg:classifiers":[
        {
            "category":"Professional",
            "subcategory":"Engineering",
            "type":"Services"
        }
    ],
    "sg:phone":"+61 3 9381 2200",
    "sg:postcode":"3056",
    "sg:province":"VIC",
    "sg:tags":[
        "consulting",
        "engineer"
    ],
    "wof:name":"Incode Pty Ltd",
    "wof:placetype":"venue"
},
  "geometry": {"coordinates":[144.96437072800001,-37.7749328613],"type":"Point"}
}