{
  "type": "Feature",
  "properties": {
    "iso:country":"AU",
    "sg:address":"9 Mitchell St",
    "sg:city":"Bendigo",
    "sg:classifiers":[
        {
            "category":"Shopping",
            "subcategory":"Clothing, Apparel, & Fashions",
            "type":"Retail Goods"
        }
    ],
    "sg:phone":"+61 3 5444 4972",
    "sg:postcode":"3539",
    "sg:province":"VIC",
    "sg:tags":[
        "menswear"
    ],
    "wof:name":"Ed Harry Menswear",
    "wof:placetype":"venue"
},
  "geometry": {"coordinates":[144.278885,-36.759796],"type":"Point"}
}