{
  "type": "Feature",
  "properties": {
    "addr:full":"120- 130 Townsend Rd St Albans Park VIC 3219",
    "addr:housenumber":"130",
    "addr:postcode":"3219",
    "addr:street":"Townsend Rd",
    "iso:country":"AU",
    "sg:address":"120- 130 Townsend Rd St",
    "sg:city":"Albans Park",
    "sg:classifiers":[
        {
            "category":"Health Services",
            "subcategory":"Nursing And Care Facility",
            "type":"Services"
        }
    ],
    "sg:phone":"+61 1800 243 227",
    "sg:postcode":"3219",
    "sg:province":"VIC",
    "sg:tags":[
        "home"
    ],
    "wof:name":"Tannoch Brae Hostel",
    "wof:placetype":"venue"
},
  "geometry": {"coordinates":[144.395462036,-38.181968689],"type":"Point"}
}