{
  "type": "Feature",
  "properties": {
    "iso:country":"AU",
    "sg:address":"4 Hunt Rd",
    "sg:city":"Hahndorf",
    "sg:classifiers":[
        {
            "category":"Building & Trades",
            "subcategory":"Plumbing",
            "type":"Services"
        }
    ],
    "sg:phone":"+61 438 887 965",
    "sg:postcode":"5245",
    "sg:province":"SA",
    "sg:tags":[
        "plumber",
        "gasfitters"
    ],
    "wof:name":"Keith White Plumbing",
    "wof:placetype":"venue"
},
  "geometry": {"coordinates":[138.80552673299999,-35.0289306641],"type":"Point"}
}