{
  "type": "Feature",
  "properties": {
    "addr:full":"St John of God 29 Heathfeild Rd Brighton East VIC 3187",
    "addr:housenumber":"29",
    "addr:postcode":"3187",
    "addr:street":"Heathfeild Rd",
    "iso:country":"AU",
    "sg:address":"St John of God 29 Heathfeild Rd",
    "sg:city":"Brighton East",
    "sg:classifiers":[
        {
            "category":"Health Services",
            "subcategory":"Doctor",
            "type":"Services"
        }
    ],
    "sg:phone":"+61 3 9592 4399",
    "sg:postcode":"3187",
    "sg:province":"VIC",
    "sg:tags":[
        "medical",
        "practitioner"
    ],
    "wof:name":"Robinson W B",
    "wof:placetype":"venue"
},
  "geometry": {"coordinates":[145.008666992,-37.9273414612],"type":"Point"}
}