{
  "type": "Feature",
  "properties": {
    "addr:full":"2 Industry Drv Lismore NSW 2480",
    "addr:housenumber":"2",
    "addr:postcode":"2480",
    "addr:street":"Industry Drv",
    "iso:country":"AU",
    "sg:address":"2 Industry Drv",
    "sg:city":"Lismore",
    "sg:classifiers":[
        {
            "category":"Wholesale",
            "subcategory":"Durable Goods & Equipment",
            "type":"Manufacturing & Wholesale Goods"
        }
    ],
    "sg:phone":"+61 2 6621 9544",
    "sg:postcode":"2480",
    "sg:province":"NSW",
    "sg:tags":[
        "logging",
        "sawmilling"
    ],
    "wof:name":"McKeeco General Engineering Pty. Ltd.",
    "wof:placetype":"venue"
},
  "geometry": {"coordinates":[153.30067443900001,-28.8217830658],"type":"Point"}
}