{
  "type": "Feature",
  "properties": {
    "iso:country":"AU",
    "sg:address":"Unit 4 151 Robinson Rd",
    "sg:city":"(East) Geebung",
    "sg:classifiers":[
        {
            "category":"Manufacturing",
            "subcategory":"Paper Products",
            "type":"Manufacturing & Wholesale Goods"
        }
    ],
    "sg:phone":"+61 7 3865 2993",
    "sg:postcode":"4034",
    "sg:province":"QLD",
    "sg:tags":[
        "building",
        "fibre",
        "cement"
    ],
    "wof:name":"Guardian Building Products (QLD) Pty Ltd",
    "wof:placetype":"venue"
},
  "geometry": {"coordinates":[153.05401599999999,-27.369165],"type":"Point"}
}