{
  "type": "Feature",
  "properties": {
    "iso:country":"AU",
    "sg:address":"16 Holloway St",
    "sg:city":"Ormond",
    "sg:classifiers":[
        {
            "category":"Building & Trades",
            "subcategory":"Plumbing",
            "type":"Services"
        }
    ],
    "sg:phone":"+61 418 342 552",
    "sg:postcode":"3204",
    "sg:province":"VIC",
    "sg:tags":[
        "plumber",
        "gasfitters"
    ],
    "wof:name":"Le Couilliard Bros Pty Ltd",
    "wof:placetype":"venue"
},
  "geometry": {"coordinates":[145.04624899999999,-37.901867],"type":"Point"}
}