{
  "type": "Feature",
  "properties": {
    "addr:full":"Lot 1 Sturt Hwy Mildura South VIC 3500",
    "addr:housenumber":"1",
    "addr:postcode":"3500",
    "addr:street":"Sturt Hwy",
    "iso:country":"AU",
    "sg:address":"Lot 1 Sturt Hwy",
    "sg:city":"Mildura South",
    "sg:classifiers":[
        {
            "category":"Building & Trades",
            "subcategory":"Construction",
            "type":"Services"
        }
    ],
    "sg:phone":"+61 3 5023 2133",
    "sg:postcode":"3500",
    "sg:province":"VIC",
    "sg:tags":[
        "concrete",
        "contractor"
    ],
    "wof:name":"Arnold R.J. & T.",
    "wof:placetype":"venue"
},
  "geometry": {"coordinates":[142.10023498499999,-34.2321548462],"type":"Point"}
}