{
  "type": "Feature",
  "properties": {
    "addr:full":"26 Avondale Drv Banora Point NSW 2486",
    "addr:housenumber":"26",
    "addr:postcode":"2486",
    "addr:street":"Avondale Drv",
    "iso:country":"AU",
    "sg:address":"26 Avondale Drv",
    "sg:city":"Banora Point",
    "sg:classifiers":[
        {
            "category":"Professional",
            "subcategory":"Art Services",
            "type":"Services"
        }
    ],
    "sg:phone":"+61 7 5524 2256",
    "sg:postcode":"2486",
    "sg:province":"NSW",
    "sg:tags":[
        "decorator",
        "painter"
    ],
    "wof:name":"Everingham & Walker",
    "wof:placetype":"venue"
},
  "geometry": {"coordinates":[153.530395508,-28.2106533051],"type":"Point"}
}