{
  "type": "Feature",
  "properties": {
    "iso:country":"AU",
    "sg:address":"Shop 8, 290- 300 Elizabeth St",
    "sg:city":"Surry Hills",
    "sg:classifiers":[
        {
            "category":"Health Services",
            "subcategory":"Dentist",
            "type":"Services"
        }
    ],
    "sg:phone":"+61 2 9211 2224",
    "sg:postcode":"2010",
    "sg:province":"NSW",
    "wof:name":"Dr Naji Freiha",
    "wof:placetype":"venue"
},
  "geometry": {"coordinates":[151.20893859899999,-33.8811416626],"type":"Point"}
}