{
  "type": "Feature",
  "properties": {
    "iso:country":"AU",
    "sg:address":"38 Dowling St",
    "sg:city":"Thargomindah",
    "sg:classifiers":[
        {
            "category":"Travel",
            "subcategory":"Hotels & Motels",
            "type":"Entertainment"
        }
    ],
    "sg:phone":"+61 7 4655 3155",
    "sg:postcode":"4492",
    "sg:province":"QLD",
    "wof:name":"Thargomindah Oasis Motel",
    "wof:placetype":"venue"
},
  "geometry": {"coordinates":[143.82290649399999,-27.9966983795],"type":"Point"}
}