{
  "type": "Feature",
  "properties": {
    "addr:full":"Level 8 - 88 Philip St Sydney NSW 2000",
    "addr:housenumber":"88",
    "addr:postcode":"2000",
    "addr:street":"Philip St",
    "iso:country":"AU",
    "sg:address":"Level 8 - 88 Philip St",
    "sg:city":"Sydney",
    "sg:classifiers":[
        {
            "category":"Professional",
            "subcategory":"Employment Agencies",
            "type":"Services"
        }
    ],
    "sg:phone":"+61 2 9252 8555",
    "sg:postcode":"2000",
    "sg:province":"NSW",
    "wof:name":"ELR Executive Pty Ltd",
    "wof:placetype":"venue"
},
  "geometry": {"coordinates":[151.211791992,-33.8648147583],"type":"Point"}
}