{
  "type": "Feature",
  "properties": {
    "addr:full":"Kiosk 210, Westfield S/C, Creek Rd Carindale QLD 4152",
    "addr:housenumber":"210",
    "addr:postcode":"4152",
    "addr:street":"Westfield S / C Creek Rd",
    "iso:country":"AU",
    "sg:address":"Kiosk 210, Westfield S/C, Creek Rd",
    "sg:city":"Carindale",
    "sg:classifiers":[
        {
            "category":"Shopping",
            "subcategory":"Mobile Phones",
            "type":"Retail Goods"
        }
    ],
    "sg:phone":"+61 7 3324 9977",
    "sg:postcode":"4152",
    "sg:province":"QLD",
    "sg:tags":[
        "telephone",
        "accessory"
    ],
    "wof:name":"TeleChoice",
    "wof:placetype":"venue"
},
  "geometry": {"coordinates":[153.09974670400001,-27.5049972534],"type":"Point"}
}