{
  "type": "Feature",
  "properties": {
    "addr:full":"478 Ruthven St Toowoomba QLD 4350",
    "addr:housenumber":"478",
    "addr:postcode":"4350",
    "addr:street":"Ruthven St",
    "iso:country":"AU",
    "sg:address":"478 Ruthven St",
    "sg:city":"Toowoomba",
    "sg:classifiers":[
        {
            "category":"Shopping",
            "subcategory":"Discount & Variety Stores",
            "type":"Retail Goods"
        }
    ],
    "sg:phone":"+61 7 4613 1005",
    "sg:postcode":"4350",
    "sg:province":"QLD",
    "sg:tags":[
        "shop",
        "adult"
    ],
    "sg:website":"http://www.aoadultshop.com.au",
    "wof:name":"AO Adult Shop",
    "wof:placetype":"venue"
},
  "geometry": {"coordinates":[151.95230100000001,-27.568174],"type":"Point"}
}