{
  "type": "Feature",
  "properties": {
    "addr:full":"9- 11 Parsons St Clayton VIC 3168",
    "addr:housenumber":"11",
    "addr:postcode":"3168",
    "addr:street":"9;Parsons St",
    "iso:country":"AU",
    "sg:address":"9- 11 Parsons St",
    "sg:city":"Clayton",
    "sg:classifiers":[
        {
            "category":"Community Center",
            "subcategory":"Youth",
            "type":"Public Place"
        }
    ],
    "sg:phone":"+61 3 9543 7666",
    "sg:postcode":"3168",
    "sg:province":"VIC",
    "sg:tags":[
        "workshop",
        "sheltered"
    ],
    "wof:name":"South East Industries",
    "wof:placetype":"venue"
},
  "geometry": {"coordinates":[145.12005615199999,-37.9306640625],"type":"Point"}
}