{
  "type": "Feature",
  "properties": {
    "addr:full":"52 Winter Rd Kallangur QLD 4503",
    "addr:housenumber":"52",
    "addr:postcode":"4503",
    "addr:street":"Winter Rd",
    "iso:country":"AU",
    "sg:address":"52 Winter Rd",
    "sg:city":"Kallangur",
    "sg:classifiers":[
        {
            "category":"Utilities",
            "subcategory":"Electric",
            "type":"Services"
        }
    ],
    "sg:phone":"+61 7 3886 0124",
    "sg:postcode":"4503",
    "sg:province":"QLD",
    "sg:tags":[
        "electrical",
        "contractor"
    ],
    "wof:name":"Peter E Richardson",
    "wof:placetype":"venue"
},
  "geometry": {"coordinates":[153.00506591800001,-27.2509231567],"type":"Point"}
}