{
  "type": "Feature",
  "properties": {
    "addr:full":"Lvl 1/ 29 Melrose St Sandringham VIC 3191",
    "addr:housenumber":"/ 29",
    "addr:postcode":"3191",
    "addr:street":"Melrose St",
    "iso:country":"AU",
    "sg:address":"Lvl 1/ 29 Melrose St",
    "sg:city":"Sandringham",
    "sg:classifiers":[
        {
            "category":"Travel",
            "subcategory":"Travel Agent",
            "type":"Entertainment"
        }
    ],
    "sg:phone":"+61 3 9598 1400",
    "sg:postcode":"3191",
    "sg:province":"VIC",
    "sg:tags":[
        "consultant"
    ],
    "wof:name":"Encore Travel Pty Ltd",
    "wof:placetype":"venue"
},
  "geometry": {"coordinates":[145.00367736800001,-37.9504585266],"type":"Point"}
}