{
  "type": "Feature",
  "properties": {
    "iso:country":"AU",
    "sg:address":"96 Bell St",
    "sg:city":"Preston",
    "sg:classifiers":[
        {
            "category":"Manufacturing",
            "subcategory":"Paper Products",
            "type":"Manufacturing & Wholesale Goods"
        }
    ],
    "sg:phone":"+61 3 9474 0900",
    "sg:postcode":"3072",
    "sg:province":"VIC",
    "sg:tags":[
        "metal",
        "non-ferrous",
        "foundry"
    ],
    "wof:name":"Harrop Casting Technologies Pty Ltd",
    "wof:placetype":"venue"
},
  "geometry": {"coordinates":[145.025787353,-37.7475280762],"type":"Point"}
}