{
  "type": "Feature",
  "properties": {
    "addr:full":"77 Illoura Rd Romaine TAS 7320",
    "addr:housenumber":"77",
    "addr:postcode":"7320",
    "addr:street":"Illoura Rd",
    "iso:country":"AU",
    "sg:address":"77 Illoura Rd",
    "sg:city":"Romaine",
    "sg:classifiers":[
        {
            "category":"Building & Trades",
            "subcategory":"Cleaning & Sanitation",
            "type":"Services"
        }
    ],
    "sg:phone":"+61 3 6433 1269",
    "sg:postcode":"7320",
    "sg:province":"TAS",
    "sg:tags":[
        "tank",
        "septic"
    ],
    "wof:name":"Newmans Industrial Pumping",
    "wof:placetype":"venue"
},
  "geometry": {"coordinates":[145.89810199999999,-41.098251],"type":"Point"}
}