{
  "type": "Feature",
  "properties": {
    "iso:country":"AU",
    "sg:address":"12 Orford Crt",
    "sg:city":"Toowoomba",
    "sg:classifiers":[
        {
            "category":"Autos & Motor Vehicles",
            "subcategory":"Automobile Sales",
            "type":"Retail Goods"
        }
    ],
    "sg:phone":"+61 7 4633 7402",
    "sg:postcode":"4350",
    "sg:province":"QLD",
    "sg:tags":[
        "equipment",
        "trailer"
    ],
    "wof:name":"Byrne Trailers QLD",
    "wof:placetype":"venue"
},
  "geometry": {"coordinates":[151.908401,-27.54077],"type":"Point"}
}