{
  "type": "Feature",
  "properties": {
    "addr:full":"15 Long St Beaconsfield WA 6162",
    "addr:housenumber":"15",
    "addr:postcode":"6162",
    "addr:street":"Long St",
    "iso:country":"AU",
    "sg:address":"15 Long St",
    "sg:city":"Beaconsfield",
    "sg:classifiers":[
        {
            "category":"Education",
            "subcategory":"Dance Studio",
            "type":"Public Place"
        }
    ],
    "sg:phone":"+61 8 9337 3452",
    "sg:postcode":"6162",
    "sg:province":"WA",
    "sg:tags":[
        "venue",
        "tuition"
    ],
    "wof:name":"Bickley Shirley School Of Dancing",
    "wof:placetype":"venue"
},
  "geometry": {"coordinates":[115.776138,-32.073845],"type":"Point"}
}