{
  "type": "Feature",
  "properties": {
    "addr:full":"1039 South Rd Melrose Park SA 5039",
    "addr:housenumber":"1039",
    "addr:postcode":"5039",
    "addr:street":"South Rd",
    "iso:country":"AU",
    "sg:address":"1039 South Rd",
    "sg:city":"Melrose Park",
    "sg:classifiers":[
        {
            "category":"Autos & Motor Vehicles",
            "subcategory":"Automobile Sales",
            "type":"Retail Goods"
        }
    ],
    "sg:phone":"+61 8 8357 4456",
    "sg:postcode":"5039",
    "sg:province":"SA",
    "sg:tags":[
        "car",
        "used"
    ],
    "wof:name":"Autobuy",
    "wof:placetype":"venue"
},
  "geometry": {"coordinates":[138.574584961,-34.986076355],"type":"Point"}
}