{
  "type": "Feature",
  "properties": {
    "addr:full":"11 River Rd Hahndorf SA 5245",
    "addr:housenumber":"11",
    "addr:postcode":"5245",
    "addr:street":"River Rd",
    "iso:country":"AU",
    "sg:address":"11 River Rd",
    "sg:city":"Hahndorf",
    "sg:classifiers":[
        {
            "category":"Personal",
            "subcategory":"Beauty Salon",
            "type":"Services"
        }
    ],
    "sg:phone":"+61 8 8388 7453",
    "sg:postcode":"5245",
    "sg:province":"SA",
    "wof:name":"Hills Skincare Retreat",
    "wof:placetype":"venue"
},
  "geometry": {"coordinates":[138.79449462900001,-35.022315979],"type":"Point"}
}