{
  "type": "Feature",
  "properties": {
    "iso:country":"AU",
    "sg:address":"U3/ 16 Millwood Ave",
    "sg:city":"Narellan",
    "sg:classifiers":[
        {
            "category":"Manufacturing",
            "subcategory":"Chemicals & Compounds",
            "type":"Manufacturing & Wholesale Goods"
        }
    ],
    "sg:phone":"+61 2 4648 1541",
    "sg:postcode":"2567",
    "sg:province":"NSW",
    "sg:tags":[
        "electroplating"
    ],
    "wof:name":"Albury Electro Platers",
    "wof:placetype":"venue"
},
  "geometry": {"coordinates":[150.72865295400001,-34.0391464233],"type":"Point"}
}