{
  "type": "Feature",
  "properties": {
    "iso:country":"AU",
    "sg:address":"Suite 4, Cnr Fitzroy & Dragon Sts",
    "sg:city":"Warwick",
    "sg:classifiers":[
        {
            "category":"Social Services",
            "type":"Services"
        }
    ],
    "sg:phone":"+61 419 762 316",
    "sg:postcode":"4370",
    "sg:province":"QLD",
    "sg:tags":[
        "kinesiology"
    ],
    "wof:name":"Warwick Kinesiology",
    "wof:placetype":"venue"
},
  "geometry": {"coordinates":[152.02833557100001,-28.2134056091],"type":"Point"}
}