{
  "type": "Feature",
  "properties": {
    "addr:full":"12 Larkin St Riverwood NSW 2210",
    "addr:housenumber":"12",
    "addr:postcode":"2210",
    "addr:street":"Larkin St",
    "iso:country":"AU",
    "sg:address":"12 Larkin St",
    "sg:city":"Riverwood",
    "sg:classifiers":[
        {
            "category":"Landmark",
            "subcategory":"Fountain",
            "type":"Public Place"
        }
    ],
    "sg:phone":"+61 2 9533 5366",
    "sg:postcode":"2210",
    "sg:province":"NSW",
    "sg:tags":[
        "wholesaler",
        "spring",
        "mfrs"
    ],
    "wof:name":"John While Springs",
    "wof:placetype":"venue"
},
  "geometry": {"coordinates":[151.061218,-33.941338],"type":"Point"}
}