{
  "type": "Feature",
  "properties": {
    "iso:country":"AU",
    "sg:address":"Main Rd",
    "sg:city":"Cooee",
    "sg:classifiers":[
        {
            "category":"Farming",
            "subcategory":"Dairy Farm",
            "type":"Manufacturing & Wholesale Goods"
        }
    ],
    "sg:phone":"+61 3 6431 2588",
    "sg:postcode":"7320",
    "sg:province":"TAS",
    "wof:name":"Cadbury Schweppes Pty Ltd",
    "wof:placetype":"venue"
},
  "geometry": {"coordinates":[145.92659,-41.06723],"type":"Point"}
}