{
  "type": "Feature",
  "properties": {
    "addr:full":"Shp8/ 25 Junction Rd Morningside QLD 4170",
    "addr:housenumber":"25",
    "addr:postcode":"4170",
    "addr:street":"Junction Rd",
    "iso:country":"AU",
    "sg:address":"Shp8/ 25 Junction Rd",
    "sg:city":"Morningside",
    "sg:classifiers":[
        {
            "category":"Real Estate",
            "subcategory":"Real Estate Agent",
            "type":"Services"
        }
    ],
    "sg:phone":"+61 7 3899 4545",
    "sg:postcode":"4170",
    "sg:province":"QLD",
    "wof:name":"Rout Brothers Real Estate",
    "wof:placetype":"venue"
},
  "geometry": {"coordinates":[153.07882690400001,-27.4668121338],"type":"Point"}
}