{
  "type": "Feature",
  "properties": {
    "addr:full":"123 Boundary Rd Rocklea QLD 4106",
    "addr:housenumber":"123",
    "addr:postcode":"4106",
    "addr:street":"Boundary Rd",
    "iso:country":"AU",
    "sg:address":"123 Boundary Rd",
    "sg:city":"Rocklea",
    "sg:classifiers":[
        {
            "category":"Building & Trades",
            "subcategory":"Landscaping Services",
            "type":"Services"
        }
    ],
    "sg:phone":"+61 7 3277 3553",
    "sg:postcode":"4106",
    "sg:province":"QLD",
    "sg:tags":[
        "gardener"
    ],
    "wof:name":"Best Mate Nursery & Landscape",
    "wof:placetype":"venue"
},
  "geometry": {"coordinates":[152.998168945,-27.5647964478],"type":"Point"}
}