{
  "type": "Feature",
  "properties": {
    "addr:full":"20B John St Cabramatta NSW 2166",
    "addr:housenumber":"20b",
    "addr:postcode":"2166",
    "addr:street":"John St",
    "iso:country":"AU",
    "sg:address":"20B John St",
    "sg:city":"Cabramatta",
    "sg:classifiers":[
        {
            "category":"Real Estate",
            "subcategory":"Real Estate Agent",
            "type":"Services"
        }
    ],
    "sg:phone":"+61 2 9754 1100",
    "sg:postcode":"2166",
    "sg:province":"NSW",
    "wof:name":"Laing + Simmons Cabramatta",
    "wof:placetype":"venue"
},
  "geometry": {"coordinates":[150.937225342,-33.895362854],"type":"Point"}
}