{
  "type": "Feature",
  "properties": {
    "addr:full":"8th Floor 114 Albert Rd South Melbourne VIC 3205",
    "addr:housenumber":"114",
    "addr:postcode":"3205",
    "addr:street":"Albert Rd",
    "iso:country":"AU",
    "sg:address":"8th Floor 114 Albert Rd",
    "sg:city":"South Melbourne",
    "sg:classifiers":[
        {
            "category":"Insurance",
            "subcategory":"Hazard Insurance",
            "type":"Services"
        }
    ],
    "sg:phone":"+61 13 29 39",
    "sg:postcode":"3205",
    "sg:province":"VIC",
    "sg:tags":[
        "fire",
        "accident",
        "marine"
    ],
    "wof:name":"Australian Unity",
    "wof:placetype":"venue"
},
  "geometry": {"coordinates":[144.96992499999999,-37.835842],"type":"Point"}
}