{
  "type": "Feature",
  "properties": {
    "addr:full":"33- 35 Takalvan St Bundaberg QLD 4670",
    "addr:housenumber":"35",
    "addr:postcode":"4670",
    "addr:street":"Takalvan St",
    "iso:country":"AU",
    "sg:address":"33- 35 Takalvan St",
    "sg:city":"Bundaberg",
    "sg:classifiers":[
        {
            "category":"Professional",
            "subcategory":"Employment Agencies",
            "type":"Services"
        }
    ],
    "sg:phone":"+61 1300 363 050",
    "sg:postcode":"4670",
    "sg:province":"QLD",
    "wof:name":"Busy At Work",
    "wof:placetype":"venue"
},
  "geometry": {"coordinates":[152.331954956,-24.8746585846],"type":"Point"}
}