{
  "type": "Feature",
  "properties": {
    "iso:country":"AU",
    "sg:address":"Rupert St",
    "sg:city":"Port Augusta",
    "sg:classifiers":[
        {
            "category":"Education",
            "subcategory":"School",
            "type":"Public Place"
        }
    ],
    "sg:phone":"+61 8 8642 2281",
    "sg:postcode":"5700",
    "sg:province":"SA",
    "sg:tags":[
        "state",
        "except",
        "nsw"
    ],
    "wof:name":"Carlton School",
    "wof:placetype":"venue"
},
  "geometry": {"coordinates":[137.77737426799999,-32.4893341064],"type":"Point"}
}