{
  "type": "Feature",
  "properties": {
    "addr:full":"22 Dudley St Eltham VIC 3095",
    "addr:housenumber":"22",
    "addr:postcode":"3095",
    "addr:street":"Dudley St",
    "iso:country":"AU",
    "sg:address":"22 Dudley St",
    "sg:city":"Eltham",
    "sg:classifiers":[
        {
            "category":"Health Services",
            "subcategory":"Doctor",
            "type":"Services"
        }
    ],
    "sg:phone":"+61 3 9439 1206",
    "sg:postcode":"3095",
    "sg:province":"VIC",
    "sg:tags":[
        "reflexology"
    ],
    "wof:name":"Leamon Deidre",
    "wof:placetype":"venue"
},
  "geometry": {"coordinates":[145.149780273,-37.7159538269],"type":"Point"}
}