{
  "type": "Feature",
  "properties": {
    "addr:full":"311/ 20 Dale St Brookvale NSW 2100",
    "addr:housenumber":"311 / 20",
    "addr:postcode":"2100",
    "addr:street":"Dale St",
    "iso:country":"AU",
    "sg:address":"311/ 20 Dale St",
    "sg:city":"Brookvale",
    "sg:classifiers":[
        {
            "category":"Shopping",
            "subcategory":"Computers & Home Electronics",
            "type":"Retail Goods"
        }
    ],
    "sg:phone":"+61 1300 734 557",
    "sg:postcode":"2100",
    "sg:province":"NSW",
    "sg:tags":[
        "hardware",
        "equipment"
    ],
    "wof:name":"Jantech Computers",
    "wof:placetype":"venue"
},
  "geometry": {"coordinates":[151.268234253,-33.7652168274],"type":"Point"}
}