{
  "type": "Feature",
  "properties": {
    "iso:country":"AU",
    "sg:address":"Un 2/ 10 Uppill Rd",
    "sg:city":"Wangara",
    "sg:classifiers":[
        {
            "category":"Autos & Motor Vehicles",
            "subcategory":"Boat Sales",
            "type":"Retail Goods"
        }
    ],
    "sg:phone":"+61 8 9408 1066",
    "sg:postcode":"6065",
    "sg:province":"WA",
    "sg:tags":[
        "builder",
        "yacht",
        "repairer"
    ],
    "wof:name":"Preston Craft",
    "wof:placetype":"venue"
},
  "geometry": {"coordinates":[115.81214904799999,-31.7852191925],"type":"Point"}
}