{
  "type": "Feature",
  "properties": {
    "iso:country":"AU",
    "sg:address":"6 Herbert St",
    "sg:city":"Goondiwindi",
    "sg:classifiers":[
        {
            "category":"Food & Beverages",
            "subcategory":"Supermarket",
            "type":"Retail Goods"
        }
    ],
    "sg:phone":"+61 7 4677 7899",
    "sg:postcode":"4390",
    "sg:province":"QLD",
    "sg:tags":[
        "grocery",
        "store"
    ],
    "wof:name":"Goondiwindi Co-Op Society Ltd",
    "wof:placetype":"venue"
},
  "geometry": {"coordinates":[150.30520629899999,-28.5458889008],"type":"Point"}
}