{
  "type": "Feature",
  "properties": {
    "iso:country":"AU",
    "sg:address":"316 Highbury Rd",
    "sg:city":"Mt Waverley",
    "sg:classifiers":[
        {
            "category":"Health Services",
            "subcategory":"Health Practitioner",
            "type":"Services"
        }
    ],
    "sg:phone":"+61 3 9884 5592",
    "sg:postcode":"3149",
    "sg:province":"VIC",
    "sg:tags":[
        "psychologist"
    ],
    "wof:name":"A. Cheryl Hopcroft",
    "wof:placetype":"venue"
},
  "geometry": {"coordinates":[145.129104614,-37.8574028015],"type":"Point"}
}