{
  "type": "Feature",
  "properties": {
    "addr:full":"60 City Rd Southbank VIC 3006",
    "addr:housenumber":"60",
    "addr:postcode":"3006",
    "addr:street":"City Rd",
    "iso:country":"AU",
    "sg:address":"60 City Rd",
    "sg:city":"Southbank",
    "sg:classifiers":[
        {
            "category":"Professional",
            "subcategory":"Business Services",
            "type":"Services"
        }
    ],
    "sg:phone":"+61 1300 366 850",
    "sg:postcode":"3006",
    "sg:province":"VIC",
    "sg:tags":[
        "management",
        "event"
    ],
    "wof:name":"The Events Company",
    "wof:placetype":"venue"
},
  "geometry": {"coordinates":[144.965896606,-37.8216629028],"type":"Point"}
}