{
  "type": "Feature",
  "properties": {
    "addr:full":"83 Trail St Wagga Wagga NSW 2650",
    "addr:housenumber":"83",
    "addr:postcode":"2650",
    "addr:street":"Trail St",
    "iso:country":"AU",
    "sg:address":"83 Trail St",
    "sg:city":"Wagga Wagga",
    "sg:classifiers":[
        {
            "category":"Insurance",
            "subcategory":"Insurance Agent",
            "type":"Services"
        }
    ],
    "sg:phone":"+61 1800 806 130",
    "sg:postcode":"2650",
    "sg:province":"NSW",
    "sg:tags":[
        "wool",
        "broker"
    ],
    "wof:name":"Dalgety Meatbid",
    "wof:placetype":"venue"
},
  "geometry": {"coordinates":[147.36579895,-35.1030044556],"type":"Point"}
}