{
  "type": "Feature",
  "properties": {
    "iso:country":"AU",
    "sg:address":"PO Box 878",
    "sg:city":"Berri",
    "sg:classifiers":[
        {
            "category":"Banks & Credit Unions",
            "subcategory":"Investment Brokerage",
            "type":"Services"
        }
    ],
    "sg:phone":"+61 407 974 100",
    "sg:postcode":"5343",
    "sg:province":"SA",
    "sg:tags":[
        "broker"
    ],
    "wof:name":"TH Rooney Water Brokerage",
    "wof:placetype":"venue"
},
  "geometry": {"coordinates":[140.598846436,-34.2817192078],"type":"Point"}
}