{
  "type": "Feature",
  "properties": {
    "addr:full":"9 Loton Ave Midland WA 6056",
    "addr:housenumber":"9",
    "addr:postcode":"6056",
    "addr:street":"Loton Ave",
    "iso:country":"AU",
    "sg:address":"9 Loton Ave",
    "sg:city":"Midland",
    "sg:classifiers":[
        {
            "category":"Education",
            "subcategory":"Special Training",
            "type":"Public Place"
        }
    ],
    "sg:phone":"+61 1300 791 064",
    "sg:postcode":"6056",
    "sg:province":"WA",
    "sg:tags":[
        "development"
    ],
    "sg:website":"http://www.tradeskillstraining.com.au",
    "wof:name":"Trade Skills Training",
    "wof:placetype":"venue"
},
  "geometry": {"coordinates":[116.014801025,-31.8935527802],"type":"Point"}
}