{
  "type": "Feature",
  "properties": {
    "addr:full":"324 Stephensons Rd Mt Waverley VIC 3149",
    "addr:housenumber":"324",
    "addr:postcode":"3149",
    "addr:street":"Stephensons Rd",
    "iso:country":"AU",
    "sg:address":"324 Stephensons Rd",
    "sg:city":"Mt Waverley",
    "sg:classifiers":[
        {
            "category":"Health Services",
            "subcategory":"Doctor",
            "type":"Services"
        }
    ],
    "sg:phone":"+61 3 9888 1345",
    "sg:postcode":"3149",
    "sg:province":"VIC",
    "sg:tags":[
        "medical",
        "practitioner"
    ],
    "wof:name":"Little Colin H Dr.",
    "wof:placetype":"venue"
},
  "geometry": {"coordinates":[145.12855529800001,-37.8792533875],"type":"Point"}
}