{
  "type": "Feature",
  "properties": {
    "addr:full":"Lot 2 Sandham Rd Bell NSW 2786",
    "addr:postcode":"2786",
    "addr:street":"Sandham Rd",
    "iso:country":"AU",
    "sg:address":"Lot 2 Sandham Rd",
    "sg:city":"Bell",
    "sg:classifiers":[
        {
            "category":"Government",
            "subcategory":"Fire Station",
            "type":"Public Place"
        }
    ],
    "sg:phone":"+61 2 6355 2790",
    "sg:postcode":"2786",
    "sg:province":"NSW",
    "sg:tags":[
        "brigade"
    ],
    "wof:name":"Bell Volunteer Bush Fire Brigades",
    "wof:placetype":"venue"
},
  "geometry": {"coordinates":[150.28240966800001,-33.5110778809],"type":"Point"}
}