{
  "type": "Feature",
  "properties": {
    "iso:country":"AU",
    "sg:address":"17 Fursden St",
    "sg:city":"Mackay",
    "sg:classifiers":[
        {
            "category":"Professional",
            "subcategory":"Testing Lab",
            "type":"Services"
        }
    ],
    "sg:phone":"+61 7 4942 5600",
    "sg:postcode":"4740",
    "sg:province":"QLD",
    "sg:tags":[
        "inspection"
    ],
    "wof:name":"M-Test (Mackay) Pty Ltd",
    "wof:placetype":"venue"
},
  "geometry": {"coordinates":[149.15069600000001,-21.129061],"type":"Point"}
}