{
  "type": "Feature",
  "properties": {
    "iso:country":"AU",
    "sg:address":"Lot 9 Hawkins Pl",
    "sg:city":"Emerald",
    "sg:classifiers":[
        {
            "category":"Building & Trades",
            "subcategory":"Electrical",
            "type":"Services"
        }
    ],
    "sg:phone":"+61 7 4982 4144",
    "sg:postcode":"4720",
    "sg:province":"QLD",
    "sg:tags":[
        "wholesaler",
        "mfrs",
        "appliance"
    ],
    "wof:name":"Lawrence & Hanson",
    "wof:placetype":"venue"
},
  "geometry": {"coordinates":[148.155365,-23.503399],"type":"Point"}
}