{
  "type": "Feature",
  "properties": {
    "addr:full":"8 Dallas Crt Hallam VIC 3803",
    "addr:housenumber":"8",
    "addr:postcode":"3803",
    "addr:street":"Dallas Crt",
    "iso:country":"AU",
    "sg:address":"8 Dallas Crt",
    "sg:city":"Hallam",
    "sg:classifiers":[
        {
            "category":"Building & Trades",
            "subcategory":"Construction",
            "type":"Services"
        }
    ],
    "sg:phone":"+61 3 8786 3222",
    "sg:postcode":"3803",
    "sg:province":"VIC",
    "sg:tags":[
        "earth",
        "excavating",
        "moving",
        "contractor"
    ],
    "wof:name":"Independent Plant Hire",
    "wof:placetype":"venue"
},
  "geometry": {"coordinates":[145.27401733400001,-38.0117301941],"type":"Point"}
}