{
  "type": "Feature",
  "properties": {
    "iso:country":"AU",
    "sg:address":"Gun Club Rd",
    "sg:city":"Milang",
    "sg:classifiers":[
        {
            "category":"Farming",
            "subcategory":"Farm",
            "type":"Manufacturing & Wholesale Goods"
        }
    ],
    "sg:phone":"+61 8 8537 0017",
    "sg:postcode":"5256",
    "sg:province":"SA",
    "sg:tags":[
        "farmer"
    ],
    "wof:name":"McInnes A F & M H",
    "wof:placetype":"venue"
},
  "geometry": {"coordinates":[138.968307495,-35.3984680176],"type":"Point"}
}