{
  "type": "Feature",
  "properties": {
    "addr:full":"Shp 11, Watergardens Shopng Cntr Taylors Lakes VIC 3038",
    "addr:housenumber":"11",
    "addr:postcode":"3038",
    "addr:street":"Watergardens Shopng Cntr",
    "iso:country":"AU",
    "sg:address":"Shp 11, Watergardens Shopng Cntr",
    "sg:city":"Taylors Lakes",
    "sg:classifiers":[
        {
            "category":"Shopping",
            "subcategory":"Mobile Phones",
            "type":"Retail Goods"
        }
    ],
    "sg:phone":"+61 3 9449 0335",
    "sg:postcode":"3038",
    "sg:province":"VIC",
    "sg:tags":[
        "telephone",
        "accessory"
    ],
    "wof:name":"Vodafone",
    "wof:placetype":"venue"
},
  "geometry": {"coordinates":[144.78132600000001,-37.696911],"type":"Point"}
}