{
  "type": "Feature",
  "properties": {
    "iso:country":"AU",
    "sg:address":"Shop 2 Smith Rd Shopng Vlge 153 Smith Rd",
    "sg:city":"Woodridge",
    "sg:classifiers":[
        {
            "category":"Health Services",
            "subcategory":"Doctor",
            "type":"Services"
        }
    ],
    "sg:phone":"+61 7 3808 7388",
    "sg:postcode":"4114",
    "sg:province":"QLD",
    "sg:tags":[
        "medical",
        "practitioner"
    ],
    "wof:name":"Smith D P",
    "wof:placetype":"venue"
},
  "geometry": {"coordinates":[153.10234069800001,-27.6278247833],"type":"Point"}
}