{
  "type": "Feature",
  "properties": {
    "iso:country":"AU",
    "sg:address":"5 Robin Ave",
    "sg:city":"Sorrento",
    "sg:classifiers":[
        {
            "category":"Banks & Credit Unions",
            "subcategory":"Financial Services",
            "type":"Services"
        }
    ],
    "sg:phone":"+61 8 9246 1666",
    "sg:postcode":"6020",
    "sg:province":"WA",
    "sg:tags":[
        "planning"
    ],
    "wof:name":"Stedman Holdings Pty Ltd",
    "wof:placetype":"venue"
},
  "geometry": {"coordinates":[115.748847961,-31.8333854675],"type":"Point"}
}