{
  "type": "Feature",
  "properties": {
    "iso:country":"AU",
    "sg:address":"3 Camberwarra Ave",
    "sg:city":"Clifton Springs",
    "sg:classifiers":[
        {
            "category":"Recreation",
            "subcategory":"Boat Charter",
            "type":"Entertainment"
        }
    ],
    "sg:phone":"+61 3 5253 1431",
    "sg:postcode":"3222",
    "sg:province":"VIC",
    "wof:name":"Bellarine Fishing Charters",
    "wof:placetype":"venue"
},
  "geometry": {"coordinates":[144.57620199999999,-38.146366],"type":"Point"}
}