{
  "type": "Feature",
  "properties": {
    "addr:full":"5/ 1050 Manly Rd Tingalpa QLD 4173",
    "addr:housenumber":"/ 1050",
    "addr:postcode":"4173",
    "addr:street":"Manly Rd",
    "iso:country":"AU",
    "sg:address":"5/ 1050 Manly Rd",
    "sg:city":"Tingalpa",
    "sg:classifiers":[
        {
            "category":"Health Services",
            "subcategory":"Health Practitioner",
            "type":"Services"
        }
    ],
    "sg:phone":"+61 7 3390 7002",
    "sg:postcode":"4173",
    "sg:province":"QLD",
    "sg:tags":[
        "psychologist"
    ],
    "wof:name":"Douglas Family Therapy",
    "wof:placetype":"venue"
},
  "geometry": {"coordinates":[153.12840270999999,-27.4748973846],"type":"Point"}
}