{
  "type": "Feature",
  "properties": {
    "iso:country":"AU",
    "sg:address":"70 Hopetoun Rd",
    "sg:city":"Rutherglen",
    "sg:classifiers":[
        {
            "category":"Farming",
            "subcategory":"Farm & Veterinary Services",
            "type":"Manufacturing & Wholesale Goods"
        }
    ],
    "sg:phone":"+61 2 6032 7788",
    "sg:postcode":"3685",
    "sg:province":"VIC",
    "sg:tags":[
        "agricultural",
        "advisory"
    ],
    "wof:name":"Steed G R & Associates",
    "wof:placetype":"venue"
},
  "geometry": {"coordinates":[146.46400451700001,-36.0450744629],"type":"Point"}
}