{
  "type": "Feature",
  "properties": {
    "addr:full":"Shop 2/ 72 May Rd Narraweena NSW 2099",
    "addr:housenumber":"shop 2 / 72",
    "addr:postcode":"2099",
    "addr:street":"May Rd",
    "iso:country":"AU",
    "sg:address":"Shop 2/ 72 May Rd",
    "sg:city":"Narraweena",
    "sg:classifiers":[
        {
            "category":"Manufacturing",
            "subcategory":"Chemicals & Compounds",
            "type":"Manufacturing & Wholesale Goods"
        }
    ],
    "sg:phone":"+61 2 9981 3899",
    "sg:postcode":"2099",
    "sg:province":"NSW",
    "sg:tags":[
        "industrial"
    ],
    "wof:name":"Kinyun Australia Pty Ltd",
    "wof:placetype":"venue"
},
  "geometry": {"coordinates":[151.27557373100001,-33.7554893494],"type":"Point"}
}