{
  "type": "Feature",
  "properties": {
    "iso:country":"AU",
    "sg:address":"4 Bristol Ave",
    "sg:city":"Enfield",
    "sg:classifiers":[
        {
            "category":"Organizations",
            "subcategory":"Non-profit Organization",
            "type":"Services"
        }
    ],
    "sg:phone":"+61 8 8262 6464",
    "sg:postcode":"5085",
    "sg:province":"SA",
    "sg:tags":[
        "support",
        "disability",
        "organisation"
    ],
    "wof:name":"&#034;Ain Karim&#034;",
    "wof:placetype":"venue"
},
  "geometry": {"coordinates":[138.60226440400001,-34.863483429],"type":"Point"}
}