{
  "type": "Feature",
  "properties": {
    "addr:full":"2/ 243 Princes Hwy Albion Park Rail NSW 2527",
    "addr:housenumber":"/ 243",
    "addr:postcode":"2527",
    "addr:street":"Princes Hwy Albion",
    "iso:country":"AU",
    "sg:address":"2/ 243 Princes Hwy",
    "sg:city":"Albion Park Rail",
    "sg:classifiers":[
        {
            "category":"Communications",
            "subcategory":"Film & Video Production",
            "type":"Services"
        }
    ],
    "sg:phone":"+61 2 4257 7511",
    "sg:postcode":"2527",
    "sg:province":"NSW",
    "sg:tags":[
        "dvd",
        "library"
    ],
    "wof:name":"Network Video & DVD Illawarra",
    "wof:placetype":"venue"
},
  "geometry": {"coordinates":[150.801239014,-34.5664520264],"type":"Point"}
}