{
  "type": "Feature",
  "properties": {
    "iso:country":"AU",
    "sg:address":"PO Box 3190",
    "sg:city":"Sunnybank South",
    "sg:classifiers":[
        {
            "category":"Utilities",
            "subcategory":"Natural Gas",
            "type":"Services"
        }
    ],
    "sg:phone":"+61 7 3841 3030",
    "sg:postcode":"4109",
    "sg:province":"QLD",
    "sg:tags":[
        "supplier"
    ],
    "wof:name":"Qld Gas Pty Ltd",
    "wof:placetype":"venue"
},
  "geometry": {"coordinates":[153.06077575699999,-27.5878391266],"type":"Point"}
}