{
  "type": "Feature",
  "properties": {
    "addr:full":"PO Box 2997 Mildura VIC 3502",
    "addr:postcode":"3502",
    "iso:country":"AU",
    "sg:address":"PO Box 2997",
    "sg:city":"Mildura",
    "sg:classifiers":[
        {
            "category":"Building & Trades",
            "subcategory":"Construction",
            "type":"Services"
        }
    ],
    "sg:phone":"+61 3 5023 6218",
    "sg:postcode":"3502",
    "sg:province":"VIC",
    "sg:tags":[
        "earth",
        "excavating",
        "moving",
        "contractor"
    ],
    "wof:name":"G M Richardson Pty Ltd",
    "wof:placetype":"venue"
},
  "geometry": {"coordinates":[142.165557861,-34.184551239],"type":"Point"}
}