{
  "type": "Feature",
  "properties": {
    "iso:country":"AU",
    "sg:address":"112 Lee St",
    "sg:city":"Kelso",
    "sg:classifiers":[
        {
            "category":"Home & Garden",
            "subcategory":"Building Materials",
            "type":"Retail Goods"
        }
    ],
    "sg:phone":"+61 2 6331 0700",
    "sg:postcode":"2795",
    "sg:province":"NSW",
    "sg:tags":[
        "balustrading"
    ],
    "wof:name":"Calgaroo Stainless",
    "wof:placetype":"venue"
},
  "geometry": {"coordinates":[149.61227417000001,-33.4265632629],"type":"Point"}
}