{
  "type": "Feature",
  "properties": {
    "addr:full":"731 Eureka St Ballarat VIC 3350",
    "addr:housenumber":"731",
    "addr:postcode":"3350",
    "addr:street":"Eureka St",
    "iso:country":"AU",
    "sg:address":"731 Eureka St",
    "sg:city":"Ballarat",
    "sg:classifiers":[
        {
            "category":"Health Services",
            "subcategory":"Health Practitioner",
            "type":"Services"
        }
    ],
    "sg:phone":"+61 3 5332 2024",
    "sg:postcode":"3350",
    "sg:province":"VIC",
    "sg:tags":[
        "bowen",
        "therapy"
    ],
    "wof:name":"Peter Kelly",
    "wof:placetype":"venue"
},
  "geometry": {"coordinates":[143.88987700000001,-37.565739],"type":"Point"}
}