{
  "type": "Feature",
  "properties": {
    "addr:full":"Suite 1-3 / 117 Cape St Heidelberg VIC 3084",
    "addr:housenumber":"1-3 / 117",
    "addr:postcode":"3084",
    "addr:street":"Cape St",
    "iso:country":"AU",
    "sg:address":"Suite 1-3 / 117 Cape St",
    "sg:city":"Heidelberg",
    "sg:classifiers":[
        {
            "category":"Personal",
            "type":"Services"
        }
    ],
    "sg:phone":"+61 3 9455 0845",
    "sg:postcode":"3084",
    "sg:province":"VIC",
    "sg:tags":[
        "counselling",
        "alcohol",
        "drug"
    ],
    "wof:name":"Health Issues",
    "wof:placetype":"venue"
},
  "geometry": {"coordinates":[145.06721496599999,-37.7548866272],"type":"Point"}
}