{
  "type": "Feature",
  "properties": {
    "addr:full":"20 Morris St Parkdale VIC 3195",
    "addr:housenumber":"20",
    "addr:postcode":"3195",
    "addr:street":"Morris St",
    "iso:country":"AU",
    "sg:address":"20 Morris St",
    "sg:city":"Parkdale",
    "sg:classifiers":[
        {
            "category":"Home & Garden",
            "subcategory":"Carpets & Floor Coverings",
            "type":"Retail Goods"
        }
    ],
    "sg:phone":"+61 417 771 931",
    "sg:postcode":"3195",
    "sg:province":"VIC",
    "wof:name":"Boland Floors Pty Ltd",
    "wof:placetype":"venue"
},
  "geometry": {"coordinates":[145.09085082999999,-37.9937095642],"type":"Point"}
}