{
  "type": "Feature",
  "properties": {
    "iso:country":"AU",
    "sg:address":"Shop LG1, 580 George St Pavillion Plaza",
    "sg:city":"Sydney",
    "sg:classifiers":[
        {
            "category":"Cafe",
            "type":"Food & Drink"
        }
    ],
    "sg:phone":"+61 2 9212 4154",
    "sg:postcode":"2000",
    "sg:province":"NSW",
    "wof:name":"Passionflower",
    "wof:placetype":"venue"
},
  "geometry": {"coordinates":[151.20680236800001,-33.8751754761],"type":"Point"}
}