{
  "type": "Feature",
  "properties": {
    "iso:country":"AU",
    "sg:address":"304- 306 Police Rd",
    "sg:city":"Noble Park North",
    "sg:classifiers":[
        {
            "category":"Health Services",
            "subcategory":"Doctor",
            "type":"Services"
        }
    ],
    "sg:phone":"+61 3 9795 0468",
    "sg:postcode":"3174",
    "sg:province":"VIC",
    "sg:tags":[
        "medical",
        "practitioner"
    ],
    "wof:name":"Leung Avi Dr",
    "wof:placetype":"venue"
},
  "geometry": {"coordinates":[145.18650817899999,-37.9369087219],"type":"Point"}
}