{
  "type": "Feature",
  "properties": {
    "addr:full":"13 Connell Rd Oakleigh VIC 3166",
    "addr:housenumber":"13",
    "addr:postcode":"3166",
    "addr:street":"Connell Rd",
    "iso:country":"AU",
    "sg:address":"13 Connell Rd",
    "sg:city":"Oakleigh",
    "sg:classifiers":[
        {
            "category":"Health Services",
            "subcategory":"Health Practitioner",
            "type":"Services"
        }
    ],
    "sg:phone":"+61 3 9568 1949",
    "sg:postcode":"3166",
    "sg:province":"VIC",
    "sg:tags":[
        "psychologist"
    ],
    "wof:name":"Coram M.D.",
    "wof:placetype":"venue"
},
  "geometry": {"coordinates":[145.09829711899999,-37.9013938904],"type":"Point"}
}