{
  "type": "Feature",
  "properties": {
    "iso:country":"AU",
    "sg:address":"3 Keane Pl",
    "sg:city":"Wagga Wagga",
    "sg:classifiers":[
        {
            "category":"Real Estate",
            "subcategory":"Architect",
            "type":"Services"
        }
    ],
    "sg:phone":"+61 2 6922 6825",
    "sg:postcode":"2650",
    "sg:province":"NSW",
    "sg:tags":[
        "building",
        "designer"
    ],
    "wof:name":"Drawing Board Drafting Service Pty. Ltd.",
    "wof:placetype":"venue"
},
  "geometry": {"coordinates":[147.38630676299999,-35.1379127502],"type":"Point"}
}