{
  "type": "Feature",
  "properties": {
    "iso:country":"AU",
    "sg:address":"4 Ryan St",
    "sg:city":"Moonta",
    "sg:classifiers":[
        {
            "category":"Retail",
            "subcategory":"Auto Repair",
            "type":"Services"
        }
    ],
    "sg:phone":"+61 8 8825 2052",
    "sg:postcode":"5558",
    "sg:province":"SA",
    "sg:tags":[
        "repairer",
        "motor",
        "engineer"
    ],
    "wof:name":"Warren R G & Son",
    "wof:placetype":"venue"
},
  "geometry": {"coordinates":[137.59237670900001,-34.0673065186],"type":"Point"}
}