{
  "type": "Feature",
  "properties": {
    "addr:full":"1/569 Stirling Hwy Cottesloe WA 6011",
    "addr:housenumber":"/ 569",
    "addr:postcode":"6011",
    "addr:street":"Stirling Hwy",
    "iso:country":"AU",
    "sg:address":"1/569 Stirling Hwy",
    "sg:city":"Cottesloe",
    "sg:classifiers":[
        {
            "category":"Banks & Credit Unions",
            "subcategory":"Investment Brokerage",
            "type":"Services"
        }
    ],
    "sg:phone":"+61 8 9385 3377",
    "sg:postcode":"6011",
    "sg:province":"WA",
    "sg:tags":[
        "management",
        "property"
    ],
    "wof:name":"Peard West Coast",
    "wof:placetype":"venue"
},
  "geometry": {"coordinates":[115.762168884,-31.9986248016],"type":"Point"}
}