{
  "type": "Feature",
  "properties": {
    "addr:full":"Shp1&2/ 305 Thomas St Dandenong VIC 3175",
    "addr:housenumber":"305",
    "addr:postcode":"3175",
    "addr:street":"Thomas St",
    "iso:country":"AU",
    "sg:address":"Shp1&2/ 305 Thomas St",
    "sg:city":"Dandenong",
    "sg:classifiers":[
        {
            "category":"Restaurant",
            "type":"Food & Drink"
        }
    ],
    "sg:phone":"+61 3 9791 9568",
    "sg:postcode":"3175",
    "sg:province":"VIC",
    "wof:name":"Alexandar Restaurant",
    "wof:placetype":"venue"
},
  "geometry": {"coordinates":[145.212280273,-37.9855041504],"type":"Point"}
}