{
  "type": "Feature",
  "properties": {
    "iso:country":"AU",
    "sg:address":"3 Bruce St",
    "sg:city":"Kensington",
    "sg:classifiers":[
        {
            "category":"Professional",
            "subcategory":"Engineering",
            "type":"Services"
        }
    ],
    "sg:phone":"+61 3 9376 0921",
    "sg:postcode":"3031",
    "sg:province":"VIC",
    "sg:tags":[
        "engineer"
    ],
    "wof:name":"ESO Australia Pty Ltd",
    "wof:placetype":"venue"
},
  "geometry": {"coordinates":[144.933548,-37.798107],"type":"Point"}
}