{
  "type": "Feature",
  "properties": {
    "addr:full":"782 Burke Rd Camberwell VIC 3124",
    "addr:housenumber":"782",
    "addr:postcode":"3124",
    "addr:street":"Burke Rd",
    "iso:country":"AU",
    "sg:address":"782 Burke Rd",
    "sg:city":"Camberwell",
    "sg:classifiers":[
        {
            "category":"Shopping",
            "subcategory":"Stationery & Office Supplies",
            "type":"Retail Goods"
        }
    ],
    "sg:phone":"+61 3 9813 1121",
    "sg:postcode":"3124",
    "sg:province":"VIC",
    "sg:tags":[
        "equipment",
        "facsimile"
    ],
    "wof:name":"Business Works",
    "wof:placetype":"venue"
},
  "geometry": {"coordinates":[145.05821227999999,-37.8243484497],"type":"Point"}
}