{
  "type": "Feature",
  "properties": {
    "iso:country":"AU",
    "sg:address":"49 Graham St",
    "sg:city":"Glendale",
    "sg:classifiers":[
        {
            "category":"Utilities",
            "subcategory":"Electric",
            "type":"Services"
        }
    ],
    "sg:phone":"+61 2 4954 9004",
    "sg:postcode":"2285",
    "sg:province":"NSW",
    "sg:tags":[
        "electrical",
        "contractor"
    ],
    "wof:name":"Laroc & Associates",
    "wof:placetype":"venue"
},
  "geometry": {"coordinates":[151.65826415999999,-32.9299049377],"type":"Point"}
}