{
  "type": "Feature",
  "properties": {
    "addr:full":"Fact 3, 356 Lr Dandenong Rd Braeside VIC 3195",
    "addr:housenumber":"3",
    "addr:postcode":"356;3195",
    "addr:street":"Fact;Dandenong Rd",
    "iso:country":"AU",
    "sg:address":"Fact 3, 356 Lr Dandenong Rd",
    "sg:city":"Braeside",
    "sg:classifiers":[
        {
            "category":"Building & Trades",
            "subcategory":"Locksmith",
            "type":"Services"
        }
    ],
    "sg:phone":"+61 1300 365 651",
    "sg:postcode":"3195",
    "sg:province":"VIC",
    "sg:tags":[
        "lock"
    ],
    "sg:website":"http://www.nepeanlocksmiths.com.au",
    "wof:name":"Nepean Security Solutions Pty Ltd",
    "wof:placetype":"venue"
},
  "geometry": {"coordinates":[145.10968017600001,-37.986831665],"type":"Point"}
}