{
  "type": "Feature",
  "properties": {
    "addr:full":"190 River St Ballina NSW 2478",
    "addr:housenumber":"190",
    "addr:postcode":"2478",
    "addr:street":"River St",
    "iso:country":"AU",
    "sg:address":"190 River St",
    "sg:city":"Ballina",
    "sg:classifiers":[
        {
            "category":"Personal",
            "subcategory":"Beauty Salon",
            "type":"Services"
        }
    ],
    "sg:phone":"+61 2 6686 9288",
    "sg:postcode":"2478",
    "sg:province":"NSW",
    "sg:tags":[
        "supply",
        "artist",
        "make-up"
    ],
    "wof:name":"Chelles Indulgence",
    "wof:placetype":"venue"
},
  "geometry": {"coordinates":[153.55856323200001,-28.8698387146],"type":"Point"}
}