{
  "type": "Feature",
  "properties": {
    "addr:full":"U38/ 8 Herbert St St Leonards NSW 2065",
    "addr:housenumber":"8",
    "addr:postcode":"2065",
    "addr:street":"/;Herbert St",
    "iso:country":"AU",
    "sg:address":"U38/ 8 Herbert St",
    "sg:city":"St Leonards",
    "sg:classifiers":[
        {
            "category":"Professional",
            "subcategory":"Engineering",
            "type":"Services"
        }
    ],
    "sg:phone":"+61 2 9906 3688",
    "sg:postcode":"2065",
    "sg:province":"NSW",
    "sg:tags":[
        "engineer",
        "mechanical"
    ],
    "wof:name":"GWA Consultants Australia Pty Ltd.",
    "wof:placetype":"venue"
},
  "geometry": {"coordinates":[151.199127197,-33.8257369995],"type":"Point"}
}