{
  "type": "Feature",
  "properties": {
    "addr:full":"33b Otho St Inverell NSW 2360",
    "addr:housenumber":"33b",
    "addr:postcode":"2360",
    "addr:street":"Otho St",
    "iso:country":"AU",
    "sg:address":"33b Otho St",
    "sg:city":"Inverell",
    "sg:classifiers":[
        {
            "category":"Personal",
            "subcategory":"Beauty Salon",
            "type":"Services"
        }
    ],
    "sg:phone":"+61 2 6722 2219",
    "sg:postcode":"2360",
    "sg:province":"NSW",
    "sg:tags":[
        "hairdresser"
    ],
    "wof:name":"Nova Hair Fashions",
    "wof:placetype":"venue"
},
  "geometry": {"coordinates":[151.11541748100001,-29.7774887085],"type":"Point"}
}