{
  "type": "Feature",
  "properties": {
    "iso:country":"AU",
    "sg:address":"PO Box 204",
    "sg:city":"Clayfield",
    "sg:classifiers":[
        {
            "category":"Sports & Exercise",
            "subcategory":"Sports Center",
            "type":"Entertainment"
        }
    ],
    "sg:phone":"+61 413 158 999",
    "sg:postcode":"4011",
    "sg:province":"QLD",
    "sg:tags":[
        "coach",
        "tennis"
    ],
    "wof:name":"LifeTime Tennis",
    "wof:placetype":"venue"
},
  "geometry": {"coordinates":[153.05899,-27.41213],"type":"Point"}
}