{
  "type": "Feature",
  "properties": {
    "addr:full":"9A - 9D Anderson St Pascoe Vale South VIC 3044",
    "addr:housenumber":"9d",
    "addr:postcode":"3044",
    "addr:street":"Anderson St",
    "iso:country":"AU",
    "sg:address":"9A - 9D Anderson St",
    "sg:city":"Pascoe Vale South",
    "sg:classifiers":[
        {
            "category":"Education",
            "subcategory":"Dance Studio",
            "type":"Public Place"
        }
    ],
    "sg:phone":"+61 3 9354 3781",
    "sg:postcode":"3044",
    "sg:province":"VIC",
    "sg:tags":[
        "venue",
        "tuition"
    ],
    "wof:name":"Shirlene School Of Classical Ballet",
    "wof:placetype":"venue"
},
  "geometry": {"coordinates":[144.93458557100001,-37.7368850708],"type":"Point"}
}