{
  "type": "Feature",
  "properties": {
    "iso:country":"AU",
    "sg:address":"Sunraysia Hwy",
    "sg:city":"Donald",
    "sg:classifiers":[
        {
            "category":"Manufacturing",
            "subcategory":"Glass & Minerals",
            "type":"Manufacturing & Wholesale Goods"
        }
    ],
    "sg:phone":"+61 3 5497 1166",
    "sg:postcode":"3480",
    "sg:province":"VIC",
    "sg:tags":[
        "fabricator",
        "fibreglass"
    ],
    "wof:name":"Maydek Donald Fibreglass Industry Pty Ltd",
    "wof:placetype":"venue"
},
  "geometry": {"coordinates":[142.97764587399999,-36.3670768738],"type":"Point"}
}