{
  "type": "Feature",
  "properties": {
    "addr:full":"L1, 132 Victoria St Richmond VIC 3121",
    "addr:housenumber":"132",
    "addr:postcode":"3121",
    "addr:street":"Victoria St",
    "iso:country":"AU",
    "sg:address":"L1, 132 Victoria St",
    "sg:city":"Richmond",
    "sg:classifiers":[
        {
            "category":"Professional",
            "subcategory":"Accounting & Tax Preparation",
            "type":"Services"
        }
    ],
    "sg:phone":"+61 3 9429 8835",
    "sg:postcode":"3121",
    "sg:province":"VIC",
    "sg:tags":[
        "accountant",
        "auditor"
    ],
    "wof:name":"Yew & Co Pty Ltd",
    "wof:placetype":"venue"
},
  "geometry": {"coordinates":[144.99578857399999,-37.8101806641],"type":"Point"}
}