{
  "type": "Feature",
  "properties": {
    "iso:country":"AU",
    "sg:address":"612 Beaufort St",
    "sg:city":"Mt Lawley",
    "sg:classifiers":[
        {
            "category":"Real Estate",
            "subcategory":"Real Estate Agent",
            "type":"Services"
        }
    ],
    "sg:phone":"+61 8 9228 1777",
    "sg:postcode":"6050",
    "sg:province":"WA",
    "wof:name":"Lyndon Rodgers & Associates",
    "wof:placetype":"venue"
},
  "geometry": {"coordinates":[115.871559143,-31.9356327057],"type":"Point"}
}