{
  "type": "Feature",
  "properties": {
    "iso:country":"AU",
    "sg:address":"3 Cleveland-Redland Bay Rd",
    "sg:city":"Thornlands",
    "sg:classifiers":[
        {
            "category":"Health Services",
            "subcategory":"Doctor",
            "type":"Services"
        }
    ],
    "sg:phone":"+61 7 3286 4666",
    "sg:postcode":"4164",
    "sg:province":"QLD",
    "sg:tags":[
        "medical",
        "practitioner"
    ],
    "wof:name":"Peng, Rebecca",
    "wof:placetype":"venue"
},
  "geometry": {"coordinates":[153.26661682100001,-27.5572032928],"type":"Point"}
}