{
  "type": "Feature",
  "properties": {
    "addr:full":"Unit 2/ 4 Kingston Ave Richmond SA 5033",
    "addr:postcode":"5033",
    "addr:street":"Kingston Ave",
    "iso:country":"AU",
    "sg:address":"Unit 2/ 4 Kingston Ave",
    "sg:city":"Richmond",
    "sg:classifiers":[
        {
            "category":"Retail",
            "subcategory":"Repair Shop",
            "type":"Services"
        }
    ],
    "sg:phone":"+61 8 8234 5211",
    "sg:postcode":"5033",
    "sg:province":"SA",
    "sg:tags":[
        "upholsterer"
    ],
    "wof:name":"Abbey Upholstery",
    "wof:placetype":"venue"
},
  "geometry": {"coordinates":[138.568756103,-34.9394378662],"type":"Point"}
}