{
  "type": "Feature",
  "properties": {
    "addr:full":"6 Richards Ave Surry Hills NSW 2010",
    "addr:housenumber":"6",
    "addr:postcode":"2010",
    "addr:street":"Richards Ave",
    "iso:country":"AU",
    "sg:address":"6 Richards Ave",
    "sg:city":"Surry Hills",
    "sg:classifiers":[
        {
            "category":"Professional",
            "subcategory":"Computer Services",
            "type":"Services"
        }
    ],
    "sg:phone":"+61 2 9331 2417",
    "sg:postcode":"2010",
    "sg:province":"NSW",
    "sg:tags":[
        "consultant",
        "system"
    ],
    "wof:name":"Keycom",
    "wof:placetype":"venue"
},
  "geometry": {"coordinates":[151.214920044,-33.8856239319],"type":"Point"}
}