{
  "type": "Feature",
  "properties": {
    "iso:country":"AU",
    "sg:address":"7/ 70 Princes Hwy",
    "sg:city":"Beaconsfield",
    "sg:classifiers":[
        {
            "category":"Health Services",
            "subcategory":"Doctor",
            "type":"Services"
        }
    ],
    "sg:phone":"+61 3 9707 4922",
    "sg:postcode":"3807",
    "sg:province":"VIC",
    "sg:tags":[
        "podiatrist"
    ],
    "wof:name":"Hainsworth Steven",
    "wof:placetype":"venue"
},
  "geometry": {"coordinates":[145.36958313,-38.0477333069],"type":"Point"}
}