{
  "type": "Feature",
  "properties": {
    "addr:full":"118 Bower St Manly NSW 2095",
    "addr:housenumber":"118",
    "addr:postcode":"2095",
    "addr:street":"Bower St",
    "iso:country":"AU",
    "sg:address":"118 Bower St",
    "sg:city":"Manly",
    "sg:classifiers":[
        {
            "category":"Real Estate",
            "subcategory":"Real Estate Services",
            "type":"Services"
        }
    ],
    "sg:phone":"+61 2 9976 2682",
    "sg:postcode":"2095",
    "sg:province":"NSW",
    "sg:tags":[
        "consultant",
        "property"
    ],
    "wof:name":"Rowe John",
    "wof:placetype":"venue"
},
  "geometry": {"coordinates":[151.29197692899999,-33.8001327515],"type":"Point"}
}