{
  "type": "Feature",
  "properties": {
    "addr:full":"Level 12, 1 Pacific Hwy North Sydney NSW 2060",
    "addr:housenumber":"1",
    "addr:postcode":"2060",
    "addr:street":"Pacific Hwy",
    "iso:country":"AU",
    "sg:address":"Level 12, 1 Pacific Hwy",
    "sg:city":"North Sydney",
    "sg:classifiers":[
        {
            "category":"Professional",
            "subcategory":"Computer Services",
            "type":"Services"
        }
    ],
    "sg:phone":"+61 2 9959 1018",
    "sg:postcode":"2060",
    "sg:province":"NSW",
    "sg:tags":[
        "package",
        "software"
    ],
    "wof:name":"Microdec PLC",
    "wof:placetype":"venue"
},
  "geometry": {"coordinates":[151.20913696299999,-33.841053009],"type":"Point"}
}