{
  "type": "Feature",
  "properties": {
    "addr:full":"Jones Arcade Cnr Forrest & Steere Sts Collie WA 6225",
    "addr:postcode":"6225",
    "addr:street":"Cnr",
    "iso:country":"AU",
    "sg:address":"Jones Arcade Cnr Forrest & Steere Sts",
    "sg:city":"Collie",
    "sg:classifiers":[
        {
            "category":"Travel",
            "subcategory":"Travel Agent",
            "type":"Entertainment"
        }
    ],
    "sg:phone":"+61 8 9734 5788",
    "sg:postcode":"6225",
    "sg:province":"WA",
    "sg:tags":[
        "consultant"
    ],
    "wof:name":"Collie Travelcentre",
    "wof:placetype":"venue"
},
  "geometry": {"coordinates":[116.15512099999999,-33.359169],"type":"Point"}
}