{
  "type": "Feature",
  "properties": {
    "addr:full":"23- 25 Station St Nerang QLD 4211",
    "addr:housenumber":"25",
    "addr:postcode":"4211",
    "addr:street":"Station St",
    "iso:country":"AU",
    "sg:address":"23- 25 Station St",
    "sg:city":"Nerang",
    "sg:classifiers":[
        {
            "category":"Shopping",
            "subcategory":"Clothing, Apparel, & Fashions",
            "type":"Retail Goods"
        }
    ],
    "sg:phone":"+61 7 5596 2377",
    "sg:postcode":"4211",
    "sg:province":"QLD",
    "sg:tags":[
        "recycled",
        "clothing"
    ],
    "wof:name":"Salvos Stores",
    "wof:placetype":"venue"
},
  "geometry": {"coordinates":[153.33941650400001,-27.994436264],"type":"Point"}
}