{
  "type": "Feature",
  "properties": {
    "addr:full":"4/ 20 Howard Ave Dee Why NSW 2099",
    "addr:housenumber":"/ 20",
    "addr:postcode":"2099",
    "addr:street":"Howard Ave",
    "iso:country":"AU",
    "sg:address":"4/ 20 Howard Ave",
    "sg:city":"Dee Why",
    "sg:classifiers":[
        {
            "category":"Travel",
            "subcategory":"Travel Agent",
            "type":"Entertainment"
        }
    ],
    "sg:phone":"+61 2 9981 3500",
    "sg:postcode":"2099",
    "sg:province":"NSW",
    "sg:tags":[
        "tour",
        "holiday",
        "adventure"
    ],
    "wof:name":"Telstar Travel Services Pty Ltd",
    "wof:placetype":"venue"
},
  "geometry": {"coordinates":[151.28848266599999,-33.7525672913],"type":"Point"}
}