{
  "type": "Feature",
  "properties": {
    "addr:full":"238 Maroondah Hwy Healesville VIC 3777",
    "addr:housenumber":"238",
    "addr:postcode":"3777",
    "addr:street":"Maroondah Hwy",
    "iso:country":"AU",
    "sg:address":"238 Maroondah Hwy",
    "sg:city":"Healesville",
    "sg:classifiers":[
        {
            "category":"Shopping",
            "subcategory":"Antiques",
            "type":"Retail Goods"
        }
    ],
    "sg:phone":"+61 3 5962 6666",
    "sg:postcode":"3777",
    "sg:province":"VIC",
    "wof:name":"Brookfield Antique Boutique",
    "wof:placetype":"venue"
},
  "geometry": {"coordinates":[145.51518200000001,-37.654362],"type":"Point"}
}