{
  "type": "Feature",
  "properties": {
    "iso:country":"AU",
    "sg:address":"Lot 6 Pinta St",
    "sg:city":"Wallerawang",
    "sg:classifiers":[
        {
            "category":"Building & Trades",
            "subcategory":"Plumbing",
            "type":"Services"
        }
    ],
    "sg:phone":"+61 2 6355 7777",
    "sg:postcode":"2845",
    "sg:province":"NSW",
    "sg:tags":[
        "pump",
        "repairer"
    ],
    "wof:name":"Western Pump Repairers",
    "wof:placetype":"venue"
},
  "geometry": {"coordinates":[150.06950399999999,-33.404991],"type":"Point"}
}