{
  "type": "Feature",
  "properties": {
    "addr:full":"Sawmill Rd Huntly VIC 3551",
    "addr:postcode":"3551",
    "addr:street":"Sawmill Rd",
    "iso:country":"AU",
    "sg:address":"Sawmill Rd",
    "sg:city":"Huntly",
    "sg:classifiers":[
        {
            "category":"Building & Trades",
            "subcategory":"Construction",
            "type":"Services"
        }
    ],
    "sg:phone":"+61 3 5448 7182",
    "sg:postcode":"3551",
    "sg:province":"VIC",
    "sg:tags":[
        "concrete",
        "contractor"
    ],
    "wof:name":"R. & C. Concreting",
    "wof:placetype":"venue"
},
  "geometry": {"coordinates":[144.334716797,-36.658290863],"type":"Point"}
}