{
  "type": "Feature",
  "properties": {
    "iso:country":"AU",
    "sg:address":"Unit 45/ 64 Beresford Rd",
    "sg:city":"Lilydale",
    "sg:classifiers":[
        {
            "category":"Manufacturing",
            "subcategory":"Food",
            "type":"Manufacturing & Wholesale Goods"
        }
    ],
    "sg:phone":"+61 3 9735 3936",
    "sg:postcode":"3140",
    "sg:province":"VIC",
    "sg:tags":[
        "product",
        "nut",
        "edible"
    ],
    "wof:name":"Yarra Valley Snack Foods",
    "wof:placetype":"venue"
},
  "geometry": {"coordinates":[145.34397888199999,-37.7503356934],"type":"Point"}
}