{
  "type": "Feature",
  "properties": {
    "addr:full":"1 St Johns Park Shopng Cntr St Johns Park NSW 2176",
    "addr:housenumber":"1",
    "addr:postcode":"2176",
    "addr:street":"St Johns Park Shopng Cntr St",
    "iso:country":"AU",
    "sg:address":"1 St Johns Park Shopng Cntr",
    "sg:city":"St Johns Park",
    "sg:classifiers":[
        {
            "category":"Food & Beverages",
            "subcategory":"Bakery",
            "type":"Retail Goods"
        }
    ],
    "sg:phone":"+61 2 9823 7719",
    "sg:postcode":"2176",
    "sg:province":"NSW",
    "sg:tags":[
        "baker"
    ],
    "wof:name":"St Johns Park Cake & Hot Bread",
    "wof:placetype":"venue"
},
  "geometry": {"coordinates":[150.91551208499999,-33.8873634338],"type":"Point"}
}