{
  "type": "Feature",
  "properties": {
    "iso:country":"AU",
    "sg:address":"27 Elizabeth St",
    "sg:city":"Hobart",
    "sg:classifiers":[
        {
            "category":"Banks & Credit Unions",
            "subcategory":"Financial Services",
            "type":"Services"
        }
    ],
    "sg:phone":"+61 3 6235 5528",
    "sg:postcode":"7000",
    "sg:province":"TAS",
    "sg:tags":[
        "annuity",
        "rollover",
        "superannuation",
        "consultant"
    ],
    "wof:name":"Keith Lello",
    "wof:placetype":"venue"
},
  "geometry": {"coordinates":[147.32908630399999,-42.8820457458],"type":"Point"}
}