{
  "type": "Feature",
  "properties": {
    "addr:full":"279 Alice St Maryborough QLD 4650",
    "addr:housenumber":"279",
    "addr:postcode":"4650",
    "addr:street":"Alice St",
    "iso:country":"AU",
    "sg:address":"279 Alice St",
    "sg:city":"Maryborough",
    "sg:classifiers":[
        {
            "category":"Structure",
            "subcategory":"Bridge",
            "type":"Public Place"
        }
    ],
    "sg:phone":"+61 7 4121 3900",
    "sg:postcode":"4650",
    "sg:province":"QLD",
    "sg:tags":[
        "chainsaw",
        "brushcutters"
    ],
    "wof:name":"Wilson's Mower Centre",
    "wof:placetype":"venue"
},
  "geometry": {"coordinates":[152.70043899999999,-25.541294],"type":"Point"}
}