{
  "type": "Feature",
  "properties": {
    "addr:full":"Unit 1, 41A Munibung Rd Cardiff NSW 2285",
    "addr:housenumber":"41a",
    "addr:postcode":"2285",
    "addr:street":"Munibung Rd",
    "iso:country":"AU",
    "sg:address":"Unit 1, 41A Munibung Rd",
    "sg:city":"Cardiff",
    "sg:classifiers":[
        {
            "category":"Building & Trades",
            "subcategory":"Pest Control",
            "type":"Services"
        }
    ],
    "sg:phone":"+61 2 4954 0111",
    "sg:postcode":"2285",
    "sg:province":"NSW",
    "wof:name":"Pro-Master Pest Control",
    "wof:placetype":"venue"
},
  "geometry": {"coordinates":[151.650024414,-32.9429397583],"type":"Point"}
}