{
  "type": "Feature",
  "properties": {
    "addr:full":"Shp 2/ 371 Ballina Rd Goonellabah NSW 2480",
    "addr:housenumber":"/ 371",
    "addr:postcode":"2480",
    "addr:street":"Ballina Rd",
    "iso:country":"AU",
    "sg:address":"Shp 2/ 371 Ballina Rd",
    "sg:city":"Goonellabah",
    "sg:classifiers":[
        {
            "category":"Food & Beverages",
            "subcategory":"Bakery",
            "type":"Retail Goods"
        }
    ],
    "sg:phone":"+61 2 6624 7995",
    "sg:postcode":"2480",
    "sg:province":"NSW",
    "sg:tags":[
        "baker"
    ],
    "wof:name":"Village Bakehouse",
    "wof:placetype":"venue"
},
  "geometry": {"coordinates":[153.34739685100001,-28.8121471405],"type":"Point"}
}