{
  "type": "Feature",
  "properties": {
    "iso:country":"AU",
    "sg:address":"1/88 Munibung Rd",
    "sg:city":"Cardiff",
    "sg:classifiers":[
        {
            "category":"Wholesale",
            "subcategory":"Metals & Minerals",
            "type":"Manufacturing & Wholesale Goods"
        }
    ],
    "sg:phone":"+61 2 4954 0455",
    "sg:postcode":"2285",
    "sg:province":"NSW",
    "sg:tags":[
        "steel",
        "merchant"
    ],
    "wof:name":"Metaland",
    "wof:placetype":"venue"
},
  "geometry": {"coordinates":[151.63955688499999,-32.9427986145],"type":"Point"}
}