{
  "type": "Feature",
  "properties": {
    "addr:full":"Highland Shopng Cntr 222 Target Hill Rd Greenwith SA 5125",
    "addr:housenumber":"222",
    "addr:postcode":"5125",
    "addr:street":"Target Hill Rd",
    "iso:country":"AU",
    "sg:address":"Highland Shopng Cntr 222 Target Hill Rd",
    "sg:city":"Greenwith",
    "sg:classifiers":[
        {
            "category":"Health Services",
            "subcategory":"Doctor",
            "type":"Services"
        }
    ],
    "sg:phone":"+61 8 8289 6911",
    "sg:postcode":"5125",
    "sg:province":"SA",
    "sg:tags":[
        "medical",
        "practitioner"
    ],
    "wof:name":"Brimage Robert",
    "wof:placetype":"venue"
},
  "geometry": {"coordinates":[138.719696,-34.768936],"type":"Point"}
}