{
  "type": "Feature",
  "properties": {
    "addr:full":"141 Sportsman Pde Bokarina QLD 4575",
    "addr:housenumber":"141",
    "addr:postcode":"4575",
    "addr:street":"Sportsman Pde",
    "iso:country":"AU",
    "sg:address":"141 Sportsman Pde",
    "sg:city":"Bokarina",
    "sg:classifiers":[
        {
            "category":"Education",
            "subcategory":"Kindergarten",
            "type":"Public Place"
        }
    ],
    "sg:phone":"+61 7 5493 3566",
    "sg:postcode":"4575",
    "sg:province":"QLD",
    "sg:tags":[
        "pre-schools"
    ],
    "wof:name":"Kawana Community Kindergarten",
    "wof:placetype":"venue"
},
  "geometry": {"coordinates":[153.12785299999999,-26.742588],"type":"Point"}
}