{
  "type": "Feature",
  "properties": {
    "addr:full":"31 Sawry Crt Tamborine QLD 4270",
    "addr:housenumber":"31",
    "addr:postcode":"4270",
    "addr:street":"Sawry Crt",
    "iso:country":"AU",
    "sg:address":"31 Sawry Crt",
    "sg:city":"Tamborine",
    "sg:classifiers":[
        {
            "category":"Manufacturing",
            "subcategory":"Tools & Machinery",
            "type":"Manufacturing & Wholesale Goods"
        }
    ],
    "sg:phone":"+61 7 5543 8608",
    "sg:postcode":"4270",
    "sg:province":"QLD",
    "sg:tags":[
        "earth",
        "excavating",
        "moving",
        "equipment"
    ],
    "wof:name":"About Town Mini Earthworks",
    "wof:placetype":"venue"
},
  "geometry": {"coordinates":[153.08148193400001,-27.8477611542],"type":"Point"}
}