{
  "type": "Feature",
  "properties": {
    "iso:country":"AU",
    "sg:address":"17 Sirius Cove Rd",
    "sg:city":"Mosman",
    "sg:classifiers":[
        {
            "category":"Professional",
            "subcategory":"Art Services",
            "type":"Services"
        }
    ],
    "sg:phone":"+61 2 9969 5361",
    "sg:postcode":"2088",
    "sg:province":"NSW",
    "sg:tags":[
        "artist"
    ],
    "wof:name":"Hetherington N F",
    "wof:placetype":"venue"
},
  "geometry": {"coordinates":[151.24029540999999,-33.8376808167],"type":"Point"}
}