{
  "type": "Feature",
  "properties": {
    "iso:country":"AU",
    "sg:address":"1 Paluna Pl",
    "sg:city":"Ellen Grove",
    "sg:classifiers":[
        {
            "category":"Real Estate",
            "subcategory":"Surveying",
            "type":"Services"
        }
    ],
    "sg:phone":"+61 7 3271 5060",
    "sg:postcode":"4078",
    "sg:province":"QLD",
    "sg:tags":[
        "mathematical",
        "statistical"
    ],
    "wof:name":"Grid Statistical Services",
    "wof:placetype":"venue"
},
  "geometry": {"coordinates":[152.94871520999999,-27.6063632965],"type":"Point"}
}