{
  "type": "Feature",
  "properties": {
    "addr:full":"Shop 5a/ 191 Sir Fred Schonell Drv St Lucia QLD 4067",
    "addr:housenumber":"shop 5a / 191",
    "addr:postcode":"4067",
    "addr:street":"Sir Fred Schonell Drv",
    "iso:country":"AU",
    "sg:address":"Shop 5a/ 191 Sir Fred Schonell Drv St",
    "sg:city":"Lucia",
    "sg:classifiers":[
        {
            "category":"Personal",
            "subcategory":"Beauty Salon",
            "type":"Services"
        }
    ],
    "sg:phone":"+61 7 3217 8828",
    "sg:postcode":"4067",
    "sg:province":"QLD",
    "sg:tags":[
        "hairdresser"
    ],
    "wof:name":"Shyen Hair",
    "wof:placetype":"venue"
},
  "geometry": {"coordinates":[153.003082275,-27.4944057465],"type":"Point"}
}