{
  "type": "Feature",
  "properties": {
    "addr:full":"1 Pike Crt Noble Park VIC 3174",
    "addr:housenumber":"1",
    "addr:postcode":"3174",
    "addr:street":"Pike Crt",
    "iso:country":"AU",
    "sg:address":"1 Pike Crt",
    "sg:city":"Noble Park",
    "sg:classifiers":[
        {
            "category":"Building & Trades",
            "subcategory":"Plumbing",
            "type":"Services"
        }
    ],
    "sg:phone":"+61 419 364 831",
    "sg:postcode":"3174",
    "sg:province":"VIC",
    "sg:tags":[
        "plumber",
        "gasfitters"
    ],
    "wof:name":"Keysborough Plumbing Service",
    "wof:placetype":"venue"
},
  "geometry": {"coordinates":[145.16546630900001,-37.97473526],"type":"Point"}
}