{
  "type": "Feature",
  "properties": {
    "iso:country":"AU",
    "sg:address":"395 New South Head Rd",
    "sg:city":"Double Bay",
    "sg:classifiers":[
        {
            "category":"Communications",
            "subcategory":"News Services",
            "type":"Services"
        }
    ],
    "sg:phone":"+61 2 9328 1722",
    "sg:postcode":"2028",
    "sg:province":"NSW",
    "sg:tags":[
        "information",
        "tourist",
        "attractions"
    ],
    "wof:name":"Israel Tourism Office",
    "wof:placetype":"venue"
},
  "geometry": {"coordinates":[151.24293518100001,-33.8778915405],"type":"Point"}
}