{
  "type": "Feature",
  "properties": {
    "iso:country":"AU",
    "sg:address":"28- 30 Greenway Drv",
    "sg:city":"Tweed Heads South",
    "sg:classifiers":[
        {
            "category":"Manufacturing",
            "subcategory":"Furniture",
            "type":"Manufacturing & Wholesale Goods"
        }
    ],
    "sg:phone":"+61 7 5523 1662",
    "sg:postcode":"2486",
    "sg:province":"NSW",
    "sg:tags":[
        "builder",
        "designer",
        "custom"
    ],
    "wof:name":"Jigsaw Furniture",
    "wof:placetype":"venue"
},
  "geometry": {"coordinates":[153.536712647,-28.207403183],"type":"Point"}
}