{
  "type": "Feature",
  "properties": {
    "addr:full":"12-14 Tapley St Adelaide SA 5000",
    "addr:housenumber":"12-14",
    "addr:postcode":"5000",
    "addr:street":"Tapley St",
    "iso:country":"AU",
    "sg:address":"12-14 Tapley St",
    "sg:city":"Adelaide",
    "sg:classifiers":[
        {
            "category":"Building & Trades",
            "subcategory":"Locksmith",
            "type":"Services"
        }
    ],
    "sg:phone":"+61 8 8231 5534",
    "sg:postcode":"5000",
    "sg:province":"SA",
    "sg:tags":[
        "strongroom",
        "safe",
        "door"
    ],
    "wof:name":"S.A. Locksmiths",
    "wof:placetype":"venue"
},
  "geometry": {"coordinates":[138.59971618599999,-34.9243736267],"type":"Point"}
}