{
  "type": "Feature",
  "properties": {
    "iso:country":"AU",
    "sg:address":"73 Auburn St",
    "sg:city":"Wollongong",
    "sg:classifiers":[
        {
            "category":"Professional",
            "subcategory":"Engineering",
            "type":"Services"
        }
    ],
    "sg:phone":"+61 2 4229 3012",
    "sg:postcode":"2500",
    "sg:province":"NSW",
    "sg:tags":[
        "consulting",
        "engineer"
    ],
    "wof:name":"Davron Engineering Pty Ltd",
    "wof:placetype":"venue"
},
  "geometry": {"coordinates":[150.888245,-34.433567],"type":"Point"}
}