{
  "type": "Feature",
  "properties": {
    "iso:country":"AU",
    "sg:address":"Unit B5/ 3-9 Birnie Av",
    "sg:city":"Lidcombe",
    "sg:classifiers":[
        {
            "category":"Professional",
            "subcategory":"Detective & Security Services",
            "type":"Services"
        }
    ],
    "sg:phone":"+61 2 9741 7900",
    "sg:postcode":"2141",
    "sg:province":"NSW",
    "sg:tags":[
        "guard",
        "patrol"
    ],
    "wof:name":"Armaguard",
    "wof:placetype":"venue"
},
  "geometry": {"coordinates":[151.06060790999999,-33.8559150696],"type":"Point"}
}