{
  "type": "Feature",
  "properties": {
    "addr:full":"Shop 5 337 Logan Rd Stones Corner QLD 4120",
    "addr:housenumber":"shop 5 337",
    "addr:postcode":"4120",
    "addr:street":"Logan Rd",
    "iso:country":"AU",
    "sg:address":"Shop 5 337 Logan Rd",
    "sg:city":"Stones Corner",
    "sg:classifiers":[
        {
            "category":"Personal",
            "subcategory":"Beauty Salon",
            "type":"Services"
        }
    ],
    "sg:phone":"+61 7 3397 7651",
    "sg:postcode":"4120",
    "sg:province":"QLD",
    "wof:name":"The Make-up Studio",
    "wof:placetype":"venue"
},
  "geometry": {"coordinates":[153.04454040499999,-27.4986934662],"type":"Point"}
}