{
  "type": "Feature",
  "properties": {
    "iso:country":"AU",
    "sg:address":"Rear 52 Toorak Rd",
    "sg:city":"South Yarra",
    "sg:classifiers":[
        {
            "category":"Personal",
            "subcategory":"Beauty Salon",
            "type":"Services"
        }
    ],
    "sg:phone":"+61 3 9866 3535",
    "sg:postcode":"3141",
    "sg:province":"VIC",
    "sg:tags":[
        "hairdresser"
    ],
    "wof:name":"Etre Hair",
    "wof:placetype":"venue"
},
  "geometry": {"coordinates":[144.98826599099999,-37.8386573792],"type":"Point"}
}