{
  "type": "Feature",
  "properties": {
    "iso:country":"AU",
    "sg:address":"24 Brisbane Rd",
    "sg:city":"Mooloolaba",
    "sg:classifiers":[
        {
            "category":"Health Services",
            "subcategory":"Health Practitioner",
            "type":"Services"
        }
    ],
    "sg:phone":"+61 414 982 854",
    "sg:postcode":"4557",
    "sg:province":"QLD",
    "sg:tags":[
        "naturopath"
    ],
    "wof:name":"Cantlon Theresa",
    "wof:placetype":"venue"
},
  "geometry": {"coordinates":[153.11898803700001,-26.6815471649],"type":"Point"}
}