{
  "type": "Feature",
  "properties": {
    "addr:full":"16 Cahill St Dandenong VIC 3175",
    "addr:housenumber":"16",
    "addr:postcode":"3175",
    "addr:street":"Cahill St",
    "iso:country":"AU",
    "sg:address":"16 Cahill St",
    "sg:city":"Dandenong",
    "sg:classifiers":[
        {
            "category":"Wholesale",
            "subcategory":"Machinery & Supplies",
            "type":"Manufacturing & Wholesale Goods"
        }
    ],
    "sg:phone":"+61 419 415 566",
    "sg:postcode":"3175",
    "sg:province":"VIC",
    "sg:tags":[
        "agricultural"
    ],
    "wof:name":"Kanga Farm Equipment",
    "wof:placetype":"venue"
},
  "geometry": {"coordinates":[145.20094299300001,-38.0268936157],"type":"Point"}
}