{
  "type": "Feature",
  "properties": {
    "addr:full":"13 Bonnal Rd Erina NSW 2250",
    "addr:housenumber":"13",
    "addr:postcode":"2250",
    "addr:street":"Bonnal Rd",
    "iso:country":"AU",
    "sg:address":"13 Bonnal Rd",
    "sg:city":"Erina",
    "sg:classifiers":[
        {
            "category":"Food & Beverages",
            "subcategory":"Fruits & Vegetables",
            "type":"Retail Goods"
        }
    ],
    "sg:phone":"+61 2 4367 5992",
    "sg:postcode":"2250",
    "sg:province":"NSW",
    "sg:tags":[
        "consultant",
        "catering"
    ],
    "wof:name":"Fresh Plates",
    "wof:placetype":"venue"
},
  "geometry": {"coordinates":[151.383712769,-33.4349327087],"type":"Point"}
}