{
  "type": "Feature",
  "properties": {
    "addr:full":"4/49 Lavinia St Athol Park SA 5012",
    "addr:housenumber":"/ 49",
    "addr:postcode":"5012",
    "addr:street":"Lavinia St",
    "iso:country":"AU",
    "sg:address":"4/49 Lavinia St",
    "sg:city":"Athol Park",
    "sg:classifiers":[
        {
            "category":"Real Estate",
            "subcategory":"Surveying",
            "type":"Services"
        }
    ],
    "sg:phone":"+61 8 8240 4499",
    "sg:postcode":"5012",
    "sg:province":"SA",
    "sg:tags":[
        "acoustic",
        "material"
    ],
    "wof:name":"Aro Technology",
    "wof:placetype":"venue"
},
  "geometry": {"coordinates":[138.54432678200001,-34.8542289734],"type":"Point"}
}