{
  "type": "Feature",
  "properties": {
    "iso:country":"AU",
    "sg:address":"1371 Dohertys Rd",
    "sg:city":"Werribee",
    "sg:classifiers":[
        {
            "category":"Manufacturing",
            "subcategory":"Chemicals & Compounds",
            "type":"Manufacturing & Wholesale Goods"
        }
    ],
    "sg:phone":"+61 3 9748 1300",
    "sg:postcode":"3030",
    "sg:province":"VIC",
    "sg:tags":[
        "oil",
        "recovery",
        "dispersal",
        "spill"
    ],
    "wof:name":"Sprinkle & Sweep Pty Ltd",
    "wof:placetype":"venue"
},
  "geometry": {"coordinates":[144.65365600000001,-37.815002],"type":"Point"}
}