{
  "type": "Feature",
  "properties": {
    "iso:country":"AU",
    "sg:address":"111 Nott St",
    "sg:city":"Port Melbourne",
    "sg:classifiers":[
        {
            "category":"Professional",
            "subcategory":"Computer Services",
            "type":"Services"
        }
    ],
    "sg:phone":"+61 3 9646 9766",
    "sg:postcode":"3207",
    "sg:province":"VIC",
    "sg:tags":[
        "consultant",
        "system"
    ],
    "wof:name":"Megabus Systems Pty Ltd",
    "wof:placetype":"venue"
},
  "geometry": {"coordinates":[144.93895000000001,-37.840115],"type":"Point"}
}