{
  "type": "Feature",
  "properties": {
    "addr:full":"75 Main Rd Meander TAS 7304",
    "addr:housenumber":"75",
    "addr:postcode":"7304",
    "addr:street":"Main Rd",
    "iso:country":"AU",
    "sg:address":"75 Main Rd",
    "sg:city":"Meander",
    "sg:classifiers":[
        {
            "category":"Government",
            "subcategory":"Post Office",
            "type":"Public Place"
        }
    ],
    "sg:phone":"+61 3 6369 5215",
    "sg:postcode":"7304",
    "sg:province":"TAS",
    "sg:tags":[
        "postal"
    ],
    "wof:name":"Australia Post",
    "wof:placetype":"venue"
},
  "geometry": {"coordinates":[146.61630199999999,-41.649055],"type":"Point"}
}