{
  "type": "Feature",
  "properties": {
    "addr:full":"86-88 Governor Road Mordialloc VIC 3195",
    "addr:housenumber":"86-88",
    "addr:postcode":"3195",
    "addr:street":"Governor Road",
    "iso:country":"AU",
    "sg:address":"86-88 Governor Road",
    "sg:city":"Mordialloc",
    "sg:classifiers":[
        {
            "category":"Building & Trades",
            "subcategory":"Construction",
            "type":"Services"
        }
    ],
    "sg:phone":"+61 3 9590 9961",
    "sg:postcode":"3195",
    "sg:province":"VIC",
    "sg:tags":[
        "concrete",
        "paving"
    ],
    "wof:name":"Lumeah Limestone",
    "wof:placetype":"venue"
},
  "geometry": {"coordinates":[145.10188293499999,-38.0078735352],"type":"Point"}
}