{
  "type": "Feature",
  "properties": {
    "addr:full":"11 Wynn St Woonona NSW 2517",
    "addr:housenumber":"11",
    "addr:postcode":"2517",
    "addr:street":"Wynn St",
    "iso:country":"AU",
    "sg:address":"11 Wynn St",
    "sg:city":"Woonona",
    "sg:classifiers":[
        {
            "category":"Recreation",
            "type":"Entertainment"
        }
    ],
    "sg:phone":"+61 2 9255 7795",
    "sg:postcode":"2517",
    "sg:province":"NSW",
    "sg:tags":[
        "hire",
        "tour",
        "motor",
        "cycle"
    ],
    "wof:name":"Easyrider Motorbike Tours",
    "wof:placetype":"venue"
},
  "geometry": {"coordinates":[150.91194200000001,-34.352489],"type":"Point"}
}