{
  "type": "Feature",
  "properties": {
    "iso:country":"AU",
    "sg:address":"6 Kings La",
    "sg:city":"Darlinghurst",
    "sg:classifiers":[
        {
            "category":"Wholesale",
            "subcategory":"Music Publishers",
            "type":"Manufacturing & Wholesale Goods"
        }
    ],
    "sg:phone":"+61 2 9361 4666",
    "sg:postcode":"2010",
    "sg:province":"NSW",
    "sg:tags":[
        "wholesaler",
        "dvd",
        "mfrs",
        "cd"
    ],
    "wof:name":"Modular People",
    "wof:placetype":"venue"
},
  "geometry": {"coordinates":[151.217559814,-33.8780326843],"type":"Point"}
}