{
  "type": "Feature",
  "properties": {
    "addr:full":"Richardson St Serpentine WA 6125",
    "addr:postcode":"6125",
    "addr:street":"Richardson St",
    "iso:country":"AU",
    "sg:address":"Richardson St",
    "sg:city":"Serpentine",
    "sg:classifiers":[
        {
            "category":"Home & Garden",
            "subcategory":"Building Materials",
            "type":"Retail Goods"
        }
    ],
    "sg:phone":"+61 8 9525 2637",
    "sg:postcode":"6125",
    "sg:province":"WA",
    "sg:tags":[
        "roofing"
    ],
    "wof:name":"Steel Kit Homes",
    "wof:placetype":"venue"
},
  "geometry": {"coordinates":[115.976898193,-32.3628768921],"type":"Point"}
}