{
  "type": "Feature",
  "properties": {
    "addr:full":"184 Brisbane St Ipswich QLD 4305",
    "addr:housenumber":"184",
    "addr:postcode":"4305",
    "addr:street":"Brisbane St",
    "iso:country":"AU",
    "sg:address":"184 Brisbane St",
    "sg:city":"Ipswich",
    "sg:classifiers":[
        {
            "category":"Professional",
            "subcategory":"Accounting & Tax Preparation",
            "type":"Services"
        }
    ],
    "sg:phone":"+61 7 3281 2468",
    "sg:postcode":"4305",
    "sg:province":"QLD",
    "sg:tags":[
        "consultant",
        "taxation"
    ],
    "wof:name":"Personal Tax Services",
    "wof:placetype":"venue"
},
  "geometry": {"coordinates":[152.75709533700001,-27.613948822],"type":"Point"}
}