{
  "type": "Feature",
  "properties": {
    "iso:country":"AU",
    "sg:address":"17- 23 Parramatta Rd",
    "sg:city":"Haberfield",
    "sg:classifiers":[
        {
            "category":"Education",
            "subcategory":"Special Training",
            "type":"Public Place"
        }
    ],
    "sg:phone":"+61 2 9716 0150",
    "sg:postcode":"2045",
    "sg:province":"NSW",
    "sg:tags":[
        "development"
    ],
    "wof:name":"RGV Systems International",
    "wof:placetype":"venue"
},
  "geometry": {"coordinates":[151.143204,-33.888355],"type":"Point"}
}