{
  "type": "Feature",
  "properties": {
    "addr:full":"6 Mandina Pl Bringelly NSW 2171",
    "addr:housenumber":"6",
    "addr:postcode":"2171",
    "addr:street":"Mandina Pl",
    "iso:country":"AU",
    "sg:address":"6 Mandina Pl",
    "sg:city":"Bringelly",
    "sg:classifiers":[
        {
            "category":"Professional",
            "subcategory":"Computer Services",
            "type":"Services"
        }
    ],
    "sg:phone":"+61 2 4774 8979",
    "sg:postcode":"2171",
    "sg:province":"NSW",
    "sg:tags":[
        "consultant",
        "system"
    ],
    "wof:name":"Spiral Systems Support Pty Ltd",
    "wof:placetype":"venue"
},
  "geometry": {"coordinates":[150.753005981,-33.9230918884],"type":"Point"}
}