{
  "type": "Feature",
  "properties": {
    "addr:full":"PO Box 170 Huntly VIC 3551",
    "addr:postcode":"3551",
    "iso:country":"AU",
    "sg:address":"PO Box 170",
    "sg:city":"Huntly",
    "sg:classifiers":[
        {
            "category":"Arena",
            "subcategory":"Sports Club",
            "type":"Entertainment"
        }
    ],
    "sg:phone":"+61 3 5448 8109",
    "sg:postcode":"3551",
    "sg:province":"VIC",
    "sg:tags":[
        "defence",
        "supply",
        "self",
        "instruction",
        "martial art"
    ],
    "wof:name":"Dragon City Karate Academy",
    "wof:placetype":"venue"
},
  "geometry": {"coordinates":[144.333526611,-36.6647109985],"type":"Point"}
}