{
  "type": "Feature",
  "properties": {
    "addr:full":"58 Prospect Rd Prospect SA 5082",
    "addr:housenumber":"58",
    "addr:postcode":"5082",
    "addr:street":"Prospect Rd",
    "iso:country":"AU",
    "sg:address":"58 Prospect Rd",
    "sg:city":"Prospect",
    "sg:classifiers":[
        {
            "category":"Banks & Credit Unions",
            "subcategory":"Financial Services",
            "type":"Services"
        }
    ],
    "sg:phone":"+61 8 8269 9100",
    "sg:postcode":"5082",
    "sg:province":"SA",
    "sg:tags":[
        "planning"
    ],
    "wof:name":"PAK Plans Pty Ltd",
    "wof:placetype":"venue"
},
  "geometry": {"coordinates":[138.594207764,-34.8920402527],"type":"Point"}
}