{
  "type": "Feature",
  "properties": {
    "addr:full":"103 Columba St Inala QLD 4077",
    "addr:housenumber":"103",
    "addr:postcode":"4077",
    "addr:street":"Columba St",
    "iso:country":"AU",
    "sg:address":"103 Columba St",
    "sg:city":"Inala",
    "sg:classifiers":[
        {
            "category":"Building & Trades",
            "subcategory":"Cleaning & Sanitation",
            "type":"Services"
        }
    ],
    "sg:phone":"+61 7 3372 8097",
    "sg:postcode":"4077",
    "sg:province":"QLD",
    "sg:tags":[
        "industrial",
        "commercial",
        "contractor"
    ],
    "wof:name":"Fair Dinkum Cleaning Services",
    "wof:placetype":"venue"
},
  "geometry": {"coordinates":[152.96386718799999,-27.5985240936],"type":"Point"}
}