{
  "type": "Feature",
  "properties": {
    "addr:full":"52B Kewdale Rd Welshpool WA 6106",
    "addr:housenumber":"52b",
    "addr:postcode":"6106",
    "addr:street":"Kewdale Rd",
    "iso:country":"AU",
    "sg:address":"52B Kewdale Rd",
    "sg:city":"Welshpool",
    "sg:classifiers":[
        {
            "category":"Building & Trades",
            "subcategory":"Equipment Rental",
            "type":"Services"
        }
    ],
    "sg:phone":"+61 8 9350 6255",
    "sg:postcode":"6106",
    "sg:province":"WA",
    "sg:tags":[
        "builder",
        "contractor"
    ],
    "wof:name":"Easymix",
    "wof:placetype":"venue"
},
  "geometry": {"coordinates":[115.973876953,-31.9974346161],"type":"Point"}
}