{
  "type": "Feature",
  "properties": {
    "addr:full":"Edwin St West Lakes Shore SA 5020",
    "addr:postcode":"5020",
    "addr:street":"Edwin St",
    "iso:country":"AU",
    "sg:address":"Edwin St",
    "sg:city":"West Lakes Shore",
    "sg:classifiers":[
        {
            "category":"Education",
            "subcategory":"School",
            "type":"Public Place"
        }
    ],
    "sg:phone":"+61 8 8449 7255",
    "sg:postcode":"5020",
    "sg:province":"SA",
    "sg:tags":[
        "state",
        "except",
        "nsw"
    ],
    "wof:name":"West Lakes Shore Schools",
    "wof:placetype":"venue"
},
  "geometry": {"coordinates":[138.48333740199999,-34.864906311],"type":"Point"}
}