{
  "type": "Feature",
  "properties": {
    "iso:country":"AU",
    "sg:address":"79 Eton St",
    "sg:city":"Smithfield",
    "sg:classifiers":[
        {
            "category":"Retail",
            "subcategory":"Repair Shop",
            "type":"Services"
        }
    ],
    "sg:phone":"+61 409 907 215",
    "sg:postcode":"2164",
    "sg:province":"NSW",
    "sg:tags":[
        "upholsterer"
    ],
    "wof:name":"Agius F.G. Upholstery",
    "wof:placetype":"venue"
},
  "geometry": {"coordinates":[150.94128418,-33.8554382324],"type":"Point"}
}