{
  "type": "Feature",
  "properties": {
    "iso:country":"AU",
    "sg:address":"Victoria Ave",
    "sg:city":"Castle Hill",
    "sg:classifiers":[
        {
            "category":"Shopping",
            "subcategory":"Pets & Pet Supplies",
            "type":"Retail Goods"
        }
    ],
    "sg:phone":"+61 2 9899 2257",
    "sg:postcode":"2154",
    "sg:province":"NSW",
    "sg:tags":[
        "food"
    ],
    "wof:name":"Hudson Resorces Holding Ltd",
    "wof:placetype":"venue"
},
  "geometry": {"coordinates":[150.98161315900001,-33.7353782654],"type":"Point"}
}