{
  "type": "Feature",
  "properties": {
    "iso:country":"AU",
    "sg:address":"16 Stevenson St",
    "sg:city":"Ascot",
    "sg:classifiers":[
        {
            "category":"Arts & Performance",
            "subcategory":"Art Gallery",
            "type":"Entertainment"
        }
    ],
    "sg:phone":"+61 7 3868 2454",
    "sg:postcode":"4007",
    "sg:province":"QLD",
    "wof:name":"Michel Sourgnes Fine Arts",
    "wof:placetype":"venue"
},
  "geometry": {"coordinates":[153.06572,-27.435083],"type":"Point"}
}