{
  "type": "Feature",
  "properties": {
    "iso:country":"AU",
    "sg:address":"422 Lyons Rd",
    "sg:city":"Five Dock",
    "sg:classifiers":[
        {
            "category":"Social Services",
            "subcategory":"Adult Care",
            "type":"Services"
        }
    ],
    "sg:phone":"+61 2 9799 5951",
    "sg:postcode":"2046",
    "sg:province":"NSW",
    "sg:tags":[
        "disadvantaged",
        "aid",
        "organisation",
        "group"
    ],
    "wof:name":"Home & Community Care Program Neighbour",
    "wof:placetype":"venue"
},
  "geometry": {"coordinates":[151.133087,-33.863194],"type":"Point"}
}