{
  "type": "Feature",
  "properties": {
    "addr:full":"170 WHill St Walcha NSW 2354",
    "addr:housenumber":"170",
    "addr:postcode":"2354",
    "addr:street":"Whill St",
    "iso:country":"AU",
    "sg:address":"170 WHill St",
    "sg:city":"Walcha",
    "sg:classifiers":[
        {
            "category":"Building & Trades",
            "subcategory":"Construction",
            "type":"Services"
        }
    ],
    "sg:phone":"+61 2 6777 2104",
    "sg:postcode":"2354",
    "sg:province":"NSW",
    "sg:tags":[
        "contractor"
    ],
    "wof:name":"Tickle G M",
    "wof:placetype":"venue"
},
  "geometry": {"coordinates":[151.58758544899999,-30.984380722],"type":"Point"}
}