{
  "type": "Feature",
  "properties": {
    "iso:country":"AU",
    "sg:address":"152 Stringybark Rd",
    "sg:city":"Buderim",
    "sg:classifiers":[
        {
            "category":"Building & Trades",
            "subcategory":"Construction",
            "type":"Services"
        }
    ],
    "sg:phone":"+61 7 5476 8834",
    "sg:postcode":"4556",
    "sg:province":"QLD",
    "sg:tags":[
        "contractor"
    ],
    "wof:name":"Celtic Homes",
    "wof:placetype":"venue"
},
  "geometry": {"coordinates":[153.05642700199999,-26.7088031769],"type":"Point"}
}