{
  "type": "Feature",
  "properties": {
    "iso:country":"AU",
    "sg:address":"422 Darling St",
    "sg:city":"Balmain",
    "sg:classifiers":[
        {
            "category":"Health Services",
            "subcategory":"Doctor",
            "type":"Services"
        }
    ],
    "sg:phone":"+61 2 9818 4102",
    "sg:postcode":"2041",
    "sg:province":"NSW",
    "sg:tags":[
        "medical",
        "practitioner"
    ],
    "wof:name":"Malcolm Jean Dr",
    "wof:placetype":"venue"
},
  "geometry": {"coordinates":[151.174393,-33.856087],"type":"Point"}
}