{
  "type": "Feature",
  "properties": {
    "addr:full":"212 Toombul Rd Northgate QLD 4013",
    "addr:housenumber":"212",
    "addr:postcode":"4013",
    "addr:street":"Toombul Rd",
    "iso:country":"AU",
    "sg:address":"212 Toombul Rd",
    "sg:city":"Northgate",
    "sg:classifiers":[
        {
            "category":"Professional",
            "type":"Services"
        }
    ],
    "sg:phone":"+61 7 3266 2170",
    "sg:postcode":"4013",
    "sg:province":"QLD",
    "sg:tags":[
        "forwarding",
        "agent",
        "transport"
    ],
    "wof:name":"AFL International Pty Ltd",
    "wof:placetype":"venue"
},
  "geometry": {"coordinates":[153.07389831500001,-27.3941822052],"type":"Point"}
}