{
  "type": "Feature",
  "properties": {
    "iso:country":"AU",
    "sg:address":"U4/ 3485 Pacific Hwy",
    "sg:city":"Slacks Creek",
    "sg:classifiers":[
        {
            "category":"Autos & Motor Vehicles",
            "subcategory":"Auto Supplies",
            "type":"Retail Goods"
        }
    ],
    "sg:phone":"+61 7 3208 9359",
    "sg:postcode":"4127",
    "sg:province":"QLD",
    "sg:tags":[
        "tyre"
    ],
    "wof:name":"Chiefs Budget Tyres",
    "wof:placetype":"venue"
},
  "geometry": {"coordinates":[153.13238525400001,-27.6344089508],"type":"Point"}
}