{
  "type": "Feature",
  "properties": {
    "addr:full":"37-41 St John St Launceston TAS 7250",
    "addr:housenumber":"37-41",
    "addr:postcode":"7250",
    "addr:street":"St John St",
    "iso:country":"AU",
    "sg:address":"37-41 St John St",
    "sg:city":"Launceston",
    "sg:classifiers":[
        {
            "category":"Autos & Motor Vehicles",
            "subcategory":"Automobile Sales",
            "type":"Retail Goods"
        }
    ],
    "sg:phone":"+61 3 6334 8444",
    "sg:postcode":"7250",
    "sg:province":"TAS",
    "sg:tags":[
        "car",
        "new"
    ],
    "wof:name":"Neil Buckby Motors Pty Ltd",
    "wof:placetype":"venue"
},
  "geometry": {"coordinates":[147.13671875,-41.4342651367],"type":"Point"}
}