{
  "type": "Feature",
  "properties": {
    "addr:full":"Basement Level, 820 Old Cleveland Road Carina QLD 4152",
    "addr:housenumber":"820",
    "addr:postcode":"4152",
    "addr:street":"Old Cleveland Road",
    "iso:country":"AU",
    "sg:address":"Basement Level, 820 Old Cleveland Road",
    "sg:city":"Carina",
    "sg:classifiers":[
        {
            "category":"Sports & Exercise",
            "subcategory":"Gym",
            "type":"Entertainment"
        }
    ],
    "sg:phone":"+61 423 176 808",
    "sg:postcode":"4152",
    "sg:province":"QLD",
    "sg:tags":[
        "personal",
        "trainer",
        "fitness"
    ],
    "wof:name":"A.J. Fitness Personal Training",
    "wof:placetype":"venue"
},
  "geometry": {"coordinates":[153.07257080100001,-27.4941520691],"type":"Point"}
}