{
  "type": "Feature",
  "properties": {
    "iso:country":"AU",
    "sg:address":"Cnr Chapman Rd & Cathedral Ave",
    "sg:city":"Geraldton",
    "sg:classifiers":[
        {
            "category":"Autos & Motor Vehicles",
            "subcategory":"Automobile Sales",
            "type":"Retail Goods"
        }
    ],
    "sg:phone":"+61 8 9921 1088",
    "sg:postcode":"6530",
    "sg:province":"WA",
    "sg:tags":[
        "car",
        "new"
    ],
    "wof:name":"Young Motors Pty Ltd",
    "wof:placetype":"venue"
},
  "geometry": {"coordinates":[114.62223815900001,-28.7424926758],"type":"Point"}
}