{
  "type": "Feature",
  "properties": {
    "addr:full":"44 Riverpoint Blv Riverhills QLD 4074",
    "addr:housenumber":"44",
    "addr:postcode":"4074",
    "addr:street":"Riverpoint Blv",
    "iso:country":"AU",
    "sg:address":"44 Riverpoint Blv",
    "sg:city":"Riverhills",
    "sg:classifiers":[
        {
            "category":"Building & Trades",
            "subcategory":"Landscaping Services",
            "type":"Services"
        }
    ],
    "sg:phone":"+61 7 3279 2268",
    "sg:postcode":"4074",
    "sg:province":"QLD",
    "sg:tags":[
        "firebreak",
        "clearing",
        "land",
        "contractor"
    ],
    "wof:name":"JJ's Wood Mulching",
    "wof:placetype":"venue"
},
  "geometry": {"coordinates":[152.90223693900001,-27.5649852753],"type":"Point"}
}