{
  "type": "Feature",
  "properties": {
    "iso:country":"AU",
    "sg:address":"39 Simpson St",
    "sg:city":"Beerwah",
    "sg:classifiers":[
        {
            "category":"Farming",
            "subcategory":"Farm & Veterinary Services",
            "type":"Manufacturing & Wholesale Goods"
        }
    ],
    "sg:phone":"+61 7 5494 6219",
    "sg:postcode":"4519",
    "sg:province":"QLD",
    "sg:tags":[
        "irrigation",
        "reticulation",
        "system"
    ],
    "wof:name":"Coochin Creek Co-Op",
    "wof:placetype":"venue"
},
  "geometry": {"coordinates":[152.95803799999999,-26.85771],"type":"Point"}
}