{
  "type": "Feature",
  "properties": {
    "iso:country":"AU",
    "sg:address":"Cnr Mary & Curlewis Sts",
    "sg:city":"Swan Hill",
    "sg:classifiers":[
        {
            "category":"Autos & Motor Vehicles",
            "subcategory":"Auto Supplies",
            "type":"Retail Goods"
        }
    ],
    "sg:phone":"+61 3 5032 9144",
    "sg:postcode":"3585",
    "sg:province":"VIC",
    "sg:tags":[
        "oil",
        "spirit"
    ],
    "wof:name":"Swan Hill Energy Services",
    "wof:placetype":"venue"
},
  "geometry": {"coordinates":[143.561554,-35.340954],"type":"Point"}
}