{
  "type": "Feature",
  "properties": {
    "iso:country":"AU",
    "sg:address":"Wallgrove Rd",
    "sg:city":"Eastern Creek",
    "sg:classifiers":[
        {
            "category":"Communications",
            "subcategory":"News Services",
            "type":"Services"
        }
    ],
    "sg:phone":"+61 2 9830 9100",
    "sg:postcode":"2766",
    "sg:province":"NSW",
    "sg:tags":[
        "information",
        "tourist",
        "attractions"
    ],
    "wof:name":"Australias Wonderland",
    "wof:placetype":"venue"
},
  "geometry": {"coordinates":[150.85159301799999,-33.8063316345],"type":"Point"}
}