{
  "type": "Feature",
  "properties": {
    "addr:full":"Baileys Corner, Cnr East Row & London Cct Canberra City ACT 2601",
    "addr:postcode":"2601",
    "addr:street":"Cnr East Row &",
    "iso:country":"AU",
    "sg:address":"Baileys Corner, Cnr East Row & London Cct",
    "sg:city":"Canberra City",
    "sg:classifiers":[
        {
            "category":"Personal",
            "type":"Services"
        }
    ],
    "sg:phone":"+61 2 6248 7766",
    "sg:postcode":"2601",
    "sg:province":"ACT",
    "sg:tags":[
        "gift"
    ],
    "sg:website":"http://www.janineflorist.com.au",
    "wof:name":"Send A Basket",
    "wof:placetype":"venue"
},
  "geometry": {"coordinates":[149.13055419899999,-35.2791786194],"type":"Point"}
}