{
  "type": "Feature",
  "properties": {
    "addr:full":"1 Heidke St Bundaberg QLD 4670",
    "addr:housenumber":"1",
    "addr:postcode":"4670",
    "addr:street":"Heidke St",
    "iso:country":"AU",
    "sg:address":"1 Heidke St",
    "sg:city":"Bundaberg",
    "sg:classifiers":[
        {
            "category":"Health Services",
            "subcategory":"Dentist",
            "type":"Services"
        }
    ],
    "sg:phone":"+61 7 4153 2566",
    "sg:postcode":"4670",
    "sg:province":"QLD",
    "wof:name":"Makepeace Phillip",
    "wof:placetype":"venue"
},
  "geometry": {"coordinates":[152.320510864,-24.8874187469],"type":"Point"}
}