{
  "type": "Feature",
  "properties": {
    "iso:country":"AU",
    "sg:address":"12 Thomas Drv",
    "sg:city":"Chevron Island",
    "sg:classifiers":[
        {
            "category":"Personal",
            "subcategory":"Massage",
            "type":"Services"
        }
    ],
    "sg:phone":"+61 7 5539 9798",
    "sg:postcode":"4217",
    "sg:province":"QLD",
    "sg:tags":[
        "therapy"
    ],
    "wof:name":"Surfers Paradise Massage Centre",
    "wof:placetype":"venue"
},
  "geometry": {"coordinates":[153.422927856,-27.9986572266],"type":"Point"}
}