{
  "type": "Feature",
  "properties": {
    "addr:full":"41 Peachey Rd Davoren Park SA 5113",
    "addr:housenumber":"41",
    "addr:postcode":"5113",
    "addr:street":"Peachey Rd",
    "iso:country":"AU",
    "sg:address":"41 Peachey Rd",
    "sg:city":"Davoren Park",
    "sg:classifiers":[
        {
            "category":"Retail",
            "subcategory":"Auto Repair",
            "type":"Services"
        }
    ],
    "sg:phone":"+61 8 8255 1607",
    "sg:postcode":"5113",
    "sg:province":"SA",
    "sg:tags":[
        "repairer",
        "motor",
        "engineer"
    ],
    "wof:name":"Mobil Car Care",
    "wof:placetype":"venue"
},
  "geometry": {"coordinates":[138.670578003,-34.6863822937],"type":"Point"}
}