{
  "type": "Feature",
  "properties": {
    "addr:full":"Hobart Bus Terminal 64 Brisbane St Hobart TAS 7000",
    "addr:housenumber":"64",
    "addr:postcode":"7000",
    "addr:street":"Brisbane St",
    "iso:country":"AU",
    "sg:address":"Hobart Bus Terminal 64 Brisbane St",
    "sg:city":"Hobart",
    "sg:classifiers":[
        {
            "category":"Communications",
            "subcategory":"News Services",
            "type":"Services"
        }
    ],
    "sg:phone":"+61 1300 300 520",
    "sg:postcode":"7000",
    "sg:province":"TAS",
    "sg:tags":[
        "information",
        "tourist",
        "attractions"
    ],
    "wof:name":"Tigerline Travel Tasmania",
    "wof:placetype":"venue"
},
  "geometry": {"coordinates":[147.32351684599999,-42.8795928955],"type":"Point"}
}