{
  "type": "Feature",
  "properties": {
    "iso:country":"AU",
    "sg:address":"6 Firebrace St",
    "sg:city":"Horsham",
    "sg:classifiers":[
        {
            "category":"Food & Beverages",
            "subcategory":"Bakery",
            "type":"Retail Goods"
        }
    ],
    "sg:phone":"+61 3 5382 1862",
    "sg:postcode":"3400",
    "sg:province":"VIC",
    "sg:tags":[
        "cake",
        "shop",
        "pastry"
    ],
    "wof:name":"Wimmera Cake Centre",
    "wof:placetype":"venue"
},
  "geometry": {"coordinates":[142.19953918499999,-36.7119483948],"type":"Point"}
}