{
  "type": "Feature",
  "properties": {
    "addr:full":"3 Pound St West Ipswich QLD 4305",
    "addr:housenumber":"3",
    "addr:postcode":"4305",
    "addr:street":"Pound St West",
    "iso:country":"AU",
    "sg:address":"3 Pound St",
    "sg:city":"West Ipswich",
    "sg:classifiers":[
        {
            "category":"Home & Garden",
            "subcategory":"Building Materials",
            "type":"Retail Goods"
        }
    ],
    "sg:phone":"+61 7 3812 0411",
    "sg:postcode":"4305",
    "sg:province":"QLD",
    "sg:tags":[
        "plaster",
        "plasterboard",
        "supply"
    ],
    "wof:name":"Boral Plasterboard",
    "wof:placetype":"venue"
},
  "geometry": {"coordinates":[152.75004577600001,-27.6216087341],"type":"Point"}
}