{
  "type": "Feature",
  "properties": {
    "iso:country":"AU",
    "sg:address":"208 Macquarie St",
    "sg:city":"Liverpool",
    "sg:classifiers":[
        {
            "category":"Food & Beverages",
            "subcategory":"Bakery",
            "type":"Retail Goods"
        }
    ],
    "sg:phone":"+61 2 9601 6588",
    "sg:postcode":"2170",
    "sg:province":"NSW",
    "sg:tags":[
        "cake",
        "shop",
        "pastry"
    ],
    "wof:name":"Cle`de Sol Patisserie & Cafe",
    "wof:placetype":"venue"
},
  "geometry": {"coordinates":[150.923904419,-33.9224853516],"type":"Point"}
}