{
  "type": "Feature",
  "properties": {
    "addr:full":"1011 Doncaster Rd Doncaster East VIC 3109",
    "addr:housenumber":"1011",
    "addr:postcode":"3109",
    "addr:street":"Doncaster Rd",
    "iso:country":"AU",
    "sg:address":"1011 Doncaster Rd",
    "sg:city":"Doncaster East",
    "sg:classifiers":[
        {
            "category":"Real Estate",
            "subcategory":"Developer",
            "type":"Services"
        }
    ],
    "sg:phone":"+61 3 9894 5400",
    "sg:postcode":"3109",
    "sg:province":"VIC",
    "sg:tags":[
        "development"
    ],
    "wof:name":"QLA Development Company Pty Ltd",
    "wof:placetype":"venue"
},
  "geometry": {"coordinates":[145.16027832,-37.7890014648],"type":"Point"}
}