{
  "type": "Feature",
  "properties": {
    "addr:full":"4 Lenaro St Dandenong VIC 3175",
    "addr:housenumber":"4",
    "addr:postcode":"3175",
    "addr:street":"Lenaro St",
    "iso:country":"AU",
    "sg:address":"4 Lenaro St",
    "sg:city":"Dandenong",
    "sg:classifiers":[
        {
            "category":"Professional",
            "subcategory":"Computer Services",
            "type":"Services"
        }
    ],
    "sg:phone":"+61 3 9706 9362",
    "sg:postcode":"3175",
    "sg:province":"VIC",
    "sg:tags":[
        "package",
        "software"
    ],
    "wof:name":"Artemidia Software",
    "wof:placetype":"venue"
},
  "geometry": {"coordinates":[145.20631408700001,-38.0000038147],"type":"Point"}
}