{
  "type": "Feature",
  "properties": {
    "addr:full":"Cnr Darby, Tooke & Brooks Sts Newcastle NSW 2300",
    "addr:postcode":"2300",
    "addr:street":"Cnr Darby",
    "iso:country":"AU",
    "sg:address":"Cnr Darby, Tooke & Brooks Sts",
    "sg:city":"Newcastle",
    "sg:classifiers":[
        {
            "category":"Health Services",
            "subcategory":"Health Practitioner",
            "type":"Services"
        }
    ],
    "sg:phone":"+61 2 4929 6411",
    "sg:postcode":"2300",
    "sg:province":"NSW",
    "sg:tags":[
        "physiotherapist"
    ],
    "wof:name":"Reid Melissa",
    "wof:placetype":"venue"
},
  "geometry": {"coordinates":[151.76980599999999,-32.937469],"type":"Point"}
}