{
  "type": "Feature",
  "properties": {
    "addr:full":"Level3/ 405 Little Bourke St Melbourne VIC 3000",
    "addr:housenumber":"/ 405",
    "addr:postcode":"3000",
    "addr:street":"Little Bourke St",
    "iso:country":"AU",
    "sg:address":"Level3/ 405 Little Bourke St",
    "sg:city":"Melbourne",
    "sg:classifiers":[
        {
            "category":"Banks & Credit Unions",
            "subcategory":"Investment Brokerage",
            "type":"Services"
        }
    ],
    "sg:phone":"+61 3 9670 9541",
    "sg:postcode":"3000",
    "sg:province":"VIC",
    "sg:tags":[
        "debt",
        "collection"
    ],
    "wof:name":"Credit Consultants Group Pty Ltd",
    "wof:placetype":"venue"
},
  "geometry": {"coordinates":[144.961013794,-37.8138885498],"type":"Point"}
}