{
  "type": "Feature",
  "properties": {
    "addr:full":"Unit 2/ 101 President St Welshpool WA 6106",
    "addr:housenumber":"/ 101",
    "addr:postcode":"6106",
    "addr:street":"President St",
    "iso:country":"AU",
    "sg:address":"Unit 2/ 101 President St",
    "sg:city":"Welshpool",
    "sg:classifiers":[
        {
            "category":"Retail",
            "subcategory":"Auto Repair",
            "type":"Services"
        }
    ],
    "sg:phone":"+61 8 9472 1575",
    "sg:postcode":"6106",
    "sg:province":"WA",
    "sg:tags":[
        "repairer",
        "motor",
        "engineer"
    ],
    "wof:name":"Allens Automotive Services Pty Ltd",
    "wof:placetype":"venue"
},
  "geometry": {"coordinates":[115.929298401,-31.9843883514],"type":"Point"}
}