{
  "type": "Feature",
  "properties": {
    "addr:full":"Meamder Valley Hwy Carrick TAS 7291",
    "addr:postcode":"7291",
    "addr:street":"Valley Hwy",
    "iso:country":"AU",
    "sg:address":"Meamder Valley Hwy",
    "sg:city":"Carrick",
    "sg:classifiers":[
        {
            "category":"Restaurant",
            "type":"Food & Drink"
        }
    ],
    "sg:phone":"+61 3 6393 6143",
    "sg:postcode":"7291",
    "sg:province":"TAS",
    "wof:name":"Carrick Inn",
    "wof:placetype":"venue"
},
  "geometry": {"coordinates":[147.014404297,-41.5297012329],"type":"Point"}
}