{
  "type": "Feature",
  "properties": {
    "iso:country":"AU",
    "sg:address":"1594 Beaudesert-Beenleigh Rd",
    "sg:city":"Tamborine",
    "sg:classifiers":[
        {
            "category":"Autos & Motor Vehicles",
            "subcategory":"Automobile Sales",
            "type":"Retail Goods"
        }
    ],
    "sg:phone":"+61 7 5546 4414",
    "sg:postcode":"4270",
    "sg:province":"QLD",
    "sg:tags":[
        "equipment",
        "trailer"
    ],
    "wof:name":"Sumoto Pty Ltd",
    "wof:placetype":"venue"
},
  "geometry": {"coordinates":[153.14552307100001,-27.8728713989],"type":"Point"}
}