{
  "type": "Feature",
  "properties": {
    "iso:country":"AU",
    "sg:address":"36 Industrial Drv",
    "sg:city":"Ulverstone",
    "sg:classifiers":[
        {
            "category":"Wholesale",
            "subcategory":"Machinery & Supplies",
            "type":"Manufacturing & Wholesale Goods"
        }
    ],
    "sg:phone":"+61 3 6425 5533",
    "sg:postcode":"7315",
    "sg:province":"TAS",
    "sg:tags":[
        "agricultural"
    ],
    "wof:name":"Dobsons Vegetable Machinery Pty Ltd",
    "wof:placetype":"venue"
},
  "geometry": {"coordinates":[146.204025269,-41.1582756042],"type":"Point"}
}