{
  "type": "Feature",
  "properties": {
    "iso:country":"AU",
    "sg:address":"Shop 2, The Village Walk, 493 Toorak Rd",
    "sg:city":"Toorak",
    "sg:classifiers":[
        {
            "category":"Personal",
            "subcategory":"Beauty Salon",
            "type":"Services"
        }
    ],
    "sg:phone":"+61 3 9826 0204",
    "sg:postcode":"3142",
    "sg:province":"VIC",
    "wof:name":"The Beauty Experts",
    "wof:placetype":"venue"
},
  "geometry": {"coordinates":[145.00944519000001,-37.8409996033],"type":"Point"}
}