{
  "type": "Feature",
  "properties": {
    "iso:country":"AU",
    "sg:address":"3/ 168 Lonsdale St",
    "sg:city":"Melbourne",
    "sg:classifiers":[
        {
            "category":"Professional",
            "subcategory":"Business Services",
            "type":"Services"
        }
    ],
    "sg:phone":"+61 3 9662 2722",
    "sg:postcode":"3000",
    "sg:province":"VIC",
    "sg:tags":[
        "consultant",
        "promoter",
        "entertainment"
    ],
    "wof:name":"Antipodes Festival",
    "wof:placetype":"venue"
},
  "geometry": {"coordinates":[144.96737670900001,-37.8106498718],"type":"Point"}
}