{
  "type": "Feature",
  "properties": {
    "iso:country":"AU",
    "sg:address":"13 Sir John Overall Drv",
    "sg:city":"Helensvale",
    "sg:classifiers":[
        {
            "category":"Real Estate",
            "subcategory":"Real Estate Agent",
            "type":"Services"
        }
    ],
    "sg:phone":"+61 7 5529 7155",
    "sg:postcode":"4212",
    "sg:province":"QLD",
    "wof:name":"Ray White- Helensvale",
    "wof:placetype":"venue"
},
  "geometry": {"coordinates":[153.33534240700001,-27.9225635529],"type":"Point"}
}