{
  "type": "Feature",
  "properties": {
    "addr:full":"8 Goodall St Wellington Point QLD 4160",
    "addr:housenumber":"8",
    "addr:postcode":"4160",
    "addr:street":"Goodall St",
    "iso:country":"AU",
    "sg:address":"8 Goodall St",
    "sg:city":"Wellington Point",
    "sg:classifiers":[
        {
            "category":"Professional",
            "subcategory":"Business Services",
            "type":"Services"
        }
    ],
    "sg:phone":"+61 7 3822 3128",
    "sg:postcode":"4160",
    "sg:province":"QLD",
    "sg:tags":[
        "drafting"
    ],
    "wof:name":"Bronwyn & Rod Cuskelly",
    "wof:placetype":"venue"
},
  "geometry": {"coordinates":[153.23538207999999,-27.4997425079],"type":"Point"}
}