{
  "type": "Feature",
  "properties": {
    "addr:full":"PO Box 324 Carrick TAS 7291",
    "addr:postcode":"7291",
    "iso:country":"AU",
    "sg:address":"PO Box 324",
    "sg:city":"Carrick",
    "sg:classifiers":[
        {
            "category":"Building & Trades",
            "subcategory":"Landscaping Services",
            "type":"Services"
        }
    ],
    "sg:phone":"+61 3 6393 7001",
    "sg:postcode":"7291",
    "sg:province":"TAS",
    "sg:tags":[
        "fertilizer",
        "spreading",
        "insecticide"
    ],
    "wof:name":"Altrac Spreading Tasmania",
    "wof:placetype":"venue"
},
  "geometry": {"coordinates":[147.02217102,-41.5416793823],"type":"Point"}
}