{
  "type": "Feature",
  "properties": {
    "iso:country":"AU",
    "sg:address":"738 Main Rd",
    "sg:city":"Edgeworth",
    "sg:classifiers":[
        {
            "category":"Autos & Motor Vehicles",
            "subcategory":"Fuel & Gas Station",
            "type":"Retail Goods"
        }
    ],
    "sg:phone":"+61 2 4965 8262",
    "sg:postcode":"2285",
    "sg:province":"NSW",
    "wof:name":"Mobil Oil Aust Pty Ltd",
    "wof:placetype":"venue"
},
  "geometry": {"coordinates":[151.62396240199999,-32.9445037842],"type":"Point"}
}