{
  "type": "Feature",
  "properties": {
    "iso:country":"AU",
    "sg:address":"8 Macedon Rd",
    "sg:city":"Templestowe Lower",
    "sg:classifiers":[
        {
            "category":"Fast Food",
            "type":"Food & Drink"
        }
    ],
    "sg:phone":"+61 3 9852 1886",
    "sg:postcode":"3107",
    "sg:province":"VIC",
    "sg:tags":[
        "away",
        "take"
    ],
    "wof:name":"Macedon Fish Bowl",
    "wof:placetype":"venue"
},
  "geometry": {"coordinates":[145.11244201700001,-37.7729759216],"type":"Point"}
}