{
  "type": "Feature",
  "properties": {
    "iso:country":"AU",
    "sg:address":"2/ 32 Stephen Rd",
    "sg:city":"Dandenong",
    "sg:classifiers":[
        {
            "category":"Manufacturing",
            "subcategory":"Metals",
            "type":"Manufacturing & Wholesale Goods"
        }
    ],
    "sg:phone":"+61 3 9791 5828",
    "sg:postcode":"3175",
    "sg:province":"VIC",
    "sg:tags":[
        "fabricator",
        "aluminium"
    ],
    "wof:name":"T & B Racecraft",
    "wof:placetype":"venue"
},
  "geometry": {"coordinates":[145.213165283,-38.0078163147],"type":"Point"}
}