{
  "type": "Feature",
  "properties": {
    "addr:full":"180 Marian Rd Glynde SA 5070",
    "addr:housenumber":"180",
    "addr:postcode":"5070",
    "addr:street":"Marian Rd",
    "iso:country":"AU",
    "sg:address":"180 Marian Rd",
    "sg:city":"Glynde",
    "sg:classifiers":[
        {
            "category":"Professional",
            "subcategory":"Art Services",
            "type":"Services"
        }
    ],
    "sg:phone":"+61 8 8365 6544",
    "sg:postcode":"5070",
    "sg:province":"SA",
    "sg:tags":[
        "graphic",
        "designer"
    ],
    "wof:name":"Graphity",
    "wof:placetype":"venue"
},
  "geometry": {"coordinates":[138.65655517600001,-34.9008369446],"type":"Point"}
}