{
  "type": "Feature",
  "properties": {
    "iso:country":"AU",
    "sg:address":"PO Box 482",
    "sg:city":"Bentley PLB",
    "sg:classifiers":[
        {
            "category":"Professional",
            "type":"Services"
        }
    ],
    "sg:phone":"+61 418 927 745",
    "sg:postcode":"6982",
    "sg:province":"WA",
    "sg:tags":[
        "transport"
    ],
    "wof:name":"R & L Hiab Services",
    "wof:placetype":"venue"
},
  "geometry": {"coordinates":[115.918983,-32.001781],"type":"Point"}
}