{
  "type": "Feature",
  "properties": {
    "addr:full":"Cnr Wharf & Macrossan St Port Douglas QLD 4877",
    "addr:postcode":"4877",
    "addr:street":"Cnr;St",
    "iso:country":"AU",
    "sg:address":"Cnr Wharf & Macrossan St",
    "sg:city":"Port Douglas",
    "sg:classifiers":[
        {
            "category":"Restaurant",
            "type":"Food & Drink"
        }
    ],
    "sg:phone":"+61 7 4099 6100",
    "sg:postcode":"4877",
    "sg:province":"QLD",
    "wof:name":"Bistro 3 Port Douglas",
    "wof:placetype":"venue"
},
  "geometry": {"coordinates":[145.46182250999999,-16.4836177826],"type":"Point"}
}