{
  "type": "Feature",
  "properties": {
    "iso:country":"AU",
    "sg:address":"Webb Rd",
    "sg:city":"Wongaling Beach",
    "sg:classifiers":[
        {
            "category":"Education",
            "subcategory":"School",
            "type":"Public Place"
        }
    ],
    "sg:phone":"+61 7 4088 8333",
    "sg:postcode":"4852",
    "sg:province":"QLD",
    "sg:tags":[
        "state",
        "except",
        "nsw"
    ],
    "wof:name":"Mission Beach Primary School",
    "wof:placetype":"venue"
},
  "geometry": {"coordinates":[146.09388732900001,-17.9046916962],"type":"Point"}
}