{
  "type": "Feature",
  "properties": {
    "addr:full":"3 Nambucca St Turramurra NSW 2074",
    "addr:housenumber":"3",
    "addr:postcode":"2074",
    "addr:street":"Nambucca St",
    "iso:country":"AU",
    "sg:address":"3 Nambucca St",
    "sg:city":"Turramurra",
    "sg:classifiers":[
        {
            "category":"Professional",
            "subcategory":"Management & Consulting",
            "type":"Services"
        }
    ],
    "sg:phone":"+61 2 9988 0001",
    "sg:postcode":"2074",
    "sg:province":"NSW",
    "sg:tags":[
        "consultant"
    ],
    "wof:name":"Buker Australasia Pty Ltd",
    "wof:placetype":"venue"
},
  "geometry": {"coordinates":[151.140136719,-33.7220077515],"type":"Point"}
}