{
  "type": "Feature",
  "properties": {
    "addr:full":"453 High St Preston VIC 3072",
    "addr:housenumber":"453",
    "addr:postcode":"3072",
    "addr:street":"High St",
    "iso:country":"AU",
    "sg:address":"453 High St",
    "sg:city":"Preston",
    "sg:classifiers":[
        {
            "category":"Health Services",
            "subcategory":"Optometrist",
            "type":"Services"
        }
    ],
    "sg:phone":"+61 3 9470 4444",
    "sg:postcode":"3072",
    "sg:province":"VIC",
    "wof:name":"Klidis Nick",
    "wof:placetype":"venue"
},
  "geometry": {"coordinates":[145.00372314399999,-37.7386131287],"type":"Point"}
}