{
  "type": "Feature",
  "properties": {
    "addr:full":"Unit 5/ 101 Motivation Drv Wangara WA 6065",
    "addr:housenumber":"/ 101",
    "addr:postcode":"6065",
    "addr:street":"Motivation Drv",
    "iso:country":"AU",
    "sg:address":"Unit 5/ 101 Motivation Drv",
    "sg:city":"Wangara",
    "sg:classifiers":[
        {
            "category":"Utilities",
            "subcategory":"Electric",
            "type":"Services"
        }
    ],
    "sg:phone":"+61 8 9302 3233",
    "sg:postcode":"6065",
    "sg:province":"WA",
    "sg:tags":[
        "electrical",
        "contractor"
    ],
    "wof:name":"West Coast Electrical Service",
    "wof:placetype":"venue"
},
  "geometry": {"coordinates":[115.837120056,-31.7913799286],"type":"Point"}
}