{
  "type": "Feature",
  "properties": {
    "addr:full":"77 Station St Fairfield VIC 3078",
    "addr:housenumber":"77",
    "addr:postcode":"3078",
    "addr:street":"Station St",
    "iso:country":"AU",
    "sg:address":"77 Station St",
    "sg:city":"Fairfield",
    "sg:classifiers":[
        {
            "category":"Retail",
            "subcategory":"Auto Repair",
            "type":"Services"
        }
    ],
    "sg:phone":"+61 3 9482 5833",
    "sg:postcode":"3078",
    "sg:province":"VIC",
    "sg:tags":[
        "repairer",
        "motor",
        "engineer"
    ],
    "wof:name":"B.M. Replacements",
    "wof:placetype":"venue"
},
  "geometry": {"coordinates":[145.01817321799999,-37.779838562],"type":"Point"}
}