{
  "type": "Feature",
  "properties": {
    "iso:country":"AU",
    "sg:address":"207b Garden St",
    "sg:city":"Warriewood",
    "sg:classifiers":[
        {
            "category":"Sports & Exercise",
            "subcategory":"Gym",
            "type":"Entertainment"
        }
    ],
    "sg:phone":"+61 2 9999 2208",
    "sg:postcode":"2102",
    "sg:province":"NSW",
    "sg:tags":[
        "health",
        "fitness"
    ],
    "wof:name":"Action Purchaser",
    "wof:placetype":"venue"
},
  "geometry": {"coordinates":[151.28982500000001,-33.686729],"type":"Point"}
}