{
  "type": "Feature",
  "properties": {
    "addr:full":"Sports Med West Building 116 Macquarie St Parramatta NSW 2150",
    "addr:housenumber":"116",
    "addr:postcode":"2150",
    "addr:street":"Macquarie St",
    "iso:country":"AU",
    "sg:address":"Sports Med West Building 116 Macquarie St",
    "sg:city":"Parramatta",
    "sg:classifiers":[
        {
            "category":"Health Services",
            "subcategory":"Health Practitioner",
            "type":"Services"
        }
    ],
    "sg:phone":"+61 2 9687 1511",
    "sg:postcode":"2150",
    "sg:province":"NSW",
    "sg:tags":[
        "physiotherapist"
    ],
    "wof:name":"Matthew Stewart",
    "wof:placetype":"venue"
},
  "geometry": {"coordinates":[151.05824279800001,-33.9097175598],"type":"Point"}
}