{
  "type": "Feature",
  "properties": {
    "addr:full":"23 Ogilvie Ave Echuca VIC 3564",
    "addr:housenumber":"23",
    "addr:postcode":"3564",
    "addr:street":"Ogilvie Ave",
    "iso:country":"AU",
    "sg:address":"23 Ogilvie Ave",
    "sg:city":"Echuca",
    "sg:classifiers":[
        {
            "category":"Retail",
            "subcategory":"Auto Rental",
            "type":"Services"
        }
    ],
    "sg:phone":"+61 3 5482 5233",
    "sg:postcode":"3564",
    "sg:province":"VIC",
    "sg:tags":[
        "bus",
        "truck"
    ],
    "wof:name":"Budget",
    "wof:placetype":"venue"
},
  "geometry": {"coordinates":[144.74827575699999,-36.1404953003],"type":"Point"}
}