{
  "type": "Feature",
  "properties": {
    "addr:full":"2 Levanswell Rd Moorabbin VIC 3189",
    "addr:housenumber":"2",
    "addr:postcode":"3189",
    "addr:street":"Levanswell Rd",
    "iso:country":"AU",
    "sg:address":"2 Levanswell Rd",
    "sg:city":"Moorabbin",
    "sg:classifiers":[
        {
            "category":"Retail",
            "subcategory":"Auto Repair",
            "type":"Services"
        }
    ],
    "sg:phone":"+61 3 9555 8648",
    "sg:postcode":"3189",
    "sg:province":"VIC",
    "sg:tags":[
        "beater",
        "painter",
        "panel"
    ],
    "wof:name":"Levanswell Panels",
    "wof:placetype":"venue"
},
  "geometry": {"coordinates":[145.060012817,-37.9441986084],"type":"Point"}
}