{
  "type": "Feature",
  "properties": {
    "addr:full":"3 Eaglesfield St Beaudesert QLD 4285",
    "addr:housenumber":"3",
    "addr:postcode":"4285",
    "addr:street":"Eaglesfield St",
    "iso:country":"AU",
    "sg:address":"3 Eaglesfield St",
    "sg:city":"Beaudesert",
    "sg:classifiers":[
        {
            "category":"Personal",
            "subcategory":"Beauty Salon",
            "type":"Services"
        }
    ],
    "sg:phone":"+61 400 589 369",
    "sg:postcode":"4285",
    "sg:province":"QLD",
    "sg:tags":[
        "hairdresser"
    ],
    "wof:name":"Alley Hairdesigns",
    "wof:placetype":"venue"
},
  "geometry": {"coordinates":[152.99704,-27.98662],"type":"Point"}
}