{
  "type": "Feature",
  "properties": {
    "addr:full":"71 Dampier Ave City Beach WA 6015",
    "addr:housenumber":"71",
    "addr:postcode":"6015",
    "addr:street":"Dampier Ave",
    "iso:country":"AU",
    "sg:address":"71 Dampier Ave",
    "sg:city":"City Beach",
    "sg:classifiers":[
        {
            "category":"Structure",
            "subcategory":"Office Building",
            "type":"Public Place"
        }
    ],
    "sg:phone":"+61 408 841 229",
    "sg:postcode":"6015",
    "sg:province":"WA",
    "sg:tags":[
        "slater",
        "tiler",
        "roof"
    ],
    "wof:name":"Great Slate Roofing (W.A.)",
    "wof:placetype":"venue"
},
  "geometry": {"coordinates":[115.759567261,-31.9302616119],"type":"Point"}
}