{
  "type": "Feature",
  "properties": {
    "iso:country":"AU",
    "sg:address":"Victoria St",
    "sg:city":"Cardwell",
    "sg:classifiers":[
        {
            "category":"Autos & Motor Vehicles",
            "subcategory":"Fuel & Gas Station",
            "type":"Retail Goods"
        }
    ],
    "sg:phone":"+61 7 4066 8690",
    "sg:postcode":"4849",
    "sg:province":"QLD",
    "wof:name":"BP Australia Limited",
    "wof:placetype":"venue"
},
  "geometry": {"coordinates":[146.01870700000001,-18.25754],"type":"Point"}
}