{
  "type": "Feature",
  "properties": {
    "addr:full":"46 Raffan Rd Honeywood TAS 7017",
    "addr:housenumber":"46",
    "addr:postcode":"7017",
    "addr:street":"Raffan Rd",
    "iso:country":"AU",
    "sg:address":"46 Raffan Rd",
    "sg:city":"Honeywood",
    "sg:classifiers":[
        {
            "category":"Professional",
            "subcategory":"Detective & Security Services",
            "type":"Services"
        }
    ],
    "sg:phone":"+61 3 6268 1937",
    "sg:postcode":"7017",
    "sg:province":"TAS",
    "sg:tags":[
        "consultant",
        "system"
    ],
    "wof:name":"Atkinson Security",
    "wof:placetype":"venue"
},
  "geometry": {"coordinates":[147.29139709500001,-42.7256317139],"type":"Point"}
}