{
  "type": "Feature",
  "properties": {
    "addr:full":"703 - 705 Sturt St Ballarat VIC 3350",
    "addr:housenumber":"705",
    "addr:postcode":"3350",
    "addr:street":"Sturt St",
    "iso:country":"AU",
    "sg:address":"703 - 705 Sturt St",
    "sg:city":"Ballarat",
    "sg:classifiers":[
        {
            "category":"Shopping",
            "subcategory":"Jewelry",
            "type":"Retail Goods"
        }
    ],
    "sg:phone":"+61 3 5332 3480",
    "sg:postcode":"3350",
    "sg:province":"VIC",
    "sg:tags":[
        "jeweller"
    ],
    "wof:name":"Karington Jewelry",
    "wof:placetype":"venue"
},
  "geometry": {"coordinates":[143.85008199999999,-37.561359],"type":"Point"}
}