{
  "type": "Feature",
  "properties": {
    "addr:full":"8 Hayward Pde Coogee WA 6166",
    "addr:housenumber":"8",
    "addr:postcode":"6166",
    "addr:street":"Hayward Pde",
    "iso:country":"AU",
    "sg:address":"8 Hayward Pde",
    "sg:city":"Coogee",
    "sg:classifiers":[
        {
            "category":"Retail",
            "subcategory":"Driving School",
            "type":"Services"
        }
    ],
    "sg:phone":"+61 8 9434 3623",
    "sg:postcode":"6166",
    "sg:province":"WA",
    "wof:name":"Pats Driving School",
    "wof:placetype":"venue"
},
  "geometry": {"coordinates":[115.771423,-32.117058],"type":"Point"}
}