{
  "type": "Feature",
  "properties": {
    "iso:country":"AU",
    "sg:address":"Cnr Queens Rd & Walker St",
    "sg:city":"Canada Bay",
    "sg:classifiers":[
        {
            "category":"Education",
            "subcategory":"School",
            "type":"Public Place"
        }
    ],
    "sg:phone":"+61 2 9744 6461",
    "sg:postcode":"2046",
    "sg:province":"NSW",
    "wof:name":"Lucas Special School",
    "wof:placetype":"venue"
},
  "geometry": {"coordinates":[151.12887599999999,-33.870548],"type":"Point"}
}