{
  "type": "Feature",
  "properties": {
    "addr:full":"184 Hay St Kalgoorlie WA 6430",
    "addr:housenumber":"184",
    "addr:postcode":"6430",
    "addr:street":"Hay St",
    "iso:country":"AU",
    "sg:address":"184 Hay St",
    "sg:city":"Kalgoorlie",
    "sg:classifiers":[
        {
            "category":"Retail",
            "subcategory":"Repair Shop",
            "type":"Services"
        }
    ],
    "sg:phone":"+61 8 9091 7460",
    "sg:postcode":"6430",
    "sg:province":"WA",
    "sg:tags":[
        "windscreen"
    ],
    "wof:name":"Kalgoorlie Windscreen Service",
    "wof:placetype":"venue"
},
  "geometry": {"coordinates":[121.465270996,-30.751958847],"type":"Point"}
}