{
  "type": "Feature",
  "properties": {
    "addr:full":"PO Box 2368 Richmond South VIC 3121",
    "addr:postcode":"3121",
    "iso:country":"AU",
    "sg:address":"PO Box 2368",
    "sg:city":"Richmond South",
    "sg:classifiers":[
        {
            "category":"Wholesale",
            "subcategory":"Machinery & Supplies",
            "type":"Manufacturing & Wholesale Goods"
        }
    ],
    "sg:phone":"+61 3 9853 9886",
    "sg:postcode":"3121",
    "sg:province":"VIC",
    "sg:tags":[
        "machine",
        "tool",
        "engineer"
    ],
    "wof:name":"Auswede Mte Pty Ltd",
    "wof:placetype":"venue"
},
  "geometry": {"coordinates":[145.00822448700001,-37.8229217529],"type":"Point"}
}