{
  "type": "Feature",
  "properties": {
    "addr:full":"4 Vichers St Parap NT 0820",
    "addr:housenumber":"4",
    "addr:postcode":"nt 0820",
    "addr:street":"Vichers St",
    "iso:country":"AU",
    "sg:address":"4 Vichers St",
    "sg:city":"Parap",
    "sg:classifiers":[
        {
            "category":"Government",
            "subcategory":"Post Office",
            "type":"Public Place"
        }
    ],
    "sg:phone":"+61 8 8981 5896",
    "sg:postcode":"0820",
    "sg:province":"NT",
    "sg:tags":[
        "postal"
    ],
    "wof:name":"Australia Post",
    "wof:placetype":"venue"
},
  "geometry": {"coordinates":[130.84461975100001,-12.4308662415],"type":"Point"}
}