{
  "type": "Feature",
  "properties": {
    "iso:country":"AU",
    "sg:address":"110 Old Hereford Rd",
    "sg:city":"Mt Evelyn",
    "sg:classifiers":[
        {
            "category":"Building & Trades",
            "subcategory":"Equipment Rental",
            "type":"Services"
        }
    ],
    "sg:phone":"+61 3 9736 1366",
    "sg:postcode":"3796",
    "sg:province":"VIC",
    "sg:tags":[
        "crane",
        "hire"
    ],
    "wof:name":"Ace Tree Management",
    "wof:placetype":"venue"
},
  "geometry": {"coordinates":[145.38064575199999,-37.7662696838],"type":"Point"}
}