{
  "type": "Feature",
  "properties": {
    "iso:country":"AU",
    "sg:address":"520 Pacific Hwy",
    "sg:city":"Wyoming",
    "sg:classifiers":[
        {
            "category":"Fast Food",
            "type":"Food & Drink"
        }
    ],
    "sg:phone":"+61 2 4328 2228",
    "sg:postcode":"2250",
    "sg:province":"NSW",
    "sg:tags":[
        "away",
        "take"
    ],
    "wof:name":"Dawn To Dusk",
    "wof:placetype":"venue"
},
  "geometry": {"coordinates":[151.35055542000001,-33.4049034119],"type":"Point"}
}