{
  "type": "Feature",
  "properties": {
    "iso:country":"AU",
    "sg:address":"Old Glen Innes Rd",
    "sg:city":"South Grafton",
    "sg:classifiers":[
        {
            "category":"Wholesale",
            "subcategory":"Auto Parts",
            "type":"Manufacturing & Wholesale Goods"
        }
    ],
    "sg:phone":"+61 2 6644 9353",
    "sg:postcode":"2460",
    "sg:province":"NSW",
    "sg:tags":[
        "recyclers"
    ],
    "wof:name":"Campbell Wrecking & Towing",
    "wof:placetype":"venue"
},
  "geometry": {"coordinates":[152.866897583,-29.6860351562],"type":"Point"}
}