{
  "type": "Feature",
  "properties": {
    "addr:full":"12 Redfern Cl Pambula NSW 2549",
    "addr:housenumber":"12",
    "addr:postcode":"2549",
    "addr:street":"Redfern Cl",
    "iso:country":"AU",
    "sg:address":"12 Redfern Cl",
    "sg:city":"Pambula",
    "sg:classifiers":[
        {
            "category":"Commercial Area",
            "type":"Public Place"
        }
    ],
    "sg:phone":"+61 2 6495 6733",
    "sg:postcode":"2549",
    "sg:province":"NSW",
    "sg:tags":[
        "heavy",
        "carrier"
    ],
    "wof:name":"Bobbins Transport",
    "wof:placetype":"venue"
},
  "geometry": {"coordinates":[149.84695434599999,-36.9444541931],"type":"Point"}
}