{
  "type": "Feature",
  "properties": {
    "addr:full":"Gympie Rd Petrie QLD 4502",
    "addr:postcode":"4502",
    "addr:street":"Gympie Rd",
    "iso:country":"AU",
    "sg:address":"Gympie Rd",
    "sg:city":"Petrie",
    "sg:classifiers":[
        {
            "category":"Wholesale",
            "subcategory":"Machinery & Supplies",
            "type":"Manufacturing & Wholesale Goods"
        }
    ],
    "sg:phone":"+61 7 3285 6066",
    "sg:postcode":"4502",
    "sg:province":"QLD",
    "sg:tags":[
        "agricultural"
    ],
    "wof:name":"North Pine Motors",
    "wof:placetype":"venue"
},
  "geometry": {"coordinates":[152.978347778,-27.2704658508],"type":"Point"}
}