{
  "type": "Feature",
  "properties": {
    "addr:full":"Suite 3, Level 1, 35 Main St Greensborough VIC 3088",
    "addr:housenumber":"35",
    "addr:postcode":"3088",
    "addr:street":"Main St",
    "iso:country":"AU",
    "sg:address":"Suite 3, Level 1, 35 Main St",
    "sg:city":"Greensborough",
    "sg:classifiers":[
        {
            "category":"Professional",
            "subcategory":"Computer Services",
            "type":"Services"
        }
    ],
    "sg:phone":"+61 3 9432 1400",
    "sg:postcode":"3088",
    "sg:province":"VIC",
    "sg:tags":[
        "package",
        "software"
    ],
    "wof:name":"Transacct Australia Pty Ltd",
    "wof:placetype":"venue"
},
  "geometry": {"coordinates":[145.10366821299999,-37.7035942078],"type":"Point"}
}