{
  "type": "Feature",
  "properties": {
    "addr:full":"132 Grange Rd Allenby Gardens SA 5009",
    "addr:housenumber":"132",
    "addr:postcode":"5009",
    "addr:street":"Grange Rd",
    "iso:country":"AU",
    "sg:address":"132 Grange Rd",
    "sg:city":"Allenby Gardens",
    "sg:classifiers":[
        {
            "category":"Food & Beverages",
            "subcategory":"Fruits & Vegetables",
            "type":"Retail Goods"
        }
    ],
    "sg:phone":"+61 8 8340 9868",
    "sg:postcode":"5009",
    "sg:province":"SA",
    "sg:tags":[
        "wholesale"
    ],
    "wof:name":"Fruitalicious",
    "wof:placetype":"venue"
},
  "geometry": {"coordinates":[138.553756714,-34.904510498],"type":"Point"}
}