{
  "type": "Feature",
  "properties": {
    "iso:country":"AU",
    "sg:address":"25 Pannamena Crs",
    "sg:city":"Eleebana",
    "sg:classifiers":[
        {
            "category":"Building & Trades",
            "subcategory":"Construction",
            "type":"Services"
        }
    ],
    "sg:phone":"+61 411 196 119",
    "sg:postcode":"2282",
    "sg:province":"NSW",
    "sg:tags":[
        "contractor"
    ],
    "wof:name":"Optum Constructions Pty Ltd",
    "wof:placetype":"venue"
},
  "geometry": {"coordinates":[151.63616943400001,-32.9896888733],"type":"Point"}
}