{
  "type": "Feature",
  "properties": {
    "addr:full":"3/ 324 Great Eastern Hwy Ascot WA 6104",
    "addr:housenumber":"/ 324",
    "addr:postcode":"6104",
    "addr:street":"Great Eastern Hwy",
    "iso:country":"AU",
    "sg:address":"3/ 324 Great Eastern Hwy",
    "sg:city":"Ascot",
    "sg:classifiers":[
        {
            "category":"Professional",
            "subcategory":"Employment Agencies",
            "type":"Services"
        }
    ],
    "sg:phone":"+61 8 9477 7777",
    "sg:postcode":"6104",
    "sg:province":"WA",
    "sg:tags":[
        "hire",
        "labour",
        "contractor"
    ],
    "wof:name":"QFS Australia Pty Ltd",
    "wof:placetype":"venue"
},
  "geometry": {"coordinates":[115.945579529,-31.9293365479],"type":"Point"}
}