{
  "type": "Feature",
  "properties": {
    "iso:country":"AU",
    "sg:address":"Shp 17/ 3 Melton Hwy",
    "sg:city":"Taylors Lakes",
    "sg:classifiers":[
        {
            "category":"Education",
            "subcategory":"Vocational School",
            "type":"Public Place"
        }
    ],
    "sg:phone":"+61 3 9390 7200",
    "sg:postcode":"3038",
    "sg:province":"VIC",
    "sg:tags":[
        "beauty"
    ],
    "wof:name":"Vivid Nail & Beaute",
    "wof:placetype":"venue"
},
  "geometry": {"coordinates":[144.800323,-37.701912],"type":"Point"}
}