{
  "type": "Feature",
  "properties": {
    "iso:country":"AU",
    "sg:address":"Brickport Rd",
    "sg:city":"Cooee",
    "sg:classifiers":[
        {
            "category":"Wholesale",
            "subcategory":"Machinery & Supplies",
            "type":"Manufacturing & Wholesale Goods"
        }
    ],
    "sg:phone":"+61 3 6431 3255",
    "sg:postcode":"7320",
    "sg:province":"TAS",
    "sg:tags":[
        "agricultural"
    ],
    "wof:name":"Tasmania Farm Equipment Pty Ltd",
    "wof:placetype":"venue"
},
  "geometry": {"coordinates":[145.87797499999999,-41.043526],"type":"Point"}
}