{
  "type": "Feature",
  "properties": {
    "addr:full":"95 Alma St Maryborough VIC 3465",
    "addr:housenumber":"95",
    "addr:postcode":"3465",
    "addr:street":"Alma St",
    "iso:country":"AU",
    "sg:address":"95 Alma St",
    "sg:city":"Maryborough",
    "sg:classifiers":[
        {
            "category":"Personal",
            "subcategory":"Beauty Salon",
            "type":"Services"
        }
    ],
    "sg:phone":"+61 3 5461 2084",
    "sg:postcode":"3465",
    "sg:province":"VIC",
    "sg:tags":[
        "hairdresser"
    ],
    "wof:name":"Pascoe's Hairdressing Salon",
    "wof:placetype":"venue"
},
  "geometry": {"coordinates":[143.737747192,-37.0474815369],"type":"Point"}
}