{
  "type": "Feature",
  "properties": {
    "addr:full":"16 Deanne Crt Caboolture QLD 4510",
    "addr:housenumber":"16",
    "addr:postcode":"4510",
    "addr:street":"Deanne Crt",
    "iso:country":"AU",
    "sg:address":"16 Deanne Crt",
    "sg:city":"Caboolture",
    "sg:classifiers":[
        {
            "category":"Professional",
            "subcategory":"Advertising",
            "type":"Services"
        }
    ],
    "sg:phone":"+61 7 5495 3812",
    "sg:postcode":"4510",
    "sg:province":"QLD",
    "sg:tags":[
        "balloon",
        "novelty"
    ],
    "wof:name":"Adorable Balloon Bouquets",
    "wof:placetype":"venue"
},
  "geometry": {"coordinates":[152.940033,-27.095251],"type":"Point"}
}