{
  "type": "Feature",
  "properties": {
    "iso:country":"AU",
    "sg:address":"2 Lakeshore Drv",
    "sg:city":"North Avoca",
    "sg:classifiers":[
        {
            "category":"Building & Trades",
            "subcategory":"Landscaping Services",
            "type":"Services"
        }
    ],
    "sg:phone":"+61 2 4384 6846",
    "sg:postcode":"2260",
    "sg:province":"NSW",
    "sg:tags":[
        "consultant"
    ],
    "wof:name":"Coastal Pole Homes Pty Ltd",
    "wof:placetype":"venue"
},
  "geometry": {"coordinates":[151.430222,-33.458088],"type":"Point"}
}