{
  "type": "Feature",
  "properties": {
    "iso:country":"AU",
    "sg:address":"10- 12 Wenvoe St",
    "sg:city":"Devonport",
    "sg:classifiers":[
        {
            "category":"Organizations",
            "subcategory":"Professional Association",
            "type":"Services"
        }
    ],
    "sg:phone":"+61 3 6424 5885",
    "sg:postcode":"7310",
    "sg:province":"TAS",
    "sg:tags":[
        "web",
        "internet"
    ],
    "wof:name":"H W Inprint Pty Ltd",
    "wof:placetype":"venue"
},
  "geometry": {"coordinates":[146.34860229500001,-41.1798057556],"type":"Point"}
}