{
  "type": "Feature",
  "properties": {
    "addr:full":"Shop 102/ 412 George St Sydney NSW 2000",
    "addr:housenumber":"102 / 412",
    "addr:postcode":"2000",
    "addr:street":"George St",
    "iso:country":"AU",
    "sg:address":"Shop 102/ 412 George St",
    "sg:city":"Sydney",
    "sg:classifiers":[
        {
            "category":"Personal",
            "subcategory":"Tanning Parlor",
            "type":"Services"
        }
    ],
    "sg:phone":"+61 2 9232 2000",
    "sg:postcode":"2000",
    "sg:province":"NSW",
    "sg:tags":[
        "solarium"
    ],
    "wof:name":"Body Bronze Strand Arcade",
    "wof:placetype":"venue"
},
  "geometry": {"coordinates":[151.207122803,-33.8694114685],"type":"Point"}
}