{
  "type": "Feature",
  "properties": {
    "addr:full":"Oxley Station Rd Oxley QLD 4075",
    "addr:postcode":"4075",
    "addr:street":"Station Rd",
    "iso:country":"AU",
    "sg:address":"Oxley Station Rd",
    "sg:city":"Oxley",
    "sg:classifiers":[
        {
            "category":"Personal",
            "subcategory":"Nail Salon",
            "type":"Services"
        }
    ],
    "sg:phone":"+61 417 769 716",
    "sg:postcode":"4075",
    "sg:province":"QLD",
    "sg:tags":[
        "artificial"
    ],
    "wof:name":"Antonias Nails",
    "wof:placetype":"venue"
},
  "geometry": {"coordinates":[152.974243164,-27.5534973145],"type":"Point"}
}