{
  "type": "Feature",
  "properties": {
    "iso:country":"AU",
    "sg:address":"8 Stuart St",
    "sg:city":"Bulimba",
    "sg:classifiers":[
        {
            "category":"Professional",
            "subcategory":"Art Services",
            "type":"Services"
        }
    ],
    "sg:phone":"+61 7 3899 5680",
    "sg:postcode":"4171",
    "sg:province":"QLD",
    "sg:tags":[
        "interior",
        "decorator"
    ],
    "wof:name":"Oxford Interiors",
    "wof:placetype":"venue"
},
  "geometry": {"coordinates":[153.05848693900001,-27.4516029358],"type":"Point"}
}