{
  "type": "Feature",
  "properties": {
    "iso:country":"AU",
    "sg:address":"PO Box 334",
    "sg:city":"Mandurah",
    "sg:classifiers":[
        {
            "category":"Building & Trades",
            "subcategory":"Construction",
            "type":"Services"
        }
    ],
    "sg:phone":"+61 8 9534 3993",
    "sg:postcode":"6210",
    "sg:province":"WA",
    "sg:tags":[
        "contractor"
    ],
    "wof:name":"Dolphin Building Service",
    "wof:placetype":"venue"
},
  "geometry": {"coordinates":[115.784737,-32.509258],"type":"Point"}
}