{
  "type": "Feature",
  "properties": {
    "addr:full":"Ewingsdale Rd Byron Bay NSW 2481",
    "addr:postcode":"2481",
    "addr:street":"Ewingsdale Rd",
    "iso:country":"AU",
    "sg:address":"Ewingsdale Rd",
    "sg:city":"Byron Bay",
    "sg:classifiers":[
        {
            "category":"Personal",
            "type":"Services"
        }
    ],
    "sg:phone":"+61 2 6685 7559",
    "sg:postcode":"2481",
    "sg:province":"NSW",
    "sg:tags":[
        "counselling",
        "alcohol",
        "drug"
    ],
    "wof:name":"Al-Anon",
    "wof:placetype":"venue"
},
  "geometry": {"coordinates":[153.59930419899999,-28.6383285522],"type":"Point"}
}