{
  "type": "Feature",
  "properties": {
    "iso:country":"AU",
    "sg:address":"29 David St",
    "sg:city":"Rockville",
    "sg:classifiers":[
        {
            "category":"Banks & Credit Unions",
            "subcategory":"Investment Brokerage",
            "type":"Services"
        }
    ],
    "sg:phone":"+61 7 4634 8982",
    "sg:postcode":"4350",
    "sg:province":"QLD",
    "sg:tags":[
        "finance",
        "broker"
    ],
    "wof:name":"Wise Financial Solutions",
    "wof:placetype":"venue"
},
  "geometry": {"coordinates":[151.93691999999999,-27.531202],"type":"Point"}
}