{
  "type": "Feature",
  "properties": {
    "addr:full":"19 Austin Ave North Curl Curl NSW 2099",
    "addr:housenumber":"19",
    "addr:postcode":"2099",
    "addr:street":"Austin Ave North",
    "iso:country":"AU",
    "sg:address":"19 Austin Ave",
    "sg:city":"North Curl Curl",
    "sg:classifiers":[
        {
            "category":"Building & Trades",
            "subcategory":"Landscaping Services",
            "type":"Services"
        }
    ],
    "sg:phone":"+61 2 9905 7870",
    "sg:postcode":"2099",
    "sg:province":"NSW",
    "sg:tags":[
        "designer",
        "landscape",
        "contractor"
    ],
    "wof:name":"Space Landscape Designs",
    "wof:placetype":"venue"
},
  "geometry": {"coordinates":[151.29887390100001,-33.7621078491],"type":"Point"}
}