{
  "type": "Feature",
  "properties": {
    "addr:full":"Beaumaris City Shopping Centre Shop 7/ 168 Constellation Drv Ocean Reef WA 6027",
    "addr:housenumber":"shop 7 / 168",
    "addr:postcode":"6027",
    "addr:street":"Constellation Drv",
    "iso:country":"AU",
    "sg:address":"Beaumaris City Shopping Centre Shop 7/ 168 Constellation Drv",
    "sg:city":"Ocean Reef",
    "sg:classifiers":[
        {
            "category":"Government",
            "subcategory":"Post Office",
            "type":"Public Place"
        }
    ],
    "sg:phone":"+61 8 9300 4420",
    "sg:postcode":"6027",
    "sg:province":"WA",
    "sg:tags":[
        "postal"
    ],
    "wof:name":"Australia Post",
    "wof:placetype":"venue"
},
  "geometry": {"coordinates":[115.732971191,-31.7506599426],"type":"Point"}
}