{
  "type": "Feature",
  "properties": {
    "iso:country":"AU",
    "sg:address":"15-19 Galli Crt",
    "sg:city":"Dandenong South",
    "sg:classifiers":[
        {
            "category":"Building & Trades",
            "subcategory":"Construction",
            "type":"Services"
        }
    ],
    "sg:phone":"+61 3 9799 3622",
    "sg:postcode":"3175",
    "sg:province":"VIC",
    "sg:tags":[
        "rigging",
        "erection",
        "contractor"
    ],
    "wof:name":"Aus Truestyle Pty Ltd",
    "wof:placetype":"venue"
},
  "geometry": {"coordinates":[145.238815308,-38.0316162109],"type":"Point"}
}