{
  "type": "Feature",
  "properties": {
    "iso:country":"AU",
    "sg:address":"19 Lang Pde",
    "sg:city":"Milton",
    "sg:classifiers":[
        {
            "category":"Communications",
            "type":"Services"
        }
    ],
    "sg:phone":"+61 7 3871 8000",
    "sg:postcode":"4064",
    "sg:province":"QLD",
    "sg:tags":[
        "equipment",
        "radio"
    ],
    "wof:name":"TV NZ Australia",
    "wof:placetype":"venue"
},
  "geometry": {"coordinates":[153.001754761,-27.4740123749],"type":"Point"}
}