{
  "type": "Feature",
  "properties": {
    "addr:full":"Riddell Rd Wantirna South VIC 3152",
    "addr:postcode":"3152",
    "addr:street":"Riddell Rd",
    "iso:country":"AU",
    "sg:address":"Riddell Rd",
    "sg:city":"Wantirna South",
    "sg:classifiers":[
        {
            "category":"Education",
            "subcategory":"Kindergarten",
            "type":"Public Place"
        }
    ],
    "sg:phone":"+61 3 9800 1945",
    "sg:postcode":"3152",
    "sg:province":"VIC",
    "sg:tags":[
        "pre-schools"
    ],
    "wof:name":"Riddell Rd Pre-School Incorporated",
    "wof:placetype":"venue"
},
  "geometry": {"coordinates":[145.243865967,-37.8775367737],"type":"Point"}
}