{
  "type": "Feature",
  "properties": {
    "addr:full":"13- 16 Warratah St Sutherland NSW 1499",
    "addr:housenumber":"16",
    "addr:postcode":"1499",
    "addr:street":"Warratah St",
    "iso:country":"AU",
    "sg:address":"13- 16 Warratah St",
    "sg:city":"Sutherland",
    "sg:classifiers":[
        {
            "category":"Autos & Motor Vehicles",
            "subcategory":"Auto Supplies",
            "type":"Retail Goods"
        }
    ],
    "sg:phone":"+61 2 9545 1888",
    "sg:postcode":"1499",
    "sg:province":"NSW",
    "sg:tags":[
        "tyre"
    ],
    "wof:name":"Tyresplus Sutherland",
    "wof:placetype":"venue"
},
  "geometry": {"coordinates":[151.07742300000001,-33.975948],"type":"Point"}
}