{
  "type": "Feature",
  "properties": {
    "addr:full":"16 Undine St Maroubra NSW 2035",
    "addr:housenumber":"16",
    "addr:postcode":"2035",
    "addr:street":"Undine St",
    "iso:country":"AU",
    "sg:address":"16 Undine St",
    "sg:city":"Maroubra",
    "sg:classifiers":[
        {
            "category":"Professional",
            "subcategory":"Accounting & Tax Preparation",
            "type":"Services"
        }
    ],
    "sg:phone":"+61 412 355 364",
    "sg:postcode":"2035",
    "sg:province":"NSW",
    "sg:tags":[
        "accountant",
        "auditor"
    ],
    "wof:name":"Jack Lawrence Consulting",
    "wof:placetype":"venue"
},
  "geometry": {"coordinates":[151.26173400900001,-33.9401931763],"type":"Point"}
}