{
  "type": "Feature",
  "properties": {
    "iso:country":"AU",
    "sg:address":"Kukerin South Rd",
    "sg:city":"Kukerin",
    "sg:classifiers":[
        {
            "category":"Farming",
            "subcategory":"Farm",
            "type":"Manufacturing & Wholesale Goods"
        }
    ],
    "sg:phone":"+61 8 9864 6068",
    "sg:postcode":"6352",
    "sg:province":"WA",
    "sg:tags":[
        "farmer"
    ],
    "wof:name":"Gray K J & J M",
    "wof:placetype":"venue"
},
  "geometry": {"coordinates":[118.101128,-33.214325],"type":"Point"}
}