{
  "type": "Feature",
  "properties": {
    "addr:full":"65 Young St Ayr QLD 4807",
    "addr:housenumber":"65",
    "addr:postcode":"4807",
    "addr:street":"Young St",
    "iso:country":"AU",
    "sg:address":"65 Young St",
    "sg:city":"Ayr",
    "sg:classifiers":[
        {
            "category":"Utilities",
            "subcategory":"Water",
            "type":"Services"
        }
    ],
    "sg:phone":"+61 7 4783 1630",
    "sg:postcode":"4807",
    "sg:province":"QLD",
    "sg:tags":[
        "cartage"
    ],
    "wof:name":"Polga A G & L D",
    "wof:placetype":"venue"
},
  "geometry": {"coordinates":[147.39617919899999,-19.5688304901],"type":"Point"}
}