{
  "type": "Feature",
  "properties": {
    "iso:country":"AU",
    "sg:address":"130 Lygon St",
    "sg:city":"Brunswick East",
    "sg:classifiers":[
        {
            "category":"Cafe",
            "type":"Food & Drink"
        }
    ],
    "sg:phone":"+61 3 9381 2244",
    "sg:postcode":"3057",
    "sg:province":"VIC",
    "wof:name":"Small Block",
    "wof:placetype":"venue"
},
  "geometry": {"coordinates":[144.97140502900001,-37.7741928101],"type":"Point"}
}