{
  "type": "Feature",
  "properties": {
    "addr:full":"Shop 2 Elizabeth Mall Elizabeth St Hobart TAS 7000",
    "addr:housenumber":"shop 2",
    "addr:postcode":"7000",
    "addr:street":"Elizabeth Mall Elizabeth St",
    "iso:country":"AU",
    "sg:address":"Shop 2 Elizabeth Mall Elizabeth St",
    "sg:city":"Hobart",
    "sg:classifiers":[
        {
            "category":"Shopping",
            "subcategory":"Clothing, Apparel, & Fashions",
            "type":"Retail Goods"
        }
    ],
    "sg:phone":"+61 3 6236 9617",
    "sg:postcode":"7000",
    "sg:province":"TAS",
    "sg:tags":[
        "jean"
    ],
    "wof:name":"Jay Jay's",
    "wof:placetype":"venue"
},
  "geometry": {"coordinates":[147.31666564899999,-42.874168396],"type":"Point"}
}