{
  "type": "Feature",
  "properties": {
    "iso:country":"AU",
    "sg:address":"54 Gordon Ave",
    "sg:city":"Hamilton",
    "sg:classifiers":[
        {
            "category":"Fast Food",
            "type":"Food & Drink"
        }
    ],
    "sg:phone":"+61 2 4969 8238",
    "sg:postcode":"2303",
    "sg:province":"NSW",
    "sg:tags":[
        "away",
        "take"
    ],
    "wof:name":"Tucker Box Corner Store",
    "wof:placetype":"venue"
},
  "geometry": {"coordinates":[151.751053,-32.925552],"type":"Point"}
}