{
  "type": "Feature",
  "properties": {
    "iso:country":"AU",
    "sg:address":"10 Broadway",
    "sg:city":"Nedlands",
    "sg:classifiers":[
        {
            "category":"Professional",
            "subcategory":"Art Services",
            "type":"Services"
        }
    ],
    "sg:phone":"+61 8 9386 5528",
    "sg:postcode":"6009",
    "sg:province":"WA",
    "sg:tags":[
        "interior",
        "decorator"
    ],
    "sg:website":"http://www.curtainlady.com.au",
    "wof:name":"Curtain Lady Interiors",
    "wof:placetype":"venue"
},
  "geometry": {"coordinates":[115.814148,-31.977707],"type":"Point"}
}