{
  "type": "Feature",
  "properties": {
    "addr:full":"52a Lower Coast Rd Stanwell Park NSW 2508",
    "addr:housenumber":"52a",
    "addr:postcode":"2508",
    "addr:street":"Lower Coast Rd",
    "iso:country":"AU",
    "sg:address":"52a Lower Coast Rd",
    "sg:city":"Stanwell Park",
    "sg:classifiers":[
        {
            "category":"Building & Trades",
            "subcategory":"Landscaping Services",
            "type":"Services"
        }
    ],
    "sg:phone":"+61 2 4294 2929",
    "sg:postcode":"2508",
    "sg:province":"NSW",
    "sg:tags":[
        "designer",
        "landscape",
        "contractor"
    ],
    "wof:name":"Barrett Stephen R & Associates",
    "wof:placetype":"venue"
},
  "geometry": {"coordinates":[150.98634300000001,-34.233097],"type":"Point"}
}