{
  "type": "Feature",
  "properties": {
    "iso:country":"AU",
    "sg:address":"69 Kromes Rd",
    "sg:city":"Yandina",
    "sg:classifiers":[
        {
            "category":"Building & Trades",
            "subcategory":"Construction",
            "type":"Services"
        }
    ],
    "sg:phone":"+61 7 5472 7365",
    "sg:postcode":"4561",
    "sg:province":"QLD",
    "sg:tags":[
        "fencing",
        "contractor"
    ],
    "wof:name":"Sunshine Coast Fencing Specialists",
    "wof:placetype":"venue"
},
  "geometry": {"coordinates":[152.92828369099999,-26.5121936798],"type":"Point"}
}