{
  "type": "Feature",
  "properties": {
    "addr:full":"Level 1 16 Welch St Southport QLD 4215",
    "addr:housenumber":"16",
    "addr:postcode":"4215",
    "addr:street":"Welch St",
    "iso:country":"AU",
    "sg:address":"Level 1 16 Welch St",
    "sg:city":"Southport",
    "sg:classifiers":[
        {
            "category":"Organizations",
            "subcategory":"Non-profit Organization",
            "type":"Services"
        }
    ],
    "sg:phone":"+61 7 5531 1877",
    "sg:postcode":"4215",
    "sg:province":"QLD",
    "sg:tags":[
        "environmental",
        "organisation",
        "conservation"
    ],
    "wof:name":"Environment Education Association",
    "wof:placetype":"venue"
},
  "geometry": {"coordinates":[153.41328430199999,-27.9644298553],"type":"Point"}
}