{
  "type": "Feature",
  "properties": {
    "addr:full":"4 Mann Pl Higgins ACT 2615",
    "addr:housenumber":"4",
    "addr:postcode":"2615",
    "addr:street":"Mann Pl Higgins",
    "iso:country":"AU",
    "sg:address":"4 Mann Pl",
    "sg:city":"Higgins",
    "sg:classifiers":[
        {
            "category":"Building & Trades",
            "subcategory":"Construction",
            "type":"Services"
        }
    ],
    "sg:phone":"+61 2 6254 8240",
    "sg:postcode":"2615",
    "sg:province":"ACT",
    "sg:tags":[
        "management"
    ],
    "wof:name":"Encore Construction Services",
    "wof:placetype":"venue"
},
  "geometry": {"coordinates":[149.032592773,-35.23487854],"type":"Point"}
}