{
  "type": "Feature",
  "properties": {
    "iso:country":"AU",
    "sg:address":"PO Box 330",
    "sg:city":"Kellyville",
    "sg:classifiers":[
        {
            "category":"Shopping",
            "subcategory":"Stationery & Office Supplies",
            "type":"Retail Goods"
        }
    ],
    "sg:phone":"+61 2 9899 5333",
    "sg:postcode":"2155",
    "sg:province":"NSW",
    "sg:tags":[
        "equipment",
        "facsimile"
    ],
    "wof:name":"Sydney Office Equipment",
    "wof:placetype":"venue"
},
  "geometry": {"coordinates":[150.95611572300001,-33.7114982605],"type":"Point"}
}