{
  "type": "Feature",
  "properties": {
    "iso:country":"AU",
    "sg:address":"700 Mooreville Rd",
    "sg:city":"Ridgley",
    "sg:classifiers":[
        {
            "category":"Farming",
            "subcategory":"Farm",
            "type":"Manufacturing & Wholesale Goods"
        }
    ],
    "sg:phone":"+61 3 6435 7250",
    "sg:postcode":"7321",
    "sg:province":"TAS",
    "sg:tags":[
        "farmer"
    ],
    "wof:name":"White P M",
    "wof:placetype":"venue"
},
  "geometry": {"coordinates":[145.835587,-41.093807],"type":"Point"}
}