{
  "type": "Feature",
  "properties": {
    "iso:country":"AU",
    "sg:address":"157 Racecourse Rd",
    "sg:city":"Flemington",
    "sg:classifiers":[
        {
            "category":"Professional",
            "subcategory":"Art Services",
            "type":"Services"
        }
    ],
    "sg:phone":"+61 421 542 945",
    "sg:postcode":"3031",
    "sg:province":"VIC",
    "sg:tags":[
        "decorator",
        "painter"
    ],
    "wof:name":"Flemington Painting Service",
    "wof:placetype":"venue"
},
  "geometry": {"coordinates":[144.936111,-37.788834],"type":"Point"}
}