{
  "type": "Feature",
  "properties": {
    "iso:country":"AU",
    "sg:address":"Springhill Rd",
    "sg:city":"Wollongong",
    "sg:classifiers":[
        {
            "category":"Banks & Credit Unions",
            "subcategory":"Bank",
            "type":"Services"
        }
    ],
    "sg:phone":"+61 2 4275 6988",
    "sg:postcode":"2500",
    "sg:province":"NSW",
    "wof:name":"Lysaght Credit Union",
    "wof:placetype":"venue"
},
  "geometry": {"coordinates":[150.89738500000001,-34.436981],"type":"Point"}
}