{
  "type": "Feature",
  "properties": {
    "addr:full":"Shop 18 Whitsunday Shopping Centre Cannonvale QLD 4802",
    "addr:housenumber":"shop 18",
    "addr:postcode":"4802",
    "addr:street":"Whitsunday Shopping",
    "iso:country":"AU",
    "sg:address":"Shop 18 Whitsunday Shopping Centre",
    "sg:city":"Cannonvale",
    "sg:classifiers":[
        {
            "category":"Banks & Credit Unions",
            "subcategory":"Financial Services",
            "type":"Services"
        }
    ],
    "sg:phone":"+61 7 4946 8893",
    "sg:postcode":"4802",
    "sg:province":"QLD",
    "sg:tags":[
        "advisory",
        "planning",
        "retirement"
    ],
    "wof:name":"Count Wealth Accountants",
    "wof:placetype":"venue"
},
  "geometry": {"coordinates":[148.69070434599999,-20.280090332],"type":"Point"}
}