{
  "type": "Feature",
  "properties": {
    "addr:full":"21/ 152 Musgrave Rd Red Hill QLD 4059",
    "addr:housenumber":"21 / 152",
    "addr:postcode":"4059",
    "addr:street":"Musgrave Rd",
    "iso:country":"AU",
    "sg:address":"21/ 152 Musgrave Rd",
    "sg:city":"Red Hill",
    "sg:classifiers":[
        {
            "category":"Health Services",
            "subcategory":"Health Practitioner",
            "type":"Services"
        }
    ],
    "sg:phone":"+61 410 294 274",
    "sg:postcode":"4059",
    "sg:province":"QLD",
    "sg:tags":[
        "psychologist"
    ],
    "wof:name":"Robertson Samantha",
    "wof:placetype":"venue"
},
  "geometry": {"coordinates":[153.00668335,-27.454328537],"type":"Point"}
}