{
  "type": "Feature",
  "properties": {
    "addr:full":"Factory 9 166 Bridge Rd Keysborough VIC 3173",
    "addr:housenumber":"166",
    "addr:postcode":"3173",
    "addr:street":"Bridge Rd",
    "iso:country":"AU",
    "sg:address":"Factory 9 166 Bridge Rd",
    "sg:city":"Keysborough",
    "sg:classifiers":[
        {
            "category":"Home & Garden",
            "subcategory":"Building Materials",
            "type":"Retail Goods"
        }
    ],
    "sg:phone":"+61 3 9701 8333",
    "sg:postcode":"3173",
    "sg:province":"VIC",
    "sg:tags":[
        "gate"
    ],
    "wof:name":"Artkon Wrought Iron Industries Pty Ltd",
    "wof:placetype":"venue"
},
  "geometry": {"coordinates":[145.1925354,-37.9844932556],"type":"Point"}
}