{
  "type": "Feature",
  "properties": {
    "iso:country":"AU",
    "sg:address":"Castledoyle Rd",
    "sg:city":"Armidale",
    "sg:classifiers":[
        {
            "category":"Professional",
            "subcategory":"Engineering",
            "type":"Services"
        }
    ],
    "sg:phone":"+61 2 6775 3796",
    "sg:postcode":"2350",
    "sg:province":"NSW",
    "sg:tags":[
        "engineer",
        "designing"
    ],
    "wof:name":"Raoul Design Engineering",
    "wof:placetype":"venue"
},
  "geometry": {"coordinates":[151.74809265100001,-30.5849304199],"type":"Point"}
}