{
  "type": "Feature",
  "properties": {
    "addr:full":"981 Hay St Perth WA 6000",
    "addr:housenumber":"981",
    "addr:postcode":"6000",
    "addr:street":"Hay St",
    "iso:country":"AU",
    "sg:address":"981 Hay St",
    "sg:city":"Perth",
    "sg:classifiers":[
        {
            "category":"Shopping",
            "subcategory":"Clothing, Apparel, & Fashions",
            "type":"Retail Goods"
        }
    ],
    "sg:phone":"+61 8 9321 3693",
    "sg:postcode":"6000",
    "sg:province":"WA",
    "sg:tags":[
        "hire",
        "men's",
        "wear",
        "formal"
    ],
    "sg:website":"http://www.penguinsformalwear.com",
    "wof:name":"Penguins Formal Suit Hire",
    "wof:placetype":"venue"
},
  "geometry": {"coordinates":[115.849479675,-31.9512386322],"type":"Point"}
}