{
  "type": "Feature",
  "properties": {
    "addr:full":"79 Grandview St Pymble NSW 2073",
    "addr:housenumber":"79",
    "addr:postcode":"2073",
    "addr:street":"Grandview St",
    "iso:country":"AU",
    "sg:address":"79 Grandview St",
    "sg:city":"Pymble",
    "sg:classifiers":[
        {
            "category":"Fast Food",
            "type":"Food & Drink"
        }
    ],
    "sg:phone":"+61 2 9144 1952",
    "sg:postcode":"2073",
    "sg:province":"NSW",
    "sg:tags":[
        "away",
        "take"
    ],
    "wof:name":"Pymble Gourmet Foods",
    "wof:placetype":"venue"
},
  "geometry": {"coordinates":[151.14251709000001,-33.7444877625],"type":"Point"}
}