{
  "type": "Feature",
  "properties": {
    "addr:full":"100 Marquis St Gunnedah NSW 2380",
    "addr:housenumber":"100",
    "addr:postcode":"2380",
    "addr:street":"Marquis St",
    "iso:country":"AU",
    "sg:address":"100 Marquis St",
    "sg:city":"Gunnedah",
    "sg:classifiers":[
        {
            "category":"Banks & Credit Unions",
            "subcategory":"Investment Brokerage",
            "type":"Services"
        }
    ],
    "sg:phone":"+61 2 6742 6677",
    "sg:postcode":"2380",
    "sg:province":"NSW",
    "sg:tags":[
        "management",
        "property"
    ],
    "wof:name":"Lakeford Real Estate",
    "wof:placetype":"venue"
},
  "geometry": {"coordinates":[150.257522583,-30.9802150726],"type":"Point"}
}