{
  "type": "Feature",
  "properties": {
    "addr:full":"637 Pacific Hwy Killara NSW 2071",
    "addr:housenumber":"637",
    "addr:postcode":"2071",
    "addr:street":"Pacific Hwy",
    "iso:country":"AU",
    "sg:address":"637 Pacific Hwy",
    "sg:city":"Killara",
    "sg:classifiers":[
        {
            "category":"Professional",
            "subcategory":"Computer Services",
            "type":"Services"
        }
    ],
    "sg:phone":"+61 2 9499 6565",
    "sg:postcode":"2071",
    "sg:province":"NSW",
    "sg:tags":[
        "package",
        "software"
    ],
    "wof:name":"Network Micro Systems Pty Ltd",
    "wof:placetype":"venue"
},
  "geometry": {"coordinates":[151.15687560999999,-33.7643432617],"type":"Point"}
}