{
  "type": "Feature",
  "properties": {
    "addr:full":"64 Birdwood St Box Hill South VIC 3128",
    "addr:housenumber":"64",
    "addr:postcode":"3128",
    "addr:street":"Birdwood St",
    "iso:country":"AU",
    "sg:address":"64 Birdwood St",
    "sg:city":"Box Hill South",
    "sg:classifiers":[
        {
            "category":"Building & Trades",
            "subcategory":"Landscaping Services",
            "type":"Services"
        }
    ],
    "sg:phone":"+61 409 184 782",
    "sg:postcode":"3128",
    "sg:province":"VIC",
    "sg:tags":[
        "gardener"
    ],
    "wof:name":"Nita Garden Services",
    "wof:placetype":"venue"
},
  "geometry": {"coordinates":[145.12469482399999,-37.8356628418],"type":"Point"}
}