{
  "type": "Feature",
  "properties": {
    "iso:country":"AU",
    "sg:address":"1 Perry St",
    "sg:city":"Batemans Bay",
    "sg:classifiers":[
        {
            "category":"Food & Beverages",
            "subcategory":"Specialty",
            "type":"Retail Goods"
        }
    ],
    "sg:phone":"+61 2 4472 2002",
    "sg:postcode":"2536",
    "sg:province":"NSW",
    "sg:tags":[
        "product",
        "health"
    ],
    "wof:name":"Healthy Life",
    "wof:placetype":"venue"
},
  "geometry": {"coordinates":[150.17637634299999,-35.7070083618],"type":"Point"}
}