{
  "type": "Feature",
  "properties": {
    "addr:full":"22 Campbell Pde Bondi NSW 2026",
    "addr:housenumber":"22",
    "addr:postcode":"2026",
    "addr:street":"Campbell Pde",
    "iso:country":"AU",
    "sg:address":"22 Campbell Pde",
    "sg:city":"Bondi",
    "sg:classifiers":[
        {
            "category":"Food & Beverages",
            "subcategory":"Groceries & Convenience Stores",
            "type":"Retail Goods"
        }
    ],
    "sg:phone":"+61 2 9130 8322",
    "sg:postcode":"2026",
    "sg:province":"NSW",
    "wof:name":"Bondi Beach Convenient Store",
    "wof:placetype":"venue"
},
  "geometry": {"coordinates":[151.273040772,-33.8944282532],"type":"Point"}
}