{
  "type": "Feature",
  "properties": {
    "iso:country":"AU",
    "sg:address":"3/ 8 Marmion Rd",
    "sg:city":"Abbotsford",
    "sg:classifiers":[
        {
            "category":"Building & Trades",
            "subcategory":"Construction",
            "type":"Services"
        }
    ],
    "sg:phone":"+61 433 114 557",
    "sg:postcode":"2046",
    "sg:province":"NSW",
    "sg:tags":[
        "contractor"
    ],
    "wof:name":"Painting Illusions",
    "wof:placetype":"venue"
},
  "geometry": {"coordinates":[151.12886,-33.846119],"type":"Point"}
}