{
  "type": "Feature",
  "properties": {
    "addr:full":"30a Cunningham St Sale VIC 3850",
    "addr:housenumber":"30a",
    "addr:postcode":"3850",
    "addr:street":"Cunningham St",
    "iso:country":"AU",
    "sg:address":"30a Cunningham St",
    "sg:city":"Sale",
    "sg:classifiers":[
        {
            "category":"Health Services",
            "subcategory":"Health Practitioner",
            "type":"Services"
        }
    ],
    "sg:phone":"+61 3 5144 1044",
    "sg:postcode":"3850",
    "sg:province":"VIC",
    "sg:tags":[
        "psychologist"
    ],
    "wof:name":"Petrina Howlings - Psychologist",
    "wof:placetype":"venue"
},
  "geometry": {"coordinates":[147.05984497099999,-38.1076278687],"type":"Point"}
}