{
  "type": "Feature",
  "properties": {
    "addr:full":"2 Rose St Ivanhoe VIC 3079",
    "addr:housenumber":"2",
    "addr:postcode":"3079",
    "addr:street":"Rose St",
    "iso:country":"AU",
    "sg:address":"2 Rose St",
    "sg:city":"Ivanhoe",
    "sg:classifiers":[
        {
            "category":"Health Services",
            "subcategory":"Health Practitioner",
            "type":"Services"
        }
    ],
    "sg:phone":"+61 3 9380 4444",
    "sg:postcode":"3079",
    "sg:province":"VIC",
    "sg:tags":[
        "psychologist"
    ],
    "wof:name":"Life Resolutions",
    "wof:placetype":"venue"
},
  "geometry": {"coordinates":[145.04010009800001,-37.773979187],"type":"Point"}
}