{
  "type": "Feature",
  "properties": {
    "addr:full":"8 Carl Crt Hallam VIC 3803",
    "addr:housenumber":"8",
    "addr:postcode":"3803",
    "addr:street":"Carl Crt",
    "iso:country":"AU",
    "sg:address":"8 Carl Crt",
    "sg:city":"Hallam",
    "sg:classifiers":[
        {
            "category":"Professional",
            "subcategory":"Engineering",
            "type":"Services"
        }
    ],
    "sg:phone":"+61 3 9702 4255",
    "sg:postcode":"3803",
    "sg:province":"VIC",
    "sg:tags":[
        "electronic",
        "engineer"
    ],
    "wof:name":"Bryford Pty Ltd T/As DJ Electronics",
    "wof:placetype":"venue"
},
  "geometry": {"coordinates":[145.26771545400001,-38.0090675354],"type":"Point"}
}