{
  "type": "Feature",
  "properties": {
    "iso:country":"AU",
    "sg:address":"37 The Corso",
    "sg:city":"Manly",
    "sg:classifiers":[
        {
            "category":"Health Services",
            "subcategory":"Health Practitioner",
            "type":"Services"
        }
    ],
    "sg:phone":"+61 2 9977 4979",
    "sg:postcode":"2095",
    "sg:province":"NSW",
    "sg:tags":[
        "alternative"
    ],
    "wof:name":"Peninsula Spinology",
    "wof:placetype":"venue"
},
  "geometry": {"coordinates":[151.286056519,-33.7967338562],"type":"Point"}
}