{
  "type": "Feature",
  "properties": {
    "addr:full":"74 Austin St Hopetoun VIC 3396",
    "addr:housenumber":"74",
    "addr:postcode":"3396",
    "addr:street":"Austin St",
    "iso:country":"AU",
    "sg:address":"74 Austin St",
    "sg:city":"Hopetoun",
    "sg:classifiers":[
        {
            "category":"Cafe",
            "type":"Food & Drink"
        }
    ],
    "sg:phone":"+61 3 5083 3082",
    "sg:postcode":"3396",
    "sg:province":"VIC",
    "wof:name":"Bon Bon Cafe",
    "wof:placetype":"venue"
},
  "geometry": {"coordinates":[142.367645264,-35.7259635925],"type":"Point"}
}