{
  "type": "Feature",
  "properties": {
    "iso:country":"AU",
    "sg:address":"27 Bowen St",
    "sg:city":"Prahran",
    "sg:classifiers":[
        {
            "category":"Organizations",
            "subcategory":"Professional Association",
            "type":"Services"
        }
    ],
    "sg:phone":"+61 417 052 126",
    "sg:postcode":"3181",
    "sg:province":"VIC",
    "sg:tags":[
        "web",
        "internet"
    ],
    "wof:name":"Word Design Interactive Pty Ltd",
    "wof:placetype":"venue"
},
  "geometry": {"coordinates":[145.00326538100001,-37.8548278809],"type":"Point"}
}