{
  "type": "Feature",
  "properties": {
    "addr:full":"Mount Terricks Rd Echuca VIC 3564",
    "addr:postcode":"3564",
    "addr:street":"Terricks Rd",
    "iso:country":"AU",
    "sg:address":"Mount Terricks Rd",
    "sg:city":"Echuca",
    "sg:classifiers":[
        {
            "category":"Professional",
            "type":"Services"
        }
    ],
    "sg:phone":"+61 408 505 928",
    "sg:postcode":"3564",
    "sg:province":"VIC",
    "sg:tags":[
        "transport"
    ],
    "wof:name":"Whites Transport Services",
    "wof:placetype":"venue"
},
  "geometry": {"coordinates":[144.72416687,-36.1294708252],"type":"Point"}
}