{
  "type": "Feature",
  "properties": {
    "addr:full":"26 Bruce Hwy Kybong QLD 4570",
    "addr:housenumber":"26",
    "addr:postcode":"4570",
    "addr:street":"Bruce Hwy",
    "iso:country":"AU",
    "sg:address":"26 Bruce Hwy",
    "sg:city":"Kybong",
    "sg:classifiers":[
        {
            "category":"Autos & Motor Vehicles",
            "subcategory":"Fuel & Gas Station",
            "type":"Retail Goods"
        }
    ],
    "sg:phone":"+61 7 5483 5153",
    "sg:postcode":"4570",
    "sg:province":"QLD",
    "wof:name":"Burmah Fuels Australia Ltd",
    "wof:placetype":"venue"
},
  "geometry": {"coordinates":[152.70585632300001,-26.2621860504],"type":"Point"}
}