{
  "type": "Feature",
  "properties": {
    "addr:full":"8/ 218 Macquarie Rd Warners Bay NSW 2282",
    "addr:housenumber":"/ 218",
    "addr:postcode":"2282",
    "addr:street":"Macquarie Rd",
    "iso:country":"AU",
    "sg:address":"8/ 218 Macquarie Rd",
    "sg:city":"Warners Bay",
    "sg:classifiers":[
        {
            "category":"Building & Trades",
            "subcategory":"Pest Control",
            "type":"Services"
        }
    ],
    "sg:phone":"+61 1800 010 630",
    "sg:postcode":"2282",
    "sg:province":"NSW",
    "wof:name":"Multi Pest Control",
    "wof:placetype":"venue"
},
  "geometry": {"coordinates":[151.65281677199999,-32.9658470154],"type":"Point"}
}