{
  "type": "Feature",
  "properties": {
    "addr:full":"PO Box 52 Bicheno TAS 7215",
    "addr:postcode":"7215",
    "iso:country":"AU",
    "sg:address":"PO Box 52",
    "sg:city":"Bicheno",
    "sg:classifiers":[
        {
            "category":"Building & Trades",
            "subcategory":"Construction",
            "type":"Services"
        }
    ],
    "sg:phone":"+61 3 6375 1299",
    "sg:postcode":"7215",
    "sg:province":"TAS",
    "sg:tags":[
        "contractor"
    ],
    "wof:name":"Burrows Wayne",
    "wof:placetype":"venue"
},
  "geometry": {"coordinates":[148.29963699999999,-41.88522],"type":"Point"}
}