{
  "type": "Feature",
  "properties": {
    "iso:country":"AU",
    "sg:address":"245 Whitehorse Road",
    "sg:city":"(Cnr Goodwin St) Nunawading",
    "sg:classifiers":[
        {
            "category":"Travel",
            "subcategory":"Hotels & Motels",
            "type":"Entertainment"
        }
    ],
    "sg:phone":"+61 3 9877 6511",
    "sg:postcode":"3131",
    "sg:province":"VIC",
    "sg:website":"http://www.nunawadingmotorinn.com.au",
    "wof:name":"Nunawading Motor Inn",
    "wof:placetype":"venue"
},
  "geometry": {"coordinates":[145.166549683,-37.8183898926],"type":"Point"}
}