{
  "type": "Feature",
  "properties": {
    "addr:full":"2 Campbell St Yarragon VIC 3823",
    "addr:housenumber":"2",
    "addr:postcode":"3823",
    "addr:street":"Campbell St",
    "iso:country":"AU",
    "sg:address":"2 Campbell St",
    "sg:city":"Yarragon",
    "sg:classifiers":[
        {
            "category":"Food & Beverages",
            "subcategory":"Supermarket",
            "type":"Retail Goods"
        }
    ],
    "sg:phone":"+61 3 5634 2774",
    "sg:postcode":"3823",
    "sg:province":"VIC",
    "sg:tags":[
        "grocery",
        "store"
    ],
    "wof:name":"Yarragon Village Supermarket",
    "wof:placetype":"venue"
},
  "geometry": {"coordinates":[146.06446800000001,-38.204159],"type":"Point"}
}