{
  "type": "Feature",
  "properties": {
    "addr:full":"3 Madison Pl Carina QLD 4152",
    "addr:housenumber":"3",
    "addr:postcode":"4152",
    "addr:street":"Madison Pl",
    "iso:country":"AU",
    "sg:address":"3 Madison Pl",
    "sg:city":"Carina",
    "sg:classifiers":[
        {
            "category":"Home & Garden",
            "subcategory":"Building Materials",
            "type":"Retail Goods"
        }
    ],
    "sg:phone":"+61 7 3843 0288",
    "sg:postcode":"4152",
    "sg:province":"QLD",
    "sg:tags":[
        "retaining",
        "wall"
    ],
    "wof:name":"Gavin Knudsen Landscapes",
    "wof:placetype":"venue"
},
  "geometry": {"coordinates":[153.089477539,-27.4814910889],"type":"Point"}
}