{
  "type": "Feature",
  "properties": {
    "addr:full":"677 North Rd Carnegie VIC 3163",
    "addr:housenumber":"677",
    "addr:postcode":"3163",
    "addr:street":"North Rd",
    "iso:country":"AU",
    "sg:address":"677 North Rd",
    "sg:city":"Carnegie",
    "sg:classifiers":[
        {
            "category":"Building & Trades",
            "subcategory":"Construction",
            "type":"Services"
        }
    ],
    "sg:phone":"+61 3 9578 7511",
    "sg:postcode":"3163",
    "sg:province":"VIC",
    "sg:tags":[
        "fencing",
        "contractor"
    ],
    "wof:name":"R & K Wrought Iron",
    "wof:placetype":"venue"
},
  "geometry": {"coordinates":[145.053588867,-37.9054908752],"type":"Point"}
}