{
  "type": "Feature",
  "properties": {
    "iso:country":"AU",
    "sg:address":"1 / 34 Premier Cct",
    "sg:city":"Warana",
    "sg:classifiers":[
        {
            "category":"Home & Garden",
            "subcategory":"Carpets & Floor Coverings",
            "type":"Retail Goods"
        }
    ],
    "sg:phone":"+61 7 5493 9255",
    "sg:postcode":"4575",
    "sg:province":"QLD",
    "sg:tags":[
        "tile",
        "wall"
    ],
    "wof:name":"Tiles 2 Go",
    "wof:placetype":"venue"
},
  "geometry": {"coordinates":[153.13076799999999,-26.719839],"type":"Point"}
}