{
  "type": "Feature",
  "properties": {
    "addr:full":"Shop 001-002, The Market Erina Fair, Kralta Rd Erina NSW 2250",
    "addr:housenumber":"001-002",
    "addr:postcode":"2250",
    "addr:street":"The Market;Kralta Rd",
    "iso:country":"AU",
    "sg:address":"Shop 001-002, The Market Erina Fair, Kralta Rd",
    "sg:city":"Erina",
    "sg:classifiers":[
        {
            "category":"Food & Beverages",
            "subcategory":"Fruits & Vegetables",
            "type":"Retail Goods"
        }
    ],
    "sg:phone":"+61 2 4367 2626",
    "sg:postcode":"2250",
    "sg:province":"NSW",
    "sg:tags":[
        "greengrocer",
        "fruiterer"
    ],
    "wof:name":"Harris Farm Markets",
    "wof:placetype":"venue"
},
  "geometry": {"coordinates":[151.347412109,-33.4256591797],"type":"Point"}
}