{
  "type": "Feature",
  "properties": {
    "addr:full":"PO Box 6859 Baulkham Hills BC NSW 1755",
    "addr:postcode":"nsw 1755",
    "iso:country":"AU",
    "sg:address":"PO Box 6859",
    "sg:city":"Baulkham Hills BC",
    "sg:classifiers":[
        {
            "category":"Building & Trades",
            "subcategory":"Construction",
            "type":"Services"
        }
    ],
    "sg:phone":"+61 417 423 364",
    "sg:postcode":"1755",
    "sg:province":"NSW",
    "sg:tags":[
        "contractor"
    ],
    "wof:name":"Davidson Aaron & Joanna",
    "wof:placetype":"venue"
},
  "geometry": {"coordinates":[150.975403,-33.761982],"type":"Point"}
}