{
  "type": "Feature",
  "properties": {
    "addr:full":"115 Darby St Cooks Hill NSW 2300",
    "addr:housenumber":"115",
    "addr:postcode":"2300",
    "addr:street":"Darby St",
    "iso:country":"AU",
    "sg:address":"115 Darby St",
    "sg:city":"Cooks Hill",
    "sg:classifiers":[
        {
            "category":"Conference Center",
            "type":"Public Place"
        }
    ],
    "sg:phone":"+61 2 4926 1100",
    "sg:postcode":"2300",
    "sg:province":"NSW",
    "sg:tags":[
        "venue",
        "convention"
    ],
    "wof:name":"L'incontro Italian Restaurant",
    "wof:placetype":"venue"
},
  "geometry": {"coordinates":[151.77130099999999,-32.931667],"type":"Point"}
}