{
  "type": "Feature",
  "properties": {
    "addr:full":"Cnr Pleasant & Fischer Sts Goonellabah NSW 2480",
    "addr:postcode":"2480",
    "addr:street":"Cnr",
    "iso:country":"AU",
    "sg:address":"Cnr Pleasant & Fischer Sts",
    "sg:city":"Goonellabah",
    "sg:classifiers":[
        {
            "category":"Personal",
            "subcategory":"Beauty Salon",
            "type":"Services"
        }
    ],
    "sg:phone":"+61 2 6625 2220",
    "sg:postcode":"2480",
    "sg:province":"NSW",
    "sg:tags":[
        "hairdresser"
    ],
    "wof:name":"Hairtique Studio",
    "wof:placetype":"venue"
},
  "geometry": {"coordinates":[153.31950378400001,-28.8194389343],"type":"Point"}
}