{
  "type": "Feature",
  "properties": {
    "addr:full":"276 Kanumbra-Gobur Rd Yarck VIC 3719",
    "addr:housenumber":"276",
    "addr:postcode":"3719",
    "addr:street":"Kanumbra-Gobur Rd",
    "iso:country":"AU",
    "sg:address":"276 Kanumbra-Gobur Rd",
    "sg:city":"Yarck",
    "sg:classifiers":[
        {
            "category":"Building & Trades",
            "subcategory":"Landscaping Services",
            "type":"Services"
        }
    ],
    "sg:phone":"+61 3 5773 4212",
    "sg:postcode":"3719",
    "sg:province":"VIC",
    "sg:tags":[
        "grazier"
    ],
    "wof:name":"Jones Worrall",
    "wof:placetype":"venue"
},
  "geometry": {"coordinates":[145.60963439899999,-37.0128822327],"type":"Point"}
}