{
  "type": "Feature",
  "properties": {
    "addr:full":"39 Chute St Diamond Creek VIC 3089",
    "addr:housenumber":"39",
    "addr:postcode":"3089",
    "addr:street":"Chute St",
    "iso:country":"AU",
    "sg:address":"39 Chute St",
    "sg:city":"Diamond Creek",
    "sg:classifiers":[
        {
            "category":"Banks & Credit Unions",
            "subcategory":"Investment Brokerage",
            "type":"Services"
        }
    ],
    "sg:phone":"+61 3 9438 3322",
    "sg:postcode":"3089",
    "sg:province":"VIC",
    "wof:name":"Yarra Consulting Group Pty Ltd",
    "wof:placetype":"venue"
},
  "geometry": {"coordinates":[145.15181000000001,-37.672756],"type":"Point"}
}