{
  "type": "Feature",
  "properties": {
    "iso:country":"AU",
    "sg:address":"55 Charlotte St",
    "sg:city":"Brisbane",
    "sg:classifiers":[
        {
            "category":"Retail",
            "subcategory":"Auto Rental",
            "type":"Services"
        }
    ],
    "sg:phone":"+61 7 3221 6166",
    "sg:postcode":"4000",
    "sg:province":"QLD",
    "sg:tags":[
        "car",
        "hire",
        "minibus"
    ],
    "wof:name":"Hertz.",
    "wof:placetype":"venue"
},
  "geometry": {"coordinates":[153.02606201200001,-27.4718818665],"type":"Point"}
}