{
  "type": "Feature",
  "properties": {
    "addr:full":"408/ 39 East Esp Manly NSW 2095",
    "addr:housenumber":"408 / 39",
    "addr:postcode":"2095",
    "addr:street":"East Esp",
    "iso:country":"AU",
    "sg:address":"408/ 39 East Esp",
    "sg:city":"Manly",
    "sg:classifiers":[
        {
            "category":"Personal",
            "subcategory":"Massage",
            "type":"Services"
        }
    ],
    "sg:phone":"+61 2 9977 0122",
    "sg:postcode":"2095",
    "sg:province":"NSW",
    "sg:tags":[
        "therapy"
    ],
    "sg:website":"http://www.atms.com.au",
    "wof:name":"Harbourside Massage Clinic",
    "wof:placetype":"venue"
},
  "geometry": {"coordinates":[151.28709411599999,-33.8019104004],"type":"Point"}
}