{
  "type": "Feature",
  "properties": {
    "iso:country":"AU",
    "sg:address":"Lvl 2/ 138 Great North Rd",
    "sg:city":"Five Dock",
    "sg:classifiers":[
        {
            "category":"Education",
            "subcategory":"Dance Studio",
            "type":"Public Place"
        }
    ],
    "sg:phone":"+61 2 9726 5527",
    "sg:postcode":"2046",
    "sg:province":"NSW",
    "sg:tags":[
        "venue",
        "tuition"
    ],
    "wof:name":"Rachaels School Of Dance",
    "wof:placetype":"venue"
},
  "geometry": {"coordinates":[151.13038599999999,-33.865486],"type":"Point"}
}