{
  "type": "Feature",
  "properties": {
    "iso:country":"AU",
    "sg:address":"12 Taurus Crs",
    "sg:city":"Modbury",
    "sg:classifiers":[
        {
            "category":"Building & Trades",
            "subcategory":"Construction",
            "type":"Services"
        }
    ],
    "sg:phone":"+61 8 8264 2989",
    "sg:postcode":"5092",
    "sg:province":"SA",
    "sg:tags":[
        "contractor"
    ],
    "wof:name":"Modbury Home Maintenance Services",
    "wof:placetype":"venue"
},
  "geometry": {"coordinates":[138.69236755399999,-34.8331794739],"type":"Point"}
}