{
  "type": "Feature",
  "properties": {
    "iso:country":"AU",
    "sg:address":"80 - 84 Camooweal St",
    "sg:city":"Mt Isa",
    "sg:classifiers":[
        {
            "category":"Autos & Motor Vehicles",
            "subcategory":"Automobile Sales",
            "type":"Retail Goods"
        }
    ],
    "sg:phone":"+61 7 4743 3044",
    "sg:postcode":"4825",
    "sg:province":"QLD",
    "sg:tags":[
        "car",
        "new"
    ],
    "wof:name":"Bruce Marles Motor City",
    "wof:placetype":"venue"
},
  "geometry": {"coordinates":[139.493073,-20.726709],"type":"Point"}
}