{
  "type": "Feature",
  "properties": {
    "addr:full":"Angas Pl Strathalbyn SA 5255",
    "addr:postcode":"5255",
    "addr:street":"Angas Pl",
    "iso:country":"AU",
    "sg:address":"Angas Pl",
    "sg:city":"Strathalbyn",
    "sg:classifiers":[
        {
            "category":"Utilities",
            "subcategory":"Sewage",
            "type":"Services"
        }
    ],
    "sg:phone":"+61 8 8536 2104",
    "sg:postcode":"5255",
    "sg:province":"SA",
    "sg:tags":[
        "water",
        "waste",
        "treatment"
    ],
    "wof:name":"Septek Wastewater Systems",
    "wof:placetype":"venue"
},
  "geometry": {"coordinates":[138.95976257300001,-35.3000793457],"type":"Point"}
}