{
  "type": "Feature",
  "properties": {
    "addr:full":"177 Grose Vale Rd North Richmond NSW 2754",
    "addr:housenumber":"177",
    "addr:postcode":"2754",
    "addr:street":"Grose Vale Rd",
    "iso:country":"AU",
    "sg:address":"177 Grose Vale Rd",
    "sg:city":"North Richmond",
    "sg:classifiers":[
        {
            "category":"Government",
            "subcategory":"Court House",
            "type":"Public Place"
        }
    ],
    "sg:phone":"+61 2 4570 6128",
    "sg:postcode":"2754",
    "sg:province":"NSW",
    "sg:tags":[
        "personal",
        "marriage",
        "family",
        "counselling"
    ],
    "wof:name":"St John of God Health Services",
    "wof:placetype":"venue"
},
  "geometry": {"coordinates":[150.70269775400001,-33.5886268616],"type":"Point"}
}