{
  "type": "Feature",
  "properties": {
    "iso:country":"AU",
    "sg:address":"352 Sydenham Rd",
    "sg:city":"Sydenham",
    "sg:classifiers":[
        {
            "category":"Social Services",
            "subcategory":"Child Care",
            "type":"Services"
        }
    ],
    "sg:phone":"+61 3 8390 9866",
    "sg:postcode":"3037",
    "sg:province":"VIC",
    "wof:name":"Melbourne Kids",
    "wof:placetype":"venue"
},
  "geometry": {"coordinates":[144.77444499999999,-37.702106],"type":"Point"}
}