{
  "type": "Feature",
  "properties": {
    "addr:full":"Unit 3 40 Bessemer St Blacktown NSW 2148",
    "addr:housenumber":"40",
    "addr:postcode":"2148",
    "addr:street":"Bessemer St",
    "iso:country":"AU",
    "sg:address":"Unit 3 40 Bessemer St",
    "sg:city":"Blacktown",
    "sg:classifiers":[
        {
            "category":"Manufacturing",
            "subcategory":"Tools & Machinery",
            "type":"Manufacturing & Wholesale Goods"
        }
    ],
    "sg:phone":"+61 2 9676 4280",
    "sg:postcode":"2148",
    "sg:province":"NSW",
    "sg:tags":[
        "toolmaker"
    ],
    "wof:name":"Supreme Engireering Services",
    "wof:placetype":"venue"
},
  "geometry": {"coordinates":[150.91569519000001,-33.7500495911],"type":"Point"}
}