{
  "type": "Feature",
  "properties": {
    "iso:country":"AU",
    "sg:address":"1/ 26 Jindalee Rd",
    "sg:city":"Port Macquarie",
    "sg:classifiers":[
        {
            "category":"Fast Food",
            "type":"Food & Drink"
        }
    ],
    "sg:phone":"+61 2 6581 1764",
    "sg:postcode":"2444",
    "sg:province":"NSW",
    "sg:tags":[
        "away",
        "take"
    ],
    "wof:name":"Hungry Workers",
    "wof:placetype":"venue"
},
  "geometry": {"coordinates":[152.884995,-31.450489],"type":"Point"}
}