{
  "type": "Feature",
  "properties": {
    "addr:full":"PO Box 964 Hervey Bay QLD 4655",
    "addr:postcode":"4655",
    "iso:country":"AU",
    "sg:address":"PO Box 964",
    "sg:city":"Hervey Bay",
    "sg:classifiers":[
        {
            "category":"Professional",
            "subcategory":"Printing & Photocopies",
            "type":"Services"
        }
    ],
    "sg:phone":"+61 7 4128 2077",
    "sg:postcode":"4655",
    "sg:province":"QLD",
    "sg:tags":[
        "photocopying"
    ],
    "wof:name":"McTaggarts",
    "wof:placetype":"venue"
},
  "geometry": {"coordinates":[152.84588600000001,-25.284819],"type":"Point"}
}