{
  "type": "Feature",
  "properties": {
    "iso:country":"AU",
    "sg:address":"1011 High St",
    "sg:city":"Armadale",
    "sg:classifiers":[
        {
            "category":"Shopping",
            "subcategory":"Clothing, Apparel, & Fashions",
            "type":"Retail Goods"
        }
    ],
    "sg:phone":"+61 3 9821 0760",
    "sg:postcode":"3143",
    "sg:province":"VIC",
    "sg:tags":[
        "accessory"
    ],
    "wof:name":"Manon Cie",
    "wof:placetype":"venue"
},
  "geometry": {"coordinates":[145.02110290499999,-37.8554115295],"type":"Point"}
}