{
  "type": "Feature",
  "properties": {
    "addr:full":"Macquarie Health Professionals Shop 455 , The Loft Level, Macquarie Shopping Centre N NSW 2113",
    "addr:housenumber":"455",
    "addr:postcode":"2113",
    "addr:street":"The Loft;N",
    "iso:country":"AU",
    "sg:address":"Macquarie Health Professionals Shop 455",
    "sg:city":", The Loft Level, Macquarie Shopping Centre N",
    "sg:classifiers":[
        {
            "category":"Health Services",
            "subcategory":"Chiropractor",
            "type":"Services"
        }
    ],
    "sg:phone":"+61 2 9887 3833",
    "sg:postcode":"2113",
    "sg:province":"NSW",
    "wof:name":"Karalus Jason & Brookes Melinda",
    "wof:placetype":"venue"
},
  "geometry": {"coordinates":[151.11436462399999,-33.7759208679],"type":"Point"}
}