{
  "type": "Feature",
  "properties": {
    "addr:full":"Cnr Diviney Rd & Marjorie Berrimah NT 0828",
    "addr:postcode":"nt 0828",
    "addr:street":"Cnr Diviney Rd &",
    "iso:country":"AU",
    "sg:address":"Cnr Diviney Rd",
    "sg:city":"& Marjorie Berrimah",
    "sg:classifiers":[
        {
            "category":"Wholesale",
            "subcategory":"Machinery & Supplies",
            "type":"Manufacturing & Wholesale Goods"
        }
    ],
    "sg:phone":"+61 8 8932 8000",
    "sg:postcode":"0828",
    "sg:province":"NT",
    "sg:tags":[
        "equipment",
        "hydraulic"
    ],
    "wof:name":"Bardap Hydraulics Pty Ltd",
    "wof:placetype":"venue"
},
  "geometry": {"coordinates":[130.96578979500001,-12.4618797302],"type":"Point"}
}