{
  "type": "Feature",
  "properties": {
    "addr:full":"18 William St Beckenham WA 6107",
    "addr:housenumber":"18",
    "addr:postcode":"6107",
    "addr:street":"William St",
    "iso:country":"AU",
    "sg:address":"18 William St",
    "sg:city":"Beckenham",
    "sg:classifiers":[
        {
            "category":"Home & Garden",
            "subcategory":"Carpets & Floor Coverings",
            "type":"Retail Goods"
        }
    ],
    "sg:phone":"+61 8 9451 6565",
    "sg:postcode":"6107",
    "sg:province":"WA",
    "sg:tags":[
        "mattress"
    ],
    "wof:name":"Bedshed Beckenham",
    "wof:placetype":"venue"
},
  "geometry": {"coordinates":[115.951133728,-32.0258522034],"type":"Point"}
}