{
  "type": "Feature",
  "properties": {
    "addr:full":"136 Le Souef Drv Kardinya WA 6163",
    "addr:housenumber":"136",
    "addr:postcode":"6163",
    "addr:street":"Le Souef Drv",
    "iso:country":"AU",
    "sg:address":"136 Le Souef Drv",
    "sg:city":"Kardinya",
    "sg:classifiers":[
        {
            "category":"Education",
            "subcategory":"Kindergarten",
            "type":"Public Place"
        }
    ],
    "sg:phone":"+61 8 9337 5187",
    "sg:postcode":"6163",
    "sg:province":"WA",
    "sg:tags":[
        "pre-schools"
    ],
    "wof:name":"First Steps Independent Kindergarten",
    "wof:placetype":"venue"
},
  "geometry": {"coordinates":[115.811852,-32.060459],"type":"Point"}
}