{
  "type": "Feature",
  "properties": {
    "iso:country":"AU",
    "sg:address":"183 New Canterbury Rd",
    "sg:city":"Petersham",
    "sg:classifiers":[
        {
            "category":"Home & Garden",
            "subcategory":"Carpets & Floor Coverings",
            "type":"Retail Goods"
        }
    ],
    "sg:phone":"+61 1300 880 601",
    "sg:postcode":"2049",
    "sg:province":"NSW",
    "sg:tags":[
        "tile",
        "wall"
    ],
    "wof:name":"Classic Tiles",
    "wof:placetype":"venue"
},
  "geometry": {"coordinates":[151.150085,-33.897175],"type":"Point"}
}