{
  "type": "Feature",
  "properties": {
    "addr:full":"15 Railway Pde Mt Bryan SA 5418",
    "addr:housenumber":"15",
    "addr:postcode":"5418",
    "addr:street":"Railway Pde",
    "iso:country":"AU",
    "sg:address":"15 Railway Pde",
    "sg:city":"Mt Bryan",
    "sg:classifiers":[
        {
            "category":"Travel",
            "subcategory":"Hotels & Motels",
            "type":"Entertainment"
        }
    ],
    "sg:phone":"+61 8 8893 4010",
    "sg:postcode":"5418",
    "sg:province":"SA",
    "sg:tags":[
        "accommodation"
    ],
    "wof:name":"Mt Bryan Hotel",
    "wof:placetype":"venue"
},
  "geometry": {"coordinates":[138.89178466800001,-33.5515670776],"type":"Point"}
}