{
  "type": "Feature",
  "properties": {
    "addr:full":"49 Floribunda Ave Glenmore Park NSW 2745",
    "addr:housenumber":"49",
    "addr:postcode":"2745",
    "addr:street":"Floribunda Ave",
    "iso:country":"AU",
    "sg:address":"49 Floribunda Ave",
    "sg:city":"Glenmore Park",
    "sg:classifiers":[
        {
            "category":"Home & Garden",
            "subcategory":"Carpets & Floor Coverings",
            "type":"Retail Goods"
        }
    ],
    "sg:phone":"+61 2 4733 4284",
    "sg:postcode":"2745",
    "sg:province":"NSW",
    "sg:tags":[
        "flooring",
        "parquet"
    ],
    "wof:name":"Glenmore Park Floor Sanding",
    "wof:placetype":"venue"
},
  "geometry": {"coordinates":[150.66578674300001,-33.7821464539],"type":"Point"}
}