{
  "type": "Feature",
  "properties": {
    "iso:country":"AU",
    "sg:address":"180 Main Beach Rd",
    "sg:city":"Pinkenba",
    "sg:classifiers":[
        {
            "category":"Building & Trades",
            "subcategory":"Construction",
            "type":"Services"
        }
    ],
    "sg:phone":"+61 1300 933 444",
    "sg:postcode":"4008",
    "sg:province":"QLD",
    "sg:tags":[
        "earth",
        "excavating",
        "moving",
        "contractor"
    ],
    "wof:name":"Aussie Excavators",
    "wof:placetype":"venue"
},
  "geometry": {"coordinates":[153.143997192,-27.3829021454],"type":"Point"}
}