{
  "type": "Feature",
  "properties": {
    "addr:full":"185 Condamine St Balgowlah NSW 2093",
    "addr:housenumber":"185",
    "addr:postcode":"2093",
    "addr:street":"Condamine St",
    "iso:country":"AU",
    "sg:address":"185 Condamine St",
    "sg:city":"Balgowlah",
    "sg:classifiers":[
        {
            "category":"Health Services",
            "subcategory":"Health Practitioner",
            "type":"Services"
        }
    ],
    "sg:phone":"+61 2 9907 8919",
    "sg:postcode":"2093",
    "sg:province":"NSW",
    "sg:tags":[
        "osteopath"
    ],
    "wof:name":"North Shore Osteopaths",
    "wof:placetype":"venue"
},
  "geometry": {"coordinates":[151.26458740199999,-33.7949295044],"type":"Point"}
}