{
  "type": "Feature",
  "properties": {
    "addr:full":"296 Racecourse Rd Flemington VIC 3031",
    "addr:housenumber":"296",
    "addr:postcode":"3031",
    "addr:street":"Racecourse Rd",
    "iso:country":"AU",
    "sg:address":"296 Racecourse Rd",
    "sg:city":"Flemington",
    "sg:classifiers":[
        {
            "category":"Food & Beverages",
            "subcategory":"Fruits & Vegetables",
            "type":"Retail Goods"
        }
    ],
    "sg:phone":"+61 3 9376 6109",
    "sg:postcode":"3031",
    "sg:province":"VIC",
    "sg:tags":[
        "greengrocer",
        "fruiterer"
    ],
    "wof:name":"Flemington Fresh Centre",
    "wof:placetype":"venue"
},
  "geometry": {"coordinates":[144.930725,-37.788101],"type":"Point"}
}