{
  "type": "Feature",
  "properties": {
    "addr:full":"Ste11/ 33 Fearn Ave Margaret River WA 6285",
    "addr:postcode":"6285",
    "addr:street":"Fearn Ave",
    "iso:country":"AU",
    "sg:address":"Ste11/ 33 Fearn Ave",
    "sg:city":"Margaret River",
    "sg:classifiers":[
        {
            "category":"Professional",
            "subcategory":"Accounting & Tax Preparation",
            "type":"Services"
        }
    ],
    "sg:phone":"+61 8 9757 9841",
    "sg:postcode":"6285",
    "sg:province":"WA",
    "sg:tags":[
        "accountant",
        "auditor"
    ],
    "wof:name":"Proactive Taxation Solutions",
    "wof:placetype":"venue"
},
  "geometry": {"coordinates":[115.072410584,-33.9528274536],"type":"Point"}
}