{
  "type": "Feature",
  "properties": {
    "addr:full":"Lot3/ Flemington Rd Bowen QLD 4805",
    "addr:postcode":"4805",
    "addr:street":"/ Flemington Rd",
    "iso:country":"AU",
    "sg:address":"Lot3/ Flemington Rd",
    "sg:city":"Bowen",
    "sg:classifiers":[
        {
            "category":"Wholesale",
            "subcategory":"Farm Supplies",
            "type":"Manufacturing & Wholesale Goods"
        }
    ],
    "sg:phone":"+61 7 4786 1684",
    "sg:postcode":"4805",
    "sg:province":"QLD",
    "sg:tags":[
        "feed",
        "supplement",
        "stock"
    ],
    "wof:name":"Bowen Rural Supplies",
    "wof:placetype":"venue"
},
  "geometry": {"coordinates":[148.220245361,-20.0078697205],"type":"Point"}
}