{
  "type": "Feature",
  "properties": {
    "addr:full":"157 Mickleham Rd Tullamarine VIC 3043",
    "addr:housenumber":"157",
    "addr:postcode":"3043",
    "addr:street":"Mickleham Rd",
    "iso:country":"AU",
    "sg:address":"157 Mickleham Rd",
    "sg:city":"Tullamarine",
    "sg:classifiers":[
        {
            "category":"Retail",
            "subcategory":"Auto Rental",
            "type":"Services"
        }
    ],
    "sg:phone":"+61 3 9330 6161",
    "sg:postcode":"3043",
    "sg:province":"VIC",
    "sg:tags":[
        "car",
        "hire",
        "minibus"
    ],
    "wof:name":"Europcar",
    "wof:placetype":"venue"
},
  "geometry": {"coordinates":[144.880401611,-37.6978683472],"type":"Point"}
}