{
  "type": "Feature",
  "properties": {
    "addr:full":"Calvary Hospital North Adelaide SA 5006",
    "addr:postcode":"5006",
    "iso:country":"AU",
    "sg:address":"Calvary Hospital",
    "sg:city":"North Adelaide",
    "sg:classifiers":[
        {
            "category":"Health Services",
            "subcategory":"Doctor",
            "type":"Services"
        }
    ],
    "sg:phone":"+61 1300 665 854",
    "sg:postcode":"5006",
    "sg:province":"SA",
    "sg:tags":[
        "medical",
        "practitioner"
    ],
    "wof:name":"Singla Amita Dr",
    "wof:placetype":"venue"
},
  "geometry": {"coordinates":[138.595504761,-34.9112167358],"type":"Point"}
}