{
  "type": "Feature",
  "properties": {
    "addr:full":"2 Kingston St Toowoomba City QLD 4350",
    "addr:housenumber":"2",
    "addr:postcode":"4350",
    "addr:street":"Kingston St",
    "iso:country":"AU",
    "sg:address":"2 Kingston St",
    "sg:city":"Toowoomba City",
    "sg:classifiers":[
        {
            "category":"Professional",
            "subcategory":"Art Services",
            "type":"Services"
        }
    ],
    "sg:phone":"+61 7 4659 7330",
    "sg:postcode":"4350",
    "sg:province":"QLD",
    "sg:tags":[
        "picture",
        "frame",
        "framing"
    ],
    "wof:name":"Gayles",
    "wof:placetype":"venue"
},
  "geometry": {"coordinates":[151.94607500000001,-27.556967],"type":"Point"}
}