{
  "type": "Feature",
  "properties": {
    "iso:country":"AU",
    "sg:address":"PO Box 446",
    "sg:city":"Nelson Bay",
    "sg:classifiers":[
        {
            "category":"Home & Garden",
            "subcategory":"Building Materials",
            "type":"Retail Goods"
        }
    ],
    "sg:phone":"+61 418 326 249",
    "sg:postcode":"2315",
    "sg:province":"NSW",
    "sg:tags":[
        "retaining",
        "wall"
    ],
    "wof:name":"Aladdins Landscapes",
    "wof:placetype":"venue"
},
  "geometry": {"coordinates":[152.14331100000001,-32.72279],"type":"Point"}
}