{
  "type": "Feature",
  "properties": {
    "iso:country":"AU",
    "sg:address":"1445 North Rd",
    "sg:city":"Devon Meadows",
    "sg:classifiers":[
        {
            "category":"Wholesale",
            "subcategory":"Plants",
            "type":"Manufacturing & Wholesale Goods"
        }
    ],
    "sg:phone":"+61 3 5998 2827",
    "sg:postcode":"3977",
    "sg:province":"VIC",
    "sg:tags":[
        "florist"
    ],
    "wof:name":"Malikovski B",
    "wof:placetype":"venue"
},
  "geometry": {"coordinates":[145.324584961,-38.1811981201],"type":"Point"}
}