{
  "type": "Feature",
  "properties": {
    "addr:full":"Shop 5 Eastside Village Cnr New Cleveland and Tilley Rds Wakerley QLD 4154",
    "addr:housenumber":"shop 5",
    "addr:postcode":"4154",
    "addr:street":"Eastside Village Cnr New",
    "iso:country":"AU",
    "sg:address":"Shop 5 Eastside Village Cnr New Cleveland and Tilley Rds",
    "sg:city":"Wakerley",
    "sg:classifiers":[
        {
            "category":"Food & Beverages",
            "subcategory":"Liquor & Beverages",
            "type":"Retail Goods"
        }
    ],
    "sg:phone":"+61 7 3348 9891",
    "sg:postcode":"4154",
    "sg:province":"QLD",
    "sg:tags":[
        "store"
    ],
    "wof:name":"Liqour King Gumdale",
    "wof:placetype":"venue"
},
  "geometry": {"coordinates":[153.15335082999999,-27.4908542633],"type":"Point"}
}