{
  "type": "Feature",
  "properties": {
    "addr:full":"16 Berry St Nowra NSW 2541",
    "addr:housenumber":"16",
    "addr:postcode":"2541",
    "addr:street":"Berry St",
    "iso:country":"AU",
    "sg:address":"16 Berry St",
    "sg:city":"Nowra",
    "sg:classifiers":[
        {
            "category":"Shopping",
            "subcategory":"Stationery & Office Supplies",
            "type":"Retail Goods"
        }
    ],
    "sg:phone":"+61 2 4421 5940",
    "sg:postcode":"2541",
    "sg:province":"NSW",
    "sg:tags":[
        "equipment",
        "facsimile"
    ],
    "wof:name":"Betta Electrical & Gas",
    "wof:placetype":"venue"
},
  "geometry": {"coordinates":[150.599334717,-34.8814163208],"type":"Point"}
}