{
  "type": "Feature",
  "properties": {
    "iso:country":"AU",
    "sg:address":"2a Kirk St",
    "sg:city":"Moe",
    "sg:classifiers":[
        {
            "category":"Personal",
            "subcategory":"Tanning Parlor",
            "type":"Services"
        }
    ],
    "sg:phone":"+61 3 5127 8500",
    "sg:postcode":"3825",
    "sg:province":"VIC",
    "sg:tags":[
        "solarium"
    ],
    "wof:name":"Indulge Yourself Beauty Therapy",
    "wof:placetype":"venue"
},
  "geometry": {"coordinates":[146.263123,-38.176197],"type":"Point"}
}