{
  "type": "Feature",
  "properties": {
    "iso:country":"AU",
    "sg:address":"30 Henry St",
    "sg:city":"Penrith",
    "sg:classifiers":[
        {
            "category":"Building & Trades",
            "subcategory":"Construction",
            "type":"Services"
        }
    ],
    "sg:phone":"+61 13 88 31",
    "sg:postcode":"2740",
    "sg:province":"NSW",
    "sg:tags":[
        "window",
        "tinting"
    ],
    "wof:name":"SunGard",
    "wof:placetype":"venue"
},
  "geometry": {"coordinates":[150.704666,-33.753918],"type":"Point"}
}