{
  "type": "Feature",
  "properties": {
    "iso:country":"AU",
    "sg:address":"Level 1, Unit 14, Cnr Queens Rd & Williams St",
    "sg:city":"Five Dock",
    "sg:classifiers":[
        {
            "category":"Arena",
            "subcategory":"Sports Club",
            "type":"Entertainment"
        }
    ],
    "sg:phone":"+61 2 9744 7055",
    "sg:postcode":"2046",
    "sg:province":"NSW",
    "sg:tags":[
        "defence",
        "supply",
        "self",
        "instruction",
        "martial art"
    ],
    "sg:website":"http://www.familyselfdefence.com.au",
    "wof:name":"Family Self Defence & Fitness Academy",
    "wof:placetype":"venue"
},
  "geometry": {"coordinates":[151.128876,-33.870548],"type":"Point"}
}