{
  "type": "Feature",
  "properties": {
    "addr:full":"64 Park Rd Bowral NSW 2576",
    "addr:housenumber":"64",
    "addr:postcode":"2576",
    "addr:street":"Park Rd",
    "iso:country":"AU",
    "sg:address":"64 Park Rd",
    "sg:city":"Bowral",
    "sg:classifiers":[
        {
            "category":"Education",
            "subcategory":"Special Training",
            "type":"Public Place"
        }
    ],
    "sg:phone":"+61 2 4861 3720",
    "sg:postcode":"2576",
    "sg:province":"NSW",
    "sg:tags":[
        "tuition-educational"
    ],
    "wof:name":"Johnsson Anne",
    "wof:placetype":"venue"
},
  "geometry": {"coordinates":[150.43258667000001,-34.4894714355],"type":"Point"}
}