{
  "type": "Feature",
  "properties": {
    "iso:country":"AU",
    "sg:address":"Suite 8, 8 Sunshine Beach Rd",
    "sg:city":"Noosa Junction",
    "sg:classifiers":[
        {
            "category":"Health Services",
            "subcategory":"Health Practitioner",
            "type":"Services"
        }
    ],
    "sg:phone":"+61 7 5455 3112",
    "sg:postcode":"4567",
    "sg:province":"QLD",
    "sg:tags":[
        "pathologist",
        "speech"
    ],
    "wof:name":"Jen Fraser Speech Pathologist",
    "wof:placetype":"venue"
},
  "geometry": {"coordinates":[153.09146118199999,-26.3977680206],"type":"Point"}
}