{
  "type": "Feature",
  "properties": {
    "addr:full":"100 Callum St Mooroobool QLD 4870",
    "addr:housenumber":"100",
    "addr:postcode":"4870",
    "addr:street":"Callum St",
    "iso:country":"AU",
    "sg:address":"100 Callum St",
    "sg:city":"Mooroobool",
    "sg:classifiers":[
        {
            "category":"Social Services",
            "subcategory":"Child Care",
            "type":"Services"
        }
    ],
    "sg:phone":"+61 7 4032 0440",
    "sg:postcode":"4870",
    "sg:province":"QLD",
    "sg:website":"http://www.childcare.com.au",
    "wof:name":"ABC Mooroobool",
    "wof:placetype":"venue"
},
  "geometry": {"coordinates":[145.733444214,-16.928861618],"type":"Point"}
}