{
  "type": "Feature",
  "properties": {
    "addr:full":"1015 Fairfield Rd Rocklea QLD 4106",
    "addr:housenumber":"1015",
    "addr:postcode":"4106",
    "addr:street":"Fairfield Rd",
    "iso:country":"AU",
    "sg:address":"1015 Fairfield Rd",
    "sg:city":"Rocklea",
    "sg:classifiers":[
        {
            "category":"Retail",
            "subcategory":"Auto Repair",
            "type":"Services"
        }
    ],
    "sg:phone":"+61 7 3848 1200",
    "sg:postcode":"4106",
    "sg:province":"QLD",
    "sg:tags":[
        "testing",
        "inspection",
        "motor",
        "vehicle"
    ],
    "wof:name":"Jee Serv",
    "wof:placetype":"venue"
},
  "geometry": {"coordinates":[153.01168823200001,-27.540063858],"type":"Point"}
}