{
  "type": "Feature",
  "properties": {
    "addr:full":"4- 5 Brex Crt Reservoir VIC 3073",
    "addr:housenumber":"5",
    "addr:postcode":"3073",
    "addr:street":"Brex Crt",
    "iso:country":"AU",
    "sg:address":"4- 5 Brex Crt",
    "sg:city":"Reservoir",
    "sg:classifiers":[
        {
            "category":"Wholesale",
            "subcategory":"Machinery & Supplies",
            "type":"Manufacturing & Wholesale Goods"
        }
    ],
    "sg:phone":"+61 3 9462 2644",
    "sg:postcode":"3073",
    "sg:province":"VIC",
    "sg:tags":[
        "bearing",
        "bushing"
    ],
    "wof:name":"Australian Bearings Pty Ltd",
    "wof:placetype":"venue"
},
  "geometry": {"coordinates":[144.98130798299999,-37.7086753845],"type":"Point"}
}