{
  "type": "Feature",
  "properties": {
    "iso:country":"AU",
    "sg:address":"1 Mermaid Ave",
    "sg:city":"Emu Point",
    "sg:classifiers":[
        {
            "category":"Fast Food",
            "type":"Food & Drink"
        }
    ],
    "sg:phone":"+61 8 9844 7207",
    "sg:postcode":"6330",
    "sg:province":"WA",
    "sg:tags":[
        "away",
        "take"
    ],
    "wof:name":"Emu Point Cafe",
    "wof:placetype":"venue"
},
  "geometry": {"coordinates":[117.947143555,-34.9982795715],"type":"Point"}
}