{
  "type": "Feature",
  "properties": {
    "addr:full":"5 / 1488 Ferntree Gully Rd Knoxfield VIC 3180",
    "addr:housenumber":"/ 1488",
    "addr:postcode":"3180",
    "addr:street":"Ferntree Gully Rd",
    "iso:country":"AU",
    "sg:address":"5 / 1488 Ferntree Gully Rd",
    "sg:city":"Knoxfield",
    "sg:classifiers":[
        {
            "category":"Manufacturing",
            "subcategory":"Chemicals & Compounds",
            "type":"Manufacturing & Wholesale Goods"
        }
    ],
    "sg:phone":"+61 1300 996 999",
    "sg:postcode":"3180",
    "sg:province":"VIC",
    "sg:tags":[
        "electroplating"
    ],
    "wof:name":"Electromold Xtreme Coatings P/L",
    "wof:placetype":"venue"
},
  "geometry": {"coordinates":[145.23667907699999,-37.8987236023],"type":"Point"}
}