{
  "type": "Feature",
  "properties": {
    "addr:full":"45- 49 South Rd Drouin VIC 3818",
    "addr:housenumber":"49",
    "addr:postcode":"3818",
    "addr:street":"South Rd",
    "iso:country":"AU",
    "sg:address":"45- 49 South Rd",
    "sg:city":"Drouin",
    "sg:classifiers":[
        {
            "category":"Manufacturing",
            "subcategory":"Rubber & Plastics",
            "type":"Manufacturing & Wholesale Goods"
        }
    ],
    "sg:phone":"+61 1800 032 002",
    "sg:postcode":"3818",
    "sg:province":"VIC",
    "sg:tags":[
        "wholesaler",
        "product",
        "mfrs"
    ],
    "wof:name":"ACI Plastics Packaging",
    "wof:placetype":"venue"
},
  "geometry": {"coordinates":[145.858124,-38.136688],"type":"Point"}
}