{
  "type": "Feature",
  "properties": {
    "addr:full":"1 Taylors Rd Valley Heights NSW 2777",
    "addr:housenumber":"1",
    "addr:postcode":"2777",
    "addr:street":"Taylors Rd",
    "iso:country":"AU",
    "sg:address":"1 Taylors Rd",
    "sg:city":"Valley Heights",
    "sg:classifiers":[
        {
            "category":"Autos & Motor Vehicles",
            "subcategory":"Auto Supplies",
            "type":"Retail Goods"
        }
    ],
    "sg:phone":"+61 13 61 30",
    "sg:postcode":"2777",
    "sg:province":"NSW",
    "sg:tags":[
        "battery",
        "automotive"
    ],
    "wof:name":"Marshall Batteries",
    "wof:placetype":"venue"
},
  "geometry": {"coordinates":[150.576446533,-33.7167892456],"type":"Point"}
}