{
  "type": "Feature",
  "properties": {
    "addr:full":"Williamson Crs Warwick Farm NSW 2170",
    "addr:postcode":"2170",
    "addr:street":"Williamson Crs",
    "iso:country":"AU",
    "sg:address":"Williamson Crs",
    "sg:city":"Warwick Farm",
    "sg:classifiers":[
        {
            "category":"Social Services",
            "subcategory":"Child Care",
            "type":"Services"
        }
    ],
    "sg:phone":"+61 2 9602 5603",
    "sg:postcode":"2170",
    "sg:province":"NSW",
    "wof:name":"Warwick Farm Children's Centre",
    "wof:placetype":"venue"
},
  "geometry": {"coordinates":[150.93775939899999,-33.9115180969],"type":"Point"}
}