{
  "type": "Feature",
  "properties": {
    "addr:full":"Settlement Rd Belmont VIC 3216",
    "addr:postcode":"3216",
    "addr:street":"Settlement Rd",
    "iso:country":"AU",
    "sg:address":"Settlement Rd",
    "sg:city":"Belmont",
    "sg:classifiers":[
        {
            "category":"Sports & Exercise",
            "subcategory":"Gym",
            "type":"Entertainment"
        }
    ],
    "sg:phone":"+61 3 5243 3300",
    "sg:postcode":"3216",
    "sg:province":"VIC",
    "sg:tags":[
        "health",
        "fitness"
    ],
    "wof:name":"Club Reflex Squash & Fitness",
    "wof:placetype":"venue"
},
  "geometry": {"coordinates":[144.34115600600001,-38.1818504333],"type":"Point"}
}