{
  "type": "Feature",
  "properties": {
    "iso:country":"AU",
    "sg:address":"64 St Leonards Rd",
    "sg:city":"St Leonards",
    "sg:classifiers":[
        {
            "category":"Building & Trades",
            "subcategory":"Construction",
            "type":"Services"
        }
    ],
    "sg:phone":"+61 418 132 366",
    "sg:postcode":"7250",
    "sg:province":"TAS",
    "sg:tags":[
        "contractor"
    ],
    "wof:name":"Woodward Builders & Joiners",
    "wof:placetype":"venue"
},
  "geometry": {"coordinates":[147.18031310999999,-41.4410476685],"type":"Point"}
}