{
  "type": "Feature",
  "properties": {
    "iso:country":"AU",
    "sg:address":"120 Commercial St",
    "sg:city":"Merbein",
    "sg:classifiers":[
        {
            "category":"Health Services",
            "subcategory":"Doctor",
            "type":"Services"
        }
    ],
    "sg:phone":"+61 3 5025 2085",
    "sg:postcode":"3505",
    "sg:province":"VIC",
    "sg:tags":[
        "medical",
        "practitioner"
    ],
    "wof:name":"Shetty K P",
    "wof:placetype":"venue"
},
  "geometry": {"coordinates":[142.06228637699999,-34.1680335999],"type":"Point"}
}