{
  "type": "Feature",
  "properties": {
    "addr:full":"Christine Ave Medical Centre Cnr Bermuda St & Chri Robina QLD 4226",
    "addr:postcode":"4226",
    "addr:street":"Christine;Cnr Bermuda St &",
    "iso:country":"AU",
    "sg:address":"Christine Ave Medical Centre Cnr Bermuda St & Chri",
    "sg:city":"Robina",
    "sg:classifiers":[
        {
            "category":"Health Services",
            "subcategory":"Health Practitioner",
            "type":"Services"
        }
    ],
    "sg:phone":"+61 411 150 807",
    "sg:postcode":"4226",
    "sg:province":"QLD",
    "sg:tags":[
        "acupuncture"
    ],
    "wof:name":"Acupuncture Service Of Queensland",
    "wof:placetype":"venue"
},
  "geometry": {"coordinates":[153.408279419,-28.0520744324],"type":"Point"}
}