{
  "type": "Feature",
  "properties": {
    "addr:full":"PO Box 4267 Knox City 3152 Knox VIC 3180",
    "addr:postcode":"3152;3180",
    "iso:country":"AU",
    "sg:address":"PO Box 4267 Knox City 3152",
    "sg:city":"Knox",
    "sg:classifiers":[
        {
            "category":"Professional",
            "subcategory":"Management & Consulting",
            "type":"Services"
        }
    ],
    "sg:phone":"+61 3 9801 1396",
    "sg:postcode":"3180",
    "sg:province":"VIC",
    "sg:tags":[
        "consultant"
    ],
    "wof:name":"Merlin Business Solutions",
    "wof:placetype":"venue"
},
  "geometry": {"coordinates":[145.22270202600001,-37.8634490967],"type":"Point"}
}