{
  "type": "Feature",
  "properties": {
    "addr:full":"875 Princes Hwy Springvale VIC 3171",
    "addr:housenumber":"875",
    "addr:postcode":"3171",
    "addr:street":"Princes Hwy",
    "iso:country":"AU",
    "sg:address":"875 Princes Hwy",
    "sg:city":"Springvale",
    "sg:classifiers":[
        {
            "category":"Retail",
            "subcategory":"Auto Rental",
            "type":"Services"
        }
    ],
    "sg:phone":"+61 3 9548 5777",
    "sg:postcode":"3171",
    "sg:province":"VIC",
    "sg:tags":[
        "car",
        "hire",
        "minibus"
    ],
    "wof:name":"Hertz .",
    "wof:placetype":"venue"
},
  "geometry": {"coordinates":[145.152053833,-37.9304161072],"type":"Point"}
}