{
  "type": "Feature",
  "properties": {
    "addr:full":"141 Victoria Rd Peterhead SA 5016",
    "addr:housenumber":"141",
    "addr:postcode":"5016",
    "addr:street":"Victoria Rd",
    "iso:country":"AU",
    "sg:address":"141 Victoria Rd",
    "sg:city":"Peterhead",
    "sg:classifiers":[
        {
            "category":"Autos & Motor Vehicles",
            "subcategory":"Auto Supplies",
            "type":"Retail Goods"
        }
    ],
    "sg:phone":"+61 8 8449 4499",
    "sg:postcode":"5016",
    "sg:province":"SA",
    "sg:tags":[
        "tyre"
    ],
    "wof:name":"Marine Tyres",
    "wof:placetype":"venue"
},
  "geometry": {"coordinates":[138.50100707999999,-34.830619812],"type":"Point"}
}