{
  "type": "Feature",
  "properties": {
    "addr:full":"129 Wellington St Windsor VIC 3181",
    "addr:housenumber":"129",
    "addr:postcode":"3181",
    "addr:street":"Wellington St",
    "iso:country":"AU",
    "sg:address":"129 Wellington St",
    "sg:city":"Windsor",
    "sg:classifiers":[
        {
            "category":"Social Services",
            "subcategory":"Adult Care",
            "type":"Services"
        }
    ],
    "sg:phone":"+61 3 9533 6099",
    "sg:postcode":"3181",
    "sg:province":"VIC",
    "sg:tags":[
        "disadvantaged",
        "aid",
        "organisation",
        "group"
    ],
    "wof:name":"Hanover Young Adults Services",
    "wof:placetype":"venue"
},
  "geometry": {"coordinates":[144.991333008,-37.85729599],"type":"Point"}
}