{
  "type": "Feature",
  "properties": {
    "addr:full":"66 Manningham St Parkville VIC 3052",
    "addr:housenumber":"66",
    "addr:postcode":"3052",
    "addr:street":"Manningham St",
    "iso:country":"AU",
    "sg:address":"66 Manningham St",
    "sg:city":"Parkville",
    "sg:classifiers":[
        {
            "category":"Health Services",
            "subcategory":"Doctor",
            "type":"Services"
        }
    ],
    "sg:phone":"+61 3 9329 9203",
    "sg:postcode":"3052",
    "sg:province":"VIC",
    "sg:tags":[
        "medical",
        "practitioner"
    ],
    "wof:name":"Brown Malcolm",
    "wof:placetype":"venue"
},
  "geometry": {"coordinates":[144.942092895,-37.7863845825],"type":"Point"}
}