{
  "type": "Feature",
  "properties": {
    "addr:full":"Fullerton Cove Rd Fullerton Cove NSW 2318",
    "addr:postcode":"2318",
    "addr:street":"Fullerton Cove Rd",
    "iso:country":"AU",
    "sg:address":"Fullerton Cove Rd",
    "sg:city":"Fullerton Cove",
    "sg:classifiers":[
        {
            "category":"Building & Trades",
            "subcategory":"Construction",
            "type":"Services"
        }
    ],
    "sg:phone":"+61 2 4965 1431",
    "sg:postcode":"2318",
    "sg:province":"NSW",
    "sg:tags":[
        "contractor"
    ],
    "wof:name":"Antcliff R O",
    "wof:placetype":"venue"
},
  "geometry": {"coordinates":[151.829193,-32.839409],"type":"Point"}
}