{
  "type": "Feature",
  "properties": {
    "addr:full":"75 Fulcrum St Richlands QLD 4077",
    "addr:housenumber":"75",
    "addr:postcode":"4077",
    "addr:street":"Fulcrum St",
    "iso:country":"AU",
    "sg:address":"75 Fulcrum St",
    "sg:city":"Richlands",
    "sg:classifiers":[
        {
            "category":"Wholesale",
            "subcategory":"Chemicals & Plastics",
            "type":"Manufacturing & Wholesale Goods"
        }
    ],
    "sg:phone":"+61 7 3710 3300",
    "sg:postcode":"4077",
    "sg:province":"QLD",
    "sg:tags":[
        "bag"
    ],
    "wof:name":"Flexpack",
    "wof:placetype":"venue"
},
  "geometry": {"coordinates":[152.94610595699999,-27.5875473022],"type":"Point"}
}