{
  "type": "Feature",
  "properties": {
    "addr:full":"1 Waterloo Rd Macquarie Park NSW 2113",
    "addr:housenumber":"1",
    "addr:postcode":"2113",
    "addr:street":"Waterloo Rd",
    "iso:country":"AU",
    "sg:address":"1 Waterloo Rd",
    "sg:city":"Macquarie Park",
    "sg:classifiers":[
        {
            "category":"Real Estate",
            "subcategory":"Surveying",
            "type":"Services"
        }
    ],
    "sg:phone":"+61 1800 021 987",
    "sg:postcode":"2113",
    "sg:province":"NSW",
    "sg:tags":[
        "map",
        "mapping"
    ],
    "wof:name":"UBD",
    "wof:placetype":"venue"
},
  "geometry": {"coordinates":[151.13044738799999,-33.7863388062],"type":"Point"}
}