{
  "type": "Feature",
  "properties": {
    "iso:country":"AU",
    "sg:address":"426 Wilson St",
    "sg:city":"Albury",
    "sg:classifiers":[
        {
            "category":"Home & Garden",
            "subcategory":"Furniture",
            "type":"Retail Goods"
        }
    ],
    "sg:phone":"+61 2 6023 2600",
    "sg:postcode":"2640",
    "sg:province":"NSW",
    "sg:tags":[
        "business"
    ],
    "wof:name":"Accent Workstation Systems",
    "wof:placetype":"venue"
},
  "geometry": {"coordinates":[146.92404174800001,-36.0773620605],"type":"Point"}
}