{
  "type": "Feature",
  "properties": {
    "iso:country":"AU",
    "sg:address":"24 Vincent Ave",
    "sg:city":"Athelstone",
    "sg:classifiers":[
        {
            "category":"Home & Garden",
            "subcategory":"Carpets & Floor Coverings",
            "type":"Retail Goods"
        }
    ],
    "sg:phone":"+61 412 600 443",
    "sg:postcode":"5076",
    "sg:province":"SA",
    "sg:tags":[
        "tile",
        "wall",
        "layer"
    ],
    "wof:name":"A Cut Above The Rest Tiling",
    "wof:placetype":"venue"
},
  "geometry": {"coordinates":[138.69430542000001,-34.8795127869],"type":"Point"}
}