{
  "type": "Feature",
  "properties": {
    "addr:full":"13 Market St Nunawading VIC 3131",
    "addr:housenumber":"13",
    "addr:postcode":"3131",
    "addr:street":"Market St",
    "iso:country":"AU",
    "sg:address":"13 Market St",
    "sg:city":"Nunawading",
    "sg:classifiers":[
        {
            "category":"Health Services",
            "subcategory":"Doctor",
            "type":"Services"
        }
    ],
    "sg:phone":"+61 3 9878 2687",
    "sg:postcode":"3131",
    "sg:province":"VIC",
    "sg:tags":[
        "podiatrist"
    ],
    "wof:name":"Ben Steele Podiatry",
    "wof:placetype":"venue"
},
  "geometry": {"coordinates":[145.176437378,-37.8214797974],"type":"Point"}
}