{
  "type": "Feature",
  "properties": {
    "iso:country":"AU",
    "sg:address":"William Ave",
    "sg:city":"Warilla",
    "sg:classifiers":[
        {
            "category":"Education",
            "subcategory":"School",
            "type":"Public Place"
        }
    ],
    "sg:phone":"+61 2 4297 1611",
    "sg:postcode":"2528",
    "sg:province":"NSW",
    "sg:tags":[
        "state",
        "-",
        "nsw"
    ],
    "wof:name":"Peterborough SSP",
    "wof:placetype":"venue"
},
  "geometry": {"coordinates":[150.859207153,-34.5548439026],"type":"Point"}
}