{
  "type": "Feature",
  "properties": {
    "iso:country":"AU",
    "sg:address":"614 Browns Plains Rd",
    "sg:city":"Marsden",
    "sg:classifiers":[
        {
            "category":"Retail",
            "subcategory":"Auto Repair",
            "type":"Services"
        }
    ],
    "sg:phone":"+61 7 3803 5745",
    "sg:postcode":"4132",
    "sg:province":"QLD",
    "sg:tags":[
        "repairer",
        "motor",
        "engineer"
    ],
    "wof:name":"Kmart Tyre & Auto Service",
    "wof:placetype":"venue"
},
  "geometry": {"coordinates":[153.092895508,-27.6809673309],"type":"Point"}
}