{
  "type": "Feature",
  "properties": {
    "addr:full":"133b Lime Ave Mildura VIC 3500",
    "addr:housenumber":"133b",
    "addr:postcode":"3500",
    "addr:street":"Lime Ave",
    "iso:country":"AU",
    "sg:address":"133b Lime Ave",
    "sg:city":"Mildura",
    "sg:classifiers":[
        {
            "category":"Health Services",
            "subcategory":"Health Practitioner",
            "type":"Services"
        }
    ],
    "sg:phone":"+61 408 231 038",
    "sg:postcode":"3500",
    "sg:province":"VIC",
    "sg:tags":[
        "psychologist"
    ],
    "wof:name":"Derek H James Counselling Psychologist",
    "wof:placetype":"venue"
},
  "geometry": {"coordinates":[142.15638732900001,-34.1865501404],"type":"Point"}
}