{
  "type": "Feature",
  "properties": {
    "addr:full":"25 Kirra Rd Allambie Heights NSW 2100",
    "addr:housenumber":"25",
    "addr:postcode":"2100",
    "addr:street":"Kirra Rd",
    "iso:country":"AU",
    "sg:address":"25 Kirra Rd",
    "sg:city":"Allambie Heights",
    "sg:classifiers":[
        {
            "category":"Real Estate",
            "subcategory":"Real Estate Agent",
            "type":"Services"
        }
    ],
    "sg:phone":"+61 2 9905 0564",
    "sg:postcode":"2100",
    "sg:province":"NSW",
    "wof:name":"Smith, Gerard",
    "wof:placetype":"venue"
},
  "geometry": {"coordinates":[151.25637817399999,-33.7661170959],"type":"Point"}
}