{
  "type": "Feature",
  "properties": {
    "iso:country":"AU",
    "sg:address":"47a Little St",
    "sg:city":"Coffs Harbour",
    "sg:classifiers":[
        {
            "category":"Organizations",
            "subcategory":"Professional Association",
            "type":"Services"
        }
    ],
    "sg:phone":"+61 2 6651 6605",
    "sg:postcode":"2450",
    "sg:province":"NSW",
    "sg:tags":[
        "web",
        "internet"
    ],
    "sg:website":"http://www.braindomain.com.au",
    "wof:name":"Brain Domain",
    "wof:placetype":"venue"
},
  "geometry": {"coordinates":[153.113007,-30.298426],"type":"Point"}
}