{
  "type": "Feature",
  "properties": {
    "addr:full":"Ste266/ 25 Allen St Waterloo NSW 2017",
    "addr:housenumber":"25",
    "addr:postcode":"2017",
    "addr:street":"Allen St",
    "iso:country":"AU",
    "sg:address":"Ste266/ 25 Allen St",
    "sg:city":"Waterloo",
    "sg:classifiers":[
        {
            "category":"Wholesale",
            "subcategory":"Medical Equipment & Supplies",
            "type":"Manufacturing & Wholesale Goods"
        }
    ],
    "sg:phone":"+61 2 9690 0750",
    "sg:postcode":"2017",
    "sg:province":"NSW",
    "sg:tags":[
        "dental"
    ],
    "wof:name":"Dental Implant Dynamics",
    "wof:placetype":"venue"
},
  "geometry": {"coordinates":[151.20474243199999,-33.902469635],"type":"Point"}
}