{
  "type": "Feature",
  "properties": {
    "addr:full":"Brand Hwy Gingin WA 6503",
    "addr:postcode":"6503",
    "addr:street":"Brand Hwy",
    "iso:country":"AU",
    "sg:address":"Brand Hwy",
    "sg:city":"Gingin",
    "sg:classifiers":[
        {
            "category":"Farming",
            "subcategory":"Farm",
            "type":"Manufacturing & Wholesale Goods"
        }
    ],
    "sg:phone":"+61 8 9575 2256",
    "sg:postcode":"6503",
    "sg:province":"WA",
    "sg:tags":[
        "farmer"
    ],
    "wof:name":"Wedge W R",
    "wof:placetype":"venue"
},
  "geometry": {"coordinates":[115.889076,-31.367716],"type":"Point"}
}