{
  "type": "Feature",
  "properties": {
    "addr:full":"1256 High St Armadale VIC 3143",
    "addr:housenumber":"1256",
    "addr:postcode":"3143",
    "addr:street":"High St",
    "iso:country":"AU",
    "sg:address":"1256 High St",
    "sg:city":"Armadale",
    "sg:classifiers":[
        {
            "category":"Education",
            "subcategory":"Special Training",
            "type":"Public Place"
        }
    ],
    "sg:phone":"+61 3 9509 2311",
    "sg:postcode":"3143",
    "sg:province":"VIC",
    "sg:tags":[
        "development"
    ],
    "wof:name":"Eva Holo Pty Ltd",
    "wof:placetype":"venue"
},
  "geometry": {"coordinates":[145.02850341800001,-37.8566169739],"type":"Point"}
}