{
  "type": "Feature",
  "properties": {
    "addr:full":"10-12 Gawler St Port Noarlunga SA 5167",
    "addr:housenumber":"10-12",
    "addr:postcode":"5167",
    "addr:street":"Gawler St",
    "iso:country":"AU",
    "sg:address":"10-12 Gawler St",
    "sg:city":"Port Noarlunga",
    "sg:classifiers":[
        {
            "category":"Retail",
            "subcategory":"Auto Repair",
            "type":"Services"
        }
    ],
    "sg:phone":"+61 8 8382 1239",
    "sg:postcode":"5167",
    "sg:province":"SA",
    "sg:tags":[
        "repairer",
        "motor",
        "engineer"
    ],
    "wof:name":"Seaside Automotive",
    "wof:placetype":"venue"
},
  "geometry": {"coordinates":[138.475265503,-35.1481552124],"type":"Point"}
}