{
  "type": "Feature",
  "properties": {
    "iso:country":"AU",
    "sg:address":"4 Anzac Rd",
    "sg:city":"Proserpine",
    "sg:classifiers":[
        {
            "category":"Professional",
            "type":"Services"
        }
    ],
    "sg:phone":"+61 7 4945 2699",
    "sg:postcode":"4800",
    "sg:province":"QLD",
    "sg:tags":[
        "transport"
    ],
    "wof:name":"Whitsunday Transport",
    "wof:placetype":"venue"
},
  "geometry": {"coordinates":[148.57815551799999,-20.4056549072],"type":"Point"}
}