{
  "type": "Feature",
  "properties": {
    "addr:full":"Unit 2 8 Erceg Rd Yangebup WA 6164",
    "addr:housenumber":"8",
    "addr:postcode":"6164",
    "addr:street":"Erceg Rd",
    "iso:country":"AU",
    "sg:address":"Unit 2 8 Erceg Rd",
    "sg:city":"Yangebup",
    "sg:classifiers":[
        {
            "category":"Home & Garden",
            "subcategory":"Building Materials",
            "type":"Retail Goods"
        }
    ],
    "sg:phone":"+61 8 9437 4436",
    "sg:postcode":"6164",
    "sg:province":"WA",
    "sg:tags":[
        "shutter",
        "roller",
        "grille"
    ],
    "wof:name":"Door Repairs WA",
    "wof:placetype":"venue"
},
  "geometry": {"coordinates":[115.796959,-32.120754],"type":"Point"}
}