{
  "type": "Feature",
  "properties": {
    "addr:full":"23- 25 Overton Rd Frankston VIC 3199",
    "addr:housenumber":"25",
    "addr:postcode":"3199",
    "addr:street":"Overton Rd",
    "iso:country":"AU",
    "sg:address":"23- 25 Overton Rd",
    "sg:city":"Frankston",
    "sg:classifiers":[
        {
            "category":"Health Services",
            "subcategory":"Health Practitioner",
            "type":"Services"
        }
    ],
    "sg:phone":"+61 3 9783 2600",
    "sg:postcode":"3199",
    "sg:province":"VIC",
    "sg:tags":[
        "dietitian"
    ],
    "wof:name":"Simone Manne",
    "wof:placetype":"venue"
},
  "geometry": {"coordinates":[145.13002014200001,-38.1295204163],"type":"Point"}
}