{
  "type": "Feature",
  "properties": {
    "iso:country":"AU",
    "sg:address":"Shop 2081 Knox City Shopping Centre, Burwood Hwy",
    "sg:city":"Wantirna",
    "sg:classifiers":[
        {
            "category":"Personal",
            "subcategory":"Skin Care",
            "type":"Services"
        }
    ],
    "sg:phone":"+61 3 9801 6064",
    "sg:postcode":"3152",
    "sg:province":"VIC",
    "sg:tags":[
        "hair",
        "product"
    ],
    "wof:name":"Price Attack",
    "wof:placetype":"venue"
},
  "geometry": {"coordinates":[145.21827697800001,-37.8631973267],"type":"Point"}
}