{
  "type": "Feature",
  "properties": {
    "addr:full":"19 Alexandra Pde Hamilton VIC 3300",
    "addr:housenumber":"19",
    "addr:postcode":"3300",
    "addr:street":"Alexandra Pde",
    "iso:country":"AU",
    "sg:address":"19 Alexandra Pde",
    "sg:city":"Hamilton",
    "sg:classifiers":[
        {
            "category":"Health Services",
            "subcategory":"Dentist",
            "type":"Services"
        }
    ],
    "sg:phone":"+61 3 5572 4316",
    "sg:postcode":"3300",
    "sg:province":"VIC",
    "wof:name":"Barke J J Dr",
    "wof:placetype":"venue"
},
  "geometry": {"coordinates":[142.02461242699999,-37.7392616272],"type":"Point"}
}