{
  "type": "Feature",
  "properties": {
    "iso:country":"AU",
    "sg:address":"10 Clive Rd",
    "sg:city":"Hawthorn East",
    "sg:classifiers":[
        {
            "category":"Shopping",
            "subcategory":"Computers & Home Electronics",
            "type":"Retail Goods"
        }
    ],
    "sg:phone":"+61 3 9517 2222",
    "sg:postcode":"3123",
    "sg:province":"VIC",
    "sg:tags":[
        "equipment",
        "multimedia"
    ],
    "wof:name":"Internet Playground The",
    "wof:placetype":"venue"
},
  "geometry": {"coordinates":[145.05003356899999,-37.8312911987],"type":"Point"}
}