{
  "type": "Feature",
  "properties": {
    "addr:full":"4 Blythe La Currambine WA 6028",
    "addr:housenumber":"4",
    "addr:postcode":"6028",
    "addr:street":"Blythe La",
    "iso:country":"AU",
    "sg:address":"4 Blythe La",
    "sg:city":"Currambine",
    "sg:classifiers":[
        {
            "category":"Building & Trades",
            "subcategory":"Landscaping Services",
            "type":"Services"
        }
    ],
    "sg:phone":"+61 417 726 655",
    "sg:postcode":"6028",
    "sg:province":"WA",
    "sg:tags":[
        "designer",
        "landscape",
        "contractor"
    ],
    "wof:name":"Addmore Outdoor",
    "wof:placetype":"venue"
},
  "geometry": {"coordinates":[115.741363525,-31.7302322388],"type":"Point"}
}