{
  "type": "Feature",
  "properties": {
    "iso:country":"AU",
    "sg:address":"Park Ave",
    "sg:city":"Athol Park",
    "sg:classifiers":[
        {
            "category":"Autos & Motor Vehicles",
            "subcategory":"Boat Sales",
            "type":"Retail Goods"
        }
    ],
    "sg:phone":"+61 8 8347 2851",
    "sg:postcode":"5012",
    "sg:province":"SA",
    "sg:tags":[
        "builder",
        "yacht",
        "repairer"
    ],
    "wof:name":"Wagner Marine Pty Ltd",
    "wof:placetype":"venue"
},
  "geometry": {"coordinates":[138.54185485799999,-34.8597450256],"type":"Point"}
}