{
  "type": "Feature",
  "properties": {
    "addr:full":"Suite 1 Cnr Ferntree Gully & Jells Rds Wheelers Hill VIC 3150",
    "addr:housenumber":"cnr",
    "addr:postcode":"3150",
    "iso:country":"AU",
    "sg:address":"Suite 1 Cnr Ferntree Gully & Jells Rds",
    "sg:city":"Wheelers Hill",
    "sg:classifiers":[
        {
            "category":"Arena",
            "subcategory":"Sports Club",
            "type":"Entertainment"
        }
    ],
    "sg:phone":"+61 3 9560 0217",
    "sg:postcode":"3150",
    "sg:province":"VIC",
    "sg:tags":[
        "defence",
        "supply",
        "self",
        "instruction",
        "martial art"
    ],
    "wof:name":"Northern Praying Mantis Kung-Fu Association",
    "wof:placetype":"venue"
},
  "geometry": {"coordinates":[145.189056397,-37.9067306519],"type":"Point"}
}