{
  "type": "Feature",
  "properties": {
    "addr:full":"2 Bush Nut Crt Little Mountain QLD 4551",
    "addr:housenumber":"2",
    "addr:postcode":"4551",
    "addr:street":"Bush Nut Crt",
    "iso:country":"AU",
    "sg:address":"2 Bush Nut Crt",
    "sg:city":"Little Mountain",
    "sg:classifiers":[
        {
            "category":"Professional",
            "subcategory":"Computer Services",
            "type":"Services"
        }
    ],
    "sg:phone":"+61 7 5492 7215",
    "sg:postcode":"4551",
    "sg:province":"QLD",
    "sg:tags":[
        "equipment",
        "networking",
        "installation"
    ],
    "wof:name":"MedPrac Networks",
    "wof:placetype":"venue"
},
  "geometry": {"coordinates":[153.08981323200001,-26.7749786377],"type":"Point"}
}