{
  "type": "Feature",
  "properties": {
    "addr:full":"23 Mining St Bundamba QLD 4304",
    "addr:housenumber":"23",
    "addr:postcode":"4304",
    "addr:street":"Mining St",
    "iso:country":"AU",
    "sg:address":"23 Mining St",
    "sg:city":"Bundamba",
    "sg:classifiers":[
        {
            "category":"Retail",
            "subcategory":"Storage",
            "type":"Services"
        }
    ],
    "sg:phone":"+61 7 3282 2563",
    "sg:postcode":"4304",
    "sg:province":"QLD",
    "wof:name":"Storage Choice",
    "wof:placetype":"venue"
},
  "geometry": {"coordinates":[152.80494689899999,-27.6077518463],"type":"Point"}
}