{
  "type": "Feature",
  "properties": {
    "addr:full":"22 Goodsir Pl Chisholm ACT 2905",
    "addr:housenumber":"22",
    "addr:postcode":"2905",
    "addr:street":"Goodsir Pl",
    "iso:country":"AU",
    "sg:address":"22 Goodsir Pl",
    "sg:city":"Chisholm",
    "sg:classifiers":[
        {
            "category":"Building & Trades",
            "subcategory":"Plumbing",
            "type":"Services"
        }
    ],
    "sg:phone":"+61 411 669 939",
    "sg:postcode":"2905",
    "sg:province":"ACT",
    "sg:tags":[
        "plumber",
        "gasfitters"
    ],
    "wof:name":"Independent Plumbing",
    "wof:placetype":"venue"
},
  "geometry": {"coordinates":[149.12774658199999,-35.4274024963],"type":"Point"}
}