{
  "type": "Feature",
  "properties": {
    "addr:full":"42 Burchell La Mirboo North VIC 3871",
    "addr:housenumber":"42",
    "addr:postcode":"3871",
    "addr:street":"Burchell La",
    "iso:country":"AU",
    "sg:address":"42 Burchell La",
    "sg:city":"Mirboo North",
    "sg:classifiers":[
        {
            "category":"Autos & Motor Vehicles",
            "subcategory":"Auto Supplies",
            "type":"Retail Goods"
        }
    ],
    "sg:phone":"+61 3 5668 1360",
    "sg:postcode":"3871",
    "sg:province":"VIC",
    "sg:tags":[
        "tyre"
    ],
    "wof:name":"Ken Graeme Motors",
    "wof:placetype":"venue"
},
  "geometry": {"coordinates":[146.16041564899999,-38.4020385742],"type":"Point"}
}