{
  "type": "Feature",
  "properties": {
    "addr:full":"1300 Mulgoa Rd Mulgoa NSW 2745",
    "addr:housenumber":"1300",
    "addr:postcode":"2745",
    "addr:street":"Mulgoa Rd",
    "iso:country":"AU",
    "sg:address":"1300 Mulgoa Rd",
    "sg:city":"Mulgoa",
    "sg:classifiers":[
        {
            "category":"Retail",
            "subcategory":"Event Space",
            "type":"Services"
        }
    ],
    "sg:phone":"+61 2 4773 8277",
    "sg:postcode":"2745",
    "sg:province":"NSW",
    "sg:tags":[
        "venue",
        "reception",
        "wedding"
    ],
    "wof:name":"Settlers Reception",
    "wof:placetype":"venue"
},
  "geometry": {"coordinates":[150.65434265100001,-33.8483848572],"type":"Point"}
}