{
  "type": "Feature",
  "properties": {
    "addr:full":"45 Gosport St Hemmant QLD 4174",
    "addr:housenumber":"45",
    "addr:postcode":"4174",
    "addr:street":"Gosport St",
    "iso:country":"AU",
    "sg:address":"45 Gosport St",
    "sg:city":"Hemmant",
    "sg:classifiers":[
        {
            "category":"Manufacturing",
            "subcategory":"Textiles",
            "type":"Manufacturing & Wholesale Goods"
        }
    ],
    "sg:phone":"+61 7 3890 4333",
    "sg:postcode":"4174",
    "sg:province":"QLD",
    "sg:tags":[
        "cotton"
    ],
    "wof:name":"Queensland Cotton Corporation Limited",
    "wof:placetype":"venue"
},
  "geometry": {"coordinates":[153.12977600100001,-27.4402713776],"type":"Point"}
}