{
  "type": "Feature",
  "properties": {
    "addr:full":"486 Albert St East Melbourne VIC 3002",
    "addr:housenumber":"486",
    "addr:postcode":"3002",
    "addr:street":"Albert St",
    "iso:country":"AU",
    "sg:address":"486 Albert St",
    "sg:city":"East Melbourne",
    "sg:classifiers":[
        {
            "category":"Organizations",
            "subcategory":"Professional Association",
            "type":"Services"
        }
    ],
    "sg:phone":"+61 3 8662 5248",
    "sg:postcode":"3002",
    "sg:province":"VIC",
    "sg:tags":[
        "organisation",
        "business"
    ],
    "wof:name":"Australian Corporate Lawyers Association",
    "wof:placetype":"venue"
},
  "geometry": {"coordinates":[144.97445678700001,-37.809173584],"type":"Point"}
}