{
  "type": "Feature",
  "properties": {
    "addr:full":"Shop 7 Gazebo Centre, 43 Williams St Raymond Terrace NSW 2324",
    "addr:housenumber":"shop 7;43",
    "addr:postcode":"2324",
    "addr:street":"Gazebo Centre;Williams St",
    "iso:country":"AU",
    "sg:address":"Shop 7 Gazebo Centre, 43 Williams St",
    "sg:city":"Raymond Terrace",
    "sg:classifiers":[
        {
            "category":"Professional",
            "subcategory":"Employment Agencies",
            "type":"Services"
        }
    ],
    "sg:phone":"+61 2 4987 7077",
    "sg:postcode":"2324",
    "sg:province":"NSW",
    "sg:tags":[
        "provider",
        "internet"
    ],
    "wof:name":"BMR.Net Internet Services",
    "wof:placetype":"venue"
},
  "geometry": {"coordinates":[151.743530273,-32.7620277405],"type":"Point"}
}