{
  "type": "Feature",
  "properties": {
    "addr:full":"1 Darling St Echuca VIC 3564",
    "addr:housenumber":"1",
    "addr:postcode":"3564",
    "addr:street":"Darling St",
    "iso:country":"AU",
    "sg:address":"1 Darling St",
    "sg:city":"Echuca",
    "sg:classifiers":[
        {
            "category":"Retail",
            "subcategory":"Storage",
            "type":"Services"
        }
    ],
    "sg:phone":"+61 1800 852 278",
    "sg:postcode":"3564",
    "sg:province":"VIC",
    "sg:tags":[
        "removal",
        "furniture"
    ],
    "wof:name":"Fast Moves Australia",
    "wof:placetype":"venue"
},
  "geometry": {"coordinates":[144.764526367,-36.1291427612],"type":"Point"}
}