{
  "type": "Feature",
  "properties": {
    "addr:full":"57 Goondoon St Gladstone QLD 4680",
    "addr:housenumber":"57",
    "addr:postcode":"4680",
    "addr:street":"Goondoon St",
    "iso:country":"AU",
    "sg:address":"57 Goondoon St",
    "sg:city":"Gladstone",
    "sg:classifiers":[
        {
            "category":"Shopping",
            "subcategory":"Clothing, Apparel, & Fashions",
            "type":"Retail Goods"
        }
    ],
    "sg:phone":"+61 7 4972 2424",
    "sg:postcode":"4680",
    "sg:province":"QLD",
    "sg:tags":[
        "menswear"
    ],
    "wof:name":"Cavalier's Menswear & Suit Hire",
    "wof:placetype":"venue"
},
  "geometry": {"coordinates":[151.254394531,-23.8412532806],"type":"Point"}
}