{
  "type": "Feature",
  "properties": {
    "addr:full":"12 Langi Crt Shailer Park QLD 4128",
    "addr:housenumber":"12",
    "addr:postcode":"4128",
    "addr:street":"Langi Crt",
    "iso:country":"AU",
    "sg:address":"12 Langi Crt",
    "sg:city":"Shailer Park",
    "sg:classifiers":[
        {
            "category":"Utilities",
            "subcategory":"Water",
            "type":"Services"
        }
    ],
    "sg:phone":"+61 411 195 808",
    "sg:postcode":"4128",
    "sg:province":"QLD",
    "sg:tags":[
        "equipment",
        "treatment"
    ],
    "wof:name":"Australian E.P.A. Services",
    "wof:placetype":"venue"
},
  "geometry": {"coordinates":[153.18499755900001,-27.6521587372],"type":"Point"}
}