{
  "type": "Feature",
  "properties": {
    "iso:country":"AU",
    "sg:address":"1/ 1 Boden Rd",
    "sg:city":"Seven Hills",
    "sg:classifiers":[
        {
            "category":"Building & Trades",
            "subcategory":"Construction",
            "type":"Services"
        }
    ],
    "sg:phone":"+61 2 9838 8151",
    "sg:postcode":"2147",
    "sg:province":"NSW",
    "sg:tags":[
        "equipment",
        "system",
        "automation"
    ],
    "sg:website":"http://www.apexautomation.com.au",
    "wof:name":"Apex Automation & Robotics",
    "wof:placetype":"venue"
},
  "geometry": {"coordinates":[150.95954895,-33.7744789124],"type":"Point"}
}