{
  "type": "Feature",
  "properties": {
    "iso:country":"AU",
    "sg:address":"857 Marion Rd",
    "sg:city":"Mitchell Park",
    "sg:classifiers":[
        {
            "category":"Health Services",
            "subcategory":"Dentist",
            "type":"Services"
        }
    ],
    "sg:phone":"+61 8 8277 6025",
    "sg:postcode":"5043",
    "sg:province":"SA",
    "wof:name":"Barva Melinda Dr",
    "wof:placetype":"venue"
},
  "geometry": {"coordinates":[138.55905200000001,-35.01659],"type":"Point"}
}