{
  "type": "Feature",
  "properties": {
    "iso:country":"AU",
    "sg:address":"169- 181 Herries St",
    "sg:city":"Toowoomba",
    "sg:classifiers":[
        {
            "category":"Autos & Motor Vehicles",
            "subcategory":"Automobile Sales",
            "type":"Retail Goods"
        }
    ],
    "sg:phone":"+61 7 4631 9999",
    "sg:postcode":"4350",
    "sg:province":"QLD",
    "sg:tags":[
        "car",
        "new"
    ],
    "wof:name":"Wippells Autos",
    "wof:placetype":"venue"
},
  "geometry": {"coordinates":[151.93588299999999,-27.562],"type":"Point"}
}