{
  "type": "Feature",
  "properties": {
    "iso:country":"AU",
    "sg:address":"259 Collins St",
    "sg:city":"Melbourne",
    "sg:classifiers":[
        {
            "category":"Shopping",
            "subcategory":"Stationery & Office Supplies",
            "type":"Retail Goods"
        }
    ],
    "sg:phone":"+61 3 9654 7993",
    "sg:postcode":"3000",
    "sg:province":"VIC",
    "sg:tags":[
        "pencil",
        "pen",
        "repair"
    ],
    "wof:name":"Tafts The Pen People",
    "wof:placetype":"venue"
},
  "geometry": {"coordinates":[144.965332031,-37.8159713745],"type":"Point"}
}