{
  "type": "Feature",
  "properties": {
    "addr:full":"91 William St North Manly NSW 2100",
    "addr:housenumber":"91",
    "addr:postcode":"2100",
    "addr:street":"William St North",
    "iso:country":"AU",
    "sg:address":"91 William St",
    "sg:city":"North Manly",
    "sg:classifiers":[
        {
            "category":"Farming",
            "subcategory":"Fish & Marine Products",
            "type":"Manufacturing & Wholesale Goods"
        }
    ],
    "sg:phone":"+61 2 9907 2048",
    "sg:postcode":"2100",
    "sg:province":"NSW",
    "sg:tags":[
        "equipment",
        "salvage"
    ],
    "wof:name":"Shoreside Electrical Services Pty Ltd",
    "wof:placetype":"venue"
},
  "geometry": {"coordinates":[151.27619934099999,-33.7698326111],"type":"Point"}
}