{
  "type": "Feature",
  "properties": {
    "iso:country":"AU",
    "sg:address":"Ivanhoe Rd",
    "sg:city":"Balranald",
    "sg:classifiers":[
        {
            "category":"Manufacturing",
            "subcategory":"Lumber",
            "type":"Manufacturing & Wholesale Goods"
        }
    ],
    "sg:phone":"+61 3 5020 1573",
    "sg:postcode":"2715",
    "sg:province":"NSW",
    "sg:tags":[
        "sawmillers"
    ],
    "wof:name":"Riverina Red Gum",
    "wof:placetype":"venue"
},
  "geometry": {"coordinates":[143.57148742699999,-34.6316375732],"type":"Point"}
}