{
  "type": "Feature",
  "properties": {
    "addr:full":"Governor Rd Mordialloc VIC 3195",
    "addr:postcode":"3195",
    "addr:street":"Governor Rd",
    "iso:country":"AU",
    "sg:address":"Governor Rd",
    "sg:city":"Mordialloc",
    "sg:classifiers":[
        {
            "category":"Communications",
            "subcategory":"Film & Video Production",
            "type":"Services"
        }
    ],
    "sg:phone":"+61 3 9588 0230",
    "sg:postcode":"3195",
    "sg:province":"VIC",
    "sg:tags":[
        "information",
        "recorded",
        "telephone"
    ],
    "wof:name":"Tatyana- Voice Over Artist",
    "wof:placetype":"venue"
},
  "geometry": {"coordinates":[145.092987061,-38.0097465515],"type":"Point"}
}