{
  "type": "Feature",
  "properties": {
    "addr:full":"78 Northern Ave West Beach SA 5024",
    "addr:housenumber":"78",
    "addr:postcode":"5024",
    "addr:street":"Northern Ave",
    "iso:country":"AU",
    "sg:address":"78 Northern Ave",
    "sg:city":"West Beach",
    "sg:classifiers":[
        {
            "category":"Home & Garden",
            "subcategory":"Hardware",
            "type":"Retail Goods"
        }
    ],
    "sg:phone":"+61 8 8353 7722",
    "sg:postcode":"5024",
    "sg:province":"SA",
    "sg:tags":[
        "plumber",
        "supply"
    ],
    "wof:name":"J & W Sales Pty Ltd",
    "wof:placetype":"venue"
},
  "geometry": {"coordinates":[138.50889587399999,-34.9403762817],"type":"Point"}
}