{
  "type": "Feature",
  "properties": {
    "addr:full":"42 Popes Rd Keysborough VIC 3173",
    "addr:housenumber":"42",
    "addr:postcode":"3173",
    "addr:street":"Popes Rd",
    "iso:country":"AU",
    "sg:address":"42 Popes Rd",
    "sg:city":"Keysborough",
    "sg:classifiers":[
        {
            "category":"Wholesale",
            "subcategory":"Machinery & Supplies",
            "type":"Manufacturing & Wholesale Goods"
        }
    ],
    "sg:phone":"+61 3 9798 7522",
    "sg:postcode":"3173",
    "sg:province":"VIC",
    "sg:tags":[
        "equipment",
        "hydraulic"
    ],
    "wof:name":"A.D. Automation",
    "wof:placetype":"venue"
},
  "geometry": {"coordinates":[145.188720703,-37.9827308655],"type":"Point"}
}