{
  "type": "Feature",
  "properties": {
    "addr:full":"17 Col Braund Crs Kingsford NSW 2032",
    "addr:housenumber":"17",
    "addr:postcode":"2032",
    "addr:street":"Col Braund Crs",
    "iso:country":"AU",
    "sg:address":"17 Col Braund Crs",
    "sg:city":"Kingsford",
    "sg:classifiers":[
        {
            "category":"Building & Trades",
            "subcategory":"Construction",
            "type":"Services"
        }
    ],
    "sg:phone":"+61 2 9314 1219",
    "sg:postcode":"2032",
    "sg:province":"NSW",
    "sg:tags":[
        "joiner",
        "carpenter"
    ],
    "wof:name":"Patrick Glasheen Carpentry",
    "wof:placetype":"venue"
},
  "geometry": {"coordinates":[151.227493286,-33.9234886169],"type":"Point"}
}