{
  "type": "Feature",
  "properties": {
    "addr:full":"5 Rina Crt Varsity Lakes QLD 4226",
    "addr:housenumber":"5",
    "addr:postcode":"4226",
    "addr:street":"Rina Crt",
    "iso:country":"AU",
    "sg:address":"5 Rina Crt",
    "sg:city":"Varsity Lakes",
    "sg:classifiers":[
        {
            "category":"Home & Garden",
            "subcategory":"Building Materials",
            "type":"Retail Goods"
        }
    ],
    "sg:phone":"+61 7 5593 7188",
    "sg:postcode":"4226",
    "sg:province":"QLD",
    "sg:tags":[
        "supply"
    ],
    "wof:name":"Burleigh Secondhand Building Materials",
    "wof:placetype":"venue"
},
  "geometry": {"coordinates":[153.41113281200001,-28.1009159088],"type":"Point"}
}