{
  "type": "Feature",
  "properties": {
    "iso:country":"AU",
    "sg:address":"250 Clanfield St",
    "sg:city":"North Rockhampton",
    "sg:classifiers":[
        {
            "category":"Utilities",
            "subcategory":"Electric",
            "type":"Services"
        }
    ],
    "sg:phone":"+61 7 4926 1473",
    "sg:postcode":"4701",
    "sg:province":"QLD",
    "sg:tags":[
        "electrical",
        "contractor"
    ],
    "wof:name":"Clarke Lawre",
    "wof:placetype":"venue"
},
  "geometry": {"coordinates":[150.53474426299999,-23.3588581085],"type":"Point"}
}