{
  "type": "Feature",
  "properties": {
    "addr:full":"PO Box 1521 Mountain Creek QLD 4557",
    "addr:postcode":"4557",
    "iso:country":"AU",
    "sg:address":"PO Box 1521",
    "sg:city":"Mountain Creek",
    "sg:classifiers":[
        {
            "category":"Banks & Credit Unions",
            "subcategory":"Investment Brokerage",
            "type":"Services"
        }
    ],
    "sg:phone":"+61 7 5444 8577",
    "sg:postcode":"4557",
    "sg:province":"QLD",
    "sg:tags":[
        "finance",
        "broker"
    ],
    "wof:name":"Stallion Home Loans",
    "wof:placetype":"venue"
},
  "geometry": {"coordinates":[153.10214233400001,-26.6998100281],"type":"Point"}
}