{
  "type": "Feature",
  "properties": {
    "iso:country":"AU",
    "sg:address":"15 Eden Drv",
    "sg:city":"Eatons Hill",
    "sg:classifiers":[
        {
            "category":"Building & Trades",
            "subcategory":"Construction",
            "type":"Services"
        }
    ],
    "sg:phone":"+61 7 3264 3164",
    "sg:postcode":"4037",
    "sg:province":"QLD",
    "sg:tags":[
        "contractor"
    ],
    "wof:name":"Keith Collett",
    "wof:placetype":"venue"
},
  "geometry": {"coordinates":[152.939377,-27.332882],"type":"Point"}
}