{
  "type": "Feature",
  "properties": {
    "addr:full":"16 Arvida St Malaga WA 6090",
    "addr:housenumber":"16",
    "addr:postcode":"6090",
    "addr:street":"Arvida St",
    "iso:country":"AU",
    "sg:address":"16 Arvida St",
    "sg:city":"Malaga",
    "sg:classifiers":[
        {
            "category":"Bus Stop",
            "subcategory":"None",
            "type":"Transportation"
        }
    ],
    "sg:phone":"+61 8 9249 9660",
    "sg:postcode":"6090",
    "sg:province":"WA",
    "sg:tags":[
        "pipe",
        "fitting",
        "metal"
    ],
    "wof:name":"Total Alloys Pty Ltd",
    "wof:placetype":"venue"
},
  "geometry": {"coordinates":[115.884460449,-31.85663414],"type":"Point"}
}