{
  "type": "Feature",
  "properties": {
    "addr:full":"48 Hawthory Rd Kilsyth VIC 3137",
    "addr:housenumber":"48",
    "addr:postcode":"3137",
    "addr:street":"Hawthory Rd",
    "iso:country":"AU",
    "sg:address":"48 Hawthory Rd",
    "sg:city":"Kilsyth",
    "sg:classifiers":[
        {
            "category":"Building & Trades",
            "subcategory":"Construction",
            "type":"Services"
        }
    ],
    "sg:phone":"+61 418 538 248",
    "sg:postcode":"3137",
    "sg:province":"VIC",
    "sg:tags":[
        "polishing",
        "sanding",
        "floor"
    ],
    "wof:name":"Chris Jeffrey",
    "wof:placetype":"venue"
},
  "geometry": {"coordinates":[145.313430786,-37.7972335815],"type":"Point"}
}