{
  "type": "Feature",
  "properties": {
    "iso:country":"AU",
    "sg:address":"84- 86 Lomandra Drv",
    "sg:city":"Brisbane Airport",
    "sg:classifiers":[
        {
            "category":"Professional",
            "subcategory":"Management & Consulting",
            "type":"Services"
        }
    ],
    "sg:phone":"+61 7 3271 1155",
    "sg:postcode":"4007",
    "sg:province":"QLD",
    "sg:tags":[
        "consultant",
        "relocation"
    ],
    "wof:name":"Dogtainers",
    "wof:placetype":"venue"
},
  "geometry": {"coordinates":[153.120361,-27.417574],"type":"Point"}
}