{
  "type": "Feature",
  "properties": {
    "iso:country":"AU",
    "sg:address":"Suite 6a, Bay Shopping Village Fishery Point Rd",
    "sg:city":"Bonnells Bay",
    "sg:classifiers":[
        {
            "category":"Health Services",
            "subcategory":"Medical Lab",
            "type":"Services"
        }
    ],
    "sg:phone":"+61 2 4973 5846",
    "sg:postcode":"2264",
    "sg:province":"NSW",
    "sg:tags":[
        "laboratory",
        "pathology"
    ],
    "wof:name":"Sydney Adventist Pathology & Specialist Centre",
    "wof:placetype":"venue"
},
  "geometry": {"coordinates":[151.524811,-33.111774],"type":"Point"}
}