{
  "type": "Feature",
  "properties": {
    "addr:full":"459 Merrylands Rd Merrylands NSW 2160",
    "addr:housenumber":"459",
    "addr:postcode":"2160",
    "addr:street":"Merrylands Rd",
    "iso:country":"AU",
    "sg:address":"459 Merrylands Rd",
    "sg:city":"Merrylands",
    "sg:classifiers":[
        {
            "category":"Fast Food",
            "type":"Food & Drink"
        }
    ],
    "sg:phone":"+61 2 9637 3335",
    "sg:postcode":"2160",
    "sg:province":"NSW",
    "sg:tags":[
        "away",
        "take"
    ],
    "wof:name":"Nikki's Desserts Delivered",
    "wof:placetype":"venue"
},
  "geometry": {"coordinates":[150.97157287600001,-33.8326072693],"type":"Point"}
}