{
  "type": "Feature",
  "properties": {
    "addr:full":"72 Jasper Rd Baulkham Hills NSW 2153",
    "addr:housenumber":"72",
    "addr:postcode":"2153",
    "addr:street":"Jasper Rd",
    "iso:country":"AU",
    "sg:address":"72 Jasper Rd",
    "sg:city":"Baulkham Hills",
    "sg:classifiers":[
        {
            "category":"Building & Trades",
            "subcategory":"Construction",
            "type":"Services"
        }
    ],
    "sg:phone":"+61 2 9639 6755",
    "sg:postcode":"2153",
    "sg:province":"NSW",
    "sg:tags":[
        "plasterboard",
        "plasterer",
        "fixer"
    ],
    "wof:name":"Hills Rendering",
    "wof:placetype":"venue"
},
  "geometry": {"coordinates":[150.977752686,-33.755115509],"type":"Point"}
}