{
  "type": "Feature",
  "properties": {
    "addr:full":"138 Juliette St Greenslopes QLD 4120",
    "addr:housenumber":"138",
    "addr:postcode":"4120",
    "addr:street":"Juliette St",
    "iso:country":"AU",
    "sg:address":"138 Juliette St",
    "sg:city":"Greenslopes",
    "sg:classifiers":[
        {
            "category":"Health Services",
            "subcategory":"Doctor",
            "type":"Services"
        }
    ],
    "sg:phone":"+61 7 3421 2800",
    "sg:postcode":"4120",
    "sg:province":"QLD",
    "sg:tags":[
        "nurse",
        "nursing"
    ],
    "wof:name":"Spiritus - Care Services",
    "wof:placetype":"venue"
},
  "geometry": {"coordinates":[153.043457031,-27.5046291351],"type":"Point"}
}