{
  "type": "Feature",
  "properties": {
    "addr:full":"1/ 10 Holdsworth St Neutral Bay NSW 2089",
    "addr:housenumber":"/ 10",
    "addr:postcode":"2089",
    "addr:street":"Holdsworth St",
    "iso:country":"AU",
    "sg:address":"1/ 10 Holdsworth St",
    "sg:city":"Neutral Bay",
    "sg:classifiers":[
        {
            "category":"Real Estate",
            "subcategory":"Surveying",
            "type":"Services"
        }
    ],
    "sg:phone":"+61 2 9954 7037",
    "sg:postcode":"2089",
    "sg:province":"NSW",
    "sg:tags":[
        "surveyor",
        "land"
    ],
    "wof:name":"Sutherland Ian & Associates",
    "wof:placetype":"venue"
},
  "geometry": {"coordinates":[151.214569092,-33.8384666443],"type":"Point"}
}