{
  "type": "Feature",
  "properties": {
    "addr:full":"Lot 8 Ferrerro Crs West Hoxton NSW 2171",
    "addr:postcode":"2171",
    "addr:street":"Crs West",
    "iso:country":"AU",
    "sg:address":"Lot 8 Ferrerro Crs",
    "sg:city":"West Hoxton",
    "sg:classifiers":[
        {
            "category":"Building & Trades",
            "subcategory":"Construction",
            "type":"Services"
        }
    ],
    "sg:phone":"+61 412 450 868",
    "sg:postcode":"2171",
    "sg:province":"NSW",
    "sg:tags":[
        "rendering",
        "cement"
    ],
    "wof:name":"Hoxton Park Cement Rendering",
    "wof:placetype":"venue"
},
  "geometry": {"coordinates":[150.84800720199999,-33.9289321899],"type":"Point"}
}