{
  "type": "Feature",
  "properties": {
    "iso:country":"AU",
    "sg:address":"7- 9 Aster Ave",
    "sg:city":"Carrum Downs",
    "sg:classifiers":[
        {
            "category":"Professional",
            "subcategory":"Accounting & Tax Preparation",
            "type":"Services"
        }
    ],
    "sg:phone":"+61 3 9775 0460",
    "sg:postcode":"3201",
    "sg:province":"VIC",
    "sg:tags":[
        "insulation",
        "wholesaler",
        "material",
        "mfrs"
    ],
    "wof:name":"Battmans Insulating Services Pty Ltd",
    "wof:placetype":"venue"
},
  "geometry": {"coordinates":[145.166901,-38.103958],"type":"Point"}
}