{
  "type": "Feature",
  "properties": {
    "addr:full":"Howards Cygnet Central Mary St Cygnet TAS 7112",
    "addr:postcode":"7112",
    "addr:street":"Mary St",
    "iso:country":"AU",
    "sg:address":"Howards Cygnet Central Mary St",
    "sg:city":"Cygnet",
    "sg:classifiers":[
        {
            "category":"Food & Beverages",
            "subcategory":"Liquor & Beverages",
            "type":"Retail Goods"
        }
    ],
    "sg:phone":"+61 3 6295 1244",
    "sg:postcode":"7112",
    "sg:province":"TAS",
    "sg:tags":[
        "store"
    ],
    "wof:name":"Liquorwise",
    "wof:placetype":"venue"
},
  "geometry": {"coordinates":[147.073928833,-43.1555862427],"type":"Point"}
}