{
  "type": "Feature",
  "properties": {
    "addr:full":"Cessnock Rd North Rothbury NSW 2335",
    "addr:postcode":"2335",
    "addr:street":"Cessnock Rd",
    "iso:country":"AU",
    "sg:address":"Cessnock Rd",
    "sg:city":"North Rothbury",
    "sg:classifiers":[
        {
            "category":"Museum",
            "type":"Entertainment"
        }
    ],
    "sg:phone":"+61 2 4930 7758",
    "sg:postcode":"2335",
    "sg:province":"NSW",
    "wof:name":"The Hunter Valley Railway Museum Trust",
    "wof:placetype":"venue"
},
  "geometry": {"coordinates":[151.34518432600001,-32.6808509827],"type":"Point"}
}