{
  "type": "Feature",
  "properties": {
    "addr:full":"252 Thompson Rd North Geelong VIC 3215",
    "addr:housenumber":"252",
    "addr:postcode":"3215",
    "addr:street":"Thompson Rd",
    "iso:country":"AU",
    "sg:address":"252 Thompson Rd",
    "sg:city":"North Geelong",
    "sg:classifiers":[
        {
            "category":"Utilities",
            "subcategory":"Water",
            "type":"Services"
        }
    ],
    "sg:phone":"+61 3 5278 7985",
    "sg:postcode":"3215",
    "sg:province":"VIC",
    "sg:tags":[
        "hot",
        "system"
    ],
    "wof:name":"Specialized Solar Solutions",
    "wof:placetype":"venue"
},
  "geometry": {"coordinates":[144.34381103499999,-38.1096420288],"type":"Point"}
}