{
  "type": "Feature",
  "properties": {
    "addr:full":"110 Redfern St Wetherill Park NSW 2164",
    "addr:housenumber":"110",
    "addr:postcode":"2164",
    "addr:street":"Redfern St",
    "iso:country":"AU",
    "sg:address":"110 Redfern St",
    "sg:city":"Wetherill Park",
    "sg:classifiers":[
        {
            "category":"Retail",
            "subcategory":"Auto Repair",
            "type":"Services"
        }
    ],
    "sg:phone":"+61 2 9757 3406",
    "sg:postcode":"2164",
    "sg:province":"NSW",
    "sg:tags":[
        "bus",
        "truck"
    ],
    "wof:name":"Gough & Gilmour Holdings Pty Ltd",
    "wof:placetype":"venue"
},
  "geometry": {"coordinates":[150.920211792,-33.8448791504],"type":"Point"}
}