{
  "type": "Feature",
  "properties": {
    "addr:full":"Shp 90/ 314 Childs Rd Mill Park VIC 3082",
    "addr:housenumber":"90 / 314",
    "addr:postcode":"3082",
    "addr:street":"Childs Rd",
    "iso:country":"AU",
    "sg:address":"Shp 90/ 314 Childs Rd",
    "sg:city":"Mill Park",
    "sg:classifiers":[
        {
            "category":"Shopping",
            "subcategory":"Clothing, Apparel, & Fashions",
            "type":"Retail Goods"
        }
    ],
    "sg:phone":"+61 3 9436 0666",
    "sg:postcode":"3082",
    "sg:province":"VIC",
    "sg:tags":[
        "lady",
        "wear"
    ],
    "wof:name":"Fashion Busters",
    "wof:placetype":"venue"
},
  "geometry": {"coordinates":[145.061935425,-37.667137146],"type":"Point"}
}