{
  "type": "Feature",
  "properties": {
    "addr:full":"2b Birdwood Rd Georges Hall NSW 2198",
    "addr:housenumber":"2b",
    "addr:postcode":"2198",
    "addr:street":"Birdwood Rd",
    "iso:country":"AU",
    "sg:address":"2b Birdwood Rd",
    "sg:city":"Georges Hall",
    "sg:classifiers":[
        {
            "category":"Shopping Center",
            "type":"Public Place"
        }
    ],
    "sg:phone":"+61 2 9790 6658",
    "sg:postcode":"2198",
    "sg:province":"NSW",
    "sg:tags":[
        "spawn",
        "supplier",
        "mushroom"
    ],
    "wof:name":"E & J Marland Pty Ltd",
    "wof:placetype":"venue"
},
  "geometry": {"coordinates":[150.994339,-33.913418],"type":"Point"}
}