{
  "type": "Feature",
  "properties": {
    "addr:full":"Stentiford Rd Forest Range SA 5139",
    "addr:postcode":"5139",
    "addr:street":"Stentiford Rd",
    "iso:country":"AU",
    "sg:address":"Stentiford Rd",
    "sg:city":"Forest Range",
    "sg:classifiers":[
        {
            "category":"Farming",
            "subcategory":"Orchard",
            "type":"Manufacturing & Wholesale Goods"
        }
    ],
    "sg:phone":"+61 8 8389 8330",
    "sg:postcode":"5139",
    "sg:province":"SA",
    "sg:tags":[
        "pear",
        "apple",
        "grower"
    ],
    "wof:name":"Collins Orchards",
    "wof:placetype":"venue"
},
  "geometry": {"coordinates":[138.804321289,-34.9348602295],"type":"Point"}
}