{
  "type": "Feature",
  "properties": {
    "addr:full":"7/ 60 Compton Rd Woodridge QLD 4114",
    "addr:housenumber":"/ 60",
    "addr:postcode":"4114",
    "addr:street":"Compton Rd",
    "iso:country":"AU",
    "sg:address":"7/ 60 Compton Rd",
    "sg:city":"Woodridge",
    "sg:classifiers":[
        {
            "category":"Professional",
            "subcategory":"Printing & Photocopies",
            "type":"Services"
        }
    ],
    "sg:phone":"+61 1300 666 233",
    "sg:postcode":"4114",
    "sg:province":"QLD",
    "sg:tags":[
        "photocopier"
    ],
    "wof:name":"Office 1 Pty Ltd",
    "wof:placetype":"venue"
},
  "geometry": {"coordinates":[153.10992431599999,-27.6195430756],"type":"Point"}
}