{
  "type": "Feature",
  "properties": {
    "addr:full":"Henty Hwy Portland VIC 3305",
    "addr:postcode":"3305",
    "addr:street":"Henty Hwy",
    "iso:country":"AU",
    "sg:address":"Henty Hwy",
    "sg:city":"Portland",
    "sg:classifiers":[
        {
            "category":"Autos & Motor Vehicles",
            "subcategory":"Auto Supplies",
            "type":"Retail Goods"
        }
    ],
    "sg:phone":"+61 3 5521 7227",
    "sg:postcode":"3305",
    "sg:province":"VIC",
    "sg:tags":[
        "oil",
        "spirit"
    ],
    "wof:name":"Shell Co Of Australia Ltd",
    "wof:placetype":"venue"
},
  "geometry": {"coordinates":[141.61424255399999,-38.3552856445],"type":"Point"}
}