{
  "type": "Feature",
  "properties": {
    "addr:full":"678 Sydney Rd Brunswick VIC 3056",
    "addr:housenumber":"678",
    "addr:postcode":"3056",
    "addr:street":"Sydney Rd",
    "iso:country":"AU",
    "sg:address":"678 Sydney Rd",
    "sg:city":"Brunswick",
    "sg:classifiers":[
        {
            "category":"Government",
            "subcategory":"Court House",
            "type":"Public Place"
        }
    ],
    "sg:phone":"+61 3 9386 4665",
    "sg:postcode":"3056",
    "sg:province":"VIC",
    "sg:tags":[
        "personal",
        "marriage",
        "family",
        "counselling"
    ],
    "wof:name":"Trish Parker Counsellor",
    "wof:placetype":"venue"
},
  "geometry": {"coordinates":[144.963180542,-37.761592865],"type":"Point"}
}