{
  "type": "Feature",
  "properties": {
    "iso:country":"AU",
    "sg:address":"Shop 4, 210 - 222 Cowper St",
    "sg:city":"Warrawong",
    "sg:classifiers":[
        {
            "category":"Banks & Credit Unions",
            "subcategory":"Investment Brokerage",
            "type":"Services"
        }
    ],
    "sg:phone":"+61 2 4276 4899",
    "sg:postcode":"2502",
    "sg:province":"NSW",
    "sg:tags":[
        "cashing",
        "cheque"
    ],
    "wof:name":"AMX Money",
    "wof:placetype":"venue"
},
  "geometry": {"coordinates":[150.886673,-34.485294],"type":"Point"}
}