{
  "type": "Feature",
  "properties": {
    "iso:country":"AU",
    "sg:address":"402 Chapel St",
    "sg:city":"South Yarra",
    "sg:classifiers":[
        {
            "category":"Personal",
            "subcategory":"Beauty Salon",
            "type":"Services"
        }
    ],
    "sg:phone":"+61 3 9827 3295",
    "sg:postcode":"3141",
    "sg:province":"VIC",
    "sg:tags":[
        "hairdresser"
    ],
    "wof:name":"Linx Hairdressing",
    "wof:placetype":"venue"
},
  "geometry": {"coordinates":[144.99465942399999,-37.8450164795],"type":"Point"}
}