{
  "type": "Feature",
  "properties": {
    "addr:full":"18 Kennedy St Glen Waverley VIC 3150",
    "addr:housenumber":"18",
    "addr:postcode":"3150",
    "addr:street":"Kennedy St",
    "iso:country":"AU",
    "sg:address":"18 Kennedy St",
    "sg:city":"Glen Waverley",
    "sg:classifiers":[
        {
            "category":"Real Estate",
            "subcategory":"Real Estate Services",
            "type":"Services"
        }
    ],
    "sg:phone":"+61 3 9803 7362",
    "sg:postcode":"3150",
    "sg:province":"VIC",
    "sg:tags":[
        "consultant",
        "property"
    ],
    "wof:name":"Braid S R",
    "wof:placetype":"venue"
},
  "geometry": {"coordinates":[145.169830322,-37.8763999939],"type":"Point"}
}