{
  "type": "Feature",
  "properties": {
    "iso:country":"AU",
    "sg:address":"Western Hwy",
    "sg:city":"Horsham",
    "sg:classifiers":[
        {
            "category":"Autos & Motor Vehicles",
            "subcategory":"Automobile Sales",
            "type":"Retail Goods"
        }
    ],
    "sg:phone":"+61 3 5382 4677",
    "sg:postcode":"3400",
    "sg:province":"VIC",
    "sg:tags":[
        "car",
        "new"
    ],
    "wof:name":"Dick Wilson Ford",
    "wof:placetype":"venue"
},
  "geometry": {"coordinates":[142.198776245,-36.7116622925],"type":"Point"}
}