{
  "type": "Feature",
  "properties": {
    "addr:full":"22 Vintage Ave Hackham SA 5163",
    "addr:housenumber":"22",
    "addr:postcode":"5163",
    "addr:street":"Vintage Ave",
    "iso:country":"AU",
    "sg:address":"22 Vintage Ave",
    "sg:city":"Hackham",
    "sg:classifiers":[
        {
            "category":"Building & Trades",
            "subcategory":"Cleaning & Sanitation",
            "type":"Services"
        }
    ],
    "sg:phone":"+61 8 8384 8613",
    "sg:postcode":"5163",
    "sg:province":"SA",
    "sg:tags":[
        "industrial",
        "commercial",
        "contractor"
    ],
    "wof:name":"Matrix Quality Cleaning Services",
    "wof:placetype":"venue"
},
  "geometry": {"coordinates":[138.53619384800001,-35.1459541321],"type":"Point"}
}