{
  "type": "Feature",
  "properties": {
    "addr:full":"1093a Benetook Ave Mildura VIC 3500",
    "addr:housenumber":"1093a",
    "addr:postcode":"3500",
    "addr:street":"Benetook Ave",
    "iso:country":"AU",
    "sg:address":"1093a Benetook Ave",
    "sg:city":"Mildura",
    "sg:classifiers":[
        {
            "category":"Retail",
            "subcategory":"Auto Repair",
            "type":"Services"
        }
    ],
    "sg:phone":"+61 3 5023 2538",
    "sg:postcode":"3500",
    "sg:province":"VIC",
    "sg:tags":[
        "bus",
        "truck"
    ],
    "wof:name":"Mitchell Truck Repairs",
    "wof:placetype":"venue"
},
  "geometry": {"coordinates":[142.173751831,-34.2003364563],"type":"Point"}
}