{
  "type": "Feature",
  "properties": {
    "addr:full":"PO Box 372 Jimboomba QLD 4280",
    "addr:postcode":"4280",
    "iso:country":"AU",
    "sg:address":"PO Box 372",
    "sg:city":"Jimboomba",
    "sg:classifiers":[
        {
            "category":"Professional",
            "subcategory":"Art Services",
            "type":"Services"
        }
    ],
    "sg:phone":"+61 409 992 324",
    "sg:postcode":"4280",
    "sg:province":"QLD",
    "sg:tags":[
        "medical",
        "industrial",
        "gas"
    ],
    "wof:name":"Cryotech Industries",
    "wof:placetype":"venue"
},
  "geometry": {"coordinates":[153.02887000000001,-27.813459],"type":"Point"}
}