{
  "type": "Feature",
  "properties": {
    "iso:country":"AU",
    "sg:address":"PO Box 1093",
    "sg:city":"Lalor",
    "sg:classifiers":[
        {
            "category":"Professional",
            "subcategory":"Detective & Security Services",
            "type":"Services"
        }
    ],
    "sg:phone":"+61 409 211 248",
    "sg:postcode":"3075",
    "sg:province":"VIC",
    "sg:tags":[
        "guard",
        "patrol"
    ],
    "wof:name":"Alef Protective Security Service",
    "wof:placetype":"venue"
},
  "geometry": {"coordinates":[145.00875854500001,-37.6659889221],"type":"Point"}
}