{
  "type": "Feature",
  "properties": {
    "iso:country":"AU",
    "sg:address":"14 Bayview Pl",
    "sg:city":"Bayview",
    "sg:classifiers":[
        {
            "category":"Retail",
            "subcategory":"Event Space",
            "type":"Services"
        }
    ],
    "sg:phone":"+61 2 9997 5283",
    "sg:postcode":"2104",
    "sg:province":"NSW",
    "sg:tags":[
        "venue",
        "reception",
        "wedding"
    ],
    "wof:name":"Weddings On Water",
    "wof:placetype":"venue"
},
  "geometry": {"coordinates":[151.299835,-33.66465],"type":"Point"}
}