{
  "type": "Feature",
  "properties": {
    "iso:country":"AU",
    "sg:address":"9 Mcnamara St",
    "sg:city":"Orange",
    "sg:classifiers":[
        {
            "category":"Professional",
            "subcategory":"Art Services",
            "type":"Services"
        }
    ],
    "sg:phone":"+61 2 6360 0803",
    "sg:postcode":"2800",
    "sg:province":"NSW",
    "sg:tags":[
        "product",
        "industrial",
        "designer"
    ],
    "sg:website":"http://www.trang.com.au",
    "wof:name":"Trang Imagineering",
    "wof:placetype":"venue"
},
  "geometry": {"coordinates":[149.10255432100001,-33.2836990356],"type":"Point"}
}