{
  "type": "Feature",
  "properties": {
    "addr:full":"Clifford Rd Innisfail QLD 4860",
    "addr:postcode":"4860",
    "addr:street":"Clifford Rd",
    "iso:country":"AU",
    "sg:address":"Clifford Rd",
    "sg:city":"Innisfail",
    "sg:phone":"+61 7 4061 4544",
    "sg:postcode":"4860",
    "sg:province":"QLD",
    "wof:name":"OzPoly",
    "wof:placetype":"venue"
},
  "geometry": {"coordinates":[146.01031494099999,-17.5176029205],"type":"Point"}
}