{
  "type": "Feature",
  "properties": {
    "iso:country":"AU",
    "sg:address":"48 Narara Creek Rd",
    "sg:city":"Narara",
    "sg:classifiers":[
        {
            "category":"Farming",
            "subcategory":"Nursery",
            "type":"Manufacturing & Wholesale Goods"
        }
    ],
    "sg:phone":"+61 2 4325 2240",
    "sg:postcode":"2250",
    "sg:province":"NSW",
    "wof:name":"Glenorie Nursery",
    "wof:placetype":"venue"
},
  "geometry": {"coordinates":[151.330200195,-33.4068222046],"type":"Point"}
}