{
  "type": "Feature",
  "properties": {
    "iso:country":"AU",
    "sg:address":"59 Port Rd",
    "sg:city":"Hindmarsh",
    "sg:classifiers":[
        {
            "category":"Travel",
            "subcategory":"Hotels & Motels",
            "type":"Entertainment"
        }
    ],
    "sg:phone":"+61 8 8340 0744",
    "sg:postcode":"5007",
    "sg:province":"SA",
    "sg:tags":[
        "accommodation"
    ],
    "wof:name":"Governor Hindmarsh Hotel",
    "wof:placetype":"venue"
},
  "geometry": {"coordinates":[138.57228088400001,-34.9049415588],"type":"Point"}
}