{
  "type": "Feature",
  "properties": {
    "addr:full":"55 Endeavour Drv Cranbourne North VIC 3977",
    "addr:housenumber":"55",
    "addr:postcode":"3977",
    "addr:street":"Endeavour Drv",
    "iso:country":"AU",
    "sg:address":"55 Endeavour Drv",
    "sg:city":"Cranbourne North",
    "sg:classifiers":[
        {
            "category":"Building & Trades",
            "subcategory":"Plumbing",
            "type":"Services"
        }
    ],
    "sg:phone":"+61 3 5996 0011",
    "sg:postcode":"3977",
    "sg:province":"VIC",
    "sg:tags":[
        "plumber",
        "gasfitters"
    ],
    "wof:name":"Churchus PG",
    "wof:placetype":"venue"
},
  "geometry": {"coordinates":[145.26634216299999,-38.0798187256],"type":"Point"}
}