{
  "type": "Feature",
  "properties": {
    "addr:full":"803 Main North Rd Pooraka SA 5095",
    "addr:housenumber":"803",
    "addr:postcode":"5095",
    "addr:street":"Main North Rd",
    "iso:country":"AU",
    "sg:address":"803 Main North Rd",
    "sg:city":"Pooraka",
    "sg:classifiers":[
        {
            "category":"Farming",
            "subcategory":"Poultry Farm",
            "type":"Manufacturing & Wholesale Goods"
        }
    ],
    "sg:phone":"+61 8 8260 6540",
    "sg:postcode":"5095",
    "sg:province":"SA",
    "sg:tags":[
        "breeder",
        "bird"
    ],
    "wof:name":"Gem Birds",
    "wof:placetype":"venue"
},
  "geometry": {"coordinates":[138.619750977,-34.8225746155],"type":"Point"}
}