{
  "type": "Feature",
  "properties": {
    "addr:full":"1 Midland Hwy Stanhope VIC 3623",
    "addr:housenumber":"1",
    "addr:postcode":"3623",
    "addr:street":"Midland Hwy",
    "iso:country":"AU",
    "sg:address":"1 Midland Hwy",
    "sg:city":"Stanhope",
    "sg:classifiers":[
        {
            "category":"Autos & Motor Vehicles",
            "subcategory":"Automobile Sales",
            "type":"Retail Goods"
        }
    ],
    "sg:phone":"+61 3 5857 2406",
    "sg:postcode":"3623",
    "sg:province":"VIC",
    "sg:tags":[
        "car",
        "new"
    ],
    "wof:name":"Stanhope Motors",
    "wof:placetype":"venue"
},
  "geometry": {"coordinates":[144.982666016,-36.4473304749],"type":"Point"}
}