{
  "type": "Feature",
  "properties": {
    "addr:full":"39 Railway Pde Lithgow NSW 2790",
    "addr:housenumber":"39",
    "addr:postcode":"2790",
    "addr:street":"Railway Pde",
    "iso:country":"AU",
    "sg:address":"39 Railway Pde",
    "sg:city":"Lithgow",
    "sg:classifiers":[
        {
            "category":"Health Services",
            "subcategory":"Doctor",
            "type":"Services"
        }
    ],
    "sg:phone":"+61 2 6353 1644",
    "sg:postcode":"2790",
    "sg:province":"NSW",
    "sg:tags":[
        "medical",
        "practitioner"
    ],
    "wof:name":"Sandford Medical Centre",
    "wof:placetype":"venue"
},
  "geometry": {"coordinates":[150.15751648,-33.4800491333],"type":"Point"}
}