{
  "type": "Feature",
  "properties": {
    "addr:full":"St Albans Cl Charlestown NSW 2290",
    "addr:postcode":"2290",
    "addr:street":"St;Cl",
    "iso:country":"AU",
    "sg:address":"St Albans Cl",
    "sg:city":"Charlestown",
    "sg:classifiers":[
        {
            "category":"Arts & Performance",
            "subcategory":"Dance",
            "type":"Entertainment"
        }
    ],
    "sg:phone":"+61 2 4943 9317",
    "sg:postcode":"2290",
    "sg:province":"NSW",
    "sg:tags":[
        "theatrical",
        "ballet",
        "tuition"
    ],
    "wof:name":"Charlestown Dance Centre",
    "wof:placetype":"venue"
},
  "geometry": {"coordinates":[151.68812560999999,-32.9578514099],"type":"Point"}
}