{
  "type": "Feature",
  "properties": {
    "iso:country":"AU",
    "sg:address":"158 Arden St",
    "sg:city":"North Melbourne",
    "sg:classifiers":[
        {
            "category":"Professional",
            "subcategory":"Computer Services",
            "type":"Services"
        }
    ],
    "sg:phone":"+61 3 9326 4811",
    "sg:postcode":"3051",
    "sg:province":"VIC",
    "sg:tags":[
        "consultant",
        "system"
    ],
    "wof:name":"Techno Consultants",
    "wof:placetype":"venue"
},
  "geometry": {"coordinates":[144.94659423799999,-37.8004455566],"type":"Point"}
}