{
  "type": "Feature",
  "properties": {
    "addr:full":"20 Thackeray St Toowoomba QLD 4350",
    "addr:housenumber":"20",
    "addr:postcode":"4350",
    "addr:street":"Thackeray St",
    "iso:country":"AU",
    "sg:address":"20 Thackeray St",
    "sg:city":"Toowoomba",
    "sg:classifiers":[
        {
            "category":"Professional",
            "subcategory":"Engineering",
            "type":"Services"
        }
    ],
    "sg:phone":"+61 427 144 261",
    "sg:postcode":"4350",
    "sg:province":"QLD",
    "sg:tags":[
        "engineer"
    ],
    "wof:name":"Macfab",
    "wof:placetype":"venue"
},
  "geometry": {"coordinates":[151.942474,-27.536596],"type":"Point"}
}