{
  "type": "Feature",
  "properties": {
    "addr:full":"Unit 1, 28 Merimbula Drv Merimbula NSW 2548",
    "addr:housenumber":"28",
    "addr:postcode":"2548",
    "addr:street":"Merimbula Drv",
    "iso:country":"AU",
    "sg:address":"Unit 1, 28 Merimbula Drv",
    "sg:city":"Merimbula",
    "sg:classifiers":[
        {
            "category":"Building & Trades",
            "subcategory":"Construction",
            "type":"Services"
        }
    ],
    "sg:phone":"+61 417 054 621",
    "sg:postcode":"2548",
    "sg:province":"NSW",
    "sg:tags":[
        "joiner",
        "carpenter"
    ],
    "wof:name":"Hawthorn Carpentry & Maintenance Pty Ltd",
    "wof:placetype":"venue"
},
  "geometry": {"coordinates":[149.907073975,-36.8880653381],"type":"Point"}
}