{
  "type": "Feature",
  "properties": {
    "addr:full":"PO Box 66 Canterbury VIC 3126",
    "addr:postcode":"3126",
    "iso:country":"AU",
    "sg:address":"PO Box 66",
    "sg:city":"Canterbury",
    "sg:classifiers":[
        {
            "category":"Personal",
            "subcategory":"Tanning Parlor",
            "type":"Services"
        }
    ],
    "sg:phone":"+61 3 9830 2318",
    "sg:postcode":"3126",
    "sg:province":"VIC",
    "sg:tags":[
        "solarium"
    ],
    "wof:name":"Budget Direct Solarium Tanning Lotions",
    "wof:placetype":"venue"
},
  "geometry": {"coordinates":[145.07310485799999,-37.8242492676],"type":"Point"}
}