{
  "type": "Feature",
  "properties": {
    "addr:full":"Lvl 1/ 773 Pacific Hwy Gordon NSW 2072",
    "addr:housenumber":"/ 773",
    "addr:postcode":"2072",
    "addr:street":"Pacific Hwy",
    "iso:country":"AU",
    "sg:address":"Lvl 1/ 773 Pacific Hwy",
    "sg:city":"Gordon",
    "sg:classifiers":[
        {
            "category":"Personal",
            "subcategory":"Beauty Salon",
            "type":"Services"
        }
    ],
    "sg:phone":"+61 2 9498 2188",
    "sg:postcode":"2072",
    "sg:province":"NSW",
    "wof:name":"Body Sense Solutions",
    "wof:placetype":"venue"
},
  "geometry": {"coordinates":[151.15266418499999,-33.7549591064],"type":"Point"}
}