{
  "type": "Feature",
  "properties": {
    "addr:full":"675 Heidelberg Rd Alphington VIC 3078",
    "addr:housenumber":"675",
    "addr:postcode":"3078",
    "addr:street":"Heidelberg Rd",
    "iso:country":"AU",
    "sg:address":"675 Heidelberg Rd",
    "sg:city":"Alphington",
    "sg:classifiers":[
        {
            "category":"Retail",
            "subcategory":"Auto Repair",
            "type":"Services"
        }
    ],
    "sg:phone":"+61 3 9497 5175",
    "sg:postcode":"3078",
    "sg:province":"VIC",
    "sg:tags":[
        "repairer",
        "motor",
        "engineer"
    ],
    "wof:name":"PCI Automotive",
    "wof:placetype":"venue"
},
  "geometry": {"coordinates":[145.02833557100001,-37.7811584473],"type":"Point"}
}