{
  "type": "Feature",
  "properties": {
    "addr:full":"Suite 2 16 Benson St Toowong QLD 4066",
    "addr:housenumber":"16",
    "addr:postcode":"4066",
    "addr:street":"Benson St",
    "iso:country":"AU",
    "sg:address":"Suite 2 16 Benson St",
    "sg:city":"Toowong",
    "sg:classifiers":[
        {
            "category":"Professional",
            "subcategory":"Management & Consulting",
            "type":"Services"
        }
    ],
    "sg:phone":"+61 7 3371 8750",
    "sg:postcode":"4066",
    "sg:province":"QLD",
    "sg:tags":[
        "consultant"
    ],
    "wof:name":"Wheeler Strobel",
    "wof:placetype":"venue"
},
  "geometry": {"coordinates":[152.993530273,-27.4857196808],"type":"Point"}
}