{
  "type": "Feature",
  "properties": {
    "addr:full":"989 Sydney Rd Coburg VIC 3058",
    "addr:housenumber":"989",
    "addr:postcode":"3058",
    "addr:street":"Sydney Rd",
    "iso:country":"AU",
    "sg:address":"989 Sydney Rd",
    "sg:city":"Coburg",
    "sg:classifiers":[
        {
            "category":"Autos & Motor Vehicles",
            "subcategory":"Fuel & Gas Station",
            "type":"Retail Goods"
        }
    ],
    "sg:phone":"+61 3 9354 6962",
    "sg:postcode":"3058",
    "sg:province":"VIC",
    "wof:name":"BP Australia Pty Ltd",
    "wof:placetype":"venue"
},
  "geometry": {"coordinates":[144.96340942399999,-37.7255058289],"type":"Point"}
}