{
  "type": "Feature",
  "properties": {
    "iso:country":"AU",
    "sg:address":"Calder Hwy",
    "sg:city":"Red Cliffs",
    "sg:classifiers":[
        {
            "category":"Farming",
            "subcategory":"Farm & Veterinary Services",
            "type":"Manufacturing & Wholesale Goods"
        }
    ],
    "sg:phone":"+61 3 5024 3301",
    "sg:postcode":"3496",
    "sg:province":"VIC",
    "sg:tags":[
        "irrigation",
        "reticulation",
        "system"
    ],
    "wof:name":"North West Irrigation Systems",
    "wof:placetype":"venue"
},
  "geometry": {"coordinates":[142.18652343799999,-34.3077430725],"type":"Point"}
}