{
  "type": "Feature",
  "properties": {
    "iso:country":"AU",
    "sg:address":"439 Gympie Rd",
    "sg:city":"Kedron",
    "sg:classifiers":[
        {
            "category":"Fast Food",
            "type":"Food & Drink"
        }
    ],
    "sg:phone":"+61 7 3109 1411",
    "sg:postcode":"4031",
    "sg:province":"QLD",
    "sg:tags":[
        "away",
        "take"
    ],
    "wof:name":"Domino's Pizza",
    "wof:placetype":"venue"
},
  "geometry": {"coordinates":[153.03173799999999,-27.400808],"type":"Point"}
}