{
  "type": "Feature",
  "properties": {
    "iso:country":"AU",
    "sg:address":"34 Bedford St",
    "sg:city":"Aberdeen",
    "sg:classifiers":[
        {
            "category":"Education",
            "subcategory":"Kindergarten",
            "type":"Public Place"
        }
    ],
    "sg:phone":"+61 2 6543 7172",
    "sg:postcode":"2336",
    "sg:province":"NSW",
    "sg:tags":[
        "pre-schools"
    ],
    "wof:name":"Aberdeen Pre School",
    "wof:placetype":"venue"
},
  "geometry": {"coordinates":[150.89117431599999,-32.1677932739],"type":"Point"}
}