{
  "type": "Feature",
  "properties": {
    "addr:full":"Rodney St Proston QLD 4613",
    "addr:postcode":"4613",
    "addr:street":"Rodney St",
    "iso:country":"AU",
    "sg:address":"Rodney St",
    "sg:city":"Proston",
    "sg:classifiers":[
        {
            "category":"Education",
            "subcategory":"School",
            "type":"Public Place"
        }
    ],
    "sg:phone":"+61 7 4169 4333",
    "sg:postcode":"4613",
    "sg:province":"QLD",
    "sg:tags":[
        "state",
        "except",
        "nsw"
    ],
    "wof:name":"Proston Primary",
    "wof:placetype":"venue"
},
  "geometry": {"coordinates":[151.60035705600001,-26.1619358063],"type":"Point"}
}