{
  "type": "Feature",
  "properties": {
    "addr:full":"155 New South Head Rd Vaucluse NSW 2030",
    "addr:housenumber":"155",
    "addr:postcode":"2030",
    "addr:street":"New South Head Rd",
    "iso:country":"AU",
    "sg:address":"155 New South Head Rd",
    "sg:city":"Vaucluse",
    "sg:classifiers":[
        {
            "category":"Professional",
            "subcategory":"Detective & Security Services",
            "type":"Services"
        }
    ],
    "sg:phone":"+61 2 9937 6840",
    "sg:postcode":"2030",
    "sg:province":"NSW",
    "sg:tags":[
        "domestic",
        "alarm",
        "commercial",
        "burglar"
    ],
    "wof:name":"Absolute Security",
    "wof:placetype":"venue"
},
  "geometry": {"coordinates":[151.281936645,-33.8571357727],"type":"Point"}
}