{
  "type": "Feature",
  "properties": {
    "addr:full":"Berrambool Drv Merimbula NSW 2548",
    "addr:postcode":"2548",
    "addr:street":"Berrambool Drv",
    "iso:country":"AU",
    "sg:address":"Berrambool Drv",
    "sg:city":"Merimbula",
    "sg:classifiers":[
        {
            "category":"Sports & Exercise",
            "subcategory":"Sports Center",
            "type":"Entertainment"
        }
    ],
    "sg:phone":"+61 2 6495 3377",
    "sg:postcode":"2548",
    "sg:province":"NSW",
    "sg:tags":[
        "ground"
    ],
    "wof:name":"Berrambool Sports Complex",
    "wof:placetype":"venue"
},
  "geometry": {"coordinates":[149.905792236,-36.8883018494],"type":"Point"}
}