{
  "type": "Feature",
  "properties": {
    "iso:country":"AU",
    "sg:address":"PO Box 1745",
    "sg:city":"Gosford",
    "sg:classifiers":[
        {
            "category":"Professional",
            "subcategory":"Employment Agencies",
            "type":"Services"
        }
    ],
    "sg:phone":"+61 1300 552 698",
    "sg:postcode":"2250",
    "sg:province":"NSW",
    "sg:tags":[
        "provider",
        "internet"
    ],
    "sg:website":"http://www.cirruscomms.com.au",
    "wof:name":"Cirrus Communications P/L",
    "wof:placetype":"venue"
},
  "geometry": {"coordinates":[151.319580078,-33.423915863],"type":"Point"}
}