{
  "type": "Feature",
  "properties": {
    "addr:full":"Level 1/ 66-68 Nicholson St Footscray VIC 3011",
    "addr:housenumber":"/ 66-68",
    "addr:postcode":"3011",
    "addr:street":"Nicholson St",
    "iso:country":"AU",
    "sg:address":"Level 1/ 66-68 Nicholson St",
    "sg:city":"Footscray",
    "sg:classifiers":[
        {
            "category":"Social Services",
            "subcategory":"Job Training",
            "type":"Services"
        }
    ],
    "sg:phone":"+61 3 9689 3855",
    "sg:postcode":"3011",
    "sg:province":"VIC",
    "sg:tags":[
        "interpreter"
    ],
    "wof:name":"Nguyen Ngan V",
    "wof:placetype":"venue"
},
  "geometry": {"coordinates":[144.899536133,-37.7989006042],"type":"Point"}
}