{
  "type": "Feature",
  "properties": {
    "iso:country":"AU",
    "sg:address":"201 Brisbane St",
    "sg:city":"Ipswich",
    "sg:classifiers":[
        {
            "category":"Shopping",
            "subcategory":"Pawn Shop",
            "type":"Retail Goods"
        }
    ],
    "sg:phone":"+61 7 3281 1766",
    "sg:postcode":"4305",
    "sg:province":"QLD",
    "sg:tags":[
        "pawnbroker"
    ],
    "wof:name":"PJ's Secondhand Ipswich",
    "wof:placetype":"venue"
},
  "geometry": {"coordinates":[152.75703430199999,-27.6139583588],"type":"Point"}
}