{
  "type": "Feature",
  "properties": {
    "iso:country":"AU",
    "sg:address":"47 Russell St",
    "sg:city":"Goondiwindi",
    "sg:classifiers":[
        {
            "category":"Farming",
            "subcategory":"Farm & Veterinary Services",
            "type":"Manufacturing & Wholesale Goods"
        }
    ],
    "sg:phone":"+61 7 4671 5162",
    "sg:postcode":"4390",
    "sg:province":"QLD",
    "sg:tags":[
        "irrigation",
        "reticulation",
        "system"
    ],
    "wof:name":"Pivot Irrigation & Pumping",
    "wof:placetype":"venue"
},
  "geometry": {"coordinates":[150.30274963400001,-28.5433006287],"type":"Point"}
}