{
  "type": "Feature",
  "properties": {
    "addr:full":"Level 2 155 Queen St Melbourne VIC 3000",
    "addr:housenumber":"155",
    "addr:postcode":"3000",
    "addr:street":"Queen St",
    "iso:country":"AU",
    "sg:address":"Level 2 155 Queen St",
    "sg:city":"Melbourne",
    "sg:classifiers":[
        {
            "category":"Professional",
            "subcategory":"Computer Services",
            "type":"Services"
        }
    ],
    "sg:phone":"+61 3 9605 1600",
    "sg:postcode":"3000",
    "sg:province":"VIC",
    "sg:tags":[
        "package",
        "software"
    ],
    "wof:name":"Hyperion Solutions Australia Pty Ltd",
    "wof:placetype":"venue"
},
  "geometry": {"coordinates":[144.960494995,-37.8149337769],"type":"Point"}
}