{
  "type": "Feature",
  "properties": {
    "addr:full":"4 Nirimba Crs Heathcote NSW 2233",
    "addr:housenumber":"4",
    "addr:postcode":"2233",
    "addr:street":"Nirimba Crs",
    "iso:country":"AU",
    "sg:address":"4 Nirimba Crs",
    "sg:city":"Heathcote",
    "sg:classifiers":[
        {
            "category":"Shopping",
            "subcategory":"Crafts & Fabrics",
            "type":"Retail Goods"
        }
    ],
    "sg:phone":"+61 2 9520 0101",
    "sg:postcode":"2233",
    "sg:province":"NSW",
    "sg:tags":[
        "supply"
    ],
    "wof:name":"Neddlecraft Cottage",
    "wof:placetype":"venue"
},
  "geometry": {"coordinates":[151.00868225100001,-34.0816688538],"type":"Point"}
}