{
  "type": "Feature",
  "properties": {
    "addr:full":"81 Kalaroo Rd Redhead NSW 2290",
    "addr:housenumber":"81",
    "addr:postcode":"2290",
    "addr:street":"Kalaroo Rd",
    "iso:country":"AU",
    "sg:address":"81 Kalaroo Rd",
    "sg:city":"Redhead",
    "sg:classifiers":[
        {
            "category":"Social Services",
            "subcategory":"Retirement Home",
            "type":"Services"
        }
    ],
    "sg:phone":"+61 2 4942 6355",
    "sg:postcode":"2290",
    "sg:province":"NSW",
    "sg:tags":[
        "village"
    ],
    "wof:name":"The Sanctuary",
    "wof:placetype":"venue"
},
  "geometry": {"coordinates":[151.696136475,-33.0182723999],"type":"Point"}
}