{
  "type": "Feature",
  "properties": {
    "addr:full":"193a Lennox St Richmond VIC 3121",
    "addr:housenumber":"193a",
    "addr:postcode":"3121",
    "addr:street":"Lennox St",
    "iso:country":"AU",
    "sg:address":"193a Lennox St",
    "sg:city":"Richmond",
    "sg:classifiers":[
        {
            "category":"Organizations",
            "subcategory":"Non-profit Organization",
            "type":"Services"
        }
    ],
    "sg:phone":"+61 3 9427 7444",
    "sg:postcode":"3121",
    "sg:province":"VIC",
    "sg:tags":[
        "support",
        "disability",
        "organisation"
    ],
    "wof:name":"Citizen Advocacy Victoria Resource Unit",
    "wof:placetype":"venue"
},
  "geometry": {"coordinates":[144.99473571799999,-37.8183021545],"type":"Point"}
}