{
  "type": "Feature",
  "properties": {
    "addr:full":"Shop 28, Metro Maddington Shopping Centre, Attfiel Maddington WA 6109",
    "addr:housenumber":"shop 28",
    "addr:postcode":"6109",
    "iso:country":"AU",
    "sg:address":"Shop 28, Metro Maddington Shopping Centre, Attfiel",
    "sg:city":"Maddington",
    "sg:classifiers":[
        {
            "category":"Shopping",
            "subcategory":"Computers & Home Electronics",
            "type":"Retail Goods"
        }
    ],
    "sg:phone":"+61 8 9459 7045",
    "sg:postcode":"6109",
    "sg:province":"WA",
    "sg:tags":[
        "equipment",
        "part",
        "electronic"
    ],
    "wof:name":"Tandy",
    "wof:placetype":"venue"
},
  "geometry": {"coordinates":[115.980941773,-32.0528717041],"type":"Point"}
}