{
  "type": "Feature",
  "properties": {
    "iso:country":"AU",
    "sg:address":"659 Yarck Rd",
    "sg:city":"Yarck",
    "sg:classifiers":[
        {
            "category":"Organizations",
            "subcategory":"Professional Association",
            "type":"Services"
        }
    ],
    "sg:phone":"+61 3 5773 4236",
    "sg:postcode":"3719",
    "sg:province":"VIC",
    "sg:tags":[
        "web",
        "internet"
    ],
    "wof:name":"Graph Attack Pty Ltd",
    "wof:placetype":"venue"
},
  "geometry": {"coordinates":[145.61685180699999,-37.1004104614],"type":"Point"}
}