{
  "type": "Feature",
  "properties": {
    "iso:country":"AU",
    "sg:address":"Manchester St",
    "sg:city":"Tinonee",
    "sg:classifiers":[
        {
            "category":"Education",
            "subcategory":"School",
            "type":"Public Place"
        }
    ],
    "sg:phone":"+61 2 6553 1279",
    "sg:postcode":"2430",
    "sg:province":"NSW",
    "sg:tags":[
        "state",
        "-",
        "nsw"
    ],
    "wof:name":"Tinonee Public School",
    "wof:placetype":"venue"
},
  "geometry": {"coordinates":[152.413528,-31.939259],"type":"Point"}
}