{
  "type": "Feature",
  "properties": {
    "addr:full":"1208 High St Armadale VIC 3143",
    "addr:housenumber":"1208",
    "addr:postcode":"3143",
    "addr:street":"High St",
    "iso:country":"AU",
    "sg:address":"1208 High St",
    "sg:city":"Armadale",
    "sg:classifiers":[
        {
            "category":"Personal",
            "type":"Services"
        }
    ],
    "sg:phone":"+61 3 9576 2525",
    "sg:postcode":"3143",
    "sg:province":"VIC",
    "sg:tags":[
        "dressmaker"
    ],
    "wof:name":"Stitches",
    "wof:placetype":"venue"
},
  "geometry": {"coordinates":[145.02738952600001,-37.8564796448],"type":"Point"}
}