{
  "type": "Feature",
  "properties": {
    "addr:full":"3/ 33 Macquarie St Dubbo NSW 2830",
    "addr:housenumber":"/ 33",
    "addr:postcode":"2830",
    "addr:street":"Macquarie St",
    "iso:country":"AU",
    "sg:address":"3/ 33 Macquarie St",
    "sg:city":"Dubbo",
    "sg:classifiers":[
        {
            "category":"Utilities",
            "subcategory":"Electric",
            "type":"Services"
        }
    ],
    "sg:phone":"+61 1300 550 331",
    "sg:postcode":"2830",
    "sg:province":"NSW",
    "sg:tags":[
        "electrical",
        "contractor"
    ],
    "wof:name":"Tradesmen You Can Trust",
    "wof:placetype":"venue"
},
  "geometry": {"coordinates":[148.6015625,-32.2450904846],"type":"Point"}
}