{
  "type": "Feature",
  "properties": {
    "addr:full":"PO Box 263 Canterbury VIC 3126",
    "addr:postcode":"3126",
    "iso:country":"AU",
    "sg:address":"PO Box 263",
    "sg:city":"Canterbury",
    "sg:classifiers":[
        {
            "category":"Health Services",
            "subcategory":"Health Practitioner",
            "type":"Services"
        }
    ],
    "sg:phone":"+61 408 345 959",
    "sg:postcode":"3126",
    "sg:province":"VIC",
    "sg:tags":[
        "psychologist"
    ],
    "wof:name":"Lezon John",
    "wof:placetype":"venue"
},
  "geometry": {"coordinates":[145.07310485799999,-37.8242492676],"type":"Point"}
}