{
  "type": "Feature",
  "properties": {
    "iso:country":"AU",
    "sg:address":"Shop 25 21 Norton St",
    "sg:city":"Leichhardt",
    "sg:classifiers":[
        {
            "category":"Shopping",
            "subcategory":"Clothing, Apparel, & Fashions",
            "type":"Retail Goods"
        }
    ],
    "sg:phone":"+61 2 9572 9755",
    "sg:postcode":"2040",
    "sg:province":"NSW",
    "sg:tags":[
        "accessory"
    ],
    "wof:name":"Eurobelle",
    "wof:placetype":"venue"
},
  "geometry": {"coordinates":[151.15765400000001,-33.887016],"type":"Point"}
}