{
  "type": "Feature",
  "properties": {
    "iso:country":"AU",
    "sg:address":"43 Campbell Ave",
    "sg:city":"Normanhurst",
    "sg:classifiers":[
        {
            "category":"Professional",
            "subcategory":"Art Services",
            "type":"Services"
        }
    ],
    "sg:phone":"+61 2 9489 4247",
    "sg:postcode":"2076",
    "sg:province":"NSW",
    "sg:tags":[
        "artist"
    ],
    "wof:name":"Murphy Pat",
    "wof:placetype":"venue"
},
  "geometry": {"coordinates":[151.092193603,-33.7264900208],"type":"Point"}
}