{
  "type": "Feature",
  "properties": {
    "addr:full":"43 Whitington Rd Elizabeth Field SA 5113",
    "addr:housenumber":"43",
    "addr:postcode":"5113",
    "addr:street":"Whitington Rd",
    "iso:country":"AU",
    "sg:address":"43 Whitington Rd",
    "sg:city":"Elizabeth Field",
    "sg:classifiers":[
        {
            "category":"Health Services",
            "subcategory":"Dentist",
            "type":"Services"
        }
    ],
    "sg:phone":"+61 8 8254 6222",
    "sg:postcode":"5113",
    "sg:province":"SA",
    "wof:name":"Mann E G & Winwood P C",
    "wof:placetype":"venue"
},
  "geometry": {"coordinates":[138.67173767099999,-34.6847953796],"type":"Point"}
}