{
  "type": "Feature",
  "properties": {
    "addr:full":"27 Young St Deepwater NSW 2371",
    "addr:housenumber":"27",
    "addr:postcode":"2371",
    "addr:street":"Young St",
    "iso:country":"AU",
    "sg:address":"27 Young St",
    "sg:city":"Deepwater",
    "sg:classifiers":[
        {
            "category":"Wholesale",
            "subcategory":"Electrical",
            "type":"Manufacturing & Wholesale Goods"
        }
    ],
    "sg:phone":"+61 2 6734 5262",
    "sg:postcode":"2371",
    "sg:province":"NSW",
    "sg:tags":[
        "wholesaler"
    ],
    "wof:name":"Starlogixs",
    "wof:placetype":"venue"
},
  "geometry": {"coordinates":[151.84762573200001,-29.4421768188],"type":"Point"}
}