{
  "type": "Feature",
  "properties": {
    "addr:full":"4-5/ 226 Headland Rd Brookvale NSW 2100",
    "addr:housenumber":"4-5 / 226",
    "addr:postcode":"2100",
    "addr:street":"Headland Rd",
    "iso:country":"AU",
    "sg:address":"4-5/ 226 Headland Rd",
    "sg:city":"Brookvale",
    "sg:classifiers":[
        {
            "category":"Arts & Performance",
            "subcategory":"Art Gallery",
            "type":"Entertainment"
        }
    ],
    "sg:phone":"+61 2 9939 3900",
    "sg:postcode":"2100",
    "sg:province":"NSW",
    "wof:name":"The Base Space",
    "wof:placetype":"venue"
},
  "geometry": {"coordinates":[151.281814575,-33.7600288391],"type":"Point"}
}