{
  "type": "Feature",
  "properties": {
    "addr:full":"Shop 137 Carlingford Crt Carlingford NSW 2118",
    "addr:housenumber":"137",
    "addr:postcode":"2118",
    "addr:street":"Carlingford Crt",
    "iso:country":"AU",
    "sg:address":"Shop 137 Carlingford Crt",
    "sg:city":"Carlingford",
    "sg:classifiers":[
        {
            "category":"Travel",
            "subcategory":"Travel Agent",
            "type":"Entertainment"
        }
    ],
    "sg:phone":"+61 2 9872 4466",
    "sg:postcode":"2118",
    "sg:province":"NSW",
    "sg:tags":[
        "consultant"
    ],
    "wof:name":"Travelscene Carlingford",
    "wof:placetype":"venue"
},
  "geometry": {"coordinates":[151.06422424300001,-33.7748603821],"type":"Point"}
}