{
  "type": "Feature",
  "properties": {
    "addr:full":"15/ 35 Herbert St Dandenong VIC 3175",
    "addr:housenumber":"15 / 35",
    "addr:postcode":"3175",
    "addr:street":"Herbert St",
    "iso:country":"AU",
    "sg:address":"15/ 35 Herbert St",
    "sg:city":"Dandenong",
    "sg:classifiers":[
        {
            "category":"Arts & Performance",
            "subcategory":"Music",
            "type":"Entertainment"
        }
    ],
    "sg:phone":"+61 419 350 375",
    "sg:postcode":"3175",
    "sg:province":"VIC",
    "sg:tags":[
        "mobile",
        "jockey",
        "disc"
    ],
    "wof:name":"DanceUnlimited.com.au",
    "wof:placetype":"venue"
},
  "geometry": {"coordinates":[145.21392822300001,-37.9806404114],"type":"Point"}
}