{
  "type": "Feature",
  "properties": {
    "iso:country":"AU",
    "sg:address":"20 Pentex St",
    "sg:city":"Salisbury",
    "sg:classifiers":[
        {
            "category":"Manufacturing",
            "subcategory":"Paper Products",
            "type":"Manufacturing & Wholesale Goods"
        }
    ],
    "sg:phone":"+61 7 3274 3900",
    "sg:postcode":"4107",
    "sg:province":"QLD",
    "sg:tags":[
        "container",
        "plastic"
    ],
    "wof:name":"Arthur E Croft & Co",
    "wof:placetype":"venue"
},
  "geometry": {"coordinates":[153.03315734899999,-27.5445671082],"type":"Point"}
}