{
  "type": "Feature",
  "properties": {
    "iso:country":"AU",
    "sg:address":"1155 High St",
    "sg:city":"Armadale",
    "sg:classifiers":[
        {
            "category":"Banks & Credit Unions",
            "subcategory":"Bank",
            "type":"Services"
        }
    ],
    "sg:phone":"+61 3 9856 8100",
    "sg:postcode":"3143",
    "sg:province":"VIC",
    "wof:name":"Bank of Queensland",
    "wof:placetype":"venue"
},
  "geometry": {"coordinates":[145.02630615199999,-37.8560905457],"type":"Point"}
}