{
  "type": "Feature",
  "properties": {
    "addr:full":"(Slipyard) Napoleon St Battery Point TAS 7004",
    "addr:postcode":"7004",
    "addr:street":"St",
    "iso:country":"AU",
    "sg:address":"(Slipyard) Napoleon St",
    "sg:city":"Battery Point",
    "sg:classifiers":[
        {
            "category":"Autos & Motor Vehicles",
            "subcategory":"Boat Sales",
            "type":"Retail Goods"
        }
    ],
    "sg:phone":"+61 3 6273 3700",
    "sg:postcode":"7004",
    "sg:province":"TAS",
    "sg:tags":[
        "builder",
        "yacht",
        "repairer"
    ],
    "wof:name":"Taylor Bros (Slipway & Engineering) Pty Ltd",
    "wof:placetype":"venue"
},
  "geometry": {"coordinates":[147.33587646500001,-42.8916854858],"type":"Point"}
}