{
  "type": "Feature",
  "properties": {
    "addr:full":"PO Box 94 Kingaroy QLD 4610",
    "addr:postcode":"4610",
    "iso:country":"AU",
    "sg:address":"PO Box 94",
    "sg:city":"Kingaroy",
    "sg:classifiers":[
        {
            "category":"Building & Trades",
            "subcategory":"Equipment Rental",
            "type":"Services"
        }
    ],
    "sg:phone":"+61 7 4162 7309",
    "sg:postcode":"4610",
    "sg:province":"QLD",
    "sg:tags":[
        "party",
        "hire"
    ],
    "wof:name":"Merry-Go-Rounds Etc.",
    "wof:placetype":"venue"
},
  "geometry": {"coordinates":[151.835845947,-26.5428390503],"type":"Point"}
}