{
  "type": "Feature",
  "properties": {
    "addr:full":"588 Worongary Rd Gilston QLD 4211",
    "addr:housenumber":"588",
    "addr:postcode":"4211",
    "addr:street":"Worongary Rd",
    "iso:country":"AU",
    "sg:address":"588 Worongary Rd",
    "sg:city":"Gilston",
    "sg:classifiers":[
        {
            "category":"Education",
            "subcategory":"School",
            "type":"Public Place"
        }
    ],
    "sg:phone":"+61 7 5533 2119",
    "sg:postcode":"4211",
    "sg:province":"QLD",
    "sg:tags":[
        "state",
        "except",
        "nsw"
    ],
    "wof:name":"Gilston Preschool",
    "wof:placetype":"venue"
},
  "geometry": {"coordinates":[153.31114196799999,-28.0434799194],"type":"Point"}
}