{
  "type": "Feature",
  "properties": {
    "addr:full":"135 Grant St Alexandra VIC 3714",
    "addr:housenumber":"135",
    "addr:postcode":"3714",
    "addr:street":"Grant St",
    "iso:country":"AU",
    "sg:address":"135 Grant St",
    "sg:city":"Alexandra",
    "sg:classifiers":[
        {
            "category":"Health Services",
            "subcategory":"Health Practitioner",
            "type":"Services"
        }
    ],
    "sg:phone":"+61 3 5772 2470",
    "sg:postcode":"3714",
    "sg:province":"VIC",
    "sg:tags":[
        "bowen",
        "therapy"
    ],
    "wof:name":"Houstonia Wellness & Beauty",
    "wof:placetype":"venue"
},
  "geometry": {"coordinates":[145.71156310999999,-37.196144104],"type":"Point"}
}