{
  "type": "Feature",
  "properties": {
    "addr:full":"1/ 227 Waterworks Rd Ashgrove QLD 4060",
    "addr:housenumber":"/ 227",
    "addr:postcode":"4060",
    "addr:street":"Waterworks Rd",
    "iso:country":"AU",
    "sg:address":"1/ 227 Waterworks Rd",
    "sg:city":"Ashgrove",
    "sg:classifiers":[
        {
            "category":"Food & Beverages",
            "subcategory":"Specialty",
            "type":"Retail Goods"
        }
    ],
    "sg:phone":"+61 7 3366 0466",
    "sg:postcode":"4060",
    "sg:province":"QLD",
    "sg:tags":[
        "delicacy"
    ],
    "wof:name":"Susan's Saucepan",
    "wof:placetype":"venue"
},
  "geometry": {"coordinates":[152.992675781,-27.4453735352],"type":"Point"}
}