{
  "type": "Feature",
  "properties": {
    "addr:full":"Shop 25/ 101 Mannigham Rd Bulleen VIC 3105",
    "addr:housenumber":"shop 25 / 101",
    "addr:postcode":"3105",
    "addr:street":"Mannigham Rd",
    "iso:country":"AU",
    "sg:address":"Shop 25/ 101 Mannigham Rd",
    "sg:city":"Bulleen",
    "sg:classifiers":[
        {
            "category":"Fast Food",
            "type":"Food & Drink"
        }
    ],
    "sg:phone":"+61 3 9852 2300",
    "sg:postcode":"3105",
    "sg:province":"VIC",
    "sg:tags":[
        "away",
        "take"
    ],
    "wof:name":"Charcoal Rooster Bulleen",
    "wof:placetype":"venue"
},
  "geometry": {"coordinates":[145.09231567399999,-37.7665939331],"type":"Point"}
}