{
  "type": "Feature",
  "properties": {
    "addr:full":"Level 3/ 349 Coronation Drv Milton QLD 4064",
    "addr:housenumber":"/ 349",
    "addr:postcode":"4064",
    "addr:street":"Coronation Drv",
    "iso:country":"AU",
    "sg:address":"Level 3/ 349 Coronation Drv",
    "sg:city":"Milton",
    "sg:classifiers":[
        {
            "category":"Insurance",
            "subcategory":"Life Insurance",
            "type":"Services"
        }
    ],
    "sg:phone":"+61 7 3842 3138",
    "sg:postcode":"4064",
    "sg:province":"QLD",
    "wof:name":"Jan Swan & Associates",
    "wof:placetype":"venue"
},
  "geometry": {"coordinates":[153.00291442899999,-27.4751014709],"type":"Point"}
}