{
  "type": "Feature",
  "properties": {
    "iso:country":"AU",
    "sg:address":"PO Box 338",
    "sg:city":"Kalbarri",
    "sg:classifiers":[
        {
            "category":"Utilities",
            "subcategory":"Electric",
            "type":"Services"
        }
    ],
    "sg:phone":"+61 8 9937 1059",
    "sg:postcode":"6536",
    "sg:province":"WA",
    "sg:tags":[
        "electrical",
        "contractor"
    ],
    "wof:name":"Kalbarri Electrical Services",
    "wof:placetype":"venue"
},
  "geometry": {"coordinates":[114.161521912,-27.7110099792],"type":"Point"}
}