{
  "type": "Feature",
  "properties": {
    "addr:full":"2 Elizabeth St Burwood VIC 3125",
    "addr:housenumber":"2",
    "addr:postcode":"3125",
    "addr:street":"Elizabeth St",
    "iso:country":"AU",
    "sg:address":"2 Elizabeth St",
    "sg:city":"Burwood",
    "sg:classifiers":[
        {
            "category":"Health Services",
            "subcategory":"Nursing And Care Facility",
            "type":"Services"
        }
    ],
    "sg:phone":"+61 3 9888 8022",
    "sg:postcode":"3125",
    "sg:province":"VIC",
    "sg:tags":[
        "home"
    ],
    "wof:name":"Elizabeth Gardens Nursing Home",
    "wof:placetype":"venue"
},
  "geometry": {"coordinates":[145.09690856899999,-37.8571395874],"type":"Point"}
}