{
  "type": "Feature",
  "properties": {
    "addr:full":"Lvl 9/ 486 Albert St East Melbourne VIC 3002",
    "addr:housenumber":"/ 486",
    "addr:postcode":"3002",
    "addr:street":"Albert St",
    "iso:country":"AU",
    "sg:address":"Lvl 9/ 486 Albert St",
    "sg:city":"East Melbourne",
    "sg:classifiers":[
        {
            "category":"Banks & Credit Unions",
            "subcategory":"Financial Services",
            "type":"Services"
        }
    ],
    "sg:phone":"+61 3 9230 3444",
    "sg:postcode":"3002",
    "sg:province":"VIC",
    "sg:tags":[
        "annuity",
        "rollover",
        "superannuation",
        "consultant"
    ],
    "wof:name":"ING",
    "wof:placetype":"venue"
},
  "geometry": {"coordinates":[144.97445678700001,-37.809173584],"type":"Point"}
}