{
  "type": "Feature",
  "properties": {
    "addr:full":"PO Box 586 Cannington WA 6987",
    "addr:postcode":"6987",
    "iso:country":"AU",
    "sg:address":"PO Box 586",
    "sg:city":"Cannington",
    "sg:classifiers":[
        {
            "category":"Social Services",
            "subcategory":"Adult Care",
            "type":"Services"
        }
    ],
    "sg:phone":"+61 411 744 797",
    "sg:postcode":"6987",
    "sg:province":"WA",
    "sg:tags":[
        "towing"
    ],
    "wof:name":"Precision Towing & Tilt Tray Service",
    "wof:placetype":"venue"
},
  "geometry": {"coordinates":[115.939201,-32.019459],"type":"Point"}
}