{
  "type": "Feature",
  "properties": {
    "addr:full":"124 Lutwyche Rd Windsor QLD 4030",
    "addr:housenumber":"124",
    "addr:postcode":"4030",
    "addr:street":"Lutwyche Rd",
    "iso:country":"AU",
    "sg:address":"124 Lutwyche Rd",
    "sg:city":"Windsor",
    "sg:classifiers":[
        {
            "category":"Wholesale",
            "subcategory":"Medical Equipment & Supplies",
            "type":"Manufacturing & Wholesale Goods"
        }
    ],
    "sg:phone":"+61 7 3357 5944",
    "sg:postcode":"4030",
    "sg:province":"QLD",
    "sg:tags":[
        "aid",
        "care",
        "health",
        "home"
    ],
    "wof:name":"Morris Surgical",
    "wof:placetype":"venue"
},
  "geometry": {"coordinates":[153.03033400000001,-27.441191],"type":"Point"}
}