{
  "type": "Feature",
  "properties": {
    "addr:full":"10-12 Majors Rd Moonta SA 5558",
    "addr:housenumber":"10-12",
    "addr:postcode":"5558",
    "addr:street":"Majors Rd",
    "iso:country":"AU",
    "sg:address":"10-12 Majors Rd",
    "sg:city":"Moonta",
    "sg:classifiers":[
        {
            "category":"Travel",
            "subcategory":"Hostel",
            "type":"Entertainment"
        }
    ],
    "sg:phone":"+61 8 8825 0000",
    "sg:postcode":"5558",
    "sg:province":"SA",
    "sg:tags":[
        "home"
    ],
    "wof:name":"Parkview Aged Hostel",
    "wof:placetype":"venue"
},
  "geometry": {"coordinates":[137.58853149399999,-34.0606651306],"type":"Point"}
}