{
  "type": "Feature",
  "properties": {
    "addr:full":"Shop 4b, Centro, 395 Albany Highway Victoria Park WA 6100",
    "addr:housenumber":"shop 4b;395",
    "addr:postcode":"6100",
    "addr:street":"Centro;Albany Highway",
    "iso:country":"AU",
    "sg:address":"Shop 4b, Centro, 395 Albany Highway",
    "sg:city":"Victoria Park",
    "sg:classifiers":[
        {
            "category":"Personal",
            "subcategory":"Beauty Salon",
            "type":"Services"
        }
    ],
    "sg:phone":"+61 8 9361 2346",
    "sg:postcode":"6100",
    "sg:province":"WA",
    "sg:tags":[
        "hairdresser"
    ],
    "wof:name":"Mojo For Hair",
    "wof:placetype":"venue"
},
  "geometry": {"coordinates":[115.897277832,-31.9744415283],"type":"Point"}
}