{
  "type": "Feature",
  "properties": {
    "iso:country":"AU",
    "sg:address":"8/ 56 Wollongong St",
    "sg:city":"Fyshwick",
    "sg:classifiers":[
        {
            "category":"Utilities",
            "subcategory":"Water",
            "type":"Services"
        }
    ],
    "sg:phone":"+61 2 6228 1156",
    "sg:postcode":"2609",
    "sg:province":"ACT",
    "sg:tags":[
        "equipment",
        "treatment"
    ],
    "wof:name":"Aqua Safe",
    "wof:placetype":"venue"
},
  "geometry": {"coordinates":[149.179779053,-35.3245048523],"type":"Point"}
}