{
  "type": "Feature",
  "properties": {
    "addr:full":"West End Shopping Centre Shop 11/162 Nerang St Southport QLD 4215",
    "addr:housenumber":"shop 11 / 162",
    "addr:postcode":"4215",
    "addr:street":"Nerang St",
    "iso:country":"AU",
    "sg:address":"West End Shopping Centre Shop 11/162 Nerang St",
    "sg:city":"Southport",
    "sg:classifiers":[
        {
            "category":"Personal",
            "subcategory":"Hair Removal",
            "type":"Services"
        }
    ],
    "sg:phone":"+61 7 5532 0222",
    "sg:postcode":"4215",
    "sg:province":"QLD",
    "wof:name":"Skin Logic",
    "wof:placetype":"venue"
},
  "geometry": {"coordinates":[153.40440368599999,-27.9731235504],"type":"Point"}
}