{
  "type": "Feature",
  "properties": {
    "addr:full":"20 Central Rd Port Macquarie NSW 2444",
    "addr:housenumber":"20",
    "addr:postcode":"2444",
    "addr:street":"Central Rd",
    "iso:country":"AU",
    "sg:address":"20 Central Rd",
    "sg:city":"Port Macquarie",
    "sg:classifiers":[
        {
            "category":"Home & Garden",
            "subcategory":"Hardware",
            "type":"Retail Goods"
        }
    ],
    "sg:phone":"+61 2 6581 0544",
    "sg:postcode":"2444",
    "sg:province":"NSW",
    "sg:tags":[
        "part",
        "air conditioning"
    ],
    "wof:name":"Coolcene Air Conditioning",
    "wof:placetype":"venue"
},
  "geometry": {"coordinates":[152.89321899999999,-31.446579],"type":"Point"}
}