{
  "type": "Feature",
  "properties": {
    "iso:country":"AU",
    "sg:address":"26 Gilligans Rd",
    "sg:city":"Dural",
    "sg:classifiers":[
        {
            "category":"Building & Trades",
            "subcategory":"Construction",
            "type":"Services"
        }
    ],
    "sg:phone":"+61 2 9651 6456",
    "sg:postcode":"2158",
    "sg:province":"NSW",
    "sg:tags":[
        "management"
    ],
    "wof:name":"Project Solutions Australia Pty Ltd",
    "wof:placetype":"venue"
},
  "geometry": {"coordinates":[151.04881286599999,-33.6636543274],"type":"Point"}
}