{
  "type": "Feature",
  "properties": {
    "addr:full":"57 Hotham St Traralgon VIC 3844",
    "addr:housenumber":"57",
    "addr:postcode":"3844",
    "addr:street":"Hotham St",
    "iso:country":"AU",
    "sg:address":"57 Hotham St",
    "sg:city":"Traralgon",
    "sg:classifiers":[
        {
            "category":"Personal",
            "subcategory":"Beauty Salon",
            "type":"Services"
        }
    ],
    "sg:phone":"+61 3 5174 3046",
    "sg:postcode":"3844",
    "sg:province":"VIC",
    "sg:tags":[
        "hairdresser"
    ],
    "wof:name":"Lox Hair & Beauty Salon",
    "wof:placetype":"venue"
},
  "geometry": {"coordinates":[146.53642273,-38.1973609924],"type":"Point"}
}