{
  "type": "Feature",
  "properties": {
    "addr:full":"3897 Great Alpine Rd Myrtleford VIC 3737",
    "addr:housenumber":"3897",
    "addr:postcode":"3737",
    "addr:street":"Great Alpine Rd",
    "iso:country":"AU",
    "sg:address":"3897 Great Alpine Rd",
    "sg:city":"Myrtleford",
    "sg:classifiers":[
        {
            "category":"Farming",
            "subcategory":"Vineyard",
            "type":"Manufacturing & Wholesale Goods"
        }
    ],
    "sg:phone":"+61 3 5751 1383",
    "sg:postcode":"3737",
    "sg:province":"VIC",
    "sg:tags":[
        "winery"
    ],
    "wof:name":"Gapsted Wines",
    "wof:placetype":"venue"
},
  "geometry": {"coordinates":[146.682495117,-36.5236740112],"type":"Point"}
}