{
  "type": "Feature",
  "properties": {
    "addr:full":"3 Olinda Crt Cheltenham VIC 3192",
    "addr:housenumber":"3",
    "addr:postcode":"3192",
    "addr:street":"Olinda Crt",
    "iso:country":"AU",
    "sg:address":"3 Olinda Crt",
    "sg:city":"Cheltenham",
    "sg:classifiers":[
        {
            "category":"Home & Garden",
            "subcategory":"Household Appliances",
            "type":"Retail Goods"
        }
    ],
    "sg:phone":"+61 3 9584 7294",
    "sg:postcode":"3192",
    "sg:province":"VIC",
    "sg:tags":[
        "equipment",
        "gas"
    ],
    "wof:name":"Bill Lilburn",
    "wof:placetype":"venue"
},
  "geometry": {"coordinates":[145.0831604,-37.9642448425],"type":"Point"}
}