{
  "type": "Feature",
  "properties": {
    "addr:full":"598 High Street Rd Glen Waverley VIC 3150",
    "addr:housenumber":"598",
    "addr:postcode":"3150",
    "addr:street":"High Street Rd",
    "iso:country":"AU",
    "sg:address":"598 High Street Rd",
    "sg:city":"Glen Waverley",
    "sg:classifiers":[
        {
            "category":"Health Services",
            "subcategory":"Doctor",
            "type":"Services"
        }
    ],
    "sg:phone":"+61 3 9802 9101",
    "sg:postcode":"3150",
    "sg:province":"VIC",
    "sg:tags":[
        "medical",
        "practitioner"
    ],
    "wof:name":"Glenmount Medical Clinic",
    "wof:placetype":"venue"
},
  "geometry": {"coordinates":[145.15060424800001,-37.8725128174],"type":"Point"}
}