{
  "type": "Feature",
  "properties": {
    "addr:full":"Shop 1 Newman Shopng Cntr Newman WA 6753",
    "addr:housenumber":"shop 1",
    "addr:postcode":"6753",
    "iso:country":"AU",
    "sg:address":"Shop 1 Newman Shopng Cntr",
    "sg:city":"Newman",
    "sg:classifiers":[
        {
            "category":"Personal",
            "subcategory":"Beauty Salon",
            "type":"Services"
        }
    ],
    "sg:phone":"+61 8 9177 8308",
    "sg:postcode":"6753",
    "sg:province":"WA",
    "sg:tags":[
        "hairdresser"
    ],
    "wof:name":"ZIZX Unisex Salon",
    "wof:placetype":"venue"
},
  "geometry": {"coordinates":[119.72879791299999,-23.3580665588],"type":"Point"}
}