{
  "type": "Feature",
  "properties": {
    "iso:country":"AU",
    "sg:address":"Level 15, 15 Lake St",
    "sg:city":"Cairns",
    "sg:classifiers":[
        {
            "category":"Professional",
            "subcategory":"Accounting & Tax Preparation",
            "type":"Services"
        }
    ],
    "sg:phone":"+61 7 4042 6100",
    "sg:postcode":"4870",
    "sg:province":"QLD",
    "sg:tags":[
        "consultant",
        "taxation"
    ],
    "wof:name":"A-Counting Plus",
    "wof:placetype":"venue"
},
  "geometry": {"coordinates":[145.77874755900001,-16.9256362915],"type":"Point"}
}