{
  "type": "Feature",
  "properties": {
    "iso:country":"AU",
    "sg:address":"Wright St",
    "sg:city":"Harvey",
    "sg:classifiers":[
        {
            "category":"Social Services",
            "subcategory":"Child Care",
            "type":"Services"
        }
    ],
    "sg:phone":"+61 8 9729 3377",
    "sg:postcode":"6220",
    "sg:province":"WA",
    "sg:tags":[
        "support",
        "health"
    ],
    "wof:name":"Child Health Services",
    "wof:placetype":"venue"
},
  "geometry": {"coordinates":[115.89608,-33.077606],"type":"Point"}
}