{
  "type": "Feature",
  "properties": {
    "addr:full":"16 Plateau Rd Springwood NSW 2777",
    "addr:housenumber":"16",
    "addr:postcode":"2777",
    "addr:street":"Plateau Rd",
    "iso:country":"AU",
    "sg:address":"16 Plateau Rd",
    "sg:city":"Springwood",
    "sg:classifiers":[
        {
            "category":"Professional",
            "subcategory":"Accounting & Tax Preparation",
            "type":"Services"
        }
    ],
    "sg:phone":"+61 2 4751 7279",
    "sg:postcode":"2777",
    "sg:province":"NSW",
    "sg:tags":[
        "accountant",
        "auditor"
    ],
    "wof:name":"Michael Molloy",
    "wof:placetype":"venue"
},
  "geometry": {"coordinates":[150.551177978,-33.6944618225],"type":"Point"}
}