{
  "type": "Feature",
  "properties": {
    "iso:country":"AU",
    "sg:address":"PO Box 227",
    "sg:city":"Meningie",
    "sg:classifiers":[
        {
            "category":"Farming",
            "subcategory":"Farm",
            "type":"Manufacturing & Wholesale Goods"
        }
    ],
    "sg:phone":"+61 8 8575 1313",
    "sg:postcode":"5264",
    "sg:province":"SA",
    "sg:tags":[
        "farmer"
    ],
    "wof:name":"Jude A B",
    "wof:placetype":"venue"
},
  "geometry": {"coordinates":[139.336807,-35.690479],"type":"Point"}
}