{
  "type": "Feature",
  "properties": {
    "addr:full":"1/ 3 Mt Pleasant Rd Gympie QLD 4570",
    "addr:housenumber":"/ 3",
    "addr:postcode":"4570",
    "addr:street":"Mt Pleasant Rd",
    "iso:country":"AU",
    "sg:address":"1/ 3 Mt Pleasant Rd",
    "sg:city":"Gympie",
    "sg:classifiers":[
        {
            "category":"Professional",
            "subcategory":"Computer Services",
            "type":"Services"
        }
    ],
    "sg:phone":"+61 7 5483 7393",
    "sg:postcode":"4570",
    "sg:province":"QLD",
    "sg:tags":[
        "training"
    ],
    "wof:name":"Kingsway Computer Consultants",
    "wof:placetype":"venue"
},
  "geometry": {"coordinates":[152.673095703,-26.1951465607],"type":"Point"}
}