{
  "type": "Feature",
  "properties": {
    "addr:full":"U1/ 60 Kingston Rd Underwood QLD 4119",
    "addr:housenumber":"60",
    "addr:postcode":"4119",
    "addr:street":"U1 /;Kingston Rd",
    "iso:country":"AU",
    "sg:address":"U1/ 60 Kingston Rd",
    "sg:city":"Underwood",
    "sg:classifiers":[
        {
            "category":"Retail",
            "subcategory":"Auto Repair",
            "type":"Services"
        }
    ],
    "sg:phone":"+61 7 3841 6213",
    "sg:postcode":"4119",
    "sg:province":"QLD",
    "sg:tags":[
        "repairer",
        "motor",
        "engineer"
    ],
    "wof:name":"NK Mechanical Repairs",
    "wof:placetype":"venue"
},
  "geometry": {"coordinates":[153.114105225,-27.6140365601],"type":"Point"}
}