{
  "type": "Feature",
  "properties": {
    "iso:country":"AU",
    "sg:address":"19 Bowden St",
    "sg:city":"Guildford",
    "sg:classifiers":[
        {
            "category":"Manufacturing",
            "subcategory":"Chemicals & Compounds",
            "type":"Manufacturing & Wholesale Goods"
        }
    ],
    "sg:phone":"+61 2 9892 3185",
    "sg:postcode":"2161",
    "sg:province":"NSW",
    "sg:tags":[
        "industrial"
    ],
    "wof:name":"Prospect Industries Pty Ltd",
    "wof:placetype":"venue"
},
  "geometry": {"coordinates":[150.97253418,-33.8445549011],"type":"Point"}
}