{
  "type": "Feature",
  "properties": {
    "iso:country":"AU",
    "sg:address":"PO Box 193",
    "sg:city":"Stepney",
    "sg:classifiers":[
        {
            "category":"Professional",
            "subcategory":"Computer Services",
            "type":"Services"
        }
    ],
    "sg:phone":"+61 1300 435 772",
    "sg:postcode":"5069",
    "sg:province":"SA",
    "sg:tags":[
        "repairs",
        "upgrade",
        "equipment"
    ],
    "wof:name":"1300 Help Pc",
    "wof:placetype":"venue"
},
  "geometry": {"coordinates":[138.626785278,-34.9107894897],"type":"Point"}
}