{
  "type": "Feature",
  "properties": {
    "addr:full":"101 Ipswich St Esk QLD 4312",
    "addr:housenumber":"101",
    "addr:postcode":"4312",
    "addr:street":"Ipswich St",
    "iso:country":"AU",
    "sg:address":"101 Ipswich St",
    "sg:city":"Esk",
    "sg:classifiers":[
        {
            "category":"Banks & Credit Unions",
            "subcategory":"Financial Services",
            "type":"Services"
        }
    ],
    "sg:phone":"+61 7 5424 2940",
    "sg:postcode":"4312",
    "sg:province":"QLD",
    "sg:tags":[
        "building",
        "society"
    ],
    "wof:name":"Heritage Building Society",
    "wof:placetype":"venue"
},
  "geometry": {"coordinates":[152.42460632300001,-27.2427883148],"type":"Point"}
}