{
  "type": "Feature",
  "properties": {
    "iso:country":"AU",
    "sg:address":"Avenue Rd",
    "sg:city":"Stirling",
    "sg:classifiers":[
        {
            "category":"Cinema",
            "subcategory":"Movie Theater",
            "type":"Entertainment"
        }
    ],
    "sg:phone":"+61 8 8339 6588",
    "sg:postcode":"5152",
    "sg:province":"SA",
    "wof:name":"Stirling Community Theatre",
    "wof:placetype":"venue"
},
  "geometry": {"coordinates":[138.71453857399999,-35.0041122437],"type":"Point"}
}