{
  "type": "Feature",
  "properties": {
    "iso:country":"AU",
    "sg:address":"105 Macquarie St",
    "sg:city":"Hobart",
    "sg:classifiers":[
        {
            "category":"Professional",
            "subcategory":"Accounting & Tax Preparation",
            "type":"Services"
        }
    ],
    "sg:phone":"+61 3 6224 7560",
    "sg:postcode":"7000",
    "sg:province":"TAS",
    "sg:tags":[
        "accountant",
        "auditor"
    ],
    "wof:name":"O&#039;Connor Business Consulting Pty Ltd",
    "wof:placetype":"venue"
},
  "geometry": {"coordinates":[147.329803467,-42.8828773499],"type":"Point"}
}