{
  "type": "Feature",
  "properties": {
    "addr:full":"U7/ 9 Inspiration Drv Wangara WA 6065",
    "addr:housenumber":"9",
    "addr:postcode":"6065",
    "addr:street":"U7 /;Inspiration Drv",
    "iso:country":"AU",
    "sg:address":"U7/ 9 Inspiration Drv",
    "sg:city":"Wangara",
    "sg:classifiers":[
        {
            "category":"Wholesale",
            "subcategory":"Medical Equipment & Supplies",
            "type":"Manufacturing & Wholesale Goods"
        }
    ],
    "sg:phone":"+61 8 9302 6322",
    "sg:postcode":"6065",
    "sg:province":"WA",
    "sg:tags":[
        "aid",
        "care",
        "health",
        "home"
    ],
    "wof:name":"GoForIt Mobility Products",
    "wof:placetype":"venue"
},
  "geometry": {"coordinates":[115.83489227299999,-31.7990341187],"type":"Point"}
}