{
  "type": "Feature",
  "properties": {
    "addr:full":"Carrie St Pingrup WA 6343",
    "addr:postcode":"6343",
    "addr:street":"Carrie St",
    "iso:country":"AU",
    "sg:address":"Carrie St",
    "sg:city":"Pingrup",
    "sg:classifiers":[
        {
            "category":"Education",
            "subcategory":"School",
            "type":"Public Place"
        }
    ],
    "sg:phone":"+61 8 9820 1042",
    "sg:postcode":"6343",
    "sg:province":"WA",
    "sg:tags":[
        "state",
        "except",
        "nsw"
    ],
    "wof:name":"Pingrup Primary School",
    "wof:placetype":"venue"
},
  "geometry": {"coordinates":[118.512367,-33.53326],"type":"Point"}
}