{
  "type": "Feature",
  "properties": {
    "addr:full":"53 Williamson St Bendigo VIC 3550",
    "addr:housenumber":"53",
    "addr:postcode":"3550",
    "addr:street":"Williamson St",
    "iso:country":"AU",
    "sg:address":"53 Williamson St",
    "sg:city":"Bendigo",
    "sg:classifiers":[
        {
            "category":"Autos & Motor Vehicles",
            "subcategory":"Auto Supplies",
            "type":"Retail Goods"
        }
    ],
    "sg:phone":"+61 3 5443 9522",
    "sg:postcode":"3550",
    "sg:province":"VIC",
    "sg:tags":[
        "car",
        "alarm"
    ],
    "wof:name":"AAA1 Strathfield",
    "wof:placetype":"venue"
},
  "geometry": {"coordinates":[144.28233337399999,-36.7602844238],"type":"Point"}
}