{
  "type": "Feature",
  "properties": {
    "addr:full":"61 Mitchell St Shepparton VIC 3630",
    "addr:housenumber":"61",
    "addr:postcode":"3630",
    "addr:street":"Mitchell St",
    "iso:country":"AU",
    "sg:address":"61 Mitchell St",
    "sg:city":"Shepparton",
    "sg:classifiers":[
        {
            "category":"Retail",
            "subcategory":"Auto Repair",
            "type":"Services"
        }
    ],
    "sg:phone":"+61 3 5821 2935",
    "sg:postcode":"3630",
    "sg:province":"VIC",
    "sg:tags":[
        "clutch",
        "brake"
    ],
    "wof:name":"Knights Brake & Clutch",
    "wof:placetype":"venue"
},
  "geometry": {"coordinates":[145.420410156,-36.3836517334],"type":"Point"}
}