{
  "type": "Feature",
  "properties": {
    "iso:country":"AU",
    "sg:address":"6 Adelaide Tce St",
    "sg:city":"Marys",
    "sg:classifiers":[
        {
            "category":"Utilities",
            "subcategory":"Natural Gas",
            "type":"Services"
        }
    ],
    "sg:phone":"+61 8 8277 3822",
    "sg:postcode":"5042",
    "sg:province":"SA",
    "sg:tags":[
        "pressing",
        "metal",
        "stamping"
    ],
    "wof:name":"Ross Lighting (A&#039;Asia) Pty Ltd",
    "wof:placetype":"venue"
},
  "geometry": {"coordinates":[138.57688899999999,-34.996525],"type":"Point"}
}