{
  "type": "Feature",
  "properties": {
    "addr:full":"338 Brisbane Rd Labrador QLD 4215",
    "addr:housenumber":"338",
    "addr:postcode":"4215",
    "addr:street":"Brisbane Rd",
    "iso:country":"AU",
    "sg:address":"338 Brisbane Rd",
    "sg:city":"Labrador",
    "sg:classifiers":[
        {
            "category":"Autos & Motor Vehicles",
            "subcategory":"Auto Supplies",
            "type":"Retail Goods"
        }
    ],
    "sg:phone":"+61 7 5537 3755",
    "sg:postcode":"4215",
    "sg:province":"QLD",
    "sg:tags":[
        "camper-trailers",
        "caravan",
        "equipment"
    ],
    "wof:name":"Auswide Caravans",
    "wof:placetype":"venue"
},
  "geometry": {"coordinates":[153.39132690400001,-27.9344577789],"type":"Point"}
}