{
  "type": "Feature",
  "properties": {
    "addr:full":"198 Macleod St Bairnsdale VIC 3875",
    "addr:housenumber":"198",
    "addr:postcode":"3875",
    "addr:street":"Macleod St",
    "iso:country":"AU",
    "sg:address":"198 Macleod St",
    "sg:city":"Bairnsdale",
    "sg:classifiers":[
        {
            "category":"Home & Garden",
            "subcategory":"Building Materials",
            "type":"Retail Goods"
        }
    ],
    "sg:phone":"+61 3 5152 4268",
    "sg:postcode":"3875",
    "sg:province":"VIC",
    "sg:tags":[
        "plaster",
        "plasterboard",
        "supply"
    ],
    "wof:name":"Bairnsdale Picton Hopkins & Sons Pty Ltd",
    "wof:placetype":"venue"
},
  "geometry": {"coordinates":[147.61796569800001,-37.8300857544],"type":"Point"}
}