{
  "type": "Feature",
  "properties": {
    "addr:full":"9 Orinda Ave Gosford NSW 2250",
    "addr:housenumber":"9",
    "addr:postcode":"2250",
    "addr:street":"Orinda Ave",
    "iso:country":"AU",
    "sg:address":"9 Orinda Ave",
    "sg:city":"Gosford",
    "sg:classifiers":[
        {
            "category":"Shopping",
            "subcategory":"Musical Instruments",
            "type":"Retail Goods"
        }
    ],
    "sg:phone":"+61 2 4323 7300",
    "sg:postcode":"2250",
    "sg:province":"NSW",
    "sg:tags":[
        "musician",
        "agent"
    ],
    "wof:name":"Arrangements-Music For Your Occasion",
    "wof:placetype":"venue"
},
  "geometry": {"coordinates":[151.354705811,-33.4192657471],"type":"Point"}
}