{
  "type": "Feature",
  "properties": {
    "addr:full":"Bi-Lo Centre, Rtherford Rd Muswellbrook NSW 2333",
    "addr:postcode":"2333",
    "addr:street":"Rtherford Rd",
    "iso:country":"AU",
    "sg:address":"Bi-Lo Centre, Rtherford Rd",
    "sg:city":"Muswellbrook",
    "sg:classifiers":[
        {
            "category":"Food & Beverages",
            "subcategory":"Liquor & Beverages",
            "type":"Retail Goods"
        }
    ],
    "sg:phone":"+61 2 6543 2580",
    "sg:postcode":"2333",
    "sg:province":"NSW",
    "sg:tags":[
        "store"
    ],
    "wof:name":"Cellarbrations",
    "wof:placetype":"venue"
},
  "geometry": {"coordinates":[150.88752746599999,-32.2689208984],"type":"Point"}
}