{
  "type": "Feature",
  "properties": {
    "addr:full":"272 George St Deniliquin NSW 2710",
    "addr:housenumber":"272",
    "addr:postcode":"2710",
    "addr:street":"George St",
    "iso:country":"AU",
    "sg:address":"272 George St",
    "sg:city":"Deniliquin",
    "sg:classifiers":[
        {
            "category":"Banks & Credit Unions",
            "subcategory":"Financial Services",
            "type":"Services"
        }
    ],
    "sg:phone":"+61 3 5881 5047",
    "sg:postcode":"2710",
    "sg:province":"NSW",
    "sg:tags":[
        "financier"
    ],
    "wof:name":"Bidgee Finance Limited",
    "wof:placetype":"venue"
},
  "geometry": {"coordinates":[144.96302795400001,-35.5267868042],"type":"Point"}
}