{
  "type": "Feature",
  "properties": {
    "addr:full":"27 Orchard St Kilsyth VIC 3137",
    "addr:housenumber":"27",
    "addr:postcode":"3137",
    "addr:street":"Orchard St",
    "iso:country":"AU",
    "sg:address":"27 Orchard St",
    "sg:city":"Kilsyth",
    "sg:classifiers":[
        {
            "category":"Manufacturing",
            "subcategory":"Paper Products",
            "type":"Manufacturing & Wholesale Goods"
        }
    ],
    "sg:phone":"+61 3 9724 4600",
    "sg:postcode":"3137",
    "sg:province":"VIC",
    "sg:tags":[
        "box",
        "fibre",
        "carton",
        "cardboard"
    ],
    "wof:name":"Glama-Pak Pty Ltd",
    "wof:placetype":"venue"
},
  "geometry": {"coordinates":[145.31214904800001,-37.8110389709],"type":"Point"}
}