{
  "type": "Feature",
  "properties": {
    "addr:full":"96 Longueville Rd Lane Cove NSW 2066",
    "addr:housenumber":"96",
    "addr:postcode":"2066",
    "addr:street":"Longueville Rd",
    "iso:country":"AU",
    "sg:address":"96 Longueville Rd",
    "sg:city":"Lane Cove",
    "sg:classifiers":[
        {
            "category":"Building & Trades",
            "subcategory":"Construction",
            "type":"Services"
        }
    ],
    "sg:phone":"+61 2 9427 1777",
    "sg:postcode":"2066",
    "sg:province":"NSW",
    "sg:tags":[
        "management"
    ],
    "wof:name":"Zakos G L & Associates Pty Ltd",
    "wof:placetype":"venue"
},
  "geometry": {"coordinates":[151.17005920400001,-33.8141403198],"type":"Point"}
}