{
  "type": "Feature",
  "properties": {
    "addr:full":"133 Cunningham St Dalby QLD 4405",
    "addr:housenumber":"133",
    "addr:postcode":"4405",
    "addr:street":"Cunningham St",
    "iso:country":"AU",
    "sg:address":"133 Cunningham St",
    "sg:city":"Dalby",
    "sg:classifiers":[
        {
            "category":"Organizations",
            "subcategory":"Professional Association",
            "type":"Services"
        }
    ],
    "sg:phone":"+61 7 4662 4050",
    "sg:postcode":"4405",
    "sg:province":"QLD",
    "sg:tags":[
        "organisation",
        "business"
    ],
    "wof:name":"Dalby Chamber of Commerce & Industry",
    "wof:placetype":"venue"
},
  "geometry": {"coordinates":[151.257446289,-27.1783275604],"type":"Point"}
}