{
  "type": "Feature",
  "properties": {
    "addr:full":"1/14 Summerhill Rd Glen Iris VIC 3146",
    "addr:housenumber":"/ 14",
    "addr:postcode":"3146",
    "addr:street":"Summerhill Rd",
    "iso:country":"AU",
    "sg:address":"1/14 Summerhill Rd",
    "sg:city":"Glen Iris",
    "sg:classifiers":[
        {
            "category":"Professional",
            "subcategory":"Business Services",
            "type":"Services"
        }
    ],
    "sg:phone":"+61 419 584 962",
    "sg:postcode":"3146",
    "sg:province":"VIC",
    "sg:tags":[
        "drafting"
    ],
    "wof:name":"Haddow Drafting Pty Ltd",
    "wof:placetype":"venue"
},
  "geometry": {"coordinates":[145.07681274399999,-37.8497123718],"type":"Point"}
}