{
  "type": "Feature",
  "properties": {
    "iso:country":"AU",
    "sg:address":"1 Duffy St",
    "sg:city":"Bayswater",
    "sg:classifiers":[
        {
            "category":"Building & Trades",
            "subcategory":"Cleaning & Sanitation",
            "type":"Services"
        }
    ],
    "sg:phone":"+61 8 9377 2480",
    "sg:postcode":"6053",
    "sg:province":"WA",
    "sg:tags":[
        "commercial",
        "maintenance"
    ],
    "wof:name":"Ventara Holdings Pty Ltd",
    "wof:placetype":"venue"
},
  "geometry": {"coordinates":[115.925712585,-31.9094142914],"type":"Point"}
}