{
  "type": "Feature",
  "properties": {
    "addr:full":"31 Logan Rd Woolloongabba QLD 4102",
    "addr:housenumber":"31",
    "addr:postcode":"4102",
    "addr:street":"Logan Rd",
    "iso:country":"AU",
    "sg:address":"31 Logan Rd",
    "sg:city":"Woolloongabba",
    "sg:classifiers":[
        {
            "category":"Shopping",
            "subcategory":"Antiques",
            "type":"Retail Goods"
        }
    ],
    "sg:phone":"+61 7 3891 7735",
    "sg:postcode":"4102",
    "sg:province":"QLD",
    "wof:name":"Twice Upon A Time",
    "wof:placetype":"venue"
},
  "geometry": {"coordinates":[153.03788757300001,-27.4888038635],"type":"Point"}
}