{
  "type": "Feature",
  "properties": {
    "addr:full":"395 Pacific Hwy Artarmon NSW 2064",
    "addr:housenumber":"395",
    "addr:postcode":"2064",
    "addr:street":"Pacific Hwy",
    "iso:country":"AU",
    "sg:address":"395 Pacific Hwy",
    "sg:city":"Artarmon",
    "sg:classifiers":[
        {
            "category":"Retail",
            "subcategory":"Car Wash",
            "type":"Services"
        }
    ],
    "sg:phone":"+61 2 9437 9005",
    "sg:postcode":"2064",
    "sg:province":"NSW",
    "sg:tags":[
        "truck",
        "cleaning"
    ],
    "wof:name":"Custom Car Detailing",
    "wof:placetype":"venue"
},
  "geometry": {"coordinates":[151.178497314,-33.8156394958],"type":"Point"}
}