{
  "type": "Feature",
  "properties": {
    "addr:full":"U1/ 161 Robertson St Fortitude Valley QLD 4006",
    "addr:housenumber":"161",
    "addr:postcode":"4006",
    "addr:street":"U1 /;Robertson St",
    "iso:country":"AU",
    "sg:address":"U1/ 161 Robertson St",
    "sg:city":"Fortitude Valley",
    "sg:classifiers":[
        {
            "category":"Professional",
            "subcategory":"Computer Services",
            "type":"Services"
        }
    ],
    "sg:phone":"+61 7 3666 0399",
    "sg:postcode":"4006",
    "sg:province":"QLD",
    "sg:tags":[
        "package",
        "software"
    ],
    "wof:name":"Aconex",
    "wof:placetype":"venue"
},
  "geometry": {"coordinates":[153.039749145,-27.4578170776],"type":"Point"}
}