{
  "type": "Feature",
  "properties": {
    "addr:full":"Maitland Rd Mayfield NSW 2304",
    "addr:postcode":"2304",
    "addr:street":"Maitland Rd",
    "iso:country":"AU",
    "sg:address":"Maitland Rd",
    "sg:city":"Mayfield",
    "sg:classifiers":[
        {
            "category":"Autos & Motor Vehicles",
            "subcategory":"Fuel & Gas Station",
            "type":"Retail Goods"
        }
    ],
    "sg:phone":"+61 2 4960 1168",
    "sg:postcode":"2304",
    "sg:province":"NSW",
    "wof:name":"BP Australia Limited",
    "wof:placetype":"venue"
},
  "geometry": {"coordinates":[151.73826599099999,-32.8985939026],"type":"Point"}
}