{
  "type": "Feature",
  "properties": {
    "iso:country":"AU",
    "sg:address":"127 Chapel La",
    "sg:city":"Bella Vista",
    "sg:classifiers":[
        {
            "category":"Building & Trades",
            "subcategory":"Construction",
            "type":"Services"
        }
    ],
    "sg:phone":"+61 414 720 834",
    "sg:postcode":"2153",
    "sg:province":"NSW",
    "sg:tags":[
        "contractor"
    ],
    "wof:name":"BOUKARIM CONSTRUCTION PTY LTD",
    "wof:placetype":"venue"
},
  "geometry": {"coordinates":[150.96046447800001,-33.7534675598],"type":"Point"}
}