{
  "type": "Feature",
  "properties": {
    "iso:country":"AU",
    "sg:address":"11 Fuller Ave",
    "sg:city":"Earlwood",
    "sg:classifiers":[
        {
            "category":"Building & Trades",
            "subcategory":"Construction",
            "type":"Services"
        }
    ],
    "sg:phone":"+61 414 287 263",
    "sg:postcode":"2206",
    "sg:province":"NSW",
    "sg:tags":[
        "concrete",
        "contractor"
    ],
    "wof:name":"PNC Concreting",
    "wof:placetype":"venue"
},
  "geometry": {"coordinates":[151.117905,-33.920105],"type":"Point"}
}