{
  "type": "Feature",
  "properties": {
    "addr:full":"126A Payneham Rd Stepney SA 5069",
    "addr:housenumber":"126a",
    "addr:postcode":"5069",
    "addr:street":"Payneham Rd",
    "iso:country":"AU",
    "sg:address":"126A Payneham Rd",
    "sg:city":"Stepney",
    "sg:classifiers":[
        {
            "category":"Health Services",
            "subcategory":"Doctor",
            "type":"Services"
        }
    ],
    "sg:phone":"+61 8 8363 4144",
    "sg:postcode":"5069",
    "sg:province":"SA",
    "sg:tags":[
        "podiatrist"
    ],
    "wof:name":"Australian Podiatry Association",
    "wof:placetype":"venue"
},
  "geometry": {"coordinates":[138.629104614,-34.9083366394],"type":"Point"}
}