{
  "type": "Feature",
  "properties": {
    "addr:full":"120 Cardinal Rd Glenroy VIC 3046",
    "addr:housenumber":"120",
    "addr:postcode":"3046",
    "addr:street":"Cardinal Rd",
    "iso:country":"AU",
    "sg:address":"120 Cardinal Rd",
    "sg:city":"Glenroy",
    "sg:classifiers":[
        {
            "category":"Education",
            "subcategory":"Music School",
            "type":"Public Place"
        }
    ],
    "sg:phone":"+61 3 9306 1078",
    "sg:postcode":"3046",
    "sg:province":"VIC",
    "sg:tags":[
        "teacher"
    ],
    "wof:name":"Advance Guitar School",
    "wof:placetype":"venue"
},
  "geometry": {"coordinates":[144.929595947,-37.7001647949],"type":"Point"}
}