{
  "type": "Feature",
  "properties": {
    "iso:country":"AU",
    "sg:address":"271 Brighton Rd",
    "sg:city":"Somerton Park",
    "sg:classifiers":[
        {
            "category":"Health Services",
            "subcategory":"Doctor",
            "type":"Services"
        }
    ],
    "sg:phone":"+61 8 8294 9355",
    "sg:postcode":"5044",
    "sg:province":"SA",
    "sg:tags":[
        "medical",
        "practitioner"
    ],
    "wof:name":"Twartz J C",
    "wof:placetype":"venue"
},
  "geometry": {"coordinates":[138.521515,-34.999702],"type":"Point"}
}