{
  "type": "Feature",
  "properties": {
    "addr:full":"331 High St Echuca VIC 3564",
    "addr:housenumber":"331",
    "addr:postcode":"3564",
    "addr:street":"High St",
    "iso:country":"AU",
    "sg:address":"331 High St",
    "sg:city":"Echuca",
    "sg:classifiers":[
        {
            "category":"Retail",
            "subcategory":"Repair Shop",
            "type":"Services"
        }
    ],
    "sg:phone":"+61 3 5480 2213",
    "sg:postcode":"3564",
    "sg:province":"VIC",
    "sg:tags":[
        "leadlights"
    ],
    "wof:name":"Echuca Leadlight Studio",
    "wof:placetype":"venue"
},
  "geometry": {"coordinates":[144.75296020499999,-36.147895813],"type":"Point"}
}