{
  "type": "Feature",
  "properties": {
    "iso:country":"AU",
    "sg:address":"11B Production Drv",
    "sg:city":"Campbellfield",
    "sg:classifiers":[
        {
            "category":"Manufacturing",
            "subcategory":"Building Materials",
            "type":"Manufacturing & Wholesale Goods"
        }
    ],
    "sg:phone":"+61 3 9357 6025",
    "sg:postcode":"3061",
    "sg:province":"VIC",
    "sg:tags":[
        "adhesive",
        "tape"
    ],
    "wof:name":"Venture Tape Australasia",
    "wof:placetype":"venue"
},
  "geometry": {"coordinates":[144.96998596200001,-37.6654205322],"type":"Point"}
}