{
  "type": "Feature",
  "properties": {
    "addr:full":"5/ 205 Pirie St Adelaide SA 5000",
    "addr:housenumber":"/ 205",
    "addr:postcode":"5000",
    "addr:street":"Pirie St",
    "iso:country":"AU",
    "sg:address":"5/ 205 Pirie St",
    "sg:city":"Adelaide",
    "sg:classifiers":[
        {
            "category":"Shopping",
            "subcategory":"Clothing, Apparel, & Fashions",
            "type":"Retail Goods"
        }
    ],
    "sg:phone":"+61 8 8223 4844",
    "sg:postcode":"5000",
    "sg:province":"SA",
    "sg:tags":[
        "recycled",
        "clothing"
    ],
    "wof:name":"Mary Potter Hospice Foundation Op-Shop",
    "wof:placetype":"venue"
},
  "geometry": {"coordinates":[138.60626220699999,-34.9255714417],"type":"Point"}
}