{
  "type": "Feature",
  "properties": {
    "addr:full":"39 Dolans Rd Cronulla NSW 2230",
    "addr:housenumber":"39",
    "addr:postcode":"2230",
    "addr:street":"Dolans Rd",
    "iso:country":"AU",
    "sg:address":"39 Dolans Rd",
    "sg:city":"Cronulla",
    "sg:classifiers":[
        {
            "category":"Building & Trades",
            "subcategory":"Construction",
            "type":"Services"
        }
    ],
    "sg:phone":"+61 2 9544 1616",
    "sg:postcode":"2230",
    "sg:province":"NSW",
    "sg:tags":[
        "contractor"
    ],
    "wof:name":"CJM Building P/L",
    "wof:placetype":"venue"
},
  "geometry": {"coordinates":[151.13656616200001,-34.0490646362],"type":"Point"}
}