{
  "type": "Feature",
  "properties": {
    "addr:full":"Suite 6 / 295-299 Pennant Hills Rd Thornleigh NSW 2120",
    "addr:housenumber":"/ 295-299",
    "addr:postcode":"2120",
    "addr:street":"Pennant Hills Rd",
    "iso:country":"AU",
    "sg:address":"Suite 6 / 295-299 Pennant Hills Rd",
    "sg:city":"Thornleigh",
    "sg:classifiers":[
        {
            "category":"Shopping",
            "subcategory":"Computers & Home Electronics",
            "type":"Retail Goods"
        }
    ],
    "sg:phone":"+61 2 9481 7420",
    "sg:postcode":"2120",
    "sg:province":"NSW",
    "sg:tags":[
        "wholesaler",
        "equipment",
        "electronic",
        "mfrs"
    ],
    "wof:name":"ESIS Pty Ltd",
    "wof:placetype":"venue"
},
  "geometry": {"coordinates":[151.066314697,-33.7213096619],"type":"Point"}
}