{
  "type": "Feature",
  "properties": {
    "addr:full":"Unit 4/ 25 Keane St Currajong QLD 4812",
    "addr:housenumber":"25",
    "addr:postcode":"4812",
    "addr:street":"Keane St",
    "iso:country":"AU",
    "sg:address":"Unit 4/ 25 Keane St",
    "sg:city":"Currajong",
    "sg:classifiers":[
        {
            "category":"Retail",
            "subcategory":"Auto Repair",
            "type":"Services"
        }
    ],
    "sg:phone":"+61 7 4775 2917",
    "sg:postcode":"4812",
    "sg:province":"QLD",
    "sg:tags":[
        "repairer",
        "motor",
        "engineer"
    ],
    "wof:name":"Doig Automotive Pty Ltd",
    "wof:placetype":"venue"
},
  "geometry": {"coordinates":[146.779236,-19.271873],"type":"Point"}
}