{
  "type": "Feature",
  "properties": {
    "addr:full":"7 Wallaby St Blackwall NSW 2256",
    "addr:housenumber":"7",
    "addr:postcode":"2256",
    "addr:street":"Wallaby St",
    "iso:country":"AU",
    "sg:address":"7 Wallaby St",
    "sg:city":"Blackwall",
    "sg:classifiers":[
        {
            "category":"Building & Trades",
            "subcategory":"Cleaning & Sanitation",
            "type":"Services"
        }
    ],
    "sg:phone":"+61 408 258 494",
    "sg:postcode":"2256",
    "sg:province":"NSW",
    "sg:tags":[
        "wall",
        "brick"
    ],
    "wof:name":"Blues Blasters High Pressure Cleaning",
    "wof:placetype":"venue"
},
  "geometry": {"coordinates":[151.32969665499999,-33.5040245056],"type":"Point"}
}