{
  "type": "Feature",
  "properties": {
    "iso:country":"AU",
    "sg:address":"17 Bishop St",
    "sg:city":"Stuart Park",
    "sg:classifiers":[
        {
            "category":"Home & Garden",
            "subcategory":"Furniture",
            "type":"Retail Goods"
        }
    ],
    "sg:phone":"+61 8 8981 7161",
    "sg:postcode":"0820",
    "sg:province":"NT",
    "sg:tags":[
        "repair",
        "restoration"
    ],
    "wof:name":"Commercial Furniture Re-Upholsterers",
    "wof:placetype":"venue"
},
  "geometry": {"coordinates":[130.852172852,-12.4331073761],"type":"Point"}
}