{
  "type": "Feature",
  "properties": {
    "addr:full":"2614 Great Western St Kingswood NSW 2747",
    "addr:housenumber":"2614",
    "addr:postcode":"2747",
    "addr:street":"Great Western St",
    "iso:country":"AU",
    "sg:address":"2614 Great Western St",
    "sg:city":"Kingswood",
    "sg:classifiers":[
        {
            "category":"Autos & Motor Vehicles",
            "subcategory":"Fuel & Gas Station",
            "type":"Retail Goods"
        }
    ],
    "sg:phone":"+61 2 4736 4813",
    "sg:postcode":"2747",
    "sg:province":"NSW",
    "wof:name":"Caltex Oil Ltd",
    "wof:placetype":"venue"
},
  "geometry": {"coordinates":[150.71861267099999,-33.758228302],"type":"Point"}
}