{
  "type": "Feature",
  "properties": {
    "iso:country":"AU",
    "sg:address":"27 Meeking Drv",
    "sg:city":"Pakenham",
    "sg:classifiers":[
        {
            "category":"Building & Trades",
            "subcategory":"Construction",
            "type":"Services"
        }
    ],
    "sg:phone":"+61 3 5940 1900",
    "sg:postcode":"3810",
    "sg:province":"VIC",
    "sg:tags":[
        "equipment",
        "balancing"
    ],
    "wof:name":"Tailshaft Balancing Services",
    "wof:placetype":"venue"
},
  "geometry": {"coordinates":[145.46232599999999,-38.071114],"type":"Point"}
}