{
  "type": "Feature",
  "properties": {
    "addr:full":"17 Yomara Rd Marino SA 5049",
    "addr:housenumber":"17",
    "addr:postcode":"5049",
    "addr:street":"Yomara Rd",
    "iso:country":"AU",
    "sg:address":"17 Yomara Rd",
    "sg:city":"Marino",
    "sg:classifiers":[
        {
            "category":"Shopping",
            "subcategory":"Computers & Home Electronics",
            "type":"Retail Goods"
        }
    ],
    "sg:phone":"+61 8 8298 5755",
    "sg:postcode":"5049",
    "sg:province":"SA",
    "sg:tags":[
        "equipment",
        "multimedia"
    ],
    "wof:name":"Virtual Media Solutions",
    "wof:placetype":"venue"
},
  "geometry": {"coordinates":[138.51071200000001,-35.049858],"type":"Point"}
}