{
  "type": "Feature",
  "properties": {
    "iso:country":"AU",
    "sg:address":"11A Clarke St",
    "sg:city":"Crows Nest",
    "sg:classifiers":[
        {
            "category":"Professional",
            "subcategory":"Advertising",
            "type":"Services"
        }
    ],
    "sg:phone":"+61 2 9438 2765",
    "sg:postcode":"2065",
    "sg:province":"NSW",
    "sg:tags":[
        "balloon",
        "novelty"
    ],
    "wof:name":"Balloons &#039;N&#039; Things",
    "wof:placetype":"venue"
},
  "geometry": {"coordinates":[151.20028686500001,-33.8257064819],"type":"Point"}
}