{
  "type": "Feature",
  "properties": {
    "iso:country":"AU",
    "sg:address":"Cnr Trinity Drv & Alexander Ave",
    "sg:city":"Evanston Park",
    "sg:classifiers":[
        {
            "category":"Health Services",
            "subcategory":"Dentist",
            "type":"Services"
        }
    ],
    "sg:phone":"+61 8 8396 5466",
    "sg:postcode":"5116",
    "sg:province":"SA",
    "wof:name":"All-Ages Orthodontic Practice",
    "wof:placetype":"venue"
},
  "geometry": {"coordinates":[138.736572266,-34.6335220337],"type":"Point"}
}