{
  "type": "Feature",
  "properties": {
    "addr:full":"20 Stolzenberg St Kingaroy QLD 4610",
    "addr:housenumber":"20",
    "addr:postcode":"4610",
    "addr:street":"Stolzenberg St",
    "iso:country":"AU",
    "sg:address":"20 Stolzenberg St",
    "sg:city":"Kingaroy",
    "sg:classifiers":[
        {
            "category":"Retail",
            "subcategory":"Storage",
            "type":"Services"
        }
    ],
    "sg:phone":"+61 7 4162 1033",
    "sg:postcode":"4610",
    "sg:province":"QLD",
    "wof:name":"Freemans Real Estate",
    "wof:placetype":"venue"
},
  "geometry": {"coordinates":[151.835845947,-26.5428390503],"type":"Point"}
}