{
  "type": "Feature",
  "properties": {
    "iso:country":"AU",
    "sg:address":"117 New St",
    "sg:city":"Ringwood",
    "sg:classifiers":[
        {
            "category":"Building & Trades",
            "subcategory":"Construction",
            "type":"Services"
        }
    ],
    "sg:phone":"+61 3 9879 6665",
    "sg:postcode":"3134",
    "sg:province":"VIC",
    "sg:tags":[
        "spouting",
        "guttering"
    ],
    "wof:name":"E.J. Kefford Plumbing Services",
    "wof:placetype":"venue"
},
  "geometry": {"coordinates":[145.22064209000001,-37.8260726929],"type":"Point"}
}