{
  "type": "Feature",
  "properties": {
    "iso:country":"AU",
    "sg:address":"2 Queens Pde",
    "sg:city":"Newport",
    "sg:classifiers":[
        {
            "category":"Recreation",
            "subcategory":"Boat Charter",
            "type":"Entertainment"
        }
    ],
    "sg:phone":"+61 2 9979 7117",
    "sg:postcode":"2106",
    "sg:province":"NSW",
    "sg:tags":[
        "hire",
        "drive"
    ],
    "wof:name":"Newport City",
    "wof:placetype":"venue"
},
  "geometry": {"coordinates":[151.30955505399999,-33.659778595],"type":"Point"}
}