{
  "type": "Feature",
  "properties": {
    "iso:country":"AU",
    "sg:address":"10 Inglis St",
    "sg:city":"Wynyard",
    "sg:classifiers":[
        {
            "category":"Retail",
            "subcategory":"Auto Repair",
            "type":"Services"
        }
    ],
    "sg:phone":"+61 3 6442 5361",
    "sg:postcode":"7325",
    "sg:province":"TAS",
    "sg:tags":[
        "electrical"
    ],
    "wof:name":"Wright's Mechanical & Auto Electrical Services",
    "wof:placetype":"venue"
},
  "geometry": {"coordinates":[145.723022,-40.989807],"type":"Point"}
}