{
  "type": "Feature",
  "properties": {
    "addr:full":"2 Stokes St Lane Cove NSW 2066",
    "addr:housenumber":"2",
    "addr:postcode":"2066",
    "addr:street":"Stokes St",
    "iso:country":"AU",
    "sg:address":"2 Stokes St",
    "sg:city":"Lane Cove",
    "sg:classifiers":[
        {
            "category":"Professional",
            "subcategory":"Employment Agencies",
            "type":"Services"
        }
    ],
    "sg:phone":"+61 2 9418 8294",
    "sg:postcode":"2066",
    "sg:province":"NSW",
    "sg:tags":[
        "entertainer",
        "agent"
    ],
    "wof:name":"Drum Promotions",
    "wof:placetype":"venue"
},
  "geometry": {"coordinates":[151.173583984,-33.8095474243],"type":"Point"}
}