{
  "type": "Feature",
  "properties": {
    "iso:country":"AU",
    "sg:address":"338- 340 Crown St",
    "sg:city":"Wollongong",
    "sg:classifiers":[
        {
            "category":"Health Services",
            "subcategory":"Doctor",
            "type":"Services"
        }
    ],
    "sg:phone":"+61 2 4252 5200",
    "sg:postcode":"2500",
    "sg:province":"NSW",
    "sg:tags":[
        "medical",
        "practitioner"
    ],
    "wof:name":"Illawarra Family Medical Centre",
    "wof:placetype":"venue"
},
  "geometry": {"coordinates":[150.881058,-34.425945],"type":"Point"}
}