{
  "type": "Feature",
  "properties": {
    "addr:full":"85 Waterford-Tamborine Rd Waterford QLD 4133",
    "addr:housenumber":"85",
    "addr:postcode":"4133",
    "addr:street":"Waterford-Tamborine Rd",
    "iso:country":"AU",
    "sg:address":"85 Waterford-Tamborine Rd",
    "sg:city":"Waterford",
    "sg:classifiers":[
        {
            "category":"Home & Garden",
            "subcategory":"Garden Supply",
            "type":"Retail Goods"
        }
    ],
    "sg:phone":"+61 7 3805 2111",
    "sg:postcode":"4133",
    "sg:province":"QLD",
    "sg:tags":[
        "statuary",
        "fountains",
        "sundial"
    ],
    "wof:name":"Garden Companions (QLD)",
    "wof:placetype":"venue"
},
  "geometry": {"coordinates":[153.14706420900001,-27.7065200806],"type":"Point"}
}