{
  "type": "Feature",
  "properties": {
    "iso:country":"AU",
    "sg:address":"116 Thistlewaite St",
    "sg:city":"South Melbourne",
    "sg:classifiers":[
        {
            "category":"Retail",
            "subcategory":"Auto Repair",
            "type":"Services"
        }
    ],
    "sg:phone":"+61 3 9686 2900",
    "sg:postcode":"3205",
    "sg:province":"VIC",
    "sg:tags":[
        "beater",
        "painter",
        "panel"
    ],
    "wof:name":"Docklands Accident Repair Centre",
    "wof:placetype":"venue"
},
  "geometry": {"coordinates":[144.950195,-37.83223],"type":"Point"}
}