{
  "type": "Feature",
  "properties": {
    "addr:full":"76 Bruce Hwy Miriwinni QLD 4871",
    "addr:housenumber":"76",
    "addr:postcode":"4871",
    "addr:street":"Bruce Hwy",
    "iso:country":"AU",
    "sg:address":"76 Bruce Hwy",
    "sg:city":"Miriwinni",
    "sg:classifiers":[
        {
            "category":"Building & Trades",
            "subcategory":"Construction",
            "type":"Services"
        }
    ],
    "sg:phone":"+61 7 4067 6685",
    "sg:postcode":"4871",
    "sg:province":"QLD",
    "sg:tags":[
        "contractor"
    ],
    "wof:name":"Hadius Pty Ltd",
    "wof:placetype":"venue"
},
  "geometry": {"coordinates":[145.90957641599999,-17.3970088959],"type":"Point"}
}