{
  "type": "Feature",
  "properties": {
    "addr:full":"PO Box 74 Kew East VIC 3102",
    "addr:postcode":"3102",
    "iso:country":"AU",
    "sg:address":"PO Box 74",
    "sg:city":"Kew East",
    "sg:classifiers":[
        {
            "category":"Deli",
            "type":"Food & Drink"
        }
    ],
    "sg:phone":"+61 3 9437 1248",
    "sg:postcode":"3102",
    "sg:province":"VIC",
    "sg:tags":[
        "delicatessen"
    ],
    "wof:name":"City Link Foodservice",
    "wof:placetype":"venue"
},
  "geometry": {"coordinates":[145.05108642600001,-37.7905311584],"type":"Point"}
}