{
  "type": "Feature",
  "properties": {
    "addr:full":"Suite 1 Silver Sea Cnr Sixth Ave & Melrose Pde Maroochydore QLD 4558",
    "addr:postcode":"4558",
    "addr:street":"Cnr Sixth Ave & Melrose Pde",
    "iso:country":"AU",
    "sg:address":"Suite 1 Silver Sea Cnr Sixth Ave & Melrose Pde",
    "sg:city":"Maroochydore",
    "sg:classifiers":[
        {
            "category":"Banks & Credit Unions",
            "subcategory":"Bank",
            "type":"Services"
        }
    ],
    "sg:phone":"+61 7 5479 0077",
    "sg:postcode":"4558",
    "sg:province":"QLD",
    "sg:tags":[
        "broker",
        "mortgage"
    ],
    "wof:name":"City 2 Country Finance",
    "wof:placetype":"venue"
},
  "geometry": {"coordinates":[153.101837158,-26.6555843353],"type":"Point"}
}