{
  "type": "Feature",
  "properties": {
    "addr:full":"Wells Rd Frankston VIC 3199",
    "addr:postcode":"3199",
    "addr:street":"Wells Rd",
    "iso:country":"AU",
    "sg:address":"Wells Rd",
    "sg:city":"Frankston",
    "sg:classifiers":[
        {
            "category":"Autos & Motor Vehicles",
            "subcategory":"Auto Supplies",
            "type":"Retail Goods"
        }
    ],
    "sg:phone":"+61 3 9786 1122",
    "sg:postcode":"3199",
    "sg:province":"VIC",
    "sg:tags":[
        "tyre"
    ],
    "wof:name":"Goodyear Auto Service Centre",
    "wof:placetype":"venue"
},
  "geometry": {"coordinates":[145.13398742699999,-38.1241760254],"type":"Point"}
}