{
  "type": "Feature",
  "properties": {
    "addr:full":"Unit 2, 301- 313 Princes Hwy Bomaderry NSW 2541",
    "addr:housenumber":"301 313",
    "addr:postcode":"2541",
    "addr:street":"Princes Hwy",
    "iso:country":"AU",
    "sg:address":"Unit 2, 301- 313 Princes Hwy",
    "sg:city":"Bomaderry",
    "sg:classifiers":[
        {
            "category":"Autos & Motor Vehicles",
            "subcategory":"Auto Supplies",
            "type":"Retail Goods"
        }
    ],
    "sg:phone":"+61 2 4422 0999",
    "sg:postcode":"2541",
    "sg:province":"NSW",
    "sg:tags":[
        "accessory"
    ],
    "wof:name":"Joes Car Detailing & Accessories",
    "wof:placetype":"venue"
},
  "geometry": {"coordinates":[150.59432983400001,-34.8438453674],"type":"Point"}
}