{
  "type": "Feature",
  "properties": {
    "iso:country":"AU",
    "sg:address":"30 Commissioner St",
    "sg:city":"Cooma",
    "sg:classifiers":[
        {
            "category":"Freight",
            "type":"Transportation"
        }
    ],
    "sg:phone":"+61 13 15 31",
    "sg:postcode":"2630",
    "sg:province":"NSW",
    "sg:tags":[
        "light",
        "carrier"
    ],
    "wof:name":"Wards Skyroad",
    "wof:placetype":"venue"
},
  "geometry": {"coordinates":[149.13169860799999,-36.2337799072],"type":"Point"}
}