{
  "type": "Feature",
  "properties": {
    "addr:full":"20 Jusfrute Drv Gosford West NSW 2250",
    "addr:housenumber":"20",
    "addr:postcode":"2250",
    "addr:street":"Jusfrute Drv",
    "iso:country":"AU",
    "sg:address":"20 Jusfrute Drv",
    "sg:city":"Gosford West",
    "sg:classifiers":[
        {
            "category":"Wholesale",
            "subcategory":"Furniture",
            "type":"Manufacturing & Wholesale Goods"
        }
    ],
    "sg:phone":"+61 2 4324 7266",
    "sg:postcode":"2250",
    "sg:province":"NSW",
    "sg:tags":[
        "wholesaler",
        "mfrs"
    ],
    "wof:name":"David's Custombuilt Furniture Pty Ltd",
    "wof:placetype":"venue"
},
  "geometry": {"coordinates":[151.31460571299999,-33.4280967712],"type":"Point"}
}