{
  "type": "Feature",
  "properties": {
    "iso:country":"AU",
    "sg:address":"27 Albert Rd",
    "sg:city":"Avalon",
    "sg:classifiers":[
        {
            "category":"Health Services",
            "subcategory":"Health Practitioner",
            "type":"Services"
        }
    ],
    "sg:phone":"+61 2 9918 2803",
    "sg:postcode":"2107",
    "sg:province":"NSW",
    "sg:tags":[
        "herbalist"
    ],
    "wof:name":"Searl Geoff",
    "wof:placetype":"venue"
},
  "geometry": {"coordinates":[151.335739136,-33.6215744019],"type":"Point"}
}