{
  "type": "Feature",
  "properties": {
    "addr:full":"PO Box 99 Thomastown VIC 3074",
    "addr:postcode":"3074",
    "iso:country":"AU",
    "sg:address":"PO Box 99",
    "sg:city":"Thomastown",
    "sg:classifiers":[
        {
            "category":"Manufacturing",
            "subcategory":"Apparel",
            "type":"Manufacturing & Wholesale Goods"
        }
    ],
    "sg:phone":"+61 412 334 187",
    "sg:postcode":"3074",
    "sg:province":"VIC",
    "sg:tags":[
        "wholesaler",
        "mfrs",
        "footwear"
    ],
    "wof:name":"Cammcorp Pty Ltd",
    "wof:placetype":"venue"
},
  "geometry": {"coordinates":[145.01148986800001,-37.6832199097],"type":"Point"}
}