{
  "type": "Feature",
  "properties": {
    "iso:country":"AU",
    "sg:address":"66- 68 Stroud St",
    "sg:city":"Bulahdelah",
    "sg:classifiers":[
        {
            "category":"Autos & Motor Vehicles",
            "subcategory":"Auto Supplies",
            "type":"Retail Goods"
        }
    ],
    "sg:phone":"+61 2 4987 9261",
    "sg:postcode":"2423",
    "sg:province":"NSW",
    "sg:tags":[
        "tyre"
    ],
    "wof:name":"Bulahdelah Tyre & Mechanical",
    "wof:placetype":"venue"
},
  "geometry": {"coordinates":[152.20837399999999,-32.406536],"type":"Point"}
}