{
  "type": "Feature",
  "properties": {
    "addr:full":"Un 1/ 393 Smith St Fitzroy VIC 3065",
    "addr:housenumber":"/ 393",
    "addr:postcode":"3065",
    "addr:street":"Smith St",
    "iso:country":"AU",
    "sg:address":"Un 1/ 393 Smith St",
    "sg:city":"Fitzroy",
    "sg:classifiers":[
        {
            "category":"Health Services",
            "subcategory":"Health Practitioner",
            "type":"Services"
        }
    ],
    "sg:phone":"+61 3 9486 9996",
    "sg:postcode":"3065",
    "sg:province":"VIC",
    "sg:tags":[
        "naturopath"
    ],
    "wof:name":"Melbourne Physical & Natural Therapies Clinic",
    "wof:placetype":"venue"
},
  "geometry": {"coordinates":[144.98435974099999,-37.7974281311],"type":"Point"}
}