{
  "type": "Feature",
  "properties": {
    "addr:full":"Shop 32, Q Super Centre, Corner Markeri & Bermuda Mermaid Waters QLD 4218",
    "addr:housenumber":"shop 32",
    "addr:postcode":"4218",
    "iso:country":"AU",
    "sg:address":"Shop 32, Q Super Centre, Corner Markeri & Bermuda",
    "sg:city":"Mermaid Waters",
    "sg:classifiers":[
        {
            "category":"Health Services",
            "subcategory":"Dentist",
            "type":"Services"
        }
    ],
    "sg:phone":"+61 7 5578 5366",
    "sg:postcode":"4218",
    "sg:province":"QLD",
    "wof:name":"Ben Swindley Dental",
    "wof:placetype":"venue"
},
  "geometry": {"coordinates":[153.407272339,-28.0484409332],"type":"Point"}
}