{
  "type": "Feature",
  "properties": {
    "addr:full":"PO Box 440 Aitkenvale QLD 4814",
    "addr:postcode":"4814",
    "iso:country":"AU",
    "sg:address":"PO Box 440",
    "sg:city":"Aitkenvale",
    "sg:classifiers":[
        {
            "category":"Building & Trades",
            "subcategory":"Plumbing",
            "type":"Services"
        }
    ],
    "sg:phone":"+61 7 4779 3992",
    "sg:postcode":"4814",
    "sg:province":"QLD",
    "sg:tags":[
        "plumber",
        "gasfitters"
    ],
    "wof:name":"Accredited Valve Testing",
    "wof:placetype":"venue"
},
  "geometry": {"coordinates":[146.76745600000001,-19.2953],"type":"Point"}
}