{
  "type": "Feature",
  "properties": {
    "iso:country":"AU",
    "sg:address":"35a Lawson Crs",
    "sg:city":"Coffs Harbour",
    "sg:classifiers":[
        {
            "category":"Freight",
            "type":"Transportation"
        }
    ],
    "sg:phone":"+61 13 23 45",
    "sg:postcode":"2450",
    "sg:province":"NSW",
    "sg:tags":[
        "light",
        "carrier"
    ],
    "wof:name":"Star Track Express",
    "wof:placetype":"venue"
},
  "geometry": {"coordinates":[153.115158,-30.29701],"type":"Point"}
}