{
  "type": "Feature",
  "properties": {
    "addr:full":"11 Light St Hamley Bridge SA 5401",
    "addr:housenumber":"11",
    "addr:postcode":"5401",
    "addr:street":"Light St",
    "iso:country":"AU",
    "sg:address":"11 Light St",
    "sg:city":"Hamley Bridge",
    "sg:classifiers":[
        {
            "category":"Personal",
            "subcategory":"Beauty Salon",
            "type":"Services"
        }
    ],
    "sg:phone":"+61 8 8528 2344",
    "sg:postcode":"5401",
    "sg:province":"SA",
    "sg:tags":[
        "hairdresser"
    ],
    "wof:name":"Hamley Hair Connection",
    "wof:placetype":"venue"
},
  "geometry": {"coordinates":[138.68165588400001,-34.3569793701],"type":"Point"}
}