{
  "type": "Feature",
  "properties": {
    "addr:full":"Lvl 2/ 64 Talavera Rd North Ryde NSW 2113",
    "addr:housenumber":"/ 64",
    "addr:postcode":"2113",
    "addr:street":"Talavera Rd",
    "iso:country":"AU",
    "sg:address":"Lvl 2/ 64 Talavera Rd",
    "sg:city":"North Ryde",
    "sg:classifiers":[
        {
            "category":"Professional",
            "subcategory":"Computer Services",
            "type":"Services"
        }
    ],
    "sg:phone":"+61 2 9882 5000",
    "sg:postcode":"2113",
    "sg:province":"NSW",
    "sg:tags":[
        "consultant",
        "system"
    ],
    "wof:name":"Saturn Alliance Pty Ltd",
    "wof:placetype":"venue"
},
  "geometry": {"coordinates":[151.12362670900001,-33.7766914368],"type":"Point"}
}