{
  "type": "Feature",
  "properties": {
    "iso:country":"AU",
    "sg:address":"Lvl 6 6 Thomas St",
    "sg:city":"Chatswood",
    "sg:classifiers":[
        {
            "category":"Home & Garden",
            "subcategory":"Building Materials",
            "type":"Retail Goods"
        }
    ],
    "sg:phone":"+61 2 9928 3500",
    "sg:postcode":"2067",
    "sg:province":"NSW",
    "sg:tags":[
        "supply"
    ],
    "wof:name":"Amatek Group",
    "wof:placetype":"venue"
},
  "geometry": {"coordinates":[151.18026733400001,-33.7981338501],"type":"Point"}
}