{
  "type": "Feature",
  "properties": {
    "addr:full":"1 Formby Rd Devonport TAS 7310",
    "addr:housenumber":"1",
    "addr:postcode":"7310",
    "addr:street":"Formby Rd",
    "iso:country":"AU",
    "sg:address":"1 Formby Rd",
    "sg:city":"Devonport",
    "sg:classifiers":[
        {
            "category":"Farming",
            "subcategory":"Farm & Veterinary Services",
            "type":"Manufacturing & Wholesale Goods"
        }
    ],
    "sg:phone":"+61 3 6424 4377",
    "sg:postcode":"7310",
    "sg:province":"TAS",
    "sg:tags":[
        "agricultural",
        "advisory"
    ],
    "wof:name":"Roberts Ltd",
    "wof:placetype":"venue"
},
  "geometry": {"coordinates":[146.36286926299999,-41.1930847168],"type":"Point"}
}