{
  "type": "Feature",
  "properties": {
    "addr:full":"M S 963 Dahls Rd South Kalkie QLD 4670",
    "addr:housenumber":"963",
    "addr:postcode":"4670",
    "addr:street":"Dahls Rd South",
    "iso:country":"AU",
    "sg:address":"M S 963 Dahls Rd",
    "sg:city":"South Kalkie",
    "sg:classifiers":[
        {
            "category":"Farming",
            "subcategory":"Crops",
            "type":"Manufacturing & Wholesale Goods"
        }
    ],
    "sg:phone":"+61 7 4159 7288",
    "sg:postcode":"4670",
    "sg:province":"QLD",
    "sg:tags":[
        "sugarcane",
        "mill",
        "grower"
    ],
    "wof:name":"Lerch R & Sons",
    "wof:placetype":"venue"
},
  "geometry": {"coordinates":[152.41401672399999,-24.9089927673],"type":"Point"}
}