{
  "type": "Feature",
  "properties": {
    "iso:country":"AU",
    "sg:address":"56 Queen St",
    "sg:city":"Bentley",
    "sg:classifiers":[
        {
            "category":"Health Services",
            "subcategory":"Dentist",
            "type":"Services"
        }
    ],
    "sg:phone":"+61 8 9350 9898",
    "sg:postcode":"6102",
    "sg:province":"WA",
    "wof:name":"Hari Hament",
    "wof:placetype":"venue"
},
  "geometry": {"coordinates":[115.91887664799999,-32.003162384],"type":"Point"}
}