{
  "type": "Feature",
  "properties": {
    "iso:country":"AU",
    "sg:address":"228 Cotham Rd",
    "sg:city":"Kew",
    "sg:classifiers":[
        {
            "category":"Health Services",
            "subcategory":"Doctor",
            "type":"Services"
        }
    ],
    "sg:phone":"+61 3 9375 4552",
    "sg:postcode":"3101",
    "sg:province":"VIC",
    "sg:tags":[
        "medical",
        "practitioner"
    ],
    "wof:name":"Bernard Simon Dr",
    "wof:placetype":"venue"
},
  "geometry": {"coordinates":[145.04672241200001,-37.808807373],"type":"Point"}
}