{
  "type": "Feature",
  "properties": {
    "addr:full":"Unit 11/ 23 Enterprise Ave Tweed Heads South NSW 2486",
    "addr:housenumber":"/ 23",
    "addr:postcode":"2486",
    "addr:street":"Enterprise Ave",
    "iso:country":"AU",
    "sg:address":"Unit 11/ 23 Enterprise Ave",
    "sg:city":"Tweed Heads South",
    "sg:classifiers":[
        {
            "category":"Arena",
            "subcategory":"Sports Club",
            "type":"Entertainment"
        }
    ],
    "sg:phone":"+61 7 5513 1429",
    "sg:postcode":"2486",
    "sg:province":"NSW",
    "sg:tags":[
        "defence",
        "supply",
        "self",
        "instruction",
        "martial art"
    ],
    "wof:name":"Tweed Martial Arts Academy",
    "wof:placetype":"venue"
},
  "geometry": {"coordinates":[153.53480529800001,-28.2047386169],"type":"Point"}
}