{
  "type": "Feature",
  "properties": {
    "iso:country":"AU",
    "sg:address":"Shop 4 Eatons Hill SC Cnr Queen Elizabeth Drv & Ea",
    "sg:city":"Eatons Hill",
    "sg:classifiers":[
        {
            "category":"Food & Beverages",
            "subcategory":"Liquor & Beverages",
            "type":"Retail Goods"
        }
    ],
    "sg:phone":"+61 7 3264 4816",
    "sg:postcode":"4037",
    "sg:province":"QLD",
    "sg:tags":[
        "store"
    ],
    "wof:name":"BWS Liquor Stores",
    "wof:placetype":"venue"
},
  "geometry": {"coordinates":[152.948593,-27.339771],"type":"Point"}
}