{
  "type": "Feature",
  "properties": {
    "addr:full":"3/ 177a Orlando St Coffs Harbour NSW 2450",
    "addr:housenumber":"/ 177a",
    "addr:postcode":"2450",
    "addr:street":"Orlando St",
    "iso:country":"AU",
    "sg:address":"3/ 177a Orlando St",
    "sg:city":"Coffs Harbour",
    "sg:classifiers":[
        {
            "category":"Shopping",
            "subcategory":"Computers & Home Electronics",
            "type":"Retail Goods"
        }
    ],
    "sg:phone":"+61 2 6652 4777",
    "sg:postcode":"2450",
    "sg:province":"NSW",
    "sg:tags":[
        "hardware",
        "equipment"
    ],
    "wof:name":"Jaicor Computers",
    "wof:placetype":"venue"
},
  "geometry": {"coordinates":[153.129166,-30.286854],"type":"Point"}
}