{
  "type": "Feature",
  "properties": {
    "iso:country":"AU",
    "sg:address":"10 Nelson St",
    "sg:city":"Woollahra",
    "sg:classifiers":[
        {
            "category":"Health Services",
            "subcategory":"Doctor",
            "type":"Services"
        }
    ],
    "sg:phone":"+61 2 9363 2589",
    "sg:postcode":"2025",
    "sg:province":"NSW",
    "sg:tags":[
        "medical",
        "practitioner"
    ],
    "wof:name":"Jacobs L A",
    "wof:placetype":"venue"
},
  "geometry": {"coordinates":[151.24244689899999,-33.8881111145],"type":"Point"}
}