{
  "type": "Feature",
  "properties": {
    "iso:country":"AU",
    "sg:address":"27-31 Barkley Hwy",
    "sg:city":"Mt Isa",
    "sg:classifiers":[
        {
            "category":"Professional",
            "subcategory":"Engineering",
            "type":"Services"
        }
    ],
    "sg:phone":"+61 7 4743 3833",
    "sg:postcode":"4825",
    "sg:province":"QLD",
    "sg:tags":[
        "engineer"
    ],
    "wof:name":"Cava Hydraulics & Auto Electrics",
    "wof:placetype":"venue"
},
  "geometry": {"coordinates":[139.49430799999999,-20.712355],"type":"Point"}
}