{
  "type": "Feature",
  "properties": {
    "addr:full":"9 Caloola Rd Pendle Hill NSW 2145",
    "addr:housenumber":"9",
    "addr:postcode":"2145",
    "addr:street":"Caloola Rd",
    "iso:country":"AU",
    "sg:address":"9 Caloola Rd",
    "sg:city":"Pendle Hill",
    "sg:classifiers":[
        {
            "category":"Home & Garden",
            "subcategory":"Home Furnishings",
            "type":"Retail Goods"
        }
    ],
    "sg:phone":"+61 2 9896 6052",
    "sg:postcode":"2145",
    "sg:province":"NSW",
    "sg:tags":[
        "shower",
        "screen"
    ],
    "wof:name":"Kornerstone & Glass",
    "wof:placetype":"venue"
},
  "geometry": {"coordinates":[150.96743774399999,-33.7975273132],"type":"Point"}
}