{
  "type": "Feature",
  "properties": {
    "addr:full":"21 Niblo St Doonside NSW 2767",
    "addr:housenumber":"21",
    "addr:postcode":"2767",
    "addr:street":"Niblo St",
    "iso:country":"AU",
    "sg:address":"21 Niblo St",
    "sg:city":"Doonside",
    "sg:classifiers":[
        {
            "category":"Building & Trades",
            "subcategory":"Construction",
            "type":"Services"
        }
    ],
    "sg:phone":"+61 401 180 701",
    "sg:postcode":"2767",
    "sg:province":"NSW",
    "sg:tags":[
        "contractor"
    ],
    "wof:name":"B.E.C. Constructions",
    "wof:placetype":"venue"
},
  "geometry": {"coordinates":[150.87225341800001,-33.754524231],"type":"Point"}
}