{
  "type": "Feature",
  "properties": {
    "addr:full":"11 High St Wodonga VIC 3690",
    "addr:housenumber":"11",
    "addr:postcode":"3690",
    "addr:street":"High St",
    "iso:country":"AU",
    "sg:address":"11 High St",
    "sg:city":"Wodonga",
    "sg:classifiers":[
        {
            "category":"Travel",
            "subcategory":"Hotels & Motels",
            "type":"Entertainment"
        }
    ],
    "sg:phone":"+61 2 6024 1122",
    "sg:postcode":"3690",
    "sg:province":"VIC",
    "wof:name":"Sanctuary Park Motel",
    "wof:placetype":"venue"
},
  "geometry": {"coordinates":[146.89271545400001,-36.1134033203],"type":"Point"}
}