{
  "type": "Feature",
  "properties": {
    "addr:full":"\"Shenstone\" Culgoora Rd Wee Waa NSW 2388",
    "addr:postcode":"2388",
    "addr:street":"Culgoora Rd",
    "iso:country":"AU",
    "sg:address":"\"Shenstone\" Culgoora Rd",
    "sg:city":"Wee Waa",
    "sg:classifiers":[
        {
            "category":"Farming",
            "subcategory":"Farm & Veterinary Services",
            "type":"Manufacturing & Wholesale Goods"
        }
    ],
    "sg:phone":"+61 2 6795 0000",
    "sg:postcode":"2388",
    "sg:province":"NSW",
    "sg:tags":[
        "seedsman"
    ],
    "wof:name":"Cotton Seed Distributors Ltd",
    "wof:placetype":"venue"
},
  "geometry": {"coordinates":[149.437576294,-30.2262001038],"type":"Point"}
}