{
  "type": "Feature",
  "properties": {
    "iso:country":"AU",
    "sg:address":"465 Princes Hwy",
    "sg:city":"Bairnsdale",
    "sg:classifiers":[
        {
            "category":"Banks & Credit Unions",
            "subcategory":"Investment Brokerage",
            "type":"Services"
        }
    ],
    "sg:phone":"+61 3 5152 4584",
    "sg:postcode":"3875",
    "sg:province":"VIC",
    "sg:tags":[
        "radiator",
        "motor"
    ],
    "wof:name":"John Matchan",
    "wof:placetype":"venue"
},
  "geometry": {"coordinates":[147.59295654300001,-37.8406524658],"type":"Point"}
}