{
  "type": "Feature",
  "properties": {
    "addr:full":"29 Macfarlane St South Hobart TAS 7004",
    "addr:housenumber":"29",
    "addr:postcode":"7004",
    "addr:street":"Macfarlane St",
    "iso:country":"AU",
    "sg:address":"29 Macfarlane St",
    "sg:city":"South Hobart",
    "sg:classifiers":[
        {
            "category":"Health Services",
            "subcategory":"Health Practitioner",
            "type":"Services"
        }
    ],
    "sg:phone":"+61 3 6223 4842",
    "sg:postcode":"7004",
    "sg:province":"TAS",
    "sg:tags":[
        "naturopath"
    ],
    "wof:name":"Erin Collins",
    "wof:placetype":"venue"
},
  "geometry": {"coordinates":[147.30453491200001,-42.8945579529],"type":"Point"}
}