{
  "type": "Feature",
  "properties": {
    "addr:full":"8 Erudina Ave Edwardstown SA 5039",
    "addr:housenumber":"8",
    "addr:postcode":"5039",
    "addr:street":"Erudina Ave",
    "iso:country":"AU",
    "sg:address":"8 Erudina Ave",
    "sg:city":"Edwardstown",
    "sg:classifiers":[
        {
            "category":"Mining & Drilling",
            "type":"Manufacturing & Wholesale Goods"
        }
    ],
    "sg:phone":"+61 8 8299 0790",
    "sg:postcode":"5039",
    "sg:province":"SA",
    "sg:tags":[
        "boring",
        "contractor"
    ],
    "wof:name":"Geodrill K & W Pty Ltd",
    "wof:placetype":"venue"
},
  "geometry": {"coordinates":[138.57142639200001,-34.9904899597],"type":"Point"}
}