{
  "type": "Feature",
  "properties": {
    "addr:full":"84a Gormanston Rd Moonah TAS 7009",
    "addr:housenumber":"84a",
    "addr:postcode":"7009",
    "addr:street":"Gormanston Rd",
    "iso:country":"AU",
    "sg:address":"84a Gormanston Rd",
    "sg:city":"Moonah",
    "sg:classifiers":[
        {
            "category":"Professional",
            "subcategory":"Accounting & Tax Preparation",
            "type":"Services"
        }
    ],
    "sg:phone":"+61 3 6272 0084",
    "sg:postcode":"7009",
    "sg:province":"TAS",
    "sg:tags":[
        "accountant",
        "auditor"
    ],
    "wof:name":"Thompson, Peter",
    "wof:placetype":"venue"
},
  "geometry": {"coordinates":[147.297805786,-42.8404464722],"type":"Point"}
}