{
  "type": "Feature",
  "properties": {
    "addr:full":"Nerang St Waterford QLD 4133",
    "addr:postcode":"4133",
    "addr:street":"Nerang St",
    "iso:country":"AU",
    "sg:address":"Nerang St",
    "sg:city":"Waterford",
    "sg:classifiers":[
        {
            "category":"Education",
            "subcategory":"School",
            "type":"Public Place"
        }
    ],
    "sg:phone":"+61 7 3451 8222",
    "sg:postcode":"4133",
    "sg:province":"QLD",
    "sg:tags":[
        "state",
        "except",
        "nsw"
    ],
    "wof:name":"Waterford Primary",
    "wof:placetype":"venue"
},
  "geometry": {"coordinates":[153.14613342300001,-27.6981906891],"type":"Point"}
}