{
  "type": "Feature",
  "properties": {
    "addr:full":"40 Mary St Beacon Hill NSW 2100",
    "addr:housenumber":"40",
    "addr:postcode":"2100",
    "addr:street":"Mary St",
    "iso:country":"AU",
    "sg:address":"40 Mary St",
    "sg:city":"Beacon Hill",
    "sg:classifiers":[
        {
            "category":"Food & Beverages",
            "subcategory":"Bakery",
            "type":"Retail Goods"
        }
    ],
    "sg:phone":"+61 410 615 062",
    "sg:postcode":"2100",
    "sg:province":"NSW",
    "sg:tags":[
        "cake",
        "shop",
        "pastry"
    ],
    "wof:name":"Sugar Pea Creation",
    "wof:placetype":"venue"
},
  "geometry": {"coordinates":[151.25721740700001,-33.7545585632],"type":"Point"}
}