{
  "type": "Feature",
  "properties": {
    "iso:country":"AU",
    "sg:address":"66 High St",
    "sg:city":"Southport",
    "sg:classifiers":[
        {
            "category":"Education",
            "subcategory":"Special Training",
            "type":"Public Place"
        }
    ],
    "sg:phone":"+61 1800 625 652",
    "sg:postcode":"4215",
    "sg:province":"QLD",
    "sg:tags":[
        "development"
    ],
    "wof:name":"Admin Training Company",
    "wof:placetype":"venue"
},
  "geometry": {"coordinates":[153.409423828,-27.968038559],"type":"Point"}
}