{
  "type": "Feature",
  "properties": {
    "addr:full":"19- 20 Waratah St Rushcutters Bay NSW 2011",
    "addr:housenumber":"20",
    "addr:postcode":"2011",
    "addr:street":"Waratah St",
    "iso:country":"AU",
    "sg:address":"19- 20 Waratah St",
    "sg:city":"Rushcutters Bay",
    "sg:classifiers":[
        {
            "category":"Shopping",
            "subcategory":"Computers & Home Electronics",
            "type":"Retail Goods"
        }
    ],
    "sg:phone":"+61 2 9368 0714",
    "sg:postcode":"2011",
    "sg:province":"NSW",
    "sg:tags":[
        "small",
        "equipment",
        "business"
    ],
    "wof:name":"Aerocom Computer Solutions",
    "wof:placetype":"venue"
},
  "geometry": {"coordinates":[151.228424072,-33.8756332397],"type":"Point"}
}