{
  "type": "Feature",
  "properties": {
    "iso:country":"AU",
    "sg:address":"18 Vindex St",
    "sg:city":"Winton",
    "sg:classifiers":[
        {
            "category":"Professional",
            "type":"Services"
        }
    ],
    "sg:phone":"+61 7 4657 1403",
    "sg:postcode":"4735",
    "sg:province":"QLD",
    "sg:tags":[
        "mail",
        "contractor"
    ],
    "wof:name":"Russell P W & V J",
    "wof:placetype":"venue"
},
  "geometry": {"coordinates":[143.040543,-22.389561],"type":"Point"}
}