{
  "type": "Feature",
  "properties": {
    "addr:full":"21 Nervada Pl Oxenford QLD 4210",
    "addr:housenumber":"21",
    "addr:postcode":"4210",
    "addr:street":"Nervada Pl",
    "iso:country":"AU",
    "sg:address":"21 Nervada Pl",
    "sg:city":"Oxenford",
    "sg:classifiers":[
        {
            "category":"Utilities",
            "type":"Services"
        }
    ],
    "sg:phone":"+61 400 020 142",
    "sg:postcode":"4210",
    "sg:province":"QLD",
    "sg:tags":[
        "refrigeration",
        "industrial",
        "commercial",
        "retail"
    ],
    "wof:name":"Temprite Refrigeration",
    "wof:placetype":"venue"
},
  "geometry": {"coordinates":[153.30938720699999,-27.9019775391],"type":"Point"}
}