{
  "type": "Feature",
  "properties": {
    "addr:full":"1 Gilwell Ave Traralgon VIC 3844",
    "addr:housenumber":"1",
    "addr:postcode":"3844",
    "addr:street":"Gilwell Ave",
    "iso:country":"AU",
    "sg:address":"1 Gilwell Ave",
    "sg:city":"Traralgon",
    "sg:classifiers":[
        {
            "category":"Health Services",
            "subcategory":"Doctor",
            "type":"Services"
        }
    ],
    "sg:phone":"+61 3 5174 8140",
    "sg:postcode":"3844",
    "sg:province":"VIC",
    "sg:tags":[
        "reflexology"
    ],
    "wof:name":"Lancaster J M",
    "wof:placetype":"venue"
},
  "geometry": {"coordinates":[146.53004455600001,-38.1889953613],"type":"Point"}
}