{
  "type": "Feature",
  "properties": {
    "addr:full":"Suite 401/ 74 Pitt St Sydney NSW 2000",
    "addr:housenumber":"401 / 74",
    "addr:postcode":"2000",
    "addr:street":"Pitt St",
    "iso:country":"AU",
    "sg:address":"Suite 401/ 74 Pitt St",
    "sg:city":"Sydney",
    "sg:classifiers":[
        {
            "category":"Social Services",
            "subcategory":"Retirement Home",
            "type":"Services"
        }
    ],
    "sg:phone":"+61 2 9221 3306",
    "sg:postcode":"2000",
    "sg:province":"NSW",
    "sg:tags":[
        "life",
        "coaching"
    ],
    "wof:name":"The Happiness Institute",
    "wof:placetype":"venue"
},
  "geometry": {"coordinates":[151.20875549300001,-33.8661460876],"type":"Point"}
}