{
  "type": "Feature",
  "properties": {
    "addr:full":"16 Ian Ave North Curl Curl NSW 2099",
    "addr:housenumber":"16",
    "addr:postcode":"2099",
    "addr:street":"Ian Ave North",
    "iso:country":"AU",
    "sg:address":"16 Ian Ave",
    "sg:city":"North Curl Curl",
    "sg:classifiers":[
        {
            "category":"Building & Trades",
            "subcategory":"Construction",
            "type":"Services"
        }
    ],
    "sg:phone":"+61 419 602 072",
    "sg:postcode":"2099",
    "sg:province":"NSW",
    "sg:tags":[
        "concrete",
        "contractor"
    ],
    "wof:name":"Warren Clifton",
    "wof:placetype":"venue"
},
  "geometry": {"coordinates":[151.300537109,-33.763053894],"type":"Point"}
}