{
  "type": "Feature",
  "properties": {
    "addr:full":"155 Wycombe Rd Neutral Bay NSW 2089",
    "addr:housenumber":"155",
    "addr:postcode":"2089",
    "addr:street":"Wycombe Rd",
    "iso:country":"AU",
    "sg:address":"155 Wycombe Rd",
    "sg:city":"Neutral Bay",
    "sg:classifiers":[
        {
            "category":"Health Services",
            "subcategory":"Health Practitioner",
            "type":"Services"
        }
    ],
    "sg:phone":"+61 2 9908 3388",
    "sg:postcode":"2089",
    "sg:province":"NSW",
    "sg:tags":[
        "hypnotherapy"
    ],
    "wof:name":"Thompson Dr Geoff",
    "wof:placetype":"venue"
},
  "geometry": {"coordinates":[151.22232055699999,-33.8325538635],"type":"Point"}
}