{
  "type": "Feature",
  "properties": {
    "iso:country":"AU",
    "sg:address":"9 Ruse St",
    "sg:city":"Osborne Park",
    "sg:classifiers":[
        {
            "category":"Retail",
            "subcategory":"Auto Repair",
            "type":"Services"
        }
    ],
    "sg:phone":"+61 8 9443 7741",
    "sg:postcode":"6017",
    "sg:province":"WA",
    "sg:tags":[
        "repairer",
        "motor",
        "engineer"
    ],
    "wof:name":"Bill Lee Automotives",
    "wof:placetype":"venue"
},
  "geometry": {"coordinates":[115.815849304,-31.9077548981],"type":"Point"}
}