{
  "type": "Feature",
  "properties": {
    "addr:full":"106 Annangrove Rd Annangrove NSW 2156",
    "addr:housenumber":"106",
    "addr:postcode":"2156",
    "addr:street":"Annangrove Rd",
    "iso:country":"AU",
    "sg:address":"106 Annangrove Rd",
    "sg:city":"Annangrove",
    "sg:classifiers":[
        {
            "category":"Wholesale",
            "subcategory":"Plants",
            "type":"Manufacturing & Wholesale Goods"
        }
    ],
    "sg:phone":"+61 2 9654 0556",
    "sg:postcode":"2156",
    "sg:province":"NSW",
    "sg:tags":[
        "florist"
    ],
    "wof:name":"Agostino Flowers & Sundries",
    "wof:placetype":"venue"
},
  "geometry": {"coordinates":[150.978393555,-33.6808624268],"type":"Point"}
}