{
  "type": "Feature",
  "properties": {
    "iso:country":"AU",
    "sg:address":"7 Rochester Ave",
    "sg:city":"Colonel Light Gardens",
    "sg:classifiers":[
        {
            "category":"Retail",
            "subcategory":"Storage",
            "type":"Services"
        }
    ],
    "sg:phone":"+61 418 821 628",
    "sg:postcode":"5041",
    "sg:province":"SA",
    "sg:tags":[
        "removal",
        "furniture"
    ],
    "wof:name":"Truck Six Removals",
    "wof:placetype":"venue"
},
  "geometry": {"coordinates":[138.59298699999999,-34.981319],"type":"Point"}
}