{
  "type": "Feature",
  "properties": {
    "addr:full":"213 Gray St Hamilton VIC 3300",
    "addr:housenumber":"213",
    "addr:postcode":"3300",
    "addr:street":"Gray St",
    "iso:country":"AU",
    "sg:address":"213 Gray St",
    "sg:city":"Hamilton",
    "sg:classifiers":[
        {
            "category":"Travel",
            "subcategory":"Hotels & Motels",
            "type":"Entertainment"
        }
    ],
    "sg:phone":"+61 3 5572 1844",
    "sg:postcode":"3300",
    "sg:province":"VIC",
    "wof:name":"George Hotel-Motel",
    "wof:placetype":"venue"
},
  "geometry": {"coordinates":[142.02597045900001,-37.7421875],"type":"Point"}
}