{
  "type": "Feature",
  "properties": {
    "addr:full":"17 Regent St Mayfield NSW 2304",
    "addr:housenumber":"17",
    "addr:postcode":"2304",
    "addr:street":"Regent St",
    "iso:country":"AU",
    "sg:address":"17 Regent St",
    "sg:city":"Mayfield",
    "sg:classifiers":[
        {
            "category":"Health Services",
            "subcategory":"Health Practitioner",
            "type":"Services"
        }
    ],
    "sg:phone":"+61 2 4968 1692",
    "sg:postcode":"2304",
    "sg:province":"NSW",
    "sg:tags":[
        "dietitian"
    ],
    "wof:name":"Ryan Marilyn APD",
    "wof:placetype":"venue"
},
  "geometry": {"coordinates":[151.73802185100001,-32.8963737488],"type":"Point"}
}