{
  "type": "Feature",
  "properties": {
    "iso:country":"AU",
    "sg:address":"91 Cuthbert Drv",
    "sg:city":"Mt Warrigal",
    "sg:classifiers":[
        {
            "category":"Building & Trades",
            "subcategory":"Construction",
            "type":"Services"
        }
    ],
    "sg:phone":"+61 2 4296 3002",
    "sg:postcode":"2528",
    "sg:province":"NSW",
    "sg:tags":[
        "contractor"
    ],
    "wof:name":"Pastrovic & Co Pty Ltd",
    "wof:placetype":"venue"
},
  "geometry": {"coordinates":[150.84202575699999,-34.5497627258],"type":"Point"}
}