{
  "type": "Feature",
  "properties": {
    "addr:full":"73 Munibung Rd Cardiff NSW 2285",
    "addr:housenumber":"73",
    "addr:postcode":"2285",
    "addr:street":"Munibung Rd",
    "iso:country":"AU",
    "sg:address":"73 Munibung Rd",
    "sg:city":"Cardiff",
    "sg:classifiers":[
        {
            "category":"Military Area",
            "subcategory":"Army Base",
            "type":"Public Place"
        }
    ],
    "sg:phone":"+61 2 4956 5955",
    "sg:postcode":"2285",
    "sg:province":"NSW",
    "sg:tags":[
        "wholesaler",
        "mfrs",
        "cement",
        "supply"
    ],
    "wof:name":"Melcann Limited",
    "wof:placetype":"venue"
},
  "geometry": {"coordinates":[151.64057922399999,-32.9427986145],"type":"Point"}
}