{
  "type": "Feature",
  "properties": {
    "addr:full":"166 Grays Point Rd Grays Point NSW 2232",
    "addr:housenumber":"166",
    "addr:postcode":"2232",
    "addr:street":"Grays Point Rd",
    "iso:country":"AU",
    "sg:address":"166 Grays Point Rd",
    "sg:city":"Grays Point",
    "sg:classifiers":[
        {
            "category":"Professional",
            "subcategory":"Computer Services",
            "type":"Services"
        }
    ],
    "sg:phone":"+61 417 328 435",
    "sg:postcode":"2232",
    "sg:province":"NSW",
    "sg:tags":[
        "consultant",
        "system"
    ],
    "wof:name":"Lloyd Corporate Technologies",
    "wof:placetype":"venue"
},
  "geometry": {"coordinates":[151.076660156,-34.0583152771],"type":"Point"}
}