{
  "type": "Feature",
  "properties": {
    "iso:country":"AU",
    "sg:address":"6 Augustine St",
    "sg:city":"Hunters Hill",
    "sg:classifiers":[
        {
            "category":"Manufacturing",
            "subcategory":"Glass & Minerals",
            "type":"Manufacturing & Wholesale Goods"
        }
    ],
    "sg:phone":"+61 2 9879 4619",
    "sg:postcode":"2110",
    "sg:province":"NSW",
    "sg:tags":[
        "stained"
    ],
    "wof:name":"Anders' Stained Glass Studio",
    "wof:placetype":"venue"
},
  "geometry": {"coordinates":[151.134475708,-33.8311042786],"type":"Point"}
}