{
  "type": "Feature",
  "properties": {
    "addr:full":"28 Gassman Drv Yatala QLD 4207",
    "addr:housenumber":"28",
    "addr:postcode":"4207",
    "addr:street":"Gassman Drv",
    "iso:country":"AU",
    "sg:address":"28 Gassman Drv",
    "sg:city":"Yatala",
    "sg:classifiers":[
        {
            "category":"Wholesale",
            "subcategory":"Metals & Minerals",
            "type":"Manufacturing & Wholesale Goods"
        }
    ],
    "sg:phone":"+61 7 3287 1666",
    "sg:postcode":"4207",
    "sg:province":"QLD",
    "sg:tags":[
        "steel",
        "merchant"
    ],
    "wof:name":"The Metal Centre",
    "wof:placetype":"venue"
},
  "geometry": {"coordinates":[153.22651672399999,-27.7371501923],"type":"Point"}
}