{
  "type": "Feature",
  "properties": {
    "addr:full":"33 Lavender St Inala QLD 4077",
    "addr:housenumber":"33",
    "addr:postcode":"4077",
    "addr:street":"Lavender St",
    "iso:country":"AU",
    "sg:address":"33 Lavender St",
    "sg:city":"Inala",
    "sg:classifiers":[
        {
            "category":"Food & Beverages",
            "subcategory":"Supermarket",
            "type":"Retail Goods"
        }
    ],
    "sg:phone":"+61 7 3278 7097",
    "sg:postcode":"4077",
    "sg:province":"QLD",
    "sg:tags":[
        "grocery",
        "store"
    ],
    "wof:name":"Four Square Stores (Qld) Ltd",
    "wof:placetype":"venue"
},
  "geometry": {"coordinates":[152.96311950699999,-27.5932178497],"type":"Point"}
}