{
  "type": "Feature",
  "properties": {
    "iso:country":"AU",
    "sg:address":"Unit 1, 9 Fielden Way",
    "sg:city":"Port Kennedy",
    "sg:classifiers":[
        {
            "category":"Retail",
            "subcategory":"Veterinary Services",
            "type":"Services"
        }
    ],
    "sg:phone":"+61 8 9524 6644",
    "sg:postcode":"6172",
    "sg:province":"WA",
    "sg:tags":[
        "surgeon"
    ],
    "sg:website":"http://www.portkennedyveterinaryhospital.com.au",
    "wof:name":"Port Kennedy Veterinary Hospital",
    "wof:placetype":"venue"
},
  "geometry": {"coordinates":[115.758072,-32.364719],"type":"Point"}
}