{
  "type": "Feature",
  "properties": {
    "addr:full":"15 Hickey Rd Tallygaroopna VIC 3634",
    "addr:housenumber":"15",
    "addr:postcode":"3634",
    "addr:street":"Hickey Rd",
    "iso:country":"AU",
    "sg:address":"15 Hickey Rd",
    "sg:city":"Tallygaroopna",
    "sg:classifiers":[
        {
            "category":"Building & Trades",
            "subcategory":"Construction",
            "type":"Services"
        }
    ],
    "sg:phone":"+61 3 5828 3484",
    "sg:postcode":"3634",
    "sg:province":"VIC",
    "sg:tags":[
        "brick",
        "paving"
    ],
    "wof:name":"Sun City Paving",
    "wof:placetype":"venue"
},
  "geometry": {"coordinates":[145.53248596200001,-36.2281036377],"type":"Point"}
}