{
  "type": "Feature",
  "properties": {
    "addr:full":"Locked Bag 1 Ellenbrook WA 6069",
    "addr:postcode":"6069",
    "iso:country":"AU",
    "sg:address":"Locked Bag 1",
    "sg:city":"Ellenbrook",
    "sg:classifiers":[
        {
            "category":"Shopping",
            "subcategory":"Party Supplies",
            "type":"Retail Goods"
        }
    ],
    "sg:phone":"+61 407 929 022",
    "sg:postcode":"6069",
    "sg:province":"WA",
    "sg:tags":[
        "children's"
    ],
    "wof:name":"The Ice Cream Kids",
    "wof:placetype":"venue"
},
  "geometry": {"coordinates":[116.003829956,-31.7694969177],"type":"Point"}
}