{
  "type": "Feature",
  "properties": {
    "addr:full":"188 Newell St Bungalow QLD 4870",
    "addr:housenumber":"188",
    "addr:postcode":"4870",
    "addr:street":"Newell St",
    "iso:country":"AU",
    "sg:address":"188 Newell St",
    "sg:city":"Bungalow",
    "sg:classifiers":[
        {
            "category":"Utilities",
            "subcategory":"Electric",
            "type":"Services"
        }
    ],
    "sg:phone":"+61 7 4054 5856",
    "sg:postcode":"4870",
    "sg:province":"QLD",
    "sg:tags":[
        "electrical",
        "contractor"
    ],
    "wof:name":"C & J Electrical",
    "wof:placetype":"venue"
},
  "geometry": {"coordinates":[145.753005981,-16.9404621124],"type":"Point"}
}