{
  "type": "Feature",
  "properties": {
    "iso:country":"AU",
    "sg:address":"636 Forest Rd",
    "sg:city":"Bexley",
    "sg:classifiers":[
        {
            "category":"Professional",
            "subcategory":"Computer Services",
            "type":"Services"
        }
    ],
    "sg:phone":"+61 2 9553 6455",
    "sg:postcode":"2207",
    "sg:province":"NSW",
    "sg:tags":[
        "repairs",
        "upgrade",
        "equipment"
    ],
    "wof:name":"I. T. Tools",
    "wof:placetype":"venue"
},
  "geometry": {"coordinates":[151.118378,-33.956017],"type":"Point"}
}