{
  "type": "Feature",
  "properties": {
    "addr:full":"62 Sydney St Mackay QLD 4740",
    "addr:housenumber":"62",
    "addr:postcode":"4740",
    "addr:street":"Sydney St",
    "iso:country":"AU",
    "sg:address":"62 Sydney St",
    "sg:city":"Mackay",
    "sg:classifiers":[
        {
            "category":"Health Services",
            "subcategory":"Health Practitioner",
            "type":"Services"
        }
    ],
    "sg:phone":"+61 7 4951 3003",
    "sg:postcode":"4740",
    "sg:province":"QLD",
    "sg:tags":[
        "naturopath"
    ],
    "wof:name":"Holistic Health Mackay",
    "wof:placetype":"venue"
},
  "geometry": {"coordinates":[149.18528699999999,-21.144245],"type":"Point"}
}