{
  "type": "Feature",
  "properties": {
    "addr:full":"314 Autumn St Herne Hill VIC 3218",
    "addr:housenumber":"314",
    "addr:postcode":"3218",
    "addr:street":"Autumn St",
    "iso:country":"AU",
    "sg:address":"314 Autumn St",
    "sg:city":"Herne Hill",
    "sg:classifiers":[
        {
            "category":"Health Services",
            "subcategory":"Chiropractor",
            "type":"Services"
        }
    ],
    "sg:phone":"+61 3 5229 7872",
    "sg:postcode":"3218",
    "sg:province":"VIC",
    "wof:name":"Autumn Street Chiropractic",
    "wof:placetype":"venue"
},
  "geometry": {"coordinates":[144.326904297,-38.1403656006],"type":"Point"}
}