{
  "type": "Feature",
  "properties": {
    "addr:full":"131 Balmain Rd Leichhardt NSW 2040",
    "addr:housenumber":"131",
    "addr:postcode":"2040",
    "addr:street":"Balmain Rd",
    "iso:country":"AU",
    "sg:address":"131 Balmain Rd",
    "sg:city":"Leichhardt",
    "sg:classifiers":[
        {
            "category":"Organizations",
            "subcategory":"Community Association",
            "type":"Services"
        }
    ],
    "sg:phone":"+61 2 9564 2642",
    "sg:postcode":"2040",
    "sg:province":"NSW",
    "sg:tags":[
        "cheese",
        "product"
    ],
    "wof:name":"Staffords The Fine Cheese People",
    "wof:placetype":"venue"
},
  "geometry": {"coordinates":[151.15902700000001,-33.881649],"type":"Point"}
}