{
  "type": "Feature",
  "properties": {
    "addr:full":"65 Church hill Ave Bright VIC 3741",
    "addr:housenumber":"65",
    "addr:postcode":"3741",
    "addr:street":"Church Hill Ave",
    "iso:country":"AU",
    "sg:address":"65 Church hill Ave",
    "sg:city":"Bright",
    "sg:classifiers":[
        {
            "category":"Building & Trades",
            "subcategory":"Construction",
            "type":"Services"
        }
    ],
    "sg:phone":"+61 418 574 753",
    "sg:postcode":"3741",
    "sg:province":"VIC",
    "sg:tags":[
        "contractor"
    ],
    "wof:name":"CADZ Services Pty Ltd",
    "wof:placetype":"venue"
},
  "geometry": {"coordinates":[146.97642500000001,-36.736191],"type":"Point"}
}