{
  "type": "Feature",
  "properties": {
    "addr:full":"Cnr The Entrance Rd & Avoca Drv Erina NSW 2250",
    "addr:postcode":"2250",
    "addr:street":"Cnr The Entrance Rd & Avoca Drv",
    "iso:country":"AU",
    "sg:address":"Cnr The Entrance Rd & Avoca Drv",
    "sg:city":"Erina",
    "sg:classifiers":[
        {
            "category":"Autos & Motor Vehicles",
            "subcategory":"Motorcycle Sales",
            "type":"Retail Goods"
        }
    ],
    "sg:phone":"+61 2 4367 6898",
    "sg:postcode":"2250",
    "sg:province":"NSW",
    "sg:tags":[
        "outboard"
    ],
    "wof:name":"Coastal Outboard Sales & Service",
    "wof:placetype":"venue"
},
  "geometry": {"coordinates":[151.39132690400001,-33.432384491],"type":"Point"}
}