{
  "type": "Feature",
  "properties": {
    "addr:full":"62a Molesworth St Lismore NSW 2480",
    "addr:housenumber":"62a",
    "addr:postcode":"2480",
    "addr:street":"Molesworth St",
    "iso:country":"AU",
    "sg:address":"62a Molesworth St",
    "sg:city":"Lismore",
    "sg:classifiers":[
        {
            "category":"Fast Food",
            "type":"Food & Drink"
        }
    ],
    "sg:phone":"+61 2 6621 3839",
    "sg:postcode":"2480",
    "sg:province":"NSW",
    "sg:tags":[
        "away",
        "take"
    ],
    "wof:name":"Kol's Kebabs",
    "wof:placetype":"venue"
},
  "geometry": {"coordinates":[153.27696227999999,-28.8073863983],"type":"Point"}
}