{
  "type": "Feature",
  "properties": {
    "addr:full":"Unit 6/ 26 Hector St Osborne Park WA 6017",
    "addr:housenumber":"26",
    "addr:postcode":"6017",
    "addr:street":"Hector St",
    "iso:country":"AU",
    "sg:address":"Unit 6/ 26 Hector St",
    "sg:city":"Osborne Park",
    "sg:classifiers":[
        {
            "category":"Home & Garden",
            "subcategory":"Building Materials",
            "type":"Retail Goods"
        }
    ],
    "sg:phone":"+61 8 9445 1475",
    "sg:postcode":"6017",
    "sg:province":"WA",
    "sg:tags":[
        "balustrading"
    ],
    "wof:name":"Alchemy Iron Pty Ltd",
    "wof:placetype":"venue"
},
  "geometry": {"coordinates":[115.81407165500001,-31.8990840912],"type":"Point"}
}