{
  "type": "Feature",
  "properties": {
    "addr:full":"Shop 3, 20 Pakington St Geelong West VIC 3218",
    "addr:housenumber":"shop;20",
    "addr:postcode":"3218",
    "addr:street":"Pakington St",
    "iso:country":"AU",
    "sg:address":"Shop 3, 20 Pakington St",
    "sg:city":"Geelong West",
    "sg:classifiers":[
        {
            "category":"Manufacturing",
            "subcategory":"Furniture",
            "type":"Manufacturing & Wholesale Goods"
        }
    ],
    "sg:phone":"+61 3 5221 0622",
    "sg:postcode":"3218",
    "sg:province":"VIC",
    "sg:tags":[
        "builder",
        "designer",
        "custom"
    ],
    "wof:name":"In Furniture",
    "wof:placetype":"venue"
},
  "geometry": {"coordinates":[144.349807739,-38.1337051392],"type":"Point"}
}