{
  "type": "Feature",
  "properties": {
    "addr:full":"Unit 3, 201 Foreshore Drv Geraldton WA 6530",
    "addr:housenumber":"201",
    "addr:postcode":"6530",
    "addr:street":"Foreshore Drv",
    "iso:country":"AU",
    "sg:address":"Unit 3, 201 Foreshore Drv",
    "sg:city":"Geraldton",
    "sg:classifiers":[
        {
            "category":"Real Estate",
            "subcategory":"Real Estate Agent",
            "type":"Services"
        }
    ],
    "sg:phone":"+61 8 9921 1733",
    "sg:postcode":"6530",
    "sg:province":"WA",
    "sg:website":"http://www.raywhite.com.au",
    "wof:name":"Ray White Geraldton",
    "wof:placetype":"venue"
},
  "geometry": {"coordinates":[114.611328125,-28.7696552277],"type":"Point"}
}