{
  "type": "Feature",
  "properties": {
    "addr:full":"Dillons La Alstonville NSW 2477",
    "addr:postcode":"2477",
    "iso:country":"AU",
    "sg:address":"Dillons La",
    "sg:city":"Alstonville",
    "sg:classifiers":[
        {
            "category":"Building & Trades",
            "subcategory":"Construction",
            "type":"Services"
        }
    ],
    "sg:phone":"+61 416 257 300",
    "sg:postcode":"2477",
    "sg:province":"NSW",
    "sg:tags":[
        "contractor"
    ],
    "wof:name":"Pyowood Pty Ltd",
    "wof:placetype":"venue"
},
  "geometry": {"coordinates":[153.466064453,-28.8437728882],"type":"Point"}
}