{
  "type": "Feature",
  "properties": {
    "addr:full":"19 Dawkins Ave Willaston SA 5118",
    "addr:housenumber":"19",
    "addr:postcode":"5118",
    "addr:street":"Dawkins Ave",
    "iso:country":"AU",
    "sg:address":"19 Dawkins Ave",
    "sg:city":"Willaston",
    "sg:classifiers":[
        {
            "category":"Travel",
            "subcategory":"Hostel",
            "type":"Entertainment"
        }
    ],
    "sg:phone":"+61 8 8522 3255",
    "sg:postcode":"5118",
    "sg:province":"SA",
    "sg:tags":[
        "home"
    ],
    "wof:name":"James Martin Residential Care Centre",
    "wof:placetype":"venue"
},
  "geometry": {"coordinates":[138.74009699999999,-34.581242],"type":"Point"}
}