{
  "type": "Feature",
  "properties": {
    "iso:country":"AU",
    "sg:address":"423 Hawthorn Rd",
    "sg:city":"Caulfield South",
    "sg:classifiers":[
        {
            "category":"Health Services",
            "subcategory":"Optometrist",
            "type":"Services"
        }
    ],
    "sg:phone":"+61 3 9528 4333",
    "sg:postcode":"3162",
    "sg:province":"VIC",
    "wof:name":"Gordon Rory",
    "wof:placetype":"venue"
},
  "geometry": {"coordinates":[145.02125549300001,-37.8914604187],"type":"Point"}
}