{
  "type": "Feature",
  "properties": {
    "addr:full":"1 Granadilla Rd El Arish QLD 4855",
    "addr:housenumber":"1",
    "addr:postcode":"4855",
    "addr:street":"Granadilla Rd",
    "iso:country":"AU",
    "sg:address":"1 Granadilla Rd",
    "sg:city":"El Arish",
    "sg:classifiers":[
        {
            "category":"Farming",
            "subcategory":"Farm",
            "type":"Manufacturing & Wholesale Goods"
        }
    ],
    "sg:phone":"+61 7 4068 5138",
    "sg:postcode":"4855",
    "sg:province":"QLD",
    "sg:tags":[
        "farmer"
    ],
    "wof:name":"Ben M P & B W",
    "wof:placetype":"venue"
},
  "geometry": {"coordinates":[146.03260803200001,-17.8470840454],"type":"Point"}
}