{
  "type": "Feature",
  "properties": {
    "iso:country":"AU",
    "sg:address":"5 McCoy St",
    "sg:city":"Waikerie",
    "sg:classifiers":[
        {
            "category":"Health Services",
            "subcategory":"Dentist",
            "type":"Services"
        }
    ],
    "sg:phone":"+61 8 8541 3166",
    "sg:postcode":"5330",
    "sg:province":"SA",
    "wof:name":"Harry Michael R Dr",
    "wof:placetype":"venue"
},
  "geometry": {"coordinates":[139.98541259800001,-34.181137085],"type":"Point"}
}