{
  "type": "Feature",
  "properties": {
    "iso:country":"AU",
    "sg:address":"1 Bridge St",
    "sg:city":"Charters Towers",
    "sg:classifiers":[
        {
            "category":"Travel",
            "subcategory":"Hotels & Motels",
            "type":"Entertainment"
        }
    ],
    "sg:phone":"+61 7 4787 3555",
    "sg:postcode":"4820",
    "sg:province":"QLD",
    "wof:name":"Cattleman's Rest Motor Inn",
    "wof:placetype":"venue"
},
  "geometry": {"coordinates":[146.260086,-20.067928],"type":"Point"}
}