{
  "type": "Feature",
  "properties": {
    "iso:country":"AU",
    "sg:address":"73 Moss St",
    "sg:city":"Springwood",
    "sg:classifiers":[
        {
            "category":"Retail",
            "subcategory":"Auto Repair",
            "type":"Services"
        }
    ],
    "sg:phone":"+61 7 3808 9855",
    "sg:postcode":"4127",
    "sg:province":"QLD",
    "sg:tags":[
        "wheel",
        "balancing",
        "alignment"
    ],
    "wof:name":"All About Steering & Suspension",
    "wof:placetype":"venue"
},
  "geometry": {"coordinates":[153.12498474099999,-27.6211853027],"type":"Point"}
}