{
  "type": "Feature",
  "properties": {
    "addr:full":"Suite 1, First Floor, 1396 Pacific Hwy Turramurra NSW 2074",
    "addr:housenumber":"first floor 1396",
    "addr:postcode":"2074",
    "addr:street":"Pacific Hwy",
    "iso:country":"AU",
    "sg:address":"Suite 1, First Floor, 1396 Pacific Hwy",
    "sg:city":"Turramurra",
    "sg:classifiers":[
        {
            "category":"Sports & Exercise",
            "subcategory":"Gym",
            "type":"Entertainment"
        }
    ],
    "sg:phone":"+61 1300 287 837",
    "sg:postcode":"2074",
    "sg:province":"NSW",
    "sg:tags":[
        "health",
        "fitness"
    ],
    "wof:name":"Curves Turramurra",
    "wof:placetype":"venue"
},
  "geometry": {"coordinates":[151.127151489,-33.7334480286],"type":"Point"}
}