{
  "type": "Feature",
  "properties": {
    "addr:full":"Cnr Johnson Rd & Pacific Hwy Tuggerah NSW 2259",
    "addr:postcode":"2259",
    "addr:street":"Cnr Johnson Rd & Pacific Hwy",
    "iso:country":"AU",
    "sg:address":"Cnr Johnson Rd & Pacific Hwy",
    "sg:city":"Tuggerah",
    "sg:classifiers":[
        {
            "category":"Retail",
            "subcategory":"Auto Rental",
            "type":"Services"
        }
    ],
    "sg:phone":"+61 2 4352 2822",
    "sg:postcode":"2259",
    "sg:province":"NSW",
    "sg:tags":[
        "bus",
        "truck"
    ],
    "wof:name":"Wyong Rent-A-Truck",
    "wof:placetype":"venue"
},
  "geometry": {"coordinates":[151.420379639,-33.2943077087],"type":"Point"}
}