{
  "type": "Feature",
  "properties": {
    "addr:full":"PO Box 155 Boonah QLD 4310",
    "addr:postcode":"4310",
    "iso:country":"AU",
    "sg:address":"PO Box 155",
    "sg:city":"Boonah",
    "sg:classifiers":[
        {
            "category":"Shopping",
            "subcategory":"Hobbies, Toys, & Games",
            "type":"Retail Goods"
        }
    ],
    "sg:phone":"+61 7 5463 1516",
    "sg:postcode":"4310",
    "sg:province":"QLD",
    "sg:tags":[
        "stamp"
    ],
    "wof:name":"Sel Pfeffer Boonah Stamp Supplies",
    "wof:placetype":"venue"
},
  "geometry": {"coordinates":[152.68232727,-27.9942798615],"type":"Point"}
}