{
  "type": "Feature",
  "properties": {
    "iso:country":"AU",
    "sg:address":"PO Box 1236",
    "sg:city":"Altona Meadows",
    "sg:classifiers":[
        {
            "category":"Autos & Motor Vehicles",
            "subcategory":"Boat Sales",
            "type":"Retail Goods"
        }
    ],
    "sg:phone":"+61 3 9369 1100",
    "sg:postcode":"3028",
    "sg:province":"VIC",
    "sg:tags":[
        "builder",
        "yacht",
        "repairer"
    ],
    "wof:name":"Aquagatt",
    "wof:placetype":"venue"
},
  "geometry": {"coordinates":[144.777481,-37.872028],"type":"Point"}
}