{
  "type": "Feature",
  "properties": {
    "iso:country":"AU",
    "sg:address":"Lot 10 Dalman St",
    "sg:city":"Forster",
    "sg:classifiers":[
        {
            "category":"Home & Garden",
            "subcategory":"Building Materials",
            "type":"Retail Goods"
        }
    ],
    "sg:phone":"+61 2 6554 9566",
    "sg:postcode":"2428",
    "sg:province":"NSW",
    "sg:tags":[
        "supply"
    ],
    "wof:name":"Ezyrobe",
    "wof:placetype":"venue"
},
  "geometry": {"coordinates":[152.525024,-32.198521],"type":"Point"}
}