{
  "type": "Feature",
  "properties": {
    "addr:full":"197 Patrick St Laidley QLD 4341",
    "addr:housenumber":"197",
    "addr:postcode":"4341",
    "addr:street":"Patrick St",
    "iso:country":"AU",
    "sg:address":"197 Patrick St",
    "sg:city":"Laidley",
    "sg:classifiers":[
        {
            "category":"Retail",
            "subcategory":"Auto Repair",
            "type":"Services"
        }
    ],
    "sg:phone":"+61 7 5465 1377",
    "sg:postcode":"4341",
    "sg:province":"QLD",
    "sg:tags":[
        "beater",
        "painter",
        "panel"
    ],
    "wof:name":"Contract Panel Beating",
    "wof:placetype":"venue"
},
  "geometry": {"coordinates":[152.393844605,-27.6306762695],"type":"Point"}
}