{
  "type": "Feature",
  "properties": {
    "addr:full":"F16 1- 15 Barr St Balmain NSW 2041",
    "addr:housenumber":"f16 1 15",
    "addr:postcode":"2041",
    "addr:street":"Barr St",
    "iso:country":"AU",
    "sg:address":"F16 1- 15 Barr St",
    "sg:city":"Balmain",
    "sg:classifiers":[
        {
            "category":"Shopping",
            "subcategory":"News",
            "type":"Retail Goods"
        }
    ],
    "sg:phone":"+61 2 9555 7477",
    "sg:postcode":"2041",
    "sg:province":"NSW",
    "sg:tags":[
        "magazine",
        "periodical"
    ],
    "wof:name":"Travel Vacations Magazine",
    "wof:placetype":"venue"
},
  "geometry": {"coordinates":[151.175308,-33.857624],"type":"Point"}
}