{
  "type": "Feature",
  "properties": {
    "addr:full":"204 Walkenhorst Rd Tarrington VIC 3301",
    "addr:housenumber":"204",
    "addr:postcode":"3301",
    "addr:street":"Walkenhorst Rd",
    "iso:country":"AU",
    "sg:address":"204 Walkenhorst Rd",
    "sg:city":"Tarrington",
    "sg:classifiers":[
        {
            "category":"Professional",
            "type":"Services"
        }
    ],
    "sg:phone":"+61 3 5572 3955",
    "sg:postcode":"3301",
    "sg:province":"VIC",
    "sg:tags":[
        "overlocking",
        "rug",
        "carpet"
    ],
    "wof:name":"Western District Carpet Overlocking Service",
    "wof:placetype":"venue"
},
  "geometry": {"coordinates":[142.104705811,-37.7646217346],"type":"Point"}
}