{
  "type": "Feature",
  "properties": {
    "iso:country":"AU",
    "sg:address":"38 Adelaide St",
    "sg:city":"Paxton",
    "sg:phone":"+61 2 4990 7576",
    "sg:postcode":"2325",
    "sg:province":"NSW",
    "wof:name":"Coalfields Concrete Tanks",
    "wof:placetype":"venue"
},
  "geometry": {"coordinates":[151.28880310100001,-32.9038734436],"type":"Point"}
}