{
  "type": "Feature",
  "properties": {
    "addr:full":"93 Lockhart St Como WA 6152",
    "addr:housenumber":"93",
    "addr:postcode":"6152",
    "addr:street":"Lockhart St",
    "iso:country":"AU",
    "sg:address":"93 Lockhart St",
    "sg:city":"Como",
    "sg:classifiers":[
        {
            "category":"Retail",
            "subcategory":"Laundry & Dry Cleaning",
            "type":"Services"
        }
    ],
    "sg:phone":"+61 8 9450 4252",
    "sg:postcode":"6152",
    "sg:province":"WA",
    "wof:name":"Como Laundrette",
    "wof:placetype":"venue"
},
  "geometry": {"coordinates":[115.859077,-32.005791],"type":"Point"}
}