{
  "type": "Feature",
  "properties": {
    "addr:full":"24 Kingston Drv Helensvale QLD 4212",
    "addr:housenumber":"24",
    "addr:postcode":"4212",
    "addr:street":"Kingston Drv",
    "iso:country":"AU",
    "sg:address":"24 Kingston Drv",
    "sg:city":"Helensvale",
    "sg:classifiers":[
        {
            "category":"Building & Trades",
            "subcategory":"Construction",
            "type":"Services"
        }
    ],
    "sg:phone":"+61 7 5585 9000",
    "sg:postcode":"4212",
    "sg:province":"QLD",
    "sg:tags":[
        "fencing",
        "contractor"
    ],
    "wof:name":"Advance National Services - Temporary Fencing",
    "wof:placetype":"venue"
},
  "geometry": {"coordinates":[153.33636474599999,-27.9359397888],"type":"Point"}
}