{
  "type": "Feature",
  "properties": {
    "addr:full":"124 Springvale Rd Glen Waverley VIC 3150",
    "addr:housenumber":"124",
    "addr:postcode":"3150",
    "addr:street":"Springvale Rd",
    "iso:country":"AU",
    "sg:address":"124 Springvale Rd",
    "sg:city":"Glen Waverley",
    "sg:classifiers":[
        {
            "category":"Deli",
            "type":"Food & Drink"
        }
    ],
    "sg:phone":"+61 3 9886 5114",
    "sg:postcode":"3150",
    "sg:province":"VIC",
    "sg:tags":[
        "delicatessen"
    ],
    "wof:name":"Kristy's Gourmet Deli",
    "wof:placetype":"venue"
},
  "geometry": {"coordinates":[145.16607665999999,-37.8797035217],"type":"Point"}
}