{
  "type": "Feature",
  "properties": {
    "addr:full":"131- 137 Mica Street Synergy Park Carole Park QLD 4300",
    "addr:housenumber":"137",
    "addr:postcode":"4300",
    "addr:street":"Mica Street",
    "iso:country":"AU",
    "sg:address":"131- 137 Mica Street Synergy Park",
    "sg:city":"Carole Park",
    "sg:classifiers":[
        {
            "category":"Manufacturing",
            "subcategory":"Building Materials",
            "type":"Manufacturing & Wholesale Goods"
        }
    ],
    "sg:phone":"+61 13 73 23",
    "sg:postcode":"4300",
    "sg:province":"QLD",
    "sg:tags":[
        "equipment",
        "handling"
    ],
    "wof:name":"Blackwoods",
    "wof:placetype":"venue"
},
  "geometry": {"coordinates":[152.933197022,-27.621969223],"type":"Point"}
}