{
  "type": "Feature",
  "properties": {
    "addr:full":"PO Box 559 Tom Price WA 6751",
    "addr:postcode":"6751",
    "iso:country":"AU",
    "sg:address":"PO Box 559",
    "sg:city":"Tom Price",
    "sg:classifiers":[
        {
            "category":"Recreation",
            "type":"Entertainment"
        }
    ],
    "sg:phone":"+61 419 961 176",
    "sg:postcode":"6751",
    "sg:province":"WA",
    "sg:tags":[
        "supply",
        "outdoor",
        "adventure",
        "activity"
    ],
    "wof:name":"Red Rock Abseiling Adventures Pty Ltd",
    "wof:placetype":"venue"
},
  "geometry": {"coordinates":[117.784286499,-22.6861400604],"type":"Point"}
}