{
  "type": "Feature",
  "properties": {
    "addr:full":"23 Jeffrey St Leongatha VIC 3953",
    "addr:housenumber":"23",
    "addr:postcode":"3953",
    "addr:street":"Jeffrey St",
    "iso:country":"AU",
    "sg:address":"23 Jeffrey St",
    "sg:city":"Leongatha",
    "sg:classifiers":[
        {
            "category":"Farming",
            "subcategory":"Farm",
            "type":"Manufacturing & Wholesale Goods"
        }
    ],
    "sg:phone":"+61 3 5662 3195",
    "sg:postcode":"3953",
    "sg:province":"VIC",
    "sg:tags":[
        "farmer"
    ],
    "wof:name":"Cathie B E",
    "wof:placetype":"venue"
},
  "geometry": {"coordinates":[145.95196533199999,-38.4774208069],"type":"Point"}
}