{
  "type": "Feature",
  "properties": {
    "iso:country":"AU",
    "sg:address":"Cnr Margate & Park St",
    "sg:city":"Ramsgate",
    "sg:classifiers":[
        {
            "category":"Autos & Motor Vehicles",
            "subcategory":"Automobile Sales",
            "type":"Retail Goods"
        }
    ],
    "sg:phone":"+61 2 9529 9100",
    "sg:postcode":"2217",
    "sg:province":"NSW",
    "sg:tags":[
        "car",
        "used"
    ],
    "wof:name":"Botany Bay Car Sales",
    "wof:placetype":"venue"
},
  "geometry": {"coordinates":[151.13009600000001,-33.97052],"type":"Point"}
}