{
  "type": "Feature",
  "properties": {
    "addr:full":"Shop 4a Edgewater Shopng Cntr Edgewater Drv Edgewater WA 6027",
    "addr:housenumber":"shop 4a",
    "addr:postcode":"6027",
    "addr:street":"Edgewater Shopng Cntr Edgewater Drv",
    "iso:country":"AU",
    "sg:address":"Shop 4a Edgewater Shopng Cntr Edgewater Drv",
    "sg:city":"Edgewater",
    "sg:classifiers":[
        {
            "category":"Personal",
            "subcategory":"Beauty Salon",
            "type":"Services"
        }
    ],
    "sg:phone":"+61 8 9405 2084",
    "sg:postcode":"6027",
    "sg:province":"WA",
    "sg:tags":[
        "hairdresser"
    ],
    "wof:name":"Mark Dunnington Hair Design",
    "wof:placetype":"venue"
},
  "geometry": {"coordinates":[115.789169312,-31.7727813721],"type":"Point"}
}