{
  "type": "Feature",
  "properties": {
    "addr:full":"20 Gorden St Garbutt QLD 4814",
    "addr:postcode":"4814",
    "addr:street":"Gorden St",
    "iso:country":"AU",
    "sg:address":"20 Gorden St",
    "sg:city":"Garbutt",
    "sg:classifiers":[
        {
            "category":"Retail",
            "subcategory":"Auto Repair",
            "type":"Services"
        }
    ],
    "sg:phone":"+61 7 4779 9149",
    "sg:postcode":"4814",
    "sg:province":"QLD",
    "sg:tags":[
        "electrical"
    ],
    "wof:name":"Dewy's Auto Electrics",
    "wof:placetype":"venue"
},
  "geometry": {"coordinates":[146.78054800000001,-19.264898],"type":"Point"}
}