{
  "type": "Feature",
  "properties": {
    "addr:full":"39 Stephen St Albany Creek QLD 4035",
    "addr:housenumber":"39",
    "addr:postcode":"4035",
    "addr:street":"Stephen St",
    "iso:country":"AU",
    "sg:address":"39 Stephen St",
    "sg:city":"Albany Creek",
    "sg:classifiers":[
        {
            "category":"Building & Trades",
            "subcategory":"Equipment Rental",
            "type":"Services"
        }
    ],
    "sg:phone":"+61 7 3264 2543",
    "sg:postcode":"4035",
    "sg:province":"QLD",
    "sg:tags":[
        "demolition",
        "contractor"
    ],
    "wof:name":"Ace Demolishers",
    "wof:placetype":"venue"
},
  "geometry": {"coordinates":[152.972488,-27.343618],"type":"Point"}
}