{
  "type": "Feature",
  "properties": {
    "addr:full":"68 Riverview St Murwillumbah NSW 2484",
    "addr:housenumber":"68",
    "addr:postcode":"2484",
    "addr:street":"Riverview St",
    "iso:country":"AU",
    "sg:address":"68 Riverview St",
    "sg:city":"Murwillumbah",
    "sg:classifiers":[
        {
            "category":"Professional",
            "subcategory":"Business Services",
            "type":"Services"
        }
    ],
    "sg:phone":"+61 2 6672 6627",
    "sg:postcode":"2484",
    "sg:province":"NSW",
    "sg:tags":[
        "drafting"
    ],
    "wof:name":"Ian Webb Building Design",
    "wof:placetype":"venue"
},
  "geometry": {"coordinates":[153.391357422,-28.33244133],"type":"Point"}
}