{
  "type": "Feature",
  "properties": {
    "addr:full":"20 Albert St Preston VIC 3072",
    "addr:housenumber":"20",
    "addr:postcode":"3072",
    "addr:street":"Albert St",
    "iso:country":"AU",
    "sg:address":"20 Albert St",
    "sg:city":"Preston",
    "sg:classifiers":[
        {
            "category":"Building & Trades",
            "subcategory":"Equipment Rental",
            "type":"Services"
        }
    ],
    "sg:phone":"+61 418 531 396",
    "sg:postcode":"3072",
    "sg:province":"VIC",
    "sg:tags":[
        "demolition",
        "contractor"
    ],
    "wof:name":"Damn Serious Demolitions",
    "wof:placetype":"venue"
},
  "geometry": {"coordinates":[145.02122497600001,-37.7517127991],"type":"Point"}
}