{
  "type": "Feature",
  "properties": {
    "addr:full":"9a Spray Ave Mordialloc VIC 3195",
    "addr:housenumber":"9a",
    "addr:postcode":"3195",
    "addr:street":"Spray Ave",
    "iso:country":"AU",
    "sg:address":"9a Spray Ave",
    "sg:city":"Mordialloc",
    "sg:classifiers":[
        {
            "category":"Banks & Credit Unions",
            "subcategory":"Investment Brokerage",
            "type":"Services"
        }
    ],
    "sg:phone":"+61 3 9580 3885",
    "sg:postcode":"3195",
    "sg:province":"VIC",
    "sg:tags":[
        "radiator",
        "motor"
    ],
    "wof:name":"Braeside Radiator Service",
    "wof:placetype":"venue"
},
  "geometry": {"coordinates":[145.10260009800001,-38.0083618164],"type":"Point"}
}