{
  "type": "Feature",
  "properties": {
    "iso:country":"AU",
    "sg:address":"453 Beaudesert Rd",
    "sg:city":"Moorooka",
    "sg:classifiers":[
        {
            "category":"Retail",
            "subcategory":"Auto Rental",
            "type":"Services"
        }
    ],
    "sg:phone":"+61 7 3875 1133",
    "sg:postcode":"4105",
    "sg:province":"QLD",
    "sg:tags":[
        "car",
        "hire",
        "minibus"
    ],
    "wof:name":"Sargent Car Rental",
    "wof:placetype":"venue"
},
  "geometry": {"coordinates":[153.020294189,-27.5439662933],"type":"Point"}
}