{
  "type": "Feature",
  "properties": {
    "iso:country":"AU",
    "sg:address":"25 Bridge St",
    "sg:city":"Benalla",
    "sg:classifiers":[
        {
            "category":"Home & Garden",
            "subcategory":"Household Appliances",
            "type":"Retail Goods"
        }
    ],
    "sg:phone":"+61 3 5762 2920",
    "sg:postcode":"3672",
    "sg:province":"VIC",
    "sg:tags":[
        "equipment",
        "gas"
    ],
    "wof:name":"Benalla Heating and Cooling Centre",
    "wof:placetype":"venue"
},
  "geometry": {"coordinates":[145.983459,-36.551643],"type":"Point"}
}