{
  "type": "Feature",
  "properties": {
    "addr:full":"Suite 1, 242 Mulgrave Rd Cairns QLD 4870",
    "addr:housenumber":"242",
    "addr:postcode":"4870",
    "addr:street":"Mulgrave Rd",
    "iso:country":"AU",
    "sg:address":"Suite 1, 242 Mulgrave Rd",
    "sg:city":"Cairns",
    "sg:classifiers":[
        {
            "category":"Professional",
            "subcategory":"Engineering",
            "type":"Services"
        }
    ],
    "sg:phone":"+61 7 4030 1000",
    "sg:postcode":"4870",
    "sg:province":"QLD",
    "sg:tags":[
        "consulting",
        "engineer"
    ],
    "wof:name":"M G F Consultants (NQ) Pty Ltd",
    "wof:placetype":"venue"
},
  "geometry": {"coordinates":[145.74703979500001,-16.937789917],"type":"Point"}
}