{
  "type": "Feature",
  "properties": {
    "iso:country":"AU",
    "sg:address":"22 Lance St",
    "sg:city":"Sherwood",
    "sg:classifiers":[
        {
            "category":"Professional",
            "subcategory":"Art Services",
            "type":"Services"
        }
    ],
    "sg:phone":"+61 7 3379 2360",
    "sg:postcode":"4075",
    "sg:province":"QLD",
    "sg:tags":[
        "picture",
        "frame",
        "framing"
    ],
    "sg:website":"http://www.artsandframes.com",
    "wof:name":"Malcolm Valmadre",
    "wof:placetype":"venue"
},
  "geometry": {"coordinates":[152.97476196299999,-27.5343399048],"type":"Point"}
}