{
  "type": "Feature",
  "properties": {
    "addr:full":"33 Temple Drv Thomastown VIC 3074",
    "addr:housenumber":"33",
    "addr:postcode":"3074",
    "addr:street":"Temple Drv",
    "iso:country":"AU",
    "sg:address":"33 Temple Drv",
    "sg:city":"Thomastown",
    "sg:classifiers":[
        {
            "category":"Wholesale",
            "subcategory":"Metals & Minerals",
            "type":"Manufacturing & Wholesale Goods"
        }
    ],
    "sg:phone":"+61 3 9466 3333",
    "sg:postcode":"3074",
    "sg:province":"VIC",
    "sg:tags":[
        "steel",
        "stainless",
        "product",
        "equipment"
    ],
    "wof:name":"King Stainless Products",
    "wof:placetype":"venue"
},
  "geometry": {"coordinates":[145.018035889,-37.690738678],"type":"Point"}
}