{
  "type": "Feature",
  "properties": {
    "iso:country":"AU",
    "sg:address":"94 Taren Point Rd",
    "sg:city":"Taren Point",
    "sg:classifiers":[
        {
            "category":"Building & Trades",
            "subcategory":"Construction",
            "type":"Services"
        }
    ],
    "sg:phone":"+61 2 9540 5601",
    "sg:postcode":"2229",
    "sg:province":"NSW",
    "sg:tags":[
        "window",
        "aluminium"
    ],
    "wof:name":"Lynns Building Materials",
    "wof:placetype":"venue"
},
  "geometry": {"coordinates":[151.121368408,-34.0227508545],"type":"Point"}
}