{
  "type": "Feature",
  "properties": {
    "iso:country":"AU",
    "sg:address":"Shop 30 202 Railway Pde",
    "sg:city":"Cabramatta",
    "sg:classifiers":[
        {
            "category":"Shopping",
            "subcategory":"Baby Store",
            "type":"Retail Goods"
        }
    ],
    "sg:phone":"+61 2 9754 2835",
    "sg:postcode":"2166",
    "sg:province":"NSW",
    "sg:tags":[
        "children's",
        "wear"
    ],
    "wof:name":"Kahoa Children Wear",
    "wof:placetype":"venue"
},
  "geometry": {"coordinates":[150.938354492,-33.8950386047],"type":"Point"}
}