{
  "type": "Feature",
  "properties": {
    "iso:country":"AU",
    "sg:address":"Shd2/ 15 Kayleigh Drv",
    "sg:city":"Buderim",
    "sg:classifiers":[
        {
            "category":"Retail",
            "subcategory":"Auto Repair",
            "type":"Services"
        }
    ],
    "sg:phone":"+61 7 5443 2630",
    "sg:postcode":"4556",
    "sg:province":"QLD",
    "sg:tags":[
        "beater",
        "painter",
        "panel"
    ],
    "wof:name":"Marks Customising",
    "wof:placetype":"venue"
},
  "geometry": {"coordinates":[153.08906555199999,-26.6700286865],"type":"Point"}
}