{
  "type": "Feature",
  "properties": {
    "addr:full":"32 Crittenden Rd Findon SA 5023",
    "addr:housenumber":"32",
    "addr:postcode":"5023",
    "addr:street":"Crittenden Rd",
    "iso:country":"AU",
    "sg:address":"32 Crittenden Rd",
    "sg:city":"Findon",
    "sg:classifiers":[
        {
            "category":"Wholesale",
            "subcategory":"Toys & Hobbies",
            "type":"Manufacturing & Wholesale Goods"
        }
    ],
    "sg:phone":"+61 8 8347 7665",
    "sg:postcode":"5023",
    "sg:province":"SA",
    "wof:name":"Ace Club Supplies",
    "wof:placetype":"venue"
},
  "geometry": {"coordinates":[138.54405212399999,-34.9031028748],"type":"Point"}
}