{
  "type": "Feature",
  "properties": {
    "iso:country":"AU",
    "sg:address":"1 Ely St",
    "sg:city":"Wangaratta",
    "sg:classifiers":[
        {
            "category":"Banks & Credit Unions",
            "subcategory":"Financial Services",
            "type":"Services"
        }
    ],
    "sg:phone":"+61 3 5720 0977",
    "sg:postcode":"3677",
    "sg:province":"VIC",
    "sg:tags":[
        "financier"
    ],
    "wof:name":"CBFC Limited",
    "wof:placetype":"venue"
},
  "geometry": {"coordinates":[146.32699585,-36.3576660156],"type":"Point"}
}