{
  "type": "Feature",
  "properties": {
    "addr:full":"Church St Ryde NSW 2112",
    "addr:postcode":"2112",
    "addr:street":"Church St",
    "iso:country":"AU",
    "sg:address":"Church St",
    "sg:city":"Ryde",
    "sg:classifiers":[
        {
            "category":"Building & Trades",
            "subcategory":"Cleaning & Sanitation",
            "type":"Services"
        }
    ],
    "sg:phone":"+61 2 8819 6755",
    "sg:postcode":"2112",
    "sg:province":"NSW",
    "sg:tags":[
        "industrial",
        "commercial",
        "contractor"
    ],
    "wof:name":"Layla Cleaning Services Pty Ltd",
    "wof:placetype":"venue"
},
  "geometry": {"coordinates":[151.10533142099999,-33.8141860962],"type":"Point"}
}