{
  "type": "Feature",
  "properties": {
    "addr:full":"402 Mann St Gosford North NSW 2250",
    "addr:housenumber":"402",
    "addr:postcode":"2250",
    "addr:street":"Mann St",
    "iso:country":"AU",
    "sg:address":"402 Mann St",
    "sg:city":"Gosford North",
    "sg:classifiers":[
        {
            "category":"Health Services",
            "subcategory":"Health Practitioner",
            "type":"Services"
        }
    ],
    "sg:phone":"+61 408 515 210",
    "sg:postcode":"2250",
    "sg:province":"NSW",
    "sg:tags":[
        "acupuncture"
    ],
    "wof:name":"Gabriella Jaro",
    "wof:placetype":"venue"
},
  "geometry": {"coordinates":[151.344406128,-33.4152488708],"type":"Point"}
}