{
  "type": "Feature",
  "properties": {
    "iso:country":"AU",
    "sg:address":"219 President Ave",
    "sg:city":"Miranda",
    "sg:classifiers":[
        {
            "category":"Health Services",
            "subcategory":"Health Practitioner",
            "type":"Services"
        }
    ],
    "sg:phone":"+61 418 972 668",
    "sg:postcode":"2228",
    "sg:province":"NSW",
    "sg:tags":[
        "psychologist"
    ],
    "wof:name":"Martin, Dr Michael",
    "wof:placetype":"venue"
},
  "geometry": {"coordinates":[151.09764099099999,-34.0397415161],"type":"Point"}
}