{
  "type": "Feature",
  "properties": {
    "addr:full":"18 Schwebels La Glenorie NSW 2157",
    "addr:housenumber":"18",
    "addr:postcode":"2157",
    "addr:street":"Schwebels La",
    "iso:country":"AU",
    "sg:address":"18 Schwebels La",
    "sg:city":"Glenorie",
    "sg:classifiers":[
        {
            "category":"Professional",
            "subcategory":"Engineering",
            "type":"Services"
        }
    ],
    "sg:phone":"+61 2 9652 0489",
    "sg:postcode":"2157",
    "sg:province":"NSW",
    "sg:tags":[
        "building",
        "cladding",
        "industrial",
        "commercial"
    ],
    "wof:name":"M. Harvey Cladding Pty Ltd",
    "wof:placetype":"venue"
},
  "geometry": {"coordinates":[151.000076294,-33.5992584229],"type":"Point"}
}