{
  "type": "Feature",
  "properties": {
    "addr:full":"Sh 4, 42 Acre Ave Morphett Vale SA 5162",
    "addr:housenumber":"42",
    "addr:postcode":"5162",
    "addr:street":"Sh 4;Acre Ave",
    "iso:country":"AU",
    "sg:address":"Sh 4, 42 Acre Ave",
    "sg:city":"Morphett Vale",
    "sg:classifiers":[
        {
            "category":"Personal",
            "subcategory":"Beauty Salon",
            "type":"Services"
        }
    ],
    "sg:phone":"+61 8 8382 6033",
    "sg:postcode":"5162",
    "sg:province":"SA",
    "sg:tags":[
        "hairdresser"
    ],
    "wof:name":"Marsel Hair & Beauty",
    "wof:placetype":"venue"
},
  "geometry": {"coordinates":[138.515716553,-35.1129417419],"type":"Point"}
}