{
  "type": "Feature",
  "properties": {
    "addr:full":"11 Beach St Frankston VIC 3199",
    "addr:housenumber":"11",
    "addr:postcode":"3199",
    "addr:street":"Beach St",
    "iso:country":"AU",
    "sg:address":"11 Beach St",
    "sg:city":"Frankston",
    "sg:classifiers":[
        {
            "category":"Building & Trades",
            "subcategory":"Construction",
            "type":"Services"
        }
    ],
    "sg:phone":"+61 3 9783 9166",
    "sg:postcode":"3199",
    "sg:province":"VIC",
    "sg:tags":[
        "contractor"
    ],
    "wof:name":"Highview Homes Pty Ltd",
    "wof:placetype":"venue"
},
  "geometry": {"coordinates":[145.12307739299999,-38.3891830444],"type":"Point"}
}