{
  "type": "Feature",
  "properties": {
    "addr:full":"400 Shute Harbour Rd Airlie Beach QLD 4802",
    "addr:housenumber":"400",
    "addr:postcode":"4802",
    "addr:street":"Shute Harbour Rd",
    "iso:country":"AU",
    "sg:address":"400 Shute Harbour Rd",
    "sg:city":"Airlie Beach",
    "sg:classifiers":[
        {
            "category":"Health Services",
            "subcategory":"Health Practitioner",
            "type":"Services"
        }
    ],
    "sg:phone":"+61 7 4946 6275",
    "sg:postcode":"4802",
    "sg:province":"QLD",
    "sg:tags":[
        "naturopath"
    ],
    "wof:name":"Gillman Catherine",
    "wof:placetype":"venue"
},
  "geometry": {"coordinates":[148.720626831,-20.2697525024],"type":"Point"}
}