{
  "type": "Feature",
  "properties": {
    "iso:country":"AU",
    "sg:address":"40 Watonga St",
    "sg:city":"Port Macquarie",
    "sg:classifiers":[
        {
            "category":"Health Services",
            "subcategory":"Doctor",
            "type":"Services"
        }
    ],
    "sg:phone":"+61 2 6582 0104",
    "sg:postcode":"2444",
    "sg:province":"NSW",
    "sg:tags":[
        "medical",
        "practitioner"
    ],
    "wof:name":"Sen Gupta Dr S P",
    "wof:placetype":"venue"
},
  "geometry": {"coordinates":[152.926056,-31.477446],"type":"Point"}
}