{
  "type": "Feature",
  "properties": {
    "addr:full":"53 Bruce Hwy Edmonton QLD 4869",
    "addr:housenumber":"53",
    "addr:postcode":"4869",
    "addr:street":"Bruce Hwy",
    "iso:country":"AU",
    "sg:address":"53 Bruce Hwy",
    "sg:city":"Edmonton",
    "sg:classifiers":[
        {
            "category":"Sports & Exercise",
            "subcategory":"Gym",
            "type":"Entertainment"
        }
    ],
    "sg:phone":"+61 7 4045 2000",
    "sg:postcode":"4869",
    "sg:province":"QLD",
    "sg:tags":[
        "health",
        "fitness"
    ],
    "wof:name":"Leisurelinks Health & Leisure Centre",
    "wof:placetype":"venue"
},
  "geometry": {"coordinates":[145.74690246599999,-17.0254974365],"type":"Point"}
}