{
  "type": "Feature",
  "properties": {
    "iso:country":"AU",
    "sg:address":"29 Boulder Rd",
    "sg:city":"Kalgoorlie",
    "sg:classifiers":[
        {
            "category":"Manufacturing",
            "subcategory":"Motor Vehicles & Parts",
            "type":"Manufacturing & Wholesale Goods"
        }
    ],
    "sg:phone":"+61 8 9021 1188",
    "sg:postcode":"6430",
    "sg:province":"WA",
    "sg:tags":[
        "replacement"
    ],
    "wof:name":"Coventrys",
    "wof:placetype":"venue"
},
  "geometry": {"coordinates":[121.477783203,-30.7496910095],"type":"Point"}
}