{
  "type": "Feature",
  "properties": {
    "addr:full":"11 Highett St Mansfield VIC 3722",
    "addr:housenumber":"11",
    "addr:postcode":"3722",
    "addr:street":"Highett St",
    "iso:country":"AU",
    "sg:address":"11 Highett St",
    "sg:city":"Mansfield",
    "sg:classifiers":[
        {
            "category":"Retail",
            "subcategory":"Funeral Services",
            "type":"Services"
        }
    ],
    "sg:phone":"+61 3 5775 1066",
    "sg:postcode":"3722",
    "sg:province":"VIC",
    "sg:tags":[
        "director"
    ],
    "wof:name":"M & A McCormack Funerals",
    "wof:placetype":"venue"
},
  "geometry": {"coordinates":[146.08815002399999,-37.0505104065],"type":"Point"}
}