{
  "type": "Feature",
  "properties": {
    "addr:full":"130 Macarthur Rd Camden NSW 2570",
    "addr:housenumber":"130",
    "addr:postcode":"2570",
    "addr:street":"Macarthur Rd",
    "iso:country":"AU",
    "sg:address":"130 Macarthur Rd",
    "sg:city":"Camden",
    "sg:classifiers":[
        {
            "category":"Farming",
            "subcategory":"Berry Farm",
            "type":"Manufacturing & Wholesale Goods"
        }
    ],
    "sg:phone":"+61 2 4658 0888",
    "sg:postcode":"2570",
    "sg:province":"NSW",
    "sg:tags":[
        "fruit",
        "grower"
    ],
    "wof:name":"Carmagnola L",
    "wof:placetype":"venue"
},
  "geometry": {"coordinates":[150.71136474599999,-34.0662460327],"type":"Point"}
}