{
  "type": "Feature",
  "properties": {
    "addr:full":"42 Irwin La Unley SA 5061",
    "addr:housenumber":"42",
    "addr:postcode":"5061",
    "addr:street":"Irwin La",
    "iso:country":"AU",
    "sg:address":"42 Irwin La",
    "sg:city":"Unley",
    "sg:classifiers":[
        {
            "category":"Retail",
            "subcategory":"Auto Repair",
            "type":"Services"
        }
    ],
    "sg:phone":"+61 8 8272 9342",
    "sg:postcode":"5061",
    "sg:province":"SA",
    "sg:tags":[
        "repairer",
        "motor",
        "engineer"
    ],
    "wof:name":"Super Lube",
    "wof:placetype":"venue"
},
  "geometry": {"coordinates":[138.60638427699999,-34.9438514709],"type":"Point"}
}