{
  "type": "Feature",
  "properties": {
    "iso:country":"AU",
    "sg:address":"1951 Albany Hwy",
    "sg:city":"Maddington",
    "sg:classifiers":[
        {
            "category":"Education",
            "subcategory":"School",
            "type":"Public Place"
        }
    ],
    "sg:phone":"+61 8 9459 5910",
    "sg:postcode":"6109",
    "sg:province":"WA",
    "sg:tags":[
        "state",
        "except",
        "nsw"
    ],
    "wof:name":"Maddington Education Support Centre",
    "wof:placetype":"venue"
},
  "geometry": {"coordinates":[115.986793518,-32.0535926819],"type":"Point"}
}