{
  "type": "Feature",
  "properties": {
    "addr:full":"145 Monbulk Seville Rd Silvan VIC 3795",
    "addr:housenumber":"145",
    "addr:postcode":"3795",
    "addr:street":"Monbulk Seville Rd",
    "iso:country":"AU",
    "sg:address":"145 Monbulk Seville Rd",
    "sg:city":"Silvan",
    "sg:classifiers":[
        {
            "category":"Farming",
            "subcategory":"Nursery",
            "type":"Manufacturing & Wholesale Goods"
        }
    ],
    "sg:phone":"+61 3 9737 9407",
    "sg:postcode":"3795",
    "sg:province":"VIC",
    "wof:name":"Evergreen Nursery",
    "wof:placetype":"venue"
},
  "geometry": {"coordinates":[145.43791198700001,-37.8423843384],"type":"Point"}
}