{
  "type": "Feature",
  "properties": {
    "iso:country":"AU",
    "sg:address":"2B/ 30 Orlando St",
    "sg:city":"Coffs Harbour Jetty",
    "sg:classifiers":[
        {
            "category":"Real Estate",
            "subcategory":"Real Estate Agent",
            "type":"Services"
        }
    ],
    "sg:phone":"+61 2 6650 6555",
    "sg:postcode":"2450",
    "sg:province":"NSW",
    "wof:name":"Adams Property Management",
    "wof:placetype":"venue"
},
  "geometry": {"coordinates":[153.137955,-30.300943],"type":"Point"}
}