{
  "type": "Feature",
  "properties": {
    "addr:full":"2B/ 30 Orlando St Coffs Harbour Jetty NSW 2450",
    "addr:housenumber":"2b / 30",
    "addr:postcode":"2450",
    "addr:street":"Orlando St",
    "iso:country":"AU",
    "sg:address":"2B/ 30 Orlando St",
    "sg:city":"Coffs Harbour Jetty",
    "sg:classifiers":[
        {
            "category":"Real Estate",
            "subcategory":"Real Estate Agent",
            "type":"Services"
        }
    ],
    "sg:phone":"+61 2 6650 6555",
    "sg:postcode":"2450",
    "sg:province":"NSW",
    "wof:name":"Adams Property Management",
    "wof:placetype":"venue"
},
  "geometry": {"coordinates":[153.13795500000001,-30.300943],"type":"Point"}
}