{
  "type": "Feature",
  "properties": {
    "addr:full":"Unit 3, 55 Salisbury Rd Hornsby NSW 2077",
    "addr:housenumber":"55",
    "addr:postcode":"2077",
    "addr:street":"Salisbury Rd",
    "iso:country":"AU",
    "sg:address":"Unit 3, 55 Salisbury Rd",
    "sg:city":"Hornsby",
    "sg:classifiers":[
        {
            "category":"Bars & Pubs",
            "subcategory":"Gay Bar",
            "type":"Food & Drink"
        }
    ],
    "sg:phone":"+61 2 9476 3800",
    "sg:postcode":"2077",
    "sg:province":"NSW",
    "sg:tags":[
        "plywood",
        "veneer"
    ],
    "wof:name":"Mister Ply & Wood",
    "wof:placetype":"venue"
},
  "geometry": {"coordinates":[151.109664917,-33.6923751831],"type":"Point"}
}