{
  "type": "Feature",
  "properties": {
    "addr:full":"17 Centennial Ave Chatswood NSW 2057",
    "addr:housenumber":"17",
    "addr:postcode":"2057",
    "addr:street":"Centennial Ave",
    "iso:country":"AU",
    "sg:address":"17 Centennial Ave",
    "sg:city":"Chatswood",
    "sg:classifiers":[
        {
            "category":"Professional",
            "subcategory":"Art Services",
            "type":"Services"
        }
    ],
    "sg:phone":"+61 414 523 893",
    "sg:postcode":"2057",
    "sg:province":"NSW",
    "sg:tags":[
        "graphic",
        "designer"
    ],
    "wof:name":"Blue Desert Design",
    "wof:placetype":"venue"
},
  "geometry": {"coordinates":[151.175354,-33.798672],"type":"Point"}
}