{
  "type": "Feature",
  "properties": {
    "iso:country":"AU",
    "sg:address":"Coben Rd",
    "sg:city":"Terang",
    "sg:classifiers":[
        {
            "category":"Manufacturing",
            "subcategory":"Tools & Machinery",
            "type":"Manufacturing & Wholesale Goods"
        }
    ],
    "sg:phone":"+61 3 5592 2388",
    "sg:postcode":"3264",
    "sg:province":"VIC",
    "sg:tags":[
        "earth",
        "excavating",
        "moving",
        "equipment"
    ],
    "wof:name":"Windmill Ag - Terang",
    "wof:placetype":"venue"
},
  "geometry": {"coordinates":[142.91807556099999,-38.2450561523],"type":"Point"}
}