{
  "type": "Feature",
  "properties": {
    "addr:full":"Unit 3, 4 Bellingham St Narellan NSW 2567",
    "addr:housenumber":"4",
    "addr:postcode":"2567",
    "addr:street":"Bellingham St",
    "iso:country":"AU",
    "sg:address":"Unit 3, 4 Bellingham St",
    "sg:city":"Narellan",
    "sg:classifiers":[
        {
            "category":"Professional",
            "subcategory":"Detective & Security Services",
            "type":"Services"
        }
    ],
    "sg:phone":"+61 2 4647 2105",
    "sg:postcode":"2567",
    "sg:province":"NSW",
    "sg:tags":[
        "equipment",
        "window",
        "doors"
    ],
    "wof:name":"Narellan Blinds & Awnings",
    "wof:placetype":"venue"
},
  "geometry": {"coordinates":[150.73127746599999,-34.0374107361],"type":"Point"}
}