{
  "type": "Feature",
  "properties": {
    "addr:full":"Main St Ardath WA 6419",
    "addr:postcode":"6419",
    "addr:street":"Main St",
    "iso:country":"AU",
    "sg:address":"Main St",
    "sg:city":"Ardath",
    "sg:classifiers":[
        {
            "category":"Farming",
            "subcategory":"Nursery",
            "type":"Manufacturing & Wholesale Goods"
        }
    ],
    "sg:phone":"+61 8 9065 1041",
    "sg:postcode":"6419",
    "sg:province":"WA",
    "wof:name":"Ardath Nursery",
    "wof:placetype":"venue"
},
  "geometry": {"coordinates":[118.100143433,-32.0347709656],"type":"Point"}
}