{
  "type": "Feature",
  "properties": {
    "addr:full":"Thompson Ave George Town TAS 7253",
    "addr:postcode":"7253",
    "addr:street":"Thompson Ave",
    "iso:country":"AU",
    "sg:address":"Thompson Ave",
    "sg:city":"George Town",
    "sg:classifiers":[
        {
            "category":"Professional",
            "subcategory":"Engineering",
            "type":"Services"
        }
    ],
    "sg:phone":"+61 3 6382 3333",
    "sg:postcode":"7253",
    "sg:province":"TAS",
    "sg:tags":[
        "engineer"
    ],
    "wof:name":"CPT Engineering Pty Ltd",
    "wof:placetype":"venue"
},
  "geometry": {"coordinates":[146.83587646500001,-41.112865448],"type":"Point"}
}