{
  "type": "Feature",
  "properties": {
    "addr:full":"46 Scarr St Cloncurry QLD 4824",
    "addr:housenumber":"46",
    "addr:postcode":"4824",
    "addr:street":"Scarr St",
    "iso:country":"AU",
    "sg:address":"46 Scarr St",
    "sg:city":"Cloncurry",
    "sg:classifiers":[
        {
            "category":"Communications",
            "subcategory":"Film & Video Production",
            "type":"Services"
        }
    ],
    "sg:phone":"+61 7 4742 1044",
    "sg:postcode":"4824",
    "sg:province":"QLD",
    "sg:tags":[
        "dvd",
        "library"
    ],
    "wof:name":"Lemmons Video",
    "wof:placetype":"venue"
},
  "geometry": {"coordinates":[140.50552400000001,-20.705727],"type":"Point"}
}