{
  "type": "Feature",
  "properties": {
    "iso:country":"AU",
    "sg:address":"21 Hush Pl",
    "sg:city":"Rochedale South",
    "sg:classifiers":[
        {
            "category":"Home & Garden",
            "subcategory":"Carpets & Floor Coverings",
            "type":"Retail Goods"
        }
    ],
    "sg:phone":"+61 7 3808 3111",
    "sg:postcode":"4123",
    "sg:province":"QLD",
    "sg:tags":[
        "tile",
        "wall",
        "layer"
    ],
    "wof:name":"Best Tiling Qld",
    "wof:placetype":"venue"
},
  "geometry": {"coordinates":[153.14219665499999,-27.6087150574],"type":"Point"}
}