{
  "type": "Feature",
  "properties": {
    "addr:full":"Gasworks La Molong NSW 2866",
    "addr:postcode":"2866",
    "iso:country":"AU",
    "sg:address":"Gasworks La",
    "sg:city":"Molong",
    "sg:classifiers":[
        {
            "category":"Retail",
            "subcategory":"Auto Repair",
            "type":"Services"
        }
    ],
    "sg:phone":"+61 2 6366 8280",
    "sg:postcode":"2866",
    "sg:province":"NSW",
    "sg:tags":[
        "repairer",
        "motor",
        "engineer"
    ],
    "wof:name":"A J V Automotive",
    "wof:placetype":"venue"
},
  "geometry": {"coordinates":[148.871094,-33.092838],"type":"Point"}
}