{
  "type": "Feature",
  "properties": {
    "iso:country":"AU",
    "sg:address":"The Rear 47 Princes Rd West",
    "sg:city":"Auburn",
    "sg:classifiers":[
        {
            "category":"Shopping",
            "subcategory":"Gifts & Souvenirs",
            "type":"Retail Goods"
        }
    ],
    "sg:phone":"+61 2 9645 2938",
    "sg:postcode":"2144",
    "sg:province":"NSW",
    "sg:tags":[
        "shop",
        "supply"
    ],
    "wof:name":"Focused Gift Imports Pty Ltd",
    "wof:placetype":"venue"
},
  "geometry": {"coordinates":[151.018066406,-33.8744430542],"type":"Point"}
}