{
  "type": "Feature",
  "properties": {
    "addr:full":"286 Chatsworth Rd Gympie QLD 4570",
    "addr:housenumber":"286",
    "addr:postcode":"4570",
    "addr:street":"Chatsworth Rd",
    "iso:country":"AU",
    "sg:address":"286 Chatsworth Rd",
    "sg:city":"Gympie",
    "sg:classifiers":[
        {
            "category":"Autos & Motor Vehicles",
            "subcategory":"Automobile Sales",
            "type":"Retail Goods"
        }
    ],
    "sg:phone":"+61 7 5482 8188",
    "sg:postcode":"4570",
    "sg:province":"QLD",
    "sg:tags":[
        "bus",
        "used",
        "truck"
    ],
    "wof:name":"Golden City Trucks",
    "wof:placetype":"venue"
},
  "geometry": {"coordinates":[152.642852783,-26.1706962585],"type":"Point"}
}