{
  "type": "Feature",
  "properties": {
    "addr:full":"251-253 Russell St Melbourne VIC 3000",
    "addr:housenumber":"251-253",
    "addr:postcode":"3000",
    "addr:street":"Russell St",
    "iso:country":"AU",
    "sg:address":"251-253 Russell St",
    "sg:city":"Melbourne",
    "sg:classifiers":[
        {
            "category":"Cafe",
            "type":"Food & Drink"
        }
    ],
    "sg:phone":"+61 3 9639 0666",
    "sg:postcode":"3000",
    "sg:province":"VIC",
    "wof:name":"Hans Brinker",
    "wof:placetype":"venue"
},
  "geometry": {"coordinates":[144.96682739299999,-37.8103713989],"type":"Point"}
}