{
  "type": "Feature",
  "properties": {
    "iso:country":"AU",
    "sg:address":"481 The Entrance Rd",
    "sg:city":"Erina Heights",
    "sg:classifiers":[
        {
            "category":"Home & Garden",
            "subcategory":"Building Materials",
            "type":"Retail Goods"
        }
    ],
    "sg:phone":"+61 2 4365 5507",
    "sg:postcode":"2260",
    "sg:province":"NSW",
    "sg:tags":[
        "retaining",
        "wall"
    ],
    "wof:name":"The House of Paving",
    "wof:placetype":"venue"
},
  "geometry": {"coordinates":[151.411484,-33.425381],"type":"Point"}
}