{
  "type": "Feature",
  "properties": {
    "addr:full":"6 Philp Pl Curtin ACT 2605",
    "addr:housenumber":"6",
    "addr:postcode":"2605",
    "addr:street":"Philp Pl Curtin",
    "iso:country":"AU",
    "sg:address":"6 Philp Pl",
    "sg:city":"Curtin",
    "sg:classifiers":[
        {
            "category":"Health Services",
            "subcategory":"Health Practitioner",
            "type":"Services"
        }
    ],
    "sg:phone":"+61 2 6281 0942",
    "sg:postcode":"2605",
    "sg:province":"ACT",
    "sg:tags":[
        "psychologist"
    ],
    "wof:name":"James Linda",
    "wof:placetype":"venue"
},
  "geometry": {"coordinates":[149.079147339,-35.3248329163],"type":"Point"}
}