{
  "type": "Feature",
  "properties": {
    "addr:full":"120 Yarra St Warrandyte VIC 3113",
    "addr:housenumber":"120",
    "addr:postcode":"3113",
    "addr:street":"Yarra St",
    "iso:country":"AU",
    "sg:address":"120 Yarra St",
    "sg:city":"Warrandyte",
    "sg:classifiers":[
        {
            "category":"Retail",
            "subcategory":"Event Space",
            "type":"Services"
        }
    ],
    "sg:phone":"+61 3 9844 1199",
    "sg:postcode":"3113",
    "sg:province":"VIC",
    "sg:tags":[
        "venue",
        "reception",
        "wedding"
    ],
    "wof:name":"Club Warrandyte",
    "wof:placetype":"venue"
},
  "geometry": {"coordinates":[145.21873474099999,-37.7383308411],"type":"Point"}
}