{
  "type": "Feature",
  "properties": {
    "addr:full":"Suite 3/ 170 Burswood Rd Burswood WA 6100",
    "addr:housenumber":"/ 170",
    "addr:postcode":"6100",
    "addr:street":"Burswood Rd",
    "iso:country":"AU",
    "sg:address":"Suite 3/ 170 Burswood Rd",
    "sg:city":"Burswood",
    "sg:classifiers":[
        {
            "category":"Shopping",
            "subcategory":"Stationery & Office Supplies",
            "type":"Retail Goods"
        }
    ],
    "sg:phone":"+61 8 9362 5977",
    "sg:postcode":"6100",
    "sg:province":"WA",
    "sg:tags":[
        "partition"
    ],
    "wof:name":"Association of Wall & Ceiling Industries of WA Inc",
    "wof:placetype":"venue"
},
  "geometry": {"coordinates":[115.898712158,-31.9643440247],"type":"Point"}
}