{
  "type": "Feature",
  "properties": {
    "addr:full":"20 Watchem Rd Birchip VIC 3483",
    "addr:housenumber":"20",
    "addr:postcode":"3483",
    "addr:street":"Watchem Rd",
    "iso:country":"AU",
    "sg:address":"20 Watchem Rd",
    "sg:city":"Birchip",
    "sg:classifiers":[
        {
            "category":"Building & Trades",
            "subcategory":"Plumbing",
            "type":"Services"
        }
    ],
    "sg:phone":"+61 3 5492 2227",
    "sg:postcode":"3483",
    "sg:province":"VIC",
    "sg:tags":[
        "plumber",
        "gasfitters"
    ],
    "wof:name":"Collins Tony",
    "wof:placetype":"venue"
},
  "geometry": {"coordinates":[142.91653442399999,-35.9840202332],"type":"Point"}
}