{
  "type": "Feature",
  "properties": {
    "iso:country":"AU",
    "sg:address":"Lower Ground Floor 18- 20 Grenfell St",
    "sg:city":"Adelaide",
    "sg:classifiers":[
        {
            "category":"Travel",
            "subcategory":"Travel Agent",
            "type":"Entertainment"
        }
    ],
    "sg:phone":"+61 8 8231 4365",
    "sg:postcode":"5000",
    "sg:province":"SA",
    "sg:tags":[
        "consultant"
    ],
    "wof:name":"Tasmanian Holiday Travel Centre",
    "wof:placetype":"venue"
},
  "geometry": {"coordinates":[138.60049438499999,-34.9241294861],"type":"Point"}
}