{
  "type": "Feature",
  "properties": {
    "addr:full":"2 Sharton Ave Buccan QLD 4207",
    "addr:housenumber":"2",
    "addr:postcode":"4207",
    "addr:street":"Sharton Ave",
    "iso:country":"AU",
    "sg:address":"2 Sharton Ave",
    "sg:city":"Buccan",
    "sg:classifiers":[
        {
            "category":"Utilities",
            "subcategory":"Telephone",
            "type":"Services"
        }
    ],
    "sg:phone":"+61 7 3299 7198",
    "sg:postcode":"4207",
    "sg:province":"QLD",
    "sg:tags":[
        "equipment",
        "system"
    ],
    "wof:name":"Archway Communications",
    "wof:placetype":"venue"
},
  "geometry": {"coordinates":[153.150878906,-27.7368736267],"type":"Point"}
}