{
  "type": "Feature",
  "properties": {
    "iso:country":"AU",
    "sg:address":"Christies Fitness Centre Cnr Adelaide & Wharf Sts",
    "sg:city":"Brisbane",
    "sg:classifiers":[
        {
            "category":"Personal",
            "subcategory":"Massage",
            "type":"Services"
        }
    ],
    "sg:phone":"+61 7 3229 0699",
    "sg:postcode":"4000",
    "sg:province":"QLD",
    "sg:tags":[
        "therapy"
    ],
    "wof:name":"Explore Natural Therapies",
    "wof:placetype":"venue"
},
  "geometry": {"coordinates":[153.02536010700001,-27.4681777954],"type":"Point"}
}