{
  "type": "Feature",
  "properties": {
    "addr:full":"1/ 3 Underwood Ave Botany NSW 2019",
    "addr:housenumber":"/ 3",
    "addr:postcode":"2019",
    "addr:street":"Underwood Ave",
    "iso:country":"AU",
    "sg:address":"1/ 3 Underwood Ave",
    "sg:city":"Botany",
    "sg:classifiers":[
        {
            "category":"Retail",
            "subcategory":"Auto Repair",
            "type":"Services"
        }
    ],
    "sg:phone":"+61 2 9666 5597",
    "sg:postcode":"2019",
    "sg:province":"NSW",
    "sg:tags":[
        "beater",
        "painter",
        "panel"
    ],
    "wof:name":"Underwood Smash NSW Pty Ltd",
    "wof:placetype":"venue"
},
  "geometry": {"coordinates":[151.19471740700001,-33.9445533752],"type":"Point"}
}