{
  "type": "Feature",
  "properties": {
    "iso:country":"AU",
    "sg:address":"52 Playfield St",
    "sg:city":"Chermside Centre",
    "sg:classifiers":[
        {
            "category":"Government",
            "subcategory":"Customs House",
            "type":"Public Place"
        }
    ],
    "sg:phone":"+61 7 3350 6733",
    "sg:postcode":"4032",
    "sg:province":"QLD",
    "sg:tags":[
        "title",
        "management",
        "stratum"
    ],
    "sg:website":"http://www.capitolbca.com.au",
    "wof:name":"Capitol Body Corporate Administration",
    "wof:placetype":"venue"
},
  "geometry": {"coordinates":[153.03436300000001,-27.383678],"type":"Point"}
}