{
  "type": "Feature",
  "properties": {
    "addr:full":"66 Maple St Maleny QLD 4552",
    "addr:housenumber":"66",
    "addr:postcode":"4552",
    "addr:street":"Maple St",
    "iso:country":"AU",
    "sg:address":"66 Maple St",
    "sg:city":"Maleny",
    "sg:classifiers":[
        {
            "category":"Health Services",
            "subcategory":"Doctor",
            "type":"Services"
        }
    ],
    "sg:phone":"+61 7 5494 3999",
    "sg:postcode":"4552",
    "sg:province":"QLD",
    "sg:tags":[
        "medical",
        "practitioner"
    ],
    "wof:name":"Banksia House Medical Centre",
    "wof:placetype":"venue"
},
  "geometry": {"coordinates":[152.84872436500001,-26.7579441071],"type":"Point"}
}