{
  "type": "Feature",
  "properties": {
    "addr:full":"778- 786 Old Illawarra Rd Menai NSW 2234",
    "addr:housenumber":"786",
    "addr:postcode":"2234",
    "addr:street":"Old Illawarra Rd",
    "iso:country":"AU",
    "sg:address":"778- 786 Old Illawarra Rd",
    "sg:city":"Menai",
    "sg:classifiers":[
        {
            "category":"Shopping",
            "subcategory":"Bicycles & Sporting Goods",
            "type":"Retail Goods"
        }
    ],
    "sg:phone":"+61 2 9532 0044",
    "sg:postcode":"2234",
    "sg:province":"NSW",
    "sg:tags":[
        "chemical",
        "equipment",
        "pool",
        "swimming"
    ],
    "wof:name":"PoolWerx",
    "wof:placetype":"venue"
},
  "geometry": {"coordinates":[151.01031494099999,-34.0179786682],"type":"Point"}
}