{
  "type": "Feature",
  "properties": {
    "iso:country":"AU",
    "sg:address":"388 Pacific Hwy",
    "sg:city":"Lane Cove",
    "sg:classifiers":[
        {
            "category":"Shopping",
            "type":"Retail Goods"
        }
    ],
    "sg:phone":"+61 2 9904 0111",
    "sg:postcode":"2066",
    "sg:province":"NSW",
    "sg:tags":[
        "clearance",
        "factory",
        "outlet"
    ],
    "wof:name":"North Shore Factory Clearance",
    "wof:placetype":"venue"
},
  "geometry": {"coordinates":[151.17608642600001,-33.8134498596],"type":"Point"}
}