{
  "type": "Feature",
  "properties": {
    "addr:full":"Shop 21 Gladstone Park Shopping Centre Gladstone Park VIC 3043",
    "addr:housenumber":"shop 21",
    "addr:postcode":"3043",
    "iso:country":"AU",
    "sg:address":"Shop 21 Gladstone Park Shopping Centre",
    "sg:city":"Gladstone Park",
    "sg:classifiers":[
        {
            "category":"Real Estate",
            "subcategory":"Real Estate Agent",
            "type":"Services"
        }
    ],
    "sg:phone":"+61 3 9338 4088",
    "sg:postcode":"3043",
    "sg:province":"VIC",
    "wof:name":"Raine & Horne Gladstone Park",
    "wof:placetype":"venue"
},
  "geometry": {"coordinates":[144.883865356,-37.688999176],"type":"Point"}
}