{
  "type": "Feature",
  "properties": {
    "addr:full":"51 McCallum St Swan Hill NSW 3585",
    "addr:housenumber":"51",
    "addr:postcode":"3585",
    "addr:street":"Mccallum St",
    "iso:country":"AU",
    "sg:address":"51 McCallum St",
    "sg:city":"Swan Hill",
    "sg:classifiers":[
        {
            "category":"Organizations",
            "subcategory":"Non-profit Organization",
            "type":"Services"
        }
    ],
    "sg:phone":"+61 3 5033 1775",
    "sg:postcode":"3585",
    "sg:province":"NSW",
    "sg:tags":[
        "support",
        "disability",
        "organisation"
    ],
    "wof:name":"Interchange Sunraysia Region",
    "wof:placetype":"venue"
},
  "geometry": {"coordinates":[143.55891399999999,-35.338959],"type":"Point"}
}