{
  "type": "Feature",
  "properties": {
    "iso:country":"AU",
    "sg:address":"8 Lynbara Ave",
    "sg:city":"St Ives",
    "sg:classifiers":[
        {
            "category":"Government",
            "subcategory":"Court House",
            "type":"Public Place"
        }
    ],
    "sg:phone":"+61 2 9144 3509",
    "sg:postcode":"2075",
    "sg:province":"NSW",
    "sg:tags":[
        "personal",
        "marriage",
        "family",
        "counselling"
    ],
    "wof:name":"St Ives HolisticTherapy Center",
    "wof:placetype":"venue"
},
  "geometry": {"coordinates":[151.163375855,-33.7316436768],"type":"Point"}
}