{
  "type": "Feature",
  "properties": {
    "addr:full":"57 Coolabah Drv Churchill VIC 3842",
    "addr:housenumber":"57",
    "addr:postcode":"3842",
    "addr:street":"Coolabah Drv",
    "iso:country":"AU",
    "sg:address":"57 Coolabah Drv",
    "sg:city":"Churchill",
    "sg:classifiers":[
        {
            "category":"Building & Trades",
            "subcategory":"Construction",
            "type":"Services"
        }
    ],
    "sg:phone":"+61 3 5122 2350",
    "sg:postcode":"3842",
    "sg:province":"VIC",
    "sg:tags":[
        "contractor"
    ],
    "wof:name":"Misson TR & DR Builders & Renovators",
    "wof:placetype":"venue"
},
  "geometry": {"coordinates":[146.41586303700001,-38.3016166687],"type":"Point"}
}