{
  "type": "Feature",
  "properties": {
    "addr:full":"Shp 2/ 30 Day St Colyton NSW 2760",
    "addr:housenumber":"/ 30",
    "addr:postcode":"2760",
    "addr:street":"Day St",
    "iso:country":"AU",
    "sg:address":"Shp 2/ 30 Day St",
    "sg:city":"Colyton",
    "sg:classifiers":[
        {
            "category":"Fast Food",
            "type":"Food & Drink"
        }
    ],
    "sg:phone":"+61 2 9623 0161",
    "sg:postcode":"2760",
    "sg:province":"NSW",
    "sg:tags":[
        "away",
        "take"
    ],
    "wof:name":"Simos Take Away",
    "wof:placetype":"venue"
},
  "geometry": {"coordinates":[150.789138794,-33.776763916],"type":"Point"}
}