{
  "type": "Feature",
  "properties": {
    "iso:country":"AU",
    "sg:address":"Shp17/ 272 Church St",
    "sg:city":"Parramatta",
    "sg:classifiers":[
        {
            "category":"Shopping",
            "subcategory":"Clothing, Apparel, & Fashions",
            "type":"Retail Goods"
        }
    ],
    "sg:phone":"+61 2 9633 1277",
    "sg:postcode":"2150",
    "sg:province":"NSW",
    "sg:tags":[
        "menswear"
    ],
    "wof:name":"Broadway Design Menswear",
    "wof:placetype":"venue"
},
  "geometry": {"coordinates":[151.18084716800001,-33.894569397],"type":"Point"}
}