{
  "type": "Feature",
  "properties": {
    "iso:country":"AU",
    "sg:address":"69 Payten Ave",
    "sg:city":"Roselands",
    "sg:classifiers":[
        {
            "category":"Organizations",
            "subcategory":"Non-profit Organization",
            "type":"Services"
        }
    ],
    "sg:phone":"+61 2 9750 4466",
    "sg:postcode":"2196",
    "sg:province":"NSW",
    "sg:tags":[
        "support",
        "disability",
        "organisation"
    ],
    "wof:name":"The Northcott Society",
    "wof:placetype":"venue"
},
  "geometry": {"coordinates":[151.066101,-33.933765],"type":"Point"}
}