{
  "type": "Feature",
  "properties": {
    "addr:full":"120 Hoare St Cairns QLD 4870",
    "addr:housenumber":"120",
    "addr:postcode":"4870",
    "addr:street":"Hoare St",
    "iso:country":"AU",
    "sg:address":"120 Hoare St",
    "sg:city":"Cairns",
    "sg:classifiers":[
        {
            "category":"Health Services",
            "subcategory":"Chiropractor",
            "type":"Services"
        }
    ],
    "sg:phone":"+61 7 4032 1218",
    "sg:postcode":"4870",
    "sg:province":"QLD",
    "wof:name":"Leung Sabina",
    "wof:placetype":"venue"
},
  "geometry": {"coordinates":[145.74482727,-16.9230175018],"type":"Point"}
}