{
  "type": "Feature",
  "properties": {
    "iso:country":"AU",
    "sg:address":"39 Bush Inn Rd",
    "sg:city":"Wattle Flat",
    "sg:classifiers":[
        {
            "category":"Building & Trades",
            "subcategory":"Equipment Rental",
            "type":"Services"
        }
    ],
    "sg:phone":"+61 408 715 791",
    "sg:postcode":"3352",
    "sg:province":"VIC",
    "sg:tags":[
        "platform",
        "hire",
        "work",
        "elevating"
    ],
    "wof:name":"Regional Contractors",
    "wof:placetype":"venue"
},
  "geometry": {"coordinates":[143.93742399999999,-37.479378],"type":"Point"}
}