{
  "type": "Feature",
  "properties": {
    "iso:country":"AU",
    "sg:address":"PO Box 1108",
    "sg:city":"Mareeba",
    "sg:classifiers":[
        {
            "category":"Building & Trades",
            "subcategory":"Construction",
            "type":"Services"
        }
    ],
    "sg:phone":"+61 7 4093 2317",
    "sg:postcode":"4880",
    "sg:province":"QLD",
    "sg:tags":[
        "contractor"
    ],
    "wof:name":"Cofordo Constructions",
    "wof:placetype":"venue"
},
  "geometry": {"coordinates":[145.425704956,-17.0136604309],"type":"Point"}
}