{
  "type": "Feature",
  "properties": {
    "addr:full":"Griffin Hangar, Fauntleroy Ave Perth Airport WA 6105",
    "addr:postcode":"6105",
    "addr:street":"Fauntleroy Ave",
    "iso:country":"AU",
    "sg:address":"Griffin Hangar, Fauntleroy Ave",
    "sg:city":"Perth Airport",
    "sg:classifiers":[
        {
            "category":"Airport",
            "subcategory":"General Aviation",
            "type":"Transportation"
        }
    ],
    "sg:phone":"+61 8 9277 9044",
    "sg:postcode":"6105",
    "sg:province":"WA",
    "sg:tags":[
        "helicopter"
    ],
    "wof:name":"Griffin Helicopters",
    "wof:placetype":"venue"
},
  "geometry": {"coordinates":[115.95926666299999,-31.9320011139],"type":"Point"}
}