{
  "type": "Feature",
  "properties": {
    "iso:country":"AU",
    "sg:address":"118 Willoughby Rd",
    "sg:city":"Crows Nest",
    "sg:classifiers":[
        {
            "category":"Retail",
            "subcategory":"Event Space",
            "type":"Services"
        }
    ],
    "sg:phone":"+61 2 9966 5522",
    "sg:postcode":"2065",
    "sg:province":"NSW",
    "sg:tags":[
        "function",
        "organiser"
    ],
    "wof:name":"The Crows Nest Club",
    "wof:placetype":"venue"
},
  "geometry": {"coordinates":[151.20074462900001,-33.8242721558],"type":"Point"}
}