{
  "type": "Feature",
  "properties": {
    "addr:full":"93 Cook St Forestville NSW 2087",
    "addr:housenumber":"93",
    "addr:postcode":"2087",
    "addr:street":"Cook St",
    "iso:country":"AU",
    "sg:address":"93 Cook St",
    "sg:city":"Forestville",
    "sg:classifiers":[
        {
            "category":"Banks & Credit Unions",
            "subcategory":"Financial Services",
            "type":"Services"
        }
    ],
    "sg:phone":"+61 2 9975 6077",
    "sg:postcode":"2087",
    "sg:province":"NSW",
    "sg:tags":[
        "loan",
        "finance",
        "mortgage"
    ],
    "wof:name":"Mortgage Choice - Northern Beaches",
    "wof:placetype":"venue"
},
  "geometry": {"coordinates":[151.219207764,-33.7664642334],"type":"Point"}
}