{
  "type": "Feature",
  "properties": {
    "addr:full":"350 Marmion St Melville WA 6156",
    "addr:housenumber":"350",
    "addr:postcode":"6156",
    "addr:street":"Marmion St",
    "iso:country":"AU",
    "sg:address":"350 Marmion St",
    "sg:city":"Melville",
    "sg:classifiers":[
        {
            "category":"Deli",
            "type":"Food & Drink"
        }
    ],
    "sg:phone":"+61 8 9330 1945",
    "sg:postcode":"6156",
    "sg:province":"WA",
    "sg:tags":[
        "delicatessen"
    ],
    "wof:name":"Redwoods Cafe",
    "wof:placetype":"venue"
},
  "geometry": {"coordinates":[115.800529,-32.043354],"type":"Point"}
}