{
  "type": "Feature",
  "properties": {
    "addr:full":"33 Herbert Pl Smithfield NSW 2164",
    "addr:housenumber":"33",
    "addr:postcode":"2164",
    "addr:street":"Herbert Pl",
    "iso:country":"AU",
    "sg:address":"33 Herbert Pl",
    "sg:city":"Smithfield",
    "sg:classifiers":[
        {
            "category":"Banks & Credit Unions",
            "subcategory":"Investment Brokerage",
            "type":"Services"
        }
    ],
    "sg:phone":"+61 2 9757 4711",
    "sg:postcode":"2164",
    "sg:province":"NSW",
    "sg:tags":[
        "electricity",
        "supplier"
    ],
    "wof:name":"Smithfield Energy Facility",
    "wof:placetype":"venue"
},
  "geometry": {"coordinates":[150.948165894,-33.8483657837],"type":"Point"}
}