{
  "type": "Feature",
  "properties": {
    "addr:full":"Shop 9/ 2 Parkridge Ave Upper Caboolture QLD 4510",
    "addr:housenumber":"shop 9 / 2",
    "addr:postcode":"4510",
    "addr:street":"Parkridge Ave Upper",
    "iso:country":"AU",
    "sg:address":"Shop 9/ 2 Parkridge Ave",
    "sg:city":"Upper Caboolture",
    "sg:classifiers":[
        {
            "category":"Personal",
            "subcategory":"Beauty Salon",
            "type":"Services"
        }
    ],
    "sg:phone":"+61 7 5499 4758",
    "sg:postcode":"4510",
    "sg:province":"QLD",
    "wof:name":"A Touch Of Grace Body Beauty",
    "wof:placetype":"venue"
},
  "geometry": {"coordinates":[152.91751099999999,-27.107172],"type":"Point"}
}