{
  "type": "Feature",
  "properties": {
    "addr:full":"Suite 3/ 10 Wharf Rd Gladesville NSW 2111",
    "addr:housenumber":"10",
    "addr:postcode":"2111",
    "addr:street":"Wharf Rd",
    "iso:country":"AU",
    "sg:address":"Suite 3/ 10 Wharf Rd",
    "sg:city":"Gladesville",
    "sg:classifiers":[
        {
            "category":"Building & Trades",
            "subcategory":"Pest Control",
            "type":"Services"
        }
    ],
    "sg:phone":"+61 2 9879 5500",
    "sg:postcode":"2111",
    "sg:province":"NSW",
    "sg:tags":[
        "equipment",
        "abattoir",
        "machinery"
    ],
    "wof:name":"ProAnd Associates Australia Pty Ltd",
    "wof:placetype":"venue"
},
  "geometry": {"coordinates":[151.12690734899999,-33.834148407],"type":"Point"}
}