{
  "type": "Feature",
  "properties": {
    "addr:full":"510 Sydney Rd Balgowlah NSW 2093",
    "addr:housenumber":"510",
    "addr:postcode":"2093",
    "addr:street":"Sydney Rd",
    "iso:country":"AU",
    "sg:address":"510 Sydney Rd",
    "sg:city":"Balgowlah",
    "sg:classifiers":[
        {
            "category":"Home & Garden",
            "subcategory":"Carpets & Floor Coverings",
            "type":"Retail Goods"
        }
    ],
    "sg:phone":"+61 2 9948 7670",
    "sg:postcode":"2093",
    "sg:province":"NSW",
    "sg:tags":[
        "layer",
        "planner"
    ],
    "wof:name":"Excellent Floor Co The",
    "wof:placetype":"venue"
},
  "geometry": {"coordinates":[151.2550354,-33.7952575684],"type":"Point"}
}