{
  "type": "Feature",
  "properties": {
    "addr:full":"98 Crudge Rd Blacktown NSW 2148",
    "addr:housenumber":"98",
    "addr:postcode":"2148",
    "addr:street":"Crudge Rd",
    "iso:country":"AU",
    "sg:address":"98 Crudge Rd",
    "sg:city":"Blacktown",
    "sg:classifiers":[
        {
            "category":"Building & Trades",
            "subcategory":"Construction",
            "type":"Services"
        }
    ],
    "sg:phone":"+61 2 9622 9505",
    "sg:postcode":"2148",
    "sg:province":"NSW",
    "sg:tags":[
        "roof"
    ],
    "wof:name":"Titan Roofing",
    "wof:placetype":"venue"
},
  "geometry": {"coordinates":[150.89793395999999,-33.7535896301],"type":"Point"}
}