{
  "type": "Feature",
  "properties": {
    "iso:country":"AU",
    "sg:address":"24 Georges Rd",
    "sg:city":"The Patch",
    "sg:classifiers":[
        {
            "category":"Professional",
            "subcategory":"Detective & Security Services",
            "type":"Services"
        }
    ],
    "sg:phone":"+61 3 9756 7600",
    "sg:postcode":"3792",
    "sg:province":"VIC",
    "sg:tags":[
        "domestic",
        "alarm",
        "commercial",
        "burglar"
    ],
    "wof:name":"Australian Electronic Securities Pty Ltd",
    "wof:placetype":"venue"
},
  "geometry": {"coordinates":[145.40013122600001,-37.8860435486],"type":"Point"}
}