{
  "type": "Feature",
  "properties": {
    "addr:full":"1/ 15 Egham Rd Burswood WA 6100",
    "addr:housenumber":"/ 15",
    "addr:postcode":"6100",
    "addr:street":"Egham Rd",
    "iso:country":"AU",
    "sg:address":"1/ 15 Egham Rd",
    "sg:city":"Burswood",
    "sg:classifiers":[
        {
            "category":"Building & Trades",
            "subcategory":"Construction",
            "type":"Services"
        }
    ],
    "sg:phone":"+61 419 240 484",
    "sg:postcode":"6100",
    "sg:province":"WA",
    "sg:tags":[
        "home",
        "air conditioning"
    ],
    "wof:name":"Brett Cross Electrical & Air Conditioning",
    "wof:placetype":"venue"
},
  "geometry": {"coordinates":[115.89901733400001,-31.9662189484],"type":"Point"}
}