{
  "type": "Feature",
  "properties": {
    "addr:full":"38 Burns Bay Rd Lane Cove NSW 2066",
    "addr:housenumber":"38",
    "addr:postcode":"2066",
    "addr:street":"Burns Bay Rd",
    "iso:country":"AU",
    "sg:address":"38 Burns Bay Rd",
    "sg:city":"Lane Cove",
    "sg:classifiers":[
        {
            "category":"Manufacturing",
            "subcategory":"Musical Instruments",
            "type":"Manufacturing & Wholesale Goods"
        }
    ],
    "sg:phone":"+61 2 9428 5929",
    "sg:postcode":"2066",
    "sg:province":"NSW",
    "sg:tags":[
        "repair",
        "maker"
    ],
    "wof:name":"Somerville Robert - Harp Maker",
    "wof:placetype":"venue"
},
  "geometry": {"coordinates":[151.16763305699999,-33.8146476746],"type":"Point"}
}