{
  "type": "Feature",
  "properties": {
    "addr:full":"9/ 386 Scarborough Beach Rd Osborne Park WA 6017",
    "addr:housenumber":"/ 386",
    "addr:postcode":"6017",
    "addr:street":"Scarborough Beach Rd",
    "iso:country":"AU",
    "sg:address":"9/ 386 Scarborough Beach Rd",
    "sg:city":"Osborne Park",
    "sg:classifiers":[
        {
            "category":"Manufacturing",
            "subcategory":"Jewelry",
            "type":"Manufacturing & Wholesale Goods"
        }
    ],
    "sg:phone":"+61 8 9443 8928",
    "sg:postcode":"6017",
    "sg:province":"WA",
    "sg:tags":[
        "mfrg",
        "jeweller"
    ],
    "wof:name":"Vanessa Australia",
    "wof:placetype":"venue"
},
  "geometry": {"coordinates":[115.815788269,-31.9112911224],"type":"Point"}
}