{
  "type": "Feature",
  "properties": {
    "addr:full":"27 Ringwood St Ringwood VIC 3134",
    "addr:housenumber":"27",
    "addr:postcode":"3134",
    "addr:street":"Ringwood St",
    "iso:country":"AU",
    "sg:address":"27 Ringwood St",
    "sg:city":"Ringwood",
    "sg:classifiers":[
        {
            "category":"Personal",
            "type":"Services"
        }
    ],
    "sg:phone":"+61 3 9870 8144",
    "sg:postcode":"3134",
    "sg:province":"VIC",
    "sg:tags":[
        "reducing",
        "treatment",
        "weight"
    ],
    "wof:name":"Jenny Craig Weight Loss Centres Pty Ltd",
    "wof:placetype":"venue"
},
  "geometry": {"coordinates":[145.22718810999999,-37.8148078918],"type":"Point"}
}