{
  "type": "Feature",
  "properties": {
    "addr:full":"PO Box 302 Windsor NSW 2756",
    "addr:postcode":"2756",
    "iso:country":"AU",
    "sg:address":"PO Box 302",
    "sg:city":"Windsor",
    "sg:classifiers":[
        {
            "category":"Home & Garden",
            "subcategory":"Home Furnishings",
            "type":"Retail Goods"
        }
    ],
    "sg:phone":"+61 411 176 633",
    "sg:postcode":"2756",
    "sg:province":"NSW",
    "sg:tags":[
        "storage",
        "rack",
        "wine"
    ],
    "wof:name":"Egan Corporation Pty Ltd",
    "wof:placetype":"venue"
},
  "geometry": {"coordinates":[150.81382751500001,-33.6134490967],"type":"Point"}
}