{
  "type": "Feature",
  "properties": {
    "iso:country":"AU",
    "sg:address":"PO Box 481",
    "sg:city":"Penrith",
    "sg:classifiers":[
        {
            "category":"Shopping",
            "subcategory":"Pets & Pet Supplies",
            "type":"Retail Goods"
        }
    ],
    "sg:phone":"+61 1800 663 664",
    "sg:postcode":"2751",
    "sg:province":"NSW",
    "sg:tags":[
        "food"
    ],
    "wof:name":"Nutrience Super Premium Pet Food",
    "wof:placetype":"venue"
},
  "geometry": {"coordinates":[150.69601440400001,-33.7440681458],"type":"Point"}
}