{
  "type": "Feature",
  "properties": {
    "addr:full":"29 Hainsworth Ave Girrawheen WA 6064",
    "addr:housenumber":"29",
    "addr:postcode":"6064",
    "addr:street":"Hainsworth Ave",
    "iso:country":"AU",
    "sg:address":"29 Hainsworth Ave",
    "sg:city":"Girrawheen",
    "sg:classifiers":[
        {
            "category":"Social Services",
            "subcategory":"Child Care",
            "type":"Services"
        }
    ],
    "sg:phone":"+61 8 9342 4146",
    "sg:postcode":"6064",
    "sg:province":"WA",
    "wof:name":"Child Health Services",
    "wof:placetype":"venue"
},
  "geometry": {"coordinates":[115.848808289,-31.8460884094],"type":"Point"}
}