{
  "type": "Feature",
  "properties": {
    "addr:full":"PO Box 350 Leeton NSW 2705",
    "addr:postcode":"2705",
    "iso:country":"AU",
    "sg:address":"PO Box 350",
    "sg:city":"Leeton",
    "sg:classifiers":[
        {
            "category":"Building & Trades",
            "subcategory":"Construction",
            "type":"Services"
        }
    ],
    "sg:phone":"+61 2 6953 4565",
    "sg:postcode":"2705",
    "sg:province":"NSW",
    "sg:tags":[
        "contractor"
    ],
    "wof:name":"Thompson P & L",
    "wof:placetype":"venue"
},
  "geometry": {"coordinates":[146.40620422399999,-34.5520401001],"type":"Point"}
}