{
  "type": "Feature",
  "properties": {
    "addr:full":"5 Sayer St Midland WA 6056",
    "addr:housenumber":"5",
    "addr:postcode":"6056",
    "addr:street":"Sayer St",
    "iso:country":"AU",
    "sg:address":"5 Sayer St",
    "sg:city":"Midland",
    "sg:classifiers":[
        {
            "category":"Professional",
            "subcategory":"Accounting & Tax Preparation",
            "type":"Services"
        }
    ],
    "sg:phone":"+61 8 9274 6944",
    "sg:postcode":"6056",
    "sg:province":"WA",
    "sg:tags":[
        "consultant",
        "taxation"
    ],
    "wof:name":"L.P.R. Taylor & Associates Pty Ltd",
    "wof:placetype":"venue"
},
  "geometry": {"coordinates":[116.00981903100001,-31.8928604126],"type":"Point"}
}