{
  "type": "Feature",
  "properties": {
    "iso:country":"AU",
    "sg:address":"214 Oxford St",
    "sg:city":"Paddington",
    "sg:classifiers":[
        {
            "category":"Shopping",
            "subcategory":"Bridal",
            "type":"Retail Goods"
        }
    ],
    "sg:phone":"+61 2 9331 5118",
    "sg:postcode":"2021",
    "sg:province":"NSW",
    "sg:tags":[
        "hire",
        "wear"
    ],
    "wof:name":"Nelder Jones",
    "wof:placetype":"venue"
},
  "geometry": {"coordinates":[151.22532653799999,-33.8847694397],"type":"Point"}
}