{
  "type": "Feature",
  "properties": {
    "iso:country":"AU",
    "sg:address":"10/ 17-19 Knox St",
    "sg:city":"Double Bay",
    "sg:classifiers":[
        {
            "category":"Shopping",
            "subcategory":"Stationery & Office Supplies",
            "type":"Retail Goods"
        }
    ],
    "sg:phone":"+61 2 9362 1332",
    "sg:postcode":"2028",
    "sg:province":"NSW",
    "sg:tags":[
        "equipment",
        "display",
        "exhibition"
    ],
    "wof:name":"Christmas Company Pty Ltd The",
    "wof:placetype":"venue"
},
  "geometry": {"coordinates":[151.245162964,-33.876991272],"type":"Point"}
}