{
  "type": "Feature",
  "properties": {
    "iso:country":"AU",
    "sg:address":"227 Cambridge St",
    "sg:city":"Subiaco",
    "sg:classifiers":[
        {
            "category":"Travel",
            "subcategory":"Hotels & Motels",
            "type":"Entertainment"
        }
    ],
    "sg:phone":"+61 8 9382 4299",
    "sg:postcode":"6008",
    "sg:province":"WA",
    "sg:website":"http://www.cambridgeatrium.com.au",
    "wof:name":"Cambridge Atrium",
    "wof:placetype":"venue"
},
  "geometry": {"coordinates":[115.81640625,-31.9526691437],"type":"Point"}
}