{
  "type": "Feature",
  "properties": {
    "addr:full":"97 Coulson St Wacol QLD 4076",
    "addr:housenumber":"97",
    "addr:postcode":"4076",
    "addr:street":"Coulson St",
    "iso:country":"AU",
    "sg:address":"97 Coulson St",
    "sg:city":"Wacol",
    "sg:classifiers":[
        {
            "category":"Home & Garden",
            "subcategory":"Kitchen Supply",
            "type":"Retail Goods"
        }
    ],
    "sg:phone":"+61 7 3271 9133",
    "sg:postcode":"4076",
    "sg:province":"QLD",
    "sg:tags":[
        "traffic",
        "equipment",
        "safety",
        "road"
    ],
    "wof:name":"Australian Construction Products",
    "wof:placetype":"venue"
},
  "geometry": {"coordinates":[152.93836975100001,-27.6010875702],"type":"Point"}
}