{
  "type": "Feature",
  "properties": {
    "addr:full":"155/ 159 William St East Sydney NSW 2010",
    "addr:housenumber":"155 / 159",
    "addr:postcode":"2010",
    "addr:street":"William St East",
    "iso:country":"AU",
    "sg:address":"155/ 159 William St",
    "sg:city":"East Sydney",
    "sg:classifiers":[
        {
            "category":"Retail",
            "subcategory":"Auto Rental",
            "type":"Services"
        }
    ],
    "sg:phone":"+61 2 9360 0111",
    "sg:postcode":"2010",
    "sg:province":"NSW",
    "sg:tags":[
        "car",
        "hire",
        "minibus"
    ],
    "wof:name":"Courtesy Cars Australia",
    "wof:placetype":"venue"
},
  "geometry": {"coordinates":[151.218826294,-33.8749046326],"type":"Point"}
}