{
  "type": "Feature",
  "properties": {
    "addr:full":"Cnr Stewart & Keppel Sts Bathurst NSW 2795",
    "addr:postcode":"2795",
    "addr:street":"Cnr",
    "iso:country":"AU",
    "sg:address":"Cnr Stewart & Keppel Sts",
    "sg:city":"Bathurst",
    "sg:phone":"+61 2 6332 5616",
    "sg:postcode":"2795",
    "sg:province":"NSW",
    "wof:name":"Bathurst Tinting",
    "wof:placetype":"venue"
},
  "geometry": {"coordinates":[149.58261108400001,-33.4250221252],"type":"Point"}
}