{
  "type": "Feature",
  "properties": {
    "iso:country":"AU",
    "sg:address":"PO Box 7",
    "sg:city":"Pymble",
    "sg:classifiers":[
        {
            "category":"Utilities",
            "subcategory":"Electric",
            "type":"Services"
        }
    ],
    "sg:phone":"+61 500 875 483",
    "sg:postcode":"2073",
    "sg:province":"NSW",
    "sg:tags":[
        "electrical",
        "contractor"
    ],
    "wof:name":"Across The Board Electrical Services",
    "wof:placetype":"venue"
},
  "geometry": {"coordinates":[151.13749694800001,-33.7405281067],"type":"Point"}
}