{
  "type": "Feature",
  "properties": {
    "addr:full":"Unit 5, 81 Blackwall Rd Woy Woy NSW 2256",
    "addr:housenumber":"81",
    "addr:postcode":"2256",
    "addr:street":"Blackwall Rd",
    "iso:country":"AU",
    "sg:address":"Unit 5, 81 Blackwall Rd",
    "sg:city":"Woy Woy",
    "sg:classifiers":[
        {
            "category":"Health Services",
            "subcategory":"Doctor",
            "type":"Services"
        }
    ],
    "sg:phone":"+61 2 4341 3073",
    "sg:postcode":"2256",
    "sg:province":"NSW",
    "sg:tags":[
        "medical",
        "practitioner"
    ],
    "wof:name":"Kam Simon",
    "wof:placetype":"venue"
},
  "geometry": {"coordinates":[151.32536315900001,-33.4874534607],"type":"Point"}
}