{
  "type": "Feature",
  "properties": {
    "addr:full":"14 Nerine St Miami WA 6210",
    "addr:housenumber":"14",
    "addr:postcode":"6210",
    "addr:street":"Nerine St",
    "iso:country":"AU",
    "sg:address":"14 Nerine St",
    "sg:city":"Miami",
    "sg:classifiers":[
        {
            "category":"Utilities",
            "subcategory":"Electric",
            "type":"Services"
        }
    ],
    "sg:phone":"+61 8 9534 2016",
    "sg:postcode":"6210",
    "sg:province":"WA",
    "sg:tags":[
        "electrical",
        "contractor"
    ],
    "wof:name":"Vaux R M",
    "wof:placetype":"venue"
},
  "geometry": {"coordinates":[115.672096,-32.56889],"type":"Point"}
}