{
  "type": "Feature",
  "properties": {
    "addr:full":"5 Goodwin St Richmond VIC 3121",
    "addr:housenumber":"5",
    "addr:postcode":"3121",
    "addr:street":"Goodwin St",
    "iso:country":"AU",
    "sg:address":"5 Goodwin St",
    "sg:city":"Richmond",
    "sg:classifiers":[
        {
            "category":"Professional",
            "subcategory":"Art Services",
            "type":"Services"
        }
    ],
    "sg:phone":"+61 3 9428 6265",
    "sg:postcode":"3121",
    "sg:province":"VIC",
    "sg:tags":[
        "interior",
        "designer"
    ],
    "wof:name":"Liberati Colour",
    "wof:placetype":"venue"
},
  "geometry": {"coordinates":[144.999465942,-37.828956604],"type":"Point"}
}