{
  "type": "Feature",
  "properties": {
    "addr:full":"Level 6, 220 Pacific Hwy Crows Nest NSW 2065",
    "addr:housenumber":"220",
    "addr:postcode":"2065",
    "addr:street":"Pacific Hwy",
    "iso:country":"AU",
    "sg:address":"Level 6, 220 Pacific Hwy",
    "sg:city":"Crows Nest",
    "sg:classifiers":[
        {
            "category":"Health Services",
            "subcategory":"Dentist",
            "type":"Services"
        }
    ],
    "sg:phone":"+61 2 9954 1051",
    "sg:postcode":"2065",
    "sg:province":"NSW",
    "wof:name":"Galea Timothy",
    "wof:placetype":"venue"
},
  "geometry": {"coordinates":[151.198928833,-33.8255310059],"type":"Point"}
}