{
  "type": "Feature",
  "properties": {
    "addr:full":"PO Box 881 Armidale NSW 2350",
    "addr:postcode":"2350",
    "iso:country":"AU",
    "sg:address":"PO Box 881",
    "sg:city":"Armidale",
    "sg:classifiers":[
        {
            "category":"Building & Trades",
            "subcategory":"Landscaping Services",
            "type":"Services"
        }
    ],
    "sg:phone":"+61 2 6770 3602",
    "sg:postcode":"2350",
    "sg:province":"NSW",
    "sg:tags":[
        "control",
        "weed"
    ],
    "wof:name":"New England Weeds Authority",
    "wof:placetype":"venue"
},
  "geometry": {"coordinates":[151.74203491200001,-30.6037902832],"type":"Point"}
}