{
  "type": "Feature",
  "properties": {
    "addr:full":"12 Bimberi Crs Palmerston ACT 2913",
    "addr:housenumber":"12",
    "addr:postcode":"2913",
    "addr:street":"Bimberi Crs",
    "iso:country":"AU",
    "sg:address":"12 Bimberi Crs",
    "sg:city":"Palmerston",
    "sg:classifiers":[
        {
            "category":"Professional",
            "subcategory":"Computer Services",
            "type":"Services"
        }
    ],
    "sg:phone":"+61 413 308 003",
    "sg:postcode":"2913",
    "sg:province":"ACT",
    "sg:tags":[
        "package",
        "software"
    ],
    "wof:name":"Creative Business Solutions Pty Ltd",
    "wof:placetype":"venue"
},
  "geometry": {"coordinates":[149.11895751899999,-35.1977005005],"type":"Point"}
}