{
  "type": "Feature",
  "properties": {
    "addr:full":"Lot 1034 Warrahdale Tce Landsdale WA 6065",
    "addr:housenumber":"1034",
    "addr:postcode":"6065",
    "addr:street":"Warrahdale Tce",
    "iso:country":"AU",
    "sg:address":"Lot 1034",
    "sg:city":"Warrahdale Tce Landsdale",
    "sg:classifiers":[
        {
            "category":"Building & Trades",
            "subcategory":"Construction",
            "type":"Services"
        }
    ],
    "sg:phone":"+61 8 9302 4680",
    "sg:postcode":"6065",
    "sg:province":"WA",
    "sg:tags":[
        "contractor"
    ],
    "wof:name":"Ventura Homes Pty Ltd",
    "wof:placetype":"venue"
},
  "geometry": {"coordinates":[115.786186218,-31.7843513489],"type":"Point"}
}