{
  "type": "Feature",
  "properties": {
    "addr:full":"1st Flr, 69 Liverpool St Hobart TAS 7000",
    "addr:housenumber":"69",
    "addr:postcode":"7000",
    "addr:street":"Liverpool St",
    "iso:country":"AU",
    "sg:address":"1st Flr, 69 Liverpool St",
    "sg:city":"Hobart",
    "sg:classifiers":[
        {
            "category":"Sports & Exercise",
            "subcategory":"Gym",
            "type":"Entertainment"
        }
    ],
    "sg:phone":"+61 3 6231 3377",
    "sg:postcode":"7000",
    "sg:province":"TAS",
    "sg:tags":[
        "health",
        "fitness"
    ],
    "wof:name":"Sanctuary Health & Fitness Club",
    "wof:placetype":"venue"
},
  "geometry": {"coordinates":[147.327636719,-42.8806495667],"type":"Point"}
}