{
  "type": "Feature",
  "properties": {
    "addr:full":"151 East Derwent Hwy Lindisfarne TAS 7015",
    "addr:housenumber":"151",
    "addr:postcode":"7015",
    "addr:street":"East Derwent Hwy",
    "iso:country":"AU",
    "sg:address":"151 East Derwent Hwy",
    "sg:city":"Lindisfarne",
    "sg:classifiers":[
        {
            "category":"Retail",
            "subcategory":"Auto Repair",
            "type":"Services"
        }
    ],
    "sg:phone":"+61 3 6243 5990",
    "sg:postcode":"7015",
    "sg:province":"TAS",
    "sg:tags":[
        "electrical"
    ],
    "wof:name":"Lindisfarne Service Centre",
    "wof:placetype":"venue"
},
  "geometry": {"coordinates":[147.362518311,-42.848033905],"type":"Point"}
}