{
  "type": "Feature",
  "properties": {
    "addr:full":"75 Princes Hwy Unanderra NSW 2526",
    "addr:housenumber":"75",
    "addr:postcode":"2526",
    "addr:street":"Princes Hwy",
    "iso:country":"AU",
    "sg:address":"75 Princes Hwy",
    "sg:city":"Unanderra",
    "sg:classifiers":[
        {
            "category":"Industrial Area",
            "type":"Public Place"
        }
    ],
    "sg:phone":"+61 2 4271 4466",
    "sg:postcode":"2526",
    "sg:province":"NSW",
    "sg:tags":[
        "rural",
        "shed"
    ],
    "wof:name":"Total Span",
    "wof:placetype":"venue"
},
  "geometry": {"coordinates":[150.84677124000001,-34.4528884888],"type":"Point"}
}