{
  "type": "Feature",
  "properties": {
    "addr:full":"1/ 13 Nelson Rd Cardiff NSW 2285",
    "addr:housenumber":"/ 13",
    "addr:postcode":"2285",
    "addr:street":"Nelson Rd",
    "iso:country":"AU",
    "sg:address":"1/ 13 Nelson Rd",
    "sg:city":"Cardiff",
    "sg:classifiers":[
        {
            "category":"Manufacturing",
            "subcategory":"Metals",
            "type":"Manufacturing & Wholesale Goods"
        }
    ],
    "sg:phone":"+61 2 4904 6855",
    "sg:postcode":"2285",
    "sg:province":"NSW",
    "sg:tags":[
        "steel",
        "fabricator",
        "mfrs"
    ],
    "wof:name":"Newcastle Field Maintenance Pty Ltd",
    "wof:placetype":"venue"
},
  "geometry": {"coordinates":[151.65032959000001,-32.9404296875],"type":"Point"}
}