{
  "type": "Feature",
  "properties": {
    "iso:country":"AU",
    "sg:address":"10 Canley Vale Rd",
    "sg:city":"Canley Vale",
    "sg:classifiers":[
        {
            "category":"Building & Trades",
            "subcategory":"Construction",
            "type":"Services"
        }
    ],
    "sg:phone":"+61 2 9724 1807",
    "sg:postcode":"2166",
    "sg:province":"NSW",
    "sg:tags":[
        "contractor"
    ],
    "wof:name":"Do Thanh Construction",
    "wof:placetype":"venue"
},
  "geometry": {"coordinates":[150.943084717,-33.8872642517],"type":"Point"}
}