{
  "type": "Feature",
  "properties": {
    "addr:full":"11 Arvenis Crs Balgownie NSW 2519",
    "addr:housenumber":"11",
    "addr:postcode":"2519",
    "addr:street":"Arvenis Crs",
    "iso:country":"AU",
    "sg:address":"11 Arvenis Crs",
    "sg:city":"Balgownie",
    "sg:classifiers":[
        {
            "category":"Building & Trades",
            "subcategory":"Construction",
            "type":"Services"
        }
    ],
    "sg:phone":"+61 2 4284 9932",
    "sg:postcode":"2519",
    "sg:province":"NSW",
    "sg:tags":[
        "renovation",
        "alterations",
        "extension",
        "contractor"
    ],
    "wof:name":"Lukin M",
    "wof:placetype":"venue"
},
  "geometry": {"coordinates":[150.87814299999999,-34.388649],"type":"Point"}
}