{
  "type": "Feature",
  "properties": {
    "addr:full":"120a Elizabeth St Hobart TAS 7000",
    "addr:housenumber":"120a",
    "addr:postcode":"7000",
    "addr:street":"Elizabeth St",
    "iso:country":"AU",
    "sg:address":"120a Elizabeth St",
    "sg:city":"Hobart",
    "sg:classifiers":[
        {
            "category":"Personal",
            "subcategory":"Piercing",
            "type":"Services"
        }
    ],
    "sg:phone":"+61 3 6234 9003",
    "sg:postcode":"7000",
    "sg:province":"TAS",
    "sg:tags":[
        "body",
        "ear"
    ],
    "wof:name":"Body Piercing By Jeanette",
    "wof:placetype":"venue"
},
  "geometry": {"coordinates":[147.324676514,-42.8801879883],"type":"Point"}
}