{
  "type": "Feature",
  "properties": {
    "addr:full":"108 Country Club Drv Batemans Bay NSW 2536",
    "addr:housenumber":"108",
    "addr:postcode":"2536",
    "addr:street":"Country Club Drv",
    "iso:country":"AU",
    "sg:address":"108 Country Club Drv",
    "sg:city":"Batemans Bay",
    "sg:classifiers":[
        {
            "category":"Retail",
            "subcategory":"Auto Repair",
            "type":"Services"
        }
    ],
    "sg:phone":"+61 402 855 685",
    "sg:postcode":"2536",
    "sg:province":"NSW",
    "sg:tags":[
        "camper-trailers",
        "caravan",
        "servicing"
    ],
    "wof:name":"Bob's Caravan Repairs",
    "wof:placetype":"venue"
},
  "geometry": {"coordinates":[150.182662964,-35.7284660339],"type":"Point"}
}