{
  "type": "Feature",
  "properties": {
    "addr:full":"Unit 5 106 Dalrymple Service Rd Currajong QLD 4812",
    "addr:housenumber":"106",
    "addr:postcode":"4812",
    "addr:street":"Dalrymple Service Rd",
    "iso:country":"AU",
    "sg:address":"Unit 5 106 Dalrymple Service Rd",
    "sg:city":"Currajong",
    "sg:classifiers":[
        {
            "category":"Organizations",
            "subcategory":"Membership Organization",
            "type":"Services"
        }
    ],
    "sg:phone":"+61 7 4725 8868",
    "sg:postcode":"4812",
    "sg:province":"QLD",
    "sg:tags":[
        "support",
        "health",
        "organisation"
    ],
    "wof:name":"North Queensland Rural Division of General Practice Inc",
    "wof:placetype":"venue"
},
  "geometry": {"coordinates":[146.774765,-19.271908],"type":"Point"}
}