{
  "type": "Feature",
  "properties": {
    "addr:full":"113 Kendal St Cowra NSW 2794",
    "addr:housenumber":"113",
    "addr:postcode":"2794",
    "addr:street":"Kendal St",
    "iso:country":"AU",
    "sg:address":"113 Kendal St",
    "sg:city":"Cowra",
    "sg:classifiers":[
        {
            "category":"Personal",
            "subcategory":"Beauty Salon",
            "type":"Services"
        }
    ],
    "sg:phone":"+61 2 6341 1166",
    "sg:postcode":"2794",
    "sg:province":"NSW",
    "sg:tags":[
        "supply",
        "artist",
        "make-up"
    ],
    "wof:name":"Ambiance Hair",
    "wof:placetype":"venue"
},
  "geometry": {"coordinates":[148.69776916500001,-33.8355636597],"type":"Point"}
}