{
  "type": "Feature",
  "properties": {
    "addr:full":"8 Lyall St South Perth WA 6151",
    "addr:housenumber":"8",
    "addr:postcode":"6151",
    "addr:street":"Lyall St South",
    "iso:country":"AU",
    "sg:address":"8 Lyall St",
    "sg:city":"South Perth",
    "sg:classifiers":[
        {
            "category":"Health Services",
            "subcategory":"Health Practitioner",
            "type":"Services"
        }
    ],
    "sg:phone":"+61 8 9474 4567",
    "sg:postcode":"6151",
    "sg:province":"WA",
    "sg:tags":[
        "naturopath"
    ],
    "wof:name":"South Perth Naturopathic & Herbal Clinic",
    "wof:placetype":"venue"
},
  "geometry": {"coordinates":[115.849411,-31.975151],"type":"Point"}
}