{
  "type": "Feature",
  "properties": {
    "addr:full":"U5b/ 9 Pittwin Rd Capalaba QLD 4157",
    "addr:postcode":"4157",
    "addr:street":"Pittwin Rd",
    "iso:country":"AU",
    "sg:address":"U5b/ 9 Pittwin Rd",
    "sg:city":"Capalaba",
    "sg:classifiers":[
        {
            "category":"Shopping",
            "subcategory":"Mobile Phones",
            "type":"Retail Goods"
        }
    ],
    "sg:phone":"+61 7 3823 3223",
    "sg:postcode":"4157",
    "sg:province":"QLD",
    "sg:tags":[
        "telephone",
        "accessory"
    ],
    "wof:name":"Virtual Mobile Store",
    "wof:placetype":"venue"
},
  "geometry": {"coordinates":[153.18812560999999,-27.5231952667],"type":"Point"}
}