{
  "type": "Feature",
  "properties": {
    "iso:country":"AU",
    "sg:address":"Lvl 4, Shop 509 Castle Towers Shopping Centre",
    "sg:city":"Castle Hill",
    "sg:classifiers":[
        {
            "category":"Shopping",
            "subcategory":"Clothing, Apparel, & Fashions",
            "type":"Retail Goods"
        }
    ],
    "sg:phone":"+61 2 9659 5317",
    "sg:postcode":"2154",
    "sg:province":"NSW",
    "sg:tags":[
        "lady",
        "wear"
    ],
    "wof:name":"Sportscraft Australia",
    "wof:placetype":"venue"
},
  "geometry": {"coordinates":[151.003814697,-33.7317695618],"type":"Point"}
}