{
  "type": "Feature",
  "properties": {
    "addr:full":"1375 Canterbury Rd Punchbowl NSW 2196",
    "addr:housenumber":"1375",
    "addr:postcode":"2196",
    "addr:street":"Canterbury Rd",
    "iso:country":"AU",
    "sg:address":"1375 Canterbury Rd",
    "sg:city":"Punchbowl",
    "sg:classifiers":[
        {
            "category":"Retail",
            "subcategory":"Repair Shop",
            "type":"Services"
        }
    ],
    "sg:phone":"+61 2 9790 8172",
    "sg:postcode":"2196",
    "sg:province":"NSW",
    "sg:tags":[
        "cleaner",
        "part",
        "vacuum"
    ],
    "wof:name":"Godfreys",
    "wof:placetype":"venue"
},
  "geometry": {"coordinates":[151.05342099999999,-33.931843],"type":"Point"}
}