{
  "type": "Feature",
  "properties": {
    "addr:full":"Raymont Drv Glenore Grove QLD 4342",
    "addr:postcode":"4342",
    "addr:street":"Raymont Drv",
    "iso:country":"AU",
    "sg:address":"Raymont Drv",
    "sg:city":"Glenore Grove",
    "sg:classifiers":[
        {
            "category":"Retail",
            "subcategory":"Storage",
            "type":"Services"
        }
    ],
    "sg:phone":"+61 7 5466 5855",
    "sg:postcode":"4342",
    "sg:province":"QLD",
    "sg:tags":[
        "removal",
        "furniture"
    ],
    "wof:name":"Ozkwik Removals",
    "wof:placetype":"venue"
},
  "geometry": {"coordinates":[152.391525269,-27.553440094],"type":"Point"}
}