{
  "type": "Feature",
  "properties": {
    "addr:full":"82- 84 Kent Rd North Ryde NSW 2113",
    "addr:housenumber":"84",
    "addr:postcode":"2113",
    "addr:street":"Kent Rd",
    "iso:country":"AU",
    "sg:address":"82- 84 Kent Rd",
    "sg:city":"North Ryde",
    "sg:classifiers":[
        {
            "category":"Government",
            "subcategory":"Court House",
            "type":"Public Place"
        }
    ],
    "sg:phone":"+61 413 416 392",
    "sg:postcode":"2113",
    "sg:province":"NSW",
    "sg:tags":[
        "personal",
        "marriage",
        "family",
        "counselling"
    ],
    "wof:name":"SoulLife Counselling",
    "wof:placetype":"venue"
},
  "geometry": {"coordinates":[151.11029052699999,-33.7871665955],"type":"Point"}
}