{
  "type": "Feature",
  "properties": {
    "iso:country":"AU",
    "sg:address":"6/ 2 Jenner St",
    "sg:city":"Nundah",
    "sg:classifiers":[
        {
            "category":"Shopping",
            "subcategory":"Clothing, Apparel, & Fashions",
            "type":"Retail Goods"
        }
    ],
    "sg:phone":"+61 7 3260 8550",
    "sg:postcode":"4012",
    "sg:province":"QLD",
    "sg:tags":[
        "menswear"
    ],
    "wof:name":"Chaps Menswear",
    "wof:placetype":"venue"
},
  "geometry": {"coordinates":[153.062423706,-27.4001789093],"type":"Point"}
}