{
  "type": "Feature",
  "properties": {
    "iso:country":"AU",
    "sg:address":"10 Mason Pl",
    "sg:city":"Barden Ridge",
    "sg:classifiers":[
        {
            "category":"Health Services",
            "subcategory":"Medical Lab",
            "type":"Services"
        }
    ],
    "sg:phone":"+61 414 543 929",
    "sg:postcode":"2234",
    "sg:province":"NSW",
    "sg:tags":[
        "laboratory",
        "dental"
    ],
    "wof:name":"Zahnelf Pty Ltd",
    "wof:placetype":"venue"
},
  "geometry": {"coordinates":[151.006713867,-34.0403022766],"type":"Point"}
}