{
  "type": "Feature",
  "properties": {
    "iso:country":"AU",
    "sg:address":"98 Wyralla Rd",
    "sg:city":"Miranda",
    "sg:classifiers":[
        {
            "category":"Education",
            "subcategory":"Kindergarten",
            "type":"Public Place"
        }
    ],
    "sg:phone":"+61 2 9526 8700",
    "sg:postcode":"2228",
    "sg:province":"NSW",
    "sg:tags":[
        "pre-schools"
    ],
    "wof:name":"Wyralla Road Kindergarten",
    "wof:placetype":"venue"
},
  "geometry": {"coordinates":[151.094970703,-34.0409545898],"type":"Point"}
}