{
  "type": "Feature",
  "properties": {
    "addr:full":"22a Hovia Tce South Perth WA 6151",
    "addr:housenumber":"22a",
    "addr:postcode":"6151",
    "addr:street":"Hovia Tce South",
    "iso:country":"AU",
    "sg:address":"22a Hovia Tce",
    "sg:city":"South Perth",
    "sg:classifiers":[
        {
            "category":"Professional",
            "subcategory":"Engineering",
            "type":"Services"
        }
    ],
    "sg:phone":"+61 8 9367 8276",
    "sg:postcode":"6151",
    "sg:province":"WA",
    "sg:tags":[
        "installation",
        "maintenance",
        "engineer"
    ],
    "wof:name":"Carey Gardner Engineering Pty Ltd",
    "wof:placetype":"venue"
},
  "geometry": {"coordinates":[115.87979900000001,-31.977451],"type":"Point"}
}