{
  "type": "Feature",
  "properties": {
    "iso:country":"AU",
    "sg:address":"30-38 Joan St",
    "sg:city":"Bungalow",
    "sg:classifiers":[
        {
            "category":"Retail",
            "subcategory":"Storage",
            "type":"Services"
        }
    ],
    "sg:phone":"+61 1800 623 713",
    "sg:postcode":"4870",
    "sg:province":"QLD",
    "sg:tags":[
        "removal",
        "furniture"
    ],
    "wof:name":"Australian Movers Group",
    "wof:placetype":"venue"
},
  "geometry": {"coordinates":[145.76322937,-16.9328460693],"type":"Point"}
}