{
  "type": "Feature",
  "properties": {
    "addr:full":"Lvl 1, 725 Anzac Pde Maroubra NSW 2035",
    "addr:housenumber":"725",
    "addr:postcode":"2035",
    "addr:street":"Anzac Pde",
    "iso:country":"AU",
    "sg:address":"Lvl 1, 725 Anzac Pde",
    "sg:city":"Maroubra",
    "sg:classifiers":[
        {
            "category":"Health Services",
            "subcategory":"Doctor",
            "type":"Services"
        }
    ],
    "sg:phone":"+61 2 9314 0311",
    "sg:postcode":"2035",
    "sg:province":"NSW",
    "sg:tags":[
        "medical",
        "practitioner"
    ],
    "wof:name":"Davies Campbell de Lambert Pathology",
    "wof:placetype":"venue"
},
  "geometry": {"coordinates":[151.23892211899999,-33.941242218],"type":"Point"}
}