{
  "type": "Feature",
  "properties": {
    "iso:country":"AU",
    "sg:address":"393 Fotheringham Rd",
    "sg:city":"Muirlea",
    "sg:classifiers":[
        {
            "category":"Building & Trades",
            "subcategory":"Construction",
            "type":"Services"
        }
    ],
    "sg:phone":"+61 7 3813 0830",
    "sg:postcode":"4306",
    "sg:province":"QLD",
    "sg:tags":[
        "polishing",
        "sanding",
        "floor"
    ],
    "wof:name":"Westin Blue",
    "wof:placetype":"venue"
},
  "geometry": {"coordinates":[152.73512268100001,-27.5796737671],"type":"Point"}
}