{
  "type": "Feature",
  "properties": {
    "addr:full":"Seaside Plaza Granville St Emu Park QLD 4702",
    "addr:postcode":"4702",
    "addr:street":"Granville St",
    "iso:country":"AU",
    "sg:address":"Seaside Plaza Granville St",
    "sg:city":"Emu Park",
    "sg:classifiers":[
        {
            "category":"Fast Food",
            "type":"Food & Drink"
        }
    ],
    "sg:phone":"+61 7 4939 6636",
    "sg:postcode":"4702",
    "sg:province":"QLD",
    "sg:tags":[
        "away",
        "take"
    ],
    "wof:name":"Emu Park Fish & Chip Shop",
    "wof:placetype":"venue"
},
  "geometry": {"coordinates":[150.13389587399999,-24.090675354],"type":"Point"}
}