{
  "type": "Feature",
  "properties": {
    "addr:full":"Unit 3 22 Hazelwood Rd Morwell VIC 3840",
    "addr:housenumber":"22",
    "addr:postcode":"3840",
    "addr:street":"Hazelwood Rd",
    "iso:country":"AU",
    "sg:address":"Unit 3 22 Hazelwood Rd",
    "sg:city":"Morwell",
    "sg:classifiers":[
        {
            "category":"Health Services",
            "subcategory":"Health Practitioner",
            "type":"Services"
        }
    ],
    "sg:phone":"+61 3 5135 6348",
    "sg:postcode":"3840",
    "sg:province":"VIC",
    "sg:tags":[
        "psychologist"
    ],
    "wof:name":"KTM-SDA Group Pty Ltd",
    "wof:placetype":"venue"
},
  "geometry": {"coordinates":[146.394256592,-38.2385864258],"type":"Point"}
}