{
  "type": "Feature",
  "properties": {
    "addr:full":"178 Connection Rd Pomona QLD 4568",
    "addr:housenumber":"178",
    "addr:postcode":"4568",
    "addr:street":"Connection Rd",
    "iso:country":"AU",
    "sg:address":"178 Connection Rd",
    "sg:city":"Pomona",
    "sg:classifiers":[
        {
            "category":"Arts & Performance",
            "subcategory":"Art Gallery",
            "type":"Entertainment"
        }
    ],
    "sg:phone":"+61 7 5485 2183",
    "sg:postcode":"4568",
    "sg:province":"QLD",
    "sg:tags":[
        "aboriginal",
        "craft"
    ],
    "wof:name":"Kurun Warun",
    "wof:placetype":"venue"
},
  "geometry": {"coordinates":[152.855392456,-26.3908901215],"type":"Point"}
}