{
  "type": "Feature",
  "properties": {
    "addr:full":"16D Princess Rd Crawley WA 6009",
    "addr:housenumber":"16d",
    "addr:postcode":"6009",
    "addr:street":"Princess Rd",
    "iso:country":"AU",
    "sg:address":"16D Princess Rd",
    "sg:city":"Crawley",
    "sg:classifiers":[
        {
            "category":"Military Area",
            "subcategory":"Air Force Base",
            "type":"Public Place"
        }
    ],
    "sg:phone":"+61 407 884 106",
    "sg:postcode":"6009",
    "sg:province":"WA",
    "sg:tags":[
        "adjuster",
        "compass"
    ],
    "wof:name":"Captain Michael Furlong",
    "wof:placetype":"venue"
},
  "geometry": {"coordinates":[115.817657,-31.986538],"type":"Point"}
}