{
  "type": "Feature",
  "properties": {
    "iso:country":"AU",
    "sg:address":"Lot 18 Lowes Mount Rd",
    "sg:city":"Oberon",
    "sg:classifiers":[
        {
            "category":"Home & Garden",
            "subcategory":"Building Materials",
            "type":"Retail Goods"
        }
    ],
    "sg:phone":"+61 2 6336 0028",
    "sg:postcode":"2787",
    "sg:province":"NSW",
    "sg:tags":[
        "supply"
    ],
    "wof:name":"Dark Red Frame & Truss",
    "wof:placetype":"venue"
},
  "geometry": {"coordinates":[149.84828185999999,-33.6249160767],"type":"Point"}
}