{
  "type": "Feature",
  "properties": {
    "addr:full":"Shop 4 Middy&#039;s Complex 29 Main St Buderim QLD 4556",
    "addr:housenumber":"shop 4;29",
    "addr:postcode":"4556",
    "addr:street":"S;Main St",
    "iso:country":"AU",
    "sg:address":"Shop 4 Middy&#039;s Complex 29 Main St",
    "sg:city":"Buderim",
    "sg:classifiers":[
        {
            "category":"Food & Beverages",
            "subcategory":"Bakery",
            "type":"Retail Goods"
        }
    ],
    "sg:phone":"+61 7 5445 2849",
    "sg:postcode":"4556",
    "sg:province":"QLD",
    "sg:tags":[
        "cake",
        "shop",
        "pastry"
    ],
    "wof:name":"Bartleys Bakery",
    "wof:placetype":"venue"
},
  "geometry": {"coordinates":[153.051071167,-26.6857318878],"type":"Point"}
}