{
  "type": "Feature",
  "properties": {
    "addr:full":"Cnr Station Rd & Main Rd St Albans VIC 3021",
    "addr:postcode":"3021",
    "addr:street":"Cnr Station Rd & Main Rd",
    "iso:country":"AU",
    "sg:address":"Cnr Station Rd & Main Rd St",
    "sg:city":"Albans",
    "sg:classifiers":[
        {
            "category":"Autos & Motor Vehicles",
            "subcategory":"Fuel & Gas Station",
            "type":"Retail Goods"
        }
    ],
    "sg:phone":"+61 3 9310 8899",
    "sg:postcode":"3021",
    "sg:province":"VIC",
    "wof:name":"Shell St Albans Self Serve",
    "wof:placetype":"venue"
},
  "geometry": {"coordinates":[144.77954099999999,-37.741997],"type":"Point"}
}