{
  "type": "Feature",
  "properties": {
    "addr:full":"King George Street Family Practice, 1 King George Victoria Park WA 6100",
    "addr:housenumber":"1",
    "addr:postcode":"6100",
    "addr:street":"King George Street;King",
    "iso:country":"AU",
    "sg:address":"King George Street Family Practice, 1 King George",
    "sg:city":"Victoria Park",
    "sg:classifiers":[
        {
            "category":"Health Services",
            "subcategory":"Doctor",
            "type":"Services"
        }
    ],
    "sg:phone":"+61 8 9470 5922",
    "sg:postcode":"6100",
    "sg:province":"WA",
    "sg:tags":[
        "medical",
        "practitioner"
    ],
    "wof:name":"O&#039;Mahony John Dr",
    "wof:placetype":"venue"
},
  "geometry": {"coordinates":[115.896080017,-31.9731273651],"type":"Point"}
}