{
  "type": "Feature",
  "properties": {
    "addr:full":"29 Torrens Rd Ovingham SA 5082",
    "addr:housenumber":"29",
    "addr:postcode":"5082",
    "addr:street":"Torrens Rd",
    "iso:country":"AU",
    "sg:address":"29 Torrens Rd",
    "sg:city":"Ovingham",
    "sg:classifiers":[
        {
            "category":"Food & Beverages",
            "subcategory":"Liquor & Beverages",
            "type":"Retail Goods"
        }
    ],
    "sg:phone":"+61 8 8269 4455",
    "sg:postcode":"5082",
    "sg:province":"SA",
    "sg:tags":[
        "store"
    ],
    "wof:name":"Liquor Marketing Group - S.A. Pty Ltd Sip&#039;N Save",
    "wof:placetype":"venue"
},
  "geometry": {"coordinates":[138.586380005,-34.8983078003],"type":"Point"}
}