{
  "type": "Feature",
  "properties": {
    "addr:full":"29 Links Ave Eagle Farm QLD 4009",
    "addr:housenumber":"29",
    "addr:postcode":"4009",
    "addr:street":"Links Ave",
    "iso:country":"AU",
    "sg:address":"29 Links Ave",
    "sg:city":"Eagle Farm",
    "sg:classifiers":[
        {
            "category":"Fast Food",
            "type":"Food & Drink"
        }
    ],
    "sg:phone":"+61 7 3868 2848",
    "sg:postcode":"4009",
    "sg:province":"QLD",
    "sg:tags":[
        "away",
        "take"
    ],
    "wof:name":"Links Avenue Carvery",
    "wof:placetype":"venue"
},
  "geometry": {"coordinates":[153.08784484899999,-27.4328708649],"type":"Point"}
}