{
  "type": "Feature",
  "properties": {
    "addr:full":"Myahgah Rd Spit Junction NSW 2088",
    "addr:postcode":"2088",
    "addr:street":"Myahgah Rd",
    "iso:country":"AU",
    "sg:address":"Myahgah Rd",
    "sg:city":"Spit Junction",
    "sg:classifiers":[
        {
            "category":"Personal",
            "subcategory":"Nail Salon",
            "type":"Services"
        }
    ],
    "sg:phone":"+61 2 9969 8480",
    "sg:postcode":"2088",
    "sg:province":"NSW",
    "sg:tags":[
        "artificial"
    ],
    "wof:name":"Nails By selina",
    "wof:placetype":"venue"
},
  "geometry": {"coordinates":[151.24107360799999,-33.8251953125],"type":"Point"}
}