{
  "type": "Feature",
  "properties": {
    "iso:country":"AU",
    "sg:address":"342 Young St",
    "sg:city":"Annandale",
    "sg:classifiers":[
        {
            "category":"Professional",
            "subcategory":"Art Services",
            "type":"Services"
        }
    ],
    "sg:phone":"+61 2 9660 5059",
    "sg:postcode":"2038",
    "sg:province":"NSW",
    "sg:tags":[
        "graphic",
        "designer"
    ],
    "wof:name":"CONSTANT CREATIONS PHOTO & DESIGN",
    "wof:placetype":"venue"
},
  "geometry": {"coordinates":[151.168731689,-33.879524231],"type":"Point"}
}