{
  "type": "Feature",
  "properties": {
    "addr:full":"Kiosk 3 / 171-209 Queen St Mall Brisbane QLD 4000",
    "addr:housenumber":"171-209",
    "addr:postcode":"4000",
    "addr:street":"Queen St Mall",
    "iso:country":"AU",
    "sg:address":"Kiosk 3 / 171-209 Queen St",
    "sg:city":"Mall Brisbane",
    "sg:classifiers":[
        {
            "category":"Cafe",
            "type":"Food & Drink"
        }
    ],
    "sg:phone":"+61 7 3012 7404",
    "sg:postcode":"4000",
    "sg:province":"QLD",
    "wof:name":"Cibo Espresso",
    "wof:placetype":"venue"
},
  "geometry": {"coordinates":[153.02630615199999,-27.4689903259],"type":"Point"}
}