{
  "type": "Feature",
  "properties": {
    "addr:full":"Unit 7/ 90 Campbell Tce Alderley QLD 4051",
    "addr:housenumber":"90",
    "addr:postcode":"4051",
    "addr:street":"Campbell Tce",
    "iso:country":"AU",
    "sg:address":"Unit 7/ 90",
    "sg:city":"Campbell Tce Alderley",
    "sg:classifiers":[
        {
            "category":"Wholesale",
            "subcategory":"Construction Materials",
            "type":"Manufacturing & Wholesale Goods"
        }
    ],
    "sg:phone":"+61 7 3715 7454",
    "sg:postcode":"4051",
    "sg:province":"QLD",
    "sg:tags":[
        "protective",
        "coating"
    ],
    "wof:name":"Rhino Linings North Side",
    "wof:placetype":"venue"
},
  "geometry": {"coordinates":[152.99920654300001,-27.4246997833],"type":"Point"}
}