{
  "type": "Feature",
  "properties": {
    "iso:country":"AU",
    "sg:address":"27 Hill St",
    "sg:city":"Quirindi",
    "sg:classifiers":[
        {
            "category":"Health Services",
            "subcategory":"Nursing And Care Facility",
            "type":"Services"
        }
    ],
    "sg:phone":"+61 2 6741 2222",
    "sg:postcode":"2343",
    "sg:province":"NSW",
    "sg:tags":[
        "home"
    ],
    "wof:name":"Quirindi Retirement Homes Association",
    "wof:placetype":"venue"
},
  "geometry": {"coordinates":[150.677368164,-31.5096359253],"type":"Point"}
}