{
  "type": "Feature",
  "properties": {
    "addr:full":"103 Albert Rd Moonah TAS 7009",
    "addr:housenumber":"103",
    "addr:postcode":"7009",
    "addr:street":"Albert Rd",
    "iso:country":"AU",
    "sg:address":"103 Albert Rd",
    "sg:city":"Moonah",
    "sg:classifiers":[
        {
            "category":"Professional",
            "subcategory":"Accounting & Tax Preparation",
            "type":"Services"
        }
    ],
    "sg:phone":"+61 3 6278 3000",
    "sg:postcode":"7009",
    "sg:province":"TAS",
    "sg:tags":[
        "accountant",
        "auditor"
    ],
    "wof:name":"David L Wilson",
    "wof:placetype":"venue"
},
  "geometry": {"coordinates":[147.30674743599999,-42.8485870361],"type":"Point"}
}