{
  "type": "Feature",
  "properties": {
    "addr:full":"6/ 86 City Rd Beenleigh QLD 4207",
    "addr:housenumber":"/ 86",
    "addr:postcode":"4207",
    "addr:street":"City Rd",
    "iso:country":"AU",
    "sg:address":"6/ 86 City Rd",
    "sg:city":"Beenleigh",
    "sg:classifiers":[
        {
            "category":"Banks & Credit Unions",
            "subcategory":"Investment Brokerage",
            "type":"Services"
        }
    ],
    "sg:phone":"+61 7 3807 5300",
    "sg:postcode":"4207",
    "sg:province":"QLD",
    "sg:tags":[
        "finance",
        "broker"
    ],
    "wof:name":"New Credit",
    "wof:placetype":"venue"
},
  "geometry": {"coordinates":[153.202514648,-27.7143421173],"type":"Point"}
}