{
  "type": "Feature",
  "properties": {
    "addr:full":"Arundel St Benalla VIC 3672",
    "addr:postcode":"3672",
    "addr:street":"Arundel St",
    "iso:country":"AU",
    "sg:address":"Arundel St",
    "sg:city":"Benalla",
    "sg:classifiers":[
        {
            "category":"Education",
            "subcategory":"School",
            "type":"Public Place"
        }
    ],
    "sg:phone":"+61 3 5762 1222",
    "sg:postcode":"3672",
    "sg:province":"VIC",
    "sg:tags":[
        "co-educational"
    ],
    "wof:name":"F C J College",
    "wof:placetype":"venue"
},
  "geometry": {"coordinates":[145.97624200000001,-36.553978],"type":"Point"}
}