{
  "type": "Feature",
  "properties": {
    "addr:full":"44 Gladstone Rd Highgate Hill QLD 4101",
    "addr:housenumber":"44",
    "addr:postcode":"4101",
    "addr:street":"Gladstone Rd",
    "iso:country":"AU",
    "sg:address":"44 Gladstone Rd",
    "sg:city":"Highgate Hill",
    "sg:classifiers":[
        {
            "category":"Education",
            "subcategory":"Special Training",
            "type":"Public Place"
        }
    ],
    "sg:phone":"+61 403 083 808",
    "sg:postcode":"4101",
    "sg:province":"QLD",
    "sg:tags":[
        "development"
    ],
    "wof:name":"Transformative Groups",
    "wof:placetype":"venue"
},
  "geometry": {"coordinates":[153.01976013199999,-27.4855537415],"type":"Point"}
}