{
  "type": "Feature",
  "properties": {
    "addr:full":"55 Dalgarno St Coonabarabran NSW 2357",
    "addr:housenumber":"55",
    "addr:postcode":"2357",
    "addr:street":"Dalgarno St",
    "iso:country":"AU",
    "sg:address":"55 Dalgarno St",
    "sg:city":"Coonabarabran",
    "sg:classifiers":[
        {
            "category":"Manufacturing",
            "subcategory":"Retail Goods",
            "type":"Manufacturing & Wholesale Goods"
        }
    ],
    "sg:phone":"+61 2 6842 2006",
    "sg:postcode":"2357",
    "sg:province":"NSW",
    "sg:tags":[
        "merchant",
        "pump",
        "mfrs"
    ],
    "wof:name":"West pumps & Accessories",
    "wof:placetype":"venue"
},
  "geometry": {"coordinates":[149.27919006400001,-31.2727069855],"type":"Point"}
}