{
  "type": "Feature",
  "properties": {
    "iso:country":"AU",
    "sg:address":"48 Luscombe Ave",
    "sg:city":"Carrum Downs",
    "sg:classifiers":[
        {
            "category":"Health Services",
            "subcategory":"Health Practitioner",
            "type":"Services"
        }
    ],
    "sg:phone":"+61 414 380 322",
    "sg:postcode":"3201",
    "sg:province":"VIC",
    "sg:tags":[
        "naturopath"
    ],
    "wof:name":"Rebecca Knapcek",
    "wof:placetype":"venue"
},
  "geometry": {"coordinates":[145.182922,-38.095966],"type":"Point"}
}