{
  "type": "Feature",
  "properties": {
    "iso:country":"AU",
    "sg:address":"25 Windsor St",
    "sg:city":"Perth",
    "sg:classifiers":[
        {
            "category":"Organizations",
            "subcategory":"Non-profit Organization",
            "type":"Services"
        }
    ],
    "sg:phone":"+61 8 9328 8113",
    "sg:postcode":"6000",
    "sg:province":"WA",
    "sg:tags":[
        "support",
        "disability",
        "organisation"
    ],
    "wof:name":"Catholic Concerns Committee On Psychiatric Issues",
    "wof:placetype":"venue"
},
  "geometry": {"coordinates":[115.87583923299999,-31.9440975189],"type":"Point"}
}