{
  "type": "Feature",
  "properties": {
    "addr:full":"169 Camberwell Rd Camberwell VIC 3124",
    "addr:housenumber":"169",
    "addr:postcode":"3124",
    "addr:street":"Camberwell Rd",
    "iso:country":"AU",
    "sg:address":"169 Camberwell Rd",
    "sg:city":"Camberwell",
    "sg:classifiers":[
        {
            "category":"Building & Trades",
            "subcategory":"Construction",
            "type":"Services"
        }
    ],
    "sg:phone":"+61 13 84 68",
    "sg:postcode":"3124",
    "sg:province":"VIC",
    "sg:tags":[
        "window",
        "tinting"
    ],
    "wof:name":"Tint.A.Car",
    "wof:placetype":"venue"
},
  "geometry": {"coordinates":[145.054885864,-37.8295173645],"type":"Point"}
}