{
  "type": "Feature",
  "properties": {
    "addr:full":"92 MIca St Carole Park QLD 4300",
    "addr:housenumber":"92",
    "addr:postcode":"4300",
    "addr:street":"Mica St",
    "iso:country":"AU",
    "sg:address":"92 MIca St",
    "sg:city":"Carole Park",
    "sg:classifiers":[
        {
            "category":"Wholesale",
            "subcategory":"Machinery & Supplies",
            "type":"Manufacturing & Wholesale Goods"
        }
    ],
    "sg:phone":"+61 7 3271 5200",
    "sg:postcode":"4300",
    "sg:province":"QLD",
    "sg:tags":[
        "equipment",
        "system",
        "elevating",
        "conveying"
    ],
    "wof:name":"Magnetic Engineering (Qld) Pty Ltd",
    "wof:placetype":"venue"
},
  "geometry": {"coordinates":[152.93370056099999,-27.6216335297],"type":"Point"}
}