{
  "type": "Feature",
  "properties": {
    "addr:full":"1186 Toorak Rd Hartwell VIC 3124",
    "addr:housenumber":"1186",
    "addr:postcode":"3124",
    "addr:street":"Toorak Rd",
    "iso:country":"AU",
    "sg:address":"1186 Toorak Rd",
    "sg:city":"Hartwell",
    "sg:classifiers":[
        {
            "category":"Professional",
            "subcategory":"Computer Services",
            "type":"Services"
        }
    ],
    "sg:phone":"+61 3 9835 5400",
    "sg:postcode":"3124",
    "sg:province":"VIC",
    "sg:tags":[
        "package",
        "software"
    ],
    "wof:name":"PLM Australasia Pty Ltd",
    "wof:placetype":"venue"
},
  "geometry": {"coordinates":[145.07928466800001,-37.8486175537],"type":"Point"}
}