{
  "type": "Feature",
  "properties": {
    "iso:country":"AU",
    "sg:address":"Unit 6/ 142 Gladstone St",
    "sg:city":"Fyshwick",
    "sg:classifiers":[
        {
            "category":"Retail",
            "subcategory":"Auto Rental",
            "type":"Services"
        }
    ],
    "sg:phone":"+61 2 6239 2177",
    "sg:postcode":"2609",
    "sg:province":"ACT",
    "sg:tags":[
        "chauffeur",
        "car",
        "hire",
        "driven",
        "limousine"
    ],
    "wof:name":"Canberra Hire Cars Pty Ltd",
    "wof:placetype":"venue"
},
  "geometry": {"coordinates":[149.183517456,-35.3254508972],"type":"Point"}
}