{
  "type": "Feature",
  "properties": {
    "addr:full":"76 Melwood Ave Killarney Heights NSW 2087",
    "addr:housenumber":"76",
    "addr:postcode":"2087",
    "addr:street":"Melwood Ave",
    "iso:country":"AU",
    "sg:address":"76 Melwood Ave",
    "sg:city":"Killarney Heights",
    "sg:classifiers":[
        {
            "category":"Professional",
            "subcategory":"Accounting & Tax Preparation",
            "type":"Services"
        }
    ],
    "sg:phone":"+61 2 9401 9571",
    "sg:postcode":"2087",
    "sg:province":"NSW",
    "sg:tags":[
        "accountant",
        "auditor"
    ],
    "wof:name":"Halliday J N P",
    "wof:placetype":"venue"
},
  "geometry": {"coordinates":[151.21321105999999,-33.7719154358],"type":"Point"}
}