{
  "type": "Feature",
  "properties": {
    "addr:full":"1875 Mt Gravatt Capalaba Rd Capalaba West QLD 4157",
    "addr:housenumber":"1875",
    "addr:postcode":"4157",
    "addr:street":"Mt;Capalaba Rd",
    "iso:country":"AU",
    "sg:address":"1875 Mt Gravatt Capalaba Rd",
    "sg:city":"Capalaba West",
    "sg:classifiers":[
        {
            "category":"Banks & Credit Unions",
            "subcategory":"Financial Services",
            "type":"Services"
        }
    ],
    "sg:phone":"+61 7 3245 3200",
    "sg:postcode":"4157",
    "sg:province":"QLD",
    "sg:tags":[
        "financier"
    ],
    "wof:name":"Talanel Finance & Investment Pty Ltd",
    "wof:placetype":"venue"
},
  "geometry": {"coordinates":[153.18307495100001,-27.5198154449],"type":"Point"}
}