{
  "type": "Feature",
  "properties": {
    "iso:country":"AU",
    "sg:address":"2860 Albany Highway",
    "sg:city":"Kelmscott",
    "sg:classifiers":[
        {
            "category":"Real Estate",
            "subcategory":"Real Estate Agent",
            "type":"Services"
        }
    ],
    "sg:phone":"+61 8 9495 1212",
    "sg:postcode":"6111",
    "sg:province":"WA",
    "wof:name":"Kelmscott First National",
    "wof:placetype":"venue"
},
  "geometry": {"coordinates":[116.018226623,-32.1242752075],"type":"Point"}
}