{
  "type": "Feature",
  "properties": {
    "addr:full":"Factory 1/ 4 Wigan Rd Bayswater VIC 3153",
    "addr:housenumber":"/ 4",
    "addr:postcode":"3153",
    "addr:street":"Wigan Rd",
    "iso:country":"AU",
    "sg:address":"Factory 1/ 4 Wigan Rd",
    "sg:city":"Bayswater",
    "sg:classifiers":[
        {
            "category":"Building & Trades",
            "subcategory":"Cleaning & Sanitation",
            "type":"Services"
        }
    ],
    "sg:phone":"+61 3 9761 3600",
    "sg:postcode":"3153",
    "sg:province":"VIC",
    "sg:tags":[
        "abrasive",
        "blasting"
    ],
    "wof:name":"B & B Master Blasters",
    "wof:placetype":"venue"
},
  "geometry": {"coordinates":[145.28077697800001,-37.84557724],"type":"Point"}
}