{
  "type": "Feature",
  "properties": {
    "addr:full":"1 Fourth Ave Klemzig SA 5087",
    "addr:housenumber":"1",
    "addr:postcode":"5087",
    "addr:street":"Fourth Ave",
    "iso:country":"AU",
    "sg:address":"1 Fourth Ave",
    "sg:city":"Klemzig",
    "sg:classifiers":[
        {
            "category":"Manufacturing",
            "subcategory":"Pottery",
            "type":"Manufacturing & Wholesale Goods"
        }
    ],
    "sg:phone":"+61 8 8266 2011",
    "sg:postcode":"5087",
    "sg:province":"SA",
    "wof:name":"Studio Potters SA",
    "wof:placetype":"venue"
},
  "geometry": {"coordinates":[138.64268493599999,-34.8767585754],"type":"Point"}
}