{
  "type": "Feature",
  "properties": {
    "iso:country":"AU",
    "sg:address":"PO Box 1051",
    "sg:city":"Hartwell",
    "sg:classifiers":[
        {
            "category":"Autos & Motor Vehicles",
            "subcategory":"Auto Supplies",
            "type":"Retail Goods"
        }
    ],
    "sg:phone":"+61 402 346 032",
    "sg:postcode":"3124",
    "sg:province":"VIC",
    "sg:tags":[
        "accessory"
    ],
    "wof:name":"Justsr.Com",
    "wof:placetype":"venue"
},
  "geometry": {"coordinates":[145.067596436,-37.8465805054],"type":"Point"}
}