{
  "type": "Feature",
  "properties": {
    "addr:full":"13/52- 55 The Crs Dee Why NSW 2099",
    "addr:housenumber":"13 / 52 55",
    "addr:postcode":"2099",
    "addr:street":"The Crs",
    "iso:country":"AU",
    "sg:address":"13/52- 55 The Crs",
    "sg:city":"Dee Why",
    "sg:classifiers":[
        {
            "category":"Building & Trades",
            "subcategory":"Plumbing",
            "type":"Services"
        }
    ],
    "sg:phone":"+61 2 9971 4289",
    "sg:postcode":"2099",
    "sg:province":"NSW",
    "sg:tags":[
        "plumber",
        "gasfitters"
    ],
    "wof:name":"Accord Plumbing",
    "wof:placetype":"venue"
},
  "geometry": {"coordinates":[151.29788207999999,-33.7304573059],"type":"Point"}
}