{
  "type": "Feature",
  "properties": {
    "iso:country":"AU",
    "sg:address":"166 Melbourne Rd",
    "sg:city":"Wodonga",
    "sg:classifiers":[
        {
            "category":"Travel",
            "subcategory":"Hotels & Motels",
            "type":"Entertainment"
        }
    ],
    "sg:phone":"+61 2 6024 2111",
    "sg:postcode":"3690",
    "sg:province":"VIC",
    "wof:name":"Twin City Motor Inn",
    "wof:placetype":"venue"
},
  "geometry": {"coordinates":[146.87236023,-36.1170845032],"type":"Point"}
}