{
  "type": "Feature",
  "properties": {
    "addr:full":"8 Watchorn Rd Cowes VIC 3922",
    "addr:housenumber":"8",
    "addr:postcode":"3922",
    "addr:street":"Watchorn Rd",
    "iso:country":"AU",
    "sg:address":"8 Watchorn Rd",
    "sg:city":"Cowes",
    "sg:classifiers":[
        {
            "category":"Building & Trades",
            "subcategory":"Construction",
            "type":"Services"
        }
    ],
    "sg:phone":"+61 3 5952 2120",
    "sg:postcode":"3922",
    "sg:province":"VIC",
    "sg:tags":[
        "window",
        "aluminium"
    ],
    "wof:name":"Toovey Building Solutions",
    "wof:placetype":"venue"
},
  "geometry": {"coordinates":[145.240234375,-38.4556808472],"type":"Point"}
}