{
  "type": "Feature",
  "properties": {
    "iso:country":"AU",
    "sg:address":"19 Longhurst St",
    "sg:city":"Narembeen",
    "sg:classifiers":[
        {
            "category":"Autos & Motor Vehicles",
            "subcategory":"Auto Supplies",
            "type":"Retail Goods"
        }
    ],
    "sg:phone":"+61 8 9064 7326",
    "sg:postcode":"6369",
    "sg:province":"WA",
    "sg:tags":[
        "tyre"
    ],
    "wof:name":"Narembeen Tyre Service",
    "wof:placetype":"venue"
},
  "geometry": {"coordinates":[118.391296,-32.066582],"type":"Point"}
}