{
  "type": "Feature",
  "properties": {
    "addr:full":"6 Yandina Rd Gosford West NSW 2250",
    "addr:housenumber":"6",
    "addr:postcode":"2250",
    "addr:street":"Yandina Rd",
    "iso:country":"AU",
    "sg:address":"6 Yandina Rd",
    "sg:city":"Gosford West",
    "sg:classifiers":[
        {
            "category":"Transit Center",
            "subcategory":"Freight",
            "type":"Transportation"
        }
    ],
    "sg:phone":"+61 2 4322 6220",
    "sg:postcode":"2250",
    "sg:province":"NSW",
    "sg:tags":[
        "forklift",
        "truck"
    ],
    "wof:name":"Hunter Liftrucks Pty. Limited",
    "wof:placetype":"venue"
},
  "geometry": {"coordinates":[151.31878662099999,-33.4184417725],"type":"Point"}
}