{
  "type": "Feature",
  "properties": {
    "addr:full":"Factory 3, 8 Joyce St Springvale VIC 3171",
    "addr:housenumber":"8",
    "addr:postcode":"3171",
    "addr:street":"Joyce St",
    "iso:country":"AU",
    "sg:address":"Factory 3, 8 Joyce St",
    "sg:city":"Springvale",
    "sg:classifiers":[
        {
            "category":"Manufacturing",
            "subcategory":"Metals",
            "type":"Manufacturing & Wholesale Goods"
        }
    ],
    "sg:phone":"+61 3 9574 1899",
    "sg:postcode":"3171",
    "sg:province":"VIC",
    "sg:tags":[
        "sheet",
        "worker"
    ],
    "wof:name":"Tri-Steel Industries",
    "wof:placetype":"venue"
},
  "geometry": {"coordinates":[145.150665283,-37.9337501526],"type":"Point"}
}