{
  "type": "Feature",
  "properties": {
    "iso:country":"AU",
    "sg:address":"91 Main Rd",
    "sg:city":"Manning Point",
    "sg:classifiers":[
        {
            "category":"Restaurant",
            "type":"Food & Drink"
        }
    ],
    "sg:phone":"+61 2 6553 2753",
    "sg:postcode":"2430",
    "sg:province":"NSW",
    "wof:name":"Blue Water Cafe Restausrant & Gallery",
    "wof:placetype":"venue"
},
  "geometry": {"coordinates":[152.52212499999999,-31.90217],"type":"Point"}
}