{
  "type": "Feature",
  "properties": {
    "addr:full":"316 Railway Pde Carlton NSW 2218",
    "addr:housenumber":"316",
    "addr:postcode":"2218",
    "addr:street":"Railway Pde",
    "iso:country":"AU",
    "sg:address":"316 Railway Pde",
    "sg:city":"Carlton",
    "sg:classifiers":[
        {
            "category":"Fast Food",
            "type":"Food & Drink"
        }
    ],
    "sg:phone":"+61 2 9587 8114",
    "sg:postcode":"2218",
    "sg:province":"NSW",
    "sg:tags":[
        "away",
        "take"
    ],
    "wof:name":"Carlton Chinese Takeaway",
    "wof:placetype":"venue"
},
  "geometry": {"coordinates":[151.12316899999999,-33.968899],"type":"Point"}
}