{
  "type": "Feature",
  "properties": {
    "addr:full":"7 Acorn Pl Dunsborough WA 6281",
    "addr:housenumber":"7",
    "addr:postcode":"6281",
    "addr:street":"Acorn Pl",
    "iso:country":"AU",
    "sg:address":"7 Acorn Pl",
    "sg:city":"Dunsborough",
    "sg:classifiers":[
        {
            "category":"Communications",
            "type":"Services"
        }
    ],
    "sg:phone":"+61 8 9344 4107",
    "sg:postcode":"6281",
    "sg:province":"WA",
    "sg:tags":[
        "public",
        "system",
        "address"
    ],
    "wof:name":"South West Audio Visual",
    "wof:placetype":"venue"
},
  "geometry": {"coordinates":[115.097389221,-33.6022796631],"type":"Point"}
}