{
  "type": "Feature",
  "properties": {
    "iso:country":"AU",
    "sg:address":"110 Harris St",
    "sg:city":"Harris Park",
    "sg:classifiers":[
        {
            "category":"Social Services",
            "subcategory":"Child Care",
            "type":"Services"
        }
    ],
    "sg:phone":"+61 2 9630 3353",
    "sg:postcode":"2150",
    "sg:province":"NSW",
    "wof:name":"SDN Children's Services",
    "wof:placetype":"venue"
},
  "geometry": {"coordinates":[151.011154175,-33.8188781738],"type":"Point"}
}