{
  "type": "Feature",
  "properties": {
    "iso:country":"AU",
    "sg:address":"510 Adelaide St",
    "sg:city":"Brisbane",
    "sg:classifiers":[
        {
            "category":"Shopping",
            "subcategory":"Clothing, Apparel, & Fashions",
            "type":"Retail Goods"
        }
    ],
    "sg:phone":"+61 7 3832 1824",
    "sg:postcode":"4000",
    "sg:province":"QLD",
    "sg:tags":[
        "lady",
        "wear"
    ],
    "wof:name":"Easton Pearson",
    "wof:placetype":"venue"
},
  "geometry": {"coordinates":[153.03253173799999,-27.4622344971],"type":"Point"}
}