{
  "type": "Feature",
  "properties": {
    "iso:country":"AU",
    "sg:address":"1767 Botany Rd",
    "sg:city":"Banksmeadow",
    "sg:classifiers":[
        {
            "category":"Shopping",
            "subcategory":"Stationery & Office Supplies",
            "type":"Retail Goods"
        }
    ],
    "sg:phone":"+61 2 8333 6100",
    "sg:postcode":"2019",
    "sg:province":"NSW",
    "sg:tags":[
        "equipment",
        "display",
        "exhibition"
    ],
    "wof:name":"Xhibit",
    "wof:placetype":"venue"
},
  "geometry": {"coordinates":[151.21141052199999,-33.9599838257],"type":"Point"}
}