{
  "type": "Feature",
  "properties": {
    "addr:full":"40 Channel Hwy Kingston TAS 7050",
    "addr:housenumber":"40",
    "addr:postcode":"7050",
    "addr:street":"Channel Hwy",
    "iso:country":"AU",
    "sg:address":"40 Channel Hwy",
    "sg:city":"Kingston",
    "sg:classifiers":[
        {
            "category":"Health Services",
            "subcategory":"Doctor",
            "type":"Services"
        }
    ],
    "sg:phone":"+61 3 6229 8583",
    "sg:postcode":"7050",
    "sg:province":"TAS",
    "sg:tags":[
        "podiatrist"
    ],
    "wof:name":"Hill Julia",
    "wof:placetype":"venue"
},
  "geometry": {"coordinates":[147.30830399999999,-42.975651],"type":"Point"}
}