{
  "type": "Feature",
  "properties": {
    "iso:country":"AU",
    "sg:address":"143 Research Rd",
    "sg:city":"Warrandyte",
    "sg:classifiers":[
        {
            "category":"Shopping",
            "type":"Retail Goods"
        }
    ],
    "sg:phone":"+61 3 9844 5888",
    "sg:postcode":"3113",
    "sg:province":"VIC",
    "sg:tags":[
        "new age",
        "product"
    ],
    "wof:name":"Renascent",
    "wof:placetype":"venue"
},
  "geometry": {"coordinates":[145.23545837399999,-37.747379303],"type":"Point"}
}