{
  "type": "Feature",
  "properties": {
    "iso:country":"AU",
    "sg:address":"Unit 3, 6 Robertson Pl",
    "sg:city":"Penrith South",
    "sg:classifiers":[
        {
            "category":"Building & Trades",
            "subcategory":"Construction",
            "type":"Services"
        }
    ],
    "sg:phone":"+61 2 4732 1569",
    "sg:postcode":"2750",
    "sg:province":"NSW",
    "sg:tags":[
        "window",
        "aluminium"
    ],
    "wof:name":"Mountainview Windows & Doors",
    "wof:placetype":"venue"
},
  "geometry": {"coordinates":[150.68289184599999,-33.7683334351],"type":"Point"}
}