{
  "type": "Feature",
  "properties": {
    "addr:full":"Lvl 1, 137 Flora St Sutherland NSW 2232",
    "addr:housenumber":"137",
    "addr:postcode":"2232",
    "addr:street":"Flora St",
    "iso:country":"AU",
    "sg:address":"Lvl 1, 137 Flora St",
    "sg:city":"Sutherland",
    "sg:classifiers":[
        {
            "category":"Education",
            "subcategory":"Music School",
            "type":"Public Place"
        }
    ],
    "sg:phone":"+61 2 9545 5605",
    "sg:postcode":"2232",
    "sg:province":"NSW",
    "sg:tags":[
        "teacher"
    ],
    "wof:name":"Forte School Of Music",
    "wof:placetype":"venue"
},
  "geometry": {"coordinates":[151.058425903,-34.0317573547],"type":"Point"}
}