{
  "type": "Feature",
  "properties": {
    "addr:full":"Community Centre Lawson St Southport QLD 4215",
    "addr:postcode":"4215",
    "addr:street":"Lawson St",
    "iso:country":"AU",
    "sg:address":"Community Centre Lawson St",
    "sg:city":"Southport",
    "sg:classifiers":[
        {
            "category":"Personal",
            "type":"Services"
        }
    ],
    "sg:phone":"+61 7 5591 2062",
    "sg:postcode":"4215",
    "sg:province":"QLD",
    "sg:tags":[
        "counselling",
        "alcohol",
        "drug"
    ],
    "wof:name":"Alcoholics Anonymous",
    "wof:placetype":"venue"
},
  "geometry": {"coordinates":[153.41384887699999,-27.9706268311],"type":"Point"}
}