{
  "type": "Feature",
  "properties": {
    "addr:full":"Lot392/ Penfield Rd Virginia SA 5120",
    "addr:postcode":"5120",
    "addr:street":"Penfield Rd",
    "iso:country":"AU",
    "sg:address":"Lot392/ Penfield Rd",
    "sg:city":"Virginia",
    "sg:classifiers":[
        {
            "category":"Food & Beverages",
            "subcategory":"Fruits & Vegetables",
            "type":"Retail Goods"
        }
    ],
    "sg:phone":"+61 8 8380 9860",
    "sg:postcode":"5120",
    "sg:province":"SA",
    "sg:tags":[
        "wholesale"
    ],
    "wof:name":"Virginia Packing Shed SA Pty Ltd",
    "wof:placetype":"venue"
},
  "geometry": {"coordinates":[138.56155395499999,-34.6685218811],"type":"Point"}
}