{
  "type": "Feature",
  "properties": {
    "iso:country":"AU",
    "sg:address":"7 Wainwright St",
    "sg:city":"Ballarat",
    "sg:classifiers":[
        {
            "category":"Restaurant",
            "type":"Food & Drink"
        }
    ],
    "sg:phone":"+61 3 5331 6655",
    "sg:postcode":"3350",
    "sg:province":"VIC",
    "wof:name":"Da Uday",
    "wof:placetype":"venue"
},
  "geometry": {"coordinates":[143.869064,-37.573238],"type":"Point"}
}