{
  "type": "Feature",
  "properties": {
    "addr:full":"106 Church St Mudgee NSW 2850",
    "addr:housenumber":"106",
    "addr:postcode":"2850",
    "addr:street":"Church St",
    "iso:country":"AU",
    "sg:address":"106 Church St",
    "sg:city":"Mudgee",
    "sg:classifiers":[
        {
            "category":"Professional",
            "subcategory":"Computer Services",
            "type":"Services"
        }
    ],
    "sg:phone":"+61 2 6372 1231",
    "sg:postcode":"2850",
    "sg:province":"NSW",
    "sg:tags":[
        "repairs",
        "upgrade",
        "equipment"
    ],
    "wof:name":"DewDrop Computers",
    "wof:placetype":"venue"
},
  "geometry": {"coordinates":[149.58519000000001,-32.60741],"type":"Point"}
}