{
  "type": "Feature",
  "properties": {
    "addr:full":"Unit 4/ 42 Machinery Drv Tweed Heads South NSW 2486",
    "addr:housenumber":"42",
    "addr:postcode":"2486",
    "addr:street":"Machinery Drv",
    "iso:country":"AU",
    "sg:address":"Unit 4/ 42 Machinery Drv",
    "sg:city":"Tweed Heads South",
    "sg:classifiers":[
        {
            "category":"Communications",
            "type":"Services"
        }
    ],
    "sg:phone":"+61 7 5523 3388",
    "sg:postcode":"2486",
    "sg:province":"NSW",
    "sg:tags":[
        "antenna"
    ],
    "wof:name":"Antenna Agencies",
    "wof:placetype":"venue"
},
  "geometry": {"coordinates":[153.54153442399999,-28.2045993805],"type":"Point"}
}