{
  "type": "Feature",
  "properties": {
    "addr:full":"Cnr Wilson & Carpenter St Brighton VIC 3186",
    "addr:postcode":"3186",
    "addr:street":"Cnr;St",
    "iso:country":"AU",
    "sg:address":"Cnr Wilson & Carpenter St",
    "sg:city":"Brighton",
    "sg:classifiers":[
        {
            "category":"Education",
            "subcategory":"University",
            "type":"Public Place"
        }
    ],
    "sg:phone":"+61 3 9553 8650",
    "sg:postcode":"3186",
    "sg:province":"VIC",
    "sg:tags":[
        "educational",
        "organisation",
        "cultural"
    ],
    "wof:name":"Brighton Historical Society",
    "wof:placetype":"venue"
},
  "geometry": {"coordinates":[144.99874877900001,-37.9113578796],"type":"Point"}
}