{
  "type": "Feature",
  "properties": {
    "iso:country":"AU",
    "sg:address":"15 Carrington Drv",
    "sg:city":"Sunshine",
    "sg:classifiers":[
        {
            "category":"Retail",
            "subcategory":"Auto Repair",
            "type":"Services"
        }
    ],
    "sg:phone":"+61 3 9363 5464",
    "sg:postcode":"3020",
    "sg:province":"VIC",
    "sg:tags":[
        "repairer",
        "motor",
        "engineer"
    ],
    "wof:name":"MJ Motors",
    "wof:placetype":"venue"
},
  "geometry": {"coordinates":[144.809143,-37.773521],"type":"Point"}
}