{
  "type": "Feature",
  "properties": {
    "addr:full":"33- 39 Birralee Rd Regency Park SA 5010",
    "addr:housenumber":"39",
    "addr:postcode":"5010",
    "addr:street":"Birralee Rd",
    "iso:country":"AU",
    "sg:address":"33- 39 Birralee Rd",
    "sg:city":"Regency Park",
    "sg:classifiers":[
        {
            "category":"Farming",
            "subcategory":"Dairy Farm",
            "type":"Manufacturing & Wholesale Goods"
        }
    ],
    "sg:phone":"+61 8 8268 1504",
    "sg:postcode":"5010",
    "sg:province":"SA",
    "sg:tags":[
        "wholesaler",
        "product",
        "mfrs"
    ],
    "wof:name":"Knispel Fruit Juices Pty Ltd t/a Nippys",
    "wof:placetype":"venue"
},
  "geometry": {"coordinates":[138.569625855,-34.8525886536],"type":"Point"}
}