{
  "type": "Feature",
  "properties": {
    "addr:full":"29 Gale St Brunswick East VIC 3057",
    "addr:housenumber":"29",
    "addr:postcode":"3057",
    "addr:street":"Gale St",
    "iso:country":"AU",
    "sg:address":"29 Gale St",
    "sg:city":"Brunswick East",
    "sg:classifiers":[
        {
            "category":"Professional",
            "subcategory":"Art Services",
            "type":"Services"
        }
    ],
    "sg:phone":"+61 3 9387 8799",
    "sg:postcode":"3057",
    "sg:province":"VIC",
    "sg:tags":[
        "picture",
        "frame",
        "framing"
    ],
    "wof:name":"Graphic Allsorts Pty Ltd",
    "wof:placetype":"venue"
},
  "geometry": {"coordinates":[144.97297668499999,-37.7687759399],"type":"Point"}
}