{
  "type": "Feature",
  "properties": {
    "addr:full":"4/ 993 South Pine Rd Everton Hills QLD 4053",
    "addr:housenumber":"/ 993",
    "addr:postcode":"4053",
    "addr:street":"South Pine Rd",
    "iso:country":"AU",
    "sg:address":"4/ 993 South Pine Rd",
    "sg:city":"Everton Hills",
    "sg:classifiers":[
        {
            "category":"Professional",
            "subcategory":"Art Services",
            "type":"Services"
        }
    ],
    "sg:phone":"+61 7 3355 3354",
    "sg:postcode":"4053",
    "sg:province":"QLD",
    "sg:tags":[
        "picture",
        "frame",
        "framing"
    ],
    "wof:name":"Keynote Gallery",
    "wof:placetype":"venue"
},
  "geometry": {"coordinates":[152.974685669,-27.3915271759],"type":"Point"}
}