{
  "type": "Feature",
  "properties": {
    "addr:full":"Shop17 Cavill Place 25 Cavill Ave Surfers Paradise QLD 4217",
    "addr:housenumber":"25",
    "addr:postcode":"4217",
    "addr:street":"Cavill;Cavill Ave",
    "iso:country":"AU",
    "sg:address":"Shop17 Cavill Place 25 Cavill Ave",
    "sg:city":"Surfers Paradise",
    "sg:classifiers":[
        {
            "category":"Shopping",
            "type":"Retail Goods"
        }
    ],
    "sg:phone":"+61 7 5538 5048",
    "sg:postcode":"4217",
    "sg:province":"QLD",
    "sg:tags":[
        "new age",
        "product"
    ],
    "wof:name":"Holistic Light Healing Therapies",
    "wof:placetype":"venue"
},
  "geometry": {"coordinates":[153.42904663100001,-28.0017566681],"type":"Point"}
}