{
  "type": "Feature",
  "properties": {
    "iso:country":"AU",
    "sg:address":"5 Curio Rd",
    "sg:city":"Cambrai",
    "sg:classifiers":[
        {
            "category":"Manufacturing",
            "subcategory":"Petroleum Products",
            "type":"Manufacturing & Wholesale Goods"
        }
    ],
    "sg:phone":"+61 8 8564 5106",
    "sg:postcode":"5353",
    "sg:province":"SA",
    "sg:tags":[
        "fuel",
        "oil",
        "additive"
    ],
    "wof:name":"Greased Lightning",
    "wof:placetype":"venue"
},
  "geometry": {"coordinates":[139.280883789,-34.6550445557],"type":"Point"}
}