{
  "type": "Feature",
  "properties": {
    "iso:country":"AU",
    "sg:address":"New Holland Drv",
    "sg:city":"Cranbourne",
    "sg:classifiers":[
        {
            "category":"Sports & Exercise",
            "subcategory":"Sports Center",
            "type":"Entertainment"
        }
    ],
    "sg:phone":"+61 3 5996 6905",
    "sg:postcode":"3977",
    "sg:province":"VIC",
    "sg:tags":[
        "ground"
    ],
    "wof:name":"Casey Indoor Sports Centre",
    "wof:placetype":"venue"
},
  "geometry": {"coordinates":[145.29255676299999,-38.1100921631],"type":"Point"}
}