{
  "type": "Feature",
  "properties": {
    "addr:full":"Suite 1, 33 Elizabeth St Camden NSW 2570",
    "addr:housenumber":"33",
    "addr:postcode":"2570",
    "addr:street":"Elizabeth St",
    "iso:country":"AU",
    "sg:address":"Suite 1, 33 Elizabeth St",
    "sg:city":"Camden",
    "sg:classifiers":[
        {
            "category":"Health Services",
            "subcategory":"Doctor",
            "type":"Services"
        }
    ],
    "sg:phone":"+61 2 4655 4666",
    "sg:postcode":"2570",
    "sg:province":"NSW",
    "sg:tags":[
        "medical",
        "practitioner"
    ],
    "wof:name":"Cabot's Sandra Dr Holistic Health Clinic",
    "wof:placetype":"venue"
},
  "geometry": {"coordinates":[150.69715881400001,-34.0523986816],"type":"Point"}
}