{
  "type": "Feature",
  "properties": {
    "addr:full":"Unit 1 5 Yarana Rd Alphington VIC 3078",
    "addr:housenumber":"5",
    "addr:postcode":"3078",
    "addr:street":"Yarana Rd",
    "iso:country":"AU",
    "sg:address":"Unit 1 5 Yarana Rd",
    "sg:city":"Alphington",
    "sg:classifiers":[
        {
            "category":"Building & Trades",
            "subcategory":"Cleaning & Sanitation",
            "type":"Services"
        }
    ],
    "sg:phone":"+61 3 9499 9466",
    "sg:postcode":"3078",
    "sg:province":"VIC",
    "sg:tags":[
        "cleaner",
        "repairer",
        "roof"
    ],
    "wof:name":"Elliott Roofing Pty Ltd",
    "wof:placetype":"venue"
},
  "geometry": {"coordinates":[145.03140258799999,-37.7774848938],"type":"Point"}
}