{
  "type": "Feature",
  "properties": {
    "addr:full":"149 Macquarie St Hobart TAS 7000",
    "addr:housenumber":"149",
    "addr:postcode":"7000",
    "addr:street":"Macquarie St",
    "iso:country":"AU",
    "sg:address":"149 Macquarie St",
    "sg:city":"Hobart",
    "sg:classifiers":[
        {
            "category":"Health Services",
            "subcategory":"Dentist",
            "type":"Services"
        }
    ],
    "sg:phone":"+61 3 6234 5733",
    "sg:postcode":"7000",
    "sg:province":"TAS",
    "wof:name":"Butler Robert Dr",
    "wof:placetype":"venue"
},
  "geometry": {"coordinates":[147.327362061,-42.8847427368],"type":"Point"}
}