{
  "type": "Feature",
  "properties": {
    "addr:full":"13 Park St Launceston TAS 7250",
    "addr:housenumber":"13",
    "addr:postcode":"7250",
    "addr:street":"Park St",
    "iso:country":"AU",
    "sg:address":"13 Park St",
    "sg:city":"Launceston",
    "sg:classifiers":[
        {
            "category":"Restaurant",
            "type":"Food & Drink"
        }
    ],
    "sg:phone":"+61 3 6334 0554",
    "sg:postcode":"7250",
    "sg:province":"TAS",
    "wof:name":"Hallams Waterfront Licensed Restaurant",
    "wof:placetype":"venue"
},
  "geometry": {"coordinates":[147.13130188,-41.4385910034],"type":"Point"}
}