{
  "type": "Feature",
  "properties": {
    "addr:full":"74 Bunnerong Rd Pagewood NSW 2035",
    "addr:housenumber":"74",
    "addr:postcode":"2035",
    "addr:street":"Bunnerong Rd",
    "iso:country":"AU",
    "sg:address":"74 Bunnerong Rd",
    "sg:city":"Pagewood",
    "sg:classifiers":[
        {
            "category":"Professional",
            "subcategory":"Accounting & Tax Preparation",
            "type":"Services"
        }
    ],
    "sg:phone":"+61 2 8347 2274",
    "sg:postcode":"2035",
    "sg:province":"NSW",
    "sg:tags":[
        "accountant",
        "auditor"
    ],
    "wof:name":"ABM Accounting Solutions Pty Ltd",
    "wof:placetype":"venue"
},
  "geometry": {"coordinates":[151.229812622,-33.9363059998],"type":"Point"}
}