{
  "type": "Feature",
  "properties": {
    "iso:country":"AU",
    "sg:address":"2/ 123 Sugar Rd",
    "sg:city":"Maroochydore",
    "sg:classifiers":[
        {
            "category":"Retail",
            "subcategory":"Auto Repair",
            "type":"Services"
        }
    ],
    "sg:phone":"+61 7 5479 5144",
    "sg:postcode":"4558",
    "sg:province":"QLD",
    "sg:tags":[
        "repairer",
        "motor",
        "engineer"
    ],
    "wof:name":"Headland Auto Servicing & Air Conditioning",
    "wof:placetype":"venue"
},
  "geometry": {"coordinates":[153.09556579599999,-26.6697769165],"type":"Point"}
}