{
  "type": "Feature",
  "properties": {
    "addr:full":"15 Takalvan St Bundaberg QLD 4670",
    "addr:housenumber":"15",
    "addr:postcode":"4670",
    "addr:street":"Takalvan St",
    "iso:country":"AU",
    "sg:address":"15 Takalvan St",
    "sg:city":"Bundaberg",
    "sg:classifiers":[
        {
            "category":"Home & Garden",
            "subcategory":"Hardware",
            "type":"Retail Goods"
        }
    ],
    "sg:phone":"+61 7 4151 5436",
    "sg:postcode":"4670",
    "sg:province":"QLD",
    "sg:tags":[
        "tarpaulin"
    ],
    "wof:name":"Bundaberg Camping World",
    "wof:placetype":"venue"
},
  "geometry": {"coordinates":[152.33363342300001,-24.8727226257],"type":"Point"}
}