{
  "type": "Feature",
  "properties": {
    "iso:country":"AU",
    "sg:address":"4/ 7 Clearview Pl",
    "sg:city":"Brookvale",
    "sg:classifiers":[
        {
            "category":"Shopping",
            "subcategory":"Stationery & Office Supplies",
            "type":"Retail Goods"
        }
    ],
    "sg:phone":"+61 2 9905 5858",
    "sg:postcode":"2100",
    "sg:province":"NSW",
    "sg:tags":[
        "packaging",
        "material"
    ],
    "wof:name":"Ace Packaging Supplies P/L",
    "wof:placetype":"venue"
},
  "geometry": {"coordinates":[151.262252808,-33.7620925903],"type":"Point"}
}