{
  "type": "Feature",
  "properties": {
    "addr:full":"22 William St Gatton QLD 4343",
    "addr:housenumber":"22",
    "addr:postcode":"4343",
    "addr:street":"William St",
    "iso:country":"AU",
    "sg:address":"22 William St",
    "sg:city":"Gatton",
    "sg:classifiers":[
        {
            "category":"Shopping",
            "subcategory":"Optical Goods",
            "type":"Retail Goods"
        }
    ],
    "sg:phone":"+61 7 5462 1122",
    "sg:postcode":"4343",
    "sg:province":"QLD",
    "sg:tags":[
        "dispenser",
        "prescription"
    ],
    "wof:name":"Best Price Eyewear",
    "wof:placetype":"venue"
},
  "geometry": {"coordinates":[152.27822875999999,-27.5596141815],"type":"Point"}
}