{
  "type": "Feature",
  "properties": {
    "iso:country":"AU",
    "sg:address":"650 Wickham St",
    "sg:city":"Fortitude Valley",
    "sg:classifiers":[
        {
            "category":"Professional",
            "subcategory":"Computer Services",
            "type":"Services"
        }
    ],
    "sg:phone":"+61 7 3406 1500",
    "sg:postcode":"4006",
    "sg:province":"QLD",
    "sg:tags":[
        "tele-communications",
        "consultant"
    ],
    "wof:name":"Visionstream Pty Ltd",
    "wof:placetype":"venue"
},
  "geometry": {"coordinates":[153.040725708,-27.4503707886],"type":"Point"}
}