{
  "type": "Feature",
  "properties": {
    "addr:full":"2/ 68 Centinnial Cct Byron Bay NSW 2481",
    "addr:housenumber":"/ 68",
    "addr:postcode":"2481",
    "addr:street":"Centinnial Cct",
    "iso:country":"AU",
    "sg:address":"2/ 68 Centinnial Cct",
    "sg:city":"Byron Bay",
    "sg:classifiers":[
        {
            "category":"Building & Trades",
            "subcategory":"Plumbing",
            "type":"Services"
        }
    ],
    "sg:phone":"+61 1300 793 449",
    "sg:postcode":"2481",
    "sg:province":"NSW",
    "sg:tags":[
        "plumber",
        "gasfitters"
    ],
    "wof:name":"Cape Byron Plumbing",
    "wof:placetype":"venue"
},
  "geometry": {"coordinates":[153.612823486,-28.6468906403],"type":"Point"}
}