{
  "type": "Feature",
  "properties": {
    "addr:full":"1/ 11 Cemetery Rd Mackay QLD 4740",
    "addr:housenumber":"/ 11",
    "addr:postcode":"4740",
    "addr:street":"Cemetery Rd",
    "iso:country":"AU",
    "sg:address":"1/ 11 Cemetery Rd",
    "sg:city":"Mackay",
    "sg:classifiers":[
        {
            "category":"Manufacturing",
            "subcategory":"Electronics",
            "type":"Manufacturing & Wholesale Goods"
        }
    ],
    "sg:phone":"+61 7 4953 0734",
    "sg:postcode":"4740",
    "sg:province":"QLD",
    "sg:tags":[
        "wholesaler",
        "equipment",
        "part",
        "mfrs",
        "refrigeration"
    ],
    "wof:name":"Actrol Parts",
    "wof:placetype":"venue"
},
  "geometry": {"coordinates":[149.16365099999999,-21.145706],"type":"Point"}
}