{
  "type": "Feature",
  "properties": {
    "addr:full":"52 Sydenham Rd Norwood SA 5067",
    "addr:housenumber":"52",
    "addr:postcode":"5067",
    "addr:street":"Sydenham Rd",
    "iso:country":"AU",
    "sg:address":"52 Sydenham Rd",
    "sg:city":"Norwood",
    "sg:classifiers":[
        {
            "category":"Professional",
            "subcategory":"Art Services",
            "type":"Services"
        }
    ],
    "sg:phone":"+61 8 8363 3313",
    "sg:postcode":"5067",
    "sg:province":"SA",
    "sg:tags":[
        "graphic",
        "designer"
    ],
    "sg:website":"http://www.theprintinghub.com.au",
    "wof:name":"The Printing Hub",
    "wof:placetype":"venue"
},
  "geometry": {"coordinates":[138.62765502900001,-34.920375824],"type":"Point"}
}