{
  "type": "Feature",
  "properties": {
    "addr:full":"Suite 1, 99 Kedron Brook Rd Wilston QLD 4051",
    "addr:housenumber":"99",
    "addr:postcode":"4051",
    "addr:street":"Kedron Brook Rd",
    "iso:country":"AU",
    "sg:address":"Suite 1, 99 Kedron Brook Rd",
    "sg:city":"Wilston",
    "sg:classifiers":[
        {
            "category":"Personal",
            "subcategory":"Day Spa",
            "type":"Services"
        }
    ],
    "sg:phone":"+61 7 3856 2530",
    "sg:postcode":"4051",
    "sg:province":"QLD",
    "wof:name":"Fifth Avenue Beauty & Day Spa",
    "wof:placetype":"venue"
},
  "geometry": {"coordinates":[153.01971435600001,-27.4320545197],"type":"Point"}
}