{
  "type": "Feature",
  "properties": {
    "addr:full":"15 Doust St Jurien Bay WA 6516",
    "addr:housenumber":"15",
    "addr:postcode":"6516",
    "addr:street":"Doust St",
    "iso:country":"AU",
    "sg:address":"15 Doust St",
    "sg:city":"Jurien Bay",
    "sg:classifiers":[
        {
            "category":"Retail",
            "subcategory":"Veterinary Services",
            "type":"Services"
        }
    ],
    "sg:phone":"+61 8 9652 1407",
    "sg:postcode":"6516",
    "sg:province":"WA",
    "sg:tags":[
        "surgeon"
    ],
    "wof:name":"Jurien Bay Veterinary Hospital",
    "wof:placetype":"venue"
},
  "geometry": {"coordinates":[115.041656,-30.301661],"type":"Point"}
}