{
  "type": "Feature",
  "properties": {
    "addr:full":"41 Beacon Rd Port Melbourne VIC 3207",
    "addr:housenumber":"41",
    "addr:postcode":"3207",
    "addr:street":"Beacon Rd",
    "iso:country":"AU",
    "sg:address":"41 Beacon Rd",
    "sg:city":"Port Melbourne",
    "sg:classifiers":[
        {
            "category":"Building & Trades",
            "subcategory":"Cleaning & Sanitation",
            "type":"Services"
        }
    ],
    "sg:phone":"+61 408 037 511",
    "sg:postcode":"3207",
    "sg:province":"VIC",
    "sg:tags":[
        "sweep",
        "chimney"
    ],
    "wof:name":"AAA Chimney Sweeps",
    "wof:placetype":"venue"
},
  "geometry": {"coordinates":[144.92926,-37.835426],"type":"Point"}
}