{
  "type": "Feature",
  "properties": {
    "addr:full":"46 Carrington St Adelaide SA 5000",
    "addr:housenumber":"46",
    "addr:postcode":"5000",
    "addr:street":"Carrington St",
    "iso:country":"AU",
    "sg:address":"46 Carrington St",
    "sg:city":"Adelaide",
    "sg:classifiers":[
        {
            "category":"Shopping",
            "subcategory":"Clothing, Apparel, & Fashions",
            "type":"Retail Goods"
        }
    ],
    "sg:phone":"+61 8 8305 9385",
    "sg:postcode":"5000",
    "sg:province":"SA",
    "sg:tags":[
        "recycled",
        "clothing"
    ],
    "wof:name":"Magdalene Centre (Anglicare SA)",
    "wof:placetype":"venue"
},
  "geometry": {"coordinates":[138.60191345199999,-34.9312934875],"type":"Point"}
}