{
  "type": "Feature",
  "properties": {
    "addr:full":"144 Lethbridge St Penrith NSW 2750",
    "addr:housenumber":"144",
    "addr:postcode":"2750",
    "addr:street":"Lethbridge St",
    "iso:country":"AU",
    "sg:address":"144 Lethbridge St",
    "sg:city":"Penrith",
    "sg:classifiers":[
        {
            "category":"Health Services",
            "subcategory":"Doctor",
            "type":"Services"
        }
    ],
    "sg:phone":"+61 2 4731 5566",
    "sg:postcode":"2750",
    "sg:province":"NSW",
    "sg:tags":[
        "medical",
        "practitioner"
    ],
    "wof:name":"Deveridge R J Dr",
    "wof:placetype":"venue"
},
  "geometry": {"coordinates":[150.698394775,-33.756023407],"type":"Point"}
}