{
  "type": "Feature",
  "properties": {
    "iso:country":"AU",
    "sg:address":"33 Wilson St",
    "sg:city":"Horsham",
    "sg:classifiers":[
        {
            "category":"Autos & Motor Vehicles",
            "subcategory":"Auto Supplies",
            "type":"Retail Goods"
        }
    ],
    "sg:phone":"+61 3 5382 4951",
    "sg:postcode":"3400",
    "sg:province":"VIC",
    "sg:tags":[
        "accessory"
    ],
    "wof:name":"Autopro Horsham",
    "wof:placetype":"venue"
},
  "geometry": {"coordinates":[142.20095825199999,-36.7167434692],"type":"Point"}
}