{
  "type": "Feature",
  "properties": {
    "addr:full":"50b Prospect Rd Prospect SA 5082",
    "addr:housenumber":"50b",
    "addr:postcode":"5082",
    "addr:street":"Prospect Rd",
    "iso:country":"AU",
    "sg:address":"50b Prospect Rd",
    "sg:city":"Prospect",
    "sg:classifiers":[
        {
            "category":"Wholesale",
            "subcategory":"Stationery",
            "type":"Manufacturing & Wholesale Goods"
        }
    ],
    "sg:phone":"+61 8 8342 6607",
    "sg:postcode":"5082",
    "sg:province":"SA",
    "sg:tags":[
        "mfrg"
    ],
    "wof:name":"Statewide Rubber Stamps",
    "wof:placetype":"venue"
},
  "geometry": {"coordinates":[138.594238281,-34.8928222656],"type":"Point"}
}