{
  "type": "Feature",
  "properties": {
    "iso:country":"AU",
    "sg:address":"99B Kyle Pde",
    "sg:city":"Kyle Bay",
    "sg:classifiers":[
        {
            "category":"Manufacturing",
            "subcategory":"Metals",
            "type":"Manufacturing & Wholesale Goods"
        }
    ],
    "sg:phone":"+61 416 008 088",
    "sg:postcode":"2221",
    "sg:province":"NSW",
    "sg:tags":[
        "wholesaler",
        "aluminium",
        "mfrs"
    ],
    "wof:name":"Alumanz Alum. Co",
    "wof:placetype":"venue"
},
  "geometry": {"coordinates":[151.0990448,-33.9919319153],"type":"Point"}
}