{
  "type": "Feature",
  "properties": {
    "addr:full":"5/ 231 Collier Rd Bayswater WA 6053",
    "addr:housenumber":"/ 231",
    "addr:postcode":"6053",
    "addr:street":"Collier Rd",
    "iso:country":"AU",
    "sg:address":"5/ 231 Collier Rd",
    "sg:city":"Bayswater",
    "sg:classifiers":[
        {
            "category":"Home & Garden",
            "subcategory":"Building Materials",
            "type":"Retail Goods"
        }
    ],
    "sg:phone":"+61 8 9371 5498",
    "sg:postcode":"6053",
    "sg:province":"WA",
    "sg:tags":[
        "merchant",
        "glass",
        "glazier"
    ],
    "wof:name":"All Design Glazing",
    "wof:placetype":"venue"
},
  "geometry": {"coordinates":[115.91680145300001,-31.9043178558],"type":"Point"}
}