{
  "type": "Feature",
  "properties": {
    "addr:full":"24 Weekes Rd Carindale QLD 4152",
    "addr:housenumber":"24",
    "addr:postcode":"4152",
    "addr:street":"Weekes Rd",
    "iso:country":"AU",
    "sg:address":"24 Weekes Rd",
    "sg:city":"Carindale",
    "sg:classifiers":[
        {
            "category":"Professional",
            "subcategory":"Art Services",
            "type":"Services"
        }
    ],
    "sg:phone":"+61 7 3398 3930",
    "sg:postcode":"4152",
    "sg:province":"QLD",
    "sg:tags":[
        "decorator",
        "painter"
    ],
    "wof:name":"Ash Brian",
    "wof:placetype":"venue"
},
  "geometry": {"coordinates":[153.10157775900001,-27.5085754395],"type":"Point"}
}