{
  "type": "Feature",
  "properties": {
    "addr:full":"153 Smeaton Grange Rd Macarthur Square NSW 2560",
    "addr:housenumber":"153",
    "addr:postcode":"2560",
    "addr:street":"Smeaton Grange Rd Macarthur Square",
    "iso:country":"AU",
    "sg:address":"153 Smeaton Grange Rd",
    "sg:city":"Macarthur Square",
    "sg:classifiers":[
        {
            "category":"Industrial Area",
            "type":"Public Place"
        }
    ],
    "sg:phone":"+61 2 4648 5544",
    "sg:postcode":"2560",
    "sg:province":"NSW",
    "sg:tags":[
        "rural",
        "shed"
    ],
    "wof:name":"Totalspan",
    "wof:placetype":"venue"
},
  "geometry": {"coordinates":[150.75851440400001,-34.0450515747],"type":"Point"}
}