{
  "type": "Feature",
  "properties": {
    "iso:country":"AU",
    "sg:address":"126 Erskine St",
    "sg:city":"Dubbo",
    "sg:classifiers":[
        {
            "category":"Home & Garden",
            "subcategory":"Household Appliances",
            "type":"Retail Goods"
        }
    ],
    "sg:phone":"+61 1300 304 108",
    "sg:postcode":"2830",
    "sg:province":"NSW",
    "sg:tags":[
        "equipment",
        "gas"
    ],
    "wof:name":"Orana Energy Systems",
    "wof:placetype":"venue"
},
  "geometry": {"coordinates":[148.603424072,-32.2427940369],"type":"Point"}
}