{
  "type": "Feature",
  "properties": {
    "addr:full":"Penney's Rd Pumphreys WA 6308",
    "addr:postcode":"6308",
    "addr:street":"Penney'S Rd",
    "iso:country":"AU",
    "sg:address":"Penney's Rd",
    "sg:city":"Pumphreys",
    "sg:classifiers":[
        {
            "category":"Farming",
            "subcategory":"Farm",
            "type":"Manufacturing & Wholesale Goods"
        }
    ],
    "sg:phone":"+61 8 9887 7033",
    "sg:postcode":"6308",
    "sg:province":"WA",
    "sg:tags":[
        "farmer"
    ],
    "wof:name":"Tullett D W & M",
    "wof:placetype":"venue"
},
  "geometry": {"coordinates":[116.90387725799999,-32.6625099182],"type":"Point"}
}