{
  "type": "Feature",
  "properties": {
    "addr:full":"246 Blackburn Rd Syndal VIC 3149",
    "addr:housenumber":"246",
    "addr:postcode":"3149",
    "addr:street":"Blackburn Rd",
    "iso:country":"AU",
    "sg:address":"246 Blackburn Rd",
    "sg:city":"Syndal",
    "sg:classifiers":[
        {
            "category":"Fast Food",
            "type":"Food & Drink"
        }
    ],
    "sg:phone":"+61 3 9887 8722",
    "sg:postcode":"3149",
    "sg:province":"VIC",
    "sg:tags":[
        "away",
        "take"
    ],
    "wof:name":"Di Virgona's Pizza & Pasta",
    "wof:placetype":"venue"
},
  "geometry": {"coordinates":[145.148147583,-37.8743247986],"type":"Point"}
}