{
  "type": "Feature",
  "properties": {
    "addr:full":"Shop 7, 29 Peachey Rd Ormeau QLD 4208",
    "addr:housenumber":"shop;29",
    "addr:postcode":"4208",
    "addr:street":"Peachey Rd",
    "iso:country":"AU",
    "sg:address":"Shop 7, 29 Peachey Rd",
    "sg:city":"Ormeau",
    "sg:classifiers":[
        {
            "category":"Real Estate",
            "subcategory":"Real Estate Agent",
            "type":"Services"
        }
    ],
    "sg:phone":"+61 7 5546 6166",
    "sg:postcode":"4208",
    "sg:province":"QLD",
    "wof:name":"Harcourts Queensland Pty Ltd",
    "wof:placetype":"venue"
},
  "geometry": {"coordinates":[153.25343322800001,-27.7872180939],"type":"Point"}
}