{
  "type": "Feature",
  "properties": {
    "addr:full":"112 Eddystone Ave Craigie WA 6025",
    "addr:housenumber":"112",
    "addr:postcode":"6025",
    "addr:street":"Eddystone Ave",
    "iso:country":"AU",
    "sg:address":"112 Eddystone Ave",
    "sg:city":"Craigie",
    "sg:classifiers":[
        {
            "category":"Health Services",
            "subcategory":"Doctor",
            "type":"Services"
        }
    ],
    "sg:phone":"+61 8 9402 1922",
    "sg:postcode":"6025",
    "sg:province":"WA",
    "sg:tags":[
        "medical",
        "practitioner"
    ],
    "wof:name":"Batty G.William",
    "wof:placetype":"venue"
},
  "geometry": {"coordinates":[115.768051148,-31.7844772339],"type":"Point"}
}