{
  "type": "Feature",
  "properties": {
    "iso:country":"AU",
    "sg:address":"Bronberg Plaza Medical Centre, 150 Slatyer Ave",
    "sg:city":"Southport",
    "sg:classifiers":[
        {
            "category":"Health Services",
            "subcategory":"Doctor",
            "type":"Services"
        }
    ],
    "sg:phone":"+61 7 5539 3977",
    "sg:postcode":"4215",
    "sg:province":"QLD",
    "sg:tags":[
        "medical",
        "practitioner"
    ],
    "wof:name":"Singh Sunil Dr",
    "wof:placetype":"venue"
},
  "geometry": {"coordinates":[153.41224670400001,-27.9985122681],"type":"Point"}
}