{
  "type": "Feature",
  "properties": {
    "addr:full":"678 High St Preston VIC 3072",
    "addr:housenumber":"678",
    "addr:postcode":"3072",
    "addr:street":"High St",
    "iso:country":"AU",
    "sg:address":"678 High St",
    "sg:city":"Preston",
    "sg:classifiers":[
        {
            "category":"Shopping",
            "subcategory":"Party Supplies",
            "type":"Retail Goods"
        }
    ],
    "sg:phone":"+61 3 9471 2666",
    "sg:postcode":"3072",
    "sg:province":"VIC",
    "sg:tags":[
        "hire",
        "costume"
    ],
    "sg:website":"http://www.fancydress.com.au",
    "wof:name":"Heidelberg Fancy Dress",
    "wof:placetype":"venue"
},
  "geometry": {"coordinates":[145.00570678700001,-37.7288742065],"type":"Point"}
}