{
  "type": "Feature",
  "properties": {
    "addr:full":"81 Carter St Cammeray NSW 2062",
    "addr:housenumber":"81",
    "addr:postcode":"2062",
    "addr:street":"Carter St",
    "iso:country":"AU",
    "sg:address":"81 Carter St",
    "sg:city":"Cammeray",
    "sg:classifiers":[
        {
            "category":"Education",
            "subcategory":"Special Training",
            "type":"Public Place"
        }
    ],
    "sg:phone":"+61 2 9953 7116",
    "sg:postcode":"2062",
    "sg:province":"NSW",
    "sg:tags":[
        "development"
    ],
    "wof:name":"Cresco International Pty Limited",
    "wof:placetype":"venue"
},
  "geometry": {"coordinates":[151.220245361,-33.8214797974],"type":"Point"}
}