{
  "type": "Feature",
  "properties": {
    "addr:full":"240a Pitt Town Rd Kenthurst NSW 2156",
    "addr:housenumber":"240a",
    "addr:postcode":"2156",
    "addr:street":"Pitt Town Rd",
    "iso:country":"AU",
    "sg:address":"240a Pitt Town Rd",
    "sg:city":"Kenthurst",
    "sg:classifiers":[
        {
            "category":"Retail",
            "subcategory":"Auto Repair",
            "type":"Services"
        }
    ],
    "sg:phone":"+61 2 9654 9071",
    "sg:postcode":"2156",
    "sg:province":"NSW",
    "sg:tags":[
        "beater",
        "painter",
        "panel"
    ],
    "wof:name":"Loxton Smash Repairs",
    "wof:placetype":"venue"
},
  "geometry": {"coordinates":[150.948165894,-33.6212348938],"type":"Point"}
}