{
  "type": "Feature",
  "properties": {
    "iso:country":"AU",
    "sg:address":"Unit 6, 182 Robertson St",
    "sg:city":"Fortitude Valley",
    "sg:classifiers":[
        {
            "category":"Banks & Credit Unions",
            "subcategory":"Bank",
            "type":"Services"
        }
    ],
    "sg:phone":"+61 7 3257 2822",
    "sg:postcode":"4006",
    "sg:province":"QLD",
    "sg:tags":[
        "broker",
        "mortgage"
    ],
    "wof:name":"Mortgage Brokers Australia",
    "wof:placetype":"venue"
},
  "geometry": {"coordinates":[153.03985595699999,-27.4573192596],"type":"Point"}
}