{
  "type": "Feature",
  "properties": {
    "addr:full":"Shp 40/ 15 Valediction Rd Kings Park NSW 2148",
    "addr:housenumber":"40 / 15",
    "addr:postcode":"2148",
    "addr:street":"Valediction Rd",
    "iso:country":"AU",
    "sg:address":"Shp 40/ 15 Valediction Rd",
    "sg:city":"Kings Park",
    "sg:classifiers":[
        {
            "category":"Cafe",
            "type":"Food & Drink"
        }
    ],
    "sg:phone":"+61 2 9622 0047",
    "sg:postcode":"2148",
    "sg:province":"NSW",
    "wof:name":"Cafe Addiction",
    "wof:placetype":"venue"
},
  "geometry": {"coordinates":[150.912765503,-33.7454147339],"type":"Point"}
}