{
  "type": "Feature",
  "properties": {
    "addr:full":"Shed 7 370 Stuart Hwy Winnellie NT 0820",
    "addr:housenumber":"7 370",
    "addr:postcode":"nt 0820",
    "addr:street":"Stuart Hwy",
    "iso:country":"AU",
    "sg:address":"Shed 7 370 Stuart Hwy",
    "sg:city":"Winnellie",
    "sg:classifiers":[
        {
            "category":"Retail",
            "subcategory":"Auto Repair",
            "type":"Services"
        }
    ],
    "sg:phone":"+61 8 8947 2111",
    "sg:postcode":"0820",
    "sg:province":"NT",
    "sg:tags":[
        "repairer",
        "motor",
        "engineer"
    ],
    "wof:name":"M B N Automotive",
    "wof:placetype":"venue"
},
  "geometry": {"coordinates":[130.866500855,-12.4260044098],"type":"Point"}
}