{
  "type": "Feature",
  "properties": {
    "addr:full":"44 King St Doncaster East VIC 3109",
    "addr:housenumber":"44",
    "addr:postcode":"3109",
    "addr:street":"King St",
    "iso:country":"AU",
    "sg:address":"44 King St",
    "sg:city":"Doncaster East",
    "sg:classifiers":[
        {
            "category":"Shopping",
            "subcategory":"Computers & Home Electronics",
            "type":"Retail Goods"
        }
    ],
    "sg:phone":"+61 421 337 733",
    "sg:postcode":"3109",
    "sg:province":"VIC",
    "sg:tags":[
        "equipment",
        "multimedia"
    ],
    "wof:name":"Tranciet Design",
    "wof:placetype":"venue"
},
  "geometry": {"coordinates":[145.15080261200001,-37.7736358643],"type":"Point"}
}