{
  "type": "Feature",
  "properties": {
    "addr:full":"231a Victoria Rd Gladesville NSW 2111",
    "addr:housenumber":"231a",
    "addr:postcode":"2111",
    "addr:street":"Victoria Rd",
    "iso:country":"AU",
    "sg:address":"231a Victoria Rd",
    "sg:city":"Gladesville",
    "sg:classifiers":[
        {
            "category":"Building & Trades",
            "subcategory":"Equipment Rental",
            "type":"Services"
        }
    ],
    "sg:phone":"+61 2 9879 5622",
    "sg:postcode":"2111",
    "sg:province":"NSW",
    "sg:tags":[
        "fitness"
    ],
    "wof:name":"The FIRM",
    "wof:placetype":"venue"
},
  "geometry": {"coordinates":[151.127044678,-33.8316726685],"type":"Point"}
}