{
  "type": "Feature",
  "properties": {
    "iso:country":"AU",
    "sg:address":"11 Grevillea St",
    "sg:city":"Collaroy Plateau",
    "sg:classifiers":[
        {
            "category":"Metro Station",
            "type":"Transportation"
        }
    ],
    "sg:phone":"+61 2 9971 6629",
    "sg:postcode":"2097",
    "sg:province":"NSW",
    "sg:tags":[
        "consultant",
        "marine"
    ],
    "wof:name":"Tait Andrew",
    "wof:placetype":"venue"
},
  "geometry": {"coordinates":[151.293899536,-33.7287902832],"type":"Point"}
}