{
  "type": "Feature",
  "properties": {
    "addr:full":"51 Robinson St Dandenong VIC 3175",
    "addr:housenumber":"51",
    "addr:postcode":"3175",
    "addr:street":"Robinson St",
    "iso:country":"AU",
    "sg:address":"51 Robinson St",
    "sg:city":"Dandenong",
    "sg:classifiers":[
        {
            "category":"Professional",
            "subcategory":"Accounting & Tax Preparation",
            "type":"Services"
        }
    ],
    "sg:phone":"+61 3 9792 9555",
    "sg:postcode":"3175",
    "sg:province":"VIC",
    "sg:tags":[
        "accountant",
        "auditor"
    ],
    "wof:name":"Small Business Advisory Services",
    "wof:placetype":"venue"
},
  "geometry": {"coordinates":[145.21119689899999,-37.9852333069],"type":"Point"}
}