{
  "type": "Feature",
  "properties": {
    "addr:full":"Shop B/ 65 Ridgewood Rd Algester QLD 4115",
    "addr:housenumber":"65",
    "addr:postcode":"4115",
    "addr:street":"Ridgewood Rd",
    "iso:country":"AU",
    "sg:address":"Shop B/ 65 Ridgewood Rd",
    "sg:city":"Algester",
    "sg:classifiers":[
        {
            "category":"Health Services",
            "subcategory":"Health Practitioner",
            "type":"Services"
        }
    ],
    "sg:phone":"+61 7 3272 4622",
    "sg:postcode":"4115",
    "sg:province":"QLD",
    "sg:tags":[
        "naturopath"
    ],
    "wof:name":"Corrective Chiropractic",
    "wof:placetype":"venue"
},
  "geometry": {"coordinates":[153.03237915,-27.6112766266],"type":"Point"}
}