{
  "type": "Feature",
  "properties": {
    "addr:full":"Lot 114/ Doust St Jurien WA 6516",
    "addr:postcode":"6516",
    "addr:street":"St",
    "iso:country":"AU",
    "sg:address":"Lot 114/ Doust St",
    "sg:city":"Jurien",
    "sg:classifiers":[
        {
            "category":"Autos & Motor Vehicles",
            "subcategory":"Auto Supplies",
            "type":"Retail Goods"
        }
    ],
    "sg:phone":"+61 8 9652 1159",
    "sg:postcode":"6516",
    "sg:province":"WA",
    "sg:tags":[
        "tyre"
    ],
    "wof:name":"Jurien Tyre & Auto",
    "wof:placetype":"venue"
},
  "geometry": {"coordinates":[115.042778,-30.302147],"type":"Point"}
}