{
  "type": "Feature",
  "properties": {
    "iso:country":"AU",
    "sg:address":"Ocean Keys Shopping Centre Key Largo Drv",
    "sg:city":"Clarkson",
    "sg:classifiers":[
        {
            "category":"Real Estate",
            "subcategory":"Real Estate Agent",
            "type":"Services"
        }
    ],
    "sg:phone":"+61 8 9407 8988",
    "sg:postcode":"6030",
    "sg:province":"WA",
    "wof:name":"David Evans Real Estate",
    "wof:placetype":"venue"
},
  "geometry": {"coordinates":[115.71926879900001,-31.6893806458],"type":"Point"}
}