{
  "type": "Feature",
  "properties": {
    "iso:country":"AU",
    "sg:address":"Lot 2155 McKinnon Rd",
    "sg:city":"Berrimah",
    "sg:classifiers":[
        {
            "category":"Transit Center",
            "subcategory":"Passenger",
            "type":"Transportation"
        }
    ],
    "sg:phone":"+61 8 8932 2204",
    "sg:postcode":"0828",
    "sg:province":"NT",
    "sg:tags":[
        "frozen",
        "food",
        "retail"
    ],
    "wof:name":"Lo Castro Foods",
    "wof:placetype":"venue"
},
  "geometry": {"coordinates":[130.964233398,-12.4541091919],"type":"Point"}
}