{
  "type": "Feature",
  "properties": {
    "addr:full":"6a Montrose St Hawthorn East VIC 3123",
    "addr:housenumber":"6a",
    "addr:postcode":"3123",
    "addr:street":"Montrose St",
    "iso:country":"AU",
    "sg:address":"6a Montrose St",
    "sg:city":"Hawthorn East",
    "sg:classifiers":[
        {
            "category":"Real Estate",
            "subcategory":"Architect",
            "type":"Services"
        }
    ],
    "sg:phone":"+61 3 9882 4611",
    "sg:postcode":"3123",
    "sg:province":"VIC",
    "wof:name":"Anthony Styant-Browne Architect Pty Ltd",
    "wof:placetype":"venue"
},
  "geometry": {"coordinates":[145.046218872,-37.8230209351],"type":"Point"}
}