{
  "type": "Feature",
  "properties": {
    "addr:full":"Clear Mountain Rd Clear Mountain QLD 4500",
    "addr:postcode":"4500",
    "addr:street":"Clear Mountain Rd",
    "iso:country":"AU",
    "sg:address":"Clear Mountain Rd",
    "sg:city":"Clear Mountain",
    "sg:classifiers":[
        {
            "category":"Retail",
            "subcategory":"Event Space",
            "type":"Services"
        }
    ],
    "sg:phone":"+61 7 3298 5100",
    "sg:postcode":"4500",
    "sg:province":"QLD",
    "sg:tags":[
        "venue",
        "reception",
        "wedding"
    ],
    "wof:name":"Quality Hotel Clear Mountain",
    "wof:placetype":"venue"
},
  "geometry": {"coordinates":[152.91545105,-27.3302707672],"type":"Point"}
}