{
  "type": "Feature",
  "properties": {
    "addr:full":"45 Forest Ridge Drv Narangba QLD 4504",
    "addr:housenumber":"45",
    "addr:postcode":"4504",
    "addr:street":"Forest Ridge Drv",
    "iso:country":"AU",
    "sg:address":"45 Forest Ridge Drv",
    "sg:city":"Narangba",
    "sg:classifiers":[
        {
            "category":"Building & Trades",
            "subcategory":"Construction",
            "type":"Services"
        }
    ],
    "sg:phone":"+61 7 3637 5511",
    "sg:postcode":"4504",
    "sg:province":"QLD",
    "sg:tags":[
        "contractor"
    ],
    "wof:name":"Quanting Pty Ltd",
    "wof:placetype":"venue"
},
  "geometry": {"coordinates":[152.93095398,-27.1839199066],"type":"Point"}
}