{
  "type": "Feature",
  "properties": {
    "addr:full":"7 Ian St Noble Park VIC 3174",
    "addr:housenumber":"7",
    "addr:postcode":"3174",
    "addr:street":"Ian St",
    "iso:country":"AU",
    "sg:address":"7 Ian St",
    "sg:city":"Noble Park",
    "sg:classifiers":[
        {
            "category":"Food & Beverages",
            "subcategory":"Meat & Fish",
            "type":"Retail Goods"
        }
    ],
    "sg:phone":"+61 3 9547 3396",
    "sg:postcode":"3174",
    "sg:province":"VIC",
    "sg:tags":[
        "seafood"
    ],
    "wof:name":"Arabatzis J",
    "wof:placetype":"venue"
},
  "geometry": {"coordinates":[145.17689514200001,-37.966342926],"type":"Point"}
}