{
  "type": "Feature",
  "properties": {
    "addr:full":"97 Gloucester Crs Rockingham WA 6168",
    "addr:housenumber":"97",
    "addr:postcode":"6168",
    "addr:street":"Gloucester Crs",
    "iso:country":"AU",
    "sg:address":"97 Gloucester Crs",
    "sg:city":"Rockingham",
    "sg:classifiers":[
        {
            "category":"Home & Garden",
            "subcategory":"Building Materials",
            "type":"Retail Goods"
        }
    ],
    "sg:phone":"+61 8 9529 2062",
    "sg:postcode":"6168",
    "sg:province":"WA",
    "sg:tags":[
        "secondhand"
    ],
    "wof:name":"Nateis Contracting",
    "wof:placetype":"venue"
},
  "geometry": {"coordinates":[115.704842,-32.292522],"type":"Point"}
}