{
  "type": "Feature",
  "properties": {
    "addr:full":"Ground Floor 29 Crombie Ave Bundall QLD 4217",
    "addr:housenumber":"29",
    "addr:postcode":"4217",
    "addr:street":"Crombie Ave",
    "iso:country":"AU",
    "sg:address":"Ground Floor 29 Crombie Ave",
    "sg:city":"Bundall",
    "sg:classifiers":[
        {
            "category":"Real Estate",
            "subcategory":"Real Estate Agent",
            "type":"Services"
        }
    ],
    "sg:phone":"+61 7 5574 1544",
    "sg:postcode":"4217",
    "sg:province":"QLD",
    "wof:name":"Coldwell Banker Chateaux Realty",
    "wof:placetype":"venue"
},
  "geometry": {"coordinates":[153.41244506800001,-28.0029888153],"type":"Point"}
}