{
  "type": "Feature",
  "properties": {
    "iso:country":"AU",
    "sg:address":"21c Murray St",
    "sg:city":"Kingscote",
    "sg:classifiers":[
        {
            "category":"Education",
            "subcategory":"University",
            "type":"Public Place"
        }
    ],
    "sg:phone":"+61 8 8553 2244",
    "sg:postcode":"5223",
    "sg:province":"SA",
    "sg:tags":[
        "sewing",
        "dressmaking",
        "tuition"
    ],
    "wof:name":"Island Sewing Centre",
    "wof:placetype":"venue"
},
  "geometry": {"coordinates":[137.636260986,-35.6542701721],"type":"Point"}
}