{
  "type": "Feature",
  "properties": {
    "addr:full":"243 Rockingham Rd Spearwood WA 6163",
    "addr:housenumber":"243",
    "addr:postcode":"6163",
    "addr:street":"Rockingham Rd",
    "iso:country":"AU",
    "sg:address":"243 Rockingham Rd",
    "sg:city":"Spearwood",
    "sg:classifiers":[
        {
            "category":"Health Services",
            "subcategory":"Chiropractor",
            "type":"Services"
        }
    ],
    "sg:phone":"+61 8 9418 6233",
    "sg:postcode":"6163",
    "sg:province":"WA",
    "wof:name":"Crothers Amy",
    "wof:placetype":"venue"
},
  "geometry": {"coordinates":[115.7826,-32.095547],"type":"Point"}
}