{
  "type": "Feature",
  "properties": {
    "addr:full":"111 Victoria St Mackay QLD 4740",
    "addr:housenumber":"111",
    "addr:postcode":"4740",
    "addr:street":"Victoria St",
    "iso:country":"AU",
    "sg:address":"111 Victoria St",
    "sg:city":"Mackay",
    "sg:classifiers":[
        {
            "category":"Professional",
            "subcategory":"Business Services",
            "type":"Services"
        }
    ],
    "sg:phone":"+61 7 4957 7808",
    "sg:postcode":"4740",
    "sg:province":"QLD",
    "sg:tags":[
        "management",
        "event"
    ],
    "wof:name":"On Q Events",
    "wof:placetype":"venue"
},
  "geometry": {"coordinates":[149.18485999999999,-21.141268],"type":"Point"}
}