{
  "type": "Feature",
  "properties": {
    "iso:country":"AU",
    "sg:address":"Shop 31 Central Cafes Precinct",
    "sg:city":"South Bank",
    "sg:classifiers":[
        {
            "category":"Food & Beverages",
            "subcategory":"Bakery",
            "type":"Retail Goods"
        }
    ],
    "sg:phone":"+61 7 3846 2599",
    "sg:postcode":"4101",
    "sg:province":"QLD",
    "sg:tags":[
        "baker"
    ],
    "wof:name":"Brumby's GO!",
    "wof:placetype":"venue"
},
  "geometry": {"coordinates":[153.02061462399999,-27.477519989],"type":"Point"}
}