{
  "type": "Feature",
  "properties": {
    "addr:full":"23 Aspendale Pl Hillarys WA 6025",
    "addr:housenumber":"23",
    "addr:postcode":"6025",
    "addr:street":"Pl",
    "iso:country":"AU",
    "sg:address":"23 Aspendale Pl",
    "sg:city":"Hillarys",
    "sg:classifiers":[
        {
            "category":"Professional",
            "subcategory":"Business Services",
            "type":"Services"
        }
    ],
    "sg:phone":"+61 8 9401 7310",
    "sg:postcode":"6025",
    "sg:province":"WA",
    "sg:tags":[
        "drafting"
    ],
    "wof:name":"K & K Drafting Service",
    "wof:placetype":"venue"
},
  "geometry": {"coordinates":[115.74028778100001,-31.8088302612],"type":"Point"}
}