{
  "type": "Feature",
  "properties": {
    "iso:country":"AU",
    "sg:address":"55 Collins St",
    "sg:city":"Melbourne",
    "sg:classifiers":[
        {
            "category":"Banks & Credit Unions",
            "subcategory":"Investment Brokerage",
            "type":"Services"
        }
    ],
    "sg:phone":"+61 3 9650 2888",
    "sg:postcode":"3000",
    "sg:province":"VIC",
    "wof:name":"Clark C G & Associates Pty Ltd",
    "wof:placetype":"venue"
},
  "geometry": {"coordinates":[144.971633911,-37.814125061],"type":"Point"}
}