{
  "type": "Feature",
  "properties": {
    "addr:full":"107 Canberra Ave Manuka ACT 2603",
    "addr:housenumber":"107",
    "addr:postcode":"2603",
    "addr:street":"Canberra Ave",
    "iso:country":"AU",
    "sg:address":"107 Canberra Ave",
    "sg:city":"Manuka",
    "sg:classifiers":[
        {
            "category":"Travel",
            "subcategory":"Hotels & Motels",
            "type":"Entertainment"
        }
    ],
    "sg:phone":"+61 2 6295 2711",
    "sg:postcode":"2603",
    "sg:province":"ACT",
    "wof:name":"Canberra City Motor Inn",
    "wof:placetype":"venue"
},
  "geometry": {"coordinates":[149.14532470699999,-35.3216934204],"type":"Point"}
}