{
  "type": "Feature",
  "properties": {
    "iso:country":"AU",
    "sg:address":"35 Williams St",
    "sg:city":"Chatswood",
    "sg:classifiers":[
        {
            "category":"Utilities",
            "subcategory":"Refuse",
            "type":"Services"
        }
    ],
    "sg:phone":"+61 2 9419 6655",
    "sg:postcode":"2067",
    "sg:province":"NSW",
    "sg:tags":[
        "remover",
        "rubbish"
    ],
    "wof:name":"Redlich The Rubbisher",
    "wof:placetype":"venue"
},
  "geometry": {"coordinates":[151.18635559099999,-33.7869796753],"type":"Point"}
}