{
  "type": "Feature",
  "properties": {
    "iso:country":"AU",
    "sg:address":"468 King Georges Rd",
    "sg:city":"Beverly Hills",
    "sg:classifiers":[
        {
            "category":"Shopping",
            "subcategory":"Bicycles & Sporting Goods",
            "type":"Retail Goods"
        }
    ],
    "sg:phone":"+61 2 9502 1444",
    "sg:postcode":"2209",
    "sg:province":"NSW",
    "sg:tags":[
        "chemical",
        "equipment",
        "pool",
        "swimming"
    ],
    "wof:name":"One Stop Pool Shop",
    "wof:placetype":"venue"
},
  "geometry": {"coordinates":[151.08029199999999,-33.948486],"type":"Point"}
}