{
  "type": "Feature",
  "properties": {
    "addr:full":"PO Box 823 Cowes VIC 3922",
    "addr:postcode":"3922",
    "iso:country":"AU",
    "sg:address":"PO Box 823",
    "sg:city":"Cowes",
    "sg:classifiers":[
        {
            "category":"Utilities",
            "subcategory":"Electric",
            "type":"Services"
        }
    ],
    "sg:phone":"+61 418 542 749",
    "sg:postcode":"3922",
    "sg:province":"VIC",
    "sg:tags":[
        "electrical",
        "contractor"
    ],
    "wof:name":"Anthony Susic",
    "wof:placetype":"venue"
},
  "geometry": {"coordinates":[145.23898315400001,-38.4565200806],"type":"Point"}
}