{
  "type": "Feature",
  "properties": {
    "addr:full":"121 Blackwood Ave Augusta WA 6290",
    "addr:housenumber":"121",
    "addr:postcode":"6290",
    "addr:street":"Blackwood Ave",
    "iso:country":"AU",
    "sg:address":"121 Blackwood Ave",
    "sg:city":"Augusta",
    "sg:classifiers":[
        {
            "category":"Food & Beverages",
            "subcategory":"Bakery",
            "type":"Retail Goods"
        }
    ],
    "sg:phone":"+61 8 9758 1664",
    "sg:postcode":"6290",
    "sg:province":"WA",
    "sg:tags":[
        "baker"
    ],
    "wof:name":"Augusta Bakery",
    "wof:placetype":"venue"
},
  "geometry": {"coordinates":[115.158821106,-34.3136940002],"type":"Point"}
}