{
  "type": "Feature",
  "properties": {
    "iso:country":"AU",
    "sg:address":"97a Seaview Rd",
    "sg:city":"Yatala Vale",
    "sg:classifiers":[
        {
            "category":"Health Services",
            "subcategory":"Dentist",
            "type":"Services"
        }
    ],
    "sg:phone":"+61 8 8251 1525",
    "sg:postcode":"5126",
    "sg:province":"SA",
    "sg:tags":[
        "technician",
        "dental"
    ],
    "wof:name":"Adelaide Dental Ceramics",
    "wof:placetype":"venue"
},
  "geometry": {"coordinates":[138.74761962900001,-34.7852935791],"type":"Point"}
}