{
  "type": "Feature",
  "properties": {
    "addr:full":"2 Avoca St South Yarra VIC 3141",
    "addr:housenumber":"2",
    "addr:postcode":"3141",
    "addr:street":"Avoca St",
    "iso:country":"AU",
    "sg:address":"2 Avoca St",
    "sg:city":"South Yarra",
    "sg:classifiers":[
        {
            "category":"Shopping",
            "subcategory":"Clothing, Apparel, & Fashions",
            "type":"Retail Goods"
        }
    ],
    "sg:phone":"+61 3 9866 5744",
    "sg:postcode":"3141",
    "sg:province":"VIC",
    "sg:tags":[
        "lady",
        "wear"
    ],
    "wof:name":"Bell Book & Candle Boutique",
    "wof:placetype":"venue"
},
  "geometry": {"coordinates":[144.98927307100001,-37.8384933472],"type":"Point"}
}