{
  "type": "Feature",
  "properties": {
    "addr:full":"RMB 1218 Yarramalong Rd Wyong NSW 2259",
    "addr:postcode":"2259",
    "addr:street":"Yarramalong Rd",
    "iso:country":"AU",
    "sg:address":"RMB 1218 Yarramalong Rd",
    "sg:city":"Wyong",
    "sg:classifiers":[
        {
            "category":"Manufacturing",
            "subcategory":"Lumber",
            "type":"Manufacturing & Wholesale Goods"
        }
    ],
    "sg:phone":"+61 2 4356 1059",
    "sg:postcode":"2259",
    "sg:province":"NSW",
    "sg:tags":[
        "sawmillers"
    ],
    "wof:name":"Bradleys Sawmilling",
    "wof:placetype":"venue"
},
  "geometry": {"coordinates":[151.33111572300001,-33.2568359375],"type":"Point"}
}