{
  "type": "Feature",
  "properties": {
    "addr:full":"11 High St Burnside SA 5066",
    "addr:housenumber":"11",
    "addr:postcode":"5066",
    "addr:street":"High St",
    "iso:country":"AU",
    "sg:address":"11 High St",
    "sg:city":"Burnside",
    "sg:classifiers":[
        {
            "category":"Education",
            "subcategory":"School",
            "type":"Public Place"
        }
    ],
    "sg:phone":"+61 8 8331 7512",
    "sg:postcode":"5066",
    "sg:province":"SA",
    "sg:tags":[
        "state",
        "except",
        "nsw"
    ],
    "wof:name":"Burnside Primary",
    "wof:placetype":"venue"
},
  "geometry": {"coordinates":[138.662841797,-34.9362182617],"type":"Point"}
}