{
  "type": "Feature",
  "properties": {
    "addr:full":"Verdelho Drv The Vines WA 6069",
    "addr:postcode":"6069",
    "addr:street":"Verdelho Drv",
    "iso:country":"AU",
    "sg:address":"Verdelho Drv",
    "sg:city":"The Vines",
    "sg:classifiers":[
        {
            "category":"Restaurant",
            "type":"Food & Drink"
        }
    ],
    "sg:phone":"+61 8 9297 0209",
    "sg:postcode":"6069",
    "sg:province":"WA",
    "wof:name":"Copley's Bistro",
    "wof:placetype":"venue"
},
  "geometry": {"coordinates":[116.005828857,-31.7660369873],"type":"Point"}
}