{
  "type": "Feature",
  "properties": {
    "addr:full":"109 Rankin St Forbes NSW 2871",
    "addr:housenumber":"109",
    "addr:postcode":"2871",
    "addr:street":"Rankin St",
    "iso:country":"AU",
    "sg:address":"109 Rankin St",
    "sg:city":"Forbes",
    "sg:classifiers":[
        {
            "category":"Organizations",
            "subcategory":"Community Association",
            "type":"Services"
        }
    ],
    "sg:phone":"+61 2 6852 1865",
    "sg:postcode":"2871",
    "sg:province":"NSW",
    "sg:tags":[
        "organisation",
        "family",
        "welfare"
    ],
    "wof:name":"St Vincent de Paul Society",
    "wof:placetype":"venue"
},
  "geometry": {"coordinates":[148.00636299999999,-33.384392],"type":"Point"}
}