{
  "type": "Feature",
  "properties": {
    "addr:full":"Rivendel Drv Tweed Heads NSW 2485",
    "addr:postcode":"2485",
    "addr:street":"Rivendel Drv",
    "iso:country":"AU",
    "sg:address":"Rivendel Drv",
    "sg:city":"Tweed Heads",
    "sg:classifiers":[
        {
            "category":"Utilities",
            "subcategory":"Refuse",
            "type":"Services"
        }
    ],
    "sg:phone":"+61 1800 014 022",
    "sg:postcode":"2485",
    "sg:province":"NSW",
    "sg:tags":[
        "remover",
        "rubbish"
    ],
    "wof:name":"A. 1. Joe Lop Stump Grinding",
    "wof:placetype":"venue"
},
  "geometry": {"coordinates":[153.543045044,-28.2059936523],"type":"Point"}
}