{
  "type": "Feature",
  "properties": {
    "iso:country":"AU",
    "sg:address":"Suite 5, 2 Urquhart St",
    "sg:city":"Parap",
    "sg:classifiers":[
        {
            "category":"Health Services",
            "subcategory":"Doctor",
            "type":"Services"
        }
    ],
    "sg:phone":"+61 8 8981 3355",
    "sg:postcode":"0820",
    "sg:province":"NT",
    "sg:tags":[
        "medical",
        "practitioner"
    ],
    "wof:name":"Skin Alert Skin Cancer Clinics",
    "wof:placetype":"venue"
},
  "geometry": {"coordinates":[130.844146728,-12.4306545258],"type":"Point"}
}