{
  "type": "Feature",
  "properties": {
    "iso:country":"AU",
    "sg:address":"Shop 10, 108 Blaxland Ave",
    "sg:city":"Singleton Heights",
    "sg:classifiers":[
        {
            "category":"Food & Beverages",
            "subcategory":"Supermarket",
            "type":"Retail Goods"
        }
    ],
    "sg:phone":"+61 2 6573 1038",
    "sg:postcode":"2330",
    "sg:province":"NSW",
    "sg:tags":[
        "grocery",
        "store"
    ],
    "wof:name":"Singleton Heights Supermarket & Newsagency",
    "wof:placetype":"venue"
},
  "geometry": {"coordinates":[151.16362,-32.54789],"type":"Point"}
}