{
  "type": "Feature",
  "properties": {
    "iso:country":"AU",
    "sg:address":"Unit22/1161- 1171 Pittwater Rd",
    "sg:city":"Collaroy",
    "sg:classifiers":[
        {
            "category":"Banks & Credit Unions",
            "subcategory":"Bank",
            "type":"Services"
        }
    ],
    "sg:phone":"+61 2 9674 8670",
    "sg:postcode":"2097",
    "sg:province":"NSW",
    "sg:tags":[
        "broker",
        "mortgage"
    ],
    "wof:name":"Money Tree Loan Centre The",
    "wof:placetype":"venue"
},
  "geometry": {"coordinates":[151.299682617,-33.7289505005],"type":"Point"}
}