{
  "type": "Feature",
  "properties": {
    "addr:full":"29 Stud Rd Bayswater VIC 3153",
    "addr:housenumber":"29",
    "addr:postcode":"3153",
    "addr:street":"Stud Rd",
    "iso:country":"AU",
    "sg:address":"29 Stud Rd",
    "sg:city":"Bayswater",
    "sg:classifiers":[
        {
            "category":"Home & Garden",
            "subcategory":"Building Materials",
            "type":"Retail Goods"
        }
    ],
    "sg:phone":"+61 3 9720 1908",
    "sg:postcode":"3153",
    "sg:province":"VIC",
    "sg:tags":[
        "tile",
        "roofing"
    ],
    "sg:website":"http://www.barringtonrooftiles.com.au",
    "wof:name":"Barrington Roof Tiles",
    "wof:placetype":"venue"
},
  "geometry": {"coordinates":[145.24707031200001,-37.8464927673],"type":"Point"}
}