{
  "type": "Feature",
  "properties": {
    "addr:full":"geddes La Melbourne VIC 3000",
    "addr:postcode":"3000",
    "addr:street":"Geddes La",
    "iso:country":"AU",
    "sg:address":"geddes La",
    "sg:city":"Melbourne",
    "sg:classifiers":[
        {
            "category":"Retail",
            "subcategory":"Event Space",
            "type":"Services"
        }
    ],
    "sg:phone":"+61 3 9614 3813",
    "sg:postcode":"3000",
    "sg:province":"VIC",
    "sg:tags":[
        "function",
        "organiser"
    ],
    "sg:website":"http://www.geddeslounge.com.au",
    "wof:name":"Geddes Lounge",
    "wof:placetype":"venue"
},
  "geometry": {"coordinates":[144.95741272000001,-37.8190116882],"type":"Point"}
}