{
  "type": "Feature",
  "properties": {
    "addr:full":"31 Ilfracombe Rd Longreach QLD 4730",
    "addr:housenumber":"31",
    "addr:postcode":"4730",
    "addr:street":"Ilfracombe Rd",
    "iso:country":"AU",
    "sg:address":"31 Ilfracombe Rd",
    "sg:city":"Longreach",
    "sg:classifiers":[
        {
            "category":"Shopping",
            "subcategory":"Pets & Pet Supplies",
            "type":"Retail Goods"
        }
    ],
    "sg:phone":"+61 7 4658 3100",
    "sg:postcode":"4730",
    "sg:province":"QLD",
    "sg:tags":[
        "sheep",
        "equipment",
        "shearing"
    ],
    "wof:name":"Shear-fix",
    "wof:placetype":"venue"
},
  "geometry": {"coordinates":[144.26364100000001,-23.440847],"type":"Point"}
}