{
  "type": "Feature",
  "properties": {
    "addr:full":"Unit 4/ 3 Paisley Drv Lawnton QLD 4501",
    "addr:housenumber":"3",
    "addr:postcode":"4501",
    "addr:street":"Paisley Drv",
    "iso:country":"AU",
    "sg:address":"Unit 4/ 3 Paisley Drv",
    "sg:city":"Lawnton",
    "sg:classifiers":[
        {
            "category":"Building & Trades",
            "subcategory":"Construction",
            "type":"Services"
        }
    ],
    "sg:phone":"+61 7 3881 3588",
    "sg:postcode":"4501",
    "sg:province":"QLD",
    "sg:tags":[
        "ceiling"
    ],
    "wof:name":"Gyprock Service Centre",
    "wof:placetype":"venue"
},
  "geometry": {"coordinates":[152.98846435600001,-27.288898468],"type":"Point"}
}