{
  "type": "Feature",
  "properties": {
    "iso:country":"AU",
    "sg:address":"Shop 12",
    "sg:city":", Clifton Village, Capt Cook Hwy, Clifton Bea",
    "sg:classifiers":[
        {
            "category":"Health Services",
            "subcategory":"Doctor",
            "type":"Services"
        }
    ],
    "sg:phone":"+61 7 4059 1755",
    "sg:postcode":"4879",
    "sg:province":"QLD",
    "sg:tags":[
        "medical",
        "practitioner"
    ],
    "wof:name":"Clifton Beach Medical & Surgical",
    "wof:placetype":"venue"
},
  "geometry": {"coordinates":[145.67047119099999,-16.7694072723],"type":"Point"}
}