{
  "type": "Feature",
  "properties": {
    "iso:country":"AU",
    "sg:address":"32a Frater Ave",
    "sg:city":"Tenambit",
    "sg:classifiers":[
        {
            "category":"Retail",
            "subcategory":"Repair Shop",
            "type":"Services"
        }
    ],
    "sg:phone":"+61 2 4934 2804",
    "sg:postcode":"2323",
    "sg:province":"NSW",
    "sg:tags":[
        "upholsterer"
    ],
    "wof:name":"Colourscope Upholstery Service Pty Ltd",
    "wof:placetype":"venue"
},
  "geometry": {"coordinates":[151.60809326200001,-32.7385177612],"type":"Point"}
}