{
  "type": "Feature",
  "properties": {
    "iso:country":"AU",
    "sg:address":"3 Arkaba Rd",
    "sg:city":"Kilkenny",
    "sg:classifiers":[
        {
            "category":"Community Center",
            "subcategory":"Ethnic",
            "type":"Public Place"
        }
    ],
    "sg:phone":"+61 8 8345 1922",
    "sg:postcode":"5009",
    "sg:province":"SA",
    "sg:tags":[
        "wood",
        "carver"
    ],
    "wof:name":"Tonroy Carving Products",
    "wof:placetype":"venue"
},
  "geometry": {"coordinates":[138.55073547399999,-34.8851737976],"type":"Point"}
}