{
  "type": "Feature",
  "properties": {
    "iso:country":"AU",
    "sg:address":"Shop 78 Lyons Rd",
    "sg:city":"Drummoyne",
    "sg:classifiers":[
        {
            "category":"Building & Trades",
            "subcategory":"Locksmith",
            "type":"Services"
        }
    ],
    "sg:phone":"+61 1300 247 247",
    "sg:postcode":"2047",
    "sg:province":"NSW",
    "sg:tags":[
        "lock"
    ],
    "wof:name":"Sydney Locksmiths",
    "wof:placetype":"venue"
},
  "geometry": {"coordinates":[151.150925,-33.853291],"type":"Point"}
}