{
  "type": "Feature",
  "properties": {
    "addr:full":"170 Liebig St Warrnambool VIC 3280",
    "addr:housenumber":"170",
    "addr:postcode":"3280",
    "addr:street":"Liebig St",
    "iso:country":"AU",
    "sg:address":"170 Liebig St",
    "sg:city":"Warrnambool",
    "sg:classifiers":[
        {
            "category":"Industrial Area",
            "type":"Public Place"
        }
    ],
    "sg:phone":"+61 3 5561 6222",
    "sg:postcode":"3280",
    "sg:province":"VIC",
    "sg:tags":[
        "protective",
        "clothing"
    ],
    "wof:name":"The T Shirt Shop",
    "wof:placetype":"venue"
},
  "geometry": {"coordinates":[142.485305786,-38.3816642761],"type":"Point"}
}