{
  "type": "Feature",
  "properties": {
    "addr:full":"Shop 6, 12- 14 Lawrence St Harbord NSW 2096",
    "addr:housenumber":"shop;12 14",
    "addr:postcode":"2096",
    "addr:street":"Lawrence St",
    "iso:country":"AU",
    "sg:address":"Shop 6, 12- 14 Lawrence St",
    "sg:city":"Harbord",
    "sg:classifiers":[
        {
            "category":"Personal",
            "subcategory":"Beauty Salon",
            "type":"Services"
        }
    ],
    "sg:phone":"+61 2 9939 3959",
    "sg:postcode":"2096",
    "sg:province":"NSW",
    "sg:tags":[
        "hairdresser"
    ],
    "wof:name":"baseOne Hair Design",
    "wof:placetype":"venue"
},
  "geometry": {"coordinates":[151.284545898,-33.779006958],"type":"Point"}
}