{
  "type": "Feature",
  "properties": {
    "addr:full":"Cnr Princes Hwy & South St Kogarah NSW 2217",
    "addr:postcode":"2217",
    "addr:street":"Cnr Princes Hwy & South St",
    "iso:country":"AU",
    "sg:address":"Cnr Princes Hwy & South St",
    "sg:city":"Kogarah",
    "sg:classifiers":[
        {
            "category":"Home & Garden",
            "subcategory":"Carpets & Floor Coverings",
            "type":"Retail Goods"
        }
    ],
    "sg:phone":"+61 2 9588 6033",
    "sg:postcode":"2217",
    "sg:province":"NSW",
    "sg:tags":[
        "layer"
    ],
    "wof:name":"Wholesale Carpet Court",
    "wof:placetype":"venue"
},
  "geometry": {"coordinates":[151.13267500000001,-33.963169],"type":"Point"}
}