{
  "type": "Feature",
  "properties": {
    "iso:country":"AU",
    "sg:address":"329 Hume Hwy",
    "sg:city":"Lansvale",
    "sg:classifiers":[
        {
            "category":"Health Services",
            "subcategory":"Dentist",
            "type":"Services"
        }
    ],
    "sg:phone":"+61 2 9725 6241",
    "sg:postcode":"2166",
    "sg:province":"NSW",
    "wof:name":"Sakoutis George",
    "wof:placetype":"venue"
},
  "geometry": {"coordinates":[150.94554138199999,-33.900188446],"type":"Point"}
}