{
  "type": "Feature",
  "properties": {
    "iso:country":"AU",
    "sg:address":"PO Box 262",
    "sg:city":"Lilydale",
    "sg:classifiers":[
        {
            "category":"Home & Garden",
            "subcategory":"Household Appliances",
            "type":"Retail Goods"
        }
    ],
    "sg:phone":"+61 3 9735 3965",
    "sg:postcode":"3140",
    "sg:province":"VIC",
    "sg:tags":[
        "heating",
        "system"
    ],
    "wof:name":"Warmtech Heating Systems",
    "wof:placetype":"venue"
},
  "geometry": {"coordinates":[145.37161254899999,-37.7617797852],"type":"Point"}
}