{
  "type": "Feature",
  "properties": {
    "addr:full":"190 Wells St South Melbourne VIC 3205",
    "addr:housenumber":"190",
    "addr:postcode":"3205",
    "addr:street":"Wells St",
    "iso:country":"AU",
    "sg:address":"190 Wells St",
    "sg:city":"South Melbourne",
    "sg:classifiers":[
        {
            "category":"Cafe",
            "type":"Food & Drink"
        }
    ],
    "sg:phone":"+61 3 9686 1109",
    "sg:postcode":"3205",
    "sg:province":"VIC",
    "wof:name":"Peko Peko",
    "wof:placetype":"venue"
},
  "geometry": {"coordinates":[144.970078,-37.831963],"type":"Point"}
}