{
  "type": "Feature",
  "properties": {
    "addr:full":"7 Daphne St Prospect SA 5082",
    "addr:housenumber":"7",
    "addr:postcode":"5082",
    "addr:street":"Daphne St",
    "iso:country":"AU",
    "sg:address":"7 Daphne St",
    "sg:city":"Prospect",
    "sg:classifiers":[
        {
            "category":"Manufacturing",
            "subcategory":"Musical Instruments",
            "type":"Manufacturing & Wholesale Goods"
        }
    ],
    "sg:phone":"+61 8 8344 9661",
    "sg:postcode":"5082",
    "sg:province":"SA",
    "sg:tags":[
        "repair",
        "maker"
    ],
    "wof:name":"F.M. Audio Services",
    "wof:placetype":"venue"
},
  "geometry": {"coordinates":[138.593215942,-34.8904724121],"type":"Point"}
}