{
  "type": "Feature",
  "properties": {
    "addr:full":"15 Sanyo Drv Wodonga VIC 3689",
    "addr:housenumber":"15",
    "addr:postcode":"3689",
    "addr:street":"Sanyo Drv",
    "iso:country":"AU",
    "sg:address":"15 Sanyo Drv",
    "sg:city":"Wodonga",
    "sg:classifiers":[
        {
            "category":"Home & Garden",
            "subcategory":"Hardware",
            "type":"Retail Goods"
        }
    ],
    "sg:phone":"+61 2 6024 5922",
    "sg:postcode":"3689",
    "sg:province":"VIC",
    "sg:tags":[
        "repair",
        "tool",
        "power"
    ],
    "wof:name":"One Stop Industrial & Safety Supplies",
    "wof:placetype":"venue"
},
  "geometry": {"coordinates":[146.901535,-36.125004],"type":"Point"}
}