{
  "type": "Feature",
  "properties": {
    "iso:country":"AU",
    "sg:address":"45 Pakington St",
    "sg:city":"Geelong West",
    "sg:classifiers":[
        {
            "category":"Real Estate",
            "subcategory":"Surveying",
            "type":"Services"
        }
    ],
    "sg:phone":"+61 3 5229 3788",
    "sg:postcode":"3218",
    "sg:province":"VIC",
    "sg:tags":[
        "surveyor",
        "land"
    ],
    "wof:name":"Martin Rodney & Associates Pty Ltd",
    "wof:placetype":"venue"
},
  "geometry": {"coordinates":[144.34930419899999,-38.1345748901],"type":"Point"}
}