{
  "type": "Feature",
  "properties": {
    "addr:full":"Shop 3041 Highpoint West Shopping Centre Rosamond Rd Maribyrnong VIC 3032",
    "addr:housenumber":"3041",
    "addr:postcode":"3032",
    "addr:street":"Highpoint West;Rosamond Rd",
    "iso:country":"AU",
    "sg:address":"Shop 3041 Highpoint West Shopping Centre Rosamond Rd",
    "sg:city":"Maribyrnong",
    "sg:classifiers":[
        {
            "category":"Shopping",
            "subcategory":"Clothing, Apparel, & Fashions",
            "type":"Retail Goods"
        }
    ],
    "sg:phone":"+61 3 9317 7147",
    "sg:postcode":"3032",
    "sg:province":"VIC",
    "sg:tags":[
        "lady",
        "wear"
    ],
    "wof:name":"Colorado Adventurewear",
    "wof:placetype":"venue"
},
  "geometry": {"coordinates":[144.88632200000001,-37.771435],"type":"Point"}
}