{
  "type": "Feature",
  "properties": {
    "iso:country":"AU",
    "sg:address":"3606 Oakey-Cooyar Rd",
    "sg:city":"Peregian",
    "sg:classifiers":[
        {
            "category":"Utilities",
            "subcategory":"Water",
            "type":"Services"
        }
    ],
    "sg:phone":"+61 417 757 214",
    "sg:postcode":"4561",
    "sg:province":"QLD",
    "sg:tags":[
        "cartage"
    ],
    "wof:name":"Graham Powell",
    "wof:placetype":"venue"
},
  "geometry": {"coordinates":[152.99111938499999,-26.5447597504],"type":"Point"}
}