{
  "type": "Feature",
  "properties": {
    "addr:full":"Lvl 13 110 Collins St Hobart TAS 7000",
    "addr:housenumber":"110",
    "addr:postcode":"7000",
    "addr:street":"Collins St",
    "iso:country":"AU",
    "sg:address":"Lvl 13 110 Collins St",
    "sg:city":"Hobart",
    "sg:classifiers":[
        {
            "category":"Professional",
            "subcategory":"Computer Services",
            "type":"Services"
        }
    ],
    "sg:phone":"+61 419 503 198",
    "sg:postcode":"7000",
    "sg:province":"TAS",
    "sg:tags":[
        "consultant",
        "system"
    ],
    "wof:name":"TasIT (Tasmanian Information Technology & Telecommunications Industry Developmen",
    "wof:placetype":"venue"
},
  "geometry": {"coordinates":[147.32864379899999,-42.8824806213],"type":"Point"}
}