{
  "type": "Feature",
  "properties": {
    "addr:full":"96 Minjungbal Drv Tweed Heads South QLD 2486",
    "addr:housenumber":"96",
    "addr:postcode":"2486",
    "addr:street":"Minjungbal Drv",
    "iso:country":"AU",
    "sg:address":"96 Minjungbal Drv",
    "sg:city":"Tweed Heads South",
    "sg:classifiers":[
        {
            "category":"Autos & Motor Vehicles",
            "subcategory":"Automobile Sales",
            "type":"Retail Goods"
        }
    ],
    "sg:phone":"+61 7 5523 0011",
    "sg:postcode":"2486",
    "sg:province":"QLD",
    "sg:tags":[
        "car",
        "used"
    ],
    "wof:name":"Brenlee Motors",
    "wof:placetype":"venue"
},
  "geometry": {"coordinates":[153.544647217,-28.2044658661],"type":"Point"}
}