{
  "type": "Feature",
  "properties": {
    "iso:country":"AU",
    "sg:address":"19 John St",
    "sg:city":"Lawson",
    "sg:classifiers":[
        {
            "category":"Wholesale",
            "subcategory":"Furniture",
            "type":"Manufacturing & Wholesale Goods"
        }
    ],
    "sg:phone":"+61 2 4759 2344",
    "sg:postcode":"2783",
    "sg:province":"NSW",
    "sg:tags":[
        "wholesaler",
        "mfrs"
    ],
    "wof:name":"Olori Furniture Pty Ltd",
    "wof:placetype":"venue"
},
  "geometry": {"coordinates":[150.43484497099999,-33.7234764099],"type":"Point"}
}