{
  "type": "Feature",
  "properties": {
    "iso:country":"AU",
    "sg:address":"24 Leichardt St",
    "sg:city":"Beaufort",
    "sg:classifiers":[
        {
            "category":"Building & Trades",
            "subcategory":"Plumbing",
            "type":"Services"
        }
    ],
    "sg:phone":"+61 418 149 834",
    "sg:postcode":"3373",
    "sg:province":"VIC",
    "sg:tags":[
        "plumber",
        "gasfitters"
    ],
    "wof:name":"Beaufort Plumbing & Gasfitting",
    "wof:placetype":"venue"
},
  "geometry": {"coordinates":[143.38404846200001,-37.4309501648],"type":"Point"}
}