{
  "type": "Feature",
  "properties": {
    "addr:full":"27 Ninth St Wingfield SA 5013",
    "addr:housenumber":"27",
    "addr:postcode":"5013",
    "addr:street":"Ninth St",
    "iso:country":"AU",
    "sg:address":"27 Ninth St",
    "sg:city":"Wingfield",
    "sg:classifiers":[
        {
            "category":"Building & Trades",
            "subcategory":"Equipment Rental",
            "type":"Services"
        }
    ],
    "sg:phone":"+61 8 8243 2211",
    "sg:postcode":"5013",
    "sg:province":"SA",
    "sg:tags":[
        "renting",
        "trailer"
    ],
    "wof:name":"Maxitrans Australia Pty Ltd",
    "wof:placetype":"venue"
},
  "geometry": {"coordinates":[138.556030273,-34.8381958008],"type":"Point"}
}