{
  "type": "Feature",
  "properties": {
    "iso:country":"AU",
    "sg:address":"Willison Rd",
    "sg:city":"Bexley",
    "sg:classifiers":[
        {
            "category":"Building & Trades",
            "subcategory":"Plumbing",
            "type":"Services"
        }
    ],
    "sg:phone":"+61 2 9588 4304",
    "sg:postcode":"2207",
    "sg:province":"NSW",
    "sg:tags":[
        "plumber",
        "gasfitters"
    ],
    "wof:name":"Bardwell Park & Bexley Plumbing",
    "wof:placetype":"venue"
},
  "geometry": {"coordinates":[151.11730957,-33.9600601196],"type":"Point"}
}