{
  "type": "Feature",
  "properties": {
    "addr:full":"2 Scott Crs Mildura VIC 3500",
    "addr:housenumber":"2",
    "addr:postcode":"3500",
    "addr:street":"Scott Crs",
    "iso:country":"AU",
    "sg:address":"2 Scott Crs",
    "sg:city":"Mildura",
    "sg:classifiers":[
        {
            "category":"Building & Trades",
            "subcategory":"Equipment Rental",
            "type":"Services"
        }
    ],
    "sg:phone":"+61 3 5023 4677",
    "sg:postcode":"3500",
    "sg:province":"VIC",
    "sg:tags":[
        "party",
        "hire"
    ],
    "wof:name":"Burrells Mildura Party Hire",
    "wof:placetype":"venue"
},
  "geometry": {"coordinates":[142.154098511,-34.2107391357],"type":"Point"}
}