{
  "type": "Feature",
  "properties": {
    "addr:full":"30 Mansfield Ave Caringbah NSW 2229",
    "addr:housenumber":"30",
    "addr:postcode":"2229",
    "addr:street":"Mansfield Ave",
    "iso:country":"AU",
    "sg:address":"30 Mansfield Ave",
    "sg:city":"Caringbah",
    "sg:classifiers":[
        {
            "category":"Personal",
            "subcategory":"Beauty Salon",
            "type":"Services"
        }
    ],
    "sg:phone":"+61 2 9525 7775",
    "sg:postcode":"2229",
    "sg:province":"NSW",
    "sg:tags":[
        "hairdresser"
    ],
    "wof:name":"D&#039;Ambra John",
    "wof:placetype":"venue"
},
  "geometry": {"coordinates":[151.12376403799999,-34.0442695618],"type":"Point"}
}