{
  "type": "Feature",
  "properties": {
    "iso:country":"AU",
    "sg:address":"1 Heffron Rd",
    "sg:city":"Pagewood",
    "sg:classifiers":[
        {
            "category":"Health Services",
            "subcategory":"Doctor",
            "type":"Services"
        }
    ],
    "sg:phone":"+61 2 9349 3596",
    "sg:postcode":"2035",
    "sg:province":"NSW",
    "sg:tags":[
        "medical",
        "practitioner"
    ],
    "wof:name":"McDonogh W P",
    "wof:placetype":"venue"
},
  "geometry": {"coordinates":[151.22821044899999,-33.9399261475],"type":"Point"}
}