{
  "type": "Feature",
  "properties": {
    "addr:full":"PO Box 367 Greenacre NSW 2190",
    "addr:postcode":"2190",
    "iso:country":"AU",
    "sg:address":"PO Box 367",
    "sg:city":"Greenacre",
    "sg:classifiers":[
        {
            "category":"Building & Trades",
            "subcategory":"Construction",
            "type":"Services"
        }
    ],
    "sg:phone":"+61 417 283 094",
    "sg:postcode":"2190",
    "sg:province":"NSW",
    "sg:tags":[
        "rendering",
        "cement"
    ],
    "wof:name":"Hi Tech Rendering Pty Ltd",
    "wof:placetype":"venue"
},
  "geometry": {"coordinates":[151.06634521500001,-33.895401001],"type":"Point"}
}