{
  "type": "Feature",
  "properties": {
    "iso:country":"AU",
    "sg:address":"1 Bay St",
    "sg:city":"Port Macquarie",
    "sg:classifiers":[
        {
            "category":"Autos & Motor Vehicles",
            "subcategory":"Fuel & Gas Station",
            "type":"Retail Goods"
        }
    ],
    "sg:phone":"+61 2 6583 2117",
    "sg:postcode":"2444",
    "sg:province":"NSW",
    "wof:name":"Woolworths Plus Petrol",
    "wof:placetype":"venue"
},
  "geometry": {"coordinates":[152.89323400000001,-31.429144],"type":"Point"}
}