{
  "type": "Feature",
  "properties": {
    "iso:country":"AU",
    "sg:address":"370 Dean St",
    "sg:city":"Rockhampton",
    "sg:classifiers":[
        {
            "category":"Autos & Motor Vehicles",
            "subcategory":"Automobile Sales",
            "type":"Retail Goods"
        }
    ],
    "sg:phone":"+61 7 4926 6866",
    "sg:postcode":"4700",
    "sg:province":"QLD",
    "sg:tags":[
        "car",
        "new"
    ],
    "wof:name":"Menzies Kia",
    "wof:placetype":"venue"
},
  "geometry": {"coordinates":[150.53733825699999,-23.3484992981],"type":"Point"}
}