{
  "type": "Feature",
  "properties": {
    "addr:full":"Shp1/ 1356 Pittwater Rd Narrabeen NSW 2101",
    "addr:housenumber":"1356",
    "addr:postcode":"2101",
    "addr:street":"Pittwater Rd",
    "iso:country":"AU",
    "sg:address":"Shp1/ 1356 Pittwater Rd",
    "sg:city":"Narrabeen",
    "sg:classifiers":[
        {
            "category":"Fast Food",
            "type":"Food & Drink"
        }
    ],
    "sg:phone":"+61 2 9913 7734",
    "sg:postcode":"2101",
    "sg:province":"NSW",
    "sg:tags":[
        "away",
        "take"
    ],
    "wof:name":"Chickens Plus",
    "wof:placetype":"venue"
},
  "geometry": {"coordinates":[151.29718,-33.715355],"type":"Point"}
}