{
  "type": "Feature",
  "properties": {
    "addr:full":"610 Stanley St South Brisbane QLD 4101",
    "addr:housenumber":"610",
    "addr:postcode":"4101",
    "addr:street":"Stanley St",
    "iso:country":"AU",
    "sg:address":"610 Stanley St",
    "sg:city":"South Brisbane",
    "sg:classifiers":[
        {
            "category":"Professional",
            "subcategory":"Secretarial Services",
            "type":"Services"
        }
    ],
    "sg:phone":"+61 7 3844 9442",
    "sg:postcode":"4101",
    "sg:province":"QLD",
    "sg:tags":[
        "typing"
    ],
    "wof:name":"South Brisbane Commercial Services",
    "wof:placetype":"venue"
},
  "geometry": {"coordinates":[153.02972412099999,-27.4853954315],"type":"Point"}
}