{
  "type": "Feature",
  "properties": {
    "addr:full":"7 Exeter Pl Strathfieldsaye VIC 3551",
    "addr:housenumber":"7",
    "addr:postcode":"3551",
    "addr:street":"Exeter Pl",
    "iso:country":"AU",
    "sg:address":"7 Exeter Pl",
    "sg:city":"Strathfieldsaye",
    "sg:classifiers":[
        {
            "category":"Professional",
            "subcategory":"Art Services",
            "type":"Services"
        }
    ],
    "sg:phone":"+61 417 508 261",
    "sg:postcode":"3551",
    "sg:province":"VIC",
    "sg:tags":[
        "decorator",
        "painter"
    ],
    "wof:name":"Davcar Painting",
    "wof:placetype":"venue"
},
  "geometry": {"coordinates":[144.336395264,-36.7992248535],"type":"Point"}
}