{
  "type": "Feature",
  "properties": {
    "addr:full":"13 Hamilton Pl Mt Waverley VIC 3149",
    "addr:housenumber":"13",
    "addr:postcode":"3149",
    "addr:street":"Hamilton Pl Mt",
    "iso:country":"AU",
    "sg:address":"13 Hamilton Pl",
    "sg:city":"Mt Waverley",
    "sg:classifiers":[
        {
            "category":"Banks & Credit Unions",
            "subcategory":"Investment Brokerage",
            "type":"Services"
        }
    ],
    "sg:phone":"+61 1800 653 061",
    "sg:postcode":"3149",
    "sg:province":"VIC",
    "wof:name":"Commonwealth Financial Planning",
    "wof:placetype":"venue"
},
  "geometry": {"coordinates":[145.127563477,-37.8760070801],"type":"Point"}
}