{
  "type": "Feature",
  "properties": {
    "iso:country":"AU",
    "sg:address":"5 Dolphin Ave",
    "sg:city":"Tin Can Bay",
    "sg:classifiers":[
        {
            "category":"Health Services",
            "subcategory":"Doctor",
            "type":"Services"
        }
    ],
    "sg:phone":"+61 7 5486 4600",
    "sg:postcode":"4580",
    "sg:province":"QLD",
    "sg:tags":[
        "medical",
        "practitioner"
    ],
    "wof:name":"Martin Peter L Dr",
    "wof:placetype":"venue"
},
  "geometry": {"coordinates":[153.00209045400001,-25.9163284302],"type":"Point"}
}