{
  "type": "Feature",
  "properties": {
    "addr:full":"16 Main St Narangba QLD 4504",
    "addr:housenumber":"16",
    "addr:postcode":"4504",
    "addr:street":"Main St",
    "iso:country":"AU",
    "sg:address":"16 Main St",
    "sg:city":"Narangba",
    "sg:classifiers":[
        {
            "category":"Real Estate",
            "subcategory":"Real Estate Agent",
            "type":"Services"
        }
    ],
    "sg:phone":"+61 7 3385 5877",
    "sg:postcode":"4504",
    "sg:province":"QLD",
    "wof:name":"Anne Taplin Real Estate",
    "wof:placetype":"venue"
},
  "geometry": {"coordinates":[152.96107482900001,-27.2039146423],"type":"Point"}
}