{
  "type": "Feature",
  "properties": {
    "addr:full":"Harris St St Marys NSW 2760",
    "addr:postcode":"2760",
    "addr:street":"Harris St",
    "iso:country":"AU",
    "sg:address":"Harris St",
    "sg:city":"St Marys",
    "sg:classifiers":[
        {
            "category":"Retail",
            "subcategory":"Auto Repair",
            "type":"Services"
        }
    ],
    "sg:phone":"+61 2 9623 2373",
    "sg:postcode":"2760",
    "sg:province":"NSW",
    "sg:tags":[
        "repairer",
        "motor",
        "engineer"
    ],
    "wof:name":"Mike O'Connor Mechanical Repairs",
    "wof:placetype":"venue"
},
  "geometry": {"coordinates":[150.77792358400001,-33.7616157532],"type":"Point"}
}