{
  "type": "Feature",
  "properties": {
    "addr:full":"Shop FF 3/4 Centro Bankstown Bankstown NSW 2200",
    "addr:postcode":"2200",
    "iso:country":"AU",
    "sg:address":"Shop FF 3/4 Centro Bankstown",
    "sg:city":"Bankstown",
    "sg:classifiers":[
        {
            "category":"Food & Beverages",
            "subcategory":"Fruits & Vegetables",
            "type":"Retail Goods"
        }
    ],
    "sg:phone":"+61 2 9709 5033",
    "sg:postcode":"2200",
    "sg:province":"NSW",
    "sg:tags":[
        "greengrocer",
        "fruiterer"
    ],
    "wof:name":"Trim's Fresh Fruit Market",
    "wof:placetype":"venue"
},
  "geometry": {"coordinates":[151.034164,-33.914791],"type":"Point"}
}