{
  "type": "Feature",
  "properties": {
    "addr:full":"210 Mulhollands Rd Thirlmere NSW 2572",
    "addr:housenumber":"210",
    "addr:postcode":"2572",
    "addr:street":"Mulhollands Rd",
    "iso:country":"AU",
    "sg:address":"210 Mulhollands Rd",
    "sg:city":"Thirlmere",
    "sg:classifiers":[
        {
            "category":"Food & Beverages",
            "subcategory":"Fruits & Vegetables",
            "type":"Retail Goods"
        }
    ],
    "sg:phone":"+61 2 4681 0766",
    "sg:postcode":"2572",
    "sg:province":"NSW",
    "sg:tags":[
        "wholesale"
    ],
    "wof:name":"Summergold Marketing",
    "wof:placetype":"venue"
},
  "geometry": {"coordinates":[150.572174072,-34.1752128601],"type":"Point"}
}