{
  "type": "Feature",
  "properties": {
    "iso:country":"AU",
    "sg:address":"Hibernia Rd",
    "sg:city":"Capella",
    "sg:classifiers":[
        {
            "category":"Retail",
            "subcategory":"Auto Repair",
            "type":"Services"
        }
    ],
    "sg:phone":"+61 7 4986 4099",
    "sg:postcode":"4702",
    "sg:province":"QLD",
    "sg:tags":[
        "testing",
        "inspection",
        "motor",
        "vehicle"
    ],
    "wof:name":"Peak Downs Mechanical",
    "wof:placetype":"venue"
},
  "geometry": {"coordinates":[147.698364258,-23.417673111],"type":"Point"}
}