{
  "type": "Feature",
  "properties": {
    "addr:full":"10 St Lukes St Willunga SA 5172",
    "addr:housenumber":"10",
    "addr:postcode":"5172",
    "addr:street":"St Lukes St",
    "iso:country":"AU",
    "sg:address":"10 St Lukes St",
    "sg:city":"Willunga",
    "sg:classifiers":[
        {
            "category":"Professional",
            "subcategory":"Printing & Photocopies",
            "type":"Services"
        }
    ],
    "sg:phone":"+61 8 8556 2815",
    "sg:postcode":"5172",
    "sg:province":"SA",
    "sg:tags":[
        "embroidery"
    ],
    "wof:name":"Willunga Embroidery",
    "wof:placetype":"venue"
},
  "geometry": {"coordinates":[138.55885314899999,-35.2735137939],"type":"Point"}
}