{
  "type": "Feature",
  "properties": {
    "addr:full":"222 Moorabool St Geelong VIC 3220",
    "addr:housenumber":"222",
    "addr:postcode":"3220",
    "addr:street":"Moorabool St",
    "iso:country":"AU",
    "sg:address":"222 Moorabool St",
    "sg:city":"Geelong",
    "sg:classifiers":[
        {
            "category":"Banks & Credit Unions",
            "subcategory":"Bureau De Change",
            "type":"Services"
        }
    ],
    "sg:phone":"+61 3 5222 1418",
    "sg:postcode":"3220",
    "sg:province":"VIC",
    "sg:tags":[
        "repairs",
        "part",
        "appliance",
        "electrical"
    ],
    "wof:name":"Central Appliance Service",
    "wof:placetype":"venue"
},
  "geometry": {"coordinates":[144.358566,-38.151627],"type":"Point"}
}