{
  "type": "Feature",
  "properties": {
    "addr:full":"65 Stewart Rd Beecher QLD 4680",
    "addr:housenumber":"65",
    "addr:postcode":"4680",
    "addr:street":"Stewart Rd",
    "iso:country":"AU",
    "sg:address":"65 Stewart Rd",
    "sg:city":"Beecher",
    "sg:classifiers":[
        {
            "category":"Personal",
            "subcategory":"Beauty Salon",
            "type":"Services"
        }
    ],
    "sg:phone":"+61 7 4978 2073",
    "sg:postcode":"4680",
    "sg:province":"QLD",
    "sg:tags":[
        "hairdresser"
    ],
    "wof:name":"Mjs Shear&#039;n Shed",
    "wof:placetype":"venue"
},
  "geometry": {"coordinates":[151.20835876500001,-23.8999233246],"type":"Point"}
}