{
  "type": "Feature",
  "properties": {
    "addr:full":"14 Wheeler Rd Karrinyup WA 6018",
    "addr:housenumber":"14",
    "addr:postcode":"6018",
    "addr:street":"Wheeler Rd",
    "iso:country":"AU",
    "sg:address":"14 Wheeler Rd",
    "sg:city":"Karrinyup",
    "sg:classifiers":[
        {
            "category":"Social Services",
            "subcategory":"Retirement Home",
            "type":"Services"
        }
    ],
    "sg:phone":"+61 438 412 366",
    "sg:postcode":"6018",
    "sg:province":"WA",
    "sg:tags":[
        "environmental",
        "consultant",
        "pollution"
    ],
    "wof:name":"Sustainable Environmental & Agricultural Systems(S E A M S)",
    "wof:placetype":"venue"
},
  "geometry": {"coordinates":[115.772903442,-31.882894516],"type":"Point"}
}