{
  "type": "Feature",
  "properties": {
    "addr:full":"Shp1/ 2 Garfield Rd Riverstone NSW 2765",
    "addr:housenumber":"2",
    "addr:postcode":"2765",
    "addr:street":"Garfield Rd",
    "iso:country":"AU",
    "sg:address":"Shp1/ 2 Garfield Rd",
    "sg:city":"Riverstone",
    "sg:classifiers":[
        {
            "category":"Fast Food",
            "type":"Food & Drink"
        }
    ],
    "sg:phone":"+61 2 9627 1700",
    "sg:postcode":"2765",
    "sg:province":"NSW",
    "sg:tags":[
        "away",
        "take"
    ],
    "wof:name":"Redskins Burger Hut",
    "wof:placetype":"venue"
},
  "geometry": {"coordinates":[150.86126709000001,-33.6797027588],"type":"Point"}
}