{
  "type": "Feature",
  "properties": {
    "addr:full":"93 Hertford St Sebastopol VIC 3356",
    "addr:housenumber":"93",
    "addr:postcode":"3356",
    "addr:street":"Hertford St",
    "iso:country":"AU",
    "sg:address":"93 Hertford St",
    "sg:city":"Sebastopol",
    "sg:classifiers":[
        {
            "category":"Autos & Motor Vehicles",
            "subcategory":"Auto Supplies",
            "type":"Retail Goods"
        }
    ],
    "sg:phone":"+61 3 5335 8371",
    "sg:postcode":"3356",
    "sg:province":"VIC",
    "sg:tags":[
        "tyre"
    ],
    "wof:name":"Yokohama",
    "wof:placetype":"venue"
},
  "geometry": {"coordinates":[143.82972699999999,-37.586906],"type":"Point"}
}