{
  "type": "Feature",
  "properties": {
    "addr:full":"Cnr Taverner St & Darts Ave Rainbow VIC 3424",
    "addr:postcode":"3424",
    "addr:street":"Cnr Taverner St & Darts Ave",
    "iso:country":"AU",
    "sg:address":"Cnr Taverner St & Darts Ave",
    "sg:city":"Rainbow",
    "sg:classifiers":[
        {
            "category":"Education",
            "subcategory":"School",
            "type":"Public Place"
        }
    ],
    "sg:phone":"+61 3 5395 1172",
    "sg:postcode":"3424",
    "sg:province":"VIC",
    "wof:name":"Rainbow Pre-School Centre",
    "wof:placetype":"venue"
},
  "geometry": {"coordinates":[141.99717712399999,-35.8985366821],"type":"Point"}
}