{
  "type": "Feature",
  "properties": {
    "addr:full":"3/ 33 kent Rd Surrey Hills VIC 3127",
    "addr:housenumber":"/ 33",
    "addr:postcode":"3127",
    "addr:street":"Kent Rd",
    "iso:country":"AU",
    "sg:address":"3/ 33 kent Rd",
    "sg:city":"Surrey Hills",
    "sg:classifiers":[
        {
            "category":"Health Services",
            "subcategory":"Health Practitioner",
            "type":"Services"
        }
    ],
    "sg:phone":"+61 3 9888 4943",
    "sg:postcode":"3127",
    "sg:province":"VIC",
    "sg:tags":[
        "bowen",
        "therapy"
    ],
    "wof:name":"Brock Ann",
    "wof:placetype":"venue"
},
  "geometry": {"coordinates":[145.09373474099999,-37.8284912109],"type":"Point"}
}