{
  "type": "Feature",
  "properties": {
    "addr:full":"PO Box 64 St Leonards TAS 7250",
    "addr:postcode":"7250",
    "iso:country":"AU",
    "sg:address":"PO Box 64 St",
    "sg:city":"Leonards",
    "sg:classifiers":[
        {
            "category":"Building & Trades",
            "subcategory":"Plumbing",
            "type":"Services"
        }
    ],
    "sg:phone":"+61 418 133 553",
    "sg:postcode":"7250",
    "sg:province":"TAS",
    "sg:tags":[
        "repair",
        "appliance",
        "system",
        "heating"
    ],
    "wof:name":"P L & J James & Son",
    "wof:placetype":"venue"
},
  "geometry": {"coordinates":[147.17437744099999,-41.4355888367],"type":"Point"}
}