{
  "type": "Feature",
  "properties": {
    "addr:full":"730 New South Head Rd Rose Bay NSW 2029",
    "addr:housenumber":"730",
    "addr:postcode":"2029",
    "addr:street":"New South Head Rd",
    "iso:country":"AU",
    "sg:address":"730 New South Head Rd",
    "sg:city":"Rose Bay",
    "sg:classifiers":[
        {
            "category":"Education",
            "subcategory":"Special Training",
            "type":"Public Place"
        }
    ],
    "sg:phone":"+61 2 9371 6651",
    "sg:postcode":"2029",
    "sg:province":"NSW",
    "sg:tags":[
        "school",
        "art"
    ],
    "wof:name":"Art Shop @ Rose Bay",
    "wof:placetype":"venue"
},
  "geometry": {"coordinates":[151.269897461,-33.8693504333],"type":"Point"}
}