{
  "type": "Feature",
  "properties": {
    "iso:country":"AU",
    "sg:address":"50 St Kevins Ave",
    "sg:city":"Benowa",
    "sg:classifiers":[
        {
            "category":"Professional",
            "subcategory":"Employment Agencies",
            "type":"Services"
        }
    ],
    "sg:phone":"+61 7 5564 5269",
    "sg:postcode":"4217",
    "sg:province":"QLD",
    "sg:tags":[
        "entertainer",
        "agent"
    ],
    "wof:name":"GC Entertainment",
    "wof:placetype":"venue"
},
  "geometry": {"coordinates":[153.395263672,-28.0039157867],"type":"Point"}
}