{
  "type": "Feature",
  "properties": {
    "iso:country":"AU",
    "sg:address":"1a North St",
    "sg:city":"Midland",
    "sg:classifiers":[
        {
            "category":"Travel",
            "subcategory":"Hostel",
            "type":"Entertainment"
        }
    ],
    "sg:phone":"+61 8 9250 0400",
    "sg:postcode":"6056",
    "sg:province":"WA",
    "sg:tags":[
        "home"
    ],
    "wof:name":"Morrison Lodge",
    "wof:placetype":"venue"
},
  "geometry": {"coordinates":[116.01441955599999,-31.8851146698],"type":"Point"}
}