{
  "type": "Feature",
  "properties": {
    "addr:full":"45 Homedale Crs Connells Point NSW 2221",
    "addr:housenumber":"45",
    "addr:postcode":"2221",
    "addr:street":"Homedale Crs",
    "iso:country":"AU",
    "sg:address":"45 Homedale Crs",
    "sg:city":"Connells Point",
    "sg:classifiers":[
        {
            "category":"Building & Trades",
            "subcategory":"Landscaping Services",
            "type":"Services"
        }
    ],
    "sg:phone":"+61 2 9547 1029",
    "sg:postcode":"2221",
    "sg:province":"NSW",
    "sg:tags":[
        "designer",
        "landscape",
        "contractor"
    ],
    "wof:name":"Treetops Landscape Design",
    "wof:placetype":"venue"
},
  "geometry": {"coordinates":[151.097946167,-33.9854393005],"type":"Point"}
}