{
  "type": "Feature",
  "properties": {
    "addr:full":"George St Medical Centre, 308 George St Sydney NSW 2000",
    "addr:housenumber":"308",
    "addr:postcode":"2000",
    "addr:street":"George;George St",
    "iso:country":"AU",
    "sg:address":"George St Medical Centre, 308 George St",
    "sg:city":"Sydney",
    "sg:classifiers":[
        {
            "category":"Health Services",
            "subcategory":"Doctor",
            "type":"Services"
        }
    ],
    "sg:phone":"+61 2 9239 1677",
    "sg:postcode":"2000",
    "sg:province":"NSW",
    "sg:tags":[
        "medical",
        "practitioner"
    ],
    "sg:website":"http://www.familygp.com.au/aapmedical",
    "wof:name":"Skapinker Alan Dr",
    "wof:placetype":"venue"
},
  "geometry": {"coordinates":[151.20741272000001,-33.8658485413],"type":"Point"}
}