{
  "type": "Feature",
  "properties": {
    "addr:full":"17 Montpelier St Neutral Bay NSW 2089",
    "addr:housenumber":"17",
    "addr:postcode":"2089",
    "addr:street":"Montpelier St",
    "iso:country":"AU",
    "sg:address":"17 Montpelier St",
    "sg:city":"Neutral Bay",
    "sg:classifiers":[
        {
            "category":"Professional",
            "subcategory":"Art Services",
            "type":"Services"
        }
    ],
    "sg:phone":"+61 2 9499 9992",
    "sg:postcode":"2089",
    "sg:province":"NSW",
    "sg:tags":[
        "graphic",
        "designer"
    ],
    "wof:name":"Indigo Creative Pty Ltd",
    "wof:placetype":"venue"
},
  "geometry": {"coordinates":[151.216400147,-33.8335418701],"type":"Point"}
}