{
  "type": "Feature",
  "properties": {
    "addr:full":"109 Poplar Pde Youngtown TAS 7249",
    "addr:housenumber":"109",
    "addr:postcode":"7249",
    "addr:street":"Poplar Pde",
    "iso:country":"AU",
    "sg:address":"109 Poplar Pde",
    "sg:city":"Youngtown",
    "sg:classifiers":[
        {
            "category":"Building & Trades",
            "subcategory":"Landscaping Services",
            "type":"Services"
        }
    ],
    "sg:phone":"+61 418 360 860",
    "sg:postcode":"7249",
    "sg:province":"TAS",
    "sg:tags":[
        "designer",
        "landscape",
        "contractor"
    ],
    "wof:name":"T H & D K Coghlan Landscaping",
    "wof:placetype":"venue"
},
  "geometry": {"coordinates":[147.17898559599999,-41.4855918884],"type":"Point"}
}