{
  "type": "Feature",
  "properties": {
    "addr:full":"98 Rivett St Hackett ACT 2602",
    "addr:housenumber":"98",
    "addr:postcode":"2602",
    "addr:street":"Rivett St",
    "iso:country":"AU",
    "sg:address":"98 Rivett St",
    "sg:city":"Hackett",
    "sg:classifiers":[
        {
            "category":"Building & Trades",
            "subcategory":"Plumbing",
            "type":"Services"
        }
    ],
    "sg:phone":"+61 2 6247 8464",
    "sg:postcode":"2602",
    "sg:province":"ACT",
    "sg:tags":[
        "plumber",
        "gasfitters"
    ],
    "wof:name":"McReynolds David",
    "wof:placetype":"venue"
},
  "geometry": {"coordinates":[149.16744995100001,-35.2470169067],"type":"Point"}
}