{
  "type": "Feature",
  "properties": {
    "addr:full":"Boyanup Picton Rd Picton WA 6229",
    "addr:postcode":"6229",
    "addr:street":"Boyanup Picton Rd",
    "iso:country":"AU",
    "sg:address":"Boyanup Picton Rd",
    "sg:city":"Picton",
    "sg:classifiers":[
        {
            "category":"Professional",
            "type":"Services"
        }
    ],
    "sg:phone":"+61 8 9725 4325",
    "sg:postcode":"6229",
    "sg:province":"WA",
    "sg:tags":[
        "transport"
    ],
    "wof:name":"Giovanetti Transport",
    "wof:placetype":"venue"
},
  "geometry": {"coordinates":[115.703552,-33.354416],"type":"Point"}
}