{
  "type": "Feature",
  "properties": {
    "iso:country":"AU",
    "sg:address":"125 Swanston St",
    "sg:city":"Melbourne",
    "sg:classifiers":[
        {
            "category":"Professional",
            "subcategory":"Printing & Photocopies",
            "type":"Services"
        }
    ],
    "sg:phone":"+61 3 9654 2100",
    "sg:postcode":"3000",
    "sg:province":"VIC",
    "sg:tags":[
        "trophy"
    ],
    "wof:name":"Emil Braun",
    "wof:placetype":"venue"
},
  "geometry": {"coordinates":[144.968353272,-37.8159408569],"type":"Point"}
}