{
  "type": "Feature",
  "properties": {
    "iso:country":"AU",
    "sg:address":"2, 20 Energy Crs",
    "sg:city":"Molendinar",
    "sg:classifiers":[
        {
            "category":"Shopping",
            "subcategory":"Bicycles & Sporting Goods",
            "type":"Retail Goods"
        }
    ],
    "sg:phone":"+61 7 5574 5700",
    "sg:postcode":"4214",
    "sg:province":"QLD",
    "sg:tags":[
        "trampoline"
    ],
    "sg:website":"http://www.topline-trampolines.com",
    "wof:name":"Topline Trampolines",
    "wof:placetype":"venue"
},
  "geometry": {"coordinates":[153.36343383799999,-27.9640808105],"type":"Point"}
}