{
  "type": "Feature",
  "properties": {
    "iso:country":"AU",
    "sg:address":"25 Sugargum Drv",
    "sg:city":"Sydenham",
    "sg:classifiers":[
        {
            "category":"Professional",
            "subcategory":"Computer Services",
            "type":"Services"
        }
    ],
    "sg:phone":"+61 3 9625 2258",
    "sg:postcode":"3037",
    "sg:province":"VIC",
    "sg:tags":[
        "consultant",
        "system"
    ],
    "wof:name":"Quantan Consulting Group",
    "wof:placetype":"venue"
},
  "geometry": {"coordinates":[144.73684700000001,-37.697659],"type":"Point"}
}