{
  "type": "Feature",
  "properties": {
    "iso:country":"AU",
    "sg:address":"43 Roches Beach Rd",
    "sg:city":"Roches Beach",
    "sg:classifiers":[
        {
            "category":"Food & Beverages",
            "subcategory":"Fruits & Vegetables",
            "type":"Retail Goods"
        }
    ],
    "sg:phone":"+61 3 6248 1052",
    "sg:postcode":"7170",
    "sg:province":"TAS",
    "sg:tags":[
        "grower"
    ],
    "wof:name":"Lafresh Pty Ltd",
    "wof:placetype":"venue"
},
  "geometry": {"coordinates":[147.48643493599999,-42.8886146545],"type":"Point"}
}