{
  "type": "Feature",
  "properties": {
    "iso:country":"AU",
    "sg:address":"1/ 74 Florence St",
    "sg:city":"Port Pirie",
    "sg:classifiers":[
        {
            "category":"Professional",
            "subcategory":"Accounting & Tax Preparation",
            "type":"Services"
        }
    ],
    "sg:phone":"+61 8 8632 1599",
    "sg:postcode":"5540",
    "sg:province":"SA",
    "sg:tags":[
        "accountant",
        "auditor"
    ],
    "wof:name":"Blackeby-Langston",
    "wof:placetype":"venue"
},
  "geometry": {"coordinates":[138.00851440400001,-33.1770820618],"type":"Point"}
}