{
  "type": "Feature",
  "properties": {
    "iso:country":"AU",
    "sg:address":"PO Box 444",
    "sg:city":"Cannington PLB",
    "sg:classifiers":[
        {
            "category":"Wholesale",
            "subcategory":"Painting Supplies",
            "type":"Manufacturing & Wholesale Goods"
        }
    ],
    "sg:phone":"+61 8 9259 4350",
    "sg:postcode":"6987",
    "sg:province":"WA",
    "sg:tags":[
        "equipment",
        "spraying"
    ],
    "wof:name":"Spraytech Systems",
    "wof:placetype":"venue"
},
  "geometry": {"coordinates":[115.939201,-32.019459],"type":"Point"}
}