{
  "type": "Feature",
  "properties": {
    "addr:full":"PO Box 25 Maroubra NSW 2035",
    "addr:postcode":"2035",
    "iso:country":"AU",
    "sg:address":"PO Box 25",
    "sg:city":"Maroubra",
    "sg:classifiers":[
        {
            "category":"Building & Trades",
            "subcategory":"Construction",
            "type":"Services"
        }
    ],
    "sg:phone":"+61 1300 365 328",
    "sg:postcode":"2035",
    "sg:province":"NSW",
    "sg:tags":[
        "spouting",
        "guttering"
    ],
    "wof:name":"UltraGuard",
    "wof:placetype":"venue"
},
  "geometry": {"coordinates":[151.25892639200001,-33.9435768127],"type":"Point"}
}