{
  "type": "Feature",
  "properties": {
    "addr:full":"Trenerry Rd Loxton SA 5333",
    "addr:postcode":"5333",
    "addr:street":"Trenerry Rd",
    "iso:country":"AU",
    "sg:address":"Trenerry Rd",
    "sg:city":"Loxton",
    "sg:classifiers":[
        {
            "category":"Retail",
            "subcategory":"Auto Repair",
            "type":"Services"
        }
    ],
    "sg:phone":"+61 8 8584 7925",
    "sg:postcode":"5333",
    "sg:province":"SA",
    "sg:tags":[
        "repairer",
        "motor",
        "engineer"
    ],
    "wof:name":"Koehne Auto Repairs",
    "wof:placetype":"venue"
},
  "geometry": {"coordinates":[140.58535766599999,-34.4492874146],"type":"Point"}
}