{
  "type": "Feature",
  "properties": {
    "addr:full":"88 Moray St South Melbourne VIC 3205",
    "addr:housenumber":"88",
    "addr:postcode":"3205",
    "addr:street":"Moray St",
    "iso:country":"AU",
    "sg:address":"88 Moray St",
    "sg:city":"South Melbourne",
    "sg:classifiers":[
        {
            "category":"Professional",
            "subcategory":"Art Services",
            "type":"Services"
        }
    ],
    "sg:phone":"+61 3 9693 6900",
    "sg:postcode":"3205",
    "sg:province":"VIC",
    "sg:tags":[
        "graphic",
        "designer"
    ],
    "wof:name":"Designworks",
    "wof:placetype":"venue"
},
  "geometry": {"coordinates":[144.961243,-37.828728],"type":"Point"}
}