{
  "type": "Feature",
  "properties": {
    "addr:full":"2/ 6 Maretimo St Balgowlah NSW 2093",
    "addr:housenumber":"/ 6",
    "addr:postcode":"2093",
    "addr:street":"Maretimo St",
    "iso:country":"AU",
    "sg:address":"2/ 6 Maretimo St",
    "sg:city":"Balgowlah",
    "sg:classifiers":[
        {
            "category":"Education",
            "subcategory":"Special Training",
            "type":"Public Place"
        }
    ],
    "sg:phone":"+61 2 9948 0888",
    "sg:postcode":"2093",
    "sg:province":"NSW",
    "sg:tags":[
        "development"
    ],
    "wof:name":"M D Communication",
    "wof:placetype":"venue"
},
  "geometry": {"coordinates":[151.25485229500001,-33.7994995117],"type":"Point"}
}