{
  "type": "Feature",
  "properties": {
    "iso:country":"AU",
    "sg:address":"40 Parkwood Rd",
    "sg:city":"Coleraine",
    "sg:classifiers":[
        {
            "category":"Retail",
            "subcategory":"Auto Rental",
            "type":"Services"
        }
    ],
    "sg:phone":"+61 3 5570 8283",
    "sg:postcode":"3315",
    "sg:province":"VIC",
    "sg:tags":[
        "camper-trailers",
        "caravan",
        "hire"
    ],
    "wof:name":"Grampians Camper Trailers",
    "wof:placetype":"venue"
},
  "geometry": {"coordinates":[141.829803467,-37.589225769],"type":"Point"}
}