{
  "type": "Feature",
  "properties": {
    "iso:country":"AU",
    "sg:address":"49 Matisse Drv",
    "sg:city":"Templestowe",
    "sg:classifiers":[
        {
            "category":"Communications",
            "type":"Services"
        }
    ],
    "sg:phone":"+61 3 9842 2933",
    "sg:postcode":"3106",
    "sg:province":"VIC",
    "sg:tags":[
        "translation"
    ],
    "wof:name":"Persian Translation Services",
    "wof:placetype":"venue"
},
  "geometry": {"coordinates":[145.16473388700001,-37.7590446472],"type":"Point"}
}