{
  "type": "Feature",
  "properties": {
    "iso:country":"AU",
    "sg:address":"52 Frederick St",
    "sg:city":"Belmont",
    "sg:classifiers":[
        {
            "category":"Social Services",
            "subcategory":"Retirement Home",
            "type":"Services"
        }
    ],
    "sg:phone":"+61 8 9475 0650",
    "sg:postcode":"6104",
    "sg:province":"WA",
    "sg:tags":[
        "environmental",
        "consultant",
        "pollution"
    ],
    "wof:name":"Tanda Pty Ltd",
    "wof:placetype":"venue"
},
  "geometry": {"coordinates":[115.933570862,-31.9467906952],"type":"Point"}
}