{
  "type": "Feature",
  "properties": {
    "addr:full":"Level 1, 928 Military Rd Mosman NSW 2088",
    "addr:housenumber":"928",
    "addr:postcode":"2088",
    "addr:street":"Military Rd",
    "iso:country":"AU",
    "sg:address":"Level 1, 928 Military Rd",
    "sg:city":"Mosman",
    "sg:classifiers":[
        {
            "category":"Sports & Exercise",
            "subcategory":"Gym",
            "type":"Entertainment"
        }
    ],
    "sg:phone":"+61 2 9968 3344",
    "sg:postcode":"2088",
    "sg:province":"NSW",
    "sg:tags":[
        "personal",
        "trainer",
        "fitness"
    ],
    "wof:name":"Vision Personal Training",
    "wof:placetype":"venue"
},
  "geometry": {"coordinates":[151.24447631800001,-33.8313064575],"type":"Point"}
}