{
  "type": "Feature",
  "properties": {
    "addr:full":"56 Melville St Numurkah VIC 3636",
    "addr:housenumber":"56",
    "addr:postcode":"3636",
    "addr:street":"Melville St",
    "iso:country":"AU",
    "sg:address":"56 Melville St",
    "sg:city":"Numurkah",
    "sg:classifiers":[
        {
            "category":"Shopping",
            "type":"Retail Goods"
        }
    ],
    "sg:phone":"+61 3 5862 1077",
    "sg:postcode":"3636",
    "sg:province":"VIC",
    "sg:tags":[
        "agent",
        "stock"
    ],
    "wof:name":"Maurice McNamara & Co",
    "wof:placetype":"venue"
},
  "geometry": {"coordinates":[145.442260742,-36.0902137756],"type":"Point"}
}