{
  "type": "Feature",
  "properties": {
    "addr:full":"13 Turner St Helidon QLD 4344",
    "addr:housenumber":"13",
    "addr:postcode":"4344",
    "addr:street":"Turner St",
    "iso:country":"AU",
    "sg:address":"13 Turner St",
    "sg:city":"Helidon",
    "sg:classifiers":[
        {
            "category":"Government",
            "subcategory":"Post Office",
            "type":"Public Place"
        }
    ],
    "sg:phone":"+61 7 4697 6247",
    "sg:postcode":"4344",
    "sg:province":"QLD",
    "sg:tags":[
        "postal"
    ],
    "wof:name":"Australia Post",
    "wof:placetype":"venue"
},
  "geometry": {"coordinates":[152.125046,-27.550446],"type":"Point"}
}