{
  "type": "Feature",
  "properties": {
    "addr:full":"207 Lords Pl Orange NSW 2800",
    "addr:housenumber":"207",
    "addr:postcode":"2800",
    "addr:street":"Lords Pl",
    "iso:country":"AU",
    "sg:address":"207 Lords Pl",
    "sg:city":"Orange",
    "sg:classifiers":[
        {
            "category":"Education",
            "subcategory":"Music School",
            "type":"Public Place"
        }
    ],
    "sg:phone":"+61 2 6361 2939",
    "sg:postcode":"2800",
    "sg:province":"NSW",
    "sg:tags":[
        "teacher"
    ],
    "wof:name":"Aftershock Records",
    "wof:placetype":"venue"
},
  "geometry": {"coordinates":[149.10307312,-33.273815155],"type":"Point"}
}