{
  "type": "Feature",
  "properties": {
    "addr:full":"Terrinallum Rd Vite Vite VIC 3325",
    "addr:postcode":"3325",
    "addr:street":"Terrinallum Rd",
    "iso:country":"AU",
    "sg:address":"Terrinallum Rd",
    "sg:city":"Vite Vite",
    "sg:classifiers":[
        {
            "category":"Farming",
            "subcategory":"Farm",
            "type":"Manufacturing & Wholesale Goods"
        }
    ],
    "sg:phone":"+61 3 5597 7538",
    "sg:postcode":"3325",
    "sg:province":"VIC",
    "sg:tags":[
        "farmer"
    ],
    "wof:name":"French G J",
    "wof:placetype":"venue"
},
  "geometry": {"coordinates":[143.11604299999999,-37.869175],"type":"Point"}
}