{
  "type": "Feature",
  "properties": {
    "iso:country":"AU",
    "sg:address":"698 Albany Creek Rd",
    "sg:city":"Albany Creek",
    "sg:classifiers":[
        {
            "category":"Health Services",
            "subcategory":"Health Practitioner",
            "type":"Services"
        }
    ],
    "sg:phone":"+61 7 3264 2622",
    "sg:postcode":"4035",
    "sg:province":"QLD",
    "sg:tags":[
        "psychologist"
    ],
    "wof:name":"Dixie Statham",
    "wof:placetype":"venue"
},
  "geometry": {"coordinates":[152.965836,-27.345343],"type":"Point"}
}