{
  "type": "Feature",
  "properties": {
    "addr:full":"GPO Box 472 Darwin NT 0800",
    "addr:postcode":"nt 0800",
    "iso:country":"AU",
    "sg:address":"GPO Box 472",
    "sg:city":"Darwin",
    "sg:classifiers":[
        {
            "category":"Building & Trades",
            "subcategory":"Construction",
            "type":"Services"
        }
    ],
    "sg:phone":"+61 8 8932 9901",
    "sg:postcode":"0800",
    "sg:province":"NT",
    "sg:tags":[
        "renovation",
        "alterations",
        "extension",
        "contractor"
    ],
    "wof:name":"Lees Building Contractors",
    "wof:placetype":"venue"
},
  "geometry": {"coordinates":[130.84231567399999,-12.4620399475],"type":"Point"}
}