{
  "type": "Feature",
  "properties": {
    "addr:full":"27 Weemala Drv Mitcham SA 5062",
    "addr:housenumber":"27",
    "addr:postcode":"5062",
    "addr:street":"Weemala Drv",
    "iso:country":"AU",
    "sg:address":"27 Weemala Drv",
    "sg:city":"Mitcham",
    "sg:classifiers":[
        {
            "category":"Shopping",
            "subcategory":"Clothing, Apparel, & Fashions",
            "type":"Retail Goods"
        }
    ],
    "sg:phone":"+61 8 8172 1611",
    "sg:postcode":"5062",
    "sg:province":"SA",
    "sg:tags":[
        "textile",
        "designer"
    ],
    "wof:name":"It Girl By Liza Emanuele",
    "wof:placetype":"venue"
},
  "geometry": {"coordinates":[138.621856689,-34.9884910583],"type":"Point"}
}