{
  "type": "Feature",
  "properties": {
    "addr:full":"797 Nicholson St Carlton North VIC 3054",
    "addr:housenumber":"797",
    "addr:postcode":"3054",
    "addr:street":"Nicholson St",
    "iso:country":"AU",
    "sg:address":"797 Nicholson St",
    "sg:city":"Carlton North",
    "sg:classifiers":[
        {
            "category":"Restaurant",
            "type":"Food & Drink"
        }
    ],
    "sg:phone":"+61 3 9381 0501",
    "sg:postcode":"3054",
    "sg:province":"VIC",
    "wof:name":"Bar Fired",
    "wof:placetype":"venue"
},
  "geometry": {"coordinates":[144.977783203,-37.7805747986],"type":"Point"}
}