{
  "type": "Feature",
  "properties": {
    "iso:country":"AU",
    "sg:address":"Shop 1E Centro Karingal Shopng Cntr",
    "sg:city":"Frankston",
    "sg:classifiers":[
        {
            "category":"Personal",
            "type":"Services"
        }
    ],
    "sg:phone":"+61 3 9789 1151",
    "sg:postcode":"3199",
    "sg:province":"VIC",
    "sg:tags":[
        "gift"
    ],
    "wof:name":"Abigail Flowers",
    "wof:placetype":"venue"
},
  "geometry": {"coordinates":[144.83297729500001,-37.8198013306],"type":"Point"}
}