{
  "type": "Feature",
  "properties": {
    "addr:full":"Yarrawa Rd Moss Vale NSW 2577",
    "addr:postcode":"2577",
    "addr:street":"Yarrawa Rd",
    "iso:country":"AU",
    "sg:address":"Yarrawa Rd",
    "sg:city":"Moss Vale",
    "sg:classifiers":[
        {
            "category":"Travel",
            "subcategory":"Hostel",
            "type":"Entertainment"
        }
    ],
    "sg:phone":"+61 2 4869 4098",
    "sg:postcode":"2577",
    "sg:province":"NSW",
    "sg:tags":[
        "home"
    ],
    "wof:name":"HarbisonCare",
    "wof:placetype":"venue"
},
  "geometry": {"coordinates":[150.363815308,-34.5526618958],"type":"Point"}
}