{
  "type": "Feature",
  "properties": {
    "addr:full":"11 Wills St Kew VIC 3101",
    "addr:housenumber":"11",
    "addr:postcode":"3101",
    "addr:street":"Wills St",
    "iso:country":"AU",
    "sg:address":"11 Wills St",
    "sg:city":"Kew",
    "sg:classifiers":[
        {
            "category":"Health Services",
            "subcategory":"Doctor",
            "type":"Services"
        }
    ],
    "sg:phone":"+61 3 9853 7805",
    "sg:postcode":"3101",
    "sg:province":"VIC",
    "sg:tags":[
        "medical",
        "practitioner"
    ],
    "wof:name":"Lee N L Y",
    "wof:placetype":"venue"
},
  "geometry": {"coordinates":[145.02919006400001,-37.7992172241],"type":"Point"}
}