{
  "type": "Feature",
  "properties": {
    "addr:full":"Habgood St Northam WA 6401",
    "addr:postcode":"6401",
    "addr:street":"St",
    "iso:country":"AU",
    "sg:address":"Habgood St",
    "sg:city":"Northam",
    "sg:classifiers":[
        {
            "category":"Education",
            "subcategory":"Kindergarten",
            "type":"Public Place"
        }
    ],
    "sg:phone":"+61 8 9622 1712",
    "sg:postcode":"6401",
    "sg:province":"WA",
    "sg:tags":[
        "pre-schools"
    ],
    "wof:name":"Kadajiny Kindi",
    "wof:placetype":"venue"
},
  "geometry": {"coordinates":[116.66294860799999,-31.661901474],"type":"Point"}
}