{
  "type": "Feature",
  "properties": {
    "addr:full":"Suite 2b, 112 Synnot St Werribee VIC 3030",
    "addr:housenumber":"suite 2b",
    "addr:postcode":"112;3030",
    "addr:street":"Synnot St",
    "iso:country":"AU",
    "sg:address":"Suite 2b, 112 Synnot St",
    "sg:city":"Werribee",
    "sg:classifiers":[
        {
            "category":"Health Services",
            "subcategory":"Health Practitioner",
            "type":"Services"
        }
    ],
    "sg:phone":"+61 3 9731 1277",
    "sg:postcode":"3030",
    "sg:province":"VIC",
    "sg:tags":[
        "psychologist"
    ],
    "wof:name":"Justine Fletcher",
    "wof:placetype":"venue"
},
  "geometry": {"coordinates":[144.65463299999999,-37.906361],"type":"Point"}
}