{
  "type": "Feature",
  "properties": {
    "iso:country":"AU",
    "sg:address":"132 Gatehouse St",
    "sg:city":"Parkville",
    "sg:classifiers":[
        {
            "category":"Health Services",
            "subcategory":"Doctor",
            "type":"Services"
        }
    ],
    "sg:phone":"+61 3 9347 6950",
    "sg:postcode":"3052",
    "sg:province":"VIC",
    "sg:tags":[
        "medical",
        "practitioner"
    ],
    "wof:name":"Rickards Winston S",
    "wof:placetype":"venue"
},
  "geometry": {"coordinates":[144.95469665499999,-37.7939834595],"type":"Point"}
}