{
  "type": "Feature",
  "properties": {
    "addr:full":"Saunders St Moreland VIC 3058",
    "addr:postcode":"3058",
    "addr:street":"Saunders St",
    "iso:country":"AU",
    "sg:address":"Saunders St",
    "sg:city":"Moreland",
    "sg:classifiers":[
        {
            "category":"Education",
            "subcategory":"School",
            "type":"Public Place"
        }
    ],
    "sg:phone":"+61 3 9383 3600",
    "sg:postcode":"3058",
    "sg:province":"VIC",
    "sg:tags":[
        "co-educational"
    ],
    "wof:name":"St Fidelis Primary",
    "wof:placetype":"venue"
},
  "geometry": {"coordinates":[144.95123290999999,-37.748714447],"type":"Point"}
}