{
  "type": "Feature",
  "properties": {
    "addr:full":"3 Rosevear Pl Dickson ACT 2602",
    "addr:housenumber":"3",
    "addr:postcode":"2602",
    "addr:street":"Rosevear Pl",
    "iso:country":"AU",
    "sg:address":"3 Rosevear Pl",
    "sg:city":"Dickson",
    "sg:classifiers":[
        {
            "category":"Professional",
            "subcategory":"Employment Agencies",
            "type":"Services"
        }
    ],
    "sg:phone":"+61 2 6257 8344",
    "sg:postcode":"2602",
    "sg:province":"ACT",
    "wof:name":"CITEA",
    "wof:placetype":"venue"
},
  "geometry": {"coordinates":[149.143768311,-35.2493057251],"type":"Point"}
}