{
  "type": "Feature",
  "properties": {
    "iso:country":"AU",
    "sg:address":"Women's Wellbeing, Suite1/631 Logan Rd",
    "sg:city":"Greenslopes",
    "sg:classifiers":[
        {
            "category":"Health Services",
            "subcategory":"Doctor",
            "type":"Services"
        }
    ],
    "sg:phone":"+61 7 3394 4644",
    "sg:postcode":"4120",
    "sg:province":"QLD",
    "sg:tags":[
        "medical",
        "practitioner"
    ],
    "wof:name":"Dr Judith Reddrop",
    "wof:placetype":"venue"
},
  "geometry": {"coordinates":[153.051681519,-27.508731842],"type":"Point"}
}