{
  "type": "Feature",
  "properties": {
    "iso:country":"AU",
    "sg:address":"3/ 11 Allen St",
    "sg:city":"Harris Park",
    "sg:classifiers":[
        {
            "category":"Building & Trades",
            "subcategory":"Construction",
            "type":"Services"
        }
    ],
    "sg:phone":"+61 2 9897 1100",
    "sg:postcode":"2150",
    "sg:province":"NSW",
    "sg:tags":[
        "window",
        "tinting"
    ],
    "wof:name":"Solartint",
    "wof:placetype":"venue"
},
  "geometry": {"coordinates":[151.011993408,-33.8250312805],"type":"Point"}
}