{
  "type": "Feature",
  "properties": {
    "addr:full":"Campbell St Wollongong NSW 2500",
    "addr:postcode":"2500",
    "addr:street":"St",
    "iso:country":"AU",
    "sg:address":"Campbell St",
    "sg:city":"Wollongong",
    "sg:classifiers":[
        {
            "category":"Professional",
            "subcategory":"Engineering",
            "type":"Services"
        }
    ],
    "sg:phone":"+61 2 4225 3170",
    "sg:postcode":"2500",
    "sg:province":"NSW",
    "sg:tags":[
        "consulting",
        "engineer"
    ],
    "wof:name":"Bowdens Engineers",
    "wof:placetype":"venue"
},
  "geometry": {"coordinates":[150.89347799999999,-34.419548],"type":"Point"}
}