{
  "type": "Feature",
  "properties": {
    "addr:full":"Level 3, 2 Wellington Pde East Melbourne VIC 3002",
    "addr:housenumber":"2",
    "addr:postcode":"3002",
    "addr:street":"Wellington Pde",
    "iso:country":"AU",
    "sg:address":"Level 3, 2 Wellington Pde",
    "sg:city":"East Melbourne",
    "sg:classifiers":[
        {
            "category":"Professional",
            "subcategory":"Engineering",
            "type":"Services"
        }
    ],
    "sg:phone":"+61 3 9230 5600",
    "sg:postcode":"3002",
    "sg:province":"VIC",
    "sg:tags":[
        "consulting",
        "engineer"
    ],
    "wof:name":"Lehr Consultants Intl (Aust) Pty Ltd",
    "wof:placetype":"venue"
},
  "geometry": {"coordinates":[144.98985290499999,-37.8166732788],"type":"Point"}
}