{
  "type": "Feature",
  "properties": {
    "addr:full":"44 High St Mansfield VIC 3722",
    "addr:housenumber":"44",
    "addr:postcode":"3722",
    "addr:street":"High St",
    "iso:country":"AU",
    "sg:address":"44 High St",
    "sg:city":"Mansfield",
    "sg:classifiers":[
        {
            "category":"Shopping",
            "subcategory":"Shoes",
            "type":"Retail Goods"
        }
    ],
    "sg:phone":"+61 3 5775 2147",
    "sg:postcode":"3722",
    "sg:province":"VIC",
    "sg:tags":[
        "footwear"
    ],
    "wof:name":"Mansfield Shoe Store",
    "wof:placetype":"venue"
},
  "geometry": {"coordinates":[146.090530395,-37.0527229309],"type":"Point"}
}