{
  "type": "Feature",
  "properties": {
    "addr:full":"359 Glenhuntly Rd Elsternwick VIC 3185",
    "addr:housenumber":"359",
    "addr:postcode":"3185",
    "addr:street":"Glenhuntly Rd",
    "iso:country":"AU",
    "sg:address":"359 Glenhuntly Rd",
    "sg:city":"Elsternwick",
    "sg:classifiers":[
        {
            "category":"Travel",
            "subcategory":"Travel Agent",
            "type":"Entertainment"
        }
    ],
    "sg:phone":"+61 13 18 66",
    "sg:postcode":"3185",
    "sg:province":"VIC",
    "sg:tags":[
        "consultant"
    ],
    "wof:name":"Flight Centre",
    "wof:placetype":"venue"
},
  "geometry": {"coordinates":[144.99261474599999,-37.8833045959],"type":"Point"}
}