{
  "type": "Feature",
  "properties": {
    "addr:full":"195 Whitford Rd Green Valley NSW 2168",
    "addr:housenumber":"195",
    "addr:postcode":"2168",
    "addr:street":"Whitford Rd",
    "iso:country":"AU",
    "sg:address":"195 Whitford Rd",
    "sg:city":"Green Valley",
    "sg:classifiers":[
        {
            "category":"Juice Bar",
            "subcategory":"None",
            "type":"Food & Drink"
        }
    ],
    "sg:phone":"+61 2 9608 6994",
    "sg:postcode":"2168",
    "sg:province":"NSW",
    "sg:tags":[
        "merchant",
        "fruit",
        "processor"
    ],
    "wof:name":"Jubilee Fruit Juices Australia",
    "wof:placetype":"venue"
},
  "geometry": {"coordinates":[150.87193298299999,-33.9080162048],"type":"Point"}
}