{
  "type": "Feature",
  "properties": {
    "iso:country":"AU",
    "sg:address":"Unit 3/ 8 Armitage St",
    "sg:city":"Bongaree",
    "sg:classifiers":[
        {
            "category":"Retail",
            "subcategory":"Auto Repair",
            "type":"Services"
        }
    ],
    "sg:phone":"+61 7 3408 1821",
    "sg:postcode":"4507",
    "sg:province":"QLD",
    "sg:tags":[
        "repairer",
        "motor",
        "engineer"
    ],
    "wof:name":"Jack's Tyres & Mechanical",
    "wof:placetype":"venue"
},
  "geometry": {"coordinates":[153.18046569800001,-27.0773391724],"type":"Point"}
}