{
  "type": "Feature",
  "properties": {
    "iso:country":"AU",
    "sg:address":"Shop 3/ 9 Railway Tce",
    "sg:city":"Goolwa",
    "sg:classifiers":[
        {
            "category":"Shopping",
            "subcategory":"Clothing, Apparel, & Fashions",
            "type":"Retail Goods"
        }
    ],
    "sg:phone":"+61 8 8555 2557",
    "sg:postcode":"5214",
    "sg:province":"SA",
    "sg:tags":[
        "recycled",
        "clothing"
    ],
    "wof:name":"Carousel Kids",
    "wof:placetype":"venue"
},
  "geometry": {"coordinates":[138.78288269000001,-35.5030670166],"type":"Point"}
}