{
  "type": "Feature",
  "properties": {
    "addr:full":"37 Fullarton Rd Kent Town SA 5067",
    "addr:housenumber":"37",
    "addr:postcode":"5067",
    "addr:street":"Fullarton Rd",
    "iso:country":"AU",
    "sg:address":"37 Fullarton Rd",
    "sg:city":"Kent Town",
    "sg:classifiers":[
        {
            "category":"Professional",
            "subcategory":"Art Services",
            "type":"Services"
        }
    ],
    "sg:phone":"+61 8 8362 3122",
    "sg:postcode":"5067",
    "sg:province":"SA",
    "sg:tags":[
        "graphic",
        "designer"
    ],
    "wof:name":"Free Run Press",
    "wof:placetype":"venue"
},
  "geometry": {"coordinates":[138.617675781,-34.920715332],"type":"Point"}
}