{
  "type": "Feature",
  "properties": {
    "addr:full":"202 Royal St Yokine WA 6060",
    "addr:housenumber":"202",
    "addr:postcode":"6060",
    "addr:street":"Royal St",
    "iso:country":"AU",
    "sg:address":"202 Royal St",
    "sg:city":"Yokine",
    "sg:classifiers":[
        {
            "category":"Building & Trades",
            "subcategory":"Construction",
            "type":"Services"
        }
    ],
    "sg:phone":"+61 8 9483 6416",
    "sg:postcode":"6060",
    "sg:province":"WA",
    "sg:tags":[
        "tennis court",
        "repair"
    ],
    "wof:name":"Centre Court Renovators",
    "wof:placetype":"venue"
},
  "geometry": {"coordinates":[115.850410461,-31.896490097],"type":"Point"}
}