{
  "type": "Feature",
  "properties": {
    "iso:country":"AU",
    "sg:address":"13 Dales Pl",
    "sg:city":"Taigum",
    "sg:classifiers":[
        {
            "category":"Professional",
            "subcategory":"Business Services",
            "type":"Services"
        }
    ],
    "sg:phone":"+61 7 3865 5649",
    "sg:postcode":"4018",
    "sg:province":"QLD",
    "sg:tags":[
        "drafting"
    ],
    "wof:name":"L & F Technical Services",
    "wof:placetype":"venue"
},
  "geometry": {"coordinates":[153.05178799999999,-27.346281],"type":"Point"}
}