{
  "type": "Feature",
  "properties": {
    "iso:country":"AU",
    "sg:address":"1206 Canterbury Rd",
    "sg:city":"Punchbowl",
    "sg:classifiers":[
        {
            "category":"Communications",
            "subcategory":"Film & Video Production",
            "type":"Services"
        }
    ],
    "sg:phone":"+61 2 9758 1300",
    "sg:postcode":"2196",
    "sg:province":"NSW",
    "sg:tags":[
        "dvd",
        "library"
    ],
    "wof:name":"Blockbuster",
    "wof:placetype":"venue"
},
  "geometry": {"coordinates":[151.06521599999999,-33.930813],"type":"Point"}
}