{
  "type": "Feature",
  "properties": {
    "iso:country":"AU",
    "sg:address":"150 High St",
    "sg:city":"Broadford",
    "sg:classifiers":[
        {
            "category":"Education",
            "subcategory":"Kindergarten",
            "type":"Public Place"
        }
    ],
    "sg:phone":"+61 3 5784 1532",
    "sg:postcode":"3658",
    "sg:province":"VIC",
    "sg:tags":[
        "pre-schools"
    ],
    "wof:name":"Mt Piper Pre School",
    "wof:placetype":"venue"
},
  "geometry": {"coordinates":[145.053863525,-37.2032966614],"type":"Point"}
}