{
  "type": "Feature",
  "properties": {
    "addr:full":"974 Carcoola St Albury North NSW 2640",
    "addr:housenumber":"974",
    "addr:postcode":"2640",
    "addr:street":"Carcoola St",
    "iso:country":"AU",
    "sg:address":"974 Carcoola St",
    "sg:city":"Albury North",
    "sg:classifiers":[
        {
            "category":"Bars & Pubs",
            "subcategory":"Lounge",
            "type":"Food & Drink"
        }
    ],
    "sg:phone":"+61 1300 360 331",
    "sg:postcode":"2640",
    "sg:province":"NSW",
    "sg:tags":[
        "water",
        "filter",
        "drinking"
    ],
    "wof:name":"Palm Springs",
    "wof:placetype":"venue"
},
  "geometry": {"coordinates":[146.94461059599999,-36.0606002808],"type":"Point"}
}