{
  "type": "Feature",
  "properties": {
    "addr:full":"Shp12/ 75 Ntaba Rd Jewells NSW 2280",
    "addr:postcode":"2280",
    "addr:street":"Ntaba Rd",
    "iso:country":"AU",
    "sg:address":"Shp12/ 75 Ntaba Rd",
    "sg:city":"Jewells",
    "sg:classifiers":[
        {
            "category":"Fast Food",
            "type":"Food & Drink"
        }
    ],
    "sg:phone":"+61 2 4948 8948",
    "sg:postcode":"2280",
    "sg:province":"NSW",
    "sg:tags":[
        "away",
        "take"
    ],
    "wof:name":"Ng's Jewells Restaurant",
    "wof:placetype":"venue"
},
  "geometry": {"coordinates":[151.68417358400001,-33.012348175],"type":"Point"}
}