{
  "type": "Feature",
  "properties": {
    "addr:full":"17- 19 Martinez Ave Townsville QLD 4810",
    "addr:housenumber":"19",
    "addr:postcode":"4810",
    "addr:street":"Martinez Ave",
    "iso:country":"AU",
    "sg:address":"17- 19 Martinez Ave",
    "sg:city":"Townsville",
    "sg:classifiers":[
        {
            "category":"Health Services",
            "subcategory":"Dentist",
            "type":"Services"
        }
    ],
    "sg:phone":"+61 7 4775 4433",
    "sg:postcode":"4810",
    "sg:province":"QLD",
    "wof:name":"Hanrahan P D",
    "wof:placetype":"venue"
},
  "geometry": {"coordinates":[146.78421,-19.269787],"type":"Point"}
}