{
  "type": "Feature",
  "properties": {
    "iso:country":"AU",
    "sg:address":"Level 1 / 3 / 38 Essington St",
    "sg:city":"Mitchell",
    "sg:classifiers":[
        {
            "category":"Organizations",
            "subcategory":"Professional Association",
            "type":"Services"
        }
    ],
    "sg:phone":"+61 1300 785 230",
    "sg:postcode":"2911",
    "sg:province":"ACT",
    "sg:tags":[
        "web",
        "internet"
    ],
    "wof:name":"Synapse Worldwide",
    "wof:placetype":"venue"
},
  "geometry": {"coordinates":[149.13487243599999,-35.2105331421],"type":"Point"}
}