{
  "type": "Feature",
  "properties": {
    "addr:full":"Aust National University, North Rd Acton ACT 2601",
    "addr:postcode":"2601",
    "addr:street":"North Rd",
    "iso:country":"AU",
    "sg:address":"Aust National University, North Rd",
    "sg:city":"Acton",
    "sg:classifiers":[
        {
            "category":"Health Services",
            "subcategory":"Doctor",
            "type":"Services"
        }
    ],
    "sg:phone":"+61 2 6125 3598",
    "sg:postcode":"2601",
    "sg:province":"ACT",
    "sg:tags":[
        "medical",
        "practitioner"
    ],
    "wof:name":"University Health Services",
    "wof:placetype":"venue"
},
  "geometry": {"coordinates":[149.12109375,-35.275592804],"type":"Point"}
}