{
  "type": "Feature",
  "properties": {
    "addr:full":"Shop 17 Wondall Road Shopping Centre Manly West QLD 4179",
    "addr:housenumber":"shop 17",
    "addr:postcode":"4179",
    "addr:street":"Wondall Road",
    "iso:country":"AU",
    "sg:address":"Shop 17 Wondall Road Shopping Centre",
    "sg:city":"Manly West",
    "sg:classifiers":[
        {
            "category":"Building & Trades",
            "subcategory":"Construction",
            "type":"Services"
        }
    ],
    "sg:phone":"+61 7 3893 0515",
    "sg:postcode":"4179",
    "sg:province":"QLD",
    "sg:tags":[
        "pool",
        "swimming"
    ],
    "wof:name":"John Clark Pools & Renovations",
    "wof:placetype":"venue"
},
  "geometry": {"coordinates":[153.16636657699999,-27.4552364349],"type":"Point"}
}