{
  "type": "Feature",
  "properties": {
    "addr:full":"111 Woodville Rd Woodville SA 5011",
    "addr:housenumber":"111",
    "addr:postcode":"5011",
    "addr:street":"Woodville Rd",
    "iso:country":"AU",
    "sg:address":"111 Woodville Rd",
    "sg:city":"Woodville",
    "sg:classifiers":[
        {
            "category":"Museum",
            "type":"Entertainment"
        }
    ],
    "sg:phone":"+61 8 8445 9670",
    "sg:postcode":"5011",
    "sg:province":"SA",
    "wof:name":"The Brocas Museum - Social History",
    "wof:placetype":"venue"
},
  "geometry": {"coordinates":[138.54115295400001,-34.8743019104],"type":"Point"}
}