{
  "type": "Feature",
  "properties": {
    "addr:full":"242 Station St Fairfield VIC 3078",
    "addr:housenumber":"242",
    "addr:postcode":"3078",
    "addr:street":"Station St",
    "iso:country":"AU",
    "sg:address":"242 Station St",
    "sg:city":"Fairfield",
    "sg:classifiers":[
        {
            "category":"Health Services",
            "subcategory":"Doctor",
            "type":"Services"
        }
    ],
    "sg:phone":"+61 3 9481 6638",
    "sg:postcode":"3078",
    "sg:province":"VIC",
    "sg:tags":[
        "medical",
        "practitioner"
    ],
    "wof:name":"Fairfield Family Health Centre",
    "wof:placetype":"venue"
},
  "geometry": {"coordinates":[145.01942443900001,-37.7702331543],"type":"Point"}
}