{
  "type": "Feature",
  "properties": {
    "addr:full":"10 Hudson Ave Castle Hill NSW 2154",
    "addr:housenumber":"10",
    "addr:postcode":"2154",
    "addr:street":"Hudson Ave",
    "iso:country":"AU",
    "sg:address":"10 Hudson Ave",
    "sg:city":"Castle Hill",
    "sg:classifiers":[
        {
            "category":"Retail",
            "subcategory":"Auto Repair",
            "type":"Services"
        }
    ],
    "sg:phone":"+61 2 9680 2244",
    "sg:postcode":"2154",
    "sg:province":"NSW",
    "sg:tags":[
        "repairer",
        "motor",
        "engineer"
    ],
    "wof:name":"Automotive Professionals Pty Ltd",
    "wof:placetype":"venue"
},
  "geometry": {"coordinates":[150.97450256400001,-33.7294998169],"type":"Point"}
}