{
  "type": "Feature",
  "properties": {
    "iso:country":"AU",
    "sg:address":"PO Box 316",
    "sg:city":"Salamander Bay",
    "sg:classifiers":[
        {
            "category":"Professional",
            "subcategory":"Detective & Security Services",
            "type":"Services"
        }
    ],
    "sg:phone":"+61 2 4984 3000",
    "sg:postcode":"2317",
    "sg:province":"NSW",
    "sg:tags":[
        "guard",
        "patrol"
    ],
    "wof:name":"AR Security Services Pty Ltd",
    "wof:placetype":"venue"
},
  "geometry": {"coordinates":[152.082092,-32.731091],"type":"Point"}
}