{
  "type": "Feature",
  "properties": {
    "addr:full":"U3/ 36 Fleming Ave Cannington WA 6107",
    "addr:housenumber":"36",
    "addr:postcode":"6107",
    "addr:street":"U3 /;Fleming Ave",
    "iso:country":"AU",
    "sg:address":"U3/ 36 Fleming Ave",
    "sg:city":"Cannington",
    "sg:classifiers":[
        {
            "category":"Building & Trades",
            "subcategory":"Construction",
            "type":"Services"
        }
    ],
    "sg:phone":"+61 8 9358 1877",
    "sg:postcode":"6107",
    "sg:province":"WA",
    "sg:tags":[
        "contractor"
    ],
    "wof:name":"Westmade Homes",
    "wof:placetype":"venue"
},
  "geometry": {"coordinates":[115.92539978000001,-32.015750885],"type":"Point"}
}