{
  "type": "Feature",
  "properties": {
    "addr:full":"5 , 6 Trade St Cleveland QLD 4163",
    "addr:housenumber":"6",
    "addr:postcode":"4163",
    "addr:street":"Trade St",
    "iso:country":"AU",
    "sg:address":"5 , 6 Trade St",
    "sg:city":"Cleveland",
    "sg:classifiers":[
        {
            "category":"Communications",
            "subcategory":"Film & Video Production",
            "type":"Services"
        }
    ],
    "sg:phone":"+61 7 3821 0852",
    "sg:postcode":"4163",
    "sg:province":"QLD",
    "sg:tags":[
        "fan",
        "blower"
    ],
    "wof:name":"Les Bennell Auto Air & Electrics",
    "wof:placetype":"venue"
},
  "geometry": {"coordinates":[153.25656127900001,-27.5212783813],"type":"Point"}
}