{
  "type": "Feature",
  "properties": {
    "addr:full":"Westlake Drv Westlake QLD 4074",
    "addr:postcode":"4074",
    "addr:street":"Westlake Drv",
    "iso:country":"AU",
    "sg:address":"Westlake Drv",
    "sg:city":"Westlake",
    "sg:classifiers":[
        {
            "category":"Shopping",
            "subcategory":"Bicycles & Sporting Goods",
            "type":"Retail Goods"
        }
    ],
    "sg:phone":"+61 7 3376 5455",
    "sg:postcode":"4074",
    "sg:province":"QLD",
    "sg:tags":[
        "chemical",
        "equipment",
        "pool",
        "swimming"
    ],
    "wof:name":"Centenary Pool Mart",
    "wof:placetype":"venue"
},
  "geometry": {"coordinates":[152.90977477999999,-27.5456027985],"type":"Point"}
}