{
  "type": "Feature",
  "properties": {
    "addr:full":"Shop F56 Stockland Mall Polding St Wetherill Park NSW 2164",
    "addr:housenumber":"f56",
    "addr:postcode":"2164",
    "addr:street":"Polding St",
    "iso:country":"AU",
    "sg:address":"Shop F56 Stockland Mall Polding St",
    "sg:city":"Wetherill Park",
    "sg:classifiers":[
        {
            "category":"Cafe",
            "type":"Food & Drink"
        }
    ],
    "sg:phone":"+61 2 9604 1597",
    "sg:postcode":"2164",
    "sg:province":"NSW",
    "wof:name":"Gloria Jean's Coffees",
    "wof:placetype":"venue"
},
  "geometry": {"coordinates":[150.9034729,-33.8572120667],"type":"Point"}
}