{
  "type": "Feature",
  "properties": {
    "iso:country":"AU",
    "sg:address":"17 Merston St",
    "sg:city":"Nollamara",
    "sg:classifiers":[
        {
            "category":"Real Estate",
            "subcategory":"Real Estate Agent",
            "type":"Services"
        }
    ],
    "sg:phone":"+61 409 007 055",
    "sg:postcode":"6061",
    "sg:province":"WA",
    "wof:name":"Realty Executives Joondalup",
    "wof:placetype":"venue"
},
  "geometry": {"coordinates":[115.83989715600001,-31.8877830505],"type":"Point"}
}