{
  "type": "Feature",
  "properties": {
    "addr:full":"32 Gillian Pde Pymble NSW 2073",
    "addr:housenumber":"32",
    "addr:postcode":"2073",
    "addr:street":"Gillian Pde",
    "iso:country":"AU",
    "sg:address":"32 Gillian Pde",
    "sg:city":"Pymble",
    "sg:classifiers":[
        {
            "category":"Shopping",
            "subcategory":"Mobile Phones",
            "type":"Retail Goods"
        }
    ],
    "sg:phone":"+61 2 9499 8443",
    "sg:postcode":"2073",
    "sg:province":"NSW",
    "sg:tags":[
        "telephone",
        "accessory"
    ],
    "wof:name":"The Car Kit Company",
    "wof:placetype":"venue"
},
  "geometry": {"coordinates":[151.128219605,-33.7661705017],"type":"Point"}
}