{
  "type": "Feature",
  "properties": {
    "addr:full":"Suite 4, 344 Ferntree Gully Rd Notting Hill VIC 3168",
    "addr:housenumber":"344",
    "addr:postcode":"3168",
    "addr:street":"Ferntree Gully Rd",
    "iso:country":"AU",
    "sg:address":"Suite 4, 344 Ferntree Gully Rd",
    "sg:city":"Notting Hill",
    "sg:classifiers":[
        {
            "category":"Professional",
            "subcategory":"Computer Services",
            "type":"Services"
        }
    ],
    "sg:phone":"+61 3 9535 9535",
    "sg:postcode":"3168",
    "sg:province":"VIC",
    "sg:tags":[
        "tele-communications",
        "consultant"
    ],
    "wof:name":"Central Solutions Australia Pty Ltd",
    "wof:placetype":"venue"
},
  "geometry": {"coordinates":[145.13766479500001,-37.9007263184],"type":"Point"}
}