{
  "type": "Feature",
  "properties": {
    "addr:full":"864 Boat Harbour Drv Urangan QLD 4655",
    "addr:housenumber":"864",
    "addr:postcode":"4655",
    "addr:street":"Boat Harbour Drv",
    "iso:country":"AU",
    "sg:address":"864 Boat Harbour Drv",
    "sg:city":"Urangan",
    "sg:classifiers":[
        {
            "category":"Recreation",
            "subcategory":"Marina",
            "type":"Entertainment"
        }
    ],
    "sg:phone":"+61 7 4128 9119",
    "sg:postcode":"4655",
    "sg:province":"QLD",
    "wof:name":"Fishermans Wharf Marina",
    "wof:placetype":"venue"
},
  "geometry": {"coordinates":[152.900284,-25.294718],"type":"Point"}
}