{
  "type": "Feature",
  "properties": {
    "iso:country":"AU",
    "sg:address":"U4/ 72 O'Riordan St",
    "sg:city":"Alexandria",
    "sg:classifiers":[
        {
            "category":"Professional",
            "subcategory":"Computer Services",
            "type":"Services"
        }
    ],
    "sg:phone":"+61 2 9317 4300",
    "sg:postcode":"2015",
    "sg:province":"NSW",
    "sg:tags":[
        "equipment",
        "networking",
        "installation"
    ],
    "wof:name":"Crown Computer Cabling P/L",
    "wof:placetype":"venue"
},
  "geometry": {"coordinates":[151.197097778,-33.9120788574],"type":"Point"}
}