{
  "type": "Feature",
  "properties": {
    "iso:country":"AU",
    "sg:address":"Shop 7/ 4 Croydon Rd",
    "sg:city":"Woodridge",
    "sg:classifiers":[
        {
            "category":"Deli",
            "type":"Food & Drink"
        }
    ],
    "sg:phone":"+61 7 3208 8262",
    "sg:postcode":"4114",
    "sg:province":"QLD",
    "sg:tags":[
        "delicatessen"
    ],
    "wof:name":"Euro Deli Logan",
    "wof:placetype":"venue"
},
  "geometry": {"coordinates":[153.10430908199999,-27.6371593475],"type":"Point"}
}