{
  "type": "Feature",
  "properties": {
    "addr:full":"PO Box 6066 Mildura VIC 3501",
    "addr:postcode":"3501",
    "iso:country":"AU",
    "sg:address":"PO Box 6066",
    "sg:city":"Mildura",
    "sg:classifiers":[
        {
            "category":"Professional",
            "subcategory":"Art Services",
            "type":"Services"
        }
    ],
    "sg:phone":"+61 429 171 176",
    "sg:postcode":"3501",
    "sg:province":"VIC",
    "sg:tags":[
        "decorator",
        "painter"
    ],
    "wof:name":"Peter Williams",
    "wof:placetype":"venue"
},
  "geometry": {"coordinates":[142.161712647,-34.186050415],"type":"Point"}
}