{
  "type": "Feature",
  "properties": {
    "addr:full":"Allandale Rd Young NSW 2594",
    "addr:postcode":"2594",
    "addr:street":"Allandale Rd",
    "iso:country":"AU",
    "sg:address":"Allandale Rd",
    "sg:city":"Young",
    "sg:classifiers":[
        {
            "category":"Autos & Motor Vehicles",
            "subcategory":"Auto Supplies",
            "type":"Retail Goods"
        }
    ],
    "sg:phone":"+61 2 6382 7237",
    "sg:postcode":"2594",
    "sg:province":"NSW",
    "sg:tags":[
        "part",
        "cycles",
        "accessory"
    ],
    "wof:name":"Roly Orr's Repairs",
    "wof:placetype":"venue"
},
  "geometry": {"coordinates":[148.275466919,-34.2938423157],"type":"Point"}
}