{
  "type": "Feature",
  "properties": {
    "addr:full":"21 Norton St Leichhardt NSW 2040",
    "addr:housenumber":"21",
    "addr:postcode":"2040",
    "addr:street":"Norton St",
    "iso:country":"AU",
    "sg:address":"21 Norton St",
    "sg:city":"Leichhardt",
    "sg:classifiers":[
        {
            "category":"Banks & Credit Unions",
            "subcategory":"Financial Services",
            "type":"Services"
        }
    ],
    "sg:phone":"+61 2 9569 6599",
    "sg:postcode":"2040",
    "sg:province":"NSW",
    "sg:tags":[
        "financier"
    ],
    "wof:name":"Reincorp Pty Ltd",
    "wof:placetype":"venue"
},
  "geometry": {"coordinates":[151.157669,-33.887093],"type":"Point"}
}