{
  "type": "Feature",
  "properties": {
    "addr:full":"PO Box 6022 Hilton WA 6163",
    "addr:postcode":"6163",
    "iso:country":"AU",
    "sg:address":"PO Box 6022",
    "sg:city":"Hilton",
    "sg:classifiers":[
        {
            "category":"Shopping",
            "subcategory":"Bicycles & Sporting Goods",
            "type":"Retail Goods"
        }
    ],
    "sg:phone":"+61 1300 628 262",
    "sg:postcode":"6163",
    "sg:province":"WA",
    "sg:tags":[
        "chemical",
        "equipment",
        "pool",
        "swimming"
    ],
    "wof:name":"Pool Technix",
    "wof:placetype":"venue"
},
  "geometry": {"coordinates":[115.78967299999999,-32.067841],"type":"Point"}
}