{
  "type": "Feature",
  "properties": {
    "iso:country":"AU",
    "sg:address":"34 First Ave",
    "sg:city":"Sawtell",
    "sg:classifiers":[
        {
            "category":"Health Services",
            "subcategory":"Dentist",
            "type":"Services"
        }
    ],
    "sg:phone":"+61 2 6653 3457",
    "sg:postcode":"2452",
    "sg:province":"NSW",
    "wof:name":"Wilson Mark",
    "wof:placetype":"venue"
},
  "geometry": {"coordinates":[153.100677,-30.368593],"type":"Point"}
}