{
  "type": "Feature",
  "properties": {
    "addr:full":"12 Mt Gravatt Capalaba Rd Upper Mt Gravatt QLD 4122",
    "addr:housenumber":"12",
    "addr:postcode":"4122",
    "addr:street":"Mt Gravatt Capalaba Rd Upper",
    "iso:country":"AU",
    "sg:address":"12 Mt Gravatt Capalaba Rd",
    "sg:city":"Upper Mt Gravatt",
    "sg:classifiers":[
        {
            "category":"Education",
            "subcategory":"Special Training",
            "type":"Public Place"
        }
    ],
    "sg:phone":"+61 7 3349 6538",
    "sg:postcode":"4122",
    "sg:province":"QLD",
    "sg:tags":[
        "development"
    ],
    "wof:name":"Matters In Gray Training Organisation",
    "wof:placetype":"venue"
},
  "geometry": {"coordinates":[153.081542969,-27.5595722198],"type":"Point"}
}