{
  "type": "Feature",
  "properties": {
    "addr:full":"10 Lawley St North Beach WA 6020",
    "addr:housenumber":"10",
    "addr:postcode":"6020",
    "addr:street":"Lawley St",
    "iso:country":"AU",
    "sg:address":"10 Lawley St",
    "sg:city":"North Beach",
    "sg:classifiers":[
        {
            "category":"Travel",
            "subcategory":"Hotels & Motels",
            "type":"Entertainment"
        }
    ],
    "sg:phone":"+61 8 9246 4699",
    "sg:postcode":"6020",
    "sg:province":"WA",
    "wof:name":"Comfort Inn Ocean View",
    "wof:placetype":"venue"
},
  "geometry": {"coordinates":[115.753463745,-31.8546562195],"type":"Point"}
}