{
  "type": "Feature",
  "properties": {
    "addr:full":"226 St Georges Rd Fitzroy North VIC 3068",
    "addr:housenumber":"226",
    "addr:postcode":"3068",
    "addr:street":"St Georges Rd",
    "iso:country":"AU",
    "sg:address":"226 St Georges Rd",
    "sg:city":"Fitzroy North",
    "sg:classifiers":[
        {
            "category":"Health Services",
            "subcategory":"Doctor",
            "type":"Services"
        }
    ],
    "sg:phone":"+61 3 9482 5522",
    "sg:postcode":"3068",
    "sg:province":"VIC",
    "sg:tags":[
        "medical",
        "practitioner"
    ],
    "wof:name":"Nth Fitzroy Village Medical Practice",
    "wof:placetype":"venue"
},
  "geometry": {"coordinates":[144.983551025,-37.7838554382],"type":"Point"}
}