{
  "type": "Feature",
  "properties": {
    "addr:full":"48 Urquhart St Horsham VIC 3400",
    "addr:housenumber":"48",
    "addr:postcode":"3400",
    "addr:street":"Urquhart St",
    "iso:country":"AU",
    "sg:address":"48 Urquhart St",
    "sg:city":"Horsham",
    "sg:classifiers":[
        {
            "category":"Retail",
            "subcategory":"Auto Repair",
            "type":"Services"
        }
    ],
    "sg:phone":"+61 3 5381 0027",
    "sg:postcode":"3400",
    "sg:province":"VIC",
    "sg:tags":[
        "beater",
        "painter",
        "panel"
    ],
    "wof:name":"McAlpine Crash Repairs",
    "wof:placetype":"venue"
},
  "geometry": {"coordinates":[142.20216369600001,-36.7181434631],"type":"Point"}
}