{
  "type": "Feature",
  "properties": {
    "iso:country":"AU",
    "sg:address":"Shop 2/ 66 The Terrace Tce",
    "sg:city":"Ocean Grove",
    "sg:classifiers":[
        {
            "category":"Real Estate",
            "subcategory":"Real Estate Agent",
            "type":"Services"
        }
    ],
    "sg:phone":"+61 3 5255 1222",
    "sg:postcode":"3226",
    "sg:province":"VIC",
    "wof:name":"C.J. Keane & Co.",
    "wof:placetype":"venue"
},
  "geometry": {"coordinates":[144.523636,-38.269733],"type":"Point"}
}