{
  "type": "Feature",
  "properties": {
    "addr:full":"PO Box 1196 Hobart TAS 7000",
    "addr:postcode":"7000",
    "iso:country":"AU",
    "sg:address":"PO Box 1196",
    "sg:city":"Hobart",
    "sg:classifiers":[
        {
            "category":"Professional",
            "subcategory":"Art Services",
            "type":"Services"
        }
    ],
    "sg:phone":"+61 429 983 495",
    "sg:postcode":"7000",
    "sg:province":"TAS",
    "sg:tags":[
        "graphic",
        "designer"
    ],
    "wof:name":"Helen Bryen",
    "wof:placetype":"venue"
},
  "geometry": {"coordinates":[147.31495666500001,-42.8748512268],"type":"Point"}
}