{
  "type": "Feature",
  "properties": {
    "addr:full":"151a Main St Bacchus Marsh VIC 3340",
    "addr:housenumber":"151a",
    "addr:postcode":"3340",
    "addr:street":"Main St",
    "iso:country":"AU",
    "sg:address":"151a Main St",
    "sg:city":"Bacchus Marsh",
    "sg:classifiers":[
        {
            "category":"Food & Beverages",
            "subcategory":"Bakery",
            "type":"Retail Goods"
        }
    ],
    "sg:phone":"+61 3 5367 7077",
    "sg:postcode":"3340",
    "sg:province":"VIC",
    "sg:tags":[
        "cake",
        "shop",
        "pastry"
    ],
    "wof:name":"Ferguson Plarre Bakehouses Pty Ltd",
    "wof:placetype":"venue"
},
  "geometry": {"coordinates":[144.43817100000001,-37.676029],"type":"Point"}
}