{
  "type": "Feature",
  "properties": {
    "iso:country":"AU",
    "sg:address":"49 Monash Rd",
    "sg:city":"Gladesville",
    "sg:classifiers":[
        {
            "category":"Professional",
            "subcategory":"Business Services",
            "type":"Services"
        }
    ],
    "sg:phone":"+61 2 9879 6944",
    "sg:postcode":"2111",
    "sg:province":"NSW",
    "sg:tags":[
        "drafting"
    ],
    "wof:name":"Excell Design Consultants",
    "wof:placetype":"venue"
},
  "geometry": {"coordinates":[151.126953125,-33.82081604],"type":"Point"}
}