{
  "type": "Feature",
  "properties": {
    "addr:full":"Cnr Canning Hwy & Brandon Rd South Perth WA 6151",
    "addr:postcode":"6151",
    "addr:street":"Canning Hwy & Brandon Rd",
    "iso:country":"AU",
    "sg:address":"Cnr Canning Hwy & Brandon Rd",
    "sg:city":"South Perth",
    "sg:classifiers":[
        {
            "category":"Building & Trades",
            "subcategory":"Construction",
            "type":"Services"
        }
    ],
    "sg:phone":"+61 8 9367 3166",
    "sg:postcode":"6151",
    "sg:province":"WA",
    "sg:tags":[
        "fencing",
        "contractor"
    ],
    "wof:name":"Total Fencing Supplies",
    "wof:placetype":"venue"
},
  "geometry": {"coordinates":[115.870239,-31.98105],"type":"Point"}
}