{
  "type": "Feature",
  "properties": {
    "addr:full":"Cnr Maneroo & Nathalia Rds Bunbartha VIC 3634",
    "addr:postcode":"3634",
    "addr:street":"Cnr Maneroo &",
    "iso:country":"AU",
    "sg:address":"Cnr Maneroo & Nathalia Rds",
    "sg:city":"Bunbartha",
    "sg:classifiers":[
        {
            "category":"Farming",
            "subcategory":"Berry Farm",
            "type":"Manufacturing & Wholesale Goods"
        }
    ],
    "sg:phone":"+61 3 5826 9466",
    "sg:postcode":"3634",
    "sg:province":"VIC",
    "sg:tags":[
        "fruit",
        "grower"
    ],
    "wof:name":"Erinhaven Orchard",
    "wof:placetype":"venue"
},
  "geometry": {"coordinates":[145.360031128,-36.2795562744],"type":"Point"}
}