{
  "type": "Feature",
  "properties": {
    "iso:country":"AU",
    "sg:address":"270 Boundary Rd",
    "sg:city":"Braeside",
    "sg:classifiers":[
        {
            "category":"Wholesale",
            "subcategory":"Home Furnishings",
            "type":"Manufacturing & Wholesale Goods"
        }
    ],
    "sg:phone":"+61 3 9587 2666",
    "sg:postcode":"3195",
    "sg:province":"VIC",
    "sg:tags":[
        "wholesaler",
        "bedding",
        "mfrs",
        "bed"
    ],
    "wof:name":"Regal Mattress Manufactures",
    "wof:placetype":"venue"
},
  "geometry": {"coordinates":[145.108276367,-37.9887542725],"type":"Point"}
}