{
  "type": "Feature",
  "properties": {
    "iso:country":"AU",
    "sg:address":"PO Box 1230",
    "sg:city":"Dalby",
    "sg:classifiers":[
        {
            "category":"Banks & Credit Unions",
            "subcategory":"Bank",
            "type":"Services"
        }
    ],
    "sg:phone":"+61 7 4669 7068",
    "sg:postcode":"4405",
    "sg:province":"QLD",
    "sg:tags":[
        "broker",
        "mortgage"
    ],
    "wof:name":"Sharon Ferguson Finance",
    "wof:placetype":"venue"
},
  "geometry": {"coordinates":[151.257415772,-27.1783504486],"type":"Point"}
}