{
  "type": "Feature",
  "properties": {
    "addr:full":"110 Russell St Bathurst NSW 2795",
    "addr:housenumber":"110",
    "addr:postcode":"2795",
    "addr:street":"Russell St",
    "iso:country":"AU",
    "sg:address":"110 Russell St",
    "sg:city":"Bathurst",
    "sg:classifiers":[
        {
            "category":"Wholesale",
            "subcategory":"Electrical",
            "type":"Manufacturing & Wholesale Goods"
        }
    ],
    "sg:phone":"+61 2 6332 1848",
    "sg:postcode":"2795",
    "sg:province":"NSW",
    "sg:tags":[
        "wholesaler"
    ],
    "wof:name":"Rexel Australia Electrical Supplies",
    "wof:placetype":"venue"
},
  "geometry": {"coordinates":[149.578689575,-33.4179077148],"type":"Point"}
}