{
  "type": "Feature",
  "properties": {
    "iso:country":"AU",
    "sg:address":"26 Wallace St",
    "sg:city":"Macksville",
    "sg:classifiers":[
        {
            "category":"Government",
            "subcategory":"Fire Station",
            "type":"Public Place"
        }
    ],
    "sg:phone":"+61 2 6568 1561",
    "sg:postcode":"2447",
    "sg:province":"NSW",
    "sg:tags":[
        "brigade"
    ],
    "wof:name":"Fire Brigades-NSW",
    "wof:placetype":"venue"
},
  "geometry": {"coordinates":[152.918564,-30.707823],"type":"Point"}
}