{
  "type": "Feature",
  "properties": {
    "addr:full":"100 Brazier Rd Yanchep WA 6035",
    "addr:housenumber":"100",
    "addr:postcode":"6035",
    "addr:street":"Brazier Rd",
    "iso:country":"AU",
    "sg:address":"100 Brazier Rd",
    "sg:city":"Yanchep",
    "sg:classifiers":[
        {
            "category":"Professional",
            "subcategory":"Accounting & Tax Preparation",
            "type":"Services"
        }
    ],
    "sg:phone":"+61 417 981 715",
    "sg:postcode":"6035",
    "sg:province":"WA",
    "sg:tags":[
        "bookkeeping"
    ],
    "wof:name":"Synergy Business Services",
    "wof:placetype":"venue"
},
  "geometry": {"coordinates":[115.63279724100001,-31.5577602386],"type":"Point"}
}