{
  "type": "Feature",
  "properties": {
    "addr:full":"Suite 3 201 High St Fremantle WA 6160",
    "addr:housenumber":"201",
    "addr:postcode":"6160",
    "addr:street":"High St",
    "iso:country":"AU",
    "sg:address":"Suite 3 201 High St",
    "sg:city":"Fremantle",
    "sg:phone":"+61 8 9335 1600",
    "sg:postcode":"6160",
    "sg:province":"WA",
    "wof:name":"Wallis Group",
    "wof:placetype":"venue"
},
  "geometry": {"coordinates":[115.751938,-32.052906],"type":"Point"}
}