{
  "type": "Feature",
  "properties": {
    "addr:full":"1785 Pittwater Rd Mona Vale NSW 2103",
    "addr:housenumber":"1785",
    "addr:postcode":"2103",
    "addr:street":"Pittwater Rd",
    "iso:country":"AU",
    "sg:address":"1785 Pittwater Rd",
    "sg:city":"Mona Vale",
    "sg:classifiers":[
        {
            "category":"Health Services",
            "subcategory":"Doctor",
            "type":"Services"
        }
    ],
    "sg:phone":"+61 2 9997 2844",
    "sg:postcode":"2103",
    "sg:province":"NSW",
    "sg:tags":[
        "medical",
        "practitioner"
    ],
    "wof:name":"Curran John E",
    "wof:placetype":"venue"
},
  "geometry": {"coordinates":[151.30328369099999,-33.6755485535],"type":"Point"}
}