{
  "type": "Feature",
  "properties": {
    "addr:full":"1 Blissington St Springvale VIC 3171",
    "addr:housenumber":"1",
    "addr:postcode":"3171",
    "addr:street":"Blissington St",
    "iso:country":"AU",
    "sg:address":"1 Blissington St",
    "sg:city":"Springvale",
    "sg:classifiers":[
        {
            "category":"Banks & Credit Unions",
            "subcategory":"Bureau De Change",
            "type":"Services"
        }
    ],
    "sg:phone":"+61 1800 008 379",
    "sg:postcode":"3171",
    "sg:province":"VIC",
    "sg:tags":[
        "equipment",
        "heat",
        "exchange"
    ],
    "wof:name":"Air to Air Energy Recovery",
    "wof:placetype":"venue"
},
  "geometry": {"coordinates":[145.15232849099999,-37.932964325],"type":"Point"}
}