{
  "type": "Feature",
  "properties": {
    "iso:country":"AU",
    "sg:address":"432 Chapel Rd",
    "sg:city":"Bankstown",
    "sg:classifiers":[
        {
            "category":"Education",
            "subcategory":"Special Training",
            "type":"Public Place"
        }
    ],
    "sg:phone":"+61 2 9790 6089",
    "sg:postcode":"2200",
    "sg:province":"NSW",
    "sg:tags":[
        "development"
    ],
    "wof:name":"IPC Employment",
    "wof:placetype":"venue"
},
  "geometry": {"coordinates":[151.03331,-33.916756],"type":"Point"}
}