{
  "type": "Feature",
  "properties": {
    "iso:country":"AU",
    "sg:address":"63 Old Pitt Town Rd",
    "sg:city":"Pitt Town",
    "sg:classifiers":[
        {
            "category":"Home & Garden",
            "subcategory":"Garden Supply",
            "type":"Retail Goods"
        }
    ],
    "sg:phone":"+61 2 4572 3455",
    "sg:postcode":"2756",
    "sg:province":"NSW",
    "sg:tags":[
        "turf",
        "lawn"
    ],
    "wof:name":"Courtney Turf Supplies",
    "wof:placetype":"venue"
},
  "geometry": {"coordinates":[150.87144470199999,-33.5877532959],"type":"Point"}
}