{
  "type": "Feature",
  "properties": {
    "iso:country":"AU",
    "sg:address":"1376 Malvern Rd",
    "sg:city":"Malvern",
    "sg:classifiers":[
        {
            "category":"Museum",
            "subcategory":"Art Museum",
            "type":"Entertainment"
        }
    ],
    "sg:phone":"+61 3 9824 4792",
    "sg:postcode":"3144",
    "sg:province":"VIC",
    "sg:tags":[
        "antique",
        "fine",
        "valuer"
    ],
    "wof:name":"Ildiko Antiques",
    "wof:placetype":"venue"
},
  "geometry": {"coordinates":[145.041671753,-37.853263855],"type":"Point"}
}