{
  "type": "Feature",
  "properties": {
    "addr:full":"3 Alexa Rd North Haven SA 5018",
    "addr:housenumber":"3",
    "addr:postcode":"5018",
    "addr:street":"Alexa Rd",
    "iso:country":"AU",
    "sg:address":"3 Alexa Rd",
    "sg:city":"North Haven",
    "sg:classifiers":[
        {
            "category":"Shopping",
            "subcategory":"Crafts & Fabrics",
            "type":"Retail Goods"
        }
    ],
    "sg:phone":"+61 8 8248 1382",
    "sg:postcode":"5018",
    "sg:province":"SA",
    "sg:tags":[
        "supply"
    ],
    "wof:name":"Magic Touch Crafts & Gifts",
    "wof:placetype":"venue"
},
  "geometry": {"coordinates":[138.48939514200001,-34.7859420776],"type":"Point"}
}