{
  "type": "Feature",
  "properties": {
    "addr:full":"209 Narara Valley Drv Niagara Park NSW 2250",
    "addr:housenumber":"209",
    "addr:postcode":"2250",
    "addr:street":"Narara Valley Drv Niagara Park",
    "iso:country":"AU",
    "sg:address":"209 Narara Valley Drv",
    "sg:city":"Niagara Park",
    "sg:classifiers":[
        {
            "category":"Social Services",
            "subcategory":"Child Care",
            "type":"Services"
        }
    ],
    "sg:phone":"+61 2 4328 5485",
    "sg:postcode":"2250",
    "sg:province":"NSW",
    "wof:name":"Niagara Park Childrens Centre",
    "wof:placetype":"venue"
},
  "geometry": {"coordinates":[151.350738525,-33.3826026917],"type":"Point"}
}