{
  "type": "Feature",
  "properties": {
    "iso:country":"AU",
    "sg:address":"Cnr Somerville Rd & Williamstown Rd",
    "sg:city":"Yarraville",
    "sg:classifiers":[
        {
            "category":"Personal",
            "subcategory":"Beauty Salon",
            "type":"Services"
        }
    ],
    "sg:phone":"+61 3 9314 7557",
    "sg:postcode":"3013",
    "sg:province":"VIC",
    "wof:name":"Carnovale Natural Beauty Centre",
    "wof:placetype":"venue"
},
  "geometry": {"coordinates":[144.88348388700001,-37.8127937317],"type":"Point"}
}