{
  "type": "Feature",
  "properties": {
    "iso:country":"AU",
    "sg:address":"444 Marrickville Rd",
    "sg:city":"Marrickville",
    "sg:classifiers":[
        {
            "category":"Health Services",
            "subcategory":"Nursing And Care Facility",
            "type":"Services"
        }
    ],
    "sg:phone":"+61 2 9089 8000",
    "sg:postcode":"2204",
    "sg:province":"NSW",
    "sg:tags":[
        "home"
    ],
    "wof:name":"Grevillea Centre",
    "wof:placetype":"venue"
},
  "geometry": {"coordinates":[151.14750699999999,-33.907284],"type":"Point"}
}