{
  "type": "Feature",
  "properties": {
    "addr:full":"540 Belgrave-Hallam Rd Narre Warren North VIC 3804",
    "addr:housenumber":"540",
    "addr:postcode":"3804",
    "addr:street":"Belgrave-Hallam Rd",
    "iso:country":"AU",
    "sg:address":"540 Belgrave-Hallam Rd",
    "sg:city":"Narre Warren North",
    "sg:classifiers":[
        {
            "category":"Farming",
            "subcategory":"Nursery",
            "type":"Manufacturing & Wholesale Goods"
        }
    ],
    "sg:phone":"+61 3 9796 9422",
    "sg:postcode":"3804",
    "sg:province":"VIC",
    "wof:name":"Warner's Nurseries Pty. Ltd.",
    "wof:placetype":"venue"
},
  "geometry": {"coordinates":[145.32408142099999,-37.9658546448],"type":"Point"}
}