{
  "type": "Feature",
  "properties": {
    "iso:country":"AU",
    "sg:address":"The Mater Private Hospital Redland Weippin St",
    "sg:city":"Cleveland",
    "sg:classifiers":[
        {
            "category":"Health Services",
            "subcategory":"Doctor",
            "type":"Services"
        }
    ],
    "sg:phone":"+61 7 3847 8820",
    "sg:postcode":"4163",
    "sg:province":"QLD",
    "sg:tags":[
        "medical",
        "practitioner"
    ],
    "wof:name":"Kennedy Ross Dr",
    "wof:placetype":"venue"
},
  "geometry": {"coordinates":[153.253463745,-27.5415649414],"type":"Point"}
}