{
  "type": "Feature",
  "properties": {
    "iso:country":"AU",
    "sg:address":"3/ 2 Stoddart Rd",
    "sg:city":"Prospect",
    "sg:classifiers":[
        {
            "category":"Professional",
            "subcategory":"Art Services",
            "type":"Services"
        }
    ],
    "sg:phone":"+61 2 9688 4277",
    "sg:postcode":"2148",
    "sg:province":"NSW",
    "sg:tags":[
        "picture",
        "frame",
        "framing"
    ],
    "sg:website":"http://www.masterframes.com.au",
    "wof:name":"Masterframes",
    "wof:placetype":"venue"
},
  "geometry": {"coordinates":[150.924285889,-33.8005332947],"type":"Point"}
}