{
  "type": "Feature",
  "properties": {
    "addr:full":"Llandaff St Bondi Junction NSW 2022",
    "addr:postcode":"2022",
    "addr:street":"Llandaff St",
    "iso:country":"AU",
    "sg:address":"Llandaff St",
    "sg:city":"Bondi Junction",
    "sg:classifiers":[
        {
            "category":"Communications",
            "subcategory":"News Services",
            "type":"Services"
        }
    ],
    "sg:phone":"+61 2 9369 4304",
    "sg:postcode":"2022",
    "sg:province":"NSW",
    "sg:tags":[
        "information",
        "tourist",
        "attractions"
    ],
    "wof:name":"Euro Guide Of Sydney",
    "wof:placetype":"venue"
},
  "geometry": {"coordinates":[151.252853394,-33.8935165405],"type":"Point"}
}