{
  "type": "Feature",
  "properties": {
    "addr:full":"22 Hansford Rd Coombabah QLD 4216",
    "addr:housenumber":"22",
    "addr:postcode":"4216",
    "addr:street":"Hansford Rd",
    "iso:country":"AU",
    "sg:address":"22 Hansford Rd",
    "sg:city":"Coombabah",
    "sg:classifiers":[
        {
            "category":"Social Services",
            "subcategory":"Retirement Home",
            "type":"Services"
        }
    ],
    "sg:phone":"+61 7 5577 4066",
    "sg:postcode":"4216",
    "sg:province":"QLD",
    "sg:tags":[
        "village"
    ],
    "wof:name":"Hammond Villages Pty Ltd",
    "wof:placetype":"venue"
},
  "geometry": {"coordinates":[153.384963989,-27.8999938965],"type":"Point"}
}