{
  "type": "Feature",
  "properties": {
    "iso:country":"AU",
    "sg:address":"105 Rundle St",
    "sg:city":"Kent Town",
    "sg:classifiers":[
        {
            "category":"Communications",
            "type":"Services"
        }
    ],
    "sg:phone":"+61 8 8362 2251",
    "sg:postcode":"5067",
    "sg:province":"SA",
    "sg:tags":[
        "equipment",
        "satellite"
    ],
    "wof:name":"Orbis Technology",
    "wof:placetype":"venue"
},
  "geometry": {"coordinates":[138.62103271500001,-34.9189491272],"type":"Point"}
}