{
  "type": "Feature",
  "properties": {
    "addr:full":"5 Rohs Rd Bendigo VIC 3550",
    "addr:housenumber":"5",
    "addr:postcode":"3550",
    "addr:street":"Rohs Rd",
    "iso:country":"AU",
    "sg:address":"5 Rohs Rd",
    "sg:city":"Bendigo",
    "sg:classifiers":[
        {
            "category":"Food & Beverages",
            "subcategory":"Specialty",
            "type":"Retail Goods"
        }
    ],
    "sg:phone":"+61 3 5443 9411",
    "sg:postcode":"3550",
    "sg:province":"VIC",
    "sg:tags":[
        "product",
        "health"
    ],
    "wof:name":"APB Distribution Pty Ltd",
    "wof:placetype":"venue"
},
  "geometry": {"coordinates":[144.311965942,-36.7458496094],"type":"Point"}
}