{
  "type": "Feature",
  "properties": {
    "addr:full":"Suite 1/ 104 Railway Pde Kogarah NSW 2217",
    "addr:housenumber":"/ 104",
    "addr:postcode":"2217",
    "addr:street":"Railway Pde",
    "iso:country":"AU",
    "sg:address":"Suite 1/ 104 Railway Pde",
    "sg:city":"Kogarah",
    "sg:classifiers":[
        {
            "category":"Health Services",
            "subcategory":"Chiropractor",
            "type":"Services"
        }
    ],
    "sg:phone":"+61 2 9588 5504",
    "sg:postcode":"2217",
    "sg:province":"NSW",
    "wof:name":"Sydney Spinal Care",
    "wof:placetype":"venue"
},
  "geometry": {"coordinates":[151.132553,-33.964069],"type":"Point"}
}