{
  "type": "Feature",
  "properties": {
    "iso:country":"AU",
    "sg:address":"2 Eneabba Drv",
    "sg:city":"Eneabba",
    "sg:classifiers":[
        {
            "category":"Travel",
            "subcategory":"Hotels & Motels",
            "type":"Entertainment"
        }
    ],
    "sg:phone":"+61 8 9955 1077",
    "sg:postcode":"6518",
    "sg:province":"WA",
    "sg:tags":[
        "accommodation"
    ],
    "wof:name":"Sands Tavern",
    "wof:placetype":"venue"
},
  "geometry": {"coordinates":[115.265808,-29.82016],"type":"Point"}
}