{
  "type": "Feature",
  "properties": {
    "addr:full":"17 Parma Crs St Helens Park NSW 2560",
    "addr:housenumber":"17",
    "addr:postcode":"2560",
    "addr:street":"Parma Crs",
    "iso:country":"AU",
    "sg:address":"17 Parma Crs St",
    "sg:city":"Helens Park",
    "sg:classifiers":[
        {
            "category":"Personal",
            "subcategory":"Beauty Salon",
            "type":"Services"
        }
    ],
    "sg:phone":"+61 2 4628 0892",
    "sg:postcode":"2560",
    "sg:province":"NSW",
    "wof:name":"Knopek Tina",
    "wof:placetype":"venue"
},
  "geometry": {"coordinates":[150.80714416500001,-34.1051216125],"type":"Point"}
}