{
  "type": "Feature",
  "properties": {
    "addr:full":"7 Charles St Allenby Gardens SA 5009",
    "addr:housenumber":"7",
    "addr:postcode":"5009",
    "addr:street":"Charles St",
    "iso:country":"AU",
    "sg:address":"7 Charles St",
    "sg:city":"Allenby Gardens",
    "sg:classifiers":[
        {
            "category":"Wholesale",
            "subcategory":"Home Furnishings",
            "type":"Manufacturing & Wholesale Goods"
        }
    ],
    "sg:phone":"+61 8 8340 1588",
    "sg:postcode":"5009",
    "sg:province":"SA",
    "sg:tags":[
        "terrazzo"
    ],
    "wof:name":"Retro Floors",
    "wof:placetype":"venue"
},
  "geometry": {"coordinates":[138.554000855,-34.9052276611],"type":"Point"}
}