{
  "type": "Feature",
  "properties": {
    "addr:full":"23 Quality Drv Dandenong VIC 3175",
    "addr:housenumber":"23",
    "addr:postcode":"3175",
    "addr:street":"Quality Drv",
    "iso:country":"AU",
    "sg:address":"23 Quality Drv",
    "sg:city":"Dandenong",
    "sg:classifiers":[
        {
            "category":"Building & Trades",
            "subcategory":"Plumbing",
            "type":"Services"
        }
    ],
    "sg:phone":"+61 1800 801 210",
    "sg:postcode":"3175",
    "sg:province":"VIC",
    "sg:tags":[
        "fitting",
        "hose",
        "supply"
    ],
    "wof:name":"Linatex Australia Pty Ltd",
    "wof:placetype":"venue"
},
  "geometry": {"coordinates":[145.20510864299999,-38.025806427],"type":"Point"}
}