{
  "type": "Feature",
  "properties": {
    "addr:full":"1/ 219 Ryrie St Geelong VIC 3220",
    "addr:housenumber":"/ 219",
    "addr:postcode":"3220",
    "addr:street":"Ryrie St",
    "iso:country":"AU",
    "sg:address":"1/ 219 Ryrie St",
    "sg:city":"Geelong",
    "sg:classifiers":[
        {
            "category":"Professional",
            "subcategory":"Employment Agencies",
            "type":"Services"
        }
    ],
    "sg:phone":"+61 3 5221 3880",
    "sg:postcode":"3220",
    "sg:province":"VIC",
    "sg:website":"http://www.directrecruitment.com.au",
    "wof:name":"Direct Recruitment",
    "wof:placetype":"venue"
},
  "geometry": {"coordinates":[144.36273199999999,-38.149963],"type":"Point"}
}