{
  "type": "Feature",
  "properties": {
    "iso:country":"AU",
    "sg:address":"44 Halifax Drv",
    "sg:city":"Bunbury",
    "sg:classifiers":[
        {
            "category":"Home & Garden",
            "subcategory":"Building Materials",
            "type":"Retail Goods"
        }
    ],
    "sg:phone":"+61 8 9725 4932",
    "sg:postcode":"6230",
    "sg:province":"WA",
    "sg:tags":[
        "fencing"
    ],
    "wof:name":"Fielders Australia",
    "wof:placetype":"venue"
},
  "geometry": {"coordinates":[115.66964,-33.364601],"type":"Point"}
}