{
  "type": "Feature",
  "properties": {
    "iso:country":"AU",
    "sg:address":"911 Eastern Rd",
    "sg:city":"Traralgon",
    "sg:classifiers":[
        {
            "category":"Professional",
            "subcategory":"Engineering",
            "type":"Services"
        }
    ],
    "sg:phone":"+61 3 5174 6847",
    "sg:postcode":"3844",
    "sg:province":"VIC",
    "sg:tags":[
        "engineer",
        "structural"
    ],
    "wof:name":"Manpower Latrobe Valley Pty Ltd",
    "wof:placetype":"venue"
},
  "geometry": {"coordinates":[146.56216430699999,-38.1906318665],"type":"Point"}
}