{
  "type": "Feature",
  "properties": {
    "addr:full":"16 Phillimore St Fremantle WA 6160",
    "addr:housenumber":"16",
    "addr:postcode":"6160",
    "addr:street":"Phillimore St",
    "iso:country":"AU",
    "sg:address":"16 Phillimore St",
    "sg:city":"Fremantle",
    "sg:classifiers":[
        {
            "category":"Organizations",
            "subcategory":"Professional Association",
            "type":"Services"
        }
    ],
    "sg:phone":"+61 8 9335 2711",
    "sg:postcode":"6160",
    "sg:province":"WA",
    "sg:tags":[
        "organisation",
        "business"
    ],
    "wof:name":"Fremantle First",
    "wof:placetype":"venue"
},
  "geometry": {"coordinates":[115.743179,-32.054092],"type":"Point"}
}