{
  "type": "Feature",
  "properties": {
    "addr:full":"Shop 4/ 54 Austral Tce Katanning WA 6317",
    "addr:housenumber":"shop 4 / 54",
    "addr:postcode":"6317",
    "addr:street":"Austral Tce",
    "iso:country":"AU",
    "sg:address":"Shop 4/ 54 Austral Tce",
    "sg:city":"Katanning",
    "sg:classifiers":[
        {
            "category":"Professional",
            "subcategory":"Computer Services",
            "type":"Services"
        }
    ],
    "sg:phone":"+61 8 9821 7517",
    "sg:postcode":"6317",
    "sg:province":"WA",
    "sg:tags":[
        "consultant",
        "system"
    ],
    "wof:name":"Scott Tidey",
    "wof:placetype":"venue"
},
  "geometry": {"coordinates":[117.552993774,-33.6891365051],"type":"Point"}
}