{
  "type": "Feature",
  "properties": {
    "iso:country":"AU",
    "sg:address":"176 Barnard St",
    "sg:city":"Bendigo",
    "sg:classifiers":[
        {
            "category":"Health Services",
            "subcategory":"Doctor",
            "type":"Services"
        }
    ],
    "sg:phone":"+61 3 5443 5299",
    "sg:postcode":"3550",
    "sg:province":"VIC",
    "sg:tags":[
        "medical",
        "practitioner"
    ],
    "wof:name":"Schepisi C F",
    "wof:placetype":"venue"
},
  "geometry": {"coordinates":[144.275634766,-36.7542991638],"type":"Point"}
}