{
  "type": "Feature",
  "properties": {
    "addr:full":"a 36 Quay St Sanctuary Cove QLD 4212",
    "addr:housenumber":"36",
    "addr:postcode":"4212",
    "addr:street":"A;Quay St",
    "iso:country":"AU",
    "sg:address":"a 36 Quay St",
    "sg:city":"Sanctuary Cove",
    "sg:classifiers":[
        {
            "category":"Shopping",
            "subcategory":"Baby Store",
            "type":"Retail Goods"
        }
    ],
    "sg:phone":"+61 7 5577 9220",
    "sg:postcode":"4212",
    "sg:province":"QLD",
    "sg:tags":[
        "children's",
        "wear"
    ],
    "wof:name":"Sparrow Couture for Kids",
    "wof:placetype":"venue"
},
  "geometry": {"coordinates":[153.35943603499999,-27.8538703918],"type":"Point"}
}