{
  "type": "Feature",
  "properties": {
    "addr:full":"308 Woodward Rd Golden Square VIC 3555",
    "addr:housenumber":"308",
    "addr:postcode":"3555",
    "addr:street":"Woodward Rd",
    "iso:country":"AU",
    "sg:address":"308 Woodward Rd",
    "sg:city":"Golden Square",
    "sg:classifiers":[
        {
            "category":"Wholesale",
            "subcategory":"Meat",
            "type":"Manufacturing & Wholesale Goods"
        }
    ],
    "sg:phone":"+61 1800 355 513",
    "sg:postcode":"3555",
    "sg:province":"VIC",
    "sg:tags":[
        "abattoir"
    ],
    "wof:name":"Bendigo Knackery Service",
    "wof:placetype":"venue"
},
  "geometry": {"coordinates":[144.26565551799999,-36.7779693604],"type":"Point"}
}