{
  "type": "Feature",
  "properties": {
    "addr:full":"280 Peisley St Orange NSW 2800",
    "addr:housenumber":"280",
    "addr:postcode":"2800",
    "addr:street":"Peisley St",
    "iso:country":"AU",
    "sg:address":"280 Peisley St",
    "sg:city":"Orange",
    "sg:classifiers":[
        {
            "category":"Utilities",
            "subcategory":"Cable",
            "type":"Services"
        }
    ],
    "sg:phone":"+61 2 6362 4077",
    "sg:postcode":"2800",
    "sg:province":"NSW",
    "sg:tags":[
        "mechanical"
    ],
    "wof:name":"Central Western Brake & Clutch Service",
    "wof:placetype":"venue"
},
  "geometry": {"coordinates":[149.10458374000001,-33.2802009583],"type":"Point"}
}