{
  "type": "Feature",
  "properties": {
    "addr:full":"26 Main Rd Huonville TAS 7109",
    "addr:housenumber":"26",
    "addr:postcode":"7109",
    "addr:street":"Main Rd",
    "iso:country":"AU",
    "sg:address":"26 Main Rd",
    "sg:city":"Huonville",
    "sg:classifiers":[
        {
            "category":"Personal",
            "subcategory":"Beauty Salon",
            "type":"Services"
        }
    ],
    "sg:phone":"+61 3 6264 1300",
    "sg:postcode":"7109",
    "sg:province":"TAS",
    "sg:tags":[
        "hairdresser"
    ],
    "wof:name":"Hair On Main",
    "wof:placetype":"venue"
},
  "geometry": {"coordinates":[147.04835510300001,-43.0312767029],"type":"Point"}
}