{
  "type": "Feature",
  "properties": {
    "addr:full":"Building 17 Fox Studios Suite 104 Moore Park NSW 2021",
    "addr:housenumber":"17;104",
    "addr:postcode":"2021",
    "addr:street":"Moore",
    "iso:country":"AU",
    "sg:address":"Building 17 Fox Studios Suite 104",
    "sg:city":"Moore Park",
    "sg:classifiers":[
        {
            "category":"Professional",
            "subcategory":"Employment Agencies",
            "type":"Services"
        }
    ],
    "sg:phone":"+61 2 9356 4133",
    "sg:postcode":"2021",
    "sg:province":"NSW",
    "sg:tags":[
        "theatrical",
        "managers",
        "agent",
        "producer"
    ],
    "wof:name":"Pacific Artists Management Pty Ltd",
    "wof:placetype":"venue"
},
  "geometry": {"coordinates":[151.22596740700001,-33.8964805603],"type":"Point"}
}