{
  "type": "Feature",
  "properties": {
    "addr:full":"26 Cross St Brookvale NSW 2100",
    "addr:housenumber":"26",
    "addr:postcode":"2100",
    "addr:street":"Cross St",
    "iso:country":"AU",
    "sg:address":"26 Cross St",
    "sg:city":"Brookvale",
    "sg:classifiers":[
        {
            "category":"Retail",
            "subcategory":"Auto Repair",
            "type":"Services"
        }
    ],
    "sg:phone":"+61 2 9907 1861",
    "sg:postcode":"2100",
    "sg:province":"NSW",
    "sg:tags":[
        "fuel",
        "petrol",
        "injection"
    ],
    "wof:name":"Automotive Computers Australia",
    "wof:placetype":"venue"
},
  "geometry": {"coordinates":[151.26548767099999,-33.7648582458],"type":"Point"}
}