{
  "type": "Feature",
  "properties": {
    "addr:full":"455 Belmont Ave Kewdale WA 6105",
    "addr:housenumber":"455",
    "addr:postcode":"6105",
    "addr:street":"Belmont Ave",
    "iso:country":"AU",
    "sg:address":"455 Belmont Ave",
    "sg:city":"Kewdale",
    "sg:classifiers":[
        {
            "category":"Professional",
            "type":"Services"
        }
    ],
    "sg:phone":"+61 8 9353 3778",
    "sg:postcode":"6105",
    "sg:province":"WA",
    "sg:tags":[
        "transport"
    ],
    "wof:name":"Kimberley Molasses",
    "wof:placetype":"venue"
},
  "geometry": {"coordinates":[115.948318481,-31.9780921936],"type":"Point"}
}