{
  "type": "Feature",
  "properties": {
    "addr:full":"1 Range Rd North Houghton SA 5131",
    "addr:housenumber":"1",
    "addr:postcode":"5131",
    "addr:street":"Range Rd North",
    "iso:country":"AU",
    "sg:address":"1 Range Rd North",
    "sg:city":"Houghton",
    "sg:classifiers":[
        {
            "category":"Shopping",
            "subcategory":"Clothing, Apparel, & Fashions",
            "type":"Retail Goods"
        }
    ],
    "sg:phone":"+61 8 8380 5691",
    "sg:postcode":"5131",
    "sg:province":"SA",
    "sg:tags":[
        "wholesaler",
        "children's",
        "mfrs",
        "wear"
    ],
    "wof:name":"Threads & Trends",
    "wof:placetype":"venue"
},
  "geometry": {"coordinates":[138.75685119600001,-34.8023262024],"type":"Point"}
}