{
  "type": "Feature",
  "properties": {
    "addr:full":"34 Free St Newmarket QLD 4051",
    "addr:housenumber":"34",
    "addr:postcode":"4051",
    "addr:street":"Free St",
    "iso:country":"AU",
    "sg:address":"34 Free St",
    "sg:city":"Newmarket",
    "sg:classifiers":[
        {
            "category":"Travel",
            "subcategory":"Hostel",
            "type":"Entertainment"
        }
    ],
    "sg:phone":"+61 7 3352 6488",
    "sg:postcode":"4051",
    "sg:province":"QLD",
    "sg:tags":[
        "home"
    ],
    "wof:name":"&#034;Woodlands Park&#034;",
    "wof:placetype":"venue"
},
  "geometry": {"coordinates":[153.00416564899999,-27.4416904449],"type":"Point"}
}