{
  "type": "Feature",
  "properties": {
    "addr:full":"19 William St Beaudesert QLD 4285",
    "addr:housenumber":"19",
    "addr:postcode":"4285",
    "addr:street":"William St",
    "iso:country":"AU",
    "sg:address":"19 William St",
    "sg:city":"Beaudesert",
    "sg:classifiers":[
        {
            "category":"Professional",
            "subcategory":"Accounting & Tax Preparation",
            "type":"Services"
        }
    ],
    "sg:phone":"+61 7 5541 3055",
    "sg:postcode":"4285",
    "sg:province":"QLD",
    "sg:tags":[
        "consultant",
        "taxation"
    ],
    "wof:name":"Staib Accounting & Tax",
    "wof:placetype":"venue"
},
  "geometry": {"coordinates":[152.996475,-27.988392],"type":"Point"}
}