{
  "type": "Feature",
  "properties": {
    "addr:full":"70 Cavagna Rd Sedgwick VIC 3551",
    "addr:housenumber":"70",
    "addr:postcode":"3551",
    "addr:street":"Cavagna Rd",
    "iso:country":"AU",
    "sg:address":"70 Cavagna Rd",
    "sg:city":"Sedgwick",
    "sg:classifiers":[
        {
            "category":"Insurance",
            "subcategory":"Hazard Insurance",
            "type":"Services"
        }
    ],
    "sg:phone":"+61 3 5439 6305",
    "sg:postcode":"3551",
    "sg:province":"VIC",
    "sg:tags":[
        "loss",
        "adjuster",
        "assessor"
    ],
    "wof:name":"Naunton D & Co",
    "wof:placetype":"venue"
},
  "geometry": {"coordinates":[144.32781982399999,-36.85679245],"type":"Point"}
}