{
  "type": "Feature",
  "properties": {
    "addr:full":"Cnr Deshon & Atherton Sts Woolloongabba QLD 4102",
    "addr:postcode":"4102",
    "addr:street":"Cnr",
    "iso:country":"AU",
    "sg:address":"Cnr Deshon & Atherton Sts",
    "sg:city":"Woolloongabba",
    "sg:classifiers":[
        {
            "category":"Home & Garden",
            "subcategory":"Furniture",
            "type":"Retail Goods"
        }
    ],
    "sg:phone":"+61 7 3891 6030",
    "sg:postcode":"4102",
    "sg:province":"QLD",
    "sg:tags":[
        "repair",
        "restoration"
    ],
    "wof:name":"Strippers The",
    "wof:placetype":"venue"
},
  "geometry": {"coordinates":[153.041259766,-27.4916992188],"type":"Point"}
}