{
  "type": "Feature",
  "properties": {
    "iso:country":"AU",
    "sg:address":"66 - 74 Morayfield Rd",
    "sg:city":"Morayfield",
    "sg:classifiers":[
        {
            "category":"Food & Beverages",
            "subcategory":"Liquor & Beverages",
            "type":"Retail Goods"
        }
    ],
    "sg:phone":"+61 7 5495 8083",
    "sg:postcode":"4506",
    "sg:province":"QLD",
    "sg:tags":[
        "store"
    ],
    "wof:name":"Dukes Cellars Morayfield",
    "wof:placetype":"venue"
},
  "geometry": {"coordinates":[152.949752808,-27.1099586487],"type":"Point"}
}