{
  "type": "Feature",
  "properties": {
    "iso:country":"AU",
    "sg:address":"55 Canara St",
    "sg:city":"Cranbrook",
    "sg:classifiers":[
        {
            "category":"Wholesale",
            "subcategory":"Machinery & Supplies",
            "type":"Manufacturing & Wholesale Goods"
        }
    ],
    "sg:phone":"+61 7 4779 5455",
    "sg:postcode":"4814",
    "sg:province":"QLD",
    "sg:tags":[
        "process",
        "instrument",
        "control"
    ],
    "wof:name":"Control & Measurement NQ P/L",
    "wof:placetype":"venue"
},
  "geometry": {"coordinates":[146.751862,-19.303488],"type":"Point"}
}