{
  "type": "Feature",
  "properties": {
    "addr:full":"Shop 213 Warringah Mall Pittwater Rd Brookvale NSW 2100",
    "addr:housenumber":"213",
    "addr:postcode":"2100",
    "addr:street":"Warringah Mall Pittwater Rd",
    "iso:country":"AU",
    "sg:address":"Shop 213 Warringah Mall Pittwater Rd",
    "sg:city":"Brookvale",
    "sg:classifiers":[
        {
            "category":"Shopping",
            "subcategory":"Clothing, Apparel, & Fashions",
            "type":"Retail Goods"
        }
    ],
    "sg:phone":"+61 2 9905 2886",
    "sg:postcode":"2100",
    "sg:province":"NSW",
    "sg:tags":[
        "lady",
        "wear"
    ],
    "wof:name":"Table Eight",
    "wof:placetype":"venue"
},
  "geometry": {"coordinates":[151.27305602999999,-33.7611312866],"type":"Point"}
}