{
  "type": "Feature",
  "properties": {
    "addr:full":"39 Brodie St Rydalmere NSW 2116",
    "addr:housenumber":"39",
    "addr:postcode":"2116",
    "addr:street":"Brodie St",
    "iso:country":"AU",
    "sg:address":"39 Brodie St",
    "sg:city":"Rydalmere",
    "sg:classifiers":[
        {
            "category":"Government",
            "subcategory":"Fire Station",
            "type":"Public Place"
        }
    ],
    "sg:phone":"+61 2 9638 1300",
    "sg:postcode":"2116",
    "sg:province":"NSW",
    "sg:tags":[
        "equipment",
        "protection",
        "consultant"
    ],
    "wof:name":"Firequip Pty Ltd",
    "wof:placetype":"venue"
},
  "geometry": {"coordinates":[151.01878356899999,-33.901058197],"type":"Point"}
}