{
  "type": "Feature",
  "properties": {
    "iso:country":"AU",
    "sg:address":"4 Rafferty Rd",
    "sg:city":"Mandurah",
    "sg:classifiers":[
        {
            "category":"Fast Food",
            "type":"Food & Drink"
        }
    ],
    "sg:phone":"+61 8 9535 4462",
    "sg:postcode":"6210",
    "sg:province":"WA",
    "sg:tags":[
        "away",
        "take"
    ],
    "wof:name":"Dial-A-Snack",
    "wof:placetype":"venue"
},
  "geometry": {"coordinates":[115.74408,-32.517323],"type":"Point"}
}