{
  "type": "Feature",
  "properties": {
    "addr:full":"190 Napper Rd Arundel QLD 4214",
    "addr:housenumber":"190",
    "addr:postcode":"4214",
    "addr:street":"Napper Rd",
    "iso:country":"AU",
    "sg:address":"190 Napper Rd",
    "sg:city":"Arundel",
    "sg:classifiers":[
        {
            "category":"Social Services",
            "subcategory":"Child Care",
            "type":"Services"
        }
    ],
    "sg:phone":"+61 7 5594 9388",
    "sg:postcode":"4214",
    "sg:province":"QLD",
    "wof:name":"Club Junior Arundel",
    "wof:placetype":"venue"
},
  "geometry": {"coordinates":[153.360794067,-27.9455337524],"type":"Point"}
}