{
  "type": "Feature",
  "properties": {
    "addr:full":"342 Pacific Hwy Lindfield NSW 2070",
    "addr:housenumber":"342",
    "addr:postcode":"2070",
    "addr:street":"Pacific Hwy",
    "iso:country":"AU",
    "sg:address":"342 Pacific Hwy",
    "sg:city":"Lindfield",
    "sg:classifiers":[
        {
            "category":"Retail",
            "subcategory":"Repair Shop",
            "type":"Services"
        }
    ],
    "sg:phone":"+61 2 9415 6388",
    "sg:postcode":"2070",
    "sg:province":"NSW",
    "sg:tags":[
        "maintenance",
        "pool",
        "swimming"
    ],
    "wof:name":"Swimart Pool & Spa Services",
    "wof:placetype":"venue"
},
  "geometry": {"coordinates":[151.16741943400001,-33.7739677429],"type":"Point"}
}