{
  "type": "Feature",
  "properties": {
    "iso:country":"AU",
    "sg:address":"92 Woodlark St",
    "sg:city":"Lismore",
    "sg:classifiers":[
        {
            "category":"Real Estate",
            "subcategory":"Real Estate Agent",
            "type":"Services"
        }
    ],
    "sg:phone":"+61 2 6621 9100",
    "sg:postcode":"2480",
    "sg:province":"NSW",
    "wof:name":"Century 21 Real Estate",
    "wof:placetype":"venue"
},
  "geometry": {"coordinates":[153.27888488799999,-28.8073196411],"type":"Point"}
}