{
  "type": "Feature",
  "properties": {
    "addr:full":"PO Box 187 Calliope QLD 4680",
    "addr:postcode":"4680",
    "iso:country":"AU",
    "sg:address":"PO Box 187",
    "sg:city":"Calliope",
    "sg:classifiers":[
        {
            "category":"Building & Trades",
            "subcategory":"Construction",
            "type":"Services"
        }
    ],
    "sg:phone":"+61 408 851 804",
    "sg:postcode":"4680",
    "sg:province":"QLD",
    "sg:tags":[
        "contractor"
    ],
    "wof:name":"Gene Rosenblatt Builder",
    "wof:placetype":"venue"
},
  "geometry": {"coordinates":[151.21209716800001,-23.9871997833],"type":"Point"}
}