{
  "type": "Feature",
  "properties": {
    "addr:full":"6 Jane St Nowra NSW 2541",
    "addr:housenumber":"6",
    "addr:postcode":"2541",
    "addr:street":"Jane St",
    "iso:country":"AU",
    "sg:address":"6 Jane St",
    "sg:city":"Nowra",
    "sg:classifiers":[
        {
            "category":"Autos & Motor Vehicles",
            "subcategory":"Auto Supplies",
            "type":"Retail Goods"
        }
    ],
    "sg:phone":"+61 2 4423 1288",
    "sg:postcode":"2541",
    "sg:province":"NSW",
    "sg:tags":[
        "part",
        "cycles",
        "accessory"
    ],
    "wof:name":"Foxy Pocket Bikes",
    "wof:placetype":"venue"
},
  "geometry": {"coordinates":[150.604644775,-34.8763237],"type":"Point"}
}