{
  "type": "Feature",
  "properties": {
    "addr:full":"109 Broome St Cottesloe WA 6011",
    "addr:housenumber":"109",
    "addr:postcode":"6011",
    "addr:street":"Broome St",
    "iso:country":"AU",
    "sg:address":"109 Broome St",
    "sg:city":"Cottesloe",
    "sg:classifiers":[
        {
            "category":"Government",
            "subcategory":"Department Of Motor Vehicles",
            "type":"Public Place"
        }
    ],
    "sg:phone":"+61 8 9285 5000",
    "sg:postcode":"6011",
    "sg:province":"WA",
    "sg:tags":[
        "organisation",
        "local"
    ],
    "wof:name":"Cottesloe Town Council",
    "wof:placetype":"venue"
},
  "geometry": {"coordinates":[115.75601196300001,-31.9934711456],"type":"Point"}
}