{
  "type": "Feature",
  "properties": {
    "iso:country":"AU",
    "sg:address":"6 Euston St",
    "sg:city":"Rydalmere",
    "sg:classifiers":[
        {
            "category":"Professional",
            "subcategory":"Printing & Photocopies",
            "type":"Services"
        }
    ],
    "sg:phone":"+61 2 9638 1299",
    "sg:postcode":"2116",
    "sg:province":"NSW",
    "sg:tags":[
        "screen",
        "printer"
    ],
    "wof:name":"Craftech Pty Ltd",
    "wof:placetype":"venue"
},
  "geometry": {"coordinates":[151.03457641599999,-33.8115921021],"type":"Point"}
}