{
  "type": "Feature",
  "properties": {
    "iso:country":"AU",
    "sg:address":"Farm 1845",
    "sg:city":"Lake Wyangan",
    "sg:classifiers":[
        {
            "category":"Farming",
            "subcategory":"Orchard",
            "type":"Manufacturing & Wholesale Goods"
        }
    ],
    "sg:phone":"+61 2 6962 4894",
    "sg:postcode":"2680",
    "sg:province":"NSW",
    "sg:tags":[
        "citrus",
        "fruit",
        "grower"
    ],
    "wof:name":"Scott F D & A G",
    "wof:placetype":"venue"
},
  "geometry": {"coordinates":[146.042191,-34.280251],"type":"Point"}
}