{
  "type": "Feature",
  "properties": {
    "addr:full":"PO Box 25 Mooroopna VIC 3629",
    "addr:postcode":"3629",
    "iso:country":"AU",
    "sg:address":"PO Box 25",
    "sg:city":"Mooroopna",
    "sg:classifiers":[
        {
            "category":"Utilities",
            "subcategory":"Water",
            "type":"Services"
        }
    ],
    "sg:phone":"+61 3 5823 5123",
    "sg:postcode":"3629",
    "sg:province":"VIC",
    "sg:tags":[
        "hot",
        "system"
    ],
    "wof:name":"Bolitho Stephen",
    "wof:placetype":"venue"
},
  "geometry": {"coordinates":[145.35250854500001,-36.3956413269],"type":"Point"}
}