{
  "type": "Feature",
  "properties": {
    "addr:full":"58 Forman Ave Glenwood NSW 2768",
    "addr:housenumber":"58",
    "addr:postcode":"2768",
    "addr:street":"Forman Ave",
    "iso:country":"AU",
    "sg:address":"58 Forman Ave",
    "sg:city":"Glenwood",
    "sg:classifiers":[
        {
            "category":"Education",
            "subcategory":"Vocational School",
            "type":"Public Place"
        }
    ],
    "sg:phone":"+61 2 8824 3682",
    "sg:postcode":"2768",
    "sg:province":"NSW",
    "sg:tags":[
        "cake",
        "decorating",
        "decorator"
    ],
    "wof:name":"Cakes & Flowers",
    "wof:placetype":"venue"
},
  "geometry": {"coordinates":[150.934372,-33.733128],"type":"Point"}
}