{
  "type": "Feature",
  "properties": {
    "iso:country":"AU",
    "sg:address":"5 Bullecourt Ave",
    "sg:city":"Milperra",
    "sg:classifiers":[
        {
            "category":"Autos & Motor Vehicles",
            "subcategory":"Fuel & Gas Station",
            "type":"Retail Goods"
        }
    ],
    "sg:phone":"+61 2 9771 6189",
    "sg:postcode":"2214",
    "sg:province":"NSW",
    "wof:name":"BP Australia Pty Ltd",
    "wof:placetype":"venue"
},
  "geometry": {"coordinates":[150.98872399999999,-33.937546],"type":"Point"}
}