{
  "type": "Feature",
  "properties": {
    "addr:full":"Lawrenny Estate Main Rd Ouse TAS 7140",
    "addr:postcode":"7140",
    "addr:street":"Main Rd",
    "iso:country":"AU",
    "sg:address":"Lawrenny Estate Main Rd",
    "sg:city":"Ouse",
    "sg:classifiers":[
        {
            "category":"Utilities",
            "subcategory":"Cable",
            "type":"Services"
        }
    ],
    "sg:phone":"+61 3 6287 1225",
    "sg:postcode":"7140",
    "sg:province":"TAS",
    "sg:tags":[
        "agricultural",
        "aerial"
    ],
    "wof:name":"Air Spreaders Tasmania",
    "wof:placetype":"venue"
},
  "geometry": {"coordinates":[146.666595,-42.443531],"type":"Point"}
}