{
  "type": "Feature",
  "properties": {
    "addr:full":"9 Dixons Rd Cardinia VIC 3978",
    "addr:housenumber":"9",
    "addr:postcode":"3978",
    "addr:street":"Dixons Rd",
    "iso:country":"AU",
    "sg:address":"9 Dixons Rd",
    "sg:city":"Cardinia",
    "sg:classifiers":[
        {
            "category":"Building & Trades",
            "subcategory":"Plumbing",
            "type":"Services"
        }
    ],
    "sg:phone":"+61 409 236 738",
    "sg:postcode":"3978",
    "sg:province":"VIC",
    "sg:tags":[
        "plumber",
        "gasfitters"
    ],
    "wof:name":"Allan Plumbing & Gas Services",
    "wof:placetype":"venue"
},
  "geometry": {"coordinates":[145.42283630399999,-38.1472358704],"type":"Point"}
}