{
  "type": "Feature",
  "properties": {
    "iso:country":"AU",
    "sg:address":"4 Kuppa Ave",
    "sg:city":"Malua Bay",
    "sg:classifiers":[
        {
            "category":"Travel",
            "subcategory":"Hotels & Motels",
            "type":"Entertainment"
        }
    ],
    "sg:phone":"+61 1800 026 455",
    "sg:postcode":"2536",
    "sg:province":"NSW",
    "wof:name":"Malua Bay Inn Motel",
    "wof:placetype":"venue"
},
  "geometry": {"coordinates":[150.22929382300001,-35.7921524048],"type":"Point"}
}