{
  "type": "Feature",
  "properties": {
    "addr:full":"55 Main Rd Claremont TAS 7011",
    "addr:housenumber":"55",
    "addr:postcode":"7011",
    "addr:street":"Main Rd",
    "iso:country":"AU",
    "sg:address":"55 Main Rd",
    "sg:city":"Claremont",
    "sg:classifiers":[
        {
            "category":"Communications",
            "subcategory":"Film & Video Production",
            "type":"Services"
        }
    ],
    "sg:phone":"+61 3 6249 2111",
    "sg:postcode":"7011",
    "sg:province":"TAS",
    "sg:tags":[
        "dvd",
        "library"
    ],
    "wof:name":"Video City",
    "wof:placetype":"venue"
},
  "geometry": {"coordinates":[147.253616333,-42.7894134521],"type":"Point"}
}