{
  "type": "Feature",
  "properties": {
    "addr:full":"12 Day Rd Rockingham WA 6168",
    "addr:housenumber":"12",
    "addr:postcode":"6168",
    "addr:street":"Day Rd",
    "iso:country":"AU",
    "sg:address":"12 Day Rd",
    "sg:city":"Rockingham",
    "sg:classifiers":[
        {
            "category":"Train Station",
            "subcategory":"Light Rail",
            "type":"Transportation"
        }
    ],
    "sg:phone":"+61 8 9529 1145",
    "sg:postcode":"6168",
    "sg:province":"WA",
    "sg:tags":[
        "equipment",
        "energy",
        "solar"
    ],
    "wof:name":"Delux Pool Heating",
    "wof:placetype":"venue"
},
  "geometry": {"coordinates":[115.77407100000001,-32.275631],"type":"Point"}
}