{
  "type": "Feature",
  "properties": {
    "addr:full":"1032 Main Rd Eltham VIC 3095",
    "addr:housenumber":"1032",
    "addr:postcode":"3095",
    "addr:street":"Main Rd",
    "iso:country":"AU",
    "sg:address":"1032 Main Rd",
    "sg:city":"Eltham",
    "sg:classifiers":[
        {
            "category":"Shopping",
            "subcategory":"Shoes",
            "type":"Retail Goods"
        }
    ],
    "sg:phone":"+61 3 9431 0588",
    "sg:postcode":"3095",
    "sg:province":"VIC",
    "sg:tags":[
        "footwear"
    ],
    "wof:name":"Cinori Shoes",
    "wof:placetype":"venue"
},
  "geometry": {"coordinates":[145.149124145,-37.7126426697],"type":"Point"}
}