{
  "type": "Feature",
  "properties": {
    "addr:full":"C 3 Imperial Arcade Castlereagh St Sydney NSW 2000",
    "addr:housenumber":"3",
    "addr:postcode":"2000",
    "addr:street":"C;Imperial Arcade Castlereagh St",
    "iso:country":"AU",
    "sg:address":"C 3 Imperial Arcade Castlereagh St",
    "sg:city":"Sydney",
    "sg:classifiers":[
        {
            "category":"Shopping",
            "subcategory":"Jewelry",
            "type":"Retail Goods"
        }
    ],
    "sg:phone":"+61 2 9233 1418",
    "sg:postcode":"2000",
    "sg:province":"NSW",
    "sg:tags":[
        "jeweller"
    ],
    "wof:name":"Kalmar Antiques Pty Ltd",
    "wof:placetype":"venue"
},
  "geometry": {"coordinates":[151.20957946799999,-33.8699073792],"type":"Point"}
}