{
  "type": "Feature",
  "properties": {
    "iso:country":"AU",
    "sg:address":"Building D 70 Fraser Rd",
    "sg:city":"Duntroon",
    "sg:classifiers":[
        {
            "category":"Fast Food",
            "type":"Food & Drink"
        }
    ],
    "sg:phone":"+61 2 6275 9455",
    "sg:postcode":"2600",
    "sg:province":"ACT",
    "sg:tags":[
        "away",
        "take"
    ],
    "wof:name":"Duntroon Family Store",
    "wof:placetype":"venue"
},
  "geometry": {"coordinates":[149.09715270999999,-35.3123931885],"type":"Point"}
}