{
  "type": "Feature",
  "properties": {
    "addr:full":"Fcty 1/ 13 Cumberland Drv Seaford VIC 3198",
    "addr:housenumber":"/ 13",
    "addr:postcode":"3198",
    "addr:street":"Cumberland Drv",
    "iso:country":"AU",
    "sg:address":"Fcty 1/ 13 Cumberland Drv",
    "sg:city":"Seaford",
    "sg:classifiers":[
        {
            "category":"Home & Garden",
            "subcategory":"Building Materials",
            "type":"Retail Goods"
        }
    ],
    "sg:phone":"+61 3 9776 4422",
    "sg:postcode":"3198",
    "sg:province":"VIC",
    "sg:tags":[
        "concrete",
        "screeding",
        "machinery",
        "trowelling"
    ],
    "wof:name":"Tools Equipment & Machinery Services",
    "wof:placetype":"venue"
},
  "geometry": {"coordinates":[145.13929748499999,-38.1134223938],"type":"Point"}
}