{
  "type": "Feature",
  "properties": {
    "iso:country":"AU",
    "sg:address":"Shop 8B The Bay Arcade 478 The Esplanade",
    "sg:city":"Warners Bay",
    "sg:classifiers":[
        {
            "category":"Health Services",
            "subcategory":"Dentist",
            "type":"Services"
        }
    ],
    "sg:phone":"+61 2 4948 9863",
    "sg:postcode":"2282",
    "sg:province":"NSW",
    "sg:tags":[
        "dental",
        "prosthetist"
    ],
    "wof:name":"Olympic Denture Clinic",
    "wof:placetype":"venue"
},
  "geometry": {"coordinates":[151.64479064899999,-32.9750442505],"type":"Point"}
}