{
  "type": "Feature",
  "properties": {
    "iso:country":"AU",
    "sg:address":"Shop 5/57 Greta Rd",
    "sg:city":"Wangaratta",
    "sg:classifiers":[
        {
            "category":"Communications",
            "subcategory":"Film & Video Production",
            "type":"Services"
        }
    ],
    "sg:phone":"+61 3 5721 3733",
    "sg:postcode":"3677",
    "sg:province":"VIC",
    "sg:tags":[
        "shutter",
        "window",
        "roller"
    ],
    "wof:name":"Daley Window Furnishings",
    "wof:placetype":"venue"
},
  "geometry": {"coordinates":[146.313964844,-36.3683547974],"type":"Point"}
}