{
  "type": "Feature",
  "properties": {
    "addr:full":"16 Tedrake St Willagee WA 6156",
    "addr:housenumber":"16",
    "addr:postcode":"6156",
    "addr:street":"Tedrake St",
    "iso:country":"AU",
    "sg:address":"16 Tedrake St",
    "sg:city":"Willagee",
    "sg:classifiers":[
        {
            "category":"Manufacturing",
            "subcategory":"Glass & Minerals",
            "type":"Manufacturing & Wholesale Goods"
        }
    ],
    "sg:phone":"+61 8 9331 5858",
    "sg:postcode":"6156",
    "sg:province":"WA",
    "sg:tags":[
        "stained"
    ],
    "wof:name":"Seabreeze Leadlights",
    "wof:placetype":"venue"
},
  "geometry": {"coordinates":[115.81210299999999,-32.052395],"type":"Point"}
}