{
  "type": "Feature",
  "properties": {
    "iso:country":"AU",
    "sg:address":"38- 42 Frazer St",
    "sg:city":"Leichhardt",
    "sg:classifiers":[
        {
            "category":"Retail",
            "subcategory":"Event Space",
            "type":"Services"
        }
    ],
    "sg:phone":"+61 1300 235 568",
    "sg:postcode":"2040",
    "sg:province":"NSW",
    "sg:tags":[
        "function",
        "organiser"
    ],
    "wof:name":"Navarra Group Pty Ltd",
    "wof:placetype":"venue"
},
  "geometry": {"coordinates":[151.152939,-33.870964],"type":"Point"}
}