{
  "type": "Feature",
  "properties": {
    "addr:full":"99 Browns Rd Wahroonga NSW 2076",
    "addr:housenumber":"99",
    "addr:postcode":"2076",
    "addr:street":"Browns Rd",
    "iso:country":"AU",
    "sg:address":"99 Browns Rd",
    "sg:city":"Wahroonga",
    "sg:classifiers":[
        {
            "category":"Professional",
            "subcategory":"Management & Consulting",
            "type":"Services"
        }
    ],
    "sg:phone":"+61 2 9489 6692",
    "sg:postcode":"2076",
    "sg:province":"NSW",
    "sg:tags":[
        "consultant"
    ],
    "wof:name":"Solness Consulting Pty Ltd",
    "wof:placetype":"venue"
},
  "geometry": {"coordinates":[151.09213256800001,-33.7347106934],"type":"Point"}
}