{
  "type": "Feature",
  "properties": {
    "addr:full":"10 Church St Newbridge NSW 2795",
    "addr:housenumber":"10",
    "addr:postcode":"2795",
    "addr:street":"Church St",
    "iso:country":"AU",
    "sg:address":"10 Church St",
    "sg:city":"Newbridge",
    "sg:classifiers":[
        {
            "category":"Home & Garden",
            "subcategory":"Garden Supply",
            "type":"Retail Goods"
        }
    ],
    "sg:phone":"+61 2 6368 1081",
    "sg:postcode":"2795",
    "sg:province":"NSW",
    "sg:tags":[
        "nursery"
    ],
    "wof:name":"Newbridge Cottage Garden",
    "wof:placetype":"venue"
},
  "geometry": {"coordinates":[149.55221557600001,-33.4893341064],"type":"Point"}
}