{
  "type": "Feature",
  "properties": {
    "addr:full":"2 Mellefont St Gladstone QLD 4680",
    "addr:housenumber":"2",
    "addr:postcode":"4680",
    "addr:street":"Mellefont St",
    "iso:country":"AU",
    "sg:address":"2 Mellefont St",
    "sg:city":"Gladstone",
    "sg:classifiers":[
        {
            "category":"Health Services",
            "subcategory":"Chiropractor",
            "type":"Services"
        }
    ],
    "sg:phone":"+61 7 4972 7807",
    "sg:postcode":"4680",
    "sg:province":"QLD",
    "wof:name":"Owen, John",
    "wof:placetype":"venue"
},
  "geometry": {"coordinates":[151.24336242699999,-23.8634052277],"type":"Point"}
}