{
  "type": "Feature",
  "properties": {
    "addr:full":"35 Platform St Lidcombe NSW 2141",
    "addr:housenumber":"35",
    "addr:postcode":"2141",
    "addr:street":"Platform St",
    "iso:country":"AU",
    "sg:address":"35 Platform St",
    "sg:city":"Lidcombe",
    "sg:classifiers":[
        {
            "category":"Home & Garden",
            "subcategory":"Building Materials",
            "type":"Retail Goods"
        }
    ],
    "sg:phone":"+61 437 266 442",
    "sg:postcode":"2141",
    "sg:province":"NSW",
    "sg:tags":[
        "lawn",
        "cutting",
        "maintenance"
    ],
    "wof:name":"J P's Lawn Moving Services",
    "wof:placetype":"venue"
},
  "geometry": {"coordinates":[151.05133056599999,-33.8580665588],"type":"Point"}
}