{
  "type": "Feature",
  "properties": {
    "iso:country":"AU",
    "sg:address":"138 Percival Rd",
    "sg:city":"Stanmore",
    "sg:classifiers":[
        {
            "category":"Fast Food",
            "type":"Food & Drink"
        }
    ],
    "sg:phone":"+61 2 9572 8497",
    "sg:postcode":"2048",
    "sg:province":"NSW",
    "sg:tags":[
        "away",
        "take"
    ],
    "wof:name":"Station Take Away",
    "wof:placetype":"venue"
},
  "geometry": {"coordinates":[151.164154,-33.893566],"type":"Point"}
}