{
  "type": "Feature",
  "properties": {
    "iso:country":"AU",
    "sg:address":"86 Lytton Rd",
    "sg:city":"East Brisbane",
    "sg:classifiers":[
        {
            "category":"Professional",
            "subcategory":"Art Services",
            "type":"Services"
        }
    ],
    "sg:phone":"+61 7 3896 6600",
    "sg:postcode":"4169",
    "sg:province":"QLD",
    "sg:tags":[
        "graphic",
        "designer"
    ],
    "wof:name":"Dot Dash",
    "wof:placetype":"venue"
},
  "geometry": {"coordinates":[153.045196533,-27.4793624878],"type":"Point"}
}