{
  "type": "Feature",
  "properties": {
    "addr:full":"59 Dammans Rd Warburton VIC 3799",
    "addr:housenumber":"59",
    "addr:postcode":"3799",
    "addr:street":"Dammans Rd",
    "iso:country":"AU",
    "sg:address":"59 Dammans Rd",
    "sg:city":"Warburton",
    "sg:classifiers":[
        {
            "category":"Retail",
            "subcategory":"Auto Repair",
            "type":"Services"
        }
    ],
    "sg:phone":"+61 3 5966 5271",
    "sg:postcode":"3799",
    "sg:province":"VIC",
    "sg:tags":[
        "beater",
        "painter",
        "panel"
    ],
    "wof:name":"Luck Smash Repairers",
    "wof:placetype":"venue"
},
  "geometry": {"coordinates":[145.696655273,-37.7504196167],"type":"Point"}
}