{
  "type": "Feature",
  "properties": {
    "addr:full":"8 Kortum Drv Burleigh Heads QLD 4220",
    "addr:housenumber":"8",
    "addr:postcode":"4220",
    "addr:street":"Kortum Drv",
    "iso:country":"AU",
    "sg:address":"8 Kortum Drv",
    "sg:city":"Burleigh Heads",
    "sg:classifiers":[
        {
            "category":"Home & Garden",
            "subcategory":"Carpets & Floor Coverings",
            "type":"Retail Goods"
        }
    ],
    "sg:phone":"+61 7 5535 0688",
    "sg:postcode":"4220",
    "sg:province":"QLD",
    "sg:tags":[
        "tile",
        "wall"
    ],
    "sg:website":"http://www.burleightiles.com.au",
    "wof:name":"Burleigh Tiles & Slate",
    "wof:placetype":"venue"
},
  "geometry": {"coordinates":[153.44136047399999,-28.1019649506],"type":"Point"}
}