{
  "type": "Feature",
  "properties": {
    "addr:full":"106 Sinclair Drv Carole Park QLD 4300",
    "addr:housenumber":"106",
    "addr:postcode":"4300",
    "addr:street":"Sinclair Drv",
    "iso:country":"AU",
    "sg:address":"106 Sinclair Drv",
    "sg:city":"Carole Park",
    "sg:classifiers":[
        {
            "category":"Professional",
            "subcategory":"Art Services",
            "type":"Services"
        }
    ],
    "sg:phone":"+61 419 643 550",
    "sg:postcode":"4300",
    "sg:province":"QLD",
    "sg:tags":[
        "decorator",
        "painter"
    ],
    "wof:name":"Dominko Painters",
    "wof:placetype":"venue"
},
  "geometry": {"coordinates":[152.94070434599999,-27.6191387177],"type":"Point"}
}