{
  "type": "Feature",
  "properties": {
    "addr:full":"1 Dunraven Crt Langwarrin VIC 3910",
    "addr:housenumber":"1",
    "addr:postcode":"3910",
    "addr:street":"Dunraven Crt",
    "iso:country":"AU",
    "sg:address":"1 Dunraven Crt",
    "sg:city":"Langwarrin",
    "sg:classifiers":[
        {
            "category":"Building & Trades",
            "subcategory":"Cleaning & Sanitation",
            "type":"Services"
        }
    ],
    "sg:phone":"+61 414 579 442",
    "sg:postcode":"3910",
    "sg:province":"VIC",
    "sg:tags":[
        "window"
    ],
    "wof:name":"K & S Window Cleaning",
    "wof:placetype":"venue"
},
  "geometry": {"coordinates":[145.18356323200001,-38.1475067139],"type":"Point"}
}