{
  "type": "Feature",
  "properties": {
    "iso:country":"AU",
    "sg:address":"2nd Flr, ACT Health Bldg, Cnr Moore & Alinga Sts",
    "sg:city":"Canberra City",
    "sg:classifiers":[
        {
            "category":"Travel",
            "subcategory":"Bed & Breakfast",
            "type":"Entertainment"
        }
    ],
    "sg:phone":"+61 2 6207 9977",
    "sg:postcode":"2601",
    "sg:province":"ACT",
    "sg:tags":[
        "control",
        "system",
        "wetting"
    ],
    "wof:name":"Continence Promotion Centre",
    "wof:placetype":"venue"
},
  "geometry": {"coordinates":[149.13006591800001,-35.2784805298],"type":"Point"}
}