{
  "type": "Feature",
  "properties": {
    "addr:full":"90 Malcolm Rd Braeside VIC 3195",
    "addr:housenumber":"90",
    "addr:postcode":"3195",
    "addr:street":"Malcolm Rd",
    "iso:country":"AU",
    "sg:address":"90 Malcolm Rd",
    "sg:city":"Braeside",
    "sg:classifiers":[
        {
            "category":"Wholesale",
            "subcategory":"Machinery & Supplies",
            "type":"Manufacturing & Wholesale Goods"
        }
    ],
    "sg:phone":"+61 3 9587 3230",
    "sg:postcode":"3195",
    "sg:province":"VIC",
    "sg:tags":[
        "machine",
        "tool",
        "engineer"
    ],
    "wof:name":"Parkanson Australia",
    "wof:placetype":"venue"
},
  "geometry": {"coordinates":[145.112228394,-38.0012321472],"type":"Point"}
}