{
  "type": "Feature",
  "properties": {
    "iso:country":"AU",
    "sg:address":"25 Florence Ave",
    "sg:city":"Blair Athol",
    "sg:classifiers":[
        {
            "category":"Professional",
            "subcategory":"Computer Services",
            "type":"Services"
        }
    ],
    "sg:phone":"+61 8 8260 3881",
    "sg:postcode":"5084",
    "sg:province":"SA",
    "sg:tags":[
        "consultant",
        "system"
    ],
    "wof:name":"Cafbent Pty Ltd",
    "wof:placetype":"venue"
},
  "geometry": {"coordinates":[138.595947266,-34.8602523804],"type":"Point"}
}