{
  "type": "Feature",
  "properties": {
    "iso:country":"AU",
    "sg:address":"36- 42 Short St",
    "sg:city":"Mudgee",
    "sg:classifiers":[
        {
            "category":"Sports & Exercise",
            "subcategory":"Gym",
            "type":"Entertainment"
        }
    ],
    "sg:phone":"+61 2 6372 3955",
    "sg:postcode":"2850",
    "sg:province":"NSW",
    "sg:tags":[
        "health",
        "fitness"
    ],
    "wof:name":"Countryfit Health & Fitness",
    "wof:placetype":"venue"
},
  "geometry": {"coordinates":[149.582245,-32.58884],"type":"Point"}
}