{
  "type": "Feature",
  "properties": {
    "addr:full":"2 Susan Ave Padstow NSW 2211",
    "addr:housenumber":"2",
    "addr:postcode":"2211",
    "addr:street":"Susan Ave",
    "iso:country":"AU",
    "sg:address":"2 Susan Ave",
    "sg:city":"Padstow",
    "sg:classifiers":[
        {
            "category":"Retail",
            "subcategory":"Auto Repair",
            "type":"Services"
        }
    ],
    "sg:phone":"+61 2 9771 6605",
    "sg:postcode":"2211",
    "sg:province":"NSW",
    "sg:tags":[
        "repairer",
        "motor",
        "engineer"
    ],
    "wof:name":"Jones Ric Auto Mobile Tune",
    "wof:placetype":"venue"
},
  "geometry": {"coordinates":[151.030914,-33.965469],"type":"Point"}
}