{
  "type": "Feature",
  "properties": {
    "addr:full":"7 Highland Pl Dubbo NSW 2830",
    "addr:housenumber":"7",
    "addr:postcode":"2830",
    "addr:street":"Highland Pl",
    "iso:country":"AU",
    "sg:address":"7 Highland Pl",
    "sg:city":"Dubbo",
    "sg:classifiers":[
        {
            "category":"Building & Trades",
            "subcategory":"Construction",
            "type":"Services"
        }
    ],
    "sg:phone":"+61 2 6882 6434",
    "sg:postcode":"2830",
    "sg:province":"NSW",
    "sg:tags":[
        "fencing",
        "contractor"
    ],
    "wof:name":"Phil Wheeler Complete Fencing",
    "wof:placetype":"venue"
},
  "geometry": {"coordinates":[148.60794067399999,-32.2637329102],"type":"Point"}
}