{
  "type": "Feature",
  "properties": {
    "addr:full":"3185 Warburton Hwy Warburton VIC 3799",
    "addr:housenumber":"3185",
    "addr:postcode":"3799",
    "addr:street":"Warburton Hwy",
    "iso:country":"AU",
    "sg:address":"3185 Warburton Hwy",
    "sg:city":"Warburton",
    "sg:classifiers":[
        {
            "category":"Conference Center",
            "type":"Public Place"
        }
    ],
    "sg:phone":"+61 3 5966 9166",
    "sg:postcode":"3799",
    "sg:province":"VIC",
    "sg:tags":[
        "venue",
        "convention"
    ],
    "wof:name":"Warburton Grange Conference Centre",
    "wof:placetype":"venue"
},
  "geometry": {"coordinates":[145.60641479500001,-37.7799186707],"type":"Point"}
}