{
  "type": "Feature",
  "properties": {
    "iso:country":"AU",
    "sg:address":"551 Pittwater Rd",
    "sg:city":"Brookvale",
    "sg:classifiers":[
        {
            "category":"Wholesale",
            "subcategory":"Medical Equipment & Supplies",
            "type":"Manufacturing & Wholesale Goods"
        }
    ],
    "sg:phone":"+61 2 9938 5858",
    "sg:postcode":"2100",
    "sg:province":"NSW",
    "sg:tags":[
        "aid",
        "care",
        "health",
        "home"
    ],
    "wof:name":"Scooter Central",
    "wof:placetype":"venue"
},
  "geometry": {"coordinates":[151.27142334000001,-33.7630310059],"type":"Point"}
}