{
  "type": "Feature",
  "properties": {
    "addr:full":"St John of God Hospital 136 Botanic Rd Warrnambool VIC 3280",
    "addr:housenumber":"136",
    "addr:postcode":"3280",
    "addr:street":"Botanic Rd",
    "iso:country":"AU",
    "sg:address":"St John of God Hospital 136 Botanic Rd",
    "sg:city":"Warrnambool",
    "sg:classifiers":[
        {
            "category":"Personal",
            "subcategory":"Massage",
            "type":"Services"
        }
    ],
    "sg:phone":"+61 418 362 179",
    "sg:postcode":"3280",
    "sg:province":"VIC",
    "sg:tags":[
        "therapy"
    ],
    "wof:name":"Nerida Hamilton",
    "wof:placetype":"venue"
},
  "geometry": {"coordinates":[142.47955322300001,-38.3721618652],"type":"Point"}
}