{
  "type": "Feature",
  "properties": {
    "iso:country":"AU",
    "sg:address":"49 Bridge St",
    "sg:city":"Muswellbrook",
    "sg:classifiers":[
        {
            "category":"Insurance",
            "subcategory":"Health Insurance",
            "type":"Services"
        }
    ],
    "sg:phone":"+61 13 14 63",
    "sg:postcode":"2333",
    "sg:province":"NSW",
    "wof:name":"NIB Health Funds",
    "wof:placetype":"venue"
},
  "geometry": {"coordinates":[150.88833618199999,-32.2648849487],"type":"Point"}
}