{
  "type": "Feature",
  "properties": {
    "iso:country":"AU",
    "sg:address":"1 Wyllie St",
    "sg:city":"Bundaberg South",
    "sg:classifiers":[
        {
            "category":"Wholesale",
            "subcategory":"Farm Supplies",
            "type":"Manufacturing & Wholesale Goods"
        }
    ],
    "sg:phone":"+61 7 4154 4555",
    "sg:postcode":"4670",
    "sg:province":"QLD",
    "sg:tags":[
        "equipment"
    ],
    "wof:name":"BGA AgriServices Wide Bay Rural Supplies",
    "wof:placetype":"venue"
},
  "geometry": {"coordinates":[152.37197875999999,-24.8806381226],"type":"Point"}
}