{
  "type": "Feature",
  "properties": {
    "iso:country":"AU",
    "sg:address":"95 Carrington Rd",
    "sg:city":"Waverley",
    "sg:classifiers":[
        {
            "category":"Organizations",
            "subcategory":"Non-profit Organization",
            "type":"Services"
        }
    ],
    "sg:phone":"+61 2 9389 2689",
    "sg:postcode":"2024",
    "sg:province":"NSW",
    "sg:tags":[
        "support",
        "disability",
        "organisation"
    ],
    "wof:name":"Junction House",
    "wof:placetype":"venue"
},
  "geometry": {"coordinates":[151.25338745100001,-33.9007835388],"type":"Point"}
}