{
  "type": "Feature",
  "properties": {
    "addr:full":"61 Duffy St Woodvale WA 6026",
    "addr:housenumber":"61",
    "addr:postcode":"6026",
    "addr:street":"Duffy St",
    "iso:country":"AU",
    "sg:address":"61 Duffy St",
    "sg:city":"Woodvale",
    "sg:classifiers":[
        {
            "category":"Retail",
            "subcategory":"Driving School",
            "type":"Services"
        }
    ],
    "sg:phone":"+61 8 9409 2297",
    "sg:postcode":"6026",
    "sg:province":"WA",
    "wof:name":"Give Way Driving School",
    "wof:placetype":"venue"
},
  "geometry": {"coordinates":[115.804199219,-31.7976837158],"type":"Point"}
}