{
  "type": "Feature",
  "properties": {
    "iso:country":"AU",
    "sg:address":"2/ 255 Main Rd West St",
    "sg:city":"Albans",
    "sg:classifiers":[
        {
            "category":"Retail",
            "subcategory":"Auto Repair",
            "type":"Services"
        }
    ],
    "sg:phone":"+61 415 184 511",
    "sg:postcode":"3021",
    "sg:province":"VIC",
    "sg:tags":[
        "clutch",
        "brake"
    ],
    "wof:name":"Smooth Stop Brake Repairs",
    "wof:placetype":"venue"
},
  "geometry": {"coordinates":[144.812256,-37.745811],"type":"Point"}
}