{
  "type": "Feature",
  "properties": {
    "iso:country":"AU",
    "sg:address":"Shop 33 Rockdale Plaza 1",
    "sg:city":"Rockdale Plz Rockdale",
    "sg:classifiers":[
        {
            "category":"Shopping",
            "subcategory":"Music",
            "type":"Retail Goods"
        }
    ],
    "sg:phone":"+61 2 9553 4888",
    "sg:postcode":"2216",
    "sg:province":"NSW",
    "sg:tags":[
        "store"
    ],
    "wof:name":"Leading Edge Music",
    "wof:placetype":"venue"
},
  "geometry": {"coordinates":[151.138245,-33.947281],"type":"Point"}
}