{
  "type": "Feature",
  "properties": {
    "addr:full":"198 Melbourne Rd Williamstown VIC 3016",
    "addr:housenumber":"198",
    "addr:postcode":"3016",
    "addr:street":"Melbourne Rd",
    "iso:country":"AU",
    "sg:address":"198 Melbourne Rd",
    "sg:city":"Williamstown",
    "sg:classifiers":[
        {
            "category":"Fast Food",
            "type":"Food & Drink"
        }
    ],
    "sg:phone":"+61 3 9397 8202",
    "sg:postcode":"3016",
    "sg:province":"VIC",
    "sg:tags":[
        "away",
        "take"
    ],
    "wof:name":"Jackie's Food Pizza",
    "wof:placetype":"venue"
},
  "geometry": {"coordinates":[144.889862061,-37.8521118164],"type":"Point"}
}