{
  "type": "Feature",
  "properties": {
    "iso:country":"AU",
    "sg:address":"Cairns Central Shooping Centre McLeod St",
    "sg:city":"Cairns",
    "sg:classifiers":[
        {
            "category":"Ice Cream",
            "type":"Food & Drink"
        }
    ],
    "sg:phone":"+61 7 4041 2100",
    "sg:postcode":"4870",
    "sg:province":"QLD",
    "sg:tags":[
        "retail"
    ],
    "wof:name":"Wendy's Supa Sundaes",
    "wof:placetype":"venue"
},
  "geometry": {"coordinates":[145.774169922,-16.926197052],"type":"Point"}
}