{
  "type": "Feature",
  "properties": {
    "addr:full":"2 West Port Rd Devonport TAS 7310",
    "addr:housenumber":"2",
    "addr:postcode":"7310",
    "addr:street":"West Port Rd",
    "iso:country":"AU",
    "sg:address":"2 West Port Rd",
    "sg:city":"Devonport",
    "sg:classifiers":[
        {
            "category":"Home & Garden",
            "subcategory":"Hardware",
            "type":"Retail Goods"
        }
    ],
    "sg:phone":"+61 3 6420 4600",
    "sg:postcode":"7310",
    "sg:province":"TAS",
    "sg:tags":[
        "pumping",
        "contractor"
    ],
    "wof:name":"Collex Pty Limited",
    "wof:placetype":"venue"
},
  "geometry": {"coordinates":[146.348587036,-41.1798591614],"type":"Point"}
}