{
  "type": "Feature",
  "properties": {
    "addr:full":"6 Quamby Pl Noosa Heads QLD 4567",
    "addr:housenumber":"6",
    "addr:postcode":"4567",
    "addr:street":"Quamby Pl",
    "iso:country":"AU",
    "sg:address":"6 Quamby Pl",
    "sg:city":"Noosa Heads",
    "sg:classifiers":[
        {
            "category":"Personal",
            "subcategory":"Beauty Salon",
            "type":"Services"
        }
    ],
    "sg:phone":"+61 7 5455 3144",
    "sg:postcode":"4567",
    "sg:province":"QLD",
    "wof:name":"Studio For Beauty Skin & Massage Therapies The",
    "wof:placetype":"venue"
},
  "geometry": {"coordinates":[153.078887939,-26.3918266296],"type":"Point"}
}