{
  "type": "Feature",
  "properties": {
    "addr:full":"Shop 1090 Westfield Carindale 1151 Creek Rd Carindale QLD 4152",
    "addr:housenumber":"1090;1151",
    "addr:postcode":"4152",
    "addr:street":"Westfield;Creek Rd",
    "iso:country":"AU",
    "sg:address":"Shop 1090 Westfield Carindale 1151 Creek Rd",
    "sg:city":"Carindale",
    "sg:classifiers":[
        {
            "category":"Banks & Credit Unions",
            "subcategory":"Bureau De Change",
            "type":"Services"
        }
    ],
    "sg:phone":"+61 1800 637 642",
    "sg:postcode":"4152",
    "sg:province":"QLD",
    "sg:tags":[
        "currency",
        "exchange",
        "foreign"
    ],
    "wof:name":"Travelex",
    "wof:placetype":"venue"
},
  "geometry": {"coordinates":[153.099975586,-27.5036334991],"type":"Point"}
}