{
  "type": "Feature",
  "properties": {
    "iso:country":"AU",
    "sg:address":"Safety Bay Senior High School Malibu Rd",
    "sg:city":"Safety Bay",
    "sg:classifiers":[
        {
            "category":"Education",
            "subcategory":"School",
            "type":"Public Place"
        }
    ],
    "sg:phone":"+61 8 9527 0200",
    "sg:postcode":"6169",
    "sg:province":"WA",
    "sg:tags":[
        "state",
        "except",
        "nsw"
    ],
    "wof:name":"Schools Government (Public)",
    "wof:placetype":"venue"
},
  "geometry": {"coordinates":[115.732857,-32.308945],"type":"Point"}
}