{
  "type": "Feature",
  "properties": {
    "addr:full":"82 Morley Drv Tuart Hill WA 6060",
    "addr:housenumber":"82",
    "addr:postcode":"6060",
    "addr:street":"Morley Drv",
    "iso:country":"AU",
    "sg:address":"82 Morley Drv",
    "sg:city":"Tuart Hill",
    "sg:classifiers":[
        {
            "category":"Health Services",
            "subcategory":"Health Practitioner",
            "type":"Services"
        }
    ],
    "sg:phone":"+61 8 9349 9199",
    "sg:postcode":"6060",
    "sg:province":"WA",
    "sg:tags":[
        "naturopath"
    ],
    "wof:name":"Smith Lucy",
    "wof:placetype":"venue"
},
  "geometry": {"coordinates":[115.836608887,-31.8891563416],"type":"Point"}
}