{
  "type": "Feature",
  "properties": {
    "iso:country":"AU",
    "sg:address":"11 Rosella Rd",
    "sg:city":"Gulmarrad",
    "sg:classifiers":[
        {
            "category":"Professional",
            "subcategory":"Accounting & Tax Preparation",
            "type":"Services"
        }
    ],
    "sg:phone":"+61 2 6645 4304",
    "sg:postcode":"2463",
    "sg:province":"NSW",
    "sg:tags":[
        "accountant",
        "auditor"
    ],
    "wof:name":"A. Roberts.",
    "wof:placetype":"venue"
},
  "geometry": {"coordinates":[153.22883605999999,-29.4944820404],"type":"Point"}
}