{
  "type": "Feature",
  "properties": {
    "iso:country":"AU",
    "sg:address":"715 Blende St",
    "sg:city":"Broken Hill",
    "sg:classifiers":[
        {
            "category":"Travel",
            "subcategory":"Travel Agent",
            "type":"Entertainment"
        }
    ],
    "sg:phone":"+61 8 8087 5142",
    "sg:postcode":"2880",
    "sg:province":"NSW",
    "sg:tags":[
        "tour",
        "holiday",
        "adventure"
    ],
    "wof:name":"Corner Country Adventure Tours",
    "wof:placetype":"venue"
},
  "geometry": {"coordinates":[141.48330688499999,-31.9460887909],"type":"Point"}
}