{
  "type": "Feature",
  "properties": {
    "addr:full":"362-364 Blaxland Rd Ryde NSW 2112",
    "addr:postcode":"362-364;2112",
    "addr:street":"Blaxland Rd",
    "iso:country":"AU",
    "sg:address":"362-364 Blaxland Rd",
    "sg:city":"Ryde",
    "sg:classifiers":[
        {
            "category":"Professional",
            "type":"Services"
        }
    ],
    "sg:phone":"+61 418 242 140",
    "sg:postcode":"2112",
    "sg:province":"NSW",
    "sg:tags":[
        "overlocking",
        "rug",
        "carpet"
    ],
    "wof:name":"John F Lower & Sons",
    "wof:placetype":"venue"
},
  "geometry": {"coordinates":[151.10005188,-33.8008232117],"type":"Point"}
}