{
  "type": "Feature",
  "properties": {
    "addr:full":"Unit 2 / 20 Duerdin St Clayton VIC 3168",
    "addr:housenumber":"20",
    "addr:postcode":"3168",
    "addr:street":"Duerdin St",
    "iso:country":"AU",
    "sg:address":"Unit 2 / 20 Duerdin St",
    "sg:city":"Clayton",
    "sg:classifiers":[
        {
            "category":"Building & Trades",
            "subcategory":"Construction",
            "type":"Services"
        }
    ],
    "sg:phone":"+61 3 9543 2802",
    "sg:postcode":"3168",
    "sg:province":"VIC",
    "sg:tags":[
        "contractor"
    ],
    "wof:name":"Cope & Pyke Building Services Pty.Ltd.",
    "wof:placetype":"venue"
},
  "geometry": {"coordinates":[145.139160156,-37.9205932617],"type":"Point"}
}