{
  "type": "Feature",
  "properties": {
    "addr:full":"Lot 1 Nursery La Ballarat VIC 3350",
    "addr:housenumber":"1",
    "addr:postcode":"3350",
    "addr:street":"Nursery La",
    "iso:country":"AU",
    "sg:address":"Lot 1 Nursery La",
    "sg:city":"Ballarat",
    "sg:classifiers":[
        {
            "category":"Home & Garden",
            "subcategory":"Garden Supply",
            "type":"Retail Goods"
        }
    ],
    "sg:phone":"+61 3 5339 1825",
    "sg:postcode":"3350",
    "sg:province":"VIC",
    "sg:tags":[
        "nursery"
    ],
    "sg:website":"http://www.hortopine.com.au",
    "wof:name":"Hortopine",
    "wof:placetype":"venue"
},
  "geometry": {"coordinates":[143.82208299999999,-37.545589],"type":"Point"}
}