{
  "type": "Feature",
  "properties": {
    "addr:full":"U4/ 24 Humber Rd Croydon North VIC 3136",
    "addr:housenumber":"24",
    "addr:postcode":"3136",
    "addr:street":"U4 /;Humber Rd",
    "iso:country":"AU",
    "sg:address":"U4/ 24 Humber Rd",
    "sg:city":"Croydon North",
    "sg:classifiers":[
        {
            "category":"Professional",
            "subcategory":"Business Services",
            "type":"Services"
        }
    ],
    "sg:phone":"+61 3 9727 4659",
    "sg:postcode":"3136",
    "sg:province":"VIC",
    "sg:tags":[
        "processing",
        "word"
    ],
    "wof:name":"Michael Fitzgerald & Assoc",
    "wof:placetype":"venue"
},
  "geometry": {"coordinates":[145.287506103,-37.7672767639],"type":"Point"}
}