{
  "type": "Feature",
  "properties": {
    "iso:country":"AU",
    "sg:address":"Suite 1d 1 Eton St",
    "sg:city":"Sutherland",
    "sg:classifiers":[
        {
            "category":"Banks & Credit Unions",
            "subcategory":"Financial Services",
            "type":"Services"
        }
    ],
    "sg:phone":"+61 2 9542 1200",
    "sg:postcode":"2232",
    "sg:province":"NSW",
    "sg:tags":[
        "industrial",
        "finance"
    ],
    "wof:name":"Medilend Pty Ltd",
    "wof:placetype":"venue"
},
  "geometry": {"coordinates":[151.058883667,-34.0303649902],"type":"Point"}
}