{
  "type": "Feature",
  "properties": {
    "addr:full":"Norris Rd Bracken Ridge QLD 4017",
    "addr:postcode":"4017",
    "addr:street":"Norris Rd",
    "iso:country":"AU",
    "sg:address":"Norris Rd",
    "sg:city":"Bracken Ridge",
    "sg:classifiers":[
        {
            "category":"Fast Food",
            "type":"Food & Drink"
        }
    ],
    "sg:phone":"+61 7 3261 1753",
    "sg:postcode":"4017",
    "sg:province":"QLD",
    "sg:tags":[
        "away",
        "take"
    ],
    "wof:name":"Top Wok Asian Kitchen",
    "wof:placetype":"venue"
},
  "geometry": {"coordinates":[153.02528381400001,-27.3309993744],"type":"Point"}
}