{
  "type": "Feature",
  "properties": {
    "addr:full":"83 Argus St Cheltenham VIC 3192",
    "addr:housenumber":"83",
    "addr:postcode":"3192",
    "addr:street":"Argus St",
    "iso:country":"AU",
    "sg:address":"83 Argus St",
    "sg:city":"Cheltenham",
    "sg:classifiers":[
        {
            "category":"Retail",
            "subcategory":"Auto Repair",
            "type":"Services"
        }
    ],
    "sg:phone":"+61 3 9584 0000",
    "sg:postcode":"3192",
    "sg:province":"VIC",
    "sg:tags":[
        "repairer",
        "motor",
        "engineer"
    ],
    "wof:name":"Mainline Automotive",
    "wof:placetype":"venue"
},
  "geometry": {"coordinates":[145.07261657699999,-37.9598121643],"type":"Point"}
}