{
  "type": "Feature",
  "properties": {
    "addr:full":"34 Port Stephens Drv Anna Bay NSW 2316",
    "addr:housenumber":"34",
    "addr:postcode":"2316",
    "addr:street":"Port Stephens Drv Anna Bay",
    "iso:country":"AU",
    "sg:address":"34 Port Stephens Drv",
    "sg:city":"Anna Bay",
    "sg:classifiers":[
        {
            "category":"Building & Trades",
            "subcategory":"Construction",
            "type":"Services"
        }
    ],
    "sg:phone":"+61 2 4982 2625",
    "sg:postcode":"2316",
    "sg:province":"NSW",
    "sg:tags":[
        "contractor"
    ],
    "wof:name":"G.W.B. Design & Build",
    "wof:placetype":"venue"
},
  "geometry": {"coordinates":[152.067352,-32.760551],"type":"Point"}
}