{
  "type": "Feature",
  "properties": {
    "addr:full":"4 St James Pl Seven Hills NSW 2147",
    "addr:housenumber":"4",
    "addr:postcode":"2147",
    "addr:street":"St James Pl",
    "iso:country":"AU",
    "sg:address":"4 St James Pl",
    "sg:city":"Seven Hills",
    "sg:classifiers":[
        {
            "category":"Wholesale",
            "subcategory":"Machinery & Supplies",
            "type":"Manufacturing & Wholesale Goods"
        }
    ],
    "sg:phone":"+61 2 9620 7020",
    "sg:postcode":"2147",
    "sg:province":"NSW",
    "sg:tags":[
        "equipment",
        "welding"
    ],
    "wof:name":"Lansarc Pty Ltd",
    "wof:placetype":"venue"
},
  "geometry": {"coordinates":[150.95315551799999,-33.774017334],"type":"Point"}
}