{
  "type": "Feature",
  "properties": {
    "addr:full":"Unit 1/ 38 Tulloch Way Canning Vale WA 6155",
    "addr:housenumber":"38",
    "addr:postcode":"6155",
    "addr:street":"Tulloch Way",
    "iso:country":"AU",
    "sg:address":"Unit 1/ 38 Tulloch Way",
    "sg:city":"Canning Vale",
    "sg:classifiers":[
        {
            "category":"Retail",
            "subcategory":"Auto Repair",
            "type":"Services"
        }
    ],
    "sg:phone":"+61 8 9456 1111",
    "sg:postcode":"6155",
    "sg:province":"WA",
    "sg:tags":[
        "repairer",
        "motor",
        "engineer"
    ],
    "wof:name":"Active Automotive & Performance Centre",
    "wof:placetype":"venue"
},
  "geometry": {"coordinates":[115.93225099999999,-32.06414],"type":"Point"}
}