{
  "type": "Feature",
  "properties": {
    "iso:country":"AU",
    "sg:address":"Shop GA-01, Gallery Level, Garden Town Shopping Ce",
    "sg:city":"Toowoomba",
    "sg:classifiers":[
        {
            "category":"Manufacturing",
            "subcategory":"Textiles",
            "type":"Manufacturing & Wholesale Goods"
        }
    ],
    "sg:phone":"+61 7 4638 2188",
    "sg:postcode":"4350",
    "sg:province":"QLD",
    "sg:tags":[
        "knitted",
        "woven",
        "fabric"
    ],
    "wof:name":"Lincraft",
    "wof:placetype":"venue"
},
  "geometry": {"coordinates":[151.951004,-27.561867],"type":"Point"}
}