{
  "type": "Feature",
  "properties": {
    "iso:country":"AU",
    "sg:address":"6706 Great Alpine Rd",
    "sg:city":"Porepunkah",
    "sg:classifiers":[
        {
            "category":"Travel",
            "subcategory":"Hotels & Motels",
            "type":"Entertainment"
        }
    ],
    "sg:phone":"+61 3 5756 2334",
    "sg:postcode":"3740",
    "sg:province":"VIC",
    "wof:name":"Alpine Park",
    "wof:placetype":"venue"
},
  "geometry": {"coordinates":[146.893204,-36.682468],"type":"Point"}
}