{
  "type": "Feature",
  "properties": {
    "addr:full":"30 Court St Parkes NSW 2870",
    "addr:housenumber":"30",
    "addr:postcode":"2870",
    "addr:street":"Court St",
    "iso:country":"AU",
    "sg:address":"30 Court St",
    "sg:city":"Parkes",
    "sg:classifiers":[
        {
            "category":"Banks & Credit Unions",
            "subcategory":"Financial Services",
            "type":"Services"
        }
    ],
    "sg:phone":"+61 2 6863 5022",
    "sg:postcode":"2870",
    "sg:province":"NSW",
    "sg:tags":[
        "planning"
    ],
    "wof:name":"Blackridge Financial Services Pty Ltd",
    "wof:placetype":"venue"
},
  "geometry": {"coordinates":[148.17356899999999,-33.136395],"type":"Point"}
}