{
  "type": "Feature",
  "properties": {
    "addr:full":"Cascom Centre 2 Bradshaw Tce Casuarina NT 0810",
    "addr:housenumber":"2",
    "addr:postcode":"nt 0810",
    "addr:street":"Bradshaw Tce",
    "iso:country":"AU",
    "sg:address":"Cascom Centre 2",
    "sg:city":"Bradshaw Tce Casuarina",
    "sg:classifiers":[
        {
            "category":"Organizations",
            "subcategory":"Community Association",
            "type":"Services"
        }
    ],
    "sg:phone":"+61 8 8927 9411",
    "sg:postcode":"0810",
    "sg:province":"NT",
    "sg:tags":[
        "organisation",
        "family",
        "welfare"
    ],
    "wof:name":"Vietnam Veterans Counselling Service",
    "wof:placetype":"venue"
},
  "geometry": {"coordinates":[130.879760742,-12.3757944107],"type":"Point"}
}