{
  "type": "Feature",
  "properties": {
    "iso:country":"AU",
    "sg:address":"60 Old White Hill Rd",
    "sg:city":"Dromana",
    "sg:classifiers":[
        {
            "category":"Arts & Performance",
            "subcategory":"Art Gallery",
            "type":"Entertainment"
        }
    ],
    "sg:phone":"+61 3 5931 0146",
    "sg:postcode":"3936",
    "sg:province":"VIC",
    "wof:name":"White Hill Gallery",
    "wof:placetype":"venue"
},
  "geometry": {"coordinates":[145.007644653,-38.344291687],"type":"Point"}
}