{
  "type": "Feature",
  "properties": {
    "iso:country":"AU",
    "sg:address":"44 Stirling Ave",
    "sg:city":"North Rocks",
    "sg:classifiers":[
        {
            "category":"Building & Trades",
            "subcategory":"Pest Control",
            "type":"Services"
        }
    ],
    "sg:phone":"+61 2 9871 0511",
    "sg:postcode":"2151",
    "sg:province":"NSW",
    "wof:name":"Crown Pest Management",
    "wof:placetype":"venue"
},
  "geometry": {"coordinates":[151.02005004899999,-33.7740020752],"type":"Point"}
}