{
  "type": "Feature",
  "properties": {
    "addr:full":"Central Arcade, 59- 61 Queen St Busselton WA 6280",
    "addr:housenumber":"59 61",
    "addr:postcode":"6280",
    "addr:street":"Queen St",
    "iso:country":"AU",
    "sg:address":"Central Arcade, 59- 61 Queen St",
    "sg:city":"Busselton",
    "sg:classifiers":[
        {
            "category":"Professional",
            "subcategory":"Accounting & Tax Preparation",
            "type":"Services"
        }
    ],
    "sg:phone":"+61 8 9752 4214",
    "sg:postcode":"6280",
    "sg:province":"WA",
    "sg:tags":[
        "consultant",
        "taxation"
    ],
    "wof:name":"itp The Income Tax Professionals",
    "wof:placetype":"venue"
},
  "geometry": {"coordinates":[115.34465789799999,-33.6497459412],"type":"Point"}
}