{
  "type": "Feature",
  "properties": {
    "iso:country":"AU",
    "sg:address":"1/ 1848 Albany Hwy",
    "sg:city":"Maddington",
    "sg:classifiers":[
        {
            "category":"Autos & Motor Vehicles",
            "subcategory":"Automobile Sales",
            "type":"Retail Goods"
        }
    ],
    "sg:phone":"+61 8 9459 9088",
    "sg:postcode":"6109",
    "sg:province":"WA",
    "sg:tags":[
        "car",
        "used"
    ],
    "wof:name":"Autoscene Pty Ltd",
    "wof:placetype":"venue"
},
  "geometry": {"coordinates":[115.98033905,-32.0494384766],"type":"Point"}
}