{
  "type": "Feature",
  "properties": {
    "addr:full":"Shop 3 Forestway Shopng Cntr Frenchs Forest NSW 2086",
    "addr:housenumber":"shop 3",
    "addr:postcode":"2086",
    "addr:street":"Forestway Shopng Cntr",
    "iso:country":"AU",
    "sg:address":"Shop 3 Forestway Shopng Cntr",
    "sg:city":"Frenchs Forest",
    "sg:classifiers":[
        {
            "category":"Health Services",
            "subcategory":"Optometrist",
            "type":"Services"
        }
    ],
    "sg:phone":"+61 2 9452 6128",
    "sg:postcode":"2086",
    "sg:province":"NSW",
    "wof:name":"Peter Ramshaw Optometrists",
    "wof:placetype":"venue"
},
  "geometry": {"coordinates":[151.23475647000001,-33.7508201599],"type":"Point"}
}