{
  "type": "Feature",
  "properties": {
    "addr:full":"Wagonga St Narooma NSW 2546",
    "addr:postcode":"2546",
    "addr:street":"Wagonga St",
    "iso:country":"AU",
    "sg:address":"Wagonga St",
    "sg:city":"Narooma",
    "sg:classifiers":[
        {
            "category":"Travel",
            "subcategory":"Hotels & Motels",
            "type":"Entertainment"
        }
    ],
    "sg:phone":"+61 2 4476 2411",
    "sg:postcode":"2546",
    "sg:province":"NSW",
    "wof:name":"Whale Motor Inn",
    "wof:placetype":"venue"
},
  "geometry": {"coordinates":[150.132156372,-36.2178611755],"type":"Point"}
}