{
  "type": "Feature",
  "properties": {
    "iso:country":"AU",
    "sg:address":"53 Port Arthur St",
    "sg:city":"Lyons",
    "sg:classifiers":[
        {
            "category":"Building & Trades",
            "subcategory":"Landscaping Services",
            "type":"Services"
        }
    ],
    "sg:phone":"+61 2 6282 1016",
    "sg:postcode":"2606",
    "sg:province":"ACT",
    "sg:tags":[
        "stump",
        "tree",
        "felling",
        "removal"
    ],
    "wof:name":"Spitting Chips",
    "wof:placetype":"venue"
},
  "geometry": {"coordinates":[149.07389831500001,-35.3438949585],"type":"Point"}
}