{
  "type": "Feature",
  "properties": {
    "addr:full":"29 De Havilland Rd Mordialloc VIC 3195",
    "addr:postcode":"3195",
    "addr:street":"29 De Havilland Rd",
    "iso:country":"AU",
    "sg:address":"29 De Havilland Rd",
    "sg:city":"Mordialloc",
    "sg:classifiers":[
        {
            "category":"Shopping",
            "subcategory":"Mobile Phones",
            "type":"Retail Goods"
        }
    ],
    "sg:phone":"+61 3 9587 4499",
    "sg:postcode":"3195",
    "sg:province":"VIC",
    "sg:tags":[
        "wholesaler",
        "mfrs",
        "electrical",
        "switchboard"
    ],
    "wof:name":"DRC Switchboards",
    "wof:placetype":"venue"
},
  "geometry": {"coordinates":[145.100540161,-37.9884910583],"type":"Point"}
}