{
  "type": "Feature",
  "properties": {
    "addr:full":"113b North Beach Drv Osborne Park WA 6017",
    "addr:housenumber":"113b",
    "addr:postcode":"6017",
    "addr:street":"North Beach Drv",
    "iso:country":"AU",
    "sg:address":"113b North Beach Drv",
    "sg:city":"Osborne Park",
    "sg:classifiers":[
        {
            "category":"Building & Trades",
            "subcategory":"Landscaping Services",
            "type":"Services"
        }
    ],
    "sg:phone":"+61 400 206 491",
    "sg:postcode":"6017",
    "sg:province":"WA",
    "sg:tags":[
        "gardener"
    ],
    "wof:name":"Back Busters",
    "wof:placetype":"venue"
},
  "geometry": {"coordinates":[115.823913574,-31.8900470734],"type":"Point"}
}