{
  "type": "Feature",
  "properties": {
    "addr:full":"87 Bilton St Omeo VIC 3898",
    "addr:housenumber":"87",
    "addr:postcode":"3898",
    "addr:street":"Bilton St",
    "iso:country":"AU",
    "sg:address":"87 Bilton St",
    "sg:city":"Omeo",
    "sg:classifiers":[
        {
            "category":"Building & Trades",
            "subcategory":"Construction",
            "type":"Services"
        }
    ],
    "sg:phone":"+61 3 5159 1223",
    "sg:postcode":"3898",
    "sg:province":"VIC",
    "sg:tags":[
        "welding"
    ],
    "wof:name":"Omeo Welding & Engineering & Equipt Hire",
    "wof:placetype":"venue"
},
  "geometry": {"coordinates":[147.60038757300001,-37.1014060974],"type":"Point"}
}