{
  "type": "Feature",
  "properties": {
    "addr:full":"2576 Old Melbourne Rd Dunnstown VIC 3352",
    "addr:housenumber":"2576",
    "addr:postcode":"3352",
    "addr:street":"Old Melbourne Rd",
    "iso:country":"AU",
    "sg:address":"2576 Old Melbourne Rd",
    "sg:city":"Dunnstown",
    "sg:classifiers":[
        {
            "category":"Professional",
            "subcategory":"Art Services",
            "type":"Services"
        }
    ],
    "sg:phone":"+61 3 5334 7563",
    "sg:postcode":"3352",
    "sg:province":"VIC",
    "sg:tags":[
        "decorator",
        "painter"
    ],
    "wof:name":"Dan O&#039;Loughlin",
    "wof:placetype":"venue"
},
  "geometry": {"coordinates":[143.99217200000001,-37.588989],"type":"Point"}
}