{
  "type": "Feature",
  "properties": {
    "addr:full":"381 Dromana Pde Martha Cove Safety Beach VIC 3936",
    "addr:housenumber":"381",
    "addr:postcode":"3936",
    "addr:street":"Dromana Pde Martha Cove",
    "iso:country":"AU",
    "sg:address":"381 Dromana Pde",
    "sg:city":"Martha Cove Safety Beach",
    "sg:classifiers":[
        {
            "category":"Building & Trades",
            "subcategory":"Locksmith",
            "type":"Services"
        }
    ],
    "sg:phone":"+61 3 5988 4019",
    "sg:postcode":"3936",
    "sg:province":"VIC",
    "sg:tags":[
        "lock"
    ],
    "wof:name":"A.AAA Locksmiths",
    "wof:placetype":"venue"
},
  "geometry": {"coordinates":[144.996826172,-38.3048744202],"type":"Point"}
}