{
  "type": "Feature",
  "properties": {
    "iso:country":"AU",
    "sg:address":"10 Edward St",
    "sg:city":"Riverstone",
    "sg:classifiers":[
        {
            "category":"Wholesale",
            "subcategory":"Machinery & Supplies",
            "type":"Manufacturing & Wholesale Goods"
        }
    ],
    "sg:phone":"+61 2 9627 9099",
    "sg:postcode":"2765",
    "sg:province":"NSW",
    "wof:name":"Scantool Australia",
    "wof:placetype":"venue"
},
  "geometry": {"coordinates":[150.85580444300001,-33.6660079956],"type":"Point"}
}