{
  "type": "Feature",
  "properties": {
    "addr:full":"33- 35 Steele Rd Devonport TAS 7310",
    "addr:housenumber":"35",
    "addr:postcode":"7310",
    "addr:street":"Steele Rd",
    "iso:country":"AU",
    "sg:address":"33- 35 Steele Rd",
    "sg:city":"Devonport",
    "sg:classifiers":[
        {
            "category":"Banks & Credit Unions",
            "subcategory":"Financial Services",
            "type":"Services"
        }
    ],
    "sg:phone":"+61 1800 550 260",
    "sg:postcode":"7310",
    "sg:province":"TAS",
    "sg:tags":[
        "planning"
    ],
    "wof:name":"Hillross Financial Services Limited",
    "wof:placetype":"venue"
},
  "geometry": {"coordinates":[146.35963439899999,-41.1814079285],"type":"Point"}
}