{
  "type": "Feature",
  "properties": {
    "addr:full":"PO Box 1459 Kenmore QLD 4069",
    "addr:postcode":"4069",
    "iso:country":"AU",
    "sg:address":"PO Box 1459",
    "sg:city":"Kenmore",
    "sg:classifiers":[
        {
            "category":"Retail",
            "subcategory":"Repair Shop",
            "type":"Services"
        }
    ],
    "sg:phone":"+61 7 3374 3418",
    "sg:postcode":"4069",
    "sg:province":"QLD",
    "sg:tags":[
        "machine",
        "repairs",
        "part",
        "dryer",
        "washing"
    ],
    "wof:name":"Westside Appliance Service",
    "wof:placetype":"venue"
},
  "geometry": {"coordinates":[152.93849182100001,-27.508430481],"type":"Point"}
}