{
  "type": "Feature",
  "properties": {
    "iso:country":"AU",
    "sg:address":"444 Station St",
    "sg:city":"Box Hill",
    "sg:classifiers":[
        {
            "category":"Building & Trades",
            "subcategory":"Equipment Rental",
            "type":"Services"
        }
    ],
    "sg:phone":"+61 3 9899 5535",
    "sg:postcode":"3128",
    "sg:province":"VIC",
    "sg:tags":[
        "fitness"
    ],
    "wof:name":"Manic Fitness",
    "wof:placetype":"venue"
},
  "geometry": {"coordinates":[145.12246704099999,-37.8262481689],"type":"Point"}
}