{
  "type": "Feature",
  "properties": {
    "iso:country":"AU",
    "sg:address":"Lot 294 Boroon Pocket Rd",
    "sg:city":"Maleny",
    "sg:classifiers":[
        {
            "category":"Recreation",
            "subcategory":"Boat Charter",
            "type":"Entertainment"
        }
    ],
    "sg:phone":"+61 7 5499 9333",
    "sg:postcode":"4552",
    "sg:province":"QLD",
    "sg:tags":[
        "hire",
        "drive"
    ],
    "wof:name":"Malenys Reflections On Lake Baroon",
    "wof:placetype":"venue"
},
  "geometry": {"coordinates":[152.87263488799999,-26.7198753357],"type":"Point"}
}