{
  "type": "Feature",
  "properties": {
    "iso:country":"AU",
    "sg:address":"217 Copley Rd",
    "sg:city":"Upper Swan",
    "sg:classifiers":[
        {
            "category":"Farming",
            "subcategory":"Vineyard",
            "type":"Manufacturing & Wholesale Goods"
        }
    ],
    "sg:phone":"+61 8 9296 1436",
    "sg:postcode":"6069",
    "sg:province":"WA",
    "sg:tags":[
        "winery"
    ],
    "wof:name":"The Natural Wine Company",
    "wof:placetype":"venue"
},
  "geometry": {"coordinates":[116.049789429,-31.7729911804],"type":"Point"}
}