{
  "type": "Feature",
  "properties": {
    "iso:country":"AU",
    "sg:address":"738 Lower North East Rd",
    "sg:city":"Paradise",
    "sg:classifiers":[
        {
            "category":"Autos & Motor Vehicles",
            "subcategory":"Automobile Sales",
            "type":"Retail Goods"
        }
    ],
    "sg:phone":"+61 8 8337 3377",
    "sg:postcode":"5075",
    "sg:province":"SA",
    "sg:tags":[
        "car",
        "used"
    ],
    "wof:name":"Paradise Motors Mazda",
    "wof:placetype":"venue"
},
  "geometry": {"coordinates":[138.67526245100001,-34.8699455261],"type":"Point"}
}