{
  "type": "Feature",
  "properties": {
    "addr:full":"101 Bellevue Rd Figtree NSW 2525",
    "addr:housenumber":"101",
    "addr:postcode":"2525",
    "addr:street":"Bellevue Rd",
    "iso:country":"AU",
    "sg:address":"101 Bellevue Rd",
    "sg:city":"Figtree",
    "sg:classifiers":[
        {
            "category":"Retail",
            "subcategory":"Repair Shop",
            "type":"Services"
        }
    ],
    "sg:phone":"+61 2 4229 2379",
    "sg:postcode":"2525",
    "sg:province":"NSW",
    "sg:tags":[
        "repairing",
        "piano",
        "tuning"
    ],
    "wof:name":"Jurjens Pianos",
    "wof:placetype":"venue"
},
  "geometry": {"coordinates":[150.85354614299999,-34.4268875122],"type":"Point"}
}