{
  "type": "Feature",
  "properties": {
    "addr:full":"14 Fairymead St Underwood QLD 4119",
    "addr:housenumber":"14",
    "addr:postcode":"4119",
    "addr:street":"Fairymead St",
    "iso:country":"AU",
    "sg:address":"14 Fairymead St",
    "sg:city":"Underwood",
    "sg:classifiers":[
        {
            "category":"Professional",
            "type":"Services"
        }
    ],
    "sg:phone":"+61 417 789 374",
    "sg:postcode":"4119",
    "sg:province":"QLD",
    "sg:tags":[
        "transport"
    ],
    "wof:name":"Jonsha Transport",
    "wof:placetype":"venue"
},
  "geometry": {"coordinates":[153.11753845199999,-27.6071910858],"type":"Point"}
}