{
  "type": "Feature",
  "properties": {
    "addr:full":"21 Forest Pl Galston NSW 2159",
    "addr:housenumber":"21",
    "addr:postcode":"2159",
    "addr:street":"Forest Pl",
    "iso:country":"AU",
    "sg:address":"21 Forest Pl",
    "sg:city":"Galston",
    "sg:classifiers":[
        {
            "category":"Building & Trades",
            "subcategory":"Construction",
            "type":"Services"
        }
    ],
    "sg:phone":"+61 2 9653 1842",
    "sg:postcode":"2159",
    "sg:province":"NSW",
    "sg:tags":[
        "contractor"
    ],
    "wof:name":"Garry's Building Services",
    "wof:placetype":"venue"
},
  "geometry": {"coordinates":[151.04226684599999,-33.6513557434],"type":"Point"}
}