{
  "type": "Feature",
  "properties": {
    "iso:country":"AU",
    "sg:address":"Shp 39 Centro Shopng Cntr",
    "sg:city":"Warriewood",
    "sg:classifiers":[
        {
            "category":"Health Services",
            "subcategory":"Optometrist",
            "type":"Services"
        }
    ],
    "sg:phone":"+61 2 9913 8458",
    "sg:postcode":"2102",
    "sg:province":"NSW",
    "wof:name":"Moujan Adel",
    "wof:placetype":"venue"
},
  "geometry": {"coordinates":[151.29744,-33.688911],"type":"Point"}
}