{
  "type": "Feature",
  "properties": {
    "addr:full":"258a Dorset Rd Boronia VIC 3155",
    "addr:housenumber":"258a",
    "addr:postcode":"3155",
    "addr:street":"Dorset Rd",
    "iso:country":"AU",
    "sg:address":"258a Dorset Rd",
    "sg:city":"Boronia",
    "sg:classifiers":[
        {
            "category":"Health Services",
            "subcategory":"Health Practitioner",
            "type":"Services"
        }
    ],
    "sg:phone":"+61 1300 308 467",
    "sg:postcode":"3155",
    "sg:province":"VIC",
    "sg:tags":[
        "physiotherapist"
    ],
    "wof:name":"Back In Motion Physiotherapy",
    "wof:placetype":"venue"
},
  "geometry": {"coordinates":[145.28590393100001,-37.8602752686],"type":"Point"}
}