{
  "type": "Feature",
  "properties": {
    "addr:full":"22 Quondong Ave Athelstone SA 5076",
    "addr:housenumber":"22",
    "addr:postcode":"5076",
    "addr:street":"Quondong Ave",
    "iso:country":"AU",
    "sg:address":"22 Quondong Ave",
    "sg:city":"Athelstone",
    "sg:classifiers":[
        {
            "category":"Utilities",
            "subcategory":"Electric",
            "type":"Services"
        }
    ],
    "sg:phone":"+61 408 845 522",
    "sg:postcode":"5076",
    "sg:province":"SA",
    "sg:tags":[
        "electrical",
        "contractor"
    ],
    "wof:name":"Andreou Costas",
    "wof:placetype":"venue"
},
  "geometry": {"coordinates":[138.70765685999999,-34.8756866455],"type":"Point"}
}