{
  "type": "Feature",
  "properties": {
    "iso:country":"AU",
    "sg:address":"19 Friel St",
    "sg:city":"Buronga",
    "sg:classifiers":[
        {
            "category":"Farming",
            "subcategory":"Farm & Veterinary Services",
            "type":"Manufacturing & Wholesale Goods"
        }
    ],
    "sg:phone":"+61 3 5023 7101",
    "sg:postcode":"2739",
    "sg:province":"NSW",
    "sg:tags":[
        "producer",
        "hydroponic"
    ],
    "wof:name":"Nutrient Film Technique Enterprises ( Hydroponic Vegetables ) Pty Ltd",
    "wof:placetype":"venue"
},
  "geometry": {"coordinates":[142.18090799999999,-34.166992],"type":"Point"}
}