{
  "type": "Feature",
  "properties": {
    "addr:full":"7 Norseman Crs Worongary QLD 4213",
    "addr:housenumber":"7",
    "addr:postcode":"4213",
    "addr:street":"Norseman Crs",
    "iso:country":"AU",
    "sg:address":"7 Norseman Crs",
    "sg:city":"Worongary",
    "sg:classifiers":[
        {
            "category":"Building & Trades",
            "subcategory":"Cleaning & Sanitation",
            "type":"Services"
        }
    ],
    "sg:phone":"+61 412 032 377",
    "sg:postcode":"4213",
    "sg:province":"QLD",
    "sg:tags":[
        "industrial",
        "commercial",
        "contractor"
    ],
    "wof:name":"John Greany",
    "wof:placetype":"venue"
},
  "geometry": {"coordinates":[153.343185425,-28.0209503174],"type":"Point"}
}