{
  "type": "Feature",
  "properties": {
    "iso:country":"AU",
    "sg:address":"65- 67 Thomas Drv",
    "sg:city":"Chevron Island",
    "sg:classifiers":[
        {
            "category":"Banks & Credit Unions",
            "subcategory":"Financial Services",
            "type":"Services"
        }
    ],
    "sg:phone":"+61 7 5582 2446",
    "sg:postcode":"4217",
    "sg:province":"QLD",
    "sg:tags":[
        "annuity",
        "rollover",
        "superannuation",
        "consultant"
    ],
    "wof:name":"Goldman Sachs JBWere Pty Ltd",
    "wof:placetype":"venue"
},
  "geometry": {"coordinates":[153.41798400900001,-27.9976043701],"type":"Point"}
}