{
  "type": "Feature",
  "properties": {
    "addr:full":"PO Box 5028 Wodonga VIC 3690",
    "addr:postcode":"3690",
    "iso:country":"AU",
    "sg:address":"PO Box 5028",
    "sg:city":"Wodonga",
    "sg:classifiers":[
        {
            "category":"Professional",
            "subcategory":"Computer Services",
            "type":"Services"
        }
    ],
    "sg:phone":"+61 417 379 613",
    "sg:postcode":"3690",
    "sg:province":"VIC",
    "sg:tags":[
        "consultant",
        "system"
    ],
    "wof:name":"Lyons Business Software",
    "wof:placetype":"venue"
},
  "geometry": {"coordinates":[146.84840393100001,-36.1168785095],"type":"Point"}
}