{
  "type": "Feature",
  "properties": {
    "addr:full":"PO Box 407 Maryborough QLD 4650",
    "addr:postcode":"4650",
    "iso:country":"AU",
    "sg:address":"PO Box 407",
    "sg:city":"Maryborough",
    "sg:classifiers":[
        {
            "category":"Sports & Exercise",
            "subcategory":"Gym",
            "type":"Entertainment"
        }
    ],
    "sg:phone":"+61 7 4122 2761",
    "sg:postcode":"4650",
    "sg:province":"QLD",
    "sg:tags":[
        "personal",
        "trainer",
        "fitness"
    ],
    "wof:name":"FLAB 2 FAB Personal Training",
    "wof:placetype":"venue"
},
  "geometry": {"coordinates":[152.69215399999999,-25.535271],"type":"Point"}
}