{
  "type": "Feature",
  "properties": {
    "addr:full":"20 Redpath St Wishart QLD 4122",
    "addr:housenumber":"20",
    "addr:postcode":"4122",
    "addr:street":"Redpath St",
    "iso:country":"AU",
    "sg:address":"20 Redpath St",
    "sg:city":"Wishart",
    "sg:classifiers":[
        {
            "category":"Professional",
            "subcategory":"Computer Services",
            "type":"Services"
        }
    ],
    "sg:phone":"+61 7 3849 7659",
    "sg:postcode":"4122",
    "sg:province":"QLD",
    "sg:tags":[
        "package",
        "software"
    ],
    "wof:name":"Ample Tek",
    "wof:placetype":"venue"
},
  "geometry": {"coordinates":[153.10960388199999,-27.5500049591],"type":"Point"}
}