{
  "type": "Feature",
  "properties": {
    "iso:country":"AU",
    "sg:address":"300 Drake St",
    "sg:city":"Morley",
    "sg:classifiers":[
        {
            "category":"Autos & Motor Vehicles",
            "subcategory":"Auto Supplies",
            "type":"Retail Goods"
        }
    ],
    "sg:phone":"+61 8 9275 9276",
    "sg:postcode":"6062",
    "sg:province":"WA",
    "sg:tags":[
        "wheel",
        "automotive",
        "rim"
    ],
    "wof:name":"Mr Mag",
    "wof:placetype":"venue"
},
  "geometry": {"coordinates":[115.89141082800001,-31.8982143402],"type":"Point"}
}