{
  "type": "Feature",
  "properties": {
    "iso:country":"AU",
    "sg:address":"141 Whites Rd",
    "sg:city":"Warrnambool",
    "sg:classifiers":[
        {
            "category":"Building & Trades",
            "subcategory":"Construction",
            "type":"Services"
        }
    ],
    "sg:phone":"+61 3 5561 2927",
    "sg:postcode":"3280",
    "sg:province":"VIC",
    "sg:tags":[
        "contractor"
    ],
    "wof:name":"Bushell V J & D L",
    "wof:placetype":"venue"
},
  "geometry": {"coordinates":[142.514801025,-38.3684082031],"type":"Point"}
}