{
  "type": "Feature",
  "properties": {
    "addr:full":"47 Adelaide Rd Gawler SA 5118",
    "addr:housenumber":"47",
    "addr:postcode":"5118",
    "addr:street":"Adelaide Rd",
    "iso:country":"AU",
    "sg:address":"47 Adelaide Rd",
    "sg:city":"Gawler",
    "sg:classifiers":[
        {
            "category":"Banks & Credit Unions",
            "subcategory":"Investment Brokerage",
            "type":"Services"
        }
    ],
    "sg:phone":"+61 8 8523 0133",
    "sg:postcode":"5118",
    "sg:province":"SA",
    "wof:name":"David Pointon Chartered Accountant",
    "wof:placetype":"venue"
},
  "geometry": {"coordinates":[138.74490399999999,-34.606461],"type":"Point"}
}