{
  "type": "Feature",
  "properties": {
    "addr:full":"3439 Murray Valley Hwy Bonegilla VIC 3691",
    "addr:housenumber":"3439",
    "addr:postcode":"3691",
    "addr:street":"Murray Valley Hwy",
    "iso:country":"AU",
    "sg:address":"3439 Murray Valley Hwy",
    "sg:city":"Bonegilla",
    "sg:classifiers":[
        {
            "category":"Farming",
            "subcategory":"Farm & Veterinary Services",
            "type":"Manufacturing & Wholesale Goods"
        }
    ],
    "sg:phone":"+61 2 6020 6655",
    "sg:postcode":"3691",
    "sg:province":"VIC",
    "sg:tags":[
        "contracting"
    ],
    "wof:name":"Lehmann Contracting Pty Ltd",
    "wof:placetype":"venue"
},
  "geometry": {"coordinates":[147.00787399999999,-36.141495],"type":"Point"}
}