{
  "type": "Feature",
  "properties": {
    "iso:country":"AU",
    "sg:address":"Shop 24, Clair Shopping Village, Cnr Endeavour & Bennett Rds",
    "sg:city":"St Clair",
    "sg:classifiers":[
        {
            "category":"Autos & Motor Vehicles",
            "subcategory":"Auto Supplies",
            "type":"Retail Goods"
        }
    ],
    "sg:phone":"+61 2 9834 1411",
    "sg:postcode":"2759",
    "sg:province":"NSW",
    "sg:tags":[
        "accessory"
    ],
    "wof:name":"Autopro",
    "wof:placetype":"venue"
},
  "geometry": {"coordinates":[150.78138732900001,-33.7974128723],"type":"Point"}
}