{
  "type": "Feature",
  "properties": {
    "addr:full":"Dr Buchanan Drv Coolamon NSW 2701",
    "addr:postcode":"2701",
    "addr:street":"Dr Buchanan Drv",
    "iso:country":"AU",
    "sg:address":"Dr Buchanan Drv",
    "sg:city":"Coolamon",
    "sg:classifiers":[
        {
            "category":"Health Services",
            "subcategory":"Doctor",
            "type":"Services"
        }
    ],
    "sg:phone":"+61 2 6927 3233",
    "sg:postcode":"2701",
    "sg:province":"NSW",
    "sg:tags":[
        "medical",
        "practitioner"
    ],
    "wof:name":"Coolamon Shire Medical & Dental Clinic",
    "wof:placetype":"venue"
},
  "geometry": {"coordinates":[147.199676514,-34.8201980591],"type":"Point"}
}