{
  "type": "Feature",
  "properties": {
    "iso:country":"AU",
    "sg:address":"14 Park Ave",
    "sg:city":"Nuriootpa",
    "sg:classifiers":[
        {
            "category":"Social Services",
            "subcategory":"Child Care",
            "type":"Services"
        }
    ],
    "sg:phone":"+61 8 8562 1006",
    "sg:postcode":"5355",
    "sg:province":"SA",
    "wof:name":"Nuriootpa Community Childrens Centre",
    "wof:placetype":"venue"
},
  "geometry": {"coordinates":[138.998168945,-34.4712371826],"type":"Point"}
}