{
  "type": "Feature",
  "properties": {
    "iso:country":"AU",
    "sg:address":"PO Box 8189",
    "sg:city":"Subiaco East",
    "sg:classifiers":[
        {
            "category":"Personal",
            "type":"Services"
        }
    ],
    "sg:phone":"+61 1300 737 985",
    "sg:postcode":"6008",
    "sg:province":"WA",
    "sg:tags":[
        "gift"
    ],
    "wof:name":"The Natural Circle",
    "wof:placetype":"venue"
},
  "geometry": {"coordinates":[115.812683105,-31.9533405304],"type":"Point"}
}