{
  "type": "Feature",
  "properties": {
    "addr:full":"154 Maine Rd Clontarf QLD 4019",
    "addr:housenumber":"154",
    "addr:postcode":"4019",
    "addr:street":"Maine Rd",
    "iso:country":"AU",
    "sg:address":"154 Maine Rd",
    "sg:city":"Clontarf",
    "sg:classifiers":[
        {
            "category":"Food & Beverages",
            "subcategory":"Bakery",
            "type":"Retail Goods"
        }
    ],
    "sg:phone":"+61 7 3284 0997",
    "sg:postcode":"4019",
    "sg:province":"QLD",
    "sg:tags":[
        "baker"
    ],
    "wof:name":"Clontarf Hot Bread",
    "wof:placetype":"venue"
},
  "geometry": {"coordinates":[153.08973693900001,-27.253578186],"type":"Point"}
}