{
  "type": "Feature",
  "properties": {
    "addr:full":"47 portrush Rd Payneham SA 5070",
    "addr:housenumber":"47",
    "addr:postcode":"5070",
    "addr:street":"Portrush Rd",
    "iso:country":"AU",
    "sg:address":"47 portrush Rd",
    "sg:city":"Payneham",
    "sg:classifiers":[
        {
            "category":"Professional",
            "subcategory":"Management & Consulting",
            "type":"Services"
        }
    ],
    "sg:phone":"+61 8 8363 9985",
    "sg:postcode":"5070",
    "sg:province":"SA",
    "sg:tags":[
        "consultant",
        "industrial",
        "relation"
    ],
    "wof:name":"Cannon Corporate Solutions",
    "wof:placetype":"venue"
},
  "geometry": {"coordinates":[138.63923645,-34.9004478455],"type":"Point"}
}