{
  "type": "Feature",
  "properties": {
    "addr:full":"810 Ipswich Rd Moorooka QLD 4105",
    "addr:housenumber":"810",
    "addr:postcode":"4105",
    "addr:street":"Ipswich Rd",
    "iso:country":"AU",
    "sg:address":"810 Ipswich Rd",
    "sg:city":"Moorooka",
    "sg:classifiers":[
        {
            "category":"Building & Trades",
            "subcategory":"Construction",
            "type":"Services"
        }
    ],
    "sg:phone":"+61 7 3255 8499",
    "sg:postcode":"4105",
    "sg:province":"QLD",
    "sg:tags":[
        "window",
        "tinting"
    ],
    "wof:name":"Express Tinting",
    "wof:placetype":"venue"
},
  "geometry": {"coordinates":[153.02560424800001,-27.522354126],"type":"Point"}
}