{
  "type": "Feature",
  "properties": {
    "iso:country":"AU",
    "sg:address":"Beenleigh Exch",
    "sg:city":"Stapylton",
    "sg:classifiers":[
        {
            "category":"Building & Trades",
            "subcategory":"Construction",
            "type":"Services"
        }
    ],
    "sg:phone":"+61 7 3382 7068",
    "sg:postcode":"4207",
    "sg:province":"QLD",
    "sg:tags":[
        "earth",
        "excavating",
        "moving",
        "contractor"
    ],
    "wof:name":"Setlow Constructions",
    "wof:placetype":"venue"
},
  "geometry": {"coordinates":[153.22262573200001,-27.7306957245],"type":"Point"}
}