{
  "type": "Feature",
  "properties": {
    "iso:country":"AU",
    "sg:address":"1/16 Reid St",
    "sg:city":"Wodonga",
    "sg:classifiers":[
        {
            "category":"Professional",
            "subcategory":"Engineering",
            "type":"Services"
        }
    ],
    "sg:phone":"+61 2 6024 1200",
    "sg:postcode":"3690",
    "sg:province":"VIC",
    "sg:tags":[
        "engineer"
    ],
    "wof:name":"TPT Precision Engineering Pty Ltd",
    "wof:placetype":"venue"
},
  "geometry": {"coordinates":[146.895721436,-36.1238479614],"type":"Point"}
}