{
  "type": "Feature",
  "properties": {
    "addr:full":"1 Huhges Pl Murrumbateman NSW 2582",
    "addr:housenumber":"1",
    "addr:postcode":"2582",
    "addr:street":"Huhges Pl",
    "iso:country":"AU",
    "sg:address":"1 Huhges Pl",
    "sg:city":"Murrumbateman",
    "sg:classifiers":[
        {
            "category":"Professional",
            "subcategory":"Computer Services",
            "type":"Services"
        }
    ],
    "sg:phone":"+61 2 6112 8371",
    "sg:postcode":"2582",
    "sg:province":"NSW",
    "sg:tags":[
        "information"
    ],
    "wof:name":"Infostuff Management Pty ltd",
    "wof:placetype":"venue"
},
  "geometry": {"coordinates":[149.02662658700001,-34.9734344482],"type":"Point"}
}