{
  "type": "Feature",
  "properties": {
    "iso:country":"AU",
    "sg:address":"13 Pine Rd",
    "sg:city":"Hawthorndene",
    "sg:classifiers":[
        {
            "category":"Wholesale",
            "subcategory":"Machinery & Supplies",
            "type":"Manufacturing & Wholesale Goods"
        }
    ],
    "sg:phone":"+61 8 8370 0572",
    "sg:postcode":"5051",
    "sg:province":"SA",
    "sg:tags":[
        "bearing",
        "bushing"
    ],
    "wof:name":"General Bearing Co Pty Ltd",
    "wof:placetype":"venue"
},
  "geometry": {"coordinates":[138.62529000000001,-35.018353],"type":"Point"}
}