{
  "type": "Feature",
  "properties": {
    "addr:full":"111 Main St Rutherglen VIC 3685",
    "addr:housenumber":"111",
    "addr:postcode":"3685",
    "addr:street":"Main St",
    "iso:country":"AU",
    "sg:address":"111 Main St",
    "sg:city":"Rutherglen",
    "sg:classifiers":[
        {
            "category":"Personal",
            "subcategory":"Hair Removal",
            "type":"Services"
        }
    ],
    "sg:phone":"+61 2 6032 8818",
    "sg:postcode":"3685",
    "sg:province":"VIC",
    "wof:name":"The Silken Dragonfly",
    "wof:placetype":"venue"
},
  "geometry": {"coordinates":[146.460006714,-36.0539779663],"type":"Point"}
}