{
  "type": "Feature",
  "properties": {
    "iso:country":"AU",
    "sg:address":"Antares St",
    "sg:city":"Southern Cross",
    "sg:classifiers":[
        {
            "category":"Government",
            "subcategory":"Department Of Motor Vehicles",
            "type":"Public Place"
        }
    ],
    "sg:phone":"+61 8 9049 1001",
    "sg:postcode":"6426",
    "sg:province":"WA",
    "sg:tags":[
        "organisation",
        "local"
    ],
    "wof:name":"Yilgarn Shire Of",
    "wof:placetype":"venue"
},
  "geometry": {"coordinates":[119.32914700000001,-31.232479],"type":"Point"}
}