{
  "type": "Feature",
  "properties": {
    "addr:full":"106 Dowling St Wendouree VIC 3355",
    "addr:housenumber":"106",
    "addr:postcode":"3355",
    "addr:street":"Dowling St",
    "iso:country":"AU",
    "sg:address":"106 Dowling St",
    "sg:city":"Wendouree",
    "sg:classifiers":[
        {
            "category":"Sports & Exercise",
            "subcategory":"Gym",
            "type":"Entertainment"
        }
    ],
    "sg:phone":"+61 3 5339 1281",
    "sg:postcode":"3355",
    "sg:province":"VIC",
    "sg:tags":[
        "health",
        "fitness"
    ],
    "wof:name":"Ballarat Fitness Centre",
    "wof:placetype":"venue"
},
  "geometry": {"coordinates":[143.83973700000001,-37.541634],"type":"Point"}
}