{
  "type": "Feature",
  "properties": {
    "iso:country":"AU",
    "sg:address":"46 Hamilton St",
    "sg:city":"West Hobart",
    "sg:classifiers":[
        {
            "category":"Real Estate",
            "subcategory":"Real Estate Services",
            "type":"Services"
        }
    ],
    "sg:phone":"+61 1800 648 888",
    "sg:postcode":"7000",
    "sg:province":"TAS",
    "sg:tags":[
        "listing"
    ],
    "wof:name":"Australian Private Realty Pty Ltd",
    "wof:placetype":"venue"
},
  "geometry": {"coordinates":[147.30943298299999,-42.8793029785],"type":"Point"}
}