{
  "type": "Feature",
  "properties": {
    "addr:full":"Suite 2/ 48-52 Sydney Rd Manly NSW 2095",
    "addr:housenumber":"/ 48-52",
    "addr:postcode":"2095",
    "addr:street":"Sydney Rd",
    "iso:country":"AU",
    "sg:address":"Suite 2/ 48-52 Sydney Rd",
    "sg:city":"Manly",
    "sg:classifiers":[
        {
            "category":"Health Services",
            "subcategory":"Doctor",
            "type":"Services"
        }
    ],
    "sg:phone":"+61 2 9977 2899",
    "sg:postcode":"2095",
    "sg:province":"NSW",
    "sg:tags":[
        "medical",
        "practitioner"
    ],
    "wof:name":"Chan Wing C. Dr.",
    "wof:placetype":"venue"
},
  "geometry": {"coordinates":[151.28550720199999,-33.7968177795],"type":"Point"}
}