{
  "type": "Feature",
  "properties": {
    "addr:full":"Unit 1, 693 The Horsley Drv Smithfield NSW 2164",
    "addr:housenumber":"693",
    "addr:postcode":"2164",
    "addr:street":"The Horsley Drv",
    "iso:country":"AU",
    "sg:address":"Unit 1, 693 The Horsley Drv",
    "sg:city":"Smithfield",
    "sg:classifiers":[
        {
            "category":"Building & Trades",
            "subcategory":"Construction",
            "type":"Services"
        }
    ],
    "sg:phone":"+61 2 9729 0044",
    "sg:postcode":"2164",
    "sg:province":"NSW",
    "sg:tags":[
        "contractor"
    ],
    "wof:name":"Topline Services P/L",
    "wof:placetype":"venue"
},
  "geometry": {"coordinates":[150.93914794899999,-33.8531532288],"type":"Point"}
}