{
  "type": "Feature",
  "properties": {
    "iso:country":"AU",
    "sg:address":"3 Mitchell St",
    "sg:city":"North Bondi",
    "sg:classifiers":[
        {
            "category":"Health Services",
            "subcategory":"Chiropractor",
            "type":"Services"
        }
    ],
    "sg:phone":"+61 2 9130 5570",
    "sg:postcode":"2026",
    "sg:province":"NSW",
    "wof:name":"Pearcey Fiona",
    "wof:placetype":"venue"
},
  "geometry": {"coordinates":[151.27645874000001,-33.8822860718],"type":"Point"}
}