{
  "type": "Feature",
  "properties": {
    "iso:country":"AU",
    "sg:address":"149 Malinya Rd",
    "sg:city":"Davistown",
    "sg:classifiers":[
        {
            "category":"Building & Trades",
            "subcategory":"Cleaning & Sanitation",
            "type":"Services"
        }
    ],
    "sg:phone":"+61 2 4369 0207",
    "sg:postcode":"2251",
    "sg:province":"NSW",
    "sg:tags":[
        "window"
    ],
    "wof:name":"Painless Window Cleaning",
    "wof:placetype":"venue"
},
  "geometry": {"coordinates":[151.35113525400001,-33.4792289734],"type":"Point"}
}