{
  "type": "Feature",
  "properties": {
    "addr:full":"1/ 2A Stratheden Crt Sydenham VIC 3037",
    "addr:housenumber":"/ 2a",
    "addr:postcode":"3037",
    "addr:street":"Stratheden Crt",
    "iso:country":"AU",
    "sg:address":"1/ 2A Stratheden Crt",
    "sg:city":"Sydenham",
    "sg:classifiers":[
        {
            "category":"Building & Trades",
            "subcategory":"Construction",
            "type":"Services"
        }
    ],
    "sg:phone":"+61 412 328 505",
    "sg:postcode":"3037",
    "sg:province":"VIC",
    "sg:tags":[
        "joiner",
        "carpenter"
    ],
    "wof:name":"Trevor Honan",
    "wof:placetype":"venue"
},
  "geometry": {"coordinates":[144.763733,-37.693825],"type":"Point"}
}