{
  "type": "Feature",
  "properties": {
    "addr:full":"16 Braeside Drv Braeside VIC 3195",
    "addr:housenumber":"16",
    "addr:postcode":"3195",
    "addr:street":"Braeside Drv",
    "iso:country":"AU",
    "sg:address":"16 Braeside Drv",
    "sg:city":"Braeside",
    "sg:classifiers":[
        {
            "category":"Shopping",
            "subcategory":"Stationery & Office Supplies",
            "type":"Retail Goods"
        }
    ],
    "sg:phone":"+61 3 9588 0926",
    "sg:postcode":"3195",
    "sg:province":"VIC",
    "sg:tags":[
        "equipment",
        "display",
        "exhibition"
    ],
    "wof:name":"Can Do (Aust) Pty Ltd",
    "wof:placetype":"venue"
},
  "geometry": {"coordinates":[145.11224365199999,-37.999622345],"type":"Point"}
}