{
  "type": "Feature",
  "properties": {
    "addr:full":"Unit 6/ 1 Fort La Milton QLD 4064",
    "addr:postcode":"4064",
    "iso:country":"AU",
    "sg:address":"Unit 6/ 1 Fort La",
    "sg:city":"Milton",
    "sg:classifiers":[
        {
            "category":"Professional",
            "subcategory":"Art Services",
            "type":"Services"
        }
    ],
    "sg:phone":"+61 7 3876 5500",
    "sg:postcode":"4064",
    "sg:province":"QLD",
    "sg:tags":[
        "graphic",
        "designer"
    ],
    "wof:name":"Studio Solutions",
    "wof:placetype":"venue"
},
  "geometry": {"coordinates":[153.00497436500001,-27.4719657898],"type":"Point"}
}