{
  "type": "Feature",
  "properties": {
    "addr:full":"13 Hazelwood St Highgate Hill QLD 4101",
    "addr:housenumber":"13",
    "addr:postcode":"4101",
    "addr:street":"Hazelwood St",
    "iso:country":"AU",
    "sg:address":"13 Hazelwood St",
    "sg:city":"Highgate Hill",
    "sg:classifiers":[
        {
            "category":"Professional",
            "subcategory":"Management & Consulting",
            "type":"Services"
        }
    ],
    "sg:phone":"+61 7 3844 4375",
    "sg:postcode":"4101",
    "sg:province":"QLD",
    "sg:tags":[
        "consultant",
        "educational"
    ],
    "wof:name":"Institute Of Financial Services",
    "wof:placetype":"venue"
},
  "geometry": {"coordinates":[153.017974853,-27.4879016876],"type":"Point"}
}