{
  "type": "Feature",
  "properties": {
    "addr:full":"114 Canonbury Rd Bexley North NSW 2207",
    "addr:housenumber":"114",
    "addr:postcode":"2207",
    "addr:street":"Canonbury Rd",
    "iso:country":"AU",
    "sg:address":"114 Canonbury Rd",
    "sg:city":"Bexley North",
    "sg:classifiers":[
        {
            "category":"Professional",
            "subcategory":"Computer Services",
            "type":"Services"
        }
    ],
    "sg:phone":"+61 2 9554 9274",
    "sg:postcode":"2207",
    "sg:province":"NSW",
    "sg:tags":[
        "information"
    ],
    "wof:name":"Trade Info",
    "wof:placetype":"venue"
},
  "geometry": {"coordinates":[151.12106299999999,-33.941692],"type":"Point"}
}