{
  "type": "Feature",
  "properties": {
    "addr:full":"11 Barakee Drv Somerville VIC 3912",
    "addr:housenumber":"11",
    "addr:postcode":"3912",
    "addr:street":"Barakee Drv",
    "iso:country":"AU",
    "sg:address":"11 Barakee Drv",
    "sg:city":"Somerville",
    "sg:classifiers":[
        {
            "category":"Banks & Credit Unions",
            "subcategory":"Investment Brokerage",
            "type":"Services"
        }
    ],
    "sg:phone":"+61 3 5977 6386",
    "sg:postcode":"3912",
    "sg:province":"VIC",
    "sg:tags":[
        "paint",
        "supply",
        "removal"
    ],
    "sg:website":"http://www.davarga.com",
    "wof:name":"Davarga Pressure Cleaning",
    "wof:placetype":"venue"
},
  "geometry": {"coordinates":[145.15719604500001,-38.2333717346],"type":"Point"}
}