{
  "type": "Feature",
  "properties": {
    "iso:country":"AU",
    "sg:address":"76 Queen St",
    "sg:city":"Concord West",
    "sg:classifiers":[
        {
            "category":"Education",
            "subcategory":"University",
            "type":"Public Place"
        }
    ],
    "sg:phone":"+61 2 9743 2501",
    "sg:postcode":"2138",
    "sg:province":"NSW",
    "sg:tags":[
        "educational",
        "organisation",
        "cultural"
    ],
    "wof:name":"Embroiderer's Guild NSW Inc",
    "wof:placetype":"venue"
},
  "geometry": {"coordinates":[151.08598327600001,-33.8500442505],"type":"Point"}
}