{
  "type": "Feature",
  "properties": {
    "iso:country":"AU",
    "sg:address":"1370 Great Northern Hwy",
    "sg:city":"Wyndham",
    "sg:classifiers":[
        {
            "category":"Personal",
            "type":"Services"
        }
    ],
    "sg:phone":"+61 8 9161 1531",
    "sg:postcode":"6740",
    "sg:province":"WA",
    "sg:tags":[
        "counselling",
        "alcohol",
        "drug"
    ],
    "wof:name":"7 Mile Rehab. Centre",
    "wof:placetype":"venue"
},
  "geometry": {"coordinates":[128.163619995,-15.5059690475],"type":"Point"}
}