{
  "type": "Feature",
  "properties": {
    "addr:full":"Factory 10, 71a Milperra Rd Revesby NSW 2212",
    "addr:housenumber":"71a",
    "addr:postcode":"2212",
    "addr:street":"Milperra Rd",
    "iso:country":"AU",
    "sg:address":"Factory 10, 71a Milperra Rd",
    "sg:city":"Revesby",
    "sg:classifiers":[
        {
            "category":"Manufacturing",
            "subcategory":"Metals",
            "type":"Manufacturing & Wholesale Goods"
        }
    ],
    "sg:phone":"+61 2 9771 2222",
    "sg:postcode":"2212",
    "sg:province":"NSW",
    "sg:tags":[
        "steel",
        "fabricator",
        "mfrs"
    ],
    "wof:name":"K Kanaan Engineering",
    "wof:placetype":"venue"
},
  "geometry": {"coordinates":[151.01306199999999,-33.936646],"type":"Point"}
}