{
  "type": "Feature",
  "properties": {
    "addr:full":"6 Neill St Maryborough VIC 3465",
    "addr:housenumber":"6",
    "addr:postcode":"3465",
    "addr:street":"Neill St",
    "iso:country":"AU",
    "sg:address":"6 Neill St",
    "sg:city":"Maryborough",
    "sg:classifiers":[
        {
            "category":"Health Services",
            "subcategory":"Doctor",
            "type":"Services"
        }
    ],
    "sg:phone":"+61 3 5460 4466",
    "sg:postcode":"3465",
    "sg:province":"VIC",
    "sg:tags":[
        "medical",
        "practitioner"
    ],
    "wof:name":"Dr Mun Fook Yoong",
    "wof:placetype":"venue"
},
  "geometry": {"coordinates":[143.736602783,-37.0451469421],"type":"Point"}
}