{
  "type": "Feature",
  "properties": {
    "addr:full":"Dawson St Hawkesdale VIC 3287",
    "addr:postcode":"3287",
    "addr:street":"Dawson St",
    "iso:country":"AU",
    "sg:address":"Dawson St",
    "sg:city":"Hawkesdale",
    "sg:classifiers":[
        {
            "category":"Wholesale",
            "subcategory":"Farm Supplies",
            "type":"Manufacturing & Wholesale Goods"
        }
    ],
    "sg:phone":"+61 3 5560 7264",
    "sg:postcode":"3287",
    "sg:province":"VIC",
    "sg:tags":[
        "equipment"
    ],
    "wof:name":"Elders Limited Hawkesdale",
    "wof:placetype":"venue"
},
  "geometry": {"coordinates":[142.322174072,-38.10546875],"type":"Point"}
}