{
  "type": "Feature",
  "properties": {
    "iso:country":"AU",
    "sg:address":"48 Denman Camp Rd",
    "sg:city":"Torquay",
    "sg:classifiers":[
        {
            "category":"Building & Trades",
            "subcategory":"Construction",
            "type":"Services"
        }
    ],
    "sg:phone":"+61 7 4128 1077",
    "sg:postcode":"4655",
    "sg:province":"QLD",
    "sg:tags":[
        "earth",
        "excavating",
        "moving",
        "contractor"
    ],
    "wof:name":"Hayward's Contracting Service",
    "wof:placetype":"venue"
},
  "geometry": {"coordinates":[152.86064099999999,-25.289961],"type":"Point"}
}