{
  "type": "Feature",
  "properties": {
    "addr:full":"2475 Stoneville Rd Stoneville WA 6081",
    "addr:postcode":"2475;6081",
    "addr:street":"Stoneville Rd",
    "iso:country":"AU",
    "sg:address":"2475 Stoneville Rd",
    "sg:city":"Stoneville",
    "sg:classifiers":[
        {
            "category":"Professional",
            "subcategory":"Engineering",
            "type":"Services"
        }
    ],
    "sg:phone":"+61 8 9295 1817",
    "sg:postcode":"6081",
    "sg:province":"WA",
    "sg:tags":[
        "engineer"
    ],
    "wof:name":"Eastern Hills Engineering",
    "wof:placetype":"venue"
},
  "geometry": {"coordinates":[116.171401977,-31.8799800873],"type":"Point"}
}