{
  "type": "Feature",
  "properties": {
    "iso:country":"AU",
    "sg:address":"34 Wingecarribee St",
    "sg:city":"Bowral",
    "sg:classifiers":[
        {
            "category":"Arena",
            "subcategory":"Sports Club",
            "type":"Entertainment"
        }
    ],
    "sg:phone":"+61 2 4862 2155",
    "sg:postcode":"2576",
    "sg:province":"NSW",
    "sg:tags":[
        "hunt",
        "racing"
    ],
    "wof:name":"Bong Bong Picnic Race Club Limited",
    "wof:placetype":"venue"
},
  "geometry": {"coordinates":[150.41880798299999,-34.4787712097],"type":"Point"}
}