{
  "type": "Feature",
  "properties": {
    "addr:full":"81 B Jedda Rd Prestons NSW 2170",
    "addr:housenumber":"81 b",
    "addr:postcode":"2170",
    "addr:street":"Jedda Rd",
    "iso:country":"AU",
    "sg:address":"81 B Jedda Rd",
    "sg:city":"Prestons",
    "sg:classifiers":[
        {
            "category":"Wholesale",
            "subcategory":"Furniture",
            "type":"Manufacturing & Wholesale Goods"
        }
    ],
    "sg:phone":"+61 2 8784 1888",
    "sg:postcode":"2170",
    "sg:province":"NSW",
    "sg:tags":[
        "wholesaler",
        "mfrs"
    ],
    "wof:name":"La-Z-Boy Australia Pty Ltd",
    "wof:placetype":"venue"
},
  "geometry": {"coordinates":[150.87086486800001,-33.9324073792],"type":"Point"}
}