{
  "type": "Feature",
  "properties": {
    "iso:country":"AU",
    "sg:address":"Sing St",
    "sg:city":"Tugun",
    "sg:classifiers":[
        {
            "category":"Wholesale",
            "subcategory":"Electrical",
            "type":"Manufacturing & Wholesale Goods"
        }
    ],
    "sg:phone":"+61 421 711 909",
    "sg:postcode":"4224",
    "sg:province":"QLD",
    "sg:tags":[
        "equipment",
        "testing",
        "electronic",
        "electric"
    ],
    "wof:name":"Tugun Electrical Services",
    "wof:placetype":"venue"
},
  "geometry": {"coordinates":[153.49029540999999,-28.1429653168],"type":"Point"}
}