{
  "type": "Feature",
  "properties": {
    "addr:full":"2nd Floor 22 Grenfell St Adelaide SA 5000",
    "addr:housenumber":"22",
    "addr:postcode":"5000",
    "addr:street":"Grenfell St",
    "iso:country":"AU",
    "sg:address":"2nd Floor 22 Grenfell St",
    "sg:city":"Adelaide",
    "sg:classifiers":[
        {
            "category":"Professional",
            "subcategory":"Management & Consulting",
            "type":"Services"
        }
    ],
    "sg:phone":"+61 8 8410 3044",
    "sg:postcode":"5000",
    "sg:province":"SA",
    "sg:tags":[
        "consultant",
        "migration"
    ],
    "wof:name":"Mary Lindsay & Associates",
    "wof:placetype":"venue"
},
  "geometry": {"coordinates":[138.600540161,-34.9241256714],"type":"Point"}
}