{
  "type": "Feature",
  "properties": {
    "addr:full":"Unit 27/ 2- 8 Daniel St Wetherill Park NSW 2164",
    "addr:housenumber":"/ 2 8",
    "addr:postcode":"2164",
    "addr:street":"Daniel St",
    "iso:country":"AU",
    "sg:address":"Unit 27/ 2- 8 Daniel St",
    "sg:city":"Wetherill Park",
    "sg:classifiers":[
        {
            "category":"Shopping",
            "subcategory":"Computers & Home Electronics",
            "type":"Retail Goods"
        }
    ],
    "sg:phone":"+61 2 9729 3822",
    "sg:postcode":"2164",
    "sg:province":"NSW",
    "sg:tags":[
        "equipment",
        "supply"
    ],
    "wof:name":"Printer Cartridges",
    "wof:placetype":"venue"
},
  "geometry": {"coordinates":[150.90553283700001,-33.8479804993],"type":"Point"}
}