{
  "type": "Feature",
  "properties": {
    "addr:full":"Suite 9/ 17 Knox St Double Bay NSW 2028",
    "addr:housenumber":"17",
    "addr:postcode":"2028",
    "addr:street":"Knox St",
    "iso:country":"AU",
    "sg:address":"Suite 9/ 17 Knox St",
    "sg:city":"Double Bay",
    "sg:classifiers":[
        {
            "category":"Personal",
            "subcategory":"Beauty Salon",
            "type":"Services"
        }
    ],
    "sg:phone":"+61 2 9327 2221",
    "sg:postcode":"2028",
    "sg:province":"NSW",
    "wof:name":"Kan Rena Cosmetics",
    "wof:placetype":"venue"
},
  "geometry": {"coordinates":[151.24418640100001,-33.8761482239],"type":"Point"}
}