{
  "type": "Feature",
  "properties": {
    "addr:full":"Lvl1/ 481 Church St Richmond VIC 3121",
    "addr:housenumber":"481",
    "addr:postcode":"3121",
    "addr:street":"Church St",
    "iso:country":"AU",
    "sg:address":"Lvl1/ 481 Church St",
    "sg:city":"Richmond",
    "sg:classifiers":[
        {
            "category":"Professional",
            "subcategory":"Engineering",
            "type":"Services"
        }
    ],
    "sg:phone":"+61 3 9420 9700",
    "sg:postcode":"3121",
    "sg:province":"VIC",
    "sg:tags":[
        "consulting",
        "engineer"
    ],
    "wof:name":"JDS Civil Designs",
    "wof:placetype":"venue"
},
  "geometry": {"coordinates":[144.99769592300001,-37.8278694153],"type":"Point"}
}