{
  "type": "Feature",
  "properties": {
    "addr:full":"21 Bapaume Rd Mosman NSW 2088",
    "addr:housenumber":"21",
    "addr:postcode":"2088",
    "addr:street":"Bapaume Rd",
    "iso:country":"AU",
    "sg:address":"21 Bapaume Rd",
    "sg:city":"Mosman",
    "sg:classifiers":[
        {
            "category":"Shopping",
            "subcategory":"Computers & Home Electronics",
            "type":"Retail Goods"
        }
    ],
    "sg:phone":"+61 411 702 187",
    "sg:postcode":"2088",
    "sg:province":"NSW",
    "sg:tags":[
        "cleaning"
    ],
    "wof:name":"Clean I.T.",
    "wof:placetype":"venue"
},
  "geometry": {"coordinates":[151.242385864,-33.8174858093],"type":"Point"}
}