{
  "type": "Feature",
  "properties": {
    "addr:full":"Cnr Avocet Blv & Armitage Drv Busselton WA 6280",
    "addr:postcode":"6280",
    "addr:street":"Cnr Avocet Blv & Armitage Drv",
    "iso:country":"AU",
    "sg:address":"Cnr Avocet Blv & Armitage Drv",
    "sg:city":"Busselton",
    "sg:classifiers":[
        {
            "category":"Education",
            "subcategory":"School",
            "type":"Public Place"
        }
    ],
    "sg:phone":"+61 8 9754 2544",
    "sg:postcode":"6280",
    "sg:province":"WA",
    "sg:tags":[
        "state",
        "except",
        "nsw"
    ],
    "wof:name":"Busselton Primary School",
    "wof:placetype":"venue"
},
  "geometry": {"coordinates":[115.37773132300001,-33.639705658],"type":"Point"}
}