{
  "type": "Feature",
  "properties": {
    "iso:country":"AU",
    "sg:address":"8 Hamilton Pl",
    "sg:city":"Mt Waverley",
    "sg:classifiers":[
        {
            "category":"Personal",
            "subcategory":"Barber",
            "type":"Services"
        }
    ],
    "sg:phone":"+61 3 9807 5836",
    "sg:postcode":"3149",
    "sg:province":"VIC",
    "wof:name":"Barbers On The Hill",
    "wof:placetype":"venue"
},
  "geometry": {"coordinates":[145.12792968799999,-37.8757629395],"type":"Point"}
}