{
  "type": "Feature",
  "properties": {
    "addr:full":"52 Sackville St Montmorency VIC 3094",
    "addr:housenumber":"52",
    "addr:postcode":"3094",
    "addr:street":"Sackville St",
    "iso:country":"AU",
    "sg:address":"52 Sackville St",
    "sg:city":"Montmorency",
    "sg:classifiers":[
        {
            "category":"Shopping",
            "subcategory":"News",
            "type":"Retail Goods"
        }
    ],
    "sg:phone":"+61 3 9439 0500",
    "sg:postcode":"3094",
    "sg:province":"VIC",
    "sg:tags":[
        "magazine",
        "periodical"
    ],
    "wof:name":"K R Media Pty Ltd",
    "wof:placetype":"venue"
},
  "geometry": {"coordinates":[145.12971496599999,-37.728061676],"type":"Point"}
}