{
  "type": "Feature",
  "properties": {
    "addr:full":"PO Box 1335 Naracoorte SA 5271",
    "addr:postcode":"5271",
    "iso:country":"AU",
    "sg:address":"PO Box 1335",
    "sg:city":"Naracoorte",
    "sg:classifiers":[
        {
            "category":"Utilities",
            "subcategory":"Water",
            "type":"Services"
        }
    ],
    "sg:phone":"+61 8 8762 4078",
    "sg:postcode":"5271",
    "sg:province":"SA",
    "sg:tags":[
        "hot",
        "system"
    ],
    "wof:name":"John Hunter Plumber & Drainer",
    "wof:placetype":"venue"
},
  "geometry": {"coordinates":[140.730087,-36.95422],"type":"Point"}
}