{
  "type": "Feature",
  "properties": {
    "iso:country":"AU",
    "sg:address":"15 Semaphore Rd",
    "sg:city":"Semaphore",
    "sg:classifiers":[
        {
            "category":"Real Estate",
            "subcategory":"Real Estate Agent",
            "type":"Services"
        }
    ],
    "sg:phone":"+61 8 8449 3300",
    "sg:postcode":"5019",
    "sg:province":"SA",
    "wof:name":"Brock Harcourts",
    "wof:placetype":"venue"
},
  "geometry": {"coordinates":[138.481292725,-34.8381614685],"type":"Point"}
}