{
  "type": "Feature",
  "properties": {
    "addr:full":"237 Sydney Rd Fairlight NSW 2094",
    "addr:housenumber":"237",
    "addr:postcode":"2094",
    "addr:street":"Sydney Rd",
    "iso:country":"AU",
    "sg:address":"237 Sydney Rd",
    "sg:city":"Fairlight",
    "sg:classifiers":[
        {
            "category":"Personal",
            "subcategory":"Beauty Salon",
            "type":"Services"
        }
    ],
    "sg:phone":"+61 2 9948 7269",
    "sg:postcode":"2094",
    "sg:province":"NSW",
    "sg:tags":[
        "hairdresser"
    ],
    "wof:name":"Rusk International",
    "wof:placetype":"venue"
},
  "geometry": {"coordinates":[151.27142334000001,-33.7951202393],"type":"Point"}
}