{
  "type": "Feature",
  "properties": {
    "iso:country":"AU",
    "sg:address":"106 Fitzroy St",
    "sg:city":"Surry Hills",
    "sg:classifiers":[
        {
            "category":"Travel",
            "subcategory":"Hotels & Motels",
            "type":"Entertainment"
        }
    ],
    "sg:phone":"+61 2 9331 3301",
    "sg:postcode":"2010",
    "sg:province":"NSW",
    "sg:tags":[
        "accommodation"
    ],
    "wof:name":"The Cricketers Arms Hotel",
    "wof:placetype":"venue"
},
  "geometry": {"coordinates":[151.21726989699999,-33.8856887817],"type":"Point"}
}