{
  "type": "Feature",
  "properties": {
    "addr:full":"Silo Hill, Broadway St Stroud NSW 2425",
    "addr:housenumber":"silo",
    "addr:postcode":"2425",
    "addr:street":"Hill Broadway St",
    "iso:country":"AU",
    "sg:address":"Silo Hill, Broadway St",
    "sg:city":"Stroud",
    "sg:classifiers":[
        {
            "category":"Building & Trades",
            "subcategory":"Construction",
            "type":"Services"
        }
    ],
    "sg:phone":"+61 2 4994 5211",
    "sg:postcode":"2425",
    "sg:province":"NSW",
    "sg:tags":[
        "earth",
        "excavating",
        "moving",
        "contractor"
    ],
    "wof:name":"Midcoast Under Road Boring Pty Ltd",
    "wof:placetype":"venue"
},
  "geometry": {"coordinates":[151.96788024899999,-32.4060783386],"type":"Point"}
}