{
  "type": "Feature",
  "properties": {
    "addr:full":"735 Woodville Rd Binda NSW 2583",
    "addr:housenumber":"735",
    "addr:postcode":"2583",
    "addr:street":"Woodville Rd",
    "iso:country":"AU",
    "sg:address":"735 Woodville Rd",
    "sg:city":"Binda",
    "sg:classifiers":[
        {
            "category":"Building & Trades",
            "subcategory":"Landscaping Services",
            "type":"Services"
        }
    ],
    "sg:phone":"+61 2 4835 6205",
    "sg:postcode":"2583",
    "sg:province":"NSW",
    "sg:tags":[
        "grazier"
    ],
    "wof:name":"Leeming J E",
    "wof:placetype":"venue"
},
  "geometry": {"coordinates":[149.314697266,-34.3790740967],"type":"Point"}
}