{
  "type": "Feature",
  "properties": {
    "addr:full":"Breakwater Rd Breakwater VIC 3219",
    "addr:postcode":"3219",
    "addr:street":"Breakwater Rd",
    "iso:country":"AU",
    "sg:address":"Breakwater Rd",
    "sg:city":"Breakwater",
    "sg:classifiers":[
        {
            "category":"Retail",
            "subcategory":"Event Space",
            "type":"Services"
        }
    ],
    "sg:phone":"+61 3 5229 4414",
    "sg:postcode":"3219",
    "sg:province":"VIC",
    "sg:tags":[
        "venue",
        "reception",
        "wedding"
    ],
    "wof:name":"Geelong Racing Club",
    "wof:placetype":"venue"
},
  "geometry": {"coordinates":[144.369674683,-38.1758995056],"type":"Point"}
}