{
  "type": "Feature",
  "properties": {
    "iso:country":"AU",
    "sg:address":"160 New St",
    "sg:city":"Ringwood",
    "sg:classifiers":[
        {
            "category":"Retail",
            "subcategory":"Auto Repair",
            "type":"Services"
        }
    ],
    "sg:phone":"+61 3 9879 2011",
    "sg:postcode":"3134",
    "sg:province":"VIC",
    "sg:tags":[
        "repairer",
        "motor",
        "engineer"
    ],
    "wof:name":"Bee Kay Motors",
    "wof:placetype":"venue"
},
  "geometry": {"coordinates":[145.220306397,-37.8257598877],"type":"Point"}
}