{
  "type": "Feature",
  "properties": {
    "addr:full":"2 Telford St Earlville QLD 4870",
    "addr:housenumber":"2",
    "addr:postcode":"4870",
    "addr:street":"Telford St",
    "iso:country":"AU",
    "sg:address":"2 Telford St",
    "sg:city":"Earlville",
    "sg:classifiers":[
        {
            "category":"Manufacturing",
            "subcategory":"Petroleum Products",
            "type":"Manufacturing & Wholesale Goods"
        }
    ],
    "sg:phone":"+61 7 4054 2755",
    "sg:postcode":"4870",
    "sg:province":"QLD",
    "sg:tags":[
        "fuel",
        "oil",
        "additive"
    ],
    "wof:name":"Graford Pty Ltd",
    "wof:placetype":"venue"
},
  "geometry": {"coordinates":[145.74322509800001,-16.9437198639],"type":"Point"}
}