{
  "type": "Feature",
  "properties": {
    "addr:full":"162 Great North Rd Five Dock NSW 2046",
    "addr:housenumber":"162",
    "addr:postcode":"2046",
    "addr:street":"Great North Rd",
    "iso:country":"AU",
    "sg:address":"162 Great North Rd",
    "sg:city":"Five Dock",
    "sg:classifiers":[
        {
            "category":"Real Estate",
            "subcategory":"Real Estate Agent",
            "type":"Services"
        }
    ],
    "sg:phone":"+61 411 099 011",
    "sg:postcode":"2046",
    "sg:province":"NSW",
    "wof:name":"Century 21 Natoli",
    "wof:placetype":"venue"
},
  "geometry": {"coordinates":[151.130447,-33.864929],"type":"Point"}
}