{
  "type": "Feature",
  "properties": {
    "addr:full":"18 Main St Monbulk VIC 3793",
    "addr:housenumber":"18",
    "addr:postcode":"3793",
    "addr:street":"Main St",
    "iso:country":"AU",
    "sg:address":"18 Main St",
    "sg:city":"Monbulk",
    "sg:classifiers":[
        {
            "category":"Education",
            "subcategory":"Dance Studio",
            "type":"Public Place"
        }
    ],
    "sg:phone":"+61 3 9894 3265",
    "sg:postcode":"3793",
    "sg:province":"VIC",
    "sg:tags":[
        "venue",
        "tuition"
    ],
    "wof:name":"Kallista Dance Academy",
    "wof:placetype":"venue"
},
  "geometry": {"coordinates":[145.33003234899999,-37.9030570984],"type":"Point"}
}