{
  "type": "Feature",
  "properties": {
    "iso:country":"AU",
    "sg:address":"46 Main St",
    "sg:city":"St Marys",
    "sg:classifiers":[
        {
            "category":"Personal",
            "subcategory":"Beauty Salon",
            "type":"Services"
        }
    ],
    "sg:phone":"+61 3 6372 2108",
    "sg:postcode":"7215",
    "sg:province":"TAS",
    "sg:tags":[
        "hairdresser"
    ],
    "wof:name":"Designer Hair Studio",
    "wof:placetype":"venue"
},
  "geometry": {"coordinates":[148.18571499999999,-41.579807],"type":"Point"}
}