{
  "type": "Feature",
  "properties": {
    "addr:full":"PO Box 3191 Parramatta NSW 2124",
    "addr:postcode":"2124",
    "iso:country":"AU",
    "sg:address":"PO Box 3191",
    "sg:city":"Parramatta",
    "sg:classifiers":[
        {
            "category":"Professional",
            "subcategory":"Art Services",
            "type":"Services"
        }
    ],
    "sg:phone":"+61 2 9896 5416",
    "sg:postcode":"2124",
    "sg:province":"NSW",
    "sg:tags":[
        "decorator",
        "painter"
    ],
    "wof:name":"JP Quality Painting Services P/L",
    "wof:placetype":"venue"
},
  "geometry": {"coordinates":[151.003448486,-33.8169593811],"type":"Point"}
}