{
  "type": "Feature",
  "properties": {
    "addr:full":"29 Carlisle St St Kilda VIC 3182",
    "addr:housenumber":"29",
    "addr:postcode":"3182",
    "addr:street":"Carlisle St",
    "iso:country":"AU",
    "sg:address":"29 Carlisle St St",
    "sg:city":"Kilda",
    "sg:classifiers":[
        {
            "category":"Building & Trades",
            "subcategory":"Locksmith",
            "type":"Services"
        }
    ],
    "sg:phone":"+61 3 9534 0586",
    "sg:postcode":"3182",
    "sg:province":"VIC",
    "sg:tags":[
        "lock"
    ],
    "wof:name":"A.AAAce Locksmiths",
    "wof:placetype":"venue"
},
  "geometry": {"coordinates":[144.98101806599999,-37.8672370911],"type":"Point"}
}