{
  "type": "Feature",
  "properties": {
    "addr:full":"U12/ 84 Ainsworth St Mawson ACT 2607",
    "addr:postcode":"2607",
    "addr:street":"/ 84 Ainsworth St",
    "iso:country":"AU",
    "sg:address":"U12/ 84 Ainsworth St",
    "sg:city":"Mawson",
    "sg:classifiers":[
        {
            "category":"Health Services",
            "subcategory":"Health Practitioner",
            "type":"Services"
        }
    ],
    "sg:phone":"+61 2 6285 3738",
    "sg:postcode":"2607",
    "sg:province":"ACT",
    "sg:tags":[
        "osteopath"
    ],
    "wof:name":"Osteopathic Services Canberra",
    "wof:placetype":"venue"
},
  "geometry": {"coordinates":[149.097930908,-35.3553390503],"type":"Point"}
}