{
  "type": "Feature",
  "properties": {
    "addr:full":"Level 1 / 50 Davenport St Southport QLD 4215",
    "addr:housenumber":"/ 50",
    "addr:postcode":"4215",
    "addr:street":"Davenport St",
    "iso:country":"AU",
    "sg:address":"Level 1 / 50 Davenport St",
    "sg:city":"Southport",
    "sg:classifiers":[
        {
            "category":"Banks & Credit Unions",
            "subcategory":"Financial Services",
            "type":"Services"
        }
    ],
    "sg:phone":"+61 7 5571 1342",
    "sg:postcode":"4215",
    "sg:province":"QLD",
    "sg:tags":[
        "planning"
    ],
    "sg:website":"http://www.solutionsunlimited.com.au",
    "wof:name":"Solutions Unlimited Financial Planning",
    "wof:placetype":"venue"
},
  "geometry": {"coordinates":[153.412399292,-27.9674034119],"type":"Point"}
}