{
  "type": "Feature",
  "properties": {
    "addr:full":"39 Leewood Drv Orange NSW 2800",
    "addr:housenumber":"39",
    "addr:postcode":"2800",
    "addr:street":"Leewood Drv",
    "iso:country":"AU",
    "sg:address":"39 Leewood Drv",
    "sg:city":"Orange",
    "sg:classifiers":[
        {
            "category":"Retail",
            "subcategory":"Auto Repair",
            "type":"Services"
        }
    ],
    "sg:phone":"+61 2 6362 0848",
    "sg:postcode":"2800",
    "sg:province":"NSW",
    "sg:tags":[
        "electrical"
    ],
    "wof:name":"Apple City Auto Electrics P/L",
    "wof:placetype":"venue"
},
  "geometry": {"coordinates":[149.10667419399999,-33.3093948364],"type":"Point"}
}