{
  "type": "Feature",
  "properties": {
    "iso:country":"AU",
    "sg:address":"58 Goondoon St",
    "sg:city":"Gladstone",
    "sg:classifiers":[
        {
            "category":"Retail",
            "subcategory":"Event Space",
            "type":"Services"
        }
    ],
    "sg:phone":"+61 7 4972 2822",
    "sg:postcode":"4680",
    "sg:province":"QLD",
    "sg:tags":[
        "venue",
        "reception",
        "wedding"
    ],
    "wof:name":"Gladstone Entertainment Centre",
    "wof:placetype":"venue"
},
  "geometry": {"coordinates":[151.25457763700001,-23.8410511017],"type":"Point"}
}