{
  "type": "Feature",
  "properties": {
    "addr:full":"Lvl 7, 7 Underwood St Sydney NSW 2000",
    "addr:housenumber":"7",
    "addr:postcode":"2000",
    "addr:street":"Underwood St",
    "iso:country":"AU",
    "sg:address":"Lvl 7, 7 Underwood St",
    "sg:city":"Sydney",
    "sg:classifiers":[
        {
            "category":"Professional",
            "subcategory":"Management & Consulting",
            "type":"Services"
        }
    ],
    "sg:phone":"+61 2 9255 7855",
    "sg:postcode":"2000",
    "sg:province":"NSW",
    "sg:tags":[
        "consultant"
    ],
    "wof:name":"Robertson Burns",
    "wof:placetype":"venue"
},
  "geometry": {"coordinates":[151.20854187,-33.8624191284],"type":"Point"}
}