{
  "type": "Feature",
  "properties": {
    "iso:country":"AU",
    "sg:address":"997 Graf Ave",
    "sg:city":"West Ryde",
    "sg:classifiers":[
        {
            "category":"Health Services",
            "subcategory":"Health Practitioner",
            "type":"Services"
        }
    ],
    "sg:phone":"+61 2 9809 3854",
    "sg:postcode":"2114",
    "sg:province":"NSW",
    "sg:tags":[
        "physiotherapist"
    ],
    "wof:name":"Ekman Nicole",
    "wof:placetype":"venue"
},
  "geometry": {"coordinates":[151.08732605,-33.8069343567],"type":"Point"}
}