{
  "type": "Feature",
  "properties": {
    "addr:full":"PO Box 726 Albany DC WA 6331",
    "addr:postcode":"6331",
    "iso:country":"AU",
    "sg:address":"PO Box 726",
    "sg:city":"Albany DC",
    "sg:classifiers":[
        {
            "category":"Utilities",
            "subcategory":"Natural Gas",
            "type":"Services"
        }
    ],
    "sg:phone":"+61 8 9842 9169",
    "sg:postcode":"6331",
    "sg:province":"WA",
    "sg:tags":[
        "consultant",
        "resource"
    ],
    "wof:name":"Edenborn Pty Ltd",
    "wof:placetype":"venue"
},
  "geometry": {"coordinates":[117.859283447,-35.0605697632],"type":"Point"}
}