{
  "type": "Feature",
  "properties": {
    "addr:full":"31 Peel Rd O&#039;Connor WA 6163",
    "addr:housenumber":"31",
    "addr:postcode":"6163",
    "addr:street":"Peel Rd",
    "iso:country":"AU",
    "sg:address":"31 Peel Rd",
    "sg:city":"O&#039;Connor",
    "sg:classifiers":[
        {
            "category":"Retail",
            "subcategory":"Auto Repair",
            "type":"Services"
        }
    ],
    "sg:phone":"+61 8 9331 5599",
    "sg:postcode":"6163",
    "sg:province":"WA",
    "sg:tags":[
        "repairer",
        "motor",
        "engineer"
    ],
    "wof:name":"Formaz Performance Centre",
    "wof:placetype":"venue"
},
  "geometry": {"coordinates":[115.795479,-32.060345],"type":"Point"}
}