{
  "type": "Feature",
  "properties": {
    "iso:country":"AU",
    "sg:address":"1 Isabella St",
    "sg:city":"Geelong West",
    "sg:classifiers":[
        {
            "category":"Professional",
            "subcategory":"Printing & Photocopies",
            "type":"Services"
        }
    ],
    "sg:phone":"+61 13 14 76",
    "sg:postcode":"3218",
    "sg:province":"VIC",
    "sg:tags":[
        "photocopier"
    ],
    "wof:name":"Ricoh Australia Pty Ltd",
    "wof:placetype":"venue"
},
  "geometry": {"coordinates":[144.349365234,-38.1334724426],"type":"Point"}
}