{
  "type": "Feature",
  "properties": {
    "addr:full":"16 Dunbar St Stockton NSW 2295",
    "addr:housenumber":"16",
    "addr:postcode":"2295",
    "addr:street":"Dunbar St",
    "iso:country":"AU",
    "sg:address":"16 Dunbar St",
    "sg:city":"Stockton",
    "sg:classifiers":[
        {
            "category":"Professional",
            "subcategory":"Accounting & Tax Preparation",
            "type":"Services"
        }
    ],
    "sg:phone":"+61 2 4920 1311",
    "sg:postcode":"2295",
    "sg:province":"NSW",
    "sg:tags":[
        "consultant",
        "taxation"
    ],
    "wof:name":"Walmsley Mark",
    "wof:placetype":"venue"
},
  "geometry": {"coordinates":[151.78416442899999,-32.9150390625],"type":"Point"}
}