{
  "type": "Feature",
  "properties": {
    "addr:full":"151 Towen Mount Rd Nambour QLD 4560",
    "addr:housenumber":"151",
    "addr:postcode":"4560",
    "addr:street":"Towen Mount Rd",
    "iso:country":"AU",
    "sg:address":"151 Towen Mount Rd",
    "sg:city":"Nambour",
    "sg:classifiers":[
        {
            "category":"Building & Trades",
            "subcategory":"Construction",
            "type":"Services"
        }
    ],
    "sg:phone":"+61 7 5441 5416",
    "sg:postcode":"4560",
    "sg:province":"QLD",
    "sg:tags":[
        "contractor"
    ],
    "wof:name":"Zande Ian & Kathy",
    "wof:placetype":"venue"
},
  "geometry": {"coordinates":[152.933303833,-26.6501312256],"type":"Point"}
}