{
  "type": "Feature",
  "properties": {
    "iso:country":"AU",
    "sg:address":"36 Wells Rd",
    "sg:city":"Frankston",
    "sg:classifiers":[
        {
            "category":"Building & Trades",
            "subcategory":"Construction",
            "type":"Services"
        }
    ],
    "sg:phone":"+61 3 9786 6889",
    "sg:postcode":"3199",
    "sg:province":"VIC",
    "sg:tags":[
        "window",
        "tinting"
    ],
    "wof:name":"Tint A Car",
    "wof:placetype":"venue"
},
  "geometry": {"coordinates":[145.13470459000001,-38.1220932007],"type":"Point"}
}