{
  "type": "Feature",
  "properties": {
    "addr:full":"129 Swanport Rd Murray Bridge SA 5253",
    "addr:housenumber":"129",
    "addr:postcode":"5253",
    "addr:street":"Swanport Rd",
    "iso:country":"AU",
    "sg:address":"129 Swanport Rd",
    "sg:city":"Murray Bridge",
    "sg:classifiers":[
        {
            "category":"Personal",
            "subcategory":"Beauty Salon",
            "type":"Services"
        }
    ],
    "sg:phone":"+61 8 8532 2042",
    "sg:postcode":"5253",
    "sg:province":"SA",
    "sg:tags":[
        "hairdresser"
    ],
    "wof:name":"Haircut Junction",
    "wof:placetype":"venue"
},
  "geometry": {"coordinates":[139.280487061,-35.1324882507],"type":"Point"}
}