{
  "type": "Feature",
  "properties": {
    "addr:full":"Stall 11-12 Railway Markets Gosnells WA 6110",
    "addr:housenumber":"11-12;markets",
    "addr:postcode":"6110",
    "addr:street":"Railway",
    "iso:country":"AU",
    "sg:address":"Stall 11-12 Railway Markets",
    "sg:city":"Gosnells",
    "sg:classifiers":[
        {
            "category":"Shopping",
            "subcategory":"Baby Store",
            "type":"Retail Goods"
        }
    ],
    "sg:phone":"+61 8 9490 3630",
    "sg:postcode":"6110",
    "sg:province":"WA",
    "sg:tags":[
        "children's",
        "wear"
    ],
    "wof:name":"Great Train Clobbery The",
    "wof:placetype":"venue"
},
  "geometry": {"coordinates":[116.005996704,-32.0708580017],"type":"Point"}
}