{
  "type": "Feature",
  "properties": {
    "addr:full":"34 Dredge St Reservoir VIC 3073",
    "addr:housenumber":"34",
    "addr:postcode":"3073",
    "addr:street":"Dredge St",
    "iso:country":"AU",
    "sg:address":"34 Dredge St",
    "sg:city":"Reservoir",
    "sg:classifiers":[
        {
            "category":"Retail",
            "subcategory":"Auto Rental",
            "type":"Services"
        }
    ],
    "sg:phone":"+61 3 9460 3820",
    "sg:postcode":"3073",
    "sg:province":"VIC",
    "sg:tags":[
        "chauffeur",
        "car",
        "hire",
        "driven",
        "limousine"
    ],
    "wof:name":"A Royal Melbourne Limousines",
    "wof:placetype":"venue"
},
  "geometry": {"coordinates":[144.995483398,-37.6946334839],"type":"Point"}
}