{
  "type": "Feature",
  "properties": {
    "addr:full":"Level 6, 300 George St Sydney NSW 2000",
    "addr:housenumber":"300",
    "addr:postcode":"2000",
    "addr:street":"George St",
    "iso:country":"AU",
    "sg:address":"Level 6, 300 George St",
    "sg:city":"Sydney",
    "sg:classifiers":[
        {
            "category":"Travel",
            "subcategory":"Travel Agent",
            "type":"Entertainment"
        }
    ],
    "sg:phone":"+61 1300 660 825",
    "sg:postcode":"2000",
    "sg:province":"NSW",
    "sg:tags":[
        "consultant"
    ],
    "wof:name":"G.E.T. Educational Tours Pty Ltd",
    "wof:placetype":"venue"
},
  "geometry": {"coordinates":[151.207427978,-33.8656806946],"type":"Point"}
}