{
  "type": "Feature",
  "properties": {
    "addr:full":"5/ 746 Ipswich Rd Annerley QLD 4103",
    "addr:housenumber":"/ 746",
    "addr:postcode":"4103",
    "addr:street":"Ipswich Rd",
    "iso:country":"AU",
    "sg:address":"5/ 746 Ipswich Rd",
    "sg:city":"Annerley",
    "sg:classifiers":[
        {
            "category":"Professional",
            "subcategory":"Art Services",
            "type":"Services"
        }
    ],
    "sg:phone":"+61 7 3848 7354",
    "sg:postcode":"4103",
    "sg:province":"QLD",
    "sg:tags":[
        "decorator",
        "painter"
    ],
    "wof:name":"BFC Painters",
    "wof:placetype":"venue"
},
  "geometry": {"coordinates":[153.027267456,-27.5204982758],"type":"Point"}
}