{
  "type": "Feature",
  "properties": {
    "addr:full":"PO Box 268 Moonta SA 5558",
    "addr:postcode":"5558",
    "iso:country":"AU",
    "sg:address":"PO Box 268",
    "sg:city":"Moonta",
    "sg:classifiers":[
        {
            "category":"Recreation",
            "subcategory":"Fishing",
            "type":"Entertainment"
        }
    ],
    "sg:phone":"+61 429 413 414",
    "sg:postcode":"5558",
    "sg:province":"SA",
    "sg:tags":[
        "trip"
    ],
    "wof:name":"Dean's Fishing Charters",
    "wof:placetype":"venue"
},
  "geometry": {"coordinates":[137.59390258799999,-34.0681495667],"type":"Point"}
}