{
  "type": "Feature",
  "properties": {
    "addr:full":"60 Waterloo Rd North Ryde NSW 2113",
    "addr:housenumber":"60",
    "addr:postcode":"2113",
    "addr:street":"Waterloo Rd",
    "iso:country":"AU",
    "sg:address":"60 Waterloo Rd",
    "sg:city":"North Ryde",
    "sg:classifiers":[
        {
            "category":"Health Services",
            "subcategory":"Doctor",
            "type":"Services"
        }
    ],
    "sg:phone":"+61 2 9692 7000",
    "sg:postcode":"2113",
    "sg:province":"NSW",
    "sg:tags":[
        "medical",
        "practitioner"
    ],
    "wof:name":"Macquarie Pathology Services",
    "wof:placetype":"venue"
},
  "geometry": {"coordinates":[151.125610352,-33.7831764221],"type":"Point"}
}