{
  "type": "Feature",
  "properties": {
    "iso:country":"AU",
    "sg:address":"Shop 53 Sunshine Plaza Shopping Centre",
    "sg:city":"Sunshine",
    "sg:classifiers":[
        {
            "category":"Fast Food",
            "type":"Food & Drink"
        }
    ],
    "sg:phone":"+61 3 9310 1656",
    "sg:postcode":"3020",
    "sg:province":"VIC",
    "sg:tags":[
        "away",
        "take"
    ],
    "wof:name":"Donut King",
    "wof:placetype":"venue"
},
  "geometry": {"coordinates":[144.829041,-37.746319],"type":"Point"}
}