{
  "type": "Feature",
  "properties": {
    "iso:country":"AU",
    "sg:address":"379 Bong Bong St",
    "sg:city":"Bowral",
    "sg:classifiers":[
        {
            "category":"Shopping",
            "subcategory":"Antiques",
            "type":"Retail Goods"
        }
    ],
    "sg:phone":"+61 2 4861 2134",
    "sg:postcode":"2576",
    "sg:province":"NSW",
    "wof:name":"Lancelot Hill Antiques",
    "wof:placetype":"venue"
},
  "geometry": {"coordinates":[150.41770935100001,-34.4803276062],"type":"Point"}
}