{
  "type": "Feature",
  "properties": {
    "iso:country":"AU",
    "sg:address":"24A Tennant St",
    "sg:city":"Casula",
    "sg:classifiers":[
        {
            "category":"Professional",
            "subcategory":"Business Services",
            "type":"Services"
        }
    ],
    "sg:phone":"+61 412 700 510",
    "sg:postcode":"2170",
    "sg:province":"NSW",
    "sg:tags":[
        "drafting"
    ],
    "wof:name":"BR Taylor Designer Buildings",
    "wof:placetype":"venue"
},
  "geometry": {"coordinates":[150.89938354500001,-33.9569740295],"type":"Point"}
}