{
  "type": "Feature",
  "properties": {
    "addr:full":"61 York St Subiaco WA 6008",
    "addr:housenumber":"61",
    "addr:postcode":"6008",
    "addr:street":"York St",
    "iso:country":"AU",
    "sg:address":"61 York St",
    "sg:city":"Subiaco",
    "sg:classifiers":[
        {
            "category":"Retail",
            "subcategory":"Auto Repair",
            "type":"Services"
        }
    ],
    "sg:phone":"+61 8 9388 2282",
    "sg:postcode":"6008",
    "sg:province":"WA",
    "sg:tags":[
        "repairer",
        "motor",
        "engineer"
    ],
    "wof:name":"Stephensons Of Subiaco",
    "wof:placetype":"venue"
},
  "geometry": {"coordinates":[115.83310699499999,-31.9463863373],"type":"Point"}
}