{
  "type": "Feature",
  "properties": {
    "iso:country":"AU",
    "sg:address":"Shp2/ 94 Wises Rd",
    "sg:city":"Buderim",
    "sg:classifiers":[
        {
            "category":"Food & Beverages",
            "subcategory":"Bakery",
            "type":"Retail Goods"
        }
    ],
    "sg:phone":"+61 7 5479 1727",
    "sg:postcode":"4556",
    "sg:province":"QLD",
    "sg:tags":[
        "baker"
    ],
    "wof:name":"Bakery World",
    "wof:placetype":"venue"
},
  "geometry": {"coordinates":[153.08303832999999,-26.6709918976],"type":"Point"}
}