{
  "type": "Feature",
  "properties": {
    "addr:full":"Factory 7, 18- 20 Jesmond Rd Croydon VIC 3136",
    "addr:housenumber":"18 20",
    "addr:postcode":"3136",
    "addr:street":"Jesmond Rd",
    "iso:country":"AU",
    "sg:address":"Factory 7, 18- 20 Jesmond Rd",
    "sg:city":"Croydon",
    "sg:classifiers":[
        {
            "category":"Shopping",
            "subcategory":"Stationery & Office Supplies",
            "type":"Retail Goods"
        }
    ],
    "sg:phone":"+61 3 9723 8399",
    "sg:postcode":"3136",
    "sg:province":"VIC",
    "sg:tags":[
        "partition"
    ],
    "wof:name":"City Ceiling Services Pty Ltd",
    "wof:placetype":"venue"
},
  "geometry": {"coordinates":[145.28306579599999,-37.805896759],"type":"Point"}
}