{
  "type": "Feature",
  "properties": {
    "addr:full":"Shp1/ 62 Pendle Way Pendle Hill NSW 2145",
    "addr:housenumber":"62",
    "addr:postcode":"2145",
    "addr:street":"Pendle Way",
    "iso:country":"AU",
    "sg:address":"Shp1/ 62 Pendle Way",
    "sg:city":"Pendle Hill",
    "sg:classifiers":[
        {
            "category":"Food & Beverages",
            "subcategory":"Supermarket",
            "type":"Retail Goods"
        }
    ],
    "sg:phone":"+61 2 9896 1191",
    "sg:postcode":"2145",
    "sg:province":"NSW",
    "sg:tags":[
        "grocery",
        "store"
    ],
    "wof:name":"Rainbow Mixed Shop",
    "wof:placetype":"venue"
},
  "geometry": {"coordinates":[150.95390319800001,-33.8065261841],"type":"Point"}
}