{
  "type": "Feature",
  "properties": {
    "iso:country":"AU",
    "sg:address":"74 Main Rd",
    "sg:city":"Monbulk",
    "sg:classifiers":[
        {
            "category":"Travel",
            "subcategory":"Travel Agent",
            "type":"Entertainment"
        }
    ],
    "sg:phone":"+61 3 9756 7566",
    "sg:postcode":"3793",
    "sg:province":"VIC",
    "sg:tags":[
        "consultant"
    ],
    "wof:name":"Monbulk Travel Services (Travelscene Monbulk)",
    "wof:placetype":"venue"
},
  "geometry": {"coordinates":[145.40769958499999,-37.8751602173],"type":"Point"}
}