{
  "type": "Feature",
  "properties": {
    "iso:country":"AU",
    "sg:address":"22 Bathurst St",
    "sg:city":"Condobolin",
    "sg:classifiers":[
        {
            "category":"Wholesale",
            "subcategory":"Metals & Minerals",
            "type":"Manufacturing & Wholesale Goods"
        }
    ],
    "sg:phone":"+61 2 6895 4180",
    "sg:postcode":"2877",
    "sg:province":"NSW",
    "sg:tags":[
        "steel",
        "merchant"
    ],
    "wof:name":"C S Steel Sales",
    "wof:placetype":"venue"
},
  "geometry": {"coordinates":[147.14707899999999,-33.088295],"type":"Point"}
}