{
  "type": "Feature",
  "properties": {
    "iso:country":"AU",
    "sg:address":"267 Goonoo Goonoo Rd",
    "sg:city":"Tamworth",
    "sg:classifiers":[
        {
            "category":"Health Services",
            "subcategory":"Health Practitioner",
            "type":"Services"
        }
    ],
    "sg:phone":"+61 2 6765 7928",
    "sg:postcode":"2340",
    "sg:province":"NSW",
    "sg:tags":[
        "naturopath"
    ],
    "wof:name":"Han Hua Chinese Medicine Centre",
    "wof:placetype":"venue"
},
  "geometry": {"coordinates":[150.92315673799999,-31.1137542725],"type":"Point"}
}