{
  "type": "Feature",
  "properties": {
    "addr:full":"17 Chard Rd Brookvale NSW 2100",
    "addr:housenumber":"17",
    "addr:postcode":"2100",
    "addr:street":"Chard Rd",
    "iso:country":"AU",
    "sg:address":"17 Chard Rd",
    "sg:city":"Brookvale",
    "sg:classifiers":[
        {
            "category":"Home & Garden",
            "subcategory":"Hardware",
            "type":"Retail Goods"
        }
    ],
    "sg:phone":"+61 2 9907 3699",
    "sg:postcode":"2100",
    "sg:province":"NSW",
    "sg:tags":[
        "woodworking",
        "machinery"
    ],
    "wof:name":"Sawmill Services Pty Ltd",
    "wof:placetype":"venue"
},
  "geometry": {"coordinates":[151.275192261,-33.7646827698],"type":"Point"}
}