{
  "type": "Feature",
  "properties": {
    "addr:full":"609 Hme Hwy Casula NSW 2170",
    "addr:postcode":"2170",
    "addr:street":"Hwy",
    "iso:country":"AU",
    "sg:address":"609 Hme Hwy",
    "sg:city":"Casula",
    "sg:classifiers":[
        {
            "category":"Home & Garden",
            "subcategory":"Garden Supply",
            "type":"Retail Goods"
        }
    ],
    "sg:phone":"+61 2 9822 2861",
    "sg:postcode":"2170",
    "sg:province":"NSW",
    "sg:tags":[
        "shed"
    ],
    "wof:name":"Sheds Plus",
    "wof:placetype":"venue"
},
  "geometry": {"coordinates":[150.90455627399999,-33.9505996704],"type":"Point"}
}