{
  "type": "Feature",
  "properties": {
    "iso:country":"AU",
    "sg:address":"104 Flinders St",
    "sg:city":"East Townsville",
    "sg:classifiers":[
        {
            "category":"Fast Food",
            "type":"Food & Drink"
        }
    ],
    "sg:phone":"+61 7 4721 1311",
    "sg:postcode":"4810",
    "sg:province":"QLD",
    "sg:tags":[
        "away",
        "take"
    ],
    "wof:name":"Red Rooster",
    "wof:placetype":"venue"
},
  "geometry": {"coordinates":[146.810226,-19.266369],"type":"Point"}
}