{
  "type": "Feature",
  "properties": {
    "addr:full":"247 Old Illawarra Rd Barden Ridge NSW 2234",
    "addr:housenumber":"247",
    "addr:postcode":"2234",
    "addr:street":"Old Illawarra Rd",
    "iso:country":"AU",
    "sg:address":"247 Old Illawarra Rd",
    "sg:city":"Barden Ridge",
    "sg:classifiers":[
        {
            "category":"Professional",
            "subcategory":"Accounting & Tax Preparation",
            "type":"Services"
        }
    ],
    "sg:phone":"+61 2 9532 1986",
    "sg:postcode":"2234",
    "sg:province":"NSW",
    "sg:tags":[
        "accountant",
        "auditor"
    ],
    "wof:name":"Firm Financial & Accounting",
    "wof:placetype":"venue"
},
  "geometry": {"coordinates":[151.00814819300001,-34.0241165161],"type":"Point"}
}