{
  "type": "Feature",
  "properties": {
    "addr:full":"Shp 236 Charlestown Shopng Sq Charlestown NSW 2290",
    "addr:housenumber":"236",
    "addr:postcode":"2290",
    "addr:street":"Shopng Sq",
    "iso:country":"AU",
    "sg:address":"Shp 236",
    "sg:city":"Charlestown Shopng Sq Charlestown",
    "sg:classifiers":[
        {
            "category":"Travel",
            "subcategory":"Travel Agent",
            "type":"Entertainment"
        }
    ],
    "sg:phone":"+61 2 4943 6022",
    "sg:postcode":"2290",
    "sg:province":"NSW",
    "sg:tags":[
        "consultant"
    ],
    "wof:name":"Thomas Cook",
    "wof:placetype":"venue"
},
  "geometry": {"coordinates":[151.68707275400001,-32.9574317932],"type":"Point"}
}