{
  "type": "Feature",
  "properties": {
    "addr:full":"60 Tarwin Meadows Rd Tarwin Lower VIC 3956",
    "addr:housenumber":"60",
    "addr:postcode":"3956",
    "addr:street":"Tarwin Meadows Rd",
    "iso:country":"AU",
    "sg:address":"60 Tarwin Meadows Rd",
    "sg:city":"Tarwin Lower",
    "sg:classifiers":[
        {
            "category":"Social Services",
            "subcategory":"Child Care",
            "type":"Services"
        }
    ],
    "sg:phone":"+61 3 5663 5239",
    "sg:postcode":"3956",
    "sg:province":"VIC",
    "sg:tags":[
        "shearer"
    ],
    "wof:name":"Etherton R",
    "wof:placetype":"venue"
},
  "geometry": {"coordinates":[145.868484497,-38.706703186],"type":"Point"}
}