{
  "type": "Feature",
  "properties": {
    "iso:country":"AU",
    "sg:address":"Quiggan St",
    "sg:city":"Zeehan",
    "sg:classifiers":[
        {
            "category":"Mining & Drilling",
            "type":"Manufacturing & Wholesale Goods"
        }
    ],
    "sg:phone":"+61 3 6471 6131",
    "sg:postcode":"7469",
    "sg:province":"TAS",
    "sg:tags":[
        "boring",
        "contractor"
    ],
    "wof:name":"Almac Drilling Pty Ltd",
    "wof:placetype":"venue"
},
  "geometry": {"coordinates":[145.33467102,-41.8870811462],"type":"Point"}
}