{
  "type": "Feature",
  "properties": {
    "iso:country":"AU",
    "sg:address":"Rear Of 34c Tapleys Hill Rd",
    "sg:city":"Royal Park",
    "sg:classifiers":[
        {
            "category":"Food & Beverages",
            "subcategory":"Liquor & Beverages",
            "type":"Retail Goods"
        }
    ],
    "sg:phone":"+61 8 8240 3537",
    "sg:postcode":"5014",
    "sg:province":"SA",
    "sg:tags":[
        "merchant",
        "spirit",
        "wine"
    ],
    "wof:name":"Vintage Palate Wines",
    "wof:placetype":"venue"
},
  "geometry": {"coordinates":[138.511993408,-34.8699760437],"type":"Point"}
}