{
  "type": "Feature",
  "properties": {
    "addr:full":"Waterloo Corner Rd Salisbury SA 5108",
    "addr:postcode":"5108",
    "addr:street":"Corner Rd",
    "iso:country":"AU",
    "sg:address":"Waterloo Corner Rd",
    "sg:city":"Salisbury",
    "sg:classifiers":[
        {
            "category":"Home & Garden",
            "subcategory":"Carpets & Floor Coverings",
            "type":"Retail Goods"
        }
    ],
    "sg:phone":"+61 8 8258 3291",
    "sg:postcode":"5108",
    "sg:province":"SA",
    "sg:tags":[
        "flooring",
        "parquet"
    ],
    "wof:name":"Floored By Us",
    "wof:placetype":"venue"
},
  "geometry": {"coordinates":[138.62654113799999,-34.7531318665],"type":"Point"}
}