{
  "type": "Feature",
  "properties": {
    "addr:full":"Level 1, 14B Aplin Crt, Cnr Grafton St Cairns QLD 4870",
    "addr:housenumber":"14b",
    "addr:postcode":"4870",
    "addr:street":"Aplin Crt Cnr Grafton St",
    "iso:country":"AU",
    "sg:address":"Level 1, 14B Aplin Crt, Cnr Grafton St",
    "sg:city":"Cairns",
    "sg:classifiers":[
        {
            "category":"Banks & Credit Unions",
            "subcategory":"Financial Services",
            "type":"Services"
        }
    ],
    "sg:phone":"+61 7 4041 2222",
    "sg:postcode":"4870",
    "sg:province":"QLD",
    "sg:tags":[
        "planning"
    ],
    "wof:name":"Jim Callahan",
    "wof:placetype":"venue"
},
  "geometry": {"coordinates":[145.778396606,-16.9271087646],"type":"Point"}
}