{
  "type": "Feature",
  "properties": {
    "iso:country":"AU",
    "sg:address":"21 Sydney St",
    "sg:city":"Mogo",
    "sg:classifiers":[
        {
            "category":"Home & Garden",
            "subcategory":"Furniture",
            "type":"Retail Goods"
        }
    ],
    "sg:phone":"+61 2 4474 4400",
    "sg:postcode":"2536",
    "sg:province":"NSW",
    "sg:tags":[
        "repair",
        "restoration"
    ],
    "wof:name":"Australian Fine Wood Gallery The",
    "wof:placetype":"venue"
},
  "geometry": {"coordinates":[150.14146423299999,-35.7847518921],"type":"Point"}
}