{
  "type": "Feature",
  "properties": {
    "addr:full":"Cnr Green & Cross Sts Brookvale NSW 2100",
    "addr:postcode":"2100",
    "addr:street":"Cnr",
    "iso:country":"AU",
    "sg:address":"Cnr Green & Cross Sts",
    "sg:city":"Brookvale",
    "sg:classifiers":[
        {
            "category":"Autos & Motor Vehicles",
            "subcategory":"Auto Supplies",
            "type":"Retail Goods"
        }
    ],
    "sg:phone":"+61 2 9905 5714",
    "sg:postcode":"2100",
    "sg:province":"NSW",
    "sg:tags":[
        "tyre"
    ],
    "wof:name":"Kmart Tyre & Auto Service",
    "wof:placetype":"venue"
},
  "geometry": {"coordinates":[151.26676940900001,-33.7619018555],"type":"Point"}
}