{
  "type": "Feature",
  "properties": {
    "addr:full":"7 Brentwood Rd Stansbury SA 5582",
    "addr:housenumber":"7",
    "addr:postcode":"5582",
    "addr:street":"Brentwood Rd",
    "iso:country":"AU",
    "sg:address":"7 Brentwood Rd",
    "sg:city":"Stansbury",
    "sg:classifiers":[
        {
            "category":"Utilities",
            "subcategory":"Recycling",
            "type":"Services"
        }
    ],
    "sg:phone":"+61 8 8852 4135",
    "sg:postcode":"5582",
    "sg:province":"SA",
    "wof:name":"Modra M J & R J",
    "wof:placetype":"venue"
},
  "geometry": {"coordinates":[137.784103394,-34.9079933167],"type":"Point"}
}