{
  "type": "Feature",
  "properties": {
    "addr:full":"Francis St Echuca VIC 3564",
    "addr:postcode":"3564",
    "addr:street":"Francis St",
    "iso:country":"AU",
    "sg:address":"Francis St",
    "sg:city":"Echuca",
    "sg:classifiers":[
        {
            "category":"Health Services",
            "subcategory":"Doctor",
            "type":"Services"
        }
    ],
    "sg:phone":"+61 3 5485 5900",
    "sg:postcode":"3564",
    "sg:province":"VIC",
    "sg:tags":[
        "medical",
        "practitioner"
    ],
    "wof:name":"Murray Valley Imaging Echuca-CT-Nuclear Medicine",
    "wof:placetype":"venue"
},
  "geometry": {"coordinates":[144.74763488799999,-36.1323814392],"type":"Point"}
}