{
  "type": "Feature",
  "properties": {
    "addr:full":"15 Peacock Rd Para Hills West SA 5096",
    "addr:housenumber":"15",
    "addr:postcode":"5096",
    "addr:street":"Peacock Rd Para Hills West",
    "iso:country":"AU",
    "sg:address":"15 Peacock Rd",
    "sg:city":"Para Hills West",
    "sg:classifiers":[
        {
            "category":"Autos & Motor Vehicles",
            "subcategory":"Automobile Sales",
            "type":"Retail Goods"
        }
    ],
    "sg:phone":"+61 8 8281 6055",
    "sg:postcode":"5096",
    "sg:province":"SA",
    "sg:tags":[
        "equipment",
        "trailer"
    ],
    "wof:name":"Polite Towing Services",
    "wof:placetype":"venue"
},
  "geometry": {"coordinates":[138.64950561500001,-34.7935142517],"type":"Point"}
}