{
  "type": "Feature",
  "properties": {
    "iso:country":"AU",
    "sg:address":"Unit 5/ 136 Railway St",
    "sg:city":"Cottesloe",
    "sg:classifiers":[
        {
            "category":"Recreation",
            "type":"Entertainment"
        }
    ],
    "sg:phone":"+61 8 9385 3388",
    "sg:postcode":"6011",
    "sg:province":"WA",
    "sg:tags":[
        "club",
        "card"
    ],
    "wof:name":"Rosendorffs Bridge Centre",
    "wof:placetype":"venue"
},
  "geometry": {"coordinates":[115.765052795,-31.9881248474],"type":"Point"}
}