{
  "type": "Feature",
  "properties": {
    "iso:country":"AU",
    "sg:address":"30 Chad St",
    "sg:city":"Brookvale",
    "sg:classifiers":[
        {
            "category":"Personal",
            "subcategory":"Adult",
            "type":"Services"
        }
    ],
    "sg:phone":"+61 2 9907 4343",
    "sg:postcode":"2100",
    "sg:province":"NSW",
    "sg:tags":[
        "vic",
        "except",
        "state",
        "escort",
        "social",
        "qld"
    ],
    "wof:name":"Cecilias House of Fantasy & Pleasure",
    "wof:placetype":"venue"
},
  "geometry": {"coordinates":[151.27430725100001,-33.7631835938],"type":"Point"}
}