{
  "type": "Feature",
  "properties": {
    "addr:full":"4/ 4 Low St Eumundi QLD 4562",
    "addr:housenumber":"/ 4",
    "addr:postcode":"4562",
    "addr:street":"Low St",
    "iso:country":"AU",
    "sg:address":"4/ 4 Low St",
    "sg:city":"Eumundi",
    "sg:classifiers":[
        {
            "category":"Retail",
            "subcategory":"Auto Repair",
            "type":"Services"
        }
    ],
    "sg:phone":"+61 7 5442 7003",
    "sg:postcode":"4562",
    "sg:province":"QLD",
    "sg:tags":[
        "repairer",
        "motor",
        "engineer"
    ],
    "wof:name":"Hyperformance Motorcycles",
    "wof:placetype":"venue"
},
  "geometry": {"coordinates":[152.953216553,-26.4811649323],"type":"Point"}
}