{
  "type": "Feature",
  "properties": {
    "addr:full":"Suite 8/ 5 Rose St Hawthorn East VIC 3123",
    "addr:housenumber":"5",
    "addr:postcode":"3123",
    "addr:street":"Rose St",
    "iso:country":"AU",
    "sg:address":"Suite 8/ 5 Rose St",
    "sg:city":"Hawthorn East",
    "sg:classifiers":[
        {
            "category":"Sports & Exercise",
            "subcategory":"Gym",
            "type":"Entertainment"
        }
    ],
    "sg:phone":"+61 1300 304 068",
    "sg:postcode":"3123",
    "sg:province":"VIC",
    "sg:tags":[
        "personal",
        "trainer",
        "fitness"
    ],
    "wof:name":"Health By Design",
    "wof:placetype":"venue"
},
  "geometry": {"coordinates":[145.05203247099999,-37.8297767639],"type":"Point"}
}