{
  "type": "Feature",
  "properties": {
    "addr:full":"263 Charlestown Rd Charlestown NSW 2290",
    "addr:housenumber":"263",
    "addr:postcode":"2290",
    "addr:street":"Charlestown Rd",
    "iso:country":"AU",
    "sg:address":"263 Charlestown Rd",
    "sg:city":"Charlestown",
    "sg:classifiers":[
        {
            "category":"Food & Beverages",
            "subcategory":"Specialty",
            "type":"Retail Goods"
        }
    ],
    "sg:phone":"+61 2 4920 6650",
    "sg:postcode":"2290",
    "sg:province":"NSW",
    "sg:tags":[
        "product",
        "health"
    ],
    "wof:name":"True Health",
    "wof:placetype":"venue"
},
  "geometry": {"coordinates":[151.68856811500001,-32.9577941895],"type":"Point"}
}