{
  "type": "Feature",
  "properties": {
    "iso:country":"AU",
    "sg:address":"20 Howards Rd",
    "sg:city":"Panton Hill",
    "sg:classifiers":[
        {
            "category":"Farming",
            "subcategory":"Vineyard",
            "type":"Manufacturing & Wholesale Goods"
        }
    ],
    "sg:phone":"+61 3 9719 7687",
    "sg:postcode":"3759",
    "sg:province":"VIC",
    "sg:tags":[
        "winery"
    ],
    "wof:name":"Ridgeback Wines",
    "wof:placetype":"venue"
},
  "geometry": {"coordinates":[145.253906,-37.632988],"type":"Point"}
}