{
  "type": "Feature",
  "properties": {
    "iso:country":"AU",
    "sg:address":"43 St Andrews Drv",
    "sg:city":"Dubbo",
    "sg:classifiers":[
        {
            "category":"Commercial Area",
            "type":"Public Place"
        }
    ],
    "sg:phone":"+61 2 6882 5924",
    "sg:postcode":"2830",
    "sg:province":"NSW",
    "sg:tags":[
        "heavy",
        "carrier"
    ],
    "wof:name":"Dunstan S T",
    "wof:placetype":"venue"
},
  "geometry": {"coordinates":[148.57640075699999,-32.2556724548],"type":"Point"}
}