{
  "type": "Feature",
  "properties": {
    "addr:full":"368 Edward St Wagga Wagga NSW 2650",
    "addr:housenumber":"368",
    "addr:postcode":"2650",
    "addr:street":"Edward St",
    "iso:country":"AU",
    "sg:address":"368 Edward St",
    "sg:city":"Wagga Wagga",
    "sg:classifiers":[
        {
            "category":"Home & Garden",
            "subcategory":"Furniture",
            "type":"Retail Goods"
        }
    ],
    "sg:phone":"+61 2 6925 1186",
    "sg:postcode":"2650",
    "sg:province":"NSW",
    "sg:tags":[
        "outdoor"
    ],
    "wof:name":"Barbeques Galore",
    "wof:placetype":"venue"
},
  "geometry": {"coordinates":[147.34591674800001,-35.1157646179],"type":"Point"}
}