{
  "type": "Feature",
  "properties": {
    "addr:full":"51 Washpool Creek Rd Booral NSW 2425",
    "addr:housenumber":"51",
    "addr:postcode":"2425",
    "addr:street":"Washpool Creek Rd",
    "iso:country":"AU",
    "sg:address":"51 Washpool Creek Rd",
    "sg:city":"Booral",
    "sg:classifiers":[
        {
            "category":"Building & Trades",
            "subcategory":"Construction",
            "type":"Services"
        }
    ],
    "sg:phone":"+61 2 4994 9169",
    "sg:postcode":"2425",
    "sg:province":"NSW",
    "sg:tags":[
        "earth",
        "excavating",
        "moving",
        "contractor"
    ],
    "wof:name":"Trappel Peter Earthmoving Pty Ltd",
    "wof:placetype":"venue"
},
  "geometry": {"coordinates":[151.946807861,-32.4440345764],"type":"Point"}
}