{
  "type": "Feature",
  "properties": {
    "addr:full":"38-39/ 232 Napper Rd Arundel QLD 4214",
    "addr:housenumber":"38-39 / 232",
    "addr:postcode":"4214",
    "addr:street":"Napper Rd",
    "iso:country":"AU",
    "sg:address":"38-39/ 232 Napper Rd",
    "sg:city":"Arundel",
    "sg:classifiers":[
        {
            "category":"Health Services",
            "subcategory":"Health Practitioner",
            "type":"Services"
        }
    ],
    "sg:phone":"+61 417 831 055",
    "sg:postcode":"4214",
    "sg:province":"QLD",
    "sg:tags":[
        "naturopath"
    ],
    "wof:name":"Flanigan Mark",
    "wof:placetype":"venue"
},
  "geometry": {"coordinates":[153.35194397000001,-27.9463691711],"type":"Point"}
}