{
  "type": "Feature",
  "properties": {
    "iso:country":"AU",
    "sg:address":"25 Rivers St",
    "sg:city":"Queanbeyan",
    "sg:classifiers":[
        {
            "category":"Professional",
            "subcategory":"Art Services",
            "type":"Services"
        }
    ],
    "sg:phone":"+61 2 6232 9889",
    "sg:postcode":"2620",
    "sg:province":"ACT",
    "sg:tags":[
        "decorator",
        "painter"
    ],
    "wof:name":"Brighter Painting",
    "wof:placetype":"venue"
},
  "geometry": {"coordinates":[149.228149414,-35.338558197],"type":"Point"}
}