{
  "type": "Feature",
  "properties": {
    "addr:full":"71 Falconer Rd West Ryde NSW 2114",
    "addr:housenumber":"71",
    "addr:postcode":"2114",
    "addr:street":"Falconer Rd",
    "iso:country":"AU",
    "sg:address":"71 Falconer Rd",
    "sg:city":"West Ryde",
    "sg:classifiers":[
        {
            "category":"Utilities",
            "subcategory":"Refuse",
            "type":"Services"
        }
    ],
    "sg:phone":"+61 418 272 215",
    "sg:postcode":"2114",
    "sg:province":"NSW",
    "sg:tags":[
        "remover",
        "rubbish"
    ],
    "wof:name":"Con & Sons",
    "wof:placetype":"venue"
},
  "geometry": {"coordinates":[151.09425354000001,-33.8098068237],"type":"Point"}
}