{
  "type": "Feature",
  "properties": {
    "addr:full":"475 Glenferrie Rd Kooyong VIC 3144",
    "addr:housenumber":"475",
    "addr:postcode":"3144",
    "addr:street":"Glenferrie Rd",
    "iso:country":"AU",
    "sg:address":"475 Glenferrie Rd",
    "sg:city":"Kooyong",
    "sg:classifiers":[
        {
            "category":"Food & Beverages",
            "subcategory":"Specialty",
            "type":"Retail Goods"
        }
    ],
    "sg:phone":"+61 3 9822 2865",
    "sg:postcode":"3144",
    "sg:province":"VIC",
    "sg:tags":[
        "delicacy"
    ],
    "wof:name":"Croutons Fine Food",
    "wof:placetype":"venue"
},
  "geometry": {"coordinates":[145.03199768100001,-37.8402137756],"type":"Point"}
}