{
  "type": "Feature",
  "properties": {
    "addr:full":"Shp3/ 28 Christie St Canungra QLD 4275",
    "addr:housenumber":"28",
    "addr:postcode":"4275",
    "addr:street":"Christie St",
    "iso:country":"AU",
    "sg:address":"Shp3/ 28 Christie St",
    "sg:city":"Canungra",
    "sg:classifiers":[
        {
            "category":"Fast Food",
            "type":"Food & Drink"
        }
    ],
    "sg:phone":"+61 7 5543 4455",
    "sg:postcode":"4275",
    "sg:province":"QLD",
    "sg:tags":[
        "away",
        "take"
    ],
    "wof:name":"Canungra Pizza",
    "wof:placetype":"venue"
},
  "geometry": {"coordinates":[153.16328430199999,-28.0168018341],"type":"Point"}
}