{
  "type": "Feature",
  "properties": {
    "iso:country":"AU",
    "sg:address":"64 Jetty Rd",
    "sg:city":"Glenelg",
    "sg:classifiers":[
        {
            "category":"Ice Cream",
            "type":"Food & Drink"
        }
    ],
    "sg:phone":"+61 8 8376 5199",
    "sg:postcode":"5045",
    "sg:province":"SA",
    "sg:tags":[
        "retail"
    ],
    "wof:name":"Fair Dinkum Aussie Icecream",
    "wof:placetype":"venue"
},
  "geometry": {"coordinates":[138.514511,-34.98045],"type":"Point"}
}