{
  "type": "Feature",
  "properties": {
    "addr:full":"1060 Stud Rd Rowville VIC 3178",
    "addr:housenumber":"1060",
    "addr:postcode":"3178",
    "addr:street":"Stud Rd",
    "iso:country":"AU",
    "sg:address":"1060 Stud Rd",
    "sg:city":"Rowville",
    "sg:classifiers":[
        {
            "category":"Shopping",
            "subcategory":"Bicycles & Sporting Goods",
            "type":"Retail Goods"
        }
    ],
    "sg:phone":"+61 3 9763 9333",
    "sg:postcode":"3178",
    "sg:province":"VIC",
    "sg:tags":[
        "chemical",
        "equipment",
        "pool",
        "swimming"
    ],
    "wof:name":"Kreepy Krauly",
    "wof:placetype":"venue"
},
  "geometry": {"coordinates":[145.23492431599999,-37.9169502258],"type":"Point"}
}