{
  "type": "Feature",
  "properties": {
    "addr:full":"22/ 48-50 George St Parramatta NSW 2150",
    "addr:housenumber":"22 / 48-50",
    "addr:postcode":"2150",
    "addr:street":"George St",
    "iso:country":"AU",
    "sg:address":"22/ 48-50 George St",
    "sg:city":"Parramatta",
    "sg:classifiers":[
        {
            "category":"Shopping",
            "subcategory":"Pawn Shop",
            "type":"Retail Goods"
        }
    ],
    "sg:phone":"+61 2 9633 1447",
    "sg:postcode":"2150",
    "sg:province":"NSW",
    "sg:tags":[
        "pawnbroker"
    ],
    "wof:name":"Smiths Loan Office",
    "wof:placetype":"venue"
},
  "geometry": {"coordinates":[151.018600464,-33.8316001892],"type":"Point"}
}