{
  "type": "Feature",
  "properties": {
    "addr:full":"25 Pack St Jamboree Heights QLD 4074",
    "addr:housenumber":"25",
    "addr:postcode":"4074",
    "addr:street":"Pack St",
    "iso:country":"AU",
    "sg:address":"25 Pack St",
    "sg:city":"Jamboree Heights",
    "sg:classifiers":[
        {
            "category":"Professional",
            "subcategory":"Computer Services",
            "type":"Services"
        }
    ],
    "sg:phone":"+61 7 3715 7955",
    "sg:postcode":"4074",
    "sg:province":"QLD",
    "sg:tags":[
        "package",
        "software"
    ],
    "wof:name":"AccountingPower",
    "wof:placetype":"venue"
},
  "geometry": {"coordinates":[152.93167114299999,-27.5600032806],"type":"Point"}
}