{
  "type": "Feature",
  "properties": {
    "iso:country":"AU",
    "sg:address":"1194 Centre Rd",
    "sg:city":"Clarinda",
    "sg:classifiers":[
        {
            "category":"Health Services",
            "subcategory":"Health Practitioner",
            "type":"Services"
        }
    ],
    "sg:phone":"+61 3 9543 4433",
    "sg:postcode":"3169",
    "sg:province":"VIC",
    "sg:tags":[
        "naturopath"
    ],
    "wof:name":"Laura Wormington",
    "wof:placetype":"venue"
},
  "geometry": {"coordinates":[145.10534668,-37.9269523621],"type":"Point"}
}