{
  "type": "Feature",
  "properties": {
    "addr:full":"33a Illawarra Rd Balwyn North VIC 3104",
    "addr:housenumber":"33a",
    "addr:postcode":"3104",
    "addr:street":"Illawarra Rd",
    "iso:country":"AU",
    "sg:address":"33a Illawarra Rd",
    "sg:city":"Balwyn North",
    "sg:classifiers":[
        {
            "category":"Professional",
            "subcategory":"Accounting & Tax Preparation",
            "type":"Services"
        }
    ],
    "sg:phone":"+61 3 9859 3397",
    "sg:postcode":"3104",
    "sg:province":"VIC",
    "sg:tags":[
        "accountant",
        "auditor"
    ],
    "wof:name":"Waters M.W.",
    "wof:placetype":"venue"
},
  "geometry": {"coordinates":[145.08366394000001,-37.7983627319],"type":"Point"}
}