{
  "type": "Feature",
  "properties": {
    "addr:full":"Lines Rd Wasleys SA 5400",
    "addr:postcode":"5400",
    "addr:street":"Lines Rd",
    "iso:country":"AU",
    "sg:address":"Lines Rd",
    "sg:city":"Wasleys",
    "sg:classifiers":[
        {
            "category":"Farming",
            "subcategory":"Farm",
            "type":"Manufacturing & Wholesale Goods"
        }
    ],
    "sg:phone":"+61 8 8525 4081",
    "sg:postcode":"5400",
    "sg:province":"SA",
    "sg:tags":[
        "farmer"
    ],
    "wof:name":"Lines B R & M M",
    "wof:placetype":"venue"
},
  "geometry": {"coordinates":[138.67497253400001,-34.4713287354],"type":"Point"}
}