{
  "type": "Feature",
  "properties": {
    "addr:full":"403 Mulga Drv East Mandurah WA 6210",
    "addr:housenumber":"403",
    "addr:postcode":"6210",
    "addr:street":"Mulga Drv East",
    "iso:country":"AU",
    "sg:address":"403 Mulga Drv East",
    "sg:city":"Mandurah",
    "sg:classifiers":[
        {
            "category":"Building & Trades",
            "subcategory":"Landscaping Services",
            "type":"Services"
        }
    ],
    "sg:phone":"+61 8 9581 6956",
    "sg:postcode":"6210",
    "sg:province":"WA",
    "sg:tags":[
        "stump",
        "tree",
        "felling",
        "removal"
    ],
    "wof:name":"Hamilton's Treelopping & Cherry Picker Hire",
    "wof:placetype":"venue"
},
  "geometry": {"coordinates":[115.768463,-32.495449],"type":"Point"}
}