{
  "type": "Feature",
  "properties": {
    "iso:country":"AU",
    "sg:address":"Walhuben Rd",
    "sg:city":"Kentville",
    "sg:classifiers":[
        {
            "category":"Farming",
            "subcategory":"Farm",
            "type":"Manufacturing & Wholesale Goods"
        }
    ],
    "sg:phone":"+61 7 5465 8230",
    "sg:postcode":"4341",
    "sg:province":"QLD",
    "sg:tags":[
        "farmer"
    ],
    "wof:name":"Lyons W K & A",
    "wof:placetype":"venue"
},
  "geometry": {"coordinates":[152.41612243599999,-27.5110416412],"type":"Point"}
}