{
  "type": "Feature",
  "properties": {
    "iso:country":"AU",
    "sg:address":"78 Aberdeen St",
    "sg:city":"Albany",
    "sg:classifiers":[
        {
            "category":"Health Services",
            "subcategory":"Dentist",
            "type":"Services"
        }
    ],
    "sg:phone":"+61 8 9841 4355",
    "sg:postcode":"6330",
    "sg:province":"WA",
    "wof:name":"Barry J. Geldard & Associates",
    "wof:placetype":"venue"
},
  "geometry": {"coordinates":[117.885261536,-35.0225868225],"type":"Point"}
}