{
  "type": "Feature",
  "properties": {
    "addr:full":"Olympic Hwy Cowra NSW 2794",
    "addr:postcode":"2794",
    "addr:street":"Olympic Hwy",
    "iso:country":"AU",
    "sg:address":"Olympic Hwy",
    "sg:city":"Cowra",
    "sg:classifiers":[
        {
            "category":"Autos & Motor Vehicles",
            "subcategory":"Auto Supplies",
            "type":"Retail Goods"
        }
    ],
    "sg:phone":"+61 2 6342 5350",
    "sg:postcode":"2794",
    "sg:province":"NSW",
    "sg:tags":[
        "part",
        "cycles",
        "accessory"
    ],
    "wof:name":"Phil Tomlin Speedway Spares",
    "wof:placetype":"venue"
},
  "geometry": {"coordinates":[148.67950439399999,-33.8351745605],"type":"Point"}
}