{
  "type": "Feature",
  "properties": {
    "addr:full":"63 Pelham St Carlton VIC 3053",
    "addr:housenumber":"63",
    "addr:postcode":"3053",
    "addr:street":"Pelham St",
    "iso:country":"AU",
    "sg:address":"63 Pelham St",
    "sg:city":"Carlton",
    "sg:classifiers":[
        {
            "category":"Shopping",
            "subcategory":"Optical Goods",
            "type":"Retail Goods"
        }
    ],
    "sg:phone":"+61 3 9663 6242",
    "sg:postcode":"3053",
    "sg:province":"VIC",
    "sg:tags":[
        "supply"
    ],
    "wof:name":"Pergl L & G",
    "wof:placetype":"venue"
},
  "geometry": {"coordinates":[144.96697998100001,-37.8029747009],"type":"Point"}
}