{
  "type": "Feature",
  "properties": {
    "addr:full":"93 Main South Rd O'Halloran Hill SA 5158",
    "addr:housenumber":"93",
    "addr:postcode":"5158",
    "addr:street":"Main South Rd O'Halloran",
    "iso:country":"AU",
    "sg:address":"93 Main South Rd",
    "sg:city":"O'Halloran Hill",
    "sg:classifiers":[
        {
            "category":"Personal",
            "subcategory":"Beauty Salon",
            "type":"Services"
        }
    ],
    "sg:phone":"+61 8 8381 1964",
    "sg:postcode":"5158",
    "sg:province":"SA",
    "sg:tags":[
        "hairdresser"
    ],
    "wof:name":"Hair On The Hill",
    "wof:placetype":"venue"
},
  "geometry": {"coordinates":[138.55538940400001,-35.066947937],"type":"Point"}
}