{
  "type": "Feature",
  "properties": {
    "addr:full":"11 Skinner St South Grafton NSW 2460",
    "addr:housenumber":"11",
    "addr:postcode":"2460",
    "addr:street":"Skinner St",
    "iso:country":"AU",
    "sg:address":"11 Skinner St",
    "sg:city":"South Grafton",
    "sg:classifiers":[
        {
            "category":"Shopping",
            "subcategory":"Baby Store",
            "type":"Retail Goods"
        }
    ],
    "sg:phone":"+61 2 6642 8811",
    "sg:postcode":"2460",
    "sg:province":"NSW",
    "sg:tags":[
        "children's",
        "wear"
    ],
    "wof:name":"Bubs & Brats",
    "wof:placetype":"venue"
},
  "geometry": {"coordinates":[152.935470581,-29.7016582489],"type":"Point"}
}