{
  "type": "Feature",
  "properties": {
    "addr:full":"41 Harris St Hackett ACT 2602",
    "addr:housenumber":"41",
    "addr:postcode":"2602",
    "addr:street":"Harris St",
    "iso:country":"AU",
    "sg:address":"41 Harris St",
    "sg:city":"Hackett",
    "sg:classifiers":[
        {
            "category":"Building & Trades",
            "subcategory":"Plumbing",
            "type":"Services"
        }
    ],
    "sg:phone":"+61 412 020 059",
    "sg:postcode":"2602",
    "sg:province":"ACT",
    "sg:tags":[
        "plumber",
        "gasfitters"
    ],
    "wof:name":"G G Plumbing",
    "wof:placetype":"venue"
},
  "geometry": {"coordinates":[149.16476440400001,-35.2426681519],"type":"Point"}
}