{
  "type": "Feature",
  "properties": {
    "iso:country":"AU",
    "sg:address":"46 Mayfair St",
    "sg:city":"Mt Claremont",
    "sg:classifiers":[
        {
            "category":"Education",
            "subcategory":"University",
            "type":"Public Place"
        }
    ],
    "sg:phone":"+61 8 9384 4189",
    "sg:postcode":"6010",
    "sg:province":"WA",
    "sg:tags":[
        "educational",
        "organisation",
        "cultural"
    ],
    "wof:name":"German Cultural Club",
    "wof:placetype":"venue"
},
  "geometry": {"coordinates":[115.772789002,-31.9677791595],"type":"Point"}
}