{
  "type": "Feature",
  "properties": {
    "iso:country":"AU",
    "sg:address":"9 Cranstons Rd",
    "sg:city":"Dural",
    "sg:classifiers":[
        {
            "category":"Travel",
            "subcategory":"Travel Agent",
            "type":"Entertainment"
        }
    ],
    "sg:phone":"+61 2 9651 5116",
    "sg:postcode":"2158",
    "sg:province":"NSW",
    "sg:tags":[
        "consultant"
    ],
    "wof:name":"Lois Gubbay Travel",
    "wof:placetype":"venue"
},
  "geometry": {"coordinates":[151.015426636,-33.6498184204],"type":"Point"}
}