{
  "type": "Feature",
  "properties": {
    "iso:country":"AU",
    "sg:address":"14 Commercial St",
    "sg:city":"Burra",
    "sg:classifiers":[
        {
            "category":"Health Services",
            "subcategory":"Doctor",
            "type":"Services"
        }
    ],
    "sg:phone":"+61 8 8892 2104",
    "sg:postcode":"5417",
    "sg:province":"SA",
    "sg:tags":[
        "medical",
        "practitioner"
    ],
    "wof:name":"Simpson T J Dr",
    "wof:placetype":"venue"
},
  "geometry": {"coordinates":[138.93821716299999,-33.6824111938],"type":"Point"}
}