{
  "type": "Feature",
  "properties": {
    "iso:country":"AU",
    "sg:address":"Grnd Flr 23 Coventry St",
    "sg:city":"Southbank",
    "sg:classifiers":[
        {
            "category":"Banks & Credit Unions",
            "subcategory":"Investment Brokerage",
            "type":"Services"
        }
    ],
    "sg:phone":"+61 3 9682 6222",
    "sg:postcode":"3006",
    "sg:province":"VIC",
    "wof:name":"Southbank Property",
    "wof:placetype":"venue"
},
  "geometry": {"coordinates":[144.97023010300001,-37.8290672302],"type":"Point"}
}