{
  "type": "Feature",
  "properties": {
    "addr:full":"50 Church Rd Bellarine VIC 3221",
    "addr:housenumber":"50",
    "addr:postcode":"3221",
    "addr:street":"Church Rd",
    "iso:country":"AU",
    "sg:address":"50 Church Rd",
    "sg:city":"Bellarine",
    "sg:classifiers":[
        {
            "category":"Retail",
            "subcategory":"Event Space",
            "type":"Services"
        }
    ],
    "sg:phone":"+61 3 5259 1660",
    "sg:postcode":"3221",
    "sg:province":"VIC",
    "sg:tags":[
        "venue",
        "reception",
        "wedding"
    ],
    "wof:name":"Confessions Cafe Group (Pty Ltd)",
    "wof:placetype":"venue"
},
  "geometry": {"coordinates":[144.622894,-38.134815],"type":"Point"}
}