{
  "type": "Feature",
  "properties": {
    "iso:country":"AU",
    "sg:address":"Suite 2, Level B 42 Upper Heidelberg Rd",
    "sg:city":"Ivanhoe",
    "sg:classifiers":[
        {
            "category":"Health Services",
            "subcategory":"Health Practitioner",
            "type":"Services"
        }
    ],
    "sg:phone":"+61 3 9499 9644",
    "sg:postcode":"3079",
    "sg:province":"VIC",
    "sg:tags":[
        "osteopath"
    ],
    "wof:name":"Relinque Osteopathic Health Centre",
    "wof:placetype":"venue"
},
  "geometry": {"coordinates":[145.04090881400001,-37.7712516785],"type":"Point"}
}