{
  "type": "Feature",
  "properties": {
    "addr:full":"53 Main St Atherton QLD 4883",
    "addr:housenumber":"53",
    "addr:postcode":"4883",
    "addr:street":"Main St",
    "iso:country":"AU",
    "sg:address":"53 Main St",
    "sg:city":"Atherton",
    "sg:classifiers":[
        {
            "category":"Retail",
            "subcategory":"Event Space",
            "type":"Services"
        }
    ],
    "sg:phone":"+61 7 4091 1222",
    "sg:postcode":"4883",
    "sg:province":"QLD",
    "sg:tags":[
        "function",
        "organiser"
    ],
    "wof:name":"Barron Valley Hotel",
    "wof:placetype":"venue"
},
  "geometry": {"coordinates":[145.47598266599999,-17.2653694153],"type":"Point"}
}