{
  "type": "Feature",
  "properties": {
    "addr:full":"9 Namoi Pl Sylvania Waters NSW 2224",
    "addr:housenumber":"9",
    "addr:postcode":"2224",
    "addr:street":"Namoi Pl",
    "iso:country":"AU",
    "sg:address":"9 Namoi Pl",
    "sg:city":"Sylvania Waters",
    "sg:classifiers":[
        {
            "category":"Building & Trades",
            "subcategory":"Construction",
            "type":"Services"
        }
    ],
    "sg:phone":"+61 2 9522 5976",
    "sg:postcode":"2224",
    "sg:province":"NSW",
    "sg:tags":[
        "plasterboard",
        "plasterer",
        "fixer"
    ],
    "wof:name":"Bradley G R",
    "wof:placetype":"venue"
},
  "geometry": {"coordinates":[151.11154174800001,-34.0132598877],"type":"Point"}
}