{
  "type": "Feature",
  "properties": {
    "iso:country":"AU",
    "sg:address":"Apt 1401/ 5 Albert Rd",
    "sg:city":"Strathfield",
    "sg:classifiers":[
        {
            "category":"Professional",
            "subcategory":"Computer Services",
            "type":"Services"
        }
    ],
    "sg:phone":"+61 2 9763 2677",
    "sg:postcode":"2135",
    "sg:province":"NSW",
    "sg:tags":[
        "consultant",
        "system"
    ],
    "wof:name":"Ewave Australia Pty Ltd",
    "wof:placetype":"venue"
},
  "geometry": {"coordinates":[151.09361267099999,-33.8716087341],"type":"Point"}
}