{
  "type": "Feature",
  "properties": {
    "addr:full":"(Rear of 100 Woodlark) Lismore NSW 2480",
    "addr:housenumber":"rear;100",
    "addr:postcode":"2480",
    "addr:street":"Woodlark",
    "iso:country":"AU",
    "sg:address":"(Rear of 100",
    "sg:city":"Woodlark) Lismore",
    "sg:classifiers":[
        {
            "category":"Social Services",
            "subcategory":"Retirement Home",
            "type":"Services"
        }
    ],
    "sg:phone":"+61 2 6621 9999",
    "sg:postcode":"2480",
    "sg:province":"NSW",
    "sg:tags":[
        "environmental",
        "consultant",
        "pollution"
    ],
    "wof:name":"Carbon Pool Pty Ltd The",
    "wof:placetype":"venue"
},
  "geometry": {"coordinates":[153.27818298299999,-28.8139896393],"type":"Point"}
}