{
  "type": "Feature",
  "properties": {
    "iso:country":"AU",
    "sg:address":"179 Cornelia Rd",
    "sg:city":"Toongabbie",
    "sg:classifiers":[
        {
            "category":"Professional",
            "subcategory":"Testing Lab",
            "type":"Services"
        }
    ],
    "sg:phone":"+61 2 9636 9429",
    "sg:postcode":"2146",
    "sg:province":"NSW",
    "sg:tags":[
        "inspection"
    ],
    "wof:name":"M & M Inspections Pty Ltd",
    "wof:placetype":"venue"
},
  "geometry": {"coordinates":[150.932739258,-33.7939376831],"type":"Point"}
}