{
  "type": "Feature",
  "properties": {
    "addr:full":"119 Errol St North Melbourne VIC 3051",
    "addr:housenumber":"119",
    "addr:postcode":"3051",
    "addr:street":"Errol St",
    "iso:country":"AU",
    "sg:address":"119 Errol St",
    "sg:city":"North Melbourne",
    "sg:classifiers":[
        {
            "category":"Taxi",
            "type":"Transportation"
        }
    ],
    "sg:phone":"+61 3 9348 9507",
    "sg:postcode":"3051",
    "sg:province":"VIC",
    "sg:tags":[
        "cab"
    ],
    "wof:name":"Alex Taxi Broker Pty Ltd",
    "wof:placetype":"venue"
},
  "geometry": {"coordinates":[144.949615478,-37.8021507263],"type":"Point"}
}