{
  "type": "Feature",
  "properties": {
    "addr:full":"124 Newbridge Rd Moorebank NSW 2170",
    "addr:housenumber":"124",
    "addr:postcode":"2170",
    "addr:street":"Newbridge Rd",
    "iso:country":"AU",
    "sg:address":"124 Newbridge Rd",
    "sg:city":"Moorebank",
    "sg:classifiers":[
        {
            "category":"Home & Garden",
            "subcategory":"Building Materials",
            "type":"Retail Goods"
        }
    ],
    "sg:phone":"+61 1300 134 035",
    "sg:postcode":"2170",
    "sg:province":"NSW",
    "sg:tags":[
        "lawn",
        "cutting",
        "maintenance"
    ],
    "wof:name":"Flower Power Professional Garden Care",
    "wof:placetype":"venue"
},
  "geometry": {"coordinates":[150.94003295900001,-33.9296646118],"type":"Point"}
}