{
  "type": "Feature",
  "properties": {
    "iso:country":"AU",
    "sg:address":"125 Graham Vale Rd",
    "sg:city":"Shepparton",
    "sg:classifiers":[
        {
            "category":"Farming",
            "subcategory":"Orchard",
            "type":"Manufacturing & Wholesale Goods"
        }
    ],
    "sg:phone":"+61 3 5831 1873",
    "sg:postcode":"3630",
    "sg:province":"VIC",
    "sg:tags":[
        "pear",
        "apple",
        "grower"
    ],
    "wof:name":"Pemira Produce Pty Ltd",
    "wof:placetype":"venue"
},
  "geometry": {"coordinates":[145.41520690900001,-36.3625907898],"type":"Point"}
}