{
  "type": "Feature",
  "properties": {
    "addr:full":"94 Wheatsheaf Rd Glenroy VIC 3046",
    "addr:housenumber":"94",
    "addr:postcode":"3046",
    "addr:street":"Wheatsheaf Rd",
    "iso:country":"AU",
    "sg:address":"94 Wheatsheaf Rd",
    "sg:city":"Glenroy",
    "sg:classifiers":[
        {
            "category":"Food & Beverages",
            "subcategory":"Fruits & Vegetables",
            "type":"Retail Goods"
        }
    ],
    "sg:phone":"+61 3 9300 1999",
    "sg:postcode":"3046",
    "sg:province":"VIC",
    "sg:tags":[
        "consultant",
        "catering"
    ],
    "wof:name":"Alkhyber Cafe & Catering",
    "wof:placetype":"venue"
},
  "geometry": {"coordinates":[144.91923523,-37.706199646],"type":"Point"}
}