{
  "type": "Feature",
  "properties": {
    "iso:country":"AU",
    "sg:address":"52 Toogong St",
    "sg:city":"Cudal",
    "sg:classifiers":[
        {
            "category":"Building & Trades",
            "subcategory":"Pest Control",
            "type":"Services"
        }
    ],
    "sg:phone":"+61 2 6364 3132",
    "sg:postcode":"2864",
    "sg:province":"NSW",
    "wof:name":"Pete's Pest Control",
    "wof:placetype":"venue"
},
  "geometry": {"coordinates":[148.746994,-33.284824],"type":"Point"}
}