{
  "type": "Feature",
  "properties": {
    "addr:full":"215 Bay St Brighton VIC 3186",
    "addr:housenumber":"215",
    "addr:postcode":"3186",
    "addr:street":"Bay St",
    "iso:country":"AU",
    "sg:address":"215 Bay St",
    "sg:city":"Brighton",
    "sg:classifiers":[
        {
            "category":"Banks & Credit Unions",
            "subcategory":"Financial Services",
            "type":"Services"
        }
    ],
    "sg:phone":"+61 3 9530 6599",
    "sg:postcode":"3186",
    "sg:province":"VIC",
    "sg:tags":[
        "planning"
    ],
    "wof:name":"Invest 2 Prosper Financial Services Pty Ltd",
    "wof:placetype":"venue"
},
  "geometry": {"coordinates":[144.999176025,-37.9049186707],"type":"Point"}
}