{
  "type": "Feature",
  "properties": {
    "addr:full":"Mais Rd Nairne SA 5252",
    "addr:postcode":"5252",
    "addr:street":"Mais Rd",
    "iso:country":"AU",
    "sg:address":"Mais Rd",
    "sg:city":"Nairne",
    "sg:classifiers":[
        {
            "category":"Retail",
            "subcategory":"Repair Shop",
            "type":"Services"
        }
    ],
    "sg:phone":"+61 8 8388 0969",
    "sg:postcode":"5252",
    "sg:province":"SA",
    "sg:tags":[
        "leadlights"
    ],
    "wof:name":"Sierp Robin E",
    "wof:placetype":"venue"
},
  "geometry": {"coordinates":[138.897994995,-35.0297470093],"type":"Point"}
}