{
  "type": "Feature",
  "properties": {
    "addr:full":"16 Cambridge Drv Glen Waverley VIC 3150",
    "addr:housenumber":"16",
    "addr:postcode":"3150",
    "addr:street":"Cambridge Drv",
    "iso:country":"AU",
    "sg:address":"16 Cambridge Drv",
    "sg:city":"Glen Waverley",
    "sg:classifiers":[
        {
            "category":"Insurance",
            "subcategory":"Hazard Insurance",
            "type":"Services"
        }
    ],
    "sg:phone":"+61 3 9886 4472",
    "sg:postcode":"3150",
    "sg:province":"VIC",
    "sg:tags":[
        "loss",
        "adjuster",
        "assessor"
    ],
    "wof:name":"Burns Richard & Associates",
    "wof:placetype":"venue"
},
  "geometry": {"coordinates":[145.14698791500001,-37.8912582397],"type":"Point"}
}