{
  "type": "Feature",
  "properties": {
    "addr:full":"257 Main Rd Blackwood SA 5051",
    "addr:housenumber":"257",
    "addr:postcode":"5051",
    "addr:street":"Main Rd",
    "iso:country":"AU",
    "sg:address":"257 Main Rd",
    "sg:city":"Blackwood",
    "sg:classifiers":[
        {
            "category":"Real Estate",
            "subcategory":"Real Estate Agent",
            "type":"Services"
        }
    ],
    "sg:phone":"+61 8 8278 3322",
    "sg:postcode":"5051",
    "sg:province":"SA",
    "wof:name":"Ray White South Australia",
    "wof:placetype":"venue"
},
  "geometry": {"coordinates":[138.61827099999999,-35.021526],"type":"Point"}
}