{
  "type": "Feature",
  "properties": {
    "iso:country":"AU",
    "sg:address":"20 Wongaling Beach Rd",
    "sg:city":"Mission Beach",
    "sg:classifiers":[
        {
            "category":"Recreation",
            "type":"Entertainment"
        }
    ],
    "sg:phone":"+61 7 4068 8432",
    "sg:postcode":"4852",
    "sg:province":"QLD",
    "sg:tags":[
        "recreational",
        "diver"
    ],
    "wof:name":"Calypso Dive",
    "wof:placetype":"venue"
},
  "geometry": {"coordinates":[146.09184265100001,-17.8974170685],"type":"Point"}
}