{
  "type": "Feature",
  "properties": {
    "addr:full":"33 Alfred St Circular Quay NSW 2000",
    "addr:housenumber":"33",
    "addr:postcode":"2000",
    "addr:street":"Alfred St Circular Quay",
    "iso:country":"AU",
    "sg:address":"33 Alfred St",
    "sg:city":"Circular Quay",
    "sg:classifiers":[
        {
            "category":"Personal",
            "subcategory":"Massage",
            "type":"Services"
        }
    ],
    "sg:phone":"+61 414 962 971",
    "sg:postcode":"2000",
    "sg:province":"NSW",
    "sg:tags":[
        "therapy"
    ],
    "wof:name":"Body Moves Massage Therapy",
    "wof:placetype":"venue"
},
  "geometry": {"coordinates":[151.211013794,-33.8617897034],"type":"Point"}
}