{
  "type": "Feature",
  "properties": {
    "addr:full":"3 Livingstone Ave Pymble NSW 2073",
    "addr:housenumber":"3",
    "addr:postcode":"2073",
    "addr:street":"Livingstone Ave",
    "iso:country":"AU",
    "sg:address":"3 Livingstone Ave",
    "sg:city":"Pymble",
    "sg:classifiers":[
        {
            "category":"Health Services",
            "subcategory":"Dentist",
            "type":"Services"
        }
    ],
    "sg:phone":"+61 2 9488 7676",
    "sg:postcode":"2073",
    "sg:province":"NSW",
    "wof:name":"Keats,: Mathew",
    "wof:placetype":"venue"
},
  "geometry": {"coordinates":[151.142456055,-33.7461967468],"type":"Point"}
}