{
  "type": "Feature",
  "properties": {
    "addr:full":"317 Bay St Brighton VIC 3186",
    "addr:housenumber":"317",
    "addr:postcode":"3186",
    "addr:street":"Bay St",
    "iso:country":"AU",
    "sg:address":"317 Bay St",
    "sg:city":"Brighton",
    "sg:classifiers":[
        {
            "category":"Restaurant",
            "type":"Food & Drink"
        }
    ],
    "sg:phone":"+61 3 9596 9511",
    "sg:postcode":"3186",
    "sg:province":"VIC",
    "sg:website":"http://www.vivace.com.au",
    "wof:name":"Vivace Ristorante",
    "wof:placetype":"venue"
},
  "geometry": {"coordinates":[145.00292968799999,-37.9054412842],"type":"Point"}
}