{
  "type": "Feature",
  "properties": {
    "addr:full":"1295 Toorak Rd Camberwell VIC 3124",
    "addr:housenumber":"1295",
    "addr:postcode":"3124",
    "addr:street":"Toorak Rd",
    "iso:country":"AU",
    "sg:address":"1295 Toorak Rd",
    "sg:city":"Camberwell",
    "sg:classifiers":[
        {
            "category":"Health Services",
            "subcategory":"Health Practitioner",
            "type":"Services"
        }
    ],
    "sg:phone":"+61 3 9889 3151",
    "sg:postcode":"3124",
    "sg:province":"VIC",
    "sg:tags":[
        "physiotherapist"
    ],
    "wof:name":"Sizer M.H.",
    "wof:placetype":"venue"
},
  "geometry": {"coordinates":[145.087722778,-37.8493537903],"type":"Point"}
}