{
  "type": "Feature",
  "properties": {
    "addr:full":"131 Oxley Station Rd Oxley QLD 4075",
    "addr:housenumber":"131",
    "addr:postcode":"4075",
    "addr:street":"Oxley Station Rd",
    "iso:country":"AU",
    "sg:address":"131 Oxley Station Rd",
    "sg:city":"Oxley",
    "sg:classifiers":[
        {
            "category":"Government",
            "subcategory":"Post Office",
            "type":"Public Place"
        }
    ],
    "sg:phone":"+61 7 3379 1535",
    "sg:postcode":"4075",
    "sg:province":"QLD",
    "sg:tags":[
        "postal"
    ],
    "wof:name":"Oxley Post Office",
    "wof:placetype":"venue"
},
  "geometry": {"coordinates":[152.97479248100001,-27.5538845062],"type":"Point"}
}