{
  "type": "Feature",
  "properties": {
    "iso:country":"AU",
    "sg:address":"7/ 11 Fletcher St",
    "sg:city":"Byron Bay",
    "sg:classifiers":[
        {
            "category":"Personal",
            "subcategory":"Tattoo Parlor",
            "type":"Services"
        }
    ],
    "sg:phone":"+61 2 6685 5799",
    "sg:postcode":"2481",
    "sg:province":"NSW",
    "sg:tags":[
        "tattooing"
    ],
    "wof:name":"Creative Tattoo Art",
    "wof:placetype":"venue"
},
  "geometry": {"coordinates":[153.61378479000001,-28.6435699463],"type":"Point"}
}