{
  "type": "Feature",
  "properties": {
    "addr:full":"PO Box 3111 Prahran East VIC 3181",
    "addr:postcode":"3181",
    "iso:country":"AU",
    "sg:address":"PO Box 3111",
    "sg:city":"Prahran East",
    "sg:classifiers":[
        {
            "category":"Real Estate",
            "subcategory":"Real Estate Agent",
            "type":"Services"
        }
    ],
    "sg:phone":"+61 3 9510 3334",
    "sg:postcode":"3181",
    "sg:province":"VIC",
    "wof:name":"Melbourne Planners",
    "wof:placetype":"venue"
},
  "geometry": {"coordinates":[144.99708557100001,-37.8529281616],"type":"Point"}
}