{
  "type": "Feature",
  "properties": {
    "addr:full":"16 Shelley Rd Moruya NSW 2537",
    "addr:housenumber":"16",
    "addr:postcode":"2537",
    "addr:street":"Shelley Rd",
    "iso:country":"AU",
    "sg:address":"16 Shelley Rd",
    "sg:city":"Moruya",
    "sg:classifiers":[
        {
            "category":"Wholesale",
            "subcategory":"Metals & Minerals",
            "type":"Manufacturing & Wholesale Goods"
        }
    ],
    "sg:phone":"+61 2 4474 0499",
    "sg:postcode":"2537",
    "sg:province":"NSW",
    "sg:tags":[
        "steel",
        "merchant"
    ],
    "wof:name":"Black Swan Steel Pty. Ltd.",
    "wof:placetype":"venue"
},
  "geometry": {"coordinates":[150.08691406200001,-35.8775024414],"type":"Point"}
}