{
  "type": "Feature",
  "properties": {
    "addr:full":"Up Daradgee Rd Daradgee QLD 4860",
    "addr:postcode":"4860",
    "addr:street":"Daradgee Rd",
    "iso:country":"AU",
    "sg:address":"Up Daradgee Rd",
    "sg:city":"Daradgee",
    "sg:classifiers":[
        {
            "category":"Farming",
            "subcategory":"Farm",
            "type":"Manufacturing & Wholesale Goods"
        }
    ],
    "sg:phone":"+61 7 4063 3823",
    "sg:postcode":"4860",
    "sg:province":"QLD",
    "sg:tags":[
        "farmer"
    ],
    "wof:name":"Rossi P & A",
    "wof:placetype":"venue"
},
  "geometry": {"coordinates":[146.00457763700001,-17.4827022552],"type":"Point"}
}