{
  "type": "Feature",
  "properties": {
    "addr:full":"3/ 74 Haig St Maroubra NSW 2035",
    "addr:housenumber":"/ 74",
    "addr:postcode":"2035",
    "addr:street":"Haig St",
    "iso:country":"AU",
    "sg:address":"3/ 74 Haig St",
    "sg:city":"Maroubra",
    "sg:classifiers":[
        {
            "category":"Transit Center",
            "subcategory":"Passenger",
            "type":"Transportation"
        }
    ],
    "sg:phone":"+61 2 9314 0984",
    "sg:postcode":"2035",
    "sg:province":"NSW",
    "sg:tags":[
        "frozen",
        "food",
        "retail"
    ],
    "wof:name":"Hisense Air Conditioning",
    "wof:placetype":"venue"
},
  "geometry": {"coordinates":[151.246383667,-33.9434738159],"type":"Point"}
}