{
  "type": "Feature",
  "properties": {
    "addr:full":"23 Market St Goulburn NSW 2580",
    "addr:housenumber":"23",
    "addr:postcode":"2580",
    "addr:street":"Market St",
    "iso:country":"AU",
    "sg:address":"23 Market St",
    "sg:city":"Goulburn",
    "sg:classifiers":[
        {
            "category":"Retail",
            "subcategory":"Event Space",
            "type":"Services"
        }
    ],
    "sg:phone":"+61 2 4821 2727",
    "sg:postcode":"2580",
    "sg:province":"NSW",
    "sg:tags":[
        "venue",
        "reception",
        "wedding"
    ],
    "wof:name":"Fireside Inn The",
    "wof:placetype":"venue"
},
  "geometry": {"coordinates":[149.720245361,-34.7543449402],"type":"Point"}
}