{
  "type": "Feature",
  "properties": {
    "addr:full":"116 Maitland St Narrabri NSW 2390",
    "addr:housenumber":"116",
    "addr:postcode":"2390",
    "addr:street":"Maitland St",
    "iso:country":"AU",
    "sg:address":"116 Maitland St",
    "sg:city":"Narrabri",
    "sg:classifiers":[
        {
            "category":"Shopping",
            "subcategory":"Jewelry",
            "type":"Retail Goods"
        }
    ],
    "sg:phone":"+61 2 6792 2002",
    "sg:postcode":"2390",
    "sg:province":"NSW",
    "sg:tags":[
        "jeweller"
    ],
    "wof:name":"Barnes Jewellers",
    "wof:placetype":"venue"
},
  "geometry": {"coordinates":[149.783599853,-30.3258037567],"type":"Point"}
}