{
  "type": "Feature",
  "properties": {
    "iso:country":"AU",
    "sg:address":"2/ 12 Ascari La",
    "sg:city":"Joondalup",
    "sg:classifiers":[
        {
            "category":"Retail",
            "subcategory":"Auto Repair",
            "type":"Services"
        }
    ],
    "sg:phone":"+61 8 9405 4914",
    "sg:postcode":"6027",
    "sg:province":"WA",
    "sg:tags":[
        "repairer",
        "motor",
        "engineer"
    ],
    "wof:name":"Tony's Car & Motor Bike School",
    "wof:placetype":"venue"
},
  "geometry": {"coordinates":[115.76348114,-31.7459869385],"type":"Point"}
}