{
  "type": "Feature",
  "properties": {
    "iso:country":"AU",
    "sg:address":"Mail Svc 108",
    "sg:city":"Port Bundaberg",
    "sg:classifiers":[
        {
            "category":"Government",
            "subcategory":"Department Of Motor Vehicles",
            "type":"Public Place"
        }
    ],
    "sg:phone":"+61 7 4159 4233",
    "sg:postcode":"4670",
    "sg:province":"QLD",
    "sg:tags":[
        "organisation",
        "local"
    ],
    "wof:name":"Bundaberg Port Authority",
    "wof:placetype":"venue"
},
  "geometry": {"coordinates":[152.38803100600001,-24.7761497498],"type":"Point"}
}