{
  "type": "Feature",
  "properties": {
    "addr:full":"20 Montague Rd Cremorne NSW 2090",
    "addr:housenumber":"20",
    "addr:postcode":"2090",
    "addr:street":"Montague Rd",
    "iso:country":"AU",
    "sg:address":"20 Montague Rd",
    "sg:city":"Cremorne",
    "sg:classifiers":[
        {
            "category":"Utilities",
            "subcategory":"Electric",
            "type":"Services"
        }
    ],
    "sg:phone":"+61 2 9953 9737",
    "sg:postcode":"2090",
    "sg:province":"NSW",
    "sg:tags":[
        "electrical",
        "contractor"
    ],
    "wof:name":"Century Electrical Services Pty Ltd",
    "wof:placetype":"venue"
},
  "geometry": {"coordinates":[151.22999572800001,-33.8231391907],"type":"Point"}
}