{
  "type": "Feature",
  "properties": {
    "addr:full":"81 Wentworth St Port Kembla NSW 2505",
    "addr:housenumber":"81",
    "addr:postcode":"2505",
    "addr:street":"Wentworth St",
    "iso:country":"AU",
    "sg:address":"81 Wentworth St",
    "sg:city":"Port Kembla",
    "sg:classifiers":[
        {
            "category":"Real Estate",
            "subcategory":"Real Estate Agent",
            "type":"Services"
        }
    ],
    "sg:phone":"+61 2 4274 8000",
    "sg:postcode":"2505",
    "sg:province":"NSW",
    "wof:name":"O'Hara Real Estate",
    "wof:placetype":"venue"
},
  "geometry": {"coordinates":[150.902084,-34.481251],"type":"Point"}
}