{
  "type": "Feature",
  "properties": {
    "addr:full":"Shop 1/ 376 Kingston Rd Woodridge QLD 4114",
    "addr:housenumber":"shop 1 / 376",
    "addr:postcode":"4114",
    "addr:street":"Kingston Rd",
    "iso:country":"AU",
    "sg:address":"Shop 1/ 376 Kingston Rd",
    "sg:city":"Woodridge",
    "sg:classifiers":[
        {
            "category":"Social Services",
            "subcategory":"Adult Care",
            "type":"Services"
        }
    ],
    "sg:phone":"+61 7 3826 1598",
    "sg:postcode":"4114",
    "sg:province":"QLD",
    "sg:tags":[
        "advocate"
    ],
    "wof:name":"Tenancy Advice & Advocacy Service",
    "wof:placetype":"venue"
},
  "geometry": {"coordinates":[153.11618042000001,-27.624042511],"type":"Point"}
}