{
  "type": "Feature",
  "properties": {
    "addr:full":"45 Archer St Chatswood NSW 2067",
    "addr:housenumber":"45",
    "addr:postcode":"2067",
    "addr:street":"Archer St",
    "iso:country":"AU",
    "sg:address":"45 Archer St",
    "sg:city":"Chatswood",
    "sg:classifiers":[
        {
            "category":"Shopping",
            "subcategory":"Optical Goods",
            "type":"Retail Goods"
        }
    ],
    "sg:phone":"+61 2 9412 4338",
    "sg:postcode":"2067",
    "sg:province":"NSW",
    "sg:tags":[
        "dispenser",
        "prescription"
    ],
    "wof:name":"Robson Paul",
    "wof:placetype":"venue"
},
  "geometry": {"coordinates":[151.18655395499999,-33.7978515625],"type":"Point"}
}