{
  "type": "Feature",
  "properties": {
    "addr:full":"142 Canterbury Rd Blackburn South VIC 3130",
    "addr:housenumber":"142",
    "addr:postcode":"3130",
    "addr:street":"Canterbury Rd",
    "iso:country":"AU",
    "sg:address":"142 Canterbury Rd",
    "sg:city":"Blackburn South",
    "sg:classifiers":[
        {
            "category":"Personal",
            "subcategory":"Beauty Salon",
            "type":"Services"
        }
    ],
    "sg:phone":"+61 3 9877 3140",
    "sg:postcode":"3130",
    "sg:province":"VIC",
    "sg:tags":[
        "hairdresser"
    ],
    "wof:name":"Lee & Sara's Hair Studio",
    "wof:placetype":"venue"
},
  "geometry": {"coordinates":[145.14947509800001,-37.8322143555],"type":"Point"}
}