{
  "type": "Feature",
  "properties": {
    "addr:full":"Dangar St Armidale NSW 2350",
    "addr:postcode":"2350",
    "addr:street":"Dangar St",
    "iso:country":"AU",
    "sg:address":"Dangar St",
    "sg:city":"Armidale",
    "sg:classifiers":[
        {
            "category":"Food & Beverages",
            "subcategory":"Bakery",
            "type":"Retail Goods"
        }
    ],
    "sg:phone":"+61 2 6771 3266",
    "sg:postcode":"2350",
    "sg:province":"NSW",
    "sg:tags":[
        "baker"
    ],
    "wof:name":"Brumby's Bakeries",
    "wof:placetype":"venue"
},
  "geometry": {"coordinates":[151.66131591800001,-30.5241508484],"type":"Point"}
}