{
  "type": "Feature",
  "properties": {
    "addr:full":"389 Anzac Pde Kingsford NSW 2032",
    "addr:housenumber":"389",
    "addr:postcode":"2032",
    "addr:street":"Anzac Pde",
    "iso:country":"AU",
    "sg:address":"389 Anzac Pde",
    "sg:city":"Kingsford",
    "sg:classifiers":[
        {
            "category":"Personal",
            "subcategory":"Beauty Salon",
            "type":"Services"
        }
    ],
    "sg:phone":"+61 2 9697 9788",
    "sg:postcode":"2032",
    "sg:province":"NSW",
    "sg:tags":[
        "hairdresser"
    ],
    "wof:name":"Hair Under the Stars",
    "wof:placetype":"venue"
},
  "geometry": {"coordinates":[151.227905273,-33.9245452881],"type":"Point"}
}