{
  "type": "Feature",
  "properties": {
    "addr:full":"Union La Shepparton VIC 3630",
    "addr:postcode":"3630",
    "iso:country":"AU",
    "sg:address":"Union La",
    "sg:city":"Shepparton",
    "sg:classifiers":[
        {
            "category":"Personal",
            "subcategory":"Piercing",
            "type":"Services"
        }
    ],
    "sg:phone":"+61 3 5831 3138",
    "sg:postcode":"3630",
    "sg:province":"VIC",
    "sg:tags":[
        "body",
        "ear"
    ],
    "wof:name":"Hysteria",
    "wof:placetype":"venue"
},
  "geometry": {"coordinates":[145.39991760300001,-36.3816452026],"type":"Point"}
}