{
  "type": "Feature",
  "properties": {
    "addr:full":"25 Screen St Frankston VIC 3199",
    "addr:housenumber":"25",
    "addr:postcode":"3199",
    "addr:street":"Screen St",
    "iso:country":"AU",
    "sg:address":"25 Screen St",
    "sg:city":"Frankston",
    "sg:classifiers":[
        {
            "category":"Home & Garden",
            "subcategory":"Building Materials",
            "type":"Retail Goods"
        }
    ],
    "sg:phone":"+61 418 325 421",
    "sg:postcode":"3199",
    "sg:province":"VIC",
    "sg:tags":[
        "lawn",
        "cutting",
        "maintenance"
    ],
    "wof:name":"Lawnmaster",
    "wof:placetype":"venue"
},
  "geometry": {"coordinates":[145.14056396500001,-38.1570587158],"type":"Point"}
}