{
  "type": "Feature",
  "properties": {
    "addr:full":"45 Lime St Clermont QLD 4721",
    "addr:housenumber":"45",
    "addr:postcode":"4721",
    "addr:street":"Lime St",
    "iso:country":"AU",
    "sg:address":"45 Lime St",
    "sg:city":"Clermont",
    "sg:classifiers":[
        {
            "category":"Home & Garden",
            "subcategory":"Building Materials",
            "type":"Retail Goods"
        }
    ],
    "sg:phone":"+61 7 4983 3993",
    "sg:postcode":"4721",
    "sg:province":"QLD",
    "sg:tags":[
        "pre-mixed",
        "concrete"
    ],
    "wof:name":"Ezy Crete Pty Ltd",
    "wof:placetype":"venue"
},
  "geometry": {"coordinates":[147.63987731899999,-22.8187580109],"type":"Point"}
}