{
  "type": "Feature",
  "properties": {
    "addr:full":"31 Gregory St Mackay QLD 4740",
    "addr:housenumber":"31",
    "addr:postcode":"4740",
    "addr:street":"Gregory St",
    "iso:country":"AU",
    "sg:address":"31 Gregory St",
    "sg:city":"Mackay",
    "sg:classifiers":[
        {
            "category":"Insurance",
            "subcategory":"Insurance Agent",
            "type":"Services"
        }
    ],
    "sg:phone":"+61 7 4953 1046",
    "sg:postcode":"4740",
    "sg:province":"QLD",
    "sg:tags":[
        "broker"
    ],
    "wof:name":"Atlas Insurance Brokers",
    "wof:placetype":"venue"
},
  "geometry": {"coordinates":[149.184372,-21.143747],"type":"Point"}
}