{
  "type": "Feature",
  "properties": {
    "addr:full":"46 Gladstone St South Melbourne VIC 3205",
    "addr:housenumber":"46",
    "addr:postcode":"3205",
    "addr:street":"Gladstone St",
    "iso:country":"AU",
    "sg:address":"46 Gladstone St",
    "sg:city":"South Melbourne",
    "sg:classifiers":[
        {
            "category":"Shopping",
            "subcategory":"Computers & Home Electronics",
            "type":"Retail Goods"
        }
    ],
    "sg:phone":"+61 3 9562 2300",
    "sg:postcode":"3205",
    "sg:province":"VIC",
    "sg:tags":[
        "hardware",
        "equipment"
    ],
    "wof:name":"Advanced Components & Peripherals Pty Ltd",
    "wof:placetype":"venue"
},
  "geometry": {"coordinates":[144.95050000000001,-37.830265],"type":"Point"}
}