{
  "type": "Feature",
  "properties": {
    "addr:full":"55A Kingdon St Scone NSW 2337",
    "addr:housenumber":"55a",
    "addr:postcode":"2337",
    "addr:street":"Kingdon St",
    "iso:country":"AU",
    "sg:address":"55A Kingdon St",
    "sg:city":"Scone",
    "sg:classifiers":[
        {
            "category":"Building & Trades",
            "subcategory":"Construction",
            "type":"Services"
        }
    ],
    "sg:phone":"+61 428 952 990",
    "sg:postcode":"2337",
    "sg:province":"NSW",
    "sg:tags":[
        "earth",
        "excavating",
        "moving",
        "contractor"
    ],
    "wof:name":"A&G's Bobcat & Tipper Hire",
    "wof:placetype":"venue"
},
  "geometry": {"coordinates":[150.86317443900001,-32.0520553589],"type":"Point"}
}