{
  "type": "Feature",
  "properties": {
    "addr:full":"46 Palm St Rowes Bay QLD 4810",
    "addr:housenumber":"46",
    "addr:postcode":"4810",
    "addr:street":"Palm St",
    "iso:country":"AU",
    "sg:address":"46 Palm St",
    "sg:city":"Rowes Bay",
    "sg:classifiers":[
        {
            "category":"Government",
            "subcategory":"Customs House",
            "type":"Public Place"
        }
    ],
    "sg:phone":"+61 7 4771 5547",
    "sg:postcode":"4810",
    "sg:province":"QLD",
    "sg:tags":[
        "title",
        "management",
        "stratum"
    ],
    "wof:name":"MRS NQ",
    "wof:placetype":"venue"
},
  "geometry": {"coordinates":[146.78668200000001,-19.237165],"type":"Point"}
}