{
  "type": "Feature",
  "properties": {
    "addr:full":"PO Box 62 Mortdale NSW 2223",
    "addr:postcode":"2223",
    "iso:country":"AU",
    "sg:address":"PO Box 62",
    "sg:city":"Mortdale",
    "sg:classifiers":[
        {
            "category":"Professional",
            "subcategory":"Detective & Security Services",
            "type":"Services"
        }
    ],
    "sg:phone":"+61 2 9153 0764",
    "sg:postcode":"2223",
    "sg:province":"NSW",
    "sg:tags":[
        "distributor",
        "aircraft",
        "mfrs"
    ],
    "wof:name":"Invincible Airscrews Pty Ltd",
    "wof:placetype":"venue"
},
  "geometry": {"coordinates":[151.07974243199999,-33.9701309204],"type":"Point"}
}