{
  "type": "Feature",
  "properties": {
    "iso:country":"AU",
    "sg:address":"8 Colamba St",
    "sg:city":"Chinchilla",
    "sg:classifiers":[
        {
            "category":"Professional",
            "subcategory":"Engineering",
            "type":"Services"
        }
    ],
    "sg:phone":"+61 7 4668 9351",
    "sg:postcode":"4413",
    "sg:province":"QLD",
    "sg:tags":[
        "consulting",
        "engineer"
    ],
    "wof:name":"Brandon & Associates Pty Ltd",
    "wof:placetype":"venue"
},
  "geometry": {"coordinates":[150.628372192,-26.7384529114],"type":"Point"}
}