{
  "type": "Feature",
  "properties": {
    "iso:country":"AU",
    "sg:address":"Unit 80 30 Nobbs St",
    "sg:city":"Surry Hills",
    "sg:classifiers":[
        {
            "category":"Education",
            "subcategory":"Special Training",
            "type":"Public Place"
        }
    ],
    "sg:phone":"+61 417 711 109",
    "sg:postcode":"2010",
    "sg:province":"NSW",
    "sg:tags":[
        "development"
    ],
    "wof:name":"Avatar Training",
    "wof:placetype":"venue"
},
  "geometry": {"coordinates":[151.215896606,-33.8890190125],"type":"Point"}
}