{
  "type": "Feature",
  "properties": {
    "addr:full":"5 King St Montrose VIC 3765",
    "addr:housenumber":"5",
    "addr:postcode":"3765",
    "addr:street":"King St",
    "iso:country":"AU",
    "sg:address":"5 King St",
    "sg:city":"Montrose",
    "sg:classifiers":[
        {
            "category":"Building & Trades",
            "subcategory":"Landscaping Services",
            "type":"Services"
        }
    ],
    "sg:phone":"+61 3 9728 3367",
    "sg:postcode":"3765",
    "sg:province":"VIC",
    "sg:tags":[
        "designer",
        "landscape",
        "contractor"
    ],
    "wof:name":"Montrose Landscapes",
    "wof:placetype":"venue"
},
  "geometry": {"coordinates":[145.35144043,-37.8089103699],"type":"Point"}
}