{
  "type": "Feature",
  "properties": {
    "iso:country":"AU",
    "sg:address":"Shop 1, 1- 7 Jordan St",
    "sg:city":"Gladesville",
    "sg:classifiers":[
        {
            "category":"Real Estate",
            "subcategory":"Real Estate Agent",
            "type":"Services"
        }
    ],
    "sg:phone":"+61 2 9816 4999",
    "sg:postcode":"2111",
    "sg:province":"NSW",
    "wof:name":"Phipps For Farms",
    "wof:placetype":"venue"
},
  "geometry": {"coordinates":[151.12617492699999,-33.8302383423],"type":"Point"}
}