{
  "type": "Feature",
  "properties": {
    "iso:country":"AU",
    "sg:address":"PO Box 121",
    "sg:city":"Reynella",
    "sg:classifiers":[
        {
            "category":"Utilities",
            "subcategory":"Refuse",
            "type":"Services"
        }
    ],
    "sg:phone":"+61 407 619 846",
    "sg:postcode":"5161",
    "sg:province":"SA",
    "sg:tags":[
        "remover",
        "rubbish"
    ],
    "wof:name":"Talking Trash",
    "wof:placetype":"venue"
},
  "geometry": {"coordinates":[138.531784058,-35.1002388],"type":"Point"}
}