{
  "type": "Feature",
  "properties": {
    "addr:full":"Grattan St Prahran VIC 3181",
    "addr:postcode":"3181",
    "addr:street":"Grattan St",
    "iso:country":"AU",
    "sg:address":"Grattan St",
    "sg:city":"Prahran",
    "sg:classifiers":[
        {
            "category":"Organizations",
            "subcategory":"Community Association",
            "type":"Services"
        }
    ],
    "sg:phone":"+61 3 9510 2499",
    "sg:postcode":"3181",
    "sg:province":"VIC",
    "sg:tags":[
        "club",
        "senior",
        "citizen"
    ],
    "wof:name":"Chris Gahan Senior Citizens Centre",
    "wof:placetype":"venue"
},
  "geometry": {"coordinates":[144.99119567899999,-37.8483085632],"type":"Point"}
}