{
  "type": "Feature",
  "properties": {
    "addr:full":"269 Kalamunda Rd Maida Vale WA 6057",
    "addr:housenumber":"269",
    "addr:postcode":"6057",
    "addr:street":"Kalamunda Rd",
    "iso:country":"AU",
    "sg:address":"269 Kalamunda Rd",
    "sg:city":"Maida Vale",
    "sg:classifiers":[
        {
            "category":"Autos & Motor Vehicles",
            "subcategory":"Fuel & Gas Station",
            "type":"Retail Goods"
        }
    ],
    "sg:phone":"+61 8 9454 7716",
    "sg:postcode":"6057",
    "sg:province":"WA",
    "wof:name":"BP",
    "wof:placetype":"venue"
},
  "geometry": {"coordinates":[116.024131775,-31.9532546997],"type":"Point"}
}