{
  "type": "Feature",
  "properties": {
    "iso:country":"AU",
    "sg:address":"3- 5 Craine St",
    "sg:city":"South Melbourne",
    "sg:classifiers":[
        {
            "category":"Shopping",
            "subcategory":"Stationery & Office Supplies",
            "type":"Retail Goods"
        }
    ],
    "sg:phone":"+61 3 9696 3909",
    "sg:postcode":"3205",
    "sg:province":"VIC",
    "sg:tags":[
        "equipment",
        "display",
        "exhibition"
    ],
    "wof:name":"Work Point Pty Ltd The",
    "wof:placetype":"venue"
},
  "geometry": {"coordinates":[144.96156300000001,-37.831196],"type":"Point"}
}