{
  "type": "Feature",
  "properties": {
    "iso:country":"AU",
    "sg:address":"Kawana Shoppingworld Nicklin Way",
    "sg:city":"Kawana Waters",
    "sg:classifiers":[
        {
            "category":"Shopping",
            "subcategory":"Clothing, Apparel, & Fashions",
            "type":"Retail Goods"
        }
    ],
    "sg:phone":"+61 7 5444 0322",
    "sg:postcode":"4575",
    "sg:province":"QLD",
    "sg:tags":[
        "menswear"
    ],
    "wof:name":"Lowes Menswear",
    "wof:placetype":"venue"
},
  "geometry": {"coordinates":[153.129639,-26.700609],"type":"Point"}
}