{
  "type": "Feature",
  "properties": {
    "addr:full":"PO Box 82 Coolum Beach QLD 4573",
    "addr:postcode":"4573",
    "iso:country":"AU",
    "sg:address":"PO Box 82",
    "sg:city":"Coolum Beach",
    "sg:classifiers":[
        {
            "category":"Health Services",
            "subcategory":"Health Practitioner",
            "type":"Services"
        }
    ],
    "sg:phone":"+61 7 5471 7804",
    "sg:postcode":"4573",
    "sg:province":"QLD",
    "sg:tags":[
        "psychologist"
    ],
    "wof:name":"Jenifer Turner",
    "wof:placetype":"venue"
},
  "geometry": {"coordinates":[153.07545500000001,-26.53541],"type":"Point"}
}