{
  "type": "Feature",
  "properties": {
    "addr:full":"44 Binney St Euroa VIC 3666",
    "addr:housenumber":"44",
    "addr:postcode":"3666",
    "addr:street":"Binney St",
    "iso:country":"AU",
    "sg:address":"44 Binney St",
    "sg:city":"Euroa",
    "sg:classifiers":[
        {
            "category":"Retail",
            "subcategory":"Repair Shop",
            "type":"Services"
        }
    ],
    "sg:phone":"+61 3 5795 3208",
    "sg:postcode":"3666",
    "sg:province":"VIC",
    "sg:tags":[
        "upholsterer"
    ],
    "wof:name":"Town & Country Upholstery",
    "wof:placetype":"venue"
},
  "geometry": {"coordinates":[145.56990051299999,-36.7500114441],"type":"Point"}
}