{
  "type": "Feature",
  "properties": {
    "addr:full":"77 Planthurst Rd Carlton NSW 2218",
    "addr:housenumber":"77",
    "addr:postcode":"2218",
    "addr:street":"Planthurst Rd",
    "iso:country":"AU",
    "sg:address":"77 Planthurst Rd",
    "sg:city":"Carlton",
    "sg:classifiers":[
        {
            "category":"Retail",
            "subcategory":"Auto Rental",
            "type":"Services"
        }
    ],
    "sg:phone":"+61 2 9547 0100",
    "sg:postcode":"2218",
    "sg:province":"NSW",
    "sg:tags":[
        "home",
        "hire",
        "motor",
        "campervans"
    ],
    "wof:name":"Auto Sleepers",
    "wof:placetype":"venue"
},
  "geometry": {"coordinates":[151.11488299999999,-33.979561],"type":"Point"}
}