{
  "type": "Feature",
  "properties": {
    "addr:full":"231 Butterfield St Herston QLD 4006",
    "addr:housenumber":"231",
    "addr:postcode":"4006",
    "addr:street":"Butterfield St",
    "iso:country":"AU",
    "sg:address":"231 Butterfield St",
    "sg:city":"Herston",
    "sg:classifiers":[
        {
            "category":"Arena",
            "subcategory":"Sports Club",
            "type":"Entertainment"
        }
    ],
    "sg:phone":"+61 7 3354 9333",
    "sg:postcode":"4006",
    "sg:province":"QLD",
    "sg:tags":[
        "union",
        "rugby"
    ],
    "wof:name":"Queensland Rugby Union Ltd",
    "wof:placetype":"venue"
},
  "geometry": {"coordinates":[153.01641845699999,-27.4440345764],"type":"Point"}
}