{
  "type": "Feature",
  "properties": {
    "iso:country":"AU",
    "sg:address":"Lot 342 South Western Hwy",
    "sg:city":"Waroona",
    "sg:classifiers":[
        {
            "category":"Travel",
            "subcategory":"Hotels & Motels",
            "type":"Entertainment"
        }
    ],
    "sg:phone":"+61 8 9733 1566",
    "sg:postcode":"6215",
    "sg:province":"WA",
    "wof:name":"Drakesbrook Hotel/Motel",
    "wof:placetype":"venue"
},
  "geometry": {"coordinates":[115.883392,-32.749245],"type":"Point"}
}