{
  "type": "Feature",
  "properties": {
    "iso:country":"AU",
    "sg:address":"53 Amberley Crs",
    "sg:city":"Dandenong",
    "sg:classifiers":[
        {
            "category":"Professional",
            "type":"Services"
        }
    ],
    "sg:phone":"+61 3 9793 1611",
    "sg:postcode":"3175",
    "sg:province":"VIC",
    "sg:tags":[
        "coating",
        "powder"
    ],
    "wof:name":"Reefies Paintworks Pty Ltd",
    "wof:placetype":"venue"
},
  "geometry": {"coordinates":[145.218215942,-37.9853210449],"type":"Point"}
}