{
  "type": "Feature",
  "properties": {
    "addr:full":"101 Woodpark Rd Smithfield NSW 2164",
    "addr:housenumber":"101",
    "addr:postcode":"2164",
    "addr:street":"Woodpark Rd",
    "iso:country":"AU",
    "sg:address":"101 Woodpark Rd",
    "sg:city":"Smithfield",
    "sg:classifiers":[
        {
            "category":"Home & Garden",
            "subcategory":"Building Materials",
            "type":"Retail Goods"
        }
    ],
    "sg:phone":"+61 2 9892 4000",
    "sg:postcode":"2164",
    "sg:province":"NSW",
    "sg:tags":[
        "roofing"
    ],
    "wof:name":"K & T Metal Fabrications Pty Ltd",
    "wof:placetype":"venue"
},
  "geometry": {"coordinates":[150.93261718799999,-33.8361053467],"type":"Point"}
}