{
  "type": "Feature",
  "properties": {
    "addr:full":"454 Boundary Rd Darra QLD 4076",
    "addr:housenumber":"454",
    "addr:postcode":"4076",
    "addr:street":"Boundary Rd",
    "iso:country":"AU",
    "sg:address":"454 Boundary Rd",
    "sg:city":"Darra",
    "sg:classifiers":[
        {
            "category":"Retail",
            "subcategory":"Auto Repair",
            "type":"Services"
        }
    ],
    "sg:phone":"+61 7 3375 3166",
    "sg:postcode":"4076",
    "sg:province":"QLD",
    "sg:tags":[
        "beater",
        "painter",
        "panel"
    ],
    "wof:name":"Rocklea Truck Repairs",
    "wof:placetype":"venue"
},
  "geometry": {"coordinates":[152.965866089,-27.574092865],"type":"Point"}
}