{
  "type": "Feature",
  "properties": {
    "addr:full":"4 Govetts Leap Rd Blackheath NSW 2785",
    "addr:housenumber":"4",
    "addr:postcode":"2785",
    "addr:street":"Govetts Leap Rd",
    "iso:country":"AU",
    "sg:address":"4 Govetts Leap Rd",
    "sg:city":"Blackheath",
    "sg:classifiers":[
        {
            "category":"Shopping",
            "subcategory":"Shoes",
            "type":"Retail Goods"
        }
    ],
    "sg:phone":"+61 2 4787 8263",
    "sg:postcode":"2785",
    "sg:province":"NSW",
    "sg:tags":[
        "footwear"
    ],
    "wof:name":"Blackheath Family Shoe Store",
    "wof:placetype":"venue"
},
  "geometry": {"coordinates":[150.28515625,-33.6354598999],"type":"Point"}
}