{
  "type": "Feature",
  "properties": {
    "addr:full":"1 Edgecombe Crt Moorabbin VIC 3189",
    "addr:housenumber":"1",
    "addr:postcode":"3189",
    "addr:street":"Edgecombe Crt",
    "iso:country":"AU",
    "sg:address":"1 Edgecombe Crt",
    "sg:city":"Moorabbin",
    "sg:classifiers":[
        {
            "category":"Utilities",
            "subcategory":"Water",
            "type":"Services"
        }
    ],
    "sg:phone":"+61 3 9555 0522",
    "sg:postcode":"3189",
    "sg:province":"VIC",
    "sg:tags":[
        "equipment",
        "treatment"
    ],
    "wof:name":"T & T Engineering & Piping Contractors",
    "wof:placetype":"venue"
},
  "geometry": {"coordinates":[145.07148742699999,-37.9430656433],"type":"Point"}
}