{
  "type": "Feature",
  "properties": {
    "addr:full":"60 Bulcock St Caloundra QLD 4551",
    "addr:housenumber":"60",
    "addr:postcode":"4551",
    "addr:street":"Bulcock St",
    "iso:country":"AU",
    "sg:address":"60 Bulcock St",
    "sg:city":"Caloundra",
    "sg:classifiers":[
        {
            "category":"Shopping",
            "subcategory":"Computers & Home Electronics",
            "type":"Retail Goods"
        }
    ],
    "sg:phone":"+61 7 5438 2077",
    "sg:postcode":"4551",
    "sg:province":"QLD",
    "sg:tags":[
        "equipment",
        "part",
        "electronic"
    ],
    "wof:name":"Dick Smith Electronics",
    "wof:placetype":"venue"
},
  "geometry": {"coordinates":[153.129196167,-26.8046379089],"type":"Point"}
}