{
  "type": "Feature",
  "properties": {
    "iso:country":"AU",
    "sg:address":"52 Illowra Crs",
    "sg:city":"Primbee",
    "sg:classifiers":[
        {
            "category":"Education",
            "subcategory":"Kindergarten",
            "type":"Public Place"
        }
    ],
    "sg:phone":"+61 2 4274 3818",
    "sg:postcode":"2502",
    "sg:province":"NSW",
    "sg:tags":[
        "pre-schools"
    ],
    "wof:name":"Grandma Rosie's Quality Long Day Care",
    "wof:placetype":"venue"
},
  "geometry": {"coordinates":[150.886627,-34.499748],"type":"Point"}
}