{
  "type": "Feature",
  "properties": {
    "addr:full":"Davison St Whyalla Norrie SA 5608",
    "addr:postcode":"5608",
    "addr:street":"Davison St",
    "iso:country":"AU",
    "sg:address":"Davison St",
    "sg:city":"Whyalla Norrie",
    "sg:classifiers":[
        {
            "category":"Social Services",
            "subcategory":"Child Care",
            "type":"Services"
        }
    ],
    "sg:phone":"+61 8 8645 0169",
    "sg:postcode":"5608",
    "sg:province":"SA",
    "wof:name":"Davison St Occasional Care Centre",
    "wof:placetype":"venue"
},
  "geometry": {"coordinates":[137.53512599999999,-33.019859],"type":"Point"}
}