{
  "type": "Feature",
  "properties": {
    "addr:full":"Unit 5, 25 Veronica St Capalaba QLD 4157",
    "addr:housenumber":"25",
    "addr:postcode":"4157",
    "addr:street":"Veronica St",
    "iso:country":"AU",
    "sg:address":"Unit 5, 25 Veronica St",
    "sg:city":"Capalaba",
    "sg:classifiers":[
        {
            "category":"Retail",
            "subcategory":"Auto Repair",
            "type":"Services"
        }
    ],
    "sg:phone":"+61 7 3245 3282",
    "sg:postcode":"4157",
    "sg:province":"QLD",
    "sg:tags":[
        "repairer",
        "motor",
        "engineer"
    ],
    "wof:name":"Autodata",
    "wof:placetype":"venue"
},
  "geometry": {"coordinates":[153.19784545900001,-27.5267524719],"type":"Point"}
}