{
  "type": "Feature",
  "properties": {
    "iso:country":"AU",
    "sg:address":"9 Jardine St",
    "sg:city":"Kingston",
    "sg:classifiers":[
        {
            "category":"Professional",
            "subcategory":"Detective & Security Services",
            "type":"Services"
        }
    ],
    "sg:phone":"+61 2 6273 1061",
    "sg:postcode":"2604",
    "sg:province":"ACT",
    "sg:tags":[
        "consultant",
        "system"
    ],
    "wof:name":"Aulich & Co",
    "wof:placetype":"venue"
},
  "geometry": {"coordinates":[149.141067505,-35.3138237],"type":"Point"}
}