{
  "type": "Feature",
  "properties": {
    "addr:full":"102b City Rd Beenleigh QLD 4207",
    "addr:housenumber":"102b",
    "addr:postcode":"4207",
    "addr:street":"City Rd",
    "iso:country":"AU",
    "sg:address":"102b City Rd",
    "sg:city":"Beenleigh",
    "sg:classifiers":[
        {
            "category":"Shopping",
            "subcategory":"Jewelry",
            "type":"Retail Goods"
        }
    ],
    "sg:phone":"+61 7 3287 1230",
    "sg:postcode":"4207",
    "sg:province":"QLD",
    "sg:tags":[
        "jeweller"
    ],
    "wof:name":"Hatton Garden Jewellers",
    "wof:placetype":"venue"
},
  "geometry": {"coordinates":[153.20237731899999,-27.7151756287],"type":"Point"}
}