{
  "type": "Feature",
  "properties": {
    "addr:full":"5 Commerce Crs Victor Harbor SA 5211",
    "addr:housenumber":"5",
    "addr:postcode":"5211",
    "addr:street":"Commerce Crs",
    "iso:country":"AU",
    "sg:address":"5 Commerce Crs",
    "sg:city":"Victor Harbor",
    "sg:classifiers":[
        {
            "category":"Building & Trades",
            "subcategory":"Construction",
            "type":"Services"
        }
    ],
    "sg:phone":"+61 8 8552 8552",
    "sg:postcode":"5211",
    "sg:province":"SA",
    "sg:tags":[
        "contractor"
    ],
    "wof:name":"Cavco Constructions",
    "wof:placetype":"venue"
},
  "geometry": {"coordinates":[138.624435425,-35.5497398376],"type":"Point"}
}