{
  "type": "Feature",
  "properties": {
    "addr:full":"27 Avoca Drv Green Point NSW 2251",
    "addr:housenumber":"27",
    "addr:postcode":"2251",
    "addr:street":"Avoca Drv",
    "iso:country":"AU",
    "sg:address":"27 Avoca Drv",
    "sg:city":"Green Point",
    "sg:classifiers":[
        {
            "category":"Building & Trades",
            "subcategory":"Construction",
            "type":"Services"
        }
    ],
    "sg:phone":"+61 2 4367 7752",
    "sg:postcode":"2251",
    "sg:province":"NSW",
    "sg:tags":[
        "brick",
        "paving"
    ],
    "wof:name":"Habitat Landscape",
    "wof:placetype":"venue"
},
  "geometry": {"coordinates":[151.36529540999999,-33.4491882324],"type":"Point"}
}