{
  "type": "Feature",
  "properties": {
    "addr:full":"Hopkins St Virginia QLD 4014",
    "addr:postcode":"4014",
    "addr:street":"Hopkins St",
    "iso:country":"AU",
    "sg:address":"Hopkins St",
    "sg:city":"Virginia",
    "sg:classifiers":[
        {
            "category":"Building & Trades",
            "subcategory":"Construction",
            "type":"Services"
        }
    ],
    "sg:phone":"+61 413 127 076",
    "sg:postcode":"4014",
    "sg:province":"QLD",
    "sg:tags":[
        "repairing",
        "window"
    ],
    "wof:name":"Touch&#039;N Go",
    "wof:placetype":"venue"
},
  "geometry": {"coordinates":[153.05847168,-27.387676239],"type":"Point"}
}