{
  "type": "Feature",
  "properties": {
    "iso:country":"AU",
    "sg:address":"9 Catalyst Crt",
    "sg:city":"Bohle",
    "sg:classifiers":[
        {
            "category":"Professional",
            "subcategory":"Testing Lab",
            "type":"Services"
        }
    ],
    "sg:phone":"+61 7 4774 7888",
    "sg:postcode":"4818",
    "sg:province":"QLD",
    "sg:tags":[
        "soil",
        "investigation"
    ],
    "wof:name":"Soil Engineering Services",
    "wof:placetype":"venue"
},
  "geometry": {"coordinates":[146.74234000000001,-19.260426],"type":"Point"}
}