{
  "type": "Feature",
  "properties": {
    "addr:full":"5 Alexander St Dundas NSW 2117",
    "addr:housenumber":"5",
    "addr:postcode":"2117",
    "addr:street":"Alexander St",
    "iso:country":"AU",
    "sg:address":"5 Alexander St",
    "sg:city":"Dundas",
    "sg:classifiers":[
        {
            "category":"Professional",
            "subcategory":"Accounting & Tax Preparation",
            "type":"Services"
        }
    ],
    "sg:phone":"+61 2 9871 5086",
    "sg:postcode":"2117",
    "sg:province":"NSW",
    "sg:tags":[
        "consultant",
        "taxation"
    ],
    "wof:name":"Williams R L & Co",
    "wof:placetype":"venue"
},
  "geometry": {"coordinates":[151.056472778,-33.7937698364],"type":"Point"}
}