{
  "type": "Feature",
  "properties": {
    "iso:country":"AU",
    "sg:address":"20 Wright St",
    "sg:city":"Hurstville",
    "sg:classifiers":[
        {
            "category":"Education",
            "subcategory":"Kindergarten",
            "type":"Public Place"
        }
    ],
    "sg:phone":"+61 2 9570 8086",
    "sg:postcode":"2220",
    "sg:province":"NSW",
    "sg:tags":[
        "pre-schools"
    ],
    "wof:name":"Gumnut Grove Child Care Centre",
    "wof:placetype":"venue"
},
  "geometry": {"coordinates":[151.10943603499999,-33.965549469],"type":"Point"}
}