{
  "type": "Feature",
  "properties": {
    "addr:full":"Shop 4049, Knox O-Zone Shopping Centre, Cnr Burwood Hwy & Stud Road Wantirna South VIC 3152",
    "addr:housenumber":"4049",
    "addr:postcode":"3152",
    "addr:street":"Knox O-Zone;Cnr Burwood Hwy & Stud Road",
    "iso:country":"AU",
    "sg:address":"Shop 4049, Knox O-Zone Shopping Centre, Cnr Burwood Hwy & Stud Road",
    "sg:city":"Wantirna South",
    "sg:classifiers":[
        {
            "category":"Building & Trades",
            "subcategory":"Equipment Rental",
            "type":"Services"
        }
    ],
    "sg:phone":"+61 3 9800 0499",
    "sg:postcode":"3152",
    "sg:province":"VIC",
    "sg:tags":[
        "fitness"
    ],
    "wof:name":"Workout World Knox City",
    "wof:placetype":"venue"
},
  "geometry": {"coordinates":[145.24488830600001,-37.8719444275],"type":"Point"}
}