{
  "type": "Feature",
  "properties": {
    "addr:full":"Unit 2/ 28 Vale St Malaga WA 6090",
    "addr:housenumber":"28",
    "addr:postcode":"6090",
    "addr:street":"Vale St",
    "iso:country":"AU",
    "sg:address":"Unit 2/ 28 Vale St",
    "sg:city":"Malaga",
    "sg:classifiers":[
        {
            "category":"Shopping",
            "subcategory":"Gifts & Souvenirs",
            "type":"Retail Goods"
        }
    ],
    "sg:phone":"+61 8 9249 7588",
    "sg:postcode":"6090",
    "sg:province":"WA",
    "sg:tags":[
        "shop",
        "supply"
    ],
    "wof:name":"DCMA Collection",
    "wof:placetype":"venue"
},
  "geometry": {"coordinates":[115.893447876,-31.848405838],"type":"Point"}
}