{
  "type": "Feature",
  "properties": {
    "iso:country":"AU",
    "sg:address":"Coombe St",
    "sg:city":"Collie",
    "sg:classifiers":[
        {
            "category":"Sports & Exercise",
            "subcategory":"Sports Center",
            "type":"Entertainment"
        }
    ],
    "sg:phone":"+61 8 9734 4388",
    "sg:postcode":"6225",
    "sg:province":"WA",
    "sg:tags":[
        "ground"
    ],
    "wof:name":"Roche Park Recreation Centre",
    "wof:placetype":"venue"
},
  "geometry": {"coordinates":[116.156311,-33.35685],"type":"Point"}
}