{
  "type": "Feature",
  "properties": {
    "addr:full":"24 Kendall St Charlestown NSW 2290",
    "addr:housenumber":"24",
    "addr:postcode":"2290",
    "addr:street":"Kendall St",
    "iso:country":"AU",
    "sg:address":"24 Kendall St",
    "sg:city":"Charlestown",
    "sg:classifiers":[
        {
            "category":"Home & Garden",
            "subcategory":"Carpets & Floor Coverings",
            "type":"Retail Goods"
        }
    ],
    "sg:phone":"+61 409 489 842",
    "sg:postcode":"2290",
    "sg:province":"NSW",
    "sg:tags":[
        "wood"
    ],
    "wof:name":"Smart Floor Sanding",
    "wof:placetype":"venue"
},
  "geometry": {"coordinates":[151.68728637699999,-32.9613571167],"type":"Point"}
}