{
  "type": "Feature",
  "properties": {
    "iso:country":"AU",
    "sg:address":"72 Normanby Ave",
    "sg:city":"Thornbury",
    "sg:classifiers":[
        {
            "category":"Health Services",
            "subcategory":"Health Practitioner",
            "type":"Services"
        }
    ],
    "sg:phone":"+61 3 9416 8624",
    "sg:postcode":"3071",
    "sg:province":"VIC",
    "sg:tags":[
        "acupuncture"
    ],
    "wof:name":"Wang Natural Medical Centre",
    "wof:placetype":"venue"
},
  "geometry": {"coordinates":[144.99293518100001,-37.758480072],"type":"Point"}
}