{
  "type": "Feature",
  "properties": {
    "addr:full":"226 Hawthorn Rd Caulfield North VIC 3161",
    "addr:housenumber":"226",
    "addr:postcode":"3161",
    "addr:street":"Hawthorn Rd",
    "iso:country":"AU",
    "sg:address":"226 Hawthorn Rd",
    "sg:city":"Caulfield North",
    "sg:classifiers":[
        {
            "category":"Shopping",
            "subcategory":"Antiques",
            "type":"Retail Goods"
        }
    ],
    "sg:phone":"+61 3 9528 5912",
    "sg:postcode":"3161",
    "sg:province":"VIC",
    "wof:name":"Little Treasures",
    "wof:placetype":"venue"
},
  "geometry": {"coordinates":[145.023269653,-37.8792686462],"type":"Point"}
}