{
  "type": "Feature",
  "properties": {
    "iso:country":"AU",
    "sg:address":"118 Queen St",
    "sg:city":"Melbourne",
    "sg:classifiers":[
        {
            "category":"Professional",
            "subcategory":"Business Services",
            "type":"Services"
        }
    ],
    "sg:phone":"+61 3 9670 8266",
    "sg:postcode":"3000",
    "sg:province":"VIC",
    "sg:tags":[
        "broker"
    ],
    "wof:name":"Business & Corporate",
    "wof:placetype":"venue"
},
  "geometry": {"coordinates":[144.961227417,-37.8157234192],"type":"Point"}
}