{
  "type": "Feature",
  "properties": {
    "addr:full":"26 Charlesworth Crt Mile End SA 5031",
    "addr:housenumber":"26",
    "addr:postcode":"5031",
    "addr:street":"Charlesworth Crt",
    "iso:country":"AU",
    "sg:address":"26 Charlesworth Crt",
    "sg:city":"Mile End",
    "sg:classifiers":[
        {
            "category":"Building & Trades",
            "subcategory":"Construction",
            "type":"Services"
        }
    ],
    "sg:phone":"+61 412 827 459",
    "sg:postcode":"5031",
    "sg:province":"SA",
    "sg:tags":[
        "earth",
        "excavating",
        "moving",
        "contractor"
    ],
    "wof:name":"Michael Hayes",
    "wof:placetype":"venue"
},
  "geometry": {"coordinates":[138.577301025,-34.9279670715],"type":"Point"}
}