{
  "type": "Feature",
  "properties": {
    "addr:full":"8/ 284 Musgrave Rd Coopers Plains QLD 4108",
    "addr:housenumber":"/ 284",
    "addr:postcode":"4108",
    "addr:street":"Musgrave Rd",
    "iso:country":"AU",
    "sg:address":"8/ 284 Musgrave Rd",
    "sg:city":"Coopers Plains",
    "sg:classifiers":[
        {
            "category":"Manufacturing",
            "subcategory":"Tools & Machinery",
            "type":"Manufacturing & Wholesale Goods"
        }
    ],
    "sg:phone":"+61 7 3274 1972",
    "sg:postcode":"4108",
    "sg:province":"QLD",
    "sg:tags":[
        "equipment",
        "scale",
        "weighing"
    ],
    "wof:name":"AAA-Australian Load Cell Suppliers",
    "wof:placetype":"venue"
},
  "geometry": {"coordinates":[153.036453247,-27.5626087189],"type":"Point"}
}