{
  "type": "Feature",
  "properties": {
    "iso:country":"AU",
    "sg:address":"Shp 7 Greystanes Rd",
    "sg:city":"Greystanes",
    "sg:classifiers":[
        {
            "category":"Fast Food",
            "type":"Food & Drink"
        }
    ],
    "sg:phone":"+61 2 9636 9009",
    "sg:postcode":"2145",
    "sg:province":"NSW",
    "sg:tags":[
        "away",
        "take"
    ],
    "wof:name":"Fully Tabooly Kebab Stop",
    "wof:placetype":"venue"
},
  "geometry": {"coordinates":[150.93695068400001,-33.8097229004],"type":"Point"}
}