{
  "type": "Feature",
  "properties": {
    "iso:country":"AU",
    "sg:address":"55a Browns Rd",
    "sg:city":"Austral",
    "sg:classifiers":[
        {
            "category":"Social Services",
            "subcategory":"Child Care",
            "type":"Services"
        }
    ],
    "sg:phone":"+61 2 9606 8966",
    "sg:postcode":"2179",
    "sg:province":"NSW",
    "wof:name":"West Hoxton Before & After School Care",
    "wof:placetype":"venue"
},
  "geometry": {"coordinates":[150.81718444800001,-33.9470481873],"type":"Point"}
}