{
  "type": "Feature",
  "properties": {
    "iso:country":"AU",
    "sg:address":"PO Box 203",
    "sg:city":"Tintinara",
    "sg:classifiers":[
        {
            "category":"Farming",
            "subcategory":"Farm & Veterinary Services",
            "type":"Manufacturing & Wholesale Goods"
        }
    ],
    "sg:phone":"+61 8 8757 2556",
    "sg:postcode":"5266",
    "sg:province":"SA",
    "sg:tags":[
        "drying",
        "seed",
        "cleaning",
        "grading"
    ],
    "wof:name":"Scott Rosenzweig",
    "wof:placetype":"venue"
},
  "geometry": {"coordinates":[140.055984,-35.883831],"type":"Point"}
}