{
  "type": "Feature",
  "properties": {
    "addr:full":"6-12 Essex St Geelong VIC 3220",
    "addr:housenumber":"6-12",
    "addr:postcode":"3220",
    "addr:street":"Essex St",
    "iso:country":"AU",
    "sg:address":"6-12 Essex St",
    "sg:city":"Geelong",
    "sg:classifiers":[
        {
            "category":"Social Services",
            "subcategory":"Adult Care",
            "type":"Services"
        }
    ],
    "sg:phone":"+61 3 5248 2161",
    "sg:postcode":"3220",
    "sg:province":"VIC",
    "sg:tags":[
        "towing"
    ],
    "wof:name":"Graham Pickering Towing Pty Ltd",
    "wof:placetype":"venue"
},
  "geometry": {"coordinates":[144.41027800000001,-38.164268],"type":"Point"}
}