{
  "type": "Feature",
  "properties": {
    "iso:country":"AU",
    "sg:address":"79 Glenora St",
    "sg:city":"Wynnum",
    "sg:classifiers":[
        {
            "category":"Autos & Motor Vehicles",
            "subcategory":"Fuel & Gas Station",
            "type":"Retail Goods"
        }
    ],
    "sg:phone":"+61 7 3348 3619",
    "sg:postcode":"4178",
    "sg:province":"QLD",
    "sg:tags":[
        "petrol",
        "marketing",
        "pump",
        "equipment"
    ],
    "wof:name":"Petroleum Maintainence & Installation Services Pty Ltd",
    "wof:placetype":"venue"
},
  "geometry": {"coordinates":[153.16859435999999,-27.4367752075],"type":"Point"}
}