{
  "type": "Feature",
  "properties": {
    "addr:full":"Shop 242 Forest Hill Chase 270 Canterbury Rd Forest Hill VIC 3131",
    "addr:housenumber":"242;270",
    "addr:postcode":"3131",
    "addr:street":"Forest Hill Chase;Canterbury Rd",
    "iso:country":"AU",
    "sg:address":"Shop 242 Forest Hill Chase 270 Canterbury Rd",
    "sg:city":"Forest Hill",
    "sg:classifiers":[
        {
            "category":"Shopping",
            "subcategory":"Clothing, Apparel, & Fashions",
            "type":"Retail Goods"
        }
    ],
    "sg:phone":"+61 3 9877 1899",
    "sg:postcode":"3131",
    "sg:province":"VIC",
    "sg:tags":[
        "lady",
        "wear"
    ],
    "wof:name":"Noni B",
    "wof:placetype":"venue"
},
  "geometry": {"coordinates":[145.173065186,-37.8350105286],"type":"Point"}
}