{
  "type": "Feature",
  "properties": {
    "iso:country":"AU",
    "sg:address":"Kessells Rd",
    "sg:city":"Mt Gravatt",
    "sg:classifiers":[
        {
            "category":"Fast Food",
            "type":"Food & Drink"
        }
    ],
    "sg:phone":"+61 7 3343 8155",
    "sg:postcode":"4122",
    "sg:province":"QLD",
    "sg:tags":[
        "away",
        "take"
    ],
    "wof:name":"Origin Kebab",
    "wof:placetype":"venue"
},
  "geometry": {"coordinates":[153.08088684099999,-27.5599441528],"type":"Point"}
}