{
  "type": "Feature",
  "properties": {
    "iso:country":"AU",
    "sg:address":"PO Box 953",
    "sg:city":"Civic Square",
    "sg:classifiers":[
        {
            "category":"Building & Trades",
            "subcategory":"Cleaning & Sanitation",
            "type":"Services"
        }
    ],
    "sg:phone":"+61 413 941 744",
    "sg:postcode":"2608",
    "sg:province":"ACT",
    "sg:tags":[
        "window"
    ],
    "wof:name":"In Vogue Cleaning",
    "wof:placetype":"venue"
},
  "geometry": {"coordinates":[149.12167358400001,-35.2839012146],"type":"Point"}
}