{
  "type": "Feature",
  "properties": {
    "addr:full":"115 Palmgrove Rd Avalon NSW 2107",
    "addr:housenumber":"115",
    "addr:postcode":"2107",
    "addr:street":"Palmgrove Rd",
    "iso:country":"AU",
    "sg:address":"115 Palmgrove Rd",
    "sg:city":"Avalon",
    "sg:classifiers":[
        {
            "category":"Real Estate",
            "subcategory":"Architect",
            "type":"Services"
        }
    ],
    "sg:phone":"+61 2 9973 3312",
    "sg:postcode":"2107",
    "sg:province":"NSW",
    "sg:tags":[
        "building",
        "designer"
    ],
    "wof:name":"Peter Downes Designs",
    "wof:placetype":"venue"
},
  "geometry": {"coordinates":[151.321136475,-33.6369972229],"type":"Point"}
}