{
  "type": "Feature",
  "properties": {
    "addr:full":"397 Marion Rd Plympton SA 5038",
    "addr:housenumber":"397",
    "addr:postcode":"5038",
    "addr:street":"Marion Rd",
    "iso:country":"AU",
    "sg:address":"397 Marion Rd",
    "sg:city":"Plympton",
    "sg:classifiers":[
        {
            "category":"Health Services",
            "subcategory":"Dentist",
            "type":"Services"
        }
    ],
    "sg:phone":"+61 8 8297 4266",
    "sg:postcode":"5038",
    "sg:province":"SA",
    "wof:name":"Rajcevic Dusica Dr",
    "wof:placetype":"venue"
},
  "geometry": {"coordinates":[138.55499267600001,-34.9635238647],"type":"Point"}
}