{
  "type": "Feature",
  "properties": {
    "addr:full":"Unit 4, 15-17 Chaplin Drv Lane Cove NSW 2066",
    "addr:housenumber":"15-17",
    "addr:postcode":"2066",
    "addr:street":"Chaplin Drv",
    "iso:country":"AU",
    "sg:address":"Unit 4, 15-17 Chaplin Drv",
    "sg:city":"Lane Cove",
    "sg:classifiers":[
        {
            "category":"Building & Trades",
            "subcategory":"Landscaping Services",
            "type":"Services"
        }
    ],
    "sg:phone":"+61 2 9429 8500",
    "sg:postcode":"2066",
    "sg:province":"NSW",
    "sg:tags":[
        "designer",
        "landscape",
        "contractor"
    ],
    "wof:name":"Glascott Group Pty Ltd The",
    "wof:placetype":"venue"
},
  "geometry": {"coordinates":[151.14875793499999,-33.8092956543],"type":"Point"}
}