{
  "type": "Feature",
  "properties": {
    "addr:full":"6 Railway St Gladstone QLD 4680",
    "addr:housenumber":"6",
    "addr:postcode":"4680",
    "addr:street":"Railway St",
    "iso:country":"AU",
    "sg:address":"6 Railway St",
    "sg:city":"Gladstone",
    "sg:classifiers":[
        {
            "category":"Professional",
            "subcategory":"Accounting & Tax Preparation",
            "type":"Services"
        }
    ],
    "sg:phone":"+61 409 068 641",
    "sg:postcode":"4680",
    "sg:province":"QLD",
    "sg:tags":[
        "deduction",
        "payroll"
    ],
    "wof:name":"Leanne Kendrick",
    "wof:placetype":"venue"
},
  "geometry": {"coordinates":[151.25160217300001,-23.8485660553],"type":"Point"}
}