{
  "type": "Feature",
  "properties": {
    "iso:country":"AU",
    "sg:address":"47 Kintyre Rd",
    "sg:city":"Armidale",
    "sg:classifiers":[
        {
            "category":"Education",
            "subcategory":"Special Training",
            "type":"Public Place"
        }
    ],
    "sg:phone":"+61 2 6772 9300",
    "sg:postcode":"2350",
    "sg:province":"NSW",
    "sg:tags":[
        "development"
    ],
    "wof:name":"The Career Company Pty Ltd",
    "wof:placetype":"venue"
},
  "geometry": {"coordinates":[151.666503906,-30.512796402],"type":"Point"}
}