{
  "type": "Feature",
  "properties": {
    "addr:full":"195 Dunmore St Pendle Hill NSW 2145",
    "addr:housenumber":"195",
    "addr:postcode":"2145",
    "addr:street":"Dunmore St",
    "iso:country":"AU",
    "sg:address":"195 Dunmore St",
    "sg:city":"Pendle Hill",
    "sg:classifiers":[
        {
            "category":"Food & Beverages",
            "subcategory":"Groceries & Convenience Stores",
            "type":"Retail Goods"
        }
    ],
    "sg:phone":"+61 2 9896 1588",
    "sg:postcode":"2145",
    "sg:province":"NSW",
    "wof:name":"Eddie's On Dunmore Convenience Store",
    "wof:placetype":"venue"
},
  "geometry": {"coordinates":[150.96119689899999,-33.8051757812],"type":"Point"}
}