{
  "type": "Feature",
  "properties": {
    "addr:full":"30 McLennan Drv Kensington VIC 3031",
    "addr:housenumber":"30",
    "addr:postcode":"3031",
    "addr:street":"Mclennan Drv",
    "iso:country":"AU",
    "sg:address":"30 McLennan Drv",
    "sg:city":"Kensington",
    "sg:classifiers":[
        {
            "category":"Education",
            "subcategory":"Library",
            "type":"Public Place"
        }
    ],
    "sg:phone":"+61 3 9376 3388",
    "sg:postcode":"3031",
    "sg:province":"VIC",
    "sg:tags":[
        "equipment",
        "supply"
    ],
    "wof:name":"Languages Direct",
    "wof:placetype":"venue"
},
  "geometry": {"coordinates":[144.927628,-37.79414],"type":"Point"}
}