{
  "type": "Feature",
  "properties": {
    "addr:full":"Flinders Hwy Julia Creek QLD 4823",
    "addr:postcode":"4823",
    "addr:street":"Flinders Hwy",
    "iso:country":"AU",
    "sg:address":"Flinders Hwy",
    "sg:city":"Julia Creek",
    "sg:classifiers":[
        {
            "category":"Professional",
            "subcategory":"Business Services",
            "type":"Services"
        }
    ],
    "sg:phone":"+61 7 4746 7121",
    "sg:postcode":"4823",
    "sg:province":"QLD",
    "sg:tags":[
        "livestock",
        "transport"
    ],
    "wof:name":"North West Livestock Transport Pty Ltd",
    "wof:placetype":"venue"
},
  "geometry": {"coordinates":[141.74812299999999,-20.656889],"type":"Point"}
}