{
  "type": "Feature",
  "properties": {
    "addr:full":"12- 16 Leabons La Seven Hills NSW 2147",
    "addr:housenumber":"16",
    "addr:postcode":"2147",
    "addr:street":"Leabons La",
    "iso:country":"AU",
    "sg:address":"12- 16 Leabons La",
    "sg:city":"Seven Hills",
    "sg:classifiers":[
        {
            "category":"Wholesale",
            "subcategory":"Drugs",
            "type":"Manufacturing & Wholesale Goods"
        }
    ],
    "sg:phone":"+61 2 9621 6828",
    "sg:postcode":"2147",
    "sg:province":"NSW",
    "sg:tags":[
        "wholesaler",
        "pharmaceutical",
        "product",
        "mfrs"
    ],
    "wof:name":"Complete Clean-Pac Services",
    "wof:placetype":"venue"
},
  "geometry": {"coordinates":[150.924072266,-33.7828140259],"type":"Point"}
}