{
  "type": "Feature",
  "properties": {
    "iso:country":"AU",
    "sg:address":"347 Ruthven St",
    "sg:city":"Toowoomba",
    "sg:classifiers":[
        {
            "category":"Professional",
            "subcategory":"Printing & Photocopies",
            "type":"Services"
        }
    ],
    "sg:phone":"+61 7 4632 8349",
    "sg:postcode":"4350",
    "sg:province":"QLD",
    "sg:tags":[
        "rubber",
        "stamp",
        "metal"
    ],
    "sg:website":"http://www.expressrubberstamps.com.au",
    "wof:name":"Express Rubber Stamps",
    "wof:placetype":"venue"
},
  "geometry": {"coordinates":[151.95228599999999,-27.568314],"type":"Point"}
}