{
  "type": "Feature",
  "properties": {
    "addr:full":"88a Oakes Rd Toongabbie NSW 2146",
    "addr:housenumber":"88a",
    "addr:postcode":"2146",
    "addr:street":"Oakes Rd",
    "iso:country":"AU",
    "sg:address":"88a Oakes Rd",
    "sg:city":"Toongabbie",
    "sg:classifiers":[
        {
            "category":"Retail",
            "subcategory":"Auto Repair",
            "type":"Services"
        }
    ],
    "sg:phone":"+61 2 9688 4549",
    "sg:postcode":"2146",
    "sg:province":"NSW",
    "sg:tags":[
        "beater",
        "painter",
        "panel"
    ],
    "wof:name":"Oakes Rd Smash Repairs",
    "wof:placetype":"venue"
},
  "geometry": {"coordinates":[150.97227477999999,-33.7847633362],"type":"Point"}
}