{
  "type": "Feature",
  "properties": {
    "iso:country":"AU",
    "sg:address":"47 Coleman Pde",
    "sg:city":"Syndal",
    "sg:classifiers":[
        {
            "category":"Professional",
            "subcategory":"Accounting & Tax Preparation",
            "type":"Services"
        }
    ],
    "sg:phone":"+61 3 9802 8373",
    "sg:postcode":"3149",
    "sg:province":"VIC",
    "sg:tags":[
        "accountant",
        "auditor"
    ],
    "wof:name":"Glover R J",
    "wof:placetype":"venue"
},
  "geometry": {"coordinates":[145.15182495100001,-37.8771133423],"type":"Point"}
}