{
  "type": "Feature",
  "properties": {
    "addr:full":"12 Waratah St Mona Vale NSW 2103",
    "addr:housenumber":"12",
    "addr:postcode":"2103",
    "addr:street":"Waratah St",
    "iso:country":"AU",
    "sg:address":"12 Waratah St",
    "sg:city":"Mona Vale",
    "sg:classifiers":[
        {
            "category":"Personal",
            "subcategory":"Beauty Salon",
            "type":"Services"
        }
    ],
    "sg:phone":"+61 2 9979 7138",
    "sg:postcode":"2103",
    "sg:province":"NSW",
    "sg:tags":[
        "hairdresser"
    ],
    "wof:name":"John Brennan Haircutting Shop",
    "wof:placetype":"venue"
},
  "geometry": {"coordinates":[151.30258178700001,-33.6775474548],"type":"Point"}
}