{
  "type": "Feature",
  "properties": {
    "iso:country":"AU",
    "sg:address":"Cnr Sackville & Post Office Rds",
    "sg:city":"Ebenezer",
    "sg:classifiers":[
        {
            "category":"Wholesale",
            "subcategory":"Farm Supplies",
            "type":"Manufacturing & Wholesale Goods"
        }
    ],
    "sg:phone":"+61 2 4579 9285",
    "sg:postcode":"2756",
    "sg:province":"NSW",
    "sg:tags":[
        "feed",
        "supplement",
        "stock"
    ],
    "wof:name":"Robank Manufacturing",
    "wof:placetype":"venue"
},
  "geometry": {"coordinates":[150.88104248100001,-33.5259361267],"type":"Point"}
}