{
  "type": "Feature",
  "properties": {
    "addr:full":"633 Pacific Hwy Belmont NSW 2280",
    "addr:housenumber":"633",
    "addr:postcode":"2280",
    "addr:street":"Pacific Hwy",
    "iso:country":"AU",
    "sg:address":"633 Pacific Hwy",
    "sg:city":"Belmont",
    "sg:classifiers":[
        {
            "category":"Government",
            "subcategory":"Fire Station",
            "type":"Public Place"
        }
    ],
    "sg:phone":"+61 2 4945 2478",
    "sg:postcode":"2280",
    "sg:province":"NSW",
    "sg:tags":[
        "brigade"
    ],
    "wof:name":"Fire Brigades-NSW",
    "wof:placetype":"venue"
},
  "geometry": {"coordinates":[151.659622192,-33.0382080078],"type":"Point"}
}