{
  "type": "Feature",
  "properties": {
    "iso:country":"AU",
    "sg:address":"86 King George Pde",
    "sg:city":"Forster",
    "sg:classifiers":[
        {
            "category":"Building & Trades",
            "subcategory":"Landscaping Services",
            "type":"Services"
        }
    ],
    "sg:phone":"+61 2 6555 9044",
    "sg:postcode":"2428",
    "sg:province":"NSW",
    "sg:tags":[
        "consultant"
    ],
    "wof:name":"Integral Building Investigations",
    "wof:placetype":"venue"
},
  "geometry": {"coordinates":[152.520554,-32.215382],"type":"Point"}
}