{
  "type": "Feature",
  "properties": {
    "iso:country":"AU",
    "sg:address":"77 Miles St",
    "sg:city":"Mt Isa",
    "sg:classifiers":[
        {
            "category":"Building & Trades",
            "subcategory":"Construction",
            "type":"Services"
        }
    ],
    "sg:phone":"+61 7 4743 9040",
    "sg:postcode":"4825",
    "sg:province":"QLD",
    "sg:tags":[
        "scaffolding"
    ],
    "wof:name":"Isa Equipment Hire",
    "wof:placetype":"venue"
},
  "geometry": {"coordinates":[139.49305699999999,-20.719955],"type":"Point"}
}