{
  "type": "Feature",
  "properties": {
    "addr:full":"Lot 51 Mourilyan Harbour Rd Mourilyan QLD 4858",
    "addr:postcode":"4858",
    "addr:street":"Mourilyan Harbour Rd",
    "iso:country":"AU",
    "sg:address":"Lot 51 Mourilyan Harbour Rd",
    "sg:city":"Mourilyan",
    "sg:classifiers":[
        {
            "category":"Recreation",
            "subcategory":"Fishing",
            "type":"Entertainment"
        }
    ],
    "sg:phone":"+61 7 4063 2322",
    "sg:postcode":"4858",
    "sg:province":"QLD",
    "sg:tags":[
        "bait"
    ],
    "wof:name":"Timms Harbourside Bait & Tackle",
    "wof:placetype":"venue"
},
  "geometry": {"coordinates":[146.05584716800001,-17.5899524689],"type":"Point"}
}