{
  "type": "Feature",
  "properties": {
    "iso:country":"AU",
    "sg:address":"2 Travelga Vale Ave",
    "sg:city":"East Wellington Point",
    "sg:classifiers":[
        {
            "category":"Building & Trades",
            "subcategory":"Construction",
            "type":"Services"
        }
    ],
    "sg:phone":"+61 417 774 751",
    "sg:postcode":"4160",
    "sg:province":"QLD",
    "sg:tags":[
        "concrete",
        "contractor"
    ],
    "wof:name":"Shane Cameron Concreting",
    "wof:placetype":"venue"
},
  "geometry": {"coordinates":[153.234817505,-27.497625351],"type":"Point"}
}