{
  "type": "Feature",
  "properties": {
    "iso:country":"AU",
    "sg:address":"Level 1, 812 Pittwater Rd",
    "sg:city":"Dee Why",
    "sg:classifiers":[
        {
            "category":"Health Services",
            "subcategory":"Health Practitioner",
            "type":"Services"
        }
    ],
    "sg:phone":"+61 2 9984 9040",
    "sg:postcode":"2099",
    "sg:province":"NSW",
    "sg:tags":[
        "physiotherapist"
    ],
    "wof:name":"Wajon Anne Dr",
    "wof:placetype":"venue"
},
  "geometry": {"coordinates":[151.282592773,-33.756526947],"type":"Point"}
}