{
  "type": "Feature",
  "properties": {
    "iso:country":"AU",
    "sg:address":"1 Inglis Ave",
    "sg:city":"Mirboo North",
    "sg:classifiers":[
        {
            "category":"Retail",
            "subcategory":"Storage",
            "type":"Services"
        }
    ],
    "sg:phone":"+61 3 5668 2422",
    "sg:postcode":"3871",
    "sg:province":"VIC",
    "sg:tags":[
        "removal",
        "furniture"
    ],
    "wof:name":"Mirboo North Self Storage",
    "wof:placetype":"venue"
},
  "geometry": {"coordinates":[146.16444397000001,-38.4007797241],"type":"Point"}
}