{
  "type": "Feature",
  "properties": {
    "addr:full":"294 High St Northcote VIC 3070",
    "addr:housenumber":"294",
    "addr:postcode":"3070",
    "addr:street":"High St",
    "iso:country":"AU",
    "sg:address":"294 High St",
    "sg:city":"Northcote",
    "sg:classifiers":[
        {
            "category":"Personal",
            "subcategory":"Beauty Salon",
            "type":"Services"
        }
    ],
    "sg:phone":"+61 3 9489 2014",
    "sg:postcode":"3070",
    "sg:province":"VIC",
    "sg:tags":[
        "hairdresser"
    ],
    "wof:name":"Shades &#039;N Shapes",
    "wof:placetype":"venue"
},
  "geometry": {"coordinates":[144.998749,-37.771481],"type":"Point"}
}