{
  "type": "Feature",
  "properties": {
    "iso:country":"AU",
    "sg:address":"587 Magill Rd",
    "sg:city":"Magill",
    "sg:classifiers":[
        {
            "category":"Shopping",
            "type":"Retail Goods"
        }
    ],
    "sg:phone":"+61 8 8333 3144",
    "sg:postcode":"5072",
    "sg:province":"SA",
    "sg:tags":[
        "new age",
        "product"
    ],
    "wof:name":"A Life Abundant",
    "wof:placetype":"venue"
},
  "geometry": {"coordinates":[138.67379760700001,-34.9130134583],"type":"Point"}
}