{
  "type": "Feature",
  "properties": {
    "addr:full":"103 Lennox St Richmond NSW 2753",
    "addr:housenumber":"103",
    "addr:postcode":"2753",
    "addr:street":"Lennox St",
    "iso:country":"AU",
    "sg:address":"103 Lennox St",
    "sg:city":"Richmond",
    "sg:classifiers":[
        {
            "category":"Professional",
            "subcategory":"Accounting & Tax Preparation",
            "type":"Services"
        }
    ],
    "sg:phone":"+61 2 4578 1366",
    "sg:postcode":"2753",
    "sg:province":"NSW",
    "sg:tags":[
        "consultant",
        "taxation"
    ],
    "wof:name":"Eric B. Henderson & Co",
    "wof:placetype":"venue"
},
  "geometry": {"coordinates":[150.749267578,-33.5996437073],"type":"Point"}
}