{
  "type": "Feature",
  "properties": {
    "iso:country":"AU",
    "sg:address":"25 Carinya Ave",
    "sg:city":"Mascot",
    "sg:classifiers":[
        {
            "category":"Education",
            "subcategory":"Kindergarten",
            "type":"Public Place"
        }
    ],
    "sg:phone":"+61 2 9317 5005",
    "sg:postcode":"2020",
    "sg:province":"NSW",
    "sg:tags":[
        "pre-schools"
    ],
    "wof:name":"Kindisaurus Child Care Centre",
    "wof:placetype":"venue"
},
  "geometry": {"coordinates":[151.193649292,-33.9234046936],"type":"Point"}
}