{
  "type": "Feature",
  "properties": {
    "iso:country":"AU",
    "sg:address":"616 Ingham Rd",
    "sg:city":"Bohle",
    "sg:classifiers":[
        {
            "category":"Farming",
            "subcategory":"Fish & Marine Products",
            "type":"Manufacturing & Wholesale Goods"
        }
    ],
    "sg:phone":"+61 7 4774 6366",
    "sg:postcode":"4818",
    "sg:province":"QLD",
    "sg:tags":[
        "bitumen"
    ],
    "wof:name":"BP Bitumen",
    "wof:placetype":"venue"
},
  "geometry": {"coordinates":[146.74194299999999,-19.262253],"type":"Point"}
}