{
  "type": "Feature",
  "properties": {
    "addr:full":"8th Floor 183 Macquarie St Sydney NSW 2000",
    "addr:housenumber":"183",
    "addr:postcode":"2000",
    "addr:street":"Macquarie St",
    "iso:country":"AU",
    "sg:address":"8th Floor 183 Macquarie St",
    "sg:city":"Sydney",
    "sg:classifiers":[
        {
            "category":"Health Services",
            "subcategory":"Dentist",
            "type":"Services"
        }
    ],
    "sg:phone":"+61 2 9221 3544",
    "sg:postcode":"2000",
    "sg:province":"NSW",
    "wof:name":"Bone John G & Heard F M",
    "wof:placetype":"venue"
},
  "geometry": {"coordinates":[151.21220398,-33.8670196533],"type":"Point"}
}