{
  "type": "Feature",
  "properties": {
    "addr:full":"91 Peter St Wagga Wagga NSW 2650",
    "addr:housenumber":"91",
    "addr:postcode":"2650",
    "addr:street":"Peter St",
    "iso:country":"AU",
    "sg:address":"91 Peter St",
    "sg:city":"Wagga Wagga",
    "sg:classifiers":[
        {
            "category":"Personal",
            "subcategory":"Tanning Parlor",
            "type":"Services"
        }
    ],
    "sg:phone":"+61 2 6921 1488",
    "sg:postcode":"2650",
    "sg:province":"NSW",
    "sg:tags":[
        "solarium"
    ],
    "wof:name":"Cottage Hair Salon The",
    "wof:placetype":"venue"
},
  "geometry": {"coordinates":[147.36845398,-35.1136817932],"type":"Point"}
}