{
  "type": "Feature",
  "properties": {
    "iso:country":"AU",
    "sg:address":"Glory Rd",
    "sg:city":"Kangarilla",
    "sg:classifiers":[
        {
            "category":"Wholesale",
            "subcategory":"Farm Supplies",
            "type":"Manufacturing & Wholesale Goods"
        }
    ],
    "sg:phone":"+61 418 854 486",
    "sg:postcode":"5157",
    "sg:province":"SA",
    "sg:tags":[
        "feed",
        "supplement",
        "stock"
    ],
    "wof:name":"Tuckerbox Stock Feeds",
    "wof:placetype":"venue"
},
  "geometry": {"coordinates":[138.654006958,-35.150806427],"type":"Point"}
}