{
  "type": "Feature",
  "properties": {
    "addr:full":"17 Chambers Rd Altona North VIC 3025",
    "addr:housenumber":"17",
    "addr:postcode":"3025",
    "addr:street":"Chambers Rd",
    "iso:country":"AU",
    "sg:address":"17 Chambers Rd",
    "sg:city":"Altona North",
    "sg:classifiers":[
        {
            "category":"Wholesale",
            "subcategory":"Medical Equipment & Supplies",
            "type":"Manufacturing & Wholesale Goods"
        }
    ],
    "sg:phone":"+61 3 9391 3552",
    "sg:postcode":"3025",
    "sg:province":"VIC",
    "sg:tags":[
        "dental"
    ],
    "wof:name":"Australian Dental Engineering & Manufacture",
    "wof:placetype":"venue"
},
  "geometry": {"coordinates":[144.841095,-37.843166],"type":"Point"}
}