{
  "type": "Feature",
  "properties": {
    "iso:country":"AU",
    "sg:address":"17 Macedon St",
    "sg:city":"Sunbury",
    "sg:classifiers":[
        {
            "category":"Health Services",
            "subcategory":"Dentist",
            "type":"Services"
        }
    ],
    "sg:phone":"+61 3 9744 3677",
    "sg:postcode":"3429",
    "sg:province":"VIC",
    "wof:name":"Macedon St. Dental Group",
    "wof:placetype":"venue"
},
  "geometry": {"coordinates":[144.73301696799999,-37.5780944824],"type":"Point"}
}