{
  "type": "Feature",
  "properties": {
    "iso:country":"AU",
    "sg:address":"5/ 316 Onslow Rd",
    "sg:city":"Shenton Park",
    "sg:classifiers":[
        {
            "category":"Health Services",
            "subcategory":"Health Practitioner",
            "type":"Services"
        }
    ],
    "sg:phone":"+61 8 9388 6834",
    "sg:postcode":"6008",
    "sg:province":"WA",
    "sg:tags":[
        "psychologist"
    ],
    "wof:name":"Shenton Park Psychology Services",
    "wof:placetype":"venue"
},
  "geometry": {"coordinates":[115.80735015899999,-31.9606552124],"type":"Point"}
}