{
  "type": "Feature",
  "properties": {
    "addr:full":"175 Pitt St Sydney NSW 2000",
    "addr:housenumber":"175",
    "addr:postcode":"2000",
    "addr:street":"Pitt St",
    "iso:country":"AU",
    "sg:address":"175 Pitt St",
    "sg:city":"Sydney",
    "sg:classifiers":[
        {
            "category":"Sports & Exercise",
            "subcategory":"Gym",
            "type":"Entertainment"
        }
    ],
    "sg:phone":"+61 2 9223 7600",
    "sg:postcode":"2000",
    "sg:province":"NSW",
    "sg:tags":[
        "health",
        "fitness"
    ],
    "wof:name":"Fitness First Pitt Street",
    "wof:placetype":"venue"
},
  "geometry": {"coordinates":[151.20814514200001,-33.8687782288],"type":"Point"}
}