{
  "type": "Feature",
  "properties": {
    "iso:country":"AU",
    "sg:address":"21 Lascelle Crt",
    "sg:city":"Eatons Hill",
    "sg:classifiers":[
        {
            "category":"Professional",
            "subcategory":"Art Services",
            "type":"Services"
        }
    ],
    "sg:phone":"+61 417 714 844",
    "sg:postcode":"4037",
    "sg:province":"QLD",
    "sg:tags":[
        "decorator",
        "painter"
    ],
    "wof:name":"MACO Painters & Decorators",
    "wof:placetype":"venue"
},
  "geometry": {"coordinates":[152.926956,-27.332651],"type":"Point"}
}