{
  "type": "Feature",
  "properties": {
    "iso:country":"AU",
    "sg:address":"12 Ian Oliver Drv",
    "sg:city":"Waikerie",
    "sg:classifiers":[
        {
            "category":"Retail",
            "subcategory":"Auto Repair",
            "type":"Services"
        }
    ],
    "sg:phone":"+61 8 8541 3641",
    "sg:postcode":"5330",
    "sg:province":"SA",
    "sg:tags":[
        "beater",
        "painter",
        "panel"
    ],
    "wof:name":"Waikerie Crash Pty Ltd",
    "wof:placetype":"venue"
},
  "geometry": {"coordinates":[139.988082886,-34.1808929443],"type":"Point"}
}