{
  "type": "Feature",
  "properties": {
    "iso:country":"AU",
    "sg:address":"36 Bungil St",
    "sg:city":"Roma",
    "sg:classifiers":[
        {
            "category":"Retail",
            "subcategory":"Funeral Services",
            "type":"Services"
        }
    ],
    "sg:phone":"+61 7 4622 6486",
    "sg:postcode":"4455",
    "sg:province":"QLD",
    "sg:tags":[
        "director"
    ],
    "wof:name":"Maranoa Funeral Service",
    "wof:placetype":"venue"
},
  "geometry": {"coordinates":[148.78805542000001,-26.5693073273],"type":"Point"}
}