{
  "type": "Feature",
  "properties": {
    "addr:full":"2 Cole Crs Coburg East VIC 3058",
    "addr:housenumber":"2",
    "addr:postcode":"3058",
    "addr:street":"Cole Crs",
    "iso:country":"AU",
    "sg:address":"2 Cole Crs",
    "sg:city":"Coburg East",
    "sg:classifiers":[
        {
            "category":"Shopping",
            "subcategory":"Musical Instruments",
            "type":"Retail Goods"
        }
    ],
    "sg:phone":"+61 3 9386 7108",
    "sg:postcode":"3058",
    "sg:province":"VIC",
    "sg:tags":[
        "musician",
        "agent"
    ],
    "wof:name":"Kaleidoscope Music",
    "wof:placetype":"venue"
},
  "geometry": {"coordinates":[144.977096558,-37.7481307983],"type":"Point"}
}