{
  "type": "Feature",
  "properties": {
    "addr:full":"Unit 7 Bridge Link Centre 55 Links Ave North Eagle Farm QLD 4009",
    "addr:housenumber":"7;55",
    "addr:postcode":"4009",
    "addr:street":"Bridge Link;Links Ave North",
    "iso:country":"AU",
    "sg:address":"Unit 7 Bridge Link Centre 55 Links Ave",
    "sg:city":"North Eagle Farm",
    "sg:classifiers":[
        {
            "category":"Building & Trades",
            "subcategory":"Pest Control",
            "type":"Services"
        }
    ],
    "sg:phone":"+61 7 3268 2252",
    "sg:postcode":"4009",
    "sg:province":"QLD",
    "sg:tags":[
        "equipment",
        "insect"
    ],
    "wof:name":"Rentokil Pest Control",
    "wof:placetype":"venue"
},
  "geometry": {"coordinates":[153.088165283,-27.4319915771],"type":"Point"}
}