{
  "type": "Feature",
  "properties": {
    "addr:full":"177 Glen Osmond Rd Frewville SA 5063",
    "addr:housenumber":"177",
    "addr:postcode":"5063",
    "addr:street":"Glen Osmond Rd",
    "iso:country":"AU",
    "sg:address":"177 Glen Osmond Rd",
    "sg:city":"Frewville",
    "sg:classifiers":[
        {
            "category":"Food & Beverages",
            "subcategory":"Supermarket",
            "type":"Retail Goods"
        }
    ],
    "sg:phone":"+61 8 8433 0888",
    "sg:postcode":"5063",
    "sg:province":"SA",
    "sg:tags":[
        "grocery",
        "store"
    ],
    "wof:name":"Foodland Supermarkets",
    "wof:placetype":"venue"
},
  "geometry": {"coordinates":[138.626464844,-34.9469337463],"type":"Point"}
}