{
  "type": "Feature",
  "properties": {
    "addr:full":"17 Nicholls Crt Mordialloc VIC 3195",
    "addr:housenumber":"17",
    "addr:postcode":"3195",
    "addr:street":"Nicholls Crt",
    "iso:country":"AU",
    "sg:address":"17 Nicholls Crt",
    "sg:city":"Mordialloc",
    "sg:classifiers":[
        {
            "category":"Retail",
            "subcategory":"Auto Repair",
            "type":"Services"
        }
    ],
    "sg:phone":"+61 3 9580 9689",
    "sg:postcode":"3195",
    "sg:province":"VIC",
    "sg:tags":[
        "body",
        "motor",
        "trimmer"
    ],
    "wof:name":"Ashlor Trimming Service Pty Ltd",
    "wof:placetype":"venue"
},
  "geometry": {"coordinates":[145.104446411,-37.9913482666],"type":"Point"}
}