{
  "type": "Feature",
  "properties": {
    "iso:country":"AU",
    "sg:address":"4/ 84 Hoskins St",
    "sg:city":"Mitchell",
    "sg:classifiers":[
        {
            "category":"Manufacturing",
            "subcategory":"Rubber & Plastics",
            "type":"Manufacturing & Wholesale Goods"
        }
    ],
    "sg:phone":"+61 2 6242 9163",
    "sg:postcode":"2911",
    "sg:province":"ACT",
    "sg:tags":[
        "fabricator"
    ],
    "wof:name":"Sign Design",
    "wof:placetype":"venue"
},
  "geometry": {"coordinates":[149.138748169,-35.2101325989],"type":"Point"}
}