{
  "type": "Feature",
  "properties": {
    "addr:full":"509 High Street Rd Mt Waverley VIC 3149",
    "addr:housenumber":"509",
    "addr:postcode":"3149",
    "addr:street":"High Street Rd",
    "iso:country":"AU",
    "sg:address":"509 High Street Rd",
    "sg:city":"Mt Waverley",
    "sg:classifiers":[
        {
            "category":"Personal",
            "subcategory":"Beauty Salon",
            "type":"Services"
        }
    ],
    "sg:phone":"+61 3 9807 2129",
    "sg:postcode":"3149",
    "sg:province":"VIC",
    "sg:tags":[
        "hairdresser"
    ],
    "wof:name":"Le Funk Studio",
    "wof:placetype":"venue"
},
  "geometry": {"coordinates":[145.13693237300001,-37.8706855774],"type":"Point"}
}