{
  "type": "Feature",
  "properties": {
    "addr:full":"7 Garden Crs Port Macquarie NSW 2444",
    "addr:housenumber":"7",
    "addr:postcode":"2444",
    "addr:street":"Garden Crs",
    "iso:country":"AU",
    "sg:address":"7 Garden Crs",
    "sg:city":"Port Macquarie",
    "sg:classifiers":[
        {
            "category":"Health Services",
            "subcategory":"Nursing And Care Facility",
            "type":"Services"
        }
    ],
    "sg:phone":"+61 2 6583 5249",
    "sg:postcode":"2444",
    "sg:province":"NSW",
    "sg:tags":[
        "home"
    ],
    "wof:name":"The Port Macquarie Garden Lodge",
    "wof:placetype":"venue"
},
  "geometry": {"coordinates":[152.90817300000001,-31.4296],"type":"Point"}
}