{
  "type": "Feature",
  "properties": {
    "addr:full":"5/ 5 Canley Vale Rd Wetherill Park NSW 2164",
    "addr:housenumber":"/ 5",
    "addr:postcode":"2164",
    "addr:street":"Canley Vale Rd",
    "iso:country":"AU",
    "sg:address":"5/ 5 Canley Vale Rd",
    "sg:city":"Wetherill Park",
    "sg:classifiers":[
        {
            "category":"Transit Center",
            "subcategory":"Freight",
            "type":"Transportation"
        }
    ],
    "sg:phone":"+61 2 9756 5713",
    "sg:postcode":"2164",
    "sg:province":"NSW",
    "sg:tags":[
        "equipment",
        "transport",
        "road",
        "vehicle"
    ],
    "wof:name":"Heavy Duty Transport Equipment",
    "wof:placetype":"venue"
},
  "geometry": {"coordinates":[150.89976501500001,-33.8481025696],"type":"Point"}
}