{
  "type": "Feature",
  "properties": {
    "addr:full":"Unit 1/ 12 Accolade Ave Morisset NSW 2264",
    "addr:housenumber":"12",
    "addr:postcode":"2264",
    "addr:street":"Accolade Ave",
    "iso:country":"AU",
    "sg:address":"Unit 1/ 12 Accolade Ave",
    "sg:city":"Morisset",
    "sg:classifiers":[
        {
            "category":"Wholesale",
            "subcategory":"Auto Parts",
            "type":"Manufacturing & Wholesale Goods"
        }
    ],
    "sg:phone":"+61 2 4973 1941",
    "sg:postcode":"2264",
    "sg:province":"NSW",
    "sg:tags":[
        "recyclers"
    ],
    "wof:name":"Morisset Auto Dismantlers",
    "wof:placetype":"venue"
},
  "geometry": {"coordinates":[151.47314499999999,-33.119156],"type":"Point"}
}