{
  "type": "Feature",
  "properties": {
    "addr:full":"8 Crossley St Melbourne VIC 3000",
    "addr:housenumber":"8",
    "addr:postcode":"3000",
    "addr:street":"Crossley St",
    "iso:country":"AU",
    "sg:address":"8 Crossley St",
    "sg:city":"Melbourne",
    "sg:classifiers":[
        {
            "category":"Communications",
            "subcategory":"Film & Video Production",
            "type":"Services"
        }
    ],
    "sg:phone":"+61 3 9662 1350",
    "sg:postcode":"3000",
    "sg:province":"VIC",
    "sg:tags":[
        "made",
        "clothing",
        "custom"
    ],
    "wof:name":"Charles Edward Master Shirtmaker",
    "wof:placetype":"venue"
},
  "geometry": {"coordinates":[144.97137451200001,-37.8115997314],"type":"Point"}
}