{
  "type": "Feature",
  "properties": {
    "addr:full":"Central Ave Nowra South NSW 2541",
    "addr:postcode":"2541",
    "addr:street":"Central Ave",
    "iso:country":"AU",
    "sg:address":"Central Ave",
    "sg:city":"Nowra South",
    "sg:classifiers":[
        {
            "category":"Home & Garden",
            "subcategory":"Carpets & Floor Coverings",
            "type":"Retail Goods"
        }
    ],
    "sg:phone":"+61 2 4423 2222",
    "sg:postcode":"2541",
    "sg:province":"NSW",
    "sg:tags":[
        "mattress"
    ],
    "wof:name":"Forty Winks",
    "wof:placetype":"venue"
},
  "geometry": {"coordinates":[150.59349060100001,-34.9131202698],"type":"Point"}
}