{
  "type": "Feature",
  "properties": {
    "addr:full":"24 Crowther St Windsor QLD 4030",
    "addr:housenumber":"24",
    "addr:postcode":"4030",
    "addr:street":"Crowther St",
    "iso:country":"AU",
    "sg:address":"24 Crowther St",
    "sg:city":"Windsor",
    "sg:classifiers":[
        {
            "category":"Professional",
            "subcategory":"Computer Services",
            "type":"Services"
        }
    ],
    "sg:phone":"+61 410 823 297",
    "sg:postcode":"4030",
    "sg:province":"QLD",
    "sg:tags":[
        "equipment",
        "networking",
        "installation"
    ],
    "wof:name":"Personalised Computers",
    "wof:placetype":"venue"
},
  "geometry": {"coordinates":[153.026535,-27.425703],"type":"Point"}
}