{
  "type": "Feature",
  "properties": {
    "addr:full":"Shop G27 West Centre 1260 Hay St West Perth WA 6005",
    "addr:housenumber":"g27;1260",
    "addr:postcode":"6005",
    "addr:street":"West Centre;Hay St",
    "iso:country":"AU",
    "sg:address":"Shop G27 West Centre 1260 Hay St",
    "sg:city":"West Perth",
    "sg:classifiers":[
        {
            "category":"Shopping",
            "subcategory":"Clothing, Apparel, & Fashions",
            "type":"Retail Goods"
        }
    ],
    "sg:phone":"+61 8 9481 5351",
    "sg:postcode":"6005",
    "sg:province":"WA",
    "sg:tags":[
        "menswear"
    ],
    "wof:name":"Stags Menswear",
    "wof:placetype":"venue"
},
  "geometry": {"coordinates":[115.840118408,-31.94789505],"type":"Point"}
}