{
  "type": "Feature",
  "properties": {
    "addr:full":"35 Central Ave Chipping Norton NSW 2170",
    "addr:housenumber":"35",
    "addr:postcode":"2170",
    "addr:street":"Central Ave",
    "iso:country":"AU",
    "sg:address":"35 Central Ave",
    "sg:city":"Chipping Norton",
    "sg:classifiers":[
        {
            "category":"Education",
            "subcategory":"Kindergarten",
            "type":"Public Place"
        }
    ],
    "sg:phone":"+61 2 9755 3480",
    "sg:postcode":"2170",
    "sg:province":"NSW",
    "sg:tags":[
        "pre-schools"
    ],
    "wof:name":"Chipping Norton Child Care Centre",
    "wof:placetype":"venue"
},
  "geometry": {"coordinates":[150.959915161,-33.9107666016],"type":"Point"}
}