{
  "type": "Feature",
  "properties": {
    "iso:country":"AU",
    "sg:address":"Unit 28, Pacific Centre, 223",
    "sg:city":"Calum Road, Sunnybank Hills",
    "sg:classifiers":[
        {
            "category":"Education",
            "subcategory":"Special Training",
            "type":"Public Place"
        }
    ],
    "sg:phone":"+61 7 3272 3700",
    "sg:postcode":"4109",
    "sg:province":"QLD",
    "sg:tags":[
        "tuition-educational"
    ],
    "wof:name":"Astute Tuition",
    "wof:placetype":"venue"
},
  "geometry": {"coordinates":[153.054397583,-27.609708786],"type":"Point"}
}