{
  "type": "Feature",
  "properties": {
    "addr:full":"234 Main North Rd Clare SA 5453",
    "addr:housenumber":"234",
    "addr:postcode":"5453",
    "addr:street":"Main North Rd",
    "iso:country":"AU",
    "sg:address":"234 Main North Rd",
    "sg:city":"Clare",
    "sg:classifiers":[
        {
            "category":"Professional",
            "subcategory":"Printing & Photocopies",
            "type":"Services"
        }
    ],
    "sg:phone":"+61 8 8842 2851",
    "sg:postcode":"5453",
    "sg:province":"SA",
    "sg:tags":[
        "embroidery"
    ],
    "wof:name":"Logo Embroidery",
    "wof:placetype":"venue"
},
  "geometry": {"coordinates":[138.61137400000001,-33.832748],"type":"Point"}
}