{
  "type": "Feature",
  "properties": {
    "iso:country":"AU",
    "sg:address":"73 Point Cartwright Drv",
    "sg:city":"Buddina",
    "sg:classifiers":[
        {
            "category":"Sports & Exercise",
            "subcategory":"Gym",
            "type":"Entertainment"
        }
    ],
    "sg:phone":"+61 7 5444 4671",
    "sg:postcode":"4575",
    "sg:province":"QLD",
    "sg:tags":[
        "meditation"
    ],
    "wof:name":"Australian School of Meditation",
    "wof:placetype":"venue"
},
  "geometry": {"coordinates":[153.129715,-26.701469],"type":"Point"}
}