{
  "type": "Feature",
  "properties": {
    "addr:full":"10 Leigh St Burswood WA 6100",
    "addr:housenumber":"10",
    "addr:postcode":"6100",
    "addr:street":"Leigh St",
    "iso:country":"AU",
    "sg:address":"10 Leigh St",
    "sg:city":"Burswood",
    "sg:classifiers":[
        {
            "category":"Health Services",
            "subcategory":"Nursing And Care Facility",
            "type":"Services"
        }
    ],
    "sg:phone":"+61 8 9355 3455",
    "sg:postcode":"6100",
    "sg:province":"WA",
    "sg:tags":[
        "home"
    ],
    "wof:name":"Aegis Health Care Group",
    "wof:placetype":"venue"
},
  "geometry": {"coordinates":[115.899452209,-31.964881897],"type":"Point"}
}