{
  "type": "Feature",
  "properties": {
    "addr:full":"4 Noelana St Sunnybank Hills QLD 4109",
    "addr:housenumber":"4",
    "addr:postcode":"4109",
    "addr:street":"Noelana St",
    "iso:country":"AU",
    "sg:address":"4 Noelana St",
    "sg:city":"Sunnybank Hills",
    "sg:classifiers":[
        {
            "category":"Health Services",
            "subcategory":"Health Practitioner",
            "type":"Services"
        }
    ],
    "sg:phone":"+61 7 3273 5022",
    "sg:postcode":"4109",
    "sg:province":"QLD",
    "sg:tags":[
        "physiotherapist"
    ],
    "wof:name":"A Multi Health Centre",
    "wof:placetype":"venue"
},
  "geometry": {"coordinates":[153.058425903,-27.5980091095],"type":"Point"}
}