{
  "type": "Feature",
  "properties": {
    "iso:country":"AU",
    "sg:address":"18 Pradella St",
    "sg:city":"Darra",
    "sg:classifiers":[
        {
            "category":"Home & Garden",
            "subcategory":"Hardware",
            "type":"Retail Goods"
        }
    ],
    "sg:phone":"+61 7 3714 9821",
    "sg:postcode":"4076",
    "sg:province":"QLD",
    "sg:tags":[
        "nut",
        "bolt"
    ],
    "wof:name":"Brighton Best Socket Screw Mfg Pty Ltd",
    "wof:placetype":"venue"
},
  "geometry": {"coordinates":[152.95130920400001,-27.5763721466],"type":"Point"}
}