{
  "type": "Feature",
  "properties": {
    "iso:country":"AU",
    "sg:address":"Suite 84 85 Plaistowe La",
    "sg:city":"West Perth",
    "sg:classifiers":[
        {
            "category":"Building & Trades",
            "subcategory":"Construction",
            "type":"Services"
        }
    ],
    "sg:phone":"+61 8 9226 4444",
    "sg:postcode":"6005",
    "sg:province":"WA",
    "sg:tags":[
        "contractor"
    ],
    "wof:name":"Distinction Homes",
    "wof:placetype":"venue"
},
  "geometry": {"coordinates":[115.845596313,-31.9437980652],"type":"Point"}
}