{
  "type": "Feature",
  "properties": {
    "iso:country":"AU",
    "sg:address":"83 Cook Ave",
    "sg:city":"Hillarys",
    "sg:classifiers":[
        {
            "category":"Real Estate",
            "subcategory":"Architect",
            "type":"Services"
        }
    ],
    "sg:phone":"+61 418 959 808",
    "sg:postcode":"6025",
    "sg:province":"WA",
    "sg:tags":[
        "building",
        "designer"
    ],
    "wof:name":"Home Design Pty Ltd",
    "wof:placetype":"venue"
},
  "geometry": {"coordinates":[115.752418518,-31.8021202087],"type":"Point"}
}