{
  "type": "Feature",
  "properties": {
    "addr:full":"53 Kinross St Bendigo VIC 3550",
    "addr:housenumber":"53",
    "addr:postcode":"3550",
    "addr:street":"Kinross St",
    "iso:country":"AU",
    "sg:address":"53 Kinross St",
    "sg:city":"Bendigo",
    "sg:classifiers":[
        {
            "category":"Retail",
            "subcategory":"Auto Repair",
            "type":"Services"
        }
    ],
    "sg:phone":"+61 3 5442 2369",
    "sg:postcode":"3550",
    "sg:province":"VIC",
    "sg:tags":[
        "fuel",
        "petrol",
        "injection"
    ],
    "wof:name":"Heines Auto Care",
    "wof:placetype":"venue"
},
  "geometry": {"coordinates":[144.26289367699999,-36.7401657104],"type":"Point"}
}