{
  "type": "Feature",
  "properties": {
    "addr:full":"Cnr Kingtel & Delta Sts Geebung QLD 4034",
    "addr:postcode":"4034",
    "addr:street":"Cnr Kingtel &;Sts",
    "iso:country":"AU",
    "sg:address":"Cnr Kingtel & Delta Sts",
    "sg:city":"Geebung",
    "sg:classifiers":[
        {
            "category":"Fast Food",
            "type":"Food & Drink"
        }
    ],
    "sg:phone":"+61 7 3265 1534",
    "sg:postcode":"4034",
    "sg:province":"QLD",
    "sg:tags":[
        "away",
        "take"
    ],
    "wof:name":"Factory Takeaway",
    "wof:placetype":"venue"
},
  "geometry": {"coordinates":[153.051514,-27.36771],"type":"Point"}
}