{
  "type": "Feature",
  "properties": {
    "addr:full":"20 Atchison St St Leonards NSW 2065",
    "addr:housenumber":"20",
    "addr:postcode":"2065",
    "addr:street":"Atchison St",
    "iso:country":"AU",
    "sg:address":"20 Atchison St",
    "sg:city":"St Leonards",
    "sg:classifiers":[
        {
            "category":"Communications",
            "subcategory":"Newspaper",
            "type":"Services"
        }
    ],
    "sg:phone":"+61 1800 622 800",
    "sg:postcode":"2065",
    "sg:province":"NSW",
    "sg:tags":[
        "whiteboards",
        "chalkboard"
    ],
    "wof:name":"Electroboard",
    "wof:placetype":"venue"
},
  "geometry": {"coordinates":[151.196777344,-33.8227577209],"type":"Point"}
}