{
  "type": "Feature",
  "properties": {
    "iso:country":"AU",
    "sg:address":"37 Midelton Ave",
    "sg:city":"North Bondi",
    "sg:classifiers":[
        {
            "category":"Building & Trades",
            "subcategory":"Cleaning & Sanitation",
            "type":"Services"
        }
    ],
    "sg:phone":"+61 2 9130 3462",
    "sg:postcode":"2026",
    "sg:province":"NSW",
    "sg:tags":[
        "window"
    ],
    "wof:name":"New-Era Window Cleaning",
    "wof:placetype":"venue"
},
  "geometry": {"coordinates":[151.277069092,-33.8837394714],"type":"Point"}
}