{
  "type": "Feature",
  "properties": {
    "addr:full":"2 Sullivan Rd Tallebudgera QLD 4228",
    "addr:housenumber":"2",
    "addr:postcode":"4228",
    "addr:street":"Sullivan Rd",
    "iso:country":"AU",
    "sg:address":"2 Sullivan Rd",
    "sg:city":"Tallebudgera",
    "sg:classifiers":[
        {
            "category":"Travel",
            "subcategory":"Hostel",
            "type":"Entertainment"
        }
    ],
    "sg:phone":"+61 7 5576 3559",
    "sg:postcode":"4228",
    "sg:province":"QLD",
    "sg:tags":[
        "home"
    ],
    "sg:website":"http://www.standrews.lcaq.com.au",
    "wof:name":"St Andrews Lutheran Aged Care",
    "wof:placetype":"venue"
},
  "geometry": {"coordinates":[153.43876648,-28.1206474304],"type":"Point"}
}