{
  "type": "Feature",
  "properties": {
    "addr:full":"Shop 2, 71 Pine Ave Mildura VIC 3500",
    "addr:housenumber":"shop;71",
    "addr:postcode":"3500",
    "addr:street":"Pine Ave",
    "iso:country":"AU",
    "sg:address":"Shop 2, 71 Pine Ave",
    "sg:city":"Mildura",
    "sg:classifiers":[
        {
            "category":"Home & Garden",
            "subcategory":"Building Materials",
            "type":"Retail Goods"
        }
    ],
    "sg:phone":"+61 3 5021 5644",
    "sg:postcode":"3500",
    "sg:province":"VIC",
    "sg:tags":[
        "decorative",
        "coating"
    ],
    "wof:name":"Granosite",
    "wof:placetype":"venue"
},
  "geometry": {"coordinates":[142.158294678,-34.1833381653],"type":"Point"}
}