{
  "type": "Feature",
  "properties": {
    "addr:full":"1/ 143 Industrial Rd Oak Flats NSW 2529",
    "addr:housenumber":"/ 143",
    "addr:postcode":"2529",
    "addr:street":"Industrial Rd",
    "iso:country":"AU",
    "sg:address":"1/ 143 Industrial Rd",
    "sg:city":"Oak Flats",
    "sg:classifiers":[
        {
            "category":"Wholesale",
            "subcategory":"Painting Supplies",
            "type":"Manufacturing & Wholesale Goods"
        }
    ],
    "sg:phone":"+61 2 4257 5785",
    "sg:postcode":"2529",
    "sg:province":"NSW",
    "sg:tags":[
        "painter"
    ],
    "wof:name":"Bristol Paint & Decorator Centres",
    "wof:placetype":"venue"
},
  "geometry": {"coordinates":[150.80563354500001,-34.565372467],"type":"Point"}
}