{
  "type": "Feature",
  "properties": {
    "iso:country":"AU",
    "sg:address":"48 Sandford St",
    "sg:city":"Mitchell",
    "sg:classifiers":[
        {
            "category":"Building & Trades",
            "subcategory":"Construction",
            "type":"Services"
        }
    ],
    "sg:phone":"+61 2 6162 1040",
    "sg:postcode":"2911",
    "sg:province":"ACT",
    "sg:tags":[
        "brick",
        "paving"
    ],
    "wof:name":"Big Kevin's Hire",
    "wof:placetype":"venue"
},
  "geometry": {"coordinates":[149.138061523,-35.2201461792],"type":"Point"}
}