{
  "type": "Feature",
  "properties": {
    "iso:country":"AU",
    "sg:address":"Lot 8 Byron Bay Rd",
    "sg:city":"Bangalow",
    "sg:classifiers":[
        {
            "category":"Professional",
            "subcategory":"Engineering",
            "type":"Services"
        }
    ],
    "sg:phone":"+61 2 6687 2199",
    "sg:postcode":"2479",
    "sg:province":"NSW",
    "sg:tags":[
        "consultant",
        "geotechnical",
        "engineer"
    ],
    "wof:name":"Pullman Craig Site Investigations Pty Ltd",
    "wof:placetype":"venue"
},
  "geometry": {"coordinates":[153.53077697800001,-28.6837234497],"type":"Point"}
}