{
  "type": "Feature",
  "properties": {
    "addr:full":"62 Graham St Kondinin WA 6367",
    "addr:housenumber":"62",
    "addr:postcode":"6367",
    "addr:street":"Graham St",
    "iso:country":"AU",
    "sg:address":"62 Graham St",
    "sg:city":"Kondinin",
    "sg:classifiers":[
        {
            "category":"Retail",
            "subcategory":"Auto Repair",
            "type":"Services"
        }
    ],
    "sg:phone":"+61 8 9889 1114",
    "sg:postcode":"6367",
    "sg:province":"WA",
    "sg:tags":[
        "repairer",
        "motor",
        "engineer"
    ],
    "wof:name":"Nelson A & M",
    "wof:placetype":"venue"
},
  "geometry": {"coordinates":[118.264877,-32.495422],"type":"Point"}
}