{
  "type": "Feature",
  "properties": {
    "iso:country":"AU",
    "sg:address":"3 Silflay Crt",
    "sg:city":"Warranwood",
    "sg:classifiers":[
        {
            "category":"Professional",
            "subcategory":"Management & Consulting",
            "type":"Services"
        }
    ],
    "sg:phone":"+61 3 9876 7118",
    "sg:postcode":"3134",
    "sg:province":"VIC",
    "sg:tags":[
        "consultant"
    ],
    "wof:name":"The Masterlogics Group Pty Ltd",
    "wof:placetype":"venue"
},
  "geometry": {"coordinates":[145.25514221200001,-37.7679214478],"type":"Point"}
}