{
  "type": "Feature",
  "properties": {
    "iso:country":"AU",
    "sg:address":"\"Brycris\" Kuhlmann Rd",
    "sg:city":"Freeling",
    "sg:classifiers":[
        {
            "category":"Arena",
            "subcategory":"Bull Ring",
            "type":"Entertainment"
        }
    ],
    "sg:phone":"+61 8 8525 2108",
    "sg:postcode":"5372",
    "sg:province":"SA",
    "sg:tags":[
        "breeder",
        "pig"
    ],
    "wof:name":"Schuster B R & C D",
    "wof:placetype":"venue"
},
  "geometry": {"coordinates":[138.82174682600001,-34.471118927],"type":"Point"}
}