{
  "type": "Feature",
  "properties": {
    "addr:full":"1644 Ipswich Rd Rocklea QLD 4106",
    "addr:housenumber":"1644",
    "addr:postcode":"4106",
    "addr:street":"Ipswich Rd",
    "iso:country":"AU",
    "sg:address":"1644 Ipswich Rd",
    "sg:city":"Rocklea",
    "sg:classifiers":[
        {
            "category":"Professional",
            "subcategory":"Art Services",
            "type":"Services"
        }
    ],
    "sg:phone":"+61 7 3275 3716",
    "sg:postcode":"4106",
    "sg:province":"QLD",
    "sg:tags":[
        "graphic",
        "designer"
    ],
    "wof:name":"Barkingchicken",
    "wof:placetype":"venue"
},
  "geometry": {"coordinates":[153.009765625,-27.5523376465],"type":"Point"}
}