{
  "type": "Feature",
  "properties": {
    "addr:full":"15 Tennyson Heights Crt Tennyson SA 5022",
    "addr:housenumber":"15",
    "addr:postcode":"5022",
    "addr:street":"Tennyson Heights Crt",
    "iso:country":"AU",
    "sg:address":"15 Tennyson Heights Crt",
    "sg:city":"Tennyson",
    "sg:classifiers":[
        {
            "category":"Real Estate",
            "subcategory":"Real Estate Agent",
            "type":"Services"
        }
    ],
    "sg:phone":"+61 418 806 933",
    "sg:postcode":"5022",
    "sg:province":"SA",
    "wof:name":"MacKenzie Valerie",
    "wof:placetype":"venue"
},
  "geometry": {"coordinates":[138.484466553,-34.8829536438],"type":"Point"}
}