{
  "type": "Feature",
  "properties": {
    "addr:full":"72 Browns Rd Kingston TAS 7050",
    "addr:housenumber":"72",
    "addr:postcode":"7050",
    "addr:street":"Browns Rd",
    "iso:country":"AU",
    "sg:address":"72 Browns Rd",
    "sg:city":"Kingston",
    "sg:classifiers":[
        {
            "category":"Wholesale",
            "subcategory":"Machinery & Supplies",
            "type":"Manufacturing & Wholesale Goods"
        }
    ],
    "sg:phone":"+61 3 6229 7437",
    "sg:postcode":"7050",
    "sg:province":"TAS",
    "sg:tags":[
        "equipment",
        "laboratory"
    ],
    "wof:name":"Crown Scientific",
    "wof:placetype":"venue"
},
  "geometry": {"coordinates":[147.31321700000001,-42.967636],"type":"Point"}
}