{
  "type": "Feature",
  "properties": {
    "addr:full":"Bass Hill Plaza, 753 Hume Hwy Bass Hill NSW 2197",
    "addr:housenumber":"753",
    "addr:postcode":"2197",
    "addr:street":"Hume Hwy",
    "iso:country":"AU",
    "sg:address":"Bass Hill Plaza, 753 Hume Hwy",
    "sg:city":"Bass Hill",
    "sg:classifiers":[
        {
            "category":"Building & Trades",
            "subcategory":"Locksmith",
            "type":"Services"
        }
    ],
    "sg:phone":"+61 2 9725 6335",
    "sg:postcode":"2197",
    "sg:province":"NSW",
    "sg:tags":[
        "lock"
    ],
    "wof:name":"Mister Minit",
    "wof:placetype":"venue"
},
  "geometry": {"coordinates":[150.99427800000001,-33.898136],"type":"Point"}
}