{
  "type": "Feature",
  "properties": {
    "iso:country":"AU",
    "sg:address":"31 Commens St",
    "sg:city":"Millmerran",
    "sg:classifiers":[
        {
            "category":"Fast Food",
            "type":"Food & Drink"
        }
    ],
    "sg:phone":"+61 7 4695 1179",
    "sg:postcode":"4357",
    "sg:province":"QLD",
    "sg:tags":[
        "away",
        "take"
    ],
    "wof:name":"Mac's Store",
    "wof:placetype":"venue"
},
  "geometry": {"coordinates":[151.266251,-27.878317],"type":"Point"}
}