{
  "type": "Feature",
  "properties": {
    "iso:country":"AU",
    "sg:address":"PO Box 1029",
    "sg:city":"Mt Barker",
    "sg:classifiers":[
        {
            "category":"Food & Beverages",
            "subcategory":"Meat & Fish",
            "type":"Retail Goods"
        }
    ],
    "sg:phone":"+61 8 8398 4144",
    "sg:postcode":"5251",
    "sg:province":"SA",
    "sg:tags":[
        "aquaculture"
    ],
    "wof:name":"Adam & Amos Abalone Foods",
    "wof:placetype":"venue"
},
  "geometry": {"coordinates":[138.85289001500001,-35.0617103577],"type":"Point"}
}