{
  "type": "Feature",
  "properties": {
    "addr:full":"126 Brunswick St Fortitude Valley QLD 4006",
    "addr:housenumber":"126",
    "addr:postcode":"4006",
    "addr:street":"Brunswick St",
    "iso:country":"AU",
    "sg:address":"126 Brunswick St",
    "sg:city":"Fortitude Valley",
    "sg:classifiers":[
        {
            "category":"Organizations",
            "subcategory":"Professional Association",
            "type":"Services"
        }
    ],
    "sg:phone":"+61 7 3252 7529",
    "sg:postcode":"4006",
    "sg:province":"QLD",
    "sg:tags":[
        "organisation",
        "business"
    ],
    "wof:name":"Australian Institute of Building (Queensland Chapter)",
    "wof:placetype":"venue"
},
  "geometry": {"coordinates":[153.03123474099999,-27.4552669525],"type":"Point"}
}