{
  "type": "Feature",
  "properties": {
    "addr:full":"110 Hassall St Wetherill Park NSW 2164",
    "addr:housenumber":"110",
    "addr:postcode":"2164",
    "addr:street":"Hassall St",
    "iso:country":"AU",
    "sg:address":"110 Hassall St",
    "sg:city":"Wetherill Park",
    "sg:classifiers":[
        {
            "category":"Professional",
            "type":"Services"
        }
    ],
    "sg:phone":"+61 2 9632 2444",
    "sg:postcode":"2164",
    "sg:province":"NSW",
    "sg:tags":[
        "transport"
    ],
    "wof:name":"Combined Distribution Management",
    "wof:placetype":"venue"
},
  "geometry": {"coordinates":[150.912765503,-33.839969635],"type":"Point"}
}