{
  "type": "Feature",
  "properties": {
    "addr:full":"5 Cormie Ave Wee Waa NSW 2388",
    "addr:housenumber":"5",
    "addr:postcode":"2388",
    "addr:street":"Cormie Ave",
    "iso:country":"AU",
    "sg:address":"5 Cormie Ave",
    "sg:city":"Wee Waa",
    "sg:classifiers":[
        {
            "category":"Farming",
            "subcategory":"Farm & Veterinary Services",
            "type":"Manufacturing & Wholesale Goods"
        }
    ],
    "sg:phone":"+61 2 6795 4462",
    "sg:postcode":"2388",
    "sg:province":"NSW",
    "sg:tags":[
        "agricultural",
        "advisory"
    ],
    "wof:name":"Baird Brian",
    "wof:placetype":"venue"
},
  "geometry": {"coordinates":[149.445587158,-30.2210330963],"type":"Point"}
}