{
  "type": "Feature",
  "properties": {
    "addr:full":"Shop 9/ 330 South Tce South Fremantle WA 6162",
    "addr:housenumber":"shop 9 / 330",
    "addr:postcode":"6162",
    "addr:street":"South Tce",
    "iso:country":"AU",
    "sg:address":"Shop 9/ 330 South Tce",
    "sg:city":"South Fremantle",
    "sg:classifiers":[
        {
            "category":"Arts & Performance",
            "subcategory":"Art Gallery",
            "type":"Entertainment"
        }
    ],
    "sg:phone":"+61 8 9433 1694",
    "sg:postcode":"6162",
    "sg:province":"WA",
    "wof:name":"Earlywork Pty Ltd",
    "wof:placetype":"venue"
},
  "geometry": {"coordinates":[115.974152,-32.067917],"type":"Point"}
}