{
  "type": "Feature",
  "properties": {
    "addr:full":"13 Lipson Reach Rd Gulfview Heights SA 5096",
    "addr:housenumber":"13",
    "addr:postcode":"5096",
    "addr:street":"Lipson Reach Rd",
    "iso:country":"AU",
    "sg:address":"13 Lipson Reach Rd",
    "sg:city":"Gulfview Heights",
    "sg:classifiers":[
        {
            "category":"Building & Trades",
            "subcategory":"Construction",
            "type":"Services"
        }
    ],
    "sg:phone":"+61 8 8182 6633",
    "sg:postcode":"5096",
    "sg:province":"SA",
    "sg:tags":[
        "installation",
        "air conditioning"
    ],
    "wof:name":"Regent Home Heating & Cooling Pty Ltd",
    "wof:placetype":"venue"
},
  "geometry": {"coordinates":[138.66676330600001,-34.8020362854],"type":"Point"}
}