{
  "type": "Feature",
  "properties": {
    "addr:full":"61 Fitzroy Rd Warrnambool VIC 3280",
    "addr:housenumber":"61",
    "addr:postcode":"3280",
    "addr:street":"Fitzroy Rd",
    "iso:country":"AU",
    "sg:address":"61 Fitzroy Rd",
    "sg:city":"Warrnambool",
    "sg:classifiers":[
        {
            "category":"Professional",
            "subcategory":"Art Services",
            "type":"Services"
        }
    ],
    "sg:phone":"+61 3 5562 8827",
    "sg:postcode":"3280",
    "sg:province":"VIC",
    "sg:tags":[
        "decorator",
        "painter"
    ],
    "wof:name":"Fry K W & J L",
    "wof:placetype":"venue"
},
  "geometry": {"coordinates":[142.464401245,-38.3708229065],"type":"Point"}
}