{
  "type": "Feature",
  "properties": {
    "addr:full":"209 Bay St Brighton VIC 3186",
    "addr:housenumber":"209",
    "addr:postcode":"3186",
    "addr:street":"Bay St",
    "iso:country":"AU",
    "sg:address":"209 Bay St",
    "sg:city":"Brighton",
    "sg:classifiers":[
        {
            "category":"Travel",
            "subcategory":"Hostel",
            "type":"Entertainment"
        }
    ],
    "sg:phone":"+61 3 9596 2375",
    "sg:postcode":"3186",
    "sg:province":"VIC",
    "sg:tags":[
        "home"
    ],
    "wof:name":"Wattle Lodge Hostel",
    "wof:placetype":"venue"
},
  "geometry": {"coordinates":[144.99899292000001,-37.9048957825],"type":"Point"}
}