{
  "type": "Feature",
  "properties": {
    "iso:country":"AU",
    "sg:address":"59 Sydenham Rd",
    "sg:city":"Norwood",
    "sg:classifiers":[
        {
            "category":"Farming",
            "subcategory":"Farm & Veterinary Services",
            "type":"Manufacturing & Wholesale Goods"
        }
    ],
    "sg:phone":"+61 8 8362 9953",
    "sg:postcode":"5067",
    "sg:province":"SA",
    "sg:tags":[
        "agricultural",
        "advisory"
    ],
    "wof:name":"King Peter & Associates",
    "wof:placetype":"venue"
},
  "geometry": {"coordinates":[138.62765502900001,-34.920375824],"type":"Point"}
}