{
  "type": "Feature",
  "properties": {
    "addr:full":"21 Victoria Pde Collingwood VIC 3066",
    "addr:housenumber":"21",
    "addr:postcode":"3066",
    "addr:street":"Victoria Pde",
    "iso:country":"AU",
    "sg:address":"21 Victoria Pde",
    "sg:city":"Collingwood",
    "sg:classifiers":[
        {
            "category":"Health Services",
            "subcategory":"Dentist",
            "type":"Services"
        }
    ],
    "sg:phone":"+61 3 9417 2023",
    "sg:postcode":"3066",
    "sg:province":"VIC",
    "wof:name":"Chen Ying Dr",
    "wof:placetype":"venue"
},
  "geometry": {"coordinates":[144.98304748499999,-37.8086242676],"type":"Point"}
}