{
  "type": "Feature",
  "properties": {
    "addr:full":"9 Iraking Ave Moorebank NSW 2170",
    "addr:housenumber":"9",
    "addr:postcode":"2170",
    "addr:street":"Iraking Ave",
    "iso:country":"AU",
    "sg:address":"9 Iraking Ave",
    "sg:city":"Moorebank",
    "sg:classifiers":[
        {
            "category":"Retail",
            "subcategory":"Auto Repair",
            "type":"Services"
        }
    ],
    "sg:phone":"+61 2 9822 2369",
    "sg:postcode":"2170",
    "sg:province":"NSW",
    "sg:tags":[
        "body",
        "motor",
        "trimmer"
    ],
    "wof:name":"John Canilho Motor Trimmers",
    "wof:placetype":"venue"
},
  "geometry": {"coordinates":[150.94105529800001,-33.9319534302],"type":"Point"}
}