{
  "type": "Feature",
  "properties": {
    "iso:country":"AU",
    "sg:address":"105 Holmes St",
    "sg:city":"Kingsford",
    "sg:classifiers":[
        {
            "category":"Retail",
            "subcategory":"Auto Rental",
            "type":"Services"
        }
    ],
    "sg:phone":"+61 2 9314 3336",
    "sg:postcode":"2032",
    "sg:province":"NSW",
    "sg:tags":[
        "chauffeur",
        "car",
        "hire",
        "driven",
        "limousine"
    ],
    "wof:name":"Cross G",
    "wof:placetype":"venue"
},
  "geometry": {"coordinates":[151.24790954599999,-33.9346923828],"type":"Point"}
}