{
  "type": "Feature",
  "properties": {
    "iso:country":"AU",
    "sg:address":"8- 12 Glennie St",
    "sg:city":"West Gosford North",
    "sg:classifiers":[
        {
            "category":"Home & Garden",
            "subcategory":"Building Materials",
            "type":"Retail Goods"
        }
    ],
    "sg:phone":"+61 2 4322 8034",
    "sg:postcode":"2250",
    "sg:province":"NSW",
    "sg:tags":[
        "wall",
        "frame",
        "truss",
        "roof"
    ],
    "wof:name":"Gosford Frames & Trusses",
    "wof:placetype":"venue"
},
  "geometry": {"coordinates":[151.34109497099999,-33.4116897583],"type":"Point"}
}