{
  "type": "Feature",
  "properties": {
    "addr:full":"133 Cramer St Preston VIC 3072",
    "addr:housenumber":"133",
    "addr:postcode":"3072",
    "addr:street":"Cramer St",
    "iso:country":"AU",
    "sg:address":"133 Cramer St",
    "sg:city":"Preston",
    "sg:classifiers":[
        {
            "category":"Real Estate",
            "subcategory":"Developer",
            "type":"Services"
        }
    ],
    "sg:phone":"+61 3 9471 3771",
    "sg:postcode":"3072",
    "sg:province":"VIC",
    "sg:tags":[
        "development"
    ],
    "wof:name":"Harvard Developments Pty Ltd",
    "wof:placetype":"venue"
},
  "geometry": {"coordinates":[144.98765564000001,-37.7388877869],"type":"Point"}
}