{
  "type": "Feature",
  "properties": {
    "iso:country":"AU",
    "sg:address":"17 Ayr St",
    "sg:city":"Reservoir",
    "sg:classifiers":[
        {
            "category":"Building & Trades",
            "subcategory":"Construction",
            "type":"Services"
        }
    ],
    "sg:phone":"+61 3 9460 2918",
    "sg:postcode":"3073",
    "sg:province":"VIC",
    "sg:tags":[
        "contractor"
    ],
    "wof:name":"Ferraro D&R",
    "wof:placetype":"venue"
},
  "geometry": {"coordinates":[145.03236389200001,-37.706161499],"type":"Point"}
}