{
  "type": "Feature",
  "properties": {
    "addr:full":"52 James St North Beach WA 6020",
    "addr:housenumber":"52",
    "addr:postcode":"6020",
    "addr:street":"James St",
    "iso:country":"AU",
    "sg:address":"52 James St",
    "sg:city":"North Beach",
    "sg:classifiers":[
        {
            "category":"Professional",
            "subcategory":"Engineering",
            "type":"Services"
        }
    ],
    "sg:phone":"+61 8 9243 0263",
    "sg:postcode":"6020",
    "sg:province":"WA",
    "sg:tags":[
        "consulting",
        "engineer"
    ],
    "wof:name":"Bernie Treichel",
    "wof:placetype":"venue"
},
  "geometry": {"coordinates":[115.7579422,-31.8584327698],"type":"Point"}
}