{
  "type": "Feature",
  "properties": {
    "addr:full":"86 Hawthorn Rd Caulfield North VIC 3161",
    "addr:housenumber":"86",
    "addr:postcode":"3161",
    "addr:street":"Hawthorn Rd",
    "iso:country":"AU",
    "sg:address":"86 Hawthorn Rd",
    "sg:city":"Caulfield North",
    "sg:classifiers":[
        {
            "category":"Health Services",
            "subcategory":"Doctor",
            "type":"Services"
        }
    ],
    "sg:phone":"+61 3 9509 7255",
    "sg:postcode":"3161",
    "sg:province":"VIC",
    "sg:tags":[
        "medical",
        "practitioner"
    ],
    "wof:name":"Symons Mark Dr",
    "wof:placetype":"venue"
},
  "geometry": {"coordinates":[145.02471923799999,-37.8716239929],"type":"Point"}
}