{
  "type": "Feature",
  "properties": {
    "addr:full":"Lot 2 Silverdale Rd Silverdale NSW 2752",
    "addr:postcode":"2752",
    "addr:street":"Silverdale Rd",
    "iso:country":"AU",
    "sg:address":"Lot 2 Silverdale Rd",
    "sg:city":"Silverdale",
    "sg:classifiers":[
        {
            "category":"Personal",
            "type":"Services"
        }
    ],
    "sg:phone":"+61 2 4774 2762",
    "sg:postcode":"2752",
    "sg:province":"NSW",
    "sg:tags":[
        "dressmaker"
    ],
    "wof:name":"A.J. Mobile Dressmaker",
    "wof:placetype":"venue"
},
  "geometry": {"coordinates":[150.61968994099999,-33.8798675537],"type":"Point"}
}