{
  "type": "Feature",
  "properties": {
    "iso:country":"AU",
    "sg:address":"Orr St",
    "sg:city":"Queenstown",
    "sg:classifiers":[
        {
            "category":"Shopping",
            "subcategory":"Clothing, Apparel, & Fashions",
            "type":"Retail Goods"
        }
    ],
    "sg:phone":"+61 437 711 999",
    "sg:postcode":"7467",
    "sg:province":"TAS",
    "sg:tags":[
        "sportswear"
    ],
    "wof:name":"Shoe Mart The",
    "wof:placetype":"venue"
},
  "geometry": {"coordinates":[145.55702209500001,-42.0802192688],"type":"Point"}
}