{
  "type": "Feature",
  "properties": {
    "addr:full":"Unit 1 & 2 34 Investigator Drv Unanderra NSW 2526",
    "addr:housenumber":"&;34",
    "addr:postcode":"2526",
    "addr:street":"Investigator Drv",
    "iso:country":"AU",
    "sg:address":"Unit 1 & 2 34 Investigator Drv",
    "sg:city":"Unanderra",
    "sg:classifiers":[
        {
            "category":"Professional",
            "subcategory":"Engineering",
            "type":"Services"
        }
    ],
    "sg:phone":"+61 2 4272 1111",
    "sg:postcode":"2526",
    "sg:province":"NSW",
    "sg:tags":[
        "manufacturing",
        "engineer"
    ],
    "wof:name":"Le Mans Engineering",
    "wof:placetype":"venue"
},
  "geometry": {"coordinates":[150.843017578,-34.4620399475],"type":"Point"}
}