{
  "type": "Feature",
  "properties": {
    "iso:country":"AU",
    "sg:address":"PO Box 1580",
    "sg:city":"Hornsby",
    "sg:classifiers":[
        {
            "category":"Personal",
            "subcategory":"Adult",
            "type":"Services"
        }
    ],
    "sg:phone":"+61 2 9987 0618",
    "sg:postcode":"2077",
    "sg:province":"NSW",
    "sg:tags":[
        "vic",
        "except",
        "state",
        "escort",
        "social",
        "qld"
    ],
    "wof:name":"Smar Escorts",
    "wof:placetype":"venue"
},
  "geometry": {"coordinates":[151.09687805199999,-33.7007789612],"type":"Point"}
}