{
  "type": "Feature",
  "properties": {
    "addr:full":"52 Winston Ave Clarence Gardens SA 5039",
    "addr:housenumber":"52",
    "addr:postcode":"5039",
    "addr:street":"Winston Ave",
    "iso:country":"AU",
    "sg:address":"52 Winston Ave",
    "sg:city":"Clarence Gardens",
    "sg:classifiers":[
        {
            "category":"Food & Beverages",
            "subcategory":"Supermarket",
            "type":"Retail Goods"
        }
    ],
    "sg:phone":"+61 8 8293 3042",
    "sg:postcode":"5039",
    "sg:province":"SA",
    "sg:tags":[
        "grocery",
        "store"
    ],
    "wof:name":"Friendly Grocers",
    "wof:placetype":"venue"
},
  "geometry": {"coordinates":[138.582275391,-34.9758338928],"type":"Point"}
}