{
  "type": "Feature",
  "properties": {
    "addr:full":"157 Swan St Richmond VIC 3121",
    "addr:housenumber":"157",
    "addr:postcode":"3121",
    "addr:street":"Swan St",
    "iso:country":"AU",
    "sg:address":"157 Swan St",
    "sg:city":"Richmond",
    "sg:classifiers":[
        {
            "category":"Travel",
            "subcategory":"Hotels & Motels",
            "type":"Entertainment"
        }
    ],
    "sg:phone":"+61 3 9428 7447",
    "sg:postcode":"3121",
    "sg:province":"VIC",
    "sg:tags":[
        "pub"
    ],
    "wof:name":"Vaucluse Hotel",
    "wof:placetype":"venue"
},
  "geometry": {"coordinates":[144.996383667,-37.8253631592],"type":"Point"}
}