{
  "type": "Feature",
  "properties": {
    "iso:country":"AU",
    "sg:address":"14 Newry St",
    "sg:city":"Richmond",
    "sg:classifiers":[
        {
            "category":"Shopping",
            "subcategory":"Party Supplies",
            "type":"Retail Goods"
        }
    ],
    "sg:phone":"+61 3 9429 3621",
    "sg:postcode":"3121",
    "sg:province":"VIC",
    "sg:tags":[
        "children's"
    ],
    "sg:website":"http://www.polkadot.net.au",
    "wof:name":"Polka Dot Entertainment",
    "wof:placetype":"venue"
},
  "geometry": {"coordinates":[145.00531005900001,-37.8247413635],"type":"Point"}
}