{
  "type": "Feature",
  "properties": {
    "iso:country":"AU",
    "sg:address":"4 Moger La",
    "sg:city":"Adelaide",
    "sg:classifiers":[
        {
            "category":"Professional",
            "subcategory":"Accounting & Tax Preparation",
            "type":"Services"
        }
    ],
    "sg:phone":"+61 8 8418 2111",
    "sg:postcode":"5000",
    "sg:province":"SA",
    "sg:tags":[
        "accountant",
        "auditor"
    ],
    "sg:website":"http://www.craserobinson.com.au",
    "wof:name":"Crase Robinson",
    "wof:placetype":"venue"
},
  "geometry": {"coordinates":[138.60873413100001,-34.9250564575],"type":"Point"}
}