{
  "type": "Feature",
  "properties": {
    "iso:country":"AU",
    "sg:address":"Medical Family Practice 5 Gilbert St",
    "sg:city":"Berri",
    "sg:classifiers":[
        {
            "category":"Health Services",
            "subcategory":"Health Practitioner",
            "type":"Services"
        }
    ],
    "sg:phone":"+61 8 8582 1989",
    "sg:postcode":"5343",
    "sg:province":"SA",
    "sg:tags":[
        "psychologist"
    ],
    "wof:name":"Ursula Sombetzki",
    "wof:placetype":"venue"
},
  "geometry": {"coordinates":[140.60421752900001,-34.2851753235],"type":"Point"}
}