{
  "type": "Feature",
  "properties": {
    "addr:full":"PO Box 356 Warrandyte VIC 3113",
    "addr:postcode":"3113",
    "iso:country":"AU",
    "sg:address":"PO Box 356",
    "sg:city":"Warrandyte",
    "sg:classifiers":[
        {
            "category":"Shopping",
            "subcategory":"Bicycles & Sporting Goods",
            "type":"Retail Goods"
        }
    ],
    "sg:phone":"+61 407 532 741",
    "sg:postcode":"3113",
    "sg:province":"VIC",
    "sg:tags":[
        "synthetic",
        "surface"
    ],
    "wof:name":"Court Tecnics",
    "wof:placetype":"venue"
},
  "geometry": {"coordinates":[145.19952392600001,-37.7428970337],"type":"Point"}
}