{
  "type": "Feature",
  "properties": {
    "addr:full":"20 Ramage St Bayswater VIC 3153",
    "addr:housenumber":"20",
    "addr:postcode":"3153",
    "addr:street":"Ramage St",
    "iso:country":"AU",
    "sg:address":"20 Ramage St",
    "sg:city":"Bayswater",
    "sg:classifiers":[
        {
            "category":"Professional",
            "subcategory":"Engineering",
            "type":"Services"
        }
    ],
    "sg:phone":"+61 3 8727 6600",
    "sg:postcode":"3153",
    "sg:province":"VIC",
    "sg:tags":[
        "engineer"
    ],
    "wof:name":"Jenkin Bros Engineers (Australia) Pty Ltd",
    "wof:placetype":"venue"
},
  "geometry": {"coordinates":[145.28216552699999,-37.8417472839],"type":"Point"}
}