{
  "type": "Feature",
  "properties": {
    "addr:full":"Illawong School Hall Fowler Rd Illawong NSW 2234",
    "addr:postcode":"2234",
    "addr:street":"Fowler Rd",
    "iso:country":"AU",
    "sg:address":"Illawong School Hall Fowler Rd",
    "sg:city":"Illawong",
    "sg:classifiers":[
        {
            "category":"Arts & Performance",
            "subcategory":"Dance",
            "type":"Entertainment"
        }
    ],
    "sg:phone":"+61 2 9771 5462",
    "sg:postcode":"2234",
    "sg:province":"NSW",
    "sg:tags":[
        "theatrical",
        "ballet",
        "tuition"
    ],
    "wof:name":"Dance Studio-Illawong",
    "wof:placetype":"venue"
},
  "geometry": {"coordinates":[151.04199218799999,-33.998626709],"type":"Point"}
}