{
  "type": "Feature",
  "properties": {
    "addr:full":"150 Woongarra St West Bundaberg QLD 4670",
    "addr:housenumber":"150",
    "addr:postcode":"4670",
    "addr:street":"Woongarra St West",
    "iso:country":"AU",
    "sg:address":"150 Woongarra St",
    "sg:city":"West Bundaberg",
    "sg:classifiers":[
        {
            "category":"Personal",
            "subcategory":"Day Spa",
            "type":"Services"
        }
    ],
    "sg:phone":"+61 7 4152 0500",
    "sg:postcode":"4670",
    "sg:province":"QLD",
    "wof:name":"Aqualine Beauty & Day Spa",
    "wof:placetype":"venue"
},
  "geometry": {"coordinates":[152.33412170400001,-24.8715286255],"type":"Point"}
}