{
  "type": "Feature",
  "properties": {
    "addr:full":"129 Marion Rd Richmond SA 5033",
    "addr:housenumber":"129",
    "addr:postcode":"5033",
    "addr:street":"Marion Rd",
    "iso:country":"AU",
    "sg:address":"129 Marion Rd",
    "sg:city":"Richmond",
    "sg:classifiers":[
        {
            "category":"Health Services",
            "subcategory":"Doctor",
            "type":"Services"
        }
    ],
    "sg:phone":"+61 8 8234 6324",
    "sg:postcode":"5033",
    "sg:province":"SA",
    "sg:tags":[
        "medical",
        "practitioner"
    ],
    "wof:name":"Moschou C",
    "wof:placetype":"venue"
},
  "geometry": {"coordinates":[138.55296325699999,-34.9364395142],"type":"Point"}
}