{
  "type": "Feature",
  "properties": {
    "addr:full":"18 Leo St Fawkner VIC 3060",
    "addr:housenumber":"18",
    "addr:postcode":"3060",
    "addr:street":"Leo St",
    "iso:country":"AU",
    "sg:address":"18 Leo St",
    "sg:city":"Fawkner",
    "sg:classifiers":[
        {
            "category":"Retail",
            "subcategory":"Auto Repair",
            "type":"Services"
        }
    ],
    "sg:phone":"+61 3 9359 4952",
    "sg:postcode":"3060",
    "sg:province":"VIC",
    "sg:tags":[
        "testing",
        "inspection",
        "motor",
        "vehicle"
    ],
    "wof:name":"Hyund Serv",
    "wof:placetype":"venue"
},
  "geometry": {"coordinates":[144.96177673299999,-37.7080764771],"type":"Point"}
}