{
  "type": "Feature",
  "properties": {
    "addr:full":"Factory 11/ 657 Pine Ridge Rd Labrador QLD 4215",
    "addr:housenumber":"11 / 657",
    "addr:postcode":"4215",
    "addr:street":"Pine Ridge Rd",
    "iso:country":"AU",
    "sg:address":"Factory 11/ 657 Pine Ridge Rd",
    "sg:city":"Labrador",
    "sg:classifiers":[
        {
            "category":"Communications",
            "type":"Services"
        }
    ],
    "sg:phone":"+61 7 5563 2055",
    "sg:postcode":"4215",
    "sg:province":"QLD",
    "sg:tags":[
        "equipment",
        "radio"
    ],
    "wof:name":"ADL",
    "wof:placetype":"venue"
},
  "geometry": {"coordinates":[153.40838623100001,-27.945930481],"type":"Point"}
}