{
  "type": "Feature",
  "properties": {
    "iso:country":"AU",
    "sg:address":"Suite 13, 146- 156 Anderson St",
    "sg:city":"Cairns",
    "sg:classifiers":[
        {
            "category":"Health Services",
            "subcategory":"Dentist",
            "type":"Services"
        }
    ],
    "sg:phone":"+61 7 4053 5004",
    "sg:postcode":"4870",
    "sg:province":"QLD",
    "wof:name":"F S Khoo",
    "wof:placetype":"venue"
},
  "geometry": {"coordinates":[145.742645264,-16.916721344],"type":"Point"}
}