{
  "type": "Feature",
  "properties": {
    "iso:country":"AU",
    "sg:address":"4 Victoria St",
    "sg:city":"Forest Hill",
    "sg:classifiers":[
        {
            "category":"Travel",
            "subcategory":"Hotels & Motels",
            "type":"Entertainment"
        }
    ],
    "sg:phone":"+61 7 5465 4109",
    "sg:postcode":"4342",
    "sg:province":"QLD",
    "sg:tags":[
        "accommodation"
    ],
    "wof:name":"Forest Hill Hotel",
    "wof:placetype":"venue"
},
  "geometry": {"coordinates":[152.356567383,-27.5897254944],"type":"Point"}
}