{
  "type": "Feature",
  "properties": {
    "iso:country":"AU",
    "sg:address":"16 Highland Ave",
    "sg:city":"Highett",
    "sg:classifiers":[
        {
            "category":"Professional",
            "subcategory":"Art Services",
            "type":"Services"
        }
    ],
    "sg:phone":"+61 3 9598 6609",
    "sg:postcode":"3190",
    "sg:province":"VIC",
    "sg:tags":[
        "artist"
    ],
    "wof:name":"Pen Magic Fine Art",
    "wof:placetype":"venue"
},
  "geometry": {"coordinates":[145.028762817,-37.9532356262],"type":"Point"}
}