{
  "type": "Feature",
  "properties": {
    "addr:full":"Summit Rd Mt Buller VIC 3723",
    "addr:postcode":"3723",
    "addr:street":"Summit Rd",
    "iso:country":"AU",
    "sg:address":"Summit Rd",
    "sg:city":"Mt Buller",
    "sg:classifiers":[
        {
            "category":"Sports & Exercise",
            "subcategory":"Ski Slope",
            "type":"Entertainment"
        }
    ],
    "sg:phone":"+61 3 5777 7800",
    "sg:postcode":"3723",
    "sg:province":"VIC",
    "sg:tags":[
        "equipment",
        "hire",
        "retail",
        "snow"
    ],
    "wof:name":"Mt Buller Ski Lifts",
    "wof:placetype":"venue"
},
  "geometry": {"coordinates":[146.438522339,-37.1454315186],"type":"Point"}
}