{
  "type": "Feature",
  "properties": {
    "addr:full":"5/ 280 Grand Junction Rd Athol Park SA 5012",
    "addr:housenumber":"/ 280",
    "addr:postcode":"5012",
    "addr:street":"Grand Junction Rd",
    "iso:country":"AU",
    "sg:address":"5/ 280 Grand Junction Rd",
    "sg:city":"Athol Park",
    "sg:classifiers":[
        {
            "category":"Wholesale",
            "subcategory":"Machinery & Supplies",
            "type":"Manufacturing & Wholesale Goods"
        }
    ],
    "sg:phone":"+61 8 8240 7800",
    "sg:postcode":"5012",
    "sg:province":"SA",
    "sg:tags":[
        "equipment",
        "hydraulic"
    ],
    "wof:name":"Gough Transport Solutions",
    "wof:placetype":"venue"
},
  "geometry": {"coordinates":[138.545318603,-34.8508415222],"type":"Point"}
}