{
  "type": "Feature",
  "properties": {
    "iso:country":"AU",
    "sg:address":"1079 Pascoe Vale Rd",
    "sg:city":"Broadmeadows",
    "sg:classifiers":[
        {
            "category":"Retail",
            "subcategory":"Funeral Services",
            "type":"Services"
        }
    ],
    "sg:phone":"+61 3 9205 2200",
    "sg:postcode":"3047",
    "sg:province":"VIC",
    "sg:tags":[
        "cemetery"
    ],
    "wof:name":"Sunbury Cemetery",
    "wof:placetype":"venue"
},
  "geometry": {"coordinates":[144.918212891,-37.6834106445],"type":"Point"}
}