{
  "type": "Feature",
  "properties": {
    "iso:country":"AU",
    "sg:address":"8 Wray Ave",
    "sg:city":"Fremantle",
    "sg:classifiers":[
        {
            "category":"Shopping",
            "subcategory":"Clothing, Apparel, & Fashions",
            "type":"Retail Goods"
        }
    ],
    "sg:phone":"+61 8 9336 1632",
    "sg:postcode":"6160",
    "sg:province":"WA",
    "sg:tags":[
        "recycled",
        "clothing"
    ],
    "wof:name":"Diamond Aps Recycling Boutique",
    "wof:placetype":"venue"
},
  "geometry": {"coordinates":[115.751572,-32.059483],"type":"Point"}
}