{
  "type": "Feature",
  "properties": {
    "addr:full":"119 Flinders Hwy Port Lincoln SA 5606",
    "addr:housenumber":"119",
    "addr:postcode":"5606",
    "addr:street":"Flinders Hwy",
    "iso:country":"AU",
    "sg:address":"119 Flinders Hwy",
    "sg:city":"Port Lincoln",
    "sg:classifiers":[
        {
            "category":"Building & Trades",
            "subcategory":"Locksmith",
            "type":"Services"
        }
    ],
    "sg:phone":"+61 8 8683 3207",
    "sg:postcode":"5606",
    "sg:province":"SA",
    "sg:tags":[
        "strongroom",
        "safe",
        "door"
    ],
    "wof:name":"Lincoln Locksmiths",
    "wof:placetype":"venue"
},
  "geometry": {"coordinates":[135.832336,-34.713802],"type":"Point"}
}