{
  "type": "Feature",
  "properties": {
    "addr:full":"3 / 413 Victoria St Wetherill Park NSW 2164",
    "addr:housenumber":"/ 413",
    "addr:postcode":"2164",
    "addr:street":"Victoria St",
    "iso:country":"AU",
    "sg:address":"3 / 413 Victoria St",
    "sg:city":"Wetherill Park",
    "sg:classifiers":[
        {
            "category":"Social Services",
            "type":"Services"
        }
    ],
    "sg:phone":"+61 2 9892 1811",
    "sg:postcode":"2164",
    "sg:province":"NSW",
    "sg:tags":[
        "disabled",
        "person",
        "equipment"
    ],
    "wof:name":"ADIS Automatic Doors",
    "wof:placetype":"venue"
},
  "geometry": {"coordinates":[150.89581298799999,-33.8449821472],"type":"Point"}
}