{
  "type": "Feature",
  "properties": {
    "addr:full":"1086 Ipswich Rd Moorooka QLD 4105",
    "addr:housenumber":"1086",
    "addr:postcode":"4105",
    "addr:street":"Ipswich Rd",
    "iso:country":"AU",
    "sg:address":"1086 Ipswich Rd",
    "sg:city":"Moorooka",
    "sg:classifiers":[
        {
            "category":"Autos & Motor Vehicles",
            "subcategory":"Automobile Sales",
            "type":"Retail Goods"
        }
    ],
    "sg:phone":"+61 7 3426 7280",
    "sg:postcode":"4105",
    "sg:province":"QLD",
    "sg:tags":[
        "car",
        "used"
    ],
    "wof:name":"Motorama Budget",
    "wof:placetype":"venue"
},
  "geometry": {"coordinates":[153.01507568400001,-27.534992218],"type":"Point"}
}