{
  "type": "Feature",
  "properties": {
    "addr:full":"861 Black River Rd Townsville QLD 4810",
    "addr:housenumber":"861",
    "addr:postcode":"4810",
    "addr:street":"Black River Rd",
    "iso:country":"AU",
    "sg:address":"861 Black River Rd",
    "sg:city":"Townsville",
    "sg:classifiers":[
        {
            "category":"Military Area",
            "subcategory":"Air Force Base",
            "type":"Public Place"
        }
    ],
    "sg:phone":"+61 7 4788 8133",
    "sg:postcode":"4810",
    "sg:province":"QLD",
    "sg:tags":[
        "conditioner",
        "treatment",
        "soil"
    ],
    "wof:name":"Zinaback Pty Ltd",
    "wof:placetype":"venue"
},
  "geometry": {"coordinates":[146.75546299999999,-19.2351],"type":"Point"}
}