{
  "type": "Feature",
  "properties": {
    "addr:full":"P.O. Box 44 145 Sydney Rd Fairlight NSW 2094",
    "addr:housenumber":"145",
    "addr:postcode":"2094",
    "addr:street":"Sydney Rd",
    "iso:country":"AU",
    "sg:address":"P.O. Box 44 145 Sydney Rd",
    "sg:city":"Fairlight",
    "sg:classifiers":[
        {
            "category":"Wholesale",
            "subcategory":"Medical Equipment & Supplies",
            "type":"Manufacturing & Wholesale Goods"
        }
    ],
    "sg:phone":"+61 2 9907 9736",
    "sg:postcode":"2094",
    "sg:province":"NSW",
    "sg:tags":[
        "aid",
        "care",
        "health",
        "home"
    ],
    "wof:name":"Input Options",
    "wof:placetype":"venue"
},
  "geometry": {"coordinates":[151.276000977,-33.7959136963],"type":"Point"}
}