{
  "type": "Feature",
  "properties": {
    "addr:full":"33 Havenbrook Drv Trevallyn TAS 7250",
    "addr:housenumber":"33",
    "addr:postcode":"7250",
    "addr:street":"Havenbrook Drv",
    "iso:country":"AU",
    "sg:address":"33 Havenbrook Drv",
    "sg:city":"Trevallyn",
    "sg:classifiers":[
        {
            "category":"Professional",
            "subcategory":"Engineering",
            "type":"Services"
        }
    ],
    "sg:phone":"+61 3 6331 3509",
    "sg:postcode":"7250",
    "sg:province":"TAS",
    "sg:tags":[
        "civil",
        "engineer"
    ],
    "wof:name":"Hudson Ken",
    "wof:placetype":"venue"
},
  "geometry": {"coordinates":[147.102584839,-41.4384498596],"type":"Point"}
}