{
  "type": "Feature",
  "properties": {
    "addr:full":"64 Maurice Ave Mallacoota VIC 3892",
    "addr:housenumber":"64",
    "addr:postcode":"3892",
    "addr:street":"Maurice Ave",
    "iso:country":"AU",
    "sg:address":"64 Maurice Ave",
    "sg:city":"Mallacoota",
    "sg:classifiers":[
        {
            "category":"Communications",
            "subcategory":"Film & Video Production",
            "type":"Services"
        }
    ],
    "sg:phone":"+61 3 5158 0666",
    "sg:postcode":"3892",
    "sg:province":"VIC",
    "sg:tags":[
        "dvd",
        "library"
    ],
    "wof:name":"Mallacoota Moving Pictures",
    "wof:placetype":"venue"
},
  "geometry": {"coordinates":[149.75784301799999,-37.5580177307],"type":"Point"}
}