{
  "type": "Feature",
  "properties": {
    "iso:country":"AU",
    "sg:address":"2/ 12 Waterloo St",
    "sg:city":"Narrabeen",
    "sg:classifiers":[
        {
            "category":"Personal",
            "subcategory":"Beauty Salon",
            "type":"Services"
        }
    ],
    "sg:phone":"+61 2 9970 6634",
    "sg:postcode":"2101",
    "sg:province":"NSW",
    "sg:tags":[
        "hairdresser"
    ],
    "wof:name":"Tranquility Hair Salon",
    "wof:placetype":"venue"
},
  "geometry": {"coordinates":[151.29895,-33.713409],"type":"Point"}
}