{
  "type": "Feature",
  "properties": {
    "iso:country":"AU",
    "sg:address":"21 Dudley St",
    "sg:city":"Haberfield",
    "sg:classifiers":[
        {
            "category":"Retail",
            "subcategory":"Auto Rental",
            "type":"Services"
        }
    ],
    "sg:phone":"+61 2 9799 2222",
    "sg:postcode":"2045",
    "sg:province":"NSW",
    "sg:tags":[
        "chauffeur",
        "car",
        "hire",
        "driven",
        "limousine"
    ],
    "wof:name":"HF Wedding & Hire Cars",
    "wof:placetype":"venue"
},
  "geometry": {"coordinates":[151.14445499999999,-33.874424],"type":"Point"}
}