{
  "type": "Feature",
  "properties": {
    "iso:country":"AU",
    "sg:address":"Unit-4, 42 York Rd",
    "sg:city":"Ingleburn",
    "sg:classifiers":[
        {
            "category":"Social Services",
            "type":"Services"
        }
    ],
    "sg:phone":"+61 417 068 799",
    "sg:postcode":"2565",
    "sg:province":"NSW",
    "sg:tags":[
        "disabled",
        "person",
        "equipment"
    ],
    "wof:name":"Arlow Engineering",
    "wof:placetype":"venue"
},
  "geometry": {"coordinates":[150.85848999000001,-33.9946670532],"type":"Point"}
}