{
  "type": "Feature",
  "properties": {
    "iso:country":"AU",
    "sg:address":"190 North West Coastal Hwy",
    "sg:city":"Geraldton",
    "sg:classifiers":[
        {
            "category":"Autos & Motor Vehicles",
            "subcategory":"Fuel & Gas Station",
            "type":"Retail Goods"
        }
    ],
    "sg:phone":"+61 8 9921 1153",
    "sg:postcode":"6530",
    "sg:province":"WA",
    "wof:name":"BP Wonthella Service Station",
    "wof:placetype":"venue"
},
  "geometry": {"coordinates":[114.624992371,-28.7587146759],"type":"Point"}
}