{
  "type": "Feature",
  "properties": {
    "addr:full":"441 Logan Rd Stones Corner QLD 4120",
    "addr:housenumber":"441",
    "addr:postcode":"4120",
    "addr:street":"Logan Rd",
    "iso:country":"AU",
    "sg:address":"441 Logan Rd",
    "sg:city":"Stones Corner",
    "sg:classifiers":[
        {
            "category":"Professional",
            "subcategory":"Management & Consulting",
            "type":"Services"
        }
    ],
    "sg:phone":"+61 7 3394 8395",
    "sg:postcode":"4120",
    "sg:province":"QLD",
    "sg:tags":[
        "consultant",
        "business"
    ],
    "wof:name":"A Business Pty Ltd",
    "wof:placetype":"venue"
},
  "geometry": {"coordinates":[153.04635620100001,-27.501750946],"type":"Point"}
}