{
  "type": "Feature",
  "properties": {
    "addr:full":"Shop 2/ 107 Hanson Rd Gladstone QLD 4680",
    "addr:housenumber":"shop 2 / 107",
    "addr:postcode":"4680",
    "addr:street":"Hanson Rd",
    "iso:country":"AU",
    "sg:address":"Shop 2/ 107 Hanson Rd",
    "sg:city":"Gladstone",
    "sg:classifiers":[
        {
            "category":"Wholesale",
            "subcategory":"Machinery & Supplies",
            "type":"Manufacturing & Wholesale Goods"
        }
    ],
    "sg:phone":"+61 7 4972 0998",
    "sg:postcode":"4680",
    "sg:province":"QLD",
    "sg:tags":[
        "equipment",
        "welding"
    ],
    "wof:name":"Specialised Engineering Products",
    "wof:placetype":"venue"
},
  "geometry": {"coordinates":[151.239700317,-23.8418521881],"type":"Point"}
}