{
  "type": "Feature",
  "properties": {
    "addr:full":"150 Kelvin Grove Rd Kelvin Grove QLD 4059",
    "addr:housenumber":"150",
    "addr:postcode":"4059",
    "addr:street":"Kelvin Grove Rd",
    "iso:country":"AU",
    "sg:address":"150 Kelvin Grove Rd",
    "sg:city":"Kelvin Grove",
    "sg:classifiers":[
        {
            "category":"Retail",
            "subcategory":"Auto Repair",
            "type":"Services"
        }
    ],
    "sg:phone":"+61 7 3369 0200",
    "sg:postcode":"4059",
    "sg:province":"QLD",
    "sg:tags":[
        "muffler",
        "exhaust",
        "system"
    ],
    "wof:name":"Muffler Services",
    "wof:placetype":"venue"
},
  "geometry": {"coordinates":[153.011184692,-27.4528255463],"type":"Point"}
}