{
  "type": "Feature",
  "properties": {
    "iso:country":"AU",
    "sg:address":"299 Manningham Rd",
    "sg:city":"Lower Templestowe",
    "sg:classifiers":[
        {
            "category":"Autos & Motor Vehicles",
            "subcategory":"Fuel & Gas Station",
            "type":"Retail Goods"
        }
    ],
    "sg:phone":"+61 3 9850 4344",
    "sg:postcode":"3107",
    "sg:province":"VIC",
    "wof:name":"B E Danos Service Station Pty Ltd",
    "wof:placetype":"venue"
},
  "geometry": {"coordinates":[145.11143493599999,-37.773109436],"type":"Point"}
}