{
  "type": "Feature",
  "properties": {
    "iso:country":"AU",
    "sg:address":"Suite 5, 17 Oatley Crt",
    "sg:city":"Belconnen",
    "sg:classifiers":[
        {
            "category":"Professional",
            "subcategory":"Accounting & Tax Preparation",
            "type":"Services"
        }
    ],
    "sg:phone":"+61 2 6253 5777",
    "sg:postcode":"2616",
    "sg:province":"ACT",
    "sg:tags":[
        "accountant",
        "auditor"
    ],
    "wof:name":"McGuire & McGee",
    "wof:placetype":"venue"
},
  "geometry": {"coordinates":[149.059783936,-35.2413063049],"type":"Point"}
}