{
  "type": "Feature",
  "properties": {
    "addr:full":"Shop 2, 546 Malvern Rd Prahran VIC 3181",
    "addr:housenumber":"shop 2 546",
    "addr:postcode":"3181",
    "addr:street":"Malvern Rd",
    "iso:country":"AU",
    "sg:address":"Shop 2, 546 Malvern Rd",
    "sg:city":"Prahran",
    "sg:classifiers":[
        {
            "category":"Shopping",
            "subcategory":"Baby Store",
            "type":"Retail Goods"
        }
    ],
    "sg:phone":"+61 3 9521 1569",
    "sg:postcode":"3181",
    "sg:province":"VIC",
    "sg:tags":[
        "children's",
        "wear"
    ],
    "wof:name":"Jacadi Paris",
    "wof:placetype":"venue"
},
  "geometry": {"coordinates":[145.00460815400001,-37.8483924866],"type":"Point"}
}