{
  "type": "Feature",
  "properties": {
    "addr:full":"701 Dog Trap Rd Somersby NSW 2250",
    "addr:housenumber":"701",
    "addr:postcode":"2250",
    "addr:street":"Dog Trap Rd",
    "iso:country":"AU",
    "sg:address":"701 Dog Trap Rd",
    "sg:city":"Somersby",
    "sg:classifiers":[
        {
            "category":"Structure",
            "subcategory":"Office Building",
            "type":"Public Place"
        }
    ],
    "sg:phone":"+61 2 4372 1800",
    "sg:postcode":"2250",
    "sg:province":"NSW",
    "sg:tags":[
        "slater",
        "tiler",
        "roof"
    ],
    "wof:name":"Lamb Terry",
    "wof:placetype":"venue"
},
  "geometry": {"coordinates":[151.31544494600001,-33.3646965027],"type":"Point"}
}