{
  "type": "Feature",
  "properties": {
    "addr:full":"9 James Milne Drv Croydon North VIC 3136",
    "addr:housenumber":"9",
    "addr:postcode":"3136",
    "addr:street":"James Milne Drv",
    "iso:country":"AU",
    "sg:address":"9 James Milne Drv",
    "sg:city":"Croydon North",
    "sg:classifiers":[
        {
            "category":"Building & Trades",
            "subcategory":"Landscaping Services",
            "type":"Services"
        }
    ],
    "sg:phone":"+61 3 9725 7397",
    "sg:postcode":"3136",
    "sg:province":"VIC",
    "sg:tags":[
        "designer",
        "landscape",
        "contractor"
    ],
    "wof:name":"Top Class Landscape & Garden Maintenance",
    "wof:placetype":"venue"
},
  "geometry": {"coordinates":[145.276412964,-37.7761955261],"type":"Point"}
}