{
  "type": "Feature",
  "properties": {
    "addr:full":"20 Tralee Ave Killarney Heights NSW 2087",
    "addr:housenumber":"20",
    "addr:postcode":"2087",
    "addr:street":"Tralee Ave",
    "iso:country":"AU",
    "sg:address":"20 Tralee Ave",
    "sg:city":"Killarney Heights",
    "sg:classifiers":[
        {
            "category":"Sports & Exercise",
            "subcategory":"Sports Center",
            "type":"Entertainment"
        }
    ],
    "sg:phone":"+61 2 9451 5180",
    "sg:postcode":"2087",
    "sg:province":"NSW",
    "sg:tags":[
        "coach",
        "tennis"
    ],
    "wof:name":"Killarney Heights Tennis Centre",
    "wof:placetype":"venue"
},
  "geometry": {"coordinates":[151.21775817899999,-33.776222229],"type":"Point"}
}