{
  "type": "Feature",
  "properties": {
    "iso:country":"AU",
    "sg:address":"448 St Kilda Rd",
    "sg:city":"Melbourne",
    "sg:classifiers":[
        {
            "category":"Cafe",
            "type":"Food & Drink"
        }
    ],
    "sg:phone":"+61 3 9821 4088",
    "sg:postcode":"3004",
    "sg:province":"VIC",
    "wof:name":"Cafe Equesta",
    "wof:placetype":"venue"
},
  "geometry": {"coordinates":[144.97604370100001,-37.8386077881],"type":"Point"}
}