{
  "type": "Feature",
  "properties": {
    "addr:full":"44 Clyde St Hamilton NSW 2303",
    "addr:housenumber":"44",
    "addr:postcode":"2303",
    "addr:street":"Clyde St",
    "iso:country":"AU",
    "sg:address":"44 Clyde St",
    "sg:city":"Hamilton",
    "sg:classifiers":[
        {
            "category":"Professional",
            "subcategory":"Engineering",
            "type":"Services"
        }
    ],
    "sg:phone":"+61 2 4961 2877",
    "sg:postcode":"2303",
    "sg:province":"NSW",
    "sg:tags":[
        "building",
        "prefabricated",
        "transportable",
        "industrial",
        "commercial"
    ],
    "wof:name":"Store-Safe",
    "wof:placetype":"venue"
},
  "geometry": {"coordinates":[151.739349,-32.912506],"type":"Point"}
}