{
  "type": "Feature",
  "properties": {
    "addr:full":"PO Box 6117 Pymble NSW 2073",
    "addr:postcode":"2073",
    "iso:country":"AU",
    "sg:address":"PO Box 6117",
    "sg:city":"Pymble",
    "sg:classifiers":[
        {
            "category":"Farming",
            "subcategory":"Farm & Veterinary Services",
            "type":"Manufacturing & Wholesale Goods"
        }
    ],
    "sg:phone":"+61 412 401 154",
    "sg:postcode":"2073",
    "sg:province":"NSW",
    "sg:tags":[
        "irrigation",
        "reticulation",
        "system"
    ],
    "wof:name":"Artscape Irrigation",
    "wof:placetype":"venue"
},
  "geometry": {"coordinates":[151.13749694800001,-33.7405281067],"type":"Point"}
}