{
  "type": "Feature",
  "properties": {
    "addr:full":"16 Horan St West End (Brisbane) QLD 4101",
    "addr:housenumber":"16",
    "addr:postcode":"4101",
    "addr:street":"Horan St",
    "iso:country":"AU",
    "sg:address":"16 Horan St",
    "sg:city":"West End (Brisbane)",
    "sg:classifiers":[
        {
            "category":"Wholesale",
            "subcategory":"Home Furnishings",
            "type":"Manufacturing & Wholesale Goods"
        }
    ],
    "sg:phone":"+61 7 3846 1366",
    "sg:postcode":"4101",
    "sg:province":"QLD",
    "wof:name":"Buchanan J M & Son Pty Ltd",
    "wof:placetype":"venue"
},
  "geometry": {"coordinates":[153.008911133,-27.4795017242],"type":"Point"}
}