{
  "type": "Feature",
  "properties": {
    "iso:country":"AU",
    "sg:address":"Seymours Rd",
    "sg:city":"Ridgelands",
    "sg:classifiers":[
        {
            "category":"Building & Trades",
            "subcategory":"Construction",
            "type":"Services"
        }
    ],
    "sg:phone":"+61 407 636 839",
    "sg:postcode":"4702",
    "sg:province":"QLD",
    "sg:tags":[
        "concrete",
        "contractor"
    ],
    "wof:name":"Mark Tomkins",
    "wof:placetype":"venue"
},
  "geometry": {"coordinates":[150.26927185100001,-23.3263607025],"type":"Point"}
}