{
  "type": "Feature",
  "properties": {
    "addr:full":"147 Breakfast Creek Rd Newstead QLD 4006",
    "addr:housenumber":"147",
    "addr:postcode":"4006",
    "addr:street":"Breakfast Creek Rd",
    "iso:country":"AU",
    "sg:address":"147 Breakfast Creek Rd",
    "sg:city":"Newstead",
    "sg:classifiers":[
        {
            "category":"Autos & Motor Vehicles",
            "subcategory":"Automobile Sales",
            "type":"Retail Goods"
        }
    ],
    "sg:phone":"+61 7 3252 9977",
    "sg:postcode":"4006",
    "sg:province":"QLD",
    "sg:tags":[
        "car",
        "new"
    ],
    "wof:name":"Grand Prix Jaguar",
    "wof:placetype":"venue"
},
  "geometry": {"coordinates":[153.04394531200001,-27.4437236786],"type":"Point"}
}