{
  "type": "Feature",
  "properties": {
    "addr:full":"260 Churchill Ave Subiaco WA 6008",
    "addr:housenumber":"260",
    "addr:postcode":"6008",
    "addr:street":"Churchill Ave",
    "iso:country":"AU",
    "sg:address":"260 Churchill Ave",
    "sg:city":"Subiaco",
    "sg:classifiers":[
        {
            "category":"Health Services",
            "subcategory":"Doctor",
            "type":"Services"
        }
    ],
    "sg:phone":"+61 8 9382 2679",
    "sg:postcode":"6008",
    "sg:province":"WA",
    "sg:tags":[
        "medical",
        "practitioner"
    ],
    "wof:name":"Thompson Graeme R",
    "wof:placetype":"venue"
},
  "geometry": {"coordinates":[115.82707977299999,-31.9477558136],"type":"Point"}
}