{
  "type": "Feature",
  "properties": {
    "addr:full":"HQ @ Robina 58 Riverwalk Ave Robina QLD 4226",
    "addr:housenumber":"58",
    "addr:postcode":"4226",
    "addr:street":"Robina;Riverwalk Ave",
    "iso:country":"AU",
    "sg:address":"HQ @ Robina 58 Riverwalk Ave",
    "sg:city":"Robina",
    "sg:classifiers":[
        {
            "category":"Health Services",
            "subcategory":"Doctor",
            "type":"Services"
        }
    ],
    "sg:phone":"+61 7 5580 9900",
    "sg:postcode":"4226",
    "sg:province":"QLD",
    "sg:tags":[
        "medical",
        "practitioner"
    ],
    "wof:name":"South Coast Radiology",
    "wof:placetype":"venue"
},
  "geometry": {"coordinates":[153.381790161,-28.079662323],"type":"Point"}
}