{
  "type": "Feature",
  "properties": {
    "iso:country":"AU",
    "sg:address":"PO Box 63",
    "sg:city":"Bli Bli",
    "sg:classifiers":[
        {
            "category":"Organizations",
            "subcategory":"Professional Association",
            "type":"Services"
        }
    ],
    "sg:phone":"+61 404 862 920",
    "sg:postcode":"4560",
    "sg:province":"QLD",
    "sg:tags":[
        "web",
        "internet"
    ],
    "wof:name":"Sunsite Web Design",
    "wof:placetype":"venue"
},
  "geometry": {"coordinates":[152.98306274399999,-26.6161994934],"type":"Point"}
}