{
  "type": "Feature",
  "properties": {
    "iso:country":"AU",
    "sg:address":"Shop 12, Westfield Shoppingtown, Cnr Aird & Marsde",
    "sg:city":"Parramatta",
    "sg:classifiers":[
        {
            "category":"Health Services",
            "subcategory":"Doctor",
            "type":"Services"
        }
    ],
    "sg:phone":"+61 2 9689 2244",
    "sg:postcode":"2150",
    "sg:province":"NSW",
    "sg:tags":[
        "medical",
        "practitioner"
    ],
    "wof:name":"Fee Lai Dr.",
    "wof:placetype":"venue"
},
  "geometry": {"coordinates":[151.000854492,-33.8173675537],"type":"Point"}
}