{
  "type": "Feature",
  "properties": {
    "addr:full":"176 Gisborne Rd Bacchus Marsh VIC 3340",
    "addr:housenumber":"176",
    "addr:postcode":"3340",
    "addr:street":"Gisborne Rd",
    "iso:country":"AU",
    "sg:address":"176 Gisborne Rd",
    "sg:city":"Bacchus Marsh",
    "sg:classifiers":[
        {
            "category":"Education",
            "subcategory":"Kindergarten",
            "type":"Public Place"
        }
    ],
    "sg:phone":"+61 3 5367 7706",
    "sg:postcode":"3340",
    "sg:province":"VIC",
    "sg:tags":[
        "pre-schools"
    ],
    "wof:name":"Bacchus Marsh Montessori Pre School & Play Groups",
    "wof:placetype":"venue"
},
  "geometry": {"coordinates":[144.43817100000001,-37.665527],"type":"Point"}
}