{
  "type": "Feature",
  "properties": {
    "iso:country":"AU",
    "sg:address":"45 Acacia Rd",
    "sg:city":"Karawatha",
    "sg:classifiers":[
        {
            "category":"Education",
            "subcategory":"School",
            "type":"Public Place"
        }
    ],
    "sg:phone":"+61 7 3841 3645",
    "sg:postcode":"4117",
    "sg:province":"QLD",
    "sg:tags":[
        "co-educational"
    ],
    "wof:name":"Islamic School of Brisbane Ltd",
    "wof:placetype":"venue"
},
  "geometry": {"coordinates":[153.09588623100001,-27.6254692078],"type":"Point"}
}