{
  "type": "Feature",
  "properties": {
    "iso:country":"AU",
    "sg:address":"50 Kiewa East Rd",
    "sg:city":"Tangambalanga",
    "sg:classifiers":[
        {
            "category":"Manufacturing",
            "subcategory":"Motor Vehicles & Parts",
            "type":"Manufacturing & Wholesale Goods"
        }
    ],
    "sg:phone":"+61 2 6027 3433",
    "sg:postcode":"3691",
    "sg:province":"VIC",
    "sg:tags":[
        "engine",
        "equipment",
        "diesel"
    ],
    "wof:name":"Dewar's Performance Engines",
    "wof:placetype":"venue"
},
  "geometry": {"coordinates":[147.029617,-36.252514],"type":"Point"}
}