{
  "type": "Feature",
  "properties": {
    "iso:country":"AU",
    "sg:address":"4a Dallas Court",
    "sg:city":"Narre Warren",
    "sg:classifiers":[
        {
            "category":"Utilities",
            "subcategory":"Electric",
            "type":"Services"
        }
    ],
    "sg:phone":"+61 400 152 023",
    "sg:postcode":"3805",
    "sg:province":"VIC",
    "sg:tags":[
        "electrical",
        "contractor"
    ],
    "sg:website":"http://www.arnoldelectrical.com.au",
    "wof:name":"Arnold Electrical Pty Ltd",
    "wof:placetype":"venue"
},
  "geometry": {"coordinates":[145.305588,-38.02042],"type":"Point"}
}