{
  "type": "Feature",
  "properties": {
    "iso:country":"AU",
    "sg:address":"66 Bell St",
    "sg:city":"Yarra Glen",
    "sg:classifiers":[
        {
            "category":"Retail",
            "subcategory":"Auto Repair",
            "type":"Services"
        }
    ],
    "sg:phone":"+61 3 9730 1805",
    "sg:postcode":"3775",
    "sg:province":"VIC",
    "sg:tags":[
        "repairer",
        "motor",
        "engineer"
    ],
    "wof:name":"Yarra View Motors Pty Ltd",
    "wof:placetype":"venue"
},
  "geometry": {"coordinates":[145.375046,-37.654057],"type":"Point"}
}