{
  "type": "Feature",
  "properties": {
    "addr:full":"43 Moreton Pde Caloundra QLD 4551",
    "addr:housenumber":"43",
    "addr:postcode":"4551",
    "addr:street":"Moreton Pde",
    "iso:country":"AU",
    "sg:address":"43 Moreton Pde",
    "sg:city":"Caloundra",
    "sg:classifiers":[
        {
            "category":"Real Estate",
            "subcategory":"Real Estate Agent",
            "type":"Services"
        }
    ],
    "sg:phone":"+61 7 5491 3344",
    "sg:postcode":"4551",
    "sg:province":"QLD",
    "wof:name":"Ken Guy Real Estate",
    "wof:placetype":"venue"
},
  "geometry": {"coordinates":[153.13621520999999,-26.8047428131],"type":"Point"}
}