{
  "type": "Feature",
  "properties": {
    "addr:full":"16 Crown St Dubbo NSW 2830",
    "addr:housenumber":"16",
    "addr:postcode":"2830",
    "addr:street":"Crown St",
    "iso:country":"AU",
    "sg:address":"16 Crown St",
    "sg:city":"Dubbo",
    "sg:classifiers":[
        {
            "category":"Farming",
            "subcategory":"Farm & Veterinary Services",
            "type":"Manufacturing & Wholesale Goods"
        }
    ],
    "sg:phone":"+61 2 6884 4382",
    "sg:postcode":"2830",
    "sg:province":"NSW",
    "sg:tags":[
        "shearing",
        "contractor"
    ],
    "wof:name":"Shearpak 2000 (Australia) Pty Ltd",
    "wof:placetype":"venue"
},
  "geometry": {"coordinates":[148.61705017099999,-32.2645874023],"type":"Point"}
}