{
  "type": "Feature",
  "properties": {
    "addr:full":"Gound Floor 479 Warrigal Rd Moorabbin VIC 3189",
    "addr:housenumber":"479",
    "addr:postcode":"3189",
    "addr:street":"Warrigal Rd",
    "iso:country":"AU",
    "sg:address":"Gound Floor 479 Warrigal Rd",
    "sg:city":"Moorabbin",
    "sg:classifiers":[
        {
            "category":"Building & Trades",
            "subcategory":"Construction",
            "type":"Services"
        }
    ],
    "sg:phone":"+61 3 9555 3999",
    "sg:postcode":"3189",
    "sg:province":"VIC",
    "sg:tags":[
        "contractor"
    ],
    "wof:name":"Merkon Constructions Pty Ltd",
    "wof:placetype":"venue"
},
  "geometry": {"coordinates":[145.078216553,-37.9447822571],"type":"Point"}
}