{
  "type": "Feature",
  "properties": {
    "iso:country":"AU",
    "sg:address":"1/ 41 Gatwick Rd",
    "sg:city":"Bayswater North",
    "sg:classifiers":[
        {
            "category":"Wholesale",
            "subcategory":"Electrical",
            "type":"Manufacturing & Wholesale Goods"
        }
    ],
    "sg:phone":"+61 3 9761 6777",
    "sg:postcode":"3153",
    "sg:province":"VIC",
    "sg:tags":[
        "wholesaler",
        "mfrs",
        "accessory"
    ],
    "wof:name":"Horizon Electronic Components Pty Ltd",
    "wof:placetype":"venue"
},
  "geometry": {"coordinates":[145.29689025900001,-37.8203659058],"type":"Point"}
}