{
  "type": "Feature",
  "properties": {
    "addr:full":"Level 3 101 Sussex St Sydney NSW 2000",
    "addr:housenumber":"101",
    "addr:postcode":"2000",
    "addr:street":"Sussex St",
    "iso:country":"AU",
    "sg:address":"Level 3 101 Sussex St",
    "sg:city":"Sydney",
    "sg:classifiers":[
        {
            "category":"Building & Trades",
            "subcategory":"Landscaping Services",
            "type":"Services"
        }
    ],
    "sg:phone":"+61 2 9290 2722",
    "sg:postcode":"2000",
    "sg:province":"NSW",
    "sg:tags":[
        "architect",
        "landscape"
    ],
    "wof:name":"Jackson Teece",
    "wof:placetype":"venue"
},
  "geometry": {"coordinates":[151.20335388199999,-33.8677024841],"type":"Point"}
}