{
  "type": "Feature",
  "properties": {
    "addr:full":"Croom Rd Albion Park Rail NSW 2527",
    "addr:postcode":"2527",
    "addr:street":"Croom Rd",
    "iso:country":"AU",
    "sg:address":"Croom Rd",
    "sg:city":"Albion Park Rail",
    "sg:classifiers":[
        {
            "category":"Sports & Exercise",
            "subcategory":"Sports Center",
            "type":"Entertainment"
        }
    ],
    "sg:phone":"+61 2 4257 3468",
    "sg:postcode":"2527",
    "sg:province":"NSW",
    "sg:tags":[
        "ground"
    ],
    "wof:name":"Shellharbour City Stadium",
    "wof:placetype":"venue"
},
  "geometry": {"coordinates":[150.79293823200001,-34.5833129883],"type":"Point"}
}