{
  "type": "Feature",
  "properties": {
    "iso:country":"AU",
    "sg:address":"7 Orbon St",
    "sg:city":"Rostrevor",
    "sg:classifiers":[
        {
            "category":"Retail",
            "subcategory":"Car Wash",
            "type":"Services"
        }
    ],
    "sg:phone":"+61 401 623 006",
    "sg:postcode":"5073",
    "sg:province":"SA",
    "sg:tags":[
        "truck",
        "cleaning"
    ],
    "wof:name":"Absolute Detailing",
    "wof:placetype":"venue"
},
  "geometry": {"coordinates":[138.70001220699999,-34.8891601562],"type":"Point"}
}