{
  "type": "Feature",
  "properties": {
    "addr:full":"48 Burswood Rd Victoria Park WA 6100",
    "addr:housenumber":"48",
    "addr:postcode":"6100",
    "addr:street":"Burswood Rd",
    "iso:country":"AU",
    "sg:address":"48 Burswood Rd",
    "sg:city":"Victoria Park",
    "sg:classifiers":[
        {
            "category":"Autos & Motor Vehicles",
            "subcategory":"Automobile Sales",
            "type":"Retail Goods"
        }
    ],
    "sg:phone":"+61 8 9311 7533",
    "sg:postcode":"6100",
    "sg:province":"WA",
    "sg:tags":[
        "car",
        "new"
    ],
    "wof:name":"MINI",
    "wof:placetype":"venue"
},
  "geometry": {"coordinates":[115.893051148,-31.9679813385],"type":"Point"}
}