{
  "type": "Feature",
  "properties": {
    "iso:country":"AU",
    "sg:address":"11 Lennox St",
    "sg:city":"Campbelltown",
    "sg:classifiers":[
        {
            "category":"Wholesale",
            "subcategory":"Non-durable Goods",
            "type":"Manufacturing & Wholesale Goods"
        }
    ],
    "sg:phone":"+61 413 332 738",
    "sg:postcode":"5074",
    "sg:province":"SA",
    "sg:tags":[
        "wholesaler",
        "mfrs",
        "cosmetic"
    ],
    "wof:name":"CFC Agency",
    "wof:placetype":"venue"
},
  "geometry": {"coordinates":[138.66261291500001,-34.8820533752],"type":"Point"}
}