{
  "type": "Feature",
  "properties": {
    "iso:country":"AU",
    "sg:address":"60 Laidley-Plainland Rd",
    "sg:city":"Plainland",
    "sg:classifiers":[
        {
            "category":"Building & Trades",
            "subcategory":"Construction",
            "type":"Services"
        }
    ],
    "sg:phone":"+61 419 775 344",
    "sg:postcode":"4341",
    "sg:province":"QLD",
    "sg:tags":[
        "earth",
        "excavating",
        "moving",
        "contractor"
    ],
    "wof:name":"Kandelka Pty Ltd",
    "wof:placetype":"venue"
},
  "geometry": {"coordinates":[152.420654297,-27.5668563843],"type":"Point"}
}