{
  "type": "Feature",
  "properties": {
    "iso:country":"AU",
    "sg:address":"2- 10 Second Ave",
    "sg:city":"Blacktown",
    "sg:classifiers":[
        {
            "category":"Autos & Motor Vehicles",
            "subcategory":"Automobile Sales",
            "type":"Retail Goods"
        }
    ],
    "sg:phone":"+61 2 9672 4444",
    "sg:postcode":"2148",
    "sg:province":"NSW",
    "sg:tags":[
        "car",
        "used"
    ],
    "wof:name":"Sydneys Best Cars & 4WDs",
    "wof:placetype":"venue"
},
  "geometry": {"coordinates":[150.91180419899999,-33.7671546936],"type":"Point"}
}