{
  "type": "Feature",
  "properties": {
    "addr:full":"8 Norton St Ballina NSW 2478",
    "addr:housenumber":"8",
    "addr:postcode":"2478",
    "addr:street":"Norton St",
    "iso:country":"AU",
    "sg:address":"8 Norton St",
    "sg:city":"Ballina",
    "sg:classifiers":[
        {
            "category":"Food & Beverages",
            "subcategory":"Fruits & Vegetables",
            "type":"Retail Goods"
        }
    ],
    "sg:phone":"+61 2 6686 8311",
    "sg:postcode":"2478",
    "sg:province":"NSW",
    "sg:tags":[
        "greengrocer",
        "fruiterer"
    ],
    "wof:name":"East Side Fruit Supplies",
    "wof:placetype":"venue"
},
  "geometry": {"coordinates":[153.56556701700001,-28.8724212646],"type":"Point"}
}