{
  "type": "Feature",
  "properties": {
    "addr:full":"4 Rothwell Ave Concord West NSW 2138",
    "addr:housenumber":"4",
    "addr:postcode":"2138",
    "addr:street":"Rothwell Ave",
    "iso:country":"AU",
    "sg:address":"4 Rothwell Ave",
    "sg:city":"Concord West",
    "sg:classifiers":[
        {
            "category":"Building & Trades",
            "subcategory":"Construction",
            "type":"Services"
        }
    ],
    "sg:phone":"+61 2 9736 3911",
    "sg:postcode":"2138",
    "sg:province":"NSW",
    "sg:tags":[
        "concrete",
        "treatment",
        "repair"
    ],
    "wof:name":"C.T.I. Consultants Pty Ltd",
    "wof:placetype":"venue"
},
  "geometry": {"coordinates":[151.0834198,-33.8516731262],"type":"Point"}
}