{
  "type": "Feature",
  "properties": {
    "addr:full":"2b Lindsay Rd Wangara WA 6065",
    "addr:housenumber":"2b",
    "addr:postcode":"6065",
    "addr:street":"Lindsay Rd",
    "iso:country":"AU",
    "sg:address":"2b Lindsay Rd",
    "sg:city":"Wangara",
    "sg:classifiers":[
        {
            "category":"Home & Garden",
            "subcategory":"Mobile Homes",
            "type":"Retail Goods"
        }
    ],
    "sg:phone":"+61 8 9302 3987",
    "sg:postcode":"6065",
    "sg:province":"WA",
    "sg:tags":[
        "motor",
        "campervans"
    ],
    "wof:name":"KB Campers Caravans",
    "wof:placetype":"venue"
},
  "geometry": {"coordinates":[115.82434082,-31.7915382385],"type":"Point"}
}