{
  "type": "Feature",
  "properties": {
    "iso:country":"AU",
    "sg:address":"Suite 2, 1 Oaks Ave",
    "sg:city":"Dee Why",
    "sg:classifiers":[
        {
            "category":"Health Services",
            "subcategory":"Dentist",
            "type":"Services"
        }
    ],
    "sg:phone":"+61 2 9972 1553",
    "sg:postcode":"2099",
    "sg:province":"NSW",
    "wof:name":"Peek Gregory J",
    "wof:placetype":"venue"
},
  "geometry": {"coordinates":[151.28578185999999,-33.7536315918],"type":"Point"}
}