{
  "type": "Feature",
  "properties": {
    "iso:country":"AU",
    "sg:address":"2 Nethercote Drv",
    "sg:city":"Mt Waverley",
    "sg:classifiers":[
        {
            "category":"Professional",
            "subcategory":"Art Services",
            "type":"Services"
        }
    ],
    "sg:phone":"+61 3 9888 1964",
    "sg:postcode":"3149",
    "sg:province":"VIC",
    "sg:tags":[
        "decorator",
        "painter"
    ],
    "wof:name":"Celtic Decor",
    "wof:placetype":"venue"
},
  "geometry": {"coordinates":[145.129562378,-37.8663024902],"type":"Point"}
}