{
  "type": "Feature",
  "properties": {
    "iso:country":"AU",
    "sg:address":"773 High St",
    "sg:city":"Thornbury",
    "sg:classifiers":[
        {
            "category":"Wholesale",
            "subcategory":"Furniture",
            "type":"Manufacturing & Wholesale Goods"
        }
    ],
    "sg:phone":"+61 3 9484 2883",
    "sg:postcode":"3071",
    "sg:province":"VIC",
    "sg:tags":[
        "wholesaler",
        "mfrs"
    ],
    "wof:name":"Best Home Furniture & Bedding",
    "wof:placetype":"venue"
},
  "geometry": {"coordinates":[145.00067138700001,-37.7573318481],"type":"Point"}
}