{
  "type": "Feature",
  "properties": {
    "addr:full":"39 Blamey Drv Currumbin QLD 4223",
    "addr:housenumber":"39",
    "addr:postcode":"4223",
    "addr:street":"Blamey Drv",
    "iso:country":"AU",
    "sg:address":"39 Blamey Drv",
    "sg:city":"Currumbin",
    "sg:classifiers":[
        {
            "category":"Professional",
            "subcategory":"Art Services",
            "type":"Services"
        }
    ],
    "sg:phone":"+61 7 5534 3000",
    "sg:postcode":"4223",
    "sg:province":"QLD",
    "sg:tags":[
        "decorator",
        "painter"
    ],
    "wof:name":"Malkin P A & T L",
    "wof:placetype":"venue"
},
  "geometry": {"coordinates":[153.48526000999999,-28.1429386139],"type":"Point"}
}