{
  "type": "Feature",
  "properties": {
    "iso:country":"AU",
    "sg:address":"Suite 1 102 Burnett St",
    "sg:city":"Buderim",
    "sg:classifiers":[
        {
            "category":"Health Services",
            "subcategory":"Dentist",
            "type":"Services"
        }
    ],
    "sg:phone":"+61 7 5476 5400",
    "sg:postcode":"4556",
    "sg:province":"QLD",
    "wof:name":"ABC Dentistry",
    "wof:placetype":"venue"
},
  "geometry": {"coordinates":[153.04702758799999,-26.68841362],"type":"Point"}
}