{
  "type": "Feature",
  "properties": {
    "iso:country":"AU",
    "sg:address":"169 Swan St",
    "sg:city":"Richmond",
    "sg:classifiers":[
        {
            "category":"Food & Beverages",
            "subcategory":"Groceries & Convenience Stores",
            "type":"Retail Goods"
        }
    ],
    "sg:phone":"+61 3 9428 5563",
    "sg:postcode":"3121",
    "sg:province":"VIC",
    "wof:name":"Indian Spice Mart",
    "wof:placetype":"venue"
},
  "geometry": {"coordinates":[144.99717712399999,-37.8254547119],"type":"Point"}
}