{
  "type": "Feature",
  "properties": {
    "addr:full":"111 Woodville Rd Granville NSW 2142",
    "addr:housenumber":"111",
    "addr:postcode":"2142",
    "addr:street":"Woodville Rd",
    "iso:country":"AU",
    "sg:address":"111 Woodville Rd",
    "sg:city":"Granville",
    "sg:classifiers":[
        {
            "category":"Professional",
            "type":"Services"
        }
    ],
    "sg:phone":"+61 418 441 211",
    "sg:postcode":"2142",
    "sg:province":"NSW",
    "sg:tags":[
        "courier"
    ],
    "wof:name":"C G Contractors",
    "wof:placetype":"venue"
},
  "geometry": {"coordinates":[151.00173950199999,-33.8354225159],"type":"Point"}
}