{
  "type": "Feature",
  "properties": {
    "addr:full":"Shop 2/ 64a Farnborough Rd Yeppoon QLD 4703",
    "addr:housenumber":"shop 2 / 64a",
    "addr:postcode":"4703",
    "addr:street":"Farnborough Rd",
    "iso:country":"AU",
    "sg:address":"Shop 2/ 64a Farnborough Rd",
    "sg:city":"Yeppoon",
    "sg:classifiers":[
        {
            "category":"Personal",
            "subcategory":"Beauty Salon",
            "type":"Services"
        }
    ],
    "sg:phone":"+61 7 4939 2680",
    "sg:postcode":"4703",
    "sg:province":"QLD",
    "sg:tags":[
        "hairdresser"
    ],
    "wof:name":"Karens Klips",
    "wof:placetype":"venue"
},
  "geometry": {"coordinates":[150.74888610799999,-23.1184902191],"type":"Point"}
}