{
  "type": "Feature",
  "properties": {
    "addr:full":"101 Norman St Woolloongabba QLD 4102",
    "addr:housenumber":"101",
    "addr:postcode":"4102",
    "addr:street":"Norman St",
    "iso:country":"AU",
    "sg:address":"101 Norman St",
    "sg:city":"Woolloongabba",
    "sg:classifiers":[
        {
            "category":"Professional",
            "subcategory":"Printing & Photocopies",
            "type":"Services"
        }
    ],
    "sg:phone":"+61 7 3895 8388",
    "sg:postcode":"4102",
    "sg:province":"QLD",
    "sg:tags":[
        "embroidery"
    ],
    "wof:name":"Hi Tech Embroidery Qld Pty Ltd",
    "wof:placetype":"venue"
},
  "geometry": {"coordinates":[153.044555664,-27.4917221069],"type":"Point"}
}