{
  "type": "Feature",
  "properties": {
    "iso:country":"AU",
    "sg:address":"R M B 593",
    "sg:city":"Murtoa",
    "sg:classifiers":[
        {
            "category":"Communications",
            "type":"Services"
        }
    ],
    "sg:phone":"+61 3 5385 2467",
    "sg:postcode":"3390",
    "sg:province":"VIC",
    "sg:tags":[
        "public",
        "system",
        "address"
    ],
    "wof:name":"Superior Sound Public Address System",
    "wof:placetype":"venue"
},
  "geometry": {"coordinates":[142.47401428200001,-36.6201515198],"type":"Point"}
}