{
  "type": "Feature",
  "properties": {
    "addr:full":"12 Prospect St Bowen Hills QLD 4006",
    "addr:housenumber":"12",
    "addr:postcode":"4006",
    "addr:street":"Prospect St",
    "iso:country":"AU",
    "sg:address":"12 Prospect St",
    "sg:city":"Bowen Hills",
    "sg:classifiers":[
        {
            "category":"Education",
            "subcategory":"Music School",
            "type":"Public Place"
        }
    ],
    "sg:phone":"+61 7 3216 1110",
    "sg:postcode":"4006",
    "sg:province":"QLD",
    "sg:tags":[
        "teacher"
    ],
    "wof:name":"Jazzworx ! Pty Ltd",
    "wof:placetype":"venue"
},
  "geometry": {"coordinates":[153.03729248100001,-27.4519538879],"type":"Point"}
}