{
  "type": "Feature",
  "properties": {
    "addr:full":"Suite 3A, 1st Floor 379 Victoria Ave Chatswood NSW 2067",
    "addr:housenumber":"379",
    "addr:postcode":"2067",
    "addr:street":"Victoria Ave",
    "iso:country":"AU",
    "sg:address":"Suite 3A, 1st Floor 379 Victoria Ave",
    "sg:city":"Chatswood",
    "sg:classifiers":[
        {
            "category":"Personal",
            "subcategory":"Skin Care",
            "type":"Services"
        }
    ],
    "sg:phone":"+61 2 9415 2893",
    "sg:postcode":"2067",
    "sg:province":"NSW",
    "sg:tags":[
        "treatment"
    ],
    "wof:name":"Weena Skin Care Centre",
    "wof:placetype":"venue"
},
  "geometry": {"coordinates":[151.18539428700001,-33.795463562],"type":"Point"}
}