{
  "type": "Feature",
  "properties": {
    "iso:country":"AU",
    "sg:address":"36 Hay St",
    "sg:city":"Port Macquarie",
    "sg:classifiers":[
        {
            "category":"Shopping",
            "subcategory":"Party Supplies",
            "type":"Retail Goods"
        }
    ],
    "sg:phone":"+61 2 6582 3897",
    "sg:postcode":"2444",
    "sg:province":"NSW",
    "sg:tags":[
        "children's"
    ],
    "wof:name":"Port Jumping Castles",
    "wof:placetype":"venue"
},
  "geometry": {"coordinates":[152.909729,-31.430511],"type":"Point"}
}