{
  "type": "Feature",
  "properties": {
    "iso:country":"AU",
    "sg:address":"U6/ 49 Lavinia St",
    "sg:city":"Athol Park",
    "sg:classifiers":[
        {
            "category":"Home & Garden",
            "subcategory":"Building Materials",
            "type":"Retail Goods"
        }
    ],
    "sg:phone":"+61 8 8341 0655",
    "sg:postcode":"5012",
    "sg:province":"SA",
    "sg:tags":[
        "fire",
        "resistant",
        "supply"
    ],
    "wof:name":"Adelaide Fire Doors Pty Ltd",
    "wof:placetype":"venue"
},
  "geometry": {"coordinates":[138.54432678200001,-34.8542289734],"type":"Point"}
}