{
  "type": "Feature",
  "properties": {
    "addr:full":"PO Box 2127 Henley Beach SA 5022",
    "addr:postcode":"5022",
    "iso:country":"AU",
    "sg:address":"PO Box 2127",
    "sg:city":"Henley Beach",
    "sg:classifiers":[
        {
            "category":"Retail",
            "subcategory":"Auto Rental",
            "type":"Services"
        }
    ],
    "sg:phone":"+61 8 8353 7779",
    "sg:postcode":"5022",
    "sg:province":"SA",
    "sg:tags":[
        "chauffeur",
        "car",
        "hire",
        "driven",
        "limousine"
    ],
    "wof:name":"Shiralee Limousines",
    "wof:placetype":"venue"
},
  "geometry": {"coordinates":[138.49435424800001,-34.9197387695],"type":"Point"}
}