{
  "type": "Feature",
  "properties": {
    "iso:country":"AU",
    "sg:address":"148 Gladstone St",
    "sg:city":"South Melbourne",
    "sg:classifiers":[
        {
            "category":"Professional",
            "subcategory":"Computer Services",
            "type":"Services"
        }
    ],
    "sg:phone":"+61 3 9690 0095",
    "sg:postcode":"3205",
    "sg:province":"VIC",
    "sg:tags":[
        "repairs",
        "upgrade",
        "equipment"
    ],
    "wof:name":"Micro Response",
    "wof:placetype":"venue"
},
  "geometry": {"coordinates":[144.94856300000001,-37.830647],"type":"Point"}
}