{
  "type": "Feature",
  "properties": {
    "iso:country":"AU",
    "sg:address":"21-25 Kialba Rd",
    "sg:city":"Campbelltown",
    "sg:classifiers":[
        {
            "category":"Home & Garden",
            "subcategory":"Building Materials",
            "type":"Retail Goods"
        }
    ],
    "sg:phone":"+61 2 9820 1145",
    "sg:postcode":"2560",
    "sg:province":"NSW",
    "sg:tags":[
        "ventilating",
        "equipment",
        "system"
    ],
    "wof:name":"Natural Ventilation Equipment (IVR)",
    "wof:placetype":"venue"
},
  "geometry": {"coordinates":[150.82231140100001,-34.0568199158],"type":"Point"}
}