{
  "type": "Feature",
  "properties": {
    "addr:full":"1 Catchpole St Macquarie ACT 2614",
    "addr:housenumber":"1",
    "addr:postcode":"2614",
    "addr:street":"Catchpole St",
    "iso:country":"AU",
    "sg:address":"1 Catchpole St",
    "sg:city":"Macquarie",
    "sg:classifiers":[
        {
            "category":"Shopping",
            "subcategory":"Bicycles & Sporting Goods",
            "type":"Retail Goods"
        }
    ],
    "sg:phone":"+61 2 6258 5082",
    "sg:postcode":"2614",
    "sg:province":"ACT",
    "sg:tags":[
        "chemical",
        "equipment",
        "pool",
        "swimming"
    ],
    "wof:name":"Pool Chemical Distributors",
    "wof:placetype":"venue"
},
  "geometry": {"coordinates":[149.06939697300001,-35.2516479492],"type":"Point"}
}