{
  "type": "Feature",
  "properties": {
    "addr:full":"PO Box 6136 Blacktown BC NSW 2148",
    "addr:postcode":"nsw 2148",
    "iso:country":"AU",
    "sg:address":"PO Box 6136",
    "sg:city":"Blacktown BC",
    "sg:classifiers":[
        {
            "category":"Personal",
            "subcategory":"Piercing",
            "type":"Services"
        }
    ],
    "sg:phone":"+61 2 9837 3100",
    "sg:postcode":"2148",
    "sg:province":"NSW",
    "sg:tags":[
        "body",
        "ear"
    ],
    "wof:name":"Henna Body Art",
    "wof:placetype":"venue"
},
  "geometry": {"coordinates":[150.908813477,-33.7629585266],"type":"Point"}
}