{
  "type": "Feature",
  "properties": {
    "iso:country":"AU",
    "sg:address":"Suite 6/Level 2",
    "sg:city":", Skin & Cancer Foundation Australia Westmead",
    "sg:classifiers":[
        {
            "category":"Health Services",
            "subcategory":"Medical Lab",
            "type":"Services"
        }
    ],
    "sg:phone":"+61 2 8353 3030",
    "sg:postcode":"2145",
    "sg:province":"NSW",
    "sg:tags":[
        "medicine",
        "specialist",
        "pathology",
        "oral"
    ],
    "wof:name":"Schifter Mark Dr",
    "wof:placetype":"venue"
},
  "geometry": {"coordinates":[150.99778747600001,-33.8372077942],"type":"Point"}
}