{
  "type": "Feature",
  "properties": {
    "addr:full":"56 Bungaree Rd Toongabbie NSW 2146",
    "addr:housenumber":"56",
    "addr:postcode":"2146",
    "addr:street":"Bungaree Rd",
    "iso:country":"AU",
    "sg:address":"56 Bungaree Rd",
    "sg:city":"Toongabbie",
    "sg:classifiers":[
        {
            "category":"Social Services",
            "subcategory":"Child Care",
            "type":"Services"
        }
    ],
    "sg:phone":"+61 2 9896 0188",
    "sg:postcode":"2146",
    "sg:province":"NSW",
    "wof:name":"Caring 4 Kids Pty Ltd",
    "wof:placetype":"venue"
},
  "geometry": {"coordinates":[150.960037231,-33.7905921936],"type":"Point"}
}