{
  "type": "Feature",
  "properties": {
    "addr:full":"Unit 18 / 3 Rocks St Scarborough QLD 4020",
    "addr:housenumber":"/ 3",
    "addr:postcode":"4020",
    "addr:street":"Rocks St",
    "iso:country":"AU",
    "sg:address":"Unit 18 / 3 Rocks St",
    "sg:city":"Scarborough",
    "sg:classifiers":[
        {
            "category":"Retail",
            "subcategory":"Repair Shop",
            "type":"Services"
        }
    ],
    "sg:phone":"+61 7 3880 1211",
    "sg:postcode":"4020",
    "sg:province":"QLD",
    "sg:tags":[
        "maintenance",
        "pool",
        "swimming"
    ],
    "sg:website":"http://www.rodcameronpools.com.au",
    "wof:name":"Rod Cameron Pools",
    "wof:placetype":"venue"
},
  "geometry": {"coordinates":[153.11468500000001,-27.19817],"type":"Point"}
}