{
  "type": "Feature",
  "properties": {
    "iso:country":"AU",
    "sg:address":"2595 Westernport Rd",
    "sg:city":"Ripplebrook",
    "sg:classifiers":[
        {
            "category":"Train Station",
            "subcategory":"Light Rail",
            "type":"Transportation"
        }
    ],
    "sg:phone":"+61 3 5627 6325",
    "sg:postcode":"3818",
    "sg:province":"VIC",
    "sg:tags":[
        "searchlight"
    ],
    "wof:name":"Night Eater Searchlights",
    "wof:placetype":"venue"
},
  "geometry": {"coordinates":[145.77719099999999,-38.188232],"type":"Point"}
}