{
  "type": "Feature",
  "properties": {
    "addr:full":"Unit 3/ 74 Moss St Slacks Creek QLD 4127",
    "addr:postcode":"4127",
    "addr:street":"Moss St",
    "iso:country":"AU",
    "sg:address":"Unit 3/ 74 Moss St",
    "sg:city":"Slacks Creek",
    "sg:classifiers":[
        {
            "category":"Autos & Motor Vehicles",
            "subcategory":"Auto Supplies",
            "type":"Retail Goods"
        }
    ],
    "sg:phone":"+61 7 3808 6140",
    "sg:postcode":"4127",
    "sg:province":"QLD",
    "sg:tags":[
        "part",
        "cycles",
        "accessory"
    ],
    "sg:website":"http://www.promotorcycles.com.au",
    "wof:name":"Pro Euro",
    "wof:placetype":"venue"
},
  "geometry": {"coordinates":[153.12445068400001,-27.6210842133],"type":"Point"}
}