{
  "type": "Feature",
  "properties": {
    "iso:country":"AU",
    "sg:address":"Lafitte Rd",
    "sg:city":"Wingfield",
    "sg:classifiers":[
        {
            "category":"Fast Food",
            "type":"Food & Drink"
        }
    ],
    "sg:phone":"+61 8 8349 7166",
    "sg:postcode":"5013",
    "sg:province":"SA",
    "sg:tags":[
        "away",
        "take"
    ],
    "wof:name":"Cooks Snack Bar",
    "wof:placetype":"venue"
},
  "geometry": {"coordinates":[138.567871094,-34.8460350037],"type":"Point"}
}