{
  "type": "Feature",
  "properties": {
    "iso:country":"AU",
    "sg:address":"37 Production Ave",
    "sg:city":"Warana",
    "sg:classifiers":[
        {
            "category":"Wholesale",
            "subcategory":"Painting Supplies",
            "type":"Manufacturing & Wholesale Goods"
        }
    ],
    "sg:phone":"+61 7 5493 8944",
    "sg:postcode":"4575",
    "sg:province":"QLD",
    "sg:tags":[
        "equipment",
        "spraying"
    ],
    "wof:name":"Quik Corp (Aust) Pty Ltd",
    "wof:placetype":"venue"
},
  "geometry": {"coordinates":[153.124054,-26.727571],"type":"Point"}
}