{
  "type": "Feature",
  "properties": {
    "addr:full":"121 Wentworth St Port Kembla NSW 2505",
    "addr:housenumber":"121",
    "addr:postcode":"2505",
    "addr:street":"Wentworth St",
    "iso:country":"AU",
    "sg:address":"121 Wentworth St",
    "sg:city":"Port Kembla",
    "sg:classifiers":[
        {
            "category":"Personal",
            "subcategory":"Adult",
            "type":"Services"
        }
    ],
    "sg:phone":"+61 2 4274 2550",
    "sg:postcode":"2505",
    "sg:province":"NSW",
    "sg:tags":[
        "vic",
        "except",
        "state",
        "escort",
        "social",
        "qld"
    ],
    "wof:name":"Satisfaction",
    "wof:placetype":"venue"
},
  "geometry": {"coordinates":[150.90213,-34.481689],"type":"Point"}
}