{
  "type": "Feature",
  "properties": {
    "addr:full":"245 Racecourse Rd Flemington VIC 3031",
    "addr:housenumber":"245",
    "addr:postcode":"3031",
    "addr:street":"Racecourse Rd",
    "iso:country":"AU",
    "sg:address":"245 Racecourse Rd",
    "sg:city":"Flemington",
    "sg:classifiers":[
        {
            "category":"Shopping",
            "subcategory":"Shoes",
            "type":"Retail Goods"
        }
    ],
    "sg:phone":"+61 3 9376 4433",
    "sg:postcode":"3031",
    "sg:province":"VIC",
    "sg:tags":[
        "footwear"
    ],
    "wof:name":"Mediterranean Shoes",
    "wof:placetype":"venue"
},
  "geometry": {"coordinates":[144.933044,-37.788551],"type":"Point"}
}