{
  "type": "Feature",
  "properties": {
    "addr:full":"7 Warwick St Hobart TAS 7001",
    "addr:housenumber":"7",
    "addr:postcode":"7001",
    "addr:street":"Warwick St",
    "iso:country":"AU",
    "sg:address":"7 Warwick St",
    "sg:city":"Hobart",
    "sg:classifiers":[
        {
            "category":"Autos & Motor Vehicles",
            "subcategory":"Auto Supplies",
            "type":"Retail Goods"
        }
    ],
    "sg:phone":"+61 3 6231 5700",
    "sg:postcode":"7001",
    "sg:province":"TAS",
    "sg:tags":[
        "battery",
        "automotive"
    ],
    "wof:name":"Independant Battery Distributors",
    "wof:placetype":"venue"
},
  "geometry": {"coordinates":[147.32386779800001,-42.8740310669],"type":"Point"}
}