{
  "type": "Feature",
  "properties": {
    "addr:full":"Rogers Pl Newman WA 6753",
    "addr:postcode":"6753",
    "addr:street":"Rogers Pl",
    "iso:country":"AU",
    "sg:address":"Rogers Pl",
    "sg:city":"Newman",
    "sg:classifiers":[
        {
            "category":"Organizations",
            "subcategory":"Labor Organization",
            "type":"Services"
        }
    ],
    "sg:phone":"+61 8 9177 8018",
    "sg:postcode":"6753",
    "sg:province":"WA",
    "sg:tags":[
        "union"
    ],
    "wof:name":"Australian Workers Union (Newman)",
    "wof:placetype":"venue"
},
  "geometry": {"coordinates":[119.733222961,-23.356262207],"type":"Point"}
}