{
  "type": "Feature",
  "properties": {
    "addr:full":"27 Mackay St Taree NSW 2430",
    "addr:housenumber":"27",
    "addr:postcode":"2430",
    "addr:street":"Mackay St",
    "iso:country":"AU",
    "sg:address":"27 Mackay St",
    "sg:city":"Taree",
    "sg:classifiers":[
        {
            "category":"Retail",
            "subcategory":"Repair Shop",
            "type":"Services"
        }
    ],
    "sg:phone":"+61 2 6552 4463",
    "sg:postcode":"2430",
    "sg:province":"NSW",
    "sg:tags":[
        "repairing",
        "piano",
        "tuning"
    ],
    "wof:name":"Antony Prince",
    "wof:placetype":"venue"
},
  "geometry": {"coordinates":[152.47807299999999,-31.90321],"type":"Point"}
}