{
  "type": "Feature",
  "properties": {
    "iso:country":"AU",
    "sg:address":"Ground Floor/ 270 Lonsdale St",
    "sg:city":"Melbourne",
    "sg:classifiers":[
        {
            "category":"Food & Beverages",
            "subcategory":"Groceries & Convenience Stores",
            "type":"Retail Goods"
        }
    ],
    "sg:phone":"+61 3 9639 3336",
    "sg:postcode":"3000",
    "sg:province":"VIC",
    "wof:name":"KJG International City Mart",
    "wof:placetype":"venue"
},
  "geometry": {"coordinates":[144.96403503400001,-37.8116340637],"type":"Point"}
}