{
  "type": "Feature",
  "properties": {
    "iso:country":"AU",
    "sg:address":"100 Kitchener Rd",
    "sg:city":"Kedron",
    "sg:classifiers":[
        {
            "category":"Professional",
            "subcategory":"Art Services",
            "type":"Services"
        }
    ],
    "sg:phone":"+61 7 3350 4644",
    "sg:postcode":"4031",
    "sg:province":"QLD",
    "sg:tags":[
        "decorator",
        "painter"
    ],
    "wof:name":"Applikote QLD Pty Ltd",
    "wof:placetype":"venue"
},
  "geometry": {"coordinates":[153.026627,-27.399313],"type":"Point"}
}