{
  "type": "Feature",
  "properties": {
    "iso:country":"AU",
    "sg:address":"PO Box 2152",
    "sg:city":"Palmyra Delivery Cntr",
    "sg:classifiers":[
        {
            "category":"Organizations",
            "subcategory":"Professional Association",
            "type":"Services"
        }
    ],
    "sg:phone":"+61 8 9336 3117",
    "sg:postcode":"6961",
    "sg:province":"WA",
    "sg:tags":[
        "web",
        "internet"
    ],
    "wof:name":"API Interactive",
    "wof:placetype":"venue"
},
  "geometry": {"coordinates":[115.776161,-32.038738],"type":"Point"}
}