{
  "type": "Feature",
  "properties": {
    "addr:full":"39 Duncan St Punchbowl NSW 2196",
    "addr:housenumber":"39",
    "addr:postcode":"2196",
    "addr:street":"Duncan St",
    "iso:country":"AU",
    "sg:address":"39 Duncan St",
    "sg:city":"Punchbowl",
    "sg:classifiers":[
        {
            "category":"Building & Trades",
            "subcategory":"Plumbing",
            "type":"Services"
        }
    ],
    "sg:phone":"+61 2 9759 3734",
    "sg:postcode":"2196",
    "sg:province":"NSW",
    "sg:tags":[
        "plumber",
        "gasfitters"
    ],
    "wof:name":"Aqua International Pty Ltd",
    "wof:placetype":"venue"
},
  "geometry": {"coordinates":[151.059067,-33.931465],"type":"Point"}
}