{
  "type": "Feature",
  "properties": {
    "addr:full":"38 Jacobs Rd Kurrimine Beach QLD 4871",
    "addr:housenumber":"38",
    "addr:postcode":"4871",
    "addr:street":"Jacobs Rd",
    "iso:country":"AU",
    "sg:address":"38 Jacobs Rd",
    "sg:city":"Kurrimine Beach",
    "sg:classifiers":[
        {
            "category":"Freight",
            "type":"Transportation"
        }
    ],
    "sg:phone":"+61 7 4065 6306",
    "sg:postcode":"4871",
    "sg:province":"QLD",
    "sg:tags":[
        "light",
        "carrier"
    ],
    "wof:name":"Azzopardi Frank & John",
    "wof:placetype":"venue"
},
  "geometry": {"coordinates":[146.104614258,-17.7790489197],"type":"Point"}
}