{
  "type": "Feature",
  "properties": {
    "addr:full":"584 Park Rd Park Orchards VIC 3114",
    "addr:housenumber":"584",
    "addr:postcode":"3114",
    "addr:street":"Park Rd",
    "iso:country":"AU",
    "sg:address":"584 Park Rd",
    "sg:city":"Park Orchards",
    "sg:classifiers":[
        {
            "category":"Health Services",
            "subcategory":"Doctor",
            "type":"Services"
        }
    ],
    "sg:phone":"+61 3 9876 1766",
    "sg:postcode":"3114",
    "sg:province":"VIC",
    "sg:tags":[
        "medical",
        "practitioner"
    ],
    "wof:name":"Hayes Annette & May Shirley",
    "wof:placetype":"venue"
},
  "geometry": {"coordinates":[145.216552734,-37.7789840698],"type":"Point"}
}