{
  "type": "Feature",
  "properties": {
    "iso:country":"AU",
    "sg:address":"2 Carmichael Rd",
    "sg:city":"Oakleigh East",
    "sg:classifiers":[
        {
            "category":"Education",
            "subcategory":"Kindergarten",
            "type":"Public Place"
        }
    ],
    "sg:phone":"+61 3 9544 5704",
    "sg:postcode":"3166",
    "sg:province":"VIC",
    "sg:tags":[
        "pre-schools"
    ],
    "wof:name":"St Johns Pre School Centre",
    "wof:placetype":"venue"
},
  "geometry": {"coordinates":[145.113739014,-37.8978691101],"type":"Point"}
}