{
  "type": "Feature",
  "properties": {
    "iso:country":"AU",
    "sg:address":"136 Norton St",
    "sg:city":"Leichhardt",
    "sg:classifiers":[
        {
            "category":"Food & Beverages",
            "subcategory":"Supermarket",
            "type":"Retail Goods"
        }
    ],
    "sg:phone":"+61 2 9550 0091",
    "sg:postcode":"2040",
    "sg:province":"NSW",
    "sg:tags":[
        "grocery",
        "store"
    ],
    "wof:name":"M.F.C. Food Stores",
    "wof:placetype":"venue"
},
  "geometry": {"coordinates":[151.156754,-33.882622],"type":"Point"}
}