{
  "type": "Feature",
  "properties": {
    "addr:full":"Shop 1, 487 Princes Hwy Fairy Meadow NSW 2519",
    "addr:housenumber":"shop 1 487",
    "addr:postcode":"2519",
    "addr:street":"Princes Hwy",
    "iso:country":"AU",
    "sg:address":"Shop 1, 487 Princes Hwy",
    "sg:city":"Fairy Meadow",
    "sg:classifiers":[
        {
            "category":"Retail",
            "subcategory":"Storage",
            "type":"Services"
        }
    ],
    "sg:phone":"+61 2 4285 1005",
    "sg:postcode":"2519",
    "sg:province":"NSW",
    "sg:tags":[
        "equipment",
        "computer",
        "secondhand"
    ],
    "wof:name":"Oz Computer Supplies",
    "wof:placetype":"venue"
},
  "geometry": {"coordinates":[150.89425700000001,-34.386234],"type":"Point"}
}