{
  "type": "Feature",
  "properties": {
    "addr:full":"Cnr Kingsbury Drv & Plenty Rd Bundoora VIC 3083",
    "addr:postcode":"3083",
    "addr:street":"Cnr Kingsbury Drv & Plenty Rd",
    "iso:country":"AU",
    "sg:address":"Cnr Kingsbury Drv & Plenty Rd",
    "sg:city":"Bundoora",
    "sg:classifiers":[
        {
            "category":"Health Services",
            "subcategory":"Health Practitioner",
            "type":"Services"
        }
    ],
    "sg:phone":"+61 3 9473 8770",
    "sg:postcode":"3083",
    "sg:province":"VIC",
    "sg:tags":[
        "physiotherapist"
    ],
    "wof:name":"Takla Amir",
    "wof:placetype":"venue"
},
  "geometry": {"coordinates":[145.058761597,-37.6987876892],"type":"Point"}
}