{
  "type": "Feature",
  "properties": {
    "iso:country":"AU",
    "sg:address":"Clifford House 120 Russell St",
    "sg:city":"Toowoomba",
    "sg:classifiers":[
        {
            "category":"Organizations",
            "subcategory":"Non-profit Organization",
            "type":"Services"
        }
    ],
    "sg:phone":"+61 7 4639 4066",
    "sg:postcode":"4350",
    "sg:province":"QLD",
    "sg:tags":[
        "support",
        "disability",
        "organisation"
    ],
    "wof:name":"Volunteer Friends Program",
    "wof:placetype":"venue"
},
  "geometry": {"coordinates":[151.947403,-27.558294],"type":"Point"}
}