{
  "type": "Feature",
  "properties": {
    "addr:full":"Balanaming La Petersham NSW 2049",
    "addr:postcode":"2049",
    "iso:country":"AU",
    "sg:address":"Balanaming La",
    "sg:city":"Petersham",
    "sg:classifiers":[
        {
            "category":"Home & Garden",
            "subcategory":"Furniture",
            "type":"Retail Goods"
        }
    ],
    "sg:phone":"+61 2 9572 8998",
    "sg:postcode":"2049",
    "sg:province":"NSW",
    "sg:tags":[
        "repair",
        "restoration"
    ],
    "wof:name":"Warwick Upholstery & Design",
    "wof:placetype":"venue"
},
  "geometry": {"coordinates":[151.152985,-33.89621],"type":"Point"}
}