{
  "type": "Feature",
  "properties": {
    "addr:full":"Lvl 3/ 490 Upper Edward St Spring Hill QLD 4000",
    "addr:housenumber":"/ 490",
    "addr:postcode":"4000",
    "addr:street":"Upper Edward St",
    "iso:country":"AU",
    "sg:address":"Lvl 3/ 490 Upper Edward St",
    "sg:city":"Spring Hill",
    "sg:classifiers":[
        {
            "category":"Banks & Credit Unions",
            "subcategory":"Financial Services",
            "type":"Services"
        }
    ],
    "sg:phone":"+61 7 3839 1130",
    "sg:postcode":"4000",
    "sg:province":"QLD",
    "sg:tags":[
        "planning"
    ],
    "wof:name":"Money Mentors",
    "wof:placetype":"venue"
},
  "geometry": {"coordinates":[153.02406310999999,-27.4628295898],"type":"Point"}
}