{
  "type": "Feature",
  "properties": {
    "iso:country":"AU",
    "sg:address":"Yarrie Lake Rd",
    "sg:city":"Narrabri",
    "sg:classifiers":[
        {
            "category":"Utilities",
            "subcategory":"Fuel Oil & Lpg",
            "type":"Services"
        }
    ],
    "sg:phone":"+61 2 6792 3656",
    "sg:postcode":"2390",
    "sg:province":"NSW",
    "sg:tags":[
        "olive"
    ],
    "wof:name":"Bohena Olives",
    "wof:placetype":"venue"
},
  "geometry": {"coordinates":[149.766845703,-30.3389701843],"type":"Point"}
}