{
  "type": "Feature",
  "properties": {
    "addr:full":"25- 27 Darling St Mitchell ACT 2911",
    "addr:housenumber":"27",
    "addr:postcode":"2911",
    "addr:street":"Darling St",
    "iso:country":"AU",
    "sg:address":"25- 27 Darling St",
    "sg:city":"Mitchell",
    "sg:classifiers":[
        {
            "category":"Education",
            "subcategory":"Special Training",
            "type":"Public Place"
        }
    ],
    "sg:phone":"+61 2 6163 6699",
    "sg:postcode":"2911",
    "sg:province":"ACT",
    "sg:tags":[
        "development"
    ],
    "wof:name":"Electro Group Training",
    "wof:placetype":"venue"
},
  "geometry": {"coordinates":[149.14352417000001,-35.2190895081],"type":"Point"}
}