{
  "type": "Feature",
  "properties": {
    "addr:full":"2 Metcalf St Wallsend NSW 2287",
    "addr:housenumber":"2",
    "addr:postcode":"2287",
    "addr:street":"Metcalf St",
    "iso:country":"AU",
    "sg:address":"2 Metcalf St",
    "sg:city":"Wallsend",
    "sg:classifiers":[
        {
            "category":"Autos & Motor Vehicles",
            "subcategory":"Automobile Sales",
            "type":"Retail Goods"
        }
    ],
    "sg:phone":"+61 2 4965 6466",
    "sg:postcode":"2287",
    "sg:province":"NSW",
    "sg:tags":[
        "car",
        "used"
    ],
    "wof:name":"French Bros Motors",
    "wof:placetype":"venue"
},
  "geometry": {"coordinates":[151.669433594,-32.9033737183],"type":"Point"}
}