{
  "type": "Feature",
  "properties": {
    "iso:country":"AU",
    "sg:address":"493 Centre Rd",
    "sg:city":"Bentleigh",
    "sg:classifiers":[
        {
            "category":"Health Services",
            "subcategory":"Health Practitioner",
            "type":"Services"
        }
    ],
    "sg:phone":"+61 3 9557 8930",
    "sg:postcode":"3204",
    "sg:province":"VIC",
    "sg:tags":[
        "acupuncture"
    ],
    "wof:name":"Newton Gillian",
    "wof:placetype":"venue"
},
  "geometry": {"coordinates":[145.04281599999999,-37.918819],"type":"Point"}
}