{
  "type": "Feature",
  "properties": {
    "addr:full":"Unit 4/ 10 Crompton Rd Rockingham WA 6168",
    "addr:housenumber":"10",
    "addr:postcode":"6168",
    "addr:street":"Crompton Rd",
    "iso:country":"AU",
    "sg:address":"Unit 4/ 10 Crompton Rd",
    "sg:city":"Rockingham",
    "sg:classifiers":[
        {
            "category":"Retail",
            "subcategory":"Auto Repair",
            "type":"Services"
        }
    ],
    "sg:phone":"+61 8 9527 8066",
    "sg:postcode":"6168",
    "sg:province":"WA",
    "sg:tags":[
        "electrical"
    ],
    "wof:name":"Harness Master Wiring Systems",
    "wof:placetype":"venue"
},
  "geometry": {"coordinates":[115.76561700000001,-32.275105],"type":"Point"}
}