{
  "type": "Feature",
  "properties": {
    "addr:full":"424 Scarborough Beach Rd Osborne Park WA 6017",
    "addr:housenumber":"424",
    "addr:postcode":"6017",
    "addr:street":"Scarborough Beach Rd",
    "iso:country":"AU",
    "sg:address":"424 Scarborough Beach Rd",
    "sg:city":"Osborne Park",
    "sg:classifiers":[
        {
            "category":"Education",
            "subcategory":"School",
            "type":"Public Place"
        }
    ],
    "sg:phone":"+61 8 9443 0955",
    "sg:postcode":"6017",
    "sg:province":"WA",
    "sg:tags":[
        "supply"
    ],
    "wof:name":"Wooldridges A&M",
    "wof:placetype":"venue"
},
  "geometry": {"coordinates":[115.812423706,-31.9085636139],"type":"Point"}
}