{
  "type": "Feature",
  "properties": {
    "iso:country":"AU",
    "sg:address":"Shp 11, 168 Guildford Rd",
    "sg:city":"Maylands",
    "sg:classifiers":[
        {
            "category":"Shopping",
            "subcategory":"Crafts & Fabrics",
            "type":"Retail Goods"
        }
    ],
    "sg:phone":"+61 8 9271 2100",
    "sg:postcode":"6051",
    "sg:province":"WA",
    "sg:tags":[
        "supply"
    ],
    "wof:name":"Nymboida Crystal Pty Ltd",
    "wof:placetype":"venue"
},
  "geometry": {"coordinates":[115.895058,-31.930023],"type":"Point"}
}