{
  "type": "Feature",
  "properties": {
    "addr:full":"87 Cheltenham Rd Cheltenham NSW 2119",
    "addr:housenumber":"87",
    "addr:postcode":"2119",
    "addr:street":"Cheltenham Rd",
    "iso:country":"AU",
    "sg:address":"87 Cheltenham Rd",
    "sg:city":"Cheltenham",
    "sg:classifiers":[
        {
            "category":"Banks & Credit Unions",
            "subcategory":"Financial Services",
            "type":"Services"
        }
    ],
    "sg:phone":"+61 438 371 731",
    "sg:postcode":"2119",
    "sg:province":"NSW",
    "sg:tags":[
        "loan",
        "finance",
        "mortgage"
    ],
    "wof:name":"Findlay Felicity",
    "wof:placetype":"venue"
},
  "geometry": {"coordinates":[151.07293701200001,-33.7609558105],"type":"Point"}
}