{
  "type": "Feature",
  "properties": {
    "addr:full":"PO Box 1074 Cooma NSW 2630",
    "addr:postcode":"2630",
    "iso:country":"AU",
    "sg:address":"PO Box 1074",
    "sg:city":"Cooma",
    "sg:classifiers":[
        {
            "category":"Health Services",
            "subcategory":"Health Practitioner",
            "type":"Services"
        }
    ],
    "sg:phone":"+61 2 6452 3381",
    "sg:postcode":"2630",
    "sg:province":"NSW",
    "sg:tags":[
        "psychologist"
    ],
    "wof:name":"Snowy Mts Assessment & Counselling",
    "wof:placetype":"venue"
},
  "geometry": {"coordinates":[149.13154602,-36.2323493958],"type":"Point"}
}