{
  "type": "Feature",
  "properties": {
    "addr:full":"Shop 11 48 Hill St Cabramatta NSW 2166",
    "addr:housenumber":"shop 11 48",
    "addr:postcode":"2166",
    "addr:street":"Hill St",
    "iso:country":"AU",
    "sg:address":"Shop 11 48 Hill St",
    "sg:city":"Cabramatta",
    "sg:classifiers":[
        {
            "category":"Shopping",
            "subcategory":"Jewelry",
            "type":"Retail Goods"
        }
    ],
    "sg:phone":"+61 2 9727 7384",
    "sg:postcode":"2166",
    "sg:province":"NSW",
    "sg:tags":[
        "jeweller"
    ],
    "wof:name":"Aimy",
    "wof:placetype":"venue"
},
  "geometry": {"coordinates":[150.93391418499999,-33.8942832947],"type":"Point"}
}