{
  "type": "Feature",
  "properties": {
    "addr:full":"Shp 2/ 31 Shields St Cairns QLD 4870",
    "addr:housenumber":"/ 31",
    "addr:postcode":"4870",
    "addr:street":"Shields St",
    "iso:country":"AU",
    "sg:address":"Shp 2/ 31 Shields St",
    "sg:city":"Cairns",
    "sg:classifiers":[
        {
            "category":"Internet Cafe",
            "subcategory":"None",
            "type":"Food & Drink"
        }
    ],
    "sg:phone":"+61 7 4041 4962",
    "sg:postcode":"4870",
    "sg:province":"QLD",
    "wof:name":"Reff Highspeed Netcafe",
    "wof:placetype":"venue"
},
  "geometry": {"coordinates":[145.77491760300001,-16.9229221344],"type":"Point"}
}