{
  "type": "Feature",
  "properties": {
    "addr:full":"19 Hindman St Port Macquarie NSW 2444",
    "addr:housenumber":"19",
    "addr:postcode":"2444",
    "addr:street":"Hindman St",
    "iso:country":"AU",
    "sg:address":"19 Hindman St",
    "sg:city":"Port Macquarie",
    "sg:classifiers":[
        {
            "category":"Health Services",
            "subcategory":"Doctor",
            "type":"Services"
        }
    ],
    "sg:phone":"+61 2 6583 1601",
    "sg:postcode":"2444",
    "sg:province":"NSW",
    "sg:tags":[
        "podiatrist"
    ],
    "wof:name":"Hemsley Sarah",
    "wof:placetype":"venue"
},
  "geometry": {"coordinates":[152.91572600000001,-31.441257],"type":"Point"}
}