{
  "type": "Feature",
  "properties": {
    "iso:country":"AU",
    "sg:address":"176 Banksia Rd",
    "sg:city":"Greenacre",
    "sg:classifiers":[
        {
            "category":"Utilities",
            "subcategory":"Electric",
            "type":"Services"
        }
    ],
    "sg:phone":"+61 2 9796 1325",
    "sg:postcode":"2190",
    "sg:province":"NSW",
    "sg:tags":[
        "electrical",
        "contractor"
    ],
    "wof:name":"R J Ward",
    "wof:placetype":"venue"
},
  "geometry": {"coordinates":[151.042603,-33.906845],"type":"Point"}
}