{
  "type": "Feature",
  "properties": {
    "addr:full":"57C Aerodrome Rd Maroochydore QLD 4558",
    "addr:housenumber":"57c",
    "addr:postcode":"4558",
    "addr:street":"Aerodrome Rd",
    "iso:country":"AU",
    "sg:address":"57C Aerodrome Rd",
    "sg:city":"Maroochydore",
    "sg:classifiers":[
        {
            "category":"Wholesale",
            "subcategory":"Apparel",
            "type":"Manufacturing & Wholesale Goods"
        }
    ],
    "sg:phone":"+61 7 5451 0855",
    "sg:postcode":"4558",
    "sg:province":"QLD",
    "sg:tags":[
        "wholesaler",
        "men's",
        "mfrs",
        "sportswear"
    ],
    "sg:website":"http://www.mudsweatgear.com.au/",
    "wof:name":"KooGa Mud, Sweat & Gear",
    "wof:placetype":"venue"
},
  "geometry": {"coordinates":[153.099487305,-26.6597137451],"type":"Point"}
}