{
  "type": "Feature",
  "properties": {
    "iso:country":"AU",
    "sg:address":"20 Clem Hill St",
    "sg:city":"Gordon",
    "sg:classifiers":[
        {
            "category":"Building & Trades",
            "subcategory":"Construction",
            "type":"Services"
        }
    ],
    "sg:phone":"+61 414 731 135",
    "sg:postcode":"2906",
    "sg:province":"ACT",
    "sg:tags":[
        "earth",
        "excavating",
        "moving",
        "contractor"
    ],
    "wof:name":"Tuggeranong Bobcats",
    "wof:placetype":"venue"
},
  "geometry": {"coordinates":[149.083084106,-35.4658584595],"type":"Point"}
}