{
  "type": "Feature",
  "properties": {
    "addr:full":"117 Poath Rd Chadstone VIC 3148",
    "addr:housenumber":"117",
    "addr:postcode":"3148",
    "addr:street":"Poath Rd",
    "iso:country":"AU",
    "sg:address":"117 Poath Rd",
    "sg:city":"Chadstone",
    "sg:classifiers":[
        {
            "category":"Social Services",
            "subcategory":"Adult Care",
            "type":"Services"
        }
    ],
    "sg:phone":"+61 3 9563 2077",
    "sg:postcode":"3148",
    "sg:province":"VIC",
    "sg:tags":[
        "towing"
    ],
    "wof:name":"Ace Exhausts & Towbars",
    "wof:placetype":"venue"
},
  "geometry": {"coordinates":[145.076416016,-37.8954925537],"type":"Point"}
}