{
  "type": "Feature",
  "properties": {
    "addr:full":"4- 8 Waine St Harbord NSW 2096",
    "addr:housenumber":"8",
    "addr:postcode":"2096",
    "addr:street":"Waine St",
    "iso:country":"AU",
    "sg:address":"4- 8 Waine St",
    "sg:city":"Harbord",
    "sg:classifiers":[
        {
            "category":"Manufacturing",
            "subcategory":"Building Materials",
            "type":"Manufacturing & Wholesale Goods"
        }
    ],
    "sg:phone":"+61 2 9905 9197",
    "sg:postcode":"2096",
    "sg:province":"NSW",
    "sg:tags":[
        "concrete",
        "product"
    ],
    "sg:website":"http://www.winterstone.com.au",
    "wof:name":"Winterstone",
    "wof:placetype":"venue"
},
  "geometry": {"coordinates":[151.278076172,-33.780090332],"type":"Point"}
}