{
  "type": "Feature",
  "properties": {
    "addr:full":"2 3 Moonstone Crt Wheelers Hill VIC 3150",
    "addr:housenumber":"3",
    "addr:postcode":"3150",
    "addr:street":"Moonstone Crt",
    "iso:country":"AU",
    "sg:address":"2 3 Moonstone Crt",
    "sg:city":"Wheelers Hill",
    "sg:classifiers":[
        {
            "category":"Building & Trades",
            "subcategory":"Landscaping Services",
            "type":"Services"
        }
    ],
    "sg:phone":"+61 415 400 737",
    "sg:postcode":"3150",
    "sg:province":"VIC",
    "sg:tags":[
        "gardener"
    ],
    "wof:name":"Mathew Mightly Mow",
    "wof:placetype":"venue"
},
  "geometry": {"coordinates":[145.19781494099999,-37.920501709],"type":"Point"}
}