{
  "type": "Feature",
  "properties": {
    "iso:country":"AU",
    "sg:address":"3 Nuttall St",
    "sg:city":"Lawnton",
    "sg:classifiers":[
        {
            "category":"Farming",
            "subcategory":"Farm & Veterinary Services",
            "type":"Manufacturing & Wholesale Goods"
        }
    ],
    "sg:phone":"+61 418 191 165",
    "sg:postcode":"4501",
    "sg:province":"QLD",
    "sg:tags":[
        "irrigation",
        "reticulation",
        "system"
    ],
    "wof:name":"Lude Landscape Design & Construction",
    "wof:placetype":"venue"
},
  "geometry": {"coordinates":[152.97233581500001,-27.2811546326],"type":"Point"}
}