{
  "type": "Feature",
  "properties": {
    "iso:country":"AU",
    "sg:address":"Germain St",
    "sg:city":"Oakleigh South",
    "sg:classifiers":[
        {
            "category":"Education",
            "subcategory":"Kindergarten",
            "type":"Public Place"
        }
    ],
    "sg:phone":"+61 3 9570 2550",
    "sg:postcode":"3167",
    "sg:province":"VIC",
    "sg:tags":[
        "pre-schools"
    ],
    "wof:name":"Germain Street Kindergarten Inc.",
    "wof:placetype":"venue"
},
  "geometry": {"coordinates":[145.10287475600001,-37.9126625061],"type":"Point"}
}