{
  "type": "Feature",
  "properties": {
    "addr:full":"Cohuna Rd Koondrook VIC 3580",
    "addr:postcode":"3580",
    "addr:street":"Cohuna Rd",
    "iso:country":"AU",
    "sg:address":"Cohuna Rd",
    "sg:city":"Koondrook",
    "sg:classifiers":[
        {
            "category":"Building & Trades",
            "subcategory":"Construction",
            "type":"Services"
        }
    ],
    "sg:phone":"+61 3 5453 2821",
    "sg:postcode":"3580",
    "sg:province":"VIC",
    "sg:tags":[
        "fencing",
        "contractor"
    ],
    "wof:name":"Turvey C & C H",
    "wof:placetype":"venue"
},
  "geometry": {"coordinates":[144.13209533700001,-35.6436882019],"type":"Point"}
}