{
  "type": "Feature",
  "properties": {
    "addr:full":"158 Mckay St Nowra NSW 2541",
    "addr:housenumber":"158",
    "addr:postcode":"2541",
    "addr:street":"Mckay St",
    "iso:country":"AU",
    "sg:address":"158 Mckay St",
    "sg:city":"Nowra",
    "sg:classifiers":[
        {
            "category":"Professional",
            "subcategory":"Computer Services",
            "type":"Services"
        }
    ],
    "sg:phone":"+61 2 4423 1441",
    "sg:postcode":"2541",
    "sg:province":"NSW",
    "sg:tags":[
        "package",
        "software"
    ],
    "wof:name":"Murphy's Solutions",
    "wof:placetype":"venue"
},
  "geometry": {"coordinates":[150.60601806599999,-34.8925971985],"type":"Point"}
}