{
  "type": "Feature",
  "properties": {
    "addr:full":"880 Moggill Rd Kenmore QLD 4069",
    "addr:housenumber":"880",
    "addr:postcode":"4069",
    "addr:street":"Moggill Rd",
    "iso:country":"AU",
    "sg:address":"880 Moggill Rd",
    "sg:city":"Kenmore",
    "sg:classifiers":[
        {
            "category":"Real Estate",
            "subcategory":"Real Estate Agent",
            "type":"Services"
        }
    ],
    "sg:phone":"+61 7 3378 7777",
    "sg:postcode":"4069",
    "sg:province":"QLD",
    "wof:name":"Ray White Kenmore",
    "wof:placetype":"venue"
},
  "geometry": {"coordinates":[152.94859314000001,-27.5077133179],"type":"Point"}
}