{
  "type": "Feature",
  "properties": {
    "addr:full":"Church St Toowoomba QLD 4350",
    "addr:postcode":"4350",
    "addr:street":"Church St",
    "iso:country":"AU",
    "sg:address":"Church St",
    "sg:city":"Toowoomba",
    "sg:classifiers":[
        {
            "category":"Military Area",
            "subcategory":"Air Force Base",
            "type":"Public Place"
        }
    ],
    "sg:phone":"+61 7 4639 4500",
    "sg:postcode":"4350",
    "sg:province":"QLD",
    "sg:tags":[
        "equipment",
        "climbing",
        "venue",
        "rock"
    ],
    "wof:name":"Adrenalin Climbing Gym",
    "wof:placetype":"venue"
},
  "geometry": {"coordinates":[151.95674099999999,-27.560659],"type":"Point"}
}