{
  "type": "Feature",
  "properties": {
    "iso:country":"AU",
    "sg:address":"PO Box 5315",
    "sg:city":"Brendale",
    "sg:classifiers":[
        {
            "category":"Banks & Credit Unions",
            "subcategory":"Investment Brokerage",
            "type":"Services"
        }
    ],
    "sg:phone":"+61 7 3881 3900",
    "sg:postcode":"4500",
    "sg:province":"QLD",
    "sg:tags":[
        "mechanical",
        "oil",
        "seal"
    ],
    "sg:website":"http://www.sealstocks.net",
    "wof:name":"Sealstocks Pty Ltd",
    "wof:placetype":"venue"
},
  "geometry": {"coordinates":[152.989471436,-27.3251667023],"type":"Point"}
}