{
  "type": "Feature",
  "properties": {
    "addr:full":"135 Bryant St Tully QLD 4854",
    "addr:housenumber":"135",
    "addr:postcode":"4854",
    "addr:street":"Bryant St",
    "iso:country":"AU",
    "sg:address":"135 Bryant St",
    "sg:city":"Tully",
    "sg:classifiers":[
        {
            "category":"Professional",
            "subcategory":"Business Services",
            "type":"Services"
        }
    ],
    "sg:phone":"+61 7 4068 2072",
    "sg:postcode":"4854",
    "sg:province":"QLD",
    "sg:tags":[
        "livestock",
        "transport"
    ],
    "wof:name":"Nash Transport",
    "wof:placetype":"venue"
},
  "geometry": {"coordinates":[145.922637939,-17.9369430542],"type":"Point"}
}