{
  "type": "Feature",
  "properties": {
    "iso:country":"AU",
    "sg:address":"170 Brown St",
    "sg:city":"Bungalow",
    "sg:classifiers":[
        {
            "category":"Home & Garden",
            "subcategory":"Building Materials",
            "type":"Retail Goods"
        }
    ],
    "sg:phone":"+61 7 4051 2532",
    "sg:postcode":"4870",
    "sg:province":"QLD",
    "sg:tags":[
        "roofing"
    ],
    "wof:name":"Reeflex Roofing Systems",
    "wof:placetype":"venue"
},
  "geometry": {"coordinates":[145.75689697300001,-16.9368629456],"type":"Point"}
}