{
  "type": "Feature",
  "properties": {
    "addr:full":"7 North Arm Rd Middle Cove NSW 2068",
    "addr:housenumber":"7",
    "addr:postcode":"2068",
    "addr:street":"North Arm Rd",
    "iso:country":"AU",
    "sg:address":"7 North Arm Rd",
    "sg:city":"Middle Cove",
    "sg:classifiers":[
        {
            "category":"Professional",
            "subcategory":"Management & Consulting",
            "type":"Services"
        }
    ],
    "sg:phone":"+61 2 9882 1818",
    "sg:postcode":"2068",
    "sg:province":"NSW",
    "sg:tags":[
        "consultant"
    ],
    "wof:name":"Chris Luget & Associates Pty Ltd",
    "wof:placetype":"venue"
},
  "geometry": {"coordinates":[151.212127686,-33.7917633057],"type":"Point"}
}