{
  "type": "Feature",
  "properties": {
    "iso:country":"AU",
    "sg:address":"Cnr Heidelberg Rd & Rathmines St",
    "sg:city":"Fairfield",
    "sg:classifiers":[
        {
            "category":"Autos & Motor Vehicles",
            "subcategory":"Fuel & Gas Station",
            "type":"Retail Goods"
        }
    ],
    "sg:phone":"+61 3 9489 1782",
    "sg:postcode":"3078",
    "sg:province":"VIC",
    "wof:name":"Shell Fairfield Car Spa",
    "wof:placetype":"venue"
},
  "geometry": {"coordinates":[145.02545165999999,-37.7818031311],"type":"Point"}
}