{
  "type": "Feature",
  "properties": {
    "addr:full":"5 Endeavour Drv Balranald NSW 2715",
    "addr:housenumber":"5",
    "addr:postcode":"2715",
    "addr:street":"Endeavour Drv",
    "iso:country":"AU",
    "sg:address":"5 Endeavour Drv",
    "sg:city":"Balranald",
    "sg:classifiers":[
        {
            "category":"Shopping",
            "subcategory":"Crafts & Fabrics",
            "type":"Retail Goods"
        }
    ],
    "sg:phone":"+61 3 5020 1687",
    "sg:postcode":"2715",
    "sg:province":"NSW",
    "sg:tags":[
        "wool",
        "classers"
    ],
    "wof:name":"Lawler P.J.",
    "wof:placetype":"venue"
},
  "geometry": {"coordinates":[143.54377746599999,-34.6371154785],"type":"Point"}
}