{
  "type": "Feature",
  "properties": {
    "iso:country":"AU",
    "sg:address":"28 Belmore St",
    "sg:city":"Burwood",
    "sg:classifiers":[
        {
            "category":"Health Services",
            "subcategory":"Dentist",
            "type":"Services"
        }
    ],
    "sg:phone":"+61 2 9747 5684",
    "sg:postcode":"2134",
    "sg:province":"NSW",
    "wof:name":"Piras Michael",
    "wof:placetype":"venue"
},
  "geometry": {"coordinates":[151.10310363799999,-33.8789558411],"type":"Point"}
}