{
  "type": "Feature",
  "properties": {
    "addr:full":"25 Gresham St Adelaide SA 5000",
    "addr:housenumber":"25",
    "addr:postcode":"5000",
    "addr:street":"Gresham St",
    "iso:country":"AU",
    "sg:address":"25 Gresham St",
    "sg:city":"Adelaide",
    "sg:classifiers":[
        {
            "category":"Transit Center",
            "subcategory":"Passenger",
            "type":"Transportation"
        }
    ],
    "sg:phone":"+61 8 8415 5121",
    "sg:postcode":"5000",
    "sg:province":"SA",
    "sg:tags":[
        "reading",
        "improvement"
    ],
    "wof:name":"Rocket Reader",
    "wof:placetype":"venue"
},
  "geometry": {"coordinates":[138.5987854,-34.9227294922],"type":"Point"}
}