{
  "type": "Feature",
  "properties": {
    "addr:full":"10 / 3 Bishopgate St Wickham NSW 2293",
    "addr:housenumber":"10 / 3",
    "addr:postcode":"2293",
    "addr:street":"Bishopgate St",
    "iso:country":"AU",
    "sg:address":"10 / 3 Bishopgate St",
    "sg:city":"Wickham",
    "sg:classifiers":[
        {
            "category":"Building & Trades",
            "subcategory":"Cleaning & Sanitation",
            "type":"Services"
        }
    ],
    "sg:phone":"+61 407 485 299",
    "sg:postcode":"2293",
    "sg:province":"NSW",
    "sg:tags":[
        "wall",
        "brick"
    ],
    "wof:name":"Brick Pointing Specialist",
    "wof:placetype":"venue"
},
  "geometry": {"coordinates":[151.75990295400001,-32.9226722717],"type":"Point"}
}