{
  "type": "Feature",
  "properties": {
    "addr:full":"31 Bond St Ivanhoe VIC 3079",
    "addr:housenumber":"31",
    "addr:postcode":"3079",
    "addr:street":"Bond St",
    "iso:country":"AU",
    "sg:address":"31 Bond St",
    "sg:city":"Ivanhoe",
    "sg:classifiers":[
        {
            "category":"Building & Trades",
            "subcategory":"Construction",
            "type":"Services"
        }
    ],
    "sg:phone":"+61 3 9499 3020",
    "sg:postcode":"3079",
    "sg:province":"VIC",
    "sg:tags":[
        "tennis court",
        "repair"
    ],
    "wof:name":"Bell Tony",
    "wof:placetype":"venue"
},
  "geometry": {"coordinates":[145.041015625,-37.7627677917],"type":"Point"}
}