{
  "type": "Feature",
  "properties": {
    "iso:country":"AU",
    "sg:address":"Shop 7/ 17 Tribute St",
    "sg:city":"Shelley",
    "sg:classifiers":[
        {
            "category":"Banks & Credit Unions",
            "subcategory":"Financial Services",
            "type":"Services"
        }
    ],
    "sg:phone":"+61 8 9354 5077",
    "sg:postcode":"6148",
    "sg:province":"WA",
    "sg:tags":[
        "settlement",
        "nt",
        "agent",
        "wa"
    ],
    "wof:name":"Canning Settlement Services",
    "wof:placetype":"venue"
},
  "geometry": {"coordinates":[115.88488,-32.030727],"type":"Point"}
}