{
  "type": "Feature",
  "properties": {
    "iso:country":"AU",
    "sg:address":"Unit 3 No 2 Dual Ave",
    "sg:city":"Warana",
    "sg:classifiers":[
        {
            "category":"Professional",
            "subcategory":"Printing & Photocopies",
            "type":"Services"
        }
    ],
    "sg:phone":"+61 7 5493 7799",
    "sg:postcode":"4575",
    "sg:province":"QLD",
    "sg:tags":[
        "photocopier"
    ],
    "wof:name":"All Age Business Machines",
    "wof:placetype":"venue"
},
  "geometry": {"coordinates":[153.124115,-26.728853],"type":"Point"}
}