{
  "type": "Feature",
  "properties": {
    "addr:full":"197 Lygon St Brunswick East VIC 3057",
    "addr:housenumber":"197",
    "addr:postcode":"3057",
    "addr:street":"Lygon St",
    "iso:country":"AU",
    "sg:address":"197 Lygon St",
    "sg:city":"Brunswick East",
    "sg:classifiers":[
        {
            "category":"Building & Trades",
            "subcategory":"Construction",
            "type":"Services"
        }
    ],
    "sg:phone":"+61 3 9387 2355",
    "sg:postcode":"3057",
    "sg:province":"VIC",
    "sg:tags":[
        "contractor"
    ],
    "wof:name":"Riverbank Homes",
    "wof:placetype":"venue"
},
  "geometry": {"coordinates":[144.9715271,-37.7717170715],"type":"Point"}
}