{
  "type": "Feature",
  "properties": {
    "iso:country":"AU",
    "sg:address":"Unit 36/ 37- 39 Albert Rd",
    "sg:city":"Melbourne",
    "sg:classifiers":[
        {
            "category":"Professional",
            "type":"Services"
        }
    ],
    "sg:phone":"+61 3 9820 1960",
    "sg:postcode":"3000",
    "sg:province":"VIC",
    "sg:tags":[
        "shop",
        "fitting"
    ],
    "wof:name":"D.J.B. Interiors",
    "wof:placetype":"venue"
},
  "geometry": {"coordinates":[144.97128295900001,-37.8351707458],"type":"Point"}
}