{
  "type": "Feature",
  "properties": {
    "addr:full":"21 Benison Rd Winnellie NT 0820",
    "addr:housenumber":"21",
    "addr:postcode":"nt 0820",
    "addr:street":"Benison Rd",
    "iso:country":"AU",
    "sg:address":"21 Benison Rd",
    "sg:city":"Winnellie",
    "sg:classifiers":[
        {
            "category":"Retail",
            "subcategory":"Repair Shop",
            "type":"Services"
        }
    ],
    "sg:phone":"+61 8 8984 3663",
    "sg:postcode":"0820",
    "sg:province":"NT",
    "sg:tags":[
        "maintenance",
        "pool",
        "swimming"
    ],
    "wof:name":"PoolWerx",
    "wof:placetype":"venue"
},
  "geometry": {"coordinates":[130.86297607399999,-12.4301614761],"type":"Point"}
}