{
  "type": "Feature",
  "properties": {
    "iso:country":"AU",
    "sg:address":"578 Hamilton Rd",
    "sg:city":"Chermside",
    "sg:classifiers":[
        {
            "category":"Professional",
            "subcategory":"Employment Agencies",
            "type":"Services"
        }
    ],
    "sg:phone":"+61 411 138 014",
    "sg:postcode":"4032",
    "sg:province":"QLD",
    "wof:name":"Right Personnel",
    "wof:placetype":"venue"
},
  "geometry": {"coordinates":[153.024368,-27.384813],"type":"Point"}
}