{
  "type": "Feature",
  "properties": {
    "addr:full":"Unit 4, 13 -15 Wollongong Rd Arncliffe NSW 2205",
    "addr:housenumber":"13 -15",
    "addr:postcode":"2205",
    "addr:street":"Wollongong Rd",
    "iso:country":"AU",
    "sg:address":"Unit 4, 13 -15 Wollongong Rd",
    "sg:city":"Arncliffe",
    "sg:classifiers":[
        {
            "category":"Home & Garden",
            "subcategory":"Hardware",
            "type":"Retail Goods"
        }
    ],
    "sg:phone":"+61 2 9556 3462",
    "sg:postcode":"2205",
    "sg:province":"NSW",
    "sg:tags":[
        "product",
        "treatment",
        "floor"
    ],
    "wof:name":"No Skidding Australia",
    "wof:placetype":"venue"
},
  "geometry": {"coordinates":[151.147964,-33.933784],"type":"Point"}
}