{
  "type": "Feature",
  "properties": {
    "addr:full":"PO Box 399 Narrogin WA 6312",
    "addr:postcode":"6312",
    "iso:country":"AU",
    "sg:address":"PO Box 399",
    "sg:city":"Narrogin",
    "sg:classifiers":[
        {
            "category":"Building & Trades",
            "subcategory":"Cleaning & Sanitation",
            "type":"Services"
        }
    ],
    "sg:phone":"+61 427 477 416",
    "sg:postcode":"6312",
    "sg:province":"WA",
    "sg:tags":[
        "tank",
        "septic"
    ],
    "wof:name":"Narrogin Liquid Waste Disposal",
    "wof:placetype":"venue"
},
  "geometry": {"coordinates":[117.17830658,-32.931388855],"type":"Point"}
}