{
  "type": "Feature",
  "properties": {
    "iso:country":"AU",
    "sg:address":"2 Remington Drv",
    "sg:city":"Dandenong South",
    "sg:classifiers":[
        {
            "category":"Cafe",
            "type":"Food & Drink"
        }
    ],
    "sg:phone":"+61 3 9799 8722",
    "sg:postcode":"3175",
    "sg:province":"VIC",
    "wof:name":"Five Star Take Away & Cafe",
    "wof:placetype":"venue"
},
  "geometry": {"coordinates":[145.22752380399999,-38.0333862305],"type":"Point"}
}