{
  "type": "Feature",
  "properties": {
    "addr:full":"163 Fulham St Kewdale WA 6105",
    "addr:housenumber":"163",
    "addr:postcode":"6105",
    "addr:street":"Fulham St",
    "iso:country":"AU",
    "sg:address":"163 Fulham St",
    "sg:city":"Kewdale",
    "sg:classifiers":[
        {
            "category":"Social Services",
            "subcategory":"Child Care",
            "type":"Services"
        }
    ],
    "sg:phone":"+61 8 9479 3737",
    "sg:postcode":"6105",
    "sg:province":"WA",
    "wof:name":"Tommie Turtle Child Care & Learning Centre",
    "wof:placetype":"venue"
},
  "geometry": {"coordinates":[115.93295288100001,-31.9684581757],"type":"Point"}
}