{
  "type": "Feature",
  "properties": {
    "iso:country":"AU",
    "sg:address":"8 Roberts St",
    "sg:city":"West Osborne Park",
    "sg:classifiers":[
        {
            "category":"Retail",
            "subcategory":"Auto Repair",
            "type":"Services"
        }
    ],
    "sg:phone":"+61 8 9444 8000",
    "sg:postcode":"6017",
    "sg:province":"WA",
    "sg:tags":[
        "repairer",
        "motor",
        "engineer"
    ],
    "wof:name":"Nanzo Valuri Mechanical Repairs",
    "wof:placetype":"venue"
},
  "geometry": {"coordinates":[115.818687439,-31.907907486],"type":"Point"}
}