{
  "type": "Feature",
  "properties": {
    "iso:country":"AU",
    "sg:address":"1A Roseberry St",
    "sg:city":"Bayswater",
    "sg:classifiers":[
        {
            "category":"Building & Trades",
            "subcategory":"Construction",
            "type":"Services"
        }
    ],
    "sg:phone":"+61 8 9371 7971",
    "sg:postcode":"6053",
    "sg:province":"WA",
    "sg:tags":[
        "brick",
        "paving"
    ],
    "wof:name":"Aspect Acular",
    "wof:placetype":"venue"
},
  "geometry": {"coordinates":[115.899391174,-31.9223613739],"type":"Point"}
}