{
  "type": "Feature",
  "properties": {
    "addr:full":"14 Norfolk St Ashtonfield NSW 2323",
    "addr:housenumber":"14",
    "addr:postcode":"2323",
    "addr:street":"Norfolk St",
    "iso:country":"AU",
    "sg:address":"14 Norfolk St",
    "sg:city":"Ashtonfield",
    "sg:classifiers":[
        {
            "category":"Building & Trades",
            "subcategory":"Construction",
            "type":"Services"
        }
    ],
    "sg:phone":"+61 2 4934 1522",
    "sg:postcode":"2323",
    "sg:province":"NSW",
    "sg:tags":[
        "spouting",
        "guttering"
    ],
    "wof:name":"JT Guttering Pty. Ltd.",
    "wof:placetype":"venue"
},
  "geometry": {"coordinates":[151.59982299800001,-32.771522522],"type":"Point"}
}