{
  "type": "Feature",
  "properties": {
    "addr:full":"298 Keilor Rd Essendon North VIC 3041",
    "addr:housenumber":"298",
    "addr:postcode":"3041",
    "addr:street":"Keilor Rd",
    "iso:country":"AU",
    "sg:address":"298 Keilor Rd",
    "sg:city":"Essendon North",
    "sg:classifiers":[
        {
            "category":"Retail",
            "subcategory":"Auto Repair",
            "type":"Services"
        }
    ],
    "sg:phone":"+61 3 9379 9813",
    "sg:postcode":"3041",
    "sg:province":"VIC",
    "sg:tags":[
        "electrical"
    ],
    "wof:name":"Livewire Auto Electrical & Mechanical Specialists",
    "wof:placetype":"venue"
},
  "geometry": {"coordinates":[144.894805908,-37.7381057739],"type":"Point"}
}