{
  "type": "Feature",
  "properties": {
    "iso:country":"AU",
    "sg:address":"177 South Woodland St",
    "sg:city":"Balgowlah",
    "sg:classifiers":[
        {
            "category":"Professional",
            "subcategory":"Computer Services",
            "type":"Services"
        }
    ],
    "sg:phone":"+61 2 9949 5066",
    "sg:postcode":"2093",
    "sg:province":"NSW",
    "sg:tags":[
        "repairs",
        "upgrade",
        "equipment"
    ],
    "wof:name":"Don Brown Computing",
    "wof:placetype":"venue"
},
  "geometry": {"coordinates":[151.262252808,-33.7952041626],"type":"Point"}
}