{
  "type": "Feature",
  "properties": {
    "iso:country":"AU",
    "sg:address":"Level 3 Corporate Centre Bundall Rd",
    "sg:city":"Bundall",
    "sg:classifiers":[
        {
            "category":"Banks & Credit Unions",
            "subcategory":"Financial Services",
            "type":"Services"
        }
    ],
    "sg:phone":"+61 7 5574 2767",
    "sg:postcode":"4217",
    "sg:province":"QLD",
    "sg:tags":[
        "annuity",
        "rollover",
        "superannuation",
        "consultant"
    ],
    "wof:name":"Advisor Investment Services Ltd",
    "wof:placetype":"venue"
},
  "geometry": {"coordinates":[153.411987305,-28.0108585358],"type":"Point"}
}