{
  "type": "Feature",
  "properties": {
    "iso:country":"AU",
    "sg:address":"4 Sonia Crt",
    "sg:city":"Raceview",
    "sg:classifiers":[
        {
            "category":"Retail",
            "subcategory":"Auto Repair",
            "type":"Services"
        }
    ],
    "sg:phone":"+61 7 3294 1782",
    "sg:postcode":"4305",
    "sg:province":"QLD",
    "sg:tags":[
        "repairer",
        "motor",
        "engineer"
    ],
    "wof:name":"Andrew McClure Mechanical",
    "wof:placetype":"venue"
},
  "geometry": {"coordinates":[152.76252746599999,-27.6429615021],"type":"Point"}
}