{
  "type": "Feature",
  "properties": {
    "iso:country":"AU",
    "sg:address":"95 Brighton Rd",
    "sg:city":"Glenelg",
    "sg:classifiers":[
        {
            "category":"Real Estate",
            "subcategory":"Real Estate Agent",
            "type":"Services"
        }
    ],
    "sg:phone":"+61 8 8294 3782",
    "sg:postcode":"5045",
    "sg:province":"SA",
    "wof:name":"Boswarva A W & Sons Pty Ltd",
    "wof:placetype":"venue"
},
  "geometry": {"coordinates":[138.520493,-34.986088],"type":"Point"}
}