{
  "type": "Feature",
  "properties": {
    "addr:full":"Cnr Dean & Stewart Sts North Rockhampton QLD 4701",
    "addr:postcode":"4701",
    "addr:street":"Cnr;North",
    "iso:country":"AU",
    "sg:address":"Cnr Dean & Stewart Sts",
    "sg:city":"North Rockhampton",
    "sg:classifiers":[
        {
            "category":"Social Services",
            "subcategory":"Adult Care",
            "type":"Services"
        }
    ],
    "sg:phone":"+61 7 4926 1444",
    "sg:postcode":"4701",
    "sg:province":"QLD",
    "sg:tags":[
        "towing"
    ],
    "wof:name":"Menzies Towing",
    "wof:placetype":"venue"
},
  "geometry": {"coordinates":[150.54896545400001,-23.3510398865],"type":"Point"}
}