{
  "type": "Feature",
  "properties": {
    "addr:full":"84 Parklands Rd North Ryde NSW 2113",
    "addr:housenumber":"84",
    "addr:postcode":"2113",
    "addr:street":"Parklands Rd",
    "iso:country":"AU",
    "sg:address":"84 Parklands Rd",
    "sg:city":"North Ryde",
    "sg:classifiers":[
        {
            "category":"Education",
            "subcategory":"Special Training",
            "type":"Public Place"
        }
    ],
    "sg:phone":"+61 2 9805 1592",
    "sg:postcode":"2113",
    "sg:province":"NSW",
    "sg:tags":[
        "development"
    ],
    "wof:name":"Learning Curve Pty Ltd",
    "wof:placetype":"venue"
},
  "geometry": {"coordinates":[151.11567688,-33.7857208252],"type":"Point"}
}