{
  "type": "Feature",
  "properties": {
    "addr:full":"48a Ethel St Seaforth NSW 2092",
    "addr:housenumber":"48a",
    "addr:postcode":"2092",
    "addr:street":"Ethel St",
    "iso:country":"AU",
    "sg:address":"48a Ethel St",
    "sg:city":"Seaforth",
    "sg:classifiers":[
        {
            "category":"Ice Cream",
            "type":"Food & Drink"
        }
    ],
    "sg:phone":"+61 2 9907 7877",
    "sg:postcode":"2092",
    "sg:province":"NSW",
    "sg:tags":[
        "specialised",
        "fitting",
        "lady",
        "wear"
    ],
    "wof:name":"Opulence More to Love",
    "wof:placetype":"venue"
},
  "geometry": {"coordinates":[151.251708984,-33.7976074219],"type":"Point"}
}