{
  "type": "Feature",
  "properties": {
    "addr:full":"2a Eurella St Burwood NSW 2134",
    "addr:housenumber":"2a",
    "addr:postcode":"2134",
    "addr:street":"Eurella St",
    "iso:country":"AU",
    "sg:address":"2a Eurella St",
    "sg:city":"Burwood",
    "sg:classifiers":[
        {
            "category":"Organizations",
            "subcategory":"Non-profit Organization",
            "type":"Services"
        }
    ],
    "sg:phone":"+61 2 9747 4810",
    "sg:postcode":"2134",
    "sg:province":"NSW",
    "sg:tags":[
        "support",
        "disability",
        "organisation"
    ],
    "wof:name":"Eurella Community Services",
    "wof:placetype":"venue"
},
  "geometry": {"coordinates":[151.11053466800001,-33.8749084473],"type":"Point"}
}