{
  "type": "Feature",
  "properties": {
    "addr:full":"2 Byrne Crt Mildura VIC 3500",
    "addr:housenumber":"2",
    "addr:postcode":"3500",
    "addr:street":"Byrne Crt",
    "iso:country":"AU",
    "sg:address":"2 Byrne Crt",
    "sg:city":"Mildura",
    "sg:classifiers":[
        {
            "category":"Professional",
            "subcategory":"Engineering",
            "type":"Services"
        }
    ],
    "sg:phone":"+61 3 5023 4039",
    "sg:postcode":"3500",
    "sg:province":"VIC",
    "sg:tags":[
        "engineer"
    ],
    "wof:name":"Express Engineers",
    "wof:placetype":"venue"
},
  "geometry": {"coordinates":[142.173919678,-34.197303772],"type":"Point"}
}