{
  "type": "Feature",
  "properties": {
    "addr:full":"240 Currie St Adelaide SA 5000",
    "addr:housenumber":"240",
    "addr:postcode":"5000",
    "addr:street":"Currie St",
    "iso:country":"AU",
    "sg:address":"240 Currie St",
    "sg:city":"Adelaide",
    "sg:classifiers":[
        {
            "category":"Professional",
            "subcategory":"Computer Services",
            "type":"Services"
        }
    ],
    "sg:phone":"+61 8 8410 3066",
    "sg:postcode":"5000",
    "sg:province":"SA",
    "sg:tags":[
        "training"
    ],
    "wof:name":"Systems Education",
    "wof:placetype":"venue"
},
  "geometry": {"coordinates":[138.58917236299999,-34.9246177673],"type":"Point"}
}