{
  "type": "Feature",
  "properties": {
    "addr:full":"16 Aberdeen St Geelong West VIC 3218",
    "addr:housenumber":"16",
    "addr:postcode":"3218",
    "addr:street":"Aberdeen St",
    "iso:country":"AU",
    "sg:address":"16 Aberdeen St",
    "sg:city":"Geelong West",
    "sg:classifiers":[
        {
            "category":"Banks & Credit Unions",
            "subcategory":"Investment Brokerage",
            "type":"Services"
        }
    ],
    "sg:phone":"+61 3 5229 4637",
    "sg:postcode":"3218",
    "sg:province":"VIC",
    "sg:tags":[
        "share",
        "broker",
        "stock"
    ],
    "sg:website":"http://www.holst.com.au",
    "wof:name":"Holst",
    "wof:placetype":"venue"
},
  "geometry": {"coordinates":[144.35081481899999,-38.1470413208],"type":"Point"}
}