{
  "type": "Feature",
  "properties": {
    "iso:country":"AU",
    "sg:address":"18 Dutton Rd",
    "sg:city":"Buxton",
    "sg:classifiers":[
        {
            "category":"Professional",
            "type":"Services"
        }
    ],
    "sg:phone":"+61 411 053 486",
    "sg:postcode":"2571",
    "sg:province":"NSW",
    "sg:tags":[
        "transport"
    ],
    "wof:name":"M.J.O.Enterprises Pty Ltd",
    "wof:placetype":"venue"
},
  "geometry": {"coordinates":[150.535766602,-34.2586021423],"type":"Point"}
}