{
  "type": "Feature",
  "properties": {
    "iso:country":"AU",
    "sg:address":"PO Box 1378",
    "sg:city":"Dee Why",
    "sg:classifiers":[
        {
            "category":"Social Services",
            "subcategory":"Retirement Home",
            "type":"Services"
        }
    ],
    "sg:phone":"+61 2 9984 8917",
    "sg:postcode":"2099",
    "sg:province":"NSW",
    "sg:tags":[
        "environmental",
        "consultant",
        "pollution"
    ],
    "wof:name":"Oz GREEN Global Rivers Environmental Education Network (Australia) Inc",
    "wof:placetype":"venue"
},
  "geometry": {"coordinates":[151.285232544,-33.7537498474],"type":"Point"}
}