{
  "type": "Feature",
  "properties": {
    "addr:full":"373 Hampton St Hampton VIC 3188",
    "addr:housenumber":"373",
    "addr:postcode":"3188",
    "addr:street":"Hampton St",
    "iso:country":"AU",
    "sg:address":"373 Hampton St",
    "sg:city":"Hampton",
    "sg:classifiers":[
        {
            "category":"Shopping",
            "subcategory":"Jewelry",
            "type":"Retail Goods"
        }
    ],
    "sg:phone":"+61 3 9598 9022",
    "sg:postcode":"3188",
    "sg:province":"VIC",
    "sg:tags":[
        "jeweller"
    ],
    "wof:name":"Gold Fever",
    "wof:placetype":"venue"
},
  "geometry": {"coordinates":[145.00247192399999,-37.9367675781],"type":"Point"}
}