{
  "type": "Feature",
  "properties": {
    "addr:full":"26 Marriage Rd Brighton East VIC 3187",
    "addr:housenumber":"26",
    "addr:postcode":"3187",
    "addr:street":"Marriage Rd",
    "iso:country":"AU",
    "sg:address":"26 Marriage Rd",
    "sg:city":"Brighton East",
    "sg:classifiers":[
        {
            "category":"Professional",
            "subcategory":"Art Services",
            "type":"Services"
        }
    ],
    "sg:phone":"+61 3 9592 4847",
    "sg:postcode":"3187",
    "sg:province":"VIC",
    "sg:tags":[
        "decorator",
        "painter"
    ],
    "wof:name":"Basil Brush",
    "wof:placetype":"venue"
},
  "geometry": {"coordinates":[145.01028442399999,-37.9189949036],"type":"Point"}
}