{
  "type": "Feature",
  "properties": {
    "addr:full":"14B Elder St Alice Springs NT 0870",
    "addr:housenumber":"14b",
    "addr:postcode":"nt 0870",
    "addr:street":"Elder St",
    "iso:country":"AU",
    "sg:address":"14B Elder St",
    "sg:city":"Alice Springs",
    "sg:classifiers":[
        {
            "category":"Professional",
            "subcategory":"Engineering",
            "type":"Services"
        }
    ],
    "sg:phone":"+61 8 8952 2540",
    "sg:postcode":"0870",
    "sg:province":"NT",
    "sg:tags":[
        "consulting",
        "engineer"
    ],
    "wof:name":"Project Building Certifiers Pty Ltd",
    "wof:placetype":"venue"
},
  "geometry": {"coordinates":[133.87083435100001,-23.6984558105],"type":"Point"}
}