{
  "type": "Feature",
  "properties": {
    "addr:full":"102 Imperial Pde Labrador QLD 4215",
    "addr:housenumber":"102",
    "addr:postcode":"4215",
    "addr:street":"Imperial Pde",
    "iso:country":"AU",
    "sg:address":"102 Imperial Pde",
    "sg:city":"Labrador",
    "sg:classifiers":[
        {
            "category":"Health Services",
            "subcategory":"Doctor",
            "type":"Services"
        }
    ],
    "sg:phone":"+61 7 5631 4800",
    "sg:postcode":"4215",
    "sg:province":"QLD",
    "sg:tags":[
        "occupational",
        "safety"
    ],
    "wof:name":"Health For Industry",
    "wof:placetype":"venue"
},
  "geometry": {"coordinates":[153.399856567,-27.9431324005],"type":"Point"}
}