{
  "type": "Feature",
  "properties": {
    "addr:full":"15 First Ave Unanderra NSW 2526",
    "addr:housenumber":"15",
    "addr:postcode":"2526",
    "addr:street":"First Ave",
    "iso:country":"AU",
    "sg:address":"15 First Ave",
    "sg:city":"Unanderra",
    "sg:classifiers":[
        {
            "category":"Building & Trades",
            "subcategory":"Construction",
            "type":"Services"
        }
    ],
    "sg:phone":"+61 2 4272 4905",
    "sg:postcode":"2526",
    "sg:province":"NSW",
    "sg:tags":[
        "contractor"
    ],
    "wof:name":"Max Wood & Sons Builders",
    "wof:placetype":"venue"
},
  "geometry": {"coordinates":[150.850631714,-34.4497375488],"type":"Point"}
}