{
  "type": "Feature",
  "properties": {
    "addr:full":"Shop 36A Park Centre Albany Hwy Victoria Park WA 6100",
    "addr:housenumber":"36a",
    "addr:postcode":"6100",
    "addr:street":"Albany Hwy Victoria",
    "iso:country":"AU",
    "sg:address":"Shop 36A Park Centre Albany Hwy",
    "sg:city":"Victoria Park",
    "sg:classifiers":[
        {
            "category":"Personal",
            "subcategory":"Beauty Salon",
            "type":"Services"
        }
    ],
    "sg:phone":"+61 8 9470 5733",
    "sg:postcode":"6100",
    "sg:province":"WA",
    "wof:name":"Spa In The Park",
    "wof:placetype":"venue"
},
  "geometry": {"coordinates":[115.898368835,-31.9767799377],"type":"Point"}
}