{
  "type": "Feature",
  "properties": {
    "addr:full":"74 Burwood Rd Burwood NSW 2134",
    "addr:housenumber":"74",
    "addr:postcode":"2134",
    "addr:street":"Burwood Rd",
    "iso:country":"AU",
    "sg:address":"74 Burwood Rd",
    "sg:city":"Burwood",
    "sg:classifiers":[
        {
            "category":"Banks & Credit Unions",
            "subcategory":"Investment Brokerage",
            "type":"Services"
        }
    ],
    "sg:phone":"+61 2 8741 0333",
    "sg:postcode":"2134",
    "sg:province":"NSW",
    "sg:tags":[
        "finance",
        "broker"
    ],
    "wof:name":"Boston Mortgages Pty Ltd",
    "wof:placetype":"venue"
},
  "geometry": {"coordinates":[151.104736328,-33.8729286194],"type":"Point"}
}