{
  "type": "Feature",
  "properties": {
    "iso:country":"AU",
    "sg:address":"157 Concord Rd",
    "sg:city":"North Strathfield",
    "sg:classifiers":[
        {
            "category":"Restaurant",
            "type":"Food & Drink"
        }
    ],
    "sg:phone":"+61 2 9743 6382",
    "sg:postcode":"2137",
    "sg:province":"NSW",
    "wof:name":"Baan Raun Thai Restaurants",
    "wof:placetype":"venue"
},
  "geometry": {"coordinates":[151.092407227,-33.858291626],"type":"Point"}
}