{
  "type": "Feature",
  "properties": {
    "addr:full":"35 Wilson St Katoomba NSW 2780",
    "addr:housenumber":"35",
    "addr:postcode":"2780",
    "addr:street":"Wilson St",
    "iso:country":"AU",
    "sg:address":"35 Wilson St",
    "sg:city":"Katoomba",
    "sg:classifiers":[
        {
            "category":"Building & Trades",
            "subcategory":"Construction",
            "type":"Services"
        }
    ],
    "sg:phone":"+61 2 4788 1196",
    "sg:postcode":"2780",
    "sg:province":"NSW",
    "sg:tags":[
        "joinery"
    ],
    "wof:name":"Michael Sibiriakoff",
    "wof:placetype":"venue"
},
  "geometry": {"coordinates":[150.32029724099999,-33.7110023499],"type":"Point"}
}