{
  "type": "Feature",
  "properties": {
    "addr:full":"PO Box 63 Indooroopilly QLD 4068",
    "addr:postcode":"4068",
    "iso:country":"AU",
    "sg:address":"PO Box 63",
    "sg:city":"Indooroopilly",
    "sg:classifiers":[
        {
            "category":"Building & Trades",
            "subcategory":"Construction",
            "type":"Services"
        }
    ],
    "sg:phone":"+61 7 3277 6551",
    "sg:postcode":"4068",
    "sg:province":"QLD",
    "sg:tags":[
        "brick",
        "paving"
    ],
    "wof:name":"Green Survival Landscapes",
    "wof:placetype":"venue"
},
  "geometry": {"coordinates":[152.97575378400001,-27.4989395142],"type":"Point"}
}