{
  "type": "Feature",
  "properties": {
    "iso:country":"AU",
    "sg:address":"151 Caxton St",
    "sg:city":"Paddington",
    "sg:classifiers":[
        {
            "category":"Personal",
            "subcategory":"Beauty Salon",
            "type":"Services"
        }
    ],
    "sg:phone":"+61 7 3368 1418",
    "sg:postcode":"4064",
    "sg:province":"QLD",
    "sg:tags":[
        "hairdresser"
    ],
    "wof:name":"Purple Daze",
    "wof:placetype":"venue"
},
  "geometry": {"coordinates":[153.009109497,-27.4623737335],"type":"Point"}
}