{
  "type": "Feature",
  "properties": {
    "addr:full":"8 Murdock Crt Bacchus Marsh VIC 3340",
    "addr:housenumber":"8",
    "addr:postcode":"3340",
    "addr:street":"Murdock Crt",
    "iso:country":"AU",
    "sg:address":"8 Murdock Crt",
    "sg:city":"Bacchus Marsh",
    "sg:classifiers":[
        {
            "category":"Wholesale",
            "subcategory":"Auto Parts",
            "type":"Manufacturing & Wholesale Goods"
        }
    ],
    "sg:phone":"+61 3 5367 7804",
    "sg:postcode":"3340",
    "sg:province":"VIC",
    "sg:tags":[
        "recyclers"
    ],
    "wof:name":"C J Auto Wreckers",
    "wof:placetype":"venue"
},
  "geometry": {"coordinates":[144.42378199999999,-37.690357],"type":"Point"}
}