{
  "type": "Feature",
  "properties": {
    "addr:full":"22 Paterson Rd Bolwarra NSW 2320",
    "addr:housenumber":"22",
    "addr:postcode":"2320",
    "addr:street":"Paterson Rd",
    "iso:country":"AU",
    "sg:address":"22 Paterson Rd",
    "sg:city":"Bolwarra",
    "sg:classifiers":[
        {
            "category":"Real Estate",
            "subcategory":"Real Estate Agent",
            "type":"Services"
        }
    ],
    "sg:phone":"+61 2 4930 0200",
    "sg:postcode":"2320",
    "sg:province":"NSW",
    "wof:name":"Sarroff Sarroff & Sarroff Real Estate",
    "wof:placetype":"venue"
},
  "geometry": {"coordinates":[151.57026672399999,-32.7128677368],"type":"Point"}
}