{
  "type": "Feature",
  "properties": {
    "addr:full":"5 Libya St Birmingham Gardens NSW 2287",
    "addr:housenumber":"5",
    "addr:postcode":"2287",
    "addr:street":"Libya St",
    "iso:country":"AU",
    "sg:address":"5 Libya St",
    "sg:city":"Birmingham Gardens",
    "sg:classifiers":[
        {
            "category":"Retail",
            "subcategory":"Car Wash",
            "type":"Services"
        }
    ],
    "sg:phone":"+61 1300 131 288",
    "sg:postcode":"2287",
    "sg:province":"NSW",
    "sg:tags":[
        "truck",
        "cleaning"
    ],
    "wof:name":"King of The Road Mobile Truck Wash",
    "wof:placetype":"venue"
},
  "geometry": {"coordinates":[151.688323975,-32.8895111084],"type":"Point"}
}