{
  "type": "Feature",
  "properties": {
    "iso:country":"AU",
    "sg:address":"22 Berriman Drv",
    "sg:city":"Wangara",
    "sg:classifiers":[
        {
            "category":"Home & Garden",
            "subcategory":"Carpets & Floor Coverings",
            "type":"Retail Goods"
        }
    ],
    "sg:phone":"+61 1300 559 079",
    "sg:postcode":"6065",
    "sg:province":"WA",
    "sg:tags":[
        "wood"
    ],
    "wof:name":"Woodworks Flooring & Timber",
    "wof:placetype":"venue"
},
  "geometry": {"coordinates":[115.82022857699999,-31.7934322357],"type":"Point"}
}