{
  "type": "Feature",
  "properties": {
    "iso:country":"AU",
    "sg:address":"Shop 1039 Fountain Gate Shopping Centre Princess Hwy",
    "sg:city":"Narre Warren",
    "sg:classifiers":[
        {
            "category":"Shopping",
            "subcategory":"Clothing, Apparel, & Fashions",
            "type":"Retail Goods"
        }
    ],
    "sg:phone":"+61 3 9704 9722",
    "sg:postcode":"3805",
    "sg:province":"VIC",
    "sg:tags":[
        "lady",
        "wear"
    ],
    "wof:name":"My Size Pty Ltd",
    "wof:placetype":"venue"
},
  "geometry": {"coordinates":[145.295227,-38.014523],"type":"Point"}
}