{
  "type": "Feature",
  "properties": {
    "iso:country":"AU",
    "sg:address":"56 Lachlan Rd",
    "sg:city":"Sunshine",
    "sg:classifiers":[
        {
            "category":"Professional",
            "type":"Services"
        }
    ],
    "sg:phone":"+61 3 9311 3413",
    "sg:postcode":"3020",
    "sg:province":"VIC",
    "sg:tags":[
        "transport"
    ],
    "wof:name":"Gniot E",
    "wof:placetype":"venue"
},
  "geometry": {"coordinates":[144.810486,-37.792149],"type":"Point"}
}