{
  "type": "Feature",
  "properties": {
    "addr:full":"23 Rowood Rd Prospect NSW 2148",
    "addr:housenumber":"23",
    "addr:postcode":"2148",
    "addr:street":"Rowood Rd",
    "iso:country":"AU",
    "sg:address":"23 Rowood Rd",
    "sg:city":"Prospect",
    "sg:classifiers":[
        {
            "category":"Home & Garden",
            "subcategory":"Carpets & Floor Coverings",
            "type":"Retail Goods"
        }
    ],
    "sg:phone":"+61 2 9896 1900",
    "sg:postcode":"2148",
    "sg:province":"NSW",
    "wof:name":"Versatile Ceramics",
    "wof:placetype":"venue"
},
  "geometry": {"coordinates":[150.92219543499999,-33.8022727966],"type":"Point"}
}