{
  "type": "Feature",
  "properties": {
    "addr:full":"21 Activity St Acacia Ridge QLD 4110",
    "addr:housenumber":"21",
    "addr:postcode":"4110",
    "addr:street":"Activity St",
    "iso:country":"AU",
    "sg:address":"21 Activity St",
    "sg:city":"Acacia Ridge",
    "sg:classifiers":[
        {
            "category":"Manufacturing",
            "subcategory":"Paper Products",
            "type":"Manufacturing & Wholesale Goods"
        }
    ],
    "sg:phone":"+61 7 3345 3711",
    "sg:postcode":"4110",
    "sg:province":"QLD",
    "sg:tags":[
        "metal",
        "non-ferrous",
        "foundry"
    ],
    "wof:name":"Investment Castings Qld Pty Ltd",
    "wof:placetype":"venue"
},
  "geometry": {"coordinates":[153.038574219,-27.5917396545],"type":"Point"}
}