{
  "type": "Feature",
  "properties": {
    "addr:full":"174 Subiaco Rd Subiaco WA 6008",
    "addr:housenumber":"174",
    "addr:postcode":"6008",
    "addr:street":"Subiaco Rd",
    "iso:country":"AU",
    "sg:address":"174 Subiaco Rd",
    "sg:city":"Subiaco",
    "sg:classifiers":[
        {
            "category":"Retail",
            "subcategory":"Storage",
            "type":"Services"
        }
    ],
    "sg:phone":"+61 8 9381 7404",
    "sg:postcode":"6008",
    "sg:province":"WA",
    "sg:tags":[
        "removal",
        "furniture"
    ],
    "wof:name":"H. Santana Moves",
    "wof:placetype":"venue"
},
  "geometry": {"coordinates":[115.82923126199999,-31.9434318542],"type":"Point"}
}