{
  "type": "Feature",
  "properties": {
    "addr:full":"219 Bank St Bentley WA 6102",
    "addr:housenumber":"219",
    "addr:postcode":"6102",
    "addr:street":"Bank St",
    "iso:country":"AU",
    "sg:address":"219 Bank St",
    "sg:city":"Bentley",
    "sg:classifiers":[
        {
            "category":"Utilities",
            "type":"Services"
        }
    ],
    "sg:phone":"+61 8 9470 1256",
    "sg:postcode":"6102",
    "sg:province":"WA",
    "sg:tags":[
        "equipment",
        "towing"
    ],
    "sg:website":"http://www.parksidetowbars.com.au",
    "wof:name":"Parkside Towbars",
    "wof:placetype":"venue"
},
  "geometry": {"coordinates":[115.91802215600001,-31.9914169312],"type":"Point"}
}