{
  "type": "Feature",
  "properties": {
    "addr:full":"178 Vincent St Cessnock NSW 2325",
    "addr:housenumber":"178",
    "addr:postcode":"2325",
    "addr:street":"Vincent St",
    "iso:country":"AU",
    "sg:address":"178 Vincent St",
    "sg:city":"Cessnock",
    "sg:classifiers":[
        {
            "category":"Autos & Motor Vehicles",
            "subcategory":"Auto Supplies",
            "type":"Retail Goods"
        }
    ],
    "sg:phone":"+61 2 4990 6123",
    "sg:postcode":"2325",
    "sg:province":"NSW",
    "sg:tags":[
        "part",
        "cycles",
        "accessory"
    ],
    "wof:name":"Cross Country Action",
    "wof:placetype":"venue"
},
  "geometry": {"coordinates":[151.35743713400001,-32.8414001465],"type":"Point"}
}