{
  "type": "Feature",
  "properties": {
    "iso:country":"AU",
    "sg:address":"Suite 2/13- 15 Chandler Rd",
    "sg:city":"Boronia",
    "sg:classifiers":[
        {
            "category":"Education",
            "subcategory":"Special Training",
            "type":"Public Place"
        }
    ],
    "sg:phone":"+61 3 9762 8958",
    "sg:postcode":"3155",
    "sg:province":"VIC",
    "sg:tags":[
        "development"
    ],
    "wof:name":"Nash Industrial Training Consultant Pty Ltd",
    "wof:placetype":"venue"
},
  "geometry": {"coordinates":[145.28782653799999,-37.8598251343],"type":"Point"}
}