{
  "type": "Feature",
  "properties": {
    "addr:full":"PO Box 408 Wanneroo WA 6946",
    "addr:postcode":"6946",
    "iso:country":"AU",
    "sg:address":"PO Box 408",
    "sg:city":"Wanneroo",
    "sg:classifiers":[
        {
            "category":"Building & Trades",
            "subcategory":"Landscaping Services",
            "type":"Services"
        }
    ],
    "sg:phone":"+61 414 711 000",
    "sg:postcode":"6946",
    "sg:province":"WA",
    "sg:tags":[
        "designer",
        "landscape",
        "contractor"
    ],
    "wof:name":"Chameleon Landscaping",
    "wof:placetype":"venue"
},
  "geometry": {"coordinates":[115.805656433,-31.7503604889],"type":"Point"}
}