{
  "type": "Feature",
  "properties": {
    "iso:country":"AU",
    "sg:address":"54 Monds Ave",
    "sg:city":"Benalla",
    "sg:classifiers":[
        {
            "category":"Professional",
            "subcategory":"Accounting & Tax Preparation",
            "type":"Services"
        }
    ],
    "sg:phone":"+61 3 5762 4320",
    "sg:postcode":"3672",
    "sg:province":"VIC",
    "sg:tags":[
        "consultant",
        "taxation"
    ],
    "wof:name":"Shir Andrew",
    "wof:placetype":"venue"
},
  "geometry": {"coordinates":[145.96734599999999,-36.556786],"type":"Point"}
}