{
  "type": "Feature",
  "properties": {
    "addr:full":"56B George St Moonta SA 5558",
    "addr:housenumber":"56b",
    "addr:postcode":"5558",
    "addr:street":"George St",
    "iso:country":"AU",
    "sg:address":"56B George St",
    "sg:city":"Moonta",
    "sg:classifiers":[
        {
            "category":"Food & Beverages",
            "subcategory":"Fruits & Vegetables",
            "type":"Retail Goods"
        }
    ],
    "sg:phone":"+61 8 8825 1514",
    "sg:postcode":"5558",
    "sg:province":"SA",
    "sg:tags":[
        "greengrocer",
        "fruiterer"
    ],
    "wof:name":"Moonta Fresh",
    "wof:placetype":"venue"
},
  "geometry": {"coordinates":[137.591552734,-34.0685577393],"type":"Point"}
}