{
  "type": "Feature",
  "properties": {
    "addr:full":"Westfield Shopping Centre, Millaroo Dr Helensvale QLD 4212",
    "addr:postcode":"4212",
    "addr:street":"Millaroo Dr",
    "iso:country":"AU",
    "sg:address":"Westfield Shopping Centre, Millaroo Dr",
    "sg:city":"Helensvale",
    "sg:classifiers":[
        {
            "category":"Communications",
            "subcategory":"Film & Video Production",
            "type":"Services"
        }
    ],
    "sg:phone":"+61 7 5573 4077",
    "sg:postcode":"4212",
    "sg:province":"QLD",
    "sg:tags":[
        "dvd",
        "library"
    ],
    "wof:name":"Video Ezy",
    "wof:placetype":"venue"
},
  "geometry": {"coordinates":[153.33462524399999,-27.9292602539],"type":"Point"}
}