{
  "type": "Feature",
  "properties": {
    "addr:full":"3/ 24 Burrum St Bundaberg QLD 4670",
    "addr:housenumber":"/ 24",
    "addr:postcode":"4670",
    "addr:street":"Burrum St",
    "iso:country":"AU",
    "sg:address":"3/ 24 Burrum St",
    "sg:city":"Bundaberg",
    "sg:classifiers":[
        {
            "category":"Professional",
            "type":"Services"
        }
    ],
    "sg:phone":"+61 7 4153 4727",
    "sg:postcode":"4670",
    "sg:province":"QLD",
    "sg:tags":[
        "quality",
        "assurance"
    ],
    "wof:name":"Quality, Management & Training Services",
    "wof:placetype":"venue"
},
  "geometry": {"coordinates":[152.345581055,-24.870557785],"type":"Point"}
}