{
  "type": "Feature",
  "properties": {
    "iso:country":"AU",
    "sg:address":"Shop 2, 72 Ballina St",
    "sg:city":"Lennox Head",
    "sg:classifiers":[
        {
            "category":"Recreation",
            "subcategory":"Fishing",
            "type":"Entertainment"
        }
    ],
    "sg:phone":"+61 2 6687 6181",
    "sg:postcode":"2478",
    "sg:province":"NSW",
    "sg:tags":[
        "tackle"
    ],
    "wof:name":"Lennox Head Bait & Tackle",
    "wof:placetype":"venue"
},
  "geometry": {"coordinates":[153.59368896500001,-28.7958106995],"type":"Point"}
}