{
  "type": "Feature",
  "properties": {
    "iso:country":"AU",
    "sg:address":"28 Donaldson St",
    "sg:city":"Manunda",
    "sg:classifiers":[
        {
            "category":"Retail",
            "subcategory":"Auto Repair",
            "type":"Services"
        }
    ],
    "sg:phone":"+61 7 4051 6630",
    "sg:postcode":"4870",
    "sg:province":"QLD",
    "sg:tags":[
        "repairer",
        "motor",
        "engineer"
    ],
    "wof:name":"Cairns Dyno Tuning",
    "wof:placetype":"venue"
},
  "geometry": {"coordinates":[145.74981689399999,-16.9155406952],"type":"Point"}
}