{
  "type": "Feature",
  "properties": {
    "addr:full":"21 Moona St Leigh Creek SA 5731",
    "addr:housenumber":"21",
    "addr:postcode":"5731",
    "addr:street":"Moona St",
    "iso:country":"AU",
    "sg:address":"21 Moona St",
    "sg:city":"Leigh Creek",
    "sg:classifiers":[
        {
            "category":"Personal",
            "type":"Services"
        }
    ],
    "sg:phone":"+61 8 8343 3576",
    "sg:postcode":"5731",
    "sg:province":"SA",
    "sg:tags":[
        "reducing",
        "treatment",
        "weight"
    ],
    "wof:name":"Herbalife Australasia Pty Ltd",
    "wof:placetype":"venue"
},
  "geometry": {"coordinates":[138.40260314899999,-30.5982494354],"type":"Point"}
}