{
  "type": "Feature",
  "properties": {
    "addr:full":"22b Janes Drv Corrigin WA 6375",
    "addr:housenumber":"22b",
    "addr:postcode":"6375",
    "addr:street":"Janes Drv",
    "iso:country":"AU",
    "sg:address":"22b Janes Drv",
    "sg:city":"Corrigin",
    "sg:classifiers":[
        {
            "category":"Personal",
            "subcategory":"Massage",
            "type":"Services"
        }
    ],
    "sg:phone":"+61 8 9888 7171",
    "sg:postcode":"6375",
    "sg:province":"WA",
    "sg:tags":[
        "therapy"
    ],
    "wof:name":"Kate Paini",
    "wof:placetype":"venue"
},
  "geometry": {"coordinates":[117.88088999999999,-32.327911],"type":"Point"}
}