{
  "type": "Feature",
  "properties": {
    "addr:full":"39 Sunhill Rd Mt Waverley VIC 3149",
    "addr:housenumber":"39",
    "addr:postcode":"3149",
    "addr:street":"Sunhill Rd",
    "iso:country":"AU",
    "sg:address":"39 Sunhill Rd",
    "sg:city":"Mt Waverley",
    "sg:classifiers":[
        {
            "category":"Wholesale",
            "subcategory":"Metals & Minerals",
            "type":"Manufacturing & Wholesale Goods"
        }
    ],
    "sg:phone":"+61 3 9887 4222",
    "sg:postcode":"3149",
    "sg:province":"VIC",
    "sg:tags":[
        "steel",
        "merchant"
    ],
    "wof:name":"Waverley Metal Co Pty Ltd",
    "wof:placetype":"venue"
},
  "geometry": {"coordinates":[145.12794494600001,-37.8666343689],"type":"Point"}
}