{
  "type": "Feature",
  "properties": {
    "iso:country":"AU",
    "sg:address":"435 Woolcock St",
    "sg:city":"Garbutt",
    "sg:classifiers":[
        {
            "category":"Professional",
            "subcategory":"Detective & Security Services",
            "type":"Services"
        }
    ],
    "sg:phone":"+61 7 4799 5100",
    "sg:postcode":"4814",
    "sg:province":"QLD",
    "sg:tags":[
        "equipment",
        "window",
        "doors"
    ],
    "wof:name":"Bradnams Windows & Doors",
    "wof:placetype":"venue"
},
  "geometry": {"coordinates":[146.759491,-19.267918],"type":"Point"}
}