{
  "type": "Feature",
  "properties": {
    "addr:full":"10 Boolwey St Bowral NSW 2576",
    "addr:housenumber":"10",
    "addr:postcode":"2576",
    "addr:street":"Boolwey St",
    "iso:country":"AU",
    "sg:address":"10 Boolwey St",
    "sg:city":"Bowral",
    "sg:classifiers":[
        {
            "category":"Education",
            "subcategory":"School",
            "type":"Public Place"
        }
    ],
    "sg:phone":"+61 2 4861 3353",
    "sg:postcode":"2576",
    "sg:province":"NSW",
    "sg:tags":[
        "supply"
    ],
    "wof:name":"Creative Kid The",
    "wof:placetype":"venue"
},
  "geometry": {"coordinates":[150.42257690400001,-34.4812202454],"type":"Point"}
}