{
  "type": "Feature",
  "properties": {
    "addr:full":"Wizor St Salisbury Downs SA 5108",
    "addr:postcode":"5108",
    "addr:street":"St",
    "iso:country":"AU",
    "sg:address":"Wizor St",
    "sg:city":"Salisbury Downs",
    "sg:classifiers":[
        {
            "category":"Food & Beverages",
            "subcategory":"Supermarket",
            "type":"Retail Goods"
        }
    ],
    "sg:phone":"+61 8 8281 4663",
    "sg:postcode":"5108",
    "sg:province":"SA",
    "sg:tags":[
        "grocery",
        "store"
    ],
    "wof:name":"Woolworths (S.A.) Pty Ltd",
    "wof:placetype":"venue"
},
  "geometry": {"coordinates":[138.61895751899999,-34.7697105408],"type":"Point"}
}