{
  "type": "Feature",
  "properties": {
    "addr:full":"29 Boundary Rd Braeside VIC 3195",
    "addr:housenumber":"29",
    "addr:postcode":"3195",
    "addr:street":"Boundary Rd",
    "iso:country":"AU",
    "sg:address":"29 Boundary Rd",
    "sg:city":"Braeside",
    "sg:classifiers":[
        {
            "category":"Professional",
            "subcategory":"Printing & Photocopies",
            "type":"Services"
        }
    ],
    "sg:phone":"+61 3 9588 2292",
    "sg:postcode":"3195",
    "sg:province":"VIC",
    "sg:tags":[
        "photocopying"
    ],
    "wof:name":"Minuteman Press",
    "wof:placetype":"venue"
},
  "geometry": {"coordinates":[145.10345459000001,-38.0083503723],"type":"Point"}
}