{
  "type": "Feature",
  "properties": {
    "addr:full":"Cnr Kenny St & Owen Cl Portsmith QLD 4870",
    "addr:postcode":"4870",
    "addr:street":"Cnr Kenny St &;Cl Portsmith",
    "iso:country":"AU",
    "sg:address":"Cnr Kenny St & Owen Cl",
    "sg:city":"Portsmith",
    "sg:classifiers":[
        {
            "category":"Home & Garden",
            "subcategory":"Building Materials",
            "type":"Retail Goods"
        }
    ],
    "sg:phone":"+61 7 4041 2099",
    "sg:postcode":"4870",
    "sg:province":"QLD",
    "sg:tags":[
        "fitting",
        "door"
    ],
    "wof:name":"Hume Doors & Timber",
    "wof:placetype":"venue"
},
  "geometry": {"coordinates":[145.76953125,-16.9359302521],"type":"Point"}
}