{
  "type": "Feature",
  "properties": {
    "iso:country":"AU",
    "sg:address":"Town Hall Vincent St",
    "sg:city":"Ararat",
    "sg:classifiers":[
        {
            "category":"Arts & Performance",
            "subcategory":"Art Gallery",
            "type":"Entertainment"
        }
    ],
    "sg:phone":"+61 3 5352 2836",
    "sg:postcode":"3377",
    "sg:province":"VIC",
    "wof:name":"Ararat Regional Art Gallery",
    "wof:placetype":"venue"
},
  "geometry": {"coordinates":[142.931716919,-37.2827758789],"type":"Point"}
}