{
  "type": "Feature",
  "properties": {
    "addr:full":"17a Meroo St Blacktown NSW 2148",
    "addr:housenumber":"17a",
    "addr:postcode":"2148",
    "addr:street":"Meroo St",
    "iso:country":"AU",
    "sg:address":"17a Meroo St",
    "sg:city":"Blacktown",
    "sg:classifiers":[
        {
            "category":"Building & Trades",
            "subcategory":"Construction",
            "type":"Services"
        }
    ],
    "sg:phone":"+61 2 9671 6880",
    "sg:postcode":"2148",
    "sg:province":"NSW",
    "sg:tags":[
        "earth",
        "excavating",
        "moving",
        "contractor"
    ],
    "wof:name":"Blacktown Bobcat Hire",
    "wof:placetype":"venue"
},
  "geometry": {"coordinates":[150.89857482900001,-33.7714271545],"type":"Point"}
}