{
  "type": "Feature",
  "properties": {
    "iso:country":"AU",
    "sg:address":"Shop 1 15 North Richmond Heritage Plz",
    "sg:city":"North Richmond",
    "sg:classifiers":[
        {
            "category":"Retail",
            "subcategory":"Self-service Laundry",
            "type":"Services"
        }
    ],
    "sg:phone":"+61 2 4571 1104",
    "sg:postcode":"2754",
    "sg:province":"NSW",
    "wof:name":"North Richmond Dry Cleaner & Self Service Laundry",
    "wof:placetype":"venue"
},
  "geometry": {"coordinates":[150.722198486,-33.5824203491],"type":"Point"}
}