{
  "type": "Feature",
  "properties": {
    "addr:full":"2/ 199 Aumuller St Westcourt QLD 4870",
    "addr:housenumber":"/ 199",
    "addr:postcode":"4870",
    "addr:street":"Aumuller St",
    "iso:country":"AU",
    "sg:address":"2/ 199 Aumuller St",
    "sg:city":"Westcourt",
    "sg:classifiers":[
        {
            "category":"Professional",
            "subcategory":"Accounting & Tax Preparation",
            "type":"Services"
        }
    ],
    "sg:phone":"+61 7 4041 6777",
    "sg:postcode":"4870",
    "sg:province":"QLD",
    "sg:tags":[
        "accountant",
        "auditor"
    ],
    "sg:website":"http://www.advacc.com.au",
    "wof:name":"Advantage Accountancy Pty Ltd",
    "wof:placetype":"venue"
},
  "geometry": {"coordinates":[145.75894165,-16.9311637878],"type":"Point"}
}