{
  "type": "Feature",
  "properties": {
    "iso:country":"AU",
    "sg:address":"Augusta St",
    "sg:city":"Warners Bay",
    "sg:classifiers":[
        {
            "category":"Education",
            "subcategory":"School",
            "type":"Public Place"
        }
    ],
    "sg:phone":"+61 2 4948 8844",
    "sg:postcode":"2282",
    "sg:province":"NSW",
    "sg:tags":[
        "state",
        "-",
        "nsw"
    ],
    "wof:name":"Warners Bay Infants'",
    "wof:placetype":"venue"
},
  "geometry": {"coordinates":[151.649459839,-32.9806671143],"type":"Point"}
}