{
  "type": "Feature",
  "properties": {
    "iso:country":"AU",
    "sg:address":"2 Laser Drv",
    "sg:city":"Rowville",
    "sg:classifiers":[
        {
            "category":"Arena",
            "subcategory":"Sports Club",
            "type":"Entertainment"
        }
    ],
    "sg:phone":"+61 3 9796 1066",
    "sg:postcode":"3178",
    "sg:province":"VIC",
    "sg:tags":[
        "defence",
        "supply",
        "self",
        "instruction",
        "martial art"
    ],
    "wof:name":"Kung Fu Golden Lion",
    "wof:placetype":"venue"
},
  "geometry": {"coordinates":[145.24444580100001,-37.9112129211],"type":"Point"}
}