{
  "type": "Feature",
  "properties": {
    "iso:country":"AU",
    "sg:address":"37 Ryan St",
    "sg:city":"Charters Towers",
    "sg:classifiers":[
        {
            "category":"Real Estate",
            "subcategory":"Architect",
            "type":"Services"
        }
    ],
    "sg:phone":"+61 7 4787 8221",
    "sg:postcode":"4820",
    "sg:province":"QLD",
    "sg:tags":[
        "building",
        "designer"
    ],
    "wof:name":"Towers Building Design",
    "wof:placetype":"venue"
},
  "geometry": {"coordinates":[146.26252700000001,-20.07548],"type":"Point"}
}