{
  "type": "Feature",
  "properties": {
    "iso:country":"AU",
    "sg:address":"9-15 Ryan St",
    "sg:city":"Moonta",
    "sg:classifiers":[
        {
            "category":"Home & Garden",
            "subcategory":"Hardware",
            "type":"Retail Goods"
        }
    ],
    "sg:phone":"+61 8 8825 2867",
    "sg:postcode":"5558",
    "sg:province":"SA",
    "sg:tags":[
        "plumber",
        "supply"
    ],
    "wof:name":"Macks Moonta Hardware",
    "wof:placetype":"venue"
},
  "geometry": {"coordinates":[137.592163086,-34.0675086975],"type":"Point"}
}