{
  "type": "Feature",
  "properties": {
    "iso:country":"AU",
    "sg:address":"2/ 4 Stutt Ave",
    "sg:city":"Doncaster",
    "sg:classifiers":[
        {
            "category":"Insurance",
            "subcategory":"Hazard Insurance",
            "type":"Services"
        }
    ],
    "sg:phone":"+61 3 9857 8976",
    "sg:postcode":"3108",
    "sg:province":"VIC",
    "sg:tags":[
        "loss",
        "adjuster",
        "assessor"
    ],
    "wof:name":"CPC Claims Preparation Consultants",
    "wof:placetype":"venue"
},
  "geometry": {"coordinates":[145.106292725,-37.7861595154],"type":"Point"}
}