{
  "type": "Feature",
  "properties": {
    "addr:full":"Shp9/ 5 Hillcrest Rd Pennant Hills NSW 2120",
    "addr:housenumber":"5",
    "addr:postcode":"2120",
    "addr:street":"Hillcrest Rd",
    "iso:country":"AU",
    "sg:address":"Shp9/ 5 Hillcrest Rd",
    "sg:city":"Pennant Hills",
    "sg:classifiers":[
        {
            "category":"Fast Food",
            "type":"Food & Drink"
        }
    ],
    "sg:phone":"+61 2 9875 2006",
    "sg:postcode":"2120",
    "sg:province":"NSW",
    "sg:tags":[
        "away",
        "take"
    ],
    "wof:name":"Senju Sushi",
    "wof:placetype":"venue"
},
  "geometry": {"coordinates":[151.070602417,-33.7382469177],"type":"Point"}
}