{
  "type": "Feature",
  "properties": {
    "addr:full":"10 Aiken Rd West Pennant Hills NSW 2125",
    "addr:housenumber":"10",
    "addr:postcode":"2125",
    "addr:street":"Aiken Rd",
    "iso:country":"AU",
    "sg:address":"10 Aiken Rd",
    "sg:city":"West Pennant Hills",
    "sg:classifiers":[
        {
            "category":"Building & Trades",
            "subcategory":"Construction",
            "type":"Services"
        }
    ],
    "sg:phone":"+61 2 9871 8877",
    "sg:postcode":"2125",
    "sg:province":"NSW",
    "sg:tags":[
        "joiner",
        "carpenter"
    ],
    "wof:name":"Lovarini F L",
    "wof:placetype":"venue"
},
  "geometry": {"coordinates":[151.03248596200001,-33.7535820007],"type":"Point"}
}