{
  "type": "Feature",
  "properties": {
    "iso:country":"AU",
    "sg:address":"66 Melbourne St",
    "sg:city":"Riverstone",
    "sg:classifiers":[
        {
            "category":"Building & Trades",
            "subcategory":"Construction",
            "type":"Services"
        }
    ],
    "sg:phone":"+61 2 9627 4192",
    "sg:postcode":"2765",
    "sg:province":"NSW",
    "sg:tags":[
        "earth",
        "excavating",
        "moving",
        "contractor"
    ],
    "wof:name":"Houghton & Meredith Pty Ltd",
    "wof:placetype":"venue"
},
  "geometry": {"coordinates":[150.85987854000001,-33.6623344421],"type":"Point"}
}