{
  "type": "Feature",
  "properties": {
    "iso:country":"AU",
    "sg:address":"20 Williams Rd",
    "sg:city":"Melville",
    "sg:classifiers":[
        {
            "category":"Professional",
            "subcategory":"Art Services",
            "type":"Services"
        }
    ],
    "sg:phone":"+61 8 9330 4038",
    "sg:postcode":"6156",
    "sg:province":"WA",
    "sg:tags":[
        "graphic",
        "designer"
    ],
    "wof:name":"Creative Graphic Design",
    "wof:placetype":"venue"
},
  "geometry": {"coordinates":[115.803192,-32.035721],"type":"Point"}
}