{
  "type": "Feature",
  "properties": {
    "iso:country":"AU",
    "sg:address":"Hamilton Public School Steel St",
    "sg:city":"Hamilton",
    "sg:classifiers":[
        {
            "category":"Professional",
            "subcategory":"Management & Consulting",
            "type":"Services"
        }
    ],
    "sg:phone":"+61 2 4969 7862",
    "sg:postcode":"2303",
    "sg:province":"NSW",
    "sg:tags":[
        "consultant",
        "educational"
    ],
    "wof:name":"Parents As Teachers Programme",
    "wof:placetype":"venue"
},
  "geometry": {"coordinates":[151.74414100000001,-32.923046],"type":"Point"}
}