{
  "type": "Feature",
  "properties": {
    "addr:full":"234 Kissing Point Rd Dundas NSW 2117",
    "addr:housenumber":"234",
    "addr:postcode":"2117",
    "addr:street":"Kissing Point Rd",
    "iso:country":"AU",
    "sg:address":"234 Kissing Point Rd",
    "sg:city":"Dundas",
    "sg:classifiers":[
        {
            "category":"Manufacturing",
            "subcategory":"Food",
            "type":"Manufacturing & Wholesale Goods"
        }
    ],
    "sg:phone":"+61 2 9684 6565",
    "sg:postcode":"2117",
    "sg:province":"NSW",
    "sg:tags":[
        "function",
        "catering"
    ],
    "wof:name":"Fringe Benefit Catering",
    "wof:placetype":"venue"
},
  "geometry": {"coordinates":[151.05023193400001,-33.7982978821],"type":"Point"}
}