{
  "type": "Feature",
  "properties": {
    "addr:full":"Shop 2 1128 Burke Rd Balwyn North VIC 3104",
    "addr:housenumber":"shop 2 1128",
    "addr:postcode":"3104",
    "addr:street":"Burke Rd",
    "iso:country":"AU",
    "sg:address":"Shop 2 1128 Burke Rd",
    "sg:city":"Balwyn North",
    "sg:classifiers":[
        {
            "category":"Personal",
            "subcategory":"Beauty Salon",
            "type":"Services"
        }
    ],
    "sg:phone":"+61 3 9819 7290",
    "sg:postcode":"3104",
    "sg:province":"VIC",
    "sg:tags":[
        "hairdresser"
    ],
    "wof:name":"Hovendens Hairdressing",
    "wof:placetype":"venue"
},
  "geometry": {"coordinates":[145.063964844,-37.7941932678],"type":"Point"}
}