{
  "type": "Feature",
  "properties": {
    "addr:full":"Lot 116 Fitzroy St Dubbo NSW 2830",
    "addr:postcode":"2830",
    "addr:street":"Fitzroy St",
    "iso:country":"AU",
    "sg:address":"Lot 116 Fitzroy St",
    "sg:city":"Dubbo",
    "sg:classifiers":[
        {
            "category":"Professional",
            "type":"Services"
        }
    ],
    "sg:phone":"+61 1300 366 684",
    "sg:postcode":"2830",
    "sg:province":"NSW",
    "sg:tags":[
        "transport"
    ],
    "wof:name":"Toll IPEC",
    "wof:placetype":"venue"
},
  "geometry": {"coordinates":[148.61346435600001,-32.2498435974],"type":"Point"}
}