{
  "type": "Feature",
  "properties": {
    "addr:full":"Mt Cotton Rd Mt Cotton QLD 4165",
    "addr:postcode":"4165",
    "addr:street":"Cotton Rd",
    "iso:country":"AU",
    "sg:address":"Mt Cotton Rd",
    "sg:city":"Mt Cotton",
    "sg:classifiers":[
        {
            "category":"Building & Trades",
            "subcategory":"Construction",
            "type":"Services"
        }
    ],
    "sg:phone":"+61 7 3206 6100",
    "sg:postcode":"4165",
    "sg:province":"QLD",
    "sg:tags":[
        "earth",
        "excavating",
        "moving",
        "contractor"
    ],
    "wof:name":"Traydors Pty Ltd",
    "wof:placetype":"venue"
},
  "geometry": {"coordinates":[153.23976135300001,-27.6425285339],"type":"Point"}
}