{
  "type": "Feature",
  "properties": {
    "addr:full":"174 Pakington St Geelong West VIC 3218",
    "addr:housenumber":"174",
    "addr:postcode":"3218",
    "addr:street":"Pakington St",
    "iso:country":"AU",
    "sg:address":"174 Pakington St",
    "sg:city":"Geelong West",
    "sg:classifiers":[
        {
            "category":"Education",
            "subcategory":"University",
            "type":"Public Place"
        }
    ],
    "sg:phone":"+61 3 5229 3558",
    "sg:postcode":"3218",
    "sg:province":"VIC",
    "sg:tags":[
        "sewing",
        "dressmaking",
        "tuition"
    ],
    "wof:name":"Heights Sewing Centre",
    "wof:placetype":"venue"
},
  "geometry": {"coordinates":[144.348419189,-38.1410713196],"type":"Point"}
}