{
  "type": "Feature",
  "properties": {
    "addr:full":"PO Box 141 Glen Iris VIC 3146",
    "addr:postcode":"3146",
    "iso:country":"AU",
    "sg:address":"PO Box 141",
    "sg:city":"Glen Iris",
    "sg:classifiers":[
        {
            "category":"Industrial Area",
            "type":"Public Place"
        }
    ],
    "sg:phone":"+61 3 9509 0722",
    "sg:postcode":"3146",
    "sg:province":"VIC",
    "sg:tags":[
        "consulting",
        "chemist"
    ],
    "wof:name":"Sue Akeroyd & Associates",
    "wof:placetype":"venue"
},
  "geometry": {"coordinates":[145.067626953,-37.8564682007],"type":"Point"}
}