{
  "type": "Feature",
  "properties": {
    "addr:full":"PO Box 3146 Freemans Reach NSW 2756",
    "addr:postcode":"2756",
    "iso:country":"AU",
    "sg:address":"PO Box 3146",
    "sg:city":"Freemans Reach",
    "sg:classifiers":[
        {
            "category":"Building & Trades",
            "subcategory":"Construction",
            "type":"Services"
        }
    ],
    "sg:phone":"+61 410 724 369",
    "sg:postcode":"2756",
    "sg:province":"NSW",
    "sg:tags":[
        "concrete",
        "contractor"
    ],
    "wof:name":"Jay Zed's Decorative Concrete",
    "wof:placetype":"venue"
},
  "geometry": {"coordinates":[150.79960632300001,-33.5579185486],"type":"Point"}
}