{
  "type": "Feature",
  "properties": {
    "addr:full":"16th Level, 15 Adelaide St Brisbane QLD 4000",
    "addr:housenumber":"15",
    "addr:postcode":"4000",
    "addr:street":"Adelaide St",
    "iso:country":"AU",
    "sg:address":"16th Level, 15 Adelaide St",
    "sg:city":"Brisbane",
    "sg:classifiers":[
        {
            "category":"Professional",
            "subcategory":"Lawyer & Legal Services",
            "type":"Services"
        }
    ],
    "sg:phone":"+61 7 3001 2999",
    "sg:postcode":"4000",
    "sg:province":"QLD",
    "sg:tags":[
        "wills",
        "probate",
        "estate"
    ],
    "sg:website":"http://www.bennettphilp.com.au",
    "wof:name":"Bennett & Philp Solicitors",
    "wof:placetype":"venue"
},
  "geometry": {"coordinates":[153.02308654800001,-27.4701156616],"type":"Point"}
}