{
  "type": "Feature",
  "properties": {
    "addr:full":"Unit 33/ 756 Burwood Hwy Ferntree Gully VIC 3156",
    "addr:housenumber":"/ 756",
    "addr:postcode":"3156",
    "addr:street":"Burwood Hwy",
    "iso:country":"AU",
    "sg:address":"Unit 33/ 756 Burwood Hwy",
    "sg:city":"Ferntree Gully",
    "sg:classifiers":[
        {
            "category":"Mining & Drilling",
            "type":"Manufacturing & Wholesale Goods"
        }
    ],
    "sg:phone":"+61 3 9752 3349",
    "sg:postcode":"3156",
    "sg:province":"VIC",
    "sg:tags":[
        "concrete",
        "breaking",
        "grinding",
        "sawing"
    ],
    "wof:name":"Surfprep",
    "wof:placetype":"venue"
},
  "geometry": {"coordinates":[145.30079650900001,-37.8910942078],"type":"Point"}
}