{
  "type": "Feature",
  "properties": {
    "iso:country":"AU",
    "sg:address":"24 Gayndah Rd",
    "sg:city":"Maryborough",
    "sg:classifiers":[
        {
            "category":"Building & Trades",
            "subcategory":"Construction",
            "type":"Services"
        }
    ],
    "sg:phone":"+61 7 4121 2880",
    "sg:postcode":"4650",
    "sg:province":"QLD",
    "sg:tags":[
        "contractor"
    ],
    "wof:name":"Bowes D J & K A",
    "wof:placetype":"venue"
},
  "geometry": {"coordinates":[152.667984,-25.517174],"type":"Point"}
}