{
  "type": "Feature",
  "properties": {
    "iso:country":"AU",
    "sg:address":"10 Ridgecrest Ave",
    "sg:city":"Darlington",
    "sg:classifiers":[
        {
            "category":"Building & Trades",
            "subcategory":"Cleaning & Sanitation",
            "type":"Services"
        }
    ],
    "sg:phone":"+61 411 746 550",
    "sg:postcode":"5047",
    "sg:province":"SA",
    "sg:tags":[
        "commercial",
        "maintenance"
    ],
    "wof:name":"South Australian Building Property Maintenance Services Pty Ltd",
    "wof:placetype":"venue"
},
  "geometry": {"coordinates":[138.554382,-35.033428],"type":"Point"}
}