{
  "type": "Feature",
  "properties": {
    "iso:country":"AU",
    "sg:address":"2/ 32 - 34 Green St",
    "sg:city":"Thomastown",
    "sg:classifiers":[
        {
            "category":"Wholesale",
            "subcategory":"Machinery & Supplies",
            "type":"Manufacturing & Wholesale Goods"
        }
    ],
    "sg:phone":"+61 3 9465 0900",
    "sg:postcode":"3074",
    "sg:province":"VIC",
    "sg:tags":[
        "distributor",
        "crane",
        "mfrs"
    ],
    "wof:name":"Robway Crane Safety Systems",
    "wof:placetype":"venue"
},
  "geometry": {"coordinates":[145.038208008,-37.6915016174],"type":"Point"}
}