{
  "type": "Feature",
  "properties": {
    "addr:full":"436 William St West Melbourne VIC 3003",
    "addr:housenumber":"436",
    "addr:postcode":"3003",
    "addr:street":"William St",
    "iso:country":"AU",
    "sg:address":"436 William St",
    "sg:city":"West Melbourne",
    "sg:classifiers":[
        {
            "category":"Professional",
            "subcategory":"Detective & Security Services",
            "type":"Services"
        }
    ],
    "sg:phone":"+61 3 9326 5455",
    "sg:postcode":"3003",
    "sg:province":"VIC",
    "sg:tags":[
        "investigator"
    ],
    "wof:name":"Inge Detective Agency Pty Ltd",
    "wof:placetype":"venue"
},
  "geometry": {"coordinates":[144.95463562,-37.8074951172],"type":"Point"}
}