{
  "type": "Feature",
  "properties": {
    "iso:country":"AU",
    "sg:address":"340 Curtin Ave",
    "sg:city":"(West) Eagle Farm",
    "sg:classifiers":[
        {
            "category":"Home & Garden",
            "subcategory":"Hardware",
            "type":"Retail Goods"
        }
    ],
    "sg:phone":"+61 7 3623 3600",
    "sg:postcode":"4009",
    "sg:province":"QLD",
    "sg:tags":[
        "pumping",
        "contractor"
    ],
    "wof:name":"Coates Shorco",
    "wof:placetype":"venue"
},
  "geometry": {"coordinates":[153.08886718799999,-27.4393558502],"type":"Point"}
}