{
  "type": "Feature",
  "properties": {
    "iso:country":"AU",
    "sg:address":"209 Heatherhill Rd",
    "sg:city":"Frankston",
    "sg:classifiers":[
        {
            "category":"Utilities",
            "subcategory":"Electric",
            "type":"Services"
        }
    ],
    "sg:phone":"+61 3 9776 7952",
    "sg:postcode":"3199",
    "sg:province":"VIC",
    "sg:tags":[
        "electrical",
        "contractor"
    ],
    "wof:name":"Darren Briggs",
    "wof:placetype":"venue"
},
  "geometry": {"coordinates":[145.15895080600001,-38.1638298035],"type":"Point"}
}