{
  "type": "Feature",
  "properties": {
    "addr:full":"34 Bunbury St Newport VIC 3015",
    "addr:housenumber":"34",
    "addr:postcode":"3015",
    "addr:street":"Bunbury St",
    "iso:country":"AU",
    "sg:address":"34 Bunbury St",
    "sg:city":"Newport",
    "sg:classifiers":[
        {
            "category":"Home & Garden",
            "subcategory":"Building Materials",
            "type":"Retail Goods"
        }
    ],
    "sg:phone":"+61 3 9399 3389",
    "sg:postcode":"3015",
    "sg:province":"VIC",
    "sg:tags":[
        "merchant",
        "glass",
        "glazier"
    ],
    "wof:name":"Bayview Glass",
    "wof:placetype":"venue"
},
  "geometry": {"coordinates":[144.889938355,-37.8493423462],"type":"Point"}
}