{
  "type": "Feature",
  "properties": {
    "addr:full":"Level 3, 43 Burelli St Wollongong NSW 2500",
    "addr:housenumber":"43",
    "addr:postcode":"2500",
    "addr:street":"Burelli St",
    "iso:country":"AU",
    "sg:address":"Level 3, 43 Burelli St",
    "sg:city":"Wollongong",
    "sg:classifiers":[
        {
            "category":"Health Services",
            "subcategory":"Doctor",
            "type":"Services"
        }
    ],
    "sg:phone":"+61 2 4253 6400",
    "sg:postcode":"2500",
    "sg:province":"NSW",
    "sg:tags":[
        "occupational",
        "safety"
    ],
    "wof:name":"Health For Industry",
    "wof:placetype":"venue"
},
  "geometry": {"coordinates":[150.89819299999999,-34.426872],"type":"Point"}
}