{
  "type": "Feature",
  "properties": {
    "iso:country":"AU",
    "sg:address":"Unit 2/ 7 Gross Ave",
    "sg:city":"Umina Beach",
    "sg:classifiers":[
        {
            "category":"Building & Trades",
            "subcategory":"Construction",
            "type":"Services"
        }
    ],
    "sg:phone":"+61 410 447 983",
    "sg:postcode":"2257",
    "sg:province":"NSW",
    "sg:tags":[
        "rendering",
        "cement"
    ],
    "wof:name":"Michael Fernandes Rendering",
    "wof:placetype":"venue"
},
  "geometry": {"coordinates":[151.32313537600001,-33.5197563171],"type":"Point"}
}