{
  "type": "Feature",
  "properties": {
    "addr:full":"51 Outram St Summerhill TAS 7250",
    "addr:housenumber":"51",
    "addr:postcode":"7250",
    "addr:street":"Outram St",
    "iso:country":"AU",
    "sg:address":"51 Outram St",
    "sg:city":"Summerhill",
    "sg:classifiers":[
        {
            "category":"Building & Trades",
            "subcategory":"Cleaning & Sanitation",
            "type":"Services"
        }
    ],
    "sg:phone":"+61 417 561 660",
    "sg:postcode":"7250",
    "sg:province":"TAS",
    "sg:tags":[
        "cleaner",
        "repairer",
        "roof"
    ],
    "wof:name":"Robert Turner",
    "wof:placetype":"venue"
},
  "geometry": {"coordinates":[147.12681579599999,-41.4609298706],"type":"Point"}
}