{
  "type": "Feature",
  "properties": {
    "iso:country":"AU",
    "sg:address":"11 Sydney Rd",
    "sg:city":"Mudgee",
    "sg:classifiers":[
        {
            "category":"Autos & Motor Vehicles",
            "subcategory":"Automobile Sales",
            "type":"Retail Goods"
        }
    ],
    "sg:phone":"+61 2 6372 3288",
    "sg:postcode":"2850",
    "sg:province":"NSW",
    "sg:tags":[
        "car",
        "new"
    ],
    "wof:name":"McCarroll Motors",
    "wof:placetype":"venue"
},
  "geometry": {"coordinates":[149.587677,-32.599361],"type":"Point"}
}