{
  "type": "Feature",
  "properties": {
    "iso:country":"AU",
    "sg:address":"6/ 18 Northumberland Rd",
    "sg:city":"Taren Point",
    "sg:classifiers":[
        {
            "category":"Building & Trades",
            "subcategory":"Construction",
            "type":"Services"
        }
    ],
    "sg:phone":"+61 2 9524 1266",
    "sg:postcode":"2229",
    "sg:province":"NSW",
    "sg:tags":[
        "home",
        "air conditioning"
    ],
    "wof:name":"Harnleigh Air & Electrical Pty Ltd",
    "wof:placetype":"venue"
},
  "geometry": {"coordinates":[151.13166809099999,-34.0292282104],"type":"Point"}
}