{
  "type": "Feature",
  "properties": {
    "iso:country":"AU",
    "sg:address":"Eight Mile Plains Shopping Cntr Cnr Warrigal & Padstow Rds",
    "sg:city":"Eight Mile Plains",
    "sg:classifiers":[
        {
            "category":"Health Services",
            "subcategory":"Health Practitioner",
            "type":"Services"
        }
    ],
    "sg:phone":"+61 7 3841 0522",
    "sg:postcode":"4113",
    "sg:province":"QLD",
    "sg:tags":[
        "physiotherapist"
    ],
    "wof:name":"Eight Mile Plains Physiotherapy",
    "wof:placetype":"venue"
},
  "geometry": {"coordinates":[153.08758544899999,-27.5755310059],"type":"Point"}
}