{
  "type": "Feature",
  "properties": {
    "addr:full":"464 Bridge Rd Richmond VIC 3121",
    "addr:housenumber":"464",
    "addr:postcode":"3121",
    "addr:street":"Bridge Rd",
    "iso:country":"AU",
    "sg:address":"464 Bridge Rd",
    "sg:city":"Richmond",
    "sg:classifiers":[
        {
            "category":"Restaurant",
            "type":"Food & Drink"
        }
    ],
    "sg:phone":"+61 3 9429 7133",
    "sg:postcode":"3121",
    "sg:province":"VIC",
    "wof:name":"Montezumas",
    "wof:placetype":"venue"
},
  "geometry": {"coordinates":[145.00697326700001,-37.819480896],"type":"Point"}
}