{
  "type": "Feature",
  "properties": {
    "addr:full":"PO Box 1092 Lakes Entrance VIC 3909",
    "addr:postcode":"3909",
    "iso:country":"AU",
    "sg:address":"PO Box 1092",
    "sg:city":"Lakes Entrance",
    "sg:classifiers":[
        {
            "category":"Recreation",
            "subcategory":"Boat Charter",
            "type":"Entertainment"
        }
    ],
    "sg:phone":"+61 428 401 819",
    "sg:postcode":"3909",
    "sg:province":"VIC",
    "wof:name":"Far Out Charters",
    "wof:placetype":"venue"
},
  "geometry": {"coordinates":[148.00227355999999,-37.8771514893],"type":"Point"}
}