{
  "type": "Feature",
  "properties": {
    "iso:country":"AU",
    "sg:address":"136 Eighth St",
    "sg:city":"Mildura",
    "sg:classifiers":[
        {
            "category":"Cafe",
            "type":"Food & Drink"
        }
    ],
    "sg:phone":"+61 3 5023 0953",
    "sg:postcode":"3500",
    "sg:province":"VIC",
    "wof:name":"Eighth Street Food Fair",
    "wof:placetype":"venue"
},
  "geometry": {"coordinates":[142.16192626899999,-34.1842193604],"type":"Point"}
}