{
  "type": "Feature",
  "properties": {
    "addr:full":"8 Clyde Crt Croydon VIC 3136",
    "addr:housenumber":"8",
    "addr:postcode":"3136",
    "addr:street":"Clyde Crt",
    "iso:country":"AU",
    "sg:address":"8 Clyde Crt",
    "sg:city":"Croydon",
    "sg:classifiers":[
        {
            "category":"Organizations",
            "subcategory":"Professional Association",
            "type":"Services"
        }
    ],
    "sg:phone":"+61 409 348 266",
    "sg:postcode":"3136",
    "sg:province":"VIC",
    "sg:tags":[
        "web",
        "internet"
    ],
    "wof:name":"3 I.T. Media",
    "wof:placetype":"venue"
},
  "geometry": {"coordinates":[145.28102111800001,-37.8145179749],"type":"Point"}
}