{
  "type": "Feature",
  "properties": {
    "addr:full":"57 Bayel Drv Koorainghat NSW 2430",
    "addr:housenumber":"57",
    "addr:postcode":"2430",
    "addr:street":"Bayel Drv",
    "iso:country":"AU",
    "sg:address":"57 Bayel Drv",
    "sg:city":"Koorainghat",
    "sg:classifiers":[
        {
            "category":"Professional",
            "subcategory":"Business Services",
            "type":"Services"
        }
    ],
    "sg:phone":"+61 2 6553 6436",
    "sg:postcode":"2430",
    "sg:province":"NSW",
    "sg:tags":[
        "livestock",
        "transport"
    ],
    "wof:name":"Taree live Stock transporting",
    "wof:placetype":"venue"
},
  "geometry": {"coordinates":[152.46582000000001,-31.988688],"type":"Point"}
}