{
  "type": "Feature",
  "properties": {
    "addr:full":"Phoenix Rd Lucknow NSW 2800",
    "addr:postcode":"2800",
    "addr:street":"Phoenix Rd",
    "iso:country":"AU",
    "sg:address":"Phoenix Rd",
    "sg:city":"Lucknow",
    "sg:classifiers":[
        {
            "category":"Farming",
            "subcategory":"Berry Farm",
            "type":"Manufacturing & Wholesale Goods"
        }
    ],
    "sg:phone":"+61 2 6365 5335",
    "sg:postcode":"2800",
    "sg:province":"NSW",
    "sg:tags":[
        "fruit",
        "grower"
    ],
    "wof:name":"Floyd A J",
    "wof:placetype":"venue"
},
  "geometry": {"coordinates":[149.10310363799999,-33.2653274536],"type":"Point"}
}