{
  "type": "Feature",
  "properties": {
    "addr:full":"244 Vance Rd Leeton NSW 2705",
    "addr:housenumber":"244",
    "addr:postcode":"2705",
    "addr:street":"Vance Rd",
    "iso:country":"AU",
    "sg:address":"244 Vance Rd",
    "sg:city":"Leeton",
    "sg:classifiers":[
        {
            "category":"Building & Trades",
            "subcategory":"Landscaping Services",
            "type":"Services"
        }
    ],
    "sg:phone":"+61 428 627 619",
    "sg:postcode":"2705",
    "sg:province":"NSW",
    "sg:tags":[
        "designer",
        "landscape",
        "contractor"
    ],
    "wof:name":"MIA Laser Levelling",
    "wof:placetype":"venue"
},
  "geometry": {"coordinates":[146.38713073700001,-34.5413131714],"type":"Point"}
}