{
  "type": "Feature",
  "properties": {
    "addr:full":"623 Ruthven St Toowoomba QLD 4350",
    "addr:housenumber":"623",
    "addr:postcode":"4350",
    "addr:street":"Ruthven St",
    "iso:country":"AU",
    "sg:address":"623 Ruthven St",
    "sg:city":"Toowoomba",
    "sg:classifiers":[
        {
            "category":"Autos & Motor Vehicles",
            "subcategory":"Automobile Sales",
            "type":"Retail Goods"
        }
    ],
    "sg:phone":"+61 7 4659 7077",
    "sg:postcode":"4350",
    "sg:province":"QLD",
    "sg:tags":[
        "car",
        "used"
    ],
    "wof:name":"Tuff & Prestige Wholesale Cars",
    "wof:placetype":"venue"
},
  "geometry": {"coordinates":[151.95233200000001,-27.568022],"type":"Point"}
}