{
  "type": "Feature",
  "properties": {
    "iso:country":"AU",
    "sg:address":"3743 Pt Nepean Rd",
    "sg:city":"Portsea",
    "sg:classifiers":[
        {
            "category":"Real Estate",
            "subcategory":"Real Estate Agent",
            "type":"Services"
        }
    ],
    "sg:phone":"+61 3 5984 4500",
    "sg:postcode":"3944",
    "sg:province":"VIC",
    "wof:name":"R T Edgar Pty Ltd",
    "wof:placetype":"venue"
},
  "geometry": {"coordinates":[144.71461486800001,-38.3203201294],"type":"Point"}
}