{
  "type": "Feature",
  "properties": {
    "iso:country":"AU",
    "sg:address":"Newton Rd",
    "sg:city":"Loxton",
    "sg:classifiers":[
        {
            "category":"Retail",
            "subcategory":"Auto Repair",
            "type":"Services"
        }
    ],
    "sg:phone":"+61 8 8584 6259",
    "sg:postcode":"5333",
    "sg:province":"SA",
    "sg:tags":[
        "repairer",
        "motor",
        "engineer"
    ],
    "wof:name":"Manuel K R & D L Auto Repairs",
    "wof:placetype":"venue"
},
  "geometry": {"coordinates":[140.575408936,-34.4621200562],"type":"Point"}
}