{
  "type": "Feature",
  "properties": {
    "iso:country":"AU",
    "sg:address":"46 Lerra Rd",
    "sg:city":"Windella Downs",
    "sg:classifiers":[
        {
            "category":"Utilities",
            "subcategory":"Mobile Phone",
            "type":"Services"
        }
    ],
    "sg:phone":"+61 2 4930 7554",
    "sg:postcode":"2320",
    "sg:province":"NSW",
    "sg:tags":[
        "aviation",
        "consultant"
    ],
    "wof:name":"Evans Russ Pty Ltd",
    "wof:placetype":"venue"
},
  "geometry": {"coordinates":[151.480834961,-32.6912765503],"type":"Point"}
}