{
  "type": "Feature",
  "properties": {
    "addr:full":"52 Lynch St Footscray VIC 3011",
    "addr:housenumber":"52",
    "addr:postcode":"3011",
    "addr:street":"Lynch St",
    "iso:country":"AU",
    "sg:address":"52 Lynch St",
    "sg:city":"Footscray",
    "sg:classifiers":[
        {
            "category":"Organizations",
            "subcategory":"Professional Association",
            "type":"Services"
        }
    ],
    "sg:phone":"+61 3 9362 7707",
    "sg:postcode":"3011",
    "sg:province":"VIC",
    "sg:tags":[
        "web",
        "internet"
    ],
    "wof:name":"Symbiosis Creative",
    "wof:placetype":"venue"
},
  "geometry": {"coordinates":[144.90203857399999,-37.7963027954],"type":"Point"}
}