{
  "type": "Feature",
  "properties": {
    "addr:full":"198 Lewis Rd Forrestfield WA 6058",
    "addr:housenumber":"198",
    "addr:postcode":"6058",
    "addr:street":"Lewis Rd",
    "iso:country":"AU",
    "sg:address":"198 Lewis Rd",
    "sg:city":"Forrestfield",
    "sg:classifiers":[
        {
            "category":"Building & Trades",
            "subcategory":"Construction",
            "type":"Services"
        }
    ],
    "sg:phone":"+61 8 9359 2044",
    "sg:postcode":"6058",
    "sg:province":"WA",
    "sg:tags":[
        "installation",
        "air conditioning"
    ],
    "wof:name":"Commercial Air Solutions",
    "wof:placetype":"venue"
},
  "geometry": {"coordinates":[116.026626587,-31.9862155914],"type":"Point"}
}