{
  "type": "Feature",
  "properties": {
    "iso:country":"AU",
    "sg:address":"87 Military Rd",
    "sg:city":"Port Kembla",
    "sg:classifiers":[
        {
            "category":"Food & Beverages",
            "subcategory":"Bakery",
            "type":"Retail Goods"
        }
    ],
    "sg:phone":"+61 2 4274 4633",
    "sg:postcode":"2505",
    "sg:province":"NSW",
    "sg:tags":[
        "baker"
    ],
    "wof:name":"Cheep Bread Factory The",
    "wof:placetype":"venue"
},
  "geometry": {"coordinates":[150.903748,-34.481682],"type":"Point"}
}