{
  "type": "Feature",
  "properties": {
    "addr:full":"58 Hellawell Rd Sunnybank Hills QLD 4109",
    "addr:housenumber":"58",
    "addr:postcode":"4109",
    "addr:street":"Hellawell Rd",
    "iso:country":"AU",
    "sg:address":"58 Hellawell Rd",
    "sg:city":"Sunnybank Hills",
    "sg:classifiers":[
        {
            "category":"Sports & Exercise",
            "subcategory":"Gym",
            "type":"Entertainment"
        }
    ],
    "sg:phone":"+61 431 980 277",
    "sg:postcode":"4109",
    "sg:province":"QLD",
    "sg:tags":[
        "personal",
        "trainer",
        "fitness"
    ],
    "wof:name":"Bootylicious Lifestyle Group",
    "wof:placetype":"venue"
},
  "geometry": {"coordinates":[153.060913086,-27.5999183655],"type":"Point"}
}