{
  "type": "Feature",
  "properties": {
    "addr:full":"6 Penna Av Glynde SA 5070",
    "addr:housenumber":"6",
    "addr:postcode":"5070",
    "addr:street":"Penna Av",
    "iso:country":"AU",
    "sg:address":"6 Penna Av",
    "sg:city":"Glynde",
    "sg:classifiers":[
        {
            "category":"Building & Trades",
            "subcategory":"Construction",
            "type":"Services"
        }
    ],
    "sg:phone":"+61 8 8336 4800",
    "sg:postcode":"5070",
    "sg:province":"SA",
    "sg:tags":[
        "contractor"
    ],
    "wof:name":"Bettio Building Contractors",
    "wof:placetype":"venue"
},
  "geometry": {"coordinates":[138.65672302199999,-34.8942718506],"type":"Point"}
}