{
  "type": "Feature",
  "properties": {
    "addr:full":"277 Brunswick St Fitzroy VIC 3065",
    "addr:housenumber":"277",
    "addr:postcode":"3065",
    "addr:street":"Brunswick St",
    "iso:country":"AU",
    "sg:address":"277 Brunswick St",
    "sg:city":"Fitzroy",
    "sg:classifiers":[
        {
            "category":"Health Services",
            "subcategory":"Health Practitioner",
            "type":"Services"
        }
    ],
    "sg:phone":"+61 3 9417 6599",
    "sg:postcode":"3065",
    "sg:province":"VIC",
    "sg:tags":[
        "alternative"
    ],
    "wof:name":"Bragg Doug",
    "wof:placetype":"venue"
},
  "geometry": {"coordinates":[144.97817993199999,-37.7989387512],"type":"Point"}
}