{
  "type": "Feature",
  "properties": {
    "addr:full":"Shop 9 35 Palmerston Drv Innisfail QLD 4860",
    "addr:housenumber":"shop;35",
    "addr:postcode":"4860",
    "addr:street":"Palmerston Drv",
    "iso:country":"AU",
    "sg:address":"Shop 9 35 Palmerston Drv",
    "sg:city":"Innisfail",
    "sg:classifiers":[
        {
            "category":"Professional",
            "subcategory":"Engineering",
            "type":"Services"
        }
    ],
    "sg:phone":"+61 7 4061 8200",
    "sg:postcode":"4860",
    "sg:province":"QLD",
    "sg:tags":[
        "engineer"
    ],
    "wof:name":"Anderson Engineering (NQ) Pty Ltd",
    "wof:placetype":"venue"
},
  "geometry": {"coordinates":[146.01091003400001,-17.5208435059],"type":"Point"}
}