{
  "type": "Feature",
  "properties": {
    "addr:full":"98 Joffre St Wynnum QLD 4178",
    "addr:housenumber":"98",
    "addr:postcode":"4178",
    "addr:street":"Joffre St",
    "iso:country":"AU",
    "sg:address":"98 Joffre St",
    "sg:city":"Wynnum",
    "sg:classifiers":[
        {
            "category":"Building & Trades",
            "subcategory":"Construction",
            "type":"Services"
        }
    ],
    "sg:phone":"+61 7 3348 2905",
    "sg:postcode":"4178",
    "sg:province":"QLD",
    "sg:tags":[
        "concrete",
        "contractor"
    ],
    "wof:name":"Castner Concreting",
    "wof:placetype":"venue"
},
  "geometry": {"coordinates":[153.156341553,-27.4388141632],"type":"Point"}
}