{
  "type": "Feature",
  "properties": {
    "addr:full":"PO Box 304 Katherine NT 0850",
    "addr:postcode":"nt 0850",
    "iso:country":"AU",
    "sg:address":"PO Box 304",
    "sg:city":"Katherine",
    "sg:classifiers":[
        {
            "category":"Education",
            "subcategory":"Junior College",
            "type":"Public Place"
        }
    ],
    "sg:phone":"+61 8 8932 9888",
    "sg:postcode":"0850",
    "sg:province":"NT",
    "sg:tags":[
        "business"
    ],
    "wof:name":"Able (NT Division)",
    "wof:placetype":"venue"
},
  "geometry": {"coordinates":[132.317215,-14.40013],"type":"Point"}
}