{
  "type": "Feature",
  "properties": {
    "addr:full":"Level 1/ Cnr Brisbane & Bultje Sts Dubbo NSW 2830",
    "addr:housenumber":"/ cnr",
    "addr:postcode":"2830",
    "iso:country":"AU",
    "sg:address":"Level 1/ Cnr Brisbane & Bultje Sts",
    "sg:city":"Dubbo",
    "sg:classifiers":[
        {
            "category":"Professional",
            "subcategory":"Accounting & Tax Preparation",
            "type":"Services"
        }
    ],
    "sg:phone":"+61 2 6884 9154",
    "sg:postcode":"2830",
    "sg:province":"NSW",
    "sg:tags":[
        "accountant",
        "auditor"
    ],
    "sg:website":"http://www.scolaricomerford.com.au",
    "wof:name":"Scolari Comerford Chartered Accountants",
    "wof:placetype":"venue"
},
  "geometry": {"coordinates":[148.60307312,-32.2512397766],"type":"Point"}
}