{
  "type": "Feature",
  "properties": {
    "iso:country":"AU",
    "sg:address":"Nicolle Drv",
    "sg:city":"Morphett Vale",
    "sg:classifiers":[
        {
            "category":"Real Estate",
            "subcategory":"Real Estate Operator",
            "type":"Services"
        }
    ],
    "sg:phone":"+61 414 411 537",
    "sg:postcode":"5162",
    "sg:province":"SA",
    "sg:tags":[
        "concrete",
        "pumping"
    ],
    "wof:name":"Network Concrete Pumps",
    "wof:placetype":"venue"
},
  "geometry": {"coordinates":[138.52442932100001,-35.1262016296],"type":"Point"}
}