{
  "type": "Feature",
  "properties": {
    "iso:country":"AU",
    "sg:address":"Cnr Brady Way & Valencia St",
    "sg:city":"Leeton",
    "sg:classifiers":[
        {
            "category":"Building & Trades",
            "subcategory":"Construction",
            "type":"Services"
        }
    ],
    "sg:phone":"+61 2 6953 8800",
    "sg:postcode":"2705",
    "sg:province":"NSW",
    "sg:tags":[
        "welding"
    ],
    "wof:name":"Mark Lehman Fabrication",
    "wof:placetype":"venue"
},
  "geometry": {"coordinates":[146.39291381800001,-34.5537643433],"type":"Point"}
}