{
  "type": "Feature",
  "properties": {
    "addr:full":"Carlyle St Slacks Creek QLD 4127",
    "addr:postcode":"4127",
    "addr:street":"Carlyle St",
    "iso:country":"AU",
    "sg:address":"Carlyle St",
    "sg:city":"Slacks Creek",
    "sg:classifiers":[
        {
            "category":"Retail",
            "subcategory":"Auto Repair",
            "type":"Services"
        }
    ],
    "sg:phone":"+61 7 3209 5811",
    "sg:postcode":"4127",
    "sg:province":"QLD",
    "sg:tags":[
        "body",
        "builder",
        "motor"
    ],
    "wof:name":"O'Donnell Body Works",
    "wof:placetype":"venue"
},
  "geometry": {"coordinates":[153.13023376500001,-27.632188797],"type":"Point"}
}