{
  "type": "Feature",
  "properties": {
    "addr:full":"35 Gray St Mt Gambier SA 5290",
    "addr:housenumber":"35",
    "addr:postcode":"5290",
    "addr:street":"Gray St",
    "iso:country":"AU",
    "sg:address":"35 Gray St",
    "sg:city":"Mt Gambier",
    "sg:classifiers":[
        {
            "category":"Personal",
            "subcategory":"Beauty Salon",
            "type":"Services"
        }
    ],
    "sg:phone":"+61 8 8724 8777",
    "sg:postcode":"5290",
    "sg:province":"SA",
    "wof:name":"Passion 4 Beauty",
    "wof:placetype":"venue"
},
  "geometry": {"coordinates":[140.778198,-37.828243],"type":"Point"}
}