{
  "type": "Feature",
  "properties": {
    "addr:full":"350 Redbank Rd Wauchope NSW 2446",
    "addr:housenumber":"350",
    "addr:postcode":"2446",
    "addr:street":"Redbank Rd",
    "iso:country":"AU",
    "sg:address":"350 Redbank Rd",
    "sg:city":"Wauchope",
    "sg:classifiers":[
        {
            "category":"Professional",
            "subcategory":"Computer Services",
            "type":"Services"
        }
    ],
    "sg:phone":"+61 2 6516 0169",
    "sg:postcode":"2446",
    "sg:province":"NSW",
    "sg:tags":[
        "repairs",
        "upgrade",
        "equipment"
    ],
    "wof:name":"Active Computer Care",
    "wof:placetype":"venue"
},
  "geometry": {"coordinates":[152.71417199999999,-31.426285],"type":"Point"}
}