{
  "type": "Feature",
  "properties": {
    "addr:full":"Shop 6/ 650a Pittwater Rd Brookvale NSW 2100",
    "addr:housenumber":"shop 6 / 650a",
    "addr:postcode":"2100",
    "addr:street":"Pittwater Rd",
    "iso:country":"AU",
    "sg:address":"Shop 6/ 650a Pittwater Rd",
    "sg:city":"Brookvale",
    "sg:classifiers":[
        {
            "category":"Personal",
            "subcategory":"Barber",
            "type":"Services"
        }
    ],
    "sg:phone":"+61 2 9905 0504",
    "sg:postcode":"2100",
    "sg:province":"NSW",
    "wof:name":"Frank's Barber Shop",
    "wof:placetype":"venue"
},
  "geometry": {"coordinates":[151.27076721200001,-33.7649765015],"type":"Point"}
}