{
  "type": "Feature",
  "properties": {
    "addr:full":"Shop 65 Rundle Mall Adelaide SA 5000",
    "addr:housenumber":"shop 65",
    "addr:postcode":"5000",
    "addr:street":"Rundle Mall",
    "iso:country":"AU",
    "sg:address":"Shop 65 Rundle Mall",
    "sg:city":"Adelaide",
    "sg:classifiers":[
        {
            "category":"Shopping",
            "subcategory":"Mobile Phones",
            "type":"Retail Goods"
        }
    ],
    "sg:phone":"+61 8 8223 4581",
    "sg:postcode":"5000",
    "sg:province":"SA",
    "sg:tags":[
        "telephone",
        "accessory"
    ],
    "wof:name":"Vodafone Rundle Mall",
    "wof:placetype":"venue"
},
  "geometry": {"coordinates":[138.60206604000001,-34.9227256775],"type":"Point"}
}