{
  "type": "Feature",
  "properties": {
    "iso:country":"AU",
    "sg:address":"Hooka Creek Rd",
    "sg:city":"Berkeley",
    "sg:classifiers":[
        {
            "category":"Sports & Exercise",
            "subcategory":"Sports Center",
            "type":"Entertainment"
        }
    ],
    "sg:phone":"+61 2 4272 4342",
    "sg:postcode":"2506",
    "sg:province":"NSW",
    "sg:tags":[
        "ground"
    ],
    "wof:name":"Netball - Illawarra Dist. Asscn.",
    "wof:placetype":"venue"
},
  "geometry": {"coordinates":[150.834503,-34.474911],"type":"Point"}
}