{
  "type": "Feature",
  "properties": {
    "addr:full":"89 Lorne St Junee NSW 2663",
    "addr:housenumber":"89",
    "addr:postcode":"2663",
    "addr:street":"Lorne St",
    "iso:country":"AU",
    "sg:address":"89 Lorne St",
    "sg:city":"Junee",
    "sg:classifiers":[
        {
            "category":"Shopping",
            "subcategory":"Jewelry",
            "type":"Retail Goods"
        }
    ],
    "sg:phone":"+61 2 6924 1986",
    "sg:postcode":"2663",
    "sg:province":"NSW",
    "sg:tags":[
        "jeweller"
    ],
    "wof:name":"Layton's Timepiece Jewellers",
    "wof:placetype":"venue"
},
  "geometry": {"coordinates":[147.58486938499999,-34.8708877563],"type":"Point"}
}