{
  "type": "Feature",
  "properties": {
    "iso:country":"AU",
    "sg:address":"Cnr Napier Tce & Carnarvon St",
    "sg:city":"Broome",
    "sg:classifiers":[
        {
            "category":"Retail",
            "subcategory":"Storage",
            "type":"Services"
        }
    ],
    "sg:phone":"+61 8 9192 2000",
    "sg:postcode":"6725",
    "sg:province":"WA",
    "wof:name":"Pearl Coast Self Storage",
    "wof:placetype":"venue"
},
  "geometry": {"coordinates":[122.24107360799999,-17.9619598389],"type":"Point"}
}