{
  "type": "Feature",
  "properties": {
    "iso:country":"AU",
    "sg:address":"71 Downard St",
    "sg:city":"Calwell",
    "sg:classifiers":[
        {
            "category":"Personal",
            "subcategory":"Massage",
            "type":"Services"
        }
    ],
    "sg:phone":"+61 2 6291 6287",
    "sg:postcode":"2905",
    "sg:province":"ACT",
    "sg:tags":[
        "therapy"
    ],
    "wof:name":"Geering Pam",
    "wof:placetype":"venue"
},
  "geometry": {"coordinates":[149.10740661599999,-35.4382743835],"type":"Point"}
}