{
  "type": "Feature",
  "properties": {
    "iso:country":"AU",
    "sg:address":"372 Beranghi Rd",
    "sg:city":"Crescent Head",
    "sg:classifiers":[
        {
            "category":"Manufacturing",
            "subcategory":"Glass & Minerals",
            "type":"Manufacturing & Wholesale Goods"
        }
    ],
    "sg:phone":"+61 2 6566 0918",
    "sg:postcode":"2440",
    "sg:province":"NSW",
    "sg:tags":[
        "repair",
        "fibreglass",
        "product"
    ],
    "wof:name":"P.J. & R.M Callaghan",
    "wof:placetype":"venue"
},
  "geometry": {"coordinates":[152.910583,-31.177155],"type":"Point"}
}