{
  "type": "Feature",
  "properties": {
    "addr:full":"Shop 6/6, Angophara St Warabrook Shopping Cntr Warabrook NSW 2304",
    "addr:housenumber":"shop 6 / 6",
    "addr:postcode":"2304",
    "addr:street":"Angophara St;Shopping",
    "iso:country":"AU",
    "sg:address":"Shop 6/6, Angophara St",
    "sg:city":"Warabrook Shopping Cntr Warabrook",
    "sg:classifiers":[
        {
            "category":"Personal",
            "subcategory":"Nail Salon",
            "type":"Services"
        }
    ],
    "sg:phone":"+61 2 4960 0500",
    "sg:postcode":"2304",
    "sg:province":"NSW",
    "sg:tags":[
        "artificial"
    ],
    "wof:name":"Divine Hair & Body Works",
    "wof:placetype":"venue"
},
  "geometry": {"coordinates":[151.71446227999999,-32.8858909607],"type":"Point"}
}