{
  "type": "Feature",
  "properties": {
    "addr:full":"Cnr Nepean Hwy & Wooralla Drv Mt Eliza VIC 3930",
    "addr:postcode":"3930",
    "addr:street":"Cnr Nepean Hwy & Wooralla Drv",
    "iso:country":"AU",
    "sg:address":"Cnr Nepean Hwy & Wooralla Drv",
    "sg:city":"Mt Eliza",
    "sg:classifiers":[
        {
            "category":"Social Services",
            "subcategory":"Child Care",
            "type":"Services"
        }
    ],
    "sg:phone":"+61 3 9788 7777",
    "sg:postcode":"3930",
    "sg:province":"VIC",
    "wof:name":"Peninsula School The",
    "wof:placetype":"venue"
},
  "geometry": {"coordinates":[145.093841553,-38.1933784485],"type":"Point"}
}