{
  "type": "Feature",
  "properties": {
    "addr:full":"47 Great Ocean Rd Lorne VIC 3232",
    "addr:housenumber":"47",
    "addr:postcode":"3232",
    "addr:street":"Great Ocean Rd",
    "iso:country":"AU",
    "sg:address":"47 Great Ocean Rd",
    "sg:city":"Lorne",
    "sg:classifiers":[
        {
            "category":"Building & Trades",
            "subcategory":"Construction",
            "type":"Services"
        }
    ],
    "sg:phone":"+61 3 5289 1624",
    "sg:postcode":"3232",
    "sg:province":"VIC",
    "sg:tags":[
        "contractor"
    ],
    "wof:name":"Meredith C J",
    "wof:placetype":"venue"
},
  "geometry": {"coordinates":[143.98022499999999,-38.530563],"type":"Point"}
}