{
  "type": "Feature",
  "properties": {
    "addr:full":"Suite 3 1 Zwerner Drv Hallett Cove SA 5158",
    "addr:housenumber":"1",
    "addr:postcode":"5158",
    "addr:street":"Zwerner Drv",
    "iso:country":"AU",
    "sg:address":"Suite 3 1 Zwerner Drv",
    "sg:city":"Hallett Cove",
    "sg:classifiers":[
        {
            "category":"Health Services",
            "subcategory":"Doctor",
            "type":"Services"
        }
    ],
    "sg:phone":"+61 8 8387 0088",
    "sg:postcode":"5158",
    "sg:province":"SA",
    "sg:tags":[
        "medical",
        "practitioner"
    ],
    "wof:name":"Hallett Cove Family Practice",
    "wof:placetype":"venue"
},
  "geometry": {"coordinates":[138.516067505,-35.0766105652],"type":"Point"}
}