{
  "type": "Feature",
  "properties": {
    "addr:full":"33 Machinery Drv Tweed Heads NSW 2485",
    "addr:postcode":"2485",
    "addr:street":"Machinery Drv",
    "iso:country":"AU",
    "sg:address":"33 Machinery Drv",
    "sg:city":"Tweed Heads",
    "sg:classifiers":[
        {
            "category":"Education",
            "subcategory":"Special Training",
            "type":"Public Place"
        }
    ],
    "sg:phone":"+61 7 5524 3683",
    "sg:postcode":"2485",
    "sg:province":"NSW",
    "sg:tags":[
        "diving",
        "school",
        "scuba"
    ],
    "wof:name":"Tweed Sea Sports",
    "wof:placetype":"venue"
},
  "geometry": {"coordinates":[153.54293823200001,-28.2043075562],"type":"Point"}
}