{
  "type": "Feature",
  "properties": {
    "addr:full":"50 St Georges Rd Shepparton VIC 3630",
    "addr:housenumber":"50",
    "addr:postcode":"3630",
    "addr:street":"St Georges Rd",
    "iso:country":"AU",
    "sg:address":"50 St Georges Rd",
    "sg:city":"Shepparton",
    "sg:classifiers":[
        {
            "category":"Building & Trades",
            "subcategory":"Construction",
            "type":"Services"
        }
    ],
    "sg:phone":"+61 3 5822 1772",
    "sg:postcode":"3630",
    "sg:province":"VIC",
    "sg:tags":[
        "concrete",
        "contractor"
    ],
    "wof:name":"Goulburn Valley Decorative Concrete Resurfacing",
    "wof:placetype":"venue"
},
  "geometry": {"coordinates":[145.40716552699999,-36.3858757019],"type":"Point"}
}