{
  "type": "Feature",
  "properties": {
    "iso:country":"AU",
    "sg:address":"Shop 5,102- 108 Toorak Rd",
    "sg:city":"South Yarra",
    "sg:classifiers":[
        {
            "category":"Health Services",
            "subcategory":"Doctor",
            "type":"Services"
        }
    ],
    "sg:phone":"+61 3 9820 1144",
    "sg:postcode":"3141",
    "sg:province":"VIC",
    "sg:tags":[
        "medical",
        "practitioner"
    ],
    "wof:name":"Upjohn John W McK",
    "wof:placetype":"venue"
},
  "geometry": {"coordinates":[144.989624023,-37.838848114],"type":"Point"}
}