{
  "type": "Feature",
  "properties": {
    "iso:country":"AU",
    "sg:address":"Shop 2/ 17 James St",
    "sg:city":"Yeppoon",
    "sg:classifiers":[
        {
            "category":"Retail",
            "subcategory":"Funeral Services",
            "type":"Services"
        }
    ],
    "sg:phone":"+61 7 4939 4055",
    "sg:postcode":"4703",
    "sg:province":"QLD",
    "sg:tags":[
        "director"
    ],
    "wof:name":"Yeppoon-Emu Park Funerals",
    "wof:placetype":"venue"
},
  "geometry": {"coordinates":[150.74066162099999,-23.1296424866],"type":"Point"}
}