{
  "type": "Feature",
  "properties": {
    "iso:country":"AU",
    "sg:address":"250 Flinders La",
    "sg:city":"Melbourne",
    "sg:classifiers":[
        {
            "category":"Fast Food",
            "type":"Food & Drink"
        }
    ],
    "sg:phone":"+61 3 9662 2861",
    "sg:postcode":"3000",
    "sg:province":"VIC",
    "sg:tags":[
        "away",
        "take"
    ],
    "wof:name":"Shuji Sushi",
    "wof:placetype":"venue"
},
  "geometry": {"coordinates":[144.96572875999999,-37.8167152405],"type":"Point"}
}