{
  "type": "Feature",
  "properties": {
    "iso:country":"AU",
    "sg:address":"113 Paterson St",
    "sg:city":"Byron Bay",
    "sg:classifiers":[
        {
            "category":"Coffee & Tea",
            "type":"Food & Drink"
        }
    ],
    "sg:phone":"+61 2 6685 5830",
    "sg:postcode":"2481",
    "sg:province":"NSW",
    "sg:tags":[
        "kayak",
        "canoe"
    ],
    "wof:name":"Byron Bay Sea Kayaks",
    "wof:placetype":"venue"
},
  "geometry": {"coordinates":[153.62109375,-28.651506424],"type":"Point"}
}