{
  "type": "Feature",
  "properties": {
    "iso:country":"AU",
    "sg:address":"70 Mountain View Rd",
    "sg:city":"Mt Eliza",
    "sg:classifiers":[
        {
            "category":"Food & Beverages",
            "subcategory":"Groceries & Convenience Stores",
            "type":"Retail Goods"
        }
    ],
    "sg:phone":"+61 3 9787 9754",
    "sg:postcode":"3930",
    "sg:province":"VIC",
    "wof:name":"Mountain View General Store",
    "wof:placetype":"venue"
},
  "geometry": {"coordinates":[145.099365234,-38.2044296265],"type":"Point"}
}