{
  "type": "Feature",
  "properties": {
    "addr:full":"4 Sturt Pl Padbury WA 6025",
    "addr:housenumber":"4",
    "addr:postcode":"6025",
    "addr:street":"Sturt Pl",
    "iso:country":"AU",
    "sg:address":"4 Sturt Pl",
    "sg:city":"Padbury",
    "sg:classifiers":[
        {
            "category":"Shopping",
            "subcategory":"Pets & Pet Supplies",
            "type":"Retail Goods"
        }
    ],
    "sg:phone":"+61 8 9401 1929",
    "sg:postcode":"6025",
    "sg:province":"WA",
    "sg:tags":[
        "dog"
    ],
    "wof:name":"ABC Dog Training & Supplies",
    "wof:placetype":"venue"
},
  "geometry": {"coordinates":[115.760787964,-31.8091430664],"type":"Point"}
}