{
  "type": "Feature",
  "properties": {
    "addr:full":"22 Kilne Pl McDowall QLD 4053",
    "addr:housenumber":"22",
    "addr:postcode":"4053",
    "addr:street":"Kilne Pl",
    "iso:country":"AU",
    "sg:address":"22 Kilne Pl",
    "sg:city":"McDowall",
    "sg:classifiers":[
        {
            "category":"Banks & Credit Unions",
            "subcategory":"Investment Brokerage",
            "type":"Services"
        }
    ],
    "sg:phone":"+61 7 3353 9966",
    "sg:postcode":"4053",
    "sg:province":"QLD",
    "wof:name":"Godfrey Pembroke Financial Consultants",
    "wof:placetype":"venue"
},
  "geometry": {"coordinates":[152.99285888700001,-27.3783397675],"type":"Point"}
}