{
  "type": "Feature",
  "properties": {
    "addr:full":"PO Box 539 Hoxton Park NSW 2171",
    "addr:postcode":"2171",
    "iso:country":"AU",
    "sg:address":"PO Box 539",
    "sg:city":"Hoxton Park",
    "sg:classifiers":[
        {
            "category":"Autos & Motor Vehicles",
            "subcategory":"Auto Supplies",
            "type":"Retail Goods"
        }
    ],
    "sg:phone":"+61 418 862 844",
    "sg:postcode":"2171",
    "sg:province":"NSW",
    "sg:tags":[
        "automotive",
        "stereo",
        "radio"
    ],
    "wof:name":"Unlimited Sounds Mobile Installations",
    "wof:placetype":"venue"
},
  "geometry": {"coordinates":[150.84803772000001,-33.9280090332],"type":"Point"}
}