{
  "type": "Feature",
  "properties": {
    "addr:full":"3/ 10 Beerburrum St Dicky Beach QLD 4551",
    "addr:housenumber":"/ 10",
    "addr:postcode":"4551",
    "addr:street":"Beerburrum St",
    "iso:country":"AU",
    "sg:address":"3/ 10 Beerburrum St",
    "sg:city":"Dicky Beach",
    "sg:classifiers":[
        {
            "category":"Fast Food",
            "type":"Food & Drink"
        }
    ],
    "sg:phone":"+61 7 5491 2682",
    "sg:postcode":"4551",
    "sg:province":"QLD",
    "sg:tags":[
        "away",
        "take"
    ],
    "wof:name":"Dicky Beach Takeaway",
    "wof:placetype":"venue"
},
  "geometry": {"coordinates":[153.137939453,-26.7835388184],"type":"Point"}
}