{
  "type": "Feature",
  "properties": {
    "addr:full":"18 Stone St Ingham QLD 4850",
    "addr:housenumber":"18",
    "addr:postcode":"4850",
    "addr:street":"Stone St",
    "iso:country":"AU",
    "sg:address":"18 Stone St",
    "sg:city":"Ingham",
    "sg:classifiers":[
        {
            "category":"Building & Trades",
            "subcategory":"Locksmith",
            "type":"Services"
        }
    ],
    "sg:phone":"+61 7 4776 3807",
    "sg:postcode":"4850",
    "sg:province":"QLD",
    "sg:tags":[
        "lock"
    ],
    "wof:name":"Ingham Locksmiths & Security",
    "wof:placetype":"venue"
},
  "geometry": {"coordinates":[146.168823242,-18.6461486816],"type":"Point"}
}