{
  "type": "Feature",
  "properties": {
    "addr:full":"The Moroccan Centre, Shop 3/9- 11 Elkhorn Ave Surfers Paradise QLD 4217",
    "addr:housenumber":"shop 3 / 9 11",
    "addr:postcode":"4217",
    "addr:street":"Elkhorn Ave",
    "iso:country":"AU",
    "sg:address":"The Moroccan Centre, Shop 3/9- 11 Elkhorn Ave",
    "sg:city":"Surfers Paradise",
    "sg:classifiers":[
        {
            "category":"Shopping",
            "subcategory":"Jewelry",
            "type":"Retail Goods"
        }
    ],
    "sg:phone":"+61 7 5592 3744",
    "sg:postcode":"4217",
    "sg:province":"QLD",
    "sg:tags":[
        "jeweller"
    ],
    "wof:name":"Cartier",
    "wof:placetype":"venue"
},
  "geometry": {"coordinates":[153.4296875,-27.9989070892],"type":"Point"}
}