{
  "type": "Feature",
  "properties": {
    "addr:full":"65 Munibung Rd Cardiff NSW 2285",
    "addr:housenumber":"65",
    "addr:postcode":"2285",
    "addr:street":"Munibung Rd",
    "iso:country":"AU",
    "sg:address":"65 Munibung Rd",
    "sg:city":"Cardiff",
    "sg:classifiers":[
        {
            "category":"Building & Trades",
            "subcategory":"Construction",
            "type":"Services"
        }
    ],
    "sg:phone":"+61 2 4954 5596",
    "sg:postcode":"2285",
    "sg:province":"NSW",
    "sg:tags":[
        "home",
        "air conditioning"
    ],
    "wof:name":"The Vent Man",
    "wof:placetype":"venue"
},
  "geometry": {"coordinates":[151.641815186,-32.9428863525],"type":"Point"}
}