{
  "type": "Feature",
  "properties": {
    "iso:country":"AU",
    "sg:address":"51 Kylie Crs",
    "sg:city":"Batemans Bay",
    "sg:classifiers":[
        {
            "category":"Retail",
            "subcategory":"Auto Rental",
            "type":"Services"
        }
    ],
    "sg:phone":"+61 2 4472 8546",
    "sg:postcode":"2536",
    "sg:province":"NSW",
    "sg:tags":[
        "car",
        "armoured"
    ],
    "wof:name":"Armaguard",
    "wof:placetype":"venue"
},
  "geometry": {"coordinates":[150.17732238799999,-35.7084007263],"type":"Point"}
}