{
  "type": "Feature",
  "properties": {
    "addr:full":"2819 Point Nepean Rd Blairgowrie VIC 3942",
    "addr:housenumber":"2819",
    "addr:postcode":"3942",
    "addr:street":"Point Nepean Rd",
    "iso:country":"AU",
    "sg:address":"2819 Point Nepean Rd",
    "sg:city":"Blairgowrie",
    "sg:classifiers":[
        {
            "category":"Real Estate",
            "subcategory":"Real Estate Agent",
            "type":"Services"
        }
    ],
    "sg:phone":"+61 3 5988 9095",
    "sg:postcode":"3942",
    "sg:province":"VIC",
    "wof:name":"Hocking Stuart",
    "wof:placetype":"venue"
},
  "geometry": {"coordinates":[144.78021240199999,-38.3615570068],"type":"Point"}
}