{
  "type": "Feature",
  "properties": {
    "addr:full":"Ste 1/ 2 Charnwood Crs St Kilda VIC 3182",
    "addr:housenumber":"2",
    "addr:postcode":"3182",
    "addr:street":"Charnwood Crs",
    "iso:country":"AU",
    "sg:address":"Ste 1/ 2 Charnwood Crs",
    "sg:city":"St Kilda",
    "sg:classifiers":[
        {
            "category":"Health Services",
            "subcategory":"Health Practitioner",
            "type":"Services"
        }
    ],
    "sg:phone":"+61 3 9537 3018",
    "sg:postcode":"3182",
    "sg:province":"VIC",
    "sg:tags":[
        "psychologist"
    ],
    "wof:name":"Wesley Johnson Psychological Services",
    "wof:placetype":"venue"
},
  "geometry": {"coordinates":[144.984573364,-37.8586654663],"type":"Point"}
}