{
  "type": "Feature",
  "properties": {
    "addr:full":"132 Manning St Kiama NSW 2533",
    "addr:housenumber":"132",
    "addr:postcode":"2533",
    "addr:street":"Manning St",
    "iso:country":"AU",
    "sg:address":"132 Manning St",
    "sg:city":"Kiama",
    "sg:classifiers":[
        {
            "category":"Travel",
            "subcategory":"Hotels & Motels",
            "type":"Entertainment"
        }
    ],
    "sg:phone":"+61 2 4232 1333",
    "sg:postcode":"2533",
    "sg:province":"NSW",
    "wof:name":"Motel 617",
    "wof:placetype":"venue"
},
  "geometry": {"coordinates":[150.85067749000001,-34.6786117554],"type":"Point"}
}