{
  "type": "Feature",
  "properties": {
    "addr:full":"20 Daking St North Parramatta NSW 2151",
    "addr:housenumber":"20",
    "addr:postcode":"2151",
    "addr:street":"Daking St",
    "iso:country":"AU",
    "sg:address":"20 Daking St",
    "sg:city":"North Parramatta",
    "sg:classifiers":[
        {
            "category":"Retail",
            "subcategory":"Auto Repair",
            "type":"Services"
        }
    ],
    "sg:phone":"+61 2 9683 1855",
    "sg:postcode":"2151",
    "sg:province":"NSW",
    "sg:tags":[
        "electrical"
    ],
    "wof:name":"Romac Electrical Service",
    "wof:placetype":"venue"
},
  "geometry": {"coordinates":[151.001296997,-33.7945289612],"type":"Point"}
}