{
  "type": "Feature",
  "properties": {
    "iso:country":"AU",
    "sg:address":"Old Princes Hwy",
    "sg:city":"Tomerong",
    "sg:classifiers":[
        {
            "category":"Education",
            "subcategory":"Special Training",
            "type":"Public Place"
        }
    ],
    "sg:phone":"+61 2 4443 4853",
    "sg:postcode":"2540",
    "sg:province":"NSW",
    "sg:tags":[
        "development"
    ],
    "wof:name":"Midline Contracting Pty Ltd",
    "wof:placetype":"venue"
},
  "geometry": {"coordinates":[150.57867431599999,-35.0272216797],"type":"Point"}
}