{
  "type": "Feature",
  "properties": {
    "addr:full":"Factory 2, 23 Turbo Drv Bayswater VIC 3153",
    "addr:housenumber":"23",
    "addr:postcode":"3153",
    "addr:street":"Turbo Drv",
    "iso:country":"AU",
    "sg:address":"Factory 2, 23 Turbo Drv",
    "sg:city":"Bayswater",
    "sg:classifiers":[
        {
            "category":"Manufacturing",
            "subcategory":"Rubber & Plastics",
            "type":"Manufacturing & Wholesale Goods"
        }
    ],
    "sg:phone":"+61 3 9729 2753",
    "sg:postcode":"3153",
    "sg:province":"VIC",
    "sg:tags":[
        "moulders"
    ],
    "wof:name":"Satellite Tooling & Plastics Co. Pty Ltd",
    "wof:placetype":"venue"
},
  "geometry": {"coordinates":[145.275878906,-37.8253746033],"type":"Point"}
}