{
  "type": "Feature",
  "properties": {
    "addr:full":"229 Sydney Rd Coburg VIC 3058",
    "addr:housenumber":"229",
    "addr:postcode":"3058",
    "addr:street":"Sydney Rd",
    "iso:country":"AU",
    "sg:address":"229 Sydney Rd",
    "sg:city":"Coburg",
    "sg:classifiers":[
        {
            "category":"Manufacturing",
            "subcategory":"Tools & Machinery",
            "type":"Manufacturing & Wholesale Goods"
        }
    ],
    "sg:phone":"+61 3 9386 6322",
    "sg:postcode":"3058",
    "sg:province":"VIC",
    "sg:tags":[
        "wholesaler",
        "lingerie",
        "mfrs",
        "sleepwear"
    ],
    "wof:name":"STYLESHOP.com.au",
    "wof:placetype":"venue"
},
  "geometry": {"coordinates":[144.965118408,-37.7487716675],"type":"Point"}
}