{
  "type": "Feature",
  "properties": {
    "addr:full":"254 Hawthorne Rd Hawthorne QLD 4171",
    "addr:housenumber":"254",
    "addr:postcode":"4171",
    "addr:street":"Hawthorne Rd",
    "iso:country":"AU",
    "sg:address":"254 Hawthorne Rd",
    "sg:city":"Hawthorne",
    "sg:classifiers":[
        {
            "category":"Fast Food",
            "type":"Food & Drink"
        }
    ],
    "sg:phone":"+61 7 3399 6614",
    "sg:postcode":"4171",
    "sg:province":"QLD",
    "sg:tags":[
        "away",
        "take"
    ],
    "wof:name":"Hawthorne Seafoods",
    "wof:placetype":"venue"
},
  "geometry": {"coordinates":[153.060058594,-27.4628925323],"type":"Point"}
}