{
  "type": "Feature",
  "properties": {
    "addr:full":"Shop 21 Broadway Fair 88 Broadway Nedlands WA 6009",
    "addr:housenumber":"shop 21;88",
    "addr:postcode":"6009",
    "addr:street":"Broadway Fair;Broadway",
    "iso:country":"AU",
    "sg:address":"Shop 21 Broadway Fair 88",
    "sg:city":"Broadway Nedlands",
    "sg:classifiers":[
        {
            "category":"Personal",
            "subcategory":"Beauty Salon",
            "type":"Services"
        }
    ],
    "sg:phone":"+61 8 9386 6320",
    "sg:postcode":"6009",
    "sg:province":"WA",
    "sg:tags":[
        "hairdresser"
    ],
    "wof:name":"Anne Of Hans Salon",
    "wof:placetype":"venue"
},
  "geometry": {"coordinates":[115.813911,-31.978003],"type":"Point"}
}