{
  "type": "Feature",
  "properties": {
    "addr:full":"Goldfield Rd York WA 6302",
    "addr:postcode":"6302",
    "addr:street":"Goldfield Rd",
    "iso:country":"AU",
    "sg:address":"Goldfield Rd",
    "sg:city":"York",
    "sg:classifiers":[
        {
            "category":"Home & Garden",
            "subcategory":"Carpets & Floor Coverings",
            "type":"Retail Goods"
        }
    ],
    "sg:phone":"+61 408 908 795",
    "sg:postcode":"6302",
    "sg:province":"WA",
    "sg:tags":[
        "tile",
        "wall"
    ],
    "wof:name":"Ashford Tiling Services",
    "wof:placetype":"venue"
},
  "geometry": {"coordinates":[116.820701599,-31.8583316803],"type":"Point"}
}