{
  "type": "Feature",
  "properties": {
    "addr:full":"611 Stanley St Woolloongabba QLD 4102",
    "addr:housenumber":"611",
    "addr:postcode":"4102",
    "addr:street":"Stanley St",
    "iso:country":"AU",
    "sg:address":"611 Stanley St",
    "sg:city":"Woolloongabba",
    "sg:classifiers":[
        {
            "category":"Deli",
            "type":"Food & Drink"
        }
    ],
    "sg:phone":"+61 7 3391 3530",
    "sg:postcode":"4102",
    "sg:province":"QLD",
    "sg:tags":[
        "delicatessen"
    ],
    "wof:name":"Heinz Butcher & Continental Smallgoods",
    "wof:placetype":"venue"
},
  "geometry": {"coordinates":[153.029418945,-27.4857368469],"type":"Point"}
}