{
  "type": "Feature",
  "properties": {
    "iso:country":"AU",
    "sg:address":"PO Box 109",
    "sg:city":"Higgins",
    "sg:classifiers":[
        {
            "category":"Professional",
            "subcategory":"Printing & Photocopies",
            "type":"Services"
        }
    ],
    "sg:phone":"+61 414 896 142",
    "sg:postcode":"2615",
    "sg:province":"ACT",
    "sg:tags":[
        "publishing",
        "desktop"
    ],
    "wof:name":"Affairs with Flair",
    "wof:placetype":"venue"
},
  "geometry": {"coordinates":[149.027511597,-35.2332687378],"type":"Point"}
}