{
  "type": "Feature",
  "properties": {
    "addr:full":"U1/ 7 Levanswell Rd Moorabbin VIC 3189",
    "addr:postcode":"3189",
    "addr:street":"U1 / 7 Levanswell Rd",
    "iso:country":"AU",
    "sg:address":"U1/ 7 Levanswell Rd",
    "sg:city":"Moorabbin",
    "sg:classifiers":[
        {
            "category":"Shopping",
            "subcategory":"Computers & Home Electronics",
            "type":"Retail Goods"
        }
    ],
    "sg:phone":"+61 3 9553 5111",
    "sg:postcode":"3189",
    "sg:province":"VIC",
    "sg:tags":[
        "equipment",
        "supply"
    ],
    "wof:name":"Resolution Computer Supplies Pty Ltd",
    "wof:placetype":"venue"
},
  "geometry": {"coordinates":[145.06198120100001,-37.9441299438],"type":"Point"}
}