{
  "type": "Feature",
  "properties": {
    "iso:country":"AU",
    "sg:address":"45 Tumut St",
    "sg:city":"Adelong",
    "sg:classifiers":[
        {
            "category":"Travel",
            "subcategory":"Hotels & Motels",
            "type":"Entertainment"
        }
    ],
    "sg:phone":"+61 2 6946 2008",
    "sg:postcode":"2729",
    "sg:province":"NSW",
    "sg:tags":[
        "accommodation"
    ],
    "wof:name":"Royal Hotel",
    "wof:placetype":"venue"
},
  "geometry": {"coordinates":[148.06546,-35.308659],"type":"Point"}
}