{
  "type": "Feature",
  "properties": {
    "iso:country":"AU",
    "sg:address":"43 Hibiscus Ave",
    "sg:city":"Gladstone",
    "sg:classifiers":[
        {
            "category":"Education",
            "subcategory":"School",
            "type":"Public Place"
        }
    ],
    "sg:phone":"+61 7 4971 5111",
    "sg:postcode":"4680",
    "sg:province":"QLD",
    "sg:tags":[
        "state",
        "except",
        "nsw"
    ],
    "wof:name":"Kin Kora Primary School",
    "wof:placetype":"venue"
},
  "geometry": {"coordinates":[151.25422668499999,-23.87748909],"type":"Point"}
}