{
  "type": "Feature",
  "properties": {
    "iso:country":"AU",
    "sg:address":"6 Elata Drv",
    "sg:city":"Tullamarine",
    "sg:classifiers":[
        {
            "category":"Retail",
            "subcategory":"Auto Repair",
            "type":"Services"
        }
    ],
    "sg:phone":"+61 3 9335 1244",
    "sg:postcode":"3043",
    "sg:province":"VIC",
    "sg:tags":[
        "muffler",
        "exhaust",
        "system"
    ],
    "wof:name":"Aero Barbecue Company",
    "wof:placetype":"venue"
},
  "geometry": {"coordinates":[144.86143493599999,-37.715297699],"type":"Point"}
}