{
  "type": "Feature",
  "properties": {
    "addr:full":"PO Box 1084 Mooloolaba QLD 4557",
    "addr:postcode":"4557",
    "iso:country":"AU",
    "sg:address":"PO Box 1084",
    "sg:city":"Mooloolaba",
    "sg:classifiers":[
        {
            "category":"Professional",
            "subcategory":"Accounting & Tax Preparation",
            "type":"Services"
        }
    ],
    "sg:phone":"+61 7 5452 6311",
    "sg:postcode":"4557",
    "sg:province":"QLD",
    "sg:tags":[
        "bookkeeping"
    ],
    "wof:name":"Mercury Business Systems",
    "wof:placetype":"venue"
},
  "geometry": {"coordinates":[153.117797852,-26.6837902069],"type":"Point"}
}