{
  "type": "Feature",
  "properties": {
    "addr:full":"Shop 3/ 44 Rose St Liverpool NSW 2170",
    "addr:housenumber":"shop 3 / 44",
    "addr:postcode":"2170",
    "addr:street":"Rose St",
    "iso:country":"AU",
    "sg:address":"Shop 3/ 44 Rose St",
    "sg:city":"Liverpool",
    "sg:classifiers":[
        {
            "category":"Personal",
            "subcategory":"Beauty Salon",
            "type":"Services"
        }
    ],
    "sg:phone":"+61 2 9601 2850",
    "sg:postcode":"2170",
    "sg:province":"NSW",
    "sg:tags":[
        "hairdresser"
    ],
    "wof:name":"Paulas Hairartiezt",
    "wof:placetype":"venue"
},
  "geometry": {"coordinates":[150.91236877399999,-33.9319419861],"type":"Point"}
}