{
  "type": "Feature",
  "properties": {
    "iso:country":"AU",
    "sg:address":"Level 3 267 St",
    "sg:city":"Georges Tce Perth",
    "sg:classifiers":[
        {
            "category":"Real Estate",
            "subcategory":"Real Estate Agent",
            "type":"Services"
        }
    ],
    "sg:phone":"+61 8 9261 7755",
    "sg:postcode":"6000",
    "sg:province":"WA",
    "wof:name":"Nicholas Masters & Associates",
    "wof:placetype":"venue"
},
  "geometry": {"coordinates":[115.849342346,-31.9524593353],"type":"Point"}
}