{
  "type": "Feature",
  "properties": {
    "iso:country":"AU",
    "sg:address":"18 Brenda St",
    "sg:city":"Ingleburn",
    "sg:classifiers":[
        {
            "category":"Utilities",
            "subcategory":"Electric",
            "type":"Services"
        }
    ],
    "sg:phone":"+61 419 296 218",
    "sg:postcode":"2565",
    "sg:province":"NSW",
    "sg:tags":[
        "electrical",
        "contractor"
    ],
    "wof:name":"Romek Kuchar Electrical",
    "wof:placetype":"venue"
},
  "geometry": {"coordinates":[150.86062622099999,-34.0051002502],"type":"Point"}
}