{
  "type": "Feature",
  "properties": {
    "addr:full":"Subiaco Oval Subiaco Rd Subiaco WA 6008",
    "addr:postcode":"6008",
    "addr:street":"Subiaco Rd",
    "iso:country":"AU",
    "sg:address":"Subiaco Oval Subiaco Rd",
    "sg:city":"Subiaco",
    "sg:classifiers":[
        {
            "category":"Arena",
            "subcategory":"Sports Club",
            "type":"Entertainment"
        }
    ],
    "sg:phone":"+61 8 9382 8333",
    "sg:postcode":"6008",
    "sg:province":"WA",
    "sg:tags":[
        "organisation",
        "sporting"
    ],
    "wof:name":"AFL Group Training Co",
    "wof:placetype":"venue"
},
  "geometry": {"coordinates":[115.829772949,-31.943567276],"type":"Point"}
}