{
  "type": "Feature",
  "properties": {
    "addr:full":"4 Norfolk St Mt Druitt NSW 2770",
    "addr:housenumber":"4",
    "addr:postcode":"2770",
    "addr:street":"Norfolk St Mt",
    "iso:country":"AU",
    "sg:address":"4 Norfolk St",
    "sg:city":"Mt Druitt",
    "sg:classifiers":[
        {
            "category":"Retail",
            "subcategory":"Repair Shop",
            "type":"Services"
        }
    ],
    "sg:phone":"+61 2 9625 4303",
    "sg:postcode":"2770",
    "sg:province":"NSW",
    "sg:tags":[
        "upholsterer"
    ],
    "wof:name":"Joe's Upholstery",
    "wof:placetype":"venue"
},
  "geometry": {"coordinates":[150.808227539,-33.768901825],"type":"Point"}
}