{
  "type": "Feature",
  "properties": {
    "iso:country":"AU",
    "sg:address":"Level 13/ 469 LaTrobe St",
    "sg:city":"Melbourne",
    "sg:classifiers":[
        {
            "category":"Professional",
            "subcategory":"Lawyer & Legal Services",
            "type":"Services"
        }
    ],
    "sg:phone":"+61 3 9321 7888",
    "sg:postcode":"3000",
    "sg:province":"VIC",
    "sg:tags":[
        "wills",
        "probate",
        "estate"
    ],
    "wof:name":"Rigby Cooke Lawyers",
    "wof:placetype":"venue"
},
  "geometry": {"coordinates":[144.955154419,-37.8122406006],"type":"Point"}
}