{
  "type": "Feature",
  "properties": {
    "iso:country":"AU",
    "sg:address":"53 Torryburn Rd",
    "sg:city":"East Gresford",
    "sg:classifiers":[
        {
            "category":"Government",
            "subcategory":"Fire Station",
            "type":"Public Place"
        }
    ],
    "sg:phone":"+61 2 4938 9713",
    "sg:postcode":"2311",
    "sg:province":"NSW",
    "sg:tags":[
        "equipment",
        "protection",
        "consultant"
    ],
    "wof:name":"Alert Fire Protection Pty Ltd",
    "wof:placetype":"venue"
},
  "geometry": {"coordinates":[151.60531616200001,-32.4622840881],"type":"Point"}
}