{
  "type": "Feature",
  "properties": {
    "iso:country":"AU",
    "sg:address":"2- 30 Blackburn St",
    "sg:city":"Kilburn",
    "sg:classifiers":[
        {
            "category":"Real Estate",
            "subcategory":"Architect",
            "type":"Services"
        }
    ],
    "sg:phone":"+61 8 8359 1111",
    "sg:postcode":"5084",
    "sg:province":"SA",
    "sg:tags":[
        "raw",
        "material",
        "plastic"
    ],
    "wof:name":"Plastics Granulating Services Pty Ltd",
    "wof:placetype":"venue"
},
  "geometry": {"coordinates":[138.58515930199999,-34.8539428711],"type":"Point"}
}