{
  "type": "Feature",
  "properties": {
    "addr:full":"183 Wangandary Rd Wangaratta VIC 3677",
    "addr:housenumber":"183",
    "addr:postcode":"3677",
    "addr:street":"Wangandary Rd",
    "iso:country":"AU",
    "sg:address":"183 Wangandary Rd",
    "sg:city":"Wangaratta",
    "sg:classifiers":[
        {
            "category":"Building & Trades",
            "subcategory":"Construction",
            "type":"Services"
        }
    ],
    "sg:phone":"+61 3 5721 7849",
    "sg:postcode":"3677",
    "sg:province":"VIC",
    "sg:tags":[
        "earth",
        "excavating",
        "moving",
        "contractor"
    ],
    "wof:name":"Bordignon R & J Pty Ltd",
    "wof:placetype":"venue"
},
  "geometry": {"coordinates":[146.29571533199999,-36.3364372253],"type":"Point"}
}