{
  "type": "Feature",
  "properties": {
    "addr:full":"Reynolds Ave Bankstown NSW 2200",
    "addr:postcode":"2200",
    "addr:street":"Reynolds Ave",
    "iso:country":"AU",
    "sg:address":"Reynolds Ave",
    "sg:city":"Bankstown",
    "sg:classifiers":[
        {
            "category":"Banks & Credit Unions",
            "subcategory":"Bureau De Change",
            "type":"Services"
        }
    ],
    "sg:phone":"+61 412 892 131",
    "sg:postcode":"2200",
    "sg:province":"NSW",
    "sg:tags":[
        "repairs",
        "part",
        "appliance",
        "electrical"
    ],
    "wof:name":"Pro-Tek Appliance Services",
    "wof:placetype":"venue"
},
  "geometry": {"coordinates":[151.02972399999999,-33.913551],"type":"Point"}
}