{
  "type": "Feature",
  "properties": {
    "addr:full":"Shop 22 Castle Plaza Shopng Cntr 992 South Rd Edwardstown SA 5039",
    "addr:housenumber":"shop 22;992",
    "addr:postcode":"5039",
    "addr:street":"Castle Plaza Shopng Cntr;South Rd",
    "iso:country":"AU",
    "sg:address":"Shop 22 Castle Plaza Shopng Cntr 992 South Rd",
    "sg:city":"Edwardstown",
    "sg:classifiers":[
        {
            "category":"Professional",
            "subcategory":"Art Services",
            "type":"Services"
        }
    ],
    "sg:phone":"+61 8 8277 6775",
    "sg:postcode":"5039",
    "sg:province":"SA",
    "sg:tags":[
        "picture",
        "frame",
        "framing"
    ],
    "wof:name":"Rabbit Photo",
    "wof:placetype":"venue"
},
  "geometry": {"coordinates":[138.573776245,-34.9808921814],"type":"Point"}
}