{
  "type": "Feature",
  "properties": {
    "iso:country":"AU",
    "sg:address":"115 Ives La",
    "sg:city":"Lindenow South",
    "sg:classifiers":[
        {
            "category":"Building & Trades",
            "subcategory":"Plumbing",
            "type":"Services"
        }
    ],
    "sg:phone":"+61 438 571 721",
    "sg:postcode":"3875",
    "sg:province":"VIC",
    "sg:tags":[
        "plumber",
        "gasfitters"
    ],
    "wof:name":"Trinder GW & FA",
    "wof:placetype":"venue"
},
  "geometry": {"coordinates":[147.458496094,-37.8341827393],"type":"Point"}
}