{
  "type": "Feature",
  "properties": {
    "addr:full":"26 Outlook Drv Camberwell VIC 3124",
    "addr:housenumber":"26",
    "addr:postcode":"3124",
    "addr:street":"Outlook Drv",
    "iso:country":"AU",
    "sg:address":"26 Outlook Drv",
    "sg:city":"Camberwell",
    "sg:classifiers":[
        {
            "category":"Professional",
            "subcategory":"Employment Agencies",
            "type":"Services"
        }
    ],
    "sg:phone":"+61 3 9889 9431",
    "sg:postcode":"3124",
    "sg:province":"VIC",
    "sg:tags":[
        "provider",
        "internet"
    ],
    "wof:name":"Our Network Solutions Pty Ltd",
    "wof:placetype":"venue"
},
  "geometry": {"coordinates":[145.091629028,-37.8475914001],"type":"Point"}
}