{
  "type": "Feature",
  "properties": {
    "addr:full":"Shop LG 36, Woden Shopng Sq Woden ACT 2606",
    "addr:housenumber":"36",
    "addr:postcode":"2606",
    "addr:street":"Woden Shopng Sq",
    "iso:country":"AU",
    "sg:address":"Shop LG 36, Woden Shopng Sq",
    "sg:city":"Woden",
    "sg:classifiers":[
        {
            "category":"Shopping",
            "subcategory":"Clothing, Apparel, & Fashions",
            "type":"Retail Goods"
        }
    ],
    "sg:phone":"+61 2 6282 2191",
    "sg:postcode":"2606",
    "sg:province":"ACT",
    "sg:tags":[
        "menswear"
    ],
    "wof:name":"Roger David",
    "wof:placetype":"venue"
},
  "geometry": {"coordinates":[149.081420898,-35.3464202881],"type":"Point"}
}