{
  "type": "Feature",
  "properties": {
    "addr:full":"Unit 2/ 242 Hume Hwy Cabramatta NSW 2166",
    "addr:housenumber":"/ 242",
    "addr:postcode":"2166",
    "addr:street":"Hume Hwy",
    "iso:country":"AU",
    "sg:address":"Unit 2/ 242 Hume Hwy",
    "sg:city":"Cabramatta",
    "sg:classifiers":[
        {
            "category":"Professional",
            "type":"Services"
        }
    ],
    "sg:phone":"+61 2 9726 5000",
    "sg:postcode":"2166",
    "sg:province":"NSW",
    "sg:tags":[
        "spray",
        "painting"
    ],
    "wof:name":"Crosscairn Spraypainting & Detailing Pty Ltd",
    "wof:placetype":"venue"
},
  "geometry": {"coordinates":[150.95213317899999,-33.897983551],"type":"Point"}
}