{
  "type": "Feature",
  "properties": {
    "iso:country":"AU",
    "sg:address":"84 River Rd",
    "sg:city":"Gympie",
    "sg:classifiers":[
        {
            "category":"Real Estate",
            "subcategory":"Real Estate Agent",
            "type":"Services"
        }
    ],
    "sg:phone":"+61 7 5482 3966",
    "sg:postcode":"4570",
    "sg:province":"QLD",
    "wof:name":"Harcourts Queensland Pty Ltd",
    "wof:placetype":"venue"
},
  "geometry": {"coordinates":[152.66419982900001,-26.1965637207],"type":"Point"}
}