{
  "type": "Feature",
  "properties": {
    "iso:country":"AU",
    "sg:address":"37 Parkland Rd",
    "sg:city":"Mona Vale",
    "sg:classifiers":[
        {
            "category":"Professional",
            "subcategory":"Art Services",
            "type":"Services"
        }
    ],
    "sg:phone":"+61 2 9999 0880",
    "sg:postcode":"2103",
    "sg:province":"NSW",
    "sg:tags":[
        "interior",
        "decorator"
    ],
    "wof:name":"Coastal Finishes",
    "wof:placetype":"venue"
},
  "geometry": {"coordinates":[151.292877197,-33.6716308594],"type":"Point"}
}