{
  "type": "Feature",
  "properties": {
    "iso:country":"AU",
    "sg:address":"Suite21/Level 11, 809- 811 Pacific Hwy",
    "sg:city":"Chatswood",
    "sg:classifiers":[
        {
            "category":"Professional",
            "subcategory":"Computer Services",
            "type":"Services"
        }
    ],
    "sg:phone":"+61 2 9411 2925",
    "sg:postcode":"2067",
    "sg:province":"NSW",
    "sg:tags":[
        "consultant",
        "system"
    ],
    "wof:name":"Acapal Pty Ltd",
    "wof:placetype":"venue"
},
  "geometry": {"coordinates":[151.17814636200001,-33.7961845398],"type":"Point"}
}