{
  "type": "Feature",
  "properties": {
    "iso:country":"AU",
    "sg:address":"11 Virginia Pl",
    "sg:city":"West Pennant Hills",
    "sg:classifiers":[
        {
            "category":"Building & Trades",
            "subcategory":"Cleaning & Sanitation",
            "type":"Services"
        }
    ],
    "sg:phone":"+61 2 9872 1287",
    "sg:postcode":"2125",
    "sg:province":"NSW",
    "sg:tags":[
        "chemical",
        "pressure",
        "steam",
        "contractor"
    ],
    "wof:name":"Francis M A Pty Ltd",
    "wof:placetype":"venue"
},
  "geometry": {"coordinates":[151.029174805,-33.7611236572],"type":"Point"}
}