{
  "type": "Feature",
  "properties": {
    "addr:full":"37 Kings Park Rd West Perth WA 6005",
    "addr:housenumber":"37",
    "addr:postcode":"6005",
    "addr:street":"Kings Park Rd",
    "iso:country":"AU",
    "sg:address":"37 Kings Park Rd",
    "sg:city":"West Perth",
    "sg:classifiers":[
        {
            "category":"Cafe",
            "type":"Food & Drink"
        }
    ],
    "sg:phone":"+61 8 9481 4990",
    "sg:postcode":"6005",
    "sg:province":"WA",
    "wof:name":"Sticky Beaks Playground Cafe",
    "wof:placetype":"venue"
},
  "geometry": {"coordinates":[115.83843231199999,-31.9519367218],"type":"Point"}
}