{
  "type": "Feature",
  "properties": {
    "addr:full":"Cnr Old Northern Rd & Quarry Rd Dural NSW 2158",
    "addr:postcode":"2158",
    "addr:street":"Cnr Old Northern Rd & Quarry Rd",
    "iso:country":"AU",
    "sg:address":"Cnr Old Northern Rd & Quarry Rd",
    "sg:city":"Dural",
    "sg:classifiers":[
        {
            "category":"Education",
            "subcategory":"Kindergarten",
            "type":"Public Place"
        }
    ],
    "sg:phone":"+61 2 9651 1942",
    "sg:postcode":"2158",
    "sg:province":"NSW",
    "sg:tags":[
        "pre-schools"
    ],
    "wof:name":"Dural Early Learning Centres",
    "wof:placetype":"venue"
},
  "geometry": {"coordinates":[151.02682495100001,-33.6774368286],"type":"Point"}
}