{
  "type": "Feature",
  "properties": {
    "addr:full":"Rix Rd Officer VIC 3809",
    "addr:postcode":"3809",
    "addr:street":"Rix Rd",
    "iso:country":"AU",
    "sg:address":"Rix Rd",
    "sg:city":"Officer",
    "sg:classifiers":[
        {
            "category":"Farming",
            "subcategory":"Nursery",
            "type":"Manufacturing & Wholesale Goods"
        }
    ],
    "sg:phone":"+61 3 5943 2515",
    "sg:postcode":"3809",
    "sg:province":"VIC",
    "wof:name":"G & T Nursery",
    "wof:placetype":"venue"
},
  "geometry": {"coordinates":[145.400711,-38.067726],"type":"Point"}
}