{
  "type": "Feature",
  "properties": {
    "addr:full":"Unit 2/ 5 Foundry St Maylands WA 6051",
    "addr:housenumber":"5",
    "addr:postcode":"6051",
    "addr:street":"Foundry St",
    "iso:country":"AU",
    "sg:address":"Unit 2/ 5 Foundry St",
    "sg:city":"Maylands",
    "sg:classifiers":[
        {
            "category":"Utilities",
            "subcategory":"Water",
            "type":"Services"
        }
    ],
    "sg:phone":"+61 8 9272 1488",
    "sg:postcode":"6051",
    "sg:province":"WA",
    "sg:tags":[
        "hot",
        "system"
    ],
    "wof:name":"Ace Plumbing & Gas",
    "wof:placetype":"venue"
},
  "geometry": {"coordinates":[115.897278,-31.928041],"type":"Point"}
}