{
  "type": "Feature",
  "properties": {
    "iso:country":"AU",
    "sg:address":"507 Barkly St",
    "sg:city":"Buninyong",
    "sg:classifiers":[
        {
            "category":"Farming",
            "subcategory":"Fish & Marine Products",
            "type":"Manufacturing & Wholesale Goods"
        }
    ],
    "sg:phone":"+61 422 016 015",
    "sg:postcode":"3357",
    "sg:province":"VIC",
    "sg:tags":[
        "asphalt",
        "supply"
    ],
    "wof:name":"Porter Earthworks",
    "wof:placetype":"venue"
},
  "geometry": {"coordinates":[143.881683,-37.644802],"type":"Point"}
}