{
  "type": "Feature",
  "properties": {
    "addr:full":"507 Barkly St Buninyong VIC 3357",
    "addr:housenumber":"507",
    "addr:postcode":"3357",
    "addr:street":"Barkly St",
    "iso:country":"AU",
    "sg:address":"507 Barkly St",
    "sg:city":"Buninyong",
    "sg:classifiers":[
        {
            "category":"Farming",
            "subcategory":"Fish & Marine Products",
            "type":"Manufacturing & Wholesale Goods"
        }
    ],
    "sg:phone":"+61 422 016 015",
    "sg:postcode":"3357",
    "sg:province":"VIC",
    "sg:tags":[
        "asphalt",
        "supply"
    ],
    "wof:name":"Porter Earthworks",
    "wof:placetype":"venue"
},
  "geometry": {"coordinates":[143.88168300000001,-37.644802],"type":"Point"}
}