{
  "type": "Feature",
  "properties": {
    "addr:full":"3 Keppel St Bathurst NSW 2795",
    "addr:housenumber":"3",
    "addr:postcode":"2795",
    "addr:street":"Keppel St",
    "iso:country":"AU",
    "sg:address":"3 Keppel St",
    "sg:city":"Bathurst",
    "sg:classifiers":[
        {
            "category":"Building & Trades",
            "subcategory":"Electrical",
            "type":"Services"
        }
    ],
    "sg:phone":"+61 2 6331 4688",
    "sg:postcode":"2795",
    "sg:province":"NSW",
    "sg:tags":[
        "repair",
        "generator",
        "electric",
        "motor"
    ],
    "wof:name":"Bathurst Rewinds",
    "wof:placetype":"venue"
},
  "geometry": {"coordinates":[149.58245849599999,-33.4246444702],"type":"Point"}
}