{
  "type": "Feature",
  "properties": {
    "iso:country":"AU",
    "sg:address":"16 Cole Bard St East",
    "sg:city":"Acacia Ridge",
    "sg:classifiers":[
        {
            "category":"Home & Garden",
            "subcategory":"Building Materials",
            "type":"Retail Goods"
        }
    ],
    "sg:phone":"+61 7 3277 9339",
    "sg:postcode":"4110",
    "sg:province":"QLD",
    "sg:tags":[
        "fitting",
        "door"
    ],
    "wof:name":"Baltic Doors Pty Ltd",
    "wof:placetype":"venue"
},
  "geometry": {"coordinates":[153.005950928,-27.5800418854],"type":"Point"}
}