{
  "type": "Feature",
  "properties": {
    "addr:full":"20 Lucca St Churchlands WA 6018",
    "addr:housenumber":"20",
    "addr:postcode":"6018",
    "addr:street":"Lucca St",
    "iso:country":"AU",
    "sg:address":"20 Lucca St",
    "sg:city":"Churchlands",
    "sg:classifiers":[
        {
            "category":"Education",
            "subcategory":"School",
            "type":"Public Place"
        }
    ],
    "sg:phone":"+61 8 9446 8200",
    "sg:postcode":"6018",
    "sg:province":"WA",
    "sg:tags":[
        "state",
        "except",
        "nsw"
    ],
    "wof:name":"Churchlands Senior High School",
    "wof:placetype":"venue"
},
  "geometry": {"coordinates":[115.787879944,-31.9168319702],"type":"Point"}
}