{
  "type": "Feature",
  "properties": {
    "iso:country":"AU",
    "sg:address":"45 Edward St",
    "sg:city":"Biggenden",
    "sg:classifiers":[
        {
            "category":"Health Services",
            "subcategory":"Doctor",
            "type":"Services"
        }
    ],
    "sg:phone":"+61 7 4127 1150",
    "sg:postcode":"4621",
    "sg:province":"QLD",
    "sg:tags":[
        "nurse",
        "nursing"
    ],
    "wof:name":"Blue Care Blue Nursing",
    "wof:placetype":"venue"
},
  "geometry": {"coordinates":[152.042892,-25.510244],"type":"Point"}
}