{
  "type": "Feature",
  "properties": {
    "iso:country":"AU",
    "sg:address":"Suite 1, 49 Primary School Crt",
    "sg:city":"Maroochydore",
    "sg:classifiers":[
        {
            "category":"Health Services",
            "subcategory":"Dentist",
            "type":"Services"
        }
    ],
    "sg:phone":"+61 7 5443 9131",
    "sg:postcode":"4558",
    "sg:province":"QLD",
    "sg:tags":[
        "qld",
        "orthodontist"
    ],
    "wof:name":"Lenz Gavin Dr",
    "wof:placetype":"venue"
},
  "geometry": {"coordinates":[153.084747314,-26.6528930664],"type":"Point"}
}