{
  "type": "Feature",
  "properties": {
    "addr:full":"Thurgoona Drv Thurgoona NSW 2640",
    "addr:postcode":"2640",
    "addr:street":"Thurgoona Drv",
    "iso:country":"AU",
    "sg:address":"Thurgoona Drv",
    "sg:city":"Thurgoona",
    "sg:classifiers":[
        {
            "category":"Sports & Exercise",
            "subcategory":"Golf",
            "type":"Entertainment"
        }
    ],
    "sg:phone":"+61 2 6043 1411",
    "sg:postcode":"2640",
    "sg:province":"NSW",
    "sg:tags":[
        "club"
    ],
    "wof:name":"Thurgoona Golf Club Ltd",
    "wof:placetype":"venue"
},
  "geometry": {"coordinates":[146.98034668,-36.0413589478],"type":"Point"}
}