{
  "type": "Feature",
  "properties": {
    "addr:full":"Salvia Rd Prenzlau QLD 4311",
    "addr:postcode":"4311",
    "addr:street":"Salvia Rd",
    "iso:country":"AU",
    "sg:address":"Salvia Rd",
    "sg:city":"Prenzlau",
    "sg:classifiers":[
        {
            "category":"Manufacturing",
            "subcategory":"Tools & Machinery",
            "type":"Manufacturing & Wholesale Goods"
        }
    ],
    "sg:phone":"+61 7 5426 8487",
    "sg:postcode":"4311",
    "sg:province":"QLD",
    "sg:tags":[
        "earth",
        "excavating",
        "moving",
        "equipment"
    ],
    "wof:name":"Swan's Bobcat Hire",
    "wof:placetype":"venue"
},
  "geometry": {"coordinates":[152.52746582,-27.5087871552],"type":"Point"}
}