{
  "type": "Feature",
  "properties": {
    "addr:full":"PO Box 713 Park Holme SA 5043",
    "addr:postcode":"5043",
    "iso:country":"AU",
    "sg:address":"PO Box 713",
    "sg:city":"Park Holme",
    "sg:classifiers":[
        {
            "category":"Real Estate",
            "subcategory":"Real Estate Operator",
            "type":"Services"
        }
    ],
    "sg:phone":"+61 1300 557 266",
    "sg:postcode":"5043",
    "sg:province":"SA",
    "sg:tags":[
        "building",
        "consultant",
        "management"
    ],
    "wof:name":"Prolink Builders",
    "wof:placetype":"venue"
},
  "geometry": {"coordinates":[138.556793,-34.990849],"type":"Point"}
}