{
  "type": "Feature",
  "properties": {
    "addr:full":"Shop 42, City Centre Plaza Bolsover St Rockhampton QLD 4700",
    "addr:housenumber":"shop 42",
    "addr:postcode":"4700",
    "addr:street":"Bolsover St",
    "iso:country":"AU",
    "sg:address":"Shop 42, City Centre Plaza Bolsover St",
    "sg:city":"Rockhampton",
    "sg:classifiers":[
        {
            "category":"Shopping",
            "subcategory":"Jewelry",
            "type":"Retail Goods"
        }
    ],
    "sg:phone":"+61 7 4922 4033",
    "sg:postcode":"4700",
    "sg:province":"QLD",
    "sg:tags":[
        "jeweller"
    ],
    "wof:name":"Kleins Jewellery",
    "wof:placetype":"venue"
},
  "geometry": {"coordinates":[150.52244567899999,-23.3927211761],"type":"Point"}
}