{
  "type": "Feature",
  "properties": {
    "iso:country":"AU",
    "sg:address":"1 Kerwin St Cnr of Lake St",
    "sg:city":"Cairns",
    "sg:classifiers":[
        {
            "category":"Health Services",
            "subcategory":"Dentist",
            "type":"Services"
        }
    ],
    "sg:phone":"+61 7 4031 2134",
    "sg:postcode":"4870",
    "sg:province":"QLD",
    "wof:name":"The Smile Centre",
    "wof:placetype":"venue"
},
  "geometry": {"coordinates":[145.779205322,-16.9260311127],"type":"Point"}
}