{
  "type": "Feature",
  "properties": {
    "iso:country":"AU",
    "sg:address":"Lindsay St",
    "sg:city":"Rockdale",
    "sg:classifiers":[
        {
            "category":"Utilities",
            "subcategory":"Recycling",
            "type":"Services"
        }
    ],
    "sg:phone":"+61 1300 651 116",
    "sg:postcode":"2216",
    "sg:province":"NSW",
    "wof:name":"Waste Service NSW",
    "wof:placetype":"venue"
},
  "geometry": {"coordinates":[151.144714,-33.959263],"type":"Point"}
}