{
  "type": "Feature",
  "properties": {
    "iso:country":"AU",
    "sg:address":"Cnr Lynwood & Metcalfe Ave",
    "sg:city":"Lynwood",
    "sg:classifiers":[
        {
            "category":"Autos & Motor Vehicles",
            "subcategory":"Fuel & Gas Station",
            "type":"Retail Goods"
        }
    ],
    "sg:phone":"+61 8 9358 3255",
    "sg:postcode":"6147",
    "sg:province":"WA",
    "wof:name":"Peak Petroleum",
    "wof:placetype":"venue"
},
  "geometry": {"coordinates":[115.933258,-32.040703],"type":"Point"}
}