{
  "type": "Feature",
  "properties": {
    "addr:full":"59 Darlington Rd Darlington WA 6070",
    "addr:housenumber":"59",
    "addr:postcode":"6070",
    "addr:street":"Darlington Rd",
    "iso:country":"AU",
    "sg:address":"59 Darlington Rd",
    "sg:city":"Darlington",
    "sg:classifiers":[
        {
            "category":"Government",
            "subcategory":"Post Office",
            "type":"Public Place"
        }
    ],
    "sg:phone":"+61 8 9252 0169",
    "sg:postcode":"6070",
    "sg:province":"WA",
    "sg:tags":[
        "yoga"
    ],
    "wof:name":"Gentle Yoga & Stress Management",
    "wof:placetype":"venue"
},
  "geometry": {"coordinates":[116.07665252699999,-31.9069538116],"type":"Point"}
}