{
  "type": "Feature",
  "properties": {
    "iso:country":"AU",
    "sg:address":"5 Rifle Range Rd (via Lismore)",
    "sg:city":"Tuncester",
    "sg:classifiers":[
        {
            "category":"Wholesale",
            "subcategory":"Auto Parts",
            "type":"Manufacturing & Wholesale Goods"
        }
    ],
    "sg:phone":"+61 2 6621 7059",
    "sg:postcode":"2480",
    "sg:province":"NSW",
    "sg:tags":[
        "recyclers"
    ],
    "wof:name":"Hillside Auto Dismantlers",
    "wof:placetype":"venue"
},
  "geometry": {"coordinates":[153.22088623100001,-28.7985496521],"type":"Point"}
}