{
  "type": "Feature",
  "properties": {
    "iso:country":"AU",
    "sg:address":"58- 60 Crystal St",
    "sg:city":"Petersham",
    "sg:classifiers":[
        {
            "category":"Wholesale",
            "subcategory":"Non-durable Goods",
            "type":"Manufacturing & Wholesale Goods"
        }
    ],
    "sg:phone":"+61 2 9569 3099",
    "sg:postcode":"2049",
    "sg:province":"NSW",
    "sg:tags":[
        "wholesaler",
        "mfrs",
        "cosmetic"
    ],
    "wof:name":"Aloe Vera Cosmetics Australia",
    "wof:placetype":"venue"
},
  "geometry": {"coordinates":[151.158295,-33.89101],"type":"Point"}
}