{
  "type": "Feature",
  "properties": {
    "iso:country":"AU",
    "sg:address":"Suite 410, 71-73 Archer St",
    "sg:city":"Chatswood",
    "sg:classifiers":[
        {
            "category":"Banks & Credit Unions",
            "subcategory":"Financial Services",
            "type":"Services"
        }
    ],
    "sg:phone":"+61 13 19 37",
    "sg:postcode":"2067",
    "sg:province":"NSW",
    "sg:tags":[
        "financier"
    ],
    "wof:name":"Yes Home Loans Pty Ltd",
    "wof:placetype":"venue"
},
  "geometry": {"coordinates":[151.185638428,-33.7958946228],"type":"Point"}
}