{
  "type": "Feature",
  "properties": {
    "iso:country":"AU",
    "sg:address":"Suite 1302 84 Pitt St",
    "sg:city":"Sydney",
    "sg:classifiers":[
        {
            "category":"Professional",
            "subcategory":"Employment Agencies",
            "type":"Services"
        }
    ],
    "sg:phone":"+61 411 151 860",
    "sg:postcode":"2001",
    "sg:province":"NSW",
    "wof:name":"Look legal",
    "wof:placetype":"venue"
},
  "geometry": {"coordinates":[151.208709717,-33.8666687012],"type":"Point"}
}