{
  "type": "Feature",
  "properties": {
    "iso:country":"AU",
    "sg:address":"56 Paterson Pde",
    "sg:city":"Queanbeyan",
    "sg:classifiers":[
        {
            "category":"Professional",
            "type":"Services"
        }
    ],
    "sg:phone":"+61 2 6299 3860",
    "sg:postcode":"2620",
    "sg:province":"ACT",
    "sg:tags":[
        "shop",
        "fitting"
    ],
    "wof:name":"T.OK Carpentry & Partitioning",
    "wof:placetype":"venue"
},
  "geometry": {"coordinates":[149.20472717300001,-35.3525085449],"type":"Point"}
}