{
  "type": "Feature",
  "properties": {
    "addr:full":"2 Morgan St Parkdale VIC 3195",
    "addr:housenumber":"2",
    "addr:postcode":"3195",
    "addr:street":"Morgan St",
    "iso:country":"AU",
    "sg:address":"2 Morgan St",
    "sg:city":"Parkdale",
    "sg:classifiers":[
        {
            "category":"Professional",
            "subcategory":"Management & Consulting",
            "type":"Services"
        }
    ],
    "sg:phone":"+61 407 432 363",
    "sg:postcode":"3195",
    "sg:province":"VIC",
    "sg:tags":[
        "consultant",
        "energy"
    ],
    "wof:name":"Statewide Rating Service",
    "wof:placetype":"venue"
},
  "geometry": {"coordinates":[145.084884644,-37.9932441711],"type":"Point"}
}