{
  "type": "Feature",
  "properties": {
    "addr:full":"362 Victoria Rd Rydalmere NSW 2116",
    "addr:housenumber":"362",
    "addr:postcode":"2116",
    "addr:street":"Victoria Rd",
    "iso:country":"AU",
    "sg:address":"362 Victoria Rd",
    "sg:city":"Rydalmere",
    "sg:classifiers":[
        {
            "category":"Fast Food",
            "type":"Food & Drink"
        }
    ],
    "sg:phone":"+61 2 9638 1316",
    "sg:postcode":"2116",
    "sg:province":"NSW",
    "sg:tags":[
        "away",
        "take"
    ],
    "wof:name":"Rydalmere Take Away",
    "wof:placetype":"venue"
},
  "geometry": {"coordinates":[151.15899658199999,-33.9139404297],"type":"Point"}
}