{
  "type": "Feature",
  "properties": {
    "addr:full":"Shop 6, 122 Griffith St Coolangatta QLD 4225",
    "addr:housenumber":"shop 6 122",
    "addr:postcode":"4225",
    "addr:street":"Griffith St",
    "iso:country":"AU",
    "sg:address":"Shop 6, 122 Griffith St",
    "sg:city":"Coolangatta",
    "sg:classifiers":[
        {
            "category":"Shopping",
            "subcategory":"Clothing, Apparel, & Fashions",
            "type":"Retail Goods"
        }
    ],
    "sg:phone":"+61 7 5536 6477",
    "sg:postcode":"4225",
    "sg:province":"QLD",
    "sg:tags":[
        "lady",
        "wear"
    ],
    "wof:name":"C Water Pty Ltd",
    "wof:placetype":"venue"
},
  "geometry": {"coordinates":[153.54034423799999,-28.168888092],"type":"Point"}
}