{
  "type": "Feature",
  "properties": {
    "addr:full":"24 Wandella Rd Allambie NSW 2100",
    "addr:housenumber":"24",
    "addr:postcode":"2100",
    "addr:street":"Wandella Rd",
    "iso:country":"AU",
    "sg:address":"24 Wandella Rd",
    "sg:city":"Allambie",
    "sg:classifiers":[
        {
            "category":"Retail",
            "subcategory":"Storage",
            "type":"Services"
        }
    ],
    "sg:phone":"+61 2 9939 7642",
    "sg:postcode":"2100",
    "sg:province":"NSW",
    "sg:tags":[
        "removal",
        "furniture"
    ],
    "wof:name":"Caring Removals",
    "wof:placetype":"venue"
},
  "geometry": {"coordinates":[151.25833129899999,-33.7769165039],"type":"Point"}
}