{
  "type": "Feature",
  "properties": {
    "addr:full":"15 Nile St Port Adelaide SA 5015",
    "addr:housenumber":"15",
    "addr:postcode":"5015",
    "addr:street":"Nile St",
    "iso:country":"AU",
    "sg:address":"15 Nile St",
    "sg:city":"Port Adelaide",
    "sg:classifiers":[
        {
            "category":"Autos & Motor Vehicles",
            "subcategory":"Boat Sales",
            "type":"Retail Goods"
        }
    ],
    "sg:phone":"+61 1800 654 744",
    "sg:postcode":"5015",
    "sg:province":"SA",
    "sg:tags":[
        "equipment",
        "yacht"
    ],
    "wof:name":"Taylor Marine",
    "wof:placetype":"venue"
},
  "geometry": {"coordinates":[138.50181579599999,-34.8444747925],"type":"Point"}
}