{
  "type": "Feature",
  "properties": {
    "iso:country":"AU",
    "sg:address":"49 Furnace Rd",
    "sg:city":"Welshpool",
    "sg:classifiers":[
        {
            "category":"Building & Trades",
            "subcategory":"Construction",
            "type":"Services"
        }
    ],
    "sg:phone":"+61 8 9350 5878",
    "sg:postcode":"6106",
    "sg:province":"WA",
    "sg:tags":[
        "installation",
        "air conditioning"
    ],
    "wof:name":"Envar Service Pty Ltd",
    "wof:placetype":"venue"
},
  "geometry": {"coordinates":[115.952003479,-31.9956512451],"type":"Point"}
}