{
  "type": "Feature",
  "properties": {
    "addr:full":"Shp 4/ 180 Burton Rd Paralowie SA 5108",
    "addr:housenumber":"/ 180",
    "addr:postcode":"5108",
    "addr:street":"Burton Rd",
    "iso:country":"AU",
    "sg:address":"Shp 4/ 180 Burton Rd",
    "sg:city":"Paralowie",
    "sg:classifiers":[
        {
            "category":"Personal",
            "subcategory":"Beauty Salon",
            "type":"Services"
        }
    ],
    "sg:phone":"+61 8 8281 1200",
    "sg:postcode":"5108",
    "sg:province":"SA",
    "wof:name":"Purity Hair Beauty",
    "wof:placetype":"venue"
},
  "geometry": {"coordinates":[138.609619141,-34.7561302185],"type":"Point"}
}