{
  "type": "Feature",
  "properties": {
    "addr:full":"PO Box 47 Belmont NSW 2280",
    "addr:postcode":"2280",
    "iso:country":"AU",
    "sg:address":"PO Box 47",
    "sg:city":"Belmont",
    "sg:classifiers":[
        {
            "category":"Utilities",
            "subcategory":"Water",
            "type":"Services"
        }
    ],
    "sg:phone":"+61 2 4948 2387",
    "sg:postcode":"2280",
    "sg:province":"NSW",
    "sg:tags":[
        "hot",
        "system"
    ],
    "wof:name":"Admac Plumbing Services P/L",
    "wof:placetype":"venue"
},
  "geometry": {"coordinates":[151.66021728499999,-33.0360107422],"type":"Point"}
}