{
  "type": "Feature",
  "properties": {
    "addr:full":"10/ 4- 8 Tower Crt Keysborough VIC 3173",
    "addr:housenumber":"10 / 4 8",
    "addr:postcode":"3173",
    "addr:street":"Tower Crt",
    "iso:country":"AU",
    "sg:address":"10/ 4- 8 Tower Crt",
    "sg:city":"Keysborough",
    "sg:classifiers":[
        {
            "category":"Wholesale",
            "subcategory":"Medical Equipment & Supplies",
            "type":"Manufacturing & Wholesale Goods"
        }
    ],
    "sg:phone":"+61 3 9701 5540",
    "sg:postcode":"3173",
    "sg:province":"VIC",
    "sg:tags":[
        "industrial",
        "drying"
    ],
    "wof:name":"Dry Air Systems",
    "wof:placetype":"venue"
},
  "geometry": {"coordinates":[145.189727783,-37.9817619324],"type":"Point"}
}