{
  "type": "Feature",
  "properties": {
    "addr:full":"Weippin St Cleveland QLD 4163",
    "addr:postcode":"4163",
    "addr:street":"St",
    "iso:country":"AU",
    "sg:address":"Weippin St",
    "sg:city":"Cleveland",
    "sg:classifiers":[
        {
            "category":"Health Services",
            "subcategory":"Doctor",
            "type":"Services"
        }
    ],
    "sg:phone":"+61 7 3010 5733",
    "sg:postcode":"4163",
    "sg:province":"QLD",
    "sg:tags":[
        "medical",
        "practitioner"
    ],
    "wof:name":"Astori Ivan Dr",
    "wof:placetype":"venue"
},
  "geometry": {"coordinates":[153.253463745,-27.5415649414],"type":"Point"}
}