{
  "type": "Feature",
  "properties": {
    "iso:country":"AU",
    "sg:address":"3/ 3 Techno Park Drv",
    "sg:city":"Williamstown",
    "sg:classifiers":[
        {
            "category":"Retail",
            "subcategory":"Auto Repair",
            "type":"Services"
        }
    ],
    "sg:phone":"+61 3 9397 3993",
    "sg:postcode":"3016",
    "sg:province":"VIC",
    "sg:tags":[
        "repairer",
        "motor",
        "engineer"
    ],
    "wof:name":"Morassi & Williams",
    "wof:placetype":"venue"
},
  "geometry": {"coordinates":[144.858276367,-37.8553237915],"type":"Point"}
}