{
  "type": "Feature",
  "properties": {
    "iso:country":"AU",
    "sg:address":"5 Industrial Crt",
    "sg:city":"Seymour",
    "sg:classifiers":[
        {
            "category":"Building & Trades",
            "subcategory":"Construction",
            "type":"Services"
        }
    ],
    "sg:phone":"+61 407 128 684",
    "sg:postcode":"3660",
    "sg:province":"VIC",
    "sg:tags":[
        "welding"
    ],
    "wof:name":"KC Engineering & Welding",
    "wof:placetype":"venue"
},
  "geometry": {"coordinates":[145.13502502399999,-37.0193634033],"type":"Point"}
}