{
  "type": "Feature",
  "properties": {
    "addr:full":"94 Main Rd Glenalta SA 5052",
    "addr:housenumber":"94",
    "addr:postcode":"5052",
    "addr:street":"Main Rd",
    "iso:country":"AU",
    "sg:address":"94 Main Rd",
    "sg:city":"Glenalta",
    "sg:classifiers":[
        {
            "category":"Professional",
            "subcategory":"Computer Services",
            "type":"Services"
        }
    ],
    "sg:phone":"+61 433 216 917",
    "sg:postcode":"5052",
    "sg:province":"SA",
    "sg:tags":[
        "consultant",
        "system"
    ],
    "wof:name":"Lambert's Innovative Services",
    "wof:placetype":"venue"
},
  "geometry": {"coordinates":[138.624863,-35.006973],"type":"Point"}
}