{
  "type": "Feature",
  "properties": {
    "addr:full":"3 Curtis St Coolamon NSW 2701",
    "addr:housenumber":"3",
    "addr:postcode":"2701",
    "addr:street":"Curtis St",
    "iso:country":"AU",
    "sg:address":"3 Curtis St",
    "sg:city":"Coolamon",
    "sg:classifiers":[
        {
            "category":"Retail",
            "subcategory":"Storage",
            "type":"Services"
        }
    ],
    "sg:phone":"+61 2 6929 1246",
    "sg:postcode":"2701",
    "sg:province":"NSW",
    "wof:name":"Coolamon Self Storage",
    "wof:placetype":"venue"
},
  "geometry": {"coordinates":[147.21284484899999,-34.818359375],"type":"Point"}
}