{
  "type": "Feature",
  "properties": {
    "iso:country":"AU",
    "sg:address":"Unit 1, 25 Augusta St",
    "sg:city":"Willetton",
    "sg:classifiers":[
        {
            "category":"Shopping",
            "subcategory":"Optical Goods",
            "type":"Retail Goods"
        }
    ],
    "sg:phone":"+61 8 9354 4499",
    "sg:postcode":"6155",
    "sg:province":"WA",
    "sg:tags":[
        "supply"
    ],
    "wof:name":"Aviva Optical Supplies",
    "wof:placetype":"venue"
},
  "geometry": {"coordinates":[115.879936,-32.042702],"type":"Point"}
}