{
  "type": "Feature",
  "properties": {
    "addr:full":"Roy St Wangaratta VIC 3677",
    "addr:postcode":"3677",
    "addr:street":"Roy St",
    "iso:country":"AU",
    "sg:address":"Roy St",
    "sg:city":"Wangaratta",
    "sg:classifiers":[
        {
            "category":"Education",
            "subcategory":"Kindergarten",
            "type":"Public Place"
        }
    ],
    "sg:phone":"+61 3 5721 3797",
    "sg:postcode":"3677",
    "sg:province":"VIC",
    "sg:tags":[
        "pre-schools"
    ],
    "wof:name":"Coronation Kindergarten",
    "wof:placetype":"venue"
},
  "geometry": {"coordinates":[146.31838989299999,-36.3583717346],"type":"Point"}
}