{
  "type": "Feature",
  "properties": {
    "iso:country":"AU",
    "sg:address":"571 High St",
    "sg:city":"Epping",
    "sg:classifiers":[
        {
            "category":"Shopping",
            "subcategory":"Clothing, Apparel, & Fashions",
            "type":"Retail Goods"
        }
    ],
    "sg:phone":"+61 3 9408 9035",
    "sg:postcode":"3076",
    "sg:province":"VIC",
    "sg:tags":[
        "lingerie",
        "hosiery",
        "sleepwear"
    ],
    "wof:name":"Bras n^B Things",
    "wof:placetype":"venue"
},
  "geometry": {"coordinates":[145.02691650400001,-37.6332168579],"type":"Point"}
}