{
  "type": "Feature",
  "properties": {
    "addr:full":"35 Barry Ave Mortdale NSW 2223",
    "addr:housenumber":"35",
    "addr:postcode":"2223",
    "addr:street":"Barry Ave",
    "iso:country":"AU",
    "sg:address":"35 Barry Ave",
    "sg:city":"Mortdale",
    "sg:classifiers":[
        {
            "category":"Organizations",
            "subcategory":"Professional Association",
            "type":"Services"
        }
    ],
    "sg:phone":"+61 2 9558 6157",
    "sg:postcode":"2223",
    "sg:province":"NSW",
    "sg:tags":[
        "web",
        "internet"
    ],
    "wof:name":"Inaweb Pty Ltd",
    "wof:placetype":"venue"
},
  "geometry": {"coordinates":[151.068725586,-33.9670257568],"type":"Point"}
}