{
  "type": "Feature",
  "properties": {
    "addr:full":"333 Princes Hwy Bulli NSW 2516",
    "addr:housenumber":"333",
    "addr:postcode":"2516",
    "addr:street":"Princes Hwy",
    "iso:country":"AU",
    "sg:address":"333 Princes Hwy",
    "sg:city":"Bulli",
    "sg:classifiers":[
        {
            "category":"Autos & Motor Vehicles",
            "subcategory":"Automobile Sales",
            "type":"Retail Goods"
        }
    ],
    "sg:phone":"+61 2 4284 9300",
    "sg:postcode":"2516",
    "sg:province":"NSW",
    "sg:tags":[
        "car",
        "used"
    ],
    "wof:name":"Bulli Motor Village",
    "wof:placetype":"venue"
},
  "geometry": {"coordinates":[150.90870699999999,-34.339157],"type":"Point"}
}