{
  "type": "Feature",
  "properties": {
    "addr:full":"17 Dallas Pde Keperra QLD 4054",
    "addr:housenumber":"17",
    "addr:postcode":"4054",
    "addr:street":"Dallas Pde",
    "iso:country":"AU",
    "sg:address":"17 Dallas Pde",
    "sg:city":"Keperra",
    "sg:classifiers":[
        {
            "category":"Fast Food",
            "type":"Food & Drink"
        }
    ],
    "sg:phone":"+61 7 3355 2516",
    "sg:postcode":"4054",
    "sg:province":"QLD",
    "sg:tags":[
        "away",
        "take"
    ],
    "wof:name":"Keperra Take Away",
    "wof:placetype":"venue"
},
  "geometry": {"coordinates":[152.95843505900001,-27.4091682434],"type":"Point"}
}