{
  "type": "Feature",
  "properties": {
    "iso:country":"AU",
    "sg:address":"Cnr Gordon & Brisbane Sts",
    "sg:city":"Mackay",
    "sg:classifiers":[
        {
            "category":"Shopping",
            "subcategory":"Mobile Phones",
            "type":"Retail Goods"
        }
    ],
    "sg:phone":"+61 7 4951 7731",
    "sg:postcode":"4740",
    "sg:province":"QLD",
    "sg:tags":[
        "telephone",
        "accessory"
    ],
    "wof:name":"MCS Connect",
    "wof:placetype":"venue"
},
  "geometry": {"coordinates":[149.18760700000001,-21.146685],"type":"Point"}
}