{
  "type": "Feature",
  "properties": {
    "addr:full":"1 Oxley Pl Rockingham WA 6168",
    "addr:housenumber":"1",
    "addr:postcode":"6168",
    "addr:street":"Oxley Pl",
    "iso:country":"AU",
    "sg:address":"1 Oxley Pl",
    "sg:city":"Rockingham",
    "sg:classifiers":[
        {
            "category":"Professional",
            "subcategory":"Accounting & Tax Preparation",
            "type":"Services"
        }
    ],
    "sg:phone":"+61 8 9527 2117",
    "sg:postcode":"6168",
    "sg:province":"WA",
    "sg:tags":[
        "bookkeeping"
    ],
    "wof:name":"Booksec Services",
    "wof:placetype":"venue"
},
  "geometry": {"coordinates":[115.738823,-32.28389],"type":"Point"}
}