{
  "type": "Feature",
  "properties": {
    "addr:full":"255 High St Ashburton VIC 3147",
    "addr:housenumber":"255",
    "addr:postcode":"3147",
    "addr:street":"High St",
    "iso:country":"AU",
    "sg:address":"255 High St",
    "sg:city":"Ashburton",
    "sg:classifiers":[
        {
            "category":"Personal",
            "subcategory":"Beauty Salon",
            "type":"Services"
        }
    ],
    "sg:phone":"+61 3 9886 9499",
    "sg:postcode":"3147",
    "sg:province":"VIC",
    "wof:name":"Tranquility + Hair Skin Body",
    "wof:placetype":"venue"
},
  "geometry": {"coordinates":[145.07919311500001,-37.8632202148],"type":"Point"}
}