{
  "type": "Feature",
  "properties": {
    "addr:full":"13 Napier St Petersham NSW 2049",
    "addr:housenumber":"13",
    "addr:postcode":"2049",
    "addr:street":"Napier St",
    "iso:country":"AU",
    "sg:address":"13 Napier St",
    "sg:city":"Petersham",
    "sg:classifiers":[
        {
            "category":"Building & Trades",
            "subcategory":"Construction",
            "type":"Services"
        }
    ],
    "sg:phone":"+61 417 202 664",
    "sg:postcode":"2049",
    "sg:province":"NSW",
    "sg:tags":[
        "joiner",
        "carpenter"
    ],
    "wof:name":"Kalogiannis Carpentry & Joiner",
    "wof:placetype":"venue"
},
  "geometry": {"coordinates":[151.151611,-33.899868],"type":"Point"}
}