{
  "type": "Feature",
  "properties": {
    "addr:full":"Unit 2/ 48-54 Enterprise Ave Berwick VIC 3806",
    "addr:housenumber":"/ 48-54",
    "addr:postcode":"3806",
    "addr:street":"Enterprise Ave",
    "iso:country":"AU",
    "sg:address":"Unit 2/ 48-54 Enterprise Ave",
    "sg:city":"Berwick",
    "sg:classifiers":[
        {
            "category":"Utilities",
            "type":"Services"
        }
    ],
    "sg:phone":"+61 3 9792 2283",
    "sg:postcode":"3806",
    "sg:province":"VIC",
    "sg:tags":[
        "refrigeration",
        "industrial",
        "commercial",
        "retail"
    ],
    "wof:name":"Airepair Air Conditioning Services Pty Ltd",
    "wof:placetype":"venue"
},
  "geometry": {"coordinates":[145.339233398,-38.0363311768],"type":"Point"}
}