{
  "type": "Feature",
  "properties": {
    "addr:full":"200 Victoria Rd Gladesville NSW 2111",
    "addr:housenumber":"200",
    "addr:postcode":"2111",
    "addr:street":"Victoria Rd",
    "iso:country":"AU",
    "sg:address":"200 Victoria Rd",
    "sg:city":"Gladesville",
    "sg:classifiers":[
        {
            "category":"Banks & Credit Unions",
            "subcategory":"Bank",
            "type":"Services"
        }
    ],
    "sg:phone":"+61 13 13 14",
    "sg:postcode":"2111",
    "sg:province":"NSW",
    "wof:name":"ANZ",
    "wof:placetype":"venue"
},
  "geometry": {"coordinates":[151.12672424300001,-33.8315658569],"type":"Point"}
}