{
  "type": "Feature",
  "properties": {
    "addr:full":"Cnr Clements Ave & Colby Drv Belgrave South VIC 3160",
    "addr:postcode":"3160",
    "addr:street":"Cnr Clements Ave & Colby Drv",
    "iso:country":"AU",
    "sg:address":"Cnr Clements Ave & Colby Drv",
    "sg:city":"Belgrave South",
    "sg:classifiers":[
        {
            "category":"Social Services",
            "subcategory":"Child Care",
            "type":"Services"
        }
    ],
    "sg:phone":"+61 3 9754 4077",
    "sg:postcode":"3160",
    "sg:province":"VIC",
    "sg:tags":[
        "support",
        "health"
    ],
    "wof:name":"Maternal & Child Health Centres",
    "wof:placetype":"venue"
},
  "geometry": {"coordinates":[145.357345581,-37.9282798767],"type":"Point"}
}