{
  "type": "Feature",
  "properties": {
    "iso:country":"AU",
    "sg:address":"738 Port Rd",
    "sg:city":"Beverley",
    "sg:classifiers":[
        {
            "category":"Retail",
            "subcategory":"Auto Repair",
            "type":"Services"
        }
    ],
    "sg:phone":"+61 8 8345 3047",
    "sg:postcode":"5009",
    "sg:province":"SA",
    "sg:tags":[
        "repairer",
        "motor",
        "engineer"
    ],
    "wof:name":"Rusack Motors Pty Ltd",
    "wof:placetype":"venue"
},
  "geometry": {"coordinates":[138.54339599599999,-34.8866462708],"type":"Point"}
}