{
  "type": "Feature",
  "properties": {
    "addr:full":"11th Flr 83 Dale St Port Adelaide SA 5015",
    "addr:housenumber":"83",
    "addr:postcode":"5015",
    "addr:street":"Dale St",
    "iso:country":"AU",
    "sg:address":"11th Flr 83 Dale St",
    "sg:city":"Port Adelaide",
    "sg:classifiers":[
        {
            "category":"Banks & Credit Unions",
            "subcategory":"Investment Brokerage",
            "type":"Services"
        }
    ],
    "sg:phone":"+61 8 8206 4286",
    "sg:postcode":"5015",
    "sg:province":"SA",
    "wof:name":"Commonwealth Financial Planning",
    "wof:placetype":"venue"
},
  "geometry": {"coordinates":[138.50581359899999,-34.84633255],"type":"Point"}
}