{
  "type": "Feature",
  "properties": {
    "addr:full":"250- 252 Kingston Rd Slacks Creek QLD 4127",
    "addr:housenumber":"252",
    "addr:postcode":"4127",
    "addr:street":"Kingston Rd",
    "iso:country":"AU",
    "sg:address":"250- 252 Kingston Rd",
    "sg:city":"Slacks Creek",
    "sg:classifiers":[
        {
            "category":"Banks & Credit Unions",
            "subcategory":"Financial Services",
            "type":"Services"
        }
    ],
    "sg:phone":"+61 7 3208 2444",
    "sg:postcode":"4127",
    "sg:province":"QLD",
    "sg:tags":[
        "financier"
    ],
    "wof:name":"Fast Access Finance Slacks Creek",
    "wof:placetype":"venue"
},
  "geometry": {"coordinates":[153.118865967,-27.6399440765],"type":"Point"}
}