{
  "type": "Feature",
  "properties": {
    "addr:full":"2/ 1162 Albany Hwy Bentley WA 6102",
    "addr:housenumber":"/ 1162",
    "addr:postcode":"6102",
    "addr:street":"Albany Hwy",
    "iso:country":"AU",
    "sg:address":"2/ 1162 Albany Hwy",
    "sg:city":"Bentley",
    "sg:classifiers":[
        {
            "category":"Banks & Credit Unions",
            "subcategory":"Investment Brokerage",
            "type":"Services"
        }
    ],
    "sg:phone":"+61 8 6454 6200",
    "sg:postcode":"6102",
    "sg:province":"WA",
    "sg:tags":[
        "management",
        "property"
    ],
    "wof:name":"Target Realty Pty Ltd",
    "wof:placetype":"venue"
},
  "geometry": {"coordinates":[115.92076110799999,-32.0040168762],"type":"Point"}
}