{
  "type": "Feature",
  "properties": {
    "addr:full":"Unit 25/ 63 Wollongong St Fyshwick ACT 2609",
    "addr:housenumber":"/ 63",
    "addr:postcode":"2609",
    "addr:street":"Wollongong St",
    "iso:country":"AU",
    "sg:address":"Unit 25/ 63 Wollongong St",
    "sg:city":"Fyshwick",
    "sg:classifiers":[
        {
            "category":"Fast Food",
            "type":"Food & Drink"
        }
    ],
    "sg:phone":"+61 2 6280 7058",
    "sg:postcode":"2609",
    "sg:province":"ACT",
    "sg:tags":[
        "away",
        "take"
    ],
    "wof:name":"Rolls Choice",
    "wof:placetype":"venue"
},
  "geometry": {"coordinates":[149.17933654800001,-35.3240699768],"type":"Point"}
}