{
  "type": "Feature",
  "properties": {
    "iso:country":"AU",
    "sg:address":"41 Ramsay St",
    "sg:city":"Cloncurry",
    "sg:classifiers":[
        {
            "category":"Food & Beverages",
            "subcategory":"Supermarket",
            "type":"Retail Goods"
        }
    ],
    "sg:phone":"+61 7 4742 1303",
    "sg:postcode":"4824",
    "sg:province":"QLD",
    "sg:tags":[
        "grocery",
        "store"
    ],
    "wof:name":"Foodworks Cloncurry",
    "wof:placetype":"venue"
},
  "geometry": {"coordinates":[140.50593599999999,-20.706619],"type":"Point"}
}