{
  "type": "Feature",
  "properties": {
    "addr:full":"13- 15 Prospect St Fortitude Valley QLD 4006",
    "addr:housenumber":"15",
    "addr:postcode":"4006",
    "addr:street":"Prospect St",
    "iso:country":"AU",
    "sg:address":"13- 15 Prospect St",
    "sg:city":"Fortitude Valley",
    "sg:classifiers":[
        {
            "category":"Shopping",
            "subcategory":"Clothing, Apparel, & Fashions",
            "type":"Retail Goods"
        }
    ],
    "sg:phone":"+61 7 3252 9244",
    "sg:postcode":"4006",
    "sg:province":"QLD",
    "sg:tags":[
        "uniform"
    ],
    "wof:name":"Welborne International",
    "wof:placetype":"venue"
},
  "geometry": {"coordinates":[153.03765869099999,-27.4519882202],"type":"Point"}
}