{
  "type": "Feature",
  "properties": {
    "iso:country":"AU",
    "sg:address":"55 Warooka Rd",
    "sg:city":"Yorketown",
    "sg:classifiers":[
        {
            "category":"Education",
            "subcategory":"School",
            "type":"Public Place"
        }
    ],
    "sg:phone":"+61 8 8852 1461",
    "sg:postcode":"5576",
    "sg:province":"SA",
    "wof:name":"St Columba's Memorial School",
    "wof:placetype":"venue"
},
  "geometry": {"coordinates":[137.60017395,-35.0191383362],"type":"Point"}
}