{
  "type": "Feature",
  "properties": {
    "addr:full":"2 Neville Crt View Bank VIC 3084",
    "addr:housenumber":"2",
    "addr:postcode":"3084",
    "addr:street":"Neville Crt View Bank",
    "iso:country":"AU",
    "sg:address":"2 Neville Crt",
    "sg:city":"View Bank",
    "sg:classifiers":[
        {
            "category":"Manufacturing",
            "subcategory":"Apparel",
            "type":"Manufacturing & Wholesale Goods"
        }
    ],
    "sg:phone":"+61 409 254 562",
    "sg:postcode":"3084",
    "sg:province":"VIC",
    "sg:tags":[
        "makers-up",
        "clothing"
    ],
    "wof:name":"Gambol",
    "wof:placetype":"venue"
},
  "geometry": {"coordinates":[145.089553833,-37.7440681458],"type":"Point"}
}