{
  "type": "Feature",
  "properties": {
    "addr:full":"Wetherby Rd Molloy QLD 4880",
    "addr:postcode":"4880",
    "addr:street":"Wetherby Rd",
    "iso:country":"AU",
    "sg:address":"Wetherby Rd",
    "sg:city":"Molloy",
    "sg:classifiers":[
        {
            "category":"Farming",
            "subcategory":"Farm",
            "type":"Manufacturing & Wholesale Goods"
        }
    ],
    "sg:phone":"+61 7 4098 8012",
    "sg:postcode":"4880",
    "sg:province":"QLD",
    "sg:tags":[
        "farmer"
    ],
    "wof:name":"Spring Valley Farms",
    "wof:placetype":"venue"
},
  "geometry": {"coordinates":[145.42787170400001,-16.9976387024],"type":"Point"}
}