{
  "type": "Feature",
  "properties": {
    "iso:country":"AU",
    "sg:address":"105 Norman Ave",
    "sg:city":"Norman Park",
    "sg:classifiers":[
        {
            "category":"Social Services",
            "subcategory":"Retirement Home",
            "type":"Services"
        }
    ],
    "sg:phone":"+61 7 3899 8784",
    "sg:postcode":"4170",
    "sg:province":"QLD",
    "sg:tags":[
        "life",
        "coaching"
    ],
    "wof:name":"Campbell B J",
    "wof:placetype":"venue"
},
  "geometry": {"coordinates":[153.05816650400001,-27.479385376],"type":"Point"}
}