{
  "type": "Feature",
  "properties": {
    "iso:country":"AU",
    "sg:address":"58 Thomas St",
    "sg:city":"Parramatta",
    "sg:classifiers":[
        {
            "category":"Building & Trades",
            "subcategory":"Cleaning & Sanitation",
            "type":"Services"
        }
    ],
    "sg:phone":"+61 2 9683 6568",
    "sg:postcode":"2150",
    "sg:province":"NSW",
    "sg:tags":[
        "industrial",
        "commercial",
        "contractor"
    ],
    "wof:name":"Ably Cleaning Service Pty Ltd",
    "wof:placetype":"venue"
},
  "geometry": {"coordinates":[150.99160766599999,-33.82762146],"type":"Point"}
}