{
  "type": "Feature",
  "properties": {
    "addr:full":"1 Joseph Rd Footscray VIC 3011",
    "addr:housenumber":"1",
    "addr:postcode":"3011",
    "addr:street":"Joseph Rd",
    "iso:country":"AU",
    "sg:address":"1 Joseph Rd",
    "sg:city":"Footscray",
    "sg:classifiers":[
        {
            "category":"Building & Trades",
            "subcategory":"Pest Control",
            "type":"Services"
        }
    ],
    "sg:phone":"+61 3 9362 0355",
    "sg:postcode":"3011",
    "sg:province":"VIC",
    "wof:name":"Container Fumigation Services",
    "wof:placetype":"venue"
},
  "geometry": {"coordinates":[144.910552978,-37.798789978],"type":"Point"}
}