{
  "type": "Feature",
  "properties": {
    "addr:full":"194 Cavendish Rd Coorparoo QLD 4151",
    "addr:housenumber":"194",
    "addr:postcode":"4151",
    "addr:street":"Cavendish Rd",
    "iso:country":"AU",
    "sg:address":"194 Cavendish Rd",
    "sg:city":"Coorparoo",
    "sg:classifiers":[
        {
            "category":"Health Services",
            "subcategory":"Chiropractor",
            "type":"Services"
        }
    ],
    "sg:phone":"+61 7 3394 4522",
    "sg:postcode":"4151",
    "sg:province":"QLD",
    "wof:name":"Gundelach Felicity",
    "wof:placetype":"venue"
},
  "geometry": {"coordinates":[153.059249878,-27.4942340851],"type":"Point"}
}