{
  "type": "Feature",
  "properties": {
    "iso:country":"AU",
    "sg:address":"Lvl 2/ 157",
    "sg:city":"Wickham Tce Spring Hill",
    "sg:classifiers":[
        {
            "category":"Professional",
            "subcategory":"Business Services",
            "type":"Services"
        }
    ],
    "sg:phone":"+61 7 3832 0035",
    "sg:postcode":"4000",
    "sg:province":"QLD",
    "sg:tags":[
        "broker"
    ],
    "wof:name":"MABB Group",
    "wof:placetype":"venue"
},
  "geometry": {"coordinates":[153.02513122600001,-27.4646835327],"type":"Point"}
}