{
  "type": "Feature",
  "properties": {
    "iso:country":"AU",
    "sg:address":"416 Church St",
    "sg:city":"Richmond",
    "sg:classifiers":[
        {
            "category":"Travel",
            "subcategory":"Travel Agent",
            "type":"Entertainment"
        }
    ],
    "sg:phone":"+61 3 9429 8400",
    "sg:postcode":"3121",
    "sg:province":"VIC",
    "sg:tags":[
        "consultant"
    ],
    "wof:name":"Westminster Travel",
    "wof:placetype":"venue"
},
  "geometry": {"coordinates":[144.99794006400001,-37.8247413635],"type":"Point"}
}