{
  "type": "Feature",
  "properties": {
    "iso:country":"AU",
    "sg:address":"2 Alexandria St",
    "sg:city":"Mackay",
    "sg:classifiers":[
        {
            "category":"Retail",
            "subcategory":"Storage",
            "type":"Services"
        }
    ],
    "sg:phone":"+61 7 4954 5401",
    "sg:postcode":"4740",
    "sg:province":"QLD",
    "sg:tags":[
        "removal",
        "furniture"
    ],
    "sg:website":"http://www.regionlink.com.au/craigsremovals",
    "wof:name":"Craigs Removals",
    "wof:placetype":"venue"
},
  "geometry": {"coordinates":[149.09999099999999,-21.163673],"type":"Point"}
}