{
  "type": "Feature",
  "properties": {
    "addr:full":"3A Broadway St Bassendean WA 6054",
    "addr:housenumber":"3a",
    "addr:postcode":"6054",
    "addr:street":"Broadway St",
    "iso:country":"AU",
    "sg:address":"3A Broadway St",
    "sg:city":"Bassendean",
    "sg:classifiers":[
        {
            "category":"Personal",
            "subcategory":"Beauty Salon",
            "type":"Services"
        }
    ],
    "sg:phone":"+61 8 9279 5015",
    "sg:postcode":"6054",
    "sg:province":"WA",
    "sg:tags":[
        "hairdresser"
    ],
    "wof:name":"Broadway Hair Boutique",
    "wof:placetype":"venue"
},
  "geometry": {"coordinates":[115.946273804,-31.9028968811],"type":"Point"}
}