{
  "type": "Feature",
  "properties": {
    "addr:full":"116 Lyons St Bungalow QLD 4870",
    "addr:housenumber":"116",
    "addr:postcode":"4870",
    "addr:street":"Lyons St",
    "iso:country":"AU",
    "sg:address":"116 Lyons St",
    "sg:city":"Bungalow",
    "sg:classifiers":[
        {
            "category":"Professional",
            "subcategory":"Art Services",
            "type":"Services"
        }
    ],
    "sg:phone":"+61 7 4035 5855",
    "sg:postcode":"4870",
    "sg:province":"QLD",
    "sg:tags":[
        "graphic",
        "designer"
    ],
    "wof:name":"Prompt Printery",
    "wof:placetype":"venue"
},
  "geometry": {"coordinates":[145.75402832,-16.9370765686],"type":"Point"}
}