{
  "type": "Feature",
  "properties": {
    "addr:full":"97 Kambora Ave Davidson NSW 2085",
    "addr:housenumber":"97",
    "addr:postcode":"2085",
    "addr:street":"Kambora Ave",
    "iso:country":"AU",
    "sg:address":"97 Kambora Ave",
    "sg:city":"Davidson",
    "sg:classifiers":[
        {
            "category":"Personal",
            "subcategory":"Beauty Salon",
            "type":"Services"
        }
    ],
    "sg:phone":"+61 403 270 662",
    "sg:postcode":"2085",
    "sg:province":"NSW",
    "sg:tags":[
        "supply",
        "artist",
        "make-up"
    ],
    "wof:name":"Sjati Make Up Art",
    "wof:placetype":"venue"
},
  "geometry": {"coordinates":[151.193435669,-33.7379341125],"type":"Point"}
}