{
  "type": "Feature",
  "properties": {
    "addr:full":"1/ 91 Station St Malvern VIC 3144",
    "addr:housenumber":"/ 91",
    "addr:postcode":"3144",
    "addr:street":"Station St",
    "iso:country":"AU",
    "sg:address":"1/ 91 Station St",
    "sg:city":"Malvern",
    "sg:classifiers":[
        {
            "category":"Professional",
            "subcategory":"Accounting & Tax Preparation",
            "type":"Services"
        }
    ],
    "sg:phone":"+61 3 9500 0121",
    "sg:postcode":"3144",
    "sg:province":"VIC",
    "sg:tags":[
        "accountant",
        "auditor"
    ],
    "wof:name":"Alexander & Co Pty Ltd",
    "wof:placetype":"venue"
},
  "geometry": {"coordinates":[145.03091430699999,-37.8670539856],"type":"Point"}
}