{
  "type": "Feature",
  "properties": {
    "addr:full":"437 Penshurst St Chatswood NSW 2067",
    "addr:housenumber":"437",
    "addr:postcode":"2067",
    "addr:street":"Penshurst St",
    "iso:country":"AU",
    "sg:address":"437 Penshurst St",
    "sg:city":"Chatswood",
    "sg:classifiers":[
        {
            "category":"Building & Trades",
            "subcategory":"Plumbing",
            "type":"Services"
        }
    ],
    "sg:phone":"+61 2 9417 7850",
    "sg:postcode":"2067",
    "sg:province":"NSW",
    "sg:tags":[
        "drainers"
    ],
    "wof:name":"A A Abound Emergency Stormwater Electric Eel Drainage Pipe Relining And CCTV Pip",
    "wof:placetype":"venue"
},
  "geometry": {"coordinates":[151.192504883,-33.7852859497],"type":"Point"}
}