{
  "type": "Feature",
  "properties": {
    "iso:country":"AU",
    "sg:address":"11 Hopkinson St",
    "sg:city":"South Burnie",
    "sg:classifiers":[
        {
            "category":"Retail",
            "subcategory":"Car Wash",
            "type":"Services"
        }
    ],
    "sg:phone":"+61 3 6431 1944",
    "sg:postcode":"7320",
    "sg:province":"TAS",
    "sg:tags":[
        "truck",
        "cleaning"
    ],
    "wof:name":"Supreme Detailing",
    "wof:placetype":"venue"
},
  "geometry": {"coordinates":[145.911133,-41.062412],"type":"Point"}
}