{
  "type": "Feature",
  "properties": {
    "addr:full":"11 Hopkinson St South Burnie TAS 7320",
    "addr:housenumber":"11",
    "addr:postcode":"7320",
    "addr:street":"Hopkinson St",
    "iso:country":"AU",
    "sg:address":"11 Hopkinson St",
    "sg:city":"South Burnie",
    "sg:classifiers":[
        {
            "category":"Retail",
            "subcategory":"Car Wash",
            "type":"Services"
        }
    ],
    "sg:phone":"+61 3 6431 1944",
    "sg:postcode":"7320",
    "sg:province":"TAS",
    "sg:tags":[
        "truck",
        "cleaning"
    ],
    "wof:name":"Supreme Detailing",
    "wof:placetype":"venue"
},
  "geometry": {"coordinates":[145.91113300000001,-41.062412],"type":"Point"}
}