{
  "type": "Feature",
  "properties": {
    "addr:full":"29 Moorehouse Rd Gillman SA 5013",
    "addr:housenumber":"29",
    "addr:postcode":"5013",
    "addr:street":"Moorehouse Rd",
    "iso:country":"AU",
    "sg:address":"29 Moorehouse Rd",
    "sg:city":"Gillman",
    "sg:classifiers":[
        {
            "category":"Home & Garden",
            "subcategory":"Building Materials",
            "type":"Retail Goods"
        }
    ],
    "sg:phone":"+61 8 8240 3522",
    "sg:postcode":"5013",
    "sg:province":"SA",
    "sg:tags":[
        "retaining",
        "wall"
    ],
    "sg:website":"http://www.tasmaniansandstone.com.au",
    "wof:name":"Tasmanian Sandstone Quarries Pty Ltd",
    "wof:placetype":"venue"
},
  "geometry": {"coordinates":[138.525268555,-34.8129806519],"type":"Point"}
}