{
  "type": "Feature",
  "properties": {
    "iso:country":"AU",
    "sg:address":"183 Lygon St",
    "sg:city":"Brunswick",
    "sg:classifiers":[
        {
            "category":"Autos & Motor Vehicles",
            "subcategory":"Fuel & Gas Station",
            "type":"Retail Goods"
        }
    ],
    "sg:phone":"+61 3 9380 6497",
    "sg:postcode":"3056",
    "sg:province":"VIC",
    "wof:name":"Shell Brunswick Select & Car Wash",
    "wof:placetype":"venue"
},
  "geometry": {"coordinates":[144.97149658199999,-37.7717933655],"type":"Point"}
}