{
  "type": "Feature",
  "properties": {
    "iso:country":"AU",
    "sg:address":"1/ 11 Industrial Drv",
    "sg:city":"Coffs Harbour",
    "sg:classifiers":[
        {
            "category":"Home & Garden",
            "subcategory":"Building Materials",
            "type":"Retail Goods"
        }
    ],
    "sg:phone":"+61 2 6651 8199",
    "sg:postcode":"2450",
    "sg:province":"NSW",
    "sg:tags":[
        "fitting",
        "door"
    ],
    "wof:name":"Mobile Security Doors Coffs Harbour",
    "wof:placetype":"venue"
},
  "geometry": {"coordinates":[153.087646,-30.313799],"type":"Point"}
}