{
  "type": "Feature",
  "properties": {
    "iso:country":"AU",
    "sg:address":"615 Polding St",
    "sg:city":"Wetherill Park",
    "sg:classifiers":[
        {
            "category":"Retail",
            "subcategory":"Car Wash",
            "type":"Services"
        }
    ],
    "sg:phone":"+61 2 9757 4294",
    "sg:postcode":"2164",
    "sg:province":"NSW",
    "sg:tags":[
        "truck",
        "cleaning"
    ],
    "wof:name":"A & K Vehicle Services Pty Ltd",
    "wof:placetype":"venue"
},
  "geometry": {"coordinates":[150.89431762699999,-33.8562812805],"type":"Point"}
}