{
  "type": "Feature",
  "properties": {
    "addr:full":"12 Commercial Rd Mallacoota VIC 3892",
    "addr:housenumber":"12",
    "addr:postcode":"3892",
    "addr:street":"Commercial Rd",
    "iso:country":"AU",
    "sg:address":"12 Commercial Rd",
    "sg:city":"Mallacoota",
    "sg:classifiers":[
        {
            "category":"Manufacturing",
            "subcategory":"Building Materials",
            "type":"Manufacturing & Wholesale Goods"
        }
    ],
    "sg:phone":"+61 3 5158 0605",
    "sg:postcode":"3892",
    "sg:province":"VIC",
    "sg:tags":[
        "concrete",
        "product"
    ],
    "wof:name":"Mallacoota Concrete & Garden Supplies",
    "wof:placetype":"venue"
},
  "geometry": {"coordinates":[149.74623107900001,-37.5564918518],"type":"Point"}
}