{
  "type": "Feature",
  "properties": {
    "addr:full":"182 Lennox St Richmond VIC 3121",
    "addr:housenumber":"182",
    "addr:postcode":"3121",
    "addr:street":"Lennox St",
    "iso:country":"AU",
    "sg:address":"182 Lennox St",
    "sg:city":"Richmond",
    "sg:classifiers":[
        {
            "category":"Health Services",
            "subcategory":"Health Practitioner",
            "type":"Services"
        }
    ],
    "sg:phone":"+61 3 9429 1199",
    "sg:postcode":"3121",
    "sg:province":"VIC",
    "sg:tags":[
        "hypnotherapy"
    ],
    "wof:name":"Colville L Evans",
    "wof:placetype":"venue"
},
  "geometry": {"coordinates":[144.994262695,-37.819103241],"type":"Point"}
}