{
  "type": "Feature",
  "properties": {
    "addr:full":"Suite 6 236 Sandy Bay Rd Sandy Bay TAS 7005",
    "addr:housenumber":"236",
    "addr:postcode":"7005",
    "addr:street":"Sandy Bay Rd",
    "iso:country":"AU",
    "sg:address":"Suite 6 236 Sandy Bay Rd",
    "sg:city":"Sandy Bay",
    "sg:classifiers":[
        {
            "category":"Social Services",
            "subcategory":"Adult Care",
            "type":"Services"
        }
    ],
    "sg:phone":"+61 3 6224 2240",
    "sg:postcode":"7005",
    "sg:province":"TAS",
    "sg:tags":[
        "aged"
    ],
    "wof:name":"Advocacy Tasmania Inc",
    "wof:placetype":"venue"
},
  "geometry": {"coordinates":[147.32838439899999,-42.8958854675],"type":"Point"}
}