{
  "type": "Feature",
  "properties": {
    "addr:full":"34 Hanson St Corryong VIC 3707",
    "addr:housenumber":"34",
    "addr:postcode":"3707",
    "addr:street":"Hanson St",
    "iso:country":"AU",
    "sg:address":"34 Hanson St",
    "sg:city":"Corryong",
    "sg:classifiers":[
        {
            "category":"Banks & Credit Unions",
            "subcategory":"Bank",
            "type":"Services"
        }
    ],
    "sg:phone":"+61 2 6076 1266",
    "sg:postcode":"3707",
    "sg:province":"VIC",
    "wof:name":"WAW Credit Union",
    "wof:placetype":"venue"
},
  "geometry": {"coordinates":[147.90501403799999,-36.1954231262],"type":"Point"}
}