{
  "type": "Feature",
  "properties": {
    "addr:full":"322 Oxley Ave Margate QLD 4019",
    "addr:housenumber":"322",
    "addr:postcode":"4019",
    "addr:street":"Oxley Ave",
    "iso:country":"AU",
    "sg:address":"322 Oxley Ave",
    "sg:city":"Margate",
    "sg:classifiers":[
        {
            "category":"Professional",
            "subcategory":"Accounting & Tax Preparation",
            "type":"Services"
        }
    ],
    "sg:phone":"+61 7 3889 3598",
    "sg:postcode":"4019",
    "sg:province":"QLD",
    "sg:tags":[
        "consultant",
        "taxation"
    ],
    "wof:name":"Carpenter Jill",
    "wof:placetype":"venue"
},
  "geometry": {"coordinates":[153.107620239,-27.2413330078],"type":"Point"}
}