{
  "type": "Feature",
  "properties": {
    "addr:full":"GPO Box 2769 Brisbane QLD 4001",
    "addr:postcode":"4001",
    "iso:country":"AU",
    "sg:address":"GPO Box 2769",
    "sg:city":"Brisbane",
    "sg:classifiers":[
        {
            "category":"Building & Trades",
            "subcategory":"Pest Control",
            "type":"Services"
        }
    ],
    "sg:phone":"+61 1800 815 647",
    "sg:postcode":"4001",
    "sg:province":"QLD",
    "sg:tags":[
        "wholesaler",
        "mfrs",
        "diary"
    ],
    "wof:name":"Franklin Covey",
    "wof:placetype":"venue"
},
  "geometry": {"coordinates":[152.888595581,-27.5975875854],"type":"Point"}
}