{
  "type": "Feature",
  "properties": {
    "addr:full":"Browns Plains Specialist Centr 1 Grand Plaza Drv Browns Plains QLD 4118",
    "addr:housenumber":"1",
    "addr:postcode":"4118",
    "addr:street":"Grand Plaza Drv",
    "iso:country":"AU",
    "sg:address":"Browns Plains Specialist Centr 1 Grand Plaza Drv",
    "sg:city":"Browns Plains",
    "sg:classifiers":[
        {
            "category":"Health Services",
            "subcategory":"Doctor",
            "type":"Services"
        }
    ],
    "sg:phone":"+61 7 5545 3677",
    "sg:postcode":"4118",
    "sg:province":"QLD",
    "sg:tags":[
        "medical",
        "practitioner"
    ],
    "wof:name":"Webb John Dr",
    "wof:placetype":"venue"
},
  "geometry": {"coordinates":[153.036819458,-27.6638469696],"type":"Point"}
}