{
  "type": "Feature",
  "properties": {
    "addr:full":"20 Felton Rd Carlingford NSW 2118",
    "addr:housenumber":"20",
    "addr:postcode":"2118",
    "addr:street":"Felton Rd",
    "iso:country":"AU",
    "sg:address":"20 Felton Rd",
    "sg:city":"Carlingford",
    "sg:classifiers":[
        {
            "category":"Manufacturing",
            "subcategory":"Glass & Minerals",
            "type":"Manufacturing & Wholesale Goods"
        }
    ],
    "sg:phone":"+61 2 9872 3684",
    "sg:postcode":"2118",
    "sg:province":"NSW",
    "sg:tags":[
        "stained"
    ],
    "wof:name":"Carlingford Stained Glass",
    "wof:placetype":"venue"
},
  "geometry": {"coordinates":[151.04258727999999,-33.7831382751],"type":"Point"}
}