{
  "type": "Feature",
  "properties": {
    "addr:full":"380 Pirates Bay Drv Eaglehawk Neck TAS 7179",
    "addr:housenumber":"380",
    "addr:postcode":"7179",
    "addr:street":"Pirates Bay Drv",
    "iso:country":"AU",
    "sg:address":"380 Pirates Bay Drv",
    "sg:city":"Eaglehawk Neck",
    "sg:classifiers":[
        {
            "category":"Travel",
            "subcategory":"Hotels & Motels",
            "type":"Entertainment"
        }
    ],
    "sg:phone":"+61 3 6250 3262",
    "sg:postcode":"7179",
    "sg:province":"TAS",
    "sg:tags":[
        "accommodation"
    ],
    "wof:name":"Lufra Hotel",
    "wof:placetype":"venue"
},
  "geometry": {"coordinates":[147.92962646500001,-43.0100402832],"type":"Point"}
}