{
  "type": "Feature",
  "properties": {
    "iso:country":"AU",
    "sg:address":"23 Boundary Rd",
    "sg:city":"Mordialloc",
    "sg:classifiers":[
        {
            "category":"Building & Trades",
            "subcategory":"Construction",
            "type":"Services"
        }
    ],
    "sg:phone":"+61 3 9587 5310",
    "sg:postcode":"3195",
    "sg:province":"VIC",
    "sg:tags":[
        "concrete",
        "treatment",
        "repair"
    ],
    "wof:name":"Concrete Texturing Services",
    "wof:placetype":"venue"
},
  "geometry": {"coordinates":[145.10333251899999,-38.0090065002],"type":"Point"}
}