{
  "type": "Feature",
  "properties": {
    "iso:country":"AU",
    "sg:address":"520 Anzac Hwy",
    "sg:city":"Glenelg East",
    "sg:classifiers":[
        {
            "category":"Sports & Exercise",
            "subcategory":"Gym",
            "type":"Entertainment"
        }
    ],
    "sg:phone":"+61 8 8295 8488",
    "sg:postcode":"5045",
    "sg:province":"SA",
    "sg:tags":[
        "health",
        "fitness"
    ],
    "wof:name":"Zest Health Clubs",
    "wof:placetype":"venue"
},
  "geometry": {"coordinates":[138.53758199999999,-34.97538],"type":"Point"}
}