{
  "type": "Feature",
  "properties": {
    "addr:full":"50 Mississippi Drv Mandurah WA 6210",
    "addr:housenumber":"50",
    "addr:postcode":"6210",
    "addr:street":"Mississippi Drv",
    "iso:country":"AU",
    "sg:address":"50 Mississippi Drv",
    "sg:city":"Mandurah",
    "sg:classifiers":[
        {
            "category":"Professional",
            "type":"Services"
        }
    ],
    "sg:phone":"+61 8 9535 7475",
    "sg:postcode":"6210",
    "sg:province":"WA",
    "sg:tags":[
        "courier"
    ],
    "wof:name":"Murray Small Freights",
    "wof:placetype":"venue"
},
  "geometry": {"coordinates":[115.74839799999999,-32.535446],"type":"Point"}
}