{
  "type": "Feature",
  "properties": {
    "addr:full":"234 Macquarie St Dubbo NSW 2830",
    "addr:housenumber":"234",
    "addr:postcode":"2830",
    "addr:street":"Macquarie St",
    "iso:country":"AU",
    "sg:address":"234 Macquarie St",
    "sg:city":"Dubbo",
    "sg:classifiers":[
        {
            "category":"Shopping",
            "subcategory":"Clothing, Apparel, & Fashions",
            "type":"Retail Goods"
        }
    ],
    "sg:phone":"+61 2 6884 4755",
    "sg:postcode":"2830",
    "sg:province":"NSW",
    "sg:tags":[
        "menswear"
    ],
    "wof:name":"Bluegum Clothing Co",
    "wof:placetype":"venue"
},
  "geometry": {"coordinates":[148.600875855,-32.2504463196],"type":"Point"}
}