{
  "type": "Feature",
  "properties": {
    "addr:full":"15 Elder St Alice Springs NT 0870",
    "addr:housenumber":"15",
    "addr:postcode":"nt 0870",
    "addr:street":"Elder St",
    "iso:country":"AU",
    "sg:address":"15 Elder St",
    "sg:city":"Alice Springs",
    "sg:classifiers":[
        {
            "category":"Professional",
            "subcategory":"Engineering",
            "type":"Services"
        }
    ],
    "sg:phone":"+61 8 8952 6866",
    "sg:postcode":"0870",
    "sg:province":"NT",
    "sg:tags":[
        "refrigeration",
        "engineer"
    ],
    "wof:name":"Mecair Engineering Pty Ltd",
    "wof:placetype":"venue"
},
  "geometry": {"coordinates":[133.870162964,-23.6983032227],"type":"Point"}
}