{
  "type": "Feature",
  "properties": {
    "addr:full":"80 Railway St Cottesloe WA 6011",
    "addr:housenumber":"80",
    "addr:postcode":"6011",
    "addr:street":"Railway St",
    "iso:country":"AU",
    "sg:address":"80 Railway St",
    "sg:city":"Cottesloe",
    "sg:classifiers":[
        {
            "category":"Social Services",
            "subcategory":"Child Care",
            "type":"Services"
        }
    ],
    "sg:phone":"+61 8 9385 1060",
    "sg:postcode":"6011",
    "sg:province":"WA",
    "wof:name":"Cottesloe Child Care Centre",
    "wof:placetype":"venue"
},
  "geometry": {"coordinates":[115.765258789,-31.9876594543],"type":"Point"}
}