{
  "type": "Feature",
  "properties": {
    "addr:full":"56 Preston St Penrith NSW 2750",
    "addr:housenumber":"56",
    "addr:postcode":"2750",
    "addr:street":"Preston St",
    "iso:country":"AU",
    "sg:address":"56 Preston St",
    "sg:city":"Penrith",
    "sg:classifiers":[
        {
            "category":"Retail",
            "subcategory":"Auto Repair",
            "type":"Services"
        }
    ],
    "sg:phone":"+61 2 4731 2587",
    "sg:postcode":"2750",
    "sg:province":"NSW",
    "sg:tags":[
        "repairer",
        "motor",
        "engineer"
    ],
    "wof:name":"T.T.C. Mechanical Repairs",
    "wof:placetype":"venue"
},
  "geometry": {"coordinates":[150.68370056099999,-33.7628936768],"type":"Point"}
}