{
  "type": "Feature",
  "properties": {
    "addr:full":"10 Ormond Rd East Geelong VIC 3219",
    "addr:housenumber":"10",
    "addr:postcode":"3219",
    "addr:street":"Ormond Rd",
    "iso:country":"AU",
    "sg:address":"10 Ormond Rd",
    "sg:city":"East Geelong",
    "sg:classifiers":[
        {
            "category":"Professional",
            "subcategory":"Accounting & Tax Preparation",
            "type":"Services"
        }
    ],
    "sg:phone":"+61 3 5221 2434",
    "sg:postcode":"3219",
    "sg:province":"VIC",
    "sg:tags":[
        "insulation",
        "wholesaler",
        "material",
        "mfrs"
    ],
    "wof:name":"Australite Pty Ltd",
    "wof:placetype":"venue"
},
  "geometry": {"coordinates":[144.37179565400001,-38.1555213928],"type":"Point"}
}