{
  "type": "Feature",
  "properties": {
    "iso:country":"AU",
    "sg:address":"110 Gardner & Holman Rd",
    "sg:city":"Drouin",
    "sg:classifiers":[
        {
            "category":"Health Services",
            "subcategory":"Doctor",
            "type":"Services"
        }
    ],
    "sg:phone":"+61 419 876 527",
    "sg:postcode":"3818",
    "sg:province":"VIC",
    "sg:tags":[
        "occupational",
        "safety"
    ],
    "wof:name":"Australian Safe T Training",
    "wof:placetype":"venue"
},
  "geometry": {"coordinates":[145.768875,-38.112682],"type":"Point"}
}