{
  "type": "Feature",
  "properties": {
    "addr:full":"QML Specialist Room, Hancock St Sandgate QLD 4017",
    "addr:postcode":"4017",
    "addr:street":"Hancock St",
    "iso:country":"AU",
    "sg:address":"QML Specialist Room, Hancock St",
    "sg:city":"Sandgate",
    "sg:classifiers":[
        {
            "category":"Health Services",
            "subcategory":"Doctor",
            "type":"Services"
        }
    ],
    "sg:phone":"+61 7 3832 6328",
    "sg:postcode":"4017",
    "sg:province":"QLD",
    "sg:tags":[
        "medical",
        "practitioner"
    ],
    "wof:name":"Siu Simon",
    "wof:placetype":"venue"
},
  "geometry": {"coordinates":[153.06788635300001,-27.3207683563],"type":"Point"}
}