{
  "type": "Feature",
  "properties": {
    "addr:full":"Lvl1/ 299 Doncaster Rd Balwyn North VIC 3104",
    "addr:housenumber":"299",
    "addr:postcode":"3104",
    "addr:street":"Doncaster Rd",
    "iso:country":"AU",
    "sg:address":"Lvl1/ 299 Doncaster Rd",
    "sg:city":"Balwyn North",
    "sg:classifiers":[
        {
            "category":"Banks & Credit Unions",
            "subcategory":"Financial Services",
            "type":"Services"
        }
    ],
    "sg:phone":"+61 3 9857 3403",
    "sg:postcode":"3104",
    "sg:province":"VIC",
    "sg:tags":[
        "planning"
    ],
    "wof:name":"Money Tree Financial Planning",
    "wof:placetype":"venue"
},
  "geometry": {"coordinates":[145.09422302199999,-37.7915153503],"type":"Point"}
}