{
  "type": "Feature",
  "properties": {
    "iso:country":"AU",
    "sg:address":"18 Kent St",
    "sg:city":"Rockingham",
    "sg:classifiers":[
        {
            "category":"Personal",
            "type":"Services"
        }
    ],
    "sg:phone":"+61 8 9527 1245",
    "sg:postcode":"6168",
    "sg:province":"WA",
    "sg:tags":[
        "gift"
    ],
    "wof:name":"Rockingham Beach Florist",
    "wof:placetype":"venue"
},
  "geometry": {"coordinates":[115.732986,-32.274826],"type":"Point"}
}