{
  "type": "Feature",
  "properties": {
    "addr:full":"27-33 Perry St Matraville NSW 2036",
    "addr:housenumber":"27-33",
    "addr:postcode":"2036",
    "addr:street":"Perry St",
    "iso:country":"AU",
    "sg:address":"27-33 Perry St",
    "sg:city":"Matraville",
    "sg:classifiers":[
        {
            "category":"Home & Garden",
            "subcategory":"Furniture",
            "type":"Retail Goods"
        }
    ],
    "sg:phone":"+61 2 9666 8788",
    "sg:postcode":"2036",
    "sg:province":"NSW",
    "sg:tags":[
        "business"
    ],
    "wof:name":"General Beton",
    "wof:placetype":"venue"
},
  "geometry": {"coordinates":[151.223480225,-33.9595680237],"type":"Point"}
}