{
  "type": "Feature",
  "properties": {
    "iso:country":"AU",
    "sg:address":"65 High St",
    "sg:city":"Preston",
    "sg:classifiers":[
        {
            "category":"Autos & Motor Vehicles",
            "subcategory":"Fuel & Gas Station",
            "type":"Retail Goods"
        }
    ],
    "sg:phone":"+61 3 9484 6557",
    "sg:postcode":"3072",
    "sg:province":"VIC",
    "wof:name":"Liberty Preston",
    "wof:placetype":"venue"
},
  "geometry": {"coordinates":[145.00276184099999,-37.7448272705],"type":"Point"}
}