{
  "type": "Feature",
  "properties": {
    "iso:country":"AU",
    "sg:address":"28 Roylston St",
    "sg:city":"Paddington",
    "sg:classifiers":[
        {
            "category":"Wholesale",
            "subcategory":"Non-durable Goods",
            "type":"Manufacturing & Wholesale Goods"
        }
    ],
    "sg:phone":"+61 2 9380 4607",
    "sg:postcode":"2021",
    "sg:province":"NSW",
    "sg:tags":[
        "textile"
    ],
    "wof:name":"Domestic Textile Corporation",
    "wof:placetype":"venue"
},
  "geometry": {"coordinates":[151.232788086,-33.8817443848],"type":"Point"}
}