{
  "type": "Feature",
  "properties": {
    "addr:full":"36 Main St Croydon VIC 3136",
    "addr:housenumber":"36",
    "addr:postcode":"3136",
    "addr:street":"Main St",
    "iso:country":"AU",
    "sg:address":"36 Main St",
    "sg:city":"Croydon",
    "sg:classifiers":[
        {
            "category":"Travel",
            "subcategory":"Travel Agent",
            "type":"Entertainment"
        }
    ],
    "sg:phone":"+61 3 9725 4655",
    "sg:postcode":"3136",
    "sg:province":"VIC",
    "sg:tags":[
        "consultant"
    ],
    "wof:name":"Amtrak-U.S.A. Rail",
    "wof:placetype":"venue"
},
  "geometry": {"coordinates":[145.28231811500001,-37.794757843],"type":"Point"}
}