{
  "type": "Feature",
  "properties": {
    "addr:full":"630 Canterbury Rd Belmore NSW 2192",
    "addr:housenumber":"630",
    "addr:postcode":"2192",
    "addr:street":"Canterbury Rd",
    "iso:country":"AU",
    "sg:address":"630 Canterbury Rd",
    "sg:city":"Belmore",
    "sg:classifiers":[
        {
            "category":"Home & Garden",
            "subcategory":"Carpets & Floor Coverings",
            "type":"Retail Goods"
        }
    ],
    "sg:phone":"+61 2 9789 0611",
    "sg:postcode":"2192",
    "sg:province":"NSW",
    "sg:tags":[
        "tile",
        "wall"
    ],
    "wof:name":"Sydney Tiles Centre",
    "wof:placetype":"venue"
},
  "geometry": {"coordinates":[151.09440599999999,-33.922573],"type":"Point"}
}