{
  "type": "Feature",
  "properties": {
    "addr:full":"142 Fenaughty St Kyabram VIC 3620",
    "addr:housenumber":"142",
    "addr:postcode":"3620",
    "addr:street":"Fenaughty St",
    "iso:country":"AU",
    "sg:address":"142 Fenaughty St",
    "sg:city":"Kyabram",
    "sg:classifiers":[
        {
            "category":"Banks & Credit Unions",
            "subcategory":"Financial Services",
            "type":"Services"
        }
    ],
    "sg:phone":"+61 3 5857 0888",
    "sg:postcode":"3620",
    "sg:province":"VIC",
    "sg:tags":[
        "annuity",
        "rollover",
        "superannuation",
        "consultant"
    ],
    "wof:name":"Pinnacle Financial Planning",
    "wof:placetype":"venue"
},
  "geometry": {"coordinates":[145.04937744099999,-36.3147392273],"type":"Point"}
}