{
  "type": "Feature",
  "properties": {
    "addr:full":"7 Cross St Balgowlah NSW 2093",
    "addr:housenumber":"7",
    "addr:postcode":"2093",
    "addr:street":"Cross St",
    "iso:country":"AU",
    "sg:address":"7 Cross St",
    "sg:city":"Balgowlah",
    "sg:classifiers":[
        {
            "category":"Professional",
            "subcategory":"Engineering",
            "type":"Services"
        }
    ],
    "sg:phone":"+61 2 9907 9498",
    "sg:postcode":"2093",
    "sg:province":"NSW",
    "sg:tags":[
        "engineer"
    ],
    "wof:name":"Mon-Structural Design",
    "wof:placetype":"venue"
},
  "geometry": {"coordinates":[151.264282227,-33.7897262573],"type":"Point"}
}