{
  "type": "Feature",
  "properties": {
    "iso:country":"AU",
    "sg:address":"7 Bond St",
    "sg:city":"Mosman",
    "sg:classifiers":[
        {
            "category":"Travel",
            "subcategory":"Travel Agent",
            "type":"Entertainment"
        }
    ],
    "sg:phone":"+61 2 9968 3512",
    "sg:postcode":"2088",
    "sg:province":"NSW",
    "sg:tags":[
        "tour",
        "holiday",
        "adventure"
    ],
    "wof:name":"Walk By Water",
    "wof:placetype":"venue"
},
  "geometry": {"coordinates":[151.23770141599999,-33.8236427307],"type":"Point"}
}