{
  "type": "Feature",
  "properties": {
    "iso:country":"AU",
    "sg:address":"89 Smith St",
    "sg:city":"Wollongong",
    "sg:classifiers":[
        {
            "category":"Health Services",
            "subcategory":"Doctor",
            "type":"Services"
        }
    ],
    "sg:phone":"+61 2 4226 1755",
    "sg:postcode":"2500",
    "sg:province":"NSW",
    "sg:tags":[
        "medical",
        "practitioner"
    ],
    "wof:name":"Illawarra Nuclear Imaging",
    "wof:placetype":"venue"
},
  "geometry": {"coordinates":[150.891144,-34.421272],"type":"Point"}
}