{
  "type": "Feature",
  "properties": {
    "addr:full":"3/ 43 Hewish Rd Croydon VIC 3136",
    "addr:housenumber":"/ 43",
    "addr:postcode":"3136",
    "addr:street":"Hewish Rd",
    "iso:country":"AU",
    "sg:address":"3/ 43 Hewish Rd",
    "sg:city":"Croydon",
    "sg:classifiers":[
        {
            "category":"Retail",
            "subcategory":"Repair Shop",
            "type":"Services"
        }
    ],
    "sg:phone":"+61 3 9725 4533",
    "sg:postcode":"3136",
    "sg:province":"VIC",
    "sg:tags":[
        "windscreen"
    ],
    "wof:name":"Croydon Windscreens",
    "wof:placetype":"venue"
},
  "geometry": {"coordinates":[145.28616332999999,-37.7964859009],"type":"Point"}
}