{
  "type": "Feature",
  "properties": {
    "addr:full":"806 South West Hwy Byford WA 6122",
    "addr:housenumber":"806",
    "addr:postcode":"6122",
    "addr:street":"South West Hwy",
    "iso:country":"AU",
    "sg:address":"806 South West Hwy",
    "sg:city":"Byford",
    "sg:classifiers":[
        {
            "category":"Health Services",
            "subcategory":"Chiropractor",
            "type":"Services"
        }
    ],
    "sg:phone":"+61 8 9525 1828",
    "sg:postcode":"6122",
    "sg:province":"WA",
    "wof:name":"Harris Merri",
    "wof:placetype":"venue"
},
  "geometry": {"coordinates":[116.008422852,-32.2217216492],"type":"Point"}
}