{
  "type": "Feature",
  "properties": {
    "iso:country":"AU",
    "sg:address":"1512 Nudgee Rd",
    "sg:city":"Nudgee Beach",
    "sg:classifiers":[
        {
            "category":"Utilities",
            "subcategory":"Recycling",
            "type":"Services"
        }
    ],
    "sg:phone":"+61 7 3637 9000",
    "sg:postcode":"4014",
    "sg:province":"QLD",
    "wof:name":"Alex Fraser Pty Ltd",
    "wof:placetype":"venue"
},
  "geometry": {"coordinates":[153.10049438499999,-27.3699378967],"type":"Point"}
}