{
  "type": "Feature",
  "properties": {
    "iso:country":"AU",
    "sg:address":"23 Cunningham St",
    "sg:city":"Sale",
    "sg:classifiers":[
        {
            "category":"Shopping",
            "type":"Retail Goods"
        }
    ],
    "sg:phone":"+61 3 5144 2466",
    "sg:postcode":"3850",
    "sg:province":"VIC",
    "sg:tags":[
        "agent",
        "stock"
    ],
    "wof:name":"Landmark Operations Limited",
    "wof:placetype":"venue"
},
  "geometry": {"coordinates":[147.060256958,-38.1073608398],"type":"Point"}
}