{
  "type": "Feature",
  "properties": {
    "addr:full":"100 Nelson Rd Valley View SA 5093",
    "addr:housenumber":"100",
    "addr:postcode":"5093",
    "addr:street":"Nelson Rd",
    "iso:country":"AU",
    "sg:address":"100 Nelson Rd",
    "sg:city":"Valley View",
    "sg:classifiers":[
        {
            "category":"Health Services",
            "subcategory":"Health Practitioner",
            "type":"Services"
        }
    ],
    "sg:phone":"+61 8 8396 5216",
    "sg:postcode":"5093",
    "sg:province":"SA",
    "sg:tags":[
        "homoeopath"
    ],
    "wof:name":"Babu Rajamanickam",
    "wof:placetype":"venue"
},
  "geometry": {"coordinates":[138.662017822,-34.83543396],"type":"Point"}
}