{
  "type": "Feature",
  "properties": {
    "iso:country":"AU",
    "sg:address":"49 Bligh St",
    "sg:city":"Heatley",
    "sg:classifiers":[
        {
            "category":"Utilities",
            "subcategory":"Electric",
            "type":"Services"
        }
    ],
    "sg:phone":"+61 7 4725 2460",
    "sg:postcode":"4814",
    "sg:province":"QLD",
    "sg:tags":[
        "electrical",
        "contractor"
    ],
    "wof:name":"Brite-Lec Pty Ltd",
    "wof:placetype":"venue"
},
  "geometry": {"coordinates":[146.748367,-19.298676],"type":"Point"}
}