{
  "type": "Feature",
  "properties": {
    "iso:country":"AU",
    "sg:address":"55 Gleadow St",
    "sg:city":"Invermay",
    "sg:classifiers":[
        {
            "category":"Building & Trades",
            "subcategory":"Construction",
            "type":"Services"
        }
    ],
    "sg:phone":"+61 3 6333 2500",
    "sg:postcode":"7248",
    "sg:province":"TAS",
    "sg:tags":[
        "contractor"
    ],
    "wof:name":"Fairbrother Pty Ltd",
    "wof:placetype":"venue"
},
  "geometry": {"coordinates":[147.13099670400001,-41.4276046753],"type":"Point"}
}