{
  "type": "Feature",
  "properties": {
    "iso:country":"AU",
    "sg:address":"Hume Hwy",
    "sg:city":"Albury",
    "sg:classifiers":[
        {
            "category":"Professional",
            "subcategory":"Engineering",
            "type":"Services"
        }
    ],
    "sg:phone":"+61 2 6058 3028",
    "sg:postcode":"2640",
    "sg:province":"NSW",
    "sg:tags":[
        "installation",
        "maintenance",
        "engineer"
    ],
    "wof:name":"Silcar Pty Ltd",
    "wof:placetype":"venue"
},
  "geometry": {"coordinates":[146.908813477,-36.0840759277],"type":"Point"}
}