{
  "type": "Feature",
  "properties": {
    "addr:full":"17 Federation Rd Newtown NSW 2042",
    "addr:housenumber":"17",
    "addr:postcode":"2042",
    "addr:street":"Federation Rd",
    "iso:country":"AU",
    "sg:address":"17 Federation Rd",
    "sg:city":"Newtown",
    "sg:classifiers":[
        {
            "category":"Wholesale",
            "subcategory":"Construction Materials",
            "type":"Manufacturing & Wholesale Goods"
        }
    ],
    "sg:phone":"+61 2 9516 4922",
    "sg:postcode":"2042",
    "sg:province":"NSW",
    "sg:tags":[
        "wholesaler",
        "lighting",
        "mfrs",
        "accessory"
    ],
    "wof:name":"Transco",
    "wof:placetype":"venue"
},
  "geometry": {"coordinates":[151.178223,-33.893517],"type":"Point"}
}