{
  "type": "Feature",
  "properties": {
    "iso:country":"AU",
    "sg:address":"16 William St",
    "sg:city":"Narrandera",
    "sg:classifiers":[
        {
            "category":"Personal",
            "subcategory":"Massage",
            "type":"Services"
        }
    ],
    "sg:phone":"+61 2 6959 2501",
    "sg:postcode":"2700",
    "sg:province":"NSW",
    "sg:tags":[
        "therapy"
    ],
    "wof:name":"Hutchinson Karen",
    "wof:placetype":"venue"
},
  "geometry": {"coordinates":[146.55917358400001,-34.7424125671],"type":"Point"}
}