{
  "type": "Feature",
  "properties": {
    "addr:full":"107 Otho St Inverell NSW 2360",
    "addr:housenumber":"107",
    "addr:postcode":"2360",
    "addr:street":"Otho St",
    "iso:country":"AU",
    "sg:address":"107 Otho St",
    "sg:city":"Inverell",
    "sg:classifiers":[
        {
            "category":"Building & Trades",
            "subcategory":"Locksmith",
            "type":"Services"
        }
    ],
    "sg:phone":"+61 2 6721 0995",
    "sg:postcode":"2360",
    "sg:province":"NSW",
    "sg:tags":[
        "lock"
    ],
    "wof:name":"Sapphire City Security",
    "wof:placetype":"venue"
},
  "geometry": {"coordinates":[151.11346435600001,-29.7753810883],"type":"Point"}
}