{
  "type": "Feature",
  "properties": {
    "addr:full":"Duporth Ave Maroochydore QLD 4558",
    "addr:postcode":"4558",
    "addr:street":"Duporth Ave",
    "iso:country":"AU",
    "sg:address":"Duporth Ave",
    "sg:city":"Maroochydore",
    "sg:classifiers":[
        {
            "category":"Cafe",
            "type":"Food & Drink"
        }
    ],
    "sg:phone":"+61 7 5443 2517",
    "sg:postcode":"4558",
    "sg:province":"QLD",
    "wof:name":"Chatters Carvery & Coffee House",
    "wof:placetype":"venue"
},
  "geometry": {"coordinates":[153.08404540999999,-26.6444015503],"type":"Point"}
}