{
  "type": "Feature",
  "properties": {
    "addr:full":"493 Cross Keys Rd Cavan SA 5094",
    "addr:housenumber":"493",
    "addr:postcode":"5094",
    "addr:street":"Cross Keys Rd",
    "iso:country":"AU",
    "sg:address":"493 Cross Keys Rd",
    "sg:city":"Cavan",
    "sg:classifiers":[
        {
            "category":"Home & Garden",
            "subcategory":"Hardware",
            "type":"Retail Goods"
        }
    ],
    "sg:phone":"+61 8 8262 9277",
    "sg:postcode":"5094",
    "sg:province":"SA",
    "sg:tags":[
        "pipe",
        "fitting",
        "plastic"
    ],
    "wof:name":"Pipe King",
    "wof:placetype":"venue"
},
  "geometry": {"coordinates":[138.60040283199999,-34.8260345459],"type":"Point"}
}