{
  "type": "Feature",
  "properties": {
    "addr:full":"Great Ocean Rd Aireys Inlet VIC 3231",
    "addr:postcode":"3231",
    "addr:street":"Ocean Rd",
    "iso:country":"AU",
    "sg:address":"Great Ocean Rd",
    "sg:city":"Aireys Inlet",
    "sg:classifiers":[
        {
            "category":"Travel",
            "subcategory":"Hotels & Motels",
            "type":"Entertainment"
        }
    ],
    "sg:phone":"+61 3 5289 6270",
    "sg:postcode":"3231",
    "sg:province":"VIC",
    "sg:tags":[
        "accommodation"
    ],
    "wof:name":"Aireys Inlet Hotel",
    "wof:placetype":"venue"
},
  "geometry": {"coordinates":[144.10638427699999,-38.46043396],"type":"Point"}
}