{
  "type": "Feature",
  "properties": {
    "addr:full":"97 Narangba Rd Petrie QLD 4502",
    "addr:housenumber":"97",
    "addr:postcode":"4502",
    "addr:street":"Narangba Rd",
    "iso:country":"AU",
    "sg:address":"97 Narangba Rd",
    "sg:city":"Petrie",
    "sg:classifiers":[
        {
            "category":"Retail",
            "subcategory":"Auto Repair",
            "type":"Services"
        }
    ],
    "sg:phone":"+61 7 3285 2064",
    "sg:postcode":"4502",
    "sg:province":"QLD",
    "sg:tags":[
        "repairer",
        "motor",
        "engineer"
    ],
    "wof:name":"Gregs Garage",
    "wof:placetype":"venue"
},
  "geometry": {"coordinates":[152.97198486299999,-27.24751091],"type":"Point"}
}