{
  "type": "Feature",
  "properties": {
    "addr:full":"Offce4/ 5 Blackwood St North Melbourne VIC 3051",
    "addr:housenumber":"5",
    "addr:postcode":"3051",
    "addr:street":"Blackwood St",
    "iso:country":"AU",
    "sg:address":"Offce4/ 5 Blackwood St",
    "sg:city":"North Melbourne",
    "sg:classifiers":[
        {
            "category":"Arts & Performance",
            "subcategory":"Art Gallery",
            "type":"Entertainment"
        }
    ],
    "sg:phone":"+61 3 9329 9422",
    "sg:postcode":"3051",
    "sg:province":"VIC",
    "wof:name":"Next Wave Festival Inc",
    "wof:placetype":"venue"
},
  "geometry": {"coordinates":[144.95445251500001,-37.8016014099],"type":"Point"}
}