{
  "type": "Feature",
  "properties": {
    "addr:full":"160a Percy St Portland VIC 3305",
    "addr:housenumber":"160a",
    "addr:postcode":"3305",
    "addr:street":"Percy St",
    "iso:country":"AU",
    "sg:address":"160a Percy St",
    "sg:city":"Portland",
    "sg:classifiers":[
        {
            "category":"Retail",
            "subcategory":"Veterinary Services",
            "type":"Services"
        }
    ],
    "sg:phone":"+61 3 5523 4900",
    "sg:postcode":"3305",
    "sg:province":"VIC",
    "sg:tags":[
        "surgeon"
    ],
    "wof:name":"Miller Ann",
    "wof:placetype":"venue"
},
  "geometry": {"coordinates":[141.60418701200001,-38.3402290344],"type":"Point"}
}