{
  "type": "Feature",
  "properties": {
    "addr:full":"4 Moore Crs Millgrove VIC 3799",
    "addr:housenumber":"4",
    "addr:postcode":"3799",
    "addr:street":"Moore Crs",
    "iso:country":"AU",
    "sg:address":"4 Moore Crs",
    "sg:city":"Millgrove",
    "sg:classifiers":[
        {
            "category":"Building & Trades",
            "subcategory":"Construction",
            "type":"Services"
        }
    ],
    "sg:phone":"+61 401 694 390",
    "sg:postcode":"3799",
    "sg:province":"VIC",
    "sg:tags":[
        "fencing",
        "contractor"
    ],
    "wof:name":"Butefencing",
    "wof:placetype":"venue"
},
  "geometry": {"coordinates":[145.656906128,-37.7531394958],"type":"Point"}
}