{
  "type": "Feature",
  "properties": {
    "addr:full":"502-506 Plenty Rd Preston East VIC 3072",
    "addr:housenumber":"502-506",
    "addr:postcode":"3072",
    "addr:street":"Plenty Rd",
    "iso:country":"AU",
    "sg:address":"502-506 Plenty Rd",
    "sg:city":"Preston East",
    "sg:classifiers":[
        {
            "category":"Food & Beverages",
            "subcategory":"Groceries & Convenience Stores",
            "type":"Retail Goods"
        }
    ],
    "sg:phone":"+61 3 9470 2280",
    "sg:postcode":"3072",
    "sg:province":"VIC",
    "wof:name":"Foodies",
    "wof:placetype":"venue"
},
  "geometry": {"coordinates":[145.004440308,-37.7413063049],"type":"Point"}
}