{
  "type": "Feature",
  "properties": {
    "iso:country":"AU",
    "sg:address":"86 Ogden St",
    "sg:city":"Townsville",
    "sg:classifiers":[
        {
            "category":"Real Estate",
            "subcategory":"Real Estate Agent",
            "type":"Services"
        }
    ],
    "sg:phone":"+61 7 4724 2916",
    "sg:postcode":"4810",
    "sg:province":"QLD",
    "wof:name":"Metro Quays Property Management",
    "wof:placetype":"venue"
},
  "geometry": {"coordinates":[146.817505,-19.260292],"type":"Point"}
}