{
  "type": "Feature",
  "properties": {
    "iso:country":"AU",
    "sg:address":"303- 305 Draper St",
    "sg:city":"Cairns",
    "sg:classifiers":[
        {
            "category":"Train Station",
            "subcategory":"Rail",
            "type":"Transportation"
        }
    ],
    "sg:phone":"+61 7 4051 3512",
    "sg:postcode":"4870",
    "sg:province":"QLD",
    "sg:tags":[
        "ship",
        "chandler"
    ],
    "wof:name":"Mitchell's Marine",
    "wof:placetype":"venue"
},
  "geometry": {"coordinates":[145.76625060999999,-16.9240608215],"type":"Point"}
}