{
  "type": "Feature",
  "properties": {
    "addr:full":"321 Maribyrnong Rd Ascot Vale VIC 3032",
    "addr:housenumber":"321",
    "addr:postcode":"3032",
    "addr:street":"Maribyrnong Rd",
    "iso:country":"AU",
    "sg:address":"321 Maribyrnong Rd",
    "sg:city":"Ascot Vale",
    "sg:classifiers":[
        {
            "category":"Shopping",
            "subcategory":"Stationery & Office Supplies",
            "type":"Retail Goods"
        }
    ],
    "sg:phone":"+61 3 9370 6895",
    "sg:postcode":"3032",
    "sg:province":"VIC",
    "sg:tags":[
        "equipment",
        "badge",
        "making"
    ],
    "wof:name":"Persinality Trophies",
    "wof:placetype":"venue"
},
  "geometry": {"coordinates":[144.92051699999999,-37.772182],"type":"Point"}
}