{
  "type": "Feature",
  "properties": {
    "addr:full":"460 Church St Parramatta NSW 2150",
    "addr:housenumber":"460",
    "addr:postcode":"2150",
    "addr:street":"Church St",
    "iso:country":"AU",
    "sg:address":"460 Church St",
    "sg:city":"Parramatta",
    "sg:classifiers":[
        {
            "category":"Health Services",
            "subcategory":"Chiropractor",
            "type":"Services"
        }
    ],
    "sg:phone":"+61 2 9890 7111",
    "sg:postcode":"2150",
    "sg:province":"NSW",
    "wof:name":"Better Backs",
    "wof:placetype":"venue"
},
  "geometry": {"coordinates":[151.00601196299999,-33.8055000305],"type":"Point"}
}