{
  "type": "Feature",
  "properties": {
    "addr:full":"Twin Pines Chittering Rd Lower Chittering WA 6084",
    "addr:postcode":"6084",
    "addr:street":"Chittering Rd",
    "iso:country":"AU",
    "sg:address":"Twin Pines Chittering Rd",
    "sg:city":"Lower Chittering",
    "sg:classifiers":[
        {
            "category":"Building & Trades",
            "subcategory":"Construction",
            "type":"Services"
        }
    ],
    "sg:phone":"+61 427 440 564",
    "sg:postcode":"6084",
    "sg:province":"WA",
    "sg:tags":[
        "earth",
        "excavating",
        "moving",
        "contractor"
    ],
    "wof:name":"Read H C & L L",
    "wof:placetype":"venue"
},
  "geometry": {"coordinates":[116.08644866900001,-31.5654983521],"type":"Point"}
}