{
  "type": "Feature",
  "properties": {
    "iso:country":"AU",
    "sg:address":"Paris Rd",
    "sg:city":"Australind",
    "sg:classifiers":[
        {
            "category":"Social Services",
            "subcategory":"Child Care",
            "type":"Services"
        }
    ],
    "sg:phone":"+61 8 9797 1844",
    "sg:postcode":"6233",
    "sg:province":"WA",
    "sg:tags":[
        "support",
        "health"
    ],
    "wof:name":"Child Health Services",
    "wof:placetype":"venue"
},
  "geometry": {"coordinates":[115.718658,-33.277561],"type":"Point"}
}