{
  "type": "Feature",
  "properties": {
    "addr:full":"30 Araluen St Morley WA 6062",
    "addr:housenumber":"30",
    "addr:postcode":"6062",
    "addr:street":"Araluen St",
    "iso:country":"AU",
    "sg:address":"30 Araluen St",
    "sg:city":"Morley",
    "sg:classifiers":[
        {
            "category":"Professional",
            "type":"Services"
        }
    ],
    "sg:phone":"+61 8 9379 3328",
    "sg:postcode":"6062",
    "sg:province":"WA",
    "sg:tags":[
        "transport"
    ],
    "wof:name":"Brandstater Enterprises",
    "wof:placetype":"venue"
},
  "geometry": {"coordinates":[115.921638489,-31.8865242004],"type":"Point"}
}