{
  "type": "Feature",
  "properties": {
    "iso:country":"AU",
    "sg:address":"16 Bosworth Rd",
    "sg:city":"Woolgoolga",
    "sg:classifiers":[
        {
            "category":"Autos & Motor Vehicles",
            "subcategory":"Auto Supplies",
            "type":"Retail Goods"
        }
    ],
    "sg:phone":"+61 2 6654 2466",
    "sg:postcode":"2456",
    "sg:province":"NSW",
    "sg:tags":[
        "oil",
        "spirit"
    ],
    "wof:name":"Bowen Petroleum Services",
    "wof:placetype":"venue"
},
  "geometry": {"coordinates":[153.194229,-30.125305],"type":"Point"}
}