{
  "type": "Feature",
  "properties": {
    "iso:country":"AU",
    "sg:address":"9 Alloway Pl",
    "sg:city":"Armadale",
    "sg:classifiers":[
        {
            "category":"Building & Trades",
            "subcategory":"Construction",
            "type":"Services"
        }
    ],
    "sg:phone":"+61 8 9497 3435",
    "sg:postcode":"6112",
    "sg:province":"WA",
    "sg:tags":[
        "installation",
        "air conditioning"
    ],
    "wof:name":"Armadale Kelmscott Refrigeration",
    "wof:placetype":"venue"
},
  "geometry": {"coordinates":[115.99594116199999,-32.1339035034],"type":"Point"}
}