{
  "type": "Feature",
  "properties": {
    "addr:full":"Ste 907/ 6A Glen St Milsons Point NSW 2061",
    "addr:housenumber":"/ 6a",
    "addr:postcode":"2061",
    "addr:street":"Glen St",
    "iso:country":"AU",
    "sg:address":"Ste 907/ 6A Glen St",
    "sg:city":"Milsons Point",
    "sg:classifiers":[
        {
            "category":"Wholesale",
            "subcategory":"Metals & Minerals",
            "type":"Manufacturing & Wholesale Goods"
        }
    ],
    "sg:phone":"+61 2 9957 2759",
    "sg:postcode":"2061",
    "sg:province":"NSW",
    "sg:tags":[
        "steel",
        "merchant"
    ],
    "wof:name":"Capital Steel & Pipe Pty Ltd",
    "wof:placetype":"venue"
},
  "geometry": {"coordinates":[151.210494995,-33.8475494385],"type":"Point"}
}