{
  "type": "Feature",
  "properties": {
    "addr:full":"29 Flanigan St Wangaratta VIC 3677",
    "addr:housenumber":"29",
    "addr:postcode":"3677",
    "addr:street":"Flanigan St",
    "iso:country":"AU",
    "sg:address":"29 Flanigan St",
    "sg:city":"Wangaratta",
    "sg:classifiers":[
        {
            "category":"Social Services",
            "subcategory":"Child Care",
            "type":"Services"
        }
    ],
    "sg:phone":"+61 3 5722 0869",
    "sg:postcode":"3677",
    "sg:province":"VIC",
    "sg:tags":[
        "support",
        "health"
    ],
    "wof:name":"Wangaratta Maternal & Child Health Centres",
    "wof:placetype":"venue"
},
  "geometry": {"coordinates":[146.31672668499999,-36.3721694946],"type":"Point"}
}