{
  "type": "Feature",
  "properties": {
    "iso:country":"AU",
    "sg:address":"77 Mathew Flinders Ave",
    "sg:city":"Endeavour Hills",
    "sg:classifiers":[
        {
            "category":"Building & Trades",
            "subcategory":"Construction",
            "type":"Services"
        }
    ],
    "sg:phone":"+61 418 346 665",
    "sg:postcode":"3802",
    "sg:province":"VIC",
    "sg:tags":[
        "stonework",
        "stone",
        "mason"
    ],
    "wof:name":"Jalva Enterprises",
    "wof:placetype":"venue"
},
  "geometry": {"coordinates":[145.25813293499999,-37.9756813049],"type":"Point"}
}