{
  "type": "Feature",
  "properties": {
    "iso:country":"AU",
    "sg:address":"25 Ramah Ave",
    "sg:city":"Mt Ousley",
    "sg:classifiers":[
        {
            "category":"Professional",
            "subcategory":"Business Services",
            "type":"Services"
        }
    ],
    "sg:phone":"+61 419 638 022",
    "sg:postcode":"2519",
    "sg:province":"NSW",
    "sg:tags":[
        "drafting"
    ],
    "wof:name":"Panorama Drafting Services",
    "wof:placetype":"venue"
},
  "geometry": {"coordinates":[150.876724,-34.397236],"type":"Point"}
}