{
  "type": "Feature",
  "properties": {
    "addr:full":"Shp 5/ 20 Creek Rd Mt Gravatt QLD 4122",
    "addr:housenumber":"/ 20",
    "addr:postcode":"4122",
    "addr:street":"Creek Rd",
    "iso:country":"AU",
    "sg:address":"Shp 5/ 20 Creek Rd",
    "sg:city":"Mt Gravatt",
    "sg:classifiers":[
        {
            "category":"Professional",
            "subcategory":"Computer Services",
            "type":"Services"
        }
    ],
    "sg:phone":"+61 7 3219 2048",
    "sg:postcode":"4122",
    "sg:province":"QLD",
    "sg:tags":[
        "repairs",
        "upgrade",
        "equipment"
    ],
    "wof:name":"Brisbane Complete Computing",
    "wof:placetype":"venue"
},
  "geometry": {"coordinates":[153.080444336,-27.5386505127],"type":"Point"}
}