{
  "type": "Feature",
  "properties": {
    "iso:country":"AU",
    "sg:address":"Dreyfus St",
    "sg:city":"Bridgetown",
    "sg:classifiers":[
        {
            "category":"Manufacturing",
            "subcategory":"Furniture",
            "type":"Manufacturing & Wholesale Goods"
        }
    ],
    "sg:phone":"+61 8 9761 2117",
    "sg:postcode":"6255",
    "sg:province":"WA",
    "sg:tags":[
        "builder",
        "designer",
        "custom"
    ],
    "wof:name":"Holst Glen Furniture",
    "wof:placetype":"venue"
},
  "geometry": {"coordinates":[116.12776184099999,-33.9515686035],"type":"Point"}
}