{
  "type": "Feature",
  "properties": {
    "iso:country":"AU",
    "sg:address":"10 Stack St",
    "sg:city":"Fremantle",
    "sg:classifiers":[
        {
            "category":"Manufacturing",
            "subcategory":"Motor Vehicles & Parts",
            "type":"Manufacturing & Wholesale Goods"
        }
    ],
    "sg:phone":"+61 8 9335 9211",
    "sg:postcode":"6160",
    "sg:province":"WA",
    "sg:tags":[
        "engine",
        "equipment",
        "diesel"
    ],
    "wof:name":"Perkins",
    "wof:placetype":"venue"
},
  "geometry": {"coordinates":[115.763763,-32.055721],"type":"Point"}
}