{
  "type": "Feature",
  "properties": {
    "addr:full":"5/ 106 City Rd Beenleigh QLD 4207",
    "addr:housenumber":"/ 106",
    "addr:postcode":"4207",
    "addr:street":"City Rd",
    "iso:country":"AU",
    "sg:address":"5/ 106 City Rd",
    "sg:city":"Beenleigh",
    "sg:classifiers":[
        {
            "category":"Real Estate",
            "subcategory":"Real Estate Agent",
            "type":"Services"
        }
    ],
    "sg:phone":"+61 7 3807 5600",
    "sg:postcode":"4207",
    "sg:province":"QLD",
    "wof:name":"Albert Valley Properties",
    "wof:placetype":"venue"
},
  "geometry": {"coordinates":[153.199584961,-27.717710495],"type":"Point"}
}