{
  "type": "Feature",
  "properties": {
    "iso:country":"AU",
    "sg:address":"151 Mt Alexander Rd",
    "sg:city":"Flemington",
    "sg:classifiers":[
        {
            "category":"Wholesale",
            "subcategory":"Machinery & Supplies",
            "type":"Manufacturing & Wholesale Goods"
        }
    ],
    "sg:phone":"+61 1800 659 829",
    "sg:postcode":"3031",
    "sg:province":"VIC",
    "sg:tags":[
        "instrument"
    ],
    "wof:name":"Datcon Instruments",
    "wof:placetype":"venue"
},
  "geometry": {"coordinates":[144.934433,-37.782959],"type":"Point"}
}