{
  "type": "Feature",
  "properties": {
    "iso:country":"AU",
    "sg:address":"3 Lytton Rd",
    "sg:city":"East Brisbane",
    "sg:classifiers":[
        {
            "category":"Travel",
            "subcategory":"Hotels & Motels",
            "type":"Entertainment"
        }
    ],
    "sg:phone":"+61 7 3391 5772",
    "sg:postcode":"4169",
    "sg:province":"QLD",
    "sg:tags":[
        "accommodation"
    ],
    "wof:name":"Shafston Hotel",
    "wof:placetype":"venue"
},
  "geometry": {"coordinates":[153.04394531200001,-27.4793052673],"type":"Point"}
}