{
  "type": "Feature",
  "properties": {
    "addr:full":"Unit 12/ 16-24 Waratah Rd Kirrawee NSW 2232",
    "addr:housenumber":"/ 16-24",
    "addr:postcode":"2232",
    "addr:street":"Waratah Rd",
    "iso:country":"AU",
    "sg:address":"Unit 12/ 16-24 Waratah Rd",
    "sg:city":"Kirrawee",
    "sg:classifiers":[
        {
            "category":"Banks & Credit Unions",
            "subcategory":"Financial Services",
            "type":"Services"
        }
    ],
    "sg:phone":"+61 1300 728 248",
    "sg:postcode":"2232",
    "sg:province":"NSW",
    "sg:tags":[
        "loan",
        "finance",
        "mortgage"
    ],
    "wof:name":"Professional Mortgage Providers Pty Ltd",
    "wof:placetype":"venue"
},
  "geometry": {"coordinates":[151.07945251500001,-34.0291786194],"type":"Point"}
}