{
  "type": "Feature",
  "properties": {
    "addr:full":"72 Willard Rd Capalaba QLD 4157",
    "addr:housenumber":"72",
    "addr:postcode":"4157",
    "addr:street":"Willard Rd",
    "iso:country":"AU",
    "sg:address":"72 Willard Rd",
    "sg:city":"Capalaba",
    "sg:classifiers":[
        {
            "category":"Arena",
            "subcategory":"Sports Club",
            "type":"Entertainment"
        }
    ],
    "sg:phone":"+61 7 3823 3010",
    "sg:postcode":"4157",
    "sg:province":"QLD",
    "sg:tags":[
        "defence",
        "supply",
        "self",
        "instruction",
        "martial art"
    ],
    "wof:name":"Frontline Martial Arts",
    "wof:placetype":"venue"
},
  "geometry": {"coordinates":[153.20787048299999,-27.5160198212],"type":"Point"}
}