{
  "type": "Feature",
  "properties": {
    "iso:country":"AU",
    "sg:address":"12/ 43 Bayldon Rd",
    "sg:city":"Queanbeyan",
    "sg:classifiers":[
        {
            "category":"Shopping",
            "subcategory":"Party Supplies",
            "type":"Retail Goods"
        }
    ],
    "sg:phone":"+61 2 6297 7540",
    "sg:postcode":"2620",
    "sg:province":"ACT",
    "sg:tags":[
        "children's"
    ],
    "wof:name":"Jelly Bean Amusements",
    "wof:placetype":"venue"
},
  "geometry": {"coordinates":[149.20466613799999,-35.3546447754],"type":"Point"}
}