{
  "type": "Feature",
  "properties": {
    "addr:full":"432 Yarrie Lake Rd Narrabri NSW 2390",
    "addr:housenumber":"432",
    "addr:postcode":"2390",
    "addr:street":"Yarrie Lake Rd",
    "iso:country":"AU",
    "sg:address":"432 Yarrie Lake Rd",
    "sg:city":"Narrabri",
    "sg:classifiers":[
        {
            "category":"Professional",
            "subcategory":"Engineering",
            "type":"Services"
        }
    ],
    "sg:phone":"+61 429 333 550",
    "sg:postcode":"2390",
    "sg:province":"NSW",
    "sg:tags":[
        "consulting",
        "engineer"
    ],
    "wof:name":"Gale Engineering Consultants",
    "wof:placetype":"venue"
},
  "geometry": {"coordinates":[149.766845703,-30.3389701843],"type":"Point"}
}