{
  "type": "Feature",
  "properties": {
    "iso:country":"AU",
    "sg:address":"50 Kenthurst Rd St",
    "sg:city":"Ives",
    "sg:classifiers":[
        {
            "category":"Education",
            "subcategory":"Music School",
            "type":"Public Place"
        }
    ],
    "sg:phone":"+61 2 9402 5756",
    "sg:postcode":"2075",
    "sg:province":"NSW",
    "sg:tags":[
        "choir",
        "bands",
        "orchestra"
    ],
    "wof:name":"Chanelle Players",
    "wof:placetype":"venue"
},
  "geometry": {"coordinates":[151.16355895999999,-33.7228088379],"type":"Point"}
}