{
  "type": "Feature",
  "properties": {
    "addr:full":"Shp2/ 2043 Albany Hwy Maddington WA 6109",
    "addr:housenumber":"2043",
    "addr:postcode":"6109",
    "addr:street":"Albany Hwy",
    "iso:country":"AU",
    "sg:address":"Shp2/ 2043 Albany Hwy",
    "sg:city":"Maddington",
    "sg:classifiers":[
        {
            "category":"Food & Beverages",
            "subcategory":"Fruits & Vegetables",
            "type":"Retail Goods"
        }
    ],
    "sg:phone":"+61 8 9452 2136",
    "sg:postcode":"6109",
    "sg:province":"WA",
    "sg:tags":[
        "greengrocer",
        "fruiterer"
    ],
    "wof:name":"Maddington Fresh Market",
    "wof:placetype":"venue"
},
  "geometry": {"coordinates":[115.993751526,-32.0588912964],"type":"Point"}
}