{
  "type": "Feature",
  "properties": {
    "addr:full":"UE3, 3- 29 Birnie Lidcombe NSW 2141",
    "addr:housenumber":"3 29",
    "addr:postcode":"2141",
    "addr:street":"Ue3",
    "iso:country":"AU",
    "sg:address":"UE3, 3- 29",
    "sg:city":"Birnie Lidcombe",
    "sg:classifiers":[
        {
            "category":"Manufacturing",
            "subcategory":"Food",
            "type":"Manufacturing & Wholesale Goods"
        }
    ],
    "sg:phone":"+61 2 9911 8501",
    "sg:postcode":"2141",
    "sg:province":"NSW",
    "sg:tags":[
        "function",
        "catering"
    ],
    "wof:name":"Steve Mobile Catering",
    "wof:placetype":"venue"
},
  "geometry": {"coordinates":[151.056762695,-33.8595581055],"type":"Point"}
}