{
  "type": "Feature",
  "properties": {
    "iso:country":"AU",
    "sg:address":"Ronald Ave",
    "sg:city":"Harbord",
    "sg:classifiers":[
        {
            "category":"Building & Trades",
            "subcategory":"Cleaning & Sanitation",
            "type":"Services"
        }
    ],
    "sg:phone":"+61 2 9905 1230",
    "sg:postcode":"2096",
    "sg:province":"NSW",
    "sg:tags":[
        "industrial",
        "commercial",
        "contractor"
    ],
    "wof:name":"Netmark Health Services",
    "wof:placetype":"venue"
},
  "geometry": {"coordinates":[151.29075622600001,-33.7769126892],"type":"Point"}
}