{
  "type": "Feature",
  "properties": {
    "iso:country":"AU",
    "sg:address":"Suite 5a, 4-6 Duke St",
    "sg:city":"Windsor",
    "sg:classifiers":[
        {
            "category":"Professional",
            "subcategory":"Art Services",
            "type":"Services"
        }
    ],
    "sg:phone":"+61 3 9510 7455",
    "sg:postcode":"3181",
    "sg:province":"VIC",
    "sg:tags":[
        "graphic",
        "designer"
    ],
    "wof:name":"Visible Ink Design",
    "wof:placetype":"venue"
},
  "geometry": {"coordinates":[144.993286133,-37.853969574],"type":"Point"}
}