{
  "type": "Feature",
  "properties": {
    "addr:full":"20 Belinda St Gerringong NSW 2534",
    "addr:housenumber":"20",
    "addr:postcode":"2534",
    "addr:street":"Belinda St",
    "iso:country":"AU",
    "sg:address":"20 Belinda St",
    "sg:city":"Gerringong",
    "sg:classifiers":[
        {
            "category":"Retail",
            "subcategory":"Veterinary Services",
            "type":"Services"
        }
    ],
    "sg:phone":"+61 2 4234 1317",
    "sg:postcode":"2534",
    "sg:province":"NSW",
    "sg:tags":[
        "surgeon"
    ],
    "wof:name":"MEDENIS A J & ASSOCIATES",
    "wof:placetype":"venue"
},
  "geometry": {"coordinates":[150.823394775,-34.7465591431],"type":"Point"}
}