{
  "type": "Feature",
  "properties": {
    "addr:full":"12 Hoskins Rd Landsdale WA 6065",
    "addr:housenumber":"12",
    "addr:postcode":"6065",
    "addr:street":"Hoskins Rd",
    "iso:country":"AU",
    "sg:address":"12 Hoskins Rd",
    "sg:city":"Landsdale",
    "sg:classifiers":[
        {
            "category":"Manufacturing",
            "subcategory":"Retail Goods",
            "type":"Manufacturing & Wholesale Goods"
        }
    ],
    "sg:phone":"+61 8 9302 7000",
    "sg:postcode":"6065",
    "sg:province":"WA",
    "sg:tags":[
        "merchant",
        "pump",
        "mfrs"
    ],
    "wof:name":"Allight",
    "wof:placetype":"venue"
},
  "geometry": {"coordinates":[115.839172363,-31.8038406372],"type":"Point"}
}