{
  "type": "Feature",
  "properties": {
    "iso:country":"AU",
    "sg:address":"176A Campbell St",
    "sg:city":"Hobart",
    "sg:classifiers":[
        {
            "category":"Professional",
            "subcategory":"Printing & Photocopies",
            "type":"Services"
        }
    ],
    "sg:phone":"+61 3 6231 4470",
    "sg:postcode":"7000",
    "sg:province":"TAS",
    "sg:tags":[
        "equipment",
        "plan"
    ],
    "wof:name":"Digital Office Solutions",
    "wof:placetype":"venue"
},
  "geometry": {"coordinates":[147.32322692899999,-42.8744773865],"type":"Point"}
}