{
  "type": "Feature",
  "properties": {
    "addr:full":"Oxley State School Bannerman St Oxley QLD 4075",
    "addr:postcode":"4075",
    "addr:street":"St",
    "iso:country":"AU",
    "sg:address":"Oxley State School Bannerman St",
    "sg:city":"Oxley",
    "sg:classifiers":[
        {
            "category":"Education",
            "subcategory":"Dance Studio",
            "type":"Public Place"
        }
    ],
    "sg:phone":"+61 7 3879 8132",
    "sg:postcode":"4075",
    "sg:province":"QLD",
    "sg:tags":[
        "venue",
        "tuition"
    ],
    "wof:name":"Belly Dance &#034;Aphrodities Palace&#034;",
    "wof:placetype":"venue"
},
  "geometry": {"coordinates":[152.982955933,-27.5624732971],"type":"Point"}
}