{
  "type": "Feature",
  "properties": {
    "addr:full":"72 Scott St Warracknabeal VIC 3393",
    "addr:housenumber":"72",
    "addr:postcode":"3393",
    "addr:street":"Scott St",
    "iso:country":"AU",
    "sg:address":"72 Scott St",
    "sg:city":"Warracknabeal",
    "sg:classifiers":[
        {
            "category":"Travel",
            "subcategory":"Travel Agent",
            "type":"Entertainment"
        }
    ],
    "sg:phone":"+61 3 5398 2388",
    "sg:postcode":"3393",
    "sg:province":"VIC",
    "sg:tags":[
        "consultant"
    ],
    "wof:name":"Travelscene Warracknabeal",
    "wof:placetype":"venue"
},
  "geometry": {"coordinates":[142.39483642600001,-36.2496604919],"type":"Point"}
}