{
  "type": "Feature",
  "properties": {
    "addr:full":"1 Pickering Brook Rd Pickering Brook WA 6076",
    "addr:housenumber":"1",
    "addr:postcode":"6076",
    "addr:street":"Pickering Brook Rd",
    "iso:country":"AU",
    "sg:address":"1 Pickering Brook Rd",
    "sg:city":"Pickering Brook",
    "sg:classifiers":[
        {
            "category":"Retail",
            "subcategory":"Auto Repair",
            "type":"Services"
        }
    ],
    "sg:phone":"+61 8 9293 8161",
    "sg:postcode":"6076",
    "sg:province":"WA",
    "sg:tags":[
        "repairer",
        "motor",
        "engineer"
    ],
    "wof:name":"Spiccia C & B Automotives",
    "wof:placetype":"venue"
},
  "geometry": {"coordinates":[116.137008667,-32.0333404541],"type":"Point"}
}