{
  "type": "Feature",
  "properties": {
    "addr:full":"214 Maroondah Hwy Healesville VIC 3777",
    "addr:housenumber":"214",
    "addr:postcode":"3777",
    "addr:street":"Maroondah Hwy",
    "iso:country":"AU",
    "sg:address":"214 Maroondah Hwy",
    "sg:city":"Healesville",
    "sg:classifiers":[
        {
            "category":"Health Services",
            "subcategory":"Health Practitioner",
            "type":"Services"
        }
    ],
    "sg:phone":"+61 3 5962 5530",
    "sg:postcode":"3777",
    "sg:province":"VIC",
    "sg:tags":[
        "physiotherapist"
    ],
    "wof:name":"Champion John",
    "wof:placetype":"venue"
},
  "geometry": {"coordinates":[145.51387,-37.654518],"type":"Point"}
}