{
  "type": "Feature",
  "properties": {
    "addr:full":"22 Byre Ave Somerton Park SA 5044",
    "addr:housenumber":"22",
    "addr:postcode":"5044",
    "addr:street":"Byre Ave Somerton",
    "iso:country":"AU",
    "sg:address":"22 Byre Ave",
    "sg:city":"Somerton Park",
    "sg:classifiers":[
        {
            "category":"Building & Trades",
            "subcategory":"Construction",
            "type":"Services"
        }
    ],
    "sg:phone":"+61 8 8295 4604",
    "sg:postcode":"5044",
    "sg:province":"SA",
    "sg:tags":[
        "welding"
    ],
    "wof:name":"Ascot Welding",
    "wof:placetype":"venue"
},
  "geometry": {"coordinates":[138.52461242699999,-34.9978790283],"type":"Point"}
}