{
  "type": "Feature",
  "properties": {
    "iso:country":"AU",
    "sg:address":"32 Sinclair Rd",
    "sg:city":"Dandenong",
    "sg:classifiers":[
        {
            "category":"Autos & Motor Vehicles",
            "subcategory":"Automobile Sales",
            "type":"Retail Goods"
        }
    ],
    "sg:phone":"+61 3 9706 7555",
    "sg:postcode":"3175",
    "sg:province":"VIC",
    "sg:tags":[
        "car",
        "new"
    ],
    "wof:name":"Last Chance Rentals Pty Ltd",
    "wof:placetype":"venue"
},
  "geometry": {"coordinates":[145.19642639200001,-37.9895858765],"type":"Point"}
}