{
  "type": "Feature",
  "properties": {
    "addr:full":"Shp 4 Flaxton Drv Mapleton QLD 4560",
    "addr:housenumber":"4",
    "addr:postcode":"4560",
    "addr:street":"Flaxton Drv",
    "iso:country":"AU",
    "sg:address":"Shp 4 Flaxton Drv",
    "sg:city":"Mapleton",
    "sg:classifiers":[
        {
            "category":"Food & Beverages",
            "subcategory":"Bakery",
            "type":"Retail Goods"
        }
    ],
    "sg:phone":"+61 7 5445 7622",
    "sg:postcode":"4560",
    "sg:province":"QLD",
    "sg:tags":[
        "baker"
    ],
    "wof:name":"Mapleton Bakery",
    "wof:placetype":"venue"
},
  "geometry": {"coordinates":[152.87950134299999,-26.6631565094],"type":"Point"}
}