{
  "type": "Feature",
  "properties": {
    "addr:full":"PO Box 6011 Blacktown NSW 2148",
    "addr:postcode":"2148",
    "iso:country":"AU",
    "sg:address":"PO Box 6011",
    "sg:city":"Blacktown",
    "sg:classifiers":[
        {
            "category":"Manufacturing",
            "subcategory":"Building Materials",
            "type":"Manufacturing & Wholesale Goods"
        }
    ],
    "sg:phone":"+61 2 9621 5200",
    "sg:postcode":"2148",
    "sg:province":"NSW",
    "sg:tags":[
        "concrete",
        "product"
    ],
    "sg:website":"http://bellpipes.citysearch.com.au",
    "wof:name":"Bell Pipes Pty.Ltd.",
    "wof:placetype":"venue"
},
  "geometry": {"coordinates":[150.90629577600001,-33.759601593],"type":"Point"}
}