{
  "type": "Feature",
  "properties": {
    "addr:full":"83 King George Rd Cohuna VIC 3568",
    "addr:housenumber":"83",
    "addr:postcode":"3568",
    "addr:street":"King George Rd",
    "iso:country":"AU",
    "sg:address":"83 King George Rd",
    "sg:city":"Cohuna",
    "sg:classifiers":[
        {
            "category":"Banks & Credit Unions",
            "subcategory":"Investment Brokerage",
            "type":"Services"
        }
    ],
    "sg:phone":"+61 3 5456 4142",
    "sg:postcode":"3568",
    "sg:province":"VIC",
    "sg:tags":[
        "broker"
    ],
    "wof:name":"Water Trading Australia",
    "wof:placetype":"venue"
},
  "geometry": {"coordinates":[144.219116211,-35.8026885986],"type":"Point"}
}