{
  "type": "Feature",
  "properties": {
    "iso:country":"AU",
    "sg:address":"56 Darling St",
    "sg:city":"Moonee Ponds",
    "sg:classifiers":[
        {
            "category":"Building & Trades",
            "subcategory":"Construction",
            "type":"Services"
        }
    ],
    "sg:phone":"+61 3 9375 1865",
    "sg:postcode":"3039",
    "sg:province":"VIC",
    "sg:tags":[
        "window",
        "timber"
    ],
    "wof:name":"S.C. Smith Pty Ltd.",
    "wof:placetype":"venue"
},
  "geometry": {"coordinates":[144.911377,-37.765858],"type":"Point"}
}