{
  "type": "Feature",
  "properties": {
    "iso:country":"AU",
    "sg:address":"12 Stretham Ave",
    "sg:city":"Picnic Point",
    "sg:classifiers":[
        {
            "category":"Retail",
            "subcategory":"Repair Shop",
            "type":"Services"
        }
    ],
    "sg:phone":"+61 2 9792 1929",
    "sg:postcode":"2213",
    "sg:province":"NSW",
    "sg:tags":[
        "machine",
        "repairs",
        "part",
        "dryer",
        "washing"
    ],
    "wof:name":"Paul's Appliance Repairs",
    "wof:placetype":"venue"
},
  "geometry": {"coordinates":[151.009949,-33.965755],"type":"Point"}
}