{
  "type": "Feature",
  "properties": {
    "addr:full":"Cnr Epsom Ave & Sydenham St Redcliffe WA 6104",
    "addr:postcode":"6104",
    "addr:street":"Cnr Epsom Ave & Sydenham St",
    "iso:country":"AU",
    "sg:address":"Cnr Epsom Ave & Sydenham St",
    "sg:city":"Redcliffe",
    "sg:classifiers":[
        {
            "category":"Social Services",
            "subcategory":"Child Care",
            "type":"Services"
        }
    ],
    "sg:phone":"+61 8 9277 6864",
    "sg:postcode":"6104",
    "sg:province":"WA",
    "wof:name":"Belmont Child Care Centre",
    "wof:placetype":"venue"
},
  "geometry": {"coordinates":[115.934951782,-31.9385223389],"type":"Point"}
}