{
  "type": "Feature",
  "properties": {
    "addr:full":"U2/ 52 Theodore St St Albans VIC 3021",
    "addr:housenumber":"52",
    "addr:postcode":"3021",
    "addr:street":"U2 /;Theodore St",
    "iso:country":"AU",
    "sg:address":"U2/ 52 Theodore St St",
    "sg:city":"Albans",
    "sg:classifiers":[
        {
            "category":"Building & Trades",
            "subcategory":"Cleaning & Sanitation",
            "type":"Services"
        }
    ],
    "sg:phone":"+61 3 9356 4213",
    "sg:postcode":"3021",
    "sg:province":"VIC",
    "sg:tags":[
        "industrial",
        "commercial",
        "contractor"
    ],
    "wof:name":"Cairnlea Cleaning Contractors",
    "wof:placetype":"venue"
},
  "geometry": {"coordinates":[144.79963699999999,-37.734314],"type":"Point"}
}