{
  "type": "Feature",
  "properties": {
    "iso:country":"AU",
    "sg:address":"24 Childs Rd",
    "sg:city":"Epping",
    "sg:classifiers":[
        {
            "category":"Fast Food",
            "type":"Food & Drink"
        }
    ],
    "sg:phone":"+61 3 9401 5802",
    "sg:postcode":"3076",
    "sg:province":"VIC",
    "sg:tags":[
        "away",
        "take"
    ],
    "wof:name":"Network Take Away",
    "wof:placetype":"venue"
},
  "geometry": {"coordinates":[145.01512145999999,-37.6591758728],"type":"Point"}
}