{
  "type": "Feature",
  "properties": {
    "addr:full":"Main St Croydon VIC 3136",
    "addr:postcode":"3136",
    "addr:street":"Main St",
    "iso:country":"AU",
    "sg:address":"Main St",
    "sg:city":"Croydon",
    "sg:classifiers":[
        {
            "category":"Personal",
            "subcategory":"Beauty Salon",
            "type":"Services"
        }
    ],
    "sg:phone":"+61 3 9723 1209",
    "sg:postcode":"3136",
    "sg:province":"VIC",
    "sg:tags":[
        "hairdresser"
    ],
    "wof:name":"Budget Cuts",
    "wof:placetype":"venue"
},
  "geometry": {"coordinates":[145.280563355,-37.7986793518],"type":"Point"}
}