{
  "type": "Feature",
  "properties": {
    "addr:full":"105 Parramatta Rd Camperdown NSW 2050",
    "addr:housenumber":"105",
    "addr:postcode":"2050",
    "addr:street":"Parramatta Rd",
    "iso:country":"AU",
    "sg:address":"105 Parramatta Rd",
    "sg:city":"Camperdown",
    "sg:classifiers":[
        {
            "category":"Retail",
            "subcategory":"Repair Shop",
            "type":"Services"
        }
    ],
    "sg:phone":"+61 2 9519 7531",
    "sg:postcode":"2050",
    "sg:province":"NSW",
    "sg:tags":[
        "cleaner",
        "part",
        "vacuum"
    ],
    "wof:name":"Godfreys",
    "wof:placetype":"venue"
},
  "geometry": {"coordinates":[151.175873,-33.887062],"type":"Point"}
}