{
  "type": "Feature",
  "properties": {
    "addr:full":"193 James St Toowoomba QLD 4350",
    "addr:housenumber":"193",
    "addr:postcode":"4350",
    "addr:street":"James St",
    "iso:country":"AU",
    "sg:address":"193 James St",
    "sg:city":"Toowoomba",
    "sg:classifiers":[
        {
            "category":"Autos & Motor Vehicles",
            "subcategory":"Automobile Sales",
            "type":"Retail Goods"
        }
    ],
    "sg:phone":"+61 7 4637 5555",
    "sg:postcode":"4350",
    "sg:province":"QLD",
    "sg:tags":[
        "car",
        "new"
    ],
    "sg:website":"http://www.peterrobertshonda.com.au",
    "wof:name":"Peter Roberts Honda",
    "wof:placetype":"venue"
},
  "geometry": {"coordinates":[151.952347,-27.568586],"type":"Point"}
}