{
  "type": "Feature",
  "properties": {
    "iso:country":"AU",
    "sg:address":"36a1/ 34 Fitzroy St",
    "sg:city":"Marrickville",
    "sg:classifiers":[
        {
            "category":"Manufacturing",
            "subcategory":"Printing",
            "type":"Manufacturing & Wholesale Goods"
        }
    ],
    "sg:phone":"+61 2 9550 1260",
    "sg:postcode":"2204",
    "sg:province":"NSW",
    "sg:tags":[
        "wholesaler",
        "mfrs",
        "greeting",
        "card"
    ],
    "wof:name":"Wrapaway Foreign Language Cards",
    "wof:placetype":"venue"
},
  "geometry": {"coordinates":[151.165359,-33.909554],"type":"Point"}
}