{
  "type": "Feature",
  "properties": {
    "addr:full":"149 Woodpark Rd Smithfield NSW 2164",
    "addr:housenumber":"149",
    "addr:postcode":"2164",
    "addr:street":"Woodpark Rd",
    "iso:country":"AU",
    "sg:address":"149 Woodpark Rd",
    "sg:city":"Smithfield",
    "sg:classifiers":[
        {
            "category":"Building & Trades",
            "subcategory":"Construction",
            "type":"Services"
        }
    ],
    "sg:phone":"+61 2 9603 1300",
    "sg:postcode":"2164",
    "sg:province":"NSW",
    "sg:tags":[
        "fencing",
        "contractor"
    ],
    "wof:name":"Fence Creations Pty Ltd",
    "wof:placetype":"venue"
},
  "geometry": {"coordinates":[150.933395386,-33.8362579346],"type":"Point"}
}