{
  "type": "Feature",
  "properties": {
    "addr:full":"663 Warringah Rd Forestville NSW 2087",
    "addr:housenumber":"663",
    "addr:postcode":"2087",
    "addr:street":"Warringah Rd",
    "iso:country":"AU",
    "sg:address":"663 Warringah Rd",
    "sg:city":"Forestville",
    "sg:classifiers":[
        {
            "category":"Retail",
            "subcategory":"Auto Repair",
            "type":"Services"
        }
    ],
    "sg:phone":"+61 2 9451 5022",
    "sg:postcode":"2087",
    "sg:province":"NSW",
    "sg:tags":[
        "beater",
        "painter",
        "panel"
    ],
    "wof:name":"Forestville Autobody Repairs",
    "wof:placetype":"venue"
},
  "geometry": {"coordinates":[151.219192505,-33.7594566345],"type":"Point"}
}