{
  "type": "Feature",
  "properties": {
    "addr:full":"43 Cumberland St Cessnock NSW 2325",
    "addr:housenumber":"43",
    "addr:postcode":"2325",
    "addr:street":"Cumberland St",
    "iso:country":"AU",
    "sg:address":"43 Cumberland St",
    "sg:city":"Cessnock",
    "sg:classifiers":[
        {
            "category":"Health Services",
            "subcategory":"Dentist",
            "type":"Services"
        }
    ],
    "sg:phone":"+61 2 4990 4641",
    "sg:postcode":"2325",
    "sg:province":"NSW",
    "wof:name":"Scobie Graeme Dr.",
    "wof:placetype":"venue"
},
  "geometry": {"coordinates":[151.35694885300001,-32.8363761902],"type":"Point"}
}