{
  "type": "Feature",
  "properties": {
    "iso:country":"AU",
    "sg:address":"290 Waverley Rd",
    "sg:city":"Malvern East",
    "sg:classifiers":[
        {
            "category":"Retail",
            "subcategory":"Auto Repair",
            "type":"Services"
        }
    ],
    "sg:phone":"+61 3 9571 2131",
    "sg:postcode":"3145",
    "sg:province":"VIC",
    "sg:tags":[
        "repairer",
        "motor",
        "engineer"
    ],
    "wof:name":"All Wheel Drive Gearbox Reconditioners",
    "wof:placetype":"venue"
},
  "geometry": {"coordinates":[145.057983398,-37.8772735596],"type":"Point"}
}