{
  "type": "Feature",
  "properties": {
    "iso:country":"AU",
    "sg:address":"Unit 26/ 66 Bannister Rd",
    "sg:city":"Canning Vale",
    "sg:classifiers":[
        {
            "category":"Professional",
            "type":"Services"
        }
    ],
    "sg:phone":"+61 8 9455 5599",
    "sg:postcode":"6155",
    "sg:province":"WA",
    "sg:tags":[
        "courier"
    ],
    "wof:name":"CourierNet / FreightNet Pty Ltd",
    "wof:placetype":"venue"
},
  "geometry": {"coordinates":[115.924927,-32.062908],"type":"Point"}
}