{
  "type": "Feature",
  "properties": {
    "addr:full":"12b Beach St Frankston VIC 3199",
    "addr:housenumber":"12b",
    "addr:postcode":"3199",
    "addr:street":"Beach St",
    "iso:country":"AU",
    "sg:address":"12b Beach St",
    "sg:city":"Frankston",
    "sg:classifiers":[
        {
            "category":"Health Services",
            "subcategory":"Health Practitioner",
            "type":"Services"
        }
    ],
    "sg:phone":"+61 3 9781 3132",
    "sg:postcode":"3199",
    "sg:province":"VIC",
    "sg:tags":[
        "naturopath"
    ],
    "wof:name":"Nepean Naturopathic Centre",
    "wof:placetype":"venue"
},
  "geometry": {"coordinates":[144.966674805,-38.3327827454],"type":"Point"}
}