{
  "type": "Feature",
  "properties": {
    "addr:full":"Level 1/ 2 Elgin St Maitland NSW 2320",
    "addr:housenumber":"/ 2",
    "addr:postcode":"2320",
    "addr:street":"Elgin St",
    "iso:country":"AU",
    "sg:address":"Level 1/ 2 Elgin St",
    "sg:city":"Maitland",
    "sg:classifiers":[
        {
            "category":"Real Estate",
            "subcategory":"Real Estate Services",
            "type":"Services"
        }
    ],
    "sg:phone":"+61 2 4933 9200",
    "sg:postcode":"2320",
    "sg:province":"NSW",
    "sg:tags":[
        "valuer"
    ],
    "wof:name":"Hunter Valuation Services",
    "wof:placetype":"venue"
},
  "geometry": {"coordinates":[151.55473327600001,-32.7324562073],"type":"Point"}
}