{
  "type": "Feature",
  "properties": {
    "addr:full":"25-41 Princes Hwy Sale VIC 3850",
    "addr:housenumber":"25-41",
    "addr:postcode":"3850",
    "addr:street":"Princes Hwy",
    "iso:country":"AU",
    "sg:address":"25-41 Princes Hwy",
    "sg:city":"Sale",
    "sg:classifiers":[
        {
            "category":"Travel",
            "subcategory":"Hotels & Motels",
            "type":"Entertainment"
        }
    ],
    "sg:phone":"+61 3 5144 6599",
    "sg:postcode":"3850",
    "sg:province":"VIC",
    "wof:name":"The Comfort Inn Princeton",
    "wof:placetype":"venue"
},
  "geometry": {"coordinates":[147.069854736,-38.0875511169],"type":"Point"}
}