{
  "type": "Feature",
  "properties": {
    "addr:full":"42 Castlereagh St Penrith NSW 2750",
    "addr:housenumber":"42",
    "addr:postcode":"2750",
    "addr:street":"Castlereagh St",
    "iso:country":"AU",
    "sg:address":"42 Castlereagh St",
    "sg:city":"Penrith",
    "sg:classifiers":[
        {
            "category":"Health Services",
            "subcategory":"Doctor",
            "type":"Services"
        }
    ],
    "sg:phone":"+61 2 4732 2211",
    "sg:postcode":"2750",
    "sg:province":"NSW",
    "sg:tags":[
        "medical",
        "practitioner"
    ],
    "wof:name":"Hall R G",
    "wof:placetype":"venue"
},
  "geometry": {"coordinates":[150.86538696299999,-33.6784934998],"type":"Point"}
}