{
  "type": "Feature",
  "properties": {
    "addr:full":"25 Yuille St Frankston VIC 3199",
    "addr:housenumber":"25",
    "addr:postcode":"3199",
    "addr:street":"Yuille St",
    "iso:country":"AU",
    "sg:address":"25 Yuille St",
    "sg:city":"Frankston",
    "sg:classifiers":[
        {
            "category":"Health Services",
            "subcategory":"Health Practitioner",
            "type":"Services"
        }
    ],
    "sg:phone":"+61 3 9783 2758",
    "sg:postcode":"3199",
    "sg:province":"VIC",
    "sg:tags":[
        "dietitian"
    ],
    "wof:name":"Georgina Rist",
    "wof:placetype":"venue"
},
  "geometry": {"coordinates":[145.00148010300001,-37.9272346497],"type":"Point"}
}