{
  "type": "Feature",
  "properties": {
    "addr:full":"149 Market St South Melbourne VIC 3205",
    "addr:housenumber":"149",
    "addr:postcode":"3205",
    "addr:street":"Market St",
    "iso:country":"AU",
    "sg:address":"149 Market St",
    "sg:city":"South Melbourne",
    "sg:classifiers":[
        {
            "category":"Autos & Motor Vehicles",
            "subcategory":"Auto Supplies",
            "type":"Retail Goods"
        }
    ],
    "sg:phone":"+61 3 9699 1717",
    "sg:postcode":"3205",
    "sg:province":"VIC",
    "sg:tags":[
        "part",
        "cycles",
        "accessory"
    ],
    "wof:name":"Johnson Cycle Tune",
    "wof:placetype":"venue"
},
  "geometry": {"coordinates":[144.95503199999999,-37.830944],"type":"Point"}
}