{
  "type": "Feature",
  "properties": {
    "iso:country":"AU",
    "sg:address":"23 Darling St",
    "sg:city":"Geelong East",
    "sg:classifiers":[
        {
            "category":"Building & Trades",
            "subcategory":"Plumbing",
            "type":"Services"
        }
    ],
    "sg:phone":"+61 414 805 039",
    "sg:postcode":"3219",
    "sg:province":"VIC",
    "sg:tags":[
        "plumber",
        "gasfitters"
    ],
    "wof:name":"Allthorpe Plumbing",
    "wof:placetype":"venue"
},
  "geometry": {"coordinates":[144.37364196799999,-38.1626434326],"type":"Point"}
}