{
  "type": "Feature",
  "properties": {
    "addr:full":"Level 1/ 10 Bathurst St Sydney NSW 2000",
    "addr:housenumber":"/ 10",
    "addr:postcode":"2000",
    "addr:street":"Bathurst St",
    "iso:country":"AU",
    "sg:address":"Level 1/ 10 Bathurst St",
    "sg:city":"Sydney",
    "sg:classifiers":[
        {
            "category":"Professional",
            "subcategory":"Accounting & Tax Preparation",
            "type":"Services"
        }
    ],
    "sg:phone":"+61 2 8251 4209",
    "sg:postcode":"2000",
    "sg:province":"NSW",
    "sg:tags":[
        "consultant",
        "taxation"
    ],
    "wof:name":"Avinash Nichawde & Co",
    "wof:placetype":"venue"
},
  "geometry": {"coordinates":[151.202835083,-33.8740081787],"type":"Point"}
}