{
  "type": "Feature",
  "properties": {
    "addr:full":"Suite 6, 20-24 Gibbs St Miranda NSW 2228",
    "addr:housenumber":"20-24",
    "addr:postcode":"2228",
    "addr:street":"Gibbs St Miranda",
    "iso:country":"AU",
    "sg:address":"Suite 6, 20-24 Gibbs St",
    "sg:city":"Miranda",
    "sg:classifiers":[
        {
            "category":"Health Services",
            "subcategory":"Doctor",
            "type":"Services"
        }
    ],
    "sg:phone":"+61 2 9524 2859",
    "sg:postcode":"2228",
    "sg:province":"NSW",
    "sg:tags":[
        "medical",
        "practitioner"
    ],
    "wof:name":"Callan K",
    "wof:placetype":"venue"
},
  "geometry": {"coordinates":[151.10296630900001,-34.0367736816],"type":"Point"}
}