{
  "type": "Feature",
  "properties": {
    "addr:full":"Unit 7/ 385 Pacific Hwy Crows Nest NSW 2065",
    "addr:housenumber":"/ 385",
    "addr:postcode":"2065",
    "addr:street":"Pacific Hwy",
    "iso:country":"AU",
    "sg:address":"Unit 7/ 385 Pacific Hwy",
    "sg:city":"Crows Nest",
    "sg:classifiers":[
        {
            "category":"Travel",
            "subcategory":"Travel Agent",
            "type":"Entertainment"
        }
    ],
    "sg:phone":"+61 2 9964 0400",
    "sg:postcode":"2065",
    "sg:province":"NSW",
    "sg:tags":[
        "consultant"
    ],
    "wof:name":"American Express International Inc",
    "wof:placetype":"venue"
},
  "geometry": {"coordinates":[151.19866943400001,-33.8252754211],"type":"Point"}
}