{
  "type": "Feature",
  "properties": {
    "addr:full":"128 Beach Rd Pialba QLD 4655",
    "addr:housenumber":"128",
    "addr:postcode":"4655",
    "addr:street":"Beach Rd",
    "iso:country":"AU",
    "sg:address":"128 Beach Rd",
    "sg:city":"Pialba",
    "sg:classifiers":[
        {
            "category":"Home & Garden",
            "subcategory":"Building Materials",
            "type":"Retail Goods"
        }
    ],
    "sg:phone":"+61 7 4128 4222",
    "sg:postcode":"4655",
    "sg:province":"QLD",
    "sg:tags":[
        "fencing"
    ],
    "wof:name":"Big Produce Place",
    "wof:placetype":"venue"
},
  "geometry": {"coordinates":[152.83178699999999,-25.28517],"type":"Point"}
}