{
  "type": "Feature",
  "properties": {
    "addr:full":"Lot 2 Pleasant Drv Heathmont VIC 3135",
    "addr:postcode":"3135",
    "addr:street":"Pleasant Drv",
    "iso:country":"AU",
    "sg:address":"Lot 2 Pleasant Drv",
    "sg:city":"Heathmont",
    "sg:classifiers":[
        {
            "category":"Education",
            "subcategory":"Kindergarten",
            "type":"Public Place"
        }
    ],
    "sg:phone":"+61 3 9729 4762",
    "sg:postcode":"3135",
    "sg:province":"VIC",
    "sg:tags":[
        "pre-schools"
    ],
    "wof:name":"Heathmont East Pre-School Association",
    "wof:placetype":"venue"
},
  "geometry": {"coordinates":[145.255615234,-37.8300361633],"type":"Point"}
}