{
  "type": "Feature",
  "properties": {
    "iso:country":"AU",
    "sg:address":"1 Ocean View Drv",
    "sg:city":"Terrigal",
    "sg:classifiers":[
        {
            "category":"Travel",
            "subcategory":"Hotels & Motels",
            "type":"Entertainment"
        }
    ],
    "sg:phone":"+61 2 4384 1566",
    "sg:postcode":"2260",
    "sg:province":"NSW",
    "sg:website":"http://www.clan.com.au",
    "wof:name":"Clan Lakeside Lodge",
    "wof:placetype":"venue"
},
  "geometry": {"coordinates":[151.441101,-33.441105],"type":"Point"}
}