{
  "type": "Feature",
  "properties": {
    "iso:country":"AU",
    "sg:address":"45 Hargreaves St",
    "sg:city":"Edmonton",
    "sg:classifiers":[
        {
            "category":"Transit Center",
            "subcategory":"Freight",
            "type":"Transportation"
        }
    ],
    "sg:phone":"+61 7 4055 5774",
    "sg:postcode":"4869",
    "sg:province":"QLD",
    "sg:tags":[
        "agent",
        "shipping"
    ],
    "wof:name":"Allied Pickfords",
    "wof:placetype":"venue"
},
  "geometry": {"coordinates":[145.744750977,-17.0009098053],"type":"Point"}
}