{
  "type": "Feature",
  "properties": {
    "iso:country":"AU",
    "sg:address":"Jefferis Rd",
    "sg:city":"Beecher",
    "sg:classifiers":[
        {
            "category":"Farming",
            "subcategory":"Nursery",
            "type":"Manufacturing & Wholesale Goods"
        }
    ],
    "sg:phone":"+61 7 4978 6455",
    "sg:postcode":"4680",
    "sg:province":"QLD",
    "wof:name":"Beecher Plant Market",
    "wof:placetype":"venue"
},
  "geometry": {"coordinates":[151.20344543499999,-23.9032096863],"type":"Point"}
}