{
  "type": "Feature",
  "properties": {
    "iso:country":"AU",
    "sg:address":"134 Brown St",
    "sg:city":"Hamilton",
    "sg:classifiers":[
        {
            "category":"Arena",
            "subcategory":"Sports Club",
            "type":"Entertainment"
        }
    ],
    "sg:phone":"+61 3 5571 1736",
    "sg:postcode":"3300",
    "sg:province":"VIC",
    "sg:tags":[
        "australian",
        "football",
        "rule"
    ],
    "wof:name":"Hamilton Football Netball Club Inc",
    "wof:placetype":"venue"
},
  "geometry": {"coordinates":[142.0234375,-37.7403678894],"type":"Point"}
}