{
  "type": "Feature",
  "properties": {
    "addr:full":"166 Boronia Rd Boronia VIC 3155",
    "addr:housenumber":"166",
    "addr:postcode":"3155",
    "addr:street":"Boronia Rd",
    "iso:country":"AU",
    "sg:address":"166 Boronia Rd",
    "sg:city":"Boronia",
    "sg:classifiers":[
        {
            "category":"Professional",
            "subcategory":"Art Services",
            "type":"Services"
        }
    ],
    "sg:phone":"+61 417 139 971",
    "sg:postcode":"3155",
    "sg:province":"VIC",
    "sg:tags":[
        "graphic",
        "designer"
    ],
    "wof:name":"James Designs Pty Ltd",
    "wof:placetype":"venue"
},
  "geometry": {"coordinates":[145.28091430699999,-37.8623352051],"type":"Point"}
}