{
  "type": "Feature",
  "properties": {
    "iso:country":"AU",
    "sg:address":"92 Morgan St",
    "sg:city":"Wagga Wagga",
    "sg:classifiers":[
        {
            "category":"Banks & Credit Unions",
            "subcategory":"Financial Services",
            "type":"Services"
        }
    ],
    "sg:phone":"+61 2 6921 6700",
    "sg:postcode":"2650",
    "sg:province":"NSW",
    "sg:tags":[
        "planning"
    ],
    "wof:name":"Tysons Financial Services Pty Ltd",
    "wof:placetype":"venue"
},
  "geometry": {"coordinates":[147.36819457999999,-35.1160087585],"type":"Point"}
}