{
  "type": "Feature",
  "properties": {
    "iso:country":"AU",
    "sg:address":"60 Cecil Ave",
    "sg:city":"Castle Hill",
    "sg:classifiers":[
        {
            "category":"Health Services",
            "subcategory":"Medical Lab",
            "type":"Services"
        }
    ],
    "sg:phone":"+61 2 9899 7462",
    "sg:postcode":"2154",
    "sg:province":"NSW",
    "sg:tags":[
        "laboratory",
        "pathology"
    ],
    "wof:name":"General Clinical Laboratories",
    "wof:placetype":"venue"
},
  "geometry": {"coordinates":[151.001953125,-33.7340660095],"type":"Point"}
}