{
  "type": "Feature",
  "properties": {
    "addr:full":"86 Kooyong Rd Caulfield North VIC 3161",
    "addr:housenumber":"86",
    "addr:postcode":"3161",
    "addr:street":"Kooyong Rd",
    "iso:country":"AU",
    "sg:address":"86 Kooyong Rd",
    "sg:city":"Caulfield North",
    "sg:classifiers":[
        {
            "category":"Health Services",
            "subcategory":"Dentist",
            "type":"Services"
        }
    ],
    "sg:phone":"+61 1300 661 158",
    "sg:postcode":"3161",
    "sg:province":"VIC",
    "wof:name":"A Whiter Smiley",
    "wof:placetype":"venue"
},
  "geometry": {"coordinates":[145.01817321799999,-37.8704528809],"type":"Point"}
}