{
  "type": "Feature",
  "properties": {
    "addr:full":"38 Boron St Sumner Park QLD 4074",
    "addr:housenumber":"38",
    "addr:postcode":"4074",
    "addr:street":"Boron St",
    "iso:country":"AU",
    "sg:address":"38 Boron St",
    "sg:city":"Sumner Park",
    "sg:classifiers":[
        {
            "category":"Wholesale",
            "subcategory":"Durable Goods & Equipment",
            "type":"Manufacturing & Wholesale Goods"
        }
    ],
    "sg:phone":"+61 7 3279 3922",
    "sg:postcode":"4074",
    "sg:province":"QLD",
    "sg:tags":[
        "degreasing"
    ],
    "wof:name":"Greaseaters (Brisbane)",
    "wof:placetype":"venue"
},
  "geometry": {"coordinates":[152.935302734,-27.5665397644],"type":"Point"}
}