{
  "type": "Feature",
  "properties": {
    "addr:full":"806- 812 Anzac Pde Maroubra NSW 2035",
    "addr:housenumber":"812",
    "addr:postcode":"2035",
    "addr:street":"Anzac Pde",
    "iso:country":"AU",
    "sg:address":"806- 812 Anzac Pde",
    "sg:city":"Maroubra",
    "sg:classifiers":[
        {
            "category":"Health Services",
            "subcategory":"Doctor",
            "type":"Services"
        }
    ],
    "sg:phone":"+61 2 9349 9000",
    "sg:postcode":"2035",
    "sg:province":"NSW",
    "sg:tags":[
        "medical",
        "practitioner"
    ],
    "wof:name":"Maroubra Medical & Dental Centre",
    "wof:placetype":"venue"
},
  "geometry": {"coordinates":[151.23915100100001,-33.9390335083],"type":"Point"}
}