{
  "type": "Feature",
  "properties": {
    "addr:full":"15 Serpentine Rd Erina Heights NSW 2260",
    "addr:housenumber":"15",
    "addr:postcode":"2260",
    "addr:street":"Serpentine Rd",
    "iso:country":"AU",
    "sg:address":"15 Serpentine Rd",
    "sg:city":"Erina Heights",
    "sg:classifiers":[
        {
            "category":"Building & Trades",
            "subcategory":"Landscaping Services",
            "type":"Services"
        }
    ],
    "sg:phone":"+61 2 4365 4333",
    "sg:postcode":"2260",
    "sg:province":"NSW",
    "sg:tags":[
        "designer",
        "landscape",
        "contractor"
    ],
    "wof:name":"Brian Filby Landscape Group P/L",
    "wof:placetype":"venue"
},
  "geometry": {"coordinates":[151.412689,-33.428219],"type":"Point"}
}