{
  "type": "Feature",
  "properties": {
    "addr:full":"109 Jessie St Armidale NSW 2350",
    "addr:housenumber":"109",
    "addr:postcode":"2350",
    "addr:street":"Jessie St",
    "iso:country":"AU",
    "sg:address":"109 Jessie St",
    "sg:city":"Armidale",
    "sg:classifiers":[
        {
            "category":"Professional",
            "subcategory":"Accounting & Tax Preparation",
            "type":"Services"
        }
    ],
    "sg:phone":"+61 2 6776 5155",
    "sg:postcode":"2350",
    "sg:province":"NSW",
    "sg:tags":[
        "accountant",
        "auditor"
    ],
    "wof:name":"Schultz R B",
    "wof:placetype":"venue"
},
  "geometry": {"coordinates":[151.663528442,-30.5124015808],"type":"Point"}
}