{
  "type": "Feature",
  "properties": {
    "addr:full":"9A Railway Ave Wahroonga NSW 2076",
    "addr:housenumber":"9a",
    "addr:postcode":"2076",
    "addr:street":"Railway Ave",
    "iso:country":"AU",
    "sg:address":"9A Railway Ave",
    "sg:city":"Wahroonga",
    "sg:classifiers":[
        {
            "category":"Wholesale",
            "subcategory":"Medical Equipment & Supplies",
            "type":"Manufacturing & Wholesale Goods"
        }
    ],
    "sg:phone":"+61 2 9394 8450",
    "sg:postcode":"2076",
    "sg:province":"NSW",
    "sg:tags":[
        "aids",
        "hearing"
    ],
    "wof:name":"Better Hearing",
    "wof:placetype":"venue"
},
  "geometry": {"coordinates":[151.11677551299999,-33.7181587219],"type":"Point"}
}