{
  "type": "Feature",
  "properties": {
    "addr:full":"Ste3/ 92 George St Beenleigh QLD 4207",
    "addr:housenumber":"92",
    "addr:postcode":"4207",
    "addr:street":"George St",
    "iso:country":"AU",
    "sg:address":"Ste3/ 92 George St",
    "sg:city":"Beenleigh",
    "sg:classifiers":[
        {
            "category":"Banks & Credit Unions",
            "subcategory":"Financial Services",
            "type":"Services"
        }
    ],
    "sg:phone":"+61 7 3382 7333",
    "sg:postcode":"4207",
    "sg:province":"QLD",
    "sg:tags":[
        "financier"
    ],
    "wof:name":"Fusion Finance Australia",
    "wof:placetype":"venue"
},
  "geometry": {"coordinates":[153.204544067,-27.716545105],"type":"Point"}
}