{
  "type": "Feature",
  "properties": {
    "addr:full":"Northey Rd Tolga QLD 4882",
    "addr:postcode":"4882",
    "addr:street":"Northey Rd",
    "iso:country":"AU",
    "sg:address":"Northey Rd",
    "sg:city":"Tolga",
    "sg:classifiers":[
        {
            "category":"Farming",
            "subcategory":"Farm",
            "type":"Manufacturing & Wholesale Goods"
        }
    ],
    "sg:phone":"+61 7 4095 4316",
    "sg:postcode":"4882",
    "sg:province":"QLD",
    "sg:tags":[
        "farmer"
    ],
    "wof:name":"Standen R W",
    "wof:placetype":"venue"
},
  "geometry": {"coordinates":[145.469848633,-17.18816185],"type":"Point"}
}