{
  "type": "Feature",
  "properties": {
    "addr:full":"339 Urana Rd Lavington NSW 2641",
    "addr:housenumber":"339",
    "addr:postcode":"2641",
    "addr:street":"Urana Rd",
    "iso:country":"AU",
    "sg:address":"339 Urana Rd",
    "sg:city":"Lavington",
    "sg:classifiers":[
        {
            "category":"Manufacturing",
            "subcategory":"Electronics",
            "type":"Manufacturing & Wholesale Goods"
        }
    ],
    "sg:phone":"+61 2 6040 2229",
    "sg:postcode":"2641",
    "sg:province":"NSW",
    "sg:tags":[
        "oven",
        "microwave"
    ],
    "wof:name":"Border Video & TV Service",
    "wof:placetype":"venue"
},
  "geometry": {"coordinates":[146.931518555,-36.0495681763],"type":"Point"}
}