{
  "type": "Feature",
  "properties": {
    "addr:full":"Nundle Rd Tamworth NSW 2340",
    "addr:postcode":"2340",
    "addr:street":"Nundle Rd",
    "iso:country":"AU",
    "sg:address":"Nundle Rd",
    "sg:city":"Tamworth",
    "sg:classifiers":[
        {
            "category":"Freight",
            "type":"Transportation"
        }
    ],
    "sg:phone":"+61 2 6760 9700",
    "sg:postcode":"2340",
    "sg:province":"NSW",
    "sg:tags":[
        "light",
        "carrier"
    ],
    "wof:name":"McDonald Bros",
    "wof:placetype":"venue"
},
  "geometry": {"coordinates":[150.999710083,-31.128036499],"type":"Point"}
}