{
  "type": "Feature",
  "properties": {
    "iso:country":"AU",
    "sg:address":"12 Dalton St",
    "sg:city":"Kippa-Ring",
    "sg:classifiers":[
        {
            "category":"Home & Garden",
            "subcategory":"Building Materials",
            "type":"Retail Goods"
        }
    ],
    "sg:phone":"+61 7 3284 2410",
    "sg:postcode":"4021",
    "sg:province":"QLD",
    "sg:tags":[
        "merchant",
        "glass",
        "glazier"
    ],
    "wof:name":"Peninsula Glass",
    "wof:placetype":"venue"
},
  "geometry": {"coordinates":[153.09166,-27.224186],"type":"Point"}
}