{
  "type": "Feature",
  "properties": {
    "addr:full":"25-27 Marshall Rd Airport West VIC 3042",
    "addr:housenumber":"25-27",
    "addr:postcode":"3042",
    "addr:street":"Marshall Rd",
    "iso:country":"AU",
    "sg:address":"25-27 Marshall Rd",
    "sg:city":"Airport West",
    "sg:classifiers":[
        {
            "category":"Utilities",
            "subcategory":"Electric",
            "type":"Services"
        }
    ],
    "sg:phone":"+61 3 9335 3601",
    "sg:postcode":"3042",
    "sg:province":"VIC",
    "sg:tags":[
        "electrical",
        "contractor"
    ],
    "wof:name":"Datalec Australia Pty Ltd",
    "wof:placetype":"venue"
},
  "geometry": {"coordinates":[144.88954162600001,-37.7177505493],"type":"Point"}
}