{
  "type": "Feature",
  "properties": {
    "addr:full":"11 Watkins St Tully QLD 4854",
    "addr:housenumber":"11",
    "addr:postcode":"4854",
    "addr:street":"Watkins St",
    "iso:country":"AU",
    "sg:address":"11 Watkins St",
    "sg:city":"Tully",
    "sg:classifiers":[
        {
            "category":"Professional",
            "subcategory":"Accounting & Tax Preparation",
            "type":"Services"
        }
    ],
    "sg:phone":"+61 7 4068 1255",
    "sg:postcode":"4854",
    "sg:province":"QLD",
    "sg:tags":[
        "accountant",
        "auditor"
    ],
    "wof:name":"Norton Chris",
    "wof:placetype":"venue"
},
  "geometry": {"coordinates":[145.92265319800001,-17.9338436127],"type":"Point"}
}