{
  "type": "Feature",
  "properties": {
    "addr:full":"95 Curtin Ave Wahroonga NSW 2076",
    "addr:housenumber":"95",
    "addr:postcode":"2076",
    "addr:street":"Curtin Ave",
    "iso:country":"AU",
    "sg:address":"95 Curtin Ave",
    "sg:city":"Wahroonga",
    "sg:classifiers":[
        {
            "category":"Food & Beverages",
            "subcategory":"Specialty",
            "type":"Retail Goods"
        }
    ],
    "sg:phone":"+61 2 9489 1449",
    "sg:postcode":"2076",
    "sg:province":"NSW",
    "sg:tags":[
        "product",
        "health"
    ],
    "wof:name":"Neo Life Distributors-Ming Enterprises",
    "wof:placetype":"venue"
},
  "geometry": {"coordinates":[151.12388610799999,-33.6950416565],"type":"Point"}
}