{
  "type": "Feature",
  "properties": {
    "addr:full":"12 Gobondery St Trundle NSW 2875",
    "addr:housenumber":"12",
    "addr:postcode":"2875",
    "addr:street":"Gobondery St",
    "iso:country":"AU",
    "sg:address":"12 Gobondery St",
    "sg:city":"Trundle",
    "sg:classifiers":[
        {
            "category":"Shopping",
            "type":"Retail Goods"
        }
    ],
    "sg:phone":"+61 2 6892 1119",
    "sg:postcode":"2875",
    "sg:province":"NSW",
    "sg:tags":[
        "agent",
        "stock"
    ],
    "wof:name":"Pike A J & Son",
    "wof:placetype":"venue"
},
  "geometry": {"coordinates":[147.70727500000001,-32.920296],"type":"Point"}
}