{
  "type": "Feature",
  "properties": {
    "addr:full":"Atlas Rd Junortoun VIC 3551",
    "addr:postcode":"3551",
    "addr:street":"Atlas Rd",
    "iso:country":"AU",
    "sg:address":"Atlas Rd",
    "sg:city":"Junortoun",
    "sg:classifiers":[
        {
            "category":"Farming",
            "subcategory":"Farm & Veterinary Services",
            "type":"Manufacturing & Wholesale Goods"
        }
    ],
    "sg:phone":"+61 3 5449 3409",
    "sg:postcode":"3551",
    "sg:province":"VIC",
    "sg:tags":[
        "blacksmith",
        "farrier"
    ],
    "wof:name":"Hamilton Leigh",
    "wof:placetype":"venue"
},
  "geometry": {"coordinates":[144.356155395,-36.768032074],"type":"Point"}
}