{
  "type": "Feature",
  "properties": {
    "iso:country":"AU",
    "sg:address":"28 Brodie-Hall Drv",
    "sg:city":"Bentley",
    "sg:classifiers":[
        {
            "category":"Social Services",
            "subcategory":"Child Care",
            "type":"Services"
        }
    ],
    "sg:phone":"+61 8 9472 9472",
    "sg:postcode":"6102",
    "sg:province":"WA",
    "wof:name":"Technology Park Child Care",
    "wof:placetype":"venue"
},
  "geometry": {"coordinates":[115.892349243,-31.9968528748],"type":"Point"}
}