{
  "type": "Feature",
  "properties": {
    "addr:full":"145 Old Pacific Hwy Oxenford QLD 4210",
    "addr:housenumber":"145",
    "addr:postcode":"4210",
    "addr:street":"Old Pacific Hwy",
    "iso:country":"AU",
    "sg:address":"145 Old Pacific Hwy",
    "sg:city":"Oxenford",
    "sg:classifiers":[
        {
            "category":"Wholesale",
            "subcategory":"Electrical",
            "type":"Manufacturing & Wholesale Goods"
        }
    ],
    "sg:phone":"+61 7 5580 5422",
    "sg:postcode":"4210",
    "sg:province":"QLD",
    "sg:tags":[
        "wholesaler"
    ],
    "wof:name":"Ideal Electrical Suppliers",
    "wof:placetype":"venue"
},
  "geometry": {"coordinates":[153.31350707999999,-27.8899822235],"type":"Point"}
}