{
  "type": "Feature",
  "properties": {
    "iso:country":"AU",
    "sg:address":"45 Clifton Crs",
    "sg:city":"Mt Lawley",
    "sg:classifiers":[
        {
            "category":"Professional",
            "subcategory":"Computer Services",
            "type":"Services"
        }
    ],
    "sg:phone":"+61 8 9371 1720",
    "sg:postcode":"6050",
    "sg:province":"WA",
    "sg:tags":[
        "consultant",
        "system"
    ],
    "wof:name":"Belcom Pty Ltd",
    "wof:placetype":"venue"
},
  "geometry": {"coordinates":[115.870262146,-31.9267730713],"type":"Point"}
}