{
  "type": "Feature",
  "properties": {
    "iso:country":"AU",
    "sg:address":"361 High Rd",
    "sg:city":"Riverton",
    "sg:classifiers":[
        {
            "category":"Travel",
            "subcategory":"Hotels & Motels",
            "type":"Entertainment"
        }
    ],
    "sg:phone":"+61 8 9457 0477",
    "sg:postcode":"6148",
    "sg:province":"WA",
    "wof:name":"High Road Hotel",
    "wof:placetype":"venue"
},
  "geometry": {"coordinates":[115.90937,-32.038662],"type":"Point"}
}