{
  "type": "Feature",
  "properties": {
    "addr:full":"23 Chandra Ave Kilsyth South VIC 3137",
    "addr:housenumber":"23",
    "addr:postcode":"3137",
    "addr:street":"Chandra Ave",
    "iso:country":"AU",
    "sg:address":"23 Chandra Ave",
    "sg:city":"Kilsyth South",
    "sg:classifiers":[
        {
            "category":"Arena",
            "subcategory":"Sports Club",
            "type":"Entertainment"
        }
    ],
    "sg:phone":"+61 418 350 006",
    "sg:postcode":"3137",
    "sg:province":"VIC",
    "sg:tags":[
        "defence",
        "supply",
        "self",
        "instruction",
        "martial art"
    ],
    "wof:name":"Taekwondo 201",
    "wof:placetype":"venue"
},
  "geometry": {"coordinates":[145.30659484899999,-37.831905365],"type":"Point"}
}