{
  "type": "Feature",
  "properties": {
    "addr:full":"Shop 2 The Dome Victoria St Mackay QLD 4740",
    "addr:housenumber":"shop 2",
    "addr:postcode":"4740",
    "addr:street":"The Dome Victoria St",
    "iso:country":"AU",
    "sg:address":"Shop 2 The Dome Victoria St",
    "sg:city":"Mackay",
    "sg:classifiers":[
        {
            "category":"Personal",
            "subcategory":"Beauty Salon",
            "type":"Services"
        }
    ],
    "sg:phone":"+61 7 4953 0830",
    "sg:postcode":"4740",
    "sg:province":"QLD",
    "sg:tags":[
        "hairdresser"
    ],
    "wof:name":"Joelta Hair & Beauty Excellence",
    "wof:placetype":"venue"
},
  "geometry": {"coordinates":[149.17674299999999,-21.140074],"type":"Point"}
}