{
  "type": "Feature",
  "properties": {
    "addr:full":"97 Dixon Rd Rockingham WA 6168",
    "addr:housenumber":"97",
    "addr:postcode":"6168",
    "addr:street":"Dixon Rd",
    "iso:country":"AU",
    "sg:address":"97 Dixon Rd",
    "sg:city":"Rockingham",
    "sg:classifiers":[
        {
            "category":"Autos & Motor Vehicles",
            "subcategory":"Automobile Sales",
            "type":"Retail Goods"
        }
    ],
    "sg:phone":"+61 8 9592 6666",
    "sg:postcode":"6168",
    "sg:province":"WA",
    "sg:tags":[
        "car",
        "new"
    ],
    "wof:name":"Magic Nissan",
    "wof:placetype":"venue"
},
  "geometry": {"coordinates":[115.76741800000001,-32.276848],"type":"Point"}
}