{
  "type": "Feature",
  "properties": {
    "addr:full":"734 Merrylands Rd Greystanes NSW 2145",
    "addr:housenumber":"734",
    "addr:postcode":"2145",
    "addr:street":"Merrylands Rd",
    "iso:country":"AU",
    "sg:address":"734 Merrylands Rd",
    "sg:city":"Greystanes",
    "sg:classifiers":[
        {
            "category":"Social Services",
            "subcategory":"Child Care",
            "type":"Services"
        }
    ],
    "sg:phone":"+61 2 9631 1862",
    "sg:postcode":"2145",
    "sg:province":"NSW",
    "sg:tags":[
        "support",
        "health"
    ],
    "wof:name":"Early Childhood Health Centres",
    "wof:placetype":"venue"
},
  "geometry": {"coordinates":[150.94433593799999,-33.829158783],"type":"Point"}
}