{
  "type": "Feature",
  "properties": {
    "addr:full":"127 Grigor St Caloundra QLD 4551",
    "addr:housenumber":"127",
    "addr:postcode":"4551",
    "addr:street":"Grigor St",
    "iso:country":"AU",
    "sg:address":"127 Grigor St",
    "sg:city":"Caloundra",
    "sg:classifiers":[
        {
            "category":"Building & Trades",
            "subcategory":"Construction",
            "type":"Services"
        }
    ],
    "sg:phone":"+61 419 675 335",
    "sg:postcode":"4551",
    "sg:province":"QLD",
    "sg:tags":[
        "renovation",
        "alterations",
        "extension",
        "contractor"
    ],
    "wof:name":"Caloundra Maintenance Service",
    "wof:placetype":"venue"
},
  "geometry": {"coordinates":[153.134857178,-26.7911472321],"type":"Point"}
}