{
  "type": "Feature",
  "properties": {
    "addr:full":"29 Pradella St Darra QLD 4076",
    "addr:housenumber":"29",
    "addr:postcode":"4076",
    "addr:street":"Pradella St",
    "iso:country":"AU",
    "sg:address":"29 Pradella St",
    "sg:city":"Darra",
    "sg:classifiers":[
        {
            "category":"Retail",
            "subcategory":"Auto Repair",
            "type":"Services"
        }
    ],
    "sg:phone":"+61 7 3375 5993",
    "sg:postcode":"4076",
    "sg:province":"QLD",
    "sg:tags":[
        "body",
        "builder",
        "motor"
    ],
    "wof:name":"StyroMax",
    "wof:placetype":"venue"
},
  "geometry": {"coordinates":[152.952102661,-27.5794963837],"type":"Point"}
}