{
  "type": "Feature",
  "properties": {
    "iso:country":"AU",
    "sg:address":"Unit 12 68 Marina Blv",
    "sg:city":"Darwin",
    "sg:classifiers":[
        {
            "category":"Real Estate",
            "subcategory":"Real Estate Agent",
            "type":"Services"
        }
    ],
    "sg:phone":"+61 8 8981 8980",
    "sg:postcode":"0800",
    "sg:province":"NT",
    "wof:name":"Chin Ernie & Cheryle",
    "wof:placetype":"venue"
},
  "geometry": {"coordinates":[130.821166992,-12.4514036179],"type":"Point"}
}