{
  "type": "Feature",
  "properties": {
    "iso:country":"AU",
    "sg:address":"4 Park St",
    "sg:city":"Seaford",
    "sg:classifiers":[
        {
            "category":"Government",
            "subcategory":"Post Office",
            "type":"Public Place"
        }
    ],
    "sg:phone":"+61 3 9786 8437",
    "sg:postcode":"3198",
    "sg:province":"VIC",
    "sg:tags":[
        "house",
        "doll"
    ],
    "wof:name":"Caroline Dolls",
    "wof:placetype":"venue"
},
  "geometry": {"coordinates":[145.13160705600001,-38.1026687622],"type":"Point"}
}