{
  "type": "Feature",
  "properties": {
    "addr:full":"1/ 829 Old Northern Rd Dural NSW 2158",
    "addr:housenumber":"/ 829",
    "addr:postcode":"2158",
    "addr:street":"Old Northern Rd",
    "iso:country":"AU",
    "sg:address":"1/ 829 Old Northern Rd",
    "sg:city":"Dural",
    "sg:classifiers":[
        {
            "category":"Home & Garden",
            "subcategory":"Carpets & Floor Coverings",
            "type":"Retail Goods"
        }
    ],
    "sg:phone":"+61 2 9651 2646",
    "sg:postcode":"2158",
    "sg:province":"NSW",
    "wof:name":"Newline Carpets",
    "wof:placetype":"venue"
},
  "geometry": {"coordinates":[151.03053283700001,-33.6961555481],"type":"Point"}
}