{
  "type": "Feature",
  "properties": {
    "iso:country":"AU",
    "sg:address":"30 Melinda Crt",
    "sg:city":"Kallangur",
    "sg:classifiers":[
        {
            "category":"Building & Trades",
            "subcategory":"Construction",
            "type":"Services"
        }
    ],
    "sg:phone":"+61 7 3285 3566",
    "sg:postcode":"4503",
    "sg:province":"QLD",
    "sg:tags":[
        "contractor"
    ],
    "wof:name":"Easton W R & S A",
    "wof:placetype":"venue"
},
  "geometry": {"coordinates":[152.983032227,-27.2519817352],"type":"Point"}
}