{
  "type": "Feature",
  "properties": {
    "addr:full":"Level 5, 234 George St Sydney NSW 2000",
    "addr:housenumber":"234",
    "addr:postcode":"2000",
    "addr:street":"George St",
    "iso:country":"AU",
    "sg:address":"Level 5, 234 George St",
    "sg:city":"Sydney",
    "sg:classifiers":[
        {
            "category":"Banks & Credit Unions",
            "subcategory":"Investment Brokerage",
            "type":"Services"
        }
    ],
    "sg:phone":"+61 2 9247 4452",
    "sg:postcode":"2000",
    "sg:province":"NSW",
    "sg:tags":[
        "share",
        "broker",
        "stock"
    ],
    "wof:name":"Reynolds Stockbrokers",
    "wof:placetype":"venue"
},
  "geometry": {"coordinates":[151.20765685999999,-33.8633384705],"type":"Point"}
}