{
  "type": "Feature",
  "properties": {
    "iso:country":"AU",
    "sg:address":"168 Cathedral St",
    "sg:city":"Woolloomooloo",
    "sg:classifiers":[
        {
            "category":"Health Services",
            "subcategory":"Doctor",
            "type":"Services"
        }
    ],
    "sg:phone":"+61 2 9357 2694",
    "sg:postcode":"2011",
    "sg:province":"NSW",
    "sg:tags":[
        "medical",
        "practitioner"
    ],
    "wof:name":"Foo Brian Dr",
    "wof:placetype":"venue"
},
  "geometry": {"coordinates":[151.21981811500001,-33.8727264404],"type":"Point"}
}