{
  "type": "Feature",
  "properties": {
    "addr:full":"9 Princes Rd Kingswood SA 5062",
    "addr:housenumber":"9",
    "addr:postcode":"5062",
    "addr:street":"Princes Rd",
    "iso:country":"AU",
    "sg:address":"9 Princes Rd",
    "sg:city":"Kingswood",
    "sg:classifiers":[
        {
            "category":"Health Services",
            "subcategory":"Health Practitioner",
            "type":"Services"
        }
    ],
    "sg:phone":"+61 8 8271 4122",
    "sg:postcode":"5062",
    "sg:province":"SA",
    "sg:tags":[
        "physiotherapist"
    ],
    "wof:name":"Mitcham Pilates Exercise",
    "wof:placetype":"venue"
},
  "geometry": {"coordinates":[138.61073303200001,-34.97473526],"type":"Point"}
}