{
  "type": "Feature",
  "properties": {
    "addr:full":"301 Frankston-Dandenong Rd Frankston North VIC 3200",
    "addr:housenumber":"301",
    "addr:postcode":"3200",
    "addr:street":"Frankston-Dandenong Rd",
    "iso:country":"AU",
    "sg:address":"301 Frankston-Dandenong Rd",
    "sg:city":"Frankston North",
    "sg:classifiers":[
        {
            "category":"Personal",
            "subcategory":"Beauty Salon",
            "type":"Services"
        }
    ],
    "sg:phone":"+61 411 526 203",
    "sg:postcode":"3200",
    "sg:province":"VIC",
    "sg:tags":[
        "hairdresser"
    ],
    "wof:name":"Jennifer's Mobile Hairdressing",
    "wof:placetype":"venue"
},
  "geometry": {"coordinates":[145.144867,-38.121559],"type":"Point"}
}