{
  "type": "Feature",
  "properties": {
    "addr:full":"Goodwood Rd Bundaberg QLD 4670",
    "addr:postcode":"4670",
    "addr:street":"Goodwood Rd",
    "iso:country":"AU",
    "sg:address":"Goodwood Rd",
    "sg:city":"Bundaberg",
    "sg:classifiers":[
        {
            "category":"Farming",
            "subcategory":"Farm",
            "type":"Manufacturing & Wholesale Goods"
        }
    ],
    "sg:phone":"+61 7 4159 7265",
    "sg:postcode":"4670",
    "sg:province":"QLD",
    "sg:tags":[
        "farmer"
    ],
    "wof:name":"Steinhardt Family Farms",
    "wof:placetype":"venue"
},
  "geometry": {"coordinates":[152.36213684099999,-24.8959350586],"type":"Point"}
}