{
  "type": "Feature",
  "properties": {
    "addr:full":"581A Grand Junction Rd Gepps Cross SA 5094",
    "addr:housenumber":"581a",
    "addr:postcode":"5094",
    "addr:street":"Grand Junction Rd",
    "iso:country":"AU",
    "sg:address":"581A Grand Junction Rd",
    "sg:city":"Gepps Cross",
    "sg:classifiers":[
        {
            "category":"Shopping",
            "subcategory":"Stationery & Office Supplies",
            "type":"Retail Goods"
        }
    ],
    "sg:phone":"+61 8 8168 2500",
    "sg:postcode":"5094",
    "sg:province":"SA",
    "sg:tags":[
        "equipment",
        "facsimile"
    ],
    "wof:name":"Officematrix Pty Ltd",
    "wof:placetype":"venue"
},
  "geometry": {"coordinates":[138.590896606,-34.8483772278],"type":"Point"}
}