{
  "type": "Feature",
  "properties": {
    "addr:full":"115 Weidlich Rd Eltham North VIC 3095",
    "addr:housenumber":"115",
    "addr:postcode":"3095",
    "addr:street":"Weidlich Rd",
    "iso:country":"AU",
    "sg:address":"115 Weidlich Rd",
    "sg:city":"Eltham North",
    "sg:classifiers":[
        {
            "category":"Retail",
            "subcategory":"Repair Shop",
            "type":"Services"
        }
    ],
    "sg:phone":"+61 3 9431 1151",
    "sg:postcode":"3095",
    "sg:province":"VIC",
    "sg:tags":[
        "leadlights"
    ],
    "wof:name":"Eltham Glasscraft",
    "wof:placetype":"venue"
},
  "geometry": {"coordinates":[145.13638305699999,-37.6965942383],"type":"Point"}
}