{
  "type": "Feature",
  "properties": {
    "addr:full":"172 Annerley Rd Dutton Park QLD 4102",
    "addr:housenumber":"172",
    "addr:postcode":"4102",
    "addr:street":"Annerley Rd",
    "iso:country":"AU",
    "sg:address":"172 Annerley Rd",
    "sg:city":"Dutton Park",
    "sg:classifiers":[
        {
            "category":"Professional",
            "subcategory":"Employment Agencies",
            "type":"Services"
        }
    ],
    "sg:phone":"+61 7 3846 0533",
    "sg:postcode":"4102",
    "sg:province":"QLD",
    "wof:name":"Jamieson McGeddes & Associates",
    "wof:placetype":"venue"
},
  "geometry": {"coordinates":[153.02775573700001,-27.4970645905],"type":"Point"}
}