{
  "type": "Feature",
  "properties": {
    "iso:country":"AU",
    "sg:address":"Raine Sq, Crn William & Wellington St",
    "sg:city":"Perth",
    "sg:classifiers":[
        {
            "category":"Shopping",
            "subcategory":"Bridal",
            "type":"Retail Goods"
        }
    ],
    "sg:phone":"+61 8 9486 9888",
    "sg:postcode":"6000",
    "sg:province":"WA",
    "sg:tags":[
        "hire",
        "wear"
    ],
    "wof:name":"Studio Collection",
    "wof:placetype":"venue"
},
  "geometry": {"coordinates":[115.85492706300001,-31.9502372742],"type":"Point"}
}