{
  "type": "Feature",
  "properties": {
    "addr:full":"136 Bromfield St Warrnambool VIC 3280",
    "addr:housenumber":"136",
    "addr:postcode":"3280",
    "addr:street":"Bromfield St",
    "iso:country":"AU",
    "sg:address":"136 Bromfield St",
    "sg:city":"Warrnambool",
    "sg:classifiers":[
        {
            "category":"Airline",
            "type":"Transportation"
        }
    ],
    "sg:phone":"+61 3 5561 5800",
    "sg:postcode":"3280",
    "sg:province":"VIC",
    "sg:tags":[
        "aircraft",
        "rental",
        "charter"
    ],
    "wof:name":"Helicopter Operators Australia Pty Ltd",
    "wof:placetype":"venue"
},
  "geometry": {"coordinates":[142.484130859,-38.3645629883],"type":"Point"}
}