{
  "type": "Feature",
  "properties": {
    "iso:country":"AU",
    "sg:address":"202a Bondi Rd",
    "sg:city":"Bondi",
    "sg:classifiers":[
        {
            "category":"Health Services",
            "subcategory":"Optometrist",
            "type":"Services"
        }
    ],
    "sg:phone":"+61 2 9369 3115",
    "sg:postcode":"2026",
    "sg:province":"NSW",
    "wof:name":"Alan Ryan Optometrist",
    "wof:placetype":"venue"
},
  "geometry": {"coordinates":[151.26307678200001,-33.8936653137],"type":"Point"}
}