{
  "type": "Feature",
  "properties": {
    "addr:full":"Elkin Ave Raymond Terrace NSW 2324",
    "addr:postcode":"2324",
    "addr:street":"Elkin Ave",
    "iso:country":"AU",
    "sg:address":"Elkin Ave",
    "sg:city":"Raymond Terrace",
    "sg:classifiers":[
        {
            "category":"Education",
            "subcategory":"School",
            "type":"Public Place"
        }
    ],
    "sg:phone":"+61 2 4987 2306",
    "sg:postcode":"2324",
    "sg:province":"NSW",
    "sg:tags":[
        "state",
        "-",
        "nsw"
    ],
    "wof:name":"Hunter River HIgh School",
    "wof:placetype":"venue"
},
  "geometry": {"coordinates":[151.73634338400001,-32.7815284729],"type":"Point"}
}