{
  "type": "Feature",
  "properties": {
    "addr:full":"77A Tattersal Rd Blacktown NSW 2148",
    "addr:housenumber":"77a",
    "addr:postcode":"2148",
    "addr:street":"Tattersal Rd",
    "iso:country":"AU",
    "sg:address":"77A Tattersal Rd",
    "sg:city":"Blacktown",
    "sg:classifiers":[
        {
            "category":"Home & Garden",
            "subcategory":"Building Materials",
            "type":"Retail Goods"
        }
    ],
    "sg:phone":"+61 2 9542 4242",
    "sg:postcode":"2148",
    "sg:province":"NSW",
    "sg:tags":[
        "pre-mixed",
        "concrete"
    ],
    "wof:name":"Concrite Pty Limited",
    "wof:placetype":"venue"
},
  "geometry": {"coordinates":[150.90951538100001,-33.7485466003],"type":"Point"}
}