{
  "type": "Feature",
  "properties": {
    "addr:full":"Unit 2 1283 Kingsford Smith Drv Eagle Farm QLD 4009",
    "addr:housenumber":"1283",
    "addr:postcode":"4009",
    "addr:street":"Kingsford Smith Drv",
    "iso:country":"AU",
    "sg:address":"Unit 2 1283 Kingsford Smith Drv",
    "sg:city":"Eagle Farm",
    "sg:classifiers":[
        {
            "category":"Wholesale",
            "subcategory":"Construction Materials",
            "type":"Manufacturing & Wholesale Goods"
        }
    ],
    "sg:phone":"+61 7 3260 2511",
    "sg:postcode":"4009",
    "sg:province":"QLD",
    "sg:tags":[
        "wholesaler",
        "lighting",
        "mfrs",
        "accessory"
    ],
    "wof:name":"Interpole Pty Ltd",
    "wof:placetype":"venue"
},
  "geometry": {"coordinates":[153.10777282699999,-27.4301166534],"type":"Point"}
}