{
  "type": "Feature",
  "properties": {
    "addr:full":"11 Palmerston St Maryborough VIC 3465",
    "addr:housenumber":"11",
    "addr:postcode":"3465",
    "addr:street":"Palmerston St",
    "iso:country":"AU",
    "sg:address":"11 Palmerston St",
    "sg:city":"Maryborough",
    "sg:classifiers":[
        {
            "category":"Professional",
            "subcategory":"Engineering",
            "type":"Services"
        }
    ],
    "sg:phone":"+61 3 5461 1408",
    "sg:postcode":"3465",
    "sg:province":"VIC",
    "sg:tags":[
        "engineer"
    ],
    "wof:name":"Bartlett & Sons",
    "wof:placetype":"venue"
},
  "geometry": {"coordinates":[143.732345581,-37.046787262],"type":"Point"}
}