{
  "type": "Feature",
  "properties": {
    "addr:full":"1 Pearson St Kingswood NSW 2747",
    "addr:housenumber":"1",
    "addr:postcode":"2747",
    "addr:street":"Pearson St",
    "iso:country":"AU",
    "sg:address":"1 Pearson St",
    "sg:city":"Kingswood",
    "sg:classifiers":[
        {
            "category":"Building & Trades",
            "subcategory":"Pest Control",
            "type":"Services"
        }
    ],
    "sg:phone":"+61 2 4736 6015",
    "sg:postcode":"2747",
    "sg:province":"NSW",
    "wof:name":"Resolve Pest Services",
    "wof:placetype":"venue"
},
  "geometry": {"coordinates":[150.71636962900001,-33.7619514465],"type":"Point"}
}