{
  "type": "Feature",
  "properties": {
    "iso:country":"AU",
    "sg:address":"31 Dundas St",
    "sg:city":"Bacchus Marsh",
    "sg:classifiers":[
        {
            "category":"Building & Trades",
            "subcategory":"Construction",
            "type":"Services"
        }
    ],
    "sg:phone":"+61 3 5367 4042",
    "sg:postcode":"3340",
    "sg:province":"VIC",
    "sg:tags":[
        "earth",
        "excavating",
        "moving",
        "contractor"
    ],
    "wof:name":"Taffe's Bobcat & Tipper Hire",
    "wof:placetype":"venue"
},
  "geometry": {"coordinates":[144.440033,-37.655655],"type":"Point"}
}