{
  "type": "Feature",
  "properties": {
    "addr:full":"Dean St Albury NSW 2640",
    "addr:postcode":"2640",
    "addr:street":"Dean St",
    "iso:country":"AU",
    "sg:address":"Dean St",
    "sg:city":"Albury",
    "sg:classifiers":[
        {
            "category":"Personal",
            "subcategory":"Beauty Salon",
            "type":"Services"
        }
    ],
    "sg:phone":"+61 403 681 059",
    "sg:postcode":"2640",
    "sg:province":"NSW",
    "wof:name":"Angie Vaccaro Beauty Therapy",
    "wof:placetype":"venue"
},
  "geometry": {"coordinates":[146.905197144,-36.0793991089],"type":"Point"}
}