{
  "type": "Feature",
  "properties": {
    "iso:country":"AU",
    "sg:address":"Cnr Steptoe & Steindl Sts",
    "sg:city":"Bundaberg",
    "sg:classifiers":[
        {
            "category":"Professional",
            "subcategory":"Computer Services",
            "type":"Services"
        }
    ],
    "sg:phone":"+61 7 4151 0614",
    "sg:postcode":"4670",
    "sg:province":"QLD",
    "sg:tags":[
        "repairs",
        "upgrade",
        "equipment"
    ],
    "wof:name":"Bundaberg I.T. Support",
    "wof:placetype":"venue"
},
  "geometry": {"coordinates":[152.375686645,-24.8650894165],"type":"Point"}
}