{
  "type": "Feature",
  "properties": {
    "iso:country":"AU",
    "sg:address":"735 Gympie Rd",
    "sg:city":"Chermside",
    "sg:classifiers":[
        {
            "category":"Fast Food",
            "type":"Food & Drink"
        }
    ],
    "sg:phone":"+61 7 3359 7557",
    "sg:postcode":"4032",
    "sg:province":"QLD",
    "sg:tags":[
        "away",
        "take"
    ],
    "wof:name":"New Chungshan Restaurant",
    "wof:placetype":"venue"
},
  "geometry": {"coordinates":[153.030945,-27.388407],"type":"Point"}
}