{
  "type": "Feature",
  "properties": {
    "iso:country":"AU",
    "sg:address":"Ste 3, 417- 419 Peel St",
    "sg:city":"Tamworth",
    "sg:classifiers":[
        {
            "category":"Professional",
            "subcategory":"Accounting & Tax Preparation",
            "type":"Services"
        }
    ],
    "sg:phone":"+61 2 6766 3777",
    "sg:postcode":"2340",
    "sg:province":"NSW",
    "sg:tags":[
        "accountant",
        "auditor"
    ],
    "wof:name":"Morgan-Jones & Co",
    "wof:placetype":"venue"
},
  "geometry": {"coordinates":[150.931106567,-31.0921821594],"type":"Point"}
}