{
  "type": "Feature",
  "properties": {
    "addr:full":"1 Cordeaux St Campbelltown NSW 2560",
    "addr:housenumber":"1",
    "addr:postcode":"2560",
    "addr:street":"Cordeaux St",
    "iso:country":"AU",
    "sg:address":"1 Cordeaux St",
    "sg:city":"Campbelltown",
    "sg:classifiers":[
        {
            "category":"Health Services",
            "subcategory":"Dentist",
            "type":"Services"
        }
    ],
    "sg:phone":"+61 1300 132 228",
    "sg:postcode":"2560",
    "sg:province":"NSW",
    "sg:tags":[
        "state",
        "orthodontist",
        "qld",
        "exc"
    ],
    "sg:website":"http://www.orthodontic.net.au",
    "wof:name":"Dr Chris Van Vuuren's Orthodontic Surgery",
    "wof:placetype":"venue"
},
  "geometry": {"coordinates":[150.815109253,-34.0660018921],"type":"Point"}
}