{
  "type": "Feature",
  "properties": {
    "iso:country":"AU",
    "sg:address":"Dugal St",
    "sg:city":"Warwick",
    "sg:classifiers":[
        {
            "category":"Building & Trades",
            "subcategory":"Equipment Rental",
            "type":"Services"
        }
    ],
    "sg:phone":"+61 8 9243 0000",
    "sg:postcode":"6024",
    "sg:province":"WA",
    "sg:tags":[
        "fitness"
    ],
    "wof:name":"Energym International",
    "wof:placetype":"venue"
},
  "geometry": {"coordinates":[115.807876587,-31.8427181244],"type":"Point"}
}