{
  "type": "Feature",
  "properties": {
    "addr:full":"621a Princes Hwy Blakehurst NSW 2221",
    "addr:housenumber":"621a",
    "addr:postcode":"2221",
    "addr:street":"Princes Hwy",
    "iso:country":"AU",
    "sg:address":"621a Princes Hwy",
    "sg:city":"Blakehurst",
    "sg:classifiers":[
        {
            "category":"Real Estate",
            "subcategory":"Real Estate Agent",
            "type":"Services"
        }
    ],
    "sg:phone":"+61 2 9546 2192",
    "sg:postcode":"2221",
    "sg:province":"NSW",
    "wof:name":"Century 21 Auction Department NSW",
    "wof:placetype":"venue"
},
  "geometry": {"coordinates":[151.111694336,-33.988319397],"type":"Point"}
}