{
  "type": "Feature",
  "properties": {
    "iso:country":"AU",
    "sg:address":"2/ 59 Kinross Drv",
    "sg:city":"Kinross",
    "sg:classifiers":[
        {
            "category":"Health Services",
            "subcategory":"Dentist",
            "type":"Services"
        }
    ],
    "sg:phone":"+61 8 9305 6600",
    "sg:postcode":"6028",
    "sg:province":"WA",
    "wof:name":"Kinross Dental",
    "wof:placetype":"venue"
},
  "geometry": {"coordinates":[115.735679627,-31.719619751],"type":"Point"}
}