{
  "type": "Feature",
  "properties": {
    "iso:country":"AU",
    "sg:address":"92 Moruya Drv",
    "sg:city":"Grovedale",
    "sg:classifiers":[
        {
            "category":"Professional",
            "subcategory":"Computer Services",
            "type":"Services"
        }
    ],
    "sg:phone":"+61 419 106 179",
    "sg:postcode":"3216",
    "sg:province":"VIC",
    "sg:tags":[
        "consultant",
        "system"
    ],
    "wof:name":"Notesworks",
    "wof:placetype":"venue"
},
  "geometry": {"coordinates":[144.31738281200001,-38.2076416016],"type":"Point"}
}