{
  "type": "Feature",
  "properties": {
    "addr:full":"18 Furley St Aspley QLD 4034",
    "addr:housenumber":"18",
    "addr:postcode":"4034",
    "addr:street":"Furley St",
    "iso:country":"AU",
    "sg:address":"18 Furley St",
    "sg:city":"Aspley",
    "sg:classifiers":[
        {
            "category":"Health Services",
            "subcategory":"Health Practitioner",
            "type":"Services"
        }
    ],
    "sg:phone":"+61 402 992 100",
    "sg:postcode":"4034",
    "sg:province":"QLD",
    "sg:tags":[
        "hypnotherapy"
    ],
    "wof:name":"Hennessy Joanne",
    "wof:placetype":"venue"
},
  "geometry": {"coordinates":[153.019058,-27.365253],"type":"Point"}
}