{
  "type": "Feature",
  "properties": {
    "addr:full":"42a McLeod St Cairns QLD 4870",
    "addr:housenumber":"42a",
    "addr:postcode":"4870",
    "addr:street":"Mcleod St",
    "iso:country":"AU",
    "sg:address":"42a McLeod St",
    "sg:city":"Cairns",
    "sg:classifiers":[
        {
            "category":"Real Estate",
            "subcategory":"Real Estate Agent",
            "type":"Services"
        }
    ],
    "sg:phone":"+61 7 4051 8000",
    "sg:postcode":"4870",
    "sg:province":"QLD",
    "wof:name":"Taylor Jones Property",
    "wof:placetype":"venue"
},
  "geometry": {"coordinates":[145.77244567899999,-16.9238758087],"type":"Point"}
}