{
  "type": "Feature",
  "properties": {
    "addr:full":"24 Rostrevor Pde Mont Albert North VIC 3129",
    "addr:housenumber":"24",
    "addr:postcode":"3129",
    "addr:street":"Rostrevor Pde",
    "iso:country":"AU",
    "sg:address":"24 Rostrevor Pde",
    "sg:city":"Mont Albert North",
    "sg:classifiers":[
        {
            "category":"Arts & Performance",
            "subcategory":"Dance",
            "type":"Entertainment"
        }
    ],
    "sg:phone":"+61 3 9857 3262",
    "sg:postcode":"3129",
    "sg:province":"VIC",
    "sg:tags":[
        "theatrical",
        "ballet",
        "tuition"
    ],
    "wof:name":"Mont Albert Ballet School",
    "wof:placetype":"venue"
},
  "geometry": {"coordinates":[145.10671997099999,-37.8102531433],"type":"Point"}
}