{
  "type": "Feature",
  "properties": {
    "iso:country":"AU",
    "sg:address":"Suite 25, 15- 17 Phillip St",
    "sg:city":"Parramatta",
    "sg:classifiers":[
        {
            "category":"Professional",
            "subcategory":"Accounting & Tax Preparation",
            "type":"Services"
        }
    ],
    "sg:phone":"+61 2 9687 0001",
    "sg:postcode":"2150",
    "sg:province":"NSW",
    "sg:tags":[
        "accountant",
        "auditor"
    ],
    "wof:name":"Success Accounting Services",
    "wof:placetype":"venue"
},
  "geometry": {"coordinates":[151.02377319300001,-33.7962532043],"type":"Point"}
}