{
  "type": "Feature",
  "properties": {
    "iso:country":"AU",
    "sg:address":"6 Buchanan St",
    "sg:city":"Nailsworth",
    "sg:classifiers":[
        {
            "category":"Professional",
            "subcategory":"Detective & Security Services",
            "type":"Services"
        }
    ],
    "sg:phone":"+61 407 770 987",
    "sg:postcode":"5083",
    "sg:province":"SA",
    "sg:tags":[
        "consultant",
        "system"
    ],
    "wof:name":"Zap Electrical & Security",
    "wof:placetype":"venue"
},
  "geometry": {"coordinates":[138.60609435999999,-34.8820724487],"type":"Point"}
}