{
  "type": "Feature",
  "properties": {
    "addr:full":"20 Symmons St Bunbury WA 6230",
    "addr:housenumber":"20",
    "addr:postcode":"6230",
    "addr:street":"Symmons St",
    "iso:country":"AU",
    "sg:address":"20 Symmons St",
    "sg:city":"Bunbury",
    "sg:classifiers":[
        {
            "category":"Restaurant",
            "type":"Food & Drink"
        }
    ],
    "sg:phone":"+61 8 9721 9966",
    "sg:postcode":"6230",
    "sg:province":"WA",
    "wof:name":"Barons Restaurant",
    "wof:placetype":"venue"
},
  "geometry": {"coordinates":[115.63623800000001,-33.323135],"type":"Point"}
}