{
  "type": "Feature",
  "properties": {
    "addr:full":"50 Eucalyptus Crs Metford NSW 2323",
    "addr:housenumber":"50",
    "addr:postcode":"2323",
    "addr:street":"Eucalyptus Crs",
    "iso:country":"AU",
    "sg:address":"50 Eucalyptus Crs",
    "sg:city":"Metford",
    "sg:classifiers":[
        {
            "category":"Professional",
            "subcategory":"Accounting & Tax Preparation",
            "type":"Services"
        }
    ],
    "sg:phone":"+61 2 4936 6647",
    "sg:postcode":"2323",
    "sg:province":"NSW",
    "sg:tags":[
        "bookkeeping"
    ],
    "wof:name":"Hunters Mobile Bookkeeping",
    "wof:placetype":"venue"
},
  "geometry": {"coordinates":[151.60096740700001,-32.7607192993],"type":"Point"}
}