{
  "type": "Feature",
  "properties": {
    "iso:country":"AU",
    "sg:address":"21 Milroy St",
    "sg:city":"Brighton East",
    "sg:classifiers":[
        {
            "category":"Building & Trades",
            "subcategory":"Landscaping Services",
            "type":"Services"
        }
    ],
    "sg:phone":"+61 412 318 355",
    "sg:postcode":"3187",
    "sg:province":"VIC",
    "sg:tags":[
        "designer",
        "landscape",
        "contractor"
    ],
    "wof:name":"Margot's Gardens",
    "wof:placetype":"venue"
},
  "geometry": {"coordinates":[145.01272582999999,-37.9032058716],"type":"Point"}
}