{
  "type": "Feature",
  "properties": {
    "iso:country":"AU",
    "sg:address":"73 Hesse St",
    "sg:city":"Queenscliff",
    "sg:classifiers":[
        {
            "category":"Food & Beverages",
            "subcategory":"Supermarket",
            "type":"Retail Goods"
        }
    ],
    "sg:phone":"+61 3 5258 2328",
    "sg:postcode":"3225",
    "sg:province":"VIC",
    "sg:tags":[
        "grocery",
        "store"
    ],
    "wof:name":"Queenscliff IGA & Liquor",
    "wof:placetype":"venue"
},
  "geometry": {"coordinates":[144.660614,-38.268574],"type":"Point"}
}