{
  "type": "Feature",
  "properties": {
    "iso:country":"AU",
    "sg:address":"378- 382 Clarendon St",
    "sg:city":"South Melbourne",
    "sg:classifiers":[
        {
            "category":"Autos & Motor Vehicles",
            "subcategory":"Boat Sales",
            "type":"Retail Goods"
        }
    ],
    "sg:phone":"+61 3 9696 2566",
    "sg:postcode":"3205",
    "sg:province":"VIC",
    "sg:tags":[
        "machine",
        "dishwashing"
    ],
    "wof:name":"Jos Van Bree Kitchen Architecture",
    "wof:placetype":"venue"
},
  "geometry": {"coordinates":[144.961655,-37.835735],"type":"Point"}
}