{
  "type": "Feature",
  "properties": {
    "addr:full":"35 Rosewarne Ave Cheltenham VIC 3192",
    "addr:housenumber":"35",
    "addr:postcode":"3192",
    "addr:street":"Rosewarne Ave",
    "iso:country":"AU",
    "sg:address":"35 Rosewarne Ave",
    "sg:city":"Cheltenham",
    "sg:classifiers":[
        {
            "category":"Shopping",
            "subcategory":"Computers & Home Electronics",
            "type":"Retail Goods"
        }
    ],
    "sg:phone":"+61 3 9584 2386",
    "sg:postcode":"3192",
    "sg:province":"VIC",
    "sg:tags":[
        "equipment",
        "part",
        "electronic"
    ],
    "wof:name":"Talking Electronics",
    "wof:placetype":"venue"
},
  "geometry": {"coordinates":[145.06329345699999,-37.9540863037],"type":"Point"}
}