{
  "type": "Feature",
  "properties": {
    "addr:full":"Loftus Ave Loftus NSW 2232",
    "addr:postcode":"2232",
    "addr:street":"Loftus Ave",
    "iso:country":"AU",
    "sg:address":"Loftus Ave",
    "sg:city":"Loftus",
    "sg:classifiers":[
        {
            "category":"Government",
            "subcategory":"City Hall",
            "type":"Public Place"
        }
    ],
    "sg:phone":"+61 2 9545 0371",
    "sg:postcode":"2232",
    "sg:province":"NSW",
    "wof:name":"Loftus Community Hall",
    "wof:placetype":"venue"
},
  "geometry": {"coordinates":[151.049438477,-34.0512466431],"type":"Point"}
}