{
  "type": "Feature",
  "properties": {
    "iso:country":"AU",
    "sg:address":"80 Monyash Rd",
    "sg:city":"Carine",
    "sg:classifiers":[
        {
            "category":"Shopping",
            "subcategory":"Computers & Home Electronics",
            "type":"Retail Goods"
        }
    ],
    "sg:phone":"+61 8 9246 4772",
    "sg:postcode":"6020",
    "sg:province":"WA",
    "sg:tags":[
        "small",
        "equipment",
        "business"
    ],
    "wof:name":"Info POS",
    "wof:placetype":"venue"
},
  "geometry": {"coordinates":[115.79032135,-31.8555927277],"type":"Point"}
}