{
  "type": "Feature",
  "properties": {
    "addr:full":"PO Box 1422 Springwood QLD 4127",
    "addr:postcode":"4127",
    "iso:country":"AU",
    "sg:address":"PO Box 1422",
    "sg:city":"Springwood",
    "sg:classifiers":[
        {
            "category":"Banks & Credit Unions",
            "subcategory":"Investment Brokerage",
            "type":"Services"
        }
    ],
    "sg:phone":"+61 418 880 227",
    "sg:postcode":"4127",
    "sg:province":"QLD",
    "sg:tags":[
        "broker"
    ],
    "wof:name":"Complete Auto Search & Disposal",
    "wof:placetype":"venue"
},
  "geometry": {"coordinates":[153.13209533700001,-27.6174602509],"type":"Point"}
}