{
  "type": "Feature",
  "properties": {
    "iso:country":"AU",
    "sg:address":"PO Box 652",
    "sg:city":"Helensvale",
    "sg:classifiers":[
        {
            "category":"Building & Trades",
            "subcategory":"Construction",
            "type":"Services"
        }
    ],
    "sg:phone":"+61 404 256 003",
    "sg:postcode":"4212",
    "sg:province":"QLD",
    "sg:tags":[
        "fencing",
        "contractor"
    ],
    "wof:name":"Barrier Fencing Australia",
    "wof:placetype":"venue"
},
  "geometry": {"coordinates":[153.338256836,-27.9241008759],"type":"Point"}
}