{
  "type": "Feature",
  "properties": {
    "iso:country":"AU",
    "sg:address":"Lot 9 Gunning Rd",
    "sg:city":"Naracoorte",
    "sg:classifiers":[
        {
            "category":"Building & Trades",
            "subcategory":"Construction",
            "type":"Services"
        }
    ],
    "sg:phone":"+61 8 8762 2792",
    "sg:postcode":"5271",
    "sg:province":"SA",
    "sg:tags":[
        "contractor"
    ],
    "wof:name":"Biggins M R & J M",
    "wof:placetype":"venue"
},
  "geometry": {"coordinates":[140.730087,-36.95422],"type":"Point"}
}