{
  "type": "Feature",
  "properties": {
    "addr:full":"Unti 36 566 Gardeners Rd Alexandria NSW 2015",
    "addr:housenumber":"36",
    "addr:postcode":"566;2015",
    "addr:street":"Unti;Gardeners Rd",
    "iso:country":"AU",
    "sg:address":"Unti 36 566 Gardeners Rd",
    "sg:city":"Alexandria",
    "sg:classifiers":[
        {
            "category":"Shopping",
            "subcategory":"Musical Instruments",
            "type":"Retail Goods"
        }
    ],
    "sg:phone":"+61 2 9667 4323",
    "sg:postcode":"2015",
    "sg:province":"NSW",
    "sg:tags":[
        "piano",
        "organ"
    ],
    "wof:name":"Ebony & Ivory",
    "wof:placetype":"venue"
},
  "geometry": {"coordinates":[151.18490600600001,-33.9198188782],"type":"Point"}
}