{
  "type": "Feature",
  "properties": {
    "addr:full":"20 Green St Joondanna WA 6060",
    "addr:housenumber":"20",
    "addr:postcode":"6060",
    "addr:street":"Green St",
    "iso:country":"AU",
    "sg:address":"20 Green St",
    "sg:city":"Joondanna",
    "sg:classifiers":[
        {
            "category":"Professional",
            "subcategory":"Business Services",
            "type":"Services"
        }
    ],
    "sg:phone":"+61 8 9444 7469",
    "sg:postcode":"6060",
    "sg:province":"WA",
    "sg:tags":[
        "exporter"
    ],
    "wof:name":"Monek International",
    "wof:placetype":"venue"
},
  "geometry": {"coordinates":[115.843772888,-31.9139671326],"type":"Point"}
}