{
  "type": "Feature",
  "properties": {
    "addr:full":"77 Macquarie St Windsor NSW 2756",
    "addr:housenumber":"77",
    "addr:postcode":"2756",
    "addr:street":"Macquarie St",
    "iso:country":"AU",
    "sg:address":"77 Macquarie St",
    "sg:city":"Windsor",
    "sg:classifiers":[
        {
            "category":"Health Services",
            "subcategory":"Doctor",
            "type":"Services"
        }
    ],
    "sg:phone":"+61 2 4577 4500",
    "sg:postcode":"2756",
    "sg:province":"NSW",
    "sg:tags":[
        "medical",
        "practitioner"
    ],
    "wof:name":"Moss Geoffrey",
    "wof:placetype":"venue"
},
  "geometry": {"coordinates":[150.82044982900001,-33.6078567505],"type":"Point"}
}