{
  "type": "Feature",
  "properties": {
    "iso:country":"AU",
    "sg:address":"15 Delta St",
    "sg:city":"Geebung",
    "sg:classifiers":[
        {
            "category":"Home & Garden",
            "subcategory":"Building Materials",
            "type":"Retail Goods"
        }
    ],
    "sg:phone":"+61 7 3265 4591",
    "sg:postcode":"4034",
    "sg:province":"QLD",
    "sg:tags":[
        "gate"
    ],
    "wof:name":"N.L. Plumb & Co Pty Ltd",
    "wof:placetype":"venue"
},
  "geometry": {"coordinates":[153.049622,-27.365931],"type":"Point"}
}