{
  "type": "Feature",
  "properties": {
    "addr:full":"16 Boundary St Bundaberg QLD 4670",
    "addr:housenumber":"16",
    "addr:postcode":"4670",
    "addr:street":"Boundary St",
    "iso:country":"AU",
    "sg:address":"16 Boundary St",
    "sg:city":"Bundaberg",
    "sg:classifiers":[
        {
            "category":"Food & Beverages",
            "subcategory":"Groceries & Convenience Stores",
            "type":"Retail Goods"
        }
    ],
    "sg:phone":"+61 7 4152 2100",
    "sg:postcode":"4670",
    "sg:province":"QLD",
    "wof:name":"Five Ways Food Store",
    "wof:placetype":"venue"
},
  "geometry": {"coordinates":[152.36221313499999,-24.8720874786],"type":"Point"}
}