{
  "type": "Feature",
  "properties": {
    "addr:full":"13 Nelson St Nhill VIC 3418",
    "addr:housenumber":"13",
    "addr:postcode":"3418",
    "addr:street":"Nelson St",
    "iso:country":"AU",
    "sg:address":"13 Nelson St",
    "sg:city":"Nhill",
    "sg:classifiers":[
        {
            "category":"Farming",
            "subcategory":"Farm",
            "type":"Manufacturing & Wholesale Goods"
        }
    ],
    "sg:phone":"+61 3 5391 1105",
    "sg:postcode":"3418",
    "sg:province":"VIC",
    "sg:tags":[
        "farmer"
    ],
    "wof:name":"Dahlenburg K F",
    "wof:placetype":"venue"
},
  "geometry": {"coordinates":[141.66113281200001,-36.3342552185],"type":"Point"}
}