{
  "type": "Feature",
  "properties": {
    "iso:country":"AU",
    "sg:address":"34 Lynch St",
    "sg:city":"Hawthorn",
    "sg:classifiers":[
        {
            "category":"Manufacturing",
            "subcategory":"Building Materials",
            "type":"Manufacturing & Wholesale Goods"
        }
    ],
    "sg:phone":"+61 3 9815 0644",
    "sg:postcode":"3122",
    "sg:province":"VIC",
    "sg:tags":[
        "stone",
        "product",
        "supply"
    ],
    "sg:website":"http://www.leisurestone.com.au",
    "wof:name":"Leisure Stone",
    "wof:placetype":"venue"
},
  "geometry": {"coordinates":[145.02903747600001,-37.8212394714],"type":"Point"}
}