{
  "type": "Feature",
  "properties": {
    "addr:full":"4 Wandeara Crs Mundaring WA 6073",
    "addr:housenumber":"4",
    "addr:postcode":"6073",
    "addr:street":"Wandeara Crs",
    "iso:country":"AU",
    "sg:address":"4 Wandeara Crs",
    "sg:city":"Mundaring",
    "sg:classifiers":[
        {
            "category":"Fast Food",
            "type":"Food & Drink"
        }
    ],
    "sg:phone":"+61 8 9295 1966",
    "sg:postcode":"6073",
    "sg:province":"WA",
    "sg:tags":[
        "away",
        "take"
    ],
    "wof:name":"Flavours Lunchbar & Cafe",
    "wof:placetype":"venue"
},
  "geometry": {"coordinates":[116.167037964,-31.921880722],"type":"Point"}
}