{
  "type": "Feature",
  "properties": {
    "addr:full":"Grand Plaza Shopng Cntr Cnr Mt Lindesay Hwy & Browns Plains Rd Browns Plains QLD 4118",
    "addr:postcode":"4118",
    "addr:street":"Cnr Mt Lindesay Hwy & Browns Plains Rd",
    "iso:country":"AU",
    "sg:address":"Grand Plaza Shopng Cntr Cnr Mt Lindesay Hwy & Browns Plains Rd",
    "sg:city":"Browns Plains",
    "sg:classifiers":[
        {
            "category":"Health Services",
            "subcategory":"Optometrist",
            "type":"Services"
        }
    ],
    "sg:phone":"+61 7 3809 0992",
    "sg:postcode":"4118",
    "sg:province":"QLD",
    "wof:name":"Optical Warehouse",
    "wof:placetype":"venue"
},
  "geometry": {"coordinates":[153.03956604000001,-27.6560783386],"type":"Point"}
}