{
  "type": "Feature",
  "properties": {
    "addr:full":"152-160 Falls Rd Olinda VIC 3788",
    "addr:housenumber":"152-160",
    "addr:postcode":"3788",
    "addr:street":"Falls Rd",
    "iso:country":"AU",
    "sg:address":"152-160 Falls Rd",
    "sg:city":"Olinda",
    "sg:classifiers":[
        {
            "category":"Building & Trades",
            "subcategory":"Construction",
            "type":"Services"
        }
    ],
    "sg:phone":"+61 3 9751 2625",
    "sg:postcode":"3788",
    "sg:province":"VIC",
    "sg:tags":[
        "renovation",
        "alterations",
        "extension",
        "contractor"
    ],
    "wof:name":"M.C Elite Design & Constuction Pty Ltd",
    "wof:placetype":"venue"
},
  "geometry": {"coordinates":[145.37150600000001,-37.847687],"type":"Point"}
}