{
  "type": "Feature",
  "properties": {
    "addr:full":"10 Voyager Pl Mandurah WA 6210",
    "addr:housenumber":"10",
    "addr:postcode":"6210",
    "addr:street":"Voyager Pl",
    "iso:country":"AU",
    "sg:address":"10 Voyager Pl",
    "sg:city":"Mandurah",
    "sg:classifiers":[
        {
            "category":"Retail",
            "subcategory":"Auto Rental",
            "type":"Services"
        }
    ],
    "sg:phone":"+61 413 053 347",
    "sg:postcode":"6210",
    "sg:province":"WA",
    "sg:tags":[
        "car",
        "hire",
        "minibus"
    ],
    "wof:name":"Action Hire Cars",
    "wof:placetype":"venue"
},
  "geometry": {"coordinates":[115.635132,-32.600342],"type":"Point"}
}