{
  "type": "Feature",
  "properties": {
    "iso:country":"AU",
    "sg:address":"Unit 9/ 2 Leake St",
    "sg:city":"South Hedland",
    "sg:classifiers":[
        {
            "category":"Government",
            "subcategory":"Court House",
            "type":"Public Place"
        }
    ],
    "sg:phone":"+61 8 9172 3853",
    "sg:postcode":"6722",
    "sg:province":"WA",
    "sg:tags":[
        "personal",
        "marriage",
        "family",
        "counselling"
    ],
    "wof:name":"Victim Support Service",
    "wof:placetype":"venue"
},
  "geometry": {"coordinates":[118.602226257,-20.4117431641],"type":"Point"}
}