{
  "type": "Feature",
  "properties": {
    "iso:country":"AU",
    "sg:address":"Shop 3/ 225 Main Rd",
    "sg:city":"Blackwood",
    "sg:classifiers":[
        {
            "category":"Personal",
            "subcategory":"Beauty Salon",
            "type":"Services"
        }
    ],
    "sg:phone":"+61 8 8278 5077",
    "sg:postcode":"5051",
    "sg:province":"SA",
    "sg:tags":[
        "hairdresser"
    ],
    "wof:name":"Boskos Men's Hair Stylist",
    "wof:placetype":"venue"
},
  "geometry": {"coordinates":[138.616425,-35.018879],"type":"Point"}
}