{
  "type": "Feature",
  "properties": {
    "addr:full":"Shp10/ 169 Annangrove Rd Annangrove NSW 2156",
    "addr:housenumber":"169",
    "addr:postcode":"2156",
    "addr:street":"Annangrove Rd",
    "iso:country":"AU",
    "sg:address":"Shp10/ 169 Annangrove Rd",
    "sg:city":"Annangrove",
    "sg:classifiers":[
        {
            "category":"Personal",
            "subcategory":"Beauty Salon",
            "type":"Services"
        }
    ],
    "sg:phone":"+61 2 9679 2392",
    "sg:postcode":"2156",
    "sg:province":"NSW",
    "sg:tags":[
        "hairdresser"
    ],
    "wof:name":"Lous House Of Hair",
    "wof:placetype":"venue"
},
  "geometry": {"coordinates":[150.955078125,-33.6710281372],"type":"Point"}
}