{
  "type": "Feature",
  "properties": {
    "addr:full":"82 McLaughlin St Kawana QLD 4701",
    "addr:housenumber":"82",
    "addr:postcode":"4701",
    "addr:street":"Mclaughlin St",
    "iso:country":"AU",
    "sg:address":"82 McLaughlin St",
    "sg:city":"Kawana",
    "sg:classifiers":[
        {
            "category":"Building & Trades",
            "subcategory":"Landscaping Services",
            "type":"Services"
        }
    ],
    "sg:phone":"+61 7 4936 3544",
    "sg:postcode":"4701",
    "sg:province":"QLD",
    "sg:tags":[
        "stump",
        "tree",
        "felling",
        "removal"
    ],
    "wof:name":"Eastern Tree Service",
    "wof:placetype":"venue"
},
  "geometry": {"coordinates":[150.51167297399999,-23.3342456818],"type":"Point"}
}