{
  "type": "Feature",
  "properties": {
    "addr:full":"2 21 Cummings St Wodonga VIC 3689",
    "addr:housenumber":"21",
    "addr:postcode":"3689",
    "addr:street":"2;Cummings St",
    "iso:country":"AU",
    "sg:address":"2 21 Cummings St",
    "sg:city":"Wodonga",
    "sg:classifiers":[
        {
            "category":"Education",
            "subcategory":"Music School",
            "type":"Public Place"
        }
    ],
    "sg:phone":"+61 402 901 650",
    "sg:postcode":"3689",
    "sg:province":"VIC",
    "sg:tags":[
        "teacher"
    ],
    "wof:name":"Clark Pieper",
    "wof:placetype":"venue"
},
  "geometry": {"coordinates":[146.885559,-36.128483],"type":"Point"}
}