{
  "type": "Feature",
  "properties": {
    "iso:country":"AU",
    "sg:address":"177- 179 Melbourne Rd",
    "sg:city":"North Geelong",
    "sg:classifiers":[
        {
            "category":"Home & Garden",
            "subcategory":"Building Materials",
            "type":"Retail Goods"
        }
    ],
    "sg:phone":"+61 3 5272 2877",
    "sg:postcode":"3215",
    "sg:province":"VIC",
    "sg:tags":[
        "merchant",
        "glass",
        "glazier"
    ],
    "wof:name":"The Glass Man",
    "wof:placetype":"venue"
},
  "geometry": {"coordinates":[144.34864807100001,-38.1114006042],"type":"Point"}
}