{
  "type": "Feature",
  "properties": {
    "addr:full":"U4/ 20 Tilba St Berala NSW 2141",
    "addr:housenumber":"20",
    "addr:postcode":"2141",
    "addr:street":"U4 /;Tilba St",
    "iso:country":"AU",
    "sg:address":"U4/ 20 Tilba St",
    "sg:city":"Berala",
    "sg:classifiers":[
        {
            "category":"Building & Trades",
            "subcategory":"Construction",
            "type":"Services"
        }
    ],
    "sg:phone":"+61 2 9649 3417",
    "sg:postcode":"2141",
    "sg:province":"NSW",
    "sg:tags":[
        "renovation",
        "alterations",
        "extension",
        "contractor"
    ],
    "wof:name":"High Class Renovations",
    "wof:placetype":"venue"
},
  "geometry": {"coordinates":[151.03189086899999,-33.8689842224],"type":"Point"}
}