{
  "type": "Feature",
  "properties": {
    "addr:full":"C/- Coles Express, 90 Cowper Street Goulburn NSW 2580",
    "addr:housenumber":"90",
    "addr:postcode":"2580",
    "addr:street":"C /;Cowper Street",
    "iso:country":"AU",
    "sg:address":"C/- Coles Express, 90 Cowper Street",
    "sg:city":"Goulburn",
    "sg:classifiers":[
        {
            "category":"Autos & Motor Vehicles",
            "subcategory":"Auto Supplies",
            "type":"Retail Goods"
        }
    ],
    "sg:phone":"+61 2 4821 6855",
    "sg:postcode":"2580",
    "sg:province":"NSW",
    "sg:tags":[
        "tyre"
    ],
    "wof:name":"Kmart Tyre & Auto Service",
    "wof:placetype":"venue"
},
  "geometry": {"coordinates":[149.711181641,-34.7556343079],"type":"Point"}
}