{
  "type": "Feature",
  "properties": {
    "addr:full":"Cnr. Devonshire & Elizabeth Sts Surry Hills NSW 2010",
    "addr:postcode":"2010",
    "iso:country":"AU",
    "sg:address":"Cnr. Devonshire & Elizabeth Sts",
    "sg:city":"Surry Hills",
    "sg:classifiers":[
        {
            "category":"Retail",
            "subcategory":"Repair Shop",
            "type":"Services"
        }
    ],
    "sg:phone":"+61 2 9281 9520",
    "sg:postcode":"2010",
    "sg:province":"NSW",
    "sg:tags":[
        "handbag"
    ],
    "wof:name":"Oroton Pty Ltd",
    "wof:placetype":"venue"
},
  "geometry": {"coordinates":[151.207962036,-33.8862762451],"type":"Point"}
}