{
  "type": "Feature",
  "properties": {
    "addr:full":"25 Washington Crt Stephens QLD 4227",
    "addr:housenumber":"25",
    "addr:postcode":"4227",
    "addr:street":"Washington Crt",
    "iso:country":"AU",
    "sg:address":"25 Washington Crt",
    "sg:city":"Stephens",
    "sg:classifiers":[
        {
            "category":"Education",
            "subcategory":"Special Training",
            "type":"Public Place"
        }
    ],
    "sg:phone":"+61 7 5520 5898",
    "sg:postcode":"4227",
    "sg:province":"QLD",
    "sg:tags":[
        "development"
    ],
    "wof:name":"Don Jolly & Associates Pty Ltd",
    "wof:placetype":"venue"
},
  "geometry": {"coordinates":[153.41575622600001,-28.0825614929],"type":"Point"}
}