{
  "type": "Feature",
  "properties": {
    "iso:country":"AU",
    "sg:address":"13 Gladstone Rd",
    "sg:city":"Biloela",
    "sg:classifiers":[
        {
            "category":"Professional",
            "subcategory":"Computer Services",
            "type":"Services"
        }
    ],
    "sg:phone":"+61 7 4992 5500",
    "sg:postcode":"4715",
    "sg:province":"QLD",
    "sg:tags":[
        "repairs",
        "upgrade",
        "equipment"
    ],
    "wof:name":"Thangool Computer Service",
    "wof:placetype":"venue"
},
  "geometry": {"coordinates":[150.51846313499999,-24.3967781067],"type":"Point"}
}