{
  "type": "Feature",
  "properties": {
    "addr:full":"18 Station St Riddells Creek VIC 3431",
    "addr:housenumber":"18",
    "addr:postcode":"3431",
    "addr:street":"Station St",
    "iso:country":"AU",
    "sg:address":"18 Station St",
    "sg:city":"Riddells Creek",
    "sg:classifiers":[
        {
            "category":"Building & Trades",
            "subcategory":"Plumbing",
            "type":"Services"
        }
    ],
    "sg:phone":"+61 3 9310 4288",
    "sg:postcode":"3431",
    "sg:province":"VIC",
    "sg:tags":[
        "plumber",
        "gasfitters"
    ],
    "wof:name":"Scott Dowsett Plumbing Services",
    "wof:placetype":"venue"
},
  "geometry": {"coordinates":[144.67860412600001,-37.4640731812],"type":"Point"}
}