{
  "type": "Feature",
  "properties": {
    "addr:full":"804 Hay St Perth WA 6000",
    "addr:housenumber":"804",
    "addr:postcode":"6000",
    "addr:street":"Hay St",
    "iso:country":"AU",
    "sg:address":"804 Hay St",
    "sg:city":"Perth",
    "sg:classifiers":[
        {
            "category":"Food & Beverages",
            "subcategory":"Bakery",
            "type":"Retail Goods"
        }
    ],
    "sg:phone":"+61 8 9481 0094",
    "sg:postcode":"6000",
    "sg:province":"WA",
    "sg:tags":[
        "baker"
    ],
    "wof:name":"Hay St. Bakery & Lunch Bar",
    "wof:placetype":"venue"
},
  "geometry": {"coordinates":[115.85484314,-31.9529914856],"type":"Point"}
}