{
  "type": "Feature",
  "properties": {
    "addr:full":"Unit 1/ 99 Stanley St Hackham SA 5163",
    "addr:housenumber":"99",
    "addr:postcode":"5163",
    "addr:street":"Stanley St",
    "iso:country":"AU",
    "sg:address":"Unit 1/ 99 Stanley St",
    "sg:city":"Hackham",
    "sg:classifiers":[
        {
            "category":"Manufacturing",
            "subcategory":"Glass & Minerals",
            "type":"Manufacturing & Wholesale Goods"
        }
    ],
    "sg:phone":"+61 413 864 886",
    "sg:postcode":"5163",
    "sg:province":"SA",
    "sg:tags":[
        "merchant",
        "granite",
        "marble"
    ],
    "wof:name":"Amazing Interiors Pty Ltd",
    "wof:placetype":"venue"
},
  "geometry": {"coordinates":[138.527954102,-35.1526794434],"type":"Point"}
}