{
  "type": "Feature",
  "properties": {
    "addr:full":"Suite 1, 2/ 12 Victoria St East Lidcombe NSW 2141",
    "addr:housenumber":"2 / 12",
    "addr:postcode":"2141",
    "addr:street":"Victoria St East",
    "iso:country":"AU",
    "sg:address":"Suite 1, 2/ 12 Victoria St",
    "sg:city":"East Lidcombe",
    "sg:classifiers":[
        {
            "category":"Home & Garden",
            "subcategory":"Hardware",
            "type":"Retail Goods"
        }
    ],
    "sg:phone":"+61 2 9646 4222",
    "sg:postcode":"2141",
    "sg:province":"NSW",
    "sg:tags":[
        "nut",
        "bolt"
    ],
    "wof:name":"Tamperproof Fastener Co",
    "wof:placetype":"venue"
},
  "geometry": {"coordinates":[151.04606628400001,-33.8690376282],"type":"Point"}
}