{
  "type": "Feature",
  "properties": {
    "iso:country":"AU",
    "sg:address":"Great Western Hwy",
    "sg:city":"Hazelbrook",
    "sg:classifiers":[
        {
            "category":"Food & Beverages",
            "subcategory":"Groceries & Convenience Stores",
            "type":"Retail Goods"
        }
    ],
    "sg:phone":"+61 2 4758 6744",
    "sg:postcode":"2779",
    "sg:province":"NSW",
    "wof:name":"Star Mart at Caltex",
    "wof:placetype":"venue"
},
  "geometry": {"coordinates":[150.45307922399999,-33.7224121094],"type":"Point"}
}