{
  "type": "Feature",
  "properties": {
    "addr:full":"37 William St Gosford NSW 2250",
    "addr:housenumber":"37",
    "addr:postcode":"2250",
    "addr:street":"William St",
    "iso:country":"AU",
    "sg:address":"37 William St",
    "sg:city":"Gosford",
    "sg:classifiers":[
        {
            "category":"Health Services",
            "subcategory":"Doctor",
            "type":"Services"
        }
    ],
    "sg:phone":"+61 2 4323 7977",
    "sg:postcode":"2250",
    "sg:province":"NSW",
    "sg:tags":[
        "medical",
        "practitioner"
    ],
    "wof:name":"Roger Dr S",
    "wof:placetype":"venue"
},
  "geometry": {"coordinates":[151.3465271,-33.4266738892],"type":"Point"}
}