{
  "type": "Feature",
  "properties": {
    "addr:full":"4 Crossdale Drv Aberfoyle Park SA 5159",
    "addr:housenumber":"4",
    "addr:postcode":"5159",
    "addr:street":"Crossdale Drv",
    "iso:country":"AU",
    "sg:address":"4 Crossdale Drv",
    "sg:city":"Aberfoyle Park",
    "sg:classifiers":[
        {
            "category":"Building & Trades",
            "subcategory":"Construction",
            "type":"Services"
        }
    ],
    "sg:phone":"+61 8 8270 1097",
    "sg:postcode":"5159",
    "sg:province":"SA",
    "sg:tags":[
        "home",
        "air conditioning"
    ],
    "wof:name":"Reverse Air",
    "wof:placetype":"venue"
},
  "geometry": {"coordinates":[138.60284423799999,-35.0742492676],"type":"Point"}
}