{
  "type": "Feature",
  "properties": {
    "addr:full":"16 Nebo Dr Figtree NSW 2525",
    "addr:housenumber":"16",
    "addr:postcode":"2525",
    "addr:street":"Nebo Dr Figtree",
    "iso:country":"AU",
    "sg:address":"16 Nebo Dr",
    "sg:city":"Figtree",
    "sg:classifiers":[
        {
            "category":"Professional",
            "subcategory":"Printing & Photocopies",
            "type":"Services"
        }
    ],
    "sg:phone":"+61 2 4229 7259",
    "sg:postcode":"2525",
    "sg:province":"NSW",
    "sg:tags":[
        "embroidery"
    ],
    "wof:name":"Aarhus Embroidery Service",
    "wof:placetype":"venue"
},
  "geometry": {"coordinates":[150.84974670400001,-34.422492981],"type":"Point"}
}