{
  "type": "Feature",
  "properties": {
    "iso:country":"AU",
    "sg:address":"Maranoa Rd",
    "sg:city":"Kingston",
    "sg:classifiers":[
        {
            "category":"Cafe",
            "type":"Food & Drink"
        }
    ],
    "sg:phone":"+61 3 6229 4221",
    "sg:postcode":"7050",
    "sg:province":"TAS",
    "wof:name":"Rascal's Cafe & Diner",
    "wof:placetype":"venue"
},
  "geometry": {"coordinates":[147.307175,-42.976063],"type":"Point"}
}