{
  "type": "Feature",
  "properties": {
    "iso:country":"AU",
    "sg:address":"17 Turner St",
    "sg:city":"Beerwah",
    "sg:classifiers":[
        {
            "category":"Health Services",
            "subcategory":"Health Practitioner",
            "type":"Services"
        }
    ],
    "sg:phone":"+61 7 5494 0060",
    "sg:postcode":"4519",
    "sg:province":"QLD",
    "sg:tags":[
        "physiotherapist"
    ],
    "wof:name":"Beerwah Active Physio",
    "wof:placetype":"venue"
},
  "geometry": {"coordinates":[152.95619199999999,-26.860735],"type":"Point"}
}