{
  "type": "Feature",
  "properties": {
    "addr:full":"5 Edwin St Greenwich NSW 2065",
    "addr:housenumber":"5",
    "addr:postcode":"2065",
    "addr:street":"Edwin St",
    "iso:country":"AU",
    "sg:address":"5 Edwin St",
    "sg:city":"Greenwich",
    "sg:classifiers":[
        {
            "category":"Health Services",
            "subcategory":"Health Practitioner",
            "type":"Services"
        }
    ],
    "sg:phone":"+61 2 9439 2703",
    "sg:postcode":"2065",
    "sg:province":"NSW",
    "sg:tags":[
        "psychologist"
    ],
    "wof:name":"Green Sandy",
    "wof:placetype":"venue"
},
  "geometry": {"coordinates":[151.187103272,-33.8331298828],"type":"Point"}
}