{
  "type": "Feature",
  "properties": {
    "iso:country":"AU",
    "sg:address":"Unit 2 307 Auburn Rd",
    "sg:city":"Hawthorn",
    "sg:classifiers":[
        {
            "category":"Real Estate",
            "subcategory":"Surveying",
            "type":"Services"
        }
    ],
    "sg:phone":"+61 3 9882 3813",
    "sg:postcode":"3122",
    "sg:province":"VIC",
    "sg:tags":[
        "surveyor",
        "quantity"
    ],
    "wof:name":"Waisberg T & Associates",
    "wof:placetype":"venue"
},
  "geometry": {"coordinates":[145.04182434099999,-37.8390464783],"type":"Point"}
}