{
  "type": "Feature",
  "properties": {
    "addr:full":"48 Ironbark Ave Sandy Beach NSW 2456",
    "addr:housenumber":"48",
    "addr:postcode":"2456",
    "addr:street":"Ironbark Ave",
    "iso:country":"AU",
    "sg:address":"48 Ironbark Ave",
    "sg:city":"Sandy Beach",
    "sg:classifiers":[
        {
            "category":"Professional",
            "subcategory":"Art Services",
            "type":"Services"
        }
    ],
    "sg:phone":"+61 413 489 599",
    "sg:postcode":"2456",
    "sg:province":"NSW",
    "sg:tags":[
        "decorator",
        "painter"
    ],
    "wof:name":"Hayes Bros Painting",
    "wof:placetype":"venue"
},
  "geometry": {"coordinates":[153.19703699999999,-30.152315],"type":"Point"}
}