{
  "type": "Feature",
  "properties": {
    "addr:full":"155 Hannan St Kalgoorlie WA 6430",
    "addr:housenumber":"155",
    "addr:postcode":"6430",
    "addr:street":"Hannan St",
    "iso:country":"AU",
    "sg:address":"155 Hannan St",
    "sg:city":"Kalgoorlie",
    "sg:classifiers":[
        {
            "category":"Real Estate",
            "subcategory":"Real Estate Agent",
            "type":"Services"
        }
    ],
    "sg:phone":"+61 8 9080 9200",
    "sg:postcode":"6430",
    "sg:province":"WA",
    "wof:name":"Fyson Strachan & Assocs",
    "wof:placetype":"venue"
},
  "geometry": {"coordinates":[121.467140198,-30.7521476746],"type":"Point"}
}