{
  "type": "Feature",
  "properties": {
    "iso:country":"AU",
    "sg:address":"PO Box 3257",
    "sg:city":"North Turramurra",
    "sg:classifiers":[
        {
            "category":"Retail",
            "subcategory":"Storage",
            "type":"Services"
        }
    ],
    "sg:phone":"+61 2 9487 2489",
    "sg:postcode":"2074",
    "sg:province":"NSW",
    "sg:tags":[
        "removal",
        "furniture"
    ],
    "wof:name":"Ben Carey Removals",
    "wof:placetype":"venue"
},
  "geometry": {"coordinates":[151.13186645499999,-33.7273216248],"type":"Point"}
}