{
  "type": "Feature",
  "properties": {
    "addr:full":"10 Colchester Rd Rosebud VIC 3939",
    "addr:housenumber":"10",
    "addr:postcode":"3939",
    "addr:street":"Colchester Rd",
    "iso:country":"AU",
    "sg:address":"10 Colchester Rd",
    "sg:city":"Rosebud",
    "sg:classifiers":[
        {
            "category":"Utilities",
            "subcategory":"Refuse",
            "type":"Services"
        }
    ],
    "sg:phone":"+61 3 9408 4555",
    "sg:postcode":"3939",
    "sg:province":"VIC",
    "sg:tags":[
        "remover",
        "rubbish"
    ],
    "wof:name":"Green Planet",
    "wof:placetype":"venue"
},
  "geometry": {"coordinates":[144.88659668,-38.379108429],"type":"Point"}
}