{
  "type": "Feature",
  "properties": {
    "addr:full":"48 Great Ryrie St Heathmont VIC 3135",
    "addr:housenumber":"48",
    "addr:postcode":"3135",
    "addr:street":"Great Ryrie St",
    "iso:country":"AU",
    "sg:address":"48 Great Ryrie St",
    "sg:city":"Heathmont",
    "sg:classifiers":[
        {
            "category":"Building & Trades",
            "subcategory":"Construction",
            "type":"Services"
        }
    ],
    "sg:phone":"+61 3 9870 9623",
    "sg:postcode":"3135",
    "sg:province":"VIC",
    "sg:tags":[
        "contractor"
    ],
    "wof:name":"Noy G M",
    "wof:placetype":"venue"
},
  "geometry": {"coordinates":[145.23713684099999,-37.8265304565],"type":"Point"}
}