{
  "type": "Feature",
  "properties": {
    "iso:country":"AU",
    "sg:address":"3 Weatherby Ave",
    "sg:city":"Cambridge Park",
    "sg:classifiers":[
        {
            "category":"Building & Trades",
            "subcategory":"Cleaning & Sanitation",
            "type":"Services"
        }
    ],
    "sg:phone":"+61 423 130 124",
    "sg:postcode":"2747",
    "sg:province":"NSW",
    "sg:tags":[
        "industrial",
        "commercial",
        "contractor"
    ],
    "wof:name":"Acute Cleaning Services",
    "wof:placetype":"venue"
},
  "geometry": {"coordinates":[150.73049926799999,-33.7532272339],"type":"Point"}
}