{
  "type": "Feature",
  "properties": {
    "addr:full":"63 Broadmeadows Rd Broadmeadows VIC 3047",
    "addr:housenumber":"63",
    "addr:postcode":"3047",
    "addr:street":"Broadmeadows Rd",
    "iso:country":"AU",
    "sg:address":"63 Broadmeadows Rd",
    "sg:city":"Broadmeadows",
    "sg:classifiers":[
        {
            "category":"Building & Trades",
            "subcategory":"Construction",
            "type":"Services"
        }
    ],
    "sg:phone":"+61 2 4940 8544",
    "sg:postcode":"3047",
    "sg:province":"VIC",
    "sg:tags":[
        "home",
        "air conditioning"
    ],
    "wof:name":"Carrier Air Conditioning Pty Ltd",
    "wof:placetype":"venue"
},
  "geometry": {"coordinates":[144.87982177699999,-37.7023925781],"type":"Point"}
}