{
  "type": "Feature",
  "properties": {
    "addr:full":"Cnr Renwick St & Pacific Hwy Wyoming NSW 2250",
    "addr:postcode":"2250",
    "addr:street":"Cnr Renwick St & Pacific Hwy",
    "iso:country":"AU",
    "sg:address":"Cnr Renwick St & Pacific Hwy",
    "sg:city":"Wyoming",
    "sg:classifiers":[
        {
            "category":"Travel",
            "subcategory":"Hotels & Motels",
            "type":"Entertainment"
        }
    ],
    "sg:phone":"+61 2 4328 4933",
    "sg:postcode":"2250",
    "sg:province":"NSW",
    "sg:tags":[
        "accommodation"
    ],
    "wof:name":"Grange Hotel The",
    "wof:placetype":"venue"
},
  "geometry": {"coordinates":[151.35177612300001,-33.4035415649],"type":"Point"}
}