{
  "type": "Feature",
  "properties": {
    "iso:country":"AU",
    "sg:address":"69 Tone Rd",
    "sg:city":"Wangaratta",
    "sg:classifiers":[
        {
            "category":"Retail",
            "subcategory":"Auto Repair",
            "type":"Services"
        }
    ],
    "sg:phone":"+61 3 5721 4307",
    "sg:postcode":"3677",
    "sg:province":"VIC",
    "sg:tags":[
        "testing",
        "inspection",
        "motor",
        "vehicle"
    ],
    "wof:name":"Gear Drive",
    "wof:placetype":"venue"
},
  "geometry": {"coordinates":[146.304153442,-36.3632354736],"type":"Point"}
}