{
  "type": "Feature",
  "properties": {
    "iso:country":"AU",
    "sg:address":"603-605 Parramatta Rd",
    "sg:city":"Leichhardt",
    "sg:classifiers":[
        {
            "category":"Autos & Motor Vehicles",
            "subcategory":"Automobile Sales",
            "type":"Retail Goods"
        }
    ],
    "sg:phone":"+61 2 9550 9499",
    "sg:postcode":"2040",
    "sg:province":"NSW",
    "sg:tags":[
        "car",
        "used"
    ],
    "wof:name":"Sydney Wholesale Direct",
    "wof:placetype":"venue"
},
  "geometry": {"coordinates":[151.150177,-33.889477],"type":"Point"}
}