{
  "type": "Feature",
  "properties": {
    "iso:country":"AU",
    "sg:address":"3 Harah Crt",
    "sg:city":"Ocean Shores",
    "sg:classifiers":[
        {
            "category":"Personal",
            "subcategory":"Beauty Salon",
            "type":"Services"
        }
    ],
    "sg:phone":"+61 2 6680 2111",
    "sg:postcode":"2483",
    "sg:province":"NSW",
    "wof:name":"Beaches Day Spa Retreat",
    "wof:placetype":"venue"
},
  "geometry": {"coordinates":[153.540649414,-28.5242671967],"type":"Point"}
}