{
  "type": "Feature",
  "properties": {
    "addr:full":"Unit 3/ 286 Bolton St Eltham VIC 3095",
    "addr:housenumber":"/ 286",
    "addr:postcode":"3095",
    "addr:street":"Bolton St",
    "iso:country":"AU",
    "sg:address":"Unit 3/ 286 Bolton St",
    "sg:city":"Eltham",
    "sg:classifiers":[
        {
            "category":"Professional",
            "subcategory":"Detective & Security Services",
            "type":"Services"
        }
    ],
    "sg:phone":"+61 3 9439 9485",
    "sg:postcode":"3095",
    "sg:province":"VIC",
    "sg:tags":[
        "investigator"
    ],
    "wof:name":"Pro Active Strategies Pty Ltd",
    "wof:placetype":"venue"
},
  "geometry": {"coordinates":[145.13771057100001,-37.7197341919],"type":"Point"}
}