{
  "type": "Feature",
  "properties": {
    "iso:country":"AU",
    "sg:address":"145 Darling St",
    "sg:city":"Wentworth",
    "sg:classifiers":[
        {
            "category":"Real Estate",
            "subcategory":"Real Estate Services",
            "type":"Services"
        }
    ],
    "sg:phone":"+61 3 5027 2502",
    "sg:postcode":"2648",
    "sg:province":"NSW",
    "sg:tags":[
        "house",
        "hire",
        "boat"
    ],
    "wof:name":"Rivergums Houseboats",
    "wof:placetype":"venue"
},
  "geometry": {"coordinates":[141.916702,-34.096951],"type":"Point"}
}