{
  "type": "Feature",
  "properties": {
    "addr:full":"22 Victoria St Warragul VIC 3820",
    "addr:housenumber":"22",
    "addr:postcode":"3820",
    "addr:street":"Victoria St",
    "iso:country":"AU",
    "sg:address":"22 Victoria St",
    "sg:city":"Warragul",
    "sg:classifiers":[
        {
            "category":"Professional",
            "subcategory":"Art Services",
            "type":"Services"
        }
    ],
    "sg:phone":"+61 3 5623 5100",
    "sg:postcode":"3820",
    "sg:province":"VIC",
    "sg:tags":[
        "picture",
        "frame",
        "framing"
    ],
    "wof:name":"John Moore Photography",
    "wof:placetype":"venue"
},
  "geometry": {"coordinates":[145.930847,-38.162231],"type":"Point"}
}