{
  "type": "Feature",
  "properties": {
    "addr:full":"Suite 9/ 207 Great North Rd Five Dock NSW 2046",
    "addr:housenumber":"/ 207",
    "addr:postcode":"2046",
    "addr:street":"Great North Rd",
    "iso:country":"AU",
    "sg:address":"Suite 9/ 207 Great North Rd",
    "sg:city":"Five Dock",
    "sg:classifiers":[
        {
            "category":"Banks & Credit Unions",
            "subcategory":"Investment Brokerage",
            "type":"Services"
        }
    ],
    "sg:phone":"+61 2 9712 3277",
    "sg:postcode":"2046",
    "sg:province":"NSW",
    "sg:tags":[
        "finance",
        "broker"
    ],
    "wof:name":"Nationwide Finance Network Pty Ltd",
    "wof:placetype":"venue"
},
  "geometry": {"coordinates":[151.13002,-33.865952],"type":"Point"}
}