{
  "type": "Feature",
  "properties": {
    "addr:full":"15 Alison Ave Bulleen VIC 3105",
    "addr:housenumber":"15",
    "addr:postcode":"3105",
    "addr:street":"Alison Ave",
    "iso:country":"AU",
    "sg:address":"15 Alison Ave",
    "sg:city":"Bulleen",
    "sg:classifiers":[
        {
            "category":"Building & Trades",
            "subcategory":"Pest Control",
            "type":"Services"
        }
    ],
    "sg:phone":"+61 3 9852 1234",
    "sg:postcode":"3105",
    "sg:province":"VIC",
    "wof:name":"King-Hit",
    "wof:placetype":"venue"
},
  "geometry": {"coordinates":[145.099807739,-37.7640380859],"type":"Point"}
}