{
  "type": "Feature",
  "properties": {
    "iso:country":"AU",
    "sg:address":"Level 1/ 27 Greenfield Pde",
    "sg:city":"Bankstown",
    "sg:classifiers":[
        {
            "category":"Education",
            "subcategory":"Special Training",
            "type":"Public Place"
        }
    ],
    "sg:phone":"+61 2 9791 6020",
    "sg:postcode":"2200",
    "sg:province":"NSW",
    "sg:tags":[
        "tuition-educational"
    ],
    "wof:name":"Petrus KY College",
    "wof:placetype":"venue"
},
  "geometry": {"coordinates":[151.032715,-33.919323],"type":"Point"}
}