{
  "type": "Feature",
  "properties": {
    "addr:full":"171 Sydney St South Mackay QLD 4740",
    "addr:housenumber":"171",
    "addr:postcode":"4740",
    "addr:street":"Sydney St",
    "iso:country":"AU",
    "sg:address":"171 Sydney St",
    "sg:city":"South Mackay",
    "sg:classifiers":[
        {
            "category":"Retail",
            "subcategory":"Auto Repair",
            "type":"Services"
        }
    ],
    "sg:phone":"+61 7 4957 8635",
    "sg:postcode":"4740",
    "sg:province":"QLD",
    "sg:tags":[
        "repairer",
        "motor",
        "engineer"
    ],
    "wof:name":"Kyle's Auto Repairs",
    "wof:placetype":"venue"
},
  "geometry": {"coordinates":[149.18579099999999,-21.151255],"type":"Point"}
}