{
  "type": "Feature",
  "properties": {
    "addr:full":"Suite D, 1st Floor 36 Rous Head Rd Fremantle WA 6160",
    "addr:housenumber":"36",
    "addr:postcode":"6160",
    "addr:street":"Rous Head Rd",
    "iso:country":"AU",
    "sg:address":"Suite D, 1st Floor 36 Rous Head Rd",
    "sg:city":"Fremantle",
    "sg:classifiers":[
        {
            "category":"Transit Center",
            "subcategory":"Freight",
            "type":"Transportation"
        }
    ],
    "sg:phone":"+61 13 26 11",
    "sg:postcode":"6160",
    "sg:province":"WA",
    "sg:tags":[
        "agent",
        "shipping"
    ],
    "wof:name":"ANZDL",
    "wof:placetype":"venue"
},
  "geometry": {"coordinates":[115.736214,-32.04665],"type":"Point"}
}