{
  "type": "Feature",
  "properties": {
    "addr:full":"371 King St Newtown NSW 2042",
    "addr:housenumber":"371",
    "addr:postcode":"2042",
    "addr:street":"King St",
    "iso:country":"AU",
    "sg:address":"371 King St",
    "sg:city":"Newtown",
    "sg:classifiers":[
        {
            "category":"Professional",
            "subcategory":"Computer Services",
            "type":"Services"
        }
    ],
    "sg:phone":"+61 2 9517 2876",
    "sg:postcode":"2042",
    "sg:province":"NSW",
    "sg:tags":[
        "repairs",
        "upgrade",
        "equipment"
    ],
    "wof:name":"Digital World Warehouse",
    "wof:placetype":"venue"
},
  "geometry": {"coordinates":[151.177673,-33.898952],"type":"Point"}
}