{
  "type": "Feature",
  "properties": {
    "addr:full":"2742 Bells Line Of Road Bilpin NSW 2758",
    "addr:housenumber":"2742",
    "addr:postcode":"2758",
    "addr:street":"Bells Line Of Road",
    "iso:country":"AU",
    "sg:address":"2742 Bells Line Of Road",
    "sg:city":"Bilpin",
    "sg:classifiers":[
        {
            "category":"Food & Beverages",
            "subcategory":"Groceries & Convenience Stores",
            "type":"Retail Goods"
        }
    ],
    "sg:phone":"+61 2 4567 1112",
    "sg:postcode":"2758",
    "sg:province":"NSW",
    "wof:name":"Apple Tree Store",
    "wof:placetype":"venue"
},
  "geometry": {"coordinates":[150.498046875,-33.5073013306],"type":"Point"}
}