{
  "type": "Feature",
  "properties": {
    "addr:full":"165 Hanlon Rd Shepparton East VIC 3631",
    "addr:housenumber":"165",
    "addr:postcode":"3631",
    "addr:street":"Hanlon Rd",
    "iso:country":"AU",
    "sg:address":"165 Hanlon Rd",
    "sg:city":"Shepparton East",
    "sg:classifiers":[
        {
            "category":"Farming",
            "subcategory":"Orchard",
            "type":"Manufacturing & Wholesale Goods"
        }
    ],
    "sg:phone":"+61 3 5829 2210",
    "sg:postcode":"3631",
    "sg:province":"VIC",
    "sg:tags":[
        "pear",
        "apple",
        "grower"
    ],
    "wof:name":"Vagelatos Cool Store",
    "wof:placetype":"venue"
},
  "geometry": {"coordinates":[145.474212647,-36.4183921814],"type":"Point"}
}