{
  "type": "Feature",
  "properties": {
    "iso:country":"AU",
    "sg:address":"Bluegum Crs",
    "sg:city":"Guilderton",
    "sg:classifiers":[
        {
            "category":"Building & Trades",
            "subcategory":"Landscaping Services",
            "type":"Services"
        }
    ],
    "sg:phone":"+61 8 9577 1666",
    "sg:postcode":"6041",
    "sg:province":"WA",
    "sg:tags":[
        "designer",
        "landscape",
        "contractor"
    ],
    "wof:name":"Redfield Landscape & Garden Services",
    "wof:placetype":"venue"
},
  "geometry": {"coordinates":[115.49873352,-31.3454208374],"type":"Point"}
}