{
  "type": "Feature",
  "properties": {
    "iso:country":"AU",
    "sg:address":"Shop 52-53, Port Central Shopping Centre, 40-42 Horton St",
    "sg:city":"Port Macquarie",
    "sg:classifiers":[
        {
            "category":"Travel",
            "subcategory":"Travel Agent",
            "type":"Entertainment"
        }
    ],
    "sg:phone":"+61 13 18 66",
    "sg:postcode":"2444",
    "sg:province":"NSW",
    "sg:tags":[
        "consultant"
    ],
    "wof:name":"Flight Centre",
    "wof:placetype":"venue"
},
  "geometry": {"coordinates":[152.89505,-31.428562],"type":"Point"}
}