{
  "type": "Feature",
  "properties": {
    "addr:full":"42 Downing St Oakleigh VIC 3166",
    "addr:housenumber":"42",
    "addr:postcode":"3166",
    "addr:street":"Downing St",
    "iso:country":"AU",
    "sg:address":"42 Downing St",
    "sg:city":"Oakleigh",
    "sg:classifiers":[
        {
            "category":"Retail",
            "subcategory":"Auto Repair",
            "type":"Services"
        }
    ],
    "sg:phone":"+61 3 9564 7177",
    "sg:postcode":"3166",
    "sg:province":"VIC",
    "sg:tags":[
        "repairer",
        "motor",
        "engineer"
    ],
    "wof:name":"Oakleigh Automotive Repairs",
    "wof:placetype":"venue"
},
  "geometry": {"coordinates":[145.09361267099999,-37.9025917053],"type":"Point"}
}