{
  "type": "Feature",
  "properties": {
    "iso:country":"AU",
    "sg:address":"Cnr Daly & Cavenagh Sts",
    "sg:city":"Darwin",
    "sg:classifiers":[
        {
            "category":"Social Services",
            "subcategory":"Child Care",
            "type":"Services"
        }
    ],
    "sg:phone":"+61 8 8981 7171",
    "sg:postcode":"0800",
    "sg:province":"NT",
    "wof:name":"Darwin City Child Care",
    "wof:placetype":"venue"
},
  "geometry": {"coordinates":[130.83700561500001,-12.4567098618],"type":"Point"}
}