{
  "type": "Feature",
  "properties": {
    "addr:full":"36 Govetts Leap Rd Blackheath NSW 2785",
    "addr:housenumber":"36",
    "addr:postcode":"2785",
    "addr:street":"Govetts Leap Rd",
    "iso:country":"AU",
    "sg:address":"36 Govetts Leap Rd",
    "sg:city":"Blackheath",
    "sg:classifiers":[
        {
            "category":"Real Estate",
            "subcategory":"Real Estate Agent",
            "type":"Services"
        }
    ],
    "sg:phone":"+61 2 4787 7266",
    "sg:postcode":"2785",
    "sg:province":"NSW",
    "wof:name":"Century 21",
    "wof:placetype":"venue"
},
  "geometry": {"coordinates":[150.286499023,-33.6360206604],"type":"Point"}
}