{
  "type": "Feature",
  "properties": {
    "addr:full":"5 Honeymyrtle Crt Capalaba QLD 4157",
    "addr:housenumber":"5",
    "addr:postcode":"4157",
    "addr:street":"Honeymyrtle Crt",
    "iso:country":"AU",
    "sg:address":"5 Honeymyrtle Crt",
    "sg:city":"Capalaba",
    "sg:classifiers":[
        {
            "category":"Insurance",
            "subcategory":"Life Insurance",
            "type":"Services"
        }
    ],
    "sg:phone":"+61 7 3206 1522",
    "sg:postcode":"4157",
    "sg:province":"QLD",
    "wof:name":"Balfour Investments & Insurance Services Pty Ltd",
    "wof:placetype":"venue"
},
  "geometry": {"coordinates":[153.21969604500001,-27.5583229065],"type":"Point"}
}