{
  "type": "Feature",
  "properties": {
    "addr:full":"Shop 14B Seymour St Traralgon VIC 3844",
    "addr:housenumber":"14b",
    "addr:postcode":"3844",
    "addr:street":"Shop;Seymour St",
    "iso:country":"AU",
    "sg:address":"Shop 14B Seymour St",
    "sg:city":"Traralgon",
    "sg:classifiers":[
        {
            "category":"Building & Trades",
            "subcategory":"Locksmith",
            "type":"Services"
        }
    ],
    "sg:phone":"+61 3 5176 2844",
    "sg:postcode":"3844",
    "sg:province":"VIC",
    "sg:tags":[
        "lock"
    ],
    "wof:name":"Safe-N-Secure Locksmiths",
    "wof:placetype":"venue"
},
  "geometry": {"coordinates":[146.539154053,-38.1961631775],"type":"Point"}
}