{
  "type": "Feature",
  "properties": {
    "addr:full":"5575 Murray Valley Hwy Swan Hill NSW 3585",
    "addr:housenumber":"5575",
    "addr:postcode":"3585",
    "addr:street":"Murray Valley Hwy",
    "iso:country":"AU",
    "sg:address":"5575 Murray Valley Hwy",
    "sg:city":"Swan Hill",
    "sg:classifiers":[
        {
            "category":"Autos & Motor Vehicles",
            "subcategory":"Auto Supplies",
            "type":"Retail Goods"
        }
    ],
    "sg:phone":"+61 3 5032 2485",
    "sg:postcode":"3585",
    "sg:province":"NSW",
    "sg:tags":[
        "camper-trailers",
        "caravan",
        "equipment"
    ],
    "wof:name":"Swan Hill Caravan Hire & Sales",
    "wof:placetype":"venue"
},
  "geometry": {"coordinates":[143.562241,-35.358212],"type":"Point"}
}