{
  "type": "Feature",
  "properties": {
    "addr:full":"33 Montpelier Rd Bowen Hills QLD 4006",
    "addr:housenumber":"33",
    "addr:postcode":"4006",
    "addr:street":"Montpelier Rd",
    "iso:country":"AU",
    "sg:address":"33 Montpelier Rd",
    "sg:city":"Bowen Hills",
    "sg:classifiers":[
        {
            "category":"Professional",
            "subcategory":"Employment Agencies",
            "type":"Services"
        }
    ],
    "sg:phone":"+61 7 3257 1154",
    "sg:postcode":"4006",
    "sg:province":"QLD",
    "wof:name":"Flexiforce Pty Ltd",
    "wof:placetype":"venue"
},
  "geometry": {"coordinates":[153.03631591800001,-27.4618377686],"type":"Point"}
}