{
  "type": "Feature",
  "properties": {
    "addr:full":"2 Wellby Crt Riverleigh QLD 4626",
    "addr:housenumber":"2",
    "addr:postcode":"4626",
    "addr:street":"Wellby Crt",
    "iso:country":"AU",
    "sg:address":"2 Wellby Crt",
    "sg:city":"Riverleigh",
    "sg:classifiers":[
        {
            "category":"Farming",
            "subcategory":"Farm & Veterinary Services",
            "type":"Manufacturing & Wholesale Goods"
        }
    ],
    "sg:phone":"+61 7 4942 2558",
    "sg:postcode":"4626",
    "sg:province":"QLD",
    "sg:tags":[
        "contracting"
    ],
    "wof:name":"MacKenzie R F & R D",
    "wof:placetype":"venue"
},
  "geometry": {"coordinates":[151.23899800000001,-25.60096],"type":"Point"}
}