{
  "type": "Feature",
  "properties": {
    "addr:full":"1421 Ipswich Rd Rocklea QLD 4106",
    "addr:housenumber":"1421",
    "addr:postcode":"4106",
    "addr:street":"Ipswich Rd",
    "iso:country":"AU",
    "sg:address":"1421 Ipswich Rd",
    "sg:city":"Rocklea",
    "sg:classifiers":[
        {
            "category":"Home & Garden",
            "subcategory":"Building Materials",
            "type":"Retail Goods"
        }
    ],
    "sg:phone":"+61 7 3277 1177",
    "sg:postcode":"4106",
    "sg:province":"QLD",
    "sg:tags":[
        "supply"
    ],
    "wof:name":"Gill & Co Pty Ltd",
    "wof:placetype":"venue"
},
  "geometry": {"coordinates":[153.00955200199999,-27.546459198],"type":"Point"}
}