{
  "type": "Feature",
  "properties": {
    "iso:country":"AU",
    "sg:address":"14/ 130 Pitt St",
    "sg:city":"Sydney",
    "sg:classifiers":[
        {
            "category":"Professional",
            "subcategory":"Research",
            "type":"Services"
        }
    ],
    "sg:phone":"+61 2 9290 3520",
    "sg:postcode":"2000",
    "sg:province":"NSW",
    "sg:tags":[
        "industrial",
        "scientific"
    ],
    "wof:name":"Justice Research Centre",
    "wof:placetype":"venue"
},
  "geometry": {"coordinates":[151.208496094,-33.8684539795],"type":"Point"}
}