{
  "type": "Feature",
  "properties": {
    "addr:full":"160 Best Rd Seven Hills NSW 2147",
    "addr:housenumber":"160",
    "addr:postcode":"2147",
    "addr:street":"Best Rd",
    "iso:country":"AU",
    "sg:address":"160 Best Rd",
    "sg:city":"Seven Hills",
    "sg:classifiers":[
        {
            "category":"Building & Trades",
            "subcategory":"Landscaping Services",
            "type":"Services"
        }
    ],
    "sg:phone":"+61 2 9831 1289",
    "sg:postcode":"2147",
    "sg:province":"NSW",
    "sg:tags":[
        "consultant"
    ],
    "wof:name":"P.A.D. Prince Associated Design",
    "wof:placetype":"venue"
},
  "geometry": {"coordinates":[150.93519592300001,-33.7756347656],"type":"Point"}
}