{
  "type": "Feature",
  "properties": {
    "addr:full":"Shop 2, 50 Wrights Rd Kellyville NSW 2153",
    "addr:housenumber":"shop;50",
    "addr:postcode":"2153",
    "addr:street":"Wrights Rd",
    "iso:country":"AU",
    "sg:address":"Shop 2, 50 Wrights Rd",
    "sg:city":"Kellyville",
    "sg:classifiers":[
        {
            "category":"Communications",
            "subcategory":"Film & Video Production",
            "type":"Services"
        }
    ],
    "sg:phone":"+61 2 8814 7111",
    "sg:postcode":"2153",
    "sg:province":"NSW",
    "sg:tags":[
        "dvd",
        "library"
    ],
    "wof:name":"Blockbuster",
    "wof:placetype":"venue"
},
  "geometry": {"coordinates":[150.97543335,-33.7134094238],"type":"Point"}
}