{
  "type": "Feature",
  "properties": {
    "addr:full":"5 Kemp Pl Rivervale WA 6103",
    "addr:housenumber":"5",
    "addr:postcode":"6103",
    "addr:street":"Kemp Pl",
    "iso:country":"AU",
    "sg:address":"5 Kemp Pl",
    "sg:city":"Rivervale",
    "sg:classifiers":[
        {
            "category":"Health Services",
            "subcategory":"Nursing And Care Facility",
            "type":"Services"
        }
    ],
    "sg:phone":"+61 8 9277 2735",
    "sg:postcode":"6103",
    "sg:province":"WA",
    "sg:tags":[
        "home"
    ],
    "wof:name":"Belmont Community Nursing Home & Lodge",
    "wof:placetype":"venue"
},
  "geometry": {"coordinates":[115.916481018,-31.9558334351],"type":"Point"}
}