{
  "type": "Feature",
  "properties": {
    "addr:full":"Shop 3/ 128 Kelly St Scone NSW 2337",
    "addr:housenumber":"shop 3 / 128",
    "addr:postcode":"2337",
    "addr:street":"Kelly St",
    "iso:country":"AU",
    "sg:address":"Shop 3/ 128 Kelly St",
    "sg:city":"Scone",
    "sg:classifiers":[
        {
            "category":"Personal",
            "subcategory":"Beauty Salon",
            "type":"Services"
        }
    ],
    "sg:phone":"+61 2 6545 2954",
    "sg:postcode":"2337",
    "sg:province":"NSW",
    "sg:tags":[
        "hairdresser"
    ],
    "wof:name":"Sophistacut Hair Salon",
    "wof:placetype":"venue"
},
  "geometry": {"coordinates":[150.86810302699999,-32.04895401],"type":"Point"}
}