{
  "type": "Feature",
  "properties": {
    "addr:full":"11 Clive St Katanning WA 6317",
    "addr:housenumber":"11",
    "addr:postcode":"6317",
    "addr:street":"Clive St",
    "iso:country":"AU",
    "sg:address":"11 Clive St",
    "sg:city":"Katanning",
    "sg:classifiers":[
        {
            "category":"Farming",
            "subcategory":"Farm & Veterinary Services",
            "type":"Manufacturing & Wholesale Goods"
        }
    ],
    "sg:phone":"+61 8 9821 5076",
    "sg:postcode":"6317",
    "sg:province":"WA",
    "sg:tags":[
        "shearing",
        "contractor"
    ],
    "wof:name":"Katanning Wool Harvesting Service",
    "wof:placetype":"venue"
},
  "geometry": {"coordinates":[117.554916382,-33.6910972595],"type":"Point"}
}