{
  "type": "Feature",
  "properties": {
    "addr:full":"39 Smith St Walkerville SA 5081",
    "addr:housenumber":"39",
    "addr:postcode":"5081",
    "addr:street":"Smith St",
    "iso:country":"AU",
    "sg:address":"39 Smith St",
    "sg:city":"Walkerville",
    "sg:classifiers":[
        {
            "category":"Health Services",
            "subcategory":"Health Practitioner",
            "type":"Services"
        }
    ],
    "sg:phone":"+61 8 8269 3040",
    "sg:postcode":"5081",
    "sg:province":"SA",
    "sg:tags":[
        "naturopath"
    ],
    "wof:name":"Applied Healing Pain Management Clinic",
    "wof:placetype":"venue"
},
  "geometry": {"coordinates":[138.61325073200001,-34.8915901184],"type":"Point"}
}