{
  "type": "Feature",
  "properties": {
    "addr:full":"Level 2, 60 Leichhardt St Spring Hill QLD 4000",
    "addr:housenumber":"60",
    "addr:postcode":"4000",
    "addr:street":"Leichhardt St",
    "iso:country":"AU",
    "sg:address":"Level 2, 60 Leichhardt St",
    "sg:city":"Spring Hill",
    "sg:classifiers":[
        {
            "category":"Professional",
            "subcategory":"Engineering",
            "type":"Services"
        }
    ],
    "sg:phone":"+61 7 3230 3600",
    "sg:postcode":"4000",
    "sg:province":"QLD",
    "sg:tags":[
        "consulting",
        "engineer"
    ],
    "wof:name":"SMEC Australia Pty Ltd",
    "wof:placetype":"venue"
},
  "geometry": {"coordinates":[153.02262878400001,-27.4622135162],"type":"Point"}
}