{
  "type": "Feature",
  "properties": {
    "addr:full":"47 Yale Drv Epping VIC 3076",
    "addr:housenumber":"47",
    "addr:postcode":"3076",
    "addr:street":"Yale Drv",
    "iso:country":"AU",
    "sg:address":"47 Yale Drv",
    "sg:city":"Epping",
    "sg:classifiers":[
        {
            "category":"Utilities",
            "subcategory":"Fuel Oil & Lpg",
            "type":"Services"
        }
    ],
    "sg:phone":"+61 3 8405 9000",
    "sg:postcode":"3076",
    "sg:province":"VIC",
    "sg:tags":[
        "olive"
    ],
    "wof:name":"Australian Olive Oil Supplies",
    "wof:placetype":"venue"
},
  "geometry": {"coordinates":[145.012115478,-37.6462554932],"type":"Point"}
}