{
  "type": "Feature",
  "properties": {
    "addr:full":"7 Prescott Crs Gawler Belt SA 5118",
    "addr:housenumber":"7",
    "addr:postcode":"5118",
    "addr:street":"Prescott Crs",
    "iso:country":"AU",
    "sg:address":"7 Prescott Crs",
    "sg:city":"Gawler Belt",
    "sg:classifiers":[
        {
            "category":"Retail",
            "subcategory":"Auto Repair",
            "type":"Services"
        }
    ],
    "sg:phone":"+61 8 8522 1166",
    "sg:postcode":"5118",
    "sg:province":"SA",
    "sg:tags":[
        "electrical"
    ],
    "wof:name":"Gawler Auto Electrics",
    "wof:placetype":"venue"
},
  "geometry": {"coordinates":[138.73547400000001,-34.574772],"type":"Point"}
}