{
  "type": "Feature",
  "properties": {
    "addr:full":"10 James St Burleigh Heads QLD 4220",
    "addr:housenumber":"10",
    "addr:postcode":"4220",
    "addr:street":"James St",
    "iso:country":"AU",
    "sg:address":"10 James St",
    "sg:city":"Burleigh Heads",
    "sg:classifiers":[
        {
            "category":"Professional",
            "subcategory":"Accounting & Tax Preparation",
            "type":"Services"
        }
    ],
    "sg:phone":"+61 7 5576 7033",
    "sg:postcode":"4220",
    "sg:province":"QLD",
    "sg:tags":[
        "accountant",
        "auditor"
    ],
    "wof:name":"Hickey B",
    "wof:placetype":"venue"
},
  "geometry": {"coordinates":[153.45138549800001,-28.0894870758],"type":"Point"}
}