{
  "type": "Feature",
  "properties": {
    "addr:full":"41 Belmore St Yarrawonga VIC 3730",
    "addr:housenumber":"41",
    "addr:postcode":"3730",
    "addr:street":"Belmore St",
    "iso:country":"AU",
    "sg:address":"41 Belmore St",
    "sg:city":"Yarrawonga",
    "sg:classifiers":[
        {
            "category":"Shopping",
            "subcategory":"Clothing, Apparel, & Fashions",
            "type":"Retail Goods"
        }
    ],
    "sg:phone":"+61 3 5744 3436",
    "sg:postcode":"3730",
    "sg:province":"VIC",
    "sg:tags":[
        "lady",
        "wear"
    ],
    "wof:name":"Black Label",
    "wof:placetype":"venue"
},
  "geometry": {"coordinates":[146.00424194300001,-36.0104293823],"type":"Point"}
}