{
  "type": "Feature",
  "properties": {
    "addr:full":"16- 20 McGill St Shepparton VIC 3630",
    "addr:housenumber":"20",
    "addr:postcode":"3630",
    "addr:street":"Mcgill St",
    "iso:country":"AU",
    "sg:address":"16- 20 McGill St",
    "sg:city":"Shepparton",
    "sg:classifiers":[
        {
            "category":"Wholesale",
            "subcategory":"Painting Supplies",
            "type":"Manufacturing & Wholesale Goods"
        }
    ],
    "sg:phone":"+61 3 5821 1477",
    "sg:postcode":"3630",
    "sg:province":"VIC",
    "sg:tags":[
        "wholesaler",
        "paint",
        "mfrs"
    ],
    "wof:name":"Dominion Plastic Industries Pty Ltd",
    "wof:placetype":"venue"
},
  "geometry": {"coordinates":[145.42967224099999,-36.3633766174],"type":"Point"}
}