{
  "type": "Feature",
  "properties": {
    "iso:country":"AU",
    "sg:address":"150 Pine Ave",
    "sg:city":"Mildura",
    "sg:classifiers":[
        {
            "category":"Banks & Credit Unions",
            "subcategory":"Financial Services",
            "type":"Services"
        }
    ],
    "sg:phone":"+61 3 5021 3931",
    "sg:postcode":"3500",
    "sg:province":"VIC",
    "sg:tags":[
        "planning"
    ],
    "wof:name":"RetireInvest",
    "wof:placetype":"venue"
},
  "geometry": {"coordinates":[142.15504455600001,-34.1863861084],"type":"Point"}
}