{
  "type": "Feature",
  "properties": {
    "iso:country":"AU",
    "sg:address":"cnr West Tce & Hindley St",
    "sg:city":"Adelaide",
    "sg:classifiers":[
        {
            "category":"Autos & Motor Vehicles",
            "subcategory":"Automobile Sales",
            "type":"Retail Goods"
        }
    ],
    "sg:phone":"+61 1300 137 733",
    "sg:postcode":"5000",
    "sg:province":"SA",
    "sg:tags":[
        "car",
        "new"
    ],
    "sg:website":"http://www.jarvissubaru.com.au",
    "wof:name":"Jarvis Subaru",
    "wof:placetype":"venue"
},
  "geometry": {"coordinates":[138.59950256400001,-34.9229888916],"type":"Point"}
}