{
  "type": "Feature",
  "properties": {
    "addr:full":"25 Larch Crs Mt Waverley VIC 3149",
    "addr:housenumber":"25",
    "addr:postcode":"3149",
    "addr:street":"Larch Crs Mt",
    "iso:country":"AU",
    "sg:address":"25 Larch Crs",
    "sg:city":"Mt Waverley",
    "sg:classifiers":[
        {
            "category":"Professional",
            "subcategory":"Engineering",
            "type":"Services"
        }
    ],
    "sg:phone":"+61 3 9803 2042",
    "sg:postcode":"3149",
    "sg:province":"VIC",
    "sg:tags":[
        "consulting",
        "engineer"
    ],
    "wof:name":"Linbar Consulting Services",
    "wof:placetype":"venue"
},
  "geometry": {"coordinates":[145.15850830100001,-37.8134117126],"type":"Point"}
}