{
  "type": "Feature",
  "properties": {
    "addr:full":"522a Nepean Hwy Bonbeach VIC 3196",
    "addr:housenumber":"522a",
    "addr:postcode":"3196",
    "addr:street":"Nepean Hwy",
    "iso:country":"AU",
    "sg:address":"522a Nepean Hwy",
    "sg:city":"Bonbeach",
    "sg:classifiers":[
        {
            "category":"Professional",
            "subcategory":"Computer Services",
            "type":"Services"
        }
    ],
    "sg:phone":"+61 3 9772 1158",
    "sg:postcode":"3196",
    "sg:province":"VIC",
    "sg:tags":[
        "repairs",
        "upgrade",
        "equipment"
    ],
    "wof:name":"P.H. Tek",
    "wof:placetype":"venue"
},
  "geometry": {"coordinates":[145.11920165999999,-38.0619354248],"type":"Point"}
}