{
  "type": "Feature",
  "properties": {
    "addr:full":"20 Wallis St Woollahra NSW 2025",
    "addr:housenumber":"20",
    "addr:postcode":"2025",
    "addr:street":"Wallis St",
    "iso:country":"AU",
    "sg:address":"20 Wallis St",
    "sg:city":"Woollahra",
    "sg:classifiers":[
        {
            "category":"Autos & Motor Vehicles",
            "subcategory":"Fuel & Gas Station",
            "type":"Retail Goods"
        }
    ],
    "sg:phone":"+61 2 9363 3254",
    "sg:postcode":"2025",
    "sg:province":"NSW",
    "wof:name":"Wallis St Garage",
    "wof:placetype":"venue"
},
  "geometry": {"coordinates":[151.23739624000001,-33.8901481628],"type":"Point"}
}