{
  "type": "Feature",
  "properties": {
    "addr:full":"444 South Arm Rd Lauderdale TAS 7021",
    "addr:housenumber":"444",
    "addr:postcode":"7021",
    "addr:street":"South Arm Rd",
    "iso:country":"AU",
    "sg:address":"444 South Arm Rd",
    "sg:city":"Lauderdale",
    "sg:classifiers":[
        {
            "category":"Health Services",
            "subcategory":"Doctor",
            "type":"Services"
        }
    ],
    "sg:phone":"+61 3 6248 1222",
    "sg:postcode":"7021",
    "sg:province":"TAS",
    "sg:tags":[
        "medical",
        "practitioner"
    ],
    "wof:name":"Straatsma Paula",
    "wof:placetype":"venue"
},
  "geometry": {"coordinates":[147.48052978499999,-42.9067955017],"type":"Point"}
}