{
  "type": "Feature",
  "properties": {
    "iso:country":"AU",
    "sg:address":"347 Main Rd",
    "sg:city":"Emerald",
    "sg:classifiers":[
        {
            "category":"Banks & Credit Unions",
            "subcategory":"Financial Services",
            "type":"Services"
        }
    ],
    "sg:phone":"+61 414 709 804",
    "sg:postcode":"3782",
    "sg:province":"VIC",
    "sg:tags":[
        "loan",
        "finance",
        "mortgage"
    ],
    "wof:name":"Choice Home Loans",
    "wof:placetype":"venue"
},
  "geometry": {"coordinates":[145.441193,-37.932167],"type":"Point"}
}