{
  "type": "Feature",
  "properties": {
    "iso:country":"AU",
    "sg:address":"Lot 3, Hollylea Rd",
    "sg:city":"Leumeah",
    "sg:classifiers":[
        {
            "category":"Retail",
            "subcategory":"Auto Repair",
            "type":"Services"
        }
    ],
    "sg:phone":"+61 2 4625 0023",
    "sg:postcode":"2560",
    "sg:province":"NSW",
    "sg:tags":[
        "repairer",
        "motor",
        "engineer"
    ],
    "wof:name":"Extone Automotive",
    "wof:placetype":"venue"
},
  "geometry": {"coordinates":[150.82731628400001,-34.0509147644],"type":"Point"}
}