{
  "type": "Feature",
  "properties": {
    "addr:full":"2/ 29 Tozer St West Kempsey NSW 2440",
    "addr:housenumber":"/ 29",
    "addr:postcode":"2440",
    "addr:street":"Tozer St West",
    "iso:country":"AU",
    "sg:address":"2/ 29 Tozer St",
    "sg:city":"West Kempsey",
    "sg:classifiers":[
        {
            "category":"Banks & Credit Unions",
            "subcategory":"Financial Services",
            "type":"Services"
        }
    ],
    "sg:phone":"+61 2 6562 6551",
    "sg:postcode":"2440",
    "sg:province":"NSW",
    "sg:tags":[
        "annuity",
        "rollover",
        "superannuation",
        "consultant"
    ],
    "wof:name":"Elite Super Pty Ltd",
    "wof:placetype":"venue"
},
  "geometry": {"coordinates":[152.82905600000001,-31.079832],"type":"Point"}
}