{
  "type": "Feature",
  "properties": {
    "iso:country":"AU",
    "sg:address":"18 Canning St",
    "sg:city":"Avondale Heights",
    "sg:classifiers":[
        {
            "category":"Professional",
            "subcategory":"Accounting & Tax Preparation",
            "type":"Services"
        }
    ],
    "sg:phone":"+61 3 9318 5145",
    "sg:postcode":"3034",
    "sg:province":"VIC",
    "sg:tags":[
        "accountant",
        "auditor"
    ],
    "wof:name":"Gale L W",
    "wof:placetype":"venue"
},
  "geometry": {"coordinates":[144.866928,-37.770653],"type":"Point"}
}