{
  "type": "Feature",
  "properties": {
    "iso:country":"AU",
    "sg:address":"20 Trink St",
    "sg:city":"Cloverdale",
    "sg:classifiers":[
        {
            "category":"Building & Trades",
            "subcategory":"Construction",
            "type":"Services"
        }
    ],
    "sg:phone":"+61 407 981 544",
    "sg:postcode":"6105",
    "sg:province":"WA",
    "sg:tags":[
        "joiner",
        "carpenter"
    ],
    "wof:name":"Potts S G",
    "wof:placetype":"venue"
},
  "geometry": {"coordinates":[115.945068359,-31.9646072388],"type":"Point"}
}