{
  "type": "Feature",
  "properties": {
    "addr:full":"PO Box 266 Bulleen VIC 3105",
    "addr:postcode":"3105",
    "iso:country":"AU",
    "sg:address":"PO Box 266",
    "sg:city":"Bulleen",
    "sg:classifiers":[
        {
            "category":"Building & Trades",
            "subcategory":"Construction",
            "type":"Services"
        }
    ],
    "sg:phone":"+61 3 9852 0818",
    "sg:postcode":"3105",
    "sg:province":"VIC",
    "sg:tags":[
        "contractor"
    ],
    "wof:name":"Long Gong Building Construction P/L",
    "wof:placetype":"venue"
},
  "geometry": {"coordinates":[145.085693359,-37.766960144],"type":"Point"}
}