{
  "type": "Feature",
  "properties": {
    "iso:country":"AU",
    "sg:address":"43 Carrington Rd",
    "sg:city":"Box Hill",
    "sg:classifiers":[
        {
            "category":"Shopping",
            "subcategory":"Stationery & Office Supplies",
            "type":"Retail Goods"
        }
    ],
    "sg:phone":"+61 3 9899 4844",
    "sg:postcode":"3128",
    "sg:province":"VIC",
    "sg:tags":[
        "equipment",
        "facsimile"
    ],
    "wof:name":"Brother International (Aust) Pty Ltd",
    "wof:placetype":"venue"
},
  "geometry": {"coordinates":[145.12121582,-37.8201751709],"type":"Point"}
}