{
  "type": "Feature",
  "properties": {
    "iso:country":"AU",
    "sg:address":"5 Percy St",
    "sg:city":"Heidelberg Heights",
    "sg:classifiers":[
        {
            "category":"Building & Trades",
            "subcategory":"Construction",
            "type":"Services"
        }
    ],
    "sg:phone":"+61 3 9455 1577",
    "sg:postcode":"3081",
    "sg:province":"VIC",
    "sg:tags":[
        "welding"
    ],
    "wof:name":"Tru Line Engineering",
    "wof:placetype":"venue"
},
  "geometry": {"coordinates":[145.050323486,-37.731136322],"type":"Point"}
}