{
  "type": "Feature",
  "properties": {
    "iso:country":"AU",
    "sg:address":"PO Box 483",
    "sg:city":"Cottesloe",
    "sg:classifiers":[
        {
            "category":"Professional",
            "subcategory":"Management & Consulting",
            "type":"Services"
        }
    ],
    "sg:phone":"+61 8 9286 1826",
    "sg:postcode":"6011",
    "sg:province":"WA",
    "sg:tags":[
        "consultant"
    ],
    "wof:name":"360 Direct Pty Ltd",
    "wof:placetype":"venue"
},
  "geometry": {"coordinates":[115.757278442,-31.996049881],"type":"Point"}
}