{
  "type": "Feature",
  "properties": {
    "iso:country":"AU",
    "sg:address":"17 Edward St",
    "sg:city":"Arncliffe",
    "sg:classifiers":[
        {
            "category":"Professional",
            "subcategory":"Computer Services",
            "type":"Services"
        }
    ],
    "sg:phone":"+61 2 9567 2027",
    "sg:postcode":"2205",
    "sg:province":"NSW",
    "sg:tags":[
        "package",
        "software"
    ],
    "wof:name":"Datacrypt",
    "wof:placetype":"venue"
},
  "geometry": {"coordinates":[151.143494,-33.932423],"type":"Point"}
}