{
  "type": "Feature",
  "properties": {
    "iso:country":"AU",
    "sg:address":"87 Days Rd",
    "sg:city":"Grange",
    "sg:classifiers":[
        {
            "category":"Health Services",
            "subcategory":"Health Practitioner",
            "type":"Services"
        }
    ],
    "sg:phone":"+61 7 3356 0456",
    "sg:postcode":"4051",
    "sg:province":"QLD",
    "sg:tags":[
        "acupuncture"
    ],
    "wof:name":"Sweeting Chantel & Geoffrey",
    "wof:placetype":"venue"
},
  "geometry": {"coordinates":[153.019256592,-27.4264793396],"type":"Point"}
}