{
  "type": "Feature",
  "properties": {
    "iso:country":"AU",
    "sg:address":"Cnr Grant Ave & Bay Road",
    "sg:city":"Moorak",
    "sg:classifiers":[
        {
            "category":"Food & Beverages",
            "subcategory":"Bakery",
            "type":"Retail Goods"
        }
    ],
    "sg:phone":"+61 8 8725 8624",
    "sg:postcode":"5291",
    "sg:province":"SA",
    "sg:tags":[
        "baker"
    ],
    "wof:name":"All Occasion Cakes",
    "wof:placetype":"venue"
},
  "geometry": {"coordinates":[140.756073,-37.872105],"type":"Point"}
}