{
  "type": "Feature",
  "properties": {
    "addr:full":"61 Hanson St Corryong VIC 3707",
    "addr:housenumber":"61",
    "addr:postcode":"3707",
    "addr:street":"Hanson St",
    "iso:country":"AU",
    "sg:address":"61 Hanson St",
    "sg:city":"Corryong",
    "sg:classifiers":[
        {
            "category":"Retail",
            "subcategory":"Laundry & Dry Cleaning",
            "type":"Services"
        }
    ],
    "sg:phone":"+61 2 6076 1864",
    "sg:postcode":"3707",
    "sg:province":"VIC",
    "wof:name":"Snappy Laundry Services",
    "wof:placetype":"venue"
},
  "geometry": {"coordinates":[147.903640747,-36.1962776184],"type":"Point"}
}