{
  "type": "Feature",
  "properties": {
    "addr:full":"14 Moorcroft Crt Burnside SA 5066",
    "addr:housenumber":"14",
    "addr:postcode":"5066",
    "addr:street":"Moorcroft Crt",
    "iso:country":"AU",
    "sg:address":"14 Moorcroft Crt",
    "sg:city":"Burnside",
    "sg:classifiers":[
        {
            "category":"Building & Trades",
            "subcategory":"Construction",
            "type":"Services"
        }
    ],
    "sg:phone":"+61 8 8332 8755",
    "sg:postcode":"5066",
    "sg:province":"SA",
    "sg:tags":[
        "contractor"
    ],
    "wof:name":"Caromar Constructions Pty Ltd",
    "wof:placetype":"venue"
},
  "geometry": {"coordinates":[138.663238525,-34.9323272705],"type":"Point"}
}