{
  "type": "Feature",
  "properties": {
    "iso:country":"AU",
    "sg:address":"Queen St",
    "sg:city":"Busselton",
    "sg:classifiers":[
        {
            "category":"Retail",
            "subcategory":"Storage",
            "type":"Services"
        }
    ],
    "sg:phone":"+61 8 9754 1522",
    "sg:postcode":"6280",
    "sg:province":"WA",
    "sg:tags":[
        "removal",
        "furniture"
    ],
    "wof:name":"BJs Self Storage",
    "wof:placetype":"venue"
},
  "geometry": {"coordinates":[115.345001221,-33.6515426636],"type":"Point"}
}