{
  "type": "Feature",
  "properties": {
    "iso:country":"AU",
    "sg:address":"55 Sparks St",
    "sg:city":"Mascot",
    "sg:classifiers":[
        {
            "category":"Building & Trades",
            "subcategory":"Construction",
            "type":"Services"
        }
    ],
    "sg:phone":"+61 412 973 681",
    "sg:postcode":"2020",
    "sg:province":"NSW",
    "sg:tags":[
        "contractor"
    ],
    "wof:name":"Pantaleone Constructions",
    "wof:placetype":"venue"
},
  "geometry": {"coordinates":[151.20335388199999,-33.9330635071],"type":"Point"}
}