{
  "type": "Feature",
  "properties": {
    "addr:full":"161 Wallace St Macksville NSW 2447",
    "addr:housenumber":"161",
    "addr:postcode":"2447",
    "addr:street":"Wallace St",
    "iso:country":"AU",
    "sg:address":"161 Wallace St",
    "sg:city":"Macksville",
    "sg:classifiers":[
        {
            "category":"Manufacturing",
            "subcategory":"Musical Instruments",
            "type":"Manufacturing & Wholesale Goods"
        }
    ],
    "sg:phone":"+61 2 6568 2229",
    "sg:postcode":"2447",
    "sg:province":"NSW",
    "sg:tags":[
        "logging",
        "timber"
    ],
    "wof:name":"Donohoe R V",
    "wof:placetype":"venue"
},
  "geometry": {"coordinates":[152.91461200000001,-30.718962],"type":"Point"}
}