{
  "type": "Feature",
  "properties": {
    "addr:full":"21 Belgravia St Belmont WA 6104",
    "addr:housenumber":"21",
    "addr:postcode":"6104",
    "addr:street":"Belgravia St",
    "iso:country":"AU",
    "sg:address":"21 Belgravia St",
    "sg:city":"Belmont",
    "sg:classifiers":[
        {
            "category":"Wholesale",
            "subcategory":"Auto Parts",
            "type":"Manufacturing & Wholesale Goods"
        }
    ],
    "sg:phone":"+61 8 9277 9477",
    "sg:postcode":"6104",
    "sg:province":"WA",
    "sg:tags":[
        "tyre"
    ],
    "wof:name":"Eurotred",
    "wof:placetype":"venue"
},
  "geometry": {"coordinates":[115.92414856000001,-31.9446792603],"type":"Point"}
}