{
  "type": "Feature",
  "properties": {
    "addr:full":"45 Collins St Melbourne VIC 3000",
    "addr:housenumber":"45",
    "addr:postcode":"3000",
    "addr:street":"Collins St",
    "iso:country":"AU",
    "sg:address":"45 Collins St",
    "sg:city":"Melbourne",
    "sg:classifiers":[
        {
            "category":"Health Services",
            "subcategory":"Optometrist",
            "type":"Services"
        }
    ],
    "sg:phone":"+61 3 9650 2233",
    "sg:postcode":"3000",
    "sg:province":"VIC",
    "wof:name":"Jennings, Besley & Southgate",
    "wof:placetype":"venue"
},
  "geometry": {"coordinates":[144.97233581500001,-37.8139076233],"type":"Point"}
}