{
  "type": "Feature",
  "properties": {
    "iso:country":"AU",
    "sg:address":"57 Robertsons Ave",
    "sg:city":"Redcliffe",
    "sg:classifiers":[
        {
            "category":"Utilities",
            "subcategory":"Electric",
            "type":"Services"
        }
    ],
    "sg:phone":"+61 409 909 387",
    "sg:postcode":"4020",
    "sg:province":"QLD",
    "sg:tags":[
        "electrical",
        "contractor"
    ],
    "wof:name":"Advanced Electrical Systems",
    "wof:placetype":"venue"
},
  "geometry": {"coordinates":[153.107956,-27.239759],"type":"Point"}
}