{
  "type": "Feature",
  "properties": {
    "addr:full":"Shop 1/55- 57 Chamber Rd Marsden QLD 4132",
    "addr:housenumber":"shop 1 / 55 57",
    "addr:postcode":"4132",
    "addr:street":"Chamber Rd",
    "iso:country":"AU",
    "sg:address":"Shop 1/55- 57 Chamber Rd",
    "sg:city":"Marsden",
    "sg:classifiers":[
        {
            "category":"Food & Beverages",
            "subcategory":"Bakery",
            "type":"Retail Goods"
        }
    ],
    "sg:phone":"+61 7 3299 6775",
    "sg:postcode":"4132",
    "sg:province":"QLD",
    "sg:tags":[
        "baker"
    ],
    "wof:name":"TL Golden Bakery",
    "wof:placetype":"venue"
},
  "geometry": {"coordinates":[153.11065673799999,-27.6838645935],"type":"Point"}
}