{
  "type": "Feature",
  "properties": {
    "iso:country":"AU",
    "sg:address":"145 Darling St",
    "sg:city":"Balmain",
    "sg:classifiers":[
        {
            "category":"Deli",
            "type":"Food & Drink"
        }
    ],
    "sg:phone":"+61 2 9352 3935",
    "sg:postcode":"2041",
    "sg:province":"NSW",
    "sg:tags":[
        "delicatessen"
    ],
    "wof:name":"HomeGourmet",
    "wof:placetype":"venue"
},
  "geometry": {"coordinates":[151.18804900000001,-33.858013],"type":"Point"}
}