{
  "type": "Feature",
  "properties": {
    "addr:full":"62 Prairie Vale Rd Bossley Park NSW 2176",
    "addr:housenumber":"62",
    "addr:postcode":"2176",
    "addr:street":"Prairie Vale Rd",
    "iso:country":"AU",
    "sg:address":"62 Prairie Vale Rd",
    "sg:city":"Bossley Park",
    "sg:classifiers":[
        {
            "category":"Health Services",
            "subcategory":"Dentist",
            "type":"Services"
        }
    ],
    "sg:phone":"+61 2 9610 4450",
    "sg:postcode":"2176",
    "sg:province":"NSW",
    "wof:name":"The Dental Surgeons",
    "wof:placetype":"venue"
},
  "geometry": {"coordinates":[150.88528442399999,-33.8665237427],"type":"Point"}
}