{
  "type": "Feature",
  "properties": {
    "addr:full":"2 Point St Fremantle WA 6160",
    "addr:housenumber":"2",
    "addr:postcode":"6160",
    "addr:street":"Point St",
    "iso:country":"AU",
    "sg:address":"2 Point St",
    "sg:city":"Fremantle",
    "sg:classifiers":[
        {
            "category":"Education",
            "subcategory":"School",
            "type":"Public Place"
        }
    ],
    "sg:phone":"+61 8 9335 5215",
    "sg:postcode":"6160",
    "sg:province":"WA",
    "wof:name":"St Patrick's Primary School",
    "wof:placetype":"venue"
},
  "geometry": {"coordinates":[115.749077,-32.051849],"type":"Point"}
}