{
  "type": "Feature",
  "properties": {
    "addr:full":"Studio 11a Duff St Turramurra NSW 2074",
    "addr:housenumber":"11a",
    "addr:postcode":"2074",
    "addr:street":"Duff St",
    "iso:country":"AU",
    "sg:address":"Studio 11a Duff St",
    "sg:city":"Turramurra",
    "sg:classifiers":[
        {
            "category":"Real Estate",
            "subcategory":"Architect",
            "type":"Services"
        }
    ],
    "sg:phone":"+61 2 9440 4810",
    "sg:postcode":"2074",
    "sg:province":"NSW",
    "wof:name":"Jorge Hrdina Architects Pty Ltd",
    "wof:placetype":"venue"
},
  "geometry": {"coordinates":[151.125396728,-33.7334022522],"type":"Point"}
}