{
  "type": "Feature",
  "properties": {
    "addr:full":"Hog Bay Road Kangaroo Island SA 5223",
    "addr:postcode":"5223",
    "addr:street":"Hog Bay Road",
    "iso:country":"AU",
    "sg:address":"Hog Bay Road",
    "sg:city":"Kangaroo Island",
    "sg:classifiers":[
        {
            "category":"Farming",
            "subcategory":"Poultry Farm",
            "type":"Manufacturing & Wholesale Goods"
        }
    ],
    "sg:phone":"+61 8 8553 9097",
    "sg:postcode":"5223",
    "sg:province":"SA",
    "sg:tags":[
        "farmer"
    ],
    "wof:name":"Fryar's Kangaroo Island Free Range Eggs",
    "wof:placetype":"venue"
},
  "geometry": {"coordinates":[137.56036376899999,-35.7261314392],"type":"Point"}
}