{
  "type": "Feature",
  "properties": {
    "iso:country":"AU",
    "sg:address":"4 Abbott St",
    "sg:city":"Yarralumla",
    "sg:classifiers":[
        {
            "category":"Building & Trades",
            "subcategory":"Plumbing",
            "type":"Services"
        }
    ],
    "sg:phone":"+61 412 626 296",
    "sg:postcode":"2600",
    "sg:province":"ACT",
    "sg:tags":[
        "plumber",
        "gasfitters"
    ],
    "wof:name":"CMK Investments Pty Ltd",
    "wof:placetype":"venue"
},
  "geometry": {"coordinates":[149.09791564899999,-35.3111228943],"type":"Point"}
}