{
  "type": "Feature",
  "properties": {
    "addr:full":"Kiosk 5 , Centro Milidura, Mildura VIC 3500",
    "addr:postcode":"3500",
    "iso:country":"AU",
    "sg:address":"Kiosk 5",
    "sg:city":", Centro Milidura, Mildura",
    "sg:classifiers":[
        {
            "category":"Utilities",
            "subcategory":"Telephone",
            "type":"Services"
        }
    ],
    "sg:phone":"+61 3 5023 3199",
    "sg:postcode":"3500",
    "sg:province":"VIC",
    "sg:tags":[
        "accessory"
    ],
    "wof:name":"Allphones Mildura Pty Ltd",
    "wof:placetype":"venue"
},
  "geometry": {"coordinates":[142.154098511,-34.2107391357],"type":"Point"}
}