{
  "type": "Feature",
  "properties": {
    "iso:country":"AU",
    "sg:address":"Level 1 67 Inkerman St",
    "sg:city":"St Kilda",
    "sg:classifiers":[
        {
            "category":"Arts & Performance",
            "subcategory":"Theater",
            "type":"Entertainment"
        }
    ],
    "sg:phone":"+61 3 9525 5795",
    "sg:postcode":"3182",
    "sg:province":"VIC",
    "sg:tags":[
        "theatre"
    ],
    "wof:name":"Acting Antics Pty Ltd",
    "wof:placetype":"venue"
},
  "geometry": {"coordinates":[144.984466553,-37.8645782471],"type":"Point"}
}