{
  "type": "Feature",
  "properties": {
    "addr:full":"120a Unley Rd Unley SA 5061",
    "addr:housenumber":"120a",
    "addr:postcode":"5061",
    "addr:street":"Unley Rd",
    "iso:country":"AU",
    "sg:address":"120a Unley Rd",
    "sg:city":"Unley",
    "sg:classifiers":[
        {
            "category":"Retail",
            "subcategory":"Storage",
            "type":"Services"
        }
    ],
    "sg:phone":"+61 8 8271 1756",
    "sg:postcode":"5061",
    "sg:province":"SA",
    "sg:tags":[
        "equipment",
        "computer",
        "secondhand"
    ],
    "wof:name":"All & Anywhere PC Services",
    "wof:placetype":"venue"
},
  "geometry": {"coordinates":[138.60812377900001,-34.9564170837],"type":"Point"}
}