{
  "type": "Feature",
  "properties": {
    "addr:full":"105 Liverpool St Hobart TAS 7000",
    "addr:housenumber":"105",
    "addr:postcode":"7000",
    "addr:street":"Liverpool St",
    "iso:country":"AU",
    "sg:address":"105 Liverpool St",
    "sg:city":"Hobart",
    "sg:classifiers":[
        {
            "category":"Education",
            "subcategory":"Special Training",
            "type":"Public Place"
        }
    ],
    "sg:phone":"+61 3 6231 3550",
    "sg:postcode":"7000",
    "sg:province":"TAS",
    "sg:tags":[
        "development"
    ],
    "wof:name":"Tasmanian Wholesale, Retail, Associated & Personal Services Industry Training Advisory Board Inc",
    "wof:placetype":"venue"
},
  "geometry": {"coordinates":[147.32632446299999,-42.8818435669],"type":"Point"}
}