{
  "type": "Feature",
  "properties": {
    "addr:full":"PO Box 91 Cammeray North Sydney NSW 2060",
    "addr:postcode":"2060",
    "iso:country":"AU",
    "sg:address":"PO Box 91 Cammeray",
    "sg:city":"North Sydney",
    "sg:classifiers":[
        {
            "category":"Real Estate",
            "subcategory":"Real Estate Agent",
            "type":"Services"
        }
    ],
    "sg:phone":"+61 2 9929 7575",
    "sg:postcode":"2060",
    "sg:province":"NSW",
    "wof:name":"Raine & Horne North Sydney Residential",
    "wof:placetype":"venue"
},
  "geometry": {"coordinates":[151.21556091299999,-33.8236923218],"type":"Point"}
}