{
  "type": "Feature",
  "properties": {
    "addr:full":"92 Stirling Hwy North Fremantle WA 6159",
    "addr:housenumber":"92",
    "addr:postcode":"6159",
    "addr:street":"Stirling Hwy",
    "iso:country":"AU",
    "sg:address":"92 Stirling Hwy",
    "sg:city":"North Fremantle",
    "sg:classifiers":[
        {
            "category":"Manufacturing",
            "subcategory":"Watercraft",
            "type":"Manufacturing & Wholesale Goods"
        }
    ],
    "sg:phone":"+61 8 9335 8652",
    "sg:postcode":"6159",
    "sg:province":"WA",
    "sg:tags":[
        "sail",
        "marine",
        "maker"
    ],
    "wof:name":"West Coast Sails",
    "wof:placetype":"venue"
},
  "geometry": {"coordinates":[115.752747,-32.031269],"type":"Point"}
}