{
  "type": "Feature",
  "properties": {
    "iso:country":"AU",
    "sg:address":"64 Station Rd",
    "sg:city":"Lawnton",
    "sg:classifiers":[
        {
            "category":"Retail",
            "subcategory":"Car Wash",
            "type":"Services"
        }
    ],
    "sg:phone":"+61 413 964 866",
    "sg:postcode":"4501",
    "sg:province":"QLD",
    "sg:tags":[
        "truck",
        "cleaning"
    ],
    "wof:name":"Andy's Mobile Vehicle Detailing",
    "wof:placetype":"venue"
},
  "geometry": {"coordinates":[152.981292725,-27.2815189362],"type":"Point"}
}