{
  "type": "Feature",
  "properties": {
    "iso:country":"AU",
    "sg:address":"10 Dyson St",
    "sg:city":"Carrum",
    "sg:classifiers":[
        {
            "category":"Professional",
            "subcategory":"Art Services",
            "type":"Services"
        }
    ],
    "sg:phone":"+61 409 215 216",
    "sg:postcode":"3197",
    "sg:province":"VIC",
    "sg:tags":[
        "decorator",
        "painter"
    ],
    "wof:name":"Moon Painting",
    "wof:placetype":"venue"
},
  "geometry": {"coordinates":[145.13015747099999,-38.0771827698],"type":"Point"}
}