{
  "type": "Feature",
  "properties": {
    "addr:full":"59 Sandringham Rd Sandringham VIC 3191",
    "addr:housenumber":"59",
    "addr:postcode":"3191",
    "addr:street":"Sandringham Rd",
    "iso:country":"AU",
    "sg:address":"59 Sandringham Rd",
    "sg:city":"Sandringham",
    "sg:classifiers":[
        {
            "category":"Education",
            "subcategory":"Kindergarten",
            "type":"Public Place"
        }
    ],
    "sg:phone":"+61 3 9598 6042",
    "sg:postcode":"3191",
    "sg:province":"VIC",
    "sg:tags":[
        "pre-schools"
    ],
    "wof:name":"Nagle Pre-School Association",
    "wof:placetype":"venue"
},
  "geometry": {"coordinates":[145.01077270499999,-37.950958252],"type":"Point"}
}