{
  "type": "Feature",
  "properties": {
    "addr:full":"114 John St Singleton NSW 2330",
    "addr:housenumber":"114",
    "addr:postcode":"2330",
    "addr:street":"John St",
    "iso:country":"AU",
    "sg:address":"114 John St",
    "sg:city":"Singleton",
    "sg:classifiers":[
        {
            "category":"Banks & Credit Unions",
            "subcategory":"Bank",
            "type":"Services"
        }
    ],
    "sg:phone":"+61 13 20 32",
    "sg:postcode":"2330",
    "sg:province":"NSW",
    "wof:name":"Westpac",
    "wof:placetype":"venue"
},
  "geometry": {"coordinates":[151.16693100000001,-32.565289],"type":"Point"}
}