{
  "type": "Feature",
  "properties": {
    "addr:full":"Top Floor, Entrance via Rosieville Lane. Balmain NSW 2041",
    "addr:postcode":"2041",
    "addr:street":"Via Rosieville Lane.",
    "iso:country":"AU",
    "sg:address":"Top Floor, Entrance via Rosieville Lane.",
    "sg:city":"Balmain",
    "sg:classifiers":[
        {
            "category":"Shopping",
            "subcategory":"Stationery & Office Supplies",
            "type":"Retail Goods"
        }
    ],
    "sg:phone":"+61 2 9555 2655",
    "sg:postcode":"2041",
    "sg:province":"NSW",
    "sg:tags":[
        "equipment",
        "display",
        "exhibition"
    ],
    "wof:name":"Creative Concept Design",
    "wof:placetype":"venue"
},
  "geometry": {"coordinates":[151.17280600000001,-33.856018],"type":"Point"}
}