{
  "type": "Feature",
  "properties": {
    "iso:country":"AU",
    "sg:address":"6a / 105 Beach St",
    "sg:city":"Port Melbourne",
    "sg:classifiers":[
        {
            "category":"Health Services",
            "subcategory":"Dentist",
            "type":"Services"
        }
    ],
    "sg:phone":"+61 3 9646 1599",
    "sg:postcode":"3207",
    "sg:province":"VIC",
    "wof:name":"Fenwick David Dr",
    "wof:placetype":"venue"
},
  "geometry": {"coordinates":[144.93208300000001,-37.840527],"type":"Point"}
}