{
  "type": "Feature",
  "properties": {
    "addr:full":"Mitchell St Horrocks WA 6535",
    "addr:postcode":"6535",
    "addr:street":"Mitchell St",
    "iso:country":"AU",
    "sg:address":"Mitchell St",
    "sg:city":"Horrocks",
    "sg:classifiers":[
        {
            "category":"Farming",
            "subcategory":"Fish & Marine Products",
            "type":"Manufacturing & Wholesale Goods"
        }
    ],
    "sg:phone":"+61 8 9934 3013",
    "sg:postcode":"6535",
    "sg:province":"WA",
    "sg:tags":[
        "fisherman"
    ],
    "wof:name":"Ash R F & M",
    "wof:placetype":"venue"
},
  "geometry": {"coordinates":[114.430923462,-28.3772411346],"type":"Point"}
}