{
  "type": "Feature",
  "properties": {
    "iso:country":"AU",
    "sg:address":"Wooralla Drv",
    "sg:city":"Mt Eliza",
    "sg:classifiers":[
        {
            "category":"Education",
            "subcategory":"School",
            "type":"Public Place"
        }
    ],
    "sg:phone":"+61 3 9787 1385",
    "sg:postcode":"3930",
    "sg:province":"VIC",
    "sg:tags":[
        "state",
        "except",
        "nsw"
    ],
    "wof:name":"Mt Eliza Primary School",
    "wof:placetype":"venue"
},
  "geometry": {"coordinates":[145.092041016,-38.1959533691],"type":"Point"}
}