{
  "type": "Feature",
  "properties": {
    "iso:country":"AU",
    "sg:address":"U: 3/ 24 Parkland Rd",
    "sg:city":"Osborne Park",
    "sg:classifiers":[
        {
            "category":"Health Services",
            "subcategory":"Doctor",
            "type":"Services"
        }
    ],
    "sg:phone":"+61 8 9340 9555",
    "sg:postcode":"6017",
    "sg:province":"WA",
    "sg:tags":[
        "occupational",
        "safety"
    ],
    "wof:name":"Mount Injury Management Service",
    "wof:placetype":"venue"
},
  "geometry": {"coordinates":[115.816436768,-31.9172229767],"type":"Point"}
}