{
  "type": "Feature",
  "properties": {
    "addr:full":"8 Laidley Pl Florey ACT 2615",
    "addr:housenumber":"8",
    "addr:postcode":"2615",
    "addr:street":"Laidley Pl",
    "iso:country":"AU",
    "sg:address":"8 Laidley Pl",
    "sg:city":"Florey",
    "sg:classifiers":[
        {
            "category":"Building & Trades",
            "subcategory":"Plumbing",
            "type":"Services"
        }
    ],
    "sg:phone":"+61 418 625 147",
    "sg:postcode":"2615",
    "sg:province":"ACT",
    "sg:tags":[
        "plumber",
        "gasfitters"
    ],
    "wof:name":"Monaro, Drainage, Excavation & Hydraulic Services",
    "wof:placetype":"venue"
},
  "geometry": {"coordinates":[149.045654297,-35.2215538025],"type":"Point"}
}