{
  "type": "Feature",
  "properties": {
    "addr:full":"Terry Rd Boyup Brook WA 6244",
    "addr:postcode":"6244",
    "addr:street":"Terry Rd",
    "iso:country":"AU",
    "sg:address":"Terry Rd",
    "sg:city":"Boyup Brook",
    "sg:classifiers":[
        {
            "category":"Farming",
            "subcategory":"Farm",
            "type":"Manufacturing & Wholesale Goods"
        }
    ],
    "sg:phone":"+61 8 9765 1277",
    "sg:postcode":"6244",
    "sg:province":"WA",
    "sg:tags":[
        "farmer"
    ],
    "wof:name":"Treloar M W & B D",
    "wof:placetype":"venue"
},
  "geometry": {"coordinates":[116.38458252,-33.8393287659],"type":"Point"}
}