{
  "type": "Feature",
  "properties": {
    "iso:country":"AU",
    "sg:address":"Evans Lookout Rd",
    "sg:city":"Blackheath",
    "sg:classifiers":[
        {
            "category":"Travel",
            "subcategory":"Hotels & Motels",
            "type":"Entertainment"
        }
    ],
    "sg:phone":"+61 2 4787 8108",
    "sg:postcode":"2785",
    "sg:province":"NSW",
    "wof:name":"Redleaf Resort",
    "wof:placetype":"venue"
},
  "geometry": {"coordinates":[150.28646850600001,-33.6499061584],"type":"Point"}
}