{
  "type": "Feature",
  "properties": {
    "iso:country":"AU",
    "sg:address":"22 Botany St",
    "sg:city":"Randwick",
    "sg:classifiers":[
        {
            "category":"Social Services",
            "subcategory":"Child Care",
            "type":"Services"
        }
    ],
    "sg:phone":"+61 2 9385 1230",
    "sg:postcode":"2031",
    "sg:province":"NSW",
    "wof:name":"Honeypot Childcare Centre",
    "wof:placetype":"venue"
},
  "geometry": {"coordinates":[151.23687744099999,-33.9146156311],"type":"Point"}
}