{
  "type": "Feature",
  "properties": {
    "addr:full":"Lvl 1 34 Hercules St Dulwich Hill NSW 2203",
    "addr:housenumber":"34",
    "addr:postcode":"2203",
    "addr:street":"Hercules St",
    "iso:country":"AU",
    "sg:address":"Lvl 1 34 Hercules St",
    "sg:city":"Dulwich Hill",
    "sg:classifiers":[
        {
            "category":"Shopping",
            "subcategory":"Computers & Home Electronics",
            "type":"Retail Goods"
        }
    ],
    "sg:phone":"+61 2 9798 5509",
    "sg:postcode":"2203",
    "sg:province":"NSW",
    "sg:tags":[
        "equipment",
        "supply"
    ],
    "wof:name":"K K Innovations",
    "wof:placetype":"venue"
},
  "geometry": {"coordinates":[151.13960299999999,-33.905064],"type":"Point"}
}