{
  "type": "Feature",
  "properties": {
    "addr:full":"21 Khartoum St Footscray West VIC 3012",
    "addr:housenumber":"21",
    "addr:postcode":"3012",
    "addr:street":"Khartoum St",
    "iso:country":"AU",
    "sg:address":"21 Khartoum St",
    "sg:city":"Footscray West",
    "sg:classifiers":[
        {
            "category":"Home & Garden",
            "subcategory":"Building Materials",
            "type":"Retail Goods"
        }
    ],
    "sg:phone":"+61 414 256 256",
    "sg:postcode":"3012",
    "sg:province":"VIC",
    "sg:tags":[
        "lawn",
        "cutting",
        "maintenance"
    ],
    "wof:name":"Citywest Property Maintenance",
    "wof:placetype":"venue"
},
  "geometry": {"coordinates":[144.879760742,-37.7917785645],"type":"Point"}
}