{
  "type": "Feature",
  "properties": {
    "iso:country":"AU",
    "sg:address":"Belgrove St",
    "sg:city":"Trangie",
    "sg:classifiers":[
        {
            "category":"Building & Trades",
            "subcategory":"Landscaping Services",
            "type":"Services"
        }
    ],
    "sg:phone":"+61 2 6888 7233",
    "sg:postcode":"2823",
    "sg:province":"NSW",
    "sg:tags":[
        "firebreak",
        "clearing",
        "land",
        "contractor"
    ],
    "wof:name":"Hoey John S",
    "wof:placetype":"venue"
},
  "geometry": {"coordinates":[147.98724365199999,-32.0348091125],"type":"Point"}
}