{
  "type": "Feature",
  "properties": {
    "addr:full":"Shop G130 42 Marine Pde Southport QLD 4215",
    "addr:housenumber":"g130 42",
    "addr:postcode":"4215",
    "addr:street":"Marine Pde",
    "iso:country":"AU",
    "sg:address":"Shop G130 42 Marine Pde",
    "sg:city":"Southport",
    "sg:classifiers":[
        {
            "category":"Shopping",
            "subcategory":"Jewelry",
            "type":"Retail Goods"
        }
    ],
    "sg:phone":"+61 7 5528 3071",
    "sg:postcode":"4215",
    "sg:province":"QLD",
    "sg:tags":[
        "jeweller"
    ],
    "wof:name":"Diamond Mine Manufacturing Jewellers Pty Ltd",
    "wof:placetype":"venue"
},
  "geometry": {"coordinates":[153.41595459000001,-27.9662227631],"type":"Point"}
}