{
  "type": "Feature",
  "properties": {
    "addr:full":"Shop 2-10/ 147 Queen St Campbelltown NSW 2560",
    "addr:housenumber":"2-10 / 147",
    "addr:postcode":"2560",
    "addr:street":"Queen St",
    "iso:country":"AU",
    "sg:address":"Shop 2-10/ 147 Queen St",
    "sg:city":"Campbelltown",
    "sg:classifiers":[
        {
            "category":"Building & Trades",
            "subcategory":"Equipment Rental",
            "type":"Services"
        }
    ],
    "sg:phone":"+61 2 4628 2788",
    "sg:postcode":"2560",
    "sg:province":"NSW",
    "sg:tags":[
        "party",
        "hire"
    ],
    "wof:name":"Spotlight Party Supplies Pty Ltd (SPARTYS)",
    "wof:placetype":"venue"
},
  "geometry": {"coordinates":[150.81439209000001,-34.0663261414],"type":"Point"}
}