{
  "type": "Feature",
  "properties": {
    "iso:country":"AU",
    "sg:address":"13 Orford Crt",
    "sg:city":"Toowoomba",
    "sg:classifiers":[
        {
            "category":"Building & Trades",
            "subcategory":"Construction",
            "type":"Services"
        }
    ],
    "sg:phone":"+61 7 4633 1373",
    "sg:postcode":"4350",
    "sg:province":"QLD",
    "sg:tags":[
        "contractor"
    ],
    "wof:name":"Wayne Mahony",
    "wof:placetype":"venue"
},
  "geometry": {"coordinates":[151.90730300000001,-27.540396],"type":"Point"}
}