{
  "type": "Feature",
  "properties": {
    "iso:country":"AU",
    "sg:address":"1 Pittwater Rd",
    "sg:city":"Gladesville",
    "sg:classifiers":[
        {
            "category":"Real Estate",
            "subcategory":"Real Estate Agent",
            "type":"Services"
        }
    ],
    "sg:phone":"+61 2 9879 6466",
    "sg:postcode":"2111",
    "sg:province":"NSW",
    "wof:name":"Boland Zara Real Estate",
    "wof:placetype":"venue"
},
  "geometry": {"coordinates":[151.12727355999999,-33.8300704956],"type":"Point"}
}