{
  "type": "Feature",
  "properties": {
    "addr:full":"30 Hensler Rd Goondiwindi QLD 4390",
    "addr:housenumber":"30",
    "addr:postcode":"4390",
    "addr:street":"Hensler Rd",
    "iso:country":"AU",
    "sg:address":"30 Hensler Rd",
    "sg:city":"Goondiwindi",
    "sg:classifiers":[
        {
            "category":"Utilities",
            "type":"Services"
        }
    ],
    "sg:phone":"+61 7 4671 3410",
    "sg:postcode":"4390",
    "sg:province":"QLD",
    "sg:tags":[
        "refrigeration",
        "industrial",
        "commercial",
        "retail"
    ],
    "wof:name":"MRC Refrigeration & Air Conditioning",
    "wof:placetype":"venue"
},
  "geometry": {"coordinates":[150.30795288100001,-28.5045814514],"type":"Point"}
}