{
  "type": "Feature",
  "properties": {
    "addr:full":"8 Kippax St Surry Hills NSW 2010",
    "addr:housenumber":"8",
    "addr:postcode":"2010",
    "addr:street":"Kippax St",
    "iso:country":"AU",
    "sg:address":"8 Kippax St",
    "sg:city":"Surry Hills",
    "sg:classifiers":[
        {
            "category":"Professional",
            "subcategory":"Computer Services",
            "type":"Services"
        }
    ],
    "sg:phone":"+61 2 9281 4168",
    "sg:postcode":"2010",
    "sg:province":"NSW",
    "sg:tags":[
        "on-line",
        "provider"
    ],
    "wof:name":"Sivalley Technology",
    "wof:placetype":"venue"
},
  "geometry": {"coordinates":[151.208694458,-33.8844337463],"type":"Point"}
}