{
  "type": "Feature",
  "properties": {
    "iso:country":"AU",
    "sg:address":"PO Box 5081",
    "sg:city":"Victoria Point",
    "sg:classifiers":[
        {
            "category":"Home & Garden",
            "subcategory":"Garden Supply",
            "type":"Retail Goods"
        }
    ],
    "sg:phone":"+61 7 3847 5388",
    "sg:postcode":"4165",
    "sg:province":"QLD",
    "sg:tags":[
        "turf",
        "lawn"
    ],
    "wof:name":"A Betts",
    "wof:placetype":"venue"
},
  "geometry": {"coordinates":[153.28512573200001,-27.595079422],"type":"Point"}
}