{
  "type": "Feature",
  "properties": {
    "addr:full":"154 Bridge St Schofields NSW 2762",
    "addr:housenumber":"154",
    "addr:postcode":"2762",
    "addr:street":"Bridge St",
    "iso:country":"AU",
    "sg:address":"154 Bridge St",
    "sg:city":"Schofields",
    "sg:classifiers":[
        {
            "category":"Utilities",
            "subcategory":"Electric",
            "type":"Services"
        }
    ],
    "sg:phone":"+61 418 673 171",
    "sg:postcode":"2762",
    "sg:province":"NSW",
    "sg:tags":[
        "electrical",
        "contractor"
    ],
    "wof:name":"Ednic Electrical Contractors",
    "wof:placetype":"venue"
},
  "geometry": {"coordinates":[150.87088012699999,-33.7016792297],"type":"Point"}
}