{
  "type": "Feature",
  "properties": {
    "addr:full":"424 Badgerup Rd Wanneroo WA 6065",
    "addr:housenumber":"424",
    "addr:postcode":"6065",
    "addr:street":"Badgerup Rd",
    "iso:country":"AU",
    "sg:address":"424 Badgerup Rd",
    "sg:city":"Wanneroo",
    "sg:classifiers":[
        {
            "category":"Food & Beverages",
            "subcategory":"Fruits & Vegetables",
            "type":"Retail Goods"
        }
    ],
    "sg:phone":"+61 8 9405 1572",
    "sg:postcode":"6065",
    "sg:province":"WA",
    "sg:tags":[
        "greengrocer",
        "fruiterer"
    ],
    "wof:name":"D&#039;Uvas",
    "wof:placetype":"venue"
},
  "geometry": {"coordinates":[115.845947266,-31.7656383514],"type":"Point"}
}