{
  "type": "Feature",
  "properties": {
    "iso:country":"AU",
    "sg:address":"79 Clive St",
    "sg:city":"Katanning",
    "sg:classifiers":[
        {
            "category":"Wholesale",
            "subcategory":"Fruits & Vegetables",
            "type":"Manufacturing & Wholesale Goods"
        }
    ],
    "sg:phone":"+61 8 9821 5116",
    "sg:postcode":"6317",
    "sg:province":"WA",
    "sg:tags":[
        "produce",
        "grain"
    ],
    "wof:name":"Grain Pool Pty Ltd",
    "wof:placetype":"venue"
},
  "geometry": {"coordinates":[117.554916382,-33.6910972595],"type":"Point"}
}