{
  "type": "Feature",
  "properties": {
    "addr:full":"Cnr Picton Rd & Poat St Bunbury WA 6230",
    "addr:postcode":"6230",
    "addr:street":"Cnr Picton Rd & Poat St",
    "iso:country":"AU",
    "sg:address":"Cnr Picton Rd & Poat St",
    "sg:city":"Bunbury",
    "sg:classifiers":[
        {
            "category":"Autos & Motor Vehicles",
            "subcategory":"Auto Supplies",
            "type":"Retail Goods"
        }
    ],
    "sg:phone":"+61 8 9725 4822",
    "sg:postcode":"6230",
    "sg:province":"WA",
    "sg:tags":[
        "equipment",
        "part",
        "truck"
    ],
    "wof:name":"Truckline Truck & Trailer Parts",
    "wof:placetype":"venue"
},
  "geometry": {"coordinates":[115.66590100000001,-33.348263],"type":"Point"}
}