{
  "type": "Feature",
  "properties": {
    "addr:full":"57 Windella Ave Kew East VIC 3102",
    "addr:housenumber":"57",
    "addr:postcode":"3102",
    "addr:street":"Windella Ave",
    "iso:country":"AU",
    "sg:address":"57 Windella Ave",
    "sg:city":"Kew East",
    "sg:classifiers":[
        {
            "category":"Utilities",
            "subcategory":"Electric",
            "type":"Services"
        }
    ],
    "sg:phone":"+61 3 9859 1330",
    "sg:postcode":"3102",
    "sg:province":"VIC",
    "sg:tags":[
        "electrical",
        "contractor"
    ],
    "wof:name":"Inner East Electrics",
    "wof:placetype":"venue"
},
  "geometry": {"coordinates":[145.050247192,-37.7950134277],"type":"Point"}
}