{
  "type": "Feature",
  "properties": {
    "addr:full":"26 Mathieson Rd Ascot WA 6104",
    "addr:housenumber":"26",
    "addr:postcode":"6104",
    "addr:street":"Mathieson Rd",
    "iso:country":"AU",
    "sg:address":"26 Mathieson Rd",
    "sg:city":"Ascot",
    "sg:classifiers":[
        {
            "category":"Food & Beverages",
            "subcategory":"Fruits & Vegetables",
            "type":"Retail Goods"
        }
    ],
    "sg:phone":"+61 8 9277 3255",
    "sg:postcode":"6104",
    "sg:province":"WA",
    "sg:tags":[
        "greengrocer",
        "fruiterer"
    ],
    "wof:name":"Vegie Man The",
    "wof:placetype":"venue"
},
  "geometry": {"coordinates":[115.92761993400001,-31.937374115],"type":"Point"}
}