{
  "type": "Feature",
  "properties": {
    "iso:country":"AU",
    "sg:address":"Box Rd",
    "sg:city":"Prestons",
    "sg:classifiers":[
        {
            "category":"Social Services",
            "subcategory":"Child Care",
            "type":"Services"
        }
    ],
    "sg:phone":"+61 2 9602 7203",
    "sg:postcode":"2170",
    "sg:province":"NSW",
    "wof:name":"Prestons Children's Centre",
    "wof:placetype":"venue"
},
  "geometry": {"coordinates":[150.88948059099999,-33.9551582336],"type":"Point"}
}