{
  "type": "Feature",
  "properties": {
    "addr:full":"118 Lyttleton St Castlemaine VIC 3450",
    "addr:housenumber":"118",
    "addr:postcode":"3450",
    "addr:street":"Lyttleton St",
    "iso:country":"AU",
    "sg:address":"118 Lyttleton St",
    "sg:city":"Castlemaine",
    "sg:classifiers":[
        {
            "category":"Professional",
            "subcategory":"Art Services",
            "type":"Services"
        }
    ],
    "sg:phone":"+61 3 5472 2680",
    "sg:postcode":"3450",
    "sg:province":"VIC",
    "sg:tags":[
        "artist"
    ],
    "wof:name":"Rachel Tonkin",
    "wof:placetype":"venue"
},
  "geometry": {"coordinates":[144.22854614299999,-37.0658836365],"type":"Point"}
}