{
  "type": "Feature",
  "properties": {
    "addr:full":"Suite 1/ 64 Croydon St Cronulla NSW 2230",
    "addr:housenumber":"64",
    "addr:postcode":"2230",
    "addr:street":"Croydon St",
    "iso:country":"AU",
    "sg:address":"Suite 1/ 64 Croydon St",
    "sg:city":"Cronulla",
    "sg:classifiers":[
        {
            "category":"Real Estate",
            "subcategory":"Real Estate Agent",
            "type":"Services"
        }
    ],
    "sg:phone":"+61 2 9527 0008",
    "sg:postcode":"2230",
    "sg:province":"NSW",
    "wof:name":"Beach & Bay Realty Pty Ltd",
    "wof:placetype":"venue"
},
  "geometry": {"coordinates":[151.151489258,-34.053565979],"type":"Point"}
}