{
  "type": "Feature",
  "properties": {
    "addr:full":"403 Warrigal Rd Burwood VIC 3125",
    "addr:housenumber":"403",
    "addr:postcode":"3125",
    "addr:street":"Warrigal Rd",
    "iso:country":"AU",
    "sg:address":"403 Warrigal Rd",
    "sg:city":"Burwood",
    "sg:classifiers":[
        {
            "category":"Health Services",
            "subcategory":"Doctor",
            "type":"Services"
        }
    ],
    "sg:phone":"+61 1300 664 146",
    "sg:postcode":"3125",
    "sg:province":"VIC",
    "sg:tags":[
        "medical",
        "practitioner"
    ],
    "wof:name":"Delmont Memory Clinic",
    "wof:placetype":"venue"
},
  "geometry": {"coordinates":[145.09466552699999,-37.8565788269],"type":"Point"}
}