{
  "type": "Feature",
  "properties": {
    "addr:full":"7 Dingley St Templestowe Lower VIC 3107",
    "addr:housenumber":"7",
    "addr:postcode":"3107",
    "addr:street":"Dingley St",
    "iso:country":"AU",
    "sg:address":"7 Dingley St",
    "sg:city":"Templestowe Lower",
    "sg:classifiers":[
        {
            "category":"Building & Trades",
            "subcategory":"Construction",
            "type":"Services"
        }
    ],
    "sg:phone":"+61 418 540 087",
    "sg:postcode":"3107",
    "sg:province":"VIC",
    "sg:tags":[
        "renovation",
        "alterations",
        "extension",
        "contractor"
    ],
    "wof:name":"Evans Constructions (VIC) Pty Ltd",
    "wof:placetype":"venue"
},
  "geometry": {"coordinates":[145.10598754899999,-37.7608261108],"type":"Point"}
}