{
  "type": "Feature",
  "properties": {
    "addr:full":"37 Minkara Rd Bayview NSW 2104",
    "addr:housenumber":"37",
    "addr:postcode":"2104",
    "addr:street":"Minkara Rd",
    "iso:country":"AU",
    "sg:address":"37 Minkara Rd",
    "sg:city":"Bayview",
    "sg:classifiers":[
        {
            "category":"Professional",
            "type":"Services"
        }
    ],
    "sg:phone":"+61 2 9979 6037",
    "sg:postcode":"2104",
    "sg:province":"NSW",
    "sg:tags":[
        "shop",
        "fitting"
    ],
    "wof:name":"Jendin Pty Ltd",
    "wof:placetype":"venue"
},
  "geometry": {"coordinates":[151.28465299999999,-33.654755],"type":"Point"}
}