{
  "type": "Feature",
  "properties": {
    "addr:full":"13 Watsons Rd Kinglake West VIC 3757",
    "addr:housenumber":"13",
    "addr:postcode":"3757",
    "addr:street":"Watsons Rd",
    "iso:country":"AU",
    "sg:address":"13 Watsons Rd",
    "sg:city":"Kinglake West",
    "sg:classifiers":[
        {
            "category":"Retail",
            "subcategory":"Auto Repair",
            "type":"Services"
        }
    ],
    "sg:phone":"+61 3 5786 5438",
    "sg:postcode":"3757",
    "sg:province":"VIC",
    "sg:tags":[
        "repairer",
        "motor",
        "engineer"
    ],
    "wof:name":"Car Safety",
    "wof:placetype":"venue"
},
  "geometry": {"coordinates":[145.278885,-37.480087],"type":"Point"}
}