{
  "type": "Feature",
  "properties": {
    "addr:full":"Home Base Expo 55 Salvado Rd Subiaco WA 6008",
    "addr:housenumber":"55",
    "addr:postcode":"6008",
    "addr:street":"Salvado Rd",
    "iso:country":"AU",
    "sg:address":"Home Base Expo 55 Salvado Rd",
    "sg:city":"Subiaco",
    "sg:classifiers":[
        {
            "category":"Home & Garden",
            "subcategory":"Building Materials",
            "type":"Retail Goods"
        }
    ],
    "sg:phone":"+61 8 9381 9344",
    "sg:postcode":"6008",
    "sg:province":"WA",
    "sg:tags":[
        "fitting",
        "door"
    ],
    "wof:name":"M & B Quality Building Products",
    "wof:placetype":"venue"
},
  "geometry": {"coordinates":[115.820007324,-31.9419345856],"type":"Point"}
}