{
  "type": "Feature",
  "properties": {
    "addr:full":"1445 Keane St Mt Helena WA 6082",
    "addr:postcode":"1445;6082",
    "addr:street":"Keane St",
    "iso:country":"AU",
    "sg:address":"1445 Keane St",
    "sg:city":"Mt Helena",
    "sg:classifiers":[
        {
            "category":"Building & Trades",
            "subcategory":"Equipment Rental",
            "type":"Services"
        }
    ],
    "sg:phone":"+61 8 9572 5695",
    "sg:postcode":"6082",
    "sg:province":"WA",
    "sg:tags":[
        "demolition",
        "contractor"
    ],
    "wof:name":"Hills Asbestos Removal & Demolition",
    "wof:placetype":"venue"
},
  "geometry": {"coordinates":[116.209182739,-31.8794288635],"type":"Point"}
}