{
  "type": "Feature",
  "properties": {
    "iso:country":"AU",
    "sg:address":"Shp 7, 54 Hall St",
    "sg:city":"Bondi Beach",
    "sg:classifiers":[
        {
            "category":"Personal",
            "subcategory":"Beauty Salon",
            "type":"Services"
        }
    ],
    "sg:phone":"+61 2 9130 2312",
    "sg:postcode":"2026",
    "sg:province":"NSW",
    "sg:tags":[
        "hairdresser"
    ],
    "wof:name":"Hair Tamers",
    "wof:placetype":"venue"
},
  "geometry": {"coordinates":[151.27116394000001,-33.8895797729],"type":"Point"}
}