{
  "type": "Feature",
  "properties": {
    "addr:full":"58 Solway Crt Carbrook QLD 4130",
    "addr:housenumber":"58",
    "addr:postcode":"4130",
    "addr:street":"Solway Crt",
    "iso:country":"AU",
    "sg:address":"58 Solway Crt",
    "sg:city":"Carbrook",
    "sg:classifiers":[
        {
            "category":"Utilities",
            "subcategory":"Water",
            "type":"Services"
        }
    ],
    "sg:phone":"+61 7 3829 1876",
    "sg:postcode":"4130",
    "sg:province":"QLD",
    "sg:tags":[
        "cartage"
    ],
    "wof:name":"Solway Water Services",
    "wof:placetype":"venue"
},
  "geometry": {"coordinates":[153.27223205600001,-27.6624145508],"type":"Point"}
}