{
  "type": "Feature",
  "properties": {
    "addr:full":"PO Box 102 Watervale SA 5452",
    "addr:postcode":"5452",
    "iso:country":"AU",
    "sg:address":"PO Box 102",
    "sg:city":"Watervale",
    "sg:classifiers":[
        {
            "category":"Shopping",
            "subcategory":"Party Supplies",
            "type":"Retail Goods"
        }
    ],
    "sg:phone":"+61 8 8843 4113",
    "sg:postcode":"5452",
    "sg:province":"SA",
    "sg:tags":[
        "hire",
        "costume"
    ],
    "wof:name":"The Shed Quality Craft Works",
    "wof:placetype":"venue"
},
  "geometry": {"coordinates":[138.64515685999999,-33.9593582153],"type":"Point"}
}