{
  "type": "Feature",
  "properties": {
    "addr:full":"5 Loves Ave Oyster Bay NSW 2225",
    "addr:housenumber":"5",
    "addr:postcode":"2225",
    "addr:street":"Loves Ave",
    "iso:country":"AU",
    "sg:address":"5 Loves Ave",
    "sg:city":"Oyster Bay",
    "sg:classifiers":[
        {
            "category":"Professional",
            "subcategory":"Accounting & Tax Preparation",
            "type":"Services"
        }
    ],
    "sg:phone":"+61 2 9528 7060",
    "sg:postcode":"2225",
    "sg:province":"NSW",
    "sg:tags":[
        "accountant",
        "auditor"
    ],
    "wof:name":"McKillop R A",
    "wof:placetype":"venue"
},
  "geometry": {"coordinates":[151.07992553700001,-34.0088577271],"type":"Point"}
}