{
  "type": "Feature",
  "properties": {
    "addr:full":"Cnr Scoresby & Boronia Rds Boronia VIC 3155",
    "addr:postcode":"3155",
    "addr:street":"Cnr",
    "iso:country":"AU",
    "sg:address":"Cnr Scoresby & Boronia Rds",
    "sg:city":"Boronia",
    "sg:classifiers":[
        {
            "category":"Building & Trades",
            "subcategory":"Plumbing",
            "type":"Services"
        }
    ],
    "sg:phone":"+61 3 9762 5844",
    "sg:postcode":"3155",
    "sg:province":"VIC",
    "sg:tags":[
        "repair",
        "appliance",
        "system",
        "heating"
    ],
    "wof:name":"Plum Heating & Cooling Australia",
    "wof:placetype":"venue"
},
  "geometry": {"coordinates":[145.26707458499999,-37.8605690002],"type":"Point"}
}