{
  "type": "Feature",
  "properties": {
    "iso:country":"AU",
    "sg:address":"360 Victoria St",
    "sg:city":"Wetherill Park",
    "sg:classifiers":[
        {
            "category":"Manufacturing",
            "subcategory":"Metals",
            "type":"Manufacturing & Wholesale Goods"
        }
    ],
    "sg:phone":"+61 2 9729 0044",
    "sg:postcode":"2164",
    "sg:province":"NSW",
    "sg:tags":[
        "steel",
        "fabricator",
        "mfrs"
    ],
    "wof:name":"Tom Stoddard (NSW) Pty Ltd",
    "wof:placetype":"venue"
},
  "geometry": {"coordinates":[150.907073975,-33.8463172913],"type":"Point"}
}