{
  "type": "Feature",
  "properties": {
    "addr:full":"29 Waterloo St Cleveland QLD 4163",
    "addr:housenumber":"29",
    "addr:postcode":"4163",
    "addr:street":"Waterloo St",
    "iso:country":"AU",
    "sg:address":"29 Waterloo St",
    "sg:city":"Cleveland",
    "sg:classifiers":[
        {
            "category":"Social Services",
            "subcategory":"Child Care",
            "type":"Services"
        }
    ],
    "sg:phone":"+61 7 3286 1953",
    "sg:postcode":"4163",
    "sg:province":"QLD",
    "wof:name":"St James Lutheran Child Care Centre, C & K Pre-School & Kindergarten",
    "wof:placetype":"venue"
},
  "geometry": {"coordinates":[153.26475524899999,-27.5284996033],"type":"Point"}
}