{
  "type": "Feature",
  "properties": {
    "iso:country":"AU",
    "sg:address":"53 O&#039;Neill St",
    "sg:city":"Granville",
    "sg:classifiers":[
        {
            "category":"Building & Trades",
            "subcategory":"Construction",
            "type":"Services"
        }
    ],
    "sg:phone":"+61 412 961 673",
    "sg:postcode":"2142",
    "sg:province":"NSW",
    "sg:tags":[
        "rendering",
        "cement"
    ],
    "wof:name":"George Tak Tak & Sons Pty Ltd",
    "wof:placetype":"venue"
},
  "geometry": {"coordinates":[151.00906372099999,-33.8446846008],"type":"Point"}
}