{
  "type": "Feature",
  "properties": {
    "addr:full":"PO Box 821 Cottesloe WA 6011",
    "addr:postcode":"6011",
    "iso:country":"AU",
    "sg:address":"PO Box 821",
    "sg:city":"Cottesloe",
    "sg:classifiers":[
        {
            "category":"Utilities",
            "subcategory":"Electric",
            "type":"Services"
        }
    ],
    "sg:phone":"+61 407 997 049",
    "sg:postcode":"6011",
    "sg:province":"WA",
    "sg:tags":[
        "electrical",
        "contractor"
    ],
    "wof:name":"Electric Blue",
    "wof:placetype":"venue"
},
  "geometry": {"coordinates":[115.757278442,-31.996049881],"type":"Point"}
}