{
  "type": "Feature",
  "properties": {
    "iso:country":"AU",
    "sg:address":"4 Fitzroy Crs",
    "sg:city":"Leumeah",
    "sg:classifiers":[
        {
            "category":"Building & Trades",
            "subcategory":"Cleaning & Sanitation",
            "type":"Services"
        }
    ],
    "sg:phone":"+61 2 4626 3200",
    "sg:postcode":"2560",
    "sg:province":"NSW",
    "sg:tags":[
        "cleaner",
        "repairer",
        "roof"
    ],
    "wof:name":"Aston Roofing",
    "wof:placetype":"venue"
},
  "geometry": {"coordinates":[150.83424377399999,-34.0516700745],"type":"Point"}
}