{
  "type": "Feature",
  "properties": {
    "addr:full":"334 St Georges Rd Thornbury VIC 3071",
    "addr:housenumber":"334",
    "addr:postcode":"3071",
    "addr:street":"St Georges Rd",
    "iso:country":"AU",
    "sg:address":"334 St Georges Rd",
    "sg:city":"Thornbury",
    "sg:classifiers":[
        {
            "category":"Travel",
            "subcategory":"Hotels & Motels",
            "type":"Entertainment"
        }
    ],
    "sg:phone":"+61 3 9416 8233",
    "sg:postcode":"3071",
    "sg:province":"VIC",
    "sg:website":"http://www.stgeorgesmotorinn.com.au",
    "wof:name":"St Georges Motor Inn",
    "wof:placetype":"venue"
},
  "geometry": {"coordinates":[144.99371337900001,-37.7589607239],"type":"Point"}
}