{
  "type": "Feature",
  "properties": {
    "addr:full":"55 Withers St Albert Park VIC 3206",
    "addr:housenumber":"55",
    "addr:postcode":"3206",
    "addr:street":"Withers St",
    "iso:country":"AU",
    "sg:address":"55 Withers St",
    "sg:city":"Albert Park",
    "sg:classifiers":[
        {
            "category":"Professional",
            "subcategory":"Employment Agencies",
            "type":"Services"
        }
    ],
    "sg:phone":"+61 412 341 778",
    "sg:postcode":"3206",
    "sg:province":"VIC",
    "sg:tags":[
        "entertainer",
        "agent"
    ],
    "wof:name":"Unicomb Jamie",
    "wof:placetype":"venue"
},
  "geometry": {"coordinates":[144.947327,-37.846786],"type":"Point"}
}