{
  "type": "Feature",
  "properties": {
    "addr:full":"Unit 6 / 291 Wickham Rd Moorabbin VIC 3189",
    "addr:housenumber":"/ 291",
    "addr:postcode":"3189",
    "addr:street":"Wickham Rd",
    "iso:country":"AU",
    "sg:address":"Unit 6 / 291 Wickham Rd",
    "sg:city":"Moorabbin",
    "sg:classifiers":[
        {
            "category":"Utilities",
            "subcategory":"Electric",
            "type":"Services"
        }
    ],
    "sg:phone":"+61 3 9553 6600",
    "sg:postcode":"3189",
    "sg:province":"VIC",
    "sg:tags":[
        "electrical",
        "contractor"
    ],
    "wof:name":"Barlec Electrical Services P/L",
    "wof:placetype":"venue"
},
  "geometry": {"coordinates":[145.058517456,-37.9469871521],"type":"Point"}
}