{
  "type": "Feature",
  "properties": {
    "addr:full":"87 Gavenlock Rd Tuggerah NSW 2259",
    "addr:housenumber":"87",
    "addr:postcode":"2259",
    "addr:street":"Gavenlock Rd",
    "iso:country":"AU",
    "sg:address":"87 Gavenlock Rd",
    "sg:city":"Tuggerah",
    "sg:classifiers":[
        {
            "category":"Utilities",
            "subcategory":"Refuse",
            "type":"Services"
        }
    ],
    "sg:phone":"+61 2 4352 1485",
    "sg:postcode":"2259",
    "sg:province":"NSW",
    "sg:tags":[
        "disposal",
        "reduction",
        "waste"
    ],
    "wof:name":"Coastal Recycled Cooking Oils Pty Ltd",
    "wof:placetype":"venue"
},
  "geometry": {"coordinates":[151.41712951700001,-33.2997703552],"type":"Point"}
}