{
  "type": "Feature",
  "properties": {
    "addr:full":"23 Glassford Rd Kewdale WA 6105",
    "addr:housenumber":"23",
    "addr:postcode":"6105",
    "addr:street":"Glassford Rd",
    "iso:country":"AU",
    "sg:address":"23 Glassford Rd",
    "sg:city":"Kewdale",
    "sg:classifiers":[
        {
            "category":"Home & Garden",
            "subcategory":"Hardware",
            "type":"Retail Goods"
        }
    ],
    "sg:phone":"+61 8 9353 1366",
    "sg:postcode":"6105",
    "sg:province":"WA",
    "sg:tags":[
        "pumping",
        "contractor"
    ],
    "wof:name":"Welltech Total Water Management",
    "wof:placetype":"venue"
},
  "geometry": {"coordinates":[115.950469971,-31.9743289948],"type":"Point"}
}