{
  "type": "Feature",
  "properties": {
    "addr:full":"11 Birchfield Ave Whitfords WA 6025",
    "addr:housenumber":"11",
    "addr:postcode":"6025",
    "addr:street":"Birchfield Ave",
    "iso:country":"AU",
    "sg:address":"11 Birchfield Ave",
    "sg:city":"Whitfords",
    "sg:classifiers":[
        {
            "category":"Arts & Performance",
            "subcategory":"Music",
            "type":"Entertainment"
        }
    ],
    "sg:phone":"+61 8 9307 1234",
    "sg:postcode":"6025",
    "sg:province":"WA",
    "sg:tags":[
        "hi-fi",
        "equipment"
    ],
    "wof:name":"Tech City Electronic",
    "wof:placetype":"venue"
},
  "geometry": {"coordinates":[115.762786865,-31.8007392883],"type":"Point"}
}