{
  "type": "Feature",
  "properties": {
    "addr:full":"16- 24 Britton St Smithfield NSW 2164",
    "addr:housenumber":"24",
    "addr:postcode":"2164",
    "addr:street":"Britton St",
    "iso:country":"AU",
    "sg:address":"16- 24 Britton St",
    "sg:city":"Smithfield",
    "sg:classifiers":[
        {
            "category":"Building & Trades",
            "subcategory":"Construction",
            "type":"Services"
        }
    ],
    "sg:phone":"+61 13 67 24",
    "sg:postcode":"2164",
    "sg:province":"NSW",
    "sg:tags":[
        "scaffolding"
    ],
    "wof:name":"PCH Group Ltd",
    "wof:placetype":"venue"
},
  "geometry": {"coordinates":[150.945480347,-33.8434715271],"type":"Point"}
}