{
  "type": "Feature",
  "properties": {
    "addr:full":"Fergusson Ave Blackwood SA 5051",
    "addr:postcode":"5051",
    "addr:street":"Fergusson Ave",
    "iso:country":"AU",
    "sg:address":"Fergusson Ave",
    "sg:city":"Blackwood",
    "sg:classifiers":[
        {
            "category":"Organizations",
            "subcategory":"Non-profit Organization",
            "type":"Services"
        }
    ],
    "sg:phone":"+61 8 8278 1534",
    "sg:postcode":"5051",
    "sg:province":"SA",
    "sg:tags":[
        "support",
        "disability",
        "organisation"
    ],
    "wof:name":"Riding For The Disabled Association S.A. Incorporated",
    "wof:placetype":"venue"
},
  "geometry": {"coordinates":[138.61747700000001,-35.03904],"type":"Point"}
}