{
  "type": "Feature",
  "properties": {
    "addr:full":"8 Hallstrom Pl Wetherill Park NSW 2164",
    "addr:housenumber":"8",
    "addr:postcode":"2164",
    "addr:street":"Hallstrom Pl",
    "iso:country":"AU",
    "sg:address":"8 Hallstrom Pl",
    "sg:city":"Wetherill Park",
    "sg:classifiers":[
        {
            "category":"Manufacturing",
            "subcategory":"Chemicals & Compounds",
            "type":"Manufacturing & Wholesale Goods"
        }
    ],
    "sg:phone":"+61 2 9756 5003",
    "sg:postcode":"2164",
    "sg:province":"NSW",
    "sg:tags":[
        "equipment",
        "processing"
    ],
    "wof:name":"Mixtec Philadelphia",
    "wof:placetype":"venue"
},
  "geometry": {"coordinates":[150.88508605999999,-33.8448181152],"type":"Point"}
}