{
  "type": "Feature",
  "properties": {
    "addr:full":"PO Box 86 South Fremantle WA 6162",
    "addr:postcode":"6162",
    "iso:country":"AU",
    "sg:address":"PO Box 86",
    "sg:city":"South Fremantle",
    "sg:classifiers":[
        {
            "category":"Autos & Motor Vehicles",
            "subcategory":"Boat Sales",
            "type":"Retail Goods"
        }
    ],
    "sg:phone":"+61 8 9336 3622",
    "sg:postcode":"6162",
    "sg:province":"WA",
    "sg:tags":[
        "equipment",
        "yacht"
    ],
    "wof:name":"TMQ Marine Electronics",
    "wof:placetype":"venue"
},
  "geometry": {"coordinates":[115.974152,-32.067917],"type":"Point"}
}