{
  "type": "Feature",
  "properties": {
    "iso:country":"AU",
    "sg:address":"Shop 4/ 17 The Esplanade",
    "sg:city":"Cowes",
    "sg:classifiers":[
        {
            "category":"Cafe",
            "type":"Food & Drink"
        }
    ],
    "sg:phone":"+61 3 5952 2560",
    "sg:postcode":"3922",
    "sg:province":"VIC",
    "wof:name":"Madcowes Cafe & Food Store",
    "wof:placetype":"venue"
},
  "geometry": {"coordinates":[145.237747192,-38.4481925964],"type":"Point"}
}