{
  "type": "Feature",
  "properties": {
    "addr:full":"PO Box 188 Cooranbong NSW 2265",
    "addr:postcode":"2265",
    "iso:country":"AU",
    "sg:address":"PO Box 188",
    "sg:city":"Cooranbong",
    "sg:classifiers":[
        {
            "category":"Organizations",
            "subcategory":"Non-profit Organization",
            "type":"Services"
        }
    ],
    "sg:phone":"+61 2 4977 3330",
    "sg:postcode":"2265",
    "sg:province":"NSW",
    "sg:tags":[
        "support",
        "disability",
        "organisation"
    ],
    "wof:name":"MS Society Central Coast / New England",
    "wof:placetype":"venue"
},
  "geometry": {"coordinates":[151.46762100000001,-33.06699],"type":"Point"}
}