{
  "type": "Feature",
  "properties": {
    "addr:full":"PO Box 848 Cooma NSW 2630",
    "addr:postcode":"2630",
    "iso:country":"AU",
    "sg:address":"PO Box 848",
    "sg:city":"Cooma",
    "sg:classifiers":[
        {
            "category":"Shopping",
            "subcategory":"Hobbies, Toys, & Games",
            "type":"Retail Goods"
        }
    ],
    "sg:phone":"+61 2 6452 2804",
    "sg:postcode":"2630",
    "sg:province":"NSW",
    "sg:tags":[
        "stamp"
    ],
    "wof:name":"KJB Stamp Sales",
    "wof:placetype":"venue"
},
  "geometry": {"coordinates":[149.13154602,-36.2323493958],"type":"Point"}
}