{
  "type": "Feature",
  "properties": {
    "addr:full":"Bunning Rd Gidgegannup WA 6083",
    "addr:postcode":"6083",
    "addr:street":"Bunning Rd",
    "iso:country":"AU",
    "sg:address":"Bunning Rd",
    "sg:city":"Gidgegannup",
    "sg:classifiers":[
        {
            "category":"Education",
            "subcategory":"School",
            "type":"Public Place"
        }
    ],
    "sg:phone":"+61 8 9574 6344",
    "sg:postcode":"6083",
    "sg:province":"WA",
    "sg:tags":[
        "state",
        "except",
        "nsw"
    ],
    "wof:name":"Gidgegannup Primary",
    "wof:placetype":"venue"
},
  "geometry": {"coordinates":[116.196899414,-31.7999763489],"type":"Point"}
}