{
  "type": "Feature",
  "properties": {
    "addr:full":"45 Whiting St Artarmon NSW 2064",
    "addr:housenumber":"45",
    "addr:postcode":"2064",
    "addr:street":"Whiting St",
    "iso:country":"AU",
    "sg:address":"45 Whiting St",
    "sg:city":"Artarmon",
    "sg:classifiers":[
        {
            "category":"Autos & Motor Vehicles",
            "subcategory":"Auto Supplies",
            "type":"Retail Goods"
        }
    ],
    "sg:phone":"+61 2 9436 3980",
    "sg:postcode":"2064",
    "sg:province":"NSW",
    "sg:tags":[
        "tyre"
    ],
    "wof:name":"Marks & Wallings Tyres P/L",
    "wof:placetype":"venue"
},
  "geometry": {"coordinates":[151.18260192899999,-33.8153839111],"type":"Point"}
}