{
  "type": "Feature",
  "properties": {
    "iso:country":"AU",
    "sg:address":"20 Bourke Ave",
    "sg:city":"Yattalunga",
    "sg:classifiers":[
        {
            "category":"Personal",
            "type":"Services"
        }
    ],
    "sg:phone":"+61 2 4369 3360",
    "sg:postcode":"2251",
    "sg:province":"NSW",
    "sg:tags":[
        "dressmaker"
    ],
    "wof:name":"Sandra Taylor",
    "wof:placetype":"venue"
},
  "geometry": {"coordinates":[151.36306762699999,-33.4688682556],"type":"Point"}
}