{
  "type": "Feature",
  "properties": {
    "addr:full":"126 Moss Vale Rd Kangaroo Valley NSW 2577",
    "addr:housenumber":"126",
    "addr:postcode":"2577",
    "addr:street":"Moss Vale Rd",
    "iso:country":"AU",
    "sg:address":"126 Moss Vale Rd",
    "sg:city":"Kangaroo Valley",
    "sg:classifiers":[
        {
            "category":"Building & Trades",
            "subcategory":"Construction",
            "type":"Services"
        }
    ],
    "sg:phone":"+61 2 4465 1329",
    "sg:postcode":"2577",
    "sg:province":"NSW",
    "sg:tags":[
        "road",
        "contractor"
    ],
    "wof:name":"John Rebbeck's Kangaroo Valley Excavations",
    "wof:placetype":"venue"
},
  "geometry": {"coordinates":[150.52098083499999,-34.7270698547],"type":"Point"}
}