{
  "type": "Feature",
  "properties": {
    "iso:country":"AU",
    "sg:address":"New Farm Clinic 22 Sargent St",
    "sg:city":"New Farm",
    "sg:classifiers":[
        {
            "category":"Health Services",
            "subcategory":"Doctor",
            "type":"Services"
        }
    ],
    "sg:phone":"+61 7 3254 0639",
    "sg:postcode":"4005",
    "sg:province":"QLD",
    "sg:tags":[
        "medical",
        "practitioner"
    ],
    "wof:name":"Chau Karen Dr",
    "wof:placetype":"venue"
},
  "geometry": {"coordinates":[153.04548645,-27.4735603333],"type":"Point"}
}