{
  "type": "Feature",
  "properties": {
    "iso:country":"AU",
    "sg:address":"306 Canadian Bay Rd",
    "sg:city":"Mt Eliza",
    "sg:classifiers":[
        {
            "category":"Health Services",
            "subcategory":"Health Practitioner",
            "type":"Services"
        }
    ],
    "sg:phone":"+61 3 9787 8476",
    "sg:postcode":"3930",
    "sg:province":"VIC",
    "sg:tags":[
        "naturopath"
    ],
    "wof:name":"Michael Ellis",
    "wof:placetype":"venue"
},
  "geometry": {"coordinates":[145.100509644,-38.1981506348],"type":"Point"}
}