{
  "type": "Feature",
  "properties": {
    "iso:country":"AU",
    "sg:address":"30 Cottam Ave",
    "sg:city":"Bankstown",
    "sg:classifiers":[
        {
            "category":"Place Of Worship",
            "subcategory":"Church",
            "type":"Public Place"
        }
    ],
    "sg:phone":"+61 2 9790 2344",
    "sg:postcode":"2200",
    "sg:province":"NSW",
    "sg:tags":[
        "joinery",
        "furniture"
    ],
    "wof:name":"Claremont Joinery",
    "wof:placetype":"venue"
},
  "geometry": {"coordinates":[151.034058,-33.932083],"type":"Point"}
}