{
  "type": "Feature",
  "properties": {
    "iso:country":"AU",
    "sg:address":"16 Phillimore St",
    "sg:city":"Fremantle",
    "sg:classifiers":[
        {
            "category":"Professional",
            "subcategory":"Employment Agencies",
            "type":"Services"
        }
    ],
    "sg:phone":"+61 8 9430 6310",
    "sg:postcode":"6160",
    "sg:province":"WA",
    "sg:tags":[
        "broker",
        "custom"
    ],
    "wof:name":"Ardrossan Customs Services Pty Ltd",
    "wof:placetype":"venue"
},
  "geometry": {"coordinates":[115.743179,-32.054092],"type":"Point"}
}