{
  "type": "Feature",
  "properties": {
    "addr:full":"45 Manton St Hindmarsh SA 5007",
    "addr:housenumber":"45",
    "addr:postcode":"5007",
    "addr:street":"Manton St",
    "iso:country":"AU",
    "sg:address":"45 Manton St",
    "sg:city":"Hindmarsh",
    "sg:classifiers":[
        {
            "category":"Wholesale",
            "subcategory":"Medical Equipment & Supplies",
            "type":"Manufacturing & Wholesale Goods"
        }
    ],
    "sg:phone":"+61 8 8346 3733",
    "sg:postcode":"5007",
    "sg:province":"SA",
    "sg:tags":[
        "aid",
        "care",
        "health",
        "home"
    ],
    "wof:name":"Independent Living Care & Mobility Centre",
    "wof:placetype":"venue"
},
  "geometry": {"coordinates":[138.56883239699999,-34.9061393738],"type":"Point"}
}