{
  "type": "Feature",
  "properties": {
    "iso:country":"AU",
    "sg:address":"1200 Pittwater Rd",
    "sg:city":"Narrabeen",
    "sg:classifiers":[
        {
            "category":"Arena",
            "subcategory":"Sports Club",
            "type":"Entertainment"
        }
    ],
    "sg:phone":"+61 2 9982 2621",
    "sg:postcode":"2101",
    "sg:province":"NSW",
    "sg:tags":[
        "life",
        "surfing",
        "saving"
    ],
    "wof:name":"South Narrabeen Surf Life Saving Club",
    "wof:placetype":"venue"
},
  "geometry": {"coordinates":[151.298813,-33.722897],"type":"Point"}
}