{
  "type": "Feature",
  "properties": {
    "addr:full":"Lilla St Peppermint Grove WA 6011",
    "addr:postcode":"6011",
    "addr:street":"Lilla St",
    "iso:country":"AU",
    "sg:address":"Lilla St",
    "sg:city":"Peppermint Grove",
    "sg:classifiers":[
        {
            "category":"Cafe",
            "type":"Food & Drink"
        }
    ],
    "sg:phone":"+61 8 9383 2890",
    "sg:postcode":"6011",
    "sg:province":"WA",
    "wof:name":"Cappuccino By The River",
    "wof:placetype":"venue"
},
  "geometry": {"coordinates":[115.771759033,-32.0018501282],"type":"Point"}
}