{
  "type": "Feature",
  "properties": {
    "addr:full":"276 Norton St Leichhardt NSW 2040",
    "addr:housenumber":"276",
    "addr:postcode":"2040",
    "addr:street":"Norton St",
    "iso:country":"AU",
    "sg:address":"276 Norton St",
    "sg:city":"Leichhardt",
    "sg:classifiers":[
        {
            "category":"Retail",
            "subcategory":"Event Space",
            "type":"Services"
        }
    ],
    "sg:phone":"+61 2 9560 1674",
    "sg:postcode":"2040",
    "sg:province":"NSW",
    "sg:tags":[
        "venue",
        "reception",
        "wedding"
    ],
    "wof:name":"Villa Rosa Lounge",
    "wof:placetype":"venue"
},
  "geometry": {"coordinates":[151.15617399999999,-33.877758],"type":"Point"}
}