{
  "type": "Feature",
  "properties": {
    "iso:country":"AU",
    "sg:address":"Unit 1/ 9 Samantha Pl",
    "sg:city":"Smeaton Grange",
    "sg:classifiers":[
        {
            "category":"Retail",
            "subcategory":"Funeral Services",
            "type":"Services"
        }
    ],
    "sg:phone":"+61 2 4647 9294",
    "sg:postcode":"2567",
    "sg:province":"NSW",
    "sg:tags":[
        "director"
    ],
    "wof:name":"Sacred Funerals",
    "wof:placetype":"venue"
},
  "geometry": {"coordinates":[150.760818481,-34.0396842957],"type":"Point"}
}