{
  "type": "Feature",
  "properties": {
    "iso:country":"AU",
    "sg:address":"1 Gilders Pl",
    "sg:city":"Bayswater",
    "sg:classifiers":[
        {
            "category":"Building & Trades",
            "subcategory":"Cleaning & Sanitation",
            "type":"Services"
        }
    ],
    "sg:phone":"+61 8 9362 5968",
    "sg:postcode":"6053",
    "sg:province":"WA",
    "sg:tags":[
        "tank",
        "septic"
    ],
    "wof:name":"Bedford Waste Disposals",
    "wof:placetype":"venue"
},
  "geometry": {"coordinates":[115.906723023,-31.9104537964],"type":"Point"}
}