{
  "type": "Feature",
  "properties": {
    "addr:full":"129 Russell St Toowoomba QLD 4350",
    "addr:housenumber":"129",
    "addr:postcode":"4350",
    "addr:street":"Russell St",
    "iso:country":"AU",
    "sg:address":"129 Russell St",
    "sg:city":"Toowoomba",
    "sg:classifiers":[
        {
            "category":"Health Services",
            "subcategory":"Doctor",
            "type":"Services"
        }
    ],
    "sg:phone":"+61 7 4632 2331",
    "sg:postcode":"4350",
    "sg:province":"QLD",
    "sg:tags":[
        "medical",
        "practitioner"
    ],
    "wof:name":"Rouhead D",
    "wof:placetype":"venue"
},
  "geometry": {"coordinates":[151.94845599999999,-27.55818],"type":"Point"}
}