{
  "type": "Feature",
  "properties": {
    "iso:country":"AU",
    "sg:address":"50 Stud Rd",
    "sg:city":"Dandenong",
    "sg:classifiers":[
        {
            "category":"Health Services",
            "subcategory":"Health Practitioner",
            "type":"Services"
        }
    ],
    "sg:phone":"+61 3 9792 9899",
    "sg:postcode":"3175",
    "sg:province":"VIC",
    "sg:tags":[
        "physiotherapist"
    ],
    "wof:name":"Eden Law",
    "wof:placetype":"venue"
},
  "geometry": {"coordinates":[145.22174072300001,-37.9807815552],"type":"Point"}
}