{
  "type": "Feature",
  "properties": {
    "addr:full":"109 Gulf Point Drv North Haven SA 5018",
    "addr:housenumber":"109",
    "addr:postcode":"5018",
    "addr:street":"Gulf Point Drv",
    "iso:country":"AU",
    "sg:address":"109 Gulf Point Drv",
    "sg:city":"North Haven",
    "sg:classifiers":[
        {
            "category":"Freight",
            "type":"Transportation"
        }
    ],
    "sg:phone":"+61 8 8341 8860",
    "sg:postcode":"5018",
    "sg:province":"SA",
    "sg:tags":[
        "light",
        "carrier"
    ],
    "wof:name":"Aussiewide Economy Transport",
    "wof:placetype":"venue"
},
  "geometry": {"coordinates":[138.48373413100001,-34.7859382629],"type":"Point"}
}