{
  "type": "Feature",
  "properties": {
    "addr:full":"258 St Leonards Rd St Leonards TAS 7250",
    "addr:housenumber":"258",
    "addr:postcode":"7250",
    "addr:street":"St Leonards Rd",
    "iso:country":"AU",
    "sg:address":"258 St Leonards Rd St",
    "sg:city":"Leonards",
    "sg:classifiers":[
        {
            "category":"Wholesale",
            "subcategory":"Drugs",
            "type":"Manufacturing & Wholesale Goods"
        }
    ],
    "sg:phone":"+61 3 6339 1923",
    "sg:postcode":"7250",
    "sg:province":"TAS",
    "sg:tags":[
        "wholesaler",
        "lawn",
        "mfrs",
        "mower"
    ],
    "wof:name":"Australian Chainsaw Products",
    "wof:placetype":"venue"
},
  "geometry": {"coordinates":[147.19639587399999,-41.4536132812],"type":"Point"}
}