{
  "type": "Feature",
  "properties": {
    "iso:country":"AU",
    "sg:address":"29 Wilmot St",
    "sg:city":"West South Launceston",
    "sg:classifiers":[
        {
            "category":"Home & Garden",
            "subcategory":"Building Materials",
            "type":"Retail Goods"
        }
    ],
    "sg:phone":"+61 3 6343 7125",
    "sg:postcode":"7249",
    "sg:province":"TAS",
    "sg:tags":[
        "merchant",
        "glass",
        "glazier"
    ],
    "wof:name":"South Launceston Glass",
    "wof:placetype":"venue"
},
  "geometry": {"coordinates":[147.14039611800001,-41.4536399841],"type":"Point"}
}