{
  "type": "Feature",
  "properties": {
    "addr:full":"9 View Ave Langford WA 6147",
    "addr:housenumber":"9",
    "addr:postcode":"6147",
    "addr:street":"View Ave",
    "iso:country":"AU",
    "sg:address":"9 View Ave",
    "sg:city":"Langford",
    "sg:classifiers":[
        {
            "category":"Autos & Motor Vehicles",
            "subcategory":"Auto Supplies",
            "type":"Retail Goods"
        }
    ],
    "sg:phone":"+61 417 939 910",
    "sg:postcode":"6147",
    "sg:province":"WA",
    "sg:tags":[
        "garage",
        "equipment"
    ],
    "wof:name":"Toms Hoists",
    "wof:placetype":"venue"
},
  "geometry": {"coordinates":[115.94165,-32.035633],"type":"Point"}
}