{
  "type": "Feature",
  "properties": {
    "iso:country":"AU",
    "sg:address":"514 Highbury Rd",
    "sg:city":"Glen Waverley",
    "sg:classifiers":[
        {
            "category":"Social Services",
            "subcategory":"Child Care",
            "type":"Services"
        }
    ],
    "sg:phone":"+61 3 9802 7428",
    "sg:postcode":"3150",
    "sg:province":"VIC",
    "wof:name":"Kidzplay On Highbury",
    "wof:placetype":"venue"
},
  "geometry": {"coordinates":[145.170013428,-37.8622360229],"type":"Point"}
}