{
  "type": "Feature",
  "properties": {
    "iso:country":"AU",
    "sg:address":"Suite 205, 14 Solent Cct",
    "sg:city":"Baulkham Hills",
    "sg:classifiers":[
        {
            "category":"Professional",
            "subcategory":"Accounting & Tax Preparation",
            "type":"Services"
        }
    ],
    "sg:phone":"+61 2 9836 0011",
    "sg:postcode":"2153",
    "sg:province":"NSW",
    "sg:tags":[
        "accountant",
        "auditor"
    ],
    "wof:name":"Passaro PJ & Co Chartered Accountants",
    "wof:placetype":"venue"
},
  "geometry": {"coordinates":[150.959182739,-33.7336006165],"type":"Point"}
}