{
  "type": "Feature",
  "properties": {
    "addr:full":"8 Nolan St Mansfield VIC 3722",
    "addr:housenumber":"8",
    "addr:postcode":"3722",
    "addr:street":"Nolan St",
    "iso:country":"AU",
    "sg:address":"8 Nolan St",
    "sg:city":"Mansfield",
    "sg:classifiers":[
        {
            "category":"Retail",
            "subcategory":"Auto Repair",
            "type":"Services"
        }
    ],
    "sg:phone":"+61 3 5775 2720",
    "sg:postcode":"3722",
    "sg:province":"VIC",
    "sg:tags":[
        "repairer",
        "motor",
        "engineer"
    ],
    "wof:name":"Two & Four Wheel Motor Engineers",
    "wof:placetype":"venue"
},
  "geometry": {"coordinates":[146.090866089,-37.0516433716],"type":"Point"}
}