{
  "type": "Feature",
  "properties": {
    "addr:full":"24 Hamilton St Gisborne VIC 3437",
    "addr:housenumber":"24",
    "addr:postcode":"3437",
    "addr:street":"Hamilton St",
    "iso:country":"AU",
    "sg:address":"24 Hamilton St",
    "sg:city":"Gisborne",
    "sg:classifiers":[
        {
            "category":"Food & Beverages",
            "subcategory":"Supermarket",
            "type":"Retail Goods"
        }
    ],
    "sg:phone":"+61 3 5428 2630",
    "sg:postcode":"3437",
    "sg:province":"VIC",
    "sg:tags":[
        "grocery",
        "store"
    ],
    "wof:name":"Gisborne Foodworks Supermarket",
    "wof:placetype":"venue"
},
  "geometry": {"coordinates":[144.590698242,-37.487739563],"type":"Point"}
}