{
  "type": "Feature",
  "properties": {
    "addr:full":"10 McDonald St Clunes VIC 3370",
    "addr:housenumber":"10",
    "addr:postcode":"3370",
    "addr:street":"Mcdonald St",
    "iso:country":"AU",
    "sg:address":"10 McDonald St",
    "sg:city":"Clunes",
    "sg:classifiers":[
        {
            "category":"Autos & Motor Vehicles",
            "subcategory":"Auto Supplies",
            "type":"Retail Goods"
        }
    ],
    "sg:phone":"+61 3 5345 3793",
    "sg:postcode":"3370",
    "sg:province":"VIC",
    "sg:tags":[
        "camper-trailers",
        "caravan",
        "equipment"
    ],
    "wof:name":"Colt Caravans",
    "wof:placetype":"venue"
},
  "geometry": {"coordinates":[143.793426514,-37.2987632751],"type":"Point"}
}