{
  "type": "Feature",
  "properties": {
    "iso:country":"AU",
    "sg:address":"King St",
    "sg:city":"Clifton",
    "sg:classifiers":[
        {
            "category":"Autos & Motor Vehicles",
            "subcategory":"Fuel & Gas Station",
            "type":"Retail Goods"
        }
    ],
    "sg:phone":"+61 7 4697 3341",
    "sg:postcode":"4361",
    "sg:province":"QLD",
    "wof:name":"Bruce Hamiltons Garage",
    "wof:placetype":"venue"
},
  "geometry": {"coordinates":[151.90594482399999,-27.9301528931],"type":"Point"}
}