{
  "type": "Feature",
  "properties": {
    "addr:full":"Ipswich Rd Medical Centre 7 Waterton St Annerley QLD 4103",
    "addr:housenumber":"7",
    "addr:postcode":"4103",
    "addr:street":"Ipswich;Waterton St",
    "iso:country":"AU",
    "sg:address":"Ipswich Rd Medical Centre 7 Waterton St",
    "sg:city":"Annerley",
    "sg:classifiers":[
        {
            "category":"Health Services",
            "subcategory":"Dentist",
            "type":"Services"
        }
    ],
    "sg:phone":"+61 7 3848 7756",
    "sg:postcode":"4103",
    "sg:province":"QLD",
    "wof:name":"McKiernan Mark Dr",
    "wof:placetype":"venue"
},
  "geometry": {"coordinates":[153.03140258799999,-27.5140800476],"type":"Point"}
}