{
  "type": "Feature",
  "properties": {
    "addr:full":"119 Fairview Ave Engadine NSW 2233",
    "addr:housenumber":"119",
    "addr:postcode":"2233",
    "addr:street":"Fairview Ave",
    "iso:country":"AU",
    "sg:address":"119 Fairview Ave",
    "sg:city":"Engadine",
    "sg:classifiers":[
        {
            "category":"Professional",
            "subcategory":"Computer Services",
            "type":"Services"
        }
    ],
    "sg:phone":"+61 2 9548 1861",
    "sg:postcode":"2233",
    "sg:province":"NSW",
    "sg:tags":[
        "package",
        "software"
    ],
    "wof:name":"Applied Micros Pty Limited",
    "wof:placetype":"venue"
},
  "geometry": {"coordinates":[151.00004577600001,-34.0691452026],"type":"Point"}
}