{
  "type": "Feature",
  "properties": {
    "addr:full":"PO Box 553 Littlehampton SA 5250",
    "addr:postcode":"5250",
    "iso:country":"AU",
    "sg:address":"PO Box 553",
    "sg:city":"Littlehampton",
    "sg:classifiers":[
        {
            "category":"Professional",
            "subcategory":"Management & Consulting",
            "type":"Services"
        }
    ],
    "sg:phone":"+61 407 978 659",
    "sg:postcode":"5250",
    "sg:province":"SA",
    "sg:tags":[
        "consultant"
    ],
    "wof:name":"Wendy Lewis Business Services",
    "wof:placetype":"venue"
},
  "geometry": {"coordinates":[138.853713989,-35.0545082092],"type":"Point"}
}