{
  "type": "Feature",
  "properties": {
    "addr:full":"530 City Rd South Melbourne VIC 3205",
    "addr:housenumber":"530",
    "addr:postcode":"3205",
    "addr:street":"City Rd",
    "iso:country":"AU",
    "sg:address":"530 City Rd",
    "sg:city":"South Melbourne",
    "sg:classifiers":[
        {
            "category":"Donuts",
            "subcategory":"None",
            "type":"Food & Drink"
        }
    ],
    "sg:phone":"+61 3 9696 1717",
    "sg:postcode":"3205",
    "sg:province":"VIC",
    "sg:tags":[
        "die",
        "engraver",
        "sinker"
    ],
    "wof:name":"C G Roeszler Engraving",
    "wof:placetype":"venue"
},
  "geometry": {"coordinates":[144.95182800000001,-37.83276],"type":"Point"}
}