{
  "type": "Feature",
  "properties": {
    "iso:country":"AU",
    "sg:address":"PO Box 233",
    "sg:city":"Bakers Hill",
    "sg:classifiers":[
        {
            "category":"Banks & Credit Unions",
            "subcategory":"Bureau De Change",
            "type":"Services"
        }
    ],
    "sg:phone":"+61 8 9574 0243",
    "sg:postcode":"6562",
    "sg:province":"WA",
    "sg:tags":[
        "escort",
        "transport",
        "pilot"
    ],
    "wof:name":"SELECT-A-PILOT SERVICE",
    "wof:placetype":"venue"
},
  "geometry": {"coordinates":[116.461143,-31.74645],"type":"Point"}
}