{
  "type": "Feature",
  "properties": {
    "addr:full":"Unit 1/ 62- 66 Newton Rd Wetherill Park NSW 2164",
    "addr:housenumber":"66",
    "addr:postcode":"2164",
    "addr:street":"Newton Rd",
    "iso:country":"AU",
    "sg:address":"Unit 1/ 62- 66 Newton Rd",
    "sg:city":"Wetherill Park",
    "sg:classifiers":[
        {
            "category":"Retail",
            "subcategory":"Auto Repair",
            "type":"Services"
        }
    ],
    "sg:phone":"+61 2 9756 2699",
    "sg:postcode":"2164",
    "sg:province":"NSW",
    "sg:tags":[
        "repairer",
        "motor",
        "engineer"
    ],
    "wof:name":"Wetherill Park Automotive Services",
    "wof:placetype":"venue"
},
  "geometry": {"coordinates":[150.891479492,-33.8475418091],"type":"Point"}
}