{
  "type": "Feature",
  "properties": {
    "iso:country":"AU",
    "sg:address":"17 Bandain Ave",
    "sg:city":"Kareela",
    "sg:classifiers":[
        {
            "category":"Professional",
            "subcategory":"Printing & Photocopies",
            "type":"Services"
        }
    ],
    "sg:phone":"+61 2 9576 6606",
    "sg:postcode":"2232",
    "sg:province":"NSW",
    "sg:tags":[
        "screen",
        "printer"
    ],
    "wof:name":"Tascolour Graphics",
    "wof:placetype":"venue"
},
  "geometry": {"coordinates":[151.07893371599999,-34.0196838379],"type":"Point"}
}