{
  "type": "Feature",
  "properties": {
    "addr:full":"280a Princes Hwy Rockdale NSW 2216",
    "addr:housenumber":"280a",
    "addr:postcode":"2216",
    "addr:street":"Princes Hwy",
    "iso:country":"AU",
    "sg:address":"280a Princes Hwy",
    "sg:city":"Rockdale",
    "sg:classifiers":[
        {
            "category":"Shopping",
            "subcategory":"Party Supplies",
            "type":"Retail Goods"
        }
    ],
    "sg:phone":"+61 418 222 250",
    "sg:postcode":"2216",
    "sg:province":"NSW",
    "sg:tags":[
        "children's"
    ],
    "wof:name":"Grand Touring Slotcars",
    "wof:placetype":"venue"
},
  "geometry": {"coordinates":[151.148056,-33.95475],"type":"Point"}
}