{
  "type": "Feature",
  "properties": {
    "iso:country":"AU",
    "sg:address":"Shop 25",
    "sg:city":", Marina Pier, Holdfast Shores Glenelg",
    "sg:classifiers":[
        {
            "category":"Autos & Motor Vehicles",
            "subcategory":"Boat Sales",
            "type":"Retail Goods"
        }
    ],
    "sg:phone":"+61 8 8350 2000",
    "sg:postcode":"5045",
    "sg:province":"SA",
    "sg:tags":[
        "yacht"
    ],
    "wof:name":"Squadron Boat Sales",
    "wof:placetype":"venue"
},
  "geometry": {"coordinates":[138.519897,-34.985046],"type":"Point"}
}