{
  "type": "Feature",
  "properties": {
    "addr:full":"Shop 25 , Marina Pier, Holdfast Shores Glenelg SA 5045",
    "addr:housenumber":"shop 25",
    "addr:postcode":"5045",
    "addr:street":"Marina Pier Holdfast Shores",
    "iso:country":"AU",
    "sg:address":"Shop 25",
    "sg:city":", Marina Pier, Holdfast Shores Glenelg",
    "sg:classifiers":[
        {
            "category":"Autos & Motor Vehicles",
            "subcategory":"Boat Sales",
            "type":"Retail Goods"
        }
    ],
    "sg:phone":"+61 8 8350 2000",
    "sg:postcode":"5045",
    "sg:province":"SA",
    "sg:tags":[
        "yacht"
    ],
    "wof:name":"Squadron Boat Sales",
    "wof:placetype":"venue"
},
  "geometry": {"coordinates":[138.51989699999999,-34.985046],"type":"Point"}
}