{
  "type": "Feature",
  "properties": {
    "iso:country":"AU",
    "sg:address":"6 Seamer Rd",
    "sg:city":"Monbulk",
    "sg:classifiers":[
        {
            "category":"Building & Trades",
            "subcategory":"Plumbing",
            "type":"Services"
        }
    ],
    "sg:phone":"+61 412 575 754",
    "sg:postcode":"3793",
    "sg:province":"VIC",
    "sg:tags":[
        "plumber",
        "gasfitters"
    ],
    "wof:name":"Deacon Gary M",
    "wof:placetype":"venue"
},
  "geometry": {"coordinates":[145.42286682100001,-37.870464325],"type":"Point"}
}