{
  "type": "Feature",
  "properties": {
    "iso:country":"AU",
    "sg:address":"Victoria St",
    "sg:city":"Taree",
    "sg:classifiers":[
        {
            "category":"Retail",
            "subcategory":"Auto Repair",
            "type":"Services"
        }
    ],
    "sg:phone":"+61 414 490 578",
    "sg:postcode":"2430",
    "sg:province":"NSW",
    "sg:tags":[
        "beater",
        "painter",
        "panel"
    ],
    "wof:name":"Dek-A-Dent Mid Coast",
    "wof:placetype":"venue"
},
  "geometry": {"coordinates":[152.461502,-31.913134],"type":"Point"}
}