{
  "type": "Feature",
  "properties": {
    "addr:full":"PO Box 998 Baulkham Hills NSW 1755",
    "addr:postcode":"1755",
    "iso:country":"AU",
    "sg:address":"PO Box 998",
    "sg:city":"Baulkham Hills",
    "sg:classifiers":[
        {
            "category":"Banks & Credit Unions",
            "subcategory":"Financial Services",
            "type":"Services"
        }
    ],
    "sg:phone":"+61 2 9620 5559",
    "sg:postcode":"1755",
    "sg:province":"NSW",
    "sg:tags":[
        "loan",
        "finance",
        "mortgage"
    ],
    "wof:name":"Southern Cross Professional Investments Pty Ltd",
    "wof:placetype":"venue"
},
  "geometry": {"coordinates":[150.99288899999999,-33.758598],"type":"Point"}
}