{
  "type": "Feature",
  "properties": {
    "addr:full":"PO Box 1514 Melbourne VIC 8060",
    "addr:postcode":"8060",
    "iso:country":"AU",
    "sg:address":"PO Box 1514",
    "sg:city":"Melbourne",
    "sg:classifiers":[
        {
            "category":"Professional",
            "subcategory":"Detective & Security Services",
            "type":"Services"
        }
    ],
    "sg:phone":"+61 3 8742 3155",
    "sg:postcode":"8060",
    "sg:province":"VIC",
    "sg:tags":[
        "guard",
        "patrol"
    ],
    "wof:name":"Victorian Protection Security Services & Investigations Pty Ltd",
    "wof:placetype":"venue"
},
  "geometry": {"coordinates":[144.963165283,-37.814250946],"type":"Point"}
}