{
  "type": "Feature",
  "properties": {
    "addr:full":"1 Yarruk St Yokine WA 6060",
    "addr:housenumber":"1",
    "addr:postcode":"6060",
    "addr:street":"Yarruk St",
    "iso:country":"AU",
    "sg:address":"1 Yarruk St",
    "sg:city":"Yokine",
    "sg:classifiers":[
        {
            "category":"Professional",
            "subcategory":"Art Services",
            "type":"Services"
        }
    ],
    "sg:phone":"+61 8 9443 3297",
    "sg:postcode":"6060",
    "sg:province":"WA",
    "sg:tags":[
        "decorator",
        "painter"
    ],
    "wof:name":"McErlaine J & B",
    "wof:placetype":"venue"
},
  "geometry": {"coordinates":[115.84697723399999,-31.9072189331],"type":"Point"}
}