{
  "type": "Feature",
  "properties": {
    "addr:full":"Lot 118 Allerton Rd Albany WA 6330",
    "addr:postcode":"6330",
    "addr:street":"Allerton Rd",
    "iso:country":"AU",
    "sg:address":"Lot 118 Allerton Rd",
    "sg:city":"Albany",
    "sg:classifiers":[
        {
            "category":"Building & Trades",
            "subcategory":"Construction",
            "type":"Services"
        }
    ],
    "sg:phone":"+61 8 9842 5414",
    "sg:postcode":"6330",
    "sg:province":"WA",
    "sg:tags":[
        "scaffolding"
    ],
    "wof:name":"Albany Scaffold Hire",
    "wof:placetype":"venue"
},
  "geometry": {"coordinates":[117.84277343799999,-35.0211296082],"type":"Point"}
}