{
  "type": "Feature",
  "properties": {
    "addr:full":"PO Box 2954 Fitzroy VIC 3065",
    "addr:postcode":"3065",
    "iso:country":"AU",
    "sg:address":"PO Box 2954",
    "sg:city":"Fitzroy",
    "sg:classifiers":[
        {
            "category":"Travel",
            "subcategory":"Travel Agent",
            "type":"Entertainment"
        }
    ],
    "sg:phone":"+61 1300 737 747",
    "sg:postcode":"3065",
    "sg:province":"VIC",
    "sg:tags":[
        "tour",
        "holiday",
        "adventure"
    ],
    "wof:name":"Spirit Adventures",
    "wof:placetype":"venue"
},
  "geometry": {"coordinates":[144.97915649399999,-37.8009185791],"type":"Point"}
}