{
  "type": "Feature",
  "properties": {
    "addr:full":"Lot 24 Colston Rd Winton QLD 4735",
    "addr:postcode":"4735",
    "addr:street":"Colston Rd",
    "iso:country":"AU",
    "sg:address":"Lot 24 Colston Rd",
    "sg:city":"Winton",
    "sg:classifiers":[
        {
            "category":"Professional",
            "subcategory":"Business Services",
            "type":"Services"
        }
    ],
    "sg:phone":"+61 7 4657 1332",
    "sg:postcode":"4735",
    "sg:province":"QLD",
    "sg:tags":[
        "livestock",
        "transport"
    ],
    "wof:name":"Road Trains Of Australia Pty Ltd",
    "wof:placetype":"venue"
},
  "geometry": {"coordinates":[143.040527,-22.391609],"type":"Point"}
}