{
  "type": "Feature",
  "properties": {
    "addr:full":"Suite 8/ 113 Collins Rd Willetton WA 6155",
    "addr:housenumber":"/ 113",
    "addr:postcode":"6155",
    "addr:street":"Collins Rd",
    "iso:country":"AU",
    "sg:address":"Suite 8/ 113 Collins Rd",
    "sg:city":"Willetton",
    "sg:classifiers":[
        {
            "category":"Real Estate",
            "subcategory":"Real Estate Agent",
            "type":"Services"
        }
    ],
    "sg:phone":"+61 8 9457 9955",
    "sg:postcode":"6155",
    "sg:province":"WA",
    "wof:name":"L J Hooker",
    "wof:placetype":"venue"
},
  "geometry": {"coordinates":[115.89475299999999,-32.055218],"type":"Point"}
}