{
  "type": "Feature",
  "properties": {
    "iso:country":"AU",
    "sg:address":"19 Chifley Rd",
    "sg:city":"Morisset Park",
    "sg:classifiers":[
        {
            "category":"Personal",
            "subcategory":"Massage",
            "type":"Services"
        }
    ],
    "sg:phone":"+61 2 4973 1641",
    "sg:postcode":"2264",
    "sg:province":"NSW",
    "sg:tags":[
        "therapy"
    ],
    "wof:name":"Brooks Gaynor",
    "wof:placetype":"venue"
},
  "geometry": {"coordinates":[151.531036,-33.119213],"type":"Point"}
}