{
  "type": "Feature",
  "properties": {
    "iso:country":"AU",
    "sg:address":"7a Howey Pl",
    "sg:city":"Melbourne",
    "sg:classifiers":[
        {
            "category":"Shopping",
            "subcategory":"Clothing, Apparel, & Fashions",
            "type":"Retail Goods"
        }
    ],
    "sg:phone":"+61 3 9650 1374",
    "sg:postcode":"3000",
    "sg:province":"VIC",
    "sg:tags":[
        "lady",
        "wear"
    ],
    "wof:name":"Rich Clothing",
    "wof:placetype":"venue"
},
  "geometry": {"coordinates":[144.96536254899999,-37.8148384094],"type":"Point"}
}