{
  "type": "Feature",
  "properties": {
    "iso:country":"AU",
    "sg:address":"1 Fairway Drv",
    "sg:city":"Clear Island Waters",
    "sg:classifiers":[
        {
            "category":"Sports & Exercise",
            "subcategory":"Sports Center",
            "type":"Entertainment"
        }
    ],
    "sg:phone":"+61 7 5526 1504",
    "sg:postcode":"4226",
    "sg:province":"QLD",
    "sg:tags":[
        "coach",
        "tennis"
    ],
    "wof:name":"International Tennis Academy Gold Coast Fairways Centre",
    "wof:placetype":"venue"
},
  "geometry": {"coordinates":[153.40257263199999,-28.0343055725],"type":"Point"}
}