{
  "type": "Feature",
  "properties": {
    "addr:full":"15 Craithie Ave Park Orchards VIC 3114",
    "addr:housenumber":"15",
    "addr:postcode":"3114",
    "addr:street":"Craithie Ave",
    "iso:country":"AU",
    "sg:address":"15 Craithie Ave",
    "sg:city":"Park Orchards",
    "sg:classifiers":[
        {
            "category":"Building & Trades",
            "subcategory":"Landscaping Services",
            "type":"Services"
        }
    ],
    "sg:phone":"+61 411 814 420",
    "sg:postcode":"3114",
    "sg:province":"VIC",
    "sg:tags":[
        "designer",
        "landscape",
        "contractor"
    ],
    "wof:name":"Glennvern Landscapes & Gardens",
    "wof:placetype":"venue"
},
  "geometry": {"coordinates":[145.226165772,-37.7808036804],"type":"Point"}
}