{
  "type": "Feature",
  "properties": {
    "addr:full":"Shop 6, Dohles Rocks Rd Murrumba Downs QLD 4503",
    "addr:housenumber":"shop 6",
    "addr:postcode":"4503",
    "addr:street":"Dohles Rocks Rd",
    "iso:country":"AU",
    "sg:address":"Shop 6, Dohles Rocks Rd",
    "sg:city":"Murrumba Downs",
    "sg:classifiers":[
        {
            "category":"Food & Beverages",
            "subcategory":"Bakery",
            "type":"Retail Goods"
        }
    ],
    "sg:phone":"+61 7 3204 4273",
    "sg:postcode":"4503",
    "sg:province":"QLD",
    "sg:tags":[
        "baker"
    ],
    "wof:name":"CK's Bakery",
    "wof:placetype":"venue"
},
  "geometry": {"coordinates":[153.01499939000001,-27.2723026276],"type":"Point"}
}