{
  "type": "Feature",
  "properties": {
    "addr:full":"2 Brice Ave Mooroolbark VIC 3138",
    "addr:housenumber":"2",
    "addr:postcode":"3138",
    "addr:street":"Brice Ave",
    "iso:country":"AU",
    "sg:address":"2 Brice Ave",
    "sg:city":"Mooroolbark",
    "sg:classifiers":[
        {
            "category":"Travel",
            "subcategory":"Travel Agent",
            "type":"Entertainment"
        }
    ],
    "sg:phone":"+61 3 9727 3343",
    "sg:postcode":"3138",
    "sg:province":"VIC",
    "sg:tags":[
        "consultant"
    ],
    "wof:name":"Chris Dougherty Peregrine Bird Tours",
    "wof:placetype":"venue"
},
  "geometry": {"coordinates":[145.31121826200001,-37.7853050232],"type":"Point"}
}