{
  "type": "Feature",
  "properties": {
    "addr:full":"3 Wavell St Bentleigh VIC 3204",
    "addr:housenumber":"3",
    "addr:postcode":"3204",
    "addr:street":"Wavell St",
    "iso:country":"AU",
    "sg:address":"3 Wavell St",
    "sg:city":"Bentleigh",
    "sg:classifiers":[
        {
            "category":"Home & Garden",
            "subcategory":"Carpets & Floor Coverings",
            "type":"Retail Goods"
        }
    ],
    "sg:phone":"+61 415 535 838",
    "sg:postcode":"3204",
    "sg:province":"VIC",
    "sg:tags":[
        "tile",
        "wall",
        "layer"
    ],
    "wof:name":"J & L Tiling",
    "wof:placetype":"venue"
},
  "geometry": {"coordinates":[145.04284699999999,-37.914295],"type":"Point"}
}