{
  "type": "Feature",
  "properties": {
    "addr:full":"19 Clifton St Maylands SA 5069",
    "addr:housenumber":"19",
    "addr:postcode":"5069",
    "addr:street":"Clifton St",
    "iso:country":"AU",
    "sg:address":"19 Clifton St",
    "sg:city":"Maylands",
    "sg:classifiers":[
        {
            "category":"Utilities",
            "subcategory":"Refuse",
            "type":"Services"
        }
    ],
    "sg:phone":"+61 8 8431 1355",
    "sg:postcode":"5069",
    "sg:province":"SA",
    "sg:tags":[
        "remover",
        "rubbish"
    ],
    "wof:name":"De Cicco Giorgio",
    "wof:placetype":"venue"
},
  "geometry": {"coordinates":[138.638916016,-34.9100570679],"type":"Point"}
}