{
  "type": "Feature",
  "properties": {
    "addr:full":"16 Thompson St Abbotsford VIC 3067",
    "addr:housenumber":"16",
    "addr:postcode":"3067",
    "addr:street":"Thompson St",
    "iso:country":"AU",
    "sg:address":"16 Thompson St",
    "sg:city":"Abbotsford",
    "sg:classifiers":[
        {
            "category":"Retail",
            "subcategory":"Auto Repair",
            "type":"Services"
        }
    ],
    "sg:phone":"+61 3 9428 8167",
    "sg:postcode":"3067",
    "sg:province":"VIC",
    "sg:tags":[
        "beater",
        "painter",
        "panel"
    ],
    "wof:name":"Abbotsford Body Repairs Pty Ltd",
    "wof:placetype":"venue"
},
  "geometry": {"coordinates":[145.00352477999999,-37.8098983765],"type":"Point"}
}