{
  "type": "Feature",
  "properties": {
    "iso:country":"AU",
    "sg:address":"30 Clements Ave",
    "sg:city":"Bankstown",
    "sg:classifiers":[
        {
            "category":"Wholesale",
            "subcategory":"Hardware",
            "type":"Manufacturing & Wholesale Goods"
        }
    ],
    "sg:phone":"+61 2 9708 0200",
    "sg:postcode":"2200",
    "sg:province":"NSW",
    "wof:name":"Economy Distributor",
    "wof:placetype":"venue"
},
  "geometry": {"coordinates":[151.032959,-33.933411],"type":"Point"}
}