{
  "type": "Feature",
  "properties": {
    "addr:full":"30 Clements Ave Bankstown NSW 2200",
    "addr:housenumber":"30",
    "addr:postcode":"2200",
    "addr:street":"Clements Ave",
    "iso:country":"AU",
    "sg:address":"30 Clements Ave",
    "sg:city":"Bankstown",
    "sg:classifiers":[
        {
            "category":"Wholesale",
            "subcategory":"Hardware",
            "type":"Manufacturing & Wholesale Goods"
        }
    ],
    "sg:phone":"+61 2 9708 0200",
    "sg:postcode":"2200",
    "sg:province":"NSW",
    "wof:name":"Economy Distributor",
    "wof:placetype":"venue"
},
  "geometry": {"coordinates":[151.03295900000001,-33.933411],"type":"Point"}
}