{
  "type": "Feature",
  "properties": {
    "iso:country":"AU",
    "sg:address":"54 Hughes St",
    "sg:city":"Cabramatta",
    "sg:classifiers":[
        {
            "category":"Health Services",
            "subcategory":"Doctor",
            "type":"Services"
        }
    ],
    "sg:phone":"+61 2 9724 7177",
    "sg:postcode":"2166",
    "sg:province":"NSW",
    "sg:tags":[
        "medical",
        "practitioner"
    ],
    "wof:name":"Chau-Vo James Dr",
    "wof:placetype":"venue"
},
  "geometry": {"coordinates":[150.93206787099999,-33.8928909302],"type":"Point"}
}