{
  "type": "Feature",
  "properties": {
    "iso:country":"AU",
    "sg:address":"Unit F, 140 Old Pittwater Rd",
    "sg:city":"Brookvale",
    "sg:classifiers":[
        {
            "category":"Professional",
            "subcategory":"Advertising",
            "type":"Services"
        }
    ],
    "sg:phone":"+61 2 9905 9333",
    "sg:postcode":"2100",
    "sg:province":"NSW",
    "sg:tags":[
        "balloon",
        "novelty"
    ],
    "wof:name":"Qualatex Balloon Pty Ltd",
    "wof:placetype":"venue"
},
  "geometry": {"coordinates":[151.262405395,-33.7678451538],"type":"Point"}
}