{
  "type": "Feature",
  "properties": {
    "iso:country":"AU",
    "sg:address":"69 King Rd",
    "sg:city":"Wilberforce",
    "sg:classifiers":[
        {
            "category":"Building & Trades",
            "subcategory":"Construction",
            "type":"Services"
        }
    ],
    "sg:phone":"+61 2 4575 1843",
    "sg:postcode":"2756",
    "sg:province":"NSW",
    "sg:tags":[
        "earth",
        "excavating",
        "moving",
        "contractor"
    ],
    "wof:name":"J & L McCartney Rock Sawing & Excavations Pty Ltd",
    "wof:placetype":"venue"
},
  "geometry": {"coordinates":[150.84454345699999,-33.5593223572],"type":"Point"}
}