{
  "type": "Feature",
  "properties": {
    "iso:country":"AU",
    "sg:address":"906 Stanley St East",
    "sg:city":"Woolloongabba",
    "sg:classifiers":[
        {
            "category":"Shopping",
            "subcategory":"Bridal",
            "type":"Retail Goods"
        }
    ],
    "sg:phone":"+61 7 3391 0200",
    "sg:postcode":"4102",
    "sg:province":"QLD",
    "sg:tags":[
        "hire",
        "wear"
    ],
    "wof:name":"BellaDonna Bridal",
    "wof:placetype":"venue"
},
  "geometry": {"coordinates":[153.041412353,-27.4872131348],"type":"Point"}
}