{
  "type": "Feature",
  "properties": {
    "addr:full":"Suite 32/ 141 Grey St East Melbourne VIC 3002",
    "addr:housenumber":"32 / 141",
    "addr:postcode":"3002",
    "addr:street":"Grey St",
    "iso:country":"AU",
    "sg:address":"Suite 32/ 141 Grey St",
    "sg:city":"East Melbourne",
    "sg:classifiers":[
        {
            "category":"Health Services",
            "subcategory":"Doctor",
            "type":"Services"
        }
    ],
    "sg:phone":"+61 3 9419 5339",
    "sg:postcode":"3002",
    "sg:province":"VIC",
    "sg:tags":[
        "medical",
        "practitioner"
    ],
    "wof:name":"Williams M John Dr",
    "wof:placetype":"venue"
},
  "geometry": {"coordinates":[144.98423767099999,-37.8118057251],"type":"Point"}
}