{
  "type": "Feature",
  "properties": {
    "addr:full":"Shed 6/ 11 Cordwell Rd Yandina QLD 4561",
    "addr:housenumber":"6 / 11",
    "addr:postcode":"4561",
    "addr:street":"Cordwell Rd",
    "iso:country":"AU",
    "sg:address":"Shed 6/ 11 Cordwell Rd",
    "sg:city":"Yandina",
    "sg:classifiers":[
        {
            "category":"Food & Beverages",
            "subcategory":"Fruits & Vegetables",
            "type":"Retail Goods"
        }
    ],
    "sg:phone":"+61 7 5446 8949",
    "sg:postcode":"4561",
    "sg:province":"QLD",
    "sg:tags":[
        "wholesale"
    ],
    "wof:name":"Natoli Brothers",
    "wof:placetype":"venue"
},
  "geometry": {"coordinates":[152.95648193400001,-26.5680751801],"type":"Point"}
}