{
  "type": "Feature",
  "properties": {
    "addr:full":"PO Box 1659 Subiaco WA 6008",
    "addr:postcode":"6008",
    "iso:country":"AU",
    "sg:address":"PO Box 1659",
    "sg:city":"Subiaco",
    "sg:classifiers":[
        {
            "category":"Government",
            "subcategory":"Customs House",
            "type":"Public Place"
        }
    ],
    "sg:phone":"+61 8 9486 1866",
    "sg:postcode":"6008",
    "sg:province":"WA",
    "sg:tags":[
        "title",
        "management",
        "stratum"
    ],
    "wof:name":"Bellcourt Strata Management Pty Ltd",
    "wof:placetype":"venue"
},
  "geometry": {"coordinates":[115.824012756,-31.9468002319],"type":"Point"}
}