{
  "type": "Feature",
  "properties": {
    "addr:full":"5 Henry Lawson Drv Villawood NSW 2163",
    "addr:housenumber":"5",
    "addr:postcode":"2163",
    "addr:street":"Henry Lawson Drv",
    "iso:country":"AU",
    "sg:address":"5 Henry Lawson Drv",
    "sg:city":"Villawood",
    "sg:classifiers":[
        {
            "category":"Building & Trades",
            "subcategory":"Construction",
            "type":"Services"
        }
    ],
    "sg:phone":"+61 408 758 836",
    "sg:postcode":"2163",
    "sg:province":"NSW",
    "sg:tags":[
        "welding"
    ],
    "wof:name":"DG & Sons Welding Pty. Ltd.",
    "wof:placetype":"venue"
},
  "geometry": {"coordinates":[150.971755981,-33.8910255432],"type":"Point"}
}