{
  "type": "Feature",
  "properties": {
    "iso:country":"AU",
    "sg:address":"Suite 3 47 Nerang St",
    "sg:city":"Southport",
    "sg:classifiers":[
        {
            "category":"Professional",
            "subcategory":"Computer Services",
            "type":"Services"
        }
    ],
    "sg:phone":"+61 7 5591 5766",
    "sg:postcode":"4215",
    "sg:province":"QLD",
    "sg:tags":[
        "training"
    ],
    "wof:name":"Gold Coast Seniors On The Net",
    "wof:placetype":"venue"
},
  "geometry": {"coordinates":[153.41325378400001,-27.9678401947],"type":"Point"}
}