{
  "type": "Feature",
  "properties": {
    "addr:full":"96 Marquis St Gunnedah NSW 2380",
    "addr:housenumber":"96",
    "addr:postcode":"2380",
    "addr:street":"Marquis St",
    "iso:country":"AU",
    "sg:address":"96 Marquis St",
    "sg:city":"Gunnedah",
    "sg:classifiers":[
        {
            "category":"Health Services",
            "subcategory":"Doctor",
            "type":"Services"
        }
    ],
    "sg:phone":"+61 2 6742 4268",
    "sg:postcode":"2380",
    "sg:province":"NSW",
    "sg:tags":[
        "podiatrist"
    ],
    "wof:name":"Crawford P J",
    "wof:placetype":"venue"
},
  "geometry": {"coordinates":[150.25291442899999,-30.9779415131],"type":"Point"}
}