{
  "type": "Feature",
  "properties": {
    "addr:full":"41 Miles St Mulgrave VIC 3170",
    "addr:housenumber":"41",
    "addr:postcode":"3170",
    "addr:street":"Miles St",
    "iso:country":"AU",
    "sg:address":"41 Miles St",
    "sg:city":"Mulgrave",
    "sg:classifiers":[
        {
            "category":"Retail",
            "subcategory":"Laundry & Dry Cleaning",
            "type":"Services"
        }
    ],
    "sg:phone":"+61 3 9561 6977",
    "sg:postcode":"3170",
    "sg:province":"VIC",
    "wof:name":"Enhance Systems",
    "wof:placetype":"venue"
},
  "geometry": {"coordinates":[145.156539917,-37.9237136841],"type":"Point"}
}