{
  "type": "Feature",
  "properties": {
    "addr:full":"102 William St Rockhampton QLD 4700",
    "addr:housenumber":"102",
    "addr:postcode":"4700",
    "addr:street":"William St",
    "iso:country":"AU",
    "sg:address":"102 William St",
    "sg:city":"Rockhampton",
    "sg:classifiers":[
        {
            "category":"Wholesale",
            "subcategory":"Farm Supplies",
            "type":"Manufacturing & Wholesale Goods"
        }
    ],
    "sg:phone":"+61 7 4927 6260",
    "sg:postcode":"4700",
    "sg:province":"QLD",
    "sg:tags":[
        "feed",
        "supplement",
        "stock"
    ],
    "wof:name":"Healthy Horses",
    "wof:placetype":"venue"
},
  "geometry": {"coordinates":[150.508346558,-23.3837490082],"type":"Point"}
}