{
  "type": "Feature",
  "properties": {
    "iso:country":"AU",
    "sg:address":"Suite 11a/ 287 Military Rd",
    "sg:city":"Cremorne",
    "sg:classifiers":[
        {
            "category":"Banks & Credit Unions",
            "subcategory":"Bank",
            "type":"Services"
        }
    ],
    "sg:phone":"+61 2 9953 3979",
    "sg:postcode":"2090",
    "sg:province":"NSW",
    "sg:tags":[
        "broker",
        "mortgage"
    ],
    "wof:name":"Aspley Jandera Mortgages",
    "wof:placetype":"venue"
},
  "geometry": {"coordinates":[151.229934692,-33.8284072876],"type":"Point"}
}