{
  "type": "Feature",
  "properties": {
    "iso:country":"AU",
    "sg:address":"34 Ryley St",
    "sg:city":"Wangaratta",
    "sg:classifiers":[
        {
            "category":"Shopping",
            "subcategory":"Bicycles & Sporting Goods",
            "type":"Retail Goods"
        }
    ],
    "sg:phone":"+61 1800 333 383",
    "sg:postcode":"3677",
    "sg:province":"VIC",
    "sg:tags":[
        "chemical",
        "equipment",
        "pool",
        "swimming"
    ],
    "wof:name":"Blue Wave Pools & Spas",
    "wof:placetype":"venue"
},
  "geometry": {"coordinates":[146.31942749000001,-36.3587341309],"type":"Point"}
}