{
  "type": "Feature",
  "properties": {
    "addr:full":"3 Loudon Rd Port Augusta SA 5700",
    "addr:housenumber":"3",
    "addr:postcode":"5700",
    "addr:street":"Loudon Rd",
    "iso:country":"AU",
    "sg:address":"3 Loudon Rd",
    "sg:city":"Port Augusta",
    "sg:classifiers":[
        {
            "category":"Travel",
            "subcategory":"Hotels & Motels",
            "type":"Entertainment"
        }
    ],
    "sg:phone":"+61 8 8642 2488",
    "sg:postcode":"5700",
    "sg:province":"SA",
    "wof:name":"Comfort Inn Augusta Westside",
    "wof:placetype":"venue"
},
  "geometry": {"coordinates":[137.758499145,-32.4851036072],"type":"Point"}
}