{
  "type": "Feature",
  "properties": {
    "addr:full":"56 Christian Rd Murray Bridge SA 5253",
    "addr:housenumber":"56",
    "addr:postcode":"5253",
    "addr:street":"Christian Rd",
    "iso:country":"AU",
    "sg:address":"56 Christian Rd",
    "sg:city":"Murray Bridge",
    "sg:classifiers":[
        {
            "category":"Utilities",
            "subcategory":"Water",
            "type":"Services"
        }
    ],
    "sg:phone":"+61 419 814 138",
    "sg:postcode":"5253",
    "sg:province":"SA",
    "sg:tags":[
        "hot",
        "system"
    ],
    "wof:name":"Hein Plumbing Pty Ltd",
    "wof:placetype":"venue"
},
  "geometry": {"coordinates":[139.25782775900001,-35.1323547363],"type":"Point"}
}