{
  "type": "Feature",
  "properties": {
    "addr:full":"120 Carronvale Rd Mooroolbark VIC 3138",
    "addr:housenumber":"120",
    "addr:postcode":"3138",
    "addr:street":"Carronvale Rd",
    "iso:country":"AU",
    "sg:address":"120 Carronvale Rd",
    "sg:city":"Mooroolbark",
    "sg:classifiers":[
        {
            "category":"Banks & Credit Unions",
            "subcategory":"Investment Brokerage",
            "type":"Services"
        }
    ],
    "sg:phone":"+61 3 9727 1643",
    "sg:postcode":"3138",
    "sg:province":"VIC",
    "sg:tags":[
        "paint",
        "supply",
        "removal"
    ],
    "wof:name":"Greenwood Refinishing",
    "wof:placetype":"venue"
},
  "geometry": {"coordinates":[145.33326721200001,-37.7763977051],"type":"Point"}
}