{
  "type": "Feature",
  "properties": {
    "addr:full":"Mitala St Newport NSW 2106",
    "addr:postcode":"2106",
    "addr:street":"Mitala St",
    "iso:country":"AU",
    "sg:address":"Mitala St",
    "sg:city":"Newport",
    "sg:classifiers":[
        {
            "category":"Train Station",
            "subcategory":"Rail",
            "type":"Transportation"
        }
    ],
    "sg:phone":"+61 2 9997 2616",
    "sg:postcode":"2106",
    "sg:province":"NSW",
    "sg:tags":[
        "marine",
        "engineer"
    ],
    "wof:name":"All Inboard & Outboard Services",
    "wof:placetype":"venue"
},
  "geometry": {"coordinates":[151.30549621599999,-33.6550445557],"type":"Point"}
}