{
  "type": "Feature",
  "properties": {
    "iso:country":"AU",
    "sg:address":"5 Harewood Pl",
    "sg:city":"Warriewood",
    "sg:classifiers":[
        {
            "category":"Shopping",
            "subcategory":"Clothing, Apparel, & Fashions",
            "type":"Retail Goods"
        }
    ],
    "sg:phone":"+61 2 9999 3048",
    "sg:postcode":"2102",
    "sg:province":"NSW",
    "sg:tags":[
        "accessory"
    ],
    "wof:name":"Joaden Pty Ltd",
    "wof:placetype":"venue"
},
  "geometry": {"coordinates":[151.30569499999999,-33.693138],"type":"Point"}
}