{
  "type": "Feature",
  "properties": {
    "addr:full":"187 Morgan St Wagga Wagga NSW 2650",
    "addr:housenumber":"187",
    "addr:postcode":"2650",
    "addr:street":"Morgan St",
    "iso:country":"AU",
    "sg:address":"187 Morgan St",
    "sg:city":"Wagga Wagga",
    "sg:classifiers":[
        {
            "category":"Utilities",
            "subcategory":"Refuse",
            "type":"Services"
        }
    ],
    "sg:phone":"+61 2 6921 6390",
    "sg:postcode":"2650",
    "sg:province":"NSW",
    "sg:tags":[
        "boiler"
    ],
    "wof:name":"Martin & Wheeler Pty Ltd",
    "wof:placetype":"venue"
},
  "geometry": {"coordinates":[147.359909058,-35.1146316528],"type":"Point"}
}