{
  "type": "Feature",
  "properties": {
    "iso:country":"AU",
    "sg:address":"PO Box 280",
    "sg:city":"South Perth",
    "sg:classifiers":[
        {
            "category":"Arena",
            "subcategory":"Indoor Arena",
            "type":"Entertainment"
        }
    ],
    "sg:phone":"+61 8 9310 3689",
    "sg:postcode":"6151",
    "sg:province":"WA",
    "sg:tags":[
        "modelmakers"
    ],
    "wof:name":"Model Makers (W.A.)",
    "wof:placetype":"venue"
},
  "geometry": {"coordinates":[115.870239,-31.98105],"type":"Point"}
}