{
  "type": "Feature",
  "properties": {
    "addr:full":"36 Sweyn St Balwyn North VIC 3104",
    "addr:housenumber":"36",
    "addr:postcode":"3104",
    "addr:street":"Sweyn St",
    "iso:country":"AU",
    "sg:address":"36 Sweyn St",
    "sg:city":"Balwyn North",
    "sg:classifiers":[
        {
            "category":"Education",
            "subcategory":"School",
            "type":"Public Place"
        }
    ],
    "sg:phone":"+61 3 9857 6394",
    "sg:postcode":"3104",
    "sg:province":"VIC",
    "sg:tags":[
        "co-educational"
    ],
    "wof:name":"St Bridget's Primary Greythorn",
    "wof:placetype":"venue"
},
  "geometry": {"coordinates":[145.102416992,-37.7960472107],"type":"Point"}
}