{
  "type": "Feature",
  "properties": {
    "addr:full":"109 Molesworth St Lismore NSW 2480",
    "addr:housenumber":"109",
    "addr:postcode":"2480",
    "addr:street":"Molesworth St",
    "iso:country":"AU",
    "sg:address":"109 Molesworth St",
    "sg:city":"Lismore",
    "sg:classifiers":[
        {
            "category":"Insurance",
            "subcategory":"Hazard Insurance",
            "type":"Services"
        }
    ],
    "sg:phone":"+61 2 6621 8633",
    "sg:postcode":"2480",
    "sg:province":"NSW",
    "sg:tags":[
        "fire",
        "accident",
        "marine"
    ],
    "wof:name":"Wesfarmers Federation Insurance",
    "wof:placetype":"venue"
},
  "geometry": {"coordinates":[153.27670288100001,-28.8077373505],"type":"Point"}
}