{
  "type": "Feature",
  "properties": {
    "addr:full":"30 Smith St Kentlyn NSW 2560",
    "addr:housenumber":"30",
    "addr:postcode":"2560",
    "addr:street":"Smith St",
    "iso:country":"AU",
    "sg:address":"30 Smith St",
    "sg:city":"Kentlyn",
    "sg:classifiers":[
        {
            "category":"Travel",
            "subcategory":"Hostel",
            "type":"Entertainment"
        }
    ],
    "sg:phone":"+61 2 4625 1907",
    "sg:postcode":"2560",
    "sg:province":"NSW",
    "sg:tags":[
        "home"
    ],
    "wof:name":"Fraternity of the Holy Cross Russian Orthodox Home for the Aged",
    "wof:placetype":"venue"
},
  "geometry": {"coordinates":[150.86328125,-34.0726928711],"type":"Point"}
}