{
  "type": "Feature",
  "properties": {
    "addr:full":"376 King St Newcastle NSW 2300",
    "addr:housenumber":"376",
    "addr:postcode":"2300",
    "addr:street":"King St",
    "iso:country":"AU",
    "sg:address":"376 King St",
    "sg:city":"Newcastle",
    "sg:classifiers":[
        {
            "category":"Shopping",
            "subcategory":"Clothing, Apparel, & Fashions",
            "type":"Retail Goods"
        }
    ],
    "sg:phone":"+61 2 4926 1011",
    "sg:postcode":"2300",
    "sg:province":"NSW",
    "sg:tags":[
        "recycled",
        "clothing"
    ],
    "wof:name":"Encore Boutique",
    "wof:placetype":"venue"
},
  "geometry": {"coordinates":[151.76800499999999,-32.928589],"type":"Point"}
}