{
  "type": "Feature",
  "properties": {
    "addr:full":"606 Dean St Albury NSW 2640",
    "addr:housenumber":"606",
    "addr:postcode":"2640",
    "addr:street":"Dean St",
    "iso:country":"AU",
    "sg:address":"606 Dean St",
    "sg:city":"Albury",
    "sg:classifiers":[
        {
            "category":"Shopping",
            "subcategory":"Clothing, Apparel, & Fashions",
            "type":"Retail Goods"
        }
    ],
    "sg:phone":"+61 2 6021 6399",
    "sg:postcode":"2640",
    "sg:province":"NSW",
    "sg:tags":[
        "lady",
        "wear"
    ],
    "wof:name":"Sheppards of Albury",
    "wof:placetype":"venue"
},
  "geometry": {"coordinates":[146.914749145,-36.0804176331],"type":"Point"}
}