{
  "type": "Feature",
  "properties": {
    "addr:full":"11/ 15 Kumulla Rd Miranda NSW 2228",
    "addr:housenumber":"11 / 15",
    "addr:postcode":"2228",
    "addr:street":"Kumulla Rd",
    "iso:country":"AU",
    "sg:address":"11/ 15 Kumulla Rd",
    "sg:city":"Miranda",
    "sg:classifiers":[
        {
            "category":"Personal",
            "subcategory":"Skin Care",
            "type":"Services"
        }
    ],
    "sg:phone":"+61 1800 427 200",
    "sg:postcode":"2228",
    "sg:province":"NSW",
    "sg:tags":[
        "hair",
        "product"
    ],
    "wof:name":"Hair FX Australia",
    "wof:placetype":"venue"
},
  "geometry": {"coordinates":[151.11671447800001,-34.0285072327],"type":"Point"}
}