{
  "type": "Feature",
  "properties": {
    "addr:full":"Cnr Park St & William Kennedy Way Centre Narrogin WA 6312",
    "addr:postcode":"6312",
    "addr:street":"St & William Kennedy Way",
    "iso:country":"AU",
    "sg:address":"Cnr Park St & William Kennedy Way Centre",
    "sg:city":"Narrogin",
    "sg:classifiers":[
        {
            "category":"Social Services",
            "subcategory":"Child Care",
            "type":"Services"
        }
    ],
    "sg:phone":"+61 8 9881 2401",
    "sg:postcode":"6312",
    "sg:province":"WA",
    "wof:name":"Narrogin Regional Child Care Services Inc",
    "wof:placetype":"venue"
},
  "geometry": {"coordinates":[117.178367615,-32.9358100891],"type":"Point"}
}