{
  "type": "Feature",
  "properties": {
    "addr:full":"2 Herbert St Ingham QLD 4850",
    "addr:housenumber":"2",
    "addr:postcode":"4850",
    "addr:street":"Herbert St",
    "iso:country":"AU",
    "sg:address":"2 Herbert St",
    "sg:city":"Ingham",
    "sg:classifiers":[
        {
            "category":"Banks & Credit Unions",
            "subcategory":"Financial Services",
            "type":"Services"
        }
    ],
    "sg:phone":"+61 7 4776 3999",
    "sg:postcode":"4850",
    "sg:province":"QLD",
    "sg:tags":[
        "annuity",
        "rollover",
        "superannuation",
        "consultant"
    ],
    "wof:name":"Nino Marolla",
    "wof:placetype":"venue"
},
  "geometry": {"coordinates":[146.15713500999999,-18.6511459351],"type":"Point"}
}