{
  "type": "Feature",
  "properties": {
    "iso:country":"AU",
    "sg:address":"Unit 1, 84 Bells Line Of Rd",
    "sg:city":"North Richmond",
    "sg:classifiers":[
        {
            "category":"Manufacturing",
            "subcategory":"Retail Goods",
            "type":"Manufacturing & Wholesale Goods"
        }
    ],
    "sg:phone":"+61 2 4571 1099",
    "sg:postcode":"2754",
    "sg:province":"NSW",
    "sg:tags":[
        "merchant",
        "pump",
        "mfrs"
    ],
    "wof:name":"Hayes Bros. & Co",
    "wof:placetype":"venue"
},
  "geometry": {"coordinates":[150.71777343799999,-33.5778236389],"type":"Point"}
}