{
  "type": "Feature",
  "properties": {
    "iso:country":"AU",
    "sg:address":"28 Mossman Crs",
    "sg:city":"Lalor",
    "sg:classifiers":[
        {
            "category":"Banks & Credit Unions",
            "subcategory":"Financial Services",
            "type":"Services"
        }
    ],
    "sg:phone":"+61 3 9408 8443",
    "sg:postcode":"3075",
    "sg:province":"VIC",
    "sg:tags":[
        "loan",
        "finance",
        "mortgage"
    ],
    "wof:name":"Northend Mortgage Service",
    "wof:placetype":"venue"
},
  "geometry": {"coordinates":[145.06805419899999,-37.7633972168],"type":"Point"}
}