{
  "type": "Feature",
  "properties": {
    "addr:full":"14/ 58 Wecker Rd Mansfield QLD 4122",
    "addr:housenumber":"14 / 58",
    "addr:postcode":"4122",
    "addr:street":"Wecker Rd",
    "iso:country":"AU",
    "sg:address":"14/ 58 Wecker Rd",
    "sg:city":"Mansfield",
    "sg:classifiers":[
        {
            "category":"Manufacturing",
            "subcategory":"Building Materials",
            "type":"Manufacturing & Wholesale Goods"
        }
    ],
    "sg:phone":"+61 7 3849 6793",
    "sg:postcode":"4122",
    "sg:province":"QLD",
    "sg:tags":[
        "concrete",
        "product"
    ],
    "wof:name":"Top Line Concrete Tools",
    "wof:placetype":"venue"
},
  "geometry": {"coordinates":[153.09580993599999,-27.5326061249],"type":"Point"}
}