{
  "type": "Feature",
  "properties": {
    "addr:full":"800 Mountain Hwy Bayswater VIC 3153",
    "addr:housenumber":"800",
    "addr:postcode":"3153",
    "addr:street":"Mountain Hwy",
    "iso:country":"AU",
    "sg:address":"800 Mountain Hwy",
    "sg:city":"Bayswater",
    "sg:classifiers":[
        {
            "category":"Building & Trades",
            "subcategory":"Equipment Rental",
            "type":"Services"
        }
    ],
    "sg:phone":"+61 3 9720 6999",
    "sg:postcode":"3153",
    "sg:province":"VIC",
    "sg:tags":[
        "renting",
        "trailer"
    ],
    "wof:name":"Kennards Trailer Hire",
    "wof:placetype":"venue"
},
  "geometry": {"coordinates":[145.271392822,-37.838809967],"type":"Point"}
}