{
  "type": "Feature",
  "properties": {
    "addr:full":"712 Sydney Rd Brunswick VIC 3056",
    "addr:housenumber":"712",
    "addr:postcode":"3056",
    "addr:street":"Sydney Rd",
    "iso:country":"AU",
    "sg:address":"712 Sydney Rd",
    "sg:city":"Brunswick",
    "sg:classifiers":[
        {
            "category":"Shopping",
            "subcategory":"Shoes",
            "type":"Retail Goods"
        }
    ],
    "sg:phone":"+61 3 9386 4360",
    "sg:postcode":"3056",
    "sg:province":"VIC",
    "sg:tags":[
        "footwear"
    ],
    "wof:name":"Anna Fiori Factory Outlet",
    "wof:placetype":"venue"
},
  "geometry": {"coordinates":[144.96336364699999,-37.7605705261],"type":"Point"}
}