{
  "type": "Feature",
  "properties": {
    "addr:full":"71 Topham Rd Smeaton Grange NSW 2567",
    "addr:housenumber":"71",
    "addr:postcode":"2567",
    "addr:street":"Topham Rd",
    "iso:country":"AU",
    "sg:address":"71 Topham Rd",
    "sg:city":"Smeaton Grange",
    "sg:classifiers":[
        {
            "category":"Wholesale",
            "subcategory":"Office Equipment",
            "type":"Manufacturing & Wholesale Goods"
        }
    ],
    "sg:phone":"+61 2 4647 4333",
    "sg:postcode":"2567",
    "sg:province":"NSW",
    "sg:tags":[
        "nail",
        "nailing"
    ],
    "wof:name":"Able Fix Fasteners",
    "wof:placetype":"venue"
},
  "geometry": {"coordinates":[150.757736206,-34.0375442505],"type":"Point"}
}