{
  "type": "Feature",
  "properties": {
    "addr:full":"Unit 101/47- 51 Tingara St Portsmith QLD 4870",
    "addr:housenumber":"/;51",
    "addr:postcode":"4870",
    "addr:street":"47;Tingara St Portsmith",
    "iso:country":"AU",
    "sg:address":"Unit 101/47- 51 Tingara St",
    "sg:city":"Portsmith",
    "sg:classifiers":[
        {
            "category":"Wholesale",
            "subcategory":"Seafood",
            "type":"Manufacturing & Wholesale Goods"
        }
    ],
    "sg:phone":"+61 7 4035 3044",
    "sg:postcode":"4870",
    "sg:province":"QLD",
    "sg:tags":[
        "fish"
    ],
    "wof:name":"Ocean Link",
    "wof:placetype":"venue"
},
  "geometry": {"coordinates":[145.76953125,-16.9359207153],"type":"Point"}
}