{
  "type": "Feature",
  "properties": {
    "addr:full":"Shop 1, 51 Edinburg Rd Forrestfield WA 6058",
    "addr:housenumber":"shop;51",
    "addr:postcode":"6058",
    "addr:street":"Edinburg Rd",
    "iso:country":"AU",
    "sg:address":"Shop 1, 51 Edinburg Rd",
    "sg:city":"Forrestfield",
    "sg:classifiers":[
        {
            "category":"Food & Beverages",
            "subcategory":"Supermarket",
            "type":"Retail Goods"
        }
    ],
    "sg:phone":"+61 8 9453 3433",
    "sg:postcode":"6058",
    "sg:province":"WA",
    "sg:tags":[
        "grocery",
        "store"
    ],
    "wof:name":"FoodWorks",
    "wof:placetype":"venue"
},
  "geometry": {"coordinates":[116.01081085200001,-31.9947834015],"type":"Point"}
}