{
  "type": "Feature",
  "properties": {
    "addr:full":"28 Lawn Rd Noble Park VIC 3174",
    "addr:housenumber":"28",
    "addr:postcode":"3174",
    "addr:street":"Lawn Rd",
    "iso:country":"AU",
    "sg:address":"28 Lawn Rd",
    "sg:city":"Noble Park",
    "sg:classifiers":[
        {
            "category":"Building & Trades",
            "subcategory":"Construction",
            "type":"Services"
        }
    ],
    "sg:phone":"+61 3 9546 4592",
    "sg:postcode":"3174",
    "sg:province":"VIC",
    "sg:tags":[
        "contractor"
    ],
    "wof:name":"Garbellini P & B Pty Ltd",
    "wof:placetype":"venue"
},
  "geometry": {"coordinates":[145.16299438499999,-37.9601593018],"type":"Point"}
}