{
  "type": "Feature",
  "properties": {
    "addr:full":"Shop T50 Lithgow Valley Plaza Cnr Lithgow & Bent S Lithgow NSW 2790",
    "addr:postcode":"2790",
    "addr:street":"Cnr",
    "iso:country":"AU",
    "sg:address":"Shop T50 Lithgow Valley Plaza Cnr Lithgow & Bent S",
    "sg:city":"Lithgow",
    "sg:classifiers":[
        {
            "category":"Retail",
            "subcategory":"Repair Shop",
            "type":"Services"
        }
    ],
    "sg:phone":"+61 2 6353 1692",
    "sg:postcode":"2790",
    "sg:province":"NSW",
    "sg:tags":[
        "handbag"
    ],
    "wof:name":"Kays Bag Store",
    "wof:placetype":"venue"
},
  "geometry": {"coordinates":[150.15315246599999,-33.4849891663],"type":"Point"}
}