{
  "type": "Feature",
  "properties": {
    "addr:full":"Shop 8/ 600 Hoxton Park Rd Hoxton Park NSW 2171",
    "addr:housenumber":"shop 8 / 600",
    "addr:postcode":"2171",
    "addr:street":"Hoxton Park Rd",
    "iso:country":"AU",
    "sg:address":"Shop 8/ 600 Hoxton Park Rd",
    "sg:city":"Hoxton Park",
    "sg:classifiers":[
        {
            "category":"Personal",
            "subcategory":"Beauty Salon",
            "type":"Services"
        }
    ],
    "sg:phone":"+61 2 9825 8008",
    "sg:postcode":"2171",
    "sg:province":"NSW",
    "sg:tags":[
        "hairdresser"
    ],
    "wof:name":"Baki's Barber",
    "wof:placetype":"venue"
},
  "geometry": {"coordinates":[150.84910583499999,-33.9249610901],"type":"Point"}
}