{
  "type": "Feature",
  "properties": {
    "addr:full":"208 Canley Vale Rd Canley Vale NSW 2166",
    "addr:housenumber":"208",
    "addr:postcode":"2166",
    "addr:street":"Canley Vale Rd",
    "iso:country":"AU",
    "sg:address":"208 Canley Vale Rd",
    "sg:city":"Canley Vale",
    "sg:classifiers":[
        {
            "category":"Fast Food",
            "type":"Food & Drink"
        }
    ],
    "sg:phone":"+61 2 9726 1020",
    "sg:postcode":"2166",
    "sg:province":"NSW",
    "sg:tags":[
        "away",
        "take"
    ],
    "wof:name":"Magic Charcoal Chicken",
    "wof:placetype":"venue"
},
  "geometry": {"coordinates":[150.926635742,-33.8841209412],"type":"Point"}
}