{
  "type": "Feature",
  "properties": {
    "addr:full":"10 William St Cowra NSW 2794",
    "addr:housenumber":"10",
    "addr:postcode":"2794",
    "addr:street":"William St",
    "iso:country":"AU",
    "sg:address":"10 William St",
    "sg:city":"Cowra",
    "sg:classifiers":[
        {
            "category":"Commercial Area",
            "type":"Public Place"
        }
    ],
    "sg:phone":"+61 2 6342 3875",
    "sg:postcode":"2794",
    "sg:province":"NSW",
    "sg:tags":[
        "heavy",
        "carrier"
    ],
    "wof:name":"Boland Transport",
    "wof:placetype":"venue"
},
  "geometry": {"coordinates":[148.674102783,-33.8400764465],"type":"Point"}
}