{
  "type": "Feature",
  "properties": {
    "addr:full":"468 The Entrance Rd Erina Heights NSW 2260",
    "addr:housenumber":"468",
    "addr:postcode":"2260",
    "addr:street":"The Entrance Rd",
    "iso:country":"AU",
    "sg:address":"468 The Entrance Rd",
    "sg:city":"Erina Heights",
    "sg:classifiers":[
        {
            "category":"Retail",
            "subcategory":"Veterinary Services",
            "type":"Services"
        }
    ],
    "sg:phone":"+61 2 4367 7366",
    "sg:postcode":"2260",
    "sg:province":"NSW",
    "sg:tags":[
        "surgeon"
    ],
    "wof:name":"Jones M R & Associates",
    "wof:placetype":"venue"
},
  "geometry": {"coordinates":[151.41064499999999,-33.425556],"type":"Point"}
}