{
  "type": "Feature",
  "properties": {
    "addr:full":"24 Phillip Pde Deception Bay QLD 4508",
    "addr:housenumber":"24",
    "addr:postcode":"4508",
    "addr:street":"Phillip Pde",
    "iso:country":"AU",
    "sg:address":"24 Phillip Pde",
    "sg:city":"Deception Bay",
    "sg:classifiers":[
        {
            "category":"Transit Center",
            "subcategory":"Freight",
            "type":"Transportation"
        }
    ],
    "sg:phone":"+61 7 3293 0322",
    "sg:postcode":"4508",
    "sg:province":"QLD",
    "sg:tags":[
        "agent",
        "shipping"
    ],
    "wof:name":"Goymer & Associates",
    "wof:placetype":"venue"
},
  "geometry": {"coordinates":[153.03086852999999,-27.1994495392],"type":"Point"}
}