{
  "type": "Feature",
  "properties": {
    "addr:full":"2580 Albany Hwy Kelmscott WA 6111",
    "addr:housenumber":"2580",
    "addr:postcode":"6111",
    "addr:street":"Albany Hwy",
    "iso:country":"AU",
    "sg:address":"2580 Albany Hwy",
    "sg:city":"Kelmscott",
    "sg:classifiers":[
        {
            "category":"Banks & Credit Unions",
            "subcategory":"Bureau De Change",
            "type":"Services"
        }
    ],
    "sg:phone":"+61 8 9390 9637",
    "sg:postcode":"6111",
    "sg:province":"WA",
    "sg:tags":[
        "gas",
        "natural",
        "lp",
        "equipment"
    ],
    "wof:name":"LPG Auto Services",
    "wof:placetype":"venue"
},
  "geometry": {"coordinates":[116.01821899399999,-32.1242294312],"type":"Point"}
}