{
  "type": "Feature",
  "properties": {
    "iso:country":"AU",
    "sg:address":"31 Falkland St",
    "sg:city":"Doolandella",
    "sg:classifiers":[
        {
            "category":"Building & Trades",
            "subcategory":"Landscaping Services",
            "type":"Services"
        }
    ],
    "sg:phone":"+61 7 3879 2893",
    "sg:postcode":"4077",
    "sg:province":"QLD",
    "sg:tags":[
        "designer",
        "landscape",
        "contractor"
    ],
    "wof:name":"Naturform",
    "wof:placetype":"venue"
},
  "geometry": {"coordinates":[152.98187255900001,-27.6257305145],"type":"Point"}
}