{
  "type": "Feature",
  "properties": {
    "addr:full":"Hume Hwy Wangaratta VIC 3677",
    "addr:postcode":"3677",
    "addr:street":"Hume Hwy",
    "iso:country":"AU",
    "sg:address":"Hume Hwy",
    "sg:city":"Wangaratta",
    "sg:classifiers":[
        {
            "category":"Travel",
            "subcategory":"Hotels & Motels",
            "type":"Entertainment"
        }
    ],
    "sg:phone":"+61 1800 032 475",
    "sg:postcode":"3677",
    "sg:province":"VIC",
    "wof:name":"Parkview Motor Inn",
    "wof:placetype":"venue"
},
  "geometry": {"coordinates":[146.34605407699999,-36.3896331787],"type":"Point"}
}