{
  "type": "Feature",
  "properties": {
    "addr:full":"30 Flinders St Adelaide SA 5000",
    "addr:housenumber":"30",
    "addr:postcode":"5000",
    "addr:street":"Flinders St",
    "iso:country":"AU",
    "sg:address":"30 Flinders St",
    "sg:city":"Adelaide",
    "sg:classifiers":[
        {
            "category":"Banks & Credit Unions",
            "subcategory":"Financial Services",
            "type":"Services"
        }
    ],
    "sg:phone":"+61 8 8204 2964",
    "sg:postcode":"5000",
    "sg:province":"SA",
    "sg:tags":[
        "annuity",
        "rollover",
        "superannuation",
        "consultant"
    ],
    "wof:name":"Police Superannuation Fund",
    "wof:placetype":"venue"
},
  "geometry": {"coordinates":[138.602020264,-34.9269142151],"type":"Point"}
}