{
  "type": "Feature",
  "properties": {
    "addr:full":"4/ 10 Pilgrim Crt Ringwood VIC 3134",
    "addr:housenumber":"/ 10",
    "addr:postcode":"3134",
    "addr:street":"Pilgrim Crt",
    "iso:country":"AU",
    "sg:address":"4/ 10 Pilgrim Crt",
    "sg:city":"Ringwood",
    "sg:classifiers":[
        {
            "category":"Retail",
            "subcategory":"Auto Repair",
            "type":"Services"
        }
    ],
    "sg:phone":"+61 3 9873 5913",
    "sg:postcode":"3134",
    "sg:province":"VIC",
    "sg:tags":[
        "repairer",
        "motor",
        "engineer"
    ],
    "wof:name":"Sanders Automotive Pty Ltd",
    "wof:placetype":"venue"
},
  "geometry": {"coordinates":[145.21565246599999,-37.829624176],"type":"Point"}
}