{
  "type": "Feature",
  "properties": {
    "addr:full":"362 South Rd Moorabbin VIC 3189",
    "addr:housenumber":"362",
    "addr:postcode":"3189",
    "addr:street":"South Rd",
    "iso:country":"AU",
    "sg:address":"362 South Rd",
    "sg:city":"Moorabbin",
    "sg:classifiers":[
        {
            "category":"Manufacturing",
            "subcategory":"Motor Vehicles & Parts",
            "type":"Manufacturing & Wholesale Goods"
        }
    ],
    "sg:phone":"+61 3 9555 5551",
    "sg:postcode":"3189",
    "sg:province":"VIC",
    "sg:tags":[
        "replacement"
    ],
    "wof:name":"Moorabbin Auto Spares Pty Ltd",
    "wof:placetype":"venue"
},
  "geometry": {"coordinates":[145.03805542000001,-37.9336662292],"type":"Point"}
}