{
  "type": "Feature",
  "properties": {
    "addr:full":"Cnr Napper Rd & Parkwood Blvd Parkwood QLD 4214",
    "addr:postcode":"4214",
    "addr:street":"Cnr Napper Rd & Parkwood Blvd",
    "iso:country":"AU",
    "sg:address":"Cnr Napper Rd & Parkwood Blvd",
    "sg:city":"Parkwood",
    "sg:classifiers":[
        {
            "category":"Food & Beverages",
            "subcategory":"Supermarket",
            "type":"Retail Goods"
        }
    ],
    "sg:phone":"+61 7 5571 7538",
    "sg:postcode":"4214",
    "sg:province":"QLD",
    "sg:tags":[
        "grocery",
        "store"
    ],
    "wof:name":"Quix Food Stores",
    "wof:placetype":"venue"
},
  "geometry": {"coordinates":[153.36895751899999,-27.946264267],"type":"Point"}
}