{
  "type": "Feature",
  "properties": {
    "addr:full":"26 Douglas Pde Williamstown VIC 3016",
    "addr:housenumber":"26",
    "addr:postcode":"3016",
    "addr:street":"Douglas Pde",
    "iso:country":"AU",
    "sg:address":"26 Douglas Pde",
    "sg:city":"Williamstown",
    "sg:classifiers":[
        {
            "category":"Food & Beverages",
            "subcategory":"Bakery",
            "type":"Retail Goods"
        }
    ],
    "sg:phone":"+61 3 9397 5312",
    "sg:postcode":"3016",
    "sg:province":"VIC",
    "sg:tags":[
        "cake",
        "shop",
        "pastry"
    ],
    "wof:name":"Ferguson Plarre Bakehouses Pty Ltd",
    "wof:placetype":"venue"
},
  "geometry": {"coordinates":[144.89808654800001,-37.8580665588],"type":"Point"}
}