{
  "type": "Feature",
  "properties": {
    "addr:full":"1 / 2 Clarke St Lilydale VIC 3140",
    "addr:housenumber":"/ 2",
    "addr:postcode":"3140",
    "addr:street":"Clarke St",
    "iso:country":"AU",
    "sg:address":"1 / 2 Clarke St",
    "sg:city":"Lilydale",
    "sg:classifiers":[
        {
            "category":"Shopping",
            "subcategory":"Stationery & Office Supplies",
            "type":"Retail Goods"
        }
    ],
    "sg:phone":"+61 3 9735 4518",
    "sg:postcode":"3140",
    "sg:province":"VIC",
    "wof:name":"Office Products Depot",
    "wof:placetype":"venue"
},
  "geometry": {"coordinates":[145.35104370100001,-37.7587623596],"type":"Point"}
}