{
  "type": "Feature",
  "properties": {
    "iso:country":"AU",
    "sg:address":"3/ 43 Monash Rd",
    "sg:city":"Newborough",
    "sg:classifiers":[
        {
            "category":"Retail",
            "subcategory":"Veterinary Services",
            "type":"Services"
        }
    ],
    "sg:phone":"+61 3 5126 2880",
    "sg:postcode":"3825",
    "sg:province":"VIC",
    "sg:tags":[
        "surgeon"
    ],
    "wof:name":"Newborough Veterinary Centre",
    "wof:placetype":"venue"
},
  "geometry": {"coordinates":[146.289978,-38.185062],"type":"Point"}
}