{
  "type": "Feature",
  "properties": {
    "addr:full":"Shp 10/ 101 Hampton Drv Tannum Sands QLD 4680",
    "addr:housenumber":"10 / 101",
    "addr:postcode":"4680",
    "addr:street":"Hampton Drv",
    "iso:country":"AU",
    "sg:address":"Shp 10/ 101 Hampton Drv",
    "sg:city":"Tannum Sands",
    "sg:classifiers":[
        {
            "category":"Food & Beverages",
            "subcategory":"Liquor & Beverages",
            "type":"Retail Goods"
        }
    ],
    "sg:phone":"+61 7 4973 2533",
    "sg:postcode":"4680",
    "sg:province":"QLD",
    "sg:tags":[
        "store"
    ],
    "wof:name":"Tannum Liquor Central",
    "wof:placetype":"venue"
},
  "geometry": {"coordinates":[151.36604309099999,-23.9486846924],"type":"Point"}
}