{
  "type": "Feature",
  "properties": {
    "addr:full":"80 Hall St Bondi Beach NSW 2026",
    "addr:housenumber":"80",
    "addr:postcode":"2026",
    "addr:street":"Hall St",
    "iso:country":"AU",
    "sg:address":"80 Hall St",
    "sg:city":"Bondi Beach",
    "sg:classifiers":[
        {
            "category":"Restaurant",
            "type":"Food & Drink"
        }
    ],
    "sg:phone":"+61 2 9130 8080",
    "sg:postcode":"2026",
    "sg:province":"NSW",
    "wof:name":"Bondi Tucker",
    "wof:placetype":"venue"
},
  "geometry": {"coordinates":[151.27084350600001,-33.8893737793],"type":"Point"}
}