{
  "type": "Feature",
  "properties": {
    "addr:full":"77 Arthur Hwy Dunalley TAS 7177",
    "addr:housenumber":"77",
    "addr:postcode":"7177",
    "addr:street":"Arthur Hwy",
    "iso:country":"AU",
    "sg:address":"77 Arthur Hwy",
    "sg:city":"Dunalley",
    "sg:classifiers":[
        {
            "category":"Building & Trades",
            "subcategory":"Construction",
            "type":"Services"
        }
    ],
    "sg:phone":"+61 3 6253 5165",
    "sg:postcode":"7177",
    "sg:province":"TAS",
    "sg:tags":[
        "contractor"
    ],
    "wof:name":"A & T Petterd",
    "wof:placetype":"venue"
},
  "geometry": {"coordinates":[147.815842,-42.883133],"type":"Point"}
}