{
  "type": "Feature",
  "properties": {
    "addr:full":"PO Box 794 Jamison Centre ACT 2614",
    "addr:postcode":"2614",
    "iso:country":"AU",
    "sg:address":"PO Box 794",
    "sg:city":"Jamison Centre",
    "sg:classifiers":[
        {
            "category":"Food & Beverages",
            "subcategory":"Specialty",
            "type":"Retail Goods"
        }
    ],
    "sg:phone":"+61 2 6278 4238",
    "sg:postcode":"2614",
    "sg:province":"ACT",
    "sg:tags":[
        "product",
        "health"
    ],
    "wof:name":"Herbalife Australasia Pty Ltd",
    "wof:placetype":"venue"
},
  "geometry": {"coordinates":[149.05946350100001,-35.2556686401],"type":"Point"}
}