{
  "type": "Feature",
  "properties": {
    "addr:full":"Shp 1/ 2 Dening St The Entrance NSW 2261",
    "addr:housenumber":"/ 2",
    "addr:postcode":"2261",
    "addr:street":"Dening St The",
    "iso:country":"AU",
    "sg:address":"Shp 1/ 2 Dening St",
    "sg:city":"The Entrance",
    "sg:classifiers":[
        {
            "category":"Cafe",
            "type":"Food & Drink"
        }
    ],
    "sg:phone":"+61 2 4332 5811",
    "sg:postcode":"2261",
    "sg:province":"NSW",
    "wof:name":"Ells Cafe",
    "wof:placetype":"venue"
},
  "geometry": {"coordinates":[151.499268,-33.346684],"type":"Point"}
}