{
  "type": "Feature",
  "properties": {
    "addr:full":"53 Harris St Broken Hill NSW 2880",
    "addr:housenumber":"53",
    "addr:postcode":"2880",
    "addr:street":"Harris St",
    "iso:country":"AU",
    "sg:address":"53 Harris St",
    "sg:city":"Broken Hill",
    "sg:classifiers":[
        {
            "category":"Building & Trades",
            "subcategory":"Plumbing",
            "type":"Services"
        }
    ],
    "sg:phone":"+61 412 817 362",
    "sg:postcode":"2880",
    "sg:province":"NSW",
    "sg:tags":[
        "plumber",
        "gasfitters"
    ],
    "wof:name":"Dennis Stephens",
    "wof:placetype":"venue"
},
  "geometry": {"coordinates":[141.44204711899999,-31.9723796844],"type":"Point"}
}