{
  "type": "Feature",
  "properties": {
    "addr:full":"5 Turnbull Rd cnr Warman St Neerabup WA 6031",
    "addr:housenumber":"5",
    "addr:postcode":"6031",
    "addr:street":"Turnbull Rd Cnr Warman St",
    "iso:country":"AU",
    "sg:address":"5 Turnbull Rd cnr Warman St",
    "sg:city":"Neerabup",
    "sg:classifiers":[
        {
            "category":"Wholesale",
            "subcategory":"Auto Parts",
            "type":"Manufacturing & Wholesale Goods"
        }
    ],
    "sg:phone":"+61 8 9206 0220",
    "sg:postcode":"6031",
    "sg:province":"WA",
    "sg:tags":[
        "wholesaler",
        "mfrs",
        "lacquer"
    ],
    "wof:name":"Becker Acroma",
    "wof:placetype":"venue"
},
  "geometry": {"coordinates":[115.787559509,-31.6852149963],"type":"Point"}
}