{
  "type": "Feature",
  "properties": {
    "iso:country":"AU",
    "sg:address":"213 Ramsgate Rd",
    "sg:city":"Ramsgate",
    "sg:classifiers":[
        {
            "category":"Food & Beverages",
            "subcategory":"Liquor & Beverages",
            "type":"Retail Goods"
        }
    ],
    "sg:phone":"+61 2 9529 5740",
    "sg:postcode":"2217",
    "sg:province":"NSW",
    "sg:tags":[
        "store"
    ],
    "wof:name":"Liquor Stax Australia Pty Ltd",
    "wof:placetype":"venue"
},
  "geometry": {"coordinates":[151.146469,-33.986053],"type":"Point"}
}