{
  "type": "Feature",
  "properties": {
    "iso:country":"AU",
    "sg:address":"21 Elizabeth St",
    "sg:city":"Campsie",
    "sg:classifiers":[
        {
            "category":"Manufacturing",
            "subcategory":"Chemicals & Compounds",
            "type":"Manufacturing & Wholesale Goods"
        }
    ],
    "sg:phone":"+61 2 9718 4400",
    "sg:postcode":"2194",
    "sg:province":"NSW",
    "sg:tags":[
        "industrial"
    ],
    "wof:name":"Bel-Air Chemicals",
    "wof:placetype":"venue"
},
  "geometry": {"coordinates":[151.100296,-33.923431],"type":"Point"}
}