{
  "type": "Feature",
  "properties": {
    "addr:full":"117 Flinders St Mt Hawthorn WA 6016",
    "addr:housenumber":"117",
    "addr:postcode":"6016",
    "addr:street":"Flinders St Mt",
    "iso:country":"AU",
    "sg:address":"117 Flinders St",
    "sg:city":"Mt Hawthorn",
    "sg:classifiers":[
        {
            "category":"Retail",
            "subcategory":"Laundry & Dry Cleaning",
            "type":"Services"
        }
    ],
    "sg:phone":"+61 8 9480 5488",
    "sg:postcode":"6016",
    "sg:province":"WA",
    "sg:tags":[
        "ironing"
    ],
    "wof:name":"Ironing Services W.A.",
    "wof:placetype":"venue"
},
  "geometry": {"coordinates":[115.838752747,-31.9172859192],"type":"Point"}
}