{
  "type": "Feature",
  "properties": {
    "iso:country":"AU",
    "sg:address":"1 Stafford Rd",
    "sg:city":"Albury",
    "sg:classifiers":[
        {
            "category":"Health Services",
            "subcategory":"Nursing And Care Facility",
            "type":"Services"
        }
    ],
    "sg:phone":"+61 2 6042 1140",
    "sg:postcode":"2640",
    "sg:province":"NSW",
    "sg:tags":[
        "home"
    ],
    "wof:name":"Lutheran Aged Care - &#034;Yallaroo&#034;",
    "wof:placetype":"venue"
},
  "geometry": {"coordinates":[146.88429260300001,-36.0727233887],"type":"Point"}
}