{
  "type": "Feature",
  "properties": {
    "addr:full":"10/ 4 Gregory Ave Epping North NSW 2121",
    "addr:housenumber":"10 / 4",
    "addr:postcode":"2121",
    "addr:street":"Gregory Ave",
    "iso:country":"AU",
    "sg:address":"10/ 4 Gregory Ave",
    "sg:city":"Epping North",
    "sg:classifiers":[
        {
            "category":"Professional",
            "subcategory":"Art Services",
            "type":"Services"
        }
    ],
    "sg:phone":"+61 2 9869 3533",
    "sg:postcode":"2121",
    "sg:province":"NSW",
    "sg:tags":[
        "interior",
        "designer"
    ],
    "wof:name":"Interior Architecture Design",
    "wof:placetype":"venue"
},
  "geometry": {"coordinates":[151.09051513700001,-33.7629165649],"type":"Point"}
}