{
  "type": "Feature",
  "properties": {
    "iso:country":"AU",
    "sg:address":"Westcourt Plaza 274 Mulgrave Rd",
    "sg:city":"Cairns",
    "sg:classifiers":[
        {
            "category":"Professional",
            "subcategory":"Accounting & Tax Preparation",
            "type":"Services"
        }
    ],
    "sg:phone":"+61 7 4051 9900",
    "sg:postcode":"4870",
    "sg:province":"QLD",
    "sg:tags":[
        "consultant",
        "taxation"
    ],
    "wof:name":"MGI Cockrell Reese Pty Ltd",
    "wof:placetype":"venue"
},
  "geometry": {"coordinates":[145.747116089,-16.9377651215],"type":"Point"}
}