{
  "type": "Feature",
  "properties": {
    "addr:full":"3 Paisley Drv Lawnton QLD 4501",
    "addr:housenumber":"3",
    "addr:postcode":"4501",
    "addr:street":"Paisley Drv",
    "iso:country":"AU",
    "sg:address":"3 Paisley Drv",
    "sg:city":"Lawnton",
    "sg:classifiers":[
        {
            "category":"Wholesale",
            "subcategory":"Painting Supplies",
            "type":"Manufacturing & Wholesale Goods"
        }
    ],
    "sg:phone":"+61 7 3205 5144",
    "sg:postcode":"4501",
    "sg:province":"QLD",
    "sg:tags":[
        "equipment",
        "spraying"
    ],
    "wof:name":"Air Electric Power Tools",
    "wof:placetype":"venue"
},
  "geometry": {"coordinates":[152.98846435600001,-27.288898468],"type":"Point"}
}