{
  "type": "Feature",
  "properties": {
    "iso:country":"AU",
    "sg:address":"121 Preston-Boundary Rd",
    "sg:city":"Toowoomba",
    "sg:classifiers":[
        {
            "category":"Building & Trades",
            "subcategory":"Construction",
            "type":"Services"
        }
    ],
    "sg:phone":"+61 7 4630 9665",
    "sg:postcode":"4352",
    "sg:province":"QLD",
    "sg:tags":[
        "fencing",
        "contractor"
    ],
    "wof:name":"Michael R Willis",
    "wof:placetype":"venue"
},
  "geometry": {"coordinates":[151.942276,-27.632347],"type":"Point"}
}