{
  "type": "Feature",
  "properties": {
    "addr:full":"58- 60 Commercial Rd Morwell VIC 3840",
    "addr:housenumber":"60",
    "addr:postcode":"3840",
    "addr:street":"Commercial Rd",
    "iso:country":"AU",
    "sg:address":"58- 60 Commercial Rd",
    "sg:city":"Morwell",
    "sg:classifiers":[
        {
            "category":"Education",
            "subcategory":"University",
            "type":"Public Place"
        }
    ],
    "sg:phone":"+61 3 5135 4304",
    "sg:postcode":"3840",
    "sg:province":"VIC",
    "sg:tags":[
        "educational",
        "organisation",
        "cultural"
    ],
    "wof:name":"Gippsland Community Leadership Program",
    "wof:placetype":"venue"
},
  "geometry": {"coordinates":[146.39561462399999,-38.2367134094],"type":"Point"}
}