{
  "type": "Feature",
  "properties": {
    "addr:full":"51 Hely St Wyong NSW 2259",
    "addr:housenumber":"51",
    "addr:postcode":"2259",
    "addr:street":"Hely St",
    "iso:country":"AU",
    "sg:address":"51 Hely St",
    "sg:city":"Wyong",
    "sg:classifiers":[
        {
            "category":"Professional",
            "subcategory":"Engineering",
            "type":"Services"
        }
    ],
    "sg:phone":"+61 2 4353 1744",
    "sg:postcode":"2259",
    "sg:province":"NSW",
    "sg:tags":[
        "consulting",
        "engineer"
    ],
    "wof:name":"Slater Jessop & Armstrong Pty Ltd",
    "wof:placetype":"venue"
},
  "geometry": {"coordinates":[151.42379760700001,-33.2835922241],"type":"Point"}
}