{
  "type": "Feature",
  "properties": {
    "addr:full":"4 Hillock Ave Albury NSW 2640",
    "addr:housenumber":"4",
    "addr:postcode":"2640",
    "addr:street":"Hillock Ave",
    "iso:country":"AU",
    "sg:address":"4 Hillock Ave",
    "sg:city":"Albury",
    "sg:classifiers":[
        {
            "category":"Sports & Exercise",
            "subcategory":"Sports Center",
            "type":"Entertainment"
        }
    ],
    "sg:phone":"+61 419 220 621",
    "sg:postcode":"2640",
    "sg:province":"NSW",
    "sg:tags":[
        "coach",
        "tennis"
    ],
    "wof:name":"O&#039;Shannessy Tennis Academy Pty Ltd",
    "wof:placetype":"venue"
},
  "geometry": {"coordinates":[146.94374084500001,-36.0871086121],"type":"Point"}
}