{
  "type": "Feature",
  "properties": {
    "addr:full":"PO Box 246 Brighton TAS 7030",
    "addr:postcode":"7030",
    "iso:country":"AU",
    "sg:address":"PO Box 246",
    "sg:city":"Brighton",
    "sg:classifiers":[
        {
            "category":"Building & Trades",
            "subcategory":"Landscaping Services",
            "type":"Services"
        }
    ],
    "sg:phone":"+61 407 855 960",
    "sg:postcode":"7030",
    "sg:province":"TAS",
    "sg:tags":[
        "fertilizer",
        "spreading",
        "insecticide"
    ],
    "wof:name":"Burden Fertilizer Services",
    "wof:placetype":"venue"
},
  "geometry": {"coordinates":[147.25169372600001,-42.6992988586],"type":"Point"}
}