{
  "type": "Feature",
  "properties": {
    "addr:full":"36 Perouse Rd Randwick NSW 2031",
    "addr:housenumber":"36",
    "addr:postcode":"2031",
    "addr:street":"Perouse Rd",
    "iso:country":"AU",
    "sg:address":"36 Perouse Rd",
    "sg:city":"Randwick",
    "sg:classifiers":[
        {
            "category":"Professional",
            "subcategory":"Art Services",
            "type":"Services"
        }
    ],
    "sg:phone":"+61 2 9398 9989",
    "sg:postcode":"2031",
    "sg:province":"NSW",
    "sg:tags":[
        "graphic",
        "designer"
    ],
    "wof:name":"Magido Art",
    "wof:placetype":"venue"
},
  "geometry": {"coordinates":[151.242477417,-33.9198150635],"type":"Point"}
}