{
  "type": "Feature",
  "properties": {
    "iso:country":"AU",
    "sg:address":"Shop 7 Garran Pl",
    "sg:city":"Garran",
    "sg:classifiers":[
        {
            "category":"Personal",
            "subcategory":"Beauty Salon",
            "type":"Services"
        }
    ],
    "sg:phone":"+61 2 6281 4339",
    "sg:postcode":"2605",
    "sg:province":"ACT",
    "sg:tags":[
        "hairdresser"
    ],
    "wof:name":"Akita Hair",
    "wof:placetype":"venue"
},
  "geometry": {"coordinates":[149.107543945,-35.3425331116],"type":"Point"}
}