{
  "type": "Feature",
  "properties": {
    "addr:full":"Yacca Rd Yankalilla SA 5203",
    "addr:postcode":"5203",
    "addr:street":"Yacca Rd",
    "iso:country":"AU",
    "sg:address":"Yacca Rd",
    "sg:city":"Yankalilla",
    "sg:classifiers":[
        {
            "category":"Building & Trades",
            "subcategory":"Landscaping Services",
            "type":"Services"
        }
    ],
    "sg:phone":"+61 8 8558 3218",
    "sg:postcode":"5203",
    "sg:province":"SA",
    "sg:tags":[
        "stump",
        "tree",
        "felling",
        "removal"
    ],
    "wof:name":"Southern Mobile Mulching",
    "wof:placetype":"venue"
},
  "geometry": {"coordinates":[138.362548828,-35.4434585571],"type":"Point"}
}