{
  "type": "Feature",
  "properties": {
    "addr:full":"20 Albatross Rd Nowra NSW 2541",
    "addr:housenumber":"20",
    "addr:postcode":"2541",
    "addr:street":"Albatross Rd",
    "iso:country":"AU",
    "sg:address":"20 Albatross Rd",
    "sg:city":"Nowra",
    "sg:classifiers":[
        {
            "category":"Health Services",
            "subcategory":"Health Practitioner",
            "type":"Services"
        }
    ],
    "sg:phone":"+61 2 4421 2376",
    "sg:postcode":"2541",
    "sg:province":"NSW",
    "sg:tags":[
        "osteopath"
    ],
    "wof:name":"Maher Rod",
    "wof:placetype":"venue"
},
  "geometry": {"coordinates":[150.56918335,-34.915271759],"type":"Point"}
}