{
  "type": "Feature",
  "properties": {
    "iso:country":"AU",
    "sg:address":"70 High St",
    "sg:city":"Northcote",
    "sg:classifiers":[
        {
            "category":"Shopping",
            "subcategory":"Clothing, Apparel, & Fashions",
            "type":"Retail Goods"
        }
    ],
    "sg:phone":"+61 3 9486 6701",
    "sg:postcode":"3070",
    "sg:province":"VIC",
    "sg:tags":[
        "lady",
        "wear"
    ],
    "wof:name":"Manque Design (Retail) Pty Ltd",
    "wof:placetype":"venue"
},
  "geometry": {"coordinates":[144.99696399999999,-37.780579],"type":"Point"}
}