{
  "type": "Feature",
  "properties": {
    "iso:country":"AU",
    "sg:address":"School St",
    "sg:city":"California Gully",
    "sg:classifiers":[
        {
            "category":"Education",
            "subcategory":"Dance Studio",
            "type":"Public Place"
        }
    ],
    "sg:phone":"+61 419 343 761",
    "sg:postcode":"3556",
    "sg:province":"VIC",
    "sg:tags":[
        "venue",
        "tuition"
    ],
    "wof:name":"Melissa Abley Dance House",
    "wof:placetype":"venue"
},
  "geometry": {"coordinates":[144.257354736,-36.7343177795],"type":"Point"}
}