{
  "type": "Feature",
  "properties": {
    "iso:country":"AU",
    "sg:address":"180 Kerferd Rd",
    "sg:city":"Albert Park",
    "sg:classifiers":[
        {
            "category":"Health Services",
            "subcategory":"Health Practitioner",
            "type":"Services"
        }
    ],
    "sg:phone":"+61 3 9696 6964",
    "sg:postcode":"3206",
    "sg:province":"VIC",
    "sg:tags":[
        "psychologist"
    ],
    "wof:name":"Anderson Cate",
    "wof:placetype":"venue"
},
  "geometry": {"coordinates":[144.952484,-37.84774],"type":"Point"}
}