{
  "type": "Feature",
  "properties": {
    "addr:full":"3 Amaroo Crt Echuca VIC 3564",
    "addr:housenumber":"3",
    "addr:postcode":"3564",
    "addr:street":"Amaroo Crt",
    "iso:country":"AU",
    "sg:address":"3 Amaroo Crt",
    "sg:city":"Echuca",
    "sg:classifiers":[
        {
            "category":"Utilities",
            "subcategory":"Cable",
            "type":"Services"
        }
    ],
    "sg:phone":"+61 419 001 843",
    "sg:postcode":"3564",
    "sg:province":"VIC",
    "sg:tags":[
        "underground",
        "locator"
    ],
    "wof:name":"Echuca & District Cable Locations",
    "wof:placetype":"venue"
},
  "geometry": {"coordinates":[144.76446533199999,-36.1342811584],"type":"Point"}
}