{
  "type": "Feature",
  "properties": {
    "addr:full":"379 Morayfield Rd Caboolture QLD 4510",
    "addr:housenumber":"379",
    "addr:postcode":"4510",
    "addr:street":"Morayfield Rd",
    "iso:country":"AU",
    "sg:address":"379 Morayfield Rd",
    "sg:city":"Caboolture",
    "sg:classifiers":[
        {
            "category":"Manufacturing",
            "subcategory":"Motor Vehicles & Parts",
            "type":"Manufacturing & Wholesale Goods"
        }
    ],
    "sg:phone":"+61 7 5497 8107",
    "sg:postcode":"4510",
    "sg:province":"QLD",
    "sg:tags":[
        "replacement"
    ],
    "wof:name":"Autobarn",
    "wof:placetype":"venue"
},
  "geometry": {"coordinates":[152.95663500000001,-27.121534],"type":"Point"}
}