{
  "type": "Feature",
  "properties": {
    "addr:full":"Westfield Shopngtwn Cnr Northcliff Drv & King St Warrawong NSW 2502",
    "addr:postcode":"2502",
    "addr:street":"Cnr Northcliff Drv & King St",
    "iso:country":"AU",
    "sg:address":"Westfield Shopngtwn Cnr Northcliff Drv & King St",
    "sg:city":"Warrawong",
    "sg:classifiers":[
        {
            "category":"Food & Beverages",
            "subcategory":"Liquor & Beverages",
            "type":"Retail Goods"
        }
    ],
    "sg:phone":"+61 2 4274 6719",
    "sg:postcode":"2502",
    "sg:province":"NSW",
    "sg:tags":[
        "store"
    ],
    "wof:name":"Liquorland",
    "wof:placetype":"venue"
},
  "geometry": {"coordinates":[150.88760400000001,-34.484882],"type":"Point"}
}