{
  "type": "Feature",
  "properties": {
    "addr:full":"177 Harris St Pyrmont NSW 2009",
    "addr:housenumber":"177",
    "addr:postcode":"2009",
    "addr:street":"Harris St",
    "iso:country":"AU",
    "sg:address":"177 Harris St",
    "sg:city":"Pyrmont",
    "sg:classifiers":[
        {
            "category":"Professional",
            "subcategory":"Business Services",
            "type":"Services"
        }
    ],
    "sg:phone":"+61 2 9518 7022",
    "sg:postcode":"2009",
    "sg:province":"NSW",
    "sg:tags":[
        "management",
        "event"
    ],
    "wof:name":"Impetus TADW",
    "wof:placetype":"venue"
},
  "geometry": {"coordinates":[151.19436645499999,-33.8706703186],"type":"Point"}
}