{
  "type": "Feature",
  "properties": {
    "iso:country":"AU",
    "sg:address":"Shop 6 Brisbane Water Drv",
    "sg:city":"Gosford West",
    "sg:classifiers":[
        {
            "category":"Fast Food",
            "type":"Food & Drink"
        }
    ],
    "sg:phone":"+61 2 4324 4567",
    "sg:postcode":"2250",
    "sg:province":"NSW",
    "sg:tags":[
        "away",
        "take"
    ],
    "wof:name":"Saltwater Quality Seafoods West Gosford",
    "wof:placetype":"venue"
},
  "geometry": {"coordinates":[151.32684326200001,-33.4478302002],"type":"Point"}
}