{
  "type": "Feature",
  "properties": {
    "addr:full":"152 Sieben Drv Orange NSW 2800",
    "addr:housenumber":"152",
    "addr:postcode":"2800",
    "addr:street":"Sieben Drv",
    "iso:country":"AU",
    "sg:address":"152 Sieben Drv",
    "sg:city":"Orange",
    "sg:classifiers":[
        {
            "category":"Health Services",
            "subcategory":"Nursing And Care Facility",
            "type":"Services"
        }
    ],
    "sg:phone":"+61 2 6361 9228",
    "sg:postcode":"2800",
    "sg:province":"NSW",
    "sg:tags":[
        "home"
    ],
    "wof:name":"Cherrywood Grove Residential Aged Care Facility",
    "wof:placetype":"venue"
},
  "geometry": {"coordinates":[149.076904297,-33.2711906433],"type":"Point"}
}