{
  "type": "Feature",
  "properties": {
    "addr:full":"Taree City Centre, Manning St Taree NSW 2430",
    "addr:postcode":"2430",
    "addr:street":"Manning St",
    "iso:country":"AU",
    "sg:address":"Taree City Centre, Manning St",
    "sg:city":"Taree",
    "sg:classifiers":[
        {
            "category":"Utilities",
            "subcategory":"Mobile Phone",
            "type":"Services"
        }
    ],
    "sg:phone":"+61 2 6551 4177",
    "sg:postcode":"2430",
    "sg:province":"NSW",
    "sg:tags":[
        "repair",
        "telephone"
    ],
    "wof:name":"Network Communications",
    "wof:placetype":"venue"
},
  "geometry": {"coordinates":[152.46215799999999,-31.91324],"type":"Point"}
}