{
  "type": "Feature",
  "properties": {
    "addr:full":"5 Johns St Koolewong NSW 2256",
    "addr:housenumber":"5",
    "addr:postcode":"2256",
    "addr:street":"Johns St",
    "iso:country":"AU",
    "sg:address":"5 Johns St",
    "sg:city":"Koolewong",
    "sg:classifiers":[
        {
            "category":"Building & Trades",
            "subcategory":"Cleaning & Sanitation",
            "type":"Services"
        }
    ],
    "sg:phone":"+61 2 4341 6982",
    "sg:postcode":"2256",
    "sg:province":"NSW",
    "sg:tags":[
        "cleaner",
        "repairer",
        "roof"
    ],
    "wof:name":"MP Roofing",
    "wof:placetype":"venue"
},
  "geometry": {"coordinates":[151.321868897,-33.4739456177],"type":"Point"}
}