{
  "type": "Feature",
  "properties": {
    "iso:country":"AU",
    "sg:address":"3B 128 Old Pittwater Rd",
    "sg:city":"Brookvale",
    "sg:classifiers":[
        {
            "category":"Home & Garden",
            "subcategory":"Building Materials",
            "type":"Retail Goods"
        }
    ],
    "sg:phone":"+61 2 9905 0010",
    "sg:postcode":"2100",
    "sg:province":"NSW",
    "sg:tags":[
        "lawn",
        "cutting",
        "maintenance"
    ],
    "wof:name":"Continuumusic",
    "wof:placetype":"venue"
},
  "geometry": {"coordinates":[151.261917114,-33.7673149109],"type":"Point"}
}