{
  "type": "Feature",
  "properties": {
    "addr:full":"Upper Level 66 Owen St Huskisson NSW 2540",
    "addr:housenumber":"66",
    "addr:postcode":"2540",
    "addr:street":"Owen St",
    "iso:country":"AU",
    "sg:address":"Upper Level 66 Owen St",
    "sg:city":"Huskisson",
    "sg:classifiers":[
        {
            "category":"Education",
            "subcategory":"Vocational School",
            "type":"Public Place"
        }
    ],
    "sg:phone":"+61 2 4441 6902",
    "sg:postcode":"2540",
    "sg:province":"NSW",
    "sg:tags":[
        "beauty"
    ],
    "wof:name":"Resort To Beauty Salon & Training Academy",
    "wof:placetype":"venue"
},
  "geometry": {"coordinates":[150.66868591299999,-35.0386314392],"type":"Point"}
}