{
  "type": "Feature",
  "properties": {
    "addr:full":"Karangi Ave Whalan NSW 2770",
    "addr:postcode":"2770",
    "addr:street":"Karangi Ave Whalan",
    "iso:country":"AU",
    "sg:address":"Karangi Ave",
    "sg:city":"Whalan",
    "sg:classifiers":[
        {
            "category":"Social Services",
            "subcategory":"Child Care",
            "type":"Services"
        }
    ],
    "sg:phone":"+61 2 9625 9623",
    "sg:postcode":"2770",
    "sg:province":"NSW",
    "sg:tags":[
        "support",
        "health"
    ],
    "wof:name":"Early Childhood Health Centres",
    "wof:placetype":"venue"
},
  "geometry": {"coordinates":[150.810638428,-33.7535324097],"type":"Point"}
}