{
  "type": "Feature",
  "properties": {
    "addr:full":"Shop E/ 8 Torrens Rd Caboolture QLD 4510",
    "addr:housenumber":"8",
    "addr:postcode":"4510",
    "addr:street":"Torrens Rd",
    "iso:country":"AU",
    "sg:address":"Shop E/ 8 Torrens Rd",
    "sg:city":"Caboolture",
    "sg:classifiers":[
        {
            "category":"Recreation",
            "subcategory":"Amusement Park",
            "type":"Entertainment"
        }
    ],
    "sg:phone":"+61 7 5428 3333",
    "sg:postcode":"4510",
    "sg:province":"QLD",
    "wof:name":"Hippo's House",
    "wof:placetype":"venue"
},
  "geometry": {"coordinates":[152.94798299999999,-27.097322],"type":"Point"}
}