{
  "type": "Feature",
  "properties": {
    "iso:country":"AU",
    "sg:address":"10 Cameron St",
    "sg:city":"Fairfield",
    "sg:classifiers":[
        {
            "category":"Organizations",
            "subcategory":"Non-profit Organization",
            "type":"Services"
        }
    ],
    "sg:phone":"+61 7 3846 1258",
    "sg:postcode":"4103",
    "sg:province":"QLD",
    "sg:tags":[
        "support",
        "disability",
        "organisation"
    ],
    "wof:name":"Aid For The Blind Inc",
    "wof:placetype":"venue"
},
  "geometry": {"coordinates":[153.02737426799999,-27.503452301],"type":"Point"}
}