{
  "type": "Feature",
  "properties": {
    "addr:full":"6 Whittaker Crt Alice Springs NT 0870",
    "addr:housenumber":"6",
    "addr:postcode":"nt 0870",
    "addr:street":"Whittaker Crt",
    "iso:country":"AU",
    "sg:address":"6 Whittaker Crt",
    "sg:city":"Alice Springs",
    "sg:classifiers":[
        {
            "category":"Industrial Area",
            "type":"Public Place"
        }
    ],
    "sg:phone":"+61 8 8952 2878",
    "sg:postcode":"0870",
    "sg:province":"NT",
    "sg:tags":[
        "protective",
        "clothing"
    ],
    "wof:name":"Lawrence & Hanson",
    "wof:placetype":"venue"
},
  "geometry": {"coordinates":[133.87690734899999,-23.6961078644],"type":"Point"}
}