{
  "type": "Feature",
  "properties": {
    "addr:full":"Shop 7 120 Ashford Ave Milperra NSW 2214",
    "addr:housenumber":"shop 7 120",
    "addr:postcode":"2214",
    "addr:street":"Ashford Ave",
    "iso:country":"AU",
    "sg:address":"Shop 7 120 Ashford Ave",
    "sg:city":"Milperra",
    "sg:classifiers":[
        {
            "category":"Food & Beverages",
            "subcategory":"Bakery",
            "type":"Retail Goods"
        }
    ],
    "sg:phone":"+61 2 9771 2888",
    "sg:postcode":"2214",
    "sg:province":"NSW",
    "sg:tags":[
        "baker"
    ],
    "wof:name":"Milperra Bakehouse",
    "wof:placetype":"venue"
},
  "geometry": {"coordinates":[150.98909,-33.937889],"type":"Point"}
}