{
  "type": "Feature",
  "properties": {
    "addr:full":"1 Fern Pl Byron Bay NSW 2481",
    "addr:housenumber":"1",
    "addr:postcode":"2481",
    "addr:street":"Fern Pl",
    "iso:country":"AU",
    "sg:address":"1 Fern Pl",
    "sg:city":"Byron Bay",
    "sg:classifiers":[
        {
            "category":"Banks & Credit Unions",
            "subcategory":"Bank",
            "type":"Services"
        }
    ],
    "sg:phone":"+61 418 250 993",
    "sg:postcode":"2481",
    "sg:province":"NSW",
    "sg:tags":[
        "equipment",
        "sale",
        "point"
    ],
    "wof:name":"Byron Office Supplies",
    "wof:placetype":"venue"
},
  "geometry": {"coordinates":[153.58660888700001,-28.6353187561],"type":"Point"}
}