{
  "type": "Feature",
  "properties": {
    "addr:full":"Suite 9, 1st Floor 365 Kingsway St Caringbah NSW 2229",
    "addr:housenumber":"365",
    "addr:postcode":"2229",
    "addr:street":"Kingsway St",
    "iso:country":"AU",
    "sg:address":"Suite 9, 1st Floor 365 Kingsway St",
    "sg:city":"Caringbah",
    "sg:classifiers":[
        {
            "category":"Shopping",
            "subcategory":"Bridal",
            "type":"Retail Goods"
        }
    ],
    "sg:phone":"+61 2 9531 1223",
    "sg:postcode":"2229",
    "sg:province":"NSW",
    "sg:tags":[
        "hire",
        "wear"
    ],
    "wof:name":"Audrey Jillian Bridalwear",
    "wof:placetype":"venue"
},
  "geometry": {"coordinates":[151.12094116200001,-34.0403366089],"type":"Point"}
}