{
  "type": "Feature",
  "properties": {
    "iso:country":"AU",
    "sg:address":"82 Ryrie St",
    "sg:city":"Geelong",
    "sg:classifiers":[
        {
            "category":"Real Estate",
            "subcategory":"Real Estate Agent",
            "type":"Services"
        }
    ],
    "sg:phone":"+61 3 5221 6411",
    "sg:postcode":"3220",
    "sg:province":"VIC",
    "wof:name":"Wilson Pride",
    "wof:placetype":"venue"
},
  "geometry": {"coordinates":[144.356934,-38.148659],"type":"Point"}
}