{
  "type": "Feature",
  "properties": {
    "addr:full":"82 Newman St Wangaratta VIC 3677",
    "addr:housenumber":"82",
    "addr:postcode":"3677",
    "addr:street":"Newman St",
    "iso:country":"AU",
    "sg:address":"82 Newman St",
    "sg:city":"Wangaratta",
    "sg:classifiers":[
        {
            "category":"Freight",
            "type":"Transportation"
        }
    ],
    "sg:phone":"+61 1300 139 806",
    "sg:postcode":"3677",
    "sg:province":"VIC",
    "sg:tags":[
        "light",
        "carrier"
    ],
    "wof:name":"Vic Fast Couriers",
    "wof:placetype":"venue"
},
  "geometry": {"coordinates":[146.30389404300001,-36.3651924133],"type":"Point"}
}