{
  "type": "Feature",
  "properties": {
    "addr:full":"685 Mickleham Rd Greenvale VIC 3059",
    "addr:housenumber":"685",
    "addr:postcode":"3059",
    "addr:street":"Mickleham Rd",
    "iso:country":"AU",
    "sg:address":"685 Mickleham Rd",
    "sg:city":"Greenvale",
    "sg:classifiers":[
        {
            "category":"Home & Garden",
            "subcategory":"Garden Supply",
            "type":"Retail Goods"
        }
    ],
    "sg:phone":"+61 3 9333 3736",
    "sg:postcode":"3059",
    "sg:province":"VIC",
    "sg:tags":[
        "landscape"
    ],
    "wof:name":"Palm Place Nursery",
    "wof:placetype":"venue"
},
  "geometry": {"coordinates":[144.879348755,-37.6496543884],"type":"Point"}
}