{
  "type": "Feature",
  "properties": {
    "addr:full":"Unit 2, 32 Howson Way Bibra Lake WA 6163",
    "addr:housenumber":"32",
    "addr:postcode":"6163",
    "addr:street":"Howson Way",
    "iso:country":"AU",
    "sg:address":"Unit 2, 32",
    "sg:city":"Howson Way Bibra Lake",
    "sg:classifiers":[
        {
            "category":"Building & Trades",
            "subcategory":"Construction",
            "type":"Services"
        }
    ],
    "sg:phone":"+61 8 9434 6688",
    "sg:postcode":"6163",
    "sg:province":"WA",
    "sg:tags":[
        "plasterboard",
        "plasterer",
        "fixer"
    ],
    "wof:name":"Hamilton Plasterers",
    "wof:placetype":"venue"
},
  "geometry": {"coordinates":[115.80748,-32.111118],"type":"Point"}
}