{
  "type": "Feature",
  "properties": {
    "addr:full":"89 Pangee St Nyngan NSW 2825",
    "addr:housenumber":"89",
    "addr:postcode":"2825",
    "addr:street":"Pangee St",
    "iso:country":"AU",
    "sg:address":"89 Pangee St",
    "sg:city":"Nyngan",
    "sg:classifiers":[
        {
            "category":"Travel",
            "subcategory":"Hotels & Motels",
            "type":"Entertainment"
        }
    ],
    "sg:phone":"+61 2 6832 1535",
    "sg:postcode":"2825",
    "sg:province":"NSW",
    "wof:name":"Overlander Hotel Motel",
    "wof:placetype":"venue"
},
  "geometry": {"coordinates":[147.195022583,-31.5625076294],"type":"Point"}
}