{
  "type": "Feature",
  "properties": {
    "iso:country":"AU",
    "sg:address":"Gongflers Drv",
    "sg:city":"Kangaroo Ground",
    "sg:classifiers":[
        {
            "category":"Real Estate",
            "subcategory":"Architect",
            "type":"Services"
        }
    ],
    "sg:phone":"+61 3 9712 0547",
    "sg:postcode":"3097",
    "sg:province":"VIC",
    "wof:name":"Henry Ross",
    "wof:placetype":"venue"
},
  "geometry": {"coordinates":[145.280975342,-37.7116737366],"type":"Point"}
}