{
  "type": "Feature",
  "properties": {
    "addr:full":"PO Box 1216 Tewantin QLD 4565",
    "addr:postcode":"4565",
    "iso:country":"AU",
    "sg:address":"PO Box 1216",
    "sg:city":"Tewantin",
    "sg:classifiers":[
        {
            "category":"Government",
            "subcategory":"Fire Station",
            "type":"Public Place"
        }
    ],
    "sg:phone":"+61 7 5449 8013",
    "sg:postcode":"4565",
    "sg:province":"QLD",
    "sg:tags":[
        "equipment",
        "protection",
        "consultant"
    ],
    "wof:name":"Northcoast Fire Protection",
    "wof:placetype":"venue"
},
  "geometry": {"coordinates":[153.02789306599999,-26.3908996582],"type":"Point"}
}