{
  "type": "Feature",
  "properties": {
    "addr:full":"7 Walker Pl Church Point NSW 2105",
    "addr:housenumber":"7",
    "addr:postcode":"2105",
    "addr:street":"Walker Pl",
    "iso:country":"AU",
    "sg:address":"7 Walker Pl",
    "sg:city":"Church Point",
    "sg:classifiers":[
        {
            "category":"Utilities",
            "subcategory":"Electric",
            "type":"Services"
        }
    ],
    "sg:phone":"+61 2 9997 7473",
    "sg:postcode":"2105",
    "sg:province":"NSW",
    "sg:tags":[
        "electrical",
        "contractor"
    ],
    "wof:name":"W & L Holloway Electrical",
    "wof:placetype":"venue"
},
  "geometry": {"coordinates":[151.27749600000001,-33.652328],"type":"Point"}
}