{
  "type": "Feature",
  "properties": {
    "addr:full":"Tulloch Ave Concord Concord NSW 2137",
    "addr:postcode":"2137",
    "addr:street":"Tulloch Ave",
    "iso:country":"AU",
    "sg:address":"Tulloch Ave",
    "sg:city":"Concord Concord",
    "sg:classifiers":[
        {
            "category":"Retail",
            "subcategory":"Auto Rental",
            "type":"Services"
        }
    ],
    "sg:phone":"+61 402 013 198",
    "sg:postcode":"2137",
    "sg:province":"NSW",
    "sg:tags":[
        "chauffeur",
        "car",
        "hire",
        "driven",
        "limousine"
    ],
    "wof:name":"All Minibus Affairs",
    "wof:placetype":"venue"
},
  "geometry": {"coordinates":[151.08903503400001,-33.8357505798],"type":"Point"}
}