{
  "type": "Feature",
  "properties": {
    "iso:country":"AU",
    "sg:address":"14a Denis St",
    "sg:city":"St Marys",
    "sg:classifiers":[
        {
            "category":"Wholesale",
            "subcategory":"Painting Supplies",
            "type":"Manufacturing & Wholesale Goods"
        }
    ],
    "sg:phone":"+61 8 8276 4611",
    "sg:postcode":"5042",
    "sg:province":"SA",
    "sg:tags":[
        "equipment",
        "spraying"
    ],
    "wof:name":"Charmans Spray & Powder Equipment",
    "wof:placetype":"venue"
},
  "geometry": {"coordinates":[138.57771299999999,-34.997883],"type":"Point"}
}