{
  "type": "Feature",
  "properties": {
    "addr:full":"204 Corio St Shepparton VIC 3630",
    "addr:housenumber":"204",
    "addr:postcode":"3630",
    "addr:street":"Corio St",
    "iso:country":"AU",
    "sg:address":"204 Corio St",
    "sg:city":"Shepparton",
    "sg:classifiers":[
        {
            "category":"Communications",
            "type":"Services"
        }
    ],
    "sg:phone":"+61 3 5822 1083",
    "sg:postcode":"3630",
    "sg:province":"VIC",
    "sg:tags":[
        "public",
        "system",
        "address"
    ],
    "wof:name":"Elite Sound & Vision",
    "wof:placetype":"venue"
},
  "geometry": {"coordinates":[145.40275573700001,-36.3832626343],"type":"Point"}
}