{
  "type": "Feature",
  "properties": {
    "iso:country":"AU",
    "sg:address":"5 Rosewall Crt",
    "sg:city":"Wantirna South",
    "sg:classifiers":[
        {
            "category":"Home & Garden",
            "subcategory":"Building Materials",
            "type":"Retail Goods"
        }
    ],
    "sg:phone":"+61 3 9801 3240",
    "sg:postcode":"3152",
    "sg:province":"VIC",
    "sg:tags":[
        "lawn",
        "cutting",
        "maintenance"
    ],
    "wof:name":"Robert Jenkins Lawn Mowing Service",
    "wof:placetype":"venue"
},
  "geometry": {"coordinates":[145.22622680699999,-37.8877334595],"type":"Point"}
}