{
  "type": "Feature",
  "properties": {
    "iso:country":"AU",
    "sg:address":"61 Gipps St",
    "sg:city":"Collingwood",
    "sg:classifiers":[
        {
            "category":"Real Estate",
            "subcategory":"Architect",
            "type":"Services"
        }
    ],
    "sg:phone":"+61 3 9417 7967",
    "sg:postcode":"3066",
    "sg:province":"VIC",
    "wof:name":"Rationale Design",
    "wof:placetype":"venue"
},
  "geometry": {"coordinates":[144.98905944800001,-37.8048057556],"type":"Point"}
}