{
  "type": "Feature",
  "properties": {
    "addr:full":"202a Creswick Rd Ballarat VIC 3350",
    "addr:housenumber":"202a",
    "addr:postcode":"3350",
    "addr:street":"Creswick Rd",
    "iso:country":"AU",
    "sg:address":"202a Creswick Rd",
    "sg:city":"Ballarat",
    "sg:classifiers":[
        {
            "category":"Insurance",
            "subcategory":"Hazard Insurance",
            "type":"Services"
        }
    ],
    "sg:phone":"+61 3 5333 2300",
    "sg:postcode":"3350",
    "sg:province":"VIC",
    "sg:tags":[
        "loss",
        "adjuster",
        "assessor"
    ],
    "wof:name":"RVLA Group",
    "wof:placetype":"venue"
},
  "geometry": {"coordinates":[143.85333299999999,-37.553459],"type":"Point"}
}