{
  "type": "Feature",
  "properties": {
    "addr:full":"54 Honey's La King Valley VIC 3678",
    "addr:housenumber":"54",
    "addr:postcode":"3678",
    "addr:street":"Honey'S La",
    "iso:country":"AU",
    "sg:address":"54 Honey's La",
    "sg:city":"King Valley",
    "sg:classifiers":[
        {
            "category":"Farming",
            "subcategory":"Vineyard",
            "type":"Manufacturing & Wholesale Goods"
        }
    ],
    "sg:phone":"+61 3 5729 3615",
    "sg:postcode":"3678",
    "sg:province":"VIC",
    "sg:tags":[
        "winery"
    ],
    "wof:name":"La Cantina King Valley Corsini Vineyard",
    "wof:placetype":"venue"
},
  "geometry": {"coordinates":[146.418991089,-36.6783294678],"type":"Point"}
}