{
  "type": "Feature",
  "properties": {
    "addr:full":"PO Box 1223 Lane Cove NSW 1595",
    "addr:postcode":"1595",
    "iso:country":"AU",
    "sg:address":"PO Box 1223",
    "sg:city":"Lane Cove",
    "sg:classifiers":[
        {
            "category":"Professional",
            "subcategory":"Detective & Security Services",
            "type":"Services"
        }
    ],
    "sg:phone":"+61 411 348 632",
    "sg:postcode":"1595",
    "sg:province":"NSW",
    "sg:tags":[
        "consultant",
        "system"
    ],
    "wof:name":"MCC Security",
    "wof:placetype":"venue"
},
  "geometry": {"coordinates":[151.16871643100001,-33.8146018982],"type":"Point"}
}