{
  "type": "Feature",
  "properties": {
    "addr:full":"18 Advance St Schofields NSW 2762",
    "addr:housenumber":"18",
    "addr:postcode":"2762",
    "addr:street":"Advance St",
    "iso:country":"AU",
    "sg:address":"18 Advance St",
    "sg:city":"Schofields",
    "sg:classifiers":[
        {
            "category":"Home & Garden",
            "subcategory":"Building Materials",
            "type":"Retail Goods"
        }
    ],
    "sg:phone":"+61 2 9627 2528",
    "sg:postcode":"2762",
    "sg:province":"NSW",
    "sg:tags":[
        "insect",
        "screen"
    ],
    "wof:name":"Elandee Screens",
    "wof:placetype":"venue"
},
  "geometry": {"coordinates":[150.87298584000001,-33.6976776123],"type":"Point"}
}