{
  "type": "Feature",
  "properties": {
    "iso:country":"AU",
    "sg:address":"66 Gibbes St",
    "sg:city":"Chatswood",
    "sg:classifiers":[
        {
            "category":"Professional",
            "subcategory":"Detective & Security Services",
            "type":"Services"
        }
    ],
    "sg:phone":"+61 2 9417 5522",
    "sg:postcode":"2067",
    "sg:province":"NSW",
    "sg:tags":[
        "consultant",
        "system"
    ],
    "wof:name":"Electronic Security Pty Ltd",
    "wof:placetype":"venue"
},
  "geometry": {"coordinates":[151.198684692,-33.78673172],"type":"Point"}
}