{
  "type": "Feature",
  "properties": {
    "addr:full":"Eastlands Shopping Centre Bligh St Bellerive TAS 7018",
    "addr:postcode":"7018",
    "addr:street":"Bligh St",
    "iso:country":"AU",
    "sg:address":"Eastlands Shopping Centre Bligh St",
    "sg:city":"Bellerive",
    "sg:classifiers":[
        {
            "category":"Fast Food",
            "type":"Food & Drink"
        }
    ],
    "sg:phone":"+61 3 6244 6699",
    "sg:postcode":"7018",
    "sg:province":"TAS",
    "sg:tags":[
        "away",
        "take"
    ],
    "wof:name":"Flying Wok The",
    "wof:placetype":"venue"
},
  "geometry": {"coordinates":[147.36836242699999,-42.8682937622],"type":"Point"}
}