{
  "type": "Feature",
  "properties": {
    "addr:full":"37 Wyoming Ave Burrill Lake NSW 2539",
    "addr:housenumber":"37",
    "addr:postcode":"2539",
    "addr:street":"Wyoming Ave",
    "iso:country":"AU",
    "sg:address":"37 Wyoming Ave",
    "sg:city":"Burrill Lake",
    "sg:classifiers":[
        {
            "category":"Home & Garden",
            "subcategory":"Building Materials",
            "type":"Retail Goods"
        }
    ],
    "sg:phone":"+61 2 4455 4434",
    "sg:postcode":"2539",
    "sg:province":"NSW",
    "sg:tags":[
        "lawn",
        "cutting",
        "maintenance"
    ],
    "wof:name":"Grass- Hopper Mowing & Maintenance",
    "wof:placetype":"venue"
},
  "geometry": {"coordinates":[150.434036255,-35.3906364441],"type":"Point"}
}