{
  "type": "Feature",
  "properties": {
    "iso:country":"AU",
    "sg:address":"93 Miller St",
    "sg:city":"Epping",
    "sg:classifiers":[
        {
            "category":"Transit Center",
            "subcategory":"Freight",
            "type":"Transportation"
        }
    ],
    "sg:phone":"+61 3 9408 7255",
    "sg:postcode":"3076",
    "sg:province":"VIC",
    "sg:tags":[
        "equipment",
        "transport",
        "road",
        "vehicle"
    ],
    "wof:name":"Convair Engineering Pty Ltd",
    "wof:placetype":"venue"
},
  "geometry": {"coordinates":[144.989746094,-37.7512626648],"type":"Point"}
}