{
  "type": "Feature",
  "properties": {
    "iso:country":"AU",
    "sg:address":"Suite C, Lvl 4, 251 Wharf Rd",
    "sg:city":"Newcastle",
    "sg:classifiers":[
        {
            "category":"Professional",
            "subcategory":"Employment Agencies",
            "type":"Services"
        }
    ],
    "sg:phone":"+61 2 4925 3663",
    "sg:postcode":"2300",
    "sg:province":"NSW",
    "wof:name":"Hays",
    "wof:placetype":"venue"
},
  "geometry": {"coordinates":[151.778458,-32.925819],"type":"Point"}
}