{
  "type": "Feature",
  "properties": {
    "addr:full":"Shop 3, 144 Maryland Drv Maryland NSW 2287",
    "addr:housenumber":"shop 3 144",
    "addr:postcode":"2287",
    "addr:street":"Maryland Drv",
    "iso:country":"AU",
    "sg:address":"Shop 3, 144 Maryland Drv",
    "sg:city":"Maryland",
    "sg:classifiers":[
        {
            "category":"Personal",
            "subcategory":"Beauty Salon",
            "type":"Services"
        }
    ],
    "sg:phone":"+61 2 4955 5887",
    "sg:postcode":"2287",
    "sg:province":"NSW",
    "sg:tags":[
        "hairdresser"
    ],
    "wof:name":"Fusion Hair Nail & Beauty Maryland",
    "wof:placetype":"venue"
},
  "geometry": {"coordinates":[151.660354614,-32.8799934387],"type":"Point"}
}