{
  "type": "Feature",
  "properties": {
    "iso:country":"AU",
    "sg:address":"9 Machinery Ave",
    "sg:city":"Kawana Waters",
    "sg:classifiers":[
        {
            "category":"Home & Garden",
            "subcategory":"Hardware",
            "type":"Retail Goods"
        }
    ],
    "sg:phone":"+61 7 5493 9916",
    "sg:postcode":"4575",
    "sg:province":"QLD",
    "sg:tags":[
        "part",
        "air conditioning"
    ],
    "wof:name":"Air Additions",
    "wof:placetype":"venue"
},
  "geometry": {"coordinates":[153.123886,-26.729637],"type":"Point"}
}