{
  "type": "Feature",
  "properties": {
    "iso:country":"AU",
    "sg:address":"303B Inlet Rd",
    "sg:city":"Bolwarra",
    "sg:classifiers":[
        {
            "category":"Mining & Drilling",
            "type":"Manufacturing & Wholesale Goods"
        }
    ],
    "sg:phone":"+61 412 450 226",
    "sg:postcode":"2320",
    "sg:province":"NSW",
    "sg:tags":[
        "geologist"
    ],
    "wof:name":"Tamplin Resources P/L",
    "wof:placetype":"venue"
},
  "geometry": {"coordinates":[151.568725586,-32.7139511108],"type":"Point"}
}