{
  "type": "Feature",
  "properties": {
    "iso:country":"AU",
    "sg:address":"125 Brisbane St",
    "sg:city":"Tamworth",
    "sg:classifiers":[
        {
            "category":"Health Services",
            "subcategory":"Chiropractor",
            "type":"Services"
        }
    ],
    "sg:phone":"+61 2 6766 1522",
    "sg:postcode":"2340",
    "sg:province":"NSW",
    "wof:name":"Tamworth Chiropractic Centre",
    "wof:placetype":"venue"
},
  "geometry": {"coordinates":[150.93356323200001,-31.0873718262],"type":"Point"}
}