{
  "type": "Feature",
  "properties": {
    "addr:full":"107 Wombat St Young NSW 2594",
    "addr:housenumber":"107",
    "addr:postcode":"2594",
    "addr:street":"Wombat St",
    "iso:country":"AU",
    "sg:address":"107 Wombat St",
    "sg:city":"Young",
    "sg:classifiers":[
        {
            "category":"Building & Trades",
            "subcategory":"Pest Control",
            "type":"Services"
        }
    ],
    "sg:phone":"+61 2 6382 6675",
    "sg:postcode":"2594",
    "sg:province":"NSW",
    "wof:name":"M & L Donnelly",
    "wof:placetype":"venue"
},
  "geometry": {"coordinates":[148.29338073700001,-34.3265533447],"type":"Point"}
}