{
  "type": "Feature",
  "properties": {
    "addr:full":"Shop 218 Foodcourt Bdwy Ultimo NSW 2007",
    "addr:housenumber":"218",
    "addr:postcode":"2007",
    "addr:street":"Foodcourt Bdwy",
    "iso:country":"AU",
    "sg:address":"Shop 218",
    "sg:city":"Foodcourt Bdwy Ultimo",
    "sg:classifiers":[
        {
            "category":"Fast Food",
            "type":"Food & Drink"
        }
    ],
    "sg:phone":"+61 2 9281 6565",
    "sg:postcode":"2007",
    "sg:province":"NSW",
    "sg:tags":[
        "away",
        "take"
    ],
    "wof:name":"A La Turko Kebabs",
    "wof:placetype":"venue"
},
  "geometry": {"coordinates":[151.19728088400001,-33.8817901611],"type":"Point"}
}