{
  "type": "Feature",
  "properties": {
    "iso:country":"AU",
    "sg:address":"70 Sylvan Rd",
    "sg:city":"Toowong",
    "sg:classifiers":[
        {
            "category":"Real Estate",
            "subcategory":"Real Estate Agent",
            "type":"Services"
        }
    ],
    "sg:phone":"+61 7 3858 8888",
    "sg:postcode":"4066",
    "sg:province":"QLD",
    "wof:name":"Dixon Johnston Quality Property",
    "wof:placetype":"venue"
},
  "geometry": {"coordinates":[152.99067688,-27.4807891846],"type":"Point"}
}