{
  "type": "Feature",
  "properties": {
    "iso:country":"AU",
    "sg:address":"66 Robinson St",
    "sg:city":"Carnarvon",
    "sg:classifiers":[
        {
            "category":"Autos & Motor Vehicles",
            "subcategory":"Automobile Sales",
            "type":"Retail Goods"
        }
    ],
    "sg:phone":"+61 8 9941 1397",
    "sg:postcode":"6701",
    "sg:province":"WA",
    "sg:tags":[
        "car",
        "new"
    ],
    "wof:name":"Dellbar Motors",
    "wof:placetype":"venue"
},
  "geometry": {"coordinates":[113.65901947,-24.8817825317],"type":"Point"}
}