{
  "type": "Feature",
  "properties": {
    "addr:full":"450 Melbourne Rd Newport VIC 3015",
    "addr:housenumber":"450",
    "addr:postcode":"3015",
    "addr:street":"Melbourne Rd",
    "iso:country":"AU",
    "sg:address":"450 Melbourne Rd",
    "sg:city":"Newport",
    "sg:classifiers":[
        {
            "category":"Fast Food",
            "type":"Food & Drink"
        }
    ],
    "sg:phone":"+61 3 9391 2640",
    "sg:postcode":"3015",
    "sg:province":"VIC",
    "sg:tags":[
        "away",
        "take"
    ],
    "wof:name":"KFC",
    "wof:placetype":"venue"
},
  "geometry": {"coordinates":[144.883056641,-37.840297699],"type":"Point"}
}