{
  "type": "Feature",
  "properties": {
    "iso:country":"AU",
    "sg:address":"73 Rainbow St",
    "sg:city":"Sandgate",
    "sg:classifiers":[
        {
            "category":"Professional",
            "subcategory":"Printing & Photocopies",
            "type":"Services"
        }
    ],
    "sg:phone":"+61 7 3869 0906",
    "sg:postcode":"4017",
    "sg:province":"QLD",
    "sg:tags":[
        "plaque"
    ],
    "wof:name":"A.S.A.P. Badges",
    "wof:placetype":"venue"
},
  "geometry": {"coordinates":[153.06831359899999,-27.3215045929],"type":"Point"}
}