{
  "type": "Feature",
  "properties": {
    "addr:full":"1 24 Carrick Drv Tullamarine VIC 3043",
    "addr:housenumber":"24",
    "addr:postcode":"3043",
    "addr:street":"1;Carrick Drv",
    "iso:country":"AU",
    "sg:address":"1 24 Carrick Drv",
    "sg:city":"Tullamarine",
    "sg:classifiers":[
        {
            "category":"Recreation",
            "subcategory":"Amusement Park",
            "type":"Entertainment"
        }
    ],
    "sg:phone":"+61 3 9335 3755",
    "sg:postcode":"3043",
    "sg:province":"VIC",
    "wof:name":"Darkzone Entertainment Centres",
    "wof:placetype":"venue"
},
  "geometry": {"coordinates":[144.886032105,-37.7000923157],"type":"Point"}
}