{
  "type": "Feature",
  "properties": {
    "iso:country":"AU",
    "sg:address":"10 Stacey St",
    "sg:city":"Crafers",
    "sg:classifiers":[
        {
            "category":"Home & Garden",
            "subcategory":"Carpets & Floor Coverings",
            "type":"Retail Goods"
        }
    ],
    "sg:phone":"+61 408 829 165",
    "sg:postcode":"5152",
    "sg:province":"SA",
    "sg:tags":[
        "tile",
        "wall",
        "layer"
    ],
    "wof:name":"Rod Dent Tiling, Painting & General Maintenance",
    "wof:placetype":"venue"
},
  "geometry": {"coordinates":[138.73042297399999,-34.9892616272],"type":"Point"}
}