{
  "type": "Feature",
  "properties": {
    "iso:country":"AU",
    "sg:address":"Lvl 3, 20 Wharf St",
    "sg:city":"Brisbane",
    "sg:classifiers":[
        {
            "category":"Insurance",
            "subcategory":"Insurance Agent",
            "type":"Services"
        }
    ],
    "sg:phone":"+61 7 3002 7300",
    "sg:postcode":"4000",
    "sg:province":"QLD",
    "sg:tags":[
        "broker"
    ],
    "wof:name":"New Summit Insurance Brokers Pty Ltd",
    "wof:placetype":"venue"
},
  "geometry": {"coordinates":[153.029907227,-27.4654884338],"type":"Point"}
}