{
  "type": "Feature",
  "properties": {
    "iso:country":"AU",
    "sg:address":"Municipal Offices, 25 Cedric St",
    "sg:city":"Stirling",
    "sg:classifiers":[
        {
            "category":"Government",
            "subcategory":"Department Of Motor Vehicles",
            "type":"Public Place"
        }
    ],
    "sg:phone":"+61 8 9345 8555",
    "sg:postcode":"6021",
    "sg:province":"WA",
    "sg:tags":[
        "organisation",
        "local"
    ],
    "wof:name":"Stirling City Of",
    "wof:placetype":"venue"
},
  "geometry": {"coordinates":[115.809242248,-31.8909873962],"type":"Point"}
}