{
  "type": "Feature",
  "properties": {
    "addr:full":"999 Fairfield Rd Yeerongpilly QLD 4105",
    "addr:housenumber":"999",
    "addr:postcode":"4105",
    "addr:street":"Fairfield Rd",
    "iso:country":"AU",
    "sg:address":"999 Fairfield Rd",
    "sg:city":"Yeerongpilly",
    "sg:classifiers":[
        {
            "category":"Building & Trades",
            "subcategory":"Equipment Rental",
            "type":"Services"
        }
    ],
    "sg:phone":"+61 7 3892 4836",
    "sg:postcode":"4105",
    "sg:province":"QLD",
    "sg:tags":[
        "hire",
        "catering"
    ],
    "wof:name":"GE SeaCo Australia Pty Ltd",
    "wof:placetype":"venue"
},
  "geometry": {"coordinates":[153.01150512699999,-27.5392284393],"type":"Point"}
}