{
  "type": "Feature",
  "properties": {
    "addr:full":"2 McDonald Crs Bassendean WA 6054",
    "addr:housenumber":"2",
    "addr:postcode":"6054",
    "addr:street":"Mcdonald Crs",
    "iso:country":"AU",
    "sg:address":"2 McDonald Crs",
    "sg:city":"Bassendean",
    "sg:classifiers":[
        {
            "category":"Home & Garden",
            "subcategory":"Hardware",
            "type":"Retail Goods"
        }
    ],
    "sg:phone":"+61 8 9279 1663",
    "sg:postcode":"6054",
    "sg:province":"WA",
    "sg:tags":[
        "compressor",
        "air"
    ],
    "wof:name":"Advance AutoQuip",
    "wof:placetype":"venue"
},
  "geometry": {"coordinates":[115.9401474,-31.9076423645],"type":"Point"}
}