{
  "type": "Feature",
  "properties": {
    "iso:country":"AU",
    "sg:address":"36 Wentworth St",
    "sg:city":"Port Kembla",
    "sg:classifiers":[
        {
            "category":"Personal",
            "subcategory":"Adult",
            "type":"Services"
        }
    ],
    "sg:phone":"+61 2 4274 4873",
    "sg:postcode":"2505",
    "sg:province":"NSW",
    "sg:tags":[
        "vic",
        "except",
        "state",
        "escort",
        "social",
        "qld"
    ],
    "wof:name":"Southern Belles",
    "wof:placetype":"venue"
},
  "geometry": {"coordinates":[150.900436,-34.479889],"type":"Point"}
}