{
  "type": "Feature",
  "properties": {
    "addr:full":"116 Mount Barker Rd Stirling SA 5152",
    "addr:housenumber":"116",
    "addr:postcode":"5152",
    "addr:street":"Mount Barker Rd",
    "iso:country":"AU",
    "sg:address":"116 Mount Barker Rd",
    "sg:city":"Stirling",
    "sg:classifiers":[
        {
            "category":"Real Estate",
            "subcategory":"Architect",
            "type":"Services"
        }
    ],
    "sg:phone":"+61 8 8370 9688",
    "sg:postcode":"5152",
    "sg:province":"SA",
    "wof:name":"Scrymgour Susan Design",
    "wof:placetype":"venue"
},
  "geometry": {"coordinates":[138.72244262699999,-35.0081291199],"type":"Point"}
}