{
  "type": "Feature",
  "properties": {
    "iso:country":"AU",
    "sg:address":"69 Station St",
    "sg:city":"Engadine",
    "sg:classifiers":[
        {
            "category":"Health Services",
            "subcategory":"Dentist",
            "type":"Services"
        }
    ],
    "sg:phone":"+61 2 9520 6348",
    "sg:postcode":"2233",
    "sg:province":"NSW",
    "wof:name":"Harper Steve",
    "wof:placetype":"venue"
},
  "geometry": {"coordinates":[151.01298523,-34.0657463074],"type":"Point"}
}