{
  "type": "Feature",
  "properties": {
    "addr:full":"6- 8 Were St Montmorency VIC 3094",
    "addr:housenumber":"8",
    "addr:postcode":"3094",
    "addr:street":"Were St",
    "iso:country":"AU",
    "sg:address":"6- 8 Were St",
    "sg:city":"Montmorency",
    "sg:classifiers":[
        {
            "category":"Communications",
            "subcategory":"Film & Video Production",
            "type":"Services"
        }
    ],
    "sg:phone":"+61 3 9434 3613",
    "sg:postcode":"3094",
    "sg:province":"VIC",
    "sg:tags":[
        "dvd",
        "library"
    ],
    "wof:name":"Civic Video Pty Ltd",
    "wof:placetype":"venue"
},
  "geometry": {"coordinates":[145.12121582,-37.7172775269],"type":"Point"}
}