{
  "type": "Feature",
  "properties": {
    "addr:full":"23 Trawool St Box Hill North VIC 3129",
    "addr:housenumber":"23",
    "addr:postcode":"3129",
    "addr:street":"Trawool St",
    "iso:country":"AU",
    "sg:address":"23 Trawool St",
    "sg:city":"Box Hill North",
    "sg:classifiers":[
        {
            "category":"Fast Food",
            "type":"Food & Drink"
        }
    ],
    "sg:phone":"+61 3 9890 7460",
    "sg:postcode":"3129",
    "sg:province":"VIC",
    "sg:tags":[
        "away",
        "take"
    ],
    "wof:name":"Trawool Fish & Chips",
    "wof:placetype":"venue"
},
  "geometry": {"coordinates":[145.133865356,-37.8061752319],"type":"Point"}
}