{
  "type": "Feature",
  "properties": {
    "iso:country":"AU",
    "sg:address":"29 Houghton Ave",
    "sg:city":"Redcliffe",
    "sg:classifiers":[
        {
            "category":"Professional",
            "subcategory":"Accounting & Tax Preparation",
            "type":"Services"
        }
    ],
    "sg:phone":"+61 7 3284 4993",
    "sg:postcode":"4020",
    "sg:province":"QLD",
    "sg:tags":[
        "consultant",
        "taxation"
    ],
    "wof:name":"Elliott M F",
    "wof:placetype":"venue"
},
  "geometry": {"coordinates":[153.102066,-27.228107],"type":"Point"}
}