{
  "type": "Feature",
  "properties": {
    "addr:full":"8 Hosken St Balwyn North VIC 3104",
    "addr:housenumber":"8",
    "addr:postcode":"3104",
    "addr:street":"Hosken St",
    "iso:country":"AU",
    "sg:address":"8 Hosken St",
    "sg:city":"Balwyn North",
    "sg:classifiers":[
        {
            "category":"Real Estate",
            "subcategory":"Architect",
            "type":"Services"
        }
    ],
    "sg:phone":"+61 3 9857 9011",
    "sg:postcode":"3104",
    "sg:province":"VIC",
    "sg:tags":[
        "naval"
    ],
    "wof:name":"Chapman Bryan & Associates Pty Ltd",
    "wof:placetype":"venue"
},
  "geometry": {"coordinates":[145.09129333499999,-37.8028678894],"type":"Point"}
}