{
  "type": "Feature",
  "properties": {
    "iso:country":"AU",
    "sg:address":"10 Mitchell St",
    "sg:city":"Kedron",
    "sg:classifiers":[
        {
            "category":"Building & Trades",
            "subcategory":"Construction",
            "type":"Services"
        }
    ],
    "sg:phone":"+61 7 3357 9440",
    "sg:postcode":"4031",
    "sg:province":"QLD",
    "sg:tags":[
        "scaffolding"
    ],
    "wof:name":"Urban Scaffolding",
    "wof:placetype":"venue"
},
  "geometry": {"coordinates":[153.030197,-27.408638],"type":"Point"}
}