{
  "type": "Feature",
  "properties": {
    "iso:country":"AU",
    "sg:address":"Bulli PCYC Princes Hwy",
    "sg:city":"Bulli",
    "sg:classifiers":[
        {
            "category":"Social Services",
            "subcategory":"Child Care",
            "type":"Services"
        }
    ],
    "sg:phone":"+61 2 4283 7184",
    "sg:postcode":"2516",
    "sg:province":"NSW",
    "wof:name":"Woonona/Bulli Out of School Hours Care",
    "wof:placetype":"venue"
},
  "geometry": {"coordinates":[150.9133,-34.333656],"type":"Point"}
}