{
  "type": "Feature",
  "properties": {
    "iso:country":"AU",
    "sg:address":"16 - 24",
    "sg:city":"Westall Rd, Clayton South",
    "sg:classifiers":[
        {
            "category":"Manufacturing",
            "subcategory":"Metals",
            "type":"Manufacturing & Wholesale Goods"
        }
    ],
    "sg:phone":"+61 3 8543 3666",
    "sg:postcode":"3169",
    "sg:province":"VIC",
    "sg:tags":[
        "wholesaler",
        "aluminium",
        "mfrs"
    ],
    "wof:name":"Smorgon Steel Distribution",
    "wof:placetype":"venue"
},
  "geometry": {"coordinates":[145.141311645,-37.937171936],"type":"Point"}
}