{
  "type": "Feature",
  "properties": {
    "addr:full":"15 Tatura Ave Gosford North NSW 2250",
    "addr:housenumber":"15",
    "addr:postcode":"2250",
    "addr:street":"Tatura Ave",
    "iso:country":"AU",
    "sg:address":"15 Tatura Ave",
    "sg:city":"Gosford North",
    "sg:phone":"+61 2 4323 2306",
    "sg:postcode":"2250",
    "sg:province":"NSW",
    "wof:name":"Green Point Tank Works",
    "wof:placetype":"venue"
},
  "geometry": {"coordinates":[151.341186523,-33.4109230042],"type":"Point"}
}