{
  "type": "Feature",
  "properties": {
    "addr:full":"1 Grebe St Aroona QLD 4551",
    "addr:housenumber":"1",
    "addr:postcode":"4551",
    "addr:street":"Grebe St",
    "iso:country":"AU",
    "sg:address":"1 Grebe St",
    "sg:city":"Aroona",
    "sg:classifiers":[
        {
            "category":"Utilities",
            "subcategory":"Water",
            "type":"Services"
        }
    ],
    "sg:phone":"+61 7 5492 5952",
    "sg:postcode":"4551",
    "sg:province":"QLD",
    "sg:tags":[
        "equipment",
        "treatment"
    ],
    "wof:name":"Aqua One",
    "wof:placetype":"venue"
},
  "geometry": {"coordinates":[153.11984252900001,-26.7888278961],"type":"Point"}
}