{
  "type": "Feature",
  "properties": {
    "addr:full":"463 Boundary Rd Richlands QLD 4077",
    "addr:housenumber":"463",
    "addr:postcode":"4077",
    "addr:street":"Boundary Rd",
    "iso:country":"AU",
    "sg:address":"463 Boundary Rd",
    "sg:city":"Richlands",
    "sg:classifiers":[
        {
            "category":"Wholesale",
            "subcategory":"Machinery & Supplies",
            "type":"Manufacturing & Wholesale Goods"
        }
    ],
    "sg:phone":"+61 7 3217 0444",
    "sg:postcode":"4077",
    "sg:province":"QLD",
    "sg:tags":[
        "equipment",
        "hydraulic"
    ],
    "wof:name":"Stauff Corporation Pty Ltd",
    "wof:placetype":"venue"
},
  "geometry": {"coordinates":[152.96510314899999,-27.5744228363],"type":"Point"}
}