{
  "type": "Feature",
  "properties": {
    "addr:full":"31 Mcharg Rd Happy Valley VIC 3351",
    "addr:housenumber":"31",
    "addr:postcode":"3351",
    "addr:street":"Mcharg Rd",
    "iso:country":"AU",
    "sg:address":"31 Mcharg Rd",
    "sg:city":"Happy Valley",
    "sg:classifiers":[
        {
            "category":"Farming",
            "subcategory":"Fish & Marine Products",
            "type":"Manufacturing & Wholesale Goods"
        }
    ],
    "sg:phone":"+61 8 8322 1068",
    "sg:postcode":"3351",
    "sg:province":"VIC",
    "sg:tags":[
        "supplier",
        "oyster",
        "farmer"
    ],
    "wof:name":"Shellfish Distributors",
    "wof:placetype":"venue"
},
  "geometry": {"coordinates":[143.58590699999999,-37.719105],"type":"Point"}
}