{
  "type": "Feature",
  "properties": {
    "iso:country":"AU",
    "sg:address":"49 Flinders St",
    "sg:city":"Lawson",
    "sg:classifiers":[
        {
            "category":"Wholesale",
            "subcategory":"Scrap",
            "type":"Manufacturing & Wholesale Goods"
        }
    ],
    "sg:phone":"+61 408 960 817",
    "sg:postcode":"2783",
    "sg:province":"NSW",
    "sg:tags":[
        "merchant",
        "metal"
    ],
    "wof:name":"Blue Mountains Metal Recyclers",
    "wof:placetype":"venue"
},
  "geometry": {"coordinates":[150.442306519,-33.7259750366],"type":"Point"}
}