{
  "type": "Feature",
  "properties": {
    "iso:country":"AU",
    "sg:address":"22 Virginia St",
    "sg:city":"Mornington",
    "sg:classifiers":[
        {
            "category":"Manufacturing",
            "subcategory":"Metals",
            "type":"Manufacturing & Wholesale Goods"
        }
    ],
    "sg:phone":"+61 3 5975 8800",
    "sg:postcode":"3931",
    "sg:province":"VIC",
    "sg:tags":[
        "sheet",
        "worker"
    ],
    "wof:name":"Nepean Sheet Metal",
    "wof:placetype":"venue"
},
  "geometry": {"coordinates":[145.04913330100001,-38.2321395874],"type":"Point"}
}