{
  "type": "Feature",
  "properties": {
    "addr:full":"144 Abbotsford Rd Bowen Hills QLD 4006",
    "addr:housenumber":"144",
    "addr:postcode":"4006",
    "addr:street":"Abbotsford Rd",
    "iso:country":"AU",
    "sg:address":"144 Abbotsford Rd",
    "sg:city":"Bowen Hills",
    "sg:classifiers":[
        {
            "category":"Retail",
            "subcategory":"Auto Rental",
            "type":"Services"
        }
    ],
    "sg:phone":"+61 7 3252 2638",
    "sg:postcode":"4006",
    "sg:province":"QLD",
    "sg:tags":[
        "home",
        "hire",
        "motor",
        "campervans"
    ],
    "wof:name":"Travellers Auto Barn",
    "wof:placetype":"venue"
},
  "geometry": {"coordinates":[153.03970336899999,-27.4396934509],"type":"Point"}
}