{
  "type": "Feature",
  "properties": {
    "addr:full":"Shop 6 Westfield Shopng Cntr 1015 Sandgate Rd Toombul QLD 4012",
    "addr:housenumber":"shop 6;1015",
    "addr:postcode":"4012",
    "addr:street":"Westfield Shopng Cntr;Sandgate Rd",
    "iso:country":"AU",
    "sg:address":"Shop 6 Westfield Shopng Cntr 1015 Sandgate Rd",
    "sg:city":"Toombul",
    "sg:classifiers":[
        {
            "category":"Shopping",
            "subcategory":"Computers & Home Electronics",
            "type":"Retail Goods"
        }
    ],
    "sg:phone":"+61 7 3266 9831",
    "sg:postcode":"4012",
    "sg:province":"QLD",
    "sg:tags":[
        "equipment",
        "part",
        "electronic"
    ],
    "wof:name":"Tandy Electronics",
    "wof:placetype":"venue"
},
  "geometry": {"coordinates":[153.05986023,-27.4087333679],"type":"Point"}
}