{
  "type": "Feature",
  "properties": {
    "iso:country":"AU",
    "sg:address":"16431 Hume Hwy",
    "sg:city":"Marulan",
    "sg:classifiers":[
        {
            "category":"Utilities",
            "subcategory":"Water",
            "type":"Services"
        }
    ],
    "sg:phone":"+61 2 4841 1787",
    "sg:postcode":"2579",
    "sg:province":"NSW",
    "sg:tags":[
        "cartage"
    ],
    "wof:name":"Breeze G.T. & T.L.",
    "wof:placetype":"venue"
},
  "geometry": {"coordinates":[149.91311645499999,-34.7417030334],"type":"Point"}
}