{
  "type": "Feature",
  "properties": {
    "addr:full":"Murray Valley Hwy Cohuna VIC 3568",
    "addr:postcode":"3568",
    "addr:street":"Valley Hwy",
    "iso:country":"AU",
    "sg:address":"Murray Valley Hwy",
    "sg:city":"Cohuna",
    "sg:classifiers":[
        {
            "category":"Wholesale",
            "subcategory":"Fruits & Vegetables",
            "type":"Manufacturing & Wholesale Goods"
        }
    ],
    "sg:phone":"+61 3 5456 2199",
    "sg:postcode":"3568",
    "sg:province":"VIC",
    "sg:tags":[
        "produce",
        "grain"
    ],
    "wof:name":"Cooke J & R Trading Pty Ltd",
    "wof:placetype":"venue"
},
  "geometry": {"coordinates":[144.22111511200001,-35.8085632324],"type":"Point"}
}