{
  "type": "Feature",
  "properties": {
    "addr:full":"8/ 51 Cleeland Rd Oakleigh South VIC 3167",
    "addr:housenumber":"/ 51",
    "addr:postcode":"3167",
    "addr:street":"Cleeland Rd",
    "iso:country":"AU",
    "sg:address":"8/ 51 Cleeland Rd",
    "sg:city":"Oakleigh South",
    "sg:classifiers":[
        {
            "category":"Wholesale",
            "subcategory":"Machinery & Supplies",
            "type":"Manufacturing & Wholesale Goods"
        }
    ],
    "sg:phone":"+61 3 9543 5355",
    "sg:postcode":"3167",
    "sg:province":"VIC",
    "sg:tags":[
        "machine",
        "tool",
        "engineer"
    ],
    "wof:name":"James Machinery Pty Ltd",
    "wof:placetype":"venue"
},
  "geometry": {"coordinates":[145.09846496599999,-37.9292488098],"type":"Point"}
}