{
  "type": "Feature",
  "properties": {
    "addr:full":"Carteret Ave Willmot NSW 2770",
    "addr:postcode":"2770",
    "addr:street":"Carteret Ave",
    "iso:country":"AU",
    "sg:address":"Carteret Ave",
    "sg:city":"Willmot",
    "sg:classifiers":[
        {
            "category":"Social Services",
            "subcategory":"Child Care",
            "type":"Services"
        }
    ],
    "sg:phone":"+61 2 9628 7677",
    "sg:postcode":"2770",
    "sg:province":"NSW",
    "wof:name":"Blacktown City Council",
    "wof:placetype":"venue"
},
  "geometry": {"coordinates":[150.79281616200001,-33.7256813049],"type":"Point"}
}