{
  "type": "Feature",
  "properties": {
    "addr:full":"26- 28 Geddes St Mulgrave VIC 3170",
    "addr:housenumber":"28",
    "addr:postcode":"3170",
    "addr:street":"Geddes St",
    "iso:country":"AU",
    "sg:address":"26- 28 Geddes St",
    "sg:city":"Mulgrave",
    "sg:classifiers":[
        {
            "category":"Wholesale",
            "subcategory":"Machinery & Supplies",
            "type":"Manufacturing & Wholesale Goods"
        }
    ],
    "sg:phone":"+61 3 9574 9656",
    "sg:postcode":"3170",
    "sg:province":"VIC",
    "sg:tags":[
        "equipment",
        "laboratory"
    ],
    "wof:name":"Aircare Extraction Systems",
    "wof:placetype":"venue"
},
  "geometry": {"coordinates":[145.15338134800001,-37.9059028625],"type":"Point"}
}