{
  "type": "Feature",
  "properties": {
    "addr:full":"Shop 9 / 140a South St Toowoomba QLD 4350",
    "addr:housenumber":"shop 9 / 140a",
    "addr:postcode":"4350",
    "addr:street":"South St",
    "iso:country":"AU",
    "sg:address":"Shop 9 / 140a South St",
    "sg:city":"Toowoomba",
    "sg:classifiers":[
        {
            "category":"Fast Food",
            "type":"Food & Drink"
        }
    ],
    "sg:phone":"+61 7 4687 6800",
    "sg:postcode":"4350",
    "sg:province":"QLD",
    "sg:tags":[
        "away",
        "take"
    ],
    "wof:name":"Southtown Fish Bar Takeaway",
    "wof:placetype":"venue"
},
  "geometry": {"coordinates":[151.907455,-27.571974],"type":"Point"}
}