{
  "type": "Feature",
  "properties": {
    "addr:full":"Equine Training Centre, Lot 6 Westfield Rd Armadale WA 6112",
    "addr:housenumber":"6",
    "addr:postcode":"6112",
    "addr:street":"Westfield Rd",
    "iso:country":"AU",
    "sg:address":"Equine Training Centre, Lot 6 Westfield Rd",
    "sg:city":"Armadale",
    "sg:classifiers":[
        {
            "category":"Education",
            "subcategory":"Vocational School",
            "type":"Public Place"
        }
    ],
    "sg:phone":"+61 8 9267 7777",
    "sg:postcode":"6112",
    "sg:province":"WA",
    "sg:tags":[
        "tafe",
        "college",
        "training"
    ],
    "wof:name":"TAFEWA - SWAN",
    "wof:placetype":"venue"
},
  "geometry": {"coordinates":[115.99256133999999,-32.1276130676],"type":"Point"}
}