{
  "type": "Feature",
  "properties": {
    "addr:full":"83 Muller Rd Boondall QLD 4034",
    "addr:housenumber":"83",
    "addr:postcode":"4034",
    "addr:street":"Muller Rd",
    "iso:country":"AU",
    "sg:address":"83 Muller Rd",
    "sg:city":"Boondall",
    "sg:classifiers":[
        {
            "category":"Retail",
            "subcategory":"Repair Shop",
            "type":"Services"
        }
    ],
    "sg:phone":"+61 7 3265 2090",
    "sg:postcode":"4034",
    "sg:province":"QLD",
    "sg:tags":[
        "upholsterer"
    ],
    "wof:name":"Clifford John Upholstery & Trim",
    "wof:placetype":"venue"
},
  "geometry": {"coordinates":[153.05221599999999,-27.355028],"type":"Point"}
}