{
  "type": "Feature",
  "properties": {
    "iso:country":"AU",
    "sg:address":"59 Seville St",
    "sg:city":"Cervantes",
    "sg:classifiers":[
        {
            "category":"Communications",
            "subcategory":"News Services",
            "type":"Services"
        }
    ],
    "sg:phone":"+61 8 9652 7047",
    "sg:postcode":"6511",
    "sg:province":"WA",
    "sg:tags":[
        "information",
        "tourist",
        "attractions"
    ],
    "wof:name":"Turquoise Coast Enviro Tours",
    "wof:placetype":"venue"
},
  "geometry": {"coordinates":[115.066093,-30.505583],"type":"Point"}
}