{
  "type": "Feature",
  "properties": {
    "iso:country":"AU",
    "sg:address":"20 Marni St",
    "sg:city":"Dandenong South",
    "sg:classifiers":[
        {
            "category":"Shopping",
            "subcategory":"Pets & Pet Supplies",
            "type":"Retail Goods"
        }
    ],
    "sg:phone":"+61 3 9706 6440",
    "sg:postcode":"3175",
    "sg:province":"VIC",
    "sg:tags":[
        "equipment",
        "foundry"
    ],
    "wof:name":"Arnott & Guy Foundry Supplies",
    "wof:placetype":"venue"
},
  "geometry": {"coordinates":[145.204025269,-38.0288124084],"type":"Point"}
}