{
  "type": "Feature",
  "properties": {
    "addr:full":"3 Somerset Ave Narellan NSW 2567",
    "addr:housenumber":"3",
    "addr:postcode":"2567",
    "addr:street":"Somerset Ave",
    "iso:country":"AU",
    "sg:address":"3 Somerset Ave",
    "sg:city":"Narellan",
    "sg:classifiers":[
        {
            "category":"Professional",
            "subcategory":"Accounting & Tax Preparation",
            "type":"Services"
        }
    ],
    "sg:phone":"+61 2 4647 4088",
    "sg:postcode":"2567",
    "sg:province":"NSW",
    "sg:tags":[
        "consultant",
        "taxation"
    ],
    "wof:name":"Camden Valley Financial Solutions",
    "wof:placetype":"venue"
},
  "geometry": {"coordinates":[150.73843383799999,-34.0399360657],"type":"Point"}
}