{
  "type": "Feature",
  "properties": {
    "addr:full":"Gladstone Rd Rockhampton QLD 4700",
    "addr:postcode":"4700",
    "addr:street":"Gladstone Rd",
    "iso:country":"AU",
    "sg:address":"Gladstone Rd",
    "sg:city":"Rockhampton",
    "sg:classifiers":[
        {
            "category":"Organizations",
            "subcategory":"Community Association",
            "type":"Services"
        }
    ],
    "sg:phone":"+61 7 4922 1236",
    "sg:postcode":"4700",
    "sg:province":"QLD",
    "sg:tags":[
        "organisation",
        "family",
        "welfare"
    ],
    "wof:name":"Meals On Wheels",
    "wof:placetype":"venue"
},
  "geometry": {"coordinates":[150.50579834000001,-23.3990077972],"type":"Point"}
}