{
  "type": "Feature",
  "properties": {
    "addr:full":"42- 44 Ocean Beach Rd Sorrento VIC 3943",
    "addr:housenumber":"44",
    "addr:postcode":"3943",
    "addr:street":"Ocean Beach Rd",
    "iso:country":"AU",
    "sg:address":"42- 44 Ocean Beach Rd",
    "sg:city":"Sorrento",
    "sg:classifiers":[
        {
            "category":"Food & Beverages",
            "subcategory":"Bakery",
            "type":"Retail Goods"
        }
    ],
    "sg:phone":"+61 3 5984 0871",
    "sg:postcode":"3943",
    "sg:province":"VIC",
    "sg:tags":[
        "baker"
    ],
    "wof:name":"Brumby's Bakeries",
    "wof:placetype":"venue"
},
  "geometry": {"coordinates":[144.73991394000001,-38.3390083313],"type":"Point"}
}