{
  "type": "Feature",
  "properties": {
    "addr:full":"216 Stirling St Perth WA 6000",
    "addr:housenumber":"216",
    "addr:postcode":"6000",
    "addr:street":"Stirling St",
    "iso:country":"AU",
    "sg:address":"216 Stirling St",
    "sg:city":"Perth",
    "sg:classifiers":[
        {
            "category":"Autos & Motor Vehicles",
            "subcategory":"Fuel & Gas Station",
            "type":"Retail Goods"
        }
    ],
    "sg:phone":"+61 8 9328 1477",
    "sg:postcode":"6000",
    "sg:province":"WA",
    "wof:name":"Sydney Anderson Automotives Pty Ltd",
    "wof:placetype":"venue"
},
  "geometry": {"coordinates":[115.86681366000001,-31.9456996918],"type":"Point"}
}