{
  "type": "Feature",
  "properties": {
    "addr:full":"422 Auburn St Goulburn NSW 2580",
    "addr:housenumber":"422",
    "addr:postcode":"2580",
    "addr:street":"Auburn St",
    "iso:country":"AU",
    "sg:address":"422 Auburn St",
    "sg:city":"Goulburn",
    "sg:classifiers":[
        {
            "category":"Autos & Motor Vehicles",
            "subcategory":"Fuel & Gas Station",
            "type":"Retail Goods"
        }
    ],
    "sg:phone":"+61 2 4821 3277",
    "sg:postcode":"2580",
    "sg:province":"NSW",
    "wof:name":"Mobil Oil Aust Ltd",
    "wof:placetype":"venue"
},
  "geometry": {"coordinates":[149.723144531,-34.7488174438],"type":"Point"}
}