{
  "type": "Feature",
  "properties": {
    "iso:country":"AU",
    "sg:address":"71 Watton St",
    "sg:city":"Werribee",
    "sg:classifiers":[
        {
            "category":"Insurance",
            "subcategory":"Health Insurance",
            "type":"Services"
        }
    ],
    "sg:phone":"+61 1300 362 155",
    "sg:postcode":"3030",
    "sg:province":"VIC",
    "wof:name":"Latrobe Health Services",
    "wof:placetype":"venue"
},
  "geometry": {"coordinates":[144.661362,-37.901428],"type":"Point"}
}