{
  "type": "Feature",
  "properties": {
    "addr:full":"698 Geelong Rd Brooklyn VIC 3012",
    "addr:housenumber":"698",
    "addr:postcode":"3012",
    "addr:street":"Geelong Rd",
    "iso:country":"AU",
    "sg:address":"698 Geelong Rd",
    "sg:city":"Brooklyn",
    "sg:classifiers":[
        {
            "category":"Manufacturing",
            "subcategory":"Paper Products",
            "type":"Manufacturing & Wholesale Goods"
        }
    ],
    "sg:phone":"+61 3 9314 9800",
    "sg:postcode":"3012",
    "sg:province":"VIC",
    "sg:tags":[
        "box",
        "fibre",
        "carton",
        "cardboard"
    ],
    "wof:name":"National Storage",
    "wof:placetype":"venue"
},
  "geometry": {"coordinates":[144.84765625,-37.8172874451],"type":"Point"}
}