{
  "type": "Feature",
  "properties": {
    "iso:country":"AU",
    "sg:address":"18 Santa Monica Drv",
    "sg:city":"Keilor Lodge",
    "sg:classifiers":[
        {
            "category":"Professional",
            "subcategory":"Printing & Photocopies",
            "type":"Services"
        }
    ],
    "sg:phone":"+61 3 9390 8861",
    "sg:postcode":"3038",
    "sg:province":"VIC",
    "sg:tags":[
        "publishing",
        "desktop"
    ],
    "wof:name":"Capitol Works",
    "wof:placetype":"venue"
},
  "geometry": {"coordinates":[144.806137,-37.699169],"type":"Point"}
}