{
  "type": "Feature",
  "properties": {
    "addr:full":"3 Frederick Rd Royal Park SA 5014",
    "addr:housenumber":"3",
    "addr:postcode":"5014",
    "addr:street":"Frederick Rd",
    "iso:country":"AU",
    "sg:address":"3 Frederick Rd",
    "sg:city":"Royal Park",
    "sg:classifiers":[
        {
            "category":"Education",
            "subcategory":"Special Training",
            "type":"Public Place"
        }
    ],
    "sg:phone":"+61 8 8240 3398",
    "sg:postcode":"5014",
    "sg:province":"SA",
    "sg:tags":[
        "development"
    ],
    "wof:name":"Western Pacific Training",
    "wof:placetype":"venue"
},
  "geometry": {"coordinates":[138.50320434599999,-34.8768157959],"type":"Point"}
}