{
  "type": "Feature",
  "properties": {
    "addr:full":"23 Toyer Ave Tempe NSW 2044",
    "addr:housenumber":"23",
    "addr:postcode":"2044",
    "addr:street":"Toyer Ave",
    "iso:country":"AU",
    "sg:address":"23 Toyer Ave",
    "sg:city":"Tempe",
    "sg:classifiers":[
        {
            "category":"Health Services",
            "subcategory":"Health Practitioner",
            "type":"Services"
        }
    ],
    "sg:phone":"+61 2 9558 7517",
    "sg:postcode":"2044",
    "sg:province":"NSW",
    "sg:tags":[
        "osteopath"
    ],
    "wof:name":"Christodoulou Michael",
    "wof:placetype":"venue"
},
  "geometry": {"coordinates":[151.15988200000001,-33.919678],"type":"Point"}
}