{
  "type": "Feature",
  "properties": {
    "addr:full":"421 Sydney Rd Coburg VIC 3058",
    "addr:housenumber":"421",
    "addr:postcode":"3058",
    "addr:street":"Sydney Rd",
    "iso:country":"AU",
    "sg:address":"421 Sydney Rd",
    "sg:city":"Coburg",
    "sg:classifiers":[
        {
            "category":"Food & Beverages",
            "subcategory":"Groceries & Convenience Stores",
            "type":"Retail Goods"
        }
    ],
    "sg:phone":"+61 3 9350 5132",
    "sg:postcode":"3058",
    "sg:province":"VIC",
    "wof:name":"Coburg Food Wholesalers",
    "wof:placetype":"venue"
},
  "geometry": {"coordinates":[144.96601867699999,-37.7435379028],"type":"Point"}
}