{
  "type": "Feature",
  "properties": {
    "addr:full":"3- 5 Ashburn Pl Blackburn VIC 3130",
    "addr:housenumber":"5",
    "addr:postcode":"3130",
    "addr:street":"Pl",
    "iso:country":"AU",
    "sg:address":"3- 5 Ashburn Pl",
    "sg:city":"Blackburn",
    "sg:classifiers":[
        {
            "category":"Retail",
            "subcategory":"Auto Repair",
            "type":"Services"
        }
    ],
    "sg:phone":"+61 3 9894 4249",
    "sg:postcode":"3130",
    "sg:province":"VIC",
    "sg:tags":[
        "repairer",
        "motor",
        "engineer"
    ],
    "wof:name":"C & L Motorcabs",
    "wof:placetype":"venue"
},
  "geometry": {"coordinates":[145.16180419899999,-37.8188591003],"type":"Point"}
}