{
  "type": "Feature",
  "properties": {
    "addr:full":"3/119 Nerang St Southport QLD 4215",
    "addr:housenumber":"/ 119",
    "addr:postcode":"4215",
    "addr:street":"Nerang St",
    "iso:country":"AU",
    "sg:address":"3/119 Nerang St",
    "sg:city":"Southport",
    "sg:classifiers":[
        {
            "category":"Cafe",
            "type":"Food & Drink"
        }
    ],
    "sg:phone":"+61 7 5528 6011",
    "sg:postcode":"4215",
    "sg:province":"QLD",
    "wof:name":"Liaisons Cafe, Bar & Restaurant",
    "wof:placetype":"venue"
},
  "geometry": {"coordinates":[153.40789794899999,-27.9707832336],"type":"Point"}
}