{
  "type": "Feature",
  "properties": {
    "iso:country":"AU",
    "sg:address":"67 King Georges Rd",
    "sg:city":"Wiley Park",
    "sg:classifiers":[
        {
            "category":"Travel",
            "subcategory":"Hotels & Motels",
            "type":"Entertainment"
        }
    ],
    "sg:phone":"+61 2 9759 4833",
    "sg:postcode":"2195",
    "sg:province":"NSW",
    "sg:tags":[
        "accommodation"
    ],
    "wof:name":"Wiley Park Hotel",
    "wof:placetype":"venue"
},
  "geometry": {"coordinates":[151.067581,-33.921768],"type":"Point"}
}