{
  "type": "Feature",
  "properties": {
    "addr:full":"1 Ferngrove Pl Chester Hill NSW 2162",
    "addr:housenumber":"1",
    "addr:postcode":"2162",
    "addr:street":"Ferngrove Pl",
    "iso:country":"AU",
    "sg:address":"1 Ferngrove Pl",
    "sg:city":"Chester Hill",
    "sg:classifiers":[
        {
            "category":"Retail",
            "subcategory":"Auto Rental",
            "type":"Services"
        }
    ],
    "sg:phone":"+61 2 9738 8388",
    "sg:postcode":"2162",
    "sg:province":"NSW",
    "sg:tags":[
        "chauffeur",
        "car",
        "hire",
        "driven",
        "limousine"
    ],
    "wof:name":"Able Minibuses & Limousines",
    "wof:placetype":"venue"
},
  "geometry": {"coordinates":[151.00689697300001,-33.8722381592],"type":"Point"}
}