{
  "type": "Feature",
  "properties": {
    "iso:country":"AU",
    "sg:address":"9 Narrabeen Pl",
    "sg:city":"Kallaroo",
    "sg:classifiers":[
        {
            "category":"Real Estate",
            "subcategory":"Real Estate Services",
            "type":"Services"
        }
    ],
    "sg:phone":"+61 8 9402 8790",
    "sg:postcode":"6025",
    "sg:province":"WA",
    "sg:tags":[
        "consultant",
        "property"
    ],
    "wof:name":"Progress Developments Pty Ltd",
    "wof:placetype":"venue"
},
  "geometry": {"coordinates":[115.738006592,-31.7874031067],"type":"Point"}
}