{
  "type": "Feature",
  "properties": {
    "addr:full":"114 The Grand Pde Brighton-le-Sands NSW 2216",
    "addr:housenumber":"114",
    "addr:postcode":"2216",
    "addr:street":"The Grand Pde",
    "iso:country":"AU",
    "sg:address":"114 The Grand Pde",
    "sg:city":"Brighton-le-Sands",
    "sg:classifiers":[
        {
            "category":"Fast Food",
            "type":"Food & Drink"
        }
    ],
    "sg:phone":"+61 2 9556 3855",
    "sg:postcode":"2216",
    "sg:province":"NSW",
    "sg:tags":[
        "away",
        "take"
    ],
    "wof:name":"Gang Thai Take Away",
    "wof:placetype":"venue"
},
  "geometry": {"coordinates":[151.15472399999999,-33.964283],"type":"Point"}
}