{
  "type": "Feature",
  "properties": {
    "addr:full":"90 Craigie Rd Mt Martha VIC 3934",
    "addr:housenumber":"90",
    "addr:postcode":"3934",
    "addr:street":"Craigie Rd",
    "iso:country":"AU",
    "sg:address":"90 Craigie Rd",
    "sg:city":"Mt Martha",
    "sg:classifiers":[
        {
            "category":"Social Services",
            "subcategory":"Child Care",
            "type":"Services"
        }
    ],
    "sg:phone":"+61 3 5975 0992",
    "sg:postcode":"3934",
    "sg:province":"VIC",
    "wof:name":"ABC Learning Centres",
    "wof:placetype":"venue"
},
  "geometry": {"coordinates":[145.037567139,-38.256362915],"type":"Point"}
}