{
  "type": "Feature",
  "properties": {
    "iso:country":"AU",
    "sg:address":"196 Gladstone Rd",
    "sg:city":"Highgate Hill",
    "sg:classifiers":[
        {
            "category":"Restaurant",
            "type":"Food & Drink"
        }
    ],
    "sg:phone":"+61 7 3217 2180",
    "sg:postcode":"4101",
    "sg:province":"QLD",
    "sg:website":"http://www.blackforestrestaurant.com.au",
    "wof:name":"Black Forest German Restaurant",
    "wof:placetype":"venue"
},
  "geometry": {"coordinates":[153.02244567899999,-27.4935836792],"type":"Point"}
}