{
  "type": "Feature",
  "properties": {
    "addr:full":"Newell Hwy & Berrigan Rd Finley NSW 2713",
    "addr:postcode":"2713",
    "addr:street":"Newell Hwy & Berrigan Rd",
    "iso:country":"AU",
    "sg:address":"Newell Hwy & Berrigan Rd",
    "sg:city":"Finley",
    "sg:classifiers":[
        {
            "category":"Travel",
            "subcategory":"Hotels & Motels",
            "type":"Entertainment"
        }
    ],
    "sg:phone":"+61 3 5883 2077",
    "sg:postcode":"2713",
    "sg:province":"NSW",
    "wof:name":"Finley Palm Motor Inn",
    "wof:placetype":"venue"
},
  "geometry": {"coordinates":[145.58244323700001,-35.6298179626],"type":"Point"}
}