{
  "type": "Feature",
  "properties": {
    "addr:full":"Japoon Rd Japoonvale QLD 4856",
    "addr:postcode":"4856",
    "addr:street":"Japoon Rd",
    "iso:country":"AU",
    "sg:address":"Japoon Rd",
    "sg:city":"Japoonvale",
    "sg:classifiers":[
        {
            "category":"Farming",
            "subcategory":"Farm",
            "type":"Manufacturing & Wholesale Goods"
        }
    ],
    "sg:phone":"+61 7 4065 5134",
    "sg:postcode":"4856",
    "sg:province":"QLD",
    "sg:tags":[
        "farmer"
    ],
    "wof:name":"Campagnolo L",
    "wof:placetype":"venue"
},
  "geometry": {"coordinates":[145.93931579599999,-17.7162399292],"type":"Point"}
}