{
  "type": "Feature",
  "properties": {
    "iso:country":"AU",
    "sg:address":"Clinic 1, 82a Prospect Rd",
    "sg:city":"Prospect",
    "sg:classifiers":[
        {
            "category":"Personal",
            "subcategory":"Massage",
            "type":"Services"
        }
    ],
    "sg:phone":"+61 8 8344 1255",
    "sg:postcode":"5082",
    "sg:province":"SA",
    "sg:tags":[
        "therapy"
    ],
    "wof:name":"Energy Health & Fitness",
    "wof:placetype":"venue"
},
  "geometry": {"coordinates":[138.594024658,-34.8896217346],"type":"Point"}
}