{
  "type": "Feature",
  "properties": {
    "iso:country":"AU",
    "sg:address":"Palmerston Hwy",
    "sg:city":"Innisfail",
    "sg:classifiers":[
        {
            "category":"Home & Garden",
            "subcategory":"Garden Supply",
            "type":"Retail Goods"
        }
    ],
    "sg:phone":"+61 7 4064 4118",
    "sg:postcode":"4860",
    "sg:province":"QLD",
    "sg:tags":[
        "fertilizer"
    ],
    "wof:name":"International Mineral Consultants Pty Ltd",
    "wof:placetype":"venue"
},
  "geometry": {"coordinates":[146.01844787600001,-17.524433136],"type":"Point"}
}