{
  "type": "Feature",
  "properties": {
    "iso:country":"AU",
    "sg:address":"4 Railway Pl",
    "sg:city":"Ringwood",
    "sg:classifiers":[
        {
            "category":"Building & Trades",
            "subcategory":"Locksmith",
            "type":"Services"
        }
    ],
    "sg:phone":"+61 3 9739 7391",
    "sg:postcode":"3134",
    "sg:province":"VIC",
    "sg:tags":[
        "lock"
    ],
    "wof:name":"Statewide Locksmiths",
    "wof:placetype":"venue"
},
  "geometry": {"coordinates":[145.227752686,-37.815990448],"type":"Point"}
}