{
  "type": "Feature",
  "properties": {
    "addr:full":"Blake St Skipton VIC 3361",
    "addr:postcode":"3361",
    "addr:street":"Blake St",
    "iso:country":"AU",
    "sg:address":"Blake St",
    "sg:city":"Skipton",
    "sg:classifiers":[
        {
            "category":"Travel",
            "subcategory":"Hostel",
            "type":"Entertainment"
        }
    ],
    "sg:phone":"+61 3 5340 1124",
    "sg:postcode":"3361",
    "sg:province":"VIC",
    "sg:tags":[
        "home"
    ],
    "wof:name":"Skipton Aged Care Hostel",
    "wof:placetype":"venue"
},
  "geometry": {"coordinates":[143.368240356,-37.6845970154],"type":"Point"}
}