{
  "type": "Feature",
  "properties": {
    "iso:country":"AU",
    "sg:address":"237 Mann St",
    "sg:city":"Gosford Delivery Cntr",
    "sg:classifiers":[
        {
            "category":"Professional",
            "subcategory":"Employment Agencies",
            "type":"Services"
        }
    ],
    "sg:phone":"+61 2 4323 7088",
    "sg:postcode":"2250",
    "sg:province":"NSW",
    "wof:name":"Mission Australia",
    "wof:placetype":"venue"
},
  "geometry": {"coordinates":[151.34274292000001,-33.4233779907],"type":"Point"}
}