{
  "type": "Feature",
  "properties": {
    "iso:country":"AU",
    "sg:address":"19 Galway Bay Drv",
    "sg:city":"Ashtonfield",
    "sg:classifiers":[
        {
            "category":"Education",
            "subcategory":"Kindergarten",
            "type":"Public Place"
        }
    ],
    "sg:phone":"+61 2 4933 8632",
    "sg:postcode":"2323",
    "sg:province":"NSW",
    "sg:tags":[
        "pre-schools"
    ],
    "wof:name":"Shamrock Hill Early Learning & Long Day Care Centre",
    "wof:placetype":"venue"
},
  "geometry": {"coordinates":[151.59243774399999,-32.7715988159],"type":"Point"}
}