{
  "type": "Feature",
  "properties": {
    "iso:country":"AU",
    "sg:address":"Boat Harbour Drv",
    "sg:city":"Hervey Bay",
    "sg:classifiers":[
        {
            "category":"Professional",
            "subcategory":"Printing & Photocopies",
            "type":"Services"
        }
    ],
    "sg:phone":"+61 7 4128 2922",
    "sg:postcode":"4655",
    "sg:province":"QLD",
    "sg:tags":[
        "photocopier"
    ],
    "wof:name":"Officeline",
    "wof:placetype":"venue"
},
  "geometry": {"coordinates":[152.836288,-25.287842],"type":"Point"}
}