{
  "type": "Feature",
  "properties": {
    "iso:country":"AU",
    "sg:address":"13 Bamboo Crs",
    "sg:city":"Mt Louisa",
    "sg:classifiers":[
        {
            "category":"Education",
            "subcategory":"Music School",
            "type":"Public Place"
        }
    ],
    "sg:phone":"+61 7 4723 5288",
    "sg:postcode":"4814",
    "sg:province":"QLD",
    "sg:tags":[
        "teacher"
    ],
    "wof:name":"North Winds Studio",
    "wof:placetype":"venue"
},
  "geometry": {"coordinates":[146.74273700000001,-19.262341],"type":"Point"}
}