{
  "type": "Feature",
  "properties": {
    "addr:full":"21 Pulteney St Adelaide SA 5000",
    "addr:housenumber":"21",
    "addr:postcode":"5000",
    "addr:street":"Pulteney St",
    "iso:country":"AU",
    "sg:address":"21 Pulteney St",
    "sg:city":"Adelaide",
    "sg:classifiers":[
        {
            "category":"Manufacturing",
            "subcategory":"Jewelry",
            "type":"Manufacturing & Wholesale Goods"
        }
    ],
    "sg:phone":"+61 8 8223 5447",
    "sg:postcode":"5000",
    "sg:province":"SA",
    "sg:tags":[
        "designer",
        "jewellery"
    ],
    "wof:name":"Andrew Mazzone Design Jeweller",
    "wof:placetype":"venue"
},
  "geometry": {"coordinates":[138.60609435999999,-34.9274749756],"type":"Point"}
}