{
  "type": "Feature",
  "properties": {
    "addr:full":"19 Baylis St Wagga Wagga NSW 2650",
    "addr:housenumber":"19",
    "addr:postcode":"2650",
    "addr:street":"Baylis St",
    "iso:country":"AU",
    "sg:address":"19 Baylis St",
    "sg:city":"Wagga Wagga",
    "sg:classifiers":[
        {
            "category":"Fast Food",
            "type":"Food & Drink"
        }
    ],
    "sg:phone":"+61 2 6932 3188",
    "sg:postcode":"2650",
    "sg:province":"NSW",
    "sg:tags":[
        "away",
        "take"
    ],
    "wof:name":"Domino's Pizza",
    "wof:placetype":"venue"
},
  "geometry": {"coordinates":[147.36909484899999,-35.1182823181],"type":"Point"}
}