{
  "type": "Feature",
  "properties": {
    "addr:full":"17 Station St Wentworth Falls NSW 2782",
    "addr:housenumber":"17",
    "addr:postcode":"2782",
    "addr:street":"Station St",
    "iso:country":"AU",
    "sg:address":"17 Station St",
    "sg:city":"Wentworth Falls",
    "sg:classifiers":[
        {
            "category":"Health Services",
            "subcategory":"Dentist",
            "type":"Services"
        }
    ],
    "sg:phone":"+61 2 4757 3497",
    "sg:postcode":"2782",
    "sg:province":"NSW",
    "wof:name":"Skouros B Dr",
    "wof:placetype":"venue"
},
  "geometry": {"coordinates":[150.375732422,-33.7091064453],"type":"Point"}
}