{
  "type": "Feature",
  "properties": {
    "addr:full":"601 Blackburn Rd Notting Hill VIC 3168",
    "addr:housenumber":"601",
    "addr:postcode":"3168",
    "addr:street":"Blackburn Rd",
    "iso:country":"AU",
    "sg:address":"601 Blackburn Rd",
    "sg:city":"Notting Hill",
    "sg:classifiers":[
        {
            "category":"Shopping",
            "subcategory":"Stationery & Office Supplies",
            "type":"Retail Goods"
        }
    ],
    "sg:phone":"+61 1800 222 435",
    "sg:postcode":"3168",
    "sg:province":"VIC",
    "sg:tags":[
        "packaging",
        "equipment",
        "sealing",
        "filling"
    ],
    "wof:name":"ABB Australia",
    "wof:placetype":"venue"
},
  "geometry": {"coordinates":[145.14198303200001,-37.9057121277],"type":"Point"}
}