{
  "type": "Feature",
  "properties": {
    "iso:country":"AU",
    "sg:address":"7 Kembla Pl",
    "sg:city":"Kelso",
    "sg:classifiers":[
        {
            "category":"Communications",
            "subcategory":"Television Station",
            "type":"Services"
        }
    ],
    "sg:phone":"+61 429 917 838",
    "sg:postcode":"2795",
    "sg:province":"NSW",
    "sg:tags":[
        "screening",
        "machinery",
        "grading"
    ],
    "wof:name":"Screenmasters Australia",
    "wof:placetype":"venue"
},
  "geometry": {"coordinates":[149.617263794,-33.4252700806],"type":"Point"}
}