{
  "type": "Feature",
  "properties": {
    "addr:full":"Shop 13 - 15 Cessnock Plaza Cessnock NSW 2325",
    "addr:housenumber":"shop 13 15",
    "addr:postcode":"2325",
    "addr:street":"Cessnock Plaza",
    "iso:country":"AU",
    "sg:address":"Shop 13 - 15 Cessnock Plaza",
    "sg:city":"Cessnock",
    "sg:classifiers":[
        {
            "category":"Banks & Credit Unions",
            "subcategory":"Financial Services",
            "type":"Services"
        }
    ],
    "sg:phone":"+61 2 4990 5222",
    "sg:postcode":"2325",
    "sg:province":"NSW",
    "sg:tags":[
        "building",
        "society"
    ],
    "wof:name":"Greater Building Society Ltd",
    "wof:placetype":"venue"
},
  "geometry": {"coordinates":[151.35617065400001,-32.8348197937],"type":"Point"}
}