{
  "type": "Feature",
  "properties": {
    "addr:full":"2 Doral Pl Connolly WA 6027",
    "addr:postcode":"6027",
    "addr:street":"Pl",
    "iso:country":"AU",
    "sg:address":"2 Doral Pl",
    "sg:city":"Connolly",
    "sg:classifiers":[
        {
            "category":"Farming",
            "subcategory":"Farm & Veterinary Services",
            "type":"Manufacturing & Wholesale Goods"
        }
    ],
    "sg:phone":"+61 8 9300 1347",
    "sg:postcode":"6027",
    "sg:province":"WA",
    "sg:tags":[
        "irrigation",
        "reticulation",
        "system"
    ],
    "wof:name":"Ecko Irrigation",
    "wof:placetype":"venue"
},
  "geometry": {"coordinates":[115.75908660899999,-31.7509078979],"type":"Point"}
}