{
  "type": "Feature",
  "properties": {
    "addr:full":"6 Toddy Pl Dunsborough WA 6281",
    "addr:housenumber":"6",
    "addr:postcode":"6281",
    "addr:street":"Toddy Pl",
    "iso:country":"AU",
    "sg:address":"6 Toddy Pl",
    "sg:city":"Dunsborough",
    "sg:classifiers":[
        {
            "category":"Health Services",
            "subcategory":"Health Practitioner",
            "type":"Services"
        }
    ],
    "sg:phone":"+61 8 9756 7467",
    "sg:postcode":"6281",
    "sg:province":"WA",
    "sg:tags":[
        "physiotherapist"
    ],
    "wof:name":"Brandis Kerry",
    "wof:placetype":"venue"
},
  "geometry": {"coordinates":[115.100097656,-33.5989723206],"type":"Point"}
}