{
  "type": "Feature",
  "properties": {
    "iso:country":"AU",
    "sg:address":"23 Roderick St",
    "sg:city":"Ipswich",
    "sg:classifiers":[
        {
            "category":"Health Services",
            "subcategory":"Doctor",
            "type":"Services"
        }
    ],
    "sg:phone":"+61 7 3812 3938",
    "sg:postcode":"4305",
    "sg:province":"QLD",
    "sg:tags":[
        "medical",
        "practitioner"
    ],
    "wof:name":"Rumbach Trish",
    "wof:placetype":"venue"
},
  "geometry": {"coordinates":[152.76170349099999,-27.6178092957],"type":"Point"}
}