{
  "type": "Feature",
  "properties": {
    "addr:full":"\"Stonecrop\" Harry's Cree Rd Violet Town VIC 3669",
    "addr:postcode":"3669",
    "addr:street":"Cree Rd",
    "iso:country":"AU",
    "sg:address":"\"Stonecrop\" Harry's Cree Rd",
    "sg:city":"Violet Town",
    "sg:classifiers":[
        {
            "category":"Arts & Performance",
            "subcategory":"Art Gallery",
            "type":"Entertainment"
        }
    ],
    "sg:phone":"+61 3 5798 1444",
    "sg:postcode":"3669",
    "sg:province":"VIC",
    "wof:name":"Stonecrop Fine Art Galleries & Function Centre",
    "wof:placetype":"venue"
},
  "geometry": {"coordinates":[145.56370544399999,-36.7485847473],"type":"Point"}
}