{
  "type": "Feature",
  "properties": {
    "addr:full":"Pooraka BP 126 Bridge Rd Pooraka SA 5095",
    "addr:housenumber":"126",
    "addr:postcode":"pooraka bp;5095",
    "addr:street":"Bridge Rd",
    "iso:country":"AU",
    "sg:address":"Pooraka BP 126 Bridge Rd",
    "sg:city":"Pooraka",
    "sg:classifiers":[
        {
            "category":"Fast Food",
            "type":"Food & Drink"
        }
    ],
    "sg:phone":"+61 8 8359 4901",
    "sg:postcode":"5095",
    "sg:province":"SA",
    "sg:tags":[
        "away",
        "take"
    ],
    "wof:name":"Subway",
    "wof:placetype":"venue"
},
  "geometry": {"coordinates":[138.63186645499999,-34.8283195496],"type":"Point"}
}