{
  "type": "Feature",
  "properties": {
    "iso:country":"AU",
    "sg:address":"4 Hawker St",
    "sg:city":"Bowden",
    "sg:classifiers":[
        {
            "category":"Manufacturing",
            "subcategory":"Motor Vehicles & Parts",
            "type":"Manufacturing & Wholesale Goods"
        }
    ],
    "sg:phone":"+61 8 8340 1351",
    "sg:postcode":"5007",
    "sg:province":"SA",
    "sg:tags":[
        "press",
        "knife",
        "dy"
    ],
    "wof:name":"Custom Cutting Formes",
    "wof:placetype":"venue"
},
  "geometry": {"coordinates":[138.582122803,-34.9015388489],"type":"Point"}
}