{
  "type": "Feature",
  "properties": {
    "addr:full":"2/ 8 Nicole Cl Bayswater North VIC 3153",
    "addr:housenumber":"/ 8",
    "addr:postcode":"3153",
    "addr:street":"Nicole Cl",
    "iso:country":"AU",
    "sg:address":"2/ 8 Nicole Cl",
    "sg:city":"Bayswater North",
    "sg:classifiers":[
        {
            "category":"Building & Trades",
            "subcategory":"Construction",
            "type":"Services"
        }
    ],
    "sg:phone":"+61 3 9761 4995",
    "sg:postcode":"3153",
    "sg:province":"VIC",
    "sg:tags":[
        "fencing",
        "contractor"
    ],
    "sg:website":"http://www.proudfencing.com.au",
    "wof:name":"Proud Fencing",
    "wof:placetype":"venue"
},
  "geometry": {"coordinates":[145.29005432100001,-37.8253211975],"type":"Point"}
}