{
  "type": "Feature",
  "properties": {
    "addr:full":"14 / 17 River Rd Redbank QLD 4301",
    "addr:housenumber":"14 / 17",
    "addr:postcode":"4301",
    "addr:street":"River Rd",
    "iso:country":"AU",
    "sg:address":"14 / 17 River Rd",
    "sg:city":"Redbank",
    "sg:classifiers":[
        {
            "category":"Shopping",
            "subcategory":"Crafts & Fabrics",
            "type":"Retail Goods"
        }
    ],
    "sg:phone":"+61 418 157 835",
    "sg:postcode":"4301",
    "sg:province":"QLD",
    "sg:tags":[
        "adhesive"
    ],
    "wof:name":"Robatech Australia Pty Ltd",
    "wof:placetype":"venue"
},
  "geometry": {"coordinates":[152.83238220199999,-27.5949707031],"type":"Point"}
}