{
  "type": "Feature",
  "properties": {
    "addr:full":"8 Stamford Rd Oakleigh VIC 3166",
    "addr:housenumber":"8",
    "addr:postcode":"3166",
    "addr:street":"Stamford Rd",
    "iso:country":"AU",
    "sg:address":"8 Stamford Rd",
    "sg:city":"Oakleigh",
    "sg:classifiers":[
        {
            "category":"Professional",
            "subcategory":"Computer Services",
            "type":"Services"
        }
    ],
    "sg:phone":"+61 3 8564 0200",
    "sg:postcode":"3166",
    "sg:province":"VIC",
    "sg:tags":[
        "equipment",
        "networking",
        "installation"
    ],
    "wof:name":"Paragon Services",
    "wof:placetype":"venue"
},
  "geometry": {"coordinates":[145.101028442,-37.8926467896],"type":"Point"}
}