{
  "type": "Feature",
  "properties": {
    "iso:country":"AU",
    "sg:address":"Suite 2/ 349 Bluff Rd",
    "sg:city":"Hampton",
    "sg:classifiers":[
        {
            "category":"Professional",
            "subcategory":"Accounting & Tax Preparation",
            "type":"Services"
        }
    ],
    "sg:phone":"+61 3 9598 0322",
    "sg:postcode":"3188",
    "sg:province":"VIC",
    "sg:tags":[
        "accountant",
        "auditor"
    ],
    "wof:name":"McKenzie Lander",
    "wof:placetype":"venue"
},
  "geometry": {"coordinates":[145.02204895,-37.9461898804],"type":"Point"}
}