{
  "type": "Feature",
  "properties": {
    "addr:full":"132 Bridge St West Tamworth NSW 2340",
    "addr:housenumber":"132",
    "addr:postcode":"2340",
    "addr:street":"Bridge St West",
    "iso:country":"AU",
    "sg:address":"132 Bridge St",
    "sg:city":"West Tamworth",
    "sg:classifiers":[
        {
            "category":"Donuts",
            "subcategory":"None",
            "type":"Food & Drink"
        }
    ],
    "sg:phone":"+61 2 6765 6811",
    "sg:postcode":"2340",
    "sg:province":"NSW",
    "sg:tags":[
        "die",
        "engraver",
        "sinker"
    ],
    "wof:name":"Tamworth Trophy Supplies",
    "wof:placetype":"venue"
},
  "geometry": {"coordinates":[150.91169738799999,-31.0953731537],"type":"Point"}
}