{
  "type": "Feature",
  "properties": {
    "addr:full":"PO Box 464 Irymple VIC 3498",
    "addr:postcode":"3498",
    "iso:country":"AU",
    "sg:address":"PO Box 464",
    "sg:city":"Irymple",
    "sg:classifiers":[
        {
            "category":"Retail",
            "subcategory":"Event Space",
            "type":"Services"
        }
    ],
    "sg:phone":"+61 401 714 704",
    "sg:postcode":"3498",
    "sg:province":"VIC",
    "sg:tags":[
        "function",
        "organiser"
    ],
    "wof:name":"Breath Of The Wok",
    "wof:placetype":"venue"
},
  "geometry": {"coordinates":[142.17286682100001,-34.2372512817],"type":"Point"}
}