{
  "type": "Feature",
  "properties": {
    "addr:full":"34 Raedon St Biloela QLD 4715",
    "addr:housenumber":"34",
    "addr:postcode":"4715",
    "addr:street":"Raedon St",
    "iso:country":"AU",
    "sg:address":"34 Raedon St",
    "sg:city":"Biloela",
    "sg:classifiers":[
        {
            "category":"Wholesale",
            "subcategory":"Farm Supplies",
            "type":"Manufacturing & Wholesale Goods"
        }
    ],
    "sg:phone":"+61 7 4992 4411",
    "sg:postcode":"4715",
    "sg:province":"QLD",
    "sg:tags":[
        "feed",
        "supplement",
        "stock"
    ],
    "wof:name":"Landmark",
    "wof:placetype":"venue"
},
  "geometry": {"coordinates":[150.50404357900001,-24.4035110474],"type":"Point"}
}