{
  "type": "Feature",
  "properties": {
    "addr:full":"Shp1/ 55 George St Parramatta NSW 2150",
    "addr:housenumber":"55",
    "addr:postcode":"2150",
    "addr:street":"George St",
    "iso:country":"AU",
    "sg:address":"Shp1/ 55 George St",
    "sg:city":"Parramatta",
    "sg:classifiers":[
        {
            "category":"Food & Beverages",
            "subcategory":"Groceries & Convenience Stores",
            "type":"Retail Goods"
        }
    ],
    "sg:phone":"+61 2 9891 6390",
    "sg:postcode":"2150",
    "sg:province":"NSW",
    "wof:name":"Ray's Convenience Store",
    "wof:placetype":"venue"
},
  "geometry": {"coordinates":[151.01885986299999,-33.8317871094],"type":"Point"}
}