{
  "type": "Feature",
  "properties": {
    "addr:full":"53 Georgetown Rd Georgetown NSW 2298",
    "addr:housenumber":"53",
    "addr:postcode":"2298",
    "addr:street":"Georgetown Rd",
    "iso:country":"AU",
    "sg:address":"53 Georgetown Rd",
    "sg:city":"Georgetown",
    "sg:classifiers":[
        {
            "category":"Banks & Credit Unions",
            "subcategory":"Investment Brokerage",
            "type":"Services"
        }
    ],
    "sg:phone":"+61 2 4968 0864",
    "sg:postcode":"2298",
    "sg:province":"NSW",
    "sg:tags":[
        "bedspread",
        "quilt"
    ],
    "wof:name":"A Quilter's Hive",
    "wof:placetype":"venue"
},
  "geometry": {"coordinates":[151.72975158700001,-32.9083061218],"type":"Point"}
}