{
  "type": "Feature",
  "properties": {
    "iso:country":"AU",
    "sg:address":"London Bridge Rd",
    "sg:city":"Burra Creek",
    "sg:classifiers":[
        {
            "category":"Building & Trades",
            "subcategory":"Construction",
            "type":"Services"
        }
    ],
    "sg:phone":"+61 2 6236 3205",
    "sg:postcode":"2620",
    "sg:province":"ACT",
    "sg:tags":[
        "joiner",
        "carpenter"
    ],
    "wof:name":"Agius Charles J",
    "wof:placetype":"venue"
},
  "geometry": {"coordinates":[149.2394104,-35.5132865906],"type":"Point"}
}