{
  "type": "Feature",
  "properties": {
    "addr:full":"69 Kingsley Rd Airport West VIC 3042",
    "addr:housenumber":"69",
    "addr:postcode":"3042",
    "addr:street":"Kingsley Rd",
    "iso:country":"AU",
    "sg:address":"69 Kingsley Rd",
    "sg:city":"Airport West",
    "sg:classifiers":[
        {
            "category":"Professional",
            "subcategory":"Art Services",
            "type":"Services"
        }
    ],
    "sg:phone":"+61 3 9379 9504",
    "sg:postcode":"3042",
    "sg:province":"VIC",
    "sg:tags":[
        "decorator",
        "painter"
    ],
    "wof:name":"McElligott O'Connor Pty Ltd",
    "wof:placetype":"venue"
},
  "geometry": {"coordinates":[144.87422180199999,-37.7215690613],"type":"Point"}
}