{
  "type": "Feature",
  "properties": {
    "iso:country":"AU",
    "sg:address":"36 Acacia Ave",
    "sg:city":"Port Macquarie",
    "sg:classifiers":[
        {
            "category":"Retail",
            "subcategory":"Auto Repair",
            "type":"Services"
        }
    ],
    "sg:phone":"+61 2 6581 2203",
    "sg:postcode":"2444",
    "sg:province":"NSW",
    "sg:tags":[
        "engine",
        "reconditioning"
    ],
    "wof:name":"Watt & Parsons Engineering",
    "wof:placetype":"venue"
},
  "geometry": {"coordinates":[152.890213,-31.446947],"type":"Point"}
}