{
  "type": "Feature",
  "properties": {
    "iso:country":"AU",
    "sg:address":"39 Monro Ave",
    "sg:city":"Kirrawee",
    "sg:classifiers":[
        {
            "category":"Retail",
            "subcategory":"Auto Repair",
            "type":"Services"
        }
    ],
    "sg:phone":"+61 2 9521 1290",
    "sg:postcode":"2232",
    "sg:province":"NSW",
    "sg:tags":[
        "repairer",
        "motor",
        "engineer"
    ],
    "wof:name":"Tight Automotive Services",
    "wof:placetype":"venue"
},
  "geometry": {"coordinates":[151.07301330600001,-34.0307693481],"type":"Point"}
}