{
  "type": "Feature",
  "properties": {
    "addr:full":"Pale Face Arcade Shp7/ 242 Hoskins St Temora NSW 2666",
    "addr:housenumber":"242",
    "addr:postcode":"2666",
    "addr:street":"Hoskins St",
    "iso:country":"AU",
    "sg:address":"Pale Face Arcade Shp7/ 242 Hoskins St",
    "sg:city":"Temora",
    "sg:classifiers":[
        {
            "category":"Cafe",
            "type":"Food & Drink"
        }
    ],
    "sg:phone":"+61 2 6977 2995",
    "sg:postcode":"2666",
    "sg:province":"NSW",
    "wof:name":"Temptations Coffee Shop",
    "wof:placetype":"venue"
},
  "geometry": {"coordinates":[147.53434753400001,-34.4485168457],"type":"Point"}
}