{
  "type": "Feature",
  "properties": {
    "addr:full":"21 Main St Lobethal SA 5241",
    "addr:housenumber":"21",
    "addr:postcode":"5241",
    "addr:street":"Main St",
    "iso:country":"AU",
    "sg:address":"21 Main St",
    "sg:city":"Lobethal",
    "sg:classifiers":[
        {
            "category":"Professional",
            "subcategory":"Computer Services",
            "type":"Services"
        }
    ],
    "sg:phone":"+61 8 8389 5497",
    "sg:postcode":"5241",
    "sg:province":"SA",
    "sg:tags":[
        "repairs",
        "upgrade",
        "equipment"
    ],
    "wof:name":"JTR Computers",
    "wof:placetype":"venue"
},
  "geometry": {"coordinates":[138.874465942,-34.9055175781],"type":"Point"}
}