{
  "type": "Feature",
  "properties": {
    "iso:country":"AU",
    "sg:address":"149 Sackville St",
    "sg:city":"Collingwood",
    "sg:classifiers":[
        {
            "category":"Shopping",
            "subcategory":"Gifts & Souvenirs",
            "type":"Retail Goods"
        }
    ],
    "sg:phone":"+61 3 9416 4322",
    "sg:postcode":"3066",
    "sg:province":"VIC",
    "sg:tags":[
        "shop",
        "supply"
    ],
    "wof:name":"The Source",
    "wof:placetype":"venue"
},
  "geometry": {"coordinates":[144.992462158,-37.7991371155],"type":"Point"}
}