{
  "type": "Feature",
  "properties": {
    "iso:country":"AU",
    "sg:address":"376 Burwood Rd",
    "sg:city":"Belmore",
    "sg:classifiers":[
        {
            "category":"Food & Beverages",
            "subcategory":"Supermarket",
            "type":"Retail Goods"
        }
    ],
    "sg:phone":"+61 2 9759 8071",
    "sg:postcode":"2192",
    "sg:province":"NSW",
    "sg:tags":[
        "grocery",
        "store"
    ],
    "wof:name":"M.F.C. Food Stores",
    "wof:placetype":"venue"
},
  "geometry": {"coordinates":[151.088593,-33.918221],"type":"Point"}
}