{
  "type": "Feature",
  "properties": {
    "addr:full":"President Ave Sutherland NSW 2232",
    "addr:postcode":"2232",
    "addr:street":"President Ave",
    "iso:country":"AU",
    "sg:address":"President Ave",
    "sg:city":"Sutherland",
    "sg:classifiers":[
        {
            "category":"Building & Trades",
            "subcategory":"Cleaning & Sanitation",
            "type":"Services"
        }
    ],
    "sg:phone":"+61 414 892 601",
    "sg:postcode":"2232",
    "sg:province":"NSW",
    "sg:tags":[
        "cleaner",
        "repairer",
        "roof"
    ],
    "wof:name":"A. Andrew Stein Plumbing & Roofing",
    "wof:placetype":"venue"
},
  "geometry": {"coordinates":[151.060302734,-34.0342941284],"type":"Point"}
}