{
  "type": "Feature",
  "properties": {
    "addr:full":"1 Park St Brunswick Heads NSW 2483",
    "addr:housenumber":"1",
    "addr:postcode":"2483",
    "addr:street":"Park St",
    "iso:country":"AU",
    "sg:address":"1 Park St",
    "sg:city":"Brunswick Heads",
    "sg:classifiers":[
        {
            "category":"Shopping",
            "type":"Retail Goods"
        }
    ],
    "sg:phone":"+61 2 6685 1778",
    "sg:postcode":"2483",
    "sg:province":"NSW",
    "sg:tags":[
        "supply",
        "religious",
        "church"
    ],
    "wof:name":"Brunswick Christian Bookshop",
    "wof:placetype":"venue"
},
  "geometry": {"coordinates":[153.550247192,-28.5421257019],"type":"Point"}
}