{
  "type": "Feature",
  "properties": {
    "addr:full":"93 Hardgrave Rd West End QLD 4101",
    "addr:housenumber":"93",
    "addr:postcode":"4101",
    "addr:street":"Hardgrave Rd",
    "iso:country":"AU",
    "sg:address":"93 Hardgrave Rd",
    "sg:city":"West End",
    "sg:classifiers":[
        {
            "category":"Fast Food",
            "type":"Food & Drink"
        }
    ],
    "sg:phone":"+61 7 3844 4954",
    "sg:postcode":"4101",
    "sg:province":"QLD",
    "sg:tags":[
        "away",
        "take"
    ],
    "wof:name":"Kim Thanh West End Restaurant",
    "wof:placetype":"venue"
},
  "geometry": {"coordinates":[153.006713867,-27.4828929901],"type":"Point"}
}