{
  "type": "Feature",
  "properties": {
    "iso:country":"AU",
    "sg:address":"PO Box 46",
    "sg:city":"Laidley",
    "sg:classifiers":[
        {
            "category":"Shopping",
            "subcategory":"Musical Instruments",
            "type":"Retail Goods"
        }
    ],
    "sg:phone":"+61 7 5466 5570",
    "sg:postcode":"4341",
    "sg:province":"QLD",
    "sg:tags":[
        "musician",
        "agent"
    ],
    "wof:name":"Accordionist John Colville",
    "wof:placetype":"venue"
},
  "geometry": {"coordinates":[152.38941955600001,-27.6451702118],"type":"Point"}
}