{
  "type": "Feature",
  "properties": {
    "iso:country":"AU",
    "sg:address":"Unit 2/ 14B Hines Rd",
    "sg:city":"O&#039;Connor",
    "sg:classifiers":[
        {
            "category":"Wholesale",
            "subcategory":"Construction Materials",
            "type":"Manufacturing & Wholesale Goods"
        }
    ],
    "sg:phone":"+61 8 6363 5953",
    "sg:postcode":"6163",
    "sg:province":"WA",
    "sg:tags":[
        "lift"
    ],
    "wof:name":"Octagon - BKG Lifts",
    "wof:placetype":"venue"
},
  "geometry": {"coordinates":[115.784233,-32.058098],"type":"Point"}
}