{
  "type": "Feature",
  "properties": {
    "addr:full":"57 Theresa St Emerald QLD 4720",
    "addr:housenumber":"57",
    "addr:postcode":"4720",
    "addr:street":"Theresa St",
    "iso:country":"AU",
    "sg:address":"57 Theresa St",
    "sg:city":"Emerald",
    "sg:classifiers":[
        {
            "category":"Retail",
            "subcategory":"Veterinary Services",
            "type":"Services"
        }
    ],
    "sg:phone":"+61 7 4982 1555",
    "sg:postcode":"4720",
    "sg:province":"QLD",
    "sg:tags":[
        "surgeon"
    ],
    "wof:name":"Canty B J",
    "wof:placetype":"venue"
},
  "geometry": {"coordinates":[148.162994,-23.521318],"type":"Point"}
}