{
  "type": "Feature",
  "properties": {
    "addr:full":"PO Box 1140 Kenmore QLD 4069",
    "addr:postcode":"4069",
    "iso:country":"AU",
    "sg:address":"PO Box 1140",
    "sg:city":"Kenmore",
    "sg:classifiers":[
        {
            "category":"Farming",
            "subcategory":"Farm & Veterinary Services",
            "type":"Manufacturing & Wholesale Goods"
        }
    ],
    "sg:phone":"+61 7 3378 3146",
    "sg:postcode":"4069",
    "sg:province":"QLD",
    "sg:tags":[
        "agricultural",
        "advisory"
    ],
    "wof:name":"Breedlink Cattle Services",
    "wof:placetype":"venue"
},
  "geometry": {"coordinates":[152.93849182100001,-27.508430481],"type":"Point"}
}