{
  "type": "Feature",
  "properties": {
    "addr:full":"59 Railway Rd Blackalls Park NSW 2283",
    "addr:housenumber":"59",
    "addr:postcode":"2283",
    "addr:street":"Railway Rd",
    "iso:country":"AU",
    "sg:address":"59 Railway Rd",
    "sg:city":"Blackalls Park",
    "sg:classifiers":[
        {
            "category":"Train Station",
            "subcategory":"Rail",
            "type":"Transportation"
        }
    ],
    "sg:phone":"+61 2 4959 9180",
    "sg:postcode":"2283",
    "sg:province":"NSW",
    "sg:tags":[
        "marine",
        "engineer"
    ],
    "wof:name":"Lake Macquarie Marine Service",
    "wof:placetype":"venue"
},
  "geometry": {"coordinates":[151.586959839,-33.0047607422],"type":"Point"}
}