{
  "type": "Feature",
  "properties": {
    "iso:country":"AU",
    "sg:address":"21 Birkdale Crt",
    "sg:city":"Rockingham",
    "sg:classifiers":[
        {
            "category":"Retail",
            "subcategory":"Driving School",
            "type":"Services"
        }
    ],
    "sg:phone":"+61 412 227 184",
    "sg:postcode":"6168",
    "sg:province":"WA",
    "wof:name":"Clive's School of Motoring",
    "wof:placetype":"venue"
},
  "geometry": {"coordinates":[115.769211,-32.294968],"type":"Point"}
}