{
  "type": "Feature",
  "properties": {
    "iso:country":"AU",
    "sg:address":"17 Bennett St",
    "sg:city":"Surry Hills",
    "sg:classifiers":[
        {
            "category":"Real Estate",
            "subcategory":"Architect",
            "type":"Services"
        }
    ],
    "sg:phone":"+61 2 9810 7088",
    "sg:postcode":"2010",
    "sg:province":"NSW",
    "wof:name":"Brookes Christopher",
    "wof:placetype":"venue"
},
  "geometry": {"coordinates":[151.21697998100001,-33.886631012],"type":"Point"}
}