{
  "type": "Feature",
  "properties": {
    "addr:full":"461 Prospect Rd Blair Athol SA 5084",
    "addr:housenumber":"461",
    "addr:postcode":"5084",
    "addr:street":"Prospect Rd",
    "iso:country":"AU",
    "sg:address":"461 Prospect Rd",
    "sg:city":"Blair Athol",
    "sg:classifiers":[
        {
            "category":"Retail",
            "subcategory":"Repair Shop",
            "type":"Services"
        }
    ],
    "sg:phone":"+61 1800 229 990",
    "sg:postcode":"5084",
    "sg:province":"SA",
    "sg:tags":[
        "machine",
        "repairs",
        "part",
        "dryer",
        "washing"
    ],
    "wof:name":"Shiraz Refrigeration",
    "wof:placetype":"venue"
},
  "geometry": {"coordinates":[138.59185790999999,-34.8530311584],"type":"Point"}
}