{
  "type": "Feature",
  "properties": {
    "addr:full":"17 Lawrence St Harbord NSW 2096",
    "addr:housenumber":"17",
    "addr:postcode":"2096",
    "addr:street":"Lawrence St",
    "iso:country":"AU",
    "sg:address":"17 Lawrence St",
    "sg:city":"Harbord",
    "sg:classifiers":[
        {
            "category":"Utilities",
            "subcategory":"Electric",
            "type":"Services"
        }
    ],
    "sg:phone":"+61 425 297 334",
    "sg:postcode":"2096",
    "sg:province":"NSW",
    "sg:tags":[
        "electrical",
        "contractor"
    ],
    "wof:name":"R Roberts Pty Ltd",
    "wof:placetype":"venue"
},
  "geometry": {"coordinates":[151.284423828,-33.7787322998],"type":"Point"}
}