{
  "type": "Feature",
  "properties": {
    "iso:country":"AU",
    "sg:address":"27 Heales St",
    "sg:city":"Ballarat",
    "sg:classifiers":[
        {
            "category":"Education",
            "subcategory":"Special Training",
            "type":"Public Place"
        }
    ],
    "sg:phone":"+61 408 136 806",
    "sg:postcode":"3350",
    "sg:province":"VIC",
    "sg:tags":[
        "development"
    ],
    "wof:name":"Sovereign Fire Protection",
    "wof:placetype":"venue"
},
  "geometry": {"coordinates":[143.854904,-37.580425],"type":"Point"}
}