{
  "type": "Feature",
  "properties": {
    "iso:country":"AU",
    "sg:address":"79 Broughton St",
    "sg:city":"Old Guildford",
    "sg:classifiers":[
        {
            "category":"Food & Beverages",
            "subcategory":"Liquor & Beverages",
            "type":"Retail Goods"
        }
    ],
    "sg:phone":"+61 2 9632 6730",
    "sg:postcode":"2161",
    "sg:province":"NSW",
    "sg:tags":[
        "store"
    ],
    "wof:name":"Guildford Cellars",
    "wof:placetype":"venue"
},
  "geometry": {"coordinates":[150.983444214,-33.863861084],"type":"Point"}
}