{
  "type": "Feature",
  "properties": {
    "addr:full":"310 Mann St Gosford NSW 2250",
    "addr:housenumber":"310",
    "addr:postcode":"2250",
    "addr:street":"Mann St",
    "iso:country":"AU",
    "sg:address":"310 Mann St",
    "sg:city":"Gosford",
    "sg:classifiers":[
        {
            "category":"Home & Garden",
            "subcategory":"Carpets & Floor Coverings",
            "type":"Retail Goods"
        }
    ],
    "sg:phone":"+61 2 4323 7885",
    "sg:postcode":"2250",
    "sg:province":"NSW",
    "sg:tags":[
        "wood"
    ],
    "wof:name":"All Floors To Go",
    "wof:placetype":"venue"
},
  "geometry": {"coordinates":[151.343093872,-33.4201316833],"type":"Point"}
}