{
  "type": "Feature",
  "properties": {
    "addr:full":"Bettington St Merriwa NSW 2329",
    "addr:postcode":"2329",
    "addr:street":"St",
    "iso:country":"AU",
    "sg:address":"Bettington St",
    "sg:city":"Merriwa",
    "sg:classifiers":[
        {
            "category":"Communications",
            "subcategory":"News Services",
            "type":"Services"
        }
    ],
    "sg:phone":"+61 2 6548 2607",
    "sg:postcode":"2329",
    "sg:province":"NSW",
    "sg:tags":[
        "information",
        "tourist",
        "attractions"
    ],
    "wof:name":"Merriwa Tourist Information Centre",
    "wof:placetype":"venue"
},
  "geometry": {"coordinates":[150.35670471200001,-32.1395492554],"type":"Point"}
}