{
  "type": "Feature",
  "properties": {
    "iso:country":"AU",
    "sg:address":"Pine Crs",
    "sg:city":"Dalveen",
    "sg:classifiers":[
        {
            "category":"Education",
            "subcategory":"School",
            "type":"Public Place"
        }
    ],
    "sg:phone":"+61 7 4685 2355",
    "sg:postcode":"4374",
    "sg:province":"QLD",
    "sg:tags":[
        "state",
        "except",
        "nsw"
    ],
    "wof:name":"Dalveen Primary",
    "wof:placetype":"venue"
},
  "geometry": {"coordinates":[151.96876525900001,-28.491350174],"type":"Point"}
}