{
  "type": "Feature",
  "properties": {
    "addr:full":"14 Salkauskas Crs Lyneham ACT 2602",
    "addr:housenumber":"14",
    "addr:postcode":"2602",
    "addr:street":"Salkauskas Crs",
    "iso:country":"AU",
    "sg:address":"14 Salkauskas Crs",
    "sg:city":"Lyneham",
    "sg:classifiers":[
        {
            "category":"Professional",
            "subcategory":"Accounting & Tax Preparation",
            "type":"Services"
        }
    ],
    "sg:phone":"+61 2 6248 7477",
    "sg:postcode":"2602",
    "sg:province":"ACT",
    "sg:tags":[
        "accountant",
        "auditor"
    ],
    "wof:name":"Richards S G",
    "wof:placetype":"venue"
},
  "geometry": {"coordinates":[149.12710571299999,-35.2443618774],"type":"Point"}
}