{
  "type": "Feature",
  "properties": {
    "addr:full":"Unit 2, 3 Elma Rd Cheltenham VIC 3192",
    "addr:housenumber":"3",
    "addr:postcode":"3192",
    "addr:street":"Elma Rd",
    "iso:country":"AU",
    "sg:address":"Unit 2, 3 Elma Rd",
    "sg:city":"Cheltenham",
    "sg:classifiers":[
        {
            "category":"Autos & Motor Vehicles",
            "subcategory":"Auto Supplies",
            "type":"Retail Goods"
        }
    ],
    "sg:phone":"+61 3 9555 6624",
    "sg:postcode":"3192",
    "sg:province":"VIC",
    "sg:tags":[
        "electric"
    ],
    "wof:name":"Frankland Electrics Pty Ltd",
    "wof:placetype":"venue"
},
  "geometry": {"coordinates":[145.073287964,-37.9518089294],"type":"Point"}
}