{
  "type": "Feature",
  "properties": {
    "addr:full":"179 Talbragar St Dubbo NSW 2830",
    "addr:housenumber":"179",
    "addr:postcode":"2830",
    "addr:street":"Talbragar St",
    "iso:country":"AU",
    "sg:address":"179 Talbragar St",
    "sg:city":"Dubbo",
    "sg:classifiers":[
        {
            "category":"Retail",
            "subcategory":"Auto Repair",
            "type":"Services"
        }
    ],
    "sg:phone":"+61 2 6884 5377",
    "sg:postcode":"2830",
    "sg:province":"NSW",
    "sg:tags":[
        "repairer",
        "motor",
        "engineer"
    ],
    "wof:name":"Autotune Dubbo",
    "wof:placetype":"venue"
},
  "geometry": {"coordinates":[148.60235595699999,-32.2450485229],"type":"Point"}
}