{
  "type": "Feature",
  "properties": {
    "iso:country":"AU",
    "sg:address":"Cnr McPhail & Old Gympie Rds",
    "sg:city":"Narangba",
    "sg:classifiers":[
        {
            "category":"Manufacturing",
            "subcategory":"Motor Vehicles & Parts",
            "type":"Manufacturing & Wholesale Goods"
        }
    ],
    "sg:phone":"+61 7 3888 1316",
    "sg:postcode":"4504",
    "sg:province":"QLD",
    "sg:tags":[
        "replacement"
    ],
    "wof:name":"Narangba Wrecking Co.",
    "wof:placetype":"venue"
},
  "geometry": {"coordinates":[152.96644592300001,-27.2060089111],"type":"Point"}
}