{
  "type": "Feature",
  "properties": {
    "addr:full":"88c Wallarah Rd Gorokan NSW 2263",
    "addr:housenumber":"88c",
    "addr:postcode":"2263",
    "addr:street":"Wallarah Rd",
    "iso:country":"AU",
    "sg:address":"88c Wallarah Rd",
    "sg:city":"Gorokan",
    "sg:classifiers":[
        {
            "category":"Personal",
            "subcategory":"Beauty Salon",
            "type":"Services"
        }
    ],
    "sg:phone":"+61 2 4392 3190",
    "sg:postcode":"2263",
    "sg:province":"NSW",
    "sg:tags":[
        "hairdresser"
    ],
    "wof:name":"Gorokan Barber Shop",
    "wof:placetype":"venue"
},
  "geometry": {"coordinates":[151.51052899999999,-33.257725],"type":"Point"}
}