{
  "type": "Feature",
  "properties": {
    "addr:full":"Unit 8, 65 Barry St Bayswater VIC 3153",
    "addr:housenumber":"65",
    "addr:postcode":"3153",
    "addr:street":"Barry St",
    "iso:country":"AU",
    "sg:address":"Unit 8, 65 Barry St",
    "sg:city":"Bayswater",
    "sg:classifiers":[
        {
            "category":"Shopping",
            "type":"Retail Goods"
        }
    ],
    "sg:phone":"+61 3 9762 2500",
    "sg:postcode":"3153",
    "sg:province":"VIC",
    "sg:tags":[
        "equipment",
        "safety",
        "accessory"
    ],
    "wof:name":"Paramount Safety Products",
    "wof:placetype":"venue"
},
  "geometry": {"coordinates":[145.28428649899999,-37.8479042053],"type":"Point"}
}