{
  "type": "Feature",
  "properties": {
    "addr:full":"Sanders St Griffith NSW 2680",
    "addr:postcode":"2680",
    "addr:street":"Sanders St",
    "iso:country":"AU",
    "sg:address":"Sanders St",
    "sg:city":"Griffith",
    "sg:classifiers":[
        {
            "category":"Food & Beverages",
            "subcategory":"Supermarket",
            "type":"Retail Goods"
        }
    ],
    "sg:phone":"+61 2 6962 6377",
    "sg:postcode":"2680",
    "sg:province":"NSW",
    "sg:tags":[
        "grocery",
        "store"
    ],
    "wof:name":"Driver Mini-Mart",
    "wof:placetype":"venue"
},
  "geometry": {"coordinates":[146.070312,-34.27964],"type":"Point"}
}