{
  "type": "Feature",
  "properties": {
    "iso:country":"AU",
    "sg:address":"8/ 2- 14 Bunn St",
    "sg:city":"Pyrmont",
    "sg:classifiers":[
        {
            "category":"Professional",
            "subcategory":"Art Services",
            "type":"Services"
        }
    ],
    "sg:phone":"+61 410 143 916",
    "sg:postcode":"2009",
    "sg:province":"NSW",
    "sg:tags":[
        "decorator",
        "painter"
    ],
    "wof:name":"Santa Painting & Decorating",
    "wof:placetype":"venue"
},
  "geometry": {"coordinates":[151.19639587399999,-33.8711013794],"type":"Point"}
}