{
  "type": "Feature",
  "properties": {
    "iso:country":"AU",
    "sg:address":"32 Main St",
    "sg:city":"Samford",
    "sg:classifiers":[
        {
            "category":"Professional",
            "subcategory":"Accounting & Tax Preparation",
            "type":"Services"
        }
    ],
    "sg:phone":"+61 7 3289 1700",
    "sg:postcode":"4520",
    "sg:province":"QLD",
    "sg:tags":[
        "accountant",
        "auditor"
    ],
    "wof:name":"Robert Goodman & Associates",
    "wof:placetype":"venue"
},
  "geometry": {"coordinates":[152.88699299999999,-27.370071],"type":"Point"}
}