{
  "type": "Feature",
  "properties": {
    "iso:country":"AU",
    "sg:address":"88 Brisbane St",
    "sg:city":"Dubbo",
    "sg:classifiers":[
        {
            "category":"Retail",
            "subcategory":"Auto Repair",
            "type":"Services"
        }
    ],
    "sg:phone":"+61 2 6882 7000",
    "sg:postcode":"2830",
    "sg:province":"NSW",
    "sg:tags":[
        "electrical"
    ],
    "wof:name":"D.B. Auto Electrics",
    "wof:placetype":"venue"
},
  "geometry": {"coordinates":[148.60459899899999,-32.2438964844],"type":"Point"}
}