{
  "type": "Feature",
  "properties": {
    "addr:full":"Level 1, 1032 High St Armadale VIC 3143",
    "addr:housenumber":"1032",
    "addr:postcode":"3143",
    "addr:street":"High St",
    "iso:country":"AU",
    "sg:address":"Level 1, 1032 High St",
    "sg:city":"Armadale",
    "sg:classifiers":[
        {
            "category":"Sports & Exercise",
            "subcategory":"Gym",
            "type":"Entertainment"
        }
    ],
    "sg:phone":"+61 3 9500 2626",
    "sg:postcode":"3143",
    "sg:province":"VIC",
    "sg:tags":[
        "pilate",
        "method"
    ],
    "wof:name":"Back In Balance Clinical Pilates",
    "wof:placetype":"venue"
},
  "geometry": {"coordinates":[145.02183532699999,-37.8557510376],"type":"Point"}
}