{
  "type": "Feature",
  "properties": {
    "addr:full":"187 High St Prahran VIC 3181",
    "addr:housenumber":"187",
    "addr:postcode":"3181",
    "addr:street":"High St",
    "iso:country":"AU",
    "sg:address":"187 High St",
    "sg:city":"Prahran",
    "sg:classifiers":[
        {
            "category":"Shopping",
            "subcategory":"Crafts & Fabrics",
            "type":"Retail Goods"
        }
    ],
    "sg:phone":"+61 3 9510 5477",
    "sg:postcode":"3181",
    "sg:province":"VIC",
    "sg:tags":[
        "supply"
    ],
    "sg:website":"http://www.beadsandbuttonsgalore.com.au",
    "wof:name":"Beads and Buttons Galore",
    "wof:placetype":"venue"
},
  "geometry": {"coordinates":[144.99440002399999,-37.8518371582],"type":"Point"}
}