{
  "type": "Feature",
  "properties": {
    "addr:full":"14 Bond St Mt Waverley VIC 3149",
    "addr:housenumber":"14",
    "addr:postcode":"3149",
    "addr:street":"Bond St Mt",
    "iso:country":"AU",
    "sg:address":"14 Bond St",
    "sg:city":"Mt Waverley",
    "sg:classifiers":[
        {
            "category":"Utilities",
            "subcategory":"Electric",
            "type":"Services"
        }
    ],
    "sg:phone":"+61 418 327 873",
    "sg:postcode":"3149",
    "sg:province":"VIC",
    "sg:tags":[
        "electrical",
        "contractor"
    ],
    "wof:name":"Efficient Electrical Pty Ltd",
    "wof:placetype":"venue"
},
  "geometry": {"coordinates":[145.13819885300001,-37.880531311],"type":"Point"}
}