{
  "type": "Feature",
  "properties": {
    "addr:full":"Cnr Scott & Warner Sts Coolangatta QLD 4225",
    "addr:postcode":"4225",
    "addr:street":"Cnr",
    "iso:country":"AU",
    "sg:address":"Cnr Scott & Warner Sts",
    "sg:city":"Coolangatta",
    "sg:classifiers":[
        {
            "category":"Retail",
            "subcategory":"Event Space",
            "type":"Services"
        }
    ],
    "sg:phone":"+61 7 5536 6677",
    "sg:postcode":"4225",
    "sg:province":"QLD",
    "sg:tags":[
        "function",
        "organiser"
    ],
    "wof:name":"Coolangatta Bowls & Recreation Club Inc.",
    "wof:placetype":"venue"
},
  "geometry": {"coordinates":[153.510986328,-28.1607666016],"type":"Point"}
}