{
  "type": "Feature",
  "properties": {
    "addr:full":"26 Villamanta St Geelong West VIC 3218",
    "addr:housenumber":"26",
    "addr:postcode":"3218",
    "addr:street":"Villamanta St",
    "iso:country":"AU",
    "sg:address":"26 Villamanta St",
    "sg:city":"Geelong West",
    "sg:classifiers":[
        {
            "category":"Professional",
            "subcategory":"Accounting & Tax Preparation",
            "type":"Services"
        }
    ],
    "sg:phone":"+61 3 5229 6800",
    "sg:postcode":"3218",
    "sg:province":"VIC",
    "sg:tags":[
        "consultant",
        "taxation"
    ],
    "wof:name":"Keogh B V",
    "wof:placetype":"venue"
},
  "geometry": {"coordinates":[144.35058593799999,-38.1460266113],"type":"Point"}
}