{
  "type": "Feature",
  "properties": {
    "iso:country":"AU",
    "sg:address":"Mt Nathan Rd",
    "sg:city":"Mt Nathan",
    "sg:classifiers":[
        {
            "category":"Wholesale",
            "subcategory":"Plants",
            "type":"Manufacturing & Wholesale Goods"
        }
    ],
    "sg:phone":"+61 410 619 158",
    "sg:postcode":"4211",
    "sg:province":"QLD",
    "sg:tags":[
        "florist"
    ],
    "wof:name":"Rosaflora Rose Farm",
    "wof:placetype":"venue"
},
  "geometry": {"coordinates":[153.284713745,-27.9958438873],"type":"Point"}
}