{
  "type": "Feature",
  "properties": {
    "iso:country":"AU",
    "sg:address":"11- 15 Murray St",
    "sg:city":"East Devonport",
    "sg:classifiers":[
        {
            "category":"Shopping",
            "subcategory":"Clothing, Apparel, & Fashions",
            "type":"Retail Goods"
        }
    ],
    "sg:phone":"+61 3 6427 0973",
    "sg:postcode":"7310",
    "sg:province":"TAS",
    "sg:tags":[
        "recycled",
        "clothing"
    ],
    "wof:name":"Lifeline Bargain Shops",
    "wof:placetype":"venue"
},
  "geometry": {"coordinates":[146.36927795400001,-41.1799659729],"type":"Point"}
}