{
  "type": "Feature",
  "properties": {
    "iso:country":"AU",
    "sg:address":"5/155 King William Rd",
    "sg:city":"Hyde Park",
    "sg:classifiers":[
        {
            "category":"Manufacturing",
            "subcategory":"Jewelry",
            "type":"Manufacturing & Wholesale Goods"
        }
    ],
    "sg:phone":"+61 8 8373 7668",
    "sg:postcode":"5061",
    "sg:province":"SA",
    "sg:tags":[
        "mfrg",
        "jeweller"
    ],
    "wof:name":"Casa D'Oro Jewellers",
    "wof:placetype":"venue"
},
  "geometry": {"coordinates":[138.60038757300001,-34.9564590454],"type":"Point"}
}