{
  "type": "Feature",
  "properties": {
    "addr:full":"50 Newlands Rd Reservoir VIC 3073",
    "addr:housenumber":"50",
    "addr:postcode":"3073",
    "addr:street":"Newlands Rd",
    "iso:country":"AU",
    "sg:address":"50 Newlands Rd",
    "sg:city":"Reservoir",
    "sg:classifiers":[
        {
            "category":"Building & Trades",
            "subcategory":"Construction",
            "type":"Services"
        }
    ],
    "sg:phone":"+61 3 9469 4550",
    "sg:postcode":"3073",
    "sg:province":"VIC",
    "sg:tags":[
        "equipment",
        "balancing"
    ],
    "wof:name":"Duggan Balancing Pty Ltd",
    "wof:placetype":"venue"
},
  "geometry": {"coordinates":[144.98060607900001,-37.7188110352],"type":"Point"}
}