{
  "type": "Feature",
  "properties": {
    "addr:full":"19 Charman Ave Emerald VIC 3782",
    "addr:housenumber":"19",
    "addr:postcode":"3782",
    "addr:street":"Charman Ave",
    "iso:country":"AU",
    "sg:address":"19 Charman Ave",
    "sg:city":"Emerald",
    "sg:classifiers":[
        {
            "category":"Utilities",
            "subcategory":"Electric",
            "type":"Services"
        }
    ],
    "sg:phone":"+61 439 936 690",
    "sg:postcode":"3782",
    "sg:province":"VIC",
    "sg:tags":[
        "electrical",
        "contractor"
    ],
    "wof:name":"CNG Electrical Pty Ltd",
    "wof:placetype":"venue"
},
  "geometry": {"coordinates":[145.44581600000001,-37.918354],"type":"Point"}
}