{
  "type": "Feature",
  "properties": {
    "addr:full":"149 Heidelberg Rd Northcote VIC 3070",
    "addr:housenumber":"149",
    "addr:postcode":"3070",
    "addr:street":"Heidelberg Rd",
    "iso:country":"AU",
    "sg:address":"149 Heidelberg Rd",
    "sg:city":"Northcote",
    "sg:classifiers":[
        {
            "category":"Military Area",
            "subcategory":"Air Force Base",
            "type":"Public Place"
        }
    ],
    "sg:phone":"+61 3 9489 9811",
    "sg:postcode":"3070",
    "sg:province":"VIC",
    "sg:tags":[
        "equipment",
        "speed",
        "variation"
    ],
    "wof:name":"Naismith Engineering & Manufacturing Co Pty Ltd",
    "wof:placetype":"venue"
},
  "geometry": {"coordinates":[145.00649999999999,-37.783821],"type":"Point"}
}