{
  "type": "Feature",
  "properties": {
    "iso:country":"AU",
    "sg:address":"125 Essington Lewis Ave",
    "sg:city":"Whyalla",
    "sg:classifiers":[
        {
            "category":"Building & Trades",
            "subcategory":"Construction",
            "type":"Services"
        }
    ],
    "sg:phone":"+61 8 8645 4872",
    "sg:postcode":"5600",
    "sg:province":"SA",
    "sg:tags":[
        "contractor"
    ],
    "wof:name":"Daryl Lee",
    "wof:placetype":"venue"
},
  "geometry": {"coordinates":[137.57048,-33.039505],"type":"Point"}
}