{
  "type": "Feature",
  "properties": {
    "addr:full":"37 Dartmouth Crt Varsity Lakes QLD 4227",
    "addr:housenumber":"37",
    "addr:postcode":"4227",
    "addr:street":"Dartmouth Crt",
    "iso:country":"AU",
    "sg:address":"37 Dartmouth Crt",
    "sg:city":"Varsity Lakes",
    "sg:classifiers":[
        {
            "category":"Building & Trades",
            "subcategory":"Pest Control",
            "type":"Services"
        }
    ],
    "sg:phone":"+61 7 5568 7017",
    "sg:postcode":"4227",
    "sg:province":"QLD",
    "wof:name":"Paddy's Carpet Cleaning and Pest Control",
    "wof:placetype":"venue"
},
  "geometry": {"coordinates":[153.41586303700001,-28.0840606689],"type":"Point"}
}