{
  "type": "Feature",
  "properties": {
    "iso:country":"AU",
    "sg:address":"5- 6 Maher St",
    "sg:city":"Kilmore",
    "sg:classifiers":[
        {
            "category":"Manufacturing",
            "subcategory":"Building Materials",
            "type":"Manufacturing & Wholesale Goods"
        }
    ],
    "sg:phone":"+61 3 5782 1888",
    "sg:postcode":"3764",
    "sg:province":"VIC",
    "sg:tags":[
        "concrete",
        "product"
    ],
    "wof:name":"Automatic Concrete",
    "wof:placetype":"venue"
},
  "geometry": {"coordinates":[144.94795227,-37.281955719],"type":"Point"}
}