{
  "type": "Feature",
  "properties": {
    "addr:full":"243 Main Rd Toukley NSW 2263",
    "addr:housenumber":"243",
    "addr:postcode":"2263",
    "addr:street":"Main Rd",
    "iso:country":"AU",
    "sg:address":"243 Main Rd",
    "sg:city":"Toukley",
    "sg:classifiers":[
        {
            "category":"Wholesale",
            "subcategory":"Medical Equipment & Supplies",
            "type":"Manufacturing & Wholesale Goods"
        }
    ],
    "sg:phone":"+61 2 4397 2250",
    "sg:postcode":"2263",
    "sg:province":"NSW",
    "sg:tags":[
        "scooter",
        "mobility"
    ],
    "wof:name":"Scooters & Mobility",
    "wof:placetype":"venue"
},
  "geometry": {"coordinates":[151.543396,-33.264252],"type":"Point"}
}