{
  "type": "Feature",
  "properties": {
    "addr:full":"PO Box 1019 Willagee WA 6156",
    "addr:postcode":"6156",
    "iso:country":"AU",
    "sg:address":"PO Box 1019",
    "sg:city":"Willagee",
    "sg:classifiers":[
        {
            "category":"Retail",
            "subcategory":"Auto Rental",
            "type":"Services"
        }
    ],
    "sg:phone":"+61 409 683 155",
    "sg:postcode":"6156",
    "sg:province":"WA",
    "sg:tags":[
        "chauffeur",
        "car",
        "hire",
        "driven",
        "limousine"
    ],
    "wof:name":"Astoria Chauffeuring Service",
    "wof:placetype":"venue"
},
  "geometry": {"coordinates":[115.80547300000001,-32.050919],"type":"Point"}
}