{
  "type": "Feature",
  "properties": {
    "addr:full":"46 Sheriff St Forbes NSW 2871",
    "addr:housenumber":"46",
    "addr:postcode":"2871",
    "addr:street":"Sheriff St",
    "iso:country":"AU",
    "sg:address":"46 Sheriff St",
    "sg:city":"Forbes",
    "sg:classifiers":[
        {
            "category":"Organizations",
            "subcategory":"Professional Association",
            "type":"Services"
        }
    ],
    "sg:phone":"+61 2 6852 1688",
    "sg:postcode":"2871",
    "sg:province":"NSW",
    "sg:tags":[
        "rural",
        "organisation",
        "production",
        "primary"
    ],
    "wof:name":"Rural Lands Protection Boards",
    "wof:placetype":"venue"
},
  "geometry": {"coordinates":[148.010086,-33.385937],"type":"Point"}
}