{
  "type": "Feature",
  "properties": {
    "iso:country":"AU",
    "sg:address":"33 Rushdale St",
    "sg:city":"Knoxfield",
    "sg:classifiers":[
        {
            "category":"Retail",
            "subcategory":"Laundry & Dry Cleaning",
            "type":"Services"
        }
    ],
    "sg:phone":"+61 1800 646 302",
    "sg:postcode":"3180",
    "sg:province":"VIC",
    "sg:tags":[
        "equipment",
        "supply"
    ],
    "wof:name":"Stelco Chemicals Pty Ltd",
    "wof:placetype":"venue"
},
  "geometry": {"coordinates":[145.255462647,-37.8940582275],"type":"Point"}
}