{
  "type": "Feature",
  "properties": {
    "iso:country":"AU",
    "sg:address":"10 Simpson St",
    "sg:city":"East Melbourne",
    "sg:classifiers":[
        {
            "category":"Health Services",
            "subcategory":"Health Practitioner",
            "type":"Services"
        }
    ],
    "sg:phone":"+61 3 9427 1857",
    "sg:postcode":"3002",
    "sg:province":"VIC",
    "sg:tags":[
        "naturopath"
    ],
    "wof:name":"Karen Weippert Natural Health Care",
    "wof:placetype":"venue"
},
  "geometry": {"coordinates":[144.98797607399999,-37.8164367676],"type":"Point"}
}