{
  "type": "Feature",
  "properties": {
    "addr:full":"5 11 Hallstrom Pl Wetherill Park NSW 2164",
    "addr:housenumber":"11",
    "addr:postcode":"2164",
    "addr:street":"5;Pl",
    "iso:country":"AU",
    "sg:address":"5 11 Hallstrom Pl",
    "sg:city":"Wetherill Park",
    "sg:classifiers":[
        {
            "category":"Professional",
            "subcategory":"Computer Services",
            "type":"Services"
        }
    ],
    "sg:phone":"+61 2 9011 6111",
    "sg:postcode":"2164",
    "sg:province":"NSW",
    "sg:tags":[
        "consultant",
        "system"
    ],
    "wof:name":"Auslink System Solutions",
    "wof:placetype":"venue"
},
  "geometry": {"coordinates":[150.88507080100001,-33.8448448181],"type":"Point"}
}