{
  "type": "Feature",
  "properties": {
    "addr:full":"721 Riversdale Rd Camberwell VIC 3124",
    "addr:housenumber":"721",
    "addr:postcode":"3124",
    "addr:street":"Riversdale Rd",
    "iso:country":"AU",
    "sg:address":"721 Riversdale Rd",
    "sg:city":"Camberwell",
    "sg:classifiers":[
        {
            "category":"Health Services",
            "subcategory":"Dentist",
            "type":"Services"
        }
    ],
    "sg:phone":"+61 3 9885 7822",
    "sg:postcode":"3124",
    "sg:province":"VIC",
    "sg:tags":[
        "dental",
        "prosthetist"
    ],
    "wof:name":"Kegele David Anthony",
    "wof:placetype":"venue"
},
  "geometry": {"coordinates":[145.07650756800001,-37.8334884644],"type":"Point"}
}