{
  "type": "Feature",
  "properties": {
    "addr:full":"26c Belmore St Burwood NSW 2134",
    "addr:housenumber":"26c",
    "addr:postcode":"2134",
    "addr:street":"Belmore St",
    "iso:country":"AU",
    "sg:address":"26c Belmore St",
    "sg:city":"Burwood",
    "sg:classifiers":[
        {
            "category":"Wholesale",
            "subcategory":"Medical Equipment & Supplies",
            "type":"Manufacturing & Wholesale Goods"
        }
    ],
    "sg:phone":"+61 2 9747 4300",
    "sg:postcode":"2134",
    "sg:province":"NSW",
    "sg:tags":[
        "aids",
        "hearing"
    ],
    "wof:name":"Armstrong Gloria",
    "wof:placetype":"venue"
},
  "geometry": {"coordinates":[151.10395813,-33.8791007996],"type":"Point"}
}