{
  "type": "Feature",
  "properties": {
    "addr:full":"215 Euston Rd Alexandria NSW 2015",
    "addr:housenumber":"215",
    "addr:postcode":"2015",
    "addr:street":"Euston Rd",
    "iso:country":"AU",
    "sg:address":"215 Euston Rd",
    "sg:city":"Alexandria",
    "sg:classifiers":[
        {
            "category":"Cafe",
            "type":"Food & Drink"
        }
    ],
    "sg:phone":"+61 2 9565 5835",
    "sg:postcode":"2015",
    "sg:province":"NSW",
    "wof:name":"Sydney Park Cafe",
    "wof:placetype":"venue"
},
  "geometry": {"coordinates":[151.18661499000001,-33.9124107361],"type":"Point"}
}