{
  "type": "Feature",
  "properties": {
    "iso:country":"AU",
    "sg:address":"Unit 4/ 40 Terrence Rd",
    "sg:city":"Brendale",
    "sg:classifiers":[
        {
            "category":"Shopping",
            "subcategory":"Stationery & Office Supplies",
            "type":"Retail Goods"
        }
    ],
    "sg:phone":"+61 7 3881 1055",
    "sg:postcode":"4500",
    "sg:province":"QLD",
    "sg:tags":[
        "equipment",
        "coating",
        "powder"
    ],
    "wof:name":"G.G.S. Gas & Electrical Pty Ltd",
    "wof:placetype":"venue"
},
  "geometry": {"coordinates":[152.98088073700001,-27.3200359344],"type":"Point"}
}