{
  "type": "Feature",
  "properties": {
    "addr:full":"29 Monger St Perth WA 6000",
    "addr:housenumber":"29",
    "addr:postcode":"6000",
    "addr:street":"Monger St",
    "iso:country":"AU",
    "sg:address":"29 Monger St",
    "sg:city":"Perth",
    "sg:classifiers":[
        {
            "category":"Professional",
            "type":"Services"
        }
    ],
    "sg:phone":"+61 1300 656 866",
    "sg:postcode":"6000",
    "sg:province":"WA",
    "sg:tags":[
        "valuer"
    ],
    "wof:name":"Lotons",
    "wof:placetype":"venue"
},
  "geometry": {"coordinates":[115.863220215,-31.9450302124],"type":"Point"}
}