{
  "type": "Feature",
  "properties": {
    "addr:full":"53 Roselea St Shailer Park QLD 4128",
    "addr:housenumber":"53",
    "addr:postcode":"4128",
    "addr:street":"Roselea St",
    "iso:country":"AU",
    "sg:address":"53 Roselea St",
    "sg:city":"Shailer Park",
    "sg:classifiers":[
        {
            "category":"Retail",
            "subcategory":"Auto Repair",
            "type":"Services"
        }
    ],
    "sg:phone":"+61 7 3801 2330",
    "sg:postcode":"4128",
    "sg:province":"QLD",
    "sg:tags":[
        "sport",
        "motor"
    ],
    "wof:name":"Aerospec Racing Products",
    "wof:placetype":"venue"
},
  "geometry": {"coordinates":[153.174224853,-27.6443252563],"type":"Point"}
}