{
  "type": "Feature",
  "properties": {
    "iso:country":"AU",
    "sg:address":"86-88 Willarong Rd",
    "sg:city":"Caringbah",
    "sg:classifiers":[
        {
            "category":"Manufacturing",
            "subcategory":"Metals",
            "type":"Manufacturing & Wholesale Goods"
        }
    ],
    "sg:phone":"+61 2 9526 2288",
    "sg:postcode":"2229",
    "sg:province":"NSW",
    "sg:tags":[
        "sheet",
        "worker"
    ],
    "sg:website":"http://www.fjprecision.com.au",
    "wof:name":"F.J. Precision Pty Ltd",
    "wof:placetype":"venue"
},
  "geometry": {"coordinates":[151.12205505399999,-34.0327949524],"type":"Point"}
}