{
  "type": "Feature",
  "properties": {
    "addr:full":"27 Bates Drv Kalgoorlie WA 6430",
    "addr:housenumber":"27",
    "addr:postcode":"6430",
    "addr:street":"Bates Drv",
    "iso:country":"AU",
    "sg:address":"27 Bates Drv",
    "sg:city":"Kalgoorlie",
    "sg:classifiers":[
        {
            "category":"Building & Trades",
            "subcategory":"Construction",
            "type":"Services"
        }
    ],
    "sg:phone":"+61 408 118 114",
    "sg:postcode":"6430",
    "sg:province":"WA",
    "sg:tags":[
        "concrete",
        "contractor"
    ],
    "wof:name":"Bexhill Pty Ltd",
    "wof:placetype":"venue"
},
  "geometry": {"coordinates":[121.455108643,-30.7698116302],"type":"Point"}
}