{
  "type": "Feature",
  "properties": {
    "iso:country":"AU",
    "sg:address":"433 Police Rd",
    "sg:city":"Mulgrave",
    "sg:classifiers":[
        {
            "category":"Health Services",
            "subcategory":"Optometrist",
            "type":"Services"
        }
    ],
    "sg:phone":"+61 3 9790 0833",
    "sg:postcode":"3170",
    "sg:province":"VIC",
    "wof:name":"Karen K Y Leung",
    "wof:placetype":"venue"
},
  "geometry": {"coordinates":[145.20231628400001,-37.9381217957],"type":"Point"}
}