{
  "type": "Feature",
  "properties": {
    "iso:country":"AU",
    "sg:address":"46 Morilla St",
    "sg:city":"Lightning Ridge",
    "sg:classifiers":[
        {
            "category":"Government",
            "subcategory":"Post Office",
            "type":"Public Place"
        }
    ],
    "sg:phone":"+61 2 6829 0320",
    "sg:postcode":"2834",
    "sg:province":"NSW",
    "sg:tags":[
        "postal"
    ],
    "wof:name":"Australia Post",
    "wof:placetype":"venue"
},
  "geometry": {"coordinates":[147.98071300000001,-29.427147],"type":"Point"}
}