{
  "type": "Feature",
  "properties": {
    "addr:full":"\"Eversley\" Adelaide Rd Minlaton SA 5575",
    "addr:postcode":"5575",
    "addr:street":"Adelaide Rd",
    "iso:country":"AU",
    "sg:address":"\"Eversley\" Adelaide Rd",
    "sg:city":"Minlaton",
    "sg:classifiers":[
        {
            "category":"Farming",
            "subcategory":"Farm",
            "type":"Manufacturing & Wholesale Goods"
        }
    ],
    "sg:phone":"+61 8 8853 2311",
    "sg:postcode":"5575",
    "sg:province":"SA",
    "sg:tags":[
        "farmer"
    ],
    "wof:name":"Cook Walad K",
    "wof:placetype":"venue"
},
  "geometry": {"coordinates":[137.80747985799999,-34.853729248],"type":"Point"}
}