{
  "type": "Feature",
  "properties": {
    "iso:country":"AU",
    "sg:address":"65 Comur St",
    "sg:city":"Yass",
    "sg:classifiers":[
        {
            "category":"Shopping",
            "subcategory":"Crafts & Fabrics",
            "type":"Retail Goods"
        }
    ],
    "sg:phone":"+61 2 6226 3348",
    "sg:postcode":"2582",
    "sg:province":"NSW",
    "sg:tags":[
        "supply"
    ],
    "wof:name":"Craft Junction",
    "wof:placetype":"venue"
},
  "geometry": {"coordinates":[148.91189575199999,-34.8426322937],"type":"Point"}
}