{
  "type": "Feature",
  "properties": {
    "iso:country":"AU",
    "sg:address":"89- 91 Botany Rd",
    "sg:city":"Alexandria",
    "sg:classifiers":[
        {
            "category":"Professional",
            "subcategory":"Detective & Security Services",
            "type":"Services"
        }
    ],
    "sg:phone":"+61 2 9319 6311",
    "sg:postcode":"2015",
    "sg:province":"NSW",
    "sg:tags":[
        "consultant",
        "system"
    ],
    "wof:name":"Associated Security Co.",
    "wof:placetype":"venue"
},
  "geometry": {"coordinates":[151.19984435999999,-33.897819519],"type":"Point"}
}