{
  "type": "Feature",
  "properties": {
    "addr:full":"U4/ 493 Nicholson Rd Canning Vale WA 6155",
    "addr:housenumber":"493",
    "addr:postcode":"6155",
    "addr:street":"U4 /;Nicholson Rd",
    "iso:country":"AU",
    "sg:address":"U4/ 493 Nicholson Rd",
    "sg:city":"Canning Vale",
    "sg:classifiers":[
        {
            "category":"Home & Garden",
            "subcategory":"Garden Supply",
            "type":"Retail Goods"
        }
    ],
    "sg:phone":"+61 8 9455 5345",
    "sg:postcode":"6155",
    "sg:province":"WA",
    "sg:tags":[
        "equipment"
    ],
    "wof:name":"The Mower Shop",
    "wof:placetype":"venue"
},
  "geometry": {"coordinates":[115.916237,-32.058895],"type":"Point"}
}