{
  "type": "Feature",
  "properties": {
    "addr:full":"20 Darling Rd Gruyere VIC 3770",
    "addr:housenumber":"20",
    "addr:postcode":"3770",
    "addr:street":"Darling Rd",
    "iso:country":"AU",
    "sg:address":"20 Darling Rd",
    "sg:city":"Gruyere",
    "sg:classifiers":[
        {
            "category":"Farming",
            "subcategory":"Orchard",
            "type":"Manufacturing & Wholesale Goods"
        }
    ],
    "sg:phone":"+61 3 5964 9278",
    "sg:postcode":"3770",
    "sg:province":"VIC",
    "sg:tags":[
        "pear",
        "apple",
        "grower"
    ],
    "wof:name":"Finger G A",
    "wof:placetype":"venue"
},
  "geometry": {"coordinates":[145.461533,-37.753319],"type":"Point"}
}