{
  "type": "Feature",
  "properties": {
    "iso:country":"AU",
    "sg:address":"Wedgewood Rd",
    "sg:city":"Parndana",
    "sg:classifiers":[
        {
            "category":"Education",
            "subcategory":"School",
            "type":"Public Place"
        }
    ],
    "sg:phone":"+61 8 8559 6068",
    "sg:postcode":"5220",
    "sg:province":"SA",
    "sg:tags":[
        "state",
        "except",
        "nsw"
    ],
    "wof:name":"Parndana Area School",
    "wof:placetype":"venue"
},
  "geometry": {"coordinates":[137.26344299300001,-35.799331665],"type":"Point"}
}