{
  "type": "Feature",
  "properties": {
    "iso:country":"AU",
    "sg:address":"67 Webster Rd",
    "sg:city":"Deception Bay",
    "sg:classifiers":[
        {
            "category":"Autos & Motor Vehicles",
            "subcategory":"Automobile Sales",
            "type":"Retail Goods"
        }
    ],
    "sg:phone":"+61 7 3203 3500",
    "sg:postcode":"4508",
    "sg:province":"QLD",
    "sg:tags":[
        "car",
        "used"
    ],
    "wof:name":"Brents Wholesale Vehicles Pty Ltd",
    "wof:placetype":"venue"
},
  "geometry": {"coordinates":[153.03515625,-27.2016429901],"type":"Point"}
}