{
  "type": "Feature",
  "properties": {
    "iso:country":"AU",
    "sg:address":"Shop 64, Runaway Bay Shopping Centre, 10-12 Lea Drive",
    "sg:city":"Runaway Bay",
    "sg:classifiers":[
        {
            "category":"Shopping",
            "subcategory":"Pets & Pet Supplies",
            "type":"Retail Goods"
        }
    ],
    "sg:phone":"+61 7 5537 3155",
    "sg:postcode":"4216",
    "sg:province":"QLD",
    "sg:tags":[
        "shop",
        "supplier"
    ],
    "wof:name":"Pets Paradise",
    "wof:placetype":"venue"
},
  "geometry": {"coordinates":[153.404174805,-27.9105949402],"type":"Point"}
}