{
  "type": "Feature",
  "properties": {
    "addr:full":"Shed 1/ 45 Arnold St Stratford QLD 4870",
    "addr:housenumber":"1 / 45",
    "addr:postcode":"4870",
    "addr:street":"Arnold St",
    "iso:country":"AU",
    "sg:address":"Shed 1/ 45 Arnold St",
    "sg:city":"Stratford",
    "sg:classifiers":[
        {
            "category":"Autos & Motor Vehicles",
            "subcategory":"Motorcycle Sales",
            "type":"Retail Goods"
        }
    ],
    "sg:phone":"+61 7 4058 2001",
    "sg:postcode":"4870",
    "sg:province":"QLD",
    "sg:tags":[
        "outboard"
    ],
    "wof:name":"Boats &#039;R&#039; Us",
    "wof:placetype":"venue"
},
  "geometry": {"coordinates":[145.739624023,-16.8719425201],"type":"Point"}
}