{
  "type": "Feature",
  "properties": {
    "iso:country":"AU",
    "sg:address":"12- 16 Bream St",
    "sg:city":"Tin Can Bay",
    "sg:classifiers":[
        {
            "category":"Travel",
            "subcategory":"Hotels & Motels",
            "type":"Entertainment"
        }
    ],
    "sg:phone":"+61 7 5486 4124",
    "sg:postcode":"4580",
    "sg:province":"QLD",
    "wof:name":"Sleepy Lagoon Hotel Motel",
    "wof:placetype":"venue"
},
  "geometry": {"coordinates":[153.00462341299999,-25.9122009277],"type":"Point"}
}