{
  "type": "Feature",
  "properties": {
    "iso:country":"AU",
    "sg:address":"27 Ryan Rd",
    "sg:city":"Virginia",
    "sg:classifiers":[
        {
            "category":"Wholesale",
            "subcategory":"Electrical",
            "type":"Manufacturing & Wholesale Goods"
        }
    ],
    "sg:phone":"+61 417 882 576",
    "sg:postcode":"0835",
    "sg:province":"NT",
    "sg:tags":[
        "control",
        "equipment",
        "switch"
    ],
    "wof:name":"DMAK Electrical",
    "wof:placetype":"venue"
},
  "geometry": {"coordinates":[131.02536000000001,-12.523226],"type":"Point"}
}