{
  "type": "Feature",
  "properties": {
    "addr:full":"174 Margaret St Toowoomba QLD 4350",
    "addr:housenumber":"174",
    "addr:postcode":"4350",
    "addr:street":"Margaret St",
    "iso:country":"AU",
    "sg:address":"174 Margaret St",
    "sg:city":"Toowoomba",
    "sg:classifiers":[
        {
            "category":"Banks & Credit Unions",
            "subcategory":"Financial Services",
            "type":"Services"
        }
    ],
    "sg:phone":"+61 7 4632 9633",
    "sg:postcode":"4350",
    "sg:province":"QLD",
    "sg:tags":[
        "financier"
    ],
    "wof:name":"GE Finance & Insurance",
    "wof:placetype":"venue"
},
  "geometry": {"coordinates":[151.95457500000001,-27.561279],"type":"Point"}
}