{
  "type": "Feature",
  "properties": {
    "addr:full":"50 Morgan St Fortitude Valley QLD 4006",
    "addr:housenumber":"50",
    "addr:postcode":"4006",
    "addr:street":"Morgan St",
    "iso:country":"AU",
    "sg:address":"50 Morgan St",
    "sg:city":"Fortitude Valley",
    "sg:classifiers":[
        {
            "category":"Shopping",
            "subcategory":"Bridal",
            "type":"Retail Goods"
        }
    ],
    "sg:phone":"+61 7 3852 1423",
    "sg:postcode":"4006",
    "sg:province":"QLD",
    "sg:tags":[
        "hire",
        "wear"
    ],
    "wof:name":"93 Collections",
    "wof:placetype":"venue"
},
  "geometry": {"coordinates":[153.03785705600001,-27.4572029114],"type":"Point"}
}