{
  "type": "Feature",
  "properties": {
    "iso:country":"AU",
    "sg:address":"11 Bonton Ave",
    "sg:city":"Deception Bay",
    "sg:classifiers":[
        {
            "category":"Professional",
            "subcategory":"Employment Agencies",
            "type":"Services"
        }
    ],
    "sg:phone":"+61 417 796 552",
    "sg:postcode":"4508",
    "sg:province":"QLD",
    "sg:tags":[
        "entertainer",
        "agent"
    ],
    "wof:name":"Caesar",
    "wof:placetype":"venue"
},
  "geometry": {"coordinates":[153.0340271,-27.1979656219],"type":"Point"}
}