{
  "type": "Feature",
  "properties": {
    "iso:country":"AU",
    "sg:address":"25b Railway Pde",
    "sg:city":"Kogarah",
    "sg:classifiers":[
        {
            "category":"Personal",
            "subcategory":"Beauty Salon",
            "type":"Services"
        }
    ],
    "sg:phone":"+61 2 9553 6055",
    "sg:postcode":"2217",
    "sg:province":"NSW",
    "sg:tags":[
        "hairdresser"
    ],
    "wof:name":"Koko's Hair Studio",
    "wof:placetype":"venue"
},
  "geometry": {"coordinates":[151.132477,-33.963276],"type":"Point"}
}