{
  "type": "Feature",
  "properties": {
    "addr:full":"64 Lucerne Crs Karingal VIC 3199",
    "addr:housenumber":"64",
    "addr:postcode":"3199",
    "addr:street":"Lucerne Crs",
    "iso:country":"AU",
    "sg:address":"64 Lucerne Crs",
    "sg:city":"Karingal",
    "sg:classifiers":[
        {
            "category":"Professional",
            "type":"Services"
        }
    ],
    "sg:phone":"+61 3 9789 2886",
    "sg:postcode":"3199",
    "sg:province":"VIC",
    "sg:tags":[
        "shop",
        "fitting"
    ],
    "wof:name":"Advance Shopfitters & Maintenance Pty Limited",
    "wof:placetype":"venue"
},
  "geometry": {"coordinates":[145.152832031,-38.1436195374],"type":"Point"}
}