{
  "type": "Feature",
  "properties": {
    "addr:full":"88 Maitland St Narrabri NSW 2390",
    "addr:housenumber":"88",
    "addr:postcode":"2390",
    "addr:street":"Maitland St",
    "iso:country":"AU",
    "sg:address":"88 Maitland St",
    "sg:city":"Narrabri",
    "sg:classifiers":[
        {
            "category":"Retail",
            "subcategory":"Funeral Services",
            "type":"Services"
        }
    ],
    "sg:phone":"+61 2 6799 1316",
    "sg:postcode":"2390",
    "sg:province":"NSW",
    "sg:tags":[
        "director"
    ],
    "wof:name":"Logan & Co Pty Ltd",
    "wof:placetype":"venue"
},
  "geometry": {"coordinates":[149.78436279300001,-30.3271560669],"type":"Point"}
}