{
  "type": "Feature",
  "properties": {
    "addr:full":"187 Caroline Chisholm Drv Winston Hills NSW 2153",
    "addr:housenumber":"187",
    "addr:postcode":"2153",
    "addr:street":"Caroline Chisholm Drv",
    "iso:country":"AU",
    "sg:address":"187 Caroline Chisholm Drv",
    "sg:city":"Winston Hills",
    "sg:classifiers":[
        {
            "category":"Health Services",
            "subcategory":"Chiropractor",
            "type":"Services"
        }
    ],
    "sg:phone":"+61 2 9838 7699",
    "sg:postcode":"2153",
    "sg:province":"NSW",
    "wof:name":"Nurturing Hands Chiropractic",
    "wof:placetype":"venue"
},
  "geometry": {"coordinates":[150.97018432600001,-33.7734985352],"type":"Point"}
}