{
  "type": "Feature",
  "properties": {
    "addr:full":"9 Santa Monica Pde Iluka WA 6028",
    "addr:housenumber":"9",
    "addr:postcode":"6028",
    "addr:street":"Santa Monica Pde",
    "iso:country":"AU",
    "sg:address":"9 Santa Monica Pde",
    "sg:city":"Iluka",
    "sg:classifiers":[
        {
            "category":"Shopping",
            "type":"Retail Goods"
        }
    ],
    "sg:phone":"+61 8 9305 3579",
    "sg:postcode":"6028",
    "sg:province":"WA",
    "sg:tags":[
        "equipment",
        "safety",
        "accessory"
    ],
    "wof:name":"Glen Millington",
    "wof:placetype":"venue"
},
  "geometry": {"coordinates":[115.734512329,-31.7397460938],"type":"Point"}
}