{
  "type": "Feature",
  "properties": {
    "addr:full":"Shop 22/ 22 Enmore Rd Enmore NSW 2042",
    "addr:housenumber":"shop 22 / 22",
    "addr:postcode":"2042",
    "addr:street":"Enmore Rd",
    "iso:country":"AU",
    "sg:address":"Shop 22/ 22 Enmore Rd",
    "sg:city":"Enmore",
    "sg:classifiers":[
        {
            "category":"Home & Garden",
            "subcategory":"Carpets & Floor Coverings",
            "type":"Retail Goods"
        }
    ],
    "sg:phone":"+61 417 040 502",
    "sg:postcode":"2042",
    "sg:province":"NSW",
    "sg:tags":[
        "layer"
    ],
    "wof:name":"Platinum Flooring",
    "wof:placetype":"venue"
},
  "geometry": {"coordinates":[151.17555200000001,-33.898754],"type":"Point"}
}