{
  "type": "Feature",
  "properties": {
    "iso:country":"AU",
    "sg:address":"12 Como Ave",
    "sg:city":"South Yarra",
    "sg:classifiers":[
        {
            "category":"Professional",
            "subcategory":"Computer Services",
            "type":"Services"
        }
    ],
    "sg:phone":"+61 3 9826 5300",
    "sg:postcode":"3141",
    "sg:province":"VIC",
    "sg:tags":[
        "consultant",
        "system"
    ],
    "wof:name":"Jorgen Computer Services- J C S Pty Ltd",
    "wof:placetype":"venue"
},
  "geometry": {"coordinates":[145.00262451200001,-37.838722229],"type":"Point"}
}