{
  "type": "Feature",
  "properties": {
    "iso:country":"AU",
    "sg:address":"27-33 Yana St",
    "sg:city":"Swan Hill",
    "sg:classifiers":[
        {
            "category":"Education",
            "subcategory":"School",
            "type":"Public Place"
        }
    ],
    "sg:phone":"+61 3 5032 3683",
    "sg:postcode":"3585",
    "sg:province":"VIC",
    "sg:tags":[
        "state",
        "except",
        "nsw"
    ],
    "wof:name":"Swan Hill Specialist School",
    "wof:placetype":"venue"
},
  "geometry": {"coordinates":[143.54441800000001,-35.34922],"type":"Point"}
}