{
  "type": "Feature",
  "properties": {
    "iso:country":"AU",
    "sg:address":"144- 146 Bellevue Pde",
    "sg:city":"Carlton",
    "sg:classifiers":[
        {
            "category":"Professional",
            "subcategory":"Engineering",
            "type":"Services"
        }
    ],
    "sg:phone":"+61 2 9546 1620",
    "sg:postcode":"2218",
    "sg:province":"NSW",
    "sg:tags":[
        "diesel",
        "engineer"
    ],
    "wof:name":"Gemini Diesel Fuel Injection Service Pty. Ltd.",
    "wof:placetype":"venue"
},
  "geometry": {"coordinates":[151.11599699999999,-33.978931],"type":"Point"}
}