{
  "type": "Feature",
  "properties": {
    "iso:country":"AU",
    "sg:address":"Newman Drv",
    "sg:city":"Newman",
    "sg:classifiers":[
        {
            "category":"Autos & Motor Vehicles",
            "subcategory":"Fuel & Gas Station",
            "type":"Retail Goods"
        }
    ],
    "sg:phone":"+61 8 9175 1521",
    "sg:postcode":"6753",
    "sg:province":"WA",
    "wof:name":"BP Australia Limited",
    "wof:placetype":"venue"
},
  "geometry": {"coordinates":[119.74266815199999,-23.3473796844],"type":"Point"}
}