{
  "type": "Feature",
  "properties": {
    "iso:country":"AU",
    "sg:address":"PO Box 654",
    "sg:city":"Springwood BC",
    "sg:classifiers":[
        {
            "category":"Autos & Motor Vehicles",
            "subcategory":"Auto Supplies",
            "type":"Retail Goods"
        }
    ],
    "sg:phone":"+61 7 3380 2222",
    "sg:postcode":"4127",
    "sg:province":"QLD",
    "sg:tags":[
        "part",
        "cycles",
        "accessory"
    ],
    "wof:name":"Team Moto Motorcycles",
    "wof:placetype":"venue"
},
  "geometry": {"coordinates":[153.125930786,-27.6125297546],"type":"Point"}
}