{
  "type": "Feature",
  "properties": {
    "addr:full":"15 Burgay Crt Osborne Park WA 6017",
    "addr:housenumber":"15",
    "addr:postcode":"6017",
    "addr:street":"Burgay Crt",
    "iso:country":"AU",
    "sg:address":"15 Burgay Crt",
    "sg:city":"Osborne Park",
    "sg:classifiers":[
        {
            "category":"Manufacturing",
            "subcategory":"Furniture",
            "type":"Manufacturing & Wholesale Goods"
        }
    ],
    "sg:phone":"+61 8 9204 4848",
    "sg:postcode":"6017",
    "sg:province":"WA",
    "sg:tags":[
        "builder",
        "designer",
        "custom"
    ],
    "wof:name":"Urban Wood",
    "wof:placetype":"venue"
},
  "geometry": {"coordinates":[115.803672791,-31.9067840576],"type":"Point"}
}