{
  "type": "Feature",
  "properties": {
    "addr:full":"30 Bay St Double Bay NSW 2028",
    "addr:housenumber":"30",
    "addr:postcode":"2028",
    "addr:street":"Bay St",
    "iso:country":"AU",
    "sg:address":"30 Bay St",
    "sg:city":"Double Bay",
    "sg:classifiers":[
        {
            "category":"Food & Beverages",
            "subcategory":"Specialty",
            "type":"Retail Goods"
        }
    ],
    "sg:phone":"+61 2 9327 8002",
    "sg:postcode":"2028",
    "sg:province":"NSW",
    "sg:tags":[
        "product",
        "health"
    ],
    "wof:name":"Bayside Natural Health Centre",
    "wof:placetype":"venue"
},
  "geometry": {"coordinates":[151.24217224099999,-33.8754615784],"type":"Point"}
}