{
  "type": "Feature",
  "properties": {
    "iso:country":"AU",
    "sg:address":"44 Wollongong St",
    "sg:city":"Fyshwick",
    "sg:classifiers":[
        {
            "category":"Retail",
            "subcategory":"Auto Repair",
            "type":"Services"
        }
    ],
    "sg:phone":"+61 2 6222 1900",
    "sg:postcode":"2609",
    "sg:province":"ACT",
    "sg:tags":[
        "repairer",
        "motor",
        "engineer"
    ],
    "wof:name":"Canberra Toyota",
    "wof:placetype":"venue"
},
  "geometry": {"coordinates":[149.17965698200001,-35.3253898621],"type":"Point"}
}