{
  "type": "Feature",
  "properties": {
    "iso:country":"AU",
    "sg:address":"21 Tibrogargan Pl",
    "sg:city":"Pelican Waters",
    "sg:classifiers":[
        {
            "category":"Social Services",
            "subcategory":"Retirement Home",
            "type":"Services"
        }
    ],
    "sg:phone":"+61 7 5492 4601",
    "sg:postcode":"4551",
    "sg:province":"QLD",
    "sg:tags":[
        "environmental",
        "consultant",
        "pollution"
    ],
    "wof:name":"Mike Bugler & Associates Environtmental Consultants",
    "wof:placetype":"venue"
},
  "geometry": {"coordinates":[153.09881591800001,-26.8348827362],"type":"Point"}
}