{
  "type": "Feature",
  "properties": {
    "iso:country":"AU",
    "sg:address":"Lawrence Drive Tavern 55 Lawrence Drv",
    "sg:city":"Nerang",
    "sg:classifiers":[
        {
            "category":"Food & Beverages",
            "subcategory":"Liquor & Beverages",
            "type":"Retail Goods"
        }
    ],
    "sg:phone":"+61 7 5596 6610",
    "sg:postcode":"4211",
    "sg:province":"QLD",
    "sg:tags":[
        "store"
    ],
    "wof:name":"Liquorwise",
    "wof:placetype":"venue"
},
  "geometry": {"coordinates":[153.346633911,-27.9975337982],"type":"Point"}
}