{
  "type": "Feature",
  "properties": {
    "addr:full":"11 Itea Crt Regents Park QLD 4118",
    "addr:housenumber":"11",
    "addr:postcode":"4118",
    "addr:street":"Itea Crt",
    "iso:country":"AU",
    "sg:address":"11 Itea Crt",
    "sg:city":"Regents Park",
    "sg:classifiers":[
        {
            "category":"Manufacturing",
            "subcategory":"Tools & Machinery",
            "type":"Manufacturing & Wholesale Goods"
        }
    ],
    "sg:phone":"+61 7 3800 6525",
    "sg:postcode":"4118",
    "sg:province":"QLD",
    "sg:tags":[
        "supplier",
        "diamond"
    ],
    "wof:name":"Briscon Pty Ltd",
    "wof:placetype":"venue"
},
  "geometry": {"coordinates":[153.033035278,-27.6761722565],"type":"Point"}
}