{
  "type": "Feature",
  "properties": {
    "addr:full":"218 Woodpark Rd Smithfield NSW 2164",
    "addr:housenumber":"218",
    "addr:postcode":"2164",
    "addr:street":"Woodpark Rd",
    "iso:country":"AU",
    "sg:address":"218 Woodpark Rd",
    "sg:city":"Smithfield",
    "sg:classifiers":[
        {
            "category":"Retail",
            "subcategory":"Auto Repair",
            "type":"Services"
        }
    ],
    "sg:phone":"+61 2 9609 7785",
    "sg:postcode":"2164",
    "sg:province":"NSW",
    "sg:tags":[
        "repairer",
        "motor",
        "engineer"
    ],
    "wof:name":"Electronic Fuel Injection Service Centre",
    "wof:placetype":"venue"
},
  "geometry": {"coordinates":[150.93457031200001,-33.836517334],"type":"Point"}
}