{
  "type": "Feature",
  "properties": {
    "iso:country":"AU",
    "sg:address":"PO Box 1073",
    "sg:city":"Morwell",
    "sg:classifiers":[
        {
            "category":"Building & Trades",
            "subcategory":"Construction",
            "type":"Services"
        }
    ],
    "sg:phone":"+61 3 5166 1687",
    "sg:postcode":"3840",
    "sg:province":"VIC",
    "sg:tags":[
        "earth",
        "excavating",
        "moving",
        "contractor"
    ],
    "wof:name":"Kistler Bros",
    "wof:placetype":"venue"
},
  "geometry": {"coordinates":[146.39114379899999,-38.2888298035],"type":"Point"}
}