{
  "type": "Feature",
  "properties": {
    "addr:full":"Factory 4/ 265 Wickham Rd Moorabbin VIC 3189",
    "addr:housenumber":"/ 265",
    "addr:postcode":"3189",
    "addr:street":"Wickham Rd",
    "iso:country":"AU",
    "sg:address":"Factory 4/ 265 Wickham Rd",
    "sg:city":"Moorabbin",
    "sg:classifiers":[
        {
            "category":"Utilities",
            "subcategory":"Water",
            "type":"Services"
        }
    ],
    "sg:phone":"+61 3 9556 9336",
    "sg:postcode":"3189",
    "sg:province":"VIC",
    "sg:tags":[
        "hot",
        "system"
    ],
    "wof:name":"Red Hot Hot Water",
    "wof:placetype":"venue"
},
  "geometry": {"coordinates":[145.05499267600001,-37.9465560913],"type":"Point"}
}