{
  "type": "Feature",
  "properties": {
    "addr:full":"1010A Sturt St Ballarat VIC 3350",
    "addr:housenumber":"1010a",
    "addr:postcode":"3350",
    "addr:street":"Sturt St",
    "iso:country":"AU",
    "sg:address":"1010A Sturt St",
    "sg:city":"Ballarat",
    "sg:classifiers":[
        {
            "category":"Health Services",
            "subcategory":"Doctor",
            "type":"Services"
        }
    ],
    "sg:phone":"+61 3 5332 1421",
    "sg:postcode":"3350",
    "sg:province":"VIC",
    "sg:tags":[
        "medical",
        "practitioner"
    ],
    "wof:name":"Sturt Medical Practice",
    "wof:placetype":"venue"
},
  "geometry": {"coordinates":[143.845169,-37.560169],"type":"Point"}
}