{
  "type": "Feature",
  "properties": {
    "addr:full":"Goodeedawa Rd Doomadgee QLD 4830",
    "addr:postcode":"4830",
    "addr:street":"Goodeedawa Rd",
    "iso:country":"AU",
    "sg:address":"Goodeedawa Rd",
    "sg:city":"Doomadgee",
    "sg:classifiers":[
        {
            "category":"Organizations",
            "subcategory":"Community Association",
            "type":"Services"
        }
    ],
    "sg:phone":"+61 7 4745 8234",
    "sg:postcode":"4830",
    "sg:province":"QLD",
    "sg:tags":[
        "organisation",
        "family",
        "welfare"
    ],
    "wof:name":"Womens Shelter The",
    "wof:placetype":"venue"
},
  "geometry": {"coordinates":[138.825943,-17.943193],"type":"Point"}
}