{
  "type": "Feature",
  "properties": {
    "addr:full":"PO Box 2078 Magill North SA 5072",
    "addr:postcode":"5072",
    "iso:country":"AU",
    "sg:address":"PO Box 2078",
    "sg:city":"Magill North",
    "sg:classifiers":[
        {
            "category":"Utilities",
            "subcategory":"Electric",
            "type":"Services"
        }
    ],
    "sg:phone":"+61 417 822 204",
    "sg:postcode":"5072",
    "sg:province":"SA",
    "sg:tags":[
        "electrical",
        "contractor"
    ],
    "wof:name":"Wattage You Need Electrical",
    "wof:placetype":"venue"
},
  "geometry": {"coordinates":[138.67417907699999,-34.902431488],"type":"Point"}
}