{
  "type": "Feature",
  "properties": {
    "addr:full":"Unit 11/ 37-47 Borec Rd Penrith NSW 2750",
    "addr:housenumber":"/ 37-47",
    "addr:postcode":"2750",
    "addr:street":"Borec Rd",
    "iso:country":"AU",
    "sg:address":"Unit 11/ 37-47 Borec Rd",
    "sg:city":"Penrith",
    "sg:classifiers":[
        {
            "category":"Banks & Credit Unions",
            "subcategory":"Bank",
            "type":"Services"
        }
    ],
    "sg:phone":"+61 2 4721 4833",
    "sg:postcode":"2750",
    "sg:province":"NSW",
    "sg:tags":[
        "line",
        "marking",
        "road"
    ],
    "sg:website":"http://www.ultralinemarking.com.au",
    "wof:name":"Ultra Linemarking",
    "wof:placetype":"venue"
},
  "geometry": {"coordinates":[150.69090270999999,-33.7366142273],"type":"Point"}
}