{
  "type": "Feature",
  "properties": {
    "iso:country":"AU",
    "sg:address":"Unit 4/ 9a Ponderosa Pde",
    "sg:city":"Warriewood",
    "sg:classifiers":[
        {
            "category":"Community Center",
            "subcategory":"Ethnic",
            "type":"Public Place"
        }
    ],
    "sg:phone":"+61 2 9999 4377",
    "sg:postcode":"2102",
    "sg:province":"NSW",
    "sg:tags":[
        "window",
        "pvc"
    ],
    "wof:name":"Easy Windows",
    "wof:placetype":"venue"
},
  "geometry": {"coordinates":[151.28804,-33.682026],"type":"Point"}
}