{
  "type": "Feature",
  "properties": {
    "addr:full":"59 Power Crs Port Augusta SA 5700",
    "addr:housenumber":"59",
    "addr:postcode":"5700",
    "addr:street":"Power Crs",
    "iso:country":"AU",
    "sg:address":"59 Power Crs",
    "sg:city":"Port Augusta",
    "sg:classifiers":[
        {
            "category":"Education",
            "subcategory":"School",
            "type":"Public Place"
        }
    ],
    "sg:phone":"+61 8 8642 2077",
    "sg:postcode":"5700",
    "sg:province":"SA",
    "sg:tags":[
        "state",
        "except",
        "nsw"
    ],
    "wof:name":"School Of The Air",
    "wof:placetype":"venue"
},
  "geometry": {"coordinates":[137.78460693400001,-32.5366020203],"type":"Point"}
}