{
  "type": "Feature",
  "properties": {
    "addr:full":"109 Marian St Mt Isa QLD 4825",
    "addr:housenumber":"109",
    "addr:postcode":"4825",
    "addr:street":"Marian St",
    "iso:country":"AU",
    "sg:address":"109 Marian St",
    "sg:city":"Mt Isa",
    "sg:classifiers":[
        {
            "category":"Social Services",
            "subcategory":"Child Care",
            "type":"Services"
        }
    ],
    "sg:phone":"+61 7 4743 2859",
    "sg:postcode":"4825",
    "sg:province":"QLD",
    "wof:name":"St Paul's Lutheran Church Child Care Centre",
    "wof:placetype":"venue"
},
  "geometry": {"coordinates":[139.495834,-20.726288],"type":"Point"}
}