{
  "type": "Feature",
  "properties": {
    "addr:full":"171 Stoney Rise Rd Devonport TAS 7310",
    "addr:housenumber":"171",
    "addr:postcode":"7310",
    "addr:street":"Stoney Rise Rd",
    "iso:country":"AU",
    "sg:address":"171 Stoney Rise Rd",
    "sg:city":"Devonport",
    "sg:classifiers":[
        {
            "category":"Wholesale",
            "subcategory":"Machinery & Supplies",
            "type":"Manufacturing & Wholesale Goods"
        }
    ],
    "sg:phone":"+61 3 6420 6900",
    "sg:postcode":"7310",
    "sg:province":"TAS",
    "sg:tags":[
        "equipment",
        "hydraulic"
    ],
    "wof:name":"Delta Hydraulics",
    "wof:placetype":"venue"
},
  "geometry": {"coordinates":[146.32606506400001,-41.1886672974],"type":"Point"}
}