{
  "type": "Feature",
  "properties": {
    "addr:full":"Unit 3 45 Biscayne Way Jandakot WA 6164",
    "addr:housenumber":"45",
    "addr:postcode":"6164",
    "addr:street":"Biscayne Way",
    "iso:country":"AU",
    "sg:address":"Unit 3 45",
    "sg:city":"Biscayne Way Jandakot",
    "sg:classifiers":[
        {
            "category":"Building & Trades",
            "subcategory":"Locksmith",
            "type":"Services"
        }
    ],
    "sg:phone":"+61 417 391 904",
    "sg:postcode":"6164",
    "sg:province":"WA",
    "sg:tags":[
        "lock"
    ],
    "wof:name":"AAA Ability Locksmiths",
    "wof:placetype":"venue"
},
  "geometry": {"coordinates":[115.87233000000001,-32.121716],"type":"Point"}
}