{
  "type": "Feature",
  "properties": {
    "addr:full":"757 Glenhuntly Rd Caulfield VIC 3162",
    "addr:housenumber":"757",
    "addr:postcode":"3162",
    "addr:street":"Glenhuntly Rd",
    "iso:country":"AU",
    "sg:address":"757 Glenhuntly Rd",
    "sg:city":"Caulfield",
    "sg:classifiers":[
        {
            "category":"Professional",
            "subcategory":"Printing & Photocopies",
            "type":"Services"
        }
    ],
    "sg:phone":"+61 3 9533 0388",
    "sg:postcode":"3162",
    "sg:province":"VIC",
    "sg:tags":[
        "photocopying"
    ],
    "wof:name":"Minuteman Press",
    "wof:placetype":"venue"
},
  "geometry": {"coordinates":[145.020996094,-37.8866233826],"type":"Point"}
}