{
  "type": "Feature",
  "properties": {
    "addr:full":"Unit 26/ 33 Queens Rd Melbourne VIC 3000",
    "addr:housenumber":"/ 33",
    "addr:postcode":"3000",
    "addr:street":"Queens Rd",
    "iso:country":"AU",
    "sg:address":"Unit 26/ 33 Queens Rd",
    "sg:city":"Melbourne",
    "sg:classifiers":[
        {
            "category":"Professional",
            "subcategory":"Business Services",
            "type":"Services"
        }
    ],
    "sg:phone":"+61 3 9866 6033",
    "sg:postcode":"3000",
    "sg:province":"VIC",
    "sg:tags":[
        "consultant",
        "leasing"
    ],
    "wof:name":"Leasecorp Australia Pty Ltd",
    "wof:placetype":"venue"
},
  "geometry": {"coordinates":[144.976287842,-37.8442878723],"type":"Point"}
}