{
  "type": "Feature",
  "properties": {
    "addr:full":"150 Barwon Heads Rd Belmont VIC 3216",
    "addr:housenumber":"150",
    "addr:postcode":"3216",
    "addr:street":"Barwon Heads Rd",
    "iso:country":"AU",
    "sg:address":"150 Barwon Heads Rd",
    "sg:city":"Belmont",
    "sg:classifiers":[
        {
            "category":"Wholesale",
            "subcategory":"Farm Supplies",
            "type":"Manufacturing & Wholesale Goods"
        }
    ],
    "sg:phone":"+61 3 5241 3713",
    "sg:postcode":"3216",
    "sg:province":"VIC",
    "sg:tags":[
        "feed",
        "supplement",
        "stock"
    ],
    "wof:name":"Petstock Animal Supplies",
    "wof:placetype":"venue"
},
  "geometry": {"coordinates":[144.35386657699999,-38.1812782288],"type":"Point"}
}