{
  "type": "Feature",
  "properties": {
    "iso:country":"AU",
    "sg:address":"164 Bank St",
    "sg:city":"South Melbourne",
    "sg:classifiers":[
        {
            "category":"Banks & Credit Unions",
            "subcategory":"Financial Services",
            "type":"Services"
        }
    ],
    "sg:phone":"+61 3 9699 1799",
    "sg:postcode":"3205",
    "sg:province":"VIC",
    "sg:tags":[
        "franchising"
    ],
    "wof:name":"Melbourne Business ConneXions",
    "wof:placetype":"venue"
},
  "geometry": {"coordinates":[144.962585,-37.833546],"type":"Point"}
}