{
  "type": "Feature",
  "properties": {
    "iso:country":"AU",
    "sg:address":"3 Waratah Pl",
    "sg:city":"Yeppoon",
    "sg:classifiers":[
        {
            "category":"Professional",
            "subcategory":"Engineering",
            "type":"Services"
        }
    ],
    "sg:phone":"+61 7 4939 1264",
    "sg:postcode":"4703",
    "sg:province":"QLD",
    "sg:tags":[
        "consulting",
        "engineer"
    ],
    "wof:name":"Windress Mark",
    "wof:placetype":"venue"
},
  "geometry": {"coordinates":[150.753982544,-23.1498985291],"type":"Point"}
}