{
  "type": "Feature",
  "properties": {
    "iso:country":"AU",
    "sg:address":"63 Hamilton Pl",
    "sg:city":"Mt Waverley",
    "sg:classifiers":[
        {
            "category":"Food & Beverages",
            "subcategory":"Fruits & Vegetables",
            "type":"Retail Goods"
        }
    ],
    "sg:phone":"+61 3 9807 6367",
    "sg:postcode":"3149",
    "sg:province":"VIC",
    "sg:tags":[
        "greengrocer",
        "fruiterer"
    ],
    "wof:name":"Commisso F & F",
    "wof:placetype":"venue"
},
  "geometry": {"coordinates":[145.12809753400001,-37.8770980835],"type":"Point"}
}