{
  "type": "Feature",
  "properties": {
    "addr:full":"First Floor, 15 Edgar St Ainslie ACT 2602",
    "addr:housenumber":"15",
    "addr:postcode":"2602",
    "addr:street":"Floor;Edgar St",
    "iso:country":"AU",
    "sg:address":"First Floor, 15 Edgar St",
    "sg:city":"Ainslie",
    "sg:classifiers":[
        {
            "category":"Professional",
            "subcategory":"Art Services",
            "type":"Services"
        }
    ],
    "sg:phone":"+61 2 6230 1101",
    "sg:postcode":"2602",
    "sg:province":"ACT",
    "sg:tags":[
        "graphic",
        "designer"
    ],
    "sg:website":"http://www.nichesbc.com",
    "wof:name":"NICHE Strategic Brand Communication",
    "wof:placetype":"venue"
},
  "geometry": {"coordinates":[149.145294189,-35.261844635],"type":"Point"}
}