{
  "type": "Feature",
  "properties": {
    "addr:full":"89 Farrant St Stafford Heights QLD 4053",
    "addr:housenumber":"89",
    "addr:postcode":"4053",
    "addr:street":"Farrant St",
    "iso:country":"AU",
    "sg:address":"89 Farrant St",
    "sg:city":"Stafford Heights",
    "sg:classifiers":[
        {
            "category":"Building & Trades",
            "subcategory":"Landscaping Services",
            "type":"Services"
        }
    ],
    "sg:phone":"+61 7 3861 5075",
    "sg:postcode":"4053",
    "sg:province":"QLD",
    "sg:tags":[
        "consultant"
    ],
    "wof:name":"Henderson Carmel",
    "wof:placetype":"venue"
},
  "geometry": {"coordinates":[153.00932312,-27.3971881866],"type":"Point"}
}