{
  "type": "Feature",
  "properties": {
    "addr:full":"193 Ripley Rd Ipswich QLD 4305",
    "addr:housenumber":"193",
    "addr:postcode":"4305",
    "addr:street":"Ripley Rd",
    "iso:country":"AU",
    "sg:address":"193 Ripley Rd",
    "sg:city":"Ipswich",
    "sg:classifiers":[
        {
            "category":"Building & Trades",
            "subcategory":"Pest Control",
            "type":"Services"
        }
    ],
    "sg:phone":"+61 7 3288 8888",
    "sg:postcode":"4305",
    "sg:province":"QLD",
    "sg:tags":[
        "breastfeeding",
        "support"
    ],
    "wof:name":"Karen Hayes Lactation Services",
    "wof:placetype":"venue"
},
  "geometry": {"coordinates":[152.77398681599999,-27.6488933563],"type":"Point"}
}