{
  "type": "Feature",
  "properties": {
    "addr:full":"389 West Mt Cotton Rd Mt Cotton QLD 4165",
    "addr:housenumber":"389",
    "addr:postcode":"4165",
    "addr:street":"West Mt Cotton Rd",
    "iso:country":"AU",
    "sg:address":"389 West Mt Cotton Rd",
    "sg:city":"Mt Cotton",
    "sg:classifiers":[
        {
            "category":"Farming",
            "subcategory":"Nursery",
            "type":"Manufacturing & Wholesale Goods"
        }
    ],
    "sg:phone":"+61 7 3206 6354",
    "sg:postcode":"4165",
    "sg:province":"QLD",
    "wof:name":"West Mt Cotton Wholesale Nursery",
    "wof:placetype":"venue"
},
  "geometry": {"coordinates":[153.20799255399999,-27.602935791],"type":"Point"}
}