{
  "type": "Feature",
  "properties": {
    "addr:full":"8/ 557 Pittwater Rd Brookvale NSW 2100",
    "addr:housenumber":"/ 557",
    "addr:postcode":"2100",
    "addr:street":"Pittwater Rd",
    "iso:country":"AU",
    "sg:address":"8/ 557 Pittwater Rd",
    "sg:city":"Brookvale",
    "sg:classifiers":[
        {
            "category":"Education",
            "subcategory":"Junior College",
            "type":"Public Place"
        }
    ],
    "sg:phone":"+61 2 9905 2389",
    "sg:postcode":"2100",
    "sg:province":"NSW",
    "sg:tags":[
        "business"
    ],
    "wof:name":"Bookkeeper People",
    "wof:placetype":"venue"
},
  "geometry": {"coordinates":[151.27671814000001,-33.7609405518],"type":"Point"}
}