{
  "type": "Feature",
  "properties": {
    "addr:full":"Carlingford Court, Cnr Carlingford & Pennant Hills Rds Carlingford NSW 2118",
    "addr:postcode":"2118",
    "addr:street":"Cnr",
    "iso:country":"AU",
    "sg:address":"Carlingford Court, Cnr Carlingford & Pennant Hills Rds",
    "sg:city":"Carlingford",
    "sg:classifiers":[
        {
            "category":"Sports & Exercise",
            "subcategory":"Gym",
            "type":"Entertainment"
        }
    ],
    "sg:phone":"+61 2 9872 7666",
    "sg:postcode":"2118",
    "sg:province":"NSW",
    "sg:tags":[
        "health",
        "fitness"
    ],
    "wof:name":"Fitness First Australia Pty Limited",
    "wof:placetype":"venue"
},
  "geometry": {"coordinates":[151.05491638199999,-33.7770309448],"type":"Point"}
}