{
  "type": "Feature",
  "properties": {
    "iso:country":"AU",
    "sg:address":"306 Bay St",
    "sg:city":"Port Melbourne",
    "sg:classifiers":[
        {
            "category":"Professional",
            "subcategory":"Employment Agencies",
            "type":"Services"
        }
    ],
    "sg:phone":"+61 3 9646 8155",
    "sg:postcode":"3207",
    "sg:province":"VIC",
    "wof:name":"Innovative Recruitment",
    "wof:placetype":"venue"
},
  "geometry": {"coordinates":[144.943848,-37.837158],"type":"Point"}
}