{
  "type": "Feature",
  "properties": {
    "iso:country":"AU",
    "sg:address":"114 Darlinghurst Rd",
    "sg:city":"Darlinghurst",
    "sg:classifiers":[
        {
            "category":"Travel",
            "subcategory":"Hotels & Motels",
            "type":"Entertainment"
        }
    ],
    "sg:phone":"+61 2 9360 6868",
    "sg:postcode":"2010",
    "sg:province":"NSW",
    "sg:tags":[
        "accommodation"
    ],
    "wof:name":"L&#039;otel",
    "wof:placetype":"venue"
},
  "geometry": {"coordinates":[151.221435547,-33.8765830994],"type":"Point"}
}