{
  "type": "Feature",
  "properties": {
    "addr:full":"198 Hume Hwy Lansvale NSW 2166",
    "addr:housenumber":"198",
    "addr:postcode":"2166",
    "addr:street":"Hume Hwy",
    "iso:country":"AU",
    "sg:address":"198 Hume Hwy",
    "sg:city":"Lansvale",
    "sg:classifiers":[
        {
            "category":"Retail",
            "subcategory":"Storage",
            "type":"Services"
        }
    ],
    "sg:phone":"+61 2 9726 1888",
    "sg:postcode":"2166",
    "sg:province":"NSW",
    "sg:tags":[
        "removal",
        "furniture"
    ],
    "wof:name":"B & B Billiard Tables Pty Ltd",
    "wof:placetype":"venue"
},
  "geometry": {"coordinates":[150.95379638700001,-33.896812439],"type":"Point"}
}