{
  "type": "Feature",
  "properties": {
    "addr:full":"Shop 90 , Centro Mandurah, Mandurah WA 6210",
    "addr:housenumber":"shop 90",
    "addr:postcode":"6210",
    "iso:country":"AU",
    "sg:address":"Shop 90",
    "sg:city":", Centro Mandurah, Mandurah",
    "sg:classifiers":[
        {
            "category":"Shopping",
            "subcategory":"Jewelry",
            "type":"Retail Goods"
        }
    ],
    "sg:phone":"+61 8 9535 5724",
    "sg:postcode":"6210",
    "sg:province":"WA",
    "sg:tags":[
        "jeweller"
    ],
    "wof:name":"Zamels",
    "wof:placetype":"venue"
},
  "geometry": {"coordinates":[115.78473700000001,-32.509258],"type":"Point"}
}