{
  "type": "Feature",
  "properties": {
    "addr:full":"22 Charnfield Crt Thomastown VIC 3074",
    "addr:housenumber":"22",
    "addr:postcode":"3074",
    "addr:street":"Charnfield Crt",
    "iso:country":"AU",
    "sg:address":"22 Charnfield Crt",
    "sg:city":"Thomastown",
    "sg:classifiers":[
        {
            "category":"Professional",
            "subcategory":"Detective & Security Services",
            "type":"Services"
        }
    ],
    "sg:phone":"+61 3 9465 3841",
    "sg:postcode":"3074",
    "sg:province":"VIC",
    "sg:tags":[
        "equipment",
        "window",
        "doors"
    ],
    "wof:name":"Stylic Security Doors",
    "wof:placetype":"venue"
},
  "geometry": {"coordinates":[145.021026611,-37.6889190674],"type":"Point"}
}