{
  "type": "Feature",
  "properties": {
    "addr:full":"100 Market St South Melbourne VIC 3205",
    "addr:housenumber":"100",
    "addr:postcode":"3205",
    "addr:street":"Market St",
    "iso:country":"AU",
    "sg:address":"100 Market St",
    "sg:city":"South Melbourne",
    "sg:classifiers":[
        {
            "category":"Shopping",
            "subcategory":"Crafts & Fabrics",
            "type":"Retail Goods"
        }
    ],
    "sg:phone":"+61 3 9690 8899",
    "sg:postcode":"3205",
    "sg:province":"VIC",
    "sg:tags":[
        "material",
        "dress"
    ],
    "wof:name":"Spotlight",
    "wof:placetype":"venue"
},
  "geometry": {"coordinates":[144.95700099999999,-37.830109],"type":"Point"}
}