{
  "type": "Feature",
  "properties": {
    "addr:full":"Postcode 3115 Wheelers Hill VIC 3150",
    "addr:postcode":"3115;3150",
    "addr:street":"Postcode",
    "iso:country":"AU",
    "sg:address":"Postcode 3115",
    "sg:city":"Wheelers Hill",
    "sg:classifiers":[
        {
            "category":"Professional",
            "subcategory":"Detective & Security Services",
            "type":"Services"
        }
    ],
    "sg:phone":"+61 3 9803 7991",
    "sg:postcode":"3150",
    "sg:province":"VIC",
    "sg:tags":[
        "consultant",
        "system"
    ],
    "wof:name":"Technology Surveillance Group",
    "wof:placetype":"venue"
},
  "geometry": {"coordinates":[145.17460632300001,-37.863899231],"type":"Point"}
}