{
  "type": "Feature",
  "properties": {
    "iso:country":"AU",
    "sg:address":"2/ 88 Logan Rd",
    "sg:city":"Woolloongabba",
    "sg:classifiers":[
        {
            "category":"Building & Trades",
            "subcategory":"Construction",
            "type":"Services"
        }
    ],
    "sg:phone":"+61 13 88 31",
    "sg:postcode":"4102",
    "sg:province":"QLD",
    "sg:tags":[
        "window",
        "tinting"
    ],
    "wof:name":"SunGard",
    "wof:placetype":"venue"
},
  "geometry": {"coordinates":[153.039154053,-27.4898376465],"type":"Point"}
}