{
  "type": "Feature",
  "properties": {
    "addr:full":"195 Moorabool St Geelong VIC 3220",
    "addr:housenumber":"195",
    "addr:postcode":"3220",
    "addr:street":"Moorabool St",
    "iso:country":"AU",
    "sg:address":"195 Moorabool St",
    "sg:city":"Geelong",
    "sg:classifiers":[
        {
            "category":"Travel",
            "subcategory":"Hotels & Motels",
            "type":"Entertainment"
        }
    ],
    "sg:phone":"+61 3 5229 1211",
    "sg:postcode":"3220",
    "sg:province":"VIC",
    "sg:tags":[
        "accommodation"
    ],
    "wof:name":"National Hotel",
    "wof:placetype":"venue"
},
  "geometry": {"coordinates":[144.35952800000001,-38.15028],"type":"Point"}
}