{
  "type": "Feature",
  "properties": {
    "addr:full":"Cnr Great Western Hwy & Hewitt St Colyton NSW 2760",
    "addr:postcode":"2760",
    "addr:street":"Cnr Great Western Hwy & Hewitt St",
    "iso:country":"AU",
    "sg:address":"Cnr Great Western Hwy & Hewitt St",
    "sg:city":"Colyton",
    "sg:classifiers":[
        {
            "category":"Travel",
            "subcategory":"Hotels & Motels",
            "type":"Entertainment"
        }
    ],
    "sg:phone":"+61 2 9623 2266",
    "sg:postcode":"2760",
    "sg:province":"NSW",
    "sg:tags":[
        "accommodation"
    ],
    "wof:name":"Action Liquor",
    "wof:placetype":"venue"
},
  "geometry": {"coordinates":[150.79635620100001,-33.7753944397],"type":"Point"}
}