{
  "type": "Feature",
  "properties": {
    "addr:full":"Level 10/ 379 Queen St Brisbane QLD 4000",
    "addr:housenumber":"/ 379",
    "addr:postcode":"4000",
    "addr:street":"Queen St",
    "iso:country":"AU",
    "sg:address":"Level 10/ 379 Queen St",
    "sg:city":"Brisbane",
    "sg:classifiers":[
        {
            "category":"Professional",
            "subcategory":"Management & Consulting",
            "type":"Services"
        }
    ],
    "sg:phone":"+61 7 3229 2919",
    "sg:postcode":"4000",
    "sg:province":"QLD",
    "sg:tags":[
        "consultant"
    ],
    "wof:name":"Tooher Smart & Associates Pty Ltd",
    "wof:placetype":"venue"
},
  "geometry": {"coordinates":[153.03027343799999,-27.4659061432],"type":"Point"}
}