{
  "type": "Feature",
  "properties": {
    "addr:full":"320 Swansea Rd Lilydale VIC 3140",
    "addr:housenumber":"320",
    "addr:postcode":"3140",
    "addr:street":"Swansea Rd",
    "iso:country":"AU",
    "sg:address":"320 Swansea Rd",
    "sg:city":"Lilydale",
    "sg:classifiers":[
        {
            "category":"Banks & Credit Unions",
            "subcategory":"Financial Services",
            "type":"Services"
        }
    ],
    "sg:phone":"+61 3 9735 5974",
    "sg:postcode":"3140",
    "sg:province":"VIC",
    "sg:tags":[
        "planning"
    ],
    "sg:website":"http://www.fpa.asn.au",
    "wof:name":"Wealthplan Financial",
    "wof:placetype":"venue"
},
  "geometry": {"coordinates":[145.363845825,-37.7777099609],"type":"Point"}
}