{
  "type": "Feature",
  "properties": {
    "addr:full":"114 Edgecliff Rd Woollahra NSW 2025",
    "addr:housenumber":"114",
    "addr:postcode":"2025",
    "addr:street":"Edgecliff Rd",
    "iso:country":"AU",
    "sg:address":"114 Edgecliff Rd",
    "sg:city":"Woollahra",
    "sg:classifiers":[
        {
            "category":"Health Services",
            "subcategory":"Health Practitioner",
            "type":"Services"
        }
    ],
    "sg:phone":"+61 2 9369 4615",
    "sg:postcode":"2025",
    "sg:province":"NSW",
    "sg:tags":[
        "acupuncture"
    ],
    "wof:name":"Selecki Rupa H",
    "wof:placetype":"venue"
},
  "geometry": {"coordinates":[151.241943359,-33.88489151],"type":"Point"}
}