{
  "type": "Feature",
  "properties": {
    "addr:full":"30 Mayflower Crs Craigie WA 6025",
    "addr:housenumber":"30",
    "addr:postcode":"6025",
    "addr:street":"Mayflower Crs",
    "iso:country":"AU",
    "sg:address":"30 Mayflower Crs",
    "sg:city":"Craigie",
    "sg:classifiers":[
        {
            "category":"Building & Trades",
            "subcategory":"Cleaning & Sanitation",
            "type":"Services"
        }
    ],
    "sg:phone":"+61 8 9307 1141",
    "sg:postcode":"6025",
    "sg:province":"WA",
    "sg:tags":[
        "industrial",
        "commercial",
        "contractor"
    ],
    "wof:name":"A & M Cleaning Services",
    "wof:placetype":"venue"
},
  "geometry": {"coordinates":[115.767143249,-31.7867298126],"type":"Point"}
}