{
  "type": "Feature",
  "properties": {
    "addr:full":"PO Box 588 Balwyn North VIC 3104",
    "addr:postcode":"3104",
    "iso:country":"AU",
    "sg:address":"PO Box 588",
    "sg:city":"Balwyn North",
    "sg:classifiers":[
        {
            "category":"Professional",
            "subcategory":"Employment Agencies",
            "type":"Services"
        }
    ],
    "sg:phone":"+61 409 201 771",
    "sg:postcode":"3104",
    "sg:province":"VIC",
    "sg:tags":[
        "entertainer",
        "agent"
    ],
    "wof:name":"Epic Mobile DJs",
    "wof:placetype":"venue"
},
  "geometry": {"coordinates":[145.085540772,-37.7907905579],"type":"Point"}
}