{
  "type": "Feature",
  "properties": {
    "addr:full":"PO Box 317 Carnegie VIC 3163",
    "addr:postcode":"3163",
    "iso:country":"AU",
    "sg:address":"PO Box 317",
    "sg:city":"Carnegie",
    "sg:classifiers":[
        {
            "category":"Organizations",
            "subcategory":"Membership Organization",
            "type":"Services"
        }
    ],
    "sg:phone":"+61 3 9530 9848",
    "sg:postcode":"3163",
    "sg:province":"VIC",
    "sg:tags":[
        "equipment",
        "inter-communication",
        "system"
    ],
    "wof:name":"Bruker Systems",
    "wof:placetype":"venue"
},
  "geometry": {"coordinates":[145.056762695,-37.8907585144],"type":"Point"}
}