{
  "type": "Feature",
  "properties": {
    "addr:full":"66 Menangle St Picton NSW 2571",
    "addr:housenumber":"66",
    "addr:postcode":"2571",
    "addr:street":"Menangle St",
    "iso:country":"AU",
    "sg:address":"66 Menangle St",
    "sg:city":"Picton",
    "sg:classifiers":[
        {
            "category":"Social Services",
            "subcategory":"Child Care",
            "type":"Services"
        }
    ],
    "sg:phone":"+61 2 4677 8200",
    "sg:postcode":"2571",
    "sg:province":"NSW",
    "wof:name":"Wollondilly Family Day Care",
    "wof:placetype":"venue"
},
  "geometry": {"coordinates":[150.611495972,-34.1690788269],"type":"Point"}
}