{
  "type": "Feature",
  "properties": {
    "addr:full":"PO Box 988 Busselton WA 6280",
    "addr:postcode":"6280",
    "iso:country":"AU",
    "sg:address":"PO Box 988",
    "sg:city":"Busselton",
    "sg:classifiers":[
        {
            "category":"Building & Trades",
            "subcategory":"Cleaning & Sanitation",
            "type":"Services"
        }
    ],
    "sg:phone":"+61 427 524 663",
    "sg:postcode":"6280",
    "sg:province":"WA",
    "sg:tags":[
        "chemical",
        "pressure",
        "steam",
        "contractor"
    ],
    "wof:name":"Diligent Services",
    "wof:placetype":"venue"
},
  "geometry": {"coordinates":[115.344818115,-33.652141571],"type":"Point"}
}