{
  "type": "Feature",
  "properties": {
    "iso:country":"AU",
    "sg:address":"422 Fitzgerald St",
    "sg:city":"North Perth",
    "sg:classifiers":[
        {
            "category":"Real Estate",
            "subcategory":"Real Estate Agent",
            "type":"Services"
        }
    ],
    "sg:phone":"+61 8 9328 1555",
    "sg:postcode":"6006",
    "sg:province":"WA",
    "wof:name":"Corona Estate Agency",
    "wof:placetype":"venue"
},
  "geometry": {"coordinates":[115.85932922400001,-31.9320831299],"type":"Point"}
}