{
  "type": "Feature",
  "properties": {
    "iso:country":"AU",
    "sg:address":"27 Apricot St",
    "sg:city":"Forrestfield",
    "sg:classifiers":[
        {
            "category":"Professional",
            "subcategory":"Accounting & Tax Preparation",
            "type":"Services"
        }
    ],
    "sg:phone":"+61 8 9453 9907",
    "sg:postcode":"6058",
    "sg:province":"WA",
    "sg:tags":[
        "bookkeeping"
    ],
    "wof:name":"Glenhaven Enterprises",
    "wof:placetype":"venue"
},
  "geometry": {"coordinates":[116.005622864,-31.9702148438],"type":"Point"}
}