{
  "type": "Feature",
  "properties": {
    "addr:full":"2 Toongarah Rd Waverton NSW 2060",
    "addr:housenumber":"2",
    "addr:postcode":"2060",
    "addr:street":"Toongarah Rd",
    "iso:country":"AU",
    "sg:address":"2 Toongarah Rd",
    "sg:city":"Waverton",
    "sg:classifiers":[
        {
            "category":"Real Estate",
            "subcategory":"Architect",
            "type":"Services"
        }
    ],
    "sg:phone":"+61 2 9955 5603",
    "sg:postcode":"2060",
    "sg:province":"NSW",
    "wof:name":"Colville Anne",
    "wof:placetype":"venue"
},
  "geometry": {"coordinates":[151.20169067399999,-33.8374786377],"type":"Point"}
}