{
  "type": "Feature",
  "properties": {
    "addr:full":"49 Chute St Diamond Creek VIC 3089",
    "addr:housenumber":"49",
    "addr:postcode":"3089",
    "addr:street":"Chute St",
    "iso:country":"AU",
    "sg:address":"49 Chute St",
    "sg:city":"Diamond Creek",
    "sg:classifiers":[
        {
            "category":"Home & Garden",
            "subcategory":"Building Materials",
            "type":"Retail Goods"
        }
    ],
    "sg:phone":"+61 3 9438 1970",
    "sg:postcode":"3089",
    "sg:province":"VIC",
    "sg:tags":[
        "merchant",
        "glass",
        "glazier"
    ],
    "wof:name":"Eltham Glass Pty Ltd",
    "wof:placetype":"venue"
},
  "geometry": {"coordinates":[145.15220600000001,-37.672867],"type":"Point"}
}