{
  "type": "Feature",
  "properties": {
    "addr:full":"3511 Pacific Hwy Slacks Creek QLD 4127",
    "addr:housenumber":"3511",
    "addr:postcode":"4127",
    "addr:street":"Pacific Hwy",
    "iso:country":"AU",
    "sg:address":"3511 Pacific Hwy",
    "sg:city":"Slacks Creek",
    "sg:classifiers":[
        {
            "category":"Retail",
            "subcategory":"Auto Repair",
            "type":"Services"
        }
    ],
    "sg:phone":"+61 7 3290 0107",
    "sg:postcode":"4127",
    "sg:province":"QLD",
    "sg:tags":[
        "repairer",
        "motor",
        "engineer"
    ],
    "wof:name":"Xtreme Automotive",
    "wof:placetype":"venue"
},
  "geometry": {"coordinates":[153.13238525400001,-27.6344089508],"type":"Point"}
}