{
  "type": "Feature",
  "properties": {
    "addr:full":"Lvl 1/ 195 Adelaide Tce East Perth WA 6004",
    "addr:housenumber":"/ 195",
    "addr:postcode":"6004",
    "addr:street":"Adelaide Tce East",
    "iso:country":"AU",
    "sg:address":"Lvl 1/ 195 Adelaide Tce",
    "sg:city":"East Perth",
    "sg:classifiers":[
        {
            "category":"Travel",
            "subcategory":"Hotels & Motels",
            "type":"Entertainment"
        }
    ],
    "sg:phone":"+61 8 9325 6962",
    "sg:postcode":"6004",
    "sg:province":"WA",
    "sg:tags":[
        "accommodation"
    ],
    "wof:name":"Sunflower Holdings Pty Ltd",
    "wof:placetype":"venue"
},
  "geometry": {"coordinates":[115.878013611,-31.9621582031],"type":"Point"}
}