{
  "type": "Feature",
  "properties": {
    "addr:full":"PO Box 2168 Ascot QLD 4007",
    "addr:postcode":"4007",
    "iso:country":"AU",
    "sg:address":"PO Box 2168",
    "sg:city":"Ascot",
    "sg:classifiers":[
        {
            "category":"Education",
            "subcategory":"Special Training",
            "type":"Public Place"
        }
    ],
    "sg:phone":"+61 7 3862 1231",
    "sg:postcode":"4007",
    "sg:province":"QLD",
    "sg:tags":[
        "development"
    ],
    "wof:name":"Activities Team The",
    "wof:placetype":"venue"
},
  "geometry": {"coordinates":[153.06201200000001,-27.42802],"type":"Point"}
}