{
  "type": "Feature",
  "properties": {
    "addr:full":"Cnr Males & Moorooduc Rds Moorooduc VIC 3933",
    "addr:postcode":"3933",
    "addr:street":"Cnr",
    "iso:country":"AU",
    "sg:address":"Cnr Males & Moorooduc Rds",
    "sg:city":"Moorooduc",
    "sg:classifiers":[
        {
            "category":"Home & Garden",
            "subcategory":"Garden Supply",
            "type":"Retail Goods"
        }
    ],
    "sg:phone":"+61 3 5978 8777",
    "sg:postcode":"3933",
    "sg:province":"VIC",
    "sg:tags":[
        "statuary",
        "fountains",
        "sundial"
    ],
    "wof:name":"Garden Of Quasimodo",
    "wof:placetype":"venue"
},
  "geometry": {"coordinates":[145.096893311,-38.2600250244],"type":"Point"}
}