{
  "type": "Feature",
  "properties": {
    "addr:full":"12 Goodall Drv Lilydale VIC 3140",
    "addr:housenumber":"12",
    "addr:postcode":"3140",
    "addr:street":"Goodall Drv",
    "iso:country":"AU",
    "sg:address":"12 Goodall Drv",
    "sg:city":"Lilydale",
    "sg:classifiers":[
        {
            "category":"Home & Garden",
            "subcategory":"Building Materials",
            "type":"Retail Goods"
        }
    ],
    "sg:phone":"+61 412 403 948",
    "sg:postcode":"3140",
    "sg:province":"VIC",
    "sg:tags":[
        "restoration",
        "supply"
    ],
    "wof:name":"AAA Classic Restorations",
    "wof:placetype":"venue"
},
  "geometry": {"coordinates":[145.36637878400001,-37.7545776367],"type":"Point"}
}