{
  "type": "Feature",
  "properties": {
    "iso:country":"AU",
    "sg:address":"8 Valley Rd",
    "sg:city":"Halls Head",
    "sg:classifiers":[
        {
            "category":"Personal",
            "subcategory":"Beauty Salon",
            "type":"Services"
        }
    ],
    "sg:phone":"+61 8 9581 3900",
    "sg:postcode":"6210",
    "sg:province":"WA",
    "sg:tags":[
        "hairdresser"
    ],
    "wof:name":"Dimples Hair Care",
    "wof:placetype":"venue"
},
  "geometry": {"coordinates":[115.700867,-32.524487],"type":"Point"}
}