{
  "type": "Feature",
  "properties": {
    "iso:country":"AU",
    "sg:address":"34 Korumburra Rd",
    "sg:city":"Wonthaggi",
    "sg:classifiers":[
        {
            "category":"Health Services",
            "subcategory":"Health Practitioner",
            "type":"Services"
        }
    ],
    "sg:phone":"+61 3 5672 5882",
    "sg:postcode":"3995",
    "sg:province":"VIC",
    "sg:tags":[
        "osteopath"
    ],
    "wof:name":"Wonthaggi Spinal & Sports Injury Clinic",
    "wof:placetype":"venue"
},
  "geometry": {"coordinates":[145.591049,-38.606461],"type":"Point"}
}