{
  "type": "Feature",
  "properties": {
    "iso:country":"AU",
    "sg:address":"17 Leichhardt St",
    "sg:city":"Glebe",
    "sg:classifiers":[
        {
            "category":"Arts & Performance",
            "subcategory":"Theater",
            "type":"Entertainment"
        }
    ],
    "sg:phone":"+61 2 9660 8099",
    "sg:postcode":"2037",
    "sg:province":"NSW",
    "sg:tags":[
        "theatrical",
        "supply"
    ],
    "wof:name":"Public Event Group",
    "wof:placetype":"venue"
},
  "geometry": {"coordinates":[151.184494019,-33.8729896545],"type":"Point"}
}