{
  "type": "Feature",
  "properties": {
    "addr:full":"U4/250 Gore St Fitzroy VIC 3065",
    "addr:housenumber":"250",
    "addr:postcode":"3065",
    "addr:street":"U4 /;Gore St",
    "iso:country":"AU",
    "sg:address":"U4/250 Gore St",
    "sg:city":"Fitzroy",
    "sg:classifiers":[
        {
            "category":"Professional",
            "type":"Services"
        }
    ],
    "sg:phone":"+61 3 8415 0544",
    "sg:postcode":"3065",
    "sg:province":"VIC",
    "sg:tags":[
        "transport"
    ],
    "wof:name":"L W Group",
    "wof:placetype":"venue"
},
  "geometry": {"coordinates":[144.97915649399999,-37.8009185791],"type":"Point"}
}