{
  "type": "Feature",
  "properties": {
    "addr:full":"Suite 7, Crestpoint House 1420 Logan Rd Mt Gravatt QLD 4122",
    "addr:housenumber":"1420",
    "addr:postcode":"4122",
    "addr:street":"Logan Rd",
    "iso:country":"AU",
    "sg:address":"Suite 7, Crestpoint House 1420 Logan Rd",
    "sg:city":"Mt Gravatt",
    "sg:classifiers":[
        {
            "category":"Banks & Credit Unions",
            "subcategory":"Investment Brokerage",
            "type":"Services"
        }
    ],
    "sg:phone":"+61 7 3422 1545",
    "sg:postcode":"4122",
    "sg:province":"QLD",
    "wof:name":"Mitropoulos Jennifer L SIA(Aff)",
    "wof:placetype":"venue"
},
  "geometry": {"coordinates":[153.07864379899999,-27.5370750427],"type":"Point"}
}