{
  "type": "Feature",
  "properties": {
    "iso:country":"AU",
    "sg:address":"RMB 5610 38 Main St",
    "sg:city":"Lyonville",
    "sg:classifiers":[
        {
            "category":"Professional",
            "subcategory":"Employment Agencies",
            "type":"Services"
        }
    ],
    "sg:phone":"+61 3 5348 5659",
    "sg:postcode":"3461",
    "sg:province":"VIC",
    "sg:tags":[
        "entertainer",
        "agent"
    ],
    "wof:name":"Puppet Adventures",
    "wof:placetype":"venue"
},
  "geometry": {"coordinates":[144.26112365700001,-37.3868675232],"type":"Point"}
}