{
  "type": "Feature",
  "properties": {
    "iso:country":"AU",
    "sg:address":"PO Box 344",
    "sg:city":"Zillmere",
    "sg:classifiers":[
        {
            "category":"Education",
            "subcategory":"School",
            "type":"Public Place"
        }
    ],
    "sg:phone":"+61 7 3866 0200",
    "sg:postcode":"4034",
    "sg:province":"QLD",
    "sg:tags":[
        "supply"
    ],
    "wof:name":"SDS-Queensland Government Supplies",
    "wof:placetype":"venue"
},
  "geometry": {"coordinates":[153.038086,-27.360001],"type":"Point"}
}