{
  "type": "Feature",
  "properties": {
    "addr:full":"73 Bay St Brighton VIC 3186",
    "addr:housenumber":"73",
    "addr:postcode":"3186",
    "addr:street":"Bay St",
    "iso:country":"AU",
    "sg:address":"73 Bay St",
    "sg:city":"Brighton",
    "sg:classifiers":[
        {
            "category":"Home & Garden",
            "subcategory":"Household Appliances",
            "type":"Retail Goods"
        }
    ],
    "sg:phone":"+61 3 9596 2644",
    "sg:postcode":"3186",
    "sg:province":"VIC",
    "sg:tags":[
        "heating",
        "system"
    ],
    "wof:name":"Australian Gas Log Fires",
    "wof:placetype":"venue"
},
  "geometry": {"coordinates":[144.993484497,-37.9042167664],"type":"Point"}
}