{
  "type": "Feature",
  "properties": {
    "iso:country":"AU",
    "sg:address":"38 Britannia St",
    "sg:city":"Manly",
    "sg:classifiers":[
        {
            "category":"Professional",
            "subcategory":"Business Services",
            "type":"Services"
        }
    ],
    "sg:phone":"+61 7 3348 6369",
    "sg:postcode":"4179",
    "sg:province":"QLD",
    "sg:tags":[
        "drafting"
    ],
    "wof:name":"Geological Graphics",
    "wof:placetype":"venue"
},
  "geometry": {"coordinates":[153.18698120100001,-27.462064743],"type":"Point"}
}