{
  "type": "Feature",
  "properties": {
    "addr:full":"354 Scarborough Beach Rd Osborne Park WA 6017",
    "addr:housenumber":"354",
    "addr:postcode":"6017",
    "addr:street":"Scarborough Beach Rd",
    "iso:country":"AU",
    "sg:address":"354 Scarborough Beach Rd",
    "sg:city":"Osborne Park",
    "sg:classifiers":[
        {
            "category":"Retail",
            "subcategory":"Auto Repair",
            "type":"Services"
        }
    ],
    "sg:phone":"+61 8 9231 5922",
    "sg:postcode":"6017",
    "sg:province":"WA",
    "sg:tags":[
        "repairer",
        "motor",
        "engineer"
    ],
    "wof:name":"Barbagallo Lamborghini",
    "wof:placetype":"venue"
},
  "geometry": {"coordinates":[115.807899475,-31.9052009583],"type":"Point"}
}