{
  "type": "Feature",
  "properties": {
    "addr:full":"Unit 1/ 37 Marble Drv Kingston QLD 4114",
    "addr:housenumber":"37",
    "addr:postcode":"4114",
    "addr:street":"Marble Drv",
    "iso:country":"AU",
    "sg:address":"Unit 1/ 37 Marble Drv",
    "sg:city":"Kingston",
    "sg:classifiers":[
        {
            "category":"Retail",
            "subcategory":"Auto Repair",
            "type":"Services"
        }
    ],
    "sg:phone":"+61 7 3208 5374",
    "sg:postcode":"4114",
    "sg:province":"QLD",
    "sg:tags":[
        "repairer",
        "motor",
        "engineer"
    ],
    "wof:name":"Bob Taylor Automotive",
    "wof:placetype":"venue"
},
  "geometry": {"coordinates":[153.11428832999999,-27.6651973724],"type":"Point"}
}