{
  "type": "Feature",
  "properties": {
    "iso:country":"AU",
    "sg:address":"5 Woodside Crt",
    "sg:city":"Eden Park",
    "sg:classifiers":[
        {
            "category":"Autos & Motor Vehicles",
            "subcategory":"Automobile Sales",
            "type":"Retail Goods"
        }
    ],
    "sg:phone":"+61 3 9715 1321",
    "sg:postcode":"3757",
    "sg:province":"VIC",
    "sg:tags":[
        "equipment",
        "trailer"
    ],
    "wof:name":"Genka Ezilift",
    "wof:placetype":"venue"
},
  "geometry": {"coordinates":[145.046585,-37.521191],"type":"Point"}
}