{
  "type": "Feature",
  "properties": {
    "addr:full":"21 Hoddle Ave Goulburn NSW 2580",
    "addr:housenumber":"21",
    "addr:postcode":"2580",
    "addr:street":"Hoddle Ave",
    "iso:country":"AU",
    "sg:address":"21 Hoddle Ave",
    "sg:city":"Goulburn",
    "sg:classifiers":[
        {
            "category":"Government",
            "subcategory":"Post Office",
            "type":"Public Place"
        }
    ],
    "sg:phone":"+61 2 4821 7108",
    "sg:postcode":"2580",
    "sg:province":"NSW",
    "sg:tags":[
        "yoga"
    ],
    "wof:name":"Blevins Jennifer",
    "wof:placetype":"venue"
},
  "geometry": {"coordinates":[149.70576477,-34.7430610657],"type":"Point"}
}