{
  "type": "Feature",
  "properties": {
    "iso:country":"AU",
    "sg:address":"CWA Rooms Victoria St St",
    "sg:city":"George",
    "sg:classifiers":[
        {
            "category":"Health Services",
            "subcategory":"Chiropractor",
            "type":"Services"
        }
    ],
    "sg:phone":"+61 7 4625 5445",
    "sg:postcode":"4487",
    "sg:province":"QLD",
    "wof:name":"Barham Chiropractic",
    "wof:placetype":"venue"
},
  "geometry": {"coordinates":[148.580688477,-28.0360832214],"type":"Point"}
}