{
  "type": "Feature",
  "properties": {
    "addr:full":"Shop 3 291- 293 Windsor St Richmond NSW 2753",
    "addr:housenumber":"shop 3;293",
    "addr:postcode":"291;2753",
    "addr:street":"Windsor St",
    "iso:country":"AU",
    "sg:address":"Shop 3 291- 293 Windsor St",
    "sg:city":"Richmond",
    "sg:classifiers":[
        {
            "category":"Organizations",
            "subcategory":"Community Association",
            "type":"Services"
        }
    ],
    "sg:phone":"+61 2 4578 4933",
    "sg:postcode":"2753",
    "sg:province":"NSW",
    "sg:tags":[
        "organisation",
        "family",
        "welfare"
    ],
    "wof:name":"Home Care Service of NSW",
    "wof:placetype":"venue"
},
  "geometry": {"coordinates":[150.74830627399999,-33.5954475403],"type":"Point"}
}