{
  "type": "Feature",
  "properties": {
    "iso:country":"AU",
    "sg:address":"Lvl 1 70",
    "sg:city":"Hindmarsh Sq Adelaide",
    "sg:classifiers":[
        {
            "category":"Banks & Credit Unions",
            "subcategory":"Investment Brokerage",
            "type":"Services"
        }
    ],
    "sg:phone":"+61 8 8464 5000",
    "sg:postcode":"5000",
    "sg:province":"SA",
    "sg:tags":[
        "share",
        "broker",
        "stock"
    ],
    "wof:name":"ABN Amro Morgans",
    "wof:placetype":"venue"
},
  "geometry": {"coordinates":[138.6065979,-34.9244499207],"type":"Point"}
}