{
  "type": "Feature",
  "properties": {
    "iso:country":"AU",
    "sg:address":"51 Whittens La",
    "sg:city":"Doncaster",
    "sg:classifiers":[
        {
            "category":"Real Estate",
            "subcategory":"Architect",
            "type":"Services"
        }
    ],
    "sg:phone":"+61 3 9848 8696",
    "sg:postcode":"3108",
    "sg:province":"VIC",
    "wof:name":"Sideridis Emmanouel",
    "wof:placetype":"venue"
},
  "geometry": {"coordinates":[145.129592895,-37.7926292419],"type":"Point"}
}