{
  "type": "Feature",
  "properties": {
    "iso:country":"AU",
    "sg:address":"132 Terminus St",
    "sg:city":"Liverpool",
    "sg:classifiers":[
        {
            "category":"Autos & Motor Vehicles",
            "subcategory":"Auto Supplies",
            "type":"Retail Goods"
        }
    ],
    "sg:phone":"+61 2 9601 1022",
    "sg:postcode":"2170",
    "sg:province":"NSW",
    "sg:tags":[
        "automotive",
        "stereo",
        "radio"
    ],
    "wof:name":"Strathfield Car Radios",
    "wof:placetype":"venue"
},
  "geometry": {"coordinates":[150.921386719,-33.9269371033],"type":"Point"}
}