{
  "type": "Feature",
  "properties": {
    "addr:full":"Days Rd Cnr Regency Rd Regency Park SA 5010",
    "addr:postcode":"5010",
    "addr:street":"Days Rd Cnr Regency Rd",
    "iso:country":"AU",
    "sg:address":"Days Rd Cnr Regency Rd",
    "sg:city":"Regency Park",
    "sg:classifiers":[
        {
            "category":"Wholesale",
            "subcategory":"Seafood",
            "type":"Manufacturing & Wholesale Goods"
        }
    ],
    "sg:phone":"+61 8 8346 8764",
    "sg:postcode":"5010",
    "sg:province":"SA",
    "sg:tags":[
        "fish"
    ],
    "wof:name":"Ferguson Australia",
    "wof:placetype":"venue"
},
  "geometry": {"coordinates":[138.571868897,-34.8750801086],"type":"Point"}
}