{
  "type": "Feature",
  "properties": {
    "addr:full":"PO Box 340 Mont Albert 3127 Mont Albert VIC 3127",
    "addr:postcode":"3127;3127",
    "addr:street":"Albert",
    "iso:country":"AU",
    "sg:address":"PO Box 340 Mont Albert 3127",
    "sg:city":"Mont Albert",
    "sg:classifiers":[
        {
            "category":"Professional",
            "subcategory":"Art Services",
            "type":"Services"
        }
    ],
    "sg:phone":"+61 3 9830 4854",
    "sg:postcode":"3127",
    "sg:province":"VIC",
    "sg:tags":[
        "interior",
        "decorator"
    ],
    "wof:name":"Janine Browning Interiors",
    "wof:placetype":"venue"
},
  "geometry": {"coordinates":[145.10809326200001,-37.821559906],"type":"Point"}
}