{
  "type": "Feature",
  "properties": {
    "addr:full":"14 Bellarine Crt Keysborough VIC 3173",
    "addr:housenumber":"14",
    "addr:postcode":"3173",
    "addr:street":"Bellarine Crt",
    "iso:country":"AU",
    "sg:address":"14 Bellarine Crt",
    "sg:city":"Keysborough",
    "sg:classifiers":[
        {
            "category":"Professional",
            "subcategory":"Accounting & Tax Preparation",
            "type":"Services"
        }
    ],
    "sg:phone":"+61 3 9798 1498",
    "sg:postcode":"3173",
    "sg:province":"VIC",
    "sg:tags":[
        "consultant",
        "taxation"
    ],
    "wof:name":"Calleja Joe",
    "wof:placetype":"venue"
},
  "geometry": {"coordinates":[145.16773986800001,-37.9913902283],"type":"Point"}
}