{
  "type": "Feature",
  "properties": {
    "iso:country":"AU",
    "sg:address":"23 Restwell St",
    "sg:city":"Bankstown",
    "sg:classifiers":[
        {
            "category":"Government",
            "subcategory":"City Hall",
            "type":"Public Place"
        }
    ],
    "sg:phone":"+61 2 9790 1909",
    "sg:postcode":"2200",
    "sg:province":"NSW",
    "wof:name":"Masonic Halls & Centres",
    "wof:placetype":"venue"
},
  "geometry": {"coordinates":[151.03474399999999,-33.919682],"type":"Point"}
}