{
  "type": "Feature",
  "properties": {
    "addr:full":"Studio 8/ 224 Commonwealth St Surry Hills NSW 2010",
    "addr:housenumber":"224",
    "addr:postcode":"2010",
    "addr:street":"Commonwealth St",
    "iso:country":"AU",
    "sg:address":"Studio 8/ 224 Commonwealth St",
    "sg:city":"Surry Hills",
    "sg:classifiers":[
        {
            "category":"Professional",
            "subcategory":"Business Services",
            "type":"Services"
        }
    ],
    "sg:phone":"+61 2 9212 3465",
    "sg:postcode":"2010",
    "sg:province":"NSW",
    "sg:tags":[
        "drafting"
    ],
    "wof:name":"C M Hairis Architects",
    "wof:placetype":"venue"
},
  "geometry": {"coordinates":[151.21009826700001,-33.8835678101],"type":"Point"}
}