{
  "type": "Feature",
  "properties": {
    "addr:full":"777 Main St Kangaroo Point QLD 4169",
    "addr:housenumber":"777",
    "addr:postcode":"4169",
    "addr:street":"Main St",
    "iso:country":"AU",
    "sg:address":"777 Main St",
    "sg:city":"Kangaroo Point",
    "sg:classifiers":[
        {
            "category":"Government",
            "subcategory":"Office",
            "type":"Public Place"
        }
    ],
    "sg:phone":"+61 415 865 861",
    "sg:postcode":"4169",
    "sg:province":"QLD",
    "sg:tags":[
        "qld",
        "agency",
        "escort",
        "social"
    ],
    "wof:name":"Daniela",
    "wof:placetype":"venue"
},
  "geometry": {"coordinates":[153.035690308,-27.4830513],"type":"Point"}
}