{
  "type": "Feature",
  "properties": {
    "addr:full":"Shop 2129 Highpoint City Shopping Centre Maribyrnong VIC 3032",
    "addr:housenumber":"2129",
    "addr:postcode":"3032",
    "addr:street":"Highpoint City",
    "iso:country":"AU",
    "sg:address":"Shop 2129",
    "sg:city":"Highpoint City Shopping Centre Maribyrnong",
    "sg:classifiers":[
        {
            "category":"Shopping",
            "subcategory":"Clothing, Apparel, & Fashions",
            "type":"Retail Goods"
        }
    ],
    "sg:phone":"+61 3 9317 3199",
    "sg:postcode":"3032",
    "sg:province":"VIC",
    "sg:tags":[
        "lady",
        "wear"
    ],
    "wof:name":"Look Melbourne",
    "wof:placetype":"venue"
},
  "geometry": {"coordinates":[144.905472,-37.772739],"type":"Point"}
}