{
  "type": "Feature",
  "properties": {
    "addr:full":"126 East St Rockhampton QLD 4700",
    "addr:housenumber":"126",
    "addr:postcode":"4700",
    "addr:street":"East St",
    "iso:country":"AU",
    "sg:address":"126 East St",
    "sg:city":"Rockhampton",
    "sg:classifiers":[
        {
            "category":"Shopping",
            "subcategory":"Clothing, Apparel, & Fashions",
            "type":"Retail Goods"
        }
    ],
    "sg:phone":"+61 7 4922 7575",
    "sg:postcode":"4700",
    "sg:province":"QLD",
    "sg:tags":[
        "lady",
        "wear"
    ],
    "wof:name":"Zingara Clothing",
    "wof:placetype":"venue"
},
  "geometry": {"coordinates":[150.52134704599999,-23.3892116547],"type":"Point"}
}