{
  "type": "Feature",
  "properties": {
    "iso:country":"AU",
    "sg:address":"Main North Rd",
    "sg:city":"Elizabeth Vale",
    "sg:classifiers":[
        {
            "category":"Autos & Motor Vehicles",
            "subcategory":"Fuel & Gas Station",
            "type":"Retail Goods"
        }
    ],
    "sg:phone":"+61 8 8287 2444",
    "sg:postcode":"5112",
    "sg:province":"SA",
    "wof:name":"BP Australia Ltd",
    "wof:placetype":"venue"
},
  "geometry": {"coordinates":[138.67674255399999,-34.7475204468],"type":"Point"}
}