{
  "type": "Feature",
  "properties": {
    "iso:country":"AU",
    "sg:address":"none",
    "sg:city":"Tennant Creek",
    "sg:classifiers":[
        {
            "category":"Building & Trades",
            "subcategory":"Landscaping Services",
            "type":"Services"
        }
    ],
    "sg:phone":"+61 8 8975 9912",
    "sg:postcode":"0860",
    "sg:province":"NT",
    "sg:tags":[
        "grazier"
    ],
    "wof:name":"Mallapunyah Springs",
    "wof:placetype":"venue"
},
  "geometry": {"coordinates":[134.178955,-19.64492],"type":"Point"}
}