{
  "type": "Feature",
  "properties": {
    "addr:full":"Shop 3 4 Seymour St Laurieton NSW 2443",
    "addr:housenumber":"shop;4",
    "addr:postcode":"2443",
    "addr:street":"Seymour St",
    "iso:country":"AU",
    "sg:address":"Shop 3 4 Seymour St",
    "sg:city":"Laurieton",
    "sg:classifiers":[
        {
            "category":"Home & Garden",
            "subcategory":"Garden Supply",
            "type":"Retail Goods"
        }
    ],
    "sg:phone":"+61 2 6559 8456",
    "sg:postcode":"2443",
    "sg:province":"NSW",
    "sg:tags":[
        "shed"
    ],
    "wof:name":"Cages and Things",
    "wof:placetype":"venue"
},
  "geometry": {"coordinates":[152.79577599999999,-31.650377],"type":"Point"}
}