{
  "type": "Feature",
  "properties": {
    "addr:full":"66 Morrow Rd Lonsdale SA 5160",
    "addr:housenumber":"66",
    "addr:postcode":"5160",
    "addr:street":"Morrow Rd",
    "iso:country":"AU",
    "sg:address":"66 Morrow Rd",
    "sg:city":"Lonsdale",
    "sg:classifiers":[
        {
            "category":"Home & Garden",
            "subcategory":"Building Materials",
            "type":"Retail Goods"
        }
    ],
    "sg:phone":"+61 8 8384 7331",
    "sg:postcode":"5160",
    "sg:province":"SA",
    "sg:tags":[
        "retaining",
        "wall"
    ],
    "wof:name":"Creative Sleepers",
    "wof:placetype":"venue"
},
  "geometry": {"coordinates":[138.48489379899999,-35.1224746704],"type":"Point"}
}