{
  "type": "Feature",
  "properties": {
    "iso:country":"AU",
    "sg:address":"73 Wheelers La",
    "sg:city":"Dubbo",
    "sg:classifiers":[
        {
            "category":"Personal",
            "subcategory":"Beauty Salon",
            "type":"Services"
        }
    ],
    "sg:phone":"+61 2 6882 2338",
    "sg:postcode":"2830",
    "sg:province":"NSW",
    "sg:tags":[
        "hairdresser"
    ],
    "wof:name":"Peter Marshall Hair Design",
    "wof:placetype":"venue"
},
  "geometry": {"coordinates":[148.63088989299999,-32.2471046448],"type":"Point"}
}