{
  "type": "Feature",
  "properties": {
    "addr:full":"51 Chermside Rd Mango Hill QLD 4509",
    "addr:housenumber":"51",
    "addr:postcode":"4509",
    "addr:street":"Chermside Rd",
    "iso:country":"AU",
    "sg:address":"51 Chermside Rd",
    "sg:city":"Mango Hill",
    "sg:classifiers":[
        {
            "category":"Building & Trades",
            "subcategory":"Cleaning & Sanitation",
            "type":"Services"
        }
    ],
    "sg:phone":"+61 7 3204 2864",
    "sg:postcode":"4509",
    "sg:province":"QLD",
    "sg:tags":[
        "grease",
        "trap"
    ],
    "wof:name":"W J Fenly Grease Trap Cleaning Services",
    "wof:placetype":"venue"
},
  "geometry": {"coordinates":[153.027435303,-27.2179679871],"type":"Point"}
}