{
  "type": "Feature",
  "properties": {
    "iso:country":"AU",
    "sg:address":"176a Copeland Rd",
    "sg:city":"Beecroft",
    "sg:classifiers":[
        {
            "category":"Professional",
            "subcategory":"Management & Consulting",
            "type":"Services"
        }
    ],
    "sg:phone":"+61 2 9484 7975",
    "sg:postcode":"2119",
    "sg:province":"NSW",
    "sg:tags":[
        "consultant",
        "educational"
    ],
    "wof:name":"Total Training & Performance Solutions",
    "wof:placetype":"venue"
},
  "geometry": {"coordinates":[151.07176208499999,-33.7514762878],"type":"Point"}
}