{
  "type": "Feature",
  "properties": {
    "iso:country":"AU",
    "sg:address":"87 Main St",
    "sg:city":"Croydon",
    "sg:classifiers":[
        {
            "category":"Professional",
            "subcategory":"Accounting & Tax Preparation",
            "type":"Services"
        }
    ],
    "sg:phone":"+61 3 9723 7144",
    "sg:postcode":"3136",
    "sg:province":"VIC",
    "sg:tags":[
        "accountant",
        "auditor"
    ],
    "wof:name":"Cowley Isla Pty Ltd",
    "wof:placetype":"venue"
},
  "geometry": {"coordinates":[145.280807495,-37.7966423035],"type":"Point"}
}