{
  "type": "Feature",
  "properties": {
    "iso:country":"AU",
    "sg:address":"23 John St",
    "sg:city":"Fitzroy",
    "sg:classifiers":[
        {
            "category":"Social Services",
            "subcategory":"Child Care",
            "type":"Services"
        }
    ],
    "sg:phone":"+61 3 9419 6659",
    "sg:postcode":"3065",
    "sg:province":"VIC",
    "wof:name":"John St Community Early Childhood Co-Operative",
    "wof:placetype":"venue"
},
  "geometry": {"coordinates":[144.97622680699999,-37.8006095886],"type":"Point"}
}