{
  "type": "Feature",
  "properties": {
    "iso:country":"AU",
    "sg:address":"308 Main Rd East",
    "sg:city":"St Albans",
    "sg:classifiers":[
        {
            "category":"Real Estate",
            "subcategory":"Real Estate Agent",
            "type":"Services"
        }
    ],
    "sg:phone":"+61 3 9366 1144",
    "sg:postcode":"3021",
    "sg:province":"VIC",
    "wof:name":"Kontek John Real Estate Pty Ltd",
    "wof:placetype":"venue"
},
  "geometry": {"coordinates":[144.801865,-37.744312],"type":"Point"}
}