{
  "type": "Feature",
  "properties": {
    "addr:full":"Launer Rd Coorow West WA 6515",
    "addr:postcode":"6515",
    "addr:street":"Launer Rd",
    "iso:country":"AU",
    "sg:address":"Launer Rd",
    "sg:city":"Coorow West",
    "sg:classifiers":[
        {
            "category":"Farming",
            "subcategory":"Farm",
            "type":"Manufacturing & Wholesale Goods"
        }
    ],
    "sg:phone":"+61 8 9952 5025",
    "sg:postcode":"6515",
    "sg:province":"WA",
    "sg:tags":[
        "farmer"
    ],
    "wof:name":"Clement R J & E N",
    "wof:placetype":"venue"
},
  "geometry": {"coordinates":[115.90361,-29.927961],"type":"Point"}
}