{
  "type": "Feature",
  "properties": {
    "iso:country":"AU",
    "sg:address":"Marian Drv",
    "sg:city":"Port Macquarie",
    "sg:classifiers":[
        {
            "category":"Social Services",
            "subcategory":"Retirement Home",
            "type":"Services"
        }
    ],
    "sg:phone":"+61 2 6581 3370",
    "sg:postcode":"2444",
    "sg:province":"NSW",
    "sg:tags":[
        "village"
    ],
    "wof:name":"Lincoln Gardens",
    "wof:placetype":"venue"
},
  "geometry": {"coordinates":[152.872955,-31.446129],"type":"Point"}
}