{
  "type": "Feature",
  "properties": {
    "addr:full":"Level 2 16 Queensland Ave Broadbeach QLD 4218",
    "addr:housenumber":"16",
    "addr:postcode":"4218",
    "addr:street":"Queensland Ave",
    "iso:country":"AU",
    "sg:address":"Level 2 16 Queensland Ave",
    "sg:city":"Broadbeach",
    "sg:classifiers":[
        {
            "category":"Professional",
            "type":"Services"
        }
    ],
    "sg:phone":"+61 7 5592 5545",
    "sg:postcode":"4218",
    "sg:province":"QLD",
    "sg:tags":[
        "industrial",
        "commercial",
        "catering"
    ],
    "wof:name":"Alpha Flight Services Pty Ltd",
    "wof:placetype":"venue"
},
  "geometry": {"coordinates":[153.43205261200001,-28.0273742676],"type":"Point"}
}