{
  "type": "Feature",
  "properties": {
    "addr:full":"694 Balaren Hwy Leopold VIC 3224",
    "addr:housenumber":"694",
    "addr:postcode":"3224",
    "addr:street":"Balaren Hwy Leopold",
    "iso:country":"AU",
    "sg:address":"694 Balaren Hwy",
    "sg:city":"Leopold",
    "sg:classifiers":[
        {
            "category":"Autos & Motor Vehicles",
            "subcategory":"Fuel & Gas Station",
            "type":"Retail Goods"
        }
    ],
    "sg:phone":"+61 3 5250 2495",
    "sg:postcode":"3224",
    "sg:province":"VIC",
    "wof:name":"BP Australia Limited",
    "wof:placetype":"venue"
},
  "geometry": {"coordinates":[144.46253999999999,-38.196381],"type":"Point"}
}