{
  "type": "Feature",
  "properties": {
    "addr:full":"27 Mt Cotton Rd Capalaba QLD 4157",
    "addr:housenumber":"27",
    "addr:postcode":"4157",
    "addr:street":"Mt Cotton Rd",
    "iso:country":"AU",
    "sg:address":"27 Mt Cotton Rd",
    "sg:city":"Capalaba",
    "sg:classifiers":[
        {
            "category":"Health Services",
            "subcategory":"Chiropractor",
            "type":"Services"
        }
    ],
    "sg:phone":"+61 7 3245 4177",
    "sg:postcode":"4157",
    "sg:province":"QLD",
    "wof:name":"Centre For Integrated Medicine",
    "wof:placetype":"venue"
},
  "geometry": {"coordinates":[153.18942260700001,-27.5296497345],"type":"Point"}
}