{
  "type": "Feature",
  "properties": {
    "addr:full":"386 High St Melton VIC 3337",
    "addr:housenumber":"386",
    "addr:postcode":"3337",
    "addr:street":"High St",
    "iso:country":"AU",
    "sg:address":"386 High St",
    "sg:city":"Melton",
    "sg:classifiers":[
        {
            "category":"Health Services",
            "subcategory":"Health Practitioner",
            "type":"Services"
        }
    ],
    "sg:phone":"+61 3 9743 4479",
    "sg:postcode":"3337",
    "sg:province":"VIC",
    "sg:tags":[
        "physiotherapist"
    ],
    "wof:name":"Vigor Sports Medicine Clinic",
    "wof:placetype":"venue"
},
  "geometry": {"coordinates":[144.57957500000001,-37.683357],"type":"Point"}
}