{
  "type": "Feature",
  "properties": {
    "iso:country":"AU",
    "sg:address":"2 Val St",
    "sg:city":"Rockingham",
    "sg:classifiers":[
        {
            "category":"Recreation",
            "subcategory":"Sailing Club",
            "type":"Entertainment"
        }
    ],
    "sg:phone":"+61 8 9527 5468",
    "sg:postcode":"6168",
    "sg:province":"WA",
    "sg:tags":[
        "yacht"
    ],
    "wof:name":"The Cruising Yacht Club Of WA",
    "wof:placetype":"venue"
},
  "geometry": {"coordinates":[115.727669,-32.276367],"type":"Point"}
}