{
  "type": "Feature",
  "properties": {
    "iso:country":"AU",
    "sg:address":"Walker Crs",
    "sg:city":"Raymond Terrace",
    "sg:classifiers":[
        {
            "category":"Sports & Exercise",
            "subcategory":"Golf",
            "type":"Entertainment"
        }
    ],
    "sg:phone":"+61 2 4987 2142",
    "sg:postcode":"2324",
    "sg:province":"NSW",
    "sg:tags":[
        "club"
    ],
    "wof:name":"Muree Golf Club Ltd.",
    "wof:placetype":"venue"
},
  "geometry": {"coordinates":[151.76373290999999,-32.7550582886],"type":"Point"}
}