{
  "type": "Feature",
  "properties": {
    "addr:full":"911 High St Armadale VIC 3143",
    "addr:housenumber":"911",
    "addr:postcode":"3143",
    "addr:street":"High St",
    "iso:country":"AU",
    "sg:address":"911 High St",
    "sg:city":"Armadale",
    "sg:classifiers":[
        {
            "category":"Manufacturing",
            "subcategory":"Pottery",
            "type":"Manufacturing & Wholesale Goods"
        }
    ],
    "sg:phone":"+61 3 9824 7550",
    "sg:postcode":"3143",
    "sg:province":"VIC",
    "wof:name":"Terracotta Etc",
    "wof:placetype":"venue"
},
  "geometry": {"coordinates":[145.018768311,-37.8551139832],"type":"Point"}
}