{
  "type": "Feature",
  "properties": {
    "iso:country":"AU",
    "sg:address":"Unit 5 23 Garema Cct",
    "sg:city":"Kingsgrove",
    "sg:classifiers":[
        {
            "category":"Professional",
            "subcategory":"Art Services",
            "type":"Services"
        }
    ],
    "sg:phone":"+61 2 9750 2882",
    "sg:postcode":"2208",
    "sg:province":"NSW",
    "sg:tags":[
        "work",
        "metal"
    ],
    "wof:name":"Florentine Metal Art Pty Ltd",
    "wof:placetype":"venue"
},
  "geometry": {"coordinates":[151.094864,-33.938896],"type":"Point"}
}