{
  "type": "Feature",
  "properties": {
    "addr:full":"4/ 112 Cronulla St Cronulla NSW 2230",
    "addr:housenumber":"/ 112",
    "addr:postcode":"2230",
    "addr:street":"Cronulla St",
    "iso:country":"AU",
    "sg:address":"4/ 112 Cronulla St",
    "sg:city":"Cronulla",
    "sg:classifiers":[
        {
            "category":"Personal",
            "subcategory":"Massage",
            "type":"Services"
        }
    ],
    "sg:phone":"+61 2 9544 3227",
    "sg:postcode":"2230",
    "sg:province":"NSW",
    "sg:tags":[
        "therapy"
    ],
    "wof:name":"Body Balance",
    "wof:placetype":"venue"
},
  "geometry": {"coordinates":[151.15211486800001,-34.0546760559],"type":"Point"}
}