{
  "type": "Feature",
  "properties": {
    "iso:country":"AU",
    "sg:address":"60 Carradine Rd",
    "sg:city":"Armadale",
    "sg:classifiers":[
        {
            "category":"Airline",
            "type":"Transportation"
        }
    ],
    "sg:phone":"+61 8 9497 8802",
    "sg:postcode":"6112",
    "sg:province":"WA",
    "sg:tags":[
        "agent"
    ],
    "wof:name":"Ground Air Services",
    "wof:placetype":"venue"
},
  "geometry": {"coordinates":[116.02481079099999,-32.148765564],"type":"Point"}
}