{
  "type": "Feature",
  "properties": {
    "addr:full":"U11/ 21 Wrights Pl Arundel QLD 4214",
    "addr:postcode":"4214",
    "addr:street":"/ 21;Pl",
    "iso:country":"AU",
    "sg:address":"U11/ 21 Wrights Pl",
    "sg:city":"Arundel",
    "sg:classifiers":[
        {
            "category":"Building & Trades",
            "subcategory":"Plumbing",
            "type":"Services"
        }
    ],
    "sg:phone":"+61 7 5529 1099",
    "sg:postcode":"4214",
    "sg:province":"QLD",
    "sg:tags":[
        "plumber",
        "gasfitters"
    ],
    "wof:name":"Crooks & Cowen Plumbing",
    "wof:placetype":"venue"
},
  "geometry": {"coordinates":[153.38142395,-27.9361248016],"type":"Point"}
}