{
  "type": "Feature",
  "properties": {
    "iso:country":"AU",
    "sg:address":"7405 Great Eastern Hwy",
    "sg:city":"Mundaring",
    "sg:classifiers":[
        {
            "category":"Health Services",
            "subcategory":"Optometrist",
            "type":"Services"
        }
    ],
    "sg:phone":"+61 8 9295 0682",
    "sg:postcode":"6073",
    "sg:province":"WA",
    "wof:name":"Richardson Larraine",
    "wof:placetype":"venue"
},
  "geometry": {"coordinates":[116.168327331,-31.9019088745],"type":"Point"}
}