{
  "type": "Feature",
  "properties": {
    "addr:full":"18 Park St Guildford NSW 2161",
    "addr:housenumber":"18",
    "addr:postcode":"2161",
    "addr:street":"Park St",
    "iso:country":"AU",
    "sg:address":"18 Park St",
    "sg:city":"Guildford",
    "sg:classifiers":[
        {
            "category":"Building & Trades",
            "subcategory":"Construction",
            "type":"Services"
        }
    ],
    "sg:phone":"+61 2 9721 1022",
    "sg:postcode":"2161",
    "sg:province":"NSW",
    "sg:tags":[
        "home",
        "air conditioning"
    ],
    "wof:name":"Douglas Air Conditioning",
    "wof:placetype":"venue"
},
  "geometry": {"coordinates":[150.97915649399999,-33.8556976318],"type":"Point"}
}