{
  "type": "Feature",
  "properties": {
    "iso:country":"AU",
    "sg:address":"Cnr Church & Bourke St",
    "sg:city":"Glen Innes",
    "sg:classifiers":[
        {
            "category":"Travel",
            "subcategory":"Hotels & Motels",
            "type":"Entertainment"
        }
    ],
    "sg:phone":"+61 2 6732 3884",
    "sg:postcode":"2370",
    "sg:province":"NSW",
    "wof:name":"Tudor House Boutique Bed & Breakfast",
    "wof:placetype":"venue"
},
  "geometry": {"coordinates":[151.733352661,-29.7349205017],"type":"Point"}
}