{
  "type": "Feature",
  "properties": {
    "addr:full":"14 Vincentia St Marsfield NSW 2122",
    "addr:housenumber":"14",
    "addr:postcode":"2122",
    "addr:street":"Vincentia St",
    "iso:country":"AU",
    "sg:address":"14 Vincentia St",
    "sg:city":"Marsfield",
    "sg:classifiers":[
        {
            "category":"Social Services",
            "subcategory":"Retirement Home",
            "type":"Services"
        }
    ],
    "sg:phone":"+61 2 9632 3144",
    "sg:postcode":"2122",
    "sg:province":"NSW",
    "sg:tags":[
        "village"
    ],
    "wof:name":"Southern Cross Village",
    "wof:placetype":"venue"
},
  "geometry": {"coordinates":[151.10450744600001,-33.7813224792],"type":"Point"}
}