{
  "type": "Feature",
  "properties": {
    "addr:full":"1st Floor, 295 Anzac Pde Kingsford NSW 2032",
    "addr:housenumber":"295",
    "addr:postcode":"2032",
    "addr:street":"Anzac Pde",
    "iso:country":"AU",
    "sg:address":"1st Floor, 295 Anzac Pde",
    "sg:city":"Kingsford",
    "sg:classifiers":[
        {
            "category":"Professional",
            "subcategory":"Accounting & Tax Preparation",
            "type":"Services"
        }
    ],
    "sg:phone":"+61 2 9313 8395",
    "sg:postcode":"2032",
    "sg:province":"NSW",
    "sg:tags":[
        "consultant",
        "taxation"
    ],
    "wof:name":"John Su & Co",
    "wof:placetype":"venue"
},
  "geometry": {"coordinates":[151.226654053,-33.9215583801],"type":"Point"}
}