{
  "type": "Feature",
  "properties": {
    "addr:full":"207b Sturt Rd Seacombe Gardens SA 5047",
    "addr:housenumber":"207b",
    "addr:postcode":"5047",
    "addr:street":"Sturt Rd",
    "iso:country":"AU",
    "sg:address":"207b Sturt Rd",
    "sg:city":"Seacombe Gardens",
    "sg:classifiers":[
        {
            "category":"Personal",
            "subcategory":"Beauty Salon",
            "type":"Services"
        }
    ],
    "sg:phone":"+61 8 8298 2683",
    "sg:postcode":"5047",
    "sg:province":"SA",
    "sg:tags":[
        "hairdresser"
    ],
    "wof:name":"Razors Edge The",
    "wof:placetype":"venue"
},
  "geometry": {"coordinates":[138.546402,-35.017902],"type":"Point"}
}