{
  "type": "Feature",
  "properties": {
    "iso:country":"AU",
    "sg:address":"Shed 2 7 Basalt St",
    "sg:city":"Geebung",
    "sg:classifiers":[
        {
            "category":"Fast Food",
            "type":"Food & Drink"
        }
    ],
    "sg:phone":"+61 7 3865 1183",
    "sg:postcode":"4034",
    "sg:province":"QLD",
    "sg:tags":[
        "away",
        "take"
    ],
    "wof:name":"Hot Rocks Carvery & Snack Bar The",
    "wof:placetype":"venue"
},
  "geometry": {"coordinates":[153.049957,-27.365116],"type":"Point"}
}