{
  "type": "Feature",
  "properties": {
    "iso:country":"AU",
    "sg:address":"19 Strawberry Rd",
    "sg:city":"Mudgeeraba",
    "sg:classifiers":[
        {
            "category":"Professional",
            "subcategory":"Management & Consulting",
            "type":"Services"
        }
    ],
    "sg:phone":"+61 421 399 145",
    "sg:postcode":"4213",
    "sg:province":"QLD",
    "sg:tags":[
        "consultant",
        "industrial",
        "relation"
    ],
    "wof:name":"Leigh Bernhardt Corporate Consulting Services",
    "wof:placetype":"venue"
},
  "geometry": {"coordinates":[153.35475158700001,-28.1044635773],"type":"Point"}
}