{
  "type": "Feature",
  "properties": {
    "addr:full":"10 View St Mornington VIC 3931",
    "addr:housenumber":"10",
    "addr:postcode":"3931",
    "addr:street":"View St",
    "iso:country":"AU",
    "sg:address":"10 View St",
    "sg:city":"Mornington",
    "sg:classifiers":[
        {
            "category":"Utilities",
            "subcategory":"Water",
            "type":"Services"
        }
    ],
    "sg:phone":"+61 3 5975 6221",
    "sg:postcode":"3931",
    "sg:province":"VIC",
    "sg:tags":[
        "hot",
        "system"
    ],
    "wof:name":"Brady Plumbing",
    "wof:placetype":"venue"
},
  "geometry": {"coordinates":[145.03106689399999,-38.2260017395],"type":"Point"}
}