{
  "type": "Feature",
  "properties": {
    "addr:full":"34 Watton St Werribee VIC 3030",
    "addr:housenumber":"34",
    "addr:postcode":"3030",
    "addr:street":"Watton St",
    "iso:country":"AU",
    "sg:address":"34 Watton St",
    "sg:city":"Werribee",
    "sg:classifiers":[
        {
            "category":"Shopping",
            "subcategory":"Clothing, Apparel, & Fashions",
            "type":"Retail Goods"
        }
    ],
    "sg:phone":"+61 3 9731 1800",
    "sg:postcode":"3030",
    "sg:province":"VIC",
    "sg:tags":[
        "hire",
        "men's",
        "wear",
        "formal"
    ],
    "wof:name":"Parisi Formal Wear",
    "wof:placetype":"venue"
},
  "geometry": {"coordinates":[144.66044600000001,-37.90163],"type":"Point"}
}