{
  "type": "Feature",
  "properties": {
    "addr:full":"800 Toorak Rd Tooronga VIC 3146",
    "addr:housenumber":"800",
    "addr:postcode":"3146",
    "addr:street":"Toorak Rd",
    "iso:country":"AU",
    "sg:address":"800 Toorak Rd",
    "sg:city":"Tooronga",
    "sg:classifiers":[
        {
            "category":"Professional",
            "subcategory":"Art Services",
            "type":"Services"
        }
    ],
    "sg:phone":"+61 412 031 669",
    "sg:postcode":"3146",
    "sg:province":"VIC",
    "sg:tags":[
        "graphic",
        "designer"
    ],
    "wof:name":"Malindi Dezignz",
    "wof:placetype":"venue"
},
  "geometry": {"coordinates":[145.074981689,-37.848110199],"type":"Point"}
}