{
  "type": "Feature",
  "properties": {
    "iso:country":"AU",
    "sg:address":"Level 5, 574 St Kilda Rd",
    "sg:city":"Melbourne",
    "sg:classifiers":[
        {
            "category":"Real Estate",
            "subcategory":"Developer",
            "type":"Services"
        }
    ],
    "sg:phone":"+61 3 9525 1144",
    "sg:postcode":"3000",
    "sg:province":"VIC",
    "sg:tags":[
        "development"
    ],
    "wof:name":"South Pacific Property Group",
    "wof:placetype":"venue"
},
  "geometry": {"coordinates":[144.979446411,-37.847984314],"type":"Point"}
}