{
  "type": "Feature",
  "properties": {
    "addr:full":"Level 1 , Hawthorne Square, Hawthorn VIC 3122",
    "addr:postcode":"3122",
    "iso:country":"AU",
    "sg:address":"Level 1",
    "sg:city":", Hawthorne Square, Hawthorn",
    "sg:classifiers":[
        {
            "category":"Real Estate",
            "subcategory":"Real Estate Agent",
            "type":"Services"
        }
    ],
    "sg:phone":"+61 3 9818 5257",
    "sg:postcode":"3122",
    "sg:province":"VIC",
    "sg:tags":[
        "buyer"
    ],
    "wof:name":"Buyers Advocate Australia",
    "wof:placetype":"venue"
},
  "geometry": {"coordinates":[145.02789306599999,-37.8147964478],"type":"Point"}
}