{
  "type": "Feature",
  "properties": {
    "iso:country":"AU",
    "sg:address":"211 Union Rd",
    "sg:city":"Ascot Vale",
    "sg:classifiers":[
        {
            "category":"Food & Beverages",
            "subcategory":"Fruits & Vegetables",
            "type":"Retail Goods"
        }
    ],
    "sg:phone":"+61 3 9375 2332",
    "sg:postcode":"3032",
    "sg:province":"VIC",
    "sg:tags":[
        "greengrocer",
        "fruiterer"
    ],
    "wof:name":"Ascot Vale Fruit Market",
    "wof:placetype":"venue"
},
  "geometry": {"coordinates":[144.915878,-37.772537],"type":"Point"}
}