{
  "type": "Feature",
  "properties": {
    "addr:full":"Suite 4/ 216 Shaw Rd Wavell Heights QLD 4012",
    "addr:housenumber":"/ 216",
    "addr:postcode":"4012",
    "addr:street":"Shaw Rd",
    "iso:country":"AU",
    "sg:address":"Suite 4/ 216 Shaw Rd",
    "sg:city":"Wavell Heights",
    "sg:classifiers":[
        {
            "category":"Professional",
            "subcategory":"Employment Agencies",
            "type":"Services"
        }
    ],
    "sg:phone":"+61 411 878 228",
    "sg:postcode":"4012",
    "sg:province":"QLD",
    "sg:tags":[
        "occupational",
        "therapist"
    ],
    "wof:name":"Elvery Tim",
    "wof:placetype":"venue"
},
  "geometry": {"coordinates":[153.04827880900001,-27.3993625641],"type":"Point"}
}