{
  "type": "Feature",
  "properties": {
    "addr:full":"285 Burwood Hwy Burwood East VIC 3151",
    "addr:housenumber":"285",
    "addr:postcode":"3151",
    "addr:street":"Burwood Hwy",
    "iso:country":"AU",
    "sg:address":"285 Burwood Hwy",
    "sg:city":"Burwood East",
    "sg:classifiers":[
        {
            "category":"Health Services",
            "subcategory":"Doctor",
            "type":"Services"
        }
    ],
    "sg:phone":"+61 3 9802 6651",
    "sg:postcode":"3151",
    "sg:province":"VIC",
    "sg:tags":[
        "medical",
        "practitioner"
    ],
    "wof:name":"Hunter Dimity Dr",
    "wof:placetype":"venue"
},
  "geometry": {"coordinates":[145.159423828,-37.853427887],"type":"Point"}
}