{
  "type": "Feature",
  "properties": {
    "iso:country":"AU",
    "sg:address":"56 Carlo Rd",
    "sg:city":"Rainbow Beach",
    "sg:classifiers":[
        {
            "category":"Manufacturing",
            "subcategory":"Glass & Minerals",
            "type":"Manufacturing & Wholesale Goods"
        }
    ],
    "sg:phone":"+61 7 5486 8633",
    "sg:postcode":"4581",
    "sg:province":"QLD",
    "sg:tags":[
        "equipment",
        "processing",
        "handling"
    ],
    "wof:name":"Rainbow Beach Glass & Aluminium",
    "wof:placetype":"venue"
},
  "geometry": {"coordinates":[153.08680725100001,-25.9069633484],"type":"Point"}
}