{
  "type": "Feature",
  "properties": {
    "addr:full":"Unit 1/ 7 Brewery Pl Woolner NT 0820",
    "addr:housenumber":"7",
    "addr:postcode":"nt 0820",
    "addr:street":"Brewery Pl",
    "iso:country":"AU",
    "sg:address":"Unit 1/ 7 Brewery Pl",
    "sg:city":"Woolner",
    "sg:classifiers":[
        {
            "category":"Building & Trades",
            "subcategory":"Construction",
            "type":"Services"
        }
    ],
    "sg:phone":"+61 410 587 148",
    "sg:postcode":"0820",
    "sg:province":"NT",
    "sg:tags":[
        "installation",
        "air conditioning"
    ],
    "wof:name":"Chillertech",
    "wof:placetype":"venue"
},
  "geometry": {"coordinates":[130.84939575199999,-12.4354906082],"type":"Point"}
}