{
  "type": "Feature",
  "properties": {
    "iso:country":"AU",
    "sg:address":"115 Mckillop St",
    "sg:city":"Geelong",
    "sg:classifiers":[
        {
            "category":"Health Services",
            "subcategory":"Doctor",
            "type":"Services"
        }
    ],
    "sg:phone":"+61 3 5222 3044",
    "sg:postcode":"3220",
    "sg:province":"VIC",
    "sg:tags":[
        "medical",
        "practitioner"
    ],
    "wof:name":"Brandt Conrad",
    "wof:placetype":"venue"
},
  "geometry": {"coordinates":[144.356827,-38.152069],"type":"Point"}
}