{
  "type": "Feature",
  "properties": {
    "addr:full":"Unit 4/ 1350 Canterbury Rd Punchbowl NSW 2196",
    "addr:housenumber":"/ 1350",
    "addr:postcode":"2196",
    "addr:street":"Canterbury Rd",
    "iso:country":"AU",
    "sg:address":"Unit 4/ 1350 Canterbury Rd",
    "sg:city":"Punchbowl",
    "sg:classifiers":[
        {
            "category":"Shopping",
            "type":"Retail Goods"
        }
    ],
    "sg:phone":"+61 2 9759 3835",
    "sg:postcode":"2196",
    "sg:province":"NSW",
    "sg:tags":[
        "clearance",
        "factory",
        "outlet"
    ],
    "wof:name":"Bargain Warehouse",
    "wof:placetype":"venue"
},
  "geometry": {"coordinates":[151.05798300000001,-33.931885],"type":"Point"}
}