{
  "type": "Feature",
  "properties": {
    "addr:full":"242 Maitland Rd Sandgate NSW 2304",
    "addr:housenumber":"242",
    "addr:postcode":"2304",
    "addr:street":"Maitland Rd",
    "iso:country":"AU",
    "sg:address":"242 Maitland Rd",
    "sg:city":"Sandgate",
    "sg:classifiers":[
        {
            "category":"Social Services",
            "subcategory":"Adult Care",
            "type":"Services"
        }
    ],
    "sg:phone":"+61 2 4967 0660",
    "sg:postcode":"2304",
    "sg:province":"NSW",
    "sg:tags":[
        "aged"
    ],
    "wof:name":"Catholic Care of The Aged",
    "wof:placetype":"venue"
},
  "geometry": {"coordinates":[151.737518311,-32.8982467651],"type":"Point"}
}