{
  "type": "Feature",
  "properties": {
    "iso:country":"AU",
    "sg:address":"22531 Bass Hwy",
    "sg:city":"Smithton",
    "sg:classifiers":[
        {
            "category":"Building & Trades",
            "subcategory":"Construction",
            "type":"Services"
        }
    ],
    "sg:phone":"+61 3 6452 1736",
    "sg:postcode":"7330",
    "sg:province":"TAS",
    "sg:tags":[
        "earth",
        "excavating",
        "moving",
        "contractor"
    ],
    "wof:name":"Red Roo Contractors",
    "wof:placetype":"venue"
},
  "geometry": {"coordinates":[145.11909499999999,-40.855026],"type":"Point"}
}