{
  "type": "Feature",
  "properties": {
    "addr:full":"Axedale-Goornong Rd Fosterville VIC 3557",
    "addr:postcode":"3557",
    "addr:street":"Axedale-Goornong Rd",
    "iso:country":"AU",
    "sg:address":"Axedale-Goornong Rd",
    "sg:city":"Fosterville",
    "sg:classifiers":[
        {
            "category":"Train Station",
            "subcategory":"Light Rail",
            "type":"Transportation"
        }
    ],
    "sg:phone":"+61 3 5439 7466",
    "sg:postcode":"3557",
    "sg:province":"VIC",
    "sg:tags":[
        "equipment",
        "energy",
        "solar"
    ],
    "wof:name":"Solar Systems Pty Ltd",
    "wof:placetype":"venue"
},
  "geometry": {"coordinates":[144.51260375999999,-36.7237548828],"type":"Point"}
}