{
  "type": "Feature",
  "properties": {
    "iso:country":"AU",
    "sg:address":"10 Wallace St",
    "sg:city":"Macksville",
    "sg:classifiers":[
        {
            "category":"Real Estate",
            "subcategory":"Real Estate Agent",
            "type":"Services"
        }
    ],
    "sg:phone":"+61 2 6568 1666",
    "sg:postcode":"2447",
    "sg:province":"NSW",
    "wof:name":"Kennedy G J & Co Pty Ltd",
    "wof:placetype":"venue"
},
  "geometry": {"coordinates":[152.920425,-30.707182],"type":"Point"}
}