{
  "type": "Feature",
  "properties": {
    "iso:country":"AU",
    "sg:address":"203 Rawdon Island Rd",
    "sg:city":"Sancrox",
    "sg:classifiers":[
        {
            "category":"Communications",
            "subcategory":"News Services",
            "type":"Services"
        }
    ],
    "sg:phone":"+61 409 744 270",
    "sg:postcode":"2446",
    "sg:province":"NSW",
    "sg:tags":[
        "information",
        "tourist",
        "attractions"
    ],
    "wof:name":"Junk Cruises",
    "wof:placetype":"venue"
},
  "geometry": {"coordinates":[152.78486599999999,-31.444145],"type":"Point"}
}