{
  "type": "Feature",
  "properties": {
    "iso:country":"AU",
    "sg:address":"1/ 13 Herbert St",
    "sg:city":"Slacks Creek",
    "sg:classifiers":[
        {
            "category":"Social Services",
            "subcategory":"Adult Care",
            "type":"Services"
        }
    ],
    "sg:phone":"+61 7 3386 0637",
    "sg:postcode":"4127",
    "sg:province":"QLD",
    "sg:tags":[
        "towing"
    ],
    "wof:name":"Tarrawanna Towing",
    "wof:placetype":"venue"
},
  "geometry": {"coordinates":[153.12283325199999,-27.622423172],"type":"Point"}
}