{
  "type": "Feature",
  "properties": {
    "addr:full":"29 Bannons La Yarrambat VIC 3091",
    "addr:housenumber":"29",
    "addr:postcode":"3091",
    "addr:street":"Bannons La",
    "iso:country":"AU",
    "sg:address":"29 Bannons La",
    "sg:city":"Yarrambat",
    "sg:classifiers":[
        {
            "category":"Real Estate",
            "subcategory":"Surveying",
            "type":"Services"
        }
    ],
    "sg:phone":"+61 3 9436 2250",
    "sg:postcode":"3091",
    "sg:province":"VIC",
    "sg:tags":[
        "building",
        "surveyor"
    ],
    "wof:name":"Plenty Valley Building surveying",
    "wof:placetype":"venue"
},
  "geometry": {"coordinates":[145.13897705100001,-37.6260452271],"type":"Point"}
}