{
  "type": "Feature",
  "properties": {
    "iso:country":"AU",
    "sg:address":"186 Clovelly Rd",
    "sg:city":"Randwick",
    "sg:classifiers":[
        {
            "category":"Social Services",
            "subcategory":"Child Care",
            "type":"Services"
        }
    ],
    "sg:phone":"+61 2 9665 3058",
    "sg:postcode":"2031",
    "sg:province":"NSW",
    "wof:name":"Beulah Matumbi Child Care Centre",
    "wof:placetype":"venue"
},
  "geometry": {"coordinates":[151.252243042,-33.9106063843],"type":"Point"}
}