{
  "type": "Feature",
  "properties": {
    "addr:full":"14 Allambee Pl Valentine NSW 2280",
    "addr:housenumber":"14",
    "addr:postcode":"2280",
    "addr:street":"Allambee Pl",
    "iso:country":"AU",
    "sg:address":"14 Allambee Pl",
    "sg:city":"Valentine",
    "sg:classifiers":[
        {
            "category":"Communications",
            "subcategory":"Film & Video Production",
            "type":"Services"
        }
    ],
    "sg:phone":"+61 2 4946 8692",
    "sg:postcode":"2280",
    "sg:province":"NSW",
    "sg:tags":[
        "dvd",
        "library"
    ],
    "wof:name":"Network Video",
    "wof:placetype":"venue"
},
  "geometry": {"coordinates":[151.63528442399999,-33.008934021],"type":"Point"}
}