{
  "type": "Feature",
  "properties": {
    "addr:full":"Unit 1/ 8 Principal Link Malaga WA 6090",
    "addr:housenumber":"8",
    "addr:postcode":"6090",
    "addr:street":"Principal Link",
    "iso:country":"AU",
    "sg:address":"Unit 1/ 8 Principal Link",
    "sg:city":"Malaga",
    "sg:classifiers":[
        {
            "category":"Home & Garden",
            "subcategory":"Building Materials",
            "type":"Retail Goods"
        }
    ],
    "sg:phone":"+61 417 095 931",
    "sg:postcode":"6090",
    "sg:province":"WA",
    "sg:tags":[
        "fencing"
    ],
    "wof:name":"Allied Leisure Products",
    "wof:placetype":"venue"
},
  "geometry": {"coordinates":[115.89369201700001,-31.8516998291],"type":"Point"}
}