{
  "type": "Feature",
  "properties": {
    "addr:full":"63 Carcoar St Blayney NSW 2799",
    "addr:housenumber":"63",
    "addr:postcode":"2799",
    "addr:street":"Carcoar St",
    "iso:country":"AU",
    "sg:address":"63 Carcoar St",
    "sg:city":"Blayney",
    "sg:classifiers":[
        {
            "category":"Taxi",
            "type":"Transportation"
        }
    ],
    "sg:phone":"+61 2 6368 2294",
    "sg:postcode":"2799",
    "sg:province":"NSW",
    "sg:tags":[
        "cab"
    ],
    "wof:name":"Clinghan B J",
    "wof:placetype":"venue"
},
  "geometry": {"coordinates":[149.24949599999999,-33.528496],"type":"Point"}
}