{
  "type": "Feature",
  "properties": {
    "addr:full":"6 Reichert Drv Ernest QLD 4214",
    "addr:housenumber":"6",
    "addr:postcode":"4214",
    "addr:street":"Reichert Drv Ernest",
    "iso:country":"AU",
    "sg:address":"6 Reichert Drv",
    "sg:city":"Ernest",
    "sg:phone":"+61 7 5571 5097",
    "sg:postcode":"4214",
    "sg:province":"QLD",
    "wof:name":"Quality Tanks",
    "wof:placetype":"venue"
},
  "geometry": {"coordinates":[153.36074829099999,-27.9640274048],"type":"Point"}
}