{
  "type": "Feature",
  "properties": {
    "iso:country":"AU",
    "sg:address":"9 Second Ave",
    "sg:city":"Sandgate",
    "sg:classifiers":[
        {
            "category":"Shopping",
            "subcategory":"Clothing, Apparel, & Fashions",
            "type":"Retail Goods"
        }
    ],
    "sg:phone":"+61 7 3269 3266",
    "sg:postcode":"4017",
    "sg:province":"QLD",
    "sg:tags":[
        "lady",
        "wear"
    ],
    "wof:name":"Double Two",
    "wof:placetype":"venue"
},
  "geometry": {"coordinates":[153.07090759299999,-27.3200569153],"type":"Point"}
}