{
  "type": "Feature",
  "properties": {
    "iso:country":"AU",
    "sg:address":"Unit 32 13",
    "sg:city":"Torquata Blv Helena Valley",
    "sg:classifiers":[
        {
            "category":"Retail",
            "subcategory":"Repair Shop",
            "type":"Services"
        }
    ],
    "sg:phone":"+61 8 9274 1586",
    "sg:postcode":"6056",
    "sg:province":"WA",
    "sg:tags":[
        "upholsterer"
    ],
    "wof:name":"Creations By Chole",
    "wof:placetype":"venue"
},
  "geometry": {"coordinates":[116.028526306,-31.9167957306],"type":"Point"}
}