{
  "type": "Feature",
  "properties": {
    "addr:full":"16 Morning St Maryborough QLD 4650",
    "addr:housenumber":"16",
    "addr:postcode":"4650",
    "addr:street":"Morning St",
    "iso:country":"AU",
    "sg:address":"16 Morning St",
    "sg:city":"Maryborough",
    "sg:classifiers":[
        {
            "category":"Building & Trades",
            "subcategory":"Construction",
            "type":"Services"
        }
    ],
    "sg:phone":"+61 7 4121 2131",
    "sg:postcode":"4650",
    "sg:province":"QLD",
    "sg:tags":[
        "contractor"
    ],
    "wof:name":"Sommerfeld P W",
    "wof:placetype":"venue"
},
  "geometry": {"coordinates":[152.67993200000001,-25.527178],"type":"Point"}
}