{
  "type": "Feature",
  "properties": {
    "iso:country":"AU",
    "sg:address":"119 George St",
    "sg:city":"Bathurst",
    "sg:classifiers":[
        {
            "category":"Personal",
            "subcategory":"Nail Salon",
            "type":"Services"
        }
    ],
    "sg:phone":"+61 421 865 226",
    "sg:postcode":"2795",
    "sg:province":"NSW",
    "sg:tags":[
        "artificial"
    ],
    "wof:name":"Tracey Davis Acrylic Nails",
    "wof:placetype":"venue"
},
  "geometry": {"coordinates":[149.57844543499999,-33.4166946411],"type":"Point"}
}