{
  "type": "Feature",
  "properties": {
    "addr:full":"114 Victoria St Geelong North VIC 3215",
    "addr:housenumber":"114",
    "addr:postcode":"3215",
    "addr:street":"Victoria St",
    "iso:country":"AU",
    "sg:address":"114 Victoria St",
    "sg:city":"Geelong North",
    "sg:classifiers":[
        {
            "category":"Professional",
            "subcategory":"Engineering",
            "type":"Services"
        }
    ],
    "sg:phone":"+61 3 5278 2944",
    "sg:postcode":"3215",
    "sg:province":"VIC",
    "sg:tags":[
        "manufacturing",
        "engineer"
    ],
    "wof:name":"G.D. Manufacturing Engineers Pty Ltd",
    "wof:placetype":"venue"
},
  "geometry": {"coordinates":[144.35018920900001,-38.1229553223],"type":"Point"}
}