{
  "type": "Feature",
  "properties": {
    "addr:full":"1/ 15 Gibraltar St Bungendore ACT 2621",
    "addr:housenumber":"/ 15",
    "addr:postcode":"2621",
    "addr:street":"Gibraltar St",
    "iso:country":"AU",
    "sg:address":"1/ 15 Gibraltar St",
    "sg:city":"Bungendore",
    "sg:classifiers":[
        {
            "category":"Food & Beverages",
            "subcategory":"Liquor & Beverages",
            "type":"Retail Goods"
        }
    ],
    "sg:phone":"+61 2 6238 1735",
    "sg:postcode":"2621",
    "sg:province":"ACT",
    "sg:tags":[
        "merchant",
        "spirit",
        "wine"
    ],
    "wof:name":"Bungendore Cellars",
    "wof:placetype":"venue"
},
  "geometry": {"coordinates":[149.44036865199999,-35.2541847229],"type":"Point"}
}