{
  "type": "Feature",
  "properties": {
    "iso:country":"AU",
    "sg:address":"15 George St",
    "sg:city":"Marmong Point",
    "sg:classifiers":[
        {
            "category":"Personal",
            "subcategory":"Beauty Salon",
            "type":"Services"
        }
    ],
    "sg:phone":"+61 2 4950 8577",
    "sg:postcode":"2284",
    "sg:province":"NSW",
    "sg:tags":[
        "hairdresser"
    ],
    "wof:name":"Hairs How",
    "wof:placetype":"venue"
},
  "geometry": {"coordinates":[151.61822509800001,-32.9820213318],"type":"Point"}
}