{
  "type": "Feature",
  "properties": {
    "addr:full":"25 Bryant St Flemington VIC 3031",
    "addr:housenumber":"25",
    "addr:postcode":"3031",
    "addr:street":"Bryant St",
    "iso:country":"AU",
    "sg:address":"25 Bryant St",
    "sg:city":"Flemington",
    "sg:classifiers":[
        {
            "category":"Education",
            "subcategory":"Kindergarten",
            "type":"Public Place"
        }
    ],
    "sg:phone":"+61 3 9376 6305",
    "sg:postcode":"3031",
    "sg:province":"VIC",
    "sg:tags":[
        "pre-schools"
    ],
    "wof:name":"St Brendan's Kindergarten",
    "wof:placetype":"venue"
},
  "geometry": {"coordinates":[144.93313599999999,-37.7841],"type":"Point"}
}