{
  "type": "Feature",
  "properties": {
    "iso:country":"AU",
    "sg:address":"38 Clifton Drv",
    "sg:city":"Port Macquarie",
    "sg:classifiers":[
        {
            "category":"Health Services",
            "subcategory":"Nursing And Care Facility",
            "type":"Services"
        }
    ],
    "sg:phone":"+61 2 6583 1744",
    "sg:postcode":"2444",
    "sg:province":"NSW",
    "sg:tags":[
        "home"
    ],
    "wof:name":"Lourdes Nursing Home",
    "wof:placetype":"venue"
},
  "geometry": {"coordinates":[152.88833600000001,-31.434679],"type":"Point"}
}