{
  "type": "Feature",
  "properties": {
    "addr:full":"39 Idlewild Ave Aberfoyle Park SA 5159",
    "addr:housenumber":"39",
    "addr:postcode":"5159",
    "addr:street":"Idlewild Ave",
    "iso:country":"AU",
    "sg:address":"39 Idlewild Ave",
    "sg:city":"Aberfoyle Park",
    "sg:classifiers":[
        {
            "category":"Health Services",
            "subcategory":"Health Practitioner",
            "type":"Services"
        }
    ],
    "sg:phone":"+61 8 8270 6625",
    "sg:postcode":"5159",
    "sg:province":"SA",
    "sg:tags":[
        "naturopath"
    ],
    "wof:name":"Ken King",
    "wof:placetype":"venue"
},
  "geometry": {"coordinates":[138.588165283,-35.0770645142],"type":"Point"}
}