{
  "type": "Feature",
  "properties": {
    "iso:country":"AU",
    "sg:address":"39 Irving St",
    "sg:city":"Footscray",
    "sg:classifiers":[
        {
            "category":"Health Services",
            "subcategory":"Health Practitioner",
            "type":"Services"
        }
    ],
    "sg:phone":"+61 3 9689 8862",
    "sg:postcode":"3011",
    "sg:province":"VIC",
    "sg:tags":[
        "acupuncture"
    ],
    "wof:name":"Cai Wilson",
    "wof:placetype":"venue"
},
  "geometry": {"coordinates":[144.90159606899999,-37.8013916016],"type":"Point"}
}