{
  "type": "Feature",
  "properties": {
    "iso:country":"AU",
    "sg:address":"Shop 2 198",
    "sg:city":"Park Tce Salisbury Plain",
    "sg:classifiers":[
        {
            "category":"Building & Trades",
            "subcategory":"Locksmith",
            "type":"Services"
        }
    ],
    "sg:phone":"+61 8 8258 2814",
    "sg:postcode":"5109",
    "sg:province":"SA",
    "sg:tags":[
        "strongroom",
        "safe",
        "door"
    ],
    "wof:name":"Salisbury Locksmiths",
    "wof:placetype":"venue"
},
  "geometry": {"coordinates":[138.667434692,-34.7683906555],"type":"Point"}
}