{
  "type": "Feature",
  "properties": {
    "iso:country":"AU",
    "sg:address":"91- 111 Melrose St",
    "sg:city":"North Melbourne",
    "sg:classifiers":[
        {
            "category":"Organizations",
            "subcategory":"Community Association",
            "type":"Services"
        }
    ],
    "sg:phone":"+61 3 9328 1665",
    "sg:postcode":"3051",
    "sg:province":"VIC",
    "sg:tags":[
        "club",
        "senior",
        "citizen"
    ],
    "wof:name":"Elderly Citizens Club North West Melbourne",
    "wof:placetype":"venue"
},
  "geometry": {"coordinates":[144.942062378,-37.7926864624],"type":"Point"}
}