{
  "type": "Feature",
  "properties": {
    "addr:full":"151 Labouchere Rd Como WA 6152",
    "addr:housenumber":"151",
    "addr:postcode":"6152",
    "addr:street":"Labouchere Rd",
    "iso:country":"AU",
    "sg:address":"151 Labouchere Rd",
    "sg:city":"Como",
    "sg:classifiers":[
        {
            "category":"Deli",
            "type":"Food & Drink"
        }
    ],
    "sg:phone":"+61 8 9367 1435",
    "sg:postcode":"6152",
    "sg:province":"WA",
    "sg:tags":[
        "delicatessen"
    ],
    "wof:name":"Como Beach Deli",
    "wof:placetype":"venue"
},
  "geometry": {"coordinates":[115.858414,-31.991362],"type":"Point"}
}