{
  "type": "Feature",
  "properties": {
    "iso:country":"AU",
    "sg:address":"1/ 17 Canham Way",
    "sg:city":"Greenwood",
    "sg:classifiers":[
        {
            "category":"Communications",
            "subcategory":"Film & Video Production",
            "type":"Services"
        }
    ],
    "sg:phone":"+61 8 9247 2200",
    "sg:postcode":"6024",
    "sg:province":"WA",
    "sg:tags":[
        "lighting",
        "emergency",
        "power"
    ],
    "wof:name":"Legrand Minitronics Pty Ltd",
    "wof:placetype":"venue"
},
  "geometry": {"coordinates":[115.818122864,-31.8210372925],"type":"Point"}
}