{
  "type": "Feature",
  "properties": {
    "iso:country":"AU",
    "sg:address":"355 Exhibition St",
    "sg:city":"Melbourne",
    "sg:classifiers":[
        {
            "category":"Landmark",
            "subcategory":"Tourist Information",
            "type":"Public Place"
        }
    ],
    "sg:phone":"+61 3 9654 3176",
    "sg:postcode":"3000",
    "sg:province":"VIC",
    "sg:tags":[
        "bureau"
    ],
    "sg:website":"http://www.tourismmalaysia.gov.my",
    "wof:name":"Tourism Malaysia",
    "wof:placetype":"venue"
},
  "geometry": {"coordinates":[144.96827697800001,-37.8074760437],"type":"Point"}
}