{
  "type": "Feature",
  "properties": {
    "addr:full":"Shop 2 a West Mall Rutherford NSW 2320",
    "addr:housenumber":"shop 2 a",
    "addr:postcode":"2320",
    "addr:street":"West Mall",
    "iso:country":"AU",
    "sg:address":"Shop 2",
    "sg:city":"a West Mall Rutherford",
    "sg:classifiers":[
        {
            "category":"Retail",
            "subcategory":"Veterinary Services",
            "type":"Services"
        }
    ],
    "sg:phone":"+61 2 4932 6366",
    "sg:postcode":"2320",
    "sg:province":"NSW",
    "sg:tags":[
        "surgeon"
    ],
    "wof:name":"Caves Stewart",
    "wof:placetype":"venue"
},
  "geometry": {"coordinates":[151.52746582,-32.7152900696],"type":"Point"}
}