{
  "type": "Feature",
  "properties": {
    "iso:country":"AU",
    "sg:address":"267a Clarinda St",
    "sg:city":"Parkes",
    "sg:classifiers":[
        {
            "category":"Health Services",
            "subcategory":"Optometrist",
            "type":"Services"
        }
    ],
    "sg:phone":"+61 2 6863 5577",
    "sg:postcode":"2870",
    "sg:province":"NSW",
    "wof:name":"Chris Dajkovich",
    "wof:placetype":"venue"
},
  "geometry": {"coordinates":[148.174698,-33.136551],"type":"Point"}
}