{
  "type": "Feature",
  "properties": {
    "addr:full":"11b McHarry Pl Shepparton VIC 3630",
    "addr:housenumber":"11b",
    "addr:postcode":"3630",
    "addr:street":"Mcharry Pl",
    "iso:country":"AU",
    "sg:address":"11b McHarry Pl",
    "sg:city":"Shepparton",
    "sg:classifiers":[
        {
            "category":"Food & Beverages",
            "subcategory":"Bakery",
            "type":"Retail Goods"
        }
    ],
    "sg:phone":"+61 3 5821 3763",
    "sg:postcode":"3630",
    "sg:province":"VIC",
    "sg:tags":[
        "cake",
        "shop",
        "pastry"
    ],
    "wof:name":"Freeman's Bakery Cafes",
    "wof:placetype":"venue"
},
  "geometry": {"coordinates":[145.42335510300001,-36.3728942871],"type":"Point"}
}