{
  "type": "Feature",
  "properties": {
    "addr:full":"\"The Cottage\" 22 Nerang St Nerang QLD 4211",
    "addr:housenumber":"22",
    "addr:postcode":"4211",
    "addr:street":"Nerang St",
    "iso:country":"AU",
    "sg:address":"\"The Cottage\" 22 Nerang St",
    "sg:city":"Nerang",
    "sg:classifiers":[
        {
            "category":"Health Services",
            "subcategory":"Health Practitioner",
            "type":"Services"
        }
    ],
    "sg:phone":"+61 7 5596 4866",
    "sg:postcode":"4211",
    "sg:province":"QLD",
    "sg:tags":[
        "physiotherapist"
    ],
    "wof:name":"Yelland Simon",
    "wof:placetype":"venue"
},
  "geometry": {"coordinates":[153.336624145,-27.9918003082],"type":"Point"}
}