{
  "type": "Feature",
  "properties": {
    "iso:country":"AU",
    "sg:address":"PO Box 560",
    "sg:city":"Samford",
    "sg:classifiers":[
        {
            "category":"Bars & Pubs",
            "subcategory":"Biergarten",
            "type":"Food & Drink"
        }
    ],
    "sg:phone":"+61 7 3289 9191",
    "sg:postcode":"4520",
    "sg:province":"QLD",
    "sg:tags":[
        "eucalyptus",
        "oil",
        "tree",
        "essential",
        "tea"
    ],
    "wof:name":"Ahimsa",
    "wof:placetype":"venue"
},
  "geometry": {"coordinates":[152.88664199999999,-27.373671],"type":"Point"}
}