{
  "type": "Feature",
  "properties": {
    "addr:full":"11 Hylton Crs Forest Hill VIC 3131",
    "addr:housenumber":"11",
    "addr:postcode":"3131",
    "addr:street":"Hylton Crs",
    "iso:country":"AU",
    "sg:address":"11 Hylton Crs",
    "sg:city":"Forest Hill",
    "sg:classifiers":[
        {
            "category":"Shopping",
            "type":"Retail Goods"
        }
    ],
    "sg:phone":"+61 3 9878 2850",
    "sg:postcode":"3131",
    "sg:province":"VIC",
    "sg:tags":[
        "equipment",
        "safety",
        "accessory"
    ],
    "wof:name":"Safety Air Pty Ltd",
    "wof:placetype":"venue"
},
  "geometry": {"coordinates":[145.17112731899999,-37.8427810669],"type":"Point"}
}