{
  "type": "Feature",
  "properties": {
    "addr:full":"Bon Accord Rd King River WA 6330",
    "addr:postcode":"6330",
    "addr:street":"Bon Accord Rd",
    "iso:country":"AU",
    "sg:address":"Bon Accord Rd",
    "sg:city":"King River",
    "sg:classifiers":[
        {
            "category":"Arts & Performance",
            "subcategory":"Art Gallery",
            "type":"Entertainment"
        }
    ],
    "sg:phone":"+61 8 9844 3221",
    "sg:postcode":"6330",
    "sg:province":"WA",
    "wof:name":"Linscott Studio",
    "wof:placetype":"venue"
},
  "geometry": {"coordinates":[117.916419983,-34.9350395203],"type":"Point"}
}