{
  "type": "Feature",
  "properties": {
    "addr:full":"Shop 1 14 Homemaker Supacentre 4-6 Niang Belrose NSW 2085",
    "addr:housenumber":"shop;14;4-6",
    "addr:postcode":"2085",
    "addr:street":"Homemaker Supacentre",
    "iso:country":"AU",
    "sg:address":"Shop 1 14",
    "sg:city":"Homemaker Supacentre 4-6 Niang Belrose",
    "sg:classifiers":[
        {
            "category":"Building & Trades",
            "subcategory":"Equipment Rental",
            "type":"Services"
        }
    ],
    "sg:phone":"+61 2 9986 2590",
    "sg:postcode":"2085",
    "sg:province":"NSW",
    "sg:tags":[
        "fitness"
    ],
    "wof:name":"Elite Fitness Equipment",
    "wof:placetype":"venue"
},
  "geometry": {"coordinates":[151.22134399399999,-33.7305297852],"type":"Point"}
}