{
  "type": "Feature",
  "properties": {
    "addr:full":"12 Christie Rd Lonsdale SA 5160",
    "addr:housenumber":"12",
    "addr:postcode":"5160",
    "addr:street":"Christie Rd",
    "iso:country":"AU",
    "sg:address":"12 Christie Rd",
    "sg:city":"Lonsdale",
    "sg:classifiers":[
        {
            "category":"Utilities",
            "subcategory":"Refuse",
            "type":"Services"
        }
    ],
    "sg:phone":"+61 8 8382 6681",
    "sg:postcode":"5160",
    "sg:province":"SA",
    "sg:tags":[
        "disposal",
        "reduction",
        "waste"
    ],
    "wof:name":"All Bulk Waste",
    "wof:placetype":"venue"
},
  "geometry": {"coordinates":[138.49447631800001,-35.1021881104],"type":"Point"}
}