{
  "type": "Feature",
  "properties": {
    "addr:full":"96 Forrest St Collie WA 6225",
    "addr:housenumber":"96",
    "addr:postcode":"6225",
    "addr:street":"Forrest St",
    "iso:country":"AU",
    "sg:address":"96 Forrest St",
    "sg:city":"Collie",
    "sg:classifiers":[
        {
            "category":"Wholesale",
            "subcategory":"Machinery & Supplies",
            "type":"Manufacturing & Wholesale Goods"
        }
    ],
    "sg:phone":"+61 8 9734 1624",
    "sg:postcode":"6225",
    "sg:province":"WA",
    "sg:tags":[
        "bearing",
        "bushing"
    ],
    "wof:name":"Coalfields Bearings",
    "wof:placetype":"venue"
},
  "geometry": {"coordinates":[116.152809,-33.358326],"type":"Point"}
}