{
  "type": "Feature",
  "properties": {
    "addr:full":"100 Wigram La Glebe NSW 2037",
    "addr:housenumber":"100",
    "addr:postcode":"2037",
    "addr:street":"Wigram La",
    "iso:country":"AU",
    "sg:address":"100 Wigram La",
    "sg:city":"Glebe",
    "sg:classifiers":[
        {
            "category":"Education",
            "subcategory":"Dance Studio",
            "type":"Public Place"
        }
    ],
    "sg:phone":"+61 2 9518 4615",
    "sg:postcode":"2037",
    "sg:province":"NSW",
    "sg:tags":[
        "instruction",
        "language"
    ],
    "wof:name":"Joanna Hempel English & Accent Coaching",
    "wof:placetype":"venue"
},
  "geometry": {"coordinates":[151.17857360799999,-33.8809394836],"type":"Point"}
}