{
  "type": "Feature",
  "properties": {
    "iso:country":"AU",
    "sg:address":"PO Box 1167",
    "sg:city":"Bongaree",
    "sg:classifiers":[
        {
            "category":"Building & Trades",
            "subcategory":"Construction",
            "type":"Services"
        }
    ],
    "sg:phone":"+61 7 3410 0448",
    "sg:postcode":"4507",
    "sg:province":"QLD",
    "sg:tags":[
        "ceiling"
    ],
    "wof:name":"ARC Ceilings",
    "wof:placetype":"venue"
},
  "geometry": {"coordinates":[153.1668396,-27.0792503357],"type":"Point"}
}