{
  "type": "Feature",
  "properties": {
    "addr:full":"Shop 4, The Walk Cnr Edgeworth David Ave & Pacific Hornsby NSW 1630",
    "addr:housenumber":"shop 4",
    "addr:postcode":"1630",
    "addr:street":"The Walk Cnr Edgeworth David Ave &",
    "iso:country":"AU",
    "sg:address":"Shop 4, The Walk Cnr Edgeworth David Ave & Pacific",
    "sg:city":"Hornsby",
    "sg:classifiers":[
        {
            "category":"Building & Trades",
            "subcategory":"Locksmith",
            "type":"Services"
        }
    ],
    "sg:phone":"+61 2 9476 4363",
    "sg:postcode":"1630",
    "sg:province":"NSW",
    "sg:tags":[
        "lock"
    ],
    "wof:name":"Fortress Locksmiths",
    "wof:placetype":"venue"
},
  "geometry": {"coordinates":[151.0990448,-33.7053909302],"type":"Point"}
}