{
  "type": "Feature",
  "properties": {
    "addr:full":"18 Martin Drv Tomago NSW 2322",
    "addr:housenumber":"18",
    "addr:postcode":"2322",
    "addr:street":"Martin Drv",
    "iso:country":"AU",
    "sg:address":"18 Martin Drv",
    "sg:city":"Tomago",
    "sg:classifiers":[
        {
            "category":"Manufacturing",
            "subcategory":"Metals",
            "type":"Manufacturing & Wholesale Goods"
        }
    ],
    "sg:phone":"+61 2 4964 0500",
    "sg:postcode":"2322",
    "sg:province":"NSW",
    "sg:tags":[
        "steel",
        "fabricator",
        "mfrs"
    ],
    "wof:name":"Perfab Engineering",
    "wof:placetype":"venue"
},
  "geometry": {"coordinates":[151.70216369600001,-32.8188362122],"type":"Point"}
}