{
  "type": "Feature",
  "properties": {
    "iso:country":"AU",
    "sg:address":"23a Allunga Ave",
    "sg:city":"Port Macquarie",
    "sg:classifiers":[
        {
            "category":"Home & Garden",
            "subcategory":"Carpets & Floor Coverings",
            "type":"Retail Goods"
        }
    ],
    "sg:phone":"+61 2 6582 7024",
    "sg:postcode":"2444",
    "sg:province":"NSW",
    "sg:tags":[
        "tile",
        "wall",
        "layer"
    ],
    "wof:name":"Hyde DW & MJ",
    "wof:placetype":"venue"
},
  "geometry": {"coordinates":[152.92477400000001,-31.452751],"type":"Point"}
}