{
  "type": "Feature",
  "properties": {
    "addr:full":"630 Main Rd Granton TAS 7030",
    "addr:housenumber":"630",
    "addr:postcode":"7030",
    "addr:street":"Main Rd",
    "iso:country":"AU",
    "sg:address":"630 Main Rd",
    "sg:city":"Granton",
    "sg:classifiers":[
        {
            "category":"Retail",
            "subcategory":"Event Space",
            "type":"Services"
        }
    ],
    "sg:phone":"+61 3 6263 7335",
    "sg:postcode":"7030",
    "sg:province":"TAS",
    "sg:tags":[
        "venue",
        "reception",
        "wedding"
    ],
    "wof:name":"Hilltop Granton The",
    "wof:placetype":"venue"
},
  "geometry": {"coordinates":[147.231811523,-42.7521438599],"type":"Point"}
}