{
  "type": "Feature",
  "properties": {
    "iso:country":"AU",
    "sg:address":"103 Halifax St",
    "sg:city":"Adelaide",
    "sg:classifiers":[
        {
            "category":"Personal",
            "type":"Services"
        }
    ],
    "sg:phone":"+61 1300 308 997",
    "sg:postcode":"5000",
    "sg:province":"SA",
    "sg:tags":[
        "gift"
    ],
    "sg:website":"http://www.surprisebox.com.au",
    "wof:name":"Surprise Box",
    "wof:placetype":"venue"
},
  "geometry": {"coordinates":[138.60403442399999,-34.9328918457],"type":"Point"}
}