{
  "type": "Feature",
  "properties": {
    "addr:full":"8A Main St Blackburn VIC 3130",
    "addr:housenumber":"8a",
    "addr:postcode":"3130",
    "addr:street":"Main St",
    "iso:country":"AU",
    "sg:address":"8A Main St",
    "sg:city":"Blackburn",
    "sg:classifiers":[
        {
            "category":"Banks & Credit Unions",
            "subcategory":"Investment Brokerage",
            "type":"Services"
        }
    ],
    "sg:phone":"+61 3 9894 4055",
    "sg:postcode":"3130",
    "sg:province":"VIC",
    "wof:name":"Walkerden Clark Financial Planning Pty Ltd",
    "wof:placetype":"venue"
},
  "geometry": {"coordinates":[145.14982605,-37.8213157654],"type":"Point"}
}