{
  "type": "Feature",
  "properties": {
    "iso:country":"AU",
    "sg:address":"Park St",
    "sg:city":"Bright",
    "sg:classifiers":[
        {
            "category":"Education",
            "subcategory":"School",
            "type":"Public Place"
        }
    ],
    "sg:phone":"+61 3 5755 1166",
    "sg:postcode":"3741",
    "sg:province":"VIC",
    "sg:tags":[
        "state",
        "except",
        "nsw"
    ],
    "wof:name":"Bright P-12 College",
    "wof:placetype":"venue"
},
  "geometry": {"coordinates":[146.96241800000001,-36.732006],"type":"Point"}
}