{
  "type": "Feature",
  "properties": {
    "iso:country":"AU",
    "sg:address":"429 Hargreaves St",
    "sg:city":"Bendigo",
    "sg:classifiers":[
        {
            "category":"Health Services",
            "subcategory":"Dentist",
            "type":"Services"
        }
    ],
    "sg:phone":"+61 3 5443 7737",
    "sg:postcode":"3550",
    "sg:province":"VIC",
    "wof:name":"Cathy Pham Dental",
    "wof:placetype":"venue"
},
  "geometry": {"coordinates":[144.27636718799999,-36.7630233765],"type":"Point"}
}