{
  "type": "Feature",
  "properties": {
    "iso:country":"AU",
    "sg:address":"7 Silvertop Ave",
    "sg:city":"Halls Head",
    "sg:classifiers":[
        {
            "category":"Building & Trades",
            "subcategory":"Construction",
            "type":"Services"
        }
    ],
    "sg:phone":"+61 8 9582 8772",
    "sg:postcode":"6210",
    "sg:province":"WA",
    "sg:tags":[
        "fencing",
        "contractor"
    ],
    "wof:name":"Southern Districts Rural Fencing",
    "wof:placetype":"venue"
},
  "geometry": {"coordinates":[115.694351,-32.54858],"type":"Point"}
}