{
  "type": "Feature",
  "properties": {
    "addr:full":"79 Turea St Blacksmiths NSW 2281",
    "addr:housenumber":"79",
    "addr:postcode":"2281",
    "addr:street":"Turea St",
    "iso:country":"AU",
    "sg:address":"79 Turea St",
    "sg:city":"Blacksmiths",
    "sg:classifiers":[
        {
            "category":"Shopping",
            "subcategory":"Antiques",
            "type":"Retail Goods"
        }
    ],
    "sg:phone":"+61 2 4971 4894",
    "sg:postcode":"2281",
    "sg:province":"NSW",
    "wof:name":"Blacksmiths Antiques",
    "wof:placetype":"venue"
},
  "geometry": {"coordinates":[151.64988708499999,-33.078994751],"type":"Point"}
}