{
  "type": "Feature",
  "properties": {
    "addr:full":"Cnr Arara & Coondoo Sts Kuranda QLD 4872",
    "addr:postcode":"4872",
    "addr:street":"Cnr",
    "iso:country":"AU",
    "sg:address":"Cnr Arara & Coondoo Sts",
    "sg:city":"Kuranda",
    "sg:classifiers":[
        {
            "category":"Travel",
            "subcategory":"Hotels & Motels",
            "type":"Entertainment"
        }
    ],
    "sg:phone":"+61 7 4093 7206",
    "sg:postcode":"4872",
    "sg:province":"QLD",
    "wof:name":"Kuranda Historic Hotel Motel",
    "wof:placetype":"venue"
},
  "geometry": {"coordinates":[145.64074707,-16.8228225708],"type":"Point"}
}