{
  "type": "Feature",
  "properties": {
    "addr:full":"132 Military Rd Guildford NSW 2161",
    "addr:housenumber":"132",
    "addr:postcode":"2161",
    "addr:street":"Military Rd",
    "iso:country":"AU",
    "sg:address":"132 Military Rd",
    "sg:city":"Guildford",
    "sg:classifiers":[
        {
            "category":"Professional",
            "subcategory":"Detective & Security Services",
            "type":"Services"
        }
    ],
    "sg:phone":"+61 2 9721 1167",
    "sg:postcode":"2161",
    "sg:province":"NSW",
    "sg:tags":[
        "consultant",
        "system"
    ],
    "wof:name":"Care-Tech",
    "wof:placetype":"venue"
},
  "geometry": {"coordinates":[150.983840942,-33.8545532227],"type":"Point"}
}