{
  "type": "Feature",
  "properties": {
    "addr:full":"51 Loftus St Riverstone NSW 2765",
    "addr:housenumber":"51",
    "addr:postcode":"2765",
    "addr:street":"Loftus St",
    "iso:country":"AU",
    "sg:address":"51 Loftus St",
    "sg:city":"Riverstone",
    "sg:classifiers":[
        {
            "category":"Wholesale",
            "subcategory":"Durable Goods & Equipment",
            "type":"Manufacturing & Wholesale Goods"
        }
    ],
    "sg:phone":"+61 2 9627 5185",
    "sg:postcode":"2765",
    "sg:province":"NSW",
    "sg:tags":[
        "logging",
        "sawmilling"
    ],
    "wof:name":"Brighton Saw Sales",
    "wof:placetype":"venue"
},
  "geometry": {"coordinates":[150.86012268100001,-33.6649208069],"type":"Point"}
}