{
  "type": "Feature",
  "properties": {
    "addr:full":"189 First Ave Bribie Island QLD 4507",
    "addr:housenumber":"189",
    "addr:postcode":"4507",
    "addr:street":"First Ave Bribie",
    "iso:country":"AU",
    "sg:address":"189 First Ave",
    "sg:city":"Bribie Island",
    "sg:classifiers":[
        {
            "category":"Autos & Motor Vehicles",
            "subcategory":"Automobile Sales",
            "type":"Retail Goods"
        }
    ],
    "sg:phone":"+61 7 3408 0800",
    "sg:postcode":"4507",
    "sg:province":"QLD",
    "sg:tags":[
        "car",
        "new"
    ],
    "wof:name":"Keystar Hyundai",
    "wof:placetype":"venue"
},
  "geometry": {"coordinates":[153.185089111,-27.0765781403],"type":"Point"}
}