{
  "type": "Feature",
  "properties": {
    "iso:country":"AU",
    "sg:address":"off Turpentine Rd 7 Ulandi Cl",
    "sg:city":"Tomerong",
    "sg:classifiers":[
        {
            "category":"Transit Center",
            "subcategory":"Freight",
            "type":"Transportation"
        }
    ],
    "sg:phone":"+61 2 4443 4109",
    "sg:postcode":"2540",
    "sg:province":"NSW",
    "sg:tags":[
        "turner",
        "wood"
    ],
    "wof:name":"Esa A Purhonen",
    "wof:placetype":"venue"
},
  "geometry": {"coordinates":[150.57029724099999,-35.0513687134],"type":"Point"}
}