{
  "type": "Feature",
  "properties": {
    "iso:country":"AU",
    "sg:address":"18 Matong La",
    "sg:city":"Avoca Beach",
    "sg:classifiers":[
        {
            "category":"Building & Trades",
            "subcategory":"Construction",
            "type":"Services"
        }
    ],
    "sg:phone":"+61 2 4382 2086",
    "sg:postcode":"2251",
    "sg:province":"NSW",
    "sg:tags":[
        "contractor"
    ],
    "wof:name":"Mitchell Bros",
    "wof:placetype":"venue"
},
  "geometry": {"coordinates":[151.42755126899999,-33.4639854431],"type":"Point"}
}