{
  "type": "Feature",
  "properties": {
    "iso:country":"AU",
    "sg:address":"18 Newcastle Drv",
    "sg:city":"Toormina",
    "sg:classifiers":[
        {
            "category":"Building & Trades",
            "subcategory":"Construction",
            "type":"Services"
        }
    ],
    "sg:phone":"+61 2 6653 3211",
    "sg:postcode":"2452",
    "sg:province":"NSW",
    "sg:tags":[
        "joinery"
    ],
    "wof:name":"Sawtell Kitchen Centre",
    "wof:placetype":"venue"
},
  "geometry": {"coordinates":[153.09161399999999,-30.362993],"type":"Point"}
}