{
  "type": "Feature",
  "properties": {
    "addr:full":"114 Main St Blacktown NSW 2148",
    "addr:housenumber":"114",
    "addr:postcode":"2148",
    "addr:street":"Main St",
    "iso:country":"AU",
    "sg:address":"114 Main St",
    "sg:city":"Blacktown",
    "sg:classifiers":[
        {
            "category":"Shopping",
            "subcategory":"Pawn Shop",
            "type":"Retail Goods"
        }
    ],
    "sg:phone":"+61 2 9622 6622",
    "sg:postcode":"2148",
    "sg:province":"NSW",
    "sg:tags":[
        "pawnbroker"
    ],
    "wof:name":"Cash Brokers",
    "wof:placetype":"venue"
},
  "geometry": {"coordinates":[150.91073608400001,-33.7714576721],"type":"Point"}
}