{
  "type": "Feature",
  "properties": {
    "addr:full":"171 Bridge St Oakey QLD 4401",
    "addr:housenumber":"171",
    "addr:postcode":"4401",
    "addr:street":"Bridge St",
    "iso:country":"AU",
    "sg:address":"171 Bridge St",
    "sg:city":"Oakey",
    "sg:classifiers":[
        {
            "category":"Retail",
            "subcategory":"Auto Repair",
            "type":"Services"
        }
    ],
    "sg:phone":"+61 7 4691 1466",
    "sg:postcode":"4401",
    "sg:province":"QLD",
    "sg:tags":[
        "repairer",
        "motor",
        "engineer"
    ],
    "wof:name":"Armstrong Automotive & Industrial Services",
    "wof:placetype":"venue"
},
  "geometry": {"coordinates":[151.71058654800001,-27.4270839691],"type":"Point"}
}