{
  "type": "Feature",
  "properties": {
    "addr:full":"166 Caroline Chisholm Drv Winston Hills NSW 2153",
    "addr:housenumber":"166",
    "addr:postcode":"2153",
    "addr:street":"Caroline Chisholm Drv",
    "iso:country":"AU",
    "sg:address":"166 Caroline Chisholm Drv",
    "sg:city":"Winston Hills",
    "sg:classifiers":[
        {
            "category":"Utilities",
            "subcategory":"Electric",
            "type":"Services"
        }
    ],
    "sg:phone":"+61 2 9838 9688",
    "sg:postcode":"2153",
    "sg:province":"NSW",
    "sg:tags":[
        "electrical",
        "contractor"
    ],
    "wof:name":"McPhee Electrical",
    "wof:placetype":"venue"
},
  "geometry": {"coordinates":[150.97190856899999,-33.7744216919],"type":"Point"}
}