{
  "type": "Feature",
  "properties": {
    "iso:country":"AU",
    "sg:address":"12 Holland Drv",
    "sg:city":"Melton",
    "sg:classifiers":[
        {
            "category":"Home & Garden",
            "subcategory":"Hardware",
            "type":"Retail Goods"
        }
    ],
    "sg:phone":"+61 3 9747 9188",
    "sg:postcode":"3337",
    "sg:province":"VIC",
    "sg:tags":[
        "repair",
        "tool",
        "power"
    ],
    "wof:name":"Jaytek Sales & Service",
    "wof:placetype":"venue"
},
  "geometry": {"coordinates":[144.598282,-37.686714],"type":"Point"}
}