{
  "type": "Feature",
  "properties": {
    "iso:country":"AU",
    "sg:address":"PO Box 155",
    "sg:city":"Alderley",
    "sg:classifiers":[
        {
            "category":"Building & Trades",
            "subcategory":"Construction",
            "type":"Services"
        }
    ],
    "sg:phone":"+61 438 554 377",
    "sg:postcode":"4051",
    "sg:province":"QLD",
    "sg:tags":[
        "home",
        "air conditioning"
    ],
    "wof:name":"Thermoelectric",
    "wof:placetype":"venue"
},
  "geometry": {"coordinates":[152.99920654300001,-27.4246997833],"type":"Point"}
}