{
  "type": "Feature",
  "properties": {
    "iso:country":"AU",
    "sg:address":"Unit 4, 269 Abbotsford Rd",
    "sg:city":"Bowen Hills",
    "sg:classifiers":[
        {
            "category":"Military Area",
            "subcategory":"Air Force Base",
            "type":"Public Place"
        }
    ],
    "sg:phone":"+61 7 3257 4402",
    "sg:postcode":"4006",
    "sg:province":"QLD",
    "sg:tags":[
        "fibre",
        "optic"
    ],
    "wof:name":"Anderson Corporation Pty Ltd",
    "wof:placetype":"venue"
},
  "geometry": {"coordinates":[153.04237365700001,-27.434879303],"type":"Point"}
}