{
  "type": "Feature",
  "properties": {
    "iso:country":"AU",
    "sg:address":"43 Helen St",
    "sg:city":"Mt Gambier",
    "sg:classifiers":[
        {
            "category":"Health Services",
            "subcategory":"Health Practitioner",
            "type":"Services"
        }
    ],
    "sg:phone":"+61 8 8725 2423",
    "sg:postcode":"5290",
    "sg:province":"SA",
    "sg:tags":[
        "physiotherapist"
    ],
    "wof:name":"Northcare Mt Gambier Physiotherapy",
    "wof:placetype":"venue"
},
  "geometry": {"coordinates":[140.77673300000001,-37.829624],"type":"Point"}
}