{
  "type": "Feature",
  "properties": {
    "addr:full":"2 Easey St Collingwood VIC 3066",
    "addr:housenumber":"2",
    "addr:postcode":"3066",
    "addr:street":"Easey St",
    "iso:country":"AU",
    "sg:address":"2 Easey St",
    "sg:city":"Collingwood",
    "sg:classifiers":[
        {
            "category":"Shopping",
            "subcategory":"Computers & Home Electronics",
            "type":"Retail Goods"
        }
    ],
    "sg:phone":"+61 3 9467 1966",
    "sg:postcode":"3066",
    "sg:province":"VIC",
    "sg:tags":[
        "equipment",
        "supply"
    ],
    "wof:name":"Source Technology",
    "wof:placetype":"venue"
},
  "geometry": {"coordinates":[144.98468017600001,-37.7974433899],"type":"Point"}
}