{
  "type": "Feature",
  "properties": {
    "addr:full":"772 Pittwater Rd Brookvale NSW 2100",
    "addr:housenumber":"772",
    "addr:postcode":"2100",
    "addr:street":"Pittwater Rd",
    "iso:country":"AU",
    "sg:address":"772 Pittwater Rd",
    "sg:city":"Brookvale",
    "sg:classifiers":[
        {
            "category":"Shopping",
            "subcategory":"Computers & Home Electronics",
            "type":"Retail Goods"
        }
    ],
    "sg:phone":"+61 2 9938 2388",
    "sg:postcode":"2100",
    "sg:province":"NSW",
    "sg:tags":[
        "equipment",
        "part",
        "electronic"
    ],
    "wof:name":"J & Z Australia Electrical Suppliers Pty Ltd",
    "wof:placetype":"venue"
},
  "geometry": {"coordinates":[151.27786254899999,-33.7607879639],"type":"Point"}
}