{
  "type": "Feature",
  "properties": {
    "addr:full":"13 Pandora St Greenacre NSW 2190",
    "addr:housenumber":"13",
    "addr:postcode":"2190",
    "addr:street":"Pandora St",
    "iso:country":"AU",
    "sg:address":"13 Pandora St",
    "sg:city":"Greenacre",
    "sg:classifiers":[
        {
            "category":"Utilities",
            "subcategory":"Refuse",
            "type":"Services"
        }
    ],
    "sg:phone":"+61 410 727 272",
    "sg:postcode":"2190",
    "sg:province":"NSW",
    "sg:tags":[
        "remover",
        "rubbish"
    ],
    "wof:name":"Precision Waste Management",
    "wof:placetype":"venue"
},
  "geometry": {"coordinates":[151.059448,-33.900673],"type":"Point"}
}