{
  "type": "Feature",
  "properties": {
    "addr:full":"294a Severin St Parramatta Park QLD 4870",
    "addr:housenumber":"294a",
    "addr:postcode":"4870",
    "addr:street":"Severin St",
    "iso:country":"AU",
    "sg:address":"294a Severin St",
    "sg:city":"Parramatta Park",
    "sg:classifiers":[
        {
            "category":"Professional",
            "subcategory":"Art Services",
            "type":"Services"
        }
    ],
    "sg:phone":"+61 7 4041 2590",
    "sg:postcode":"4870",
    "sg:province":"QLD",
    "sg:tags":[
        "picture",
        "frame",
        "framing"
    ],
    "wof:name":"Air 2 Art",
    "wof:placetype":"venue"
},
  "geometry": {"coordinates":[145.76603698700001,-16.926607132],"type":"Point"}
}