{
  "type": "Feature",
  "properties": {
    "addr:full":"21 Coode Rd West Melbourne VIC 3003",
    "addr:housenumber":"21",
    "addr:postcode":"3003",
    "addr:street":"Coode Rd",
    "iso:country":"AU",
    "sg:address":"21 Coode Rd",
    "sg:city":"West Melbourne",
    "sg:classifiers":[
        {
            "category":"Social Services",
            "subcategory":"Child Care",
            "type":"Services"
        }
    ],
    "sg:phone":"+61 3 9688 8444",
    "sg:postcode":"3003",
    "sg:province":"VIC",
    "sg:tags":[
        "fleet",
        "management"
    ],
    "wof:name":"TNT Fleet Management",
    "wof:placetype":"venue"
},
  "geometry": {"coordinates":[144.91067504899999,-37.8097038269],"type":"Point"}
}