{
  "type": "Feature",
  "properties": {
    "iso:country":"AU",
    "sg:address":"31- 35 Burgess Rd",
    "sg:city":"Bayswater",
    "sg:classifiers":[
        {
            "category":"Shopping",
            "subcategory":"Stationery & Office Supplies",
            "type":"Retail Goods"
        }
    ],
    "sg:phone":"+61 3 9720 1580",
    "sg:postcode":"3153",
    "sg:province":"VIC",
    "sg:tags":[
        "packaging",
        "material"
    ],
    "wof:name":"NCI Packaging",
    "wof:placetype":"venue"
},
  "geometry": {"coordinates":[145.2890625,-37.8215560913],"type":"Point"}
}