{
  "type": "Feature",
  "properties": {
    "addr:full":"Lot 134 (No 12) Sandstone Island Crcle Bittern VIC 3918",
    "addr:postcode":"3918",
    "iso:country":"AU",
    "sg:address":"Lot 134 (No 12) Sandstone Island Crcle",
    "sg:city":"Bittern",
    "sg:classifiers":[
        {
            "category":"Health Services",
            "subcategory":"Health Practitioner",
            "type":"Services"
        }
    ],
    "sg:phone":"+61 3 5979 3884",
    "sg:postcode":"3918",
    "sg:province":"VIC",
    "sg:tags":[
        "naturopath"
    ],
    "wof:name":"Jeffrey Rew",
    "wof:placetype":"venue"
},
  "geometry": {"coordinates":[145.17848205600001,-38.3355903625],"type":"Point"}
}