{
  "type": "Feature",
  "properties": {
    "iso:country":"AU",
    "sg:address":"Big Ear Studio 8 Phillimore St",
    "sg:city":"Fremantle",
    "sg:classifiers":[
        {
            "category":"Communications",
            "type":"Services"
        }
    ],
    "sg:phone":"+61 8 9335 9490",
    "sg:postcode":"6160",
    "sg:province":"WA",
    "sg:tags":[
        "public",
        "system",
        "address"
    ],
    "wof:name":"Broomstick Productions",
    "wof:placetype":"venue"
},
  "geometry": {"coordinates":[115.742523,-32.054653],"type":"Point"}
}