{
  "type": "Feature",
  "properties": {
    "addr:full":"212 Rundle St Adelaide SA 5000",
    "addr:housenumber":"212",
    "addr:postcode":"5000",
    "addr:street":"Rundle St",
    "iso:country":"AU",
    "sg:address":"212 Rundle St",
    "sg:city":"Adelaide",
    "sg:classifiers":[
        {
            "category":"Wholesale",
            "subcategory":"Photographic Equipment",
            "type":"Manufacturing & Wholesale Goods"
        }
    ],
    "sg:phone":"+61 8 8223 3449",
    "sg:postcode":"5000",
    "sg:province":"SA",
    "sg:tags":[
        "wholesaler",
        "mfrs",
        "supply"
    ],
    "wof:name":"Teds Industrial",
    "wof:placetype":"venue"
},
  "geometry": {"coordinates":[138.607254028,-34.9224662781],"type":"Point"}
}