{
  "type": "Feature",
  "properties": {
    "iso:country":"AU",
    "sg:address":"7 Baystone Crt",
    "sg:city":"Kelso",
    "sg:classifiers":[
        {
            "category":"Military Area",
            "subcategory":"Army Base",
            "type":"Public Place"
        }
    ],
    "sg:phone":"+61 7 4789 0421",
    "sg:postcode":"4815",
    "sg:province":"QLD",
    "sg:tags":[
        "concrete",
        "slab",
        "floor"
    ],
    "wof:name":"Roskel Concreting Services",
    "wof:placetype":"venue"
},
  "geometry": {"coordinates":[146.713898,-19.409975],"type":"Point"}
}