{
  "type": "Feature",
  "properties": {
    "addr:full":"52 Lucy St Ashfield NSW 2131",
    "addr:housenumber":"52",
    "addr:postcode":"2131",
    "addr:street":"Lucy St",
    "iso:country":"AU",
    "sg:address":"52 Lucy St",
    "sg:city":"Ashfield",
    "sg:classifiers":[
        {
            "category":"Utilities",
            "subcategory":"Water",
            "type":"Services"
        }
    ],
    "sg:phone":"+61 2 9798 9005",
    "sg:postcode":"2131",
    "sg:province":"NSW",
    "sg:tags":[
        "hot",
        "system"
    ],
    "wof:name":"Bob Honeybrook",
    "wof:placetype":"venue"
},
  "geometry": {"coordinates":[151.125396728,-33.8775863647],"type":"Point"}
}