{
  "type": "Feature",
  "properties": {
    "addr:full":"112b Jellicoe St North Toowoomba QLD 4350",
    "addr:housenumber":"112b",
    "addr:postcode":"4350",
    "addr:street":"Jellicoe St North",
    "iso:country":"AU",
    "sg:address":"112b Jellicoe St",
    "sg:city":"North Toowoomba",
    "sg:classifiers":[
        {
            "category":"Professional",
            "subcategory":"Accounting & Tax Preparation",
            "type":"Services"
        }
    ],
    "sg:phone":"+61 7 4613 1833",
    "sg:postcode":"4350",
    "sg:province":"QLD",
    "sg:tags":[
        "accountant",
        "auditor"
    ],
    "wof:name":"Lawson Accounting Services",
    "wof:placetype":"venue"
},
  "geometry": {"coordinates":[151.94760099999999,-27.56629],"type":"Point"}
}