{
  "type": "Feature",
  "properties": {
    "addr:full":"324 New Cleveland Rd Tingalpa QLD 4173",
    "addr:housenumber":"324",
    "addr:postcode":"4173",
    "addr:street":"New Cleveland Rd",
    "iso:country":"AU",
    "sg:address":"324 New Cleveland Rd",
    "sg:city":"Tingalpa",
    "sg:classifiers":[
        {
            "category":"Freight",
            "type":"Transportation"
        }
    ],
    "sg:phone":"+61 7 3890 1010",
    "sg:postcode":"4173",
    "sg:province":"QLD",
    "sg:tags":[
        "transport",
        "refrigerated"
    ],
    "wof:name":"Charter Refrigerated Transport",
    "wof:placetype":"venue"
},
  "geometry": {"coordinates":[153.13990783700001,-27.4811096191],"type":"Point"}
}