{
  "type": "Feature",
  "properties": {
    "iso:country":"AU",
    "sg:address":"35 - 45",
    "sg:city":"Lithgow, Abbotsford",
    "sg:classifiers":[
        {
            "category":"Wholesale",
            "subcategory":"Furniture",
            "type":"Manufacturing & Wholesale Goods"
        }
    ],
    "sg:phone":"+61 1800 812 440",
    "sg:postcode":"3067",
    "sg:province":"VIC",
    "sg:tags":[
        "wholesaler",
        "mfrs"
    ],
    "wof:name":"James Richardson - Office",
    "wof:placetype":"venue"
},
  "geometry": {"coordinates":[144.99848938,-37.8084220886],"type":"Point"}
}