{
  "type": "Feature",
  "properties": {
    "iso:country":"AU",
    "sg:address":"36-38 Darling St",
    "sg:city":"Wentworth",
    "sg:classifiers":[
        {
            "category":"Banks & Credit Unions",
            "subcategory":"Bank",
            "type":"Services"
        }
    ],
    "sg:phone":"+61 3 5027 3362",
    "sg:postcode":"2648",
    "sg:province":"NSW",
    "wof:name":"Wentworth & District Community Bank Branch Bendigo Bank",
    "wof:placetype":"venue"
},
  "geometry": {"coordinates":[141.916199,-34.096268],"type":"Point"}
}