{
  "type": "Feature",
  "properties": {
    "addr:full":"U13/ 30-32 Beaconsfield St Alexandria NSW 2015",
    "addr:housenumber":"/ 30-32",
    "addr:postcode":"2015",
    "addr:street":"Beaconsfield St",
    "iso:country":"AU",
    "sg:address":"U13/ 30-32 Beaconsfield St",
    "sg:city":"Alexandria",
    "sg:classifiers":[
        {
            "category":"Wholesale",
            "subcategory":"Apparel",
            "type":"Manufacturing & Wholesale Goods"
        }
    ],
    "sg:phone":"+61 2 9699 7200",
    "sg:postcode":"2015",
    "sg:province":"NSW",
    "sg:tags":[
        "wholesaler",
        "mfrs",
        "menswear"
    ],
    "wof:name":"Braintree Hemp Clothing",
    "wof:placetype":"venue"
},
  "geometry": {"coordinates":[151.19776916500001,-33.9135017395],"type":"Point"}
}