{
  "type": "Feature",
  "properties": {
    "addr:full":"138 Pine St Mildura VIC 3500",
    "addr:housenumber":"138",
    "addr:postcode":"3500",
    "addr:street":"Pine St",
    "iso:country":"AU",
    "sg:address":"138 Pine St",
    "sg:city":"Mildura",
    "sg:classifiers":[
        {
            "category":"Insurance",
            "subcategory":"Hazard Insurance",
            "type":"Services"
        }
    ],
    "sg:phone":"+61 1300 308 803",
    "sg:postcode":"3500",
    "sg:province":"VIC",
    "sg:tags":[
        "fire",
        "accident",
        "marine"
    ],
    "wof:name":"QBE Insurance (Australia) Limited",
    "wof:placetype":"venue"
},
  "geometry": {"coordinates":[142.15554809599999,-34.1859703064],"type":"Point"}
}