{
  "type": "Feature",
  "properties": {
    "addr:full":"Unit 2/ 25 Durham Rd Bayswater WA 6053",
    "addr:housenumber":"25",
    "addr:postcode":"6053",
    "addr:street":"Durham Rd",
    "iso:country":"AU",
    "sg:address":"Unit 2/ 25 Durham Rd",
    "sg:city":"Bayswater",
    "sg:classifiers":[
        {
            "category":"Utilities",
            "subcategory":"Electric",
            "type":"Services"
        }
    ],
    "sg:phone":"+61 8 9371 9000",
    "sg:postcode":"6053",
    "sg:province":"WA",
    "sg:tags":[
        "electrical",
        "contractor"
    ],
    "wof:name":"Wiring And Maintenance Co",
    "wof:placetype":"venue"
},
  "geometry": {"coordinates":[115.919929504,-31.9169769287],"type":"Point"}
}