{
  "type": "Feature",
  "properties": {
    "addr:full":"28 Hasler Rd Osborne Park WA 6017",
    "addr:housenumber":"28",
    "addr:postcode":"6017",
    "addr:street":"Hasler Rd",
    "iso:country":"AU",
    "sg:address":"28 Hasler Rd",
    "sg:city":"Osborne Park",
    "sg:classifiers":[
        {
            "category":"Social Services",
            "subcategory":"Job Training",
            "type":"Services"
        }
    ],
    "sg:phone":"+61 8 9244 0000",
    "sg:postcode":"6017",
    "sg:province":"WA",
    "sg:tags":[
        "hire",
        "computer",
        "leasing"
    ],
    "sg:website":"http://www.stotthoare.com.au",
    "wof:name":"Stott & Hoare Business Computers",
    "wof:placetype":"venue"
},
  "geometry": {"coordinates":[115.808143616,-31.910451889],"type":"Point"}
}