{
  "type": "Feature",
  "properties": {
    "iso:country":"AU",
    "sg:address":"Unit 2/ 572 Frankston-Dandenong Rd",
    "sg:city":"Carrum Downs",
    "sg:classifiers":[
        {
            "category":"Shopping",
            "type":"Retail Goods"
        }
    ],
    "sg:phone":"+61 3 9775 0993",
    "sg:postcode":"3201",
    "sg:province":"VIC",
    "sg:tags":[
        "equipment",
        "safety",
        "accessory"
    ],
    "wof:name":"Central Welding & Industrial Supplies",
    "wof:placetype":"venue"
},
  "geometry": {"coordinates":[145.171982,-38.099644],"type":"Point"}
}