{
  "type": "Feature",
  "properties": {
    "iso:country":"AU",
    "sg:address":"U3/ 6 Barnett Crt",
    "sg:city":"Morley",
    "sg:classifiers":[
        {
            "category":"Professional",
            "subcategory":"Engineering",
            "type":"Services"
        }
    ],
    "sg:phone":"+61 8 9370 4038",
    "sg:postcode":"6062",
    "sg:province":"WA",
    "sg:tags":[
        "electronic",
        "engineer"
    ],
    "wof:name":"TCG Industrial Pty Ltd",
    "wof:placetype":"venue"
},
  "geometry": {"coordinates":[115.902542114,-31.9019184113],"type":"Point"}
}