{
  "type": "Feature",
  "properties": {
    "addr:full":"7 King St Chillagoe QLD 4871",
    "addr:housenumber":"7",
    "addr:postcode":"4871",
    "addr:street":"King St",
    "iso:country":"AU",
    "sg:address":"7 King St",
    "sg:city":"Chillagoe",
    "sg:classifiers":[
        {
            "category":"Travel",
            "subcategory":"Hotels & Motels",
            "type":"Entertainment"
        }
    ],
    "sg:phone":"+61 7 4094 7106",
    "sg:postcode":"4871",
    "sg:province":"QLD",
    "wof:name":"Chillagoe Caves Lodge Motel & Camping",
    "wof:placetype":"venue"
},
  "geometry": {"coordinates":[144.52467346200001,-17.1571540833],"type":"Point"}
}