{
  "type": "Feature",
  "properties": {
    "iso:country":"AU",
    "sg:address":"Suite 69, Sandford Jackson Building 30 Chasely St",
    "sg:city":"Auchenflower",
    "sg:classifiers":[
        {
            "category":"Health Services",
            "subcategory":"Doctor",
            "type":"Services"
        }
    ],
    "sg:phone":"+61 7 3720 8788",
    "sg:postcode":"4066",
    "sg:province":"QLD",
    "sg:tags":[
        "medical",
        "practitioner"
    ],
    "wof:name":"Hills Russell J Dr",
    "wof:placetype":"venue"
},
  "geometry": {"coordinates":[152.998046875,-27.4772014618],"type":"Point"}
}