{
  "type": "Feature",
  "properties": {
    "addr:full":"8 Container St Tingalpa QLD 4173",
    "addr:postcode":"4173",
    "addr:street":"St",
    "iso:country":"AU",
    "sg:address":"8 Container St",
    "sg:city":"Tingalpa",
    "sg:classifiers":[
        {
            "category":"Wholesale",
            "subcategory":"Machinery & Supplies",
            "type":"Manufacturing & Wholesale Goods"
        }
    ],
    "sg:phone":"+61 7 3890 4688",
    "sg:postcode":"4173",
    "sg:province":"QLD",
    "sg:tags":[
        "bearing",
        "bushing"
    ],
    "wof:name":"CBC Bearings Power Transmission",
    "wof:placetype":"venue"
},
  "geometry": {"coordinates":[153.10971069300001,-27.4725646973],"type":"Point"}
}