{
  "type": "Feature",
  "properties": {
    "addr:full":"Level 1/ Suite 2 8 - 10 Palmer St Parramatta NSW 2150",
    "addr:housenumber":"/ suite;8 10",
    "addr:postcode":"2150",
    "addr:street":"Palmer St",
    "iso:country":"AU",
    "sg:address":"Level 1/ Suite 2 8 - 10 Palmer St",
    "sg:city":"Parramatta",
    "sg:classifiers":[
        {
            "category":"Organizations",
            "subcategory":"Professional Association",
            "type":"Services"
        }
    ],
    "sg:phone":"+61 2 9683 6655",
    "sg:postcode":"2150",
    "sg:province":"NSW",
    "sg:tags":[
        "organisation",
        "business"
    ],
    "wof:name":"Parramatta Chamber of Commerce",
    "wof:placetype":"venue"
},
  "geometry": {"coordinates":[150.96832275400001,-33.8454666138],"type":"Point"}
}