{
  "type": "Feature",
  "properties": {
    "addr:full":"66 Rholanda Crs Springwood QLD 4127",
    "addr:housenumber":"66",
    "addr:postcode":"4127",
    "addr:street":"Rholanda Crs",
    "iso:country":"AU",
    "sg:address":"66 Rholanda Crs",
    "sg:city":"Springwood",
    "sg:classifiers":[
        {
            "category":"Professional",
            "subcategory":"Art Services",
            "type":"Services"
        }
    ],
    "sg:phone":"+61 419 654 509",
    "sg:postcode":"4127",
    "sg:province":"QLD",
    "sg:tags":[
        "decorator",
        "painter"
    ],
    "wof:name":"Powerhouse Painting",
    "wof:placetype":"venue"
},
  "geometry": {"coordinates":[153.13209533700001,-27.6174602509],"type":"Point"}
}