{
  "type": "Feature",
  "properties": {
    "addr:full":"Colbee Crt Phillip ACT 2606",
    "addr:postcode":"2606",
    "addr:street":"Colbee Crt",
    "iso:country":"AU",
    "sg:address":"Colbee Crt",
    "sg:city":"Phillip",
    "sg:classifiers":[
        {
            "category":"Fast Food",
            "type":"Food & Drink"
        }
    ],
    "sg:phone":"+61 2 6281 1363",
    "sg:postcode":"2606",
    "sg:province":"ACT",
    "sg:tags":[
        "away",
        "take"
    ],
    "wof:name":"Colbee Court Snack Bar",
    "wof:placetype":"venue"
},
  "geometry": {"coordinates":[149.08880615199999,-35.3518486023],"type":"Point"}
}