{
  "type": "Feature",
  "properties": {
    "addr:full":"Cnr Herring & Kent Rds Marsfield NSW 2122",
    "addr:postcode":"2122",
    "addr:street":"Cnr",
    "iso:country":"AU",
    "sg:address":"Cnr Herring & Kent Rds",
    "sg:city":"Marsfield",
    "sg:classifiers":[
        {
            "category":"Education",
            "subcategory":"School",
            "type":"Public Place"
        }
    ],
    "sg:phone":"+61 2 9878 2884",
    "sg:postcode":"2122",
    "sg:province":"NSW",
    "sg:tags":[
        "state",
        "-",
        "nsw"
    ],
    "wof:name":"Kent Road Public School",
    "wof:placetype":"venue"
},
  "geometry": {"coordinates":[151.10952758799999,-33.7864112854],"type":"Point"}
}