{
  "type": "Feature",
  "properties": {
    "iso:country":"AU",
    "sg:address":"10 Nyngam St",
    "sg:city":"Acacia Ridge",
    "sg:classifiers":[
        {
            "category":"Arena",
            "subcategory":"Sports Club",
            "type":"Entertainment"
        }
    ],
    "sg:phone":"+61 7 3277 6642",
    "sg:postcode":"4110",
    "sg:province":"QLD",
    "sg:tags":[
        "organisation",
        "sporting"
    ],
    "wof:name":"Japan Karate Assoc Of Aust (Shotokan)",
    "wof:placetype":"venue"
},
  "geometry": {"coordinates":[153.01382446299999,-27.5786437988],"type":"Point"}
}