{
  "type": "Feature",
  "properties": {
    "addr:full":"536 Peel St Tamworth NSW 2340",
    "addr:housenumber":"536",
    "addr:postcode":"2340",
    "addr:street":"Peel St",
    "iso:country":"AU",
    "sg:address":"536 Peel St",
    "sg:city":"Tamworth",
    "sg:classifiers":[
        {
            "category":"Banks & Credit Unions",
            "subcategory":"Financial Services",
            "type":"Services"
        }
    ],
    "sg:phone":"+61 2 6766 3442",
    "sg:postcode":"2340",
    "sg:province":"NSW",
    "sg:tags":[
        "industrial",
        "finance"
    ],
    "wof:name":"Tremain Prowse Pty Ltd",
    "wof:placetype":"venue"
},
  "geometry": {"coordinates":[150.927200317,-31.0898170471],"type":"Point"}
}