{
  "type": "Feature",
  "properties": {
    "addr:full":"1st Flr, 321 Whitehorse Rd Nunawading VIC 3131",
    "addr:housenumber":"321",
    "addr:postcode":"3131",
    "addr:street":"Whitehorse Rd",
    "iso:country":"AU",
    "sg:address":"1st Flr, 321 Whitehorse Rd",
    "sg:city":"Nunawading",
    "sg:classifiers":[
        {
            "category":"Banks & Credit Unions",
            "subcategory":"Financial Services",
            "type":"Services"
        }
    ],
    "sg:phone":"+61 3 9878 9460",
    "sg:postcode":"3131",
    "sg:province":"VIC",
    "sg:tags":[
        "planning"
    ],
    "wof:name":"Hillross Financial Services Limited",
    "wof:placetype":"venue"
},
  "geometry": {"coordinates":[145.17326355,-37.8180160522],"type":"Point"}
}