{
  "type": "Feature",
  "properties": {
    "iso:country":"AU",
    "sg:address":"4 Sierra Pl",
    "sg:city":"Baulkham Hills",
    "sg:classifiers":[
        {
            "category":"Professional",
            "subcategory":"Art Services",
            "type":"Services"
        }
    ],
    "sg:phone":"+61 2 8883 2990",
    "sg:postcode":"2153",
    "sg:province":"NSW",
    "sg:tags":[
        "picture",
        "frame",
        "framing"
    ],
    "wof:name":"Impressionable Kids The Hills",
    "wof:placetype":"venue"
},
  "geometry": {"coordinates":[150.922561645,-33.7924194336],"type":"Point"}
}