{
  "type": "Feature",
  "properties": {
    "addr:full":"6 Clare St Bayswater VIC 3153",
    "addr:housenumber":"6",
    "addr:postcode":"3153",
    "addr:street":"Clare St",
    "iso:country":"AU",
    "sg:address":"6 Clare St",
    "sg:city":"Bayswater",
    "sg:classifiers":[
        {
            "category":"Wholesale",
            "subcategory":"Home Furnishings",
            "type":"Manufacturing & Wholesale Goods"
        }
    ],
    "sg:phone":"+61 3 9721 3000",
    "sg:postcode":"3153",
    "sg:province":"VIC",
    "wof:name":"Edwards S & E Pty Ltd",
    "wof:placetype":"venue"
},
  "geometry": {"coordinates":[145.28146362300001,-37.8426094055],"type":"Point"}
}