{
  "type": "Feature",
  "properties": {
    "addr:full":"2 Uppsala Pl Canning Vale WA 6155",
    "addr:housenumber":"2",
    "addr:postcode":"6155",
    "addr:street":"Pl",
    "iso:country":"AU",
    "sg:address":"2 Uppsala Pl",
    "sg:city":"Canning Vale",
    "sg:classifiers":[
        {
            "category":"Wholesale",
            "subcategory":"Hardware",
            "type":"Manufacturing & Wholesale Goods"
        }
    ],
    "sg:phone":"+61 8 9456 2444",
    "sg:postcode":"6155",
    "sg:province":"WA",
    "wof:name":"Sontax Australia Pty Ltd",
    "wof:placetype":"venue"
},
  "geometry": {"coordinates":[115.9226,-32.069103],"type":"Point"}
}