{
  "type": "Feature",
  "properties": {
    "addr:full":"53 Bray St Plympton Park SA 5038",
    "addr:housenumber":"53",
    "addr:postcode":"5038",
    "addr:street":"Bray St",
    "iso:country":"AU",
    "sg:address":"53 Bray St",
    "sg:city":"Plympton Park",
    "sg:classifiers":[
        {
            "category":"Personal",
            "subcategory":"Beauty Salon",
            "type":"Services"
        }
    ],
    "sg:phone":"+61 8 8293 4042",
    "sg:postcode":"5038",
    "sg:province":"SA",
    "sg:tags":[
        "hairdresser"
    ],
    "wof:name":"J & S Hair & Beauty",
    "wof:placetype":"venue"
},
  "geometry": {"coordinates":[138.548995972,-34.9806137085],"type":"Point"}
}