{
  "type": "Feature",
  "properties": {
    "addr:full":"3/ 22 Strathwyn St Brendale QLD 4500",
    "addr:housenumber":"/ 22",
    "addr:postcode":"4500",
    "addr:street":"Strathwyn St",
    "iso:country":"AU",
    "sg:address":"3/ 22 Strathwyn St",
    "sg:city":"Brendale",
    "sg:classifiers":[
        {
            "category":"Building & Trades",
            "subcategory":"Construction",
            "type":"Services"
        }
    ],
    "sg:phone":"+61 1300 799 672",
    "sg:postcode":"4500",
    "sg:province":"QLD",
    "sg:tags":[
        "equipment",
        "system",
        "automation"
    ],
    "wof:name":"Automation Sales",
    "wof:placetype":"venue"
},
  "geometry": {"coordinates":[152.97869873100001,-27.3205547333],"type":"Point"}
}