{
  "type": "Feature",
  "properties": {
    "addr:full":"39 Wangara Rd Cheltenham VIC 3192",
    "addr:housenumber":"39",
    "addr:postcode":"3192",
    "addr:street":"Wangara Rd",
    "iso:country":"AU",
    "sg:address":"39 Wangara Rd",
    "sg:city":"Cheltenham",
    "sg:classifiers":[
        {
            "category":"Building & Trades",
            "subcategory":"Construction",
            "type":"Services"
        }
    ],
    "sg:phone":"+61 3 9583 1175",
    "sg:postcode":"3192",
    "sg:province":"VIC",
    "sg:tags":[
        "monumental",
        "mason"
    ],
    "sg:website":"http://www.addisonmemorials.com.au",
    "wof:name":"A C Addison & Sons Pty Ltd",
    "wof:placetype":"venue"
},
  "geometry": {"coordinates":[145.03642273,-37.9582977295],"type":"Point"}
}