{
  "type": "Feature",
  "properties": {
    "iso:country":"AU",
    "sg:address":"2 Emily Crt",
    "sg:city":"Croydon",
    "sg:classifiers":[
        {
            "category":"Building & Trades",
            "subcategory":"Cleaning & Sanitation",
            "type":"Services"
        }
    ],
    "sg:phone":"+61 3 9725 6515",
    "sg:postcode":"3136",
    "sg:province":"VIC",
    "sg:tags":[
        "industrial",
        "commercial",
        "contractor"
    ],
    "wof:name":"Cracar Pty Ltd",
    "wof:placetype":"venue"
},
  "geometry": {"coordinates":[145.28245544399999,-37.7877235413],"type":"Point"}
}