{
  "type": "Feature",
  "properties": {
    "addr:full":"308- 310 Canterbury Rd Canterbury NSW 2193",
    "addr:housenumber":"310",
    "addr:postcode":"2193",
    "addr:street":"Canterbury Rd",
    "iso:country":"AU",
    "sg:address":"308- 310 Canterbury Rd",
    "sg:city":"Canterbury",
    "sg:classifiers":[
        {
            "category":"Home & Garden",
            "subcategory":"Furniture",
            "type":"Retail Goods"
        }
    ],
    "sg:phone":"+61 2 9787 1311",
    "sg:postcode":"2193",
    "sg:province":"NSW",
    "sg:tags":[
        "business"
    ],
    "sg:website":"http://www.bowermans.com.au",
    "wof:name":"Bowermans Office Furniture Pty Ltd",
    "wof:placetype":"venue"
},
  "geometry": {"coordinates":[151.12815900000001,-33.904961],"type":"Point"}
}