{
  "type": "Feature",
  "properties": {
    "addr:full":"5 Michael Drv Wodonga NSW 3690",
    "addr:housenumber":"5",
    "addr:postcode":"3690",
    "addr:street":"Michael Drv",
    "iso:country":"AU",
    "sg:address":"5 Michael Drv",
    "sg:city":"Wodonga",
    "sg:classifiers":[
        {
            "category":"Home & Garden",
            "subcategory":"Hardware",
            "type":"Retail Goods"
        }
    ],
    "sg:phone":"+61 412 331 332",
    "sg:postcode":"3690",
    "sg:province":"NSW",
    "sg:tags":[
        "pumping",
        "contractor"
    ],
    "wof:name":"Chris Ross Concrete Pumping & Spraying Pty Ltd",
    "wof:placetype":"venue"
},
  "geometry": {"coordinates":[146.90060424800001,-36.1229820251],"type":"Point"}
}