{
  "type": "Feature",
  "properties": {
    "addr:full":"20 Lyndal Ave Port Macquarie NSW 2444",
    "addr:housenumber":"20",
    "addr:postcode":"2444",
    "addr:street":"Lyndal Ave",
    "iso:country":"AU",
    "sg:address":"20 Lyndal Ave",
    "sg:city":"Port Macquarie",
    "sg:classifiers":[
        {
            "category":"Arena",
            "subcategory":"Sports Club",
            "type":"Entertainment"
        }
    ],
    "sg:phone":"+61 418 640 298",
    "sg:postcode":"2444",
    "sg:province":"NSW",
    "sg:tags":[
        "defence",
        "supply",
        "self",
        "instruction",
        "martial art"
    ],
    "wof:name":"Kumiai-Ryu Martial Arts System",
    "wof:placetype":"venue"
},
  "geometry": {"coordinates":[152.91575599999999,-31.45083],"type":"Point"}
}