{
  "type": "Feature",
  "properties": {
    "addr:full":"Ground Flr Canosa Hospital 169 Seventeen Mile Rock Oxley QLD 4075",
    "addr:housenumber":"169",
    "addr:postcode":"4075",
    "addr:street":"Seventeen Mile",
    "iso:country":"AU",
    "sg:address":"Ground Flr Canosa Hospital 169 Seventeen Mile Rock",
    "sg:city":"Oxley",
    "sg:classifiers":[
        {
            "category":"Health Services",
            "subcategory":"Doctor",
            "type":"Services"
        }
    ],
    "sg:phone":"+61 7 3375 6155",
    "sg:postcode":"4075",
    "sg:province":"QLD",
    "sg:tags":[
        "occupational",
        "safety"
    ],
    "wof:name":"Health For Industry",
    "wof:placetype":"venue"
},
  "geometry": {"coordinates":[152.964309692,-27.5547008514],"type":"Point"}
}