{
  "type": "Feature",
  "properties": {
    "addr:full":"2 Lauricella Ave Keilor East VIC 3033",
    "addr:housenumber":"2",
    "addr:postcode":"3033",
    "addr:street":"Lauricella Ave",
    "iso:country":"AU",
    "sg:address":"2 Lauricella Ave",
    "sg:city":"Keilor East",
    "sg:classifiers":[
        {
            "category":"Building & Trades",
            "subcategory":"Construction",
            "type":"Services"
        }
    ],
    "sg:phone":"+61 413 212 104",
    "sg:postcode":"3033",
    "sg:province":"VIC",
    "sg:tags":[
        "contractor"
    ],
    "wof:name":"Prima Construction Pty Ltd",
    "wof:placetype":"venue"
},
  "geometry": {"coordinates":[144.86257900000001,-37.745556],"type":"Point"}
}