{
  "type": "Feature",
  "properties": {
    "iso:country":"AU",
    "sg:address":"30 Darlinghurst Rd",
    "sg:city":"Kings Cross",
    "sg:classifiers":[
        {
            "category":"Travel",
            "subcategory":"Hotels & Motels",
            "type":"Entertainment"
        }
    ],
    "sg:phone":"+61 2 9358 5599",
    "sg:postcode":"2011",
    "sg:province":"NSW",
    "sg:tags":[
        "accommodation"
    ],
    "wof:name":"Castle Accommodation Group The",
    "wof:placetype":"venue"
},
  "geometry": {"coordinates":[151.224121094,-33.8732795715],"type":"Point"}
}