{
  "type": "Feature",
  "properties": {
    "addr:full":"5 Margaret St Palmwoods QLD 4555",
    "addr:housenumber":"5",
    "addr:postcode":"4555",
    "addr:street":"Margaret St",
    "iso:country":"AU",
    "sg:address":"5 Margaret St",
    "sg:city":"Palmwoods",
    "sg:classifiers":[
        {
            "category":"Real Estate",
            "subcategory":"Real Estate Agent",
            "type":"Services"
        }
    ],
    "sg:phone":"+61 7 5478 9122",
    "sg:postcode":"4555",
    "sg:province":"QLD",
    "wof:name":"Elders Real Estate",
    "wof:placetype":"venue"
},
  "geometry": {"coordinates":[152.958786011,-26.686504364],"type":"Point"}
}