{
  "type": "Feature",
  "properties": {
    "iso:country":"AU",
    "sg:address":"71 O'Reilly Rd",
    "sg:city":"Tatura",
    "sg:classifiers":[
        {
            "category":"Manufacturing",
            "subcategory":"Tools & Machinery",
            "type":"Manufacturing & Wholesale Goods"
        }
    ],
    "sg:phone":"+61 3 5824 2270",
    "sg:postcode":"3616",
    "sg:province":"VIC",
    "sg:tags":[
        "toolmaker"
    ],
    "wof:name":"Brumby Coupling Spanners",
    "wof:placetype":"venue"
},
  "geometry": {"coordinates":[145.23982238799999,-36.4396286011],"type":"Point"}
}