{
  "type": "Feature",
  "properties": {
    "addr:full":"4/ 8 Pennant St Cardiff NSW 2285",
    "addr:housenumber":"/ 8",
    "addr:postcode":"2285",
    "addr:street":"Pennant St",
    "iso:country":"AU",
    "sg:address":"4/ 8 Pennant St",
    "sg:city":"Cardiff",
    "sg:classifiers":[
        {
            "category":"Wholesale",
            "subcategory":"Chemicals & Plastics",
            "type":"Manufacturing & Wholesale Goods"
        }
    ],
    "sg:phone":"+61 2 4954 6907",
    "sg:postcode":"2285",
    "sg:province":"NSW",
    "sg:tags":[
        "repair"
    ],
    "wof:name":"Farmer Bros Bumper & Automotive Supplies",
    "wof:placetype":"venue"
},
  "geometry": {"coordinates":[151.64431762699999,-32.9400901794],"type":"Point"}
}