{
  "type": "Feature",
  "properties": {
    "addr:full":"34 Caroline St Riverview QLD 4303",
    "addr:housenumber":"34",
    "addr:postcode":"4303",
    "addr:street":"Caroline St",
    "iso:country":"AU",
    "sg:address":"34 Caroline St",
    "sg:city":"Riverview",
    "sg:classifiers":[
        {
            "category":"Professional",
            "subcategory":"Computer Services",
            "type":"Services"
        }
    ],
    "sg:phone":"+61 7 3816 3285",
    "sg:postcode":"4303",
    "sg:province":"QLD",
    "sg:tags":[
        "information"
    ],
    "wof:name":"Tafe's Turf Guide",
    "wof:placetype":"venue"
},
  "geometry": {"coordinates":[152.853347778,-27.6027984619],"type":"Point"}
}