{
  "type": "Feature",
  "properties": {
    "iso:country":"AU",
    "sg:address":"6/ 36 Uriarra Rd",
    "sg:city":"Queanbeyan",
    "sg:classifiers":[
        {
            "category":"Food & Beverages",
            "subcategory":"Specialty",
            "type":"Retail Goods"
        }
    ],
    "sg:phone":"+61 2 6297 4886",
    "sg:postcode":"2620",
    "sg:province":"ACT",
    "sg:tags":[
        "product",
        "health"
    ],
    "wof:name":"Herbalife Australasia Pty Ltd",
    "wof:placetype":"venue"
},
  "geometry": {"coordinates":[149.214385986,-35.3440628052],"type":"Point"}
}