{
  "type": "Feature",
  "properties": {
    "iso:country":"AU",
    "sg:address":"36 Francis St",
    "sg:city":"Northmead",
    "sg:classifiers":[
        {
            "category":"Autos & Motor Vehicles",
            "subcategory":"Fuel & Gas Station",
            "type":"Retail Goods"
        }
    ],
    "sg:phone":"+61 412 603 666",
    "sg:postcode":"2152",
    "sg:province":"NSW",
    "sg:tags":[
        "injection",
        "diesel"
    ],
    "wof:name":"Keeping It Clean Diesel Emissions",
    "wof:placetype":"venue"
},
  "geometry": {"coordinates":[151.00340270999999,-33.7382926941],"type":"Point"}
}