{
  "type": "Feature",
  "properties": {
    "addr:full":"24/ 10 J Hilltop Rd Merrylands NSW 2160",
    "addr:housenumber":"24 / 10 j",
    "addr:postcode":"2160",
    "addr:street":"Hilltop Rd",
    "iso:country":"AU",
    "sg:address":"24/ 10 J Hilltop Rd",
    "sg:city":"Merrylands",
    "sg:classifiers":[
        {
            "category":"Professional",
            "subcategory":"Computer Services",
            "type":"Services"
        }
    ],
    "sg:phone":"+61 2 9613 0775",
    "sg:postcode":"2160",
    "sg:province":"NSW",
    "sg:tags":[
        "equipment",
        "networking",
        "installation"
    ],
    "wof:name":"National Computer Contracting Services",
    "wof:placetype":"venue"
},
  "geometry": {"coordinates":[150.98382568400001,-33.8267173767],"type":"Point"}
}