{
  "type": "Feature",
  "properties": {
    "iso:country":"AU",
    "sg:address":"17 Denman Ave",
    "sg:city":"St Kilda East",
    "sg:classifiers":[
        {
            "category":"Professional",
            "subcategory":"Computer Services",
            "type":"Services"
        }
    ],
    "sg:phone":"+61 3 9527 8967",
    "sg:postcode":"3183",
    "sg:province":"VIC",
    "sg:tags":[
        "consultant",
        "system"
    ],
    "wof:name":"Emptar Engineering",
    "wof:placetype":"venue"
},
  "geometry": {"coordinates":[145.00050354000001,-37.8712234497],"type":"Point"}
}