{
  "type": "Feature",
  "properties": {
    "addr:full":"Cnr Hamilton & Park Sts Eglinton NSW 2795",
    "addr:postcode":"2795",
    "addr:street":"Cnr",
    "iso:country":"AU",
    "sg:address":"Cnr Hamilton & Park Sts",
    "sg:city":"Eglinton",
    "sg:classifiers":[
        {
            "category":"Personal",
            "subcategory":"Beauty Salon",
            "type":"Services"
        }
    ],
    "sg:phone":"+61 2 6337 1795",
    "sg:postcode":"2795",
    "sg:province":"NSW",
    "sg:tags":[
        "hairdresser"
    ],
    "wof:name":"Eglinton Cutting Cottage",
    "wof:placetype":"venue"
},
  "geometry": {"coordinates":[149.54649352999999,-33.3783187866],"type":"Point"}
}