{
  "type": "Feature",
  "properties": {
    "iso:country":"AU",
    "sg:address":"47 Cook St",
    "sg:city":"Flinders",
    "sg:classifiers":[
        {
            "category":"Real Estate",
            "subcategory":"Real Estate Agent",
            "type":"Services"
        }
    ],
    "sg:phone":"+61 3 5989 1000",
    "sg:postcode":"3929",
    "sg:province":"VIC",
    "sg:website":"http://www.kayburton.com.au",
    "wof:name":"Kay & Burton Flinders",
    "wof:placetype":"venue"
},
  "geometry": {"coordinates":[145.01695251500001,-38.4739227295],"type":"Point"}
}