{
  "type": "Feature",
  "properties": {
    "addr:full":"1 Ridge St Merrylands NSW 2160",
    "addr:housenumber":"1",
    "addr:postcode":"2160",
    "addr:street":"Ridge St",
    "iso:country":"AU",
    "sg:address":"1 Ridge St",
    "sg:city":"Merrylands",
    "sg:classifiers":[
        {
            "category":"Building & Trades",
            "subcategory":"Construction",
            "type":"Services"
        }
    ],
    "sg:phone":"+61 2 9637 2498",
    "sg:postcode":"2160",
    "sg:province":"NSW",
    "sg:tags":[
        "contractor"
    ],
    "wof:name":"Coz-Ped Pty Ltd",
    "wof:placetype":"venue"
},
  "geometry": {"coordinates":[150.971099853,-33.8325767517],"type":"Point"}
}