{
  "type": "Feature",
  "properties": {
    "iso:country":"AU",
    "sg:address":"83 Crocker Drv",
    "sg:city":"Malaga",
    "sg:classifiers":[
        {
            "category":"Home & Garden",
            "subcategory":"Home Furnishings",
            "type":"Retail Goods"
        }
    ],
    "sg:phone":"+61 8 9249 2429",
    "sg:postcode":"6090",
    "sg:province":"WA",
    "sg:tags":[
        "shower",
        "screen"
    ],
    "wof:name":"Action Glass Pty Ltd",
    "wof:placetype":"venue"
},
  "geometry": {"coordinates":[115.882011414,-31.8546352386],"type":"Point"}
}