{
  "type": "Feature",
  "properties": {
    "addr:full":"Cnr Bay Rd & Meylin St Port MacDonnell SA 5291",
    "addr:postcode":"5291",
    "addr:street":"Cnr Bay Rd & Meylin St",
    "iso:country":"AU",
    "sg:address":"Cnr Bay Rd & Meylin St",
    "sg:city":"Port MacDonnell",
    "sg:classifiers":[
        {
            "category":"Fast Food",
            "type":"Food & Drink"
        }
    ],
    "sg:phone":"+61 8 8738 2409",
    "sg:postcode":"5291",
    "sg:province":"SA",
    "sg:tags":[
        "away",
        "take"
    ],
    "wof:name":"Starks Bakery & Cafe Licensed Bistro",
    "wof:placetype":"venue"
},
  "geometry": {"coordinates":[140.70457500000001,-38.051373],"type":"Point"}
}