{
  "type": "Feature",
  "properties": {
    "addr:full":"15 Karuah St Thornton NSW 2322",
    "addr:housenumber":"15",
    "addr:postcode":"2322",
    "addr:street":"Karuah St",
    "iso:country":"AU",
    "sg:address":"15 Karuah St",
    "sg:city":"Thornton",
    "sg:classifiers":[
        {
            "category":"Home & Garden",
            "subcategory":"Building Materials",
            "type":"Retail Goods"
        }
    ],
    "sg:phone":"+61 2 4966 2445",
    "sg:postcode":"2322",
    "sg:province":"NSW",
    "sg:tags":[
        "lawn",
        "cutting",
        "maintenance"
    ],
    "wof:name":"Haynes Lawncare",
    "wof:placetype":"venue"
},
  "geometry": {"coordinates":[151.64036560100001,-32.7831726074],"type":"Point"}
}